{
  "type": "Feature",
  "properties": {
    "iso:country":"GB",
    "sg:address":"12 Dock Rd",
    "sg:city":"Gosport",
    "sg:classifiers":[
        {
            "category":"Home & Garden",
            "subcategory":"Building Materials",
            "type":"Retail Goods"
        }
    ],
    "sg:phone":"+44 23 9279 6633",
    "sg:postcode":"PO12 1SJ",
    "sg:province":"Hampshire",
    "sg:tags":[
        "furnishers",
        "bathroom",
        "planner"
    ],
    "wof:name":"Keeling Heating Products Ltd",
    "wof:placetype":"venue"
},
  "geometry": {"coordinates":[-1.132339,50.792919],"type":"Point"}
}