{
  "type": "Feature",
  "properties": {
    "addr:full":"8 Cooper Hill Drive, Walton-le-dale Preston Lancashire PR5 4HE",
    "addr:housenumber":"8",
    "addr:postcode":"pr5 4he",
    "addr:street":"Cooper Hill Drive",
    "iso:country":"GB",
    "sg:address":"8 Cooper Hill Drive, Walton-le-dale",
    "sg:city":"Preston",
    "sg:classifiers":[
        {
            "category":"Utilities",
            "subcategory":"Refuse",
            "type":"Services"
        }
    ],
    "sg:phone":"+44 1772 827603",
    "sg:postcode":"PR5 4HE",
    "sg:province":"Lancashire",
    "sg:tags":[
        "skip",
        "hire"
    ],
    "wof:name":"Preston Skip Hire Ltd",
    "wof:placetype":"venue"
},
  "geometry": {"coordinates":[-2.669291,53.747402],"type":"Point"}
}