{
  "type": "Feature",
  "properties": {
    "iso:country":"GB",
    "sg:address":"128 Thornton Rd",
    "sg:city":"Bradford",
    "sg:classifiers":[
        {
            "category":"Professional",
            "subcategory":"Business Services",
            "type":"Services"
        }
    ],
    "sg:postcode":"BD1 2DX",
    "sg:province":"West Yorkshire",
    "sg:tags":[
        "import",
        "export",
        "agent"
    ],
    "wof:name":"Cellphone Warehouse",
    "wof:placetype":"venue"
},
  "geometry": {"coordinates":[-1.76099,53.793747],"type":"Point"}
}