{
  "type": "Feature",
  "properties": {
    "iso:country":"GB",
    "sg:address":"James Street",
    "sg:city":"Dunfermline",
    "sg:classifiers":[
        {
            "category":"Taxi",
            "type":"Transportation"
        }
    ],
    "sg:phone":"+44 1383 732257",
    "sg:postcode":"KY12 7QE",
    "sg:province":"Fife",
    "sg:tags":[
        "mini",
        "cab"
    ],
    "wof:name":"DUNFERMLINE TAXI RANK",
    "wof:placetype":"venue"
},
  "geometry": {"coordinates":[-3.45818,56.072159],"type":"Point"}
}