{
  "type": "Feature",
  "properties": {
    "addr:full":"11 St Johns Walk Harrogate North Yorkshire HG1 3AJ",
    "addr:housenumber":"11",
    "addr:postcode":"hg1 3aj",
    "addr:street":"St Johns Walk",
    "iso:country":"GB",
    "sg:address":"11 St Johns Walk",
    "sg:city":"Harrogate",
    "sg:classifiers":[
        {
            "category":"Building & Trades",
            "subcategory":"Construction",
            "type":"Services"
        }
    ],
    "sg:phone":"+44 1423 524525",
    "sg:postcode":"HG1 3AJ",
    "sg:province":"North Yorkshire",
    "sg:tags":[
        "repair",
        "window",
        "replacement"
    ],
    "wof:name":"Crescent Windows",
    "wof:placetype":"venue"
},
  "geometry": {"coordinates":[-1.541865,54.009109],"type":"Point"}
}