{
  "type": "Feature",
  "properties": {
    "iso:country":"GB",
    "sg:address":"Old Court House, Roman Square",
    "sg:city":"Sittingbourne",
    "sg:classifiers":[
        {
            "category":"Restaurant",
            "type":"Food & Drink"
        }
    ],
    "sg:phone":"+44 1795 436000",
    "sg:postcode":"ME10 4BJ",
    "sg:province":"Kent",
    "sg:tags":[
        "-",
        "chinese"
    ],
    "wof:name":"Xian Chinese Restaurant",
    "wof:placetype":"venue"
},
  "geometry": {"coordinates":[0.736607,51.338566],"type":"Point"}
}