{
  "type": "Feature",
  "properties": {
    "addr:full":"1a Lodge St Stockton On Tees Durham TS18 1EN",
    "addr:housenumber":"1a",
    "addr:postcode":"ts18 1en",
    "addr:street":"Lodge St",
    "iso:country":"GB",
    "sg:address":"1a Lodge St",
    "sg:city":"Stockton On Tees",
    "sg:classifiers":[
        {
            "category":"Health Services",
            "subcategory":"Clinic",
            "type":"Services"
        }
    ],
    "sg:phone":"+44 1642 351433",
    "sg:postcode":"TS18 1EN",
    "sg:province":"Durham",
    "sg:tags":[
        "aromatherapy"
    ],
    "wof:name":"Judy's",
    "wof:placetype":"venue"
},
  "geometry": {"coordinates":[-1.31614,54.562222],"type":"Point"}
}