{
  "type": "Feature",
  "properties": {
    "addr:full":"31 King Street Kilmarnock East Ayrshire KA1 1PT",
    "addr:housenumber":"31",
    "addr:postcode":"ka1 1pt",
    "addr:street":"King Street",
    "iso:country":"GB",
    "sg:address":"31 King Street",
    "sg:city":"Kilmarnock",
    "sg:classifiers":[
        {
            "category":"Banks & Credit Unions",
            "subcategory":"Bank",
            "type":"Services"
        },
        {
            "category":"Banks & Credit Unions",
            "subcategory":"Financial Services",
            "type":"Services"
        }
    ],
    "sg:phone":"+44 1563 541317",
    "sg:postcode":"KA1 1PT",
    "sg:province":"East Ayrshire",
    "sg:tags":[
        "consultant",
        "institution"
    ],
    "wof:name":"London Scottish Bank Plc",
    "wof:placetype":"venue"
},
  "geometry": {"coordinates":[-4.497027,55.609329],"type":"Point"}
}