{
  "type": "Feature",
  "properties": {
    "addr:full":"11 Chapel Street Denbigh Conwy LL16 3SP",
    "addr:housenumber":"11",
    "addr:postcode":"ll16 3sp",
    "addr:street":"Chapel Street",
    "iso:country":"GB",
    "sg:address":"11 Chapel Street",
    "sg:city":"Denbigh",
    "sg:classifiers":[
        {
            "category":"Professional",
            "subcategory":"Accounting & Tax Preparation",
            "type":"Services"
        }
    ],
    "sg:phone":"+44 1745 812345",
    "sg:postcode":"LL16 3SP",
    "sg:province":"Conwy",
    "sg:tags":[
        "accountant"
    ],
    "wof:name":"Hooson & Co",
    "wof:placetype":"venue"
},
  "geometry": {"coordinates":[-3.4186570644,53.184387207],"type":"Point"}
}