{
  "type": "Feature",
  "properties": {
    "iso:country":"GB",
    "sg:address":"256 Chester Rd",
    "sg:city":"Birmingham",
    "sg:classifiers":[
        {
            "category":"Manufacturing",
            "subcategory":"Tools & Machinery",
            "type":"Manufacturing & Wholesale Goods"
        }
    ],
    "sg:phone":"+44 121 748 2211",
    "sg:postcode":"B36 0JE",
    "sg:province":"West Midlands",
    "sg:tags":[
        "society",
        "friendly"
    ],
    "wof:name":"Hill House Hammond Ltd",
    "wof:placetype":"venue"
},
  "geometry": {"coordinates":[-1.764552,52.501209],"type":"Point"}
}