{
  "type": "Feature",
  "properties": {
    "addr:full":"486 Nottingham Road, Chaddesden Derby Derbyshire DE21 6PF",
    "addr:housenumber":"486",
    "addr:postcode":"de21 6pf",
    "addr:street":"Nottingham Road",
    "iso:country":"GB",
    "sg:address":"486 Nottingham Road, Chaddesden",
    "sg:city":"Derby",
    "sg:classifiers":[
        {
            "category":"Fast Food",
            "type":"Food & Drink"
        }
    ],
    "sg:phone":"+44 1332 280282",
    "sg:postcode":"DE21 6PF",
    "sg:province":"Derbyshire",
    "sg:tags":[
        "delivery"
    ],
    "wof:name":"Gino's Dial-A-Pizza",
    "wof:placetype":"venue"
},
  "geometry": {"coordinates":[-1.438368,52.923862],"type":"Point"}
}