{
  "type": "Feature",
  "properties": {
    "addr:full":"185 Marsh Road Luton Bedfordshire LU3 2QG",
    "addr:housenumber":"185",
    "addr:postcode":"lu3 2qg",
    "addr:street":"Marsh Road",
    "iso:country":"GB",
    "sg:address":"185 Marsh Road",
    "sg:city":"Luton",
    "sg:classifiers":[
        {
            "category":"Real Estate",
            "subcategory":"Real Estate Agent",
            "type":"Services"
        }
    ],
    "sg:phone":"+44 1582 595127",
    "sg:postcode":"LU3 2QG",
    "sg:province":"Bedfordshire",
    "wof:name":"Connell Estate Agents",
    "wof:placetype":"venue"
},
  "geometry": {"coordinates":[-0.453517,51.90451],"type":"Point"}
}