{
  "type": "Feature",
  "properties": {
    "addr:full":"32 Rectory Avenue Rochford Essex SS4 3AQ",
    "addr:housenumber":"32",
    "addr:postcode":"ss4 3aq",
    "addr:street":"Rectory Avenue",
    "iso:country":"GB",
    "sg:address":"32 Rectory Avenue",
    "sg:city":"Rochford",
    "sg:classifiers":[
        {
            "category":"Manufacturing",
            "subcategory":"Furniture",
            "type":"Manufacturing & Wholesale Goods"
        }
    ],
    "sg:phone":"+44 1702 541214",
    "sg:postcode":"SS4 3AQ",
    "sg:province":"Essex",
    "sg:tags":[
        "polishing",
        "french"
    ],
    "wof:name":"Clark's French Polishing",
    "wof:placetype":"venue"
},
  "geometry": {"coordinates":[0.688288,51.597717],"type":"Point"}
}