{
  "type": "Feature",
  "properties": {
    "addr:full":"Beckford Business Centre, Beckford Street Hamilton South Lanarkshire ML3 0BT",
    "addr:postcode":"ml3 0bt",
    "addr:street":"Beckford Street",
    "iso:country":"GB",
    "sg:address":"Beckford Business Centre, Beckford Street",
    "sg:city":"Hamilton",
    "sg:classifiers":[
        {
            "category":"Utilities",
            "type":"Services"
        }
    ],
    "sg:postcode":"ML3 0BT",
    "sg:province":"South Lanarkshire",
    "sg:tags":[
        "internet"
    ],
    "wof:name":"H M G Internet Services Ltd.",
    "wof:placetype":"venue"
},
  "geometry": {"coordinates":[-4.0528907776,55.7773208618],"type":"Point"}
}