{
  "type": "Feature",
  "properties": {
    "addr:full":"Winscombe Mount, Clifton Estate Nottingham Nottinghamshire NG11 9FP",
    "addr:postcode":"ng11 9fp",
    "addr:street":"Winscombe Mount Clifton Estate",
    "iso:country":"GB",
    "sg:address":"Winscombe Mount, Clifton Estate",
    "sg:city":"Nottingham",
    "sg:classifiers":[
        {
            "category":"Education",
            "subcategory":"School",
            "type":"Public Place"
        }
    ],
    "sg:postcode":"NG11 9FP",
    "sg:province":"Nottinghamshire",
    "sg:tags":[
        "local",
        "authority"
    ],
    "wof:name":"Nottingham City Council",
    "wof:placetype":"venue"
},
  "geometry": {"coordinates":[-1.1851389408,52.8950233459],"type":"Point"}
}