{
  "type": "Feature",
  "properties": {
    "iso:country":"GB",
    "sg:address":"1 Longs Cottage, Main Street, East Challow",
    "sg:city":"Wantage",
    "sg:classifiers":[
        {
            "category":"Building & Trades",
            "subcategory":"Equipment Rental",
            "type":"Services"
        },
        {
            "category":"Building & Trades",
            "subcategory":"Construction",
            "type":"Services"
        }
    ],
    "sg:phone":"+44 1235 766585",
    "sg:postcode":"OX12 9SS",
    "sg:province":"Berkshire",
    "sg:tags":[
        "plant",
        "machinery"
    ],
    "wof:name":"C H Field",
    "wof:placetype":"venue"
},
  "geometry": {"coordinates":[-1.4523789883,51.5912361145],"type":"Point"}
}