{
  "type": "Feature",
  "properties": {
    "addr:full":"Unit Ic Betton Way, Moretonhampstead Newton Abbot Devon TQ13 8NA",
    "addr:postcode":"tq13 8na",
    "addr:street":"Betton Way",
    "iso:country":"GB",
    "sg:address":"Unit Ic Betton Way, Moretonhampstead",
    "sg:city":"Newton Abbot",
    "sg:classifiers":[
        {
            "category":"Autos & Motor Vehicles",
            "subcategory":"Automobile Sales",
            "type":"Retail Goods"
        }
    ],
    "sg:phone":"+44 1647 440888",
    "sg:postcode":"TQ13 8NA",
    "sg:province":"Devon",
    "sg:tags":[
        "commercial"
    ],
    "wof:name":"Turners Trade Centre",
    "wof:placetype":"venue"
},
  "geometry": {"coordinates":[-3.7648940086,50.6608657837],"type":"Point"}
}