{
  "type": "Feature",
  "properties": {
    "addr:full":"58 Hurrs Road Skipton Lancashire BD23 2JX",
    "addr:housenumber":"58",
    "addr:postcode":"bd23 2jx",
    "addr:street":"Hurrs Road",
    "iso:country":"GB",
    "sg:address":"58 Hurrs Road",
    "sg:city":"Skipton",
    "sg:classifiers":[
        {
            "category":"Freight",
            "type":"Transportation"
        }
    ],
    "sg:phone":"+44 1756 793934",
    "sg:postcode":"BD23 2JX",
    "sg:province":"Lancashire",
    "sg:tags":[
        "haulage",
        "road"
    ],
    "wof:name":"B Nash",
    "wof:placetype":"venue"
},
  "geometry": {"coordinates":[-2.004527,53.960911],"type":"Point"}
}