{
  "type": "Feature",
  "properties": {
    "addr:full":"41 High Street Corby Northamptonshire NN17 1UU",
    "addr:housenumber":"41",
    "addr:postcode":"nn17 1uu",
    "addr:street":"High Street",
    "iso:country":"GB",
    "sg:address":"41 High Street",
    "sg:city":"Corby",
    "sg:classifiers":[
        {
            "category":"Personal",
            "subcategory":"Beauty Salon",
            "type":"Services"
        }
    ],
    "sg:phone":"+44 1536 202682",
    "sg:postcode":"NN17 1UU",
    "sg:province":"Northamptonshire",
    "sg:tags":[
        "unisex",
        "hairdresser"
    ],
    "wof:name":"Altered Image",
    "wof:placetype":"venue"
},
  "geometry": {"coordinates":[-0.6830350161,52.4908866882],"type":"Point"}
}