{
  "type": "Feature",
  "properties": {
    "iso:country":"GB",
    "sg:address":"Suite 7, 1st Floor",
    "sg:city":"Wolverhampton",
    "sg:classifiers":[
        {
            "category":"Personal",
            "subcategory":"Psychics & Astrologers",
            "type":"Services"
        }
    ],
    "sg:postcode":"WV1 1HP",
    "sg:province":"West Midlands",
    "wof:name":"Anthony Love",
    "wof:placetype":"venue"
},
  "geometry": {"coordinates":[-2.126112,52.589146],"type":"Point"}
}