{
  "type": "Feature",
  "properties": {
    "addr:full":"Mercury Rd, Gallowfields Trading Est Richmond North Yorkshire DL10 4TQ",
    "addr:postcode":"dl10 4tq",
    "addr:street":"Mercury Rd Gallowfields;Yorkshire",
    "iso:country":"GB",
    "sg:address":"Mercury Rd, Gallowfields Trading Est",
    "sg:city":"Richmond",
    "sg:classifiers":[
        {
            "category":"Shopping",
            "subcategory":"Clothing, Apparel, & Fashions",
            "type":"Retail Goods"
        }
    ],
    "sg:phone":"+44 1748 826668",
    "sg:postcode":"DL10 4TQ",
    "sg:province":"North Yorkshire",
    "sg:tags":[
        "workwear",
        "protective"
    ],
    "wof:name":"R S R Sports Wear",
    "wof:placetype":"venue"
},
  "geometry": {"coordinates":[-1.749341011,54.4121742249],"type":"Point"}
}