{
  "type": "Feature",
  "properties": {
    "iso:country":"GB",
    "sg:address":"8 Percy Street",
    "sg:city":"Larkhall",
    "sg:classifiers":[
        {
            "category":"Home & Garden",
            "subcategory":"Building Materials",
            "type":"Retail Goods"
        }
    ],
    "sg:phone":"+44 1698 881032",
    "sg:postcode":"ML9 2AF",
    "sg:province":"South Lanarkshire",
    "sg:tags":[
        "fencing"
    ],
    "wof:name":"Marchbank  R  & Son Ltd.",
    "wof:placetype":"venue"
},
  "geometry": {"coordinates":[-3.972836,55.742161],"type":"Point"}
}