{
  "type": "Feature",
  "properties": {
    "addr:full":"Cairston Road Stromness Orkney Islands KW16 3JS",
    "addr:postcode":"kw16 3js",
    "addr:street":"Cairston Road",
    "iso:country":"GB",
    "sg:address":"Cairston Road",
    "sg:city":"Stromness",
    "sg:classifiers":[
        {
            "category":"Social Services",
            "subcategory":"Job Training",
            "type":"Services"
        },
        {
            "category":"Military Area",
            "subcategory":"Coast Guard Base",
            "type":"Public Place"
        }
    ],
    "sg:phone":"+44 1856 850576",
    "sg:postcode":"KW16 3JS",
    "sg:province":"Orkney Islands",
    "sg:tags":[
        "engine",
        "engineering",
        "marine"
    ],
    "wof:name":"Hamnavoe Engineering",
    "wof:placetype":"venue"
},
  "geometry": {"coordinates":[-3.2837491035,58.9714241028],"type":"Point"}
}