{
  "type": "Feature",
  "properties": {
    "addr:full":"Redstone Industrial Estate, Redstone Road Boston Lincolnshire PE21 8EA",
    "addr:housenumber":"estate",
    "addr:postcode":"pe21 8ea",
    "addr:street":"Redstone Road",
    "iso:country":"GB",
    "sg:address":"Redstone Industrial Estate, Redstone Road",
    "sg:city":"Boston",
    "sg:classifiers":[
        {
            "category":"Retail",
            "subcategory":"Auto Repair",
            "type":"Services"
        }
    ],
    "sg:phone":"+44 1205 311834",
    "sg:postcode":"PE21 8EA",
    "sg:province":"Lincolnshire",
    "sg:tags":[
        "modification",
        "garage"
    ],
    "wof:name":"John Robinson Motor Services",
    "wof:placetype":"venue"
},
  "geometry": {"coordinates":[-0.0297219995,52.9679336548],"type":"Point"}
}