{
  "type": "Feature",
  "properties": {
    "addr:full":"Cowpe Bottom House, Cowpe Road, Waterfoot Rossendale Lancashire BB4 7DQ",
    "addr:postcode":"bb4 7dq",
    "addr:street":"Cowpe;Cowpe Road",
    "iso:country":"GB",
    "sg:address":"Cowpe Bottom House, Cowpe Road, Waterfoot",
    "sg:city":"Rossendale",
    "sg:classifiers":[
        {
            "category":"Professional",
            "subcategory":"Engineering",
            "type":"Services"
        }
    ],
    "sg:postcode":"BB4 7DQ",
    "sg:province":"Lancashire",
    "sg:tags":[
        "contractor",
        "electrical",
        "engineer"
    ],
    "wof:name":"C B H Electrical Services",
    "wof:placetype":"venue"
},
  "geometry": {"coordinates":[-2.249104,53.68644],"type":"Point"}
}