{
  "type": "Feature",
  "properties": {
    "iso:country":"GB",
    "sg:address":"7 High Street, Wednesfield",
    "sg:city":"Wolverhampton",
    "sg:classifiers":[
        {
            "category":"Food & Beverages",
            "subcategory":"Bakery",
            "type":"Retail Goods"
        }
    ],
    "sg:phone":"+44 1902 305172",
    "sg:postcode":"WV11 1SP",
    "sg:province":"Staffordshire",
    "sg:tags":[
        "baker"
    ],
    "wof:name":"Three Cooks Ltd.",
    "wof:placetype":"venue"
},
  "geometry": {"coordinates":[-2.083739,52.599003],"type":"Point"}
}