{
  "type": "Feature",
  "properties": {
    "iso:country":"GB",
    "sg:address":"113 Golden Cross Lane, Catshill",
    "sg:city":"Bromsgrove",
    "sg:classifiers":[
        {
            "category":"Professional",
            "subcategory":"Business Services",
            "type":"Services"
        },
        {
            "category":"Shopping",
            "subcategory":"Pets & Pet Supplies",
            "type":"Retail Goods"
        }
    ],
    "sg:phone":"+44 1527 871432",
    "sg:postcode":"B61 0LA",
    "sg:province":"Worcestershire",
    "sg:tags":[
        "shop",
        "import",
        "export",
        "agent"
    ],
    "wof:name":"Village Pets & Gardens",
    "wof:placetype":"venue"
},
  "geometry": {"coordinates":[-2.056733,52.363869],"type":"Point"}
}