{
  "type": "Feature",
  "properties": {
    "iso:country":"GB",
    "sg:address":"207-215 High St",
    "sg:city":"Orpington",
    "sg:classifiers":[
        {
            "category":"Shopping",
            "subcategory":"Books",
            "type":"Retail Goods"
        }
    ],
    "sg:phone":"+44 20 8665 7565",
    "sg:postcode":"BR6 0PF",
    "sg:province":"Kent",
    "wof:name":"DTS Publishing Ltd",
    "wof:placetype":"venue"
},
  "geometry": {"coordinates":[0.099884,51.376305],"type":"Point"}
}