{
  "type": "Feature",
  "properties": {
    "addr:full":"Ffynnon Menter, Phoenix Way Swansea Neath Port Talbot SA7 9HW",
    "addr:postcode":"sa7 9hw",
    "addr:street":"Ffynnon Menter Phoenix Way",
    "iso:country":"GB",
    "sg:address":"Ffynnon Menter, Phoenix Way",
    "sg:city":"Swansea",
    "sg:classifiers":[
        {
            "category":"Utilities",
            "subcategory":"Water",
            "type":"Services"
        }
    ],
    "sg:phone":"+44 800 052 0145",
    "sg:postcode":"SA7 9HW",
    "sg:province":"Neath Port Talbot",
    "wof:name":"Dwr Cwmru Welsh Water",
    "wof:placetype":"venue"
},
  "geometry": {"coordinates":[-3.8978970051,51.6597328186],"type":"Point"}
}