{
  "type": "Feature",
  "properties": {
    "addr:full":"Hartley Street Dewsbury West Yorkshire WF13 2BJ",
    "addr:postcode":"wf13 2bj",
    "addr:street":"Hartley Street",
    "iso:country":"GB",
    "sg:address":"Hartley Street",
    "sg:city":"Dewsbury",
    "sg:classifiers":[
        {
            "category":"Manufacturing",
            "subcategory":"Building Materials",
            "type":"Manufacturing & Wholesale Goods"
        }
    ],
    "sg:postcode":"WF13 2BJ",
    "sg:province":"West Yorkshire",
    "sg:tags":[
        "merchant",
        "builder"
    ],
    "wof:name":"W R Thompson & Co. Ltd.",
    "wof:placetype":"venue"
},
  "geometry": {"coordinates":[-1.633889,53.698261],"type":"Point"}
}