{
  "type": "Feature",
  "properties": {
    "addr:full":"1a Walpole Rd Wimbledon Greater London SW19 2BZ",
    "addr:housenumber":"1a",
    "addr:postcode":"sw19 2bz",
    "addr:street":"Walpole Rd",
    "iso:country":"GB",
    "sg:address":"1a Walpole Rd",
    "sg:city":"Wimbledon",
    "sg:classifiers":[
        {
            "category":"Farming",
            "subcategory":"Nursery",
            "type":"Manufacturing & Wholesale Goods"
        }
    ],
    "sg:phone":"+44 20 8543 2307",
    "sg:postcode":"SW19 2BZ",
    "sg:province":"Greater London",
    "sg:tags":[
        "creche"
    ],
    "wof:name":"First Steps Nursery",
    "wof:placetype":"venue"
},
  "geometry": {"coordinates":[-0.175618,51.420998],"type":"Point"}
}