{
  "type": "Feature",
  "properties": {
    "addr:full":"71 Warwick Road London Greater London SW5 9HB",
    "addr:housenumber":"71",
    "addr:postcode":"sw5 9hb",
    "addr:street":"Warwick Road",
    "iso:country":"GB",
    "sg:address":"71 Warwick Road",
    "sg:city":"London",
    "sg:classifiers":[
        {
            "category":"Real Estate",
            "subcategory":"Architect",
            "type":"Services"
        }
    ],
    "sg:phone":"+44 20 7370 3129",
    "sg:postcode":"SW5 9HB",
    "sg:province":"Greater London",
    "wof:name":"Stefan Zins Associates",
    "wof:placetype":"venue"
},
  "geometry": {"coordinates":[-0.19777,51.491142],"type":"Point"}
}