{
  "type": "Feature",
  "properties": {
    "addr:full":"12a Hampton Lovett Industrial Estate, Lovett Road, Hampton Lovett Droitwich Worcestershire WR9 0NX",
    "addr:housenumber":"12a",
    "addr:postcode":"wr9 0nx",
    "addr:street":"Hampton Lovett Industrial Estate Lovett Road",
    "iso:country":"GB",
    "sg:address":"12a Hampton Lovett Industrial Estate, Lovett Road, Hampton Lovett",
    "sg:city":"Droitwich",
    "sg:classifiers":[
        {
            "category":"Manufacturing",
            "subcategory":"Petroleum Products",
            "type":"Manufacturing & Wholesale Goods"
        }
    ],
    "sg:phone":"+44 1905 794130",
    "sg:postcode":"WR9 0NX",
    "sg:province":"Worcestershire",
    "sg:tags":[
        "double",
        "glazing"
    ],
    "wof:name":"Season Master Double Glazing Ltd.",
    "wof:placetype":"venue"
},
  "geometry": {"coordinates":[-2.166929,52.28429],"type":"Point"}
}