{
  "type": "Feature",
  "properties": {
    "iso:country":"GB",
    "sg:address":"Unit 8 Blackburn Trading Estate, Northumberland Close, Stanwell",
    "sg:city":"Staines",
    "sg:classifiers":[
        {
            "category":"Professional",
            "subcategory":"Detective & Security Services",
            "type":"Services"
        }
    ],
    "sg:phone":"+44 1784 421311",
    "sg:postcode":"TW19 7LN",
    "sg:province":"Berkshire",
    "wof:name":"Securicor Cash Services (Heathrow) Ltd.",
    "wof:placetype":"venue"
},
  "geometry": {"coordinates":[-0.480125,51.457314],"type":"Point"}
}