{
  "type": "Feature",
  "properties": {
    "addr:full":"52 North Harbour Street Ayr South Ayrshire KA8 8AH",
    "addr:housenumber":"52",
    "addr:postcode":"ka8 8ah",
    "addr:street":"North Harbour Street",
    "iso:country":"GB",
    "sg:address":"52 North Harbour Street",
    "sg:city":"Ayr",
    "sg:classifiers":[
        {
            "category":"Freight",
            "type":"Transportation"
        }
    ],
    "sg:phone":"+44 1292 610451",
    "sg:postcode":"KA8 8AH",
    "sg:province":"South Ayrshire",
    "sg:tags":[
        "overseas",
        "shipping",
        "removal"
    ],
    "wof:name":"Denholm Barwil Ltd.",
    "wof:placetype":"venue"
},
  "geometry": {"coordinates":[-4.636447,55.467995],"type":"Point"}
}