{
  "type": "Feature",
  "properties": {
    "addr:full":"Unit 5 The Lanchesters, 162-166 Fulham Palace Road London Greater London W6 9ER",
    "addr:housenumber":"unit 5;162-166",
    "addr:postcode":"w6 9er",
    "addr:street":"The Lanchesters;Fulham Palace Road",
    "iso:country":"GB",
    "sg:address":"Unit 5 The Lanchesters, 162-166 Fulham Palace Road",
    "sg:city":"London",
    "sg:classifiers":[
        {
            "category":"Personal",
            "type":"Services"
        }
    ],
    "sg:phone":"+44 870 010 4909",
    "sg:postcode":"W6 9ER",
    "sg:province":"Greater London",
    "sg:tags":[
        "gift"
    ],
    "wof:name":"Virgin Vouchers Ltd.",
    "wof:placetype":"venue"
},
  "geometry": {"coordinates":[-0.22094,51.486469],"type":"Point"}
}