{
  "type": "Feature",
  "properties": {
    "addr:full":"Shamblehurst La North Southampton Hampshire SO32 2BY",
    "addr:postcode":"so32 2by",
    "addr:street":"La North",
    "iso:country":"GB",
    "sg:address":"Shamblehurst La North",
    "sg:city":"Southampton",
    "sg:classifiers":[
        {
            "category":"Building & Trades",
            "subcategory":"Construction",
            "type":"Services"
        }
    ],
    "sg:postcode":"SO32 2BY",
    "sg:province":"Hampshire",
    "sg:tags":[
        "joiner",
        "carpenter"
    ],
    "wof:name":"Crook,S,",
    "wof:placetype":"venue"
},
  "geometry": {"coordinates":[-1.293795,50.937092],"type":"Point"}
}