{
  "type": "Feature",
  "properties": {
    "iso:country":"GB",
    "sg:address":"57 Ship Street",
    "sg:city":"Brighton",
    "sg:classifiers":[
        {
            "category":"Shopping",
            "subcategory":"Comic Books",
            "type":"Retail Goods"
        }
    ],
    "sg:phone":"+44 1273 325257",
    "sg:postcode":"BN1 1AF",
    "sg:province":"East Sussex",
    "sg:tags":[
        "jeweller"
    ],
    "wof:name":"Northern Goldsmiths Ltd.",
    "wof:placetype":"venue"
},
  "geometry": {"coordinates":[-0.141536,50.82206],"type":"Point"}
}