{
  "type": "Feature",
  "properties": {
    "iso:country":"GB",
    "sg:address":"Upper Buckholt, Manson",
    "sg:city":"Monmouth",
    "sg:classifiers":[
        {
            "category":"Farming",
            "subcategory":"Livestock Farm",
            "type":"Manufacturing & Wholesale Goods"
        }
    ],
    "sg:postcode":"NP25 5RB",
    "sg:province":"Gloucestershire",
    "sg:tags":[
        "others"
    ],
    "wof:name":"I Jones",
    "wof:placetype":"venue"
},
  "geometry": {"coordinates":[-2.71673,51.841293],"type":"Point"}
}