{
  "type": "Feature",
  "properties": {
    "addr:full":"165 Quince Tamworth Staffordshire B77 4ET",
    "addr:housenumber":"165",
    "addr:postcode":"b77 4et",
    "addr:street":"Quince",
    "iso:country":"GB",
    "sg:address":"165 Quince",
    "sg:city":"Tamworth",
    "sg:classifiers":[
        {
            "category":"Home & Garden",
            "subcategory":"Building Materials",
            "type":"Retail Goods"
        }
    ],
    "sg:phone":"+44 1827 65792",
    "sg:postcode":"B77 4ET",
    "sg:province":"Staffordshire",
    "sg:tags":[
        "furnishers",
        "bathroom",
        "planner"
    ],
    "wof:name":"Elegant Bathrooms",
    "wof:placetype":"venue"
},
  "geometry": {"coordinates":[-1.6528849602,52.6292800903],"type":"Point"}
}