{
  "type": "Feature",
  "properties": {
    "addr:full":"Cafeteria, Abbey Fields Swimming Pool Kenilworth Warwickshire CV8 1BP",
    "addr:postcode":"cv8 1bp",
    "iso:country":"GB",
    "sg:address":"Cafeteria, Abbey Fields Swimming Pool",
    "sg:city":"Kenilworth",
    "sg:classifiers":[
        {
            "category":"Government",
            "subcategory":"Office",
            "type":"Public Place"
        }
    ],
    "sg:phone":"+44 1926 857494",
    "sg:postcode":"CV8 1BP",
    "sg:province":"Warwickshire",
    "sg:tags":[
        "local"
    ],
    "wof:name":"Louise Nixon Catering",
    "wof:placetype":"venue"
},
  "geometry": {"coordinates":[-1.579441,52.342937],"type":"Point"}
}