{
  "type": "Feature",
  "properties": {
    "addr:full":"1 Station Square, Flitwick Bedford Bedfordshire MK45 1DP",
    "addr:housenumber":"1",
    "addr:postcode":"mk45 1dp",
    "addr:street":"Station Square",
    "iso:country":"GB",
    "sg:address":"1 Station Square, Flitwick",
    "sg:city":"Bedford",
    "sg:classifiers":[
        {
            "category":"Building & Trades",
            "subcategory":"Cleaning & Sanitation",
            "type":"Services"
        }
    ],
    "sg:phone":"+44 1525 717878",
    "sg:postcode":"MK45 1DP",
    "sg:province":"Bedfordshire",
    "sg:tags":[
        "cleaner",
        "window"
    ],
    "wof:name":"D & R Cleaning Services Ltd.",
    "wof:placetype":"venue"
},
  "geometry": {"coordinates":[-0.4940899909,52.0033912659],"type":"Point"}
}