{
  "type": "Feature",
  "properties": {
    "addr:full":"Unit 2, Eastlands Lane Maidstone Road Tonbridge Kent TN12 6BU",
    "addr:housenumber":"unit 2",
    "addr:postcode":"tn12 6bu",
    "addr:street":"Eastlands Lane Maidstone Road",
    "iso:country":"GB",
    "sg:address":"Unit 2, Eastlands Lane Maidstone Road",
    "sg:city":"Tonbridge",
    "sg:classifiers":[
        {
            "category":"Manufacturing",
            "subcategory":"Electronics",
            "type":"Manufacturing & Wholesale Goods"
        }
    ],
    "sg:phone":"+44 1892 836836",
    "sg:postcode":"TN12 6BU",
    "sg:province":"Kent",
    "sg:tags":[
        "control",
        "component",
        "-",
        "electronic"
    ],
    "wof:name":"Solid State Supplies Plc",
    "wof:placetype":"venue"
},
  "geometry": {"coordinates":[0.38803,51.18681],"type":"Point"}
}