{
  "type": "Feature",
  "properties": {
    "addr:full":"26-28 Market Street Ulverston Cumbria LA12 7LR",
    "addr:housenumber":"26-28",
    "addr:postcode":"la12 7lr",
    "addr:street":"Market Street",
    "iso:country":"GB",
    "sg:address":"26-28 Market Street",
    "sg:city":"Ulverston",
    "sg:classifiers":[
        {
            "category":"Shopping",
            "subcategory":"Jewelry",
            "type":"Retail Goods"
        },
        {
            "category":"Shopping",
            "subcategory":"Comic Books",
            "type":"Retail Goods"
        }
    ],
    "sg:phone":"+44 1229 585430",
    "sg:postcode":"LA12 7LR",
    "sg:province":"Cumbria",
    "sg:tags":[
        "jeweller",
        "sale",
        "jewellery"
    ],
    "wof:name":"Lindow's Jewellers",
    "wof:placetype":"venue"
},
  "geometry": {"coordinates":[-3.094878,54.195869],"type":"Point"}
}