{
  "type": "Feature",
  "properties": {
    "addr:full":"3 Sylvan Avenue London Greater London N22 5HX",
    "addr:housenumber":"3",
    "addr:postcode":"n22 5hx",
    "addr:street":"Sylvan Avenue",
    "iso:country":"GB",
    "sg:address":"3 Sylvan Avenue",
    "sg:city":"London",
    "sg:classifiers":[
        {
            "category":"Freight",
            "type":"Transportation"
        }
    ],
    "sg:postcode":"N22 5HX",
    "sg:province":"Greater London",
    "sg:tags":[
        "haulage",
        "road"
    ],
    "wof:name":"G. A. Devlin Haulage Limited",
    "wof:placetype":"venue"
},
  "geometry": {"coordinates":[-0.111029,51.606045],"type":"Point"}
}