{
  "type": "Feature",
  "properties": {
    "addr:full":"Watford Business Centre, 135 The Parade, High St Watford Hertfordshire WD1 1NA",
    "addr:housenumber":"135",
    "addr:postcode":"wd1 1na",
    "addr:street":"The Parade High St",
    "iso:country":"GB",
    "sg:address":"Watford Business Centre, 135 The Parade, High St",
    "sg:city":"Watford",
    "sg:classifiers":[
        {
            "category":"Health Services",
            "subcategory":"Health Practitioner",
            "type":"Services"
        }
    ],
    "sg:phone":"+44 1923 448877",
    "sg:postcode":"WD1 1NA",
    "sg:province":"Hertfordshire",
    "sg:tags":[
        "hypnotherapists"
    ],
    "wof:name":"Ascend Plus",
    "wof:placetype":"venue"
},
  "geometry": {"coordinates":[-0.39072,51.652119],"type":"Point"}
}