{
  "type": "Feature",
  "properties": {
    "addr:full":"1 Rochester Parade Feltham Greater London TW13 4DX",
    "addr:housenumber":"1",
    "addr:postcode":"tw13 4dx",
    "addr:street":"Rochester Parade",
    "iso:country":"GB",
    "sg:address":"1 Rochester Parade",
    "sg:city":"Feltham",
    "sg:classifiers":[
        {
            "category":"Shopping",
            "subcategory":"Pharmacy",
            "type":"Retail Goods"
        }
    ],
    "sg:phone":"+44 20 8890 8784",
    "sg:postcode":"TW13 4DX",
    "sg:province":"Greater London",
    "sg:tags":[
        "pharmacist",
        "chemist"
    ],
    "wof:name":"Moss Pharmacy",
    "wof:placetype":"venue"
},
  "geometry": {"coordinates":[-0.4165900052,51.4408531189],"type":"Point"}
}