{
  "type": "Feature",
  "properties": {
    "iso:country":"GB",
    "sg:address":"Arch 880, Rosendale Road",
    "sg:city":"London",
    "sg:classifiers":[
        {
            "category":"Retail",
            "subcategory":"Auto Repair",
            "type":"Services"
        }
    ],
    "sg:phone":"+44 20 8674 5081",
    "sg:postcode":"SE24 9EH",
    "sg:province":"Greater London",
    "sg:tags":[
        "modification",
        "garage"
    ],
    "wof:name":"Keith Roberts",
    "wof:placetype":"venue"
},
  "geometry": {"coordinates":[-0.10114,51.448311],"type":"Point"}
}