{
  "type": "Feature",
  "properties": {
    "iso:country":"GB",
    "sg:address":"23 Blaengarw Road, Blaengarw",
    "sg:city":"Bridgend",
    "sg:classifiers":[
        {
            "category":"Organizations",
            "subcategory":"Community Association",
            "type":"Services"
        },
        {
            "category":"Organizations",
            "subcategory":"Membership Organization",
            "type":"Services"
        }
    ],
    "sg:phone":"+44 1656 870262",
    "sg:postcode":"CF32 8AW",
    "sg:province":"Bridgend",
    "sg:tags":[
        "club",
        "social"
    ],
    "wof:name":"BLAENGARW WORKMEN'S CLUB",
    "wof:placetype":"venue"
},
  "geometry": {"coordinates":[-3.591184,51.628223],"type":"Point"}
}