{
  "type": "Feature",
  "properties": {
    "iso:country":"GB",
    "sg:address":"Illers Leary, Filleigh",
    "sg:city":"Barnstaple",
    "sg:classifiers":[
        {
            "category":"Farming",
            "subcategory":"Livestock Farm",
            "type":"Manufacturing & Wholesale Goods"
        }
    ],
    "sg:postcode":"EX32 0SA",
    "sg:province":"Devon",
    "sg:tags":[
        "others"
    ],
    "wof:name":"Jonathan G Gill",
    "wof:placetype":"venue"
},
  "geometry": {"coordinates":[-3.9105539322,51.0349884033],"type":"Point"}
}