{
  "type": "Feature",
  "properties": {
    "iso:country":"GB",
    "sg:address":"1 Hereford Road",
    "sg:city":"London",
    "sg:classifiers":[
        {
            "category":"Banks & Credit Unions",
            "subcategory":"Financial Services",
            "type":"Services"
        }
    ],
    "sg:postcode":"W5 4SE",
    "sg:province":"Greater London",
    "sg:tags":[
        "adviser"
    ],
    "wof:name":"Day Profundis Ltd.",
    "wof:placetype":"venue"
},
  "geometry": {"coordinates":[-0.3100480139,51.4996147156],"type":"Point"}
}