{
  "type": "Feature",
  "properties": {
    "iso:country":"GB",
    "sg:address":"Lidget Lane, Thurnscoe",
    "sg:city":"Rotherham",
    "sg:classifiers":[
        {
            "category":"Arena",
            "subcategory":"Sports Club",
            "type":"Entertainment"
        },
        {
            "category":"Organizations",
            "subcategory":"Membership Organization",
            "type":"Services"
        }
    ],
    "sg:postcode":"S63 0BZ",
    "sg:province":"South Yorkshire",
    "sg:tags":[
        "social"
    ],
    "wof:name":"Hickleton Colliery Officials Club",
    "wof:placetype":"venue"
},
  "geometry": {"coordinates":[-1.306574,53.544479],"type":"Point"}
}