{
  "type": "Feature",
  "properties": {
    "addr:full":"The Frensham Suite, 13-21 High Street Guildford Surrey GU1 3DG",
    "addr:housenumber":"suite 13-21",
    "addr:postcode":"gu1 3dg",
    "addr:street":"High Street",
    "iso:country":"GB",
    "sg:address":"The Frensham Suite, 13-21 High Street",
    "sg:city":"Guildford",
    "sg:classifiers":[
        {
            "category":"Professional",
            "subcategory":"Employment Agencies",
            "type":"Services"
        }
    ],
    "sg:phone":"+44 1483 534872",
    "sg:postcode":"GU1 3DG",
    "sg:province":"Surrey",
    "sg:tags":[
        "consultant"
    ],
    "wof:name":"Busy Bodies",
    "wof:placetype":"venue"
},
  "geometry": {"coordinates":[-0.570516,51.237087],"type":"Point"}
}