{
  "type": "Feature",
  "properties": {
    "addr:full":"Glebe View, Wolvey Lodge Business Centre Hinckley Leicestershire LE10 3HB",
    "addr:housenumber":"wolvey;business",
    "addr:postcode":"le10 3hb",
    "addr:street":"Glebe",
    "iso:country":"GB",
    "sg:address":"Glebe View, Wolvey Lodge Business Centre",
    "sg:city":"Hinckley",
    "sg:classifiers":[
        {
            "category":"Home & Garden",
            "subcategory":"Hardware",
            "type":"Retail Goods"
        }
    ],
    "sg:phone":"+44 1455 222080",
    "sg:postcode":"LE10 3HB",
    "sg:province":"Leicestershire",
    "sg:tags":[
        "equipment",
        "heating"
    ],
    "wof:name":"Bekaert Combustion Technology Ltd.",
    "wof:placetype":"venue"
},
  "geometry": {"coordinates":[-1.369322,52.485638],"type":"Point"}
}