{
  "type": "Feature",
  "properties": {
    "addr:full":"Lindsey Avenue York North Yorkshire YO26 4RL",
    "addr:postcode":"yo26 4rl",
    "addr:street":"Lindsey Avenue",
    "iso:country":"GB",
    "sg:address":"Lindsey Avenue",
    "sg:city":"York",
    "sg:classifiers":[
        {
            "category":"Bars & Pubs",
            "type":"Food & Drink"
        },
        {
            "category":"Community Center",
            "subcategory":"Social",
            "type":"Public Place"
        }
    ],
    "sg:phone":"+44 1904 792173",
    "sg:postcode":"YO26 4RL",
    "sg:province":"North Yorkshire",
    "sg:tags":[
        "pubs",
        "house",
        "inn",
        "activity"
    ],
    "wof:name":"Pack of Cards",
    "wof:placetype":"venue"
},
  "geometry": {"coordinates":[-1.117097,53.962128],"type":"Point"}
}