{
  "type": "Feature",
  "properties": {
    "addr:full":"Ridley Hall Road Cambridge Cambridgeshire CB3 9HG",
    "addr:postcode":"cb3 9hg",
    "addr:street":"Hall Road",
    "iso:country":"GB",
    "sg:address":"Ridley Hall Road",
    "sg:city":"Cambridge",
    "sg:classifiers":[
        {
            "category":"Organizations",
            "subcategory":"Non-profit Organization",
            "type":"Services"
        }
    ],
    "sg:phone":"+44 1223 741083",
    "sg:postcode":"CB3 9HG",
    "sg:province":"Cambridgeshire",
    "sg:tags":[
        "organisation",
        "voluntary",
        "charity"
    ],
    "wof:name":"Centre for Youth Ministry",
    "wof:placetype":"venue"
},
  "geometry": {"coordinates":[0.1117149964,52.1999549866],"type":"Point"}
}