{
  "type": "Feature",
  "properties": {
    "addr:full":"48 Trinity Gdns London Greater London SW9 8DR",
    "addr:housenumber":"48",
    "addr:postcode":"sw9 8dr",
    "addr:street":"Trinity Gdns",
    "iso:country":"GB",
    "sg:address":"48 Trinity Gdns",
    "sg:city":"London",
    "sg:classifiers":[
        {
            "category":"Building & Trades",
            "subcategory":"Plumbing",
            "type":"Services"
        }
    ],
    "sg:postcode":"SW9 8DR",
    "sg:province":"Greater London",
    "sg:tags":[
        "heating"
    ],
    "wof:name":"Fast Aid",
    "wof:placetype":"venue"
},
  "geometry": {"coordinates":[-0.1192269996,51.4618034363],"type":"Point"}
}