{
  "type": "Feature",
  "properties": {
    "iso:country":"GB",
    "sg:address":"Durban Road",
    "sg:city":"Lowestoft",
    "sg:classifiers":[
        {
            "category":"Bars & Pubs",
            "type":"Food & Drink"
        }
    ],
    "sg:postcode":"NR33 0UH",
    "sg:province":"Suffolk",
    "sg:tags":[
        "pubs",
        "inn"
    ],
    "wof:name":"The Kevill Arms",
    "wof:placetype":"venue"
},
  "geometry": {"coordinates":[1.736385,52.469891],"type":"Point"}
}