{
  "type": "Feature",
  "properties": {
    "iso:country":"GB",
    "sg:address":"105 Wakefield Road, Lightcliffe",
    "sg:city":"Halifax",
    "sg:classifiers":[
        {
            "category":"Personal",
            "subcategory":"Beauty Salon",
            "type":"Services"
        }
    ],
    "sg:phone":"+44 1422 203804",
    "sg:postcode":"HX3 8SH",
    "sg:province":"West Yorkshire",
    "sg:tags":[
        "lady",
        "hairdresser"
    ],
    "wof:name":"Copper Top Hair Fashions",
    "wof:placetype":"venue"
},
  "geometry": {"coordinates":[-1.799335,53.725636],"type":"Point"}
}