{
  "type": "Feature",
  "properties": {
    "addr:full":"11 Gorse Road, Corfe Mullen Wimborne Dorset BH21 3SJ",
    "addr:housenumber":"11",
    "addr:postcode":"bh21 3sj",
    "addr:street":"Gorse Road",
    "iso:country":"GB",
    "sg:address":"11 Gorse Road, Corfe Mullen",
    "sg:city":"Wimborne",
    "sg:classifiers":[
        {
            "category":"Professional",
            "subcategory":"Computer Services",
            "type":"Services"
        }
    ],
    "sg:postcode":"BH21 3SJ",
    "sg:province":"Dorset",
    "sg:tags":[
        "system",
        "software"
    ],
    "wof:name":"Opex Computing",
    "wof:placetype":"venue"
},
  "geometry": {"coordinates":[-2.0263750553,50.7667732239],"type":"Point"}
}