{
  "type": "Feature",
  "properties": {
    "addr:full":"Craven Edge Enterprise Centre, Back Clarendon Place, Hopwood Lane Halifax West Yorkshire HX1 5EL",
    "addr:postcode":"hx1 5el",
    "addr:street":"Back Clarendon Place Hopwood Lane",
    "iso:country":"GB",
    "sg:address":"Craven Edge Enterprise Centre, Back Clarendon Place, Hopwood Lane",
    "sg:city":"Halifax",
    "sg:classifiers":[
        {
            "category":"Professional",
            "type":"Services"
        }
    ],
    "sg:phone":"+44 1422 367277",
    "sg:postcode":"HX1 5EL",
    "sg:province":"West Yorkshire",
    "sg:tags":[
        "control",
        "system"
    ],
    "wof:name":"Penrose Control Systems Ltd.",
    "wof:placetype":"venue"
},
  "geometry": {"coordinates":[-1.862224,53.721233],"type":"Point"}
}