{
  "type": "Feature",
  "properties": {
    "addr:full":"34 High Street Auchterarder Perth and Kinross PH3 1DB",
    "addr:housenumber":"34",
    "addr:postcode":"ph3 1db",
    "addr:street":"High Street",
    "iso:country":"GB",
    "sg:address":"34 High Street",
    "sg:city":"Auchterarder",
    "sg:classifiers":[
        {
            "category":"Cafe",
            "type":"Food & Drink"
        }
    ],
    "sg:postcode":"PH3 1DB",
    "sg:province":"Perth and Kinross",
    "sg:tags":[
        "tea",
        "room"
    ],
    "wof:name":"The Little Tearoom",
    "wof:placetype":"venue"
},
  "geometry": {"coordinates":[-3.7022531033,56.2974128723],"type":"Point"}
}