{
  "type": "Feature",
  "properties": {
    "addr:full":"11 Heritage Court, Lower Bridge Street Chester Cheshire CH1 1RD",
    "addr:housenumber":"11",
    "addr:postcode":"ch1 1rd",
    "addr:street":"Heritage Court Lower Bridge Street",
    "iso:country":"GB",
    "sg:address":"11 Heritage Court, Lower Bridge Street",
    "sg:city":"Chester",
    "sg:classifiers":[
        {
            "category":"Professional",
            "subcategory":"Management & Consulting",
            "type":"Services"
        }
    ],
    "sg:phone":"+44 1244 313022",
    "sg:postcode":"CH1 1RD",
    "sg:province":"Cheshire",
    "sg:tags":[
        "consultant",
        "business"
    ],
    "sg:website":"http://www.clseurope.com",
    "wof:name":"C L S Europe",
    "wof:placetype":"venue"
},
  "geometry": {"coordinates":[-2.8943688869,53.188129425],"type":"Point"}
}