{
  "type": "Feature",
  "properties": {
    "iso:country":"GB",
    "sg:address":"36 Montgomery Road",
    "sg:city":"Barry",
    "sg:classifiers":[
        {
            "category":"Home & Garden",
            "subcategory":"Carpets & Floor Coverings",
            "type":"Retail Goods"
        }
    ],
    "sg:postcode":"CF62 7DB",
    "sg:province":"The Vale of Glamorgan",
    "sg:tags":[
        "cleaner",
        "upholstery"
    ],
    "wof:name":"Masterclean",
    "wof:placetype":"venue"
},
  "geometry": {"coordinates":[-3.2816519737,51.4029655457],"type":"Point"}
}