{
  "type": "Feature",
  "properties": {
    "addr:full":"45 Trehafod Road, Trehafod Pontypridd Caerphilly CF37 2LR",
    "addr:housenumber":"45",
    "addr:postcode":"cf37 2lr",
    "addr:street":"Trehafod Road",
    "iso:country":"GB",
    "sg:address":"45 Trehafod Road, Trehafod",
    "sg:city":"Pontypridd",
    "sg:classifiers":[
        {
            "category":"Organizations",
            "subcategory":"Membership Organization",
            "type":"Services"
        }
    ],
    "sg:phone":"+44 1443 682753",
    "sg:postcode":"CF37 2LR",
    "sg:province":"Caerphilly",
    "sg:tags":[
        "club"
    ],
    "wof:name":"Trehafod Memorial Hall Social Club Ltd.",
    "wof:placetype":"venue"
},
  "geometry": {"coordinates":[-3.3775229454,51.6092453003],"type":"Point"}
}