{
  "type": "Feature",
  "properties": {
    "iso:country":"GB",
    "sg:address":"120 Crosland Hill Road",
    "sg:city":"Huddersfield",
    "sg:classifiers":[
        {
            "category":"Building & Trades",
            "subcategory":"Construction",
            "type":"Services"
        }
    ],
    "sg:phone":"+44 1484 654312",
    "sg:postcode":"HD4 5NZ",
    "sg:province":"West Yorkshire",
    "sg:tags":[
        "builder"
    ],
    "wof:name":"Paul Graham",
    "wof:placetype":"venue"
},
  "geometry": {"coordinates":[-1.825357,53.632675],"type":"Point"}
}