{
  "type": "Feature",
  "properties": {
    "addr:full":"2b Boswell Park Ayr South Ayrshire KA7 1QF",
    "addr:housenumber":"2b",
    "addr:postcode":"ka7 1qf",
    "addr:street":"Boswell Park",
    "iso:country":"GB",
    "sg:address":"2b Boswell Park",
    "sg:city":"Ayr",
    "sg:classifiers":[
        {
            "category":"Professional",
            "subcategory":"Employment Agencies",
            "type":"Services"
        }
    ],
    "sg:phone":"+44 1292 281421",
    "sg:postcode":"KA7 1QF",
    "sg:province":"South Ayrshire",
    "sg:tags":[
        "career",
        "guidance"
    ],
    "wof:name":"Careers Centre (Scotland)",
    "wof:placetype":"venue"
},
  "geometry": {"coordinates":[-4.6339421272,55.4624786377],"type":"Point"}
}