{
  "type": "Feature",
  "properties": {
    "addr:full":"19 Chapel Market London Greater London N1 9EZ",
    "addr:housenumber":"19",
    "addr:postcode":"n1 9ez",
    "addr:street":"Chapel Market",
    "iso:country":"GB",
    "sg:address":"19 Chapel Market",
    "sg:city":"London",
    "sg:classifiers":[
        {
            "category":"Personal",
            "subcategory":"Beauty Salon",
            "type":"Services"
        },
        {
            "category":"Personal",
            "subcategory":"Barber",
            "type":"Services"
        }
    ],
    "sg:phone":"+44 20 7833 2878",
    "sg:postcode":"N1 9EZ",
    "sg:province":"Greater London",
    "sg:tags":[
        "unisex",
        "hairdresser"
    ],
    "wof:name":"Hair Base",
    "wof:placetype":"venue"
},
  "geometry": {"coordinates":[-0.109608002,51.5335578918],"type":"Point"}
}