{
  "type": "Feature",
  "properties": {
    "addr:full":"Uphill, How La Coulsdon Surrey CR5 3LL",
    "addr:postcode":"cr5 3ll",
    "iso:country":"GB",
    "sg:address":"Uphill, How La",
    "sg:city":"Coulsdon",
    "sg:classifiers":[
        {
            "category":"Farming",
            "subcategory":"Vineyard",
            "type":"Manufacturing & Wholesale Goods"
        }
    ],
    "sg:phone":"+44 1737 553600",
    "sg:postcode":"CR5 3LL",
    "sg:province":"Surrey",
    "wof:name":"C R Vaughan",
    "wof:placetype":"venue"
},
  "geometry": {"coordinates":[-0.139179,51.318924],"type":"Point"}
}