{
  "type": "Feature",
  "properties": {
    "iso:country":"GB",
    "sg:address":"103 St James Lane",
    "sg:city":"Coventry",
    "sg:classifiers":[
        {
            "category":"Health Services",
            "subcategory":"Doctor",
            "type":"Services"
        }
    ],
    "sg:phone":"+44 24 7630 2082",
    "sg:postcode":"CV3 3FW",
    "sg:province":"Warwickshire",
    "sg:tags":[
        "practitioners"
    ],
    "wof:name":"R Hogg",
    "wof:placetype":"venue"
},
  "geometry": {"coordinates":[-1.466706,52.38419],"type":"Point"}
}