{
  "type": "Feature",
  "properties": {
    "addr:full":"195a Station Road, Foston Derby Derbyshire DE65 5PT",
    "addr:housenumber":"195a",
    "addr:postcode":"de65 5pt",
    "addr:street":"Station Road",
    "iso:country":"GB",
    "sg:address":"195a Station Road, Foston",
    "sg:city":"Derby",
    "sg:classifiers":[
        {
            "category":"Building & Trades",
            "subcategory":"Construction",
            "type":"Services"
        }
    ],
    "sg:postcode":"DE65 5PT",
    "sg:province":"Derbyshire",
    "sg:tags":[
        "window",
        "replacement"
    ],
    "wof:name":"Euro U K Design",
    "wof:placetype":"venue"
},
  "geometry": {"coordinates":[-1.6791579723,52.8733444214],"type":"Point"}
}