{
  "type": "Feature",
  "properties": {
    "addr:full":"25 New Street Honiton Devon EX14 1HA",
    "addr:housenumber":"25",
    "addr:postcode":"ex14 1ha",
    "addr:street":"New Street",
    "iso:country":"GB",
    "sg:address":"25 New Street",
    "sg:city":"Honiton",
    "sg:classifiers":[
        {
            "category":"Food & Beverages",
            "subcategory":"Bakery",
            "type":"Retail Goods"
        }
    ],
    "sg:phone":"+44 1404 42994",
    "sg:postcode":"EX14 1HA",
    "sg:province":"Devon",
    "sg:tags":[
        "baker"
    ],
    "wof:name":"Acutts Bakery",
    "wof:placetype":"venue"
},
  "geometry": {"coordinates":[-3.188472,50.79884],"type":"Point"}
}