{
  "type": "Feature",
  "properties": {
    "iso:country":"GB",
    "sg:address":"Quarry Lane",
    "sg:city":"Mansfield",
    "sg:classifiers":[
        {
            "category":"Farming",
            "subcategory":"Dairy Farm",
            "type":"Manufacturing & Wholesale Goods"
        }
    ],
    "sg:phone":"+44 1623 624564",
    "sg:postcode":"NG18 5DA",
    "sg:province":"Nottinghamshire",
    "wof:name":"Express Dairies",
    "wof:placetype":"venue"
},
  "geometry": {"coordinates":[-1.203329,53.136475],"type":"Point"}
}