{
  "type": "Feature",
  "properties": {
    "addr:full":"122 New Rd, Side, Horsforth Leeds West Yorkshire LS18 4QB",
    "addr:housenumber":"122",
    "addr:postcode":"ls18 4qb",
    "addr:street":"New Rd Side",
    "iso:country":"GB",
    "sg:address":"122 New Rd, Side, Horsforth",
    "sg:city":"Leeds",
    "sg:classifiers":[
        {
            "category":"Professional",
            "subcategory":"Accounting & Tax Preparation",
            "type":"Services"
        }
    ],
    "sg:phone":"+44 113 281 8131",
    "sg:postcode":"LS18 4QB",
    "sg:province":"West Yorkshire",
    "sg:tags":[
        "accountant"
    ],
    "wof:name":"Rushworth Helliwell",
    "wof:placetype":"venue"
},
  "geometry": {"coordinates":[-1.639522,53.834335],"type":"Point"}
}