{
  "type": "Feature",
  "properties": {
    "iso:country":"GB",
    "sg:address":"6 Eastbank Street",
    "sg:city":"Southport",
    "sg:classifiers":[
        {
            "category":"Home & Garden",
            "subcategory":"Furniture",
            "type":"Retail Goods"
        }
    ],
    "sg:phone":"+44 1704 500478",
    "sg:postcode":"PR8 1DW",
    "sg:province":"Lancashire",
    "wof:name":"Waldmans",
    "wof:placetype":"venue"
},
  "geometry": {"coordinates":[-3.006627,53.646629],"type":"Point"}
}