{
  "type": "Feature",
  "properties": {
    "iso:country":"GB",
    "sg:address":"Haulfryn, Bryn Dedwydd",
    "sg:city":"Denbigh",
    "sg:classifiers":[
        {
            "category":"Building & Trades",
            "subcategory":"Plumbing",
            "type":"Services"
        }
    ],
    "sg:phone":"+44 1745 813179",
    "sg:postcode":"LL16 3TP",
    "sg:province":"Conwy",
    "sg:tags":[
        "heating"
    ],
    "wof:name":"Edward C Wynne",
    "wof:placetype":"venue"
},
  "geometry": {"coordinates":[-3.4211490154,53.1834106445],"type":"Point"}
}