{
  "type": "Feature",
  "properties": {
    "addr:full":"Brookfield Centre, Brookfield Drive, Aintree Liverpool Merseyside L9 7AS",
    "addr:postcode":"l9 7as",
    "addr:street":"Brookfield Drive",
    "iso:country":"GB",
    "sg:address":"Brookfield Centre, Brookfield Drive, Aintree",
    "sg:city":"Liverpool",
    "sg:classifiers":[
        {
            "category":"Retail",
            "subcategory":"Storage",
            "type":"Services"
        }
    ],
    "sg:phone":"+44 151 523 0200",
    "sg:postcode":"L9 7AS",
    "sg:province":"Merseyside",
    "sg:tags":[
        "household",
        "removal"
    ],
    "wof:name":"Northwest Storage & Distribution Ltd.",
    "wof:placetype":"venue"
},
  "geometry": {"coordinates":[-2.943934,53.460651],"type":"Point"}
}