{
  "type": "Feature",
  "properties": {
    "addr:full":"15 New Burlington St London Greater London W1S 3BG",
    "addr:housenumber":"15",
    "addr:postcode":"w1s 3bg",
    "addr:street":"New Burlington St",
    "iso:country":"GB",
    "sg:address":"15 New Burlington St",
    "sg:city":"London",
    "sg:classifiers":[
        {
            "category":"Bars & Pubs",
            "subcategory":"Wine Bar",
            "type":"Food & Drink"
        }
    ],
    "sg:phone":"+44 20 7287 8327",
    "sg:postcode":"W1S 3BG",
    "sg:province":"Greater London",
    "wof:name":"Tarlcourt Ltd",
    "wof:placetype":"venue"
},
  "geometry": {"coordinates":[-0.1404079944,51.5116996765],"type":"Point"}
}