{
  "type": "Feature",
  "properties": {
    "addr:full":"North St Peterborough Cambridgeshire PE6 0EG",
    "addr:postcode":"pe6 0eg",
    "addr:street":"North St",
    "iso:country":"GB",
    "sg:address":"North St",
    "sg:city":"Peterborough",
    "sg:classifiers":[
        {
            "category":"Shopping",
            "subcategory":"Pharmacy",
            "type":"Retail Goods"
        }
    ],
    "sg:phone":"+44 1733 210207",
    "sg:postcode":"PE6 0EG",
    "sg:province":"Cambridgeshire",
    "sg:tags":[
        "pharmacist",
        "chemist"
    ],
    "wof:name":"Hills Pharmacy The",
    "wof:placetype":"venue"
},
  "geometry": {"coordinates":[-0.169574,52.679424],"type":"Point"}
}