{
  "type": "Feature",
  "properties": {
    "addr:full":"31 Cambridge Street Cleethorpes Lincolnshire DN35 8HB",
    "addr:housenumber":"31",
    "addr:postcode":"dn35 8hb",
    "addr:street":"Cambridge Street",
    "iso:country":"GB",
    "sg:address":"31 Cambridge Street",
    "sg:city":"Cleethorpes",
    "sg:classifiers":[
        {
            "category":"Professional",
            "subcategory":"Art Services",
            "type":"Services"
        }
    ],
    "sg:postcode":"DN35 8HB",
    "sg:province":"Lincolnshire",
    "sg:tags":[
        "framing"
    ],
    "wof:name":"Gallery",
    "wof:placetype":"venue"
},
  "geometry": {"coordinates":[-0.0266430005,53.5570716858],"type":"Point"}
}