{
  "type": "Feature",
  "properties": {
    "addr:full":"290 Jeans Way Dunstable Bedfordshire LU5 4PT",
    "addr:housenumber":"290",
    "addr:postcode":"lu5 4pt",
    "addr:street":"Jeans Way",
    "iso:country":"GB",
    "sg:address":"290 Jeans Way",
    "sg:city":"Dunstable",
    "sg:classifiers":[
        {
            "category":"Building & Trades",
            "subcategory":"Construction",
            "type":"Services"
        }
    ],
    "sg:phone":"+44 1582 661655",
    "sg:postcode":"LU5 4PT",
    "sg:province":"Bedfordshire",
    "sg:tags":[
        "roofing",
        "contracting"
    ],
    "wof:name":"V E B Roofing Co",
    "wof:placetype":"venue"
},
  "geometry": {"coordinates":[-0.4879179895,51.8887939453],"type":"Point"}
}