{
  "type": "Feature",
  "properties": {
    "iso:country":"GB",
    "sg:address":"2 Market Square",
    "sg:city":"Bishops Stortford",
    "sg:classifiers":[
        {
            "category":"Personal",
            "subcategory":"Beauty Salon",
            "type":"Services"
        }
    ],
    "sg:phone":"+44 1279 652617",
    "sg:postcode":"CM23 3UU",
    "sg:province":"Essex",
    "sg:tags":[
        "unisex",
        "hairdresser"
    ],
    "wof:name":"Avant Garde",
    "wof:placetype":"venue"
},
  "geometry": {"coordinates":[0.158637,51.870861],"type":"Point"}
}