{
  "type": "Feature",
  "properties": {
    "iso:country":"GB",
    "sg:address":"Unit 3 Station Road Industrial E, State Station Roa",
    "sg:city":"Stroud",
    "sg:classifiers":[
        {
            "category":"Wholesale",
            "subcategory":"Meat",
            "type":"Manufacturing & Wholesale Goods"
        }
    ],
    "sg:phone":"+44 1453 873400",
    "sg:postcode":"GL5 5EQ",
    "sg:province":"Gloucestershire",
    "sg:tags":[
        "wholesaler",
        "-"
    ],
    "wof:name":"Amberley Vale Foods Ltd",
    "wof:placetype":"venue"
},
  "geometry": {"coordinates":[-2.231226,51.718784],"type":"Point"}
}