{
  "type": "Feature",
  "properties": {
    "iso:country":"GB",
    "sg:address":"Fowley Cross",
    "sg:city":"Okehampton",
    "sg:classifiers":[
        {
            "category":"Travel",
            "subcategory":"Hotels & Motels",
            "type":"Entertainment"
        }
    ],
    "sg:phone":"+44 1837 53053",
    "sg:postcode":"EX20 3NA",
    "sg:province":"Devon",
    "wof:name":"Manor House Hotel",
    "wof:placetype":"venue"
},
  "geometry": {"coordinates":[-4.043043,50.731056],"type":"Point"}
}