{
  "type": "Feature",
  "properties": {
    "iso:country":"GB",
    "sg:address":"Lower Aynho Grounds, Aynho",
    "sg:city":"Banbury",
    "sg:classifiers":[
        {
            "category":"Farming",
            "subcategory":"Farm",
            "type":"Manufacturing & Wholesale Goods"
        }
    ],
    "sg:phone":"+44 1869 810224",
    "sg:postcode":"OX17 3BW",
    "sg:province":"Northamptonshire",
    "sg:tags":[
        "mixed",
        "crop"
    ],
    "wof:name":"E N & T E Boswell",
    "wof:placetype":"venue"
},
  "geometry": {"coordinates":[-1.2538360357,51.9940643311],"type":"Point"}
}