{
  "type": "Feature",
  "properties": {
    "addr:full":"357-361 Lewisham High St Lewisham Greater London SE13 6NZ",
    "addr:housenumber":"357-361",
    "addr:postcode":"se13 6nz",
    "addr:street":"Lewisham High St",
    "iso:country":"GB",
    "sg:address":"357-361 Lewisham High St",
    "sg:city":"Lewisham",
    "sg:classifiers":[
        {
            "category":"Professional",
            "subcategory":"Lawyer & Legal Services",
            "type":"Services"
        }
    ],
    "sg:phone":"+44 1303 226854",
    "sg:postcode":"SE13 6NZ",
    "sg:province":"Greater London",
    "sg:tags":[
        "writing"
    ],
    "wof:name":"Wills Register The",
    "wof:placetype":"venue"
},
  "geometry": {"coordinates":[-0.0167410001,51.4518508911],"type":"Point"}
}