{
  "type": "Feature",
  "properties": {
    "addr:full":"24 St Lukes Road Southport Lancashire PR9 0SH",
    "addr:housenumber":"24",
    "addr:postcode":"pr9 0sh",
    "addr:street":"St Lukes Road",
    "iso:country":"GB",
    "sg:address":"24 St Lukes Road",
    "sg:city":"Southport",
    "sg:classifiers":[
        {
            "category":"Retail",
            "subcategory":"Driving School",
            "type":"Services"
        }
    ],
    "sg:postcode":"PR9 0SH",
    "sg:province":"Lancashire",
    "wof:name":"Kim Houston",
    "wof:placetype":"venue"
},
  "geometry": {"coordinates":[-2.9877319336,53.644859314],"type":"Point"}
}