{
  "type": "Feature",
  "properties": {
    "iso:country":"GB",
    "sg:address":"Ludham Hall",
    "sg:city":"Great Yarmouth",
    "sg:classifiers":[
        {
            "category":"Farming",
            "subcategory":"Dairy Farm",
            "type":"Manufacturing & Wholesale Goods"
        }
    ],
    "sg:phone":"+44 1692 678232",
    "sg:postcode":"NR29 5NU",
    "sg:province":"Norfolk",
    "wof:name":"D L Ritchie",
    "wof:placetype":"venue"
},
  "geometry": {"coordinates":[1.534781,52.739906],"type":"Point"}
}