{
  "type": "Feature",
  "properties": {
    "iso:country":"GB",
    "sg:address":"Southern Airs, 46 Cliff Rd",
    "sg:city":"Cowes",
    "sg:classifiers":[
        {
            "category":"Building & Trades",
            "subcategory":"Construction",
            "type":"Services"
        }
    ],
    "sg:phone":"+44 1983 291406",
    "sg:postcode":"PO31 8BN",
    "sg:province":"Isle of Wight",
    "sg:tags":[
        "decorator",
        "painter"
    ],
    "wof:name":"Dave Bryant",
    "wof:placetype":"venue"
},
  "geometry": {"coordinates":[-1.297866,50.758121],"type":"Point"}
}