{
  "type": "Feature",
  "properties": {
    "iso:country":"GB",
    "sg:address":"477 Chell Heath Road, Chell Heath",
    "sg:city":"Stoke-on-trent",
    "sg:classifiers":[
        {
            "category":"Fast Food",
            "type":"Food & Drink"
        }
    ],
    "sg:phone":"+44 1782 815700",
    "sg:postcode":"ST6 6HJ",
    "sg:province":"Staffordshire",
    "sg:tags":[
        "away",
        "take"
    ],
    "wof:name":"Srinager Balti & Kebab House Takeaway",
    "wof:placetype":"venue"
},
  "geometry": {"coordinates":[-2.182287,53.069241],"type":"Point"}
}