{
  "type": "Feature",
  "properties": {
    "addr:full":"179 Station Rd Edgware Greater London HA8 7JX",
    "addr:housenumber":"179",
    "addr:postcode":"ha8 7jx",
    "addr:street":"Station Rd",
    "iso:country":"GB",
    "sg:address":"179 Station Rd",
    "sg:city":"Edgware",
    "sg:classifiers":[
        {
            "category":"Travel",
            "subcategory":"Travel Agent",
            "type":"Entertainment"
        }
    ],
    "sg:phone":"+44 20 8951 5151",
    "sg:postcode":"HA8 7JX",
    "sg:province":"Greater London",
    "wof:name":"Broadway Travel Ltd",
    "wof:placetype":"venue"
},
  "geometry": {"coordinates":[-0.2758539915,51.6152801514],"type":"Point"}
}