{
  "type": "Feature",
  "properties": {
    "iso:country":"GB",
    "sg:address":"51 The Riddings, Stechford",
    "sg:city":"Birmingham",
    "sg:classifiers":[
        {
            "category":"Building & Trades",
            "subcategory":"Construction",
            "type":"Services"
        }
    ],
    "sg:postcode":"B33 9DE",
    "sg:province":"West Midlands",
    "sg:tags":[
        "roofing"
    ],
    "wof:name":"Barratt,James,",
    "wof:placetype":"venue"
},
  "geometry": {"coordinates":[-1.801311,52.489426],"type":"Point"}
}