{
  "type": "Feature",
  "properties": {
    "addr:full":"305 London Rd Westcliff On Sea Essex SS0 7BX",
    "addr:housenumber":"305",
    "addr:postcode":"ss0 7bx",
    "addr:street":"London Rd",
    "iso:country":"GB",
    "sg:address":"305 London Rd",
    "sg:city":"Westcliff On Sea",
    "sg:classifiers":[
        {
            "category":"Shopping",
            "subcategory":"Clothing, Apparel, & Fashions",
            "type":"Retail Goods"
        }
    ],
    "sg:phone":"+44 1702 430022",
    "sg:postcode":"SS0 7BX",
    "sg:province":"Essex",
    "sg:tags":[
        "t-shirt"
    ],
    "wof:name":"Pukka Signs",
    "wof:placetype":"venue"
},
  "geometry": {"coordinates":[0.6971920133,51.5416259766],"type":"Point"}
}