{
  "type": "Feature",
  "properties": {
    "iso:country":"GB",
    "sg:address":"15 Warbreck Court, Warbreck Hill Road",
    "sg:city":"Blackpool",
    "sg:classifiers":[
        {
            "category":"Home & Garden",
            "subcategory":"Household Appliances",
            "type":"Retail Goods"
        }
    ],
    "sg:phone":"+44 1253 358242",
    "sg:postcode":"FY2 9SR",
    "sg:province":"Lancashire",
    "sg:tags":[
        "electrical"
    ],
    "wof:name":"North Shore Domestics",
    "wof:placetype":"venue"
},
  "geometry": {"coordinates":[-3.050639,53.835514],"type":"Point"}
}