{
  "type": "Feature",
  "properties": {
    "addr:full":"9a Harvester Way, Fengate Peterborough Cambridgeshire PE1 5UT",
    "addr:housenumber":"9a",
    "addr:postcode":"pe1 5ut",
    "addr:street":"Harvester Way",
    "iso:country":"GB",
    "sg:address":"9a Harvester Way, Fengate",
    "sg:city":"Peterborough",
    "sg:classifiers":[
        {
            "category":"Wholesale",
            "subcategory":"Groceries",
            "type":"Manufacturing & Wholesale Goods"
        }
    ],
    "sg:phone":"+44 1733 348744",
    "sg:postcode":"PE1 5UT",
    "sg:province":"Cambridgeshire",
    "sg:tags":[
        "food",
        "supplier",
        "drink"
    ],
    "wof:name":"Golden Wonder Ltd.",
    "wof:placetype":"venue"
},
  "geometry": {"coordinates":[-0.2250889987,52.5701942444],"type":"Point"}
}