{
  "type": "Feature",
  "properties": {
    "addr:full":"Churchbridge Ho, Watling St Cannock Staffordshire WS11 3BP",
    "addr:postcode":"ws11 3bp",
    "addr:street":"Watling St",
    "iso:country":"GB",
    "sg:address":"Churchbridge Ho, Watling St",
    "sg:city":"Cannock",
    "sg:classifiers":[
        {
            "category":"Retail",
            "subcategory":"Storage",
            "type":"Services"
        }
    ],
    "sg:phone":"+44 1543 505077",
    "sg:postcode":"WS11 3BP",
    "sg:province":"Staffordshire",
    "sg:tags":[
        "vault",
        "safe"
    ],
    "wof:name":"Keep Secure Ltd",
    "wof:placetype":"venue"
},
  "geometry": {"coordinates":[-2.033145,52.690952],"type":"Point"}
}