{
  "type": "Feature",
  "properties": {
    "addr:full":"62 Norman Rd Walsall West Midlands WS5 3QN",
    "addr:housenumber":"62",
    "addr:postcode":"ws5 3qn",
    "addr:street":"Norman Rd",
    "iso:country":"GB",
    "sg:address":"62 Norman Rd",
    "sg:city":"Walsall",
    "sg:classifiers":[
        {
            "category":"Building & Trades",
            "subcategory":"Construction",
            "type":"Services"
        }
    ],
    "sg:postcode":"WS5 3QN",
    "sg:province":"West Midlands",
    "sg:tags":[
        "welder"
    ],
    "wof:name":"Orabin,Billy,",
    "wof:placetype":"venue"
},
  "geometry": {"coordinates":[-1.949014,52.577286],"type":"Point"}
}