{
  "type": "Feature",
  "properties": {
    "iso:country":"GB",
    "sg:address":"Unit 23, Dawkins Road, Hamworthy Industrial Estate",
    "sg:city":"Poole",
    "sg:classifiers":[
        {
            "category":"Retail",
            "subcategory":"Auto Repair",
            "type":"Services"
        }
    ],
    "sg:phone":"+44 1202 671741",
    "sg:postcode":"BH15 4JY",
    "sg:province":"Dorset",
    "sg:tags":[
        "body",
        "car",
        "repairer"
    ],
    "wof:name":"Ni-Dor Bodyworks",
    "wof:placetype":"venue"
},
  "geometry": {"coordinates":[-2.0148539543,50.7235984802],"type":"Point"}
}