{
  "type": "Feature",
  "properties": {
    "addr:full":"Penlon, Saron Llandysul Carmarthenshire SA44 5DZ",
    "addr:postcode":"sa44 5dz",
    "iso:country":"GB",
    "sg:address":"Penlon, Saron",
    "sg:city":"Llandysul",
    "sg:classifiers":[
        {
            "category":"Freight",
            "type":"Transportation"
        }
    ],
    "sg:postcode":"SA44 5DZ",
    "sg:province":"Carmarthenshire",
    "sg:tags":[
        "haulage",
        "road"
    ],
    "wof:name":"T M Davies & Sons",
    "wof:placetype":"venue"
},
  "geometry": {"coordinates":[-4.3699088097,52.0170898438],"type":"Point"}
}