{
  "type": "Feature",
  "properties": {
    "addr:full":"16 Larkfield Lane, Churchtown Southport Lancashire PR9 8NW",
    "addr:housenumber":"16",
    "addr:postcode":"pr9 8nw",
    "addr:street":"Larkfield Lane",
    "iso:country":"GB",
    "sg:address":"16 Larkfield Lane, Churchtown",
    "sg:city":"Southport",
    "sg:classifiers":[
        {
            "category":"Building & Trades",
            "subcategory":"Construction",
            "type":"Services"
        }
    ],
    "sg:postcode":"PR9 8NW",
    "sg:province":"Lancashire",
    "sg:tags":[
        "decorator",
        "painter"
    ],
    "wof:name":"Bill McCluskey",
    "wof:placetype":"venue"
},
  "geometry": {"coordinates":[-2.966424,53.666214],"type":"Point"}
}