{
  "type": "Feature",
  "properties": {
    "addr:full":"10 South End, Bookham Leatherhead Surrey KT23 4SQ",
    "addr:housenumber":"10",
    "addr:postcode":"kt23 4sq",
    "addr:street":"South End",
    "iso:country":"GB",
    "sg:address":"10 South End, Bookham",
    "sg:city":"Leatherhead",
    "sg:classifiers":[
        {
            "category":"Professional",
            "subcategory":"Management & Consulting",
            "type":"Services"
        }
    ],
    "sg:postcode":"KT23 4SQ",
    "sg:province":"Surrey",
    "sg:tags":[
        "consultant",
        "business"
    ],
    "wof:name":"Galestar Consultants Ltd.",
    "wof:placetype":"venue"
},
  "geometry": {"coordinates":[-0.367302,51.276783],"type":"Point"}
}