{
  "type": "Feature",
  "properties": {
    "iso:country":"GB",
    "sg:address":"Moray Golf Club, Stotfield Road",
    "sg:city":"Lossiemouth",
    "sg:classifiers":[
        {
            "category":"Sports & Exercise",
            "subcategory":"Golf",
            "type":"Entertainment"
        }
    ],
    "sg:phone":"+44 1343 813330",
    "sg:postcode":"IV31 6QS",
    "sg:province":"Moray",
    "sg:tags":[
        "equipment"
    ],
    "wof:name":"The Pro Shop",
    "wof:placetype":"venue"
},
  "geometry": {"coordinates":[-3.289304018,57.716709137],"type":"Point"}
}