{
  "type": "Feature",
  "properties": {
    "iso:country":"GB",
    "sg:address":"Burnbanks Village",
    "sg:city":"Aberdeen",
    "sg:classifiers":[
        {
            "category":"Farming",
            "subcategory":"Fish & Marine Products",
            "type":"Manufacturing & Wholesale Goods"
        }
    ],
    "sg:postcode":"AB12 3WN",
    "sg:province":"Aberdeen City",
    "sg:tags":[
        "fishmonger"
    ],
    "wof:name":"Woodward,Leslie McKenzie,",
    "wof:placetype":"venue"
},
  "geometry": {"coordinates":[-2.0700600147,57.1097183228],"type":"Point"}
}