{
  "type": "Feature",
  "properties": {
    "addr:full":"The Workshop, Bodrhyddan Hall, Dyserth Rd, Rhuddlan Rhyl Conwy LL18 5SB",
    "addr:postcode":"ll18 5sb",
    "addr:street":"Dyserth Rd",
    "iso:country":"GB",
    "sg:address":"The Workshop, Bodrhyddan Hall, Dyserth Rd, Rhuddlan",
    "sg:city":"Rhyl",
    "sg:classifiers":[
        {
            "category":"Building & Trades",
            "subcategory":"Construction",
            "type":"Services"
        }
    ],
    "sg:phone":"+44 1745 591129",
    "sg:postcode":"LL18 5SB",
    "sg:province":"Conwy",
    "sg:tags":[
        "joinery"
    ],
    "wof:name":"Llanelwy Joinery",
    "wof:placetype":"venue"
},
  "geometry": {"coordinates":[-3.4327700138,53.2959403992],"type":"Point"}
}