{
  "type": "Feature",
  "properties": {
    "addr:full":"617 Hertford Road Enfield Greater London EN3 6UP",
    "addr:housenumber":"617",
    "addr:postcode":"en3 6up",
    "addr:street":"Hertford Road",
    "iso:country":"GB",
    "sg:address":"617 Hertford Road",
    "sg:city":"Enfield",
    "sg:classifiers":[
        {
            "category":"Shopping",
            "subcategory":"Clothing, Apparel, & Fashions",
            "type":"Retail Goods"
        }
    ],
    "sg:phone":"+44 1992 761800",
    "sg:postcode":"EN3 6UP",
    "sg:province":"Greater London",
    "sg:tags":[
        "haberdasher"
    ],
    "wof:name":"The Sewing Box",
    "wof:placetype":"venue"
},
  "geometry": {"coordinates":[-0.040016,51.671535],"type":"Point"}
}