{
  "type": "Feature",
  "properties": {
    "iso:country":"GB",
    "sg:address":"Tow Top Farm, Cononley",
    "sg:city":"Keighley",
    "sg:classifiers":[
        {
            "category":"Farming",
            "subcategory":"Livestock Farm",
            "type":"Manufacturing & Wholesale Goods"
        }
    ],
    "sg:postcode":"BD20 8HY",
    "sg:province":"North Yorkshire",
    "sg:tags":[
        "others"
    ],
    "wof:name":"J Gooch",
    "wof:placetype":"venue"
},
  "geometry": {"coordinates":[-2.014676,53.918289],"type":"Point"}
}