{
  "type": "Feature",
  "properties": {
    "addr:full":"2 Ilkley Rd, Riddlesden Keighley North Yorkshire BD20 5PS",
    "addr:housenumber":"2",
    "addr:postcode":"bd20 5ps",
    "addr:street":"Ilkley Rd",
    "iso:country":"GB",
    "sg:address":"2 Ilkley Rd, Riddlesden",
    "sg:city":"Keighley",
    "sg:classifiers":[
        {
            "category":"Building & Trades",
            "subcategory":"Construction",
            "type":"Services"
        }
    ],
    "sg:phone":"+44 1535 212482",
    "sg:postcode":"BD20 5PS",
    "sg:province":"North Yorkshire",
    "sg:tags":[
        "roofing"
    ],
    "wof:name":"Copper Ridge",
    "wof:placetype":"venue"
},
  "geometry": {"coordinates":[-1.8839520216,53.8808708191],"type":"Point"}
}