{
  "type": "Feature",
  "properties": {
    "addr:full":"78 Parkstone Avenue Hornchurch Essex RM11 3LS",
    "addr:housenumber":"78",
    "addr:postcode":"rm11 3ls",
    "addr:street":"Parkstone Avenue",
    "iso:country":"GB",
    "sg:address":"78 Parkstone Avenue",
    "sg:city":"Hornchurch",
    "sg:classifiers":[
        {
            "category":"Retail",
            "subcategory":"Driving School",
            "type":"Services"
        }
    ],
    "sg:phone":"+44 1708 443631",
    "sg:postcode":"RM11 3LS",
    "sg:province":"Essex",
    "wof:name":"Wisdom School of Motoring",
    "wof:placetype":"venue"
},
  "geometry": {"coordinates":[0.232567,51.570087],"type":"Point"}
}