{
  "type": "Feature",
  "properties": {
    "addr:full":"Po Box 213 Torquay Devon TQ1 2ZG",
    "addr:housenumber":"po",
    "addr:postcode":"tq1 2zg",
    "addr:street":"Box 213",
    "iso:country":"GB",
    "sg:address":"Po Box 213",
    "sg:city":"Torquay",
    "sg:classifiers":[
        {
            "category":"Food & Beverages",
            "subcategory":"Specialty",
            "type":"Retail Goods"
        }
    ],
    "sg:phone":"+44 1803 212965",
    "sg:postcode":"TQ1 2ZG",
    "sg:province":"Devon",
    "sg:tags":[
        "product",
        "health"
    ],
    "wof:name":"Summerbee Products",
    "wof:placetype":"venue"
},
  "geometry": {"coordinates":[-3.5195200443,50.4598884583],"type":"Point"}
}