{
  "type": "Feature",
  "properties": {
    "addr:full":"Curate, 30 Carisbrooke Rd Leigh Lancashire WN7 2XA",
    "addr:housenumber":"30",
    "addr:postcode":"wn7 2xa",
    "addr:street":"Curate;Carisbrooke Rd",
    "iso:country":"GB",
    "sg:address":"Curate, 30 Carisbrooke Rd",
    "sg:city":"Leigh",
    "sg:classifiers":[
        {
            "category":"Place Of Worship",
            "type":"Public Place"
        }
    ],
    "sg:phone":"+44 1942 607893",
    "sg:postcode":"WN7 2XA",
    "sg:province":"Lancashire",
    "wof:name":"St Thomas C of E Church",
    "wof:placetype":"venue"
},
  "geometry": {"coordinates":[-2.5189940929,53.4969711304],"type":"Point"}
}