{
  "type": "Feature",
  "properties": {
    "addr:full":"25 Westfield Terrace Aberdeen Aberdeen City AB25 2RU",
    "addr:housenumber":"25",
    "addr:postcode":"ab25 2ru",
    "addr:street":"Westfield Terrace",
    "iso:country":"GB",
    "sg:address":"25 Westfield Terrace",
    "sg:city":"Aberdeen",
    "sg:classifiers":[
        {
            "category":"Organizations",
            "subcategory":"Non-profit Organization",
            "type":"Services"
        }
    ],
    "sg:phone":"+44 1224 640269",
    "sg:postcode":"AB25 2RU",
    "sg:province":"Aberdeen City",
    "sg:tags":[
        "organisation",
        "voluntary",
        "charity"
    ],
    "wof:name":"The Cornerstone Community Ltd.",
    "wof:placetype":"venue"
},
  "geometry": {"coordinates":[-2.121481,57.146626],"type":"Point"}
}