{
  "type": "Feature",
  "properties": {
    "addr:full":"Brinklow Road, Binley Coventry Warwickshire CV3 2HY",
    "addr:postcode":"cv3 2hy",
    "addr:street":"Brinklow Road",
    "iso:country":"GB",
    "sg:address":"Brinklow Road, Binley",
    "sg:city":"Coventry",
    "sg:classifiers":[
        {
            "category":"Transit Center",
            "subcategory":"Freight",
            "type":"Transportation"
        },
        {
            "category":"Manufacturing",
            "subcategory":"Musical Instruments",
            "type":"Manufacturing & Wholesale Goods"
        }
    ],
    "sg:phone":"+44 24 7645 0455",
    "sg:postcode":"CV3 2HY",
    "sg:province":"Warwickshire",
    "sg:tags":[
        "piano",
        "accessory"
    ],
    "wof:name":"Coombe Pianos",
    "wof:placetype":"venue"
},
  "geometry": {"coordinates":[-1.4388940334,52.4048194885],"type":"Point"}
}