{
  "type": "Feature",
  "properties": {
    "addr:full":"Willow Lane Huddersfield West Yorkshire HD1 5ED",
    "addr:postcode":"hd1 5ed",
    "addr:street":"Willow Lane",
    "iso:country":"GB",
    "sg:address":"Willow Lane",
    "sg:city":"Huddersfield",
    "sg:classifiers":[
        {
            "category":"Manufacturing",
            "subcategory":"Food",
            "type":"Manufacturing & Wholesale Goods"
        }
    ],
    "sg:phone":"+44 1484 427427",
    "sg:postcode":"HD1 5ED",
    "sg:province":"West Yorkshire",
    "sg:tags":[
        "mnfr",
        "drink",
        "soft"
    ],
    "wof:name":"Benjamin Shaw & Sons Ltd.",
    "wof:placetype":"venue"
},
  "geometry": {"coordinates":[-1.786402,53.656651],"type":"Point"}
}