{
  "type": "Feature",
  "properties": {
    "iso:country":"GB",
    "sg:address":"22 Ellacombe Road, Longwell Grn",
    "sg:city":"Bristol",
    "sg:classifiers":[
        {
            "category":"Fast Food",
            "type":"Food & Drink"
        }
    ],
    "sg:phone":"+44 117 932 9900",
    "sg:postcode":"BS30 9BA",
    "sg:province":"Gloucestershire",
    "sg:tags":[
        "away",
        "take"
    ],
    "wof:name":"Orient Express Chinese Takeaway",
    "wof:placetype":"venue"
},
  "geometry": {"coordinates":[-2.494509,51.43671],"type":"Point"}
}