{
  "type": "Feature",
  "properties": {
    "iso:country":"GB",
    "sg:address":"St Edmunds Centre, Tamarisk Way",
    "sg:city":"Colchester",
    "sg:classifiers":[
        {
            "category":"Government",
            "subcategory":"Office",
            "type":"Public Place"
        }
    ],
    "sg:phone":"+44 1206 871186",
    "sg:postcode":"CO4 3GW",
    "sg:province":"Essex",
    "sg:tags":[
        "local"
    ],
    "wof:name":"Colchester North and South Team",
    "wof:placetype":"venue"
},
  "geometry": {"coordinates":[0.922595,51.892872],"type":"Point"}
}