{
  "type": "Feature",
  "properties": {
    "iso:country":"GB",
    "sg:address":"Ennerdale Rd",
    "sg:city":"Maryport",
    "sg:classifiers":[
        {
            "category":"Organizations",
            "subcategory":"Membership Organization",
            "type":"Services"
        }
    ],
    "sg:phone":"+44 1900 813390",
    "sg:postcode":"CA15 8HN",
    "sg:province":"Cumbria",
    "sg:tags":[
        "club"
    ],
    "wof:name":"Clubs For Young People",
    "wof:placetype":"venue"
},
  "geometry": {"coordinates":[-3.4903740883,54.7074394226],"type":"Point"}
}