{
  "type": "Feature",
  "properties": {
    "iso:country":"GB",
    "sg:address":"3 Grasmere Close",
    "sg:city":"Gainsborough",
    "sg:classifiers":[
        {
            "category":"Retail",
            "subcategory":"Driving School",
            "type":"Services"
        }
    ],
    "sg:postcode":"DN21 1YA",
    "sg:province":"Lincolnshire",
    "wof:name":"Roland Sadler",
    "wof:placetype":"venue"
},
  "geometry": {"coordinates":[-0.7616659999,53.4073219299],"type":"Point"}
}