{
  "type": "Feature",
  "properties": {
    "iso:country":"GB",
    "sg:address":"17 Silbury Cl",
    "sg:city":"Westbury",
    "sg:classifiers":[
        {
            "category":"Building & Trades",
            "subcategory":"Construction",
            "type":"Services"
        }
    ],
    "sg:phone":"+44 1373 826160",
    "sg:postcode":"BA13 3TD",
    "sg:province":"Wiltshire",
    "sg:tags":[
        "builder"
    ],
    "wof:name":"Mike Millard",
    "wof:placetype":"venue"
},
  "geometry": {"coordinates":[-2.1895530224,51.2654533386],"type":"Point"}
}