{
  "type": "Feature",
  "properties": {
    "addr:full":"192-196 High Road, Willesden Grn London Greater London NW10 2PB",
    "addr:housenumber":"192-196",
    "addr:postcode":"nw10 2pb",
    "addr:street":"High Road Willesden Grn",
    "iso:country":"GB",
    "sg:address":"192-196 High Road, Willesden Grn",
    "sg:city":"London",
    "sg:classifiers":[
        {
            "category":"Organizations",
            "subcategory":"Community Association",
            "type":"Services"
        }
    ],
    "sg:phone":"+44 20 8537 4200",
    "sg:postcode":"NW10 2PB",
    "sg:province":"Greater London",
    "sg:tags":[
        "society",
        "housing"
    ],
    "wof:name":"Paddington Churches Housing Association Ltd.",
    "wof:placetype":"venue"
},
  "geometry": {"coordinates":[-0.234585,51.54731],"type":"Point"}
}