{
  "type": "Feature",
  "properties": {
    "addr:full":"Auction Ho, Essex Rd Hoddesdon Essex EN11 0DP",
    "addr:postcode":"en11 0dp",
    "addr:street":"Essex Rd",
    "iso:country":"GB",
    "sg:address":"Auction Ho, Essex Rd",
    "sg:city":"Hoddesdon",
    "sg:classifiers":[
        {
            "category":"Manufacturing",
            "subcategory":"Tools & Machinery",
            "type":"Manufacturing & Wholesale Goods"
        }
    ],
    "sg:phone":"+44 1992 445806",
    "sg:postcode":"EN11 0DP",
    "sg:province":"Essex",
    "wof:name":"Aznew Machine Tools",
    "wof:placetype":"venue"
},
  "geometry": {"coordinates":[-0.0132550001,51.7678413391],"type":"Point"}
}