{
  "type": "Feature",
  "properties": {
    "iso:country":"GB",
    "sg:address":"Burlington House, Burlington Arcade",
    "sg:city":"Barnsley",
    "sg:classifiers":[
        {
            "category":"Professional",
            "subcategory":"Management & Consulting",
            "type":"Services"
        }
    ],
    "sg:postcode":"S70 1SZ",
    "sg:province":"South Yorkshire",
    "sg:tags":[
        "consultant",
        "specialist"
    ],
    "wof:name":"K G's Beauty Salon",
    "wof:placetype":"venue"
},
  "geometry": {"coordinates":[-1.4799389839,53.5528106689],"type":"Point"}
}