{
  "type": "Feature",
  "properties": {
    "addr:full":"Unit 8 & 11 Seaford East Sussex BN25 3JE",
    "addr:housenumber":"unit 8 & 11",
    "addr:postcode":"bn25 3je",
    "iso:country":"GB",
    "sg:address":"Unit 8 & 11",
    "sg:city":"Seaford",
    "sg:classifiers":[
        {
            "category":"Manufacturing",
            "subcategory":"Lumber",
            "type":"Manufacturing & Wholesale Goods"
        },
        {
            "category":"Manufacturing",
            "subcategory":"Building Materials",
            "type":"Manufacturing & Wholesale Goods"
        }
    ],
    "sg:phone":"+44 1323 894280",
    "sg:postcode":"BN25 3JE",
    "sg:province":"East Sussex",
    "sg:tags":[
        "merchants",
        "agent",
        "importer",
        "tile",
        "mnfrs",
        "timber"
    ],
    "wof:name":"Everett Tiles Ltd.",
    "wof:placetype":"venue"
},
  "geometry": {"coordinates":[0.1203199998,50.7823295593],"type":"Point"}
}