{
  "type": "Feature",
  "properties": {
    "iso:country":"GB",
    "sg:address":"70 London Road, Newington",
    "sg:city":"Sittingbourne",
    "sg:classifiers":[
        {
            "category":"Home & Garden",
            "subcategory":"Household Appliances",
            "type":"Retail Goods"
        }
    ],
    "sg:phone":"+44 1795 844377",
    "sg:postcode":"ME9 7NR",
    "sg:province":"Kent",
    "sg:tags":[
        "equipment",
        "air conditioning"
    ],
    "wof:name":"The Air Conditioning Co",
    "wof:placetype":"venue"
},
  "geometry": {"coordinates":[0.6544100046,51.3544387817],"type":"Point"}
}