{
  "type": "Feature",
  "properties": {
    "iso:country":"GB",
    "sg:address":"10 Scarth Walk",
    "sg:city":"Stockton On Tees",
    "sg:classifiers":[
        {
            "category":"Organizations",
            "subcategory":"Community Association",
            "type":"Services"
        }
    ],
    "sg:phone":"+44 1274 682215",
    "sg:postcode":"TS18 1PF",
    "sg:province":"Durham",
    "sg:tags":[
        "society",
        "housing"
    ],
    "wof:name":"Habinteg Housing Association (Ulster) Ltd",
    "wof:placetype":"venue"
},
  "geometry": {"coordinates":[-1.319752,54.564655],"type":"Point"}
}