{
  "type": "Feature",
  "properties": {
    "iso:country":"GB",
    "sg:address":"12 Graham Avenue, Withdean",
    "sg:city":"Brighton",
    "sg:classifiers":[
        {
            "category":"Building & Trades",
            "subcategory":"Construction",
            "type":"Services"
        }
    ],
    "sg:postcode":"BN1 8HA",
    "sg:province":"East Sussex",
    "sg:tags":[
        "excavation",
        "groundwork",
        "contractor"
    ],
    "wof:name":"Roland Hall",
    "wof:placetype":"venue"
},
  "geometry": {"coordinates":[-0.14823,50.856373],"type":"Point"}
}