{
  "type": "Feature",
  "properties": {
    "addr:full":"Madeira Parade, Madeira Avenue Bognor Regis West Sussex PO22 8DX",
    "addr:postcode":"po22 8dx",
    "addr:street":"Madeira Parade Madeira Avenue",
    "iso:country":"GB",
    "sg:address":"Madeira Parade, Madeira Avenue",
    "sg:city":"Bognor Regis",
    "sg:classifiers":[
        {
            "category":"Home & Garden",
            "subcategory":"Home Furnishings",
            "type":"Retail Goods"
        }
    ],
    "sg:phone":"+44 1243 826441",
    "sg:postcode":"PO22 8DX",
    "sg:province":"West Sussex",
    "sg:tags":[
        "awning",
        "canopy",
        "blinds"
    ],
    "wof:name":"Sun-X (U K) Ltd.",
    "wof:placetype":"venue"
},
  "geometry": {"coordinates":[-0.6666989923,50.7935333252],"type":"Point"}
}