{
  "type": "Feature",
  "properties": {
    "addr:full":"5 Bigstone Close, Tutshill Chepstow Gloucestershire NP16 7EP",
    "addr:housenumber":"5",
    "addr:postcode":"np16 7ep",
    "addr:street":"Bigstone Close",
    "iso:country":"GB",
    "sg:address":"5 Bigstone Close, Tutshill",
    "sg:city":"Chepstow",
    "sg:classifiers":[
        {
            "category":"Personal",
            "subcategory":"Beauty Salon",
            "type":"Services"
        }
    ],
    "sg:postcode":"NP16 7EP",
    "sg:province":"Gloucestershire",
    "sg:tags":[
        "unisex",
        "hairdresser"
    ],
    "wof:name":"Sarah's",
    "wof:placetype":"venue"
},
  "geometry": {"coordinates":[-2.664984,51.648376],"type":"Point"}
}