{
  "type": "Feature",
  "properties": {
    "addr:full":"The Old Customs House, Torwood Gardens Road Torquay Devon TQ1 1EG",
    "addr:postcode":"tq1 1eg",
    "addr:street":"Torwood Gardens Road",
    "iso:country":"GB",
    "sg:address":"The Old Customs House, Torwood Gardens Road",
    "sg:city":"Torquay",
    "sg:classifiers":[
        {
            "category":"Professional",
            "subcategory":"Accounting & Tax Preparation",
            "type":"Services"
        }
    ],
    "sg:phone":"+44 1803 292692",
    "sg:postcode":"TQ1 1EG",
    "sg:province":"Devon",
    "sg:tags":[
        "accountant",
        "activity"
    ],
    "wof:name":"Spence Robert Pethick & Co",
    "wof:placetype":"venue"
},
  "geometry": {"coordinates":[-3.518571,50.461533],"type":"Point"}
}