{
  "type": "Feature",
  "properties": {
    "iso:country":"GB",
    "sg:address":"Spring Vale, Middleton",
    "sg:city":"Manchester",
    "sg:classifiers":[
        {
            "category":"Manufacturing",
            "subcategory":"Metals",
            "type":"Manufacturing & Wholesale Goods"
        },
        {
            "category":"Wholesale",
            "subcategory":"Metals & Minerals",
            "type":"Manufacturing & Wholesale Goods"
        }
    ],
    "sg:phone":"+44 161 643 2462",
    "sg:postcode":"M24 2HS",
    "sg:province":"Greater Manchester",
    "sg:tags":[
        "fabricator",
        "work",
        "sheet"
    ],
    "wof:name":"Middleton Sheet Metal Co Ltd",
    "wof:placetype":"venue"
},
  "geometry": {"coordinates":[-2.191324,53.5494],"type":"Point"}
}