{
  "type": "Feature",
  "properties": {
    "iso:country":"GB",
    "sg:address":"78 Shields Road",
    "sg:city":"Newcastle-upon-tyne",
    "sg:classifiers":[
        {
            "category":"Shopping",
            "subcategory":"Music",
            "type":"Retail Goods"
        }
    ],
    "sg:postcode":"NE6 1DS",
    "sg:province":"Tyne and Wear",
    "sg:tags":[
        "record",
        "tape",
        "cd"
    ],
    "wof:name":"Double 'R' Records",
    "wof:placetype":"venue"
},
  "geometry": {"coordinates":[-1.583354,54.976681],"type":"Point"}
}