{
  "type": "Feature",
  "properties": {
    "addr:full":"Craven Drive, Churchdown Gloucester Gloucestershire GL3 2DR",
    "addr:postcode":"gl3 2dr",
    "addr:street":"Craven Drive",
    "iso:country":"GB",
    "sg:address":"Craven Drive, Churchdown",
    "sg:city":"Gloucester",
    "sg:classifiers":[
        {
            "category":"Education",
            "subcategory":"School",
            "type":"Public Place"
        }
    ],
    "sg:phone":"+44 1452 713262",
    "sg:postcode":"GL3 2DR",
    "sg:province":"Gloucestershire",
    "sg:tags":[
        "local",
        "authority"
    ],
    "wof:name":"Parton Manor Junior School",
    "wof:placetype":"venue"
},
  "geometry": {"coordinates":[-2.1724889278,51.8763923645],"type":"Point"}
}