{
  "type": "Feature",
  "properties": {
    "iso:country":"GB",
    "sg:address":"62 Fairfield Road, Edmonton",
    "sg:city":"London",
    "sg:classifiers":[
        {
            "category":"Building & Trades",
            "subcategory":"Construction",
            "type":"Services"
        }
    ],
    "sg:phone":"+44 20 8345 7426",
    "sg:postcode":"N18 2QJ",
    "sg:province":"Greater London",
    "sg:tags":[
        "decorator",
        "painter"
    ],
    "wof:name":"Carl Manders",
    "wof:placetype":"venue"
},
  "geometry": {"coordinates":[-0.060585,51.615025],"type":"Point"}
}