{
  "type": "Feature",
  "properties": {
    "addr:full":"51-55 Market Place, Market Weighton York East Riding of Yorkshire YO43 3AJ",
    "addr:housenumber":"51-55",
    "addr:postcode":"yo43 3aj",
    "addr:street":"Market Place",
    "iso:country":"GB",
    "sg:address":"51-55 Market Place, Market Weighton",
    "sg:city":"York",
    "sg:classifiers":[
        {
            "category":"Shopping",
            "subcategory":"Comic Books",
            "type":"Retail Goods"
        }
    ],
    "sg:phone":"+44 1430 872391",
    "sg:postcode":"YO43 3AJ",
    "sg:province":"East Riding of Yorkshire",
    "sg:tags":[
        "jeweller"
    ],
    "wof:name":"C P Dyson",
    "wof:placetype":"venue"
},
  "geometry": {"coordinates":[-0.667872,53.865025],"type":"Point"}
}