{
  "type": "Feature",
  "properties": {
    "addr:full":"1 High Street, West End Southampton Hampshire SO30 3AA",
    "addr:housenumber":"1",
    "addr:postcode":"so30 3aa",
    "addr:street":"High Street",
    "iso:country":"GB",
    "sg:address":"1 High Street, West End",
    "sg:city":"Southampton",
    "sg:classifiers":[
        {
            "category":"Bars & Pubs",
            "type":"Food & Drink"
        }
    ],
    "sg:phone":"+44 23 8047 2171",
    "sg:postcode":"SO30 3AA",
    "sg:province":"Hampshire",
    "sg:tags":[
        "pubs",
        "inn"
    ],
    "wof:name":"Lamp & Mantle",
    "wof:placetype":"venue"
},
  "geometry": {"coordinates":[-1.34146,50.92886],"type":"Point"}
}