{
  "type": "Feature",
  "properties": {
    "iso:country":"GB",
    "sg:address":"Abbey Close",
    "sg:city":"Abingdon",
    "sg:classifiers":[
        {
            "category":"Sports & Exercise",
            "subcategory":"Swimming Pool",
            "type":"Entertainment"
        }
    ],
    "sg:phone":"+44 1235 523113",
    "sg:postcode":"OX14 3JD",
    "sg:province":"Oxfordshire",
    "wof:name":"Abbey Meadow Open Air Swimming Pool",
    "wof:placetype":"venue"
},
  "geometry": {"coordinates":[-1.280449,51.670666],"type":"Point"}
}