{
  "type": "Feature",
  "properties": {
    "iso:country":"GB",
    "sg:address":"Manners Indstl Est, The Old Powerhouse",
    "sg:city":"Ilkeston",
    "sg:classifiers":[
        {
            "category":"Building & Trades",
            "subcategory":"Construction",
            "type":"Services"
        }
    ],
    "sg:postcode":"DE7 8EF",
    "sg:province":"Derbyshire",
    "sg:tags":[
        "platform",
        "work",
        "scaffolding"
    ],
    "wof:name":"Brookes,Michael,",
    "wof:placetype":"venue"
},
  "geometry": {"coordinates":[-1.310189,52.978611],"type":"Point"}
}