{
  "type": "Feature",
  "properties": {
    "addr:full":"Unit 17, Red Lion Business Park Surbiton Surrey KT6 7QD",
    "addr:housenumber":"unit 17",
    "addr:postcode":"kt6 7qd",
    "addr:street":"Red;Business Park",
    "iso:country":"GB",
    "sg:address":"Unit 17, Red Lion Business Park",
    "sg:city":"Surbiton",
    "sg:classifiers":[
        {
            "category":"Building & Trades",
            "subcategory":"Construction",
            "type":"Services"
        }
    ],
    "sg:phone":"+44 20 8974 2460",
    "sg:postcode":"KT6 7QD",
    "sg:province":"Surrey",
    "sg:tags":[
        "decorator",
        "painter"
    ],
    "wof:name":"E Poole & Co",
    "wof:placetype":"venue"
},
  "geometry": {"coordinates":[-0.289474,51.382629],"type":"Point"}
}