{
  "type": "Feature",
  "properties": {
    "addr:full":"28-32 Shelton Street, Covent Garden London Greater London WC2H 9HP",
    "addr:housenumber":"28-32",
    "addr:postcode":"wc2h 9hp",
    "addr:street":"Shelton Street",
    "iso:country":"GB",
    "sg:address":"28-32 Shelton Street, Covent Garden",
    "sg:city":"London",
    "sg:classifiers":[
        {
            "category":"Communications",
            "subcategory":"Film & Video Production",
            "type":"Services"
        }
    ],
    "sg:phone":"+44 20 7593 0505",
    "sg:postcode":"WC2H 9HP",
    "sg:province":"Greater London",
    "sg:tags":[
        "illustrator",
        "artist"
    ],
    "wof:name":"New Division",
    "wof:placetype":"venue"
},
  "geometry": {"coordinates":[-0.1253370047,51.5135803223],"type":"Point"}
}