{
  "type": "Feature",
  "properties": {
    "iso:country":"GB",
    "sg:address":"Canterbury Road, Lyminge",
    "sg:city":"Folkestone",
    "sg:classifiers":[
        {
            "category":"Shopping",
            "subcategory":"News",
            "type":"Retail Goods"
        }
    ],
    "sg:phone":"+44 1303 862566",
    "sg:postcode":"CT18 8HU",
    "sg:province":"Kent",
    "sg:tags":[
        "newsagent"
    ],
    "wof:name":"Lyminge Newsagency",
    "wof:placetype":"venue"
},
  "geometry": {"coordinates":[1.094515,51.113354],"type":"Point"}
}