{
  "type": "Feature",
  "properties": {
    "addr:full":"16 Bath Crescent Cheadle Cheshire SK8 7QU",
    "addr:housenumber":"16",
    "addr:postcode":"sk8 7qu",
    "addr:street":"Bath Crescent Cheadle",
    "iso:country":"GB",
    "sg:address":"16 Bath Crescent",
    "sg:city":"Cheadle",
    "sg:classifiers":[
        {
            "category":"Manufacturing",
            "subcategory":"Petroleum Products",
            "type":"Manufacturing & Wholesale Goods"
        }
    ],
    "sg:postcode":"SK8 7QU",
    "sg:province":"Cheshire",
    "sg:tags":[
        "double",
        "glazing"
    ],
    "wof:name":"L & P Windows of Cheadle",
    "wof:placetype":"venue"
},
  "geometry": {"coordinates":[-2.187993,53.359768],"type":"Point"}
}