{
  "type": "Feature",
  "properties": {
    "iso:country":"GB",
    "sg:address":"3 Grimshaw Street",
    "sg:city":"Burnley",
    "sg:classifiers":[
        {
            "category":"Professional",
            "subcategory":"Lawyer & Legal Services",
            "type":"Services"
        }
    ],
    "sg:phone":"+44 1282 426441",
    "sg:postcode":"BB11 2AS",
    "sg:province":"Lancashire",
    "sg:tags":[
        "solicitor"
    ],
    "wof:name":"Currie & Sons",
    "wof:placetype":"venue"
},
  "geometry": {"coordinates":[-2.2433578968,53.7880134583],"type":"Point"}
}