{
  "type": "Feature",
  "properties": {
    "iso:country":"GB",
    "sg:address":"Park Road Garage, Park Road",
    "sg:city":"Ebbw Vale",
    "sg:classifiers":[
        {
            "category":"Retail",
            "subcategory":"Auto Repair",
            "type":"Services"
        }
    ],
    "sg:phone":"+44 1495 305879",
    "sg:postcode":"NP23 6UP",
    "sg:province":"Blaenau Gwent",
    "sg:tags":[
        "modification",
        "garage"
    ],
    "wof:name":"Pee Dees",
    "wof:placetype":"venue"
},
  "geometry": {"coordinates":[-3.2040290833,51.7627830505],"type":"Point"}
}