{
  "type": "Feature",
  "properties": {
    "addr:full":"Mount Road, Burntwood Walsall Staffordshire WS3 4PG",
    "addr:postcode":"ws3 4pg",
    "addr:street":"Mount Road",
    "iso:country":"GB",
    "sg:address":"Mount Road, Burntwood",
    "sg:city":"Walsall",
    "sg:classifiers":[
        {
            "category":"Manufacturing",
            "subcategory":"Metals",
            "type":"Manufacturing & Wholesale Goods"
        }
    ],
    "sg:phone":"+44 1543 674600",
    "sg:postcode":"WS3 4PG",
    "sg:province":"Staffordshire",
    "sg:tags":[
        "steel",
        "fabricator",
        "erectors"
    ],
    "wof:name":"Giltbuild Ltd.",
    "wof:placetype":"venue"
},
  "geometry": {"coordinates":[-1.970273,52.632477],"type":"Point"}
}