{
  "type": "Feature",
  "properties": {
    "addr:full":"8 Parliament Row, Hanley Stoke-on-trent Staffordshire ST1 1QD",
    "addr:housenumber":"8",
    "addr:postcode":"staffordshire st1 1qd",
    "addr:street":"Parliament Row",
    "iso:country":"GB",
    "sg:address":"8 Parliament Row, Hanley",
    "sg:city":"Stoke-on-trent",
    "sg:classifiers":[
        {
            "category":"Shopping",
            "subcategory":"Gifts & Souvenirs",
            "type":"Retail Goods"
        }
    ],
    "sg:phone":"+44 1782 274148",
    "sg:postcode":"ST1 1QD",
    "sg:province":"Staffordshire",
    "sg:tags":[
        "poster",
        "card"
    ],
    "wof:name":"Birthdays",
    "wof:placetype":"venue"
},
  "geometry": {"coordinates":[-2.173871994,53.0252609253],"type":"Point"}
}