{
  "type": "Feature",
  "properties": {
    "iso:country":"GB",
    "sg:address":"Lealand Way, Riverside Industrial Estate, Marsh Lane",
    "sg:city":"Boston",
    "sg:classifiers":[
        {
            "category":"Education",
            "subcategory":"Special Training",
            "type":"Public Place"
        },
        {
            "category":"Government",
            "subcategory":"Office",
            "type":"Public Place"
        }
    ],
    "sg:phone":"+44 1205 357698",
    "sg:postcode":"PE21 7SW",
    "sg:province":"Lincolnshire",
    "sg:tags":[
        "product",
        "local",
        "centre"
    ],
    "wof:name":"B O S S C A T",
    "wof:placetype":"venue"
},
  "geometry": {"coordinates":[-0.011703,52.965557],"type":"Point"}
}