{
  "type": "Feature",
  "properties": {
    "addr:full":"14 & 15 Regent Parade, High Harrogate Harrogate North Yorkshire HG1 5AR",
    "addr:housenumber":"14 & 15",
    "addr:postcode":"hg1 5ar",
    "addr:street":"Regent Parade High Harrogate",
    "iso:country":"GB",
    "sg:address":"14 & 15 Regent Parade, High Harrogate",
    "sg:city":"Harrogate",
    "sg:classifiers":[
        {
            "category":"Wholesale",
            "subcategory":"Books, Periodicals, & Newspapers",
            "type":"Manufacturing & Wholesale Goods"
        }
    ],
    "sg:phone":"+44 1423 566755",
    "sg:postcode":"HG1 5AR",
    "sg:province":"North Yorkshire",
    "sg:tags":[
        "maps",
        "globe",
        "chart",
        "pub"
    ],
    "wof:name":"Geoplan (U K) Ltd.",
    "wof:placetype":"venue"
},
  "geometry": {"coordinates":[-1.528939,53.996998],"type":"Point"}
}