{
  "type": "Feature",
  "properties": {
    "addr:full":"Wellington Road, Bollington Macclesfield Cheshire SK10 5JR",
    "addr:postcode":"sk10 5jr",
    "addr:street":"Wellington Road",
    "iso:country":"GB",
    "sg:address":"Wellington Road, Bollington",
    "sg:city":"Macclesfield",
    "sg:classifiers":[
        {
            "category":"Education",
            "subcategory":"Preschool",
            "type":"Public Place"
        }
    ],
    "sg:phone":"+44 1625 573938",
    "sg:postcode":"SK10 5JR",
    "sg:province":"Cheshire",
    "sg:tags":[
        "pre-school",
        "playgroups"
    ],
    "wof:name":"Bollington Methodist Playgroup",
    "wof:placetype":"venue"
},
  "geometry": {"coordinates":[-2.1103689671,53.2933883667],"type":"Point"}
}