{
  "type": "Feature",
  "properties": {
    "addr:full":"56 Coxley Crescent, Netherton Wakefield West Yorkshire WF4 4NH",
    "addr:housenumber":"56",
    "addr:postcode":"wf4 4nh",
    "addr:street":"Coxley Crescent;West",
    "iso:country":"GB",
    "sg:address":"56 Coxley Crescent, Netherton",
    "sg:city":"Wakefield",
    "sg:classifiers":[
        {
            "category":"Building & Trades",
            "subcategory":"Construction",
            "type":"Services"
        }
    ],
    "sg:phone":"+44 1924 262559",
    "sg:postcode":"WF4 4NH",
    "sg:province":"West Yorkshire",
    "sg:tags":[
        "glazier"
    ],
    "wof:name":"Martin Barlow",
    "wof:placetype":"venue"
},
  "geometry": {"coordinates":[-1.580146,53.645164],"type":"Point"}
}