{
  "type": "Feature",
  "properties": {
    "addr:full":"Woodbine Hill Blackwood Caerphilly NP12 1QF",
    "addr:postcode":"np12 1qf",
    "addr:street":"Woodbine Hill",
    "iso:country":"GB",
    "sg:address":"Woodbine Hill",
    "sg:city":"Blackwood",
    "sg:classifiers":[
        {
            "category":"Professional",
            "subcategory":"Employment Agencies",
            "type":"Services"
        }
    ],
    "sg:phone":"+44 1495 224874",
    "sg:postcode":"NP12 1QF",
    "sg:province":"Caerphilly",
    "sg:tags":[
        "career",
        "guidance"
    ],
    "wof:name":"Gwent Careers Service Partnership Ltd.",
    "wof:placetype":"venue"
},
  "geometry": {"coordinates":[-3.1956140995,51.6672744751],"type":"Point"}
}