{
  "type": "Feature",
  "properties": {
    "iso:country":"GB",
    "sg:address":"56 Seymour St",
    "sg:city":"Cardiff",
    "sg:classifiers":[
        {
            "category":"Building & Trades",
            "subcategory":"Plumbing",
            "type":"Services"
        }
    ],
    "sg:phone":"+44 29 2048 2973",
    "sg:postcode":"CF2 2NS",
    "sg:province":"Cardiff",
    "sg:tags":[
        "heating"
    ],
    "wof:name":"Plumbob",
    "wof:placetype":"venue"
},
  "geometry": {"coordinates":[-3.147943,51.484562],"type":"Point"}
}