{
  "type": "Feature",
  "properties": {
    "iso:country":"GB",
    "sg:address":"Unit 19-21 Manor Side Industrial Estate, Walkers Road, North Moons Moat",
    "sg:city":"Redditch",
    "sg:classifiers":[
        {
            "category":"Manufacturing",
            "subcategory":"Tools & Machinery",
            "type":"Manufacturing & Wholesale Goods"
        }
    ],
    "sg:phone":"+44 1527 60281",
    "sg:postcode":"B98 9HE",
    "sg:province":"Warwickshire",
    "wof:name":"G B Walter Ltd.",
    "wof:placetype":"venue"
},
  "geometry": {"coordinates":[-1.89596,52.315632],"type":"Point"}
}