{
  "type": "Feature",
  "properties": {
    "addr:full":"Middleton Hall Cotts, Middleton Sudbury Essex CO10 7LL",
    "addr:housenumber":"cotts",
    "addr:postcode":"co10 7ll",
    "addr:street":"Middleton;Middleton Sudbury",
    "iso:country":"GB",
    "sg:address":"Middleton Hall Cotts, Middleton",
    "sg:city":"Sudbury",
    "sg:classifiers":[
        {
            "category":"Farming",
            "subcategory":"Poultry Farm",
            "type":"Manufacturing & Wholesale Goods"
        }
    ],
    "sg:phone":"+44 1787 371214",
    "sg:postcode":"CO10 7LL",
    "sg:province":"Essex",
    "sg:tags":[
        "wholesaler"
    ],
    "wof:name":"Wishbone Turkeys Ltd",
    "wof:placetype":"venue"
},
  "geometry": {"coordinates":[0.7272589803,52.0228691101],"type":"Point"}
}