{
  "type": "Feature",
  "properties": {
    "iso:country":"GB",
    "sg:address":"Unit 4 125 High St",
    "sg:city":"Canvey Island",
    "sg:classifiers":[
        {
            "category":"Retail",
            "subcategory":"Car Wash",
            "type":"Services"
        }
    ],
    "sg:phone":"+44 1268 515677",
    "sg:postcode":"SS8 7RF",
    "sg:province":"Essex",
    "sg:tags":[
        "polishing",
        "washing"
    ],
    "wof:name":"Car Wash (Canvey)",
    "wof:placetype":"venue"
},
  "geometry": {"coordinates":[0.599698,51.522671],"type":"Point"}
}