{
  "type": "Feature",
  "properties": {
    "addr:full":"4 Beer Road Seaton Devon EX12 2PA",
    "addr:housenumber":"4",
    "addr:postcode":"ex12 2pa",
    "addr:street":"Beer Road",
    "iso:country":"GB",
    "sg:address":"4 Beer Road",
    "sg:city":"Seaton",
    "sg:classifiers":[
        {
            "category":"Shopping",
            "subcategory":"Clothing, Apparel, & Fashions",
            "type":"Retail Goods"
        }
    ],
    "sg:phone":"+44 1297 24420",
    "sg:postcode":"EX12 2PA",
    "sg:province":"Devon",
    "sg:tags":[
        "shop"
    ],
    "wof:name":"Buffys",
    "wof:placetype":"venue"
},
  "geometry": {"coordinates":[-3.072124,50.705341],"type":"Point"}
}