{
  "type": "Feature",
  "properties": {
    "addr:full":"46 London Road Bognor Regis West Sussex PO21 1PY",
    "addr:housenumber":"46",
    "addr:postcode":"po21 1py",
    "addr:street":"London Road",
    "iso:country":"GB",
    "sg:address":"46 London Road",
    "sg:city":"Bognor Regis",
    "sg:classifiers":[
        {
            "category":"Professional",
            "type":"Services"
        },
        {
            "category":"Cafe",
            "type":"Food & Drink"
        }
    ],
    "sg:phone":"+44 1243 863753",
    "sg:postcode":"PO21 1PY",
    "sg:province":"West Sussex",
    "sg:tags":[
        "tea",
        "room",
        "caterer"
    ],
    "wof:name":"S Macari & Sons Ltd.",
    "wof:placetype":"venue"
},
  "geometry": {"coordinates":[-0.6745340228,50.7849807739],"type":"Point"}
}