{
  "type": "Feature",
  "properties": {
    "iso:country":"GB",
    "sg:address":"Moss Side Careers Office, Millennium Powerhouse",
    "sg:city":"Manchester",
    "sg:classifiers":[
        {
            "category":"Professional",
            "subcategory":"Employment Agencies",
            "type":"Services"
        }
    ],
    "sg:phone":"+44 161 226 8609",
    "sg:postcode":"M14 4SQ",
    "sg:province":"Greater Manchester",
    "sg:tags":[
        "career",
        "guidance"
    ],
    "wof:name":"Better Choices Ltd.",
    "wof:placetype":"venue"
},
  "geometry": {"coordinates":[-2.2365999222,53.4562187195],"type":"Point"}
}