{
  "type": "Feature",
  "properties": {
    "addr:full":"Racecourse Industrial Estate, Ormskirk Road Liverpool Merseyside L9 5AL",
    "addr:postcode":"l9 5al",
    "addr:street":"Racecourse Industrial Estate Ormskirk Road",
    "iso:country":"GB",
    "sg:address":"Racecourse Industrial Estate, Ormskirk Road",
    "sg:city":"Liverpool",
    "sg:classifiers":[
        {
            "category":"Home & Garden",
            "subcategory":"Carpets & Floor Coverings",
            "type":"Retail Goods"
        }
    ],
    "sg:phone":"+44 151 525 4858",
    "sg:postcode":"L9 5AL",
    "sg:province":"Merseyside",
    "sg:tags":[
        "carpets",
        "rug",
        "matting"
    ],
    "wof:name":"Carpetworld Ltd.",
    "wof:placetype":"venue"
},
  "geometry": {"coordinates":[-2.950484,53.482635],"type":"Point"}
}