{
  "type": "Feature",
  "properties": {
    "addr:full":"Pubs Group, Po Box 8627 Birmingham West Midlands B16 0PJ",
    "addr:housenumber":"po box 8627",
    "addr:postcode":"b16 0pj",
    "iso:country":"GB",
    "sg:address":"Pubs Group, Po Box 8627",
    "sg:city":"Birmingham",
    "sg:classifiers":[
        {
            "category":"Bars & Pubs",
            "type":"Food & Drink"
        }
    ],
    "sg:phone":"+44 121 558 1481",
    "sg:postcode":"B16 0PJ",
    "sg:province":"West Midlands",
    "sg:tags":[
        "pubs",
        "inn"
    ],
    "wof:name":"Bass Leisure Retail",
    "wof:placetype":"venue"
},
  "geometry": {"coordinates":[-1.9086040258,52.4785957336],"type":"Point"}
}