{
  "type": "Feature",
  "properties": {
    "iso:country":"GB",
    "sg:address":"57 Firthview Road",
    "sg:city":"Inverness",
    "sg:classifiers":[
        {
            "category":"Building & Trades",
            "subcategory":"Construction",
            "type":"Services"
        }
    ],
    "sg:postcode":"IV3 8LZ",
    "sg:province":"Highland",
    "sg:tags":[
        "roofing"
    ],
    "wof:name":"Cleanco",
    "wof:placetype":"venue"
},
  "geometry": {"coordinates":[-4.256083,57.485016],"type":"Point"}
}