{
  "type": "Feature",
  "properties": {
    "addr:full":"Haggs Wood Racing Stables, Stainforth Doncaster South Yorkshire DN7 5PS",
    "addr:housenumber":"stainforth",
    "addr:postcode":"dn7 5ps",
    "addr:street":"Doncaster South",
    "iso:country":"GB",
    "sg:address":"Haggs Wood Racing Stables, Stainforth",
    "sg:city":"Doncaster",
    "sg:classifiers":[
        {
            "category":"Professional",
            "subcategory":"Business Services",
            "type":"Services"
        },
        {
            "category":"Personal",
            "subcategory":"Adult",
            "type":"Services"
        }
    ],
    "sg:phone":"+44 1302 845904",
    "sg:postcode":"DN7 5PS",
    "sg:province":"South Yorkshire",
    "sg:tags":[
        "bookmaker",
        "equestrian"
    ],
    "wof:name":"R Thompson Race Horse Trainer",
    "wof:placetype":"venue"
},
  "geometry": {"coordinates":[-1.030399,53.595074],"type":"Point"}
}