{
  "type": "Feature",
  "properties": {
    "addr:full":"31 Assembly Street, Leith Edinburgh City of Edinburgh EH6 7BQ",
    "addr:housenumber":"31",
    "addr:postcode":"eh6 7bq",
    "addr:street":"Assembly Street",
    "iso:country":"GB",
    "sg:address":"31 Assembly Street, Leith",
    "sg:city":"Edinburgh",
    "sg:classifiers":[
        {
            "category":"Manufacturing",
            "subcategory":"Metals",
            "type":"Manufacturing & Wholesale Goods"
        }
    ],
    "sg:phone":"+44 131 554 6550",
    "sg:postcode":"EH6 7BQ",
    "sg:province":"City of Edinburgh",
    "sg:tags":[
        "work",
        "sheet"
    ],
    "wof:name":"Hastie & Co. (Edinburgh) Ltd.",
    "wof:placetype":"venue"
},
  "geometry": {"coordinates":[-3.1653590202,55.9749488831],"type":"Point"}
}