{
  "type": "Feature",
  "properties": {
    "iso:country":"GB",
    "sg:address":"52 Atholl Street",
    "sg:city":"Perth",
    "sg:classifiers":[
        {
            "category":"Retail",
            "subcategory":"Storage",
            "type":"Services"
        }
    ],
    "sg:phone":"+44 1738 626683",
    "sg:postcode":"PH1 5NN",
    "sg:province":"Perth and Kinross",
    "sg:tags":[
        "household",
        "removal"
    ],
    "wof:name":"Atholl Removal & Storage",
    "wof:placetype":"venue"
},
  "geometry": {"coordinates":[-3.4346849918,56.3994789124],"type":"Point"}
}