{
  "type": "Feature",
  "properties": {
    "addr:full":"Roman Road Darwen Lancashire BB3 3BN",
    "addr:postcode":"bb3 3bn",
    "addr:street":"Roman Road",
    "iso:country":"GB",
    "sg:address":"Roman Road",
    "sg:city":"Darwen",
    "sg:classifiers":[
        {
            "category":"Organizations",
            "subcategory":"Non-profit Organization",
            "type":"Services"
        }
    ],
    "sg:phone":"+44 1254 703731",
    "sg:postcode":"BB3 3BN",
    "sg:province":"Lancashire",
    "sg:tags":[
        "organisation",
        "voluntary",
        "charity"
    ],
    "wof:name":"The Cancer Research Campaign",
    "wof:placetype":"venue"
},
  "geometry": {"coordinates":[-2.4514009953,53.7027664185],"type":"Point"}
}