{
  "type": "Feature",
  "properties": {
    "addr:full":"Skelwith Fold Farm, Skelwith Fold Ambleside Cumbria LA22 0HT",
    "addr:postcode":"la22 0ht",
    "addr:street":"Skelwith Fold",
    "iso:country":"GB",
    "sg:address":"Skelwith Fold Farm, Skelwith Fold",
    "sg:city":"Ambleside",
    "sg:classifiers":[
        {
            "category":"Farming",
            "subcategory":"Livestock Farm",
            "type":"Manufacturing & Wholesale Goods"
        }
    ],
    "sg:postcode":"LA22 0HT",
    "sg:province":"Cumbria",
    "sg:tags":[
        "others"
    ],
    "wof:name":"J F Benson",
    "wof:placetype":"venue"
},
  "geometry": {"coordinates":[-2.9630889893,54.4326057434],"type":"Point"}
}