{
  "type": "Feature",
  "properties": {
    "addr:full":"St. James Rd, Goffs Oak Waltham Cross Greater London EN7 6TP",
    "addr:postcode":"en7 6tp",
    "addr:street":"St. James Rd;Cross",
    "iso:country":"GB",
    "sg:address":"St. James Rd, Goffs Oak",
    "sg:city":"Waltham Cross",
    "sg:classifiers":[
        {
            "category":"Place Of Worship",
            "type":"Public Place"
        }
    ],
    "sg:phone":"+44 1707 876086",
    "sg:postcode":"EN7 6TP",
    "sg:province":"Greater London",
    "wof:name":"St. James Church C.E",
    "wof:placetype":"venue"
},
  "geometry": {"coordinates":[-0.0797500014,51.7126235962],"type":"Point"}
}