{
  "type": "Feature",
  "properties": {
    "addr:full":"96 Fore Street Kingsbridge Devon TQ7 1PP",
    "addr:housenumber":"96",
    "addr:postcode":"tq7 1pp",
    "addr:street":"Fore Street",
    "iso:country":"GB",
    "sg:address":"96 Fore Street",
    "sg:city":"Kingsbridge",
    "sg:classifiers":[
        {
            "category":"Personal",
            "subcategory":"Beauty Salon",
            "type":"Services"
        }
    ],
    "sg:postcode":"TQ7 1PP",
    "sg:province":"Devon",
    "sg:tags":[
        "unisex",
        "hairdresser"
    ],
    "wof:name":"Belinda David Hair Studio",
    "wof:placetype":"venue"
},
  "geometry": {"coordinates":[-3.7779419422,50.2869567871],"type":"Point"}
}