{
  "type": "Feature",
  "properties": {
    "addr:full":"Unit 12/13, Egham Business Village Egham Surrey TW20 8RB",
    "addr:housenumber":"unit 12 / 13",
    "addr:postcode":"tw20 8rb",
    "addr:street":"Egham Business Village",
    "iso:country":"GB",
    "sg:address":"Unit 12/13, Egham Business Village",
    "sg:city":"Egham",
    "sg:classifiers":[
        {
            "category":"Shopping",
            "subcategory":"Computers & Home Electronics",
            "type":"Retail Goods"
        }
    ],
    "sg:postcode":"TW20 8RB",
    "sg:province":"Surrey",
    "sg:tags":[
        "equipment",
        "audio-visual"
    ],
    "wof:name":"Matrix Display Systems Ltd.",
    "wof:placetype":"venue"
},
  "geometry": {"coordinates":[-0.5474889874,51.430896759],"type":"Point"}
}