{
  "type": "Feature",
  "properties": {
    "addr:full":"15 Perryfield Street Maidstone Kent ME14 2SY",
    "addr:housenumber":"15",
    "addr:postcode":"me14 2sy",
    "addr:street":"Perryfield Street",
    "iso:country":"GB",
    "sg:address":"15 Perryfield Street",
    "sg:city":"Maidstone",
    "sg:classifiers":[
        {
            "category":"Bars & Pubs",
            "type":"Food & Drink"
        }
    ],
    "sg:phone":"+44 1622 677326",
    "sg:postcode":"ME14 2SY",
    "sg:province":"Kent",
    "sg:tags":[
        "pubs",
        "inn"
    ],
    "wof:name":"Earls Ltd.",
    "wof:placetype":"venue"
},
  "geometry": {"coordinates":[0.519217,51.281288],"type":"Point"}
}