{
  "type": "Feature",
  "properties": {
    "addr:full":"Flaval House, Caldwell Road Nuneaton Leicestershire CV11 4NB",
    "addr:postcode":"cv11 4nb",
    "addr:street":"Caldwell Road",
    "iso:country":"GB",
    "sg:address":"Flaval House, Caldwell Road",
    "sg:city":"Nuneaton",
    "sg:classifiers":[
        {
            "category":"Professional",
            "subcategory":"Engineering",
            "type":"Services"
        }
    ],
    "sg:phone":"+44 24 7635 3662",
    "sg:postcode":"CV11 4NB",
    "sg:province":"Leicestershire",
    "sg:tags":[
        "contractor",
        "electrical",
        "engineer"
    ],
    "wof:name":"B W Electrical Installations",
    "wof:placetype":"venue"
},
  "geometry": {"coordinates":[-1.4612109661,52.5090713501],"type":"Point"}
}