{
  "type": "Feature",
  "properties": {
    "addr:full":"33 Offerton Industrial Estate, Hempshaw Lane Stockport Cheshire SK2 5TJ",
    "addr:housenumber":"33",
    "addr:postcode":"sk2 5tj",
    "addr:street":"Offerton Industrial Estate Hempshaw Lane",
    "iso:country":"GB",
    "sg:address":"33 Offerton Industrial Estate, Hempshaw Lane",
    "sg:city":"Stockport",
    "sg:classifiers":[
        {
            "category":"Shopping",
            "subcategory":"Clothing, Apparel, & Fashions",
            "type":"Retail Goods"
        }
    ],
    "sg:phone":"+44 161 480 1210",
    "sg:postcode":"SK2 5TJ",
    "sg:province":"Cheshire",
    "sg:tags":[
        "clothing",
        "fabric"
    ],
    "wof:name":"M Chapman & Sons (Textiles) Ltd.",
    "wof:placetype":"venue"
},
  "geometry": {"coordinates":[-2.1348888874,53.4018211365],"type":"Point"}
}