{
  "type": "Feature",
  "properties": {
    "iso:country":"GB",
    "sg:address":"5 Richard St",
    "sg:city":"Blyth",
    "sg:classifiers":[
        {
            "category":"Professional",
            "type":"Services"
        }
    ],
    "sg:phone":"+44 1670 360695",
    "sg:postcode":"NE24 2HF",
    "sg:province":"Northumberland",
    "sg:tags":[
        "reflexologists"
    ],
    "wof:name":"Sandra Aynsley",
    "wof:placetype":"venue"
},
  "geometry": {"coordinates":[-1.508925,55.124275],"type":"Point"}
}