{
  "type": "Feature",
  "properties": {
    "addr:full":"Friday Street Chorley Lancashire PR6 0AA",
    "addr:postcode":"pr6 0aa",
    "addr:street":"Street",
    "iso:country":"GB",
    "sg:address":"Friday Street",
    "sg:city":"Chorley",
    "sg:classifiers":[
        {
            "category":"Retail",
            "subcategory":"Auto Repair",
            "type":"Services"
        }
    ],
    "sg:phone":"+44 1257 269298",
    "sg:postcode":"PR6 0AA",
    "sg:province":"Lancashire",
    "sg:tags":[
        "modification",
        "garage",
        "related"
    ],
    "wof:name":"D M Wood (Autocentre) Ltd.",
    "wof:placetype":"venue"
},
  "geometry": {"coordinates":[-2.6264419556,53.6550827026],"type":"Point"}
}