{
  "type": "Feature",
  "properties": {
    "addr:full":"Renfrew House, Renfield Street Glasgow Glasgow City G2 3AU",
    "addr:postcode":"g2 3au",
    "addr:street":"Renfield Street",
    "iso:country":"GB",
    "sg:address":"Renfrew House, Renfield Street",
    "sg:city":"Glasgow",
    "sg:classifiers":[
        {
            "category":"Professional",
            "subcategory":"Management & Consulting",
            "type":"Services"
        }
    ],
    "sg:postcode":"G2 3AU",
    "sg:province":"Glasgow City",
    "sg:tags":[
        "fire",
        "consultant",
        "protection"
    ],
    "wof:name":"Fire Guard Scotland",
    "wof:placetype":"venue"
},
  "geometry": {"coordinates":[-4.255152,55.865788],"type":"Point"}
}