{
  "type": "Feature",
  "properties": {
    "iso:country":"GB",
    "sg:address":"4 Victoria Circus",
    "sg:city":"Glasgow",
    "sg:classifiers":[
        {
            "category":"Social Services",
            "subcategory":"Retirement Home",
            "type":"Services"
        }
    ],
    "sg:postcode":"G12 9LD",
    "sg:province":"Glasgow City",
    "sg:tags":[
        "care"
    ],
    "wof:name":"Communicare Services",
    "wof:placetype":"venue"
},
  "geometry": {"coordinates":[-4.300688,55.879143],"type":"Point"}
}