{
  "type": "Feature",
  "properties": {
    "iso:country":"GB",
    "sg:address":"Dale Farm Ho, Dale Farm, Greensbridge La",
    "sg:city":"Prescot",
    "sg:classifiers":[
        {
            "category":"Shopping",
            "subcategory":"Bicycles & Sporting Goods",
            "type":"Retail Goods"
        },
        {
            "category":"Shopping",
            "subcategory":"Pets & Pet Supplies",
            "type":"Retail Goods"
        }
    ],
    "sg:phone":"+44 151 487 0512",
    "sg:postcode":"L35 1QB",
    "sg:province":"Cheshire",
    "sg:tags":[
        "riding",
        "saddlery",
        "equestrian",
        "wear"
    ],
    "wof:name":"Dale Farm Saddlery",
    "wof:placetype":"venue"
},
  "geometry": {"coordinates":[-2.8161799908,53.381942749],"type":"Point"}
}