{
  "type": "Feature",
  "properties": {
    "addr:full":"The Garage, Nicholson Street Newark Nottinghamshire NG24 1RD",
    "addr:postcode":"ng24 1rd",
    "addr:street":"Nicholson Street",
    "iso:country":"GB",
    "sg:address":"The Garage, Nicholson Street",
    "sg:city":"Newark",
    "sg:classifiers":[
        {
            "category":"Retail",
            "subcategory":"Auto Repair",
            "type":"Services"
        }
    ],
    "sg:phone":"+44 1636 703278",
    "sg:postcode":"NG24 1RD",
    "sg:province":"Nottinghamshire",
    "sg:tags":[
        "modification",
        "garage"
    ],
    "wof:name":"Lou Newstead",
    "wof:placetype":"venue"
},
  "geometry": {"coordinates":[-0.809347,53.073895],"type":"Point"}
}