{
  "type": "Feature",
  "properties": {
    "addr:full":"Ryecroft, Plantation Road Leighton Buzzard Bedfordshire LU7 3HT",
    "addr:postcode":"lu7 3ht",
    "addr:street":"Plantation Road",
    "iso:country":"GB",
    "sg:address":"Ryecroft, Plantation Road",
    "sg:city":"Leighton Buzzard",
    "sg:classifiers":[
        {
            "category":"Health Services",
            "subcategory":"Chiropractor",
            "type":"Services"
        }
    ],
    "sg:phone":"+44 1525 377384",
    "sg:postcode":"LU7 3HT",
    "sg:province":"Bedfordshire",
    "wof:name":"Eileen Naples",
    "wof:placetype":"venue"
},
  "geometry": {"coordinates":[-0.6617090106,51.929271698],"type":"Point"}
}