{
  "type": "Feature",
  "properties": {
    "addr:full":"59 Poulters La Worthing West Sussex BN14 7SX",
    "addr:housenumber":"59",
    "addr:postcode":"bn14 7sx",
    "addr:street":"Poulters La Worthing",
    "iso:country":"GB",
    "sg:address":"59 Poulters La",
    "sg:city":"Worthing",
    "sg:classifiers":[
        {
            "category":"Building & Trades",
            "subcategory":"Construction",
            "type":"Services"
        }
    ],
    "sg:phone":"+44 1903 265800",
    "sg:postcode":"BN14 7SX",
    "sg:province":"West Sussex",
    "sg:tags":[
        "roofing"
    ],
    "wof:name":"Stoner Asphalt Flat Roof Contractors",
    "wof:placetype":"venue"
},
  "geometry": {"coordinates":[-0.385720998,50.8303794861],"type":"Point"}
}