{
  "type": "Feature",
  "properties": {
    "addr:full":"31 Church Road, Barton Torquay Devon TQ2 8PN",
    "addr:housenumber":"31",
    "addr:postcode":"tq2 8pn",
    "addr:street":"Church Road",
    "iso:country":"GB",
    "sg:address":"31 Church Road, Barton",
    "sg:city":"Torquay",
    "sg:classifiers":[
        {
            "category":"Professional",
            "subcategory":"Engineering",
            "type":"Services"
        }
    ],
    "sg:phone":"+44 1803 329074",
    "sg:postcode":"TQ2 8PN",
    "sg:province":"Devon",
    "sg:tags":[
        "underpinning",
        "foundation",
        "engineer"
    ],
    "wof:name":"A Robin Hood & Associates Geotechnical",
    "wof:placetype":"venue"
},
  "geometry": {"coordinates":[-3.535956,50.495304],"type":"Point"}
}