{
  "type": "Feature",
  "properties": {
    "iso:country":"GB",
    "sg:address":"24 Paget Drive",
    "sg:city":"Billericay",
    "sg:classifiers":[
        {
            "category":"Manufacturing",
            "subcategory":"Signs",
            "type":"Manufacturing & Wholesale Goods"
        }
    ],
    "sg:postcode":"CM12 0YX",
    "sg:province":"Essex",
    "sg:tags":[
        "writer"
    ],
    "wof:name":"Classic Signs",
    "wof:placetype":"venue"
},
  "geometry": {"coordinates":[0.415419,51.64122],"type":"Point"}
}