{
  "type": "Feature",
  "properties": {
    "iso:country":"GB",
    "sg:address":"152 High Street",
    "sg:city":"Southend-on-sea",
    "sg:classifiers":[
        {
            "category":"Sports & Exercise",
            "subcategory":"Sports Center",
            "type":"Entertainment"
        }
    ],
    "sg:phone":"+44 1702 613018",
    "sg:postcode":"SS1 1JX",
    "sg:province":"Essex",
    "sg:tags":[
        "shop",
        "good"
    ],
    "wof:name":"J D Sports Ltd.",
    "wof:placetype":"venue"
},
  "geometry": {"coordinates":[0.7129849792,51.5390129089],"type":"Point"}
}