{
  "type": "Feature",
  "properties": {
    "addr:full":"Unit 9 St Davids Square, Fengate Peterborough Cambridgeshire PE1 5QA",
    "addr:housenumber":"unit 9",
    "addr:postcode":"pe1 5qa",
    "addr:street":"St Davids Square",
    "iso:country":"GB",
    "sg:address":"Unit 9 St Davids Square, Fengate",
    "sg:city":"Peterborough",
    "sg:classifiers":[
        {
            "category":"Food & Beverages",
            "subcategory":"Bakery",
            "type":"Retail Goods"
        }
    ],
    "sg:phone":"+44 1733 897789",
    "sg:postcode":"PE1 5QA",
    "sg:province":"Cambridgeshire",
    "sg:tags":[
        "pizza"
    ],
    "wof:name":"Carlitos Pizzas",
    "wof:placetype":"venue"
},
  "geometry": {"coordinates":[-0.2209589928,52.5749130249],"type":"Point"}
}