{
  "type": "Feature",
  "properties": {
    "addr:full":"Unit 12 Eelmore Road Farnborough Hampshire GU14 7QN",
    "addr:housenumber":"unit 12",
    "addr:postcode":"gu14 7qn",
    "addr:street":"Eelmore Road",
    "iso:country":"GB",
    "sg:address":"Unit 12 Eelmore Road",
    "sg:city":"Farnborough",
    "sg:classifiers":[
        {
            "category":"Military Area",
            "subcategory":"Coast Guard Base",
            "type":"Public Place"
        },
        {
            "category":"Manufacturing",
            "subcategory":"Petroleum Products",
            "type":"Manufacturing & Wholesale Goods"
        },
        {
            "category":"Manufacturing",
            "subcategory":"Lumber",
            "type":"Manufacturing & Wholesale Goods"
        }
    ],
    "sg:phone":"+44 1252 399020",
    "sg:postcode":"GU14 7QN",
    "sg:province":"Hampshire",
    "sg:tags":[
        "merchants",
        "glazing",
        "double",
        "frame",
        "importer",
        "agent",
        "window",
        "timber",
        "manufacturer"
    ],
    "wof:name":"Paragon Profiles Ltd",
    "wof:placetype":"venue"
},
  "geometry": {"coordinates":[-0.770208,51.285313],"type":"Point"}
}