{
  "type": "Feature",
  "properties": {
    "iso:country":"GB",
    "sg:address":"42 High Street",
    "sg:city":"Ross-on-wye",
    "sg:classifiers":[
        {
            "category":"Shopping",
            "subcategory":"Pets & Pet Supplies",
            "type":"Retail Goods"
        }
    ],
    "sg:postcode":"HR9 5HD",
    "sg:province":"Gloucestershire",
    "wof:name":"Petsave",
    "wof:placetype":"venue"
},
  "geometry": {"coordinates":[-2.584586,51.91407],"type":"Point"}
}