{
  "type": "Feature",
  "properties": {
    "iso:country":"GB",
    "sg:address":"Gate Cottage, Arlescote",
    "sg:city":"Banbury",
    "sg:classifiers":[
        {
            "category":"Professional",
            "subcategory":"Management & Consulting",
            "type":"Services"
        },
        {
            "category":"Wholesale",
            "subcategory":"Scrap",
            "type":"Manufacturing & Wholesale Goods"
        }
    ],
    "sg:phone":"+44 1295 670497",
    "sg:postcode":"OX17 1DQ",
    "sg:province":"Northamptonshire",
    "sg:tags":[
        "consultant",
        "waste",
        "metal",
        "environmental"
    ],
    "wof:name":"Recycling Concepts Ltd.",
    "wof:placetype":"venue"
},
  "geometry": {"coordinates":[-1.4405390024,52.13230896],"type":"Point"}
}