{
  "type": "Feature",
  "properties": {
    "addr:full":"65e King Street Belper Derbyshire DE56 1QA",
    "addr:housenumber":"65e",
    "addr:postcode":"de56 1qa",
    "addr:street":"King Street",
    "iso:country":"GB",
    "sg:address":"65e King Street",
    "sg:city":"Belper",
    "sg:classifiers":[
        {
            "category":"Health Services",
            "subcategory":"Health Practitioner",
            "type":"Services"
        }
    ],
    "sg:phone":"+44 1773 824364",
    "sg:postcode":"DE56 1QA",
    "sg:province":"Derbyshire",
    "sg:tags":[
        "hypnotherapists"
    ],
    "wof:name":"Belper Hypnotherapy Centre",
    "wof:placetype":"venue"
},
  "geometry": {"coordinates":[-1.479742,53.023491],"type":"Point"}
}