{
  "type": "Feature",
  "properties": {
    "addr:full":"Hillsleigh Clinic, 12-14 Nightingale Road Godalming Surrey GU7 3AA",
    "addr:housenumber":"12-14",
    "addr:postcode":"gu7 3aa",
    "addr:street":"Nightingale Road",
    "iso:country":"GB",
    "sg:address":"Hillsleigh Clinic, 12-14 Nightingale Road",
    "sg:city":"Godalming",
    "sg:classifiers":[
        {
            "category":"Health Services",
            "subcategory":"Dentist",
            "type":"Services"
        }
    ],
    "sg:phone":"+44 1483 416204",
    "sg:postcode":"GU7 3AA",
    "sg:province":"Surrey",
    "wof:name":"Godalming Community Dental Clinic",
    "wof:placetype":"venue"
},
  "geometry": {"coordinates":[-0.6183840036,51.1839561462],"type":"Point"}
}