{
  "type": "Feature",
  "properties": {
    "iso:country":"GB",
    "sg:address":"73 Friargate, Freshney Pl",
    "sg:city":"Grimsby",
    "sg:classifiers":[
        {
            "category":"Shopping",
            "subcategory":"Shoes",
            "type":"Retail Goods"
        }
    ],
    "sg:phone":"+44 1472 241999",
    "sg:postcode":"DN31 1ED",
    "sg:province":"Lincolnshire",
    "wof:name":"Saddlers",
    "wof:placetype":"venue"
},
  "geometry": {"coordinates":[-0.08884,53.565331],"type":"Point"}
}