{
  "type": "Feature",
  "properties": {
    "addr:full":"209 Uxbridge Rd London Greater London W13 9AA",
    "addr:housenumber":"209",
    "addr:postcode":"w13 9aa",
    "addr:street":"Uxbridge Rd",
    "iso:country":"GB",
    "sg:address":"209 Uxbridge Rd",
    "sg:city":"London",
    "sg:classifiers":[
        {
            "category":"Personal",
            "subcategory":"Beauty Salon",
            "type":"Services"
        }
    ],
    "sg:phone":"+44 20 8579 5885",
    "sg:postcode":"W13 9AA",
    "sg:province":"Greater London",
    "sg:tags":[
        "lady",
        "hairdresser"
    ],
    "wof:name":"Connect 2",
    "wof:placetype":"venue"
},
  "geometry": {"coordinates":[-0.318898,51.51091],"type":"Point"}
}