{
  "type": "Feature",
  "properties": {
    "iso:country":"GB",
    "sg:address":"43 Station Road",
    "sg:city":"Scunthorpe",
    "sg:classifiers":[
        {
            "category":"Bus Charters",
            "type":"Transportation"
        }
    ],
    "sg:postcode":"DN15 6QE",
    "sg:province":"Lincolnshire",
    "sg:tags":[
        "coach"
    ],
    "wof:name":"Williams Coaches",
    "wof:placetype":"venue"
},
  "geometry": {"coordinates":[-0.648212,53.58773],"type":"Point"}
}