{
  "type": "Feature",
  "properties": {
    "iso:country":"GB",
    "sg:address":"127 Thorpe Bay Grdns",
    "sg:city":"Southend-on-sea",
    "sg:classifiers":[
        {
            "category":"Professional",
            "subcategory":"Engineering",
            "type":"Services"
        },
        {
            "category":"Building & Trades",
            "subcategory":"Construction",
            "type":"Services"
        }
    ],
    "sg:phone":"+44 1702 292001",
    "sg:postcode":"SS1 3NW",
    "sg:province":"Essex",
    "sg:tags":[
        "builder",
        "contractor",
        "electrical",
        "engineer"
    ],
    "wof:name":"Electrical Installation & Technical Services Ltd.",
    "wof:placetype":"venue"
},
  "geometry": {"coordinates":[0.766824,51.527119],"type":"Point"}
}