{
  "type": "Feature",
  "properties": {
    "addr:full":"Unit 1-3 London Greater London SW19 1AA",
    "addr:housenumber":"unit 1-3",
    "addr:postcode":"sw19 1aa",
    "iso:country":"GB",
    "sg:address":"Unit 1-3",
    "sg:city":"London",
    "sg:classifiers":[
        {
            "category":"Professional",
            "subcategory":"Printing & Photocopies",
            "type":"Services"
        }
    ],
    "sg:postcode":"SW19 1AA",
    "sg:province":"Greater London",
    "sg:tags":[
        "printer"
    ],
    "wof:name":"Wandle Press",
    "wof:placetype":"venue"
},
  "geometry": {"coordinates":[-0.161311,51.420242],"type":"Point"}
}