{
  "type": "Feature",
  "properties": {
    "addr:full":"Eaglescott, Burrington Umberleigh Devon EX37 9LH",
    "addr:postcode":"ex37 9lh",
    "iso:country":"GB",
    "sg:address":"Eaglescott, Burrington",
    "sg:city":"Umberleigh",
    "sg:classifiers":[
        {
            "category":"Arena",
            "subcategory":"Sports Club",
            "type":"Entertainment"
        }
    ],
    "sg:phone":"+44 1769 520404",
    "sg:postcode":"EX37 9LH",
    "sg:province":"Devon",
    "wof:name":"Devon Airsports Limited",
    "wof:placetype":"venue"
},
  "geometry": {"coordinates":[-3.985345,50.995815],"type":"Point"}
}