{
  "type": "Feature",
  "properties": {
    "addr:full":"52-54 Prestongate Hessle East Riding of Yorkshire HU13 0RF",
    "addr:housenumber":"52-54",
    "addr:postcode":"hu13 0rf",
    "addr:street":"Prestongate Hessle",
    "iso:country":"GB",
    "sg:address":"52-54 Prestongate",
    "sg:city":"Hessle",
    "sg:classifiers":[
        {
            "category":"Real Estate",
            "subcategory":"Real Estate Agent",
            "type":"Services"
        }
    ],
    "sg:phone":"+44 1482 641266",
    "sg:postcode":"HU13 0RF",
    "sg:province":"East Riding of Yorkshire",
    "wof:name":"Halifax Property Services",
    "wof:placetype":"venue"
},
  "geometry": {"coordinates":[-0.4367659986,53.7230072021],"type":"Point"}
}