{
  "type": "Feature",
  "properties": {
    "addr:full":"Pitt House, Broad Street Lyme Regis Devon DT7 3QF",
    "addr:postcode":"dt7 3qf",
    "addr:street":"Broad Street",
    "iso:country":"GB",
    "sg:address":"Pitt House, Broad Street",
    "sg:city":"Lyme Regis",
    "sg:classifiers":[
        {
            "category":"Food & Beverages",
            "subcategory":"Bakery",
            "type":"Retail Goods"
        }
    ],
    "sg:phone":"+44 1297 445515",
    "sg:postcode":"DT7 3QF",
    "sg:province":"Devon",
    "sg:tags":[
        "baker"
    ],
    "wof:name":"The Village Bakery",
    "wof:placetype":"venue"
},
  "geometry": {"coordinates":[-2.934793,50.724792],"type":"Point"}
}