{
  "type": "Feature",
  "properties": {
    "addr:full":"Riparian Way, Cross Hills Keighley North Yorkshire BD20 7BW",
    "addr:postcode":"bd20 7bw",
    "addr:street":"Riparian Way",
    "iso:country":"GB",
    "sg:address":"Riparian Way, Cross Hills",
    "sg:city":"Keighley",
    "sg:classifiers":[
        {
            "category":"Freight",
            "type":"Transportation"
        }
    ],
    "sg:phone":"+44 1535 634590",
    "sg:postcode":"BD20 7BW",
    "sg:province":"North Yorkshire",
    "sg:tags":[
        "haulage",
        "transport",
        "road"
    ],
    "wof:name":"Joda Freight Ltd",
    "wof:placetype":"venue"
},
  "geometry": {"coordinates":[-1.976516,53.904564],"type":"Point"}
}