{
  "type": "Feature",
  "properties": {
    "addr:full":"8 Cassandra Gate Waltham Cross Essex EN8 0XE",
    "addr:housenumber":"8",
    "addr:postcode":"en8 0xe",
    "addr:street":"Cassandra Gate Waltham",
    "iso:country":"GB",
    "sg:address":"8 Cassandra Gate",
    "sg:city":"Waltham Cross",
    "sg:classifiers":[
        {
            "category":"Home & Garden",
            "subcategory":"Household Appliances",
            "type":"Retail Goods"
        }
    ],
    "sg:postcode":"EN8 0XE",
    "sg:province":"Essex",
    "sg:tags":[
        "electrical"
    ],
    "wof:name":"Solo Appliance Services",
    "wof:placetype":"venue"
},
  "geometry": {"coordinates":[-0.02469,51.717781],"type":"Point"}
}