{
  "type": "Feature",
  "properties": {
    "iso:country":"GB",
    "sg:address":"Church Street",
    "sg:city":"King's Lynn",
    "sg:classifiers":[
        {
            "category":"Organizations",
            "subcategory":"Community Association",
            "type":"Services"
        },
        {
            "category":"Organizations",
            "subcategory":"Membership Organization",
            "type":"Services"
        }
    ],
    "sg:phone":"+44 1553 772983",
    "sg:postcode":"PE30 5EB",
    "sg:province":"Norfolk",
    "sg:tags":[
        "club",
        "social"
    ],
    "wof:name":"Kings Lynn Workers Club",
    "wof:placetype":"venue"
},
  "geometry": {"coordinates":[0.39613,52.751759],"type":"Point"}
}