{
  "type": "Feature",
  "properties": {
    "addr:full":"Harbour Ho, Coldharbour La Rainham Essex RM13 9YB",
    "addr:postcode":"rm13 9yb",
    "addr:street":"La Rainham",
    "iso:country":"GB",
    "sg:address":"Harbour Ho, Coldharbour La",
    "sg:city":"Rainham",
    "sg:classifiers":[
        {
            "category":"Building & Trades",
            "subcategory":"Construction",
            "type":"Services"
        }
    ],
    "sg:phone":"+44 1708 526582",
    "sg:postcode":"RM13 9YB",
    "sg:province":"Essex",
    "sg:tags":[
        "restoration",
        "refurbishment"
    ],
    "wof:name":"Commercial Interiors",
    "wof:placetype":"venue"
},
  "geometry": {"coordinates":[0.18099,51.506596],"type":"Point"}
}