{
  "type": "Feature",
  "properties": {
    "addr:full":"92 Leigh Road Leigh-on-sea Essex SS9 1BU",
    "addr:housenumber":"92",
    "addr:postcode":"ss9 1bu",
    "addr:street":"Leigh Road",
    "iso:country":"GB",
    "sg:address":"92 Leigh Road",
    "sg:city":"Leigh-on-sea",
    "sg:classifiers":[
        {
            "category":"Food & Beverages",
            "subcategory":"Specialty",
            "type":"Retail Goods"
        }
    ],
    "sg:postcode":"SS9 1BU",
    "sg:province":"Essex",
    "sg:tags":[
        "organic"
    ],
    "wof:name":"The Happy Caterpillar",
    "wof:placetype":"venue"
},
  "geometry": {"coordinates":[0.667053,51.543331],"type":"Point"}
}