{
  "type": "Feature",
  "properties": {
    "iso:country":"GB",
    "sg:address":"95 Southbourne Road",
    "sg:city":"Bournemouth",
    "sg:classifiers":[
        {
            "category":"Travel",
            "subcategory":"Hotels & Motels",
            "type":"Entertainment"
        }
    ],
    "sg:phone":"+44 1202 424363",
    "sg:postcode":"BH6 3QN",
    "sg:province":"Dorset",
    "wof:name":"White Gables",
    "wof:placetype":"venue"
},
  "geometry": {"coordinates":[-1.8086559772,50.724899292],"type":"Point"}
}