{
  "type": "Feature",
  "properties": {
    "addr:full":"48 Central Drive, Dudley Fields Walsall Staffordshire WS3 2QJ",
    "addr:housenumber":"48",
    "addr:postcode":"ws3 2qj",
    "addr:street":"Central Drive;Fields",
    "iso:country":"GB",
    "sg:address":"48 Central Drive, Dudley Fields",
    "sg:city":"Walsall",
    "sg:classifiers":[
        {
            "category":"Wholesale",
            "subcategory":"Meat",
            "type":"Manufacturing & Wholesale Goods"
        }
    ],
    "sg:phone":"+44 1922 479619",
    "sg:postcode":"WS3 2QJ",
    "sg:province":"Staffordshire",
    "sg:tags":[
        "product"
    ],
    "wof:name":"Pat Gorman",
    "wof:placetype":"venue"
},
  "geometry": {"coordinates":[-2.011624,52.616722],"type":"Point"}
}