{
  "type": "Feature",
  "properties": {
    "addr:full":"43 Kelvin Street, Holderness Road Hull East Riding of Yorkshire HU9 3EH",
    "addr:housenumber":"43",
    "addr:postcode":"hu9 3eh",
    "addr:street":"Kelvin Street Holderness Road",
    "iso:country":"GB",
    "sg:address":"43 Kelvin Street, Holderness Road",
    "sg:city":"Hull",
    "sg:classifiers":[
        {
            "category":"Professional",
            "subcategory":"Computer Services",
            "type":"Services"
        }
    ],
    "sg:postcode":"HU9 3EH",
    "sg:province":"East Riding of Yorkshire",
    "sg:tags":[
        "system",
        "software"
    ],
    "wof:name":"Noddin' Dog Ltd.",
    "wof:placetype":"venue"
},
  "geometry": {"coordinates":[-0.2977679968,53.7608642578],"type":"Point"}
}