{
  "type": "Feature",
  "properties": {
    "iso:country":"GB",
    "sg:address":"Unit E3",
    "sg:city":"Rochdale",
    "sg:classifiers":[
        {
            "category":"Manufacturing",
            "subcategory":"Metals",
            "type":"Manufacturing & Wholesale Goods"
        }
    ],
    "sg:phone":"+44 1706 647802",
    "sg:postcode":"OL12 0AA",
    "sg:province":"Lancashire",
    "wof:name":"Townhead Electroplating Services",
    "wof:placetype":"venue"
},
  "geometry": {"coordinates":[-2.171969,53.638531],"type":"Point"}
}