{
  "type": "Feature",
  "properties": {
    "iso:country":"GB",
    "sg:address":"70 Vale Road",
    "sg:city":"Rhyl",
    "sg:classifiers":[
        {
            "category":"Food & Beverages",
            "subcategory":"Bakery",
            "type":"Retail Goods"
        }
    ],
    "sg:postcode":"LL18 2BY",
    "sg:province":"Conwy",
    "sg:tags":[
        "baker",
        "confectionery"
    ],
    "wof:name":"G Thomson Bakery",
    "wof:placetype":"venue"
},
  "geometry": {"coordinates":[-3.483387,53.317265],"type":"Point"}
}