{
  "type": "Feature",
  "properties": {
    "addr:full":"9-11 High Street, Pullox Hill Bedford Bedfordshire MK45 5HA",
    "addr:housenumber":"9-11",
    "addr:postcode":"mk45 5ha",
    "addr:street":"High Street",
    "iso:country":"GB",
    "sg:address":"9-11 High Street, Pullox Hill",
    "sg:city":"Bedford",
    "sg:classifiers":[
        {
            "category":"Government",
            "subcategory":"Post Office",
            "type":"Public Place"
        }
    ],
    "sg:postcode":"MK45 5HA",
    "sg:province":"Bedfordshire",
    "wof:name":"Pullox Hill Sub P.O",
    "wof:placetype":"venue"
},
  "geometry": {"coordinates":[-0.457805,52.009026],"type":"Point"}
}