{
  "type": "Feature",
  "properties": {
    "iso:country":"GB",
    "sg:address":"Meadow Street, Mevagissey",
    "sg:city":"St Austell",
    "sg:classifiers":[
        {
            "category":"Social Services",
            "subcategory":"Adult Care",
            "type":"Services"
        },
        {
            "category":"Landmark",
            "subcategory":"Tourist Attraction",
            "type":"Public Place"
        }
    ],
    "sg:phone":"+44 1726 842457",
    "sg:postcode":"PL26 6UL",
    "sg:province":"Cornwall",
    "sg:tags":[
        "model",
        "interest",
        "village"
    ],
    "wof:name":"Mevagissey Model Railway Ltd.",
    "wof:placetype":"venue"
},
  "geometry": {"coordinates":[-4.77165,50.350323],"type":"Point"}
}