{
  "type": "Feature",
  "properties": {
    "addr:full":"7 Larkspur Close Wokingham Berkshire RG41 3NA",
    "addr:housenumber":"7",
    "addr:postcode":"rg41 3na",
    "addr:street":"Larkspur Close",
    "iso:country":"GB",
    "sg:address":"7 Larkspur Close",
    "sg:city":"Wokingham",
    "sg:classifiers":[
        {
            "category":"Communications",
            "type":"Services"
        }
    ],
    "sg:href":"http://api.simplegeo.com/1.0/features/SG_1BQQY1lttxBvscs9uElF0O_51.418091_-0.867135@1300740015.json",
    "sg:postcode":"RG41 3NA",
    "sg:province":"Berkshire",
    "sg:tags":[
        "audio-visual"
    ],
    "wof:name":"Fingertips Presentation Perfect",
    "wof:placetype":"venue"
},
  "geometry": {"coordinates":[-0.867135,51.418091],"type":"Point"}
}