{"geometry":{"type":"Point","coordinates":[-0.867135,51.418091]},"type":"Feature","id":102560819,"bbox":[-0.867135,51.418091,-0.867135,51.418091],"properties":{"sg:province":"Berkshire","sg:tags":["audio-visual"],"geom:longitude":-0.867135,"wof:breaches":[],"sg:href":"http://api.simplegeo.com/1.0/features/SG_1BQQY1lttxBvscs9uElF0O_51.418091_-0.867135@1300740015.json","sg:owner":"simplegeo","sg:postcode":"RG41 3NA","geom:latitude":51.418091,"sg:classifiers":[{"category":"Communications","type":"Services","subcategory":""}],"sg:address":"7 Larkspur Close","wof:hierarchy":[{"venue_id":102560819,"country_id":85633159,"region_id":85684209}],"geom:area":0.000000,"sg:city":"Wokingham","wof:lastmodified":1438093374,"iso:country":"GB","wof:geomhash":"a51e77111e64e563749b4c92417b04ac","wof:name":"Fingertips Presentation Perfect","wof:belongsto":[85633159,85684209],"src:geom":"simplegeo","wof:placetype":"venue","wof:supersedes":[],"wof:id":102560819,"wof:superseded_by":[],"wof:concordances":{"sg:id":"SG_1BQQY1lttxBvscs9uElF0O_51.418091_-0.867135@1300740015"},"wof:parent_id":85684209}}