{
  "type": "Feature",
  "properties": {
    "addr:full":"2-4 Monnow Street Monmouth Gloucestershire NP25 3EE",
    "addr:housenumber":"2-4",
    "addr:postcode":"np25 3ee",
    "addr:street":"Monnow Street",
    "iso:country":"GB",
    "sg:address":"2-4 Monnow Street",
    "sg:city":"Monmouth",
    "sg:classifiers":[
        {
            "category":"Personal",
            "subcategory":"Beauty Salon",
            "type":"Services"
        }
    ],
    "sg:postcode":"NP25 3EE",
    "sg:province":"Gloucestershire",
    "sg:tags":[
        "unisex",
        "hairdresser"
    ],
    "wof:name":"Slades for Hair",
    "wof:placetype":"venue"
},
  "geometry": {"coordinates":[-2.715877,51.811844],"type":"Point"}
}