{
  "type": "Feature",
  "properties": {
    "iso:country":"GB",
    "sg:address":"2-12 City Rd",
    "sg:city":"Cardiff",
    "sg:classifiers":[
        {
            "category":"Shopping",
            "subcategory":"Department Store",
            "type":"Retail Goods"
        }
    ],
    "sg:postcode":"CF24 3DL",
    "sg:province":"Cardiff",
    "wof:name":"Daniel,W J,& Co Ltd",
    "wof:placetype":"venue"
},
  "geometry": {"coordinates":[-3.165981,51.485619],"type":"Point"}
}