{
  "type": "Feature",
  "properties": {
    "addr:full":"33-35 Highgate Kendal Cumbria LA9 4ED",
    "addr:housenumber":"33-35",
    "addr:postcode":"la9 4ed",
    "addr:street":"Highgate",
    "iso:country":"GB",
    "sg:address":"33-35 Highgate",
    "sg:city":"Kendal",
    "sg:classifiers":[
        {
            "category":"Professional",
            "subcategory":"Computer Services",
            "type":"Services"
        }
    ],
    "sg:postcode":"LA9 4ED",
    "sg:province":"Cumbria",
    "sg:tags":[
        "information"
    ],
    "wof:name":"Motorist's Information Centre Ltd",
    "wof:placetype":"venue"
},
  "geometry": {"coordinates":[-2.747419,54.326698],"type":"Point"}
}