{
  "type": "Feature",
  "properties": {
    "addr:full":"44 Market Place Malton North Yorkshire YO17 7LW",
    "addr:housenumber":"44",
    "addr:postcode":"yo17 7lw",
    "addr:street":"Market Place",
    "iso:country":"GB",
    "sg:address":"44 Market Place",
    "sg:city":"Malton",
    "sg:classifiers":[
        {
            "category":"Shopping",
            "subcategory":"Jewelry",
            "type":"Retail Goods"
        },
        {
            "category":"Shopping",
            "subcategory":"Comic Books",
            "type":"Retail Goods"
        }
    ],
    "sg:phone":"+44 1653 692921",
    "sg:postcode":"YO17 7LW",
    "sg:province":"North Yorkshire",
    "sg:tags":[
        "jeweller",
        "sale",
        "jewellery"
    ],
    "wof:name":"B Leefe & Sons",
    "wof:placetype":"venue"
},
  "geometry": {"coordinates":[-0.7982710004,54.1359558105],"type":"Point"}
}