{
  "type": "Feature",
  "properties": {
    "iso:country":"GB",
    "sg:address":"320-326 Ashley Rd",
    "sg:city":"Poole",
    "sg:classifiers":[
        {
            "category":"Food & Beverages",
            "subcategory":"Bakery",
            "type":"Retail Goods"
        }
    ],
    "sg:postcode":"BH14 9DF",
    "sg:province":"Dorset",
    "sg:tags":[
        "baker"
    ],
    "wof:name":"Baxters Patisserie",
    "wof:placetype":"venue"
},
  "geometry": {"coordinates":[-1.9359740019,50.7287788391],"type":"Point"}
}