{
  "type": "Feature",
  "properties": {
    "addr:full":"3 Hill St., Hakin Milford Haven Pembrokeshire SA73 3LP",
    "addr:housenumber":"3",
    "addr:postcode":"sa73 3lp",
    "addr:street":"Hill St. Hakin",
    "iso:country":"GB",
    "sg:address":"3 Hill St., Hakin",
    "sg:city":"Milford Haven",
    "sg:classifiers":[
        {
            "category":"Health Services",
            "subcategory":"Health Practitioner",
            "type":"Services"
        }
    ],
    "sg:phone":"+44 1646 690535",
    "sg:postcode":"SA73 3LP",
    "sg:province":"Pembrokeshire",
    "sg:tags":[
        "psychotherapist"
    ],
    "wof:name":"S M Latham",
    "wof:placetype":"venue"
},
  "geometry": {"coordinates":[-5.044766,51.711769],"type":"Point"}
}