{
  "type": "Feature",
  "properties": {
    "addr:full":"144 Pinehurst Road Ferndown Dorset BH22 0AT",
    "addr:housenumber":"144",
    "addr:postcode":"bh22 0at",
    "addr:street":"Pinehurst Road",
    "iso:country":"GB",
    "sg:address":"144 Pinehurst Road",
    "sg:city":"Ferndown",
    "sg:classifiers":[
        {
            "category":"Food & Beverages",
            "subcategory":"Bakery",
            "type":"Retail Goods"
        }
    ],
    "sg:postcode":"BH22 0AT",
    "sg:province":"Dorset",
    "sg:tags":[
        "baker"
    ],
    "wof:name":"Pandoras Bakery",
    "wof:placetype":"venue"
},
  "geometry": {"coordinates":[-1.870692,50.815533],"type":"Point"}
}