{
  "type": "Feature",
  "properties": {
    "addr:full":"2 Church Cottage, High St Etchingham East Sussex TN19 7AN",
    "addr:housenumber":"2",
    "addr:postcode":"tn19 7an",
    "addr:street":"Church;High St",
    "iso:country":"GB",
    "sg:address":"2 Church Cottage, High St",
    "sg:city":"Etchingham",
    "sg:classifiers":[
        {
            "category":"Manufacturing",
            "subcategory":"Textiles",
            "type":"Manufacturing & Wholesale Goods"
        }
    ],
    "sg:phone":"+44 1580 819180",
    "sg:postcode":"TN19 7AN",
    "sg:province":"East Sussex",
    "wof:name":"Union Textiles",
    "wof:placetype":"venue"
},
  "geometry": {"coordinates":[0.4416419864,51.0093803406],"type":"Point"}
}