{
  "type": "Feature",
  "properties": {
    "iso:country":"GB",
    "sg:address":"57 High Street",
    "sg:city":"Fareham",
    "sg:classifiers":[
        {
            "category":"Professional",
            "type":"Services"
        }
    ],
    "sg:phone":"+44 1329 231361",
    "sg:postcode":"PO16 7BG",
    "sg:province":"Hampshire",
    "sg:tags":[
        "entertainer"
    ],
    "wof:name":"Murder Mystery Southern Ltd.",
    "wof:placetype":"venue"
},
  "geometry": {"coordinates":[-1.1737799644,50.8532104492],"type":"Point"}
}