{
  "type": "Feature",
  "properties": {
    "iso:country":"GB",
    "sg:address":"108 London Rd",
    "sg:city":"Neath",
    "sg:classifiers":[
        {
            "category":"Health Services",
            "subcategory":"Health Practitioner",
            "type":"Services"
        }
    ],
    "sg:phone":"+44 1639 633292",
    "sg:postcode":"SA11 1HL",
    "sg:province":"Neath Port Talbot",
    "sg:tags":[
        "osteopath"
    ],
    "wof:name":"Katie Graham",
    "wof:placetype":"venue"
},
  "geometry": {"coordinates":[-3.804032,51.658783],"type":"Point"}
}