{
  "type": "Feature",
  "properties": {
    "addr:full":"157 Rawson Rd Liverpool Merseyside L21 1HL",
    "addr:housenumber":"157",
    "addr:postcode":"l21 1hl",
    "addr:street":"Rawson Rd",
    "iso:country":"GB",
    "sg:address":"157 Rawson Rd",
    "sg:city":"Liverpool",
    "sg:classifiers":[
        {
            "category":"Building & Trades",
            "subcategory":"Construction",
            "type":"Services"
        }
    ],
    "sg:phone":"+44 151 928 0684",
    "sg:postcode":"L21 1HL",
    "sg:province":"Merseyside",
    "sg:tags":[
        "builder"
    ],
    "wof:name":"A A A Contractors",
    "wof:placetype":"venue"
},
  "geometry": {"coordinates":[-3.016616106,53.469417572],"type":"Point"}
}