{
  "type": "Feature",
  "properties": {
    "iso:country":"GB",
    "sg:address":"62 Canterbury Rd, Holland On Sea",
    "sg:city":"Clacton On Sea",
    "sg:classifiers":[
        {
            "category":"Building & Trades",
            "subcategory":"Construction",
            "type":"Services"
        }
    ],
    "sg:phone":"+44 1255 813527",
    "sg:postcode":"CO15 5QL",
    "sg:province":"Essex",
    "sg:tags":[
        "roofing"
    ],
    "wof:name":"B F C C",
    "wof:placetype":"venue"
},
  "geometry": {"coordinates":[1.196689,51.802364],"type":"Point"}
}