{
  "type": "Feature",
  "properties": {
    "addr:full":"Olden Business Center Colchester Essex CO6 3PN",
    "addr:postcode":"co6 3pn",
    "iso:country":"GB",
    "sg:address":"Olden Business Center",
    "sg:city":"Colchester",
    "sg:classifiers":[
        {
            "category":"Commercial Area",
            "type":"Public Place"
        }
    ],
    "sg:phone":"+44 1206 549999",
    "sg:postcode":"CO6 3PN",
    "sg:province":"Essex",
    "sg:tags":[
        "shop",
        "centre"
    ],
    "wof:name":"New Homes Marketing",
    "wof:placetype":"venue"
},
  "geometry": {"coordinates":[0.7900400162,51.9072113037],"type":"Point"}
}