{
  "type": "Feature",
  "properties": {
    "addr:full":"35-37 Folgate Street London Greater London E1 6BX",
    "addr:housenumber":"35-37",
    "addr:postcode":"e1 6bx",
    "addr:street":"Folgate Street",
    "iso:country":"GB",
    "sg:address":"35-37 Folgate Street",
    "sg:city":"London",
    "sg:classifiers":[
        {
            "category":"Building & Trades",
            "subcategory":"Cleaning & Sanitation",
            "type":"Services"
        }
    ],
    "sg:phone":"+44 20 7377 9300",
    "sg:postcode":"E1 6BX",
    "sg:province":"Greater London",
    "sg:tags":[
        "commercial"
    ],
    "wof:name":"Dougland Sports Services",
    "wof:placetype":"venue"
},
  "geometry": {"coordinates":[-0.0752020031,51.5207977295],"type":"Point"}
}