{
  "type": "Feature",
  "properties": {
    "addr:full":"6 East Point, High Street, Seal Sevenoaks Kent TN15 0EG",
    "addr:housenumber":"6",
    "addr:postcode":"tn15 0eg",
    "addr:street":"High Street",
    "iso:country":"GB",
    "sg:address":"6 East Point, High Street, Seal",
    "sg:city":"Sevenoaks",
    "sg:classifiers":[
        {
            "category":"Professional",
            "subcategory":"Management & Consulting",
            "type":"Services"
        }
    ],
    "sg:phone":"+44 1732 761010",
    "sg:postcode":"TN15 0EG",
    "sg:province":"Kent",
    "sg:tags":[
        "consultant",
        "business"
    ],
    "wof:name":"Penzer Allen Ltd.",
    "wof:placetype":"venue"
},
  "geometry": {"coordinates":[0.2236700058,51.2879104614],"type":"Point"}
}