{
  "type": "Feature",
  "properties": {
    "iso:country":"GB",
    "sg:address":"2 The Mall, Millgate Centre",
    "sg:city":"Bury",
    "sg:classifiers":[
        {
            "category":"Shopping",
            "subcategory":"Comic Books",
            "type":"Retail Goods"
        }
    ],
    "sg:phone":"+44 161 797 4682",
    "sg:postcode":"BL9 0QQ",
    "sg:province":"Lancashire",
    "sg:tags":[
        "jeweller"
    ],
    "wof:name":"H Samuel",
    "wof:placetype":"venue"
},
  "geometry": {"coordinates":[-2.297368,53.593609],"type":"Point"}
}