{
  "type": "Feature",
  "properties": {
    "addr:full":"Bridge Rd Maidenhead Berkshire SL6 8NH",
    "addr:postcode":"sl6 8nh",
    "addr:street":"Bridge Rd",
    "iso:country":"GB",
    "sg:address":"Bridge Rd",
    "sg:city":"Maidenhead",
    "sg:classifiers":[
        {
            "category":"Autos & Motor Vehicles",
            "subcategory":"Fuel & Gas Station",
            "type":"Retail Goods"
        }
    ],
    "sg:phone":"+44 1628 503100",
    "sg:postcode":"SL6 8NH",
    "sg:province":"Berkshire",
    "sg:tags":[
        "petrol",
        "filling"
    ],
    "wof:name":"Texaco",
    "wof:placetype":"venue"
},
  "geometry": {"coordinates":[-0.7052689791,51.5238609314],"type":"Point"}
}