{
  "type": "Feature",
  "properties": {
    "iso:country":"GB",
    "sg:address":"9 Brookfield, Duncan Close",
    "sg:city":"Northampton",
    "sg:classifiers":[
        {
            "category":"Retail",
            "subcategory":"Auto Repair",
            "type":"Services"
        }
    ],
    "sg:postcode":"NN3 6WL",
    "sg:province":"Northamptonshire",
    "sg:tags":[
        "modification",
        "garage"
    ],
    "wof:name":"Anthony Brooks Ltd",
    "wof:placetype":"venue"
},
  "geometry": {"coordinates":[-0.87943,52.277981],"type":"Point"}
}