{
  "type": "Feature",
  "properties": {
    "addr:full":"Queen St Pembroke Dock Pembrokeshire SA72 6JE",
    "addr:postcode":"sa72 6je",
    "addr:street":"Queen St",
    "iso:country":"GB",
    "sg:address":"Queen St",
    "sg:city":"Pembroke Dock",
    "sg:classifiers":[
        {
            "category":"Bars & Pubs",
            "type":"Food & Drink"
        }
    ],
    "sg:postcode":"SA72 6JE",
    "sg:province":"Pembrokeshire",
    "sg:tags":[
        "pubs",
        "inn"
    ],
    "wof:name":"Royal Edinburgh Hotel",
    "wof:placetype":"venue"
},
  "geometry": {"coordinates":[-4.9474291801,51.6939811707],"type":"Point"}
}