{
  "type": "Feature",
  "properties": {
    "iso:country":"GB",
    "sg:address":"32 King Edward Street",
    "sg:city":"Perth",
    "sg:classifiers":[
        {
            "category":"Shopping",
            "subcategory":"Clothing, Apparel, & Fashions",
            "type":"Retail Goods"
        }
    ],
    "sg:postcode":"PH1 5UT",
    "sg:province":"Perth and Kinross",
    "sg:tags":[
        "shop"
    ],
    "wof:name":"La Femella",
    "wof:placetype":"venue"
},
  "geometry": {"coordinates":[-3.4297509193,56.3959503174],"type":"Point"}
}