{
  "type": "Feature",
  "properties": {
    "addr:full":"36 Glasshouse St West End Hampshire W1R 5RH",
    "addr:housenumber":"36",
    "addr:postcode":"w1r 5rh",
    "addr:street":"Glasshouse St",
    "iso:country":"GB",
    "sg:address":"36 Glasshouse St",
    "sg:city":"West End",
    "sg:classifiers":[
        {
            "category":"Professional",
            "subcategory":"Business Services",
            "type":"Services"
        }
    ],
    "sg:phone":"+44 20 7287 7744",
    "sg:postcode":"W1R 5RH",
    "sg:province":"Hampshire",
    "sg:tags":[
        "distributor",
        "film"
    ],
    "wof:name":"Hot Foot Films Ltd",
    "wof:placetype":"venue"
},
  "geometry": {"coordinates":[-0.1378259957,51.5105552673],"type":"Point"}
}