{
  "type": "Feature",
  "properties": {
    "addr:full":"Sutton Road Walsall Staffordshire WS9 0QH",
    "addr:postcode":"ws9 0qh",
    "addr:street":"Sutton Road",
    "iso:country":"GB",
    "sg:address":"Sutton Road",
    "sg:city":"Walsall",
    "sg:classifiers":[
        {
            "category":"Shopping",
            "subcategory":"Antiques",
            "type":"Retail Goods"
        }
    ],
    "sg:postcode":"WS9 0QH",
    "sg:province":"Staffordshire",
    "wof:name":"P & K Turner",
    "wof:placetype":"venue"
},
  "geometry": {"coordinates":[-1.914229,52.580601],"type":"Point"}
}