{
  "type": "Feature",
  "properties": {
    "addr:full":"22 Old Milton Road New Milton Hampshire BH25 6DX",
    "addr:housenumber":"22",
    "addr:postcode":"bh25 6dx",
    "addr:street":"Old Milton Road",
    "iso:country":"GB",
    "sg:address":"22 Old Milton Road",
    "sg:city":"New Milton",
    "sg:classifiers":[
        {
            "category":"Health Services",
            "subcategory":"Dentist",
            "type":"Services"
        }
    ],
    "sg:phone":"+44 1425 612200",
    "sg:postcode":"BH25 6DX",
    "sg:province":"Hampshire",
    "sg:tags":[
        "technician",
        "dental"
    ],
    "wof:name":"Denture World",
    "wof:placetype":"venue"
},
  "geometry": {"coordinates":[-1.65868,50.752148],"type":"Point"}
}