{
  "type": "Feature",
  "properties": {
    "iso:country":"GB",
    "sg:address":"Basingstoke Delivery Office, Hermes House, Priestley Road",
    "sg:city":"Basingstoke",
    "sg:classifiers":[
        {
            "category":"Personal",
            "type":"Services"
        }
    ],
    "sg:phone":"+44 845 774 0740",
    "sg:postcode":"RG24 9AA",
    "sg:province":"Hampshire",
    "sg:tags":[
        "delivery"
    ],
    "wof:name":"Royal Mail",
    "wof:placetype":"venue"
},
  "geometry": {"coordinates":[-1.105546,51.277355],"type":"Point"}
}