{
  "type": "Feature",
  "properties": {
    "iso:country":"GB",
    "sg:address":"Llwyn Ganrdyll",
    "sg:city":"Holyhead",
    "sg:classifiers":[
        {
            "category":"Building & Trades",
            "subcategory":"Construction",
            "type":"Services"
        }
    ],
    "sg:phone":"+44 1407 720905",
    "sg:postcode":"LL65 4TA",
    "sg:province":"Isle of Anglesey",
    "sg:tags":[
        "builder"
    ],
    "wof:name":"Edwards Bros",
    "wof:placetype":"venue"
},
  "geometry": {"coordinates":[-4.45186,53.296619],"type":"Point"}
}