{
  "type": "Feature",
  "properties": {
    "iso:country":"GB",
    "sg:address":"Preston Brook Marina, Preston Brook",
    "sg:city":"Runcorn",
    "sg:classifiers":[
        {
            "category":"Professional",
            "type":"Services"
        }
    ],
    "sg:phone":"+44 1928 790700",
    "sg:postcode":"WA7 3AF",
    "sg:province":"Cheshire",
    "sg:tags":[
        "entertainer"
    ],
    "wof:name":"Ace Entertainments",
    "wof:placetype":"venue"
},
  "geometry": {"coordinates":[-2.654914,53.320465],"type":"Point"}
}