{
  "type": "Feature",
  "properties": {
    "addr:full":"27a Cleveland Street Wolverhampton West Midlands WV1 3HT",
    "addr:housenumber":"27a",
    "addr:postcode":"wv1 3ht",
    "addr:street":"Cleveland Street",
    "iso:country":"GB",
    "sg:address":"27a Cleveland Street",
    "sg:city":"Wolverhampton",
    "sg:classifiers":[
        {
            "category":"Home & Garden",
            "subcategory":"Home Furnishings",
            "type":"Retail Goods"
        }
    ],
    "sg:phone":"+44 1902 710693",
    "sg:postcode":"WV1 3HT",
    "sg:province":"West Midlands",
    "sg:tags":[
        "blind",
        "curtain",
        "fitting"
    ],
    "wof:name":"Smiley Balloons",
    "wof:placetype":"venue"
},
  "geometry": {"coordinates":[-2.1276700497,52.5828857422],"type":"Point"}
}