{
  "type": "Feature",
  "properties": {
    "addr:full":"1 Commercial Street, Bedlinog Treharris Caerphilly CF46 6RE",
    "addr:housenumber":"1",
    "addr:postcode":"cf46 6re",
    "addr:street":"Commercial Street",
    "iso:country":"GB",
    "sg:address":"1 Commercial Street, Bedlinog",
    "sg:city":"Treharris",
    "sg:classifiers":[
        {
            "category":"Bus Charters",
            "type":"Transportation"
        }
    ],
    "sg:phone":"+44 1443 710608",
    "sg:postcode":"CF46 6RE",
    "sg:province":"Caerphilly",
    "sg:tags":[
        "hire",
        "coach"
    ],
    "wof:name":"Katies Coaches",
    "wof:placetype":"venue"
},
  "geometry": {"coordinates":[-3.3118579388,51.6995315552],"type":"Point"}
}