{
  "type": "Feature",
  "properties": {
    "iso:country":"GB",
    "sg:address":"28 Queensway, Caversham",
    "sg:city":"Reading",
    "sg:classifiers":[
        {
            "category":"Professional",
            "subcategory":"Computer Services",
            "type":"Services"
        }
    ],
    "sg:phone":"+44 118 946 5940",
    "sg:postcode":"RG4 6SQ",
    "sg:province":"Berkshire",
    "sg:tags":[
        "consultant"
    ],
    "wof:name":"Ramjam Consultants Ltd.",
    "wof:placetype":"venue"
},
  "geometry": {"coordinates":[-0.9511579871,51.4848022461],"type":"Point"}
}