{
  "type": "Feature",
  "properties": {
    "addr:full":"Unit 9, Castle Street Hinckley Leicestershire LE10 1DA",
    "addr:housenumber":"unit 9",
    "addr:postcode":"le10 1da",
    "addr:street":"Castle Street",
    "iso:country":"GB",
    "sg:address":"Unit 9, Castle Street",
    "sg:city":"Hinckley",
    "sg:classifiers":[
        {
            "category":"Retail",
            "subcategory":"Photofinishing",
            "type":"Services"
        }
    ],
    "sg:phone":"+44 1455 613288",
    "sg:postcode":"LE10 1DA",
    "sg:province":"Leicestershire",
    "sg:tags":[
        "photographic",
        "processor"
    ],
    "wof:name":"Sketchley Retail Ltd.",
    "wof:placetype":"venue"
},
  "geometry": {"coordinates":[-1.3681390285,52.5420837402],"type":"Point"}
}