{
  "type": "Feature",
  "properties": {
    "addr:full":"10 Orchard Close Nuneaton Leicestershire CV10 0NE",
    "addr:housenumber":"10",
    "addr:postcode":"cv10 0ne",
    "addr:street":"Orchard Close",
    "iso:country":"GB",
    "sg:address":"10 Orchard Close",
    "sg:city":"Nuneaton",
    "sg:classifiers":[
        {
            "category":"Building & Trades",
            "subcategory":"Construction",
            "type":"Services"
        }
    ],
    "sg:phone":"+44 24 7639 3425",
    "sg:postcode":"CV10 0NE",
    "sg:province":"Leicestershire",
    "sg:tags":[
        "roofing",
        "contracting"
    ],
    "wof:name":"John D Ramm",
    "wof:placetype":"venue"
},
  "geometry": {"coordinates":[-1.5222879648,52.537815094],"type":"Point"}
}