{
  "type": "Feature",
  "properties": {
    "iso:country":"GB",
    "sg:address":"Mystarz Church Lane, Claydon",
    "sg:city":"Ipswich",
    "sg:classifiers":[
        {
            "category":"Retail",
            "subcategory":"Animal Services",
            "type":"Services"
        }
    ],
    "sg:postcode":"IP6 0EN",
    "sg:province":"Suffolk",
    "sg:tags":[
        "box",
        "horse",
        "transporting"
    ],
    "wof:name":"B Bloss",
    "wof:placetype":"venue"
},
  "geometry": {"coordinates":[1.10906,52.106945],"type":"Point"}
}