{
  "type": "Feature",
  "properties": {
    "iso:country":"GB",
    "sg:address":"Denend Farm, Newtyle",
    "sg:city":"Blairgowrie",
    "sg:classifiers":[
        {
            "category":"Professional",
            "type":"Services"
        },
        {
            "category":"Banks & Credit Unions",
            "subcategory":"Investment Brokerage",
            "type":"Services"
        }
    ],
    "sg:phone":"+44 1828 650263",
    "sg:postcode":"PH12 8SQ",
    "sg:province":"Angus",
    "sg:tags":[
        "farm",
        "agricultural",
        "contractor"
    ],
    "wof:name":"James A Graham",
    "wof:placetype":"venue"
},
  "geometry": {"coordinates":[-3.146834,56.558289],"type":"Point"}
}