{
  "type": "Feature",
  "properties": {
    "addr:full":"Ladywell Centre Newtown Powys SY16 1AF",
    "addr:postcode":"sy16 1af",
    "iso:country":"GB",
    "sg:address":"Ladywell Centre",
    "sg:city":"Newtown",
    "sg:classifiers":[
        {
            "category":"Food & Beverages",
            "subcategory":"Supermarket",
            "type":"Retail Goods"
        }
    ],
    "sg:phone":"+44 1686 628449",
    "sg:postcode":"SY16 1AF",
    "sg:province":"Powys",
    "wof:name":"Crs",
    "wof:placetype":"venue"
},
  "geometry": {"coordinates":[-3.3146119118,52.5127754211],"type":"Point"}
}