{
  "type": "Feature",
  "properties": {
    "addr:full":"Lichfield Rd Fareham Hampshire PO14 4QN",
    "addr:postcode":"po14 4qn",
    "addr:street":"Lichfield Rd",
    "iso:country":"GB",
    "sg:address":"Lichfield Rd",
    "sg:city":"Fareham",
    "sg:classifiers":[
        {
            "category":"Retail",
            "subcategory":"Laundry & Dry Cleaning",
            "type":"Services"
        }
    ],
    "sg:phone":"+44 1489 578440",
    "sg:postcode":"PO14 4QN",
    "sg:province":"Hampshire",
    "sg:tags":[
        "home",
        "ironing"
    ],
    "wof:name":"Ironability",
    "wof:placetype":"venue"
},
  "geometry": {"coordinates":[-1.258593,50.862949],"type":"Point"}
}