{
  "type": "Feature",
  "properties": {
    "iso:country":"GB",
    "sg:address":"New Dairy, Credenhill",
    "sg:city":"Hereford",
    "sg:classifiers":[
        {
            "category":"Farming",
            "subcategory":"Dairy Farm",
            "type":"Manufacturing & Wholesale Goods"
        }
    ],
    "sg:phone":"+44 1432 761216",
    "sg:postcode":"HR4 7DN",
    "sg:province":"Herefordshire",
    "wof:name":"H & R Holdings",
    "wof:placetype":"venue"
},
  "geometry": {"coordinates":[-2.79594,52.088409],"type":"Point"}
}