{
  "type": "Feature",
  "properties": {
    "iso:country":"GB",
    "sg:address":"49 Alderley Lane",
    "sg:city":"Leigh",
    "sg:classifiers":[
        {
            "category":"Building & Trades",
            "subcategory":"Construction",
            "type":"Services"
        }
    ],
    "sg:phone":"+44 1942 517520",
    "sg:postcode":"WN7 3DW",
    "sg:province":"Lancashire",
    "sg:tags":[
        "dry",
        "lining",
        "plasterers",
        "screeders"
    ],
    "wof:name":"T Woods",
    "wof:placetype":"venue"
},
  "geometry": {"coordinates":[-2.499245,53.486496],"type":"Point"}
}