{
  "type": "Feature",
  "properties": {
    "addr:full":"3 Chesford Grove Stratford-upon-avon Warwickshire CV37 9LS",
    "addr:housenumber":"3",
    "addr:postcode":"cv37 9ls",
    "addr:street":"Chesford Grove",
    "iso:country":"GB",
    "sg:address":"3 Chesford Grove",
    "sg:city":"Stratford-upon-avon",
    "sg:classifiers":[
        {
            "category":"Retail",
            "subcategory":"Driving School",
            "type":"Services"
        }
    ],
    "sg:phone":"+44 1789 551839",
    "sg:postcode":"CV37 9LS",
    "sg:province":"Warwickshire",
    "wof:name":"Alan Davis",
    "wof:placetype":"venue"
},
  "geometry": {"coordinates":[-1.730761,52.20097],"type":"Point"}
}