{
  "type": "Feature",
  "properties": {
    "addr:full":"447 Sewerby Road, Sewerby Bridlington East Riding of Yorkshire YO15 1ER",
    "addr:housenumber":"447",
    "addr:postcode":"yo15 1er",
    "addr:street":"Sewerby Road Sewerby Bridlington",
    "iso:country":"GB",
    "sg:address":"447 Sewerby Road, Sewerby",
    "sg:city":"Bridlington",
    "sg:classifiers":[
        {
            "category":"Building & Trades",
            "subcategory":"Construction",
            "type":"Services"
        }
    ],
    "sg:phone":"+44 1262 676819",
    "sg:postcode":"YO15 1ER",
    "sg:province":"East Riding of Yorkshire",
    "sg:tags":[
        "builder"
    ],
    "wof:name":"P Richardson",
    "wof:placetype":"venue"
},
  "geometry": {"coordinates":[-0.1688549966,54.1009368896],"type":"Point"}
}