{
  "type": "Feature",
  "properties": {
    "iso:country":"GB",
    "sg:address":"The Maesydd, Pool Quay",
    "sg:city":"Welshpool",
    "sg:classifiers":[
        {
            "category":"Farming",
            "subcategory":"Livestock Farm",
            "type":"Manufacturing & Wholesale Goods"
        }
    ],
    "sg:phone":"+44 1938 590351",
    "sg:postcode":"SY21 9LA",
    "sg:province":"Shropshire",
    "sg:tags":[
        "others"
    ],
    "wof:name":"M & T G Steadman",
    "wof:placetype":"venue"
},
  "geometry": {"coordinates":[-3.1020638943,52.6946792603],"type":"Point"}
}