{
  "type": "Feature",
  "properties": {
    "addr:full":"Ffordd Pen Y Cefn Dolgellau Gwynedd LL40 2YW",
    "addr:postcode":"ll40 2yw",
    "addr:street":"Ffordd Pen Y Cefn",
    "iso:country":"GB",
    "sg:address":"Ffordd Pen Y Cefn",
    "sg:city":"Dolgellau",
    "sg:classifiers":[
        {
            "category":"Education",
            "subcategory":"School",
            "type":"Public Place"
        },
        {
            "category":"Government",
            "subcategory":"Office",
            "type":"Public Place"
        }
    ],
    "sg:phone":"+44 1341 423034",
    "sg:postcode":"LL40 2YW",
    "sg:province":"Gwynedd",
    "sg:tags":[
        "local",
        "authority"
    ],
    "wof:name":"Dolgellau Primary School",
    "wof:placetype":"venue"
},
  "geometry": {"coordinates":[-3.892138958,52.7491188049],"type":"Point"}
}