{
  "type": "Feature",
  "properties": {
    "addr:full":"1 Broadgate Preston Lancashire PR1 8DX",
    "addr:housenumber":"1",
    "addr:postcode":"pr1 8dx",
    "addr:street":"Broadgate Preston",
    "iso:country":"GB",
    "sg:address":"1 Broadgate",
    "sg:city":"Preston",
    "sg:classifiers":[
        {
            "category":"Bars & Pubs",
            "type":"Food & Drink"
        }
    ],
    "sg:phone":"+44 1772 463676",
    "sg:postcode":"PR1 8DX",
    "sg:province":"Lancashire",
    "sg:tags":[
        "pubs",
        "house",
        "inn",
        "public",
        "activity"
    ],
    "wof:name":"Ribbleside Inn",
    "wof:placetype":"venue"
},
  "geometry": {"coordinates":[-2.716101,53.753689],"type":"Point"}
}