{
  "type": "Feature",
  "properties": {
    "addr:full":"Cheltenham Road, Bisley Stroud Gloucestershire GL6 7BL",
    "addr:postcode":"gl6 7bl",
    "addr:street":"Cheltenham Road",
    "iso:country":"GB",
    "sg:address":"Cheltenham Road, Bisley",
    "sg:city":"Stroud",
    "sg:classifiers":[
        {
            "category":"Bars & Pubs",
            "type":"Food & Drink"
        }
    ],
    "sg:phone":"+44 1452 770280",
    "sg:postcode":"GL6 7BL",
    "sg:province":"Gloucestershire",
    "sg:tags":[
        "pubs",
        "inn"
    ],
    "wof:name":"The Stirrup Cup",
    "wof:placetype":"venue"
},
  "geometry": {"coordinates":[-2.1404619217,51.7529220581],"type":"Point"}
}