{
  "type": "Feature",
  "properties": {
    "addr:full":"25-27 Colegreen Lane Welwyn Garden City Hertfordshire AL7 3PP",
    "addr:housenumber":"25-27",
    "addr:postcode":"al7 3pp",
    "addr:street":"Colegreen Lane",
    "iso:country":"GB",
    "sg:address":"25-27 Colegreen Lane",
    "sg:city":"Welwyn Garden City",
    "sg:classifiers":[
        {
            "category":"Home & Garden",
            "subcategory":"Hardware",
            "type":"Retail Goods"
        }
    ],
    "sg:phone":"+44 1707 326161",
    "sg:postcode":"AL7 3PP",
    "sg:province":"Hertfordshire",
    "sg:tags":[
        "retailer",
        "diy"
    ],
    "wof:name":"Welwyn Home Improvement Centre",
    "wof:placetype":"venue"
},
  "geometry": {"coordinates":[-0.195419997,51.7916564941],"type":"Point"}
}