{
  "type": "Feature",
  "properties": {
    "addr:full":"Church Lane, Darley Abbey Derby Derbyshire DE22 1EX",
    "addr:postcode":"de22 1ex",
    "addr:street":"Church Lane",
    "iso:country":"GB",
    "sg:address":"Church Lane, Darley Abbey",
    "sg:city":"Derby",
    "sg:classifiers":[
        {
            "category":"Shopping",
            "subcategory":"Clothing, Apparel, & Fashions",
            "type":"Retail Goods"
        }
    ],
    "sg:postcode":"DE22 1EX",
    "sg:province":"Derbyshire",
    "sg:tags":[
        "shop",
        "hat"
    ],
    "wof:name":"Darley Abbey Hat Hire",
    "wof:placetype":"venue"
},
  "geometry": {"coordinates":[-1.4792109728,52.9453544617],"type":"Point"}
}