{
  "type": "Feature",
  "properties": {
    "addr:full":"9 Park Road Lytham St Annes Lancashire FY8 1QX",
    "addr:housenumber":"9",
    "addr:postcode":"fy8 1qx",
    "addr:street":"Park Road",
    "iso:country":"GB",
    "sg:address":"9 Park Road",
    "sg:city":"Lytham St Annes",
    "sg:classifiers":[
        {
            "category":"Cafe",
            "type":"Food & Drink"
        }
    ],
    "sg:phone":"+44 1253 724721",
    "sg:postcode":"FY8 1QX",
    "sg:province":"Lancashire",
    "sg:tags":[
        "tea",
        "room"
    ],
    "wof:name":"The Coffee Pot",
    "wof:placetype":"venue"
},
  "geometry": {"coordinates":[-3.029017,53.751282],"type":"Point"}
}