{
  "type": "Feature",
  "properties": {
    "addr:full":"Orchard Street Kidderminster Staffordshire DY10 2JA",
    "addr:postcode":"dy10 2ja",
    "addr:street":"Orchard Street",
    "iso:country":"GB",
    "sg:address":"Orchard Street",
    "sg:city":"Kidderminster",
    "sg:classifiers":[
        {
            "category":"Travel",
            "subcategory":"Hostel",
            "type":"Entertainment"
        },
        {
            "category":"Government",
            "subcategory":"Office",
            "type":"Public Place"
        }
    ],
    "sg:phone":"+44 1562 823656",
    "sg:postcode":"DY10 2JA",
    "sg:province":"Staffordshire",
    "sg:tags":[
        "local"
    ],
    "wof:name":"Freda Eddy Court Hostel",
    "wof:placetype":"venue"
},
  "geometry": {"coordinates":[-2.2490890026,52.3903236389],"type":"Point"}
}