{
  "type": "Feature",
  "properties": {
    "addr:full":"Dunbiggin, The Square, Kintore Inverurie Aberdeenshire AB51 0US",
    "addr:postcode":"ab51 0us",
    "addr:street":"The Square Kintore",
    "iso:country":"GB",
    "sg:address":"Dunbiggin, The Square, Kintore",
    "sg:city":"Inverurie",
    "sg:classifiers":[
        {
            "category":"Building & Trades",
            "subcategory":"Construction",
            "type":"Services"
        }
    ],
    "sg:postcode":"AB51 0US",
    "sg:province":"Aberdeenshire",
    "sg:tags":[
        "dry",
        "lining",
        "plasterers",
        "screeders"
    ],
    "wof:name":"Stuart Napier",
    "wof:placetype":"venue"
},
  "geometry": {"coordinates":[-2.3466339111,57.2341918945],"type":"Point"}
}