{
  "type": "Feature",
  "properties": {
    "iso:country":"GB",
    "sg:address":"2 Brooklands Road",
    "sg:city":"Sale",
    "sg:classifiers":[
        {
            "category":"Bars & Pubs",
            "subcategory":"Oxygen Bar",
            "type":"Food & Drink"
        },
        {
            "category":"Real Estate",
            "subcategory":"Real Estate Agent",
            "type":"Services"
        }
    ],
    "sg:phone":"+44 161 973 6262",
    "sg:postcode":"M33 3SS",
    "sg:province":"Cheshire",
    "sg:tags":[
        "ventilation",
        "system"
    ],
    "wof:name":"Willan Group Ltd",
    "wof:placetype":"venue"
},
  "geometry": {"coordinates":[-2.325132,53.417252],"type":"Point"}
}