{
  "type": "Feature",
  "properties": {
    "addr:full":"78 Gt Junction St Edinburgh City of Edinburgh EH6 5LD",
    "addr:housenumber":"78",
    "addr:postcode":"eh6 5ld",
    "addr:street":"Gt Junction St Edinburgh",
    "iso:country":"GB",
    "sg:address":"78 Gt Junction St",
    "sg:city":"Edinburgh",
    "sg:classifiers":[
        {
            "category":"Shopping",
            "subcategory":"Clothing, Apparel, & Fashions",
            "type":"Retail Goods"
        }
    ],
    "sg:postcode":"EH6 5LD",
    "sg:province":"City of Edinburgh",
    "sg:tags":[
        "lingerie",
        "hosiery"
    ],
    "wof:name":"Little,Beverley,",
    "wof:placetype":"venue"
},
  "geometry": {"coordinates":[-3.174259901,55.9722976685],"type":"Point"}
}