{
  "type": "Feature",
  "properties": {
    "addr:full":"Woodfield House, Woodfield Road Altrincham Cheshire WA14 4ED",
    "addr:postcode":"wa14 4ed",
    "addr:street":"Woodfield Road",
    "iso:country":"GB",
    "sg:address":"Woodfield House, Woodfield Road",
    "sg:city":"Altrincham",
    "sg:classifiers":[
        {
            "category":"Sports & Exercise",
            "subcategory":"Gym",
            "type":"Entertainment"
        }
    ],
    "sg:phone":"+44 161 929 8786",
    "sg:postcode":"WA14 4ED",
    "sg:province":"Cheshire",
    "sg:tags":[
        "fitness",
        "health",
        "centre"
    ],
    "wof:name":"Jag Fitness Base One Gym",
    "wof:placetype":"venue"
},
  "geometry": {"coordinates":[-2.352854,53.397137],"type":"Point"}
}