{
  "type": "Feature",
  "properties": {
    "addr:full":"Unit 11 Betws Park Workshops, Park Street Ammanford Carmarthenshire SA18 2ET",
    "addr:housenumber":"unit 11 betws",
    "addr:postcode":"sa18 2et",
    "addr:street":"Park Workshops Park Street",
    "iso:country":"GB",
    "sg:address":"Unit 11 Betws Park Workshops, Park Street",
    "sg:city":"Ammanford",
    "sg:classifiers":[
        {
            "category":"Professional",
            "subcategory":"Management & Consulting",
            "type":"Services"
        }
    ],
    "sg:phone":"+44 1269 597118",
    "sg:postcode":"SA18 2ET",
    "sg:province":"Carmarthenshire",
    "sg:tags":[
        "music"
    ],
    "wof:name":"Artists 2 Events",
    "wof:placetype":"venue"
},
  "geometry": {"coordinates":[-3.985546,51.780876],"type":"Point"}
}