{
  "type": "Feature",
  "properties": {
    "addr:full":"35 Hunters Drive Burnley Lancashire BB12 0HT",
    "addr:housenumber":"35",
    "addr:postcode":"bb12 0ht",
    "addr:street":"Hunters Drive",
    "iso:country":"GB",
    "sg:address":"35 Hunters Drive",
    "sg:city":"Burnley",
    "sg:classifiers":[
        {
            "category":"Professional",
            "subcategory":"Management & Consulting",
            "type":"Services"
        }
    ],
    "sg:postcode":"BB12 0HT",
    "sg:province":"Lancashire",
    "sg:tags":[
        "consultant",
        "business"
    ],
    "wof:name":"J P B Consultancy Ltd.",
    "wof:placetype":"venue"
},
  "geometry": {"coordinates":[-2.264438,53.798706],"type":"Point"}
}