{
  "type": "Feature",
  "properties": {
    "iso:country":"GB",
    "sg:address":"Maerdy Road",
    "sg:city":"Ferndale",
    "sg:classifiers":[
        {
            "category":"Government",
            "subcategory":"Fire Station",
            "type":"Public Place"
        }
    ],
    "sg:phone":"+44 1443 735735",
    "sg:postcode":"CF43 4AD",
    "sg:province":"Rhondda, Cynon, Taff",
    "sg:tags":[
        "security"
    ],
    "wof:name":"Chubb Fire Ltd.",
    "wof:placetype":"venue"
},
  "geometry": {"coordinates":[-3.447809,51.661114],"type":"Point"}
}