{
  "type": "Feature",
  "properties": {
    "iso:country":"GB",
    "sg:address":"Welfare Rights Service, William Molson Centre, Kent St",
    "sg:city":"Grimsby",
    "sg:classifiers":[
        {
            "category":"Government",
            "subcategory":"Office",
            "type":"Public Place"
        }
    ],
    "sg:phone":"+44 1472 325325",
    "sg:postcode":"DN32 7DJ",
    "sg:province":"Lincolnshire",
    "sg:tags":[
        "local"
    ],
    "wof:name":"North East Lincolnshire Council",
    "wof:placetype":"venue"
},
  "geometry": {"coordinates":[-0.07152,53.573608],"type":"Point"}
}