{
  "type": "Feature",
  "properties": {
    "addr:full":"9 Millers Orchard, Fivehead Taunton Devon TA3 6PL",
    "addr:housenumber":"9",
    "addr:postcode":"ta3 6pl",
    "addr:street":"Millers Orchard",
    "iso:country":"GB",
    "sg:address":"9 Millers Orchard, Fivehead",
    "sg:city":"Taunton",
    "sg:classifiers":[
        {
            "category":"Building & Trades",
            "subcategory":"Landscaping Services",
            "type":"Services"
        }
    ],
    "sg:phone":"+44 1460 281611",
    "sg:postcode":"TA3 6PL",
    "sg:province":"Devon",
    "sg:tags":[
        "forestry",
        "tree"
    ],
    "wof:name":"Arbortech",
    "wof:placetype":"venue"
},
  "geometry": {"coordinates":[-2.9252109528,51.0057258606],"type":"Point"}
}