{
  "type": "Feature",
  "properties": {
    "iso:country":"GB",
    "sg:address":"16 Tilling Crescent",
    "sg:city":"High Wycombe",
    "sg:classifiers":[
        {
            "category":"Manufacturing",
            "subcategory":"Building Materials",
            "type":"Manufacturing & Wholesale Goods"
        }
    ],
    "sg:phone":"+44 1494 436983",
    "sg:postcode":"HP13 7XZ",
    "sg:province":"Buckinghamshire",
    "sg:tags":[
        "tile",
        "mnfrs"
    ],
    "wof:name":"A J Smith",
    "wof:placetype":"venue"
},
  "geometry": {"coordinates":[-0.7126320004,51.6306381226],"type":"Point"}
}