{
  "type": "Feature",
  "properties": {
    "iso:country":"GB",
    "sg:address":"8-10 Dryden St",
    "sg:city":"London",
    "sg:classifiers":[
        {
            "category":"Professional",
            "subcategory":"Art Services",
            "type":"Services"
        }
    ],
    "sg:phone":"+44 171 520 5858",
    "sg:postcode":"WC2E 9NA",
    "sg:province":"Greater London",
    "sg:tags":[
        "consultant",
        "design"
    ],
    "wof:name":"October Design Consultants Ltd",
    "wof:placetype":"venue"
},
  "geometry": {"coordinates":[-0.122922,51.514721],"type":"Point"}
}