{
  "type": "Feature",
  "properties": {
    "iso:country":"GB",
    "sg:address":"12 Richmond Hill",
    "sg:city":"Bournemouth",
    "sg:classifiers":[
        {
            "category":"Fast Food",
            "type":"Food & Drink"
        }
    ],
    "sg:postcode":"BH2 6EJ",
    "sg:province":"Dorset",
    "sg:tags":[
        "away",
        "take"
    ],
    "wof:name":"Trattoria Tosca",
    "wof:placetype":"venue"
},
  "geometry": {"coordinates":[-1.879174,50.720909],"type":"Point"}
}