{
  "type": "Feature",
  "properties": {
    "addr:full":"Longton Bamber Bridge & Preston, Venues Preston Lancashire PR1 6BN",
    "addr:postcode":"pr1 6bn",
    "addr:street":"Preston",
    "iso:country":"GB",
    "sg:address":"Longton Bamber Bridge & Preston, Venues",
    "sg:city":"Preston",
    "sg:classifiers":[
        {
            "category":"Community Center",
            "type":"Public Place"
        }
    ],
    "sg:phone":"+44 1772 495748",
    "sg:postcode":"PR1 6BN",
    "sg:province":"Lancashire",
    "sg:tags":[
        "recreation",
        "leisure",
        "centre"
    ],
    "wof:name":"Aquability Swim School",
    "wof:placetype":"venue"
},
  "geometry": {"coordinates":[-2.69912,53.769711],"type":"Point"}
}