{
  "type": "Feature",
  "properties": {
    "iso:country":"GB",
    "sg:address":"Cross Smithfield",
    "sg:city":"Sheffield",
    "sg:classifiers":[
        {
            "category":"Home & Garden",
            "subcategory":"Hardware",
            "type":"Retail Goods"
        }
    ],
    "sg:phone":"+44 114 272 4615",
    "sg:postcode":"S3 7AU",
    "sg:province":"South Yorkshire",
    "sg:tags":[
        "product",
        "wire",
        "electrical"
    ],
    "wof:name":"Rigby Wireworks & Co. (1982) Ltd.",
    "wof:placetype":"venue"
},
  "geometry": {"coordinates":[-1.4758989811,53.3862876892],"type":"Point"}
}