{
  "type": "Feature",
  "properties": {
    "addr:full":"2 Marlpit Rd East Grinstead East Sussex RH19 4PD",
    "addr:housenumber":"2",
    "addr:postcode":"rh19 4pd",
    "addr:street":"Marlpit Rd",
    "iso:country":"GB",
    "sg:address":"2 Marlpit Rd",
    "sg:city":"East Grinstead",
    "sg:classifiers":[
        {
            "category":"Home & Garden",
            "subcategory":"Carpets & Floor Coverings",
            "type":"Retail Goods"
        }
    ],
    "sg:phone":"+44 1342 810631",
    "sg:postcode":"RH19 4PD",
    "sg:province":"East Sussex",
    "sg:tags":[
        "carpets",
        "rug",
        "matting"
    ],
    "wof:name":"Carpet Shop The",
    "wof:placetype":"venue"
},
  "geometry": {"coordinates":[-0.0448089987,51.0772285461],"type":"Point"}
}