{
  "type": "Feature",
  "properties": {
    "iso:country":"GB",
    "sg:address":"16 Station Street",
    "sg:city":"Keswick",
    "sg:classifiers":[
        {
            "category":"Food & Beverages",
            "subcategory":"Liquor & Beverages",
            "type":"Retail Goods"
        }
    ],
    "sg:phone":"+44 17687 72313",
    "sg:postcode":"CA12 5HF",
    "sg:province":"Cumbria",
    "sg:tags":[
        "beer",
        "spirit",
        "wines"
    ],
    "wof:name":"Thresher",
    "wof:placetype":"venue"
},
  "geometry": {"coordinates":[-3.1356139183,54.6004676819],"type":"Point"}
}