{
  "type": "Feature",
  "properties": {
    "iso:country":"GB",
    "sg:address":"Cefn Holdings, Holywell",
    "sg:city":"Bagillt",
    "sg:classifiers":[
        {
            "category":"Farming",
            "subcategory":"Livestock Farm",
            "type":"Manufacturing & Wholesale Goods"
        }
    ],
    "sg:phone":"+44 1352 712338",
    "sg:postcode":"CH6 6DT",
    "sg:province":"Flintshire",
    "sg:tags":[
        "others"
    ],
    "wof:name":"S Williams",
    "wof:placetype":"venue"
},
  "geometry": {"coordinates":[-3.171054,53.268921],"type":"Point"}
}