{
  "type": "Feature",
  "properties": {
    "iso:country":"GB",
    "sg:address":"Llangattock Cottage, Llangattock Vibon Avel",
    "sg:city":"Monmouth",
    "sg:classifiers":[
        {
            "category":"Professional",
            "subcategory":"Engineering",
            "type":"Services"
        }
    ],
    "sg:postcode":"NP25 5NG",
    "sg:province":"Gloucestershire",
    "sg:tags":[
        "contractor",
        "electrical",
        "engineer"
    ],
    "wof:name":"A J Powell",
    "wof:placetype":"venue"
},
  "geometry": {"coordinates":[-2.794039011,51.8415145874],"type":"Point"}
}