{
  "type": "Feature",
  "properties": {
    "iso:country":"GB",
    "sg:address":"43 Eden Way",
    "sg:city":"Beckenham",
    "sg:classifiers":[
        {
            "category":"Building & Trades",
            "subcategory":"Construction",
            "type":"Services"
        }
    ],
    "sg:phone":"+44 20 8402 8121",
    "sg:postcode":"BR3 3DN",
    "sg:province":"Kent",
    "sg:tags":[
        "roofing"
    ],
    "wof:name":"R M L Roofing Services",
    "wof:placetype":"venue"
},
  "geometry": {"coordinates":[-0.032208,51.390694],"type":"Point"}
}