{
  "type": "Feature",
  "properties": {
    "addr:full":"121 The Luton Arndale Centre Luton Bedfordshire LU1 2TN",
    "addr:housenumber":"121",
    "addr:postcode":"lu1 2tn",
    "addr:street":"The",
    "iso:country":"GB",
    "sg:address":"121 The Luton Arndale Centre",
    "sg:city":"Luton",
    "sg:classifiers":[
        {
            "category":"Sports & Exercise",
            "subcategory":"Sports Center",
            "type":"Entertainment"
        }
    ],
    "sg:phone":"+44 1582 733998",
    "sg:postcode":"LU1 2TN",
    "sg:province":"Bedfordshire",
    "sg:tags":[
        "shop",
        "good"
    ],
    "wof:name":"Allsports",
    "wof:placetype":"venue"
},
  "geometry": {"coordinates":[-0.4156149924,51.8813362122],"type":"Point"}
}