{
  "type": "Feature",
  "properties": {
    "addr:full":"372 Nacton Road Ipswich Suffolk IP3 9ND",
    "addr:housenumber":"372",
    "addr:postcode":"ip3 9nd",
    "addr:street":"Nacton Road",
    "iso:country":"GB",
    "sg:address":"372 Nacton Road",
    "sg:city":"Ipswich",
    "sg:classifiers":[
        {
            "category":"Home & Garden",
            "subcategory":"Household Appliances",
            "type":"Retail Goods"
        }
    ],
    "sg:phone":"+44 1473 400271",
    "sg:postcode":"IP3 9ND",
    "sg:province":"Suffolk",
    "sg:tags":[
        "electrical"
    ],
    "wof:name":"Suffolk Domestic Aplliances",
    "wof:placetype":"venue"
},
  "geometry": {"coordinates":[1.187829,52.038223],"type":"Point"}
}