{
  "type": "Feature",
  "properties": {
    "addr:full":"Devon House Water Street Menai Bridge Isle of Anglesey LL59 5DD",
    "addr:postcode":"ll59 5dd",
    "addr:street":"Water Street",
    "iso:country":"GB",
    "sg:address":"Devon House Water Street",
    "sg:city":"Menai Bridge",
    "sg:classifiers":[
        {
            "category":"Recreation",
            "subcategory":"Fishing",
            "type":"Entertainment"
        }
    ],
    "sg:phone":"+44 1248 712700",
    "sg:postcode":"LL59 5DD",
    "sg:province":"Isle of Anglesey",
    "sg:tags":[
        "angling"
    ],
    "wof:name":"Ken Johnson",
    "wof:placetype":"venue"
},
  "geometry": {"coordinates":[-4.1627340317,53.2256965637],"type":"Point"}
}