{
  "type": "Feature",
  "properties": {
    "iso:country":"GB",
    "sg:address":"10 Copeman Road, Aylsham",
    "sg:city":"Norwich",
    "sg:classifiers":[
        {
            "category":"Military Area",
            "subcategory":"Air Force Base",
            "type":"Public Place"
        }
    ],
    "sg:phone":"+44 1263 735573",
    "sg:postcode":"NR11 6JL",
    "sg:province":"Norfolk",
    "sg:tags":[
        "taxi",
        "hire",
        "private"
    ],
    "wof:name":"Trust Taxis",
    "wof:placetype":"venue"
},
  "geometry": {"coordinates":[1.2552169561,52.7875595093],"type":"Point"}
}