{
  "type": "Feature",
  "properties": {
    "addr:full":"24 Boston Road Spilsby Lincolnshire PE23 5HG",
    "addr:housenumber":"24",
    "addr:postcode":"pe23 5hg",
    "addr:street":"Boston Road",
    "iso:country":"GB",
    "sg:address":"24 Boston Road",
    "sg:city":"Spilsby",
    "sg:classifiers":[
        {
            "category":"Food & Beverages",
            "subcategory":"Groceries & Convenience Stores",
            "type":"Retail Goods"
        }
    ],
    "sg:phone":"+44 1790 753516",
    "sg:postcode":"PE23 5HG",
    "sg:province":"Lincolnshire",
    "wof:name":"Boston Road Stores",
    "wof:placetype":"venue"
},
  "geometry": {"coordinates":[0.093141,53.171497],"type":"Point"}
}