{
  "type": "Feature",
  "properties": {
    "addr:full":"64 Malling Rd Snodland Kent ME6 5NB",
    "addr:housenumber":"64",
    "addr:postcode":"me6 5nb",
    "addr:street":"Malling Rd",
    "iso:country":"GB",
    "sg:address":"64 Malling Rd",
    "sg:city":"Snodland",
    "sg:classifiers":[
        {
            "category":"Insurance",
            "subcategory":"Insurance Agent",
            "type":"Services"
        }
    ],
    "sg:phone":"+44 1634 249572",
    "sg:postcode":"ME6 5NB",
    "sg:province":"Kent",
    "sg:tags":[
        "broker"
    ],
    "wof:name":"Coopers Insurance Associates",
    "wof:placetype":"venue"
},
  "geometry": {"coordinates":[0.441601,51.328564],"type":"Point"}
}