{
  "type": "Feature",
  "properties": {
    "iso:country":"GB",
    "sg:address":"205 Marine Road",
    "sg:city":"Morecambe",
    "sg:classifiers":[
        {
            "category":"Shopping",
            "subcategory":"Shoes",
            "type":"Retail Goods"
        }
    ],
    "sg:phone":"+44 1524 419293",
    "sg:postcode":"LA4 4PU",
    "sg:province":"Lancashire",
    "sg:tags":[
        "shop"
    ],
    "wof:name":"Briggs & Shoe Mines",
    "wof:placetype":"venue"
},
  "geometry": {"coordinates":[-2.849963,54.076885],"type":"Point"}
}