{
  "type": "Feature",
  "properties": {
    "addr:full":"Unit 2, Yard 2, Stricklandgate Kendal Cumbria LA9 4ND",
    "addr:housenumber":"unit 2;2",
    "addr:postcode":"la9 4nd",
    "addr:street":"Yard;Stricklandgate",
    "iso:country":"GB",
    "sg:address":"Unit 2, Yard 2, Stricklandgate",
    "sg:city":"Kendal",
    "sg:classifiers":[
        {
            "category":"Cafe",
            "type":"Food & Drink"
        }
    ],
    "sg:postcode":"LA9 4ND",
    "sg:province":"Cumbria",
    "sg:tags":[
        "tea",
        "room"
    ],
    "wof:name":"Internet Cafe (The)",
    "wof:placetype":"venue"
},
  "geometry": {"coordinates":[-2.7480840683,54.3240013123],"type":"Point"}
}