{
  "type": "Feature",
  "properties": {
    "addr:full":"125 Netherhampton Road Salisbury Wiltshire SP2 8NA",
    "addr:housenumber":"125",
    "addr:postcode":"sp2 8na",
    "addr:street":"Netherhampton Road",
    "iso:country":"GB",
    "sg:address":"125 Netherhampton Road",
    "sg:city":"Salisbury",
    "sg:classifiers":[
        {
            "category":"Home & Garden",
            "subcategory":"Building Materials",
            "type":"Retail Goods"
        }
    ],
    "sg:postcode":"SP2 8NA",
    "sg:province":"Wiltshire",
    "sg:tags":[
        "furnishers",
        "bathroom",
        "planner"
    ],
    "wof:name":"Derek T Symes Spire Bathrooms",
    "wof:placetype":"venue"
},
  "geometry": {"coordinates":[-1.8168799877,51.0617218018],"type":"Point"}
}