{
  "type": "Feature",
  "properties": {
    "addr:full":"1/2 Knighton Chambers, 39 Aldwick Road Bognor Regis West Sussex PO21 2LN",
    "addr:housenumber":"1 / 2;39",
    "addr:postcode":"po21 2ln",
    "addr:street":"Aldwick Road",
    "iso:country":"GB",
    "sg:address":"1/2 Knighton Chambers, 39 Aldwick Road",
    "sg:city":"Bognor Regis",
    "sg:classifiers":[
        {
            "category":"Professional",
            "subcategory":"Management & Consulting",
            "type":"Services"
        },
        {
            "category":"Professional",
            "subcategory":"Business Services",
            "type":"Services"
        }
    ],
    "sg:phone":"+44 1243 841034",
    "sg:postcode":"PO21 2LN",
    "sg:province":"West Sussex",
    "sg:tags":[
        "house",
        "public",
        "pub"
    ],
    "wof:name":"Southern Counties Taverns Ltd",
    "wof:placetype":"venue"
},
  "geometry": {"coordinates":[-0.6753489971,50.7829666138],"type":"Point"}
}