{
  "type": "Feature",
  "properties": {
    "addr:full":"Higher Down Road Torquay Devon TQ1 3LD",
    "addr:postcode":"tq1 3ld",
    "addr:street":"Down Road",
    "iso:country":"GB",
    "sg:address":"Higher Down Road",
    "sg:city":"Torquay",
    "sg:classifiers":[
        {
            "category":"Travel",
            "subcategory":"Hotels & Motels",
            "type":"Entertainment"
        }
    ],
    "sg:phone":"+44 1803 327637",
    "sg:postcode":"TQ1 3LD",
    "sg:province":"Devon",
    "wof:name":"Blue Conifer Hotel",
    "wof:placetype":"venue"
},
  "geometry": {"coordinates":[-3.5191268921,50.4814834595],"type":"Point"}
}