{
  "type": "Feature",
  "properties": {
    "addr:full":"31 Glebeside Clo Worthing West Sussex BN14 7NU",
    "addr:housenumber":"31",
    "addr:postcode":"bn14 7nu",
    "addr:street":"Glebeside Clo Worthing",
    "iso:country":"GB",
    "sg:address":"31 Glebeside Clo",
    "sg:city":"Worthing",
    "sg:classifiers":[
        {
            "category":"Retail",
            "subcategory":"Driving School",
            "type":"Services"
        }
    ],
    "sg:phone":"+44 1903 821754",
    "sg:postcode":"BN14 7NU",
    "sg:province":"West Sussex",
    "wof:name":"Daves Driving School",
    "wof:placetype":"venue"
},
  "geometry": {"coordinates":[-0.389447,50.826633],"type":"Point"}
}