{
  "type": "Feature",
  "properties": {
    "iso:country":"GB",
    "sg:address":"Park Street Surgery, Park Street",
    "sg:city":"Bootle",
    "sg:classifiers":[
        {
            "category":"Health Services",
            "subcategory":"Doctor",
            "type":"Services"
        }
    ],
    "sg:phone":"+44 151 944 1090",
    "sg:postcode":"L20 3RF",
    "sg:province":"Merseyside",
    "sg:tags":[
        "practitioners"
    ],
    "wof:name":"Stanley Chung & Maier",
    "wof:placetype":"venue"
},
  "geometry": {"coordinates":[-2.985541,53.450283],"type":"Point"}
}