{
  "type": "Feature",
  "properties": {
    "iso:country":"GB",
    "sg:address":"London Rd, Welwyn-by-pass",
    "sg:city":"Welwyn",
    "sg:classifiers":[
        {
            "category":"Autos & Motor Vehicles",
            "subcategory":"Fuel & Gas Station",
            "type":"Retail Goods"
        }
    ],
    "sg:phone":"+44 1438 714258",
    "sg:postcode":"AL6 9DJ",
    "sg:province":"Hertfordshire",
    "sg:tags":[
        "hr",
        "petrol"
    ],
    "wof:name":"Nodeway Filling Station",
    "wof:placetype":"venue"
},
  "geometry": {"coordinates":[-0.214939,51.828648],"type":"Point"}
}