{
  "type": "Feature",
  "properties": {
    "addr:full":"3-4 Dynevor Terrace, Pontardawe Swansea Neath Port Talbot SA8 4HY",
    "addr:housenumber":"3-4",
    "addr:postcode":"sa8 4hy",
    "addr:street":"Dynevor Terrace",
    "iso:country":"GB",
    "sg:address":"3-4 Dynevor Terrace, Pontardawe",
    "sg:city":"Swansea",
    "sg:classifiers":[
        {
            "category":"Professional",
            "subcategory":"Lawyer & Legal Services",
            "type":"Services"
        }
    ],
    "sg:phone":"+44 1792 862334",
    "sg:postcode":"SA8 4HY",
    "sg:province":"Neath Port Talbot",
    "sg:tags":[
        "solicitor"
    ],
    "wof:name":"D R James & Son",
    "wof:placetype":"venue"
},
  "geometry": {"coordinates":[-3.852785,51.721085],"type":"Point"}
}