{
  "type": "Feature",
  "properties": {
    "iso:country":"GB",
    "sg:address":"34 Charles Street",
    "sg:city":"Kettering",
    "sg:classifiers":[
        {
            "category":"Shopping",
            "subcategory":"Music",
            "type":"Retail Goods"
        }
    ],
    "sg:postcode":"NN16 9RN",
    "sg:province":"Northamptonshire",
    "sg:tags":[
        "record",
        "tape",
        "cd"
    ],
    "wof:name":"Barry Simcoe Records",
    "wof:placetype":"venue"
},
  "geometry": {"coordinates":[-0.72665,52.408947],"type":"Point"}
}