{
  "type": "Feature",
  "properties": {
    "addr:full":"The White House Chipping Norton Gloucestershire OX7 5QH",
    "addr:postcode":"ox7 5qh",
    "iso:country":"GB",
    "sg:address":"The White House",
    "sg:city":"Chipping Norton",
    "sg:classifiers":[
        {
            "category":"Manufacturing",
            "subcategory":"Signs",
            "type":"Manufacturing & Wholesale Goods"
        }
    ],
    "sg:phone":"+44 1608 683999",
    "sg:postcode":"OX7 5QH",
    "sg:province":"Gloucestershire",
    "sg:tags":[
        "marquee"
    ],
    "wof:name":"Ascot Event Hire Ltd.",
    "wof:placetype":"venue"
},
  "geometry": {"coordinates":[-1.545912981,51.9404067993],"type":"Point"}
}