{
  "type": "Feature",
  "properties": {
    "addr:full":"Cherry Trees, 8 Webb Avenue, Perton Wolverhampton Shropshire WV6 7YH",
    "addr:housenumber":"8",
    "addr:postcode":"wv6 7yh",
    "addr:street":"Webb Avenue",
    "iso:country":"GB",
    "sg:address":"Cherry Trees, 8 Webb Avenue, Perton",
    "sg:city":"Wolverhampton",
    "sg:classifiers":[
        {
            "category":"Arena",
            "subcategory":"Sports Club",
            "type":"Entertainment"
        }
    ],
    "sg:phone":"+44 1902 750964",
    "sg:postcode":"WV6 7YH",
    "sg:province":"Shropshire",
    "wof:name":"Adventure Divers",
    "wof:placetype":"venue"
},
  "geometry": {"coordinates":[-2.2020730972,52.5980491638],"type":"Point"}
}