{
  "type": "Feature",
  "properties": {
    "addr:full":"Mermagen House, Vicarage St, Painswick Stroud Gloucestershire GL6 6XS",
    "addr:postcode":"gl6 6xs",
    "addr:street":"Vicarage St",
    "iso:country":"GB",
    "sg:address":"Mermagen House, Vicarage St, Painswick",
    "sg:city":"Stroud",
    "sg:classifiers":[
        {
            "category":"Professional",
            "subcategory":"Secretarial Services",
            "type":"Services"
        }
    ],
    "sg:phone":"+44 1452 812775",
    "sg:postcode":"GL6 6XS",
    "sg:province":"Gloucestershire",
    "wof:name":"Cotswold Secretarial Services",
    "wof:placetype":"venue"
},
  "geometry": {"coordinates":[-2.1919639111,51.7860565186],"type":"Point"}
}