{
  "type": "Feature",
  "properties": {
    "addr:full":"140 St Johns Wood, High Street London Greater London NW8 7SE",
    "addr:housenumber":"140",
    "addr:postcode":"nw8 7se",
    "addr:street":"St Johns Wood High Street",
    "iso:country":"GB",
    "sg:address":"140 St Johns Wood, High Street",
    "sg:city":"London",
    "sg:classifiers":[
        {
            "category":"Retail",
            "subcategory":"Photofinishing",
            "type":"Services"
        },
        {
            "category":"Cinema",
            "subcategory":"Movie Rental",
            "type":"Entertainment"
        }
    ],
    "sg:phone":"+44 20 7586 7586",
    "sg:postcode":"NW8 7SE",
    "sg:province":"Greater London",
    "sg:tags":[
        "video",
        "photographic",
        "processor",
        "library"
    ],
    "wof:name":"Questcharm Ltd.",
    "wof:placetype":"venue"
},
  "geometry": {"coordinates":[-0.171058,51.533989],"type":"Point"}
}