{
  "type": "Feature",
  "properties": {
    "addr:full":"Gas Technology Ltd, Ocean Park House, East Tyndall St Cardiff Cardiff CF24 5GT",
    "addr:housenumber":"ocean",
    "addr:postcode":"cf24 5gt",
    "addr:street":"House East Tyndall St",
    "iso:country":"GB",
    "sg:address":"Gas Technology Ltd, Ocean Park House, East Tyndall St",
    "sg:city":"Cardiff",
    "sg:classifiers":[
        {
            "category":"Professional",
            "subcategory":"Engineering",
            "type":"Services"
        },
        {
            "category":"Utilities",
            "subcategory":"Natural Gas",
            "type":"Services"
        }
    ],
    "sg:phone":"+44 29 2045 4864",
    "sg:postcode":"CF24 5GT",
    "sg:province":"Cardiff",
    "sg:tags":[
        "consulting",
        "engineer"
    ],
    "wof:name":"Gas Technology Ltd",
    "wof:placetype":"venue"
},
  "geometry": {"coordinates":[-3.1553859711,51.4796676636],"type":"Point"}
}