{
  "type": "Feature",
  "properties": {
    "iso:country":"GB",
    "sg:address":"Selside Farm, Horton In Ribblesdale",
    "sg:city":"Settle",
    "sg:classifiers":[
        {
            "category":"Farming",
            "subcategory":"Livestock Farm",
            "type":"Manufacturing & Wholesale Goods"
        }
    ],
    "sg:postcode":"BD24 0HZ",
    "sg:province":"North Yorkshire",
    "sg:tags":[
        "others"
    ],
    "wof:name":"W & A Lambert & Son",
    "wof:placetype":"venue"
},
  "geometry": {"coordinates":[-2.327187,54.172188],"type":"Point"}
}