{
  "type": "Feature",
  "properties": {
    "iso:country":"GB",
    "sg:address":"Tanner House, Tanner Street",
    "sg:city":"Thetford",
    "sg:classifiers":[
        {
            "category":"Education",
            "subcategory":"University",
            "type":"Public Place"
        },
        {
            "category":"Education",
            "subcategory":"School",
            "type":"Public Place"
        },
        {
            "category":"Government",
            "subcategory":"Office",
            "type":"Public Place"
        }
    ],
    "sg:phone":"+44 1842 755492",
    "sg:postcode":"IP24 2BQ",
    "sg:province":"Norfolk",
    "sg:tags":[
        "local",
        "adult",
        "authority"
    ],
    "wof:name":"NORFOLK COUNTY COUNCIL",
    "wof:placetype":"venue"
},
  "geometry": {"coordinates":[0.748239994,52.4138946533],"type":"Point"}
}