{
  "type": "Feature",
  "properties": {
    "iso:country":"GB",
    "sg:address":"The Moot Hall, Market Square",
    "sg:city":"Daventry",
    "sg:classifiers":[
        {
            "category":"Museum",
            "subcategory":"Art Museum",
            "type":"Entertainment"
        }
    ],
    "sg:phone":"+44 1327 302463",
    "sg:postcode":"NN11 4BH",
    "sg:province":"Northamptonshire",
    "sg:tags":[
        "gallery"
    ],
    "wof:name":"Daventry Museum",
    "wof:placetype":"venue"
},
  "geometry": {"coordinates":[-1.162239,52.260433],"type":"Point"}
}