{
  "type": "Feature",
  "properties": {
    "addr:full":"Dorking Road, Kingsfold Horsham West Sussex RH12 3SB",
    "addr:postcode":"rh12 3sb",
    "addr:street":"Dorking Road Kingsfold",
    "iso:country":"GB",
    "sg:address":"Dorking Road, Kingsfold",
    "sg:city":"Horsham",
    "sg:classifiers":[
        {
            "category":"Wholesale",
            "subcategory":"Vending Machines",
            "type":"Manufacturing & Wholesale Goods"
        }
    ],
    "sg:phone":"+44 1306 627051",
    "sg:postcode":"RH12 3SB",
    "sg:province":"West Sussex",
    "sg:tags":[
        "sale"
    ],
    "wof:name":"Quickmate Vending",
    "wof:placetype":"venue"
},
  "geometry": {"coordinates":[-0.3396750093,51.0988502502],"type":"Point"}
}