{
  "type": "Feature",
  "properties": {
    "addr:full":"76 Cheriton Road Folkestone Kent CT20 1DG",
    "addr:housenumber":"76",
    "addr:postcode":"ct20 1dg",
    "addr:street":"Cheriton Road",
    "iso:country":"GB",
    "sg:address":"76 Cheriton Road",
    "sg:city":"Folkestone",
    "sg:classifiers":[
        {
            "category":"Travel",
            "subcategory":"Hotels & Motels",
            "type":"Entertainment"
        }
    ],
    "sg:phone":"+44 1303 259661",
    "sg:postcode":"CT20 1DG",
    "sg:province":"Kent",
    "sg:tags":[
        "house",
        "guest"
    ],
    "wof:name":"Kentmere Guest House",
    "wof:placetype":"venue"
},
  "geometry": {"coordinates":[1.173655,51.081291],"type":"Point"}
}