{
  "type": "Feature",
  "properties": {
    "iso:country":"GB",
    "sg:address":"Livingston House, 213 Chester Road, Helsby",
    "sg:city":"Warrington",
    "sg:classifiers":[
        {
            "category":"Professional",
            "subcategory":"Engineering",
            "type":"Services"
        }
    ],
    "sg:phone":"+44 1928 727066",
    "sg:postcode":"WA6 0DA",
    "sg:province":"Cheshire",
    "sg:tags":[
        "design",
        "engineer"
    ],
    "wof:name":"Livingston Gunn Projects Ltd.",
    "wof:placetype":"venue"
},
  "geometry": {"coordinates":[-2.769151,53.273987],"type":"Point"}
}