{
  "type": "Feature",
  "properties": {
    "addr:full":"Botley Mills, High Street, Botley Southampton Hampshire SO30 2GB",
    "addr:postcode":"so30 2gb",
    "addr:street":"High Street",
    "iso:country":"GB",
    "sg:address":"Botley Mills, High Street, Botley",
    "sg:city":"Southampton",
    "sg:classifiers":[
        {
            "category":"Professional",
            "subcategory":"Detective & Security Services",
            "type":"Services"
        }
    ],
    "sg:postcode":"SO30 2GB",
    "sg:province":"Hampshire",
    "wof:name":"J A Jerome",
    "wof:placetype":"venue"
},
  "geometry": {"coordinates":[-1.270219,50.914333],"type":"Point"}
}