{
  "type": "Feature",
  "properties": {
    "addr:full":"28a Durham Road Stockton-on-tees Durham TS19 0BS",
    "addr:housenumber":"28a",
    "addr:postcode":"ts19 0bs",
    "addr:street":"Durham Road",
    "iso:country":"GB",
    "sg:address":"28a Durham Road",
    "sg:city":"Stockton-on-tees",
    "sg:classifiers":[
        {
            "category":"Autos & Motor Vehicles",
            "subcategory":"Automobile Sales",
            "type":"Retail Goods"
        }
    ],
    "sg:postcode":"TS19 0BS",
    "sg:province":"Durham",
    "sg:tags":[
        "car"
    ],
    "wof:name":"A D M Car & Commercial",
    "wof:placetype":"venue"
},
  "geometry": {"coordinates":[-1.320119,54.56979],"type":"Point"}
}