{
  "type": "Feature",
  "properties": {
    "iso:country":"GB",
    "sg:address":"Front Street, Ringwould",
    "sg:city":"Deal",
    "sg:classifiers":[
        {
            "category":"Bars & Pubs",
            "type":"Food & Drink"
        }
    ],
    "sg:phone":"+44 1304 373489",
    "sg:postcode":"CT14 8HP",
    "sg:province":"Kent",
    "sg:tags":[
        "pubs",
        "inn"
    ],
    "wof:name":"The Five Bells",
    "wof:placetype":"venue"
},
  "geometry": {"coordinates":[1.37522,51.183811],"type":"Point"}
}