{
  "type": "Feature",
  "properties": {
    "addr:full":"165 Newland Park Hull East Riding of Yorkshire HU5 2DX",
    "addr:housenumber":"165",
    "addr:postcode":"hu5 2dx",
    "addr:street":"Newland Park",
    "iso:country":"GB",
    "sg:address":"165 Newland Park",
    "sg:city":"Hull",
    "sg:classifiers":[
        {
            "category":"Professional",
            "subcategory":"Computer Services",
            "type":"Services"
        }
    ],
    "sg:phone":"+44 1482 346284",
    "sg:postcode":"HU5 2DX",
    "sg:province":"East Riding of Yorkshire",
    "sg:tags":[
        "consultant"
    ],
    "wof:name":"John Porter",
    "wof:placetype":"venue"
},
  "geometry": {"coordinates":[-0.3722189963,53.7686309814],"type":"Point"}
}