{
  "type": "Feature",
  "properties": {
    "iso:country":"GB",
    "sg:address":"English Walls",
    "sg:city":"Oswestry",
    "sg:classifiers":[
        {
            "category":"Food & Beverages",
            "subcategory":"Supermarket",
            "type":"Retail Goods"
        }
    ],
    "sg:phone":"+44 1691 654236",
    "sg:postcode":"SY11 2PA",
    "sg:province":"Shropshire",
    "wof:name":"Kwik Save Foodstores",
    "wof:placetype":"venue"
},
  "geometry": {"coordinates":[-3.054334,52.858521],"type":"Point"}
}