{
  "type": "Feature",
  "properties": {
    "iso:country":"GB",
    "sg:address":"Ystrad Road",
    "sg:city":"Pentre",
    "sg:classifiers":[
        {
            "category":"Bars & Pubs",
            "type":"Food & Drink"
        }
    ],
    "sg:phone":"+44 1443 441691",
    "sg:postcode":"CF41 7PP",
    "sg:province":"Rhondda, Cynon, Taff",
    "sg:tags":[
        "pubs",
        "inn"
    ],
    "wof:name":"The Railway Inn",
    "wof:placetype":"venue"
},
  "geometry": {"coordinates":[-3.475154,51.646439],"type":"Point"}
}