{
  "type": "Feature",
  "properties": {
    "addr:full":"Priory Vicarage Church Terrace, Monkton Pembroke Pembrokeshire SA71 4LW",
    "addr:postcode":"sa71 4lw",
    "addr:street":"Church Terrace",
    "iso:country":"GB",
    "sg:address":"Priory Vicarage Church Terrace, Monkton",
    "sg:city":"Pembroke",
    "sg:classifiers":[
        {
            "category":"Place Of Worship",
            "type":"Public Place"
        }
    ],
    "sg:phone":"+44 1646 682723",
    "sg:postcode":"SA71 4LW",
    "sg:province":"Pembrokeshire",
    "wof:name":"The Priory Church",
    "wof:placetype":"venue"
},
  "geometry": {"coordinates":[-4.915889,51.674725],"type":"Point"}
}