{
  "type": "Feature",
  "properties": {
    "iso:country":"GB",
    "sg:address":"105 Brighton Rd",
    "sg:city":"Purley",
    "sg:classifiers":[
        {
            "category":"Professional",
            "subcategory":"Lawyer & Legal Services",
            "type":"Services"
        }
    ],
    "sg:phone":"+44 20 8660 6800",
    "sg:postcode":"CR8 4HD",
    "sg:province":"Surrey",
    "sg:tags":[
        "advice",
        "counselling"
    ],
    "wof:name":"Citizens Advice Bureau",
    "wof:placetype":"venue"
},
  "geometry": {"coordinates":[-0.124136,51.331951],"type":"Point"}
}