{
  "type": "Feature",
  "properties": {
    "iso:country":"GB",
    "sg:address":"1 Lee Lane, Kirkburton",
    "sg:city":"Huddersfield",
    "sg:classifiers":[
        {
            "category":"Building & Trades",
            "subcategory":"Construction",
            "type":"Services"
        },
        {
            "category":"Building & Trades",
            "subcategory":"Pest Control",
            "type":"Services"
        }
    ],
    "sg:phone":"+44 1484 605150",
    "sg:postcode":"HD8 0PG",
    "sg:province":"South Yorkshire",
    "sg:tags":[
        "equipment",
        "hire",
        "crane",
        "sales"
    ],
    "wof:name":"Bandshire Crane Hire",
    "wof:placetype":"venue"
},
  "geometry": {"coordinates":[-1.712926,53.609509],"type":"Point"}
}