{
  "type": "Feature",
  "properties": {
    "iso:country":"GB",
    "sg:address":"Unit 12 Rother Court",
    "sg:city":"Rotherham",
    "sg:classifiers":[
        {
            "category":"Professional",
            "subcategory":"Engineering",
            "type":"Services"
        }
    ],
    "sg:phone":"+44 1709 522754",
    "sg:postcode":"S62 6DR",
    "sg:province":"South Yorkshire",
    "sg:tags":[
        "engineer"
    ],
    "wof:name":"Fluid Sealing & Engineering",
    "wof:placetype":"venue"
},
  "geometry": {"coordinates":[-1.348035,53.449711],"type":"Point"}
}