{
  "type": "Feature",
  "properties": {
    "iso:country":"GB",
    "sg:address":"12 Blue Chalet Studio West Kings, Down",
    "sg:city":"Sevenoaks",
    "sg:classifiers":[
        {
            "category":"Shopping",
            "subcategory":"Computers & Home Electronics",
            "type":"Retail Goods"
        }
    ],
    "sg:phone":"+44 1474 852963",
    "sg:postcode":"TN15 6BQ",
    "sg:province":"Kent",
    "sg:tags":[
        "electrical"
    ],
    "wof:name":"Advanced Coilwinding Equipment Ltd.",
    "wof:placetype":"venue"
},
  "geometry": {"coordinates":[0.25136,51.352829],"type":"Point"}
}