{
  "type": "Feature",
  "properties": {
    "iso:country":"GB",
    "sg:address":"328 New Cross Rd",
    "sg:city":"New Cross",
    "sg:classifiers":[
        {
            "category":"Taxi",
            "type":"Transportation"
        }
    ],
    "sg:phone":"+44 20 8694 6688",
    "sg:postcode":"SE14 6AG",
    "sg:province":"Greater London",
    "sg:tags":[
        "mini",
        "cab"
    ],
    "wof:name":"Continental Mini Cabs",
    "wof:placetype":"venue"
},
  "geometry": {"coordinates":[-0.035697,51.475582],"type":"Point"}
}