{
  "type": "Feature",
  "properties": {
    "iso:country":"GB",
    "sg:address":"6 Raleigh Walk, Brigantine Place",
    "sg:city":"Cardiff",
    "sg:classifiers":[
        {
            "category":"Professional",
            "subcategory":"Management & Consulting",
            "type":"Services"
        }
    ],
    "sg:postcode":"CF10 4LN",
    "sg:province":"Cardiff",
    "sg:tags":[
        "consultant",
        "business"
    ],
    "wof:name":"Keyplan Consulting Ltd",
    "wof:placetype":"venue"
},
  "geometry": {"coordinates":[-3.16874,51.475746],"type":"Point"}
}