{
  "type": "Feature",
  "properties": {
    "addr:full":"251 Alcester Road South, Kingsheath Birmingham West Midlands B14 6DT",
    "addr:housenumber":"251",
    "addr:postcode":"b14 6dt",
    "addr:street":"Alcester Road South",
    "iso:country":"GB",
    "sg:address":"251 Alcester Road South, Kingsheath",
    "sg:city":"Birmingham",
    "sg:classifiers":[
        {
            "category":"Military Area",
            "subcategory":"Air Force Base",
            "type":"Public Place"
        }
    ],
    "sg:phone":"+44 121 444 4266",
    "sg:postcode":"B14 6DT",
    "sg:province":"West Midlands",
    "sg:tags":[
        "magnet"
    ],
    "wof:name":"Master Magnets Ltd.",
    "wof:placetype":"venue"
},
  "geometry": {"coordinates":[-1.8920010328,52.4227905273],"type":"Point"}
}