{
  "type": "Feature",
  "properties": {
    "addr:full":"Phoenix Ho, Rushton Ave Bradford West Yorkshire BD3 7BH",
    "addr:postcode":"bd3 7bh",
    "addr:street":"Rushton Ave",
    "iso:country":"GB",
    "sg:address":"Phoenix Ho, Rushton Ave",
    "sg:city":"Bradford",
    "sg:classifiers":[
        {
            "category":"Professional",
            "subcategory":"Advertising",
            "type":"Services"
        }
    ],
    "sg:postcode":"BD3 7BH",
    "sg:province":"West Yorkshire",
    "sg:tags":[
        "mail",
        "direct"
    ],
    "wof:name":"Donovan,Judith,Associates Ltd",
    "wof:placetype":"venue"
},
  "geometry": {"coordinates":[-1.713,53.80106],"type":"Point"}
}