{
  "type": "Feature",
  "properties": {
    "addr:full":"8 Station Road Ossett West Yorkshire WF5 8AD",
    "addr:housenumber":"8",
    "addr:postcode":"wf5 8ad",
    "addr:street":"Station Road",
    "iso:country":"GB",
    "sg:address":"8 Station Road",
    "sg:city":"Ossett",
    "sg:classifiers":[
        {
            "category":"Social Services",
            "subcategory":"Job Training",
            "type":"Services"
        }
    ],
    "sg:phone":"+44 1924 271487",
    "sg:postcode":"WF5 8AD",
    "sg:province":"West Yorkshire",
    "sg:tags":[
        "draughtsman",
        "drawing"
    ],
    "wof:name":"Engineering Design Services",
    "wof:placetype":"venue"
},
  "geometry": {"coordinates":[-1.5785889626,53.6786613464],"type":"Point"}
}