{
  "type": "Feature",
  "properties": {
    "iso:country":"GB",
    "sg:address":"Evanton Place, Thornliebank",
    "sg:city":"Glasgow",
    "sg:classifiers":[
        {
            "category":"Home & Garden",
            "subcategory":"Carpets & Floor Coverings",
            "type":"Retail Goods"
        }
    ],
    "sg:phone":"+44 141 638 1134",
    "sg:postcode":"G46 8JD",
    "sg:province":"East Renfrewshire",
    "sg:tags":[
        "rubber",
        "plastic"
    ],
    "wof:name":"City Rubber Products Co. Ltd.",
    "wof:placetype":"venue"
},
  "geometry": {"coordinates":[-4.3233861923,55.803401947],"type":"Point"}
}