{
  "type": "Feature",
  "properties": {
    "addr:full":"24 Rose Street London Greater London WC2E 9EA",
    "addr:housenumber":"24",
    "addr:postcode":"wc2e 9ea",
    "addr:street":"Rose Street",
    "iso:country":"GB",
    "sg:address":"24 Rose Street",
    "sg:city":"London",
    "sg:classifiers":[
        {
            "category":"Professional",
            "subcategory":"Art Services",
            "type":"Services"
        }
    ],
    "sg:phone":"+44 20 7836 9638",
    "sg:postcode":"WC2E 9EA",
    "sg:province":"Greater London",
    "sg:tags":[
        "graphic",
        "designer"
    ],
    "wof:name":"S & M Art",
    "wof:placetype":"venue"
},
  "geometry": {"coordinates":[-0.1262889951,51.5118865967],"type":"Point"}
}