{
  "type": "Feature",
  "properties": {
    "iso:country":"GB",
    "sg:address":"Scampston Hall",
    "sg:city":"Malton",
    "sg:classifiers":[
        {
            "category":"Farming",
            "subcategory":"Farm",
            "type":"Manufacturing & Wholesale Goods"
        }
    ],
    "sg:phone":"+44 1944 758890",
    "sg:postcode":"YO17 8NG",
    "sg:province":"North Yorkshire",
    "sg:tags":[
        "mixed",
        "crop"
    ],
    "wof:name":"Scampston Farming Co. Ltd.",
    "wof:placetype":"venue"
},
  "geometry": {"coordinates":[-0.6813820004,54.1678237915],"type":"Point"}
}