{
  "type": "Feature",
  "properties": {
    "iso:country":"GB",
    "sg:address":"40 Windermere Road, Brymrock, Morriston",
    "sg:city":"Swansea",
    "sg:classifiers":[
        {
            "category":"Professional",
            "subcategory":"Detective & Security Services",
            "type":"Services"
        }
    ],
    "sg:phone":"+44 1792 795380",
    "sg:postcode":"SA6 7QE",
    "sg:province":"Swansea",
    "sg:tags":[
        "alarm",
        "burglar",
        "system"
    ],
    "wof:name":"Ultimate Security Systems",
    "wof:placetype":"venue"
},
  "geometry": {"coordinates":[-3.934806,51.659363],"type":"Point"}
}