{
  "type": "Feature",
  "properties": {
    "iso:country":"GB",
    "sg:address":"Bluebell Wood, Mobile Home Estate",
    "sg:city":"Canterbury",
    "sg:classifiers":[
        {
            "category":"Manufacturing",
            "subcategory":"Buildings",
            "type":"Manufacturing & Wholesale Goods"
        }
    ],
    "sg:phone":"+44 1227 710268",
    "sg:postcode":"CT2 0QA",
    "sg:province":"Kent",
    "sg:tags":[
        "mobile",
        "home"
    ],
    "wof:name":"Colin Saunders",
    "wof:placetype":"venue"
},
  "geometry": {"coordinates":[1.108692,51.305458],"type":"Point"}
}