{
  "type": "Feature",
  "properties": {
    "addr:full":"Cottage Farm, Little Blakenham Ipswich Suffolk IP8 4LZ",
    "addr:postcode":"ip8 4lz",
    "addr:street":"Blakenham",
    "iso:country":"GB",
    "sg:address":"Cottage Farm, Little Blakenham",
    "sg:city":"Ipswich",
    "sg:classifiers":[
        {
            "category":"Farming",
            "subcategory":"Dairy Farm",
            "type":"Manufacturing & Wholesale Goods"
        }
    ],
    "sg:phone":"+44 1473 830843",
    "sg:postcode":"IP8 4LZ",
    "sg:province":"Suffolk",
    "wof:name":"Blakenham Farms",
    "wof:placetype":"venue"
},
  "geometry": {"coordinates":[1.075649,52.096607],"type":"Point"}
}