{
  "type": "Feature",
  "properties": {
    "addr:full":"1 Kew Gardens Rd Richmond Greater London TW9 3HN",
    "addr:housenumber":"1",
    "addr:postcode":"tw9 3hn",
    "addr:street":"Kew Gardens Rd",
    "iso:country":"GB",
    "sg:address":"1 Kew Gardens Rd",
    "sg:city":"Richmond",
    "sg:classifiers":[
        {
            "category":"Health Services",
            "subcategory":"Doctor",
            "type":"Services"
        }
    ],
    "sg:phone":"+44 20 8940 1048",
    "sg:postcode":"TW9 3HN",
    "sg:province":"Greater London",
    "sg:tags":[
        "practitioners"
    ],
    "wof:name":"Drs Kirkbride Beales & Lawrence",
    "wof:placetype":"venue"
},
  "geometry": {"coordinates":[-0.2885420024,51.4803314209],"type":"Point"}
}