{
  "type": "Feature",
  "properties": {
    "addr:full":"166 Lincoln Rd Enfield Greater London EN1 1LN",
    "addr:housenumber":"166",
    "addr:postcode":"en1 1ln",
    "addr:street":"Lincoln Rd",
    "iso:country":"GB",
    "sg:address":"166 Lincoln Rd",
    "sg:city":"Enfield",
    "sg:classifiers":[
        {
            "category":"Retail",
            "subcategory":"Auto Repair",
            "type":"Services"
        }
    ],
    "sg:postcode":"EN1 1LN",
    "sg:province":"Greater London",
    "sg:tags":[
        "modification",
        "garage"
    ],
    "wof:name":"G & S Motor Services",
    "wof:placetype":"venue"
},
  "geometry": {"coordinates":[-0.0639579967,51.646320343],"type":"Point"}
}