{
  "type": "Feature",
  "properties": {
    "addr:full":"4 Saxony Way, Donington Spalding Lincolnshire PE11 4YA",
    "addr:housenumber":"4",
    "addr:postcode":"pe11 4ya",
    "addr:street":"Saxony Way",
    "iso:country":"GB",
    "sg:address":"4 Saxony Way, Donington",
    "sg:city":"Spalding",
    "sg:classifiers":[
        {
            "category":"Professional",
            "subcategory":"Business Services",
            "type":"Services"
        }
    ],
    "sg:phone":"+44 1775 822511",
    "sg:postcode":"PE11 4YA",
    "sg:province":"Lincolnshire",
    "sg:tags":[
        "food",
        "import",
        "export",
        "agent"
    ],
    "wof:name":"Langford Produce Merchants",
    "wof:placetype":"venue"
},
  "geometry": {"coordinates":[-0.1984429955,52.9025306702],"type":"Point"}
}