{
  "type": "Feature",
  "properties": {
    "addr:full":"27 Heywood Drive Luton Bedfordshire LU2 7LW",
    "addr:housenumber":"27",
    "addr:postcode":"lu2 7lw",
    "addr:street":"Heywood Drive",
    "iso:country":"GB",
    "sg:address":"27 Heywood Drive",
    "sg:city":"Luton",
    "sg:classifiers":[
        {
            "category":"Home & Garden",
            "subcategory":"Building Materials",
            "type":"Retail Goods"
        }
    ],
    "sg:postcode":"LU2 7LW",
    "sg:province":"Bedfordshire",
    "sg:tags":[
        "furnishers",
        "bathroom",
        "planner"
    ],
    "wof:name":"D J Coakley & Co",
    "wof:placetype":"venue"
},
  "geometry": {"coordinates":[-0.408136,51.894199],"type":"Point"}
}