{
  "type": "Feature",
  "properties": {
    "addr:full":"Smithymoor Farm, Stanton Ashbourne Derbyshire DE6 2DD",
    "addr:housenumber":"stanton",
    "addr:postcode":"de6 2dd",
    "iso:country":"GB",
    "sg:address":"Smithymoor Farm, Stanton",
    "sg:city":"Ashbourne",
    "sg:classifiers":[
        {
            "category":"Farming",
            "subcategory":"Dairy Farm",
            "type":"Manufacturing & Wholesale Goods"
        }
    ],
    "sg:phone":"+44 1335 324293",
    "sg:postcode":"DE6 2DD",
    "sg:province":"Derbyshire",
    "wof:name":"E G Capener",
    "wof:placetype":"venue"
},
  "geometry": {"coordinates":[-1.812016,53.011837],"type":"Point"}
}