{
  "type": "Feature",
  "properties": {
    "addr:full":"Redford Farm Laurencekirk Aberdeenshire AB30 1HS",
    "addr:postcode":"ab30 1hs",
    "iso:country":"GB",
    "sg:address":"Redford Farm",
    "sg:city":"Laurencekirk",
    "sg:classifiers":[
        {
            "category":"Farming",
            "subcategory":"Livestock Farm",
            "type":"Manufacturing & Wholesale Goods"
        }
    ],
    "sg:postcode":"AB30 1HS",
    "sg:province":"Aberdeenshire",
    "sg:tags":[
        "others"
    ],
    "wof:name":"Fearn's",
    "wof:placetype":"venue"
},
  "geometry": {"coordinates":[-2.4693739414,56.8306617737],"type":"Point"}
}