{
  "type": "Feature",
  "properties": {
    "iso:country":"GB",
    "sg:address":"15 Bedford Street",
    "sg:city":"Norwich",
    "sg:classifiers":[
        {
            "category":"Travel",
            "subcategory":"Travel Agent",
            "type":"Entertainment"
        }
    ],
    "sg:phone":"+44 1603 627224",
    "sg:postcode":"NR2 1AR",
    "sg:province":"Norfolk",
    "wof:name":"Travel Centre (Norwich)",
    "wof:placetype":"venue"
},
  "geometry": {"coordinates":[1.294575,52.629883],"type":"Point"}
}