{
  "type": "Feature",
  "properties": {
    "addr:full":"The Square, Barnack Stamford Cambridgeshire PE9 3EA",
    "addr:postcode":"pe9 3ea",
    "addr:street":"The Square",
    "iso:country":"GB",
    "sg:address":"The Square, Barnack",
    "sg:city":"Stamford",
    "sg:classifiers":[
        {
            "category":"Bars & Pubs",
            "type":"Food & Drink"
        },
        {
            "category":"Community Center",
            "subcategory":"Social",
            "type":"Public Place"
        }
    ],
    "sg:postcode":"PE9 3EA",
    "sg:province":"Cambridgeshire",
    "sg:tags":[
        "pubs",
        "house",
        "inn",
        "activity"
    ],
    "wof:name":"A G ORD",
    "wof:placetype":"venue"
},
  "geometry": {"coordinates":[-0.409224987,52.6322059631],"type":"Point"}
}