{
  "type": "Feature",
  "properties": {
    "addr:full":"63 Northfield Rd Waltham Cross Essex EN8 7RF",
    "addr:housenumber":"63",
    "addr:postcode":"en8 7rf",
    "addr:street":"Northfield Rd;Cross",
    "iso:country":"GB",
    "sg:address":"63 Northfield Rd",
    "sg:city":"Waltham Cross",
    "sg:classifiers":[
        {
            "category":"Professional",
            "type":"Services"
        }
    ],
    "sg:phone":"+44 1992 626517",
    "sg:postcode":"EN8 7RF",
    "sg:province":"Essex",
    "sg:tags":[
        "reflexologists"
    ],
    "wof:name":"P Drummond",
    "wof:placetype":"venue"
},
  "geometry": {"coordinates":[-0.03014,51.693733],"type":"Point"}
}