{
  "type": "Feature",
  "properties": {
    "iso:country":"GB",
    "sg:address":"35 The Beeches, Milwr",
    "sg:city":"Holywell",
    "sg:classifiers":[
        {
            "category":"Building & Trades",
            "subcategory":"Construction",
            "type":"Services"
        }
    ],
    "sg:postcode":"CH8 7SW",
    "sg:province":"Denbighshire",
    "sg:tags":[
        "builder"
    ],
    "wof:name":"Ian Lewis Moorcroft Building Services",
    "wof:placetype":"venue"
},
  "geometry": {"coordinates":[-3.21673,53.264561],"type":"Point"}
}