{
  "type": "Feature",
  "properties": {
    "addr:full":"Unit H10a, Chester Enterprise Centre Chester Cheshire CH2 3NE",
    "addr:housenumber":"h10a",
    "addr:postcode":"ch2 3ne",
    "addr:street":"Chester;Chester",
    "iso:country":"GB",
    "sg:address":"Unit H10a, Chester Enterprise Centre",
    "sg:city":"Chester",
    "sg:classifiers":[
        {
            "category":"Military Area",
            "subcategory":"Air Force Base",
            "type":"Public Place"
        }
    ],
    "sg:phone":"+44 1244 320020",
    "sg:postcode":"CH2 3NE",
    "sg:province":"Cheshire",
    "sg:tags":[
        "water",
        "treatment"
    ],
    "wof:name":"Airstream Environmental Ltd.",
    "wof:placetype":"venue"
},
  "geometry": {"coordinates":[-2.8796598911,53.1978416443],"type":"Point"}
}