{
  "type": "Feature",
  "properties": {
    "addr:full":"17 Old Court Place London Greater London W8 4PL",
    "addr:housenumber":"17",
    "addr:postcode":"w8 4pl",
    "addr:street":"Old Court Place",
    "iso:country":"GB",
    "sg:address":"17 Old Court Place",
    "sg:city":"London",
    "sg:classifiers":[
        {
            "category":"Education",
            "subcategory":"School",
            "type":"Public Place"
        }
    ],
    "sg:phone":"+44 20 7937 3858",
    "sg:postcode":"W8 4PL",
    "sg:province":"Greater London",
    "sg:tags":[
        "independent",
        "preparatory",
        "college"
    ],
    "wof:name":"Ashbourne Independent School Ltd.",
    "wof:placetype":"venue"
},
  "geometry": {"coordinates":[-0.1904730052,51.5028343201],"type":"Point"}
}