{
  "type": "Feature",
  "properties": {
    "addr:full":"St Giles Avenue Lincoln Lincolnshire LN2 4PE",
    "addr:postcode":"ln2 4pe",
    "addr:street":"St Giles Avenue",
    "iso:country":"GB",
    "sg:address":"St Giles Avenue",
    "sg:city":"Lincoln",
    "sg:classifiers":[
        {
            "category":"Arena",
            "subcategory":"Sports Club",
            "type":"Entertainment"
        }
    ],
    "sg:phone":"+44 1522 526592",
    "sg:postcode":"LN2 4PE",
    "sg:province":"Lincolnshire",
    "wof:name":"Lindum Sports Association",
    "wof:placetype":"venue"
},
  "geometry": {"coordinates":[-0.529703,53.23708],"type":"Point"}
}