{
  "type": "Feature",
  "properties": {
    "iso:country":"GB",
    "sg:address":"44 Marler Rd, Forest Hill",
    "sg:city":"Forest Hill",
    "sg:classifiers":[
        {
            "category":"Professional",
            "subcategory":"Detective & Security Services",
            "type":"Services"
        }
    ],
    "sg:phone":"+44 20 8699 1094",
    "sg:postcode":"SE23 2AD",
    "sg:province":"Greater London",
    "sg:tags":[
        "alarm",
        "burglar",
        "system"
    ],
    "wof:name":"Taylor C J",
    "wof:placetype":"venue"
},
  "geometry": {"coordinates":[-0.0377090015,51.440284729],"type":"Point"}
}