{
  "type": "Feature",
  "properties": {
    "iso:country":"GB",
    "sg:address":"102 Sprowston Mews",
    "sg:city":"London",
    "sg:classifiers":[
        {
            "category":"Retail",
            "subcategory":"Auto Repair",
            "type":"Services"
        }
    ],
    "sg:phone":"+44 20 8519 0194",
    "sg:postcode":"E7 9AE",
    "sg:province":"Greater London",
    "sg:tags":[
        "modification",
        "garage",
        "related"
    ],
    "wof:name":"M S Motors",
    "wof:placetype":"venue"
},
  "geometry": {"coordinates":[0.022802,51.546852],"type":"Point"}
}