{
  "type": "Feature",
  "properties": {
    "iso:country":"GB",
    "sg:address":"Reading Retail Park, 709-723 Oxford Rd",
    "sg:city":"Reading",
    "sg:classifiers":[
        {
            "category":"Shopping",
            "type":"Retail Goods"
        }
    ],
    "sg:phone":"+44 118 945 1477",
    "sg:postcode":"RG30 1PR",
    "sg:province":"Berkshire",
    "sg:tags":[
        "part",
        "accessory"
    ],
    "wof:name":"Halfords Garage Servicing",
    "wof:placetype":"venue"
},
  "geometry": {"coordinates":[-1.01393,51.4608],"type":"Point"}
}