{
  "type": "Feature",
  "properties": {
    "iso:country":"GB",
    "sg:address":"51 New St, Three Bridges Crawley",
    "sg:city":"Crawley",
    "sg:classifiers":[
        {
            "category":"Wholesale",
            "subcategory":"Scrap",
            "type":"Manufacturing & Wholesale Goods"
        }
    ],
    "sg:phone":"+44 1293 525287",
    "sg:postcode":"RH10 1LP",
    "sg:province":"Surrey",
    "sg:tags":[
        "waste",
        "metal"
    ],
    "wof:name":"G Holmwood",
    "wof:placetype":"venue"
},
  "geometry": {"coordinates":[-0.1658969969,51.1184577942],"type":"Point"}
}