{
  "type": "Feature",
  "properties": {
    "addr:full":"102 Fulham Palace Road London Greater London W6 9PL",
    "addr:housenumber":"102",
    "addr:postcode":"w6 9pl",
    "addr:street":"Fulham Palace Road",
    "iso:country":"GB",
    "sg:address":"102 Fulham Palace Road",
    "sg:city":"London",
    "sg:classifiers":[
        {
            "category":"Real Estate",
            "subcategory":"Developer",
            "type":"Services"
        }
    ],
    "sg:postcode":"W6 9PL",
    "sg:province":"Greater London",
    "sg:tags":[
        "property"
    ],
    "wof:name":"21ST Century Developments Ltd",
    "wof:placetype":"venue"
},
  "geometry": {"coordinates":[-0.222644,51.488026],"type":"Point"}
}