{
  "type": "Feature",
  "properties": {
    "iso:country":"GB",
    "sg:address":"Wickdown Avenue",
    "sg:city":"Swindon",
    "sg:classifiers":[
        {
            "category":"Real Estate",
            "subcategory":"Real Estate Agent",
            "type":"Services"
        },
        {
            "category":"Social Services",
            "subcategory":"Adult Care",
            "type":"Services"
        },
        {
            "category":"Government",
            "subcategory":"Office",
            "type":"Public Place"
        }
    ],
    "sg:phone":"+44 1793 616918",
    "sg:postcode":"SN25 3EB",
    "sg:province":"Wiltshire",
    "sg:tags":[
        "housing",
        "local",
        "sheltered"
    ],
    "wof:name":"Chilton Gardens",
    "wof:placetype":"venue"
},
  "geometry": {"coordinates":[-1.804454,51.58424],"type":"Point"}
}