{
  "type": "Feature",
  "properties": {
    "iso:country":"GB",
    "sg:address":"741 Market Street, Facit",
    "sg:city":"Rochdale",
    "sg:classifiers":[
        {
            "category":"Food & Beverages",
            "subcategory":"Bakery",
            "type":"Retail Goods"
        }
    ],
    "sg:phone":"+44 1706 852313",
    "sg:postcode":"OL12 8LD",
    "sg:province":"Lancashire",
    "sg:tags":[
        "baker"
    ],
    "wof:name":"Len's Bakery",
    "wof:placetype":"venue"
},
  "geometry": {"coordinates":[-2.1705539227,53.6685180664],"type":"Point"}
}