{
  "type": "Feature",
  "properties": {
    "addr:full":"Condell Road London Greater London SW8 4JB",
    "addr:postcode":"sw8 4jb",
    "addr:street":"Condell Road",
    "iso:country":"GB",
    "sg:address":"Condell Road",
    "sg:city":"London",
    "sg:classifiers":[
        {
            "category":"Education",
            "subcategory":"School",
            "type":"Public Place"
        }
    ],
    "sg:phone":"+44 20 7622 5108",
    "sg:postcode":"SW8 4JB",
    "sg:province":"Greater London",
    "sg:tags":[
        "local",
        "authority"
    ],
    "wof:name":"Sir James Barrie Primary School",
    "wof:placetype":"venue"
},
  "geometry": {"coordinates":[-0.1370709985,51.4745903015],"type":"Point"}
}