{
  "type": "Feature",
  "properties": {
    "iso:country":"GB",
    "sg:address":"9 Wide Bargate",
    "sg:city":"Boston",
    "sg:classifiers":[
        {
            "category":"Shopping",
            "subcategory":"Photographic Equipment",
            "type":"Retail Goods"
        }
    ],
    "sg:phone":"+44 1205 362454",
    "sg:postcode":"PE21 6RB",
    "sg:province":"Lincolnshire",
    "sg:tags":[
        "supply"
    ],
    "wof:name":"Addys (Boston) Ltd.",
    "wof:placetype":"venue"
},
  "geometry": {"coordinates":[-0.021945,52.979664],"type":"Point"}
}