{
  "type": "Feature",
  "properties": {
    "iso:country":"GB",
    "sg:address":"158 Garratt Lane",
    "sg:city":"London",
    "sg:classifiers":[
        {
            "category":"Taxi",
            "type":"Transportation"
        }
    ],
    "sg:phone":"+44 20 8870 9969",
    "sg:postcode":"SW18 4DA",
    "sg:province":"Greater London",
    "sg:tags":[
        "mini",
        "cab"
    ],
    "wof:name":"Instacars",
    "wof:placetype":"venue"
},
  "geometry": {"coordinates":[-0.189906,51.449306],"type":"Point"}
}