{
  "type": "Feature",
  "properties": {
    "iso:country":"GB",
    "sg:address":"10 Park Road",
    "sg:city":"Oxted",
    "sg:classifiers":[
        {
            "category":"Recreation",
            "subcategory":"Gun Range",
            "type":"Entertainment"
        }
    ],
    "sg:phone":"+44 1883 715360",
    "sg:postcode":"RH8 0AW",
    "sg:province":"Surrey",
    "sg:tags":[
        "operator",
        "tour"
    ],
    "wof:name":"Namaste Adventures",
    "wof:placetype":"venue"
},
  "geometry": {"coordinates":[0.001761,51.261776],"type":"Point"}
}