{
  "type": "Feature",
  "properties": {
    "iso:country":"GB",
    "sg:address":"Unit 1 Chesil Ho, Arrow Clo",
    "sg:city":"Eastleigh",
    "sg:classifiers":[
        {
            "category":"Food & Beverages",
            "subcategory":"Bakery",
            "type":"Retail Goods"
        }
    ],
    "sg:phone":"+44 23 8061 9909",
    "sg:postcode":"SO50 4SY",
    "sg:province":"Hampshire",
    "sg:tags":[
        "baker"
    ],
    "wof:name":"Rise & Shine Bakery",
    "wof:placetype":"venue"
},
  "geometry": {"coordinates":[-1.3505929708,50.9683227539],"type":"Point"}
}