{
  "type": "Feature",
  "properties": {
    "iso:country":"GB",
    "sg:address":"48 Sheffield Rd",
    "sg:city":"Sutton Coldfield",
    "sg:classifiers":[
        {
            "category":"Shopping",
            "subcategory":"Stationery & Office Supplies",
            "type":"Retail Goods"
        }
    ],
    "sg:phone":"+44 121 373 1221",
    "sg:postcode":"B73 5HD",
    "sg:province":"West Midlands",
    "sg:tags":[
        "machine",
        "facsimile"
    ],
    "wof:name":"Advantage Business Copiers",
    "wof:placetype":"venue"
},
  "geometry": {"coordinates":[-1.834135,52.537594],"type":"Point"}
}