{
  "type": "Feature",
  "properties": {
    "addr:full":"175 Billet Road London Greater London E17 5HG",
    "addr:housenumber":"175",
    "addr:postcode":"e17 5hg",
    "addr:street":"Billet Road",
    "iso:country":"GB",
    "sg:address":"175 Billet Road",
    "sg:city":"London",
    "sg:classifiers":[
        {
            "category":"Retail",
            "subcategory":"Auto Repair",
            "type":"Services"
        }
    ],
    "sg:phone":"+44 20 8527 1166",
    "sg:postcode":"E17 5HG",
    "sg:province":"Greater London",
    "sg:tags":[
        "modification",
        "garage"
    ],
    "wof:name":"Avalon Motors",
    "wof:placetype":"venue"
},
  "geometry": {"coordinates":[-0.031057,51.599422],"type":"Point"}
}