{
  "type": "Feature",
  "properties": {
    "addr:full":"Unit 18c Boxer Place, Moss Side Instl Estate Preston Lancashire PR26 7QL",
    "addr:housenumber":"unit 18c;estate",
    "addr:postcode":"pr26 7ql",
    "addr:street":"Boxer Place;Instl;Preston",
    "iso:country":"GB",
    "sg:address":"Unit 18c Boxer Place, Moss Side Instl Estate",
    "sg:city":"Preston",
    "sg:classifiers":[
        {
            "category":"Professional",
            "subcategory":"Art Services",
            "type":"Services"
        }
    ],
    "sg:phone":"+44 1772 490260",
    "sg:postcode":"PR26 7QL",
    "sg:province":"Lancashire",
    "sg:tags":[
        "graphic",
        "designer"
    ],
    "wof:name":"Type House",
    "wof:placetype":"venue"
},
  "geometry": {"coordinates":[-2.722046,53.701477],"type":"Point"}
}