{
  "type": "Feature",
  "properties": {
    "addr:full":"8 Hanley Terrace Malvern Herefordshire WR14 4PF",
    "addr:housenumber":"8",
    "addr:postcode":"wr14 4pf",
    "addr:street":"Hanley Terrace;Herefordshire",
    "iso:country":"GB",
    "sg:address":"8 Hanley Terrace",
    "sg:city":"Malvern",
    "sg:classifiers":[
        {
            "category":"Professional",
            "subcategory":"Management & Consulting",
            "type":"Services"
        }
    ],
    "sg:phone":"+44 1684 565808",
    "sg:postcode":"WR14 4PF",
    "sg:province":"Herefordshire",
    "sg:tags":[
        "marketing",
        "consultant"
    ],
    "wof:name":"The Publicity Co",
    "wof:placetype":"venue"
},
  "geometry": {"coordinates":[-2.33357,52.087391],"type":"Point"}
}