{
  "type": "Feature",
  "properties": {
    "iso:country":"GB",
    "sg:address":"55 Sagecroft Road",
    "sg:city":"Thatcham",
    "sg:classifiers":[
        {
            "category":"Organizations",
            "subcategory":"Non-profit Organization",
            "type":"Services"
        }
    ],
    "sg:phone":"+44 1635 866547",
    "sg:postcode":"RG18 3AX",
    "sg:province":"Berkshire",
    "sg:tags":[
        "charitable",
        "organisation",
        "voluntary",
        "charity"
    ],
    "wof:name":"THE GUIDE DOGS FOR THE BLIND ASSOCIATION",
    "wof:placetype":"venue"
},
  "geometry": {"coordinates":[-1.263037,51.411575],"type":"Point"}
}