{
  "type": "Feature",
  "properties": {
    "addr:full":"34 High Street Sandbach Cheshire CW11 1JA",
    "addr:housenumber":"34",
    "addr:postcode":"cw11 1ja",
    "addr:street":"High Street",
    "iso:country":"GB",
    "sg:address":"34 High Street",
    "sg:city":"Sandbach",
    "sg:classifiers":[
        {
            "category":"Travel",
            "subcategory":"Travel Agent",
            "type":"Entertainment"
        }
    ],
    "sg:phone":"+44 1270 766404",
    "sg:postcode":"CW11 1JA",
    "sg:province":"Cheshire",
    "sg:tags":[
        "agency",
        "activity"
    ],
    "wof:name":"Sandbach Travel Ltd.",
    "wof:placetype":"venue"
},
  "geometry": {"coordinates":[-2.3608250618,53.1431922913],"type":"Point"}
}