{
  "type": "Feature",
  "properties": {
    "addr:full":"Unit 15, Welch Hill Mill, Welch Hill St Leigh Lancashire WN7 4DU",
    "addr:housenumber":"unit 15",
    "addr:postcode":"wn7 4du",
    "addr:street":"Welch Hill;Welch Hill St",
    "iso:country":"GB",
    "sg:address":"Unit 15, Welch Hill Mill, Welch Hill St",
    "sg:city":"Leigh",
    "sg:classifiers":[
        {
            "category":"Shopping",
            "subcategory":"Beauty & Cosmetics",
            "type":"Retail Goods"
        }
    ],
    "sg:phone":"+44 1942 671377",
    "sg:postcode":"WN7 4DU",
    "sg:province":"Lancashire",
    "sg:tags":[
        "product"
    ],
    "wof:name":"House of Herbs Ltd",
    "wof:placetype":"venue"
},
  "geometry": {"coordinates":[-2.518994,53.496971],"type":"Point"}
}