{
  "type": "Feature",
  "properties": {
    "addr:full":"Suite 3d, Kirkgate Business Centre, Stennard Island Wakefield West Yorkshire WF1 5DL",
    "addr:housenumber":"suite 3d",
    "addr:postcode":"wf1 5dl",
    "addr:street":"Kirkgate Business Centre Stennard Island",
    "iso:country":"GB",
    "sg:address":"Suite 3d, Kirkgate Business Centre, Stennard Island",
    "sg:city":"Wakefield",
    "sg:classifiers":[
        {
            "category":"Arts & Performance",
            "subcategory":"Art Gallery",
            "type":"Entertainment"
        }
    ],
    "sg:phone":"+44 1924 217218",
    "sg:postcode":"WF1 5DL",
    "sg:province":"West Yorkshire",
    "wof:name":"Classic Art",
    "wof:placetype":"venue"
},
  "geometry": {"coordinates":[-1.488409996,53.6769256592],"type":"Point"}
}