{
  "type": "Feature",
  "properties": {
    "iso:country":"GB",
    "sg:address":"18 Fir Road, Bramhall",
    "sg:city":"Stockport",
    "sg:classifiers":[
        {
            "category":"Retail",
            "subcategory":"Laundry & Dry Cleaning",
            "type":"Services"
        }
    ],
    "sg:postcode":"SK7 2NP",
    "sg:province":"Cheshire",
    "sg:tags":[
        "alteration"
    ],
    "wof:name":"Bramhall Dry Cleaners",
    "wof:placetype":"venue"
},
  "geometry": {"coordinates":[-2.1596159935,53.3717575073],"type":"Point"}
}