{
  "type": "Feature",
  "properties": {
    "iso:country":"GB",
    "sg:address":"14 Titan Court, Laporte Way, Kingsway",
    "sg:city":"Luton",
    "sg:classifiers":[
        {
            "category":"Professional",
            "subcategory":"Advertising",
            "type":"Services"
        }
    ],
    "sg:phone":"+44 1582 486886",
    "sg:postcode":"LU4 8EF",
    "sg:province":"Bedfordshire",
    "sg:tags":[
        "agency"
    ],
    "wof:name":"Taylor Gibson Associates Ltd.",
    "wof:placetype":"venue"
},
  "geometry": {"coordinates":[-0.448484,51.8881],"type":"Point"}
}