{
  "type": "Feature",
  "properties": {
    "iso:country":"GB",
    "sg:address":"Unit 3 Burnside Business Court, North Road",
    "sg:city":"Inverkeithing",
    "sg:classifiers":[
        {
            "category":"Home & Garden",
            "subcategory":"Building Materials",
            "type":"Retail Goods"
        }
    ],
    "sg:phone":"+44 1383 411400",
    "sg:postcode":"KY11 1NZ",
    "sg:province":"Fife",
    "sg:tags":[
        "stairlifts"
    ],
    "wof:name":"Laurence Ewart",
    "wof:placetype":"venue"
},
  "geometry": {"coordinates":[-3.395135,56.037445],"type":"Point"}
}