{
  "type": "Feature",
  "properties": {
    "addr:full":"60 Aire Street Goole East Riding of Yorkshire DN14 5QE",
    "addr:housenumber":"60",
    "addr:postcode":"dn14 5qe",
    "addr:street":"Aire Street",
    "iso:country":"GB",
    "sg:address":"60 Aire Street",
    "sg:city":"Goole",
    "sg:classifiers":[
        {
            "category":"Manufacturing",
            "subcategory":"Tools & Machinery",
            "type":"Manufacturing & Wholesale Goods"
        }
    ],
    "sg:phone":"+44 1405 768568",
    "sg:postcode":"DN14 5QE",
    "sg:province":"East Riding of Yorkshire",
    "sg:tags":[
        "society",
        "friendly"
    ],
    "wof:name":"John Hughes Insurances",
    "wof:placetype":"venue"
},
  "geometry": {"coordinates":[-0.870857,53.702698],"type":"Point"}
}