{
  "type": "Feature",
  "properties": {
    "addr:full":"New House Dozens Bank, West Pinchbeck Spalding Lincolnshire PE11 3ND",
    "addr:postcode":"pe11 3nd",
    "addr:street":"West",
    "iso:country":"GB",
    "sg:address":"New House Dozens Bank, West Pinchbeck",
    "sg:city":"Spalding",
    "sg:classifiers":[
        {
            "category":"Building & Trades",
            "subcategory":"Landscaping Services",
            "type":"Services"
        }
    ],
    "sg:postcode":"PE11 3ND",
    "sg:province":"Lincolnshire",
    "sg:tags":[
        "landscape",
        "contractor"
    ],
    "wof:name":"R B Haulage Landscape & Garden Services",
    "wof:placetype":"venue"
},
  "geometry": {"coordinates":[-0.161251,52.816528],"type":"Point"}
}