{
  "type": "Feature",
  "properties": {
    "addr:full":"Wilmslow House Grove Way, Water Lane Wilmslow Cheshire SK9 5AQ",
    "addr:postcode":"sk9 5aq",
    "addr:street":"Grove Way Water Lane",
    "iso:country":"GB",
    "sg:address":"Wilmslow House Grove Way, Water Lane",
    "sg:city":"Wilmslow",
    "sg:classifiers":[
        {
            "category":"Professional",
            "subcategory":"Employment Agencies",
            "type":"Services"
        }
    ],
    "sg:phone":"+44 1625 533844",
    "sg:postcode":"SK9 5AQ",
    "sg:province":"Cheshire",
    "sg:tags":[
        "consultant"
    ],
    "wof:name":"Forrest Recruitment Ltd.",
    "wof:placetype":"venue"
},
  "geometry": {"coordinates":[-2.233108,53.326473],"type":"Point"}
}