{
  "type": "Feature",
  "properties": {
    "addr:full":"Link House, Oakway Amersham Buckinghamshire HP6 5PQ",
    "addr:postcode":"hp6 5pq",
    "addr:street":"Oakway Amersham",
    "iso:country":"GB",
    "sg:address":"Link House, Oakway",
    "sg:city":"Amersham",
    "sg:classifiers":[
        {
            "category":"Health Services",
            "subcategory":"Podiatrist",
            "type":"Services"
        }
    ],
    "sg:phone":"+44 1494 725034",
    "sg:postcode":"HP6 5PQ",
    "sg:province":"Buckinghamshire",
    "sg:tags":[
        "podiatrists",
        "chiropodist"
    ],
    "wof:name":"Judith Barnes",
    "wof:placetype":"venue"
},
  "geometry": {"coordinates":[-0.616634,51.688164],"type":"Point"}
}