{
  "type": "Feature",
  "properties": {
    "addr:full":"316a Hook Road Chessington Surrey KT9 1NY",
    "addr:housenumber":"316a",
    "addr:postcode":"kt9 1ny",
    "addr:street":"Hook Road",
    "iso:country":"GB",
    "sg:address":"316a Hook Road",
    "sg:city":"Chessington",
    "sg:classifiers":[
        {
            "category":"Professional",
            "subcategory":"Business Services",
            "type":"Services"
        },
        {
            "category":"Casinos & Gambling",
            "type":"Entertainment"
        }
    ],
    "sg:phone":"+44 20 8974 2240",
    "sg:postcode":"KT9 1NY",
    "sg:province":"Surrey",
    "sg:tags":[
        "turf",
        "accountant",
        "bookmaker"
    ],
    "wof:name":"Hestview Ltd.",
    "wof:placetype":"venue"
},
  "geometry": {"coordinates":[-0.3066869974,51.3677864075],"type":"Point"}
}