{
  "type": "Feature",
  "properties": {
    "iso:country":"GB",
    "sg:address":"Albert Chambers, Canal Street",
    "sg:city":"Congleton",
    "sg:classifiers":[
        {
            "category":"Communications",
            "subcategory":"Newspaper",
            "type":"Services"
        }
    ],
    "sg:phone":"+44 1260 281012",
    "sg:postcode":"CW12 4AA",
    "sg:province":"Cheshire",
    "sg:tags":[
        "magazine"
    ],
    "wof:name":"South Cheshire Advertiser",
    "wof:placetype":"venue"
},
  "geometry": {"coordinates":[-2.2122049332,53.1636352539],"type":"Point"}
}