{
  "type": "Feature",
  "properties": {
    "addr:full":"40 Mersey Road Widnes Cheshire WA8 0DS",
    "addr:housenumber":"40",
    "addr:postcode":"wa8 0ds",
    "addr:street":"Mersey Road",
    "iso:country":"GB",
    "sg:address":"40 Mersey Road",
    "sg:city":"Widnes",
    "sg:classifiers":[
        {
            "category":"Retail",
            "subcategory":"Repair Shop",
            "type":"Services"
        }
    ],
    "sg:phone":"+44 151 424 0002",
    "sg:postcode":"WA8 0DS",
    "sg:province":"Cheshire",
    "sg:tags":[
        "radio",
        "television",
        "video"
    ],
    "wof:name":"C R Tv",
    "wof:placetype":"venue"
},
  "geometry": {"coordinates":[-2.7344489098,53.3506965637],"type":"Point"}
}