{
  "type": "Feature",
  "properties": {
    "addr:full":"55 Chaseside, Southgate London Greater London N14 5BU",
    "addr:housenumber":"55",
    "addr:postcode":"n14 5bu",
    "addr:street":"Chaseside Southgate",
    "iso:country":"GB",
    "sg:address":"55 Chaseside, Southgate",
    "sg:city":"London",
    "sg:classifiers":[
        {
            "category":"Banks & Credit Unions",
            "subcategory":"Bank",
            "type":"Services"
        }
    ],
    "sg:phone":"+44 845 600 1010",
    "sg:postcode":"N14 5BU",
    "sg:province":"Greater London",
    "wof:name":"Halifax Plc",
    "wof:placetype":"venue"
},
  "geometry": {"coordinates":[-0.130843,51.633118],"type":"Point"}
}