{
  "type": "Feature",
  "properties": {
    "iso:country":"GB",
    "sg:address":"Marton Road",
    "sg:city":"Bridlington",
    "sg:classifiers":[
        {
            "category":"Education",
            "subcategory":"School",
            "type":"Public Place"
        },
        {
            "category":"Government",
            "subcategory":"Office",
            "type":"Public Place"
        }
    ],
    "sg:phone":"+44 1262 674487",
    "sg:postcode":"YO16 7AQ",
    "sg:province":"East Riding of Yorkshire",
    "sg:tags":[
        "local",
        "authority"
    ],
    "wof:name":"Burlington County Junior School",
    "wof:placetype":"venue"
},
  "geometry": {"coordinates":[-0.189879,54.098614],"type":"Point"}
}