{
  "type": "Feature",
  "properties": {
    "addr:full":"23-27 Lower St Haslemere Hampshire GU27 2NY",
    "addr:housenumber":"23-27",
    "addr:postcode":"gu27 2ny",
    "addr:street":"Lower St",
    "iso:country":"GB",
    "sg:address":"23-27 Lower St",
    "sg:city":"Haslemere",
    "sg:classifiers":[
        {
            "category":"Fast Food",
            "type":"Food & Drink"
        },
        {
            "category":"Restaurant",
            "type":"Food & Drink"
        }
    ],
    "sg:postcode":"GU27 2NY",
    "sg:province":"Hampshire",
    "sg:tags":[
        "away",
        "take",
        "french"
    ],
    "wof:name":"Peruad,Michel,",
    "wof:placetype":"venue"
},
  "geometry": {"coordinates":[-0.712186,51.0882],"type":"Point"}
}