{
  "type": "Feature",
  "properties": {
    "iso:country":"GB",
    "sg:address":"54 Suttonfield, Whitehill",
    "sg:city":"Bordon",
    "sg:classifiers":[
        {
            "category":"Retail",
            "subcategory":"Auto Repair",
            "type":"Services"
        }
    ],
    "sg:postcode":"GU35 9BP",
    "sg:province":"Hampshire",
    "sg:tags":[
        "car",
        "upholsterer"
    ],
    "wof:name":"Graham Sears Car Trimming",
    "wof:placetype":"venue"
},
  "geometry": {"coordinates":[-0.87315,51.112682],"type":"Point"}
}