{
  "type": "Feature",
  "properties": {
    "addr:full":"300a Foleshill Road Coventry Warwickshire CV6 5AH",
    "addr:housenumber":"300a",
    "addr:postcode":"cv6 5ah",
    "addr:street":"Foleshill Road",
    "iso:country":"GB",
    "sg:address":"300a Foleshill Road",
    "sg:city":"Coventry",
    "sg:classifiers":[
        {
            "category":"Autos & Motor Vehicles",
            "subcategory":"Auto Supplies",
            "type":"Retail Goods"
        },
        {
            "category":"Retail",
            "subcategory":"Auto Repair",
            "type":"Services"
        }
    ],
    "sg:phone":"+44 24 7666 5799",
    "sg:postcode":"CV6 5AH",
    "sg:province":"Warwickshire",
    "sg:tags":[
        "modification",
        "garage",
        "windscreen"
    ],
    "wof:name":"Novus Windscreen Repair",
    "wof:placetype":"venue"
},
  "geometry": {"coordinates":[-1.501022,52.426144],"type":"Point"}
}