{
  "type": "Feature",
  "properties": {
    "addr:full":"Storage House, Priority Enterprise Park, Cardiff Rd Barry The Vale of Glamorgan CF63 2BG",
    "addr:postcode":"cf63 2bg",
    "addr:street":"Enterprise Park Cardiff Rd;Vale",
    "iso:country":"GB",
    "sg:address":"Storage House, Priority Enterprise Park, Cardiff Rd",
    "sg:city":"Barry",
    "sg:classifiers":[
        {
            "category":"Retail",
            "subcategory":"Storage",
            "type":"Services"
        }
    ],
    "sg:phone":"+44 1656 660400",
    "sg:postcode":"CF63 2BG",
    "sg:province":"The Vale of Glamorgan",
    "sg:tags":[
        "household",
        "removal"
    ],
    "wof:name":"Masons Removals",
    "wof:placetype":"venue"
},
  "geometry": {"coordinates":[-3.2369000912,51.4153900146],"type":"Point"}
}