{
  "type": "Feature",
  "properties": {
    "addr:full":"Glebe Farm, Stock Road, Galleywood Chelmsford Essex CM2 8JZ",
    "addr:postcode":"cm2 8jz",
    "addr:street":"Stock Road",
    "iso:country":"GB",
    "sg:address":"Glebe Farm, Stock Road, Galleywood",
    "sg:city":"Chelmsford",
    "sg:classifiers":[
        {
            "category":"Building & Trades",
            "subcategory":"Construction",
            "type":"Services"
        }
    ],
    "sg:phone":"+44 1245 261283",
    "sg:postcode":"CM2 8JZ",
    "sg:province":"Essex",
    "sg:tags":[
        "builder"
    ],
    "wof:name":"M S Clark & Son",
    "wof:placetype":"venue"
},
  "geometry": {"coordinates":[0.4663569927,51.6970100403],"type":"Point"}
}