{
  "type": "Feature",
  "properties": {
    "addr:full":"Phiskardo, Normanby Road Scunthorpe Lincolnshire DN15 9AD",
    "addr:postcode":"dn15 9ad",
    "addr:street":"Phiskardo Normanby Road",
    "iso:country":"GB",
    "sg:address":"Phiskardo, Normanby Road",
    "sg:city":"Scunthorpe",
    "sg:classifiers":[
        {
            "category":"Building & Trades",
            "subcategory":"Construction",
            "type":"Services"
        },
        {
            "category":"Manufacturing",
            "subcategory":"Lumber",
            "type":"Manufacturing & Wholesale Goods"
        }
    ],
    "sg:postcode":"DN15 9AD",
    "sg:province":"Lincolnshire",
    "sg:tags":[
        "merchants",
        "carpenter",
        "agent",
        "importer",
        "joiner",
        "timber"
    ],
    "wof:name":"Scunthorpe Timber & Joinery Supplies",
    "wof:placetype":"venue"
},
  "geometry": {"coordinates":[-0.6652280092,53.6398468018],"type":"Point"}
}