{
  "type": "Feature",
  "properties": {
    "addr:full":"19 Water Street Todmorden Lancashire OL14 5AB",
    "addr:housenumber":"19",
    "addr:postcode":"ol14 5ab",
    "addr:street":"Water Street",
    "iso:country":"GB",
    "sg:address":"19 Water Street",
    "sg:city":"Todmorden",
    "sg:classifiers":[
        {
            "category":"Health Services",
            "subcategory":"Optometrist",
            "type":"Services"
        },
        {
            "category":"Shopping",
            "subcategory":"Optician",
            "type":"Retail Goods"
        }
    ],
    "sg:phone":"+44 1706 815551",
    "sg:postcode":"OL14 5AB",
    "sg:province":"Lancashire",
    "sg:tags":[
        "ophthalmic"
    ],
    "wof:name":"S W Allen",
    "wof:placetype":"venue"
},
  "geometry": {"coordinates":[-2.097853,53.712891],"type":"Point"}
}