{
  "type": "Feature",
  "properties": {
    "iso:country":"GB",
    "sg:address":"Fleetwood Road",
    "sg:city":"Fleetwood",
    "sg:classifiers":[
        {
            "category":"Sports & Exercise",
            "subcategory":"Bowling",
            "type":"Entertainment"
        }
    ],
    "sg:phone":"+44 1253 876222",
    "sg:postcode":"FY7 8JY",
    "sg:province":"Lancashire",
    "wof:name":"Cala Gran Bowling Centre",
    "wof:placetype":"venue"
},
  "geometry": {"coordinates":[-3.033388,53.912331],"type":"Point"}
}