{
  "type": "Feature",
  "properties": {
    "addr:full":"1/1a Stanley Walk, Stanley Street Luton Bedfordshire LU1 5AW",
    "addr:housenumber":"1 / 1a",
    "addr:postcode":"lu1 5aw",
    "addr:street":"Stanley Walk Stanley Street",
    "iso:country":"GB",
    "sg:address":"1/1a Stanley Walk, Stanley Street",
    "sg:city":"Luton",
    "sg:classifiers":[
        {
            "category":"Deli",
            "type":"Food & Drink"
        },
        {
            "category":"Communications",
            "type":"Services"
        }
    ],
    "sg:phone":"+44 1582 483634",
    "sg:postcode":"LU1 5AW",
    "sg:province":"Bedfordshire",
    "sg:tags":[
        "delivery",
        "sandwich",
        "audio-visual"
    ],
    "wof:name":"L T V Ltd.",
    "wof:placetype":"venue"
},
  "geometry": {"coordinates":[-0.4213669896,51.8764343262],"type":"Point"}
}