{
  "type": "Feature",
  "properties": {
    "iso:country":"GB",
    "sg:address":"Glenridding",
    "sg:city":"Penrith",
    "sg:classifiers":[
        {
            "category":"Travel",
            "subcategory":"Hotels & Motels",
            "type":"Entertainment"
        }
    ],
    "sg:phone":"+44 17684 82444",
    "sg:postcode":"CA11 0PA",
    "sg:province":"Cumbria",
    "wof:name":"Ullswater Hotel",
    "wof:placetype":"venue"
},
  "geometry": {"coordinates":[-2.95097,54.543339],"type":"Point"}
}