{
  "type": "Feature",
  "properties": {
    "addr:full":"Unit 1a, Batemans Court, Waynfleet Skegness Lincolnshire PE24 4AW",
    "addr:housenumber":"unit 1a",
    "addr:postcode":"pe24 4aw",
    "addr:street":"Batemans Court",
    "iso:country":"GB",
    "sg:address":"Unit 1a, Batemans Court, Waynfleet",
    "sg:city":"Skegness",
    "sg:classifiers":[
        {
            "category":"Professional",
            "subcategory":"Business Services",
            "type":"Services"
        },
        {
            "category":"Wholesale",
            "subcategory":"Fruits & Vegetables",
            "type":"Manufacturing & Wholesale Goods"
        }
    ],
    "sg:phone":"+44 1754 880725",
    "sg:postcode":"PE24 4AW",
    "sg:province":"Lincolnshire",
    "sg:tags":[
        "broker",
        "commodity"
    ],
    "wof:name":"Fruit Warehouse",
    "wof:placetype":"venue"
},
  "geometry": {"coordinates":[0.245598,53.111282],"type":"Point"}
}