{
  "type": "Feature",
  "properties": {
    "addr:full":"375 Edgware Rd Bayswater Greater London W2 1BS",
    "addr:housenumber":"375",
    "addr:postcode":"w2 1bs",
    "addr:street":"Edgware Rd",
    "iso:country":"GB",
    "sg:address":"375 Edgware Rd",
    "sg:city":"Bayswater",
    "sg:classifiers":[
        {
            "category":"Real Estate",
            "subcategory":"Real Estate Operator",
            "type":"Services"
        }
    ],
    "sg:phone":"+44 20 7724 1122",
    "sg:postcode":"W2 1BS",
    "sg:province":"Greater London",
    "sg:tags":[
        "letting",
        "agent"
    ],
    "wof:name":"Delta Accommodation",
    "wof:placetype":"venue"
},
  "geometry": {"coordinates":[-0.1741929948,51.5226898193],"type":"Point"}
}