{
  "type": "Feature",
  "properties": {
    "addr:full":"Bell Chambers, Lower Gungate Tamworth Staffordshire B79 7AS",
    "addr:postcode":"b79 7as",
    "addr:street":"Lower Gungate",
    "iso:country":"GB",
    "sg:address":"Bell Chambers, Lower Gungate",
    "sg:city":"Tamworth",
    "sg:classifiers":[
        {
            "category":"Professional",
            "subcategory":"Employment Agencies",
            "type":"Services"
        }
    ],
    "sg:phone":"+44 1827 316316",
    "sg:postcode":"B79 7AS",
    "sg:province":"Staffordshire",
    "sg:tags":[
        "consultant"
    ],
    "wof:name":"Protemp Recruitment Ltd.",
    "wof:placetype":"venue"
},
  "geometry": {"coordinates":[-1.687684,52.634094],"type":"Point"}
}