{
  "type": "Feature",
  "properties": {
    "addr:full":"Town Lane, Mobberley Knutsford Cheshire WA16 7HH",
    "addr:postcode":"wa16 7hh",
    "addr:street":"Town Lane",
    "iso:country":"GB",
    "sg:address":"Town Lane, Mobberley",
    "sg:city":"Knutsford",
    "sg:classifiers":[
        {
            "category":"Travel",
            "subcategory":"Hotels & Motels",
            "type":"Entertainment"
        }
    ],
    "sg:phone":"+44 1565 873484",
    "sg:postcode":"WA16 7HH",
    "sg:province":"Cheshire",
    "sg:tags":[
        "house",
        "guest"
    ],
    "wof:name":"The Hinton",
    "wof:placetype":"venue"
},
  "geometry": {"coordinates":[-2.3301339149,53.3141059875],"type":"Point"}
}