{
  "type": "Feature",
  "properties": {
    "addr:full":"48 High Street Newhaven East Sussex BN9 9PA",
    "addr:housenumber":"48",
    "addr:postcode":"bn9 9pa",
    "addr:street":"High Street",
    "iso:country":"GB",
    "sg:address":"48 High Street",
    "sg:city":"Newhaven",
    "sg:classifiers":[
        {
            "category":"Real Estate",
            "subcategory":"Real Estate Agent",
            "type":"Services"
        }
    ],
    "sg:phone":"+44 1273 515151",
    "sg:postcode":"BN9 9PA",
    "sg:province":"East Sussex",
    "wof:name":"Lampons Lettings",
    "wof:placetype":"venue"
},
  "geometry": {"coordinates":[0.047742,50.793839],"type":"Point"}
}