{
  "type": "Feature",
  "properties": {
    "iso:country":"GB",
    "sg:address":"20 Crescent Road",
    "sg:city":"Luton",
    "sg:classifiers":[
        {
            "category":"Professional",
            "subcategory":"Engineering",
            "type":"Services"
        }
    ],
    "sg:phone":"+44 1582 452962",
    "sg:postcode":"LU2 0AG",
    "sg:province":"Bedfordshire",
    "wof:name":"Coleman Engineering",
    "wof:placetype":"venue"
},
  "geometry": {"coordinates":[-0.40486601,51.8801994324],"type":"Point"}
}