{
  "type": "Feature",
  "properties": {
    "iso:country":"GB",
    "sg:address":"154 Plumstead High Street",
    "sg:city":"London",
    "sg:classifiers":[
        {
            "category":"Shopping",
            "subcategory":"Pharmacy",
            "type":"Retail Goods"
        }
    ],
    "sg:phone":"+44 20 8854 4913",
    "sg:postcode":"SE18 1JQ",
    "sg:province":"Greater London",
    "sg:tags":[
        "pharmacist",
        "chemist"
    ],
    "wof:name":"Moss Chemists",
    "wof:placetype":"venue"
},
  "geometry": {"coordinates":[0.092695,51.487286],"type":"Point"}
}