{
  "type": "Feature",
  "properties": {
    "addr:full":"Stockport Delivery Office, 1 Exchange Street Stockport Cheshire SK1 1AA",
    "addr:housenumber":"1",
    "addr:postcode":"sk1 1aa",
    "addr:street":"Exchange Street",
    "iso:country":"GB",
    "sg:address":"Stockport Delivery Office, 1 Exchange Street",
    "sg:city":"Stockport",
    "sg:classifiers":[
        {
            "category":"Personal",
            "type":"Services"
        }
    ],
    "sg:phone":"+44 161 480 8101",
    "sg:postcode":"SK1 1AA",
    "sg:province":"Cheshire",
    "sg:tags":[
        "delivery"
    ],
    "wof:name":"Royal Mail",
    "wof:placetype":"venue"
},
  "geometry": {"coordinates":[-2.1580200195,53.4112510681],"type":"Point"}
}