{
  "type": "Feature",
  "properties": {
    "addr:full":"Lullingsford Castle, Lullingstone Park, Eynsford Dartford Kent DA4 0JA",
    "addr:postcode":"da4 0ja",
    "iso:country":"GB",
    "sg:address":"Lullingsford Castle, Lullingstone Park, Eynsford",
    "sg:city":"Dartford",
    "sg:classifiers":[
        {
            "category":"Landmark",
            "subcategory":"Tourist Attraction",
            "type":"Public Place"
        }
    ],
    "sg:phone":"+44 1322 862114",
    "sg:postcode":"DA4 0JA",
    "sg:province":"Kent",
    "sg:tags":[
        "interest"
    ],
    "wof:name":"Lullingstone Estates Ltd.",
    "wof:placetype":"venue"
},
  "geometry": {"coordinates":[0.2061049938,51.3650093079],"type":"Point"}
}