{
  "type": "Feature",
  "properties": {
    "iso:country":"GB",
    "sg:address":"Ferndale House, Pound Hill",
    "sg:city":"Alresford",
    "sg:classifiers":[
        {
            "category":"Professional",
            "subcategory":"Art Services",
            "type":"Services"
        }
    ],
    "sg:phone":"+44 1962 732693",
    "sg:postcode":"SO24 9BP",
    "sg:province":"Hampshire",
    "sg:tags":[
        "photographer"
    ],
    "wof:name":"Brian Champion Studios",
    "wof:placetype":"venue"
},
  "geometry": {"coordinates":[-1.164829,51.089821],"type":"Point"}
}