{
  "type": "Feature",
  "properties": {
    "iso:country":"GB",
    "sg:address":"33 Military Road, Hilsea",
    "sg:city":"Portsmouth",
    "sg:classifiers":[
        {
            "category":"Building & Trades",
            "subcategory":"Cleaning & Sanitation",
            "type":"Services"
        }
    ],
    "sg:postcode":"PO3 5LS",
    "sg:province":"Hampshire",
    "sg:tags":[
        "commercial"
    ],
    "wof:name":"J J Fleming",
    "wof:placetype":"venue"
},
  "geometry": {"coordinates":[-1.067695,50.834831],"type":"Point"}
}