{
  "type": "Feature",
  "properties": {
    "addr:full":"Normanby Rd Scunthorpe Lincolnshire DN15 8QZ",
    "addr:postcode":"dn15 8qz",
    "addr:street":"Normanby Rd",
    "iso:country":"GB",
    "sg:address":"Normanby Rd",
    "sg:city":"Scunthorpe",
    "sg:classifiers":[
        {
            "category":"Professional",
            "subcategory":"Engineering",
            "type":"Services"
        }
    ],
    "sg:phone":"+44 1724 871306",
    "sg:postcode":"DN15 8QZ",
    "sg:province":"Lincolnshire",
    "sg:tags":[
        "civil",
        "engineer"
    ],
    "wof:name":"Northmoor Services Ltd",
    "wof:placetype":"venue"
},
  "geometry": {"coordinates":[-0.652204,53.60363],"type":"Point"}
}