{
  "type": "Feature",
  "properties": {
    "addr:full":"2 Abbey Farm, The Street, Marham King's Lynn Norfolk PE33 9HP",
    "addr:housenumber":"2",
    "addr:postcode":"pe33 9hp",
    "addr:street":"Abbey;The Street;Lynn",
    "iso:country":"GB",
    "sg:address":"2 Abbey Farm, The Street, Marham",
    "sg:city":"King's Lynn",
    "sg:classifiers":[
        {
            "category":"Freight",
            "type":"Transportation"
        }
    ],
    "sg:phone":"+44 1760 338200",
    "sg:postcode":"PE33 9HP",
    "sg:province":"Norfolk",
    "sg:tags":[
        "forwarders"
    ],
    "wof:name":"Boxer Freight Ltd.",
    "wof:placetype":"venue"
},
  "geometry": {"coordinates":[0.5247700214,52.659198761],"type":"Point"}
}