{
  "type": "Feature",
  "properties": {
    "addr:full":"36 The Oval Otley North Yorkshire LS21 2EE",
    "addr:housenumber":"36",
    "addr:postcode":"ls21 2ee",
    "addr:street":"The Oval",
    "iso:country":"GB",
    "sg:address":"36 The Oval",
    "sg:city":"Otley",
    "sg:classifiers":[
        {
            "category":"Building & Trades",
            "subcategory":"Construction",
            "type":"Services"
        }
    ],
    "sg:postcode":"LS21 2EE",
    "sg:province":"North Yorkshire",
    "sg:tags":[
        "builder"
    ],
    "wof:name":"D Ausobsky",
    "wof:placetype":"venue"
},
  "geometry": {"coordinates":[-1.702519,53.91296],"type":"Point"}
}