{
  "type": "Feature",
  "properties": {
    "addr:full":"9 High Street, Colerne Chippenham Gloucestershire SN14 8DB",
    "addr:housenumber":"9",
    "addr:postcode":"sn14 8db",
    "addr:street":"High Street",
    "iso:country":"GB",
    "sg:address":"9 High Street, Colerne",
    "sg:city":"Chippenham",
    "sg:classifiers":[
        {
            "category":"Bars & Pubs",
            "type":"Food & Drink"
        }
    ],
    "sg:phone":"+44 1225 743506",
    "sg:postcode":"SN14 8DB",
    "sg:province":"Gloucestershire",
    "sg:tags":[
        "pubs",
        "inn"
    ],
    "wof:name":"The Fox & Hounds",
    "wof:placetype":"venue"
},
  "geometry": {"coordinates":[-2.2639029026,51.437953949],"type":"Point"}
}