{
  "type": "Feature",
  "properties": {
    "iso:country":"GB",
    "sg:address":"4 Vinings Gardens",
    "sg:city":"Sandown",
    "sg:classifiers":[
        {
            "category":"Building & Trades",
            "subcategory":"Construction",
            "type":"Services"
        }
    ],
    "sg:postcode":"PO36 8DX",
    "sg:province":"Isle of Wight",
    "sg:tags":[
        "joinery",
        "joiner",
        "carpenter",
        "carpentry"
    ],
    "wof:name":"M V Price",
    "wof:placetype":"venue"
},
  "geometry": {"coordinates":[-1.153889,50.660236],"type":"Point"}
}