{
  "type": "Feature",
  "properties": {
    "iso:country":"GB",
    "sg:address":"Clowes Ground, Barrowell Green",
    "sg:city":"Winchmore Hill",
    "sg:classifiers":[
        {
            "category":"Arena",
            "subcategory":"Sports Club",
            "type":"Entertainment"
        }
    ],
    "sg:phone":"+44 20 8886 2077",
    "sg:postcode":"N21 3AU",
    "sg:province":"Greater London",
    "wof:name":"Northampton Exiles C.C.",
    "wof:placetype":"venue"
},
  "geometry": {"coordinates":[-0.09378,51.625648],"type":"Point"}
}