{
  "type": "Feature",
  "properties": {
    "addr:full":"36 Paddock Road, Mapplewell Barnsley South Yorkshire S75 6LG",
    "addr:housenumber":"36",
    "addr:postcode":"s75 6lg",
    "addr:street":"Paddock Road Mapplewell;Yorkshire",
    "iso:country":"GB",
    "sg:address":"36 Paddock Road, Mapplewell",
    "sg:city":"Barnsley",
    "sg:classifiers":[
        {
            "category":"Building & Trades",
            "subcategory":"Construction",
            "type":"Services"
        }
    ],
    "sg:phone":"+44 1226 385053",
    "sg:postcode":"S75 6LG",
    "sg:province":"South Yorkshire",
    "sg:tags":[
        "builder"
    ],
    "wof:name":"Paul Turfrey Pointing",
    "wof:placetype":"venue"
},
  "geometry": {"coordinates":[-1.4955830574,53.5887451172],"type":"Point"}
}