{
  "type": "Feature",
  "properties": {
    "iso:country":"GB",
    "sg:address":"Newhampton Farm, Docklow",
    "sg:city":"Leominster",
    "sg:classifiers":[
        {
            "category":"Farming",
            "subcategory":"Farm",
            "type":"Manufacturing & Wholesale Goods"
        }
    ],
    "sg:phone":"+44 1568 760259",
    "sg:postcode":"HR6 0SL",
    "sg:province":"Herefordshire",
    "sg:tags":[
        "mixed",
        "crop"
    ],
    "wof:name":"David T Hughes",
    "wof:placetype":"venue"
},
  "geometry": {"coordinates":[-2.641096,52.213734],"type":"Point"}
}