{
  "type": "Feature",
  "properties": {
    "iso:country":"GB",
    "sg:address":"38 Lord Street",
    "sg:city":"Coventry",
    "sg:classifiers":[
        {
            "category":"Bars & Pubs",
            "type":"Food & Drink"
        }
    ],
    "sg:phone":"+44 24 7667 4530",
    "sg:postcode":"CV5 8DA",
    "sg:province":"West Midlands",
    "sg:tags":[
        "pubs",
        "house",
        "inn",
        "public",
        "activity"
    ],
    "wof:name":"The Nursery Tavern",
    "wof:placetype":"venue"
},
  "geometry": {"coordinates":[-1.533654,52.40786],"type":"Point"}
}