{
  "type": "Feature",
  "properties": {
    "addr:full":"263 Wilmslow Rd Manchester Greater Manchester M14 6LE",
    "addr:housenumber":"263",
    "addr:postcode":"m14 6le",
    "addr:street":"Wilmslow Rd",
    "iso:country":"GB",
    "sg:address":"263 Wilmslow Rd",
    "sg:city":"Manchester",
    "sg:classifiers":[
        {
            "category":"Bars & Pubs",
            "type":"Food & Drink"
        }
    ],
    "sg:phone":"+44 161 248 4820",
    "sg:postcode":"M14 6LE",
    "sg:province":"Greater Manchester",
    "sg:tags":[
        "pubs",
        "inn"
    ],
    "wof:name":"Shed",
    "wof:placetype":"venue"
},
  "geometry": {"coordinates":[-2.2196490765,53.440410614],"type":"Point"}
}