{
  "type": "Feature",
  "properties": {
    "iso:country":"GB",
    "sg:address":"Hillcrest, Moor End Lane, Stibbard",
    "sg:city":"Fakenham",
    "sg:classifiers":[
        {
            "category":"Building & Trades",
            "subcategory":"Construction",
            "type":"Services"
        }
    ],
    "sg:phone":"+44 1328 829253",
    "sg:postcode":"NR21 0EJ",
    "sg:province":"Norfolk",
    "sg:tags":[
        "builder"
    ],
    "wof:name":"R A Bunting & Son",
    "wof:placetype":"venue"
},
  "geometry": {"coordinates":[0.940549,52.815228],"type":"Point"}
}