{
  "type": "Feature",
  "properties": {
    "addr:full":"Glandwr, Llangeitho Tregaron Ceredigion SY25 6QG",
    "addr:postcode":"sy25 6qg",
    "iso:country":"GB",
    "sg:address":"Glandwr, Llangeitho",
    "sg:city":"Tregaron",
    "sg:classifiers":[
        {
            "category":"Professional",
            "subcategory":"Art Services",
            "type":"Services"
        }
    ],
    "sg:phone":"+44 1974 821545",
    "sg:postcode":"SY25 6QG",
    "sg:province":"Ceredigion",
    "sg:tags":[
        "consultant",
        "design"
    ],
    "wof:name":"Progressive Print Production Ltd.",
    "wof:placetype":"venue"
},
  "geometry": {"coordinates":[-3.934748888,52.220085144],"type":"Point"}
}