{
  "type": "Feature",
  "properties": {
    "addr:full":"Ellon Road Aberdeen Aberdeen City AB23 8DB",
    "addr:postcode":"ab23 8db",
    "addr:street":"Ellon Road",
    "iso:country":"GB",
    "sg:address":"Ellon Road",
    "sg:city":"Aberdeen",
    "sg:classifiers":[
        {
            "category":"Community Center",
            "subcategory":"Youth",
            "type":"Public Place"
        }
    ],
    "sg:phone":"+44 1224 708807",
    "sg:postcode":"AB23 8DB",
    "sg:province":"Aberdeen City",
    "sg:tags":[
        "organisation",
        "centre"
    ],
    "wof:name":"Air Training Corps",
    "wof:placetype":"venue"
},
  "geometry": {"coordinates":[-2.0905020237,57.1792449951],"type":"Point"}
}