{
  "type": "Feature",
  "properties": {
    "iso:country":"GB",
    "sg:address":"Church Street, Paulton",
    "sg:city":"Bristol",
    "sg:classifiers":[
        {
            "category":"Manufacturing",
            "subcategory":"Lumber",
            "type":"Manufacturing & Wholesale Goods"
        }
    ],
    "sg:postcode":"BS39 7LG",
    "sg:province":"Somerset",
    "sg:tags":[
        "importer",
        "merchants",
        "agent",
        "timber"
    ],
    "wof:name":"S D & R D Gay",
    "wof:placetype":"venue"
},
  "geometry": {"coordinates":[-2.500631,51.305626],"type":"Point"}
}