{
  "type": "Feature",
  "properties": {
    "addr:full":"Bear St, Nayland Colchester Essex CO6 4HY",
    "addr:postcode":"co6 4hy",
    "addr:street":"Bear St Nayland Colchester",
    "iso:country":"GB",
    "sg:address":"Bear St, Nayland",
    "sg:city":"Colchester",
    "sg:classifiers":[
        {
            "category":"Education",
            "subcategory":"School",
            "type":"Public Place"
        }
    ],
    "sg:phone":"+44 1206 262348",
    "sg:postcode":"CO6 4HY",
    "sg:province":"Essex",
    "sg:tags":[
        "local",
        "authority"
    ],
    "wof:name":"Nayland County Primary School",
    "wof:placetype":"venue"
},
  "geometry": {"coordinates":[0.871774,51.972328],"type":"Point"}
}