{
  "type": "Feature",
  "properties": {
    "addr:full":"59 Lake View Drive Plymouth Devon PL5 4LW",
    "addr:housenumber":"59",
    "addr:postcode":"pl5 4lw",
    "addr:street":"Lake View Drive",
    "iso:country":"GB",
    "sg:address":"59 Lake View Drive",
    "sg:city":"Plymouth",
    "sg:classifiers":[
        {
            "category":"Building & Trades",
            "subcategory":"Landscaping Services",
            "type":"Services"
        },
        {
            "category":"Wholesale",
            "subcategory":"Plants",
            "type":"Manufacturing & Wholesale Goods"
        }
    ],
    "sg:phone":"+44 1752 708469",
    "sg:postcode":"PL5 4LW",
    "sg:province":"Devon",
    "sg:tags":[
        "horticultural",
        "consultant"
    ],
    "wof:name":"Shilston Plant Service",
    "wof:placetype":"venue"
},
  "geometry": {"coordinates":[-4.160896,50.42561],"type":"Point"}
}