{
  "type": "Feature",
  "properties": {
    "addr:full":"28 Church Road, Earley Reading Berkshire RG6 1HS",
    "addr:housenumber":"28",
    "addr:postcode":"rg6 1hs",
    "addr:street":"Church Road",
    "iso:country":"GB",
    "sg:address":"28 Church Road, Earley",
    "sg:city":"Reading",
    "sg:classifiers":[
        {
            "category":"Professional",
            "subcategory":"Art Services",
            "type":"Services"
        }
    ],
    "sg:phone":"+44 118 962 6680",
    "sg:postcode":"RG6 1HS",
    "sg:province":"Berkshire",
    "sg:tags":[
        "graphic",
        "designer"
    ],
    "wof:name":"Time Design",
    "wof:placetype":"venue"
},
  "geometry": {"coordinates":[-0.927940011,51.44556427],"type":"Point"}
}