{
  "type": "Feature",
  "properties": {
    "addr:full":"Tufton Street Ashford Kent TN23 1AA",
    "addr:postcode":"tn23 1aa",
    "addr:street":"Tufton Street",
    "iso:country":"GB",
    "sg:address":"Tufton Street",
    "sg:city":"Ashford",
    "sg:classifiers":[
        {
            "category":"Government",
            "subcategory":"Post Office",
            "type":"Public Place"
        }
    ],
    "sg:phone":"+44 845 722 3344",
    "sg:postcode":"TN23 1AA",
    "sg:province":"Kent",
    "wof:name":"Post Office Ltd",
    "wof:placetype":"venue"
},
  "geometry": {"coordinates":[0.8723800182,51.1480140686],"type":"Point"}
}