{
  "type": "Feature",
  "properties": {
    "addr:full":"7 Market Place Banbury Oxfordshire OX16 5LG",
    "addr:housenumber":"7",
    "addr:postcode":"ox16 5lg",
    "addr:street":"Market Place",
    "iso:country":"GB",
    "sg:address":"7 Market Place",
    "sg:city":"Banbury",
    "sg:classifiers":[
        {
            "category":"Fast Food",
            "type":"Food & Drink"
        }
    ],
    "sg:postcode":"OX16 5LG",
    "sg:province":"Oxfordshire",
    "sg:tags":[
        "away",
        "take"
    ],
    "wof:name":"Permasafe Ltd",
    "wof:placetype":"venue"
},
  "geometry": {"coordinates":[-1.3356610537,52.0621871948],"type":"Point"}
}