{
  "type": "Feature",
  "properties": {
    "addr:full":"15 Norfolk Street Wisbech Cambridgeshire PE13 2LD",
    "addr:housenumber":"15",
    "addr:postcode":"pe13 2ld",
    "addr:street":"Norfolk Street",
    "iso:country":"GB",
    "sg:address":"15 Norfolk Street",
    "sg:city":"Wisbech",
    "sg:classifiers":[
        {
            "category":"Shopping",
            "subcategory":"Pets & Pet Supplies",
            "type":"Retail Goods"
        }
    ],
    "sg:phone":"+44 1945 461476",
    "sg:postcode":"PE13 2LD",
    "sg:province":"Cambridgeshire",
    "sg:tags":[
        "food"
    ],
    "wof:name":"June's Pet Foods",
    "wof:placetype":"venue"
},
  "geometry": {"coordinates":[0.163955003,52.6621055603],"type":"Point"}
}