{
  "type": "Feature",
  "properties": {
    "iso:country":"GB",
    "sg:address":"16-20 Stockport Road",
    "sg:city":"Altrincham",
    "sg:classifiers":[
        {
            "category":"Autos & Motor Vehicles",
            "subcategory":"Automobile Sales",
            "type":"Retail Goods"
        }
    ],
    "sg:phone":"+44 161 929 9019",
    "sg:postcode":"WA15 8EX",
    "sg:province":"Cheshire",
    "sg:tags":[
        "car"
    ],
    "wof:name":"Newalt Ltd.",
    "wof:placetype":"venue"
},
  "geometry": {"coordinates":[-2.344556,53.390537],"type":"Point"}
}