{
  "type": "Feature",
  "properties": {
    "addr:full":"116 Spring Meadow Preston Lancashire PR25 5LY",
    "addr:housenumber":"116",
    "addr:postcode":"pr25 5ly",
    "addr:street":"Spring Meadow",
    "iso:country":"GB",
    "sg:address":"116 Spring Meadow",
    "sg:city":"Preston",
    "sg:classifiers":[
        {
            "category":"Professional",
            "subcategory":"Management & Consulting",
            "type":"Services"
        }
    ],
    "sg:postcode":"PR25 5LY",
    "sg:province":"Lancashire",
    "sg:tags":[
        "consultant",
        "training"
    ],
    "wof:name":"People First",
    "wof:placetype":"venue"
},
  "geometry": {"coordinates":[-2.711039,53.756119],"type":"Point"}
}