{
  "type": "Feature",
  "properties": {
    "addr:full":"Dockray Street Colne Lancashire BB8 9HT",
    "addr:postcode":"bb8 9ht",
    "addr:street":"Dockray Street",
    "iso:country":"GB",
    "sg:address":"Dockray Street",
    "sg:city":"Colne",
    "sg:classifiers":[
        {
            "category":"Professional",
            "type":"Services"
        }
    ],
    "sg:phone":"+44 1282 865723",
    "sg:postcode":"BB8 9HT",
    "sg:province":"Lancashire",
    "sg:tags":[
        "car",
        "transportation"
    ],
    "wof:name":"Colne Vehicle Delivery Ltd.",
    "wof:placetype":"venue"
},
  "geometry": {"coordinates":[-2.1660540104,53.8587799072],"type":"Point"}
}