{
  "type": "Feature",
  "properties": {
    "iso:country":"GB",
    "sg:address":"Hereford & Worcester Contracting, Lydiate Ash Depot, Sandy La",
    "sg:city":"Bromsgrove",
    "sg:classifiers":[
        {
            "category":"Government",
            "subcategory":"Office",
            "type":"Public Place"
        }
    ],
    "sg:phone":"+44 121 453 3762",
    "sg:postcode":"B61 0QN",
    "sg:province":"Worcestershire",
    "sg:tags":[
        "local"
    ],
    "wof:name":"Worcestershire County Council",
    "wof:placetype":"venue"
},
  "geometry": {"coordinates":[-2.04735,52.38002],"type":"Point"}
}