{
  "type": "Feature",
  "properties": {
    "addr:full":"Park Court Offices, 45 Rhosddu Road Wrexham Wrexham LL11 2NS",
    "addr:housenumber":"45",
    "addr:postcode":"ll11 2ns",
    "addr:street":"Rhosddu Road",
    "iso:country":"GB",
    "sg:address":"Park Court Offices, 45 Rhosddu Road",
    "sg:city":"Wrexham",
    "sg:classifiers":[
        {
            "category":"Professional",
            "subcategory":"Employment Agencies",
            "type":"Services"
        }
    ],
    "sg:postcode":"LL11 2NS",
    "sg:province":"Wrexham",
    "sg:tags":[
        "consultant"
    ],
    "wof:name":"C R I S Ltd",
    "wof:placetype":"venue"
},
  "geometry": {"coordinates":[-2.99619,53.052052],"type":"Point"}
}