{
  "type": "Feature",
  "properties": {
    "iso:country":"GB",
    "sg:address":"11 Wellington Pl",
    "sg:city":"Hastings",
    "sg:classifiers":[
        {
            "category":"Food & Beverages",
            "subcategory":"Liquor & Beverages",
            "type":"Retail Goods"
        }
    ],
    "sg:phone":"+44 1424 436482",
    "sg:postcode":"TN34 1NY",
    "sg:province":"East Sussex",
    "sg:tags":[
        "beer",
        "spirit",
        "wines"
    ],
    "wof:name":"Whitbread Plc",
    "wof:placetype":"venue"
},
  "geometry": {"coordinates":[0.580581,50.855621],"type":"Point"}
}