{
  "type": "Feature",
  "properties": {
    "iso:country":"GB",
    "sg:address":"190 Norwich Road",
    "sg:city":"Fakenham",
    "sg:classifiers":[
        {
            "category":"Building & Trades",
            "subcategory":"Plumbing",
            "type":"Services"
        }
    ],
    "sg:phone":"+44 1328 863222",
    "sg:postcode":"NR21 8LX",
    "sg:province":"Norfolk",
    "sg:tags":[
        "heating"
    ],
    "wof:name":"R Williamson",
    "wof:placetype":"venue"
},
  "geometry": {"coordinates":[0.877864,52.832146],"type":"Point"}
}