{
  "type": "Feature",
  "properties": {
    "addr:full":"176a Camberwell Rd Camberwell Greater London SE5 0EE",
    "addr:housenumber":"176a",
    "addr:postcode":"se5 0ee",
    "addr:street":"Camberwell Rd",
    "iso:country":"GB",
    "sg:address":"176a Camberwell Rd",
    "sg:city":"Camberwell",
    "sg:classifiers":[
        {
            "category":"Retail",
            "subcategory":"Driving School",
            "type":"Services"
        }
    ],
    "sg:phone":"+44 20 7703 1614",
    "sg:postcode":"SE5 0EE",
    "sg:province":"Greater London",
    "wof:name":"Royal School of Motoring",
    "wof:placetype":"venue"
},
  "geometry": {"coordinates":[-0.1025289968,51.477771759],"type":"Point"}
}