{
  "type": "Feature",
  "properties": {
    "addr:full":"13 Well Hall Parade London Greater London SE9 6SP",
    "addr:housenumber":"13",
    "addr:postcode":"se9 6sp",
    "addr:street":"Well Hall Parade",
    "iso:country":"GB",
    "sg:address":"13 Well Hall Parade",
    "sg:city":"London",
    "sg:classifiers":[
        {
            "category":"Shopping",
            "subcategory":"Clothing, Apparel, & Fashions",
            "type":"Retail Goods"
        }
    ],
    "sg:phone":"+44 20 8850 7930",
    "sg:postcode":"SE9 6SP",
    "sg:province":"Greater London",
    "sg:tags":[
        "shop"
    ],
    "wof:name":"Joanne Fashions",
    "wof:placetype":"venue"
},
  "geometry": {"coordinates":[0.0508019999,51.4564247131],"type":"Point"}
}