{
  "type": "Feature",
  "properties": {
    "addr:full":"Unit 3, Old Roman Road, Stalling Downs Cowbridge The Vale of Glamorgan CF71 7DT",
    "addr:housenumber":"unit 3",
    "addr:postcode":"cf71 7dt",
    "addr:street":"Old Roman Road Stalling Downs;Vale",
    "iso:country":"GB",
    "sg:address":"Unit 3, Old Roman Road, Stalling Downs",
    "sg:city":"Cowbridge",
    "sg:classifiers":[
        {
            "category":"Professional",
            "subcategory":"Computer Services",
            "type":"Services"
        }
    ],
    "sg:postcode":"CF71 7DT",
    "sg:province":"The Vale of Glamorgan",
    "sg:tags":[
        "system",
        "software"
    ],
    "wof:name":"Microware",
    "wof:placetype":"venue"
},
  "geometry": {"coordinates":[-3.4504249096,51.4623908997],"type":"Point"}
}