{
  "type": "Feature",
  "properties": {
    "addr:full":"New Road, Dowlais Merthyr Tydfil Caerphilly CF48 3DA",
    "addr:postcode":"cf48 3da",
    "addr:street":"New Road",
    "iso:country":"GB",
    "sg:address":"New Road, Dowlais",
    "sg:city":"Merthyr Tydfil",
    "sg:classifiers":[
        {
            "category":"Autos & Motor Vehicles",
            "subcategory":"Fuel & Gas Station",
            "type":"Retail Goods"
        }
    ],
    "sg:phone":"+44 1685 722363",
    "sg:postcode":"CF48 3DA",
    "sg:province":"Caerphilly",
    "sg:tags":[
        "hr",
        "petrol"
    ],
    "wof:name":"Dowlais Service Station",
    "wof:placetype":"venue"
},
  "geometry": {"coordinates":[-3.3517639637,51.7607002258],"type":"Point"}
}