{
  "type": "Feature",
  "properties": {
    "addr:full":"21 Hartley Road Exmouth Devon EX8 2SG",
    "addr:housenumber":"21",
    "addr:postcode":"ex8 2sg",
    "addr:street":"Hartley Road",
    "iso:country":"GB",
    "sg:address":"21 Hartley Road",
    "sg:city":"Exmouth",
    "sg:classifiers":[
        {
            "category":"Health Services",
            "subcategory":"Hospital",
            "type":"Services"
        }
    ],
    "sg:postcode":"EX8 2SG",
    "sg:province":"Devon",
    "wof:name":"Exmouth Learning Disability Team",
    "wof:placetype":"venue"
},
  "geometry": {"coordinates":[-3.4080750942,50.6175231934],"type":"Point"}
}