{
  "type": "Feature",
  "properties": {
    "iso:country":"GB",
    "sg:address":"10 Watery Lane, Ashton On Ribble",
    "sg:city":"Preston",
    "sg:classifiers":[
        {
            "category":"Fast Food",
            "type":"Food & Drink"
        },
        {
            "category":"Food & Beverages",
            "subcategory":"Meat & Fish",
            "type":"Retail Goods"
        }
    ],
    "sg:phone":"+44 1772 726097",
    "sg:postcode":"PR2 2NN",
    "sg:province":"Lancashire",
    "sg:tags":[
        "shop",
        "chip"
    ],
    "wof:name":"Umberto's",
    "wof:placetype":"venue"
},
  "geometry": {"coordinates":[-2.7239439487,53.7636528015],"type":"Point"}
}