{
  "type": "Feature",
  "properties": {
    "iso:country":"GB",
    "sg:address":"174 High Street, Cradley Heath",
    "sg:city":"Smethwick",
    "sg:classifiers":[
        {
            "category":"Communications",
            "type":"Services"
        }
    ],
    "sg:phone":"+44 1384 566778",
    "sg:postcode":"B64 5HN",
    "sg:province":"West Midlands",
    "sg:tags":[
        "tv",
        "video",
        "radio"
    ],
    "wof:name":"Superview",
    "wof:placetype":"venue"
},
  "geometry": {"coordinates":[-2.081857,52.47245],"type":"Point"}
}