{
  "type": "Feature",
  "properties": {
    "addr:full":"The Old Vicarage, Town Hall Square Llanelli Carmarthenshire SA15 3DD",
    "addr:postcode":"sa15 3dd",
    "addr:street":"Square;Carmarthenshire",
    "iso:country":"GB",
    "sg:address":"The Old Vicarage, Town Hall Square",
    "sg:city":"Llanelli",
    "sg:classifiers":[
        {
            "category":"Organizations",
            "subcategory":"Non-profit Organization",
            "type":"Services"
        }
    ],
    "sg:phone":"+44 1554 774352",
    "sg:postcode":"SA15 3DD",
    "sg:province":"Carmarthenshire",
    "sg:tags":[
        "charitable",
        "organisation",
        "voluntary",
        "charity"
    ],
    "wof:name":"Llanelli & District Talking Newspapers For The Blind",
    "wof:placetype":"venue"
},
  "geometry": {"coordinates":[-4.1342988014,51.6826820374],"type":"Point"}
}