{
  "type": "Feature",
  "properties": {
    "addr:full":"Topaz, Saint Catherines Drive Faversham Kent ME13 8LQ",
    "addr:postcode":"me13 8lq",
    "addr:street":"Saint Catherines Drive",
    "iso:country":"GB",
    "sg:address":"Topaz, Saint Catherines Drive",
    "sg:city":"Faversham",
    "sg:classifiers":[
        {
            "category":"Building & Trades",
            "subcategory":"Construction",
            "type":"Services"
        }
    ],
    "sg:postcode":"ME13 8LQ",
    "sg:province":"Kent",
    "sg:tags":[
        "roofing"
    ],
    "wof:name":"Topaz Electrical Ltd",
    "wof:placetype":"venue"
},
  "geometry": {"coordinates":[0.891638,51.309036],"type":"Point"}
}