{
  "type": "Feature",
  "properties": {
    "iso:country":"GB",
    "sg:address":"187 Whiteladies Road, Clifton",
    "sg:city":"Bristol",
    "sg:classifiers":[
        {
            "category":"Banks & Credit Unions",
            "subcategory":"Financial Services",
            "type":"Services"
        }
    ],
    "sg:phone":"+44 117 300 7097",
    "sg:postcode":"BS8 2RY",
    "sg:province":"City of Bristol",
    "sg:tags":[
        "consultant"
    ],
    "wof:name":"Ocean Financial Services Ltd.",
    "wof:placetype":"venue"
},
  "geometry": {"coordinates":[-2.6140160561,51.4693336487],"type":"Point"}
}