{
  "type": "Feature",
  "properties": {
    "addr:full":"19a Park Mall Ashford Kent TN24 8RY",
    "addr:housenumber":"19a",
    "addr:postcode":"tn24 8ry",
    "addr:street":"Park Mall",
    "iso:country":"GB",
    "sg:address":"19a Park Mall",
    "sg:city":"Ashford",
    "sg:classifiers":[
        {
            "category":"Commercial Area",
            "type":"Public Place"
        }
    ],
    "sg:phone":"+44 1233 630811",
    "sg:postcode":"TN24 8RY",
    "sg:province":"Kent",
    "sg:tags":[
        "shop",
        "centre"
    ],
    "wof:name":"Park Mall Shopping Centre",
    "wof:placetype":"venue"
},
  "geometry": {"coordinates":[0.8725129962,51.1498222351],"type":"Point"}
}