{
  "type": "Feature",
  "properties": {
    "addr:full":"Tarrel Kyle Highland IV20 1SL",
    "addr:postcode":"iv20 1sl",
    "addr:street":"Tarrel",
    "iso:country":"GB",
    "sg:address":"Tarrel",
    "sg:city":"Kyle",
    "sg:classifiers":[
        {
            "category":"Farming",
            "subcategory":"Farm",
            "type":"Manufacturing & Wholesale Goods"
        }
    ],
    "sg:phone":"+44 1862 871248",
    "sg:postcode":"IV20 1SL",
    "sg:province":"Highland",
    "sg:tags":[
        "mixed",
        "crop"
    ],
    "wof:name":"Young S G",
    "wof:placetype":"venue"
},
  "geometry": {"coordinates":[-3.9018828869,57.7864837646],"type":"Point"}
}