{
  "type": "Feature",
  "properties": {
    "iso:country":"GB",
    "sg:address":"20 Blantyre Street",
    "sg:city":"Elgin",
    "sg:classifiers":[
        {
            "category":"Building & Trades",
            "subcategory":"Construction",
            "type":"Services"
        }
    ],
    "sg:phone":"+44 1343 544473",
    "sg:postcode":"IV30 4DW",
    "sg:province":"Moray",
    "sg:tags":[
        "roofing"
    ],
    "wof:name":"Douglas Melvin",
    "wof:placetype":"venue"
},
  "geometry": {"coordinates":[-3.3190779686,57.6559181213],"type":"Point"}
}