{
  "type": "Feature",
  "properties": {
    "addr:full":"Bolton Road, Boxwood Court Stevenage Hertfordshire SG1 4QX",
    "addr:postcode":"sg1 4qx",
    "addr:street":"Bolton Road Boxwood Court",
    "iso:country":"GB",
    "sg:address":"Bolton Road, Boxwood Court",
    "sg:city":"Stevenage",
    "sg:classifiers":[
        {
            "category":"Manufacturing",
            "subcategory":"Wood Products",
            "type":"Manufacturing & Wholesale Goods"
        }
    ],
    "sg:phone":"+44 1438 742400",
    "sg:postcode":"SG1 4QX",
    "sg:province":"Hertfordshire",
    "sg:tags":[
        "packaging",
        "crate",
        "pallets"
    ],
    "wof:name":"Clear-Sell Ltd.",
    "wof:placetype":"venue"
},
  "geometry": {"coordinates":[-0.1886799932,51.9056091309],"type":"Point"}
}