{
  "type": "Feature",
  "properties": {
    "addr:full":"Unit 13 Bright Rd Manchester Greater Manchester M30 0WG",
    "addr:housenumber":"unit 13",
    "addr:postcode":"m30 0wg",
    "addr:street":"Bright Rd",
    "iso:country":"GB",
    "sg:address":"Unit 13 Bright Rd",
    "sg:city":"Manchester",
    "sg:classifiers":[
        {
            "category":"Building & Trades",
            "subcategory":"Construction",
            "type":"Services"
        }
    ],
    "sg:phone":"+44 161 707 4602",
    "sg:postcode":"M30 0WG",
    "sg:province":"Greater Manchester",
    "sg:tags":[
        "pipework",
        "contractor"
    ],
    "wof:name":"J F & J Pooley",
    "wof:placetype":"venue"
},
  "geometry": {"coordinates":[-2.3450040817,53.485080719],"type":"Point"}
}