{
  "type": "Feature",
  "properties": {
    "addr:full":"5 Guest Avenue Poole Dorset BH12 1JA",
    "addr:housenumber":"5",
    "addr:postcode":"bh12 1ja",
    "addr:street":"Guest Avenue",
    "iso:country":"GB",
    "sg:address":"5 Guest Avenue",
    "sg:city":"Poole",
    "sg:classifiers":[
        {
            "category":"Arts & Performance",
            "subcategory":"Art Gallery",
            "type":"Entertainment"
        },
        {
            "category":"Museum",
            "type":"Entertainment"
        }
    ],
    "sg:phone":"+44 1202 731882",
    "sg:postcode":"BH12 1JA",
    "sg:province":"Dorset",
    "wof:name":"Michael Weber",
    "wof:placetype":"venue"
},
  "geometry": {"coordinates":[-1.9143010378,50.7350959778],"type":"Point"}
}