{
  "type": "Feature",
  "properties": {
    "addr:full":"10 The Glen Bedford Bedfordshire MK42 7EL",
    "addr:housenumber":"10",
    "addr:postcode":"mk42 7el",
    "addr:street":"The Glen",
    "iso:country":"GB",
    "sg:address":"10 The Glen",
    "sg:city":"Bedford",
    "sg:classifiers":[
        {
            "category":"Building & Trades",
            "subcategory":"Construction",
            "type":"Services"
        }
    ],
    "sg:phone":"+44 1234 853659",
    "sg:postcode":"MK42 7EL",
    "sg:province":"Bedfordshire",
    "sg:tags":[
        "joiner",
        "carpenter"
    ],
    "wof:name":"D J Palmer",
    "wof:placetype":"venue"
},
  "geometry": {"coordinates":[-0.500276,52.115181],"type":"Point"}
}