{
  "type": "Feature",
  "properties": {
    "iso:country":"GB",
    "sg:address":"31 West Street",
    "sg:city":"Wimborne",
    "sg:classifiers":[
        {
            "category":"Professional",
            "subcategory":"Lawyer & Legal Services",
            "type":"Services"
        }
    ],
    "sg:phone":"+44 1202 885211",
    "sg:postcode":"BH21 1JT",
    "sg:province":"Dorset",
    "sg:tags":[
        "solicitor"
    ],
    "wof:name":"Steele Raymond",
    "wof:placetype":"venue"
},
  "geometry": {"coordinates":[-1.9892799854,50.800075531],"type":"Point"}
}