{
  "type": "Feature",
  "properties": {
    "addr:full":"35 Sheering Lower Road Sawbridgeworth Essex CM21 9LF",
    "addr:housenumber":"35",
    "addr:postcode":"cm21 9lf",
    "addr:street":"Sheering Lower Road",
    "iso:country":"GB",
    "sg:address":"35 Sheering Lower Road",
    "sg:city":"Sawbridgeworth",
    "sg:classifiers":[
        {
            "category":"Retail",
            "subcategory":"Driving School",
            "type":"Services"
        },
        {
            "category":"Education",
            "subcategory":"University",
            "type":"Public Place"
        }
    ],
    "sg:phone":"+44 1279 722735",
    "sg:postcode":"CM21 9LF",
    "sg:province":"Essex",
    "sg:tags":[
        "higher"
    ],
    "wof:name":"Compass",
    "wof:placetype":"venue"
},
  "geometry": {"coordinates":[0.157659,51.801315],"type":"Point"}
}