{
  "type": "Feature",
  "properties": {
    "iso:country":"GB",
    "sg:address":"30 St Giles Street, New Bradwell",
    "sg:city":"Milton Keynes",
    "sg:classifiers":[
        {
            "category":"Professional",
            "subcategory":"Accounting & Tax Preparation",
            "type":"Services"
        }
    ],
    "sg:phone":"+44 1908 223206",
    "sg:postcode":"MK13 0BE",
    "sg:province":"Buckinghamshire",
    "sg:tags":[
        "accountant",
        "activites",
        "primarily",
        "bookeeping"
    ],
    "wof:name":"QUANTUM ACCOUNTING SERVICES LTD",
    "wof:placetype":"venue"
},
  "geometry": {"coordinates":[-0.794876,52.064716],"type":"Point"}
}