{
  "type": "Feature",
  "properties": {
    "addr:full":"Colwyn Bay Delivery Office, 46 Princes Dr Colwyn Bay Conwy LL29 8HY",
    "addr:housenumber":"46",
    "addr:postcode":"ll29 8hy",
    "addr:street":"Princes Dr",
    "iso:country":"GB",
    "sg:address":"Colwyn Bay Delivery Office, 46 Princes Dr",
    "sg:city":"Colwyn Bay",
    "sg:classifiers":[
        {
            "category":"Utilities",
            "subcategory":"Refuse",
            "type":"Services"
        }
    ],
    "sg:postcode":"LL29 8HY",
    "sg:province":"Conwy",
    "sg:tags":[
        "disposal",
        "waste"
    ],
    "wof:name":"Clean Easy Drain Services",
    "wof:placetype":"venue"
},
  "geometry": {"coordinates":[-3.725414,53.293911],"type":"Point"}
}