{
  "type": "Feature",
  "properties": {
    "addr:full":"2 Kelvedon Rd, Walmer Deal Kent CT14 7HX",
    "addr:housenumber":"2",
    "addr:postcode":"ct14 7hx",
    "addr:street":"Kelvedon Rd;Deal",
    "iso:country":"GB",
    "sg:address":"2 Kelvedon Rd, Walmer",
    "sg:city":"Deal",
    "sg:classifiers":[
        {
            "category":"Manufacturing",
            "subcategory":"Building Materials",
            "type":"Manufacturing & Wholesale Goods"
        }
    ],
    "sg:phone":"+44 1304 367940",
    "sg:postcode":"CT14 7HX",
    "sg:province":"Kent",
    "sg:tags":[
        "tarmac",
        "asphalt"
    ],
    "wof:name":"Godden Construction & Plant Hire",
    "wof:placetype":"venue"
},
  "geometry": {"coordinates":[1.3971409798,51.2077598572],"type":"Point"}
}