{
  "type": "Feature",
  "properties": {
    "iso:country":"GB",
    "sg:address":"Tabard House",
    "sg:city":"London",
    "sg:classifiers":[
        {
            "category":"Professional",
            "subcategory":"Engineering",
            "type":"Services"
        }
    ],
    "sg:phone":"+44 20 7593 0098",
    "sg:postcode":"SE1 0TA",
    "sg:province":"Greater London",
    "sg:tags":[
        "consulting",
        "design",
        "engineer"
    ],
    "wof:name":"Yolles Partnership Ltd.",
    "wof:placetype":"venue"
},
  "geometry": {"coordinates":[-0.0879139975,51.5073699951],"type":"Point"}
}