{
  "type": "Feature",
  "properties": {
    "addr:full":"193 High Street, Kelvedon Colchester Essex CO5 9JD",
    "addr:housenumber":"193",
    "addr:postcode":"co5 9jd",
    "addr:street":"High Street",
    "iso:country":"GB",
    "sg:address":"193 High Street, Kelvedon",
    "sg:city":"Colchester",
    "sg:classifiers":[
        {
            "category":"Building & Trades",
            "subcategory":"Landscaping Services",
            "type":"Services"
        }
    ],
    "sg:phone":"+44 1376 570508",
    "sg:postcode":"CO5 9JD",
    "sg:province":"Essex",
    "sg:tags":[
        "design",
        "garden"
    ],
    "wof:name":"Carolyn Hinds",
    "wof:placetype":"venue"
},
  "geometry": {"coordinates":[0.7038779855,51.8395843506],"type":"Point"}
}