{
  "type": "Feature",
  "properties": {
    "addr:full":"157 Plaistow Road London Greater London E15 3ET",
    "addr:housenumber":"157",
    "addr:postcode":"e15 3et",
    "addr:street":"Plaistow Road",
    "iso:country":"GB",
    "sg:address":"157 Plaistow Road",
    "sg:city":"London",
    "sg:classifiers":[
        {
            "category":"Fast Food",
            "type":"Food & Drink"
        }
    ],
    "sg:phone":"+44 20 8519 1419",
    "sg:postcode":"E15 3ET",
    "sg:province":"Greater London",
    "sg:tags":[
        "away",
        "take"
    ],
    "wof:name":"China Express",
    "wof:placetype":"venue"
},
  "geometry": {"coordinates":[0.01334,51.533409],"type":"Point"}
}