{
  "type": "Feature",
  "properties": {
    "iso:country":"GB",
    "sg:address":"52 Wentworth Drive",
    "sg:city":"Bishops Stortford",
    "sg:classifiers":[
        {
            "category":"Professional",
            "subcategory":"Accounting & Tax Preparation",
            "type":"Services"
        }
    ],
    "sg:postcode":"CM23 2PD",
    "sg:province":"Essex",
    "sg:tags":[
        "accountant"
    ],
    "wof:name":"Andrew Hardy & Co",
    "wof:placetype":"venue"
},
  "geometry": {"coordinates":[0.146371007,51.8661384583],"type":"Point"}
}