{
  "type": "Feature",
  "properties": {
    "iso:country":"GB",
    "sg:address":"206 Central Drive",
    "sg:city":"Blackpool",
    "sg:classifiers":[
        {
            "category":"Personal",
            "type":"Services"
        },
        {
            "category":"Shopping",
            "subcategory":"Bridal",
            "type":"Retail Goods"
        }
    ],
    "sg:phone":"+44 1253 622306",
    "sg:postcode":"FY1 5EB",
    "sg:province":"Lancashire",
    "sg:tags":[
        "shop",
        "dressmaker",
        "gown"
    ],
    "wof:name":"A Stitch in Time",
    "wof:placetype":"venue"
},
  "geometry": {"coordinates":[-3.045998,53.809708],"type":"Point"}
}