{
  "type": "Feature",
  "properties": {
    "iso:country":"GB",
    "sg:address":"Chadwell Place Farm, Chadwell St Mary",
    "sg:city":"Grays",
    "sg:classifiers":[
        {
            "category":"Farming",
            "subcategory":"Farm",
            "type":"Manufacturing & Wholesale Goods"
        }
    ],
    "sg:phone":"+44 1375 842727",
    "sg:postcode":"RM16 4AX",
    "sg:province":"Essex",
    "sg:tags":[
        "mixed",
        "crop"
    ],
    "wof:name":"Ray Osborne",
    "wof:placetype":"venue"
},
  "geometry": {"coordinates":[0.368965,51.480579],"type":"Point"}
}