{
  "type": "Feature",
  "properties": {
    "addr:full":"46 Baberton Mains Dell Edinburgh City of Edinburgh EH14 3DQ",
    "addr:housenumber":"46",
    "addr:postcode":"eh14 3dq",
    "addr:street":"Baberton Mains",
    "iso:country":"GB",
    "sg:address":"46 Baberton Mains Dell",
    "sg:city":"Edinburgh",
    "sg:classifiers":[
        {
            "category":"Taxi",
            "type":"Transportation"
        }
    ],
    "sg:postcode":"EH14 3DQ",
    "sg:province":"City of Edinburgh",
    "sg:tags":[
        "mini",
        "cab"
    ],
    "wof:name":"Clantrip Ltd.",
    "wof:placetype":"venue"
},
  "geometry": {"coordinates":[-3.289766,55.911903],"type":"Point"}
}