{
  "type": "Feature",
  "properties": {
    "addr:full":"1 Oxford St Wellingborough Northamptonshire NN8 4JE",
    "addr:housenumber":"1",
    "addr:postcode":"nn8 4je",
    "addr:street":"Oxford St",
    "iso:country":"GB",
    "sg:address":"1 Oxford St",
    "sg:city":"Wellingborough",
    "sg:classifiers":[
        {
            "category":"Professional",
            "subcategory":"Lawyer & Legal Services",
            "type":"Services"
        }
    ],
    "sg:phone":"+44 1933 223796",
    "sg:postcode":"NN8 4JE",
    "sg:province":"Northamptonshire",
    "sg:tags":[
        "advice",
        "counselling"
    ],
    "wof:name":"C A N",
    "wof:placetype":"venue"
},
  "geometry": {"coordinates":[-0.695274,52.301422],"type":"Point"}
}