{
  "type": "Feature",
  "properties": {
    "addr:full":"36 New Road Eastleigh Hampshire SO50 8EN",
    "addr:housenumber":"36",
    "addr:postcode":"so50 8en",
    "addr:street":"New Road",
    "iso:country":"GB",
    "sg:address":"36 New Road",
    "sg:city":"Eastleigh",
    "sg:classifiers":[
        {
            "category":"Professional",
            "subcategory":"Engineering",
            "type":"Services"
        }
    ],
    "sg:href":"http://api.simplegeo.com/1.0/features/SG_0qIkJZIjPClG37obwfMCwf_50.966122_-1.309196@1300740015.json",
    "sg:postcode":"SO50 8EN",
    "sg:province":"Hampshire",
    "sg:tags":[
        "gas",
        "engineer"
    ],
    "wof:name":"Patrick L Gibby",
    "wof:placetype":"venue"
},
  "geometry": {"coordinates":[-1.309196,50.966122],"type":"Point"}
}