{"geometry":{"type":"Point","coordinates":[-1.309196,50.966122]},"type":"Feature","id":102560573,"bbox":[-1.309196,50.966122,-1.309196,50.966122],"properties":{"sg:province":"Hampshire","sg:tags":["gas","engineer"],"geom:longitude":-1.309196,"wof:breaches":[],"sg:href":"http://api.simplegeo.com/1.0/features/SG_0qIkJZIjPClG37obwfMCwf_50.966122_-1.309196@1300740015.json","sg:owner":"simplegeo","sg:postcode":"SO50 8EN","geom:latitude":50.966122,"sg:classifiers":[{"category":"Professional","type":"Services","subcategory":"Engineering"}],"sg:address":"36 New Road","wof:hierarchy":[{"venue_id":102560573,"country_id":85633159,"neighbourhood_id":85790467,"region_id":85684375}],"geom:area":0.000000,"sg:city":"Eastleigh","wof:lastmodified":1438093294,"iso:country":"GB","wof:geomhash":"69f765adaff1db10fb6fb83c09e4b940","wof:name":"Patrick L Gibby","wof:belongsto":[85633159,85790467,85684375],"src:geom":"simplegeo","wof:placetype":"venue","wof:supersedes":[],"wof:id":102560573,"wof:superseded_by":[],"wof:concordances":{"sg:id":"SG_0qIkJZIjPClG37obwfMCwf_50.966122_-1.309196@1300740015"},"wof:parent_id":85790467}}