{
  "type": "Feature",
  "properties": {
    "iso:country":"GB",
    "sg:address":"Unit 26 The Parker Centre, Mansfield Rd",
    "sg:city":"Derby",
    "sg:classifiers":[
        {
            "category":"Professional",
            "subcategory":"Computer Services",
            "type":"Services"
        }
    ],
    "sg:phone":"+44 1332 366161",
    "sg:postcode":"DE21 4SZ",
    "sg:province":"Derbyshire",
    "sg:tags":[
        "system",
        "software"
    ],
    "wof:name":"Peripheral Technology International Ltd",
    "wof:placetype":"venue"
},
  "geometry": {"coordinates":[-1.4672329426,52.9358100891],"type":"Point"}
}