{
  "type": "Feature",
  "properties": {
    "iso:country":"GB",
    "sg:address":"London Road (a21), Hurst Green",
    "sg:city":"Etchingham",
    "sg:classifiers":[
        {
            "category":"Autos & Motor Vehicles",
            "subcategory":"Fuel & Gas Station",
            "type":"Retail Goods"
        }
    ],
    "sg:phone":"+44 1580 860120",
    "sg:postcode":"TN19 7QR",
    "sg:province":"East Sussex",
    "sg:tags":[
        "hr",
        "petrol"
    ],
    "wof:name":"Ashdene Service Station - Nort",
    "wof:placetype":"venue"
},
  "geometry": {"coordinates":[0.470265,51.018085],"type":"Point"}
}