{
  "type": "Feature",
  "properties": {
    "addr:full":"78 Waterloo Rd Stoke-on-trent Staffordshire ST6 3EX",
    "addr:housenumber":"78",
    "addr:postcode":"st6 3ex",
    "addr:street":"Waterloo Rd",
    "iso:country":"GB",
    "sg:address":"78 Waterloo Rd",
    "sg:city":"Stoke-on-trent",
    "sg:classifiers":[
        {
            "category":"Shopping",
            "type":"Retail Goods"
        }
    ],
    "sg:postcode":"ST6 3EX",
    "sg:province":"Staffordshire",
    "sg:tags":[
        "part",
        "accessory"
    ],
    "wof:name":"Jones,Alan,",
    "wof:placetype":"venue"
},
  "geometry": {"coordinates":[-2.1938641071,53.0424423218],"type":"Point"}
}