{
  "type": "Feature",
  "properties": {
    "addr:full":"8 Main Street Strathaven South Lanarkshire ML10 6AJ",
    "addr:housenumber":"8",
    "addr:postcode":"ml10 6aj",
    "addr:street":"Main Street",
    "iso:country":"GB",
    "sg:address":"8 Main Street",
    "sg:city":"Strathaven",
    "sg:classifiers":[
        {
            "category":"Food & Beverages",
            "subcategory":"Specialty",
            "type":"Retail Goods"
        }
    ],
    "sg:postcode":"ML10 6AJ",
    "sg:province":"South Lanarkshire",
    "sg:tags":[
        "product",
        "health"
    ],
    "wof:name":"Wholefood Harvest",
    "wof:placetype":"venue"
},
  "geometry": {"coordinates":[-4.0953669548,55.7112541199],"type":"Point"}
}