{
  "type": "Feature",
  "properties": {
    "addr:full":"13 High Street, Prestwood Great Missenden Buckinghamshire HP16 9EE",
    "addr:housenumber":"13",
    "addr:postcode":"hp16 9ee",
    "addr:street":"High Street Prestwood",
    "iso:country":"GB",
    "sg:address":"13 High Street, Prestwood",
    "sg:city":"Great Missenden",
    "sg:classifiers":[
        {
            "category":"Professional",
            "subcategory":"Computer Services",
            "type":"Services"
        }
    ],
    "sg:postcode":"HP16 9EE",
    "sg:province":"Buckinghamshire",
    "sg:tags":[
        "consultant"
    ],
    "wof:name":"Ray Kirkham & Partners",
    "wof:placetype":"venue"
},
  "geometry": {"coordinates":[-0.7297840118,51.6998748779],"type":"Point"}
}