{
  "type": "Feature",
  "properties": {
    "iso:country":"GB",
    "sg:address":"1a Copeland Rd, Walthamstow",
    "sg:city":"Walthamstow",
    "sg:classifiers":[
        {
            "category":"Place Of Worship",
            "type":"Public Place"
        }
    ],
    "sg:phone":"+44 20 8521 1361",
    "sg:postcode":"E17 9DB",
    "sg:province":"Greater London",
    "wof:name":"St Stephens C Of E Church",
    "wof:placetype":"venue"
},
  "geometry": {"coordinates":[-0.011519,51.578815],"type":"Point"}
}