{
  "type": "Feature",
  "properties": {
    "addr:full":"404 Bradford Road Batley West Yorkshire WF17 5LZ",
    "addr:housenumber":"404",
    "addr:postcode":"wf17 5lz",
    "addr:street":"Bradford Road",
    "iso:country":"GB",
    "sg:address":"404 Bradford Road",
    "sg:city":"Batley",
    "sg:classifiers":[
        {
            "category":"Home & Garden",
            "subcategory":"Home Furnishings",
            "type":"Retail Goods"
        }
    ],
    "sg:phone":"+44 1924 420886",
    "sg:postcode":"WF17 5LZ",
    "sg:province":"West Yorkshire",
    "sg:tags":[
        "blind",
        "curtain",
        "fitting"
    ],
    "wof:name":"Style Interior Design",
    "wof:placetype":"venue"
},
  "geometry": {"coordinates":[-1.626754,53.711956],"type":"Point"}
}