{
  "type": "Feature",
  "properties": {
    "addr:full":"Dudman Rd Truro Cornwall TR1 3PP",
    "addr:postcode":"tr1 3pp",
    "addr:street":"Dudman Rd",
    "iso:country":"GB",
    "sg:address":"Dudman Rd",
    "sg:city":"Truro",
    "sg:classifiers":[
        {
            "category":"Home & Garden",
            "subcategory":"Garden Supply",
            "type":"Retail Goods"
        }
    ],
    "sg:phone":"+44 1872 274710",
    "sg:postcode":"TR1 3PP",
    "sg:province":"Cornwall",
    "sg:tags":[
        "tree",
        "shrub"
    ],
    "wof:name":"Three Spires Tree Nurseries",
    "wof:placetype":"venue"
},
  "geometry": {"coordinates":[-5.077354,50.260906],"type":"Point"}
}