{
  "type": "Feature",
  "properties": {
    "iso:country":"GB",
    "sg:address":"18 Clay Avenue",
    "sg:city":"Nuneaton",
    "sg:classifiers":[
        {
            "category":"Taxi",
            "type":"Transportation"
        }
    ],
    "sg:phone":"+44 24 7632 9999",
    "sg:postcode":"CV11 6DU",
    "sg:province":"Leicestershire",
    "sg:tags":[
        "mini",
        "cab"
    ],
    "wof:name":"1st Taxis",
    "wof:placetype":"venue"
},
  "geometry": {"coordinates":[-1.445535,52.536877],"type":"Point"}
}