{
  "type": "Feature",
  "properties": {
    "iso:country":"GB",
    "sg:address":"8 Tower Centre",
    "sg:city":"Hoddesdon",
    "sg:classifiers":[
        {
            "category":"Personal",
            "subcategory":"Barber",
            "type":"Services"
        }
    ],
    "sg:phone":"+44 1992 465722",
    "sg:postcode":"EN11 8UB",
    "sg:province":"Essex",
    "sg:tags":[
        "men's",
        "hairdresser"
    ],
    "wof:name":"George's",
    "wof:placetype":"venue"
},
  "geometry": {"coordinates":[-0.0132550001,51.7678413391],"type":"Point"}
}