{
  "type": "Feature",
  "properties": {
    "iso:country":"GB",
    "sg:address":"57 Timbers Sq",
    "sg:city":"Cardiff",
    "sg:classifiers":[
        {
            "category":"Building & Trades",
            "subcategory":"Construction",
            "type":"Services"
        }
    ],
    "sg:phone":"+44 29 2049 7043",
    "sg:postcode":"CF2 3SH",
    "sg:province":"Cardiff",
    "sg:tags":[
        "roofing"
    ],
    "wof:name":"Coverwell Roofing",
    "wof:placetype":"venue"
},
  "geometry": {"coordinates":[-3.15786,51.491947],"type":"Point"}
}