{
  "type": "Feature",
  "properties": {
    "iso:country":"GB",
    "sg:address":"Inshes Retail Park",
    "sg:city":"Inverness",
    "sg:classifiers":[
        {
            "category":"Food & Beverages",
            "subcategory":"Supermarket",
            "type":"Retail Goods"
        }
    ],
    "sg:phone":"+44 1463 880500",
    "sg:postcode":"IV2 3TW",
    "sg:province":"Highland",
    "wof:name":"Tesco",
    "wof:placetype":"venue"
},
  "geometry": {"coordinates":[-4.20031,57.467602],"type":"Point"}
}