{
  "type": "Feature",
  "properties": {
    "addr:full":"Haggersgate Ho, Haggersgate Whitby North Yorkshire YO21 3PP",
    "addr:postcode":"yo21 3pp",
    "addr:street":"Haggersgate;Haggersgate",
    "iso:country":"GB",
    "sg:address":"Haggersgate Ho, Haggersgate",
    "sg:city":"Whitby",
    "sg:classifiers":[
        {
            "category":"Education",
            "subcategory":"University",
            "type":"Public Place"
        }
    ],
    "sg:phone":"+44 1947 600545",
    "sg:postcode":"YO21 3PP",
    "sg:province":"North Yorkshire",
    "sg:tags":[
        "adult"
    ],
    "wof:name":"Centre For Continuing Education Development & Training The",
    "wof:placetype":"venue"
},
  "geometry": {"coordinates":[-0.6147930026,54.4878997803],"type":"Point"}
}