{
  "type": "Feature",
  "properties": {
    "iso:country":"GB",
    "sg:address":"11 Packhorse Road",
    "sg:city":"Gerrards Cross",
    "sg:classifiers":[
        {
            "category":"Communications",
            "type":"Services"
        }
    ],
    "sg:phone":"+44 1753 883243",
    "sg:postcode":"SL9 7QA",
    "sg:province":"Buckinghamshire",
    "sg:tags":[
        "tv",
        "video",
        "radio"
    ],
    "wof:name":"The Video Factor Ltd.",
    "wof:placetype":"venue"
},
  "geometry": {"coordinates":[-0.555089,51.586754],"type":"Point"}
}