{
  "type": "Feature",
  "properties": {
    "addr:full":"16 The Maltings, Keith Place Inverkeithing Fife KY11 1NE",
    "addr:housenumber":"16",
    "addr:postcode":"ky11 1ne",
    "addr:street":"The Maltings Keith Place Inverkeithing",
    "iso:country":"GB",
    "sg:address":"16 The Maltings, Keith Place",
    "sg:city":"Inverkeithing",
    "sg:classifiers":[
        {
            "category":"Professional",
            "subcategory":"Art Services",
            "type":"Services"
        }
    ],
    "sg:phone":"+44 1383 860809",
    "sg:postcode":"KY11 1NE",
    "sg:province":"Fife",
    "sg:tags":[
        "photographer"
    ],
    "wof:name":"Picture This",
    "wof:placetype":"venue"
},
  "geometry": {"coordinates":[-3.3976790905,56.0311317444],"type":"Point"}
}