{
  "type": "Feature",
  "properties": {
    "iso:country":"GB",
    "sg:address":"5 St Thomas Road",
    "sg:city":"Brentwood",
    "sg:classifiers":[
        {
            "category":"Professional",
            "subcategory":"Employment Agencies",
            "type":"Services"
        }
    ],
    "sg:phone":"+44 1277 228486",
    "sg:postcode":"CM14 4DB",
    "sg:province":"Essex",
    "sg:tags":[
        "consultant"
    ],
    "wof:name":"Nicholls Browning Ltd.",
    "wof:placetype":"venue"
},
  "geometry": {"coordinates":[0.3040620089,51.6198501587],"type":"Point"}
}