{
  "type": "Feature",
  "properties": {
    "iso:country":"GB",
    "sg:address":"73 Silbury Arcade",
    "sg:city":"Milton Keynes",
    "sg:classifiers":[
        {
            "category":"Shopping",
            "subcategory":"Shoes",
            "type":"Retail Goods"
        }
    ],
    "sg:phone":"+44 1908 670896",
    "sg:postcode":"MK9 3AG",
    "sg:province":"Buckinghamshire",
    "sg:tags":[
        "shop"
    ],
    "wof:name":"Barratt Shoes",
    "wof:placetype":"venue"
},
  "geometry": {"coordinates":[-0.759709,52.043072],"type":"Point"}
}