{
  "type": "Feature",
  "properties": {
    "addr:full":"125 High St Fort William Highland PH33 6DG",
    "addr:housenumber":"125",
    "addr:postcode":"ph33 6dg",
    "addr:street":"High St",
    "iso:country":"GB",
    "sg:address":"125 High St",
    "sg:city":"Fort William",
    "sg:classifiers":[
        {
            "category":"Health Services",
            "subcategory":"Dentist",
            "type":"Services"
        }
    ],
    "sg:phone":"+44 1397 702501",
    "sg:postcode":"PH33 6DG",
    "sg:province":"Highland",
    "wof:name":"J Muir & Associates",
    "wof:placetype":"venue"
},
  "geometry": {"coordinates":[-5.1132478714,56.8169898987],"type":"Point"}
}