{
  "type": "Feature",
  "properties": {
    "iso:country":"GB",
    "sg:address":"2 Trent Road, Midanbury",
    "sg:city":"Southampton",
    "sg:classifiers":[
        {
            "category":"Building & Trades",
            "subcategory":"Construction",
            "type":"Services"
        }
    ],
    "sg:postcode":"SO18 4PP",
    "sg:province":"Hampshire",
    "sg:tags":[
        "builder"
    ],
    "wof:name":"J C C Construction Ltd",
    "wof:placetype":"venue"
},
  "geometry": {"coordinates":[-1.366916,50.925846],"type":"Point"}
}