{
  "type": "Feature",
  "properties": {
    "addr:full":"Tavistock House South, Tavistock Square London Greater London WC1H 9LS",
    "addr:postcode":"wc1h 9ls",
    "addr:street":"South Tavistock Square",
    "iso:country":"GB",
    "sg:address":"Tavistock House South, Tavistock Square",
    "sg:city":"London",
    "sg:classifiers":[
        {
            "category":"Professional",
            "subcategory":"Lawyer & Legal Services",
            "type":"Services"
        }
    ],
    "sg:phone":"+44 20 7383 7111",
    "sg:postcode":"WC1H 9LS",
    "sg:province":"Greater London",
    "sg:tags":[
        "solicitor"
    ],
    "wof:name":"Lockharts Ltd.",
    "wof:placetype":"venue"
},
  "geometry": {"coordinates":[-0.128580004,51.525718689],"type":"Point"}
}