{
  "type": "Feature",
  "properties": {
    "addr:full":", Tedburn St Mary Exeter Devon EX6 6EB",
    "addr:postcode":"ex6 6eb",
    "iso:country":"GB",
    "sg:address":", Tedburn St Mary",
    "sg:city":"Exeter",
    "sg:classifiers":[
        {
            "category":"Retail",
            "subcategory":"Auto Repair",
            "type":"Services"
        }
    ],
    "sg:phone":"+44 1647 61220",
    "sg:postcode":"EX6 6EB",
    "sg:province":"Devon",
    "sg:tags":[
        "modification",
        "garage"
    ],
    "wof:name":"Fry's Garage",
    "wof:placetype":"venue"
},
  "geometry": {"coordinates":[-3.6795239449,50.7346382141],"type":"Point"}
}