{
  "type": "Feature",
  "properties": {
    "addr:full":"1 Churchfield Road, Rothwell Leeds West Yorkshire LS26 0EJ",
    "addr:housenumber":"1",
    "addr:postcode":"ls26 0ej",
    "addr:street":"Churchfield Road",
    "iso:country":"GB",
    "sg:address":"1 Churchfield Road, Rothwell",
    "sg:city":"Leeds",
    "sg:classifiers":[
        {
            "category":"Building & Trades",
            "subcategory":"Plumbing",
            "type":"Services"
        }
    ],
    "sg:phone":"+44 113 282 6733",
    "sg:postcode":"LS26 0EJ",
    "sg:province":"West Yorkshire",
    "sg:tags":[
        "plumber",
        "heating"
    ],
    "wof:name":"Ray Adams",
    "wof:placetype":"venue"
},
  "geometry": {"coordinates":[-1.4795490503,53.7514190674],"type":"Point"}
}