{
  "type": "Feature",
  "properties": {
    "addr:full":"437 Middleton Road, Chadderton Oldham Lancashire OL9 9JX",
    "addr:housenumber":"437",
    "addr:postcode":"ol9 9jx",
    "addr:street":"Middleton Road",
    "iso:country":"GB",
    "sg:address":"437 Middleton Road, Chadderton",
    "sg:city":"Oldham",
    "sg:classifiers":[
        {
            "category":"Retail",
            "subcategory":"Funeral Services",
            "type":"Services"
        }
    ],
    "sg:phone":"+44 161 624 2361",
    "sg:postcode":"OL9 9JX",
    "sg:province":"Lancashire",
    "sg:tags":[
        "director"
    ],
    "wof:name":"James Taylors Funeral Service",
    "wof:placetype":"venue"
},
  "geometry": {"coordinates":[-2.137202,53.544094],"type":"Point"}
}