{
  "type": "Feature",
  "properties": {
    "addr:full":"Chilwell Retail Park, Beeston Nottingham Nottinghamshire NG9 6DP",
    "addr:postcode":"ng9 6dp",
    "addr:street":"Park",
    "iso:country":"GB",
    "sg:address":"Chilwell Retail Park, Beeston",
    "sg:city":"Nottingham",
    "sg:classifiers":[
        {
            "category":"Food & Beverages",
            "subcategory":"Meat & Fish",
            "type":"Retail Goods"
        }
    ],
    "sg:postcode":"NG9 6DP",
    "sg:province":"Nottinghamshire",
    "sg:tags":[
        "butcher"
    ],
    "wof:name":"Stuart Ryalls",
    "wof:placetype":"venue"
},
  "geometry": {"coordinates":[-1.243619,52.903976],"type":"Point"}
}