{
  "type": "Feature",
  "properties": {
    "iso:country":"GB",
    "sg:address":"15 Culver Road",
    "sg:city":"Lancing",
    "sg:classifiers":[
        {
            "category":"Home & Garden",
            "subcategory":"Hardware",
            "type":"Retail Goods"
        },
        {
            "category":"Home & Garden",
            "subcategory":"Building Materials",
            "type":"Retail Goods"
        }
    ],
    "sg:phone":"+44 1903 851212",
    "sg:postcode":"BN15 9AX",
    "sg:province":"West Sussex",
    "sg:tags":[
        "garage",
        "door",
        "diy",
        "retailer"
    ],
    "wof:name":"Anchor Garage Doors",
    "wof:placetype":"venue"
},
  "geometry": {"coordinates":[-0.323130995,50.8289337158],"type":"Point"}
}