{
  "type": "Feature",
  "properties": {
    "iso:country":"GB",
    "sg:address":"149 London Rd",
    "sg:city":"Worcester",
    "sg:classifiers":[
        {
            "category":"Professional",
            "type":"Services"
        }
    ],
    "sg:phone":"+44 1905 359777",
    "sg:postcode":"WR5 2ED",
    "sg:province":"Worcestershire",
    "sg:tags":[
        "caterer"
    ],
    "wof:name":"Freshbites Catering",
    "wof:placetype":"venue"
},
  "geometry": {"coordinates":[-2.2056450844,52.1850738525],"type":"Point"}
}