{
  "type": "Feature",
  "properties": {
    "addr:full":"12-18 Crown Street Reading Berkshire RG1 2HP",
    "addr:housenumber":"12-18",
    "addr:postcode":"rg1 2hp",
    "addr:street":"Crown Street",
    "iso:country":"GB",
    "sg:address":"12-18 Crown Street",
    "sg:city":"Reading",
    "sg:classifiers":[
        {
            "category":"Professional",
            "subcategory":"Computer Services",
            "type":"Services"
        }
    ],
    "sg:phone":"+44 118 958 3696",
    "sg:postcode":"RG1 2HP",
    "sg:province":"Berkshire",
    "sg:tags":[
        "system",
        "software"
    ],
    "wof:name":"Icl",
    "wof:placetype":"venue"
},
  "geometry": {"coordinates":[-0.9682629704,51.450302124],"type":"Point"}
}