{
  "type": "Feature",
  "properties": {
    "addr:full":"B5 Marquis Court, Team Valley Trading Estate Gateshead Tyne and Wear NE11 0RU",
    "addr:housenumber":"b5",
    "addr:postcode":"ne11 0ru",
    "addr:street":"Marquis Court Team",
    "iso:country":"GB",
    "sg:address":"B5 Marquis Court, Team Valley Trading Estate",
    "sg:city":"Gateshead",
    "sg:classifiers":[
        {
            "category":"Banks & Credit Unions",
            "subcategory":"Financial Services",
            "type":"Services"
        }
    ],
    "sg:phone":"+44 191 487 2000",
    "sg:postcode":"NE11 0RU",
    "sg:province":"Tyne and Wear",
    "sg:tags":[
        "adviser"
    ],
    "wof:name":"Northern Financial Management Ltd.",
    "wof:placetype":"venue"
},
  "geometry": {"coordinates":[-1.6203989983,54.9331130981],"type":"Point"}
}