{
  "type": "Feature",
  "properties": {
    "iso:country":"GB",
    "sg:address":"At De Barrys Hair Salon, 44 Aylesbury Street, Fenny Stratford",
    "sg:city":"Milton Keynes",
    "sg:classifiers":[
        {
            "category":"Personal",
            "subcategory":"Beauty Salon",
            "type":"Services"
        }
    ],
    "sg:phone":"+44 1908 376546",
    "sg:postcode":"MK2 2BA",
    "sg:province":"Buckinghamshire",
    "wof:name":"Elegance Beauty Salon",
    "wof:placetype":"venue"
},
  "geometry": {"coordinates":[-0.71681,51.997349],"type":"Point"}
}