{
  "type": "Feature",
  "properties": {
    "addr:full":"The Cyder House, Polson Launceston Cornwall PL15 9QR",
    "addr:postcode":"pl15 9qr",
    "iso:country":"GB",
    "sg:address":"The Cyder House, Polson",
    "sg:city":"Launceston",
    "sg:classifiers":[
        {
            "category":"Sports & Exercise",
            "subcategory":"Stables",
            "type":"Entertainment"
        }
    ],
    "sg:phone":"+44 1566 775543",
    "sg:postcode":"PL15 9QR",
    "sg:province":"Cornwall",
    "sg:tags":[
        "equestrian",
        "centre",
        "livery",
        "schools",
        "riding",
        "education"
    ],
    "wof:name":"St Leonards Equestrian Centre",
    "wof:placetype":"venue"
},
  "geometry": {"coordinates":[-4.335879,50.63126],"type":"Point"}
}