{
  "type": "Feature",
  "properties": {
    "iso:country":"GB",
    "sg:address":"86 Bunting Road",
    "sg:city":"Northampton",
    "sg:classifiers":[
        {
            "category":"Manufacturing",
            "subcategory":"Apparel",
            "type":"Manufacturing & Wholesale Goods"
        }
    ],
    "sg:phone":"+44 1604 712159",
    "sg:postcode":"NN2 6EE",
    "sg:province":"Northamptonshire",
    "sg:tags":[
        "mnfr",
        "footwear"
    ],
    "wof:name":"Chancery Footwear Ltd.",
    "wof:placetype":"venue"
},
  "geometry": {"coordinates":[-0.895768,52.251541],"type":"Point"}
}