{
  "type": "Feature",
  "properties": {
    "addr:full":"Mill Farm, Guildford Road Cranleigh Surrey GU6 8LB",
    "addr:postcode":"gu6 8lb",
    "addr:street":"Guildford Road",
    "iso:country":"GB",
    "sg:address":"Mill Farm, Guildford Road",
    "sg:city":"Cranleigh",
    "sg:classifiers":[
        {
            "category":"Farming",
            "subcategory":"Livestock Farm",
            "type":"Manufacturing & Wholesale Goods"
        }
    ],
    "sg:phone":"+44 1483 272983",
    "sg:postcode":"GU6 8LB",
    "sg:province":"Surrey",
    "sg:tags":[
        "others"
    ],
    "wof:name":"Peter J Hewett",
    "wof:placetype":"venue"
},
  "geometry": {"coordinates":[-0.482998997,51.1415405273],"type":"Point"}
}