{
  "type": "Feature",
  "properties": {
    "addr:full":"79 Tranmere Cres Morecambe Lancashire LA3 2BE",
    "addr:housenumber":"79",
    "addr:postcode":"la3 2be",
    "addr:street":"Tranmere Cres",
    "iso:country":"GB",
    "sg:address":"79 Tranmere Cres",
    "sg:city":"Morecambe",
    "sg:classifiers":[
        {
            "category":"Military Area",
            "subcategory":"Air Force Base",
            "type":"Public Place"
        }
    ],
    "sg:phone":"+44 1524 850850",
    "sg:postcode":"LA3 2BE",
    "sg:province":"Lancashire",
    "sg:tags":[
        "taxi",
        "hire",
        "private"
    ],
    "wof:name":"Bay Taxis",
    "wof:placetype":"venue"
},
  "geometry": {"coordinates":[-2.889445,54.051594],"type":"Point"}
}