{
  "type": "Feature",
  "properties": {
    "iso:country":"GB",
    "sg:address":"1 Holly Hill",
    "sg:city":"London",
    "sg:classifiers":[
        {
            "category":"Real Estate",
            "subcategory":"Real Estate Agent",
            "type":"Services"
        }
    ],
    "sg:phone":"+44 20 7431 2258",
    "sg:postcode":"NW3 6UB",
    "sg:province":"Greater London",
    "wof:name":"Wayne & Silver",
    "wof:placetype":"venue"
},
  "geometry": {"coordinates":[-0.17878,51.556683],"type":"Point"}
}