{
  "type": "Feature",
  "properties": {
    "addr:full":"50 West Street, Portchester Fareham Hampshire PO16 9UN",
    "addr:housenumber":"50",
    "addr:postcode":"po16 9un",
    "addr:street":"West Street",
    "iso:country":"GB",
    "sg:address":"50 West Street, Portchester",
    "sg:city":"Fareham",
    "sg:classifiers":[
        {
            "category":"Shopping",
            "subcategory":"Optician",
            "type":"Retail Goods"
        },
        {
            "category":"Health Services",
            "subcategory":"Optometrist",
            "type":"Services"
        }
    ],
    "sg:phone":"+44 23 9237 3015",
    "sg:postcode":"PO16 9UN",
    "sg:province":"Hampshire",
    "sg:tags":[
        "opthalmic"
    ],
    "wof:name":"Cameron-Davies",
    "wof:placetype":"venue"
},
  "geometry": {"coordinates":[-1.128459,50.845905],"type":"Point"}
}