{
  "type": "Feature",
  "properties": {
    "addr:full":"Fimber Field Farm, Fridaythorpe Driffield East Riding of Yorkshire YO25 9RZ",
    "addr:postcode":"yo25 9rz",
    "addr:street":"Fimber;Fridaythorpe",
    "iso:country":"GB",
    "sg:address":"Fimber Field Farm, Fridaythorpe",
    "sg:city":"Driffield",
    "sg:classifiers":[
        {
            "category":"Farming",
            "subcategory":"Livestock Farm",
            "type":"Manufacturing & Wholesale Goods"
        },
        {
            "category":"Farming",
            "subcategory":"Farm",
            "type":"Manufacturing & Wholesale Goods"
        }
    ],
    "sg:postcode":"YO25 9RZ",
    "sg:province":"East Riding of Yorkshire",
    "sg:tags":[
        "mixed",
        "crop"
    ],
    "wof:name":"H Chapman & Son",
    "wof:placetype":"venue"
},
  "geometry": {"coordinates":[-0.6640580297,54.0201683044],"type":"Point"}
}