{
  "type": "Feature",
  "properties": {
    "iso:country":"GB",
    "sg:address":"1 Albion Road",
    "sg:city":"Scarborough",
    "sg:classifiers":[
        {
            "category":"Taxi",
            "type":"Transportation"
        },
        {
            "category":"Retail",
            "subcategory":"Auto Repair",
            "type":"Services"
        }
    ],
    "sg:phone":"+44 1723 377377",
    "sg:postcode":"YO11 2BT",
    "sg:province":"North Yorkshire",
    "sg:tags":[
        "modification",
        "garage",
        "mini",
        "cab"
    ],
    "wof:name":"Nippy Taxis",
    "wof:placetype":"venue"
},
  "geometry": {"coordinates":[-0.399357,54.276104],"type":"Point"}
}