{
  "type": "Feature",
  "properties": {
    "iso:country":"GB",
    "sg:address":"Ludgate Hot, 107 Fleet Street",
    "sg:city":"London",
    "sg:classifiers":[
        {
            "category":"Education",
            "subcategory":"Special Training",
            "type":"Public Place"
        }
    ],
    "sg:phone":"+44 20 7936 9020",
    "sg:postcode":"EC4A 2AB",
    "sg:province":"Greater London",
    "sg:tags":[
        "product",
        "centre"
    ],
    "wof:name":"Information Horizons Ltd.",
    "wof:placetype":"venue"
},
  "geometry": {"coordinates":[-0.10893,51.51421],"type":"Point"}
}