{
  "type": "Feature",
  "properties": {
    "iso:country":"GB",
    "sg:address":"66/68 High Road, Bushey Heath",
    "sg:city":"Watford",
    "sg:classifiers":[
        {
            "category":"Professional",
            "subcategory":"Business Services",
            "type":"Services"
        }
    ],
    "sg:phone":"+44 20 8950 5522",
    "sg:postcode":"WD23 1GG",
    "sg:province":"Hertfordshire",
    "sg:tags":[
        "import",
        "export",
        "agent"
    ],
    "wof:name":"John Parkins & Co. Ltd.",
    "wof:placetype":"venue"
},
  "geometry": {"coordinates":[-0.3434930146,51.6354675293],"type":"Point"}
}