{
  "type": "Feature",
  "properties": {
    "addr:full":"166 Cricklade Road Swindon Wiltshire SN2 8AN",
    "addr:housenumber":"166",
    "addr:postcode":"sn2 8an",
    "addr:street":"Cricklade Road",
    "iso:country":"GB",
    "sg:address":"166 Cricklade Road",
    "sg:city":"Swindon",
    "sg:classifiers":[
        {
            "category":"Building & Trades",
            "subcategory":"Plumbing",
            "type":"Services"
        }
    ],
    "sg:phone":"+44 1793 693880",
    "sg:postcode":"SN2 8AN",
    "sg:province":"Wiltshire",
    "sg:tags":[
        "central",
        "heating"
    ],
    "wof:name":"Phillips & Sutton Ltd.",
    "wof:placetype":"venue"
},
  "geometry": {"coordinates":[-1.777149,51.572899],"type":"Point"}
}