{
  "type": "Feature",
  "properties": {
    "iso:country":"GB",
    "sg:address":"27 Dover Str",
    "sg:city":"London",
    "sg:classifiers":[
        {
            "category":"Real Estate",
            "subcategory":"Real Estate Agent",
            "type":"Services"
        }
    ],
    "sg:phone":"+44 20 7495 1011",
    "sg:postcode":"W1S 4DY",
    "sg:province":"Greater London",
    "wof:name":"Dunedin Property Ltd.",
    "wof:placetype":"venue"
},
  "geometry": {"coordinates":[-0.142734,51.509174],"type":"Point"}
}