{
  "type": "Feature",
  "properties": {
    "addr:full":"Amber Business Centre, Charity Road Alfreton Derbyshire DE55 4BR",
    "addr:postcode":"de55 4br",
    "addr:street":"Charity Road",
    "iso:country":"GB",
    "sg:address":"Amber Business Centre, Charity Road",
    "sg:city":"Alfreton",
    "sg:classifiers":[
        {
            "category":"Professional",
            "type":"Services"
        },
        {
            "category":"Professional",
            "subcategory":"Printing & Photocopies",
            "type":"Services"
        }
    ],
    "sg:phone":"+44 1773 607887",
    "sg:postcode":"DE55 4BR",
    "sg:province":"Derbyshire",
    "sg:tags":[
        "directory",
        "plate",
        "lithographic",
        "maker",
        "pub"
    ],
    "wof:name":"John Murfin & Associates",
    "wof:placetype":"venue"
},
  "geometry": {"coordinates":[-1.3850489855,53.097618103],"type":"Point"}
}