{
  "type": "Feature",
  "properties": {
    "addr:full":"The Bank, 112 Heaton Moor Road Stockport Cheshire SK4 4PA",
    "addr:housenumber":"112",
    "addr:postcode":"sk4 4pa",
    "addr:street":"Heaton Moor Road",
    "iso:country":"GB",
    "sg:address":"The Bank, 112 Heaton Moor Road",
    "sg:city":"Stockport",
    "sg:classifiers":[
        {
            "category":"Manufacturing",
            "subcategory":"Textiles",
            "type":"Manufacturing & Wholesale Goods"
        }
    ],
    "sg:postcode":"SK4 4PA",
    "sg:province":"Cheshire",
    "sg:tags":[
        "knitwear"
    ],
    "wof:name":"Intral (U K) Ltd.",
    "wof:placetype":"venue"
},
  "geometry": {"coordinates":[-2.18438,53.422791],"type":"Point"}
}