{
  "type": "Feature",
  "properties": {
    "addr:full":"283 Whitegate Drive Blackpool Lancashire FY3 9JY",
    "addr:housenumber":"283",
    "addr:postcode":"fy3 9jy",
    "addr:street":"Whitegate Drive",
    "iso:country":"GB",
    "sg:address":"283 Whitegate Drive",
    "sg:city":"Blackpool",
    "sg:classifiers":[
        {
            "category":"Social Services",
            "subcategory":"Retirement Home",
            "type":"Services"
        }
    ],
    "sg:phone":"+44 1253 761324",
    "sg:postcode":"FY3 9JY",
    "sg:province":"Lancashire",
    "sg:tags":[
        "rest"
    ],
    "wof:name":"Whitegate Manor",
    "wof:placetype":"venue"
},
  "geometry": {"coordinates":[-3.028723,53.806019],"type":"Point"}
}