{
  "type": "Feature",
  "properties": {
    "addr:full":"Unit 2 2nd Floor, Imperial Building, Rolleston Street Leicester Leicestershire LE5 3SD",
    "addr:housenumber":"unit 2 2nd floor imperial building",
    "addr:postcode":"le5 3sd",
    "addr:street":"Rolleston Street",
    "iso:country":"GB",
    "sg:address":"Unit 2 2nd Floor, Imperial Building, Rolleston Street",
    "sg:city":"Leicester",
    "sg:classifiers":[
        {
            "category":"Shopping",
            "subcategory":"Clothing, Apparel, & Fashions",
            "type":"Retail Goods"
        }
    ],
    "sg:phone":"+44 116 276 3044",
    "sg:postcode":"LE5 3SD",
    "sg:province":"Leicestershire",
    "sg:tags":[
        "clothing",
        "fabric"
    ],
    "wof:name":"Seasonwise",
    "wof:placetype":"venue"
},
  "geometry": {"coordinates":[-1.1043599844,52.6365585327],"type":"Point"}
}