{
  "type": "Feature",
  "properties": {
    "addr:full":"157 Longfleet Road Poole Dorset BH15 2HS",
    "addr:housenumber":"157",
    "addr:postcode":"bh15 2hs",
    "addr:street":"Longfleet Road",
    "iso:country":"GB",
    "sg:address":"157 Longfleet Road",
    "sg:city":"Poole",
    "sg:classifiers":[
        {
            "category":"Travel",
            "subcategory":"Hotels & Motels",
            "type":"Entertainment"
        }
    ],
    "sg:phone":"+44 1202 672421",
    "sg:postcode":"BH15 2HS",
    "sg:province":"Dorset",
    "sg:tags":[
        "house",
        "guest"
    ],
    "wof:name":"The Harbour View Guest House",
    "wof:placetype":"venue"
},
  "geometry": {"coordinates":[-1.968495,50.724705],"type":"Point"}
}