{
  "type": "Feature",
  "properties": {
    "addr:full":"18 Park Road Wellingborough Northamptonshire NN8 4PG",
    "addr:housenumber":"18",
    "addr:postcode":"nn8 4pg",
    "addr:street":"Park Road",
    "iso:country":"GB",
    "sg:address":"18 Park Road",
    "sg:city":"Wellingborough",
    "sg:classifiers":[
        {
            "category":"Personal",
            "subcategory":"Beauty Salon",
            "type":"Services"
        },
        {
            "category":"Personal",
            "subcategory":"Barber",
            "type":"Services"
        }
    ],
    "sg:phone":"+44 1933 271188",
    "sg:postcode":"NN8 4PG",
    "sg:province":"Northamptonshire",
    "sg:tags":[
        "unisex",
        "hairdresser"
    ],
    "wof:name":"Melanie C's",
    "wof:placetype":"venue"
},
  "geometry": {"coordinates":[-0.692201972,52.3038444519],"type":"Point"}
}