{
  "type": "Feature",
  "properties": {
    "iso:country":"GB",
    "sg:address":"1 Stulpfield Road, Granchester",
    "sg:city":"Cambridge",
    "sg:classifiers":[
        {
            "category":"Government",
            "subcategory":"Post Office",
            "type":"Public Place"
        }
    ],
    "sg:postcode":"CB3 9NL",
    "sg:province":"Cambridgeshire",
    "wof:name":"Granchester Sub Post Office",
    "wof:placetype":"venue"
},
  "geometry": {"coordinates":[0.0903650001,52.1810264587],"type":"Point"}
}