{
  "type": "Feature",
  "properties": {
    "addr:full":"Faraday Road Runcorn Cheshire WA7 1QG",
    "addr:postcode":"wa7 1qg",
    "addr:street":"Faraday Road",
    "iso:country":"GB",
    "sg:address":"Faraday Road",
    "sg:city":"Runcorn",
    "sg:classifiers":[
        {
            "category":"Professional",
            "subcategory":"Engineering",
            "type":"Services"
        }
    ],
    "sg:phone":"+44 1928 590080",
    "sg:postcode":"WA7 1QG",
    "sg:province":"Cheshire",
    "sg:tags":[
        "contractor",
        "electrical",
        "engineer"
    ],
    "wof:name":"Mechanical & Electrical Works Services Ltd.",
    "wof:placetype":"venue"
},
  "geometry": {"coordinates":[-2.708727,53.344334],"type":"Point"}
}