{
  "type": "Feature",
  "properties": {
    "addr:full":"St. Barnabas Office, Perth Rd Beckenham Kent BR3 6PP",
    "addr:postcode":"br3 6pp",
    "addr:street":"Perth Rd",
    "iso:country":"GB",
    "sg:address":"St. Barnabas Office, Perth Rd",
    "sg:city":"Beckenham",
    "sg:classifiers":[
        {
            "category":"Place Of Worship",
            "type":"Public Place"
        }
    ],
    "sg:phone":"+44 20 8650 3393",
    "sg:postcode":"BR3 6PP",
    "sg:province":"Kent",
    "wof:name":"Churches & Other Places of Worship",
    "wof:placetype":"venue"
},
  "geometry": {"coordinates":[-0.0155189997,51.4047355652],"type":"Point"}
}