{
  "type": "Feature",
  "properties": {
    "addr:full":"Albion Rd Edinburgh City of Edinburgh EH7 5QG",
    "addr:postcode":"eh7 5qg",
    "addr:street":"Albion Rd",
    "iso:country":"GB",
    "sg:address":"Albion Rd",
    "sg:city":"Edinburgh",
    "sg:classifiers":[
        {
            "category":"Communications",
            "type":"Services"
        }
    ],
    "sg:postcode":"EH7 5QG",
    "sg:province":"City of Edinburgh",
    "sg:tags":[
        "broadcasting"
    ],
    "wof:name":"Edinburgh Live",
    "wof:placetype":"venue"
},
  "geometry": {"coordinates":[-3.167562,55.961617],"type":"Point"}
}