{
  "type": "Feature",
  "properties": {
    "addr:full":"The Pickeridge, Stoke Common Rd Slough Berkshire SL3 6HA",
    "addr:postcode":"sl3 6ha",
    "addr:street":"Stoke Common Rd",
    "iso:country":"GB",
    "sg:address":"The Pickeridge, Stoke Common Rd",
    "sg:city":"Slough",
    "sg:classifiers":[
        {
            "category":"Utilities",
            "subcategory":"Refuse",
            "type":"Services"
        }
    ],
    "sg:phone":"+44 1753 662700",
    "sg:postcode":"SL3 6HA",
    "sg:province":"Berkshire",
    "sg:tags":[
        "disposal",
        "waste"
    ],
    "wof:name":"Browning Ferris Industries UK Ltd",
    "wof:placetype":"venue"
},
  "geometry": {"coordinates":[-0.5727599859,51.5613708496],"type":"Point"}
}