{
  "type": "Feature",
  "properties": {
    "addr:full":"50 Villiers Road Kingston-upon-thames Greater London KT1 3BA",
    "addr:housenumber":"50",
    "addr:postcode":"kt1 3ba",
    "addr:street":"Villiers Road",
    "iso:country":"GB",
    "sg:address":"50 Villiers Road",
    "sg:city":"Kingston-upon-thames",
    "sg:classifiers":[
        {
            "category":"Personal",
            "subcategory":"Beauty Salon",
            "type":"Services"
        }
    ],
    "sg:postcode":"KT1 3BA",
    "sg:province":"Greater London",
    "sg:tags":[
        "unisex",
        "hairdresser"
    ],
    "wof:name":"Zak's Hair Design",
    "wof:placetype":"venue"
},
  "geometry": {"coordinates":[-0.2945649922,51.4033927917],"type":"Point"}
}