{
  "type": "Feature",
  "properties": {
    "addr:full":"Unit 3 Langley Rd Ormskirk Lancashire L40 8JN",
    "addr:housenumber":"unit 3",
    "addr:postcode":"l40 8jn",
    "addr:street":"Langley Rd",
    "iso:country":"GB",
    "sg:address":"Unit 3 Langley Rd",
    "sg:city":"Ormskirk",
    "sg:classifiers":[
        {
            "category":"Building & Trades",
            "subcategory":"Construction",
            "type":"Services"
        }
    ],
    "sg:phone":"+44 1704 889000",
    "sg:postcode":"L40 8JN",
    "sg:province":"Lancashire",
    "sg:tags":[
        "concrete"
    ],
    "wof:name":"P S C S Ltd",
    "wof:placetype":"venue"
},
  "geometry": {"coordinates":[-2.8662641048,53.6024703979],"type":"Point"}
}