{
  "type": "Feature",
  "properties": {
    "iso:country":"GB",
    "sg:address":"153 St Neots Road, Hardwick",
    "sg:city":"Cambridge",
    "sg:classifiers":[
        {
            "category":"Organizations",
            "subcategory":"Political Organization",
            "type":"Services"
        }
    ],
    "sg:phone":"+44 1954 211444",
    "sg:postcode":"CB3 7QJ",
    "sg:province":"Cambridgeshire",
    "sg:tags":[
        "party"
    ],
    "wof:name":"South East Cambridgeshire Conservative Association",
    "wof:placetype":"venue"
},
  "geometry": {"coordinates":[0.012454,52.217426],"type":"Point"}
}