{
  "type": "Feature",
  "properties": {
    "addr:full":"The Woodyard, Rear Of 44 Pye Corner, Gilston Harlow Essex CM20 2RB",
    "addr:housenumber":"rear of 44",
    "addr:postcode":"cm20 2rb",
    "addr:street":"Pye Corner",
    "iso:country":"GB",
    "sg:address":"The Woodyard, Rear Of 44 Pye Corner, Gilston",
    "sg:city":"Harlow",
    "sg:classifiers":[
        {
            "category":"Building & Trades",
            "subcategory":"Landscaping Services",
            "type":"Services"
        }
    ],
    "sg:phone":"+44 1279 411701",
    "sg:postcode":"CM20 2RB",
    "sg:province":"Essex",
    "sg:tags":[
        "forestry",
        "tree"
    ],
    "wof:name":"G D Redman & Son",
    "wof:placetype":"venue"
},
  "geometry": {"coordinates":[0.1012950018,51.7910652161],"type":"Point"}
}