{
  "type": "Feature",
  "properties": {
    "iso:country":"GB",
    "sg:address":"5 Crompton Gardens, Rear Of Hastings Rd",
    "sg:city":"Maidstone",
    "sg:classifiers":[
        {
            "category":"Organizations",
            "subcategory":"Non-profit Organization",
            "type":"Services"
        }
    ],
    "sg:phone":"+44 1622 756641",
    "sg:postcode":"ME15 7HD",
    "sg:province":"Kent",
    "sg:tags":[
        "organisation",
        "voluntary",
        "charity"
    ],
    "wof:name":"Peggy Wood",
    "wof:placetype":"venue"
},
  "geometry": {"coordinates":[0.530237,51.269203],"type":"Point"}
}