{
  "type": "Feature",
  "properties": {
    "addr:full":"Islington Mill, James St Salford Greater Manchester M3 5HW",
    "addr:postcode":"m3 5hw",
    "addr:street":"James St",
    "iso:country":"GB",
    "sg:address":"Islington Mill, James St",
    "sg:city":"Salford",
    "sg:classifiers":[
        {
            "category":"Building & Trades",
            "subcategory":"Construction",
            "type":"Services"
        }
    ],
    "sg:phone":"+44 161 832 7675",
    "sg:postcode":"M3 5HW",
    "sg:province":"Greater Manchester",
    "sg:tags":[
        "builder"
    ],
    "wof:name":"C & A Mooreltd",
    "wof:placetype":"venue"
},
  "geometry": {"coordinates":[-2.260876,53.482979],"type":"Point"}
}