{
  "type": "Feature",
  "properties": {
    "iso:country":"GB",
    "sg:address":"Park Lodge, 5 Parkgate Close",
    "sg:city":"Kingston Upon Thames",
    "sg:classifiers":[
        {
            "category":"Professional",
            "type":"Services"
        }
    ],
    "sg:phone":"+44 20 8547 2797",
    "sg:postcode":"KT2 7LU",
    "sg:province":"Greater London",
    "sg:tags":[
        "interior",
        "furnishers",
        "designer"
    ],
    "wof:name":"Feng Shui By Design",
    "wof:placetype":"venue"
},
  "geometry": {"coordinates":[-0.291474,51.411026],"type":"Point"}
}