{
  "type": "Feature",
  "properties": {
    "addr:full":"62a St Mary's Street Weymouth Dorset DT4 8PP",
    "addr:housenumber":"62a",
    "addr:postcode":"dt4 8pp",
    "addr:street":"St Mary'S Street",
    "iso:country":"GB",
    "sg:address":"62a St Mary's Street",
    "sg:city":"Weymouth",
    "sg:classifiers":[
        {
            "category":"Professional",
            "subcategory":"Art Services",
            "type":"Services"
        }
    ],
    "sg:postcode":"DT4 8PP",
    "sg:province":"Dorset",
    "sg:tags":[
        "picture",
        "restoration"
    ],
    "wof:name":"Change of Seen",
    "wof:placetype":"venue"
},
  "geometry": {"coordinates":[-2.4543418884,50.6078834534],"type":"Point"}
}