{
  "type": "Feature",
  "properties": {
    "iso:country":"GB",
    "sg:address":"The Horn, Errol",
    "sg:city":"Perth",
    "sg:classifiers":[
        {
            "category":"Personal",
            "type":"Services"
        },
        {
            "category":"Education",
            "subcategory":"Special Training",
            "type":"Public Place"
        }
    ],
    "sg:postcode":"PH2 7SR",
    "sg:province":"Perth and Kinross",
    "sg:tags":[
        "product",
        "wedding",
        "centre"
    ],
    "wof:name":"F X Video",
    "wof:placetype":"venue"
},
  "geometry": {"coordinates":[-3.209753,56.393379],"type":"Point"}
}