{
  "type": "Feature",
  "properties": {
    "addr:full":"Hope Road Deal Kent CT14 7UP",
    "addr:postcode":"ct14 7up",
    "addr:street":"Hope Road Deal",
    "iso:country":"GB",
    "sg:address":"Hope Road",
    "sg:city":"Deal",
    "sg:classifiers":[
        {
            "category":"Government",
            "subcategory":"Office",
            "type":"Public Place"
        },
        {
            "category":"Social Services",
            "subcategory":"Adult Care",
            "type":"Services"
        },
        {
            "category":"Social Services",
            "subcategory":"Retirement Home",
            "type":"Services"
        }
    ],
    "sg:phone":"+44 1304 366730",
    "sg:postcode":"CT14 7UP",
    "sg:province":"Kent",
    "sg:tags":[
        "housing",
        "local",
        "accommodation",
        "sheltered"
    ],
    "wof:name":"Norman Tailyour House",
    "wof:placetype":"venue"
},
  "geometry": {"coordinates":[1.401815,51.220226],"type":"Point"}
}