{
  "type": "Feature",
  "properties": {
    "addr:full":"Mooredges, Thorne Doncaster East Riding of Yorkshire DN8 5SE",
    "addr:postcode":"dn8 5se",
    "addr:street":"Mooredges;Riding",
    "iso:country":"GB",
    "sg:address":"Mooredges, Thorne",
    "sg:city":"Doncaster",
    "sg:classifiers":[
        {
            "category":"Farming",
            "subcategory":"Farm",
            "type":"Manufacturing & Wholesale Goods"
        }
    ],
    "sg:phone":"+44 1405 812510",
    "sg:postcode":"DN8 5SE",
    "sg:province":"East Riding of Yorkshire",
    "sg:tags":[
        "mixed",
        "crop"
    ],
    "wof:name":"R Bellamy",
    "wof:placetype":"venue"
},
  "geometry": {"coordinates":[-0.961637,53.611591],"type":"Point"}
}