{
  "type": "Feature",
  "properties": {
    "addr:full":"Glen Elg Kyle Highland IV40 8JG",
    "addr:postcode":"iv40 8jg",
    "addr:street":"Glen Elg",
    "iso:country":"GB",
    "sg:address":"Glen Elg",
    "sg:city":"Kyle",
    "sg:classifiers":[
        {
            "category":"Professional",
            "subcategory":"Lawyer & Legal Services",
            "type":"Services"
        }
    ],
    "sg:phone":"+44 1599 522218",
    "sg:postcode":"IV40 8JG",
    "sg:province":"Highland",
    "sg:tags":[
        "solicitor"
    ],
    "wof:name":"Frederick Main",
    "wof:placetype":"venue"
},
  "geometry": {"coordinates":[-5.7140522003,57.2809448242],"type":"Point"}
}