{
  "type": "Feature",
  "properties": {
    "addr:full":"Alice Springs, 103 Cambridge Rd, Church Town Southport Lancashire PR9 9SB",
    "addr:housenumber":"103",
    "addr:postcode":"pr9 9sb",
    "addr:street":"Cambridge Rd",
    "iso:country":"GB",
    "sg:address":"Alice Springs, 103 Cambridge Rd, Church Town",
    "sg:city":"Southport",
    "sg:classifiers":[
        {
            "category":"Professional",
            "subcategory":"Accounting & Tax Preparation",
            "type":"Services"
        }
    ],
    "sg:phone":"+44 1704 211613",
    "sg:postcode":"PR9 9SB",
    "sg:province":"Lancashire",
    "sg:tags":[
        "accountant"
    ],
    "wof:name":"R Rahman & Co",
    "wof:placetype":"venue"
},
  "geometry": {"coordinates":[-2.9694600105,53.6610183716],"type":"Point"}
}