{
  "type": "Feature",
  "properties": {
    "iso:country":"GB",
    "sg:address":"Lowther Street",
    "sg:city":"Whitehaven",
    "sg:classifiers":[
        {
            "category":"Education",
            "subcategory":"Library",
            "type":"Public Place"
        }
    ],
    "sg:phone":"+44 1946 852903",
    "sg:postcode":"CA28 7QZ",
    "sg:province":"Cumbria",
    "sg:tags":[
        "book"
    ],
    "wof:name":"The Young Peoples Library Service",
    "wof:placetype":"venue"
},
  "geometry": {"coordinates":[-3.588614,54.548214],"type":"Point"}
}