{
  "type": "Feature",
  "properties": {
    "addr:full":"Cambridge House, Henry Street Bath Bath and North East Somerset BA1 1DJ",
    "addr:postcode":"ba1 1dj",
    "addr:street":"Henry Street",
    "iso:country":"GB",
    "sg:address":"Cambridge House, Henry Street",
    "sg:city":"Bath",
    "sg:classifiers":[
        {
            "category":"Government",
            "subcategory":"Court House",
            "type":"Public Place"
        }
    ],
    "sg:phone":"+44 1225 310282",
    "sg:postcode":"BA1 1DJ",
    "sg:province":"Bath and North East Somerset",
    "wof:name":"Bath County Courts",
    "wof:placetype":"venue"
},
  "geometry": {"coordinates":[-2.3580238819,51.3797912598],"type":"Point"}
}