{
  "type": "Feature",
  "properties": {
    "addr:full":"79 Julian Road Southampton Hampshire SO19 8LY",
    "addr:housenumber":"79",
    "addr:postcode":"so19 8ly",
    "addr:street":"Julian Road",
    "iso:country":"GB",
    "sg:address":"79 Julian Road",
    "sg:city":"Southampton",
    "sg:classifiers":[
        {
            "category":"Building & Trades",
            "subcategory":"Construction",
            "type":"Services"
        }
    ],
    "sg:phone":"+44 23 8036 3333",
    "sg:postcode":"SO19 8LY",
    "sg:province":"Hampshire",
    "sg:tags":[
        "ceiling",
        "contractor"
    ],
    "wof:name":"Betatex",
    "wof:placetype":"venue"
},
  "geometry": {"coordinates":[-1.346077,50.901379],"type":"Point"}
}