{
  "type": "Feature",
  "properties": {
    "addr:full":"The Old Rectory, Glebe Rd Swansea Carmarthenshire SA4 6SR",
    "addr:postcode":"sa4 6sr",
    "addr:street":"Glebe Rd",
    "iso:country":"GB",
    "sg:address":"The Old Rectory, Glebe Rd",
    "sg:city":"Swansea",
    "sg:classifiers":[
        {
            "category":"Retail",
            "subcategory":"Funeral Services",
            "type":"Services"
        }
    ],
    "sg:phone":"+44 1792 891160",
    "sg:postcode":"SA4 6SR",
    "sg:province":"Carmarthenshire",
    "wof:name":"David Inkin & Son",
    "wof:placetype":"venue"
},
  "geometry": {"coordinates":[-4.05998,51.663738],"type":"Point"}
}