{
  "type": "Feature",
  "properties": {
    "iso:country":"GB",
    "sg:address":"Oliver Ho, Wardley Indust Est, Priestley Rd",
    "sg:city":"Manchester",
    "sg:classifiers":[
        {
            "category":"Manufacturing",
            "subcategory":"Wood Products",
            "type":"Manufacturing & Wholesale Goods"
        }
    ],
    "sg:phone":"+44 161 793 1191",
    "sg:postcode":"M28 2LY",
    "sg:province":"Greater Manchester",
    "sg:tags":[
        "packaging",
        "crate",
        "pallets"
    ],
    "wof:name":"A1 Pallets",
    "wof:placetype":"venue"
},
  "geometry": {"coordinates":[-2.3590960503,53.5139122009],"type":"Point"}
}