{
  "type": "Feature",
  "properties": {
    "addr:full":"Balado Home Farm, Balado Kinross Clackmannanshire KY13 0NJ",
    "addr:postcode":"ky13 0nj",
    "iso:country":"GB",
    "sg:address":"Balado Home Farm, Balado",
    "sg:city":"Kinross",
    "sg:classifiers":[
        {
            "category":"Farming",
            "subcategory":"Farm",
            "type":"Manufacturing & Wholesale Goods"
        }
    ],
    "sg:postcode":"KY13 0NJ",
    "sg:province":"Clackmannanshire",
    "sg:tags":[
        "mixed",
        "crop"
    ],
    "wof:name":"G & M Lawrie",
    "wof:placetype":"venue"
},
  "geometry": {"coordinates":[-3.4589490891,56.2083244324],"type":"Point"}
}