{
  "type": "Feature",
  "properties": {
    "addr:full":"Shepperton Studios, Studios Rd Shepperton Surrey TW17 0QD",
    "addr:postcode":"tw17 0qd",
    "addr:street":"Studios Rd",
    "iso:country":"GB",
    "sg:address":"Shepperton Studios, Studios Rd",
    "sg:city":"Shepperton",
    "sg:classifiers":[
        {
            "category":"Farming",
            "subcategory":"Nursery",
            "type":"Manufacturing & Wholesale Goods"
        }
    ],
    "sg:phone":"+44 1932 572525",
    "sg:postcode":"TW17 0QD",
    "sg:province":"Surrey",
    "sg:tags":[
        "creche"
    ],
    "wof:name":"Toad Hall Day Nursery",
    "wof:placetype":"venue"
},
  "geometry": {"coordinates":[-0.4635159969,51.4011497498],"type":"Point"}
}