{
  "type": "Feature",
  "properties": {
    "addr:full":"145 Tunnel Avenue, Greenwich London Greater London SE10 0PW",
    "addr:housenumber":"145",
    "addr:postcode":"se10 0pw",
    "addr:street":"Tunnel Avenue",
    "iso:country":"GB",
    "sg:address":"145 Tunnel Avenue, Greenwich",
    "sg:city":"London",
    "sg:classifiers":[
        {
            "category":"Wholesale",
            "subcategory":"Electrical",
            "type":"Manufacturing & Wholesale Goods"
        },
        {
            "category":"Shopping",
            "subcategory":"Computers & Home Electronics",
            "type":"Retail Goods"
        }
    ],
    "sg:phone":"+44 20 8858 0356",
    "sg:postcode":"SE10 0PW",
    "sg:province":"Greater London",
    "sg:tags":[
        "wholesaler"
    ],
    "wof:name":"Burner Radio Electrical Factors Ltd",
    "wof:placetype":"venue"
},
  "geometry": {"coordinates":[0.0101239998,51.489654541],"type":"Point"}
}