{
  "type": "Feature",
  "properties": {
    "addr:full":"Common Farm Chester Cheshire CH3 7QT",
    "addr:postcode":"ch3 7qt",
    "iso:country":"GB",
    "sg:address":"Common Farm",
    "sg:city":"Chester",
    "sg:classifiers":[
        {
            "category":"Farming",
            "subcategory":"Livestock Farm",
            "type":"Manufacturing & Wholesale Goods"
        }
    ],
    "sg:phone":"+44 1244 335816",
    "sg:postcode":"CH3 7QT",
    "sg:province":"Cheshire",
    "sg:tags":[
        "others"
    ],
    "wof:name":"M Davies",
    "wof:placetype":"venue"
},
  "geometry": {"coordinates":[-2.813263,53.167881],"type":"Point"}
}