{
  "type": "Feature",
  "properties": {
    "addr:full":"12 Station Rd, Chapeltown Sheffield South Yorkshire S35 2XH",
    "addr:housenumber":"12",
    "addr:postcode":"s35 2xh",
    "addr:street":"Station Rd",
    "iso:country":"GB",
    "sg:address":"12 Station Rd, Chapeltown",
    "sg:city":"Sheffield",
    "sg:classifiers":[
        {
            "category":"Shopping",
            "subcategory":"Thrift Store",
            "type":"Retail Goods"
        }
    ],
    "sg:phone":"+44 114 246 0362",
    "sg:postcode":"S35 2XH",
    "sg:province":"South Yorkshire",
    "sg:tags":[
        "shop",
        "charity"
    ],
    "wof:name":"St. Lukes Hospice",
    "wof:placetype":"venue"
},
  "geometry": {"coordinates":[-1.4653600454,53.4622612],"type":"Point"}
}