{
  "type": "Feature",
  "properties": {
    "addr:full":"9 Halliwick Court Parade, Woodhouse Rd, Colney Hatch Lane North Finchley Greater London N12 0NB",
    "addr:housenumber":"9",
    "addr:postcode":"n12 0nb",
    "addr:street":"Halliwick Court Parade Woodhouse Rd;Hatch Lane",
    "iso:country":"GB",
    "sg:address":"9 Halliwick Court Parade, Woodhouse Rd, Colney Hatch Lane",
    "sg:city":"North Finchley",
    "sg:classifiers":[
        {
            "category":"Retail",
            "subcategory":"Laundry & Dry Cleaning",
            "type":"Services"
        }
    ],
    "sg:phone":"+44 20 8361 4088",
    "sg:postcode":"N12 0NB",
    "sg:province":"Greater London",
    "sg:tags":[
        "cleaner",
        "alteration"
    ],
    "wof:name":"Colney Hatch Dry Cleaners",
    "wof:placetype":"venue"
},
  "geometry": {"coordinates":[-0.1587799937,51.6125106812],"type":"Point"}
}