{
  "type": "Feature",
  "properties": {
    "iso:country":"GB",
    "sg:address":"Crosscrake Bungalow, Stainton",
    "sg:city":"Kendal",
    "sg:classifiers":[
        {
            "category":"Banks & Credit Unions",
            "subcategory":"Investment Brokerage",
            "type":"Services"
        }
    ],
    "sg:postcode":"LA8 0AB",
    "sg:province":"Cumbria",
    "sg:tags":[
        "contractor"
    ],
    "wof:name":"John Stott",
    "wof:placetype":"venue"
},
  "geometry": {"coordinates":[-2.72913,54.277981],"type":"Point"}
}