{
  "type": "Feature",
  "properties": {
    "addr:full":"Larkfield Clinic Martin Square, Larkfield Aylesford Kent ME20 6QJ",
    "addr:postcode":"me20 6qj",
    "addr:street":"Martin Square",
    "iso:country":"GB",
    "sg:address":"Larkfield Clinic Martin Square, Larkfield",
    "sg:city":"Aylesford",
    "sg:classifiers":[
        {
            "category":"Health Services",
            "subcategory":"Clinic",
            "type":"Services"
        }
    ],
    "sg:phone":"+44 1732 225890",
    "sg:postcode":"ME20 6QJ",
    "sg:province":"Kent",
    "sg:tags":[
        "private"
    ],
    "wof:name":"Health Visitor",
    "wof:placetype":"venue"
},
  "geometry": {"coordinates":[0.442005,51.301151],"type":"Point"}
}