{
  "type": "Feature",
  "properties": {
    "iso:country":"GB",
    "sg:address":"57 Curzon Street",
    "sg:city":"Burnley",
    "sg:classifiers":[
        {
            "category":"Shopping",
            "subcategory":"Computers & Home Electronics",
            "type":"Retail Goods"
        },
        {
            "category":"Communications",
            "type":"Services"
        }
    ],
    "sg:phone":"+44 1282 438481",
    "sg:postcode":"BB11 1DF",
    "sg:province":"Lancashire",
    "sg:tags":[
        "tv",
        "radio",
        "television",
        "video",
        "sale"
    ],
    "wof:name":"Sound Service",
    "wof:placetype":"venue"
},
  "geometry": {"coordinates":[-2.2440440655,53.7914428711],"type":"Point"}
}