{
  "type": "Feature",
  "properties": {
    "addr:full":"23 Totland House, 2 Vermont Road London Greater London SW18 2LQ",
    "addr:housenumber":"23;2",
    "addr:postcode":"sw18 2lq",
    "addr:street":"Totland;Vermont Road",
    "iso:country":"GB",
    "sg:address":"23 Totland House, 2 Vermont Road",
    "sg:city":"London",
    "sg:classifiers":[
        {
            "category":"Landmark",
            "subcategory":"Tourist Information",
            "type":"Public Place"
        }
    ],
    "sg:postcode":"SW18 2LQ",
    "sg:province":"Greater London",
    "sg:tags":[
        "tour",
        "guide",
        "sightseeing"
    ],
    "wof:name":"Tudor Journeys",
    "wof:placetype":"venue"
},
  "geometry": {"coordinates":[-0.189787,51.45224],"type":"Point"}
}