{
  "type": "Feature",
  "properties": {
    "iso:country":"GB",
    "sg:address":"10 Orwell Street",
    "sg:city":"Grimsby",
    "sg:classifiers":[
        {
            "category":"Home & Garden",
            "subcategory":"Carpets & Floor Coverings",
            "type":"Retail Goods"
        }
    ],
    "sg:phone":"+44 1472 347192",
    "sg:postcode":"DN31 3HB",
    "sg:province":"Lincolnshire",
    "sg:tags":[
        "carpets",
        "rug",
        "matting"
    ],
    "wof:name":"Parkside Carpet Warehouse",
    "wof:placetype":"venue"
},
  "geometry": {"coordinates":[-0.0719629973,53.5755004883],"type":"Point"}
}