{
  "type": "Feature",
  "properties": {
    "iso:country":"GB",
    "sg:address":"7 Strangeways Terrace",
    "sg:city":"Truro",
    "sg:classifiers":[
        {
            "category":"Recreation",
            "subcategory":"Dog Park",
            "type":"Entertainment"
        }
    ],
    "sg:phone":"+44 1872 275239",
    "sg:postcode":"TR1 2NY",
    "sg:province":"Cornwall",
    "wof:name":"Basement Salon",
    "wof:placetype":"venue"
},
  "geometry": {"coordinates":[-5.051992,50.25946],"type":"Point"}
}