{
  "type": "Feature",
  "properties": {
    "iso:country":"GB",
    "sg:address":"1 Jury Street",
    "sg:city":"Warwick",
    "sg:classifiers":[
        {
            "category":"Real Estate",
            "subcategory":"Real Estate Agent",
            "type":"Services"
        }
    ],
    "sg:phone":"+44 1926 497552",
    "sg:postcode":"CV34 4EH",
    "sg:province":"Warwickshire",
    "wof:name":"Loveitts",
    "wof:placetype":"venue"
},
  "geometry": {"coordinates":[-1.5873860121,52.2814598083],"type":"Point"}
}