{
  "type": "Feature",
  "properties": {
    "iso:country":"GB",
    "sg:address":"Nash Ho, St George St",
    "sg:city":"West End",
    "sg:classifiers":[
        {
            "category":"Professional",
            "subcategory":"Computer Services",
            "type":"Services"
        }
    ],
    "sg:phone":"+44 20 7753 8642",
    "sg:postcode":"W1R 9DE",
    "sg:province":"Hampshire",
    "sg:tags":[
        "information"
    ],
    "wof:name":"Osaka Gas Europe PLC",
    "wof:placetype":"venue"
},
  "geometry": {"coordinates":[-0.142851,51.511974],"type":"Point"}
}