{
  "type": "Feature",
  "properties": {
    "addr:full":"254 Sauchiehall Street Glasgow Glasgow City G2 3EQ",
    "addr:housenumber":"254",
    "addr:postcode":"g2 3eq",
    "addr:street":"Sauchiehall Street",
    "iso:country":"GB",
    "sg:address":"254 Sauchiehall Street",
    "sg:city":"Glasgow",
    "sg:classifiers":[
        {
            "category":"Travel",
            "subcategory":"Travel Agent",
            "type":"Entertainment"
        }
    ],
    "sg:phone":"+44 141 353 3532",
    "sg:postcode":"G2 3EQ",
    "sg:province":"Glasgow City",
    "wof:name":"Lunn Poly Ltd.",
    "wof:placetype":"venue"
},
  "geometry": {"coordinates":[-4.2623391151,55.8654174805],"type":"Point"}
}