{
  "type": "Feature",
  "properties": {
    "addr:full":"8 Hoburne Lane, Highcliffe Christchurch Dorset BH23 4HP",
    "addr:housenumber":"8",
    "addr:postcode":"bh23 4hp",
    "addr:street":"Hoburne Lane",
    "iso:country":"GB",
    "sg:address":"8 Hoburne Lane, Highcliffe",
    "sg:city":"Christchurch",
    "sg:classifiers":[
        {
            "category":"Building & Trades",
            "subcategory":"Construction",
            "type":"Services"
        }
    ],
    "sg:postcode":"BH23 4HP",
    "sg:province":"Dorset",
    "sg:tags":[
        "tiling",
        "contractor"
    ],
    "wof:name":"Nick Bullard",
    "wof:placetype":"venue"
},
  "geometry": {"coordinates":[-1.731721,50.741631],"type":"Point"}
}