{
  "type": "Feature",
  "properties": {
    "iso:country":"GB",
    "sg:address":"Castle Hill Yard",
    "sg:city":"Carluke",
    "sg:classifiers":[
        {
            "category":"Wholesale",
            "subcategory":"Metals & Minerals",
            "type":"Manufacturing & Wholesale Goods"
        }
    ],
    "sg:postcode":"ML8 5EP",
    "sg:province":"South Lanarkshire",
    "sg:tags":[
        "merchant"
    ],
    "wof:name":"Castle Hill Minerals Ltd",
    "wof:placetype":"venue"
},
  "geometry": {"coordinates":[-3.841883,55.752827],"type":"Point"}
}