{
  "type": "Feature",
  "properties": {
    "addr:full":"22 Dorset St West End Greater London W1H 3FT",
    "addr:housenumber":"22",
    "addr:postcode":"w1h 3ft",
    "addr:street":"Dorset St",
    "iso:country":"GB",
    "sg:address":"22 Dorset St",
    "sg:city":"West End",
    "sg:classifiers":[
        {
            "category":"Shopping",
            "subcategory":"Crafts & Fabrics",
            "type":"Retail Goods"
        }
    ],
    "sg:phone":"+44 20 7224 0255",
    "sg:postcode":"W1H 3FT",
    "sg:province":"Greater London",
    "sg:tags":[
        "knitwear",
        "yarn"
    ],
    "wof:name":"Fang Brothers Ltd",
    "wof:placetype":"venue"
},
  "geometry": {"coordinates":[-0.15961,51.516178],"type":"Point"}
}