{
  "type": "Feature",
  "properties": {
    "addr:full":"39 Oakdale Road Nottingham Nottinghamshire NG3 7EL",
    "addr:housenumber":"39",
    "addr:postcode":"ng3 7el",
    "addr:street":"Oakdale Road",
    "iso:country":"GB",
    "sg:address":"39 Oakdale Road",
    "sg:city":"Nottingham",
    "sg:classifiers":[
        {
            "category":"Professional",
            "subcategory":"Accounting & Tax Preparation",
            "type":"Services"
        }
    ],
    "sg:phone":"+44 115 911 2227",
    "sg:postcode":"NG3 7EL",
    "sg:province":"Nottinghamshire",
    "sg:tags":[
        "consultant"
    ],
    "wof:name":"Spence & Partners",
    "wof:placetype":"venue"
},
  "geometry": {"coordinates":[-1.1099749804,52.9598121643],"type":"Point"}
}