{
  "type": "Feature",
  "properties": {
    "iso:country":"GB",
    "sg:address":"Church Square",
    "sg:city":"Whitby",
    "sg:classifiers":[
        {
            "category":"Education",
            "subcategory":"School",
            "type":"Public Place"
        },
        {
            "category":"Government",
            "subcategory":"Office",
            "type":"Public Place"
        }
    ],
    "sg:phone":"+44 1947 602510",
    "sg:postcode":"YO21 3EG",
    "sg:province":"North Yorkshire",
    "sg:tags":[
        "local",
        "authority"
    ],
    "wof:name":"West Cliff County Primary School",
    "wof:placetype":"venue"
},
  "geometry": {"coordinates":[-0.621006,54.488968],"type":"Point"}
}