{
  "type": "Feature",
  "properties": {
    "addr:full":"170 Finchley Road London Greater London NW3 6BP",
    "addr:housenumber":"170",
    "addr:postcode":"nw3 6bp",
    "addr:street":"Finchley Road",
    "iso:country":"GB",
    "sg:address":"170 Finchley Road",
    "sg:city":"London",
    "sg:classifiers":[
        {
            "category":"Real Estate",
            "subcategory":"Real Estate Services",
            "type":"Services"
        },
        {
            "category":"Real Estate",
            "subcategory":"Developer",
            "type":"Services"
        }
    ],
    "sg:phone":"+44 20 7483 6100",
    "sg:postcode":"NW3 6BP",
    "sg:province":"Greater London",
    "sg:tags":[
        "property",
        "management"
    ],
    "wof:name":"George Kay Ltd.",
    "wof:placetype":"venue"
},
  "geometry": {"coordinates":[-0.181784004,51.5496711731],"type":"Point"}
}