{
  "type": "Feature",
  "properties": {
    "addr:full":"47 Coxhill Street Glasgow East Dunbartonshire G21 1HL",
    "addr:housenumber":"47",
    "addr:postcode":"g21 1hl",
    "addr:street":"Coxhill Street",
    "iso:country":"GB",
    "sg:address":"47 Coxhill Street",
    "sg:city":"Glasgow",
    "sg:classifiers":[
        {
            "category":"Wholesale",
            "subcategory":"Groceries",
            "type":"Manufacturing & Wholesale Goods"
        }
    ],
    "sg:postcode":"G21 1HL",
    "sg:province":"East Dunbartonshire",
    "sg:tags":[
        "food",
        "supplier",
        "drink"
    ],
    "wof:name":"Argo Poultry",
    "wof:placetype":"venue"
},
  "geometry": {"coordinates":[-4.245672226,55.8760910034],"type":"Point"}
}