{
  "type": "Feature",
  "properties": {
    "iso:country":"GB",
    "sg:address":"Haven Road",
    "sg:city":"Lytham St Annes",
    "sg:classifiers":[
        {
            "category":"Arts & Performance",
            "subcategory":"Arts Center",
            "type":"Entertainment"
        }
    ],
    "sg:phone":"+44 1253 794509",
    "sg:postcode":"FY8 5EG",
    "sg:province":"Lancashire",
    "sg:tags":[
        "centre"
    ],
    "wof:name":"Lytham St Annes Art Society",
    "wof:placetype":"venue"
},
  "geometry": {"coordinates":[-2.9565889835,53.7385749817],"type":"Point"}
}