{
  "type": "Feature",
  "properties": {
    "addr:full":"37 Oakley Road Bromley Kent BR2 8HD",
    "addr:housenumber":"37",
    "addr:postcode":"br2 8hd",
    "addr:street":"Oakley Road",
    "iso:country":"GB",
    "sg:address":"37 Oakley Road",
    "sg:city":"Bromley",
    "sg:classifiers":[
        {
            "category":"Bars & Pubs",
            "type":"Food & Drink"
        }
    ],
    "sg:phone":"+44 20 8462 1627",
    "sg:postcode":"BR2 8HD",
    "sg:province":"Kent",
    "sg:tags":[
        "pubs",
        "inn"
    ],
    "wof:name":"The Two Doves",
    "wof:placetype":"venue"
},
  "geometry": {"coordinates":[0.039559,51.372761],"type":"Point"}
}