{
  "type": "Feature",
  "properties": {
    "addr:full":"Marathon Works, Newport Bridge Middlesbrough North Yorkshire TS1 5TG",
    "addr:postcode":"ts1 5tg",
    "addr:street":"Newport Bridge",
    "iso:country":"GB",
    "sg:address":"Marathon Works, Newport Bridge",
    "sg:city":"Middlesbrough",
    "sg:classifiers":[
        {
            "category":"Manufacturing",
            "subcategory":"Metals",
            "type":"Manufacturing & Wholesale Goods"
        }
    ],
    "sg:phone":"+44 1642 245161",
    "sg:postcode":"TS1 5TG",
    "sg:province":"North Yorkshire",
    "sg:tags":[
        "steel",
        "stockholder"
    ],
    "wof:name":"S M Thompson Ltd.",
    "wof:placetype":"venue"
},
  "geometry": {"coordinates":[-1.236569047,54.572971344],"type":"Point"}
}