{
  "type": "Feature",
  "properties": {
    "addr:full":"35 Palmerston Rd Southport Lancashire PR9 7AG",
    "addr:housenumber":"35",
    "addr:postcode":"pr9 7ag",
    "addr:street":"Palmerston Rd",
    "iso:country":"GB",
    "sg:address":"35 Palmerston Rd",
    "sg:city":"Southport",
    "sg:classifiers":[
        {
            "category":"Health Services",
            "subcategory":"Hospital",
            "type":"Services"
        }
    ],
    "sg:phone":"+44 1704 532448",
    "sg:postcode":"PR9 7AG",
    "sg:province":"Lancashire",
    "sg:tags":[
        "ambulance"
    ],
    "wof:name":"A B A Ambulance Service Ltd",
    "wof:placetype":"venue"
},
  "geometry": {"coordinates":[-2.9717919827,53.6432952881],"type":"Point"}
}