{
  "type": "Feature",
  "properties": {
    "addr:full":"Maidstone Road, Sutton Valence Maidstone Kent ME17 3LS",
    "addr:postcode":"me17 3ls",
    "addr:street":"Maidstone Road",
    "iso:country":"GB",
    "sg:address":"Maidstone Road, Sutton Valence",
    "sg:city":"Maidstone",
    "sg:classifiers":[
        {
            "category":"Wholesale",
            "subcategory":"Fruits & Vegetables",
            "type":"Manufacturing & Wholesale Goods"
        }
    ],
    "sg:phone":"+44 1622 843332",
    "sg:postcode":"ME17 3LS",
    "sg:province":"Kent",
    "wof:name":"Oak Dene Farm",
    "wof:placetype":"venue"
},
  "geometry": {"coordinates":[0.5894070268,51.2278137207],"type":"Point"}
}