{
  "type": "Feature",
  "properties": {
    "addr:full":"Salters Lane South Darlington Durham DL1 2RB",
    "addr:postcode":"dl1 2rb",
    "addr:street":"Salters Lane South",
    "iso:country":"GB",
    "sg:address":"Salters Lane South",
    "sg:city":"Darlington",
    "sg:classifiers":[
        {
            "category":"Bars & Pubs",
            "type":"Food & Drink"
        }
    ],
    "sg:phone":"+44 1325 288669",
    "sg:postcode":"DL1 2RB",
    "sg:province":"Durham",
    "sg:tags":[
        "pubs",
        "inn"
    ],
    "wof:name":"The Springfield",
    "wof:placetype":"venue"
},
  "geometry": {"coordinates":[-1.531039,54.544361],"type":"Point"}
}