{
  "type": "Feature",
  "properties": {
    "iso:country":"GB",
    "sg:address":"27 Stewart Street",
    "sg:city":"Glasgow",
    "sg:classifiers":[
        {
            "category":"Communications",
            "subcategory":"Newspaper",
            "type":"Services"
        },
        {
            "category":"Wholesale",
            "subcategory":"Books, Periodicals, & Newspapers",
            "type":"Manufacturing & Wholesale Goods"
        }
    ],
    "sg:phone":"+44 141 956 3533",
    "sg:postcode":"G62 6BW",
    "sg:province":"East Dunbartonshire",
    "sg:tags":[
        "publisher",
        "magazine"
    ],
    "wof:name":"Milngavie & Bearsden Herald",
    "wof:placetype":"venue"
},
  "geometry": {"coordinates":[-4.319369,55.939957],"type":"Point"}
}