{
  "type": "Feature",
  "properties": {
    "addr:full":"55 Loudoun Rd, St. Johns Wood London Greater London NW8 0DL",
    "addr:housenumber":"55",
    "addr:postcode":"nw8 0dl",
    "addr:street":"Loudoun Rd",
    "iso:country":"GB",
    "sg:address":"55 Loudoun Rd, St. Johns Wood",
    "sg:city":"London",
    "sg:classifiers":[
        {
            "category":"Communications",
            "type":"Services"
        }
    ],
    "sg:postcode":"NW8 0DL",
    "sg:province":"Greater London",
    "sg:tags":[
        "audio-visual"
    ],
    "wof:name":"C 21 C Ltd",
    "wof:placetype":"venue"
},
  "geometry": {"coordinates":[-0.178339,51.53981],"type":"Point"}
}