{
  "type": "Feature",
  "properties": {
    "iso:country":"GB",
    "sg:address":"Market Street",
    "sg:city":"Watchet",
    "sg:classifiers":[
        {
            "category":"Bars & Pubs",
            "type":"Food & Drink"
        }
    ],
    "sg:postcode":"TA23 0AN",
    "sg:province":"Somerset",
    "sg:tags":[
        "pubs",
        "inn"
    ],
    "wof:name":"The Bell Inn",
    "wof:placetype":"venue"
},
  "geometry": {"coordinates":[-3.330938,51.182632],"type":"Point"}
}