{
  "type": "Feature",
  "properties": {
    "iso:country":"GB",
    "sg:address":"Old Spital Farm, Stainmore Rd, Bowes",
    "sg:city":"Barnard Castle",
    "sg:classifiers":[
        {
            "category":"Retail",
            "subcategory":"Animal Services",
            "type":"Services"
        }
    ],
    "sg:phone":"+44 1833 628468",
    "sg:postcode":"DL12 9RH",
    "sg:province":"Cumbria",
    "sg:tags":[
        "training",
        "dog"
    ],
    "wof:name":"Hawk Security",
    "wof:placetype":"venue"
},
  "geometry": {"coordinates":[-2.0078890324,54.5167007446],"type":"Point"}
}