{
  "type": "Feature",
  "properties": {
    "addr:full":"287 Kenilworth Rd, Balsall Common Coventry Warwickshire CV7 7EL",
    "addr:housenumber":"287",
    "addr:postcode":"cv7 7el",
    "addr:street":"Kenilworth Rd",
    "iso:country":"GB",
    "sg:address":"287 Kenilworth Rd, Balsall Common",
    "sg:city":"Coventry",
    "sg:classifiers":[
        {
            "category":"Personal",
            "subcategory":"Beauty Salon",
            "type":"Services"
        }
    ],
    "sg:postcode":"CV7 7EL",
    "sg:province":"Warwickshire",
    "sg:tags":[
        "unisex",
        "hairdresser"
    ],
    "wof:name":"Adams,Shelly Ann,",
    "wof:placetype":"venue"
},
  "geometry": {"coordinates":[-1.650369,52.392319],"type":"Point"}
}