{
  "type": "Feature",
  "properties": {
    "iso:country":"GB",
    "sg:address":"Eigie Road, Balmedie",
    "sg:city":"Aberdeen",
    "sg:classifiers":[
        {
            "category":"Community Center",
            "type":"Public Place"
        },
        {
            "category":"Government",
            "subcategory":"Office",
            "type":"Public Place"
        }
    ],
    "sg:phone":"+44 1358 743725",
    "sg:postcode":"AB23 8YF",
    "sg:province":"Aberdeen City",
    "sg:tags":[
        "recreation",
        "local",
        "leisure",
        "centre"
    ],
    "wof:name":"Balmedie Leisure Centre",
    "wof:placetype":"venue"
},
  "geometry": {"coordinates":[-2.056249,57.249691],"type":"Point"}
}