{
  "type": "Feature",
  "properties": {
    "iso:country":"GB",
    "sg:address":"97 Richmond Park Road",
    "sg:city":"London",
    "sg:classifiers":[
        {
            "category":"Professional",
            "subcategory":"Art Services",
            "type":"Services"
        }
    ],
    "sg:postcode":"SW14 8JY",
    "sg:province":"Greater London",
    "sg:tags":[
        "photographer"
    ],
    "wof:name":"Richmond Park Holographics",
    "wof:placetype":"venue"
},
  "geometry": {"coordinates":[-0.26691,51.461205],"type":"Point"}
}