{
  "type": "Feature",
  "properties": {
    "addr:full":"Nationwide House, Pearson Road, Central Park Telford Shropshire TF2 9TX",
    "addr:postcode":"tf2 9tx",
    "addr:street":"Pearson Road",
    "iso:country":"GB",
    "sg:address":"Nationwide House, Pearson Road, Central Park",
    "sg:city":"Telford",
    "sg:classifiers":[
        {
            "category":"Utilities",
            "subcategory":"Refuse",
            "type":"Services"
        }
    ],
    "sg:phone":"+44 1952 200222",
    "sg:postcode":"TF2 9TX",
    "sg:province":"Shropshire",
    "sg:tags":[
        "skip",
        "hire"
    ],
    "wof:name":"U K Nationwide Skip Hire Ltd.",
    "wof:placetype":"venue"
},
  "geometry": {"coordinates":[-2.4440040588,52.6871109009],"type":"Point"}
}