{
  "type": "Feature",
  "properties": {
    "addr:full":"Railway Terrace Queenborough Kent ME11 5AY",
    "addr:postcode":"me11 5ay",
    "addr:street":"Railway Terrace",
    "iso:country":"GB",
    "sg:address":"Railway Terrace",
    "sg:city":"Queenborough",
    "sg:classifiers":[
        {
            "category":"Education",
            "subcategory":"Library",
            "type":"Public Place"
        }
    ],
    "sg:phone":"+44 1795 663695",
    "sg:postcode":"ME11 5AY",
    "sg:province":"Kent",
    "sg:tags":[
        "book"
    ],
    "wof:name":"Queenborough Library",
    "wof:placetype":"venue"
},
  "geometry": {"coordinates":[0.7476950288,51.4161224365],"type":"Point"}
}