{
  "type": "Feature",
  "properties": {
    "addr:full":"Nash Ct, Boughton Faversham Kent ME13 9SW",
    "addr:postcode":"me13 9sw",
    "addr:street":"Nash Ct",
    "iso:country":"GB",
    "sg:address":"Nash Ct, Boughton",
    "sg:city":"Faversham",
    "sg:classifiers":[
        {
            "category":"Community Center",
            "type":"Public Place"
        }
    ],
    "sg:phone":"+44 1227 751144",
    "sg:postcode":"ME13 9SW",
    "sg:province":"Kent",
    "sg:tags":[
        "recreation",
        "leisure",
        "centre"
    ],
    "wof:name":"Farming World",
    "wof:placetype":"venue"
},
  "geometry": {"coordinates":[0.937095,51.299198],"type":"Point"}
}