{
  "type": "Feature",
  "properties": {
    "addr:full":"Beltinge Surgery, 90 Osborne Gardens Herne Bay Kent CT6 6SE",
    "addr:housenumber":"90",
    "addr:postcode":"ct6 6se",
    "addr:street":"Osborne Gardens;Bay",
    "iso:country":"GB",
    "sg:address":"Beltinge Surgery, 90 Osborne Gardens",
    "sg:city":"Herne Bay",
    "sg:classifiers":[
        {
            "category":"Health Services",
            "subcategory":"Doctor",
            "type":"Services"
        },
        {
            "category":"Health Services",
            "subcategory":"Clinic",
            "type":"Services"
        }
    ],
    "sg:phone":"+44 1227 374902",
    "sg:postcode":"CT6 6SE",
    "sg:province":"Kent",
    "sg:tags":[
        "nh",
        "practitioners"
    ],
    "wof:name":"Drs Feathers & Cleverley",
    "wof:placetype":"venue"
},
  "geometry": {"coordinates":[1.1251,51.371216],"type":"Point"}
}