{
  "type": "Feature",
  "properties": {
    "iso:country":"GB",
    "sg:address":"3 Caley Close, Sweet Briar Road Industrial Estate",
    "sg:city":"Norwich",
    "sg:classifiers":[
        {
            "category":"Wholesale",
            "subcategory":"Electrical",
            "type":"Manufacturing & Wholesale Goods"
        },
        {
            "category":"Shopping",
            "subcategory":"Computers & Home Electronics",
            "type":"Retail Goods"
        }
    ],
    "sg:phone":"+44 1603 416060",
    "sg:postcode":"NR3 2BU",
    "sg:province":"Norfolk",
    "sg:tags":[
        "wholesaler"
    ],
    "sg:website":"http://www.bdc.co.uk",
    "wof:name":"Bridisco Ltd.",
    "wof:placetype":"venue"
},
  "geometry": {"coordinates":[1.262522,52.650532],"type":"Point"}
}