{
  "type": "Feature",
  "properties": {
    "addr:full":"4 Holloway Road London Greater London E11 4LD",
    "addr:housenumber":"4",
    "addr:postcode":"e11 4ld",
    "addr:street":"Holloway Road",
    "iso:country":"GB",
    "sg:address":"4 Holloway Road",
    "sg:city":"London",
    "sg:classifiers":[
        {
            "category":"Place Of Worship",
            "type":"Public Place"
        }
    ],
    "sg:phone":"+44 20 8539 7760",
    "sg:postcode":"E11 4LD",
    "sg:province":"Greater London",
    "wof:name":"Holy Trinity & St. Augustine of Hippo Church",
    "wof:placetype":"venue"
},
  "geometry": {"coordinates":[0.0576249994,51.5243759155],"type":"Point"}
}