{
  "type": "Feature",
  "properties": {
    "addr:full":"9-10 St Thomas Street Weymouth Dorset DT4 8EW",
    "addr:housenumber":"9-10",
    "addr:postcode":"dt4 8ew",
    "addr:street":"St Thomas Street",
    "iso:country":"GB",
    "sg:address":"9-10 St Thomas Street",
    "sg:city":"Weymouth",
    "sg:classifiers":[
        {
            "category":"Restaurant",
            "type":"Food & Drink"
        }
    ],
    "sg:phone":"+44 1305 766550",
    "sg:postcode":"DT4 8EW",
    "sg:province":"Dorset",
    "wof:name":"Wimpy International Ltd.",
    "wof:placetype":"venue"
},
  "geometry": {"coordinates":[-2.4543130398,50.6105117798],"type":"Point"}
}