{
  "type": "Feature",
  "properties": {
    "addr:full":"2 Kilby Avenue Birmingham West Midlands B16 8EN",
    "addr:housenumber":"2",
    "addr:postcode":"b16 8en",
    "addr:street":"Kilby Avenue",
    "iso:country":"GB",
    "sg:address":"2 Kilby Avenue",
    "sg:city":"Birmingham",
    "sg:classifiers":[
        {
            "category":"Shopping",
            "subcategory":"News",
            "type":"Retail Goods"
        }
    ],
    "sg:phone":"+44 121 233 2297",
    "sg:postcode":"B16 8EN",
    "sg:province":"West Midlands",
    "sg:tags":[
        "newsagent"
    ],
    "wof:name":"Monument News",
    "wof:placetype":"venue"
},
  "geometry": {"coordinates":[-1.9193960428,52.4796180725],"type":"Point"}
}