{
  "type": "Feature",
  "properties": {
    "iso:country":"GB",
    "sg:address":"Unit C Cotton Street",
    "sg:city":"Liverpool",
    "sg:classifiers":[
        {
            "category":"Manufacturing",
            "subcategory":"Metals",
            "type":"Manufacturing & Wholesale Goods"
        }
    ],
    "sg:phone":"+44 151 236 7349",
    "sg:postcode":"L3 7DY",
    "sg:province":"Merseyside",
    "sg:tags":[
        "work",
        "sheet"
    ],
    "wof:name":"Merseyside Metal Works Ltd.",
    "wof:placetype":"venue"
},
  "geometry": {"coordinates":[-2.997069,53.418983],"type":"Point"}
}