{
  "type": "Feature",
  "properties": {
    "iso:country":"GB",
    "sg:address":"47 Carisbrooke Court",
    "sg:city":"New Milton",
    "sg:classifiers":[
        {
            "category":"Building & Trades",
            "subcategory":"Landscaping Services",
            "type":"Services"
        }
    ],
    "sg:postcode":"BH25 5UE",
    "sg:province":"Hampshire",
    "sg:tags":[
        "forestry",
        "tree"
    ],
    "wof:name":"R J Cutler",
    "wof:placetype":"venue"
},
  "geometry": {"coordinates":[-1.6663579941,50.754825592],"type":"Point"}
}