{
  "type": "Feature",
  "properties": {
    "addr:full":"36 Clinton Rd Penarth The Vale of Glamorgan CF64 3JD",
    "addr:housenumber":"36",
    "addr:postcode":"cf64 3jd",
    "addr:street":"Clinton Rd;Vale",
    "iso:country":"GB",
    "sg:address":"36 Clinton Rd",
    "sg:city":"Penarth",
    "sg:classifiers":[
        {
            "category":"Personal",
            "subcategory":"Beauty Salon",
            "type":"Services"
        }
    ],
    "sg:phone":"+44 29 2070 1165",
    "sg:postcode":"CF64 3JD",
    "sg:province":"The Vale of Glamorgan",
    "wof:name":"Face Facts",
    "wof:placetype":"venue"
},
  "geometry": {"coordinates":[-3.180739,51.43203],"type":"Point"}
}