{
  "type": "Feature",
  "properties": {
    "addr:full":"Merrimeade Parade, 2 Beaulieu Road Southampton Hampshire SO45 4PY",
    "addr:housenumber":"2",
    "addr:postcode":"so45 4py",
    "addr:street":"Merrimeade;Beaulieu Road",
    "iso:country":"GB",
    "sg:address":"Merrimeade Parade, 2 Beaulieu Road",
    "sg:city":"Southampton",
    "sg:classifiers":[
        {
            "category":"Shopping",
            "subcategory":"Pharmacy",
            "type":"Retail Goods"
        }
    ],
    "sg:phone":"+44 23 8084 3222",
    "sg:postcode":"SO45 4PY",
    "sg:province":"Hampshire",
    "sg:tags":[
        "pharmacist",
        "dispensing",
        "chemist"
    ],
    "wof:name":"Jays Chemists",
    "wof:placetype":"venue"
},
  "geometry": {"coordinates":[-1.4142899513,50.85338974],"type":"Point"}
}