{
  "type": "Feature",
  "properties": {
    "addr:full":"Agricilture House, Devon Place Newport Newport NP20 4NU",
    "addr:postcode":"np20 4nu",
    "addr:street":"Devon Place",
    "iso:country":"GB",
    "sg:address":"Agricilture House, Devon Place",
    "sg:city":"Newport",
    "sg:classifiers":[
        {
            "category":"Insurance",
            "subcategory":"Insurance Agent",
            "type":"Services"
        }
    ],
    "sg:phone":"+44 1633 266724",
    "sg:postcode":"NP20 4NU",
    "sg:province":"Newport",
    "wof:name":"NFU Mutual",
    "wof:placetype":"venue"
},
  "geometry": {"coordinates":[-2.999744,51.589745],"type":"Point"}
}