{
  "type": "Feature",
  "properties": {
    "iso:country":"GB",
    "sg:address":"23a Wood Street, Wootton Bassett",
    "sg:city":"Swindon",
    "sg:classifiers":[
        {
            "category":"Health Services",
            "subcategory":"Health Practitioner",
            "type":"Services"
        }
    ],
    "sg:phone":"+44 1793 848093",
    "sg:postcode":"SN4 7BD",
    "sg:province":"Wiltshire",
    "sg:tags":[
        "osteopath"
    ],
    "wof:name":"DAVID BRUNSKILL",
    "wof:placetype":"venue"
},
  "geometry": {"coordinates":[-1.8949389458,51.4913787842],"type":"Point"}
}