{
  "type": "Feature",
  "properties": {
    "iso:country":"GB",
    "sg:address":"Unit 1 Wessington Yard, London Road",
    "sg:city":"Calne",
    "sg:classifiers":[
        {
            "category":"Home & Garden",
            "subcategory":"Furniture",
            "type":"Retail Goods"
        }
    ],
    "sg:postcode":"SN11 0AP",
    "sg:province":"Wiltshire",
    "wof:name":"Andrew P Smith  Kitchen Manufacturer",
    "wof:placetype":"venue"
},
  "geometry": {"coordinates":[-1.994189,51.43026],"type":"Point"}
}