{
  "type": "Feature",
  "properties": {
    "addr:full":"2a Halsall Lane, Formby Liverpool Lancashire L37 3NW",
    "addr:housenumber":"2a",
    "addr:postcode":"l37 3nw",
    "addr:street":"Halsall Lane",
    "iso:country":"GB",
    "sg:address":"2a Halsall Lane, Formby",
    "sg:city":"Liverpool",
    "sg:classifiers":[
        {
            "category":"Shopping",
            "subcategory":"Optician",
            "type":"Retail Goods"
        },
        {
            "category":"Health Services",
            "subcategory":"Optometrist",
            "type":"Services"
        }
    ],
    "sg:phone":"+44 1704 833558",
    "sg:postcode":"L37 3NW",
    "sg:province":"Lancashire",
    "sg:tags":[
        "opthalmic"
    ],
    "wof:name":"ALICE JOYCE OPTICIANS LTD",
    "wof:placetype":"venue"
},
  "geometry": {"coordinates":[-3.060229063,53.5577507019],"type":"Point"}
}