{
  "type": "Feature",
  "properties": {
    "iso:country":"GB",
    "sg:address":"135 East Park Road",
    "sg:city":"Leicester",
    "sg:classifiers":[
        {
            "category":"Food & Beverages",
            "subcategory":"Supermarket",
            "type":"Retail Goods"
        },
        {
            "category":"Food & Beverages",
            "subcategory":"Fruits & Vegetables",
            "type":"Retail Goods"
        }
    ],
    "sg:phone":"+44 116 254 2654",
    "sg:postcode":"LE5 5AZ",
    "sg:province":"Leicestershire",
    "sg:tags":[
        "greengrocer"
    ],
    "wof:name":"Mohni Supermarket",
    "wof:placetype":"venue"
},
  "geometry": {"coordinates":[-1.1072640419,52.6303863525],"type":"Point"}
}