{
  "type": "Feature",
  "properties": {
    "iso:country":"GB",
    "sg:address":"5 Victoria Square, Brynford Street",
    "sg:city":"Holywell",
    "sg:classifiers":[
        {
            "category":"Organizations",
            "subcategory":"Professional Association",
            "type":"Services"
        }
    ],
    "sg:phone":"+44 1352 713055",
    "sg:postcode":"CH8 7RD",
    "sg:province":"Denbighshire",
    "sg:tags":[
        "union",
        "trade"
    ],
    "wof:name":"John E Hughes",
    "wof:placetype":"venue"
},
  "geometry": {"coordinates":[-3.225195,53.274548],"type":"Point"}
}