{
  "type": "Feature",
  "properties": {
    "addr:full":"6 St Michaels Gro, Bolton Le Sands Carnforth Cumbria LA5 8JB",
    "addr:housenumber":"6",
    "addr:postcode":"la5 8jb",
    "addr:street":"St",
    "iso:country":"GB",
    "sg:address":"6 St Michaels Gro, Bolton Le Sands",
    "sg:city":"Carnforth",
    "sg:classifiers":[
        {
            "category":"Personal",
            "type":"Services"
        },
        {
            "category":"Retail",
            "subcategory":"Laundry & Dry Cleaning",
            "type":"Services"
        }
    ],
    "sg:postcode":"LA5 8JB",
    "sg:province":"Cumbria",
    "sg:tags":[
        "dressmaker",
        "alteration"
    ],
    "wof:name":"Una McGrath",
    "wof:placetype":"venue"
},
  "geometry": {"coordinates":[-2.7937719822,54.1051330566],"type":"Point"}
}