{
  "type": "Feature",
  "properties": {
    "addr:full":"9a Church Street Troon South Ayrshire KA10 6AU",
    "addr:housenumber":"9a",
    "addr:postcode":"ka10 6au",
    "addr:street":"Church Street",
    "iso:country":"GB",
    "sg:address":"9a Church Street",
    "sg:city":"Troon",
    "sg:classifiers":[
        {
            "category":"Government",
            "subcategory":"Post Office",
            "type":"Public Place"
        }
    ],
    "sg:phone":"+44 1292 314331",
    "sg:postcode":"KA10 6AU",
    "sg:province":"South Ayrshire",
    "wof:name":"Troon Post Office",
    "wof:placetype":"venue"
},
  "geometry": {"coordinates":[-4.661102,55.544197],"type":"Point"}
}