{
  "type": "Feature",
  "properties": {
    "addr:full":"63 Castle St Bilston West Midlands WV14 9DW",
    "addr:housenumber":"63",
    "addr:postcode":"wv14 9dw",
    "addr:street":"Castle St",
    "iso:country":"GB",
    "sg:address":"63 Castle St",
    "sg:city":"Bilston",
    "sg:classifiers":[
        {
            "category":"Bars & Pubs",
            "type":"Food & Drink"
        }
    ],
    "sg:phone":"+44 1902 885356",
    "sg:postcode":"WV14 9DW",
    "sg:province":"West Midlands",
    "sg:tags":[
        "pubs",
        "inn"
    ],
    "wof:name":"Old Chainyard The",
    "wof:placetype":"venue"
},
  "geometry": {"coordinates":[-2.087834,52.542],"type":"Point"}
}