{
  "type": "Feature",
  "properties": {
    "iso:country":"GB",
    "sg:address":"632 Radford Road, New Basford",
    "sg:city":"Nottingham",
    "sg:classifiers":[
        {
            "category":"Sports & Exercise",
            "subcategory":"Sports Center",
            "type":"Entertainment"
        }
    ],
    "sg:postcode":"NG7 7EX",
    "sg:province":"Nottinghamshire",
    "sg:tags":[
        "shop",
        "good"
    ],
    "wof:name":"S + N Sports & Fashion Ltd.",
    "wof:placetype":"venue"
},
  "geometry": {"coordinates":[-1.1743079424,52.9785842896],"type":"Point"}
}