{
  "type": "Feature",
  "properties": {
    "addr:full":"192 Caledonian Road London Greater London N1 0SQ",
    "addr:housenumber":"192",
    "addr:postcode":"n1 0sq",
    "addr:street":"Caledonian Road",
    "iso:country":"GB",
    "sg:address":"192 Caledonian Road",
    "sg:city":"London",
    "sg:classifiers":[
        {
            "category":"Health Services",
            "subcategory":"Dentist",
            "type":"Services"
        }
    ],
    "sg:phone":"+44 20 7837 2491",
    "sg:postcode":"N1 0SQ",
    "sg:province":"Greater London",
    "wof:name":"JOSIE M TALIB",
    "wof:placetype":"venue"
},
  "geometry": {"coordinates":[-0.116442,51.536415],"type":"Point"}
}