{
  "type": "Feature",
  "properties": {
    "iso:country":"GB",
    "sg:address":"11 Troy Road, Morley",
    "sg:city":"Leeds",
    "sg:classifiers":[
        {
            "category":"Shopping",
            "subcategory":"Crafts & Fabrics",
            "type":"Retail Goods"
        }
    ],
    "sg:phone":"+44 113 204 9416",
    "sg:postcode":"LS27 8JG",
    "sg:province":"West Yorkshire",
    "sg:tags":[
        "machine",
        "sewing",
        "knitting"
    ],
    "wof:name":"E & M (Industrial) Sewing Machines Ltd.",
    "wof:placetype":"venue"
},
  "geometry": {"coordinates":[-1.6009800434,53.7484207153],"type":"Point"}
}