{
  "type": "Feature",
  "properties": {
    "addr:full":"252-256 Freeman Street Grimsby Lincolnshire DN32 9DR",
    "addr:housenumber":"252-256",
    "addr:postcode":"dn32 9dr",
    "addr:street":"Freeman Street",
    "iso:country":"GB",
    "sg:address":"252-256 Freeman Street",
    "sg:city":"Grimsby",
    "sg:classifiers":[
        {
            "category":"Shopping",
            "subcategory":"Clothing, Apparel, & Fashions",
            "type":"Retail Goods"
        },
        {
            "category":"Shopping",
            "subcategory":"Baby Store",
            "type":"Retail Goods"
        }
    ],
    "sg:phone":"+44 1472 362457",
    "sg:postcode":"DN32 9DR",
    "sg:province":"Lincolnshire",
    "sg:tags":[
        "child",
        "nursery",
        "babywear",
        "accessory"
    ],
    "wof:name":"Moiser's (Grimsby) Ltd.",
    "wof:placetype":"venue"
},
  "geometry": {"coordinates":[-0.0749140009,53.5675811768],"type":"Point"}
}