{
  "type": "Feature",
  "properties": {
    "addr:full":"4 Park View Avenue, Ashton On Ribble Preston Lancashire PR2 1JH",
    "addr:housenumber":"4",
    "addr:postcode":"pr2 1jh",
    "addr:street":"Park View Avenue",
    "iso:country":"GB",
    "sg:address":"4 Park View Avenue, Ashton On Ribble",
    "sg:city":"Preston",
    "sg:classifiers":[
        {
            "category":"Building & Trades",
            "subcategory":"Construction",
            "type":"Services"
        }
    ],
    "sg:postcode":"PR2 1JH",
    "sg:province":"Lancashire",
    "sg:tags":[
        "builder"
    ],
    "wof:name":"Ashton & Billington Building Contractors",
    "wof:placetype":"venue"
},
  "geometry": {"coordinates":[-2.7335050106,53.7701683044],"type":"Point"}
}