{
  "type": "Feature",
  "properties": {
    "addr:full":"78-82 Great Junction Street Edinburgh City of Edinburgh EH6 5LD",
    "addr:housenumber":"78-82",
    "addr:postcode":"eh6 5ld",
    "addr:street":"Great Junction Street",
    "iso:country":"GB",
    "sg:address":"78-82 Great Junction Street",
    "sg:city":"Edinburgh",
    "sg:classifiers":[
        {
            "category":"Cafe",
            "type":"Food & Drink"
        }
    ],
    "sg:phone":"+44 131 555 4848",
    "sg:postcode":"EH6 5LD",
    "sg:province":"City of Edinburgh",
    "sg:tags":[
        "tea",
        "room"
    ],
    "wof:name":"Relax Cafe",
    "wof:placetype":"venue"
},
  "geometry": {"coordinates":[-3.174259901,55.9722976685],"type":"Point"}
}