{
  "type": "Feature",
  "properties": {
    "addr:full":"12 Boxfield Green Stevenage Hertfordshire SG2 7DR",
    "addr:housenumber":"12",
    "addr:postcode":"sg2 7dr",
    "addr:street":"Boxfield Green",
    "iso:country":"GB",
    "sg:address":"12 Boxfield Green",
    "sg:city":"Stevenage",
    "sg:classifiers":[
        {
            "category":"Professional",
            "subcategory":"Detective & Security Services",
            "type":"Services"
        }
    ],
    "sg:phone":"+44 1438 743051",
    "sg:postcode":"SG2 7DR",
    "sg:province":"Hertfordshire",
    "sg:tags":[
        "locksmith"
    ],
    "wof:name":"Abbey Locksmiths",
    "wof:placetype":"venue"
},
  "geometry": {"coordinates":[-0.1590349972,51.9152412415],"type":"Point"}
}