{
  "type": "Feature",
  "properties": {
    "addr:full":"7 Pheasant Way, Beeches Pk Cirencester Gloucestershire GL7 1BJ",
    "addr:housenumber":"7",
    "addr:postcode":"gl7 1bj",
    "addr:street":"Pheasant Way Beeches Pk",
    "iso:country":"GB",
    "sg:address":"7 Pheasant Way, Beeches Pk",
    "sg:city":"Cirencester",
    "sg:classifiers":[
        {
            "category":"Professional",
            "subcategory":"Management & Consulting",
            "type":"Services"
        }
    ],
    "sg:postcode":"GL7 1BJ",
    "sg:province":"Gloucestershire",
    "sg:tags":[
        "consultant",
        "business"
    ],
    "wof:name":"Timebox Consultancy Services Ltd",
    "wof:placetype":"venue"
},
  "geometry": {"coordinates":[-1.9507709742,51.7184524536],"type":"Point"}
}