{
  "type": "Feature",
  "properties": {
    "addr:full":"26 Bear Srteet Barnstaple Devon EX32 7BX",
    "addr:housenumber":"26",
    "addr:postcode":"ex32 7bx",
    "addr:street":"Bear Srteet",
    "iso:country":"GB",
    "sg:address":"26 Bear Srteet",
    "sg:city":"Barnstaple",
    "sg:classifiers":[
        {
            "category":"Retail",
            "subcategory":"Funeral Services",
            "type":"Services"
        }
    ],
    "sg:phone":"+44 1271 379727",
    "sg:postcode":"EX32 7BX",
    "sg:province":"Devon",
    "wof:name":"Napier Services",
    "wof:placetype":"venue"
},
  "geometry": {"coordinates":[-4.001959,51.088425],"type":"Point"}
}