{
  "type": "Feature",
  "properties": {
    "iso:country":"GB",
    "sg:address":"20 Oak Tree Road",
    "sg:city":"Thatcham",
    "sg:classifiers":[
        {
            "category":"Professional",
            "subcategory":"Engineering",
            "type":"Services"
        }
    ],
    "sg:phone":"+44 1635 862602",
    "sg:postcode":"RG19 4QF",
    "sg:province":"Berkshire",
    "sg:tags":[
        "hydraulic",
        "engineer"
    ],
    "wof:name":"Industrial Hydraulics & Pneumatics Ltd.",
    "wof:placetype":"venue"
},
  "geometry": {"coordinates":[-1.2519609928,51.3994102478],"type":"Point"}
}