{
  "type": "Feature",
  "properties": {
    "addr:full":"Redwood Drive Hemel Hempstead Hertfordshire HP3 9ER",
    "addr:postcode":"hp3 9er",
    "addr:street":"Redwood Drive",
    "iso:country":"GB",
    "sg:address":"Redwood Drive",
    "sg:city":"Hemel Hempstead",
    "sg:classifiers":[
        {
            "category":"Education",
            "subcategory":"School",
            "type":"Public Place"
        }
    ],
    "sg:phone":"+44 1442 256294",
    "sg:postcode":"HP3 9ER",
    "sg:province":"Hertfordshire",
    "sg:tags":[
        "local",
        "authority"
    ],
    "wof:name":"Tudor Junior Mixed Infants School",
    "wof:placetype":"venue"
},
  "geometry": {"coordinates":[-0.4643540084,51.7461395264],"type":"Point"}
}