{
  "type": "Feature",
  "properties": {
    "addr:full":"Regents Ho, Fore St Castle Cary Somerset BA7 7BG",
    "addr:postcode":"ba7 7bg",
    "addr:street":"Fore St",
    "iso:country":"GB",
    "sg:address":"Regents Ho, Fore St",
    "sg:city":"Castle Cary",
    "sg:classifiers":[
        {
            "category":"Real Estate",
            "subcategory":"Architect",
            "type":"Services"
        }
    ],
    "sg:phone":"+44 1963 359040",
    "sg:postcode":"BA7 7BG",
    "sg:province":"Somerset",
    "wof:name":"Muir,Mark,& Co Ltd",
    "wof:placetype":"venue"
},
  "geometry": {"coordinates":[-2.5180859566,51.0890693665],"type":"Point"}
}