{
  "type": "Feature",
  "properties": {
    "iso:country":"GB",
    "sg:address":"131 Roscoe Cres",
    "sg:city":"Runcorn",
    "sg:classifiers":[
        {
            "category":"Building & Trades",
            "subcategory":"Locksmith",
            "type":"Services"
        }
    ],
    "sg:phone":"+44 1928 566664",
    "sg:postcode":"WA7 4ES",
    "sg:province":"Cheshire",
    "wof:name":"Safeguard Distrubution Ltd",
    "wof:placetype":"venue"
},
  "geometry": {"coordinates":[-2.7494189739,53.3250999451],"type":"Point"}
}