{
  "type": "Feature",
  "properties": {
    "addr:full":"Within C & E, Caberfeidh Avenue Dingwall Highland IV15 9TD",
    "addr:postcode":"iv15 9td",
    "addr:street":"Avenue Dingwall",
    "iso:country":"GB",
    "sg:address":"Within C & E, Caberfeidh Avenue",
    "sg:city":"Dingwall",
    "sg:classifiers":[
        {
            "category":"Military Area",
            "subcategory":"Air Force Base",
            "type":"Public Place"
        }
    ],
    "sg:phone":"+44 1349 866007",
    "sg:postcode":"IV15 9TD",
    "sg:province":"Highland",
    "sg:tags":[
        "taxi",
        "hire",
        "private"
    ],
    "wof:name":"Caberfeidh Taxi Centre",
    "wof:placetype":"venue"
},
  "geometry": {"coordinates":[-4.43259,57.594761],"type":"Point"}
}