{
  "type": "Feature",
  "properties": {
    "addr:full":"Care Of Natural History Museum, Cromwell Rd South Kensington Greater London SW7 5BD",
    "addr:postcode":"sw7 5bd",
    "addr:street":"Cromwell Rd",
    "iso:country":"GB",
    "sg:address":"Care Of Natural History Museum, Cromwell Rd",
    "sg:city":"South Kensington",
    "sg:classifiers":[
        {
            "category":"Organizations",
            "subcategory":"Non-profit Organization",
            "type":"Services"
        }
    ],
    "sg:phone":"+44 20 7938 9387",
    "sg:postcode":"SW7 5BD",
    "sg:province":"Greater London",
    "sg:tags":[
        "organisation",
        "voluntary",
        "charity"
    ],
    "wof:name":"International Commission On Zoological Nomenclature",
    "wof:placetype":"venue"
},
  "geometry": {"coordinates":[-0.17687,51.49651],"type":"Point"}
}