{
  "type": "Feature",
  "properties": {
    "addr:full":"3 Thornfield Road Stockport Cheshire SK4 3LD",
    "addr:housenumber":"3",
    "addr:postcode":"sk4 3ld",
    "addr:street":"Thornfield Road",
    "iso:country":"GB",
    "sg:address":"3 Thornfield Road",
    "sg:city":"Stockport",
    "sg:classifiers":[
        {
            "category":"Personal",
            "subcategory":"Beauty Salon",
            "type":"Services"
        },
        {
            "category":"Personal",
            "subcategory":"Barber",
            "type":"Services"
        }
    ],
    "sg:phone":"+44 161 442 3272",
    "sg:postcode":"SK4 3LD",
    "sg:province":"Cheshire",
    "sg:tags":[
        "unisex",
        "hairdresser"
    ],
    "wof:name":"Robert Morris",
    "wof:placetype":"venue"
},
  "geometry": {"coordinates":[-2.190543,53.416939],"type":"Point"}
}