{
  "type": "Feature",
  "properties": {
    "addr:full":"104 Westborough Road Maidenhead Berkshire SL6 4AT",
    "addr:housenumber":"104",
    "addr:postcode":"sl6 4at",
    "addr:street":"Westborough Road",
    "iso:country":"GB",
    "sg:address":"104 Westborough Road",
    "sg:city":"Maidenhead",
    "sg:classifiers":[
        {
            "category":"Building & Trades",
            "subcategory":"Construction",
            "type":"Services"
        }
    ],
    "sg:phone":"+44 1628 672202",
    "sg:postcode":"SL6 4AT",
    "sg:province":"Berkshire",
    "sg:tags":[
        "glazier"
    ],
    "wof:name":"Kenlee Glazing",
    "wof:placetype":"venue"
},
  "geometry": {"coordinates":[-0.741707,51.517086],"type":"Point"}
}