{
  "type": "Feature",
  "properties": {
    "iso:country":"GB",
    "sg:address":"7 Wesley St",
    "sg:city":"Consett",
    "sg:classifiers":[
        {
            "category":"Home & Garden",
            "subcategory":"Home Furnishings",
            "type":"Retail Goods"
        }
    ],
    "sg:postcode":"DH8 5BJ",
    "sg:province":"Durham",
    "sg:tags":[
        "awning",
        "canopy",
        "blinds"
    ],
    "wof:name":"Lace & Drapes",
    "wof:placetype":"venue"
},
  "geometry": {"coordinates":[-1.832459,54.852497],"type":"Point"}
}