{
  "type": "Feature",
  "properties": {
    "iso:country":"GB",
    "sg:address":"Forward Park, Sheene Road",
    "sg:city":"Leicester",
    "sg:classifiers":[
        {
            "category":"Professional",
            "subcategory":"Printing & Photocopies",
            "type":"Services"
        }
    ],
    "sg:phone":"+44 116 233 0776",
    "sg:postcode":"LE4 1BS",
    "sg:province":"Leicestershire",
    "sg:tags":[
        "printer"
    ],
    "wof:name":"B B H Colourprint Group Ltd.",
    "wof:placetype":"venue"
},
  "geometry": {"coordinates":[-1.1704000235,52.6667785645],"type":"Point"}
}