{
  "type": "Feature",
  "properties": {
    "addr:full":"18-20 Victoria Street Paignton Devon TQ4 5DN",
    "addr:housenumber":"18-20",
    "addr:postcode":"tq4 5dn",
    "addr:street":"Victoria Street",
    "iso:country":"GB",
    "sg:address":"18-20 Victoria Street",
    "sg:city":"Paignton",
    "sg:classifiers":[
        {
            "category":"Community Center",
            "subcategory":"Social",
            "type":"Public Place"
        }
    ],
    "sg:phone":"+44 1803 558777",
    "sg:postcode":"TQ4 5DN",
    "sg:province":"Devon",
    "sg:tags":[
        "frozen",
        "food",
        "freezer",
        "centre"
    ],
    "wof:name":"Iceland Foods Plc",
    "wof:placetype":"venue"
},
  "geometry": {"coordinates":[-3.56659,50.435528],"type":"Point"}
}