{
  "type": "Feature",
  "properties": {
    "addr:full":"Monitor House, 2a Belmont Road Sutton Surrey SM2 6DW",
    "addr:housenumber":"2a",
    "addr:postcode":"sm2 6dw",
    "addr:street":"Belmont Road",
    "iso:country":"GB",
    "sg:address":"Monitor House, 2a Belmont Road",
    "sg:city":"Sutton",
    "sg:classifiers":[
        {
            "category":"Education",
            "subcategory":"Special Training",
            "type":"Public Place"
        }
    ],
    "sg:phone":"+44 20 8770 9992",
    "sg:postcode":"SM2 6DW",
    "sg:province":"Surrey",
    "sg:tags":[
        "product",
        "centre"
    ],
    "wof:name":"Apprenticeship Training Ltd",
    "wof:placetype":"venue"
},
  "geometry": {"coordinates":[-0.2046539932,51.3451156616],"type":"Point"}
}