{
  "type": "Feature",
  "properties": {
    "addr:full":"The Green, Wick Bristol Gloucestershire BS30 5RA",
    "addr:postcode":"bs30 5ra",
    "addr:street":"The Green",
    "iso:country":"GB",
    "sg:address":"The Green, Wick",
    "sg:city":"Bristol",
    "sg:classifiers":[
        {
            "category":"Building & Trades",
            "subcategory":"Construction",
            "type":"Services"
        }
    ],
    "sg:phone":"+44 117 937 2570",
    "sg:postcode":"BS30 5RA",
    "sg:province":"Gloucestershire",
    "sg:tags":[
        "glazier"
    ],
    "wof:name":"D F Bryant",
    "wof:placetype":"venue"
},
  "geometry": {"coordinates":[-2.498673,51.470577],"type":"Point"}
}