{
  "type": "Feature",
  "properties": {
    "addr:full":"Waterloo, Cornwall Rd London Greater London SE1 8TE",
    "addr:postcode":"se1 8te",
    "addr:street":"Cornwall Rd",
    "iso:country":"GB",
    "sg:address":"Waterloo, Cornwall Rd",
    "sg:city":"London",
    "sg:classifiers":[
        {
            "category":"Bus Charters",
            "type":"Transportation"
        }
    ],
    "sg:phone":"+44 20 7928 1597",
    "sg:postcode":"SE1 8TE",
    "sg:province":"Greater London",
    "sg:tags":[
        "coach"
    ],
    "wof:name":"London General Transport Services Ltd",
    "wof:placetype":"venue"
},
  "geometry": {"coordinates":[-0.1094390005,51.5017585754],"type":"Point"}
}