{
  "type": "Feature",
  "properties": {
    "iso:country":"GB",
    "sg:address":"68 Broadway",
    "sg:city":"Leigh-on-sea",
    "sg:classifiers":[
        {
            "category":"Real Estate",
            "subcategory":"Real Estate Agent",
            "type":"Services"
        }
    ],
    "sg:postcode":"SS9 1AE",
    "sg:province":"Essex",
    "wof:name":"Marine Estates",
    "wof:placetype":"venue"
},
  "geometry": {"coordinates":[0.658899,51.541386],"type":"Point"}
}