{
  "type": "Feature",
  "properties": {
    "iso:country":"GB",
    "sg:address":"64 Orsett Road",
    "sg:city":"Grays",
    "sg:classifiers":[
        {
            "category":"Shopping",
            "subcategory":"Antiques",
            "type":"Retail Goods"
        }
    ],
    "sg:postcode":"RM17 5EH",
    "sg:province":"Essex",
    "wof:name":"Antiques & Collectables",
    "wof:placetype":"venue"
},
  "geometry": {"coordinates":[0.326033,51.479176],"type":"Point"}
}