{
  "type": "Feature",
  "properties": {
    "addr:full":"Unit 5 Birch Business Park, Progress Drive Cannock Staffordshire WS11 3JE",
    "addr:housenumber":"unit 5",
    "addr:postcode":"ws11 3je",
    "addr:street":"Birch Business Park Progress Drive",
    "iso:country":"GB",
    "sg:address":"Unit 5 Birch Business Park, Progress Drive",
    "sg:city":"Cannock",
    "sg:classifiers":[
        {
            "category":"Retail",
            "subcategory":"Auto Repair",
            "type":"Services"
        }
    ],
    "sg:postcode":"WS11 3JE",
    "sg:province":"Staffordshire",
    "sg:tags":[
        "car",
        "upholsterer"
    ],
    "wof:name":"Barrie Rogers Valeting",
    "wof:placetype":"venue"
},
  "geometry": {"coordinates":[-2.0224919319,52.6783790588],"type":"Point"}
}