{
  "type": "Feature",
  "properties": {
    "addr:full":"8 Bedingstone Drive, Penkridge Stafford Shropshire ST19 5TE",
    "addr:housenumber":"8",
    "addr:postcode":"st19 5te",
    "addr:street":"Bedingstone Drive",
    "iso:country":"GB",
    "sg:address":"8 Bedingstone Drive, Penkridge",
    "sg:city":"Stafford",
    "sg:classifiers":[
        {
            "category":"Home & Garden",
            "subcategory":"Carpets & Floor Coverings",
            "type":"Retail Goods"
        }
    ],
    "sg:phone":"+44 1785 712861",
    "sg:postcode":"ST19 5TE",
    "sg:province":"Shropshire",
    "sg:tags":[
        "cleaner",
        "upholstery"
    ],
    "wof:name":"Stay Fresh Chem Dry",
    "wof:placetype":"venue"
},
  "geometry": {"coordinates":[-2.104564,52.714855],"type":"Point"}
}