{
  "type": "Feature",
  "properties": {
    "iso:country":"GB",
    "sg:address":"Challenge House, 45-47 Victoria Street",
    "sg:city":"Mansfield",
    "sg:classifiers":[
        {
            "category":"Real Estate",
            "subcategory":"Real Estate Operator",
            "type":"Services"
        }
    ],
    "sg:phone":"+44 1623 645901",
    "sg:postcode":"NG18 5SU",
    "sg:province":"Nottinghamshire",
    "sg:tags":[
        "letting",
        "agent"
    ],
    "wof:name":"J E Wright (Home Heating Systems) Ltd.",
    "wof:placetype":"venue"
},
  "geometry": {"coordinates":[-1.202612,53.140598],"type":"Point"}
}