{
  "type": "Feature",
  "properties": {
    "addr:full":"1 Meaburn Terr Sunderland Tyne and Wear SR1 2LR",
    "addr:housenumber":"1",
    "addr:postcode":"sr1 2lr",
    "addr:street":"Meaburn Terr",
    "iso:country":"GB",
    "sg:address":"1 Meaburn Terr",
    "sg:city":"Sunderland",
    "sg:classifiers":[
        {
            "category":"Shopping",
            "subcategory":"Pharmacy",
            "type":"Retail Goods"
        }
    ],
    "sg:phone":"+44 191 567 2560",
    "sg:postcode":"SR1 2LR",
    "sg:province":"Tyne and Wear",
    "sg:tags":[
        "pharmacist",
        "chemist"
    ],
    "wof:name":"L Storey Pharmacy",
    "wof:placetype":"venue"
},
  "geometry": {"coordinates":[-1.37274,54.903469],"type":"Point"}
}