{
  "type": "Feature",
  "properties": {
    "addr:full":"142 Lucy Ave Folkestone Kent CT19 5TN",
    "addr:housenumber":"142",
    "addr:postcode":"ct19 5tn",
    "addr:street":"Lucy Ave",
    "iso:country":"GB",
    "sg:address":"142 Lucy Ave",
    "sg:city":"Folkestone",
    "sg:classifiers":[
        {
            "category":"Building & Trades",
            "subcategory":"Construction",
            "type":"Services"
        }
    ],
    "sg:postcode":"CT19 5TN",
    "sg:province":"Kent",
    "sg:tags":[
        "platform",
        "work",
        "scaffolding"
    ],
    "wof:name":"Jones,Robert,",
    "wof:placetype":"venue"
},
  "geometry": {"coordinates":[1.1638230085,51.0906791687],"type":"Point"}
}