{
  "type": "Feature",
  "properties": {
    "addr:full":"30 Merebank Lane Croydon Surrey CR0 4NP",
    "addr:housenumber":"30",
    "addr:postcode":"cr0 4np",
    "addr:street":"Merebank Lane",
    "iso:country":"GB",
    "sg:address":"30 Merebank Lane",
    "sg:city":"Croydon",
    "sg:classifiers":[
        {
            "category":"Professional",
            "type":"Services"
        },
        {
            "category":"Building & Trades",
            "subcategory":"Cleaning & Sanitation",
            "type":"Services"
        }
    ],
    "sg:phone":"+44 20 8688 1500",
    "sg:postcode":"CR0 4NP",
    "sg:province":"Surrey",
    "sg:tags":[
        "interior",
        "furnishers",
        "designer",
        "commercial"
    ],
    "wof:name":"D B Cleaning & Restoration",
    "wof:placetype":"venue"
},
  "geometry": {"coordinates":[-0.121209003,51.3625793457],"type":"Point"}
}