{
  "type": "Feature",
  "properties": {
    "iso:country":"GB",
    "sg:address":"The Quadrant, St Peters Rd",
    "sg:city":"Bournemouth",
    "sg:classifiers":[
        {
            "category":"Home & Garden",
            "subcategory":"Kitchen Supply",
            "type":"Retail Goods"
        }
    ],
    "sg:phone":"+44 1202 551279",
    "sg:postcode":"BH1 2AB",
    "sg:province":"Dorset",
    "sg:tags":[
        "ware"
    ],
    "wof:name":"Kitchen Flair",
    "wof:placetype":"venue"
},
  "geometry": {"coordinates":[-1.874224,50.721245],"type":"Point"}
}