{
  "type": "Feature",
  "properties": {
    "iso:country":"GB",
    "sg:address":"102 East Duck Lees Lane",
    "sg:city":"Enfield",
    "sg:classifiers":[
        {
            "category":"Structure",
            "subcategory":"Warehouse",
            "type":"Public Place"
        }
    ],
    "sg:phone":"+44 20 8804 5552",
    "sg:postcode":"EN3 7SS",
    "sg:province":"Greater London",
    "wof:name":"Pointbid Plc",
    "wof:placetype":"venue"
},
  "geometry": {"coordinates":[-0.028354,51.647346],"type":"Point"}
}