{
  "type": "Feature",
  "properties": {
    "addr:full":"Estuary Farm Cottage, Marsh Road, North Wootton King's Lynn Norfolk PE30 3QJ",
    "addr:postcode":"pe30 3qj",
    "addr:street":"Marsh Road North Wootton;Lynn",
    "iso:country":"GB",
    "sg:address":"Estuary Farm Cottage, Marsh Road, North Wootton",
    "sg:city":"King's Lynn",
    "sg:classifiers":[
        {
            "category":"Transit Center",
            "subcategory":"Passenger",
            "type":"Transportation"
        }
    ],
    "sg:phone":"+44 1553 631463",
    "sg:postcode":"PE30 3QJ",
    "sg:province":"Norfolk",
    "sg:tags":[
        "boarding",
        "kennel",
        "catteries"
    ],
    "wof:name":"Catnaps Cattery",
    "wof:placetype":"venue"
},
  "geometry": {"coordinates":[0.418689996,52.8153381348],"type":"Point"}
}