{
  "type": "Feature",
  "properties": {
    "addr:full":"8 Castle Street Edinburgh City of Edinburgh EH2 3AT",
    "addr:housenumber":"8",
    "addr:postcode":"eh2 3at",
    "addr:street":"Castle Street",
    "iso:country":"GB",
    "sg:address":"8 Castle Street",
    "sg:city":"Edinburgh",
    "sg:classifiers":[
        {
            "category":"Shopping",
            "subcategory":"Clothing, Apparel, & Fashions",
            "type":"Retail Goods"
        }
    ],
    "sg:postcode":"EH2 3AT",
    "sg:province":"City of Edinburgh",
    "sg:tags":[
        "menswear"
    ],
    "wof:name":"Nicklebys",
    "wof:placetype":"venue"
},
  "geometry": {"coordinates":[-3.2031219006,55.9512748718],"type":"Point"}
}