{
  "type": "Feature",
  "properties": {
    "addr:full":"The Pebbles, Southwick Road, North Boarhunt Fareham Hampshire PO17 6JF",
    "addr:postcode":"po17 6jf",
    "addr:street":"Southwick Road North",
    "iso:country":"GB",
    "sg:address":"The Pebbles, Southwick Road, North Boarhunt",
    "sg:city":"Fareham",
    "sg:classifiers":[
        {
            "category":"Food & Beverages",
            "subcategory":"Farmers Market",
            "type":"Retail Goods"
        }
    ],
    "sg:phone":"+44 1329 833339",
    "sg:postcode":"PO17 6JF",
    "sg:province":"Hampshire",
    "sg:tags":[
        "gardener"
    ],
    "wof:name":"Keith P Butler",
    "wof:placetype":"venue"
},
  "geometry": {"coordinates":[-1.14270401,50.8879394531],"type":"Point"}
}