{
  "type": "Feature",
  "properties": {
    "iso:country":"GB",
    "sg:address":"3-6 Nightingale Court",
    "sg:city":"Weston-super-mare",
    "sg:classifiers":[
        {
            "category":"Food & Beverages",
            "subcategory":"Groceries & Convenience Stores",
            "type":"Retail Goods"
        }
    ],
    "sg:postcode":"BS22 8SX",
    "sg:province":"Somerset",
    "wof:name":"Mead Vale Shops (Management) Ltd.",
    "wof:placetype":"venue"
},
  "geometry": {"coordinates":[-2.9283280373,51.353351593],"type":"Point"}
}