{
  "type": "Feature",
  "properties": {
    "iso:country":"GB",
    "sg:address":"Manor Farm Barn West, Lower End, Daglingworth",
    "sg:city":"Cirencester",
    "sg:classifiers":[
        {
            "category":"Professional",
            "subcategory":"Printing & Photocopies",
            "type":"Services"
        }
    ],
    "sg:postcode":"GL7 7AH",
    "sg:province":"Gloucestershire",
    "sg:tags":[
        "printer"
    ],
    "wof:name":"Merchandising & Marketing Matters Ltd.",
    "wof:placetype":"venue"
},
  "geometry": {"coordinates":[-2.010799,51.744976],"type":"Point"}
}