{
  "type": "Feature",
  "properties": {
    "addr:full":"132 St Georges Road Cheltenham Gloucestershire GL50 3EN",
    "addr:housenumber":"132",
    "addr:postcode":"gl50 3en",
    "addr:street":"St Georges Road",
    "iso:country":"GB",
    "sg:address":"132 St Georges Road",
    "sg:city":"Cheltenham",
    "sg:classifiers":[
        {
            "category":"Professional",
            "subcategory":"Engineering",
            "type":"Services"
        }
    ],
    "sg:phone":"+44 1242 583100",
    "sg:postcode":"GL50 3EN",
    "sg:province":"Gloucestershire",
    "sg:tags":[
        "engineer"
    ],
    "wof:name":"Spirax-Sarco Ltd.",
    "wof:placetype":"venue"
},
  "geometry": {"coordinates":[-2.091137886,51.9014358521],"type":"Point"}
}