{
  "type": "Feature",
  "properties": {
    "addr:full":"2b Craiglockhart Drive South Edinburgh City of Edinburgh EH14 1HZ",
    "addr:housenumber":"2b",
    "addr:postcode":"eh14 1hz",
    "addr:street":"Craiglockhart Drive South Edinburgh",
    "iso:country":"GB",
    "sg:address":"2b Craiglockhart Drive South",
    "sg:city":"Edinburgh",
    "sg:classifiers":[
        {
            "category":"Building & Trades",
            "subcategory":"Plumbing",
            "type":"Services"
        }
    ],
    "sg:phone":"+44 131 455 7805",
    "sg:postcode":"EH14 1HZ",
    "sg:province":"City of Edinburgh",
    "sg:tags":[
        "central",
        "installation",
        "system",
        "servicing",
        "heating"
    ],
    "wof:name":"Arnott & Mann",
    "wof:placetype":"venue"
},
  "geometry": {"coordinates":[-3.238146,55.923862],"type":"Point"}
}