{
  "type": "Feature",
  "properties": {
    "addr:full":"Watermead Road, Limbury Mead Luton Bedfordshire LU3 2TF",
    "addr:postcode":"lu3 2tf",
    "addr:street":"Watermead Road Limbury Mead",
    "iso:country":"GB",
    "sg:address":"Watermead Road, Limbury Mead",
    "sg:city":"Luton",
    "sg:classifiers":[
        {
            "category":"Bars & Pubs",
            "type":"Food & Drink"
        }
    ],
    "sg:phone":"+44 1582 574014",
    "sg:postcode":"LU3 2TF",
    "sg:province":"Bedfordshire",
    "sg:tags":[
        "pubs",
        "inn"
    ],
    "wof:name":"The Heron",
    "wof:placetype":"venue"
},
  "geometry": {"coordinates":[-0.4488680065,51.9118156433],"type":"Point"}
}