{
  "type": "Feature",
  "properties": {
    "addr:full":"26 Upper Ground Southwark Greater London SE1 9PD",
    "addr:housenumber":"26",
    "addr:postcode":"se1 9pd",
    "addr:street":"Upper Ground",
    "iso:country":"GB",
    "sg:address":"26 Upper Ground",
    "sg:city":"Southwark",
    "sg:classifiers":[
        {
            "category":"Professional",
            "subcategory":"Management & Consulting",
            "type":"Services"
        }
    ],
    "sg:phone":"+44 20 7633 9040",
    "sg:postcode":"SE1 9PD",
    "sg:province":"Greater London",
    "sg:tags":[
        "consultant",
        "business"
    ],
    "wof:name":"Foureyes PLC",
    "wof:placetype":"venue"
},
  "geometry": {"coordinates":[-0.1123149991,51.5067481995],"type":"Point"}
}