{
  "type": "Feature",
  "properties": {
    "addr:full":"High Street, Hogsthorpe Skegness Lincolnshire PE24 5NB",
    "addr:postcode":"pe24 5nb",
    "addr:street":"High Street",
    "iso:country":"GB",
    "sg:address":"High Street, Hogsthorpe",
    "sg:city":"Skegness",
    "sg:classifiers":[
        {
            "category":"Farming",
            "subcategory":"Fish & Marine Products",
            "type":"Manufacturing & Wholesale Goods"
        },
        {
            "category":"Food & Beverages",
            "subcategory":"Meat & Fish",
            "type":"Retail Goods"
        }
    ],
    "sg:postcode":"PE24 5NB",
    "sg:province":"Lincolnshire",
    "sg:tags":[
        "fishmonger",
        "butcher"
    ],
    "wof:name":"J Taylor & Sons",
    "wof:placetype":"venue"
},
  "geometry": {"coordinates":[0.3013199866,53.2241897583],"type":"Point"}
}