{
  "type": "Feature",
  "properties": {
    "iso:country":"GB",
    "sg:address":"187 Lyndhurst Rd, Ashurst",
    "sg:city":"Southampton",
    "sg:classifiers":[
        {
            "category":"Autos & Motor Vehicles",
            "subcategory":"Automobile Sales",
            "type":"Retail Goods"
        }
    ],
    "sg:phone":"+44 1703 292999",
    "sg:postcode":"SO40 7AR",
    "sg:province":"Hampshire",
    "sg:tags":[
        "car"
    ],
    "wof:name":"Morgan Pembridge Vehicles Ltd",
    "wof:placetype":"venue"
},
  "geometry": {"coordinates":[-1.5228259563,50.8923072815],"type":"Point"}
}