{
  "type": "Feature",
  "properties": {
    "iso:country":"GB",
    "sg:address":"74 North St",
    "sg:city":"Guildford",
    "sg:classifiers":[
        {
            "category":"Banks & Credit Unions",
            "subcategory":"Financial Services",
            "type":"Services"
        }
    ],
    "sg:phone":"+44 1483 567262",
    "sg:postcode":"GU1 4ES",
    "sg:province":"Surrey",
    "sg:tags":[
        "adviser"
    ],
    "wof:name":"Lloyds Private Banking Ltd",
    "wof:placetype":"venue"
},
  "geometry": {"coordinates":[-0.572794,51.236778],"type":"Point"}
}