{
  "type": "Feature",
  "properties": {
    "iso:country":"GB",
    "sg:address":"Old Abattoir, Unit 1, Builder Street",
    "sg:city":"Llandudno",
    "sg:classifiers":[
        {
            "category":"Building & Trades",
            "subcategory":"Construction",
            "type":"Services"
        }
    ],
    "sg:postcode":"LL30 1DR",
    "sg:province":"Conwy",
    "sg:tags":[
        "joinery"
    ],
    "wof:name":"Oakay Joinery",
    "wof:placetype":"venue"
},
  "geometry": {"coordinates":[-3.818764,53.322433],"type":"Point"}
}