{
  "type": "Feature",
  "properties": {
    "addr:full":"47a Mount Pleasant Rd Alton Hampshire GU34 1NL",
    "addr:housenumber":"47a",
    "addr:postcode":"gu34 1nl",
    "addr:street":"Mount Pleasant Rd",
    "iso:country":"GB",
    "sg:address":"47a Mount Pleasant Rd",
    "sg:city":"Alton",
    "sg:classifiers":[
        {
            "category":"Wholesale",
            "subcategory":"Scrap",
            "type":"Manufacturing & Wholesale Goods"
        }
    ],
    "sg:phone":"+44 1420 83312",
    "sg:postcode":"GU34 1NL",
    "sg:province":"Hampshire",
    "sg:tags":[
        "waste",
        "metal"
    ],
    "wof:name":"H Davis",
    "wof:placetype":"venue"
},
  "geometry": {"coordinates":[-0.977034,51.145531],"type":"Point"}
}