{
  "type": "Feature",
  "properties": {
    "addr:full":"168 Saron Road, Saron Ammanford Carmarthenshire SA18 3LN",
    "addr:housenumber":"168",
    "addr:postcode":"sa18 3ln",
    "addr:street":"Saron Road",
    "iso:country":"GB",
    "sg:address":"168 Saron Road, Saron",
    "sg:city":"Ammanford",
    "sg:classifiers":[
        {
            "category":"Transit Center",
            "subcategory":"Freight",
            "type":"Transportation"
        }
    ],
    "sg:phone":"+44 1269 592716",
    "sg:postcode":"SA18 3LN",
    "sg:province":"Carmarthenshire",
    "sg:tags":[
        "shop",
        "craft",
        "centre"
    ],
    "wof:name":"Saron Post Office & Friendly Crafts",
    "wof:placetype":"venue"
},
  "geometry": {"coordinates":[-4.0305871964,51.7929267883],"type":"Point"}
}