{
  "type": "Feature",
  "properties": {
    "addr:full":"A30 Carwin Rise, Loggans Hayle Cornwall TR27 4PN",
    "addr:postcode":"tr27 4pn",
    "addr:street":"Carwin Rise",
    "iso:country":"GB",
    "sg:address":"A30 Carwin Rise, Loggans",
    "sg:city":"Hayle",
    "sg:classifiers":[
        {
            "category":"Restaurant",
            "type":"Food & Drink"
        }
    ],
    "sg:phone":"+44 1736 757318",
    "sg:postcode":"TR27 4PN",
    "sg:province":"Cornwall",
    "wof:name":"Little Chef",
    "wof:placetype":"venue"
},
  "geometry": {"coordinates":[-5.407609,50.192036],"type":"Point"}
}