{
  "type": "Feature",
  "properties": {
    "addr:full":"62 Corstorphine High Street Edinburgh City of Edinburgh EH12 7SY",
    "addr:housenumber":"62",
    "addr:postcode":"eh12 7sy",
    "addr:street":"Corstorphine High Street",
    "iso:country":"GB",
    "sg:address":"62 Corstorphine High Street",
    "sg:city":"Edinburgh",
    "sg:classifiers":[
        {
            "category":"Education",
            "subcategory":"School",
            "type":"Public Place"
        }
    ],
    "sg:phone":"+44 131 334 3865",
    "sg:postcode":"EH12 7SY",
    "sg:province":"City of Edinburgh",
    "sg:tags":[
        "local",
        "authority"
    ],
    "wof:name":"Corstorphine Primary School",
    "wof:placetype":"venue"
},
  "geometry": {"coordinates":[-3.2855429649,55.9405555725],"type":"Point"}
}