{
  "type": "Feature",
  "properties": {
    "addr:full":"136 Thatto Heath Road St. Helens Cheshire WA9 5PE",
    "addr:housenumber":"136",
    "addr:postcode":"wa9 5pe",
    "addr:street":"Thatto Heath Road",
    "iso:country":"GB",
    "sg:address":"136 Thatto Heath Road",
    "sg:city":"St. Helens",
    "sg:classifiers":[
        {
            "category":"Professional",
            "type":"Services"
        }
    ],
    "sg:phone":"+44 1744 601758",
    "sg:postcode":"WA9 5PE",
    "sg:province":"Cheshire",
    "sg:tags":[
        "exhibition"
    ],
    "wof:name":"I C T Promotions",
    "wof:placetype":"venue"
},
  "geometry": {"coordinates":[-2.759093,53.436813],"type":"Point"}
}