{
  "type": "Feature",
  "properties": {
    "addr:full":"127 Walkwood Road, Hunt End Redditch Warwickshire B97 5NP",
    "addr:housenumber":"127",
    "addr:postcode":"b97 5np",
    "addr:street":"Walkwood Road Hunt End",
    "iso:country":"GB",
    "sg:address":"127 Walkwood Road, Hunt End",
    "sg:city":"Redditch",
    "sg:classifiers":[
        {
            "category":"Building & Trades",
            "subcategory":"Landscaping Services",
            "type":"Services"
        }
    ],
    "sg:postcode":"B97 5NP",
    "sg:province":"Warwickshire",
    "sg:tags":[
        "landscape",
        "contractor"
    ],
    "wof:name":"Hunt End Garden Services",
    "wof:placetype":"venue"
},
  "geometry": {"coordinates":[-1.946711,52.278755],"type":"Point"}
}