{
  "type": "Feature",
  "properties": {
    "addr:full":"1 Riverside Mews, Commercial Street Manchester Cheshire M15 4RQ",
    "addr:housenumber":"1",
    "addr:postcode":"m15 4rq",
    "addr:street":"Riverside Mews Commercial Street",
    "iso:country":"GB",
    "sg:address":"1 Riverside Mews, Commercial Street",
    "sg:city":"Manchester",
    "sg:classifiers":[
        {
            "category":"Building & Trades",
            "subcategory":"Electrical",
            "type":"Services"
        }
    ],
    "sg:postcode":"M15 4RQ",
    "sg:province":"Cheshire",
    "sg:tags":[
        "heating"
    ],
    "wof:name":"Linquartz",
    "wof:placetype":"venue"
},
  "geometry": {"coordinates":[-2.25131,53.473289],"type":"Point"}
}