{
  "type": "Feature",
  "properties": {
    "iso:country":"GB",
    "sg:address":"25 Swanley Centre",
    "sg:city":"Swanley",
    "sg:classifiers":[
        {
            "category":"Shopping",
            "subcategory":"Pharmacy",
            "type":"Retail Goods"
        }
    ],
    "sg:phone":"+44 1322 663209",
    "sg:postcode":"BR8 7TG",
    "sg:province":"Kent",
    "sg:tags":[
        "pharmacist",
        "chemist"
    ],
    "wof:name":"Co-op Pharmacy",
    "wof:placetype":"venue"
},
  "geometry": {"coordinates":[0.177865997,51.3967628479],"type":"Point"}
}