{
  "type": "Feature",
  "properties": {
    "addr:full":"152 City Rd London Greater London EC1V 2NX",
    "addr:housenumber":"152",
    "addr:postcode":"ec1v 2nx",
    "addr:street":"City Rd",
    "iso:country":"GB",
    "sg:address":"152 City Rd",
    "sg:city":"London",
    "sg:classifiers":[
        {
            "category":"Building & Trades",
            "subcategory":"Construction",
            "type":"Services"
        }
    ],
    "sg:postcode":"EC1V 2NX",
    "sg:province":"Greater London",
    "sg:tags":[
        "welder"
    ],
    "wof:name":"Helifusion Engineering Ltd",
    "wof:placetype":"venue"
},
  "geometry": {"coordinates":[-0.0887420028,51.5272827148],"type":"Point"}
}