{
  "type": "Feature",
  "properties": {
    "addr:full":"6-8 St Michaels St Southampton Hampshire SO14 2JS",
    "addr:housenumber":"6-8",
    "addr:postcode":"so14 2js",
    "addr:street":"St Michaels St",
    "iso:country":"GB",
    "sg:address":"6-8 St Michaels St",
    "sg:city":"Southampton",
    "sg:classifiers":[
        {
            "category":"Professional",
            "subcategory":"Lawyer & Legal Services",
            "type":"Services"
        }
    ],
    "sg:postcode":"SO14 2JS",
    "sg:province":"Hampshire",
    "sg:tags":[
        "solicitor"
    ],
    "wof:name":"D H Wills",
    "wof:placetype":"venue"
},
  "geometry": {"coordinates":[-1.4041019678,50.8996391296],"type":"Point"}
}