{
  "type": "Feature",
  "properties": {
    "addr:full":"Unit 1, 143 Seabourne Road Bournemouth Dorset BH5 2HQ",
    "addr:housenumber":"unit 1",
    "addr:postcode":"143;bh5 2hq",
    "addr:street":"Seabourne Road",
    "iso:country":"GB",
    "sg:address":"Unit 1, 143 Seabourne Road",
    "sg:city":"Bournemouth",
    "sg:classifiers":[
        {
            "category":"Fast Food",
            "type":"Food & Drink"
        }
    ],
    "sg:phone":"+44 1202 418519",
    "sg:postcode":"BH5 2HQ",
    "sg:province":"Dorset",
    "sg:tags":[
        "away",
        "take"
    ],
    "wof:name":"la Pizza Takeaway",
    "wof:placetype":"venue"
},
  "geometry": {"coordinates":[-1.820574,50.728287],"type":"Point"}
}