{
  "type": "Feature",
  "properties": {
    "iso:country":"GB",
    "sg:address":"175 Albert Road",
    "sg:city":"Southsea",
    "sg:classifiers":[
        {
            "category":"Shopping",
            "subcategory":"Books",
            "type":"Retail Goods"
        }
    ],
    "sg:postcode":"PO4 0JW",
    "sg:province":"Hampshire",
    "sg:tags":[
        "bookseller",
        "retailer"
    ],
    "wof:name":"Edward Caldwell",
    "wof:placetype":"venue"
},
  "geometry": {"coordinates":[-1.0747289658,50.7867851257],"type":"Point"}
}