{
  "type": "Feature",
  "properties": {
    "addr:full":"Abacus House, 93 High Street Huntingdon Cambridgeshire PE29 3DP",
    "addr:housenumber":"93",
    "addr:postcode":"pe29 3dp",
    "addr:street":"High Street",
    "iso:country":"GB",
    "sg:address":"Abacus House, 93 High Street",
    "sg:city":"Huntingdon",
    "sg:classifiers":[
        {
            "category":"Professional",
            "subcategory":"Employment Agencies",
            "type":"Services"
        }
    ],
    "sg:phone":"+44 870 163 5100",
    "sg:postcode":"PE29 3DP",
    "sg:province":"Cambridgeshire",
    "sg:tags":[
        "consultant"
    ],
    "wof:name":"Technical Personnel Ltd.",
    "wof:placetype":"venue"
},
  "geometry": {"coordinates":[-0.185243,52.331287],"type":"Point"}
}