{
  "type": "Feature",
  "properties": {
    "addr:full":"18 Croft Parade Walsall Staffordshire WS9 8LY",
    "addr:housenumber":"18",
    "addr:postcode":"ws9 8ly",
    "addr:street":"Croft Parade",
    "iso:country":"GB",
    "sg:address":"18 Croft Parade",
    "sg:city":"Walsall",
    "sg:classifiers":[
        {
            "category":"Home & Garden",
            "subcategory":"Hardware",
            "type":"Retail Goods"
        },
        {
            "category":"Community Center",
            "subcategory":"Social",
            "type":"Public Place"
        }
    ],
    "sg:phone":"+44 1922 452998",
    "sg:postcode":"WS9 8LY",
    "sg:province":"Staffordshire",
    "sg:tags":[
        "furnishers",
        "contract"
    ],
    "wof:name":"Ronovan Ltd.",
    "wof:placetype":"venue"
},
  "geometry": {"coordinates":[-1.9880599976,52.592830658],"type":"Point"}
}