{
  "type": "Feature",
  "properties": {
    "addr:full":"2 The Spendlove Centre, Charlbury Chipping Norton Gloucestershire OX7 3PQ",
    "addr:housenumber":"2;norton",
    "addr:postcode":"ox7 3pq",
    "addr:street":"The Spendlove Centre",
    "iso:country":"GB",
    "sg:address":"2 The Spendlove Centre, Charlbury",
    "sg:city":"Chipping Norton",
    "sg:classifiers":[
        {
            "category":"Real Estate",
            "subcategory":"Architect",
            "type":"Services"
        }
    ],
    "sg:postcode":"OX7 3PQ",
    "sg:province":"Gloucestershire",
    "wof:name":"James Cockle Chartered Surveyors",
    "wof:placetype":"venue"
},
  "geometry": {"coordinates":[-1.545912981,51.9404067993],"type":"Point"}
}