{
  "type": "Feature",
  "properties": {
    "addr:full":"Blackbushe Business Park, Saxony Way Yateley Hampshire GU46 6GG",
    "addr:postcode":"gu46 6gg",
    "addr:street":"Blackbushe Business Park Saxony Way",
    "iso:country":"GB",
    "sg:address":"Blackbushe Business Park, Saxony Way",
    "sg:city":"Yateley",
    "sg:classifiers":[
        {
            "category":"Professional",
            "subcategory":"Testing Lab",
            "type":"Services"
        }
    ],
    "sg:phone":"+44 1252 863800",
    "sg:postcode":"GU46 6GG",
    "sg:province":"Hampshire",
    "sg:tags":[
        "laboratory"
    ],
    "wof:name":"Samsung Euro Q.A Lab",
    "wof:placetype":"venue"
},
  "geometry": {"coordinates":[-0.8271089792,51.3423194885],"type":"Point"}
}