{
  "type": "Feature",
  "properties": {
    "iso:country":"GB",
    "sg:address":"Broad Oak Road",
    "sg:city":"Canterbury",
    "sg:classifiers":[
        {
            "category":"Wholesale",
            "subcategory":"Non-durable Goods",
            "type":"Manufacturing & Wholesale Goods"
        }
    ],
    "sg:phone":"+44 1227 766101",
    "sg:postcode":"CT2 7PX",
    "sg:province":"Kent",
    "sg:tags":[
        "carry",
        "cash"
    ],
    "wof:name":"Booker Cash & Carry",
    "wof:placetype":"venue"
},
  "geometry": {"coordinates":[1.0886050463,51.2901763916],"type":"Point"}
}