{
  "type": "Feature",
  "properties": {
    "addr:full":"362 Pickhurst Rise West Wickham Kent BR4 0AY",
    "addr:housenumber":"362",
    "addr:postcode":"br4 0ay",
    "addr:street":"Pickhurst Rise",
    "iso:country":"GB",
    "sg:address":"362 Pickhurst Rise",
    "sg:city":"West Wickham",
    "sg:classifiers":[
        {
            "category":"Professional",
            "subcategory":"Accounting & Tax Preparation",
            "type":"Services"
        }
    ],
    "sg:postcode":"BR4 0AY",
    "sg:province":"Kent",
    "sg:tags":[
        "accountant"
    ],
    "wof:name":"T E Carpenter",
    "wof:placetype":"venue"
},
  "geometry": {"coordinates":[0.002486,51.382164],"type":"Point"}
}