{
  "type": "Feature",
  "properties": {
    "iso:country":"GB",
    "sg:address":"Doonholm Nursery, Castle Douglas Road",
    "sg:city":"Dumfries",
    "sg:classifiers":[
        {
            "category":"Building & Trades",
            "subcategory":"Landscaping Services",
            "type":"Services"
        }
    ],
    "sg:postcode":"DG2 8PP",
    "sg:province":"Dumfries and Galloway",
    "sg:tags":[
        "landscape",
        "contractor"
    ],
    "wof:name":"Dunfries & Galloway",
    "wof:placetype":"venue"
},
  "geometry": {"coordinates":[-3.64017,55.06538],"type":"Point"}
}