{
  "type": "Feature",
  "properties": {
    "iso:country":"GB",
    "sg:address":"Plaisterers Hall, 1 London Wall",
    "sg:city":"Moorgate",
    "sg:classifiers":[
        {
            "category":"Professional",
            "type":"Services"
        }
    ],
    "sg:phone":"+44 20 7726 4315",
    "sg:postcode":"EC2Y 5JU",
    "sg:province":"Greater London",
    "sg:tags":[
        "caterer"
    ],
    "wof:name":"Ring & Brymer",
    "wof:placetype":"venue"
},
  "geometry": {"coordinates":[-0.09591,51.517151],"type":"Point"}
}