{
  "type": "Feature",
  "properties": {
    "addr:full":"1-4 Caer Street Swansea Neath Port Talbot SA1 3PP",
    "addr:housenumber":"1-4",
    "addr:postcode":"sa1 3pp",
    "addr:street":"Caer Street",
    "iso:country":"GB",
    "sg:address":"1-4 Caer Street",
    "sg:city":"Swansea",
    "sg:classifiers":[
        {
            "category":"Bars & Pubs",
            "type":"Food & Drink"
        }
    ],
    "sg:phone":"+44 1792 472440",
    "sg:postcode":"SA1 3PP",
    "sg:province":"Neath Port Talbot",
    "sg:tags":[
        "pubs",
        "inn"
    ],
    "wof:name":"Yates' Wine Lodges Ltd.",
    "wof:placetype":"venue"
},
  "geometry": {"coordinates":[-3.941479,51.62011],"type":"Point"}
}