{
  "type": "Feature",
  "properties": {
    "iso:country":"GB",
    "sg:address":"Priory Hall, Priory Road",
    "sg:city":"Dudley",
    "sg:classifiers":[
        {
            "category":"Professional",
            "type":"Services"
        },
        {
            "category":"Conference Center",
            "type":"Public Place"
        },
        {
            "category":"Government",
            "subcategory":"Office",
            "type":"Public Place"
        }
    ],
    "sg:phone":"+44 1384 814728",
    "sg:postcode":"DY1 4EU",
    "sg:province":"West Midlands",
    "sg:tags":[
        "local",
        "related"
    ],
    "wof:name":"Priory Hall Training & Conference Centre",
    "wof:placetype":"venue"
},
  "geometry": {"coordinates":[-2.0872941017,52.5258407593],"type":"Point"}
}