{
  "type": "Feature",
  "properties": {
    "addr:full":"493 Marston Road, Marston Oxford Oxfordshire OX3 0JQ",
    "addr:housenumber":"493",
    "addr:postcode":"ox3 0jq",
    "addr:street":"Marston Road",
    "iso:country":"GB",
    "sg:address":"493 Marston Road, Marston",
    "sg:city":"Oxford",
    "sg:classifiers":[
        {
            "category":"Shopping",
            "subcategory":"Pets & Pet Supplies",
            "type":"Retail Goods"
        }
    ],
    "sg:postcode":"OX3 0JQ",
    "sg:province":"Oxfordshire",
    "sg:tags":[
        "shop"
    ],
    "wof:name":"PADS & PAWS",
    "wof:placetype":"venue"
},
  "geometry": {"coordinates":[-1.2324769497,51.7671699524],"type":"Point"}
}