{
  "type": "Feature",
  "properties": {
    "addr:full":"175 Main Road, Newport Brough East Riding of Yorkshire HU15 2QS",
    "addr:housenumber":"175",
    "addr:postcode":"hu15 2qs",
    "addr:street":"Main Road",
    "iso:country":"GB",
    "sg:address":"175 Main Road, Newport",
    "sg:city":"Brough",
    "sg:classifiers":[
        {
            "category":"Farming",
            "subcategory":"Farm",
            "type":"Manufacturing & Wholesale Goods"
        }
    ],
    "sg:phone":"+44 1430 440215",
    "sg:postcode":"HU15 2QS",
    "sg:province":"East Riding of Yorkshire",
    "sg:tags":[
        "mixed",
        "crop"
    ],
    "wof:name":"F Wainman & Sons",
    "wof:placetype":"venue"
},
  "geometry": {"coordinates":[-0.7004410028,53.7622528076],"type":"Point"}
}