{
  "type": "Feature",
  "properties": {
    "iso:country":"GB",
    "sg:address":"149 Kingston Road",
    "sg:city":"Staines",
    "sg:classifiers":[
        {
            "category":"Shopping",
            "subcategory":"News",
            "type":"Retail Goods"
        }
    ],
    "sg:phone":"+44 1784 453980",
    "sg:postcode":"TW18 1PD",
    "sg:province":"Berkshire",
    "sg:tags":[
        "newsagent"
    ],
    "wof:name":"Mars News",
    "wof:placetype":"venue"
},
  "geometry": {"coordinates":[-0.490192,51.427788],"type":"Point"}
}