{
  "type": "Feature",
  "properties": {
    "iso:country":"GB",
    "sg:address":"47-49 Longridge Avenue, Saltdean",
    "sg:city":"Brighton",
    "sg:classifiers":[
        {
            "category":"Food & Beverages",
            "subcategory":"Fruits & Vegetables",
            "type":"Retail Goods"
        }
    ],
    "sg:postcode":"BN2 8LG",
    "sg:province":"East Sussex",
    "sg:tags":[
        "greengrocer"
    ],
    "wof:name":"R A Manchester",
    "wof:placetype":"venue"
},
  "geometry": {"coordinates":[-0.037189,50.800873],"type":"Point"}
}