{
  "type": "Feature",
  "properties": {
    "addr:full":"Cemetery Road, Lidget Green Bradford West Yorkshire BD7 2PY",
    "addr:postcode":"bd7 2py",
    "addr:street":"Cemetery Road Lidget Green Bradford West",
    "iso:country":"GB",
    "sg:address":"Cemetery Road, Lidget Green",
    "sg:city":"Bradford",
    "sg:classifiers":[
        {
            "category":"Government",
            "subcategory":"Office",
            "type":"Public Place"
        }
    ],
    "sg:phone":"+44 1274 414504",
    "sg:postcode":"BD7 2PY",
    "sg:province":"West Yorkshire",
    "sg:tags":[
        "local"
    ],
    "wof:name":"City of Bradford Metropolitan Council",
    "wof:placetype":"venue"
},
  "geometry": {"coordinates":[-1.7916790247,53.7926483154],"type":"Point"}
}