{
  "type": "Feature",
  "properties": {
    "addr:full":"24 Hornsey Rise Gardens Archway Greater London N19 3PR",
    "addr:housenumber":"24",
    "addr:postcode":"n19 3pr",
    "addr:street":"Hornsey Rise Gardens",
    "iso:country":"GB",
    "sg:address":"24 Hornsey Rise Gardens",
    "sg:city":"Archway",
    "sg:classifiers":[
        {
            "category":"Building & Trades",
            "subcategory":"Electrical",
            "type":"Services"
        }
    ],
    "sg:phone":"+44 20 7272 1950",
    "sg:postcode":"N19 3PR",
    "sg:province":"Greater London",
    "sg:tags":[
        "consultant",
        "lighting"
    ],
    "wof:name":"J.H Cadbury",
    "wof:placetype":"venue"
},
  "geometry": {"coordinates":[-0.1241289973,51.570690155],"type":"Point"}
}