{
  "type": "Feature",
  "properties": {
    "addr:full":"9 Victoria Centre, Mostyn Street Centre Llandudno Conwy LL30 2PS",
    "addr:housenumber":"9",
    "addr:postcode":"ll30 2ps",
    "addr:street":"Victoria Centre Mostyn Street",
    "iso:country":"GB",
    "sg:address":"9 Victoria Centre, Mostyn Street Centre",
    "sg:city":"Llandudno",
    "sg:classifiers":[
        {
            "category":"Shopping",
            "subcategory":"Pharmacy",
            "type":"Retail Goods"
        }
    ],
    "sg:phone":"+44 1492 876633",
    "sg:postcode":"LL30 2PS",
    "sg:province":"Conwy",
    "sg:tags":[
        "pharmacist",
        "chemist"
    ],
    "wof:name":"Boots the Chemists",
    "wof:placetype":"venue"
},
  "geometry": {"coordinates":[-3.818764,53.322433],"type":"Point"}
}