{
  "type": "Feature",
  "properties": {
    "iso:country":"GB",
    "sg:address":"Allen House, Newarke Street",
    "sg:city":"Leicester",
    "sg:classifiers":[
        {
            "category":"Professional",
            "subcategory":"Accounting & Tax Preparation",
            "type":"Services"
        }
    ],
    "sg:phone":"+44 116 233 5959",
    "sg:postcode":"LE1 5SG",
    "sg:province":"Leicestershire",
    "sg:tags":[
        "accountant",
        "activity"
    ],
    "wof:name":"Thomas May & Co",
    "wof:placetype":"venue"
},
  "geometry": {"coordinates":[-1.1347990036,52.6318397522],"type":"Point"}
}