{
  "type": "Feature",
  "properties": {
    "addr:full":"327 Holdenhurst Road Bournemouth Dorset BH8 8BT",
    "addr:housenumber":"327",
    "addr:postcode":"bh8 8bt",
    "addr:street":"Holdenhurst Road",
    "iso:country":"GB",
    "sg:address":"327 Holdenhurst Road",
    "sg:city":"Bournemouth",
    "sg:classifiers":[
        {
            "category":"Home & Garden",
            "subcategory":"Building Materials",
            "type":"Retail Goods"
        }
    ],
    "sg:phone":"+44 1202 301267",
    "sg:postcode":"BH8 8BT",
    "sg:province":"Dorset",
    "sg:tags":[
        "garage",
        "door"
    ],
    "wof:name":"Openings",
    "wof:placetype":"venue"
},
  "geometry": {"coordinates":[-1.85141,50.732498],"type":"Point"}
}