{
  "type": "Feature",
  "properties": {
    "addr:full":"107 Church Street Stoke-on-trent Staffordshire ST4 1DE",
    "addr:housenumber":"107",
    "addr:postcode":"st4 1de",
    "addr:street":"Church Street",
    "iso:country":"GB",
    "sg:address":"107 Church Street",
    "sg:city":"Stoke-on-trent",
    "sg:classifiers":[
        {
            "category":"Shopping",
            "subcategory":"Florist",
            "type":"Retail Goods"
        }
    ],
    "sg:phone":"+44 1782 412555",
    "sg:postcode":"ST4 1DE",
    "sg:province":"Staffordshire",
    "wof:name":"Moody Blooms",
    "wof:placetype":"venue"
},
  "geometry": {"coordinates":[-2.1860799789,53.004196167],"type":"Point"}
}