{
  "type": "Feature",
  "properties": {
    "addr:full":"33 Holman Street Kidderminster Staffordshire DY11 6QY",
    "addr:housenumber":"33",
    "addr:postcode":"dy11 6qy",
    "addr:street":"Holman Street",
    "iso:country":"GB",
    "sg:address":"33 Holman Street",
    "sg:city":"Kidderminster",
    "sg:classifiers":[
        {
            "category":"Home & Garden",
            "subcategory":"Carpets & Floor Coverings",
            "type":"Retail Goods"
        }
    ],
    "sg:phone":"+44 1562 755791",
    "sg:postcode":"DY11 6QY",
    "sg:province":"Staffordshire",
    "sg:tags":[
        "textile",
        "floorcoverings"
    ],
    "wof:name":"N & M Dyer",
    "wof:placetype":"venue"
},
  "geometry": {"coordinates":[-2.259597,52.382587],"type":"Point"}
}