{
  "type": "Feature",
  "properties": {
    "iso:country":"GB",
    "sg:address":"93 College Road, Llandaff North",
    "sg:city":"Cardiff",
    "sg:classifiers":[
        {
            "category":"Shopping",
            "subcategory":"Florist",
            "type":"Retail Goods"
        }
    ],
    "sg:phone":"+44 29 2061 3271",
    "sg:postcode":"CF14 2NR",
    "sg:province":"Cardiff",
    "wof:name":"Ann Hanks",
    "wof:placetype":"venue"
},
  "geometry": {"coordinates":[-3.2202680111,51.5038757324],"type":"Point"}
}