{
  "type": "Feature",
  "properties": {
    "addr:full":"28 Main Avenue, Moor Park Northwood Greater London HA6 2HJ",
    "addr:housenumber":"28",
    "addr:postcode":"ha6 2hj",
    "addr:street":"Main Avenue Moor Park",
    "iso:country":"GB",
    "sg:address":"28 Main Avenue, Moor Park",
    "sg:city":"Northwood",
    "sg:classifiers":[
        {
            "category":"Restaurant",
            "type":"Food & Drink"
        }
    ],
    "sg:phone":"+44 1923 820951",
    "sg:postcode":"HA6 2HJ",
    "sg:province":"Greater London",
    "sg:tags":[
        "chinese"
    ],
    "wof:name":"The Peking Garden Restaurant",
    "wof:placetype":"venue"
},
  "geometry": {"coordinates":[-0.434712,51.629395],"type":"Point"}
}