{
  "type": "Feature",
  "properties": {
    "iso:country":"GB",
    "sg:address":"28 Main Avenue, Moor Park",
    "sg:city":"Northwood",
    "sg:classifiers":[
        {
            "category":"Restaurant",
            "type":"Food & Drink"
        }
    ],
    "sg:phone":"+44 1923 820951",
    "sg:postcode":"HA6 2HJ",
    "sg:province":"Greater London",
    "sg:tags":[
        "chinese"
    ],
    "wof:name":"The Peking Garden Restaurant",
    "wof:placetype":"venue"
},
  "geometry": {"coordinates":[-0.434712,51.629395],"type":"Point"}
}