{
  "type": "Feature",
  "properties": {
    "addr:full":"North Road Porth Bridgend CF39 9SP",
    "addr:postcode":"cf39 9sp",
    "addr:street":"North Road",
    "iso:country":"GB",
    "sg:address":"North Road",
    "sg:city":"Porth",
    "sg:classifiers":[
        {
            "category":"Shopping",
            "subcategory":"Stationery & Office Supplies",
            "type":"Retail Goods"
        }
    ],
    "sg:phone":"+44 870 094 0623",
    "sg:postcode":"CF39 9SP",
    "sg:province":"Bridgend",
    "sg:tags":[
        "box",
        "carton"
    ],
    "wof:name":"Jacob Beatus Ltd.",
    "wof:placetype":"venue"
},
  "geometry": {"coordinates":[-3.4076089859,51.6137237549],"type":"Point"}
}