{
  "type": "Feature",
  "properties": {
    "iso:country":"GB",
    "sg:address":"Winterbourne Rd",
    "sg:city":"Teignmouth",
    "sg:classifiers":[
        {
            "category":"Community Center",
            "subcategory":"Youth",
            "type":"Public Place"
        }
    ],
    "sg:phone":"+44 1626 774707",
    "sg:postcode":"TQ14 8JT",
    "sg:province":"Devon",
    "sg:tags":[
        "organisation",
        "centre"
    ],
    "wof:name":"Winterbourne Youth Centre",
    "wof:placetype":"venue"
},
  "geometry": {"coordinates":[-3.497279,50.54953],"type":"Point"}
}