{
  "type": "Feature",
  "properties": {
    "iso:country":"GB",
    "sg:address":"29 Grange Road",
    "sg:city":"Jarrow",
    "sg:classifiers":[
        {
            "category":"Shopping",
            "subcategory":"Discount & Variety Stores",
            "type":"Retail Goods"
        }
    ],
    "sg:phone":"+44 191 489 4162",
    "sg:postcode":"NE32 3JY",
    "sg:province":"Tyne and Wear",
    "sg:tags":[
        "centre"
    ],
    "wof:name":"Lewins Discount Hardware",
    "wof:placetype":"venue"
},
  "geometry": {"coordinates":[-1.489652,54.98143],"type":"Point"}
}