{
  "type": "Feature",
  "properties": {
    "iso:country":"GB",
    "sg:address":"Bridge End Industrial Estate",
    "sg:city":"Egremont",
    "sg:classifiers":[
        {
            "category":"Retail",
            "subcategory":"Auto Repair",
            "type":"Services"
        }
    ],
    "sg:postcode":"CA22 2RD",
    "sg:province":"Cumbria",
    "sg:tags":[
        "modification",
        "garage",
        "related"
    ],
    "wof:name":"MILL GARAGE",
    "wof:placetype":"venue"
},
  "geometry": {"coordinates":[-3.524109,54.477356],"type":"Point"}
}