{
  "type": "Feature",
  "properties": {
    "iso:country":"GB",
    "sg:address":"Ferry Rd, Jackfield",
    "sg:city":"Telford",
    "sg:classifiers":[
        {
            "category":"Bars & Pubs",
            "type":"Food & Drink"
        }
    ],
    "sg:phone":"+44 1952 882178",
    "sg:postcode":"TF8 7LS",
    "sg:province":"Shropshire",
    "sg:tags":[
        "pubs",
        "inn"
    ],
    "wof:name":"The Boat Inn",
    "wof:placetype":"venue"
},
  "geometry": {"coordinates":[-2.454638958,52.6199302673],"type":"Point"}
}