{
  "type": "Feature",
  "properties": {
    "addr:full":"Crabbe Street Aldeburgh Suffolk IP15 5BN",
    "addr:postcode":"ip15 5bn",
    "addr:street":"Crabbe Street",
    "iso:country":"GB",
    "sg:address":"Crabbe Street",
    "sg:city":"Aldeburgh",
    "sg:classifiers":[
        {
            "category":"Bars & Pubs",
            "type":"Food & Drink"
        }
    ],
    "sg:phone":"+44 1728 452637",
    "sg:postcode":"IP15 5BN",
    "sg:province":"Suffolk",
    "sg:tags":[
        "pubs",
        "inn"
    ],
    "wof:name":"Cross Keys",
    "wof:placetype":"venue"
},
  "geometry": {"coordinates":[1.601626,52.152145],"type":"Point"}
}