{
  "type": "Feature",
  "properties": {
    "addr:full":"105a Mount Road Chessington Surrey KT9 1JH",
    "addr:housenumber":"105a",
    "addr:postcode":"kt9 1jh",
    "addr:street":"Mount Road",
    "iso:country":"GB",
    "sg:address":"105a Mount Road",
    "sg:city":"Chessington",
    "sg:classifiers":[
        {
            "category":"Social Services",
            "type":"Services"
        }
    ],
    "sg:phone":"+44 20 8397 0156",
    "sg:postcode":"KT9 1JH",
    "sg:province":"Surrey",
    "wof:name":"Four Oaks Adolescent Resource Centre",
    "wof:placetype":"venue"
},
  "geometry": {"coordinates":[-0.2949419916,51.3668060303],"type":"Point"}
}