{
  "type": "Feature",
  "properties": {
    "addr:full":"Perry Mill, Feckenham Rd, Hunt End Redditch Warwickshire B97 5QP",
    "addr:postcode":"b97 5qp",
    "addr:street":"Perry;Feckenham Rd;End",
    "iso:country":"GB",
    "sg:address":"Perry Mill, Feckenham Rd, Hunt End",
    "sg:city":"Redditch",
    "sg:classifiers":[
        {
            "category":"Professional",
            "subcategory":"Management & Consulting",
            "type":"Services"
        }
    ],
    "sg:phone":"+44 1527 540323",
    "sg:postcode":"B97 5QP",
    "sg:province":"Warwickshire",
    "sg:tags":[
        "consultant",
        "business"
    ],
    "wof:name":"West Midlands Management Consultancy",
    "wof:placetype":"venue"
},
  "geometry": {"coordinates":[-1.953354,52.278568],"type":"Point"}
}