{
  "type": "Feature",
  "properties": {
    "iso:country":"GB",
    "sg:address":"36 Starfield Rd, Shepherds Bush",
    "sg:city":"London",
    "sg:classifiers":[
        {
            "category":"Professional",
            "subcategory":"Detective & Security Services",
            "type":"Services"
        }
    ],
    "sg:postcode":"W12 9SW",
    "sg:province":"Greater London",
    "sg:tags":[
        "car"
    ],
    "wof:name":"Phillips,Dave,",
    "wof:placetype":"venue"
},
  "geometry": {"coordinates":[-0.24079,51.502769],"type":"Point"}
}