{
  "type": "Feature",
  "properties": {
    "addr:full":"Brecon Terr, St Dogmaels Rd Cardigan Ceredigion SA43 3AT",
    "addr:postcode":"sa43 3at",
    "addr:street":"Terr St Dogmaels Rd",
    "iso:country":"GB",
    "sg:address":"Brecon Terr, St Dogmaels Rd",
    "sg:city":"Cardigan",
    "sg:classifiers":[
        {
            "category":"Food & Beverages",
            "subcategory":"Farmers Market",
            "type":"Retail Goods"
        }
    ],
    "sg:phone":"+44 1239 612534",
    "sg:postcode":"SA43 3AT",
    "sg:province":"Ceredigion",
    "sg:tags":[
        "gardener"
    ],
    "wof:name":"G Trem",
    "wof:placetype":"venue"
},
  "geometry": {"coordinates":[-4.678309,52.081451],"type":"Point"}
}