{
  "type": "Feature",
  "properties": {
    "addr:full":"Inghams Barn, Valley Rd, Little Blakenham Ipswich Suffolk IP8 4LR",
    "addr:postcode":"ip8 4lr",
    "addr:street":"Valley Rd",
    "iso:country":"GB",
    "sg:address":"Inghams Barn, Valley Rd, Little Blakenham",
    "sg:city":"Ipswich",
    "sg:classifiers":[
        {
            "category":"Home & Garden",
            "subcategory":"Household Appliances",
            "type":"Retail Goods"
        }
    ],
    "sg:postcode":"IP8 4LR",
    "sg:province":"Suffolk",
    "sg:tags":[
        "electrical"
    ],
    "wof:name":"Dee,Len,",
    "wof:placetype":"venue"
},
  "geometry": {"coordinates":[1.0756490231,52.0966072083],"type":"Point"}
}