{
  "type": "Feature",
  "properties": {
    "addr:full":"14 Victoria Road Cirencester Gloucestershire GL7 1EN",
    "addr:housenumber":"14",
    "addr:postcode":"gl7 1en",
    "addr:street":"Victoria Road",
    "iso:country":"GB",
    "sg:address":"14 Victoria Road",
    "sg:city":"Cirencester",
    "sg:classifiers":[
        {
            "category":"Bars & Pubs",
            "type":"Food & Drink"
        },
        {
            "category":"Community Center",
            "subcategory":"Social",
            "type":"Public Place"
        }
    ],
    "sg:phone":"+44 1285 653760",
    "sg:postcode":"GL7 1EN",
    "sg:province":"Gloucestershire",
    "sg:tags":[
        "pubs",
        "house",
        "inn",
        "activity"
    ],
    "wof:name":"The Talbot Hotel",
    "wof:placetype":"venue"
},
  "geometry": {"coordinates":[-1.9619179964,51.7148704529],"type":"Point"}
}