{
  "type": "Feature",
  "properties": {
    "iso:country":"GB",
    "sg:address":"307 New Cross Road",
    "sg:city":"London",
    "sg:classifiers":[
        {
            "category":"Shopping",
            "subcategory":"Clothing, Apparel, & Fashions",
            "type":"Retail Goods"
        }
    ],
    "sg:phone":"+44 20 8694 8492",
    "sg:postcode":"SE14 6AS",
    "sg:province":"Greater London",
    "sg:tags":[
        "menswear"
    ],
    "wof:name":"Dappas",
    "wof:placetype":"venue"
},
  "geometry": {"coordinates":[-0.037965,51.475639],"type":"Point"}
}