{
  "type": "Feature",
  "properties": {
    "iso:country":"GB",
    "sg:address":"12 Stapledon Road, Orton Southgate",
    "sg:city":"Peterborough",
    "sg:classifiers":[
        {
            "category":"Home & Garden",
            "subcategory":"Hardware",
            "type":"Retail Goods"
        },
        {
            "category":"Home & Garden",
            "subcategory":"Building Materials",
            "type":"Retail Goods"
        }
    ],
    "sg:phone":"+44 1733 361222",
    "sg:postcode":"PE2 6TD",
    "sg:province":"Cambridgeshire",
    "sg:tags":[
        "manufacture",
        "adhesive",
        "adhesives",
        "sealant",
        "distribution",
        "glue"
    ],
    "wof:name":"CHEMFIL LTD",
    "wof:placetype":"venue"
},
  "geometry": {"coordinates":[-0.3076950014,52.5397262573],"type":"Point"}
}