{
  "type": "Feature",
  "properties": {
    "addr:full":"139 Station Road, Hesketh Bank Preston Lancashire PR4 6SR",
    "addr:housenumber":"139",
    "addr:postcode":"pr4 6sr",
    "addr:street":"Station Road",
    "iso:country":"GB",
    "sg:address":"139 Station Road, Hesketh Bank",
    "sg:city":"Preston",
    "sg:classifiers":[
        {
            "category":"Home & Garden",
            "subcategory":"Garden Supply",
            "type":"Retail Goods"
        },
        {
            "category":"Food & Beverages",
            "subcategory":"Farmers Market",
            "type":"Retail Goods"
        }
    ],
    "sg:phone":"+44 1772 812574",
    "sg:postcode":"PR4 6SR",
    "sg:province":"Lancashire",
    "sg:tags":[
        "tree",
        "shrub",
        "gardener"
    ],
    "wof:name":"Edenbreck Nurseries",
    "wof:placetype":"venue"
},
  "geometry": {"coordinates":[-2.842135,53.705135],"type":"Point"}
}