{
  "type": "Feature",
  "properties": {
    "addr:full":"Church Road Haslemere Hampshire GU27 1BH",
    "addr:postcode":"gu27 1bh",
    "addr:street":"Church Road",
    "iso:country":"GB",
    "sg:address":"Church Road",
    "sg:city":"Haslemere",
    "sg:classifiers":[
        {
            "category":"Social Services",
            "subcategory":"Retirement Home",
            "type":"Services"
        }
    ],
    "sg:phone":"+44 1428 661372",
    "sg:postcode":"GU27 1BH",
    "sg:province":"Hampshire",
    "sg:tags":[
        "rest"
    ],
    "wof:name":"Rosemary Court",
    "wof:placetype":"venue"
},
  "geometry": {"coordinates":[-0.7136989832,51.0915641785],"type":"Point"}
}