{
  "type": "Feature",
  "properties": {
    "addr:full":"8 Snapehill Rd Barnsley South Yorkshire S73 9JU",
    "addr:housenumber":"8",
    "addr:postcode":"s73 9ju",
    "addr:street":"Snapehill Rd;Yorkshire",
    "iso:country":"GB",
    "sg:address":"8 Snapehill Rd",
    "sg:city":"Barnsley",
    "sg:classifiers":[
        {
            "category":"Personal",
            "subcategory":"Beauty Salon",
            "type":"Services"
        }
    ],
    "sg:phone":"+44 1226 758324",
    "sg:postcode":"S73 9JU",
    "sg:province":"South Yorkshire",
    "sg:tags":[
        "unisex",
        "hairdresser"
    ],
    "wof:name":"Creative Designs",
    "wof:placetype":"venue"
},
  "geometry": {"coordinates":[-1.3742669821,53.5338630676],"type":"Point"}
}