{
  "type": "Feature",
  "properties": {
    "iso:country":"GB",
    "sg:address":"Bay Cottage, Little London",
    "sg:city":"Bath",
    "sg:classifiers":[
        {
            "category":"Building & Trades",
            "subcategory":"Construction",
            "type":"Services"
        }
    ],
    "sg:phone":"+44 1749 841246",
    "sg:postcode":"BA3 5AU",
    "sg:province":"Somerset",
    "sg:tags":[
        "joiner",
        "carpenter"
    ],
    "wof:name":"Woodford Joinery",
    "wof:placetype":"venue"
},
  "geometry": {"coordinates":[-2.53238,51.22377],"type":"Point"}
}