{
  "type": "Feature",
  "properties": {
    "iso:country":"GB",
    "sg:address":"Tudor Works, Fountain Street North",
    "sg:city":"Bury",
    "sg:classifiers":[
        {
            "category":"Manufacturing",
            "subcategory":"Petroleum Products",
            "type":"Manufacturing & Wholesale Goods"
        }
    ],
    "sg:phone":"+44 161 705 2430",
    "sg:postcode":"BL9 7AN",
    "sg:province":"Lancashire",
    "sg:tags":[
        "double",
        "glazing"
    ],
    "wof:name":"Tudor Glass & Glazing",
    "wof:placetype":"venue"
},
  "geometry": {"coordinates":[-2.285704,53.595276],"type":"Point"}
}