{
  "type": "Feature",
  "properties": {
    "addr:full":"26 Cadogan Gdn(s) London Greater London SW3 2RP",
    "addr:housenumber":"26",
    "addr:postcode":"sw3 2rp",
    "addr:street":"Cadogan Gdn S",
    "iso:country":"GB",
    "sg:address":"26 Cadogan Gdn(s)",
    "sg:city":"London",
    "sg:classifiers":[
        {
            "category":"Travel",
            "subcategory":"Hotels & Motels",
            "type":"Entertainment"
        }
    ],
    "sg:phone":"+44 20 7730 6466",
    "sg:postcode":"SW3 2RP",
    "sg:province":"Greater London",
    "wof:name":"Mantis London Ltd.",
    "wof:placetype":"venue"
},
  "geometry": {"coordinates":[-0.1596339941,51.4931297302],"type":"Point"}
}