{
  "type": "Feature",
  "properties": {
    "iso:country":"GB",
    "sg:address":"27 Gateford Rd",
    "sg:city":"Worksop",
    "sg:classifiers":[
        {
            "category":"Manufacturing",
            "subcategory":"Textiles",
            "type":"Manufacturing & Wholesale Goods"
        }
    ],
    "sg:phone":"+44 1909 472103",
    "sg:postcode":"S80 1DY",
    "sg:province":"Nottinghamshire",
    "sg:tags":[
        "made-up"
    ],
    "wof:name":"Tomlinsons Gateford Curtains",
    "wof:placetype":"venue"
},
  "geometry": {"coordinates":[-1.1234719753,53.307964325],"type":"Point"}
}