{
  "type": "Feature",
  "properties": {
    "iso:country":"GB",
    "sg:address":"14 St.johns Road",
    "sg:city":"Tunbridge Wells",
    "sg:classifiers":[
        {
            "category":"Insurance",
            "subcategory":"Health Insurance",
            "type":"Services"
        }
    ],
    "sg:postcode":"TN4 9NP",
    "sg:province":"Kent",
    "wof:name":"Mckenzie Ltd",
    "wof:placetype":"venue"
},
  "geometry": {"coordinates":[0.261806,51.137562],"type":"Point"}
}