{
  "type": "Feature",
  "properties": {
    "iso:country":"GB",
    "sg:address":"Fowlswick Farm, Fowlswick Lane, Allington",
    "sg:city":"Chippenham",
    "sg:classifiers":[
        {
            "category":"Freight",
            "type":"Transportation"
        }
    ],
    "sg:postcode":"SN14 6QE",
    "sg:province":"Gloucestershire",
    "sg:tags":[
        "haulage",
        "road"
    ],
    "wof:name":"Compass Couriers",
    "wof:placetype":"venue"
},
  "geometry": {"coordinates":[-2.154439,51.473461],"type":"Point"}
}