{
  "type": "Feature",
  "properties": {
    "addr:full":"400 Capability Green Luton Bedfordshire LU1 3LU",
    "addr:housenumber":"400",
    "addr:postcode":"lu1 3lu",
    "addr:street":"Capability Green",
    "iso:country":"GB",
    "sg:address":"400 Capability Green",
    "sg:city":"Luton",
    "sg:classifiers":[
        {
            "category":"Organizations",
            "subcategory":"Membership Organization",
            "type":"Services"
        }
    ],
    "sg:postcode":"LU1 3LU",
    "sg:province":"Bedfordshire",
    "sg:tags":[
        "club"
    ],
    "wof:name":"Ashcourt Consultants Ltd",
    "wof:placetype":"venue"
},
  "geometry": {"coordinates":[-0.408908993,51.8658905029],"type":"Point"}
}