{
  "type": "Feature",
  "properties": {
    "iso:country":"GB",
    "sg:address":"496 Elswick Road",
    "sg:city":"Newcastle-upon-tyne",
    "sg:classifiers":[
        {
            "category":"Shopping",
            "subcategory":"Pets & Pet Supplies",
            "type":"Retail Goods"
        }
    ],
    "sg:phone":"+44 191 226 0700",
    "sg:postcode":"NE4 8ED",
    "sg:province":"Tyne and Wear",
    "sg:tags":[
        "shop"
    ],
    "wof:name":"Petwise",
    "wof:placetype":"venue"
},
  "geometry": {"coordinates":[-1.654350996,54.9698638916],"type":"Point"}
}