{
  "type": "Feature",
  "properties": {
    "addr:full":"21 Allensway Stockton-on-tees Durham TS17 9HA",
    "addr:housenumber":"21",
    "addr:postcode":"ts17 9ha",
    "addr:street":"Allensway Stockton-On-Tees",
    "iso:country":"GB",
    "sg:address":"21 Allensway",
    "sg:city":"Stockton-on-tees",
    "sg:classifiers":[
        {
            "category":"Professional",
            "subcategory":"Engineering",
            "type":"Services"
        }
    ],
    "sg:phone":"+44 1642 769085",
    "sg:postcode":"TS17 9HA",
    "sg:province":"Durham",
    "wof:name":"E I - W H S Electrical Instrumentation",
    "wof:placetype":"venue"
},
  "geometry": {"coordinates":[-1.289933,54.536819],"type":"Point"}
}