{
  "type": "Feature",
  "properties": {
    "addr:full":"22 Milk Street Bath Bath and North East Somerset BA1 1UT",
    "addr:housenumber":"22",
    "addr:postcode":"ba1 1ut",
    "addr:street":"Milk Street",
    "iso:country":"GB",
    "sg:address":"22 Milk Street",
    "sg:city":"Bath",
    "sg:classifiers":[
        {
            "category":"Professional",
            "subcategory":"Printing & Photocopies",
            "type":"Services"
        }
    ],
    "sg:phone":"+44 1225 461888",
    "sg:postcode":"BA1 1UT",
    "sg:province":"Bath and North East Somerset",
    "sg:tags":[
        "printer"
    ],
    "wof:name":"Bcn (Bath) Ltd.",
    "wof:placetype":"venue"
},
  "geometry": {"coordinates":[-2.3638999462,51.3798828125],"type":"Point"}
}