{
  "type": "Feature",
  "properties": {
    "addr:full":"Winthorns Premises, Salters Lane, Wootton Wawen Solihull Warwickshire B95 6DN",
    "addr:postcode":"b95 6dn",
    "addr:street":"Salters Lane",
    "iso:country":"GB",
    "sg:address":"Winthorns Premises, Salters Lane, Wootton Wawen",
    "sg:city":"Solihull",
    "sg:classifiers":[
        {
            "category":"Sports & Exercise",
            "subcategory":"Stables",
            "type":"Entertainment"
        }
    ],
    "sg:phone":"+44 1789 731432",
    "sg:postcode":"B95 6DN",
    "sg:province":"Warwickshire",
    "sg:tags":[
        "education",
        "equestrian"
    ],
    "wof:name":"Winthorns Livery Yard",
    "wof:placetype":"venue"
},
  "geometry": {"coordinates":[-1.777409,52.266731],"type":"Point"}
}