{
  "type": "Feature",
  "properties": {
    "iso:country":"GB",
    "sg:address":"Cheshire House, 18-20 Booth Street",
    "sg:city":"Manchester",
    "sg:classifiers":[
        {
            "category":"Real Estate",
            "subcategory":"Architect",
            "type":"Services"
        }
    ],
    "sg:phone":"+44 161 236 4550",
    "sg:postcode":"M2 4AN",
    "sg:province":"Greater Manchester",
    "sg:tags":[
        "architectural"
    ],
    "wof:name":"Landscape Projects",
    "wof:placetype":"venue"
},
  "geometry": {"coordinates":[-2.243329,53.480309],"type":"Point"}
}