{
  "type": "Feature",
  "properties": {
    "iso:country":"GB",
    "sg:address":"12 Church St",
    "sg:city":"Reigate",
    "sg:classifiers":[
        {
            "category":"Bars & Pubs",
            "type":"Food & Drink"
        }
    ],
    "sg:phone":"+44 1737 246383",
    "sg:postcode":"RH2 0AN",
    "sg:province":"Surrey",
    "sg:tags":[
        "pubs",
        "inn"
    ],
    "wof:name":"Faucet & Firkin",
    "wof:placetype":"venue"
},
  "geometry": {"coordinates":[-0.2046499997,51.2377433777],"type":"Point"}
}