{
  "type": "Feature",
  "properties": {
    "addr:full":"Dailfearn, Achmore Strome Ferry Highland IV53 8UW",
    "addr:postcode":"iv53 8uw",
    "addr:street":"Ferry",
    "iso:country":"GB",
    "sg:address":"Dailfearn, Achmore",
    "sg:city":"Strome Ferry",
    "sg:classifiers":[
        {
            "category":"Manufacturing",
            "subcategory":"Food",
            "type":"Manufacturing & Wholesale Goods"
        }
    ],
    "sg:postcode":"IV53 8UW",
    "sg:province":"Highland",
    "sg:tags":[
        "cheese",
        "producer"
    ],
    "wof:name":"West Highland Dairy Sheep",
    "wof:placetype":"venue"
},
  "geometry": {"coordinates":[-5.5543279648,57.3524093628],"type":"Point"}
}