{
  "type": "Feature",
  "properties": {
    "addr:full":"65/67 New Dover Road Canterbury Kent CT1 3DX",
    "addr:housenumber":"65 / 67",
    "addr:postcode":"ct1 3dx",
    "addr:street":"New Dover Road",
    "iso:country":"GB",
    "sg:address":"65/67 New Dover Road",
    "sg:city":"Canterbury",
    "sg:classifiers":[
        {
            "category":"Travel",
            "subcategory":"Hotels & Motels",
            "type":"Entertainment"
        }
    ],
    "sg:phone":"+44 1227 768433",
    "sg:postcode":"CT1 3DX",
    "sg:province":"Kent",
    "wof:name":"Peter Mason (Canterbury) Ltd.",
    "wof:placetype":"venue"
},
  "geometry": {"coordinates":[1.0920430422,51.2717018127],"type":"Point"}
}