{
  "type": "Feature",
  "properties": {
    "addr:full":"406-408 High Street Winsford Cheshire CW7 2DD",
    "addr:housenumber":"406-408",
    "addr:postcode":"cw7 2dd",
    "addr:street":"High Street",
    "iso:country":"GB",
    "sg:address":"406-408 High Street",
    "sg:city":"Winsford",
    "sg:classifiers":[
        {
            "category":"Health Services",
            "subcategory":"Dentist",
            "type":"Services"
        }
    ],
    "sg:phone":"+44 1606 550264",
    "sg:postcode":"CW7 2DD",
    "sg:province":"Cheshire",
    "wof:name":"Park House Dental Practice",
    "wof:placetype":"venue"
},
  "geometry": {"coordinates":[-2.533264,53.191891],"type":"Point"}
}