{
  "type": "Feature",
  "properties": {
    "addr:full":"1st Floor, 16 Bushland Road Northampton Northamptonshire NN3 2NS",
    "addr:housenumber":"16",
    "addr:postcode":"nn3 2ns",
    "addr:street":"Bushland Road",
    "iso:country":"GB",
    "sg:address":"1st Floor, 16 Bushland Road",
    "sg:city":"Northampton",
    "sg:classifiers":[
        {
            "category":"Professional",
            "type":"Services"
        }
    ],
    "sg:phone":"+44 1604 409111",
    "sg:postcode":"NN3 2NS",
    "sg:province":"Northamptonshire",
    "sg:tags":[
        "repair",
        "tech",
        "maintenance"
    ],
    "wof:name":"Routecliff Ltd.",
    "wof:placetype":"venue"
},
  "geometry": {"coordinates":[-0.852981,52.259209],"type":"Point"}
}