{
  "type": "Feature",
  "properties": {
    "iso:country":"GB",
    "sg:address":"16 Harper Lane, Yeadon",
    "sg:city":"Leeds",
    "sg:classifiers":[
        {
            "category":"Health Services",
            "subcategory":"Nursing And Care Facility",
            "type":"Services"
        },
        {
            "category":"Social Services",
            "subcategory":"Retirement Home",
            "type":"Services"
        }
    ],
    "sg:phone":"+44 113 250 8677",
    "sg:postcode":"LS19 7RR",
    "sg:province":"West Yorkshire",
    "sg:tags":[
        "residential"
    ],
    "wof:name":"Brooklands Residential Home",
    "wof:placetype":"venue"
},
  "geometry": {"coordinates":[-1.684497,53.864483],"type":"Point"}
}