{
  "type": "Feature",
  "properties": {
    "addr:full":"37 Dewhurst Rd, Birchwood Warrington Cheshire WA3 7PG",
    "addr:housenumber":"37",
    "addr:postcode":"wa3 7pg",
    "addr:street":"Dewhurst Rd",
    "iso:country":"GB",
    "sg:address":"37 Dewhurst Rd, Birchwood",
    "sg:city":"Warrington",
    "sg:classifiers":[
        {
            "category":"Personal",
            "subcategory":"Beauty Salon",
            "type":"Services"
        }
    ],
    "sg:postcode":"WA3 7PG",
    "sg:province":"Cheshire",
    "sg:tags":[
        "unisex",
        "hairdresser"
    ],
    "wof:name":"Brewster's (Haircare) Ltd",
    "wof:placetype":"venue"
},
  "geometry": {"coordinates":[-2.5254030228,53.4133033752],"type":"Point"}
}