{
  "type": "Feature",
  "properties": {
    "addr:full":"Westhead Avenue Liverpool Lancashire L33 0XN",
    "addr:postcode":"l33 0xn",
    "addr:street":"Westhead Avenue",
    "iso:country":"GB",
    "sg:address":"Westhead Avenue",
    "sg:city":"Liverpool",
    "sg:classifiers":[
        {
            "category":"Organizations",
            "subcategory":"Non-profit Organization",
            "type":"Services"
        }
    ],
    "sg:phone":"+44 151 547 1433",
    "sg:postcode":"L33 0XN",
    "sg:province":"Lancashire",
    "sg:tags":[
        "organisation",
        "voluntary",
        "charity"
    ],
    "wof:name":"Multi Skilled Resources",
    "wof:placetype":"venue"
},
  "geometry": {"coordinates":[-2.880753994,53.4825515747],"type":"Point"}
}