{
  "type": "Feature",
  "properties": {
    "iso:country":"GB",
    "sg:address":"Whitegates, Romaldkirk",
    "sg:city":"Barnard Castle",
    "sg:classifiers":[
        {
            "category":"Health Services",
            "subcategory":"Doctor",
            "type":"Services"
        }
    ],
    "sg:phone":"+44 1833 650341",
    "sg:postcode":"DL12 9EG",
    "sg:province":"Cumbria",
    "sg:tags":[
        "practitioners"
    ],
    "wof:name":"Pakiam, A",
    "wof:placetype":"venue"
},
  "geometry": {"coordinates":[-2.010925,54.594795],"type":"Point"}
}