{
  "type": "Feature",
  "properties": {
    "iso:country":"GB",
    "sg:address":"35 Lock Cres",
    "sg:city":"Kidlington",
    "sg:classifiers":[
        {
            "category":"Parking",
            "type":"Transportation"
        }
    ],
    "sg:phone":"+44 1865 881598",
    "sg:postcode":"OX5 1HD",
    "sg:province":"Buckinghamshire",
    "sg:tags":[
        "car",
        "valet"
    ],
    "wof:name":"Gleam Team",
    "wof:placetype":"venue"
},
  "geometry": {"coordinates":[-1.286402,51.810562],"type":"Point"}
}