{
  "type": "Feature",
  "properties": {
    "iso:country":"GB",
    "sg:address":"Unit 9, Sussex House Industrial Estate",
    "sg:city":"Hove",
    "sg:classifiers":[
        {
            "category":"Retail",
            "subcategory":"Auto Repair",
            "type":"Services"
        }
    ],
    "sg:phone":"+44 1273 771352",
    "sg:postcode":"BN3 7DX",
    "sg:province":"East Sussex",
    "sg:tags":[
        "body",
        "car"
    ],
    "wof:name":"Mike Reynolds Coach Works",
    "wof:placetype":"venue"
},
  "geometry": {"coordinates":[-0.182449,50.838943],"type":"Point"}
}