{
  "type": "Feature",
  "properties": {
    "iso:country":"GB",
    "sg:address":"Unit 2, Planet Wks, Atlantic St, Broadheath",
    "sg:city":"Altrincham",
    "sg:classifiers":[
        {
            "category":"Wholesale",
            "subcategory":"Construction Materials",
            "type":"Manufacturing & Wholesale Goods"
        }
    ],
    "sg:postcode":"WA14 5DW",
    "sg:province":"Cheshire",
    "sg:tags":[
        "coating",
        "powder"
    ],
    "wof:name":"Corrosion Control International Ltd",
    "wof:placetype":"venue"
},
  "geometry": {"coordinates":[-2.352551,53.400391],"type":"Point"}
}