{
  "type": "Feature",
  "properties": {
    "addr:full":"37 Market Street, Woolwich London Greater London SE18 6QR",
    "addr:housenumber":"37",
    "addr:postcode":"se18 6qr",
    "addr:street":"Market Street",
    "iso:country":"GB",
    "sg:address":"37 Market Street, Woolwich",
    "sg:city":"London",
    "sg:classifiers":[
        {
            "category":"Autos & Motor Vehicles",
            "subcategory":"Fuel & Gas Station",
            "type":"Retail Goods"
        }
    ],
    "sg:phone":"+44 20 8854 5535",
    "sg:postcode":"SE18 6QR",
    "sg:province":"Greater London",
    "sg:tags":[
        "petrol",
        "filling"
    ],
    "wof:name":"Plaistow Broadway Filling Stations Ltd.",
    "wof:placetype":"venue"
},
  "geometry": {"coordinates":[0.0636970028,51.4899978638],"type":"Point"}
}