{
  "type": "Feature",
  "properties": {
    "iso:country":"GB",
    "sg:address":"11 Willow Lane, Langar",
    "sg:city":"Nottingham",
    "sg:classifiers":[
        {
            "category":"Taxi",
            "type":"Transportation"
        }
    ],
    "sg:phone":"+44 1949 860921",
    "sg:postcode":"NG13 9HL",
    "sg:province":"Leicestershire",
    "sg:tags":[
        "mini",
        "cab"
    ],
    "wof:name":"Belvoir Executive Cars",
    "wof:placetype":"venue"
},
  "geometry": {"coordinates":[-0.922796,52.904083],"type":"Point"}
}