{
  "type": "Feature",
  "properties": {
    "addr:full":"11 Willow Lane, Langar Nottingham Leicestershire NG13 9HL",
    "addr:housenumber":"11",
    "addr:postcode":"ng13 9hl",
    "addr:street":"Willow Lane",
    "iso:country":"GB",
    "sg:address":"11 Willow Lane, Langar",
    "sg:city":"Nottingham",
    "sg:classifiers":[
        {
            "category":"Taxi",
            "type":"Transportation"
        }
    ],
    "sg:phone":"+44 1949 860921",
    "sg:postcode":"NG13 9HL",
    "sg:province":"Leicestershire",
    "sg:tags":[
        "mini",
        "cab"
    ],
    "wof:name":"Belvoir Executive Cars",
    "wof:placetype":"venue"
},
  "geometry": {"coordinates":[-0.922796,52.904083],"type":"Point"}
}