{
  "type": "Feature",
  "properties": {
    "addr:full":"102 Belgrave Road Leicester Leicestershire LE4 5AT",
    "addr:housenumber":"102",
    "addr:postcode":"le4 5at",
    "addr:street":"Belgrave Road",
    "iso:country":"GB",
    "sg:address":"102 Belgrave Road",
    "sg:city":"Leicester",
    "sg:classifiers":[
        {
            "category":"Fast Food",
            "type":"Food & Drink"
        }
    ],
    "sg:phone":"+44 116 268 0100",
    "sg:postcode":"LE4 5AT",
    "sg:province":"Leicestershire",
    "sg:tags":[
        "away",
        "take"
    ],
    "wof:name":"Melton Hot Potato Shop",
    "wof:placetype":"venue"
},
  "geometry": {"coordinates":[-1.1240069866,52.6482124329],"type":"Point"}
}