{
  "type": "Feature",
  "properties": {
    "iso:country":"GB",
    "sg:address":"Bank House, Wine Street",
    "sg:city":"Bristol",
    "sg:classifiers":[
        {
            "category":"Banks & Credit Unions",
            "subcategory":"Bank",
            "type":"Services"
        }
    ],
    "sg:phone":"+44 117 925 1332",
    "sg:postcode":"BS1 2AN",
    "sg:province":"City of Bristol",
    "wof:name":"Lloyds T S B Private Banking Ltd.",
    "wof:placetype":"venue"
},
  "geometry": {"coordinates":[-2.592578,51.455082],"type":"Point"}
}