{
  "type": "Feature",
  "properties": {
    "addr:full":"Unit A, Aerial Business Park, Lambourn Woodland Hungerford Berkshire RG17 7RZ",
    "addr:housenumber":"unit a",
    "addr:postcode":"rg17 7rz",
    "addr:street":"Aerial Business Park",
    "iso:country":"GB",
    "sg:address":"Unit A, Aerial Business Park, Lambourn Woodland",
    "sg:city":"Hungerford",
    "sg:classifiers":[
        {
            "category":"Manufacturing",
            "subcategory":"Rubber & Plastics",
            "type":"Manufacturing & Wholesale Goods"
        },
        {
            "category":"Manufacturing",
            "subcategory":"Wood Products",
            "type":"Manufacturing & Wholesale Goods"
        }
    ],
    "sg:phone":"+44 1488 72070",
    "sg:postcode":"RG17 7RZ",
    "sg:province":"Berkshire",
    "sg:tags":[
        "packaging",
        "injection",
        "moulding",
        "crate",
        "pallets"
    ],
    "wof:name":"Kennet Packaging Ltd.",
    "wof:placetype":"venue"
},
  "geometry": {"coordinates":[-1.553495,51.477058],"type":"Point"}
}