{
  "type": "Feature",
  "properties": {
    "iso:country":"GB",
    "sg:address":"34 Market Hall, Teall Street",
    "sg:city":"Wakefield",
    "sg:classifiers":[
        {
            "category":"Shopping",
            "subcategory":"Books",
            "type":"Retail Goods"
        },
        {
            "category":"Shopping",
            "subcategory":"News",
            "type":"Retail Goods"
        }
    ],
    "sg:postcode":"WF1 1QF",
    "sg:province":"West Yorkshire",
    "sg:tags":[
        "bookseller",
        "newsagent"
    ],
    "wof:name":"W H Stringer & Sons",
    "wof:placetype":"venue"
},
  "geometry": {"coordinates":[-1.4959000349,53.6834793091],"type":"Point"}
}