{
  "type": "Feature",
  "properties": {
    "iso:country":"GB",
    "sg:address":"115-117 Caledonia Street",
    "sg:city":"Bradford",
    "sg:classifiers":[
        {
            "category":"Home & Garden",
            "subcategory":"Carpets & Floor Coverings",
            "type":"Retail Goods"
        },
        {
            "category":"Home & Garden",
            "subcategory":"Kitchen Supply",
            "type":"Retail Goods"
        }
    ],
    "sg:phone":"+44 1274 723629",
    "sg:postcode":"BD4 7BJ",
    "sg:province":"West Yorkshire",
    "sg:tags":[
        "measuring",
        "scale",
        "manufacturer"
    ],
    "wof:name":"Gibbs & Windle",
    "wof:placetype":"venue"
},
  "geometry": {"coordinates":[-1.749546,53.787994],"type":"Point"}
}