{
  "type": "Feature",
  "properties": {
    "addr:full":"Alderley Rd, Chelford Macclesfield Cheshire SK11 9AR",
    "addr:postcode":"sk11 9ar",
    "addr:street":"Alderley Rd",
    "iso:country":"GB",
    "sg:address":"Alderley Rd, Chelford",
    "sg:city":"Macclesfield",
    "sg:classifiers":[
        {
            "category":"Autos & Motor Vehicles",
            "subcategory":"Fuel & Gas Station",
            "type":"Retail Goods"
        }
    ],
    "sg:postcode":"SK11 9AR",
    "sg:province":"Cheshire",
    "sg:tags":[
        "petrol",
        "filling"
    ],
    "wof:name":"Gilbert,S T,& N A Heggs",
    "wof:placetype":"venue"
},
  "geometry": {"coordinates":[-2.284085,53.271271],"type":"Point"}
}