{
  "type": "Feature",
  "properties": {
    "iso:country":"GB",
    "sg:address":"116 High Road, Needham",
    "sg:city":"Harleston",
    "sg:classifiers":[
        {
            "category":"Freight",
            "type":"Transportation"
        }
    ],
    "sg:phone":"+44 1379 852885",
    "sg:postcode":"IP20 9LG",
    "sg:province":"Norfolk",
    "sg:tags":[
        "forwarders"
    ],
    "wof:name":"D J & S Simmonds",
    "wof:placetype":"venue"
},
  "geometry": {"coordinates":[1.2644699812,52.3788986206],"type":"Point"}
}