{
  "type": "Feature",
  "properties": {
    "addr:full":"67 Church Street Shildon Durham DL4 1DT",
    "addr:housenumber":"67",
    "addr:postcode":"dl4 1dt",
    "addr:street":"Church Street",
    "iso:country":"GB",
    "sg:address":"67 Church Street",
    "sg:city":"Shildon",
    "sg:classifiers":[
        {
            "category":"Shopping",
            "subcategory":"Thrift Store",
            "type":"Retail Goods"
        }
    ],
    "sg:phone":"+44 1388 775445",
    "sg:postcode":"DL4 1DT",
    "sg:province":"Durham",
    "sg:tags":[
        "shop",
        "charity"
    ],
    "wof:name":"St. Teresa's Hospice",
    "wof:placetype":"venue"
},
  "geometry": {"coordinates":[-1.644725,54.634079],"type":"Point"}
}