{
  "type": "Feature",
  "properties": {
    "addr:full":"8 Victoria Pl Haverfordwest Pembrokeshire SA61 2LQ",
    "addr:housenumber":"8",
    "addr:postcode":"sa61 2lq",
    "addr:street":"Victoria Pl",
    "iso:country":"GB",
    "sg:address":"8 Victoria Pl",
    "sg:city":"Haverfordwest",
    "sg:classifiers":[
        {
            "category":"Professional",
            "subcategory":"Employment Agencies",
            "type":"Services"
        }
    ],
    "sg:phone":"+44 1437 772100",
    "sg:postcode":"SA61 2LQ",
    "sg:province":"Pembrokeshire",
    "sg:tags":[
        "career",
        "guidance"
    ],
    "wof:name":"Dyfed Careers Co",
    "wof:placetype":"venue"
},
  "geometry": {"coordinates":[-4.9670739174,51.8025398254],"type":"Point"}
}