{
  "type": "Feature",
  "properties": {
    "iso:country":"GB",
    "sg:address":"Stockfield Mount Sheltered House, Stockfield Mount",
    "sg:city":"Oldham",
    "sg:classifiers":[
        {
            "category":"Government",
            "subcategory":"Office",
            "type":"Public Place"
        },
        {
            "category":"Social Services",
            "subcategory":"Adult Care",
            "type":"Services"
        },
        {
            "category":"Social Services",
            "subcategory":"Retirement Home",
            "type":"Services"
        }
    ],
    "sg:phone":"+44 161 627 3868",
    "sg:postcode":"OL9 9AT",
    "sg:province":"Lancashire",
    "sg:tags":[
        "accomodation",
        "housing",
        "local",
        "sheltered"
    ],
    "wof:name":"Oldham Metropolitan Borough Council",
    "wof:placetype":"venue"
},
  "geometry": {"coordinates":[-2.1396439075,53.5396614075],"type":"Point"}
}