{
  "type": "Feature",
  "properties": {
    "iso:country":"GB",
    "sg:address":"10 Rylstone Road",
    "sg:city":"Eastbourne",
    "sg:classifiers":[
        {
            "category":"Travel",
            "subcategory":"Hotels & Motels",
            "type":"Entertainment"
        }
    ],
    "sg:phone":"+44 1323 639709",
    "sg:postcode":"BN22 7HN",
    "sg:province":"East Sussex",
    "sg:tags":[
        "house",
        "guest"
    ],
    "wof:name":"Westways Guest House",
    "wof:placetype":"venue"
},
  "geometry": {"coordinates":[0.29849,50.773708],"type":"Point"}
}