{
  "type": "Feature",
  "properties": {
    "iso:country":"GB",
    "sg:address":"18 Norby Rd",
    "sg:city":"Glasgow",
    "sg:classifiers":[
        {
            "category":"Personal",
            "subcategory":"Beauty Salon",
            "type":"Services"
        }
    ],
    "sg:phone":"+44 141 337 1700",
    "sg:postcode":"G11 7BN",
    "sg:province":"Glasgow City",
    "sg:tags":[
        "unisex",
        "hairdresser"
    ],
    "wof:name":"Hair By Rae & Co",
    "wof:placetype":"venue"
},
  "geometry": {"coordinates":[-4.324445,55.875912],"type":"Point"}
}