{
  "type": "Feature",
  "properties": {
    "iso:country":"GB",
    "sg:address":"Headless Cross House, Rivington Lane, Anderton",
    "sg:city":"Chorley",
    "sg:classifiers":[
        {
            "category":"Real Estate",
            "subcategory":"Surveying",
            "type":"Services"
        }
    ],
    "sg:phone":"+44 1257 474734",
    "sg:postcode":"PR6 9HQ",
    "sg:province":"Lancashire",
    "sg:tags":[
        "surveyor",
        "quantity"
    ],
    "wof:name":"Beaumont Partnership",
    "wof:placetype":"venue"
},
  "geometry": {"coordinates":[-2.5761239529,53.6115493774],"type":"Point"}
}