{
  "type": "Feature",
  "properties": {
    "iso:country":"GB",
    "sg:address":"Charlbury,",
    "sg:city":"Chipping Norton",
    "sg:classifiers":[
        {
            "category":"Communications",
            "subcategory":"Newspaper",
            "type":"Services"
        }
    ],
    "sg:postcode":"OX7 3PQ",
    "sg:province":"Gloucestershire",
    "sg:tags":[
        "magazine"
    ],
    "wof:name":"Mediawatch International",
    "wof:placetype":"venue"
},
  "geometry": {"coordinates":[-1.4943490028,51.8727607727],"type":"Point"}
}