{
  "type": "Feature",
  "properties": {
    "iso:country":"GB",
    "sg:address":"170 High Street",
    "sg:city":"Guildford",
    "sg:classifiers":[
        {
            "category":"Shopping",
            "subcategory":"Books",
            "type":"Retail Goods"
        }
    ],
    "sg:postcode":"GU1 3HP",
    "sg:province":"Surrey",
    "sg:tags":[
        "bookseller"
    ],
    "wof:name":"Thomas Thorp",
    "wof:placetype":"venue"
},
  "geometry": {"coordinates":[-0.570374,51.236153],"type":"Point"}
}