{
  "type": "Feature",
  "properties": {
    "iso:country":"GB",
    "sg:address":"19 Dighton Road",
    "sg:city":"London",
    "sg:classifiers":[
        {
            "category":"Building & Trades",
            "subcategory":"Construction",
            "type":"Services"
        }
    ],
    "sg:phone":"+44 20 8874 5381",
    "sg:postcode":"SW18 1AN",
    "sg:province":"Greater London",
    "sg:tags":[
        "builder"
    ],
    "wof:name":"Clifford James Construction",
    "wof:placetype":"venue"
},
  "geometry": {"coordinates":[-0.1855179965,51.4598808289],"type":"Point"}
}