{
  "type": "Feature",
  "properties": {
    "iso:country":"GB",
    "sg:address":"Hart Mill, Lees Rd",
    "sg:city":"Ashton Under Lyne",
    "sg:classifiers":[
        {
            "category":"Manufacturing",
            "subcategory":"Building Materials",
            "type":"Manufacturing & Wholesale Goods"
        }
    ],
    "sg:phone":"+44 1457 839370",
    "sg:postcode":"OL5 0PG",
    "sg:province":"Greater Manchester",
    "sg:tags":[
        "concrete",
        "product"
    ],
    "wof:name":"Centrestone",
    "wof:placetype":"venue"
},
  "geometry": {"coordinates":[-2.048304,53.521473],"type":"Point"}
}