{
  "type": "Feature",
  "properties": {
    "iso:country":"GB",
    "sg:address":"The Workshop Penstone Road",
    "sg:city":"Bude",
    "sg:classifiers":[
        {
            "category":"Building & Trades",
            "subcategory":"Construction",
            "type":"Services"
        }
    ],
    "sg:phone":"+44 1288 321688",
    "sg:postcode":"EX23 9QT",
    "sg:province":"Cornwall",
    "sg:tags":[
        "builder"
    ],
    "wof:name":"J G Oke",
    "wof:placetype":"venue"
},
  "geometry": {"coordinates":[-4.544478,50.828362],"type":"Point"}
}