{
  "type": "Feature",
  "properties": {
    "addr:full":"Hanover House, 33 The Avenue Eastbourne East Sussex BN21 3YD",
    "addr:housenumber":"33",
    "addr:postcode":"bn21 3yd",
    "addr:street":"The Avenue",
    "iso:country":"GB",
    "sg:address":"Hanover House, 33 The Avenue",
    "sg:city":"Eastbourne",
    "sg:classifiers":[
        {
            "category":"Education",
            "subcategory":"Special Training",
            "type":"Public Place"
        }
    ],
    "sg:phone":"+44 1323 411255",
    "sg:postcode":"BN21 3YD",
    "sg:province":"East Sussex",
    "sg:tags":[
        "product",
        "centre"
    ],
    "wof:name":"Tomorrow's People Trust",
    "wof:placetype":"venue"
},
  "geometry": {"coordinates":[0.282271,50.772793],"type":"Point"}
}