{
  "type": "Feature",
  "properties": {
    "iso:country":"GB",
    "sg:address":"3 Nursery Park",
    "sg:city":"Brechin",
    "sg:classifiers":[
        {
            "category":"Taxi",
            "type":"Transportation"
        }
    ],
    "sg:phone":"+44 1356 624697",
    "sg:postcode":"DD9 7EY",
    "sg:province":"Aberdeenshire",
    "sg:tags":[
        "mini",
        "hire",
        "cab",
        "private",
        "vehicle"
    ],
    "wof:name":"G W Murray",
    "wof:placetype":"venue"
},
  "geometry": {"coordinates":[-2.649705,56.725727],"type":"Point"}
}