{
  "type": "Feature",
  "properties": {
    "addr:full":"Unit 8, Trent Trading Park Stoke On Trent Staffordshire ST1 3LY",
    "addr:housenumber":"unit 8",
    "addr:postcode":"st1 3ly",
    "addr:street":"Trent Trading Park",
    "iso:country":"GB",
    "sg:address":"Unit 8, Trent Trading Park",
    "sg:city":"Stoke On Trent",
    "sg:classifiers":[
        {
            "category":"Retail",
            "subcategory":"Repair Shop",
            "type":"Services"
        }
    ],
    "sg:phone":"+44 1782 271000",
    "sg:postcode":"ST1 3LY",
    "sg:province":"Staffordshire",
    "sg:tags":[
        "upholsterer"
    ],
    "wof:name":"K Steele Upholstery",
    "wof:placetype":"venue"
},
  "geometry": {"coordinates":[-2.175069,53.029369],"type":"Point"}
}