{
  "type": "Feature",
  "properties": {
    "addr:full":"302 Ballards Lane London Greater London N12 0EY",
    "addr:housenumber":"302",
    "addr:postcode":"n12 0ey",
    "addr:street":"Ballards Lane",
    "iso:country":"GB",
    "sg:address":"302 Ballards Lane",
    "sg:city":"London",
    "sg:classifiers":[
        {
            "category":"Food & Beverages",
            "subcategory":"Liquor & Beverages",
            "type":"Retail Goods"
        }
    ],
    "sg:phone":"+44 20 8446 4208",
    "sg:postcode":"N12 0EY",
    "sg:province":"Greater London",
    "sg:tags":[
        "beer",
        "spirit",
        "wines"
    ],
    "wof:name":"Tottenham Wines",
    "wof:placetype":"venue"
},
  "geometry": {"coordinates":[-0.178659007,51.6115036011],"type":"Point"}
}