{
  "type": "Feature",
  "properties": {
    "iso:country":"GB",
    "sg:address":"70 Caves Lane",
    "sg:city":"Bedford",
    "sg:classifiers":[
        {
            "category":"Building & Trades",
            "subcategory":"Construction",
            "type":"Services"
        }
    ],
    "sg:postcode":"MK40 3DN",
    "sg:province":"Bedfordshire",
    "sg:tags":[
        "builder"
    ],
    "wof:name":"Afzal Moudie",
    "wof:placetype":"venue"
},
  "geometry": {"coordinates":[-0.449694,52.144413],"type":"Point"}
}