{
  "type": "Feature",
  "properties": {
    "addr:full":"5 Ward Road, Rosehearty Fraserburgh Aberdeenshire AB43 7NN",
    "addr:housenumber":"5",
    "addr:postcode":"ab43 7nn",
    "addr:street":"Ward Road",
    "iso:country":"GB",
    "sg:address":"5 Ward Road, Rosehearty",
    "sg:city":"Fraserburgh",
    "sg:classifiers":[
        {
            "category":"Personal",
            "subcategory":"Beauty Salon",
            "type":"Services"
        },
        {
            "category":"Personal",
            "subcategory":"Barber",
            "type":"Services"
        }
    ],
    "sg:phone":"+44 1346 571669",
    "sg:postcode":"AB43 7NN",
    "sg:province":"Aberdeenshire",
    "sg:tags":[
        "unisex",
        "hairdresser"
    ],
    "wof:name":"Cutting Corner",
    "wof:placetype":"venue"
},
  "geometry": {"coordinates":[-2.1158890724,57.6979598999],"type":"Point"}
}