{
  "type": "Feature",
  "properties": {
    "iso:country":"GB",
    "sg:address":"47 Milton Road",
    "sg:city":"Southampton",
    "sg:classifiers":[
        {
            "category":"Home & Garden",
            "subcategory":"Hardware",
            "type":"Retail Goods"
        }
    ],
    "sg:phone":"+44 23 8033 9498",
    "sg:postcode":"SO15 2HS",
    "sg:province":"Hampshire",
    "sg:tags":[
        "retailer",
        "diy"
    ],
    "wof:name":"Gordon Poore",
    "wof:placetype":"venue"
},
  "geometry": {"coordinates":[-1.408367,50.914806],"type":"Point"}
}