{
  "type": "Feature",
  "properties": {
    "addr:full":"Brook La Altrincham Cheshire WA15 6RL",
    "addr:postcode":"wa15 6rl",
    "addr:street":"Brook La Altrincham",
    "iso:country":"GB",
    "sg:address":"Brook La",
    "sg:city":"Altrincham",
    "sg:classifiers":[
        {
            "category":"Place Of Worship",
            "type":"Public Place"
        }
    ],
    "sg:phone":"+44 161 980 4330",
    "sg:postcode":"WA15 6RL",
    "sg:province":"Cheshire",
    "wof:name":"St Andrews C of E Church",
    "wof:placetype":"venue"
},
  "geometry": {"coordinates":[-2.3376739025,53.3973312378],"type":"Point"}
}