{
  "type": "Feature",
  "properties": {
    "addr:full":"78 High Street Bridgnorth Shropshire WV16 4DS",
    "addr:housenumber":"78",
    "addr:postcode":"wv16 4ds",
    "addr:street":"High Street",
    "iso:country":"GB",
    "sg:address":"78 High Street",
    "sg:city":"Bridgnorth",
    "sg:classifiers":[
        {
            "category":"Real Estate",
            "subcategory":"Real Estate Agent",
            "type":"Services"
        }
    ],
    "sg:phone":"+44 1746 767488",
    "sg:postcode":"WV16 4DS",
    "sg:province":"Shropshire",
    "wof:name":"Philip Herdson",
    "wof:placetype":"venue"
},
  "geometry": {"coordinates":[-2.420402,52.537018],"type":"Point"}
}