{
  "type": "Feature",
  "properties": {
    "iso:country":"GB",
    "sg:address":"104 Tollington Park",
    "sg:city":"London",
    "sg:classifiers":[
        {
            "category":"Building & Trades",
            "subcategory":"Plumbing",
            "type":"Services"
        }
    ],
    "sg:phone":"+44 20 7272 2524",
    "sg:postcode":"N4 3RB",
    "sg:province":"Greater London",
    "sg:tags":[
        "heating"
    ],
    "wof:name":"A A T B F & Co Heating",
    "wof:placetype":"venue"
},
  "geometry": {"coordinates":[-0.114067,51.566319],"type":"Point"}
}