{
  "type": "Feature",
  "properties": {
    "addr:full":"119 Finnart Street Greenock Inverclyde PA16 8HT",
    "addr:housenumber":"119",
    "addr:postcode":"pa16 8ht",
    "addr:street":"Finnart Street Greenock",
    "iso:country":"GB",
    "sg:address":"119 Finnart Street",
    "sg:city":"Greenock",
    "sg:classifiers":[
        {
            "category":"Social Services",
            "type":"Services"
        },
        {
            "category":"Health Services",
            "subcategory":"Nursing And Care Facility",
            "type":"Services"
        }
    ],
    "sg:phone":"+44 1475 787777",
    "sg:postcode":"PA16 8HT",
    "sg:province":"Inverclyde",
    "sg:tags":[
        "need",
        "residential",
        "disability",
        "special"
    ],
    "wof:name":"Matilda Care Transport",
    "wof:placetype":"venue"
},
  "geometry": {"coordinates":[-4.7763128281,55.9533882141],"type":"Point"}
}