{
  "type": "Feature",
  "properties": {
    "addr:full":"Brucklay Estate Office, Shevado Peterhead Aberdeenshire AB42 4QN",
    "addr:postcode":"ab42 4qn",
    "addr:street":"Shevado",
    "iso:country":"GB",
    "sg:address":"Brucklay Estate Office, Shevado",
    "sg:city":"Peterhead",
    "sg:classifiers":[
        {
            "category":"Farming",
            "subcategory":"Farm",
            "type":"Manufacturing & Wholesale Goods"
        }
    ],
    "sg:phone":"+44 1771 613263",
    "sg:postcode":"AB42 4QN",
    "sg:province":"Aberdeenshire",
    "sg:tags":[
        "mixed",
        "crop"
    ],
    "wof:name":"Brucklay Estates",
    "wof:placetype":"venue"
},
  "geometry": {"coordinates":[-2.1563100815,57.5342292786],"type":"Point"}
}