{
  "type": "Feature",
  "properties": {
    "addr:full":"The Corn Mill, Stanstead Abbots Ware Hertfordshire SG12 8HQ",
    "addr:postcode":"sg12 8hq",
    "iso:country":"GB",
    "sg:address":"The Corn Mill, Stanstead Abbots",
    "sg:city":"Ware",
    "sg:classifiers":[
        {
            "category":"Professional",
            "subcategory":"Advertising",
            "type":"Services"
        }
    ],
    "sg:phone":"+44 1920 876543",
    "sg:postcode":"SG12 8HQ",
    "sg:province":"Hertfordshire",
    "sg:tags":[
        "agency"
    ],
    "wof:name":"Tableau Design & Marketing Ltd",
    "wof:placetype":"venue"
},
  "geometry": {"coordinates":[0.0110950004,51.787071228],"type":"Point"}
}