{
  "type": "Feature",
  "properties": {
    "addr:full":"Canon Collins House, 64 Essex Road London Greater London N1 8LR",
    "addr:housenumber":"64",
    "addr:postcode":"n1 8lr",
    "addr:street":"Essex Road",
    "iso:country":"GB",
    "sg:address":"Canon Collins House, 64 Essex Road",
    "sg:city":"London",
    "sg:classifiers":[
        {
            "category":"Communications",
            "subcategory":"Newspaper",
            "type":"Services"
        }
    ],
    "sg:phone":"+44 20 8559 4881",
    "sg:postcode":"N1 8LR",
    "sg:province":"Greater London",
    "sg:tags":[
        "magazine"
    ],
    "wof:name":"Greystone Services Ltd.",
    "wof:placetype":"venue"
},
  "geometry": {"coordinates":[-0.097439,51.539661],"type":"Point"}
}