{
  "type": "Feature",
  "properties": {
    "addr:full":"9 Bath Rd Newbury Berkshire RG14 1QN",
    "addr:housenumber":"9",
    "addr:postcode":"rg14 1qn",
    "addr:street":"Bath Rd",
    "iso:country":"GB",
    "sg:address":"9 Bath Rd",
    "sg:city":"Newbury",
    "sg:classifiers":[
        {
            "category":"Health Services",
            "subcategory":"Dentist",
            "type":"Services"
        }
    ],
    "sg:phone":"+44 1635 863131",
    "sg:postcode":"RG14 1QN",
    "sg:province":"Berkshire",
    "wof:name":"K E Alford",
    "wof:placetype":"venue"
},
  "geometry": {"coordinates":[-1.3287279606,51.4056892395],"type":"Point"}
}