{
  "type": "Feature",
  "properties": {
    "addr:full":"28 West St Leominster Herefordshire HR6 8ES",
    "addr:housenumber":"28",
    "addr:postcode":"hr6 8es",
    "addr:street":"West St",
    "iso:country":"GB",
    "sg:address":"28 West St",
    "sg:city":"Leominster",
    "sg:classifiers":[
        {
            "category":"Shopping",
            "subcategory":"Jewelry",
            "type":"Retail Goods"
        }
    ],
    "sg:phone":"+44 1568 611777",
    "sg:postcode":"HR6 8ES",
    "sg:province":"Herefordshire",
    "sg:tags":[
        "gold",
        "silversmith"
    ],
    "wof:name":"Compliments",
    "wof:placetype":"venue"
},
  "geometry": {"coordinates":[-2.740337,52.226971],"type":"Point"}
}