{
  "type": "Feature",
  "properties": {
    "addr:full":"188 Mill Road Cambridge Cambridgeshire CB1 3LP",
    "addr:housenumber":"188",
    "addr:postcode":"cb1 3lp",
    "addr:street":"Mill Road",
    "iso:country":"GB",
    "sg:address":"188 Mill Road",
    "sg:city":"Cambridge",
    "sg:classifiers":[
        {
            "category":"Shopping",
            "subcategory":"Department Store",
            "type":"Retail Goods"
        },
        {
            "category":"Shopping",
            "subcategory":"Gifts & Souvenirs",
            "type":"Retail Goods"
        }
    ],
    "sg:postcode":"CB1 3LP",
    "sg:province":"Cambridgeshire",
    "sg:tags":[
        "shop"
    ],
    "wof:name":"S WYNES",
    "wof:placetype":"venue"
},
  "geometry": {"coordinates":[0.143605,52.197746],"type":"Point"}
}