{
  "type": "Feature",
  "properties": {
    "addr:full":"Bodafon, Lon Refail Llanfairpwllgwyngyll Isle of Anglesey LL61 5YN",
    "addr:postcode":"ll61 5yn",
    "addr:street":"Lon Refail Llanfairpwllgwyngyll",
    "iso:country":"GB",
    "sg:address":"Bodafon, Lon Refail",
    "sg:city":"Llanfairpwllgwyngyll",
    "sg:classifiers":[
        {
            "category":"Building & Trades",
            "subcategory":"Construction",
            "type":"Services"
        }
    ],
    "sg:postcode":"LL61 5YN",
    "sg:province":"Isle of Anglesey",
    "sg:tags":[
        "builder"
    ],
    "wof:name":"John C Lewis",
    "wof:placetype":"venue"
},
  "geometry": {"coordinates":[-4.1979942322,53.2257194519],"type":"Point"}
}