{
  "type": "Feature",
  "properties": {
    "addr:full":"Waldon Street Hartlepool Durham TS24 7QJ",
    "addr:postcode":"ts24 7qj",
    "addr:street":"Waldon Street",
    "iso:country":"GB",
    "sg:address":"Waldon Street",
    "sg:city":"Hartlepool",
    "sg:classifiers":[
        {
            "category":"Social Services",
            "subcategory":"Retirement Home",
            "type":"Services"
        }
    ],
    "sg:phone":"+44 1429 289111",
    "sg:postcode":"TS24 7QJ",
    "sg:province":"Durham",
    "sg:tags":[
        "rest"
    ],
    "wof:name":"Stranton House",
    "wof:placetype":"venue"
},
  "geometry": {"coordinates":[-1.21428895,54.6818466187],"type":"Point"}
}