{
  "type": "Feature",
  "properties": {
    "addr:full":"99 The Square, Kinmel Bay Rhyl Conwy LL18 1HU",
    "addr:housenumber":"99",
    "addr:postcode":"ll18 1hu",
    "addr:street":"The Square",
    "iso:country":"GB",
    "sg:address":"99 The Square, Kinmel Bay",
    "sg:city":"Rhyl",
    "sg:classifiers":[
        {
            "category":"Communications",
            "subcategory":"Film & Video Production",
            "type":"Services"
        }
    ],
    "sg:phone":"+44 1745 342537",
    "sg:postcode":"LL18 1HU",
    "sg:province":"Conwy",
    "sg:tags":[
        "tv"
    ],
    "wof:name":"Kavern Video",
    "wof:placetype":"venue"
},
  "geometry": {"coordinates":[-3.499710083,53.3157501221],"type":"Point"}
}