{
  "type": "Feature",
  "properties": {
    "addr:full":"St. Patricks Place, Walton Le Dale Preston Lancashire PR5 4HN",
    "addr:postcode":"pr5 4hn",
    "addr:street":"St. Patricks Place",
    "iso:country":"GB",
    "sg:address":"St. Patricks Place, Walton Le Dale",
    "sg:city":"Preston",
    "sg:classifiers":[
        {
            "category":"Farming",
            "subcategory":"Nursery",
            "type":"Manufacturing & Wholesale Goods"
        }
    ],
    "sg:phone":"+44 1772 888066",
    "sg:postcode":"PR5 4HN",
    "sg:province":"Lancashire",
    "sg:tags":[
        "creche"
    ],
    "wof:name":"Clever Clogs Childcare Centre",
    "wof:placetype":"venue"
},
  "geometry": {"coordinates":[-2.6652491093,53.7461051941],"type":"Point"}
}