{
  "type": "Feature",
  "properties": {
    "iso:country":"GB",
    "sg:address":"Milton Road",
    "sg:city":"Cambridge",
    "sg:classifiers":[
        {
            "category":"Military Area",
            "subcategory":"Air Force Base",
            "type":"Public Place"
        }
    ],
    "sg:postcode":"CB4 1UY",
    "sg:province":"Cambridgeshire",
    "sg:tags":[
        "taxi",
        "hire",
        "private"
    ],
    "wof:name":"Cabco Cambridge Radio Taxis",
    "wof:placetype":"venue"
},
  "geometry": {"coordinates":[0.14752,52.228893],"type":"Point"}
}