{
  "type": "Feature",
  "properties": {
    "iso:country":"GB",
    "sg:address":"5 Little Stonegate",
    "sg:city":"York",
    "sg:classifiers":[
        {
            "category":"Food & Beverages",
            "subcategory":"Specialty",
            "type":"Retail Goods"
        }
    ],
    "sg:phone":"+44 1904 676076",
    "sg:postcode":"YO1 8AX",
    "sg:province":"North Yorkshire",
    "sg:tags":[
        "vegetarian"
    ],
    "wof:name":"The Rubicon",
    "wof:placetype":"venue"
},
  "geometry": {"coordinates":[-1.083063,53.960281],"type":"Point"}
}