{
  "type": "Feature",
  "properties": {
    "addr:full":"Research Ho Business Centre, Fraser Rd Greenford Greater London UB6 7AQ",
    "addr:postcode":"ub6 7aq",
    "addr:street":"Fraser Rd",
    "iso:country":"GB",
    "sg:address":"Research Ho Business Centre, Fraser Rd",
    "sg:city":"Greenford",
    "sg:classifiers":[
        {
            "category":"Professional",
            "subcategory":"Computer Services",
            "type":"Services"
        }
    ],
    "sg:phone":"+44 20 8537 3237",
    "sg:postcode":"UB6 7AQ",
    "sg:province":"Greater London",
    "sg:tags":[
        "system",
        "software"
    ],
    "wof:name":"K J Computer Systems Ltd",
    "wof:placetype":"venue"
},
  "geometry": {"coordinates":[-0.31465,51.53931],"type":"Point"}
}