{
  "type": "Feature",
  "properties": {
    "addr:full":"Borough Business Centre, Neild Street Oldham Lancashire OL8 1QG",
    "addr:postcode":"ol8 1qg",
    "addr:street":"Neild Street",
    "iso:country":"GB",
    "sg:address":"Borough Business Centre, Neild Street",
    "sg:city":"Oldham",
    "sg:classifiers":[
        {
            "category":"Professional",
            "subcategory":"Computer Services",
            "type":"Services"
        }
    ],
    "sg:phone":"+44 870 750 4725",
    "sg:postcode":"OL8 1QG",
    "sg:province":"Lancashire",
    "sg:tags":[
        "system",
        "software"
    ],
    "wof:name":"e-qua via Ltd",
    "wof:placetype":"venue"
},
  "geometry": {"coordinates":[-2.1160540581,53.5366363525],"type":"Point"}
}