{
  "type": "Feature",
  "properties": {
    "addr:full":"162a Worplesdon Rd Guildford Surrey GU2 6RX",
    "addr:housenumber":"162a",
    "addr:postcode":"gu2 6rx",
    "addr:street":"Worplesdon Rd",
    "iso:country":"GB",
    "sg:address":"162a Worplesdon Rd",
    "sg:city":"Guildford",
    "sg:classifiers":[
        {
            "category":"Professional",
            "subcategory":"Computer Services",
            "type":"Services"
        }
    ],
    "sg:phone":"+44 1483 535593",
    "sg:postcode":"GU2 6RX",
    "sg:province":"Surrey",
    "sg:tags":[
        "consultant"
    ],
    "wof:name":"Steel Breeze Systems Ltd",
    "wof:placetype":"venue"
},
  "geometry": {"coordinates":[-0.5930609703,51.2544784546],"type":"Point"}
}