{
  "type": "Feature",
  "properties": {
    "iso:country":"GB",
    "sg:address":"Vaughan Road",
    "sg:city":"Exeter",
    "sg:classifiers":[
        {
            "category":"Social Services",
            "type":"Services"
        }
    ],
    "sg:phone":"+44 1392 467584",
    "sg:postcode":"EX1 3JN",
    "sg:province":"Devon",
    "wof:name":"Whipton Barton Ho",
    "wof:placetype":"venue"
},
  "geometry": {"coordinates":[-3.490587,50.731449],"type":"Point"}
}