{
  "type": "Feature",
  "properties": {
    "iso:country":"GB",
    "sg:address":"334 York Rd",
    "sg:city":"Leeds",
    "sg:classifiers":[
        {
            "category":"Health Services",
            "subcategory":"Clinic",
            "type":"Services"
        }
    ],
    "sg:phone":"+44 113 235 0000",
    "sg:postcode":"LS9 9DN",
    "sg:province":"West Yorkshire",
    "sg:tags":[
        "private"
    ],
    "wof:name":"Allen Carr's Easyway To Stop Smoking",
    "wof:placetype":"venue"
},
  "geometry": {"coordinates":[-1.504197,53.800087],"type":"Point"}
}