{
  "type": "Feature",
  "properties": {
    "addr:full":"Canewdon Hall Farm, Canewdon Rochford Essex SS4 3QW",
    "addr:housenumber":"canewdon",
    "addr:postcode":"ss4 3qw",
    "addr:street":"Hall",
    "iso:country":"GB",
    "sg:address":"Canewdon Hall Farm, Canewdon",
    "sg:city":"Rochford",
    "sg:classifiers":[
        {
            "category":"Farming",
            "subcategory":"Livestock Farm",
            "type":"Manufacturing & Wholesale Goods"
        }
    ],
    "sg:postcode":"SS4 3QW",
    "sg:province":"Essex",
    "sg:tags":[
        "others"
    ],
    "wof:name":"J W Robinson",
    "wof:placetype":"venue"
},
  "geometry": {"coordinates":[0.7424839735,51.6176109314],"type":"Point"}
}