{
  "type": "Feature",
  "properties": {
    "addr:full":"51-52 Broad Street Mall Reading Berkshire RG1 7QE",
    "addr:housenumber":"51-52",
    "addr:postcode":"rg1 7qe",
    "addr:street":"Broad Street Mall",
    "iso:country":"GB",
    "sg:address":"51-52 Broad Street Mall",
    "sg:city":"Reading",
    "sg:classifiers":[
        {
            "category":"Shopping",
            "subcategory":"Discount & Variety Stores",
            "type":"Retail Goods"
        }
    ],
    "sg:phone":"+44 118 958 6899",
    "sg:postcode":"RG1 7QE",
    "sg:province":"Berkshire",
    "sg:tags":[
        "shop",
        "model"
    ],
    "wof:name":"Beatties of London",
    "wof:placetype":"venue"
},
  "geometry": {"coordinates":[-0.963009,51.453522],"type":"Point"}
}