{
  "type": "Feature",
  "properties": {
    "addr:full":"Ty-nant Corwen Conwy LL21 0PR",
    "addr:postcode":"ll21 0pr",
    "addr:street":"Corwen",
    "iso:country":"GB",
    "sg:address":"Ty-nant",
    "sg:city":"Corwen",
    "sg:classifiers":[
        {
            "category":"Retail",
            "subcategory":"Auto Repair",
            "type":"Services"
        }
    ],
    "sg:postcode":"LL21 0PR",
    "sg:province":"Conwy",
    "sg:tags":[
        "modification",
        "garage"
    ],
    "wof:name":"Ty-Nant Service Station",
    "wof:placetype":"venue"
},
  "geometry": {"coordinates":[-3.3736679554,52.9806480408],"type":"Point"}
}