{
  "type": "Feature",
  "properties": {
    "iso:country":"GB",
    "sg:address":"129 Tarring Road",
    "sg:city":"Worthing",
    "sg:classifiers":[
        {
            "category":"Real Estate",
            "subcategory":"Surveying",
            "type":"Services"
        }
    ],
    "sg:phone":"+44 1903 217313",
    "sg:postcode":"BN11 4HE",
    "sg:province":"West Sussex",
    "sg:tags":[
        "building",
        "surveyor"
    ],
    "wof:name":"K G Designs",
    "wof:placetype":"venue"
},
  "geometry": {"coordinates":[-0.3849849999,50.8179779053],"type":"Point"}
}