{
  "type": "Feature",
  "properties": {
    "iso:country":"GB",
    "sg:address":"442c Cowbridge Road East",
    "sg:city":"Cardiff",
    "sg:classifiers":[
        {
            "category":"Restaurant",
            "type":"Food & Drink"
        }
    ],
    "sg:phone":"+44 29 2023 3506",
    "sg:postcode":"CF5 1JN",
    "sg:province":"Cardiff",
    "wof:name":"Sergios Gourmet Restaurant",
    "wof:placetype":"venue"
},
  "geometry": {"coordinates":[-3.2173080444,51.4828681946],"type":"Point"}
}