{
  "type": "Feature",
  "properties": {
    "iso:country":"GB",
    "sg:address":"8 Chanctonbury Drive",
    "sg:city":"Hastings",
    "sg:classifiers":[
        {
            "category":"Organizations",
            "subcategory":"Non-profit Organization",
            "type":"Services"
        }
    ],
    "sg:postcode":"TN34 2QN",
    "sg:province":"East Sussex",
    "sg:tags":[
        "organisation",
        "voluntary",
        "charity"
    ],
    "wof:name":"British Limbless Ex-Servicemens Association",
    "wof:placetype":"venue"
},
  "geometry": {"coordinates":[0.5731250048,50.8816223145],"type":"Point"}
}