{
  "type": "Feature",
  "properties": {
    "iso:country":"GB",
    "sg:address":"Upper Farm, Binweston",
    "sg:city":"Shrewsbury",
    "sg:classifiers":[
        {
            "category":"Farming",
            "subcategory":"Livestock Farm",
            "type":"Manufacturing & Wholesale Goods"
        }
    ],
    "sg:phone":"+44 1743 891383",
    "sg:postcode":"SY5 9JG",
    "sg:province":"Shropshire",
    "sg:tags":[
        "others"
    ],
    "wof:name":"J R J Mills",
    "wof:placetype":"venue"
},
  "geometry": {"coordinates":[-3.03405,52.630878],"type":"Point"}
}