{
  "type": "Feature",
  "properties": {
    "addr:full":"4 Harlequin Av Brentford Greater London TW8 9EW",
    "addr:housenumber":"4",
    "addr:postcode":"tw8 9ew",
    "addr:street":"Harlequin Av Brentford",
    "iso:country":"GB",
    "sg:address":"4 Harlequin Av",
    "sg:city":"Brentford",
    "sg:classifiers":[
        {
            "category":"Food & Beverages",
            "subcategory":"Liquor & Beverages",
            "type":"Retail Goods"
        }
    ],
    "sg:phone":"+44 20 8758 4500",
    "sg:postcode":"TW8 9EW",
    "sg:province":"Greater London",
    "sg:tags":[
        "beer",
        "spirit",
        "wines"
    ],
    "wof:name":"Caxton Tower Wines Ltd",
    "wof:placetype":"venue"
},
  "geometry": {"coordinates":[-0.3264659941,51.4860992432],"type":"Point"}
}