{
  "type": "Feature",
  "properties": {
    "addr:full":"P O Box 10552 London Greater London N1 4DF",
    "addr:housenumber":"box 10552",
    "addr:postcode":"n1 4df",
    "iso:country":"GB",
    "sg:address":"P O Box 10552",
    "sg:city":"London",
    "sg:classifiers":[
        {
            "category":"Organizations",
            "subcategory":"Non-profit Organization",
            "type":"Services"
        }
    ],
    "sg:phone":"+44 20 7511 5777",
    "sg:postcode":"N1 4DF",
    "sg:province":"Greater London",
    "sg:tags":[
        "organisation",
        "voluntary",
        "charity"
    ],
    "wof:name":"Basic Trust",
    "wof:placetype":"venue"
},
  "geometry": {"coordinates":[-0.08194,51.545609],"type":"Point"}
}