{
  "type": "Feature",
  "properties": {
    "addr:full":"72 St James's Street Nottingham Nottinghamshire NG1 6FJ",
    "addr:housenumber":"72",
    "addr:postcode":"ng1 6fj",
    "addr:street":"St James'S Street",
    "iso:country":"GB",
    "sg:address":"72 St James's Street",
    "sg:city":"Nottingham",
    "sg:classifiers":[
        {
            "category":"Professional",
            "subcategory":"Lawyer & Legal Services",
            "type":"Services"
        }
    ],
    "sg:phone":"+44 115 924 0631",
    "sg:postcode":"NG1 6FJ",
    "sg:province":"Nottinghamshire",
    "sg:tags":[
        "solicitor"
    ],
    "wof:name":"Edwards Geldard Solicitors",
    "wof:placetype":"venue"
},
  "geometry": {"coordinates":[-1.1535400152,52.9524688721],"type":"Point"}
}