{
  "type": "Feature",
  "properties": {
    "iso:country":"GB",
    "sg:address":"384 Kenilworth Road",
    "sg:city":"Coventry",
    "sg:classifiers":[
        {
            "category":"Health Services",
            "subcategory":"Optometrist",
            "type":"Services"
        }
    ],
    "sg:phone":"+44 1676 532180",
    "sg:postcode":"CV7 7ER",
    "sg:province":"Warwickshire",
    "sg:tags":[
        "optician"
    ],
    "wof:name":"Maginnis Opticians (Optometrists) Ltd.",
    "wof:placetype":"venue"
},
  "geometry": {"coordinates":[-1.650538,52.391941],"type":"Point"}
}