{
  "type": "Feature",
  "properties": {
    "addr:full":"United Kingdom House, 180 Oxford Street London Greater London W1D 1EL",
    "addr:housenumber":"180",
    "addr:postcode":"w1d 1el",
    "addr:street":"Oxford Street",
    "iso:country":"GB",
    "sg:address":"United Kingdom House, 180 Oxford Street",
    "sg:city":"London",
    "sg:classifiers":[
        {
            "category":"Airline",
            "type":"Transportation"
        }
    ],
    "sg:phone":"+44 20 7957 4200",
    "sg:postcode":"W1D 1EL",
    "sg:province":"Greater London",
    "wof:name":"El Al Israel Airlines Ltd.",
    "wof:placetype":"venue"
},
  "geometry": {"coordinates":[-0.1392150074,51.5156745911],"type":"Point"}
}