{
  "type": "Feature",
  "properties": {
    "addr:full":"36 Wates Way Mitcham Greater London CR4 4HR",
    "addr:housenumber":"36",
    "addr:postcode":"cr4 4hr",
    "addr:street":"Wates Way",
    "iso:country":"GB",
    "sg:address":"36 Wates Way",
    "sg:city":"Mitcham",
    "sg:classifiers":[
        {
            "category":"Professional",
            "subcategory":"Engineering",
            "type":"Services"
        }
    ],
    "sg:phone":"+44 20 8640 0553",
    "sg:postcode":"CR4 4HR",
    "sg:province":"Greater London",
    "wof:name":"Tingey & Co. (Engineers) Ltd.",
    "wof:placetype":"venue"
},
  "geometry": {"coordinates":[-0.1652310044,51.388835907],"type":"Point"}
}