{
  "type": "Feature",
  "properties": {
    "addr:full":"127 Belmont Rd Erith Kent DA8 1LF",
    "addr:housenumber":"127",
    "addr:postcode":"da8 1lf",
    "addr:street":"Belmont Rd",
    "iso:country":"GB",
    "sg:address":"127 Belmont Rd",
    "sg:city":"Erith",
    "sg:classifiers":[
        {
            "category":"Building & Trades",
            "subcategory":"Construction",
            "type":"Services"
        }
    ],
    "sg:phone":"+44 1322 405466",
    "sg:postcode":"DA8 1LF",
    "sg:province":"Kent",
    "sg:tags":[
        "flooring"
    ],
    "wof:name":"The Floor Co",
    "wof:placetype":"venue"
},
  "geometry": {"coordinates":[0.152177006,51.4713592529],"type":"Point"}
}