{
  "type": "Feature",
  "properties": {
    "addr:full":"Suite 102 London Greater London EC1N 8NX",
    "addr:housenumber":"suite 102",
    "addr:postcode":"ec1n 8nx",
    "iso:country":"GB",
    "sg:address":"Suite 102",
    "sg:city":"London",
    "sg:classifiers":[
        {
            "category":"Shopping",
            "subcategory":"Jewelry",
            "type":"Retail Goods"
        },
        {
            "category":"Manufacturing",
            "subcategory":"Jewelry",
            "type":"Manufacturing & Wholesale Goods"
        }
    ],
    "sg:phone":"+44 20 8907 2032",
    "sg:postcode":"EC1N 8NX",
    "sg:province":"Greater London",
    "sg:tags":[
        "repair",
        "jewellery",
        "gold",
        "silversmith"
    ],
    "wof:name":"Setwell Diamonds",
    "wof:placetype":"venue"
},
  "geometry": {"coordinates":[0.019903,51.528072],"type":"Point"}
}