{
  "type": "Feature",
  "properties": {
    "addr:full":"Winsbury Way Bristol Gloucestershire BS32 9BF",
    "addr:postcode":"bs32 9bf",
    "addr:street":"Winsbury Way",
    "iso:country":"GB",
    "sg:address":"Winsbury Way",
    "sg:city":"Bristol",
    "sg:classifiers":[
        {
            "category":"Professional",
            "type":"Services"
        }
    ],
    "sg:postcode":"BS32 9BF",
    "sg:province":"Gloucestershire",
    "sg:tags":[
        "exhibition"
    ],
    "wof:name":"Tates Marquees",
    "wof:placetype":"venue"
},
  "geometry": {"coordinates":[-2.556365,51.536373],"type":"Point"}
}