{
  "type": "Feature",
  "properties": {
    "iso:country":"GB",
    "sg:address":"Saxham Street, Stowupland",
    "sg:city":"Stowmarket",
    "sg:classifiers":[
        {
            "category":"Autos & Motor Vehicles",
            "subcategory":"Auto Supplies",
            "type":"Retail Goods"
        }
    ],
    "sg:postcode":"IP14 5DD",
    "sg:province":"Suffolk",
    "sg:tags":[
        "windscreen"
    ],
    "wof:name":"Suffolk Windscreens",
    "wof:placetype":"venue"
},
  "geometry": {"coordinates":[0.996769,52.188625],"type":"Point"}
}