{
  "type": "Feature",
  "properties": {
    "iso:country":"GB",
    "sg:address":"Trelimsy Farm",
    "sg:city":"Ferryside",
    "sg:classifiers":[
        {
            "category":"Farming",
            "subcategory":"Dairy Farm",
            "type":"Manufacturing & Wholesale Goods"
        },
        {
            "category":"Farming",
            "subcategory":"Livestock Farm",
            "type":"Manufacturing & Wholesale Goods"
        }
    ],
    "sg:phone":"+44 1267 267427",
    "sg:postcode":"SA17 5TP",
    "sg:province":"Carmarthenshire",
    "sg:tags":[
        "others"
    ],
    "wof:name":"E A & H M Anderson",
    "wof:placetype":"venue"
},
  "geometry": {"coordinates":[-4.36857,51.767345],"type":"Point"}
}