{
  "type": "Feature",
  "properties": {
    "iso:country":"GB",
    "sg:address":"337a Handsworth Rd",
    "sg:city":"Sheffield",
    "sg:classifiers":[
        {
            "category":"Personal",
            "subcategory":"Beauty Salon",
            "type":"Services"
        }
    ],
    "sg:phone":"+44 114 269 2701",
    "sg:postcode":"S13 9BP",
    "sg:province":"South Yorkshire",
    "sg:tags":[
        "unisex",
        "hairdresser"
    ],
    "wof:name":"Re-style",
    "wof:placetype":"venue"
},
  "geometry": {"coordinates":[-1.388043,53.371994],"type":"Point"}
}