{
  "type": "Feature",
  "properties": {
    "iso:country":"GB",
    "sg:address":"40 Green Leys, Badsey",
    "sg:city":"Evesham",
    "sg:classifiers":[
        {
            "category":"Military Area",
            "subcategory":"Air Force Base",
            "type":"Public Place"
        }
    ],
    "sg:phone":"+44 1386 833185",
    "sg:postcode":"WR11 7XE",
    "sg:province":"Gloucestershire",
    "sg:tags":[
        "taxi",
        "hire",
        "private"
    ],
    "wof:name":"M D Taxis",
    "wof:placetype":"venue"
},
  "geometry": {"coordinates":[-1.8392089605,52.0931015015],"type":"Point"}
}