{
  "type": "Feature",
  "properties": {
    "addr:full":"4 Clifford Street York North Yorkshire YO1 9RD",
    "addr:housenumber":"4",
    "addr:postcode":"yo1 9rd",
    "addr:street":"Clifford Street",
    "iso:country":"GB",
    "sg:address":"4 Clifford Street",
    "sg:city":"York",
    "sg:classifiers":[
        {
            "category":"Professional",
            "subcategory":"Art Services",
            "type":"Services"
        }
    ],
    "sg:phone":"+44 1904 610611",
    "sg:postcode":"YO1 9RD",
    "sg:province":"North Yorkshire",
    "sg:tags":[
        "consultant",
        "design"
    ],
    "wof:name":"Headline Communications",
    "wof:placetype":"venue"
},
  "geometry": {"coordinates":[-1.0819330215,53.9573669434],"type":"Point"}
}