{
  "type": "Feature",
  "properties": {
    "addr:full":"Home& Colonial, 134 High Street Berkhamsted Bedfordshire HP4 3AT",
    "addr:housenumber":"134",
    "addr:postcode":"hp4 3at",
    "addr:street":"High Street",
    "iso:country":"GB",
    "sg:address":"Home& Colonial, 134 High Street",
    "sg:city":"Berkhamsted",
    "sg:classifiers":[
        {
            "category":"Shopping",
            "subcategory":"Antiques",
            "type":"Retail Goods"
        }
    ],
    "sg:phone":"+44 1442 877007",
    "sg:postcode":"HP4 3AT",
    "sg:province":"Bedfordshire",
    "wof:name":"Home & Colonial Antique Centre",
    "wof:placetype":"venue"
},
  "geometry": {"coordinates":[-0.5627220273,51.7598266602],"type":"Point"}
}