{
  "type": "Feature",
  "properties": {
    "addr:full":"King Arthur Court, Cheshunt Waltham Cross Essex EN8 8XN",
    "addr:postcode":"en8 8xn",
    "addr:street":"King Arthur Court;Cross",
    "iso:country":"GB",
    "sg:address":"King Arthur Court, Cheshunt",
    "sg:city":"Waltham Cross",
    "sg:classifiers":[
        {
            "category":"Health Services",
            "subcategory":"Hospital",
            "type":"Services"
        }
    ],
    "sg:phone":"+44 1992 622157",
    "sg:postcode":"EN8 8XN",
    "sg:province":"Essex",
    "wof:name":"Cheshunt Community Hospital",
    "wof:placetype":"venue"
},
  "geometry": {"coordinates":[-0.0304070003,51.6998443604],"type":"Point"}
}