{
  "type": "Feature",
  "properties": {
    "iso:country":"GB",
    "sg:address":"4 Market Way",
    "sg:city":"Northwich",
    "sg:classifiers":[
        {
            "category":"Shopping",
            "subcategory":"News",
            "type":"Retail Goods"
        }
    ],
    "sg:postcode":"CW9 5BA",
    "sg:province":"Cheshire",
    "sg:tags":[
        "newsagent"
    ],
    "wof:name":"Fred & Sandra Coulson",
    "wof:placetype":"venue"
},
  "geometry": {"coordinates":[-2.514324,53.261559],"type":"Point"}
}