{
  "type": "Feature",
  "properties": {
    "addr:full":"20 Elm Gro Southsea Hampshire PO5 1JG",
    "addr:housenumber":"20",
    "addr:postcode":"po5 1jg",
    "addr:street":"Elm Gro Southsea",
    "iso:country":"GB",
    "sg:address":"20 Elm Gro",
    "sg:city":"Southsea",
    "sg:classifiers":[
        {
            "category":"Shopping",
            "subcategory":"Used Merchandise",
            "type":"Retail Goods"
        }
    ],
    "sg:postcode":"PO5 1JG",
    "sg:province":"Hampshire",
    "sg:tags":[
        "shop",
        "second-hand"
    ],
    "wof:name":"William Bryant",
    "wof:placetype":"venue"
},
  "geometry": {"coordinates":[-1.0894019604,50.7902679443],"type":"Point"}
}