{
  "type": "Feature",
  "properties": {
    "iso:country":"GB",
    "sg:address":"202 Shopping Hall, Market Place",
    "sg:city":"Romford",
    "sg:classifiers":[
        {
            "category":"Personal",
            "subcategory":"Beauty Salon",
            "type":"Services"
        }
    ],
    "sg:phone":"+44 1708 724562",
    "sg:postcode":"RM1 3AT",
    "sg:province":"Essex",
    "sg:tags":[
        "unisex",
        "hairdresser"
    ],
    "wof:name":"Ziggi's",
    "wof:placetype":"venue"
},
  "geometry": {"coordinates":[0.1863150001,51.5813903809],"type":"Point"}
}