{
  "type": "Feature",
  "properties": {
    "addr:full":"441 Springfield Rd Chelmsford Essex CM2 6AP",
    "addr:housenumber":"441",
    "addr:postcode":"cm2 6ap",
    "addr:street":"Springfield Rd",
    "iso:country":"GB",
    "sg:address":"441 Springfield Rd",
    "sg:city":"Chelmsford",
    "sg:classifiers":[
        {
            "category":"Health Services",
            "subcategory":"Health Practitioner",
            "type":"Services"
        }
    ],
    "sg:phone":"+44 1245 357706",
    "sg:postcode":"CM2 6AP",
    "sg:province":"Essex",
    "sg:tags":[
        "technique",
        "alexander"
    ],
    "wof:name":"Alan Lambert M.S.T.A.T",
    "wof:placetype":"venue"
},
  "geometry": {"coordinates":[0.48806,51.73909],"type":"Point"}
}