{
  "type": "Feature",
  "properties": {
    "addr:full":"91 Hollett Road, Treboeth Swansea Swansea SA5 9EY",
    "addr:housenumber":"91",
    "addr:postcode":"sa5 9ey",
    "addr:street":"Hollett Road Treboeth",
    "iso:country":"GB",
    "sg:address":"91 Hollett Road, Treboeth",
    "sg:city":"Swansea",
    "sg:classifiers":[
        {
            "category":"Building & Trades",
            "subcategory":"Plumbing",
            "type":"Services"
        }
    ],
    "sg:phone":"+44 1792 799133",
    "sg:postcode":"SA5 9EY",
    "sg:province":"Swansea",
    "sg:tags":[
        "drain",
        "clearance",
        "sewer"
    ],
    "wof:name":"Mark Tyzack Water Jetting",
    "wof:placetype":"venue"
},
  "geometry": {"coordinates":[-3.950678,51.646507],"type":"Point"}
}