{
  "type": "Feature",
  "properties": {
    "iso:country":"GB",
    "sg:address":"29 Forge Lane, Norristhorpe",
    "sg:city":"Liversedge",
    "sg:classifiers":[
        {
            "category":"Building & Trades",
            "subcategory":"Construction",
            "type":"Services"
        }
    ],
    "sg:phone":"+44 1924 403005",
    "sg:postcode":"WF15 7AU",
    "sg:province":"West Yorkshire",
    "sg:tags":[
        "builder",
        "contractor"
    ],
    "wof:name":"Mckelvey Construction Ltd",
    "wof:placetype":"venue"
},
  "geometry": {"coordinates":[-1.6842670441,53.702381134],"type":"Point"}
}