{
  "type": "Feature",
  "properties": {
    "addr:full":"20 Mapperley Clo Coventry Warwickshire CV2 2SE",
    "addr:housenumber":"20",
    "addr:postcode":"cv2 2se",
    "addr:street":"Mapperley Clo",
    "iso:country":"GB",
    "sg:address":"20 Mapperley Clo",
    "sg:city":"Coventry",
    "sg:classifiers":[
        {
            "category":"Professional",
            "type":"Services"
        }
    ],
    "sg:phone":"+44 24 7661 6700",
    "sg:postcode":"CV2 2SE",
    "sg:province":"Warwickshire",
    "sg:tags":[
        "caterer"
    ],
    "wof:name":"Blue Rose",
    "wof:placetype":"venue"
},
  "geometry": {"coordinates":[-1.440605,52.430561],"type":"Point"}
}