{
  "type": "Feature",
  "properties": {
    "addr:full":"Woodside, Ridgeway (the) Lightwater Surrey GU18 5XS",
    "addr:postcode":"gu18 5xs",
    "addr:street":"Ridgeway",
    "iso:country":"GB",
    "sg:address":"Woodside, Ridgeway (the)",
    "sg:city":"Lightwater",
    "sg:classifiers":[
        {
            "category":"Professional",
            "subcategory":"Management & Consulting",
            "type":"Services"
        }
    ],
    "sg:postcode":"GU18 5XS",
    "sg:province":"Surrey",
    "sg:tags":[
        "consultant",
        "business"
    ],
    "wof:name":"M B Partnership",
    "wof:placetype":"venue"
},
  "geometry": {"coordinates":[-0.6643589735,51.3508338928],"type":"Point"}
}