{
  "type": "Feature",
  "properties": {
    "addr:full":"17 Whessoe Rd Darlington Durham DL3 0QP",
    "addr:housenumber":"17",
    "addr:postcode":"dl3 0qp",
    "addr:street":"Whessoe Rd",
    "iso:country":"GB",
    "sg:address":"17 Whessoe Rd",
    "sg:city":"Darlington",
    "sg:classifiers":[
        {
            "category":"Personal",
            "subcategory":"Tanning Parlor",
            "type":"Services"
        }
    ],
    "sg:phone":"+44 1325 369859",
    "sg:postcode":"DL3 0QP",
    "sg:province":"Durham",
    "sg:tags":[
        "sunbeds"
    ],
    "wof:name":"Deep Tan",
    "wof:placetype":"venue"
},
  "geometry": {"coordinates":[-1.5549659729,54.5374298096],"type":"Point"}
}