{
  "type": "Feature",
  "properties": {
    "iso:country":"GB",
    "sg:address":"2 Carlton Terrace",
    "sg:city":"Brighton",
    "sg:classifiers":[
        {
            "category":"Real Estate",
            "subcategory":"Architect",
            "type":"Services"
        }
    ],
    "sg:phone":"+44 1273 439126",
    "sg:postcode":"BN41 1XF",
    "sg:province":"East Sussex",
    "sg:tags":[
        "technologist",
        "architectural"
    ],
    "wof:name":"Building Technical Services",
    "wof:placetype":"venue"
},
  "geometry": {"coordinates":[-0.205877,50.835899],"type":"Point"}
}