{
  "type": "Feature",
  "properties": {
    "addr:full":"P O Box 12, Rillington Malton North Yorkshire YO17 8YX",
    "addr:housenumber":"box 12",
    "addr:postcode":"yo17 8yx",
    "addr:street":"P O;Rillington",
    "iso:country":"GB",
    "sg:address":"P O Box 12, Rillington",
    "sg:city":"Malton",
    "sg:classifiers":[
        {
            "category":"Wholesale",
            "subcategory":"Sporting Goods",
            "type":"Manufacturing & Wholesale Goods"
        }
    ],
    "sg:postcode":"YO17 8YX",
    "sg:province":"North Yorkshire",
    "sg:tags":[
        "mnfr",
        "sport",
        "equipment"
    ],
    "wof:name":"Neuff",
    "wof:placetype":"venue"
},
  "geometry": {"coordinates":[-0.6916490197,54.1594085693],"type":"Point"}
}