{
  "type": "Feature",
  "properties": {
    "addr:full":"19 Blackheath, Mersay Road Colchester Essex CO2 0AE",
    "addr:housenumber":"19",
    "addr:postcode":"co2 0ae",
    "addr:street":"Blackheath Mersay Road Colchester",
    "iso:country":"GB",
    "sg:address":"19 Blackheath, Mersay Road",
    "sg:city":"Colchester",
    "sg:classifiers":[
        {
            "category":"Bars & Pubs",
            "type":"Food & Drink"
        },
        {
            "category":"Retail",
            "subcategory":"Auto Repair",
            "type":"Services"
        }
    ],
    "sg:phone":"+44 1206 570044",
    "sg:postcode":"CO2 0AE",
    "sg:province":"Essex",
    "sg:tags":[
        "pubs",
        "garage",
        "inn",
        "modification"
    ],
    "wof:name":"Cherrytree Garage (Colchester) Ltd.",
    "wof:placetype":"venue"
},
  "geometry": {"coordinates":[0.90802598,51.8601837158],"type":"Point"}
}