{
  "type": "Feature",
  "properties": {
    "addr:full":"The Green, Reeth Richmond Durham DL11 6SU",
    "addr:postcode":"dl11 6su",
    "addr:street":"Green",
    "iso:country":"GB",
    "sg:address":"The Green, Reeth",
    "sg:city":"Richmond",
    "sg:classifiers":[
        {
            "category":"Manufacturing",
            "subcategory":"Building Materials",
            "type":"Manufacturing & Wholesale Goods"
        }
    ],
    "sg:phone":"+44 1748 884188",
    "sg:postcode":"DL11 6SU",
    "sg:province":"Durham",
    "sg:tags":[
        "tile",
        "mnfrs"
    ],
    "wof:name":"Garden House Pottery",
    "wof:placetype":"venue"
},
  "geometry": {"coordinates":[-1.9425139427,54.3891906738],"type":"Point"}
}