{
  "type": "Feature",
  "properties": {
    "addr:full":"38 New Church Road London Greater London SE5 7JJ",
    "addr:housenumber":"38",
    "addr:postcode":"se5 7jj",
    "addr:street":"New Church Road",
    "iso:country":"GB",
    "sg:address":"38 New Church Road",
    "sg:city":"London",
    "sg:classifiers":[
        {
            "category":"Shopping",
            "subcategory":"News",
            "type":"Retail Goods"
        }
    ],
    "sg:phone":"+44 20 7703 8097",
    "sg:postcode":"SE5 7JJ",
    "sg:province":"Greater London",
    "sg:tags":[
        "newsagent"
    ],
    "wof:name":"New Church Newsagents",
    "wof:placetype":"venue"
},
  "geometry": {"coordinates":[-0.091844,51.479591],"type":"Point"}
}