{
  "type": "Feature",
  "properties": {
    "addr:full":"7 Bennetts Hill Birmingham West Midlands B2 5ST",
    "addr:housenumber":"7;b2",
    "addr:postcode":"5st",
    "addr:street":"Bennetts Hill",
    "iso:country":"GB",
    "sg:address":"7 Bennetts Hill",
    "sg:city":"Birmingham",
    "sg:classifiers":[
        {
            "category":"Banks & Credit Unions",
            "subcategory":"Financial Services",
            "type":"Services"
        }
    ],
    "sg:phone":"+44 121 236 7136",
    "sg:postcode":"B2 5ST",
    "sg:province":"West Midlands",
    "sg:tags":[
        "building",
        "society"
    ],
    "wof:name":"Britannia Building Society",
    "wof:placetype":"venue"
},
  "geometry": {"coordinates":[-1.9007589817,52.4803695679],"type":"Point"}
}