{
  "type": "Feature",
  "properties": {
    "addr:full":"5-6 The Arches Bath Somerset BA2 9ES",
    "addr:housenumber":"5-6;arches",
    "addr:postcode":"ba2 9es",
    "addr:street":"The",
    "iso:country":"GB",
    "sg:address":"5-6 The Arches",
    "sg:city":"Bath",
    "sg:classifiers":[
        {
            "category":"Home & Garden",
            "subcategory":"Building Materials",
            "type":"Retail Goods"
        }
    ],
    "sg:phone":"+44 1225 339050",
    "sg:postcode":"BA2 9ES",
    "sg:province":"Somerset",
    "sg:tags":[
        "brick"
    ],
    "wof:name":"Moxhams Fireplaces",
    "wof:placetype":"venue"
},
  "geometry": {"coordinates":[-2.4380888939,51.3617706299],"type":"Point"}
}