{
  "type": "Feature",
  "properties": {
    "addr:full":"32-34 Tudor Street Cardiff Cardiff CF11 6AH",
    "addr:housenumber":"32-34",
    "addr:postcode":"cf11 6ah",
    "addr:street":"Tudor Street",
    "iso:country":"GB",
    "sg:address":"32-34 Tudor Street",
    "sg:city":"Cardiff",
    "sg:classifiers":[
        {
            "category":"Shopping",
            "subcategory":"Department Store",
            "type":"Retail Goods"
        }
    ],
    "sg:phone":"+44 29 2037 7599",
    "sg:postcode":"CF11 6AH",
    "sg:province":"Cardiff",
    "wof:name":"China Supermarket",
    "wof:placetype":"venue"
},
  "geometry": {"coordinates":[-3.1856040955,51.4766159058],"type":"Point"}
}