{
  "type": "Feature",
  "properties": {
    "addr:full":"16 Isigny Road Kingsbridge Devon TQ7 1EN",
    "addr:housenumber":"16",
    "addr:postcode":"tq7 1en",
    "addr:street":"Isigny Road",
    "iso:country":"GB",
    "sg:address":"16 Isigny Road",
    "sg:city":"Kingsbridge",
    "sg:classifiers":[
        {
            "category":"Professional",
            "subcategory":"Engineering",
            "type":"Services"
        }
    ],
    "sg:phone":"+44 1548 852840",
    "sg:postcode":"TQ7 1EN",
    "sg:province":"Devon",
    "sg:tags":[
        "contractor",
        "electrical",
        "engineer"
    ],
    "wof:name":"Michael D Head",
    "wof:placetype":"venue"
},
  "geometry": {"coordinates":[-3.783241,50.285507],"type":"Point"}
}