{
  "type": "Feature",
  "properties": {
    "addr:full":"19 Larkfield Avenue Harrow Greater London HA3 8NQ",
    "addr:housenumber":"19",
    "addr:postcode":"ha3 8nq",
    "addr:street":"Larkfield Avenue",
    "iso:country":"GB",
    "sg:address":"19 Larkfield Avenue",
    "sg:city":"Harrow",
    "sg:classifiers":[
        {
            "category":"Professional",
            "type":"Services"
        }
    ],
    "sg:phone":"+44 20 8900 0184",
    "sg:postcode":"HA3 8NQ",
    "sg:province":"Greater London",
    "sg:tags":[
        "entertainer"
    ],
    "wof:name":"Touch of Class",
    "wof:placetype":"venue"
},
  "geometry": {"coordinates":[-0.3129900098,51.5934638977],"type":"Point"}
}