{
  "type": "Feature",
  "properties": {
    "addr:full":"Cholswell Road Abingdon Oxfordshire OX13 6JB",
    "addr:postcode":"ox13 6jb",
    "addr:street":"Cholswell Road",
    "iso:country":"GB",
    "sg:address":"Cholswell Road",
    "sg:city":"Abingdon",
    "sg:classifiers":[
        {
            "category":"Shopping",
            "subcategory":"Department Store",
            "type":"Retail Goods"
        }
    ],
    "sg:phone":"+44 1235 520432",
    "sg:postcode":"OX13 6JB",
    "sg:province":"Oxfordshire",
    "wof:name":"Naafi",
    "wof:placetype":"venue"
},
  "geometry": {"coordinates":[-1.3035180569,51.6905059814],"type":"Point"}
}