{
  "type": "Feature",
  "properties": {
    "addr:full":"Tamworth Business Centre, 24-25 Amber Close Tamworth Staffordshire B77 4RP",
    "addr:housenumber":"24-25",
    "addr:postcode":"b77 4rp",
    "addr:street":"Amber Close",
    "iso:country":"GB",
    "sg:address":"Tamworth Business Centre, 24-25 Amber Close",
    "sg:city":"Tamworth",
    "sg:classifiers":[
        {
            "category":"Home & Garden",
            "subcategory":"Building Materials",
            "type":"Retail Goods"
        }
    ],
    "sg:postcode":"B77 4RP",
    "sg:province":"Staffordshire",
    "sg:tags":[
        "shower",
        "unit"
    ],
    "wof:name":"Berry Showers",
    "wof:placetype":"venue"
},
  "geometry": {"coordinates":[-1.64893,52.62656],"type":"Point"}
}