{
  "type": "Feature",
  "properties": {
    "addr:full":"13 County Road North Hull East Riding of Yorkshire HU5 4HB",
    "addr:housenumber":"13",
    "addr:postcode":"hu5 4hb",
    "addr:street":"County Road North",
    "iso:country":"GB",
    "sg:address":"13 County Road North",
    "sg:city":"Hull",
    "sg:classifiers":[
        {
            "category":"Health Services",
            "subcategory":"Health Practitioner",
            "type":"Services"
        }
    ],
    "sg:phone":"+44 1482 446784",
    "sg:postcode":"HU5 4HB",
    "sg:province":"East Riding of Yorkshire",
    "sg:tags":[
        "hypnotherapists"
    ],
    "wof:name":"St.King Ian",
    "wof:placetype":"venue"
},
  "geometry": {"coordinates":[-0.382011,53.762478],"type":"Point"}
}