{
  "type": "Feature",
  "properties": {
    "iso:country":"GB",
    "sg:address":"5 Bickerstaffe Close, Shaw",
    "sg:city":"Oldham",
    "sg:classifiers":[
        {
            "category":"Personal",
            "type":"Services"
        },
        {
            "category":"Organizations",
            "subcategory":"Community Association",
            "type":"Services"
        }
    ],
    "sg:phone":"+44 1706 843554",
    "sg:postcode":"OL2 7DF",
    "sg:province":"Lancashire",
    "sg:tags":[
        "care",
        "organisation",
        "welfare",
        "animal",
        "wedding"
    ],
    "wof:name":"C K W Parrot Rescue",
    "wof:placetype":"venue"
},
  "geometry": {"coordinates":[-2.100934,53.5728],"type":"Point"}
}