{
  "type": "Feature",
  "properties": {
    "addr:full":"Unit 2 Polbeth Indstl Est, Polbeth West Calder South Lanarkshire EH55 8TJ",
    "addr:housenumber":"unit 2",
    "addr:postcode":"eh55 8tj",
    "addr:street":"Polbeth Indstl Est Polbeth West",
    "iso:country":"GB",
    "sg:address":"Unit 2 Polbeth Indstl Est, Polbeth",
    "sg:city":"West Calder",
    "sg:classifiers":[
        {
            "category":"Professional",
            "subcategory":"Business Services",
            "type":"Services"
        }
    ],
    "sg:postcode":"EH55 8TJ",
    "sg:province":"South Lanarkshire",
    "sg:tags":[
        "import",
        "export",
        "agent"
    ],
    "wof:name":"McCallum,Steven,",
    "wof:placetype":"venue"
},
  "geometry": {"coordinates":[-3.5723719597,55.8511238098],"type":"Point"}
}