{
  "type": "Feature",
  "properties": {
    "addr:full":"1 Ash Tree Rd Knaresborough North Yorkshire HG5 0UB",
    "addr:housenumber":"1",
    "addr:postcode":"hg5 0ub",
    "addr:street":"Ash Tree Rd",
    "iso:country":"GB",
    "sg:address":"1 Ash Tree Rd",
    "sg:city":"Knaresborough",
    "sg:classifiers":[
        {
            "category":"Health Services",
            "subcategory":"Doctor",
            "type":"Services"
        }
    ],
    "sg:phone":"+44 1423 542561",
    "sg:postcode":"HG5 0UB",
    "sg:province":"North Yorkshire",
    "sg:tags":[
        "practitioners"
    ],
    "wof:name":"Drs Yarrow Watson Carradine Keogh & Keenleyside",
    "wof:placetype":"venue"
},
  "geometry": {"coordinates":[-1.4657160044,54.0107192993],"type":"Point"}
}