{
  "type": "Feature",
  "properties": {
    "addr:full":"63 Connaught Street London Greater London W2 2AE",
    "addr:housenumber":"63",
    "addr:postcode":"w2 2ae",
    "addr:street":"Connaught Street",
    "iso:country":"GB",
    "sg:address":"63 Connaught Street",
    "sg:city":"London",
    "sg:classifiers":[
        {
            "category":"Arts & Performance",
            "subcategory":"Art Gallery",
            "type":"Entertainment"
        }
    ],
    "sg:phone":"+44 20 7706 3013",
    "sg:postcode":"W2 2AE",
    "sg:province":"Greater London",
    "wof:name":"The Studio Glass Gallery",
    "wof:placetype":"venue"
},
  "geometry": {"coordinates":[-0.167109,51.514229],"type":"Point"}
}