{
  "type": "Feature",
  "properties": {
    "addr:full":"Toddings, Leintwardine Craven Arms Herefordshire SY7 0LX",
    "addr:postcode":"sy7 0lx",
    "addr:street":"Leintwardine;Herefordshire",
    "iso:country":"GB",
    "sg:address":"Toddings, Leintwardine",
    "sg:city":"Craven Arms",
    "sg:classifiers":[
        {
            "category":"Bars & Pubs",
            "type":"Food & Drink"
        }
    ],
    "sg:phone":"+44 1547 540298",
    "sg:postcode":"SY7 0LX",
    "sg:province":"Herefordshire",
    "sg:tags":[
        "pubs",
        "inn"
    ],
    "wof:name":"Cottagers Comfort",
    "wof:placetype":"venue"
},
  "geometry": {"coordinates":[-2.8768339157,52.3620185852],"type":"Point"}
}