{
  "type": "Feature",
  "properties": {
    "addr:full":"1 Moorside Avenue Blackburn Lancashire BB1 2BA",
    "addr:housenumber":"1",
    "addr:postcode":"bb1 2ba",
    "addr:street":"Moorside Avenue",
    "iso:country":"GB",
    "sg:address":"1 Moorside Avenue",
    "sg:city":"Blackburn",
    "sg:classifiers":[
        {
            "category":"Building & Trades",
            "subcategory":"Landscaping Services",
            "type":"Services"
        }
    ],
    "sg:phone":"+44 1254 263094",
    "sg:postcode":"BB1 2BA",
    "sg:province":"Lancashire",
    "sg:tags":[
        "landscape",
        "contractor"
    ],
    "wof:name":"John F Hosker",
    "wof:placetype":"venue"
},
  "geometry": {"coordinates":[-2.446839,53.745819],"type":"Point"}
}