{
  "type": "Feature",
  "properties": {
    "iso:country":"GB",
    "sg:address":"The Acorns, Sicklehatch Lane, Maynards Grn",
    "sg:city":"Heathfield",
    "sg:classifiers":[
        {
            "category":"Building & Trades",
            "subcategory":"Plumbing",
            "type":"Services"
        }
    ],
    "sg:postcode":"TN21 0BX",
    "sg:province":"East Sussex",
    "sg:tags":[
        "central",
        "heating"
    ],
    "wof:name":"J G Smith Plumbing & Heating",
    "wof:placetype":"venue"
},
  "geometry": {"coordinates":[0.25044,50.944695],"type":"Point"}
}