{
  "type": "Feature",
  "properties": {
    "addr:full":"College Way Ashford Greater London TW15 2XG",
    "addr:postcode":"tw15 2xg",
    "addr:street":"College Way",
    "iso:country":"GB",
    "sg:address":"College Way",
    "sg:city":"Ashford",
    "sg:classifiers":[
        {
            "category":"Sports & Exercise",
            "subcategory":"Sports Center",
            "type":"Entertainment"
        }
    ],
    "sg:phone":"+44 1784 880474",
    "sg:postcode":"TW15 2XG",
    "sg:province":"Greater London",
    "sg:tags":[
        "coaching"
    ],
    "wof:name":"Spelthorne School Of Gymnastics",
    "wof:placetype":"venue"
},
  "geometry": {"coordinates":[-0.462899,51.434196],"type":"Point"}
}