{
  "type": "Feature",
  "properties": {
    "addr:full":"The Feathers Hotel, Market Place York North Yorkshire YO62 5BH",
    "addr:postcode":"yo62 5bh",
    "addr:street":"Market Place York",
    "iso:country":"GB",
    "sg:address":"The Feathers Hotel, Market Place",
    "sg:city":"York",
    "sg:classifiers":[
        {
            "category":"Travel",
            "subcategory":"Hotels & Motels",
            "type":"Entertainment"
        }
    ],
    "sg:phone":"+44 1439 770275",
    "sg:postcode":"YO62 5BH",
    "sg:province":"North Yorkshire",
    "wof:name":"Dialet Ltd.",
    "wof:placetype":"venue"
},
  "geometry": {"coordinates":[-1.0608700514,54.2463912964],"type":"Point"}
}