{
  "type": "Feature",
  "properties": {
    "iso:country":"GB",
    "sg:address":"Hainault",
    "sg:city":"Ilford",
    "sg:classifiers":[
        {
            "category":"Shopping",
            "subcategory":"Stationery & Office Supplies",
            "type":"Retail Goods"
        }
    ],
    "sg:postcode":"IG6 3TU",
    "sg:province":"Essex",
    "wof:name":"Gibbs Stationery",
    "wof:placetype":"venue"
},
  "geometry": {"coordinates":[0.114453,51.600792],"type":"Point"}
}