{
  "type": "Feature",
  "properties": {
    "addr:full":"6 Kettering Road, Islip Kettering Northamptonshire NN14 3JU",
    "addr:housenumber":"6",
    "addr:postcode":"nn14 3ju",
    "addr:street":"Kettering Road",
    "iso:country":"GB",
    "sg:address":"6 Kettering Road, Islip",
    "sg:city":"Kettering",
    "sg:classifiers":[
        {
            "category":"Travel",
            "subcategory":"Hotels & Motels",
            "type":"Entertainment"
        }
    ],
    "sg:phone":"+44 1832 732578",
    "sg:postcode":"NN14 3JU",
    "sg:province":"Northamptonshire",
    "wof:name":"The Woolpack Inn",
    "wof:placetype":"venue"
},
  "geometry": {"coordinates":[-0.549071,52.395988],"type":"Point"}
}