{
  "type": "Feature",
  "properties": {
    "iso:country":"GB",
    "sg:address":"Barn End, 9 Church Lane",
    "sg:city":"Liversedge",
    "sg:classifiers":[
        {
            "category":"Professional",
            "subcategory":"Employment Agencies",
            "type":"Services"
        }
    ],
    "sg:postcode":"WF15 8ET",
    "sg:province":"West Yorkshire",
    "sg:tags":[
        "consultant"
    ],
    "wof:name":"Robinson Jeffrey",
    "wof:placetype":"venue"
},
  "geometry": {"coordinates":[-1.7036349773,53.7106666565],"type":"Point"}
}