{
  "type": "Feature",
  "properties": {
    "addr:full":"222 Wellgate Rotherham South Yorkshire S60 2PD",
    "addr:housenumber":"222",
    "addr:postcode":"s60 2pd",
    "addr:street":"Wellgate Rotherham South",
    "iso:country":"GB",
    "sg:address":"222 Wellgate",
    "sg:city":"Rotherham",
    "sg:classifiers":[
        {
            "category":"Shopping",
            "subcategory":"Bicycles & Sporting Goods",
            "type":"Retail Goods"
        }
    ],
    "sg:phone":"+44 1709 369607",
    "sg:postcode":"S60 2PD",
    "sg:province":"South Yorkshire",
    "sg:tags":[
        "cycle",
        "accessory"
    ],
    "wof:name":"Sondec Cycles",
    "wof:placetype":"venue"
},
  "geometry": {"coordinates":[-1.348041,53.426888],"type":"Point"}
}