{
  "type": "Feature",
  "properties": {
    "iso:country":"GB",
    "sg:address":"4 The Limes, Standish",
    "sg:city":"Wigan",
    "sg:classifiers":[
        {
            "category":"Real Estate",
            "subcategory":"Real Estate Agent",
            "type":"Services"
        }
    ],
    "sg:phone":"+44 1257 427506",
    "sg:postcode":"WN6 0BJ",
    "sg:province":"Lancashire",
    "wof:name":"Stonefield Properties Ltd.",
    "wof:placetype":"venue"
},
  "geometry": {"coordinates":[-2.663401,53.586021],"type":"Point"}
}