{
  "type": "Feature",
  "properties": {
    "addr:full":"5-5a Collingwood Road Witham Essex CM8 2DY",
    "addr:housenumber":"5-5a",
    "addr:postcode":"cm8 2dy",
    "addr:street":"Collingwood Road",
    "iso:country":"GB",
    "sg:address":"5-5a Collingwood Road",
    "sg:city":"Witham",
    "sg:classifiers":[
        {
            "category":"Fast Food",
            "type":"Food & Drink"
        }
    ],
    "sg:phone":"+44 1376 510345",
    "sg:postcode":"CM8 2DY",
    "sg:province":"Essex",
    "sg:tags":[
        "away",
        "take"
    ],
    "wof:name":"Little India",
    "wof:placetype":"venue"
},
  "geometry": {"coordinates":[0.6400439739,51.800491333],"type":"Point"}
}