{
  "type": "Feature",
  "properties": {
    "addr:full":"Forshaw Heath Road, Earlswood Solihull Warwickshire B94 5JU",
    "addr:postcode":"b94 5ju",
    "addr:street":"Forshaw Heath Road",
    "iso:country":"GB",
    "sg:address":"Forshaw Heath Road, Earlswood",
    "sg:city":"Solihull",
    "sg:classifiers":[
        {
            "category":"Home & Garden",
            "subcategory":"Garden Supply",
            "type":"Retail Goods"
        }
    ],
    "sg:phone":"+44 1564 702314",
    "sg:postcode":"B94 5JU",
    "sg:province":"Warwickshire",
    "sg:tags":[
        "nursery",
        "centre"
    ],
    "wof:name":"Earlswood Nurseries Ltd.",
    "wof:placetype":"venue"
},
  "geometry": {"coordinates":[-1.8299939632,52.3637008667],"type":"Point"}
}