{
  "type": "Feature",
  "properties": {
    "iso:country":"GB",
    "sg:address":"Station Road, Rawcliffe Bridge",
    "sg:city":"Goole",
    "sg:classifiers":[
        {
            "category":"Travel",
            "subcategory":"Hotels & Motels",
            "type":"Entertainment"
        }
    ],
    "sg:phone":"+44 1405 839589",
    "sg:postcode":"DN14 8PQ",
    "sg:province":"East Riding of Yorkshire",
    "wof:name":"Rawcliffe Bridge Hotel",
    "wof:placetype":"venue"
},
  "geometry": {"coordinates":[-0.9619489908,53.6983032227],"type":"Point"}
}