{
  "type": "Feature",
  "properties": {
    "iso:country":"GB",
    "sg:address":"9 The Precinct, Station Lane, Featherstone",
    "sg:city":"Pontefract",
    "sg:classifiers":[
        {
            "category":"Professional",
            "subcategory":"Lawyer & Legal Services",
            "type":"Services"
        }
    ],
    "sg:phone":"+44 1977 705490",
    "sg:postcode":"WF7 5BE",
    "sg:province":"West Yorkshire",
    "sg:tags":[
        "solicitor"
    ],
    "wof:name":"Wood Solicitors",
    "wof:placetype":"venue"
},
  "geometry": {"coordinates":[-1.345647,53.670567],"type":"Point"}
}