{
  "type": "Feature",
  "properties": {
    "iso:country":"GB",
    "sg:address":"26 Bushey Hall Road",
    "sg:city":"Bushey",
    "sg:classifiers":[
        {
            "category":"Building & Trades",
            "subcategory":"Plumbing",
            "type":"Services"
        }
    ],
    "sg:phone":"+44 1923 224875",
    "sg:postcode":"WD23 2ED",
    "sg:province":"Hertfordshire",
    "sg:tags":[
        "merchant",
        "plumbers'"
    ],
    "wof:name":"Express Heating Supplies Ltd.",
    "wof:placetype":"venue"
},
  "geometry": {"coordinates":[-0.38321,51.655071],"type":"Point"}
}