{
  "type": "Feature",
  "properties": {
    "addr:full":"1 Broad Street Carlisle Cumbria CA1 2AG",
    "addr:housenumber":"1",
    "addr:postcode":"ca1 2ag",
    "addr:street":"Broad Street",
    "iso:country":"GB",
    "sg:address":"1 Broad Street",
    "sg:city":"Carlisle",
    "sg:classifiers":[
        {
            "category":"Health Services",
            "subcategory":"Medical Lab",
            "type":"Services"
        }
    ],
    "sg:phone":"+44 1228 513090",
    "sg:postcode":"CA1 2AG",
    "sg:province":"Cumbria",
    "sg:tags":[
        "laboratory",
        "dental"
    ],
    "wof:name":"Cumbrian Ceramics",
    "wof:placetype":"venue"
},
  "geometry": {"coordinates":[-2.9246981144,54.8918075562],"type":"Point"}
}