{
  "type": "Feature",
  "properties": {
    "addr:full":"2 Dudley Walk Ripon North Yorkshire HG4 2PJ",
    "addr:housenumber":"2",
    "addr:postcode":"hg4 2pj",
    "addr:street":"Dudley Walk",
    "iso:country":"GB",
    "sg:address":"2 Dudley Walk",
    "sg:city":"Ripon",
    "sg:classifiers":[
        {
            "category":"Professional",
            "subcategory":"Art Services",
            "type":"Services"
        },
        {
            "category":"Building & Trades",
            "subcategory":"Construction",
            "type":"Services"
        }
    ],
    "sg:phone":"+44 1765 609595",
    "sg:postcode":"HG4 2PJ",
    "sg:province":"North Yorkshire",
    "sg:tags":[
        "decorator",
        "painter"
    ],
    "wof:name":"Michael John Bullough",
    "wof:placetype":"venue"
},
  "geometry": {"coordinates":[-1.5273970366,54.1259918213],"type":"Point"}
}