{
  "type": "Feature",
  "properties": {
    "addr:full":"Darleith Farm Ardrossan North Ayrshire KA22 7NX",
    "addr:postcode":"ka22 7nx",
    "iso:country":"GB",
    "sg:address":"Darleith Farm",
    "sg:city":"Ardrossan",
    "sg:classifiers":[
        {
            "category":"Professional",
            "subcategory":"Engineering",
            "type":"Services"
        },
        {
            "category":"Farming",
            "subcategory":"Livestock Farm",
            "type":"Manufacturing & Wholesale Goods"
        }
    ],
    "sg:phone":"+44 1294 464179",
    "sg:postcode":"KA22 7NX",
    "sg:province":"North Ayrshire",
    "wof:name":"John Sharp",
    "wof:placetype":"venue"
},
  "geometry": {"coordinates":[-4.8092489243,55.6479873657],"type":"Point"}
}