{
  "type": "Feature",
  "properties": {
    "iso:country":"GB",
    "sg:address":"22-26 Cricklewood Broadway",
    "sg:city":"Cricklewood",
    "sg:classifiers":[
        {
            "category":"Professional",
            "subcategory":"Business Services",
            "type":"Services"
        }
    ],
    "sg:postcode":"NW2 3HD",
    "sg:province":"Greater London",
    "sg:tags":[
        "import",
        "export",
        "agent"
    ],
    "wof:name":"Motorlease plc",
    "wof:placetype":"venue"
},
  "geometry": {"coordinates":[-0.210673,51.55294],"type":"Point"}
}