{
  "type": "Feature",
  "properties": {
    "addr:full":"Swan House, Swan Square Haverfordwest Pembrokeshire SA61 2AN",
    "addr:postcode":"sa61 2an",
    "addr:street":"Swan Square",
    "iso:country":"GB",
    "sg:address":"Swan House, Swan Square",
    "sg:city":"Haverfordwest",
    "sg:classifiers":[
        {
            "category":"Professional",
            "subcategory":"Lawyer & Legal Services",
            "type":"Services"
        }
    ],
    "sg:postcode":"SA61 2AN",
    "sg:province":"Pembrokeshire",
    "sg:tags":[
        "solicitor"
    ],
    "wof:name":"Paul Settatree & Co.",
    "wof:placetype":"venue"
},
  "geometry": {"coordinates":[-4.970335,51.804138],"type":"Point"}
}