{
  "type": "Feature",
  "properties": {
    "iso:country":"GB",
    "sg:address":"509 Victoria Road, Queenspark",
    "sg:city":"Glasgow",
    "sg:classifiers":[
        {
            "category":"Food & Beverages",
            "subcategory":"Liquor & Beverages",
            "type":"Retail Goods"
        }
    ],
    "sg:phone":"+44 141 423 0055",
    "sg:postcode":"G42 8BH",
    "sg:province":"Glasgow City",
    "sg:tags":[
        "beer",
        "spirit",
        "wines"
    ],
    "wof:name":"Oddbins",
    "wof:placetype":"venue"
},
  "geometry": {"coordinates":[-4.265332,55.834614],"type":"Point"}
}