{
  "type": "Feature",
  "properties": {
    "iso:country":"GB",
    "sg:address":"1 Doublegates Walk, Woodlands",
    "sg:city":"Ripon",
    "sg:classifiers":[
        {
            "category":"Building & Trades",
            "subcategory":"Plumbing",
            "type":"Services"
        }
    ],
    "sg:phone":"+44 1765 603183",
    "sg:postcode":"HG4 2TX",
    "sg:province":"North Yorkshire",
    "sg:tags":[
        "plumber",
        "heating"
    ],
    "wof:name":"JOHN K WILLIAMSON",
    "wof:placetype":"venue"
},
  "geometry": {"coordinates":[-1.5488439798,54.1382446289],"type":"Point"}
}