{
  "type": "Feature",
  "properties": {
    "iso:country":"GB",
    "sg:address":"Bankfield Road",
    "sg:city":"Liverpool",
    "sg:classifiers":[
        {
            "category":"Community Center",
            "type":"Public Place"
        }
    ],
    "sg:phone":"+44 151 254 1968",
    "sg:postcode":"L13 0BQ",
    "sg:province":"Merseyside",
    "sg:tags":[
        "recreation",
        "leisure",
        "centre"
    ],
    "wof:name":"Peter Lloyd Leisure Centre",
    "wof:placetype":"venue"
},
  "geometry": {"coordinates":[-2.920949,53.423634],"type":"Point"}
}