{
  "type": "Feature",
  "properties": {
    "addr:full":"72 Bournemouth Park Road Southend-on-sea Essex SS2 5LP",
    "addr:housenumber":"72",
    "addr:postcode":"ss2 5lp",
    "addr:street":"Bournemouth Park Road",
    "iso:country":"GB",
    "sg:address":"72 Bournemouth Park Road",
    "sg:city":"Southend-on-sea",
    "sg:classifiers":[
        {
            "category":"Food & Beverages",
            "subcategory":"Groceries & Convenience Stores",
            "type":"Retail Goods"
        }
    ],
    "sg:postcode":"SS2 5LP",
    "sg:province":"Essex",
    "wof:name":"Seaside Stores",
    "wof:placetype":"venue"
},
  "geometry": {"coordinates":[0.7225300074,51.5436935425],"type":"Point"}
}