{
  "type": "Feature",
  "properties": {
    "iso:country":"GB",
    "sg:address":"Warboys Road, Bury, Ramsey",
    "sg:city":"Huntingdon",
    "sg:classifiers":[
        {
            "category":"Transit Center",
            "subcategory":"Passenger",
            "type":"Transportation"
        }
    ],
    "sg:postcode":"PE26 2NU",
    "sg:province":"Cambridgeshire",
    "sg:tags":[
        "boarding",
        "kennel",
        "catteries"
    ],
    "wof:name":"Cromwell Farm Boarding Kennels",
    "wof:placetype":"venue"
},
  "geometry": {"coordinates":[-0.1054899991,52.4347686768],"type":"Point"}
}