{
  "type": "Feature",
  "properties": {
    "addr:full":"Unit 27 Tonge Bridge Industrial Estate, Tonge Brige Way Bolton Lancashire BL2 6BD",
    "addr:housenumber":"unit 27",
    "addr:postcode":"bl2 6bd",
    "addr:street":"Tonge Bridge;Brige Way",
    "iso:country":"GB",
    "sg:address":"Unit 27 Tonge Bridge Industrial Estate, Tonge Brige Way",
    "sg:city":"Bolton",
    "sg:classifiers":[
        {
            "category":"Professional",
            "subcategory":"Engineering",
            "type":"Services"
        },
        {
            "category":"Professional",
            "subcategory":"Detective & Security Services",
            "type":"Services"
        }
    ],
    "sg:phone":"+44 1204 380944",
    "sg:postcode":"BL2 6BD",
    "sg:province":"Lancashire",
    "sg:tags":[
        "burglar",
        "alarm",
        "system",
        "contractor",
        "electrical",
        "engineer"
    ],
    "wof:name":"B S Entwistle Electrical Contractors Ltd.",
    "wof:placetype":"venue"
},
  "geometry": {"coordinates":[-2.3794059753,53.5819206238],"type":"Point"}
}