{
  "type": "Feature",
  "properties": {
    "iso:country":"GB",
    "sg:address":"1 Slack Hall, Off Thorpe Lane",
    "sg:city":"Oldham",
    "sg:classifiers":[
        {
            "category":"Building & Trades",
            "subcategory":"Construction",
            "type":"Services"
        }
    ],
    "sg:phone":"+44 161 624 9773",
    "sg:postcode":"OL4 3QE",
    "sg:province":"Lancashire",
    "sg:tags":[
        "builder"
    ],
    "wof:name":"Mark Callaghan",
    "wof:placetype":"venue"
},
  "geometry": {"coordinates":[-2.0636160374,53.546787262],"type":"Point"}
}