{
  "type": "Feature",
  "properties": {
    "iso:country":"GB",
    "sg:address":"Cliff Road",
    "sg:city":"Newquay",
    "sg:classifiers":[
        {
            "category":"Real Estate",
            "subcategory":"Real Estate Agent",
            "type":"Services"
        }
    ],
    "sg:phone":"+44 1637 873888",
    "sg:postcode":"TR7 1SE",
    "sg:province":"Cornwall",
    "wof:name":"Graham Harrison",
    "wof:placetype":"venue"
},
  "geometry": {"coordinates":[-5.076394,50.415176],"type":"Point"}
}