{
  "type": "Feature",
  "properties": {
    "addr:full":"Park House, 116 Park St, Mayfair West End Hampshire W1Y 4LL",
    "addr:housenumber":"116",
    "addr:postcode":"w1y 4ll",
    "addr:street":"Park St",
    "iso:country":"GB",
    "sg:address":"Park House, 116 Park St, Mayfair",
    "sg:city":"West End",
    "sg:classifiers":[
        {
            "category":"Manufacturing",
            "subcategory":"Tools & Machinery",
            "type":"Manufacturing & Wholesale Goods"
        }
    ],
    "sg:phone":"+44 20 7304 4070",
    "sg:postcode":"W1Y 4LL",
    "sg:province":"Hampshire",
    "sg:tags":[
        "society",
        "friendly"
    ],
    "wof:name":"Foundation Health",
    "wof:placetype":"venue"
},
  "geometry": {"coordinates":[-0.1556340009,51.5134811401],"type":"Point"}
}