{
  "type": "Feature",
  "properties": {
    "iso:country":"GB",
    "sg:address":"The Goldsworth Park Health Centre, Goldsworth Park",
    "sg:city":"Woking",
    "sg:classifiers":[
        {
            "category":"Health Services",
            "subcategory":"Dentist",
            "type":"Services"
        }
    ],
    "sg:phone":"+44 1483 766355",
    "sg:postcode":"GU21 3LQ",
    "sg:province":"Surrey",
    "wof:name":"A.S Gough & Associates",
    "wof:placetype":"venue"
},
  "geometry": {"coordinates":[-0.573885,51.315243],"type":"Point"}
}