{
  "type": "Feature",
  "properties": {
    "addr:full":"130 Thurleigh Rd London Greater London SW12 8TU",
    "addr:housenumber":"130",
    "addr:postcode":"sw12 8tu",
    "addr:street":"Thurleigh Rd",
    "iso:country":"GB",
    "sg:address":"130 Thurleigh Rd",
    "sg:city":"London",
    "sg:classifiers":[
        {
            "category":"Professional",
            "subcategory":"Lawyer & Legal Services",
            "type":"Services"
        }
    ],
    "sg:postcode":"SW12 8TU",
    "sg:province":"Greater London",
    "sg:tags":[
        "solicitor"
    ],
    "wof:name":"Heaton,Nicholas,",
    "wof:placetype":"venue"
},
  "geometry": {"coordinates":[-0.153212,51.453693],"type":"Point"}
}