{
  "type": "Feature",
  "properties": {
    "addr:full":"24 Pothouse Lane Darwen Lancashire BB3 3AZ",
    "addr:housenumber":"24",
    "addr:postcode":"bb3 3az",
    "addr:street":"Pothouse Lane",
    "iso:country":"GB",
    "sg:address":"24 Pothouse Lane",
    "sg:city":"Darwen",
    "sg:classifiers":[
        {
            "category":"Retail",
            "subcategory":"Driving School",
            "type":"Services"
        }
    ],
    "sg:phone":"+44 1254 772987",
    "sg:postcode":"BB3 3AZ",
    "sg:province":"Lancashire",
    "wof:name":"Tower School of Motoring",
    "wof:placetype":"venue"
},
  "geometry": {"coordinates":[-2.4531040192,53.7030906677],"type":"Point"}
}