{
  "type": "Feature",
  "properties": {
    "addr:full":"34 Seven Sisters Rd London Greater London N7 6AA",
    "addr:housenumber":"34",
    "addr:postcode":"n7 6aa",
    "addr:street":"Seven Sisters Rd",
    "iso:country":"GB",
    "sg:address":"34 Seven Sisters Rd",
    "sg:city":"London",
    "sg:classifiers":[
        {
            "category":"Bars & Pubs",
            "type":"Food & Drink"
        }
    ],
    "sg:phone":"+44 20 7607 1493",
    "sg:postcode":"N7 6AA",
    "sg:province":"Greater London",
    "sg:tags":[
        "pubs",
        "inn"
    ],
    "wof:name":"Punch Inns (U K) Ltd",
    "wof:placetype":"venue"
},
  "geometry": {"coordinates":[-0.117826,51.558636],"type":"Point"}
}