{
  "type": "Feature",
  "properties": {
    "iso:country":"GB",
    "sg:address":"148 Royal Victoria Place",
    "sg:city":"Tunbridge Wells",
    "sg:classifiers":[
        {
            "category":"Shopping",
            "subcategory":"Clothing, Apparel, & Fashions",
            "type":"Retail Goods"
        }
    ],
    "sg:postcode":"TN1 2SR",
    "sg:province":"Kent",
    "sg:tags":[
        "ladieswear"
    ],
    "wof:name":"Morgan",
    "wof:placetype":"venue"
},
  "geometry": {"coordinates":[0.26513,51.135658],"type":"Point"}
}