{
  "type": "Feature",
  "properties": {
    "addr:full":"The Welsh House, Station Road, Darley Dale Matlock Derbyshire DE4 2EQ",
    "addr:postcode":"de4 2eq",
    "addr:street":"Station Road;Dale",
    "iso:country":"GB",
    "sg:address":"The Welsh House, Station Road, Darley Dale",
    "sg:city":"Matlock",
    "sg:classifiers":[
        {
            "category":"Retail",
            "subcategory":"Auto Repair",
            "type":"Services"
        }
    ],
    "sg:phone":"+44 1629 734961",
    "sg:postcode":"DE4 2EQ",
    "sg:province":"Derbyshire",
    "sg:tags":[
        "modification",
        "garage"
    ],
    "wof:name":"Station Road Motors",
    "wof:placetype":"venue"
},
  "geometry": {"coordinates":[-1.5916390419,53.1611709595],"type":"Point"}
}