{
  "type": "Feature",
  "properties": {
    "addr:full":"161 Rosebery Avenue Clerkenwell Greater London EC1R 4QX",
    "addr:housenumber":"161",
    "addr:postcode":"ec1r 4qx",
    "addr:street":"Rosebery Avenue",
    "iso:country":"GB",
    "sg:address":"161 Rosebery Avenue",
    "sg:city":"Clerkenwell",
    "sg:classifiers":[
        {
            "category":"Real Estate",
            "subcategory":"Architect",
            "type":"Services"
        }
    ],
    "sg:phone":"+44 20 7278 8488",
    "sg:postcode":"EC1R 4QX",
    "sg:province":"Greater London",
    "wof:name":"John Rowe Parr Architects",
    "wof:placetype":"venue"
},
  "geometry": {"coordinates":[-0.107705,51.52758],"type":"Point"}
}