{
  "type": "Feature",
  "properties": {
    "iso:country":"GB",
    "sg:address":"St Georges Street",
    "sg:city":"Norwich",
    "sg:classifiers":[
        {
            "category":"Professional",
            "subcategory":"Art Services",
            "type":"Services"
        },
        {
            "category":"Education",
            "subcategory":"Dance Studio",
            "type":"Public Place"
        }
    ],
    "sg:phone":"+44 1603 610561",
    "sg:postcode":"NR3 1BB",
    "sg:province":"Norfolk",
    "sg:tags":[
        "college",
        "school",
        "design"
    ],
    "sg:website":"http://www.nsad.ac.uk",
    "wof:name":"Norwich School of Art & Design",
    "wof:placetype":"venue"
},
  "geometry": {"coordinates":[1.2937949896,52.6345405579],"type":"Point"}
}