{
  "type": "Feature",
  "properties": {
    "addr:full":"72 St Georges Road Bolton Lancashire BL1 2DD",
    "addr:housenumber":"72",
    "addr:postcode":"bl1 2dd",
    "addr:street":"St Georges Road",
    "iso:country":"GB",
    "sg:address":"72 St Georges Road",
    "sg:city":"Bolton",
    "sg:classifiers":[
        {
            "category":"Professional",
            "subcategory":"Lawyer & Legal Services",
            "type":"Services"
        }
    ],
    "sg:phone":"+44 1204 526465",
    "sg:postcode":"BL1 2DD",
    "sg:province":"Lancashire",
    "sg:tags":[
        "solicitor"
    ],
    "wof:name":"Singh Hussain Khan & Co.",
    "wof:placetype":"venue"
},
  "geometry": {"coordinates":[-2.432258,53.581852],"type":"Point"}
}