{
  "type": "Feature",
  "properties": {
    "addr:full":"Romeland Borehamwood Hertfordshire WD6 3BJ",
    "addr:postcode":"wd6 3bj",
    "addr:street":"Romeland Borehamwood",
    "iso:country":"GB",
    "sg:address":"Romeland",
    "sg:city":"Borehamwood",
    "sg:classifiers":[
        {
            "category":"Health Services",
            "subcategory":"Clinic",
            "type":"Services"
        }
    ],
    "sg:phone":"+44 20 8953 1008",
    "sg:postcode":"WD6 3BJ",
    "sg:province":"Hertfordshire",
    "sg:tags":[
        "nh"
    ],
    "wof:name":"Schopwick Surgery",
    "wof:placetype":"venue"
},
  "geometry": {"coordinates":[-0.29855901,51.6450958252],"type":"Point"}
}