{
  "type": "Feature",
  "properties": {
    "addr:full":"45 Woodland Road, Patney Devizes Wiltshire SN10 3RD",
    "addr:housenumber":"45",
    "addr:postcode":"sn10 3rd",
    "addr:street":"Woodland Road",
    "iso:country":"GB",
    "sg:address":"45 Woodland Road, Patney",
    "sg:city":"Devizes",
    "sg:classifiers":[
        {
            "category":"Farming",
            "subcategory":"Livestock Farm",
            "type":"Manufacturing & Wholesale Goods"
        }
    ],
    "sg:postcode":"SN10 3RD",
    "sg:province":"Wiltshire",
    "sg:tags":[
        "others"
    ],
    "wof:name":"David Harold Snook",
    "wof:placetype":"venue"
},
  "geometry": {"coordinates":[-1.8983440399,51.3274154663],"type":"Point"}
}