{
  "type": "Feature",
  "properties": {
    "iso:country":"GB",
    "sg:address":"10 Havercroft Road",
    "sg:city":"Rotherham",
    "sg:classifiers":[
        {
            "category":"Building & Trades",
            "subcategory":"Plumbing",
            "type":"Services"
        }
    ],
    "sg:phone":"+44 1709 326238",
    "sg:postcode":"S60 3PB",
    "sg:province":"South Yorkshire",
    "sg:tags":[
        "heating"
    ],
    "wof:name":"Dave Rodgers",
    "wof:placetype":"venue"
},
  "geometry": {"coordinates":[-1.323566,53.417019],"type":"Point"}
}