{
  "type": "Feature",
  "properties": {
    "addr:full":"Rear Of 7-9 Hall Lane, Chingford London Greater London E4 8HH",
    "addr:housenumber":"rear of 7-9",
    "addr:postcode":"e4 8hh",
    "addr:street":"Hall Lane",
    "iso:country":"GB",
    "sg:address":"Rear Of 7-9 Hall Lane, Chingford",
    "sg:city":"London",
    "sg:classifiers":[
        {
            "category":"Building & Trades",
            "subcategory":"Construction",
            "type":"Services"
        }
    ],
    "sg:phone":"+44 20 8559 3699",
    "sg:postcode":"E4 8HH",
    "sg:province":"Greater London",
    "sg:tags":[
        "builder"
    ],
    "wof:name":"Woodberry Group Ltd.",
    "wof:placetype":"venue"
},
  "geometry": {"coordinates":[-0.02875,51.615219],"type":"Point"}
}