{
  "type": "Feature",
  "properties": {
    "iso:country":"GB",
    "sg:address":"3 Onega Gate",
    "sg:city":"Sth Bermondsey",
    "sg:classifiers":[
        {
            "category":"Professional",
            "subcategory":"Management & Consulting",
            "type":"Services"
        }
    ],
    "sg:phone":"+44 20 7252 2834",
    "sg:postcode":"SE16 7PF",
    "sg:province":"Greater London",
    "sg:tags":[
        "consultant",
        "business"
    ],
    "wof:name":"Ainsworth & Associates",
    "wof:placetype":"venue"
},
  "geometry": {"coordinates":[-0.039527,51.496246],"type":"Point"}
}