{
  "type": "Feature",
  "properties": {
    "iso:country":"GB",
    "sg:address":"Cemetery Road",
    "sg:city":"Heckmondwike",
    "sg:classifiers":[
        {
            "category":"Arena",
            "subcategory":"Sports Club",
            "type":"Entertainment"
        }
    ],
    "sg:phone":"+44 1924 403701",
    "sg:postcode":"WF16 9ED",
    "sg:province":"West Yorkshire",
    "wof:name":"Heckmondwike Sports Club",
    "wof:placetype":"venue"
},
  "geometry": {"coordinates":[-1.6711720228,53.7102088928],"type":"Point"}
}