{
  "type": "Feature",
  "properties": {
    "iso:country":"GB",
    "sg:address":"Fair View House, Back Lane, Curry Rivel",
    "sg:city":"Langport",
    "sg:classifiers":[
        {
            "category":"Professional",
            "subcategory":"Art Services",
            "type":"Services"
        }
    ],
    "sg:phone":"+44 1458 253290",
    "sg:postcode":"TA10 0NY",
    "sg:province":"Somerset",
    "sg:tags":[
        "graphic",
        "designer"
    ],
    "wof:name":"P & M ASSOCIATES",
    "wof:placetype":"venue"
},
  "geometry": {"coordinates":[-2.865173,51.018539],"type":"Point"}
}