{
  "type": "Feature",
  "properties": {
    "iso:country":"GB",
    "sg:address":"Wholesale Fruit Market, Worthington Way",
    "sg:city":"Wigan",
    "sg:classifiers":[
        {
            "category":"Professional",
            "type":"Services"
        },
        {
            "category":"Cafe",
            "type":"Food & Drink"
        }
    ],
    "sg:postcode":"WN1 2TT",
    "sg:province":"Lancashire",
    "sg:tags":[
        "tea",
        "room",
        "caterer"
    ],
    "wof:name":"M C Catering",
    "wof:placetype":"venue"
},
  "geometry": {"coordinates":[-2.633532,53.544155],"type":"Point"}
}