{
  "type": "Feature",
  "properties": {
    "addr:full":"70 Kingslea Road, Didsbury Manchester Greater Manchester M20 4UA",
    "addr:housenumber":"70",
    "addr:postcode":"m20 4ua",
    "addr:street":"Kingslea Road",
    "iso:country":"GB",
    "sg:address":"70 Kingslea Road, Didsbury",
    "sg:city":"Manchester",
    "sg:classifiers":[
        {
            "category":"Building & Trades",
            "subcategory":"Cleaning & Sanitation",
            "type":"Services"
        }
    ],
    "sg:phone":"+44 161 445 7707",
    "sg:postcode":"M20 4UA",
    "sg:province":"Greater Manchester",
    "sg:tags":[
        "commercial"
    ],
    "wof:name":"Breanheath Ltd.",
    "wof:placetype":"venue"
},
  "geometry": {"coordinates":[-2.22258,53.425667],"type":"Point"}
}