{
  "type": "Feature",
  "properties": {
    "addr:full":"42 Lakeside Rainham Essex RM13 9SW",
    "addr:housenumber":"42",
    "addr:postcode":"rm13 9sw",
    "addr:street":"Lakeside Rainham",
    "iso:country":"GB",
    "sg:address":"42 Lakeside",
    "sg:city":"Rainham",
    "sg:classifiers":[
        {
            "category":"Building & Trades",
            "subcategory":"Plumbing",
            "type":"Services"
        }
    ],
    "sg:postcode":"RM13 9SW",
    "sg:province":"Essex",
    "sg:tags":[
        "heating"
    ],
    "wof:name":"Windsor Plumbing",
    "wof:placetype":"venue"
},
  "geometry": {"coordinates":[0.2188069969,51.5259971619],"type":"Point"}
}