{
  "type": "Feature",
  "properties": {
    "addr:full":"School Way Leigh On Sea Essex SS9 4HX",
    "addr:postcode":"ss9 4hx",
    "addr:street":"School Way",
    "iso:country":"GB",
    "sg:address":"School Way",
    "sg:city":"Leigh On Sea",
    "sg:classifiers":[
        {
            "category":"Education",
            "subcategory":"School",
            "type":"Public Place"
        }
    ],
    "sg:phone":"+44 1702 474684",
    "sg:postcode":"SS9 4HX",
    "sg:province":"Essex",
    "sg:tags":[
        "local",
        "authority"
    ],
    "wof:name":"Blenheim County Primary School",
    "wof:placetype":"venue"
},
  "geometry": {"coordinates":[0.6607499719,51.5549201965],"type":"Point"}
}