{
  "type": "Feature",
  "properties": {
    "iso:country":"GB",
    "sg:address":"10 Kingsmead Square",
    "sg:city":"Bath",
    "sg:classifiers":[
        {
            "category":"Shopping",
            "subcategory":"Clothing, Apparel, & Fashions",
            "type":"Retail Goods"
        }
    ],
    "sg:phone":"+44 1225 461518",
    "sg:postcode":"BA1 2AB",
    "sg:province":"Bath and North East Somerset",
    "sg:tags":[
        "dresswear"
    ],
    "wof:name":"Mrs Simpson",
    "wof:placetype":"venue"
},
  "geometry": {"coordinates":[-2.3633561134,51.3812484741],"type":"Point"}
}