{
  "type": "Feature",
  "properties": {
    "iso:country":"GB",
    "sg:address":"17 Grey Street",
    "sg:city":"Newcastle-upon-tyne",
    "sg:classifiers":[
        {
            "category":"Restaurant",
            "type":"Food & Drink"
        }
    ],
    "sg:phone":"+44 191 221 0312",
    "sg:postcode":"NE1 6EE",
    "sg:province":"Tyne and Wear",
    "sg:tags":[
        "indian",
        "-"
    ],
    "wof:name":"Tandoori Night",
    "wof:placetype":"venue"
},
  "geometry": {"coordinates":[-1.611237,54.971172],"type":"Point"}
}