{
  "type": "Feature",
  "properties": {
    "addr:full":"27 Cinque Ports Street Rye East Sussex TN31 7AD",
    "addr:housenumber":"27",
    "addr:postcode":"tn31 7ad",
    "addr:street":"Cinque Ports Street",
    "iso:country":"GB",
    "sg:address":"27 Cinque Ports Street",
    "sg:city":"Rye",
    "sg:classifiers":[
        {
            "category":"Personal",
            "subcategory":"Barber",
            "type":"Services"
        }
    ],
    "sg:phone":"+44 1797 227533",
    "sg:postcode":"TN31 7AD",
    "sg:province":"East Sussex",
    "sg:tags":[
        "men's",
        "hairdresser"
    ],
    "wof:name":"Brodies Traditional Barbers",
    "wof:placetype":"venue"
},
  "geometry": {"coordinates":[0.7311530113,50.9510688782],"type":"Point"}
}