{
  "type": "Feature",
  "properties": {
    "iso:country":"GB",
    "sg:address":"44 Marvell Avenue",
    "sg:city":"Hayes",
    "sg:classifiers":[
        {
            "category":"Building & Trades",
            "subcategory":"Construction",
            "type":"Services"
        }
    ],
    "sg:phone":"+44 20 8561 5312",
    "sg:postcode":"UB4 0QS",
    "sg:province":"Greater London",
    "sg:tags":[
        "contractor"
    ],
    "wof:name":"Atkinson Craig Construction",
    "wof:placetype":"venue"
},
  "geometry": {"coordinates":[-0.409021,51.524551],"type":"Point"}
}