{
  "type": "Feature",
  "properties": {
    "iso:country":"GB",
    "sg:address":"Edgar Road Community Centre, Edgar Rd",
    "sg:city":"Hounslow",
    "sg:classifiers":[
        {
            "category":"Community Center",
            "subcategory":"Youth",
            "type":"Public Place"
        }
    ],
    "sg:phone":"+44 20 8570 8409",
    "sg:postcode":"TW4 5QP",
    "sg:province":"Greater London",
    "sg:tags":[
        "organisation",
        "centre"
    ],
    "wof:name":"Centre Unit",
    "wof:placetype":"venue"
},
  "geometry": {"coordinates":[-0.377579,51.453644],"type":"Point"}
}