{
  "type": "Feature",
  "properties": {
    "iso:country":"GB",
    "sg:address":"33 Nicholl Street",
    "sg:city":"Swansea",
    "sg:classifiers":[
        {
            "category":"Health Services",
            "subcategory":"Doctor",
            "type":"Services"
        },
        {
            "category":"Health Services",
            "subcategory":"Clinic",
            "type":"Services"
        }
    ],
    "sg:phone":"+44 1792 653548",
    "sg:postcode":"SA1 4HF",
    "sg:province":"Neath Port Talbot",
    "sg:tags":[
        "nh",
        "practitioners"
    ],
    "wof:name":"Nicholl Street Medical Centre",
    "wof:placetype":"venue"
},
  "geometry": {"coordinates":[-3.9515099525,51.6189041138],"type":"Point"}
}