{
  "type": "Feature",
  "properties": {
    "addr:full":"88 Middleton Road Leeds West Yorkshire LS10 3DS",
    "addr:housenumber":"88",
    "addr:postcode":"ls10 3ds",
    "addr:street":"Middleton Road",
    "iso:country":"GB",
    "sg:address":"88 Middleton Road",
    "sg:city":"Leeds",
    "sg:classifiers":[
        {
            "category":"Freight",
            "type":"Transportation"
        }
    ],
    "sg:phone":"+44 113 271 2486",
    "sg:postcode":"LS10 3DS",
    "sg:province":"West Yorkshire",
    "sg:tags":[
        "haulage",
        "transport",
        "road"
    ],
    "wof:name":"G S Deighton",
    "wof:placetype":"venue"
},
  "geometry": {"coordinates":[-1.523232,53.764866],"type":"Point"}
}