{
  "type": "Feature",
  "properties": {
    "iso:country":"GB",
    "sg:address":"224 The Broadway, West Hendon",
    "sg:city":"Colindale",
    "sg:classifiers":[
        {
            "category":"Professional",
            "subcategory":"Business Services",
            "type":"Services"
        }
    ],
    "sg:phone":"+44 20 8202 0145",
    "sg:postcode":"NW9 7ED",
    "sg:province":"Greater London",
    "sg:tags":[
        "bookmaker"
    ],
    "wof:name":"Starkins Bookmakers Ltd",
    "wof:placetype":"venue"
},
  "geometry": {"coordinates":[-0.2395399958,51.5777702332],"type":"Point"}
}