{
  "type": "Feature",
  "properties": {
    "addr:full":"11 Fish Street Shrewsbury Shropshire SY1 1UR",
    "addr:housenumber":"11",
    "addr:postcode":"sy1 1ur",
    "addr:street":"Fish Street",
    "iso:country":"GB",
    "sg:address":"11 Fish Street",
    "sg:city":"Shrewsbury",
    "sg:classifiers":[
        {
            "category":"Shopping",
            "subcategory":"Clothing, Apparel, & Fashions",
            "type":"Retail Goods"
        }
    ],
    "sg:phone":"+44 1743 247770",
    "sg:postcode":"SY1 1UR",
    "sg:province":"Shropshire",
    "sg:tags":[
        "shop"
    ],
    "wof:name":"Zebra",
    "wof:placetype":"venue"
},
  "geometry": {"coordinates":[-2.7529890537,52.7077102661],"type":"Point"}
}