{
  "type": "Feature",
  "properties": {
    "addr:full":"15-17 Mautland Square Houghton-le-spring Durham DH4 4BJ",
    "addr:housenumber":"15-17",
    "addr:postcode":"dh4 4bj",
    "addr:street":"Mautland Square",
    "iso:country":"GB",
    "sg:address":"15-17 Mautland Square",
    "sg:city":"Houghton-le-spring",
    "sg:classifiers":[
        {
            "category":"Shopping",
            "subcategory":"Bicycles & Sporting Goods",
            "type":"Retail Goods"
        }
    ],
    "sg:phone":"+44 191 584 4465",
    "sg:postcode":"DH4 4BJ",
    "sg:province":"Durham",
    "sg:tags":[
        "cycle",
        "accessory"
    ],
    "wof:name":"Houghton Cycles",
    "wof:placetype":"venue"
},
  "geometry": {"coordinates":[-1.471589,54.844109],"type":"Point"}
}