{
  "type": "Feature",
  "properties": {
    "addr:full":"Alpha House, Peel Street, Denton Manchester Greater Manchester M34 3JY",
    "addr:postcode":"m34 3jy",
    "addr:street":"Peel Street",
    "iso:country":"GB",
    "sg:address":"Alpha House, Peel Street, Denton",
    "sg:city":"Manchester",
    "sg:classifiers":[
        {
            "category":"Professional",
            "subcategory":"Printing & Photocopies",
            "type":"Services"
        }
    ],
    "sg:phone":"+44 161 337 8954",
    "sg:postcode":"M34 3JY",
    "sg:province":"Greater Manchester",
    "sg:tags":[
        "computer",
        "tag",
        "label"
    ],
    "wof:name":"Alphatec Labelling Systems Ltd.",
    "wof:placetype":"venue"
},
  "geometry": {"coordinates":[-2.1169240475,53.4567108154],"type":"Point"}
}