{
  "type": "Feature",
  "properties": {
    "addr:full":"36 Glasgow Street Millport North Ayrshire KA28 0DL",
    "addr:housenumber":"36",
    "addr:postcode":"ka28 0dl",
    "addr:street":"Glasgow Street",
    "iso:country":"GB",
    "sg:address":"36 Glasgow Street",
    "sg:city":"Millport",
    "sg:classifiers":[
        {
            "category":"Bars & Pubs",
            "type":"Food & Drink"
        }
    ],
    "sg:postcode":"KA28 0DL",
    "sg:province":"North Ayrshire",
    "sg:tags":[
        "pubs",
        "inn"
    ],
    "wof:name":"The Tavern",
    "wof:placetype":"venue"
},
  "geometry": {"coordinates":[-4.9228172302,55.7538261414],"type":"Point"}
}