{
  "type": "Feature",
  "properties": {
    "addr:full":"Priory Lodge Priory Drive Stanmore Greater London HA7 3HJ",
    "addr:postcode":"ha7 3hj",
    "addr:street":"Priory Drive",
    "iso:country":"GB",
    "sg:address":"Priory Lodge Priory Drive",
    "sg:city":"Stanmore",
    "sg:classifiers":[
        {
            "category":"Real Estate",
            "subcategory":"Developer",
            "type":"Services"
        }
    ],
    "sg:phone":"+44 20 8954 3954",
    "sg:postcode":"HA7 3HJ",
    "sg:province":"Greater London",
    "sg:tags":[
        "property"
    ],
    "wof:name":"Liberty Investments Ltd.",
    "wof:placetype":"venue"
},
  "geometry": {"coordinates":[-0.3104090095,51.6175460815],"type":"Point"}
}