{
  "type": "Feature",
  "properties": {
    "iso:country":"GB",
    "sg:address":"Bishops Weald House, Albion Way",
    "sg:city":"Horsham",
    "sg:classifiers":[
        {
            "category":"Shopping",
            "subcategory":"Pharmacy",
            "type":"Retail Goods"
        }
    ],
    "sg:phone":"+44 1403 272451",
    "sg:postcode":"RH12 1AH",
    "sg:province":"West Sussex",
    "sg:tags":[
        "pharmaceutical"
    ],
    "wof:name":"Link Pharmaceuticals Ltd.",
    "wof:placetype":"venue"
},
  "geometry": {"coordinates":[-0.327677,51.064095],"type":"Point"}
}