{
  "type": "Feature",
  "properties": {
    "addr:full":"159 Millersneuk Crescent Glasgow Glasgow City G33 6PW",
    "addr:housenumber":"159",
    "addr:postcode":"g33 6pw",
    "addr:street":"Millersneuk Crescent",
    "iso:country":"GB",
    "sg:address":"159 Millersneuk Crescent",
    "sg:city":"Glasgow",
    "sg:classifiers":[
        {
            "category":"Personal",
            "type":"Services"
        }
    ],
    "sg:phone":"+44 141 770 9576",
    "sg:postcode":"G33 6PW",
    "sg:province":"Glasgow City",
    "sg:tags":[
        "wedding"
    ],
    "wof:name":"K B Wedding Video",
    "wof:placetype":"venue"
},
  "geometry": {"coordinates":[-4.1670951843,55.8870048523],"type":"Point"}
}