{
  "type": "Feature",
  "properties": {
    "addr:full":"Old Station Yard Hull Road, Dunnington York North Yorkshire YO1 5LP",
    "addr:postcode":"yo1 5lp",
    "addr:street":"Old Station Yard Hull Road",
    "iso:country":"GB",
    "sg:address":"Old Station Yard Hull Road, Dunnington",
    "sg:city":"York",
    "sg:classifiers":[
        {
            "category":"Building & Trades",
            "subcategory":"Construction",
            "type":"Services"
        }
    ],
    "sg:phone":"+44 1904 488292",
    "sg:postcode":"YO1 5LP",
    "sg:province":"North Yorkshire",
    "sg:tags":[
        "platform",
        "work",
        "scaffolding"
    ],
    "wof:name":"B & A Scaffolding Ltd.",
    "wof:placetype":"venue"
},
  "geometry": {"coordinates":[-1.0813499689,53.958770752],"type":"Point"}
}