{
  "type": "Feature",
  "properties": {
    "addr:full":"7 Field End, Drakes Drive Aylesbury Buckinghamshire HP18 9EJ",
    "addr:housenumber":"7",
    "addr:postcode":"hp18 9ej",
    "addr:street":"Field End Drakes Drive",
    "iso:country":"GB",
    "sg:address":"7 Field End, Drakes Drive",
    "sg:city":"Aylesbury",
    "sg:classifiers":[
        {
            "category":"Sports & Exercise",
            "subcategory":"Playing Field",
            "type":"Entertainment"
        }
    ],
    "sg:postcode":"HP18 9EJ",
    "sg:province":"Buckinghamshire",
    "sg:tags":[
        "sanitary",
        "hygiene",
        "appliance"
    ],
    "wof:name":"T N T Logistics",
    "wof:placetype":"venue"
},
  "geometry": {"coordinates":[-1.058019,51.760471],"type":"Point"}
}