{
  "type": "Feature",
  "properties": {
    "addr:full":"4 Buckholt Drive Worcester Worcestershire WR4 9ND",
    "addr:housenumber":"4",
    "addr:postcode":"wr4 9nd",
    "addr:street":"Buckholt Drive",
    "iso:country":"GB",
    "sg:address":"4 Buckholt Drive",
    "sg:city":"Worcester",
    "sg:classifiers":[
        {
            "category":"Professional",
            "subcategory":"Printing & Photocopies",
            "type":"Services"
        }
    ],
    "sg:phone":"+44 1905 754554",
    "sg:postcode":"WR4 9ND",
    "sg:province":"Worcestershire",
    "sg:tags":[
        "printer"
    ],
    "wof:name":"Pace Litho",
    "wof:placetype":"venue"
},
  "geometry": {"coordinates":[-2.188744,52.217644],"type":"Point"}
}