{
  "type": "Feature",
  "properties": {
    "addr:full":"Media Ho, 4 Crown Ct Wakefield West Yorkshire WF1 2SU",
    "addr:housenumber":"4",
    "addr:postcode":"wf1 2su",
    "addr:street":"Crown Ct",
    "iso:country":"GB",
    "sg:address":"Media Ho, 4 Crown Ct",
    "sg:city":"Wakefield",
    "sg:classifiers":[
        {
            "category":"Communications",
            "type":"Services"
        }
    ],
    "sg:postcode":"WF1 2SU",
    "sg:province":"West Yorkshire",
    "sg:tags":[
        "telecommunication"
    ],
    "wof:name":"Professional Print & Communications Ltd",
    "wof:placetype":"venue"
},
  "geometry": {"coordinates":[-1.5004400015,53.6832313538],"type":"Point"}
}