{
  "type": "Feature",
  "properties": {
    "addr:full":"150 Elder Rd Stoke-on-trent Staffordshire ST6 2JG",
    "addr:housenumber":"150",
    "addr:postcode":"st6 2jg",
    "addr:street":"Elder Rd",
    "iso:country":"GB",
    "sg:address":"150 Elder Rd",
    "sg:city":"Stoke-on-trent",
    "sg:classifiers":[
        {
            "category":"Personal",
            "subcategory":"Beauty Salon",
            "type":"Services"
        }
    ],
    "sg:postcode":"ST6 2JG",
    "sg:province":"Staffordshire",
    "sg:tags":[
        "lady",
        "hairdresser"
    ],
    "wof:name":"Madonna Hairstyles",
    "wof:placetype":"venue"
},
  "geometry": {"coordinates":[-2.18592906,53.0360145569],"type":"Point"}
}