{
  "type": "Feature",
  "properties": {
    "iso:country":"GB",
    "sg:address":"Eversfield, Station Road",
    "sg:city":"Warminster",
    "sg:classifiers":[
        {
            "category":"Professional",
            "subcategory":"Accounting & Tax Preparation",
            "type":"Services"
        }
    ],
    "sg:phone":"+44 1985 212613",
    "sg:postcode":"BA12 9BP",
    "sg:province":"Somerset",
    "sg:tags":[
        "accountant"
    ],
    "wof:name":"Pearson May",
    "wof:placetype":"venue"
},
  "geometry": {"coordinates":[-2.1831250191,51.2053642273],"type":"Point"}
}