{
  "type": "Feature",
  "properties": {
    "iso:country":"GB",
    "sg:address":"8 Maud Road",
    "sg:city":"Dorchester",
    "sg:classifiers":[
        {
            "category":"Food & Beverages",
            "subcategory":"Groceries & Convenience Stores",
            "type":"Retail Goods"
        }
    ],
    "sg:phone":"+44 1305 262707",
    "sg:postcode":"DT1 2LW",
    "sg:province":"Dorset",
    "wof:name":"Nisa Conveenience Store",
    "wof:placetype":"venue"
},
  "geometry": {"coordinates":[-2.446355,50.710346],"type":"Point"}
}