{
  "type": "Feature",
  "properties": {
    "addr:full":"Beeching Close Chard Devon TA20 1BB",
    "addr:postcode":"ta20 1bb",
    "addr:street":"Beeching Close",
    "iso:country":"GB",
    "sg:address":"Beeching Close",
    "sg:city":"Chard",
    "sg:classifiers":[
        {
            "category":"Retail",
            "subcategory":"Auto Repair",
            "type":"Services"
        }
    ],
    "sg:postcode":"TA20 1BB",
    "sg:province":"Devon",
    "sg:tags":[
        "body",
        "car"
    ],
    "wof:name":"Chard Auto Body Repairs",
    "wof:placetype":"venue"
},
  "geometry": {"coordinates":[-2.9516839981,50.8818473816],"type":"Point"}
}