{
  "type": "Feature",
  "properties": {
    "addr:full":"14-22 Sussex Road South Croydon Surrey CR2 7DA",
    "addr:housenumber":"14-22",
    "addr:postcode":"cr2 7da",
    "addr:street":"Sussex Road",
    "iso:country":"GB",
    "sg:address":"14-22 Sussex Road",
    "sg:city":"South Croydon",
    "sg:classifiers":[
        {
            "category":"Professional",
            "subcategory":"Testing Lab",
            "type":"Services"
        },
        {
            "category":"Retail",
            "subcategory":"Auto Repair",
            "type":"Services"
        }
    ],
    "sg:phone":"+44 20 8686 1906",
    "sg:postcode":"CR2 7DA",
    "sg:province":"Surrey",
    "sg:tags":[
        "modification",
        "garage",
        "mot"
    ],
    "wof:name":"R D Autos",
    "wof:placetype":"venue"
},
  "geometry": {"coordinates":[-0.093534,51.358604],"type":"Point"}
}