{
  "type": "Feature",
  "properties": {
    "iso:country":"GB",
    "sg:address":"Pier Cott, Ship St",
    "sg:city":"Aberaeron",
    "sg:classifiers":[
        {
            "category":"Travel",
            "subcategory":"Hotels & Motels",
            "type":"Entertainment"
        }
    ],
    "sg:postcode":"SA46 0BS",
    "sg:province":"Ceredigion",
    "sg:tags":[
        "house",
        "guest"
    ],
    "wof:name":"Bell,A,",
    "wof:placetype":"venue"
},
  "geometry": {"coordinates":[-4.259634,52.242119],"type":"Point"}
}