{
  "type": "Feature",
  "properties": {
    "addr:full":"124 Derby Road, Stapleford Nottingham Nottinghamshire NG9 1AY",
    "addr:housenumber":"124",
    "addr:postcode":"ng9 1ay",
    "addr:street":"Derby Road",
    "iso:country":"GB",
    "sg:address":"124 Derby Road, Stapleford",
    "sg:city":"Nottingham",
    "sg:classifiers":[
        {
            "category":"Restaurant",
            "type":"Food & Drink"
        }
    ],
    "sg:phone":"+44 115 939 4929",
    "sg:postcode":"NG9 1AY",
    "sg:province":"Nottinghamshire",
    "sg:tags":[
        "indian"
    ],
    "wof:name":"Moushumi Indian Cuisine",
    "wof:placetype":"venue"
},
  "geometry": {"coordinates":[-1.22212,52.930119],"type":"Point"}
}