{
  "type": "Feature",
  "properties": {
    "addr:full":"325a Wells Rd Bristol City of Bristol BS4 2QB",
    "addr:housenumber":"325a",
    "addr:postcode":"bs4 2qb",
    "addr:street":"Wells Rd",
    "iso:country":"GB",
    "sg:address":"325a Wells Rd",
    "sg:city":"Bristol",
    "sg:classifiers":[
        {
            "category":"Health Services",
            "subcategory":"Dentist",
            "type":"Services"
        }
    ],
    "sg:phone":"+44 117 971 3107",
    "sg:postcode":"BS4 2QB",
    "sg:province":"City of Bristol",
    "wof:name":"I Skerratt",
    "wof:placetype":"venue"
},
  "geometry": {"coordinates":[-2.5672700405,51.4348983765],"type":"Point"}
}