{
  "type": "Feature",
  "properties": {
    "addr:full":"Rye Lane Indoor Market, Rye La Peckham Greater London SE15 5BY",
    "addr:postcode":"se15 5by",
    "addr:street":"Rye Lane;La Peckham",
    "iso:country":"GB",
    "sg:address":"Rye Lane Indoor Market, Rye La",
    "sg:city":"Peckham",
    "sg:classifiers":[
        {
            "category":"Food & Beverages",
            "subcategory":"Supermarket",
            "type":"Retail Goods"
        }
    ],
    "sg:phone":"+44 20 7252 8872",
    "sg:postcode":"SE15 5BY",
    "sg:province":"Greater London",
    "wof:name":"Matfhi International",
    "wof:placetype":"venue"
},
  "geometry": {"coordinates":[-0.069755,51.47258],"type":"Point"}
}