{
  "type": "Feature",
  "properties": {
    "addr:full":"Farlingaye Hall, 48 Hasketon Road Woodbridge Suffolk IP12 4LD",
    "addr:housenumber":"48",
    "addr:postcode":"ip12 4ld",
    "addr:street":"Hasketon Road",
    "iso:country":"GB",
    "sg:address":"Farlingaye Hall, 48 Hasketon Road",
    "sg:city":"Woodbridge",
    "sg:classifiers":[
        {
            "category":"Professional",
            "type":"Services"
        }
    ],
    "sg:phone":"+44 1394 386709",
    "sg:postcode":"IP12 4LD",
    "sg:province":"Suffolk",
    "sg:tags":[
        "caterer"
    ],
    "wof:name":"Classic Catering",
    "wof:placetype":"venue"
},
  "geometry": {"coordinates":[1.3253899813,52.1054496765],"type":"Point"}
}