{
  "type": "Feature",
  "properties": {
    "addr:full":"1 Kingstanding Farm, Ascott Under Wychwood Chipping Norton Gloucestershire OX7 6AR",
    "addr:housenumber":"1",
    "addr:postcode":"gloucestershire ox7 6ar",
    "addr:street":"Kingstanding Farm;Under Wychwood",
    "iso:country":"GB",
    "sg:address":"1 Kingstanding Farm, Ascott Under Wychwood",
    "sg:city":"Chipping Norton",
    "sg:classifiers":[
        {
            "category":"Autos & Motor Vehicles",
            "subcategory":"Motorcycle Sales",
            "type":"Retail Goods"
        }
    ],
    "sg:phone":"+44 1993 832085",
    "sg:postcode":"OX7 6AR",
    "sg:province":"Gloucestershire",
    "sg:tags":[
        "chauffeur",
        "driven",
        "car"
    ],
    "wof:name":"Renaissance Chauffeur Services",
    "wof:placetype":"venue"
},
  "geometry": {"coordinates":[-1.545913,51.940407],"type":"Point"}
}