{
  "type": "Feature",
  "properties": {
    "addr:full":"144 Chepstow Road Newport Newport NP19 8XE",
    "addr:housenumber":"144",
    "addr:postcode":"np19 8xe",
    "addr:street":"Chepstow Road",
    "iso:country":"GB",
    "sg:address":"144 Chepstow Road",
    "sg:city":"Newport",
    "sg:classifiers":[
        {
            "category":"Shopping",
            "subcategory":"Pets & Pet Supplies",
            "type":"Retail Goods"
        }
    ],
    "sg:phone":"+44 1633 258756",
    "sg:postcode":"NP19 8XE",
    "sg:province":"Newport",
    "wof:name":"A J North & Son",
    "wof:placetype":"venue"
},
  "geometry": {"coordinates":[-2.9790000916,51.5898284912],"type":"Point"}
}