{
  "type": "Feature",
  "properties": {
    "addr:full":"Owens Rd, Skippers Lane Indust Est Middlesbrough North Yorkshire TS6 6HE",
    "addr:postcode":"ts6 6he",
    "addr:street":"Owens Rd Skippers Lane",
    "iso:country":"GB",
    "sg:address":"Owens Rd, Skippers Lane Indust Est",
    "sg:city":"Middlesbrough",
    "sg:classifiers":[
        {
            "category":"Utilities",
            "subcategory":"Natural Gas",
            "type":"Services"
        }
    ],
    "sg:phone":"+44 1642 469123",
    "sg:postcode":"TS6 6HE",
    "sg:province":"North Yorkshire",
    "sg:tags":[
        "supplier"
    ],
    "wof:name":"J W Gas",
    "wof:placetype":"venue"
},
  "geometry": {"coordinates":[-1.183441,54.575153],"type":"Point"}
}