{
  "type": "Feature",
  "properties": {
    "iso:country":"GB",
    "sg:address":"Unit 14 Hilton Industrial Estate, Sutton Lane, Hilton",
    "sg:city":"Derby",
    "sg:classifiers":[
        {
            "category":"Manufacturing",
            "subcategory":"Wood Products",
            "type":"Manufacturing & Wholesale Goods"
        },
        {
            "category":"Home & Garden",
            "subcategory":"Building Materials",
            "type":"Retail Goods"
        }
    ],
    "sg:postcode":"DE65 5FE",
    "sg:province":"Derbyshire",
    "sg:tags":[
        "woodturning",
        "rafter",
        "roofing",
        "beams"
    ],
    "wof:name":"Octo Products",
    "wof:placetype":"venue"
},
  "geometry": {"coordinates":[-1.640199,52.872623],"type":"Point"}
}