{
  "type": "Feature",
  "properties": {
    "addr:full":"Lloyds Bank House, 30 Market Street, Oakengates Telford Shropshire TF2 6DD",
    "addr:housenumber":"30",
    "addr:postcode":"tf2 6dd",
    "addr:street":"Market Street",
    "iso:country":"GB",
    "sg:address":"Lloyds Bank House, 30 Market Street, Oakengates",
    "sg:city":"Telford",
    "sg:classifiers":[
        {
            "category":"Professional",
            "subcategory":"Lawyer & Legal Services",
            "type":"Services"
        }
    ],
    "sg:phone":"+44 1952 618787",
    "sg:postcode":"TF2 6DD",
    "sg:province":"Shropshire",
    "sg:tags":[
        "solicitor"
    ],
    "wof:name":"Clarkes",
    "wof:placetype":"venue"
},
  "geometry": {"coordinates":[-2.4505240917,52.6948394775],"type":"Point"}
}