{
  "type": "Feature",
  "properties": {
    "addr:full":"30 Meadow Drive Knutsford Cheshire WA16 0DT",
    "addr:housenumber":"30",
    "addr:postcode":"wa16 0dt",
    "addr:street":"Meadow Drive",
    "iso:country":"GB",
    "sg:address":"30 Meadow Drive",
    "sg:city":"Knutsford",
    "sg:classifiers":[
        {
            "category":"Professional",
            "subcategory":"Engineering",
            "type":"Services"
        },
        {
            "category":"Organizations",
            "subcategory":"Non-profit Organization",
            "type":"Services"
        }
    ],
    "sg:phone":"+44 1565 634211",
    "sg:postcode":"WA16 0DT",
    "sg:province":"Cheshire",
    "sg:tags":[
        "alarm",
        "engineer",
        "electrical",
        "system",
        "contractor"
    ],
    "wof:name":"Knutsford Home Guard",
    "wof:placetype":"venue"
},
  "geometry": {"coordinates":[-2.378609,53.298306],"type":"Point"}
}