{
  "type": "Feature",
  "properties": {
    "iso:country":"GB",
    "sg:address":"44 Woodland Rd",
    "sg:city":"Wolverhampton",
    "sg:classifiers":[
        {
            "category":"Home & Garden",
            "subcategory":"Hardware",
            "type":"Retail Goods"
        }
    ],
    "sg:phone":"+44 1902 380097",
    "sg:postcode":"WV3 8AW",
    "sg:province":"Staffordshire",
    "sg:tags":[
        "device",
        "fixing",
        "fastener"
    ],
    "wof:name":"Traq Fasteners Ltd",
    "wof:placetype":"venue"
},
  "geometry": {"coordinates":[-2.168179,52.573917],"type":"Point"}
}