{
  "type": "Feature",
  "properties": {
    "addr:full":"33 Harrowside Blackpool Lancashire FY4 1QH",
    "addr:housenumber":"33",
    "addr:postcode":"fy4 1qh",
    "addr:street":"Harrowside",
    "iso:country":"GB",
    "sg:address":"33 Harrowside",
    "sg:city":"Blackpool",
    "sg:classifiers":[
        {
            "category":"Home & Garden",
            "subcategory":"Home Furnishings",
            "type":"Retail Goods"
        }
    ],
    "sg:phone":"+44 1253 348008",
    "sg:postcode":"FY4 1QH",
    "sg:province":"Lancashire",
    "sg:tags":[
        "furnishers",
        "planner",
        "bedroom"
    ],
    "wof:name":"Steven Taylor",
    "wof:placetype":"venue"
},
  "geometry": {"coordinates":[-3.054833,53.783749],"type":"Point"}
}