{
  "type": "Feature",
  "properties": {
    "addr:full":"Long Sutton Hook Hampshire RG29 1TB",
    "addr:postcode":"rg29 1tb",
    "iso:country":"GB",
    "sg:address":"Long Sutton",
    "sg:city":"Hook",
    "sg:classifiers":[
        {
            "category":"Education",
            "subcategory":"School",
            "type":"Public Place"
        }
    ],
    "sg:phone":"+44 1256 862201",
    "sg:postcode":"RG29 1TB",
    "sg:province":"Hampshire",
    "sg:tags":[
        "independent",
        "local",
        "authority"
    ],
    "wof:name":"Lord Wandsworth College & Foundation",
    "wof:placetype":"venue"
},
  "geometry": {"coordinates":[-0.9428160191,51.2206001282],"type":"Point"}
}