{
  "type": "Feature",
  "properties": {
    "addr:full":"Aran House, Spring Lane, West Bergholt Colchester Essex CO6 3HH",
    "addr:postcode":"co6 3hh",
    "addr:street":"Spring Lane",
    "iso:country":"GB",
    "sg:address":"Aran House, Spring Lane, West Bergholt",
    "sg:city":"Colchester",
    "sg:classifiers":[
        {
            "category":"Home & Garden",
            "subcategory":"Household Appliances",
            "type":"Retail Goods"
        }
    ],
    "sg:phone":"+44 1206 240638",
    "sg:postcode":"CO6 3HH",
    "sg:province":"Essex",
    "sg:tags":[
        "refrigeration",
        "air conditioning"
    ],
    "wof:name":"Willsher Refrigeration",
    "wof:placetype":"venue"
},
  "geometry": {"coordinates":[0.825127,51.89827],"type":"Point"}
}