{
  "type": "Feature",
  "properties": {
    "addr:full":"2 Sharpenhoe Road, Barton Le Clay Bedford Bedfordshire MK45 4SD",
    "addr:housenumber":"2",
    "addr:postcode":"mk45 4sd",
    "addr:street":"Sharpenhoe Road;Le Clay",
    "iso:country":"GB",
    "sg:address":"2 Sharpenhoe Road, Barton Le Clay",
    "sg:city":"Bedford",
    "sg:classifiers":[
        {
            "category":"Real Estate",
            "subcategory":"Real Estate Agent",
            "type":"Services"
        }
    ],
    "sg:phone":"+44 1582 882411",
    "sg:postcode":"MK45 4SD",
    "sg:province":"Bedfordshire",
    "wof:name":"D S F Property Services",
    "wof:placetype":"venue"
},
  "geometry": {"coordinates":[-0.427209,51.965969],"type":"Point"}
}