{
  "type": "Feature",
  "properties": {
    "iso:country":"GB",
    "sg:address":"Broomhill, Peters Marland",
    "sg:city":"Torrington",
    "sg:classifiers":[
        {
            "category":"Farming",
            "subcategory":"Dairy Farm",
            "type":"Manufacturing & Wholesale Goods"
        }
    ],
    "sg:phone":"+44 1805 601284",
    "sg:postcode":"EX38 8QG",
    "sg:province":"Devon",
    "sg:tags":[
        "farmer"
    ],
    "wof:name":"Pintace Ltd.",
    "wof:placetype":"venue"
},
  "geometry": {"coordinates":[-4.1422548294,50.9531517029],"type":"Point"}
}