{
  "type": "Feature",
  "properties": {
    "iso:country":"GB",
    "sg:address":"230 Albert Road",
    "sg:city":"Plymouth",
    "sg:classifiers":[
        {
            "category":"Community Center",
            "subcategory":"Senior",
            "type":"Public Place"
        },
        {
            "category":"Shopping",
            "subcategory":"Used Merchandise",
            "type":"Retail Goods"
        }
    ],
    "sg:phone":"+44 1752 558595",
    "sg:postcode":"PL2 1AW",
    "sg:province":"Devon",
    "sg:tags":[
        "second",
        "furniture",
        "hand"
    ],
    "wof:name":"Shauns",
    "wof:placetype":"venue"
},
  "geometry": {"coordinates":[-4.1778640747,50.3785209656],"type":"Point"}
}