{
  "type": "Feature",
  "properties": {
    "iso:country":"GB",
    "sg:address":"Rosewood, Windsor Road",
    "sg:city":"Saltburn-by-the-sea",
    "sg:classifiers":[
        {
            "category":"Building & Trades",
            "subcategory":"Construction",
            "type":"Services"
        }
    ],
    "sg:postcode":"TS12 1BQ",
    "sg:province":"North Yorkshire",
    "sg:tags":[
        "builder"
    ],
    "wof:name":"P Bell & Son",
    "wof:placetype":"venue"
},
  "geometry": {"coordinates":[-0.974189,54.582371],"type":"Point"}
}