{
  "type": "Feature",
  "properties": {
    "addr:full":"40 Cliffe Road, Market Weighton York East Riding of Yorkshire YO43 3BN",
    "addr:housenumber":"40",
    "addr:postcode":"yo43 3bn",
    "addr:street":"Cliffe Road",
    "iso:country":"GB",
    "sg:address":"40 Cliffe Road, Market Weighton",
    "sg:city":"York",
    "sg:classifiers":[
        {
            "category":"Retail",
            "subcategory":"Driving School",
            "type":"Services"
        }
    ],
    "sg:postcode":"YO43 3BN",
    "sg:province":"East Riding of Yorkshire",
    "wof:name":"Lind School of Motoring",
    "wof:placetype":"venue"
},
  "geometry": {"coordinates":[-0.6623889804,53.8582611084],"type":"Point"}
}