{
  "type": "Feature",
  "properties": {
    "addr:full":"49 Butterbache Road, Huntington Chester Cheshire CH3 6DD",
    "addr:housenumber":"49",
    "addr:postcode":"ch3 6dd",
    "addr:street":"Butterbache Road",
    "iso:country":"GB",
    "sg:address":"49 Butterbache Road, Huntington",
    "sg:city":"Chester",
    "sg:classifiers":[
        {
            "category":"Professional",
            "subcategory":"Management & Consulting",
            "type":"Services"
        },
        {
            "category":"Real Estate",
            "subcategory":"Architect",
            "type":"Services"
        }
    ],
    "sg:phone":"+44 1244 345352",
    "sg:postcode":"CH3 6DD",
    "sg:province":"Cheshire",
    "sg:tags":[
        "consultant",
        "business"
    ],
    "wof:name":"Auburn Consulting Ltd.",
    "wof:placetype":"venue"
},
  "geometry": {"coordinates":[-2.868368,53.177048],"type":"Point"}
}