{
  "type": "Feature",
  "properties": {
    "addr:full":"Ashfield Mill, Active Way Burnley Lancashire BB11 1BS",
    "addr:postcode":"bb11 1bs",
    "addr:street":"Ashfield;Active Way",
    "iso:country":"GB",
    "sg:address":"Ashfield Mill, Active Way",
    "sg:city":"Burnley",
    "sg:classifiers":[
        {
            "category":"Manufacturing",
            "subcategory":"Textiles",
            "type":"Manufacturing & Wholesale Goods"
        }
    ],
    "sg:phone":"+44 1282 423111",
    "sg:postcode":"BB11 1BS",
    "sg:province":"Lancashire",
    "sg:tags":[
        "made-up"
    ],
    "wof:name":"John Spencer (Textiles) Ltd.",
    "wof:placetype":"venue"
},
  "geometry": {"coordinates":[-2.243809,53.78801],"type":"Point"}
}