{
  "type": "Feature",
  "properties": {
    "iso:country":"GB",
    "sg:address":"10 St Wilfrids Square",
    "sg:city":"Nottingham",
    "sg:classifiers":[
        {
            "category":"Food & Beverages",
            "subcategory":"Fruits & Vegetables",
            "type":"Retail Goods"
        }
    ],
    "sg:postcode":"NG14 6FP",
    "sg:province":"Nottinghamshire",
    "sg:tags":[
        "greengrocer"
    ],
    "wof:name":"Bill's Fruit & Veg",
    "wof:placetype":"venue"
},
  "geometry": {"coordinates":[-1.082414031,53.0370445251],"type":"Point"}
}