{
  "type": "Feature",
  "properties": {
    "addr:full":"Lyons Road, Trafford Park Manchester Cheshire M17 1RN",
    "addr:postcode":"m17 1rn",
    "addr:street":"Lyons Road",
    "iso:country":"GB",
    "sg:address":"Lyons Road, Trafford Park",
    "sg:city":"Manchester",
    "sg:classifiers":[
        {
            "category":"Food & Beverages",
            "subcategory":"Farmers Market",
            "type":"Retail Goods"
        }
    ],
    "sg:phone":"+44 161 872 1095",
    "sg:postcode":"M17 1RN",
    "sg:province":"Cheshire",
    "sg:tags":[
        "supplier",
        "refiner",
        "sugar"
    ],
    "wof:name":"Napier Brown",
    "wof:placetype":"venue"
},
  "geometry": {"coordinates":[-2.3275790215,53.4725532532],"type":"Point"}
}