{
  "type": "Feature",
  "properties": {
    "addr:full":"48 Carnarvon Rd Clacton On Sea Essex CO15 6QA",
    "addr:housenumber":"48",
    "addr:postcode":"co15 6qa",
    "addr:street":"Carnarvon Rd",
    "iso:country":"GB",
    "sg:address":"48 Carnarvon Rd",
    "sg:city":"Clacton On Sea",
    "sg:classifiers":[
        {
            "category":"Organizations",
            "subcategory":"Membership Organization",
            "type":"Services"
        }
    ],
    "sg:phone":"+44 1255 424633",
    "sg:postcode":"CO15 6QA",
    "sg:province":"Essex",
    "sg:tags":[
        "club"
    ],
    "wof:name":"Clacton Railway Club",
    "wof:placetype":"venue"
},
  "geometry": {"coordinates":[1.152721,51.79409],"type":"Point"}
}