{
  "type": "Feature",
  "properties": {
    "addr:full":"Unit 2a Cavendish Arcade, The Crescent Buxton Derbyshire SK17 6BQ",
    "addr:housenumber":"unit 2a;arcade",
    "addr:postcode":"sk17 6bq",
    "addr:street":"Cavendish;The Crescent",
    "iso:country":"GB",
    "sg:address":"Unit 2a Cavendish Arcade, The Crescent",
    "sg:city":"Buxton",
    "sg:classifiers":[
        {
            "category":"Shopping",
            "subcategory":"Antiques",
            "type":"Retail Goods"
        }
    ],
    "sg:postcode":"SK17 6BQ",
    "sg:province":"Derbyshire",
    "wof:name":"Sunburst Decorative Arts",
    "wof:placetype":"venue"
},
  "geometry": {"coordinates":[-1.914773941,53.2597312927],"type":"Point"}
}