{
  "type": "Feature",
  "properties": {
    "addr:full":"Castlefields Health Centre, Chester Clo Runcorn Cheshire WA7 2HY",
    "addr:postcode":"wa7 2hy",
    "iso:country":"GB",
    "sg:address":"Castlefields Health Centre, Chester Clo",
    "sg:city":"Runcorn",
    "sg:classifiers":[
        {
            "category":"Health Services",
            "subcategory":"Doctor",
            "type":"Services"
        }
    ],
    "sg:phone":"+44 1928 566671",
    "sg:postcode":"WA7 2HY",
    "sg:province":"Cheshire",
    "sg:tags":[
        "practitioners"
    ],
    "wof:name":"Wild, A M",
    "wof:placetype":"venue"
},
  "geometry": {"coordinates":[-2.6952960491,53.3404998779],"type":"Point"}
}