{
  "type": "Feature",
  "properties": {
    "iso:country":"GB",
    "sg:address":"Symal House, 43 Edgeware Road",
    "sg:city":"London",
    "sg:classifiers":[
        {
            "category":"Shopping",
            "subcategory":"Mobile Phones",
            "type":"Retail Goods"
        }
    ],
    "sg:phone":"+44 20 8200 0088",
    "sg:postcode":"NW9 0HU",
    "sg:province":"Greater London",
    "wof:name":"Cellular U K Ltd.",
    "wof:placetype":"venue"
},
  "geometry": {"coordinates":[-0.255287,51.588844],"type":"Point"}
}