{
  "type": "Feature",
  "properties": {
    "addr:full":"13 New Lairdship Yards Edinburgh City of Edinburgh EH11 3UY",
    "addr:housenumber":"13",
    "addr:postcode":"eh11 3uy",
    "addr:street":"New Lairdship Yards Edinburgh",
    "iso:country":"GB",
    "sg:address":"13 New Lairdship Yards",
    "sg:city":"Edinburgh",
    "sg:classifiers":[
        {
            "category":"Retail",
            "subcategory":"Auto Rental",
            "type":"Services"
        },
        {
            "category":"Autos & Motor Vehicles",
            "subcategory":"Motorcycle Sales",
            "type":"Retail Goods"
        }
    ],
    "sg:phone":"+44 131 444 1666",
    "sg:postcode":"EH11 3UY",
    "sg:province":"City of Edinburgh",
    "sg:tags":[
        "chauffeur",
        "driven",
        "hire",
        "car"
    ],
    "wof:name":"Charlton Chauffeur Drive",
    "wof:placetype":"venue"
},
  "geometry": {"coordinates":[-3.2823901176,55.9261703491],"type":"Point"}
}