{
  "type": "Feature",
  "properties": {
    "iso:country":"GB",
    "sg:address":"138-140 Station Road",
    "sg:city":"Burnham-on-crouch",
    "sg:classifiers":[
        {
            "category":"Shopping",
            "subcategory":"Stationery & Office Supplies",
            "type":"Retail Goods"
        }
    ],
    "sg:postcode":"CM0 8HH",
    "sg:province":"Essex",
    "wof:name":"Crouch Stationers",
    "wof:placetype":"venue"
},
  "geometry": {"coordinates":[0.8145260215,51.628036499],"type":"Point"}
}