{
  "type": "Feature",
  "properties": {
    "addr:full":"138-140 Station Road Burnham-on-crouch Essex CM0 8HH",
    "addr:housenumber":"138-140",
    "addr:postcode":"cm0 8hh",
    "addr:street":"Station Road",
    "iso:country":"GB",
    "sg:address":"138-140 Station Road",
    "sg:city":"Burnham-on-crouch",
    "sg:classifiers":[
        {
            "category":"Shopping",
            "subcategory":"Stationery & Office Supplies",
            "type":"Retail Goods"
        }
    ],
    "sg:postcode":"CM0 8HH",
    "sg:province":"Essex",
    "wof:name":"Crouch Stationers",
    "wof:placetype":"venue"
},
  "geometry": {"coordinates":[0.8145260215,51.628036499],"type":"Point"}
}