{
  "type": "Feature",
  "properties": {
    "iso:country":"GB",
    "sg:address":"Nettle Bank, South Brink",
    "sg:city":"Wisbech",
    "sg:classifiers":[
        {
            "category":"Wholesale",
            "subcategory":"Fruits & Vegetables",
            "type":"Manufacturing & Wholesale Goods"
        }
    ],
    "sg:phone":"+44 1945 589303",
    "sg:postcode":"PE14 0SA",
    "sg:province":"Cambridgeshire",
    "wof:name":"J Lankfer Cauliflowers",
    "wof:placetype":"venue"
},
  "geometry": {"coordinates":[0.100945,52.627377],"type":"Point"}
}