{
  "type": "Feature",
  "properties": {
    "iso:country":"GB",
    "sg:address":"80 High Street, Old Amersham",
    "sg:city":"Amersham",
    "sg:classifiers":[
        {
            "category":"Shopping",
            "subcategory":"Antiques",
            "type":"Retail Goods"
        }
    ],
    "sg:phone":"+44 1494 722882",
    "sg:postcode":"HP7 0DS",
    "sg:province":"Buckinghamshire",
    "wof:name":"The Cupboard Antiques",
    "wof:placetype":"venue"
},
  "geometry": {"coordinates":[-0.620444,51.667259],"type":"Point"}
}