{
  "type": "Feature",
  "properties": {
    "addr:full":"55 Mayhill Road London Greater London SE7 7JG",
    "addr:housenumber":"55",
    "addr:postcode":"se7 7jg",
    "addr:street":"Mayhill Road",
    "iso:country":"GB",
    "sg:address":"55 Mayhill Road",
    "sg:city":"London",
    "sg:classifiers":[
        {
            "category":"Professional",
            "subcategory":"Management & Consulting",
            "type":"Services"
        }
    ],
    "sg:phone":"+44 20 8305 2196",
    "sg:postcode":"SE7 7JG",
    "sg:province":"Greater London",
    "sg:tags":[
        "consultant",
        "business"
    ],
    "wof:name":"D T Sharman",
    "wof:placetype":"venue"
},
  "geometry": {"coordinates":[0.023325,51.481064],"type":"Point"}
}