{
  "type": "Feature",
  "properties": {
    "addr:full":"Wolverton Tadley Berkshire RG26 5RT",
    "addr:postcode":"rg26 5rt",
    "iso:country":"GB",
    "sg:address":"Wolverton",
    "sg:city":"Tadley",
    "sg:classifiers":[
        {
            "category":"Sports & Exercise",
            "subcategory":"Golf",
            "type":"Entertainment"
        }
    ],
    "sg:phone":"+44 1635 296800",
    "sg:postcode":"RG26 5RT",
    "sg:province":"Berkshire",
    "sg:tags":[
        "club",
        "course"
    ],
    "wof:name":"Sandford Springs Golf Club",
    "wof:placetype":"venue"
},
  "geometry": {"coordinates":[-1.2171900272,51.3213195801],"type":"Point"}
}