{
  "type": "Feature",
  "properties": {
    "iso:country":"GB",
    "sg:address":"18-22 Bridge Street",
    "sg:city":"Maidenhead",
    "sg:classifiers":[
        {
            "category":"Home & Garden",
            "subcategory":"Carpets & Floor Coverings",
            "type":"Retail Goods"
        }
    ],
    "sg:postcode":"SL6 8BJ",
    "sg:province":"Berkshire",
    "sg:tags":[
        "carpets",
        "rug",
        "matting"
    ],
    "wof:name":"Cornish Carpets Ltd.",
    "wof:placetype":"venue"
},
  "geometry": {"coordinates":[-0.715659976,51.5231628418],"type":"Point"}
}