{
  "type": "Feature",
  "properties": {
    "iso:country":"GB",
    "sg:address":"2 Lowther St",
    "sg:city":"Bradford",
    "sg:classifiers":[
        {
            "category":"Building & Trades",
            "subcategory":"Plumbing",
            "type":"Services"
        }
    ],
    "sg:phone":"+44 1274 637021",
    "sg:postcode":"BD2 4RA",
    "sg:province":"West Yorkshire",
    "sg:tags":[
        "heating"
    ],
    "wof:name":"W Bairstow & Son",
    "wof:placetype":"venue"
},
  "geometry": {"coordinates":[-1.731515,53.807079],"type":"Point"}
}