{
  "type": "Feature",
  "properties": {
    "iso:country":"GB",
    "sg:address":"12 Brunton Terrace",
    "sg:city":"Edinburgh",
    "sg:classifiers":[
        {
            "category":"Communications",
            "subcategory":"Film & Video Production",
            "type":"Services"
        }
    ],
    "sg:postcode":"EH8 7SE",
    "sg:province":"City of Edinburgh",
    "sg:tags":[
        "illustrator",
        "artist"
    ],
    "wof:name":"Paul Mudie Illustration & Design",
    "wof:placetype":"venue"
},
  "geometry": {"coordinates":[-3.1486051083,55.9550514221],"type":"Point"}
}