{
  "type": "Feature",
  "properties": {
    "addr:full":"150 Granby Street Liverpool Merseyside L8 2US",
    "addr:housenumber":"150",
    "addr:postcode":"l8 2us",
    "addr:street":"Granby Street",
    "iso:country":"GB",
    "sg:address":"150 Granby Street",
    "sg:city":"Liverpool",
    "sg:classifiers":[
        {
            "category":"Personal",
            "subcategory":"Barber",
            "type":"Services"
        }
    ],
    "sg:phone":"+44 151 726 1308",
    "sg:postcode":"L8 2US",
    "sg:province":"Merseyside",
    "sg:tags":[
        "men's",
        "hairdresser"
    ],
    "wof:name":"Ken's Barber Shop",
    "wof:placetype":"venue"
},
  "geometry": {"coordinates":[-2.956716,53.391418],"type":"Point"}
}