{
  "type": "Feature",
  "properties": {
    "iso:country":"GB",
    "sg:address":"196 Spring Lane, Lambley",
    "sg:city":"Nottingham",
    "sg:classifiers":[
        {
            "category":"Transit Center",
            "subcategory":"Passenger",
            "type":"Transportation"
        }
    ],
    "sg:phone":"+44 115 926 6124",
    "sg:postcode":"NG4 4PE",
    "sg:province":"Nottinghamshire",
    "sg:tags":[
        "boarding",
        "kennel",
        "catteries"
    ],
    "wof:name":"Samfio Cattery",
    "wof:placetype":"venue"
},
  "geometry": {"coordinates":[-1.0807679892,52.9940643311],"type":"Point"}
}