{
  "type": "Feature",
  "properties": {
    "addr:full":"1st Floor 236 Graham Road London Greater London E8 1BP",
    "addr:housenumber":"236",
    "addr:postcode":"e8 1bp",
    "addr:street":"Graham Road",
    "iso:country":"GB",
    "sg:address":"1st Floor 236 Graham Road",
    "sg:city":"London",
    "sg:classifiers":[
        {
            "category":"Professional",
            "subcategory":"Computer Services",
            "type":"Services"
        }
    ],
    "sg:postcode":"E8 1BP",
    "sg:province":"Greater London",
    "sg:tags":[
        "system",
        "software"
    ],
    "wof:name":"U S Computers Ltd",
    "wof:placetype":"venue"
},
  "geometry": {"coordinates":[-0.0560449995,51.5464859009],"type":"Point"}
}