{
  "type": "Feature",
  "properties": {
    "addr:full":"Care Of Great Mills, Stuart Road Gravesend Kent DA11 0BZ",
    "addr:postcode":"da11 0bz",
    "addr:street":"Stuart Road",
    "iso:country":"GB",
    "sg:address":"Care Of Great Mills, Stuart Road",
    "sg:city":"Gravesend",
    "sg:classifiers":[
        {
            "category":"Home & Garden",
            "subcategory":"Home Furnishings",
            "type":"Retail Goods"
        }
    ],
    "sg:phone":"+44 1474 334057",
    "sg:postcode":"DA11 0BZ",
    "sg:province":"Kent",
    "sg:tags":[
        "furnishers",
        "planner",
        "kitchen"
    ],
    "wof:name":"Moben Kitchens",
    "wof:placetype":"venue"
},
  "geometry": {"coordinates":[0.364605993,51.4328269958],"type":"Point"}
}