{
  "type": "Feature",
  "properties": {
    "addr:full":"Unit 2 Pentraeth Industrial Estate, Red Wharf Bay Pentraeth Isle of Anglesey LL75 8PQ",
    "addr:housenumber":"unit 2",
    "addr:postcode":"ll75 8pq",
    "addr:street":"Industrial Estate Red Wharf Bay",
    "iso:country":"GB",
    "sg:address":"Unit 2 Pentraeth Industrial Estate, Red Wharf Bay",
    "sg:city":"Pentraeth",
    "sg:classifiers":[
        {
            "category":"Autos & Motor Vehicles",
            "subcategory":"Auto Supplies",
            "type":"Retail Goods"
        }
    ],
    "sg:postcode":"LL75 8PQ",
    "sg:province":"Isle of Anglesey",
    "sg:tags":[
        "exhaust",
        "absorber",
        "shock"
    ],
    "wof:name":"Barnes Exhausts",
    "wof:placetype":"venue"
},
  "geometry": {"coordinates":[-4.216624,53.282597],"type":"Point"}
}