{
  "type": "Feature",
  "properties": {
    "addr:full":"Greenfields House, Greenfields View, Lower Road Newport Monmouthshire NP18 2AJ",
    "addr:postcode":"np18 2aj",
    "addr:street":"Greenfields View Lower Road",
    "iso:country":"GB",
    "sg:address":"Greenfields House, Greenfields View, Lower Road",
    "sg:city":"Newport",
    "sg:classifiers":[
        {
            "category":"Utilities",
            "subcategory":"Fuel Oil & Lpg",
            "type":"Services"
        }
    ],
    "sg:phone":"+44 1633 400088",
    "sg:postcode":"NP18 2AJ",
    "sg:province":"Monmouthshire",
    "wof:name":"A G Mould",
    "wof:placetype":"venue"
},
  "geometry": {"coordinates":[-2.8684799671,51.6090278625],"type":"Point"}
}