{
  "type": "Feature",
  "properties": {
    "addr:full":"Enquiries, 21 King St Hereford Herefordshire HR4 0LQ",
    "addr:housenumber":"21",
    "addr:postcode":"hr4 0lq",
    "addr:street":"Enquiries;King St",
    "iso:country":"GB",
    "sg:address":"Enquiries, 21 King St",
    "sg:city":"Hereford",
    "sg:classifiers":[
        {
            "category":"Place Of Worship",
            "type":"Public Place"
        }
    ],
    "sg:phone":"+44 1432 269073",
    "sg:postcode":"HR4 0LQ",
    "sg:province":"Herefordshire",
    "wof:name":"Friends Religious Society of Quakers",
    "wof:placetype":"venue"
},
  "geometry": {"coordinates":[-2.731761,52.059204],"type":"Point"}
}