{
  "type": "Feature",
  "properties": {
    "addr:full":"Turnpike Rd Arrochar Argyll and Bute G83 7AA",
    "addr:postcode":"g83 7aa",
    "addr:street":"Turnpike Rd",
    "iso:country":"GB",
    "sg:address":"Turnpike Rd",
    "sg:city":"Arrochar",
    "sg:classifiers":[
        {
            "category":"Bars & Pubs",
            "type":"Food & Drink"
        }
    ],
    "sg:phone":"+44 1301 702347",
    "sg:postcode":"G83 7AA",
    "sg:province":"Argyll and Bute",
    "sg:tags":[
        "pubs",
        "inn"
    ],
    "wof:name":"Moorings The",
    "wof:placetype":"venue"
},
  "geometry": {"coordinates":[-4.748878,56.19537],"type":"Point"}
}