{
  "type": "Feature",
  "properties": {
    "addr:full":"3 Southhouse Broadway Edinburgh City of Edinburgh EH17 8DR",
    "addr:housenumber":"3",
    "addr:postcode":"eh17 8dr",
    "addr:street":"Southhouse Broadway",
    "iso:country":"GB",
    "sg:address":"3 Southhouse Broadway",
    "sg:city":"Edinburgh",
    "sg:classifiers":[
        {
            "category":"Food & Beverages",
            "subcategory":"Supermarket",
            "type":"Retail Goods"
        },
        {
            "category":"Food & Beverages",
            "subcategory":"Groceries & Convenience Stores",
            "type":"Retail Goods"
        }
    ],
    "sg:phone":"+44 131 664 5085",
    "sg:postcode":"EH17 8DR",
    "sg:province":"City of Edinburgh",
    "wof:name":"Broadway Supermarket",
    "wof:placetype":"venue"
},
  "geometry": {"coordinates":[-3.1568789482,55.9015960693],"type":"Point"}
}