{
  "type": "Feature",
  "properties": {
    "iso:country":"GB",
    "sg:address":"19 Railway Rd",
    "sg:city":"Leigh",
    "sg:classifiers":[
        {
            "category":"Shopping",
            "subcategory":"Baby Store",
            "type":"Retail Goods"
        }
    ],
    "sg:postcode":"WN7 4AA",
    "sg:province":"Lancashire",
    "sg:tags":[
        "babywear",
        "childrens"
    ],
    "wof:name":"Smith,Jeffery,",
    "wof:placetype":"venue"
},
  "geometry": {"coordinates":[-2.520483017,53.4967765808],"type":"Point"}
}