{
  "type": "Feature",
  "properties": {
    "addr:full":"48 Brockhurst Lane, Monks Kirby Rugby Northamptonshire CV23 0RA",
    "addr:housenumber":"48",
    "addr:postcode":"cv23 0ra",
    "addr:street":"Brockhurst Lane",
    "iso:country":"GB",
    "sg:address":"48 Brockhurst Lane, Monks Kirby",
    "sg:city":"Rugby",
    "sg:classifiers":[
        {
            "category":"Building & Trades",
            "subcategory":"Plumbing",
            "type":"Services"
        },
        {
            "category":"Building & Trades",
            "subcategory":"Construction",
            "type":"Services"
        }
    ],
    "sg:postcode":"CV23 0RA",
    "sg:province":"Northamptonshire",
    "sg:tags":[
        "heating",
        "contractor"
    ],
    "wof:name":"Raynor Scholes",
    "wof:placetype":"venue"
},
  "geometry": {"coordinates":[-1.311023,52.446754],"type":"Point"}
}