{
  "type": "Feature",
  "properties": {
    "iso:country":"GB",
    "sg:address":"72a Commercial St",
    "sg:city":"Brighouse",
    "sg:classifiers":[
        {
            "category":"Insurance",
            "subcategory":"Insurance Agent",
            "type":"Services"
        }
    ],
    "sg:phone":"+44 1484 400585",
    "sg:postcode":"HD6 1AJ",
    "sg:province":"West Yorkshire",
    "sg:tags":[
        "broker"
    ],
    "wof:name":"Bikerline Direct",
    "wof:placetype":"venue"
},
  "geometry": {"coordinates":[-1.781098,53.702358],"type":"Point"}
}