{
  "type": "Feature",
  "properties": {
    "iso:country":"GB",
    "sg:address":"Robins Park, The Butts",
    "sg:city":"Kingsbridge",
    "sg:classifiers":[
        {
            "category":"Manufacturing",
            "subcategory":"Wood Products",
            "type":"Manufacturing & Wholesale Goods"
        }
    ],
    "sg:phone":"+44 1548 550090",
    "sg:postcode":"TQ7 4SL",
    "sg:province":"Devon",
    "wof:name":"Unipac",
    "wof:placetype":"venue"
},
  "geometry": {"coordinates":[-3.777619,50.283104],"type":"Point"}
}