{
  "type": "Feature",
  "properties": {
    "iso:country":"GB",
    "sg:address":"High Street",
    "sg:city":"Shepperton",
    "sg:classifiers":[
        {
            "category":"Education",
            "subcategory":"Library",
            "type":"Public Place"
        }
    ],
    "sg:phone":"+44 1932 225047",
    "sg:postcode":"TW17 9AU",
    "sg:province":"Surrey",
    "sg:tags":[
        "book"
    ],
    "wof:name":"Shepperton Library",
    "wof:placetype":"venue"
},
  "geometry": {"coordinates":[-0.448948,51.395542],"type":"Point"}
}