{
  "type": "Feature",
  "properties": {
    "addr:full":"114 Felpham Way, Felpham Bognor Regis West Sussex PO22 8QW",
    "addr:housenumber":"114",
    "addr:postcode":"po22 8qw",
    "addr:street":"Felpham Way",
    "iso:country":"GB",
    "sg:address":"114 Felpham Way, Felpham",
    "sg:city":"Bognor Regis",
    "sg:classifiers":[
        {
            "category":"Professional",
            "type":"Services"
        }
    ],
    "sg:phone":"+44 1243 582860",
    "sg:postcode":"PO22 8QW",
    "sg:province":"West Sussex",
    "sg:tags":[
        "entertainer"
    ],
    "wof:name":"David Allen International Entertainments",
    "wof:placetype":"venue"
},
  "geometry": {"coordinates":[-0.6400960088,50.7937088013],"type":"Point"}
}