{
  "type": "Feature",
  "properties": {
    "iso:country":"GB",
    "sg:address":"Clydach, Llanfaes",
    "sg:city":"Beaumaris",
    "sg:classifiers":[
        {
            "category":"Utilities",
            "subcategory":"Fuel Oil & Lpg",
            "type":"Services"
        }
    ],
    "sg:phone":"+44 1248 490837",
    "sg:postcode":"LL58 8RL",
    "sg:province":"Isle of Anglesey",
    "sg:tags":[
        "coal",
        "smokeless"
    ],
    "wof:name":"F E Roberts",
    "wof:placetype":"venue"
},
  "geometry": {"coordinates":[-4.091869,53.26342],"type":"Point"}
}