{
  "type": "Feature",
  "properties": {
    "iso:country":"GB",
    "sg:address":"11-15 High Street, Bookham",
    "sg:city":"Leatherhead",
    "sg:classifiers":[
        {
            "category":"Real Estate",
            "subcategory":"Real Estate Agent",
            "type":"Services"
        }
    ],
    "sg:phone":"+44 1372 457011",
    "sg:postcode":"KT23 4AA",
    "sg:province":"Surrey",
    "wof:name":"Norman & Huggins",
    "wof:placetype":"venue"
},
  "geometry": {"coordinates":[-0.373548,51.278873],"type":"Point"}
}