{
  "type": "Feature",
  "properties": {
    "iso:country":"GB",
    "sg:address":"Abbots Manor, Thaxted Road, Wimbish",
    "sg:city":"Saffron Walden",
    "sg:classifiers":[
        {
            "category":"Professional",
            "subcategory":"Printing & Photocopies",
            "type":"Services"
        }
    ],
    "sg:phone":"+44 1799 527230",
    "sg:postcode":"CB10 2UT",
    "sg:province":"Cambridgeshire",
    "sg:tags":[
        "embroiderer"
    ],
    "wof:name":"Eva Rosentand Ltd.",
    "wof:placetype":"venue"
},
  "geometry": {"coordinates":[0.320355,52.005924],"type":"Point"}
}