{
  "type": "Feature",
  "properties": {
    "addr:full":"Eastgate Shopping Centre, 11a The Forum Gloucester Gloucestershire GL1 1PL",
    "addr:housenumber":"11a the forum",
    "addr:postcode":"gl1 1pl",
    "addr:street":"Eastgate Shopping Centre",
    "iso:country":"GB",
    "sg:address":"Eastgate Shopping Centre, 11a The Forum",
    "sg:city":"Gloucester",
    "sg:classifiers":[
        {
            "category":"Restaurant",
            "type":"Food & Drink"
        }
    ],
    "sg:phone":"+44 1452 501690",
    "sg:postcode":"GL1 1PL",
    "sg:province":"Gloucestershire",
    "wof:name":"Traditional",
    "wof:placetype":"venue"
},
  "geometry": {"coordinates":[-2.249624,51.863811],"type":"Point"}
}