{
  "type": "Feature",
  "properties": {
    "addr:full":"Dockray Halunit 16a, Dockray Hall Kendal Cumbria LA9 4RY",
    "addr:housenumber":"16a",
    "addr:postcode":"la9 4ry",
    "addr:street":"Dockray;Dockray Hall Kendal",
    "iso:country":"GB",
    "sg:address":"Dockray Halunit 16a, Dockray Hall",
    "sg:city":"Kendal",
    "sg:classifiers":[
        {
            "category":"Manufacturing",
            "subcategory":"Building Materials",
            "type":"Manufacturing & Wholesale Goods"
        },
        {
            "category":"Farming",
            "subcategory":"Farm",
            "type":"Manufacturing & Wholesale Goods"
        }
    ],
    "sg:postcode":"LA9 4RY",
    "sg:province":"Cumbria",
    "sg:tags":[
        "merchant",
        "agricultural",
        "builder"
    ],
    "wof:name":"T H Wiggans Builders Hardware Supplies",
    "wof:placetype":"venue"
},
  "geometry": {"coordinates":[-2.7480840683,54.3240013123],"type":"Point"}
}