{
  "type": "Feature",
  "properties": {
    "iso:country":"GB",
    "sg:address":"2 Almondvale Centre",
    "sg:city":"Livingston",
    "sg:classifiers":[
        {
            "category":"Home & Garden",
            "subcategory":"Carpets & Floor Coverings",
            "type":"Retail Goods"
        }
    ],
    "sg:postcode":"EH54 6NB",
    "sg:province":"West Lothian",
    "sg:tags":[
        "carpets",
        "rug",
        "matting"
    ],
    "wof:name":"Allied Carpets Group Plc",
    "wof:placetype":"venue"
},
  "geometry": {"coordinates":[-3.5098340511,55.8862457275],"type":"Point"}
}