{
  "type": "Feature",
  "properties": {
    "addr:full":"9 Staple Inn London Greater London WC1V 7QH",
    "addr:housenumber":"9",
    "addr:postcode":"wc1v 7qh",
    "addr:street":"Staple",
    "iso:country":"GB",
    "sg:address":"9 Staple Inn",
    "sg:city":"London",
    "sg:classifiers":[
        {
            "category":"Professional",
            "subcategory":"Lawyer & Legal Services",
            "type":"Services"
        }
    ],
    "sg:postcode":"WC1V 7QH",
    "sg:province":"Greater London",
    "sg:tags":[
        "barrister"
    ],
    "wof:name":"Staple Inn Chambers",
    "wof:placetype":"venue"
},
  "geometry": {"coordinates":[-0.1111330017,51.5177078247],"type":"Point"}
}