{
  "type": "Feature",
  "properties": {
    "iso:country":"GB",
    "sg:address":"8 Mill Street",
    "sg:city":"Bedford",
    "sg:classifiers":[
        {
            "category":"Personal",
            "subcategory":"Beauty Salon",
            "type":"Services"
        }
    ],
    "sg:phone":"+44 1234 273131",
    "sg:postcode":"MK40 3HD",
    "sg:province":"Bedfordshire",
    "sg:tags":[
        "unisex",
        "hairdresser"
    ],
    "wof:name":"Split Enz",
    "wof:placetype":"venue"
},
  "geometry": {"coordinates":[-0.466231,52.137074],"type":"Point"}
}