{
  "type": "Feature",
  "properties": {
    "iso:country":"GB",
    "sg:address":"180-184 Barford St",
    "sg:city":"Birmingham",
    "sg:classifiers":[
        {
            "category":"Wholesale",
            "subcategory":"Scrap",
            "type":"Manufacturing & Wholesale Goods"
        }
    ],
    "sg:phone":"+44 121 622 4244",
    "sg:postcode":"B5 7EP",
    "sg:province":"West Midlands",
    "sg:tags":[
        "waste",
        "metal"
    ],
    "wof:name":"Assorted Alloys Ltd",
    "wof:placetype":"venue"
},
  "geometry": {"coordinates":[-1.8926780224,52.4699172974],"type":"Point"}
}