{
  "type": "Feature",
  "properties": {
    "addr:full":"1 Granville Street Kettering Northamptonshire NN16 0TA",
    "addr:housenumber":"1",
    "addr:postcode":"nn16 0ta",
    "addr:street":"Granville Street",
    "iso:country":"GB",
    "sg:address":"1 Granville Street",
    "sg:city":"Kettering",
    "sg:classifiers":[
        {
            "category":"Fast Food",
            "type":"Food & Drink"
        }
    ],
    "sg:phone":"+44 1536 512003",
    "sg:postcode":"NN16 0TA",
    "sg:province":"Northamptonshire",
    "sg:tags":[
        "away",
        "meal",
        "outlet",
        "take"
    ],
    "wof:name":"New Village",
    "wof:placetype":"venue"
},
  "geometry": {"coordinates":[-0.7191550136,52.3995513916],"type":"Point"}
}