{
  "type": "Feature",
  "properties": {
    "iso:country":"GB",
    "sg:address":"69 Park Road",
    "sg:city":"Sutton Coldfield",
    "sg:classifiers":[
        {
            "category":"Shopping",
            "subcategory":"News",
            "type":"Retail Goods"
        }
    ],
    "sg:phone":"+44 121 354 5696",
    "sg:postcode":"B73 6BX",
    "sg:province":"West Midlands",
    "sg:tags":[
        "newsagent"
    ],
    "wof:name":"Sanjay News Shop",
    "wof:placetype":"venue"
},
  "geometry": {"coordinates":[-1.828649,52.564732],"type":"Point"}
}