{
  "type": "Feature",
  "properties": {
    "iso:country":"GB",
    "sg:address":"2 The Parade, Church Street, Hoo",
    "sg:city":"Rochester",
    "sg:classifiers":[
        {
            "category":"Food & Beverages",
            "subcategory":"Meat & Fish",
            "type":"Retail Goods"
        }
    ],
    "sg:postcode":"ME3 9AJ",
    "sg:province":"Kent",
    "sg:tags":[
        "chip"
    ],
    "wof:name":"The Captains Table",
    "wof:placetype":"venue"
},
  "geometry": {"coordinates":[0.56409,51.420029],"type":"Point"}
}