{
  "type": "Feature",
  "properties": {
    "addr:full":"Friers Lodge, 1 First Ave Wolverhampton Staffordshire WV10 9SA",
    "addr:housenumber":"1",
    "addr:postcode":"wv10 9sa",
    "addr:street":"First Ave",
    "iso:country":"GB",
    "sg:address":"Friers Lodge, 1 First Ave",
    "sg:city":"Wolverhampton",
    "sg:classifiers":[
        {
            "category":"Fast Food",
            "type":"Food & Drink"
        }
    ],
    "sg:postcode":"WV10 9SA",
    "sg:province":"Staffordshire",
    "sg:tags":[
        "away",
        "take"
    ],
    "wof:name":"Dad's Dreams",
    "wof:placetype":"venue"
},
  "geometry": {"coordinates":[-2.121669054,52.5886497498],"type":"Point"}
}