{
  "type": "Feature",
  "properties": {
    "addr:full":"Kent House, Lower Stone St Maidstone Kent ME15 6LH",
    "addr:postcode":"me15 6lh",
    "addr:street":"Lower Stone St",
    "iso:country":"GB",
    "sg:address":"Kent House, Lower Stone St",
    "sg:city":"Maidstone",
    "sg:classifiers":[
        {
            "category":"Professional",
            "subcategory":"Art Services",
            "type":"Services"
        }
    ],
    "sg:phone":"+44 1622 661669",
    "sg:postcode":"ME15 6LH",
    "sg:province":"Kent",
    "sg:tags":[
        "consultant",
        "design"
    ],
    "wof:name":"Connex Design Associates",
    "wof:placetype":"venue"
},
  "geometry": {"coordinates":[0.5251539946,51.2710418701],"type":"Point"}
}