{
  "type": "Feature",
  "properties": {
    "iso:country":"GB",
    "sg:address":"168 Station Road",
    "sg:city":"Harrow",
    "sg:classifiers":[
        {
            "category":"Shopping",
            "subcategory":"Computers & Home Electronics",
            "type":"Retail Goods"
        }
    ],
    "sg:phone":"+44 20 8863 2211",
    "sg:postcode":"HA1 2RH",
    "sg:province":"Greater London",
    "sg:tags":[
        "hi-fi",
        "centre"
    ],
    "wof:name":"Digital Domain",
    "wof:placetype":"venue"
},
  "geometry": {"coordinates":[-0.331647,51.584122],"type":"Point"}
}