{
  "type": "Feature",
  "properties": {
    "addr:full":"48-52 Darwen Street Blackburn Lancashire BB2 2BH",
    "addr:housenumber":"48-52",
    "addr:postcode":"bb2 2bh",
    "addr:street":"Darwen Street",
    "iso:country":"GB",
    "sg:address":"48-52 Darwen Street",
    "sg:city":"Blackburn",
    "sg:classifiers":[
        {
            "category":"Restaurant",
            "type":"Food & Drink"
        }
    ],
    "sg:postcode":"BB2 2BH",
    "sg:province":"Lancashire",
    "sg:tags":[
        "indian"
    ],
    "wof:name":"Gujrat Tandoori",
    "wof:placetype":"venue"
},
  "geometry": {"coordinates":[-2.4826340675,53.7462425232],"type":"Point"}
}