{
  "type": "Feature",
  "properties": {
    "iso:country":"GB",
    "sg:address":"17 West Quay",
    "sg:city":"Bridgwater",
    "sg:classifiers":[
        {
            "category":"Organizations",
            "subcategory":"Community Association",
            "type":"Services"
        },
        {
            "category":"Organizations",
            "subcategory":"Membership Organization",
            "type":"Services"
        }
    ],
    "sg:phone":"+44 1278 455646",
    "sg:postcode":"TA6 3HW",
    "sg:province":"Somerset",
    "sg:tags":[
        "club",
        "social"
    ],
    "wof:name":"Lions Club",
    "wof:placetype":"venue"
},
  "geometry": {"coordinates":[-3.002074,51.130531],"type":"Point"}
}