{
  "type": "Feature",
  "properties": {
    "iso:country":"GB",
    "sg:address":"Smithsons Farm, Pilling Lane, Pilling",
    "sg:city":"Preston",
    "sg:classifiers":[
        {
            "category":"Farming",
            "subcategory":"Livestock Farm",
            "type":"Manufacturing & Wholesale Goods"
        }
    ],
    "sg:phone":"+44 1253 790270",
    "sg:postcode":"PR3 6HR",
    "sg:province":"Lancashire",
    "sg:tags":[
        "others"
    ],
    "wof:name":"F Lupton",
    "wof:placetype":"venue"
},
  "geometry": {"coordinates":[-2.910156,53.930977],"type":"Point"}
}