{
  "type": "Feature",
  "properties": {
    "addr:full":"Salisbury House, Finsbury Circus London Greater London EC2M 5QQ",
    "addr:postcode":"ec2m 5qq",
    "addr:street":"Finsbury Circus",
    "iso:country":"GB",
    "sg:address":"Salisbury House, Finsbury Circus",
    "sg:city":"London",
    "sg:classifiers":[
        {
            "category":"Banks & Credit Unions",
            "subcategory":"Financial Services",
            "type":"Services"
        }
    ],
    "sg:phone":"+44 20 7588 2378",
    "sg:postcode":"EC2M 5QQ",
    "sg:province":"Greater London",
    "sg:tags":[
        "adviser"
    ],
    "wof:name":"Michael Davey Financial Management Ltd.",
    "wof:placetype":"venue"
},
  "geometry": {"coordinates":[-0.0878389999,51.5180702209],"type":"Point"}
}