{
  "type": "Feature",
  "properties": {
    "addr:full":"113a Monnow Street Monmouth Gloucestershire NP25 3EG",
    "addr:housenumber":"113a",
    "addr:postcode":"np25 3eg",
    "addr:street":"Monnow Street",
    "iso:country":"GB",
    "sg:address":"113a Monnow Street",
    "sg:city":"Monmouth",
    "sg:classifiers":[
        {
            "category":"Professional",
            "subcategory":"Computer Services",
            "type":"Services"
        }
    ],
    "sg:postcode":"NP25 3EG",
    "sg:province":"Gloucestershire",
    "sg:tags":[
        "consultant"
    ],
    "wof:name":"Miracle Training Services Ltd.",
    "wof:placetype":"venue"
},
  "geometry": {"coordinates":[-2.71955,51.809601],"type":"Point"}
}