{
  "type": "Feature",
  "properties": {
    "addr:full":"Olswang, 90 Long Acre London Greater London WC2E 9TT",
    "addr:housenumber":"90",
    "addr:postcode":"wc2e 9tt",
    "addr:street":"Olswang;Long Acre",
    "iso:country":"GB",
    "sg:address":"Olswang, 90 Long Acre",
    "sg:city":"London",
    "sg:classifiers":[
        {
            "category":"Professional",
            "subcategory":"Computer Services",
            "type":"Services"
        }
    ],
    "sg:postcode":"WC2E 9TT",
    "sg:province":"Greater London",
    "sg:tags":[
        "system",
        "software"
    ],
    "wof:name":"Real Time Financial Management Ltd",
    "wof:placetype":"venue"
},
  "geometry": {"coordinates":[-0.1232900023,51.5140991211],"type":"Point"}
}