{
  "type": "Feature",
  "properties": {
    "iso:country":"GB",
    "sg:address":"20 Rickmansworth Rd",
    "sg:city":"Amersham",
    "sg:classifiers":[
        {
            "category":"Social Services",
            "subcategory":"Adult Care",
            "type":"Services"
        }
    ],
    "sg:phone":"+44 1494 726733",
    "sg:postcode":"HP6 5JW",
    "sg:province":"Buckinghamshire",
    "sg:tags":[
        "domestic",
        "cleaning"
    ],
    "wof:name":"Cleanteam",
    "wof:placetype":"venue"
},
  "geometry": {"coordinates":[-0.6065940261,51.6796112061],"type":"Point"}
}