{
  "type": "Feature",
  "properties": {
    "addr:full":"4 The Walk Llanwrtyd Wells Powys LD5 4YA",
    "addr:housenumber":"4",
    "addr:postcode":"ld5 4ya",
    "addr:street":"The Walk",
    "iso:country":"GB",
    "sg:address":"4 The Walk",
    "sg:city":"Llanwrtyd Wells",
    "sg:classifiers":[
        {
            "category":"Social Services",
            "subcategory":"Adult Care",
            "type":"Services"
        }
    ],
    "sg:phone":"+44 1591 620291",
    "sg:postcode":"LD5 4YA",
    "sg:province":"Powys",
    "sg:tags":[
        "housing",
        "sheltered"
    ],
    "wof:name":"Brecknockshire Sheltered Housing",
    "wof:placetype":"venue"
},
  "geometry": {"coordinates":[-3.638735,52.107296],"type":"Point"}
}