{
  "type": "Feature",
  "properties": {
    "addr:full":"Acorn Business Centre 51 High, Street, Grimethorpe Barnsley South Yorkshire S72 7BB",
    "addr:housenumber":"51",
    "addr:postcode":"s72 7bb",
    "addr:street":"High Street;Yorkshire",
    "iso:country":"GB",
    "sg:address":"Acorn Business Centre 51 High, Street, Grimethorpe",
    "sg:city":"Barnsley",
    "sg:classifiers":[
        {
            "category":"Building & Trades",
            "subcategory":"Construction",
            "type":"Services"
        }
    ],
    "sg:postcode":"S72 7BB",
    "sg:province":"South Yorkshire",
    "sg:tags":[
        "roofing"
    ],
    "wof:name":"Landmark Environmental Services Ltd",
    "wof:placetype":"venue"
},
  "geometry": {"coordinates":[-1.3805240393,53.5815658569],"type":"Point"}
}