{
  "type": "Feature",
  "properties": {
    "addr:full":"Crossland Cottage, Severn Road, Pilning Bristol Gloucestershire BS35 4HW",
    "addr:postcode":"bs35 4hw",
    "addr:street":"Severn Road",
    "iso:country":"GB",
    "sg:address":"Crossland Cottage, Severn Road, Pilning",
    "sg:city":"Bristol",
    "sg:classifiers":[
        {
            "category":"Transit Center",
            "subcategory":"Passenger",
            "type":"Transportation"
        }
    ],
    "sg:phone":"+44 1454 632976",
    "sg:postcode":"BS35 4HW",
    "sg:province":"Gloucestershire",
    "sg:tags":[
        "boarding",
        "kennel",
        "catteries"
    ],
    "wof:name":"Cameo Cattery",
    "wof:placetype":"venue"
},
  "geometry": {"coordinates":[-2.6469480991,51.564491272],"type":"Point"}
}