{
  "type": "Feature",
  "properties": {
    "addr:full":"211 High Road Romford Essex RM6 6NY",
    "addr:housenumber":"211",
    "addr:postcode":"rm6 6ny",
    "addr:street":"High Road",
    "iso:country":"GB",
    "sg:address":"211 High Road",
    "sg:city":"Romford",
    "sg:classifiers":[
        {
            "category":"Manufacturing",
            "subcategory":"Petroleum Products",
            "type":"Manufacturing & Wholesale Goods"
        }
    ],
    "sg:phone":"+44 20 8597 8321",
    "sg:postcode":"RM6 6NY",
    "sg:province":"Essex",
    "sg:tags":[
        "double",
        "glazing"
    ],
    "wof:name":"Weatherbest",
    "wof:placetype":"venue"
},
  "geometry": {"coordinates":[0.141009,51.572254],"type":"Point"}
}