{
  "type": "Feature",
  "properties": {
    "iso:country":"GB",
    "sg:address":"13 Mill Street",
    "sg:city":"Wantage",
    "sg:classifiers":[
        {
            "category":"Travel",
            "subcategory":"Travel Agent",
            "type":"Entertainment"
        }
    ],
    "sg:phone":"+44 1235 770056",
    "sg:postcode":"OX12 9AB",
    "sg:province":"Berkshire",
    "sg:tags":[
        "agency",
        "activity"
    ],
    "wof:name":"Ambassador Travel",
    "wof:placetype":"venue"
},
  "geometry": {"coordinates":[-1.427654,51.589237],"type":"Point"}
}