{
  "type": "Feature",
  "properties": {
    "iso:country":"GB",
    "sg:address":"7 Gresham Rd, Blackfords,",
    "sg:city":"Cannock",
    "sg:classifiers":[
        {
            "category":"Social Services",
            "subcategory":"Adult Care",
            "type":"Services"
        }
    ],
    "sg:postcode":"WS11 2BT",
    "sg:province":"Staffordshire",
    "sg:tags":[
        "domestic",
        "cleaning"
    ],
    "wof:name":"Parlour Maids",
    "wof:placetype":"venue"
},
  "geometry": {"coordinates":[-2.022272,52.696716],"type":"Point"}
}