{
  "type": "Feature",
  "properties": {
    "addr:full":"33 Crendon Street High Wycombe Buckinghamshire HP13 6LJ",
    "addr:housenumber":"33",
    "addr:postcode":"hp13 6lj",
    "addr:street":"Crendon Street",
    "iso:country":"GB",
    "sg:address":"33 Crendon Street",
    "sg:city":"High Wycombe",
    "sg:classifiers":[
        {
            "category":"Deli",
            "type":"Food & Drink"
        }
    ],
    "sg:phone":"+44 1494 524243",
    "sg:postcode":"HP13 6LJ",
    "sg:province":"Buckinghamshire",
    "sg:tags":[
        "delicatessen"
    ],
    "wof:name":"Roots' Delicatessen Ltd.",
    "wof:placetype":"venue"
},
  "geometry": {"coordinates":[-0.747709,51.629322],"type":"Point"}
}