{
  "type": "Feature",
  "properties": {
    "iso:country":"GB",
    "sg:address":"120 Mauldeth Road, Withington",
    "sg:city":"Manchester",
    "sg:classifiers":[
        {
            "category":"Shopping",
            "subcategory":"Department Store",
            "type":"Retail Goods"
        },
        {
            "category":"Deli",
            "type":"Food & Drink"
        }
    ],
    "sg:phone":"+44 161 434 3657",
    "sg:postcode":"M14 6SQ",
    "sg:province":"Greater Manchester",
    "sg:tags":[
        "delicatessen"
    ],
    "wof:name":"Mario Miniaci Ltd.",
    "wof:placetype":"venue"
},
  "geometry": {"coordinates":[-2.213241,53.434944],"type":"Point"}
}