{
  "type": "Feature",
  "properties": {
    "iso:country":"GB",
    "sg:address":"Unit 5 St Pauls Road, Rock Ferry/",
    "sg:city":"Birkenhead",
    "sg:classifiers":[
        {
            "category":"Retail",
            "subcategory":"Auto Repair",
            "type":"Services"
        }
    ],
    "sg:phone":"+44 151 644 5353",
    "sg:postcode":"CH42 1LG",
    "sg:province":"Merseyside",
    "sg:tags":[
        "car",
        "sprayer",
        "painter"
    ],
    "wof:name":"D'N'a Bodycrafts",
    "wof:placetype":"venue"
},
  "geometry": {"coordinates":[-3.010564,53.376026],"type":"Point"}
}