{
  "type": "Feature",
  "properties": {
    "iso:country":"GB",
    "sg:address":"12 Carlton Rd, Kibworth",
    "sg:city":"Leicester",
    "sg:classifiers":[
        {
            "category":"Professional",
            "subcategory":"Computer Services",
            "type":"Services"
        }
    ],
    "sg:phone":"+44 116 279 2932",
    "sg:postcode":"LE8 0LZ",
    "sg:province":"Leicestershire",
    "sg:tags":[
        "system",
        "software"
    ],
    "wof:name":"Leisure Base International",
    "wof:placetype":"venue"
},
  "geometry": {"coordinates":[-0.987052,52.55138],"type":"Point"}
}