{
  "type": "Feature",
  "properties": {
    "addr:full":"25 Market Place Spalding Lincolnshire PE11 1SS",
    "addr:housenumber":"25",
    "addr:postcode":"pe11 1ss",
    "addr:street":"Market Place",
    "iso:country":"GB",
    "sg:address":"25 Market Place",
    "sg:city":"Spalding",
    "sg:classifiers":[
        {
            "category":"Shopping",
            "subcategory":"Clothing, Apparel, & Fashions",
            "type":"Retail Goods"
        }
    ],
    "sg:postcode":"PE11 1SS",
    "sg:province":"Lincolnshire",
    "sg:tags":[
        "shop"
    ],
    "wof:name":"Felicity Fashions",
    "wof:placetype":"venue"
},
  "geometry": {"coordinates":[-0.150411,52.786713],"type":"Point"}
}