{
  "type": "Feature",
  "properties": {
    "addr:full":"West Midlands House, Gypsy Lane Willenhall West Midlands WV13 2HA",
    "addr:postcode":"wv13 2ha",
    "addr:street":"Gypsy Lane",
    "iso:country":"GB",
    "sg:address":"West Midlands House, Gypsy Lane",
    "sg:city":"Willenhall",
    "sg:classifiers":[
        {
            "category":"Professional",
            "subcategory":"Art Services",
            "type":"Services"
        }
    ],
    "sg:phone":"+44 121 609 7239",
    "sg:postcode":"WV13 2HA",
    "sg:province":"West Midlands",
    "sg:tags":[
        "framing"
    ],
    "wof:name":"Peel Collectables",
    "wof:placetype":"venue"
},
  "geometry": {"coordinates":[-2.047673,52.582958],"type":"Point"}
}