{
  "type": "Feature",
  "properties": {
    "addr:full":"15 Tirlemont Road South Croydon Surrey CR2 6DS",
    "addr:housenumber":"15",
    "addr:postcode":"cr2 6ds",
    "addr:street":"Tirlemont Road",
    "iso:country":"GB",
    "sg:address":"15 Tirlemont Road",
    "sg:city":"South Croydon",
    "sg:classifiers":[
        {
            "category":"Professional",
            "subcategory":"Management & Consulting",
            "type":"Services"
        },
        {
            "category":"Social Services",
            "subcategory":"Job Training",
            "type":"Services"
        }
    ],
    "sg:phone":"+44 20 8649 8281",
    "sg:postcode":"CR2 6DS",
    "sg:province":"Surrey",
    "sg:tags":[
        "consultant",
        "provider"
    ],
    "wof:name":"Martin Faiers Associates",
    "wof:placetype":"venue"
},
  "geometry": {"coordinates":[-0.103897,51.354568],"type":"Point"}
}