{
  "type": "Feature",
  "properties": {
    "addr:full":"Worth Rd Crawley Surrey RH10 7EB",
    "addr:postcode":"rh10 7eb",
    "addr:street":"Worth Rd",
    "iso:country":"GB",
    "sg:address":"Worth Rd",
    "sg:city":"Crawley",
    "sg:classifiers":[
        {
            "category":"Place Of Worship",
            "type":"Public Place"
        }
    ],
    "sg:phone":"+44 1293 513398",
    "sg:postcode":"RH10 7EB",
    "sg:province":"Surrey",
    "wof:name":"St Barnabas C of E Church",
    "wof:placetype":"venue"
},
  "geometry": {"coordinates":[-0.143459,51.112083],"type":"Point"}
}