{
  "type": "Feature",
  "properties": {
    "addr:full":"Halifax Road Huddersfield West Yorkshire HD3 3AS",
    "addr:postcode":"hd3 3as",
    "addr:street":"Halifax Road",
    "iso:country":"GB",
    "sg:address":"Halifax Road",
    "sg:city":"Huddersfield",
    "sg:classifiers":[
        {
            "category":"Farming",
            "subcategory":"Nursery",
            "type":"Manufacturing & Wholesale Goods"
        },
        {
            "category":"Government",
            "subcategory":"Office",
            "type":"Public Place"
        }
    ],
    "sg:postcode":"HD3 3AS",
    "sg:province":"West Yorkshire",
    "sg:tags":[
        "creche",
        "agency",
        "education",
        "authority"
    ],
    "wof:name":"Harlequin Day Nursery",
    "wof:placetype":"venue"
},
  "geometry": {"coordinates":[-1.824834,53.668449],"type":"Point"}
}