{
  "type": "Feature",
  "properties": {
    "addr:full":"Cumberland Terrace, Willington Crook Durham DL15 0PB",
    "addr:postcode":"dl15 0pb",
    "addr:street":"Cumberland Terrace",
    "iso:country":"GB",
    "sg:address":"Cumberland Terrace, Willington",
    "sg:city":"Crook",
    "sg:classifiers":[
        {
            "category":"Education",
            "subcategory":"School",
            "type":"Public Place"
        },
        {
            "category":"Government",
            "subcategory":"Office",
            "type":"Public Place"
        }
    ],
    "sg:phone":"+44 1388 746336",
    "sg:postcode":"DL15 0PB",
    "sg:province":"Durham",
    "sg:tags":[
        "local",
        "authority"
    ],
    "wof:name":"Willington R C Primary School",
    "wof:placetype":"venue"
},
  "geometry": {"coordinates":[-1.696789,54.712311],"type":"Point"}
}