{
  "type": "Feature",
  "properties": {
    "iso:country":"GB",
    "sg:address":"Maddison Street",
    "sg:city":"Blyth",
    "sg:classifiers":[
        {
            "category":"Retail",
            "subcategory":"Auto Repair",
            "type":"Services"
        }
    ],
    "sg:phone":"+44 1670 353175",
    "sg:postcode":"NE24 1EY",
    "sg:province":"Northumberland",
    "sg:tags":[
        "modification",
        "garage"
    ],
    "wof:name":"T & B Garage",
    "wof:placetype":"venue"
},
  "geometry": {"coordinates":[-1.5131340027,55.1289253235],"type":"Point"}
}