{
  "type": "Feature",
  "properties": {
    "iso:country":"GB",
    "sg:address":"15 Berrywood Road",
    "sg:city":"Northampton",
    "sg:classifiers":[
        {
            "category":"Wholesale",
            "subcategory":"Non-durable Goods",
            "type":"Manufacturing & Wholesale Goods"
        }
    ],
    "sg:postcode":"NN5 6JU",
    "sg:province":"Northamptonshire",
    "sg:tags":[
        "carry",
        "cash"
    ],
    "wof:name":"Duston Packaging Ltd.",
    "wof:placetype":"venue"
},
  "geometry": {"coordinates":[-0.949809,52.2453],"type":"Point"}
}