{
  "type": "Feature",
  "properties": {
    "addr:full":"Care Of Goulds Garden Centre Weymouth Dorset DT3 6AD",
    "addr:postcode":"dt3 6ad",
    "iso:country":"GB",
    "sg:address":"Care Of Goulds Garden Centre",
    "sg:city":"Weymouth",
    "sg:classifiers":[
        {
            "category":"Food & Beverages",
            "subcategory":"Farmers Market",
            "type":"Retail Goods"
        }
    ],
    "sg:postcode":"DT3 6AD",
    "sg:province":"Dorset",
    "sg:tags":[
        "farm",
        "shop",
        "pyo"
    ],
    "wof:name":"Marswood Farm Shop",
    "wof:placetype":"venue"
},
  "geometry": {"coordinates":[-2.44039011,50.6457099915],"type":"Point"}
}