{
  "type": "Feature",
  "properties": {
    "addr:full":"116 West End Lane London Greater London NW6 2LS",
    "addr:housenumber":"116",
    "addr:postcode":"nw6 2ls",
    "addr:street":"West End Lane",
    "iso:country":"GB",
    "sg:address":"116 West End Lane",
    "sg:city":"London",
    "sg:classifiers":[
        {
            "category":"Food & Beverages",
            "subcategory":"Groceries & Convenience Stores",
            "type":"Retail Goods"
        }
    ],
    "sg:phone":"+44 20 7328 3788",
    "sg:postcode":"NW6 2LS",
    "sg:province":"Greater London",
    "wof:name":"Western Food Store",
    "wof:placetype":"venue"
},
  "geometry": {"coordinates":[-0.190873,51.54678],"type":"Point"}
}