{
  "type": "Feature",
  "properties": {
    "iso:country":"GB",
    "sg:address":"107 Wellington Road",
    "sg:city":"Leeds",
    "sg:classifiers":[
        {
            "category":"Home & Garden",
            "subcategory":"Home Furnishings",
            "type":"Retail Goods"
        }
    ],
    "sg:phone":"+44 113 263 5225",
    "sg:postcode":"LS12 1DX",
    "sg:province":"West Yorkshire",
    "sg:tags":[
        "merchant",
        "diy",
        "decorators'"
    ],
    "wof:name":"Dulux Decorator Centre",
    "wof:placetype":"venue"
},
  "geometry": {"coordinates":[-1.572367,53.79105],"type":"Point"}
}