{
  "type": "Feature",
  "properties": {
    "iso:country":"GB",
    "sg:address":"25 Seaton Road, Wigston",
    "sg:city":"Leicester",
    "sg:classifiers":[
        {
            "category":"Professional",
            "type":"Services"
        }
    ],
    "sg:phone":"+44 116 288 8527",
    "sg:postcode":"LE18 2BY",
    "sg:province":"Leicestershire",
    "sg:tags":[
        "shopfitters"
    ],
    "wof:name":"Carter & Bass Ltd.",
    "wof:placetype":"venue"
},
  "geometry": {"coordinates":[-1.1139919758,52.5813369751],"type":"Point"}
}