{
  "type": "Feature",
  "properties": {
    "iso:country":"GB",
    "sg:address":"161a Green Lanes, Palmers Green",
    "sg:city":"Palmers Green",
    "sg:classifiers":[
        {
            "category":"Professional",
            "subcategory":"Business Services",
            "type":"Services"
        }
    ],
    "sg:phone":"+44 20 8881 9849",
    "sg:postcode":"N13 4SP",
    "sg:province":"Greater London",
    "sg:tags":[
        "import",
        "export",
        "agent"
    ],
    "wof:name":"Kasal & Co",
    "wof:placetype":"venue"
},
  "geometry": {"coordinates":[-0.109671,51.612202],"type":"Point"}
}