{
  "type": "Feature",
  "properties": {
    "addr:full":"81 Fawcett Road Southsea Hampshire PO4 0DB",
    "addr:housenumber":"81",
    "addr:postcode":"po4 0db",
    "addr:street":"Fawcett Road",
    "iso:country":"GB",
    "sg:address":"81 Fawcett Road",
    "sg:city":"Southsea",
    "sg:classifiers":[
        {
            "category":"Autos & Motor Vehicles",
            "subcategory":"Fuel & Gas Station",
            "type":"Retail Goods"
        },
        {
            "category":"Communications",
            "type":"Services"
        }
    ],
    "sg:phone":"+44 23 9287 6583",
    "sg:postcode":"PO4 0DB",
    "sg:province":"Hampshire",
    "sg:tags":[
        "tv",
        "radio",
        "video",
        "aga",
        "cooker"
    ],
    "wof:name":"Annes Secondhand Furniture",
    "wof:placetype":"venue"
},
  "geometry": {"coordinates":[-1.076269,50.791519],"type":"Point"}
}