{
  "type": "Feature",
  "properties": {
    "addr:full":"92 Chewton Road, Walthamstow London Greater London E17 7DN",
    "addr:housenumber":"92",
    "addr:postcode":"e17 7dn",
    "addr:street":"Chewton Road",
    "iso:country":"GB",
    "sg:address":"92 Chewton Road, Walthamstow",
    "sg:city":"London",
    "sg:classifiers":[
        {
            "category":"Manufacturing",
            "subcategory":"Furniture",
            "type":"Manufacturing & Wholesale Goods"
        }
    ],
    "sg:postcode":"E17 7DN",
    "sg:province":"Greater London",
    "sg:tags":[
        "polishing",
        "french"
    ],
    "wof:name":"Wendys French Polishing",
    "wof:placetype":"venue"
},
  "geometry": {"coordinates":[-0.0356759988,51.58436203],"type":"Point"}
}