{
  "type": "Feature",
  "properties": {
    "iso:country":"GB",
    "sg:address":"5a Station Road, Marston Moreteyne",
    "sg:city":"Bedford",
    "sg:classifiers":[
        {
            "category":"Personal",
            "subcategory":"Beauty Salon",
            "type":"Services"
        }
    ],
    "sg:phone":"+44 1234 768554",
    "sg:postcode":"MK43 0PH",
    "sg:province":"Bedfordshire",
    "sg:tags":[
        "unisex",
        "hairdresser"
    ],
    "wof:name":"Brambles the Salon",
    "wof:placetype":"venue"
},
  "geometry": {"coordinates":[-0.559077,52.041439],"type":"Point"}
}