{
  "type": "Feature",
  "properties": {
    "addr:full":"69 Melchett Road, Kings Norton Business Centre, Kings Norton Birmingham West Midlands B30 3HP",
    "addr:housenumber":"69;business centre",
    "addr:postcode":"b30 3hp",
    "addr:street":"Melchett Road",
    "iso:country":"GB",
    "sg:address":"69 Melchett Road, Kings Norton Business Centre, Kings Norton",
    "sg:city":"Birmingham",
    "sg:classifiers":[
        {
            "category":"Wholesale",
            "subcategory":"Metals & Minerals",
            "type":"Manufacturing & Wholesale Goods"
        }
    ],
    "sg:phone":"+44 121 486 4321",
    "sg:postcode":"B30 3HP",
    "sg:province":"West Midlands",
    "sg:tags":[
        "industry",
        "b-m"
    ],
    "wof:name":"L & N Metallurgical Products (U K) Ltd.",
    "wof:placetype":"venue"
},
  "geometry": {"coordinates":[-1.9225640297,52.4158401489],"type":"Point"}
}