{
  "type": "Feature",
  "properties": {
    "addr:full":"Shoshanna, West End, Warfield Bracknell Berkshire RG42 5RP",
    "addr:postcode":"rg42 5rp",
    "addr:street":"West",
    "iso:country":"GB",
    "sg:address":"Shoshanna, West End, Warfield",
    "sg:city":"Bracknell",
    "sg:classifiers":[
        {
            "category":"Building & Trades",
            "subcategory":"Pest Control",
            "type":"Services"
        },
        {
            "category":"Building & Trades",
            "subcategory":"Construction",
            "type":"Services"
        }
    ],
    "sg:phone":"+44 1344 861303",
    "sg:postcode":"RG42 5RP",
    "sg:province":"Berkshire",
    "sg:tags":[
        "vermin",
        "decorator",
        "painter"
    ],
    "wof:name":"As You Like It",
    "wof:placetype":"venue"
},
  "geometry": {"coordinates":[-0.7567800283,51.4180412292],"type":"Point"}
}