{
  "type": "Feature",
  "properties": {
    "iso:country":"GB",
    "sg:address":"48 High Street",
    "sg:city":"Romford",
    "sg:classifiers":[
        {
            "category":"Bars & Pubs",
            "subcategory":"Nightclub",
            "type":"Food & Drink"
        }
    ],
    "sg:phone":"+44 1708 752222",
    "sg:postcode":"RM1 1AB",
    "sg:province":"Essex",
    "sg:tags":[
        "club",
        "night"
    ],
    "wof:name":"Secrets Ltd.",
    "wof:placetype":"venue"
},
  "geometry": {"coordinates":[0.1780129969,51.5773735046],"type":"Point"}
}