{
  "type": "Feature",
  "properties": {
    "addr:full":"146 Queens Road Watford Hertfordshire WD17 2NX",
    "addr:housenumber":"146",
    "addr:postcode":"wd17 2nx",
    "addr:street":"Queens Road",
    "iso:country":"GB",
    "sg:address":"146 Queens Road",
    "sg:city":"Watford",
    "sg:classifiers":[
        {
            "category":"Autos & Motor Vehicles",
            "subcategory":"Automobile Sales",
            "type":"Retail Goods"
        }
    ],
    "sg:postcode":"WD17 2NX",
    "sg:province":"Hertfordshire",
    "sg:tags":[
        "car"
    ],
    "wof:name":"Sterling Traders Limited",
    "wof:placetype":"venue"
},
  "geometry": {"coordinates":[-0.393110007,51.66015625],"type":"Point"}
}