{
  "type": "Feature",
  "properties": {
    "addr:full":"90 Church Street, Hunslet Leeds West Yorkshire LS10 2AR",
    "addr:housenumber":"90",
    "addr:postcode":"ls10 2ar",
    "addr:street":"Church Street",
    "iso:country":"GB",
    "sg:address":"90 Church Street, Hunslet",
    "sg:city":"Leeds",
    "sg:classifiers":[
        {
            "category":"Bars & Pubs",
            "type":"Food & Drink"
        }
    ],
    "sg:phone":"+44 113 270 0776",
    "sg:postcode":"LS10 2AR",
    "sg:province":"West Yorkshire",
    "sg:tags":[
        "pubs",
        "house",
        "inn",
        "public",
        "activity"
    ],
    "wof:name":"Penny Hill",
    "wof:placetype":"venue"
},
  "geometry": {"coordinates":[-1.529759,53.778027],"type":"Point"}
}