{
  "type": "Feature",
  "properties": {
    "addr:full":"53 Central Rd Worcester Park Surrey KT4 8EB",
    "addr:housenumber":"53",
    "addr:postcode":"kt4 8eb",
    "addr:street":"Central Rd",
    "iso:country":"GB",
    "sg:address":"53 Central Rd",
    "sg:city":"Worcester Park",
    "sg:classifiers":[
        {
            "category":"Manufacturing",
            "subcategory":"Textiles",
            "type":"Manufacturing & Wholesale Goods"
        }
    ],
    "sg:phone":"+44 20 8337 7007",
    "sg:postcode":"KT4 8EB",
    "sg:province":"Surrey",
    "sg:tags":[
        "made-up"
    ],
    "wof:name":"Beds To Go",
    "wof:placetype":"venue"
},
  "geometry": {"coordinates":[-0.2397959977,51.377494812],"type":"Point"}
}