{
  "type": "Feature",
  "properties": {
    "iso:country":"GB",
    "sg:address":"Waldot Service Station, Middlewood Road",
    "sg:city":"Sheffield",
    "sg:classifiers":[
        {
            "category":"Autos & Motor Vehicles",
            "subcategory":"Automobile Sales",
            "type":"Retail Goods"
        }
    ],
    "sg:postcode":"S6 1TF",
    "sg:province":"South Yorkshire",
    "sg:tags":[
        "car"
    ],
    "wof:name":"Gilder Volkswagen Ltd.",
    "wof:placetype":"venue"
},
  "geometry": {"coordinates":[-1.50502,53.411171],"type":"Point"}
}