{
  "type": "Feature",
  "properties": {
    "iso:country":"GB",
    "sg:address":"57 High St, Hinderwell",
    "sg:city":"Saltburn By The Sea",
    "sg:classifiers":[
        {
            "category":"Health Services",
            "subcategory":"Dentist",
            "type":"Services"
        }
    ],
    "sg:phone":"+44 1947 841249",
    "sg:postcode":"TS13 5ET",
    "sg:province":"North Yorkshire",
    "wof:name":"C.H Bee",
    "wof:placetype":"venue"
},
  "geometry": {"coordinates":[-0.7749469876,54.5395088196],"type":"Point"}
}