{
  "type": "Feature",
  "properties": {
    "addr:full":"Unit Su 5, The Wheatsheaf Centre Rochdale Lancashire OL16 1JZ",
    "addr:housenumber":"5",
    "addr:postcode":"ol16 1jz",
    "addr:street":"The;Rochdale",
    "iso:country":"GB",
    "sg:address":"Unit Su 5, The Wheatsheaf Centre",
    "sg:city":"Rochdale",
    "sg:classifiers":[
        {
            "category":"Shopping",
            "subcategory":"Gifts & Souvenirs",
            "type":"Retail Goods"
        }
    ],
    "sg:phone":"+44 1706 526452",
    "sg:postcode":"OL16 1JZ",
    "sg:province":"Lancashire",
    "sg:tags":[
        "poster",
        "card"
    ],
    "wof:name":"Athena",
    "wof:placetype":"venue"
},
  "geometry": {"coordinates":[-2.1556499004,53.6184806824],"type":"Point"}
}