{
  "type": "Feature",
  "properties": {
    "iso:country":"GB",
    "sg:address":"35 Bexhill Rd",
    "sg:city":"St Leonards-on-sea",
    "sg:classifiers":[
        {
            "category":"Building & Trades",
            "subcategory":"Construction",
            "type":"Services"
        }
    ],
    "sg:postcode":"TN38 0AJ",
    "sg:province":"East Sussex",
    "sg:tags":[
        "builder"
    ],
    "wof:name":"L & M Builders",
    "wof:placetype":"venue"
},
  "geometry": {"coordinates":[0.536525,50.851093],"type":"Point"}
}