{
  "type": "Feature",
  "properties": {
    "addr:full":"22 Oakdale Terrace Chester-le-street Durham DH3 3DH",
    "addr:housenumber":"22",
    "addr:postcode":"dh3 3dh",
    "addr:street":"Oakdale Terrace",
    "iso:country":"GB",
    "sg:address":"22 Oakdale Terrace",
    "sg:city":"Chester-le-street",
    "sg:classifiers":[
        {
            "category":"Health Services",
            "subcategory":"Chiropractor",
            "type":"Services"
        }
    ],
    "sg:phone":"+44 191 389 1866",
    "sg:postcode":"DH3 3DH",
    "sg:province":"Durham",
    "wof:name":"Clinic 1",
    "wof:placetype":"venue"
},
  "geometry": {"coordinates":[-1.5749640465,54.8591346741],"type":"Point"}
}