{
  "type": "Feature",
  "properties": {
    "iso:country":"GB",
    "sg:address":"86 Worcester Walk",
    "sg:city":"Birmingham",
    "sg:classifiers":[
        {
            "category":"Professional",
            "subcategory":"Art Services",
            "type":"Services"
        }
    ],
    "sg:postcode":"B37 5NZ",
    "sg:province":"West Midlands",
    "sg:tags":[
        "photographer"
    ],
    "wof:name":"Whitlock Photography",
    "wof:placetype":"venue"
},
  "geometry": {"coordinates":[-1.7527389526,52.4722442627],"type":"Point"}
}