{
  "type": "Feature",
  "properties": {
    "addr:full":"Barton House, 28 Wimpole Road, Barton Cambridge Cambridgeshire CB3 7AB",
    "addr:housenumber":"28",
    "addr:postcode":"cb3 7ab",
    "addr:street":"Wimpole Road",
    "iso:country":"GB",
    "sg:address":"Barton House, 28 Wimpole Road, Barton",
    "sg:city":"Cambridge",
    "sg:classifiers":[
        {
            "category":"Real Estate",
            "subcategory":"Surveying",
            "type":"Services"
        }
    ],
    "sg:phone":"+44 1223 264044",
    "sg:postcode":"CB3 7AB",
    "sg:province":"Cambridgeshire",
    "sg:tags":[
        "surveyor",
        "quantity"
    ],
    "wof:name":"T P Associates Ltd.",
    "wof:placetype":"venue"
},
  "geometry": {"coordinates":[-0.012662,52.1597175598],"type":"Point"}
}