{
  "type": "Feature",
  "properties": {
    "iso:country":"GB",
    "sg:address":"62 Turners Hill",
    "sg:city":"Waltham Cross",
    "sg:classifiers":[
        {
            "category":"Banks & Credit Unions",
            "subcategory":"Bank",
            "type":"Services"
        }
    ],
    "sg:phone":"+44 20 8805 7000",
    "sg:postcode":"EN8 8LH",
    "sg:province":"Essex",
    "wof:name":"NatWest",
    "wof:placetype":"venue"
},
  "geometry": {"coordinates":[-0.034485,51.701527],"type":"Point"}
}