{
  "type": "Feature",
  "properties": {
    "addr:full":"Mcmillan House, 54 Cheam Common Road Worcester Park Surrey KT4 8RH",
    "addr:housenumber":"54",
    "addr:postcode":"kt4 8rh",
    "addr:street":"Cheam Common Road",
    "iso:country":"GB",
    "sg:address":"Mcmillan House, 54 Cheam Common Road",
    "sg:city":"Worcester Park",
    "sg:classifiers":[
        {
            "category":"Shopping",
            "subcategory":"Stationery & Office Supplies",
            "type":"Retail Goods"
        }
    ],
    "sg:phone":"+44 20 8337 3333",
    "sg:postcode":"KT4 8RH",
    "sg:province":"Surrey",
    "sg:tags":[
        "equipment",
        "school"
    ],
    "wof:name":"The Consortium for Purchasing & Distribution",
    "wof:placetype":"venue"
},
  "geometry": {"coordinates":[-0.230376,51.372478],"type":"Point"}
}