{
  "type": "Feature",
  "properties": {
    "iso:country":"GB",
    "sg:address":"Broombank Park",
    "sg:city":"Chesterfield",
    "sg:classifiers":[
        {
            "category":"Wholesale",
            "subcategory":"Scrap",
            "type":"Manufacturing & Wholesale Goods"
        }
    ],
    "sg:phone":"+44 1246 452226",
    "sg:postcode":"S41 9RT",
    "sg:province":"Derbyshire",
    "sg:tags":[
        "waste",
        "metal"
    ],
    "wof:name":"Chesterfield Recycling Centre",
    "wof:placetype":"venue"
},
  "geometry": {"coordinates":[-1.449493,53.271336],"type":"Point"}
}