{
  "type": "Feature",
  "properties": {
    "addr:full":"306-314 Poplar High Street London Greater London E14 0BB",
    "addr:housenumber":"306-314",
    "addr:postcode":"e14 0bb",
    "addr:street":"Poplar High Street",
    "iso:country":"GB",
    "sg:address":"306-314 Poplar High Street",
    "sg:city":"London",
    "sg:classifiers":[
        {
            "category":"Retail",
            "subcategory":"Auto Repair",
            "type":"Services"
        }
    ],
    "sg:phone":"+44 20 7515 9099",
    "sg:postcode":"E14 0BB",
    "sg:province":"Greater London",
    "sg:tags":[
        "modification",
        "garage"
    ],
    "wof:name":"Dockland Service Centre Ltd.",
    "wof:placetype":"venue"
},
  "geometry": {"coordinates":[-0.009786,51.50869],"type":"Point"}
}