{
  "type": "Feature",
  "properties": {
    "addr:full":"Unit 2b, Shawcross Industrial Park, Ackworth Road Portsmouth Hampshire PO3 5JP",
    "addr:housenumber":"unit 2b",
    "addr:postcode":"hampshire po3 5jp",
    "addr:street":"Shawcross Industrial Park Ackworth Road",
    "iso:country":"GB",
    "sg:address":"Unit 2b, Shawcross Industrial Park, Ackworth Road",
    "sg:city":"Portsmouth",
    "sg:classifiers":[
        {
            "category":"Building & Trades",
            "subcategory":"Construction",
            "type":"Services"
        },
        {
            "category":"Home & Garden",
            "subcategory":"Furniture",
            "type":"Retail Goods"
        }
    ],
    "sg:phone":"+44 1243 574573",
    "sg:postcode":"PO3 5JP",
    "sg:province":"Hampshire",
    "sg:tags":[
        "decorator",
        "painter"
    ],
    "wof:name":"Mr Picketts Paint Stripping Service",
    "wof:placetype":"venue"
},
  "geometry": {"coordinates":[-1.0599600077,50.8339118958],"type":"Point"}
}