{
  "type": "Feature",
  "properties": {
    "addr:full":"The Cottage Dassels, Braughing Ware Hertfordshire SG11 2RP",
    "addr:postcode":"sg11 2rp",
    "addr:street":"Dassels",
    "iso:country":"GB",
    "sg:address":"The Cottage Dassels, Braughing",
    "sg:city":"Ware",
    "sg:classifiers":[
        {
            "category":"Real Estate",
            "subcategory":"Surveying",
            "type":"Services"
        }
    ],
    "sg:phone":"+44 1763 289999",
    "sg:postcode":"SG11 2RP",
    "sg:province":"Hertfordshire",
    "sg:tags":[
        "surveyor",
        "valuer"
    ],
    "sg:website":"http://www.dgwco-surveyors.com",
    "wof:name":"David G Williamson & Co",
    "wof:placetype":"venue"
},
  "geometry": {"coordinates":[0.03096,51.908604],"type":"Point"}
}