{
  "type": "Feature",
  "properties": {
    "addr:full":"20-22 Craven Road London Greater London W2 3PX",
    "addr:housenumber":"20-22",
    "addr:postcode":"w2 3px",
    "addr:street":"Craven Road",
    "iso:country":"GB",
    "sg:address":"20-22 Craven Road",
    "sg:city":"London",
    "sg:classifiers":[
        {
            "category":"Organizations",
            "subcategory":"Community Association",
            "type":"Services"
        }
    ],
    "sg:phone":"+44 20 7724 5840",
    "sg:postcode":"W2 3PX",
    "sg:province":"Greater London",
    "sg:tags":[
        "society",
        "housing"
    ],
    "wof:name":"St.Johns Housing Association",
    "wof:placetype":"venue"
},
  "geometry": {"coordinates":[-0.177361,51.514809],"type":"Point"}
}