{
  "type": "Feature",
  "properties": {
    "iso:country":"GB",
    "sg:address":"5 Blackwood Rise, Cookridge",
    "sg:city":"Leeds",
    "sg:classifiers":[
        {
            "category":"Home & Garden",
            "subcategory":"Building Materials",
            "type":"Retail Goods"
        }
    ],
    "sg:phone":"+44 113 261 0006",
    "sg:postcode":"LS16 7BG",
    "sg:province":"West Yorkshire",
    "sg:tags":[
        "insulation",
        "installers"
    ],
    "wof:name":"Revive",
    "wof:placetype":"venue"
},
  "geometry": {"coordinates":[-1.625609,53.848892],"type":"Point"}
}