{
  "type": "Feature",
  "properties": {
    "iso:country":"GB",
    "sg:address":"118 Ewell Road",
    "sg:city":"Surbiton",
    "sg:classifiers":[
        {
            "category":"Home & Garden",
            "subcategory":"Kitchen Supply",
            "type":"Retail Goods"
        }
    ],
    "sg:phone":"+44 20 8399 0123",
    "sg:postcode":"KT6 6HA",
    "sg:province":"Surrey",
    "sg:tags":[
        "equipment",
        "catering"
    ],
    "wof:name":"Immediate Catering Supplies Ltd.",
    "wof:placetype":"venue"
},
  "geometry": {"coordinates":[-0.298,51.389923],"type":"Point"}
}