{
  "type": "Feature",
  "properties": {
    "addr:full":"Blackpool And Fylde Ind Est, Brunell Way Blackpool Lancashire FY4 5NP",
    "addr:housenumber":"est",
    "addr:postcode":"fy4 5np",
    "addr:street":"Brunell Way",
    "iso:country":"GB",
    "sg:address":"Blackpool And Fylde Ind Est, Brunell Way",
    "sg:city":"Blackpool",
    "sg:classifiers":[
        {
            "category":"Wholesale",
            "subcategory":"Non-durable Goods",
            "type":"Manufacturing & Wholesale Goods"
        }
    ],
    "sg:phone":"+44 1253 791989",
    "sg:postcode":"FY4 5NP",
    "sg:province":"Lancashire",
    "sg:tags":[
        "carry",
        "wholesaler",
        "cash"
    ],
    "wof:name":"Booker Cash & Carry Ltd",
    "wof:placetype":"venue"
},
  "geometry": {"coordinates":[-3.0002501011,53.7933616638],"type":"Point"}
}