{
  "type": "Feature",
  "properties": {
    "iso:country":"GB",
    "sg:address":"Gamble Rd",
    "sg:city":"Thornton Cleveleys",
    "sg:classifiers":[
        {
            "category":"Bars & Pubs",
            "type":"Food & Drink"
        },
        {
            "category":"Community Center",
            "subcategory":"Social",
            "type":"Public Place"
        }
    ],
    "sg:phone":"+44 1253 852954",
    "sg:postcode":"FY5 4JF",
    "sg:province":"Lancashire",
    "sg:tags":[
        "pubs",
        "house",
        "inn",
        "activity"
    ],
    "wof:name":"Burn Naze",
    "wof:placetype":"venue"
},
  "geometry": {"coordinates":[-3.009709,53.887424],"type":"Point"}
}