{
  "type": "Feature",
  "properties": {
    "addr:full":"2 The Flat, Apollonia House, Elysian Fields, Vicarage Road Sidmouth Devon EX10 8UH",
    "addr:housenumber":"2;apollonia;elysian",
    "addr:postcode":"ex10 8uh",
    "addr:street":"The Flat;Vicarage Road",
    "iso:country":"GB",
    "sg:address":"2 The Flat, Apollonia House, Elysian Fields, Vicarage Road",
    "sg:city":"Sidmouth",
    "sg:classifiers":[
        {
            "category":"Health Services",
            "subcategory":"Dentist",
            "type":"Services"
        }
    ],
    "sg:phone":"+44 1395 513333",
    "sg:postcode":"EX10 8UH",
    "sg:province":"Devon",
    "wof:name":"APPOLONIA HOUSE DENTAL SURGERY",
    "wof:placetype":"venue"
},
  "geometry": {"coordinates":[-3.2396199703,50.6850814819],"type":"Point"}
}