{
  "type": "Feature",
  "properties": {
    "addr:full":"The White House, Chantry Lane York North Yorkshire YO23 2GF",
    "addr:postcode":"yo23 2gf",
    "addr:street":"Chantry Lane",
    "iso:country":"GB",
    "sg:address":"The White House, Chantry Lane",
    "sg:city":"York",
    "sg:classifiers":[
        {
            "category":"Shopping",
            "subcategory":"Pharmacy",
            "type":"Retail Goods"
        }
    ],
    "sg:phone":"+44 1904 702704",
    "sg:postcode":"YO23 2GF",
    "sg:province":"North Yorkshire",
    "sg:tags":[
        "pharmacist",
        "chemist"
    ],
    "wof:name":"F W Wood & Son (York) Ltd.",
    "wof:placetype":"venue"
},
  "geometry": {"coordinates":[-1.092949,53.922165],"type":"Point"}
}