{
  "type": "Feature",
  "properties": {
    "iso:country":"GB",
    "sg:address":"352 Chanterlands Avenue",
    "sg:city":"Hull",
    "sg:classifiers":[
        {
            "category":"Professional",
            "type":"Services"
        }
    ],
    "sg:postcode":"HU5 4ED",
    "sg:province":"East Riding of Yorkshire",
    "sg:tags":[
        "repair",
        "tech",
        "maintenance"
    ],
    "wof:name":"Computer Printer Repairs",
    "wof:placetype":"venue"
},
  "geometry": {"coordinates":[-0.3720940053,53.7627296448],"type":"Point"}
}