{
  "type": "Feature",
  "properties": {
    "addr:full":"Wingrove House, Alnwick Moor Alnwick Northumberland NE66 2AG",
    "addr:postcode":"ne66 2ag",
    "addr:street":"Alnwick Moor",
    "iso:country":"GB",
    "sg:address":"Wingrove House, Alnwick Moor",
    "sg:city":"Alnwick",
    "sg:classifiers":[
        {
            "category":"Wholesale",
            "subcategory":"Scrap",
            "type":"Manufacturing & Wholesale Goods"
        }
    ],
    "sg:phone":"+44 1665 606661",
    "sg:postcode":"NE66 2AG",
    "sg:province":"Northumberland",
    "sg:tags":[
        "car",
        "breaker",
        "dismantlers"
    ],
    "wof:name":"Bits",
    "wof:placetype":"venue"
},
  "geometry": {"coordinates":[-1.703514,55.412601],"type":"Point"}
}