{
  "type": "Feature",
  "properties": {
    "addr:full":"167 London Road, Holybourne Alton Hampshire GU34 4HB",
    "addr:housenumber":"167",
    "addr:postcode":"gu34 4hb",
    "addr:street":"London Road",
    "iso:country":"GB",
    "sg:address":"167 London Road, Holybourne",
    "sg:city":"Alton",
    "sg:classifiers":[
        {
            "category":"Home & Garden",
            "subcategory":"Hardware",
            "type":"Retail Goods"
        }
    ],
    "sg:phone":"+44 1420 84458",
    "sg:postcode":"GU34 4HB",
    "sg:province":"Hampshire",
    "sg:tags":[
        "lawnmowers",
        "machinery"
    ],
    "wof:name":"Allison & Garwood Ltd.",
    "wof:placetype":"venue"
},
  "geometry": {"coordinates":[-0.946039,51.16452],"type":"Point"}
}