{
  "type": "Feature",
  "properties": {
    "addr:full":"Bow Street Chambers, 1-2 Bow Street Rugeley Staffordshire WS15 2BT",
    "addr:housenumber":"1-2",
    "addr:postcode":"ws15 2bt",
    "addr:street":"Bow Street;Bow Street",
    "iso:country":"GB",
    "sg:address":"Bow Street Chambers, 1-2 Bow Street",
    "sg:city":"Rugeley",
    "sg:classifiers":[
        {
            "category":"Professional",
            "subcategory":"Accounting & Tax Preparation",
            "type":"Services"
        }
    ],
    "sg:phone":"+44 1889 578824",
    "sg:postcode":"WS15 2BT",
    "sg:province":"Staffordshire",
    "sg:tags":[
        "accountant"
    ],
    "wof:name":"M J Accountancy Services",
    "wof:placetype":"venue"
},
  "geometry": {"coordinates":[-1.935352,52.757557],"type":"Point"}
}