{
  "type": "Feature",
  "properties": {
    "addr:full":"64 Garstang Road South, Wesham Preston Lancashire PR4 3BL",
    "addr:housenumber":"64",
    "addr:postcode":"pr4 3bl",
    "addr:street":"Garstang Road South Wesham",
    "iso:country":"GB",
    "sg:address":"64 Garstang Road South, Wesham",
    "sg:city":"Preston",
    "sg:classifiers":[
        {
            "category":"Banks & Credit Unions",
            "subcategory":"Bureau De Change",
            "type":"Services"
        },
        {
            "category":"Food & Beverages",
            "subcategory":"Liquor & Beverages",
            "type":"Retail Goods"
        }
    ],
    "sg:phone":"+44 1772 684256",
    "sg:postcode":"PR4 3BL",
    "sg:province":"Lancashire",
    "sg:tags":[
        "beer",
        "wine",
        "spirit",
        "wines"
    ],
    "wof:name":"Booze Buster",
    "wof:placetype":"venue"
},
  "geometry": {"coordinates":[-2.8866760731,53.7911453247],"type":"Point"}
}