{
  "type": "Feature",
  "properties": {
    "addr:full":"11a Abbott St Heanor Derbyshire DE75 7QD",
    "addr:housenumber":"11a",
    "addr:postcode":"de75 7qd",
    "addr:street":"Abbott St",
    "iso:country":"GB",
    "sg:address":"11a Abbott St",
    "sg:city":"Heanor",
    "sg:classifiers":[
        {
            "category":"Shopping",
            "subcategory":"Clothing, Apparel, & Fashions",
            "type":"Retail Goods"
        }
    ],
    "sg:phone":"+44 1773 764868",
    "sg:postcode":"DE75 7QD",
    "sg:province":"Derbyshire",
    "sg:tags":[
        "clothing"
    ],
    "wof:name":"Ashleywear International",
    "wof:placetype":"venue"
},
  "geometry": {"coordinates":[-1.358175,53.013111],"type":"Point"}
}