{
  "type": "Feature",
  "properties": {
    "addr:full":"Unit 24 Brampton Road, Longtown Carlisle Cumbria CA6 5TR",
    "addr:housenumber":"unit 24",
    "addr:postcode":"ca6 5tr",
    "addr:street":"Brampton Road",
    "iso:country":"GB",
    "sg:address":"Unit 24 Brampton Road, Longtown",
    "sg:city":"Carlisle",
    "sg:classifiers":[
        {
            "category":"Wholesale",
            "subcategory":"Scrap",
            "type":"Manufacturing & Wholesale Goods"
        }
    ],
    "sg:phone":"+44 1228 791115",
    "sg:postcode":"CA6 5TR",
    "sg:province":"Cumbria",
    "sg:tags":[
        "salvage"
    ],
    "wof:name":"Thompson's Auto Salvage",
    "wof:placetype":"venue"
},
  "geometry": {"coordinates":[-2.9694559574,55.0072631836],"type":"Point"}
}