{
  "type": "Feature",
  "properties": {
    "iso:country":"GB",
    "sg:address":"Unit 1",
    "sg:city":"Boston",
    "sg:classifiers":[
        {
            "category":"Shopping",
            "subcategory":"Crafts & Fabrics",
            "type":"Retail Goods"
        }
    ],
    "sg:phone":"+44 1205 360888",
    "sg:postcode":"PE22 7DJ",
    "sg:province":"Lincolnshire",
    "sg:tags":[
        "shop"
    ],
    "wof:name":"Ashcroft Fabrics Ltd.",
    "wof:placetype":"venue"
},
  "geometry": {"coordinates":[-0.078199,53.096001],"type":"Point"}
}