{
  "type": "Feature",
  "properties": {
    "addr:full":"6 High Street Buxton Derbyshire SK17 6EU",
    "addr:housenumber":"6",
    "addr:postcode":"sk17 6eu",
    "addr:street":"High Street",
    "iso:country":"GB",
    "sg:address":"6 High Street",
    "sg:city":"Buxton",
    "sg:classifiers":[
        {
            "category":"Real Estate",
            "subcategory":"Real Estate Agent",
            "type":"Services"
        }
    ],
    "sg:phone":"+44 1298 24357",
    "sg:postcode":"SK17 6EU",
    "sg:province":"Derbyshire",
    "wof:name":"Lady Estates",
    "wof:placetype":"venue"
},
  "geometry": {"coordinates":[-1.915474,53.255077],"type":"Point"}
}