{
  "type": "Feature",
  "properties": {
    "iso:country":"GB",
    "sg:address":"Old Skene Rd, Skene",
    "sg:city":"Westhill",
    "sg:classifiers":[
        {
            "category":"Sports & Exercise",
            "subcategory":"Stables",
            "type":"Entertainment"
        }
    ],
    "sg:postcode":"AB32 6RP",
    "sg:province":"Aberdeen City",
    "sg:tags":[
        "education",
        "equestrian"
    ],
    "wof:name":"Broadshade Livery Stables",
    "wof:placetype":"venue"
},
  "geometry": {"coordinates":[-2.292684,57.149445],"type":"Point"}
}