{
  "type": "Feature",
  "properties": {
    "iso:country":"GB",
    "sg:address":"Woodlands, Waddington Close",
    "sg:city":"Bury",
    "sg:classifiers":[
        {
            "category":"Building & Trades",
            "subcategory":"Cleaning & Sanitation",
            "type":"Services"
        }
    ],
    "sg:postcode":"BL8 2JB",
    "sg:province":"Lancashire",
    "sg:tags":[
        "door",
        "manufacturer"
    ],
    "wof:name":"Portiere Architectural Systems Ltd.",
    "wof:placetype":"venue"
},
  "geometry": {"coordinates":[-2.341657,53.593304],"type":"Point"}
}