{
  "type": "Feature",
  "properties": {
    "addr:full":"29 Birchy Clo, Shirley Solihull West Midlands B90 1QL",
    "addr:housenumber":"29",
    "addr:postcode":"b90 1ql",
    "addr:street":"Birchy Clo",
    "iso:country":"GB",
    "sg:address":"29 Birchy Clo, Shirley",
    "sg:city":"Solihull",
    "sg:classifiers":[
        {
            "category":"Retail",
            "subcategory":"Auto Repair",
            "type":"Services"
        }
    ],
    "sg:phone":"+44 1564 823006",
    "sg:postcode":"B90 1QL",
    "sg:province":"West Midlands",
    "sg:tags":[
        "modification",
        "garage",
        "electrician"
    ],
    "wof:name":"Hinks,David,",
    "wof:placetype":"venue"
},
  "geometry": {"coordinates":[-1.8432379961,52.3854293823],"type":"Point"}
}