{
  "type": "Feature",
  "properties": {
    "iso:country":"GB",
    "sg:address":"Chapmans Hill Farm, Green Lane, Chapmans Hill",
    "sg:city":"Halesowen",
    "sg:classifiers":[
        {
            "category":"Farming",
            "subcategory":"Dairy Farm",
            "type":"Manufacturing & Wholesale Goods"
        }
    ],
    "sg:postcode":"B62 0HB",
    "sg:province":"West Midlands",
    "wof:name":"Tom William Jones",
    "wof:placetype":"venue"
},
  "geometry": {"coordinates":[-2.048331,52.400799],"type":"Point"}
}