{
  "type": "Feature",
  "properties": {
    "addr:full":"55 Southfield Road Huddersfield West Yorkshire HD5 8SA",
    "addr:housenumber":"55",
    "addr:postcode":"hd5 8sa",
    "addr:street":"Southfield Road",
    "iso:country":"GB",
    "sg:address":"55 Southfield Road",
    "sg:city":"Huddersfield",
    "sg:classifiers":[
        {
            "category":"Home & Garden",
            "subcategory":"Home Furnishings",
            "type":"Retail Goods"
        }
    ],
    "sg:phone":"+44 1484 429773",
    "sg:postcode":"HD5 8SA",
    "sg:province":"West Yorkshire",
    "sg:tags":[
        "blind",
        "curtain",
        "fitting"
    ],
    "wof:name":"Anne Keen Soft Furnishings",
    "wof:placetype":"venue"
},
  "geometry": {"coordinates":[-1.745571,53.636707],"type":"Point"}
}