{
  "type": "Feature",
  "properties": {
    "iso:country":"GB",
    "sg:address":"3-5 Kelsey Park Rd",
    "sg:city":"Beckenham",
    "sg:classifiers":[
        {
            "category":"Building & Trades",
            "subcategory":"Landscaping Services",
            "type":"Services"
        }
    ],
    "sg:phone":"+44 20 8658 4455",
    "sg:postcode":"BR3 6LH",
    "sg:province":"Kent",
    "sg:tags":[
        "landscape",
        "contractor"
    ],
    "wof:name":"Architectural Landscape Design Ltd",
    "wof:placetype":"venue"
},
  "geometry": {"coordinates":[-0.025288,51.407505],"type":"Point"}
}