{
  "type": "Feature",
  "properties": {
    "addr:full":"27 Greendykes Road Broxburn City of Edinburgh EH52 5AF",
    "addr:housenumber":"27",
    "addr:postcode":"eh52 5af",
    "addr:street":"Greendykes Road",
    "iso:country":"GB",
    "sg:address":"27 Greendykes Road",
    "sg:city":"Broxburn",
    "sg:classifiers":[
        {
            "category":"Personal",
            "subcategory":"Beauty Salon",
            "type":"Services"
        }
    ],
    "sg:phone":"+44 1506 857123",
    "sg:postcode":"EH52 5AF",
    "sg:province":"City of Edinburgh",
    "sg:tags":[
        "unisex",
        "hairdresser"
    ],
    "wof:name":"Utopia",
    "wof:placetype":"venue"
},
  "geometry": {"coordinates":[-3.4698939323,55.9350395203],"type":"Point"}
}