{
  "type": "Feature",
  "properties": {
    "addr:full":"43 Market Street Bridgend Bridgend CF31 1LJ",
    "addr:housenumber":"43",
    "addr:postcode":"cf31 1lj",
    "addr:street":"Market Street",
    "iso:country":"GB",
    "sg:address":"43 Market Street",
    "sg:city":"Bridgend",
    "sg:classifiers":[
        {
            "category":"Manufacturing",
            "subcategory":"Tools & Machinery",
            "type":"Manufacturing & Wholesale Goods"
        },
        {
            "category":"Insurance",
            "subcategory":"Insurance Agent",
            "type":"Services"
        }
    ],
    "sg:phone":"+44 1656 662488",
    "sg:postcode":"CF31 1LJ",
    "sg:province":"Bridgend",
    "sg:tags":[
        "society",
        "friendly"
    ],
    "wof:name":"A G Insurance Services",
    "wof:placetype":"venue"
},
  "geometry": {"coordinates":[-3.579609,51.50695],"type":"Point"}
}