{
  "type": "Feature",
  "properties": {
    "iso:country":"GB",
    "sg:address":"31 Langmead Road",
    "sg:city":"Plymouth",
    "sg:classifiers":[
        {
            "category":"Building & Trades",
            "subcategory":"Construction",
            "type":"Services"
        }
    ],
    "sg:phone":"+44 1752 703051",
    "sg:postcode":"PL6 5TA",
    "sg:province":"Devon",
    "sg:tags":[
        "dry",
        "lining",
        "plasterers",
        "screeders"
    ],
    "wof:name":"Burnard Bros",
    "wof:placetype":"venue"
},
  "geometry": {"coordinates":[-4.109085,50.401131],"type":"Point"}
}