{
  "type": "Feature",
  "properties": {
    "iso:country":"GB",
    "sg:address":"2 George Street",
    "sg:city":"Batley",
    "sg:classifiers":[
        {
            "category":"Manufacturing",
            "subcategory":"Chemicals & Compounds",
            "type":"Manufacturing & Wholesale Goods"
        },
        {
            "category":"Wholesale",
            "subcategory":"Chemicals & Plastics",
            "type":"Manufacturing & Wholesale Goods"
        }
    ],
    "sg:phone":"+44 1924 423322",
    "sg:postcode":"WF17 5AU",
    "sg:province":"West Yorkshire",
    "sg:tags":[
        "product",
        "allied"
    ],
    "wof:name":"Harlow Chemical Co. Ltd.",
    "wof:placetype":"venue"
},
  "geometry": {"coordinates":[-1.6300979853,53.7112770081],"type":"Point"}
}