{
  "type": "Feature",
  "properties": {
    "addr:full":"Room 24 Routemaster Building, Walton Avenue Felixstowe Suffolk IP11 3HE",
    "addr:housenumber":"24;building",
    "addr:postcode":"ip11 3he",
    "addr:street":"Walton Avenue",
    "iso:country":"GB",
    "sg:address":"Room 24 Routemaster Building, Walton Avenue",
    "sg:city":"Felixstowe",
    "sg:classifiers":[
        {
            "category":"Military Area",
            "subcategory":"Air Force Base",
            "type":"Public Place"
        }
    ],
    "sg:postcode":"IP11 3HE",
    "sg:province":"Suffolk",
    "sg:tags":[
        "taxi",
        "hire",
        "private"
    ],
    "wof:name":"A A A Airport Taxis",
    "wof:placetype":"venue"
},
  "geometry": {"coordinates":[1.3424650431,51.9613685608],"type":"Point"}
}