{
  "type": "Feature",
  "properties": {
    "iso:country":"GB",
    "sg:address":"6a Agincourt Street",
    "sg:city":"Monmouth",
    "sg:classifiers":[
        {
            "category":"Personal",
            "subcategory":"Beauty Salon",
            "type":"Services"
        }
    ],
    "sg:phone":"+44 1600 715975",
    "sg:postcode":"NP25 3DZ",
    "sg:province":"Gloucestershire",
    "sg:tags":[
        "unisex",
        "hairdresser"
    ],
    "wof:name":"Profile",
    "wof:placetype":"venue"
},
  "geometry": {"coordinates":[-2.7147018909,51.8114624023],"type":"Point"}
}