{
  "type": "Feature",
  "properties": {
    "iso:country":"GB",
    "sg:address":"358 Otley Road",
    "sg:city":"Bradford",
    "sg:classifiers":[
        {
            "category":"Retail",
            "subcategory":"Veterinary Services",
            "type":"Services"
        }
    ],
    "sg:phone":"+44 1274 632222",
    "sg:postcode":"BD2 4QR",
    "sg:province":"West Yorkshire",
    "sg:tags":[
        "surgeon"
    ],
    "wof:name":"Northcote Veterinary Surgery",
    "wof:placetype":"venue"
},
  "geometry": {"coordinates":[-1.731146,53.807964],"type":"Point"}
}