{
  "type": "Feature",
  "properties": {
    "addr:full":"Church Lane, Corley Coventry Warwickshire CV7 8BA",
    "addr:postcode":"cv7 8ba",
    "addr:street":"Church Lane",
    "iso:country":"GB",
    "sg:address":"Church Lane, Corley",
    "sg:city":"Coventry",
    "sg:classifiers":[
        {
            "category":"Shopping",
            "subcategory":"Optician",
            "type":"Retail Goods"
        }
    ],
    "sg:postcode":"CV7 8BA",
    "sg:province":"Warwickshire",
    "wof:name":"Focus Optics",
    "wof:placetype":"venue"
},
  "geometry": {"coordinates":[-1.558937,52.464916],"type":"Point"}
}