{
  "type": "Feature",
  "properties": {
    "addr:full":"108 Clarence Rd Fleet Dorset GU13 9RS",
    "addr:housenumber":"108",
    "addr:postcode":"gu13 9rs",
    "addr:street":"Clarence Rd",
    "iso:country":"GB",
    "sg:address":"108 Clarence Rd",
    "sg:city":"Fleet",
    "sg:classifiers":[
        {
            "category":"Organizations",
            "subcategory":"Membership Organization",
            "type":"Services"
        }
    ],
    "sg:phone":"+44 1252 614087",
    "sg:postcode":"GU13 9RS",
    "sg:province":"Dorset",
    "sg:tags":[
        "club"
    ],
    "wof:name":"Royal British Legion The",
    "wof:placetype":"venue"
},
  "geometry": {"coordinates":[-0.839737,51.280273],"type":"Point"}
}