{
  "type": "Feature",
  "properties": {
    "addr:full":"354 Harwich Road Colchester Essex CO4 3HP",
    "addr:housenumber":"354",
    "addr:postcode":"co4 3hp",
    "addr:street":"Harwich Road Colchester",
    "iso:country":"GB",
    "sg:address":"354 Harwich Road",
    "sg:city":"Colchester",
    "sg:classifiers":[
        {
            "category":"Fast Food",
            "type":"Food & Drink"
        }
    ],
    "sg:postcode":"CO4 3HP",
    "sg:province":"Essex",
    "sg:tags":[
        "away",
        "take"
    ],
    "wof:name":"Cafe India",
    "wof:placetype":"venue"
},
  "geometry": {"coordinates":[0.9362919927,51.8972206116],"type":"Point"}
}