{
  "type": "Feature",
  "properties": {
    "addr:full":"Unit 10-11 Hackford Walk, 119-123 Hackford Rd Brixton Greater London SW9 0QT",
    "addr:housenumber":"unit 10-11",
    "addr:postcode":"119-123;sw9 0qt",
    "addr:street":"Hackford Walk;Hackford Rd",
    "iso:country":"GB",
    "sg:address":"Unit 10-11 Hackford Walk, 119-123 Hackford Rd",
    "sg:city":"Brixton",
    "sg:classifiers":[
        {
            "category":"Professional",
            "subcategory":"Computer Services",
            "type":"Services"
        }
    ],
    "sg:phone":"+44 20 7207 3346",
    "sg:postcode":"SW9 0QT",
    "sg:province":"Greater London",
    "sg:tags":[
        "system",
        "software"
    ],
    "wof:name":"Resolve",
    "wof:placetype":"venue"
},
  "geometry": {"coordinates":[-0.11539,51.47374],"type":"Point"}
}