{
  "type": "Feature",
  "properties": {
    "iso:country":"GB",
    "sg:address":"Old Nichol Street",
    "sg:city":"London",
    "sg:classifiers":[
        {
            "category":"Communications",
            "type":"Services"
        }
    ],
    "sg:phone":"+44 20 7613 3211",
    "sg:postcode":"E2 7HR",
    "sg:province":"Greater London",
    "sg:tags":[
        "audio-visual"
    ],
    "wof:name":"Somethin' Else Sound Directions Ltd.",
    "wof:placetype":"venue"
},
  "geometry": {"coordinates":[-0.073969,51.52491],"type":"Point"}
}