{
  "type": "Feature",
  "properties": {
    "iso:country":"GB",
    "sg:address":"Market Place",
    "sg:city":"Penzance",
    "sg:classifiers":[
        {
            "category":"Food & Beverages",
            "subcategory":"Bakery",
            "type":"Retail Goods"
        }
    ],
    "sg:phone":"+44 1736 710332",
    "sg:postcode":"TR18 2JA",
    "sg:province":"Cornwall",
    "sg:tags":[
        "baker"
    ],
    "wof:name":"Marazion Bakery",
    "wof:placetype":"venue"
},
  "geometry": {"coordinates":[-5.5368189812,50.1189422607],"type":"Point"}
}