{
  "type": "Feature",
  "properties": {
    "addr:full":"17 Cottage La Bromsgrove Worcestershire B60 1DU",
    "addr:housenumber":"17",
    "addr:postcode":"b60 1du",
    "addr:street":"Cottage La",
    "iso:country":"GB",
    "sg:address":"17 Cottage La",
    "sg:city":"Bromsgrove",
    "sg:classifiers":[
        {
            "category":"Real Estate",
            "subcategory":"Surveying",
            "type":"Services"
        }
    ],
    "sg:phone":"+44 121 445 3570",
    "sg:postcode":"B60 1DU",
    "sg:province":"Worcestershire",
    "sg:tags":[
        "surveyor",
        "quantity"
    ],
    "wof:name":"Chris Parsons",
    "wof:placetype":"venue"
},
  "geometry": {"coordinates":[-2.039267,52.366817],"type":"Point"}
}