{
  "type": "Feature",
  "properties": {
    "iso:country":"GB",
    "sg:address":"29 Ladies Lane, Hindley",
    "sg:city":"Wigan",
    "sg:classifiers":[
        {
            "category":"Professional",
            "subcategory":"Engineering",
            "type":"Services"
        }
    ],
    "sg:phone":"+44 1942 523611",
    "sg:postcode":"WN2 2QA",
    "sg:province":"Lancashire",
    "sg:tags":[
        "engineer"
    ],
    "wof:name":"Fixfast Engineers Supplies",
    "wof:placetype":"venue"
},
  "geometry": {"coordinates":[-2.576433,53.538452],"type":"Point"}
}