{
  "type": "Feature",
  "properties": {
    "addr:full":"2 Balfour Way Aylesbury Buckinghamshire HP20 1HG",
    "addr:housenumber":"2",
    "addr:postcode":"hp20 1hg",
    "addr:street":"Balfour Way",
    "iso:country":"GB",
    "sg:address":"2 Balfour Way",
    "sg:city":"Aylesbury",
    "sg:classifiers":[
        {
            "category":"Home & Garden",
            "subcategory":"Carpets & Floor Coverings",
            "type":"Retail Goods"
        }
    ],
    "sg:postcode":"HP20 1HG",
    "sg:province":"Buckinghamshire",
    "sg:tags":[
        "cleaner",
        "upholstery"
    ],
    "wof:name":"J & S Carpet & Upholstery Cleaners",
    "wof:placetype":"venue"
},
  "geometry": {"coordinates":[-0.8051720262,51.824508667],"type":"Point"}
}