{
  "type": "Feature",
  "properties": {
    "addr:full":"16 Lockton Avenue Heanor Derbyshire DE75 7EQ",
    "addr:housenumber":"16",
    "addr:postcode":"de75 7eq",
    "addr:street":"Lockton Avenue",
    "iso:country":"GB",
    "sg:address":"16 Lockton Avenue",
    "sg:city":"Heanor",
    "sg:classifiers":[
        {
            "category":"Professional",
            "subcategory":"Art Services",
            "type":"Services"
        },
        {
            "category":"Building & Trades",
            "subcategory":"Construction",
            "type":"Services"
        }
    ],
    "sg:phone":"+44 1773 718041",
    "sg:postcode":"DE75 7EQ",
    "sg:province":"Derbyshire",
    "sg:tags":[
        "decorator",
        "painter"
    ],
    "wof:name":"M Faulkner",
    "wof:placetype":"venue"
},
  "geometry": {"coordinates":[-1.3514590263,53.0088157654],"type":"Point"}
}