{
  "type": "Feature",
  "properties": {
    "addr:full":"Unit 2 & 4, Hudsons Dr, Cotteridge Birmingham West Midlands B30 3BS",
    "addr:housenumber":"unit 2 & 4",
    "addr:postcode":"b30 3bs",
    "addr:street":"Hudsons Dr",
    "iso:country":"GB",
    "sg:address":"Unit 2 & 4, Hudsons Dr, Cotteridge",
    "sg:city":"Birmingham",
    "sg:classifiers":[
        {
            "category":"Shopping",
            "subcategory":"Stationery & Office Supplies",
            "type":"Retail Goods"
        }
    ],
    "sg:phone":"+44 121 451 3054",
    "sg:postcode":"B30 3BS",
    "sg:province":"West Midlands",
    "sg:tags":[
        "equipment"
    ],
    "wof:name":"Carter,Frank,(Furniture) Ltd",
    "wof:placetype":"venue"
},
  "geometry": {"coordinates":[-1.91887,52.423229],"type":"Point"}
}