{
  "type": "Feature",
  "properties": {
    "addr:full":"Town Hall, High St Wem Shrewsbury Shropshire SY4 5DR",
    "addr:postcode":"sy4 5dr",
    "addr:street":"High St",
    "iso:country":"GB",
    "sg:address":"Town Hall, High St Wem",
    "sg:city":"Shrewsbury",
    "sg:classifiers":[
        {
            "category":"Government",
            "subcategory":"Office",
            "type":"Public Place"
        }
    ],
    "sg:phone":"+44 1939 232733",
    "sg:postcode":"SY4 5DR",
    "sg:province":"Shropshire",
    "sg:tags":[
        "local"
    ],
    "wof:name":"Wem Town Council",
    "wof:placetype":"venue"
},
  "geometry": {"coordinates":[-2.7275500298,52.8550987244],"type":"Point"}
}