{
  "type": "Feature",
  "properties": {
    "addr:full":"International Ho, Chapel Hill Huddersfield West Yorkshire HD1 3EE",
    "addr:postcode":"hd1 3ee",
    "addr:street":"Hill;West",
    "iso:country":"GB",
    "sg:address":"International Ho, Chapel Hill",
    "sg:city":"Huddersfield",
    "sg:classifiers":[
        {
            "category":"Professional",
            "subcategory":"Business Services",
            "type":"Services"
        }
    ],
    "sg:phone":"+44 1484 435569",
    "sg:postcode":"HD1 3EE",
    "sg:province":"West Yorkshire",
    "sg:tags":[
        "hospitality",
        "corporate"
    ],
    "wof:name":"Sellers Arenascene Ltd",
    "wof:placetype":"venue"
},
  "geometry": {"coordinates":[-1.782684,53.646954],"type":"Point"}
}