{
  "type": "Feature",
  "properties": {
    "addr:full":"23 St Albans Hill Hemel Hempstead Hertfordshire HP3 9NG",
    "addr:housenumber":"23",
    "addr:postcode":"hp3 9ng",
    "addr:street":"St Albans Hill",
    "iso:country":"GB",
    "sg:address":"23 St Albans Hill",
    "sg:city":"Hemel Hempstead",
    "sg:classifiers":[
        {
            "category":"Building & Trades",
            "subcategory":"Construction",
            "type":"Services"
        }
    ],
    "sg:phone":"+44 1442 245297",
    "sg:postcode":"HP3 9NG",
    "sg:province":"Hertfordshire",
    "sg:tags":[
        "roofing"
    ],
    "wof:name":"Goodchild Roofing",
    "wof:placetype":"venue"
},
  "geometry": {"coordinates":[-0.463954,51.740879],"type":"Point"}
}