{
  "type": "Feature",
  "properties": {
    "addr:full":"2 Moor Lane Lancaster Lancashire LA1 1QD",
    "addr:housenumber":"2",
    "addr:postcode":"la1 1qd",
    "addr:street":"Moor Lane",
    "iso:country":"GB",
    "sg:address":"2 Moor Lane",
    "sg:city":"Lancaster",
    "sg:classifiers":[
        {
            "category":"Restaurant",
            "type":"Food & Drink"
        },
        {
            "category":"Food & Beverages",
            "subcategory":"Bakery",
            "type":"Retail Goods"
        }
    ],
    "sg:phone":"+44 1524 36333",
    "sg:postcode":"LA1 1QD",
    "sg:province":"Lancashire",
    "sg:tags":[
        "-",
        "pizza"
    ],
    "wof:name":"Pizza Margherita Ltd",
    "wof:placetype":"venue"
},
  "geometry": {"coordinates":[-2.797759,54.049149],"type":"Point"}
}