{
  "type": "Feature",
  "properties": {
    "addr:full":"Harding St Garage, Adlington Chorley Lancashire PR6 9LU",
    "addr:postcode":"pr6 9lu",
    "addr:street":"Harding",
    "iso:country":"GB",
    "sg:address":"Harding St Garage, Adlington",
    "sg:city":"Chorley",
    "sg:classifiers":[
        {
            "category":"Government",
            "subcategory":"Department Of Motor Vehicles",
            "type":"Public Place"
        },
        {
            "category":"Retail",
            "subcategory":"Auto Repair",
            "type":"Services"
        }
    ],
    "sg:phone":"+44 1257 482507",
    "sg:postcode":"PR6 9LU",
    "sg:province":"Lancashire",
    "sg:tags":[
        "garage",
        "mechanic"
    ],
    "wof:name":"Brians Autos",
    "wof:placetype":"venue"
},
  "geometry": {"coordinates":[-2.598379,53.618244],"type":"Point"}
}