{
  "type": "Feature",
  "properties": {
    "iso:country":"GB",
    "sg:address":"Unit 1 Phoenix Workshops, Station Rd",
    "sg:city":"Colwyn Bay",
    "sg:classifiers":[
        {
            "category":"Shopping",
            "subcategory":"Jewelry",
            "type":"Retail Goods"
        }
    ],
    "sg:phone":"+44 1492 547117",
    "sg:postcode":"LL28 5EF",
    "sg:province":"Conwy",
    "sg:tags":[
        "diamond"
    ],
    "wof:name":"Geo-Research Ltd",
    "wof:placetype":"venue"
},
  "geometry": {"coordinates":[-3.7658,53.291988],"type":"Point"}
}