{
  "type": "Feature",
  "properties": {
    "iso:country":"GB",
    "sg:address":"1 Birch Villas, Hibbert La",
    "sg:city":"Stockport",
    "sg:classifiers":[
        {
            "category":"Taxi",
            "type":"Transportation"
        }
    ],
    "sg:postcode":"SK6 7NN",
    "sg:province":"Cheshire",
    "sg:tags":[
        "mini",
        "cab"
    ],
    "wof:name":"A M Adlam",
    "wof:placetype":"venue"
},
  "geometry": {"coordinates":[-2.06417,53.385571],"type":"Point"}
}