{
  "type": "Feature",
  "properties": {
    "iso:country":"GB",
    "sg:address":"35 Westgate",
    "sg:city":"Shipley",
    "sg:classifiers":[
        {
            "category":"Fast Food",
            "type":"Food & Drink"
        }
    ],
    "sg:postcode":"BD18 3QX",
    "sg:province":"West Yorkshire",
    "sg:tags":[
        "away",
        "take"
    ],
    "wof:name":"Cawood,Rosina,",
    "wof:placetype":"venue"
},
  "geometry": {"coordinates":[-1.778787,53.834736],"type":"Point"}
}