{
  "type": "Feature",
  "properties": {
    "addr:full":"Belgrave Hall, Church Road, Belgrave Leicester Leicestershire LE4 5PE",
    "addr:postcode":"le4 5pe",
    "addr:street":"Church Road",
    "iso:country":"GB",
    "sg:address":"Belgrave Hall, Church Road, Belgrave",
    "sg:city":"Leicester",
    "sg:classifiers":[
        {
            "category":"Museum",
            "type":"Entertainment"
        },
        {
            "category":"Museum",
            "subcategory":"Art Museum",
            "type":"Entertainment"
        },
        {
            "category":"Government",
            "subcategory":"Office",
            "type":"Public Place"
        }
    ],
    "sg:phone":"+44 116 266 6590",
    "sg:postcode":"LE4 5PE",
    "sg:province":"Leicestershire",
    "sg:tags":[
        "local",
        "gallery"
    ],
    "wof:name":"Leicestershire Museum",
    "wof:placetype":"venue"
},
  "geometry": {"coordinates":[-1.122364,52.655064],"type":"Point"}
}