{
  "type": "Feature",
  "properties": {
    "iso:country":"GB",
    "sg:address":"61 Buxton Road",
    "sg:city":"Leek",
    "sg:classifiers":[
        {
            "category":"Personal",
            "subcategory":"Beauty Salon",
            "type":"Services"
        }
    ],
    "sg:postcode":"ST13 6EG",
    "sg:province":"Staffordshire",
    "sg:tags":[
        "unisex",
        "hairdresser"
    ],
    "wof:name":"Russell Hair Shop",
    "wof:placetype":"venue"
},
  "geometry": {"coordinates":[-2.017499,53.10759],"type":"Point"}
}