{
  "type": "Feature",
  "properties": {
    "iso:country":"GB",
    "sg:address":"27 Huntly Street",
    "sg:city":"Aberdeen",
    "sg:classifiers":[
        {
            "category":"Shopping",
            "subcategory":"Florist",
            "type":"Retail Goods"
        }
    ],
    "sg:phone":"+44 1224 636644",
    "sg:postcode":"AB10 1TJ",
    "sg:province":"Aberdeen City",
    "wof:name":"Flower Studio",
    "wof:placetype":"venue"
},
  "geometry": {"coordinates":[-2.106859,57.145126],"type":"Point"}
}