{
  "type": "Feature",
  "properties": {
    "addr:full":"71 Manor Road, Manselton Swansea Swansea SA5 9PD",
    "addr:housenumber":"71",
    "addr:postcode":"sa5 9pd",
    "addr:street":"Manor Road Manselton",
    "iso:country":"GB",
    "sg:address":"71 Manor Road, Manselton",
    "sg:city":"Swansea",
    "sg:classifiers":[
        {
            "category":"Government",
            "subcategory":"Post Office",
            "type":"Public Place"
        }
    ],
    "sg:phone":"+44 1792 655079",
    "sg:postcode":"SA5 9PD",
    "sg:province":"Swansea",
    "wof:name":"Brondeg Post Office",
    "wof:placetype":"venue"
},
  "geometry": {"coordinates":[-3.951379,51.641392],"type":"Point"}
}