{
  "type": "Feature",
  "properties": {
    "addr:full":"Green Court, Hall Lane, Hankelow Crewe Cheshire CW3 0JB",
    "addr:postcode":"cw3 0jb",
    "addr:street":"Green Court Hall Lane",
    "iso:country":"GB",
    "sg:address":"Green Court, Hall Lane, Hankelow",
    "sg:city":"Crewe",
    "sg:classifiers":[
        {
            "category":"Building & Trades",
            "subcategory":"Construction",
            "type":"Services"
        },
        {
            "category":"Sports & Exercise",
            "subcategory":"Playing Field",
            "type":"Entertainment"
        }
    ],
    "sg:phone":"+44 1270 812112",
    "sg:postcode":"CW3 0JB",
    "sg:province":"Cheshire",
    "sg:tags":[
        "tennis",
        "court",
        "surface"
    ],
    "sg:website":"http://www.leisuresurfacescheshire.co.uk",
    "wof:name":"Leisure Surfaces (Cheshire)",
    "wof:placetype":"venue"
},
  "geometry": {"coordinates":[-2.4945669174,53.0076293945],"type":"Point"}
}