{
  "type": "Feature",
  "properties": {
    "iso:country":"GB",
    "sg:address":"5j Harmer House, 3 Harmer Street",
    "sg:city":"Gravesend",
    "sg:classifiers":[
        {
            "category":"Professional",
            "subcategory":"Engineering",
            "type":"Services"
        }
    ],
    "sg:phone":"+44 1474 536620",
    "sg:postcode":"DA12 2AP",
    "sg:province":"Kent",
    "sg:tags":[
        "consulting",
        "engineer"
    ],
    "wof:name":"C J Norman Ltd.",
    "wof:placetype":"venue"
},
  "geometry": {"coordinates":[0.37345,51.442612],"type":"Point"}
}