{
  "type": "Feature",
  "properties": {
    "iso:country":"GB",
    "sg:address":"Lock La",
    "sg:city":"Maidstone",
    "sg:classifiers":[
        {
            "category":"Museum",
            "subcategory":"Art Museum",
            "type":"Entertainment"
        }
    ],
    "sg:phone":"+44 1622 763936",
    "sg:postcode":"ME14 3AU",
    "sg:province":"Kent",
    "sg:tags":[
        "gallery"
    ],
    "wof:name":"Museum Of Kent Life Cobtree",
    "wof:placetype":"venue"
},
  "geometry": {"coordinates":[0.507543,51.29636],"type":"Point"}
}