{
  "type": "Feature",
  "properties": {
    "addr:full":"Robinsons Place, Bowness On Windermere Windermere Cumbria LA23 3DQ",
    "addr:postcode":"la23 3dq",
    "addr:street":"Bowness",
    "iso:country":"GB",
    "sg:address":"Robinsons Place, Bowness On Windermere",
    "sg:city":"Windermere",
    "sg:classifiers":[
        {
            "category":"Recreation",
            "subcategory":"Fishing",
            "type":"Entertainment"
        }
    ],
    "sg:postcode":"LA23 3DQ",
    "sg:province":"Cumbria",
    "sg:tags":[
        "angling"
    ],
    "wof:name":"Go Fishing",
    "wof:placetype":"venue"
},
  "geometry": {"coordinates":[-2.9224359989,54.3628692627],"type":"Point"}
}