{
  "type": "Feature",
  "properties": {
    "addr:full":"34 Avondale Dr Leigh On Sea Essex SS9 4HN",
    "addr:housenumber":"34",
    "addr:postcode":"ss9 4hn",
    "addr:street":"Avondale Dr",
    "iso:country":"GB",
    "sg:address":"34 Avondale Dr",
    "sg:city":"Leigh On Sea",
    "sg:classifiers":[
        {
            "category":"Personal",
            "subcategory":"Hair Removal",
            "type":"Services"
        }
    ],
    "sg:phone":"+44 1702 473425",
    "sg:postcode":"SS9 4HN",
    "sg:province":"Essex",
    "sg:tags":[
        "electrolysis"
    ],
    "wof:name":"Jennys Therapeutic Massage",
    "wof:placetype":"venue"
},
  "geometry": {"coordinates":[0.6607000232,51.5576133728],"type":"Point"}
}