{
  "type": "Feature",
  "properties": {
    "addr:full":"Samson Road, Comet Way Leicester Leicestershire LE3 3FP",
    "addr:postcode":"le3 3fp",
    "addr:street":"Samson Road Comet Way",
    "iso:country":"GB",
    "sg:address":"Samson Road, Comet Way",
    "sg:city":"Leicester",
    "sg:classifiers":[
        {
            "category":"Building & Trades",
            "subcategory":"Construction",
            "type":"Services"
        }
    ],
    "sg:postcode":"LE3 3FP",
    "sg:province":"Leicestershire",
    "sg:tags":[
        "joiner",
        "carpenter"
    ],
    "wof:name":"Doors Plus",
    "wof:placetype":"venue"
},
  "geometry": {"coordinates":[-1.2296589613,52.6199264526],"type":"Point"}
}