{
  "type": "Feature",
  "properties": {
    "iso:country":"GB",
    "sg:address":"17 Wilton Road",
    "sg:city":"London",
    "sg:classifiers":[
        {
            "category":"Arts & Performance",
            "subcategory":"Theater",
            "type":"Entertainment"
        }
    ],
    "sg:phone":"+44 20 7834 6318",
    "sg:postcode":"SW1V 1LG",
    "sg:province":"Greater London",
    "sg:tags":[
        "hall",
        "theatre",
        "concert"
    ],
    "wof:name":"Apollo Victoria Theatre",
    "wof:placetype":"venue"
},
  "geometry": {"coordinates":[-0.1425530016,51.4952316284],"type":"Point"}
}