{
  "type": "Feature",
  "properties": {
    "addr:full":"Stanhope Rd South Darlington Durham DL3 7SJ",
    "addr:postcode":"dl3 7sj",
    "addr:street":"Stanhope Rd South",
    "iso:country":"GB",
    "sg:address":"Stanhope Rd South",
    "sg:city":"Darlington",
    "sg:classifiers":[
        {
            "category":"Social Services",
            "subcategory":"Retirement Home",
            "type":"Services"
        }
    ],
    "sg:phone":"+44 1325 282983",
    "sg:postcode":"DL3 7SJ",
    "sg:province":"Durham",
    "sg:tags":[
        "residential",
        "care"
    ],
    "wof:name":"Raydaleside Residential Home",
    "wof:placetype":"venue"
},
  "geometry": {"coordinates":[-1.5630890131,54.5275382996],"type":"Point"}
}