{
  "type": "Feature",
  "properties": {
    "addr:full":"142a Caldmore Rd Walsall West Midlands WS1 3RF",
    "addr:housenumber":"142a",
    "addr:postcode":"ws1 3rf",
    "addr:street":"Caldmore Rd",
    "iso:country":"GB",
    "sg:address":"142a Caldmore Rd",
    "sg:city":"Walsall",
    "sg:classifiers":[
        {
            "category":"Retail",
            "subcategory":"Laundry & Dry Cleaning",
            "type":"Services"
        }
    ],
    "sg:postcode":"WS1 3RF",
    "sg:province":"West Midlands",
    "sg:tags":[
        "launderette"
    ],
    "wof:name":"Begum,Rokfa,",
    "wof:placetype":"venue"
},
  "geometry": {"coordinates":[-1.9822020531,52.5772857666],"type":"Point"}
}