{
  "type": "Feature",
  "properties": {
    "addr:full":"38 Wellington Road, North Weald Epping Essex CM16 6JY",
    "addr:housenumber":"38",
    "addr:postcode":"cm16 6jy",
    "addr:street":"Wellington Road North",
    "iso:country":"GB",
    "sg:address":"38 Wellington Road, North Weald",
    "sg:city":"Epping",
    "sg:classifiers":[
        {
            "category":"Health Services",
            "subcategory":"Health Practitioner",
            "type":"Services"
        }
    ],
    "sg:postcode":"CM16 6JY",
    "sg:province":"Essex",
    "sg:tags":[
        "psychotherapist"
    ],
    "wof:name":"Jemima Buller",
    "wof:placetype":"venue"
},
  "geometry": {"coordinates":[0.162446,51.713978],"type":"Point"}
}