{
  "type": "Feature",
  "properties": {
    "addr:full":"48-50 Welling High Street Welling Kent DA16 1TQ",
    "addr:housenumber":"48-50",
    "addr:postcode":"da16 1tq",
    "addr:street":"Welling High Street",
    "iso:country":"GB",
    "sg:address":"48-50 Welling High Street",
    "sg:city":"Welling",
    "sg:classifiers":[
        {
            "category":"Home & Garden",
            "subcategory":"Home Furnishings",
            "type":"Retail Goods"
        },
        {
            "category":"Building & Trades",
            "subcategory":"Construction",
            "type":"Services"
        }
    ],
    "sg:phone":"+44 20 8304 2546",
    "sg:postcode":"DA16 1TQ",
    "sg:province":"Kent",
    "sg:tags":[
        "mantelpiece",
        "fireplace"
    ],
    "wof:name":"Glowing Embers",
    "wof:placetype":"venue"
},
  "geometry": {"coordinates":[0.1111830026,51.4619178772],"type":"Point"}
}