{
  "type": "Feature",
  "properties": {
    "addr:full":"57 Garth Crescent, Ernesford Grange Coventry Warwickshire CV3 2PP",
    "addr:housenumber":"57",
    "addr:postcode":"cv3 2pp",
    "addr:street":"Garth Crescent Ernesford Grange",
    "iso:country":"GB",
    "sg:address":"57 Garth Crescent, Ernesford Grange",
    "sg:city":"Coventry",
    "sg:classifiers":[
        {
            "category":"Retail",
            "subcategory":"Auto Repair",
            "type":"Services"
        }
    ],
    "sg:phone":"+44 24 7645 0174",
    "sg:postcode":"CV3 2PP",
    "sg:province":"Warwickshire",
    "sg:tags":[
        "engine",
        "specialist",
        "garage",
        "modification",
        "car"
    ],
    "wof:name":"Mobile Service",
    "wof:placetype":"venue"
},
  "geometry": {"coordinates":[-1.462381,52.395908],"type":"Point"}
}