{
  "type": "Feature",
  "properties": {
    "iso:country":"GB",
    "sg:address":"2 Liverpool Rd, Islington",
    "sg:city":"Islington",
    "sg:classifiers":[
        {
            "category":"Travel",
            "subcategory":"Travel Agent",
            "type":"Entertainment"
        }
    ],
    "sg:phone":"+44 20 7354 0909",
    "sg:postcode":"N1 0PU",
    "sg:province":"Greater London",
    "wof:name":"Angel Travel",
    "wof:placetype":"venue"
},
  "geometry": {"coordinates":[-0.107158,51.53672],"type":"Point"}
}