{
  "type": "Feature",
  "properties": {
    "addr:full":"30 Southgate Sleaford Lincolnshire NG34 7RY",
    "addr:housenumber":"30",
    "addr:postcode":"ng34 7ry",
    "addr:street":"Southgate Sleaford",
    "iso:country":"GB",
    "sg:address":"30 Southgate",
    "sg:city":"Sleaford",
    "sg:classifiers":[
        {
            "category":"Retail",
            "subcategory":"Laundry & Dry Cleaning",
            "type":"Services"
        }
    ],
    "sg:phone":"+44 1529 303005",
    "sg:postcode":"NG34 7RY",
    "sg:province":"Lincolnshire",
    "sg:tags":[
        "alteration"
    ],
    "wof:name":"Sketchley Dry Cleaners",
    "wof:placetype":"venue"
},
  "geometry": {"coordinates":[-0.413209,52.998661],"type":"Point"}
}