{
  "type": "Feature",
  "properties": {
    "addr:full":"Boundary Park, Furtherwood Road Oldham Lancashire OL1 2PA",
    "addr:postcode":"ol1 2pa",
    "addr:street":"Boundary Park Furtherwood Road",
    "iso:country":"GB",
    "sg:address":"Boundary Park, Furtherwood Road",
    "sg:city":"Oldham",
    "sg:classifiers":[
        {
            "category":"Sports & Exercise",
            "subcategory":"Sports Center",
            "type":"Entertainment"
        }
    ],
    "sg:phone":"+44 161 652 0966",
    "sg:postcode":"OL1 2PA",
    "sg:province":"Lancashire",
    "sg:tags":[
        "shop",
        "good"
    ],
    "wof:name":"The Latique",
    "wof:placetype":"venue"
},
  "geometry": {"coordinates":[-2.1187980175,53.5507392883],"type":"Point"}
}