{
  "type": "Feature",
  "properties": {
    "iso:country":"GB",
    "sg:address":"42-44 High Rd, Leyton",
    "sg:city":"London",
    "sg:classifiers":[
        {
            "category":"Autos & Motor Vehicles",
            "subcategory":"Auto Supplies",
            "type":"Retail Goods"
        }
    ],
    "sg:phone":"+44 20 8534 8116",
    "sg:postcode":"E15 2BP",
    "sg:province":"Greater London",
    "sg:tags":[
        "tyre"
    ],
    "wof:name":"Grays Tyre & Exhaust Centres Ltd",
    "wof:placetype":"venue"
},
  "geometry": {"coordinates":[0.0226060003,51.5935211182],"type":"Point"}
}