{
  "type": "Feature",
  "properties": {
    "addr:full":"Mill St Driffield East Riding of Yorkshire YO25 7TN",
    "addr:postcode":"yo25 7tn",
    "addr:street":"Mill St",
    "iso:country":"GB",
    "sg:address":"Mill St",
    "sg:city":"Driffield",
    "sg:classifiers":[
        {
            "category":"Military Area",
            "subcategory":"Air Force Base",
            "type":"Public Place"
        }
    ],
    "sg:phone":"+44 1377 255788",
    "sg:postcode":"YO25 7TN",
    "sg:province":"East Riding of Yorkshire",
    "sg:tags":[
        "taxi",
        "hire",
        "private"
    ],
    "wof:name":"Driffield Cars",
    "wof:placetype":"venue"
},
  "geometry": {"coordinates":[-0.4363000095,54.0089683533],"type":"Point"}
}