{
  "type": "Feature",
  "properties": {
    "addr:full":"22a High St, Caterham On The Hill Caterham Surrey CR3 5UA",
    "addr:housenumber":"22a",
    "addr:postcode":"cr3 5ua",
    "addr:street":"High St",
    "iso:country":"GB",
    "sg:address":"22a High St, Caterham On The Hill",
    "sg:city":"Caterham",
    "sg:classifiers":[
        {
            "category":"Professional",
            "subcategory":"Engineering",
            "type":"Services"
        }
    ],
    "sg:phone":"+44 1883 330886",
    "sg:postcode":"CR3 5UA",
    "sg:province":"Surrey",
    "sg:tags":[
        "electrical",
        "engineer"
    ],
    "wof:name":"P.L.C Direct",
    "wof:placetype":"venue"
},
  "geometry": {"coordinates":[-0.088936,51.286629],"type":"Point"}
}