{
  "type": "Feature",
  "properties": {
    "addr:full":"43-45 South Street, Hythe Southampton Hampshire SO45 6EA",
    "addr:housenumber":"43-45",
    "addr:postcode":"so45 6ea",
    "addr:street":"South Street",
    "iso:country":"GB",
    "sg:address":"43-45 South Street, Hythe",
    "sg:city":"Southampton",
    "sg:classifiers":[
        {
            "category":"Bars & Pubs",
            "type":"Food & Drink"
        }
    ],
    "sg:phone":"+44 23 8084 2086",
    "sg:postcode":"SO45 6EA",
    "sg:province":"Hampshire",
    "sg:tags":[
        "pubs",
        "house",
        "inn",
        "public",
        "activity"
    ],
    "wof:name":"Malt & Hops",
    "wof:placetype":"venue"
},
  "geometry": {"coordinates":[-1.3982139826,50.866443634],"type":"Point"}
}