{
  "type": "Feature",
  "properties": {
    "addr:full":"7 Fern Dene, Madeley Crewe Cheshire CW3 9ER",
    "addr:housenumber":"7",
    "addr:postcode":"cw3 9er",
    "addr:street":"Fern Dene",
    "iso:country":"GB",
    "sg:address":"7 Fern Dene, Madeley",
    "sg:city":"Crewe",
    "sg:classifiers":[
        {
            "category":"Professional",
            "subcategory":"Engineering",
            "type":"Services"
        },
        {
            "category":"Building & Trades",
            "subcategory":"Electrical",
            "type":"Services"
        }
    ],
    "sg:phone":"+44 1782 750706",
    "sg:postcode":"CW3 9ER",
    "sg:province":"Cheshire",
    "sg:tags":[
        "engineer",
        "electrician",
        "contractor"
    ],
    "wof:name":"Ashton Electrical Services",
    "wof:placetype":"venue"
},
  "geometry": {"coordinates":[-2.3343179226,53.004119873],"type":"Point"}
}