{
  "type": "Feature",
  "properties": {
    "addr:full":"1 Perry Road, Continuation Of Park Row Bristol City of Bristol BS1 5BQ",
    "addr:housenumber":"1",
    "addr:postcode":"bs1 5bq",
    "addr:street":"Perry Road;Park Row",
    "iso:country":"GB",
    "sg:address":"1 Perry Road, Continuation Of Park Row",
    "sg:city":"Bristol",
    "sg:classifiers":[
        {
            "category":"Personal",
            "subcategory":"Psychics & Astrologers",
            "type":"Services"
        }
    ],
    "sg:postcode":"BS1 5BQ",
    "sg:province":"City of Bristol",
    "sg:tags":[
        "clairvoyant",
        "palmist"
    ],
    "wof:name":"Taro",
    "wof:placetype":"venue"
},
  "geometry": {"coordinates":[-2.5991950035,51.4559593201],"type":"Point"}
}