{
  "type": "Feature",
  "properties": {
    "addr:full":"65 Main Street, Newmills Dunfermline Fife KY12 8ST",
    "addr:housenumber":"65",
    "addr:postcode":"ky12 8st",
    "addr:street":"Main Street",
    "iso:country":"GB",
    "sg:address":"65 Main Street, Newmills",
    "sg:city":"Dunfermline",
    "sg:classifiers":[
        {
            "category":"Building & Trades",
            "subcategory":"Plumbing",
            "type":"Services"
        },
        {
            "category":"Shopping",
            "subcategory":"Party Supplies",
            "type":"Retail Goods"
        }
    ],
    "sg:phone":"+44 1383 881453",
    "sg:postcode":"KY12 8ST",
    "sg:province":"Fife",
    "sg:tags":[
        "inflatables",
        "castle",
        "plumber",
        "heating",
        "bouncy"
    ],
    "wof:name":"Brian Dawson",
    "wof:placetype":"venue"
},
  "geometry": {"coordinates":[-3.5316638947,56.0601730347],"type":"Point"}
}