{
  "type": "Feature",
  "properties": {
    "addr:full":"10-12 High Street, Wiveliscombe Taunton Devon TA4 2JX",
    "addr:housenumber":"10-12",
    "addr:postcode":"ta4 2jx",
    "addr:street":"High Street",
    "iso:country":"GB",
    "sg:address":"10-12 High Street, Wiveliscombe",
    "sg:city":"Taunton",
    "sg:classifiers":[
        {
            "category":"Bars & Pubs",
            "type":"Food & Drink"
        },
        {
            "category":"Community Center",
            "subcategory":"Social",
            "type":"Public Place"
        }
    ],
    "sg:phone":"+44 1984 624444",
    "sg:postcode":"TA4 2JX",
    "sg:province":"Devon",
    "sg:tags":[
        "pubs",
        "house",
        "inn",
        "activity"
    ],
    "wof:name":"The Courtyard Inn",
    "wof:placetype":"venue"
},
  "geometry": {"coordinates":[-3.3121249676,51.0416793823],"type":"Point"}
}