{
  "type": "Feature",
  "properties": {
    "addr:full":"19 Darklake View, Estover Plymouth Devon PL6 7TL",
    "addr:housenumber":"19",
    "addr:postcode":"pl6 7tl",
    "addr:street":"Darklake View Estover",
    "iso:country":"GB",
    "sg:address":"19 Darklake View, Estover",
    "sg:city":"Plymouth",
    "sg:classifiers":[
        {
            "category":"Manufacturing",
            "subcategory":"Tools & Machinery",
            "type":"Manufacturing & Wholesale Goods"
        }
    ],
    "sg:phone":"+44 1752 202066",
    "sg:postcode":"PL6 7TL",
    "sg:province":"Devon",
    "sg:tags":[
        "design",
        "maker",
        "manufacturer"
    ],
    "wof:name":"Delta Engineering",
    "wof:placetype":"venue"
},
  "geometry": {"coordinates":[-4.0990271568,50.4216003418],"type":"Point"}
}