{
  "type": "Feature",
  "properties": {
    "addr:full":"3 Kennel Terrace, Brixworth Northampton Northamptonshire NN6 9DL",
    "addr:housenumber":"3",
    "addr:postcode":"nn6 9dl",
    "addr:street":"Kennel Terrace",
    "iso:country":"GB",
    "sg:address":"3 Kennel Terrace, Brixworth",
    "sg:city":"Northampton",
    "sg:classifiers":[
        {
            "category":"Real Estate",
            "subcategory":"Architect",
            "type":"Services"
        }
    ],
    "sg:phone":"+44 1604 880294",
    "sg:postcode":"NN6 9DL",
    "sg:province":"Northamptonshire",
    "wof:name":"Myles & Sims",
    "wof:placetype":"venue"
},
  "geometry": {"coordinates":[-0.903998971,52.3291816711],"type":"Point"}
}