{
  "type": "Feature",
  "properties": {
    "iso:country":"GB",
    "sg:address":"135 High Street, Farnborough",
    "sg:city":"Orpington",
    "sg:classifiers":[
        {
            "category":"Government",
            "subcategory":"Post Office",
            "type":"Public Place"
        }
    ],
    "sg:phone":"+44 1689 852013",
    "sg:postcode":"BR6 7AZ",
    "sg:province":"Kent",
    "wof:name":"Farnborough Sub Post Office",
    "wof:placetype":"venue"
},
  "geometry": {"coordinates":[0.073009,51.359715],"type":"Point"}
}