{
  "type": "Feature",
  "properties": {
    "addr:full":"203 Long Lane, Hillingdon Uxbridge Greater London UB10 9JW",
    "addr:housenumber":"203",
    "addr:postcode":"ub10 9jw",
    "addr:street":"Long Lane",
    "iso:country":"GB",
    "sg:address":"203 Long Lane, Hillingdon",
    "sg:city":"Uxbridge",
    "sg:classifiers":[
        {
            "category":"Real Estate",
            "subcategory":"Surveying",
            "type":"Services"
        }
    ],
    "sg:phone":"+44 1895 239034",
    "sg:postcode":"UB10 9JW",
    "sg:province":"Greater London",
    "sg:tags":[
        "surveyor",
        "quantity"
    ],
    "wof:name":"B Jenkinson & Associates",
    "wof:placetype":"venue"
},
  "geometry": {"coordinates":[-0.450115,51.544228],"type":"Point"}
}