{
  "type": "Feature",
  "properties": {
    "iso:country":"GB",
    "sg:address":"Ravenswood Lodge, Stoodleigh",
    "sg:city":"Tiverton",
    "sg:classifiers":[
        {
            "category":"Professional",
            "subcategory":"Computer Services",
            "type":"Services"
        }
    ],
    "sg:postcode":"EX16 9PL",
    "sg:province":"Devon",
    "sg:tags":[
        "development",
        "system",
        "software"
    ],
    "wof:name":"Tum - Tum (U K) Ltd.",
    "wof:placetype":"venue"
},
  "geometry": {"coordinates":[-3.536477,50.960098],"type":"Point"}
}