{
  "type": "Feature",
  "properties": {
    "addr:full":"20 Oldham Road, Denshaw Oldham Lancashire OL3 5SN",
    "addr:housenumber":"20",
    "addr:postcode":"ol3 5sn",
    "addr:street":"Oldham Road Denshaw",
    "iso:country":"GB",
    "sg:address":"20 Oldham Road, Denshaw",
    "sg:city":"Oldham",
    "sg:classifiers":[
        {
            "category":"Bars & Pubs",
            "type":"Food & Drink"
        }
    ],
    "sg:phone":"+44 1457 874248",
    "sg:postcode":"OL3 5SN",
    "sg:province":"Lancashire",
    "sg:tags":[
        "pubs",
        "inn"
    ],
    "wof:name":"Printers Arms",
    "wof:placetype":"venue"
},
  "geometry": {"coordinates":[-2.042427063,53.5897331238],"type":"Point"}
}