{
  "type": "Feature",
  "properties": {
    "addr:full":"120 High Street Tillicoultry Clackmannanshire FK13 6DX",
    "addr:housenumber":"120",
    "addr:postcode":"fk13 6dx",
    "addr:street":"High Street",
    "iso:country":"GB",
    "sg:address":"120 High Street",
    "sg:city":"Tillicoultry",
    "sg:classifiers":[
        {
            "category":"Farming",
            "subcategory":"Livestock Farm",
            "type":"Manufacturing & Wholesale Goods"
        },
        {
            "category":"Shopping",
            "subcategory":"Florist",
            "type":"Retail Goods"
        }
    ],
    "sg:phone":"+44 1259 752867",
    "sg:postcode":"FK13 6DX",
    "sg:province":"Clackmannanshire",
    "sg:tags":[
        "breeder"
    ],
    "wof:name":"Wilson Flowers",
    "wof:placetype":"venue"
},
  "geometry": {"coordinates":[-3.741755,56.15337],"type":"Point"}
}