{
  "type": "Feature",
  "properties": {
    "iso:country":"GB",
    "sg:address":"Satley",
    "sg:city":"Bishop Auckland",
    "sg:classifiers":[
        {
            "category":"Professional",
            "type":"Services"
        },
        {
            "category":"Retail",
            "subcategory":"Auto Repair",
            "type":"Services"
        }
    ],
    "sg:phone":"+44 1388 730258",
    "sg:postcode":"DL13 4HT",
    "sg:province":"Durham",
    "sg:tags":[
        "modification",
        "caravan",
        "towing",
        "transport",
        "garage"
    ],
    "wof:name":"J L Veitch",
    "wof:placetype":"venue"
},
  "geometry": {"coordinates":[-1.8176599741,54.7850418091],"type":"Point"}
}