{
  "type": "Feature",
  "properties": {
    "addr:full":"Portland Mews Leamington Spa Warwickshire CV32 5HD",
    "addr:postcode":"cv32 5hd",
    "addr:street":"Portland Mews",
    "iso:country":"GB",
    "sg:address":"Portland Mews",
    "sg:city":"Leamington Spa",
    "sg:classifiers":[
        {
            "category":"Professional",
            "subcategory":"Management & Consulting",
            "type":"Services"
        }
    ],
    "sg:phone":"+44 1926 312481",
    "sg:postcode":"CV32 5HD",
    "sg:province":"Warwickshire",
    "sg:tags":[
        "consultant",
        "business"
    ],
    "wof:name":"DBI Associates Ltd",
    "wof:placetype":"venue"
},
  "geometry": {"coordinates":[-1.5391989946,52.2907485962],"type":"Point"}
}