{
  "type": "Feature",
  "properties": {
    "addr:full":"Penbetha Farm, Grampound Road Truro Cornwall TR2 4BY",
    "addr:postcode":"tr2 4by",
    "addr:street":"Grampound Road",
    "iso:country":"GB",
    "sg:address":"Penbetha Farm, Grampound Road",
    "sg:city":"Truro",
    "sg:classifiers":[
        {
            "category":"Farming",
            "subcategory":"Farm",
            "type":"Manufacturing & Wholesale Goods"
        }
    ],
    "sg:phone":"+44 1726 882389",
    "sg:postcode":"TR2 4BY",
    "sg:province":"Cornwall",
    "sg:tags":[
        "mixed",
        "crop"
    ],
    "wof:name":"Thomas P J John",
    "wof:placetype":"venue"
},
  "geometry": {"coordinates":[-4.9298939705,50.3182907104],"type":"Point"}
}