{
  "type": "Feature",
  "properties": {
    "addr:full":"31 High Street Bristol City of Bristol BS15 4NF",
    "addr:housenumber":"31",
    "addr:postcode":"bs15 4nf",
    "addr:street":"High Street",
    "iso:country":"GB",
    "sg:address":"31 High Street",
    "sg:city":"Bristol",
    "sg:classifiers":[
        {
            "category":"Autos & Motor Vehicles",
            "subcategory":"Motorcycle Sales",
            "type":"Retail Goods"
        }
    ],
    "sg:phone":"+44 117 960 0627",
    "sg:postcode":"BS15 4NF",
    "sg:province":"City of Bristol",
    "sg:tags":[
        "component"
    ],
    "wof:name":"Motoextreme",
    "wof:placetype":"venue"
},
  "geometry": {"coordinates":[-2.4766669273,51.4601325989],"type":"Point"}
}