{
  "type": "Feature",
  "properties": {
    "addr:full":"2 Avon Buildings Christchurch Dorset BH23 1QS",
    "addr:housenumber":"2;buildings",
    "addr:postcode":"bh23 1qs",
    "addr:street":"Avon",
    "iso:country":"GB",
    "sg:address":"2 Avon Buildings",
    "sg:city":"Christchurch",
    "sg:classifiers":[
        {
            "category":"Recreation",
            "subcategory":"Fishing",
            "type":"Entertainment"
        }
    ],
    "sg:phone":"+44 1202 485262",
    "sg:postcode":"BH23 1QS",
    "sg:province":"Dorset",
    "sg:tags":[
        "angling"
    ],
    "wof:name":"Royalty Fishery",
    "wof:placetype":"venue"
},
  "geometry": {"coordinates":[-1.779613,50.738117],"type":"Point"}
}