{
  "type": "Feature",
  "properties": {
    "iso:country":"GB",
    "sg:address":"Worlds End Farm Cottage, Clapton",
    "sg:city":"Berkeley",
    "sg:classifiers":[
        {
            "category":"Farming",
            "subcategory":"Livestock Farm",
            "type":"Manufacturing & Wholesale Goods"
        }
    ],
    "sg:phone":"+44 1453 810142",
    "sg:postcode":"GL13 9RA",
    "sg:province":"Gloucestershire",
    "sg:tags":[
        "others"
    ],
    "wof:name":"G M Sealey & Son",
    "wof:placetype":"venue"
},
  "geometry": {"coordinates":[-2.459569,51.693188],"type":"Point"}
}