{
  "type": "Feature",
  "properties": {
    "addr:full":"8 Kensington, Cockton Hill Rd Bishop Auckland Durham DL14 6HX",
    "addr:housenumber":"8",
    "addr:postcode":"dl14 6hx",
    "addr:street":"Kensington Cockton Hill Rd",
    "iso:country":"GB",
    "sg:address":"8 Kensington, Cockton Hill Rd",
    "sg:city":"Bishop Auckland",
    "sg:classifiers":[
        {
            "category":"Government",
            "subcategory":"Police Station",
            "type":"Public Place"
        },
        {
            "category":"Government",
            "subcategory":"Office",
            "type":"Public Place"
        }
    ],
    "sg:phone":"+44 1388 602182",
    "sg:postcode":"DL14 6HX",
    "sg:province":"Durham",
    "sg:tags":[
        "support",
        "local"
    ],
    "wof:name":"The Probation Service",
    "wof:placetype":"venue"
},
  "geometry": {"coordinates":[-1.680494,54.650101],"type":"Point"}
}