{
  "type": "Feature",
  "properties": {
    "addr:full":"Napton Marina, Stockton Southam Warwickshire CV47 8HX",
    "addr:postcode":"cv47 8hx",
    "iso:country":"GB",
    "sg:address":"Napton Marina, Stockton",
    "sg:city":"Southam",
    "sg:classifiers":[
        {
            "category":"Recreation",
            "subcategory":"Boat Charter",
            "type":"Entertainment"
        }
    ],
    "sg:phone":"+44 1926 813644",
    "sg:postcode":"CV47 8HX",
    "sg:province":"Warwickshire",
    "sg:tags":[
        "excursion"
    ],
    "wof:name":"Metalacre Ltd.",
    "wof:placetype":"venue"
},
  "geometry": {"coordinates":[-1.321037,52.252895],"type":"Point"}
}