{
  "type": "Feature",
  "properties": {
    "iso:country":"GB",
    "sg:address":"32 Hillbrook Gro, Stechford",
    "sg:city":"Birmingham",
    "sg:classifiers":[
        {
            "category":"Building & Trades",
            "subcategory":"Construction",
            "type":"Services"
        }
    ],
    "sg:phone":"+44 121 628 2186",
    "sg:postcode":"B33 8DG",
    "sg:province":"West Midlands",
    "sg:tags":[
        "builder"
    ],
    "wof:name":"Genesis Contractors Ltd.",
    "wof:placetype":"venue"
},
  "geometry": {"coordinates":[-1.809209,52.4823],"type":"Point"}
}