{
  "type": "Feature",
  "properties": {
    "addr:full":", Nethertown Egremont Cumbria CA22 2UH",
    "addr:postcode":"ca22 2uh",
    "iso:country":"GB",
    "sg:address":", Nethertown",
    "sg:city":"Egremont",
    "sg:classifiers":[
        {
            "category":"Arena",
            "subcategory":"Sports Club",
            "type":"Entertainment"
        }
    ],
    "sg:phone":"+44 1946 823005",
    "sg:postcode":"CA22 2UH",
    "sg:province":"Cumbria",
    "sg:tags":[
        "country"
    ],
    "wof:name":"VILLAGE INN & COUNTRY CLUB",
    "wof:placetype":"venue"
},
  "geometry": {"coordinates":[-3.52831,54.482918],"type":"Point"}
}