{
  "type": "Feature",
  "properties": {
    "addr:full":"27 North Street, Winchcombe Cheltenham Gloucestershire GL54 5PS",
    "addr:housenumber":"27",
    "addr:postcode":"gl54 5ps",
    "addr:street":"North Street",
    "iso:country":"GB",
    "sg:address":"27 North Street, Winchcombe",
    "sg:city":"Cheltenham",
    "sg:classifiers":[
        {
            "category":"Shopping",
            "subcategory":"Stationery & Office Supplies",
            "type":"Retail Goods"
        },
        {
            "category":"Government",
            "subcategory":"Post Office",
            "type":"Public Place"
        }
    ],
    "sg:phone":"+44 1242 602315",
    "sg:postcode":"GL54 5PS",
    "sg:province":"Gloucestershire",
    "wof:name":"Winchcombe Sub Post Office",
    "wof:placetype":"venue"
},
  "geometry": {"coordinates":[-1.9646919966,51.9542961121],"type":"Point"}
}