{
  "type": "Feature",
  "properties": {
    "iso:country":"GB",
    "sg:address":"105 Coombe Rise, Oadby",
    "sg:city":"Leicester",
    "sg:classifiers":[
        {
            "category":"Bus Charters",
            "type":"Transportation"
        }
    ],
    "sg:postcode":"LE2 5TZ",
    "sg:province":"Leicestershire",
    "sg:tags":[
        "hire",
        "coach"
    ],
    "wof:name":"Confidence Bus & Coach Hire",
    "wof:placetype":"venue"
},
  "geometry": {"coordinates":[-1.066229,52.587662],"type":"Point"}
}