{
  "type": "Feature",
  "properties": {
    "addr:full":"19 The Moor Sheffield South Yorkshire S1 4PF",
    "addr:housenumber":"19",
    "addr:postcode":"s1 4pf",
    "addr:street":"The Moor",
    "iso:country":"GB",
    "sg:address":"19 The Moor",
    "sg:city":"Sheffield",
    "sg:classifiers":[
        {
            "category":"Shopping",
            "subcategory":"Pharmacy",
            "type":"Retail Goods"
        }
    ],
    "sg:phone":"+44 114 276 7984",
    "sg:postcode":"S1 4PF",
    "sg:province":"South Yorkshire",
    "sg:tags":[
        "store",
        "drug"
    ],
    "wof:name":"Superdrug Stores Plc",
    "wof:placetype":"venue"
},
  "geometry": {"coordinates":[-1.472672,53.376858],"type":"Point"}
}