{
  "type": "Feature",
  "properties": {
    "addr:full":"8a Mill St Bedford Bedfordshire MK40 3HD",
    "addr:housenumber":"8a",
    "addr:postcode":"mk40 3hd",
    "addr:street":"Mill St",
    "iso:country":"GB",
    "sg:address":"8a Mill St",
    "sg:city":"Bedford",
    "sg:classifiers":[
        {
            "category":"Professional",
            "subcategory":"Employment Agencies",
            "type":"Services"
        }
    ],
    "sg:phone":"+44 1234 352732",
    "sg:postcode":"MK40 3HD",
    "sg:province":"Bedfordshire",
    "sg:tags":[
        "consultant"
    ],
    "wof:name":"Agency 2000 Ltd",
    "wof:placetype":"venue"
},
  "geometry": {"coordinates":[-0.466231,52.137074],"type":"Point"}
}