{
  "type": "Feature",
  "properties": {
    "addr:full":"500 Dunsbury Way, Leigh Park Havant Hampshire PO9 5BL",
    "addr:housenumber":"500",
    "addr:postcode":"po9 5bl",
    "addr:street":"Dunsbury Way",
    "iso:country":"GB",
    "sg:address":"500 Dunsbury Way, Leigh Park",
    "sg:city":"Havant",
    "sg:classifiers":[
        {
            "category":"Food & Beverages",
            "subcategory":"Liquor & Beverages",
            "type":"Retail Goods"
        }
    ],
    "sg:postcode":"PO9 5BL",
    "sg:province":"Hampshire",
    "sg:tags":[
        "beer",
        "spirit",
        "wines"
    ],
    "wof:name":"Victoria Wine",
    "wof:placetype":"venue"
},
  "geometry": {"coordinates":[-0.990569,50.872883],"type":"Point"}
}