{
  "type": "Feature",
  "properties": {
    "iso:country":"GB",
    "sg:address":"Unit 6a Hartley Pk Farm Business Centr,",
    "sg:city":"Alton",
    "sg:classifiers":[
        {
            "category":"Food & Beverages",
            "subcategory":"Bakery",
            "type":"Retail Goods"
        }
    ],
    "sg:postcode":"GU34 3HS",
    "sg:province":"Hampshire",
    "sg:tags":[
        "baker"
    ],
    "wof:name":"Giovanni Confectionery",
    "wof:placetype":"venue"
},
  "geometry": {"coordinates":[-0.974329,51.14756],"type":"Point"}
}