{
  "type": "Feature",
  "properties": {
    "iso:country":"GB",
    "sg:address":"4-5 Anglers Court, 33-44 Spittal Street",
    "sg:city":"Marlow",
    "sg:classifiers":[
        {
            "category":"Professional",
            "subcategory":"Management & Consulting",
            "type":"Services"
        }
    ],
    "sg:phone":"+44 1628 405119",
    "sg:postcode":"SL7 1DB",
    "sg:province":"Berkshire",
    "sg:tags":[
        "marketing",
        "consultant"
    ],
    "wof:name":"Interwood Marketing (U K) Ltd.",
    "wof:placetype":"venue"
},
  "geometry": {"coordinates":[-0.776189,51.573067],"type":"Point"}
}