{
  "type": "Feature",
  "properties": {
    "addr:full":"Havannah Business Centre, Havannah St Congleton Cheshire CW12 2AG",
    "addr:postcode":"cw12 2ag",
    "addr:street":"Havannah St",
    "iso:country":"GB",
    "sg:address":"Havannah Business Centre, Havannah St",
    "sg:city":"Congleton",
    "sg:classifiers":[
        {
            "category":"Health Services",
            "subcategory":"Nursing And Care Facility",
            "type":"Services"
        }
    ],
    "sg:postcode":"CW12 2AG",
    "sg:province":"Cheshire",
    "sg:tags":[
        "home"
    ],
    "wof:name":"Bankvale Healthcare Ltd",
    "wof:placetype":"venue"
},
  "geometry": {"coordinates":[-2.1976630688,53.1783905029],"type":"Point"}
}