{
  "type": "Feature",
  "properties": {
    "addr:full":"4 Dancastle Court London Greater London N3 2HS",
    "addr:housenumber":"4",
    "addr:postcode":"n3 2hs",
    "addr:street":"Dancastle Court",
    "iso:country":"GB",
    "sg:address":"4 Dancastle Court",
    "sg:city":"London",
    "sg:classifiers":[
        {
            "category":"Bars & Pubs",
            "subcategory":"Nightclub",
            "type":"Food & Drink"
        }
    ],
    "sg:postcode":"N3 2HS",
    "sg:province":"Greater London",
    "sg:tags":[
        "club",
        "night"
    ],
    "wof:name":"Sanctuary Leisure Ltd.",
    "wof:placetype":"venue"
},
  "geometry": {"coordinates":[-0.185349,51.598629],"type":"Point"}
}