{
  "type": "Feature",
  "properties": {
    "iso:country":"GB",
    "sg:address":"62 Lambsdowne",
    "sg:city":"Dursley",
    "sg:classifiers":[
        {
            "category":"Professional",
            "subcategory":"Engineering",
            "type":"Services"
        }
    ],
    "sg:postcode":"GL11 6PX",
    "sg:province":"Gloucestershire",
    "sg:tags":[
        "design",
        "engineer"
    ],
    "wof:name":"Modesign Ltd.",
    "wof:placetype":"venue"
},
  "geometry": {"coordinates":[-2.367924,51.692947],"type":"Point"}
}