{
  "type": "Feature",
  "properties": {
    "iso:country":"GB",
    "sg:address":"77 Prestbury Rd",
    "sg:city":"Macclesfield",
    "sg:classifiers":[
        {
            "category":"Museum",
            "subcategory":"Art Museum",
            "type":"Entertainment"
        },
        {
            "category":"Museum",
            "type":"Entertainment"
        }
    ],
    "sg:phone":"+44 1625 619831",
    "sg:postcode":"SK10 3BJ",
    "sg:province":"Cheshire",
    "sg:tags":[
        "gallery"
    ],
    "wof:name":"West Park Museum",
    "wof:placetype":"venue"
},
  "geometry": {"coordinates":[-2.136701107,53.2630577087],"type":"Point"}
}