{
  "type": "Feature",
  "properties": {
    "iso:country":"GB",
    "sg:address":"Mores Lane, Pilgrims Hatch",
    "sg:city":"Brentwood",
    "sg:classifiers":[
        {
            "category":"Retail",
            "subcategory":"Auto Repair",
            "type":"Services"
        }
    ],
    "sg:phone":"+44 1277 375005",
    "sg:postcode":"CM14 5RZ",
    "sg:province":"Essex",
    "sg:tags":[
        "modification",
        "garage"
    ],
    "wof:name":"C M S Car Maintenance & Servicing",
    "wof:placetype":"venue"
},
  "geometry": {"coordinates":[0.2628200054,51.6396141052],"type":"Point"}
}