{
  "type": "Feature",
  "properties": {
    "iso:country":"GB",
    "sg:address":"P.o Box 1194, Westlea,, Swindon",
    "sg:city":"Swindon",
    "sg:classifiers":[
        {
            "category":"Banks & Credit Unions",
            "subcategory":"Bank",
            "type":"Services"
        }
    ],
    "sg:phone":"+44 1793 882277",
    "sg:postcode":"SN5 7RR",
    "sg:province":"Wiltshire",
    "sg:tags":[
        "broker",
        "mortgage"
    ],
    "wof:name":"MMB Mortgate Brokers",
    "wof:placetype":"venue"
},
  "geometry": {"coordinates":[-1.828754,51.561008],"type":"Point"}
}