{
  "type": "Feature",
  "properties": {
    "addr:full":"639 Cathcart Rd Glasgow Glasgow City G42 8AE",
    "addr:housenumber":"639",
    "addr:postcode":"g42 8ae",
    "addr:street":"Cathcart Rd",
    "iso:country":"GB",
    "sg:address":"639 Cathcart Rd",
    "sg:city":"Glasgow",
    "sg:classifiers":[
        {
            "category":"Shopping",
            "subcategory":"Pharmacy",
            "type":"Retail Goods"
        }
    ],
    "sg:phone":"+44 141 423 2494",
    "sg:postcode":"G42 8AE",
    "sg:province":"Glasgow City",
    "sg:tags":[
        "pharmacist",
        "chemist"
    ],
    "wof:name":"Joyce Morrison",
    "wof:placetype":"venue"
},
  "geometry": {"coordinates":[-4.2561130524,55.8347167969],"type":"Point"}
}