{
  "type": "Feature",
  "properties": {
    "iso:country":"GB",
    "sg:address":"Woodlands, Wood Lane, Netherley",
    "sg:city":"Liverpool",
    "sg:classifiers":[
        {
            "category":"Health Services",
            "subcategory":"Nursing And Care Facility",
            "type":"Services"
        }
    ],
    "sg:phone":"+44 151 487 5234",
    "sg:postcode":"L27 4YA",
    "sg:province":"Merseyside",
    "sg:tags":[
        "home"
    ],
    "wof:name":"Woodlands Homecare Agency",
    "wof:placetype":"venue"
},
  "geometry": {"coordinates":[-2.83061,53.385399],"type":"Point"}
}