{
  "type": "Feature",
  "properties": {
    "addr:full":"252 Barnsley Road, Cudworth Barnsley South Yorkshire S72 8SS",
    "addr:housenumber":"252",
    "addr:postcode":"s72 8ss",
    "addr:street":"Barnsley Road;Yorkshire",
    "iso:country":"GB",
    "sg:address":"252 Barnsley Road, Cudworth",
    "sg:city":"Barnsley",
    "sg:classifiers":[
        {
            "category":"Food & Beverages",
            "subcategory":"Candy",
            "type":"Retail Goods"
        }
    ],
    "sg:phone":"+44 1226 713877",
    "sg:postcode":"S72 8SS",
    "sg:province":"South Yorkshire",
    "sg:tags":[
        "confectioner"
    ],
    "wof:name":"Lyndales Bakers",
    "wof:placetype":"venue"
},
  "geometry": {"coordinates":[-1.418033,53.57719],"type":"Point"}
}