{
  "type": "Feature",
  "properties": {
    "iso:country":"GB",
    "sg:address":"The Mill, 19 Shelley Woodhouse Lane",
    "sg:city":"Huddersfield",
    "sg:classifiers":[
        {
            "category":"Building & Trades",
            "subcategory":"Construction",
            "type":"Services"
        }
    ],
    "sg:postcode":"HD8 8PU",
    "sg:province":"South Yorkshire",
    "sg:tags":[
        "restoration",
        "refurbishment"
    ],
    "wof:name":"Millfield Construction (Northern) Ltd",
    "wof:placetype":"venue"
},
  "geometry": {"coordinates":[-1.6983439922,53.5935668945],"type":"Point"}
}