{
  "type": "Feature",
  "properties": {
    "addr:full":"61 Highfield Road Blackpool Lancashire FY4 2JE",
    "addr:housenumber":"61",
    "addr:postcode":"fy4 2je",
    "addr:street":"Highfield Road",
    "iso:country":"GB",
    "sg:address":"61 Highfield Road",
    "sg:city":"Blackpool",
    "sg:classifiers":[
        {
            "category":"Professional",
            "subcategory":"Lawyer & Legal Services",
            "type":"Services"
        }
    ],
    "sg:phone":"+44 1253 348142",
    "sg:postcode":"FY4 2JE",
    "sg:province":"Lancashire",
    "sg:tags":[
        "solicitor"
    ],
    "wof:name":"Taylor Poole",
    "wof:placetype":"venue"
},
  "geometry": {"coordinates":[-3.0445899963,53.7856826782],"type":"Point"}
}