{
  "type": "Feature",
  "properties": {
    "addr:full":"Office 4, Bank Chambers, Hardshaw St St Helens Merseyside WA10 1RE",
    "addr:housenumber":"4",
    "addr:postcode":"wa10 1re",
    "addr:street":"Chambers Hardshaw St",
    "iso:country":"GB",
    "sg:address":"Office 4, Bank Chambers, Hardshaw St",
    "sg:city":"St Helens",
    "sg:classifiers":[
        {
            "category":"Professional",
            "subcategory":"Computer Services",
            "type":"Services"
        }
    ],
    "sg:postcode":"WA10 1RE",
    "sg:province":"Merseyside",
    "sg:tags":[
        "system",
        "software"
    ],
    "wof:name":"Price,Paul,",
    "wof:placetype":"venue"
},
  "geometry": {"coordinates":[-2.738868,53.451687],"type":"Point"}
}