{
  "type": "Feature",
  "properties": {
    "iso:country":"GB",
    "sg:address":"Crown Square",
    "sg:city":"Denbigh",
    "sg:classifiers":[
        {
            "category":"Travel",
            "subcategory":"Hotels & Motels",
            "type":"Entertainment"
        }
    ],
    "sg:phone":"+44 1745 816374",
    "sg:postcode":"LL16 3AA",
    "sg:province":"Conwy",
    "wof:name":"R J M S Ltd.",
    "wof:placetype":"venue"
},
  "geometry": {"coordinates":[-3.4193189144,53.1837844849],"type":"Point"}
}