{
  "type": "Feature",
  "properties": {
    "iso:country":"GB",
    "sg:address":"282 Barking Road",
    "sg:city":"London",
    "sg:classifiers":[
        {
            "category":"Shopping",
            "subcategory":"News",
            "type":"Retail Goods"
        }
    ],
    "sg:phone":"+44 20 8471 0900",
    "sg:postcode":"E6 3BA",
    "sg:province":"Greater London",
    "sg:tags":[
        "newsagent"
    ],
    "wof:name":"A & A Newsagents",
    "wof:placetype":"venue"
},
  "geometry": {"coordinates":[0.051171,51.532368],"type":"Point"}
}