{
  "type": "Feature",
  "properties": {
    "iso:country":"GB",
    "sg:address":"43 Curzon St",
    "sg:city":"Ibstock",
    "sg:classifiers":[
        {
            "category":"Building & Trades",
            "subcategory":"Plumbing",
            "type":"Services"
        }
    ],
    "sg:phone":"+44 1530 261575",
    "sg:postcode":"LE67 6LA",
    "sg:province":"Leicestershire",
    "sg:tags":[
        "heating"
    ],
    "wof:name":"M Perkins",
    "wof:placetype":"venue"
},
  "geometry": {"coordinates":[-1.394758,52.689888],"type":"Point"}
}