{
  "type": "Feature",
  "properties": {
    "addr:full":"Unit 5 Mullensgrove Farms Sutton Coldfield Warwickshire B76 0DF",
    "addr:housenumber":"unit 5",
    "addr:postcode":"b76 0df",
    "iso:country":"GB",
    "sg:address":"Unit 5 Mullensgrove Farms",
    "sg:city":"Sutton Coldfield",
    "sg:classifiers":[
        {
            "category":"Professional",
            "subcategory":"Engineering",
            "type":"Services"
        }
    ],
    "sg:phone":"+44 1675 471144",
    "sg:postcode":"B76 0DF",
    "sg:province":"Warwickshire",
    "wof:name":"Resroc Ltd.",
    "wof:placetype":"venue"
},
  "geometry": {"coordinates":[-1.800584,52.556713],"type":"Point"}
}