{
  "type": "Feature",
  "properties": {
    "addr:full":"Llannon Llanelli Carmarthenshire SA14 8HX",
    "addr:postcode":"sa14 8hx",
    "addr:street":"Llannon;Carmarthenshire",
    "iso:country":"GB",
    "sg:address":"Llannon",
    "sg:city":"Llanelli",
    "sg:classifiers":[
        {
            "category":"Farming",
            "subcategory":"Livestock Farm",
            "type":"Manufacturing & Wholesale Goods"
        }
    ],
    "sg:phone":"+44 1269 841534",
    "sg:postcode":"SA14 8HX",
    "sg:province":"Carmarthenshire",
    "sg:tags":[
        "others"
    ],
    "wof:name":"S Oakley & Co.",
    "wof:placetype":"venue"
},
  "geometry": {"coordinates":[-4.1233401299,51.7385597229],"type":"Point"}
}