{
  "type": "Feature",
  "properties": {
    "iso:country":"GB",
    "sg:address":"53 Pennington Avenue",
    "sg:city":"Ormskirk",
    "sg:classifiers":[
        {
            "category":"Building & Trades",
            "subcategory":"Construction",
            "type":"Services"
        }
    ],
    "sg:phone":"+44 1695 577071",
    "sg:postcode":"L39 1NG",
    "sg:province":"Lancashire",
    "sg:tags":[
        "roofing"
    ],
    "wof:name":"Andrews Roofing & Building",
    "wof:placetype":"venue"
},
  "geometry": {"coordinates":[-2.8861050606,53.5709342957],"type":"Point"}
}