{
  "type": "Feature",
  "properties": {
    "iso:country":"GB",
    "sg:address":"Hecla Avenue",
    "sg:city":"Glasgow",
    "sg:classifiers":[
        {
            "category":"Government",
            "subcategory":"Post Office",
            "type":"Public Place"
        }
    ],
    "sg:phone":"+44 845 722 3344",
    "sg:postcode":"G15 8LZ",
    "sg:province":"Glasgow City",
    "wof:name":"POST OFFICE LTD",
    "wof:placetype":"venue"
},
  "geometry": {"coordinates":[-4.373004,55.911091],"type":"Point"}
}