{
  "type": "Feature",
  "properties": {
    "addr:full":"2 Queen Anne Terrace Plymouth Devon PL4 8EF",
    "addr:housenumber":"2",
    "addr:postcode":"pl4 8ef",
    "addr:street":"Queen Anne Terrace",
    "iso:country":"GB",
    "sg:address":"2 Queen Anne Terrace",
    "sg:city":"Plymouth",
    "sg:classifiers":[
        {
            "category":"Real Estate",
            "subcategory":"Surveying",
            "type":"Services"
        }
    ],
    "sg:phone":"+44 1752 269552",
    "sg:postcode":"PL4 8EF",
    "sg:province":"Devon",
    "sg:tags":[
        "surveyor",
        "land"
    ],
    "wof:name":"Countrywide Surveyors",
    "wof:placetype":"venue"
},
  "geometry": {"coordinates":[-4.136894,50.375805],"type":"Point"}
}