{
  "type": "Feature",
  "properties": {
    "addr:full":"Hurdcott, Winterbourne Earls Salisbury Hampshire SP4 6HR",
    "addr:postcode":"sp4 6hr",
    "iso:country":"GB",
    "sg:address":"Hurdcott, Winterbourne Earls",
    "sg:city":"Salisbury",
    "sg:classifiers":[
        {
            "category":"Travel",
            "subcategory":"Hotels & Motels",
            "type":"Entertainment"
        }
    ],
    "sg:postcode":"SP4 6HR",
    "sg:province":"Hampshire",
    "sg:tags":[
        "house",
        "guest"
    ],
    "wof:name":"Tennis Cottage",
    "wof:placetype":"venue"
},
  "geometry": {"coordinates":[-1.758146,51.105659],"type":"Point"}
}