{
  "type": "Feature",
  "properties": {
    "addr:full":"Hareden Farm, Trough Road, Dunsop Bridge Clitheroe Lancashire BB7 3BQ",
    "addr:postcode":"bb7 3bq",
    "addr:street":"Trough Road Dunsop Bridge",
    "iso:country":"GB",
    "sg:address":"Hareden Farm, Trough Road, Dunsop Bridge",
    "sg:city":"Clitheroe",
    "sg:classifiers":[
        {
            "category":"Farming",
            "subcategory":"Livestock Farm",
            "type":"Manufacturing & Wholesale Goods"
        }
    ],
    "sg:postcode":"BB7 3BQ",
    "sg:province":"Lancashire",
    "sg:tags":[
        "others"
    ],
    "wof:name":"E W & J R Parkinson",
    "wof:placetype":"venue"
},
  "geometry": {"coordinates":[-2.5187749863,53.9457588196],"type":"Point"}
}