{
  "type": "Feature",
  "properties": {
    "iso:country":"GB",
    "sg:address":"77-79 Commercial Road",
    "sg:city":"Bournemouth",
    "sg:classifiers":[
        {
            "category":"Bars & Pubs",
            "type":"Food & Drink"
        },
        {
            "category":"Community Center",
            "subcategory":"Social",
            "type":"Public Place"
        }
    ],
    "sg:phone":"+44 1202 555506",
    "sg:postcode":"BH2 5RT",
    "sg:province":"Dorset",
    "sg:tags":[
        "pubs",
        "house",
        "inn",
        "activity"
    ],
    "sg:website":"http://www.bakersarms.com",
    "wof:name":"Bakers Arms & Dorothy's Bar",
    "wof:placetype":"venue"
},
  "geometry": {"coordinates":[-1.884125,50.720016],"type":"Point"}
}