{
  "type": "Feature",
  "properties": {
    "addr:full":"126 High Street Dunbar East Lothian EH42 1JJ",
    "addr:housenumber":"126",
    "addr:postcode":"eh42 1jj",
    "addr:street":"High Street",
    "iso:country":"GB",
    "sg:address":"126 High Street",
    "sg:city":"Dunbar",
    "sg:classifiers":[
        {
            "category":"Museum",
            "subcategory":"Art Museum",
            "type":"Entertainment"
        },
        {
            "category":"Museum",
            "type":"Entertainment"
        }
    ],
    "sg:phone":"+44 1368 862585",
    "sg:postcode":"EH42 1JJ",
    "sg:province":"East Lothian",
    "sg:tags":[
        "gallery"
    ],
    "wof:name":"EAST LOTHIAN COUNCIL",
    "wof:placetype":"venue"
},
  "geometry": {"coordinates":[-2.5168740749,56.0029945374],"type":"Point"}
}