{
  "type": "Feature",
  "properties": {
    "iso:country":"GB",
    "sg:address":"55 Union Street",
    "sg:city":"Chorley",
    "sg:classifiers":[
        {
            "category":"Professional",
            "subcategory":"Computer Services",
            "type":"Services"
        },
        {
            "category":"Government",
            "subcategory":"Office",
            "type":"Public Place"
        }
    ],
    "sg:phone":"+44 1257 241693",
    "sg:postcode":"PR7 1EB",
    "sg:province":"Lancashire",
    "sg:tags":[
        "information",
        "local"
    ],
    "wof:name":"The County Information Centre",
    "wof:placetype":"venue"
},
  "geometry": {"coordinates":[-2.6309790611,53.6544494629],"type":"Point"}
}