{
  "type": "Feature",
  "properties": {
    "addr:full":"6 Court Farm Road Warlingham Kent CR6 9BD",
    "addr:housenumber":"6",
    "addr:postcode":"cr6 9bd",
    "addr:street":"Court Farm Road",
    "iso:country":"GB",
    "sg:address":"6 Court Farm Road",
    "sg:city":"Warlingham",
    "sg:classifiers":[
        {
            "category":"Building & Trades",
            "subcategory":"Construction",
            "type":"Services"
        }
    ],
    "sg:phone":"+44 1883 626246",
    "sg:postcode":"CR6 9BD",
    "sg:province":"Kent",
    "sg:tags":[
        "builder"
    ],
    "wof:name":"Bryan Smith Construction Ltd.",
    "wof:placetype":"venue"
},
  "geometry": {"coordinates":[-0.0752110034,51.3091049194],"type":"Point"}
}