{
  "type": "Feature",
  "properties": {
    "iso:country":"GB",
    "sg:address":"61 Polden Street",
    "sg:city":"Bridgwater",
    "sg:classifiers":[
        {
            "category":"Home & Garden",
            "subcategory":"Building Materials",
            "type":"Retail Goods"
        }
    ],
    "sg:phone":"+44 1278 450307",
    "sg:postcode":"TA6 5EL",
    "sg:province":"Somerset",
    "sg:tags":[
        "fencing"
    ],
    "wof:name":"Samson Fencing",
    "wof:placetype":"venue"
},
  "geometry": {"coordinates":[-2.994473,51.129925],"type":"Point"}
}