{
  "type": "Feature",
  "properties": {
    "iso:country":"GB",
    "sg:address":"32 North Street, Oldland Common",
    "sg:city":"Bristol",
    "sg:classifiers":[
        {
            "category":"Building & Trades",
            "subcategory":"Construction",
            "type":"Services"
        }
    ],
    "sg:phone":"+44 117 932 4846",
    "sg:postcode":"BS30 8TR",
    "sg:province":"Gloucestershire",
    "sg:tags":[
        "builder"
    ],
    "wof:name":"Avon Porch Builders",
    "wof:placetype":"venue"
},
  "geometry": {"coordinates":[-2.4722220898,51.4439697266],"type":"Point"}
}