{
  "type": "Feature",
  "properties": {
    "iso:country":"GB",
    "sg:address":"The Fold, High St, Waddingham",
    "sg:city":"Gainsborough",
    "sg:classifiers":[
        {
            "category":"Professional",
            "subcategory":"Printing & Photocopies",
            "type":"Services"
        }
    ],
    "sg:phone":"+44 1673 818284",
    "sg:postcode":"DN21 4SN",
    "sg:province":"Lincolnshire",
    "sg:tags":[
        "t-shirt"
    ],
    "wof:name":"Print-it",
    "wof:placetype":"venue"
},
  "geometry": {"coordinates":[-0.5192400217,53.4532318115],"type":"Point"}
}