{
  "type": "Feature",
  "properties": {
    "addr:full":"243 Old Christchurch Road Bournemouth Dorset BH1 1PE",
    "addr:housenumber":"243",
    "addr:postcode":"bh1 1pe",
    "addr:street":"Old Christchurch Road",
    "iso:country":"GB",
    "sg:address":"243 Old Christchurch Road",
    "sg:city":"Bournemouth",
    "sg:classifiers":[
        {
            "category":"Fast Food",
            "type":"Food & Drink"
        }
    ],
    "sg:phone":"+44 1202 558080",
    "sg:postcode":"BH1 1PE",
    "sg:province":"Dorset",
    "sg:tags":[
        "away",
        "take"
    ],
    "wof:name":"Adnanes Pizzeria",
    "wof:placetype":"venue"
},
  "geometry": {"coordinates":[-1.874279,50.722191],"type":"Point"}
}