{
  "type": "Feature",
  "properties": {
    "addr:full":"7 Southbourne Gro, Southbourne Bournemouth Dorset BH6 3QS",
    "addr:housenumber":"7",
    "addr:postcode":"bh6 3qs",
    "addr:street":"Southbourne Gro",
    "iso:country":"GB",
    "sg:address":"7 Southbourne Gro, Southbourne",
    "sg:city":"Bournemouth",
    "sg:classifiers":[
        {
            "category":"Sports & Exercise",
            "subcategory":"Sports Center",
            "type":"Entertainment"
        }
    ],
    "sg:postcode":"BH6 3QS",
    "sg:province":"Dorset",
    "sg:tags":[
        "shop",
        "good"
    ],
    "wof:name":"Grove Sports",
    "wof:placetype":"venue"
},
  "geometry": {"coordinates":[-1.8176389933,50.7264862061],"type":"Point"}
}