{
  "type": "Feature",
  "properties": {
    "addr:full":"West India House, 30 Marsh Wall London Greater London E14 9TP",
    "addr:housenumber":"30",
    "addr:postcode":"e14 9tp",
    "addr:street":"Marsh Wall",
    "iso:country":"GB",
    "sg:address":"West India House, 30 Marsh Wall",
    "sg:city":"London",
    "sg:classifiers":[
        {
            "category":"Professional",
            "subcategory":"Employment Agencies",
            "type":"Services"
        }
    ],
    "sg:phone":"+44 20 7512 0220",
    "sg:postcode":"E14 9TP",
    "sg:province":"Greater London",
    "sg:tags":[
        "consultant"
    ],
    "wof:name":"Kelly Services (U K) Ltd.",
    "wof:placetype":"venue"
},
  "geometry": {"coordinates":[-0.0222529992,51.5009841919],"type":"Point"}
}