{
  "type": "Feature",
  "properties": {
    "addr:full":"Corner Of Larkhall La & Studley Rd London Greater London SW4 6RJ",
    "addr:postcode":"sw4 6rj",
    "addr:street":"Corner;Rd",
    "iso:country":"GB",
    "sg:address":"Corner Of Larkhall La & Studley Rd",
    "sg:city":"London",
    "sg:classifiers":[
        {
            "category":"Community Center",
            "subcategory":"Youth",
            "type":"Public Place"
        }
    ],
    "sg:phone":"+44 20 7498 2329",
    "sg:postcode":"SW4 6RJ",
    "sg:province":"Greater London",
    "sg:tags":[
        "organisation",
        "centre"
    ],
    "wof:name":"Oasis Children's Venture",
    "wof:placetype":"venue"
},
  "geometry": {"coordinates":[-0.127791,51.473534],"type":"Point"}
}