{
  "type": "Feature",
  "properties": {
    "addr:full":"Greenwell Rd Aberdeen Aberdeen City AB12 3AX",
    "addr:postcode":"ab12 3ax",
    "addr:street":"Greenwell Rd",
    "iso:country":"GB",
    "sg:address":"Greenwell Rd",
    "sg:city":"Aberdeen",
    "sg:classifiers":[
        {
            "category":"Professional",
            "type":"Services"
        }
    ],
    "sg:phone":"+44 1224 890069",
    "sg:postcode":"AB12 3AX",
    "sg:province":"Aberdeen City",
    "sg:tags":[
        "caterer"
    ],
    "wof:name":"Kelvin",
    "wof:placetype":"venue"
},
  "geometry": {"coordinates":[-2.0895290375,57.1068000793],"type":"Point"}
}