{
  "type": "Feature",
  "properties": {
    "addr:full":"307 Baldwins Lane, Croxley Grn Rickmansworth Hertfordshire WD3 3LE",
    "addr:housenumber":"307",
    "addr:postcode":"wd3 3le",
    "addr:street":"Baldwins Lane Croxley Grn",
    "iso:country":"GB",
    "sg:address":"307 Baldwins Lane, Croxley Grn",
    "sg:city":"Rickmansworth",
    "sg:classifiers":[
        {
            "category":"Shopping",
            "subcategory":"Pets & Pet Supplies",
            "type":"Retail Goods"
        }
    ],
    "sg:phone":"+44 1923 775245",
    "sg:postcode":"WD3 3LE",
    "sg:province":"Hertfordshire",
    "sg:tags":[
        "food"
    ],
    "wof:name":"A & A Sims",
    "wof:placetype":"venue"
},
  "geometry": {"coordinates":[-0.449291,51.653927],"type":"Point"}
}