{
  "type": "Feature",
  "properties": {
    "iso:country":"GB",
    "sg:address":"30 Merrick Road",
    "sg:city":"Southall",
    "sg:classifiers":[
        {
            "category":"Retail",
            "subcategory":"Auto Repair",
            "type":"Services"
        }
    ],
    "sg:phone":"+44 20 8574 3000",
    "sg:postcode":"UB2 4AU",
    "sg:province":"Greater London",
    "sg:tags":[
        "modification",
        "garage"
    ],
    "wof:name":"Ajay Autos",
    "wof:placetype":"venue"
},
  "geometry": {"coordinates":[-0.3763689995,51.5042724609],"type":"Point"}
}