{
  "type": "Feature",
  "properties": {
    "addr:full":"4 Valley Bridge Parade Scarborough North Yorkshire YO11 2PF",
    "addr:housenumber":"4",
    "addr:postcode":"yo11 2pf",
    "addr:street":"Valley Bridge Parade",
    "iso:country":"GB",
    "sg:address":"4 Valley Bridge Parade",
    "sg:city":"Scarborough",
    "sg:classifiers":[
        {
            "category":"Real Estate",
            "subcategory":"Real Estate Agent",
            "type":"Services"
        }
    ],
    "sg:phone":"+44 1723 506021",
    "sg:postcode":"YO11 2PF",
    "sg:province":"North Yorkshire",
    "wof:name":"Nicholsons Yorkshire Coast Estate Agents",
    "wof:placetype":"venue"
},
  "geometry": {"coordinates":[-0.4038490057,54.2793617249],"type":"Point"}
}