{
  "type": "Feature",
  "properties": {
    "addr:full":"Station La Pontefract West Yorkshire WF7 5BA",
    "addr:postcode":"wf7 5ba",
    "addr:street":"West",
    "iso:country":"GB",
    "sg:address":"Station La",
    "sg:city":"Pontefract",
    "sg:classifiers":[
        {
            "category":"Utilities",
            "subcategory":"Fuel Oil & Lpg",
            "type":"Services"
        }
    ],
    "sg:phone":"+44 1977 603399",
    "sg:postcode":"WF7 5BA",
    "sg:province":"West Yorkshire",
    "sg:tags":[
        "coal",
        "smokeless"
    ],
    "wof:name":"Stead Fuels",
    "wof:placetype":"venue"
},
  "geometry": {"coordinates":[-1.358409,53.678467],"type":"Point"}
}