{
  "type": "Feature",
  "properties": {
    "iso:country":"GB",
    "sg:address":"7 Stretham Way",
    "sg:city":"Bourne",
    "sg:classifiers":[
        {
            "category":"Building & Trades",
            "subcategory":"Construction",
            "type":"Services"
        }
    ],
    "sg:phone":"+44 1778 393681",
    "sg:postcode":"PE10 9DE",
    "sg:province":"Lincolnshire",
    "sg:tags":[
        "builder"
    ],
    "wof:name":"Gambles Carpentry Joinery & Building Ltd.",
    "wof:placetype":"venue"
},
  "geometry": {"coordinates":[-0.380544,52.777004],"type":"Point"}
}