{
  "type": "Feature",
  "properties": {
    "addr:full":"26 Eastbourne Rd Pevensey East Sussex BN24 6ET",
    "addr:housenumber":"26",
    "addr:postcode":"bn24 6et",
    "addr:street":"Eastbourne Rd",
    "iso:country":"GB",
    "sg:address":"26 Eastbourne Rd",
    "sg:city":"Pevensey",
    "sg:classifiers":[
        {
            "category":"Shopping",
            "subcategory":"Pharmacy",
            "type":"Retail Goods"
        }
    ],
    "sg:phone":"+44 1323 761321",
    "sg:postcode":"BN24 6ET",
    "sg:province":"East Sussex",
    "sg:tags":[
        "pharmacist",
        "chemist"
    ],
    "wof:name":"Moss Chemists",
    "wof:placetype":"venue"
},
  "geometry": {"coordinates":[0.3508189917,50.8120536804],"type":"Point"}
}