{
  "type": "Feature",
  "properties": {
    "addr:full":"13 Portland Rd, Edgbaston Birmingham West Midlands B16 9HN",
    "addr:housenumber":"13",
    "addr:postcode":"b16 9hn",
    "addr:street":"Portland Rd",
    "iso:country":"GB",
    "sg:address":"13 Portland Rd, Edgbaston",
    "sg:city":"Birmingham",
    "sg:classifiers":[
        {
            "category":"Shopping",
            "subcategory":"Department Store",
            "type":"Retail Goods"
        }
    ],
    "sg:postcode":"B16 9HN",
    "sg:province":"West Midlands",
    "wof:name":"David's Jewellery Ltd",
    "wof:placetype":"venue"
},
  "geometry": {"coordinates":[-1.937249,52.472576],"type":"Point"}
}