{
  "type": "Feature",
  "properties": {
    "iso:country":"GB",
    "sg:address":"1st Floor 2 Isambard Brunel Road",
    "sg:city":"Portsmouth",
    "sg:classifiers":[
        {
            "category":"Banks & Credit Unions",
            "subcategory":"Financial Services",
            "type":"Services"
        }
    ],
    "sg:phone":"+44 23 9281 9221",
    "sg:postcode":"PO1 2DU",
    "sg:province":"Hampshire",
    "sg:tags":[
        "consultant"
    ],
    "wof:name":"Citifinancial Europe Plc",
    "wof:placetype":"venue"
},
  "geometry": {"coordinates":[-1.0916039944,50.7979049683],"type":"Point"}
}