{
  "type": "Feature",
  "properties": {
    "addr:full":"10a New Bond Street London Greater London W1S 3SX",
    "addr:housenumber":"10a",
    "addr:postcode":"w1s 3sx",
    "addr:street":"New Bond Street",
    "iso:country":"GB",
    "sg:address":"10a New Bond Street",
    "sg:city":"London",
    "sg:classifiers":[
        {
            "category":"Shopping",
            "subcategory":"Pawn Shop",
            "type":"Retail Goods"
        }
    ],
    "sg:postcode":"W1S 3SX",
    "sg:province":"Greater London",
    "sg:tags":[
        "pawnbroker"
    ],
    "wof:name":"Clough Antiques",
    "wof:placetype":"venue"
},
  "geometry": {"coordinates":[-0.1419740021,51.5101699829],"type":"Point"}
}