{
  "type": "Feature",
  "properties": {
    "addr:full":"Unit 31, Cattell Drive Sutton Coldfield Staffordshire B75 7LQ",
    "addr:housenumber":"unit 31",
    "addr:postcode":"b75 7lq",
    "addr:street":"Cattell Drive",
    "iso:country":"GB",
    "sg:address":"Unit 31, Cattell Drive",
    "sg:city":"Sutton Coldfield",
    "sg:classifiers":[
        {
            "category":"Home & Garden",
            "subcategory":"Building Materials",
            "type":"Retail Goods"
        },
        {
            "category":"Building & Trades",
            "subcategory":"Construction",
            "type":"Services"
        }
    ],
    "sg:phone":"+44 121 311 1160",
    "sg:postcode":"B75 7LQ",
    "sg:province":"Staffordshire",
    "sg:tags":[
        "insulation",
        "installers"
    ],
    "wof:name":"Badger Insulation Ltd",
    "wof:placetype":"venue"
},
  "geometry": {"coordinates":[-1.785738,52.562775],"type":"Point"}
}