{
  "type": "Feature",
  "properties": {
    "iso:country":"GB",
    "sg:address":"127 Victoria Road",
    "sg:city":"Scarborough",
    "sg:classifiers":[
        {
            "category":"Shopping",
            "subcategory":"Pets & Pet Supplies",
            "type":"Retail Goods"
        }
    ],
    "sg:phone":"+44 1723 375162",
    "sg:postcode":"YO11 1SP",
    "sg:province":"North Yorkshire",
    "wof:name":"Aquazoo",
    "wof:placetype":"venue"
},
  "geometry": {"coordinates":[-0.407741,54.280476],"type":"Point"}
}