{
  "type": "Feature",
  "properties": {
    "addr:full":"36 Eastworth Road Chertsey Surrey KT16 8DW",
    "addr:housenumber":"36",
    "addr:postcode":"kt16 8dw",
    "addr:street":"Eastworth Road",
    "iso:country":"GB",
    "sg:address":"36 Eastworth Road",
    "sg:city":"Chertsey",
    "sg:classifiers":[
        {
            "category":"Retail",
            "subcategory":"Funeral Services",
            "type":"Services"
        }
    ],
    "sg:phone":"+44 1932 563238",
    "sg:postcode":"KT16 8DW",
    "sg:province":"Surrey",
    "sg:tags":[
        "director"
    ],
    "wof:name":"P Boast & Son",
    "wof:placetype":"venue"
},
  "geometry": {"coordinates":[-0.5056080222,51.3870811462],"type":"Point"}
}