{
  "type": "Feature",
  "properties": {
    "iso:country":"GB",
    "sg:address":"Backwell Recreation Grounds, West Town Road, Backwell",
    "sg:city":"Bristol",
    "sg:classifiers":[
        {
            "category":"Arena",
            "subcategory":"Sports Club",
            "type":"Entertainment"
        }
    ],
    "sg:phone":"+44 1275 462612",
    "sg:postcode":"BS48 3HP",
    "sg:province":"Somerset",
    "wof:name":"Backwell United Football Club",
    "wof:placetype":"venue"
},
  "geometry": {"coordinates":[-2.741179,51.41309],"type":"Point"}
}