{
  "type": "Feature",
  "properties": {
    "addr:full":"55 Holford Rd Guildford Surrey GU1 2QE",
    "addr:housenumber":"55",
    "addr:postcode":"gu1 2qe",
    "addr:street":"Holford Rd",
    "iso:country":"GB",
    "sg:address":"55 Holford Rd",
    "sg:city":"Guildford",
    "sg:classifiers":[
        {
            "category":"Professional",
            "subcategory":"Management & Consulting",
            "type":"Services"
        },
        {
            "category":"Sports & Exercise",
            "subcategory":"Sports Center",
            "type":"Entertainment"
        }
    ],
    "sg:phone":"+44 1483 887000",
    "sg:postcode":"GU1 2QE",
    "sg:province":"Surrey",
    "sg:tags":[
        "technician",
        "adviser",
        "safety",
        "environmental",
        "consultant"
    ],
    "wof:name":"Micro Diagnostics UK Ltd",
    "wof:placetype":"venue"
},
  "geometry": {"coordinates":[-0.53784,51.240891],"type":"Point"}
}