{
  "type": "Feature",
  "properties": {
    "addr:full":"9 Northway Rugby Warwickshire CV21 2JS",
    "addr:housenumber":"9",
    "addr:postcode":"cv21 2js",
    "addr:street":"Northway",
    "iso:country":"GB",
    "sg:address":"9 Northway",
    "sg:city":"Rugby",
    "sg:classifiers":[
        {
            "category":"Food & Beverages",
            "subcategory":"Bakery",
            "type":"Retail Goods"
        }
    ],
    "sg:phone":"+44 1788 575873",
    "sg:postcode":"CV21 2JS",
    "sg:province":"Warwickshire",
    "sg:tags":[
        "baker"
    ],
    "wof:name":"The Bakers Oven",
    "wof:placetype":"venue"
},
  "geometry": {"coordinates":[-1.2628200054,52.3739471436],"type":"Point"}
}