{
  "type": "Feature",
  "properties": {
    "addr:full":", Culgaith Penrith Cumbria CA10 1QW",
    "addr:postcode":"ca10 1qw",
    "iso:country":"GB",
    "sg:address":", Culgaith",
    "sg:city":"Penrith",
    "sg:classifiers":[
        {
            "category":"Bars & Pubs",
            "type":"Food & Drink"
        }
    ],
    "sg:phone":"+44 1768 88223",
    "sg:postcode":"CA10 1QW",
    "sg:province":"Cumbria",
    "sg:tags":[
        "pubs",
        "inn"
    ],
    "wof:name":"Black Swan",
    "wof:placetype":"venue"
},
  "geometry": {"coordinates":[-2.605558,54.661037],"type":"Point"}
}