{
  "type": "Feature",
  "properties": {
    "addr:full":"243 South Coast Road Peacehaven East Sussex BN10 8LD",
    "addr:housenumber":"243",
    "addr:postcode":"bn10 8ld",
    "addr:street":"South Coast Road Peacehaven",
    "iso:country":"GB",
    "sg:address":"243 South Coast Road",
    "sg:city":"Peacehaven",
    "sg:classifiers":[
        {
            "category":"Food & Beverages",
            "subcategory":"Liquor & Beverages",
            "type":"Retail Goods"
        }
    ],
    "sg:phone":"+44 1273 582235",
    "sg:postcode":"BN10 8LD",
    "sg:province":"East Sussex",
    "sg:tags":[
        "beer",
        "spirit",
        "wines"
    ],
    "wof:name":"Unwins Wine Merchants",
    "wof:placetype":"venue"
},
  "geometry": {"coordinates":[-0.0027290001,50.7915802002],"type":"Point"}
}