{
  "type": "Feature",
  "properties": {
    "iso:country":"GB",
    "sg:address":"892 Rochdale Rd, Blackley",
    "sg:city":"Manchester",
    "sg:classifiers":[
        {
            "category":"Professional",
            "subcategory":"Engineering",
            "type":"Services"
        }
    ],
    "sg:postcode":"M9 4DE",
    "sg:province":"Greater Manchester",
    "sg:tags":[
        "civil",
        "engineer"
    ],
    "wof:name":"Dyer Landscapes",
    "wof:placetype":"venue"
},
  "geometry": {"coordinates":[-2.214304,53.511929],"type":"Point"}
}