{
  "type": "Feature",
  "properties": {
    "iso:country":"GB",
    "sg:address":"Gaston Farm, Gaston, Holt",
    "sg:city":"Trowbridge",
    "sg:classifiers":[
        {
            "category":"Farming",
            "subcategory":"Livestock Farm",
            "type":"Manufacturing & Wholesale Goods"
        }
    ],
    "sg:phone":"+44 1225 782203",
    "sg:postcode":"BA14 6QA",
    "sg:province":"Wiltshire",
    "sg:tags":[
        "others"
    ],
    "wof:name":"F J Moody & Son",
    "wof:placetype":"venue"
},
  "geometry": {"coordinates":[-2.197939,51.356846],"type":"Point"}
}