{
  "type": "Feature",
  "properties": {
    "addr:full":"430 Meanwood Road Leeds West Yorkshire LS7 2LP",
    "addr:housenumber":"430",
    "addr:postcode":"ls7 2lp",
    "addr:street":"Meanwood Road",
    "iso:country":"GB",
    "sg:address":"430 Meanwood Road",
    "sg:city":"Leeds",
    "sg:classifiers":[
        {
            "category":"Home & Garden",
            "subcategory":"Household Appliances",
            "type":"Retail Goods"
        }
    ],
    "sg:phone":"+44 7810 641519",
    "sg:postcode":"LS7 2LP",
    "sg:province":"West Yorkshire",
    "sg:tags":[
        "electrical"
    ],
    "wof:name":"B Clarkeson",
    "wof:placetype":"venue"
},
  "geometry": {"coordinates":[-1.5570509434,53.8207626343],"type":"Point"}
}