{
  "type": "Feature",
  "properties": {
    "iso:country":"GB",
    "sg:address":"Business Centres, Po Box 306",
    "sg:city":"Haywards Heath",
    "sg:classifiers":[
        {
            "category":"Banks & Credit Unions",
            "subcategory":"Bank",
            "type":"Services"
        }
    ],
    "sg:phone":"+44 1444 414115",
    "sg:postcode":"RH16 4FE",
    "sg:province":"East Sussex",
    "wof:name":"NatWest",
    "wof:placetype":"venue"
},
  "geometry": {"coordinates":[-0.1020469964,50.9966583252],"type":"Point"}
}