{
  "type": "Feature",
  "properties": {
    "addr:full":"Sovereign House, 202 Upper Fifth Street Milton Keynes Buckinghamshire MK9 2JB",
    "addr:housenumber":"202",
    "addr:postcode":"mk9 2jb",
    "addr:street":"Upper Fifth Street",
    "iso:country":"GB",
    "sg:address":"Sovereign House, 202 Upper Fifth Street",
    "sg:city":"Milton Keynes",
    "sg:classifiers":[
        {
            "category":"Real Estate",
            "subcategory":"Developer",
            "type":"Services"
        }
    ],
    "sg:postcode":"MK9 2JB",
    "sg:province":"Buckinghamshire",
    "sg:tags":[
        "property"
    ],
    "wof:name":"Coppergate Ltd.",
    "wof:placetype":"venue"
},
  "geometry": {"coordinates":[-0.7649790049,52.0403404236],"type":"Point"}
}