{
  "type": "Feature",
  "properties": {
    "addr:full":"20 Woodside Road Sutton Surrey SM1 3SU",
    "addr:housenumber":"20",
    "addr:postcode":"sm1 3su",
    "addr:street":"Woodside Road",
    "iso:country":"GB",
    "sg:address":"20 Woodside Road",
    "sg:city":"Sutton",
    "sg:classifiers":[
        {
            "category":"Banks & Credit Unions",
            "subcategory":"Investment Brokerage",
            "type":"Services"
        }
    ],
    "sg:phone":"+44 20 8644 1232",
    "sg:postcode":"SM1 3SU",
    "sg:province":"Surrey",
    "wof:name":"Whitechurch Securities Ltd.",
    "wof:placetype":"venue"
},
  "geometry": {"coordinates":[-0.189324,51.371059],"type":"Point"}
}