{
  "type": "Feature",
  "properties": {
    "iso:country":"GB",
    "sg:address":"20 Woodside Road",
    "sg:city":"Sutton",
    "sg:classifiers":[
        {
            "category":"Banks & Credit Unions",
            "subcategory":"Investment Brokerage",
            "type":"Services"
        }
    ],
    "sg:phone":"+44 20 8644 1232",
    "sg:postcode":"SM1 3SU",
    "sg:province":"Surrey",
    "wof:name":"Whitechurch Securities Ltd.",
    "wof:placetype":"venue"
},
  "geometry": {"coordinates":[-0.189324,51.371059],"type":"Point"}
}