{
  "type": "Feature",
  "properties": {
    "addr:full":"Broadwater Park, Summers Road, Farncombe Godalming Surrey GU7 3BE",
    "addr:postcode":"gu7 3be",
    "addr:street":"Broadwater Park Summers Road",
    "iso:country":"GB",
    "sg:address":"Broadwater Park, Summers Road, Farncombe",
    "sg:city":"Godalming",
    "sg:classifiers":[
        {
            "category":"Arena",
            "subcategory":"Sports Club",
            "type":"Entertainment"
        }
    ],
    "sg:phone":"+44 1483 414511",
    "sg:postcode":"GU7 3BE",
    "sg:province":"Surrey",
    "wof:name":"Farncombe Cricket Club",
    "wof:placetype":"venue"
},
  "geometry": {"coordinates":[-0.5992490053,51.1930160522],"type":"Point"}
}