{
  "type": "Feature",
  "properties": {
    "addr:full":"Dock Office Grangemouth Falkirk FK3 8UE",
    "addr:postcode":"fk3 8ue",
    "iso:country":"GB",
    "sg:address":"Dock Office",
    "sg:city":"Grangemouth",
    "sg:classifiers":[
        {
            "category":"Harbor",
            "type":"Transportation"
        }
    ],
    "sg:phone":"+44 1324 482591",
    "sg:postcode":"FK3 8UE",
    "sg:province":"Falkirk",
    "sg:tags":[
        "dock",
        "ports",
        "harbour"
    ],
    "wof:name":"Forth Ports Plc",
    "wof:placetype":"venue"
},
  "geometry": {"coordinates":[-3.727298975,56.0127296448],"type":"Point"}
}