{
  "type": "Feature",
  "properties": {
    "addr:full":"53 Church Hill Road, East Barnet Barnet Hertfordshire EN4 8SY",
    "addr:housenumber":"53",
    "addr:postcode":"en4 8sy",
    "addr:street":"Church Hill Road",
    "iso:country":"GB",
    "sg:address":"53 Church Hill Road, East Barnet",
    "sg:city":"Barnet",
    "sg:classifiers":[
        {
            "category":"Insurance",
            "subcategory":"Insurance Agent",
            "type":"Services"
        }
    ],
    "sg:phone":"+44 20 8440 5353",
    "sg:postcode":"EN4 8SY",
    "sg:province":"Hertfordshire",
    "sg:tags":[
        "broker"
    ],
    "wof:name":"Tangent Insurance Brokers Ltd.",
    "wof:placetype":"venue"
},
  "geometry": {"coordinates":[-0.162541002,51.6415138245],"type":"Point"}
}