{
  "type": "Feature",
  "properties": {
    "addr:full":"The Urdang Academy, 20-22 Shelton Street London Greater London WC2H 9JJ",
    "addr:housenumber":"20-22",
    "addr:postcode":"wc2h 9jj",
    "addr:street":"Shelton Street",
    "iso:country":"GB",
    "sg:address":"The Urdang Academy, 20-22 Shelton Street",
    "sg:city":"London",
    "sg:classifiers":[
        {
            "category":"Education",
            "subcategory":"Dance Studio",
            "type":"Public Place"
        }
    ],
    "sg:phone":"+44 20 7289 1869",
    "sg:postcode":"WC2H 9JJ",
    "sg:province":"Greater London",
    "sg:tags":[
        "school",
        "dancing"
    ],
    "wof:name":"Susan Zalcman School of Ballet",
    "wof:placetype":"venue"
},
  "geometry": {"coordinates":[-0.1262,51.51329],"type":"Point"}
}