{
  "type": "Feature",
  "properties": {
    "addr:full":"The Mount Feltham Greater London TW13 6AR",
    "addr:postcode":"tw13 6ar",
    "iso:country":"GB",
    "sg:address":"The Mount",
    "sg:city":"Feltham",
    "sg:classifiers":[
        {
            "category":"Bars & Pubs",
            "type":"Food & Drink"
        }
    ],
    "sg:phone":"+44 20 8894 9436",
    "sg:postcode":"TW13 6AR",
    "sg:province":"Greater London",
    "sg:tags":[
        "pubs",
        "inn"
    ],
    "wof:name":"The Horse & Groom",
    "wof:placetype":"venue"
},
  "geometry": {"coordinates":[-0.388304,51.439377],"type":"Point"}
}