{
  "type": "Feature",
  "properties": {
    "iso:country":"GB",
    "sg:address":"2 The Avenue, Kidsgrove",
    "sg:city":"Stoke-on-trent",
    "sg:classifiers":[
        {
            "category":"Retail",
            "subcategory":"Veterinary Services",
            "type":"Services"
        }
    ],
    "sg:phone":"+44 1782 782582",
    "sg:postcode":"ST7 1AE",
    "sg:province":"Cheshire",
    "sg:tags":[
        "surgeon"
    ],
    "wof:name":"Beechwood Veterinary Surgery",
    "wof:placetype":"venue"
},
  "geometry": {"coordinates":[-2.24081,53.08651],"type":"Point"}
}