{
  "type": "Feature",
  "properties": {
    "addr:full":"54 Europa Av West Bromwich West Midlands B70 6TU",
    "addr:housenumber":"54",
    "addr:postcode":"b70 6tu",
    "addr:street":"Europa Av West",
    "iso:country":"GB",
    "sg:address":"54 Europa Av",
    "sg:city":"West Bromwich",
    "sg:classifiers":[
        {
            "category":"Retail",
            "subcategory":"Driving School",
            "type":"Services"
        }
    ],
    "sg:phone":"+44 121 525 9648",
    "sg:postcode":"B70 6TU",
    "sg:province":"West Midlands",
    "wof:name":"M P Vehicle Training",
    "wof:placetype":"venue"
},
  "geometry": {"coordinates":[-1.9787100554,52.5151863098],"type":"Point"}
}