{
  "type": "Feature",
  "properties": {
    "addr:full":"Winchester Ho Arisdale Ave South Ockendon Essex RM15 5TT",
    "addr:postcode":"rm15 5tt",
    "addr:street":"Winchester;Arisdale Ave",
    "iso:country":"GB",
    "sg:address":"Winchester Ho Arisdale Ave",
    "sg:city":"South Ockendon",
    "sg:classifiers":[
        {
            "category":"Social Services",
            "subcategory":"Job Training",
            "type":"Services"
        }
    ],
    "sg:postcode":"RM15 5TT",
    "sg:province":"Essex",
    "sg:tags":[
        "translator",
        "interpreter"
    ],
    "wof:name":"Exchange Translations",
    "wof:placetype":"venue"
},
  "geometry": {"coordinates":[0.28365,51.502476],"type":"Point"}
}