{
  "type": "Feature",
  "properties": {
    "iso:country":"GB",
    "sg:address":"35 Wellgate",
    "sg:city":"Clitheroe",
    "sg:classifiers":[
        {
            "category":"Fast Food",
            "type":"Food & Drink"
        }
    ],
    "sg:phone":"+44 1200 442193",
    "sg:postcode":"BB7 2DP",
    "sg:province":"Lancashire",
    "sg:tags":[
        "away",
        "meal",
        "outlet",
        "take"
    ],
    "wof:name":"Romero Pizza House",
    "wof:placetype":"venue"
},
  "geometry": {"coordinates":[-2.389513,53.872707],"type":"Point"}
}