{
  "type": "Feature",
  "properties": {
    "iso:country":"GB",
    "sg:address":"1 West Ealing Business Centre, Alexandriveia Rd",
    "sg:city":"West Ealing",
    "sg:classifiers":[
        {
            "category":"Retail",
            "subcategory":"Auto Repair",
            "type":"Services"
        }
    ],
    "sg:phone":"+44 20 8840 9537",
    "sg:postcode":"W13 0NJ",
    "sg:province":"Greater London",
    "sg:tags":[
        "modification",
        "garage"
    ],
    "wof:name":"Enbis Motors",
    "wof:placetype":"venue"
},
  "geometry": {"coordinates":[-0.30671,51.504143],"type":"Point"}
}