{
  "type": "Feature",
  "properties": {
    "addr:full":"124 Newport St Bolton Lancashire BL3 6AB",
    "addr:housenumber":"124",
    "addr:postcode":"bl3 6ab",
    "addr:street":"Newport St",
    "iso:country":"GB",
    "sg:address":"124 Newport St",
    "sg:city":"Bolton",
    "sg:classifiers":[
        {
            "category":"Shopping",
            "subcategory":"Books",
            "type":"Retail Goods"
        }
    ],
    "sg:phone":"+44 1204 400088",
    "sg:postcode":"BL3 6AB",
    "sg:province":"Lancashire",
    "wof:name":"Outlook Publishing Ltd",
    "wof:placetype":"venue"
},
  "geometry": {"coordinates":[-2.427891,53.574505],"type":"Point"}
}