{
  "type": "Feature",
  "properties": {
    "iso:country":"GB",
    "sg:address":"94 Weston Drive",
    "sg:city":"Stanmore",
    "sg:classifiers":[
        {
            "category":"Health Services",
            "subcategory":"Doctor",
            "type":"Services"
        },
        {
            "category":"Health Services",
            "subcategory":"Health Practitioner",
            "type":"Services"
        }
    ],
    "sg:phone":"+44 20 8907 3997",
    "sg:postcode":"HA7 2EN",
    "sg:province":"Greater London",
    "sg:tags":[
        "osteopath"
    ],
    "wof:name":"JOHN K BIRD",
    "wof:placetype":"venue"
},
  "geometry": {"coordinates":[-0.3115949929,51.6040725708],"type":"Point"}
}