{
  "type": "Feature",
  "properties": {
    "iso:country":"GB",
    "sg:address":"39 Queen Elizabeth Avenue, Bentley",
    "sg:city":"Walsall",
    "sg:classifiers":[
        {
            "category":"Shopping",
            "subcategory":"Pets & Pet Supplies",
            "type":"Retail Goods"
        }
    ],
    "sg:postcode":"WS2 0BD",
    "sg:province":"West Midlands",
    "wof:name":"A & A Pets",
    "wof:placetype":"venue"
},
  "geometry": {"coordinates":[-2.022714,52.588764],"type":"Point"}
}