{
  "type": "Feature",
  "properties": {
    "addr:full":"646-648 High Road Leytonstone London Greater London E11 3AA",
    "addr:housenumber":"646-648",
    "addr:postcode":"e11 3aa",
    "addr:street":"High Road",
    "iso:country":"GB",
    "sg:address":"646-648 High Road Leytonstone",
    "sg:city":"London",
    "sg:classifiers":[
        {
            "category":"Professional",
            "subcategory":"Lawyer & Legal Services",
            "type":"Services"
        }
    ],
    "sg:phone":"+44 20 8558 8884",
    "sg:postcode":"E11 3AA",
    "sg:province":"Greater London",
    "sg:tags":[
        "solicitor"
    ],
    "wof:name":"Bambos Tsiattalou",
    "wof:placetype":"venue"
},
  "geometry": {"coordinates":[0.01148,51.56868],"type":"Point"}
}