{
  "type": "Feature",
  "properties": {
    "addr:full":"Old Car Yard, Worster Road Kidderminster Staffordshire DY10 1HQ",
    "addr:postcode":"dy10 1hq",
    "addr:street":"Worster Road",
    "iso:country":"GB",
    "sg:address":"Old Car Yard, Worster Road",
    "sg:city":"Kidderminster",
    "sg:classifiers":[
        {
            "category":"Manufacturing",
            "subcategory":"Building Materials",
            "type":"Manufacturing & Wholesale Goods"
        }
    ],
    "sg:phone":"+44 1562 755585",
    "sg:postcode":"DY10 1HQ",
    "sg:province":"Staffordshire",
    "sg:tags":[
        "merchant",
        "builder"
    ],
    "wof:name":"A F G Ray & Sons",
    "wof:placetype":"venue"
},
  "geometry": {"coordinates":[-2.2490839958,52.3881111145],"type":"Point"}
}