{
  "type": "Feature",
  "properties": {
    "addr:full":"Chapel Lane Sale Cheshire M33 5PJ",
    "addr:postcode":"m33 5pj",
    "addr:street":"Chapel Lane",
    "iso:country":"GB",
    "sg:address":"Chapel Lane",
    "sg:city":"Sale",
    "sg:classifiers":[
        {
            "category":"Autos & Motor Vehicles",
            "subcategory":"Fuel & Gas Station",
            "type":"Retail Goods"
        }
    ],
    "sg:phone":"+44 161 905 2408",
    "sg:postcode":"M33 5PJ",
    "sg:province":"Cheshire",
    "sg:tags":[
        "petrol",
        "filling"
    ],
    "wof:name":"Manor Service Stations Ltd.",
    "wof:placetype":"venue"
},
  "geometry": {"coordinates":[-2.3408739567,53.4292831421],"type":"Point"}
}