{
  "type": "Feature",
  "properties": {
    "addr:full":"34 New Rd, Rubery Birmingham West Midlands B45 9HU",
    "addr:housenumber":"34",
    "addr:postcode":"b45 9hu",
    "addr:street":"New Rd",
    "iso:country":"GB",
    "sg:address":"34 New Rd, Rubery",
    "sg:city":"Birmingham",
    "sg:classifiers":[
        {
            "category":"Professional",
            "subcategory":"Lawyer & Legal Services",
            "type":"Services"
        }
    ],
    "sg:phone":"+44 121 453 5133",
    "sg:postcode":"B45 9HU",
    "sg:province":"West Midlands",
    "sg:tags":[
        "solicitor"
    ],
    "wof:name":"Deeley Graham T",
    "wof:placetype":"venue"
},
  "geometry": {"coordinates":[-2.025097,52.39151],"type":"Point"}
}