{
  "type": "Feature",
  "properties": {
    "addr:full":"51 Elmfield Pl Newton Aycliffe Durham DL5 7BE",
    "addr:housenumber":"51",
    "addr:postcode":"dl5 7be",
    "addr:street":"Elmfield Pl",
    "iso:country":"GB",
    "sg:address":"51 Elmfield Pl",
    "sg:city":"Newton Aycliffe",
    "sg:classifiers":[
        {
            "category":"Military Area",
            "subcategory":"Air Force Base",
            "type":"Public Place"
        }
    ],
    "sg:postcode":"DL5 7BE",
    "sg:province":"Durham",
    "sg:tags":[
        "taxi",
        "hire",
        "private"
    ],
    "wof:name":"Green Light Taxis",
    "wof:placetype":"venue"
},
  "geometry": {"coordinates":[-1.589957,54.615349],"type":"Point"}
}