{
  "type": "Feature",
  "properties": {
    "addr:full":"54 Osborne St Stockport Cheshire SK6 2DA",
    "addr:housenumber":"54",
    "addr:postcode":"sk6 2da",
    "addr:street":"Osborne St",
    "iso:country":"GB",
    "sg:address":"54 Osborne St",
    "sg:city":"Stockport",
    "sg:classifiers":[
        {
            "category":"Government",
            "subcategory":"Post Office",
            "type":"Public Place"
        }
    ],
    "sg:phone":"+44 161 430 2172",
    "sg:postcode":"SK6 2DA",
    "sg:province":"Cheshire",
    "wof:name":"Osborne Street Post Office",
    "wof:placetype":"venue"
},
  "geometry": {"coordinates":[-2.1552779675,53.398147583],"type":"Point"}
}