{
  "type": "Feature",
  "properties": {
    "addr:full":"17 George St, Kingsclere Newbury Berkshire RG20 5NH",
    "addr:housenumber":"17",
    "addr:postcode":"rg20 5nh",
    "addr:street":"George St",
    "iso:country":"GB",
    "sg:address":"17 George St, Kingsclere",
    "sg:city":"Newbury",
    "sg:classifiers":[
        {
            "category":"Professional",
            "subcategory":"Computer Services",
            "type":"Services"
        }
    ],
    "sg:postcode":"RG20 5NH",
    "sg:province":"Berkshire",
    "sg:tags":[
        "consultant"
    ],
    "wof:name":"Simpkin,G,",
    "wof:placetype":"venue"
},
  "geometry": {"coordinates":[-1.2457150221,51.3248596191],"type":"Point"}
}