{
  "type": "Feature",
  "properties": {
    "iso:country":"GB",
    "sg:address":"Kingcross Ho, Kingcross St",
    "sg:city":"Stoke-on-trent",
    "sg:classifiers":[
        {
            "category":"Bus Charters",
            "type":"Transportation"
        }
    ],
    "sg:postcode":"ST3 1NQ",
    "sg:province":"Staffordshire",
    "sg:tags":[
        "hire",
        "coach"
    ],
    "wof:name":"R & S Coaches",
    "wof:placetype":"venue"
},
  "geometry": {"coordinates":[-2.13375,52.987801],"type":"Point"}
}