{
  "type": "Feature",
  "properties": {
    "iso:country":"GB",
    "sg:address":"57 Walsham Road",
    "sg:city":"Chatham",
    "sg:classifiers":[
        {
            "category":"Professional",
            "subcategory":"Accounting & Tax Preparation",
            "type":"Services"
        }
    ],
    "sg:phone":"+44 1732 456444",
    "sg:postcode":"ME5 9HX",
    "sg:province":"Kent",
    "sg:tags":[
        "accountant"
    ],
    "wof:name":"Lambourne's Accounting Services",
    "wof:placetype":"venue"
},
  "geometry": {"coordinates":[0.518482,51.331303],"type":"Point"}
}