{
  "type": "Feature",
  "properties": {
    "iso:country":"GB",
    "sg:address":"Site Office, Hanchett Village",
    "sg:city":"Haverhill",
    "sg:classifiers":[
        {
            "category":"Building & Trades",
            "subcategory":"Construction",
            "type":"Services"
        }
    ],
    "sg:phone":"+44 1440 714325",
    "sg:postcode":"CB9 7RP",
    "sg:province":"Essex",
    "sg:tags":[
        "builder"
    ],
    "wof:name":"H C Moss Ltd",
    "wof:placetype":"venue"
},
  "geometry": {"coordinates":[0.4357979894,52.0851287842],"type":"Point"}
}