{
  "type": "Feature",
  "properties": {
    "iso:country":"GB",
    "sg:address":"32 Longmoore Street",
    "sg:city":"London",
    "sg:classifiers":[
        {
            "category":"Social Services",
            "subcategory":"Job Training",
            "type":"Services"
        }
    ],
    "sg:phone":"+44 20 7834 8262",
    "sg:postcode":"SW1V 1JF",
    "sg:province":"Greater London",
    "sg:tags":[
        "translator",
        "interpreter"
    ],
    "wof:name":"Spanish & Portugese Translation",
    "wof:placetype":"venue"
},
  "geometry": {"coordinates":[-0.1410750002,51.4924888611],"type":"Point"}
}