{
  "type": "Feature",
  "properties": {
    "addr:full":"5-7 Little Oaks Road Birmingham West Midlands B6 6JY",
    "addr:housenumber":"5-7",
    "addr:postcode":"b6 6jy",
    "addr:street":"Little Oaks Road",
    "iso:country":"GB",
    "sg:address":"5-7 Little Oaks Road",
    "sg:city":"Birmingham",
    "sg:classifiers":[
        {
            "category":"Health Services",
            "subcategory":"Doctor",
            "type":"Services"
        }
    ],
    "sg:phone":"+44 121 328 1977",
    "sg:postcode":"B6 6JY",
    "sg:province":"West Midlands",
    "sg:tags":[
        "practitioners"
    ],
    "wof:name":"ZAFIR ALI",
    "wof:placetype":"venue"
},
  "geometry": {"coordinates":[-1.891648,52.505665],"type":"Point"}
}