{
  "type": "Feature",
  "properties": {
    "iso:country":"GB",
    "sg:address":"7 Daltongate Business Centre, Daltongate",
    "sg:city":"Ulverston",
    "sg:classifiers":[
        {
            "category":"Professional",
            "subcategory":"Accounting & Tax Preparation",
            "type":"Services"
        }
    ],
    "sg:postcode":"LA12 7AJ",
    "sg:province":"Cumbria",
    "sg:tags":[
        "accountant"
    ],
    "wof:name":"J F Hornby Ltd.",
    "wof:placetype":"venue"
},
  "geometry": {"coordinates":[-3.0968670845,54.1959075928],"type":"Point"}
}