{
  "type": "Feature",
  "properties": {
    "addr:full":"16 Keswick Drive Nelson Lancashire BB9 0SZ",
    "addr:housenumber":"16",
    "addr:postcode":"bb9 0sz",
    "addr:street":"Keswick Drive",
    "iso:country":"GB",
    "sg:address":"16 Keswick Drive",
    "sg:city":"Nelson",
    "sg:classifiers":[
        {
            "category":"Professional",
            "subcategory":"Accounting & Tax Preparation",
            "type":"Services"
        }
    ],
    "sg:phone":"+44 1282 617661",
    "sg:postcode":"BB9 0SZ",
    "sg:province":"Lancashire",
    "sg:tags":[
        "accountant"
    ],
    "wof:name":"Chippendale Classic",
    "wof:placetype":"venue"
},
  "geometry": {"coordinates":[-2.2087540627,53.827545166],"type":"Point"}
}