{
  "type": "Feature",
  "properties": {
    "iso:country":"GB",
    "sg:address":"Block A, Bay 5, The Bescot Estate",
    "sg:city":"Wednesbury",
    "sg:classifiers":[
        {
            "category":"Manufacturing",
            "subcategory":"Rubber & Plastics",
            "type":"Manufacturing & Wholesale Goods"
        }
    ],
    "sg:postcode":"WS10 7SG",
    "sg:province":"West Midlands",
    "sg:tags":[
        "supplier",
        "stockist"
    ],
    "wof:name":"Irpen (U K) Ltd.",
    "wof:placetype":"venue"
},
  "geometry": {"coordinates":[-2.019254,52.552731],"type":"Point"}
}