{
  "type": "Feature",
  "properties": {
    "addr:full":"Stoneham House, 13 Queens Rd Richmond Greater London TW10 6JW",
    "addr:housenumber":"13",
    "addr:postcode":"tw10 6jw",
    "addr:street":"Queens Rd",
    "iso:country":"GB",
    "sg:address":"Stoneham House, 13 Queens Rd",
    "sg:city":"Richmond",
    "sg:classifiers":[
        {
            "category":"Professional",
            "subcategory":"Management & Consulting",
            "type":"Services"
        }
    ],
    "sg:phone":"+44 20 8940 5195",
    "sg:postcode":"TW10 6JW",
    "sg:province":"Greater London",
    "sg:tags":[
        "consultant",
        "business"
    ],
    "wof:name":"Performance Coaching Group",
    "wof:placetype":"venue"
},
  "geometry": {"coordinates":[-0.294561,51.453445],"type":"Point"}
}