{
  "type": "Feature",
  "properties": {
    "iso:country":"GB",
    "sg:address":"Knights Hill, West Norwood",
    "sg:city":"London",
    "sg:classifiers":[
        {
            "category":"Place Of Worship",
            "type":"Public Place"
        }
    ],
    "sg:phone":"+44 20 8761 0068",
    "sg:postcode":"SE27 0HS",
    "sg:province":"Greater London",
    "wof:name":"St. Luke's Church",
    "wof:placetype":"venue"
},
  "geometry": {"coordinates":[-0.103759,51.433235],"type":"Point"}
}