{
  "type": "Feature",
  "properties": {
    "iso:country":"GB",
    "sg:address":"9 Bethel Street",
    "sg:city":"Brighouse",
    "sg:classifiers":[
        {
            "category":"Fast Food",
            "type":"Food & Drink"
        }
    ],
    "sg:phone":"+44 1484 711364",
    "sg:postcode":"HD6 1JR",
    "sg:province":"West Yorkshire",
    "sg:tags":[
        "away",
        "take"
    ],
    "wof:name":"Mr Pizza",
    "wof:placetype":"venue"
},
  "geometry": {"coordinates":[-1.779924,53.701172],"type":"Point"}
}