{
  "type": "Feature",
  "properties": {
    "addr:full":"Pellon Industrial Estate Halifax West Yorkshire HX1 4PR",
    "addr:postcode":"hx1 4pr",
    "addr:street":"Pellon Industrial Estate",
    "iso:country":"GB",
    "sg:address":"Pellon Industrial Estate",
    "sg:city":"Halifax",
    "sg:classifiers":[
        {
            "category":"Shopping",
            "subcategory":"Gifts & Souvenirs",
            "type":"Retail Goods"
        }
    ],
    "sg:phone":"+44 1422 362361",
    "sg:postcode":"HX1 4PR",
    "sg:province":"West Yorkshire",
    "sg:tags":[
        "ducting"
    ],
    "wof:name":"Hsm & V Environmental Engineers",
    "wof:placetype":"venue"
},
  "geometry": {"coordinates":[-1.862224,53.721233],"type":"Point"}
}