{
  "type": "Feature",
  "properties": {
    "addr:full":"Unit 8 Egremont Road Maidstone Kent ME15 8LH",
    "addr:housenumber":"unit 8",
    "addr:postcode":"me15 8lh",
    "addr:street":"Egremont Road",
    "iso:country":"GB",
    "sg:address":"Unit 8 Egremont Road",
    "sg:city":"Maidstone",
    "sg:classifiers":[
        {
            "category":"Food & Beverages",
            "subcategory":"Bakery",
            "type":"Retail Goods"
        }
    ],
    "sg:postcode":"ME15 8LH",
    "sg:province":"Kent",
    "sg:tags":[
        "baker"
    ],
    "wof:name":"Munchies",
    "wof:placetype":"venue"
},
  "geometry": {"coordinates":[0.5610399842,51.2652397156],"type":"Point"}
}