{
  "type": "Feature",
  "properties": {
    "addr:full":"2a St Michaels Road Newcastle Staffordshire ST5 9LW",
    "addr:housenumber":"2a",
    "addr:postcode":"st5 9lw",
    "addr:street":"St Michaels Road",
    "iso:country":"GB",
    "sg:address":"2a St Michaels Road",
    "sg:city":"Newcastle",
    "sg:classifiers":[
        {
            "category":"Retail",
            "subcategory":"Repair Shop",
            "type":"Services"
        }
    ],
    "sg:postcode":"ST5 9LW",
    "sg:province":"Staffordshire",
    "sg:tags":[
        "upholsterer"
    ],
    "wof:name":"T & M Haycock",
    "wof:placetype":"venue"
},
  "geometry": {"coordinates":[-2.2307550907,53.0214195251],"type":"Point"}
}