{
  "type": "Feature",
  "properties": {
    "addr:full":"Priests House, Main Road, Exminster Exeter Devon EX6 8AP",
    "addr:postcode":"ex6 8ap",
    "addr:street":"Main Road",
    "iso:country":"GB",
    "sg:address":"Priests House, Main Road, Exminster",
    "sg:city":"Exeter",
    "sg:classifiers":[
        {
            "category":"Professional",
            "subcategory":"Accounting & Tax Preparation",
            "type":"Services"
        }
    ],
    "sg:phone":"+44 1392 824777",
    "sg:postcode":"EX6 8AP",
    "sg:province":"Devon",
    "sg:tags":[
        "accountant"
    ],
    "wof:name":"Stephen L Williams",
    "wof:placetype":"venue"
},
  "geometry": {"coordinates":[-3.495039,50.679585],"type":"Point"}
}