{
  "type": "Feature",
  "properties": {
    "iso:country":"GB",
    "sg:address":"11 Throwley Close",
    "sg:city":"Basildon",
    "sg:classifiers":[
        {
            "category":"Building & Trades",
            "subcategory":"Plumbing",
            "type":"Services"
        },
        {
            "category":"Building & Trades",
            "subcategory":"Construction",
            "type":"Services"
        }
    ],
    "sg:phone":"+44 1268 551709",
    "sg:postcode":"SS13 2AW",
    "sg:province":"Essex",
    "sg:tags":[
        "heating",
        "contractor"
    ],
    "wof:name":"Michael J Taiani",
    "wof:placetype":"venue"
},
  "geometry": {"coordinates":[0.510653019,51.5676956177],"type":"Point"}
}