{
  "type": "Feature",
  "properties": {
    "iso:country":"GB",
    "sg:address":"Heathmans Yd, Heathmans Rd",
    "sg:city":"London",
    "sg:classifiers":[
        {
            "category":"Food & Beverages",
            "subcategory":"Liquor & Beverages",
            "type":"Retail Goods"
        }
    ],
    "sg:postcode":"SW6 4TJ",
    "sg:province":"Greater London",
    "sg:tags":[
        "beer",
        "spirit",
        "wines"
    ],
    "wof:name":"Express Beer Co (The)",
    "wof:placetype":"venue"
},
  "geometry": {"coordinates":[-0.202076,51.473999],"type":"Point"}
}