{
  "type": "Feature",
  "properties": {
    "addr:full":"Buckland House, High Street Berkhamsted Bedfordshire HP4 2BL",
    "addr:postcode":"hp4 2bl",
    "addr:street":"High Street",
    "iso:country":"GB",
    "sg:address":"Buckland House, High Street",
    "sg:city":"Berkhamsted",
    "sg:classifiers":[
        {
            "category":"Professional",
            "subcategory":"Management & Consulting",
            "type":"Services"
        }
    ],
    "sg:postcode":"HP4 2BL",
    "sg:province":"Bedfordshire",
    "sg:tags":[
        "consultant",
        "business"
    ],
    "wof:name":"Utek-Pax Ltd.",
    "wof:placetype":"venue"
},
  "geometry": {"coordinates":[-0.5656189919,51.7607307434],"type":"Point"}
}