{
  "type": "Feature",
  "properties": {
    "iso:country":"GB",
    "sg:address":"37 Poplar Grove",
    "sg:city":"Sale",
    "sg:classifiers":[
        {
            "category":"Farming",
            "subcategory":"Nursery",
            "type":"Manufacturing & Wholesale Goods"
        },
        {
            "category":"Social Services",
            "subcategory":"Child Care",
            "type":"Services"
        }
    ],
    "sg:phone":"+44 161 973 5231",
    "sg:postcode":"M33 3AX",
    "sg:province":"Cheshire",
    "sg:tags":[
        "creche"
    ],
    "wof:name":"Alphabets Day Nursery",
    "wof:placetype":"venue"
},
  "geometry": {"coordinates":[-2.3213601112,53.4192504883],"type":"Point"}
}