{
  "type": "Feature",
  "properties": {
    "addr:full":"2a Victoria Street Ripley Derbyshire DE5 3BG",
    "addr:housenumber":"2a",
    "addr:postcode":"de5 3bg",
    "addr:street":"Victoria Street",
    "iso:country":"GB",
    "sg:address":"2a Victoria Street",
    "sg:city":"Ripley",
    "sg:classifiers":[
        {
            "category":"Building & Trades",
            "subcategory":"Construction",
            "type":"Services"
        }
    ],
    "sg:phone":"+44 1773 742813",
    "sg:postcode":"DE5 3BG",
    "sg:province":"Derbyshire",
    "sg:tags":[
        "builder"
    ],
    "wof:name":"G H C Builders & Joiners",
    "wof:placetype":"venue"
},
  "geometry": {"coordinates":[-1.3966619968,53.0517425537],"type":"Point"}
}