{
  "type": "Feature",
  "properties": {
    "addr:full":"Care Of United Reformed Church, Eversfield Gardens Mill Hill Greater London NW7 2AE",
    "addr:postcode":"nw7 2ae",
    "addr:street":"Eversfield Gardens;Hill",
    "iso:country":"GB",
    "sg:address":"Care Of United Reformed Church, Eversfield Gardens",
    "sg:city":"Mill Hill",
    "sg:classifiers":[
        {
            "category":"Farming",
            "subcategory":"Nursery",
            "type":"Manufacturing & Wholesale Goods"
        }
    ],
    "sg:phone":"+44 20 8906 4370",
    "sg:postcode":"NW7 2AE",
    "sg:province":"Greater London",
    "sg:tags":[
        "creche"
    ],
    "wof:name":"AM Pre-School Nursery",
    "wof:placetype":"venue"
},
  "geometry": {"coordinates":[-0.2506099939,51.6086807251],"type":"Point"}
}