{
  "type": "Feature",
  "properties": {
    "addr:full":"7 Church Street Malvern Herefordshire WR14 2AA",
    "addr:housenumber":"7",
    "addr:postcode":"wr14 2aa",
    "addr:street":"Church Street;Herefordshire",
    "iso:country":"GB",
    "sg:address":"7 Church Street",
    "sg:city":"Malvern",
    "sg:classifiers":[
        {
            "category":"Shopping",
            "subcategory":"Shoes",
            "type":"Retail Goods"
        }
    ],
    "sg:phone":"+44 1684 573904",
    "sg:postcode":"WR14 2AA",
    "sg:province":"Herefordshire",
    "sg:tags":[
        "shop"
    ],
    "wof:name":"Robin Elt Shoes",
    "wof:placetype":"venue"
},
  "geometry": {"coordinates":[-2.329282999,52.111541748],"type":"Point"}
}