{
  "type": "Feature",
  "properties": {
    "iso:country":"GB",
    "sg:address":"Unit B Cwmdraw Industrial Estate",
    "sg:city":"Ebbw Vale",
    "sg:classifiers":[
        {
            "category":"Shopping",
            "subcategory":"Stationery & Office Supplies",
            "type":"Retail Goods"
        }
    ],
    "sg:phone":"+44 1495 303366",
    "sg:postcode":"NP23 5AE",
    "sg:province":"Blaenau Gwent",
    "sg:tags":[
        "box",
        "carton"
    ],
    "wof:name":"Capitol Packaging Ltd.",
    "wof:placetype":"venue"
},
  "geometry": {"coordinates":[-3.200026,51.777477],"type":"Point"}
}