{
  "type": "Feature",
  "properties": {
    "addr:full":"1 St. Nicholas Rd, West Boldon East Boldon Tyne and Wear NE36 0QR",
    "addr:housenumber":"1",
    "addr:postcode":"ne36 0qr",
    "addr:street":"St. Nicholas Rd West Boldon",
    "iso:country":"GB",
    "sg:address":"1 St. Nicholas Rd, West Boldon",
    "sg:city":"East Boldon",
    "sg:classifiers":[
        {
            "category":"Professional",
            "subcategory":"Engineering",
            "type":"Services"
        }
    ],
    "sg:phone":"+44 191 549 8007",
    "sg:postcode":"NE36 0QR",
    "sg:province":"Tyne and Wear",
    "sg:tags":[
        "engineer"
    ],
    "wof:name":"Building Technical Services",
    "wof:placetype":"venue"
},
  "geometry": {"coordinates":[-1.454046,54.943161],"type":"Point"}
}