{
  "type": "Feature",
  "properties": {
    "iso:country":"GB",
    "sg:address":"Clock House, Hyde Road, Denchworth",
    "sg:city":"Wantage",
    "sg:classifiers":[
        {
            "category":"Farming",
            "subcategory":"Livestock Farm",
            "type":"Manufacturing & Wholesale Goods"
        }
    ],
    "sg:phone":"+44 1235 868612",
    "sg:postcode":"OX12 0DU",
    "sg:province":"Berkshire",
    "sg:tags":[
        "others"
    ],
    "wof:name":"S L Cottrell",
    "wof:placetype":"venue"
},
  "geometry": {"coordinates":[-1.450003,51.624817],"type":"Point"}
}