{
  "type": "Feature",
  "properties": {
    "addr:full":"17 Union Passage Bath Bath and North East Somerset BA1 1RE",
    "addr:housenumber":"17",
    "addr:postcode":"ba1 1re",
    "addr:street":"Union Passage Bath",
    "iso:country":"GB",
    "sg:address":"17 Union Passage",
    "sg:city":"Bath",
    "sg:classifiers":[
        {
            "category":"Shopping",
            "subcategory":"Books",
            "type":"Retail Goods"
        },
        {
            "category":"Shopping",
            "subcategory":"Pharmacy",
            "type":"Retail Goods"
        }
    ],
    "sg:postcode":"BA1 1RE",
    "sg:province":"Bath and North East Somerset",
    "sg:tags":[
        "bookseller",
        "medicine",
        "therapy"
    ],
    "wof:name":"Arcania",
    "wof:placetype":"venue"
},
  "geometry": {"coordinates":[-2.3605649471,51.3822097778],"type":"Point"}
}