{
  "type": "Feature",
  "properties": {
    "addr:full":"Thorold Street Grimsby Lincolnshire DN31 3AL",
    "addr:postcode":"dn31 3al",
    "addr:street":"Thorold Street",
    "iso:country":"GB",
    "sg:address":"Thorold Street",
    "sg:city":"Grimsby",
    "sg:classifiers":[
        {
            "category":"Manufacturing",
            "subcategory":"Wood Products",
            "type":"Manufacturing & Wholesale Goods"
        },
        {
            "category":"Home & Garden",
            "subcategory":"Building Materials",
            "type":"Retail Goods"
        }
    ],
    "sg:phone":"+44 1472 362677",
    "sg:postcode":"DN31 3AL",
    "sg:province":"Lincolnshire",
    "sg:tags":[
        "pallet",
        "crate",
        "packaging",
        "packing",
        "pallets",
        "supplier"
    ],
    "wof:name":"CROFTON PALLETS LTD",
    "wof:placetype":"venue"
},
  "geometry": {"coordinates":[-0.064524,53.574696],"type":"Point"}
}