{
  "type": "Feature",
  "properties": {
    "iso:country":"GB",
    "sg:address":"Unit 5 155 Orford Road",
    "sg:city":"London",
    "sg:classifiers":[
        {
            "category":"Professional",
            "subcategory":"Printing & Photocopies",
            "type":"Services"
        }
    ],
    "sg:phone":"+44 20 8521 2405",
    "sg:postcode":"E17 9QU",
    "sg:province":"Greater London",
    "sg:tags":[
        "embroiderer"
    ],
    "wof:name":"Artistique Embroidery",
    "wof:placetype":"venue"
},
  "geometry": {"coordinates":[-0.0183789991,51.5801391602],"type":"Point"}
}