{
  "type": "Feature",
  "properties": {
    "addr:full":"Head Office 58 High Street, South Norwood London Greater London SE25 6EB",
    "addr:housenumber":"58",
    "addr:postcode":"se25 6eb",
    "addr:street":"High Street",
    "iso:country":"GB",
    "sg:address":"Head Office 58 High Street, South Norwood",
    "sg:city":"London",
    "sg:classifiers":[
        {
            "category":"Building & Trades",
            "subcategory":"Cleaning & Sanitation",
            "type":"Services"
        }
    ],
    "sg:phone":"+44 20 8771 7447",
    "sg:postcode":"SE25 6EB",
    "sg:province":"Greater London",
    "sg:tags":[
        "dry",
        "control",
        "damp",
        "rot"
    ],
    "wof:name":"Aspect Preservation Services",
    "wof:placetype":"venue"
},
  "geometry": {"coordinates":[-0.0736550018,51.399974823],"type":"Point"}
}