{
  "type": "Feature",
  "properties": {
    "addr:full":"78 Cross Lane, Great Horton Bradford West Yorkshire BD7 3LA",
    "addr:housenumber":"78",
    "addr:postcode":"yorkshire bd7 3la",
    "addr:street":"Cross Lane",
    "iso:country":"GB",
    "sg:address":"78 Cross Lane, Great Horton",
    "sg:city":"Bradford",
    "sg:classifiers":[
        {
            "category":"Wholesale",
            "subcategory":"Metals & Minerals",
            "type":"Manufacturing & Wholesale Goods"
        }
    ],
    "sg:phone":"+44 1274 571719",
    "sg:postcode":"BD7 3LA",
    "sg:province":"West Yorkshire",
    "sg:tags":[
        "non-ferrous"
    ],
    "wof:name":"Cross Lane Foundry",
    "wof:placetype":"venue"
},
  "geometry": {"coordinates":[-1.7812210321,53.7801818848],"type":"Point"}
}