{
  "type": "Feature",
  "properties": {
    "addr:full":"45 Park Street Oldbury West Midlands B69 4LJ",
    "addr:housenumber":"45",
    "addr:postcode":"b69 4lj",
    "addr:street":"Park Street",
    "iso:country":"GB",
    "sg:address":"45 Park Street",
    "sg:city":"Oldbury",
    "sg:classifiers":[
        {
            "category":"Manufacturing",
            "subcategory":"Building Materials",
            "type":"Manufacturing & Wholesale Goods"
        }
    ],
    "sg:phone":"+44 121 552 3170",
    "sg:postcode":"B69 4LJ",
    "sg:province":"West Midlands",
    "sg:tags":[
        "merchant",
        "builder"
    ],
    "wof:name":"Sandwell Builders & Plumbers Supplies Ltd.",
    "wof:placetype":"venue"
},
  "geometry": {"coordinates":[-2.015068,52.494862],"type":"Point"}
}