{
  "type": "Feature",
  "properties": {
    "iso:country":"GB",
    "sg:address":"157 Evington Road",
    "sg:city":"Leicester",
    "sg:classifiers":[
        {
            "category":"Manufacturing",
            "subcategory":"Tools & Machinery",
            "type":"Manufacturing & Wholesale Goods"
        }
    ],
    "sg:phone":"+44 116 273 9090",
    "sg:postcode":"LE2 1QL",
    "sg:province":"Leicestershire",
    "sg:tags":[
        "society",
        "friendly"
    ],
    "wof:name":"Seth Estate & Insurance Agents",
    "wof:placetype":"venue"
},
  "geometry": {"coordinates":[-1.108911,52.625504],"type":"Point"}
}