{
  "type": "Feature",
  "properties": {
    "iso:country":"GB",
    "sg:address":"107 South Avenue",
    "sg:city":"Abingdon",
    "sg:classifiers":[
        {
            "category":"Retail",
            "subcategory":"Funeral Services",
            "type":"Services"
        }
    ],
    "sg:phone":"+44 1235 528293",
    "sg:postcode":"OX14 1QS",
    "sg:province":"Oxfordshire",
    "sg:tags":[
        "director"
    ],
    "wof:name":"Edward Carter",
    "wof:placetype":"venue"
},
  "geometry": {"coordinates":[-1.276497,51.686058],"type":"Point"}
}