{
  "type": "Feature",
  "properties": {
    "iso:country":"GB",
    "sg:address":"Martins Rd",
    "sg:city":"Bristol",
    "sg:classifiers":[
        {
            "category":"Shopping",
            "subcategory":"Catalog Store",
            "type":"Retail Goods"
        }
    ],
    "sg:phone":"+44 117 975 0350",
    "sg:postcode":"BS15 3DY",
    "sg:province":"City of Bristol",
    "sg:tags":[
        "mail",
        "order"
    ],
    "wof:name":"Kleeneze Ltd",
    "wof:placetype":"venue"
},
  "geometry": {"coordinates":[-2.516159,51.448589],"type":"Point"}
}