{
  "type": "Feature",
  "properties": {
    "iso:country":"GB",
    "sg:address":"36 Leeds Road",
    "sg:city":"Harrogate",
    "sg:classifiers":[
        {
            "category":"Health Services",
            "subcategory":"Nursing And Care Facility",
            "type":"Services"
        }
    ],
    "sg:postcode":"HG2 8BQ",
    "sg:province":"North Yorkshire",
    "sg:tags":[
        "home"
    ],
    "wof:name":"Minster View",
    "wof:placetype":"venue"
},
  "geometry": {"coordinates":[-1.5363919735,53.9816932678],"type":"Point"}
}