{
  "type": "Feature",
  "properties": {
    "addr:full":"8 Valley View Barnet Hertfordshire EN5 2NY",
    "addr:housenumber":"8",
    "addr:postcode":"en5 2ny",
    "addr:street":"Valley View",
    "iso:country":"GB",
    "sg:address":"8 Valley View",
    "sg:city":"Barnet",
    "sg:classifiers":[
        {
            "category":"Retail",
            "subcategory":"Driving School",
            "type":"Services"
        }
    ],
    "sg:postcode":"EN5 2NY",
    "sg:province":"Hertfordshire",
    "wof:name":"Bearne Driving Tuition",
    "wof:placetype":"venue"
},
  "geometry": {"coordinates":[-0.2042769939,51.6439476013],"type":"Point"}
}