{
  "type": "Feature",
  "properties": {
    "addr:full":"1 The Broadway Crowborough East Sussex TN6 1DF",
    "addr:housenumber":"1",
    "addr:postcode":"tn6 1df",
    "addr:street":"The Broadway",
    "iso:country":"GB",
    "sg:address":"1 The Broadway",
    "sg:city":"Crowborough",
    "sg:classifiers":[
        {
            "category":"Social Services",
            "subcategory":"Job Training",
            "type":"Services"
        }
    ],
    "sg:postcode":"TN6 1DF",
    "sg:province":"East Sussex",
    "sg:tags":[
        "translator",
        "interpreter"
    ],
    "wof:name":"Wordland",
    "wof:placetype":"venue"
},
  "geometry": {"coordinates":[0.1624120027,51.0588798523],"type":"Point"}
}