{
  "type": "Feature",
  "properties": {
    "iso:country":"GB",
    "sg:address":"Stirling House, Stirling Road, Surrey Research Park",
    "sg:city":"Guildford",
    "sg:classifiers":[
        {
            "category":"Professional",
            "subcategory":"Computer Services",
            "type":"Services"
        }
    ],
    "sg:phone":"+44 1483 883000",
    "sg:postcode":"GU2 7RF",
    "sg:province":"Surrey",
    "sg:tags":[
        "development",
        "system",
        "software"
    ],
    "wof:name":"Applied Network Technology Ltd.",
    "wof:placetype":"venue"
},
  "geometry": {"coordinates":[-0.610879004,51.2414131165],"type":"Point"}
}