{
  "type": "Feature",
  "properties": {
    "addr:full":"Unit 5a, 50 Pingle Drive, Bicester Retail Park Bicester Oxfordshire OX26 6WD",
    "addr:housenumber":"unit 5a 50",
    "addr:postcode":"ox26 6wd",
    "addr:street":"Pingle Drive;Retail Park",
    "iso:country":"GB",
    "sg:address":"Unit 5a, 50 Pingle Drive, Bicester Retail Park",
    "sg:city":"Bicester",
    "sg:classifiers":[
        {
            "category":"Shopping",
            "subcategory":"Clothing, Apparel, & Fashions",
            "type":"Retail Goods"
        }
    ],
    "sg:phone":"+44 1869 369415",
    "sg:postcode":"OX26 6WD",
    "sg:province":"Oxfordshire",
    "sg:tags":[
        "shop"
    ],
    "wof:name":"Inwear Matinique",
    "wof:placetype":"venue"
},
  "geometry": {"coordinates":[-1.1563600302,51.893081665],"type":"Point"}
}