{
  "type": "Feature",
  "properties": {
    "addr:full":"9 Chiswick High Rd Chiswick Greater London W4 2ND",
    "addr:housenumber":"9",
    "addr:postcode":"w4 2nd",
    "addr:street":"Chiswick High Rd",
    "iso:country":"GB",
    "sg:address":"9 Chiswick High Rd",
    "sg:city":"Chiswick",
    "sg:classifiers":[
        {
            "category":"Professional",
            "subcategory":"Management & Consulting",
            "type":"Services"
        }
    ],
    "sg:phone":"+44 20 8994 0066",
    "sg:postcode":"W4 2ND",
    "sg:province":"Greater London",
    "sg:tags":[
        "marketing",
        "consultant"
    ],
    "wof:name":"Marketing Office,The",
    "wof:placetype":"venue"
},
  "geometry": {"coordinates":[-0.2514800131,51.4922065735],"type":"Point"}
}