{
  "type": "Feature",
  "properties": {
    "addr:full":"35 Myddelton Street London Greater London EC1R 1UA",
    "addr:housenumber":"35",
    "addr:postcode":"ec1r 1ua",
    "addr:street":"Myddelton Street",
    "iso:country":"GB",
    "sg:address":"35 Myddelton Street",
    "sg:city":"London",
    "sg:classifiers":[
        {
            "category":"Food & Beverages",
            "subcategory":"Specialty",
            "type":"Retail Goods"
        }
    ],
    "sg:postcode":"EC1R 1UA",
    "sg:province":"Greater London",
    "sg:tags":[
        "product",
        "health"
    ],
    "wof:name":"Rye Wholefoods",
    "wof:placetype":"venue"
},
  "geometry": {"coordinates":[-0.1051189974,51.5276298523],"type":"Point"}
}