{
  "type": "Feature",
  "properties": {
    "addr:full":"Portland House, Moor View Leeds West Yorkshire LS11 9NF",
    "addr:postcode":"ls11 9nf",
    "addr:street":"Moor View",
    "iso:country":"GB",
    "sg:address":"Portland House, Moor View",
    "sg:city":"Leeds",
    "sg:classifiers":[
        {
            "category":"Professional",
            "subcategory":"Engineering",
            "type":"Services"
        }
    ],
    "sg:phone":"+44 113 243 2366",
    "sg:postcode":"LS11 9NF",
    "sg:province":"West Yorkshire",
    "sg:tags":[
        "contractor",
        "electrical",
        "engineer"
    ],
    "wof:name":"Baker & Hyman Ltd.",
    "wof:placetype":"venue"
},
  "geometry": {"coordinates":[-1.553637,53.78466],"type":"Point"}
}