{
  "type": "Feature",
  "properties": {
    "iso:country":"GB",
    "sg:address":"'voila', Station Road, Brent Knoll",
    "sg:city":"Highbridge",
    "sg:classifiers":[
        {
            "category":"Building & Trades",
            "subcategory":"Construction",
            "type":"Services"
        }
    ],
    "sg:phone":"+44 1278 760455",
    "sg:postcode":"TA9 4BH",
    "sg:province":"Somerset",
    "sg:tags":[
        "builder"
    ],
    "wof:name":"E W Jones Brothers",
    "wof:placetype":"venue"
},
  "geometry": {"coordinates":[-2.96676,51.258438],"type":"Point"}
}