{
  "type": "Feature",
  "properties": {
    "iso:country":"GB",
    "sg:address":"300 Plymouth Road, Crabtree",
    "sg:city":"Plymouth",
    "sg:classifiers":[
        {
            "category":"Restaurant",
            "type":"Food & Drink"
        }
    ],
    "sg:postcode":"PL3 6RW",
    "sg:province":"Devon",
    "wof:name":"Beefeater & Travel Inn",
    "wof:placetype":"venue"
},
  "geometry": {"coordinates":[-4.08788,50.390728],"type":"Point"}
}