{
  "type": "Feature",
  "properties": {
    "addr:full":"Fawcus Place Chard Devon TA20 1LW",
    "addr:postcode":"ta20 1lw",
    "addr:street":"Place",
    "iso:country":"GB",
    "sg:address":"Fawcus Place",
    "sg:city":"Chard",
    "sg:classifiers":[
        {
            "category":"Social Services",
            "subcategory":"Adult Care",
            "type":"Services"
        },
        {
            "category":"Government",
            "subcategory":"Office",
            "type":"Public Place"
        }
    ],
    "sg:phone":"+44 1460 63691",
    "sg:postcode":"TA20 1LW",
    "sg:province":"Devon",
    "sg:tags":[
        "housing",
        "local",
        "sheltered"
    ],
    "wof:name":"Fawcus Place Sheltered Housing",
    "wof:placetype":"venue"
},
  "geometry": {"coordinates":[-2.9681780338,50.8737869263],"type":"Point"}
}