{
  "type": "Feature",
  "properties": {
    "addr:full":"473 Stanningley Road, Bramley Leeds West Yorkshire LS13 4AP",
    "addr:housenumber":"473",
    "addr:postcode":"ls13 4ap",
    "addr:street":"Stanningley Road",
    "iso:country":"GB",
    "sg:address":"473 Stanningley Road, Bramley",
    "sg:city":"Leeds",
    "sg:classifiers":[
        {
            "category":"Home & Garden",
            "subcategory":"Carpets & Floor Coverings",
            "type":"Retail Goods"
        }
    ],
    "sg:phone":"+44 113 255 0477",
    "sg:postcode":"LS13 4AP",
    "sg:province":"West Yorkshire",
    "sg:tags":[
        "carpets",
        "rug",
        "matting"
    ],
    "wof:name":"Carpet Corner",
    "wof:placetype":"venue"
},
  "geometry": {"coordinates":[-1.632851,53.805908],"type":"Point"}
}