{
  "type": "Feature",
  "properties": {
    "iso:country":"GB",
    "sg:address":"Beechwood, Diss Road",
    "sg:city":"Diss",
    "sg:classifiers":[
        {
            "category":"Professional",
            "subcategory":"Engineering",
            "type":"Services"
        }
    ],
    "sg:postcode":"IP22 5TP",
    "sg:province":"Norfolk",
    "sg:tags":[
        "finishing",
        "printing"
    ],
    "wof:name":"Printech East Anglia",
    "wof:placetype":"venue"
},
  "geometry": {"coordinates":[1.111036,52.373421],"type":"Point"}
}