{
  "type": "Feature",
  "properties": {
    "addr:full":"256 Gospel Lane, Olton Birmingham West Midlands B27 7AH",
    "addr:housenumber":"256",
    "addr:postcode":"b27 7ah",
    "addr:street":"Gospel Lane",
    "iso:country":"GB",
    "sg:address":"256 Gospel Lane, Olton",
    "sg:city":"Birmingham",
    "sg:classifiers":[
        {
            "category":"Fast Food",
            "type":"Food & Drink"
        }
    ],
    "sg:phone":"+44 121 707 8750",
    "sg:postcode":"B27 7AH",
    "sg:province":"West Midlands",
    "sg:tags":[
        "away",
        "take"
    ],
    "wof:name":"Tandoori Night",
    "wof:placetype":"venue"
},
  "geometry": {"coordinates":[-1.816607,52.434448],"type":"Point"}
}