{
  "type": "Feature",
  "properties": {
    "iso:country":"GB",
    "sg:address":"9 Brixton Station Road",
    "sg:city":"London",
    "sg:classifiers":[
        {
            "category":"Shopping",
            "subcategory":"Comic Books",
            "type":"Retail Goods"
        }
    ],
    "sg:phone":"+44 20 7737 5074",
    "sg:postcode":"SW9 8PA",
    "sg:province":"Greater London",
    "sg:tags":[
        "jeweller",
        "sale",
        "jewellery"
    ],
    "wof:name":"Gold Discount Jewellery",
    "wof:placetype":"venue"
},
  "geometry": {"coordinates":[-0.114178,51.463482],"type":"Point"}
}