{
  "type": "Feature",
  "properties": {
    "addr:full":"11 Warwick Way London Greater London SW1V 1QT",
    "addr:housenumber":"11",
    "addr:postcode":"sw1v 1qt",
    "addr:street":"Warwick Way",
    "iso:country":"GB",
    "sg:address":"11 Warwick Way",
    "sg:city":"London",
    "sg:classifiers":[
        {
            "category":"Bars & Pubs",
            "type":"Food & Drink"
        }
    ],
    "sg:phone":"+44 20 7834 3313",
    "sg:postcode":"SW1V 1QT",
    "sg:province":"Greater London",
    "sg:tags":[
        "pubs",
        "inn"
    ],
    "wof:name":"The Slug & Lettuce",
    "wof:placetype":"venue"
},
  "geometry": {"coordinates":[-0.139125,51.492569],"type":"Point"}
}