{
  "type": "Feature",
  "properties": {
    "addr:full":"St Nicholas Centre, St Nicholas St Aberdeen Aberdeen City AB10 1HW",
    "addr:postcode":"ab10 1hw",
    "addr:street":"St Nicholas St",
    "iso:country":"GB",
    "sg:address":"St Nicholas Centre, St Nicholas St",
    "sg:city":"Aberdeen",
    "sg:classifiers":[
        {
            "category":"Communications",
            "subcategory":"Film & Video Production",
            "type":"Services"
        }
    ],
    "sg:phone":"+44 1224 690895",
    "sg:postcode":"AB10 1HW",
    "sg:province":"Aberdeen City",
    "sg:tags":[
        "illustrator",
        "artist"
    ],
    "wof:name":"Dial An Artist",
    "wof:placetype":"venue"
},
  "geometry": {"coordinates":[-2.098106,57.147346],"type":"Point"}
}