{
  "type": "Feature",
  "properties": {
    "iso:country":"GB",
    "sg:address":"157 Main St, Cayton",
    "sg:city":"Scarborough",
    "sg:classifiers":[
        {
            "category":"Health Services",
            "subcategory":"Health Practitioner",
            "type":"Services"
        }
    ],
    "sg:phone":"+44 1723 582338",
    "sg:postcode":"YO11 3TF",
    "sg:province":"North Yorkshire",
    "sg:tags":[
        "acupuncture"
    ],
    "wof:name":"Margaret Rukin M.B.AcC S.R.N",
    "wof:placetype":"venue"
},
  "geometry": {"coordinates":[-0.375064,54.231728],"type":"Point"}
}