{
  "type": "Feature",
  "properties": {
    "addr:full":"97-99 Wellingborough Road, Finedon Wellingborough Northamptonshire NN9 5LG",
    "addr:housenumber":"97-99",
    "addr:postcode":"nn9 5lg",
    "addr:street":"Wellingborough Road",
    "iso:country":"GB",
    "sg:address":"97-99 Wellingborough Road, Finedon",
    "sg:city":"Wellingborough",
    "sg:classifiers":[
        {
            "category":"Autos & Motor Vehicles",
            "subcategory":"Motorcycle Sales",
            "type":"Retail Goods"
        }
    ],
    "sg:phone":"+44 1933 680274",
    "sg:postcode":"NN9 5LG",
    "sg:province":"Northamptonshire",
    "wof:name":"Anchor Kawasaki Centre",
    "wof:placetype":"venue"
},
  "geometry": {"coordinates":[-0.6548219919,52.3370895386],"type":"Point"}
}