{
  "type": "Feature",
  "properties": {
    "addr:full":"55 Station Road London Greater London E12 5BP",
    "addr:housenumber":"55",
    "addr:postcode":"e12 5bp",
    "addr:street":"Station Road",
    "iso:country":"GB",
    "sg:address":"55 Station Road",
    "sg:city":"London",
    "sg:classifiers":[
        {
            "category":"Shopping",
            "subcategory":"Hobbies, Toys, & Games",
            "type":"Retail Goods"
        },
        {
            "category":"Transit Center",
            "subcategory":"Freight",
            "type":"Transportation"
        }
    ],
    "sg:phone":"+44 20 7922 6436",
    "sg:postcode":"E12 5BP",
    "sg:province":"Greater London",
    "sg:tags":[
        "collectors'",
        "item",
        "collector"
    ],
    "wof:name":"COLLECTORS CORNER",
    "wof:placetype":"venue"
},
  "geometry": {"coordinates":[0.046522,51.552391],"type":"Point"}
}