{
  "type": "Feature",
  "properties": {
    "addr:full":"4a Broad St Lyme Regis Devon DT7 3QD",
    "addr:housenumber":"4a",
    "addr:postcode":"dt7 3qd",
    "addr:street":"Broad St",
    "iso:country":"GB",
    "sg:address":"4a Broad St",
    "sg:city":"Lyme Regis",
    "sg:classifiers":[
        {
            "category":"Manufacturing",
            "subcategory":"Textiles",
            "type":"Manufacturing & Wholesale Goods"
        }
    ],
    "sg:phone":"+44 1297 445737",
    "sg:postcode":"DT7 3QD",
    "sg:province":"Devon",
    "sg:tags":[
        "made-up"
    ],
    "wof:name":"Creative Interiors",
    "wof:placetype":"venue"
},
  "geometry": {"coordinates":[-2.933711,50.724445],"type":"Point"}
}