{
  "type": "Feature",
  "properties": {
    "addr:full":"131 Entwisle Road Rochdale Lancashire OL16 2JJ",
    "addr:housenumber":"131",
    "addr:postcode":"ol16 2jj",
    "addr:street":"Entwisle Road",
    "iso:country":"GB",
    "sg:address":"131 Entwisle Road",
    "sg:city":"Rochdale",
    "sg:classifiers":[
        {
            "category":"Community Center",
            "type":"Public Place"
        }
    ],
    "sg:phone":"+44 1706 860349",
    "sg:postcode":"OL16 2JJ",
    "sg:province":"Lancashire",
    "sg:tags":[
        "centre"
    ],
    "wof:name":"Bangladesh Association & Community Project",
    "wof:placetype":"venue"
},
  "geometry": {"coordinates":[-2.1454410553,53.6195030212],"type":"Point"}
}