{
  "type": "Feature",
  "properties": {
    "iso:country":"GB",
    "sg:address":"54 Southern Road",
    "sg:city":"Basingstoke",
    "sg:classifiers":[
        {
            "category":"Cinema",
            "subcategory":"Movie Rental",
            "type":"Entertainment"
        }
    ],
    "sg:postcode":"RG21 3EA",
    "sg:province":"Hampshire",
    "sg:tags":[
        "video",
        "library"
    ],
    "wof:name":"G PARSON",
    "wof:placetype":"venue"
},
  "geometry": {"coordinates":[-1.0870469809,51.2609405518],"type":"Point"}
}