{
  "type": "Feature",
  "properties": {
    "addr:full":"Wallerscote House, Winnington Lane Northwich Cheshire CW8 4EG",
    "addr:postcode":"cw8 4eg",
    "addr:street":"Winnington Lane",
    "iso:country":"GB",
    "sg:address":"Wallerscote House, Winnington Lane",
    "sg:city":"Northwich",
    "sg:classifiers":[
        {
            "category":"Health Services",
            "subcategory":"Dentist",
            "type":"Services"
        }
    ],
    "sg:phone":"+44 1606 871000",
    "sg:postcode":"CW8 4EG",
    "sg:province":"Cheshire",
    "sg:tags":[
        "technician",
        "dental"
    ],
    "wof:name":"David Morris Dental Ceramics",
    "wof:placetype":"venue"
},
  "geometry": {"coordinates":[-2.538088,53.268414],"type":"Point"}
}