{
  "type": "Feature",
  "properties": {
    "iso:country":"GB",
    "sg:address":"25 Richville Road",
    "sg:city":"Southampton",
    "sg:classifiers":[
        {
            "category":"Shopping",
            "subcategory":"Computers & Home Electronics",
            "type":"Retail Goods"
        }
    ],
    "sg:phone":"+44 23 8049 9100",
    "sg:postcode":"SO16 4GH",
    "sg:province":"Hampshire",
    "sg:tags":[
        "sound",
        "equipment"
    ],
    "wof:name":"Moses Media Systems Ltd.",
    "wof:placetype":"venue"
},
  "geometry": {"coordinates":[-1.440381,50.923172],"type":"Point"}
}