{
  "type": "Feature",
  "properties": {
    "addr:full":"Unit 75-76 Askern Industrial Estate, Moss Rd Doncaster North Yorkshire DN6 0DD",
    "addr:housenumber":"unit 75-76",
    "addr:postcode":"dn6 0dd",
    "addr:street":"Askern Industrial Estate Moss Rd",
    "iso:country":"GB",
    "sg:address":"Unit 75-76 Askern Industrial Estate, Moss Rd",
    "sg:city":"Doncaster",
    "sg:classifiers":[
        {
            "category":"Professional",
            "type":"Services"
        }
    ],
    "sg:phone":"+44 1302 708526",
    "sg:postcode":"DN6 0DD",
    "sg:province":"North Yorkshire",
    "sg:tags":[
        "services",
        "belt",
        "conveyor"
    ],
    "wof:name":"UK Belt Technology",
    "wof:placetype":"venue"
},
  "geometry": {"coordinates":[-1.13878,53.616657],"type":"Point"}
}