{
  "type": "Feature",
  "properties": {
    "iso:country":"GB",
    "sg:address":"11 Traverse Street",
    "sg:city":"Norwich",
    "sg:classifiers":[
        {
            "category":"Professional",
            "subcategory":"Accounting & Tax Preparation",
            "type":"Services"
        }
    ],
    "sg:phone":"+44 1603 410754",
    "sg:postcode":"NR3 1EQ",
    "sg:province":"Norfolk",
    "sg:tags":[
        "accountant",
        "activity"
    ],
    "wof:name":"Geoffrey G Dyer",
    "wof:placetype":"venue"
},
  "geometry": {"coordinates":[1.293466,52.642429],"type":"Point"}
}