{
  "type": "Feature",
  "properties": {
    "addr:full":"5 Marsh Street Bristol City of Bristol BS1 4TH",
    "addr:housenumber":"5",
    "addr:postcode":"bs1 4th",
    "addr:street":"Marsh Street",
    "iso:country":"GB",
    "sg:address":"5 Marsh Street",
    "sg:city":"Bristol",
    "sg:classifiers":[
        {
            "category":"Real Estate",
            "subcategory":"Real Estate Agent",
            "type":"Services"
        }
    ],
    "sg:postcode":"BS1 4TH",
    "sg:province":"City of Bristol",
    "wof:name":"Gordian Properties Ltd.",
    "wof:placetype":"venue"
},
  "geometry": {"coordinates":[-2.596026,51.453041],"type":"Point"}
}