{
  "type": "Feature",
  "properties": {
    "addr:full":"Perch Bldgs, 20 West Bute St Cardiff Cardiff CF10 5GE",
    "addr:housenumber":"20",
    "addr:postcode":"cf10 5ge",
    "addr:street":"West Bute St",
    "iso:country":"GB",
    "sg:address":"Perch Bldgs, 20 West Bute St",
    "sg:city":"Cardiff",
    "sg:classifiers":[
        {
            "category":"Recreation",
            "subcategory":"Campground",
            "type":"Entertainment"
        }
    ],
    "sg:postcode":"CF10 5GE",
    "sg:province":"Cardiff",
    "sg:tags":[
        "caravan",
        "park"
    ],
    "wof:name":"Greenfields Leisure Ltd",
    "wof:placetype":"venue"
},
  "geometry": {"coordinates":[-3.180669,51.481258],"type":"Point"}
}