{
  "type": "Feature",
  "properties": {
    "addr:full":"Unit 12 City Industrial Park, Southern Road Southampton Hampshire SO15 1HA",
    "addr:housenumber":"unit 12",
    "addr:postcode":"so15 1ha",
    "addr:street":"City Industrial Park Southern Road",
    "iso:country":"GB",
    "sg:address":"Unit 12 City Industrial Park, Southern Road",
    "sg:city":"Southampton",
    "sg:classifiers":[
        {
            "category":"Autos & Motor Vehicles",
            "subcategory":"Auto Supplies",
            "type":"Retail Goods"
        },
        {
            "category":"Retail",
            "subcategory":"Auto Repair",
            "type":"Services"
        }
    ],
    "sg:phone":"+44 23 8033 8555",
    "sg:postcode":"SO15 1HA",
    "sg:province":"Hampshire",
    "sg:tags":[
        "windscreen",
        "replacement"
    ],
    "wof:name":"24HR Mobile Windscreens",
    "wof:placetype":"venue"
},
  "geometry": {"coordinates":[-1.4073189497,50.9099388123],"type":"Point"}
}