{
  "type": "Feature",
  "properties": {
    "iso:country":"GB",
    "sg:address":"266 Harrow Road",
    "sg:city":"London",
    "sg:classifiers":[
        {
            "category":"Food & Beverages",
            "subcategory":"Supermarket",
            "type":"Retail Goods"
        }
    ],
    "sg:phone":"+44 20 7286 5919",
    "sg:postcode":"W2 5ES",
    "sg:province":"Greater London",
    "wof:name":"Warwick Food Centre",
    "wof:placetype":"venue"
},
  "geometry": {"coordinates":[-0.191373,51.520744],"type":"Point"}
}