{
  "type": "Feature",
  "properties": {
    "addr:full":"Middleton Lime Works, Middleton Gorebridge Midlothian EH23 4QP",
    "addr:postcode":"eh23 4qp",
    "iso:country":"GB",
    "sg:address":"Middleton Lime Works, Middleton",
    "sg:city":"Gorebridge",
    "sg:classifiers":[
        {
            "category":"Manufacturing",
            "subcategory":"Glass & Minerals",
            "type":"Manufacturing & Wholesale Goods"
        }
    ],
    "sg:phone":"+44 1875 820339",
    "sg:postcode":"EH23 4QP",
    "sg:province":"Midlothian",
    "sg:tags":[
        "chalk",
        "stone",
        "slate"
    ],
    "wof:name":"Reid James & Co",
    "wof:placetype":"venue"
},
  "geometry": {"coordinates":[-3.04762,55.841717],"type":"Point"}
}