{
  "type": "Feature",
  "properties": {
    "iso:country":"GB",
    "sg:address":"28 St Georges Street",
    "sg:city":"Canterbury",
    "sg:classifiers":[
        {
            "category":"Sports & Exercise",
            "subcategory":"Sports Center",
            "type":"Entertainment"
        }
    ],
    "sg:postcode":"CT1 2SS",
    "sg:province":"Kent",
    "sg:tags":[
        "shop",
        "good"
    ],
    "wof:name":"Stylo Barratt Shoes Ltd.",
    "wof:placetype":"venue"
},
  "geometry": {"coordinates":[1.0826029778,51.2772827148],"type":"Point"}
}