{
  "type": "Feature",
  "properties": {
    "addr:full":"Unit 8 Paardeberg Road, Walker Lines Industrial Estate Bodmin Cornwall PL31 1EY",
    "addr:housenumber":"unit 8",
    "addr:postcode":"pl31 1ey",
    "addr:street":"Paardeberg Road;Lines Industrial Estate",
    "iso:country":"GB",
    "sg:address":"Unit 8 Paardeberg Road, Walker Lines Industrial Estate",
    "sg:city":"Bodmin",
    "sg:classifiers":[
        {
            "category":"Autos & Motor Vehicles",
            "subcategory":"Auto Supplies",
            "type":"Retail Goods"
        }
    ],
    "sg:phone":"+44 1208 77492",
    "sg:postcode":"PL31 1EY",
    "sg:province":"Cornwall",
    "sg:tags":[
        "tyre"
    ],
    "wof:name":"A1 Bodmin Discount Tyres & Exhausts",
    "wof:placetype":"venue"
},
  "geometry": {"coordinates":[-4.7050480843,50.4594230652],"type":"Point"}
}