{
  "type": "Feature",
  "properties": {
    "addr:full":"Commsworld House, 37-45 Peffer Place Edinburgh City of Edinburgh EH16 4BB",
    "addr:housenumber":"37-45",
    "addr:postcode":"eh16 4bb",
    "addr:street":"Peffer Place Edinburgh",
    "iso:country":"GB",
    "sg:address":"Commsworld House, 37-45 Peffer Place",
    "sg:city":"Edinburgh",
    "sg:classifiers":[
        {
            "category":"Communications",
            "type":"Services"
        }
    ],
    "sg:phone":"+44 131 661 3335",
    "sg:postcode":"EH16 4BB",
    "sg:province":"City of Edinburgh",
    "sg:tags":[
        "telecommunication"
    ],
    "wof:name":"Commsworld Management Services Ltd.",
    "wof:placetype":"venue"
},
  "geometry": {"coordinates":[-3.1411790848,55.9347686768],"type":"Point"}
}