{
  "type": "Feature",
  "properties": {
    "iso:country":"GB",
    "sg:address":"6 Devonshire Rd",
    "sg:city":"Buxton",
    "sg:classifiers":[
        {
            "category":"Health Services",
            "subcategory":"Nursing And Care Facility",
            "type":"Services"
        }
    ],
    "sg:postcode":"SK17 6RZ",
    "sg:province":"Derbyshire",
    "sg:tags":[
        "home"
    ],
    "wof:name":"Devonshire Nursing Home",
    "wof:placetype":"venue"
},
  "geometry": {"coordinates":[-1.917611,53.261494],"type":"Point"}
}