{
  "type": "Feature",
  "properties": {
    "addr:full":"60 King Street, Thorne Doncaster East Riding of Yorkshire DN8 5BA",
    "addr:housenumber":"60",
    "addr:postcode":"dn8 5ba",
    "addr:street":"King Street;Riding",
    "iso:country":"GB",
    "sg:address":"60 King Street, Thorne",
    "sg:city":"Doncaster",
    "sg:classifiers":[
        {
            "category":"Autos & Motor Vehicles",
            "subcategory":"Motorcycle Sales",
            "type":"Retail Goods"
        }
    ],
    "sg:phone":"+44 1405 740248",
    "sg:postcode":"DN8 5BA",
    "sg:province":"East Riding of Yorkshire",
    "wof:name":"Ken Urwin",
    "wof:placetype":"venue"
},
  "geometry": {"coordinates":[-0.9634019732,53.6124572754],"type":"Point"}
}