{
  "type": "Feature",
  "properties": {
    "addr:full":"London Road Downham Market Cambridgeshire PE38 9BH",
    "addr:postcode":"pe38 9bh",
    "addr:street":"London Road",
    "iso:country":"GB",
    "sg:address":"London Road",
    "sg:city":"Downham Market",
    "sg:classifiers":[
        {
            "category":"Retail",
            "subcategory":"Auto Repair",
            "type":"Services"
        }
    ],
    "sg:phone":"+44 1366 383397",
    "sg:postcode":"PE38 9BH",
    "sg:province":"Cambridgeshire",
    "sg:tags":[
        "modification",
        "garage"
    ],
    "wof:name":"Jim Russell",
    "wof:placetype":"venue"
},
  "geometry": {"coordinates":[0.378145,52.60173],"type":"Point"}
}