{
  "type": "Feature",
  "properties": {
    "addr:full":"Unit 25 The Forum, 127-129 Devonshire Street Sheffield South Yorkshire S3 7SB",
    "addr:housenumber":"unit 25 the forum 127-129",
    "addr:postcode":"s3 7sb",
    "addr:street":"Devonshire Street",
    "iso:country":"GB",
    "sg:address":"Unit 25 The Forum, 127-129 Devonshire Street",
    "sg:city":"Sheffield",
    "sg:classifiers":[
        {
            "category":"Shopping",
            "subcategory":"Gifts & Souvenirs",
            "type":"Retail Goods"
        }
    ],
    "sg:phone":"+44 114 249 1311",
    "sg:postcode":"S3 7SB",
    "sg:province":"South Yorkshire",
    "sg:tags":[
        "shop"
    ],
    "wof:name":"The Golden Harvest",
    "wof:placetype":"venue"
},
  "geometry": {"coordinates":[-1.47727,53.379372],"type":"Point"}
}