{
  "type": "Feature",
  "properties": {
    "addr:full":"58-60 Longbridge Rd Barking Essex IG11 8RT",
    "addr:housenumber":"58-60",
    "addr:postcode":"ig11 8rt",
    "addr:street":"Longbridge Rd",
    "iso:country":"GB",
    "sg:address":"58-60 Longbridge Rd",
    "sg:city":"Barking",
    "sg:classifiers":[
        {
            "category":"Building & Trades",
            "subcategory":"Construction",
            "type":"Services"
        }
    ],
    "sg:postcode":"IG11 8RT",
    "sg:province":"Essex",
    "sg:tags":[
        "builder"
    ],
    "wof:name":"Chudleigh Construction Ltd",
    "wof:placetype":"venue"
},
  "geometry": {"coordinates":[0.082625,51.540119],"type":"Point"}
}