{
  "type": "Feature",
  "properties": {
    "addr:full":"60 Copthall Lane, Chalfont St Peter Gerrards Cross Buckinghamshire SL9 0DJ",
    "addr:housenumber":"60",
    "addr:postcode":"sl9 0dj",
    "addr:street":"Copthall Lane",
    "iso:country":"GB",
    "sg:address":"60 Copthall Lane, Chalfont St Peter",
    "sg:city":"Gerrards Cross",
    "sg:classifiers":[
        {
            "category":"Real Estate",
            "subcategory":"Surveying",
            "type":"Services"
        }
    ],
    "sg:phone":"+44 1753 885659",
    "sg:postcode":"SL9 0DJ",
    "sg:province":"Buckinghamshire",
    "sg:tags":[
        "surveyor",
        "valuer"
    ],
    "wof:name":"R W LARMAN ASSOCIATES",
    "wof:placetype":"venue"
},
  "geometry": {"coordinates":[-0.5467330217,51.6116065979],"type":"Point"}
}