{
  "type": "Feature",
  "properties": {
    "addr:full":"North Road, Church Street Brighton East Sussex BN1 1YA",
    "addr:postcode":"bn1 1ya",
    "addr:street":"North Road Church Street",
    "iso:country":"GB",
    "sg:address":"North Road, Church Street",
    "sg:city":"Brighton",
    "sg:classifiers":[
        {
            "category":"Sports & Exercise",
            "subcategory":"Swimming Pool",
            "type":"Entertainment"
        }
    ],
    "sg:phone":"+44 1273 685692",
    "sg:postcode":"BN1 1YA",
    "sg:province":"East Sussex",
    "wof:name":"Prince Regent Swimming Complex",
    "wof:placetype":"venue"
},
  "geometry": {"coordinates":[-0.139594,50.825729],"type":"Point"}
}