{
  "type": "Feature",
  "properties": {
    "addr:full":"2 Harvester Place, Ditcheat Shepton Mallet Somerset BA4 6RB",
    "addr:housenumber":"2",
    "addr:postcode":"ba4 6rb",
    "addr:street":"Harvester Place",
    "iso:country":"GB",
    "sg:address":"2 Harvester Place, Ditcheat",
    "sg:city":"Shepton Mallet",
    "sg:classifiers":[
        {
            "category":"Farming",
            "subcategory":"Poultry Farm",
            "type":"Manufacturing & Wholesale Goods"
        }
    ],
    "sg:phone":"+44 1749 860553",
    "sg:postcode":"BA4 6RB",
    "sg:province":"Somerset",
    "sg:tags":[
        "related"
    ],
    "wof:name":"YeoMaker Ltd",
    "wof:placetype":"venue"
},
  "geometry": {"coordinates":[-2.535669,51.124241],"type":"Point"}
}