{
  "type": "Feature",
  "properties": {
    "iso:country":"GB",
    "sg:address":"Radcliffe Rd",
    "sg:city":"Nottingham",
    "sg:classifiers":[
        {
            "category":"Retail",
            "subcategory":"Auto Repair",
            "type":"Services"
        }
    ],
    "sg:phone":"+44 115 981 0685",
    "sg:postcode":"NG12 2LP",
    "sg:province":"Nottinghamshire",
    "sg:tags":[
        "modification",
        "garage"
    ],
    "wof:name":"J & E Garage At Greenacres",
    "wof:placetype":"venue"
},
  "geometry": {"coordinates":[-1.064384,52.937595],"type":"Point"}
}