{
  "type": "Feature",
  "properties": {
    "addr:full":"Unit 4 Custom House, Custom House Quay Greenock Inverclyde PA15 1EQ",
    "addr:housenumber":"unit 4",
    "addr:postcode":"pa15 1eq",
    "addr:street":"Custom House Custom House Quay Greenock",
    "iso:country":"GB",
    "sg:address":"Unit 4 Custom House, Custom House Quay",
    "sg:city":"Greenock",
    "sg:classifiers":[
        {
            "category":"Home & Garden",
            "subcategory":"Household Appliances",
            "type":"Retail Goods"
        }
    ],
    "sg:phone":"+44 845 600 7002",
    "sg:postcode":"PA15 1EQ",
    "sg:province":"Inverclyde",
    "sg:tags":[
        "electrical",
        "domestic"
    ],
    "wof:name":"Comet",
    "wof:placetype":"venue"
},
  "geometry": {"coordinates":[-4.7509288788,55.9477958679],"type":"Point"}
}