{
  "type": "Feature",
  "properties": {
    "addr:full":"57 High Street Tunbridge Wells Kent TN1 1XU",
    "addr:housenumber":"57",
    "addr:postcode":"tn1 1xu",
    "addr:street":"High Street",
    "iso:country":"GB",
    "sg:address":"57 High Street",
    "sg:city":"Tunbridge Wells",
    "sg:classifiers":[
        {
            "category":"Professional",
            "subcategory":"Lawyer & Legal Services",
            "type":"Services"
        }
    ],
    "sg:phone":"+44 1732 747900",
    "sg:postcode":"TN1 1XU",
    "sg:province":"Kent",
    "sg:tags":[
        "solicitor"
    ],
    "wof:name":"Ryder & Co",
    "wof:placetype":"venue"
},
  "geometry": {"coordinates":[0.2612479925,51.1276473999],"type":"Point"}
}