{
  "type": "Feature",
  "properties": {
    "addr:full":"244 Bath St Glasgow Glasgow City G2 4JW",
    "addr:housenumber":"244",
    "addr:postcode":"g2 4jw",
    "addr:street":"Bath St",
    "iso:country":"GB",
    "sg:address":"244 Bath St",
    "sg:city":"Glasgow",
    "sg:classifiers":[
        {
            "category":"Communications",
            "type":"Services"
        }
    ],
    "sg:phone":"+44 141 332 3221",
    "sg:postcode":"G2 4JW",
    "sg:province":"Glasgow City",
    "sg:tags":[
        "telecommunication"
    ],
    "wof:name":"Cellphone Group",
    "wof:placetype":"venue"
},
  "geometry": {"coordinates":[-4.2654042244,55.8650360107],"type":"Point"}
}