{
  "type": "Feature",
  "properties": {
    "addr:full":"Park Farm, Lee Chapel Lane Basildon Essex SS16 5PW",
    "addr:postcode":"ss16 5pw",
    "addr:street":"Park;Lee Chapel Lane",
    "iso:country":"GB",
    "sg:address":"Park Farm, Lee Chapel Lane",
    "sg:city":"Basildon",
    "sg:classifiers":[
        {
            "category":"Building & Trades",
            "subcategory":"Landscaping Services",
            "type":"Services"
        }
    ],
    "sg:phone":"+44 1268 540476",
    "sg:postcode":"SS16 5PW",
    "sg:province":"Essex",
    "sg:tags":[
        "landscape",
        "contractor"
    ],
    "wof:name":"R G Joyce",
    "wof:placetype":"venue"
},
  "geometry": {"coordinates":[0.4380460083,51.5604515076],"type":"Point"}
}