{
  "type": "Feature",
  "properties": {
    "iso:country":"GB",
    "sg:address":"63/65 Highmoor Cres",
    "sg:city":"Leeds",
    "sg:classifiers":[
        {
            "category":"Farming",
            "subcategory":"Fish & Marine Products",
            "type":"Manufacturing & Wholesale Goods"
        }
    ],
    "sg:phone":"+44 113 225 0403",
    "sg:postcode":"LS17 6DX",
    "sg:province":"North Yorkshire",
    "sg:tags":[
        "fishmonger"
    ],
    "wof:name":"Grant,P,& E Grant",
    "wof:placetype":"venue"
},
  "geometry": {"coordinates":[-1.52422,53.847038],"type":"Point"}
}