{
  "type": "Feature",
  "properties": {
    "addr:full":"127 Prince Edward Road South Shields Tyne and Wear NE34 8PJ",
    "addr:housenumber":"127",
    "addr:postcode":"ne34 8pj",
    "addr:street":"Prince Edward Road",
    "iso:country":"GB",
    "sg:address":"127 Prince Edward Road",
    "sg:city":"South Shields",
    "sg:classifiers":[
        {
            "category":"Personal",
            "subcategory":"Barber",
            "type":"Services"
        }
    ],
    "sg:postcode":"NE34 8PJ",
    "sg:province":"Tyne and Wear",
    "sg:tags":[
        "men's",
        "hairdresser"
    ],
    "wof:name":"Fellaz Barber Shop",
    "wof:placetype":"venue"
},
  "geometry": {"coordinates":[-1.413443,54.972134],"type":"Point"}
}