{
  "type": "Feature",
  "properties": {
    "iso:country":"GB",
    "sg:address":"29 Caldecote Road, Ickwell",
    "sg:city":"Biggleswade",
    "sg:classifiers":[
        {
            "category":"Professional",
            "subcategory":"Engineering",
            "type":"Services"
        }
    ],
    "sg:phone":"+44 1767 627330",
    "sg:postcode":"SG18 9EH",
    "sg:province":"Bedfordshire",
    "sg:tags":[
        "contractor",
        "electrical",
        "engineer"
    ],
    "wof:name":"Philip Armstrong",
    "wof:placetype":"venue"
},
  "geometry": {"coordinates":[-0.319774,52.09761],"type":"Point"}
}