{
  "type": "Feature",
  "properties": {
    "addr:full":"Napier Road Waterlooville Hampshire PO8 9LR",
    "addr:postcode":"po8 9lr",
    "addr:street":"Napier Road",
    "iso:country":"GB",
    "sg:address":"Napier Road",
    "sg:city":"Waterlooville",
    "sg:classifiers":[
        {
            "category":"Utilities",
            "subcategory":"Refuse",
            "type":"Services"
        }
    ],
    "sg:postcode":"PO8 9LR",
    "sg:province":"Hampshire",
    "sg:tags":[
        "collection"
    ],
    "wof:name":"Jones Rubbish Clearance",
    "wof:placetype":"venue"
},
  "geometry": {"coordinates":[-1.003119,50.912151],"type":"Point"}
}