{
  "type": "Feature",
  "properties": {
    "addr:full":"Unit 2 Unity Court, Broadmead Lane, Keynsham Bristol City of Bristol BS31 1ST",
    "addr:housenumber":"unit 2",
    "addr:postcode":"bs31 1st",
    "addr:street":"Unity Court Broadmead Lane",
    "iso:country":"GB",
    "sg:address":"Unit 2 Unity Court, Broadmead Lane, Keynsham",
    "sg:city":"Bristol",
    "sg:classifiers":[
        {
            "category":"Home & Garden",
            "subcategory":"Carpets & Floor Coverings",
            "type":"Retail Goods"
        }
    ],
    "sg:phone":"+44 117 986 9979",
    "sg:postcode":"BS31 1ST",
    "sg:province":"City of Bristol",
    "sg:tags":[
        "carpets",
        "rug",
        "matting"
    ],
    "wof:name":"Right At Your Feet Flooring",
    "wof:placetype":"venue"
},
  "geometry": {"coordinates":[-2.4838340282,51.4178733826],"type":"Point"}
}