{
  "type": "Feature",
  "properties": {
    "addr:full":"Unit 2-5 Cariocca Business Park, Hellidon Close Manchester Greater Manchester M12 4AH",
    "addr:housenumber":"unit 2-5",
    "addr:postcode":"m12 4ah",
    "addr:street":"Cariocca Business Park Hellidon Close",
    "iso:country":"GB",
    "sg:address":"Unit 2-5 Cariocca Business Park, Hellidon Close",
    "sg:city":"Manchester",
    "sg:classifiers":[
        {
            "category":"Restaurant",
            "type":"Food & Drink"
        }
    ],
    "sg:phone":"+44 161 273 3469",
    "sg:postcode":"M12 4AH",
    "sg:province":"Greater Manchester",
    "wof:name":"Rosemary Watts Bespoke Catering",
    "wof:placetype":"venue"
},
  "geometry": {"coordinates":[-2.21717906,53.4678764343],"type":"Point"}
}