{
  "type": "Feature",
  "properties": {
    "iso:country":"GB",
    "sg:address":"94 Cutenhoe Rd",
    "sg:city":"Luton",
    "sg:classifiers":[
        {
            "category":"Professional",
            "type":"Services"
        }
    ],
    "sg:phone":"+44 1582 526724",
    "sg:postcode":"LU1 3NF",
    "sg:province":"Bedfordshire",
    "sg:tags":[
        "reflexologists"
    ],
    "wof:name":"Feet First",
    "wof:placetype":"venue"
},
  "geometry": {"coordinates":[-0.412198,51.867569],"type":"Point"}
}