{
  "type": "Feature",
  "properties": {
    "iso:country":"GB",
    "sg:address":"5a Chapel Street",
    "sg:city":"Stratford-upon-avon",
    "sg:classifiers":[
        {
            "category":"Fast Food",
            "type":"Food & Drink"
        }
    ],
    "sg:postcode":"CV37 6EP",
    "sg:province":"Warwickshire",
    "sg:tags":[
        "away",
        "take"
    ],
    "wof:name":"P A Soobroy",
    "wof:placetype":"venue"
},
  "geometry": {"coordinates":[-1.7080789804,52.1907653809],"type":"Point"}
}