{
  "type": "Feature",
  "properties": {
    "addr:full":"Ynys Y Gwas, Cwmavon Port Talbot Neath Port Talbot SA12 9AB",
    "addr:postcode":"sa12 9ab",
    "addr:street":"Cwmavon;Talbot",
    "iso:country":"GB",
    "sg:address":"Ynys Y Gwas, Cwmavon",
    "sg:city":"Port Talbot",
    "sg:classifiers":[
        {
            "category":"Home & Garden",
            "subcategory":"Garden Supply",
            "type":"Retail Goods"
        }
    ],
    "sg:phone":"+44 1639 896715",
    "sg:postcode":"SA12 9AB",
    "sg:province":"Neath Port Talbot",
    "sg:tags":[
        "equipment",
        "playground"
    ],
    "wof:name":"Forest Products Centre",
    "wof:placetype":"venue"
},
  "geometry": {"coordinates":[-3.7582330704,51.6159172058],"type":"Point"}
}