{
  "type": "Feature",
  "properties": {
    "addr:full":"66a North Street Leighton Buzzard Bedfordshire LU7 1EN",
    "addr:housenumber":"66a",
    "addr:postcode":"lu7 1en",
    "addr:street":"North Street",
    "iso:country":"GB",
    "sg:address":"66a North Street",
    "sg:city":"Leighton Buzzard",
    "sg:classifiers":[
        {
            "category":"Fast Food",
            "type":"Food & Drink"
        },
        {
            "category":"Food & Beverages",
            "subcategory":"Meat & Fish",
            "type":"Retail Goods"
        }
    ],
    "sg:phone":"+44 1525 374072",
    "sg:postcode":"LU7 1EN",
    "sg:province":"Bedfordshire",
    "sg:tags":[
        "shop",
        "chip"
    ],
    "wof:name":"Ocean Fish Bar",
    "wof:placetype":"venue"
},
  "geometry": {"coordinates":[-0.6600210071,51.918926239],"type":"Point"}
}