{
  "type": "Feature",
  "properties": {
    "addr:full":"Units 2-5 Amor Way Letchworth Hertfordshire SG6 1UG",
    "addr:housenumber":"units 2-5",
    "addr:postcode":"sg6 1ug",
    "addr:street":"Amor Way",
    "iso:country":"GB",
    "sg:address":"Units 2-5 Amor Way",
    "sg:city":"Letchworth",
    "sg:classifiers":[
        {
            "category":"Shopping",
            "subcategory":"Pharmacy",
            "type":"Retail Goods"
        }
    ],
    "sg:phone":"+44 1462 686644",
    "sg:postcode":"SG6 1UG",
    "sg:province":"Hertfordshire",
    "sg:tags":[
        "pharmaceutical"
    ],
    "wof:name":"Lipha Pharmaceuticals Ltd.",
    "wof:placetype":"venue"
},
  "geometry": {"coordinates":[-0.2222429961,51.9725494385],"type":"Point"}
}