{
  "type": "Feature",
  "properties": {
    "iso:country":"GB",
    "sg:address":"196 Petts Wood Road",
    "sg:city":"Orpington",
    "sg:classifiers":[
        {
            "category":"Food & Beverages",
            "subcategory":"Meat & Fish",
            "type":"Retail Goods"
        }
    ],
    "sg:phone":"+44 1689 830190",
    "sg:postcode":"BR5 1LG",
    "sg:province":"Kent",
    "sg:tags":[
        "chip"
    ],
    "wof:name":"Pine Lake Fish & Chip Shop",
    "wof:placetype":"venue"
},
  "geometry": {"coordinates":[0.0749730021,51.3903808594],"type":"Point"}
}