{
  "type": "Feature",
  "properties": {
    "addr:full":"42 Milnrow Road Rochdale Lancashire OL16 1UD",
    "addr:housenumber":"42",
    "addr:postcode":"ol16 1ud",
    "addr:street":"Milnrow Road",
    "iso:country":"GB",
    "sg:address":"42 Milnrow Road",
    "sg:city":"Rochdale",
    "sg:classifiers":[
        {
            "category":"Autos & Motor Vehicles",
            "subcategory":"Automobile Sales",
            "type":"Retail Goods"
        }
    ],
    "sg:postcode":"OL16 1UD",
    "sg:province":"Lancashire",
    "sg:tags":[
        "car"
    ],
    "wof:name":"The Rochdale 4 X 4 Centre",
    "wof:placetype":"venue"
},
  "geometry": {"coordinates":[-2.1514489651,53.6139297485],"type":"Point"}
}