{
  "type": "Feature",
  "properties": {
    "iso:country":"GB",
    "sg:address":"Pepper La",
    "sg:city":"Ludlow",
    "sg:classifiers":[
        {
            "category":"Shopping",
            "subcategory":"Antiques",
            "type":"Retail Goods"
        }
    ],
    "sg:postcode":"SY8 1PX",
    "sg:province":"Herefordshire",
    "wof:name":"Antique Centre",
    "wof:placetype":"venue"
},
  "geometry": {"coordinates":[-2.7176930904,52.3677787781],"type":"Point"}
}