{
  "type": "Feature",
  "properties": {
    "addr:full":"56 The Thoroughfare Woodbridge Suffolk IP12 1AH",
    "addr:housenumber":"56",
    "addr:postcode":"ip12 1ah",
    "addr:street":"The Thoroughfare",
    "iso:country":"GB",
    "sg:address":"56 The Thoroughfare",
    "sg:city":"Woodbridge",
    "sg:classifiers":[
        {
            "category":"Farming",
            "subcategory":"Livestock Farm",
            "type":"Manufacturing & Wholesale Goods"
        },
        {
            "category":"Shopping",
            "subcategory":"Florist",
            "type":"Retail Goods"
        }
    ],
    "sg:postcode":"IP12 1AH",
    "sg:province":"Suffolk",
    "sg:tags":[
        "breeder"
    ],
    "wof:name":"Flowers by Norman Paul",
    "wof:placetype":"venue"
},
  "geometry": {"coordinates":[1.331041,52.105785],"type":"Point"}
}