{
  "type": "Feature",
  "properties": {
    "addr:full":"215-221 Green Street London Greater London E7 8LL",
    "addr:housenumber":"215-221",
    "addr:postcode":"e7 8ll",
    "addr:street":"Green Street",
    "iso:country":"GB",
    "sg:address":"215-221 Green Street",
    "sg:city":"London",
    "sg:classifiers":[
        {
            "category":"Building & Trades",
            "subcategory":"Construction",
            "type":"Services"
        }
    ],
    "sg:phone":"+44 20 8470 1131",
    "sg:postcode":"E7 8LL",
    "sg:province":"Greater London",
    "sg:tags":[
        "builder"
    ],
    "wof:name":"Troy Homes Ltd.",
    "wof:placetype":"venue"
},
  "geometry": {"coordinates":[0.0328739993,51.5416221619],"type":"Point"}
}