{
  "type": "Feature",
  "properties": {
    "addr:full":"5 Southern Court, South Street Reading Berkshire RG1 4QS",
    "addr:housenumber":"5",
    "addr:postcode":"rg1 4qs",
    "addr:street":"Southern Court South Street",
    "iso:country":"GB",
    "sg:address":"5 Southern Court, South Street",
    "sg:city":"Reading",
    "sg:classifiers":[
        {
            "category":"Building & Trades",
            "subcategory":"Electrical",
            "type":"Services"
        }
    ],
    "sg:postcode":"RG1 4QS",
    "sg:province":"Berkshire",
    "sg:tags":[
        "equipment",
        "purification",
        "air"
    ],
    "wof:name":"S A E S Getter (G B) Ltd.",
    "wof:placetype":"venue"
},
  "geometry": {"coordinates":[-0.963009,51.453522],"type":"Point"}
}