{
  "type": "Feature",
  "properties": {
    "iso:country":"GB",
    "sg:address":"17 Duncannon Drive",
    "sg:city":"Falmouth",
    "sg:classifiers":[
        {
            "category":"Shopping",
            "subcategory":"Mobile Phones",
            "type":"Retail Goods"
        }
    ],
    "sg:postcode":"TR11 4AQ",
    "sg:province":"Cornwall",
    "wof:name":"Max Burrows Phone Fit",
    "wof:placetype":"venue"
},
  "geometry": {"coordinates":[-5.085694,50.152035],"type":"Point"}
}