{
  "type": "Feature",
  "properties": {
    "addr:full":"1a Kirk Lane, Ruddington Nottingham Nottinghamshire NG11 6NN",
    "addr:housenumber":"1a",
    "addr:postcode":"ng11 6nn",
    "addr:street":"Kirk Lane",
    "iso:country":"GB",
    "sg:address":"1a Kirk Lane, Ruddington",
    "sg:city":"Nottingham",
    "sg:classifiers":[
        {
            "category":"Education",
            "subcategory":"Special Training",
            "type":"Public Place"
        }
    ],
    "sg:postcode":"NG11 6NN",
    "sg:province":"Nottinghamshire",
    "sg:tags":[
        "diving",
        "school"
    ],
    "wof:name":"First Stage Diving",
    "wof:placetype":"venue"
},
  "geometry": {"coordinates":[-1.1488829851,52.8918228149],"type":"Point"}
}