{
  "type": "Feature",
  "properties": {
    "addr:full":"49-51 Magdalen Yard Road Dundee Dundee City DD1 4NF",
    "addr:housenumber":"49-51",
    "addr:postcode":"dd1 4nf",
    "addr:street":"Magdalen Yard Road",
    "iso:country":"GB",
    "sg:address":"49-51 Magdalen Yard Road",
    "sg:city":"Dundee",
    "sg:classifiers":[
        {
            "category":"Home & Garden",
            "subcategory":"Home Furnishings",
            "type":"Retail Goods"
        }
    ],
    "sg:phone":"+44 1382 666833",
    "sg:postcode":"DD1 4NF",
    "sg:province":"Dundee City",
    "sg:tags":[
        "mantelpiece",
        "fireplace"
    ],
    "wof:name":"Taymouth Architectural Antiques",
    "wof:placetype":"venue"
},
  "geometry": {"coordinates":[-2.9883110523,56.4532928467],"type":"Point"}
}