{
  "type": "Feature",
  "properties": {
    "addr:full":"Newington Enterprise Centre, Wardwell Lane, Lower Halstow Sittingbourne Kent ME9 7ER",
    "addr:postcode":"me9 7er",
    "addr:street":"Wardwell Lane",
    "iso:country":"GB",
    "sg:address":"Newington Enterprise Centre, Wardwell Lane, Lower Halstow",
    "sg:city":"Sittingbourne",
    "sg:classifiers":[
        {
            "category":"Autos & Motor Vehicles",
            "subcategory":"Automobile Sales",
            "type":"Retail Goods"
        }
    ],
    "sg:phone":"+44 1795 841050",
    "sg:postcode":"ME9 7ER",
    "sg:province":"Kent",
    "sg:tags":[
        "car",
        "truck"
    ],
    "wof:name":"Wire Tech",
    "wof:placetype":"venue"
},
  "geometry": {"coordinates":[0.6686099768,51.373790741],"type":"Point"}
}