{
  "type": "Feature",
  "properties": {
    "addr:full":"30 East St Petworth West Sussex GU28 0AB",
    "addr:housenumber":"30",
    "addr:postcode":"gu28 0ab",
    "addr:street":"East St",
    "iso:country":"GB",
    "sg:address":"30 East St",
    "sg:city":"Petworth",
    "sg:classifiers":[
        {
            "category":"Shopping",
            "subcategory":"Bicycles & Sporting Goods",
            "type":"Retail Goods"
        }
    ],
    "sg:phone":"+44 1798 344165",
    "sg:postcode":"GU28 0AB",
    "sg:province":"West Sussex",
    "sg:tags":[
        "riding",
        "saddlery",
        "wear"
    ],
    "wof:name":"Petworth Saddlery",
    "wof:placetype":"venue"
},
  "geometry": {"coordinates":[-0.608529,50.986931],"type":"Point"}
}