{
  "type": "Feature",
  "properties": {
    "addr:full":"35 Connaught Square Bayswater Greater London W2 2HL",
    "addr:housenumber":"35",
    "addr:postcode":"w2 2hl",
    "addr:street":"Connaught Square",
    "iso:country":"GB",
    "sg:address":"35 Connaught Square",
    "sg:city":"Bayswater",
    "sg:classifiers":[
        {
            "category":"Arts & Performance",
            "subcategory":"Art Gallery",
            "type":"Entertainment"
        }
    ],
    "sg:phone":"+44 20 7724 4435",
    "sg:postcode":"W2 2HL",
    "sg:province":"Greater London",
    "wof:name":"Alexander Gotz",
    "wof:placetype":"venue"
},
  "geometry": {"coordinates":[-0.164257,51.514072],"type":"Point"}
}