{
  "type": "Feature",
  "properties": {
    "iso:country":"GB",
    "sg:address":"52 Obelisk Way",
    "sg:city":"Camberley",
    "sg:classifiers":[
        {
            "category":"Personal",
            "subcategory":"Barber",
            "type":"Services"
        }
    ],
    "sg:phone":"+44 1276 671998",
    "sg:postcode":"GU15 3SG",
    "sg:province":"Berkshire",
    "sg:tags":[
        "men's",
        "hairdresser"
    ],
    "wof:name":"Luigi's",
    "wof:placetype":"venue"
},
  "geometry": {"coordinates":[-0.7450090051,51.3390197754],"type":"Point"}
}