{
  "type": "Feature",
  "properties": {
    "iso:country":"GB",
    "sg:address":"263-265 Manchester Road",
    "sg:city":"Northwich",
    "sg:classifiers":[
        {
            "category":"Home & Garden",
            "subcategory":"Hardware",
            "type":"Retail Goods"
        }
    ],
    "sg:postcode":"CW9 7NE",
    "sg:province":"Cheshire",
    "sg:tags":[
        "part",
        "accessory"
    ],
    "wof:name":"Scoot N Commute Ltd.",
    "wof:placetype":"venue"
},
  "geometry": {"coordinates":[-2.480133,53.266998],"type":"Point"}
}