{
  "type": "Feature",
  "properties": {
    "iso:country":"GB",
    "sg:address":"30 North St",
    "sg:city":"Ashford",
    "sg:classifiers":[
        {
            "category":"Shopping",
            "subcategory":"Music",
            "type":"Retail Goods"
        }
    ],
    "sg:postcode":"TN24 8JR",
    "sg:province":"Kent",
    "sg:tags":[
        "record",
        "tape",
        "cd"
    ],
    "wof:name":"Down, Barry G,",
    "wof:placetype":"venue"
},
  "geometry": {"coordinates":[0.8734160066,51.149684906],"type":"Point"}
}