{
  "type": "Feature",
  "properties": {
    "addr:full":"Westby House, Golden Hill, Leyland Preston Lancashire PR5 2NN",
    "addr:postcode":"pr5 2nn",
    "iso:country":"GB",
    "sg:address":"Westby House, Golden Hill, Leyland",
    "sg:city":"Preston",
    "sg:classifiers":[
        {
            "category":"Organizations",
            "subcategory":"Non-profit Organization",
            "type":"Services"
        }
    ],
    "sg:phone":"+44 1772 421512",
    "sg:postcode":"PR5 2NN",
    "sg:province":"Lancashire",
    "sg:tags":[
        "organisation",
        "voluntary",
        "charity"
    ],
    "wof:name":"R A F Association",
    "wof:placetype":"venue"
},
  "geometry": {"coordinates":[-2.6934900284,53.6953392029],"type":"Point"}
}