{
  "type": "Feature",
  "properties": {
    "addr:full":"46 Oxford St Ripley Derbyshire DE5 3AP",
    "addr:housenumber":"46",
    "addr:postcode":"de5 3ap",
    "addr:street":"Oxford St",
    "iso:country":"GB",
    "sg:address":"46 Oxford St",
    "sg:city":"Ripley",
    "sg:classifiers":[
        {
            "category":"Shopping",
            "subcategory":"Hobbies, Toys, & Games",
            "type":"Retail Goods"
        }
    ],
    "sg:phone":"+44 1773 513920",
    "sg:postcode":"DE5 3AP",
    "sg:province":"Derbyshire",
    "sg:tags":[
        "toy"
    ],
    "wof:name":"Fantasy Fayre",
    "wof:placetype":"venue"
},
  "geometry": {"coordinates":[-1.4042030573,53.050151825],"type":"Point"}
}