{
  "type": "Feature",
  "properties": {
    "addr:full":"78 Albion Road Edinburgh City of Edinburgh EH7 5QZ",
    "addr:housenumber":"78",
    "addr:postcode":"eh7 5qz",
    "addr:street":"Albion Road",
    "iso:country":"GB",
    "sg:address":"78 Albion Road",
    "sg:city":"Edinburgh",
    "sg:classifiers":[
        {
            "category":"Communications",
            "subcategory":"Film & Video Production",
            "type":"Services"
        }
    ],
    "sg:phone":"+44 131 659 6673",
    "sg:postcode":"EH7 5QZ",
    "sg:province":"City of Edinburgh",
    "sg:tags":[
        "recording",
        "studio"
    ],
    "wof:name":"Cava East",
    "wof:placetype":"venue"
},
  "geometry": {"coordinates":[-3.163846,55.961411],"type":"Point"}
}