{
  "type": "Feature",
  "properties": {
    "addr:full":"179 London Road North Lowestoft Suffolk NR32 1HG",
    "addr:housenumber":"179",
    "addr:postcode":"nr32 1hg",
    "addr:street":"London Road North",
    "iso:country":"GB",
    "sg:address":"179 London Road North",
    "sg:city":"Lowestoft",
    "sg:classifiers":[
        {
            "category":"Shopping",
            "subcategory":"Clothing, Apparel, & Fashions",
            "type":"Retail Goods"
        }
    ],
    "sg:phone":"+44 1502 500059",
    "sg:postcode":"NR32 1HG",
    "sg:province":"Suffolk",
    "sg:tags":[
        "menswear"
    ],
    "wof:name":"Academy Clothing",
    "wof:placetype":"venue"
},
  "geometry": {"coordinates":[1.7550230026,52.4790725708],"type":"Point"}
}