{
  "type": "Feature",
  "properties": {
    "iso:country":"GB",
    "sg:address":"Unit 1f Pier Road, North Felton Trading Estate",
    "sg:city":"Feltham",
    "sg:classifiers":[
        {
            "category":"Freight",
            "type":"Transportation"
        }
    ],
    "sg:phone":"+44 20 8890 6070",
    "sg:postcode":"TW14 0TT",
    "sg:province":"Greater London",
    "sg:tags":[
        "haulage",
        "road"
    ],
    "wof:name":"All Star Transport (Heathrow) Ltd.",
    "wof:placetype":"venue"
},
  "geometry": {"coordinates":[-0.408422,51.46236],"type":"Point"}
}