{
  "type": "Feature",
  "properties": {
    "iso:country":"GB",
    "sg:address":"245 Holland Road",
    "sg:city":"Clacton-on-sea",
    "sg:classifiers":[
        {
            "category":"Building & Trades",
            "subcategory":"Plumbing",
            "type":"Services"
        }
    ],
    "sg:phone":"+44 1255 432535",
    "sg:postcode":"CO15 6NL",
    "sg:province":"Essex",
    "sg:tags":[
        "central",
        "heating"
    ],
    "wof:name":"Holland Gas",
    "wof:placetype":"venue"
},
  "geometry": {"coordinates":[1.175148,51.802635],"type":"Point"}
}