{
  "type": "Feature",
  "properties": {
    "iso:country":"GB",
    "sg:address":"45 Bridge Street",
    "sg:city":"Chester",
    "sg:classifiers":[
        {
            "category":"Food & Beverages",
            "subcategory":"Meat & Fish",
            "type":"Retail Goods"
        }
    ],
    "sg:phone":"+44 1244 324896",
    "sg:postcode":"CH1 1NG",
    "sg:province":"Cheshire",
    "sg:tags":[
        "butcher"
    ],
    "wof:name":"GEORGE VENABLES & SONS",
    "wof:placetype":"venue"
},
  "geometry": {"coordinates":[-2.890995,53.189178],"type":"Point"}
}