{
  "type": "Feature",
  "properties": {
    "iso:country":"GB",
    "sg:address":"Unit 30 Derwent Business Centre, Clarke Street",
    "sg:city":"Derby",
    "sg:classifiers":[
        {
            "category":"Home & Garden",
            "subcategory":"Home Furnishings",
            "type":"Retail Goods"
        }
    ],
    "sg:phone":"+44 1332 344090",
    "sg:postcode":"DE1 2BU",
    "sg:province":"Derbyshire",
    "sg:tags":[
        "racking",
        "shelving",
        "diy"
    ],
    "wof:name":"Complete Logistic Solutions Ltd.",
    "wof:placetype":"venue"
},
  "geometry": {"coordinates":[-1.4688489437,52.928150177],"type":"Point"}
}