{
  "type": "Feature",
  "properties": {
    "addr:full":"8 Poplar Terrace, West Cornforth Ferryhill Durham DL17 9ES",
    "addr:housenumber":"8",
    "addr:postcode":"dl17 9es",
    "addr:street":"Poplar Terrace",
    "iso:country":"GB",
    "sg:address":"8 Poplar Terrace, West Cornforth",
    "sg:city":"Ferryhill",
    "sg:classifiers":[
        {
            "category":"Building & Trades",
            "subcategory":"Landscaping Services",
            "type":"Services"
        }
    ],
    "sg:phone":"+44 1740 655561",
    "sg:postcode":"DL17 9ES",
    "sg:province":"Durham",
    "sg:tags":[
        "landscape",
        "contractor"
    ],
    "wof:name":"L Nicholson",
    "wof:placetype":"venue"
},
  "geometry": {"coordinates":[-1.5200359821,54.699508667],"type":"Point"}
}