{
  "type": "Feature",
  "properties": {
    "addr:full":"Main St, Bowmore Isle Of Islay Argyll and Bute PA43 7JH",
    "addr:postcode":"pa43 7jh",
    "addr:street":"Main St",
    "iso:country":"GB",
    "sg:address":"Main St, Bowmore",
    "sg:city":"Isle Of Islay",
    "sg:classifiers":[
        {
            "category":"Communications",
            "subcategory":"Newspaper",
            "type":"Services"
        }
    ],
    "sg:phone":"+44 1496 810355",
    "sg:postcode":"PA43 7JH",
    "sg:province":"Argyll and Bute",
    "sg:tags":[
        "magazine"
    ],
    "wof:name":"Ileach Teleservices Ltd",
    "wof:placetype":"venue"
},
  "geometry": {"coordinates":[-6.2878241539,55.7566719055],"type":"Point"}
}