{
  "type": "Feature",
  "properties": {
    "addr:full":"67 Greengates St Stoke On Trent Staffordshire ST6 6BZ",
    "addr:housenumber":"67",
    "addr:postcode":"st6 6bz",
    "addr:street":"Greengates St",
    "iso:country":"GB",
    "sg:address":"67 Greengates St",
    "sg:city":"Stoke On Trent",
    "sg:classifiers":[
        {
            "category":"Personal",
            "subcategory":"Beauty Salon",
            "type":"Services"
        }
    ],
    "sg:phone":"+44 1782 835125",
    "sg:postcode":"ST6 6BZ",
    "sg:province":"Staffordshire",
    "sg:tags":[
        "unisex",
        "hairdresser"
    ],
    "wof:name":"Snippets The",
    "wof:placetype":"venue"
},
  "geometry": {"coordinates":[-2.208805,53.060928],"type":"Point"}
}