{
  "type": "Feature",
  "properties": {
    "iso:country":"GB",
    "sg:address":"1 Church Street, Conisbrough",
    "sg:city":"Doncaster",
    "sg:classifiers":[
        {
            "category":"Retail",
            "subcategory":"Repair Shop",
            "type":"Services"
        }
    ],
    "sg:phone":"+44 1709 868299",
    "sg:postcode":"DN12 3HL",
    "sg:province":"South Yorkshire",
    "sg:tags":[
        "upholstering",
        "upholsterer"
    ],
    "wof:name":"J B & J HARDIE",
    "wof:placetype":"venue"
},
  "geometry": {"coordinates":[-1.2290489674,53.4834442139],"type":"Point"}
}