{
  "type": "Feature",
  "properties": {
    "addr:full":"Wingates Wholme, Wingates Morpeth Northumberland NE65 8RS",
    "addr:postcode":"ne65 8rs",
    "addr:street":"Northumberland",
    "iso:country":"GB",
    "sg:address":"Wingates Wholme, Wingates",
    "sg:city":"Morpeth",
    "sg:classifiers":[
        {
            "category":"Farming",
            "subcategory":"Farm",
            "type":"Manufacturing & Wholesale Goods"
        }
    ],
    "sg:phone":"+44 1670 788304",
    "sg:postcode":"NE65 8RS",
    "sg:province":"Northumberland",
    "sg:tags":[
        "mixed",
        "crop"
    ],
    "wof:name":"John R Moore",
    "wof:placetype":"venue"
},
  "geometry": {"coordinates":[-1.8490920067,55.2494621277],"type":"Point"}
}