{
  "type": "Feature",
  "properties": {
    "addr:full":"321 Evesham Road Redditch Warwickshire B97 5JA",
    "addr:housenumber":"321",
    "addr:postcode":"b97 5ja",
    "addr:street":"Evesham Road",
    "iso:country":"GB",
    "sg:address":"321 Evesham Road",
    "sg:city":"Redditch",
    "sg:classifiers":[
        {
            "category":"Social Services",
            "subcategory":"Retirement Home",
            "type":"Services"
        },
        {
            "category":"Organizations",
            "subcategory":"Professional Association",
            "type":"Services"
        }
    ],
    "sg:phone":"+44 1527 401543",
    "sg:postcode":"B97 5JA",
    "sg:province":"Warwickshire",
    "sg:tags":[
        "genealogical",
        "organisation",
        "historian",
        "family"
    ],
    "wof:name":"Redditch Family History Centre",
    "wof:placetype":"venue"
},
  "geometry": {"coordinates":[-1.944019,52.286098],"type":"Point"}
}