{
  "type": "Feature",
  "properties": {
    "iso:country":"GB",
    "sg:address":", Penley",
    "sg:city":"Wrexham",
    "sg:classifiers":[
        {
            "category":"Bars & Pubs",
            "type":"Food & Drink"
        }
    ],
    "sg:phone":"+44 1948 830221",
    "sg:postcode":"LL13 0LS",
    "sg:province":"Wrexham",
    "sg:tags":[
        "pubs",
        "inn"
    ],
    "wof:name":"Dymock Arms",
    "wof:placetype":"venue"
},
  "geometry": {"coordinates":[-2.915759,53.00412],"type":"Point"}
}