{
  "type": "Feature",
  "properties": {
    "iso:country":"GB",
    "sg:address":"51 Gardner Street",
    "sg:city":"Brighton",
    "sg:classifiers":[
        {
            "category":"Shopping",
            "subcategory":"Department Store",
            "type":"Retail Goods"
        },
        {
            "category":"Shopping",
            "subcategory":"Crafts & Fabrics",
            "type":"Retail Goods"
        }
    ],
    "sg:phone":"+44 1273 605512",
    "sg:postcode":"BN1 1UN",
    "sg:province":"East Sussex",
    "sg:tags":[
        "shop"
    ],
    "wof:name":"New Fabric Fair",
    "wof:placetype":"venue"
},
  "geometry": {"coordinates":[-0.139438,50.824692],"type":"Point"}
}