{
  "type": "Feature",
  "properties": {
    "addr:full":"98 Station Road Sidcup Kent DA15 7BY",
    "addr:housenumber":"98",
    "addr:postcode":"da15 7by",
    "addr:street":"Station Road",
    "iso:country":"GB",
    "sg:address":"98 Station Road",
    "sg:city":"Sidcup",
    "sg:classifiers":[
        {
            "category":"Professional",
            "subcategory":"Accounting & Tax Preparation",
            "type":"Services"
        }
    ],
    "sg:phone":"+44 20 8300 2307",
    "sg:postcode":"DA15 7BY",
    "sg:province":"Kent",
    "sg:tags":[
        "accountant",
        "activity"
    ],
    "wof:name":"Opass Billings Wilson & Honey",
    "wof:placetype":"venue"
},
  "geometry": {"coordinates":[0.1026230007,51.4321937561],"type":"Point"}
}