{
  "type": "Feature",
  "properties": {
    "addr:full":"108 Locks Ride, Chavey Down Ascot Berkshire SL5 8QX",
    "addr:housenumber":"108",
    "addr:postcode":"sl5 8qx",
    "addr:street":"Locks Ride Chavey",
    "iso:country":"GB",
    "sg:address":"108 Locks Ride, Chavey Down",
    "sg:city":"Ascot",
    "sg:classifiers":[
        {
            "category":"Building & Trades",
            "subcategory":"Construction",
            "type":"Services"
        }
    ],
    "sg:phone":"+44 1344 890991",
    "sg:postcode":"SL5 8QX",
    "sg:province":"Berkshire",
    "sg:tags":[
        "builder"
    ],
    "wof:name":"Berkshire & Surrey Property Maintenance Ltd.",
    "wof:placetype":"venue"
},
  "geometry": {"coordinates":[-0.702316,51.427948],"type":"Point"}
}