{
  "type": "Feature",
  "properties": {
    "iso:country":"GB",
    "sg:address":"17 Coquet Avenue",
    "sg:city":"Whitley Bay",
    "sg:classifiers":[
        {
            "category":"Building & Trades",
            "subcategory":"Construction",
            "type":"Services"
        }
    ],
    "sg:phone":"+44 191 252 6681",
    "sg:postcode":"NE26 1EE",
    "sg:province":"Northumberland",
    "sg:tags":[
        "builder"
    ],
    "wof:name":"T Graham",
    "wof:placetype":"venue"
},
  "geometry": {"coordinates":[-1.4497270584,55.0453071594],"type":"Point"}
}