{
  "type": "Feature",
  "properties": {
    "iso:country":"GB",
    "sg:address":"47a Union Street",
    "sg:city":"Kettering",
    "sg:classifiers":[
        {
            "category":"Home & Garden",
            "subcategory":"Carpets & Floor Coverings",
            "type":"Retail Goods"
        }
    ],
    "sg:postcode":"NN16 9DA",
    "sg:province":"Northamptonshire",
    "sg:tags":[
        "cleaner",
        "upholstery"
    ],
    "wof:name":"Wren's Cleaning Services",
    "wof:placetype":"venue"
},
  "geometry": {"coordinates":[-0.731938,52.404602],"type":"Point"}
}