{
  "type": "Feature",
  "properties": {
    "addr:full":"7-11 Queensberry Place London Greater London SW7 2DW",
    "addr:housenumber":"7-11",
    "addr:postcode":"sw7 2dw",
    "addr:street":"Queensberry Place",
    "iso:country":"GB",
    "sg:address":"7-11 Queensberry Place",
    "sg:city":"London",
    "sg:classifiers":[
        {
            "category":"Travel",
            "subcategory":"Hotels & Motels",
            "type":"Entertainment"
        }
    ],
    "sg:phone":"+44 20 7957 0000",
    "sg:postcode":"SW7 2DW",
    "sg:province":"Greater London",
    "wof:name":"Gainsborough Hotel",
    "wof:placetype":"venue"
},
  "geometry": {"coordinates":[-0.177359,51.494991],"type":"Point"}
}