{
  "type": "Feature",
  "properties": {
    "iso:country":"GB",
    "sg:address":"1 West Street",
    "sg:city":"Tavistock",
    "sg:classifiers":[
        {
            "category":"Cafe",
            "type":"Food & Drink"
        }
    ],
    "sg:postcode":"PL19 8AD",
    "sg:province":"Devon",
    "sg:tags":[
        "tea",
        "room"
    ],
    "wof:name":"Coffee House",
    "wof:placetype":"venue"
},
  "geometry": {"coordinates":[-4.145707,50.549904],"type":"Point"}
}