{
  "type": "Feature",
  "properties": {
    "addr:full":"15 Strand Street Kilmarnock East Ayrshire KA1 1HU",
    "addr:housenumber":"15",
    "addr:postcode":"ka1 1hu",
    "addr:street":"Strand Street",
    "iso:country":"GB",
    "sg:address":"15 Strand Street",
    "sg:city":"Kilmarnock",
    "sg:classifiers":[
        {
            "category":"Shopping",
            "subcategory":"Shoes",
            "type":"Retail Goods"
        }
    ],
    "sg:phone":"+44 1563 537795",
    "sg:postcode":"KA1 1HU",
    "sg:province":"East Ayrshire",
    "sg:tags":[
        "shop",
        "retailer",
        "footwear"
    ],
    "wof:name":"Shoefayre Ltd",
    "wof:placetype":"venue"
},
  "geometry": {"coordinates":[-4.497702,55.610397],"type":"Point"}
}