{
  "type": "Feature",
  "properties": {
    "iso:country":"GB",
    "sg:address":"69 Doncaster Road",
    "sg:city":"Scunthorpe",
    "sg:classifiers":[
        {
            "category":"Government",
            "subcategory":"Post Office",
            "type":"Public Place"
        }
    ],
    "sg:phone":"+44 1724 843030",
    "sg:postcode":"DN15 7RG",
    "sg:province":"Lincolnshire",
    "wof:name":"Doncaster Road Post Office",
    "wof:placetype":"venue"
},
  "geometry": {"coordinates":[-0.66057,53.590515],"type":"Point"}
}