{
  "type": "Feature",
  "properties": {
    "addr:full":"7-9 Ramerely House Carterton Gloucestershire OX18 3HN",
    "addr:housenumber":"7-9;house",
    "addr:postcode":"ox18 3hn",
    "addr:street":"Carterton Gloucestershire",
    "iso:country":"GB",
    "sg:address":"7-9 Ramerely House",
    "sg:city":"Carterton",
    "sg:classifiers":[
        {
            "category":"Shopping",
            "subcategory":"Clothing, Apparel, & Fashions",
            "type":"Retail Goods"
        }
    ],
    "sg:phone":"+44 1993 841200",
    "sg:postcode":"OX18 3HN",
    "sg:province":"Gloucestershire",
    "sg:tags":[
        "shop"
    ],
    "wof:name":"Sign Soloution",
    "wof:placetype":"venue"
},
  "geometry": {"coordinates":[-1.5903840065,51.7606239319],"type":"Point"}
}