{
  "type": "Feature",
  "properties": {
    "addr:full":"77-81 Alma Rd,, Clifton, Bristol City of Bristol BS8 2DP",
    "addr:housenumber":"77-81",
    "addr:postcode":"bs8 2dp",
    "addr:street":"Alma Rd",
    "iso:country":"GB",
    "sg:address":"77-81 Alma Rd,, Clifton,",
    "sg:city":"Bristol",
    "sg:classifiers":[
        {
            "category":"Real Estate",
            "subcategory":"Real Estate Agent",
            "type":"Services"
        }
    ],
    "sg:postcode":"BS8 2DP",
    "sg:province":"City of Bristol",
    "wof:name":"Watcombe Properties Ltd",
    "wof:placetype":"venue"
},
  "geometry": {"coordinates":[-2.610318,51.463371],"type":"Point"}
}