{
  "type": "Feature",
  "properties": {
    "iso:country":"GB",
    "sg:address":"Unit 7 North Walls",
    "sg:city":"Stafford",
    "sg:classifiers":[
        {
            "category":"Education",
            "subcategory":"Music School",
            "type":"Public Place"
        }
    ],
    "sg:phone":"+44 1785 229259",
    "sg:postcode":"ST16 3AD",
    "sg:province":"Staffordshire",
    "sg:tags":[
        "teacher"
    ],
    "wof:name":"Staffordshire Musical Centre",
    "wof:placetype":"venue"
},
  "geometry": {"coordinates":[-2.11393,52.807507],"type":"Point"}
}