{
  "type": "Feature",
  "properties": {
    "addr:full":"Varfell Farm, Long Rock Penzance Cornwall TR20 8AQ",
    "addr:postcode":"tr20 8aq",
    "addr:street":"Varfell",
    "iso:country":"GB",
    "sg:address":"Varfell Farm, Long Rock",
    "sg:city":"Penzance",
    "sg:classifiers":[
        {
            "category":"Home & Garden",
            "subcategory":"Garden Supply",
            "type":"Retail Goods"
        }
    ],
    "sg:phone":"+44 1736 711271",
    "sg:postcode":"TR20 8AQ",
    "sg:province":"Cornwall",
    "sg:tags":[
        "bulb",
        "grower"
    ],
    "wof:name":"Winchester Growers Ltd.",
    "wof:placetype":"venue"
},
  "geometry": {"coordinates":[-5.5022687912,50.128868103],"type":"Point"}
}