{
  "type": "Feature",
  "properties": {
    "iso:country":"GB",
    "sg:address":"21 St Johns Green",
    "sg:city":"Colchester",
    "sg:classifiers":[
        {
            "category":"Organizations",
            "subcategory":"Membership Organization",
            "type":"Services"
        }
    ],
    "sg:postcode":"CO2 7EZ",
    "sg:province":"Essex",
    "sg:tags":[
        "club"
    ],
    "wof:name":"Neptune Court Management Ltd",
    "wof:placetype":"venue"
},
  "geometry": {"coordinates":[0.937395,51.900604],"type":"Point"}
}