{
  "type": "Feature",
  "properties": {
    "addr:full":"Goodwood Rd Eastleigh Hampshire SO50 4NT",
    "addr:postcode":"so50 4nt",
    "addr:street":"Goodwood Rd",
    "iso:country":"GB",
    "sg:address":"Goodwood Rd",
    "sg:city":"Eastleigh",
    "sg:classifiers":[
        {
            "category":"Manufacturing",
            "subcategory":"Metals",
            "type":"Manufacturing & Wholesale Goods"
        }
    ],
    "sg:postcode":"SO50 4NT",
    "sg:province":"Hampshire",
    "sg:tags":[
        "steel",
        "fabricator",
        "erectors"
    ],
    "wof:name":"Pirelli Construction Co Ltd",
    "wof:placetype":"venue"
},
  "geometry": {"coordinates":[-1.365209,50.976505],"type":"Point"}
}