{
  "type": "Feature",
  "properties": {
    "addr:full":"131 Courtlands Drive Watford Hertfordshire WD24 5LL",
    "addr:housenumber":"131",
    "addr:postcode":"wd24 5ll",
    "addr:street":"Courtlands Drive",
    "iso:country":"GB",
    "sg:address":"131 Courtlands Drive",
    "sg:city":"Watford",
    "sg:classifiers":[
        {
            "category":"Autos & Motor Vehicles",
            "subcategory":"Auto Supplies",
            "type":"Retail Goods"
        }
    ],
    "sg:phone":"+44 1923 672696",
    "sg:postcode":"WD24 5LL",
    "sg:province":"Hertfordshire",
    "sg:tags":[
        "tyre"
    ],
    "wof:name":"Ed's Treads Ltd.",
    "wof:placetype":"venue"
},
  "geometry": {"coordinates":[-0.418055,51.682945],"type":"Point"}
}