{
  "type": "Feature",
  "properties": {
    "iso:country":"GB",
    "sg:address":"Hillfoot Farm, Hitchin Road",
    "sg:city":"Shefford",
    "sg:classifiers":[
        {
            "category":"Building & Trades",
            "subcategory":"Construction",
            "type":"Services"
        }
    ],
    "sg:phone":"+44 1462 813325",
    "sg:postcode":"SG17 5JD",
    "sg:province":"Bedfordshire",
    "sg:tags":[
        "platform",
        "work",
        "scaffolding"
    ],
    "wof:name":"K & F Hydraulic Platforms Ltd.",
    "wof:placetype":"venue"
},
  "geometry": {"coordinates":[-0.334879,52.04134],"type":"Point"}
}