{
  "type": "Feature",
  "properties": {
    "iso:country":"GB",
    "sg:address":"Legh Road",
    "sg:city":"Manchester",
    "sg:classifiers":[
        {
            "category":"Education",
            "subcategory":"School",
            "type":"Public Place"
        }
    ],
    "sg:phone":"+44 161 792 7773",
    "sg:postcode":"M7 4RT",
    "sg:province":"Greater Manchester",
    "sg:tags":[
        "local",
        "authority"
    ],
    "wof:name":"Broughton Jewish Cassel Fox Primary School",
    "wof:placetype":"venue"
},
  "geometry": {"coordinates":[-2.26008,53.510971],"type":"Point"}
}