{
  "type": "Feature",
  "properties": {
    "addr:full":"7 Shelsley Dr Basildon Essex SS16 6NA",
    "addr:housenumber":"7",
    "addr:postcode":"ss16 6na",
    "addr:street":"Shelsley Dr",
    "iso:country":"GB",
    "sg:address":"7 Shelsley Dr",
    "sg:city":"Basildon",
    "sg:classifiers":[
        {
            "category":"Building & Trades",
            "subcategory":"Plumbing",
            "type":"Services"
        }
    ],
    "sg:phone":"+44 1268 417651",
    "sg:postcode":"SS16 6NA",
    "sg:province":"Essex",
    "sg:tags":[
        "heating"
    ],
    "wof:name":"T S B Heating",
    "wof:placetype":"venue"
},
  "geometry": {"coordinates":[0.423383,51.559013],"type":"Point"}
}