{
  "type": "Feature",
  "properties": {
    "addr:full":"Stamford House, High Street Northallerton North Yorkshire DL7 8EJ",
    "addr:postcode":"dl7 8ej",
    "addr:street":"High Street",
    "iso:country":"GB",
    "sg:address":"Stamford House, High Street",
    "sg:city":"Northallerton",
    "sg:classifiers":[
        {
            "category":"Real Estate",
            "subcategory":"Real Estate Operator",
            "type":"Services"
        }
    ],
    "sg:phone":"+44 1609 777757",
    "sg:postcode":"DL7 8EJ",
    "sg:province":"North Yorkshire",
    "sg:tags":[
        "letting",
        "agent"
    ],
    "wof:name":"John Prest Property Management",
    "wof:placetype":"venue"
},
  "geometry": {"coordinates":[-1.435759,54.341911],"type":"Point"}
}