{
  "type": "Feature",
  "properties": {
    "addr:full":"Asterby Cottage, Goulceby Lane Louth Lincolnshire LN11 9UX",
    "addr:postcode":"ln11 9ux",
    "addr:street":"Goulceby Lane Louth",
    "iso:country":"GB",
    "sg:address":"Asterby Cottage, Goulceby Lane",
    "sg:city":"Louth",
    "sg:classifiers":[
        {
            "category":"Farming",
            "subcategory":"Farm",
            "type":"Manufacturing & Wholesale Goods"
        }
    ],
    "sg:postcode":"LN11 9UX",
    "sg:province":"Lincolnshire",
    "sg:tags":[
        "mixed",
        "crop"
    ],
    "wof:name":"M E & A Gilding",
    "wof:placetype":"venue"
},
  "geometry": {"coordinates":[-0.106419,53.299606],"type":"Point"}
}