{
  "type": "Feature",
  "properties": {
    "iso:country":"GB",
    "sg:address":"1 Bungalow, Moorhouse Road, Laxton",
    "sg:city":"Newark",
    "sg:classifiers":[
        {
            "category":"Freight",
            "type":"Transportation"
        }
    ],
    "sg:postcode":"NG22 0NU",
    "sg:province":"Nottinghamshire",
    "sg:tags":[
        "haulage",
        "road"
    ],
    "wof:name":"George D Noble",
    "wof:placetype":"venue"
},
  "geometry": {"coordinates":[-0.9203490019,53.1962013245],"type":"Point"}
}