{
  "type": "Feature",
  "properties": {
    "iso:country":"GB",
    "sg:address":"16 Lower Village Road, Sunninghill",
    "sg:city":"Ascot",
    "sg:classifiers":[
        {
            "category":"Autos & Motor Vehicles",
            "subcategory":"Automobile Sales",
            "type":"Retail Goods"
        }
    ],
    "sg:postcode":"SL5 7AU",
    "sg:province":"Berkshire",
    "sg:tags":[
        "car"
    ],
    "wof:name":"Centrephase Ltd.",
    "wof:placetype":"venue"
},
  "geometry": {"coordinates":[-0.657412,51.403706],"type":"Point"}
}