{
  "type": "Feature",
  "properties": {
    "iso:country":"GB",
    "sg:address":"85 Highways Avenue, Euxton",
    "sg:city":"Chorley",
    "sg:classifiers":[
        {
            "category":"Utilities",
            "subcategory":"Water",
            "type":"Services"
        },
        {
            "category":"Military Area",
            "subcategory":"Air Force Base",
            "type":"Public Place"
        }
    ],
    "sg:phone":"+44 1257 279359",
    "sg:postcode":"PR7 6QD",
    "sg:province":"Lancashire",
    "sg:tags":[
        "treatment"
    ],
    "wof:name":"The Cutting Edge",
    "wof:placetype":"venue"
},
  "geometry": {"coordinates":[-2.668924,53.657433],"type":"Point"}
}