{
  "type": "Feature",
  "properties": {
    "addr:full":"6 Railway Rd Leigh Lancashire WN7 4AX",
    "addr:housenumber":"6",
    "addr:postcode":"wn7 4ax",
    "addr:street":"Railway Rd",
    "iso:country":"GB",
    "sg:address":"6 Railway Rd",
    "sg:city":"Leigh",
    "sg:classifiers":[
        {
            "category":"Recreation",
            "subcategory":"Amusement Park",
            "type":"Entertainment"
        }
    ],
    "sg:postcode":"WN7 4AX",
    "sg:province":"Lancashire",
    "sg:tags":[
        "arcade"
    ],
    "wof:name":"Otium Investments Ltd",
    "wof:placetype":"venue"
},
  "geometry": {"coordinates":[-2.5196609497,53.4967575073],"type":"Point"}
}