{
  "type": "Feature",
  "properties": {
    "addr:full":"Pepper Road, Hazel Gro Stockport Cheshire SK7 5BW",
    "addr:postcode":"sk7 5bw",
    "addr:street":"Pepper Road",
    "iso:country":"GB",
    "sg:address":"Pepper Road, Hazel Gro",
    "sg:city":"Stockport",
    "sg:classifiers":[
        {
            "category":"Arena",
            "subcategory":"Sports Club",
            "type":"Entertainment"
        }
    ],
    "sg:phone":"+44 161 483 0593",
    "sg:postcode":"SK7 5BW",
    "sg:province":"Cheshire",
    "wof:name":"Philips Sports & Social Club",
    "wof:placetype":"venue"
},
  "geometry": {"coordinates":[-2.137787,53.377171],"type":"Point"}
}