{
  "type": "Feature",
  "properties": {
    "addr:full":"Marlebeck, Carr Lane York East Riding of Yorkshire YO41 5PG",
    "addr:postcode":"yo41 5pg",
    "addr:street":"Marlebeck Carr Lane",
    "iso:country":"GB",
    "sg:address":"Marlebeck, Carr Lane",
    "sg:city":"York",
    "sg:classifiers":[
        {
            "category":"Retail",
            "subcategory":"Auto Repair",
            "type":"Services"
        }
    ],
    "sg:postcode":"YO41 5PG",
    "sg:province":"East Riding of Yorkshire",
    "sg:tags":[
        "body",
        "car"
    ],
    "wof:name":"A Mahon Motor Body Repairs",
    "wof:placetype":"venue"
},
  "geometry": {"coordinates":[-0.8795999885,53.937461853],"type":"Point"}
}