{
  "type": "Feature",
  "properties": {
    "addr:full":"4 Paxcroft Way Trowbridge Wiltshire BA14 7DG",
    "addr:housenumber":"4",
    "addr:postcode":"ba14 7dg",
    "addr:street":"Paxcroft Way",
    "iso:country":"GB",
    "sg:address":"4 Paxcroft Way",
    "sg:city":"Trowbridge",
    "sg:classifiers":[
        {
            "category":"Retail",
            "subcategory":"Veterinary Services",
            "type":"Services"
        }
    ],
    "sg:phone":"+44 1225 760630",
    "sg:postcode":"BA14 7DG",
    "sg:province":"Wiltshire",
    "sg:tags":[
        "surgeon"
    ],
    "wof:name":"Harris Hill & Warner",
    "wof:placetype":"venue"
},
  "geometry": {"coordinates":[-2.193802,51.318687],"type":"Point"}
}