{
  "type": "Feature",
  "properties": {
    "addr:full":"Imex Business Park, Hamilton Rd Manchester Greater Manchester M13 0PD",
    "addr:postcode":"m13 0pd",
    "addr:street":"Hamilton Rd",
    "iso:country":"GB",
    "sg:address":"Imex Business Park, Hamilton Rd",
    "sg:city":"Manchester",
    "sg:classifiers":[
        {
            "category":"Education",
            "subcategory":"Special Training",
            "type":"Public Place"
        }
    ],
    "sg:phone":"+44 161 225 9527",
    "sg:postcode":"M13 0PD",
    "sg:province":"Greater Manchester",
    "sg:tags":[
        "product",
        "centre"
    ],
    "wof:name":"Seeds Ltd",
    "wof:placetype":"venue"
},
  "geometry": {"coordinates":[-2.24881,53.479622],"type":"Point"}
}