{
  "type": "Feature",
  "properties": {
    "iso:country":"GB",
    "sg:address":"3 Hollybush Est",
    "sg:city":"Cardiff",
    "sg:classifiers":[
        {
            "category":"Shopping",
            "subcategory":"News",
            "type":"Retail Goods"
        }
    ],
    "sg:phone":"+44 29 2069 2655",
    "sg:postcode":"CF4 7DS",
    "sg:province":"Cardiff",
    "sg:tags":[
        "newsagent"
    ],
    "wof:name":"T & D News",
    "wof:placetype":"venue"
},
  "geometry": {"coordinates":[-3.234306,51.521332],"type":"Point"}
}