{
  "type": "Feature",
  "properties": {
    "addr:full":"Brixbury Ho, Down La Guildford Surrey GU3 1DQ",
    "addr:postcode":"gu3 1dq",
    "addr:street":"La",
    "iso:country":"GB",
    "sg:address":"Brixbury Ho, Down La",
    "sg:city":"Guildford",
    "sg:classifiers":[
        {
            "category":"Professional",
            "subcategory":"Engineering",
            "type":"Services"
        }
    ],
    "sg:phone":"+44 1483 810992",
    "sg:postcode":"GU3 1DQ",
    "sg:province":"Surrey",
    "sg:tags":[
        "consulting",
        "engineer"
    ],
    "wof:name":"Crouch Waterfall & Partners",
    "wof:placetype":"venue"
},
  "geometry": {"coordinates":[-0.62874,51.222172],"type":"Point"}
}