{
  "type": "Feature",
  "properties": {
    "addr:full":"2rd Floor, Suffolk House Croydon Surrey CR0 0YN",
    "addr:housenumber":"2rd floor suffolk house",
    "addr:postcode":"cr0 0yn",
    "addr:street":"Croydon",
    "iso:country":"GB",
    "sg:address":"2rd Floor, Suffolk House",
    "sg:city":"Croydon",
    "sg:classifiers":[
        {
            "category":"Professional",
            "subcategory":"Employment Agencies",
            "type":"Services"
        }
    ],
    "sg:phone":"+44 20 8649 9999",
    "sg:postcode":"CR0 0YN",
    "sg:province":"Surrey",
    "sg:tags":[
        "consultant"
    ],
    "wof:name":"Abacus Financial Selection",
    "wof:placetype":"venue"
},
  "geometry": {"coordinates":[-0.0118310004,51.3433303833],"type":"Point"}
}