{
  "type": "Feature",
  "properties": {
    "iso:country":"GB",
    "sg:address":"313 Kennington Road",
    "sg:city":"London",
    "sg:classifiers":[
        {
            "category":"Restaurant",
            "type":"Food & Drink"
        }
    ],
    "sg:phone":"+44 20 7735 9247",
    "sg:postcode":"SE11 4QE",
    "sg:province":"Greater London",
    "sg:tags":[
        "indian"
    ],
    "wof:name":"Kennington Tandoori",
    "wof:placetype":"venue"
},
  "geometry": {"coordinates":[-0.111061,51.488125],"type":"Point"}
}