{
  "type": "Feature",
  "properties": {
    "addr:full":"25 Botwell Lane Hayes Greater London UB3 2AB",
    "addr:housenumber":"25",
    "addr:postcode":"ub3 2ab",
    "addr:street":"Botwell Lane",
    "iso:country":"GB",
    "sg:address":"25 Botwell Lane",
    "sg:city":"Hayes",
    "sg:classifiers":[
        {
            "category":"Shopping",
            "subcategory":"News",
            "type":"Retail Goods"
        }
    ],
    "sg:postcode":"UB3 2AB",
    "sg:province":"Greater London",
    "sg:tags":[
        "newsagent"
    ],
    "wof:name":"Martin the Newsagent",
    "wof:placetype":"venue"
},
  "geometry": {"coordinates":[-0.4202100039,51.5078887939],"type":"Point"}
}