{
  "type": "Feature",
  "properties": {
    "iso:country":"GB",
    "sg:address":"3 Trinity St",
    "sg:city":"St Austell",
    "sg:classifiers":[
        {
            "category":"Home & Garden",
            "subcategory":"Home Furnishings",
            "type":"Retail Goods"
        }
    ],
    "sg:postcode":"PL25 5LS",
    "sg:province":"Cornwall",
    "sg:tags":[
        "blind",
        "curtain",
        "fitting"
    ],
    "wof:name":"Lee,Lindsey,",
    "wof:placetype":"venue"
},
  "geometry": {"coordinates":[-4.795656,50.338207],"type":"Point"}
}