{
  "type": "Feature",
  "properties": {
    "iso:country":"GB",
    "sg:address":"141a High St",
    "sg:city":"Waltham Cross",
    "sg:classifiers":[
        {
            "category":"Home & Garden",
            "subcategory":"Home Furnishings",
            "type":"Retail Goods"
        }
    ],
    "sg:phone":"+44 1992 641555",
    "sg:postcode":"EN8 7AP",
    "sg:province":"Essex",
    "sg:tags":[
        "blind",
        "curtain",
        "fitting"
    ],
    "wof:name":"The Curtain Factory",
    "wof:placetype":"venue"
},
  "geometry": {"coordinates":[-0.032969,51.685299],"type":"Point"}
}