{
  "type": "Feature",
  "properties": {
    "addr:full":"Higher Newton, Metherell Callington Cornwall PL17 8DF",
    "addr:postcode":"pl17 8df",
    "iso:country":"GB",
    "sg:address":"Higher Newton, Metherell",
    "sg:city":"Callington",
    "sg:classifiers":[
        {
            "category":"Shopping",
            "type":"Retail Goods"
        }
    ],
    "sg:postcode":"PL17 8DF",
    "sg:province":"Cornwall",
    "sg:tags":[
        "merchant"
    ],
    "wof:name":"Stephens,David,",
    "wof:placetype":"venue"
},
  "geometry": {"coordinates":[-4.2441940308,50.5050506592],"type":"Point"}
}