{
  "type": "Feature",
  "properties": {
    "iso:country":"GB",
    "sg:address":"Corporation Road",
    "sg:city":"Leicester",
    "sg:classifiers":[
        {
            "category":"Utilities",
            "subcategory":"Natural Gas",
            "type":"Services"
        }
    ],
    "sg:phone":"+44 116 268 1103",
    "sg:postcode":"LE4 5PW",
    "sg:province":"Leicestershire",
    "sg:tags":[
        "supplier"
    ],
    "wof:name":"Midland Gas",
    "wof:placetype":"venue"
},
  "geometry": {"coordinates":[-1.131629,52.655849],"type":"Point"}
}