{
  "type": "Feature",
  "properties": {
    "addr:full":"15 Mayfair Avenue, Whitefield Manchester Lancashire M45 6AR",
    "addr:housenumber":"15",
    "addr:postcode":"m45 6ar",
    "addr:street":"Mayfair Avenue",
    "iso:country":"GB",
    "sg:address":"15 Mayfair Avenue, Whitefield",
    "sg:city":"Manchester",
    "sg:classifiers":[
        {
            "category":"Professional",
            "subcategory":"Art Services",
            "type":"Services"
        }
    ],
    "sg:postcode":"M45 6AR",
    "sg:province":"Lancashire",
    "sg:tags":[
        "photographer"
    ],
    "wof:name":"Walter Brooks",
    "wof:placetype":"venue"
},
  "geometry": {"coordinates":[-2.287786,53.543552],"type":"Point"}
}