{
  "type": "Feature",
  "properties": {
    "addr:full":"Main Street, Old Plean Stirling Falkirk FK7 8BQ",
    "addr:postcode":"fk7 8bq",
    "addr:street":"Main Street",
    "iso:country":"GB",
    "sg:address":"Main Street, Old Plean",
    "sg:city":"Stirling",
    "sg:classifiers":[
        {
            "category":"Health Services",
            "subcategory":"Nursing And Care Facility",
            "type":"Services"
        },
        {
            "category":"Social Services",
            "subcategory":"Retirement Home",
            "type":"Services"
        }
    ],
    "sg:phone":"+44 1786 812421",
    "sg:postcode":"FK7 8BQ",
    "sg:province":"Falkirk",
    "sg:tags":[
        "residential"
    ],
    "wof:name":"William Simpson's Home",
    "wof:placetype":"venue"
},
  "geometry": {"coordinates":[-3.916309,56.091114],"type":"Point"}
}