{
  "type": "Feature",
  "properties": {
    "addr:full":"412 Manchester Road, Heaton Chapel Stockport Cheshire SK4 5BY",
    "addr:housenumber":"412",
    "addr:postcode":"sk4 5by",
    "addr:street":"Manchester Road",
    "iso:country":"GB",
    "sg:address":"412 Manchester Road, Heaton Chapel",
    "sg:city":"Stockport",
    "sg:classifiers":[
        {
            "category":"Organizations",
            "subcategory":"Religious Organization",
            "type":"Services"
        }
    ],
    "sg:phone":"+44 161 442 4090",
    "sg:postcode":"SK4 5BY",
    "sg:province":"Cheshire",
    "sg:tags":[
        "organisation"
    ],
    "wof:name":"Child Evangelism Fellowship",
    "wof:placetype":"venue"
},
  "geometry": {"coordinates":[-2.174768,53.428257],"type":"Point"}
}