{
  "type": "Feature",
  "properties": {
    "addr:full":"24-26 Eagle Court, Roentgen Road Basingstoke Hampshire RG24 8QX",
    "addr:housenumber":"24-26",
    "addr:postcode":"rg24 8qx",
    "addr:street":"Eagle Court Roentgen Road",
    "iso:country":"GB",
    "sg:address":"24-26 Eagle Court, Roentgen Road",
    "sg:city":"Basingstoke",
    "sg:classifiers":[
        {
            "category":"Conference Center",
            "type":"Public Place"
        }
    ],
    "sg:postcode":"RG24 8QX",
    "sg:province":"Hampshire",
    "sg:tags":[
        "trade",
        "exhibition",
        "centre"
    ],
    "wof:name":"Courts Exhibition Display Services",
    "wof:placetype":"venue"
},
  "geometry": {"coordinates":[-1.05964,51.272099],"type":"Point"}
}