{
  "type": "Feature",
  "properties": {
    "addr:full":"Hockley Way, Alfreton Trading Estate Alfreton Derbyshire DE55 7FA",
    "addr:housenumber":"estate",
    "addr:postcode":"de55 7fa",
    "addr:street":"Hockley Way;Trading",
    "iso:country":"GB",
    "sg:address":"Hockley Way, Alfreton Trading Estate",
    "sg:city":"Alfreton",
    "sg:classifiers":[
        {
            "category":"Wholesale",
            "subcategory":"Construction Materials",
            "type":"Manufacturing & Wholesale Goods"
        }
    ],
    "sg:phone":"+44 1773 608477",
    "sg:postcode":"DE55 7FA",
    "sg:province":"Derbyshire",
    "sg:tags":[
        "lift"
    ],
    "wof:name":"N I M Winches Ltd.",
    "wof:placetype":"venue"
},
  "geometry": {"coordinates":[-1.3774089813,53.0883865356],"type":"Point"}
}