{
  "type": "Feature",
  "properties": {
    "iso:country":"GB",
    "sg:address":"Unit 10 Hermes Road, Gilmoss Industrial Estate",
    "sg:city":"Liverpool",
    "sg:classifiers":[
        {
            "category":"Professional",
            "subcategory":"Art Services",
            "type":"Services"
        }
    ],
    "sg:phone":"+44 151 549 2411",
    "sg:postcode":"L11 0ED",
    "sg:province":"Merseyside",
    "sg:tags":[
        "decorating",
        "painting"
    ],
    "wof:name":"Courtaulds Coatings",
    "wof:placetype":"venue"
},
  "geometry": {"coordinates":[-2.904511,53.463943],"type":"Point"}
}