{
  "type": "Feature",
  "properties": {
    "addr:full":"Gargrave Road, Stirton Skipton Lancashire BD23 1UE",
    "addr:postcode":"bd23 1ue",
    "addr:street":"Gargrave Road",
    "iso:country":"GB",
    "sg:address":"Gargrave Road, Stirton",
    "sg:city":"Skipton",
    "sg:classifiers":[
        {
            "category":"Autos & Motor Vehicles",
            "subcategory":"Automobile Sales",
            "type":"Retail Goods"
        }
    ],
    "sg:phone":"+44 1756 792277",
    "sg:postcode":"BD23 1UE",
    "sg:province":"Lancashire",
    "sg:tags":[
        "car"
    ],
    "wof:name":"Nicholas Smith's Garages Ltd.",
    "wof:placetype":"venue"
},
  "geometry": {"coordinates":[-2.0274329185,53.96326828],"type":"Point"}
}