{
  "type": "Feature",
  "properties": {
    "addr:full":"9-13 St Anns Parade Wilmslow Cheshire SK9 1HG",
    "addr:housenumber":"9-13",
    "addr:postcode":"sk9 1hg",
    "addr:street":"St Anns Parade",
    "iso:country":"GB",
    "sg:address":"9-13 St Anns Parade",
    "sg:city":"Wilmslow",
    "sg:classifiers":[
        {
            "category":"Shopping",
            "subcategory":"Clothing, Apparel, & Fashions",
            "type":"Retail Goods"
        }
    ],
    "sg:phone":"+44 1625 532204",
    "sg:postcode":"SK9 1HG",
    "sg:province":"Cheshire",
    "sg:tags":[
        "menswear"
    ],
    "wof:name":"Robert Leonards (Wilmslow) Ltd.",
    "wof:placetype":"venue"
},
  "geometry": {"coordinates":[-2.2278969288,53.3267974854],"type":"Point"}
}