{
  "type": "Feature",
  "properties": {
    "addr:full":"17 Corn Square Leominster Herefordshire HR6 8AB",
    "addr:housenumber":"17",
    "addr:postcode":"hr6 8ab",
    "addr:street":"Corn Square",
    "iso:country":"GB",
    "sg:address":"17 Corn Square",
    "sg:city":"Leominster",
    "sg:classifiers":[
        {
            "category":"Retail",
            "subcategory":"Laundry & Dry Cleaning",
            "type":"Services"
        }
    ],
    "sg:phone":"+44 1568 616346",
    "sg:postcode":"HR6 8AB",
    "sg:province":"Herefordshire",
    "sg:tags":[
        "launderette"
    ],
    "wof:name":"One Stop Launderette & Dry Cleaning",
    "wof:placetype":"venue"
},
  "geometry": {"coordinates":[-2.737949,52.226917],"type":"Point"}
}