{
  "type": "Feature",
  "properties": {
    "addr:full":"8 London Road Liphook Hampshire GU30 7AN",
    "addr:housenumber":"8",
    "addr:postcode":"gu30 7an",
    "addr:street":"London Road",
    "iso:country":"GB",
    "sg:address":"8 London Road",
    "sg:city":"Liphook",
    "sg:classifiers":[
        {
            "category":"Conference Center",
            "type":"Public Place"
        }
    ],
    "sg:phone":"+44 1428 727476",
    "sg:postcode":"GU30 7AN",
    "sg:province":"Hampshire",
    "wof:name":"I M L Ltd.",
    "wof:placetype":"venue"
},
  "geometry": {"coordinates":[-0.8024029732,51.0776443481],"type":"Point"}
}