{
  "type": "Feature",
  "properties": {
    "addr:full":"10/11 Market Street Barry The Vale of Glamorgan CF62 7AS",
    "addr:housenumber":"10 / 11",
    "addr:postcode":"cf62 7as",
    "addr:street":"Market Street;Vale",
    "iso:country":"GB",
    "sg:address":"10/11 Market Street",
    "sg:city":"Barry",
    "sg:classifiers":[
        {
            "category":"Organizations",
            "subcategory":"Political Organization",
            "type":"Services"
        }
    ],
    "sg:phone":"+44 1446 733516",
    "sg:postcode":"CF62 7AS",
    "sg:province":"The Vale of Glamorgan",
    "sg:tags":[
        "party"
    ],
    "wof:name":"Conservative Association",
    "wof:placetype":"venue"
},
  "geometry": {"coordinates":[-3.284636,51.398865],"type":"Point"}
}