{
  "type": "Feature",
  "properties": {
    "addr:full":"Brook House, 43 Shetland Drive Ellesmere Port Cheshire CH65 9HT",
    "addr:housenumber":"43",
    "addr:postcode":"ch65 9ht",
    "addr:street":"Shetland Drive",
    "iso:country":"GB",
    "sg:address":"Brook House, 43 Shetland Drive",
    "sg:city":"Ellesmere Port",
    "sg:classifiers":[
        {
            "category":"Recreation",
            "type":"Entertainment"
        }
    ],
    "sg:phone":"+44 151 357 3376",
    "sg:postcode":"CH65 9HT",
    "sg:province":"Cheshire",
    "sg:tags":[
        "corporate",
        "leisure"
    ],
    "wof:name":"Diamond Destination",
    "wof:placetype":"venue"
},
  "geometry": {"coordinates":[-2.89545,53.260895],"type":"Point"}
}