{
  "type": "Feature",
  "properties": {
    "addr:full":"Unit D1 Bank Top Industrial Estate, St Martins Oswestry Shropshire SY10 7BB",
    "addr:postcode":"sy10 7bb",
    "addr:street":"Top Industrial Estate St",
    "iso:country":"GB",
    "sg:address":"Unit D1 Bank Top Industrial Estate, St Martins",
    "sg:city":"Oswestry",
    "sg:classifiers":[
        {
            "category":"Retail",
            "subcategory":"Auto Repair",
            "type":"Services"
        }
    ],
    "sg:phone":"+44 1691 774853",
    "sg:postcode":"SY10 7BB",
    "sg:province":"Shropshire",
    "sg:tags":[
        "body",
        "car"
    ],
    "wof:name":"Panel Fix",
    "wof:placetype":"venue"
},
  "geometry": {"coordinates":[-3.00663,52.924999],"type":"Point"}
}