{
  "type": "Feature",
  "properties": {
    "iso:country":"GB",
    "sg:address":"36 Russell Road",
    "sg:city":"Rhyl",
    "sg:classifiers":[
        {
            "category":"Building & Trades",
            "subcategory":"Construction",
            "type":"Services"
        }
    ],
    "sg:postcode":"LL18 3DS",
    "sg:province":"Conwy",
    "sg:tags":[
        "dry",
        "lining",
        "plasterers",
        "screeders"
    ],
    "wof:name":"A1 Ceilings",
    "wof:placetype":"venue"
},
  "geometry": {"coordinates":[-3.4789988995,53.3261795044],"type":"Point"}
}