{
  "type": "Feature",
  "properties": {
    "addr:full":"154 Felixstowe Road Ipswich Suffolk IP3 8EF",
    "addr:housenumber":"154",
    "addr:postcode":"ip3 8ef",
    "addr:street":"Felixstowe Road",
    "iso:country":"GB",
    "sg:address":"154 Felixstowe Road",
    "sg:city":"Ipswich",
    "sg:classifiers":[
        {
            "category":"Recreation",
            "subcategory":"Fishing",
            "type":"Entertainment"
        }
    ],
    "sg:postcode":"IP3 8EF",
    "sg:province":"Suffolk",
    "sg:tags":[
        "angling"
    ],
    "wof:name":"Ipswich Angling Centre",
    "wof:placetype":"venue"
},
  "geometry": {"coordinates":[1.179666,52.048161],"type":"Point"}
}