{
  "type": "Feature",
  "properties": {
    "addr:full":"Paynes Park Garages, Paynes Park Hitchin Bedfordshire SG5 1EH",
    "addr:postcode":"sg5 1eh",
    "addr:street":"Paynes Park Garages Paynes Park",
    "iso:country":"GB",
    "sg:address":"Paynes Park Garages, Paynes Park",
    "sg:city":"Hitchin",
    "sg:classifiers":[
        {
            "category":"Autos & Motor Vehicles",
            "subcategory":"Automobile Sales",
            "type":"Retail Goods"
        }
    ],
    "sg:phone":"+44 1462 453060",
    "sg:postcode":"SG5 1EH",
    "sg:province":"Bedfordshire",
    "sg:tags":[
        "car"
    ],
    "wof:name":"Redacre Cars",
    "wof:placetype":"venue"
},
  "geometry": {"coordinates":[-0.280312,51.948723],"type":"Point"}
}