{
  "type": "Feature",
  "properties": {
    "addr:full":"Rowan Rd Redditch Warwickshire B97 6NB",
    "addr:postcode":"b97 6nb",
    "addr:street":"Rowan Rd",
    "iso:country":"GB",
    "sg:address":"Rowan Rd",
    "sg:city":"Redditch",
    "sg:classifiers":[
        {
            "category":"Place Of Worship",
            "type":"Public Place"
        }
    ],
    "sg:phone":"+44 1527 63096",
    "sg:postcode":"B97 6NB",
    "sg:province":"Warwickshire",
    "wof:name":"St Benedict Church",
    "wof:placetype":"venue"
},
  "geometry": {"coordinates":[-1.9681090117,52.3073806763],"type":"Point"}
}