{
  "type": "Feature",
  "properties": {
    "iso:country":"GB",
    "sg:address":"8 High Street",
    "sg:city":"Wirral",
    "sg:classifiers":[
        {
            "category":"Communications",
            "type":"Services"
        }
    ],
    "sg:phone":"+44 151 334 1874",
    "sg:postcode":"CH62 7HA",
    "sg:province":"Cheshire",
    "sg:tags":[
        "tv",
        "video",
        "radio"
    ],
    "wof:name":"Peters Hi Fi",
    "wof:placetype":"venue"
},
  "geometry": {"coordinates":[-2.9767520428,53.3320922852],"type":"Point"}
}