{
  "type": "Feature",
  "properties": {
    "iso:country":"GB",
    "sg:address":"Burtonhead Road",
    "sg:city":"St Helens",
    "sg:classifiers":[
        {
            "category":"Manufacturing",
            "subcategory":"Building Materials",
            "type":"Manufacturing & Wholesale Goods"
        }
    ],
    "sg:phone":"+44 1744 756634",
    "sg:postcode":"WA9 5DS",
    "sg:province":"Cheshire",
    "sg:tags":[
        "merchant",
        "builder"
    ],
    "wof:name":"Mainsway Ltd.",
    "wof:placetype":"venue"
},
  "geometry": {"coordinates":[-2.7316789627,53.4423942566],"type":"Point"}
}