{
  "type": "Feature",
  "properties": {
    "addr:full":"15a Vicarage Field Centre, Ripple Road Barking Essex IG11 8DQ",
    "addr:housenumber":"15a",
    "addr:postcode":"ig11 8dq",
    "addr:street":"Vicarage Field Centre Ripple Road",
    "iso:country":"GB",
    "sg:address":"15a Vicarage Field Centre, Ripple Road",
    "sg:city":"Barking",
    "sg:classifiers":[
        {
            "category":"Shopping",
            "subcategory":"Comic Books",
            "type":"Retail Goods"
        }
    ],
    "sg:phone":"+44 20 8507 9313",
    "sg:postcode":"IG11 8DQ",
    "sg:province":"Essex",
    "sg:tags":[
        "jeweller"
    ],
    "wof:name":"H Samuel",
    "wof:placetype":"venue"
},
  "geometry": {"coordinates":[0.0811149999,51.539100647],"type":"Point"}
}