{
  "type": "Feature",
  "properties": {
    "iso:country":"GB",
    "sg:address":"51 Norman Street",
    "sg:city":"Ilkeston",
    "sg:classifiers":[
        {
            "category":"Food & Beverages",
            "subcategory":"Meat & Fish",
            "type":"Retail Goods"
        }
    ],
    "sg:postcode":"DE7 8JZ",
    "sg:province":"Derbyshire",
    "sg:tags":[
        "chip"
    ],
    "wof:name":"Fish & Chips Emporium",
    "wof:placetype":"venue"
},
  "geometry": {"coordinates":[-1.3119009733,52.9850845337],"type":"Point"}
}