{
  "type": "Feature",
  "properties": {
    "addr:full":"Unit 10 Canal Bank Estate, Seabegs Road Bonnybridge Falkirk FK4 2BP",
    "addr:housenumber":"unit 10",
    "addr:postcode":"fk4 2bp",
    "addr:street":"Canal Bank Estate Seabegs Road",
    "iso:country":"GB",
    "sg:address":"Unit 10 Canal Bank Estate, Seabegs Road",
    "sg:city":"Bonnybridge",
    "sg:classifiers":[
        {
            "category":"Retail",
            "subcategory":"Auto Repair",
            "type":"Services"
        }
    ],
    "sg:phone":"+44 1324 812096",
    "sg:postcode":"FK4 2BP",
    "sg:province":"Falkirk",
    "sg:tags":[
        "modification",
        "garage",
        "related"
    ],
    "wof:name":"Saltire Motor Services",
    "wof:placetype":"venue"
},
  "geometry": {"coordinates":[-3.877349,55.994091],"type":"Point"}
}