{
  "type": "Feature",
  "properties": {
    "iso:country":"GB",
    "sg:address":"Tardygate Mill, Coote Lane, Lostock Hall",
    "sg:city":"Preston",
    "sg:classifiers":[
        {
            "category":"Retail",
            "subcategory":"Auto Rental",
            "type":"Services"
        }
    ],
    "sg:phone":"+44 1772 315588",
    "sg:postcode":"PR5 5JD",
    "sg:province":"Lancashire",
    "sg:tags":[
        "car"
    ],
    "wof:name":"4 Lane West Yorkshire Accident Assistance",
    "wof:placetype":"venue"
},
  "geometry": {"coordinates":[-2.687744,53.727406],"type":"Point"}
}