{
  "type": "Feature",
  "properties": {
    "addr:full":"Factory Street Bradford West Yorkshire BD4 9NN",
    "addr:postcode":"bd4 9nn",
    "addr:street":"Factory Street",
    "iso:country":"GB",
    "sg:address":"Factory Street",
    "sg:city":"Bradford",
    "sg:classifiers":[
        {
            "category":"Shopping",
            "type":"Retail Goods"
        }
    ],
    "sg:phone":"+44 1274 688795",
    "sg:postcode":"BD4 9NN",
    "sg:province":"West Yorkshire",
    "sg:tags":[
        "part",
        "accessory"
    ],
    "wof:name":"S C C Marketing Ltd.",
    "wof:placetype":"venue"
},
  "geometry": {"coordinates":[-1.727581,53.774261],"type":"Point"}
}