{
  "type": "Feature",
  "properties": {
    "addr:full":"Spring Farm, Spring Lane, Moorlinch Bridgwater Somerset TA7 9DD",
    "addr:postcode":"ta7 9dd",
    "addr:street":"Spring Lane",
    "iso:country":"GB",
    "sg:address":"Spring Farm, Spring Lane, Moorlinch",
    "sg:city":"Bridgwater",
    "sg:classifiers":[
        {
            "category":"Manufacturing",
            "subcategory":"Glass & Minerals",
            "type":"Manufacturing & Wholesale Goods"
        }
    ],
    "sg:phone":"+44 1458 211153",
    "sg:postcode":"TA7 9DD",
    "sg:province":"Somerset",
    "sg:tags":[
        "mnfrs",
        "product",
        "fibre"
    ],
    "wof:name":"The Original Perfume Bottle Co. Ltd.",
    "wof:placetype":"venue"
},
  "geometry": {"coordinates":[-2.862434,51.12936],"type":"Point"}
}