{
  "type": "Feature",
  "properties": {
    "addr:full":"10 West Street Bicester Oxfordshire OX26 2EW",
    "addr:housenumber":"10",
    "addr:postcode":"ox26 2ew",
    "addr:street":"West Street",
    "iso:country":"GB",
    "sg:address":"10 West Street",
    "sg:city":"Bicester",
    "sg:classifiers":[
        {
            "category":"Building & Trades",
            "subcategory":"Plumbing",
            "type":"Services"
        }
    ],
    "sg:postcode":"OX26 2EW",
    "sg:province":"Oxfordshire",
    "sg:tags":[
        "heating"
    ],
    "wof:name":"Timothy Sean Ward",
    "wof:placetype":"venue"
},
  "geometry": {"coordinates":[-1.1625809669,51.9043273926],"type":"Point"}
}