{
  "type": "Feature",
  "properties": {
    "iso:country":"GB",
    "sg:address":"107-109 Albert Road",
    "sg:city":"Southsea",
    "sg:classifiers":[
        {
            "category":"Home & Garden",
            "subcategory":"Carpets & Floor Coverings",
            "type":"Retail Goods"
        }
    ],
    "sg:phone":"+44 23 9282 6415",
    "sg:postcode":"PO5 2SQ",
    "sg:province":"Hampshire",
    "sg:tags":[
        "carpets",
        "rug",
        "matting"
    ],
    "wof:name":"Classic Carpets",
    "wof:placetype":"venue"
},
  "geometry": {"coordinates":[-1.077537,50.786785],"type":"Point"}
}