{
  "type": "Feature",
  "properties": {
    "addr:full":"157 Station Rd, Impington Cambridge Cambridgeshire CB4 9NP",
    "addr:housenumber":"157",
    "addr:postcode":"cb4 9np",
    "addr:street":"Station Rd",
    "iso:country":"GB",
    "sg:address":"157 Station Rd, Impington",
    "sg:city":"Cambridge",
    "sg:classifiers":[
        {
            "category":"Shopping",
            "subcategory":"News",
            "type":"Retail Goods"
        }
    ],
    "sg:phone":"+44 1223 232560",
    "sg:postcode":"CB4 9NP",
    "sg:province":"Cambridgeshire",
    "sg:tags":[
        "newsagent"
    ],
    "wof:name":"Balfour News",
    "wof:placetype":"venue"
},
  "geometry": {"coordinates":[0.1108969972,52.2426605225],"type":"Point"}
}