{
  "type": "Feature",
  "properties": {
    "addr:full":"Scope House, High Street Bordon Hampshire GU35 0AY",
    "addr:postcode":"gu35 0ay",
    "addr:street":"High Street",
    "iso:country":"GB",
    "sg:address":"Scope House, High Street",
    "sg:city":"Bordon",
    "sg:classifiers":[
        {
            "category":"Professional",
            "subcategory":"Accounting & Tax Preparation",
            "type":"Services"
        }
    ],
    "sg:phone":"+44 1420 473473",
    "sg:postcode":"GU35 0AY",
    "sg:province":"Hampshire",
    "sg:tags":[
        "accountant",
        "chartered"
    ],
    "wof:name":"The Dyer Partnership Ltd.",
    "wof:placetype":"venue"
},
  "geometry": {"coordinates":[-0.8637040257,51.1113395691],"type":"Point"}
}