{
  "type": "Feature",
  "properties": {
    "addr:full":"London Heathrow Airport Hounslow Greater London TW6 2JA",
    "addr:postcode":"tw6 2ja",
    "addr:street":"Airport",
    "iso:country":"GB",
    "sg:address":"London Heathrow Airport",
    "sg:city":"Hounslow",
    "sg:classifiers":[
        {
            "category":"Airline",
            "type":"Transportation"
        }
    ],
    "sg:phone":"+44 20 8759 1119",
    "sg:postcode":"TW6 2JA",
    "sg:province":"Greater London",
    "wof:name":"Yugoslav Airlines",
    "wof:placetype":"venue"
},
  "geometry": {"coordinates":[-0.4412499964,51.4804992676],"type":"Point"}
}