{
  "type": "Feature",
  "properties": {
    "addr:full":"9 Market Sq Chesham Buckinghamshire HP5 1HG",
    "addr:housenumber":"9",
    "addr:postcode":"hp5 1hg",
    "addr:street":"Market Sq",
    "iso:country":"GB",
    "sg:address":"9 Market Sq",
    "sg:city":"Chesham",
    "sg:classifiers":[
        {
            "category":"Shopping",
            "subcategory":"Florist",
            "type":"Retail Goods"
        }
    ],
    "sg:postcode":"HP5 1HG",
    "sg:province":"Buckinghamshire",
    "wof:name":"Effloresce Florists",
    "wof:placetype":"venue"
},
  "geometry": {"coordinates":[-0.609333,51.710537],"type":"Point"}
}