{
  "type": "Feature",
  "properties": {
    "addr:full":"17 Hartop Rd Torquay Devon TQ1 4QH",
    "addr:housenumber":"17",
    "addr:postcode":"tq1 4qh",
    "addr:street":"Hartop Rd",
    "iso:country":"GB",
    "sg:address":"17 Hartop Rd",
    "sg:city":"Torquay",
    "sg:classifiers":[
        {
            "category":"Retail",
            "subcategory":"Repair Shop",
            "type":"Services"
        }
    ],
    "sg:postcode":"TQ1 4QH",
    "sg:province":"Devon",
    "sg:tags":[
        "radio",
        "television",
        "video"
    ],
    "wof:name":"Avis,Richard,",
    "wof:placetype":"venue"
},
  "geometry": {"coordinates":[-3.5246610641,50.4857254028],"type":"Point"}
}