{
  "type": "Feature",
  "properties": {
    "iso:country":"GB",
    "sg:address":"Territorial Army Centre, Townsend Avenue, Norris Grn",
    "sg:city":"Liverpool",
    "sg:classifiers":[
        {
            "category":"Arts & Performance",
            "subcategory":"Music",
            "type":"Entertainment"
        },
        {
            "category":"Government",
            "subcategory":"Office",
            "type":"Public Place"
        }
    ],
    "sg:phone":"+44 151 270 1177",
    "sg:postcode":"L11 5AF",
    "sg:province":"Merseyside",
    "sg:tags":[
        "musician",
        "armed",
        "composer",
        "reserve"
    ],
    "wof:name":"Army T A Centre",
    "wof:placetype":"venue"
},
  "geometry": {"coordinates":[-2.978481,53.409775],"type":"Point"}
}