{
  "type": "Feature",
  "properties": {
    "addr:full":"Thornville House, Ladysmill Falkirk Falkirk FK2 9AU",
    "addr:postcode":"fk2 9au",
    "addr:street":"Ladysmill",
    "iso:country":"GB",
    "sg:address":"Thornville House, Ladysmill",
    "sg:city":"Falkirk",
    "sg:classifiers":[
        {
            "category":"Organizations",
            "subcategory":"Community Association",
            "type":"Services"
        }
    ],
    "sg:phone":"+44 1324 634357",
    "sg:postcode":"FK2 9AU",
    "sg:province":"Falkirk",
    "sg:tags":[
        "co-operatives",
        "society",
        "housing",
        "trust"
    ],
    "wof:name":"Abbeyfield Society (Falkirk)",
    "wof:placetype":"venue"
},
  "geometry": {"coordinates":[-3.7715480328,56.0023841858],"type":"Point"}
}