{
  "type": "Feature",
  "properties": {
    "iso:country":"GB",
    "sg:address":"Hems Court, 86 Longbrook Street",
    "sg:city":"Exeter",
    "sg:classifiers":[
        {
            "category":"Real Estate",
            "subcategory":"Surveying",
            "type":"Services"
        }
    ],
    "sg:phone":"+44 1392 427417",
    "sg:postcode":"EX4 6AP",
    "sg:province":"Devon",
    "sg:tags":[
        "building",
        "surveyor"
    ],
    "wof:name":"Povall Flood & Wilson Ltd.",
    "wof:placetype":"venue"
},
  "geometry": {"coordinates":[-3.5263540745,50.7282600403],"type":"Point"}
}