{
  "type": "Feature",
  "properties": {
    "iso:country":"GB",
    "sg:address":"16 Freeman Street",
    "sg:city":"Birmingham",
    "sg:classifiers":[
        {
            "category":"Bars & Pubs",
            "type":"Food & Drink"
        }
    ],
    "sg:postcode":"B5 5HT",
    "sg:province":"West Midlands",
    "sg:tags":[
        "pubs",
        "inn"
    ],
    "wof:name":"Fox & Grapes",
    "wof:placetype":"venue"
},
  "geometry": {"coordinates":[-1.890699,52.47961],"type":"Point"}
}