{
  "type": "Feature",
  "properties": {
    "addr:full":"5 Garrett Road, Lynx Trading Estate Yeovil Somerset BA20 2TJ",
    "addr:housenumber":"5",
    "addr:postcode":"ba20 2tj",
    "addr:street":"Garrett Road Lynx Trading Estate",
    "iso:country":"GB",
    "sg:address":"5 Garrett Road, Lynx Trading Estate",
    "sg:city":"Yeovil",
    "sg:classifiers":[
        {
            "category":"Manufacturing",
            "subcategory":"Tobacco Products",
            "type":"Manufacturing & Wholesale Goods"
        },
        {
            "category":"Professional",
            "subcategory":"Engineering",
            "type":"Services"
        }
    ],
    "sg:phone":"+44 1935 426695",
    "sg:postcode":"BA20 2TJ",
    "sg:province":"Somerset",
    "sg:tags":[
        "equipment",
        "suppliers",
        "disability",
        "manufacturers"
    ],
    "wof:name":"Koller Engineering Ltd",
    "wof:placetype":"venue"
},
  "geometry": {"coordinates":[-2.658467,50.933712],"type":"Point"}
}