{
  "type": "Feature",
  "properties": {
    "addr:full":"853 Dunstable Rd Luton Bedfordshire LU4 0HW",
    "addr:housenumber":"853",
    "addr:postcode":"lu4 0hw",
    "addr:street":"Dunstable Rd",
    "iso:country":"GB",
    "sg:address":"853 Dunstable Rd",
    "sg:city":"Luton",
    "sg:classifiers":[
        {
            "category":"Food & Beverages",
            "subcategory":"Liquor & Beverages",
            "type":"Retail Goods"
        }
    ],
    "sg:phone":"+44 1582 580140",
    "sg:postcode":"LU4 0HW",
    "sg:province":"Bedfordshire",
    "sg:tags":[
        "beer",
        "spirit",
        "wines"
    ],
    "wof:name":"AB Wines",
    "wof:placetype":"venue"
},
  "geometry": {"coordinates":[-0.4816040099,51.8919677734],"type":"Point"}
}