{
  "type": "Feature",
  "properties": {
    "iso:country":"GB",
    "sg:address":"Gurnos Road",
    "sg:city":"Merthyr Tydfil",
    "sg:classifiers":[
        {
            "category":"Health Services",
            "subcategory":"Nursing And Care Facility",
            "type":"Services"
        },
        {
            "category":"Social Services",
            "subcategory":"Retirement Home",
            "type":"Services"
        },
        {
            "category":"Government",
            "subcategory":"Office",
            "type":"Public Place"
        }
    ],
    "sg:phone":"+44 1685 722348",
    "sg:postcode":"CF47 9PT",
    "sg:province":"Merthyr Tydfil",
    "sg:tags":[
        "residential",
        "local"
    ],
    "wof:name":"Gurnos House",
    "wof:placetype":"venue"
},
  "geometry": {"coordinates":[-3.380089,51.760521],"type":"Point"}
}