{
  "type": "Feature",
  "properties": {
    "iso:country":"GB",
    "sg:address":"5 Orrock Place",
    "sg:city":"Hawick",
    "sg:classifiers":[
        {
            "category":"Shopping",
            "subcategory":"Antiques",
            "type":"Retail Goods"
        }
    ],
    "sg:postcode":"TD9 0HQ",
    "sg:province":"Cumbria",
    "wof:name":"Chisholme Antiques",
    "wof:placetype":"venue"
},
  "geometry": {"coordinates":[-2.790311,55.421783],"type":"Point"}
}