{
  "type": "Feature",
  "properties": {
    "addr:full":"Ashford Road, St Michaels Tenterden Kent TN30 6PR",
    "addr:postcode":"tn30 6pr",
    "addr:street":"Ashford Road",
    "iso:country":"GB",
    "sg:address":"Ashford Road, St Michaels",
    "sg:city":"Tenterden",
    "sg:classifiers":[
        {
            "category":"Food & Beverages",
            "subcategory":"Supermarket",
            "type":"Retail Goods"
        }
    ],
    "sg:postcode":"TN30 6PR",
    "sg:province":"Kent",
    "wof:name":"Costcutter",
    "wof:placetype":"venue"
},
  "geometry": {"coordinates":[0.6931949854,51.0739135742],"type":"Point"}
}