{
  "type": "Feature",
  "properties": {
    "iso:country":"GB",
    "sg:address":", Scorrier",
    "sg:city":"Redruth",
    "sg:classifiers":[
        {
            "category":"Cafe",
            "type":"Food & Drink"
        }
    ],
    "sg:phone":"+44 1209 821810",
    "sg:postcode":"TR16 5BJ",
    "sg:province":"Cornwall",
    "sg:tags":[
        "tea",
        "room"
    ],
    "wof:name":"Smokey Joe's Cafe",
    "wof:placetype":"venue"
},
  "geometry": {"coordinates":[-5.186599,50.249737],"type":"Point"}
}