{
  "type": "Feature",
  "properties": {
    "iso:country":"GB",
    "sg:address":"244b Edgware Road",
    "sg:city":"London",
    "sg:classifiers":[
        {
            "category":"Professional",
            "subcategory":"Lawyer & Legal Services",
            "type":"Services"
        }
    ],
    "sg:phone":"+44 20 8723 1266",
    "sg:postcode":"W2 1DS",
    "sg:province":"Greater London",
    "sg:tags":[
        "solicitor"
    ],
    "wof:name":"D W & Partnerships",
    "wof:placetype":"venue"
},
  "geometry": {"coordinates":[-0.168661,51.519138],"type":"Point"}
}