{
  "type": "Feature",
  "properties": {
    "iso:country":"GB",
    "sg:address":"Fairfield Surgery, High St",
    "sg:city":"Etchingham",
    "sg:classifiers":[
        {
            "category":"Health Services",
            "subcategory":"Doctor",
            "type":"Services"
        }
    ],
    "sg:phone":"+44 1435 882306",
    "sg:postcode":"TN19 7EU",
    "sg:province":"East Sussex",
    "sg:tags":[
        "practitioners"
    ],
    "wof:name":"Woodgate Dr B",
    "wof:placetype":"venue"
},
  "geometry": {"coordinates":[0.441642,51.00938],"type":"Point"}
}