{
  "type": "Feature",
  "properties": {
    "iso:country":"GB",
    "sg:address":"Preston Road, Charnock Richard",
    "sg:city":"Chorley",
    "sg:classifiers":[
        {
            "category":"Professional",
            "subcategory":"Engineering",
            "type":"Services"
        }
    ],
    "sg:phone":"+44 1257 794800",
    "sg:postcode":"PR7 5HL",
    "sg:province":"Lancashire",
    "wof:name":"Martin Calderbank",
    "wof:placetype":"venue"
},
  "geometry": {"coordinates":[-2.666289,53.634129],"type":"Point"}
}