{
  "type": "Feature",
  "properties": {
    "addr:full":"136 New St Birmingham West Midlands B2 4NS",
    "addr:housenumber":"136",
    "addr:postcode":"4ns",
    "addr:street":"New St",
    "iso:country":"GB",
    "sg:address":"136 New St",
    "sg:city":"Birmingham",
    "sg:classifiers":[
        {
            "category":"Shopping",
            "subcategory":"Mobile Phones",
            "type":"Retail Goods"
        }
    ],
    "sg:phone":"+44 121 633 7720",
    "sg:postcode":"B2 4NS",
    "sg:province":"West Midlands",
    "wof:name":"Martin Dawes",
    "wof:placetype":"venue"
},
  "geometry": {"coordinates":[-1.896977,52.478813],"type":"Point"}
}