{
  "type": "Feature",
  "properties": {
    "addr:full":"36a The Walk, New Inn Pontypool Monmouthshire NP4 0PU",
    "addr:housenumber":"36a",
    "addr:postcode":"np4 0pu",
    "addr:street":"The Walk",
    "iso:country":"GB",
    "sg:address":"36a The Walk, New Inn",
    "sg:city":"Pontypool",
    "sg:classifiers":[
        {
            "category":"Fast Food",
            "type":"Food & Drink"
        }
    ],
    "sg:phone":"+44 1495 757561",
    "sg:postcode":"NP4 0PU",
    "sg:province":"Monmouthshire",
    "sg:tags":[
        "away",
        "take"
    ],
    "wof:name":"Mayflower Take Away",
    "wof:placetype":"venue"
},
  "geometry": {"coordinates":[-3.0079960823,51.6914520264],"type":"Point"}
}