{
  "type": "Feature",
  "properties": {
    "iso:country":"GB",
    "sg:address":"18 Mt St",
    "sg:city":"Dorking",
    "sg:classifiers":[
        {
            "category":"Home & Garden",
            "subcategory":"Home Furnishings",
            "type":"Retail Goods"
        }
    ],
    "sg:phone":"+44 1306 883475",
    "sg:postcode":"RH4 3HT",
    "sg:province":"Surrey",
    "sg:tags":[
        "awning",
        "canopy",
        "blinds"
    ],
    "wof:name":"Alpine Blinds",
    "wof:placetype":"venue"
},
  "geometry": {"coordinates":[-0.348434,51.226986],"type":"Point"}
}