{
  "type": "Feature",
  "properties": {
    "addr:full":"26 Crosby Rd Southport Lancashire PR8 4TE",
    "addr:housenumber":"26",
    "addr:postcode":"pr8 4te",
    "addr:street":"Crosby Rd",
    "iso:country":"GB",
    "sg:address":"26 Crosby Rd",
    "sg:city":"Southport",
    "sg:classifiers":[
        {
            "category":"Building & Trades",
            "subcategory":"Construction",
            "type":"Services"
        }
    ],
    "sg:phone":"+44 1704 568769",
    "sg:postcode":"PR8 4TE",
    "sg:province":"Lancashire",
    "sg:tags":[
        "joiner",
        "carpenter"
    ],
    "wof:name":"Birkdale Windows & Conservatories",
    "wof:placetype":"venue"
},
  "geometry": {"coordinates":[-3.015174,53.630989],"type":"Point"}
}