{
  "type": "Feature",
  "properties": {
    "iso:country":"GB",
    "sg:address":"67 High Street",
    "sg:city":"Dover",
    "sg:classifiers":[
        {
            "category":"Restaurant",
            "type":"Food & Drink"
        }
    ],
    "sg:phone":"+44 1304 204419",
    "sg:postcode":"CT16 1EB",
    "sg:province":"Kent",
    "sg:tags":[
        "-",
        "chinese"
    ],
    "wof:name":"Good Luck Retaurant",
    "wof:placetype":"venue"
},
  "geometry": {"coordinates":[1.306034,51.129448],"type":"Point"}
}