{
  "type": "Feature",
  "properties": {
    "addr:full":"15 St. Christophers Place West End Hampshire W1M 5HD",
    "addr:housenumber":"15",
    "addr:postcode":"w1m 5hd",
    "addr:street":"St. Christophers Place",
    "iso:country":"GB",
    "sg:address":"15 St. Christophers Place",
    "sg:city":"West End",
    "sg:classifiers":[
        {
            "category":"Travel",
            "subcategory":"Hotels & Motels",
            "type":"Entertainment"
        }
    ],
    "sg:phone":"+44 20 7935 9191",
    "sg:postcode":"W1M 5HD",
    "sg:province":"Hampshire",
    "wof:name":"23 Greengarden House",
    "wof:placetype":"venue"
},
  "geometry": {"coordinates":[-0.1506879926,51.5159339905],"type":"Point"}
}