{
  "type": "Feature",
  "properties": {
    "addr:full":"Unit 14 Goodwood Square, Thornerby Stockton-on-tees Durham TS17 7BT",
    "addr:housenumber":"unit 14",
    "addr:postcode":"ts17 7bt",
    "addr:street":"Goodwood Square Thornerby",
    "iso:country":"GB",
    "sg:address":"Unit 14 Goodwood Square, Thornerby",
    "sg:city":"Stockton-on-tees",
    "sg:classifiers":[
        {
            "category":"Home & Garden",
            "subcategory":"Carpets & Floor Coverings",
            "type":"Retail Goods"
        }
    ],
    "sg:phone":"+44 1642 677784",
    "sg:postcode":"TS17 7BT",
    "sg:province":"Durham",
    "sg:tags":[
        "carpets",
        "rug",
        "matting"
    ],
    "wof:name":"Allied Carpets Group",
    "wof:placetype":"venue"
},
  "geometry": {"coordinates":[-1.275138,54.556126],"type":"Point"}
}