{
  "type": "Feature",
  "properties": {
    "addr:full":"Nether Mill Farm, Halberton Road, Willand Cullompton Devon EX15 2QQ",
    "addr:postcode":"ex15 2qq",
    "addr:street":"Nether;Halberton Road",
    "iso:country":"GB",
    "sg:address":"Nether Mill Farm, Halberton Road, Willand",
    "sg:city":"Cullompton",
    "sg:classifiers":[
        {
            "category":"Farming",
            "subcategory":"Livestock Farm",
            "type":"Manufacturing & Wholesale Goods"
        }
    ],
    "sg:phone":"+44 1884 820297",
    "sg:postcode":"EX15 2QQ",
    "sg:province":"Devon",
    "sg:tags":[
        "others"
    ],
    "wof:name":"J R Westcott",
    "wof:placetype":"venue"
},
  "geometry": {"coordinates":[-3.370959,50.888596],"type":"Point"}
}