{
  "type": "Feature",
  "properties": {
    "addr:full":"9 Heaton Close, Walton Le Dale Preston Lancashire PR5 4LJ",
    "addr:housenumber":"9",
    "addr:postcode":"pr5 4lj",
    "addr:street":"Heaton Close",
    "iso:country":"GB",
    "sg:address":"9 Heaton Close, Walton Le Dale",
    "sg:city":"Preston",
    "sg:classifiers":[
        {
            "category":"Retail",
            "subcategory":"Driving School",
            "type":"Services"
        }
    ],
    "sg:phone":"+44 1772 252449",
    "sg:postcode":"PR5 4LJ",
    "sg:province":"Lancashire",
    "wof:name":"Abba Driving School",
    "wof:placetype":"venue"
},
  "geometry": {"coordinates":[-2.674126,53.744785],"type":"Point"}
}