{
  "type": "Feature",
  "properties": {
    "addr:full":"Upper Brydekirk, Brydekirk Annan Dumfries and Galloway DG12 5NW",
    "addr:postcode":"dg12 5nw",
    "addr:street":"Upper;Brydekirk",
    "iso:country":"GB",
    "sg:address":"Upper Brydekirk, Brydekirk",
    "sg:city":"Annan",
    "sg:classifiers":[
        {
            "category":"Farming",
            "subcategory":"Farm",
            "type":"Manufacturing & Wholesale Goods"
        }
    ],
    "sg:phone":"+44 1576 300603",
    "sg:postcode":"DG12 5NW",
    "sg:province":"Dumfries and Galloway",
    "sg:tags":[
        "mixed",
        "crop"
    ],
    "wof:name":"T W & J Hunter",
    "wof:placetype":"venue"
},
  "geometry": {"coordinates":[-3.277154,55.022106],"type":"Point"}
}