{
  "type": "Feature",
  "properties": {
    "iso:country":"GB",
    "sg:address":"429 Chorley Old Road",
    "sg:city":"Bolton",
    "sg:classifiers":[
        {
            "category":"Professional",
            "subcategory":"Engineering",
            "type":"Services"
        },
        {
            "category":"Building & Trades",
            "subcategory":"Electrical",
            "type":"Services"
        }
    ],
    "sg:phone":"+44 1204 494909",
    "sg:postcode":"BL1 6AH",
    "sg:province":"Lancashire",
    "sg:tags":[
        "engineer",
        "electrician",
        "contractor"
    ],
    "wof:name":"R & T Shepherd Ltd",
    "wof:placetype":"venue"
},
  "geometry": {"coordinates":[-2.457737,53.58839],"type":"Point"}
}