{
  "type": "Feature",
  "properties": {
    "addr:full":"133 Bury New Road, Prestwich Manchester Greater Manchester M25 9NX",
    "addr:housenumber":"133",
    "addr:postcode":"m25 9nx",
    "addr:street":"Bury New Road",
    "iso:country":"GB",
    "sg:address":"133 Bury New Road, Prestwich",
    "sg:city":"Manchester",
    "sg:classifiers":[
        {
            "category":"Shopping",
            "subcategory":"News",
            "type":"Retail Goods"
        }
    ],
    "sg:phone":"+44 161 773 2804",
    "sg:postcode":"M25 9NX",
    "sg:province":"Greater Manchester",
    "sg:tags":[
        "newsagent"
    ],
    "wof:name":"Butt Hill Stores",
    "wof:placetype":"venue"
},
  "geometry": {"coordinates":[-2.2766749859,53.523601532],"type":"Point"}
}