{
  "type": "Feature",
  "properties": {
    "addr:full":"The Quaker House, Doncaster Road Wakefield West Yorkshire WF1 5EB",
    "addr:postcode":"wf1 5eb",
    "addr:street":"Doncaster Road",
    "iso:country":"GB",
    "sg:address":"The Quaker House, Doncaster Road",
    "sg:city":"Wakefield",
    "sg:classifiers":[
        {
            "category":"Autos & Motor Vehicles",
            "subcategory":"Automobile Sales",
            "type":"Retail Goods"
        },
        {
            "category":"Personal",
            "type":"Services"
        }
    ],
    "sg:phone":"+44 1924 364089",
    "sg:postcode":"WF1 5EB",
    "sg:province":"West Yorkshire",
    "sg:tags":[
        "car",
        "wedding"
    ],
    "wof:name":"Quaker House Classic Wedding Car Hire",
    "wof:placetype":"venue"
},
  "geometry": {"coordinates":[-1.4862589836,53.6732902527],"type":"Point"}
}