{
  "type": "Feature",
  "properties": {
    "iso:country":"GB",
    "sg:address":"Unit 3 Chunnel Industrial Estate, Victoria Road",
    "sg:city":"Ashford",
    "sg:classifiers":[
        {
            "category":"Autos & Motor Vehicles",
            "subcategory":"Auto Supplies",
            "type":"Retail Goods"
        }
    ],
    "sg:phone":"+44 1233 636363",
    "sg:postcode":"TN23 4HE",
    "sg:province":"Kent",
    "sg:tags":[
        "windscreen"
    ],
    "wof:name":"Autoglass (U K) Ltd.",
    "wof:placetype":"venue"
},
  "geometry": {"coordinates":[0.876037,51.146633],"type":"Point"}
}