{
  "type": "Feature",
  "properties": {
    "iso:country":"GB",
    "sg:address":"Unit 1 Best Of British",
    "sg:city":"Middlesbrough",
    "sg:classifiers":[
        {
            "category":"Food & Beverages",
            "subcategory":"Meat & Fish",
            "type":"Retail Goods"
        }
    ],
    "sg:phone":"+44 1642 319217",
    "sg:postcode":"TS6 7EF",
    "sg:province":"North Yorkshire",
    "sg:tags":[
        "chip"
    ],
    "wof:name":"Harlands",
    "wof:placetype":"venue"
},
  "geometry": {"coordinates":[-1.15085,54.578918],"type":"Point"}
}