{
  "type": "Feature",
  "properties": {
    "addr:full":"Gifford Ho 11 Denmark St Gateshead Tyne and Wear NE8 1NQ",
    "addr:housenumber":"11",
    "addr:postcode":"ne8 1nq",
    "addr:street":"Denmark St",
    "iso:country":"GB",
    "sg:address":"Gifford Ho 11 Denmark St",
    "sg:city":"Gateshead",
    "sg:classifiers":[
        {
            "category":"Travel",
            "subcategory":"Hotels & Motels",
            "type":"Entertainment"
        },
        {
            "category":"Organizations",
            "subcategory":"Non-profit Organization",
            "type":"Services"
        }
    ],
    "sg:phone":"+44 191 478 3931",
    "sg:postcode":"NE8 1NQ",
    "sg:province":"Tyne and Wear",
    "sg:tags":[
        "organisation",
        "voluntary",
        "charity"
    ],
    "wof:name":"Elliott House Management Company Limited",
    "wof:placetype":"venue"
},
  "geometry": {"coordinates":[-1.6011810303,54.9569396973],"type":"Point"}
}