{
  "type": "Feature",
  "properties": {
    "addr:full":"6 Greenhill Corsham Wiltshire SN13 9RN",
    "addr:housenumber":"6",
    "addr:postcode":"sn13 9rn",
    "addr:street":"Greenhill Corsham",
    "iso:country":"GB",
    "sg:address":"6 Greenhill",
    "sg:city":"Corsham",
    "sg:classifiers":[
        {
            "category":"Building & Trades",
            "subcategory":"Plumbing",
            "type":"Services"
        }
    ],
    "sg:phone":"+44 1225 810063",
    "sg:postcode":"SN13 9RN",
    "sg:province":"Wiltshire",
    "sg:tags":[
        "heating"
    ],
    "wof:name":"M Lindsey",
    "wof:placetype":"venue"
},
  "geometry": {"coordinates":[-2.205051899,51.4188232422],"type":"Point"}
}