{
  "type": "Feature",
  "properties": {
    "addr:full":"111 Stratford Road, Shirley Solihull West Midlands B90 3ND",
    "addr:housenumber":"111",
    "addr:postcode":"b90 3nd",
    "addr:street":"Stratford Road",
    "iso:country":"GB",
    "sg:address":"111 Stratford Road, Shirley",
    "sg:city":"Solihull",
    "sg:classifiers":[
        {
            "category":"Real Estate",
            "subcategory":"Real Estate Agent",
            "type":"Services"
        }
    ],
    "sg:phone":"+44 121 744 0777",
    "sg:postcode":"B90 3ND",
    "sg:province":"West Midlands",
    "wof:name":"Robert Oulsnam & Co",
    "wof:placetype":"venue"
},
  "geometry": {"coordinates":[-1.8284970522,52.4158172607],"type":"Point"}
}