{
  "type": "Feature",
  "properties": {
    "iso:country":"GB",
    "sg:address":"8 Wood Street",
    "sg:city":"Leicester",
    "sg:classifiers":[
        {
            "category":"Food & Beverages",
            "subcategory":"Bakery",
            "type":"Retail Goods"
        }
    ],
    "sg:phone":"+44 1455 840388",
    "sg:postcode":"LE9 7ND",
    "sg:province":"Leicestershire",
    "sg:tags":[
        "baker"
    ],
    "wof:name":"Simpkins",
    "wof:placetype":"venue"
},
  "geometry": {"coordinates":[-1.3162720203,52.5758247375],"type":"Point"}
}