{
  "type": "Feature",
  "properties": {
    "iso:country":"GB",
    "sg:address":"Out Lane Head Farm",
    "sg:city":"Preston",
    "sg:classifiers":[
        {
            "category":"Freight",
            "type":"Transportation"
        }
    ],
    "sg:phone":"+44 1995 61335",
    "sg:postcode":"PR3 2NQ",
    "sg:province":"Lancashire",
    "sg:tags":[
        "haulage",
        "road"
    ],
    "wof:name":"Keith S C Hardman",
    "wof:placetype":"venue"
},
  "geometry": {"coordinates":[-2.575067997,53.876537323],"type":"Point"}
}