{
  "type": "Feature",
  "properties": {
    "iso:country":"GB",
    "sg:address":"46 Richmond St",
    "sg:city":"Aberdeen",
    "sg:classifiers":[
        {
            "category":"Health Services",
            "subcategory":"Health Practitioner",
            "type":"Services"
        }
    ],
    "sg:postcode":"AB25 2TR",
    "sg:province":"Aberdeen City",
    "sg:tags":[
        "hypnotherapists"
    ],
    "wof:name":"Thompson,Hazel,",
    "wof:placetype":"venue"
},
  "geometry": {"coordinates":[-2.113962,57.150143],"type":"Point"}
}