{
  "type": "Feature",
  "properties": {
    "iso:country":"GB",
    "sg:address":"73 Rathbone Road, Wavertree",
    "sg:city":"Liverpool",
    "sg:classifiers":[
        {
            "category":"Banks & Credit Unions",
            "subcategory":"Bank",
            "type":"Services"
        },
        {
            "category":"Professional",
            "subcategory":"Business Services",
            "type":"Services"
        }
    ],
    "sg:phone":"+44 151 734 4914",
    "sg:postcode":"L15 4HG",
    "sg:province":"Merseyside",
    "sg:tags":[
        "stocktaking",
        "inventory"
    ],
    "wof:name":"JOHN CLAY",
    "wof:placetype":"venue"
},
  "geometry": {"coordinates":[-2.925259,53.401707],"type":"Point"}
}