{
  "type": "Feature",
  "properties": {
    "iso:country":"GB",
    "sg:address":"Regent House, 291 Kirkdale, Sydenham",
    "sg:city":"London",
    "sg:classifiers":[
        {
            "category":"Professional",
            "subcategory":"Detective & Security Services",
            "type":"Services"
        }
    ],
    "sg:phone":"+44 20 8778 7807",
    "sg:postcode":"SE26 4QD",
    "sg:province":"Greater London",
    "sg:tags":[
        "equipment"
    ],
    "wof:name":"Home Security Services",
    "wof:placetype":"venue"
},
  "geometry": {"coordinates":[-0.0563700013,51.4277153015],"type":"Point"}
}