{
  "type": "Feature",
  "properties": {
    "iso:country":"GB",
    "sg:address":"6 Queensgate",
    "sg:city":"Inverness",
    "sg:classifiers":[
        {
            "category":"Real Estate",
            "subcategory":"Surveying",
            "type":"Services"
        }
    ],
    "sg:phone":"+44 1463 713666",
    "sg:postcode":"IV1 1DA",
    "sg:province":"Highland",
    "sg:tags":[
        "surveyor",
        "valuer"
    ],
    "wof:name":"J & E SHEPHERD",
    "wof:placetype":"venue"
},
  "geometry": {"coordinates":[-4.225673,57.479614],"type":"Point"}
}