{
  "type": "Feature",
  "properties": {
    "iso:country":"GB",
    "sg:address":"18 Alexandra Rd",
    "sg:city":"Watford",
    "sg:classifiers":[
        {
            "category":"Social Services",
            "subcategory":"Retirement Home",
            "type":"Services"
        }
    ],
    "sg:phone":"+44 1923 228211",
    "sg:postcode":"WD17 4QY",
    "sg:province":"Hertfordshire",
    "sg:tags":[
        "rest"
    ],
    "wof:name":"B & M Residential Care Ltd",
    "wof:placetype":"venue"
},
  "geometry": {"coordinates":[-0.404271,51.663567],"type":"Point"}
}