{
  "type": "Feature",
  "properties": {
    "addr:full":"195c Desborough Avenue High Wycombe Buckinghamshire HP11 2TW",
    "addr:housenumber":"195c",
    "addr:postcode":"hp11 2tw",
    "addr:street":"Desborough Avenue",
    "iso:country":"GB",
    "sg:address":"195c Desborough Avenue",
    "sg:city":"High Wycombe",
    "sg:classifiers":[
        {
            "category":"Shopping",
            "subcategory":"Computers & Home Electronics",
            "type":"Retail Goods"
        }
    ],
    "sg:phone":"+44 1494 447446",
    "sg:postcode":"HP11 2TW",
    "sg:province":"Buckinghamshire",
    "sg:tags":[
        "hi-fi",
        "equipment",
        "mnfr"
    ],
    "wof:name":"TDL Electronics",
    "wof:placetype":"venue"
},
  "geometry": {"coordinates":[-0.7650060058,51.6257591248],"type":"Point"}
}