{
  "type": "Feature",
  "properties": {
    "addr:full":"1st Floor 33 Constitution Hill, Hockley Birmingham West Midlands B19 3LE",
    "addr:housenumber":"33",
    "addr:postcode":"b19 3le",
    "addr:street":"Constitution Hill Hockley",
    "iso:country":"GB",
    "sg:address":"1st Floor 33 Constitution Hill, Hockley",
    "sg:city":"Birmingham",
    "sg:classifiers":[
        {
            "category":"Manufacturing",
            "subcategory":"Textiles",
            "type":"Manufacturing & Wholesale Goods"
        }
    ],
    "sg:postcode":"B19 3LE",
    "sg:province":"West Midlands",
    "sg:tags":[
        "knitwear"
    ],
    "wof:name":"Newco Imports (Uk) Ltd",
    "wof:placetype":"venue"
},
  "geometry": {"coordinates":[-1.9025290012,52.4871330261],"type":"Point"}
}