{
  "type": "Feature",
  "properties": {
    "addr:full":"Leegate House, Burnt Ash Road London Greater London SE12 8RG",
    "addr:postcode":"se12 8rg",
    "addr:street":"Leegate;Burnt Ash Road",
    "iso:country":"GB",
    "sg:address":"Leegate House, Burnt Ash Road",
    "sg:city":"London",
    "sg:classifiers":[
        {
            "category":"Health Services",
            "subcategory":"Clinic",
            "type":"Services"
        },
        {
            "category":"Government",
            "subcategory":"Office",
            "type":"Public Place"
        }
    ],
    "sg:phone":"+44 20 8297 0707",
    "sg:postcode":"SE12 8RG",
    "sg:province":"Greater London",
    "sg:tags":[
        "nh",
        "local"
    ],
    "wof:name":"Lewisham & Guys Mental Health Nhs Trust",
    "wof:placetype":"venue"
},
  "geometry": {"coordinates":[0.01165,51.455799],"type":"Point"}
}