{
  "type": "Feature",
  "properties": {
    "iso:country":"GB",
    "sg:address":"1 Sowell Street",
    "sg:city":"Broadstairs",
    "sg:classifiers":[
        {
            "category":"Shopping",
            "subcategory":"Discount & Variety Stores",
            "type":"Retail Goods"
        }
    ],
    "sg:phone":"+44 1843 864087",
    "sg:postcode":"CT10 2AT",
    "sg:province":"Kent",
    "sg:tags":[
        "cleaning",
        "supply"
    ],
    "wof:name":"Total Supplies",
    "wof:placetype":"venue"
},
  "geometry": {"coordinates":[1.427974,51.362972],"type":"Point"}
}