{
  "type": "Feature",
  "properties": {
    "iso:country":"GB",
    "sg:address":"129 Chesterton Road",
    "sg:city":"Cambridge",
    "sg:classifiers":[
        {
            "category":"Bars & Pubs",
            "type":"Food & Drink"
        }
    ],
    "sg:phone":"+44 1223 357268",
    "sg:postcode":"CB4 3BA",
    "sg:province":"Cambridgeshire",
    "sg:tags":[
        "pubs",
        "inn"
    ],
    "wof:name":"The Portland Arms",
    "wof:placetype":"venue"
},
  "geometry": {"coordinates":[0.124859,52.21431],"type":"Point"}
}