{
  "type": "Feature",
  "properties": {
    "addr:full":"1 Trowbridge Retail Park, 235 Bradley Road Trowbridge Wiltshire BA14 0RQ",
    "addr:housenumber":"1;235",
    "addr:postcode":"ba14 0rq",
    "addr:street":"Trowbridge Retail Park;Bradley Road",
    "iso:country":"GB",
    "sg:address":"1 Trowbridge Retail Park, 235 Bradley Road",
    "sg:city":"Trowbridge",
    "sg:classifiers":[
        {
            "category":"Home & Garden",
            "subcategory":"Furniture",
            "type":"Retail Goods"
        }
    ],
    "sg:phone":"+44 1225 775454",
    "sg:postcode":"BA14 0RQ",
    "sg:province":"Wiltshire",
    "wof:name":"Sharps Bedrooms",
    "wof:placetype":"venue"
},
  "geometry": {"coordinates":[-2.208374,51.315342],"type":"Point"}
}