{
  "type": "Feature",
  "properties": {
    "addr:full":"Unit 1 490 Calder St Glasgow Glasgow City G42 0QD",
    "addr:housenumber":"unit 1",
    "addr:postcode":"490;g42 0qd",
    "addr:street":"Calder St",
    "iso:country":"GB",
    "sg:address":"Unit 1 490 Calder St",
    "sg:city":"Glasgow",
    "sg:classifiers":[
        {
            "category":"Building & Trades",
            "subcategory":"Construction",
            "type":"Services"
        }
    ],
    "sg:phone":"+44 1355 245977",
    "sg:postcode":"G42 0QD",
    "sg:province":"Glasgow City",
    "sg:tags":[
        "builder"
    ],
    "wof:name":"S D M Building Contractors",
    "wof:placetype":"venue"
},
  "geometry": {"coordinates":[-4.2485442162,55.8355140686],"type":"Point"}
}