{
  "type": "Feature",
  "properties": {
    "iso:country":"GB",
    "sg:address":"80 Forest Road",
    "sg:city":"Torquay",
    "sg:classifiers":[
        {
            "category":"Professional",
            "subcategory":"Advertising",
            "type":"Services"
        },
        {
            "category":"Manufacturing",
            "subcategory":"Signs",
            "type":"Manufacturing & Wholesale Goods"
        }
    ],
    "sg:phone":"+44 1803 329898",
    "sg:postcode":"TQ1 4JS",
    "sg:province":"Devon",
    "sg:tags":[
        "writer",
        "signwriters"
    ],
    "wof:name":"Sign Art & Display",
    "wof:placetype":"venue"
},
  "geometry": {"coordinates":[-3.533282,50.476379],"type":"Point"}
}