{
  "type": "Feature",
  "properties": {
    "addr:full":"Church Lane, Thornton Dale Pickering North Yorkshire YO18 7QL",
    "addr:postcode":"yo18 7ql",
    "addr:street":"Church Lane;Dale",
    "iso:country":"GB",
    "sg:address":"Church Lane, Thornton Dale",
    "sg:city":"Pickering",
    "sg:classifiers":[
        {
            "category":"Military Area",
            "subcategory":"Air Force Base",
            "type":"Public Place"
        }
    ],
    "sg:postcode":"YO18 7QL",
    "sg:province":"North Yorkshire",
    "sg:tags":[
        "taxi",
        "hire",
        "private"
    ],
    "wof:name":"Geoffrey Chaplin",
    "wof:placetype":"venue"
},
  "geometry": {"coordinates":[-0.7793880105,54.245010376],"type":"Point"}
}