{
  "type": "Feature",
  "properties": {
    "iso:country":"GB",
    "sg:address":"96 Windsor Road, Neath",
    "sg:city":"Swansea",
    "sg:classifiers":[
        {
            "category":"Shopping",
            "subcategory":"Computers & Home Electronics",
            "type":"Retail Goods"
        }
    ],
    "sg:phone":"+44 1639 632374",
    "sg:postcode":"SA11 1NR",
    "sg:province":"Neath Port Talbot",
    "sg:tags":[
        "equipment",
        "radio"
    ],
    "wof:name":"Transworld Communication",
    "wof:placetype":"venue"
},
  "geometry": {"coordinates":[-3.806091,51.658432],"type":"Point"}
}