{
  "type": "Feature",
  "properties": {
    "iso:country":"GB",
    "sg:address":"74 Laneside Road, New Mills",
    "sg:city":"High Peak",
    "sg:classifiers":[
        {
            "category":"Manufacturing",
            "subcategory":"Wood Products",
            "type":"Manufacturing & Wholesale Goods"
        },
        {
            "category":"Shopping",
            "subcategory":"Computers & Home Electronics",
            "type":"Retail Goods"
        }
    ],
    "sg:postcode":"SK22 4LX",
    "sg:province":"Cheshire",
    "sg:tags":[
        "packaging",
        "equipment",
        "crate",
        "pallets",
        "audio-visual"
    ],
    "wof:name":"Lilytone Ltd.",
    "wof:placetype":"venue"
},
  "geometry": {"coordinates":[-1.986622,53.365585],"type":"Point"}
}