{
  "type": "Feature",
  "properties": {
    "addr:full":"76 Aldwick Road Bognor Regis West Sussex PO21 2PE",
    "addr:housenumber":"76",
    "addr:postcode":"po21 2pe",
    "addr:street":"Aldwick Road",
    "iso:country":"GB",
    "sg:address":"76 Aldwick Road",
    "sg:city":"Bognor Regis",
    "sg:classifiers":[
        {
            "category":"Professional",
            "subcategory":"Accounting & Tax Preparation",
            "type":"Services"
        }
    ],
    "sg:phone":"+44 1243 862400",
    "sg:postcode":"PO21 2PE",
    "sg:province":"West Sussex",
    "sg:tags":[
        "accountant",
        "activity"
    ],
    "wof:name":"Stuart Bromley & Co",
    "wof:placetype":"venue"
},
  "geometry": {"coordinates":[-0.6869429946,50.7816085815],"type":"Point"}
}