{
  "type": "Feature",
  "properties": {
    "addr:full":"Church Street Mexborough South Yorkshire S64 0HA",
    "addr:postcode":"s64 0ha",
    "addr:street":"Church Street",
    "iso:country":"GB",
    "sg:address":"Church Street",
    "sg:city":"Mexborough",
    "sg:classifiers":[
        {
            "category":"Real Estate",
            "subcategory":"Real Estate Agent",
            "type":"Services"
        }
    ],
    "sg:phone":"+44 1709 590121",
    "sg:postcode":"S64 0HA",
    "sg:province":"South Yorkshire",
    "wof:name":"Mexborough Park Homes",
    "wof:placetype":"venue"
},
  "geometry": {"coordinates":[-1.275029,53.492592],"type":"Point"}
}