{
  "type": "Feature",
  "properties": {
    "iso:country":"GB",
    "sg:address":"Greenwood Close",
    "sg:city":"Birmingham",
    "sg:classifiers":[
        {
            "category":"Education",
            "subcategory":"School",
            "type":"Public Place"
        },
        {
            "category":"Government",
            "subcategory":"Office",
            "type":"Public Place"
        }
    ],
    "sg:phone":"+44 121 444 5203",
    "sg:postcode":"B14 6ET",
    "sg:province":"West Midlands",
    "sg:tags":[
        "local",
        "authority"
    ],
    "wof:name":"Woodthorpe Junior & Infant School",
    "wof:placetype":"venue"
},
  "geometry": {"coordinates":[-1.896839,52.41914],"type":"Point"}
}