{
  "type": "Feature",
  "properties": {
    "iso:country":"GB",
    "sg:address":"Unit 32, Marlands Shopping Centre, Civic Centre Rd",
    "sg:city":"Southampton",
    "sg:classifiers":[
        {
            "category":"Shopping",
            "subcategory":"Clothing, Apparel, & Fashions",
            "type":"Retail Goods"
        }
    ],
    "sg:phone":"+44 23 8023 1821",
    "sg:postcode":"SO14 7SJ",
    "sg:province":"Hampshire",
    "sg:tags":[
        "shop"
    ],
    "wof:name":"Benetton",
    "wof:placetype":"venue"
},
  "geometry": {"coordinates":[-1.4058899879,50.9058418274],"type":"Point"}
}