{
  "type": "Feature",
  "properties": {
    "addr:full":"154c High St, Bloxwich Walsall Staffordshire WS3 3JT",
    "addr:housenumber":"154c",
    "addr:postcode":"ws3 3jt",
    "addr:street":"High St",
    "iso:country":"GB",
    "sg:address":"154c High St, Bloxwich",
    "sg:city":"Walsall",
    "sg:classifiers":[
        {
            "category":"Professional",
            "subcategory":"Employment Agencies",
            "type":"Services"
        }
    ],
    "sg:postcode":"WS3 3JT",
    "sg:province":"Staffordshire",
    "sg:tags":[
        "consultant"
    ],
    "wof:name":"Hatton,Lynda,",
    "wof:placetype":"venue"
},
  "geometry": {"coordinates":[-2.0042209625,52.6146011353],"type":"Point"}
}