{
  "type": "Feature",
  "properties": {
    "iso:country":"GB",
    "sg:address":"28 Trafalgar Street, Southbank",
    "sg:city":"York",
    "sg:classifiers":[
        {
            "category":"Retail",
            "subcategory":"Repair Shop",
            "type":"Services"
        }
    ],
    "sg:phone":"+44 1904 670174",
    "sg:postcode":"YO23 1HZ",
    "sg:province":"North Yorkshire",
    "sg:tags":[
        "upholsterer"
    ],
    "wof:name":"Camerons Re-Upholstery Work Shop",
    "wof:placetype":"venue"
},
  "geometry": {"coordinates":[-1.0884530544,53.945274353],"type":"Point"}
}