{
  "type": "Feature",
  "properties": {
    "addr:full":"Crossroads School Banchory Aberdeen City AB31 6BX",
    "addr:postcode":"ab31 6bx",
    "addr:street":"Banchory Aberdeen",
    "iso:country":"GB",
    "sg:address":"Crossroads School",
    "sg:city":"Banchory",
    "sg:classifiers":[
        {
            "category":"Government",
            "subcategory":"Office",
            "type":"Public Place"
        }
    ],
    "sg:phone":"+44 1330 844685",
    "sg:postcode":"AB31 6BX",
    "sg:province":"Aberdeen City",
    "sg:tags":[
        "local"
    ],
    "wof:name":"Aberdeenshire Council",
    "wof:placetype":"venue"
},
  "geometry": {"coordinates":[-2.498155,57.03347],"type":"Point"}
}