{
  "type": "Feature",
  "properties": {
    "iso:country":"GB",
    "sg:address":"Trinity House, Summer Place",
    "sg:city":"Manchester",
    "sg:classifiers":[
        {
            "category":"Government",
            "subcategory":"Office",
            "type":"Public Place"
        }
    ],
    "sg:postcode":"M14 5AA",
    "sg:province":"Greater Manchester",
    "sg:tags":[
        "local"
    ],
    "wof:name":"Childminding Support Project",
    "wof:placetype":"venue"
},
  "geometry": {"coordinates":[-2.225499,53.451164],"type":"Point"}
}