{
  "type": "Feature",
  "properties": {
    "iso:country":"GB",
    "sg:address":"15 Middleton Park Circus",
    "sg:city":"Leeds",
    "sg:classifiers":[
        {
            "category":"Shopping",
            "subcategory":"Pharmacy",
            "type":"Retail Goods"
        }
    ],
    "sg:postcode":"LS10 4LX",
    "sg:province":"West Yorkshire",
    "sg:tags":[
        "toiletry"
    ],
    "wof:name":"Dash's Toiletries",
    "wof:placetype":"venue"
},
  "geometry": {"coordinates":[-1.547576,53.746834],"type":"Point"}
}