{
  "type": "Feature",
  "properties": {
    "addr:full":"41 Victoria Street Kirkwall Orkney Islands KW15 1DN",
    "addr:housenumber":"41",
    "addr:postcode":"kw15 1dn",
    "addr:street":"Victoria Street",
    "iso:country":"GB",
    "sg:address":"41 Victoria Street",
    "sg:city":"Kirkwall",
    "sg:classifiers":[
        {
            "category":"Shopping",
            "subcategory":"Florist",
            "type":"Retail Goods"
        }
    ],
    "sg:postcode":"KW15 1DN",
    "sg:province":"Orkney Islands",
    "wof:name":"Fine Design",
    "wof:placetype":"venue"
},
  "geometry": {"coordinates":[-2.96169,58.98016],"type":"Point"}
}