{
  "type": "Feature",
  "properties": {
    "addr:full":"Unit 3 Business Station, Newport Road Middlesbrough North Yorkshire TS1 1LL",
    "addr:housenumber":"unit 3 business",
    "addr:postcode":"ts1 1ll",
    "addr:street":"Newport Road",
    "iso:country":"GB",
    "sg:address":"Unit 3 Business Station, Newport Road",
    "sg:city":"Middlesbrough",
    "sg:classifiers":[
        {
            "category":"Shopping",
            "subcategory":"News",
            "type":"Retail Goods"
        }
    ],
    "sg:phone":"+44 1642 225673",
    "sg:postcode":"TS1 1LL",
    "sg:province":"North Yorkshire",
    "sg:tags":[
        "newsagent"
    ],
    "wof:name":"Travel Point News",
    "wof:placetype":"venue"
},
  "geometry": {"coordinates":[-1.236569047,54.572971344],"type":"Point"}
}