{
  "type": "Feature",
  "properties": {
    "iso:country":"GB",
    "sg:address":"By-pass Road",
    "sg:city":"Bridgend",
    "sg:classifiers":[
        {
            "category":"Autos & Motor Vehicles",
            "subcategory":"Fuel & Gas Station",
            "type":"Retail Goods"
        }
    ],
    "sg:phone":"+44 1656 660066",
    "sg:postcode":"CF31 3LJ",
    "sg:province":"Bridgend",
    "sg:tags":[
        "petrol",
        "filling"
    ],
    "wof:name":"Waterton Filling Station",
    "wof:placetype":"venue"
},
  "geometry": {"coordinates":[-3.5915369987,51.495388031],"type":"Point"}
}