{
  "type": "Feature",
  "properties": {
    "addr:full":"Norden Farm, Norden, Corfe Castle Wareham Dorset BH20 5DS",
    "addr:postcode":"bh20 5ds",
    "addr:street":"Norden",
    "iso:country":"GB",
    "sg:address":"Norden Farm, Norden, Corfe Castle",
    "sg:city":"Wareham",
    "sg:classifiers":[
        {
            "category":"Food & Beverages",
            "subcategory":"Farmers Market",
            "type":"Retail Goods"
        }
    ],
    "sg:phone":"+44 1929 480098",
    "sg:postcode":"BH20 5DS",
    "sg:province":"Dorset",
    "sg:tags":[
        "farm",
        "shop",
        "pyo"
    ],
    "wof:name":"Norden Farm Shop",
    "wof:placetype":"venue"
},
  "geometry": {"coordinates":[-2.0535941124,50.6338386536],"type":"Point"}
}