{
  "type": "Feature",
  "properties": {
    "iso:country":"GB",
    "sg:address":"258 Nottingham Road",
    "sg:city":"Mansfield",
    "sg:classifiers":[
        {
            "category":"Travel",
            "subcategory":"Travel Agent",
            "type":"Entertainment"
        }
    ],
    "sg:phone":"+44 1623 649376",
    "sg:postcode":"NG18 4SH",
    "sg:province":"Nottinghamshire",
    "wof:name":"Holiday Villas Uk (florida)",
    "wof:placetype":"venue"
},
  "geometry": {"coordinates":[-1.193568,53.128414],"type":"Point"}
}