{
  "type": "Feature",
  "properties": {
    "addr:full":"155 Belgrave Rd Stoke On Trent Staffordshire ST3 4NL",
    "addr:housenumber":"155",
    "addr:postcode":"st3 4nl",
    "addr:street":"Belgrave Rd",
    "iso:country":"GB",
    "sg:address":"155 Belgrave Rd",
    "sg:city":"Stoke On Trent",
    "sg:classifiers":[
        {
            "category":"Building & Trades",
            "subcategory":"Landscaping Services",
            "type":"Services"
        }
    ],
    "sg:phone":"+44 1782 323567",
    "sg:postcode":"ST3 4NL",
    "sg:province":"Staffordshire",
    "sg:tags":[
        "gardening"
    ],
    "wof:name":"Brian Burton",
    "wof:placetype":"venue"
},
  "geometry": {"coordinates":[-2.129953,52.97842],"type":"Point"}
}