{
  "type": "Feature",
  "properties": {
    "addr:full":"14 Willow Drive, Hutton Weston-super-mare Somerset BS24 9TJ",
    "addr:housenumber":"14",
    "addr:postcode":"bs24 9tj",
    "addr:street":"Willow Drive Hutton",
    "iso:country":"GB",
    "sg:address":"14 Willow Drive, Hutton",
    "sg:city":"Weston-super-mare",
    "sg:classifiers":[
        {
            "category":"Retail",
            "subcategory":"Driving School",
            "type":"Services"
        }
    ],
    "sg:phone":"+44 1934 811311",
    "sg:postcode":"BS24 9TJ",
    "sg:province":"Somerset",
    "wof:name":"Eagle School of Motoring",
    "wof:placetype":"venue"
},
  "geometry": {"coordinates":[-2.9292891026,51.3263092041],"type":"Point"}
}