{
  "type": "Feature",
  "properties": {
    "iso:country":"GB",
    "sg:address":"Drum Lane, Haseley Knob",
    "sg:city":"Warwick",
    "sg:classifiers":[
        {
            "category":"Travel",
            "subcategory":"Hotels & Motels",
            "type":"Entertainment"
        }
    ],
    "sg:phone":"+44 1926 484447",
    "sg:postcode":"CV35 7NL",
    "sg:province":"Warwickshire",
    "sg:tags":[
        "house",
        "guest"
    ],
    "wof:name":"The Croft Guest House",
    "wof:placetype":"venue"
},
  "geometry": {"coordinates":[-1.659011,52.336159],"type":"Point"}
}