{
  "type": "Feature",
  "properties": {
    "iso:country":"GB",
    "sg:address":"Colebrook Industrial Estate, Longfield Road",
    "sg:city":"Tunbridge Wells",
    "sg:classifiers":[
        {
            "category":"Building & Trades",
            "subcategory":"Construction",
            "type":"Services"
        }
    ],
    "sg:phone":"+44 1892 862888",
    "sg:postcode":"TN2 3DG",
    "sg:province":"East Sussex",
    "sg:tags":[
        "concrete"
    ],
    "wof:name":"Factory Improvement Supplies",
    "wof:placetype":"venue"
},
  "geometry": {"coordinates":[0.291687,51.155922],"type":"Point"}
}