{
  "type": "Feature",
  "properties": {
    "iso:country":"GB",
    "sg:address":"Unit 2 5 Auchinairn Road, Bishopbriggs",
    "sg:city":"Glasgow",
    "sg:classifiers":[
        {
            "category":"Building & Trades",
            "subcategory":"Construction",
            "type":"Services"
        }
    ],
    "sg:phone":"+44 141 772 2852",
    "sg:postcode":"G64 1RX",
    "sg:province":"East Dunbartonshire",
    "sg:tags":[
        "ceiling",
        "contractor"
    ],
    "wof:name":"Quality Ceilings",
    "wof:placetype":"venue"
},
  "geometry": {"coordinates":[-4.227973,55.896786],"type":"Point"}
}