{
  "type": "Feature",
  "properties": {
    "addr:full":"29 High Street Stratford-upon-avon Warwickshire CV37 6AU",
    "addr:housenumber":"29",
    "addr:postcode":"cv37 6au",
    "addr:street":"High Street",
    "iso:country":"GB",
    "sg:address":"29 High Street",
    "sg:city":"Stratford-upon-avon",
    "sg:classifiers":[
        {
            "category":"Food & Beverages",
            "subcategory":"Specialty",
            "type":"Retail Goods"
        }
    ],
    "sg:phone":"+44 1789 721830",
    "sg:postcode":"CV37 6AU",
    "sg:province":"Warwickshire",
    "sg:tags":[
        "retailer",
        "product",
        "health"
    ],
    "wof:name":"Forever Living Products (U.K.) Ltd",
    "wof:placetype":"venue"
},
  "geometry": {"coordinates":[-1.706987977,52.1920013428],"type":"Point"}
}