{
  "type": "Feature",
  "properties": {
    "addr:full":"16 Market Street, Longton Stoke-on-trent Staffordshire ST3 1BX",
    "addr:housenumber":"16",
    "addr:postcode":"staffordshire st3 1bx",
    "addr:street":"Market Street",
    "iso:country":"GB",
    "sg:address":"16 Market Street, Longton",
    "sg:city":"Stoke-on-trent",
    "sg:classifiers":[
        {
            "category":"Professional",
            "subcategory":"Lawyer & Legal Services",
            "type":"Services"
        }
    ],
    "sg:phone":"+44 1782 333462",
    "sg:postcode":"ST3 1BX",
    "sg:province":"Staffordshire",
    "sg:tags":[
        "solicitor"
    ],
    "wof:name":"Leslie Dodd & Co.",
    "wof:placetype":"venue"
},
  "geometry": {"coordinates":[-2.1349470615,52.9890594482],"type":"Point"}
}