{
  "type": "Feature",
  "properties": {
    "addr:full":"Field Terrace Jarrow Tyne and Wear NE32 5PR",
    "addr:postcode":"ne32 5pr",
    "addr:street":"Field Terrace",
    "iso:country":"GB",
    "sg:address":"Field Terrace",
    "sg:city":"Jarrow",
    "sg:classifiers":[
        {
            "category":"Education",
            "subcategory":"School",
            "type":"Public Place"
        },
        {
            "category":"Government",
            "subcategory":"Office",
            "type":"Public Place"
        }
    ],
    "sg:phone":"+44 191 489 3225",
    "sg:postcode":"NE32 5PR",
    "sg:province":"Tyne and Wear",
    "sg:tags":[
        "local",
        "authority"
    ],
    "wof:name":"Springfield Comprehensive School",
    "wof:placetype":"venue"
},
  "geometry": {"coordinates":[-1.489729,54.972809],"type":"Point"}
}