{
  "type": "Feature",
  "properties": {
    "iso:country":"GB",
    "sg:address":"M M Ho, Sebastopol Rd",
    "sg:city":"Aldershot",
    "sg:classifiers":[
        {
            "category":"Building & Trades",
            "subcategory":"Electrical",
            "type":"Services"
        }
    ],
    "sg:postcode":"GU11 1SG",
    "sg:province":"Hampshire",
    "sg:tags":[
        "lighting"
    ],
    "wof:name":"Lucifer Lighting",
    "wof:placetype":"venue"
},
  "geometry": {"coordinates":[-0.759639,51.249149],"type":"Point"}
}