{
  "type": "Feature",
  "properties": {
    "iso:country":"GB",
    "sg:address":"24 Mayfield Road",
    "sg:city":"Ryde",
    "sg:classifiers":[
        {
            "category":"Food & Beverages",
            "subcategory":"Groceries & Convenience Stores",
            "type":"Retail Goods"
        }
    ],
    "sg:postcode":"PO33 3PR",
    "sg:province":"Isle of Wight",
    "sg:tags":[
        "frozen",
        "ice"
    ],
    "wof:name":"Island Ice Supplies",
    "wof:placetype":"venue"
},
  "geometry": {"coordinates":[-1.1742119789,50.7262649536],"type":"Point"}
}