{
  "type": "Feature",
  "properties": {
    "addr:full":"8 Vernon St Blackburn Lancashire BB2 2AX",
    "addr:housenumber":"8",
    "addr:postcode":"bb2 2ax",
    "addr:street":"Vernon St",
    "iso:country":"GB",
    "sg:address":"8 Vernon St",
    "sg:city":"Blackburn",
    "sg:classifiers":[
        {
            "category":"Professional",
            "subcategory":"Accounting & Tax Preparation",
            "type":"Services"
        }
    ],
    "sg:postcode":"BB2 2AX",
    "sg:province":"Lancashire",
    "sg:tags":[
        "accountant"
    ],
    "wof:name":"Chopdat,Miayh,",
    "wof:placetype":"venue"
},
  "geometry": {"coordinates":[-2.4832980633,53.7452888489],"type":"Point"}
}