{
  "type": "Feature",
  "properties": {
    "addr:full":"259 Bellrock Street Glasgow Glasgow City G33 3LN",
    "addr:housenumber":"259",
    "addr:postcode":"g33 3ln",
    "addr:street":"Bellrock Street",
    "iso:country":"GB",
    "sg:address":"259 Bellrock Street",
    "sg:city":"Glasgow",
    "sg:classifiers":[
        {
            "category":"Place Of Worship",
            "type":"Public Place"
        },
        {
            "category":"Education",
            "subcategory":"School",
            "type":"Public Place"
        }
    ],
    "sg:phone":"+44 141 774 4152",
    "sg:postcode":"G33 3LN",
    "sg:province":"Glasgow City",
    "sg:tags":[
        "local",
        "authority"
    ],
    "wof:name":"ST MARIA GORETTI CATHOLIC CHURCH",
    "wof:placetype":"venue"
},
  "geometry": {"coordinates":[-4.159569,55.866009],"type":"Point"}
}