{
  "type": "Feature",
  "properties": {
    "iso:country":"GB",
    "sg:address":"Valley Garage, 83-75 Drayton Road",
    "sg:city":"Norwich",
    "sg:classifiers":[
        {
            "category":"Retail",
            "subcategory":"Auto Repair",
            "type":"Services"
        }
    ],
    "sg:postcode":"NR3 2DN",
    "sg:province":"Norfolk",
    "sg:tags":[
        "modification",
        "garage"
    ],
    "wof:name":"J C Body Repairs",
    "wof:placetype":"venue"
},
  "geometry": {"coordinates":[1.2823599577,52.6433982849],"type":"Point"}
}