{
  "type": "Feature",
  "properties": {
    "addr:full":"Woodside Way Glenrothes Fife KY7 5RA",
    "addr:postcode":"ky7 5ra",
    "addr:street":"Woodside Way",
    "iso:country":"GB",
    "sg:address":"Woodside Way",
    "sg:city":"Glenrothes",
    "sg:classifiers":[
        {
            "category":"Community Center",
            "type":"Public Place"
        },
        {
            "category":"Government",
            "subcategory":"Office",
            "type":"Public Place"
        }
    ],
    "sg:phone":"+44 1592 415678",
    "sg:postcode":"KY7 5RA",
    "sg:province":"Fife",
    "sg:tags":[
        "recreation",
        "local",
        "leisure",
        "centre"
    ],
    "wof:name":"Lomond Centre",
    "wof:placetype":"venue"
},
  "geometry": {"coordinates":[-3.1508541107,56.1928787231],"type":"Point"}
}