{
  "type": "Feature",
  "properties": {
    "iso:country":"GB",
    "sg:address":"25 Cranmer Road",
    "sg:city":"Croydon",
    "sg:classifiers":[
        {
            "category":"Communications",
            "type":"Services"
        }
    ],
    "sg:phone":"+44 20 8686 9713",
    "sg:postcode":"CR0 1SR",
    "sg:province":"Surrey",
    "sg:tags":[
        "audio-visual"
    ],
    "wof:name":"D Vince",
    "wof:placetype":"venue"
},
  "geometry": {"coordinates":[-0.104417,51.371246],"type":"Point"}
}