{
  "type": "Feature",
  "properties": {
    "iso:country":"GB",
    "sg:address":"Roman Ridge Road, Winkcobank",
    "sg:city":"Sheffield",
    "sg:classifiers":[
        {
            "category":"Retail",
            "subcategory":"Storage",
            "type":"Services"
        }
    ],
    "sg:phone":"+44 114 243 3156",
    "sg:postcode":"S9 1FF",
    "sg:province":"South Yorkshire",
    "sg:tags":[
        "cold"
    ],
    "wof:name":"Sheffield Cold Stores Ltd.",
    "wof:placetype":"venue"
},
  "geometry": {"coordinates":[-1.418702,53.417698],"type":"Point"}
}