{
  "type": "Feature",
  "properties": {
    "iso:country":"GB",
    "sg:address":"24 Colliergate",
    "sg:city":"York",
    "sg:classifiers":[
        {
            "category":"Home & Garden",
            "subcategory":"Hardware",
            "type":"Retail Goods"
        }
    ],
    "sg:phone":"+44 1904 625601",
    "sg:postcode":"YO1 8BW",
    "sg:province":"North Yorkshire",
    "sg:tags":[
        "merchant",
        "ironmonger"
    ],
    "sg:website":"http://www.barnitts.co.uk",
    "wof:name":"Barnitts Ltd",
    "wof:placetype":"venue"
},
  "geometry": {"coordinates":[-1.079345,53.959709],"type":"Point"}
}