{
  "type": "Feature",
  "properties": {
    "iso:country":"GB",
    "sg:address":"9 Lauder Pl",
    "sg:city":"East Linton",
    "sg:classifiers":[
        {
            "category":"Professional",
            "subcategory":"Computer Services",
            "type":"Services"
        }
    ],
    "sg:postcode":"EH40 3DB",
    "sg:province":"East Lothian",
    "sg:tags":[
        "consultant"
    ],
    "wof:name":"Capacity Planning Services Ltd",
    "wof:placetype":"venue"
},
  "geometry": {"coordinates":[-2.654134,55.983978],"type":"Point"}
}