{
  "type": "Feature",
  "properties": {
    "addr:full":"269a Bridge Court, High Street Waltham Cross Essex EN8 7AT",
    "addr:housenumber":"269a",
    "addr:postcode":"en8 7at",
    "addr:street":"Bridge Court High Street",
    "iso:country":"GB",
    "sg:address":"269a Bridge Court, High Street",
    "sg:city":"Waltham Cross",
    "sg:classifiers":[
        {
            "category":"Sports & Exercise",
            "subcategory":"Gym",
            "type":"Entertainment"
        }
    ],
    "sg:phone":"+44 1992 637736",
    "sg:postcode":"EN8 7AT",
    "sg:province":"Essex",
    "sg:tags":[
        "fitness",
        "health",
        "centre"
    ],
    "wof:name":"Body Fit Health & Fitness Club",
    "wof:placetype":"venue"
},
  "geometry": {"coordinates":[-0.033814,51.69051],"type":"Point"}
}