{
  "type": "Feature",
  "properties": {
    "iso:country":"GB",
    "sg:address":"Moston Lane, Moston",
    "sg:city":"Manchester",
    "sg:classifiers":[
        {
            "category":"Bars & Pubs",
            "type":"Food & Drink"
        }
    ],
    "sg:phone":"+44 161 203 7921",
    "sg:postcode":"M9 4HF",
    "sg:province":"Greater Manchester",
    "sg:tags":[
        "pubs",
        "inn"
    ],
    "wof:name":"Mowers Arms",
    "wof:placetype":"venue"
},
  "geometry": {"coordinates":[-2.2029869556,53.5138015747],"type":"Point"}
}