{
  "type": "Feature",
  "properties": {
    "addr:full":"26 High St, Cheadle Stoke On Trent Staffordshire ST10 1AF",
    "addr:housenumber":"26",
    "addr:postcode":"st10 1af",
    "addr:street":"High St Cheadle",
    "iso:country":"GB",
    "sg:address":"26 High St, Cheadle",
    "sg:city":"Stoke On Trent",
    "sg:classifiers":[
        {
            "category":"Shopping",
            "subcategory":"Thrift Store",
            "type":"Retail Goods"
        }
    ],
    "sg:phone":"+44 1538 267091",
    "sg:postcode":"ST10 1AF",
    "sg:province":"Staffordshire",
    "sg:tags":[
        "shop",
        "charity"
    ],
    "wof:name":"Douglas Macmillan Hospice Shop",
    "wof:placetype":"venue"
},
  "geometry": {"coordinates":[-1.988748,52.987858],"type":"Point"}
}