{
  "type": "Feature",
  "properties": {
    "addr:full":"41 North Street Martock Somerset TA12 6DH",
    "addr:housenumber":"41",
    "addr:postcode":"ta12 6dh",
    "addr:street":"North Street",
    "iso:country":"GB",
    "sg:address":"41 North Street",
    "sg:city":"Martock",
    "sg:classifiers":[
        {
            "category":"Shopping",
            "subcategory":"Florist",
            "type":"Retail Goods"
        }
    ],
    "sg:postcode":"TA12 6DH",
    "sg:province":"Somerset",
    "wof:name":"Flower Loft",
    "wof:placetype":"venue"
},
  "geometry": {"coordinates":[-2.7665719986,50.9731369019],"type":"Point"}
}