{
  "type": "Feature",
  "properties": {
    "addr:full":"104 Barloch St Glasgow Glasgow City G22 5BY",
    "addr:housenumber":"104",
    "addr:postcode":"g22 5by",
    "addr:street":"Barloch St",
    "iso:country":"GB",
    "sg:address":"104 Barloch St",
    "sg:city":"Glasgow",
    "sg:classifiers":[
        {
            "category":"Government",
            "subcategory":"Police Station",
            "type":"Public Place"
        }
    ],
    "sg:phone":"+44 141 532 3900",
    "sg:postcode":"G22 5BY",
    "sg:province":"Glasgow City",
    "sg:tags":[
        "support",
        "force"
    ],
    "wof:name":"Police",
    "wof:placetype":"venue"
},
  "geometry": {"coordinates":[-4.2530889511,55.8843002319],"type":"Point"}
}