{
  "type": "Feature",
  "properties": {
    "iso:country":"GB",
    "sg:address":"23 Gaol Lane",
    "sg:city":"Sudbury",
    "sg:classifiers":[
        {
            "category":"Shopping",
            "subcategory":"Hobbies, Toys, & Games",
            "type":"Retail Goods"
        }
    ],
    "sg:phone":"+44 1787 372238",
    "sg:postcode":"CO10 1JL",
    "sg:province":"Essex",
    "sg:tags":[
        "shop",
        "toy"
    ],
    "wof:name":"Toymaster Kingdom",
    "wof:placetype":"venue"
},
  "geometry": {"coordinates":[0.730152,52.039272],"type":"Point"}
}