{
  "type": "Feature",
  "properties": {
    "addr:full":"Prospect House, 143 Birmingham Road Lichfield Staffordshire WS14 9BJ",
    "addr:housenumber":"143",
    "addr:postcode":"ws14 9bj",
    "addr:street":"Birmingham Road",
    "iso:country":"GB",
    "sg:address":"Prospect House, 143 Birmingham Road",
    "sg:city":"Lichfield",
    "sg:classifiers":[
        {
            "category":"Professional",
            "subcategory":"Employment Agencies",
            "type":"Services"
        }
    ],
    "sg:phone":"+44 1543 415500",
    "sg:postcode":"WS14 9BJ",
    "sg:province":"Staffordshire",
    "sg:tags":[
        "consultant"
    ],
    "wof:name":"Personnel (Midlands)",
    "wof:placetype":"venue"
},
  "geometry": {"coordinates":[-1.8312200308,52.6735954285],"type":"Point"}
}