{
  "type": "Feature",
  "properties": {
    "addr:full":"Main Street, Sutton On Derwent York East Riding of Yorkshire YO41 4BT",
    "addr:postcode":"yo41 4bt",
    "addr:street":"Main Street",
    "iso:country":"GB",
    "sg:address":"Main Street, Sutton On Derwent",
    "sg:city":"York",
    "sg:classifiers":[
        {
            "category":"Bars & Pubs",
            "type":"Food & Drink"
        }
    ],
    "sg:phone":"+44 1904 608477",
    "sg:postcode":"YO41 4BT",
    "sg:province":"East Riding of Yorkshire",
    "sg:tags":[
        "pubs",
        "inn"
    ],
    "wof:name":"The Sutton Arms",
    "wof:placetype":"venue"
},
  "geometry": {"coordinates":[-0.9350190163,53.9203796387],"type":"Point"}
}