{
  "type": "Feature",
  "properties": {
    "iso:country":"GB",
    "sg:address":"8 Fane Road",
    "sg:city":"Peterborough",
    "sg:classifiers":[
        {
            "category":"Building & Trades",
            "subcategory":"Plumbing",
            "type":"Services"
        }
    ],
    "sg:postcode":"PE4 6ED",
    "sg:province":"Cambridgeshire",
    "sg:tags":[
        "heating"
    ],
    "wof:name":"Brent,Bob,",
    "wof:placetype":"venue"
},
  "geometry": {"coordinates":[-0.258378,52.60117],"type":"Point"}
}