{
  "type": "Feature",
  "properties": {
    "addr:full":"Lessarna House, Lessarna Court Bradford West Yorkshire BD4 8ST",
    "addr:postcode":"bd4 8st",
    "addr:street":"Lessarna Court",
    "iso:country":"GB",
    "sg:address":"Lessarna House, Lessarna Court",
    "sg:city":"Bradford",
    "sg:classifiers":[
        {
            "category":"Professional",
            "type":"Services"
        }
    ],
    "sg:phone":"+44 1274 724108",
    "sg:postcode":"BD4 8ST",
    "sg:province":"West Yorkshire",
    "sg:tags":[
        "shopfitters"
    ],
    "wof:name":"Euroshopfitters (U K) Ltd.",
    "wof:placetype":"venue"
},
  "geometry": {"coordinates":[-1.7268899679,53.7856216431],"type":"Point"}
}