{
  "type": "Feature",
  "properties": {
    "iso:country":"GB",
    "sg:address":"Central Office, Tennant Hall, Blenheim Gro",
    "sg:city":"Leeds",
    "sg:classifiers":[
        {
            "category":"Health Services",
            "subcategory":"Nursing And Care Facility",
            "type":"Services"
        }
    ],
    "sg:phone":"+44 113 294 2000",
    "sg:postcode":"LS2 9ET",
    "sg:province":"West Yorkshire",
    "sg:tags":[
        "home"
    ],
    "wof:name":"Leeds Federated Housing Association",
    "wof:placetype":"venue"
},
  "geometry": {"coordinates":[-1.54626,53.807739],"type":"Point"}
}