{
  "type": "Feature",
  "properties": {
    "iso:country":"GB",
    "sg:address":"The Printing Wks, Park Row",
    "sg:city":"Selby",
    "sg:classifiers":[
        {
            "category":"Professional",
            "subcategory":"Printing & Photocopies",
            "type":"Services"
        }
    ],
    "sg:postcode":"YO8 4PR",
    "sg:province":"East Riding of Yorkshire",
    "sg:tags":[
        "process",
        "screen",
        "printer"
    ],
    "wof:name":"Watson,R N,",
    "wof:placetype":"venue"
},
  "geometry": {"coordinates":[-1.070346,53.783909],"type":"Point"}
}