{
  "type": "Feature",
  "properties": {
    "iso:country":"GB",
    "sg:address":"Dt House, 14 Copsterhill Road",
    "sg:city":"Oldham",
    "sg:classifiers":[
        {
            "category":"Travel",
            "subcategory":"Travel Agent",
            "type":"Entertainment"
        }
    ],
    "sg:phone":"+44 161 627 0099",
    "sg:postcode":"OL8 1QB",
    "sg:province":"Lancashire",
    "wof:name":"The Air Line",
    "wof:placetype":"venue"
},
  "geometry": {"coordinates":[-2.1145451069,53.5318260193],"type":"Point"}
}