{
  "type": "Feature",
  "properties": {
    "addr:full":"447 Alexandra Parade, Unit 2 Glasgow Glasgow City G31 3AD",
    "addr:housenumber":"447",
    "addr:postcode":"g31 3ad",
    "addr:street":"Alexandra Parade Unit",
    "iso:country":"GB",
    "sg:address":"447 Alexandra Parade, Unit 2",
    "sg:city":"Glasgow",
    "sg:classifiers":[
        {
            "category":"Community Center",
            "subcategory":"Social",
            "type":"Public Place"
        }
    ],
    "sg:phone":"+44 141 554 5455",
    "sg:postcode":"G31 3AD",
    "sg:province":"Glasgow City",
    "sg:tags":[
        "frozen",
        "food",
        "freezer",
        "centre"
    ],
    "wof:name":"Iceland Foods Plc",
    "wof:placetype":"venue"
},
  "geometry": {"coordinates":[-4.2201547623,55.8642272949],"type":"Point"}
}