{
  "type": "Feature",
  "properties": {
    "iso:country":"GB",
    "sg:address":"5 Macgregor Court",
    "sg:city":"Oban",
    "sg:classifiers":[
        {
            "category":"Autos & Motor Vehicles",
            "subcategory":"Auto Supplies",
            "type":"Retail Goods"
        }
    ],
    "sg:phone":"+44 1631 564608",
    "sg:postcode":"PA34 4DJ",
    "sg:province":"Argyll and Bute",
    "sg:tags":[
        "component",
        "factor"
    ],
    "wof:name":"B & H Auto Spares Oban Ltd",
    "wof:placetype":"venue"
},
  "geometry": {"coordinates":[-5.508568,56.356796],"type":"Point"}
}