{
  "type": "Feature",
  "properties": {
    "addr:full":"The Kiosk, Saddlers Centre, Park Street Walsall West Midlands WS1 1LY",
    "addr:postcode":"ws1 1ly",
    "addr:street":"Centre Park Street",
    "iso:country":"GB",
    "sg:address":"The Kiosk, Saddlers Centre, Park Street",
    "sg:city":"Walsall",
    "sg:classifiers":[
        {
            "category":"Home & Garden",
            "subcategory":"Home Furnishings",
            "type":"Retail Goods"
        },
        {
            "category":"Manufacturing",
            "subcategory":"Textiles",
            "type":"Manufacturing & Wholesale Goods"
        }
    ],
    "sg:phone":"+44 1922 647703",
    "sg:postcode":"WS1 1LY",
    "sg:province":"West Midlands",
    "sg:tags":[
        "blind",
        "made-up",
        "fitting",
        "curtain"
    ],
    "wof:name":"Samrex Textiles",
    "wof:placetype":"venue"
},
  "geometry": {"coordinates":[-1.976104,52.585289],"type":"Point"}
}