{
  "type": "Feature",
  "properties": {
    "iso:country":"GB",
    "sg:address":"Unit B, Trafalgar Industrial Estate, Sovereign Way",
    "sg:city":"Downham Market",
    "sg:classifiers":[
        {
            "category":"Home & Garden",
            "subcategory":"Building Materials",
            "type":"Retail Goods"
        }
    ],
    "sg:phone":"+44 1760 337850",
    "sg:postcode":"PE38 9SW",
    "sg:province":"Cambridgeshire",
    "sg:tags":[
        "insulation",
        "installers"
    ],
    "wof:name":"A B Insulation Supplies",
    "wof:placetype":"venue"
},
  "geometry": {"coordinates":[0.378795,52.602283],"type":"Point"}
}