{
  "type": "Feature",
  "properties": {
    "addr:full":"The Cottage, Hunthill Jedburgh Scottish Borders TD8 6QR",
    "addr:postcode":"td8 6qr",
    "addr:street":"Hunthill",
    "iso:country":"GB",
    "sg:address":"The Cottage, Hunthill",
    "sg:city":"Jedburgh",
    "sg:classifiers":[
        {
            "category":"Banks & Credit Unions",
            "subcategory":"Investment Brokerage",
            "type":"Services"
        }
    ],
    "sg:phone":"+44 1835 862347",
    "sg:postcode":"TD8 6QR",
    "sg:province":"Scottish Borders",
    "sg:tags":[
        "contractor"
    ],
    "wof:name":"William Martin Farm Relief",
    "wof:placetype":"venue"
},
  "geometry": {"coordinates":[-2.554624,55.477718],"type":"Point"}
}