{
  "type": "Feature",
  "properties": {
    "iso:country":"GB",
    "sg:address":"29 Castle St",
    "sg:city":"Aylesbury",
    "sg:classifiers":[
        {
            "category":"Conference Center",
            "type":"Public Place"
        }
    ],
    "sg:phone":"+44 1296 415107",
    "sg:postcode":"HP20 2RA",
    "sg:province":"Buckinghamshire",
    "wof:name":"Hayes Conference Management",
    "wof:placetype":"venue"
},
  "geometry": {"coordinates":[-0.816864,51.816727],"type":"Point"}
}