{
  "type": "Feature",
  "properties": {
    "addr:full":"19 Eastern Grn Road, Eastern Grn Coventry West Midlands CV5 7LG",
    "addr:housenumber":"19",
    "addr:postcode":"cv5 7lg",
    "addr:street":"Eastern Grn Road",
    "iso:country":"GB",
    "sg:address":"19 Eastern Grn Road, Eastern Grn",
    "sg:city":"Coventry",
    "sg:classifiers":[
        {
            "category":"Farming",
            "subcategory":"Nursery",
            "type":"Manufacturing & Wholesale Goods"
        }
    ],
    "sg:phone":"+44 24 7647 1228",
    "sg:postcode":"CV5 7LG",
    "sg:province":"West Midlands",
    "sg:tags":[
        "greenhouse"
    ],
    "wof:name":"P & N L Moore",
    "wof:placetype":"venue"
},
  "geometry": {"coordinates":[-1.578675,52.412834],"type":"Point"}
}