{
  "type": "Feature",
  "properties": {
    "addr:full":"2 Seaview Units, Lewis Road Cardiff Cardiff CF24 5EB",
    "addr:housenumber":"2",
    "addr:postcode":"cf24 5eb",
    "addr:street":"Seaview Units Lewis Road",
    "iso:country":"GB",
    "sg:address":"2 Seaview Units, Lewis Road",
    "sg:city":"Cardiff",
    "sg:classifiers":[
        {
            "category":"Professional",
            "subcategory":"Printing & Photocopies",
            "type":"Services"
        }
    ],
    "sg:phone":"+44 29 2046 0636",
    "sg:postcode":"CF24 5EB",
    "sg:province":"Cardiff",
    "sg:tags":[
        "printer"
    ],
    "wof:name":"Hartley's Printing Co.",
    "wof:placetype":"venue"
},
  "geometry": {"coordinates":[-3.1525900364,51.4783401489],"type":"Point"}
}