{
  "type": "Feature",
  "properties": {
    "addr:full":"Thomson House Cardiff Cardiff CF10 1XR",
    "addr:postcode":"cf10 1xr",
    "iso:country":"GB",
    "sg:address":"Thomson House",
    "sg:city":"Cardiff",
    "sg:classifiers":[
        {
            "category":"Communications",
            "subcategory":"Newspaper",
            "type":"Services"
        }
    ],
    "sg:phone":"+44 1685 383848",
    "sg:postcode":"CF10 1XR",
    "sg:province":"Cardiff",
    "sg:tags":[
        "magazine"
    ],
    "wof:name":"Pontypridd Observer",
    "wof:placetype":"venue"
},
  "geometry": {"coordinates":[-3.1806690693,51.4812583923],"type":"Point"}
}