{
  "type": "Feature",
  "properties": {
    "addr:full":"White Hart House, Silwood Road Ascot Berkshire SL5 0PY",
    "addr:postcode":"sl5 0py",
    "addr:street":"Silwood Road",
    "iso:country":"GB",
    "sg:address":"White Hart House, Silwood Road",
    "sg:city":"Ascot",
    "sg:classifiers":[
        {
            "category":"Wholesale",
            "subcategory":"Books, Periodicals, & Newspapers",
            "type":"Manufacturing & Wholesale Goods"
        }
    ],
    "sg:postcode":"SL5 0PY",
    "sg:province":"Berkshire",
    "sg:tags":[
        "publishing"
    ],
    "wof:name":"Mediaspec Ltd",
    "wof:placetype":"venue"
},
  "geometry": {"coordinates":[-0.639064,51.405472],"type":"Point"}
}