{
  "type": "Feature",
  "properties": {
    "iso:country":"GB",
    "sg:address":"227 Church Rd",
    "sg:city":"Birmingham",
    "sg:classifiers":[
        {
            "category":"Conference Center",
            "type":"Public Place"
        }
    ],
    "sg:phone":"+44 121 693 8889",
    "sg:postcode":"B25 8UR",
    "sg:province":"West Midlands",
    "wof:name":"Travel Groups Conference Division",
    "wof:placetype":"venue"
},
  "geometry": {"coordinates":[-1.8079880476,52.4682197571],"type":"Point"}
}