{
  "type": "Feature",
  "properties": {
    "iso:country":"GB",
    "sg:address":"26 Deptford High Street",
    "sg:city":"London",
    "sg:classifiers":[
        {
            "category":"Fast Food",
            "type":"Food & Drink"
        }
    ],
    "sg:phone":"+44 20 8692 8815",
    "sg:postcode":"SE8 4AF",
    "sg:province":"Greater London",
    "sg:tags":[
        "away",
        "take"
    ],
    "wof:name":"Star of Bengal",
    "wof:placetype":"venue"
},
  "geometry": {"coordinates":[-0.023155,51.474277],"type":"Point"}
}