{
  "type": "Feature",
  "properties": {
    "iso:country":"GB",
    "sg:address":"334 Moss Lane, Hesketh Bank",
    "sg:city":"Preston",
    "sg:classifiers":[
        {
            "category":"Food & Beverages",
            "subcategory":"Farmers Market",
            "type":"Retail Goods"
        }
    ],
    "sg:phone":"+44 1772 813350",
    "sg:postcode":"PR4 6XJ",
    "sg:province":"Lancashire",
    "sg:tags":[
        "gardener"
    ],
    "wof:name":"Peter Holden",
    "wof:placetype":"venue"
},
  "geometry": {"coordinates":[-2.868023,53.694355],"type":"Point"}
}