{
  "type": "Feature",
  "properties": {
    "addr:full":"53 Castle View, Ravensworth Richmond Durham DL11 7ES",
    "addr:housenumber":"53",
    "addr:postcode":"dl11 7es",
    "addr:street":"Castle View",
    "iso:country":"GB",
    "sg:address":"53 Castle View, Ravensworth",
    "sg:city":"Richmond",
    "sg:classifiers":[
        {
            "category":"Retail",
            "subcategory":"Auto Repair",
            "type":"Services"
        }
    ],
    "sg:phone":"+44 1325 718496",
    "sg:postcode":"DL11 7ES",
    "sg:province":"Durham",
    "sg:tags":[
        "breakdown",
        "recovery",
        "vehicle"
    ],
    "wof:name":"Ravensworth Recovery & Repair",
    "wof:placetype":"venue"
},
  "geometry": {"coordinates":[-1.785188,54.467091],"type":"Point"}
}