{
  "type": "Feature",
  "properties": {
    "addr:full":"6 Brabourne Heights, Marsh Lane London Greater London NW7 4NU",
    "addr:housenumber":"6",
    "addr:postcode":"nw7 4nu",
    "addr:street":"Brabourne Heights Marsh Lane",
    "iso:country":"GB",
    "sg:address":"6 Brabourne Heights, Marsh Lane",
    "sg:city":"London",
    "sg:classifiers":[
        {
            "category":"Social Services",
            "subcategory":"Child Care",
            "type":"Services"
        }
    ],
    "sg:postcode":"NW7 4NU",
    "sg:province":"Greater London",
    "sg:tags":[
        "agency",
        "nanny"
    ],
    "wof:name":"J K Child Care Agency",
    "wof:placetype":"venue"
},
  "geometry": {"coordinates":[-0.24719,51.624561],"type":"Point"}
}