{
  "type": "Feature",
  "properties": {
    "iso:country":"GB",
    "sg:address":"Mitchelswood Farm Riding School, Allington Road, Newick",
    "sg:city":"Lewes",
    "sg:classifiers":[
        {
            "category":"Sports & Exercise",
            "subcategory":"Stables",
            "type":"Entertainment"
        },
        {
            "category":"Shopping Center",
            "type":"Public Place"
        }
    ],
    "sg:phone":"+44 1825 722296",
    "sg:postcode":"BN8 4NH",
    "sg:province":"East Sussex",
    "sg:tags":[
        "school",
        "equestrian",
        "centre",
        "livery",
        "riding",
        "education"
    ],
    "sg:website":"http://www.mitchelswoodfarm.com",
    "wof:name":"Mitchelswood Farm Riding School",
    "wof:placetype":"venue"
},
  "geometry": {"coordinates":[0.00841,50.970982],"type":"Point"}
}