{
  "type": "Feature",
  "properties": {
    "iso:country":"GB",
    "sg:address":"65 Brockhurst Road",
    "sg:city":"Gosport",
    "sg:classifiers":[
        {
            "category":"Professional",
            "subcategory":"Engineering",
            "type":"Services"
        },
        {
            "category":"Building & Trades",
            "subcategory":"Electrical",
            "type":"Services"
        }
    ],
    "sg:phone":"+44 23 9252 2212",
    "sg:postcode":"PO12 3AR",
    "sg:province":"Hampshire",
    "sg:tags":[
        "engineer",
        "electrician",
        "contractor"
    ],
    "wof:name":"Alver Contracts Ltd",
    "wof:placetype":"venue"
},
  "geometry": {"coordinates":[-1.152358,50.804909],"type":"Point"}
}