{
  "type": "Feature",
  "properties": {
    "iso:country":"GB",
    "sg:address":"Redgates Nursery, Great Cambridge Rd",
    "sg:city":"Waltham Cross",
    "sg:classifiers":[
        {
            "category":"Community Center",
            "type":"Public Place"
        }
    ],
    "sg:phone":"+44 1992 761515",
    "sg:postcode":"EN8 8EX",
    "sg:province":"Essex",
    "sg:tags":[
        "nursery",
        "centre"
    ],
    "wof:name":"Barr's Bedding Plants",
    "wof:placetype":"venue"
},
  "geometry": {"coordinates":[-0.050149,51.681805],"type":"Point"}
}