{
  "type": "Feature",
  "properties": {
    "iso:country":"GB",
    "sg:address":"Bangor Exhaust Centre, Caernarfon Road",
    "sg:city":"Bangor",
    "sg:classifiers":[
        {
            "category":"Autos & Motor Vehicles",
            "subcategory":"Auto Supplies",
            "type":"Retail Goods"
        }
    ],
    "sg:postcode":"LL57 4SU",
    "sg:province":"Gwynedd",
    "sg:tags":[
        "exhaust",
        "absorber",
        "shock"
    ],
    "wof:name":"Barnes Exhaust",
    "wof:placetype":"venue"
},
  "geometry": {"coordinates":[-4.126064,53.229595],"type":"Point"}
}