{
  "type": "Feature",
  "properties": {
    "iso:country":"GB",
    "sg:address":"9 Craig Leith Road",
    "sg:city":"Stirling",
    "sg:classifiers":[
        {
            "category":"Home & Garden",
            "subcategory":"Building Materials",
            "type":"Retail Goods"
        },
        {
            "category":"Building & Trades",
            "subcategory":"Construction",
            "type":"Services"
        }
    ],
    "sg:phone":"+44 1786 849100",
    "sg:postcode":"FK7 7LQ",
    "sg:province":"Falkirk",
    "sg:tags":[
        "insulation",
        "installers"
    ],
    "wof:name":"Clyde Insulation Supplies Ltd.",
    "wof:placetype":"venue"
},
  "geometry": {"coordinates":[-3.9165689945,56.1118202209],"type":"Point"}
}