{
  "type": "Feature",
  "properties": {
    "addr:full":"244 Ribbleton La Preston Lancashire PR1 5EB",
    "addr:housenumber":"244",
    "addr:postcode":"pr1 5eb",
    "addr:street":"Ribbleton La Preston",
    "iso:country":"GB",
    "sg:address":"244 Ribbleton La",
    "sg:city":"Preston",
    "sg:classifiers":[
        {
            "category":"Personal",
            "subcategory":"Beauty Salon",
            "type":"Services"
        }
    ],
    "sg:postcode":"PR1 5EB",
    "sg:province":"Lancashire",
    "sg:tags":[
        "unisex",
        "hairdresser"
    ],
    "wof:name":"Lee,Lorraine,",
    "wof:placetype":"venue"
},
  "geometry": {"coordinates":[-2.680383,53.766422],"type":"Point"}
}