{
  "type": "Feature",
  "properties": {
    "addr:full":"10 Coleshill Terrace Llanelli Carmarthenshire SA15 3DA",
    "addr:housenumber":"10",
    "addr:postcode":"sa15 3da",
    "addr:street":"Coleshill Terrace",
    "iso:country":"GB",
    "sg:address":"10 Coleshill Terrace",
    "sg:city":"Llanelli",
    "sg:classifiers":[
        {
            "category":"Health Services",
            "subcategory":"Dentist",
            "type":"Services"
        }
    ],
    "sg:phone":"+44 1554 773576",
    "sg:postcode":"SA15 3DA",
    "sg:province":"Carmarthenshire",
    "wof:name":"D E Lang & M C Wills-Wood",
    "wof:placetype":"venue"
},
  "geometry": {"coordinates":[-4.1643781662,51.6823959351],"type":"Point"}
}