{
  "type": "Feature",
  "properties": {
    "addr:full":"96 Holton Road Barry The Vale of Glamorgan CF63 4HJ",
    "addr:housenumber":"96",
    "addr:postcode":"cf63 4hj",
    "addr:street":"Holton Road;Vale",
    "iso:country":"GB",
    "sg:address":"96 Holton Road",
    "sg:city":"Barry",
    "sg:classifiers":[
        {
            "category":"Shopping",
            "subcategory":"Clothing, Apparel, & Fashions",
            "type":"Retail Goods"
        }
    ],
    "sg:phone":"+44 1446 733061",
    "sg:postcode":"CF63 4HJ",
    "sg:province":"The Vale of Glamorgan",
    "sg:tags":[
        "shop"
    ],
    "wof:name":"Nefertiti Fashions Ltd.",
    "wof:placetype":"venue"
},
  "geometry": {"coordinates":[-3.268196106,51.4057159424],"type":"Point"}
}