{
  "type": "Feature",
  "properties": {
    "iso:country":"GB",
    "sg:address":"197 Portswood Road, Portswood",
    "sg:city":"Southampton",
    "sg:classifiers":[
        {
            "category":"Home & Garden",
            "subcategory":"Hardware",
            "type":"Retail Goods"
        },
        {
            "category":"Building & Trades",
            "subcategory":"Locksmith",
            "type":"Services"
        }
    ],
    "sg:phone":"+44 23 8055 1655",
    "sg:postcode":"SO17 2NF",
    "sg:province":"Hampshire",
    "sg:tags":[
        "merchant",
        "cutting",
        "ironmonger",
        "key"
    ],
    "wof:name":"Portswood Hardware",
    "wof:placetype":"venue"
},
  "geometry": {"coordinates":[-1.393754,50.92511],"type":"Point"}
}