{
  "type": "Feature",
  "properties": {
    "addr:full":"Maes Gwm, Ganllwyd Dolgellau Gwynedd LL40 2HY",
    "addr:postcode":"ll40 2hy",
    "addr:street":"Ganllwyd",
    "iso:country":"GB",
    "sg:address":"Maes Gwm, Ganllwyd",
    "sg:city":"Dolgellau",
    "sg:classifiers":[
        {
            "category":"Shopping",
            "subcategory":"Clothing, Apparel, & Fashions",
            "type":"Retail Goods"
        },
        {
            "category":"Landmark",
            "subcategory":"Tourist Attraction",
            "type":"Public Place"
        }
    ],
    "sg:phone":"+44 1341 440666",
    "sg:postcode":"LL40 2HY",
    "sg:province":"Gwynedd",
    "sg:tags":[
        "clothing",
        "fabric",
        "interest"
    ],
    "wof:name":"Coed Y Brenin Visitors Centre",
    "wof:placetype":"venue"
},
  "geometry": {"coordinates":[-3.8842759132,52.7448501587],"type":"Point"}
}