{
  "type": "Feature",
  "properties": {
    "addr:full":"35 Green Road Bournemouth Dorset BH9 1DX",
    "addr:housenumber":"35",
    "addr:postcode":"bh9 1dx",
    "addr:street":"Green Road",
    "iso:country":"GB",
    "sg:address":"35 Green Road",
    "sg:city":"Bournemouth",
    "sg:classifiers":[
        {
            "category":"Retail",
            "subcategory":"Auto Repair",
            "type":"Services"
        }
    ],
    "sg:phone":"+44 1202 528667",
    "sg:postcode":"BH9 1DX",
    "sg:province":"Dorset",
    "sg:tags":[
        "engine",
        "specialist",
        "tuning",
        "car",
        "diagnostic",
        "garage",
        "modification"
    ],
    "wof:name":"The Forge Garage",
    "wof:placetype":"venue"
},
  "geometry": {"coordinates":[-1.870369,50.743889],"type":"Point"}
}