{
  "type": "Feature",
  "properties": {
    "iso:country":"GB",
    "sg:address":"Brockhill Farm, Seafield Lane, Beoley",
    "sg:city":"Redditch",
    "sg:classifiers":[
        {
            "category":"Retail",
            "subcategory":"Auto Repair",
            "type":"Services"
        }
    ],
    "sg:phone":"+44 1564 823992",
    "sg:postcode":"B98 9BX",
    "sg:province":"Warwickshire",
    "sg:tags":[
        "modification",
        "garage"
    ],
    "wof:name":"Craig's Autos",
    "wof:placetype":"venue"
},
  "geometry": {"coordinates":[-1.906234026,52.3238983154],"type":"Point"}
}