{
  "type": "Feature",
  "properties": {
    "addr:full":"180 Southgate Street Gloucester Gloucestershire GL1 2EZ",
    "addr:housenumber":"180",
    "addr:postcode":"gl1 2ez",
    "addr:street":"Southgate Street",
    "iso:country":"GB",
    "sg:address":"180 Southgate Street",
    "sg:city":"Gloucester",
    "sg:classifiers":[
        {
            "category":"Autos & Motor Vehicles",
            "subcategory":"Motorcycle Sales",
            "type":"Retail Goods"
        }
    ],
    "sg:phone":"+44 1452 380883",
    "sg:postcode":"GL1 2EZ",
    "sg:province":"Gloucestershire",
    "sg:tags":[
        "scooter",
        "cycle"
    ],
    "wof:name":"Polygon engineering",
    "wof:placetype":"venue"
},
  "geometry": {"coordinates":[-2.248349,51.863312],"type":"Point"}
}