{
  "type": "Feature",
  "properties": {
    "iso:country":"GB",
    "sg:address":"7 St Brelades Place, Jersey Farm",
    "sg:city":"St Albans",
    "sg:classifiers":[
        {
            "category":"Shopping",
            "subcategory":"Pharmacy",
            "type":"Retail Goods"
        }
    ],
    "sg:phone":"+44 1727 847534",
    "sg:postcode":"AL4 9RG",
    "sg:province":"Hertfordshire",
    "sg:tags":[
        "pharmacist",
        "dispensing",
        "chemist"
    ],
    "wof:name":"Springfield Pharmacy",
    "wof:placetype":"venue"
},
  "geometry": {"coordinates":[-0.297969,51.769413],"type":"Point"}
}