{
  "type": "Feature",
  "properties": {
    "iso:country":"GB",
    "sg:address":"201 Unthank Rd",
    "sg:city":"Norwich",
    "sg:classifiers":[
        {
            "category":"Shopping",
            "subcategory":"Pets & Pet Supplies",
            "type":"Retail Goods"
        }
    ],
    "sg:phone":"+44 1603 505512",
    "sg:postcode":"NR2 2PQ",
    "sg:province":"Norfolk",
    "sg:tags":[
        "food"
    ],
    "wof:name":"Judges Choice Petfood Co",
    "wof:placetype":"venue"
},
  "geometry": {"coordinates":[1.273235,52.621967],"type":"Point"}
}