{
  "type": "Feature",
  "properties": {
    "addr:full":"Aspen House, 48 Coverlands, Haydon Wick Swindon Wiltshire SN25 1RW",
    "addr:housenumber":"48",
    "addr:postcode":"sn25 1rw",
    "addr:street":"Coverlands",
    "iso:country":"GB",
    "sg:address":"Aspen House, 48 Coverlands, Haydon Wick",
    "sg:city":"Swindon",
    "sg:classifiers":[
        {
            "category":"Professional",
            "subcategory":"Management & Consulting",
            "type":"Services"
        }
    ],
    "sg:phone":"+44 1793 701000",
    "sg:postcode":"SN25 1RW",
    "sg:province":"Wiltshire",
    "sg:tags":[
        "consultant",
        "business"
    ],
    "wof:name":"Business Performance Plc",
    "wof:placetype":"venue"
},
  "geometry": {"coordinates":[-1.81479,51.589809],"type":"Point"}
}