{
  "type": "Feature",
  "properties": {
    "iso:country":"GB",
    "sg:address":"48 High Street",
    "sg:city":"Gravesend",
    "sg:classifiers":[
        {
            "category":"Health Services",
            "subcategory":"Optometrist",
            "type":"Services"
        }
    ],
    "sg:phone":"+44 1474 323447",
    "sg:postcode":"DA11 0AY",
    "sg:province":"Kent",
    "sg:tags":[
        "optician"
    ],
    "wof:name":"Eye 2 Eye Opticians",
    "wof:placetype":"venue"
},
  "geometry": {"coordinates":[0.369159,51.442909],"type":"Point"}
}