{
  "type": "Feature",
  "properties": {
    "iso:country":"GB",
    "sg:address":"576 Liverpool Rd, Peel Green",
    "sg:city":"Manchester",
    "sg:classifiers":[
        {
            "category":"Autos & Motor Vehicles",
            "subcategory":"Automobile Sales",
            "type":"Retail Goods"
        }
    ],
    "sg:phone":"+44 161 789 4737",
    "sg:postcode":"M30 7NA",
    "sg:province":"Greater Manchester",
    "sg:tags":[
        "car"
    ],
    "wof:name":"Unicorn Motors",
    "wof:placetype":"venue"
},
  "geometry": {"coordinates":[-2.368391037,53.4773635864],"type":"Point"}
}