{
  "type": "Feature",
  "properties": {
    "iso:country":"GB",
    "sg:address":"463 Penistone Road, Shelley",
    "sg:city":"Huddersfield",
    "sg:classifiers":[
        {
            "category":"Home & Garden",
            "subcategory":"Household Appliances",
            "type":"Retail Goods"
        }
    ],
    "sg:phone":"+44 1484 604554",
    "sg:postcode":"HD8 8HY",
    "sg:province":"South Yorkshire",
    "sg:tags":[
        "electrical"
    ],
    "wof:name":"J C E",
    "wof:placetype":"venue"
},
  "geometry": {"coordinates":[-1.6985379457,53.5938491821],"type":"Point"}
}