{
  "type": "Feature",
  "properties": {
    "addr:full":"The Retreat, 6 Woodlands Road Hassocks East Sussex BN6 8HE",
    "addr:housenumber":"6",
    "addr:postcode":"bn6 8he",
    "addr:street":"Woodlands Road",
    "iso:country":"GB",
    "sg:address":"The Retreat, 6 Woodlands Road",
    "sg:city":"Hassocks",
    "sg:classifiers":[
        {
            "category":"Personal",
            "type":"Services"
        }
    ],
    "sg:postcode":"BN6 8HE",
    "sg:province":"East Sussex",
    "sg:tags":[
        "wedding"
    ],
    "wof:name":"Chimera Wedding Management",
    "wof:placetype":"venue"
},
  "geometry": {"coordinates":[-0.1402689964,50.9239959717],"type":"Point"}
}