{
  "type": "Feature",
  "properties": {
    "addr:full":"2 Saltley Business Park, Pennine Way Birmingham West Midlands B8 1JW",
    "addr:housenumber":"2",
    "addr:postcode":"b8 1jw",
    "addr:street":"Saltley Business Park Pennine Way",
    "iso:country":"GB",
    "sg:address":"2 Saltley Business Park, Pennine Way",
    "sg:city":"Birmingham",
    "sg:classifiers":[
        {
            "category":"Shopping",
            "subcategory":"Comic Books",
            "type":"Retail Goods"
        }
    ],
    "sg:phone":"+44 121 682 8000",
    "sg:postcode":"B8 1JW",
    "sg:province":"West Midlands",
    "sg:tags":[
        "jeweller"
    ],
    "wof:name":"Claire's Accessories (UK) Ltd",
    "wof:placetype":"venue"
},
  "geometry": {"coordinates":[-1.857419014,52.4956359863],"type":"Point"}
}