{
  "type": "Feature",
  "properties": {
    "addr:full":"67 West St Congleton Cheshire CW12 1JY",
    "addr:housenumber":"67",
    "addr:postcode":"cw12 1jy",
    "addr:street":"West St",
    "iso:country":"GB",
    "sg:address":"67 West St",
    "sg:city":"Congleton",
    "sg:classifiers":[
        {
            "category":"Health Services",
            "subcategory":"Dentist",
            "type":"Services"
        }
    ],
    "sg:phone":"+44 1260 273274",
    "sg:postcode":"CW12 1JY",
    "sg:province":"Cheshire",
    "sg:tags":[
        "technician",
        "dental"
    ],
    "wof:name":"P Ball & Co",
    "wof:placetype":"venue"
},
  "geometry": {"coordinates":[-2.2195510864,53.1645507812],"type":"Point"}
}