{
  "type": "Feature",
  "properties": {
    "addr:full":"22 Aldeburgh Drive, Clayton Newcastle Staffordshire ST5 4LH",
    "addr:housenumber":"22",
    "addr:postcode":"st5 4lh",
    "addr:street":"Aldeburgh Drive",
    "iso:country":"GB",
    "sg:address":"22 Aldeburgh Drive, Clayton",
    "sg:city":"Newcastle",
    "sg:classifiers":[
        {
            "category":"Manufacturing",
            "subcategory":"Petroleum Products",
            "type":"Manufacturing & Wholesale Goods"
        }
    ],
    "sg:phone":"+44 1782 621038",
    "sg:postcode":"ST5 4LH",
    "sg:province":"Staffordshire",
    "sg:tags":[
        "double",
        "glazing"
    ],
    "wof:name":"Paramount Windows",
    "wof:placetype":"venue"
},
  "geometry": {"coordinates":[-2.2258429527,52.9806671143],"type":"Point"}
}