{
  "type": "Feature",
  "properties": {
    "addr:full":"Unit 23 St James Mill Business Pk, Millb Northampton Northamptonshire NN5 5JF",
    "addr:housenumber":"unit 23",
    "addr:postcode":"nn5 5jf",
    "addr:street":"St James Mill Business Pk Millb",
    "iso:country":"GB",
    "sg:address":"Unit 23 St James Mill Business Pk, Millb",
    "sg:city":"Northampton",
    "sg:classifiers":[
        {
            "category":"Retail",
            "subcategory":"Auto Repair",
            "type":"Services"
        }
    ],
    "sg:postcode":"NN5 5JF",
    "sg:province":"Northamptonshire",
    "sg:tags":[
        "modification",
        "garage"
    ],
    "wof:name":"Booth,John M,",
    "wof:placetype":"venue"
},
  "geometry": {"coordinates":[-0.9179800153,52.2331504822],"type":"Point"}
}