{
  "type": "Feature",
  "properties": {
    "addr:full":"Bridge End Road Grantham Leicestershire NG32 3AD",
    "addr:postcode":"ng32 3ad",
    "addr:street":"Bridge End Road",
    "iso:country":"GB",
    "sg:address":"Bridge End Road",
    "sg:city":"Grantham",
    "sg:classifiers":[
        {
            "category":"Cafe",
            "type":"Food & Drink"
        }
    ],
    "sg:phone":"+44 1476 576477",
    "sg:postcode":"NG32 3AD",
    "sg:province":"Leicestershire",
    "sg:tags":[
        "tea",
        "room"
    ],
    "wof:name":"The Roman Cafe",
    "wof:placetype":"venue"
},
  "geometry": {"coordinates":[-0.6352589726,52.9041252136],"type":"Point"}
}