{
  "type": "Feature",
  "properties": {
    "addr:full":"38 Brewery Street Dumfries Dumfries and Galloway DG1 2RP",
    "addr:housenumber":"38",
    "addr:postcode":"dg1 2rp",
    "addr:street":"Brewery Street",
    "iso:country":"GB",
    "sg:address":"38 Brewery Street",
    "sg:city":"Dumfries",
    "sg:classifiers":[
        {
            "category":"Travel",
            "subcategory":"Hotels & Motels",
            "type":"Entertainment"
        }
    ],
    "sg:phone":"+44 1387 253337",
    "sg:postcode":"DG1 2RP",
    "sg:province":"Dumfries and Galloway",
    "wof:name":"The White Hart Hotel",
    "wof:placetype":"venue"
},
  "geometry": {"coordinates":[-3.6161489487,55.0693359375],"type":"Point"}
}