{
  "type": "Feature",
  "properties": {
    "addr:full":"45 High Street Princes Risborough Buckinghamshire HP27 0AE",
    "addr:housenumber":"45",
    "addr:postcode":"hp27 0ae",
    "addr:street":"High Street",
    "iso:country":"GB",
    "sg:address":"45 High Street",
    "sg:city":"Princes Risborough",
    "sg:classifiers":[
        {
            "category":"Home & Garden",
            "subcategory":"Garden Supply",
            "type":"Retail Goods"
        },
        {
            "category":"Professional",
            "subcategory":"Business Services",
            "type":"Services"
        }
    ],
    "sg:phone":"+44 1844 344062",
    "sg:postcode":"HP27 0AE",
    "sg:province":"Buckinghamshire",
    "sg:tags":[
        "import",
        "nursery",
        "export",
        "agent",
        "centre"
    ],
    "wof:name":"Animal Fare",
    "wof:placetype":"venue"
},
  "geometry": {"coordinates":[-0.8316529989,51.723739624],"type":"Point"}
}