{
  "type": "Feature",
  "properties": {
    "addr:full":"Belivat Farm Nairn Highland IV12 5PT",
    "addr:housenumber":"nairn",
    "addr:postcode":"iv12 5pt",
    "addr:street":"Highland",
    "iso:country":"GB",
    "sg:address":"Belivat Farm",
    "sg:city":"Nairn",
    "sg:classifiers":[
        {
            "category":"Home & Garden",
            "subcategory":"Garden Supply",
            "type":"Retail Goods"
        },
        {
            "category":"Farming",
            "subcategory":"Farm",
            "type":"Manufacturing & Wholesale Goods"
        }
    ],
    "sg:phone":"+44 1309 651214",
    "sg:postcode":"IV12 5PT",
    "sg:province":"Highland",
    "sg:tags":[
        "mixed",
        "bulb",
        "crop",
        "grower"
    ],
    "wof:name":"R & J R Innes",
    "wof:placetype":"venue"
},
  "geometry": {"coordinates":[-3.8594069481,57.5499305725],"type":"Point"}
}