{
  "type": "Feature",
  "properties": {
    "addr:full":"5 St James' Road Hastings East Sussex TN34 3LH",
    "addr:housenumber":"5",
    "addr:postcode":"tn34 3lh",
    "addr:street":"St James ' Road",
    "iso:country":"GB",
    "sg:address":"5 St James' Road",
    "sg:city":"Hastings",
    "sg:classifiers":[
        {
            "category":"Communications",
            "subcategory":"Film & Video Production",
            "type":"Services"
        }
    ],
    "sg:postcode":"TN34 3LH",
    "sg:province":"East Sussex",
    "sg:tags":[
        "illustrator",
        "artist"
    ],
    "wof:name":"Obsidian Artworks",
    "wof:placetype":"venue"
},
  "geometry": {"coordinates":[0.5841,50.863461],"type":"Point"}
}