{
  "type": "Feature",
  "properties": {
    "iso:country":"GB",
    "sg:address":"37 Broadway",
    "sg:city":"Sheerness",
    "sg:classifiers":[
        {
            "category":"Real Estate",
            "subcategory":"Real Estate Agent",
            "type":"Services"
        }
    ],
    "sg:phone":"+44 1795 662056",
    "sg:postcode":"ME12 1AD",
    "sg:province":"Kent",
    "wof:name":"Rule & Rule",
    "wof:placetype":"venue"
},
  "geometry": {"coordinates":[0.764929,51.440468],"type":"Point"}
}