{
  "type": "Feature",
  "properties": {
    "addr:full":"Park Street, Royton Oldham Lancashire OL2 6QN",
    "addr:postcode":"ol2 6qn",
    "addr:street":"Park Street",
    "iso:country":"GB",
    "sg:address":"Park Street, Royton",
    "sg:city":"Oldham",
    "sg:classifiers":[
        {
            "category":"Retail",
            "subcategory":"Auto Repair",
            "type":"Services"
        }
    ],
    "sg:phone":"+44 161 620 5907",
    "sg:postcode":"OL2 6QN",
    "sg:province":"Lancashire",
    "sg:tags":[
        "modification",
        "garage",
        "related"
    ],
    "wof:name":"James Motors",
    "wof:placetype":"venue"
},
  "geometry": {"coordinates":[-2.122254,53.56712],"type":"Point"}
}