{
  "type": "Feature",
  "properties": {
    "iso:country":"GB",
    "sg:address":"27 Faringdon Road",
    "sg:city":"Swindon",
    "sg:classifiers":[
        {
            "category":"Professional",
            "subcategory":"Computer Services",
            "type":"Services"
        }
    ],
    "sg:postcode":"SN1 5AR",
    "sg:province":"Wiltshire",
    "sg:tags":[
        "system",
        "software"
    ],
    "wof:name":"Camlab Electronics",
    "wof:placetype":"venue"
},
  "geometry": {"coordinates":[-1.788965,51.56152],"type":"Point"}
}