{
  "type": "Feature",
  "properties": {
    "iso:country":"GB",
    "sg:address":"Ocean House",
    "sg:city":"Edinburgh",
    "sg:classifiers":[
        {
            "category":"Professional",
            "subcategory":"Employment Agencies",
            "type":"Services"
        }
    ],
    "sg:phone":"+44 131 553 9100",
    "sg:postcode":"EH6 6NF",
    "sg:province":"City of Edinburgh",
    "sg:tags":[
        "consultant"
    ],
    "wof:name":"Parity Resources Ltd.",
    "wof:placetype":"venue"
},
  "geometry": {"coordinates":[-3.172299,55.977219],"type":"Point"}
}