{
  "type": "Feature",
  "properties": {
    "addr:full":"Malborne Ho, 1 Benyon Gro Peterborough Cambridgeshire PE2 5ZJ",
    "addr:housenumber":"1",
    "addr:postcode":"pe2 5zj",
    "addr:street":"Benyon Gro Peterborough",
    "iso:country":"GB",
    "sg:address":"Malborne Ho, 1 Benyon Gro",
    "sg:city":"Peterborough",
    "sg:classifiers":[
        {
            "category":"Real Estate",
            "subcategory":"Architect",
            "type":"Services"
        }
    ],
    "sg:phone":"+44 1733 236666",
    "sg:postcode":"PE2 5ZJ",
    "sg:province":"Cambridgeshire",
    "wof:name":"Accent On Architecture",
    "wof:placetype":"venue"
},
  "geometry": {"coordinates":[-0.2877990007,52.5444793701],"type":"Point"}
}