{
  "type": "Feature",
  "properties": {
    "addr:full":"Aldridge Farm Woodbridge Suffolk IP13 8EN",
    "addr:housenumber":"woodbridge",
    "addr:postcode":"ip13 8en",
    "addr:street":"Suffolk",
    "iso:country":"GB",
    "sg:address":"Aldridge Farm",
    "sg:city":"Woodbridge",
    "sg:classifiers":[
        {
            "category":"Farming",
            "subcategory":"Farm",
            "type":"Manufacturing & Wholesale Goods"
        }
    ],
    "sg:phone":"+44 1379 384274",
    "sg:postcode":"IP13 8EN",
    "sg:province":"Suffolk",
    "sg:tags":[
        "mixed",
        "crop"
    ],
    "wof:name":"C E Rolfe",
    "wof:placetype":"venue"
},
  "geometry": {"coordinates":[1.3405799866,52.3173599243],"type":"Point"}
}