{
  "type": "Feature",
  "properties": {
    "addr:full":"116a Windham Rd Bournemouth Dorset BH1 4RD",
    "addr:housenumber":"116a",
    "addr:postcode":"bh1 4rd",
    "addr:street":"Windham Rd",
    "iso:country":"GB",
    "sg:address":"116a Windham Rd",
    "sg:city":"Bournemouth",
    "sg:classifiers":[
        {
            "category":"Retail",
            "subcategory":"Auto Repair",
            "type":"Services"
        }
    ],
    "sg:phone":"+44 1202 300222",
    "sg:postcode":"BH1 4RD",
    "sg:province":"Dorset",
    "sg:tags":[
        "modification",
        "garage"
    ],
    "wof:name":"A 1 Bournemouth Repairs",
    "wof:placetype":"venue"
},
  "geometry": {"coordinates":[-1.8533159494,50.7287597656],"type":"Point"}
}