{
  "type": "Feature",
  "properties": {
    "iso:country":"GB",
    "sg:address":"41 Parade",
    "sg:city":"Leamington Spa",
    "sg:classifiers":[
        {
            "category":"Shopping",
            "subcategory":"Clothing, Apparel, & Fashions",
            "type":"Retail Goods"
        }
    ],
    "sg:phone":"+44 1926 316213",
    "sg:postcode":"CV32 4BL",
    "sg:province":"Warwickshire",
    "sg:tags":[
        "shop"
    ],
    "wof:name":"Wallis Fashion Group",
    "wof:placetype":"venue"
},
  "geometry": {"coordinates":[-1.535475,52.291267],"type":"Point"}
}