{
  "type": "Feature",
  "properties": {
    "addr:full":"Unit 27 Lychgate Farms, Arterial Road Rayleigh Essex SS6 7TZ",
    "addr:housenumber":"unit 27",
    "addr:postcode":"ss6 7tz",
    "addr:street":"Lychgate Farms Arterial Road Rayleigh",
    "iso:country":"GB",
    "sg:address":"Unit 27 Lychgate Farms, Arterial Road",
    "sg:city":"Rayleigh",
    "sg:classifiers":[
        {
            "category":"Home & Garden",
            "subcategory":"Home Furnishings",
            "type":"Retail Goods"
        }
    ],
    "sg:postcode":"SS6 7TZ",
    "sg:province":"Essex",
    "sg:tags":[
        "furnishers",
        "planner",
        "kitchen"
    ],
    "wof:name":"Brian Hoy",
    "wof:placetype":"venue"
},
  "geometry": {"coordinates":[0.604678,51.586445],"type":"Point"}
}