{
  "type": "Feature",
  "properties": {
    "iso:country":"GB",
    "sg:address":"80 Latimer Rd",
    "sg:city":"Luton",
    "sg:classifiers":[
        {
            "category":"Bars & Pubs",
            "type":"Food & Drink"
        }
    ],
    "sg:postcode":"LU1 3XD",
    "sg:province":"Bedfordshire",
    "sg:tags":[
        "pubs",
        "inn"
    ],
    "wof:name":"Greene King Plc",
    "wof:placetype":"venue"
},
  "geometry": {"coordinates":[-0.4141359925,51.8739929199],"type":"Point"}
}