{
  "type": "Feature",
  "properties": {
    "addr:full":"71-73 Albion Street Glasgow Glasgow City G1 1RB",
    "addr:housenumber":"71-73",
    "addr:postcode":"g1 1rb",
    "addr:street":"Albion Street",
    "iso:country":"GB",
    "sg:address":"71-73 Albion Street",
    "sg:city":"Glasgow",
    "sg:classifiers":[
        {
            "category":"Professional",
            "subcategory":"Management & Consulting",
            "type":"Services"
        }
    ],
    "sg:phone":"+44 141 552 5908",
    "sg:postcode":"G1 1RB",
    "sg:province":"Glasgow City",
    "sg:tags":[
        "marketing",
        "consultant"
    ],
    "wof:name":"Merchant City Developments Ltd.",
    "wof:placetype":"venue"
},
  "geometry": {"coordinates":[-4.2422790527,55.8586006165],"type":"Point"}
}