{
  "type": "Feature",
  "properties": {
    "addr:full":"142 Fore St Exeter Devon EX4 3AN",
    "addr:housenumber":"142",
    "addr:postcode":"ex4 3an",
    "addr:street":"Fore St",
    "iso:country":"GB",
    "sg:address":"142 Fore St",
    "sg:city":"Exeter",
    "sg:classifiers":[
        {
            "category":"Food & Beverages",
            "subcategory":"Groceries & Convenience Stores",
            "type":"Retail Goods"
        }
    ],
    "sg:postcode":"EX4 3AN",
    "sg:province":"Devon",
    "wof:name":"Cream,Elizabeth,",
    "wof:placetype":"venue"
},
  "geometry": {"coordinates":[-3.535199,50.720779],"type":"Point"}
}