{
  "type": "Feature",
  "properties": {
    "iso:country":"GB",
    "sg:address":"9 Willow Place, Hastingwood",
    "sg:city":"Harlow",
    "sg:classifiers":[
        {
            "category":"Professional",
            "subcategory":"Engineering",
            "type":"Services"
        },
        {
            "category":"Building & Trades",
            "subcategory":"Electrical",
            "type":"Services"
        }
    ],
    "sg:phone":"+44 1279 422826",
    "sg:postcode":"CM17 9JH",
    "sg:province":"Essex",
    "sg:tags":[
        "engineer",
        "electrician",
        "contractor"
    ],
    "wof:name":"ROGER V LUCKING",
    "wof:placetype":"venue"
},
  "geometry": {"coordinates":[0.1576139927,51.7504043579],"type":"Point"}
}