{
  "type": "Feature",
  "properties": {
    "iso:country":"GB",
    "sg:address":"St Georges Down, Blackwater",
    "sg:city":"Newport",
    "sg:classifiers":[
        {
            "category":"Retail",
            "subcategory":"Repair Shop",
            "type":"Services"
        }
    ],
    "sg:postcode":"PO30 3BX",
    "sg:province":"Isle of Wight",
    "sg:tags":[
        "maintenance"
    ],
    "wof:name":"Bradley Builders",
    "wof:placetype":"venue"
},
  "geometry": {"coordinates":[-1.287264,50.689732],"type":"Point"}
}