{
  "type": "Feature",
  "properties": {
    "addr:full":"Spurryhill Lock Indstl Est, Broomhill Rd Stonehaven Aberdeenshire AB39 2NH",
    "addr:postcode":"ab39 2nh",
    "addr:street":"Broomhill Rd",
    "iso:country":"GB",
    "sg:address":"Spurryhill Lock Indstl Est, Broomhill Rd",
    "sg:city":"Stonehaven",
    "sg:classifiers":[
        {
            "category":"Building & Trades",
            "subcategory":"Construction",
            "type":"Services"
        }
    ],
    "sg:phone":"+44 1569 765675",
    "sg:postcode":"AB39 2NH",
    "sg:province":"Aberdeenshire",
    "sg:tags":[
        "welder"
    ],
    "wof:name":"N B Fabrications Ltd",
    "wof:placetype":"venue"
},
  "geometry": {"coordinates":[-2.2087590694,56.9637413025],"type":"Point"}
}