{
  "type": "Feature",
  "properties": {
    "addr:full":"199 East Lane Wembley Greater London HA0 3NG",
    "addr:housenumber":"199",
    "addr:postcode":"ha0 3ng",
    "addr:street":"East Lane",
    "iso:country":"GB",
    "sg:address":"199 East Lane",
    "sg:city":"Wembley",
    "sg:classifiers":[
        {
            "category":"Food & Beverages",
            "subcategory":"Fruits & Vegetables",
            "type":"Retail Goods"
        }
    ],
    "sg:phone":"+44 20 8904 5178",
    "sg:postcode":"HA0 3NG",
    "sg:province":"Greater London",
    "sg:tags":[
        "greengrocer"
    ],
    "wof:name":"Priti Foods",
    "wof:placetype":"venue"
},
  "geometry": {"coordinates":[-0.3053759933,51.5625267029],"type":"Point"}
}