{
  "type": "Feature",
  "properties": {
    "iso:country":"GB",
    "sg:address":"12 Elm Place, Bloomfield Road",
    "sg:city":"Bath",
    "sg:classifiers":[
        {
            "category":"Professional",
            "subcategory":"Management & Consulting",
            "type":"Services"
        }
    ],
    "sg:postcode":"BA2 2AB",
    "sg:province":"Somerset",
    "sg:tags":[
        "marketing",
        "consultant"
    ],
    "wof:name":"Link & Bind Limited",
    "wof:placetype":"venue"
},
  "geometry": {"coordinates":[-2.380927,51.358192],"type":"Point"}
}