{
  "type": "Feature",
  "properties": {
    "iso:country":"GB",
    "sg:address":"Unit 10 Attercliffe Common Industrial Estate, Fell Road",
    "sg:city":"Sheffield",
    "sg:classifiers":[
        {
            "category":"Home & Garden",
            "subcategory":"Hardware",
            "type":"Retail Goods"
        }
    ],
    "sg:phone":"+44 114 244 3350",
    "sg:postcode":"S9 2AL",
    "sg:province":"South Yorkshire",
    "sg:tags":[
        "merchant",
        "ironmonger"
    ],
    "wof:name":"Lloyd Worrall (Sheffield) Ltd",
    "wof:placetype":"venue"
},
  "geometry": {"coordinates":[-1.416234,53.405231],"type":"Point"}
}