{
  "type": "Feature",
  "properties": {
    "addr:full":"13 Rose Terrace Perth Perth and Kinross PH1 5HA",
    "addr:housenumber":"13",
    "addr:postcode":"ph1 5ha",
    "addr:street":"Rose Terrace",
    "iso:country":"GB",
    "sg:address":"13 Rose Terrace",
    "sg:city":"Perth",
    "sg:classifiers":[
        {
            "category":"Insurance",
            "subcategory":"Insurance Agent",
            "type":"Services"
        }
    ],
    "sg:phone":"+44 1738 441555",
    "sg:postcode":"PH1 5HA",
    "sg:province":"Perth and Kinross",
    "sg:tags":[
        "broker"
    ],
    "wof:name":"George Stubbs Insurance Services Ltd.",
    "wof:placetype":"venue"
},
  "geometry": {"coordinates":[-3.4327540398,56.4006385803],"type":"Point"}
}