{
  "type": "Feature",
  "properties": {
    "iso:country":"GB",
    "sg:address":"23 The Main Street, The Village",
    "sg:city":"Glasgow",
    "sg:classifiers":[
        {
            "category":"Food & Beverages",
            "subcategory":"Meat & Fish",
            "type":"Retail Goods"
        }
    ],
    "sg:postcode":"G67 2RR",
    "sg:province":"Falkirk",
    "sg:tags":[
        "butcher"
    ],
    "wof:name":"McRob the Butcher",
    "wof:placetype":"venue"
},
  "geometry": {"coordinates":[-3.974497,55.962078],"type":"Point"}
}