{
  "type": "Feature",
  "properties": {
    "addr:full":"22 Royal Road, Disley Stockport Cheshire SK12 2BS",
    "addr:housenumber":"22",
    "addr:postcode":"sk12 2bs",
    "addr:street":"Royal Road",
    "iso:country":"GB",
    "sg:address":"22 Royal Road, Disley",
    "sg:city":"Stockport",
    "sg:classifiers":[
        {
            "category":"Building & Trades",
            "subcategory":"Landscaping Services",
            "type":"Services"
        }
    ],
    "sg:phone":"+44 1663 764683",
    "sg:postcode":"SK12 2BS",
    "sg:province":"Cheshire",
    "sg:tags":[
        "gardening"
    ],
    "wof:name":"Garden-Life",
    "wof:placetype":"venue"
},
  "geometry": {"coordinates":[-2.0342009068,53.3553657532],"type":"Point"}
}