{
  "type": "Feature",
  "properties": {
    "addr:full":"24-28 King St Oldham Lancashire OL8 1ES",
    "addr:housenumber":"24-28",
    "addr:postcode":"ol8 1es",
    "addr:street":"King St",
    "iso:country":"GB",
    "sg:address":"24-28 King St",
    "sg:city":"Oldham",
    "sg:classifiers":[
        {
            "category":"Food & Beverages",
            "subcategory":"Supermarket",
            "type":"Retail Goods"
        }
    ],
    "sg:postcode":"OL8 1ES",
    "sg:province":"Lancashire",
    "wof:name":"United Norwest Co-Operatives Ltd",
    "wof:placetype":"venue"
},
  "geometry": {"coordinates":[-2.117204,53.539936],"type":"Point"}
}