{
  "type": "Feature",
  "properties": {
    "iso:country":"GB",
    "sg:address":"1778 Coventry Road, Yardley",
    "sg:city":"Birmingham",
    "sg:classifiers":[
        {
            "category":"Shopping",
            "subcategory":"Mobile Phones",
            "type":"Retail Goods"
        }
    ],
    "sg:phone":"+44 121 743 6643",
    "sg:postcode":"B26 1PB",
    "sg:province":"West Midlands",
    "sg:tags":[
        "supplier"
    ],
    "wof:name":"Talk Talk Mobile Phones Ltd.",
    "wof:placetype":"venue"
},
  "geometry": {"coordinates":[-1.802154,52.46048],"type":"Point"}
}