{
  "type": "Feature",
  "properties": {
    "iso:country":"GB",
    "sg:address":"131-132 Snargate Street",
    "sg:city":"Dover",
    "sg:classifiers":[
        {
            "category":"Restaurant",
            "type":"Food & Drink"
        }
    ],
    "sg:phone":"+44 1304 241486",
    "sg:postcode":"CT17 9DA",
    "sg:province":"Kent",
    "wof:name":"Happy Chef",
    "wof:placetype":"venue"
},
  "geometry": {"coordinates":[1.310076952,51.1211891174],"type":"Point"}
}