{
  "type": "Feature",
  "properties": {
    "addr:full":"St Judes Church, Dulwich Road London Greater London SE24 0PB",
    "addr:postcode":"se24 0pb",
    "addr:street":"Dulwich Road",
    "iso:country":"GB",
    "sg:address":"St Judes Church, Dulwich Road",
    "sg:city":"London",
    "sg:classifiers":[
        {
            "category":"Shopping",
            "subcategory":"Stationery & Office Supplies",
            "type":"Retail Goods"
        }
    ],
    "sg:phone":"+44 20 7737 1371",
    "sg:postcode":"SE24 0PB",
    "sg:province":"Greater London",
    "sg:tags":[
        "equipment",
        "furniture"
    ],
    "wof:name":"Tulse Hill Furniture (Holdings) Ltd.",
    "wof:placetype":"venue"
},
  "geometry": {"coordinates":[-0.10864,51.45409],"type":"Point"}
}