{
  "type": "Feature",
  "properties": {
    "addr:full":"12 Sun Street Lancaster Lancashire LA1 1EW",
    "addr:housenumber":"12",
    "addr:postcode":"la1 1ew",
    "addr:street":"Sun Street",
    "iso:country":"GB",
    "sg:address":"12 Sun Street",
    "sg:city":"Lancaster",
    "sg:classifiers":[
        {
            "category":"Professional",
            "subcategory":"Lawyer & Legal Services",
            "type":"Services"
        }
    ],
    "sg:phone":"+44 1524 61671",
    "sg:postcode":"LA1 1EW",
    "sg:province":"Lancashire",
    "sg:tags":[
        "solicitor"
    ],
    "wof:name":"Jobling & Knape",
    "wof:placetype":"venue"
},
  "geometry": {"coordinates":[-2.802668,54.049587],"type":"Point"}
}