{
  "type": "Feature",
  "properties": {
    "addr:full":"9 Lozells Road Birmingham West Midlands B19 2TN",
    "addr:housenumber":"9",
    "addr:postcode":"b19 2tn",
    "addr:street":"Lozells Road",
    "iso:country":"GB",
    "sg:address":"9 Lozells Road",
    "sg:city":"Birmingham",
    "sg:classifiers":[
        {
            "category":"Bars & Pubs",
            "type":"Food & Drink"
        }
    ],
    "sg:postcode":"B19 2TN",
    "sg:province":"West Midlands",
    "sg:tags":[
        "pubs",
        "inn"
    ],
    "wof:name":"The Royal Oak",
    "wof:placetype":"venue"
},
  "geometry": {"coordinates":[-1.9006839991,52.5027351379],"type":"Point"}
}