{
  "type": "Feature",
  "properties": {
    "iso:country":"GB",
    "sg:address":"Hillfield Rd",
    "sg:city":"Chichester",
    "sg:classifiers":[
        {
            "category":"Restaurant",
            "type":"Food & Drink"
        }
    ],
    "sg:phone":"+44 1243 605000",
    "sg:postcode":"PO20 9DB",
    "sg:province":"West Sussex",
    "wof:name":"Rushmere Barn Restaurant The",
    "wof:placetype":"venue"
},
  "geometry": {"coordinates":[-0.793675,50.730385],"type":"Point"}
}