{
  "type": "Feature",
  "properties": {
    "iso:country":"GB",
    "sg:address":"Unit 5c Pury Hill Farm, Alderton Road, Paulerspury",
    "sg:city":"Towcester",
    "sg:classifiers":[
        {
            "category":"Manufacturing",
            "subcategory":"Wood Products",
            "type":"Manufacturing & Wholesale Goods"
        }
    ],
    "sg:phone":"+44 1327 811391",
    "sg:postcode":"NN12 7LS",
    "sg:province":"Buckinghamshire",
    "sg:tags":[
        "packaging",
        "crate",
        "pallets"
    ],
    "wof:name":"Adpack Europe Ltd.",
    "wof:placetype":"venue"
},
  "geometry": {"coordinates":[-0.919294,52.115608],"type":"Point"}
}