{
  "type": "Feature",
  "properties": {
    "addr:full":"48a West Kensington Mansions, Beaumont Crescent London Greater London W14 9PF",
    "addr:housenumber":"48a",
    "addr:postcode":"w14 9pf",
    "addr:street":"West;Beaumont Crescent",
    "iso:country":"GB",
    "sg:address":"48a West Kensington Mansions, Beaumont Crescent",
    "sg:city":"London",
    "sg:classifiers":[
        {
            "category":"Professional",
            "subcategory":"Accounting & Tax Preparation",
            "type":"Services"
        }
    ],
    "sg:postcode":"W14 9PF",
    "sg:province":"Greater London",
    "sg:tags":[
        "accountant"
    ],
    "wof:name":"Enchante Trading Ltd",
    "wof:placetype":"venue"
},
  "geometry": {"coordinates":[-0.20482,51.489189],"type":"Point"}
}