{
  "type": "Feature",
  "properties": {
    "addr:full":"Booker Common High Wycombe Buckinghamshire HP12 4QZ",
    "addr:postcode":"hp12 4qz",
    "addr:street":"Booker",
    "iso:country":"GB",
    "sg:address":"Booker Common",
    "sg:city":"High Wycombe",
    "sg:classifiers":[
        {
            "category":"Bars & Pubs",
            "type":"Food & Drink"
        },
        {
            "category":"Community Center",
            "subcategory":"Social",
            "type":"Public Place"
        }
    ],
    "sg:phone":"+44 1494 520105",
    "sg:postcode":"HP12 4QZ",
    "sg:province":"Buckinghamshire",
    "sg:tags":[
        "pubs",
        "house",
        "inn",
        "activity"
    ],
    "wof:name":"Live & Let Live",
    "wof:placetype":"venue"
},
  "geometry": {"coordinates":[-0.793908,51.61235],"type":"Point"}
}