{
  "type": "Feature",
  "properties": {
    "addr:full":"8 Norfolk Place, Berwick Mills Middlesbrough North Yorkshire TS3 7PD",
    "addr:housenumber":"8",
    "addr:postcode":"ts3 7pd",
    "addr:street":"Norfolk Place",
    "iso:country":"GB",
    "sg:address":"8 Norfolk Place, Berwick Mills",
    "sg:city":"Middlesbrough",
    "sg:classifiers":[
        {
            "category":"Banks & Credit Unions",
            "subcategory":"Bank",
            "type":"Services"
        }
    ],
    "sg:phone":"+44 1642 225121",
    "sg:postcode":"TS3 7PD",
    "sg:province":"North Yorkshire",
    "sg:tags":[
        "financial",
        "institution"
    ],
    "wof:name":"Yorkshire Bank Plc",
    "wof:placetype":"venue"
},
  "geometry": {"coordinates":[-1.2050100565,54.5614585876],"type":"Point"}
}