{
  "type": "Feature",
  "properties": {
    "addr:full":"Sandholme Mill, Key Sike Lane Todmorden Lancashire OL14 5RH",
    "addr:postcode":"ol14 5rh",
    "addr:street":"Sandholme;Sike Lane",
    "iso:country":"GB",
    "sg:address":"Sandholme Mill, Key Sike Lane",
    "sg:city":"Todmorden",
    "sg:classifiers":[
        {
            "category":"Professional",
            "type":"Services"
        }
    ],
    "sg:phone":"+44 1706 816692",
    "sg:postcode":"OL14 5RH",
    "sg:province":"Lancashire",
    "sg:tags":[
        "display",
        "maker"
    ],
    "wof:name":"Mardan Products Ltd.",
    "wof:placetype":"venue"
},
  "geometry": {"coordinates":[-2.097308,53.71431],"type":"Point"}
}