{
  "type": "Feature",
  "properties": {
    "addr:full":"Higher Blakelow Farm Macclesfield Cheshire SK11 0AF",
    "addr:postcode":"sk11 0af",
    "iso:country":"GB",
    "sg:address":"Higher Blakelow Farm",
    "sg:city":"Macclesfield",
    "sg:classifiers":[
        {
            "category":"Farming",
            "subcategory":"Livestock Farm",
            "type":"Manufacturing & Wholesale Goods"
        }
    ],
    "sg:phone":"+44 1625 424788",
    "sg:postcode":"SK11 0AF",
    "sg:province":"Cheshire",
    "sg:tags":[
        "others"
    ],
    "wof:name":"H & P F Pearson",
    "wof:placetype":"venue"
},
  "geometry": {"coordinates":[-2.037759,53.244656],"type":"Point"}
}