{
  "type": "Feature",
  "properties": {
    "iso:country":"GB",
    "sg:address":"109 High Street",
    "sg:city":"Braintree",
    "sg:classifiers":[
        {
            "category":"Building & Trades",
            "subcategory":"Construction",
            "type":"Services"
        }
    ],
    "sg:phone":"+44 1376 322584",
    "sg:postcode":"CM7 1JS",
    "sg:province":"Essex",
    "sg:tags":[
        "builder"
    ],
    "wof:name":"Augustus D Letch Ltd.",
    "wof:placetype":"venue"
},
  "geometry": {"coordinates":[0.54823,51.877235],"type":"Point"}
}