{
  "type": "Feature",
  "properties": {
    "addr:full":"Canal Walk Southampton Hampshire SO14 3BH",
    "addr:postcode":"so14 3bh",
    "addr:street":"Canal Walk",
    "iso:country":"GB",
    "sg:address":"Canal Walk",
    "sg:city":"Southampton",
    "sg:classifiers":[
        {
            "category":"Building & Trades",
            "subcategory":"Construction",
            "type":"Services"
        }
    ],
    "sg:postcode":"SO14 3BH",
    "sg:province":"Hampshire",
    "sg:tags":[
        "monumental",
        "mason"
    ],
    "wof:name":"W A Hoare & Sons (Sculptors) Ltd.",
    "wof:placetype":"venue"
},
  "geometry": {"coordinates":[-1.401498,50.900425],"type":"Point"}
}