{
  "type": "Feature",
  "properties": {
    "iso:country":"GB",
    "sg:address":"Fountain House, 4 South Parade",
    "sg:city":"Leeds",
    "sg:classifiers":[
        {
            "category":"Professional",
            "subcategory":"Lawyer & Legal Services",
            "type":"Services"
        }
    ],
    "sg:phone":"+44 113 243 1714",
    "sg:postcode":"LS1 5QX",
    "sg:province":"West Yorkshire",
    "sg:tags":[
        "solicitor"
    ],
    "wof:name":"I Fisch & Co",
    "wof:placetype":"venue"
},
  "geometry": {"coordinates":[-1.54739,53.799187],"type":"Point"}
}