{
  "type": "Feature",
  "properties": {
    "addr:full":"Victoria Square Dental Practice, 28 Victoria Sq Bristol City of Bristol BS8 4EW",
    "addr:housenumber":"28",
    "addr:postcode":"bs8 4ew",
    "addr:street":"Victoria Sq",
    "iso:country":"GB",
    "sg:address":"Victoria Square Dental Practice, 28 Victoria Sq",
    "sg:city":"Bristol",
    "sg:classifiers":[
        {
            "category":"Health Services",
            "subcategory":"Dentist",
            "type":"Services"
        }
    ],
    "sg:phone":"+44 117 973 5685",
    "sg:postcode":"BS8 4EW",
    "sg:province":"City of Bristol",
    "wof:name":"R J Hudson",
    "wof:placetype":"venue"
},
  "geometry": {"coordinates":[-2.6176290512,51.4501495361],"type":"Point"}
}