{
  "type": "Feature",
  "properties": {
    "iso:country":"GB",
    "sg:address":"Ipswich Hospital, Heath Road",
    "sg:city":"Ipswich",
    "sg:classifiers":[
        {
            "category":"Health Services",
            "subcategory":"Hospital",
            "type":"Services"
        }
    ],
    "sg:phone":"+44 1473 703750",
    "sg:postcode":"IP4 5PD",
    "sg:province":"Suffolk",
    "wof:name":"Laboratory",
    "wof:placetype":"venue"
},
  "geometry": {"coordinates":[1.19796,52.056801],"type":"Point"}
}