{
  "type": "Feature",
  "properties": {
    "addr:full":"Buckridge Farm, Bickington Newton Abbot Devon TQ12 6EJ",
    "addr:housenumber":"bickington newton",
    "addr:postcode":"tq12 6ej",
    "iso:country":"GB",
    "sg:address":"Buckridge Farm, Bickington",
    "sg:city":"Newton Abbot",
    "sg:classifiers":[
        {
            "category":"Banks & Credit Unions",
            "subcategory":"Investment Brokerage",
            "type":"Services"
        }
    ],
    "sg:postcode":"TQ12 6EJ",
    "sg:province":"Devon",
    "sg:tags":[
        "contractor"
    ],
    "wof:name":"Smith,G T,",
    "wof:placetype":"venue"
},
  "geometry": {"coordinates":[-3.695219,50.541859],"type":"Point"}
}