{
  "type": "Feature",
  "properties": {
    "iso:country":"GB",
    "sg:address":"286-288 Leigh Road",
    "sg:city":"Leigh-on-sea",
    "sg:classifiers":[
        {
            "category":"Government",
            "subcategory":"Post Office",
            "type":"Public Place"
        }
    ],
    "sg:phone":"+44 1702 480007",
    "sg:postcode":"SS9 1BW",
    "sg:province":"Essex",
    "sg:tags":[
        "messenger",
        "courier"
    ],
    "wof:name":"Connection Express Couriers Ltd.",
    "wof:placetype":"venue"
},
  "geometry": {"coordinates":[0.661526,51.542782],"type":"Point"}
}