{
  "type": "Feature",
  "properties": {
    "addr:full":"12 Fountain Court, Market Place, Epworth Doncaster Lincolnshire DN9 1EG",
    "addr:housenumber":"12",
    "addr:postcode":"dn9 1eg",
    "addr:street":"Fountain Court Market Place",
    "iso:country":"GB",
    "sg:address":"12 Fountain Court, Market Place, Epworth",
    "sg:city":"Doncaster",
    "sg:classifiers":[
        {
            "category":"Real Estate",
            "subcategory":"Developer",
            "type":"Services"
        }
    ],
    "sg:phone":"+44 1427 875655",
    "sg:postcode":"DN9 1EG",
    "sg:province":"Lincolnshire",
    "sg:tags":[
        "property"
    ],
    "wof:name":"Eastfield Developments Ltd.",
    "wof:placetype":"venue"
},
  "geometry": {"coordinates":[-0.8241299987,53.5256729126],"type":"Point"}
}