{
  "type": "Feature",
  "properties": {
    "addr:full":"Little Mearley Hall, Worston Clitheroe Lancashire BB7 1QA",
    "addr:postcode":"bb7 1qa",
    "iso:country":"GB",
    "sg:address":"Little Mearley Hall, Worston",
    "sg:city":"Clitheroe",
    "sg:classifiers":[
        {
            "category":"Farming",
            "subcategory":"Livestock Farm",
            "type":"Manufacturing & Wholesale Goods"
        }
    ],
    "sg:phone":"+44 1200 441395",
    "sg:postcode":"BB7 1QA",
    "sg:province":"Lancashire",
    "sg:tags":[
        "others"
    ],
    "wof:name":"Robert Lister",
    "wof:placetype":"venue"
},
  "geometry": {"coordinates":[-2.3371469975,53.8790359497],"type":"Point"}
}