{
  "type": "Feature",
  "properties": {
    "addr:full":"Unit 8 North Orbital Trading Estate, Napsbury Lane St Albans Hertfordshire AL1 1XB",
    "addr:housenumber":"unit 8",
    "addr:postcode":"al1 1xb",
    "addr:street":"North Orbital Trading Estate Napsbury Lane",
    "iso:country":"GB",
    "sg:address":"Unit 8 North Orbital Trading Estate, Napsbury Lane",
    "sg:city":"St Albans",
    "sg:classifiers":[
        {
            "category":"Professional",
            "type":"Services"
        }
    ],
    "sg:phone":"+44 1727 811442",
    "sg:postcode":"AL1 1XB",
    "sg:province":"Hertfordshire",
    "sg:tags":[
        "shopfitters"
    ],
    "wof:name":"GD Contstruction",
    "wof:placetype":"venue"
},
  "geometry": {"coordinates":[-0.3377520144,51.7531890869],"type":"Point"}
}