{
  "type": "Feature",
  "properties": {
    "addr:full":"Firs Garage, Glenlyon Place Leven Fife KY8 4QY",
    "addr:postcode":"ky8 4qy",
    "addr:street":"Glenlyon Place Leven",
    "iso:country":"GB",
    "sg:address":"Firs Garage, Glenlyon Place",
    "sg:city":"Leven",
    "sg:classifiers":[
        {
            "category":"Autos & Motor Vehicles",
            "subcategory":"Motorcycle Sales",
            "type":"Retail Goods"
        }
    ],
    "sg:phone":"+44 1333 429400",
    "sg:postcode":"KY8 4QY",
    "sg:province":"Fife",
    "sg:tags":[
        "chauffeur",
        "driven",
        "car"
    ],
    "wof:name":"Ecosse Cabs",
    "wof:placetype":"venue"
},
  "geometry": {"coordinates":[-2.9987869263,56.1944007874],"type":"Point"}
}