{
  "type": "Feature",
  "properties": {
    "iso:country":"GB",
    "sg:address":"16 Nottingham Road, Gotham",
    "sg:city":"Nottingham",
    "sg:classifiers":[
        {
            "category":"Building & Trades",
            "subcategory":"Cleaning & Sanitation",
            "type":"Services"
        },
        {
            "category":"Home & Garden",
            "subcategory":"Carpets & Floor Coverings",
            "type":"Retail Goods"
        }
    ],
    "sg:phone":"+44 115 983 0802",
    "sg:postcode":"NG11 0HG",
    "sg:province":"Nottinghamshire",
    "sg:tags":[
        "cleaner",
        "upholstery",
        "commercial"
    ],
    "wof:name":"Aqua-Pro",
    "wof:placetype":"venue"
},
  "geometry": {"coordinates":[-1.205739975,52.8678092957],"type":"Point"}
}