{
  "type": "Feature",
  "properties": {
    "addr:full":"7 Castle Street Canterbury Kent CT1 2QF",
    "addr:housenumber":"7",
    "addr:postcode":"ct1 2qf",
    "addr:street":"Castle Street",
    "iso:country":"GB",
    "sg:address":"7 Castle Street",
    "sg:city":"Canterbury",
    "sg:classifiers":[
        {
            "category":"Real Estate",
            "subcategory":"Real Estate Agent",
            "type":"Services"
        }
    ],
    "sg:phone":"+44 1227 760214",
    "sg:postcode":"CT1 2QF",
    "sg:province":"Kent",
    "wof:name":"Mundays Estate Agents",
    "wof:placetype":"venue"
},
  "geometry": {"coordinates":[1.077687,51.277199],"type":"Point"}
}