{
  "type": "Feature",
  "properties": {
    "iso:country":"GB",
    "sg:address":"36 Barratt Ave",
    "sg:city":"Wood Green",
    "sg:classifiers":[
        {
            "category":"Professional",
            "type":"Services"
        }
    ],
    "sg:phone":"+44 20 8881 8000",
    "sg:postcode":"N22 4EZ",
    "sg:province":"Greater London",
    "sg:tags":[
        "entertainer"
    ],
    "wof:name":"Murder By Accident",
    "wof:placetype":"venue"
},
  "geometry": {"coordinates":[-0.116549,51.597801],"type":"Point"}
}