{
  "type": "Feature",
  "properties": {
    "iso:country":"GB",
    "sg:address":"Wykeham Pit",
    "sg:city":"Scarborough",
    "sg:classifiers":[
        {
            "category":"Home & Garden",
            "subcategory":"Garden Supply",
            "type":"Retail Goods"
        }
    ],
    "sg:phone":"+44 1723 862142",
    "sg:postcode":"YO13 9QU",
    "sg:province":"North Yorkshire",
    "sg:tags":[
        "sand",
        "gravel"
    ],
    "wof:name":"ARC Northern",
    "wof:placetype":"venue"
},
  "geometry": {"coordinates":[-0.5365350246,54.2554702759],"type":"Point"}
}