{
  "type": "Feature",
  "properties": {
    "addr:full":"Church Street, Willersey Broadway Gloucestershire WR12 7PN",
    "addr:postcode":"wr12 7pn",
    "addr:street":"Church Street;Broadway",
    "iso:country":"GB",
    "sg:address":"Church Street, Willersey",
    "sg:city":"Broadway",
    "sg:classifiers":[
        {
            "category":"Education",
            "subcategory":"School",
            "type":"Public Place"
        }
    ],
    "sg:phone":"+44 1386 852646",
    "sg:postcode":"WR12 7PN",
    "sg:province":"Gloucestershire",
    "sg:tags":[
        "local",
        "authority"
    ],
    "wof:name":"Willersey Primary School",
    "wof:placetype":"venue"
},
  "geometry": {"coordinates":[-1.863964,52.035858],"type":"Point"}
}