{
  "type": "Feature",
  "properties": {
    "addr:full":"Halifax Road, Bowerhill Melksham Wiltshire SN12 6UB",
    "addr:postcode":"sn12 6ub",
    "addr:street":"Halifax Road Bowerhill",
    "iso:country":"GB",
    "sg:address":"Halifax Road, Bowerhill",
    "sg:city":"Melksham",
    "sg:classifiers":[
        {
            "category":"Manufacturing",
            "subcategory":"Electronics",
            "type":"Manufacturing & Wholesale Goods"
        }
    ],
    "sg:phone":"+44 1225 705600",
    "sg:postcode":"SN12 6UB",
    "sg:province":"Wiltshire",
    "sg:tags":[
        "control",
        "component",
        "-",
        "electronic"
    ],
    "wof:name":"Citronic Ltd.",
    "wof:placetype":"venue"
},
  "geometry": {"coordinates":[-2.1221280098,51.3611679077],"type":"Point"}
}