{
  "type": "Feature",
  "properties": {
    "addr:full":"53 Murray Rd Northwood Greater London HA6 2YP",
    "addr:housenumber":"53",
    "addr:postcode":"ha6 2yp",
    "addr:street":"Murray Rd",
    "iso:country":"GB",
    "sg:address":"53 Murray Rd",
    "sg:city":"Northwood",
    "sg:classifiers":[
        {
            "category":"Building & Trades",
            "subcategory":"Plumbing",
            "type":"Services"
        }
    ],
    "sg:phone":"+44 1923 828874",
    "sg:postcode":"HA6 2YP",
    "sg:province":"Greater London",
    "sg:tags":[
        "drain",
        "clearance",
        "sewer"
    ],
    "wof:name":"Bridgenorth Drainage Co",
    "wof:placetype":"venue"
},
  "geometry": {"coordinates":[-0.4239310026,51.608795166],"type":"Point"}
}