{
  "type": "Feature",
  "properties": {
    "addr:full":"Plas Pentre Cefn Farm, Craigllwyn Oswestry Shropshire SY10 9BJ",
    "addr:postcode":"sy10 9bj",
    "addr:street":"Plas;Cefn;Craigllwyn",
    "iso:country":"GB",
    "sg:address":"Plas Pentre Cefn Farm, Craigllwyn",
    "sg:city":"Oswestry",
    "sg:classifiers":[
        {
            "category":"Farming",
            "subcategory":"Livestock Farm",
            "type":"Manufacturing & Wholesale Goods"
        },
        {
            "category":"Farming",
            "subcategory":"Farm",
            "type":"Manufacturing & Wholesale Goods"
        }
    ],
    "sg:postcode":"SY10 9BJ",
    "sg:province":"Shropshire",
    "sg:tags":[
        "mixed",
        "crop",
        "others"
    ],
    "wof:name":"B E Dyke",
    "wof:placetype":"venue"
},
  "geometry": {"coordinates":[-3.131509,52.841396],"type":"Point"}
}