{
  "type": "Feature",
  "properties": {
    "addr:full":"539 Loose Road Maidstone Kent ME15 9UQ",
    "addr:housenumber":"539",
    "addr:postcode":"me15 9uq",
    "addr:street":"Loose Road",
    "iso:country":"GB",
    "sg:address":"539 Loose Road",
    "sg:city":"Maidstone",
    "sg:classifiers":[
        {
            "category":"Building & Trades",
            "subcategory":"Plumbing",
            "type":"Services"
        },
        {
            "category":"Building & Trades",
            "subcategory":"Construction",
            "type":"Services"
        }
    ],
    "sg:postcode":"ME15 9UQ",
    "sg:province":"Kent",
    "sg:tags":[
        "heating",
        "contractor"
    ],
    "wof:name":"Mark Jenkins Plumbing & Heating Engineers",
    "wof:placetype":"venue"
},
  "geometry": {"coordinates":[0.5255849957,51.2482719421],"type":"Point"}
}