{
  "type": "Feature",
  "properties": {
    "iso:country":"GB",
    "sg:address":"Unit 1 Bridge Road Ho, Bridge Road Business Park",
    "sg:city":"Haywards Heath",
    "sg:classifiers":[
        {
            "category":"Real Estate",
            "subcategory":"Architect",
            "type":"Services"
        }
    ],
    "sg:phone":"+44 1444 441440",
    "sg:postcode":"RH16 1TX",
    "sg:province":"East Sussex",
    "sg:tags":[
        "architectural"
    ],
    "wof:name":"Arc Design Services",
    "wof:placetype":"venue"
},
  "geometry": {"coordinates":[-0.0977770016,51.0088691711],"type":"Point"}
}