{
  "type": "Feature",
  "properties": {
    "iso:country":"GB",
    "sg:address":"156 Bury Old Road",
    "sg:city":"Salford",
    "sg:classifiers":[
        {
            "category":"Wholesale",
            "subcategory":"Construction Materials",
            "type":"Manufacturing & Wholesale Goods"
        }
    ],
    "sg:postcode":"M7 4QY",
    "sg:province":"Greater Manchester",
    "sg:tags":[
        "merchant",
        "brick"
    ],
    "wof:name":"Manchester Reclaimed Brick Co",
    "wof:placetype":"venue"
},
  "geometry": {"coordinates":[-2.250423,53.516132],"type":"Point"}
}