{
  "type": "Feature",
  "properties": {
    "iso:country":"GB",
    "sg:address":"A B C House, 156 Elm Road",
    "sg:city":"March",
    "sg:classifiers":[
        {
            "category":"Retail",
            "subcategory":"Driving School",
            "type":"Services"
        }
    ],
    "sg:postcode":"PE15 8PP",
    "sg:province":"Cambridgeshire",
    "wof:name":"A B C Driving Tuition",
    "wof:placetype":"venue"
},
  "geometry": {"coordinates":[0.093364,52.567039],"type":"Point"}
}