{
  "type": "Feature",
  "properties": {
    "iso:country":"GB",
    "sg:address":"14-18 North Street",
    "sg:city":"Wellington",
    "sg:classifiers":[
        {
            "category":"Organizations",
            "subcategory":"Non-profit Organization",
            "type":"Services"
        }
    ],
    "sg:phone":"+44 1823 665622",
    "sg:postcode":"TA21 8LT",
    "sg:province":"Devon",
    "sg:tags":[
        "organisation",
        "voluntary",
        "charity"
    ],
    "wof:name":"Wellington Christian Outreach Centre",
    "wof:placetype":"venue"
},
  "geometry": {"coordinates":[-3.228993,50.978809],"type":"Point"}
}