{
  "type": "Feature",
  "properties": {
    "iso:country":"GB",
    "sg:address":"84 London Road, Southborough",
    "sg:city":"Tunbridge Wells",
    "sg:classifiers":[
        {
            "category":"Fast Food",
            "type":"Food & Drink"
        }
    ],
    "sg:phone":"+44 1892 529276",
    "sg:postcode":"TN4 0PP",
    "sg:province":"Kent",
    "sg:tags":[
        "away",
        "meal",
        "outlet",
        "take"
    ],
    "wof:name":"Royal Victoria Charcoal Grill",
    "wof:placetype":"venue"
},
  "geometry": {"coordinates":[0.25289,51.164719],"type":"Point"}
}