{
  "type": "Feature",
  "properties": {
    "addr:full":"Halden Lane Cranbrook Kent TN17 4JG",
    "addr:postcode":"tn17 4jg",
    "addr:street":"Halden Lane",
    "iso:country":"GB",
    "sg:address":"Halden Lane",
    "sg:city":"Cranbrook",
    "sg:classifiers":[
        {
            "category":"Professional",
            "subcategory":"Printing & Photocopies",
            "type":"Services"
        }
    ],
    "sg:phone":"+44 1580 241021",
    "sg:postcode":"TN17 4JG",
    "sg:province":"Kent",
    "sg:tags":[
        "printer"
    ],
    "wof:name":"Capstick Printers",
    "wof:placetype":"venue"
},
  "geometry": {"coordinates":[0.6231,51.080952],"type":"Point"}
}