{
  "type": "Feature",
  "properties": {
    "addr:full":"45-48 Fore Street, Chudleigh Newton Abbot Devon TQ13 0HY",
    "addr:housenumber":"45-48",
    "addr:postcode":"tq13 0hy",
    "addr:street":"Fore Street",
    "iso:country":"GB",
    "sg:address":"45-48 Fore Street, Chudleigh",
    "sg:city":"Newton Abbot",
    "sg:classifiers":[
        {
            "category":"Social Services",
            "subcategory":"Retirement Home",
            "type":"Services"
        }
    ],
    "sg:postcode":"TQ13 0HY",
    "sg:province":"Devon",
    "sg:tags":[
        "residential",
        "care"
    ],
    "wof:name":"Haven Hotpots",
    "wof:placetype":"venue"
},
  "geometry": {"coordinates":[-3.6034700871,50.6030921936],"type":"Point"}
}