{
  "type": "Feature",
  "properties": {
    "iso:country":"GB",
    "sg:address":"428 Cheetham Hill Rd",
    "sg:city":"Manchester",
    "sg:classifiers":[
        {
            "category":"Fast Food",
            "type":"Food & Drink"
        }
    ],
    "sg:postcode":"M8 9LE",
    "sg:province":"Greater Manchester",
    "sg:tags":[
        "away",
        "take"
    ],
    "wof:name":"Hussain,L,",
    "wof:placetype":"venue"
},
  "geometry": {"coordinates":[-2.242853,53.509499],"type":"Point"}
}