{
  "type": "Feature",
  "properties": {
    "addr:full":"55 High Holborn Bloomsbury Greater London WC1V 6DX",
    "addr:housenumber":"55",
    "addr:postcode":"wc1v 6dx",
    "addr:street":"High Holborn",
    "iso:country":"GB",
    "sg:address":"55 High Holborn",
    "sg:city":"Bloomsbury",
    "sg:classifiers":[
        {
            "category":"Professional",
            "subcategory":"Management & Consulting",
            "type":"Services"
        }
    ],
    "sg:phone":"+44 20 7440 8600",
    "sg:postcode":"WC1V 6DX",
    "sg:province":"Greater London",
    "sg:tags":[
        "consultant",
        "business"
    ],
    "wof:name":"Momentus New Media Ltd",
    "wof:placetype":"venue"
},
  "geometry": {"coordinates":[-0.1152819991,51.5181732178],"type":"Point"}
}