{
  "type": "Feature",
  "properties": {
    "iso:country":"GB",
    "sg:address":"19 Chesham Rd",
    "sg:city":"Amersham",
    "sg:classifiers":[
        {
            "category":"Banks & Credit Unions",
            "subcategory":"Financial Services",
            "type":"Services"
        }
    ],
    "sg:phone":"+44 1494 433434",
    "sg:postcode":"HP6 5HN",
    "sg:province":"Buckinghamshire",
    "sg:tags":[
        "adviser"
    ],
    "wof:name":"Beaumont Pensions Protection & Investment Consultants",
    "wof:placetype":"venue"
},
  "geometry": {"coordinates":[-0.6074180007,51.6772613525],"type":"Point"}
}