{
  "type": "Feature",
  "properties": {
    "addr:full":"93 Manor Road Fleetwood Lancashire FY7 7HY",
    "addr:housenumber":"93",
    "addr:postcode":"fy7 7hy",
    "addr:street":"Manor Road",
    "iso:country":"GB",
    "sg:address":"93 Manor Road",
    "sg:city":"Fleetwood",
    "sg:classifiers":[
        {
            "category":"Food & Beverages",
            "subcategory":"Supermarket",
            "type":"Retail Goods"
        }
    ],
    "sg:phone":"+44 1253 776596",
    "sg:postcode":"FY7 7HY",
    "sg:province":"Lancashire",
    "wof:name":"Cost Quarter",
    "wof:placetype":"venue"
},
  "geometry": {"coordinates":[-3.031419,53.92215],"type":"Point"}
}