{
  "type": "Feature",
  "properties": {
    "iso:country":"GB",
    "sg:address":"10 Oak Road, Watchfield",
    "sg:city":"Swindon",
    "sg:classifiers":[
        {
            "category":"Bars & Pubs",
            "type":"Food & Drink"
        }
    ],
    "sg:phone":"+44 1793 782668",
    "sg:postcode":"SN6 8TD",
    "sg:province":"Gloucestershire",
    "sg:tags":[
        "pubs",
        "inn"
    ],
    "wof:name":"The Royal Oak",
    "wof:placetype":"venue"
},
  "geometry": {"coordinates":[-1.649542,51.611542],"type":"Point"}
}