{
  "type": "Feature",
  "properties": {
    "addr:full":"Thorpe Park, Staines Lane Chertsey Surrey KT16 8PN",
    "addr:postcode":"kt16 8pn",
    "addr:street":"Staines Lane",
    "iso:country":"GB",
    "sg:address":"Thorpe Park, Staines Lane",
    "sg:city":"Chertsey",
    "sg:classifiers":[
        {
            "category":"Professional",
            "subcategory":"Art Services",
            "type":"Services"
        }
    ],
    "sg:phone":"+44 1932 566826",
    "sg:postcode":"KT16 8PN",
    "sg:province":"Surrey",
    "sg:tags":[
        "photographer"
    ],
    "wof:name":"Flash Back Old Time Portraits",
    "wof:placetype":"venue"
},
  "geometry": {"coordinates":[-0.508254,51.388199],"type":"Point"}
}