{
  "type": "Feature",
  "properties": {
    "iso:country":"GB",
    "sg:address":"The Square",
    "sg:city":"Swanage",
    "sg:classifiers":[
        {
            "category":"Fast Food",
            "type":"Food & Drink"
        }
    ],
    "sg:phone":"+44 1929 426357",
    "sg:postcode":"BH19 2LJ",
    "sg:province":"Dorset",
    "sg:tags":[
        "away",
        "meal",
        "outlet",
        "take"
    ],
    "wof:name":"Dinos",
    "wof:placetype":"venue"
},
  "geometry": {"coordinates":[-1.956785,50.608253],"type":"Point"}
}