{
  "type": "Feature",
  "properties": {
    "iso:country":"GB",
    "sg:address":"31 High Street",
    "sg:city":"March",
    "sg:classifiers":[
        {
            "category":"Shopping",
            "subcategory":"Clothing, Apparel, & Fashions",
            "type":"Retail Goods"
        }
    ],
    "sg:phone":"+44 1354 659526",
    "sg:postcode":"PE15 9JA",
    "sg:province":"Cambridgeshire",
    "sg:tags":[
        "lady",
        "fashionwear",
        "ladieswear"
    ],
    "wof:name":"Fashion Wheel",
    "wof:placetype":"venue"
},
  "geometry": {"coordinates":[0.08815,52.549042],"type":"Point"}
}