{
  "type": "Feature",
  "properties": {
    "addr:full":"51 North Prospect Road Plymouth Devon PL2 3HZ",
    "addr:housenumber":"51",
    "addr:postcode":"pl2 3hz",
    "addr:street":"North Prospect Road",
    "iso:country":"GB",
    "sg:address":"51 North Prospect Road",
    "sg:city":"Plymouth",
    "sg:classifiers":[
        {
            "category":"Building & Trades",
            "subcategory":"Construction",
            "type":"Services"
        }
    ],
    "sg:postcode":"PL2 3HZ",
    "sg:province":"Devon",
    "sg:tags":[
        "roofing"
    ],
    "wof:name":"Matthew & Sons",
    "wof:placetype":"venue"
},
  "geometry": {"coordinates":[-4.1623311043,50.3886032104],"type":"Point"}
}