{
  "type": "Feature",
  "properties": {
    "addr:full":"23 Bentinck Street London Greater London W1U 2EZ",
    "addr:housenumber":"23",
    "addr:postcode":"w1u 2ez",
    "addr:street":"Bentinck Street",
    "iso:country":"GB",
    "sg:address":"23 Bentinck Street",
    "sg:city":"London",
    "sg:classifiers":[
        {
            "category":"Arts & Performance",
            "subcategory":"Theater",
            "type":"Entertainment"
        }
    ],
    "sg:phone":"+44 20 7245 6912",
    "sg:postcode":"W1U 2EZ",
    "sg:province":"Greater London",
    "sg:tags":[
        "theatrical",
        "agency"
    ],
    "wof:name":"The London Co. (International Plays) Ltd.",
    "wof:placetype":"venue"
},
  "geometry": {"coordinates":[-0.149422,51.517113],"type":"Point"}
}