{
  "type": "Feature",
  "properties": {
    "iso:country":"GB",
    "sg:address":"22 New Road",
    "sg:city":"Dagenham",
    "sg:classifiers":[
        {
            "category":"Retail",
            "subcategory":"Auto Repair",
            "type":"Services"
        }
    ],
    "sg:phone":"+44 20 8592 4444",
    "sg:postcode":"RM9 6YS",
    "sg:province":"Essex",
    "sg:tags":[
        "modification",
        "garage"
    ],
    "wof:name":"Days Garage",
    "wof:placetype":"venue"
},
  "geometry": {"coordinates":[0.150352,51.530846],"type":"Point"}
}