{
  "type": "Feature",
  "properties": {
    "addr:full":"Low Leighton Road, New Mills High Peak Cheshire SK22 4LS",
    "addr:postcode":"sk22 4ls",
    "addr:street":"Leighton Road",
    "iso:country":"GB",
    "sg:address":"Low Leighton Road, New Mills",
    "sg:city":"High Peak",
    "sg:classifiers":[
        {
            "category":"Health Services",
            "subcategory":"Hospital",
            "type":"Services"
        }
    ],
    "sg:phone":"+44 1663 744153",
    "sg:postcode":"SK22 4LS",
    "sg:province":"Cheshire",
    "wof:name":"Ollersett View Hospital",
    "wof:placetype":"venue"
},
  "geometry": {"coordinates":[-1.989441,53.366589],"type":"Point"}
}