{
  "type": "Feature",
  "properties": {
    "addr:full":"Arundel Gate Sheffield South Yorkshire S1 2PN",
    "addr:postcode":"s1 2pn",
    "addr:street":"Arundel Gate",
    "iso:country":"GB",
    "sg:address":"Arundel Gate",
    "sg:city":"Sheffield",
    "sg:classifiers":[
        {
            "category":"Parking",
            "type":"Transportation"
        }
    ],
    "sg:phone":"+44 20 7499 7050",
    "sg:postcode":"S1 2PN",
    "sg:province":"South Yorkshire",
    "sg:tags":[
        "car",
        "park"
    ],
    "wof:name":"Ncp",
    "wof:placetype":"venue"
},
  "geometry": {"coordinates":[-1.4690630436,53.3781929016],"type":"Point"}
}