{
  "type": "Feature",
  "properties": {
    "iso:country":"GB",
    "sg:address":"6 Garden Rd, Stornoway",
    "sg:city":"Isle Of Lewis",
    "sg:classifiers":[
        {
            "category":"Manufacturing",
            "subcategory":"Textiles",
            "type":"Manufacturing & Wholesale Goods"
        }
    ],
    "sg:phone":"+44 1851 702269",
    "sg:postcode":"HS1 2QJ",
    "sg:province":"Eilean Siar",
    "sg:tags":[
        "made-up"
    ],
    "wof:name":"Harris",
    "wof:placetype":"venue"
},
  "geometry": {"coordinates":[-6.383355,58.208782],"type":"Point"}
}