{
  "type": "Feature",
  "properties": {
    "iso:country":"GB",
    "sg:address":"Private Road No 2, Colwick Industrial Estate",
    "sg:city":"Nottingham",
    "sg:classifiers":[
        {
            "category":"Health Services",
            "subcategory":"Hospital",
            "type":"Services"
        }
    ],
    "sg:phone":"+44 115 961 8692",
    "sg:postcode":"NG4 2JR",
    "sg:province":"Nottinghamshire",
    "sg:tags":[
        "ambulance"
    ],
    "wof:name":"Sprays Transport",
    "wof:placetype":"venue"
},
  "geometry": {"coordinates":[-1.080202,52.956261],"type":"Point"}
}