{
  "type": "Feature",
  "properties": {
    "addr:full":"1 City Road Cardiff Cardiff CF24 3BJ",
    "addr:housenumber":"1",
    "addr:postcode":"cf24 3bj",
    "addr:street":"City Road",
    "iso:country":"GB",
    "sg:address":"1 City Road",
    "sg:city":"Cardiff",
    "sg:classifiers":[
        {
            "category":"Retail",
            "subcategory":"Auto Repair",
            "type":"Services"
        }
    ],
    "sg:phone":"+44 29 2048 0829",
    "sg:postcode":"CF24 3BJ",
    "sg:province":"Cardiff",
    "sg:tags":[
        "modification",
        "garage"
    ],
    "wof:name":"Lewis Motors",
    "wof:placetype":"venue"
},
  "geometry": {"coordinates":[-3.1658680439,51.4855613708],"type":"Point"}
}