{
  "type": "Feature",
  "properties": {
    "addr:full":"6 Hunters Row, Boroughbridge York North Yorkshire YO51 9PE",
    "addr:housenumber":"6",
    "addr:postcode":"yo51 9pe",
    "addr:street":"Hunters Row",
    "iso:country":"GB",
    "sg:address":"6 Hunters Row, Boroughbridge",
    "sg:city":"York",
    "sg:classifiers":[
        {
            "category":"Building & Trades",
            "subcategory":"Construction",
            "type":"Services"
        }
    ],
    "sg:phone":"+44 1423 322765",
    "sg:postcode":"YO51 9PE",
    "sg:province":"North Yorkshire",
    "sg:tags":[
        "decorator",
        "painter"
    ],
    "wof:name":"Vaughan Watts",
    "wof:placetype":"venue"
},
  "geometry": {"coordinates":[-1.395615,54.086605],"type":"Point"}
}