{
  "type": "Feature",
  "properties": {
    "addr:full":"Thakeham Road, Storrington Pulborough West Sussex RH20 3PP",
    "addr:postcode":"rh20 3pp",
    "addr:street":"Thakeham Road",
    "iso:country":"GB",
    "sg:address":"Thakeham Road, Storrington",
    "sg:city":"Pulborough",
    "sg:classifiers":[
        {
            "category":"Autos & Motor Vehicles",
            "subcategory":"Automobile Sales",
            "type":"Retail Goods"
        },
        {
            "category":"Retail",
            "subcategory":"Auto Repair",
            "type":"Services"
        }
    ],
    "sg:phone":"+44 1903 740928",
    "sg:postcode":"RH20 3PP",
    "sg:province":"West Sussex",
    "sg:tags":[
        "body",
        "car"
    ],
    "wof:name":"Rice Adrian",
    "wof:placetype":"venue"
},
  "geometry": {"coordinates":[-0.426565,50.945549],"type":"Point"}
}