{
  "type": "Feature",
  "properties": {
    "addr:full":"8-10 St Martins Square Leicester Leicestershire LE1 5DF",
    "addr:housenumber":"8-10",
    "addr:postcode":"le1 5df",
    "addr:street":"St Martins Square",
    "iso:country":"GB",
    "sg:address":"8-10 St Martins Square",
    "sg:city":"Leicester",
    "sg:classifiers":[
        {
            "category":"Shopping",
            "subcategory":"Clothing, Apparel, & Fashions",
            "type":"Retail Goods"
        }
    ],
    "sg:postcode":"LE1 5DF",
    "sg:province":"Leicestershire",
    "sg:tags":[
        "shop"
    ],
    "wof:name":"The Sweater Shop Group Ltd.",
    "wof:placetype":"venue"
},
  "geometry": {"coordinates":[-1.136466,52.634144],"type":"Point"}
}