{
  "type": "Feature",
  "properties": {
    "addr:full":"Claypits Farm, School Lane, Winfrith Newburgh Dorchester Dorset DT2 8JX",
    "addr:postcode":"dt2 8jx",
    "addr:street":"School Lane",
    "iso:country":"GB",
    "sg:address":"Claypits Farm, School Lane, Winfrith Newburgh",
    "sg:city":"Dorchester",
    "sg:classifiers":[
        {
            "category":"Shopping",
            "subcategory":"Jewelry",
            "type":"Retail Goods"
        },
        {
            "category":"Professional",
            "subcategory":"Art Services",
            "type":"Services"
        }
    ],
    "sg:phone":"+44 1305 852803",
    "sg:postcode":"DT2 8JX",
    "sg:province":"Dorset",
    "sg:tags":[
        "carver",
        "sculptor",
        "sale",
        "jewellery"
    ],
    "wof:name":"Harriet Glen Design",
    "wof:placetype":"venue"
},
  "geometry": {"coordinates":[-2.2699,50.662689],"type":"Point"}
}