{
  "type": "Feature",
  "properties": {
    "addr:full":"6 Ranelagh Drive South Liverpool Merseyside L19 9DR",
    "addr:housenumber":"6",
    "addr:postcode":"l19 9dr",
    "addr:street":"Ranelagh Drive South",
    "iso:country":"GB",
    "sg:address":"6 Ranelagh Drive South",
    "sg:city":"Liverpool",
    "sg:classifiers":[
        {
            "category":"Health Services",
            "subcategory":"Health Practitioner",
            "type":"Services"
        }
    ],
    "sg:phone":"+44 151 427 9248",
    "sg:postcode":"L19 9DR",
    "sg:province":"Merseyside",
    "sg:tags":[
        "hypnotherapists"
    ],
    "wof:name":"Kate Rawlinson",
    "wof:placetype":"venue"
},
  "geometry": {"coordinates":[-2.9137060642,53.3629684448],"type":"Point"}
}