{
  "type": "Feature",
  "properties": {
    "iso:country":"GB",
    "sg:address":"Cedars Farm, Broadwas-upon-teme",
    "sg:city":"Worcester",
    "sg:classifiers":[
        {
            "category":"Building & Trades",
            "subcategory":"Construction",
            "type":"Services"
        }
    ],
    "sg:postcode":"WR6 5NE",
    "sg:province":"Herefordshire",
    "sg:tags":[
        "joinery"
    ],
    "wof:name":"P Brooke",
    "wof:placetype":"venue"
},
  "geometry": {"coordinates":[-2.349366,52.194145],"type":"Point"}
}