{
  "type": "Feature",
  "properties": {
    "iso:country":"GB",
    "sg:address":"305 Wolverhampton Road",
    "sg:city":"Walsall",
    "sg:classifiers":[
        {
            "category":"Shopping",
            "subcategory":"News",
            "type":"Retail Goods"
        }
    ],
    "sg:phone":"+44 1922 637275",
    "sg:postcode":"WS2 8RL",
    "sg:province":"West Midlands",
    "sg:tags":[
        "newsagent"
    ],
    "wof:name":"Jas's News",
    "wof:placetype":"venue"
},
  "geometry": {"coordinates":[-2.00719,52.587067],"type":"Point"}
}