{
  "type": "Feature",
  "properties": {
    "addr:full":"28 Calonne Rd Wimbledon Greater London SW19 5HJ",
    "addr:housenumber":"28",
    "addr:postcode":"sw19 5hj",
    "addr:street":"Calonne Rd",
    "iso:country":"GB",
    "sg:address":"28 Calonne Rd",
    "sg:city":"Wimbledon",
    "sg:classifiers":[
        {
            "category":"Professional",
            "type":"Services"
        }
    ],
    "sg:phone":"+44 20 8944 9430",
    "sg:postcode":"SW19 5HJ",
    "sg:province":"Greater London",
    "sg:tags":[
        "entertainer"
    ],
    "wof:name":"Monte Carlo Fun Casino",
    "wof:placetype":"venue"
},
  "geometry": {"coordinates":[-0.2195159942,51.4312095642],"type":"Point"}
}