{
  "type": "Feature",
  "properties": {
    "iso:country":"GB",
    "sg:address":"47 London Road",
    "sg:city":"Beccles",
    "sg:classifiers":[
        {
            "category":"Professional",
            "type":"Services"
        }
    ],
    "sg:phone":"+44 1502 717478",
    "sg:postcode":"NR34 9YR",
    "sg:province":"Norfolk",
    "sg:tags":[
        "interior",
        "furnishers",
        "designer"
    ],
    "wof:name":"Quinlan Design Consultants",
    "wof:placetype":"venue"
},
  "geometry": {"coordinates":[1.564037,52.451157],"type":"Point"}
}