{
  "type": "Feature",
  "properties": {
    "addr:full":"79 Idle Road Bradford West Yorkshire BD2 4NT",
    "addr:housenumber":"79",
    "addr:postcode":"bd2 4nt",
    "addr:street":"Idle Road",
    "iso:country":"GB",
    "sg:address":"79 Idle Road",
    "sg:city":"Bradford",
    "sg:classifiers":[
        {
            "category":"Professional",
            "subcategory":"Detective & Security Services",
            "type":"Services"
        }
    ],
    "sg:phone":"+44 1274 626322",
    "sg:postcode":"BD2 4NT",
    "sg:province":"West Yorkshire",
    "sg:tags":[
        "locksmith"
    ],
    "wof:name":"Michael Hiles Security",
    "wof:placetype":"venue"
},
  "geometry": {"coordinates":[-1.7332049608,53.809589386],"type":"Point"}
}