{
  "type": "Feature",
  "properties": {
    "iso:country":"GB",
    "sg:address":"Byron House, 2a Lower Road",
    "sg:city":"Kenley",
    "sg:classifiers":[
        {
            "category":"Professional",
            "type":"Services"
        }
    ],
    "sg:phone":"+44 20 8660 9999",
    "sg:postcode":"CR8 5NB",
    "sg:province":"Surrey",
    "sg:tags":[
        "repair",
        "tech",
        "maintenance"
    ],
    "wof:name":"Amsys Ltd.",
    "wof:placetype":"venue"
},
  "geometry": {"coordinates":[-0.1086819991,51.3297576904],"type":"Point"}
}