{
  "type": "Feature",
  "properties": {
    "addr:full":"Green Shadows, 26 Portsmouth Rd Camberley Berkshire GU15 1JX",
    "addr:housenumber":"26",
    "addr:postcode":"gu15 1jx",
    "addr:street":"Green;Portsmouth Rd",
    "iso:country":"GB",
    "sg:address":"Green Shadows, 26 Portsmouth Rd",
    "sg:city":"Camberley",
    "sg:classifiers":[
        {
            "category":"Shopping",
            "subcategory":"Bicycles & Sporting Goods",
            "type":"Retail Goods"
        }
    ],
    "sg:phone":"+44 1276 65793",
    "sg:postcode":"GU15 1JX",
    "sg:province":"Berkshire",
    "sg:tags":[
        "equipment",
        "gym",
        "sport"
    ],
    "wof:name":"Beck & Deane Sports Hire Ltd",
    "wof:placetype":"venue"
},
  "geometry": {"coordinates":[-0.7342299819,51.3362159729],"type":"Point"}
}