{
  "type": "Feature",
  "properties": {
    "addr:full":"Stirling Enterprise Pk Stirling Falkirk FK7 7RP",
    "addr:postcode":"fk7 7rp",
    "addr:street":"Pk Stirling",
    "iso:country":"GB",
    "sg:address":"Stirling Enterprise Pk",
    "sg:city":"Stirling",
    "sg:classifiers":[
        {
            "category":"Communications",
            "subcategory":"Film & Video Production",
            "type":"Services"
        }
    ],
    "sg:phone":"+44 1786 472121",
    "sg:postcode":"FK7 7RP",
    "sg:province":"Falkirk",
    "sg:tags":[
        "illustrator",
        "artist"
    ],
    "wof:name":"Graham Baxter Fine Art",
    "wof:placetype":"venue"
},
  "geometry": {"coordinates":[-3.9056990147,56.1088790894],"type":"Point"}
}