{
  "type": "Feature",
  "properties": {
    "addr:full":"Unit 3b, Plumtree Farm Industrial Estate Doncaster South Yorkshire DN11 8EW",
    "addr:housenumber":"unit 3b plumtree farm industrial estate doncaster",
    "addr:postcode":"dn11 8ew",
    "addr:street":"South Yorkshire",
    "iso:country":"GB",
    "sg:address":"Unit 3b, Plumtree Farm Industrial Estate",
    "sg:city":"Doncaster",
    "sg:classifiers":[
        {
            "category":"Wholesale",
            "subcategory":"Construction Materials",
            "type":"Manufacturing & Wholesale Goods"
        }
    ],
    "sg:phone":"+44 1302 711552",
    "sg:postcode":"DN11 8EW",
    "sg:province":"South Yorkshire",
    "sg:tags":[
        "lift"
    ],
    "wof:name":"Lifting Equipment Services",
    "wof:placetype":"venue"
},
  "geometry": {"coordinates":[-1.0494940281,53.4264717102],"type":"Point"}
}