{
  "type": "Feature",
  "properties": {
    "iso:country":"GB",
    "sg:address":"Borough Farm, Burgh Common",
    "sg:city":"Attleborough",
    "sg:classifiers":[
        {
            "category":"Farming",
            "subcategory":"Farm",
            "type":"Manufacturing & Wholesale Goods"
        }
    ],
    "sg:postcode":"NR17 1QF",
    "sg:province":"Norfolk",
    "sg:tags":[
        "mixed",
        "crop"
    ],
    "wof:name":"K R West",
    "wof:placetype":"venue"
},
  "geometry": {"coordinates":[1.014435,52.519054],"type":"Point"}
}