{
  "type": "Feature",
  "properties": {
    "iso:country":"GB",
    "sg:address":"9 Head Street",
    "sg:city":"Halstead",
    "sg:classifiers":[
        {
            "category":"Shopping",
            "subcategory":"Used Merchandise",
            "type":"Retail Goods"
        }
    ],
    "sg:phone":"+44 1787 476273",
    "sg:postcode":"CO9 2AT",
    "sg:province":"Essex",
    "sg:tags":[
        "furniture"
    ],
    "wof:name":"Appleton Allsorts",
    "wof:placetype":"venue"
},
  "geometry": {"coordinates":[0.639579,51.945496],"type":"Point"}
}