{
  "type": "Feature",
  "properties": {
    "iso:country":"GB",
    "sg:address":"Duthie Park, Workshops, Great Southern Rd",
    "sg:city":"Aberdeen",
    "sg:classifiers":[
        {
            "category":"Government",
            "subcategory":"Office",
            "type":"Public Place"
        }
    ],
    "sg:phone":"+44 1224 588089",
    "sg:postcode":"AB10 6BH",
    "sg:province":"Aberdeen City",
    "sg:tags":[
        "local"
    ],
    "wof:name":"City of Aberdeen District Council",
    "wof:placetype":"venue"
},
  "geometry": {"coordinates":[-2.12389,57.135929],"type":"Point"}
}