{
  "type": "Feature",
  "properties": {
    "addr:full":"12 Thorkhill Road Thames Ditton Surrey KT7 0UE",
    "addr:housenumber":"12",
    "addr:postcode":"kt7 0ue",
    "addr:street":"Thorkhill Road",
    "iso:country":"GB",
    "sg:address":"12 Thorkhill Road",
    "sg:city":"Thames Ditton",
    "sg:classifiers":[
        {
            "category":"Building & Trades",
            "subcategory":"Landscaping Services",
            "type":"Services"
        }
    ],
    "sg:phone":"+44 1737 246366",
    "sg:postcode":"KT7 0UE",
    "sg:province":"Surrey",
    "sg:tags":[
        "preservation",
        "timber"
    ],
    "wof:name":"Tapco (Preservation) Ltd.",
    "wof:placetype":"venue"
},
  "geometry": {"coordinates":[-0.3253909945,51.3889045715],"type":"Point"}
}