{
  "type": "Feature",
  "properties": {
    "iso:country":"GB",
    "sg:address":"22 St John Street",
    "sg:city":"Perth",
    "sg:classifiers":[
        {
            "category":"Organizations",
            "subcategory":"Membership Organization",
            "type":"Services"
        }
    ],
    "sg:phone":"+44 870 321 3474",
    "sg:postcode":"PH1 5SP",
    "sg:province":"Perth and Kinross",
    "sg:tags":[
        "club"
    ],
    "wof:name":"Laird Management Ltd.",
    "wof:placetype":"venue"
},
  "geometry": {"coordinates":[-3.42726,56.396446],"type":"Point"}
}