{
  "type": "Feature",
  "properties": {
    "iso:country":"GB",
    "sg:address":"85 Leaford Crescent",
    "sg:city":"Watford",
    "sg:classifiers":[
        {
            "category":"Building & Trades",
            "subcategory":"Plumbing",
            "type":"Services"
        }
    ],
    "sg:phone":"+44 1923 233290",
    "sg:postcode":"WD2 5JQ",
    "sg:province":"Hertfordshire",
    "sg:tags":[
        "heating"
    ],
    "wof:name":"Pulcris Plumbing Services",
    "wof:placetype":"venue"
},
  "geometry": {"coordinates":[-0.413163,51.678631],"type":"Point"}
}