{
  "type": "Feature",
  "properties": {
    "addr:full":"Islington Road Trowbridge Wiltshire BA14 8QJ",
    "addr:postcode":"ba14 8qj",
    "addr:street":"Islington Road",
    "iso:country":"GB",
    "sg:address":"Islington Road",
    "sg:city":"Trowbridge",
    "sg:classifiers":[
        {
            "category":"Home & Garden",
            "subcategory":"Garden Supply",
            "type":"Retail Goods"
        }
    ],
    "sg:phone":"+44 1225 768977",
    "sg:postcode":"BA14 8QJ",
    "sg:province":"Wiltshire",
    "sg:tags":[
        "nursery",
        "centre"
    ],
    "wof:name":"Palmer Gardens Plant Centre",
    "wof:placetype":"venue"
},
  "geometry": {"coordinates":[-2.2042291164,51.3270301819],"type":"Point"}
}