{
  "type": "Feature",
  "properties": {
    "addr:full":"684a Old Dalkeith Rd, Danderhall Dalkeith City of Edinburgh EH22 1RR",
    "addr:housenumber":"684a",
    "addr:postcode":"eh22 1rr",
    "addr:street":"Old Dalkeith Rd",
    "iso:country":"GB",
    "sg:address":"684a Old Dalkeith Rd, Danderhall",
    "sg:city":"Dalkeith",
    "sg:classifiers":[
        {
            "category":"Retail",
            "subcategory":"Auto Repair",
            "type":"Services"
        }
    ],
    "sg:postcode":"EH22 1RR",
    "sg:province":"City of Edinburgh",
    "sg:tags":[
        "modification",
        "garage"
    ],
    "wof:name":"Dix,James,",
    "wof:placetype":"venue"
},
  "geometry": {"coordinates":[-3.097839,55.90398],"type":"Point"}
}