{
  "type": "Feature",
  "properties": {
    "iso:country":"GB",
    "sg:address":"250-251 Coronation Rd",
    "sg:city":"Bristol",
    "sg:classifiers":[
        {
            "category":"Home & Garden",
            "subcategory":"Furniture",
            "type":"Retail Goods"
        }
    ],
    "sg:phone":"+44 117 953 3286",
    "sg:postcode":"BS3 1RL",
    "sg:province":"City of Bristol",
    "wof:name":"Interiorscapes",
    "wof:placetype":"venue"
},
  "geometry": {"coordinates":[-2.6158280373,51.4447631836],"type":"Point"}
}