{
  "type": "Feature",
  "properties": {
    "iso:country":"GB",
    "sg:address":"124 Leander Drive",
    "sg:city":"Rochdale",
    "sg:classifiers":[
        {
            "category":"Building & Trades",
            "subcategory":"Construction",
            "type":"Services"
        }
    ],
    "sg:phone":"+44 1706 658780",
    "sg:postcode":"OL11 2XE",
    "sg:province":"Lancashire",
    "sg:tags":[
        "contractor",
        "paving",
        "driveway"
    ],
    "wof:name":"B & J Flagging",
    "wof:placetype":"venue"
},
  "geometry": {"coordinates":[-2.171889,53.587727],"type":"Point"}
}