{
  "type": "Feature",
  "properties": {
    "addr:full":"13 High St Clay Cross, Chesterfield Derby Derbyshire S45 9DX",
    "addr:housenumber":"13",
    "addr:postcode":"s45 9dx",
    "addr:street":"High St",
    "iso:country":"GB",
    "sg:address":"13 High St Clay Cross, Chesterfield",
    "sg:city":"Derby",
    "sg:classifiers":[
        {
            "category":"Retail",
            "subcategory":"Funeral Services",
            "type":"Services"
        }
    ],
    "sg:phone":"+44 1246 862142",
    "sg:postcode":"S45 9DX",
    "sg:province":"Derbyshire",
    "wof:name":"W Stoppard & Son",
    "wof:placetype":"venue"
},
  "geometry": {"coordinates":[-1.4163980484,53.1703300476],"type":"Point"}
}