{
  "type": "Feature",
  "properties": {
    "addr:full":"Stockwell Head Hinckley Leicestershire LE10 1RG",
    "addr:postcode":"le10 1rg",
    "addr:street":"Stockwell",
    "iso:country":"GB",
    "sg:address":"Stockwell Head",
    "sg:city":"Hinckley",
    "sg:classifiers":[
        {
            "category":"Retail",
            "subcategory":"Repair Shop",
            "type":"Services"
        }
    ],
    "sg:postcode":"LE10 1RG",
    "sg:province":"Leicestershire",
    "sg:tags":[
        "radio",
        "television",
        "video"
    ],
    "wof:name":"Q M N Electronics",
    "wof:placetype":"venue"
},
  "geometry": {"coordinates":[-1.3707079887,52.5425872803],"type":"Point"}
}