{
  "type": "Feature",
  "properties": {
    "iso:country":"GB",
    "sg:address":"Unit 3 Bridge Park Road, Thurmaston",
    "sg:city":"Leicester",
    "sg:classifiers":[
        {
            "category":"Manufacturing",
            "subcategory":"Textiles",
            "type":"Manufacturing & Wholesale Goods"
        }
    ],
    "sg:phone":"+44 116 269 5073",
    "sg:postcode":"LE4 8BL",
    "sg:province":"Leicestershire",
    "sg:tags":[
        "made-up"
    ],
    "wof:name":"Jordan Lovatt & Jones Ltd.",
    "wof:placetype":"venue"
},
  "geometry": {"coordinates":[-1.103599,52.676334],"type":"Point"}
}