{
  "type": "Feature",
  "properties": {
    "iso:country":"GB",
    "sg:address":"19 London End",
    "sg:city":"Beaconsfield",
    "sg:classifiers":[
        {
            "category":"Professional",
            "subcategory":"Management & Consulting",
            "type":"Services"
        },
        {
            "category":"Organizations",
            "subcategory":"Community Association",
            "type":"Services"
        }
    ],
    "sg:phone":"+44 1494 670444",
    "sg:postcode":"HP9 2HN",
    "sg:province":"Buckinghamshire",
    "sg:tags":[
        "consultant",
        "relation",
        "public"
    ],
    "wof:name":"Storm Communications Ltd.",
    "wof:placetype":"venue"
},
  "geometry": {"coordinates":[-0.636063,51.602013],"type":"Point"}
}