{
  "type": "Feature",
  "properties": {
    "iso:country":"GB",
    "sg:address":"120 Leman Street",
    "sg:city":"London",
    "sg:classifiers":[
        {
            "category":"Manufacturing",
            "subcategory":"Tools & Machinery",
            "type":"Manufacturing & Wholesale Goods"
        }
    ],
    "sg:phone":"+44 20 7972 0011",
    "sg:postcode":"E1 8EU",
    "sg:province":"Greater London",
    "sg:tags":[
        "society",
        "friendly"
    ],
    "wof:name":"Albis Associates Ltd.",
    "wof:placetype":"venue"
},
  "geometry": {"coordinates":[-0.068803,51.511372],"type":"Point"}
}