{
  "type": "Feature",
  "properties": {
    "addr:full":"94 High St Doncaster South Yorkshire DN7 4BX",
    "addr:housenumber":"94",
    "addr:postcode":"dn7 4bx",
    "addr:street":"High St",
    "iso:country":"GB",
    "sg:address":"94 High St",
    "sg:city":"Doncaster",
    "sg:classifiers":[
        {
            "category":"Personal",
            "subcategory":"Beauty Salon",
            "type":"Services"
        }
    ],
    "sg:phone":"+44 1302 887801",
    "sg:postcode":"DN7 4BX",
    "sg:province":"South Yorkshire",
    "sg:tags":[
        "unisex",
        "hairdresser"
    ],
    "wof:name":"Top Crop Hair Studio",
    "wof:placetype":"venue"
},
  "geometry": {"coordinates":[-1.026077,53.562737],"type":"Point"}
}