{
  "type": "Feature",
  "properties": {
    "addr:full":"7 Pond Rd Blackheath Greater London SE3 9JL",
    "addr:housenumber":"7",
    "addr:postcode":"se3 9jl",
    "addr:street":"Pond Rd",
    "iso:country":"GB",
    "sg:address":"7 Pond Rd",
    "sg:city":"Blackheath",
    "sg:classifiers":[
        {
            "category":"Organizations",
            "subcategory":"Community Association",
            "type":"Services"
        }
    ],
    "sg:phone":"+44 20 8852 4732",
    "sg:postcode":"SE3 9JL",
    "sg:province":"Greater London",
    "sg:tags":[
        "relation",
        "public"
    ],
    "wof:name":"Abbott Banks Ltd",
    "wof:placetype":"venue"
},
  "geometry": {"coordinates":[0.013334,51.466347],"type":"Point"}
}