{
  "type": "Feature",
  "properties": {
    "iso:country":"GB",
    "sg:address":"Transport Ho, Nelson St",
    "sg:city":"Deeside",
    "sg:classifiers":[
        {
            "category":"Wholesale",
            "subcategory":"Sporting Goods",
            "type":"Manufacturing & Wholesale Goods"
        }
    ],
    "sg:phone":"+44 1244 831765",
    "sg:postcode":"CH5 1DH",
    "sg:province":"Flintshire",
    "sg:tags":[
        "wholesaler",
        "mnfrs",
        "cycle"
    ],
    "wof:name":"Velosave Wholesale Supplies",
    "wof:placetype":"venue"
},
  "geometry": {"coordinates":[-3.024988,53.20248],"type":"Point"}
}