{
  "type": "Feature",
  "properties": {
    "addr:full":"Plymouthwood Road Cardiff Cardiff CF5 4XD",
    "addr:postcode":"cf5 4xd",
    "addr:street":"Plymouthwood Road",
    "iso:country":"GB",
    "sg:address":"Plymouthwood Road",
    "sg:city":"Cardiff",
    "sg:classifiers":[
        {
            "category":"Education",
            "subcategory":"School",
            "type":"Public Place"
        },
        {
            "category":"Government",
            "subcategory":"Office",
            "type":"Public Place"
        }
    ],
    "sg:phone":"+44 29 2056 1115",
    "sg:postcode":"CF5 4XD",
    "sg:province":"Cardiff",
    "sg:tags":[
        "local",
        "authority"
    ],
    "wof:name":"Herbert Thompson County Junior School",
    "wof:placetype":"venue"
},
  "geometry": {"coordinates":[-3.2404201031,51.4842567444],"type":"Point"}
}