{
  "type": "Feature",
  "properties": {
    "addr:full":"86 South Road Southall Greater London UB1 1RD",
    "addr:housenumber":"86",
    "addr:postcode":"ub1 1rd",
    "addr:street":"South Road",
    "iso:country":"GB",
    "sg:address":"86 South Road",
    "sg:city":"Southall",
    "sg:classifiers":[
        {
            "category":"Professional",
            "subcategory":"Lawyer & Legal Services",
            "type":"Services"
        }
    ],
    "sg:phone":"+44 20 8551 1661",
    "sg:postcode":"UB1 1RD",
    "sg:province":"Greater London",
    "sg:tags":[
        "solicitor"
    ],
    "wof:name":"NATHAN & CO",
    "wof:placetype":"venue"
},
  "geometry": {"coordinates":[-0.3780370057,51.5080032349],"type":"Point"}
}