{
  "type": "Feature",
  "properties": {
    "addr:full":"17 George Street Warminster Somerset BA12 8QA",
    "addr:housenumber":"17",
    "addr:postcode":"ba12 8qa",
    "addr:street":"George Street",
    "iso:country":"GB",
    "sg:address":"17 George Street",
    "sg:city":"Warminster",
    "sg:classifiers":[
        {
            "category":"Home & Garden",
            "subcategory":"Furniture",
            "type":"Retail Goods"
        }
    ],
    "sg:phone":"+44 1985 846679",
    "sg:postcode":"BA12 8QA",
    "sg:province":"Somerset",
    "wof:name":"Home Style Furnishers",
    "wof:placetype":"venue"
},
  "geometry": {"coordinates":[-2.1852419376,51.2052383423],"type":"Point"}
}