{
  "type": "Feature",
  "properties": {
    "addr:full":"Unit 1 Cedar Road Paignton Devon TQ3 2DB",
    "addr:housenumber":"unit 1",
    "addr:postcode":"tq3 2db",
    "addr:street":"Cedar Road",
    "iso:country":"GB",
    "sg:address":"Unit 1 Cedar Road",
    "sg:city":"Paignton",
    "sg:classifiers":[
        {
            "category":"Retail",
            "subcategory":"Repair Shop",
            "type":"Services"
        }
    ],
    "sg:phone":"+44 1803 553700",
    "sg:postcode":"TQ3 2DB",
    "sg:province":"Devon",
    "sg:tags":[
        "maintenance"
    ],
    "wof:name":"First Call (South West) Ltd.",
    "wof:placetype":"venue"
},
  "geometry": {"coordinates":[-3.557847023,50.4489479065],"type":"Point"}
}