{
  "type": "Feature",
  "properties": {
    "addr:full":"16 Alexandra Road, Waterloo Liverpool Merseyside L22 1RJ",
    "addr:housenumber":"16",
    "addr:postcode":"l22 1rj",
    "addr:street":"Alexandra Road",
    "iso:country":"GB",
    "sg:address":"16 Alexandra Road, Waterloo",
    "sg:city":"Liverpool",
    "sg:classifiers":[
        {
            "category":"Social Services",
            "subcategory":"Retirement Home",
            "type":"Services"
        }
    ],
    "sg:postcode":"L22 1RJ",
    "sg:province":"Merseyside",
    "sg:tags":[
        "rest"
    ],
    "wof:name":"Oakwood House Rest Home",
    "wof:placetype":"venue"
},
  "geometry": {"coordinates":[-3.022069931,53.4716720581],"type":"Point"}
}