{
  "type": "Feature",
  "properties": {
    "iso:country":"GB",
    "sg:address":"1 Worcester St",
    "sg:city":"Monmouth",
    "sg:classifiers":[
        {
            "category":"Shopping",
            "subcategory":"Clothing, Apparel, & Fashions",
            "type":"Retail Goods"
        }
    ],
    "sg:postcode":"NP25 3DF",
    "sg:province":"Gloucestershire",
    "sg:tags":[
        "t-shirt"
    ],
    "wof:name":"Webb,M,",
    "wof:placetype":"venue"
},
  "geometry": {"coordinates":[-2.7131750584,51.8118553162],"type":"Point"}
}