{
  "type": "Feature",
  "properties": {
    "addr:full":"35 St Helens Park Road Hastings East Sussex TN34 2DN",
    "addr:housenumber":"35",
    "addr:postcode":"tn34 2dn",
    "addr:street":"St;Park Road",
    "iso:country":"GB",
    "sg:address":"35 St Helens Park Road",
    "sg:city":"Hastings",
    "sg:classifiers":[
        {
            "category":"Government",
            "subcategory":"Fire Station",
            "type":"Public Place"
        }
    ],
    "sg:phone":"+44 1424 423468",
    "sg:postcode":"TN34 2DN",
    "sg:province":"East Sussex",
    "sg:tags":[
        "security"
    ],
    "wof:name":"D B Fire Consultants",
    "wof:placetype":"venue"
},
  "geometry": {"coordinates":[0.578159,50.868214],"type":"Point"}
}