{
  "type": "Feature",
  "properties": {
    "iso:country":"GB",
    "sg:address":"P O Box 137",
    "sg:city":"Newark",
    "sg:classifiers":[
        {
            "category":"Professional",
            "subcategory":"Employment Agencies",
            "type":"Services"
        }
    ],
    "sg:phone":"+44 870 513 4396",
    "sg:postcode":"NG24 1TL",
    "sg:province":"Nottinghamshire",
    "sg:tags":[
        "consultant"
    ],
    "wof:name":"Henlys Appointments",
    "wof:placetype":"venue"
},
  "geometry": {"coordinates":[-0.805866,53.076843],"type":"Point"}
}