{
  "type": "Feature",
  "properties": {
    "addr:full":"Smallmead House, Smallmead Horley Surrey RH6 9AX",
    "addr:postcode":"rh6 9ax",
    "addr:street":"Smallmead",
    "iso:country":"GB",
    "sg:address":"Smallmead House, Smallmead",
    "sg:city":"Horley",
    "sg:classifiers":[
        {
            "category":"Shopping",
            "subcategory":"Computers & Home Electronics",
            "type":"Retail Goods"
        }
    ],
    "sg:phone":"+44 1293 435400",
    "sg:postcode":"RH6 9AX",
    "sg:province":"Surrey",
    "wof:name":"Instant Products",
    "wof:placetype":"venue"
},
  "geometry": {"coordinates":[-0.1561760008,51.1737480164],"type":"Point"}
}