{
  "type": "Feature",
  "properties": {
    "addr:full":"283 Hawthorn Drive Ipswich Suffolk IP2 0QG",
    "addr:housenumber":"283",
    "addr:postcode":"ip2 0qg",
    "addr:street":"Hawthorn Drive",
    "iso:country":"GB",
    "sg:address":"283 Hawthorn Drive",
    "sg:city":"Ipswich",
    "sg:classifiers":[
        {
            "category":"Personal",
            "subcategory":"Beauty Salon",
            "type":"Services"
        },
        {
            "category":"Personal",
            "subcategory":"Barber",
            "type":"Services"
        }
    ],
    "sg:phone":"+44 1473 685912",
    "sg:postcode":"IP2 0QG",
    "sg:province":"Suffolk",
    "sg:tags":[
        "unisex",
        "hairdresser"
    ],
    "wof:name":"Top Shop Hair Salon",
    "wof:placetype":"venue"
},
  "geometry": {"coordinates":[1.1223579645,52.0459022522],"type":"Point"}
}