{
  "type": "Feature",
  "properties": {
    "iso:country":"GB",
    "sg:address":"Lloyds Bank Chambers, High Street",
    "sg:city":"Lechlade",
    "sg:classifiers":[
        {
            "category":"Professional",
            "subcategory":"Accounting & Tax Preparation",
            "type":"Services"
        }
    ],
    "sg:phone":"+44 1367 252362",
    "sg:postcode":"GL7 3AE",
    "sg:province":"Gloucestershire",
    "sg:tags":[
        "accountant"
    ],
    "wof:name":"Baulcombe & Co",
    "wof:placetype":"venue"
},
  "geometry": {"coordinates":[-1.6919089556,51.6940765381],"type":"Point"}
}