{
  "type": "Feature",
  "properties": {
    "addr:full":"Unit 7 Romney House Industrial Est , Wol Wednesbury West Midlands WS10 8UB",
    "addr:housenumber":"unit 7 romney house",
    "addr:postcode":"ws10 8ub",
    "addr:street":"Industrial Est;Wednesbury",
    "iso:country":"GB",
    "sg:address":"Unit 7 Romney House Industrial Est , Wol",
    "sg:city":"Wednesbury",
    "sg:classifiers":[
        {
            "category":"Home & Garden",
            "subcategory":"Hardware",
            "type":"Retail Goods"
        }
    ],
    "sg:postcode":"WS10 8UB",
    "sg:province":"West Midlands",
    "sg:tags":[
        "device",
        "fixing",
        "fastener"
    ],
    "wof:name":"Oakwood Manufacturing Limited",
    "wof:placetype":"venue"
},
  "geometry": {"coordinates":[-2.0192539692,52.5527305603],"type":"Point"}
}