{
  "type": "Feature",
  "properties": {
    "addr:full":"Unit 4 Astley Centre, Bolton St Chorley Lancashire PR7 3DX",
    "addr:housenumber":"unit 4",
    "addr:postcode":"pr7 3dx",
    "addr:street":"Bolton St",
    "iso:country":"GB",
    "sg:address":"Unit 4 Astley Centre, Bolton St",
    "sg:city":"Chorley",
    "sg:classifiers":[
        {
            "category":"Utilities",
            "type":"Services"
        }
    ],
    "sg:phone":"+44 1257 414243",
    "sg:postcode":"PR7 3DX",
    "sg:province":"Lancashire",
    "sg:tags":[
        "connection",
        "provider",
        "internet"
    ],
    "wof:name":"Cyberquest",
    "wof:placetype":"venue"
},
  "geometry": {"coordinates":[-2.6321339607,53.6520881653],"type":"Point"}
}