{
  "type": "Feature",
  "properties": {
    "addr:full":"Liberty House, Liberty Business Park, Attleborough Nuneaton Leicestershire CV11 6RZ",
    "addr:postcode":"cv11 6rz",
    "addr:street":"Liberty Business Park",
    "iso:country":"GB",
    "sg:address":"Liberty House, Liberty Business Park, Attleborough",
    "sg:city":"Nuneaton",
    "sg:classifiers":[
        {
            "category":"Manufacturing",
            "subcategory":"Building Materials",
            "type":"Manufacturing & Wholesale Goods"
        }
    ],
    "sg:phone":"+44 24 7664 1777",
    "sg:postcode":"CV11 6RZ",
    "sg:province":"Leicestershire",
    "sg:tags":[
        "merchant",
        "builder"
    ],
    "wof:name":"Peter Savage Ltd.",
    "wof:placetype":"venue"
},
  "geometry": {"coordinates":[-1.439103961,52.5223503113],"type":"Point"}
}