{
  "type": "Feature",
  "properties": {
    "iso:country":"GB",
    "sg:address":"196 Dudley Road",
    "sg:city":"Birmingham",
    "sg:classifiers":[
        {
            "category":"Fast Food",
            "type":"Food & Drink"
        }
    ],
    "sg:phone":"+44 121 454 9833",
    "sg:postcode":"B18 4NY",
    "sg:province":"West Midlands",
    "sg:tags":[
        "away",
        "take"
    ],
    "wof:name":"Summerfield Chippy",
    "wof:placetype":"venue"
},
  "geometry": {"coordinates":[-1.9393589497,52.4864501953],"type":"Point"}
}