{
  "type": "Feature",
  "properties": {
    "iso:country":"GB",
    "sg:address":"Churchill Close, Ettington",
    "sg:city":"Stratford-upon-avon",
    "sg:classifiers":[
        {
            "category":"Education",
            "subcategory":"School",
            "type":"Public Place"
        }
    ],
    "sg:phone":"+44 1789 740919",
    "sg:postcode":"CV37 7SP",
    "sg:province":"Warwickshire",
    "sg:tags":[
        "local",
        "authority"
    ],
    "wof:name":"Ettington C Of E Primary School",
    "wof:placetype":"venue"
},
  "geometry": {"coordinates":[-1.608049,52.137959],"type":"Point"}
}