{
  "type": "Feature",
  "properties": {
    "iso:country":"GB",
    "sg:address":"Harks Lane",
    "sg:city":"Ventnor",
    "sg:classifiers":[
        {
            "category":"Autos & Motor Vehicles",
            "subcategory":"Automobile Sales",
            "type":"Retail Goods"
        }
    ],
    "sg:postcode":"PO38 3NY",
    "sg:province":"Isle of Wight",
    "sg:tags":[
        "car",
        "specialist",
        "sales",
        "classic"
    ],
    "wof:name":"B R Atkinson-Goffe",
    "wof:placetype":"venue"
},
  "geometry": {"coordinates":[-1.2004890442,50.5965270996],"type":"Point"}
}