{
  "type": "Feature",
  "properties": {
    "iso:country":"GB",
    "sg:address":"144 Stockport Road",
    "sg:city":"Cheadle",
    "sg:classifiers":[
        {
            "category":"Professional",
            "subcategory":"Management & Consulting",
            "type":"Services"
        }
    ],
    "sg:phone":"+44 161 428 2123",
    "sg:postcode":"SK8 2DP",
    "sg:province":"Cheshire",
    "sg:tags":[
        "consultant",
        "specialist"
    ],
    "wof:name":"Honeys Natural Beauty Clinic",
    "wof:placetype":"venue"
},
  "geometry": {"coordinates":[-2.204368,53.395252],"type":"Point"}
}