{
  "type": "Feature",
  "properties": {
    "addr:full":"270 Wickham Road Croydon Surrey CR0 8BJ",
    "addr:housenumber":"270",
    "addr:postcode":"cr0 8bj",
    "addr:street":"Wickham Road",
    "iso:country":"GB",
    "sg:address":"270 Wickham Road",
    "sg:city":"Croydon",
    "sg:classifiers":[
        {
            "category":"Taxi",
            "type":"Transportation"
        }
    ],
    "sg:phone":"+44 20 8656 5656",
    "sg:postcode":"CR0 8BJ",
    "sg:province":"Surrey",
    "sg:tags":[
        "mini",
        "cab"
    ],
    "wof:name":"Croydon Carrigae Co",
    "wof:placetype":"venue"
},
  "geometry": {"coordinates":[-0.046482,51.375141],"type":"Point"}
}