{
  "type": "Feature",
  "properties": {
    "iso:country":"GB",
    "sg:address":"22 Trees Road, Hughenden Valley",
    "sg:city":"High Wycombe",
    "sg:classifiers":[
        {
            "category":"Building & Trades",
            "subcategory":"Construction",
            "type":"Services"
        },
        {
            "category":"Military Area",
            "subcategory":"Air Force Base",
            "type":"Public Place"
        }
    ],
    "sg:phone":"+44 1494 564888",
    "sg:postcode":"HP14 4PW",
    "sg:province":"Buckinghamshire",
    "sg:tags":[
        "groundwork",
        "builder",
        "contractor"
    ],
    "wof:name":"David J Hester",
    "wof:placetype":"venue"
},
  "geometry": {"coordinates":[-0.755859,51.664749],"type":"Point"}
}