{
  "type": "Feature",
  "properties": {
    "iso:country":"GB",
    "sg:address":"Llynfa Penygawsi Day Nursery, Tirmeibion Lane, Llantrisant",
    "sg:city":"Pontyclun",
    "sg:classifiers":[
        {
            "category":"Farming",
            "subcategory":"Nursery",
            "type":"Manufacturing & Wholesale Goods"
        },
        {
            "category":"Government",
            "subcategory":"Office",
            "type":"Public Place"
        }
    ],
    "sg:postcode":"CF72 8DJ",
    "sg:province":"Bridgend",
    "sg:tags":[
        "local",
        "creche"
    ],
    "wof:name":"Llynfa Penygawsi Day Nursery",
    "wof:placetype":"venue"
},
  "geometry": {"coordinates":[-3.374301,51.540771],"type":"Point"}
}