{
  "type": "Feature",
  "properties": {
    "addr:full":"Unit 13 Hampshire Centre, Castle La Bournemouth Dorset BH8 9EW",
    "addr:housenumber":"unit 13",
    "addr:postcode":"bh8 9ew",
    "addr:street":"Hampshire Centre;La Bournemouth",
    "iso:country":"GB",
    "sg:address":"Unit 13 Hampshire Centre, Castle La",
    "sg:city":"Bournemouth",
    "sg:classifiers":[
        {
            "category":"Shopping",
            "subcategory":"Department Store",
            "type":"Retail Goods"
        }
    ],
    "sg:postcode":"BH8 9EW",
    "sg:province":"Dorset",
    "wof:name":"Centresport",
    "wof:placetype":"venue"
},
  "geometry": {"coordinates":[-1.860839963,50.7413291931],"type":"Point"}
}