{
  "type": "Feature",
  "properties": {
    "addr:full":"Pat Brook, Badley Wood, Whitbourne Worcester Herefordshire WR6 5SJ",
    "addr:postcode":"wr6 5sj",
    "addr:street":"Pat;Badley Wood",
    "iso:country":"GB",
    "sg:address":"Pat Brook, Badley Wood, Whitbourne",
    "sg:city":"Worcester",
    "sg:classifiers":[
        {
            "category":"Professional",
            "type":"Services"
        }
    ],
    "sg:phone":"+44 1886 821684",
    "sg:postcode":"WR6 5SJ",
    "sg:province":"Herefordshire",
    "sg:tags":[
        "entertainer"
    ],
    "wof:name":"Merry Wizard Magic Show",
    "wof:placetype":"venue"
},
  "geometry": {"coordinates":[-2.411139,52.208172],"type":"Point"}
}