{
  "type": "Feature",
  "properties": {
    "iso:country":"GB",
    "sg:address":"6 Claremont Avenue",
    "sg:city":"Stockport",
    "sg:classifiers":[
        {
            "category":"Personal",
            "type":"Services"
        }
    ],
    "sg:phone":"+44 161 431 4889",
    "sg:postcode":"SK4 4QR",
    "sg:province":"Cheshire",
    "sg:tags":[
        "wedding"
    ],
    "wof:name":"WEDDING PHOTOGRAPHY",
    "wof:placetype":"venue"
},
  "geometry": {"coordinates":[-2.178209,53.427559],"type":"Point"}
}