{
  "type": "Feature",
  "properties": {
    "iso:country":"GB",
    "sg:address":"Flat 1 33 Market Place, Longridge",
    "sg:city":"Preston",
    "sg:classifiers":[
        {
            "category":"Real Estate",
            "subcategory":"Architect",
            "type":"Services"
        }
    ],
    "sg:postcode":"PR3 3RR",
    "sg:province":"Lancashire",
    "wof:name":"Phil Charnock Engineering Ltd",
    "wof:placetype":"venue"
},
  "geometry": {"coordinates":[-2.601544,53.829071],"type":"Point"}
}