{
  "type": "Feature",
  "properties": {
    "iso:country":"GB",
    "sg:address":"Brandts Court Elstree Way",
    "sg:city":"Borehamwood",
    "sg:classifiers":[
        {
            "category":"Professional",
            "subcategory":"Computer Services",
            "type":"Services"
        }
    ],
    "sg:phone":"+44 20 8905 1555",
    "sg:postcode":"WD6 1JH",
    "sg:province":"Hertfordshire",
    "sg:tags":[
        "system",
        "software"
    ],
    "wof:name":"Foundation Systems",
    "wof:placetype":"venue"
},
  "geometry": {"coordinates":[-0.256754,51.659546],"type":"Point"}
}