{
  "type": "Feature",
  "properties": {
    "iso:country":"GB",
    "sg:address":"Pembroke Dock",
    "sg:city":"Pembroke Dock",
    "sg:classifiers":[
        {
            "category":"Home & Garden",
            "subcategory":"Garden Supply",
            "type":"Retail Goods"
        }
    ],
    "sg:phone":"+44 1646 621566",
    "sg:postcode":"SA72 4RX",
    "sg:province":"Pembrokeshire",
    "sg:tags":[
        "nursery",
        "centre"
    ],
    "wof:name":"Bangeston Farm Yard Garden Centre",
    "wof:placetype":"venue"
},
  "geometry": {"coordinates":[-4.942424,51.691856],"type":"Point"}
}