{
  "type": "Feature",
  "properties": {
    "iso:country":"GB",
    "sg:address":"Bird House, Bishops Wood Lane, Crossway Green",
    "sg:city":"Stourport On Severn",
    "sg:classifiers":[
        {
            "category":"Utilities",
            "subcategory":"Natural Gas",
            "type":"Services"
        }
    ],
    "sg:phone":"+44 1299 251200",
    "sg:postcode":"DY13 9SE",
    "sg:province":"Worcestershire",
    "sg:tags":[
        "control",
        "energy",
        "management",
        "system"
    ],
    "wof:name":"New Burn Services",
    "wof:placetype":"venue"
},
  "geometry": {"coordinates":[-2.2480020523,52.3139801025],"type":"Point"}
}