{
  "type": "Feature",
  "properties": {
    "addr:full":"Freight House, Kirkhill Place Aberdeen Aberdeen City AB21 0GU",
    "addr:postcode":"ab21 0gu",
    "addr:street":"Kirkhill Place",
    "iso:country":"GB",
    "sg:address":"Freight House, Kirkhill Place",
    "sg:city":"Aberdeen",
    "sg:classifiers":[
        {
            "category":"Freight",
            "type":"Transportation"
        }
    ],
    "sg:phone":"+44 1224 337733",
    "sg:postcode":"AB21 0GU",
    "sg:province":"Aberdeen City",
    "sg:tags":[
        "forwarders"
    ],
    "wof:name":"Petrasco Services Ltd.",
    "wof:placetype":"venue"
},
  "geometry": {"coordinates":[-2.212751,57.202412],"type":"Point"}
}