{
  "type": "Feature",
  "properties": {
    "iso:country":"GB",
    "sg:address":"Woolbarn Lawn",
    "sg:city":"Barnstaple",
    "sg:classifiers":[
        {
            "category":"Taxi",
            "type":"Transportation"
        }
    ],
    "sg:phone":"+44 1271 376619",
    "sg:postcode":"EX32 8PQ",
    "sg:province":"Devon",
    "sg:tags":[
        "mini",
        "cab"
    ],
    "wof:name":"Kevs Cabs",
    "wof:placetype":"venue"
},
  "geometry": {"coordinates":[-4.033144,51.075989],"type":"Point"}
}