{
  "type": "Feature",
  "properties": {
    "iso:country":"GB",
    "sg:address":"18 Parkway Centre",
    "sg:city":"Middlesbrough",
    "sg:classifiers":[
        {
            "category":"Food & Beverages",
            "subcategory":"Candy",
            "type":"Retail Goods"
        }
    ],
    "sg:phone":"+44 1642 595392",
    "sg:postcode":"TS8 0TJ",
    "sg:province":"North Yorkshire",
    "sg:tags":[
        "confectioner"
    ],
    "wof:name":"Cards 'R' Us",
    "wof:placetype":"venue"
},
  "geometry": {"coordinates":[-1.214304,54.523476],"type":"Point"}
}