{
  "type": "Feature",
  "properties": {
    "addr:full":"Church Row, Beckwithshaw Harrogate North Yorkshire HG3 1QW",
    "addr:postcode":"hg3 1qw",
    "iso:country":"GB",
    "sg:address":"Church Row, Beckwithshaw",
    "sg:city":"Harrogate",
    "sg:classifiers":[
        {
            "category":"Education",
            "subcategory":"School",
            "type":"Public Place"
        },
        {
            "category":"Government",
            "subcategory":"Office",
            "type":"Public Place"
        }
    ],
    "sg:phone":"+44 1423 504642",
    "sg:postcode":"HG3 1QW",
    "sg:province":"North Yorkshire",
    "sg:tags":[
        "local",
        "authority"
    ],
    "wof:name":"Beckwithshaw Community Primary School",
    "wof:placetype":"venue"
},
  "geometry": {"coordinates":[-1.5930030346,53.9738731384],"type":"Point"}
}