{
  "type": "Feature",
  "properties": {
    "iso:country":"GB",
    "sg:address":"51 Addison Road",
    "sg:city":"Mexborough",
    "sg:classifiers":[
        {
            "category":"Home & Garden",
            "subcategory":"Carpets & Floor Coverings",
            "type":"Retail Goods"
        }
    ],
    "sg:phone":"+44 1709 583290",
    "sg:postcode":"S64 0DH",
    "sg:province":"South Yorkshire",
    "sg:tags":[
        "cleaner",
        "upholstery"
    ],
    "wof:name":"Newey's Cleaning Services",
    "wof:placetype":"venue"
},
  "geometry": {"coordinates":[-1.275088,53.497501],"type":"Point"}
}