{
  "type": "Feature",
  "properties": {
    "iso:country":"GB",
    "sg:address":"431-435 Downham Way",
    "sg:city":"Bromley",
    "sg:classifiers":[
        {
            "category":"Food & Beverages",
            "subcategory":"Supermarket",
            "type":"Retail Goods"
        }
    ],
    "sg:phone":"+44 20 8591 5275",
    "sg:postcode":"BR1 5NY",
    "sg:province":"Kent",
    "wof:name":"South East Co-Op",
    "wof:placetype":"venue"
},
  "geometry": {"coordinates":[0.013688,51.427643],"type":"Point"}
}