{
  "type": "Feature",
  "properties": {
    "addr:full":"Tong Street, Dudley Hill Bradford West Yorkshire BD4 9PY",
    "addr:postcode":"bd4 9py",
    "addr:street":"Tong Street",
    "iso:country":"GB",
    "sg:address":"Tong Street, Dudley Hill",
    "sg:city":"Bradford",
    "sg:classifiers":[
        {
            "category":"Education",
            "subcategory":"School",
            "type":"Public Place"
        },
        {
            "category":"Government",
            "subcategory":"Office",
            "type":"Public Place"
        }
    ],
    "sg:phone":"+44 1274 681961",
    "sg:postcode":"BD4 9PY",
    "sg:province":"West Yorkshire",
    "sg:tags":[
        "local",
        "authority"
    ],
    "wof:name":"St Columba's R C Primary School",
    "wof:placetype":"venue"
},
  "geometry": {"coordinates":[-1.7239940166,53.7727890015],"type":"Point"}
}