{
  "type": "Feature",
  "properties": {
    "iso:country":"GB",
    "sg:address":"2 Wymeswold Road, Rempstone",
    "sg:city":"Loughborough",
    "sg:classifiers":[
        {
            "category":"Building & Trades",
            "subcategory":"Cleaning & Sanitation",
            "type":"Services"
        }
    ],
    "sg:postcode":"LE12 6RN",
    "sg:province":"Leicestershire",
    "sg:tags":[
        "toilet",
        "portable"
    ],
    "wof:name":"Michael Beeby",
    "wof:placetype":"venue"
},
  "geometry": {"coordinates":[-1.138686,52.813404],"type":"Point"}
}