{
  "type": "Feature",
  "properties": {
    "addr:full":"Wellington Street Aberdare Neath Port Talbot CF44 8EW",
    "addr:postcode":"cf44 8ew",
    "addr:street":"Wellington Street",
    "iso:country":"GB",
    "sg:address":"Wellington Street",
    "sg:city":"Aberdare",
    "sg:classifiers":[
        {
            "category":"Home & Garden",
            "subcategory":"Furniture",
            "type":"Retail Goods"
        }
    ],
    "sg:postcode":"CF44 8EW",
    "sg:province":"Neath Port Talbot",
    "wof:name":"Collin Brown Reproduction",
    "wof:placetype":"venue"
},
  "geometry": {"coordinates":[-3.447354,51.720081],"type":"Point"}
}