{
  "type": "Feature",
  "properties": {
    "addr:full":"Manor Farm, Main Road, Farthinghoe Brackley Buckinghamshire NN13 5XT",
    "addr:postcode":"nn13 5xt",
    "addr:street":"Manor;Main Road",
    "iso:country":"GB",
    "sg:address":"Manor Farm, Main Road, Farthinghoe",
    "sg:city":"Brackley",
    "sg:classifiers":[
        {
            "category":"Farming",
            "subcategory":"Livestock Farm",
            "type":"Manufacturing & Wholesale Goods"
        },
        {
            "category":"Farming",
            "subcategory":"Farm",
            "type":"Manufacturing & Wholesale Goods"
        }
    ],
    "sg:phone":"+44 1295 711229",
    "sg:postcode":"NN13 5XT",
    "sg:province":"Buckinghamshire",
    "sg:tags":[
        "mixed",
        "crop",
        "others"
    ],
    "wof:name":"D J & H A Deeley",
    "wof:placetype":"venue"
},
  "geometry": {"coordinates":[-1.2196569443,52.0536613464],"type":"Point"}
}