{
  "type": "Feature",
  "properties": {
    "addr:full":"65 Regents Park Road London Greater London NW1 8XD",
    "addr:housenumber":"65",
    "addr:postcode":"nw1 8xd",
    "addr:street":"Regents Park Road",
    "iso:country":"GB",
    "sg:address":"65 Regents Park Road",
    "sg:city":"London",
    "sg:classifiers":[
        {
            "category":"Social Services",
            "subcategory":"Retirement Home",
            "type":"Services"
        }
    ],
    "sg:phone":"+44 20 7722 5870",
    "sg:postcode":"NW1 8XD",
    "sg:province":"Greater London",
    "sg:tags":[
        "furrier"
    ],
    "wof:name":"Gale Furs",
    "wof:placetype":"venue"
},
  "geometry": {"coordinates":[-0.155391,51.538799],"type":"Point"}
}