{
  "type": "Feature",
  "properties": {
    "iso:country":"GB",
    "sg:address":"Unit 8 Old Church Rd",
    "sg:city":"Chelmsford",
    "sg:classifiers":[
        {
            "category":"Manufacturing",
            "subcategory":"Metals",
            "type":"Manufacturing & Wholesale Goods"
        }
    ],
    "sg:phone":"+44 1245 400700",
    "sg:postcode":"CM3 8BG",
    "sg:province":"Essex",
    "sg:tags":[
        "work",
        "sheet"
    ],
    "wof:name":"Arbour Electronics Ltd",
    "wof:placetype":"venue"
},
  "geometry": {"coordinates":[0.553,51.675297],"type":"Point"}
}