{
  "type": "Feature",
  "properties": {
    "iso:country":"GB",
    "sg:address":"Gates Garage, Bridge La",
    "sg:city":"Warrington",
    "sg:classifiers":[
        {
            "category":"Retail",
            "subcategory":"Auto Repair",
            "type":"Services"
        }
    ],
    "sg:phone":"+44 1928 735888",
    "sg:postcode":"WA6 7HN",
    "sg:province":"Cheshire",
    "sg:tags":[
        "modification",
        "garage"
    ],
    "wof:name":"Autow Garage Services",
    "wof:placetype":"venue"
},
  "geometry": {"coordinates":[-2.71286,53.299099],"type":"Point"}
}