{
  "type": "Feature",
  "properties": {
    "addr:full":"18 Church St Bishop's Stortford Essex CM23 2LY",
    "addr:housenumber":"18",
    "addr:postcode":"cm23 2ly",
    "addr:street":"Church St",
    "iso:country":"GB",
    "sg:address":"18 Church St",
    "sg:city":"Bishop's Stortford",
    "sg:classifiers":[
        {
            "category":"Building & Trades",
            "subcategory":"Landscaping Services",
            "type":"Services"
        }
    ],
    "sg:phone":"+44 1279 652452",
    "sg:postcode":"CM23 2LY",
    "sg:province":"Essex",
    "sg:tags":[
        "consultant"
    ],
    "wof:name":"David Blackwell Associates",
    "wof:placetype":"venue"
},
  "geometry": {"coordinates":[0.158633,51.87022],"type":"Point"}
}