{
  "type": "Feature",
  "properties": {
    "addr:full":"12 King Street Stroud Gloucestershire GL5 3DE",
    "addr:housenumber":"12",
    "addr:postcode":"gl5 3de",
    "addr:street":"King Street",
    "iso:country":"GB",
    "sg:address":"12 King Street",
    "sg:city":"Stroud",
    "sg:classifiers":[
        {
            "category":"Home & Garden",
            "subcategory":"Furniture",
            "type":"Retail Goods"
        }
    ],
    "sg:phone":"+44 1453 762792",
    "sg:postcode":"GL5 3DE",
    "sg:province":"Gloucestershire",
    "wof:name":"The Pine Shop",
    "wof:placetype":"venue"
},
  "geometry": {"coordinates":[-2.217675,51.745647],"type":"Point"}
}