{
  "type": "Feature",
  "properties": {
    "addr:full":"Flat 6, 68-70 Richmond Hill Richmond Greater London TW10 6RH",
    "addr:housenumber":"68-70",
    "addr:postcode":"tw10 6rh",
    "addr:street":"Richmond Hill",
    "iso:country":"GB",
    "sg:address":"Flat 6, 68-70 Richmond Hill",
    "sg:city":"Richmond",
    "sg:classifiers":[
        {
            "category":"Organizations",
            "subcategory":"Membership Organization",
            "type":"Services"
        }
    ],
    "sg:postcode":"TW10 6RH",
    "sg:province":"Greater London",
    "sg:tags":[
        "club"
    ],
    "wof:name":"Warwick Residents Association Ltd (The)",
    "wof:placetype":"venue"
},
  "geometry": {"coordinates":[-0.2999100089,51.4546813965],"type":"Point"}
}