{
  "type": "Feature",
  "properties": {
    "addr:full":"15-17 New Road Dagenham Essex RM13 8DJ",
    "addr:housenumber":"15-17",
    "addr:postcode":"rm13 8dj",
    "addr:street":"New Road",
    "iso:country":"GB",
    "sg:address":"15-17 New Road",
    "sg:city":"Dagenham",
    "sg:classifiers":[
        {
            "category":"Building & Trades",
            "subcategory":"Construction",
            "type":"Services"
        }
    ],
    "sg:phone":"+44 1708 556921",
    "sg:postcode":"RM13 8DJ",
    "sg:province":"Essex",
    "sg:tags":[
        "dry",
        "lining",
        "plasterers",
        "screeders"
    ],
    "wof:name":"Jonathan James Ltd.",
    "wof:placetype":"venue"
},
  "geometry": {"coordinates":[0.149654,51.531395],"type":"Point"}
}