{
  "type": "Feature",
  "properties": {
    "addr:full":"7 Lower Platts Wadhurst East Sussex TN5 7BX",
    "addr:housenumber":"7",
    "addr:postcode":"tn5 7bx",
    "addr:street":"Lower Platts",
    "iso:country":"GB",
    "sg:address":"7 Lower Platts",
    "sg:city":"Wadhurst",
    "sg:classifiers":[
        {
            "category":"Autos & Motor Vehicles",
            "subcategory":"Auto Supplies",
            "type":"Retail Goods"
        }
    ],
    "sg:phone":"+44 1580 200637",
    "sg:postcode":"TN5 7BX",
    "sg:province":"East Sussex",
    "sg:tags":[
        "tyre"
    ],
    "wof:name":"Cleeveford Ltd",
    "wof:placetype":"venue"
},
  "geometry": {"coordinates":[0.417832,51.046703],"type":"Point"}
}