{
  "type": "Feature",
  "properties": {
    "iso:country":"GB",
    "sg:address":"Unit 2, Old Mills Trading Estate",
    "sg:city":"Bristol",
    "sg:classifiers":[
        {
            "category":"Retail",
            "subcategory":"Event Space",
            "type":"Services"
        }
    ],
    "sg:phone":"+44 1761 416661",
    "sg:postcode":"BS39 7SU",
    "sg:province":"Somerset",
    "sg:tags":[
        "exhibition",
        "organiser"
    ],
    "wof:name":"Screen 2 Print",
    "wof:placetype":"venue"
},
  "geometry": {"coordinates":[-2.505231,51.296944],"type":"Point"}
}