{
  "type": "Feature",
  "properties": {
    "iso:country":"GB",
    "sg:address":"Mullcroft, Off Arran Way",
    "sg:city":"Birmingham",
    "sg:classifiers":[
        {
            "category":"Recreation",
            "type":"Entertainment"
        }
    ],
    "sg:phone":"+44 121 770 6018",
    "sg:postcode":"B36 0QT",
    "sg:province":"West Midlands",
    "sg:tags":[
        "snooker",
        "billiards",
        "pool"
    ],
    "wof:name":"Rays Snooker Club",
    "wof:placetype":"venue"
},
  "geometry": {"coordinates":[-1.74773,52.50172],"type":"Point"}
}