{
  "type": "Feature",
  "properties": {
    "addr:full":"98 Melbourne Way Enfield Greater London EN1 1XQ",
    "addr:housenumber":"98",
    "addr:postcode":"en1 1xq",
    "addr:street":"Melbourne Way",
    "iso:country":"GB",
    "sg:address":"98 Melbourne Way",
    "sg:city":"Enfield",
    "sg:classifiers":[
        {
            "category":"Manufacturing",
            "subcategory":"Signs",
            "type":"Manufacturing & Wholesale Goods"
        }
    ],
    "sg:postcode":"EN1 1XQ",
    "sg:province":"Greater London",
    "sg:tags":[
        "nameplate"
    ],
    "wof:name":"Monterey Signs",
    "wof:placetype":"venue"
},
  "geometry": {"coordinates":[-0.0664379969,51.6387748718],"type":"Point"}
}