{
  "type": "Feature",
  "properties": {
    "addr:full":"Pentlepoir Garage Saundersfoot Pembrokeshire SA69 9BN",
    "addr:postcode":"sa69 9bn",
    "iso:country":"GB",
    "sg:address":"Pentlepoir Garage",
    "sg:city":"Saundersfoot",
    "sg:classifiers":[
        {
            "category":"Retail",
            "subcategory":"Auto Repair",
            "type":"Services"
        }
    ],
    "sg:phone":"+44 1834 860777",
    "sg:postcode":"SA69 9BN",
    "sg:province":"Pembrokeshire",
    "sg:tags":[
        "modification",
        "garage"
    ],
    "wof:name":"Pentlepoir Garage",
    "wof:placetype":"venue"
},
  "geometry": {"coordinates":[-4.6995558739,51.7102050781],"type":"Point"}
}