{
  "type": "Feature",
  "properties": {
    "addr:full":"Lonsdale Chambers, 27 Chancery Lane London Greater London WC2A 1NE",
    "addr:housenumber":"27",
    "addr:postcode":"wc2a 1ne",
    "addr:street":"Chancery Lane",
    "iso:country":"GB",
    "sg:address":"Lonsdale Chambers, 27 Chancery Lane",
    "sg:city":"London",
    "sg:classifiers":[
        {
            "category":"Professional",
            "subcategory":"Lawyer & Legal Services",
            "type":"Services"
        }
    ],
    "sg:postcode":"WC2A 1NE",
    "sg:province":"Greater London",
    "sg:tags":[
        "solicitor"
    ],
    "wof:name":"Dibb & Clegg",
    "wof:placetype":"venue"
},
  "geometry": {"coordinates":[-0.1113300025,51.5157203674],"type":"Point"}
}