{
  "type": "Feature",
  "properties": {
    "iso:country":"GB",
    "sg:address":"2 Greenhill Parade, Station Road",
    "sg:city":"Barnet",
    "sg:classifiers":[
        {
            "category":"Home & Garden",
            "subcategory":"Home Furnishings",
            "type":"Retail Goods"
        }
    ],
    "sg:postcode":"EN5 1ES",
    "sg:province":"Hertfordshire",
    "sg:tags":[
        "furnishers",
        "planner",
        "kitchen"
    ],
    "wof:name":"Trade Kitchen World",
    "wof:placetype":"venue"
},
  "geometry": {"coordinates":[-0.185461998,51.6457138062],"type":"Point"}
}