{
  "type": "Feature",
  "properties": {
    "addr:full":"88 Woodhurst Avenue Watford Hertfordshire WD25 9RW",
    "addr:housenumber":"88",
    "addr:postcode":"wd25 9rw",
    "addr:street":"Woodhurst Avenue",
    "iso:country":"GB",
    "sg:address":"88 Woodhurst Avenue",
    "sg:city":"Watford",
    "sg:classifiers":[
        {
            "category":"Organizations",
            "subcategory":"Non-profit Organization",
            "type":"Services"
        }
    ],
    "sg:postcode":"WD25 9RW",
    "sg:province":"Hertfordshire",
    "sg:tags":[
        "organisation",
        "voluntary",
        "charity"
    ],
    "wof:name":"Woodhouse Avenue Project",
    "wof:placetype":"venue"
},
  "geometry": {"coordinates":[-0.3835450113,51.6861534119],"type":"Point"}
}