{
  "type": "Feature",
  "properties": {
    "iso:country":"GB",
    "sg:address":"Brimstage Road, Bebington",
    "sg:city":"Wirral",
    "sg:classifiers":[
        {
            "category":"Health Services",
            "subcategory":"Nursing And Care Facility",
            "type":"Services"
        },
        {
            "category":"Health Services",
            "subcategory":"Hospice",
            "type":"Services"
        }
    ],
    "sg:phone":"+44 151 342 2150",
    "sg:postcode":"CH63 6HF",
    "sg:province":"Merseyside",
    "sg:tags":[
        "home"
    ],
    "wof:name":"Activecare Ltd",
    "wof:placetype":"venue"
},
  "geometry": {"coordinates":[-3.0464060307,53.3371658325],"type":"Point"}
}