{
  "type": "Feature",
  "properties": {
    "iso:country":"GB",
    "sg:address":"34 Duncrievie Rd",
    "sg:city":"Lewisham",
    "sg:classifiers":[
        {
            "category":"Building & Trades",
            "subcategory":"Plumbing",
            "type":"Services"
        }
    ],
    "sg:phone":"+44 20 8318 6352",
    "sg:postcode":"SE13 6TE",
    "sg:province":"Greater London",
    "sg:tags":[
        "heating"
    ],
    "wof:name":"A B M Plumbing",
    "wof:placetype":"venue"
},
  "geometry": {"coordinates":[-0.002427,51.449394],"type":"Point"}
}