{
  "type": "Feature",
  "properties": {
    "addr:full":"34 Sackville Road Bexhill-on-sea East Sussex TN39 3JE",
    "addr:housenumber":"34",
    "addr:postcode":"tn39 3je",
    "addr:street":"Sackville Road",
    "iso:country":"GB",
    "sg:address":"34 Sackville Road",
    "sg:city":"Bexhill-on-sea",
    "sg:classifiers":[
        {
            "category":"Shopping",
            "subcategory":"Stationery & Office Supplies",
            "type":"Retail Goods"
        }
    ],
    "sg:phone":"+44 1424 217550",
    "sg:postcode":"TN39 3JE",
    "sg:province":"East Sussex",
    "sg:tags":[
        "equipment"
    ],
    "wof:name":"Office Equipment",
    "wof:placetype":"venue"
},
  "geometry": {"coordinates":[0.469647,50.839123],"type":"Point"}
}