{
  "type": "Feature",
  "properties": {
    "addr:full":"96 Cricklade Road Swindon Wiltshire SN2 8AF",
    "addr:housenumber":"96",
    "addr:postcode":"sn2 8af",
    "addr:street":"Cricklade Road",
    "iso:country":"GB",
    "sg:address":"96 Cricklade Road",
    "sg:city":"Swindon",
    "sg:classifiers":[
        {
            "category":"Banks & Credit Unions",
            "subcategory":"Financial Services",
            "type":"Services"
        }
    ],
    "sg:phone":"+44 1793 538772",
    "sg:postcode":"SN2 8AF",
    "sg:province":"Wiltshire",
    "sg:tags":[
        "building",
        "society"
    ],
    "sg:website":"http://www.portman.co.uk",
    "wof:name":"Portman Building Society",
    "wof:placetype":"venue"
},
  "geometry": {"coordinates":[-1.776858,51.571903],"type":"Point"}
}