{
  "type": "Feature",
  "properties": {
    "iso:country":"GB",
    "sg:address":"Hale Rd, Ashill",
    "sg:city":"Thetford",
    "sg:classifiers":[
        {
            "category":"Community Center",
            "type":"Public Place"
        }
    ],
    "sg:phone":"+44 1760 441775",
    "sg:postcode":"IP25 7AX",
    "sg:province":"Norfolk",
    "sg:tags":[
        "centre"
    ],
    "wof:name":"Norfolk County Council",
    "wof:placetype":"venue"
},
  "geometry": {"coordinates":[0.780673,52.602528],"type":"Point"}
}