{
  "type": "Feature",
  "properties": {
    "iso:country":"GB",
    "sg:address":"Unit 11 & 12, Stag Business Park",
    "sg:city":"Ringwood",
    "sg:classifiers":[
        {
            "category":"Building & Trades",
            "subcategory":"Landscaping Services",
            "type":"Services"
        }
    ],
    "sg:phone":"+44 1425 474751",
    "sg:postcode":"BH24 3AS",
    "sg:province":"Dorset",
    "sg:tags":[
        "irrigation",
        "system"
    ],
    "wof:name":"Tailored Irrigation & Engineering Services Ltd.",
    "wof:placetype":"venue"
},
  "geometry": {"coordinates":[-1.7835,50.837238],"type":"Point"}
}