{
  "type": "Feature",
  "properties": {
    "addr:full":"Chapel Works, Halifax Road Liversedge West Yorkshire WF15 6NP",
    "addr:postcode":"wf15 6np",
    "addr:street":"Halifax Road",
    "iso:country":"GB",
    "sg:address":"Chapel Works, Halifax Road",
    "sg:city":"Liversedge",
    "sg:classifiers":[
        {
            "category":"Professional",
            "subcategory":"Engineering",
            "type":"Services"
        }
    ],
    "sg:phone":"+44 1274 876464",
    "sg:postcode":"WF15 6NP",
    "sg:province":"West Yorkshire",
    "sg:tags":[
        "precision",
        "engineer"
    ],
    "wof:name":"Hanson Engineers",
    "wof:placetype":"venue"
},
  "geometry": {"coordinates":[-1.7036349773,53.7106666565],"type":"Point"}
}