{
  "type": "Feature",
  "properties": {
    "iso:country":"GB",
    "sg:address":"Unit 2-3, White Hall Farm, Frogmore Hill",
    "sg:city":"Hertford",
    "sg:classifiers":[
        {
            "category":"Professional",
            "subcategory":"Engineering",
            "type":"Services"
        }
    ],
    "sg:phone":"+44 1920 830910",
    "sg:postcode":"SG14 3RR",
    "sg:province":"Hertfordshire",
    "wof:name":"Tefloturn Ltd.",
    "wof:placetype":"venue"
},
  "geometry": {"coordinates":[-0.082699,51.796341],"type":"Point"}
}