{
  "type": "Feature",
  "properties": {
    "addr:full":"83 North Castle Street Banff Aberdeenshire AB45 1JJ",
    "addr:housenumber":"83",
    "addr:postcode":"ab45 1jj",
    "addr:street":"North Castle Street",
    "iso:country":"GB",
    "sg:address":"83 North Castle Street",
    "sg:city":"Banff",
    "sg:classifiers":[
        {
            "category":"Retail",
            "subcategory":"Auto Repair",
            "type":"Services"
        }
    ],
    "sg:postcode":"AB45 1JJ",
    "sg:province":"Aberdeenshire",
    "sg:tags":[
        "engine",
        "car",
        "specialist"
    ],
    "wof:name":"Ace Mobile Tuning",
    "wof:placetype":"venue"
},
  "geometry": {"coordinates":[-2.5237491131,57.6675682068],"type":"Point"}
}