{
  "type": "Feature",
  "properties": {
    "iso:country":"GB",
    "sg:address":"Care Of Hilton National Hotel, Eastern Road",
    "sg:city":"Portsmouth",
    "sg:classifiers":[
        {
            "category":"Sports & Exercise",
            "subcategory":"Gym",
            "type":"Entertainment"
        }
    ],
    "sg:phone":"+44 23 9221 9111",
    "sg:postcode":"PO6 1UN",
    "sg:province":"Hampshire",
    "sg:tags":[
        "fitness",
        "health",
        "centre"
    ],
    "wof:name":"Livingwell Health Clubs",
    "wof:placetype":"venue"
},
  "geometry": {"coordinates":[-1.0413,50.83625],"type":"Point"}
}