{
  "type": "Feature",
  "properties": {
    "addr:full":"110 Kimberley Park Road Falmouth Cornwall TR11 2JJ",
    "addr:housenumber":"110",
    "addr:postcode":"tr11 2jj",
    "addr:street":"Kimberley Park Road",
    "iso:country":"GB",
    "sg:address":"110 Kimberley Park Road",
    "sg:city":"Falmouth",
    "sg:classifiers":[
        {
            "category":"Travel",
            "subcategory":"Hotels & Motels",
            "type":"Entertainment"
        }
    ],
    "sg:postcode":"TR11 2JJ",
    "sg:province":"Cornwall",
    "wof:name":"The Rosslyn Hotel",
    "wof:placetype":"venue"
},
  "geometry": {"coordinates":[-5.0845398903,50.1547775269],"type":"Point"}
}