{
  "type": "Feature",
  "properties": {
    "addr:full":"Whitfield Street, Tranmere Birkenhead Merseyside CH42 0LR",
    "addr:postcode":"ch42 0lr",
    "addr:street":"Whitfield Street",
    "iso:country":"GB",
    "sg:address":"Whitfield Street, Tranmere",
    "sg:city":"Birkenhead",
    "sg:classifiers":[
        {
            "category":"Bars & Pubs",
            "type":"Food & Drink"
        },
        {
            "category":"Community Center",
            "subcategory":"Social",
            "type":"Public Place"
        }
    ],
    "sg:phone":"+44 151 647 4561",
    "sg:postcode":"CH42 0LR",
    "sg:province":"Merseyside",
    "sg:tags":[
        "pubs",
        "house",
        "inn",
        "activity"
    ],
    "wof:name":"THE IMPERIAL TAVERN",
    "wof:placetype":"venue"
},
  "geometry": {"coordinates":[-3.0252890587,53.3783836365],"type":"Point"}
}