{
  "type": "Feature",
  "properties": {
    "addr:full":"11 Canmore Place, Stewarton Kilmarnock East Ayrshire KA3 5PS",
    "addr:housenumber":"11",
    "addr:postcode":"ka3 5ps",
    "addr:street":"Canmore Place",
    "iso:country":"GB",
    "sg:address":"11 Canmore Place, Stewarton",
    "sg:city":"Kilmarnock",
    "sg:classifiers":[
        {
            "category":"Professional",
            "subcategory":"Art Services",
            "type":"Services"
        },
        {
            "category":"Building & Trades",
            "subcategory":"Construction",
            "type":"Services"
        }
    ],
    "sg:phone":"+44 1560 482541",
    "sg:postcode":"KA3 5PS",
    "sg:province":"East Ayrshire",
    "sg:tags":[
        "decorator",
        "painter"
    ],
    "wof:name":"Edward Minnes & Son",
    "wof:placetype":"venue"
},
  "geometry": {"coordinates":[-4.503778,55.685024],"type":"Point"}
}