{
  "type": "Feature",
  "properties": {
    "iso:country":"GB",
    "sg:address":"2, The Old George, George Street, Nailsworth",
    "sg:city":"Stroud",
    "sg:classifiers":[
        {
            "category":"Shopping",
            "subcategory":"Clothing, Apparel, & Fashions",
            "type":"Retail Goods"
        }
    ],
    "sg:phone":"+44 1453 836835",
    "sg:postcode":"GL6 0AG",
    "sg:province":"Gloucestershire",
    "sg:tags":[
        "shop"
    ],
    "wof:name":"Clock Tower Clothing",
    "wof:placetype":"venue"
},
  "geometry": {"coordinates":[-2.2173750401,51.6964378357],"type":"Point"}
}