{
  "type": "Feature",
  "properties": {
    "addr:full":"Diamond House, 36-38 Hatton Garden London Greater London EC1N 8EB",
    "addr:housenumber":"36-38",
    "addr:postcode":"ec1n 8eb",
    "addr:street":"Hatton Garden",
    "iso:country":"GB",
    "sg:address":"Diamond House, 36-38 Hatton Garden",
    "sg:city":"London",
    "sg:classifiers":[
        {
            "category":"Manufacturing",
            "subcategory":"Jewelry",
            "type":"Manufacturing & Wholesale Goods"
        }
    ],
    "sg:phone":"+44 20 7242 9550",
    "sg:postcode":"EC1N 8EB",
    "sg:province":"Greater London",
    "sg:tags":[
        "repair",
        "jewellery"
    ],
    "wof:name":"Maxwell James & Co.",
    "wof:placetype":"venue"
},
  "geometry": {"coordinates":[-0.0618890002,51.5324668884],"type":"Point"}
}