{
  "type": "Feature",
  "properties": {
    "addr:full":"86d Camberwell Road London Greater London SE5 0EG",
    "addr:housenumber":"86d",
    "addr:postcode":"se5 0eg",
    "addr:street":"Camberwell Road",
    "iso:country":"GB",
    "sg:address":"86d Camberwell Road",
    "sg:city":"London",
    "sg:classifiers":[
        {
            "category":"Communications",
            "type":"Services"
        }
    ],
    "sg:phone":"+44 20 8309 5040",
    "sg:postcode":"SE5 0EG",
    "sg:province":"Greater London",
    "sg:tags":[
        "telecommunication"
    ],
    "wof:name":"Communication Cabling Ltd.",
    "wof:placetype":"venue"
},
  "geometry": {"coordinates":[-0.0945760012,51.4813270569],"type":"Point"}
}