{
  "type": "Feature",
  "properties": {
    "addr:full":"Dunshalt, Auchtermuchty Cupar Fife KY14 7ER",
    "addr:postcode":"ky14 7er",
    "addr:street":"Cupar",
    "iso:country":"GB",
    "sg:address":"Dunshalt, Auchtermuchty",
    "sg:city":"Cupar",
    "sg:classifiers":[
        {
            "category":"Farming",
            "subcategory":"Farm",
            "type":"Manufacturing & Wholesale Goods"
        }
    ],
    "sg:phone":"+44 1337 828470",
    "sg:postcode":"KY14 7ER",
    "sg:province":"Fife",
    "sg:tags":[
        "mixed",
        "crop"
    ],
    "wof:name":"Duncan A W Black",
    "wof:placetype":"venue"
},
  "geometry": {"coordinates":[-3.229918,56.291855],"type":"Point"}
}