{
  "type": "Feature",
  "properties": {
    "addr:full":"3 Ferrier Street London Greater London SW18 1SL",
    "addr:housenumber":"3",
    "addr:postcode":"sw18 1sl",
    "addr:street":"Ferrier Street",
    "iso:country":"GB",
    "sg:address":"3 Ferrier Street",
    "sg:city":"London",
    "sg:classifiers":[
        {
            "category":"Home & Garden",
            "subcategory":"Furniture",
            "type":"Retail Goods"
        }
    ],
    "sg:phone":"+44 20 8871 1235",
    "sg:postcode":"SW18 1SL",
    "sg:province":"Greater London",
    "wof:name":"Page Lacquer Co. Ltd.",
    "wof:placetype":"venue"
},
  "geometry": {"coordinates":[-0.1888190061,51.4603500366],"type":"Point"}
}