{
  "type": "Feature",
  "properties": {
    "addr:full":"67 Kidbrooke Park Rd Blackheath Greater London SE3 0EE",
    "addr:housenumber":"67",
    "addr:postcode":"se3 0ee",
    "addr:street":"Kidbrooke Park Rd",
    "iso:country":"GB",
    "sg:address":"67 Kidbrooke Park Rd",
    "sg:city":"Blackheath",
    "sg:classifiers":[
        {
            "category":"Building & Trades",
            "subcategory":"Plumbing",
            "type":"Services"
        }
    ],
    "sg:phone":"+44 20 8856 6151",
    "sg:postcode":"SE3 0EE",
    "sg:province":"Greater London",
    "sg:tags":[
        "heating"
    ],
    "wof:name":"Badgers Of Blackheath",
    "wof:placetype":"venue"
},
  "geometry": {"coordinates":[0.0244730003,51.4699783325],"type":"Point"}
}