{
  "type": "Feature",
  "properties": {
    "iso:country":"GB",
    "sg:address":"79 St Michaels Rd",
    "sg:city":"Stoke-on-trent",
    "sg:classifiers":[
        {
            "category":"Government",
            "subcategory":"Post Office",
            "type":"Public Place"
        }
    ],
    "sg:postcode":"ST6 6LD",
    "sg:province":"Staffordshire",
    "wof:name":"Rigby,Barbara,",
    "wof:placetype":"venue"
},
  "geometry": {"coordinates":[-2.200077,53.069172],"type":"Point"}
}