{
  "type": "Feature",
  "properties": {
    "addr:full":"The Brindles, Frolesworth Lutterworth Leicestershire LE17 5EL",
    "addr:postcode":"le17 5el",
    "iso:country":"GB",
    "sg:address":"The Brindles, Frolesworth",
    "sg:city":"Lutterworth",
    "sg:classifiers":[
        {
            "category":"Professional",
            "type":"Services"
        },
        {
            "category":"Banks & Credit Unions",
            "subcategory":"Investment Brokerage",
            "type":"Services"
        }
    ],
    "sg:phone":"+44 1455 209350",
    "sg:postcode":"LE17 5EL",
    "sg:province":"Leicestershire",
    "sg:tags":[
        "farm",
        "agricultural",
        "contractor"
    ],
    "wof:name":"C Clayton",
    "wof:placetype":"venue"
},
  "geometry": {"coordinates":[-1.256242,52.51078],"type":"Point"}
}