{
  "type": "Feature",
  "properties": {
    "iso:country":"GB",
    "sg:address":"11 White Hart Street",
    "sg:city":"Dalkeith",
    "sg:classifiers":[
        {
            "category":"Professional",
            "subcategory":"Lawyer & Legal Services",
            "type":"Services"
        }
    ],
    "sg:phone":"+44 131 663 9568",
    "sg:postcode":"EH22 1AE",
    "sg:province":"City of Edinburgh",
    "sg:tags":[
        "solicitor"
    ],
    "wof:name":"Drummond Miller",
    "wof:placetype":"venue"
},
  "geometry": {"coordinates":[-3.068929,55.894138],"type":"Point"}
}