{
  "type": "Feature",
  "properties": {
    "iso:country":"GB",
    "sg:address":"Ealinghearth, Haverthwaite",
    "sg:city":"Ulverston",
    "sg:classifiers":[
        {
            "category":"Transit Center",
            "subcategory":"Passenger",
            "type":"Transportation"
        }
    ],
    "sg:phone":"+44 15395 31452",
    "sg:postcode":"LA12 8JR",
    "sg:province":"Cumbria",
    "sg:tags":[
        "boarding",
        "kennel",
        "catteries"
    ],
    "wof:name":"Hill Top Boarding Kennels",
    "wof:placetype":"venue"
},
  "geometry": {"coordinates":[-3.012839,54.246437],"type":"Point"}
}