{
  "type": "Feature",
  "properties": {
    "addr:full":"47 Albemarle Street London Greater London W1S 4JW",
    "addr:housenumber":"47",
    "addr:postcode":"w1s 4jw",
    "addr:street":"Albemarle Street",
    "iso:country":"GB",
    "sg:address":"47 Albemarle Street",
    "sg:city":"London",
    "sg:classifiers":[
        {
            "category":"Freight",
            "type":"Transportation"
        }
    ],
    "sg:phone":"+44 20 7499 3186",
    "sg:postcode":"W1S 4JW",
    "sg:province":"Greater London",
    "sg:tags":[
        "overseas",
        "shipping",
        "removal"
    ],
    "wof:name":"Berge Y Cia (U K) Ltd.",
    "wof:placetype":"venue"
},
  "geometry": {"coordinates":[-0.14117,51.508026],"type":"Point"}
}