{
  "type": "Feature",
  "properties": {
    "iso:country":"GB",
    "sg:address":"1 Poets Corner, Milton Rd",
    "sg:city":"Harpenden",
    "sg:classifiers":[
        {
            "category":"Professional",
            "subcategory":"Accounting & Tax Preparation",
            "type":"Services"
        }
    ],
    "sg:phone":"+44 1582 766787",
    "sg:postcode":"AL5 5LS",
    "sg:province":"Hertfordshire",
    "sg:tags":[
        "accountant"
    ],
    "wof:name":"Wilkins Kennedy Chartered Accountants",
    "wof:placetype":"venue"
},
  "geometry": {"coordinates":[-0.3498390019,51.8159179688],"type":"Point"}
}