{
  "type": "Feature",
  "properties": {
    "iso:country":"GB",
    "sg:address":"91 Uxbridge Road",
    "sg:city":"Rickmansworth",
    "sg:classifiers":[
        {
            "category":"Bars & Pubs",
            "type":"Food & Drink"
        }
    ],
    "sg:phone":"+44 1923 712253",
    "sg:postcode":"WD3 7DQ",
    "sg:province":"Hertfordshire",
    "sg:tags":[
        "pubs",
        "inn"
    ],
    "wof:name":"Half Way House",
    "wof:placetype":"venue"
},
  "geometry": {"coordinates":[-0.480371,51.637054],"type":"Point"}
}