{
  "type": "Feature",
  "properties": {
    "iso:country":"GB",
    "sg:address":"28 Bank Croft, Longton",
    "sg:city":"Preston",
    "sg:classifiers":[
        {
            "category":"Building & Trades",
            "subcategory":"Construction",
            "type":"Services"
        }
    ],
    "sg:phone":"+44 1772 615872",
    "sg:postcode":"PR4 5AL",
    "sg:province":"Lancashire",
    "sg:tags":[
        "builder",
        "conversion",
        "loft"
    ],
    "wof:name":"Michael J Procter",
    "wof:placetype":"venue"
},
  "geometry": {"coordinates":[-2.787734,53.725426],"type":"Point"}
}