{
  "type": "Feature",
  "properties": {
    "iso:country":"GB",
    "sg:address":"Squires Farm Industrial Estate, Framfield",
    "sg:city":"Uckfield",
    "sg:classifiers":[
        {
            "category":"Professional",
            "subcategory":"Engineering",
            "type":"Services"
        },
        {
            "category":"Shopping",
            "subcategory":"Pharmacy",
            "type":"Retail Goods"
        }
    ],
    "sg:phone":"+44 1825 840982",
    "sg:postcode":"TN22 5RB",
    "sg:province":"East Sussex",
    "sg:tags":[
        "civil",
        "pharmacist",
        "chemist",
        "engineer"
    ],
    "wof:name":"G W Allen",
    "wof:placetype":"venue"
},
  "geometry": {"coordinates":[0.131599,50.964581],"type":"Point"}
}