{
  "type": "Feature",
  "properties": {
    "iso:country":"GB",
    "sg:address":"Unit 4, Winnall Valley Road",
    "sg:city":"Winchester",
    "sg:classifiers":[
        {
            "category":"Professional",
            "subcategory":"Detective & Security Services",
            "type":"Services"
        }
    ],
    "sg:phone":"+44 1962 843222",
    "sg:postcode":"SO23 0LD",
    "sg:province":"Hampshire",
    "sg:tags":[
        "alarm",
        "burglar",
        "system"
    ],
    "wof:name":"Bridger Alarms Ltd.",
    "wof:placetype":"venue"
},
  "geometry": {"coordinates":[-1.298695,51.06641],"type":"Point"}
}