{
  "type": "Feature",
  "properties": {
    "iso:country":"GB",
    "sg:address":"Kwiksave Precint, Well 1, The Lane",
    "sg:city":"Rochdale",
    "sg:classifiers":[
        {
            "category":"Community Center",
            "subcategory":"Social",
            "type":"Public Place"
        }
    ],
    "sg:phone":"+44 1706 649622",
    "sg:postcode":"OL11 1BL",
    "sg:province":"Lancashire",
    "sg:tags":[
        "frozen",
        "food",
        "freezer",
        "centre"
    ],
    "wof:name":"Iceland Frozen Foods",
    "wof:placetype":"venue"
},
  "geometry": {"coordinates":[-2.149649,53.605415],"type":"Point"}
}