{
  "type": "Feature",
  "properties": {
    "addr:full":"2 Townend, Worksop Road, Aston Sheffield South Yorkshire S26 2EA",
    "addr:housenumber":"2",
    "addr:postcode":"s26 2ea",
    "addr:street":"Townend Worksop Road",
    "iso:country":"GB",
    "sg:address":"2 Townend, Worksop Road, Aston",
    "sg:city":"Sheffield",
    "sg:classifiers":[
        {
            "category":"Travel",
            "subcategory":"Travel Agent",
            "type":"Entertainment"
        }
    ],
    "sg:phone":"+44 114 287 4605",
    "sg:postcode":"S26 2EA",
    "sg:province":"South Yorkshire",
    "wof:name":"Travel Talk",
    "wof:placetype":"venue"
},
  "geometry": {"coordinates":[-1.315413,53.359032],"type":"Point"}
}