{
  "type": "Feature",
  "properties": {
    "addr:full":"P O Box 1757 Warminster Somerset BA12 0YB",
    "addr:housenumber":"p o;1757",
    "addr:postcode":"ba12 0yb",
    "iso:country":"GB",
    "sg:address":"P O Box 1757",
    "sg:city":"Warminster",
    "sg:classifiers":[
        {
            "category":"Professional",
            "subcategory":"Management & Consulting",
            "type":"Services"
        }
    ],
    "sg:phone":"+44 1985 850940",
    "sg:postcode":"BA12 0YB",
    "sg:province":"Somerset",
    "sg:tags":[
        "marketing",
        "consultant"
    ],
    "wof:name":"Horsfall International Ltd.",
    "wof:placetype":"venue"
},
  "geometry": {"coordinates":[-2.086988,51.177429],"type":"Point"}
}