{
  "type": "Feature",
  "properties": {
    "addr:full":"18 Bishop Road Calne Wiltshire SN11 9AF",
    "addr:housenumber":"18",
    "addr:postcode":"sn11 9af",
    "addr:street":"Bishop Road",
    "iso:country":"GB",
    "sg:address":"18 Bishop Road",
    "sg:city":"Calne",
    "sg:classifiers":[
        {
            "category":"Bus Charters",
            "type":"Transportation"
        }
    ],
    "sg:phone":"+44 1249 812592",
    "sg:postcode":"SN11 9AF",
    "sg:province":"Wiltshire",
    "sg:tags":[
        "mini",
        "hire",
        "coach",
        "leasing"
    ],
    "wof:name":"Connors Mini Buses",
    "wof:placetype":"venue"
},
  "geometry": {"coordinates":[-2.004718,51.442726],"type":"Point"}
}