{
  "type": "Feature",
  "properties": {
    "addr:full":"1 Lavender Close Manchester Cheshire M23 9SH",
    "addr:housenumber":"1",
    "addr:postcode":"m23 9sh",
    "addr:street":"Lavender Close",
    "iso:country":"GB",
    "sg:address":"1 Lavender Close",
    "sg:city":"Manchester",
    "sg:classifiers":[
        {
            "category":"Personal",
            "subcategory":"Hair Removal",
            "type":"Services"
        }
    ],
    "sg:phone":"+44 161 945 4195",
    "sg:postcode":"M23 9SH",
    "sg:province":"Cheshire",
    "sg:tags":[
        "electrolysis"
    ],
    "wof:name":"Valerie Oldham",
    "wof:placetype":"venue"
},
  "geometry": {"coordinates":[-2.2964799404,53.3892250061],"type":"Point"}
}