{
  "type": "Feature",
  "properties": {
    "addr:full":"140 Lower Mortlake Rd Richmond Greater London TW9 2LJ",
    "addr:housenumber":"140",
    "addr:postcode":"tw9 2lj",
    "addr:street":"Lower Mortlake Rd",
    "iso:country":"GB",
    "sg:address":"140 Lower Mortlake Rd",
    "sg:city":"Richmond",
    "sg:classifiers":[
        {
            "category":"Utilities",
            "subcategory":"Natural Gas",
            "type":"Services"
        }
    ],
    "sg:phone":"+44 20 8940 4630",
    "sg:postcode":"TW9 2LJ",
    "sg:province":"Greater London",
    "sg:tags":[
        "resurfacing",
        "bath"
    ],
    "wof:name":"Shining Example",
    "wof:placetype":"venue"
},
  "geometry": {"coordinates":[-0.2906079888,51.4669265747],"type":"Point"}
}