{
  "type": "Feature",
  "properties": {
    "addr:full":"Hawthornes, 3 Little Marsh Gro Stafford Shropshire ST19 5SF",
    "addr:housenumber":"3",
    "addr:postcode":"st19 5sf",
    "addr:street":"Hawthornes;Little Marsh Gro",
    "iso:country":"GB",
    "sg:address":"Hawthornes, 3 Little Marsh Gro",
    "sg:city":"Stafford",
    "sg:classifiers":[
        {
            "category":"Building & Trades",
            "subcategory":"Plumbing",
            "type":"Services"
        }
    ],
    "sg:phone":"+44 1785 712085",
    "sg:postcode":"ST19 5SF",
    "sg:province":"Shropshire",
    "sg:tags":[
        "heating"
    ],
    "wof:name":"J Kirby",
    "wof:placetype":"venue"
},
  "geometry": {"coordinates":[-2.1071000099,52.7240905762],"type":"Point"}
}