{
  "type": "Feature",
  "properties": {
    "iso:country":"GB",
    "sg:address":"Caemawr Farm, Cwmifor",
    "sg:city":"Llandeilo",
    "sg:classifiers":[
        {
            "category":"Farming",
            "subcategory":"Livestock Farm",
            "type":"Manufacturing & Wholesale Goods"
        }
    ],
    "sg:postcode":"SA19 7AW",
    "sg:province":"Carmarthenshire",
    "sg:tags":[
        "others"
    ],
    "wof:name":"G R Thomas & Sons",
    "wof:placetype":"venue"
},
  "geometry": {"coordinates":[-3.9509,51.912609],"type":"Point"}
}