{
  "type": "Feature",
  "properties": {
    "iso:country":"GB",
    "sg:address":"18 Chapel Road",
    "sg:city":"Wisbech",
    "sg:classifiers":[
        {
            "category":"Real Estate",
            "subcategory":"Surveying",
            "type":"Services"
        },
        {
            "category":"Real Estate",
            "subcategory":"Real Estate Agent",
            "type":"Services"
        }
    ],
    "sg:phone":"+44 1945 583756",
    "sg:postcode":"PE13 1RF",
    "sg:province":"Cambridgeshire",
    "sg:tags":[
        "building",
        "surveyor"
    ],
    "wof:name":"Russen & Turner",
    "wof:placetype":"venue"
},
  "geometry": {"coordinates":[0.15703,52.666172],"type":"Point"}
}