{
  "type": "Feature",
  "properties": {
    "addr:full":"38 Manor Road Southport Lancashire PR9 7LE",
    "addr:housenumber":"38",
    "addr:postcode":"pr9 7le",
    "addr:street":"Manor Road",
    "iso:country":"GB",
    "sg:address":"38 Manor Road",
    "sg:city":"Southport",
    "sg:classifiers":[
        {
            "category":"Government",
            "subcategory":"Post Office",
            "type":"Public Place"
        }
    ],
    "sg:postcode":"PR9 7LE",
    "sg:province":"Lancashire",
    "wof:name":"Churchtown Post Office",
    "wof:placetype":"venue"
},
  "geometry": {"coordinates":[-2.9649488926,53.6586380005],"type":"Point"}
}