{
  "type": "Feature",
  "properties": {
    "addr:full":"40 Saddler Gate Derby Derbyshire DE1 3NR",
    "addr:housenumber":"40",
    "addr:postcode":"de1 3nr",
    "addr:street":"Saddler Gate",
    "iso:country":"GB",
    "sg:address":"40 Saddler Gate",
    "sg:city":"Derby",
    "sg:classifiers":[
        {
            "category":"Shopping",
            "subcategory":"Gifts & Souvenirs",
            "type":"Retail Goods"
        }
    ],
    "sg:phone":"+44 1332 296436",
    "sg:postcode":"DE1 3NR",
    "sg:province":"Derbyshire",
    "sg:tags":[
        "shop"
    ],
    "wof:name":"A & K Bruce",
    "wof:placetype":"venue"
},
  "geometry": {"coordinates":[-1.4789110422,52.9230537415],"type":"Point"}
}