{
  "type": "Feature",
  "properties": {
    "iso:country":"GB",
    "sg:address":"Rosemary Lane Farm, Lawrenny Road, Cresselly",
    "sg:city":"Kilgetty",
    "sg:classifiers":[
        {
            "category":"Farming",
            "subcategory":"Livestock Farm",
            "type":"Manufacturing & Wholesale Goods"
        }
    ],
    "sg:postcode":"SA68 0TA",
    "sg:province":"Pembrokeshire",
    "sg:tags":[
        "others"
    ],
    "wof:name":"T G Cole",
    "wof:placetype":"venue"
},
  "geometry": {"coordinates":[-4.82553,51.714607],"type":"Point"}
}