{
  "type": "Feature",
  "properties": {
    "iso:country":"GB",
    "sg:address":"141 Nathan Way",
    "sg:city":"London",
    "sg:classifiers":[
        {
            "category":"Manufacturing",
            "subcategory":"Rubber & Plastics",
            "type":"Manufacturing & Wholesale Goods"
        }
    ],
    "sg:phone":"+44 20 8312 0599",
    "sg:postcode":"SE28 0AU",
    "sg:province":"Greater London",
    "sg:tags":[
        "injection",
        "moulding"
    ],
    "wof:name":"Greenwood Air Management Ltd.",
    "wof:placetype":"venue"
},
  "geometry": {"coordinates":[0.098864,51.495628],"type":"Point"}
}