{
  "type": "Feature",
  "properties": {
    "addr:full":"Weir House, Whitby Road Bristol City of Bristol BS4 4DF",
    "addr:postcode":"bs4 4df",
    "addr:street":"Whitby Road",
    "iso:country":"GB",
    "sg:address":"Weir House, Whitby Road",
    "sg:city":"Bristol",
    "sg:classifiers":[
        {
            "category":"Professional",
            "subcategory":"Computer Services",
            "type":"Services"
        }
    ],
    "sg:postcode":"BS4 4DF",
    "sg:province":"City of Bristol",
    "sg:tags":[
        "consultant"
    ],
    "wof:name":"J & J Consultant",
    "wof:placetype":"venue"
},
  "geometry": {"coordinates":[-2.5545499325,51.4504356384],"type":"Point"}
}