{
  "type": "Feature",
  "properties": {
    "iso:country":"GB",
    "sg:address":"Walkers Rise",
    "sg:city":"Rugeley",
    "sg:classifiers":[
        {
            "category":"Communications",
            "type":"Services"
        }
    ],
    "sg:postcode":"WS12 5QU",
    "sg:province":"Staffordshire",
    "sg:tags":[
        "audio-visual"
    ],
    "wof:name":"Hi-Res Av Ltd.",
    "wof:placetype":"venue"
},
  "geometry": {"coordinates":[-1.9889,52.723431],"type":"Point"}
}