{
  "type": "Feature",
  "properties": {
    "iso:country":"GB",
    "sg:address":"Unit 20 Borers Yard, Borers Arms Road, Copthorne",
    "sg:city":"Crawley",
    "sg:classifiers":[
        {
            "category":"Shopping",
            "subcategory":"Computers & Home Electronics",
            "type":"Retail Goods"
        }
    ],
    "sg:postcode":"RH10 3LH",
    "sg:province":"Surrey",
    "sg:tags":[
        "equipment",
        "video",
        "cctv"
    ],
    "wof:name":"Transerve Ltd.",
    "wof:placetype":"venue"
},
  "geometry": {"coordinates":[-0.111629,51.139404],"type":"Point"}
}