{
  "type": "Feature",
  "properties": {
    "addr:full":"109 Efford Road Plymouth Devon PL3 6NG",
    "addr:housenumber":"109",
    "addr:postcode":"pl3 6ng",
    "addr:street":"Efford Road",
    "iso:country":"GB",
    "sg:address":"109 Efford Road",
    "sg:city":"Plymouth",
    "sg:classifiers":[
        {
            "category":"Shopping",
            "subcategory":"Florist",
            "type":"Retail Goods"
        }
    ],
    "sg:postcode":"PL3 6NG",
    "sg:province":"Devon",
    "wof:name":"EVERGREEN FLORIST",
    "wof:placetype":"venue"
},
  "geometry": {"coordinates":[-4.1118578911,50.3909568787],"type":"Point"}
}