{
  "type": "Feature",
  "properties": {
    "iso:country":"GB",
    "sg:address":"1227 Melton Road, Syston",
    "sg:city":"Leicester",
    "sg:classifiers":[
        {
            "category":"Home & Garden",
            "subcategory":"Hardware",
            "type":"Retail Goods"
        }
    ],
    "sg:phone":"+44 116 260 8055",
    "sg:postcode":"LE7 2JT",
    "sg:province":"Leicestershire",
    "sg:tags":[
        "retailer",
        "diy"
    ],
    "wof:name":"Wilkinsons Hardware Stores",
    "wof:placetype":"venue"
},
  "geometry": {"coordinates":[-1.073739,52.698257],"type":"Point"}
}