{
  "type": "Feature",
  "properties": {
    "iso:country":"GB",
    "sg:address":"56 Mere Road",
    "sg:city":"Wigston",
    "sg:classifiers":[
        {
            "category":"Home & Garden",
            "subcategory":"Home Furnishings",
            "type":"Retail Goods"
        },
        {
            "category":"Home & Garden",
            "subcategory":"Building Materials",
            "type":"Retail Goods"
        }
    ],
    "sg:phone":"+44 116 281 1466",
    "sg:postcode":"LE18 3RL",
    "sg:province":"Leicestershire",
    "sg:tags":[
        "installers",
        "planner",
        "kitchen",
        "furnishers"
    ],
    "wof:name":"R J Harding",
    "wof:placetype":"venue"
},
  "geometry": {"coordinates":[-1.09666,52.587437],"type":"Point"}
}