{
  "type": "Feature",
  "properties": {
    "addr:full":"Unit 17a Arndale Centre Manchester Cheshire M32 9BA",
    "addr:housenumber":"unit 17a arndale centre",
    "addr:postcode":"m32 9ba",
    "addr:street":"Manchester Cheshire",
    "iso:country":"GB",
    "sg:address":"Unit 17a Arndale Centre",
    "sg:city":"Manchester",
    "sg:classifiers":[
        {
            "category":"Food & Beverages",
            "subcategory":"Liquor & Beverages",
            "type":"Retail Goods"
        }
    ],
    "sg:phone":"+44 161 865 8907",
    "sg:postcode":"M32 9BA",
    "sg:province":"Cheshire",
    "sg:tags":[
        "beer",
        "spirit",
        "wines"
    ],
    "wof:name":"LiquorZone",
    "wof:placetype":"venue"
},
  "geometry": {"coordinates":[-2.327489,53.449219],"type":"Point"}
}