{
  "type": "Feature",
  "properties": {
    "iso:country":"GB",
    "sg:address":"96 Sandy Lane",
    "sg:city":"Skelmersdale",
    "sg:classifiers":[
        {
            "category":"Professional",
            "subcategory":"Engineering",
            "type":"Services"
        }
    ],
    "sg:phone":"+44 1695 731999",
    "sg:postcode":"WN8 8LQ",
    "sg:province":"Lancashire",
    "sg:tags":[
        "contractor",
        "electrical",
        "engineer"
    ],
    "wof:name":"A E G Electrical Supplies",
    "wof:placetype":"venue"
},
  "geometry": {"coordinates":[-2.8058431149,53.5488471985],"type":"Point"}
}