{
  "type": "Feature",
  "properties": {
    "addr:full":"365 Union Street Aberdeen Aberdeen City AB11 6BT",
    "addr:housenumber":"365",
    "addr:postcode":"ab11 6bt",
    "addr:street":"Union Street",
    "iso:country":"GB",
    "sg:address":"365 Union Street",
    "sg:city":"Aberdeen",
    "sg:classifiers":[
        {
            "category":"Bars & Pubs",
            "type":"Food & Drink"
        },
        {
            "category":"Shopping",
            "subcategory":"Music",
            "type":"Retail Goods"
        },
        {
            "category":"Community Center",
            "subcategory":"Social",
            "type":"Public Place"
        }
    ],
    "sg:phone":"+44 1224 580092",
    "sg:postcode":"AB11 6BT",
    "sg:province":"Aberdeen City",
    "sg:tags":[
        "shop",
        "house",
        "inn",
        "pubs",
        "activity"
    ],
    "wof:name":"The Howff",
    "wof:placetype":"venue"
},
  "geometry": {"coordinates":[-2.1047389507,57.144908905],"type":"Point"}
}