{
  "type": "Feature",
  "properties": {
    "iso:country":"GB",
    "sg:address":"Quarry Mills Quarry Rd",
    "sg:city":"Godstone",
    "sg:classifiers":[
        {
            "category":"Shopping",
            "subcategory":"Stationery & Office Supplies",
            "type":"Retail Goods"
        }
    ],
    "sg:phone":"+44 1883 744254",
    "sg:postcode":"RH9 8DQ",
    "sg:province":"Surrey",
    "sg:tags":[
        "equipment"
    ],
    "wof:name":"Arbat International Ltd",
    "wof:placetype":"venue"
},
  "geometry": {"coordinates":[-0.0669879988,51.2500801086],"type":"Point"}
}