{
  "type": "Feature",
  "properties": {
    "iso:country":"GB",
    "sg:address":"2 Southwold Road",
    "sg:city":"London",
    "sg:classifiers":[
        {
            "category":"Food & Beverages",
            "subcategory":"Meat & Fish",
            "type":"Retail Goods"
        },
        {
            "category":"Food & Beverages",
            "subcategory":"Groceries & Convenience Stores",
            "type":"Retail Goods"
        }
    ],
    "sg:phone":"+44 20 8806 4464",
    "sg:postcode":"E5 9PT",
    "sg:province":"Greater London",
    "sg:tags":[
        "shop",
        "chip"
    ],
    "wof:name":"Nice Place",
    "wof:placetype":"venue"
},
  "geometry": {"coordinates":[-0.05513,51.562008],"type":"Point"}
}