{
  "type": "Feature",
  "properties": {
    "addr:full":"36 Holgate Road York North Yorkshire YO24 4AB",
    "addr:housenumber":"36",
    "addr:postcode":"yo24 4ab",
    "addr:street":"Holgate Road",
    "iso:country":"GB",
    "sg:address":"36 Holgate Road",
    "sg:city":"York",
    "sg:classifiers":[
        {
            "category":"Autos & Motor Vehicles",
            "subcategory":"Auto Supplies",
            "type":"Retail Goods"
        }
    ],
    "sg:phone":"+44 1904 641400",
    "sg:postcode":"YO24 4AB",
    "sg:province":"North Yorkshire",
    "sg:tags":[
        "rubber",
        "tyre"
    ],
    "wof:name":"P W Tyres",
    "wof:placetype":"venue"
},
  "geometry": {"coordinates":[-1.0952459574,53.9540901184],"type":"Point"}
}