{
  "type": "Feature",
  "properties": {
    "addr:full":"17 Waltham Road, Boscombe East Bournemouth Dorset BH7 6PE",
    "addr:housenumber":"17",
    "addr:postcode":"bh7 6pe",
    "addr:street":"Waltham Road",
    "iso:country":"GB",
    "sg:address":"17 Waltham Road, Boscombe East",
    "sg:city":"Bournemouth",
    "sg:classifiers":[
        {
            "category":"Education",
            "subcategory":"Special Training",
            "type":"Public Place"
        }
    ],
    "sg:phone":"+44 1202 428667",
    "sg:postcode":"BH7 6PE",
    "sg:province":"Dorset",
    "sg:tags":[
        "product",
        "centre"
    ],
    "wof:name":"Software Training & Consultancy",
    "wof:placetype":"venue"
},
  "geometry": {"coordinates":[-1.8192130327,50.7348747253],"type":"Point"}
}