{
  "type": "Feature",
  "properties": {
    "addr:full":"94 Haverstock Hill London Greater London NW3 2BD",
    "addr:housenumber":"94",
    "addr:postcode":"nw3 2bd",
    "addr:street":"Haverstock Hill",
    "iso:country":"GB",
    "sg:address":"94 Haverstock Hill",
    "sg:city":"London",
    "sg:classifiers":[
        {
            "category":"Bars & Pubs",
            "type":"Food & Drink"
        }
    ],
    "sg:postcode":"NW3 2BD",
    "sg:province":"Greater London",
    "sg:tags":[
        "pubs",
        "inn"
    ],
    "wof:name":"The Load of Hay",
    "wof:placetype":"venue"
},
  "geometry": {"coordinates":[-0.154724,51.544735],"type":"Point"}
}