{
  "type": "Feature",
  "properties": {
    "iso:country":"GB",
    "sg:address":"20 Highfield Close, Gildersome, Morley",
    "sg:city":"Leeds",
    "sg:classifiers":[
        {
            "category":"Building & Trades",
            "subcategory":"Construction",
            "type":"Services"
        }
    ],
    "sg:postcode":"LS27 7LT",
    "sg:province":"West Yorkshire",
    "sg:tags":[
        "decorator",
        "painter"
    ],
    "wof:name":"Highfield Decorators",
    "wof:placetype":"venue"
},
  "geometry": {"coordinates":[-1.620123,53.757462],"type":"Point"}
}