{
  "type": "Feature",
  "properties": {
    "addr:full":"1 King Street Tamworth Staffordshire B79 7DB",
    "addr:housenumber":"1",
    "addr:postcode":"b79 7db",
    "addr:street":"King Street",
    "iso:country":"GB",
    "sg:address":"1 King Street",
    "sg:city":"Tamworth",
    "sg:classifiers":[
        {
            "category":"Professional",
            "type":"Services"
        }
    ],
    "sg:postcode":"B79 7DB",
    "sg:province":"Staffordshire",
    "sg:tags":[
        "caterer"
    ],
    "wof:name":"King Street Caterers & Sandwich Bar",
    "wof:placetype":"venue"
},
  "geometry": {"coordinates":[-1.6966639757,52.6335983276],"type":"Point"}
}