{
  "type": "Feature",
  "properties": {
    "iso:country":"GB",
    "sg:address":"47 Wellington Rd",
    "sg:city":"Bournemouth",
    "sg:classifiers":[
        {
            "category":"Social Services",
            "subcategory":"Retirement Home",
            "type":"Services"
        }
    ],
    "sg:postcode":"BH8 8JJ",
    "sg:province":"Dorset",
    "sg:tags":[
        "rest"
    ],
    "wof:name":"Bellamy,Maureen,",
    "wof:placetype":"venue"
},
  "geometry": {"coordinates":[-1.8691079617,50.731010437],"type":"Point"}
}