{
  "type": "Feature",
  "properties": {
    "addr:full":"36-44 High Street Southend-on-sea Essex SS1 1JG",
    "addr:housenumber":"36-44",
    "addr:postcode":"ss1 1jg",
    "addr:street":"High Street",
    "iso:country":"GB",
    "sg:address":"36-44 High Street",
    "sg:city":"Southend-on-sea",
    "sg:classifiers":[
        {
            "category":"Shopping",
            "subcategory":"Department Store",
            "type":"Retail Goods"
        }
    ],
    "sg:phone":"+44 1702 467282",
    "sg:postcode":"SS1 1JG",
    "sg:province":"Essex",
    "wof:name":"B H S Ltd.",
    "wof:placetype":"venue"
},
  "geometry": {"coordinates":[0.7142099738,51.5355377197],"type":"Point"}
}