{
  "type": "Feature",
  "properties": {
    "iso:country":"GB",
    "sg:address":"26 Town Street, Duffield",
    "sg:city":"Belper",
    "sg:classifiers":[
        {
            "category":"Deli",
            "type":"Food & Drink"
        }
    ],
    "sg:phone":"+44 1332 842089",
    "sg:postcode":"DE56 4EH",
    "sg:province":"Derbyshire",
    "sg:tags":[
        "delicatessen"
    ],
    "wof:name":"Country Larder",
    "wof:placetype":"venue"
},
  "geometry": {"coordinates":[-1.4880479574,52.9867477417],"type":"Point"}
}