{
  "type": "Feature",
  "properties": {
    "iso:country":"GB",
    "sg:address":"1 Barnfield Place",
    "sg:city":"London",
    "sg:classifiers":[
        {
            "category":"Shopping",
            "subcategory":"Stationery & Office Supplies",
            "type":"Retail Goods"
        },
        {
            "category":"Professional",
            "subcategory":"Computer Services",
            "type":"Services"
        }
    ],
    "sg:phone":"+44 20 7987 6160",
    "sg:postcode":"E14 9YA",
    "sg:province":"Greater London",
    "sg:tags":[
        "development",
        "equipment",
        "school",
        "software"
    ],
    "wof:name":"CLICK TECHNOLOGY LTD",
    "wof:placetype":"venue"
},
  "geometry": {"coordinates":[-0.020701,51.490749],"type":"Point"}
}