{
  "type": "Feature",
  "properties": {
    "addr:full":"Tormax House, Unit 21 Mole Business Park, Randalls Rd Leatherhead Surrey KT22 7BD",
    "addr:housenumber":"unit 21",
    "addr:postcode":"kt22 7bd",
    "addr:street":"Business Park Randalls Rd",
    "iso:country":"GB",
    "sg:address":"Tormax House, Unit 21 Mole Business Park, Randalls Rd",
    "sg:city":"Leatherhead",
    "sg:classifiers":[
        {
            "category":"Home & Garden",
            "subcategory":"Building Materials",
            "type":"Retail Goods"
        }
    ],
    "sg:phone":"+44 20 7407 6271",
    "sg:postcode":"KT22 7BD",
    "sg:province":"Surrey",
    "sg:tags":[
        "shutter",
        "door"
    ],
    "wof:name":"Tormax (langley Systems) Ltd",
    "wof:placetype":"venue"
},
  "geometry": {"coordinates":[-0.329419,51.29636],"type":"Point"}
}