{
  "type": "Feature",
  "properties": {
    "iso:country":"GB",
    "sg:address":"Unit 46 City Business Park, Somerset Place",
    "sg:city":"Plymouth",
    "sg:classifiers":[
        {
            "category":"Education",
            "subcategory":"Special Training",
            "type":"Public Place"
        }
    ],
    "sg:postcode":"PL3 4BB",
    "sg:province":"Devon",
    "sg:tags":[
        "aid",
        "first"
    ],
    "wof:name":"K J A Medical Services",
    "wof:placetype":"venue"
},
  "geometry": {"coordinates":[-4.1607899666,50.3811607361],"type":"Point"}
}