{
  "type": "Feature",
  "properties": {
    "iso:country":"GB",
    "sg:address":"Unit 10, Potters Ind Park, Church Crookham",
    "sg:city":"Fleet",
    "sg:classifiers":[
        {
            "category":"Professional",
            "subcategory":"Engineering",
            "type":"Services"
        }
    ],
    "sg:phone":"+44 1252 615083",
    "sg:postcode":"GU13 0EU",
    "sg:province":"Dorset",
    "sg:tags":[
        "precision",
        "engineer"
    ],
    "wof:name":"J.C.M Engineering",
    "wof:placetype":"venue"
},
  "geometry": {"coordinates":[-0.803534,51.271469],"type":"Point"}
}