{
  "type": "Feature",
  "properties": {
    "addr:full":"71 Ecton Avenue Macclesfield Cheshire SK10 1RA",
    "addr:housenumber":"71",
    "addr:postcode":"sk10 1ra",
    "addr:street":"Ecton Avenue",
    "iso:country":"GB",
    "sg:address":"71 Ecton Avenue",
    "sg:city":"Macclesfield",
    "sg:classifiers":[
        {
            "category":"Building & Trades",
            "subcategory":"Construction",
            "type":"Services"
        }
    ],
    "sg:phone":"+44 1625 610001",
    "sg:postcode":"SK10 1RA",
    "sg:province":"Cheshire",
    "sg:tags":[
        "joiner",
        "carpenter"
    ],
    "wof:name":"Ray Brown Joinery",
    "wof:placetype":"venue"
},
  "geometry": {"coordinates":[-2.09749,53.25922],"type":"Point"}
}