{
  "type": "Feature",
  "properties": {
    "addr:full":"Unit 4 Wueller Drive, Finchampstead Wokingham Berkshire RG40 4QZ",
    "addr:housenumber":"unit 4",
    "addr:postcode":"rg40 4qz",
    "addr:street":"Wueller Drive",
    "iso:country":"GB",
    "sg:address":"Unit 4 Wueller Drive, Finchampstead",
    "sg:city":"Wokingham",
    "sg:classifiers":[
        {
            "category":"Social Services",
            "subcategory":"Job Training",
            "type":"Services"
        }
    ],
    "sg:phone":"+44 118 973 6903",
    "sg:postcode":"RG40 4QZ",
    "sg:province":"Berkshire",
    "sg:tags":[
        "engineering",
        "marine"
    ],
    "wof:name":"Hydro-Lek Ltd.",
    "wof:placetype":"venue"
},
  "geometry": {"coordinates":[-0.891948998,51.3765068054],"type":"Point"}
}