{
  "type": "Feature",
  "properties": {
    "addr:full":"The Old Hairpin Shop, Mallory Park Circuit, Church Rd Swadlincote Derbyshire DE11 0DP",
    "addr:postcode":"de11 0dp",
    "addr:street":"Mallory Park Circuit Church Rd",
    "iso:country":"GB",
    "sg:address":"The Old Hairpin Shop, Mallory Park Circuit, Church Rd",
    "sg:city":"Swadlincote",
    "sg:classifiers":[
        {
            "category":"Health Services",
            "subcategory":"Hospital",
            "type":"Services"
        }
    ],
    "sg:phone":"+44 1283 552232",
    "sg:postcode":"DE11 0DP",
    "sg:province":"Derbyshire",
    "sg:tags":[
        "ambulance"
    ],
    "wof:name":"Formerly Europe T/A Pro Medical 2000",
    "wof:placetype":"venue"
},
  "geometry": {"coordinates":[-1.552209,52.774094],"type":"Point"}
}