{
  "type": "Feature",
  "properties": {
    "iso:country":"GB",
    "sg:address":"12a South Street",
    "sg:city":"Chichester",
    "sg:classifiers":[
        {
            "category":"Restaurant",
            "type":"Food & Drink"
        }
    ],
    "sg:postcode":"PO19 1EJ",
    "sg:province":"West Sussex",
    "wof:name":"The Crypt Brasserie",
    "wof:placetype":"venue"
},
  "geometry": {"coordinates":[-0.779437,50.835888],"type":"Point"}
}