{
  "type": "Feature",
  "properties": {
    "addr:full":"12a South Street Chichester West Sussex PO19 1EJ",
    "addr:housenumber":"12a",
    "addr:postcode":"po19 1ej",
    "addr:street":"South Street",
    "iso:country":"GB",
    "sg:address":"12a South Street",
    "sg:city":"Chichester",
    "sg:classifiers":[
        {
            "category":"Restaurant",
            "type":"Food & Drink"
        }
    ],
    "sg:postcode":"PO19 1EJ",
    "sg:province":"West Sussex",
    "wof:name":"The Crypt Brasserie",
    "wof:placetype":"venue"
},
  "geometry": {"coordinates":[-0.779437,50.835888],"type":"Point"}
}