{
  "type": "Feature",
  "properties": {
    "iso:country":"GB",
    "sg:address":"10 Fechney Park",
    "sg:city":"Perth",
    "sg:classifiers":[
        {
            "category":"Recreation",
            "subcategory":"Dance Hall",
            "type":"Entertainment"
        }
    ],
    "sg:phone":"+44 1738 443594",
    "sg:postcode":"PH1 1PT",
    "sg:province":"Perth and Kinross",
    "sg:tags":[
        "disco"
    ],
    "wof:name":"Henry's Disco",
    "wof:placetype":"venue"
},
  "geometry": {"coordinates":[-3.448804,56.397507],"type":"Point"}
}