{
  "type": "Feature",
  "properties": {
    "addr:full":"32 Faulkner Street, Hoole Chester Cheshire CH2 3BD",
    "addr:housenumber":"32",
    "addr:postcode":"ch2 3bd",
    "addr:street":"Faulkner Street",
    "iso:country":"GB",
    "sg:address":"32 Faulkner Street, Hoole",
    "sg:city":"Chester",
    "sg:classifiers":[
        {
            "category":"Personal",
            "subcategory":"Barber",
            "type":"Services"
        }
    ],
    "sg:phone":"+44 1244 326567",
    "sg:postcode":"CH2 3BD",
    "sg:province":"Cheshire",
    "sg:tags":[
        "men's",
        "hairdresser"
    ],
    "wof:name":"Dereks Mens Hair Shop",
    "wof:placetype":"venue"
},
  "geometry": {"coordinates":[-2.876187,53.19939],"type":"Point"}
}