{
  "type": "Feature",
  "properties": {
    "addr:full":"64 Bridge Road Tipton West Midlands DY4 0JL",
    "addr:housenumber":"64",
    "addr:postcode":"dy4 0jl",
    "addr:street":"Bridge Road",
    "iso:country":"GB",
    "sg:address":"64 Bridge Road",
    "sg:city":"Tipton",
    "sg:classifiers":[
        {
            "category":"Autos & Motor Vehicles",
            "subcategory":"Automobile Sales",
            "type":"Retail Goods"
        }
    ],
    "sg:postcode":"DY4 0JL",
    "sg:province":"West Midlands",
    "sg:tags":[
        "car"
    ],
    "wof:name":"Wheels Car Centre",
    "wof:placetype":"venue"
},
  "geometry": {"coordinates":[-2.041893959,52.5361633301],"type":"Point"}
}