{
  "type": "Feature",
  "properties": {
    "iso:country":"GB",
    "sg:address":"P O Box 114",
    "sg:city":"Solihull",
    "sg:classifiers":[
        {
            "category":"Organizations",
            "subcategory":"Political Organization",
            "type":"Services"
        }
    ],
    "sg:phone":"+44 121 603 1922",
    "sg:postcode":"B91 2UR",
    "sg:province":"West Midlands",
    "sg:tags":[
        "party"
    ],
    "wof:name":"National Front-West Midlands",
    "wof:placetype":"venue"
},
  "geometry": {"coordinates":[-1.772829,52.418911],"type":"Point"}
}