{
  "type": "Feature",
  "properties": {
    "addr:full":"Beach Road, Croyde Braunton Devon EX33 1NZ",
    "addr:postcode":"ex33 1nz",
    "addr:street":"Beach Road",
    "iso:country":"GB",
    "sg:address":"Beach Road, Croyde",
    "sg:city":"Braunton",
    "sg:classifiers":[
        {
            "category":"Travel",
            "subcategory":"Hotels & Motels",
            "type":"Entertainment"
        },
        {
            "category":"Bars & Pubs",
            "subcategory":"Hookah Bar",
            "type":"Food & Drink"
        }
    ],
    "sg:phone":"+44 1271 890828",
    "sg:postcode":"EX33 1NZ",
    "sg:province":"Devon",
    "sg:tags":[
        "self",
        "holiday",
        "catering"
    ],
    "wof:name":"Croyde Bay Holidays Ltd",
    "wof:placetype":"venue"
},
  "geometry": {"coordinates":[-4.2279090881,51.1284141541],"type":"Point"}
}