{
  "type": "Feature",
  "properties": {
    "addr:full":"10 Robert Street Carlisle Cumbria CA2 5AB",
    "addr:housenumber":"10",
    "addr:postcode":"ca2 5ab",
    "addr:street":"Robert Street",
    "iso:country":"GB",
    "sg:address":"10 Robert Street",
    "sg:city":"Carlisle",
    "sg:classifiers":[
        {
            "category":"Home & Garden",
            "subcategory":"Building Materials",
            "type":"Retail Goods"
        }
    ],
    "sg:phone":"+44 1228 549000",
    "sg:postcode":"CA2 5AB",
    "sg:province":"Cumbria",
    "sg:tags":[
        "window",
        "frame"
    ],
    "wof:name":"The Trade Window & Door Centre",
    "wof:placetype":"venue"
},
  "geometry": {"coordinates":[-2.9328439236,54.88904953],"type":"Point"}
}