{
  "type": "Feature",
  "properties": {
    "addr:full":"472 Old London Road Hastings East Sussex TN35 5BG",
    "addr:housenumber":"472",
    "addr:postcode":"tn35 5bg",
    "addr:street":"Old London Road",
    "iso:country":"GB",
    "sg:address":"472 Old London Road",
    "sg:city":"Hastings",
    "sg:classifiers":[
        {
            "category":"Fast Food",
            "type":"Food & Drink"
        }
    ],
    "sg:phone":"+44 1424 420062",
    "sg:postcode":"TN35 5BG",
    "sg:province":"East Sussex",
    "sg:tags":[
        "away",
        "take"
    ],
    "wof:name":"Kfc",
    "wof:placetype":"venue"
},
  "geometry": {"coordinates":[0.6087880135,50.8726043701],"type":"Point"}
}