{
  "type": "Feature",
  "properties": {
    "addr:full":"194 All Saints Road Burton-on-trent Derbyshire DE14 3LS",
    "addr:housenumber":"194",
    "addr:postcode":"de14 3ls",
    "addr:street":"All Saints Road",
    "iso:country":"GB",
    "sg:address":"194 All Saints Road",
    "sg:city":"Burton-on-trent",
    "sg:classifiers":[
        {
            "category":"Building & Trades",
            "subcategory":"Plumbing",
            "type":"Services"
        }
    ],
    "sg:phone":"+44 1283 564144",
    "sg:postcode":"DE14 3LS",
    "sg:province":"Derbyshire",
    "sg:tags":[
        "central",
        "heating"
    ],
    "wof:name":"M Smith",
    "wof:placetype":"venue"
},
  "geometry": {"coordinates":[-1.6430840492,52.7942276001],"type":"Point"}
}