{
  "type": "Feature",
  "properties": {
    "addr:full":"12 Perry Road Witham Essex CM8 3YZ",
    "addr:housenumber":"12",
    "addr:postcode":"cm8 3yz",
    "addr:street":"Perry Road",
    "iso:country":"GB",
    "sg:address":"12 Perry Road",
    "sg:city":"Witham",
    "sg:classifiers":[
        {
            "category":"Professional",
            "subcategory":"Printing & Photocopies",
            "type":"Services"
        }
    ],
    "sg:phone":"+44 1376 517600",
    "sg:postcode":"CM8 3YZ",
    "sg:province":"Essex",
    "sg:tags":[
        "printer"
    ],
    "wof:name":"Bensons Printing Co",
    "wof:placetype":"venue"
},
  "geometry": {"coordinates":[0.6465849876,51.7948112488],"type":"Point"}
}