{
  "type": "Feature",
  "properties": {
    "addr:full":"12-20 Crown Hill, Church Street Croydon Surrey CR0 1RZ",
    "addr:housenumber":"12-20",
    "addr:postcode":"cr0 1rz",
    "addr:street":"Crown Hill Church Street",
    "iso:country":"GB",
    "sg:address":"12-20 Crown Hill, Church Street",
    "sg:city":"Croydon",
    "sg:classifiers":[
        {
            "category":"Recreation",
            "type":"Entertainment"
        }
    ],
    "sg:phone":"+44 20 8688 9627",
    "sg:postcode":"CR0 1RZ",
    "sg:province":"Surrey",
    "sg:tags":[
        "snooker",
        "billiards",
        "pool"
    ],
    "wof:name":"New World Snooker Club",
    "wof:placetype":"venue"
},
  "geometry": {"coordinates":[-0.100717,51.373653],"type":"Point"}
}