{
  "type": "Feature",
  "properties": {
    "iso:country":"GB",
    "sg:address":"Unit 2 Block 8 Moorfield Indust Est",
    "sg:city":"Kilmarnock",
    "sg:classifiers":[
        {
            "category":"Shopping",
            "subcategory":"Pharmacy",
            "type":"Retail Goods"
        }
    ],
    "sg:phone":"+44 1563 574020",
    "sg:postcode":"KA2 0BA",
    "sg:province":"East Ayrshire",
    "sg:tags":[
        "pharmaceutical"
    ],
    "wof:name":"Core Technologies",
    "wof:placetype":"venue"
},
  "geometry": {"coordinates":[-4.541719,55.61179],"type":"Point"}
}