{
  "type": "Feature",
  "properties": {
    "iso:country":"GB",
    "sg:address":"4 Elm Court, Arden Street",
    "sg:city":"Stratford-upon-avon",
    "sg:classifiers":[
        {
            "category":"Professional",
            "subcategory":"Engineering",
            "type":"Services"
        }
    ],
    "sg:phone":"+44 1789 295377",
    "sg:postcode":"CV37 6PA",
    "sg:province":"Warwickshire",
    "sg:tags":[
        "consulting",
        "engineer"
    ],
    "wof:name":"Crouch Butler Structures Ltd.",
    "wof:placetype":"venue"
},
  "geometry": {"coordinates":[-1.710649,52.194935],"type":"Point"}
}