{
  "type": "Feature",
  "properties": {
    "iso:country":"GB",
    "sg:address":"Rooley Moore Road, P O Box 40",
    "sg:city":"Rochdale",
    "sg:classifiers":[
        {
            "category":"Manufacturing",
            "subcategory":"Textiles",
            "type":"Manufacturing & Wholesale Goods"
        }
    ],
    "sg:phone":"+44 1706 647422",
    "sg:postcode":"OL12 7EQ",
    "sg:province":"Lancashire",
    "sg:tags":[
        "made-up"
    ],
    "wof:name":"T B A Industrial Products Ltd.",
    "wof:placetype":"venue"
},
  "geometry": {"coordinates":[-2.162766,53.619007],"type":"Point"}
}