{
  "type": "Feature",
  "properties": {
    "iso:country":"GB",
    "sg:address":"7 Commercial Square",
    "sg:city":"Haywards Heath",
    "sg:classifiers":[
        {
            "category":"Shopping",
            "subcategory":"Antiques",
            "type":"Retail Goods"
        }
    ],
    "sg:phone":"+44 1444 417654",
    "sg:postcode":"RH16 1DW",
    "sg:province":"East Sussex",
    "wof:name":"Roundabout Antiques",
    "wof:placetype":"venue"
},
  "geometry": {"coordinates":[-0.103416,51.005943],"type":"Point"}
}