{
  "type": "Feature",
  "properties": {
    "iso:country":"GB",
    "sg:address":"5 Holmes Lane, Bilton",
    "sg:city":"Hull",
    "sg:classifiers":[
        {
            "category":"Bus Charters",
            "type":"Transportation"
        }
    ],
    "sg:postcode":"HU11 4EX",
    "sg:province":"East Riding of Yorkshire",
    "sg:tags":[
        "coach"
    ],
    "wof:name":"Lords Coaches",
    "wof:placetype":"venue"
},
  "geometry": {"coordinates":[-0.2338670045,53.7806472778],"type":"Point"}
}