{
  "type": "Feature",
  "properties": {
    "iso:country":"GB",
    "sg:address":"1 Rusthall Rd",
    "sg:city":"Tunbridge Wells",
    "sg:classifiers":[
        {
            "category":"Home & Garden",
            "subcategory":"Hardware",
            "type":"Retail Goods"
        }
    ],
    "sg:phone":"+44 1892 547011",
    "sg:postcode":"TN4 8XG",
    "sg:province":"Kent",
    "sg:tags":[
        "tarpaulin"
    ],
    "wof:name":"Cover-All",
    "wof:placetype":"venue"
},
  "geometry": {"coordinates":[0.2329770029,51.1344451904],"type":"Point"}
}