{
  "type": "Feature",
  "properties": {
    "addr:full":"218 Roundhay Road Leeds West Yorkshire LS8 5AA",
    "addr:housenumber":"218",
    "addr:postcode":"ls8 5aa",
    "addr:street":"Roundhay Road",
    "iso:country":"GB",
    "sg:address":"218 Roundhay Road",
    "sg:city":"Leeds",
    "sg:classifiers":[
        {
            "category":"Insurance",
            "subcategory":"Insurance Agent",
            "type":"Services"
        }
    ],
    "sg:phone":"+44 113 248 8211",
    "sg:postcode":"LS8 5AA",
    "sg:province":"West Yorkshire",
    "sg:tags":[
        "broker"
    ],
    "wof:name":"Colonnade Insurance Brokers Ltd",
    "wof:placetype":"venue"
},
  "geometry": {"coordinates":[-1.5182989836,53.8157691956],"type":"Point"}
}