{
  "type": "Feature",
  "properties": {
    "addr:full":"6 Commercial Street Aberdare Neath Port Talbot CF44 7RW",
    "addr:housenumber":"6",
    "addr:postcode":"cf44 7rw",
    "addr:street":"Commercial Street",
    "iso:country":"GB",
    "sg:address":"6 Commercial Street",
    "sg:city":"Aberdare",
    "sg:classifiers":[
        {
            "category":"Shopping",
            "subcategory":"Gifts & Souvenirs",
            "type":"Retail Goods"
        }
    ],
    "sg:phone":"+44 1685 877595",
    "sg:postcode":"CF44 7RW",
    "sg:province":"Neath Port Talbot",
    "sg:tags":[
        "poster",
        "card"
    ],
    "wof:name":"Kard King",
    "wof:placetype":"venue"
},
  "geometry": {"coordinates":[-3.443655014,51.7136230469],"type":"Point"}
}