{
  "type": "Feature",
  "properties": {
    "addr:full":"Mersa, Haroldslea Drive Horley Surrey RH6 9DT",
    "addr:postcode":"rh6 9dt",
    "addr:street":"Haroldslea Drive",
    "iso:country":"GB",
    "sg:address":"Mersa, Haroldslea Drive",
    "sg:city":"Horley",
    "sg:classifiers":[
        {
            "category":"Professional",
            "subcategory":"Computer Services",
            "type":"Services"
        }
    ],
    "sg:phone":"+44 1293 774747",
    "sg:postcode":"RH6 9DT",
    "sg:province":"Surrey",
    "sg:tags":[
        "aided",
        "design"
    ],
    "wof:name":"Trilobyte Design Ltd",
    "wof:placetype":"venue"
},
  "geometry": {"coordinates":[-0.1487040073,51.1662635803],"type":"Point"}
}