{
  "type": "Feature",
  "properties": {
    "iso:country":"GB",
    "sg:address":"22 South Parade",
    "sg:city":"Skegness",
    "sg:classifiers":[
        {
            "category":"Travel",
            "subcategory":"Hotels & Motels",
            "type":"Entertainment"
        }
    ],
    "sg:phone":"+44 1754 764113",
    "sg:postcode":"PE25 3HW",
    "sg:province":"Lincolnshire",
    "wof:name":"South Parade Hotel",
    "wof:placetype":"venue"
},
  "geometry": {"coordinates":[0.343518,53.140682],"type":"Point"}
}