{
  "type": "Feature",
  "properties": {
    "addr:full":"3 Cavendish Place Eastbourne East Sussex BN21 3EJ",
    "addr:housenumber":"3",
    "addr:postcode":"bn21 3ej",
    "addr:street":"Cavendish Place",
    "iso:country":"GB",
    "sg:address":"3 Cavendish Place",
    "sg:city":"Eastbourne",
    "sg:classifiers":[
        {
            "category":"Travel",
            "subcategory":"Hotels & Motels",
            "type":"Entertainment"
        }
    ],
    "sg:phone":"+44 1323 731258",
    "sg:postcode":"BN21 3EJ",
    "sg:province":"East Sussex",
    "wof:name":"Regent Hotel",
    "wof:placetype":"venue"
},
  "geometry": {"coordinates":[0.2922439873,50.7676925659],"type":"Point"}
}