{
  "type": "Feature",
  "properties": {
    "addr:full":"Enterprise Way, Hardwick Narrows Indstl Est King's Lynn Norfolk PE30 4LJ",
    "addr:postcode":"pe30 4lj",
    "addr:street":"Enterprise Way;Narrows Indstl Est",
    "iso:country":"GB",
    "sg:address":"Enterprise Way, Hardwick Narrows Indstl Est",
    "sg:city":"King's Lynn",
    "sg:classifiers":[
        {
            "category":"Professional",
            "subcategory":"Engineering",
            "type":"Services"
        }
    ],
    "sg:postcode":"PE30 4LJ",
    "sg:province":"Norfolk",
    "sg:tags":[
        "precision",
        "engineer"
    ],
    "wof:name":"Brown,Robert G,",
    "wof:placetype":"venue"
},
  "geometry": {"coordinates":[0.4143199921,52.7483215332],"type":"Point"}
}