{
  "type": "Feature",
  "properties": {
    "iso:country":"GB",
    "sg:address":"391 Westgate Road",
    "sg:city":"Newcastle-upon-tyne",
    "sg:classifiers":[
        {
            "category":"Personal",
            "subcategory":"Barber",
            "type":"Services"
        }
    ],
    "sg:phone":"+44 191 272 2285",
    "sg:postcode":"NE4 6PA",
    "sg:province":"Tyne and Wear",
    "sg:tags":[
        "men's",
        "hairdresser"
    ],
    "wof:name":"Fan Barber Shop",
    "wof:placetype":"venue"
},
  "geometry": {"coordinates":[-1.6386049986,54.9732170105],"type":"Point"}
}