{
  "type": "Feature",
  "properties": {
    "addr:full":"Old Vicarage 6 Market St, Castle Donington Derby Leicestershire DE74 2JB",
    "addr:housenumber":"6",
    "addr:postcode":"de74 2jb",
    "addr:street":"Market St",
    "iso:country":"GB",
    "sg:address":"Old Vicarage 6 Market St, Castle Donington",
    "sg:city":"Derby",
    "sg:classifiers":[
        {
            "category":"Professional",
            "type":"Services"
        }
    ],
    "sg:phone":"+44 1332 814814",
    "sg:postcode":"DE74 2JB",
    "sg:province":"Leicestershire",
    "sg:tags":[
        "directory",
        "pub"
    ],
    "wof:name":"PML Publishing",
    "wof:placetype":"venue"
},
  "geometry": {"coordinates":[-1.337384,52.844879],"type":"Point"}
}