{
  "type": "Feature",
  "properties": {
    "addr:full":"22 Chequer Street Nuneaton Warwickshire CV12 9NH",
    "addr:housenumber":"22",
    "addr:postcode":"cv12 9nh",
    "addr:street":"Chequer Street",
    "iso:country":"GB",
    "sg:address":"22 Chequer Street",
    "sg:city":"Nuneaton",
    "sg:classifiers":[
        {
            "category":"Community Center",
            "subcategory":"Social",
            "type":"Public Place"
        }
    ],
    "sg:postcode":"CV12 9NH",
    "sg:province":"Warwickshire",
    "sg:tags":[
        "frozen",
        "food",
        "freezer",
        "centre"
    ],
    "wof:name":"Roger Pickard",
    "wof:placetype":"venue"
},
  "geometry": {"coordinates":[-1.42468,52.475471],"type":"Point"}
}