{
  "type": "Feature",
  "properties": {
    "addr:full":"10 Market Street, Kingswinford Brierley Hill Staffordshire DY6 9JR",
    "addr:housenumber":"10",
    "addr:postcode":"dy6 9jr",
    "addr:street":"Market Street",
    "iso:country":"GB",
    "sg:address":"10 Market Street, Kingswinford",
    "sg:city":"Brierley Hill",
    "sg:classifiers":[
        {
            "category":"Manufacturing",
            "subcategory":"Tools & Machinery",
            "type":"Manufacturing & Wholesale Goods"
        }
    ],
    "sg:phone":"+44 1384 401330",
    "sg:postcode":"DY6 9JR",
    "sg:province":"Staffordshire",
    "sg:tags":[
        "society",
        "friendly"
    ],
    "wof:name":"Obc Insurance Consultants",
    "wof:placetype":"venue"
},
  "geometry": {"coordinates":[-2.16835,52.496925],"type":"Point"}
}