{
  "type": "Feature",
  "properties": {
    "iso:country":"GB",
    "sg:address":"Ashford House, County Square",
    "sg:city":"Ashford",
    "sg:classifiers":[
        {
            "category":"Professional",
            "subcategory":"Employment Agencies",
            "type":"Services"
        }
    ],
    "sg:postcode":"TN23 1YB",
    "sg:province":"Kent",
    "sg:tags":[
        "consultant"
    ],
    "wof:name":"Accountancy & Secretarial Personnel Ltd",
    "wof:placetype":"venue"
},
  "geometry": {"coordinates":[0.87033,51.148319],"type":"Point"}
}