{
  "type": "Feature",
  "properties": {
    "addr:full":"Caterware House, Welbeck Avenue Blackpool Lancashire FY4 4ES",
    "addr:postcode":"fy4 4es",
    "addr:street":"Welbeck Avenue",
    "iso:country":"GB",
    "sg:address":"Caterware House, Welbeck Avenue",
    "sg:city":"Blackpool",
    "sg:classifiers":[
        {
            "category":"Home & Garden",
            "subcategory":"Kitchen Supply",
            "type":"Retail Goods"
        }
    ],
    "sg:phone":"+44 1253 760777",
    "sg:postcode":"FY4 4ES",
    "sg:province":"Lancashire",
    "sg:tags":[
        "equipment",
        "catering"
    ],
    "wof:name":"Caterware Ltd",
    "wof:placetype":"venue"
},
  "geometry": {"coordinates":[-3.0263690948,53.7989883423],"type":"Point"}
}