{
  "type": "Feature",
  "properties": {
    "iso:country":"GB",
    "sg:address":"5 Hyde Cotts, Handcross",
    "sg:city":"Haywards Heath",
    "sg:classifiers":[
        {
            "category":"Professional",
            "subcategory":"Art Services",
            "type":"Services"
        }
    ],
    "sg:phone":"+44 1444 400074",
    "sg:postcode":"RH17 6EZ",
    "sg:province":"East Sussex",
    "sg:tags":[
        "photographer"
    ],
    "wof:name":"Photographic Productions",
    "wof:placetype":"venue"
},
  "geometry": {"coordinates":[-0.22276,51.057289],"type":"Point"}
}