{
  "type": "Feature",
  "properties": {
    "addr:full":"Over Square, Over Winsford, Winsford Cheshire CW7 2JP",
    "addr:postcode":"cw7 2jp",
    "addr:street":"Over Square Over",
    "iso:country":"GB",
    "sg:address":"Over Square, Over Winsford,",
    "sg:city":"Winsford",
    "sg:classifiers":[
        {
            "category":"Sports & Exercise",
            "subcategory":"Winter Sports",
            "type":"Entertainment"
        }
    ],
    "sg:postcode":"CW7 2JP",
    "sg:province":"Cheshire",
    "sg:tags":[
        "skiing"
    ],
    "wof:name":"A C Sports",
    "wof:placetype":"venue"
},
  "geometry": {"coordinates":[-2.540047884,53.1891975403],"type":"Point"}
}