{
  "type": "Feature",
  "properties": {
    "iso:country":"GB",
    "sg:address":"Mount Ararat Road",
    "sg:city":"Richmond",
    "sg:classifiers":[
        {
            "category":"Farming",
            "subcategory":"Nursery",
            "type":"Manufacturing & Wholesale Goods"
        }
    ],
    "sg:postcode":"TW10 6PN",
    "sg:province":"Greater London",
    "sg:tags":[
        "creche"
    ],
    "wof:name":"Wings Nursery School",
    "wof:placetype":"venue"
},
  "geometry": {"coordinates":[-0.300105989,51.4602470398],"type":"Point"}
}