{
  "type": "Feature",
  "properties": {
    "iso:country":"GB",
    "sg:address":"161 Winchester Road, Brislington",
    "sg:city":"Bristol",
    "sg:classifiers":[
        {
            "category":"Shopping",
            "subcategory":"Gifts & Souvenirs",
            "type":"Retail Goods"
        }
    ],
    "sg:phone":"+44 117 909 6615",
    "sg:postcode":"BS4 3NJ",
    "sg:province":"City of Bristol",
    "sg:tags":[
        "shop"
    ],
    "wof:name":"Viridian",
    "wof:placetype":"venue"
},
  "geometry": {"coordinates":[-2.5534551144,51.4360351562],"type":"Point"}
}