{
  "type": "Feature",
  "properties": {
    "addr:full":"68a Edward Rd Walthamstow Greater London E17 6LU",
    "addr:housenumber":"68a",
    "addr:postcode":"e17 6lu",
    "addr:street":"Edward Rd",
    "iso:country":"GB",
    "sg:address":"68a Edward Rd",
    "sg:city":"Walthamstow",
    "sg:classifiers":[
        {
            "category":"Professional",
            "subcategory":"Computer Services",
            "type":"Services"
        }
    ],
    "sg:phone":"+44 20 8509 0128",
    "sg:postcode":"E17 6LU",
    "sg:province":"Greater London",
    "sg:tags":[
        "system",
        "software"
    ],
    "wof:name":"Valtex",
    "wof:placetype":"venue"
},
  "geometry": {"coordinates":[-0.03954,51.582375],"type":"Point"}
}