{
  "type": "Feature",
  "properties": {
    "iso:country":"GB",
    "sg:address":"46 Parton Road, Churchdown",
    "sg:city":"Gloucester",
    "sg:classifiers":[
        {
            "category":"Farming",
            "subcategory":"Nursery",
            "type":"Manufacturing & Wholesale Goods"
        }
    ],
    "sg:phone":"+44 1452 531105",
    "sg:postcode":"GL3 2AF",
    "sg:province":"Gloucestershire",
    "sg:tags":[
        "creche"
    ],
    "wof:name":"Churchdown Day Nursery",
    "wof:placetype":"venue"
},
  "geometry": {"coordinates":[-2.181841,51.88736],"type":"Point"}
}