{
  "type": "Feature",
  "properties": {
    "iso:country":"GB",
    "sg:address":"8 Rotherham Road",
    "sg:city":"Barnsley",
    "sg:classifiers":[
        {
            "category":"Shopping",
            "type":"Retail Goods"
        }
    ],
    "sg:postcode":"S72 0EX",
    "sg:province":"South Yorkshire",
    "sg:tags":[
        "part",
        "accessory"
    ],
    "wof:name":"Apex Auto Factors",
    "wof:placetype":"venue"
},
  "geometry": {"coordinates":[-1.34766,53.552025],"type":"Point"}
}