{
  "type": "Feature",
  "properties": {
    "addr:full":"124 Cranbrook Road Ilford Essex IG1 4LZ",
    "addr:housenumber":"124",
    "addr:postcode":"ig1 4lz",
    "addr:street":"Cranbrook Road",
    "iso:country":"GB",
    "sg:address":"124 Cranbrook Road",
    "sg:city":"Ilford",
    "sg:classifiers":[
        {
            "category":"Cafe",
            "type":"Food & Drink"
        },
        {
            "category":"Ice Cream",
            "type":"Food & Drink"
        }
    ],
    "sg:phone":"+44 20 8554 1537",
    "sg:postcode":"IG1 4LZ",
    "sg:province":"Essex",
    "sg:tags":[
        "shop",
        "mobile",
        "snack",
        "bar",
        "parlour"
    ],
    "wof:name":"Titanic Cafe",
    "wof:placetype":"venue"
},
  "geometry": {"coordinates":[0.068442,51.562088],"type":"Point"}
}