{
  "type": "Feature",
  "properties": {
    "iso:country":"GB",
    "sg:address":"60 Osterley Views, West Park Rd",
    "sg:city":"Southall",
    "sg:classifiers":[
        {
            "category":"Professional",
            "subcategory":"Management & Consulting",
            "type":"Services"
        }
    ],
    "sg:phone":"+44 20 8574 7884",
    "sg:postcode":"UB2 4UN",
    "sg:province":"Greater London",
    "sg:tags":[
        "consultant",
        "business"
    ],
    "wof:name":"David Burns",
    "wof:placetype":"venue"
},
  "geometry": {"coordinates":[-0.35173,51.506969],"type":"Point"}
}