{
  "type": "Feature",
  "properties": {
    "addr:full":"1508 Maryhill Road Glasgow Glasgow City G20 9AD",
    "addr:housenumber":"1508",
    "addr:postcode":"g20 9ad",
    "addr:street":"Maryhill Road",
    "iso:country":"GB",
    "sg:address":"1508 Maryhill Road",
    "sg:city":"Glasgow",
    "sg:classifiers":[
        {
            "category":"Education",
            "subcategory":"Library",
            "type":"Public Place"
        }
    ],
    "sg:phone":"+44 141 946 2348",
    "sg:postcode":"G20 9AD",
    "sg:province":"Glasgow City",
    "sg:tags":[
        "book"
    ],
    "wof:name":"Maryhill Library",
    "wof:placetype":"venue"
},
  "geometry": {"coordinates":[-4.2910318375,55.8913459778],"type":"Point"}
}