{
  "type": "Feature",
  "properties": {
    "addr:full":"10 North Cray Rd Bexley Kent DA5 3LZ",
    "addr:housenumber":"10",
    "addr:postcode":"da5 3lz",
    "addr:street":"North Cray Rd",
    "iso:country":"GB",
    "sg:address":"10 North Cray Rd",
    "sg:city":"Bexley",
    "sg:classifiers":[
        {
            "category":"Building & Trades",
            "subcategory":"Construction",
            "type":"Services"
        }
    ],
    "sg:phone":"+44 1322 522881",
    "sg:postcode":"DA5 3LZ",
    "sg:province":"Kent",
    "sg:tags":[
        "builder"
    ],
    "wof:name":"M S Building Contractors",
    "wof:placetype":"venue"
},
  "geometry": {"coordinates":[0.153054,51.439697],"type":"Point"}
}