{
  "type": "Feature",
  "properties": {
    "addr:full":"180 Chichester Road Portsmouth Hampshire PO2 0AH",
    "addr:housenumber":"180",
    "addr:postcode":"hampshire po2 0ah",
    "addr:street":"Chichester Road",
    "iso:country":"GB",
    "sg:address":"180 Chichester Road",
    "sg:city":"Portsmouth",
    "sg:classifiers":[
        {
            "category":"Cinema",
            "subcategory":"Movie Rental",
            "type":"Entertainment"
        }
    ],
    "sg:postcode":"PO2 0AH",
    "sg:province":"Hampshire",
    "sg:tags":[
        "video",
        "library"
    ],
    "wof:name":"Total Video",
    "wof:placetype":"venue"
},
  "geometry": {"coordinates":[-1.071613,50.813828],"type":"Point"}
}