{
  "type": "Feature",
  "properties": {
    "iso:country":"GB",
    "sg:address":"Stora Terminal, Immingham Dock",
    "sg:city":"Grimsby",
    "sg:classifiers":[
        {
            "category":"Freight",
            "type":"Transportation"
        }
    ],
    "sg:phone":"+44 1469 572069",
    "sg:postcode":"DN40 1AA",
    "sg:province":"Lincolnshire",
    "sg:tags":[
        "haulage",
        "road"
    ],
    "wof:name":"Fox David Transport",
    "wof:placetype":"venue"
},
  "geometry": {"coordinates":[-0.22397,53.611481],"type":"Point"}
}