{
  "type": "Feature",
  "properties": {
    "iso:country":"GB",
    "sg:address":"103 Sydenham Rd",
    "sg:city":"Sydenham",
    "sg:classifiers":[
        {
            "category":"Professional",
            "subcategory":"Detective & Security Services",
            "type":"Services"
        }
    ],
    "sg:phone":"+44 20 8676 0139",
    "sg:postcode":"SE26 5UA",
    "sg:province":"Greater London",
    "sg:tags":[
        "agency"
    ],
    "wof:name":"Paging Services",
    "wof:placetype":"venue"
},
  "geometry": {"coordinates":[-0.0503950007,51.4261169434],"type":"Point"}
}