{
  "type": "Feature",
  "properties": {
    "iso:country":"GB",
    "sg:address":"Colne Bridge Road",
    "sg:city":"Huddersfield",
    "sg:classifiers":[
        {
            "category":"Shopping",
            "subcategory":"Baby Store",
            "type":"Retail Goods"
        }
    ],
    "sg:phone":"+44 1484 438200",
    "sg:postcode":"HD5 0RH",
    "sg:province":"West Yorkshire",
    "sg:tags":[
        "nursery",
        "accessory"
    ],
    "wof:name":"Mamas & Papas (Retail) Ltd.",
    "wof:placetype":"venue"
},
  "geometry": {"coordinates":[-1.734218955,53.677898407],"type":"Point"}
}