{
  "type": "Feature",
  "properties": {
    "addr:full":"Theale House, Brunel Road, Theale Reading Berkshire RG7 4AQ",
    "addr:postcode":"rg7 4aq",
    "addr:street":"Brunel Road",
    "iso:country":"GB",
    "sg:address":"Theale House, Brunel Road, Theale",
    "sg:city":"Reading",
    "sg:classifiers":[
        {
            "category":"Professional",
            "subcategory":"Detective & Security Services",
            "type":"Services"
        },
        {
            "category":"Professional",
            "subcategory":"Computer Services",
            "type":"Services"
        }
    ],
    "sg:phone":"+44 118 930 6060",
    "sg:postcode":"RG7 4AQ",
    "sg:province":"Berkshire",
    "sg:tags":[
        "retail"
    ],
    "sg:website":"http://www.integralis.com",
    "wof:name":"Integralis Ltd",
    "wof:placetype":"venue"
},
  "geometry": {"coordinates":[-1.0668480396,51.4346122742],"type":"Point"}
}