{
  "type": "Feature",
  "properties": {
    "addr:full":"4 Brocket Road Welwyn Garden City Hertfordshire AL8 7TY",
    "addr:housenumber":"4",
    "addr:postcode":"al8 7ty",
    "addr:street":"Brocket Road",
    "iso:country":"GB",
    "sg:address":"4 Brocket Road",
    "sg:city":"Welwyn Garden City",
    "sg:classifiers":[
        {
            "category":"Building & Trades",
            "subcategory":"Construction",
            "type":"Services"
        }
    ],
    "sg:postcode":"AL8 7TY",
    "sg:province":"Hertfordshire",
    "sg:tags":[
        "builder"
    ],
    "wof:name":"Michael J Comer",
    "wof:placetype":"venue"
},
  "geometry": {"coordinates":[-0.2260929942,51.78490448],"type":"Point"}
}