{
  "type": "Feature",
  "properties": {
    "iso:country":"GB",
    "sg:address":"16 Thackeray Square",
    "sg:city":"Fareham",
    "sg:classifiers":[
        {
            "category":"Shopping",
            "subcategory":"Pharmacy",
            "type":"Retail Goods"
        }
    ],
    "sg:phone":"+44 1329 280924",
    "sg:postcode":"PO16 0PG",
    "sg:province":"Hampshire",
    "sg:tags":[
        "pharmacist",
        "store",
        "drug",
        "chemist"
    ],
    "wof:name":"Superdrug Stores Plc",
    "wof:placetype":"venue"
},
  "geometry": {"coordinates":[-1.174099,50.852734],"type":"Point"}
}