{
  "type": "Feature",
  "properties": {
    "addr:full":"The Bungalow, Belmont Hospital, Belmont Road Tiverton Devon EX16 6QY",
    "addr:postcode":"ex16 6qy",
    "addr:street":"Belmont;Belmont Road",
    "iso:country":"GB",
    "sg:address":"The Bungalow, Belmont Hospital, Belmont Road",
    "sg:city":"Tiverton",
    "sg:classifiers":[
        {
            "category":"Farming",
            "subcategory":"Nursery",
            "type":"Manufacturing & Wholesale Goods"
        }
    ],
    "sg:phone":"+44 1884 243712",
    "sg:postcode":"EX16 6QY",
    "sg:province":"Devon",
    "sg:tags":[
        "creche"
    ],
    "wof:name":"Belmont Day Nursery",
    "wof:placetype":"venue"
},
  "geometry": {"coordinates":[-3.493149,50.905025],"type":"Point"}
}