{
  "type": "Feature",
  "properties": {
    "iso:country":"GB",
    "sg:address":"14-15 Eddison Road, Swan Industrial Estate",
    "sg:city":"Washington",
    "sg:classifiers":[
        {
            "category":"Home & Garden",
            "subcategory":"Household Appliances",
            "type":"Retail Goods"
        },
        {
            "category":"Retail",
            "subcategory":"Repair Shop",
            "type":"Services"
        }
    ],
    "sg:phone":"+44 191 415 5336",
    "sg:postcode":"NE38 8JH",
    "sg:province":"Durham",
    "sg:tags":[
        "machine",
        "electrical",
        "washing"
    ],
    "wof:name":"Beejay Repairs",
    "wof:placetype":"venue"
},
  "geometry": {"coordinates":[-1.506659,54.896744],"type":"Point"}
}