{
  "type": "Feature",
  "properties": {
    "addr:full":"Alexander House, 94 Talbot Road Manchester Cheshire M16 0PG",
    "addr:housenumber":"94",
    "addr:postcode":"m16 0pg",
    "addr:street":"Talbot Road",
    "iso:country":"GB",
    "sg:address":"Alexander House, 94 Talbot Road",
    "sg:city":"Manchester",
    "sg:classifiers":[
        {
            "category":"Professional",
            "subcategory":"Engineering",
            "type":"Services"
        }
    ],
    "sg:phone":"+44 161 831 5600",
    "sg:postcode":"M16 0PG",
    "sg:province":"Cheshire",
    "sg:tags":[
        "consulting",
        "engineer"
    ],
    "wof:name":"J M P CONSULTANTS LTD",
    "wof:placetype":"venue"
},
  "geometry": {"coordinates":[-2.2733490467,53.4528884888],"type":"Point"}
}