{
  "type": "Feature",
  "properties": {
    "addr:full":"14 Forsey Close Swindon Wiltshire SN3 5DQ",
    "addr:housenumber":"14",
    "addr:postcode":"sn3 5dq",
    "addr:street":"Forsey Close",
    "iso:country":"GB",
    "sg:address":"14 Forsey Close",
    "sg:city":"Swindon",
    "sg:classifiers":[
        {
            "category":"Building & Trades",
            "subcategory":"Construction",
            "type":"Services"
        }
    ],
    "sg:phone":"+44 1793 491197",
    "sg:postcode":"SN3 5DQ",
    "sg:province":"Wiltshire",
    "sg:tags":[
        "contractor",
        "paving",
        "driveway"
    ],
    "wof:name":"Reillys Block Paving",
    "wof:placetype":"venue"
},
  "geometry": {"coordinates":[-1.725346,51.566471],"type":"Point"}
}