{
  "type": "Feature",
  "properties": {
    "addr:full":"422 Upper Richmond Road West London Greater London SW14 7JX",
    "addr:housenumber":"422",
    "addr:postcode":"sw14 7jx",
    "addr:street":"Upper Richmond Road West",
    "iso:country":"GB",
    "sg:address":"422 Upper Richmond Road West",
    "sg:city":"London",
    "sg:classifiers":[
        {
            "category":"Personal",
            "subcategory":"Beauty Salon",
            "type":"Services"
        }
    ],
    "sg:phone":"+44 20 8392 1859",
    "sg:postcode":"SW14 7JX",
    "sg:province":"Greater London",
    "wof:name":"Impressions",
    "wof:placetype":"venue"
},
  "geometry": {"coordinates":[-0.2761490047,51.4644317627],"type":"Point"}
}