{
  "type": "Feature",
  "properties": {
    "addr:full":"50 Larkspur Gdns, Holbury Southampton Hampshire SO45 2QH",
    "addr:housenumber":"50",
    "addr:postcode":"so45 2qh",
    "addr:street":"Larkspur Gdns Holbury",
    "iso:country":"GB",
    "sg:address":"50 Larkspur Gdns, Holbury",
    "sg:city":"Southampton",
    "sg:classifiers":[
        {
            "category":"Professional",
            "subcategory":"Engineering",
            "type":"Services"
        }
    ],
    "sg:phone":"+44 23 8089 8644",
    "sg:postcode":"SO45 2QH",
    "sg:province":"Hampshire",
    "sg:tags":[
        "engineer",
        "mechanical"
    ],
    "wof:name":"Trykar Ltd",
    "wof:placetype":"venue"
},
  "geometry": {"coordinates":[-1.392788,50.833893],"type":"Point"}
}