{
  "type": "Feature",
  "properties": {
    "addr:full":"15 Briarfield Road, Farnworth Bolton Lancashire BL4 0HD",
    "addr:housenumber":"15",
    "addr:postcode":"bl4 0hd",
    "addr:street":"Briarfield Road",
    "iso:country":"GB",
    "sg:address":"15 Briarfield Road, Farnworth",
    "sg:city":"Bolton",
    "sg:classifiers":[
        {
            "category":"Building & Trades",
            "subcategory":"Construction",
            "type":"Services"
        }
    ],
    "sg:postcode":"BL4 0HD",
    "sg:province":"Lancashire",
    "sg:tags":[
        "builder"
    ],
    "wof:name":"K Murphy Builders",
    "wof:placetype":"venue"
},
  "geometry": {"coordinates":[-2.42165,53.550117],"type":"Point"}
}