{
  "type": "Feature",
  "properties": {
    "addr:full":"Runshaw Moor Farm, Runshaw Lane, Euxton Chorley Lancashire PR7 6HD",
    "addr:postcode":"pr7 6hd",
    "addr:street":"Runshaw Moor;Runshaw Lane",
    "iso:country":"GB",
    "sg:address":"Runshaw Moor Farm, Runshaw Lane, Euxton",
    "sg:city":"Chorley",
    "sg:classifiers":[
        {
            "category":"Farming",
            "subcategory":"Farm",
            "type":"Manufacturing & Wholesale Goods"
        }
    ],
    "sg:postcode":"PR7 6HD",
    "sg:province":"Lancashire",
    "sg:tags":[
        "mixed",
        "crop"
    ],
    "wof:name":"J J & E Grimshaw",
    "wof:placetype":"venue"
},
  "geometry": {"coordinates":[-2.6758608818,53.6690940857],"type":"Point"}
}