{
  "type": "Feature",
  "properties": {
    "addr:full":"1515 Dumbarton Road Glasgow Glasgow City G14 9XQ",
    "addr:housenumber":"1515",
    "addr:postcode":"g14 9xq",
    "addr:street":"Dumbarton Road",
    "iso:country":"GB",
    "sg:address":"1515 Dumbarton Road",
    "sg:city":"Glasgow",
    "sg:classifiers":[
        {
            "category":"Manufacturing",
            "subcategory":"Petroleum Products",
            "type":"Manufacturing & Wholesale Goods"
        }
    ],
    "sg:phone":"+44 141 950 2820",
    "sg:postcode":"G14 9XQ",
    "sg:province":"Glasgow City",
    "sg:tags":[
        "double",
        "glazing"
    ],
    "wof:name":"Sunshine Windows (Scotland) Ltd.",
    "wof:placetype":"venue"
},
  "geometry": {"coordinates":[-4.3497190475,55.8785438538],"type":"Point"}
}