{
  "type": "Feature",
  "properties": {
    "iso:country":"GB",
    "sg:address":"Kilbride Road",
    "sg:city":"Dunoon",
    "sg:classifiers":[
        {
            "category":"Professional",
            "subcategory":"Engineering",
            "type":"Services"
        }
    ],
    "sg:postcode":"PA23 7LN",
    "sg:province":"Argyll and Bute",
    "sg:tags":[
        "civil",
        "engineer"
    ],
    "wof:name":"Storie (Argyll) Ltd.",
    "wof:placetype":"venue"
},
  "geometry": {"coordinates":[-4.938499,55.944771],"type":"Point"}
}