{
  "type": "Feature",
  "properties": {
    "addr:full":"Roman Road, Mountnessing Brentwood Essex CM15 0TZ",
    "addr:postcode":"cm15 0tz",
    "addr:street":"Roman Road",
    "iso:country":"GB",
    "sg:address":"Roman Road, Mountnessing",
    "sg:city":"Brentwood",
    "sg:classifiers":[
        {
            "category":"Bars & Pubs",
            "type":"Food & Drink"
        },
        {
            "category":"Restaurant",
            "type":"Food & Drink"
        }
    ],
    "sg:phone":"+44 1277 352461",
    "sg:postcode":"CM15 0TZ",
    "sg:province":"Essex",
    "sg:tags":[
        "-"
    ],
    "sg:website":"http://www.whitbread.com",
    "wof:name":"The George & Dragon",
    "wof:placetype":"venue"
},
  "geometry": {"coordinates":[0.3464550078,51.6485786438],"type":"Point"}
}