{
  "type": "Feature",
  "properties": {
    "addr:full":"8-10 Burngreave Road Sheffield South Yorkshire S3 9DD",
    "addr:housenumber":"8-10",
    "addr:postcode":"s3 9dd",
    "addr:street":"Burngreave Road",
    "iso:country":"GB",
    "sg:address":"8-10 Burngreave Road",
    "sg:city":"Sheffield",
    "sg:classifiers":[
        {
            "category":"Retail",
            "subcategory":"Auto Repair",
            "type":"Services"
        }
    ],
    "sg:postcode":"S3 9DD",
    "sg:province":"South Yorkshire",
    "sg:tags":[
        "modification",
        "garage"
    ],
    "wof:name":"Curtis Motors Garage",
    "wof:placetype":"venue"
},
  "geometry": {"coordinates":[-1.459016,53.393372],"type":"Point"}
}