{
  "type": "Feature",
  "properties": {
    "iso:country":"GB",
    "sg:address":"5 Leighs Brow, Barnton",
    "sg:city":"Northwich",
    "sg:classifiers":[
        {
            "category":"Utilities",
            "type":"Services"
        }
    ],
    "sg:postcode":"CW8 4HT",
    "sg:province":"Cheshire",
    "sg:tags":[
        "internet"
    ],
    "wof:name":"Canal Junction Services",
    "wof:placetype":"venue"
},
  "geometry": {"coordinates":[-2.5840470791,53.280708313],"type":"Point"}
}