{
  "type": "Feature",
  "properties": {
    "addr:full":"Centre For Independant Living, Beaufort Street Warrington Cheshire WA5 1BA",
    "addr:postcode":"wa5 1ba",
    "addr:street":"Beaufort Street",
    "iso:country":"GB",
    "sg:address":"Centre For Independant Living, Beaufort Street",
    "sg:city":"Warrington",
    "sg:classifiers":[
        {
            "category":"Professional",
            "subcategory":"Computer Services",
            "type":"Services"
        }
    ],
    "sg:phone":"+44 1925 240064",
    "sg:postcode":"WA5 1BA",
    "sg:province":"Cheshire",
    "sg:tags":[
        "information"
    ],
    "wof:name":"Warrington Disability Information Services",
    "wof:placetype":"venue"
},
  "geometry": {"coordinates":[-2.6159899235,53.3858795166],"type":"Point"}
}