{
  "type": "Feature",
  "properties": {
    "iso:country":"GB",
    "sg:address":"Marine Building, Queen Anne Battery, Victoria Wharf",
    "sg:city":"Plymouth",
    "sg:classifiers":[
        {
            "category":"Professional",
            "subcategory":"Engineering",
            "type":"Services"
        },
        {
            "category":"Building & Trades",
            "subcategory":"Construction",
            "type":"Services"
        }
    ],
    "sg:phone":"+44 1752 252004",
    "sg:postcode":"PL4 0LP",
    "sg:province":"Devon",
    "sg:tags":[
        "civil",
        "equipment",
        "engineer"
    ],
    "wof:name":"Webb Construction",
    "wof:placetype":"venue"
},
  "geometry": {"coordinates":[-4.1327137947,50.3703842163],"type":"Point"}
}