{
  "type": "Feature",
  "properties": {
    "addr:full":"32 High Street, St Peters Broadstairs Kent CT10 2TQ",
    "addr:housenumber":"32",
    "addr:postcode":"ct10 2tq",
    "addr:street":"High Street",
    "iso:country":"GB",
    "sg:address":"32 High Street, St Peters",
    "sg:city":"Broadstairs",
    "sg:classifiers":[
        {
            "category":"Health Services",
            "subcategory":"Dentist",
            "type":"Services"
        }
    ],
    "sg:phone":"+44 1843 860625",
    "sg:postcode":"CT10 2TQ",
    "sg:province":"Kent",
    "wof:name":"The St Peters Dental Practice",
    "wof:placetype":"venue"
},
  "geometry": {"coordinates":[1.420754,51.364307],"type":"Point"}
}