{
  "type": "Feature",
  "properties": {
    "addr:full":"14d Oakfield Road, Clifton Bristol City of Bristol BS8 2AW",
    "addr:housenumber":"14d",
    "addr:postcode":"bs8 2aw",
    "addr:street":"Oakfield Road",
    "iso:country":"GB",
    "sg:address":"14d Oakfield Road, Clifton",
    "sg:city":"Bristol",
    "sg:classifiers":[
        {
            "category":"Professional",
            "subcategory":"Computer Services",
            "type":"Services"
        }
    ],
    "sg:postcode":"BS8 2AW",
    "sg:province":"City of Bristol",
    "sg:tags":[
        "system",
        "software"
    ],
    "wof:name":"Techcare Ltd",
    "wof:placetype":"venue"
},
  "geometry": {"coordinates":[-2.612671,51.459778],"type":"Point"}
}