{
  "type": "Feature",
  "properties": {
    "iso:country":"GB",
    "sg:address":"Unit No 2, Girton Street, Salford 7",
    "sg:city":"Manchester",
    "sg:classifiers":[
        {
            "category":"Professional",
            "subcategory":"Art Services",
            "type":"Services"
        }
    ],
    "sg:phone":"+44 161 832 5818",
    "sg:postcode":"M7 9UR",
    "sg:province":"Greater Manchester",
    "sg:tags":[
        "framing"
    ],
    "wof:name":"Classic Art Pictures Ltd.",
    "wof:placetype":"venue"
},
  "geometry": {"coordinates":[-2.2690401077,53.501789093],"type":"Point"}
}