{
  "type": "Feature",
  "properties": {
    "addr:full":"Unit 33 26-28 Queensway Enfield Greater London EN3 4SA",
    "addr:housenumber":"unit 33",
    "addr:postcode":"26-28;en3 4sa",
    "addr:street":"Queensway",
    "iso:country":"GB",
    "sg:address":"Unit 33 26-28 Queensway",
    "sg:city":"Enfield",
    "sg:classifiers":[
        {
            "category":"Wholesale",
            "subcategory":"Books, Periodicals, & Newspapers",
            "type":"Manufacturing & Wholesale Goods"
        }
    ],
    "sg:phone":"+44 20 8292 2191",
    "sg:postcode":"EN3 4SA",
    "sg:province":"Greater London",
    "sg:tags":[
        "publishing"
    ],
    "wof:name":"Brainded Publishing",
    "wof:placetype":"venue"
},
  "geometry": {"coordinates":[-0.0484599993,51.6464729309],"type":"Point"}
}