{
  "type": "Feature",
  "properties": {
    "iso:country":"GB",
    "sg:address":"3tansey Ct, Old School La",
    "sg:city":"Warwick",
    "sg:classifiers":[
        {
            "category":"Communications",
            "type":"Services"
        }
    ],
    "sg:phone":"+44 1926 651080",
    "sg:postcode":"CV35 0AX",
    "sg:province":"Warwickshire",
    "sg:tags":[
        "telecommunication"
    ],
    "wof:name":"Linear Consultants",
    "wof:placetype":"venue"
},
  "geometry": {"coordinates":[-1.5019580126,52.1995887756],"type":"Point"}
}