{
  "type": "Feature",
  "properties": {
    "iso:country":"GB",
    "sg:address":"17 Crescent Rd",
    "sg:city":"Worthing",
    "sg:classifiers":[
        {
            "category":"Sports & Exercise",
            "subcategory":"Sports Center",
            "type":"Entertainment"
        }
    ],
    "sg:phone":"+44 1903 823990",
    "sg:postcode":"BN11 1RL",
    "sg:province":"West Sussex",
    "sg:tags":[
        "shop",
        "good"
    ],
    "wof:name":"Zavo Ltd",
    "wof:placetype":"venue"
},
  "geometry": {"coordinates":[-0.3766750097,50.8111724854],"type":"Point"}
}