{
  "type": "Feature",
  "properties": {
    "addr:full":"44 Kenilworth Drive, Oadby Industrial Estate, Oadby Leicester Leicestershire LE2 5LG",
    "addr:housenumber":"44",
    "addr:postcode":"le2 5lg",
    "addr:street":"Kenilworth Drive;Industrial Estate",
    "iso:country":"GB",
    "sg:address":"44 Kenilworth Drive, Oadby Industrial Estate, Oadby",
    "sg:city":"Leicester",
    "sg:classifiers":[
        {
            "category":"Retail",
            "subcategory":"Car Wash",
            "type":"Services"
        },
        {
            "category":"Home & Garden",
            "subcategory":"Hardware",
            "type":"Retail Goods"
        }
    ],
    "sg:phone":"+44 116 271 0401",
    "sg:postcode":"LE2 5LG",
    "sg:province":"Leicestershire",
    "sg:tags":[
        "compressor",
        "gas",
        "air"
    ],
    "wof:name":"Cooper Freer Ltd",
    "wof:placetype":"venue"
},
  "geometry": {"coordinates":[-1.0910520554,52.5957107544],"type":"Point"}
}