{
  "type": "Feature",
  "properties": {
    "addr:full":"21 Brassey Avenue Eastbourne East Sussex BN22 9NH",
    "addr:housenumber":"21",
    "addr:postcode":"bn22 9nh",
    "addr:street":"Brassey Avenue",
    "iso:country":"GB",
    "sg:address":"21 Brassey Avenue",
    "sg:city":"Eastbourne",
    "sg:classifiers":[
        {
            "category":"Shopping",
            "subcategory":"Florist",
            "type":"Retail Goods"
        }
    ],
    "sg:postcode":"BN22 9NH",
    "sg:province":"East Sussex",
    "wof:name":"Paula Ann's",
    "wof:placetype":"venue"
},
  "geometry": {"coordinates":[0.2778330147,50.7967376709],"type":"Point"}
}