{
  "type": "Feature",
  "properties": {
    "addr:full":"Suite 120 Silk House, Park Green Macclesfield Cheshire SK11 7QJ",
    "addr:housenumber":"suite 120 silk house",
    "addr:postcode":"sk11 7qj",
    "addr:street":"Park Green",
    "iso:country":"GB",
    "sg:address":"Suite 120 Silk House, Park Green",
    "sg:city":"Macclesfield",
    "sg:classifiers":[
        {
            "category":"Professional",
            "subcategory":"Business Services",
            "type":"Services"
        }
    ],
    "sg:postcode":"SK11 7QJ",
    "sg:province":"Cheshire",
    "sg:tags":[
        "holding"
    ],
    "wof:name":"Sovereign Group Holdings Ltd",
    "wof:placetype":"venue"
},
  "geometry": {"coordinates":[-2.1223890781,53.2561645508],"type":"Point"}
}