{
  "type": "Feature",
  "properties": {
    "addr:full":"Brook Lane, Clowne Chesterfield Derbyshire S43 4RY",
    "addr:postcode":"s43 4ry",
    "addr:street":"Brook Lane",
    "iso:country":"GB",
    "sg:address":"Brook Lane, Clowne",
    "sg:city":"Chesterfield",
    "sg:classifiers":[
        {
            "category":"Social Services",
            "subcategory":"Retirement Home",
            "type":"Services"
        }
    ],
    "sg:postcode":"S43 4RY",
    "sg:province":"Derbyshire",
    "sg:tags":[
        "residential",
        "care"
    ],
    "wof:name":"Brookcroft Residential Care Home",
    "wof:placetype":"venue"
},
  "geometry": {"coordinates":[-1.26326,53.274757],"type":"Point"}
}