{
  "type": "Feature",
  "properties": {
    "addr:full":"Fenton Lane, Sherburn In Elmet Leeds North Yorkshire LS25 6EZ",
    "addr:postcode":"ls25 6ez",
    "addr:street":"Fenton Lane",
    "iso:country":"GB",
    "sg:address":"Fenton Lane, Sherburn In Elmet",
    "sg:city":"Leeds",
    "sg:classifiers":[
        {
            "category":"Freight",
            "type":"Transportation"
        }
    ],
    "sg:phone":"+44 1977 685022",
    "sg:postcode":"LS25 6EZ",
    "sg:province":"North Yorkshire",
    "sg:tags":[
        "haulage",
        "road"
    ],
    "wof:name":"Fergusons (Blyth) Ltd.",
    "wof:placetype":"venue"
},
  "geometry": {"coordinates":[-1.2311990261,53.7973632812],"type":"Point"}
}