{
  "type": "Feature",
  "properties": {
    "iso:country":"GB",
    "sg:address":"5 Royer Close, Clements Hall Way, Hawkwell",
    "sg:city":"Hockley",
    "sg:classifiers":[
        {
            "category":"Manufacturing",
            "subcategory":"Petroleum Products",
            "type":"Manufacturing & Wholesale Goods"
        }
    ],
    "sg:postcode":"SS5 4LR",
    "sg:province":"Essex",
    "sg:tags":[
        "double",
        "glazing"
    ],
    "wof:name":"Double Vision",
    "wof:placetype":"venue"
},
  "geometry": {"coordinates":[0.6733469963,51.5928497314],"type":"Point"}
}