{
  "type": "Feature",
  "properties": {
    "iso:country":"GB",
    "sg:address":"267 Chorley Road, Standish",
    "sg:city":"Wigan",
    "sg:classifiers":[
        {
            "category":"Personal",
            "subcategory":"Beauty Salon",
            "type":"Services"
        }
    ],
    "sg:phone":"+44 1257 424353",
    "sg:postcode":"WN1 2TX",
    "sg:province":"Lancashire",
    "sg:tags":[
        "unisex",
        "hairdresser"
    ],
    "wof:name":"Renoir Hair Studio",
    "wof:placetype":"venue"
},
  "geometry": {"coordinates":[-2.637673,53.585926],"type":"Point"}
}