{
  "type": "Feature",
  "properties": {
    "iso:country":"GB",
    "sg:address":"Clifftown Rd",
    "sg:city":"Southend-on-sea",
    "sg:classifiers":[
        {
            "category":"Bars & Pubs",
            "type":"Food & Drink"
        }
    ],
    "sg:postcode":"SS1 1AJ",
    "sg:province":"Essex",
    "sg:tags":[
        "pubs",
        "inn"
    ],
    "wof:name":"Jennings,T,",
    "wof:placetype":"venue"
},
  "geometry": {"coordinates":[0.712412,51.53693],"type":"Point"}
}