{
  "type": "Feature",
  "properties": {
    "iso:country":"GB",
    "sg:address":"128b Milton Road",
    "sg:city":"Gravesend",
    "sg:classifiers":[
        {
            "category":"Shopping",
            "subcategory":"Party Supplies",
            "type":"Retail Goods"
        }
    ],
    "sg:phone":"+44 1474 566024",
    "sg:postcode":"DA12 2PG",
    "sg:province":"Kent",
    "sg:tags":[
        "equipment",
        "disco"
    ],
    "wof:name":"Gravesend Sound & Lighting",
    "wof:placetype":"venue"
},
  "geometry": {"coordinates":[0.375707,51.440762],"type":"Point"}
}