{
  "type": "Feature",
  "properties": {
    "iso:country":"GB",
    "sg:address":"Dersingham Library, Chapel Road, Dersingham",
    "sg:city":"King's Lynn",
    "sg:classifiers":[
        {
            "category":"Education",
            "subcategory":"Library",
            "type":"Public Place"
        }
    ],
    "sg:phone":"+44 1485 540181",
    "sg:postcode":"PE31 6PN",
    "sg:province":"Norfolk",
    "sg:tags":[
        "book"
    ],
    "wof:name":"Kings Lynn & West Norfolk Borough Council",
    "wof:placetype":"venue"
},
  "geometry": {"coordinates":[0.5052800179,52.8479614258],"type":"Point"}
}