{
  "type": "Feature",
  "properties": {
    "addr:full":"Prizewood Road Taunton Somerset TA2 8DN",
    "addr:postcode":"ta2 8dn",
    "addr:street":"Prizewood Road",
    "iso:country":"GB",
    "sg:address":"Prizewood Road",
    "sg:city":"Taunton",
    "sg:classifiers":[
        {
            "category":"Autos & Motor Vehicles",
            "subcategory":"Automobile Sales",
            "type":"Retail Goods"
        }
    ],
    "sg:phone":"+44 1823 321321",
    "sg:postcode":"TA2 8DN",
    "sg:province":"Somerset",
    "sg:tags":[
        "car"
    ],
    "wof:name":"Howards Taunton",
    "wof:placetype":"venue"
},
  "geometry": {"coordinates":[-3.0860381126,51.0285682678],"type":"Point"}
}