{
  "type": "Feature",
  "properties": {
    "addr:full":"5 Terrace Road Aberystwyth Ceredigion SY23 1NY",
    "addr:housenumber":"5",
    "addr:postcode":"sy23 1ny",
    "addr:street":"Terrace Road",
    "iso:country":"GB",
    "sg:address":"5 Terrace Road",
    "sg:city":"Aberystwyth",
    "sg:classifiers":[
        {
            "category":"Real Estate",
            "subcategory":"Real Estate Agent",
            "type":"Services"
        }
    ],
    "sg:phone":"+44 1970 612310",
    "sg:postcode":"SY23 1NY",
    "sg:province":"Ceredigion",
    "wof:name":"John Francis",
    "wof:placetype":"venue"
},
  "geometry": {"coordinates":[-4.082356,52.41544],"type":"Point"}
}