{
  "type": "Feature",
  "properties": {
    "addr:full":"25 Main Street, Ponteland Newcastle-upon-tyne Northumberland NE20 9NH",
    "addr:housenumber":"25",
    "addr:postcode":"ne20 9nh",
    "addr:street":"Main Street",
    "iso:country":"GB",
    "sg:address":"25 Main Street, Ponteland",
    "sg:city":"Newcastle-upon-tyne",
    "sg:classifiers":[
        {
            "category":"Health Services",
            "subcategory":"Optometrist",
            "type":"Services"
        },
        {
            "category":"Shopping",
            "subcategory":"Optician",
            "type":"Retail Goods"
        }
    ],
    "sg:phone":"+44 1661 823374",
    "sg:postcode":"NE20 9NH",
    "sg:province":"Northumberland",
    "sg:tags":[
        "ophthalmic"
    ],
    "wof:name":"Mackley & Studdert",
    "wof:placetype":"venue"
},
  "geometry": {"coordinates":[-1.744638,55.049343],"type":"Point"}
}