{
  "type": "Feature",
  "properties": {
    "addr:full":"17 West Register Street Edinburgh City of Edinburgh EH2 2AA",
    "addr:housenumber":"17",
    "addr:postcode":"eh2 2aa",
    "addr:street":"West Register Street",
    "iso:country":"GB",
    "sg:address":"17 West Register Street",
    "sg:city":"Edinburgh",
    "sg:classifiers":[
        {
            "category":"Bars & Pubs",
            "type":"Food & Drink"
        },
        {
            "category":"Manufacturing",
            "subcategory":"Motor Vehicles & Parts",
            "type":"Manufacturing & Wholesale Goods"
        }
    ],
    "sg:phone":"+44 131 557 4792",
    "sg:postcode":"EH2 2AA",
    "sg:province":"City of Edinburgh",
    "sg:tags":[
        "pubs",
        "inn",
        "component",
        "manufacturer"
    ],
    "wof:name":"BRINGHURST TAVERNS LTD",
    "wof:placetype":"venue"
},
  "geometry": {"coordinates":[-3.1905760765,55.953754425],"type":"Point"}
}