{
  "type": "Feature",
  "properties": {
    "addr:full":"110 St Marks Road Enfield Greater London EN1 1BB",
    "addr:housenumber":"110",
    "addr:postcode":"en1 1bb",
    "addr:street":"St Marks Road",
    "iso:country":"GB",
    "sg:address":"110 St Marks Road",
    "sg:city":"Enfield",
    "sg:classifiers":[
        {
            "category":"Personal",
            "subcategory":"Barber",
            "type":"Services"
        }
    ],
    "sg:phone":"+44 20 8245 6791",
    "sg:postcode":"EN1 1BB",
    "sg:province":"Greater London",
    "sg:tags":[
        "men's",
        "hairdresser"
    ],
    "wof:name":"Rodneys",
    "wof:placetype":"venue"
},
  "geometry": {"coordinates":[-0.0680790022,51.6418075562],"type":"Point"}
}