{
  "type": "Feature",
  "properties": {
    "addr:full":"51 Clapham High St Clapham Greater London SW4 7TL",
    "addr:housenumber":"51",
    "addr:postcode":"sw4 7tl",
    "addr:street":"Clapham High St",
    "iso:country":"GB",
    "sg:address":"51 Clapham High St",
    "sg:city":"Clapham",
    "sg:classifiers":[
        {
            "category":"Health Services",
            "subcategory":"Doctor",
            "type":"Services"
        }
    ],
    "sg:phone":"+44 20 7622 4455",
    "sg:postcode":"SW4 7TL",
    "sg:province":"Greater London",
    "sg:tags":[
        "practitioners"
    ],
    "wof:name":"Clapham Family Practice",
    "wof:placetype":"venue"
},
  "geometry": {"coordinates":[-0.1326300055,51.4637336731],"type":"Point"}
}