{
  "type": "Feature",
  "properties": {
    "addr:full":"Kelsick Old Hall, Church St Ambleside Cumbria LA22 0BU",
    "addr:postcode":"la22 0bu",
    "addr:street":"Church St",
    "iso:country":"GB",
    "sg:address":"Kelsick Old Hall, Church St",
    "sg:city":"Ambleside",
    "sg:classifiers":[
        {
            "category":"Restaurant",
            "type":"Food & Drink"
        }
    ],
    "sg:phone":"+44 15394 33332",
    "sg:postcode":"LA22 0BU",
    "sg:province":"Cumbria",
    "wof:name":"Lynchristies Of Ambleside",
    "wof:placetype":"venue"
},
  "geometry": {"coordinates":[-2.963401,54.429897],"type":"Point"}
}