{
  "type": "Feature",
  "properties": {
    "iso:country":"GB",
    "sg:address":"12 Barns Road, Warkworth",
    "sg:city":"Morpeth",
    "sg:classifiers":[
        {
            "category":"Home & Garden",
            "subcategory":"Building Materials",
            "type":"Retail Goods"
        }
    ],
    "sg:postcode":"NE65 0TS",
    "sg:province":"Northumberland",
    "sg:tags":[
        "fencing"
    ],
    "wof:name":"T J Scott",
    "wof:placetype":"venue"
},
  "geometry": {"coordinates":[-1.6153719425,55.3413391113],"type":"Point"}
}