{
  "type": "Feature",
  "properties": {
    "addr:full":"16 New Street Stourport-on-severn Worcestershire DY13 8UW",
    "addr:housenumber":"16",
    "addr:postcode":"dy13 8uw",
    "addr:street":"New Street",
    "iso:country":"GB",
    "sg:address":"16 New Street",
    "sg:city":"Stourport-on-severn",
    "sg:classifiers":[
        {
            "category":"Real Estate",
            "subcategory":"Architect",
            "type":"Services"
        }
    ],
    "sg:phone":"+44 1299 827760",
    "sg:postcode":"DY13 8UW",
    "sg:province":"Worcestershire",
    "wof:name":"Perkins & Evans Design Group",
    "wof:placetype":"venue"
},
  "geometry": {"coordinates":[-2.2810211182,52.3395271301],"type":"Point"}
}