{
  "type": "Feature",
  "properties": {
    "iso:country":"GB",
    "sg:address":"19 The Mall, Eccles",
    "sg:city":"Manchester",
    "sg:classifiers":[
        {
            "category":"Cafe",
            "type":"Food & Drink"
        },
        {
            "category":"Food & Beverages",
            "subcategory":"Meat & Fish",
            "type":"Retail Goods"
        }
    ],
    "sg:postcode":"M30 0EA",
    "sg:province":"Greater Manchester",
    "sg:tags":[
        "chip",
        "snack",
        "bar"
    ],
    "wof:name":"Kingfisher",
    "wof:placetype":"venue"
},
  "geometry": {"coordinates":[-2.344437,53.482872],"type":"Point"}
}