{
  "type": "Feature",
  "properties": {
    "addr:full":"49 Fennel Close, Chineham Basingstoke Hampshire RG24 8XF",
    "addr:housenumber":"49",
    "addr:postcode":"rg24 8xf",
    "addr:street":"Fennel Close",
    "iso:country":"GB",
    "sg:address":"49 Fennel Close, Chineham",
    "sg:city":"Basingstoke",
    "sg:classifiers":[
        {
            "category":"Professional",
            "subcategory":"Management & Consulting",
            "type":"Services"
        }
    ],
    "sg:phone":"+44 1256 356151",
    "sg:postcode":"RG24 8XF",
    "sg:province":"Hampshire",
    "sg:tags":[
        "consultant",
        "business"
    ],
    "wof:name":"M.D Associates",
    "wof:placetype":"venue"
},
  "geometry": {"coordinates":[-1.0506980419,51.29845047],"type":"Point"}
}