{
  "type": "Feature",
  "properties": {
    "iso:country":"GB",
    "sg:address":"51-53 Basingstoke Road",
    "sg:city":"Reading",
    "sg:classifiers":[
        {
            "category":"Professional",
            "subcategory":"Employment Agencies",
            "type":"Services"
        }
    ],
    "sg:phone":"+44 118 987 1133",
    "sg:postcode":"RG2 0ER",
    "sg:province":"Berkshire",
    "sg:tags":[
        "consultant"
    ],
    "wof:name":"P T Recruitment Ltd.",
    "wof:placetype":"venue"
},
  "geometry": {"coordinates":[-0.966456,51.440231],"type":"Point"}
}