{
  "type": "Feature",
  "properties": {
    "iso:country":"GB",
    "sg:address":"54 Belsize Ave, Palmers Grn",
    "sg:city":"London",
    "sg:classifiers":[
        {
            "category":"Professional",
            "subcategory":"Management & Consulting",
            "type":"Services"
        }
    ],
    "sg:phone":"+44 20 8888 7006",
    "sg:postcode":"N13 4TJ",
    "sg:province":"Greater London",
    "sg:tags":[
        "marketing",
        "consultant"
    ],
    "wof:name":"Alizarin Ltd",
    "wof:placetype":"venue"
},
  "geometry": {"coordinates":[-0.113338,51.60973],"type":"Point"}
}