{
  "type": "Feature",
  "properties": {
    "iso:country":"GB",
    "sg:address":"Unit 7 Wheatear, Perry Rd",
    "sg:city":"Witham",
    "sg:classifiers":[
        {
            "category":"Shopping",
            "subcategory":"Computers & Home Electronics",
            "type":"Retail Goods"
        }
    ],
    "sg:phone":"+44 1376 520515",
    "sg:postcode":"CM8 3YY",
    "sg:province":"Essex",
    "sg:tags":[
        "equipment",
        "radio"
    ],
    "wof:name":"C B Witham Centre",
    "wof:placetype":"venue"
},
  "geometry": {"coordinates":[0.639991,51.800713],"type":"Point"}
}