{
  "type": "Feature",
  "properties": {
    "addr:full":"Cross & Pillory House, Cross & Pillory Lane Alton Hampshire GU34 1HL",
    "addr:postcode":"gu34 1hl",
    "addr:street":"Lane",
    "iso:country":"GB",
    "sg:address":"Cross & Pillory House, Cross & Pillory Lane",
    "sg:city":"Alton",
    "sg:classifiers":[
        {
            "category":"Professional",
            "subcategory":"Computer Services",
            "type":"Services"
        }
    ],
    "sg:phone":"+44 1420 547500",
    "sg:postcode":"GU34 1HL",
    "sg:province":"Hampshire",
    "sg:tags":[
        "consultant",
        "system",
        "software"
    ],
    "wof:name":"Triangle Development Services Ltd.",
    "wof:placetype":"venue"
},
  "geometry": {"coordinates":[-0.97775,51.148392],"type":"Point"}
}