{
  "type": "Feature",
  "properties": {
    "addr:full":"Lakeside Service Station, Sturry Road Canterbury Kent CT1 1DS",
    "addr:postcode":"ct1 1ds",
    "addr:street":"Sturry Road",
    "iso:country":"GB",
    "sg:address":"Lakeside Service Station, Sturry Road",
    "sg:city":"Canterbury",
    "sg:classifiers":[
        {
            "category":"Autos & Motor Vehicles",
            "subcategory":"Auto Supplies",
            "type":"Retail Goods"
        }
    ],
    "sg:phone":"+44 1227 762791",
    "sg:postcode":"CT1 1DS",
    "sg:province":"Kent",
    "sg:tags":[
        "car",
        "audio"
    ],
    "wof:name":"Canterbury Car Radio Centre",
    "wof:placetype":"venue"
},
  "geometry": {"coordinates":[1.0756100416,51.275970459],"type":"Point"}
}