{
  "type": "Feature",
  "properties": {
    "addr:full":"York Chiropractic Clinic, 312 Stockton La York East Riding of Yorkshire YO3 0JW",
    "addr:housenumber":"312",
    "addr:postcode":"yo3 0jw",
    "addr:street":"Stockton La York",
    "iso:country":"GB",
    "sg:address":"York Chiropractic Clinic, 312 Stockton La",
    "sg:city":"York",
    "sg:classifiers":[
        {
            "category":"Health Services",
            "subcategory":"Chiropractor",
            "type":"Services"
        }
    ],
    "sg:phone":"+44 1904 430300",
    "sg:postcode":"YO3 0JW",
    "sg:province":"East Riding of Yorkshire",
    "wof:name":"B Ward",
    "wof:placetype":"venue"
},
  "geometry": {"coordinates":[-1.0834200382,53.9533309937],"type":"Point"}
}