{
  "type": "Feature",
  "properties": {
    "iso:country":"GB",
    "sg:address":"Unit 2, Glantwymyn Village Workshop, Cemmaes Road",
    "sg:city":"Machynlleth",
    "sg:classifiers":[
        {
            "category":"Utilities",
            "subcategory":"Natural Gas",
            "type":"Services"
        }
    ],
    "sg:phone":"+44 1650 511809",
    "sg:postcode":"SY20 8LY",
    "sg:province":"Ceredigion",
    "sg:tags":[
        "windmill",
        "power",
        "wind"
    ],
    "wof:name":"NEG Micon UK Ltd",
    "wof:placetype":"venue"
},
  "geometry": {"coordinates":[-3.8467230797,52.5909614563],"type":"Point"}
}