{
  "type": "Feature",
  "properties": {
    "addr:full":"Suite C Kings Chambers, Queens Road Coventry West Midlands CV1 3EH",
    "addr:housenumber":"suite c",
    "addr:postcode":"cv1 3eh",
    "addr:street":"Kings Chambers Queens Road",
    "iso:country":"GB",
    "sg:address":"Suite C Kings Chambers, Queens Road",
    "sg:city":"Coventry",
    "sg:classifiers":[
        {
            "category":"Real Estate",
            "subcategory":"Surveying",
            "type":"Services"
        }
    ],
    "sg:phone":"+44 24 7625 6888",
    "sg:postcode":"CV1 3EH",
    "sg:province":"West Midlands",
    "sg:tags":[
        "surveyor",
        "quantity"
    ],
    "wof:name":"Wilson Large & Partners",
    "wof:placetype":"venue"
},
  "geometry": {"coordinates":[-1.507768,52.406986],"type":"Point"}
}