{
  "type": "Feature",
  "properties": {
    "addr:full":"32 Hexworthy Avenue Coventry Warwickshire CV3 6LT",
    "addr:housenumber":"32",
    "addr:postcode":"cv3 6lt",
    "addr:street":"Hexworthy Avenue",
    "iso:country":"GB",
    "sg:address":"32 Hexworthy Avenue",
    "sg:city":"Coventry",
    "sg:classifiers":[
        {
            "category":"Personal",
            "subcategory":"Beauty Salon",
            "type":"Services"
        },
        {
            "category":"Personal",
            "subcategory":"Barber",
            "type":"Services"
        }
    ],
    "sg:phone":"+44 24 7641 3088",
    "sg:postcode":"CV3 6LT",
    "sg:province":"Warwickshire",
    "sg:tags":[
        "unisex",
        "hairdresser"
    ],
    "wof:name":"Quality Hair Design",
    "wof:placetype":"venue"
},
  "geometry": {"coordinates":[-1.5221810341,52.3835105896],"type":"Point"}
}