{
  "type": "Feature",
  "properties": {
    "iso:country":"GB",
    "sg:address":"199-201 Balgreen Road",
    "sg:city":"Edinburgh",
    "sg:classifiers":[
        {
            "category":"Shopping",
            "subcategory":"Crafts & Fabrics",
            "type":"Retail Goods"
        }
    ],
    "sg:phone":"+44 131 346 0990",
    "sg:postcode":"EH11 2RZ",
    "sg:province":"City of Edinburgh",
    "sg:tags":[
        "machine",
        "sewing",
        "knitting"
    ],
    "wof:name":"Sewing Centre (Edinburgh) Ltd.",
    "wof:placetype":"venue"
},
  "geometry": {"coordinates":[-3.2459709644,55.9345054626],"type":"Point"}
}