{
  "type": "Feature",
  "properties": {
    "iso:country":"GB",
    "sg:address":"Bayton Road, Exhall",
    "sg:city":"Coventry",
    "sg:classifiers":[
        {
            "category":"Manufacturing",
            "subcategory":"Metals",
            "type":"Manufacturing & Wholesale Goods"
        },
        {
            "category":"Wholesale",
            "subcategory":"Construction Materials",
            "type":"Manufacturing & Wholesale Goods"
        }
    ],
    "sg:phone":"+44 24 7636 1101",
    "sg:postcode":"CV7 9EJ",
    "sg:province":"Warwickshire",
    "sg:tags":[
        "coating",
        "powder"
    ],
    "wof:name":"Foleshill Plating Co. Ltd.",
    "wof:placetype":"venue"
},
  "geometry": {"coordinates":[-1.482574,52.465111],"type":"Point"}
}