{
  "type": "Feature",
  "properties": {
    "addr:full":"Unit 5 Penny Lane, Furtherwick Road Canvey Island Essex SS8 7AJ",
    "addr:housenumber":"unit 5",
    "addr:postcode":"ss8 7aj",
    "addr:street":"Penny Lane Furtherwick Road",
    "iso:country":"GB",
    "sg:address":"Unit 5 Penny Lane, Furtherwick Road",
    "sg:city":"Canvey Island",
    "sg:classifiers":[
        {
            "category":"Personal",
            "type":"Services"
        }
    ],
    "sg:postcode":"SS8 7AJ",
    "sg:province":"Essex",
    "sg:tags":[
        "wedding"
    ],
    "wof:name":"Country Corner Crafts",
    "wof:placetype":"venue"
},
  "geometry": {"coordinates":[0.592413,51.522285],"type":"Point"}
}