{
  "type": "Feature",
  "properties": {
    "addr:full":"Hurst Lane, Fishers Pond Eastleigh Hampshire SO50 7NQ",
    "addr:postcode":"so50 7nq",
    "addr:street":"Hurst Lane;Pond",
    "iso:country":"GB",
    "sg:address":"Hurst Lane, Fishers Pond",
    "sg:city":"Eastleigh",
    "sg:classifiers":[
        {
            "category":"Military Area",
            "subcategory":"Air Force Base",
            "type":"Public Place"
        }
    ],
    "sg:phone":"+44 1962 777751",
    "sg:postcode":"SO50 7NQ",
    "sg:province":"Hampshire",
    "sg:tags":[
        "water",
        "treatment"
    ],
    "wof:name":"Aqua Techniks",
    "wof:placetype":"venue"
},
  "geometry": {"coordinates":[-1.3058160543,50.984413147],"type":"Point"}
}