{
  "type": "Feature",
  "properties": {
    "addr:full":"18-19 Bourne Enterprise Centre, Wrotham Road, Borough Green Sevenoaks Kent TN15 8DG",
    "addr:housenumber":"18-19",
    "addr:postcode":"tn15 8dg",
    "addr:street":"Bourne Enterprise Centre Wrotham Road",
    "iso:country":"GB",
    "sg:address":"18-19 Bourne Enterprise Centre, Wrotham Road, Borough Green",
    "sg:city":"Sevenoaks",
    "sg:classifiers":[
        {
            "category":"Professional",
            "subcategory":"Engineering",
            "type":"Services"
        }
    ],
    "sg:phone":"+44 1732 882044",
    "sg:postcode":"TN15 8DG",
    "sg:province":"Kent",
    "sg:tags":[
        "consulting",
        "engineer"
    ],
    "wof:name":"Pollution & Process Monitoring Ltd.",
    "wof:placetype":"venue"
},
  "geometry": {"coordinates":[0.3112010062,51.2904701233],"type":"Point"}
}