{
  "type": "Feature",
  "properties": {
    "iso:country":"GB",
    "sg:address":"28 Springmead Drive, Garforth",
    "sg:city":"Leeds",
    "sg:classifiers":[
        {
            "category":"Retail",
            "subcategory":"Veterinary Services",
            "type":"Services"
        }
    ],
    "sg:phone":"+44 113 232 0030",
    "sg:postcode":"LS25 1JW",
    "sg:province":"North Yorkshire",
    "sg:tags":[
        "surgeon",
        "activity"
    ],
    "wof:name":"Beechwood Veterinary Group",
    "wof:placetype":"venue"
},
  "geometry": {"coordinates":[-1.383656,53.789658],"type":"Point"}
}