{
  "type": "Feature",
  "properties": {
    "addr:full":"23 Mayfield Road Leicester Leicestershire LE2 1LR",
    "addr:housenumber":"23",
    "addr:postcode":"le2 1lr",
    "addr:street":"Mayfield Road",
    "iso:country":"GB",
    "sg:address":"23 Mayfield Road",
    "sg:city":"Leicester",
    "sg:classifiers":[
        {
            "category":"Social Services",
            "type":"Services"
        },
        {
            "category":"Food & Beverages",
            "subcategory":"Liquor & Beverages",
            "type":"Retail Goods"
        }
    ],
    "sg:phone":"+44 116 254 4003",
    "sg:postcode":"LE2 1LR",
    "sg:province":"Leicestershire",
    "sg:tags":[
        "beer",
        "spirit",
        "wine"
    ],
    "wof:name":"Mayfield News",
    "wof:placetype":"venue"
},
  "geometry": {"coordinates":[-1.1134669781,52.6244888306],"type":"Point"}
}