{
  "type": "Feature",
  "properties": {
    "iso:country":"GB",
    "sg:address":"38 North Road",
    "sg:city":"St Helens",
    "sg:classifiers":[
        {
            "category":"Restaurant",
            "type":"Food & Drink"
        }
    ],
    "sg:phone":"+44 1744 613731",
    "sg:postcode":"WA10 2TR",
    "sg:province":"Merseyside",
    "wof:name":"Larkin's Restaurant",
    "wof:placetype":"venue"
},
  "geometry": {"coordinates":[-2.739322,53.457096],"type":"Point"}
}