{
  "type": "Feature",
  "properties": {
    "addr:full":"Unit 1a, 70 Dale Street Manchester Greater Manchester M1 2HR",
    "addr:housenumber":"unit 1a 70",
    "addr:postcode":"m1 2hr",
    "addr:street":"Dale Street",
    "iso:country":"GB",
    "sg:address":"Unit 1a, 70 Dale Street",
    "sg:city":"Manchester",
    "sg:classifiers":[
        {
            "category":"Travel",
            "subcategory":"Travel Agent",
            "type":"Entertainment"
        }
    ],
    "sg:phone":"+44 161 228 1833",
    "sg:postcode":"M1 2HR",
    "sg:province":"Greater Manchester",
    "wof:name":"Dawson & Sanderson Ltd.",
    "wof:placetype":"venue"
},
  "geometry": {"coordinates":[-2.232578,53.480362],"type":"Point"}
}