{
  "type": "Feature",
  "properties": {
    "iso:country":"GB",
    "sg:address":"Care Of Co-op 12 South Street",
    "sg:city":"Ilkeston",
    "sg:classifiers":[
        {
            "category":"Shopping",
            "subcategory":"Books",
            "type":"Retail Goods"
        }
    ],
    "sg:phone":"+44 115 930 6362",
    "sg:postcode":"DE7 5SG",
    "sg:province":"Derbyshire",
    "sg:tags":[
        "bookseller"
    ],
    "wof:name":"Book Thrift",
    "wof:placetype":"venue"
},
  "geometry": {"coordinates":[-1.3101890087,52.9786109924],"type":"Point"}
}