{
  "type": "Feature",
  "properties": {
    "addr:full":"Unit 2 Minerva House, Calleva Park, Aldermaston Reading Berkshire RG7 8NA",
    "addr:housenumber":"unit 2",
    "addr:postcode":"rg7 8na",
    "addr:street":"Calleva",
    "iso:country":"GB",
    "sg:address":"Unit 2 Minerva House, Calleva Park, Aldermaston",
    "sg:city":"Reading",
    "sg:classifiers":[
        {
            "category":"Professional",
            "subcategory":"Art Services",
            "type":"Services"
        }
    ],
    "sg:postcode":"RG7 8NA",
    "sg:province":"Berkshire",
    "sg:tags":[
        "graphic",
        "designer"
    ],
    "wof:name":"Lines & Words",
    "wof:placetype":"venue"
},
  "geometry": {"coordinates":[-1.16395,51.36179],"type":"Point"}
}