{
  "type": "Feature",
  "properties": {
    "iso:country":"GB",
    "sg:address":"16 Hazelwood, Great Linford",
    "sg:city":"Milton Keynes",
    "sg:classifiers":[
        {
            "category":"Shopping",
            "subcategory":"Party Supplies",
            "type":"Retail Goods"
        },
        {
            "category":"Arts & Performance",
            "subcategory":"Music",
            "type":"Entertainment"
        }
    ],
    "sg:phone":"+44 1908 605040",
    "sg:postcode":"MK14 5DU",
    "sg:province":"Buckinghamshire",
    "sg:tags":[
        "mobile",
        "operator",
        "disco"
    ],
    "wof:name":"Night Patrol Disco",
    "wof:placetype":"venue"
},
  "geometry": {"coordinates":[-0.752933979,52.0667533875],"type":"Point"}
}