{
  "type": "Feature",
  "properties": {
    "addr:full":"49 Rancliffe Crescent Leicester Leicestershire LE3 1NR",
    "addr:housenumber":"49",
    "addr:postcode":"le3 1nr",
    "addr:street":"Rancliffe Crescent",
    "iso:country":"GB",
    "sg:address":"49 Rancliffe Crescent",
    "sg:city":"Leicester",
    "sg:classifiers":[
        {
            "category":"Building & Trades",
            "subcategory":"Landscaping Services",
            "type":"Services"
        }
    ],
    "sg:phone":"+44 116 285 8103",
    "sg:postcode":"LE3 1NR",
    "sg:province":"Leicestershire",
    "sg:tags":[
        "landscape",
        "contractor"
    ],
    "wof:name":"A M Landscapes",
    "wof:placetype":"venue"
},
  "geometry": {"coordinates":[-1.1704250574,52.6276321411],"type":"Point"}
}