{
  "type": "Feature",
  "properties": {
    "iso:country":"GB",
    "sg:address":"8 Houghton Parade",
    "sg:city":"Dunstable",
    "sg:classifiers":[
        {
            "category":"Building & Trades",
            "subcategory":"Construction",
            "type":"Services"
        }
    ],
    "sg:postcode":"LU6 1DA",
    "sg:province":"Bedfordshire",
    "sg:tags":[
        "roofing"
    ],
    "wof:name":"Elsam & Son",
    "wof:placetype":"venue"
},
  "geometry": {"coordinates":[-0.5325689912,51.8942832947],"type":"Point"}
}