{
  "type": "Feature",
  "properties": {
    "iso:country":"GB",
    "sg:address":"10 Park Street",
    "sg:city":"Slough",
    "sg:classifiers":[
        {
            "category":"Restaurant",
            "type":"Food & Drink"
        }
    ],
    "sg:phone":"+44 1753 512966",
    "sg:postcode":"SL1 1PD",
    "sg:province":"Berkshire",
    "wof:name":"Shahzad Restaurant",
    "wof:placetype":"venue"
},
  "geometry": {"coordinates":[-0.5913490057,51.5076141357],"type":"Point"}
}