{
  "type": "Feature",
  "properties": {
    "iso:country":"GB",
    "sg:address":"9 Cockfosters Parade",
    "sg:city":"Barnet",
    "sg:classifiers":[
        {
            "category":"Personal",
            "subcategory":"Beauty Salon",
            "type":"Services"
        }
    ],
    "sg:postcode":"EN4 0BX",
    "sg:province":"Hertfordshire",
    "sg:tags":[
        "unisex",
        "hairdresser"
    ],
    "wof:name":"Strands",
    "wof:placetype":"venue"
},
  "geometry": {"coordinates":[-0.1538890004,51.6595497131],"type":"Point"}
}