{
  "type": "Feature",
  "properties": {
    "addr:full":"5 Etive Drive, Giffnock Glasgow East Renfrewshire G46 6PN",
    "addr:housenumber":"5",
    "addr:postcode":"g46 6pn",
    "addr:street":"Etive Drive",
    "iso:country":"GB",
    "sg:address":"5 Etive Drive, Giffnock",
    "sg:city":"Glasgow",
    "sg:classifiers":[
        {
            "category":"Building & Trades",
            "subcategory":"Construction",
            "type":"Services"
        }
    ],
    "sg:phone":"+44 141 638 0163",
    "sg:postcode":"G46 6PN",
    "sg:province":"East Renfrewshire",
    "sg:tags":[
        "builder"
    ],
    "wof:name":"D S Contracts",
    "wof:placetype":"venue"
},
  "geometry": {"coordinates":[-4.288718,55.795475],"type":"Point"}
}