{
  "type": "Feature",
  "properties": {
    "iso:country":"GB",
    "sg:address":"Green Lane",
    "sg:city":"Crawley",
    "sg:classifiers":[
        {
            "category":"Education",
            "subcategory":"School",
            "type":"Public Place"
        }
    ],
    "sg:phone":"+44 1293 419951",
    "sg:postcode":"RH10 8DX",
    "sg:province":"Surrey",
    "sg:tags":[
        "local",
        "authority"
    ],
    "wof:name":"Northgate First School",
    "wof:placetype":"venue"
},
  "geometry": {"coordinates":[-0.179224,51.125664],"type":"Point"}
}