{
  "type": "Feature",
  "properties": {
    "iso:country":"GB",
    "sg:address":"Redhouse, Shieldhill Road",
    "sg:city":"Falkirk",
    "sg:classifiers":[
        {
            "category":"Shopping",
            "subcategory":"Clothing, Apparel, & Fashions",
            "type":"Retail Goods"
        }
    ],
    "sg:postcode":"FK2 0DT",
    "sg:province":"Falkirk",
    "sg:tags":[
        "clothing",
        "fabric"
    ],
    "wof:name":"C M T Manufacturing",
    "wof:placetype":"venue"
},
  "geometry": {"coordinates":[-3.740679,55.980728],"type":"Point"}
}