{
  "type": "Feature",
  "properties": {
    "addr:full":"Axminster Chiropractic Clinic, Calam Ho, Chard St Axminster Devon EX13 5EB",
    "addr:postcode":"ex13 5eb",
    "addr:street":"St",
    "iso:country":"GB",
    "sg:address":"Axminster Chiropractic Clinic, Calam Ho, Chard St",
    "sg:city":"Axminster",
    "sg:classifiers":[
        {
            "category":"Health Services",
            "subcategory":"Chiropractor",
            "type":"Services"
        }
    ],
    "sg:phone":"+44 1297 35844",
    "sg:postcode":"EX13 5EB",
    "sg:province":"Devon",
    "wof:name":"R Stenning",
    "wof:placetype":"venue"
},
  "geometry": {"coordinates":[-3.0005619526,50.7812767029],"type":"Point"}
}