{
  "type": "Feature",
  "properties": {
    "iso:country":"GB",
    "sg:address":"1a Peel Street",
    "sg:city":"Accrington",
    "sg:classifiers":[
        {
            "category":"Shopping",
            "subcategory":"News",
            "type":"Retail Goods"
        }
    ],
    "sg:phone":"+44 1254 232052",
    "sg:postcode":"BB5 1EA",
    "sg:province":"Lancashire",
    "sg:tags":[
        "newsagent"
    ],
    "wof:name":"M & P Smithson",
    "wof:placetype":"venue"
},
  "geometry": {"coordinates":[-2.363624,53.752968],"type":"Point"}
}