{
  "type": "Feature",
  "properties": {
    "iso:country":"GB",
    "sg:address":"46 Low Ferrry Lane",
    "sg:city":"Worcester",
    "sg:classifiers":[
        {
            "category":"Sports & Exercise",
            "subcategory":"Swimming Pool",
            "type":"Entertainment"
        }
    ],
    "sg:phone":"+44 1905 830915",
    "sg:postcode":"WR2 4UN",
    "sg:province":"Worcestershire",
    "sg:tags":[
        "examination",
        "board"
    ],
    "wof:name":"The New Era Academy of Drama & Music (London) Ltd.",
    "wof:placetype":"venue"
},
  "geometry": {"coordinates":[-2.238096,52.14077],"type":"Point"}
}