{
  "type": "Feature",
  "properties": {
    "addr:full":"Care Of Grove End Farm, Grove End Lane, Whitminster Gloucester Gloucestershire GL2 7NZ",
    "addr:postcode":"gl2 7nz",
    "addr:street":"Grove End Lane",
    "iso:country":"GB",
    "sg:address":"Care Of Grove End Farm, Grove End Lane, Whitminster",
    "sg:city":"Gloucester",
    "sg:classifiers":[
        {
            "category":"Banks & Credit Unions",
            "subcategory":"Bureau De Change",
            "type":"Services"
        },
        {
            "category":"Shopping",
            "subcategory":"Used Merchandise",
            "type":"Retail Goods"
        }
    ],
    "sg:phone":"+44 1452 741454",
    "sg:postcode":"GL2 7NZ",
    "sg:province":"Gloucestershire",
    "sg:tags":[
        "paint",
        "varnish",
        "remover",
        "furniture"
    ],
    "wof:name":"Tim Tyler",
    "wof:placetype":"venue"
},
  "geometry": {"coordinates":[-2.327346,51.771236],"type":"Point"}
}