{
  "type": "Feature",
  "properties": {
    "addr:full":"161b St Margarets Rd Twickenham Greater London TW1 1RD",
    "addr:housenumber":"161b",
    "addr:postcode":"tw1 1rd",
    "addr:street":"St Margarets Rd",
    "iso:country":"GB",
    "sg:address":"161b St Margarets Rd",
    "sg:city":"Twickenham",
    "sg:classifiers":[
        {
            "category":"Building & Trades",
            "subcategory":"Construction",
            "type":"Services"
        }
    ],
    "sg:phone":"+44 7956 872702",
    "sg:postcode":"TW1 1RD",
    "sg:province":"Greater London",
    "sg:tags":[
        "roofing"
    ],
    "wof:name":"Rodney Thatcher Roofing",
    "wof:placetype":"venue"
},
  "geometry": {"coordinates":[-0.3217380047,51.4566421509],"type":"Point"}
}