{
  "type": "Feature",
  "properties": {
    "addr:full":"44 Victoria Street Paignton Devon TQ4 5DS",
    "addr:housenumber":"44",
    "addr:postcode":"tq4 5ds",
    "addr:street":"Victoria Street",
    "iso:country":"GB",
    "sg:address":"44 Victoria Street",
    "sg:city":"Paignton",
    "sg:classifiers":[
        {
            "category":"Personal",
            "subcategory":"Beauty Salon",
            "type":"Services"
        }
    ],
    "sg:postcode":"TQ4 5DS",
    "sg:province":"Devon",
    "wof:name":"The Natural Way",
    "wof:placetype":"venue"
},
  "geometry": {"coordinates":[-3.5659,50.435394],"type":"Point"}
}