{
  "type": "Feature",
  "properties": {
    "addr:full":"Craigievar Court Aberdeen Aberdeen City AB10 7FA",
    "addr:postcode":"ab10 7fa",
    "addr:street":"Craigievar Court",
    "iso:country":"GB",
    "sg:address":"Craigievar Court",
    "sg:city":"Aberdeen",
    "sg:classifiers":[
        {
            "category":"Social Services",
            "subcategory":"Adult Care",
            "type":"Services"
        }
    ],
    "sg:phone":"+44 1224 326353",
    "sg:postcode":"AB10 7FA",
    "sg:province":"Aberdeen City",
    "sg:tags":[
        "housing",
        "sheltered"
    ],
    "wof:name":"Castlehill Housing Association",
    "wof:placetype":"venue"
},
  "geometry": {"coordinates":[-2.129539,57.122055],"type":"Point"}
}