{
  "type": "Feature",
  "properties": {
    "addr:full":"Unit 7 London Greater London SE1 3ER",
    "addr:housenumber":"unit 7",
    "addr:postcode":"se1 3er",
    "iso:country":"GB",
    "sg:address":"Unit 7",
    "sg:city":"London",
    "sg:classifiers":[
        {
            "category":"Manufacturing",
            "subcategory":"Glass & Minerals",
            "type":"Manufacturing & Wholesale Goods"
        }
    ],
    "sg:postcode":"SE1 3ER",
    "sg:province":"Greater London",
    "sg:tags":[
        "product"
    ],
    "wof:name":"London Glassblowing Workshop",
    "wof:placetype":"venue"
},
  "geometry": {"coordinates":[-0.081704,51.49762],"type":"Point"}
}