{
  "type": "Feature",
  "properties": {
    "iso:country":"GB",
    "sg:address":"Beaufort Road, Plas Marl Industrial Estate, Morriston",
    "sg:city":"Swansea",
    "sg:classifiers":[
        {
            "category":"Autos & Motor Vehicles",
            "subcategory":"Automobile Sales",
            "type":"Retail Goods"
        }
    ],
    "sg:phone":"+44 1792 310410",
    "sg:postcode":"SA6 8HR",
    "sg:province":"Swansea",
    "sg:tags":[
        "car"
    ],
    "wof:name":"Days of Swansea",
    "wof:placetype":"venue"
},
  "geometry": {"coordinates":[-3.923893,51.658905],"type":"Point"}
}