{
  "type": "Feature",
  "properties": {
    "iso:country":"GB",
    "sg:address":"655 Wells Rd",
    "sg:city":"Bristol",
    "sg:classifiers":[
        {
            "category":"Home & Garden",
            "subcategory":"Hardware",
            "type":"Retail Goods"
        }
    ],
    "sg:phone":"+44 1275 834603",
    "sg:postcode":"BS14 9BE",
    "sg:province":"City of Bristol",
    "sg:tags":[
        "heat",
        "mech",
        "exchanger"
    ],
    "wof:name":"Trade Cooling Ltd",
    "wof:placetype":"venue"
},
  "geometry": {"coordinates":[-2.561071,51.419487],"type":"Point"}
}