{
  "type": "Feature",
  "properties": {
    "iso:country":"GB",
    "sg:address":"62 Bridgewater Walk, Ellesmere Shopping Centre, Walkden",
    "sg:city":"Manchester",
    "sg:classifiers":[
        {
            "category":"Shopping",
            "subcategory":"Thrift Store",
            "type":"Retail Goods"
        }
    ],
    "sg:phone":"+44 161 703 7750",
    "sg:postcode":"M28 3ZD",
    "sg:province":"Greater Manchester",
    "sg:tags":[
        "shop",
        "charity"
    ],
    "wof:name":"Help the Aged",
    "wof:placetype":"venue"
},
  "geometry": {"coordinates":[-2.401437,53.520794],"type":"Point"}
}