{
  "type": "Feature",
  "properties": {
    "addr:full":"Unit 4, Damgate Lane Norwich Norfolk NR13 3DJ",
    "addr:housenumber":"unit 4",
    "addr:postcode":"nr13 3dj",
    "addr:street":"Damgate Lane",
    "iso:country":"GB",
    "sg:address":"Unit 4, Damgate Lane",
    "sg:city":"Norwich",
    "sg:classifiers":[
        {
            "category":"Manufacturing",
            "subcategory":"Metals",
            "type":"Manufacturing & Wholesale Goods"
        },
        {
            "category":"Manufacturing",
            "subcategory":"Furniture",
            "type":"Manufacturing & Wholesale Goods"
        }
    ],
    "sg:phone":"+44 1493 751761",
    "sg:postcode":"NR13 3DJ",
    "sg:province":"Norfolk",
    "sg:tags":[
        "polishing",
        "heat",
        "-",
        "treatment",
        "french"
    ],
    "wof:name":"James M Darley",
    "wof:placetype":"venue"
},
  "geometry": {"coordinates":[1.5541700125,52.6328735352],"type":"Point"}
}