{
  "type": "Feature",
  "properties": {
    "addr:full":"2 Church End, Thurleigh Bedford Bedfordshire MK44 2DA",
    "addr:housenumber":"2",
    "addr:postcode":"mk44 2da",
    "addr:street":"Church End",
    "iso:country":"GB",
    "sg:address":"2 Church End, Thurleigh",
    "sg:city":"Bedford",
    "sg:classifiers":[
        {
            "category":"Retail",
            "subcategory":"Veterinary Services",
            "type":"Services"
        }
    ],
    "sg:postcode":"MK44 2DA",
    "sg:province":"Bedfordshire",
    "sg:tags":[
        "surgeon"
    ],
    "wof:name":"J R B Speed Veterinary Surgeons",
    "wof:placetype":"venue"
},
  "geometry": {"coordinates":[-0.389156,52.207714],"type":"Point"}
}