{
  "type": "Feature",
  "properties": {
    "iso:country":"GB",
    "sg:address":"Lansdowne Place",
    "sg:city":"Rugby",
    "sg:classifiers":[
        {
            "category":"Education",
            "subcategory":"School",
            "type":"Public Place"
        }
    ],
    "sg:postcode":"CV21 3RY",
    "sg:province":"Warwickshire",
    "sg:tags":[
        "local",
        "authority"
    ],
    "wof:name":"Eastlands Primary School",
    "wof:placetype":"venue"
},
  "geometry": {"coordinates":[-1.240809,52.368687],"type":"Point"}
}