{
  "type": "Feature",
  "properties": {
    "addr:full":"Bridge Street Halkirk Highland KW12 6XY",
    "addr:postcode":"kw12 6xy",
    "addr:street":"Bridge Street",
    "iso:country":"GB",
    "sg:address":"Bridge Street",
    "sg:city":"Halkirk",
    "sg:classifiers":[
        {
            "category":"Professional",
            "subcategory":"Engineering",
            "type":"Services"
        },
        {
            "category":"Food & Beverages",
            "subcategory":"Groceries & Convenience Stores",
            "type":"Retail Goods"
        }
    ],
    "sg:phone":"+44 1847 831800",
    "sg:postcode":"KW12 6XY",
    "sg:province":"Highland",
    "sg:tags":[
        "engineer",
        "electrical",
        "contractor"
    ],
    "wof:name":"Bond Electrical",
    "wof:placetype":"venue"
},
  "geometry": {"coordinates":[-3.495164,58.513454],"type":"Point"}
}