{
  "type": "Feature",
  "properties": {
    "addr:full":"18 St Peters Road Great Yarmouth Norfolk NR30 3BQ",
    "addr:housenumber":"18",
    "addr:postcode":"nr30 3bq",
    "addr:street":"St Peters Road",
    "iso:country":"GB",
    "sg:address":"18 St Peters Road",
    "sg:city":"Great Yarmouth",
    "sg:classifiers":[
        {
            "category":"Shopping",
            "subcategory":"Department Store",
            "type":"Retail Goods"
        }
    ],
    "sg:phone":"+44 1493 843244",
    "sg:postcode":"NR30 3BQ",
    "sg:province":"Norfolk",
    "wof:name":"Davids Mini Market",
    "wof:placetype":"venue"
},
  "geometry": {"coordinates":[1.733039,52.602638],"type":"Point"}
}