{
  "type": "Feature",
  "properties": {
    "iso:country":"GB",
    "sg:address":"Tennyson Rd",
    "sg:city":"Manchester",
    "sg:classifiers":[
        {
            "category":"Professional",
            "subcategory":"Engineering",
            "type":"Services"
        }
    ],
    "sg:phone":"+44 161 370 7757",
    "sg:postcode":"M43 7YJ",
    "sg:province":"Greater Manchester",
    "sg:tags":[
        "contractor",
        "electrical",
        "engineer"
    ],
    "wof:name":"Q Electrics",
    "wof:placetype":"venue"
},
  "geometry": {"coordinates":[-2.1504790783,53.4861984253],"type":"Point"}
}