{
  "type": "Feature",
  "properties": {
    "iso:country":"GB",
    "sg:address":"2 Waterloo Sq, Hakin",
    "sg:city":"Milford Haven",
    "sg:classifiers":[
        {
            "category":"Shopping",
            "subcategory":"Department Store",
            "type":"Retail Goods"
        },
        {
            "category":"Shopping",
            "subcategory":"Crafts & Fabrics",
            "type":"Retail Goods"
        }
    ],
    "sg:postcode":"SA73 3DY",
    "sg:province":"Pembrokeshire",
    "sg:tags":[
        "shop",
        "needlecraft",
        "wool"
    ],
    "wof:name":"Thomas,Lynda A,",
    "wof:placetype":"venue"
},
  "geometry": {"coordinates":[-5.047642,51.712299],"type":"Point"}
}