{
  "type": "Feature",
  "properties": {
    "addr:full":"Vine Cottage, Gilson Road Birmingham Warwickshire B46 1LN",
    "addr:postcode":"b46 1ln",
    "addr:street":"Gilson Road",
    "iso:country":"GB",
    "sg:address":"Vine Cottage, Gilson Road",
    "sg:city":"Birmingham",
    "sg:classifiers":[
        {
            "category":"Manufacturing",
            "subcategory":"Tools & Machinery",
            "type":"Manufacturing & Wholesale Goods"
        },
        {
            "category":"Banks & Credit Unions",
            "subcategory":"Bank",
            "type":"Services"
        }
    ],
    "sg:postcode":"B46 1LN",
    "sg:province":"Warwickshire",
    "sg:tags":[
        "society",
        "broker",
        "mortgage",
        "friendly"
    ],
    "wof:name":"Kingsbury Insurance Services",
    "wof:placetype":"venue"
},
  "geometry": {"coordinates":[-1.7225699425,52.5086517334],"type":"Point"}
}