{
  "type": "Feature",
  "properties": {
    "addr:full":"429 Oldham Road Rochdale Lancashire OL16 4TA",
    "addr:housenumber":"429",
    "addr:postcode":"ol16 4ta",
    "addr:street":"Oldham Road",
    "iso:country":"GB",
    "sg:address":"429 Oldham Road",
    "sg:city":"Rochdale",
    "sg:classifiers":[
        {
            "category":"Government",
            "subcategory":"Post Office",
            "type":"Public Place"
        }
    ],
    "sg:phone":"+44 1706 644871",
    "sg:postcode":"OL16 4TA",
    "sg:province":"Lancashire",
    "wof:name":"Lower Place P.O",
    "wof:placetype":"venue"
},
  "geometry": {"coordinates":[-2.1456739902,53.6002006531],"type":"Point"}
}