{
  "type": "Feature",
  "properties": {
    "addr:full":"Car Nation House Mill Lane Bradford West Yorkshire BD5 0HG",
    "addr:postcode":"bd5 0hg",
    "addr:street":"Mill Lane",
    "iso:country":"GB",
    "sg:address":"Car Nation House Mill Lane",
    "sg:city":"Bradford",
    "sg:classifiers":[
        {
            "category":"Autos & Motor Vehicles",
            "subcategory":"Automobile Sales",
            "type":"Retail Goods"
        }
    ],
    "sg:phone":"+44 1274 743879",
    "sg:postcode":"BD5 0HG",
    "sg:province":"West Yorkshire",
    "sg:tags":[
        "car"
    ],
    "wof:name":"The Car Nation Ltd.",
    "wof:placetype":"venue"
},
  "geometry": {"coordinates":[-1.752619,53.78606],"type":"Point"}
}