{
  "type": "Feature",
  "properties": {
    "addr:full":"Unit M3 Cody Court, Cansas Avenue Manchester Greater Manchester M50 2GE",
    "addr:postcode":"m50 2ge",
    "addr:street":"Cody Court Cansas Avenue",
    "iso:country":"GB",
    "sg:address":"Unit M3 Cody Court, Cansas Avenue",
    "sg:city":"Manchester",
    "sg:classifiers":[
        {
            "category":"Professional",
            "subcategory":"Printing & Photocopies",
            "type":"Services"
        }
    ],
    "sg:phone":"+44 161 872 7881",
    "sg:postcode":"M50 2GE",
    "sg:province":"Greater Manchester",
    "sg:tags":[
        "printer"
    ],
    "wof:name":"Burgess Printing Ltd.",
    "wof:placetype":"venue"
},
  "geometry": {"coordinates":[-2.2997899055,53.4763412476],"type":"Point"}
}