{
  "type": "Feature",
  "properties": {
    "iso:country":"GB",
    "sg:address":"10 Frances St",
    "sg:city":"Truro",
    "sg:classifiers":[
        {
            "category":"Shopping",
            "subcategory":"Pharmacy",
            "type":"Retail Goods"
        }
    ],
    "sg:postcode":"TR1 3DN",
    "sg:province":"Cornwall",
    "sg:tags":[
        "store",
        "drug"
    ],
    "wof:name":"Brack,G & G,",
    "wof:placetype":"venue"
},
  "geometry": {"coordinates":[-5.0562472343,50.2635879517],"type":"Point"}
}