{
  "type": "Feature",
  "properties": {
    "iso:country":"GB",
    "sg:address":"Llwyn Ynn Cottage",
    "sg:city":"Talybont",
    "sg:classifiers":[
        {
            "category":"Retail",
            "subcategory":"Driving School",
            "type":"Services"
        }
    ],
    "sg:phone":"+44 1341 247777",
    "sg:postcode":"LL43 2AH",
    "sg:province":"Gwynedd",
    "wof:name":"Barmouth School of Motoring",
    "wof:placetype":"venue"
},
  "geometry": {"coordinates":[-4.092428,52.774815],"type":"Point"}
}