{
  "type": "Feature",
  "properties": {
    "addr:full":"64 Leagrave Road Luton Bedfordshire LU4 8HZ",
    "addr:housenumber":"64",
    "addr:postcode":"lu4 8hz",
    "addr:street":"Leagrave Road",
    "iso:country":"GB",
    "sg:address":"64 Leagrave Road",
    "sg:city":"Luton",
    "sg:classifiers":[
        {
            "category":"Cafe",
            "type":"Food & Drink"
        }
    ],
    "sg:phone":"+44 1582 655033",
    "sg:postcode":"LU4 8HZ",
    "sg:province":"Bedfordshire",
    "sg:tags":[
        "tea",
        "room"
    ],
    "wof:name":"Kelly's Diner",
    "wof:placetype":"venue"
},
  "geometry": {"coordinates":[-0.431042999,51.8877220154],"type":"Point"}
}