{
  "type": "Feature",
  "properties": {
    "addr:full":"152 Stanley Green Rd Poole Dorset BH15 3AH",
    "addr:housenumber":"152",
    "addr:postcode":"bh15 3ah",
    "addr:street":"Stanley Green Rd",
    "iso:country":"GB",
    "sg:address":"152 Stanley Green Rd",
    "sg:city":"Poole",
    "sg:classifiers":[
        {
            "category":"Wholesale",
            "subcategory":"Scrap",
            "type":"Manufacturing & Wholesale Goods"
        }
    ],
    "sg:phone":"+44 1202 666533",
    "sg:postcode":"BH15 3AH",
    "sg:province":"Dorset",
    "sg:tags":[
        "car",
        "breaker",
        "dismantlers"
    ],
    "wof:name":"A1 Super Deals",
    "wof:placetype":"venue"
},
  "geometry": {"coordinates":[-1.9862669706,50.7285995483],"type":"Point"}
}