{
  "type": "Feature",
  "properties": {
    "addr:full":"Chaffeymoor Farm, Bourton Gillingham Dorset SP8 5BX",
    "addr:postcode":"sp8 5bx",
    "iso:country":"GB",
    "sg:address":"Chaffeymoor Farm, Bourton",
    "sg:city":"Gillingham",
    "sg:classifiers":[
        {
            "category":"Farming",
            "subcategory":"Livestock Farm",
            "type":"Manufacturing & Wholesale Goods"
        }
    ],
    "sg:postcode":"SP8 5BX",
    "sg:province":"Dorset",
    "sg:tags":[
        "others"
    ],
    "wof:name":"Gerald C Moores",
    "wof:placetype":"venue"
},
  "geometry": {"coordinates":[-2.322488,51.07539],"type":"Point"}
}