{
  "type": "Feature",
  "properties": {
    "iso:country":"GB",
    "sg:address":"Pinfold House, Stubbers Green Road",
    "sg:city":"Walsall",
    "sg:classifiers":[
        {
            "category":"Home & Garden",
            "subcategory":"Home Furnishings",
            "type":"Retail Goods"
        }
    ],
    "sg:phone":"+44 1922 454345",
    "sg:postcode":"WS9 8BJ",
    "sg:province":"Staffordshire",
    "sg:tags":[
        "awning",
        "canopy",
        "blinds"
    ],
    "wof:name":"Contract & Home Blinds Ltd.",
    "wof:placetype":"venue"
},
  "geometry": {"coordinates":[-1.934316,52.611504],"type":"Point"}
}