{
  "type": "Feature",
  "properties": {
    "addr:full":"Park Farm, Caerleon Newport Monmouthshire NP18 3PB",
    "addr:postcode":"np18 3pb",
    "iso:country":"GB",
    "sg:address":"Park Farm, Caerleon",
    "sg:city":"Newport",
    "sg:classifiers":[
        {
            "category":"Farming",
            "subcategory":"Livestock Farm",
            "type":"Manufacturing & Wholesale Goods"
        }
    ],
    "sg:phone":"+44 1633 423342",
    "sg:postcode":"NP18 3PB",
    "sg:province":"Monmouthshire",
    "sg:tags":[
        "others"
    ],
    "wof:name":"T Pritchard & Sons",
    "wof:placetype":"venue"
},
  "geometry": {"coordinates":[-2.95921,51.616547],"type":"Point"}
}