{
  "type": "Feature",
  "properties": {
    "addr:full":"300 Aigburth Rd Liverpool Merseyside L17 9PW",
    "addr:housenumber":"300",
    "addr:postcode":"l17 9pw",
    "addr:street":"Aigburth Rd",
    "iso:country":"GB",
    "sg:address":"300 Aigburth Rd",
    "sg:city":"Liverpool",
    "sg:classifiers":[
        {
            "category":"Autos & Motor Vehicles",
            "subcategory":"Motorcycle Sales",
            "type":"Retail Goods"
        }
    ],
    "sg:postcode":"L17 9PW",
    "sg:province":"Merseyside",
    "wof:name":"Wilding,Geoffrey,",
    "wof:placetype":"venue"
},
  "geometry": {"coordinates":[-2.934917,53.37323],"type":"Point"}
}