{
  "type": "Feature",
  "properties": {
    "iso:country":"GB",
    "sg:address":"92 Burnham Road, Hullbridge",
    "sg:city":"Hockley",
    "sg:classifiers":[
        {
            "category":"Building & Trades",
            "subcategory":"Cleaning & Sanitation",
            "type":"Services"
        }
    ],
    "sg:phone":"+44 1702 232584",
    "sg:postcode":"SS5 6HQ",
    "sg:province":"Essex",
    "sg:tags":[
        "blast"
    ],
    "wof:name":"Masterblast",
    "wof:placetype":"venue"
},
  "geometry": {"coordinates":[0.619968,51.621494],"type":"Point"}
}