{
  "type": "Feature",
  "properties": {
    "iso:country":"GB",
    "sg:address":"Stafford Park 9",
    "sg:city":"Telford",
    "sg:classifiers":[
        {
            "category":"Manufacturing",
            "subcategory":"Wood Products",
            "type":"Manufacturing & Wholesale Goods"
        }
    ],
    "sg:phone":"+44 1952 290471",
    "sg:postcode":"TF3 3BZ",
    "sg:province":"Shropshire",
    "sg:tags":[
        "packaging",
        "crate",
        "pallets"
    ],
    "wof:name":"Trigon Packaging Systems (Uk)",
    "wof:placetype":"venue"
},
  "geometry": {"coordinates":[-2.423359,52.677368],"type":"Point"}
}