{
  "type": "Feature",
  "properties": {
    "iso:country":"GB",
    "sg:address":"554 Hagley Road West",
    "sg:city":"Oldbury",
    "sg:classifiers":[
        {
            "category":"Cinema",
            "subcategory":"Movie Rental",
            "type":"Entertainment"
        }
    ],
    "sg:phone":"+44 121 423 2923",
    "sg:postcode":"B68 0BZ",
    "sg:province":"West Midlands",
    "sg:tags":[
        "video",
        "library"
    ],
    "wof:name":"Appello",
    "wof:placetype":"venue"
},
  "geometry": {"coordinates":[-1.999779,52.468941],"type":"Point"}
}