{
  "type": "Feature",
  "properties": {
    "iso:country":"GB",
    "sg:address":"17 Rodney St",
    "sg:city":"Rochdale",
    "sg:classifiers":[
        {
            "category":"Building & Trades",
            "subcategory":"Landscaping Services",
            "type":"Services"
        }
    ],
    "sg:phone":"+44 1706 526826",
    "sg:postcode":"OL11 3DF",
    "sg:province":"Lancashire",
    "sg:tags":[
        "forestry",
        "tree"
    ],
    "wof:name":"Rochdale Tree Service",
    "wof:placetype":"venue"
},
  "geometry": {"coordinates":[-2.186458,53.59169],"type":"Point"}
}