{
  "type": "Feature",
  "properties": {
    "addr:full":"403 Thornton Rd, Thornton Bradford West Yorkshire BD13 3JN",
    "addr:housenumber":"403",
    "addr:postcode":"bd13 3jn",
    "addr:street":"Thornton Rd",
    "iso:country":"GB",
    "sg:address":"403 Thornton Rd, Thornton",
    "sg:city":"Bradford",
    "sg:classifiers":[
        {
            "category":"Food & Beverages",
            "subcategory":"Liquor & Beverages",
            "type":"Retail Goods"
        }
    ],
    "sg:postcode":"BD13 3JN",
    "sg:province":"West Yorkshire",
    "sg:tags":[
        "beer",
        "spirit",
        "wines"
    ],
    "wof:name":"Thornton Mini Market",
    "wof:placetype":"venue"
},
  "geometry": {"coordinates":[-1.8535779715,53.7905464172],"type":"Point"}
}