{
  "type": "Feature",
  "properties": {
    "addr:full":"19 Shaws Road Altrincham Cheshire WA14 1QU",
    "addr:housenumber":"19",
    "addr:postcode":"wa14 1qu",
    "addr:street":"Shaws Road",
    "iso:country":"GB",
    "sg:address":"19 Shaws Road",
    "sg:city":"Altrincham",
    "sg:classifiers":[
        {
            "category":"Fast Food",
            "type":"Food & Drink"
        }
    ],
    "sg:phone":"+44 161 928 5040",
    "sg:postcode":"WA14 1QU",
    "sg:province":"Cheshire",
    "sg:tags":[
        "away",
        "take"
    ],
    "wof:name":"Dodgers Sandwich Bar",
    "wof:placetype":"venue"
},
  "geometry": {"coordinates":[-2.351416,53.387444],"type":"Point"}
}