{
  "type": "Feature",
  "properties": {
    "addr:full":"Top Flat 56 Schubert Road, Putney London Greater London SW15 2QS",
    "addr:housenumber":"56",
    "addr:postcode":"sw15 2qs",
    "addr:street":"Schubert Road",
    "iso:country":"GB",
    "sg:address":"Top Flat 56 Schubert Road, Putney",
    "sg:city":"London",
    "sg:classifiers":[
        {
            "category":"Professional",
            "subcategory":"Accounting & Tax Preparation",
            "type":"Services"
        }
    ],
    "sg:postcode":"SW15 2QS",
    "sg:province":"Greater London",
    "sg:tags":[
        "accountant"
    ],
    "wof:name":"Becks Associates Ltd",
    "wof:placetype":"venue"
},
  "geometry": {"coordinates":[-0.2047600001,51.456741333],"type":"Point"}
}