{
  "type": "Feature",
  "properties": {
    "iso:country":"GB",
    "sg:address":"73 Nathans Road",
    "sg:city":"Wembley",
    "sg:classifiers":[
        {
            "category":"Building & Trades",
            "subcategory":"Construction",
            "type":"Services"
        }
    ],
    "sg:postcode":"HA0 3RU",
    "sg:province":"Greater London",
    "sg:tags":[
        "builder"
    ],
    "wof:name":"Lynmeth Construction Ltd.",
    "wof:placetype":"venue"
},
  "geometry": {"coordinates":[-0.309907,51.570671],"type":"Point"}
}