{
  "type": "Feature",
  "properties": {
    "addr:full":"Home Farm, Syleham Diss Norfolk IP21 4LU",
    "addr:postcode":"ip21 4lu",
    "iso:country":"GB",
    "sg:address":"Home Farm, Syleham",
    "sg:city":"Diss",
    "sg:classifiers":[
        {
            "category":"Farming",
            "subcategory":"Livestock Farm",
            "type":"Manufacturing & Wholesale Goods"
        },
        {
            "category":"Farming",
            "subcategory":"Farm",
            "type":"Manufacturing & Wholesale Goods"
        }
    ],
    "sg:phone":"+44 1379 668392",
    "sg:postcode":"IP21 4LU",
    "sg:province":"Norfolk",
    "sg:tags":[
        "mixed",
        "crop"
    ],
    "wof:name":"I & B WINGFIELD & SONS",
    "wof:placetype":"venue"
},
  "geometry": {"coordinates":[1.2505400181,52.3560447693],"type":"Point"}
}