{
  "type": "Feature",
  "properties": {
    "addr:full":"65 Worcester Avenue, Mansfield Woodhouse Mansfield Derbyshire NG19 8QY",
    "addr:housenumber":"65",
    "addr:postcode":"ng19 8qy",
    "addr:street":"Worcester Avenue",
    "iso:country":"GB",
    "sg:address":"65 Worcester Avenue, Mansfield Woodhouse",
    "sg:city":"Mansfield",
    "sg:classifiers":[
        {
            "category":"Building & Trades",
            "subcategory":"Cleaning & Sanitation",
            "type":"Services"
        },
        {
            "category":"Professional",
            "subcategory":"Art Services",
            "type":"Services"
        },
        {
            "category":"Building & Trades",
            "subcategory":"Construction",
            "type":"Services"
        }
    ],
    "sg:phone":"+44 1623 646166",
    "sg:postcode":"NG19 8QY",
    "sg:province":"Derbyshire",
    "sg:tags":[
        "stone",
        "restoration",
        "builder",
        "exterior"
    ],
    "wof:name":"Jenlyn Power",
    "wof:placetype":"venue"
},
  "geometry": {"coordinates":[-1.187418,53.177029],"type":"Point"}
}