{
  "type": "Feature",
  "properties": {
    "iso:country":"GB",
    "sg:address":"10 Champion Grove",
    "sg:city":"London",
    "sg:classifiers":[
        {
            "category":"Professional",
            "subcategory":"Accounting & Tax Preparation",
            "type":"Services"
        }
    ],
    "sg:postcode":"SE5 8BW",
    "sg:province":"Greater London",
    "sg:tags":[
        "accountant"
    ],
    "wof:name":"Swagman Accounting Contracts Ltd",
    "wof:placetype":"venue"
},
  "geometry": {"coordinates":[-0.0865330026,51.4662780762],"type":"Point"}
}