{
  "type": "Feature",
  "properties": {
    "addr:full":"Hadrian Road Wallsend Tyne and Wear NE28 6HF",
    "addr:postcode":"ne28 6hf",
    "addr:street":"Hadrian Road",
    "iso:country":"GB",
    "sg:address":"Hadrian Road",
    "sg:city":"Wallsend",
    "sg:classifiers":[
        {
            "category":"Autos & Motor Vehicles",
            "subcategory":"Fuel & Gas Station",
            "type":"Retail Goods"
        }
    ],
    "sg:phone":"+44 191 263 8048",
    "sg:postcode":"NE28 6HF",
    "sg:province":"Tyne and Wear",
    "sg:tags":[
        "hr",
        "petrol"
    ],
    "wof:name":"Carrville Service Station",
    "wof:placetype":"venue"
},
  "geometry": {"coordinates":[-1.5071920156,54.9928474426],"type":"Point"}
}