{
  "type": "Feature",
  "properties": {
    "addr:full":"7 Aller Parade Weston-super-mare Somerset BS24 9DD",
    "addr:housenumber":"7",
    "addr:postcode":"bs24 9dd",
    "addr:street":"Aller Parade",
    "iso:country":"GB",
    "sg:address":"7 Aller Parade",
    "sg:city":"Weston-super-mare",
    "sg:classifiers":[
        {
            "category":"Shopping",
            "subcategory":"Pets & Pet Supplies",
            "type":"Retail Goods"
        }
    ],
    "sg:phone":"+44 1934 815512",
    "sg:postcode":"BS24 9DD",
    "sg:province":"Somerset",
    "wof:name":"Noah's Ark",
    "wof:placetype":"venue"
},
  "geometry": {"coordinates":[-2.9554400444,51.3234291077],"type":"Point"}
}