{
  "type": "Feature",
  "properties": {
    "addr:full":"Heath Cross, Whitestone Exeter Devon EX4 2HR",
    "addr:postcode":"ex4 2hr",
    "addr:street":"Heath Cross",
    "iso:country":"GB",
    "sg:address":"Heath Cross, Whitestone",
    "sg:city":"Exeter",
    "sg:classifiers":[
        {
            "category":"Government",
            "subcategory":"Office",
            "type":"Public Place"
        }
    ],
    "sg:postcode":"EX4 2HR",
    "sg:province":"Devon",
    "sg:tags":[
        "central"
    ],
    "wof:name":"Cameroon",
    "wof:placetype":"venue"
},
  "geometry": {"coordinates":[-3.605,50.730537],"type":"Point"}
}