{
  "type": "Feature",
  "properties": {
    "iso:country":"GB",
    "sg:address":"Orchard House, Victoria Square",
    "sg:city":"Droitwich",
    "sg:classifiers":[
        {
            "category":"Professional",
            "subcategory":"Engineering",
            "type":"Services"
        }
    ],
    "sg:phone":"+44 1905 794784",
    "sg:postcode":"WR9 8DS",
    "sg:province":"Worcestershire",
    "sg:tags":[
        "consulting",
        "engineer"
    ],
    "wof:name":"Bettridge Turner & Partners",
    "wof:placetype":"venue"
},
  "geometry": {"coordinates":[-2.150446,52.266949],"type":"Point"}
}