{
  "type": "Feature",
  "properties": {
    "iso:country":"GB",
    "sg:address":"140 Uxbridge Road",
    "sg:city":"London",
    "sg:classifiers":[
        {
            "category":"Manufacturing",
            "subcategory":"Metals",
            "type":"Manufacturing & Wholesale Goods"
        },
        {
            "category":"Home & Garden",
            "subcategory":"Hardware",
            "type":"Retail Goods"
        }
    ],
    "sg:phone":"+44 20 8579 3856",
    "sg:postcode":"W7 3SL",
    "sg:province":"Greater London",
    "sg:tags":[
        "equipment",
        "welding"
    ],
    "wof:name":"London Welding Supplies Ltd.",
    "wof:placetype":"venue"
},
  "geometry": {"coordinates":[-0.33849,51.508736],"type":"Point"}
}