{
  "type": "Feature",
  "properties": {
    "addr:full":"The Yard, College Road Cardiff Cardiff CF14 2NZ",
    "addr:postcode":"cf14 2nz",
    "addr:street":"College Road",
    "iso:country":"GB",
    "sg:address":"The Yard, College Road",
    "sg:city":"Cardiff",
    "sg:classifiers":[
        {
            "category":"Manufacturing",
            "subcategory":"Building Materials",
            "type":"Manufacturing & Wholesale Goods"
        }
    ],
    "sg:phone":"+44 29 2062 5422",
    "sg:postcode":"CF14 2NZ",
    "sg:province":"Cardiff",
    "sg:tags":[
        "merchant",
        "builder"
    ],
    "wof:name":"Whitchurch Builders & Decorators Supplies Ltd.",
    "wof:placetype":"venue"
},
  "geometry": {"coordinates":[-3.2319939137,51.5090789795],"type":"Point"}
}