{
  "type": "Feature",
  "properties": {
    "addr:full":"Romford Ice Rink, Rom Valley Way Romford Essex RM7 0AE",
    "addr:postcode":"rm7 0ae",
    "addr:street":"Rom Valley Way",
    "iso:country":"GB",
    "sg:address":"Romford Ice Rink, Rom Valley Way",
    "sg:city":"Romford",
    "sg:classifiers":[
        {
            "category":"Sports & Exercise",
            "subcategory":"Sports Center",
            "type":"Entertainment"
        }
    ],
    "sg:phone":"+44 1708 739916",
    "sg:postcode":"RM7 0AE",
    "sg:province":"Essex",
    "sg:tags":[
        "shop",
        "good"
    ],
    "wof:name":"Power Pro Sports",
    "wof:placetype":"venue"
},
  "geometry": {"coordinates":[0.18137,51.569672],"type":"Point"}
}