{
  "type": "Feature",
  "properties": {
    "addr:full":"243 Fleet Road Fleet Hampshire GU51 3BN",
    "addr:housenumber":"243",
    "addr:postcode":"gu51 3bn",
    "addr:street":"Fleet Road",
    "iso:country":"GB",
    "sg:address":"243 Fleet Road",
    "sg:city":"Fleet",
    "sg:classifiers":[
        {
            "category":"Shopping",
            "subcategory":"Clothing, Apparel, & Fashions",
            "type":"Retail Goods"
        }
    ],
    "sg:postcode":"GU51 3BN",
    "sg:province":"Hampshire",
    "sg:tags":[
        "menswear"
    ],
    "wof:name":"Mr Suave",
    "wof:placetype":"venue"
},
  "geometry": {"coordinates":[-0.8375689983,51.2850112915],"type":"Point"}
}