{
  "type": "Feature",
  "properties": {
    "addr:full":"17 Wilcox Rd London Greater London SW8 2XA",
    "addr:housenumber":"17",
    "addr:postcode":"sw8 2xa",
    "addr:street":"Wilcox Rd",
    "iso:country":"GB",
    "sg:address":"17 Wilcox Rd",
    "sg:city":"London",
    "sg:classifiers":[
        {
            "category":"Cafe",
            "type":"Food & Drink"
        }
    ],
    "sg:postcode":"SW8 2XA",
    "sg:province":"Greater London",
    "sg:tags":[
        "tea",
        "room"
    ],
    "wof:name":"Panetta,L A,",
    "wof:placetype":"venue"
},
  "geometry": {"coordinates":[-0.1271319985,51.4797515869],"type":"Point"}
}