{
  "type": "Feature",
  "properties": {
    "addr:full":"Dark Lane Bedworth Warwickshire CV12 0JH",
    "addr:postcode":"cv12 0jh",
    "addr:street":"Dark Lane",
    "iso:country":"GB",
    "sg:address":"Dark Lane",
    "sg:city":"Bedworth",
    "sg:classifiers":[
        {
            "category":"Bars & Pubs",
            "type":"Food & Drink"
        }
    ],
    "sg:phone":"+44 24 7636 2247",
    "sg:postcode":"CV12 0JH",
    "sg:province":"Warwickshire",
    "sg:tags":[
        "pubs",
        "inn"
    ],
    "wof:name":"The Carousel",
    "wof:placetype":"venue"
},
  "geometry": {"coordinates":[-1.499794,52.469486],"type":"Point"}
}