{
  "type": "Feature",
  "properties": {
    "iso:country":"GB",
    "sg:address":"33 East Street",
    "sg:city":"Derby",
    "sg:classifiers":[
        {
            "category":"Shopping",
            "subcategory":"Gifts & Souvenirs",
            "type":"Retail Goods"
        }
    ],
    "sg:phone":"+44 1332 291534",
    "sg:postcode":"DE1 2AL",
    "sg:province":"Derbyshire",
    "sg:tags":[
        "shop",
        "poster",
        "card"
    ],
    "wof:name":"CLINTON CARDS PLC",
    "wof:placetype":"venue"
},
  "geometry": {"coordinates":[-1.475075,52.920868],"type":"Point"}
}