{
  "type": "Feature",
  "properties": {
    "addr:full":"147 London Rd, Hazel Grove Stockport Cheshire SK7 4HH",
    "addr:housenumber":"147",
    "addr:postcode":"sk7 4hh",
    "addr:street":"London Rd",
    "iso:country":"GB",
    "sg:address":"147 London Rd, Hazel Grove",
    "sg:city":"Stockport",
    "sg:classifiers":[
        {
            "category":"Shopping",
            "subcategory":"Party Supplies",
            "type":"Retail Goods"
        }
    ],
    "sg:phone":"+44 161 487 3133",
    "sg:postcode":"SK7 4HH",
    "sg:province":"Cheshire",
    "sg:tags":[
        "novelty"
    ],
    "wof:name":"BOBBY DAZZLERS",
    "wof:placetype":"venue"
},
  "geometry": {"coordinates":[-2.1227369308,53.3808898926],"type":"Point"}
}