{
  "type": "Feature",
  "properties": {
    "addr:full":"13 Conway Road London Greater London SE18 1AH",
    "addr:housenumber":"13",
    "addr:postcode":"se18 1ah",
    "addr:street":"Conway Road",
    "iso:country":"GB",
    "sg:address":"13 Conway Road",
    "sg:city":"London",
    "sg:classifiers":[
        {
            "category":"Food & Beverages",
            "subcategory":"Liquor & Beverages",
            "type":"Retail Goods"
        }
    ],
    "sg:phone":"+44 20 8855 9768",
    "sg:postcode":"SE18 1AH",
    "sg:province":"Greater London",
    "sg:tags":[
        "beer",
        "spirit",
        "wines"
    ],
    "wof:name":"Conway Griffin Wines",
    "wof:placetype":"venue"
},
  "geometry": {"coordinates":[0.0858089998,51.4872550964],"type":"Point"}
}