{
  "type": "Feature",
  "properties": {
    "addr:full":"New Showroom High St Blackwood Caerphilly NP12 1BA",
    "addr:postcode":"np12 1ba",
    "addr:street":"High St",
    "iso:country":"GB",
    "sg:address":"New Showroom High St",
    "sg:city":"Blackwood",
    "sg:classifiers":[
        {
            "category":"Retail",
            "subcategory":"Auto Rental",
            "type":"Services"
        }
    ],
    "sg:phone":"+44 1495 226545",
    "sg:postcode":"NP12 1BA",
    "sg:province":"Caerphilly",
    "sg:tags":[
        "truck",
        "hire",
        "van"
    ],
    "wof:name":"Halo Van Hire",
    "wof:placetype":"venue"
},
  "geometry": {"coordinates":[-3.1956140995,51.6672744751],"type":"Point"}
}