{
  "type": "Feature",
  "properties": {
    "iso:country":"GB",
    "sg:address":"Clay Flatts Trading Estate",
    "sg:city":"Workington",
    "sg:classifiers":[
        {
            "category":"Autos & Motor Vehicles",
            "subcategory":"Automobile Sales",
            "type":"Retail Goods"
        }
    ],
    "sg:phone":"+44 1900 604542",
    "sg:postcode":"CA14 2TQ",
    "sg:province":"Cumbria",
    "sg:tags":[
        "car"
    ],
    "wof:name":"Graham & Bowness (West)",
    "wof:placetype":"venue"
},
  "geometry": {"coordinates":[-3.550002,54.638981],"type":"Point"}
}