{
  "type": "Feature",
  "properties": {
    "addr:full":"14 Gerald Avenue, Burnholme York North Yorkshire YO31 0QR",
    "addr:housenumber":"14",
    "addr:postcode":"yo31 0qr",
    "addr:street":"Gerald Avenue",
    "iso:country":"GB",
    "sg:address":"14 Gerald Avenue, Burnholme",
    "sg:city":"York",
    "sg:classifiers":[
        {
            "category":"Professional",
            "subcategory":"Printing & Photocopies",
            "type":"Services"
        }
    ],
    "sg:postcode":"YO31 0QR",
    "sg:province":"North Yorkshire",
    "sg:tags":[
        "printer"
    ],
    "wof:name":"Julie Walker",
    "wof:placetype":"venue"
},
  "geometry": {"coordinates":[-1.0522500277,53.9646110535],"type":"Point"}
}