{
  "type": "Feature",
  "properties": {
    "iso:country":"GB",
    "sg:address":"3 Mill La",
    "sg:city":"Wallasey",
    "sg:classifiers":[
        {
            "category":"Bakery",
            "type":"Food & Drink"
        }
    ],
    "sg:phone":"+44 151 638 4615",
    "sg:postcode":"L44 5UA",
    "sg:province":"Merseyside",
    "sg:tags":[
        "cake",
        "maker"
    ],
    "wof:name":"Cakecraft",
    "wof:placetype":"venue"
},
  "geometry": {"coordinates":[-3.042739,53.418751],"type":"Point"}
}