{
  "type": "Feature",
  "properties": {
    "iso:country":"GB",
    "sg:address":"Dental Surgery, 24 Bore Street",
    "sg:city":"Lichfield",
    "sg:classifiers":[
        {
            "category":"Health Services",
            "subcategory":"Podiatrist",
            "type":"Services"
        }
    ],
    "sg:phone":"+44 1543 250093",
    "sg:postcode":"WS13 6LL",
    "sg:province":"Staffordshire",
    "sg:tags":[
        "podiatrists",
        "chiropodist"
    ],
    "wof:name":"P J Thompson",
    "wof:placetype":"venue"
},
  "geometry": {"coordinates":[-1.8196599483,52.6840286255],"type":"Point"}
}