{
  "type": "Feature",
  "properties": {
    "iso:country":"GB",
    "sg:address":"Macklin Avenue, Cowpen Lane Industrial Estate",
    "sg:city":"Billingham",
    "sg:classifiers":[
        {
            "category":"Freight",
            "type":"Transportation"
        },
        {
            "category":"Retail",
            "subcategory":"Storage",
            "type":"Services"
        }
    ],
    "sg:phone":"+44 1642 414300",
    "sg:postcode":"TS23 4BY",
    "sg:province":"Durham",
    "sg:tags":[
        "haulage",
        "household",
        "road",
        "removal"
    ],
    "wof:name":"Wincanton Trans European Ltd.",
    "wof:placetype":"venue"
},
  "geometry": {"coordinates":[-1.256729,54.612396],"type":"Point"}
}