{
  "type": "Feature",
  "properties": {
    "addr:full":"Winchcombe, Hailes Cheltenham Gloucestershire GL54 5PB",
    "addr:postcode":"gl54 5pb",
    "addr:street":"Hailes",
    "iso:country":"GB",
    "sg:address":"Winchcombe, Hailes",
    "sg:city":"Cheltenham",
    "sg:classifiers":[
        {
            "category":"Food & Beverages",
            "subcategory":"Farmers Market",
            "type":"Retail Goods"
        },
        {
            "category":"Food & Beverages",
            "subcategory":"Fruits & Vegetables",
            "type":"Retail Goods"
        }
    ],
    "sg:phone":"+44 1242 602398",
    "sg:postcode":"GL54 5PB",
    "sg:province":"Gloucestershire",
    "sg:tags":[
        "farm",
        "shop",
        "greengrocer",
        "pyo"
    ],
    "wof:name":"Hailes Fruit Farm Ltd",
    "wof:placetype":"venue"
},
  "geometry": {"coordinates":[-1.9643529654,51.9533882141],"type":"Point"}
}