{
  "type": "Feature",
  "properties": {
    "addr:full":"33-35 Silent Street Ipswich Suffolk IP1 1TF",
    "addr:housenumber":"33-35",
    "addr:postcode":"ip1 1tf",
    "addr:street":"Silent Street",
    "iso:country":"GB",
    "sg:address":"33-35 Silent Street",
    "sg:city":"Ipswich",
    "sg:classifiers":[
        {
            "category":"Government",
            "subcategory":"Office",
            "type":"Public Place"
        }
    ],
    "sg:phone":"+44 1473 281559",
    "sg:postcode":"IP1 1TF",
    "sg:province":"Suffolk",
    "sg:tags":[
        "mp",
        "meps"
    ],
    "wof:name":"Chris Mole",
    "wof:placetype":"venue"
},
  "geometry": {"coordinates":[1.1537530422,52.0555343628],"type":"Point"}
}