{
  "type": "Feature",
  "properties": {
    "iso:country":"GB",
    "sg:address":"262-264 Sea Front",
    "sg:city":"Hayling Island",
    "sg:classifiers":[
        {
            "category":"Recreation",
            "subcategory":"Water Park",
            "type":"Entertainment"
        }
    ],
    "sg:phone":"+44 23 9246 7755",
    "sg:postcode":"PO11 0AY",
    "sg:province":"Hampshire",
    "sg:tags":[
        "sport"
    ],
    "wof:name":"Andrew Biggs",
    "wof:placetype":"venue"
},
  "geometry": {"coordinates":[-0.991396,50.786293],"type":"Point"}
}