{
  "type": "Feature",
  "properties": {
    "addr:full":"Ballochruin Farm, Balfron Glasgow Argyll and Bute G63 0LE",
    "addr:postcode":"g63 0le",
    "iso:country":"GB",
    "sg:address":"Ballochruin Farm, Balfron",
    "sg:city":"Glasgow",
    "sg:classifiers":[
        {
            "category":"Farming",
            "subcategory":"Farm",
            "type":"Manufacturing & Wholesale Goods"
        }
    ],
    "sg:postcode":"G63 0LE",
    "sg:province":"Argyll and Bute",
    "sg:tags":[
        "mixed",
        "crop"
    ],
    "wof:name":"A M Cuthbert",
    "wof:placetype":"venue"
},
  "geometry": {"coordinates":[-4.3369731903,56.0710144043],"type":"Point"}
}