{
  "type": "Feature",
  "properties": {
    "iso:country":"GB",
    "sg:address":"Hurshens, 291 Green Lanes",
    "sg:city":"London",
    "sg:classifiers":[
        {
            "category":"Real Estate",
            "subcategory":"Real Estate Agent",
            "type":"Services"
        }
    ],
    "sg:postcode":"N13 4XS",
    "sg:province":"Greater London",
    "wof:name":"H & O Properties Ltd",
    "wof:placetype":"venue"
},
  "geometry": {"coordinates":[-0.10939,51.617008],"type":"Point"}
}