{
  "type": "Feature",
  "properties": {
    "iso:country":"GB",
    "sg:address":"130 Holden Rd",
    "sg:city":"North Finchley",
    "sg:classifiers":[
        {
            "category":"Organizations",
            "subcategory":"Religious Organization",
            "type":"Services"
        }
    ],
    "sg:phone":"+44 20 8445 6430",
    "sg:postcode":"N12 7EA",
    "sg:province":"Greater London",
    "sg:tags":[
        "organisation"
    ],
    "wof:name":"Xaverian Missionaries",
    "wof:placetype":"venue"
},
  "geometry": {"coordinates":[-0.1832409948,51.6230773926],"type":"Point"}
}