{
  "type": "Feature",
  "properties": {
    "iso:country":"GB",
    "sg:address":"Wells Farm, Wells Lane",
    "sg:city":"Ascot",
    "sg:classifiers":[
        {
            "category":"Professional",
            "type":"Services"
        },
        {
            "category":"Banks & Credit Unions",
            "subcategory":"Investment Brokerage",
            "type":"Services"
        }
    ],
    "sg:phone":"+44 1344 626918",
    "sg:postcode":"SL5 7DY",
    "sg:province":"Berkshire",
    "sg:tags":[
        "farm",
        "agricultural",
        "contractor"
    ],
    "wof:name":"Oakfield Farm",
    "wof:placetype":"venue"
},
  "geometry": {"coordinates":[-0.6737939715,51.4106750488],"type":"Point"}
}