{
  "type": "Feature",
  "properties": {
    "iso:country":"GB",
    "sg:address":"17 Greenbank Court, Milner Road, Baildon",
    "sg:city":"Shipley",
    "sg:classifiers":[
        {
            "category":"Social Services",
            "subcategory":"Adult Care",
            "type":"Services"
        },
        {
            "category":"Government",
            "subcategory":"Office",
            "type":"Public Place"
        }
    ],
    "sg:phone":"+44 1274 585543",
    "sg:postcode":"BD17 5LD",
    "sg:province":"West Yorkshire",
    "sg:tags":[
        "local",
        "housing",
        "central",
        "sheltered"
    ],
    "wof:name":"Greenbank Court Sheltered Housing",
    "wof:placetype":"venue"
},
  "geometry": {"coordinates":[-1.77791,53.842289],"type":"Point"}
}