{
  "type": "Feature",
  "properties": {
    "iso:country":"GB",
    "sg:address":"36 Cornfield Road",
    "sg:city":"Eastbourne",
    "sg:classifiers":[
        {
            "category":"Real Estate",
            "subcategory":"Real Estate Agent",
            "type":"Services"
        }
    ],
    "sg:phone":"+44 1323 430133",
    "sg:postcode":"BN21 4QH",
    "sg:province":"East Sussex",
    "wof:name":"Rager & Roberts",
    "wof:placetype":"venue"
},
  "geometry": {"coordinates":[0.284574,50.766727],"type":"Point"}
}