{
  "type": "Feature",
  "properties": {
    "iso:country":"GB",
    "sg:address":"13 Spring Vale, Bilton",
    "sg:city":"Hull",
    "sg:classifiers":[
        {
            "category":"Building & Trades",
            "subcategory":"Construction",
            "type":"Services"
        }
    ],
    "sg:postcode":"HU11 4DN",
    "sg:province":"East Riding of Yorkshire",
    "sg:tags":[
        "tiling",
        "contractor"
    ],
    "wof:name":"Ceramic Tiling",
    "wof:placetype":"venue"
},
  "geometry": {"coordinates":[-0.2575449944,53.7754592896],"type":"Point"}
}