{
  "type": "Feature",
  "properties": {
    "addr:full":"19 Victoria Road, Walthamstow London Greater London E17 4JT",
    "addr:housenumber":"19",
    "addr:postcode":"e17 4jt",
    "addr:street":"Victoria Road",
    "iso:country":"GB",
    "sg:address":"19 Victoria Road, Walthamstow",
    "sg:city":"London",
    "sg:classifiers":[
        {
            "category":"Personal",
            "subcategory":"Beauty Salon",
            "type":"Services"
        }
    ],
    "sg:phone":"+44 20 8531 8886",
    "sg:postcode":"E17 4JT",
    "sg:province":"Greater London",
    "sg:tags":[
        "unisex",
        "hairdresser"
    ],
    "wof:name":"Flicks",
    "wof:placetype":"venue"
},
  "geometry": {"coordinates":[-0.007489,51.594025],"type":"Point"}
}