{
  "type": "Feature",
  "properties": {
    "addr:full":"Whitfield Farm, Warwick Road, Ettington Stratford-upon-avon Warwickshire CV37 7PN",
    "addr:postcode":"cv37 7pn",
    "addr:street":"Warwick Road",
    "iso:country":"GB",
    "sg:address":"Whitfield Farm, Warwick Road, Ettington",
    "sg:city":"Stratford-upon-avon",
    "sg:classifiers":[
        {
            "category":"Farming",
            "subcategory":"Crops",
            "type":"Manufacturing & Wholesale Goods"
        },
        {
            "category":"Farming",
            "subcategory":"Livestock Farm",
            "type":"Manufacturing & Wholesale Goods"
        }
    ],
    "sg:phone":"+44 1789 740260",
    "sg:postcode":"CV37 7PN",
    "sg:province":"Warwickshire",
    "sg:tags":[
        "arable",
        "others"
    ],
    "wof:name":"B J & J M & R J Wakeham",
    "wof:placetype":"venue"
},
  "geometry": {"coordinates":[-1.608049,52.137959],"type":"Point"}
}