{
  "type": "Feature",
  "properties": {
    "addr:full":"28 Barfillan Drive Glasgow Glasgow City G52 1AA",
    "addr:housenumber":"28",
    "addr:postcode":"g52 1aa",
    "addr:street":"Barfillan Drive",
    "iso:country":"GB",
    "sg:address":"28 Barfillan Drive",
    "sg:city":"Glasgow",
    "sg:classifiers":[
        {
            "category":"Personal",
            "subcategory":"Beauty Salon",
            "type":"Services"
        },
        {
            "category":"Personal",
            "subcategory":"Barber",
            "type":"Services"
        }
    ],
    "sg:phone":"+44 141 883 7000",
    "sg:postcode":"G52 1AA",
    "sg:province":"Glasgow City",
    "sg:tags":[
        "unisex",
        "hairdresser"
    ],
    "wof:name":"Marie C Rice Hair & Beauty",
    "wof:placetype":"venue"
},
  "geometry": {"coordinates":[-4.331703186,55.8475189209],"type":"Point"}
}