{
  "type": "Feature",
  "properties": {
    "addr:full":"324 Holloway Rd London Greater London N7 6NJ",
    "addr:housenumber":"324",
    "addr:postcode":"n7 6nj",
    "addr:street":"Holloway Rd",
    "iso:country":"GB",
    "sg:address":"324 Holloway Rd",
    "sg:city":"London",
    "sg:classifiers":[
        {
            "category":"Professional",
            "subcategory":"Computer Services",
            "type":"Services"
        }
    ],
    "sg:postcode":"N7 6NJ",
    "sg:province":"Greater London",
    "sg:tags":[
        "consultant"
    ],
    "wof:name":"Integrated Business Computer Systems Ltd",
    "wof:placetype":"venue"
},
  "geometry": {"coordinates":[-0.1152499989,51.5550575256],"type":"Point"}
}