{
  "type": "Feature",
  "properties": {
    "addr:full":"Marlborough House London Greater London E15 2PW",
    "addr:postcode":"e15 2pw",
    "iso:country":"GB",
    "sg:address":"Marlborough House",
    "sg:city":"London",
    "sg:classifiers":[
        {
            "category":"Building & Trades",
            "subcategory":"Construction",
            "type":"Services"
        },
        {
            "category":"Manufacturing",
            "subcategory":"Glass & Minerals",
            "type":"Manufacturing & Wholesale Goods"
        }
    ],
    "sg:phone":"+44 20 8536 0300",
    "sg:postcode":"E15 2PW",
    "sg:province":"Greater London",
    "sg:tags":[
        "builder",
        "stained"
    ],
    "wof:name":"Goddard & Gibbs Studios Ltd.",
    "wof:placetype":"venue"
},
  "geometry": {"coordinates":[-0.13589,51.505001],"type":"Point"}
}