{
  "type": "Feature",
  "properties": {
    "addr:full":"23 Maney Corner Sutton Coldfield West Midlands B72 1QL",
    "addr:housenumber":"23",
    "addr:postcode":"b72 1ql",
    "addr:street":"Maney Corner",
    "iso:country":"GB",
    "sg:address":"23 Maney Corner",
    "sg:city":"Sutton Coldfield",
    "sg:classifiers":[
        {
            "category":"Shopping",
            "subcategory":"Antiques",
            "type":"Retail Goods"
        }
    ],
    "sg:postcode":"B72 1QL",
    "sg:province":"West Midlands",
    "wof:name":"H & R L Parry Ltd.",
    "wof:placetype":"venue"
},
  "geometry": {"coordinates":[-1.826227,52.556976],"type":"Point"}
}