{
  "type": "Feature",
  "properties": {
    "iso:country":"GB",
    "sg:address":"High Street, Sengennedd",
    "sg:city":"Caerphilly",
    "sg:classifiers":[
        {
            "category":"Building & Trades",
            "subcategory":"Construction",
            "type":"Services"
        }
    ],
    "sg:phone":"+44 29 2083 0000",
    "sg:postcode":"CF83 4GH",
    "sg:province":"Caerphilly",
    "sg:tags":[
        "builder"
    ],
    "wof:name":"De Davies & Son",
    "wof:placetype":"venue"
},
  "geometry": {"coordinates":[-3.270457,51.598766],"type":"Point"}
}