{
  "type": "Feature",
  "properties": {
    "iso:country":"GB",
    "sg:address":"7-11 High St",
    "sg:city":"Sittingbourne",
    "sg:classifiers":[
        {
            "category":"Organizations",
            "subcategory":"Membership Organization",
            "type":"Services"
        },
        {
            "category":"Recreation",
            "type":"Entertainment"
        }
    ],
    "sg:phone":"+44 1795 471333",
    "sg:postcode":"ME10 4AY",
    "sg:province":"Kent",
    "sg:tags":[
        "club",
        "snooker",
        "billiards",
        "pool"
    ],
    "wof:name":"D L Leisure Ltd",
    "wof:placetype":"venue"
},
  "geometry": {"coordinates":[0.739964,51.339172],"type":"Point"}
}