{
  "type": "Feature",
  "properties": {
    "addr:full":"778 Green Lane, Winchmore Hill London Greater London N21 3RE",
    "addr:housenumber":"778",
    "addr:postcode":"n21 3re",
    "addr:street":"Green Lane",
    "iso:country":"GB",
    "sg:address":"778 Green Lane, Winchmore Hill",
    "sg:city":"London",
    "sg:classifiers":[
        {
            "category":"Sports & Exercise",
            "subcategory":"Sports Center",
            "type":"Entertainment"
        }
    ],
    "sg:postcode":"N21 3RE",
    "sg:province":"Greater London",
    "sg:tags":[
        "shop",
        "good"
    ],
    "wof:name":"Winchmore Sports",
    "wof:placetype":"venue"
},
  "geometry": {"coordinates":[-0.0957240015,51.6313247681],"type":"Point"}
}