{
  "type": "Feature",
  "properties": {
    "iso:country":"GB",
    "sg:address":"Foresters Hall, 25-27 Westow St",
    "sg:city":"London",
    "sg:classifiers":[
        {
            "category":"Manufacturing",
            "subcategory":"Textiles",
            "type":"Manufacturing & Wholesale Goods"
        }
    ],
    "sg:phone":"+44 20 8653 5511",
    "sg:postcode":"SE19 3RY",
    "sg:province":"Greater London",
    "sg:tags":[
        "merchant",
        "agent"
    ],
    "wof:name":"P H Marketing Ltd",
    "wof:placetype":"venue"
},
  "geometry": {"coordinates":[-0.082630001,51.4190597534],"type":"Point"}
}