{
  "type": "Feature",
  "properties": {
    "iso:country":"GB",
    "sg:address":"25 Chester Road",
    "sg:city":"Liverpool",
    "sg:classifiers":[
        {
            "category":"Building & Trades",
            "subcategory":"Plumbing",
            "type":"Services"
        }
    ],
    "sg:phone":"+44 151 263 3266",
    "sg:postcode":"L6 4DY",
    "sg:province":"Merseyside",
    "sg:tags":[
        "central",
        "heating"
    ],
    "wof:name":"Gillespie & Unwin",
    "wof:placetype":"venue"
},
  "geometry": {"coordinates":[-2.937058,53.424496],"type":"Point"}
}