{
  "type": "Feature",
  "properties": {
    "iso:country":"GB",
    "sg:address":"27 Wavell Road, Bridgemary",
    "sg:city":"Gosport",
    "sg:classifiers":[
        {
            "category":"Home & Garden",
            "subcategory":"Building Materials",
            "type":"Retail Goods"
        }
    ],
    "sg:phone":"+44 1329 312784",
    "sg:postcode":"PO13 0XR",
    "sg:province":"Hampshire",
    "sg:tags":[
        "fencing"
    ],
    "wof:name":"S P H Boundaries",
    "wof:placetype":"venue"
},
  "geometry": {"coordinates":[-1.166877,50.826164],"type":"Point"}
}