{
  "type": "Feature",
  "properties": {
    "addr:full":"29 China Street Lancaster Lancashire LA1 1EX",
    "addr:housenumber":"29",
    "addr:postcode":"la1 1ex",
    "addr:street":"China Street",
    "iso:country":"GB",
    "sg:address":"29 China Street",
    "sg:city":"Lancaster",
    "sg:classifiers":[
        {
            "category":"Shopping",
            "subcategory":"Clothing, Apparel, & Fashions",
            "type":"Retail Goods"
        }
    ],
    "sg:phone":"+44 1524 63047",
    "sg:postcode":"LA1 1EX",
    "sg:province":"Lancashire",
    "sg:tags":[
        "shop"
    ],
    "wof:name":"Margee Ltd.",
    "wof:placetype":"venue"
},
  "geometry": {"coordinates":[-2.802978,54.049908],"type":"Point"}
}