{
  "type": "Feature",
  "properties": {
    "iso:country":"GB",
    "sg:address":"Butterhaugh Farm, Gargrave",
    "sg:city":"Skipton",
    "sg:classifiers":[
        {
            "category":"Shopping",
            "subcategory":"Department Store",
            "type":"Retail Goods"
        },
        {
            "category":"Wholesale",
            "subcategory":"Toys & Hobbies",
            "type":"Manufacturing & Wholesale Goods"
        }
    ],
    "sg:postcode":"BD23 3QY",
    "sg:province":"Lancashire",
    "sg:tags":[
        "balloon",
        "novelty"
    ],
    "wof:name":"Black Sheep Balloons",
    "wof:placetype":"venue"
},
  "geometry": {"coordinates":[-2.1063439846,53.9831085205],"type":"Point"}
}