{
  "type": "Feature",
  "properties": {
    "iso:country":"GB",
    "sg:address":"59 Cathedral Rd",
    "sg:city":"Cardiff",
    "sg:classifiers":[
        {
            "category":"Health Services",
            "subcategory":"Doctor",
            "type":"Services"
        }
    ],
    "sg:phone":"+44 29 2039 7495",
    "sg:postcode":"CF1 9HE",
    "sg:province":"Cardiff",
    "sg:tags":[
        "practitioners"
    ],
    "wof:name":"Knight, A",
    "wof:placetype":"venue"
},
  "geometry": {"coordinates":[-3.193488,51.484859],"type":"Point"}
}