{
  "type": "Feature",
  "properties": {
    "addr:full":"292 Old Kent Road London Greater London SE1 5UE",
    "addr:housenumber":"292",
    "addr:postcode":"se1 5ue",
    "addr:street":"Old Kent Road",
    "iso:country":"GB",
    "sg:address":"292 Old Kent Road",
    "sg:city":"London",
    "sg:classifiers":[
        {
            "category":"Food & Beverages",
            "subcategory":"Bakery",
            "type":"Retail Goods"
        }
    ],
    "sg:phone":"+44 20 7703 5766",
    "sg:postcode":"SE1 5UE",
    "sg:province":"Greater London",
    "sg:tags":[
        "pizza"
    ],
    "wof:name":"Gabriella Pizza",
    "wof:placetype":"venue"
},
  "geometry": {"coordinates":[-0.077728,51.488712],"type":"Point"}
}