{
  "type": "Feature",
  "properties": {
    "addr:full":"44-46 Canal Street Nottingham Nottinghamshire NG1 7EH",
    "addr:housenumber":"44-46",
    "addr:postcode":"ng1 7eh",
    "addr:street":"Canal Street",
    "iso:country":"GB",
    "sg:address":"44-46 Canal Street",
    "sg:city":"Nottingham",
    "sg:classifiers":[
        {
            "category":"Bars & Pubs",
            "type":"Food & Drink"
        }
    ],
    "sg:phone":"+44 115 947 3904",
    "sg:postcode":"NG1 7EH",
    "sg:province":"Nottinghamshire",
    "sg:tags":[
        "pubs",
        "inn"
    ],
    "wof:name":"Greenalls Management Ltd.",
    "wof:placetype":"venue"
},
  "geometry": {"coordinates":[-1.1489230394,52.9485282898],"type":"Point"}
}