{
  "type": "Feature",
  "properties": {
    "iso:country":"GB",
    "sg:address":"13 Clarence Street",
    "sg:city":"Greenock",
    "sg:classifiers":[
        {
            "category":"Professional",
            "subcategory":"Engineering",
            "type":"Services"
        }
    ],
    "sg:phone":"+44 1475 720934",
    "sg:postcode":"PA15 1LR",
    "sg:province":"Inverclyde",
    "sg:tags":[
        "engineer"
    ],
    "sg:website":"http://www.devol.com",
    "wof:name":"Devol Engineering Ltd",
    "wof:placetype":"venue"
},
  "geometry": {"coordinates":[-4.762911,55.953842],"type":"Point"}
}