{
  "type": "Feature",
  "properties": {
    "iso:country":"GB",
    "sg:address":"Harcourt Mews, 13 Royal Cres",
    "sg:city":"Cheltenham",
    "sg:classifiers":[
        {
            "category":"Wholesale",
            "subcategory":"Books, Periodicals, & Newspapers",
            "type":"Manufacturing & Wholesale Goods"
        }
    ],
    "sg:phone":"+44 1242 578247",
    "sg:postcode":"GL50 3DA",
    "sg:province":"Gloucestershire",
    "sg:tags":[
        "publishing"
    ],
    "wof:name":"Ram Media Services Ltd",
    "wof:placetype":"venue"
},
  "geometry": {"coordinates":[-2.078459,51.898048],"type":"Point"}
}