{
  "type": "Feature",
  "properties": {
    "iso:country":"GB",
    "sg:address":"10 Hawthorn Avenue, Headington",
    "sg:city":"Oxford",
    "sg:classifiers":[
        {
            "category":"Organizations",
            "subcategory":"Religious Organization",
            "type":"Services"
        }
    ],
    "sg:phone":"+44 1865 763872",
    "sg:postcode":"OX3 9JG",
    "sg:province":"Oxfordshire",
    "sg:tags":[
        "organisation",
        "place",
        "worship"
    ],
    "wof:name":"Quakers Religious Society Of Friends",
    "wof:placetype":"venue"
},
  "geometry": {"coordinates":[-1.20403,51.763248],"type":"Point"}
}