{
  "type": "Feature",
  "properties": {
    "iso:country":"GB",
    "sg:address":"60 Brighton Rd",
    "sg:city":"Horley",
    "sg:classifiers":[
        {
            "category":"Bars & Pubs",
            "type":"Food & Drink"
        }
    ],
    "sg:phone":"+44 1293 820188",
    "sg:postcode":"RH6 7HE",
    "sg:province":"Surrey",
    "sg:tags":[
        "pubs",
        "inn"
    ],
    "wof:name":"Punch Leisure Ltd",
    "wof:placetype":"venue"
},
  "geometry": {"coordinates":[-0.17012,51.174202],"type":"Point"}
}