{
  "type": "Feature",
  "properties": {
    "iso:country":"GB",
    "sg:address":"28 High St",
    "sg:city":"Buntingford",
    "sg:classifiers":[
        {
            "category":"Food & Beverages",
            "subcategory":"Bakery",
            "type":"Retail Goods"
        }
    ],
    "sg:postcode":"SG9 9AQ",
    "sg:province":"Hertfordshire",
    "sg:tags":[
        "baker"
    ],
    "wof:name":"Mitchell,Sylvia,",
    "wof:placetype":"venue"
},
  "geometry": {"coordinates":[-0.019164,51.947449],"type":"Point"}
}