{
  "type": "Feature",
  "properties": {
    "iso:country":"GB",
    "sg:address":"11 Grattan Street, Kimbleworth",
    "sg:city":"Rotherham",
    "sg:classifiers":[
        {
            "category":"Building & Trades",
            "subcategory":"Construction",
            "type":"Services"
        }
    ],
    "sg:phone":"+44 1709 552306",
    "sg:postcode":"S61 2JP",
    "sg:province":"South Yorkshire",
    "sg:tags":[
        "builder"
    ],
    "wof:name":"McEwan & Swift",
    "wof:placetype":"venue"
},
  "geometry": {"coordinates":[-1.396484,53.43045],"type":"Point"}
}