{
  "type": "Feature",
  "properties": {
    "iso:country":"GB",
    "sg:address":"Longaller Mill, Longaller, Bishops Hull",
    "sg:city":"Taunton",
    "sg:classifiers":[
        {
            "category":"Home & Garden",
            "subcategory":"Furniture",
            "type":"Retail Goods"
        }
    ],
    "sg:postcode":"TA4 1AD",
    "sg:province":"Devon",
    "wof:name":"The Curtain Exchange",
    "wof:placetype":"venue"
},
  "geometry": {"coordinates":[-3.14661,51.020828],"type":"Point"}
}