{
  "type": "Feature",
  "properties": {
    "addr:full":"1a Paget Rd Barry The Vale of Glamorgan CF62 5TQ",
    "addr:housenumber":"1a",
    "addr:postcode":"cf62 5tq",
    "addr:street":"Paget Rd;Vale",
    "iso:country":"GB",
    "sg:address":"1a Paget Rd",
    "sg:city":"Barry",
    "sg:classifiers":[
        {
            "category":"Recreation",
            "subcategory":"Amusement Park",
            "type":"Entertainment"
        }
    ],
    "sg:phone":"+44 1446 421037",
    "sg:postcode":"CF62 5TQ",
    "sg:province":"The Vale of Glamorgan",
    "sg:tags":[
        "arcade"
    ],
    "wof:name":"Cha Cha's Amusements",
    "wof:placetype":"venue"
},
  "geometry": {"coordinates":[-3.2725479603,51.3931312561],"type":"Point"}
}