{
  "type": "Feature",
  "properties": {
    "addr:full":"Bergamoor Cottage, Woodhall Road, Stickswold Woodhall Spa Lincolnshire LN10 5HL",
    "addr:postcode":"ln10 5hl",
    "addr:street":"Woodhall Road Stickswold Woodhall Spa",
    "iso:country":"GB",
    "sg:address":"Bergamoor Cottage, Woodhall Road, Stickswold",
    "sg:city":"Woodhall Spa",
    "sg:classifiers":[
        {
            "category":"Building & Trades",
            "subcategory":"Plumbing",
            "type":"Services"
        }
    ],
    "sg:phone":"+44 1526 354346",
    "sg:postcode":"LN10 5HL",
    "sg:province":"Lincolnshire",
    "sg:tags":[
        "drain",
        "clearance",
        "sewer"
    ],
    "wof:name":"Ajet",
    "wof:placetype":"venue"
},
  "geometry": {"coordinates":[-0.23427,53.16938],"type":"Point"}
}