{
  "type": "Feature",
  "properties": {
    "addr:full":"6 Middlefield Road Falkirk Falkirk FK2 9AG",
    "addr:housenumber":"6",
    "addr:postcode":"fk2 9ag",
    "addr:street":"Middlefield Road",
    "iso:country":"GB",
    "sg:address":"6 Middlefield Road",
    "sg:city":"Falkirk",
    "sg:classifiers":[
        {
            "category":"Professional",
            "subcategory":"Engineering",
            "type":"Services"
        }
    ],
    "sg:postcode":"FK2 9AG",
    "sg:province":"Falkirk",
    "sg:tags":[
        "contractor",
        "electrical",
        "engineer"
    ],
    "wof:name":"Smith Contracting Services Ltd.",
    "wof:placetype":"venue"
},
  "geometry": {"coordinates":[-3.7659440041,56.0066719055],"type":"Point"}
}