{
  "type": "Feature",
  "properties": {
    "iso:country":"GB",
    "sg:address":"5 Church Street, Stapleford",
    "sg:city":"Nottingham",
    "sg:classifiers":[
        {
            "category":"Bars & Pubs",
            "type":"Food & Drink"
        },
        {
            "category":"Community Center",
            "subcategory":"Social",
            "type":"Public Place"
        }
    ],
    "sg:phone":"+44 115 939 9402",
    "sg:postcode":"NG9 8GA",
    "sg:province":"Nottinghamshire",
    "sg:tags":[
        "pubs",
        "house",
        "inn",
        "activity"
    ],
    "wof:name":"The Feathers Tavern",
    "wof:placetype":"venue"
},
  "geometry": {"coordinates":[-1.2744840384,52.9298439026],"type":"Point"}
}