{
  "type": "Feature",
  "properties": {
    "addr:full":"Genesis Centre, Garret Field Warrington Cheshire WA3 7BH",
    "addr:postcode":"wa3 7bh",
    "iso:country":"GB",
    "sg:address":"Genesis Centre, Garret Field",
    "sg:city":"Warrington",
    "sg:classifiers":[
        {
            "category":"Professional",
            "subcategory":"Lawyer & Legal Services",
            "type":"Services"
        }
    ],
    "sg:phone":"+44 1925 817837",
    "sg:postcode":"WA3 7BH",
    "sg:province":"Cheshire",
    "sg:tags":[
        "patent",
        "agent"
    ],
    "wof:name":"Potts Kerr & Co.",
    "wof:placetype":"venue"
},
  "geometry": {"coordinates":[-2.5282399654,53.4248580933],"type":"Point"}
}