{
  "type": "Feature",
  "properties": {
    "addr:full":"Craigencat, Henderson St Dunfermline Fife KY12 0TP",
    "addr:postcode":"ky12 0tp",
    "addr:street":"Henderson St",
    "iso:country":"GB",
    "sg:address":"Craigencat, Henderson St",
    "sg:city":"Dunfermline",
    "sg:classifiers":[
        {
            "category":"Freight",
            "type":"Transportation"
        }
    ],
    "sg:phone":"+44 1383 724356",
    "sg:postcode":"KY12 0TP",
    "sg:province":"Fife",
    "sg:tags":[
        "haulage",
        "road"
    ],
    "wof:name":"Ian Whitelaw",
    "wof:placetype":"venue"
},
  "geometry": {"coordinates":[-3.4613740444,56.0748443604],"type":"Point"}
}