{
  "type": "Feature",
  "properties": {
    "addr:full":"199 Westbourne Gro London Greater London W11 2SB",
    "addr:housenumber":"199",
    "addr:postcode":"w11 2sb",
    "addr:street":"Westbourne Gro",
    "iso:country":"GB",
    "sg:address":"199 Westbourne Gro",
    "sg:city":"London",
    "sg:classifiers":[
        {
            "category":"Professional",
            "type":"Services"
        }
    ],
    "sg:phone":"+44 20 7727 6016",
    "sg:postcode":"W11 2SB",
    "sg:province":"Greater London",
    "sg:tags":[
        "interior",
        "furnishers",
        "designer"
    ],
    "wof:name":"David Champion Ltd.",
    "wof:placetype":"venue"
},
  "geometry": {"coordinates":[-0.1986400038,51.5145301819],"type":"Point"}
}