{
  "type": "Feature",
  "properties": {
    "iso:country":"GB",
    "sg:address":"108 Park Drive",
    "sg:city":"Ilkeston",
    "sg:classifiers":[
        {
            "category":"Manufacturing",
            "subcategory":"Signs",
            "type":"Manufacturing & Wholesale Goods"
        }
    ],
    "sg:phone":"+44 115 930 5961",
    "sg:postcode":"DE7 5NS",
    "sg:province":"Derbyshire",
    "sg:tags":[
        "commercial",
        "maker"
    ],
    "wof:name":"Park Studio Signs & Displays",
    "wof:placetype":"venue"
},
  "geometry": {"coordinates":[-1.3020750284,52.9682312012],"type":"Point"}
}