{
  "type": "Feature",
  "properties": {
    "iso:country":"GB",
    "sg:address":"9 Briarwood Avenue",
    "sg:city":"Bury St Edmunds",
    "sg:classifiers":[
        {
            "category":"Farming",
            "subcategory":"Farm",
            "type":"Manufacturing & Wholesale Goods"
        }
    ],
    "sg:phone":"+44 1284 766336",
    "sg:postcode":"IP33 3QF",
    "sg:province":"Suffolk",
    "sg:tags":[
        "agricultural"
    ],
    "wof:name":"William Diaper",
    "wof:placetype":"venue"
},
  "geometry": {"coordinates":[0.693101,52.243904],"type":"Point"}
}