{
  "type": "Feature",
  "properties": {
    "addr:full":"Rowe La Hackney Greater London E9 6EL",
    "addr:postcode":"e9 6el",
    "iso:country":"GB",
    "sg:address":"Rowe La",
    "sg:city":"Hackney",
    "sg:classifiers":[
        {
            "category":"Manufacturing",
            "subcategory":"Metals",
            "type":"Manufacturing & Wholesale Goods"
        }
    ],
    "sg:phone":"+44 20 8985 5104",
    "sg:postcode":"E9 6EL",
    "sg:province":"Greater London",
    "wof:name":"Ronketti A H & Co Ltd",
    "wof:placetype":"venue"
},
  "geometry": {"coordinates":[-0.052009,51.550186],"type":"Point"}
}