{
  "type": "Feature",
  "properties": {
    "iso:country":"GB",
    "sg:address":"75 Commercial Road",
    "sg:city":"Bournemouth",
    "sg:classifiers":[
        {
            "category":"Shopping",
            "subcategory":"Clothing, Apparel, & Fashions",
            "type":"Retail Goods"
        }
    ],
    "sg:postcode":"BH2 5RT",
    "sg:province":"Dorset",
    "sg:tags":[
        "ladieswear"
    ],
    "wof:name":"Approved Fashions Ltd.",
    "wof:placetype":"venue"
},
  "geometry": {"coordinates":[-1.884054,50.720013],"type":"Point"}
}