{
  "type": "Feature",
  "properties": {
    "addr:full":"16 Mostyn Street Llandudno Conwy LL30 2PS",
    "addr:housenumber":"16",
    "addr:postcode":"ll30 2ps",
    "addr:street":"Mostyn Street",
    "iso:country":"GB",
    "sg:address":"16 Mostyn Street",
    "sg:city":"Llandudno",
    "sg:classifiers":[
        {
            "category":"Home & Garden",
            "subcategory":"Furniture",
            "type":"Retail Goods"
        }
    ],
    "sg:phone":"+44 1492 871809",
    "sg:postcode":"LL30 2PS",
    "sg:province":"Conwy",
    "wof:name":"Mensworld",
    "wof:placetype":"venue"
},
  "geometry": {"coordinates":[-3.825938,53.322433],"type":"Point"}
}