{
  "type": "Feature",
  "properties": {
    "addr:full":"The Granary, Stone Street, Crowfield Ipswich Suffolk IP6 9SZ",
    "addr:postcode":"ip6 9sz",
    "addr:street":"Stone Street",
    "iso:country":"GB",
    "sg:address":"The Granary, Stone Street, Crowfield",
    "sg:city":"Ipswich",
    "sg:classifiers":[
        {
            "category":"Personal",
            "type":"Services"
        }
    ],
    "sg:phone":"+44 1449 760567",
    "sg:postcode":"IP6 9SZ",
    "sg:province":"Suffolk",
    "sg:tags":[
        "wedding"
    ],
    "wof:name":"Lynda Grey Couturier",
    "wof:placetype":"venue"
},
  "geometry": {"coordinates":[1.201266,52.092407],"type":"Point"}
}