{
  "type": "Feature",
  "properties": {
    "addr:full":"Westwood Avenue Ayr South Ayrshire KA8 0QZ",
    "addr:postcode":"ka8 0qz",
    "addr:street":"Westwood Avenue",
    "iso:country":"GB",
    "sg:address":"Westwood Avenue",
    "sg:city":"Ayr",
    "sg:classifiers":[
        {
            "category":"Community Center",
            "type":"Public Place"
        },
        {
            "category":"Government",
            "subcategory":"Office",
            "type":"Public Place"
        }
    ],
    "sg:phone":"+44 1292 264578",
    "sg:postcode":"KA8 0QZ",
    "sg:province":"South Ayrshire",
    "sg:tags":[
        "local",
        "centre"
    ],
    "wof:name":"Dalmilling & Whitletts Community Centre",
    "wof:placetype":"venue"
},
  "geometry": {"coordinates":[-4.5869760513,55.471282959],"type":"Point"}
}