{
  "type": "Feature",
  "properties": {
    "iso:country":"GB",
    "sg:address":"Westhill Farm, Main St",
    "sg:city":"Hull",
    "sg:classifiers":[
        {
            "category":"Farming",
            "subcategory":"Livestock Farm",
            "type":"Manufacturing & Wholesale Goods"
        }
    ],
    "sg:phone":"+44 1964 670359",
    "sg:postcode":"HU12 0JF",
    "sg:province":"East Riding of Yorkshire",
    "sg:tags":[
        "others"
    ],
    "wof:name":"F A Grassby",
    "wof:placetype":"venue"
},
  "geometry": {"coordinates":[-0.031205,53.684456],"type":"Point"}
}