{
  "type": "Feature",
  "properties": {
    "addr:full":"Co-bam House, Pleasant Street Stoke-on-trent Staffordshire ST6 3DL",
    "addr:postcode":"st6 3dl",
    "addr:street":"Pleasant Street",
    "iso:country":"GB",
    "sg:address":"Co-bam House, Pleasant Street",
    "sg:city":"Stoke-on-trent",
    "sg:classifiers":[
        {
            "category":"Professional",
            "subcategory":"Engineering",
            "type":"Services"
        }
    ],
    "sg:phone":"+44 1782 577136",
    "sg:postcode":"ST6 3DL",
    "sg:province":"Staffordshire",
    "wof:name":"Co-Bam Ltd.",
    "wof:placetype":"venue"
},
  "geometry": {"coordinates":[-2.1971991062,53.0411567688],"type":"Point"}
}