{
  "type": "Feature",
  "properties": {
    "iso:country":"GB",
    "sg:address":"13 School Lane",
    "sg:city":"Leominster",
    "sg:classifiers":[
        {
            "category":"Personal",
            "subcategory":"Shoe Repair & Shine",
            "type":"Services"
        },
        {
            "category":"Shopping",
            "subcategory":"Shoes",
            "type":"Retail Goods"
        }
    ],
    "sg:phone":"+44 1568 611967",
    "sg:postcode":"HR6 8AA",
    "sg:province":"Herefordshire",
    "wof:name":"The Shoemakers Shop",
    "wof:placetype":"venue"
},
  "geometry": {"coordinates":[-2.737694,52.226566],"type":"Point"}
}