{
  "type": "Feature",
  "properties": {
    "addr:full":"28 Monkton Cres Poole Dorset BH12 4BX",
    "addr:housenumber":"28",
    "addr:postcode":"bh12 4bx",
    "addr:street":"Monkton Cres",
    "iso:country":"GB",
    "sg:address":"28 Monkton Cres",
    "sg:city":"Poole",
    "sg:classifiers":[
        {
            "category":"Professional",
            "subcategory":"Printing & Photocopies",
            "type":"Services"
        }
    ],
    "sg:postcode":"BH12 4BX",
    "sg:province":"Dorset",
    "sg:tags":[
        "trophy"
    ],
    "wof:name":"Randall,E,",
    "wof:placetype":"venue"
},
  "geometry": {"coordinates":[-1.9238220453,50.7435417175],"type":"Point"}
}