{
  "type": "Feature",
  "properties": {
    "addr:full":"11 Clayknowes Court Musselburgh City of Edinburgh EH21 6UT",
    "addr:housenumber":"11",
    "addr:postcode":"eh21 6ut",
    "addr:street":"Clayknowes Court",
    "iso:country":"GB",
    "sg:address":"11 Clayknowes Court",
    "sg:city":"Musselburgh",
    "sg:classifiers":[
        {
            "category":"Professional",
            "subcategory":"Engineering",
            "type":"Services"
        }
    ],
    "sg:postcode":"EH21 6UT",
    "sg:province":"City of Edinburgh",
    "sg:tags":[
        "contractor",
        "electrical",
        "engineer"
    ],
    "wof:name":"Advanced Security Systems",
    "wof:placetype":"venue"
},
  "geometry": {"coordinates":[-3.072009,55.935127],"type":"Point"}
}