{
  "type": "Feature",
  "properties": {
    "iso:country":"GB",
    "sg:address":"725 Pollokshaws Rd",
    "sg:city":"Glasgow",
    "sg:classifiers":[
        {
            "category":"Shopping",
            "subcategory":"News",
            "type":"Retail Goods"
        }
    ],
    "sg:postcode":"G41 2AA",
    "sg:province":"Glasgow City",
    "sg:tags":[
        "newsagent"
    ],
    "wof:name":"Kazmi,S I H,",
    "wof:placetype":"venue"
},
  "geometry": {"coordinates":[-4.270973,55.835953],"type":"Point"}
}