{
  "type": "Feature",
  "properties": {
    "iso:country":"GB",
    "sg:address":"Workshop Riccall Airfield, Barly",
    "sg:city":"Selby",
    "sg:classifiers":[
        {
            "category":"Freight",
            "type":"Transportation"
        }
    ],
    "sg:phone":"+44 1757 289285",
    "sg:postcode":"YO8 5LD",
    "sg:province":"East Riding of Yorkshire",
    "sg:tags":[
        "haulage",
        "road"
    ],
    "wof:name":"David Jarred Transport",
    "wof:placetype":"venue"
},
  "geometry": {"coordinates":[-1.0703459978,53.783908844],"type":"Point"}
}