{
  "type": "Feature",
  "properties": {
    "iso:country":"GB",
    "sg:address":"25 Upper Aughton Road",
    "sg:city":"Southport",
    "sg:classifiers":[
        {
            "category":"Food & Beverages",
            "subcategory":"Meat & Fish",
            "type":"Retail Goods"
        }
    ],
    "sg:phone":"+44 1704 568233",
    "sg:postcode":"PR8 5NA",
    "sg:province":"Lancashire",
    "sg:tags":[
        "butcher"
    ],
    "wof:name":"P Wragge",
    "wof:placetype":"venue"
},
  "geometry": {"coordinates":[-3.0091500282,53.6367530823],"type":"Point"}
}