{
  "type": "Feature",
  "properties": {
    "addr:full":"45 Dyer Street Cirencester Gloucestershire GL7 2PP",
    "addr:housenumber":"45",
    "addr:postcode":"gl7 2pp",
    "addr:street":"Dyer Street",
    "iso:country":"GB",
    "sg:address":"45 Dyer Street",
    "sg:city":"Cirencester",
    "sg:classifiers":[
        {
            "category":"Professional",
            "subcategory":"Computer Services",
            "type":"Services"
        }
    ],
    "sg:phone":"+44 1285 643400",
    "sg:postcode":"GL7 2PP",
    "sg:province":"Gloucestershire",
    "sg:tags":[
        "consultant"
    ],
    "wof:name":"The Virtual World (U K) Ltd.",
    "wof:placetype":"venue"
},
  "geometry": {"coordinates":[-1.963213,51.716251],"type":"Point"}
}