{
  "type": "Feature",
  "properties": {
    "iso:country":"GB",
    "sg:address":"42 Palace Avenue",
    "sg:city":"Paignton",
    "sg:classifiers":[
        {
            "category":"Organizations",
            "subcategory":"Non-profit Organization",
            "type":"Services"
        }
    ],
    "sg:phone":"+44 1803 668080",
    "sg:postcode":"TQ3 3HF",
    "sg:province":"Devon",
    "sg:tags":[
        "organisation",
        "voluntary",
        "charity"
    ],
    "wof:name":"The Childrens Society",
    "wof:placetype":"venue"
},
  "geometry": {"coordinates":[-3.5698471069,50.4350395203],"type":"Point"}
}