{
  "type": "Feature",
  "properties": {
    "addr:full":"Fleet House, 15 Trafalgar Street Plymouth Devon PL4 9AE",
    "addr:housenumber":"15",
    "addr:postcode":"pl4 9ae",
    "addr:street":"Trafalgar Street",
    "iso:country":"GB",
    "sg:address":"Fleet House, 15 Trafalgar Street",
    "sg:city":"Plymouth",
    "sg:classifiers":[
        {
            "category":"Building & Trades",
            "subcategory":"Construction",
            "type":"Services"
        }
    ],
    "sg:postcode":"PL4 9AE",
    "sg:province":"Devon",
    "sg:tags":[
        "roofing"
    ],
    "wof:name":"Roofseal",
    "wof:placetype":"venue"
},
  "geometry": {"coordinates":[-4.134133,50.372456],"type":"Point"}
}