{
  "type": "Feature",
  "properties": {
    "addr:full":"4 Cattle Market Road Peterborough Cambridgeshire PE1 1TW",
    "addr:housenumber":"4",
    "addr:postcode":"pe1 1tw",
    "addr:street":"Cattle Market Road",
    "iso:country":"GB",
    "sg:address":"4 Cattle Market Road",
    "sg:city":"Peterborough",
    "sg:classifiers":[
        {
            "category":"Shopping",
            "subcategory":"Musical Instruments",
            "type":"Retail Goods"
        }
    ],
    "sg:phone":"+44 1733 345385",
    "sg:postcode":"PE1 1TW",
    "sg:province":"Cambridgeshire",
    "sg:tags":[
        "music",
        "sheet"
    ],
    "wof:name":"STAMFORD MUSIC SHOP",
    "wof:placetype":"venue"
},
  "geometry": {"coordinates":[-0.240673,52.575405],"type":"Point"}
}