{
  "type": "Feature",
  "properties": {
    "addr:full":"8a London Road Grays Essex RM17 5XY",
    "addr:housenumber":"8a",
    "addr:postcode":"rm17 5xy",
    "addr:street":"London Road",
    "iso:country":"GB",
    "sg:address":"8a London Road",
    "sg:city":"Grays",
    "sg:classifiers":[
        {
            "category":"Real Estate",
            "subcategory":"Real Estate Agent",
            "type":"Services"
        }
    ],
    "sg:postcode":"RM17 5XY",
    "sg:province":"Essex",
    "wof:name":"Purple Property Management Limited",
    "wof:placetype":"venue"
},
  "geometry": {"coordinates":[0.3224380016,51.4784507751],"type":"Point"}
}