{
  "type": "Feature",
  "properties": {
    "addr:full":"190 Gravelly Lane, Erdington Birmingham West Midlands B23 5SN",
    "addr:housenumber":"190",
    "addr:postcode":"b23 5sn",
    "addr:street":"Gravelly Lane",
    "iso:country":"GB",
    "sg:address":"190 Gravelly Lane, Erdington",
    "sg:city":"Birmingham",
    "sg:classifiers":[
        {
            "category":"Shopping",
            "subcategory":"Discount & Variety Stores",
            "type":"Retail Goods"
        }
    ],
    "sg:phone":"+44 121 384 3737",
    "sg:postcode":"B23 5SN",
    "sg:province":"West Midlands",
    "sg:tags":[
        "shop",
        "model"
    ],
    "wof:name":"Sleepers",
    "wof:placetype":"venue"
},
  "geometry": {"coordinates":[-1.840982,52.531883],"type":"Point"}
}