{
  "type": "Feature",
  "properties": {
    "addr:full":"33 Westbourne Road, Urmston Manchester Cheshire M41 0XQ",
    "addr:housenumber":"33",
    "addr:postcode":"m41 0xq",
    "addr:street":"Westbourne Road",
    "iso:country":"GB",
    "sg:address":"33 Westbourne Road, Urmston",
    "sg:city":"Manchester",
    "sg:classifiers":[
        {
            "category":"Health Services",
            "subcategory":"Podiatrist",
            "type":"Services"
        }
    ],
    "sg:phone":"+44 161 748 5194",
    "sg:postcode":"M41 0XQ",
    "sg:province":"Cheshire",
    "sg:tags":[
        "podiatrists",
        "chiropodist"
    ],
    "wof:name":"ELIZABETH MILLER",
    "wof:placetype":"venue"
},
  "geometry": {"coordinates":[-2.350271,53.45129],"type":"Point"}
}