{
  "type": "Feature",
  "properties": {
    "addr:full":"46 Girton Avenue Colindale Greater London NW9 9SU",
    "addr:housenumber":"46",
    "addr:postcode":"nw9 9su",
    "addr:street":"Girton Avenue",
    "iso:country":"GB",
    "sg:address":"46 Girton Avenue",
    "sg:city":"Colindale",
    "sg:classifiers":[
        {
            "category":"Health Services",
            "subcategory":"Doctor",
            "type":"Services"
        }
    ],
    "sg:phone":"+44 20 8206 1490",
    "sg:postcode":"NW9 9SU",
    "sg:province":"Greater London",
    "sg:tags":[
        "practitioners"
    ],
    "wof:name":"Dr N Banerjee",
    "wof:placetype":"venue"
},
  "geometry": {"coordinates":[-0.2786220014,51.5925941467],"type":"Point"}
}