{
  "type": "Feature",
  "properties": {
    "addr:full":"39 Kirfield Dr Hinckley Leicestershire LE10 1SX",
    "addr:housenumber":"39",
    "addr:postcode":"le10 1sx",
    "addr:street":"Kirfield Dr",
    "iso:country":"GB",
    "sg:address":"39 Kirfield Dr",
    "sg:city":"Hinckley",
    "sg:classifiers":[
        {
            "category":"Building & Trades",
            "subcategory":"Construction",
            "type":"Services"
        }
    ],
    "sg:postcode":"LE10 1SX",
    "sg:province":"Leicestershire",
    "sg:tags":[
        "valve"
    ],
    "wof:name":"Eurovalve Uk",
    "wof:placetype":"venue"
},
  "geometry": {"coordinates":[-1.356732,52.553013],"type":"Point"}
}