{
  "type": "Feature",
  "properties": {
    "iso:country":"GB",
    "sg:address":"High Street",
    "sg:city":"Ipswich",
    "sg:classifiers":[
        {
            "category":"Arena",
            "subcategory":"Sports Club",
            "type":"Entertainment"
        }
    ],
    "sg:phone":"+44 1449 760577",
    "sg:postcode":"IP6 9PN",
    "sg:province":"Suffolk",
    "sg:tags":[
        "country"
    ],
    "wof:name":"Coddenham Country Club",
    "wof:placetype":"venue"
},
  "geometry": {"coordinates":[1.122784,52.144955],"type":"Point"}
}