{
  "type": "Feature",
  "properties": {
    "addr:full":"Merril Grange, Belton Loughborough Leicestershire LE12 9UJ",
    "addr:postcode":"le12 9uj",
    "iso:country":"GB",
    "sg:address":"Merril Grange, Belton",
    "sg:city":"Loughborough",
    "sg:classifiers":[
        {
            "category":"Farming",
            "subcategory":"Crops",
            "type":"Manufacturing & Wholesale Goods"
        },
        {
            "category":"Farming",
            "subcategory":"Farm",
            "type":"Manufacturing & Wholesale Goods"
        }
    ],
    "sg:phone":"+44 1530 222214",
    "sg:postcode":"LE12 9UJ",
    "sg:province":"Leicestershire",
    "sg:tags":[
        "mixed",
        "arable"
    ],
    "wof:name":"W H Groombridge & Sons",
    "wof:placetype":"venue"
},
  "geometry": {"coordinates":[-1.3379230499,52.7799072266],"type":"Point"}
}