{
  "type": "Feature",
  "properties": {
    "addr:full":"Unit 7 Millfield Road, Boundary Industrial Estate Bolton Lancashire BL2 6QZ",
    "addr:housenumber":"unit 7",
    "addr:postcode":"bl2 6qz",
    "addr:street":"Millfield Road Boundary Industrial Estate",
    "iso:country":"GB",
    "sg:address":"Unit 7 Millfield Road, Boundary Industrial Estate",
    "sg:city":"Bolton",
    "sg:classifiers":[
        {
            "category":"Professional",
            "type":"Services"
        }
    ],
    "sg:phone":"+44 1204 395730",
    "sg:postcode":"BL2 6QZ",
    "sg:province":"Lancashire",
    "sg:tags":[
        "display",
        "maker"
    ],
    "wof:name":"Harewood Products Ltd.",
    "wof:placetype":"venue"
},
  "geometry": {"coordinates":[-2.375837,53.579628],"type":"Point"}
}