{
  "type": "Feature",
  "properties": {
    "iso:country":"GB",
    "sg:address":"Maryfield Sports Centre, Mains Loan",
    "sg:city":"Dundee",
    "sg:classifiers":[
        {
            "category":"Building & Trades",
            "subcategory":"Landscaping Services",
            "type":"Services"
        }
    ],
    "sg:phone":"+44 1382 457061",
    "sg:postcode":"DD4 7AB",
    "sg:province":"Dundee City",
    "sg:tags":[
        "contractor",
        "sport",
        "ground"
    ],
    "wof:name":"Maryfield Astro Turf",
    "wof:placetype":"venue"
},
  "geometry": {"coordinates":[-2.9564139843,56.4753494263],"type":"Point"}
}