{
  "type": "Feature",
  "properties": {
    "addr:full":"Elder Cottage, 17 The Flat, Kilburn Belper Derbyshire DE56 0LA",
    "addr:housenumber":"17",
    "addr:postcode":"de56 0la",
    "addr:street":"The Flat",
    "iso:country":"GB",
    "sg:address":"Elder Cottage, 17 The Flat, Kilburn",
    "sg:city":"Belper",
    "sg:classifiers":[
        {
            "category":"Building & Trades",
            "subcategory":"Cleaning & Sanitation",
            "type":"Services"
        }
    ],
    "sg:postcode":"DE56 0LA",
    "sg:province":"Derbyshire",
    "sg:tags":[
        "cleaner",
        "window"
    ],
    "wof:name":"Stephen R Moore",
    "wof:placetype":"venue"
},
  "geometry": {"coordinates":[-1.4373650551,53.0078353882],"type":"Point"}
}