{
  "type": "Feature",
  "properties": {
    "addr:full":"Unit 201 Mare Street Studios, 203/213 Mare Street London Greater London E8 3QE",
    "addr:housenumber":"201;203 / 213",
    "addr:postcode":"e8 3qe",
    "addr:street":"Mare;Mare Street",
    "iso:country":"GB",
    "sg:address":"Unit 201 Mare Street Studios, 203/213 Mare Street",
    "sg:city":"London",
    "sg:classifiers":[
        {
            "category":"Professional",
            "subcategory":"Detective & Security Services",
            "type":"Services"
        }
    ],
    "sg:phone":"+44 20 8985 9510",
    "sg:postcode":"E8 3QE",
    "sg:province":"Greater London",
    "sg:tags":[
        "car"
    ],
    "wof:name":"Targetace Ltd",
    "wof:placetype":"venue"
},
  "geometry": {"coordinates":[-0.05482,51.547241],"type":"Point"}
}