{
  "type": "Feature",
  "properties": {
    "iso:country":"GB",
    "sg:address":"Double Row, Seaton Delaval",
    "sg:city":"Whitley Bay",
    "sg:classifiers":[
        {
            "category":"Wholesale",
            "subcategory":"Fruits & Vegetables",
            "type":"Manufacturing & Wholesale Goods"
        }
    ],
    "sg:phone":"+44 191 237 3073",
    "sg:postcode":"NE25 0PP",
    "sg:province":"Northumberland",
    "wof:name":"J H Laidler & Son",
    "wof:placetype":"venue"
},
  "geometry": {"coordinates":[-1.5266029835,55.0733108521],"type":"Point"}
}