{
  "type": "Feature",
  "properties": {
    "addr:full":"34 Balsham Road, Linton Cambridge Cambridgeshire CB1 6LD",
    "addr:housenumber":"34",
    "addr:postcode":"cb1 6ld",
    "addr:street":"Balsham Road",
    "iso:country":"GB",
    "sg:address":"34 Balsham Road, Linton",
    "sg:city":"Cambridge",
    "sg:classifiers":[
        {
            "category":"Building & Trades",
            "subcategory":"Plumbing",
            "type":"Services"
        }
    ],
    "sg:phone":"+44 1223 892027",
    "sg:postcode":"CB1 6LD",
    "sg:province":"Cambridgeshire",
    "sg:tags":[
        "heating"
    ],
    "wof:name":"Boilercare",
    "wof:placetype":"venue"
},
  "geometry": {"coordinates":[0.28495,52.099579],"type":"Point"}
}