{
  "type": "Feature",
  "properties": {
    "addr:full":"15 Ravenhill Avenue, Knowle Bristol City of Bristol BS3 5DU",
    "addr:housenumber":"15",
    "addr:postcode":"bs3 5du",
    "addr:street":"Ravenhill Avenue",
    "iso:country":"GB",
    "sg:address":"15 Ravenhill Avenue, Knowle",
    "sg:city":"Bristol",
    "sg:classifiers":[
        {
            "category":"Utilities",
            "type":"Services"
        }
    ],
    "sg:phone":"+44 117 908 1432",
    "sg:postcode":"BS3 5DU",
    "sg:province":"City of Bristol",
    "sg:tags":[
        "internet"
    ],
    "wof:name":"Trefoil Solutions Ltd.",
    "wof:placetype":"venue"
},
  "geometry": {"coordinates":[-2.5793368816,51.4360351562],"type":"Point"}
}