{
  "type": "Feature",
  "properties": {
    "iso:country":"GB",
    "sg:address":"983 Tyburn Road",
    "sg:city":"Birmingham",
    "sg:classifiers":[
        {
            "category":"Personal",
            "subcategory":"Beauty Salon",
            "type":"Services"
        },
        {
            "category":"Personal",
            "subcategory":"Barber",
            "type":"Services"
        }
    ],
    "sg:phone":"+44 121 373 7989",
    "sg:postcode":"B24 0TJ",
    "sg:province":"West Midlands",
    "sg:tags":[
        "unisex",
        "hairdresser"
    ],
    "wof:name":"Bojangles",
    "wof:placetype":"venue"
},
  "geometry": {"coordinates":[-1.8182369471,52.5172195435],"type":"Point"}
}