{
  "type": "Feature",
  "properties": {
    "addr:full":"3rd Floor, 59 Brewer St London Greater London W1F 9UN",
    "addr:housenumber":"3rd floor 59",
    "addr:postcode":"w1f 9un",
    "addr:street":"Brewer St",
    "iso:country":"GB",
    "sg:address":"3rd Floor, 59 Brewer St",
    "sg:city":"London",
    "sg:classifiers":[
        {
            "category":"Personal",
            "type":"Services"
        }
    ],
    "sg:postcode":"W1F 9UN",
    "sg:province":"Greater London",
    "sg:tags":[
        "tailor"
    ],
    "wof:name":"Soteriou,S,",
    "wof:placetype":"venue"
},
  "geometry": {"coordinates":[-0.1354569942,51.5114059448],"type":"Point"}
}