{
  "type": "Feature",
  "properties": {
    "addr:full":"376-378 Queens Road Halifax West Yorkshire HX1 4PH",
    "addr:housenumber":"376-378",
    "addr:postcode":"hx1 4ph",
    "addr:street":"Queens Road",
    "iso:country":"GB",
    "sg:address":"376-378 Queens Road",
    "sg:city":"Halifax",
    "sg:classifiers":[
        {
            "category":"Shopping",
            "subcategory":"Used Merchandise",
            "type":"Retail Goods"
        }
    ],
    "sg:phone":"+44 1422 364090",
    "sg:postcode":"HX1 4PH",
    "sg:province":"West Yorkshire",
    "sg:tags":[
        "furniture"
    ],
    "wof:name":"Queens Road Travel",
    "wof:placetype":"venue"
},
  "geometry": {"coordinates":[-1.8806090355,53.7283592224],"type":"Point"}
}