{
  "type": "Feature",
  "properties": {
    "addr:full":"Security Ho, 23 Heathfield Rd Birmingham West Midlands B14 7BY",
    "addr:housenumber":"23",
    "addr:postcode":"b14 7by",
    "addr:street":"Heathfield Rd",
    "iso:country":"GB",
    "sg:address":"Security Ho, 23 Heathfield Rd",
    "sg:city":"Birmingham",
    "sg:classifiers":[
        {
            "category":"Banks & Credit Unions",
            "subcategory":"Financial Services",
            "type":"Services"
        }
    ],
    "sg:phone":"+44 121 693 9106",
    "sg:postcode":"B14 7BY",
    "sg:province":"West Midlands",
    "sg:tags":[
        "consultant"
    ],
    "wof:name":"Secure Homes Personal Lending",
    "wof:placetype":"venue"
},
  "geometry": {"coordinates":[-1.908604,52.478596],"type":"Point"}
}