{
  "type": "Feature",
  "properties": {
    "addr:full":"Kebcote Todmorden Lancashire OL14 8SB",
    "addr:postcode":"ol14 8sb",
    "iso:country":"GB",
    "sg:address":"Kebcote",
    "sg:city":"Todmorden",
    "sg:classifiers":[
        {
            "category":"Transit Center",
            "subcategory":"Passenger",
            "type":"Transportation"
        }
    ],
    "sg:postcode":"OL14 8SB",
    "sg:province":"Lancashire",
    "sg:tags":[
        "boarding",
        "kennel",
        "catteries"
    ],
    "wof:name":"Sunnyview Kennels & Cattery",
    "wof:placetype":"venue"
},
  "geometry": {"coordinates":[-2.0973079205,53.7143096924],"type":"Point"}
}