{
  "type": "Feature",
  "properties": {
    "addr:full":"16 Grange Av Kenilworth Warwickshire CV8 1DD",
    "addr:housenumber":"16",
    "addr:postcode":"cv8 1dd",
    "addr:street":"Grange Av",
    "iso:country":"GB",
    "sg:address":"16 Grange Av",
    "sg:city":"Kenilworth",
    "sg:classifiers":[
        {
            "category":"Professional",
            "subcategory":"Lawyer & Legal Services",
            "type":"Services"
        }
    ],
    "sg:phone":"+44 1926 511154",
    "sg:postcode":"CV8 1DD",
    "sg:province":"Warwickshire",
    "sg:tags":[
        "writing"
    ],
    "wof:name":"P Ramsbottom",
    "wof:placetype":"venue"
},
  "geometry": {"coordinates":[-1.588966,52.354084],"type":"Point"}
}