{
  "type": "Feature",
  "properties": {
    "addr:full":"1st Floor, 2-4 Kenway Road London Greater London SW5 0RR",
    "addr:housenumber":"2-4",
    "addr:postcode":"sw5 0rr",
    "addr:street":"Kenway Road",
    "iso:country":"GB",
    "sg:address":"1st Floor, 2-4 Kenway Road",
    "sg:city":"London",
    "sg:classifiers":[
        {
            "category":"Professional",
            "subcategory":"Business Services",
            "type":"Services"
        }
    ],
    "sg:postcode":"SW5 0RR",
    "sg:province":"Greater London",
    "sg:tags":[
        "import",
        "export",
        "agent"
    ],
    "wof:name":"Europhil Shipping (U.K.) Ltd",
    "wof:placetype":"venue"
},
  "geometry": {"coordinates":[-0.1934410036,51.4927024841],"type":"Point"}
}