{
  "type": "Feature",
  "properties": {
    "iso:country":"GB",
    "sg:address":"Chatsworth Road, Gorton",
    "sg:city":"Manchester",
    "sg:classifiers":[
        {
            "category":"Autos & Motor Vehicles",
            "subcategory":"Auto Supplies",
            "type":"Retail Goods"
        }
    ],
    "sg:postcode":"M18 7AF",
    "sg:province":"Greater Manchester",
    "sg:tags":[
        "tyre"
    ],
    "wof:name":"Roadrunner Tyres",
    "wof:placetype":"venue"
},
  "geometry": {"coordinates":[-2.172884,53.461079],"type":"Point"}
}