{
  "type": "Feature",
  "properties": {
    "iso:country":"GB",
    "sg:address":"162 Folkestone Rd",
    "sg:city":"Dover",
    "sg:classifiers":[
        {
            "category":"Education",
            "subcategory":"Special Training",
            "type":"Public Place"
        }
    ],
    "sg:phone":"+44 1304 241376",
    "sg:postcode":"CT17 9SN",
    "sg:province":"Kent",
    "sg:tags":[
        "product",
        "centre"
    ],
    "wof:name":"The Glen Study Centre",
    "wof:placetype":"venue"
},
  "geometry": {"coordinates":[1.296503,51.123581],"type":"Point"}
}