{
  "type": "Feature",
  "properties": {
    "addr:full":"Maryfield Goods Yard, Clepington Road Dundee Dundee City DD4 7DF",
    "addr:postcode":"dd4 7df",
    "addr:street":"Clepington Road",
    "iso:country":"GB",
    "sg:address":"Maryfield Goods Yard, Clepington Road",
    "sg:city":"Dundee",
    "sg:classifiers":[
        {
            "category":"Professional",
            "type":"Services"
        },
        {
            "category":"Personal",
            "type":"Services"
        }
    ],
    "sg:phone":"+44 1382 462999",
    "sg:postcode":"DD4 7DF",
    "sg:province":"Dundee City",
    "sg:tags":[
        "delivery",
        "good"
    ],
    "sg:website":"http://www.lynx.co.uk",
    "wof:name":"Lynx Express Ltd",
    "wof:placetype":"venue"
},
  "geometry": {"coordinates":[-2.956414,56.475349],"type":"Point"}
}