{
  "type": "Feature",
  "properties": {
    "addr:full":"108 Leonard Street London Greater London EC2A 4RH",
    "addr:housenumber":"108",
    "addr:postcode":"ec2a 4rh",
    "addr:street":"Leonard Street",
    "iso:country":"GB",
    "sg:address":"108 Leonard Street",
    "sg:city":"London",
    "sg:classifiers":[
        {
            "category":"Communications",
            "subcategory":"Film & Video Production",
            "type":"Services"
        }
    ],
    "sg:phone":"+44 20 7613 4040",
    "sg:postcode":"EC2A 4RH",
    "sg:province":"Greater London",
    "sg:tags":[
        "illustrator",
        "artist"
    ],
    "wof:name":"Arena",
    "wof:placetype":"venue"
},
  "geometry": {"coordinates":[-0.0811539963,51.5245513916],"type":"Point"}
}