{
  "type": "Feature",
  "properties": {
    "iso:country":"GB",
    "sg:address":"36 Huntley Road",
    "sg:city":"Sheffield",
    "sg:classifiers":[
        {
            "category":"Military Area",
            "subcategory":"Air Force Base",
            "type":"Public Place"
        }
    ],
    "sg:phone":"+44 114 268 3502",
    "sg:postcode":"S11 7PA",
    "sg:province":"Derbyshire",
    "sg:tags":[
        "taxi",
        "hire",
        "private"
    ],
    "wof:name":"Westside Travel",
    "wof:placetype":"venue"
},
  "geometry": {"coordinates":[-1.516693,53.358364],"type":"Point"}
}