{
  "type": "Feature",
  "properties": {
    "addr:full":"49 Craigneuk Street Motherwell North Lanarkshire ML1 2NT",
    "addr:housenumber":"49",
    "addr:postcode":"ml1 2nt",
    "addr:street":"Craigneuk Street",
    "iso:country":"GB",
    "sg:address":"49 Craigneuk Street",
    "sg:city":"Motherwell",
    "sg:classifiers":[
        {
            "category":"Shopping",
            "subcategory":"Used Merchandise",
            "type":"Retail Goods"
        }
    ],
    "sg:phone":"+44 1698 356801",
    "sg:postcode":"ML1 2NT",
    "sg:province":"North Lanarkshire",
    "sg:tags":[
        "shop",
        "second-hand"
    ],
    "wof:name":"Ger-Rards",
    "wof:placetype":"venue"
},
  "geometry": {"coordinates":[-3.9687240124,55.7815208435],"type":"Point"}
}