{
  "type": "Feature",
  "properties": {
    "iso:country":"GB",
    "sg:address":"6 Hazelbank Close, Sheet",
    "sg:city":"Petersfield",
    "sg:classifiers":[
        {
            "category":"Professional",
            "subcategory":"Computer Services",
            "type":"Services"
        }
    ],
    "sg:postcode":"GU31 4BY",
    "sg:province":"Hampshire",
    "sg:tags":[
        "system",
        "software"
    ],
    "wof:name":"Allcode Ltd",
    "wof:placetype":"venue"
},
  "geometry": {"coordinates":[-0.9196090102,51.0092468262],"type":"Point"}
}