{
  "type": "Feature",
  "properties": {
    "addr:full":"108 Windmill Lane Smethwick West Midlands B66 3EW",
    "addr:housenumber":"108",
    "addr:postcode":"b66 3ew",
    "addr:street":"Windmill Lane",
    "iso:country":"GB",
    "sg:address":"108 Windmill Lane",
    "sg:city":"Smethwick",
    "sg:classifiers":[
        {
            "category":"Fast Food",
            "type":"Food & Drink"
        }
    ],
    "sg:postcode":"B66 3EW",
    "sg:province":"West Midlands",
    "sg:tags":[
        "away",
        "take"
    ],
    "wof:name":"Carribean Takeaway",
    "wof:placetype":"venue"
},
  "geometry": {"coordinates":[-1.959727,52.486912],"type":"Point"}
}