{
  "type": "Feature",
  "properties": {
    "iso:country":"GB",
    "sg:address":"74 Calder Street",
    "sg:city":"Glasgow",
    "sg:classifiers":[
        {
            "category":"Food & Beverages",
            "subcategory":"Meat & Fish",
            "type":"Retail Goods"
        },
        {
            "category":"Food & Beverages",
            "subcategory":"Groceries & Convenience Stores",
            "type":"Retail Goods"
        }
    ],
    "sg:phone":"+44 141 423 4450",
    "sg:postcode":"G42 7RX",
    "sg:province":"Glasgow City",
    "sg:tags":[
        "shop",
        "chip"
    ],
    "wof:name":"Danny's Fish Bar",
    "wof:placetype":"venue"
},
  "geometry": {"coordinates":[-4.264924,55.837826],"type":"Point"}
}