{
  "type": "Feature",
  "properties": {
    "iso:country":"GB",
    "sg:address":"274 Picton Road, Wavertree",
    "sg:city":"Liverpool",
    "sg:classifiers":[
        {
            "category":"Manufacturing",
            "subcategory":"Wood Products",
            "type":"Manufacturing & Wholesale Goods"
        },
        {
            "category":"Building & Trades",
            "subcategory":"Construction",
            "type":"Services"
        }
    ],
    "sg:phone":"+44 151 734 1744",
    "sg:postcode":"L15 4LP",
    "sg:province":"Merseyside",
    "sg:tags":[
        "joinery",
        "joiner",
        "carpenter",
        "manufacturer"
    ],
    "wof:name":"Hi Tech Joinery",
    "wof:placetype":"venue"
},
  "geometry": {"coordinates":[-2.922631,53.39904],"type":"Point"}
}