{
  "type": "Feature",
  "properties": {
    "addr:full":"Tyn-y-coed Farm, Bonvilston Cardiff Cardiff CF5 6TQ",
    "addr:postcode":"cf5 6tq",
    "addr:street":"Bonvilston",
    "iso:country":"GB",
    "sg:address":"Tyn-y-coed Farm, Bonvilston",
    "sg:city":"Cardiff",
    "sg:classifiers":[
        {
            "category":"Farming",
            "subcategory":"Livestock Farm",
            "type":"Manufacturing & Wholesale Goods"
        },
        {
            "category":"Farming",
            "subcategory":"Farm",
            "type":"Manufacturing & Wholesale Goods"
        }
    ],
    "sg:phone":"+44 1446 781256",
    "sg:postcode":"CF5 6TQ",
    "sg:province":"Cardiff",
    "sg:tags":[
        "mixed",
        "crop",
        "others"
    ],
    "wof:name":"W S Jones & Son",
    "wof:placetype":"venue"
},
  "geometry": {"coordinates":[-3.3435111046,51.4577407837],"type":"Point"}
}