{
  "type": "Feature",
  "properties": {
    "addr:full":"West Mains Granary, Blyth Bridge West Linton Midlothian EH46 7AH",
    "addr:postcode":"eh46 7ah",
    "addr:street":"West;Blyth Bridge West",
    "iso:country":"GB",
    "sg:address":"West Mains Granary, Blyth Bridge",
    "sg:city":"West Linton",
    "sg:classifiers":[
        {
            "category":"Building & Trades",
            "subcategory":"Construction",
            "type":"Services"
        }
    ],
    "sg:phone":"+44 1721 752689",
    "sg:postcode":"EH46 7AH",
    "sg:province":"Midlothian",
    "sg:tags":[
        "paint",
        "household",
        "spraying"
    ],
    "wof:name":"The Byre",
    "wof:placetype":"venue"
},
  "geometry": {"coordinates":[-3.356034,55.754299],"type":"Point"}
}