{
  "type": "Feature",
  "properties": {
    "addr:full":"Sutton Rd Salisbury Wiltshire SP3 5LF",
    "addr:postcode":"sp3 5lf",
    "addr:street":"Sutton Rd",
    "iso:country":"GB",
    "sg:address":"Sutton Rd",
    "sg:city":"Salisbury",
    "sg:classifiers":[
        {
            "category":"Bars & Pubs",
            "type":"Food & Drink"
        }
    ],
    "sg:phone":"+44 1722 714658",
    "sg:postcode":"SP3 5LF",
    "sg:province":"Wiltshire",
    "sg:tags":[
        "pubs",
        "inn"
    ],
    "wof:name":"Poplar Inn",
    "wof:placetype":"venue"
},
  "geometry": {"coordinates":[-2.0066099167,51.061756134],"type":"Point"}
}