{
  "type": "Feature",
  "properties": {
    "addr:full":"1 Luard Court Havant Hampshire PO9 2TN",
    "addr:housenumber":"1",
    "addr:postcode":"po9 2tn",
    "addr:street":"Luard Court",
    "iso:country":"GB",
    "sg:address":"1 Luard Court",
    "sg:city":"Havant",
    "sg:classifiers":[
        {
            "category":"Real Estate",
            "subcategory":"Real Estate Services",
            "type":"Services"
        },
        {
            "category":"Retail",
            "subcategory":"Repair Shop",
            "type":"Services"
        }
    ],
    "sg:phone":"+44 23 9247 4465",
    "sg:postcode":"PO9 2TN",
    "sg:province":"Hampshire",
    "sg:tags":[
        "property",
        "maintenance"
    ],
    "wof:name":"Darren Sweatman",
    "wof:placetype":"venue"
},
  "geometry": {"coordinates":[-0.9683579803,50.8493003845],"type":"Point"}
}