{
  "type": "Feature",
  "properties": {
    "addr:full":"Vincents Road, Bumpers Farm Industrial Estate Chippenham Gloucestershire SN14 6NQ",
    "addr:housenumber":"industrial",
    "addr:postcode":"sn14 6nq",
    "addr:street":"Vincents Road Bumpers;Estate",
    "iso:country":"GB",
    "sg:address":"Vincents Road, Bumpers Farm Industrial Estate",
    "sg:city":"Chippenham",
    "sg:classifiers":[
        {
            "category":"Military Area",
            "subcategory":"Air Force Base",
            "type":"Public Place"
        }
    ],
    "sg:phone":"+44 1249 461744",
    "sg:postcode":"SN14 6NQ",
    "sg:province":"Gloucestershire",
    "sg:tags":[
        "water",
        "treatment"
    ],
    "wof:name":"Brocol Consultants Ltd.",
    "wof:placetype":"venue"
},
  "geometry": {"coordinates":[-2.143969,51.464214],"type":"Point"}
}