{
  "type": "Feature",
  "properties": {
    "addr:full":"11 Plains Road, Mapperley Nottingham Nottinghamshire NG3 5JH",
    "addr:housenumber":"11",
    "addr:postcode":"ng3 5jh",
    "addr:street":"Plains Road",
    "iso:country":"GB",
    "sg:address":"11 Plains Road, Mapperley",
    "sg:city":"Nottingham",
    "sg:classifiers":[
        {
            "category":"Food & Beverages",
            "subcategory":"Specialty",
            "type":"Retail Goods"
        }
    ],
    "sg:postcode":"NG3 5JH",
    "sg:province":"Nottinghamshire",
    "sg:tags":[
        "product",
        "health"
    ],
    "wof:name":"Health Wise",
    "wof:placetype":"venue"
},
  "geometry": {"coordinates":[-1.122058,52.984138],"type":"Point"}
}