{
  "type": "Feature",
  "properties": {
    "addr:full":"169 Stamford Street Ashton-under-lyne Greater Manchester OL6 7PS",
    "addr:housenumber":"169",
    "addr:postcode":"ol6 7ps",
    "addr:street":"Stamford Street",
    "iso:country":"GB",
    "sg:address":"169 Stamford Street",
    "sg:city":"Ashton-under-lyne",
    "sg:classifiers":[
        {
            "category":"Home & Garden",
            "subcategory":"Home Furnishings",
            "type":"Retail Goods"
        }
    ],
    "sg:phone":"+44 161 330 3022",
    "sg:postcode":"OL6 7PS",
    "sg:province":"Greater Manchester",
    "sg:tags":[
        "blind",
        "curtain",
        "fitting"
    ],
    "wof:name":"R D Corlett & Co. Ltd.",
    "wof:placetype":"venue"
},
  "geometry": {"coordinates":[-2.0994091034,53.4853401184],"type":"Point"}
}