{
  "type": "Feature",
  "properties": {
    "iso:country":"GB",
    "sg:address":"178a Wakefords Way",
    "sg:city":"Havant",
    "sg:classifiers":[
        {
            "category":"Bars & Pubs",
            "type":"Food & Drink"
        }
    ],
    "sg:postcode":"PO9 5QB",
    "sg:province":"Hampshire",
    "sg:tags":[
        "pubs",
        "inn"
    ],
    "wof:name":"Cobden Arms Ltd",
    "wof:placetype":"venue"
},
  "geometry": {"coordinates":[-0.965417,50.868412],"type":"Point"}
}