{
  "type": "Feature",
  "properties": {
    "iso:country":"GB",
    "sg:address":"12 Chichester Close, Peel Common",
    "sg:city":"Gosport",
    "sg:classifiers":[
        {
            "category":"Retail",
            "subcategory":"Driving School",
            "type":"Services"
        }
    ],
    "sg:phone":"+44 1329 282587",
    "sg:postcode":"PO13 0QH",
    "sg:province":"Hampshire",
    "wof:name":"Alpha School of Motoring",
    "wof:placetype":"venue"
},
  "geometry": {"coordinates":[-1.183335,50.82058],"type":"Point"}
}