{
  "type": "Feature",
  "properties": {
    "addr:full":"53 Diamond Avenue, Kirkby In Ashfield Nottingham Nottinghamshire NG17 7LP",
    "addr:housenumber":"53",
    "addr:postcode":"ng17 7lp",
    "addr:street":"Diamond Avenue;In Ashfield",
    "iso:country":"GB",
    "sg:address":"53 Diamond Avenue, Kirkby In Ashfield",
    "sg:city":"Nottingham",
    "sg:classifiers":[
        {
            "category":"Cinema",
            "subcategory":"Movie Rental",
            "type":"Entertainment"
        },
        {
            "category":"Home & Garden",
            "subcategory":"Building Materials",
            "type":"Retail Goods"
        }
    ],
    "sg:postcode":"NG17 7LP",
    "sg:province":"Nottinghamshire",
    "sg:tags":[
        "video",
        "polythene",
        "library",
        "plastic"
    ],
    "wof:name":"A Taylor",
    "wof:placetype":"venue"
},
  "geometry": {"coordinates":[-1.2392339706,53.0979919434],"type":"Point"}
}