{
  "type": "Feature",
  "properties": {
    "iso:country":"GB",
    "sg:address":"39 Bank Street",
    "sg:city":"Carlisle",
    "sg:classifiers":[
        {
            "category":"Shopping",
            "subcategory":"Jewelry",
            "type":"Retail Goods"
        },
        {
            "category":"Shopping",
            "subcategory":"Comic Books",
            "type":"Retail Goods"
        }
    ],
    "sg:phone":"+44 1228 544459",
    "sg:postcode":"CA3 8HJ",
    "sg:province":"Cumbria",
    "sg:tags":[
        "jeweller",
        "sale",
        "jewellery"
    ],
    "wof:name":"St.Nicholas Galleries Ltd.",
    "wof:placetype":"venue"
},
  "geometry": {"coordinates":[-2.934016,54.894024],"type":"Point"}
}