{
  "type": "Feature",
  "properties": {
    "addr:full":"Sawbridge Grounds, Sawbridge Rugby Northamptonshire CV23 8BB",
    "addr:postcode":"cv23 8bb",
    "iso:country":"GB",
    "sg:address":"Sawbridge Grounds, Sawbridge",
    "sg:city":"Rugby",
    "sg:classifiers":[
        {
            "category":"Farming",
            "subcategory":"Livestock Farm",
            "type":"Manufacturing & Wholesale Goods"
        }
    ],
    "sg:phone":"+44 1788 890632",
    "sg:postcode":"CV23 8BB",
    "sg:province":"Northamptonshire",
    "sg:tags":[
        "others"
    ],
    "wof:name":"I F BLELOCH",
    "wof:placetype":"venue"
},
  "geometry": {"coordinates":[-1.263482,52.289646],"type":"Point"}
}