{
  "type": "Feature",
  "properties": {
    "iso:country":"GB",
    "sg:address":"36 New John St West, Newtown",
    "sg:city":"Birmingham",
    "sg:classifiers":[
        {
            "category":"Shopping",
            "subcategory":"Clothing, Apparel, & Fashions",
            "type":"Retail Goods"
        }
    ],
    "sg:phone":"+44 121 359 6674",
    "sg:postcode":"B19 3NB",
    "sg:province":"West Midlands",
    "sg:tags":[
        "clothing"
    ],
    "wof:name":"R K Fabrics",
    "wof:placetype":"venue"
},
  "geometry": {"coordinates":[-1.8978300095,52.4924125671],"type":"Point"}
}