{
  "type": "Feature",
  "properties": {
    "iso:country":"GB",
    "sg:address":"12 Elgin Crescent",
    "sg:city":"London",
    "sg:classifiers":[
        {
            "category":"Shopping",
            "subcategory":"News",
            "type":"Retail Goods"
        }
    ],
    "sg:phone":"+44 20 7727 5209",
    "sg:postcode":"W11 2HX",
    "sg:province":"Greater London",
    "sg:tags":[
        "newsagent"
    ],
    "wof:name":"Rococo",
    "wof:placetype":"venue"
},
  "geometry": {"coordinates":[-0.205223,51.515106],"type":"Point"}
}