{
  "type": "Feature",
  "properties": {
    "addr:full":"79 Grainger St, Newcastle Newcastle Upon Tyne Tyne and Wear NE1 5JF",
    "addr:housenumber":"79",
    "addr:postcode":"ne1 5jf",
    "addr:street":"Grainger St",
    "iso:country":"GB",
    "sg:address":"79 Grainger St, Newcastle",
    "sg:city":"Newcastle Upon Tyne",
    "sg:classifiers":[
        {
            "category":"Travel",
            "subcategory":"Travel Agent",
            "type":"Entertainment"
        }
    ],
    "sg:phone":"+44 191 232 5809",
    "sg:postcode":"NE1 5JF",
    "sg:province":"Tyne and Wear",
    "wof:name":"Worldchoice Carlson",
    "wof:placetype":"venue"
},
  "geometry": {"coordinates":[-1.6150490046,54.9715385437],"type":"Point"}
}