{
  "type": "Feature",
  "properties": {
    "iso:country":"GB",
    "sg:address":"6 Gordon Row",
    "sg:city":"Weymouth",
    "sg:classifiers":[
        {
            "category":"Food & Beverages",
            "subcategory":"Fruits & Vegetables",
            "type":"Retail Goods"
        }
    ],
    "sg:phone":"+44 1305 787975",
    "sg:postcode":"DT4 8LL",
    "sg:province":"Dorset",
    "sg:tags":[
        "greengrocer"
    ],
    "wof:name":"Alex & Pauline Claire",
    "wof:placetype":"venue"
},
  "geometry": {"coordinates":[-2.4568939209,50.6054840088],"type":"Point"}
}