{
  "type": "Feature",
  "properties": {
    "addr:full":"Suite 1 & 3, Keyne House Derby Derbyshire DE21 4AS",
    "addr:housenumber":"suite 1 & 3 keyne house",
    "addr:postcode":"de21 4as",
    "iso:country":"GB",
    "sg:address":"Suite 1 & 3, Keyne House",
    "sg:city":"Derby",
    "sg:classifiers":[
        {
            "category":"Building & Trades",
            "subcategory":"Cleaning & Sanitation",
            "type":"Services"
        }
    ],
    "sg:phone":"+44 1332 299222",
    "sg:postcode":"DE21 4AS",
    "sg:province":"Derbyshire",
    "sg:tags":[
        "dry",
        "control",
        "damp",
        "rot"
    ],
    "wof:name":"Terminix Peter Cox",
    "wof:placetype":"venue"
},
  "geometry": {"coordinates":[-1.47088,52.934811],"type":"Point"}
}