{
  "type": "Feature",
  "properties": {
    "addr:full":"13 High Street Sheerness Kent ME12 1NY",
    "addr:housenumber":"13",
    "addr:postcode":"me12 1ny",
    "addr:street":"High Street",
    "iso:country":"GB",
    "sg:address":"13 High Street",
    "sg:city":"Sheerness",
    "sg:classifiers":[
        {
            "category":"Cafe",
            "type":"Food & Drink"
        }
    ],
    "sg:phone":"+44 1795 662487",
    "sg:postcode":"ME12 1NY",
    "sg:province":"Kent",
    "sg:tags":[
        "tea",
        "room"
    ],
    "wof:name":"Neptune",
    "wof:placetype":"venue"
},
  "geometry": {"coordinates":[0.75939,51.440872],"type":"Point"}
}