{
  "type": "Feature",
  "properties": {
    "iso:country":"GB",
    "sg:address":"Springfield Farm, Morwenstow",
    "sg:city":"Bude",
    "sg:classifiers":[
        {
            "category":"Home & Garden",
            "subcategory":"Garden Supply",
            "type":"Retail Goods"
        },
        {
            "category":"Farming",
            "subcategory":"Farm",
            "type":"Manufacturing & Wholesale Goods"
        }
    ],
    "sg:postcode":"EX23 9SR",
    "sg:province":"Cornwall",
    "sg:tags":[
        "mixed",
        "bulb",
        "crop",
        "grower"
    ],
    "wof:name":"Edward J Moore",
    "wof:placetype":"venue"
},
  "geometry": {"coordinates":[-4.553809,50.908798],"type":"Point"}
}