{
  "type": "Feature",
  "properties": {
    "iso:country":"GB",
    "sg:address":"Sunnymead, Brecks Lane, Huntington",
    "sg:city":"York",
    "sg:classifiers":[
        {
            "category":"Shopping",
            "subcategory":"Computers & Home Electronics",
            "type":"Retail Goods"
        }
    ],
    "sg:phone":"+44 1904 768678",
    "sg:postcode":"YO32 9NP",
    "sg:province":"North Yorkshire",
    "wof:name":"Automatic Services Ltd",
    "wof:placetype":"venue"
},
  "geometry": {"coordinates":[-1.068378,53.988235],"type":"Point"}
}