{
  "type": "Feature",
  "properties": {
    "addr:full":"57 Leigh Road Worthing West Sussex BN14 9HG",
    "addr:housenumber":"57",
    "addr:postcode":"bn14 9hg",
    "addr:street":"Leigh Road",
    "iso:country":"GB",
    "sg:address":"57 Leigh Road",
    "sg:city":"Worthing",
    "sg:classifiers":[
        {
            "category":"Building & Trades",
            "subcategory":"Construction",
            "type":"Services"
        }
    ],
    "sg:phone":"+44 1903 232095",
    "sg:postcode":"BN14 9HG",
    "sg:province":"West Sussex",
    "sg:tags":[
        "glazier"
    ],
    "wof:name":"John E A Hope",
    "wof:placetype":"venue"
},
  "geometry": {"coordinates":[-0.3681289852,50.8308601379],"type":"Point"}
}