{
  "type": "Feature",
  "properties": {
    "iso:country":"GB",
    "sg:address":"Wentworth Business Park, Maple Road, Tankersley",
    "sg:city":"Barnsley",
    "sg:classifiers":[
        {
            "category":"Professional",
            "subcategory":"Computer Services",
            "type":"Services"
        }
    ],
    "sg:phone":"+44 1226 749994",
    "sg:postcode":"S75 3DL",
    "sg:province":"South Yorkshire",
    "sg:tags":[
        "system",
        "software"
    ],
    "wof:name":"Axxia Systems Ltd.",
    "wof:placetype":"venue"
},
  "geometry": {"coordinates":[-1.482897,53.495152],"type":"Point"}
}