{
  "type": "Feature",
  "properties": {
    "addr:full":"54 Sovereign Arc, Kingsway Centre Newport East Riding of Yorkshire NP9 1ED",
    "addr:housenumber":"54",
    "addr:postcode":"np9 1ed",
    "addr:street":"Sovereign Arc Kingsway",
    "iso:country":"GB",
    "sg:address":"54 Sovereign Arc, Kingsway Centre",
    "sg:city":"Newport",
    "sg:classifiers":[
        {
            "category":"Shopping",
            "subcategory":"Pharmacy",
            "type":"Retail Goods"
        }
    ],
    "sg:phone":"+44 1633 265200",
    "sg:postcode":"NP9 1ED",
    "sg:province":"East Riding of Yorkshire",
    "sg:tags":[
        "store",
        "drug"
    ],
    "wof:name":"Lloyds Health & Beauty",
    "wof:placetype":"venue"
},
  "geometry": {"coordinates":[-2.9944980145,51.5888137817],"type":"Point"}
}