{
  "type": "Feature",
  "properties": {
    "iso:country":"GB",
    "sg:address":"Grove House, 551 London Road",
    "sg:city":"Isleworth",
    "sg:classifiers":[
        {
            "category":"Home & Garden",
            "subcategory":"Hardware",
            "type":"Retail Goods"
        }
    ],
    "sg:phone":"+44 20 8847 2227",
    "sg:postcode":"TW7 4EE",
    "sg:province":"Greater London",
    "sg:tags":[
        "sealant",
        "glue",
        "adhesives"
    ],
    "wof:name":"Uhu (U K) Ltd.",
    "wof:placetype":"venue"
},
  "geometry": {"coordinates":[-0.342259,51.474819],"type":"Point"}
}