{
  "type": "Feature",
  "properties": {
    "iso:country":"GB",
    "sg:address":"7-73a New Road, Rubery, Rednal",
    "sg:city":"Birmingham",
    "sg:classifiers":[
        {
            "category":"Retail",
            "subcategory":"Car Wash",
            "type":"Services"
        },
        {
            "category":"Retail",
            "subcategory":"Auto Repair",
            "type":"Services"
        }
    ],
    "sg:phone":"+44 121 453 8783",
    "sg:postcode":"B45 9JT",
    "sg:province":"West Midlands",
    "sg:tags":[
        "upholsterer",
        "trimmer"
    ],
    "wof:name":"J M Grant",
    "wof:placetype":"venue"
},
  "geometry": {"coordinates":[-2.0242390633,52.3918495178],"type":"Point"}
}