{
  "type": "Feature",
  "properties": {
    "addr:full":"Maybury Hill Woking Surrey GU22 8AE",
    "addr:postcode":"gu22 8ae",
    "addr:street":"Maybury Hill",
    "iso:country":"GB",
    "sg:address":"Maybury Hill",
    "sg:city":"Woking",
    "sg:classifiers":[
        {
            "category":"Health Services",
            "subcategory":"Nursing And Care Facility",
            "type":"Services"
        }
    ],
    "sg:phone":"+44 1483 761137",
    "sg:postcode":"GU22 8AE",
    "sg:province":"Surrey",
    "sg:tags":[
        "home"
    ],
    "wof:name":"St.Peter's Convent",
    "wof:placetype":"venue"
},
  "geometry": {"coordinates":[-0.5417339802,51.3240814209],"type":"Point"}
}