{
  "type": "Feature",
  "properties": {
    "addr:full":"Homer Road Solihull West Midlands B91 3BN",
    "addr:postcode":"b91 3bn",
    "addr:street":"Homer Road",
    "iso:country":"GB",
    "sg:address":"Homer Road",
    "sg:city":"Solihull",
    "sg:classifiers":[
        {
            "category":"Professional",
            "subcategory":"Employment Agencies",
            "type":"Services"
        }
    ],
    "sg:postcode":"B91 3BN",
    "sg:province":"West Midlands",
    "sg:tags":[
        "career",
        "guidance"
    ],
    "wof:name":"Connexions",
    "wof:placetype":"venue"
},
  "geometry": {"coordinates":[-1.784984,52.414017],"type":"Point"}
}