{
  "type": "Feature",
  "properties": {
    "iso:country":"GB",
    "sg:address":"26 Hoghton Street",
    "sg:city":"Southport",
    "sg:classifiers":[
        {
            "category":"Retail",
            "subcategory":"Event Space",
            "type":"Services"
        }
    ],
    "sg:phone":"+44 1704 501908",
    "sg:postcode":"PR9 0PA",
    "sg:province":"Lancashire",
    "sg:tags":[
        "function",
        "room"
    ],
    "wof:name":"Nolan Brothers Ltd.",
    "wof:placetype":"venue"
},
  "geometry": {"coordinates":[-3.000809,53.648582],"type":"Point"}
}