{
  "type": "Feature",
  "properties": {
    "iso:country":"GB",
    "sg:address":"Enquiries, Cambria Surgery, Aculta Av",
    "sg:city":"Holyhead",
    "sg:classifiers":[
        {
            "category":"Health Services",
            "subcategory":"Doctor",
            "type":"Services"
        }
    ],
    "sg:phone":"+44 1407 762735",
    "sg:postcode":"LL65 1RA",
    "sg:province":"Isle of Anglesey",
    "sg:tags":[
        "practitioners"
    ],
    "wof:name":"O'Toole, J",
    "wof:placetype":"venue"
},
  "geometry": {"coordinates":[-4.6307139397,53.3063697815],"type":"Point"}
}