{
  "type": "Feature",
  "properties": {
    "addr:full":"Nelson House, Nelson Road Salisbury Wiltshire SP1 3LT",
    "addr:postcode":"sp1 3lt",
    "addr:street":"Nelson Road",
    "iso:country":"GB",
    "sg:address":"Nelson House, Nelson Road",
    "sg:city":"Salisbury",
    "sg:classifiers":[
        {
            "category":"Home & Garden",
            "subcategory":"Home Furnishings",
            "type":"Retail Goods"
        }
    ],
    "sg:phone":"+44 1722 413987",
    "sg:postcode":"SP1 3LT",
    "sg:province":"Wiltshire",
    "sg:tags":[
        "furnishers",
        "planner",
        "kitchen"
    ],
    "wof:name":"Keith Sutcliffe",
    "wof:placetype":"venue"
},
  "geometry": {"coordinates":[-1.797388,51.07552],"type":"Point"}
}