{
  "type": "Feature",
  "properties": {
    "addr:full":"7 Floral St Holborn Greater London WC2E 9DH",
    "addr:housenumber":"7",
    "addr:postcode":"wc2e 9dh",
    "addr:street":"Floral St",
    "iso:country":"GB",
    "sg:address":"7 Floral St",
    "sg:city":"Holborn",
    "sg:classifiers":[
        {
            "category":"Communications",
            "subcategory":"News Services",
            "type":"Services"
        }
    ],
    "sg:phone":"+44 20 7497 0857",
    "sg:postcode":"WC2E 9DH",
    "sg:province":"Greater London",
    "sg:tags":[
        "photo",
        "agency"
    ],
    "wof:name":"Image Transfer UK Ltd",
    "wof:placetype":"venue"
},
  "geometry": {"coordinates":[-0.1237780005,51.5126724243],"type":"Point"}
}