{
  "type": "Feature",
  "properties": {
    "addr:full":"Gallowsclough Road Stalybridge Greater Manchester SK15 3QS",
    "addr:postcode":"sk15 3qs",
    "addr:street":"Gallowsclough Road",
    "iso:country":"GB",
    "sg:address":"Gallowsclough Road",
    "sg:city":"Stalybridge",
    "sg:classifiers":[
        {
            "category":"Farming",
            "subcategory":"Livestock Farm",
            "type":"Manufacturing & Wholesale Goods"
        }
    ],
    "sg:phone":"+44 1457 763509",
    "sg:postcode":"SK15 3QS",
    "sg:province":"Greater Manchester",
    "sg:tags":[
        "others"
    ],
    "wof:name":"J Thompson",
    "wof:placetype":"venue"
},
  "geometry": {"coordinates":[-2.025033,53.467567],"type":"Point"}
}