{
  "type": "Feature",
  "properties": {
    "iso:country":"GB",
    "sg:address":"Hatton House, Church Lane, Cheshunt",
    "sg:city":"Waltham Cross",
    "sg:classifiers":[
        {
            "category":"Communications",
            "subcategory":"Film & Video Production",
            "type":"Services"
        }
    ],
    "sg:phone":"+44 1992 630507",
    "sg:postcode":"EN8 0DW",
    "sg:province":"Essex",
    "sg:tags":[
        "illustrator",
        "artist"
    ],
    "wof:name":"Ian West Cartoons",
    "wof:placetype":"venue"
},
  "geometry": {"coordinates":[-0.046281,51.709084],"type":"Point"}
}