{
  "type": "Feature",
  "properties": {
    "iso:country":"GB",
    "sg:address":"114 Muswell Hill Broadway",
    "sg:city":"Muswell Hill",
    "sg:classifiers":[
        {
            "category":"Coffee & Tea",
            "type":"Food & Drink"
        }
    ],
    "sg:phone":"+44 20 8883 8559",
    "sg:postcode":"N10 3RU",
    "sg:province":"Greater London",
    "wof:name":"Seattle Coffee Co",
    "wof:placetype":"venue"
},
  "geometry": {"coordinates":[-0.143661,51.590195],"type":"Point"}
}