{
  "type": "Feature",
  "properties": {
    "addr:full":"30 Philips Park Road Manchester Greater Manchester M11 3FX",
    "addr:housenumber":"30",
    "addr:postcode":"m11 3fx",
    "addr:street":"Philips Park Road",
    "iso:country":"GB",
    "sg:address":"30 Philips Park Road",
    "sg:city":"Manchester",
    "sg:classifiers":[
        {
            "category":"Manufacturing",
            "subcategory":"Textiles",
            "type":"Manufacturing & Wholesale Goods"
        }
    ],
    "sg:phone":"+44 161 273 4744",
    "sg:postcode":"M11 3FX",
    "sg:province":"Greater Manchester",
    "sg:tags":[
        "merchant",
        "agent"
    ],
    "wof:name":"Glen Fabrics Ltd.",
    "wof:placetype":"venue"
},
  "geometry": {"coordinates":[-2.2071070671,53.4834403992],"type":"Point"}
}