{
  "type": "Feature",
  "properties": {
    "addr:full":"52 Glendale Avenue Edgware Greater London HA8 8HH",
    "addr:housenumber":"52",
    "addr:postcode":"ha8 8hh",
    "addr:street":"Glendale Avenue",
    "iso:country":"GB",
    "sg:address":"52 Glendale Avenue",
    "sg:city":"Edgware",
    "sg:classifiers":[
        {
            "category":"Home & Garden",
            "subcategory":"Building Materials",
            "type":"Retail Goods"
        }
    ],
    "sg:phone":"+44 20 8958 1285",
    "sg:postcode":"HA8 8HH",
    "sg:province":"Greater London",
    "sg:tags":[
        "polythene",
        "plastic"
    ],
    "wof:name":"Aruna Jeswani",
    "wof:placetype":"venue"
},
  "geometry": {"coordinates":[-0.282348007,51.6217575073],"type":"Point"}
}