{
  "type": "Feature",
  "properties": {
    "iso:country":"GB",
    "sg:address":"28 Mawney Road",
    "sg:city":"Romford",
    "sg:classifiers":[
        {
            "category":"Organizations",
            "subcategory":"Membership Organization",
            "type":"Services"
        }
    ],
    "sg:phone":"+44 1708 740378",
    "sg:postcode":"RM7 7HB",
    "sg:province":"Essex",
    "sg:tags":[
        "club"
    ],
    "wof:name":"Romford United Services Club Ltd.",
    "wof:placetype":"venue"
},
  "geometry": {"coordinates":[0.176771,51.57832],"type":"Point"}
}