{
  "type": "Feature",
  "properties": {
    "addr:full":"Unit 6 Archway Business Centre, Wedmore St London Greater London N19 4RU",
    "addr:housenumber":"unit 6 archway business centre",
    "addr:postcode":"n19 4ru",
    "addr:street":"St",
    "iso:country":"GB",
    "sg:address":"Unit 6 Archway Business Centre, Wedmore St",
    "sg:city":"London",
    "sg:classifiers":[
        {
            "category":"Professional",
            "subcategory":"Research",
            "type":"Services"
        }
    ],
    "sg:postcode":"N19 4RU",
    "sg:province":"Greater London",
    "sg:tags":[
        "market"
    ],
    "wof:name":"Market Tracking International Ltd",
    "wof:placetype":"venue"
},
  "geometry": {"coordinates":[-0.1274980009,51.5608291626],"type":"Point"}
}