{
  "type": "Feature",
  "properties": {
    "addr:full":"Workhouse Loke Mundesley Rd North Walsham Norfolk NR28 0DA",
    "addr:postcode":"nr28 0da",
    "addr:street":"Workhouse Loke Mundesley Rd",
    "iso:country":"GB",
    "sg:address":"Workhouse Loke Mundesley Rd",
    "sg:city":"North Walsham",
    "sg:classifiers":[
        {
            "category":"Utilities",
            "subcategory":"Electric",
            "type":"Services"
        }
    ],
    "sg:phone":"+44 1692 409907",
    "sg:postcode":"NR28 0DA",
    "sg:province":"Norfolk",
    "sg:tags":[
        "electrical",
        "contractor"
    ],
    "wof:name":"Pro-pat",
    "wof:placetype":"venue"
},
  "geometry": {"coordinates":[1.3896750212,52.8272895813],"type":"Point"}
}