{
  "type": "Feature",
  "properties": {
    "iso:country":"GB",
    "sg:address":"14 Hill Avenue",
    "sg:city":"Amersham",
    "sg:classifiers":[
        {
            "category":"Home & Garden",
            "subcategory":"Home Furnishings",
            "type":"Retail Goods"
        },
        {
            "category":"Building & Trades",
            "subcategory":"Construction",
            "type":"Services"
        },
        {
            "category":"Home & Garden",
            "subcategory":"Furniture",
            "type":"Retail Goods"
        }
    ],
    "sg:phone":"+44 1494 434200",
    "sg:postcode":"HP6 5BW",
    "sg:province":"Buckinghamshire",
    "sg:tags":[
        "planner",
        "installers",
        "built-in",
        "furnishers",
        "fitted",
        "kitchen"
    ],
    "sg:website":"http://www.cotteswood.co.uk",
    "wof:name":"Cotteswood Traditional Kitchens",
    "wof:placetype":"venue"
},
  "geometry": {"coordinates":[-0.607834,51.67564],"type":"Point"}
}