{
  "type": "Feature",
  "properties": {
    "addr:full":"Sheepscar House, Sheepscar Street South Leeds West Yorkshire LS7 1AD",
    "addr:postcode":"ls7 1ad",
    "addr:street":"Sheepscar Street South Leeds West",
    "iso:country":"GB",
    "sg:address":"Sheepscar House, Sheepscar Street South",
    "sg:city":"Leeds",
    "sg:classifiers":[
        {
            "category":"Retail",
            "subcategory":"Auto Rental",
            "type":"Services"
        }
    ],
    "sg:phone":"+44 113 245 5959",
    "sg:postcode":"LS7 1AD",
    "sg:province":"West Yorkshire",
    "sg:tags":[
        "car",
        "vehicle"
    ],
    "sg:website":"http://www.enterprise.co.uk",
    "wof:name":"Enterprise Rent-A-Car U K Ltd",
    "wof:placetype":"venue"
},
  "geometry": {"coordinates":[-1.538803,53.812931],"type":"Point"}
}