{
  "type": "Feature",
  "properties": {
    "addr:full":"32 Stone Street Llandovery Carmarthenshire SA20 0JP",
    "addr:housenumber":"32",
    "addr:postcode":"sa20 0jp",
    "addr:street":"Stone Street",
    "iso:country":"GB",
    "sg:address":"32 Stone Street",
    "sg:city":"Llandovery",
    "sg:classifiers":[
        {
            "category":"Bars & Pubs",
            "type":"Food & Drink"
        }
    ],
    "sg:phone":"+44 1550 720576",
    "sg:postcode":"SA20 0JP",
    "sg:province":"Carmarthenshire",
    "sg:tags":[
        "pubs",
        "inn"
    ],
    "wof:name":"The Plough Hotel",
    "wof:placetype":"venue"
},
  "geometry": {"coordinates":[-3.797004,51.995537],"type":"Point"}
}