{
  "type": "Feature",
  "properties": {
    "addr:full":"2nd Southern House, Station Approach Woking Surrey GU22 7UY",
    "addr:postcode":"gu22 7uy",
    "addr:street":"Station Approach",
    "iso:country":"GB",
    "sg:address":"2nd Southern House, Station Approach",
    "sg:city":"Woking",
    "sg:classifiers":[
        {
            "category":"Organizations",
            "subcategory":"Membership Organization",
            "type":"Services"
        }
    ],
    "sg:postcode":"GU22 7UY",
    "sg:province":"Surrey",
    "sg:tags":[
        "club"
    ],
    "wof:name":"The Uk Reprographic Association",
    "wof:placetype":"venue"
},
  "geometry": {"coordinates":[-0.55961,51.316021],"type":"Point"}
}