{
  "type": "Feature",
  "properties": {
    "iso:country":"GB",
    "sg:address":"3 Wratting Road",
    "sg:city":"Haverhill",
    "sg:classifiers":[
        {
            "category":"Health Services",
            "subcategory":"Dentist",
            "type":"Services"
        }
    ],
    "sg:phone":"+44 1440 702527",
    "sg:postcode":"CB9 0DA",
    "sg:province":"Essex",
    "wof:name":"LLOYD QUAN",
    "wof:placetype":"venue"
},
  "geometry": {"coordinates":[0.4368070066,52.085018158],"type":"Point"}
}