{
  "type": "Feature",
  "properties": {
    "addr:full":"Mill House Works, Columbia Avenue Edgware Greater London HA8 5DQ",
    "addr:postcode":"ha8 5dq",
    "addr:street":"Columbia Avenue",
    "iso:country":"GB",
    "sg:address":"Mill House Works, Columbia Avenue",
    "sg:city":"Edgware",
    "sg:classifiers":[
        {
            "category":"Manufacturing",
            "subcategory":"Building Materials",
            "type":"Manufacturing & Wholesale Goods"
        }
    ],
    "sg:phone":"+44 20 8951 4177",
    "sg:postcode":"HA8 5DQ",
    "sg:province":"Greater London",
    "sg:tags":[
        "extrusion"
    ],
    "wof:name":"Rustin Allen Ltd.",
    "wof:placetype":"venue"
},
  "geometry": {"coordinates":[-0.272644,51.604115],"type":"Point"}
}