{
  "type": "Feature",
  "properties": {
    "iso:country":"GB",
    "sg:address":"3 Barth Close, Great Oakley",
    "sg:city":"Corby",
    "sg:classifiers":[
        {
            "category":"Shopping",
            "subcategory":"Pharmacy",
            "type":"Retail Goods"
        }
    ],
    "sg:phone":"+44 1536 745791",
    "sg:postcode":"NN18 8LU",
    "sg:province":"Northamptonshire",
    "sg:tags":[
        "pharmacist",
        "chemist"
    ],
    "wof:name":"National Co-Operative Chemists",
    "wof:placetype":"venue"
},
  "geometry": {"coordinates":[-0.7214589715,52.4701042175],"type":"Point"}
}