{
  "type": "Feature",
  "properties": {
    "addr:full":"Duchra Farm, Lochans Stranraer Dumfries and Galloway DG9 9AZ",
    "addr:postcode":"dg9 9az",
    "iso:country":"GB",
    "sg:address":"Duchra Farm, Lochans",
    "sg:city":"Stranraer",
    "sg:classifiers":[
        {
            "category":"Farming",
            "subcategory":"Livestock Farm",
            "type":"Manufacturing & Wholesale Goods"
        }
    ],
    "sg:phone":"+44 1776 820219",
    "sg:postcode":"DG9 9AZ",
    "sg:province":"Dumfries and Galloway",
    "sg:tags":[
        "others"
    ],
    "wof:name":"W Mcharrie",
    "wof:placetype":"venue"
},
  "geometry": {"coordinates":[-5.013074,54.868404],"type":"Point"}
}