{
  "type": "Feature",
  "properties": {
    "addr:full":"North Farm, Buckland Ripers Weymouth Dorset DT3 4BU",
    "addr:postcode":"dt3 4bu",
    "addr:street":"North;Buckland Ripers",
    "iso:country":"GB",
    "sg:address":"North Farm, Buckland Ripers",
    "sg:city":"Weymouth",
    "sg:classifiers":[
        {
            "category":"Farming",
            "subcategory":"Livestock Farm",
            "type":"Manufacturing & Wholesale Goods"
        }
    ],
    "sg:phone":"+44 1305 813322",
    "sg:postcode":"DT3 4BU",
    "sg:province":"Dorset",
    "sg:tags":[
        "others"
    ],
    "wof:name":"T J Swaffield",
    "wof:placetype":"venue"
},
  "geometry": {"coordinates":[-2.4953210354,50.6416778564],"type":"Point"}
}