{
  "type": "Feature",
  "properties": {
    "addr:full":"First Floor, 17 Hill St London Greater London W1J 5LJ",
    "addr:housenumber":"17",
    "addr:postcode":"w1j 5lj",
    "addr:street":"Hill St",
    "iso:country":"GB",
    "sg:address":"First Floor, 17 Hill St",
    "sg:city":"London",
    "sg:classifiers":[
        {
            "category":"Manufacturing",
            "subcategory":"Paper Products",
            "type":"Manufacturing & Wholesale Goods"
        }
    ],
    "sg:phone":"+44 20 7409 0424",
    "sg:postcode":"W1J 5LJ",
    "sg:province":"Greater London",
    "sg:tags":[
        "cardboard"
    ],
    "wof:name":"Mundet International",
    "wof:placetype":"venue"
},
  "geometry": {"coordinates":[-0.14799,51.508739],"type":"Point"}
}