{
  "type": "Feature",
  "properties": {
    "addr:full":"12 Oaklea Rd Wirral Merseyside CH61 3US",
    "addr:housenumber":"12",
    "addr:postcode":"ch61 3us",
    "addr:street":"Oaklea Rd",
    "iso:country":"GB",
    "sg:address":"12 Oaklea Rd",
    "sg:city":"Wirral",
    "sg:classifiers":[
        {
            "category":"Building & Trades",
            "subcategory":"Construction",
            "type":"Services"
        }
    ],
    "sg:phone":"+44 151 648 7632",
    "sg:postcode":"CH61 3US",
    "sg:province":"Merseyside",
    "sg:tags":[
        "builder"
    ],
    "wof:name":"Calico",
    "wof:placetype":"venue"
},
  "geometry": {"coordinates":[-3.102378,53.354832],"type":"Point"}
}