{
  "type": "Feature",
  "properties": {
    "addr:full":"7 Surrey Court, 55 Woodcote Road Wallington Surrey SM6 0PN",
    "addr:housenumber":"7;55",
    "addr:postcode":"sm6 0pn",
    "addr:street":"Surrey;Woodcote Road",
    "iso:country":"GB",
    "sg:address":"7 Surrey Court, 55 Woodcote Road",
    "sg:city":"Wallington",
    "sg:classifiers":[
        {
            "category":"Health Services",
            "subcategory":"Dentist",
            "type":"Services"
        }
    ],
    "sg:phone":"+44 20 8647 1081",
    "sg:postcode":"SM6 0PN",
    "sg:province":"Surrey",
    "wof:name":"J G F Roscoe & Associates",
    "wof:placetype":"venue"
},
  "geometry": {"coordinates":[-0.1498979926,51.3601226807],"type":"Point"}
}