{
  "type": "Feature",
  "properties": {
    "iso:country":"GB",
    "sg:address":"55-56 Bradmore Grn, Brookmans Park",
    "sg:city":"Hatfield",
    "sg:classifiers":[
        {
            "category":"Restaurant",
            "type":"Food & Drink"
        }
    ],
    "sg:phone":"+44 1707 662652",
    "sg:postcode":"AL9 7QS",
    "sg:province":"Hertfordshire",
    "sg:tags":[
        "indian"
    ],
    "wof:name":"Raj Tandoori",
    "wof:placetype":"venue"
},
  "geometry": {"coordinates":[-0.202057,51.721775],"type":"Point"}
}