{
  "type": "Feature",
  "properties": {
    "iso:country":"GB",
    "sg:address":"Appletree Gardens",
    "sg:city":"Whitley Bay",
    "sg:classifiers":[
        {
            "category":"Education",
            "subcategory":"School",
            "type":"Public Place"
        }
    ],
    "sg:phone":"+44 191 252 3546",
    "sg:postcode":"NE25 8XS",
    "sg:province":"Northumberland",
    "sg:tags":[
        "local",
        "authority"
    ],
    "wof:name":"Appletree Gardens First School",
    "wof:placetype":"venue"
},
  "geometry": {"coordinates":[-1.4627590179,55.0377731323],"type":"Point"}
}