{
  "type": "Feature",
  "properties": {
    "addr:full":"Suite 1 Trennick Ho, 114 Kenwyn St Truro Cornwall TR1 3DJ",
    "addr:housenumber":"suite 1;114",
    "addr:postcode":"tr1 3dj",
    "addr:street":"Trennick Ho;Kenwyn St",
    "iso:country":"GB",
    "sg:address":"Suite 1 Trennick Ho, 114 Kenwyn St",
    "sg:city":"Truro",
    "sg:classifiers":[
        {
            "category":"Manufacturing",
            "subcategory":"Tools & Machinery",
            "type":"Manufacturing & Wholesale Goods"
        }
    ],
    "sg:phone":"+44 1872 222848",
    "sg:postcode":"TR1 3DJ",
    "sg:province":"Cornwall",
    "sg:tags":[
        "society",
        "friendly"
    ],
    "wof:name":"Cunningham Hart",
    "wof:placetype":"venue"
},
  "geometry": {"coordinates":[-5.053631,50.26524],"type":"Point"}
}