{
  "type": "Feature",
  "properties": {
    "iso:country":"GB",
    "sg:address":"Pound Green, Guilden Morden",
    "sg:city":"Royston",
    "sg:classifiers":[
        {
            "category":"Education",
            "subcategory":"School",
            "type":"Public Place"
        }
    ],
    "sg:phone":"+44 1763 852318",
    "sg:postcode":"SG8 0JZ",
    "sg:province":"Bedfordshire",
    "sg:tags":[
        "local",
        "authority"
    ],
    "wof:name":"Guilden Morden Primary School",
    "wof:placetype":"venue"
},
  "geometry": {"coordinates":[-0.13353,52.082436],"type":"Point"}
}