{
  "type": "Feature",
  "properties": {
    "addr:full":"102 Westbury Street, Thornaby Stockton-on-tees Durham TS17 6NA",
    "addr:housenumber":"102",
    "addr:postcode":"ts17 6na",
    "addr:street":"Westbury Street",
    "iso:country":"GB",
    "sg:address":"102 Westbury Street, Thornaby",
    "sg:city":"Stockton-on-tees",
    "sg:classifiers":[
        {
            "category":"Home & Garden",
            "subcategory":"Hardware",
            "type":"Retail Goods"
        }
    ],
    "sg:phone":"+44 1642 676087",
    "sg:postcode":"TS17 6NA",
    "sg:province":"Durham",
    "sg:tags":[
        "retailer",
        "diy"
    ],
    "wof:name":"Bennett D I Y",
    "wof:placetype":"venue"
},
  "geometry": {"coordinates":[-1.2991440296,54.553401947],"type":"Point"}
}