{
  "type": "Feature",
  "properties": {
    "iso:country":"GB",
    "sg:address":"128 Sunbridge Road",
    "sg:city":"Bradford",
    "sg:classifiers":[
        {
            "category":"Professional",
            "subcategory":"Lawyer & Legal Services",
            "type":"Services"
        }
    ],
    "sg:postcode":"BD1 2AT",
    "sg:province":"West Yorkshire",
    "sg:tags":[
        "solicitor"
    ],
    "wof:name":"Last & Co.",
    "wof:placetype":"venue"
},
  "geometry": {"coordinates":[-1.760559,53.794689],"type":"Point"}
}