{
  "type": "Feature",
  "properties": {
    "addr:full":"69 Kingsway Cambridge Cambridgeshire CB4 2ER",
    "addr:housenumber":"69",
    "addr:postcode":"cb4 2er",
    "addr:street":"Kingsway",
    "iso:country":"GB",
    "sg:address":"69 Kingsway",
    "sg:city":"Cambridge",
    "sg:classifiers":[
        {
            "category":"Retail",
            "subcategory":"Driving School",
            "type":"Services"
        },
        {
            "category":"Education",
            "subcategory":"University",
            "type":"Public Place"
        }
    ],
    "sg:phone":"+44 1223 311763",
    "sg:postcode":"CB4 2ER",
    "sg:province":"Cambridgeshire",
    "sg:tags":[
        "higher"
    ],
    "wof:name":"1ST Gear Driver Training",
    "wof:placetype":"venue"
},
  "geometry": {"coordinates":[0.1361600012,52.2330818176],"type":"Point"}
}