{
  "type": "Feature",
  "properties": {
    "iso:country":"GB",
    "sg:address":"9 Helena Road",
    "sg:city":"Norwich",
    "sg:classifiers":[
        {
            "category":"Building & Trades",
            "subcategory":"Construction",
            "type":"Services"
        }
    ],
    "sg:postcode":"NR2 3BY",
    "sg:province":"Norfolk",
    "sg:tags":[
        "dry",
        "lining",
        "plasterers",
        "screeders"
    ],
    "wof:name":"Clarke & Sons",
    "wof:placetype":"venue"
},
  "geometry": {"coordinates":[1.27233,52.634232],"type":"Point"}
}