{
  "type": "Feature",
  "properties": {
    "iso:country":"GB",
    "sg:address":"116 Standishgate",
    "sg:city":"Wigan",
    "sg:classifiers":[
        {
            "category":"Taxi",
            "type":"Transportation"
        }
    ],
    "sg:phone":"+44 1942 700532",
    "sg:postcode":"WN1 1XP",
    "sg:province":"Lancashire",
    "sg:tags":[
        "mini",
        "cab"
    ],
    "wof:name":"Midas Cars",
    "wof:placetype":"venue"
},
  "geometry": {"coordinates":[-2.628738,53.550095],"type":"Point"}
}