{
  "type": "Feature",
  "properties": {
    "addr:full":"Hedingham Road, Gosfield Halstead Essex CO9 1PW",
    "addr:postcode":"co9 1pw",
    "addr:street":"Hedingham Road Gosfield",
    "iso:country":"GB",
    "sg:address":"Hedingham Road, Gosfield",
    "sg:city":"Halstead",
    "sg:classifiers":[
        {
            "category":"Autos & Motor Vehicles",
            "subcategory":"Fuel & Gas Station",
            "type":"Retail Goods"
        },
        {
            "category":"Utilities",
            "subcategory":"Fuel Oil & Lpg",
            "type":"Services"
        }
    ],
    "sg:phone":"+44 1787 475102",
    "sg:postcode":"CO9 1PW",
    "sg:province":"Essex",
    "sg:tags":[
        "hr",
        "distributor",
        "petrol"
    ],
    "wof:name":"Shell Direct (South East)",
    "wof:placetype":"venue"
},
  "geometry": {"coordinates":[0.5912200212,51.9385604858],"type":"Point"}
}