{
  "type": "Feature",
  "properties": {
    "addr:full":"29 Bridport Street Liverpool Merseyside L3 5QF",
    "addr:housenumber":"29",
    "addr:postcode":"l3 5qf",
    "addr:street":"Bridport Street",
    "iso:country":"GB",
    "sg:address":"29 Bridport Street",
    "sg:city":"Liverpool",
    "sg:classifiers":[
        {
            "category":"Autos & Motor Vehicles",
            "subcategory":"Auto Supplies",
            "type":"Retail Goods"
        },
        {
            "category":"Retail",
            "subcategory":"Auto Repair",
            "type":"Services"
        }
    ],
    "sg:phone":"+44 151 709 9306",
    "sg:postcode":"L3 5QF",
    "sg:province":"Merseyside",
    "sg:tags":[
        "modification",
        "clutch",
        "replacement",
        "brake",
        "garage"
    ],
    "wof:name":"Advanced Auto Services",
    "wof:placetype":"venue"
},
  "geometry": {"coordinates":[-2.975954,53.408813],"type":"Point"}
}