{
  "type": "Feature",
  "properties": {
    "addr:full":"Stratford Rd Solihull West Midlands B90 4LA",
    "addr:postcode":"b90 4la",
    "addr:street":"Stratford Rd",
    "iso:country":"GB",
    "sg:address":"Stratford Rd",
    "sg:city":"Solihull",
    "sg:classifiers":[
        {
            "category":"Shopping",
            "type":"Retail Goods"
        }
    ],
    "sg:phone":"+44 121 697 5000",
    "sg:postcode":"B90 4LA",
    "sg:province":"West Midlands",
    "sg:tags":[
        "part",
        "accessory"
    ],
    "wof:name":"Lucas Aftermarket Operations",
    "wof:placetype":"venue"
},
  "geometry": {"coordinates":[-1.8015120029,52.3875770569],"type":"Point"}
}