{
  "type": "Feature",
  "properties": {
    "addr:full":"22 Taeping St Poplar Greater London E14 9UN",
    "addr:housenumber":"22",
    "addr:postcode":"e14 9un",
    "addr:street":"Taeping St",
    "iso:country":"GB",
    "sg:address":"22 Taeping St",
    "sg:city":"Poplar",
    "sg:classifiers":[
        {
            "category":"Professional",
            "subcategory":"Art Services",
            "type":"Services"
        }
    ],
    "sg:phone":"+44 20 7515 0340",
    "sg:postcode":"E14 9UN",
    "sg:province":"Greater London",
    "sg:tags":[
        "graphic",
        "designer"
    ],
    "wof:name":"Victor Saumarez",
    "wof:placetype":"venue"
},
  "geometry": {"coordinates":[-0.0176129993,51.4921875],"type":"Point"}
}