{
  "type": "Feature",
  "properties": {
    "iso:country":"GB",
    "sg:address":"Penylan House, Penprysg Road",
    "sg:city":"Bridgend",
    "sg:classifiers":[
        {
            "category":"Professional",
            "subcategory":"Computer Services",
            "type":"Services"
        }
    ],
    "sg:phone":"+44 1656 862653",
    "sg:postcode":"CF35 6LT",
    "sg:province":"Bridgend",
    "sg:tags":[
        "consultant"
    ],
    "wof:name":"Griffiths Associates Ltd.",
    "wof:placetype":"venue"
},
  "geometry": {"coordinates":[-3.496789,51.532185],"type":"Point"}
}