{
  "type": "Feature",
  "properties": {
    "addr:full":"Derlwyn Tregaron Ceredigion SY25 6LH",
    "addr:postcode":"sy25 6lh",
    "iso:country":"GB",
    "sg:address":"Derlwyn",
    "sg:city":"Tregaron",
    "sg:classifiers":[
        {
            "category":"Farming",
            "subcategory":"Livestock Farm",
            "type":"Manufacturing & Wholesale Goods"
        }
    ],
    "sg:phone":"+44 1974 298346",
    "sg:postcode":"SY25 6LH",
    "sg:province":"Ceredigion",
    "sg:tags":[
        "others"
    ],
    "wof:name":"J D M E & T R Davies",
    "wof:placetype":"venue"
},
  "geometry": {"coordinates":[-3.951499,52.236881],"type":"Point"}
}