{
  "type": "Feature",
  "properties": {
    "addr:full":"Unit 14a, Great Western Industrial Centre Dorchester Dorset DT1 1RD",
    "addr:housenumber":"unit 14a",
    "addr:postcode":"dt1 1rd",
    "addr:street":"Great Western Industrial Centre",
    "iso:country":"GB",
    "sg:address":"Unit 14a, Great Western Industrial Centre",
    "sg:city":"Dorchester",
    "sg:classifiers":[
        {
            "category":"Home & Garden",
            "subcategory":"Carpets & Floor Coverings",
            "type":"Retail Goods"
        }
    ],
    "sg:phone":"+44 1305 251385",
    "sg:postcode":"DT1 1RD",
    "sg:province":"Dorset",
    "sg:tags":[
        "carpets",
        "rug",
        "matting"
    ],
    "wof:name":"Dorchester Carpets",
    "wof:placetype":"venue"
},
  "geometry": {"coordinates":[-2.440724,50.711231],"type":"Point"}
}