{
  "type": "Feature",
  "properties": {
    "iso:country":"GB",
    "sg:address":"5/7/9 Grey Street",
    "sg:city":"Newcastle-upon-tyne",
    "sg:classifiers":[
        {
            "category":"Autos & Motor Vehicles",
            "subcategory":"Motorcycle Sales",
            "type":"Retail Goods"
        }
    ],
    "sg:phone":"+44 191 245 0095",
    "sg:postcode":"NE1 6AS",
    "sg:province":"Tyne and Wear",
    "sg:tags":[
        "chauffeur",
        "driven",
        "car"
    ],
    "wof:name":"St.James Executive Cars",
    "wof:placetype":"venue"
},
  "geometry": {"coordinates":[-1.610963,54.971081],"type":"Point"}
}