{
  "type": "Feature",
  "properties": {
    "addr:full":"23 Burnt Street Wells-next-the-sea Norfolk NR23 1HP",
    "addr:housenumber":"23",
    "addr:postcode":"nr23 1hp",
    "addr:street":"Burnt Street",
    "iso:country":"GB",
    "sg:address":"23 Burnt Street",
    "sg:city":"Wells-next-the-sea",
    "sg:classifiers":[
        {
            "category":"Building & Trades",
            "subcategory":"Construction",
            "type":"Services"
        }
    ],
    "sg:postcode":"NR23 1HP",
    "sg:province":"Norfolk",
    "sg:tags":[
        "builder"
    ],
    "wof:name":"Terrington Builder",
    "wof:placetype":"venue"
},
  "geometry": {"coordinates":[0.851387,52.951717],"type":"Point"}
}