{
  "type": "Feature",
  "properties": {
    "addr:full":"Nash House, London Road Hemel Hempstead Hertfordshire HP3 9SR",
    "addr:postcode":"hp3 9sr",
    "addr:street":"London Road",
    "iso:country":"GB",
    "sg:address":"Nash House, London Road",
    "sg:city":"Hemel Hempstead",
    "sg:classifiers":[
        {
            "category":"Shopping",
            "subcategory":"Stationery & Office Supplies",
            "type":"Retail Goods"
        }
    ],
    "sg:phone":"+44 1442 235200",
    "sg:postcode":"HP3 9SR",
    "sg:province":"Hertfordshire",
    "wof:name":"T B L (Supplies) Ltd.",
    "wof:placetype":"venue"
},
  "geometry": {"coordinates":[-0.484864,51.743076],"type":"Point"}
}