{
  "type": "Feature",
  "properties": {
    "iso:country":"GB",
    "sg:address":"1 Lincoln Gro, Harwood",
    "sg:city":"Bolton",
    "sg:classifiers":[
        {
            "category":"Banks & Credit Unions",
            "subcategory":"Investment Brokerage",
            "type":"Services"
        }
    ],
    "sg:phone":"+44 1204 532914",
    "sg:postcode":"BL2 4EG",
    "sg:province":"Lancashire",
    "wof:name":"Parkland Properties",
    "wof:placetype":"venue"
},
  "geometry": {"coordinates":[-2.385434,53.601875],"type":"Point"}
}