{
  "type": "Feature",
  "properties": {
    "addr:full":"1 Lincoln Gro, Harwood Bolton Lancashire BL2 4EG",
    "addr:housenumber":"1",
    "addr:postcode":"bl2 4eg",
    "addr:street":"Lincoln Gro Harwood",
    "iso:country":"GB",
    "sg:address":"1 Lincoln Gro, Harwood",
    "sg:city":"Bolton",
    "sg:classifiers":[
        {
            "category":"Banks & Credit Unions",
            "subcategory":"Investment Brokerage",
            "type":"Services"
        }
    ],
    "sg:phone":"+44 1204 532914",
    "sg:postcode":"BL2 4EG",
    "sg:province":"Lancashire",
    "wof:name":"Parkland Properties",
    "wof:placetype":"venue"
},
  "geometry": {"coordinates":[-2.385434,53.601875],"type":"Point"}
}