{
  "type": "Feature",
  "properties": {
    "iso:country":"GB",
    "sg:address":"44 Birch Coppice",
    "sg:city":"Brierley Hill",
    "sg:classifiers":[
        {
            "category":"Professional",
            "subcategory":"Engineering",
            "type":"Services"
        }
    ],
    "sg:phone":"+44 1384 566926",
    "sg:postcode":"DY5 1AP",
    "sg:province":"West Midlands",
    "sg:tags":[
        "industrial",
        "engineer"
    ],
    "wof:name":"Naylor Combustion Services Ltd",
    "wof:placetype":"venue"
},
  "geometry": {"coordinates":[-2.0989511013,52.4756698608],"type":"Point"}
}