{
  "type": "Feature",
  "properties": {
    "addr:full":"Unit 46/47, Two Shay Haul Road, Stakehill Industrial Estate Manchester Greater Manchester M24 2FL",
    "addr:housenumber":"unit 46 / 47",
    "addr:postcode":"m24 2fl",
    "addr:street":"Haul Road Stakehill Industrial Estate",
    "iso:country":"GB",
    "sg:address":"Unit 46/47, Two Shay Haul Road, Stakehill Industrial Estate",
    "sg:city":"Manchester",
    "sg:classifiers":[
        {
            "category":"Freight",
            "type":"Transportation"
        }
    ],
    "sg:phone":"+44 161 643 0463",
    "sg:postcode":"M24 2FL",
    "sg:province":"Greater Manchester",
    "sg:tags":[
        "haulage",
        "transport",
        "road"
    ],
    "wof:name":"ASPRAY TRANSPORT NORTHERN LTD",
    "wof:placetype":"venue"
},
  "geometry": {"coordinates":[-2.1708900928,53.5681800842],"type":"Point"}
}