{
  "type": "Feature",
  "properties": {
    "iso:country":"GB",
    "sg:address":"16-18 Old Montague St",
    "sg:city":"Whitechapel",
    "sg:classifiers":[
        {
            "category":"Wholesale",
            "subcategory":"Non-durable Goods",
            "type":"Manufacturing & Wholesale Goods"
        }
    ],
    "sg:phone":"+44 20 7377 6684",
    "sg:postcode":"E1 5NG",
    "sg:province":"Greater London",
    "sg:tags":[
        "carry",
        "cash"
    ],
    "wof:name":"Sound & Vision International",
    "wof:placetype":"venue"
},
  "geometry": {"coordinates":[-0.069856,51.517563],"type":"Point"}
}