{
  "type": "Feature",
  "properties": {
    "iso:country":"GB",
    "sg:address":"The Hollybush, Worcester Rd",
    "sg:city":"Worcester",
    "sg:classifiers":[
        {
            "category":"Professional",
            "type":"Services"
        }
    ],
    "sg:phone":"+44 1886 821885",
    "sg:postcode":"WR6 5RB",
    "sg:province":"Herefordshire",
    "sg:tags":[
        "exhibition"
    ],
    "wof:name":"Hollybush",
    "wof:placetype":"venue"
},
  "geometry": {"coordinates":[-2.40742,52.201481],"type":"Point"}
}