{
  "type": "Feature",
  "properties": {
    "addr:full":"Unit 18, Sittingbourne Industrial Park, Crown Quay Lane Sittingbourne Kent ME10 3JZ",
    "addr:housenumber":"unit 18",
    "addr:postcode":"me10 3jz",
    "addr:street":"Sittingbourne Industrial Park Crown Quay Lane",
    "iso:country":"GB",
    "sg:address":"Unit 18, Sittingbourne Industrial Park, Crown Quay Lane",
    "sg:city":"Sittingbourne",
    "sg:classifiers":[
        {
            "category":"Professional",
            "subcategory":"Engineering",
            "type":"Services"
        }
    ],
    "sg:phone":"+44 1795 476367",
    "sg:postcode":"ME10 3JZ",
    "sg:province":"Kent",
    "wof:name":"Plalite Ltd.",
    "wof:placetype":"venue"
},
  "geometry": {"coordinates":[0.7379099727,51.3408203125],"type":"Point"}
}