{
  "type": "Feature",
  "properties": {
    "addr:full":"Chesterfield Trading Estate, Carwood Road, Sheepbridge Chesterfield Derbyshire S41 9QB",
    "addr:postcode":"s41 9qb",
    "addr:street":"Carwood Road Sheepbridge",
    "iso:country":"GB",
    "sg:address":"Chesterfield Trading Estate, Carwood Road, Sheepbridge",
    "sg:city":"Chesterfield",
    "sg:classifiers":[
        {
            "category":"Manufacturing",
            "subcategory":"Metals",
            "type":"Manufacturing & Wholesale Goods"
        }
    ],
    "sg:phone":"+44 1246 264500",
    "sg:postcode":"S41 9QB",
    "sg:province":"Derbyshire",
    "sg:tags":[
        "steel",
        "stockholder"
    ],
    "wof:name":"International Metal Service (U K) Ltd.",
    "wof:placetype":"venue"
},
  "geometry": {"coordinates":[-1.4585000277,53.2748413086],"type":"Point"}
}