{
  "type": "Feature",
  "properties": {
    "iso:country":"GB",
    "sg:address":"Mole Rd, Sindlesham",
    "sg:city":"Wokingham",
    "sg:classifiers":[
        {
            "category":"Community Center",
            "type":"Public Place"
        }
    ],
    "sg:phone":"+44 118 977 1777",
    "sg:postcode":"RG41 5DJ",
    "sg:province":"Berkshire",
    "sg:tags":[
        "recreation",
        "leisure",
        "centre"
    ],
    "wof:name":"Nirvana Spa & Pulse 8 Fitness Club",
    "wof:placetype":"venue"
},
  "geometry": {"coordinates":[-0.8848479986,51.422668457],"type":"Point"}
}