{
  "type": "Feature",
  "properties": {
    "iso:country":"GB",
    "sg:address":"42 York Place",
    "sg:city":"Harrogate",
    "sg:classifiers":[
        {
            "category":"Social Services",
            "subcategory":"Retirement Home",
            "type":"Services"
        }
    ],
    "sg:phone":"+44 1423 565411",
    "sg:postcode":"HG1 5RH",
    "sg:province":"North Yorkshire",
    "sg:tags":[
        "rest"
    ],
    "wof:name":"Straygarth Home for the Elderly",
    "wof:placetype":"venue"
},
  "geometry": {"coordinates":[-1.5318089724,53.9899177551],"type":"Point"}
}