{
  "type": "Feature",
  "properties": {
    "addr:full":"8 Reighton Croft, Greengates Bradford West Yorkshire BD10 0DH",
    "addr:housenumber":"8",
    "addr:postcode":"bd10 0dh",
    "addr:street":"Reighton Croft",
    "iso:country":"GB",
    "sg:address":"8 Reighton Croft, Greengates",
    "sg:city":"Bradford",
    "sg:classifiers":[
        {
            "category":"Retail",
            "subcategory":"Laundry & Dry Cleaning",
            "type":"Services"
        }
    ],
    "sg:phone":"+44 1274 622633",
    "sg:postcode":"BD10 0DH",
    "sg:province":"West Yorkshire",
    "sg:tags":[
        "home",
        "ironing"
    ],
    "wof:name":"Exclusive Ironing Service",
    "wof:placetype":"venue"
},
  "geometry": {"coordinates":[-1.7080370188,53.8274650574],"type":"Point"}
}