{
  "type": "Feature",
  "properties": {
    "addr:full":"1 Coventry Street Stourbridge Staffordshire DY8 1EP",
    "addr:housenumber":"1",
    "addr:postcode":"dy8 1ep",
    "addr:street":"Coventry Street",
    "iso:country":"GB",
    "sg:address":"1 Coventry Street",
    "sg:city":"Stourbridge",
    "sg:classifiers":[
        {
            "category":"Deli",
            "type":"Food & Drink"
        },
        {
            "category":"Restaurant",
            "type":"Food & Drink"
        }
    ],
    "sg:phone":"+44 1384 377371",
    "sg:postcode":"DY8 1EP",
    "sg:province":"Staffordshire",
    "sg:tags":[
        "delicatessen",
        "french"
    ],
    "wof:name":"French Delicatessen",
    "wof:placetype":"venue"
},
  "geometry": {"coordinates":[-2.145979,52.457829],"type":"Point"}
}