{
  "type": "Feature",
  "properties": {
    "addr:full":"10 Shrubbery St Kidderminster Staffordshire DY10 2QZ",
    "addr:housenumber":"10",
    "addr:postcode":"dy10 2qz",
    "addr:street":"Shrubbery St",
    "iso:country":"GB",
    "sg:address":"10 Shrubbery St",
    "sg:city":"Kidderminster",
    "sg:classifiers":[
        {
            "category":"Arts & Performance",
            "subcategory":"Music",
            "type":"Entertainment"
        }
    ],
    "sg:phone":"+44 1562 636281",
    "sg:postcode":"DY10 2QZ",
    "sg:province":"Staffordshire",
    "sg:tags":[
        "mobile",
        "disco"
    ],
    "wof:name":"Sound Tec",
    "wof:placetype":"venue"
},
  "geometry": {"coordinates":[-2.2372319698,52.392124176],"type":"Point"}
}