{
  "type": "Feature",
  "properties": {
    "addr:full":"208 Whitegate Drive Blackpool Lancashire FY3 9JL",
    "addr:housenumber":"208",
    "addr:postcode":"fy3 9jl",
    "addr:street":"Whitegate Drive",
    "iso:country":"GB",
    "sg:address":"208 Whitegate Drive",
    "sg:city":"Blackpool",
    "sg:classifiers":[
        {
            "category":"Personal",
            "subcategory":"Beauty Salon",
            "type":"Services"
        }
    ],
    "sg:phone":"+44 1253 764218",
    "sg:postcode":"FY3 9JL",
    "sg:province":"Lancashire",
    "sg:tags":[
        "unisex",
        "hairdresser"
    ],
    "wof:name":"Profile",
    "wof:placetype":"venue"
},
  "geometry": {"coordinates":[-3.031544,53.808228],"type":"Point"}
}