{
  "type": "Feature",
  "properties": {
    "addr:full":"Suite 35 Burlington House, 369 Wellingborough Road Northampton Northamptonshire NN1 4EU",
    "addr:housenumber":"369",
    "addr:postcode":"nn1 4eu",
    "addr:street":"Suite 35;Wellingborough Road",
    "iso:country":"GB",
    "sg:address":"Suite 35 Burlington House, 369 Wellingborough Road",
    "sg:city":"Northampton",
    "sg:classifiers":[
        {
            "category":"Organizations",
            "subcategory":"Non-profit Organization",
            "type":"Services"
        }
    ],
    "sg:phone":"+44 1604 239404",
    "sg:postcode":"NN1 4EU",
    "sg:province":"Northamptonshire",
    "sg:tags":[
        "organisation",
        "voluntary",
        "charity"
    ],
    "wof:name":"Northamptonshire Society for Autism",
    "wof:placetype":"venue"
},
  "geometry": {"coordinates":[-0.8714810014,52.2447319031],"type":"Point"}
}