{
  "type": "Feature",
  "properties": {
    "iso:country":"GB",
    "sg:address":"33 Penn Rd",
    "sg:city":"Rickmansworth",
    "sg:classifiers":[
        {
            "category":"Home & Garden",
            "subcategory":"Household Appliances",
            "type":"Retail Goods"
        }
    ],
    "sg:postcode":"WD3 8QW",
    "sg:province":"Hertfordshire",
    "sg:tags":[
        "gas"
    ],
    "wof:name":"A.T.C. Installations",
    "wof:placetype":"venue"
},
  "geometry": {"coordinates":[-0.4980790019,51.6354598999],"type":"Point"}
}