{
  "type": "Feature",
  "properties": {
    "iso:country":"GB",
    "sg:address":"Bonville Road",
    "sg:city":"Bristol",
    "sg:classifiers":[
        {
            "category":"Professional",
            "subcategory":"Business Services",
            "type":"Services"
        }
    ],
    "sg:phone":"+44 117 971 3553",
    "sg:postcode":"BS4 5QH",
    "sg:province":"City of Bristol",
    "sg:tags":[
        "shop",
        "cleaning"
    ],
    "wof:name":"Minster Cleaning Services",
    "wof:placetype":"venue"
},
  "geometry": {"coordinates":[-2.5358119011,51.4370498657],"type":"Point"}
}