{
  "type": "Feature",
  "properties": {
    "addr:full":"64 Ashfield Liverpool Merseyside L15 1EZ",
    "addr:housenumber":"64",
    "addr:postcode":"l15 1ez",
    "addr:street":"Ashfield",
    "iso:country":"GB",
    "sg:address":"64 Ashfield",
    "sg:city":"Liverpool",
    "sg:classifiers":[
        {
            "category":"Building & Trades",
            "subcategory":"Construction",
            "type":"Services"
        }
    ],
    "sg:phone":"+44 151 733 5505",
    "sg:postcode":"L15 1EZ",
    "sg:province":"Merseyside",
    "sg:tags":[
        "builder"
    ],
    "wof:name":"G H C Contractors",
    "wof:placetype":"venue"
},
  "geometry": {"coordinates":[-2.93537,53.399879],"type":"Point"}
}