{
  "type": "Feature",
  "properties": {
    "iso:country":"GB",
    "sg:address":"Field Barn Farm, Brettenham Road",
    "sg:city":"Thetford",
    "sg:classifiers":[
        {
            "category":"Farming",
            "subcategory":"Livestock Farm",
            "type":"Manufacturing & Wholesale Goods"
        }
    ],
    "sg:phone":"+44 1842 753271",
    "sg:postcode":"IP24 2RW",
    "sg:province":"Norfolk",
    "sg:tags":[
        "others"
    ],
    "wof:name":"Kemps Herbs",
    "wof:placetype":"venue"
},
  "geometry": {"coordinates":[0.837435,52.41552],"type":"Point"}
}