{
  "type": "Feature",
  "properties": {
    "addr:full":"Lullington Studio, Lullington Frome Somerset BA11 2PW",
    "addr:postcode":"ba11 2pw",
    "iso:country":"GB",
    "sg:address":"Lullington Studio, Lullington",
    "sg:city":"Frome",
    "sg:classifiers":[
        {
            "category":"Professional",
            "subcategory":"Art Services",
            "type":"Services"
        }
    ],
    "sg:postcode":"BA11 2PW",
    "sg:province":"Somerset",
    "sg:tags":[
        "carver",
        "sculptor"
    ],
    "wof:name":"Backhouse Sculptures",
    "wof:placetype":"venue"
},
  "geometry": {"coordinates":[-2.30653,51.265896],"type":"Point"}
}