{
  "type": "Feature",
  "properties": {
    "addr:full":"West Street Cambridge Cambridgeshire CB3 7DS",
    "addr:postcode":"cb3 7ds",
    "addr:street":"West Street",
    "iso:country":"GB",
    "sg:address":"West Street",
    "sg:city":"Cambridge",
    "sg:classifiers":[
        {
            "category":"Shopping",
            "subcategory":"Florist",
            "type":"Retail Goods"
        }
    ],
    "sg:postcode":"CB3 7DS",
    "sg:province":"Cambridgeshire",
    "wof:name":"Westside Flower Mill",
    "wof:placetype":"venue"
},
  "geometry": {"coordinates":[0.0178389996,52.1868629456],"type":"Point"}
}