{
  "type": "Feature",
  "properties": {
    "addr:full":"Northampton Road Market Harborough Leicestershire LE16 9HD",
    "addr:postcode":"le16 9hd",
    "addr:street":"Northampton Road",
    "iso:country":"GB",
    "sg:address":"Northampton Road",
    "sg:city":"Market Harborough",
    "sg:classifiers":[
        {
            "category":"Autos & Motor Vehicles",
            "subcategory":"Automobile Sales",
            "type":"Retail Goods"
        }
    ],
    "sg:phone":"+44 1858 465511",
    "sg:postcode":"LE16 9HD",
    "sg:province":"Leicestershire",
    "sg:tags":[
        "car",
        "used"
    ],
    "wof:name":"Protheroe Motor Group Ltd",
    "wof:placetype":"venue"
},
  "geometry": {"coordinates":[-0.918686,52.475746],"type":"Point"}
}