{
  "type": "Feature",
  "properties": {
    "addr:full":"1a Kent Street, Salford Manchester Greater Manchester M7 9UL",
    "addr:housenumber":"1a",
    "addr:postcode":"m7 9ul",
    "addr:street":"Kent Street",
    "iso:country":"GB",
    "sg:address":"1a Kent Street, Salford",
    "sg:city":"Manchester",
    "sg:classifiers":[
        {
            "category":"Food & Beverages",
            "subcategory":"Liquor & Beverages",
            "type":"Retail Goods"
        }
    ],
    "sg:postcode":"M7 9UL",
    "sg:province":"Greater Manchester",
    "sg:tags":[
        "beer",
        "spirit",
        "wines"
    ],
    "wof:name":"Swiderski Liquor Merchants",
    "wof:placetype":"venue"
},
  "geometry": {"coordinates":[-2.2690401077,53.501789093],"type":"Point"}
}