{
  "type": "Feature",
  "properties": {
    "addr:full":"4 Finchley Road Blackpool Lancashire FY1 2LP",
    "addr:housenumber":"4",
    "addr:postcode":"fy1 2lp",
    "addr:street":"Finchley Road",
    "iso:country":"GB",
    "sg:address":"4 Finchley Road",
    "sg:city":"Blackpool",
    "sg:classifiers":[
        {
            "category":"Travel",
            "subcategory":"Hotels & Motels",
            "type":"Entertainment"
        },
        {
            "category":"Bars & Pubs",
            "subcategory":"Hookah Bar",
            "type":"Food & Drink"
        }
    ],
    "sg:phone":"+44 1253 354407",
    "sg:postcode":"FY1 2LP",
    "sg:province":"Lancashire",
    "sg:tags":[
        "self",
        "holiday",
        "catering"
    ],
    "wof:name":"Willow Dene Holiday Flats",
    "wof:placetype":"venue"
},
  "geometry": {"coordinates":[-3.0523920059,53.8324432373],"type":"Point"}
}