{
  "type": "Feature",
  "properties": {
    "addr:full":"117 Grove Street Edinburgh City of Edinburgh EH3 8AA",
    "addr:housenumber":"117",
    "addr:postcode":"eh3 8aa",
    "addr:street":"Grove Street",
    "iso:country":"GB",
    "sg:address":"117 Grove Street",
    "sg:city":"Edinburgh",
    "sg:classifiers":[
        {
            "category":"Education",
            "subcategory":"College",
            "type":"Public Place"
        },
        {
            "category":"Taxi",
            "type":"Transportation"
        }
    ],
    "sg:phone":"+44 131 229 6857",
    "sg:postcode":"EH3 8AA",
    "sg:province":"City of Edinburgh",
    "sg:tags":[
        "school"
    ],
    "wof:name":"Clan House of Edinburgh Ltd.",
    "wof:placetype":"venue"
},
  "geometry": {"coordinates":[-3.211208,55.943485],"type":"Point"}
}