{
  "type": "Feature",
  "properties": {
    "iso:country":"GB",
    "sg:address":"48 Station Road",
    "sg:city":"Redhill",
    "sg:classifiers":[
        {
            "category":"Professional",
            "subcategory":"Accounting & Tax Preparation",
            "type":"Services"
        }
    ],
    "sg:postcode":"RH1 1PH",
    "sg:province":"Surrey",
    "sg:tags":[
        "accountant"
    ],
    "wof:name":"Cole Marie & Co.",
    "wof:placetype":"venue"
},
  "geometry": {"coordinates":[-0.1690039933,51.2403030396],"type":"Point"}
}