{
  "type": "Feature",
  "properties": {
    "addr:full":"Shap Penrith Cumbria CA10 3PZ",
    "addr:postcode":"ca10 3pz",
    "iso:country":"GB",
    "sg:address":"Shap",
    "sg:city":"Penrith",
    "sg:classifiers":[
        {
            "category":"Retail",
            "subcategory":"Auto Repair",
            "type":"Services"
        }
    ],
    "sg:phone":"+44 1931 716351",
    "sg:postcode":"CA10 3PZ",
    "sg:province":"Cumbria",
    "sg:tags":[
        "modification",
        "garage"
    ],
    "wof:name":"Fell Garage",
    "wof:placetype":"venue"
},
  "geometry": {"coordinates":[-2.66949,54.518631],"type":"Point"}
}