{
  "type": "Feature",
  "properties": {
    "addr:full":"61 Woodside Drive, Cottingley Bingley West Yorkshire BD16 1RG",
    "addr:housenumber":"61",
    "addr:postcode":"bd16 1rg",
    "addr:street":"Woodside Drive",
    "iso:country":"GB",
    "sg:address":"61 Woodside Drive, Cottingley",
    "sg:city":"Bingley",
    "sg:classifiers":[
        {
            "category":"Building & Trades",
            "subcategory":"Construction",
            "type":"Services"
        }
    ],
    "sg:phone":"+44 1274 566241",
    "sg:postcode":"BD16 1RG",
    "sg:province":"West Yorkshire",
    "sg:tags":[
        "joiner",
        "carpenter"
    ],
    "wof:name":"Peter Gray",
    "wof:placetype":"venue"
},
  "geometry": {"coordinates":[-1.8349989653,53.8291168213],"type":"Point"}
}