{
  "type": "Feature",
  "properties": {
    "iso:country":"GB",
    "sg:address":"38 Spring Lane, Little Common",
    "sg:city":"Bexhill-on-sea",
    "sg:classifiers":[
        {
            "category":"Building & Trades",
            "subcategory":"Construction",
            "type":"Services"
        }
    ],
    "sg:postcode":"TN39 4EP",
    "sg:province":"East Sussex",
    "sg:tags":[
        "contractor",
        "paving",
        "driveway"
    ],
    "wof:name":"Builders Direct",
    "wof:placetype":"venue"
},
  "geometry": {"coordinates":[0.430916,50.849113],"type":"Point"}
}