{
  "type": "Feature",
  "properties": {
    "addr:full":"6 Hillside Avenue, Chaddesden Derby Derbyshire DE21 6SP",
    "addr:housenumber":"6",
    "addr:postcode":"de21 6sp",
    "addr:street":"Hillside Avenue",
    "iso:country":"GB",
    "sg:address":"6 Hillside Avenue, Chaddesden",
    "sg:city":"Derby",
    "sg:classifiers":[
        {
            "category":"Home & Garden",
            "subcategory":"Household Appliances",
            "type":"Retail Goods"
        },
        {
            "category":"Retail",
            "subcategory":"Repair Shop",
            "type":"Services"
        }
    ],
    "sg:phone":"+44 1332 675828",
    "sg:postcode":"DE21 6SP",
    "sg:province":"Derbyshire",
    "sg:tags":[
        "television",
        "video",
        "servicing",
        "maintenance",
        "electrical",
        "radio"
    ],
    "wof:name":"Oakwood T V",
    "wof:placetype":"venue"
},
  "geometry": {"coordinates":[-1.4334360361,52.9209938049],"type":"Point"}
}