{
  "type": "Feature",
  "properties": {
    "addr:full":"Litchard Industrial Estate Bridgend Bridgend CF31 2AL",
    "addr:postcode":"cf31 2al",
    "addr:street":"Estate",
    "iso:country":"GB",
    "sg:address":"Litchard Industrial Estate",
    "sg:city":"Bridgend",
    "sg:classifiers":[
        {
            "category":"Social Services",
            "type":"Services"
        }
    ],
    "sg:phone":"+44 1656 657495",
    "sg:postcode":"CF31 2AL",
    "sg:province":"Bridgend",
    "sg:tags":[
        "disability"
    ],
    "wof:name":"Days Healthcare U K  Ltd.",
    "wof:placetype":"venue"
},
  "geometry": {"coordinates":[-3.5782630444,51.5088348389],"type":"Point"}
}