{
  "type": "Feature",
  "properties": {
    "addr:full":"490 Cowbridge Road East Cardiff Cardiff CF5 1BL",
    "addr:housenumber":"490",
    "addr:postcode":"cf5 1bl",
    "addr:street":"Cowbridge Road East",
    "iso:country":"GB",
    "sg:address":"490 Cowbridge Road East",
    "sg:city":"Cardiff",
    "sg:classifiers":[
        {
            "category":"Sports & Exercise",
            "subcategory":"Winter Sports",
            "type":"Entertainment"
        }
    ],
    "sg:phone":"+44 29 2056 9355",
    "sg:postcode":"CF5 1BL",
    "sg:province":"Cardiff",
    "sg:tags":[
        "skiing"
    ],
    "wof:name":"Ski Dreams",
    "wof:placetype":"venue"
},
  "geometry": {"coordinates":[-3.2224049568,51.483669281],"type":"Point"}
}