{
  "type": "Feature",
  "properties": {
    "addr:full":"Cairn Valley Medical Practice, Kirkgate Dumfries Dumfries and Galloway DG2 0SZ",
    "addr:postcode":"dg2 0sz",
    "addr:street":"Cairn;Kirkgate",
    "iso:country":"GB",
    "sg:address":"Cairn Valley Medical Practice, Kirkgate",
    "sg:city":"Dumfries",
    "sg:classifiers":[
        {
            "category":"Health Services",
            "subcategory":"Doctor",
            "type":"Services"
        }
    ],
    "sg:phone":"+44 1387 820266",
    "sg:postcode":"DG2 0SZ",
    "sg:province":"Dumfries and Galloway",
    "sg:tags":[
        "practitioners"
    ],
    "wof:name":"Lowry, W S",
    "wof:placetype":"venue"
},
  "geometry": {"coordinates":[-3.778606,55.140598],"type":"Point"}
}