{
  "type": "Feature",
  "properties": {
    "iso:country":"GB",
    "sg:address":"435 Bearwood Road",
    "sg:city":"Smethwick",
    "sg:classifiers":[
        {
            "category":"Manufacturing",
            "subcategory":"Tools & Machinery",
            "type":"Manufacturing & Wholesale Goods"
        },
        {
            "category":"Insurance",
            "subcategory":"Insurance Agent",
            "type":"Services"
        }
    ],
    "sg:phone":"+44 121 434 3887",
    "sg:postcode":"B66 4DH",
    "sg:province":"West Midlands",
    "sg:tags":[
        "society",
        "friendly"
    ],
    "wof:name":"N V INSURANCE SERVICES",
    "wof:placetype":"venue"
},
  "geometry": {"coordinates":[-1.969969,52.478107],"type":"Point"}
}