{
  "type": "Feature",
  "properties": {
    "iso:country":"GB",
    "sg:address":"94c Gilesgate",
    "sg:city":"Durham",
    "sg:classifiers":[
        {
            "category":"Cinema",
            "subcategory":"Movie Rental",
            "type":"Entertainment"
        }
    ],
    "sg:phone":"+44 191 386 9474",
    "sg:postcode":"DH1 1JA",
    "sg:province":"Durham",
    "sg:tags":[
        "video",
        "library"
    ],
    "wof:name":"Channel 5 Video",
    "wof:placetype":"venue"
},
  "geometry": {"coordinates":[-1.5591800213,54.7788963318],"type":"Point"}
}