{
  "type": "Feature",
  "properties": {
    "addr:full":"72 Rider Haggard Road Norwich Norfolk NR7 9UQ",
    "addr:housenumber":"72",
    "addr:postcode":"nr7 9uq",
    "addr:street":"Rider Haggard Road Norwich Norfolk",
    "iso:country":"GB",
    "sg:address":"72 Rider Haggard Road",
    "sg:city":"Norwich",
    "sg:classifiers":[
        {
            "category":"Health Services",
            "subcategory":"Podiatrist",
            "type":"Services"
        }
    ],
    "sg:phone":"+44 1603 431315",
    "sg:postcode":"NR7 9UQ",
    "sg:province":"Norfolk",
    "sg:tags":[
        "podiatrists",
        "chiropodist"
    ],
    "wof:name":"ADRIAN STEWART HARTHEN",
    "wof:placetype":"venue"
},
  "geometry": {"coordinates":[1.3317450285,52.6426124573],"type":"Point"}
}