{
  "type": "Feature",
  "properties": {
    "iso:country":"GB",
    "sg:address":"12 Lower Cippenham Lane",
    "sg:city":"Slough",
    "sg:classifiers":[
        {
            "category":"Professional",
            "subcategory":"Detective & Security Services",
            "type":"Services"
        },
        {
            "category":"Retail",
            "subcategory":"Auto Repair",
            "type":"Services"
        }
    ],
    "sg:phone":"+44 1753 533754",
    "sg:postcode":"SL1 5DF",
    "sg:province":"Berkshire",
    "sg:tags":[
        "car",
        "electrician"
    ],
    "wof:name":"Malcolm Auto Electrical Services",
    "wof:placetype":"venue"
},
  "geometry": {"coordinates":[-0.630415976,51.5132408142],"type":"Point"}
}