{
  "type": "Feature",
  "properties": {
    "iso:country":"GB",
    "sg:address":"15 The Lawns",
    "sg:city":"Farnborough",
    "sg:classifiers":[
        {
            "category":"Professional",
            "subcategory":"Computer Services",
            "type":"Services"
        }
    ],
    "sg:phone":"+44 1252 376860",
    "sg:postcode":"GU14 0RF",
    "sg:province":"Hampshire",
    "sg:tags":[
        "system",
        "software"
    ],
    "wof:name":"Globaltech Systems Ltd.",
    "wof:placetype":"venue"
},
  "geometry": {"coordinates":[-0.781723,51.288998],"type":"Point"}
}