{
  "type": "Feature",
  "properties": {
    "iso:country":"GB",
    "sg:address":"49a Williams Rd, Bosham",
    "sg:city":"Chichester",
    "sg:classifiers":[
        {
            "category":"Retail",
            "subcategory":"Auto Repair",
            "type":"Services"
        }
    ],
    "sg:postcode":"PO18 8JR",
    "sg:province":"West Sussex",
    "sg:tags":[
        "electrician"
    ],
    "wof:name":"Holland,Peter,",
    "wof:placetype":"venue"
},
  "geometry": {"coordinates":[-0.8440369964,50.8418998718],"type":"Point"}
}