{
  "type": "Feature",
  "properties": {
    "iso:country":"GB",
    "sg:address":"Forth Families Club Castle Road, Rosyth",
    "sg:city":"Dunfermline",
    "sg:classifiers":[
        {
            "category":"Organizations",
            "subcategory":"Non-profit Organization",
            "type":"Services"
        }
    ],
    "sg:phone":"+44 1383 416747",
    "sg:postcode":"KY11 2AS",
    "sg:province":"Fife",
    "sg:tags":[
        "organisation",
        "voluntary",
        "charity"
    ],
    "wof:name":"The Naval Personal & Family Service",
    "wof:placetype":"venue"
},
  "geometry": {"coordinates":[-3.426864,56.036427],"type":"Point"}
}