{
  "type": "Feature",
  "properties": {
    "addr:full":"Upper Hill Farm, Wiston Haverfordwest Pembrokeshire SA62 4PT",
    "addr:postcode":"sa62 4pt",
    "addr:street":"Upper Hill",
    "iso:country":"GB",
    "sg:address":"Upper Hill Farm, Wiston",
    "sg:city":"Haverfordwest",
    "sg:classifiers":[
        {
            "category":"Farming",
            "subcategory":"Dairy Farm",
            "type":"Manufacturing & Wholesale Goods"
        }
    ],
    "sg:postcode":"SA62 4PT",
    "sg:province":"Pembrokeshire",
    "wof:name":"P E & M C Lewis",
    "wof:placetype":"venue"
},
  "geometry": {"coordinates":[-4.8731389046,51.8261795044],"type":"Point"}
}