{
  "type": "Feature",
  "properties": {
    "iso:country":"GB",
    "sg:address":"South Bucks Continuing Education Office, Evreham Centre, Swallow Street",
    "sg:city":"Iver",
    "sg:classifiers":[
        {
            "category":"Education",
            "subcategory":"University",
            "type":"Public Place"
        }
    ],
    "sg:phone":"+44 1753 650035",
    "sg:postcode":"SL0 0HS",
    "sg:province":"Berkshire",
    "sg:tags":[
        "adult"
    ],
    "wof:name":"Continuing Education",
    "wof:placetype":"venue"
},
  "geometry": {"coordinates":[-0.5206189752,51.5365447998],"type":"Point"}
}