{
  "type": "Feature",
  "properties": {
    "iso:country":"GB",
    "sg:address":"73 Deptford High Street",
    "sg:city":"London",
    "sg:classifiers":[
        {
            "category":"Personal",
            "subcategory":"Shoe Repair & Shine",
            "type":"Services"
        },
        {
            "category":"Shopping",
            "subcategory":"Shoes",
            "type":"Retail Goods"
        }
    ],
    "sg:phone":"+44 20 8692 1918",
    "sg:postcode":"SE8 4AA",
    "sg:province":"Greater London",
    "wof:name":"Deptford Cobbler",
    "wof:placetype":"venue"
},
  "geometry": {"coordinates":[-0.026014,51.477001],"type":"Point"}
}