{
  "type": "Feature",
  "properties": {
    "iso:country":"GB",
    "sg:address":"53-55 Queensway, Bletchley",
    "sg:city":"Milton Keynes",
    "sg:classifiers":[
        {
            "category":"Food & Beverages",
            "subcategory":"Supermarket",
            "type":"Retail Goods"
        }
    ],
    "sg:phone":"+44 1908 373002",
    "sg:postcode":"MK2 2DR",
    "sg:province":"Buckinghamshire",
    "wof:name":"Solo",
    "wof:placetype":"venue"
},
  "geometry": {"coordinates":[-0.731525,51.99469],"type":"Point"}
}