{
  "type": "Feature",
  "properties": {
    "iso:country":"GB",
    "sg:address":"84 High Street",
    "sg:city":"Caernarfon",
    "sg:classifiers":[
        {
            "category":"Food & Beverages",
            "subcategory":"Bakery",
            "type":"Retail Goods"
        }
    ],
    "sg:phone":"+44 1286 870491",
    "sg:postcode":"LL55 4SU",
    "sg:province":"Gwynedd",
    "sg:tags":[
        "baker"
    ],
    "wof:name":"E W & G Roberts (Llanberis) Ltd.",
    "wof:placetype":"venue"
},
  "geometry": {"coordinates":[-4.131444,53.124611],"type":"Point"}
}