{
  "type": "Feature",
  "properties": {
    "iso:country":"GB",
    "sg:address":"34 St Marys Place",
    "sg:city":"Newcastle-upon-tyne",
    "sg:classifiers":[
        {
            "category":"Banks & Credit Unions",
            "subcategory":"Financial Services",
            "type":"Services"
        }
    ],
    "sg:phone":"+44 191 230 3358",
    "sg:postcode":"NE1 7PQ",
    "sg:province":"Tyne and Wear",
    "sg:tags":[
        "adviser",
        "independent"
    ],
    "wof:name":"K S M ASSOCIATES",
    "wof:placetype":"venue"
},
  "geometry": {"coordinates":[-1.6115089655,54.9779510498],"type":"Point"}
}