{
  "type": "Feature",
  "properties": {
    "addr:full":"Oak Ryse, Acrise Folkestone Kent CT18 8LH",
    "addr:postcode":"ct18 8lh",
    "iso:country":"GB",
    "sg:address":"Oak Ryse, Acrise",
    "sg:city":"Folkestone",
    "sg:classifiers":[
        {
            "category":"Banks & Credit Unions",
            "subcategory":"Investment Brokerage",
            "type":"Services"
        }
    ],
    "sg:postcode":"CT18 8LH",
    "sg:province":"Kent",
    "sg:tags":[
        "contractor"
    ],
    "wof:name":"Rentrac",
    "wof:placetype":"venue"
},
  "geometry": {"coordinates":[1.14882,51.131893],"type":"Point"}
}