{
  "type": "Feature",
  "properties": {
    "iso:country":"GB",
    "sg:address":"116 High Street, Harlesden",
    "sg:city":"London",
    "sg:classifiers":[
        {
            "category":"Home & Garden",
            "subcategory":"Furniture",
            "type":"Retail Goods"
        }
    ],
    "sg:postcode":"NW10 4SL",
    "sg:province":"Greater London",
    "wof:name":"Suite Deal Furnishers Ltd",
    "wof:placetype":"venue"
},
  "geometry": {"coordinates":[-0.2450630069,51.535949707],"type":"Point"}
}