{
  "type": "Feature",
  "properties": {
    "addr:full":"35 Langley Avenue Surbiton Surrey KT6 6QP",
    "addr:housenumber":"35",
    "addr:postcode":"kt6 6qp",
    "addr:street":"Langley Avenue",
    "iso:country":"GB",
    "sg:address":"35 Langley Avenue",
    "sg:city":"Surbiton",
    "sg:classifiers":[
        {
            "category":"Banks & Credit Unions",
            "subcategory":"Financial Services",
            "type":"Services"
        }
    ],
    "sg:postcode":"KT6 6QP",
    "sg:province":"Surrey",
    "sg:tags":[
        "adviser"
    ],
    "wof:name":"Penmor",
    "wof:placetype":"venue"
},
  "geometry": {"coordinates":[-0.306534,51.383144],"type":"Point"}
}