{
  "type": "Feature",
  "properties": {
    "iso:country":"GB",
    "sg:address":"Warmfield View",
    "sg:city":"Wakefield",
    "sg:classifiers":[
        {
            "category":"Community Center",
            "subcategory":"Youth",
            "type":"Public Place"
        }
    ],
    "sg:phone":"+44 1924 302275",
    "sg:postcode":"WF3 4HW",
    "sg:province":"West Yorkshire",
    "sg:tags":[
        "organisation",
        "centre"
    ],
    "wof:name":"Eastmoor Youth Club",
    "wof:placetype":"venue"
},
  "geometry": {"coordinates":[-1.477959,53.688847],"type":"Point"}
}