{
  "type": "Feature",
  "properties": {
    "iso:country":"GB",
    "sg:address":"P O Box 142, Peace House, The Priory",
    "sg:city":"Hitchin",
    "sg:classifiers":[
        {
            "category":"Banks & Credit Unions",
            "subcategory":"Financial Services",
            "type":"Services"
        }
    ],
    "sg:phone":"+44 1462 421454",
    "sg:postcode":"SG5 2GS",
    "sg:province":"Bedfordshire",
    "sg:tags":[
        "consultant",
        "pension"
    ],
    "wof:name":"National Mutual",
    "wof:placetype":"venue"
},
  "geometry": {"coordinates":[-0.284408,51.952435],"type":"Point"}
}