{
  "type": "Feature",
  "properties": {
    "addr:full":"62 High Street Fraserburgh Aberdeenshire AB43 9HP",
    "addr:housenumber":"62",
    "addr:postcode":"ab43 9hp",
    "addr:street":"High Street",
    "iso:country":"GB",
    "sg:address":"62 High Street",
    "sg:city":"Fraserburgh",
    "sg:classifiers":[
        {
            "category":"Shopping",
            "subcategory":"Pharmacy",
            "type":"Retail Goods"
        }
    ],
    "sg:postcode":"AB43 9HP",
    "sg:province":"Aberdeenshire",
    "sg:tags":[
        "pharmacist",
        "chemist"
    ],
    "wof:name":"R S Goldie",
    "wof:placetype":"venue"
},
  "geometry": {"coordinates":[-2.0081179142,57.6941375732],"type":"Point"}
}