{
  "type": "Feature",
  "properties": {
    "iso:country":"GB",
    "sg:address":"The Gallery, Water Street",
    "sg:city":"Martock",
    "sg:classifiers":[
        {
            "category":"Professional",
            "subcategory":"Art Services",
            "type":"Services"
        }
    ],
    "sg:phone":"+44 1935 823254",
    "sg:postcode":"TA12 6JN",
    "sg:province":"Somerset",
    "sg:tags":[
        "framing"
    ],
    "wof:name":"Martock Gallery",
    "wof:placetype":"venue"
},
  "geometry": {"coordinates":[-2.770669,50.967247],"type":"Point"}
}