{
  "type": "Feature",
  "properties": {
    "addr:full":"7 Randolph Court, Randolph Avenue London Greater London W9 1NW",
    "addr:housenumber":"7",
    "addr:postcode":"w9 1nw",
    "addr:street":"Randolph Court Randolph Avenue",
    "iso:country":"GB",
    "sg:address":"7 Randolph Court, Randolph Avenue",
    "sg:city":"London",
    "sg:classifiers":[
        {
            "category":"Professional",
            "subcategory":"Management & Consulting",
            "type":"Services"
        }
    ],
    "sg:postcode":"W9 1NW",
    "sg:province":"Greater London",
    "sg:tags":[
        "consultant",
        "business"
    ],
    "wof:name":"Get Going (U K) Ltd",
    "wof:placetype":"venue"
},
  "geometry": {"coordinates":[-0.182585,51.52483],"type":"Point"}
}