{
  "type": "Feature",
  "properties": {
    "addr:full":"Laithes Lane Barnsley South Yorkshire S71 3AN",
    "addr:postcode":"s71 3an",
    "addr:street":"Laithes Lane;Yorkshire",
    "iso:country":"GB",
    "sg:address":"Laithes Lane",
    "sg:city":"Barnsley",
    "sg:classifiers":[
        {
            "category":"Food & Beverages",
            "subcategory":"Bakery",
            "type":"Retail Goods"
        }
    ],
    "sg:phone":"+44 1226 290065",
    "sg:postcode":"S71 3AN",
    "sg:province":"South Yorkshire",
    "sg:tags":[
        "baker"
    ],
    "wof:name":"Potts Bakers",
    "wof:placetype":"venue"
},
  "geometry": {"coordinates":[-1.4708549976,53.5805473328],"type":"Point"}
}