{
  "type": "Feature",
  "properties": {
    "iso:country":"GB",
    "sg:address":"Club House Recreation Centre, Frimley Green Rd, Frimley Green",
    "sg:city":"Camberley",
    "sg:classifiers":[
        {
            "category":"Government",
            "subcategory":"City Hall",
            "type":"Public Place"
        }
    ],
    "sg:phone":"+44 1252 835089",
    "sg:postcode":"GU16 6JX",
    "sg:province":"Hampshire",
    "wof:name":"Frimley Green Football Club",
    "wof:placetype":"venue"
},
  "geometry": {"coordinates":[-0.7291839719,51.3046760559],"type":"Point"}
}