{
  "type": "Feature",
  "properties": {
    "iso:country":"GB",
    "sg:address":"309 Greenford Road",
    "sg:city":"Greenford",
    "sg:classifiers":[
        {
            "category":"Retail",
            "subcategory":"Funeral Services",
            "type":"Services"
        }
    ],
    "sg:phone":"+44 20 8578 1406",
    "sg:postcode":"UB6 8RE",
    "sg:province":"Greater London",
    "wof:name":"Henry Paul Funeral Services",
    "wof:placetype":"venue"
},
  "geometry": {"coordinates":[-0.350247,51.531326],"type":"Point"}
}