{
  "type": "Feature",
  "properties": {
    "addr:full":"82 Harley Street London Greater London W1G 7HN",
    "addr:housenumber":"82",
    "addr:postcode":"w1g 7hn",
    "addr:street":"Harley Street",
    "iso:country":"GB",
    "sg:address":"82 Harley Street",
    "sg:city":"London",
    "sg:classifiers":[
        {
            "category":"Health Services",
            "subcategory":"Dentist",
            "type":"Services"
        }
    ],
    "sg:phone":"+44 20 7580 3435",
    "sg:postcode":"W1G 7HN",
    "sg:province":"Greater London",
    "wof:name":"D R Burton",
    "wof:placetype":"venue"
},
  "geometry": {"coordinates":[-0.1473100036,51.5202865601],"type":"Point"}
}