{
  "type": "Feature",
  "properties": {
    "iso:country":"GB",
    "sg:address":"200 Rushmore Road",
    "sg:city":"London",
    "sg:classifiers":[
        {
            "category":"Building & Trades",
            "subcategory":"Construction",
            "type":"Services"
        }
    ],
    "sg:phone":"+44 20 8985 3642",
    "sg:postcode":"E5 0HB",
    "sg:province":"Greater London",
    "sg:tags":[
        "builder"
    ],
    "wof:name":"A W Holdsworth",
    "wof:placetype":"venue"
},
  "geometry": {"coordinates":[-0.042691,51.554821],"type":"Point"}
}