{
  "type": "Feature",
  "properties": {
    "iso:country":"GB",
    "sg:address":"Lombard St West",
    "sg:city":"West Bromwich",
    "sg:classifiers":[
        {
            "category":"Shopping",
            "subcategory":"Stationery & Office Supplies",
            "type":"Retail Goods"
        }
    ],
    "sg:phone":"+44 121 525 8626",
    "sg:postcode":"B70 8EG",
    "sg:province":"West Midlands",
    "sg:tags":[
        "item",
        "promotional"
    ],
    "wof:name":"Regent Publicity Ltd.",
    "wof:placetype":"venue"
},
  "geometry": {"coordinates":[-1.9975789785,52.5197296143],"type":"Point"}
}