{
  "type": "Feature",
  "properties": {
    "addr:full":"6 The Strand Blackpool Lancashire FY3 0AH",
    "addr:housenumber":"6",
    "addr:postcode":"fy3 0ah",
    "addr:street":"The Strand",
    "iso:country":"GB",
    "sg:address":"6 The Strand",
    "sg:city":"Blackpool",
    "sg:classifiers":[
        {
            "category":"Food & Beverages",
            "subcategory":"Fruits & Vegetables",
            "type":"Retail Goods"
        }
    ],
    "sg:phone":"+44 1253 395551",
    "sg:postcode":"FY3 0AH",
    "sg:province":"Lancashire",
    "sg:tags":[
        "greengrocer"
    ],
    "wof:name":"Fruits & Roots",
    "wof:placetype":"venue"
},
  "geometry": {"coordinates":[-3.0546469688,53.8201751709],"type":"Point"}
}