{
  "type": "Feature",
  "properties": {
    "iso:country":"GB",
    "sg:address":"Midway Down Farm, Copyhold Lane, Winterbourne Abbas",
    "sg:city":"Dorchester",
    "sg:classifiers":[
        {
            "category":"Home & Garden",
            "subcategory":"Home Furnishings",
            "type":"Retail Goods"
        },
        {
            "category":"Home & Garden",
            "subcategory":"Building Materials",
            "type":"Retail Goods"
        },
        {
            "category":"Building & Trades",
            "subcategory":"Construction",
            "type":"Services"
        }
    ],
    "sg:postcode":"DT2 9LT",
    "sg:province":"Dorset",
    "sg:tags":[
        "planner",
        "installers",
        "carpenter",
        "furnishers",
        "joiner",
        "kitchen"
    ],
    "wof:name":"KITCHEN WORKSHOP",
    "wof:placetype":"venue"
},
  "geometry": {"coordinates":[-2.539453,50.712425],"type":"Point"}
}