{
  "type": "Feature",
  "properties": {
    "iso:country":"GB",
    "sg:address":"20 Kingsland High Street",
    "sg:city":"London",
    "sg:classifiers":[
        {
            "category":"Fast Food",
            "type":"Food & Drink"
        }
    ],
    "sg:phone":"+44 20 7275 9818",
    "sg:postcode":"E8 2JP",
    "sg:province":"Greater London",
    "sg:tags":[
        "away",
        "take"
    ],
    "wof:name":"Pepper & Spice Restaurant",
    "wof:placetype":"venue"
},
  "geometry": {"coordinates":[-0.07546,51.546753],"type":"Point"}
}