{
  "type": "Feature",
  "properties": {
    "addr:full":"Old Bedw, Near Erwood, Gwenddwr Builth Wells Powys LD2 3LQ",
    "addr:postcode":"ld2 3lq",
    "addr:street":"Near Erwood Gwenddwr Builth Wells",
    "iso:country":"GB",
    "sg:address":"Old Bedw, Near Erwood, Gwenddwr",
    "sg:city":"Builth Wells",
    "sg:classifiers":[
        {
            "category":"Organizations",
            "subcategory":"Non-profit Organization",
            "type":"Services"
        }
    ],
    "sg:phone":"+44 1982 560468",
    "sg:postcode":"LD2 3LQ",
    "sg:province":"Powys",
    "sg:tags":[
        "organisation",
        "voluntary",
        "charity"
    ],
    "wof:name":"Cruse Bereavement Care",
    "wof:placetype":"venue"
},
  "geometry": {"coordinates":[-3.4030599594,52.148273468],"type":"Point"}
}