{
  "type": "Feature",
  "properties": {
    "iso:country":"GB",
    "sg:address":"Green Road",
    "sg:city":"Liversedge",
    "sg:classifiers":[
        {
            "category":"Professional",
            "subcategory":"Engineering",
            "type":"Services"
        }
    ],
    "sg:phone":"+44 1924 408832",
    "sg:postcode":"WF15 6EB",
    "sg:province":"West Yorkshire",
    "sg:tags":[
        "precision",
        "engineer"
    ],
    "wof:name":"B Kemp Grinders",
    "wof:placetype":"venue"
},
  "geometry": {"coordinates":[-1.6921600103,53.7135696411],"type":"Point"}
}