{
  "type": "Feature",
  "properties": {
    "addr:full":"69 High Street Berkhamsted Bedfordshire HP4 2DE",
    "addr:housenumber":"69",
    "addr:postcode":"hp4 2de",
    "addr:street":"High Street",
    "iso:country":"GB",
    "sg:address":"69 High Street",
    "sg:city":"Berkhamsted",
    "sg:classifiers":[
        {
            "category":"Health Services",
            "subcategory":"Chiropractor",
            "type":"Services"
        }
    ],
    "sg:phone":"+44 1442 863800",
    "sg:postcode":"HP4 2DE",
    "sg:province":"Bedfordshire",
    "wof:name":"D L Tribe",
    "wof:placetype":"venue"
},
  "geometry": {"coordinates":[-0.558574,51.758396],"type":"Point"}
}