{
  "type": "Feature",
  "properties": {
    "iso:country":"GB",
    "sg:address":"14 Links Close",
    "sg:city":"Harrogate",
    "sg:classifiers":[
        {
            "category":"Professional",
            "subcategory":"Art Services",
            "type":"Services"
        },
        {
            "category":"Building & Trades",
            "subcategory":"Construction",
            "type":"Services"
        }
    ],
    "sg:phone":"+44 1423 887454",
    "sg:postcode":"HG2 7EP",
    "sg:province":"North Yorkshire",
    "sg:tags":[
        "decorator",
        "painter"
    ],
    "wof:name":"BARRY STEPHENSON",
    "wof:placetype":"venue"
},
  "geometry": {"coordinates":[-1.4888000488,53.9981155396],"type":"Point"}
}