{
  "type": "Feature",
  "properties": {
    "iso:country":"GB",
    "sg:address":"5 Valley Road, Tasburgh",
    "sg:city":"Norwich",
    "sg:classifiers":[
        {
            "category":"Professional",
            "subcategory":"Art Services",
            "type":"Services"
        }
    ],
    "sg:postcode":"NR15 1NG",
    "sg:province":"Norfolk",
    "sg:tags":[
        "photographer"
    ],
    "wof:name":"Memories Photography",
    "wof:placetype":"venue"
},
  "geometry": {"coordinates":[1.247408,52.513702],"type":"Point"}
}