{
  "type": "Feature",
  "properties": {
    "addr:full":"64 Tower Bridge Road London Greater London SE1 4TR",
    "addr:housenumber":"64",
    "addr:postcode":"se1 4tr",
    "addr:street":"Tower Bridge Road",
    "iso:country":"GB",
    "sg:address":"64 Tower Bridge Road",
    "sg:city":"London",
    "sg:classifiers":[
        {
            "category":"Bars & Pubs",
            "type":"Food & Drink"
        }
    ],
    "sg:postcode":"SE1 4TR",
    "sg:province":"Greater London",
    "sg:tags":[
        "pubs",
        "inn"
    ],
    "wof:name":"The Pagoda",
    "wof:placetype":"venue"
},
  "geometry": {"coordinates":[-0.08296,51.495861],"type":"Point"}
}