{
  "type": "Feature",
  "properties": {
    "iso:country":"GB",
    "sg:address":"82 Bridge Street, Golbourne",
    "sg:city":"Warrington",
    "sg:classifiers":[
        {
            "category":"Building & Trades",
            "subcategory":"Construction",
            "type":"Services"
        }
    ],
    "sg:postcode":"WA3 3QB",
    "sg:province":"Cheshire",
    "sg:tags":[
        "joiner",
        "carpenter"
    ],
    "wof:name":"M Don Building & Joinery",
    "wof:placetype":"venue"
},
  "geometry": {"coordinates":[-2.5985920429,53.4725265503],"type":"Point"}
}