{
  "type": "Feature",
  "properties": {
    "addr:full":"Park Road, Witton Park Bishop Auckland Durham DL14 0EN",
    "addr:postcode":"dl14 0en",
    "addr:street":"Park Road",
    "iso:country":"GB",
    "sg:address":"Park Road, Witton Park",
    "sg:city":"Bishop Auckland",
    "sg:classifiers":[
        {
            "category":"Professional",
            "subcategory":"Engineering",
            "type":"Services"
        }
    ],
    "sg:phone":"+44 1388 663116",
    "sg:postcode":"DL14 0EN",
    "sg:province":"Durham",
    "sg:tags":[
        "contractor",
        "electrical",
        "engineer"
    ],
    "wof:name":"R Lightfoot",
    "wof:placetype":"venue"
},
  "geometry": {"coordinates":[-1.7380139828,54.6615142822],"type":"Point"}
}