{
  "type": "Feature",
  "properties": {
    "iso:country":"GB",
    "sg:address":"89 Wentworth Avenue",
    "sg:city":"Slough",
    "sg:classifiers":[
        {
            "category":"Food & Beverages",
            "subcategory":"Fruits & Vegetables",
            "type":"Retail Goods"
        }
    ],
    "sg:phone":"+44 1753 526333",
    "sg:postcode":"SL2 2DT",
    "sg:province":"Berkshire",
    "sg:tags":[
        "greengrocer"
    ],
    "wof:name":"Donoghue Fruit & Veg",
    "wof:placetype":"venue"
},
  "geometry": {"coordinates":[-0.630904,51.535522],"type":"Point"}
}