{
  "type": "Feature",
  "properties": {
    "iso:country":"GB",
    "sg:address":"39 Springfield Road",
    "sg:city":"Horsham",
    "sg:classifiers":[
        {
            "category":"Retail",
            "subcategory":"Repair Shop",
            "type":"Services"
        },
        {
            "category":"Building & Trades",
            "subcategory":"Construction",
            "type":"Services"
        },
        {
            "category":"Home & Garden",
            "subcategory":"Carpets & Floor Coverings",
            "type":"Retail Goods"
        }
    ],
    "sg:phone":"+44 1403 265418",
    "sg:postcode":"RH12 2PG",
    "sg:province":"West Sussex",
    "sg:tags":[
        "textile",
        "tiling",
        "floorcoverings",
        "contractor"
    ],
    "wof:name":"C Berwick & Sons",
    "wof:placetype":"venue"
},
  "geometry": {"coordinates":[-0.33008,51.065525],"type":"Point"}
}