{
  "type": "Feature",
  "properties": {
    "addr:full":"120 Padgate La Warrington Cheshire WA1 3RY",
    "addr:housenumber":"120",
    "addr:postcode":"wa1 3ry",
    "addr:street":"Padgate La Warrington Cheshire",
    "iso:country":"GB",
    "sg:address":"120 Padgate La",
    "sg:city":"Warrington",
    "sg:classifiers":[
        {
            "category":"Cinema",
            "subcategory":"Movie Rental",
            "type":"Entertainment"
        }
    ],
    "sg:phone":"+44 1925 415571",
    "sg:postcode":"WA1 3RY",
    "sg:province":"Cheshire",
    "sg:tags":[
        "video",
        "library"
    ],
    "wof:name":"Jack Beanstalk Video Ltd",
    "wof:placetype":"venue"
},
  "geometry": {"coordinates":[-2.5700318813,53.3985748291],"type":"Point"}
}