{
  "type": "Feature",
  "properties": {
    "addr:full":"Mitre House, The Green, Acle Norwich Norfolk NR13 3QJ",
    "addr:postcode":"nr13 3qj",
    "addr:street":"The Green;Norwich",
    "iso:country":"GB",
    "sg:address":"Mitre House, The Green, Acle",
    "sg:city":"Norwich",
    "sg:classifiers":[
        {
            "category":"Shopping",
            "subcategory":"Clothing, Apparel, & Fashions",
            "type":"Retail Goods"
        }
    ],
    "sg:phone":"+44 1493 751212",
    "sg:postcode":"NR13 3QJ",
    "sg:province":"Norfolk",
    "sg:tags":[
        "shop"
    ],
    "wof:name":"Bishops of Acle",
    "wof:placetype":"venue"
},
  "geometry": {"coordinates":[1.5559569597,52.5946273804],"type":"Point"}
}