{
  "type": "Feature",
  "properties": {
    "addr:full":"G A House, North Weald Airfield, North Weald Epping Essex CM16 6AA",
    "addr:postcode":"cm16 6aa",
    "addr:street":"G",
    "iso:country":"GB",
    "sg:address":"G A House, North Weald Airfield, North Weald",
    "sg:city":"Epping",
    "sg:classifiers":[
        {
            "category":"Retail",
            "subcategory":"Event Space",
            "type":"Services"
        }
    ],
    "sg:phone":"+44 1992 522210",
    "sg:postcode":"CM16 6AA",
    "sg:province":"Essex",
    "sg:tags":[
        "exhibition",
        "organiser"
    ],
    "wof:name":"North Weald Exhibition Services Ltd.",
    "wof:placetype":"venue"
},
  "geometry": {"coordinates":[0.16918,51.717686],"type":"Point"}
}