{
  "type": "Feature",
  "properties": {
    "iso:country":"GB",
    "sg:address":"Spring Gardens Rd",
    "sg:city":"High Wycombe",
    "sg:classifiers":[
        {
            "category":"Home & Garden",
            "subcategory":"Household Appliances",
            "type":"Retail Goods"
        }
    ],
    "sg:phone":"+44 1494 464565",
    "sg:postcode":"HP13 7AG",
    "sg:province":"Buckinghamshire",
    "sg:tags":[
        "refrigeration",
        "air conditioning"
    ],
    "wof:name":"Computerised Building Services Ltd",
    "wof:placetype":"venue"
},
  "geometry": {"coordinates":[-0.729424,51.624058],"type":"Point"}
}