{
  "type": "Feature",
  "properties": {
    "addr:full":"Gables Farm, Lindle La Preston Lancashire PR4 4AU",
    "addr:postcode":"pr4 4au",
    "addr:street":"Lindle La Preston",
    "iso:country":"GB",
    "sg:address":"Gables Farm, Lindle La",
    "sg:city":"Preston",
    "sg:classifiers":[
        {
            "category":"Farming",
            "subcategory":"Farm",
            "type":"Manufacturing & Wholesale Goods"
        }
    ],
    "sg:phone":"+44 1772 614071",
    "sg:postcode":"PR4 4AU",
    "sg:province":"Lancashire",
    "sg:tags":[
        "mixed",
        "crop"
    ],
    "wof:name":"A G Bracewell",
    "wof:placetype":"venue"
},
  "geometry": {"coordinates":[-2.7635,53.715069],"type":"Point"}
}