{
  "type": "Feature",
  "properties": {
    "iso:country":"GB",
    "sg:address":"Church Road, Boldmere",
    "sg:city":"Sutton Coldfield",
    "sg:classifiers":[
        {
            "category":"Arena",
            "subcategory":"Sports Club",
            "type":"Entertainment"
        }
    ],
    "sg:phone":"+44 121 373 4435",
    "sg:postcode":"B73 5RY",
    "sg:province":"West Midlands",
    "wof:name":"Boldmere St. Michael's Football & Athletic Club Ltd.",
    "wof:placetype":"venue"
},
  "geometry": {"coordinates":[-1.8396639824,52.5416297913],"type":"Point"}
}