{
  "type": "Feature",
  "properties": {
    "addr:full":"34 Hillfield Road Hemel Hempstead Hertfordshire HP2 4AB",
    "addr:housenumber":"34",
    "addr:postcode":"hp2 4ab",
    "addr:street":"Hillfield Road",
    "iso:country":"GB",
    "sg:address":"34 Hillfield Road",
    "sg:city":"Hemel Hempstead",
    "sg:classifiers":[
        {
            "category":"Health Services",
            "subcategory":"Nursing And Care Facility",
            "type":"Services"
        }
    ],
    "sg:phone":"+44 1442 230066",
    "sg:postcode":"HP2 4AB",
    "sg:province":"Hertfordshire",
    "sg:tags":[
        "agency"
    ],
    "wof:name":"Hamlin Nursing Agency",
    "wof:placetype":"venue"
},
  "geometry": {"coordinates":[-0.464068,51.752789],"type":"Point"}
}