{
  "type": "Feature",
  "properties": {
    "addr:full":"40-41 Victoria Rd Southampton Hampshire SO31 5DQ",
    "addr:housenumber":"40-41",
    "addr:postcode":"so31 5dq",
    "addr:street":"Victoria Rd",
    "iso:country":"GB",
    "sg:address":"40-41 Victoria Rd",
    "sg:city":"Southampton",
    "sg:classifiers":[
        {
            "category":"Personal",
            "subcategory":"Beauty Salon",
            "type":"Services"
        }
    ],
    "sg:phone":"+44 23 8045 3200",
    "sg:postcode":"SO31 5DQ",
    "sg:province":"Hampshire",
    "wof:name":"Guinot Beauty Salon",
    "wof:placetype":"venue"
},
  "geometry": {"coordinates":[-1.35417,50.874302],"type":"Point"}
}