{
  "type": "Feature",
  "properties": {
    "addr:full":"6 Castle Mews Sunderland Tyne and Wear SR3 3DX",
    "addr:housenumber":"6",
    "addr:postcode":"sr3 3dx",
    "addr:street":"Castle Mews",
    "iso:country":"GB",
    "sg:address":"6 Castle Mews",
    "sg:city":"Sunderland",
    "sg:classifiers":[
        {
            "category":"Retail",
            "subcategory":"Driving School",
            "type":"Services"
        }
    ],
    "sg:postcode":"SR3 3DX",
    "sg:province":"Tyne and Wear",
    "wof:name":"Silksworth School of Motoring",
    "wof:placetype":"venue"
},
  "geometry": {"coordinates":[-1.424766,54.872662],"type":"Point"}
}