{
  "type": "Feature",
  "properties": {
    "iso:country":"GB",
    "sg:address":"88 Old Oak Common Lane, East Acton",
    "sg:city":"London",
    "sg:classifiers":[
        {
            "category":"Health Services",
            "subcategory":"Nursing And Care Facility",
            "type":"Services"
        }
    ],
    "sg:postcode":"W3 7DA",
    "sg:province":"Greater London",
    "sg:tags":[
        "home"
    ],
    "wof:name":"Practical Staffing Ltd",
    "wof:placetype":"venue"
},
  "geometry": {"coordinates":[-0.249048,51.514683],"type":"Point"}
}