{
  "type": "Feature",
  "properties": {
    "addr:full":"Cheadle Road, Alton Stoke-on-trent Staffordshire ST10 4DG",
    "addr:postcode":"st10 4dg",
    "addr:street":"Cheadle Road",
    "iso:country":"GB",
    "sg:address":"Cheadle Road, Alton",
    "sg:city":"Stoke-on-trent",
    "sg:classifiers":[
        {
            "category":"Recreation",
            "subcategory":"Campground",
            "type":"Entertainment"
        }
    ],
    "sg:phone":"+44 1538 702005",
    "sg:postcode":"ST10 4DG",
    "sg:province":"Staffordshire",
    "sg:tags":[
        "caravan",
        "park"
    ],
    "wof:name":"Rainroache Farm Caravan Park",
    "wof:placetype":"venue"
},
  "geometry": {"coordinates":[-1.895513,52.975594],"type":"Point"}
}