{
  "type": "Feature",
  "properties": {
    "addr:full":"72 High Street, Brant Broughton Lincoln Lincolnshire LN5 0RZ",
    "addr:housenumber":"72",
    "addr:postcode":"ln5 0rz",
    "addr:street":"High Street Brant Broughton",
    "iso:country":"GB",
    "sg:address":"72 High Street, Brant Broughton",
    "sg:city":"Lincoln",
    "sg:classifiers":[
        {
            "category":"Bars & Pubs",
            "type":"Food & Drink"
        }
    ],
    "sg:phone":"+44 1400 272119",
    "sg:postcode":"LN5 0RZ",
    "sg:province":"Lincolnshire",
    "sg:tags":[
        "pubs",
        "house",
        "inn",
        "public",
        "activity"
    ],
    "wof:name":"Penny Taylor",
    "wof:placetype":"venue"
},
  "geometry": {"coordinates":[-0.6323000193,53.0777053833],"type":"Point"}
}