{
  "type": "Feature",
  "properties": {
    "iso:country":"GB",
    "sg:address":"126 High Street",
    "sg:city":"West Bromwich",
    "sg:classifiers":[
        {
            "category":"Professional",
            "subcategory":"Computer Services",
            "type":"Services"
        }
    ],
    "sg:postcode":"B70 6JW",
    "sg:province":"West Midlands",
    "sg:tags":[
        "system",
        "software"
    ],
    "wof:name":"S M Rajpura",
    "wof:placetype":"venue"
},
  "geometry": {"coordinates":[-1.9882249832,52.51512146],"type":"Point"}
}