{
  "type": "Feature",
  "properties": {
    "iso:country":"GB",
    "sg:address":"170 Shooters Hill Rd",
    "sg:city":"Blackheath",
    "sg:classifiers":[
        {
            "category":"Food & Beverages",
            "subcategory":"Liquor & Beverages",
            "type":"Retail Goods"
        }
    ],
    "sg:phone":"+44 20 8856 1231",
    "sg:postcode":"SE3 8RP",
    "sg:province":"Greater London",
    "sg:tags":[
        "beer",
        "spirit",
        "wines"
    ],
    "wof:name":"Huttons",
    "wof:placetype":"venue"
},
  "geometry": {"coordinates":[0.033877,51.474781],"type":"Point"}
}