{
  "type": "Feature",
  "properties": {
    "addr:full":"62 Kingston Rd Portsmouth Hampshire PO2 7PA",
    "addr:housenumber":"62",
    "addr:postcode":"hampshire po2 7pa",
    "addr:street":"Kingston Rd",
    "iso:country":"GB",
    "sg:address":"62 Kingston Rd",
    "sg:city":"Portsmouth",
    "sg:classifiers":[
        {
            "category":"Bars & Pubs",
            "type":"Food & Drink"
        }
    ],
    "sg:postcode":"PO2 7PA",
    "sg:province":"Hampshire",
    "sg:tags":[
        "pubs",
        "inn"
    ],
    "wof:name":"Kingston Tavern",
    "wof:placetype":"venue"
},
  "geometry": {"coordinates":[-1.0772789717,50.8082809448],"type":"Point"}
}