{
  "type": "Feature",
  "properties": {
    "iso:country":"GB",
    "sg:address":"The Coach Ho, 60 St Johns Rd",
    "sg:city":"Wallingford",
    "sg:classifiers":[
        {
            "category":"Home & Garden",
            "subcategory":"Household Appliances",
            "type":"Retail Goods"
        }
    ],
    "sg:phone":"+44 1491 826633",
    "sg:postcode":"OX10 9AG",
    "sg:province":"Oxfordshire",
    "sg:tags":[
        "refrigeration",
        "air conditioning"
    ],
    "wof:name":"D S Services",
    "wof:placetype":"venue"
},
  "geometry": {"coordinates":[-1.1256229877,51.6009101868],"type":"Point"}
}