{
  "type": "Feature",
  "properties": {
    "iso:country":"GB",
    "sg:address":"30 Techno Trading Estate, Bramble Road",
    "sg:city":"Swindon",
    "sg:classifiers":[
        {
            "category":"Freight",
            "type":"Transportation"
        }
    ],
    "sg:phone":"+44 1793 436711",
    "sg:postcode":"SN2 8ET",
    "sg:province":"Wiltshire",
    "sg:tags":[
        "airfreight"
    ],
    "wof:name":"Expeditors International (U K) Ltd.",
    "wof:placetype":"venue"
},
  "geometry": {"coordinates":[-1.76266,51.576626],"type":"Point"}
}