{
  "type": "Feature",
  "properties": {
    "addr:full":"Wheel Road, Alpington Norwich Norfolk NR14 7NL",
    "addr:postcode":"nr14 7nl",
    "addr:street":"Wheel Road",
    "iso:country":"GB",
    "sg:address":"Wheel Road, Alpington",
    "sg:city":"Norwich",
    "sg:classifiers":[
        {
            "category":"Bars & Pubs",
            "type":"Food & Drink"
        }
    ],
    "sg:phone":"+44 1508 492712",
    "sg:postcode":"NR14 7NL",
    "sg:province":"Norfolk",
    "sg:tags":[
        "pubs",
        "inn"
    ],
    "wof:name":"The Wheel of Fortune",
    "wof:placetype":"venue"
},
  "geometry": {"coordinates":[1.385028,52.561119],"type":"Point"}
}