{
  "type": "Feature",
  "properties": {
    "iso:country":"GB",
    "sg:address":"26 Somers Road",
    "sg:city":"Rugby",
    "sg:classifiers":[
        {
            "category":"Building & Trades",
            "subcategory":"Construction",
            "type":"Services"
        },
        {
            "category":"Professional",
            "subcategory":"Computer Services",
            "type":"Services"
        }
    ],
    "sg:phone":"+44 871 984 7755",
    "sg:postcode":"CV22 7DH",
    "sg:province":"Warwickshire",
    "sg:tags":[
        "union",
        "software",
        "system",
        "activity"
    ],
    "wof:name":"Stak Trading Computer Services Ltd.",
    "wof:placetype":"venue"
},
  "geometry": {"coordinates":[-1.287427,52.372803],"type":"Point"}
}