{
  "type": "Feature",
  "properties": {
    "addr:full":"Unit 1 Ipswich Suffolk IP4 1DL",
    "addr:housenumber":"unit 1",
    "addr:postcode":"ip4 1dl",
    "iso:country":"GB",
    "sg:address":"Unit 1",
    "sg:city":"Ipswich",
    "sg:classifiers":[
        {
            "category":"Professional",
            "subcategory":"Printing & Photocopies",
            "type":"Services"
        }
    ],
    "sg:phone":"+44 1473 212751",
    "sg:postcode":"IP4 1DL",
    "sg:province":"Suffolk",
    "sg:tags":[
        "process",
        "screen",
        "printer"
    ],
    "wof:name":"Clearscore Ltd",
    "wof:placetype":"venue"
},
  "geometry": {"coordinates":[1.15484,52.054668],"type":"Point"}
}