{
  "type": "Feature",
  "properties": {
    "addr:full":"Unit 12 Inmosthay, Eastern Lane Portland Dorset DT5 2JS",
    "addr:housenumber":"unit 12",
    "addr:postcode":"dt5 2js",
    "addr:street":"Inmosthay Eastern Lane",
    "iso:country":"GB",
    "sg:address":"Unit 12 Inmosthay, Eastern Lane",
    "sg:city":"Portland",
    "sg:classifiers":[
        {
            "category":"Autos & Motor Vehicles",
            "subcategory":"Automobile Sales",
            "type":"Retail Goods"
        },
        {
            "category":"Retail",
            "subcategory":"Auto Repair",
            "type":"Services"
        }
    ],
    "sg:phone":"+44 1305 821414",
    "sg:postcode":"DT5 2JS",
    "sg:province":"Dorset",
    "sg:tags":[
        "modification",
        "garage",
        "car"
    ],
    "wof:name":"Southwell Motor Services",
    "wof:placetype":"venue"
},
  "geometry": {"coordinates":[-2.438028,50.551411],"type":"Point"}
}