{
  "type": "Feature",
  "properties": {
    "iso:country":"GB",
    "sg:address":"437 Birmingham Road",
    "sg:city":"Redditch",
    "sg:classifiers":[
        {
            "category":"Real Estate",
            "subcategory":"Real Estate Services",
            "type":"Services"
        },
        {
            "category":"Building & Trades",
            "subcategory":"Equipment Rental",
            "type":"Services"
        }
    ],
    "sg:phone":"+44 1527 68512",
    "sg:postcode":"B97 6RL",
    "sg:province":"Warwickshire",
    "sg:tags":[
        "hire",
        "leasing",
        "plant",
        "machinery"
    ],
    "wof:name":"J M S Plant Hire",
    "wof:placetype":"venue"
},
  "geometry": {"coordinates":[-1.946408,52.329201],"type":"Point"}
}