{
  "type": "Feature",
  "properties": {
    "iso:country":"GB",
    "sg:address":"1 Tavern La",
    "sg:city":"Daventry",
    "sg:classifiers":[
        {
            "category":"Real Estate",
            "subcategory":"Architect",
            "type":"Services"
        }
    ],
    "sg:postcode":"NN11 4ET",
    "sg:province":"Northamptonshire",
    "wof:name":"H D A Architects",
    "wof:placetype":"venue"
},
  "geometry": {"coordinates":[-1.1647850275,52.2573318481],"type":"Point"}
}