{
  "type": "Feature",
  "properties": {
    "addr:full":"27 Deerpark Crescent, Wingerworth Chesterfield Derbyshire S42 6XE",
    "addr:housenumber":"27",
    "addr:postcode":"s42 6xe",
    "addr:street":"Deerpark Crescent",
    "iso:country":"GB",
    "sg:address":"27 Deerpark Crescent, Wingerworth",
    "sg:city":"Chesterfield",
    "sg:classifiers":[
        {
            "category":"Home & Garden",
            "subcategory":"Carpets & Floor Coverings",
            "type":"Retail Goods"
        }
    ],
    "sg:postcode":"S42 6XE",
    "sg:province":"Derbyshire",
    "sg:tags":[
        "cleaner",
        "upholstery"
    ],
    "wof:name":"Michael Cox",
    "wof:placetype":"venue"
},
  "geometry": {"coordinates":[-1.4344359636,53.1987495422],"type":"Point"}
}