{
  "type": "Feature",
  "properties": {
    "iso:country":"GB",
    "sg:address":"Ashford",
    "sg:city":"Barnstaple",
    "sg:classifiers":[
        {
            "category":"Home & Garden",
            "subcategory":"Garden Supply",
            "type":"Retail Goods"
        }
    ],
    "sg:phone":"+44 1271 342880",
    "sg:postcode":"EX31 4BW",
    "sg:province":"Devon",
    "sg:tags":[
        "nursery",
        "centre"
    ],
    "wof:name":"North Devon Garden Centre",
    "wof:placetype":"venue"
},
  "geometry": {"coordinates":[-4.0998702049,51.0966682434],"type":"Point"}
}