{
  "type": "Feature",
  "properties": {
    "iso:country":"GB",
    "sg:address":"Greenfield Avenue, Glyncoch",
    "sg:city":"Pontypridd",
    "sg:classifiers":[
        {
            "category":"Education",
            "subcategory":"School",
            "type":"Public Place"
        }
    ],
    "sg:phone":"+44 1443 486826",
    "sg:postcode":"CF37 3BD",
    "sg:province":"Caerphilly",
    "sg:tags":[
        "local",
        "authority"
    ],
    "wof:name":"Cefn Primary School",
    "wof:placetype":"venue"
},
  "geometry": {"coordinates":[-3.338459,51.623482],"type":"Point"}
}