{
  "type": "Feature",
  "properties": {
    "addr:full":"112 The Broadway London Greater London SW19 1RH",
    "addr:housenumber":"112",
    "addr:postcode":"sw19 1rh",
    "addr:street":"The Broadway",
    "iso:country":"GB",
    "sg:address":"112 The Broadway",
    "sg:city":"London",
    "sg:classifiers":[
        {
            "category":"Cafe",
            "type":"Food & Drink"
        }
    ],
    "sg:phone":"+44 20 8540 4868",
    "sg:postcode":"SW19 1RH",
    "sg:province":"Greater London",
    "sg:tags":[
        "tea",
        "room"
    ],
    "wof:name":"Maksim",
    "wof:placetype":"venue"
},
  "geometry": {"coordinates":[-0.20089,51.419468],"type":"Point"}
}