{
  "type": "Feature",
  "properties": {
    "iso:country":"GB",
    "sg:address":"Wallbridge",
    "sg:city":"Stroud",
    "sg:classifiers":[
        {
            "category":"Travel",
            "subcategory":"Hotels & Motels",
            "type":"Entertainment"
        }
    ],
    "sg:phone":"+44 1453 763556",
    "sg:postcode":"GL5 3JS",
    "sg:province":"Gloucestershire",
    "wof:name":"Bell Hotel",
    "wof:placetype":"venue"
},
  "geometry": {"coordinates":[-2.2224400043,51.7437782288],"type":"Point"}
}