{
  "type": "Feature",
  "properties": {
    "iso:country":"GB",
    "sg:address":"Ground Floor, Whiteleys Centre, Queensway",
    "sg:city":"London",
    "sg:classifiers":[
        {
            "category":"Shopping",
            "subcategory":"Clothing, Apparel, & Fashions",
            "type":"Retail Goods"
        }
    ],
    "sg:phone":"+44 20 7792 0400",
    "sg:postcode":"W2 4QG",
    "sg:province":"Greater London",
    "sg:tags":[
        "menswear"
    ],
    "wof:name":"Cecil Gee",
    "wof:placetype":"venue"
},
  "geometry": {"coordinates":[-0.18773,51.512501],"type":"Point"}
}