{
  "type": "Feature",
  "properties": {
    "addr:full":"5 Elmfield Court, Liphook Road, Lindford Bordon Hampshire GU35 0QA",
    "addr:housenumber":"5",
    "addr:postcode":"gu35 0qa",
    "addr:street":"Elmfield Court Liphook Road",
    "iso:country":"GB",
    "sg:address":"5 Elmfield Court, Liphook Road, Lindford",
    "sg:city":"Bordon",
    "sg:classifiers":[
        {
            "category":"Food & Beverages",
            "subcategory":"Groceries & Convenience Stores",
            "type":"Retail Goods"
        }
    ],
    "sg:phone":"+44 1420 472870",
    "sg:postcode":"GU35 0QA",
    "sg:province":"Hampshire",
    "wof:name":"One Stop Community Stores Ltd.",
    "wof:placetype":"venue"
},
  "geometry": {"coordinates":[-0.8434619904,51.1209220886],"type":"Point"}
}