{
  "type": "Feature",
  "properties": {
    "addr:full":"30 Railway Side, Barnes London Greater London SW13 0PN",
    "addr:housenumber":"30",
    "addr:postcode":"sw13 0pn",
    "addr:street":"Railway Side",
    "iso:country":"GB",
    "sg:address":"30 Railway Side, Barnes",
    "sg:city":"London",
    "sg:classifiers":[
        {
            "category":"Professional",
            "subcategory":"Computer Services",
            "type":"Services"
        }
    ],
    "sg:postcode":"SW13 0PN",
    "sg:province":"Greater London",
    "sg:tags":[
        "system",
        "software"
    ],
    "wof:name":"Axiomaesis Ltd",
    "wof:placetype":"venue"
},
  "geometry": {"coordinates":[-0.2519420087,51.4686660767],"type":"Point"}
}