{
  "type": "Feature",
  "properties": {
    "iso:country":"GB",
    "sg:address":"50 Whinhill Road",
    "sg:city":"Ayr",
    "sg:classifiers":[
        {
            "category":"Social Services",
            "subcategory":"Adult Care",
            "type":"Services"
        }
    ],
    "sg:phone":"+44 1292 441372",
    "sg:postcode":"KA7 4RP",
    "sg:province":"South Ayrshire",
    "sg:tags":[
        "domestic",
        "cleaning"
    ],
    "wof:name":"Selclene",
    "wof:placetype":"venue"
},
  "geometry": {"coordinates":[-4.617544,55.43684],"type":"Point"}
}