{
  "type": "Feature",
  "properties": {
    "iso:country":"GB",
    "sg:address":"Abbeyfield House, Dovedale Close, High Lane",
    "sg:city":"Stockport",
    "sg:classifiers":[
        {
            "category":"Organizations",
            "subcategory":"Community Association",
            "type":"Services"
        }
    ],
    "sg:phone":"+44 1663 764498",
    "sg:postcode":"SK6 8DU",
    "sg:province":"Cheshire",
    "sg:tags":[
        "society",
        "housing"
    ],
    "wof:name":"Abbeyfield High Lane Society Ltd.",
    "wof:placetype":"venue"
},
  "geometry": {"coordinates":[-2.072588,53.365604],"type":"Point"}
}