{
  "type": "Feature",
  "properties": {
    "addr:full":"27 Quarry Rd Witney Oxfordshire OX8 5JS",
    "addr:housenumber":"27",
    "addr:postcode":"ox8 5js",
    "addr:street":"Quarry Rd",
    "iso:country":"GB",
    "sg:address":"27 Quarry Rd",
    "sg:city":"Witney",
    "sg:classifiers":[
        {
            "category":"Retail",
            "subcategory":"Repair Shop",
            "type":"Services"
        }
    ],
    "sg:phone":"+44 1993 779761",
    "sg:postcode":"OX8 5JS",
    "sg:province":"Oxfordshire",
    "sg:tags":[
        "maintenance"
    ],
    "wof:name":"K J Property Maintenance Services",
    "wof:placetype":"venue"
},
  "geometry": {"coordinates":[-1.4883110523,51.795791626],"type":"Point"}
}