{
  "type": "Feature",
  "properties": {
    "addr:full":"2 Richfield Pl, 12 Richfield Ave Reading Berkshire RG1 8EQ",
    "addr:housenumber":"2;12",
    "addr:postcode":"rg1 8eq",
    "addr:street":"Richfield Pl;Richfield Ave",
    "iso:country":"GB",
    "sg:address":"2 Richfield Pl, 12 Richfield Ave",
    "sg:city":"Reading",
    "sg:classifiers":[
        {
            "category":"Professional",
            "subcategory":"Advertising",
            "type":"Services"
        }
    ],
    "sg:postcode":"RG1 8EQ",
    "sg:province":"Berkshire",
    "sg:tags":[
        "agency"
    ],
    "wof:name":"Delaney,Michael,",
    "wof:placetype":"venue"
},
  "geometry": {"coordinates":[-0.9630089998,51.4535217285],"type":"Point"}
}