{
  "type": "Feature",
  "properties": {
    "iso:country":"GB",
    "sg:address":"27 Cape Hill",
    "sg:city":"Smethwick",
    "sg:classifiers":[
        {
            "category":"Shopping",
            "subcategory":"Crafts & Fabrics",
            "type":"Retail Goods"
        }
    ],
    "sg:phone":"+44 121 558 8208",
    "sg:postcode":"B66 4RX",
    "sg:province":"West Midlands",
    "sg:tags":[
        "machine",
        "sewing",
        "knitting",
        "centre"
    ],
    "wof:name":"Tame Sewing Centre",
    "wof:placetype":"venue"
},
  "geometry": {"coordinates":[-1.960541,52.4869],"type":"Point"}
}