{
  "type": "Feature",
  "properties": {
    "addr:full":"Unit G Riverside Business Centre, Haldane Place London Greater London SW18 4UQ",
    "addr:housenumber":"unit g;business",
    "addr:postcode":"sw18 4uq",
    "addr:street":"Haldane Place",
    "iso:country":"GB",
    "sg:address":"Unit G Riverside Business Centre, Haldane Place",
    "sg:city":"London",
    "sg:classifiers":[
        {
            "category":"Shopping",
            "subcategory":"Stationery & Office Supplies",
            "type":"Retail Goods"
        },
        {
            "category":"Shopping",
            "subcategory":"Computers & Home Electronics",
            "type":"Retail Goods"
        }
    ],
    "sg:phone":"+44 20 8875 0099",
    "sg:postcode":"SW18 4UQ",
    "sg:province":"Greater London",
    "sg:tags":[
        "printers'",
        "consumables"
    ],
    "wof:name":"Schriftbild und Image (U K) Ltd.",
    "wof:placetype":"venue"
},
  "geometry": {"coordinates":[-0.1928499937,51.4459686279],"type":"Point"}
}