{
  "type": "Feature",
  "properties": {
    "addr:full":"A38 Alfreton Derbyshire DE55 1HJ",
    "addr:postcode":"de55 1hj",
    "iso:country":"GB",
    "sg:address":"A38",
    "sg:city":"Alfreton",
    "sg:classifiers":[
        {
            "category":"Autos & Motor Vehicles",
            "subcategory":"Fuel & Gas Station",
            "type":"Retail Goods"
        }
    ],
    "sg:phone":"+44 1773 830971",
    "sg:postcode":"DE55 1HJ",
    "sg:province":"Derbyshire",
    "sg:tags":[
        "hr",
        "petrol"
    ],
    "wof:name":"Granada Motorway Services",
    "wof:placetype":"venue"
},
  "geometry": {"coordinates":[-1.4087280035,53.0827827454],"type":"Point"}
}