{
  "type": "Feature",
  "properties": {
    "addr:full":"3 Park Road Peterborough Cambridgeshire PE1 2HX",
    "addr:housenumber":"3",
    "addr:postcode":"pe1 2hx",
    "addr:street":"Park Road",
    "iso:country":"GB",
    "sg:address":"3 Park Road",
    "sg:city":"Peterborough",
    "sg:classifiers":[
        {
            "category":"Travel",
            "subcategory":"Travel Agent",
            "type":"Entertainment"
        }
    ],
    "sg:phone":"+44 1733 340333",
    "sg:postcode":"PE1 2HX",
    "sg:province":"Cambridgeshire",
    "wof:name":"Lonsdale Travel Ltd.",
    "wof:placetype":"venue"
},
  "geometry": {"coordinates":[-0.2378789932,52.5846443176],"type":"Point"}
}