{
  "type": "Feature",
  "properties": {
    "iso:country":"GB",
    "sg:address":"181 London Road",
    "sg:city":"Bexhill-on-sea",
    "sg:classifiers":[
        {
            "category":"Health Services",
            "subcategory":"Clinic",
            "type":"Services"
        }
    ],
    "sg:phone":"+44 1424 216290",
    "sg:postcode":"TN39 4AB",
    "sg:province":"East Sussex",
    "sg:tags":[
        "nh"
    ],
    "wof:name":"Bexhill Clinic",
    "wof:placetype":"venue"
},
  "geometry": {"coordinates":[0.469636,50.848969],"type":"Point"}
}