{
  "type": "Feature",
  "properties": {
    "addr:full":"4 Sheaf Street Daventry Northamptonshire NN11 4AB",
    "addr:housenumber":"4",
    "addr:postcode":"nn11 4ab",
    "addr:street":"Sheaf Street",
    "iso:country":"GB",
    "sg:address":"4 Sheaf Street",
    "sg:city":"Daventry",
    "sg:classifiers":[
        {
            "category":"Shopping",
            "subcategory":"News",
            "type":"Retail Goods"
        }
    ],
    "sg:phone":"+44 1327 702722",
    "sg:postcode":"NN11 4AB",
    "sg:province":"Northamptonshire",
    "sg:tags":[
        "newsagent"
    ],
    "wof:name":"Sheaf Street News",
    "wof:placetype":"venue"
},
  "geometry": {"coordinates":[-1.1629110575,52.2560768127],"type":"Point"}
}