{
  "type": "Feature",
  "properties": {
    "addr:full":"394 Railway Arches London Greater London E2 8HZ",
    "addr:housenumber":"394",
    "addr:postcode":"e2 8hz",
    "addr:street":"Railway Arches",
    "iso:country":"GB",
    "sg:address":"394 Railway Arches",
    "sg:city":"London",
    "sg:classifiers":[
        {
            "category":"Manufacturing",
            "subcategory":"Wood Products",
            "type":"Manufacturing & Wholesale Goods"
        }
    ],
    "sg:phone":"+44 20 7739 6170",
    "sg:postcode":"E2 8HZ",
    "sg:province":"Greater London",
    "sg:tags":[
        "woodturning"
    ],
    "wof:name":"S Grisley & Son Ltd.",
    "wof:placetype":"venue"
},
  "geometry": {"coordinates":[-0.0758100003,51.5321006775],"type":"Point"}
}