{
  "type": "Feature",
  "properties": {
    "addr:full":"Nunthorpe Oaks, 114 Guisborough Road Middlesbrough North Yorkshire TS7 0JA",
    "addr:housenumber":"114",
    "addr:postcode":"ts7 0ja",
    "addr:street":"Nunthorpe;Guisborough Road",
    "iso:country":"GB",
    "sg:address":"Nunthorpe Oaks, 114 Guisborough Road",
    "sg:city":"Middlesbrough",
    "sg:classifiers":[
        {
            "category":"Building & Trades",
            "subcategory":"Construction",
            "type":"Services"
        }
    ],
    "sg:postcode":"TS7 0JA",
    "sg:province":"North Yorkshire",
    "sg:tags":[
        "contractor"
    ],
    "wof:name":"Geffen Construction Ltd.",
    "wof:placetype":"venue"
},
  "geometry": {"coordinates":[-1.16978,54.52729],"type":"Point"}
}