{
  "type": "Feature",
  "properties": {
    "iso:country":"GB",
    "sg:address":"Unit 62h, Perth Aerodrome, Scone",
    "sg:city":"Perth",
    "sg:classifiers":[
        {
            "category":"Building & Trades",
            "subcategory":"Landscaping Services",
            "type":"Services"
        }
    ],
    "sg:phone":"+44 1738 553390",
    "sg:postcode":"PH2 6PL",
    "sg:province":"Perth and Kinross",
    "sg:tags":[
        "forestry",
        "tree"
    ],
    "wof:name":"Tayside Native Woodlands",
    "wof:placetype":"venue"
},
  "geometry": {"coordinates":[-3.432414,56.396053],"type":"Point"}
}