{
  "type": "Feature",
  "properties": {
    "addr:full":"Units 2/3 Trafford Park Road, Newbridge, Trafford Park Manchester Cheshire M17 1HG",
    "addr:housenumber":"units 2 / 3",
    "addr:postcode":"m17 1hg",
    "addr:street":"Trafford Park Road;Trafford Park",
    "iso:country":"GB",
    "sg:address":"Units 2/3 Trafford Park Road, Newbridge, Trafford Park",
    "sg:city":"Manchester",
    "sg:classifiers":[
        {
            "category":"Building & Trades",
            "subcategory":"Cleaning & Sanitation",
            "type":"Services"
        }
    ],
    "sg:phone":"+44 161 877 4677",
    "sg:postcode":"M17 1HG",
    "sg:province":"Cheshire",
    "sg:tags":[
        "steam"
    ],
    "wof:name":"Bymond Ltd.",
    "wof:placetype":"venue"
},
  "geometry": {"coordinates":[-2.3083589077,53.4681396484],"type":"Point"}
}