{
  "type": "Feature",
  "properties": {
    "iso:country":"GB",
    "sg:address":"8 Ouseburn Avenue",
    "sg:city":"York",
    "sg:classifiers":[
        {
            "category":"Building & Trades",
            "subcategory":"Construction",
            "type":"Services"
        }
    ],
    "sg:postcode":"YO26 5NN",
    "sg:province":"North Yorkshire",
    "sg:tags":[
        "decorator",
        "painter"
    ],
    "wof:name":"M S Decor & Maintenance",
    "wof:placetype":"venue"
},
  "geometry": {"coordinates":[-1.127371,53.966221],"type":"Point"}
}