{
  "type": "Feature",
  "properties": {
    "iso:country":"GB",
    "sg:address":"257 Kingsway",
    "sg:city":"Manchester",
    "sg:classifiers":[
        {
            "category":"Food & Beverages",
            "subcategory":"Bakery",
            "type":"Retail Goods"
        }
    ],
    "sg:phone":"+44 161 442 2921",
    "sg:postcode":"M19 1AN",
    "sg:province":"Greater Manchester",
    "sg:tags":[
        "pizza"
    ],
    "wof:name":"Saqib Hussain",
    "wof:placetype":"venue"
},
  "geometry": {"coordinates":[-2.2103190422,53.4273605347],"type":"Point"}
}