{
  "type": "Feature",
  "properties": {
    "addr:full":"14 Birmingham Road, Great Barr Birmingham West Midlands B43 6NR",
    "addr:housenumber":"14",
    "addr:postcode":"b43 6nr",
    "addr:street":"Birmingham Road",
    "iso:country":"GB",
    "sg:address":"14 Birmingham Road, Great Barr",
    "sg:city":"Birmingham",
    "sg:classifiers":[
        {
            "category":"Personal",
            "subcategory":"Beauty Salon",
            "type":"Services"
        }
    ],
    "sg:phone":"+44 121 357 2426",
    "sg:postcode":"B43 6NR",
    "sg:province":"West Midlands",
    "sg:tags":[
        "unisex",
        "hairdresser"
    ],
    "wof:name":"Chequers Hair Studio",
    "wof:placetype":"venue"
},
  "geometry": {"coordinates":[-1.9349280596,52.5469398499],"type":"Point"}
}