{
  "type": "Feature",
  "properties": {
    "iso:country":"GB",
    "sg:address":"Bridge Farm, Bilsington",
    "sg:city":"Ashford",
    "sg:classifiers":[
        {
            "category":"Farming",
            "subcategory":"Livestock Farm",
            "type":"Manufacturing & Wholesale Goods"
        }
    ],
    "sg:postcode":"TN25 7JZ",
    "sg:province":"Kent",
    "sg:tags":[
        "others"
    ],
    "wof:name":"H Crump & Son",
    "wof:placetype":"venue"
},
  "geometry": {"coordinates":[0.9111149907,51.0727386475],"type":"Point"}
}