{
  "type": "Feature",
  "properties": {
    "iso:country":"GB",
    "sg:address":"Frederick St",
    "sg:city":"Bolton",
    "sg:classifiers":[
        {
            "category":"Shopping",
            "subcategory":"Discount & Variety Stores",
            "type":"Retail Goods"
        }
    ],
    "sg:phone":"+44 1204 571217",
    "sg:postcode":"BL4 9AL",
    "sg:province":"Lancashire",
    "sg:tags":[
        "centre"
    ],
    "wof:name":"Supasave",
    "wof:placetype":"venue"
},
  "geometry": {"coordinates":[-2.3923039436,53.5463600159],"type":"Point"}
}