{
  "type": "Feature",
  "properties": {
    "addr:full":"294 Haunch Lane, Kings Heath Birmingham West Midlands B13 0QS",
    "addr:housenumber":"294",
    "addr:postcode":"b13 0qs",
    "addr:street":"Haunch Lane",
    "iso:country":"GB",
    "sg:address":"294 Haunch Lane, Kings Heath",
    "sg:city":"Birmingham",
    "sg:classifiers":[
        {
            "category":"Personal",
            "subcategory":"Barber",
            "type":"Services"
        }
    ],
    "sg:phone":"+44 121 443 2684",
    "sg:postcode":"B13 0QS",
    "sg:province":"West Midlands",
    "sg:tags":[
        "men's",
        "hairdresser"
    ],
    "wof:name":"Davids Hairdressers",
    "wof:placetype":"venue"
},
  "geometry": {"coordinates":[-1.8788330555,52.4212760925],"type":"Point"}
}