{
  "type": "Feature",
  "properties": {
    "addr:full":"21-39 Candleriggs Glasgow Glasgow City G1 1LD",
    "addr:housenumber":"21-39",
    "addr:postcode":"g1 1ld",
    "addr:street":"Candleriggs",
    "iso:country":"GB",
    "sg:address":"21-39 Candleriggs",
    "sg:city":"Glasgow",
    "sg:classifiers":[
        {
            "category":"Shopping",
            "subcategory":"Department Store",
            "type":"Retail Goods"
        }
    ],
    "sg:phone":"+44 141 552 1024",
    "sg:postcode":"G1 1LD",
    "sg:province":"Glasgow City",
    "wof:name":"Weisfelds PLC",
    "wof:placetype":"venue"
},
  "geometry": {"coordinates":[-4.246366,55.857487],"type":"Point"}
}