{
  "type": "Feature",
  "properties": {
    "iso:country":"GB",
    "sg:address":"The New Shopping Hall, Bell Walk",
    "sg:city":"Uckfield",
    "sg:classifiers":[
        {
            "category":"Farming",
            "subcategory":"Fish & Marine Products",
            "type":"Manufacturing & Wholesale Goods"
        }
    ],
    "sg:phone":"+44 1825 764262",
    "sg:postcode":"TN22 1QX",
    "sg:province":"East Sussex",
    "sg:tags":[
        "fishmonger"
    ],
    "wof:name":"Toby George",
    "wof:placetype":"venue"
},
  "geometry": {"coordinates":[0.0966499969,50.9718132019],"type":"Point"}
}