{
  "type": "Feature",
  "properties": {
    "iso:country":"GB",
    "sg:address":"P.o Box 353 St. Andrews Rd",
    "sg:city":"Cambridge",
    "sg:classifiers":[
        {
            "category":"Communications",
            "type":"Services"
        }
    ],
    "sg:phone":"+44 1223 442000",
    "sg:postcode":"CB4 1EQ",
    "sg:province":"Cambridgeshire",
    "sg:tags":[
        "telecommunication"
    ],
    "wof:name":"Advantra Ltd",
    "wof:placetype":"venue"
},
  "geometry": {"coordinates":[0.13965,52.214409],"type":"Point"}
}