{
  "type": "Feature",
  "properties": {
    "addr:full":"Beech Tree Farm, Marksbury Bath Somerset BA2 9HQ",
    "addr:postcode":"ba2 9hq",
    "addr:street":"Beech",
    "iso:country":"GB",
    "sg:address":"Beech Tree Farm, Marksbury",
    "sg:city":"Bath",
    "sg:classifiers":[
        {
            "category":"Home & Garden",
            "subcategory":"Garden Supply",
            "type":"Retail Goods"
        },
        {
            "category":"Sports & Exercise",
            "subcategory":"Stables",
            "type":"Entertainment"
        },
        {
            "category":"Farming",
            "subcategory":"Livestock Farm",
            "type":"Manufacturing & Wholesale Goods"
        }
    ],
    "sg:phone":"+44 1761 472305",
    "sg:postcode":"BA2 9HQ",
    "sg:province":"Somerset",
    "sg:tags":[
        "equestrian",
        "centre",
        "bulb",
        "livery",
        "others",
        "schools",
        "riding",
        "grower"
    ],
    "wof:name":"P S Collins",
    "wof:placetype":"venue"
},
  "geometry": {"coordinates":[-2.438089,51.361771],"type":"Point"}
}