{
  "type": "Feature",
  "properties": {
    "iso:country":"GB",
    "sg:address":"242 Camden High Street",
    "sg:city":"London",
    "sg:classifiers":[
        {
            "category":"Shopping",
            "subcategory":"Clothing, Apparel, & Fashions",
            "type":"Retail Goods"
        }
    ],
    "sg:postcode":"NW1 8QS",
    "sg:province":"Greater London",
    "sg:tags":[
        "shop"
    ],
    "wof:name":"Aries Fashion Ltd",
    "wof:placetype":"venue"
},
  "geometry": {"coordinates":[-0.144543,51.541161],"type":"Point"}
}