{
  "type": "Feature",
  "properties": {
    "iso:country":"GB",
    "sg:address":"38 Brackley Street, Farnworth",
    "sg:city":"Bolton",
    "sg:classifiers":[
        {
            "category":"Farming",
            "subcategory":"Fish & Marine Products",
            "type":"Manufacturing & Wholesale Goods"
        },
        {
            "category":"Food & Beverages",
            "subcategory":"Meat & Fish",
            "type":"Retail Goods"
        }
    ],
    "sg:phone":"+44 1204 577862",
    "sg:postcode":"BL4 9DR",
    "sg:province":"Lancashire",
    "sg:tags":[
        "fishmonger",
        "butcher"
    ],
    "wof:name":"Grahams Butchers",
    "wof:placetype":"venue"
},
  "geometry": {"coordinates":[-2.3940770626,53.5480003357],"type":"Point"}
}