{
  "type": "Feature",
  "properties": {
    "addr:full":"140 High Street, Rainham Gillingham Kent ME8 8AR",
    "addr:housenumber":"140",
    "addr:postcode":"me8 8ar",
    "addr:street":"High Street",
    "iso:country":"GB",
    "sg:address":"140 High Street, Rainham",
    "sg:city":"Gillingham",
    "sg:classifiers":[
        {
            "category":"Personal",
            "type":"Services"
        }
    ],
    "sg:postcode":"ME8 8AR",
    "sg:province":"Kent",
    "sg:tags":[
        "wedding"
    ],
    "wof:name":"P Hughes",
    "wof:placetype":"venue"
},
  "geometry": {"coordinates":[0.612146,51.362354],"type":"Point"}
}