{
  "type": "Feature",
  "properties": {
    "addr:full":"Titterstone Farm, Clee Hill Ludlow Herefordshire SY8 3PW",
    "addr:postcode":"sy8 3pw",
    "addr:street":"Clee Hill",
    "iso:country":"GB",
    "sg:address":"Titterstone Farm, Clee Hill",
    "sg:city":"Ludlow",
    "sg:classifiers":[
        {
            "category":"Farming",
            "subcategory":"Farm",
            "type":"Manufacturing & Wholesale Goods"
        }
    ],
    "sg:phone":"+44 1584 890272",
    "sg:postcode":"SY8 3PW",
    "sg:province":"Herefordshire",
    "sg:tags":[
        "mixed",
        "crop"
    ],
    "wof:name":"I J Barnett & Son",
    "wof:placetype":"venue"
},
  "geometry": {"coordinates":[-2.7190139294,52.3705940247],"type":"Point"}
}