{
  "type": "Feature",
  "properties": {
    "addr:full":"10 Coventry Road, Bedworth Nuneaton Warwickshire CV12 8NN",
    "addr:housenumber":"10",
    "addr:postcode":"cv12 8nn",
    "addr:street":"Coventry Road",
    "iso:country":"GB",
    "sg:address":"10 Coventry Road, Bedworth",
    "sg:city":"Nuneaton",
    "sg:classifiers":[
        {
            "category":"Organizations",
            "subcategory":"Community Association",
            "type":"Services"
        },
        {
            "category":"Organizations",
            "subcategory":"Political Organization",
            "type":"Services"
        }
    ],
    "sg:phone":"+44 24 7631 2129",
    "sg:postcode":"CV12 8NN",
    "sg:province":"Warwickshire",
    "sg:tags":[
        "club",
        "party",
        "social"
    ],
    "wof:name":"Bedworth Conservative Club Ltd",
    "wof:placetype":"venue"
},
  "geometry": {"coordinates":[-1.472052,52.477425],"type":"Point"}
}