{
  "type": "Feature",
  "properties": {
    "addr:full":"53 Alloway Street Ayr South Ayrshire KA7 1SP",
    "addr:housenumber":"53",
    "addr:postcode":"ka7 1sp",
    "addr:street":"Alloway Street",
    "iso:country":"GB",
    "sg:address":"53 Alloway Street",
    "sg:city":"Ayr",
    "sg:classifiers":[
        {
            "category":"Shopping",
            "subcategory":"News",
            "type":"Retail Goods"
        }
    ],
    "sg:phone":"+44 1292 610064",
    "sg:postcode":"KA7 1SP",
    "sg:province":"South Ayrshire",
    "sg:tags":[
        "newsagent"
    ],
    "wof:name":"R S McColl",
    "wof:placetype":"venue"
},
  "geometry": {"coordinates":[-4.6287579536,55.4592552185],"type":"Point"}
}