{
  "type": "Feature",
  "properties": {
    "iso:country":"GB",
    "sg:address":"44-46 High Street",
    "sg:city":"Worthing",
    "sg:classifiers":[
        {
            "category":"Professional",
            "type":"Services"
        },
        {
            "category":"Real Estate",
            "subcategory":"Real Estate Agent",
            "type":"Services"
        }
    ],
    "sg:phone":"+44 1903 237777",
    "sg:postcode":"BN11 1LL",
    "sg:province":"West Sussex",
    "sg:tags":[
        "auctioneer"
    ],
    "wof:name":"R H Ellis & Sons",
    "wof:placetype":"venue"
},
  "geometry": {"coordinates":[-0.367867,50.813576],"type":"Point"}
}