{
  "type": "Feature",
  "properties": {
    "iso:country":"GB",
    "sg:address":"Lees Hall Golf Club, Hemsworth Road",
    "sg:city":"Sheffield",
    "sg:classifiers":[
        {
            "category":"Sports & Exercise",
            "subcategory":"Golf",
            "type":"Entertainment"
        }
    ],
    "sg:phone":"+44 114 250 7868",
    "sg:postcode":"S8 8LL",
    "sg:province":"Derbyshire",
    "sg:tags":[
        "equipment"
    ],
    "wof:name":"Golf Professional Shop",
    "wof:placetype":"venue"
},
  "geometry": {"coordinates":[-1.467362,53.339966],"type":"Point"}
}