{
  "type": "Feature",
  "properties": {
    "addr:full":"1 Guardian Court, Moorend Road, Charlton Kings Cheltenham Gloucestershire GL53 9DP",
    "addr:housenumber":"1",
    "addr:postcode":"gl53 9dp",
    "addr:street":"Guardian Court Moorend Road",
    "iso:country":"GB",
    "sg:address":"1 Guardian Court, Moorend Road, Charlton Kings",
    "sg:city":"Cheltenham",
    "sg:classifiers":[
        {
            "category":"Organizations",
            "subcategory":"Community Association",
            "type":"Services"
        }
    ],
    "sg:postcode":"GL53 9DP",
    "sg:province":"Gloucestershire",
    "sg:tags":[
        "society",
        "housing"
    ],
    "wof:name":"Guardian Retirement Housing",
    "wof:placetype":"venue"
},
  "geometry": {"coordinates":[-2.06013,51.883724],"type":"Point"}
}