{
  "type": "Feature",
  "properties": {
    "iso:country":"GB",
    "sg:address":"Unit 2, Viscount Industrial Estate",
    "sg:city":"Slough",
    "sg:classifiers":[
        {
            "category":"Government",
            "subcategory":"Post Office",
            "type":"Public Place"
        }
    ],
    "sg:phone":"+44 1753 682974",
    "sg:postcode":"SL3 0DF",
    "sg:province":"Berkshire",
    "sg:tags":[
        "messenger",
        "courier"
    ],
    "wof:name":"Rapid Air Express (U K) Ltd.",
    "wof:placetype":"venue"
},
  "geometry": {"coordinates":[-0.5164999962,51.4707984924],"type":"Point"}
}