{
  "type": "Feature",
  "properties": {
    "addr:full":"Wakefield House Care Home, Seafield Place, Cullen Buckie Moray AB56 4TE",
    "addr:postcode":"ab56 4te",
    "addr:street":"Seafield Place",
    "iso:country":"GB",
    "sg:address":"Wakefield House Care Home, Seafield Place, Cullen",
    "sg:city":"Buckie",
    "sg:classifiers":[
        {
            "category":"Health Services",
            "subcategory":"Nursing And Care Facility",
            "type":"Services"
        }
    ],
    "sg:phone":"+44 1542 841326",
    "sg:postcode":"AB56 4TE",
    "sg:province":"Moray",
    "sg:tags":[
        "home"
    ],
    "wof:name":"Wakefield House",
    "wof:placetype":"venue"
},
  "geometry": {"coordinates":[-2.8181979656,57.690612793],"type":"Point"}
}