{
  "type": "Feature",
  "properties": {
    "addr:full":"4 Nottingham Road Belper Derbyshire DE56 1JG",
    "addr:housenumber":"4",
    "addr:postcode":"de56 1jg",
    "addr:street":"Nottingham Road",
    "iso:country":"GB",
    "sg:address":"4 Nottingham Road",
    "sg:city":"Belper",
    "sg:classifiers":[
        {
            "category":"Professional",
            "subcategory":"Computer Services",
            "type":"Services"
        }
    ],
    "sg:phone":"+44 1773 825350",
    "sg:postcode":"DE56 1JG",
    "sg:province":"Derbyshire",
    "sg:tags":[
        "system",
        "software"
    ],
    "wof:name":"Alpha Enterprises",
    "wof:placetype":"venue"
},
  "geometry": {"coordinates":[-1.474856019,53.0239067078],"type":"Point"}
}