{
  "type": "Feature",
  "properties": {
    "iso:country":"GB",
    "sg:address":"Sandyfields Road",
    "sg:city":"Dudley",
    "sg:classifiers":[
        {
            "category":"Sports & Exercise",
            "subcategory":"Golf",
            "type":"Entertainment"
        }
    ],
    "sg:phone":"+44 1902 880503",
    "sg:postcode":"DY3 3DL",
    "sg:province":"Staffordshire",
    "sg:tags":[
        "club",
        "course"
    ],
    "wof:name":"Sedgley Golf Centre",
    "wof:placetype":"venue"
},
  "geometry": {"coordinates":[-2.131454,52.53653],"type":"Point"}
}