{
  "type": "Feature",
  "properties": {
    "addr:full":"Avondale, New Road, Porchfield Newport Isle of Wight PO30 4LT",
    "addr:postcode":"po30 4lt",
    "addr:street":"New Road",
    "iso:country":"GB",
    "sg:address":"Avondale, New Road, Porchfield",
    "sg:city":"Newport",
    "sg:classifiers":[
        {
            "category":"Retail",
            "subcategory":"Repair Shop",
            "type":"Services"
        }
    ],
    "sg:postcode":"PO30 4LT",
    "sg:province":"Isle of Wight",
    "sg:tags":[
        "radio",
        "television",
        "video"
    ],
    "wof:name":"West Wight Vision",
    "wof:placetype":"venue"
},
  "geometry": {"coordinates":[-1.3687989712,50.7189445496],"type":"Point"}
}