{
  "type": "Feature",
  "properties": {
    "iso:country":"GB",
    "sg:address":"60 Regent Place, Hockley",
    "sg:city":"Birmingham",
    "sg:classifiers":[
        {
            "category":"Wholesale",
            "subcategory":"Sporting Goods",
            "type":"Manufacturing & Wholesale Goods"
        }
    ],
    "sg:phone":"+44 121 236 6711",
    "sg:postcode":"B1 3NJ",
    "sg:province":"West Midlands",
    "sg:tags":[
        "mnfr",
        "sport",
        "equipment"
    ],
    "wof:name":"J & W (Precision Engineers) Ltd.",
    "wof:placetype":"venue"
},
  "geometry": {"coordinates":[-1.908549,52.486496],"type":"Point"}
}