{
  "type": "Feature",
  "properties": {
    "addr:full":"Booth Bank Farm, Reddy Lane, Millington Warrington Cheshire WA14 3RE",
    "addr:postcode":"wa14 3re",
    "addr:street":"Reddy Lane",
    "iso:country":"GB",
    "sg:address":"Booth Bank Farm, Reddy Lane, Millington",
    "sg:city":"Warrington",
    "sg:classifiers":[
        {
            "category":"Organizations",
            "subcategory":"Non-profit Organization",
            "type":"Services"
        }
    ],
    "sg:phone":"+44 1565 830053",
    "sg:postcode":"WA14 3RE",
    "sg:province":"Cheshire",
    "sg:tags":[
        "organisation",
        "voluntary",
        "charity"
    ],
    "wof:name":"The Adventure Farm Trading Co. Ltd.",
    "wof:placetype":"venue"
},
  "geometry": {"coordinates":[-2.415329,53.362011],"type":"Point"}
}