{
  "type": "Feature",
  "properties": {
    "addr:full":"Shelton House, 4 Coningsby Street Hereford Herefordshire HR1 2DY",
    "addr:housenumber":"4",
    "addr:postcode":"hr1 2dy",
    "addr:street":"Coningsby Street",
    "iso:country":"GB",
    "sg:address":"Shelton House, 4 Coningsby Street",
    "sg:city":"Hereford",
    "sg:classifiers":[
        {
            "category":"Food & Beverages",
            "subcategory":"Liquor & Beverages",
            "type":"Retail Goods"
        },
        {
            "category":"Wholesale",
            "subcategory":"Wine & Distilled Alcoholic Beverages",
            "type":"Manufacturing & Wholesale Goods"
        }
    ],
    "sg:phone":"+44 1432 262800",
    "sg:postcode":"HR1 2DY",
    "sg:province":"Herefordshire",
    "sg:tags":[
        "beer",
        "importers",
        "spirit",
        "wines"
    ],
    "sg:website":"http://polroger.co.uk",
    "wof:name":"Pol Roger Ltd.",
    "wof:placetype":"venue"
},
  "geometry": {"coordinates":[-2.714402,52.059284],"type":"Point"}
}