{
  "type": "Feature",
  "properties": {
    "addr:full":"34 Fernhill Rd, Rutherglen Glasgow Glasgow City G73 4BT",
    "addr:housenumber":"34",
    "addr:postcode":"g73 4bt",
    "addr:street":"Fernhill Rd",
    "iso:country":"GB",
    "sg:address":"34 Fernhill Rd, Rutherglen",
    "sg:city":"Glasgow",
    "sg:classifiers":[
        {
            "category":"Fast Food",
            "type":"Food & Drink"
        }
    ],
    "sg:postcode":"G73 4BT",
    "sg:province":"Glasgow City",
    "sg:tags":[
        "away",
        "take"
    ],
    "wof:name":"Alizagh,N,",
    "wof:placetype":"venue"
},
  "geometry": {"coordinates":[-4.2065649033,55.807800293],"type":"Point"}
}