{
  "type": "Feature",
  "properties": {
    "iso:country":"GB",
    "sg:address":"30 Woodfield Street, Morriston",
    "sg:city":"Swansea",
    "sg:classifiers":[
        {
            "category":"Shopping",
            "subcategory":"Pharmacy",
            "type":"Retail Goods"
        }
    ],
    "sg:phone":"+44 1792 771029",
    "sg:postcode":"SA6 8BH",
    "sg:province":"Swansea",
    "sg:tags":[
        "pharmacist",
        "chemist"
    ],
    "wof:name":"Boots the Chemists",
    "wof:placetype":"venue"
},
  "geometry": {"coordinates":[-3.9256350994,51.6648597717],"type":"Point"}
}