{
  "type": "Feature",
  "properties": {
    "addr:full":"Pavilion, Lasswade Road Edinburgh City of Edinburgh EH16 6JB",
    "addr:postcode":"eh16 6jb",
    "addr:street":"Lasswade Road",
    "iso:country":"GB",
    "sg:address":"Pavilion, Lasswade Road",
    "sg:city":"Edinburgh",
    "sg:classifiers":[
        {
            "category":"Arena",
            "subcategory":"Sports Club",
            "type":"Entertainment"
        },
        {
            "category":"Government",
            "subcategory":"Office",
            "type":"Public Place"
        }
    ],
    "sg:phone":"+44 131 654 1032",
    "sg:postcode":"EH16 6JB",
    "sg:province":"City of Edinburgh",
    "sg:tags":[
        "local",
        "ground"
    ],
    "wof:name":"Lasswade Park",
    "wof:placetype":"venue"
},
  "geometry": {"coordinates":[-3.159457,55.913078],"type":"Point"}
}