{
  "type": "Feature",
  "properties": {
    "addr:full":"Stoney Acres, Robinson Road Colchester Essex CO7 0ST",
    "addr:postcode":"co7 0st",
    "addr:street":"Stoney;Robinson Road Colchester",
    "iso:country":"GB",
    "sg:address":"Stoney Acres, Robinson Road",
    "sg:city":"Colchester",
    "sg:classifiers":[
        {
            "category":"Freight",
            "type":"Transportation"
        }
    ],
    "sg:phone":"+44 1206 303635",
    "sg:postcode":"CO7 0ST",
    "sg:province":"Essex",
    "sg:tags":[
        "haulage",
        "road"
    ],
    "wof:name":"John I Aldridge",
    "wof:placetype":"venue"
},
  "geometry": {"coordinates":[1.03422,51.81506],"type":"Point"}
}