{
  "type": "Feature",
  "properties": {
    "addr:full":"Poplar Farm, South Leverton Retford Nottinghamshire DN22 0BT",
    "addr:housenumber":"leverton",
    "addr:postcode":"dn22 0bt",
    "iso:country":"GB",
    "sg:address":"Poplar Farm, South Leverton",
    "sg:city":"Retford",
    "sg:classifiers":[
        {
            "category":"Building & Trades",
            "subcategory":"Equipment Rental",
            "type":"Services"
        }
    ],
    "sg:phone":"+44 1427 880362",
    "sg:postcode":"DN22 0BT",
    "sg:province":"Nottinghamshire",
    "sg:tags":[
        "plant",
        "machinery"
    ],
    "wof:name":"Loates Bros Ltd.",
    "wof:placetype":"venue"
},
  "geometry": {"coordinates":[-0.8256109953,53.3191337585],"type":"Point"}
}