{
  "type": "Feature",
  "properties": {
    "addr:full":"1-3 Bdwy, New Moston Manchester Greater Manchester M40 3PA",
    "addr:housenumber":"1-3",
    "addr:postcode":"m40 3pa",
    "addr:street":"Bdwy New",
    "iso:country":"GB",
    "sg:address":"1-3 Bdwy, New Moston",
    "sg:city":"Manchester",
    "sg:classifiers":[
        {
            "category":"Shopping",
            "subcategory":"Baby Store",
            "type":"Retail Goods"
        }
    ],
    "sg:phone":"+44 161 682 3592",
    "sg:postcode":"M40 3PA",
    "sg:province":"Greater Manchester",
    "sg:tags":[
        "equipment",
        "nursery",
        "accessory"
    ],
    "wof:name":"C Bickley",
    "wof:placetype":"venue"
},
  "geometry": {"coordinates":[-2.1689488888,53.5170783997],"type":"Point"}
}