{
  "type": "Feature",
  "properties": {
    "addr:full":"Lenton Business Centre Nottingham Nottinghamshire NG7 2BY",
    "addr:postcode":"ng7 2by",
    "iso:country":"GB",
    "sg:address":"Lenton Business Centre",
    "sg:city":"Nottingham",
    "sg:classifiers":[
        {
            "category":"Building & Trades",
            "subcategory":"Construction",
            "type":"Services"
        }
    ],
    "sg:postcode":"NG7 2BY",
    "sg:province":"Nottinghamshire",
    "sg:tags":[
        "decorator",
        "painter"
    ],
    "wof:name":"McGovern Decorators",
    "wof:placetype":"venue"
},
  "geometry": {"coordinates":[-1.1740139723,52.9476509094],"type":"Point"}
}