{
  "type": "Feature",
  "properties": {
    "iso:country":"GB",
    "sg:address":"10 Station Square",
    "sg:city":"Coventry",
    "sg:classifiers":[
        {
            "category":"Fast Food",
            "type":"Food & Drink"
        }
    ],
    "sg:postcode":"CV1 2GT",
    "sg:province":"West Midlands",
    "sg:tags":[
        "away",
        "take"
    ],
    "wof:name":"Loaf-Ers",
    "wof:placetype":"venue"
},
  "geometry": {"coordinates":[-1.5128530264,52.4017524719],"type":"Point"}
}