{
  "type": "Feature",
  "properties": {
    "addr:full":"23 Northfield End Henley-on-thames Berkshire RG9 2JQ",
    "addr:housenumber":"23",
    "addr:postcode":"rg9 2jq",
    "addr:street":"Northfield End",
    "iso:country":"GB",
    "sg:address":"23 Northfield End",
    "sg:city":"Henley-on-thames",
    "sg:classifiers":[
        {
            "category":"Shopping",
            "subcategory":"Department Store",
            "type":"Retail Goods"
        }
    ],
    "sg:postcode":"RG9 2JQ",
    "sg:province":"Berkshire",
    "wof:name":"Walker Stores",
    "wof:placetype":"venue"
},
  "geometry": {"coordinates":[-0.9055380225,51.5414237976],"type":"Point"}
}