{
  "type": "Feature",
  "properties": {
    "addr:full":"41 Ombersley Road Worcester Worcestershire WR3 7BP",
    "addr:housenumber":"41",
    "addr:postcode":"wr3 7bp",
    "addr:street":"Ombersley Road",
    "iso:country":"GB",
    "sg:address":"41 Ombersley Road",
    "sg:city":"Worcester",
    "sg:classifiers":[
        {
            "category":"Building & Trades",
            "subcategory":"Construction",
            "type":"Services"
        }
    ],
    "sg:phone":"+44 1905 612690",
    "sg:postcode":"WR3 7BP",
    "sg:province":"Worcestershire",
    "sg:tags":[
        "joiner",
        "carpenter"
    ],
    "wof:name":"Andrew Peace",
    "wof:placetype":"venue"
},
  "geometry": {"coordinates":[-2.2270550728,52.20911026],"type":"Point"}
}