{
  "type": "Feature",
  "properties": {
    "iso:country":"GB",
    "sg:address":"127-129 Lord Street",
    "sg:city":"Fleetwood",
    "sg:classifiers":[
        {
            "category":"Health Services",
            "subcategory":"Optometrist",
            "type":"Services"
        },
        {
            "category":"Shopping",
            "subcategory":"Optician",
            "type":"Retail Goods"
        }
    ],
    "sg:phone":"+44 1253 772777",
    "sg:postcode":"FY7 6LH",
    "sg:province":"Lancashire",
    "sg:tags":[
        "ophthalmic"
    ],
    "wof:name":"Barry Stott Optometrists Ltd.",
    "wof:placetype":"venue"
},
  "geometry": {"coordinates":[-3.013705,53.921547],"type":"Point"}
}