{
  "type": "Feature",
  "properties": {
    "iso:country":"GB",
    "sg:address":"Oxted Hospital, Eastlands Way",
    "sg:city":"Oxted",
    "sg:classifiers":[
        {
            "category":"Organizations",
            "subcategory":"Non-profit Organization",
            "type":"Services"
        }
    ],
    "sg:phone":"+44 1883 714641",
    "sg:postcode":"RH8 0LR",
    "sg:province":"Surrey",
    "sg:tags":[
        "organisation",
        "voluntary",
        "charity"
    ],
    "wof:name":"Crossroads Care Attendant Schemes",
    "wof:placetype":"venue"
},
  "geometry": {"coordinates":[-0.00468,51.254894],"type":"Point"}
}