{
  "type": "Feature",
  "properties": {
    "iso:country":"GB",
    "sg:address":"1 Erpingham Rd",
    "sg:city":"London",
    "sg:classifiers":[
        {
            "category":"Food & Beverages",
            "subcategory":"Liquor & Beverages",
            "type":"Retail Goods"
        }
    ],
    "sg:postcode":"SW15 1BE",
    "sg:province":"Greater London",
    "sg:tags":[
        "beer",
        "spirit",
        "wines"
    ],
    "wof:name":"Spiers,M,",
    "wof:placetype":"venue"
},
  "geometry": {"coordinates":[-0.226579,51.468361],"type":"Point"}
}