{
  "type": "Feature",
  "properties": {
    "addr:full":"30 Bradshaw Brow Bolton Lancashire BL2 3DH",
    "addr:housenumber":"30",
    "addr:postcode":"bl2 3dh",
    "addr:street":"Bradshaw Brow",
    "iso:country":"GB",
    "sg:address":"30 Bradshaw Brow",
    "sg:city":"Bolton",
    "sg:classifiers":[
        {
            "category":"Health Services",
            "subcategory":"Doctor",
            "type":"Services"
        }
    ],
    "sg:phone":"+44 1204 302212",
    "sg:postcode":"BL2 3DH",
    "sg:province":"Lancashire",
    "sg:tags":[
        "practitioners"
    ],
    "wof:name":"Kirby Page & Macmillian",
    "wof:placetype":"venue"
},
  "geometry": {"coordinates":[-2.4078109264,53.6016235352],"type":"Point"}
}