{
  "type": "Feature",
  "properties": {
    "iso:country":"GB",
    "sg:address":"8 Sandgate",
    "sg:city":"Whitby",
    "sg:classifiers":[
        {
            "category":"Shopping",
            "subcategory":"Gifts & Souvenirs",
            "type":"Retail Goods"
        }
    ],
    "sg:postcode":"YO22 4DB",
    "sg:province":"North Yorkshire",
    "sg:tags":[
        "shop"
    ],
    "wof:name":"Wilde,Michelle,",
    "wof:placetype":"venue"
},
  "geometry": {"coordinates":[-0.6127570271,54.4876327515],"type":"Point"}
}