{
  "type": "Feature",
  "properties": {
    "addr:full":"Unit 8, Saunders Way, Questor Dartford Kent DA1 1JW",
    "addr:housenumber":"unit 8",
    "addr:postcode":"da1 1jw",
    "addr:street":"Saunders Way Questor",
    "iso:country":"GB",
    "sg:address":"Unit 8, Saunders Way, Questor",
    "sg:city":"Dartford",
    "sg:classifiers":[
        {
            "category":"Freight",
            "type":"Transportation"
        }
    ],
    "sg:phone":"+44 1708 682883",
    "sg:postcode":"DA1 1JW",
    "sg:province":"Kent",
    "sg:tags":[
        "forwarders"
    ],
    "wof:name":"Holship Air International Ltd.",
    "wof:placetype":"venue"
},
  "geometry": {"coordinates":[0.220555,51.444633],"type":"Point"}
}