{
  "type": "Feature",
  "properties": {
    "addr:full":"4-5 Cricketers Parade, Broadwater Street West Worthing West Sussex BN14 9DB",
    "addr:housenumber":"4-5",
    "addr:postcode":"bn14 9db",
    "addr:street":"Cricketers Parade Broadwater Street",
    "iso:country":"GB",
    "sg:address":"4-5 Cricketers Parade, Broadwater Street West",
    "sg:city":"Worthing",
    "sg:classifiers":[
        {
            "category":"Manufacturing",
            "subcategory":"Petroleum Products",
            "type":"Manufacturing & Wholesale Goods"
        },
        {
            "category":"Building & Trades",
            "subcategory":"Construction",
            "type":"Services"
        }
    ],
    "sg:phone":"+44 1903 201228",
    "sg:postcode":"BN14 9DB",
    "sg:province":"West Sussex",
    "sg:tags":[
        "double",
        "glazier",
        "glazing"
    ],
    "wof:name":"Zenith Windows",
    "wof:placetype":"venue"
},
  "geometry": {"coordinates":[-0.3743579984,50.8284339905],"type":"Point"}
}