{
  "type": "Feature",
  "properties": {
    "iso:country":"GB",
    "sg:address":"103 Almondvale Centre, Almondvale Avenue",
    "sg:city":"Livingston",
    "sg:classifiers":[
        {
            "category":"Home & Garden",
            "subcategory":"Furniture",
            "type":"Retail Goods"
        }
    ],
    "sg:phone":"+44 1506 441505",
    "sg:postcode":"EH54 6HS",
    "sg:province":"West Lothian",
    "sg:tags":[
        "outlet"
    ],
    "wof:name":"Tuk Rental Ltd.",
    "wof:placetype":"venue"
},
  "geometry": {"coordinates":[-3.509834,55.886246],"type":"Point"}
}