{
  "type": "Feature",
  "properties": {
    "iso:country":"GB",
    "sg:address":"11 Beaumont Gate,, Shenley Hill",
    "sg:city":"Radlett",
    "sg:classifiers":[
        {
            "category":"Professional",
            "subcategory":"Computer Services",
            "type":"Services"
        }
    ],
    "sg:postcode":"WD7 7AR",
    "sg:province":"Hertfordshire",
    "sg:tags":[
        "system",
        "software"
    ],
    "wof:name":"Hi-Tec Projects Ltd",
    "wof:placetype":"venue"
},
  "geometry": {"coordinates":[-0.31659,51.685524],"type":"Point"}
}