{
  "type": "Feature",
  "properties": {
    "addr:full":"Boundary Service Station, 5-15 High Street, Ponders End Enfield Greater London EN3 4EJ",
    "addr:housenumber":"5-15",
    "addr:postcode":"en3 4ej",
    "addr:street":"High Street Ponders End",
    "iso:country":"GB",
    "sg:address":"Boundary Service Station, 5-15 High Street, Ponders End",
    "sg:city":"Enfield",
    "sg:classifiers":[
        {
            "category":"Retail",
            "subcategory":"Auto Rental",
            "type":"Services"
        }
    ],
    "sg:phone":"+44 20 8804 2430",
    "sg:postcode":"EN3 4EJ",
    "sg:province":"Greater London",
    "sg:tags":[
        "car",
        "vehicle"
    ],
    "wof:name":"Hertz Rent A Car Ltd",
    "wof:placetype":"venue"
},
  "geometry": {"coordinates":[-0.0470700003,51.6404304504],"type":"Point"}
}