{
  "type": "Feature",
  "properties": {
    "addr:full":"The Cottage, Summerhill Narberth Carmarthenshire SA67 8LU",
    "addr:postcode":"sa67 8lu",
    "addr:street":"Summerhill",
    "iso:country":"GB",
    "sg:address":"The Cottage, Summerhill",
    "sg:city":"Narberth",
    "sg:classifiers":[
        {
            "category":"Shopping",
            "subcategory":"Department Store",
            "type":"Retail Goods"
        }
    ],
    "sg:phone":"+44 1834 813435",
    "sg:postcode":"SA67 8LU",
    "sg:province":"Carmarthenshire",
    "wof:name":"Summerhill Stores",
    "wof:placetype":"venue"
},
  "geometry": {"coordinates":[-4.67594,51.735641],"type":"Point"}
}