{
  "type": "Feature",
  "properties": {
    "addr:full":"29 North Poulner Road Ringwood Dorset BH24 1SN",
    "addr:housenumber":"29",
    "addr:postcode":"bh24 1sn",
    "addr:street":"North Poulner Road",
    "iso:country":"GB",
    "sg:address":"29 North Poulner Road",
    "sg:city":"Ringwood",
    "sg:classifiers":[
        {
            "category":"Professional",
            "type":"Services"
        }
    ],
    "sg:postcode":"BH24 1SN",
    "sg:province":"Dorset",
    "sg:tags":[
        "caterer"
    ],
    "wof:name":"Belles Catering",
    "wof:placetype":"venue"
},
  "geometry": {"coordinates":[-1.7790490389,50.8571777344],"type":"Point"}
}