{
  "type": "Feature",
  "properties": {
    "iso:country":"GB",
    "sg:address":"Lincoln Rd Wharf",
    "sg:city":"Birmingham",
    "sg:classifiers":[
        {
            "category":"Utilities",
            "subcategory":"Fuel Oil & Lpg",
            "type":"Services"
        }
    ],
    "sg:phone":"+44 121 706 0658",
    "sg:postcode":"B27 6NY",
    "sg:province":"West Midlands",
    "sg:tags":[
        "distributor"
    ],
    "wof:name":"Lester Brothers Ltd",
    "wof:placetype":"venue"
},
  "geometry": {"coordinates":[-1.811179,52.443626],"type":"Point"}
}