{
  "type": "Feature",
  "properties": {
    "addr:full":"Unit 12 Main Street, Bramley Rotherham South Yorkshire S66 2SQ",
    "addr:housenumber":"unit 12",
    "addr:postcode":"s66 2sq",
    "addr:street":"Main Street",
    "iso:country":"GB",
    "sg:address":"Unit 12 Main Street, Bramley",
    "sg:city":"Rotherham",
    "sg:classifiers":[
        {
            "category":"Professional",
            "subcategory":"Art Services",
            "type":"Services"
        }
    ],
    "sg:phone":"+44 1709 709005",
    "sg:postcode":"S66 2SQ",
    "sg:province":"South Yorkshire",
    "sg:tags":[
        "photographer"
    ],
    "wof:name":"Little Posers",
    "wof:placetype":"venue"
},
  "geometry": {"coordinates":[-1.2673530579,53.4270973206],"type":"Point"}
}