{
  "type": "Feature",
  "properties": {
    "addr:full":"2 Meadow Way, Shooters Hill Dover Kent CT15 4LY",
    "addr:housenumber":"2",
    "addr:postcode":"ct15 4ly",
    "addr:street":"Meadow Way",
    "iso:country":"GB",
    "sg:address":"2 Meadow Way, Shooters Hill",
    "sg:city":"Dover",
    "sg:classifiers":[
        {
            "category":"Building & Trades",
            "subcategory":"Construction",
            "type":"Services"
        }
    ],
    "sg:phone":"+44 1304 830851",
    "sg:postcode":"CT15 4LY",
    "sg:province":"Kent",
    "sg:tags":[
        "builder"
    ],
    "wof:name":"Hill Acre Ltd.",
    "wof:placetype":"venue"
},
  "geometry": {"coordinates":[1.2648949623,51.1994247437],"type":"Point"}
}