{
  "type": "Feature",
  "properties": {
    "addr:full":"70 Christchurch Road Reading Berkshire RG2 7AZ",
    "addr:housenumber":"70",
    "addr:postcode":"rg2 7az",
    "addr:street":"Christchurch Road",
    "iso:country":"GB",
    "sg:address":"70 Christchurch Road",
    "sg:city":"Reading",
    "sg:classifiers":[
        {
            "category":"Food & Beverages",
            "subcategory":"Meat & Fish",
            "type":"Retail Goods"
        }
    ],
    "sg:postcode":"RG2 7AZ",
    "sg:province":"Berkshire",
    "sg:tags":[
        "butcher"
    ],
    "wof:name":"Medina Stores",
    "wof:placetype":"venue"
},
  "geometry": {"coordinates":[-0.9556099772,51.442779541],"type":"Point"}
}