{
  "type": "Feature",
  "properties": {
    "iso:country":"GB",
    "sg:address":"92 Forest Road",
    "sg:city":"London",
    "sg:classifiers":[
        {
            "category":"Food & Beverages",
            "subcategory":"Fruits & Vegetables",
            "type":"Retail Goods"
        }
    ],
    "sg:phone":"+44 20 8531 7459",
    "sg:postcode":"E17 6JQ",
    "sg:province":"Greater London",
    "sg:tags":[
        "greengrocer"
    ],
    "wof:name":"Kamathenu",
    "wof:placetype":"venue"
},
  "geometry": {"coordinates":[-0.0347150005,51.5877838135],"type":"Point"}
}