{
  "type": "Feature",
  "properties": {
    "addr:full":"29-30 Victoria Arcade Great Yarmouth Norfolk NR30 2NU",
    "addr:housenumber":"29-30",
    "addr:postcode":"nr30 2nu",
    "addr:street":"Victoria Arcade;Yarmouth",
    "iso:country":"GB",
    "sg:address":"29-30 Victoria Arcade",
    "sg:city":"Great Yarmouth",
    "sg:classifiers":[
        {
            "category":"Shopping",
            "subcategory":"News",
            "type":"Retail Goods"
        }
    ],
    "sg:postcode":"NR30 2NU",
    "sg:province":"Norfolk",
    "sg:tags":[
        "newsagent"
    ],
    "wof:name":"Central News",
    "wof:placetype":"venue"
},
  "geometry": {"coordinates":[1.7260550261,52.606426239],"type":"Point"}
}