{
  "type": "Feature",
  "properties": {
    "addr:full":"11-15 Schneider Close Felixstowe Suffolk IP11 3SS",
    "addr:housenumber":"11-15",
    "addr:postcode":"ip11 3ss",
    "addr:street":"Schneider Close",
    "iso:country":"GB",
    "sg:address":"11-15 Schneider Close",
    "sg:city":"Felixstowe",
    "sg:classifiers":[
        {
            "category":"Freight",
            "type":"Transportation"
        }
    ],
    "sg:phone":"+44 1394 675750",
    "sg:postcode":"IP11 3SS",
    "sg:province":"Suffolk",
    "sg:tags":[
        "forwarders"
    ],
    "wof:name":"Hudig (U K) Ltd.",
    "wof:placetype":"venue"
},
  "geometry": {"coordinates":[1.3266639709,51.9481086731],"type":"Point"}
}