{
  "type": "Feature",
  "properties": {
    "addr:full":"45 Albert Road Hythe Kent CT21 6BT",
    "addr:housenumber":"45",
    "addr:postcode":"ct21 6bt",
    "addr:street":"Albert Road",
    "iso:country":"GB",
    "sg:address":"45 Albert Road",
    "sg:city":"Hythe",
    "sg:classifiers":[
        {
            "category":"Professional",
            "subcategory":"Art Services",
            "type":"Services"
        }
    ],
    "sg:phone":"+44 1303 260786",
    "sg:postcode":"CT21 6BT",
    "sg:province":"Kent",
    "sg:tags":[
        "graphic",
        "designer"
    ],
    "wof:name":"Roger Judd Graphic Design",
    "wof:placetype":"venue"
},
  "geometry": {"coordinates":[1.0815989971,51.0663146973],"type":"Point"}
}