{
  "type": "Feature",
  "properties": {
    "addr:full":"178 Brent Cres Willesden Greater London NW10 7XR",
    "addr:housenumber":"178",
    "addr:postcode":"willesden;nw10 7xr",
    "addr:street":"Brent Cres",
    "iso:country":"GB",
    "sg:address":"178 Brent Cres",
    "sg:city":"Willesden",
    "sg:classifiers":[
        {
            "category":"Manufacturing",
            "subcategory":"Petroleum Products",
            "type":"Manufacturing & Wholesale Goods"
        }
    ],
    "sg:phone":"+44 20 8961 7866",
    "sg:postcode":"NW10 7XR",
    "sg:province":"Greater London",
    "sg:tags":[
        "double",
        "glazing"
    ],
    "wof:name":"Vogue",
    "wof:placetype":"venue"
},
  "geometry": {"coordinates":[-0.2894450128,51.5350990295],"type":"Point"}
}