{
  "type": "Feature",
  "properties": {
    "addr:full":"Heddon Way, Middlefields Indust Est South Shields Tyne and Wear NE34 0NT",
    "addr:postcode":"ne34 0nt",
    "addr:street":"Heddon Way Middlefields Indust Est",
    "iso:country":"GB",
    "sg:address":"Heddon Way, Middlefields Indust Est",
    "sg:city":"South Shields",
    "sg:classifiers":[
        {
            "category":"Wholesale",
            "subcategory":"Meat",
            "type":"Manufacturing & Wholesale Goods"
        }
    ],
    "sg:postcode":"NE34 0NT",
    "sg:province":"Tyne and Wear",
    "sg:tags":[
        "product"
    ],
    "wof:name":"Dickson,Michael,",
    "wof:placetype":"venue"
},
  "geometry": {"coordinates":[-1.4450600147,54.9757614136],"type":"Point"}
}