{
  "type": "Feature",
  "properties": {
    "addr:full":"Unit 4, Capstan Centre, Thurrock Park Way Tilbury Essex RM18 7HH",
    "addr:housenumber":"unit 4",
    "addr:postcode":"rm18 7hh",
    "addr:street":"Capstan Centre Thurrock Park Way",
    "iso:country":"GB",
    "sg:address":"Unit 4, Capstan Centre, Thurrock Park Way",
    "sg:city":"Tilbury",
    "sg:classifiers":[
        {
            "category":"Freight",
            "type":"Transportation"
        }
    ],
    "sg:phone":"+44 1375 858315",
    "sg:postcode":"RM18 7HH",
    "sg:province":"Essex",
    "sg:tags":[
        "haulage",
        "road"
    ],
    "wof:name":"Freight Management (U K) Ltd.",
    "wof:placetype":"venue"
},
  "geometry": {"coordinates":[0.342065,51.470375],"type":"Point"}
}