{
  "type": "Feature",
  "properties": {
    "addr:full":"21 Park Mead, South Harrow Greater London HA2 8NQ",
    "addr:housenumber":"21",
    "addr:postcode":"ha2 8nq",
    "addr:street":"Park Mead",
    "iso:country":"GB",
    "sg:address":"21 Park Mead, South",
    "sg:city":"Harrow",
    "sg:classifiers":[
        {
            "category":"Organizations",
            "subcategory":"Membership Organization",
            "type":"Services"
        }
    ],
    "sg:postcode":"HA2 8NQ",
    "sg:province":"Greater London",
    "sg:tags":[
        "club"
    ],
    "wof:name":"Fastlane Management Ltd",
    "wof:placetype":"venue"
},
  "geometry": {"coordinates":[-0.361017,51.562431],"type":"Point"}
}