{
  "type": "Feature",
  "properties": {
    "iso:country":"GB",
    "sg:address":"135 Northdown Rd, Cliftonville",
    "sg:city":"Margate",
    "sg:classifiers":[
        {
            "category":"Shopping",
            "subcategory":"Thrift Store",
            "type":"Retail Goods"
        }
    ],
    "sg:postcode":"CT9 2QY",
    "sg:province":"Kent",
    "sg:tags":[
        "shop",
        "charity"
    ],
    "wof:name":"St. Pauls Community Shop",
    "wof:placetype":"venue"
},
  "geometry": {"coordinates":[1.3957279921,51.3882865906],"type":"Point"}
}