{
  "type": "Feature",
  "properties": {
    "iso:country":"GB",
    "sg:address":"260a Abbeydale Road",
    "sg:city":"Wembley",
    "sg:classifiers":[
        {
            "category":"Professional",
            "subcategory":"Business Services",
            "type":"Services"
        }
    ],
    "sg:phone":"+44 20 8991 9161",
    "sg:postcode":"HA0 1QA",
    "sg:province":"Greater London",
    "sg:tags":[
        "import",
        "export",
        "agent"
    ],
    "wof:name":"Maygrove Contract Hire",
    "wof:placetype":"venue"
},
  "geometry": {"coordinates":[-0.284912,51.539722],"type":"Point"}
}