{
  "type": "Feature",
  "properties": {
    "addr:full":"132 Maidstone Road Gillingham Kent ME8 0DS",
    "addr:housenumber":"132",
    "addr:postcode":"me8 0ds",
    "addr:street":"Maidstone Road",
    "iso:country":"GB",
    "sg:address":"132 Maidstone Road",
    "sg:city":"Gillingham",
    "sg:classifiers":[
        {
            "category":"Real Estate",
            "subcategory":"Developer",
            "type":"Services"
        },
        {
            "category":"Building & Trades",
            "subcategory":"Construction",
            "type":"Services"
        }
    ],
    "sg:phone":"+44 1634 260727",
    "sg:postcode":"ME8 0DS",
    "sg:province":"Kent",
    "sg:tags":[
        "residential",
        "builder",
        "property"
    ],
    "wof:name":"Marshreed Properties Ltd.",
    "wof:placetype":"venue"
},
  "geometry": {"coordinates":[0.5910699964,51.3530883789],"type":"Point"}
}