{
  "type": "Feature",
  "properties": {
    "addr:full":"4 Mount Park Rd Scarborough North Yorkshire YO12 5HD",
    "addr:housenumber":"4",
    "addr:postcode":"yo12 5hd",
    "addr:street":"Mount Park Rd",
    "iso:country":"GB",
    "sg:address":"4 Mount Park Rd",
    "sg:city":"Scarborough",
    "sg:classifiers":[
        {
            "category":"Building & Trades",
            "subcategory":"Plumbing",
            "type":"Services"
        }
    ],
    "sg:phone":"+44 1723 373655",
    "sg:postcode":"YO12 5HD",
    "sg:province":"North Yorkshire",
    "sg:tags":[
        "heating"
    ],
    "wof:name":"Les Hare & Sons",
    "wof:placetype":"venue"
},
  "geometry": {"coordinates":[-0.4169239998,54.2771835327],"type":"Point"}
}