{
  "type": "Feature",
  "properties": {
    "iso:country":"GB",
    "sg:address":"440 Uxbridge Road, Shepherds Bush",
    "sg:city":"London",
    "sg:classifiers":[
        {
            "category":"Shopping",
            "subcategory":"News",
            "type":"Retail Goods"
        }
    ],
    "sg:phone":"+44 20 8743 4387",
    "sg:postcode":"W12 0NS",
    "sg:province":"Greater London",
    "sg:tags":[
        "newsagent"
    ],
    "wof:name":"Venables",
    "wof:placetype":"venue"
},
  "geometry": {"coordinates":[-0.238852,51.50658],"type":"Point"}
}