{
  "type": "Feature",
  "properties": {
    "addr:full":"20 Churchill Rd Edgware Greater London HA8 6NY",
    "addr:housenumber":"20",
    "addr:postcode":"ha8 6ny",
    "addr:street":"Churchill Rd",
    "iso:country":"GB",
    "sg:address":"20 Churchill Rd",
    "sg:city":"Edgware",
    "sg:classifiers":[
        {
            "category":"Bakery",
            "type":"Food & Drink"
        }
    ],
    "sg:phone":"+44 20 8951 3402",
    "sg:postcode":"HA8 6NY",
    "sg:province":"Greater London",
    "sg:tags":[
        "cake",
        "maker"
    ],
    "wof:name":"Clever Cakes",
    "wof:placetype":"venue"
},
  "geometry": {"coordinates":[-0.2826099992,51.6104202271],"type":"Point"}
}