{
  "type": "Feature",
  "properties": {
    "iso:country":"GB",
    "sg:address":"3 Gibsons Road",
    "sg:city":"Stockport",
    "sg:classifiers":[
        {
            "category":"Wholesale",
            "subcategory":"Books, Periodicals, & Newspapers",
            "type":"Manufacturing & Wholesale Goods"
        }
    ],
    "sg:phone":"+44 161 432 4010",
    "sg:postcode":"SK4 4JX",
    "sg:province":"Cheshire",
    "sg:tags":[
        "publishing"
    ],
    "wof:name":"Jackson Publishing & Distribution",
    "wof:placetype":"venue"
},
  "geometry": {"coordinates":[-2.183684,53.422565],"type":"Point"}
}