{
  "type": "Feature",
  "properties": {
    "addr:full":"39 Oatlands Rd Enfield Greater London EN3 5LL",
    "addr:housenumber":"39",
    "addr:postcode":"en3 5ll",
    "addr:street":"Oatlands Rd",
    "iso:country":"GB",
    "sg:address":"39 Oatlands Rd",
    "sg:city":"Enfield",
    "sg:classifiers":[
        {
            "category":"Professional",
            "subcategory":"Engineering",
            "type":"Services"
        }
    ],
    "sg:phone":"+44 20 8805 4355",
    "sg:postcode":"EN3 5LL",
    "sg:province":"Greater London",
    "sg:tags":[
        "contractor",
        "electrical",
        "engineer"
    ],
    "wof:name":"Action",
    "wof:placetype":"venue"
},
  "geometry": {"coordinates":[-0.0439249985,51.6603775024],"type":"Point"}
}