{
  "type": "Feature",
  "properties": {
    "addr:full":"Murray Home, 470 Gilmerton Road Edinburgh City of Edinburgh EH17 7SA",
    "addr:housenumber":"470",
    "addr:postcode":"eh17 7sa",
    "addr:street":"Gilmerton Road",
    "iso:country":"GB",
    "sg:address":"Murray Home, 470 Gilmerton Road",
    "sg:city":"Edinburgh",
    "sg:classifiers":[
        {
            "category":"Organizations",
            "subcategory":"Non-profit Organization",
            "type":"Services"
        }
    ],
    "sg:phone":"+44 131 664 3037",
    "sg:postcode":"EH17 7SA",
    "sg:province":"City of Edinburgh",
    "sg:tags":[
        "organisation",
        "voluntary",
        "charity"
    ],
    "wof:name":"Scottish Veterans Residences",
    "wof:placetype":"venue"
},
  "geometry": {"coordinates":[-3.1391201019,55.9098014832],"type":"Point"}
}