{
  "type": "Feature",
  "properties": {
    "addr:full":"4 Marden Way Calne Wiltshire SN11 0RY",
    "addr:housenumber":"4",
    "addr:postcode":"sn11 0ry",
    "addr:street":"Marden Way",
    "iso:country":"GB",
    "sg:address":"4 Marden Way",
    "sg:city":"Calne",
    "sg:classifiers":[
        {
            "category":"Shopping",
            "subcategory":"Hobbies, Toys, & Games",
            "type":"Retail Goods"
        }
    ],
    "sg:phone":"+44 1249 822047",
    "sg:postcode":"SN11 0RY",
    "sg:province":"Wiltshire",
    "sg:tags":[
        "collectors'",
        "item"
    ],
    "wof:name":"Bob's Football Programmes",
    "wof:placetype":"venue"
},
  "geometry": {"coordinates":[-2.008359,51.434292],"type":"Point"}
}