{
  "type": "Feature",
  "properties": {
    "iso:country":"GB",
    "sg:address":"Moat Road",
    "sg:city":"East Grinstead",
    "sg:classifiers":[
        {
            "category":"Community Center",
            "type":"Public Place"
        }
    ],
    "sg:postcode":"RH19 3LB",
    "sg:province":"East Sussex",
    "sg:tags":[
        "conference",
        "room",
        "centre"
    ],
    "wof:name":"Neale House Conference Centre",
    "wof:placetype":"venue"
},
  "geometry": {"coordinates":[-0.012766,51.130016],"type":"Point"}
}