{
  "type": "Feature",
  "properties": {
    "iso:country":"GB",
    "sg:address":"160 High Street, Codicote",
    "sg:city":"Hitchin",
    "sg:classifiers":[
        {
            "category":"Personal",
            "subcategory":"Beauty Salon",
            "type":"Services"
        }
    ],
    "sg:postcode":"SG4 8UB",
    "sg:province":"Hertfordshire",
    "sg:tags":[
        "unisex",
        "hairdresser"
    ],
    "wof:name":"It's A Snip",
    "wof:placetype":"venue"
},
  "geometry": {"coordinates":[-0.233708,51.848141],"type":"Point"}
}