{
  "type": "Feature",
  "properties": {
    "iso:country":"GB",
    "sg:address":"Po Box 142, The Brewery",
    "sg:city":"Leeds",
    "sg:classifiers":[
        {
            "category":"Landmark",
            "subcategory":"Tourist Attraction",
            "type":"Public Place"
        }
    ],
    "sg:phone":"+44 113 242 0666",
    "sg:postcode":"LS1 1QG",
    "sg:province":"West Yorkshire",
    "sg:tags":[
        "interest"
    ],
    "wof:name":"Tetley Brewery Wharf",
    "wof:placetype":"venue"
},
  "geometry": {"coordinates":[-1.5465869904,53.7944946289],"type":"Point"}
}