{
  "type": "Feature",
  "properties": {
    "iso:country":"GB",
    "sg:address":"Donnington Hall, Donnington",
    "sg:city":"Ledbury",
    "sg:classifiers":[
        {
            "category":"Sports & Exercise",
            "subcategory":"Stables",
            "type":"Entertainment"
        }
    ],
    "sg:postcode":"HR8 2HX",
    "sg:province":"Gloucestershire",
    "sg:tags":[
        "education",
        "equestrian"
    ],
    "wof:name":"Y Shechter",
    "wof:placetype":"venue"
},
  "geometry": {"coordinates":[-2.419134,52.007328],"type":"Point"}
}