{
  "type": "Feature",
  "properties": {
    "addr:full":"83 East Street, Bedminster Bristol City of Bristol BS3 4EX",
    "addr:housenumber":"83",
    "addr:postcode":"bs3 4ex",
    "addr:street":"East Street",
    "iso:country":"GB",
    "sg:address":"83 East Street, Bedminster",
    "sg:city":"Bristol",
    "sg:classifiers":[
        {
            "category":"Travel",
            "subcategory":"Travel Agent",
            "type":"Entertainment"
        }
    ],
    "sg:phone":"+44 117 963 7264",
    "sg:postcode":"BS3 4EX",
    "sg:province":"City of Bristol",
    "wof:name":"Going Places Leisure Travel Ltd.",
    "wof:placetype":"venue"
},
  "geometry": {"coordinates":[-2.597445,51.4417],"type":"Point"}
}