{
  "type": "Feature",
  "properties": {
    "addr:full":"Mailbox 107, Maghull Business Centre, 12 Liverpool Rd North Liverpool Lancashire L31 2PN",
    "addr:housenumber":"107;business;12",
    "addr:postcode":"l31 2pn",
    "addr:street":"Mailbox;Liverpool Rd",
    "iso:country":"GB",
    "sg:address":"Mailbox 107, Maghull Business Centre, 12 Liverpool Rd North",
    "sg:city":"Liverpool",
    "sg:classifiers":[
        {
            "category":"Arena",
            "subcategory":"Sports Club",
            "type":"Entertainment"
        }
    ],
    "sg:postcode":"L31 2PN",
    "sg:province":"Lancashire",
    "wof:name":"Kennedy,Alan,Soccer School (The)",
    "wof:placetype":"venue"
},
  "geometry": {"coordinates":[-2.94416,53.513008],"type":"Point"}
}