{
  "type": "Feature",
  "properties": {
    "iso:country":"GB",
    "sg:address":"1 West Road, Watton",
    "sg:city":"Thetford",
    "sg:classifiers":[
        {
            "category":"Taxi",
            "type":"Transportation"
        }
    ],
    "sg:phone":"+44 1953 885966",
    "sg:postcode":"IP25 6AU",
    "sg:province":"Norfolk",
    "sg:tags":[
        "mini",
        "cab"
    ],
    "wof:name":"Home James",
    "wof:placetype":"venue"
},
  "geometry": {"coordinates":[0.820235014,52.5699958801],"type":"Point"}
}