{
  "type": "Feature",
  "properties": {
    "iso:country":"GB",
    "sg:address":"50 Birch Drive, Cambuslang",
    "sg:city":"Glasgow",
    "sg:classifiers":[
        {
            "category":"Farming",
            "subcategory":"Nursery",
            "type":"Manufacturing & Wholesale Goods"
        },
        {
            "category":"Government",
            "subcategory":"Office",
            "type":"Public Place"
        }
    ],
    "sg:phone":"+44 141 641 7182",
    "sg:postcode":"G72 7LY",
    "sg:province":"South Lanarkshire",
    "sg:tags":[
        "local",
        "creche"
    ],
    "wof:name":"Westburn Nursery",
    "wof:placetype":"venue"
},
  "geometry": {"coordinates":[-4.1559810638,55.8190879822],"type":"Point"}
}