{
  "type": "Feature",
  "properties": {
    "iso:country":"GB",
    "sg:address":"121 Clare Road",
    "sg:city":"Staines",
    "sg:classifiers":[
        {
            "category":"Professional",
            "subcategory":"Business Services",
            "type":"Services"
        }
    ],
    "sg:phone":"+44 1784 243594",
    "sg:postcode":"TW19 7QP",
    "sg:province":"Berkshire",
    "sg:tags":[
        "import",
        "export",
        "agent"
    ],
    "wof:name":"Documentary Credit Agency",
    "wof:placetype":"venue"
},
  "geometry": {"coordinates":[-0.475756,51.451344],"type":"Point"}
}