{
  "type": "Feature",
  "properties": {
    "addr:full":"Church Rd Boston Lincolnshire PE21 0LJ",
    "addr:postcode":"pe21 0lj",
    "addr:street":"Church Rd",
    "iso:country":"GB",
    "sg:address":"Church Rd",
    "sg:city":"Boston",
    "sg:classifiers":[
        {
            "category":"Home & Garden",
            "subcategory":"Hardware",
            "type":"Retail Goods"
        }
    ],
    "sg:phone":"+44 1205 361315",
    "sg:postcode":"PE21 0LJ",
    "sg:province":"Lincolnshire",
    "sg:tags":[
        "product",
        "wire",
        "electrical"
    ],
    "wof:name":"A & M Wire Works",
    "wof:placetype":"venue"
},
  "geometry": {"coordinates":[-0.012634,52.974255],"type":"Point"}
}