{
  "type": "Feature",
  "properties": {
    "addr:full":"Coral Ho, 42 Charles St Manchester Greater Manchester M1 7DB",
    "addr:housenumber":"42",
    "addr:postcode":"m1 7db",
    "addr:street":"Charles St",
    "iso:country":"GB",
    "sg:address":"Coral Ho, 42 Charles St",
    "sg:city":"Manchester",
    "sg:classifiers":[
        {
            "category":"Shopping",
            "subcategory":"Clothing, Apparel, & Fashions",
            "type":"Retail Goods"
        }
    ],
    "sg:postcode":"M1 7DB",
    "sg:province":"Greater Manchester",
    "sg:tags":[
        "clothing",
        "fabric"
    ],
    "wof:name":"Young Mode (Manchester) Ltd",
    "wof:placetype":"venue"
},
  "geometry": {"coordinates":[-2.2382,53.47401],"type":"Point"}
}