{
  "type": "Feature",
  "properties": {
    "iso:country":"GB",
    "sg:address":"Wentworth House, 81-83 High Street",
    "sg:city":"Dunstable",
    "sg:classifiers":[
        {
            "category":"Home & Garden",
            "subcategory":"Building Materials",
            "type":"Retail Goods"
        }
    ],
    "sg:postcode":"LU6 1JJ",
    "sg:province":"Bedfordshire",
    "sg:tags":[
        "garage",
        "door"
    ],
    "wof:name":"Garage Doors Ltd.",
    "wof:placetype":"venue"
},
  "geometry": {"coordinates":[-0.5245789886,51.8886413574],"type":"Point"}
}