{
  "type": "Feature",
  "properties": {
    "addr:full":"Littlebrook Manorway Dartford Kent DA1 5PT",
    "addr:postcode":"da1 5pt",
    "addr:street":"Manorway",
    "iso:country":"GB",
    "sg:address":"Littlebrook Manorway",
    "sg:city":"Dartford",
    "sg:classifiers":[
        {
            "category":"Train Station",
            "subcategory":"Rail",
            "type":"Transportation"
        },
        {
            "category":"Retail",
            "subcategory":"Auto Repair",
            "type":"Services"
        }
    ],
    "sg:postcode":"DA1 5PT",
    "sg:province":"Kent",
    "sg:tags":[
        "caravan",
        "bodybuilder",
        "repairer"
    ],
    "wof:name":"Allen,J,",
    "wof:placetype":"venue"
},
  "geometry": {"coordinates":[0.237819,51.452724],"type":"Point"}
}