{
  "type": "Feature",
  "properties": {
    "addr:full":"94 Lordship Lane London Greater London SE22 8HF",
    "addr:housenumber":"94",
    "addr:postcode":"se22 8hf",
    "addr:street":"Lordship Lane",
    "iso:country":"GB",
    "sg:address":"94 Lordship Lane",
    "sg:city":"London",
    "sg:classifiers":[
        {
            "category":"Real Estate",
            "subcategory":"Real Estate Agent",
            "type":"Services"
        }
    ],
    "sg:phone":"+44 20 8299 1722",
    "sg:postcode":"SE22 8HF",
    "sg:province":"Greater London",
    "wof:name":"Bushells",
    "wof:placetype":"venue"
},
  "geometry": {"coordinates":[-0.0754309967,51.4576416016],"type":"Point"}
}