{
  "type": "Feature",
  "properties": {
    "addr:full":"Unit 12 The Corner Garages, Holloway Close Mitcham Greater London CR4 2QB",
    "addr:housenumber":"unit 12",
    "addr:postcode":"cr4 2qb",
    "addr:street":"Holloway Close",
    "iso:country":"GB",
    "sg:address":"Unit 12 The Corner Garages, Holloway Close",
    "sg:city":"Mitcham",
    "sg:classifiers":[
        {
            "category":"Utilities",
            "subcategory":"Refuse",
            "type":"Services"
        }
    ],
    "sg:phone":"+44 20 8773 4000",
    "sg:postcode":"CR4 2QB",
    "sg:province":"Greater London",
    "sg:tags":[
        "skip",
        "hire"
    ],
    "wof:name":"J K Skips",
    "wof:placetype":"venue"
},
  "geometry": {"coordinates":[-0.164255,51.40715],"type":"Point"}
}