{
  "type": "Feature",
  "properties": {
    "addr:full":"3 Atlantic Quay, York Street Glasgow Glasgow City G2 8JH",
    "addr:housenumber":"3",
    "addr:postcode":"g2 8jh",
    "addr:street":"York Street",
    "iso:country":"GB",
    "sg:address":"3 Atlantic Quay, York Street",
    "sg:city":"Glasgow",
    "sg:classifiers":[
        {
            "category":"Travel",
            "subcategory":"Travel Agent",
            "type":"Entertainment"
        }
    ],
    "sg:phone":"+44 141 204 4321",
    "sg:postcode":"G2 8JH",
    "sg:province":"Glasgow City",
    "wof:name":"Hilton Leisure Breaks Ltd.",
    "wof:placetype":"venue"
},
  "geometry": {"coordinates":[-4.26248,55.857182],"type":"Point"}
}