{
  "type": "Feature",
  "properties": {
    "addr:full":"1 Lilac Cottage, Northchapel Petworth West Sussex GU28 9HL",
    "addr:housenumber":"1",
    "addr:postcode":"gu28 9hl",
    "addr:street":"Lilac",
    "iso:country":"GB",
    "sg:address":"1 Lilac Cottage, Northchapel",
    "sg:city":"Petworth",
    "sg:classifiers":[
        {
            "category":"Building & Trades",
            "subcategory":"Construction",
            "type":"Services"
        }
    ],
    "sg:postcode":"GU28 9HL",
    "sg:province":"West Sussex",
    "sg:tags":[
        "joiner",
        "carpenter"
    ],
    "wof:name":"Francois,Nicholas,",
    "wof:placetype":"venue"
},
  "geometry": {"coordinates":[-0.6440590024,51.0557060242],"type":"Point"}
}