{
  "type": "Feature",
  "properties": {
    "addr:full":"Fleets Lane Poole Dorset BH15 3BT",
    "addr:postcode":"bh15 3bt",
    "addr:street":"Fleets Lane",
    "iso:country":"GB",
    "sg:address":"Fleets Lane",
    "sg:city":"Poole",
    "sg:classifiers":[
        {
            "category":"Sports & Exercise",
            "subcategory":"Gym",
            "type":"Entertainment"
        }
    ],
    "sg:phone":"+44 20 7284 0004",
    "sg:postcode":"BH15 3BT",
    "sg:province":"Dorset",
    "sg:tags":[
        "fitness",
        "health",
        "centre"
    ],
    "wof:name":"Fitness First Health Club",
    "wof:placetype":"venue"
},
  "geometry": {"coordinates":[-1.986768,50.733425],"type":"Point"}
}