{
  "type": "Feature",
  "properties": {
    "addr:full":"66 Rochester Place Camden Greater London NW1 9JX",
    "addr:housenumber":"66",
    "addr:postcode":"nw1 9jx",
    "addr:street":"Rochester Place",
    "iso:country":"GB",
    "sg:address":"66 Rochester Place",
    "sg:city":"Camden",
    "sg:classifiers":[
        {
            "category":"Communications",
            "subcategory":"Film & Video Production",
            "type":"Services"
        }
    ],
    "sg:phone":"+44 20 7267 9395",
    "sg:postcode":"NW1 9JX",
    "sg:province":"Greater London",
    "sg:tags":[
        "recording",
        "studio"
    ],
    "wof:name":"Multitrack Synchrotech Sales Ltd",
    "wof:placetype":"venue"
},
  "geometry": {"coordinates":[-0.140793,51.545238],"type":"Point"}
}