{
  "type": "Feature",
  "properties": {
    "addr:full":"184 Ford Green Road Stoke-on-trent Staffordshire ST6 1NF",
    "addr:housenumber":"184",
    "addr:postcode":"st6 1nf",
    "addr:street":"Ford Green Road",
    "iso:country":"GB",
    "sg:address":"184 Ford Green Road",
    "sg:city":"Stoke-on-trent",
    "sg:classifiers":[
        {
            "category":"Bars & Pubs",
            "type":"Food & Drink"
        }
    ],
    "sg:phone":"+44 1782 839231",
    "sg:postcode":"ST6 1NF",
    "sg:province":"Staffordshire",
    "sg:tags":[
        "pubs",
        "inn"
    ],
    "wof:name":"The Ford",
    "wof:placetype":"venue"
},
  "geometry": {"coordinates":[-2.169973,53.05418],"type":"Point"}
}