{
  "type": "Feature",
  "properties": {
    "iso:country":"GB",
    "sg:address":"9 Chapel Street",
    "sg:city":"Carlisle",
    "sg:classifiers":[
        {
            "category":"Professional",
            "subcategory":"Accounting & Tax Preparation",
            "type":"Services"
        }
    ],
    "sg:phone":"+44 1228 538321",
    "sg:postcode":"CA1 1JA",
    "sg:province":"Cumbria",
    "sg:tags":[
        "accountant",
        "activity"
    ],
    "wof:name":"Davis Mitchell Associates",
    "wof:placetype":"venue"
},
  "geometry": {"coordinates":[-2.932154,54.895573],"type":"Point"}
}