{
  "type": "Feature",
  "properties": {
    "iso:country":"GB",
    "sg:address":"Louisa Terrace",
    "sg:city":"Bishop Auckland",
    "sg:classifiers":[
        {
            "category":"Farming",
            "subcategory":"Dairy Farm",
            "type":"Manufacturing & Wholesale Goods"
        }
    ],
    "sg:postcode":"DL14 9BP",
    "sg:province":"Durham",
    "wof:name":"West Musgrave Farm",
    "wof:placetype":"venue"
},
  "geometry": {"coordinates":[-1.702339,54.638996],"type":"Point"}
}