{
  "type": "Feature",
  "properties": {
    "iso:country":"GB",
    "sg:address":"17-20 Greenfield",
    "sg:city":"Royston",
    "sg:classifiers":[
        {
            "category":"Shopping",
            "subcategory":"Computers & Home Electronics",
            "type":"Retail Goods"
        }
    ],
    "sg:phone":"+44 1763 252050",
    "sg:postcode":"SG8 5HN",
    "sg:province":"Bedfordshire",
    "wof:name":"Associated Furniture Industries (Seating) Ltd.",
    "wof:placetype":"venue"
},
  "geometry": {"coordinates":[-0.0387229994,52.0535812378],"type":"Point"}
}