{
  "type": "Feature",
  "properties": {
    "addr:full":"1 Quickley Lane, Chorley Wood Rickmansworth Hertfordshire WD3 5AB",
    "addr:housenumber":"1",
    "addr:postcode":"wd3 5ab",
    "addr:street":"Quickley Lane",
    "iso:country":"GB",
    "sg:address":"1 Quickley Lane, Chorley Wood",
    "sg:city":"Rickmansworth",
    "sg:classifiers":[
        {
            "category":"Building & Trades",
            "subcategory":"Cleaning & Sanitation",
            "type":"Services"
        }
    ],
    "sg:phone":"+44 1895 825663",
    "sg:postcode":"WD3 5AB",
    "sg:province":"Hertfordshire",
    "sg:tags":[
        "asbestos",
        "removal"
    ],
    "wof:name":"Bestoff Services Ltd.",
    "wof:placetype":"venue"
},
  "geometry": {"coordinates":[-0.5177699924,51.6515197754],"type":"Point"}
}