{
  "type": "Feature",
  "properties": {
    "iso:country":"GB",
    "sg:address":"194-198 Langworthy Road",
    "sg:city":"Salford",
    "sg:classifiers":[
        {
            "category":"Health Services",
            "subcategory":"Doctor",
            "type":"Services"
        }
    ],
    "sg:phone":"+44 161 736 2651",
    "sg:postcode":"M6 5PP",
    "sg:province":"Greater Manchester",
    "sg:tags":[
        "practitioners"
    ],
    "wof:name":"Salford Medical Centre",
    "wof:placetype":"venue"
},
  "geometry": {"coordinates":[-2.294663,53.487312],"type":"Point"}
}