{
  "type": "Feature",
  "properties": {
    "addr:full":"Youth Centre, Dartmouth Road Paignton Devon TQ4 6NX",
    "addr:postcode":"tq4 6nx",
    "addr:street":"Dartmouth Road",
    "iso:country":"GB",
    "sg:address":"Youth Centre, Dartmouth Road",
    "sg:city":"Paignton",
    "sg:classifiers":[
        {
            "category":"Farming",
            "subcategory":"Nursery",
            "type":"Manufacturing & Wholesale Goods"
        },
        {
            "category":"Organizations",
            "subcategory":"Non-profit Organization",
            "type":"Services"
        }
    ],
    "sg:phone":"+44 1803 559270",
    "sg:postcode":"TQ4 6NX",
    "sg:province":"Devon",
    "sg:tags":[
        "organisation",
        "creche",
        "voluntary",
        "charity"
    ],
    "wof:name":"Ymca South Devon",
    "wof:placetype":"venue"
},
  "geometry": {"coordinates":[-3.5634300709,50.4213409424],"type":"Point"}
}