{
  "type": "Feature",
  "properties": {
    "addr:full":"242 Brockhurst Rd Gosport Hampshire PO12 3BD",
    "addr:housenumber":"242",
    "addr:postcode":"po12 3bd",
    "addr:street":"Brockhurst Rd",
    "iso:country":"GB",
    "sg:address":"242 Brockhurst Rd",
    "sg:city":"Gosport",
    "sg:classifiers":[
        {
            "category":"Shopping",
            "subcategory":"News",
            "type":"Retail Goods"
        }
    ],
    "sg:postcode":"PO12 3BD",
    "sg:province":"Hampshire",
    "sg:tags":[
        "newsagent"
    ],
    "wof:name":"Bradbury,N,",
    "wof:placetype":"venue"
},
  "geometry": {"coordinates":[-1.1554390192,50.8123588562],"type":"Point"}
}