{
  "type": "Feature",
  "properties": {
    "iso:country":"GB",
    "sg:address":"2, The Arcade, 69 Poole Road",
    "sg:city":"Bournemouth",
    "sg:classifiers":[
        {
            "category":"Shopping",
            "subcategory":"Shoes",
            "type":"Retail Goods"
        }
    ],
    "sg:phone":"+44 1202 763322",
    "sg:postcode":"BH4 9BA",
    "sg:province":"Dorset",
    "sg:tags":[
        "shop",
        "retailer",
        "footwear"
    ],
    "wof:name":"Woodley's Shoes",
    "wof:placetype":"venue"
},
  "geometry": {"coordinates":[-1.902726,50.722847],"type":"Point"}
}