{
  "type": "Feature",
  "properties": {
    "addr:full":", Glenochil Menstrie Clackmannanshire FK11 7ES",
    "addr:postcode":"fk11 7es",
    "iso:country":"GB",
    "sg:address":", Glenochil",
    "sg:city":"Menstrie",
    "sg:classifiers":[
        {
            "category":"Government",
            "subcategory":"Post Office",
            "type":"Public Place"
        }
    ],
    "sg:phone":"+44 1259 761481",
    "sg:postcode":"FK11 7ES",
    "sg:province":"Clackmannanshire",
    "sg:tags":[
        "organisation",
        "soc",
        "research"
    ],
    "wof:name":"United Distillers & Vintners",
    "wof:placetype":"venue"
},
  "geometry": {"coordinates":[-3.8506538868,56.151550293],"type":"Point"}
}