{
  "type": "Feature",
  "properties": {
    "iso:country":"GB",
    "sg:address":"5 Danesbury Crescent, Kingstanding",
    "sg:city":"Birmingham",
    "sg:classifiers":[
        {
            "category":"Building & Trades",
            "subcategory":"Construction",
            "type":"Services"
        }
    ],
    "sg:phone":"+44 121 384 6250",
    "sg:postcode":"B44 0QP",
    "sg:province":"West Midlands",
    "sg:tags":[
        "decorator",
        "painter"
    ],
    "wof:name":"Harry A Smith (Great Barr) Ltd.",
    "wof:placetype":"venue"
},
  "geometry": {"coordinates":[-1.88054,52.542648],"type":"Point"}
}