{
  "type": "Feature",
  "properties": {
    "iso:country":"GB",
    "sg:address":"45 Pickford Street",
    "sg:city":"Macclesfield",
    "sg:classifiers":[
        {
            "category":"Professional",
            "subcategory":"Management & Consulting",
            "type":"Services"
        }
    ],
    "sg:postcode":"SK11 6HB",
    "sg:province":"Cheshire",
    "sg:tags":[
        "marketing",
        "consultant"
    ],
    "wof:name":"Avanti Marketing",
    "wof:placetype":"venue"
},
  "geometry": {"coordinates":[-2.124796,53.257702],"type":"Point"}
}