{
  "type": "Feature",
  "properties": {
    "addr:full":"22 New Cavendish St West End Hampshire W1M 7LH",
    "addr:housenumber":"22",
    "addr:postcode":"w1m 7lh",
    "addr:street":"New Cavendish St",
    "iso:country":"GB",
    "sg:address":"22 New Cavendish St",
    "sg:city":"West End",
    "sg:classifiers":[
        {
            "category":"Shopping",
            "subcategory":"Thrift Store",
            "type":"Retail Goods"
        }
    ],
    "sg:phone":"+44 20 7935 6547",
    "sg:postcode":"W1M 7LH",
    "sg:province":"Hampshire",
    "sg:tags":[
        "shop",
        "charity"
    ],
    "wof:name":"Sue Ryder Foundation",
    "wof:placetype":"venue"
},
  "geometry": {"coordinates":[-0.1505589932,51.5186347961],"type":"Point"}
}