{
  "type": "Feature",
  "properties": {
    "addr:full":"4 Westwinds Close, Waunarlwydd Swansea Swansea SA5 4RD",
    "addr:housenumber":"4",
    "addr:postcode":"sa5 4rd",
    "addr:street":"Westwinds Close",
    "iso:country":"GB",
    "sg:address":"4 Westwinds Close, Waunarlwydd",
    "sg:city":"Swansea",
    "sg:classifiers":[
        {
            "category":"Manufacturing",
            "subcategory":"Furniture",
            "type":"Manufacturing & Wholesale Goods"
        }
    ],
    "sg:phone":"+44 1792 875589",
    "sg:postcode":"SA5 4RD",
    "sg:province":"Swansea",
    "sg:tags":[
        "mnfr",
        "garden",
        "patio"
    ],
    "wof:name":"Paul Thomas Rustic Garden Furniture",
    "wof:placetype":"venue"
},
  "geometry": {"coordinates":[-4.0209088326,51.6381187439],"type":"Point"}
}