{
  "type": "Feature",
  "properties": {
    "addr:full":"21 Primula Drive Norwich Norfolk NR4 7LZ",
    "addr:housenumber":"21",
    "addr:postcode":"nr4 7lz",
    "addr:street":"Primula Drive",
    "iso:country":"GB",
    "sg:address":"21 Primula Drive",
    "sg:city":"Norwich",
    "sg:classifiers":[
        {
            "category":"Professional",
            "subcategory":"Engineering",
            "type":"Services"
        },
        {
            "category":"Building & Trades",
            "subcategory":"Electrical",
            "type":"Services"
        }
    ],
    "sg:phone":"+44 1603 458854",
    "sg:postcode":"NR4 7LZ",
    "sg:province":"Norfolk",
    "sg:tags":[
        "engineer",
        "electrician",
        "contractor"
    ],
    "wof:name":"T T JONES ELECTRICAL",
    "wof:placetype":"venue"
},
  "geometry": {"coordinates":[1.250277,52.628086],"type":"Point"}
}