{
  "type": "Feature",
  "properties": {
    "addr:full":"Cairngorm Whisky Centre, Inverdruie Aviemore Highland PH22 1QL",
    "addr:postcode":"ph22 1ql",
    "iso:country":"GB",
    "sg:address":"Cairngorm Whisky Centre, Inverdruie",
    "sg:city":"Aviemore",
    "sg:classifiers":[
        {
            "category":"Professional",
            "subcategory":"Art Services",
            "type":"Services"
        }
    ],
    "sg:phone":"+44 1479 810085",
    "sg:postcode":"PH22 1QL",
    "sg:province":"Highland",
    "sg:tags":[
        "carver",
        "sculptor"
    ],
    "wof:name":"Ceramic Sculptor",
    "wof:placetype":"venue"
},
  "geometry": {"coordinates":[-3.8287789822,57.1986694336],"type":"Point"}
}