{
  "type": "Feature",
  "properties": {
    "iso:country":"GB",
    "sg:address":"Suite 13-14 Richmond House",
    "sg:city":"Bristol",
    "sg:classifiers":[
        {
            "category":"Professional",
            "subcategory":"Detective & Security Services",
            "type":"Services"
        }
    ],
    "sg:postcode":"BS11 8DE",
    "sg:province":"City of Bristol",
    "wof:name":"Bell Security & Communications",
    "wof:placetype":"venue"
},
  "geometry": {"coordinates":[-2.6854190826,51.5025367737],"type":"Point"}
}