{
  "type": "Feature",
  "properties": {
    "addr:full":"Hallchurch Road, Holly Hall Dudley West Midlands DY2 0TQ",
    "addr:postcode":"dy2 0tq",
    "addr:street":"Hallchurch Road",
    "iso:country":"GB",
    "sg:address":"Hallchurch Road, Holly Hall",
    "sg:city":"Dudley",
    "sg:classifiers":[
        {
            "category":"Retail",
            "subcategory":"Auto Repair",
            "type":"Services"
        }
    ],
    "sg:phone":"+44 1384 78073",
    "sg:postcode":"DY2 0TQ",
    "sg:province":"West Midlands",
    "sg:tags":[
        "modification",
        "garage",
        "related"
    ],
    "wof:name":"Sharp's Repairs & Resprays Ltd.",
    "wof:placetype":"venue"
},
  "geometry": {"coordinates":[-2.107117,52.498268],"type":"Point"}
}