{
  "type": "Feature",
  "properties": {
    "addr:full":"2 Upper Teddington Rd, Hampton Wick Kingston Upon Thames Greater London KT1 4DY",
    "addr:housenumber":"2",
    "addr:postcode":"kt1 4dy",
    "addr:street":"Upper Teddington Rd",
    "iso:country":"GB",
    "sg:address":"2 Upper Teddington Rd, Hampton Wick",
    "sg:city":"Kingston Upon Thames",
    "sg:classifiers":[
        {
            "category":"Banks & Credit Unions",
            "subcategory":"Investment Brokerage",
            "type":"Services"
        }
    ],
    "sg:phone":"+44 20 8296 8543",
    "sg:postcode":"KT1 4DY",
    "sg:province":"Greater London",
    "wof:name":"Michael Laurie Securities",
    "wof:placetype":"venue"
},
  "geometry": {"coordinates":[-0.3138380051,51.4161682129],"type":"Point"}
}