{
  "type": "Feature",
  "properties": {
    "iso:country":"GB",
    "sg:address":"14 High West Street",
    "sg:city":"Dorchester",
    "sg:classifiers":[
        {
            "category":"Professional",
            "subcategory":"Lawyer & Legal Services",
            "type":"Services"
        }
    ],
    "sg:phone":"+44 1305 266866",
    "sg:postcode":"DT1 1UW",
    "sg:province":"Dorset",
    "sg:tags":[
        "solicitor"
    ],
    "wof:name":"Williamson & Co",
    "wof:placetype":"venue"
},
  "geometry": {"coordinates":[-2.438421,50.715157],"type":"Point"}
}