{
  "type": "Feature",
  "properties": {
    "addr:full":"Ashley House, 30 Saint Andrews Street Northampton Northamptonshire NN1 2HY",
    "addr:housenumber":"30",
    "addr:postcode":"nn1 2hy",
    "addr:street":"Saint Andrews Street",
    "iso:country":"GB",
    "sg:address":"Ashley House, 30 Saint Andrews Street",
    "sg:city":"Northampton",
    "sg:classifiers":[
        {
            "category":"Professional",
            "subcategory":"Employment Agencies",
            "type":"Services"
        }
    ],
    "sg:postcode":"NN1 2HY",
    "sg:province":"Northamptonshire",
    "sg:tags":[
        "consultant"
    ],
    "wof:name":"Palmer Recruitment Ltd",
    "wof:placetype":"venue"
},
  "geometry": {"coordinates":[-0.900248,52.240711],"type":"Point"}
}