{
  "type": "Feature",
  "properties": {
    "iso:country":"GB",
    "sg:address":"Pontrilas",
    "sg:city":"Hereford",
    "sg:classifiers":[
        {
            "category":"Manufacturing",
            "subcategory":"Building Materials",
            "type":"Manufacturing & Wholesale Goods"
        }
    ],
    "sg:phone":"+44 1981 242900",
    "sg:postcode":"HR2 0DJ",
    "sg:province":"Herefordshire",
    "sg:tags":[
        "mnfr",
        "maker",
        "cabinet"
    ],
    "wof:name":"Wyefront Ltd.",
    "wof:placetype":"venue"
},
  "geometry": {"coordinates":[-2.8842,51.940701],"type":"Point"}
}