{
  "type": "Feature",
  "properties": {
    "addr:full":"Unit 1a Parc-y-bont, Aneurin Bevan Av, Brynmenyn Industria Bridgend Bridgend CF32 9SZ",
    "addr:housenumber":"unit 1a",
    "addr:postcode":"cf32 9sz",
    "addr:street":"Parc-Y-Bont Aneurin Bevan Av Brynmenyn Industria",
    "iso:country":"GB",
    "sg:address":"Unit 1a Parc-y-bont, Aneurin Bevan Av, Brynmenyn Industria",
    "sg:city":"Bridgend",
    "sg:classifiers":[
        {
            "category":"Building & Trades",
            "subcategory":"Cleaning & Sanitation",
            "type":"Services"
        }
    ],
    "sg:phone":"+44 1656 722133",
    "sg:postcode":"CF32 9SZ",
    "sg:province":"Bridgend",
    "sg:tags":[
        "commercial"
    ],
    "wof:name":"O C S Cleaning Wales Ltd",
    "wof:placetype":"venue"
},
  "geometry": {"coordinates":[-3.5817439556,51.5513801575],"type":"Point"}
}