{
  "type": "Feature",
  "properties": {
    "addr:full":"Batchartfarms, Blairs Aberdeen Aberdeen City AB1 5YQ",
    "addr:postcode":"ab1 5yq",
    "addr:street":"Blairs",
    "iso:country":"GB",
    "sg:address":"Batchartfarms, Blairs",
    "sg:city":"Aberdeen",
    "sg:classifiers":[
        {
            "category":"Farming",
            "subcategory":"Livestock Farm",
            "type":"Manufacturing & Wholesale Goods"
        }
    ],
    "sg:postcode":"AB1 5YQ",
    "sg:province":"Aberdeen City",
    "sg:tags":[
        "others"
    ],
    "wof:name":"Middleton,James F,",
    "wof:placetype":"venue"
},
  "geometry": {"coordinates":[-2.1865000725,57.0905914307],"type":"Point"}
}