{
  "type": "Feature",
  "properties": {
    "addr:full":"Unit 10 Willson Bros Mills, Mill Lane Dewsbury West Yorkshire WF12 8NG",
    "addr:housenumber":"unit 10",
    "addr:postcode":"wf12 8ng",
    "addr:street":"Mills Mill Lane",
    "iso:country":"GB",
    "sg:address":"Unit 10 Willson Bros Mills, Mill Lane",
    "sg:city":"Dewsbury",
    "sg:classifiers":[
        {
            "category":"Building & Trades",
            "subcategory":"Construction",
            "type":"Services"
        }
    ],
    "sg:postcode":"WF12 8NG",
    "sg:province":"West Yorkshire",
    "sg:tags":[
        "joinery"
    ],
    "wof:name":"J D Joinery",
    "wof:placetype":"venue"
},
  "geometry": {"coordinates":[-1.60265,53.68671],"type":"Point"}
}