{
  "type": "Feature",
  "properties": {
    "addr:full":"19-21 Palace St Westminster Greater London SW1E 5HS",
    "addr:housenumber":"19-21",
    "addr:postcode":"sw1e 5hs",
    "addr:street":"Palace St",
    "iso:country":"GB",
    "sg:address":"19-21 Palace St",
    "sg:city":"Westminster",
    "sg:classifiers":[
        {
            "category":"Banks & Credit Unions",
            "subcategory":"Financial Services",
            "type":"Services"
        }
    ],
    "sg:phone":"+44 20 7233 8522",
    "sg:postcode":"SW1E 5HS",
    "sg:province":"Greater London",
    "sg:tags":[
        "adviser"
    ],
    "wof:name":"Whitehead Associates",
    "wof:placetype":"venue"
},
  "geometry": {"coordinates":[-0.1413159966,51.4988098145],"type":"Point"}
}