{
  "type": "Feature",
  "properties": {
    "addr:full":"Sampool Caravan Park, Levens Kendal Cumbria LA8 8EQ",
    "addr:postcode":"la8 8eq",
    "addr:street":"Levens Kendal",
    "iso:country":"GB",
    "sg:address":"Sampool Caravan Park, Levens",
    "sg:city":"Kendal",
    "sg:classifiers":[
        {
            "category":"Recreation",
            "subcategory":"Campground",
            "type":"Entertainment"
        }
    ],
    "sg:phone":"+44 15395 52265",
    "sg:postcode":"LA8 8EQ",
    "sg:province":"Cumbria",
    "sg:tags":[
        "caravan",
        "park"
    ],
    "wof:name":"Alan Dobson",
    "wof:placetype":"venue"
},
  "geometry": {"coordinates":[-2.788899,54.269066],"type":"Point"}
}