{
  "type": "Feature",
  "properties": {
    "addr:full":"114 Warbreck Moor Liverpool Merseyside L9 0HY",
    "addr:housenumber":"114",
    "addr:postcode":"l9 0hy",
    "addr:street":"Warbreck Moor",
    "iso:country":"GB",
    "sg:address":"114 Warbreck Moor",
    "sg:city":"Liverpool",
    "sg:classifiers":[
        {
            "category":"Retail",
            "subcategory":"Repair Shop",
            "type":"Services"
        }
    ],
    "sg:phone":"+44 151 521 8697",
    "sg:postcode":"L9 0HY",
    "sg:province":"Merseyside",
    "sg:tags":[
        "upholsterer"
    ],
    "wof:name":"T Davies Upholsterer",
    "wof:placetype":"venue"
},
  "geometry": {"coordinates":[-2.9557058811,53.4681396484],"type":"Point"}
}