{
  "type": "Feature",
  "properties": {
    "addr:full":"Dolgwm Uchaf, Pencarreg Llanybydder Carmarthenshire SA40 9QN",
    "addr:postcode":"sa40 9qn",
    "iso:country":"GB",
    "sg:address":"Dolgwm Uchaf, Pencarreg",
    "sg:city":"Llanybydder",
    "sg:classifiers":[
        {
            "category":"Farming",
            "subcategory":"Livestock Farm",
            "type":"Manufacturing & Wholesale Goods"
        }
    ],
    "sg:phone":"+44 1570 422270",
    "sg:postcode":"SA40 9QN",
    "sg:province":"Carmarthenshire",
    "sg:tags":[
        "others"
    ],
    "wof:name":"A G Thomas",
    "wof:placetype":"venue"
},
  "geometry": {"coordinates":[-4.1583609581,52.0739364624],"type":"Point"}
}