{
  "type": "Feature",
  "properties": {
    "iso:country":"GB",
    "sg:address":"Unit 2 203 Old Oak Common La",
    "sg:city":"Acton",
    "sg:classifiers":[
        {
            "category":"Freight",
            "type":"Transportation"
        }
    ],
    "sg:phone":"+44 20 8740 5731",
    "sg:postcode":"W3 7DX",
    "sg:province":"Greater London",
    "sg:tags":[
        "overseas",
        "shipping",
        "removal"
    ],
    "wof:name":"RDS Ltd",
    "wof:placetype":"venue"
},
  "geometry": {"coordinates":[-0.248821,51.513535],"type":"Point"}
}