{
  "type": "Feature",
  "properties": {
    "iso:country":"GB",
    "sg:address":"23 Rutland Square",
    "sg:city":"Edinburgh",
    "sg:classifiers":[
        {
            "category":"Professional",
            "subcategory":"Accounting & Tax Preparation",
            "type":"Services"
        }
    ],
    "sg:phone":"+44 131 229 7401",
    "sg:postcode":"EH1 2BP",
    "sg:province":"City of Edinburgh",
    "sg:tags":[
        "accountant"
    ],
    "wof:name":"Dalgliesh & Tullo",
    "wof:placetype":"venue"
},
  "geometry": {"coordinates":[-3.209745,55.948738],"type":"Point"}
}