{
  "type": "Feature",
  "properties": {
    "addr:full":"Unit 7, Ardley Works, London Rd Billericay Essex CM12 9HP",
    "addr:housenumber":"unit 7 ardley",
    "addr:postcode":"cm12 9hp",
    "addr:street":"London Rd",
    "iso:country":"GB",
    "sg:address":"Unit 7, Ardley Works, London Rd",
    "sg:city":"Billericay",
    "sg:classifiers":[
        {
            "category":"Retail",
            "subcategory":"Auto Repair",
            "type":"Services"
        }
    ],
    "sg:phone":"+44 1277 634431",
    "sg:postcode":"CM12 9HP",
    "sg:province":"Essex",
    "sg:tags":[
        "modification",
        "garage"
    ],
    "wof:name":"Automania",
    "wof:placetype":"venue"
},
  "geometry": {"coordinates":[0.4168550074,51.62474823],"type":"Point"}
}