{
  "type": "Feature",
  "properties": {
    "addr:full":"Grosvenor House, Market Street Bromsgrove Worcestershire B61 8DA",
    "addr:postcode":"b61 8da",
    "addr:street":"Market Street",
    "iso:country":"GB",
    "sg:address":"Grosvenor House, Market Street",
    "sg:city":"Bromsgrove",
    "sg:classifiers":[
        {
            "category":"Communications",
            "type":"Services"
        },
        {
            "category":"Professional",
            "subcategory":"Computer Services",
            "type":"Services"
        }
    ],
    "sg:phone":"+44 1527 571700",
    "sg:postcode":"B61 8DA",
    "sg:province":"Worcestershire",
    "sg:tags":[
        "software",
        "data",
        "network",
        "system"
    ],
    "wof:name":"Isl Biometrics Ltd.",
    "wof:placetype":"venue"
},
  "geometry": {"coordinates":[-2.059344,52.336842],"type":"Point"}
}