{
  "type": "Feature",
  "properties": {
    "addr:full":"75 Alderley Rd Wilmslow Cheshire SK9 1PA",
    "addr:housenumber":"75",
    "addr:postcode":"sk9 1pa",
    "addr:street":"Alderley Rd",
    "iso:country":"GB",
    "sg:address":"75 Alderley Rd",
    "sg:city":"Wilmslow",
    "sg:classifiers":[
        {
            "category":"Health Services",
            "subcategory":"Clinic",
            "type":"Services"
        }
    ],
    "sg:phone":"+44 1625 531000",
    "sg:postcode":"SK9 1PA",
    "sg:province":"Cheshire",
    "sg:tags":[
        "private"
    ],
    "wof:name":"Stephen Charles",
    "wof:placetype":"venue"
},
  "geometry": {"coordinates":[-2.2355079651,53.3231124878],"type":"Point"}
}