{
  "type": "Feature",
  "properties": {
    "addr:full":"West Bay, Maenporth Road Falmouth Cornwall TR11 5HP",
    "addr:postcode":"tr11 5hp",
    "addr:street":"Maenporth Road",
    "iso:country":"GB",
    "sg:address":"West Bay, Maenporth Road",
    "sg:city":"Falmouth",
    "sg:classifiers":[
        {
            "category":"Travel",
            "subcategory":"Hotels & Motels",
            "type":"Entertainment"
        }
    ],
    "sg:postcode":"TR11 5HP",
    "sg:province":"Cornwall",
    "sg:tags":[
        "self",
        "catering"
    ],
    "wof:name":"West Bay Hotel and Flats",
    "wof:placetype":"venue"
},
  "geometry": {"coordinates":[-5.0941519737,50.1250495911],"type":"Point"}
}