{
  "type": "Feature",
  "properties": {
    "addr:full":"21-25 Baltic Lane, Dalmarnock Glasgow Glasgow City G40 4UB",
    "addr:housenumber":"21-25",
    "addr:postcode":"g40 4ub",
    "addr:street":"Baltic Lane",
    "iso:country":"GB",
    "sg:address":"21-25 Baltic Lane, Dalmarnock",
    "sg:city":"Glasgow",
    "sg:classifiers":[
        {
            "category":"Building & Trades",
            "subcategory":"Construction",
            "type":"Services"
        }
    ],
    "sg:phone":"+44 141 556 6441",
    "sg:postcode":"G40 4UB",
    "sg:province":"Glasgow City",
    "sg:tags":[
        "builder"
    ],
    "wof:name":"Helforn Ltd.",
    "wof:placetype":"venue"
},
  "geometry": {"coordinates":[-4.215848,55.843067],"type":"Point"}
}