{
  "type": "Feature",
  "properties": {
    "iso:country":"GB",
    "sg:address":"Kesteven Street",
    "sg:city":"Sleaford",
    "sg:classifiers":[
        {
            "category":"Organizations",
            "subcategory":"Non-profit Organization",
            "type":"Services"
        }
    ],
    "sg:phone":"+44 1529 415417",
    "sg:postcode":"NG34 7DT",
    "sg:province":"Lincolnshire",
    "sg:tags":[
        "organisation",
        "voluntary",
        "charity"
    ],
    "wof:name":"Sleaford & District Volunteer Bureau",
    "wof:placetype":"venue"
},
  "geometry": {"coordinates":[-0.406329,52.99966],"type":"Point"}
}