{
  "type": "Feature",
  "properties": {
    "addr:full":"17 Lawrence Road Liverpool Merseyside L15 0EE",
    "addr:housenumber":"17",
    "addr:postcode":"l15 0ee",
    "addr:street":"Lawrence Road",
    "iso:country":"GB",
    "sg:address":"17 Lawrence Road",
    "sg:city":"Liverpool",
    "sg:classifiers":[
        {
            "category":"Bars & Pubs",
            "type":"Food & Drink"
        }
    ],
    "sg:postcode":"L15 0EE",
    "sg:province":"Merseyside",
    "sg:tags":[
        "pubs",
        "inn"
    ],
    "wof:name":"The Ashdale Inn",
    "wof:placetype":"venue"
},
  "geometry": {"coordinates":[-2.9377009869,53.3978652954],"type":"Point"}
}