{
  "type": "Feature",
  "properties": {
    "addr:full":"28 Portland Walk Barrow In Furness Cumbria LA14 1DB",
    "addr:housenumber":"28",
    "addr:postcode":"la14 1db",
    "addr:street":"Portland Walk",
    "iso:country":"GB",
    "sg:address":"28 Portland Walk",
    "sg:city":"Barrow In Furness",
    "sg:classifiers":[
        {
            "category":"Shopping",
            "subcategory":"Clothing, Apparel, & Fashions",
            "type":"Retail Goods"
        }
    ],
    "sg:phone":"+44 1229 870466",
    "sg:postcode":"LA14 1DB",
    "sg:province":"Cumbria",
    "sg:tags":[
        "menswear"
    ],
    "wof:name":"Top Man",
    "wof:placetype":"venue"
},
  "geometry": {"coordinates":[-3.2149970531,54.1359863281],"type":"Point"}
}