{
  "type": "Feature",
  "properties": {
    "iso:country":"GB",
    "sg:address":"Buena Vista, St Fagans",
    "sg:city":"Cardiff",
    "sg:classifiers":[
        {
            "category":"Transit Center",
            "subcategory":"Passenger",
            "type":"Transportation"
        },
        {
            "category":"Retail",
            "subcategory":"Pet Boarding",
            "type":"Services"
        }
    ],
    "sg:phone":"+44 29 2059 1520",
    "sg:postcode":"CF5 6DW",
    "sg:province":"Cardiff",
    "sg:tags":[
        "kennel",
        "catteries"
    ],
    "wof:name":"St Fagans Cattery",
    "wof:placetype":"venue"
},
  "geometry": {"coordinates":[-3.267334,51.489689],"type":"Point"}
}