{
  "type": "Feature",
  "properties": {
    "iso:country":"GB",
    "sg:address":"Unit A, Sprint Industrial Estate",
    "sg:city":"West Byfleet",
    "sg:classifiers":[
        {
            "category":"Shopping",
            "subcategory":"Stationery & Office Supplies",
            "type":"Retail Goods"
        }
    ],
    "sg:phone":"+44 1932 336262",
    "sg:postcode":"KT14 7BD",
    "sg:province":"Surrey",
    "sg:tags":[
        "printers'"
    ],
    "wof:name":"Eurograv Ltd.",
    "wof:placetype":"venue"
},
  "geometry": {"coordinates":[-0.472594,51.33794],"type":"Point"}
}