{
  "type": "Feature",
  "properties": {
    "iso:country":"GB",
    "sg:address":"52 Grange Gardens",
    "sg:city":"Pinner",
    "sg:classifiers":[
        {
            "category":"Organizations",
            "subcategory":"Non-profit Organization",
            "type":"Services"
        }
    ],
    "sg:phone":"+44 20 8429 2358",
    "sg:postcode":"HA5 5QE",
    "sg:province":"Greater London",
    "sg:tags":[
        "charitable",
        "organisation",
        "voluntary",
        "charity"
    ],
    "wof:name":"National Childbirth Trust",
    "wof:placetype":"venue"
},
  "geometry": {"coordinates":[-0.377254,51.591858],"type":"Point"}
}