{
  "type": "Feature",
  "properties": {
    "addr:full":"Thomas Buxton School House, Buxton Street London Greater London E1 5AR",
    "addr:postcode":"e1 5ar",
    "addr:street":"Buxton Street",
    "iso:country":"GB",
    "sg:address":"Thomas Buxton School House, Buxton Street",
    "sg:city":"London",
    "sg:classifiers":[
        {
            "category":"Education",
            "subcategory":"School",
            "type":"Public Place"
        }
    ],
    "sg:phone":"+44 20 7247 5343",
    "sg:postcode":"E1 5AR",
    "sg:province":"Greater London",
    "sg:tags":[
        "local",
        "authority"
    ],
    "wof:name":"Thomas Buxton Infant School",
    "wof:placetype":"venue"
},
  "geometry": {"coordinates":[-0.0657360032,51.5215873718],"type":"Point"}
}