{
  "type": "Feature",
  "properties": {
    "iso:country":"GB",
    "sg:address":"The Old Treasury, 7 Kings Road",
    "sg:city":"Southsea",
    "sg:classifiers":[
        {
            "category":"Real Estate",
            "subcategory":"Developer",
            "type":"Services"
        }
    ],
    "sg:postcode":"PO5 4DJ",
    "sg:province":"Hampshire",
    "sg:tags":[
        "property"
    ],
    "wof:name":"Endymion Elysium Ltd",
    "wof:placetype":"venue"
},
  "geometry": {"coordinates":[-1.0881639719,50.7846641541],"type":"Point"}
}