{
  "type": "Feature",
  "properties": {
    "addr:full":"Station Works, Glannant Estate Knighton Shropshire LD7 1PN",
    "addr:postcode":"ld7 1pn",
    "iso:country":"GB",
    "sg:address":"Station Works, Glannant Estate",
    "sg:city":"Knighton",
    "sg:classifiers":[
        {
            "category":"Building & Trades",
            "subcategory":"Construction",
            "type":"Services"
        }
    ],
    "sg:phone":"+44 1547 520220",
    "sg:postcode":"LD7 1PN",
    "sg:province":"Shropshire",
    "sg:tags":[
        "joinery"
    ],
    "wof:name":"Gibney Joinery",
    "wof:placetype":"venue"
},
  "geometry": {"coordinates":[-3.0477099419,52.3430671692],"type":"Point"}
}