{
  "type": "Feature",
  "properties": {
    "iso:country":"GB",
    "sg:address":"149-151 Kingston Road, Willerby",
    "sg:city":"Hull",
    "sg:classifiers":[
        {
            "category":"Home & Garden",
            "subcategory":"Household Appliances",
            "type":"Retail Goods"
        }
    ],
    "sg:phone":"+44 1482 658215",
    "sg:postcode":"HU10 6AL",
    "sg:province":"East Riding of Yorkshire",
    "sg:tags":[
        "electrical",
        "domestic"
    ],
    "wof:name":"Nu-Way Television Ltd.",
    "wof:placetype":"venue"
},
  "geometry": {"coordinates":[-0.435815,53.754642],"type":"Point"}
}