{
  "type": "Feature",
  "properties": {
    "addr:full":"Restmor Way Wallington Surrey SM6 7AH",
    "addr:postcode":"sm6 7ah",
    "addr:street":"Restmor Way",
    "iso:country":"GB",
    "sg:address":"Restmor Way",
    "sg:city":"Wallington",
    "sg:classifiers":[
        {
            "category":"Professional",
            "subcategory":"Management & Consulting",
            "type":"Services"
        }
    ],
    "sg:phone":"+44 20 8241 2458",
    "sg:postcode":"SM6 7AH",
    "sg:province":"Surrey",
    "sg:tags":[
        "consultant",
        "business"
    ],
    "wof:name":"C P A CONSULTING GROUP",
    "wof:placetype":"venue"
},
  "geometry": {"coordinates":[-0.158191,51.376118],"type":"Point"}
}