{
  "type": "Feature",
  "properties": {
    "addr:full":"1 Severn Road Gloucester Gloucestershire GL1 2LE",
    "addr:housenumber":"1",
    "addr:postcode":"gl1 2le",
    "addr:street":"Severn Road",
    "iso:country":"GB",
    "sg:address":"1 Severn Road",
    "sg:city":"Gloucester",
    "sg:classifiers":[
        {
            "category":"Professional",
            "subcategory":"Management & Consulting",
            "type":"Services"
        }
    ],
    "sg:postcode":"GL1 2LE",
    "sg:province":"Gloucestershire",
    "sg:tags":[
        "marketing",
        "consultant"
    ],
    "wof:name":"Charles Wright",
    "wof:placetype":"venue"
},
  "geometry": {"coordinates":[-2.2539410591,51.8633880615],"type":"Point"}
}