{
  "type": "Feature",
  "properties": {
    "iso:country":"GB",
    "sg:address":"Cameron Holdings, Mainsforth Terr",
    "sg:city":"Hartlepool",
    "sg:classifiers":[
        {
            "category":"Military Area",
            "subcategory":"Air Force Base",
            "type":"Public Place"
        }
    ],
    "sg:phone":"+44 1429 866660",
    "sg:postcode":"TS25 1TZ",
    "sg:province":"Durham",
    "sg:tags":[
        "taxi",
        "hire",
        "private"
    ],
    "wof:name":"B Line Taxis",
    "wof:placetype":"venue"
},
  "geometry": {"coordinates":[-1.20121,54.676651],"type":"Point"}
}