{
  "type": "Feature",
  "properties": {
    "addr:full":"18-20 Norwich Walk Basildon Essex SS14 3QP",
    "addr:housenumber":"18-20",
    "addr:postcode":"ss14 3qp",
    "addr:street":"Norwich Walk",
    "iso:country":"GB",
    "sg:address":"18-20 Norwich Walk",
    "sg:city":"Basildon",
    "sg:classifiers":[
        {
            "category":"Food & Beverages",
            "subcategory":"Supermarket",
            "type":"Retail Goods"
        }
    ],
    "sg:phone":"+44 1268 533711",
    "sg:postcode":"SS14 3QP",
    "sg:province":"Essex",
    "wof:name":"A C Ward & Son Ltd.",
    "wof:placetype":"venue"
},
  "geometry": {"coordinates":[0.4924249947,51.5771446228],"type":"Point"}
}