{
  "type": "Feature",
  "properties": {
    "addr:full":"Wayside Mold Denbighshire CH7 5PE",
    "addr:postcode":"ch7 5pe",
    "iso:country":"GB",
    "sg:address":"Wayside",
    "sg:city":"Mold",
    "sg:classifiers":[
        {
            "category":"Shopping",
            "subcategory":"Gifts & Souvenirs",
            "type":"Retail Goods"
        }
    ],
    "sg:phone":"+44 1352 740936",
    "sg:postcode":"CH7 5PE",
    "sg:province":"Denbighshire",
    "sg:tags":[
        "giftware"
    ],
    "wof:name":"Celmi Candles",
    "wof:placetype":"venue"
},
  "geometry": {"coordinates":[-3.216679,53.20002],"type":"Point"}
}