{
  "type": "Feature",
  "properties": {
    "iso:country":"GB",
    "sg:address":"41-43 Standard Road",
    "sg:city":"London",
    "sg:classifiers":[
        {
            "category":"Wholesale",
            "subcategory":"Groceries",
            "type":"Manufacturing & Wholesale Goods"
        },
        {
            "category":"Food & Beverages",
            "subcategory":"Meat & Fish",
            "type":"Retail Goods"
        }
    ],
    "sg:phone":"+44 20 8965 3444",
    "sg:postcode":"NW10 6HF",
    "sg:province":"Greater London",
    "sg:tags":[
        "supplier",
        "drink",
        "butcher"
    ],
    "wof:name":"Manaco (Mian) Ltd.",
    "wof:placetype":"venue"
},
  "geometry": {"coordinates":[-0.2636510134,51.5283050537],"type":"Point"}
}