{
  "type": "Feature",
  "properties": {
    "addr:full":"North View, Ryhope Sunderland Tyne and Wear SR2 0PE",
    "addr:postcode":"sr2 0pe",
    "addr:street":"North",
    "iso:country":"GB",
    "sg:address":"North View, Ryhope",
    "sg:city":"Sunderland",
    "sg:classifiers":[
        {
            "category":"Building & Trades",
            "subcategory":"Equipment Rental",
            "type":"Services"
        }
    ],
    "sg:phone":"+44 191 521 0472",
    "sg:postcode":"SR2 0PE",
    "sg:province":"Tyne and Wear",
    "sg:tags":[
        "plant",
        "machinery"
    ],
    "wof:name":"Forster Plant Hire",
    "wof:placetype":"venue"
},
  "geometry": {"coordinates":[-1.363809,54.866879],"type":"Point"}
}