{
  "type": "Feature",
  "properties": {
    "iso:country":"GB",
    "sg:address":"150 High Street",
    "sg:city":"Colchester",
    "sg:classifiers":[
        {
            "category":"Recreation",
            "subcategory":"Fishing",
            "type":"Entertainment"
        }
    ],
    "sg:phone":"+44 1206 572758",
    "sg:postcode":"CO1 1PG",
    "sg:province":"Essex",
    "sg:tags":[
        "angling"
    ],
    "wof:name":"K D Radcliffe Ltd.",
    "wof:placetype":"venue"
},
  "geometry": {"coordinates":[0.897684,51.889771],"type":"Point"}
}