{
  "type": "Feature",
  "properties": {
    "addr:full":"High House, Harlington Road Uxbridge Buckinghamshire UB8 3HX",
    "addr:postcode":"ub8 3hx",
    "addr:street":"High;Harlington Road",
    "iso:country":"GB",
    "sg:address":"High House, Harlington Road",
    "sg:city":"Uxbridge",
    "sg:classifiers":[
        {
            "category":"Health Services",
            "subcategory":"Dentist",
            "type":"Services"
        }
    ],
    "sg:phone":"+44 1895 273107",
    "sg:postcode":"UB8 3HX",
    "sg:province":"Buckinghamshire",
    "sg:tags":[
        "technician",
        "dental"
    ],
    "wof:name":"Riverside Ceramics",
    "wof:placetype":"venue"
},
  "geometry": {"coordinates":[-0.456736,51.5341],"type":"Point"}
}