{
  "type": "Feature",
  "properties": {
    "addr:full":"Unit 3 Southgate Works, Southgate Preston Lancashire PR1 1NP",
    "addr:housenumber":"unit 3",
    "addr:postcode":"pr1 1np",
    "addr:street":"Southgate Works Southgate",
    "iso:country":"GB",
    "sg:address":"Unit 3 Southgate Works, Southgate",
    "sg:city":"Preston",
    "sg:classifiers":[
        {
            "category":"Wholesale",
            "subcategory":"Scrap",
            "type":"Manufacturing & Wholesale Goods"
        }
    ],
    "sg:postcode":"PR1 1NP",
    "sg:province":"Lancashire",
    "sg:tags":[
        "car",
        "breaker",
        "dismantlers"
    ],
    "wof:name":"Oriental Auto Spares Ltd.",
    "wof:placetype":"venue"
},
  "geometry": {"coordinates":[-2.7032489777,53.7679214478],"type":"Point"}
}