{
  "type": "Feature",
  "properties": {
    "addr:full":"D S E Studios, Great Wolford Shipston-on-stour Warwickshire CV36 5NQ",
    "addr:postcode":"cv36 5nq",
    "addr:street":"D",
    "iso:country":"GB",
    "sg:address":"D S E Studios, Great Wolford",
    "sg:city":"Shipston-on-stour",
    "sg:classifiers":[
        {
            "category":"Manufacturing",
            "subcategory":"Wood Products",
            "type":"Manufacturing & Wholesale Goods"
        }
    ],
    "sg:phone":"+44 1608 674312",
    "sg:postcode":"CV36 5NQ",
    "sg:province":"Warwickshire",
    "sg:tags":[
        "craftsman"
    ],
    "wof:name":"Mornington Day C",
    "wof:placetype":"venue"
},
  "geometry": {"coordinates":[-1.6388360262,52.0096092224],"type":"Point"}
}