{
  "type": "Feature",
  "properties": {
    "addr:full":"152-154 New Road, Rubery, Rednal Birmingham West Midlands B45 9JA",
    "addr:housenumber":"152-154",
    "addr:postcode":"b45 9ja",
    "addr:street":"New Road;Rednal",
    "iso:country":"GB",
    "sg:address":"152-154 New Road, Rubery, Rednal",
    "sg:city":"Birmingham",
    "sg:classifiers":[
        {
            "category":"Insurance",
            "subcategory":"Insurance Agent",
            "type":"Services"
        }
    ],
    "sg:postcode":"B45 9JA",
    "sg:province":"West Midlands",
    "wof:name":"Swinton",
    "wof:placetype":"venue"
},
  "geometry": {"coordinates":[-2.0190041065,52.3931884766],"type":"Point"}
}