{
  "type": "Feature",
  "properties": {
    "addr:full":"Lower Dowshaw Farm, Lothersdale Keighley North Yorkshire BD20 8HN",
    "addr:postcode":"bd20 8hn",
    "iso:country":"GB",
    "sg:address":"Lower Dowshaw Farm, Lothersdale",
    "sg:city":"Keighley",
    "sg:classifiers":[
        {
            "category":"Farming",
            "subcategory":"Farm",
            "type":"Manufacturing & Wholesale Goods"
        }
    ],
    "sg:phone":"+44 1535 630763",
    "sg:postcode":"BD20 8HN",
    "sg:province":"North Yorkshire",
    "sg:tags":[
        "mixed",
        "crop"
    ],
    "wof:name":"M & G Booth",
    "wof:placetype":"venue"
},
  "geometry": {"coordinates":[-2.067531,53.908802],"type":"Point"}
}