{
  "type": "Feature",
  "properties": {
    "addr:full":"241 County Road Liverpool Merseyside L4 5TE",
    "addr:housenumber":"241",
    "addr:postcode":"l4 5te",
    "addr:street":"County Road",
    "iso:country":"GB",
    "sg:address":"241 County Road",
    "sg:city":"Liverpool",
    "sg:classifiers":[
        {
            "category":"Personal",
            "subcategory":"Beauty Salon",
            "type":"Services"
        }
    ],
    "sg:phone":"+44 151 525 0497",
    "sg:postcode":"L4 5TE",
    "sg:province":"Merseyside",
    "sg:tags":[
        "unisex",
        "hairdresser"
    ],
    "wof:name":"Dennis's",
    "wof:placetype":"venue"
},
  "geometry": {"coordinates":[-2.967971,53.445854],"type":"Point"}
}