{
  "type": "Feature",
  "properties": {
    "iso:country":"GB",
    "sg:address":"5 Mosman Terrace",
    "sg:city":"Middlesbrough",
    "sg:classifiers":[
        {
            "category":"Personal",
            "subcategory":"Beauty Salon",
            "type":"Services"
        }
    ],
    "sg:phone":"+44 1642 271255",
    "sg:postcode":"TS3 6QG",
    "sg:province":"North Yorkshire",
    "sg:tags":[
        "lady",
        "hairdresser"
    ],
    "wof:name":"Maureens",
    "wof:placetype":"venue"
},
  "geometry": {"coordinates":[-1.209788,54.568623],"type":"Point"}
}