{
  "type": "Feature",
  "properties": {
    "addr:full":"48-52 Hexworthy Ave Coventry Warwickshire CV3 6LT",
    "addr:housenumber":"48-52",
    "addr:postcode":"cv3 6lt",
    "addr:street":"Hexworthy Ave",
    "iso:country":"GB",
    "sg:address":"48-52 Hexworthy Ave",
    "sg:city":"Coventry",
    "sg:classifiers":[
        {
            "category":"Professional",
            "subcategory":"Business Services",
            "type":"Services"
        }
    ],
    "sg:postcode":"CV3 6LT",
    "sg:province":"Warwickshire",
    "sg:tags":[
        "tile",
        "stockist"
    ],
    "wof:name":"First Choice Tile Supplies Ltd",
    "wof:placetype":"venue"
},
  "geometry": {"coordinates":[-1.521731019,52.3833045959],"type":"Point"}
}