{
  "type": "Feature",
  "properties": {
    "iso:country":"GB",
    "sg:address":"35 Leafield Road",
    "sg:city":"Solihull",
    "sg:classifiers":[
        {
            "category":"Building & Trades",
            "subcategory":"Construction",
            "type":"Services"
        }
    ],
    "sg:phone":"+44 121 742 3763",
    "sg:postcode":"B92 8NZ",
    "sg:province":"West Midlands",
    "sg:tags":[
        "roofing",
        "contracting"
    ],
    "wof:name":"RAYMOND DYKE",
    "wof:placetype":"venue"
},
  "geometry": {"coordinates":[-1.7784769535,52.438949585],"type":"Point"}
}