{
  "type": "Feature",
  "properties": {
    "addr:full":"14 Hitchmead Rd Biggleswade Bedfordshire SG18 0NH",
    "addr:housenumber":"14",
    "addr:postcode":"sg18 0nh",
    "addr:street":"Hitchmead Rd",
    "iso:country":"GB",
    "sg:address":"14 Hitchmead Rd",
    "sg:city":"Biggleswade",
    "sg:classifiers":[
        {
            "category":"Freight",
            "type":"Transportation"
        }
    ],
    "sg:phone":"+44 1767 313094",
    "sg:postcode":"SG18 0NH",
    "sg:province":"Bedfordshire",
    "sg:tags":[
        "haulage",
        "road"
    ],
    "wof:name":"K Norman",
    "wof:placetype":"venue"
},
  "geometry": {"coordinates":[-0.253083,52.088455],"type":"Point"}
}