{
  "type": "Feature",
  "properties": {
    "addr:full":"Imperial Dock, Leith Docks Edinburgh City of Edinburgh EH6 7DR",
    "addr:postcode":"eh6 7dr",
    "iso:country":"GB",
    "sg:address":"Imperial Dock, Leith Docks",
    "sg:city":"Edinburgh",
    "sg:classifiers":[
        {
            "category":"Manufacturing",
            "subcategory":"Building Materials",
            "type":"Manufacturing & Wholesale Goods"
        }
    ],
    "sg:phone":"+44 131 554 1555",
    "sg:postcode":"EH6 7DR",
    "sg:province":"City of Edinburgh",
    "sg:tags":[
        "distributor",
        "mnfrs",
        "cement"
    ],
    "wof:name":"Seament (U K) Ltd.",
    "wof:placetype":"venue"
},
  "geometry": {"coordinates":[-3.1641139984,55.9774932861],"type":"Point"}
}