{
  "type": "Feature",
  "properties": {
    "addr:full":"Lorne Rd Larbert Falkirk FK5 4AT",
    "addr:postcode":"fk5 4at",
    "addr:street":"Lorne Rd",
    "iso:country":"GB",
    "sg:address":"Lorne Rd",
    "sg:city":"Larbert",
    "sg:classifiers":[
        {
            "category":"Sports & Exercise",
            "subcategory":"Playing Field",
            "type":"Entertainment"
        }
    ],
    "sg:postcode":"FK5 4AT",
    "sg:province":"Falkirk",
    "sg:tags":[
        "transmission",
        "power"
    ],
    "wof:name":"Aerial Industrial Supplies (Larbert) Ltd",
    "wof:placetype":"venue"
},
  "geometry": {"coordinates":[-3.8286499977,56.023601532],"type":"Point"}
}