{
  "type": "Feature",
  "properties": {
    "iso:country":"GB",
    "sg:address":"South Henry Street",
    "sg:city":"Carlisle",
    "sg:classifiers":[
        {
            "category":"Autos & Motor Vehicles",
            "subcategory":"Automobile Sales",
            "type":"Retail Goods"
        }
    ],
    "sg:phone":"+44 1228 525994",
    "sg:postcode":"CA1 1SF",
    "sg:province":"Cumbria",
    "sg:tags":[
        "car"
    ],
    "wof:name":"Melbourne House Motors",
    "wof:placetype":"venue"
},
  "geometry": {"coordinates":[-2.9272780418,54.890045166],"type":"Point"}
}