{
  "type": "Feature",
  "properties": {
    "addr:full":"Arkesden Road, Clavering Saffron Walden Essex CB11 4QU",
    "addr:postcode":"cb11 4qu",
    "addr:street":"Arkesden Road",
    "iso:country":"GB",
    "sg:address":"Arkesden Road, Clavering",
    "sg:city":"Saffron Walden",
    "sg:classifiers":[
        {
            "category":"Sports & Exercise",
            "subcategory":"Tennis Court",
            "type":"Entertainment"
        }
    ],
    "sg:postcode":"CB11 4QU",
    "sg:province":"Essex",
    "sg:tags":[
        "breakdown",
        "recovery"
    ],
    "wof:name":"Dennis J Herbert",
    "wof:placetype":"venue"
},
  "geometry": {"coordinates":[0.15692,51.989262],"type":"Point"}
}