{
  "type": "Feature",
  "properties": {
    "iso:country":"GB",
    "sg:address":"4 St Catherines Gardens",
    "sg:city":"Edinburgh",
    "sg:classifiers":[
        {
            "category":"Professional",
            "subcategory":"Management & Consulting",
            "type":"Services"
        }
    ],
    "sg:phone":"+44 131 334 0401",
    "sg:postcode":"EH12 7AZ",
    "sg:province":"City of Edinburgh",
    "sg:tags":[
        "consultant",
        "business"
    ],
    "wof:name":"Ewart Consultancy Associates",
    "wof:placetype":"venue"
},
  "geometry": {"coordinates":[-3.265781,55.942055],"type":"Point"}
}