{
  "type": "Feature",
  "properties": {
    "iso:country":"GB",
    "sg:address":"90 Armstrong Rd",
    "sg:city":"Mansfield",
    "sg:classifiers":[
        {
            "category":"Personal",
            "type":"Services"
        }
    ],
    "sg:postcode":"NG19 6JR",
    "sg:province":"Derbyshire",
    "sg:tags":[
        "wedding"
    ],
    "wof:name":"John's Outside Bar",
    "wof:placetype":"venue"
},
  "geometry": {"coordinates":[-1.227574,53.146488],"type":"Point"}
}