{
  "type": "Feature",
  "properties": {
    "iso:country":"GB",
    "sg:address":"1 Church Terrace",
    "sg:city":"Worcester",
    "sg:classifiers":[
        {
            "category":"Personal",
            "subcategory":"Barber",
            "type":"Services"
        }
    ],
    "sg:postcode":"WR2 5BX",
    "sg:province":"Worcestershire",
    "sg:tags":[
        "men's",
        "hairdresser"
    ],
    "wof:name":"Roger's",
    "wof:placetype":"venue"
},
  "geometry": {"coordinates":[-2.23653,52.187977],"type":"Point"}
}