{
  "type": "Feature",
  "properties": {
    "addr:full":"84 Upper Belmont Road Chesham Buckinghamshire HP5 2DD",
    "addr:housenumber":"84",
    "addr:postcode":"hp5 2dd",
    "addr:street":"Upper Belmont Road",
    "iso:country":"GB",
    "sg:address":"84 Upper Belmont Road",
    "sg:city":"Chesham",
    "sg:classifiers":[
        {
            "category":"Building & Trades",
            "subcategory":"Construction",
            "type":"Services"
        }
    ],
    "sg:phone":"+44 1494 782107",
    "sg:postcode":"HP5 2DD",
    "sg:province":"Buckinghamshire",
    "sg:tags":[
        "repair",
        "guttering"
    ],
    "wof:name":"Gutter Service",
    "wof:placetype":"venue"
},
  "geometry": {"coordinates":[-0.6171470284,51.7207489014],"type":"Point"}
}