{
  "type": "Feature",
  "properties": {
    "addr:full":"17 Ashcroft Road Cirencester Gloucestershire GL7 1RA",
    "addr:housenumber":"17",
    "addr:postcode":"gl7 1ra",
    "addr:street":"Ashcroft Road",
    "iso:country":"GB",
    "sg:address":"17 Ashcroft Road",
    "sg:city":"Cirencester",
    "sg:classifiers":[
        {
            "category":"Professional",
            "subcategory":"Engineering",
            "type":"Services"
        }
    ],
    "sg:phone":"+44 1285 885114",
    "sg:postcode":"GL7 1RA",
    "sg:province":"Gloucestershire",
    "sg:tags":[
        "contractor",
        "electrical",
        "engineer"
    ],
    "wof:name":"Fosseway Electrical Contracts",
    "wof:placetype":"venue"
},
  "geometry": {"coordinates":[-1.9679729939,51.7149810791],"type":"Point"}
}