{
  "type": "Feature",
  "properties": {
    "iso:country":"GB",
    "sg:address":"191 Brookvale Rd",
    "sg:city":"Birmingham",
    "sg:classifiers":[
        {
            "category":"Organizations",
            "subcategory":"Membership Organization",
            "type":"Services"
        }
    ],
    "sg:phone":"+44 121 356 5706",
    "sg:postcode":"B6 7AJ",
    "sg:province":"West Midlands",
    "sg:tags":[
        "club"
    ],
    "wof:name":"Barn Social Club Box Office",
    "wof:placetype":"venue"
},
  "geometry": {"coordinates":[-1.878511,52.519749],"type":"Point"}
}