{
  "type": "Feature",
  "properties": {
    "iso:country":"GB",
    "sg:address":"Beacon Dairy Farm, Doe Bank Lane",
    "sg:city":"Walsall",
    "sg:classifiers":[
        {
            "category":"Farming",
            "subcategory":"Dairy Farm",
            "type":"Manufacturing & Wholesale Goods"
        },
        {
            "category":"Food & Beverages",
            "subcategory":"Groceries & Convenience Stores",
            "type":"Retail Goods"
        }
    ],
    "sg:phone":"+44 121 360 7067",
    "sg:postcode":"WS9 0RQ",
    "sg:province":"Staffordshire",
    "sg:tags":[
        "merchant",
        "egg"
    ],
    "wof:name":"Beacon Dairy Farm",
    "wof:placetype":"venue"
},
  "geometry": {"coordinates":[-1.9058840275,52.5678749084],"type":"Point"}
}