{
  "type": "Feature",
  "properties": {
    "addr:full":"Back Garden Street Castleford West Yorkshire WF10 5AL",
    "addr:postcode":"wf10 5al",
    "addr:street":"Garden Street",
    "iso:country":"GB",
    "sg:address":"Back Garden Street",
    "sg:city":"Castleford",
    "sg:classifiers":[
        {
            "category":"Building & Trades",
            "subcategory":"Construction",
            "type":"Services"
        }
    ],
    "sg:phone":"+44 1977 512299",
    "sg:postcode":"WF10 5AL",
    "sg:province":"West Yorkshire",
    "sg:tags":[
        "joinery"
    ],
    "wof:name":"Taylor & Hepworth Joinery",
    "wof:placetype":"venue"
},
  "geometry": {"coordinates":[-1.3533639908,53.7187004089],"type":"Point"}
}