{
  "type": "Feature",
  "properties": {
    "iso:country":"GB",
    "sg:address":"Unit 18, Monkspath Business Park, Highlands Road",
    "sg:city":"Solihull",
    "sg:classifiers":[
        {
            "category":"Manufacturing",
            "subcategory":"Textiles",
            "type":"Manufacturing & Wholesale Goods"
        }
    ],
    "sg:phone":"+44 121 733 3833",
    "sg:postcode":"B90 4NY",
    "sg:province":"West Midlands",
    "sg:tags":[
        "printer"
    ],
    "wof:name":"Folex Ltd.",
    "wof:placetype":"venue"
},
  "geometry": {"coordinates":[-1.799626,52.396271],"type":"Point"}
}