{
  "type": "Feature",
  "properties": {
    "addr:full":"Pavilion 1 Mount Manor Business, Park, Minerva Way Glasgow Glasgow City G3 8AU",
    "addr:postcode":"g3 8au",
    "addr:street":"Mount;Business Park Minerva Way",
    "iso:country":"GB",
    "sg:address":"Pavilion 1 Mount Manor Business, Park, Minerva Way",
    "sg:city":"Glasgow",
    "sg:classifiers":[
        {
            "category":"Insurance",
            "subcategory":"Insurance Agent",
            "type":"Services"
        }
    ],
    "sg:phone":"+44 141 221 1246",
    "sg:postcode":"G3 8AU",
    "sg:province":"Glasgow City",
    "sg:tags":[
        "broker"
    ],
    "wof:name":"Medical Insurance Agency Ltd.",
    "wof:placetype":"venue"
},
  "geometry": {"coordinates":[-4.28441,55.863258],"type":"Point"}
}