{
  "type": "Feature",
  "properties": {
    "addr:full":"Crowwood Crescent, Calderbank Airdrie North Lanarkshire ML6 9TA",
    "addr:postcode":"ml6 9ta",
    "addr:street":"Crowwood Crescent",
    "iso:country":"GB",
    "sg:address":"Crowwood Crescent, Calderbank",
    "sg:city":"Airdrie",
    "sg:classifiers":[
        {
            "category":"Education",
            "subcategory":"School",
            "type":"Public Place"
        },
        {
            "category":"Government",
            "subcategory":"Office",
            "type":"Public Place"
        }
    ],
    "sg:phone":"+44 1236 763985",
    "sg:postcode":"ML6 9TA",
    "sg:province":"North Lanarkshire",
    "sg:tags":[
        "local",
        "authority"
    ],
    "wof:name":"Corpus Christi Primary School",
    "wof:placetype":"venue"
},
  "geometry": {"coordinates":[-3.9698750973,55.8440895081],"type":"Point"}
}