{
  "type": "Feature",
  "properties": {
    "addr:full":"Copperfield, Cumrew Carlisle Cumbria CA4 9DD",
    "addr:postcode":"ca4 9dd",
    "iso:country":"GB",
    "sg:address":"Copperfield, Cumrew",
    "sg:city":"Carlisle",
    "sg:classifiers":[
        {
            "category":"Building & Trades",
            "subcategory":"Construction",
            "type":"Services"
        }
    ],
    "sg:phone":"+44 1768 896459",
    "sg:postcode":"CA4 9DD",
    "sg:province":"Cumbria",
    "sg:tags":[
        "builder"
    ],
    "wof:name":"John Thorburn",
    "wof:placetype":"venue"
},
  "geometry": {"coordinates":[-2.7042200565,54.8453788757],"type":"Point"}
}