{
  "type": "Feature",
  "properties": {
    "iso:country":"GB",
    "sg:address":"Cross Inn",
    "sg:city":"Llandysul",
    "sg:classifiers":[
        {
            "category":"Organizations",
            "subcategory":"Membership Organization",
            "type":"Services"
        }
    ],
    "sg:phone":"+44 1545 560115",
    "sg:postcode":"SA44 6NL",
    "sg:province":"Carmarthenshire",
    "sg:tags":[
        "club"
    ],
    "wof:name":"Pencnwc Social Club",
    "wof:placetype":"venue"
},
  "geometry": {"coordinates":[-4.419789,52.155201],"type":"Point"}
}