{
  "type": "Feature",
  "properties": {
    "addr:full":"2 The Laurels, High Halden Ashford Kent TN26 3NA",
    "addr:housenumber":"2",
    "addr:postcode":"tn26 3na",
    "addr:street":"The Laurels",
    "iso:country":"GB",
    "sg:address":"2 The Laurels, High Halden",
    "sg:city":"Ashford",
    "sg:classifiers":[
        {
            "category":"Building & Trades",
            "subcategory":"Construction",
            "type":"Services"
        }
    ],
    "sg:phone":"+44 1233 850742",
    "sg:postcode":"TN26 3NA",
    "sg:province":"Kent",
    "sg:tags":[
        "tiling",
        "contractor"
    ],
    "wof:name":"Halden Ceramics",
    "wof:placetype":"venue"
},
  "geometry": {"coordinates":[0.7124180198,51.1035461426],"type":"Point"}
}