{
  "type": "Feature",
  "properties": {
    "addr:full":"5 Minnis Road Birchington Kent CT7 9SD",
    "addr:housenumber":"5",
    "addr:postcode":"ct7 9sd",
    "addr:street":"Minnis Road",
    "iso:country":"GB",
    "sg:address":"5 Minnis Road",
    "sg:city":"Birchington",
    "sg:classifiers":[
        {
            "category":"Autos & Motor Vehicles",
            "subcategory":"Fuel & Gas Station",
            "type":"Retail Goods"
        }
    ],
    "sg:phone":"+44 1843 847912",
    "sg:postcode":"CT7 9SD",
    "sg:province":"Kent",
    "sg:tags":[
        "petrol",
        "filling"
    ],
    "wof:name":"Chris Holt",
    "wof:placetype":"venue"
},
  "geometry": {"coordinates":[1.302584,51.376644],"type":"Point"}
}