{
  "type": "Feature",
  "properties": {
    "addr:full":"Centaur House, Torbay Road Castle Cary Somerset BA7 7EU",
    "addr:postcode":"ba7 7eu",
    "addr:street":"Torbay Road",
    "iso:country":"GB",
    "sg:address":"Centaur House, Torbay Road",
    "sg:city":"Castle Cary",
    "sg:classifiers":[
        {
            "category":"Retail",
            "subcategory":"Veterinary Services",
            "type":"Services"
        },
        {
            "category":"Shopping",
            "subcategory":"Pharmacy",
            "type":"Retail Goods"
        }
    ],
    "sg:phone":"+44 1963 350187",
    "sg:postcode":"BA7 7EU",
    "sg:province":"Somerset",
    "sg:tags":[
        "pharmaceutical"
    ],
    "wof:name":"Centaur Services Ltd.",
    "wof:placetype":"venue"
},
  "geometry": {"coordinates":[-2.5229229927,51.0898017883],"type":"Point"}
}