{
  "type": "Feature",
  "properties": {
    "iso:country":"GB",
    "sg:address":"43 Marlow Hill",
    "sg:city":"High Wycombe",
    "sg:classifiers":[
        {
            "category":"Real Estate",
            "subcategory":"Surveying",
            "type":"Services"
        },
        {
            "category":"Real Estate",
            "subcategory":"Architect",
            "type":"Services"
        }
    ],
    "sg:phone":"+44 1494 522955",
    "sg:postcode":"HP11 1PN",
    "sg:province":"Buckinghamshire",
    "sg:tags":[
        "building",
        "surveyor"
    ],
    "wof:name":"Robert William Howe",
    "wof:placetype":"venue"
},
  "geometry": {"coordinates":[-0.7603359818,51.6188964844],"type":"Point"}
}