{
  "type": "Feature",
  "properties": {
    "iso:country":"GB",
    "sg:address":"Railway Street",
    "sg:city":"Burnley",
    "sg:classifiers":[
        {
            "category":"Bars & Pubs",
            "type":"Food & Drink"
        }
    ],
    "sg:phone":"+44 1282 424238",
    "sg:postcode":"BB11 1DA",
    "sg:province":"Lancashire",
    "sg:tags":[
        "pubs",
        "inn"
    ],
    "wof:name":"Reindeer Hotel",
    "wof:placetype":"venue"
},
  "geometry": {"coordinates":[-2.244989,53.793255],"type":"Point"}
}