{
  "type": "Feature",
  "properties": {
    "iso:country":"GB",
    "sg:address":"Keelond Service Station, Wakefield Rd, Featherstone",
    "sg:city":"Pontefract",
    "sg:classifiers":[
        {
            "category":"Professional",
            "subcategory":"Printing & Photocopies",
            "type":"Services"
        }
    ],
    "sg:phone":"+44 1977 702160",
    "sg:postcode":"WF7 5HL",
    "sg:province":"West Yorkshire",
    "sg:tags":[
        "process",
        "screen",
        "printer"
    ],
    "wof:name":"Milkbond Ltd",
    "wof:placetype":"venue"
},
  "geometry": {"coordinates":[-1.3591400385,53.6747703552],"type":"Point"}
}