{
  "type": "Feature",
  "properties": {
    "iso:country":"GB",
    "sg:address":"70 Wellington Road, Greenfield",
    "sg:city":"Oldham",
    "sg:classifiers":[
        {
            "category":"Social Services",
            "subcategory":"Retirement Home",
            "type":"Services"
        }
    ],
    "sg:postcode":"OL3 7AQ",
    "sg:province":"Lancashire",
    "sg:tags":[
        "rest"
    ],
    "wof:name":"Wellington Lodge",
    "wof:placetype":"venue"
},
  "geometry": {"coordinates":[-2.00769,53.541447],"type":"Point"}
}