{
  "type": "Feature",
  "properties": {
    "iso:country":"GB",
    "sg:address":"Broughton Street, Cheetham",
    "sg:city":"Manchester",
    "sg:classifiers":[
        {
            "category":"Autos & Motor Vehicles",
            "subcategory":"Automobile Sales",
            "type":"Retail Goods"
        }
    ],
    "sg:phone":"+44 161 831 3400",
    "sg:postcode":"M8 8NN",
    "sg:province":"Greater Manchester",
    "sg:tags":[
        "car"
    ],
    "wof:name":"L T I Ltd.",
    "wof:placetype":"venue"
},
  "geometry": {"coordinates":[-2.246979,53.497231],"type":"Point"}
}