{
  "type": "Feature",
  "properties": {
    "addr:full":"Airedale High School, Crewe Rd Castleford West Yorkshire WF10 3JU",
    "addr:postcode":"wf10 3ju",
    "addr:street":"Crewe Rd",
    "iso:country":"GB",
    "sg:address":"Airedale High School, Crewe Rd",
    "sg:city":"Castleford",
    "sg:classifiers":[
        {
            "category":"Community Center",
            "subcategory":"Youth",
            "type":"Public Place"
        }
    ],
    "sg:phone":"+44 1977 722050",
    "sg:postcode":"WF10 3JU",
    "sg:province":"West Yorkshire",
    "sg:tags":[
        "organisation",
        "centre"
    ],
    "wof:name":"Airedale Youth Project",
    "wof:placetype":"venue"
},
  "geometry": {"coordinates":[-1.3442080021,53.721698761],"type":"Point"}
}