{
  "type": "Feature",
  "properties": {
    "addr:full":"246 Kingstown Road Carlisle Cumbria CA3 0DE",
    "addr:housenumber":"246",
    "addr:postcode":"ca3 0de",
    "addr:street":"Kingstown Road",
    "iso:country":"GB",
    "sg:address":"246 Kingstown Road",
    "sg:city":"Carlisle",
    "sg:classifiers":[
        {
            "category":"Travel",
            "subcategory":"Hotels & Motels",
            "type":"Entertainment"
        }
    ],
    "sg:postcode":"CA3 0DE",
    "sg:province":"Cumbria",
    "wof:name":"Kingstown Hotel",
    "wof:placetype":"venue"
},
  "geometry": {"coordinates":[-2.9448199272,54.9235725403],"type":"Point"}
}