{
  "type": "Feature",
  "properties": {
    "iso:country":"GB",
    "sg:address":"15 Middlefield",
    "sg:city":"Preston",
    "sg:classifiers":[
        {
            "category":"Building & Trades",
            "subcategory":"Construction",
            "type":"Services"
        }
    ],
    "sg:phone":"+44 1772 453304",
    "sg:postcode":"PR26 7AE",
    "sg:province":"Lancashire",
    "sg:tags":[
        "builder"
    ],
    "wof:name":"Ascroft Builders",
    "wof:placetype":"venue"
},
  "geometry": {"coordinates":[-2.731169,53.692673],"type":"Point"}
}