{
  "type": "Feature",
  "properties": {
    "iso:country":"GB",
    "sg:address":"11-15 Carolgate",
    "sg:city":"Retford",
    "sg:classifiers":[
        {
            "category":"Shopping",
            "subcategory":"Clothing, Apparel, & Fashions",
            "type":"Retail Goods"
        }
    ],
    "sg:phone":"+44 1777 700731",
    "sg:postcode":"DN22 6BZ",
    "sg:province":"Nottinghamshire",
    "sg:tags":[
        "shop"
    ],
    "wof:name":"Bewise",
    "wof:placetype":"venue"
},
  "geometry": {"coordinates":[-0.9420089722,53.3213310242],"type":"Point"}
}