{
  "type": "Feature",
  "properties": {
    "iso:country":"GB",
    "sg:address":"Unit 709, Delta Office Park, Welton Road",
    "sg:city":"Swindon",
    "sg:classifiers":[
        {
            "category":"Professional",
            "subcategory":"Employment Agencies",
            "type":"Services"
        }
    ],
    "sg:phone":"+44 1793 463885",
    "sg:postcode":"SN5 7XS",
    "sg:province":"Wiltshire",
    "sg:tags":[
        "consultant"
    ],
    "wof:name":"Transtaff Ltd.",
    "wof:placetype":"venue"
},
  "geometry": {"coordinates":[-1.81572,51.559856],"type":"Point"}
}