{
  "type": "Feature",
  "properties": {
    "addr:full":"Unit 2, Woodfield Road Doncaster South Yorkshire DN4 8EW",
    "addr:housenumber":"unit 2",
    "addr:postcode":"dn4 8ew",
    "addr:street":"Woodfield Road",
    "iso:country":"GB",
    "sg:address":"Unit 2, Woodfield Road",
    "sg:city":"Doncaster",
    "sg:classifiers":[
        {
            "category":"Recreation",
            "subcategory":"Boat Charter",
            "type":"Entertainment"
        }
    ],
    "sg:postcode":"DN4 8EW",
    "sg:province":"South Yorkshire",
    "sg:tags":[
        "excursion"
    ],
    "wof:name":"Balvy Caravan Dismantlers",
    "wof:placetype":"venue"
},
  "geometry": {"coordinates":[-1.153874,53.502899],"type":"Point"}
}