{
  "type": "Feature",
  "properties": {
    "iso:country":"GB",
    "sg:address":"Air Malta House, 314-316 Upper Richmond Road",
    "sg:city":"London",
    "sg:classifiers":[
        {
            "category":"Airline",
            "type":"Transportation"
        },
        {
            "category":"Travel",
            "subcategory":"Travel Agent",
            "type":"Entertainment"
        }
    ],
    "sg:phone":"+44 20 8785 3255",
    "sg:postcode":"SW15 6TU",
    "sg:province":"Greater London",
    "wof:name":"Belleair Holidays",
    "wof:placetype":"venue"
},
  "geometry": {"coordinates":[-0.226769,51.464279],"type":"Point"}
}