{
  "type": "Feature",
  "properties": {
    "addr:full":"6 Homer Drive London Greater London E14 3UB",
    "addr:housenumber":"6",
    "addr:postcode":"e14 3ub",
    "addr:street":"Homer Drive",
    "iso:country":"GB",
    "sg:address":"6 Homer Drive",
    "sg:city":"London",
    "sg:classifiers":[
        {
            "category":"Wholesale",
            "subcategory":"Motor Vehicles",
            "type":"Manufacturing & Wholesale Goods"
        }
    ],
    "sg:postcode":"E14 3UB",
    "sg:province":"Greater London",
    "sg:tags":[
        "aircraft",
        "spare"
    ],
    "wof:name":"Robert Wilson",
    "wof:placetype":"venue"
},
  "geometry": {"coordinates":[-0.0250630006,51.4913444519],"type":"Point"}
}