{
  "type": "Feature",
  "properties": {
    "addr:full":"176a Victoria Rd, Kirkby In Ashfield Nottingham Nottinghamshire NG17 8AT",
    "addr:housenumber":"176a",
    "addr:postcode":"ng17 8at",
    "addr:street":"Victoria Rd;In Ashfield",
    "iso:country":"GB",
    "sg:address":"176a Victoria Rd, Kirkby In Ashfield",
    "sg:city":"Nottingham",
    "sg:classifiers":[
        {
            "category":"Professional",
            "subcategory":"Employment Agencies",
            "type":"Services"
        }
    ],
    "sg:phone":"+44 1623 456828",
    "sg:postcode":"NG17 8AT",
    "sg:province":"Nottinghamshire",
    "sg:tags":[
        "consultant"
    ],
    "wof:name":"Arnarge",
    "wof:placetype":"venue"
},
  "geometry": {"coordinates":[-1.2607469559,53.1007041931],"type":"Point"}
}