{
  "type": "Feature",
  "properties": {
    "addr:full":"Learys Chambers, Market Pl Ripley Derbyshire DE5 3BR",
    "addr:postcode":"de5 3br",
    "addr:street":"Market Pl",
    "iso:country":"GB",
    "sg:address":"Learys Chambers, Market Pl",
    "sg:city":"Ripley",
    "sg:classifiers":[
        {
            "category":"Education",
            "subcategory":"Dance Studio",
            "type":"Public Place"
        }
    ],
    "sg:phone":"+44 1773 743324",
    "sg:postcode":"DE5 3BR",
    "sg:province":"Derbyshire",
    "sg:tags":[
        "school",
        "dancing"
    ],
    "wof:name":"Ripley School Of Dancing",
    "wof:placetype":"venue"
},
  "geometry": {"coordinates":[-1.407668,53.050701],"type":"Point"}
}