{
  "type": "Feature",
  "properties": {
    "addr:full":"36 Priory Road, Bicknacre Chelmsford Essex CM3 4EY",
    "addr:housenumber":"36",
    "addr:postcode":"cm3 4ey",
    "addr:street":"Priory Road",
    "iso:country":"GB",
    "sg:address":"36 Priory Road, Bicknacre",
    "sg:city":"Chelmsford",
    "sg:classifiers":[
        {
            "category":"Manufacturing",
            "subcategory":"Petroleum Products",
            "type":"Manufacturing & Wholesale Goods"
        },
        {
            "category":"Building & Trades",
            "subcategory":"Construction",
            "type":"Services"
        }
    ],
    "sg:phone":"+44 1245 225780",
    "sg:postcode":"CM3 4EY",
    "sg:province":"Essex",
    "sg:tags":[
        "double",
        "glazing",
        "installers"
    ],
    "wof:name":"K S S Home Improvements K S S Windows",
    "wof:placetype":"venue"
},
  "geometry": {"coordinates":[0.58029,51.692501],"type":"Point"}
}