{
  "type": "Feature",
  "properties": {
    "addr:full":"Denby Dale Rd Wakefield West Yorkshire WF4 3JF",
    "addr:postcode":"wf4 3jf",
    "addr:street":"Denby Dale Rd",
    "iso:country":"GB",
    "sg:address":"Denby Dale Rd",
    "sg:city":"Wakefield",
    "sg:classifiers":[
        {
            "category":"Place Of Worship",
            "type":"Public Place"
        }
    ],
    "sg:phone":"+44 1924 255360",
    "sg:postcode":"WF4 3JF",
    "sg:province":"West Yorkshire",
    "wof:name":"St Johns Church",
    "wof:placetype":"venue"
},
  "geometry": {"coordinates":[-1.5373929739,53.6476135254],"type":"Point"}
}