{
  "type": "Feature",
  "properties": {
    "addr:full":"68 Martlesham Road Woodbridge Suffolk IP13 6LX",
    "addr:housenumber":"68",
    "addr:postcode":"ip13 6lx",
    "addr:street":"Martlesham Road",
    "iso:country":"GB",
    "sg:address":"68 Martlesham Road",
    "sg:city":"Woodbridge",
    "sg:classifiers":[
        {
            "category":"Building & Trades",
            "subcategory":"Construction",
            "type":"Services"
        }
    ],
    "sg:postcode":"IP13 6LX",
    "sg:province":"Suffolk",
    "sg:tags":[
        "builder"
    ],
    "wof:name":"L C M  (Ipswich) Ltd.",
    "wof:placetype":"venue"
},
  "geometry": {"coordinates":[1.2632199526,52.0787658691],"type":"Point"}
}