{
  "type": "Feature",
  "properties": {
    "addr:full":"323 Kenton Rd Harrow Greater London HA3 0XN",
    "addr:housenumber":"323",
    "addr:postcode":"ha3 0xn",
    "addr:street":"Kenton Rd",
    "iso:country":"GB",
    "sg:address":"323 Kenton Rd",
    "sg:city":"Harrow",
    "sg:classifiers":[
        {
            "category":"Building & Trades",
            "subcategory":"Construction",
            "type":"Services"
        }
    ],
    "sg:phone":"+44 20 8909 2444",
    "sg:postcode":"HA3 0XN",
    "sg:province":"Greater London",
    "sg:tags":[
        "builder"
    ],
    "wof:name":"Property & Construction Co",
    "wof:placetype":"venue"
},
  "geometry": {"coordinates":[-0.3069519997,51.5862998962],"type":"Point"}
}