{
  "type": "Feature",
  "properties": {
    "iso:country":"GB",
    "sg:address":"Unit 4 St John Business Centre, St Peters Road",
    "sg:city":"Margate",
    "sg:classifiers":[
        {
            "category":"Communications",
            "subcategory":"Film & Video Production",
            "type":"Services"
        }
    ],
    "sg:postcode":"CT9 1TE",
    "sg:province":"Kent",
    "sg:tags":[
        "illustrator",
        "artist"
    ],
    "wof:name":"Artworks",
    "wof:placetype":"venue"
},
  "geometry": {"coordinates":[1.379247,51.386662],"type":"Point"}
}