{
  "type": "Feature",
  "properties": {
    "iso:country":"GB",
    "sg:address":"23 New Quebec St",
    "sg:city":"West End",
    "sg:classifiers":[
        {
            "category":"Shopping",
            "subcategory":"Antiques",
            "type":"Retail Goods"
        }
    ],
    "sg:phone":"+44 20 7262 3401",
    "sg:postcode":"W1H 7DE",
    "sg:province":"Greater London",
    "wof:name":"Eldridge Restorations",
    "wof:placetype":"venue"
},
  "geometry": {"coordinates":[-0.158349,51.515011],"type":"Point"}
}