{
  "type": "Feature",
  "properties": {
    "addr:full":"146/148 Belgrave Road Leicester Leicestershire LE4 5AT",
    "addr:housenumber":"146 / 148",
    "addr:postcode":"le4 5at",
    "addr:street":"Belgrave Road",
    "iso:country":"GB",
    "sg:address":"146/148 Belgrave Road",
    "sg:city":"Leicester",
    "sg:classifiers":[
        {
            "category":"Shopping",
            "subcategory":"Comic Books",
            "type":"Retail Goods"
        }
    ],
    "sg:phone":"+44 116 266 1903",
    "sg:postcode":"LE4 5AT",
    "sg:province":"Leicestershire",
    "sg:tags":[
        "jeweller"
    ],
    "wof:name":"Bipin Jewellers Ltd.",
    "wof:placetype":"venue"
},
  "geometry": {"coordinates":[-1.1233500242,52.6489562988],"type":"Point"}
}