{
  "type": "Feature",
  "properties": {
    "iso:country":"GB",
    "sg:address":"69 Littlestone Road, Littlestone",
    "sg:city":"New Romney",
    "sg:classifiers":[
        {
            "category":"Professional",
            "subcategory":"Accounting & Tax Preparation",
            "type":"Services"
        }
    ],
    "sg:postcode":"TN28 8LP",
    "sg:province":"Kent",
    "sg:tags":[
        "accountant"
    ],
    "wof:name":"Black Margin Ltd",
    "wof:placetype":"venue"
},
  "geometry": {"coordinates":[0.958447,50.983772],"type":"Point"}
}