{
  "type": "Feature",
  "properties": {
    "addr:full":"South Gloucestershire Ass, 127 Edgeworth, Yate Bristol Gloucestershire BS37 4YP",
    "addr:housenumber":"127",
    "addr:postcode":"bs37 4yp",
    "addr:street":"Bristol",
    "iso:country":"GB",
    "sg:address":"South Gloucestershire Ass, 127 Edgeworth, Yate",
    "sg:city":"Bristol",
    "sg:classifiers":[
        {
            "category":"Organizations",
            "subcategory":"Professional Association",
            "type":"Services"
        }
    ],
    "sg:phone":"+44 1454 273552",
    "sg:postcode":"BS37 4YP",
    "sg:province":"Gloucestershire",
    "sg:tags":[
        "union",
        "trade"
    ],
    "wof:name":"N A S U W T",
    "wof:placetype":"venue"
},
  "geometry": {"coordinates":[-2.4096150398,51.5391998291],"type":"Point"}
}