{
  "type": "Feature",
  "properties": {
    "addr:full":"19 High Street Cullompton Devon EX15 1AB",
    "addr:housenumber":"19",
    "addr:postcode":"ex15 1ab",
    "addr:street":"High Street",
    "iso:country":"GB",
    "sg:address":"19 High Street",
    "sg:city":"Cullompton",
    "sg:classifiers":[
        {
            "category":"Shopping",
            "subcategory":"Pets & Pet Supplies",
            "type":"Retail Goods"
        }
    ],
    "sg:phone":"+44 1884 32457",
    "sg:postcode":"EX15 1AB",
    "sg:province":"Devon",
    "sg:tags":[
        "food"
    ],
    "wof:name":"George Smalls",
    "wof:placetype":"venue"
},
  "geometry": {"coordinates":[-3.3923969269,50.8583641052],"type":"Point"}
}