{
  "type": "Feature",
  "properties": {
    "addr:full":"22 Hawkshead Road, High Crompton Oldham Lancashire OL2 7QY",
    "addr:housenumber":"22",
    "addr:postcode":"ol2 7qy",
    "addr:street":"Hawkshead Road High",
    "iso:country":"GB",
    "sg:address":"22 Hawkshead Road, High Crompton",
    "sg:city":"Oldham",
    "sg:classifiers":[
        {
            "category":"Home & Garden",
            "subcategory":"Hardware",
            "type":"Retail Goods"
        }
    ],
    "sg:postcode":"OL2 7QY",
    "sg:province":"Lancashire",
    "sg:tags":[
        "compressor",
        "air"
    ],
    "wof:name":"Air Supply Services",
    "wof:placetype":"venue"
},
  "geometry": {"coordinates":[-2.104578,53.584583],"type":"Point"}
}