{
  "type": "Feature",
  "properties": {
    "addr:full":"51 Queen Street Exeter Devon EX4 3SR",
    "addr:housenumber":"51",
    "addr:postcode":"ex4 3sr",
    "addr:street":"Queen Street",
    "iso:country":"GB",
    "sg:address":"51 Queen Street",
    "sg:city":"Exeter",
    "sg:classifiers":[
        {
            "category":"Professional",
            "subcategory":"Engineering",
            "type":"Services"
        }
    ],
    "sg:phone":"+44 1392 219637",
    "sg:postcode":"EX4 3SR",
    "sg:province":"Devon",
    "sg:tags":[
        "consulting",
        "engineer"
    ],
    "wof:name":"Croome Tilley",
    "wof:placetype":"venue"
},
  "geometry": {"coordinates":[-3.5350561142,50.7267799377],"type":"Point"}
}