{
  "type": "Feature",
  "properties": {
    "addr:full":"Shortcross Road, Mount Hawke Truro Cornwall TR4 8DU",
    "addr:postcode":"tr4 8du",
    "addr:street":"Shortcross Road",
    "iso:country":"GB",
    "sg:address":"Shortcross Road, Mount Hawke",
    "sg:city":"Truro",
    "sg:classifiers":[
        {
            "category":"Personal",
            "subcategory":"Beauty Salon",
            "type":"Services"
        }
    ],
    "sg:postcode":"TR4 8DU",
    "sg:province":"Cornwall",
    "sg:tags":[
        "unisex",
        "hairdresser"
    ],
    "wof:name":"Hair Lines",
    "wof:placetype":"venue"
},
  "geometry": {"coordinates":[-5.208399,50.281796],"type":"Point"}
}