{
  "type": "Feature",
  "properties": {
    "iso:country":"GB",
    "sg:address":"Shortcross Road, Mount Hawke",
    "sg:city":"Truro",
    "sg:classifiers":[
        {
            "category":"Personal",
            "subcategory":"Beauty Salon",
            "type":"Services"
        }
    ],
    "sg:postcode":"TR4 8DU",
    "sg:province":"Cornwall",
    "sg:tags":[
        "unisex",
        "hairdresser"
    ],
    "wof:name":"Hair Lines",
    "wof:placetype":"venue"
},
  "geometry": {"coordinates":[-5.208399,50.281796],"type":"Point"}
}