{
  "type": "Feature",
  "properties": {
    "iso:country":"GB",
    "sg:address":"33-34 Soho Square",
    "sg:city":"London",
    "sg:classifiers":[
        {
            "category":"Professional",
            "subcategory":"Advertising",
            "type":"Services"
        }
    ],
    "sg:postcode":"W1D 3QU",
    "sg:province":"Greater London",
    "sg:tags":[
        "agency"
    ],
    "wof:name":"Collett Dickenson Pearce & Partners Ltd.",
    "wof:placetype":"venue"
},
  "geometry": {"coordinates":[-0.1328060031,51.5150108337],"type":"Point"}
}