{
  "type": "Feature",
  "properties": {
    "iso:country":"GB",
    "sg:address":"Maes Knoll Farm, Norton Malreward, Pensford",
    "sg:city":"Bristol",
    "sg:classifiers":[
        {
            "category":"Farming",
            "subcategory":"Livestock Farm",
            "type":"Manufacturing & Wholesale Goods"
        }
    ],
    "sg:phone":"+44 1275 832402",
    "sg:postcode":"BS39 4EZ",
    "sg:province":"Somerset",
    "sg:tags":[
        "others"
    ],
    "wof:name":"I W Lane & Sons",
    "wof:placetype":"venue"
},
  "geometry": {"coordinates":[-2.547366,51.369961],"type":"Point"}
}