{
  "type": "Feature",
  "properties": {
    "iso:country":"GB",
    "sg:address":"8 Lynthorne Road",
    "sg:city":"Bradford",
    "sg:classifiers":[
        {
            "category":"Taxi",
            "type":"Transportation"
        },
        {
            "category":"Military Area",
            "subcategory":"Air Force Base",
            "type":"Public Place"
        }
    ],
    "sg:phone":"+44 1274 544100",
    "sg:postcode":"BD9 4EZ",
    "sg:province":"West Yorkshire",
    "sg:tags":[
        "mini",
        "hire",
        "private",
        "cab"
    ],
    "wof:name":"Frizinghall Taxis",
    "wof:placetype":"venue"
},
  "geometry": {"coordinates":[-1.774004,53.819553],"type":"Point"}
}