{
  "type": "Feature",
  "properties": {
    "addr:full":"Unit 10, Moorehurst Road St Leonards-on-sea East Sussex TN38 9NA",
    "addr:housenumber":"unit 10",
    "addr:postcode":"leonards-on-sea;tn38 9na",
    "addr:street":"Moorehurst Road St",
    "iso:country":"GB",
    "sg:address":"Unit 10, Moorehurst Road",
    "sg:city":"St Leonards-on-sea",
    "sg:classifiers":[
        {
            "category":"Professional",
            "subcategory":"Detective & Security Services",
            "type":"Services"
        }
    ],
    "sg:phone":"+44 1424 851754",
    "sg:postcode":"TN38 9NA",
    "sg:province":"East Sussex",
    "sg:tags":[
        "equipment"
    ],
    "wof:name":"K T Assemblies Ltd.",
    "wof:placetype":"venue"
},
  "geometry": {"coordinates":[0.540708,50.884007],"type":"Point"}
}