{
  "type": "Feature",
  "properties": {
    "addr:full":"Viking House, 449 Middleton Road, Chadderton Oldham Lancashire OL9 9LB",
    "addr:housenumber":"449",
    "addr:postcode":"ol9 9lb",
    "addr:street":"Middleton Road",
    "iso:country":"GB",
    "sg:address":"Viking House, 449 Middleton Road, Chadderton",
    "sg:city":"Oldham",
    "sg:classifiers":[
        {
            "category":"Building & Trades",
            "subcategory":"Construction",
            "type":"Services"
        }
    ],
    "sg:phone":"+44 161 626 3010",
    "sg:postcode":"OL9 9LB",
    "sg:province":"Lancashire",
    "sg:tags":[
        "contractor"
    ],
    "wof:name":"Wiggett Construction Group Ltd",
    "wof:placetype":"venue"
},
  "geometry": {"coordinates":[-2.137442,53.54409],"type":"Point"}
}