{
  "type": "Feature",
  "properties": {
    "addr:full":"Peeler House Market Rasen Lincolnshire LN8 3DY",
    "addr:postcode":"ln8 3dy",
    "iso:country":"GB",
    "sg:address":"Peeler House",
    "sg:city":"Market Rasen",
    "sg:classifiers":[
        {
            "category":"Building & Trades",
            "subcategory":"Construction",
            "type":"Services"
        }
    ],
    "sg:postcode":"LN8 3DY",
    "sg:province":"Lincolnshire",
    "sg:tags":[
        "joiner",
        "carpenter"
    ],
    "wof:name":"Sandmark Woodwork",
    "wof:placetype":"venue"
},
  "geometry": {"coordinates":[-0.3330680132,53.3867874146],"type":"Point"}
}