{
  "type": "Feature",
  "properties": {
    "addr:full":"220 Electric Avenue, Aston Birmingham West Midlands B6 7EG",
    "addr:housenumber":"220",
    "addr:postcode":"b6 7eg",
    "addr:street":"Electric Avenue",
    "iso:country":"GB",
    "sg:address":"220 Electric Avenue, Aston",
    "sg:city":"Birmingham",
    "sg:classifiers":[
        {
            "category":"Building & Trades",
            "subcategory":"Construction",
            "type":"Services"
        }
    ],
    "sg:phone":"+44 121 327 2722",
    "sg:postcode":"B6 7EG",
    "sg:province":"West Midlands",
    "sg:tags":[
        "welder",
        "mechanical"
    ],
    "wof:name":"Aston Welding",
    "wof:placetype":"venue"
},
  "geometry": {"coordinates":[-1.8746190071,52.511089325],"type":"Point"}
}