{
  "type": "Feature",
  "properties": {
    "iso:country":"GB",
    "sg:address":"The John Thompson Inn, Ingleby, Stanton By Bridge",
    "sg:city":"Derby",
    "sg:classifiers":[
        {
            "category":"Brewery",
            "type":"Food & Drink"
        }
    ],
    "sg:phone":"+44 1332 863033",
    "sg:postcode":"DE73 1HW",
    "sg:province":"Derbyshire",
    "sg:tags":[
        "brewer"
    ],
    "wof:name":"Lichfield Brewery",
    "wof:placetype":"venue"
},
  "geometry": {"coordinates":[-1.447667,52.841904],"type":"Point"}
}