{
  "type": "Feature",
  "properties": {
    "addr:full":"Boon Industrial Estate, Derrington Stafford Staffordshire ST18 9LR",
    "addr:postcode":"st18 9lr",
    "addr:street":"Estate Derrington",
    "iso:country":"GB",
    "sg:address":"Boon Industrial Estate, Derrington",
    "sg:city":"Stafford",
    "sg:classifiers":[
        {
            "category":"Freight",
            "type":"Transportation"
        }
    ],
    "sg:phone":"+44 1785 242282",
    "sg:postcode":"ST18 9LR",
    "sg:province":"Staffordshire",
    "sg:tags":[
        "haulage",
        "road"
    ],
    "wof:name":"Roger Davies",
    "wof:placetype":"venue"
},
  "geometry": {"coordinates":[-2.1606740952,52.7959365845],"type":"Point"}
}