{
  "type": "Feature",
  "properties": {
    "iso:country":"GB",
    "sg:address":"5 Chartist Towers, Upper Dock Street",
    "sg:city":"Newport",
    "sg:classifiers":[
        {
            "category":"Shopping",
            "subcategory":"Department Store",
            "type":"Retail Goods"
        },
        {
            "category":"Food & Beverages",
            "subcategory":"Specialty",
            "type":"Retail Goods"
        }
    ],
    "sg:phone":"+44 1633 666150",
    "sg:postcode":"NP9 1UW",
    "sg:province":"East Riding of Yorkshire",
    "sg:tags":[
        "product",
        "health"
    ],
    "wof:name":"Beanfreaks Ltd.",
    "wof:placetype":"venue"
},
  "geometry": {"coordinates":[-2.995389,51.589294],"type":"Point"}
}