{
  "type": "Feature",
  "properties": {
    "addr:full":"36 Victoria Street Merthyr Tydfil Merthyr Tydfil CF47 8BW",
    "addr:housenumber":"36",
    "addr:postcode":"cf47 8bw",
    "addr:street":"Victoria Street",
    "iso:country":"GB",
    "sg:address":"36 Victoria Street",
    "sg:city":"Merthyr Tydfil",
    "sg:classifiers":[
        {
            "category":"Travel",
            "subcategory":"Travel Agent",
            "type":"Entertainment"
        }
    ],
    "sg:phone":"+44 1685 383731",
    "sg:postcode":"CF47 8BW",
    "sg:province":"Merthyr Tydfil",
    "sg:tags":[
        "agency",
        "activity"
    ],
    "wof:name":"House of Travel (Wales) Ltd.",
    "wof:placetype":"venue"
},
  "geometry": {"coordinates":[-3.378709,51.745991],"type":"Point"}
}