{
  "type": "Feature",
  "properties": {
    "iso:country":"GB",
    "sg:address":"Burns Crescent, Girdle Toll",
    "sg:city":"Irvine",
    "sg:classifiers":[
        {
            "category":"Education",
            "subcategory":"School",
            "type":"Public Place"
        }
    ],
    "sg:phone":"+44 1294 211914",
    "sg:postcode":"KA11 1AQ",
    "sg:province":"East Ayrshire",
    "sg:tags":[
        "local",
        "authority"
    ],
    "wof:name":"Stanecastle School",
    "wof:placetype":"venue"
},
  "geometry": {"coordinates":[-4.6357879639,55.6266555786],"type":"Point"}
}