{
  "type": "Feature",
  "properties": {
    "addr:full":"5 Elm Ter, Constantine Rd Hampstead Greater London NW3 2LL",
    "addr:housenumber":"5",
    "addr:postcode":"nw3 2ll",
    "addr:street":"Elm Ter Constantine Rd",
    "iso:country":"GB",
    "sg:address":"5 Elm Ter, Constantine Rd",
    "sg:city":"Hampstead",
    "sg:classifiers":[
        {
            "category":"Health Services",
            "subcategory":"Health Practitioner",
            "type":"Services"
        }
    ],
    "sg:phone":"+44 20 7267 4222",
    "sg:postcode":"NW3 2LL",
    "sg:province":"Greater London",
    "sg:tags":[
        "homoeopathic"
    ],
    "wof:name":"Moira Houston",
    "wof:placetype":"venue"
},
  "geometry": {"coordinates":[-0.164628,51.554317],"type":"Point"}
}