{
  "type": "Feature",
  "properties": {
    "addr:full":"65 Butts Green Road Hornchurch Essex RM11 2JS",
    "addr:housenumber":"65",
    "addr:postcode":"rm11 2js",
    "addr:street":"Butts Green Road",
    "iso:country":"GB",
    "sg:address":"65 Butts Green Road",
    "sg:city":"Hornchurch",
    "sg:classifiers":[
        {
            "category":"Insurance",
            "subcategory":"Insurance Agent",
            "type":"Services"
        }
    ],
    "sg:phone":"+44 1708 764000",
    "sg:postcode":"RM11 2JS",
    "sg:province":"Essex",
    "wof:name":"Tenaville Insurance Services Ltd.",
    "wof:placetype":"venue"
},
  "geometry": {"coordinates":[0.2190700024,51.5711555481],"type":"Point"}
}