{
  "type": "Feature",
  "properties": {
    "iso:country":"GB",
    "sg:address":"14 Glenalmond Road",
    "sg:city":"Sheffield",
    "sg:classifiers":[
        {
            "category":"Communications",
            "subcategory":"Film & Video Production",
            "type":"Services"
        }
    ],
    "sg:phone":"+44 7767 622567",
    "sg:postcode":"S11 7GW",
    "sg:province":"Derbyshire",
    "sg:tags":[
        "recording",
        "studio"
    ],
    "wof:name":"Mother Digital Studios",
    "wof:placetype":"venue"
},
  "geometry": {"coordinates":[-1.508286,53.360588],"type":"Point"}
}