{
  "type": "Feature",
  "properties": {
    "iso:country":"GB",
    "sg:address":"Showmens Winter Quarters, Stn App, Stn R, Woodford Halse",
    "sg:city":"Daventry",
    "sg:classifiers":[
        {
            "category":"Recreation",
            "subcategory":"Amusement Park",
            "type":"Entertainment"
        }
    ],
    "sg:postcode":"NN11 3RB",
    "sg:province":"Northamptonshire",
    "sg:tags":[
        "arcade"
    ],
    "wof:name":"Scarrott,J,& Sons",
    "wof:placetype":"venue"
},
  "geometry": {"coordinates":[-1.207829,52.169914],"type":"Point"}
}