{
  "type": "Feature",
  "properties": {
    "addr:full":"Sandy Lane Farm, Sandy La Ormskirk Lancashire L40 2QB",
    "addr:postcode":"l40 2qb",
    "addr:street":"Sandy Lane",
    "iso:country":"GB",
    "sg:address":"Sandy Lane Farm, Sandy La",
    "sg:city":"Ormskirk",
    "sg:classifiers":[
        {
            "category":"Farming",
            "subcategory":"Livestock Farm",
            "type":"Manufacturing & Wholesale Goods"
        }
    ],
    "sg:phone":"+44 1704 822385",
    "sg:postcode":"L40 2QB",
    "sg:province":"Lancashire",
    "sg:tags":[
        "others"
    ],
    "wof:name":"R Sharrock",
    "wof:placetype":"venue"
},
  "geometry": {"coordinates":[-2.7813439369,53.6267585754],"type":"Point"}
}