{
  "type": "Feature",
  "properties": {
    "addr:full":"Park House, Lombard Business Park, 8 Lombard Road London Greater London SW19 3TZ",
    "addr:housenumber":"8",
    "addr:postcode":"sw19 3tz",
    "addr:street":"Park;Lombard Road",
    "iso:country":"GB",
    "sg:address":"Park House, Lombard Business Park, 8 Lombard Road",
    "sg:city":"London",
    "sg:classifiers":[
        {
            "category":"Communications",
            "type":"Services"
        }
    ],
    "sg:phone":"+44 20 8543 9989",
    "sg:postcode":"SW19 3TZ",
    "sg:province":"Greater London",
    "sg:tags":[
        "data",
        "network"
    ],
    "wof:name":"Ashtead Design & Marketing Ltd.",
    "wof:placetype":"venue"
},
  "geometry": {"coordinates":[-0.189534,51.409149],"type":"Point"}
}