{
  "type": "Feature",
  "properties": {
    "iso:country":"GB",
    "sg:address":"16 Belgrave Commercial Centre, 162 Belgrave Road",
    "sg:city":"Leicester",
    "sg:classifiers":[
        {
            "category":"Professional",
            "subcategory":"Printing & Photocopies",
            "type":"Services"
        }
    ],
    "sg:postcode":"LE4 5AU",
    "sg:province":"Leicestershire",
    "sg:tags":[
        "printer"
    ],
    "wof:name":"Helandra Print",
    "wof:placetype":"venue"
},
  "geometry": {"coordinates":[-1.1223640442,52.6550636292],"type":"Point"}
}