{
  "type": "Feature",
  "properties": {
    "iso:country":"GB",
    "sg:address":"P O Box 4592",
    "sg:city":"London",
    "sg:classifiers":[
        {
            "category":"Professional",
            "subcategory":"Management & Consulting",
            "type":"Services"
        }
    ],
    "sg:phone":"+44 20 8540 7518",
    "sg:postcode":"SW19 1XJ",
    "sg:province":"Greater London",
    "sg:tags":[
        "consultant",
        "business"
    ],
    "wof:name":"Pia Consulting Ltd",
    "wof:placetype":"venue"
},
  "geometry": {"coordinates":[-0.19174,51.41983],"type":"Point"}
}