{
  "type": "Feature",
  "properties": {
    "addr:full":"Coulsdon Court Road Coulsdon Surrey CR5 2LL",
    "addr:postcode":"cr5 2ll",
    "addr:street":"Coulsdon Court Road",
    "iso:country":"GB",
    "sg:address":"Coulsdon Court Road",
    "sg:city":"Coulsdon",
    "sg:classifiers":[
        {
            "category":"Community Center",
            "type":"Public Place"
        }
    ],
    "sg:phone":"+44 20 8668 6509",
    "sg:postcode":"CR5 2LL",
    "sg:province":"Surrey",
    "sg:tags":[
        "recreation",
        "leisure",
        "centre"
    ],
    "wof:name":"Coulsdon Manor Reflections Leisure Club",
    "wof:placetype":"venue"
},
  "geometry": {"coordinates":[-0.1241249964,51.3152961731],"type":"Point"}
}