{
  "type": "Feature",
  "properties": {
    "addr:full":"116-126 Steelhouse Lane Wolverhampton West Midlands WV2 2AW",
    "addr:postcode":"116-126;wv2 2aw",
    "addr:street":"Steelhouse Lane",
    "iso:country":"GB",
    "sg:address":"116-126 Steelhouse Lane",
    "sg:city":"Wolverhampton",
    "sg:classifiers":[
        {
            "category":"Retail",
            "subcategory":"Repair Shop",
            "type":"Services"
        }
    ],
    "sg:phone":"+44 1902 450004",
    "sg:postcode":"WV2 2AW",
    "sg:province":"West Midlands",
    "sg:tags":[
        "upholsterer"
    ],
    "wof:name":"The Sofa Factory",
    "wof:placetype":"venue"
},
  "geometry": {"coordinates":[-2.115436,52.578323],"type":"Point"}
}