{
  "type": "Feature",
  "properties": {
    "addr:full":"1 Shaw Street Worcester Worcestershire WR1 3QQ",
    "addr:housenumber":"1",
    "addr:postcode":"wr1 3qq",
    "addr:street":"Shaw Street",
    "iso:country":"GB",
    "sg:address":"1 Shaw Street",
    "sg:city":"Worcester",
    "sg:classifiers":[
        {
            "category":"Real Estate",
            "subcategory":"Architect",
            "type":"Services"
        }
    ],
    "sg:postcode":"WR1 3QQ",
    "sg:province":"Worcestershire",
    "wof:name":"Wood Kendrick & Williams",
    "wof:placetype":"venue"
},
  "geometry": {"coordinates":[-2.2219090462,52.1943893433],"type":"Point"}
}