{
  "type": "Feature",
  "properties": {
    "addr:full":"2 Woodhall Rd Edinburgh City of Edinburgh EH13 0DX",
    "addr:housenumber":"2",
    "addr:postcode":"eh13 0dx",
    "addr:street":"Woodhall Rd",
    "iso:country":"GB",
    "sg:address":"2 Woodhall Rd",
    "sg:city":"Edinburgh",
    "sg:classifiers":[
        {
            "category":"Building & Trades",
            "subcategory":"Plumbing",
            "type":"Services"
        }
    ],
    "sg:phone":"+44 131 441 2003",
    "sg:postcode":"EH13 0DX",
    "sg:province":"City of Edinburgh",
    "sg:tags":[
        "heating"
    ],
    "wof:name":"OSH Plumbing",
    "wof:placetype":"venue"
},
  "geometry": {"coordinates":[-3.263009,55.906132],"type":"Point"}
}