{
  "type": "Feature",
  "properties": {
    "addr:full":"Robin Hood Rd, Willenhall Coventry Warwickshire CV3 3BB",
    "addr:postcode":"cv3 3bb",
    "addr:street":"Robin Hood Rd",
    "iso:country":"GB",
    "sg:address":"Robin Hood Rd, Willenhall",
    "sg:city":"Coventry",
    "sg:classifiers":[
        {
            "category":"Organizations",
            "subcategory":"Membership Organization",
            "type":"Services"
        }
    ],
    "sg:postcode":"CV3 3BB",
    "sg:province":"Warwickshire",
    "sg:tags":[
        "club"
    ],
    "wof:name":"Willenhall Social Club & Institute Ltd",
    "wof:placetype":"venue"
},
  "geometry": {"coordinates":[-1.463304,52.387772],"type":"Point"}
}