{
  "type": "Feature",
  "properties": {
    "addr:full":"Holymoor Road, Holymoorside Chesterfield Derbyshire S42 7DX",
    "addr:postcode":"s42 7dx",
    "addr:street":"Holymoor Road Holymoorside",
    "iso:country":"GB",
    "sg:address":"Holymoor Road, Holymoorside",
    "sg:city":"Chesterfield",
    "sg:classifiers":[
        {
            "category":"Government",
            "subcategory":"City Hall",
            "type":"Public Place"
        }
    ],
    "sg:phone":"+44 1246 569882",
    "sg:postcode":"S42 7DX",
    "sg:province":"Derbyshire",
    "wof:name":"Holymoorside & Walton Parish Council",
    "wof:placetype":"venue"
},
  "geometry": {"coordinates":[-1.493799,53.220692],"type":"Point"}
}