{
  "type": "Feature",
  "properties": {
    "addr:full":"12 Friars Street Stirling Stirling FK8 1HA",
    "addr:housenumber":"12",
    "addr:postcode":"fk8 1ha",
    "addr:street":"Friars Street",
    "iso:country":"GB",
    "sg:address":"12 Friars Street",
    "sg:city":"Stirling",
    "sg:classifiers":[
        {
            "category":"Shopping",
            "subcategory":"Baby Store",
            "type":"Retail Goods"
        }
    ],
    "sg:phone":"+44 1786 470082",
    "sg:postcode":"FK8 1HA",
    "sg:province":"Stirling",
    "sg:tags":[
        "babywear",
        "childrens"
    ],
    "wof:name":"The Honeytree",
    "wof:placetype":"venue"
},
  "geometry": {"coordinates":[-3.937865,56.11919],"type":"Point"}
}