{
  "type": "Feature",
  "properties": {
    "addr:full":"23 Trinity Farm Ct, Mistley Manningtree Essex CO11 2HL",
    "addr:housenumber":"23",
    "addr:postcode":"co11 2hl",
    "addr:street":"Trinity Farm Ct",
    "iso:country":"GB",
    "sg:address":"23 Trinity Farm Ct, Mistley",
    "sg:city":"Manningtree",
    "sg:classifiers":[
        {
            "category":"Organizations",
            "subcategory":"Non-profit Organization",
            "type":"Services"
        }
    ],
    "sg:postcode":"CO11 2HL",
    "sg:province":"Essex",
    "sg:tags":[
        "organisation",
        "voluntary",
        "charity"
    ],
    "wof:name":"The Kidney Foundation East Anglian Regio",
    "wof:placetype":"venue"
},
  "geometry": {"coordinates":[1.06304,51.945381],"type":"Point"}
}