{
  "type": "Feature",
  "properties": {
    "addr:full":"Sovereign Rd, Kings Norton Business Centre, Kings Norton Birmingham West Midlands B30 3HQ",
    "addr:housenumber":"business centre",
    "addr:postcode":"b30 3hq",
    "addr:street":"Sovereign Rd",
    "iso:country":"GB",
    "sg:address":"Sovereign Rd, Kings Norton Business Centre, Kings Norton",
    "sg:city":"Birmingham",
    "sg:classifiers":[
        {
            "category":"Autos & Motor Vehicles",
            "subcategory":"Automobile Sales",
            "type":"Retail Goods"
        }
    ],
    "sg:phone":"+44 121 433 8888",
    "sg:postcode":"B30 3HQ",
    "sg:province":"West Midlands",
    "sg:tags":[
        "commercial"
    ],
    "wof:name":"Monarch Cars",
    "wof:placetype":"venue"
},
  "geometry": {"coordinates":[-1.9236969948,52.4156188965],"type":"Point"}
}