{
  "type": "Feature",
  "properties": {
    "addr:full":"3 Oxgangs Park Edinburgh City of Edinburgh EH13 9JZ",
    "addr:housenumber":"3",
    "addr:postcode":"eh13 9jz",
    "addr:street":"Oxgangs Park Edinburgh",
    "iso:country":"GB",
    "sg:address":"3 Oxgangs Park",
    "sg:city":"Edinburgh",
    "sg:classifiers":[
        {
            "category":"Government",
            "subcategory":"Fire Station",
            "type":"Public Place"
        }
    ],
    "sg:postcode":"EH13 9JZ",
    "sg:province":"City of Edinburgh",
    "sg:tags":[
        "security"
    ],
    "wof:name":"Cheetah Fire",
    "wof:placetype":"venue"
},
  "geometry": {"coordinates":[-3.223943,55.90773],"type":"Point"}
}