{
  "type": "Feature",
  "properties": {
    "addr:full":"Unit 17 Weston-super-mare Somerset BS24 9DJ",
    "addr:housenumber":"unit 17",
    "addr:postcode":"bs24 9dj",
    "iso:country":"GB",
    "sg:address":"Unit 17",
    "sg:city":"Weston-super-mare",
    "sg:classifiers":[
        {
            "category":"Home & Garden",
            "subcategory":"Home Furnishings",
            "type":"Retail Goods"
        }
    ],
    "sg:phone":"+44 1934 414598",
    "sg:postcode":"BS24 9DJ",
    "sg:province":"Somerset",
    "sg:tags":[
        "furnishers",
        "planner",
        "bedroom"
    ],
    "wof:name":"Woodcharm Fitted Bedrooms",
    "wof:placetype":"venue"
},
  "geometry": {"coordinates":[-2.9268040657,51.3256454468],"type":"Point"}
}