{
  "type": "Feature",
  "properties": {
    "addr:full":"100 Kimbolton Crescent Stevenage Hertfordshire SG2 8RL",
    "addr:housenumber":"100",
    "addr:postcode":"sg2 8rl",
    "addr:street":"Kimbolton Crescent",
    "iso:country":"GB",
    "sg:address":"100 Kimbolton Crescent",
    "sg:city":"Stevenage",
    "sg:classifiers":[
        {
            "category":"Building & Trades",
            "subcategory":"Cleaning & Sanitation",
            "type":"Services"
        }
    ],
    "sg:phone":"+44 1438 741975",
    "sg:postcode":"SG2 8RL",
    "sg:province":"Hertfordshire",
    "sg:tags":[
        "dry",
        "control",
        "damp",
        "rot"
    ],
    "wof:name":"Countrywide Property Care",
    "wof:placetype":"venue"
},
  "geometry": {"coordinates":[-0.1832509935,51.8781204224],"type":"Point"}
}