{
  "type": "Feature",
  "properties": {
    "addr:full":"6 East Laith Gate Doncaster South Yorkshire DN1 1HZ",
    "addr:housenumber":"6",
    "addr:postcode":"dn1 1hz",
    "addr:street":"East Laith Gate",
    "iso:country":"GB",
    "sg:address":"6 East Laith Gate",
    "sg:city":"Doncaster",
    "sg:classifiers":[
        {
            "category":"Shopping",
            "subcategory":"Bicycles & Sporting Goods",
            "type":"Retail Goods"
        }
    ],
    "sg:postcode":"DN1 1HZ",
    "sg:province":"South Yorkshire",
    "sg:tags":[
        "equipment",
        "leisure"
    ],
    "wof:name":"Kingfisher Diving Services",
    "wof:placetype":"venue"
},
  "geometry": {"coordinates":[-1.131063,53.524502],"type":"Point"}
}