{
  "type": "Feature",
  "properties": {
    "addr:full":"15 Lavender Clo Aylesbury Buckinghamshire HP21 8YY",
    "addr:housenumber":"15",
    "addr:postcode":"hp21 8yy",
    "addr:street":"Lavender Clo",
    "iso:country":"GB",
    "sg:address":"15 Lavender Clo",
    "sg:city":"Aylesbury",
    "sg:classifiers":[
        {
            "category":"Home & Garden",
            "subcategory":"Carpets & Floor Coverings",
            "type":"Retail Goods"
        }
    ],
    "sg:postcode":"HP21 8YY",
    "sg:province":"Buckinghamshire",
    "sg:tags":[
        "cleaner",
        "upholstery"
    ],
    "wof:name":"Bartlett,Andrew,",
    "wof:placetype":"venue"
},
  "geometry": {"coordinates":[-0.828535974,51.8053741455],"type":"Point"}
}