{
  "type": "Feature",
  "properties": {
    "addr:full":"256 Reading Road, Winnersh Wokingham Berkshire RG41 5AA",
    "addr:housenumber":"256",
    "addr:postcode":"rg41 5aa",
    "addr:street":"Reading Road",
    "iso:country":"GB",
    "sg:address":"256 Reading Road, Winnersh",
    "sg:city":"Wokingham",
    "sg:classifiers":[
        {
            "category":"Professional",
            "subcategory":"Engineering",
            "type":"Services"
        }
    ],
    "sg:phone":"+44 118 962 9666",
    "sg:postcode":"RG41 5AA",
    "sg:province":"Berkshire",
    "sg:tags":[
        "engineer",
        "structural"
    ],
    "wof:name":"Michael Aubrey Partnership Ltd.",
    "wof:placetype":"venue"
},
  "geometry": {"coordinates":[-0.865326,51.423157],"type":"Point"}
}