{
  "type": "Feature",
  "properties": {
    "iso:country":"GB",
    "sg:address":"156 Uxbridge Rd",
    "sg:city":"London",
    "sg:classifiers":[
        {
            "category":"Professional",
            "subcategory":"Business Services",
            "type":"Services"
        }
    ],
    "sg:postcode":"W13 8SB",
    "sg:province":"Greater London",
    "sg:tags":[
        "hospitality",
        "corporate"
    ],
    "wof:name":"Avalon Events",
    "wof:placetype":"venue"
},
  "geometry": {"coordinates":[-0.3190740049,51.5110702515],"type":"Point"}
}