{
  "type": "Feature",
  "properties": {
    "iso:country":"GB",
    "sg:address":"Po Box 3",
    "sg:city":"Glastonbury",
    "sg:classifiers":[
        {
            "category":"Personal",
            "subcategory":"Skin Care",
            "type":"Services"
        }
    ],
    "sg:phone":"+44 1458 831420",
    "sg:postcode":"BA6 8YA",
    "sg:province":"Somerset",
    "sg:tags":[
        "leather",
        "merchant"
    ],
    "wof:name":"R J Draper & Co. Ltd.",
    "wof:placetype":"venue"
},
  "geometry": {"coordinates":[-2.685509,51.112499],"type":"Point"}
}