{
  "type": "Feature",
  "properties": {
    "addr:full":"20 Bond Street Dewsbury West Yorkshire WF13 1AT",
    "addr:housenumber":"20",
    "addr:postcode":"wf13 1at",
    "addr:street":"Bond Street",
    "iso:country":"GB",
    "sg:address":"20 Bond Street",
    "sg:city":"Dewsbury",
    "sg:classifiers":[
        {
            "category":"Professional",
            "subcategory":"Lawyer & Legal Services",
            "type":"Services"
        }
    ],
    "sg:phone":"+44 1924 464101",
    "sg:postcode":"WF13 1AT",
    "sg:province":"West Yorkshire",
    "sg:tags":[
        "solicitor"
    ],
    "wof:name":"Disken & Co.",
    "wof:placetype":"venue"
},
  "geometry": {"coordinates":[-1.6309809685,53.6922492981],"type":"Point"}
}