{
  "type": "Feature",
  "properties": {
    "addr:full":"Canllefaes Ganol, Penparc Cardigan Ceredigion SA43 1SG",
    "addr:postcode":"sa43 1sg",
    "addr:street":"Penparc",
    "iso:country":"GB",
    "sg:address":"Canllefaes Ganol, Penparc",
    "sg:city":"Cardigan",
    "sg:classifiers":[
        {
            "category":"Home & Garden",
            "subcategory":"Hardware",
            "type":"Retail Goods"
        }
    ],
    "sg:phone":"+44 1239 613712",
    "sg:postcode":"SA43 1SG",
    "sg:province":"Ceredigion",
    "sg:tags":[
        "equipment",
        "heating"
    ],
    "wof:name":"Cardigan Woodburners",
    "wof:placetype":"venue"
},
  "geometry": {"coordinates":[-4.655044,52.086868],"type":"Point"}
}