{
  "type": "Feature",
  "properties": {
    "addr:full":"34 Underhill Close, Oakenshaw Redditch Warwickshire B98 7WX",
    "addr:housenumber":"34",
    "addr:postcode":"oakenshaw;b98 7wx",
    "addr:street":"Underhill Close",
    "iso:country":"GB",
    "sg:address":"34 Underhill Close, Oakenshaw",
    "sg:city":"Redditch",
    "sg:classifiers":[
        {
            "category":"Professional",
            "type":"Services"
        }
    ],
    "sg:phone":"+44 1527 542118",
    "sg:postcode":"B98 7WX",
    "sg:province":"Warwickshire",
    "sg:tags":[
        "caterer"
    ],
    "wof:name":"Val's Catering",
    "wof:placetype":"venue"
},
  "geometry": {"coordinates":[-1.9332009554,52.2804718018],"type":"Point"}
}