{
  "type": "Feature",
  "properties": {
    "iso:country":"GB",
    "sg:address":"Unit 3, Trinity Trading Estate, Silverdale Road",
    "sg:city":"Hayes",
    "sg:classifiers":[
        {
            "category":"Building & Trades",
            "subcategory":"Construction",
            "type":"Services"
        }
    ],
    "sg:postcode":"UB3 3BN",
    "sg:province":"Greater London",
    "sg:tags":[
        "ceiling",
        "contractor"
    ],
    "wof:name":"Packman Contracts Plc",
    "wof:placetype":"venue"
},
  "geometry": {"coordinates":[-0.4247559905,51.5015525818],"type":"Point"}
}