{
  "type": "Feature",
  "properties": {
    "addr:full":"9 Yew Tree Avenue, Ockbrook Derby Derbyshire DE72 3TB",
    "addr:housenumber":"9",
    "addr:postcode":"de72 3tb",
    "addr:street":"Yew Tree Avenue",
    "iso:country":"GB",
    "sg:address":"9 Yew Tree Avenue, Ockbrook",
    "sg:city":"Derby",
    "sg:classifiers":[
        {
            "category":"Building & Trades",
            "subcategory":"Plumbing",
            "type":"Services"
        }
    ],
    "sg:phone":"+44 1332 673901",
    "sg:postcode":"DE72 3TB",
    "sg:province":"Derbyshire",
    "sg:tags":[
        "plumber",
        "heating"
    ],
    "wof:name":"D H Green",
    "wof:placetype":"venue"
},
  "geometry": {"coordinates":[-1.3689240217,52.9215164185],"type":"Point"}
}