{
  "type": "Feature",
  "properties": {
    "addr:full":"Tilford Road Farnham Surrey GU9 8DL",
    "addr:postcode":"gu9 8dl",
    "addr:street":"Tilford Road",
    "iso:country":"GB",
    "sg:address":"Tilford Road",
    "sg:city":"Farnham",
    "sg:classifiers":[
        {
            "category":"Building & Trades",
            "subcategory":"Construction",
            "type":"Services"
        }
    ],
    "sg:phone":"+44 1252 725626",
    "sg:postcode":"GU9 8DL",
    "sg:province":"Surrey",
    "sg:tags":[
        "roofing"
    ],
    "wof:name":"Mike Clark",
    "wof:placetype":"venue"
},
  "geometry": {"coordinates":[-0.791124,51.211262],"type":"Point"}
}