{
  "type": "Feature",
  "properties": {
    "iso:country":"GB",
    "sg:address":"Royal Parade",
    "sg:city":"Plymouth",
    "sg:classifiers":[
        {
            "category":"Personal",
            "subcategory":"Beauty Salon",
            "type":"Services"
        }
    ],
    "sg:phone":"+44 1752 257478",
    "sg:postcode":"PL1 1SA",
    "sg:province":"Devon",
    "wof:name":"Yves Rocher (London) Ltd.",
    "wof:placetype":"venue"
},
  "geometry": {"coordinates":[-4.143639,50.370346],"type":"Point"}
}