{
  "type": "Feature",
  "properties": {
    "addr:full":"Wern Farm, Pontantwn Kidwelly Carmarthenshire SA17 5LR",
    "addr:postcode":"sa17 5lr",
    "iso:country":"GB",
    "sg:address":"Wern Farm, Pontantwn",
    "sg:city":"Kidwelly",
    "sg:classifiers":[
        {
            "category":"Farming",
            "subcategory":"Livestock Farm",
            "type":"Manufacturing & Wholesale Goods"
        }
    ],
    "sg:phone":"+44 1269 860871",
    "sg:postcode":"SA17 5LR",
    "sg:province":"Carmarthenshire",
    "sg:tags":[
        "others"
    ],
    "sg:website":"http://www.waitrose.com",
    "wof:name":"V L & D M Morgan",
    "wof:placetype":"venue"
},
  "geometry": {"coordinates":[-4.2638840675,51.7945861816],"type":"Point"}
}