{
  "type": "Feature",
  "properties": {
    "iso:country":"GB",
    "sg:address":"Kitty Briggs Lane",
    "sg:city":"Grantham",
    "sg:classifiers":[
        {
            "category":"Education",
            "subcategory":"School",
            "type":"Public Place"
        },
        {
            "category":"Government",
            "subcategory":"Office",
            "type":"Public Place"
        }
    ],
    "sg:phone":"+44 1476 563251",
    "sg:postcode":"NG31 7JR",
    "sg:province":"Lincolnshire",
    "sg:tags":[
        "local",
        "authority"
    ],
    "wof:name":"The Walton Girls High School",
    "wof:placetype":"venue"
},
  "geometry": {"coordinates":[-0.657824,52.898457],"type":"Point"}
}