{
  "type": "Feature",
  "properties": {
    "addr:full":"Queen's House, Queen Street Barnstaple Devon EX32 8HJ",
    "addr:postcode":"ex32 8hj",
    "addr:street":"Queen Street",
    "iso:country":"GB",
    "sg:address":"Queen's House, Queen Street",
    "sg:city":"Barnstaple",
    "sg:classifiers":[
        {
            "category":"Education",
            "subcategory":"Special Training",
            "type":"Public Place"
        }
    ],
    "sg:phone":"+44 1271 324224",
    "sg:postcode":"EX32 8HJ",
    "sg:province":"Devon",
    "sg:tags":[
        "product",
        "centre"
    ],
    "wof:name":"North Devon Business Development Centre",
    "wof:placetype":"venue"
},
  "geometry": {"coordinates":[-4.0565900803,51.0795898438],"type":"Point"}
}