{
  "type": "Feature",
  "properties": {
    "iso:country":"GB",
    "sg:address":"South Terrace",
    "sg:city":"Cambridge",
    "sg:classifiers":[
        {
            "category":"Retail",
            "subcategory":"Storage",
            "type":"Services"
        }
    ],
    "sg:postcode":"CB2 4EL",
    "sg:province":"Cambridgeshire",
    "sg:tags":[
        "household",
        "removal"
    ],
    "wof:name":"Finbow & Sons Ltd.",
    "wof:placetype":"venue"
},
  "geometry": {"coordinates":[0.171465,52.11264],"type":"Point"}
}