{
  "type": "Feature",
  "properties": {
    "iso:country":"GB",
    "sg:address":"95 Clay Street, Soham",
    "sg:city":"Ely",
    "sg:classifiers":[
        {
            "category":"Professional",
            "subcategory":"Engineering",
            "type":"Services"
        }
    ],
    "sg:phone":"+44 1353 720346",
    "sg:postcode":"CB7 5HL",
    "sg:province":"Cambridgeshire",
    "sg:tags":[
        "contractor",
        "electrical",
        "engineer"
    ],
    "wof:name":"A L Fuller Ltd.",
    "wof:placetype":"venue"
},
  "geometry": {"coordinates":[0.330868,52.333363],"type":"Point"}
}