{
  "type": "Feature",
  "properties": {
    "addr:full":"Abbey House, Charter Street Leicester Leicestershire LE1 3UD",
    "addr:postcode":"le1 3ud",
    "addr:street":"Charter Street",
    "iso:country":"GB",
    "sg:address":"Abbey House, Charter Street",
    "sg:city":"Leicester",
    "sg:classifiers":[
        {
            "category":"Autos & Motor Vehicles",
            "subcategory":"Fuel & Gas Station",
            "type":"Retail Goods"
        },
        {
            "category":"Wholesale",
            "subcategory":"Machinery & Supplies",
            "type":"Manufacturing & Wholesale Goods"
        }
    ],
    "sg:phone":"+44 116 242 5425",
    "sg:postcode":"LE1 3UD",
    "sg:province":"Leicestershire",
    "sg:tags":[
        "pump",
        "sale",
        "servicing"
    ],
    "wof:name":"Flow Mech Products Ltd.",
    "wof:placetype":"venue"
},
  "geometry": {"coordinates":[-1.130009,52.642494],"type":"Point"}
}