{
  "type": "Feature",
  "properties": {
    "addr:full":"62 Rock La Hastings East Sussex TN35 4JN",
    "addr:housenumber":"62",
    "addr:postcode":"tn35 4jn",
    "addr:street":"Rock La Hastings",
    "iso:country":"GB",
    "sg:address":"62 Rock La",
    "sg:city":"Hastings",
    "sg:classifiers":[
        {
            "category":"Building & Trades",
            "subcategory":"Construction",
            "type":"Services"
        }
    ],
    "sg:phone":"+44 1424 433959",
    "sg:postcode":"TN35 4JN",
    "sg:province":"East Sussex",
    "sg:tags":[
        "bricklaying"
    ],
    "wof:name":"J F Ford",
    "wof:placetype":"venue"
},
  "geometry": {"coordinates":[0.608838,50.87886],"type":"Point"}
}