{
  "type": "Feature",
  "properties": {
    "addr:full":"Barbican Road, East Looe Looe Cornwall PL13 1EY",
    "addr:postcode":"pl13 1ey",
    "addr:street":"Barbican Road",
    "iso:country":"GB",
    "sg:address":"Barbican Road, East Looe",
    "sg:city":"Looe",
    "sg:classifiers":[
        {
            "category":"Bars & Pubs",
            "type":"Food & Drink"
        },
        {
            "category":"Retail",
            "subcategory":"Auto Repair",
            "type":"Services"
        }
    ],
    "sg:phone":"+44 1503 262877",
    "sg:postcode":"PL13 1EY",
    "sg:province":"Cornwall",
    "sg:tags":[
        "pubs",
        "garage",
        "inn",
        "modification"
    ],
    "wof:name":"Barbican Car Repairs",
    "wof:placetype":"venue"
},
  "geometry": {"coordinates":[-4.4486541748,50.3628807068],"type":"Point"}
}