{
  "type": "Feature",
  "properties": {
    "addr:full":"Stallington Road, Blyth Bridge Stoke-on-trent Staffordshire ST11 9PD",
    "addr:postcode":"st11 9pd",
    "addr:street":"Stallington Road;Bridge",
    "iso:country":"GB",
    "sg:address":"Stallington Road, Blyth Bridge",
    "sg:city":"Stoke-on-trent",
    "sg:classifiers":[
        {
            "category":"Manufacturing",
            "subcategory":"Lumber",
            "type":"Manufacturing & Wholesale Goods"
        }
    ],
    "sg:postcode":"ST11 9PD",
    "sg:province":"Staffordshire",
    "sg:tags":[
        "importer",
        "merchants",
        "agent",
        "timber"
    ],
    "wof:name":"Stallington Timber Importers Ltd.",
    "wof:placetype":"venue"
},
  "geometry": {"coordinates":[-2.064509,52.964775],"type":"Point"}
}