{
  "type": "Feature",
  "properties": {
    "addr:full":"4 Station Court Ware Hertfordshire SG12 9UT",
    "addr:housenumber":"4",
    "addr:postcode":"sg12 9ut",
    "addr:street":"Station Court",
    "iso:country":"GB",
    "sg:address":"4 Station Court",
    "sg:city":"Ware",
    "sg:classifiers":[
        {
            "category":"Organizations",
            "subcategory":"Membership Organization",
            "type":"Services"
        }
    ],
    "sg:postcode":"SG12 9UT",
    "sg:province":"Hertfordshire",
    "sg:tags":[
        "club"
    ],
    "wof:name":"St. Andrew's Court (Ware) Ltd.",
    "wof:placetype":"venue"
},
  "geometry": {"coordinates":[-0.028597,51.808369],"type":"Point"}
}