{
  "type": "Feature",
  "properties": {
    "iso:country":"GB",
    "sg:address":"24 Alexandra Rd",
    "sg:city":"Hull",
    "sg:classifiers":[
        {
            "category":"Building & Trades",
            "subcategory":"Construction",
            "type":"Services"
        }
    ],
    "sg:phone":"+44 1482 448593",
    "sg:postcode":"HU5 2NS",
    "sg:province":"East Riding of Yorkshire",
    "sg:tags":[
        "roofing"
    ],
    "wof:name":"Gibson Clark Builders",
    "wof:placetype":"venue"
},
  "geometry": {"coordinates":[-0.353865,53.765102],"type":"Point"}
}