{
  "type": "Feature",
  "properties": {
    "iso:country":"GB",
    "sg:address":"83 Warwick Street",
    "sg:city":"Leamington Spa",
    "sg:classifiers":[
        {
            "category":"Home & Garden",
            "subcategory":"Household Appliances",
            "type":"Retail Goods"
        }
    ],
    "sg:phone":"+44 1926 831297",
    "sg:postcode":"CV32 4RR",
    "sg:province":"Warwickshire",
    "sg:tags":[
        "electrical",
        "domestic"
    ],
    "wof:name":"Tandy",
    "wof:placetype":"venue"
},
  "geometry": {"coordinates":[-1.534016,52.292217],"type":"Point"}
}