{
  "type": "Feature",
  "properties": {
    "addr:full":"Brooklyn, Buxton Road Macclesfield Cheshire SK10 1LZ",
    "addr:postcode":"sk10 1lz",
    "addr:street":"Buxton Road",
    "iso:country":"GB",
    "sg:address":"Brooklyn, Buxton Road",
    "sg:city":"Macclesfield",
    "sg:classifiers":[
        {
            "category":"Retail",
            "subcategory":"Repair Shop",
            "type":"Services"
        }
    ],
    "sg:postcode":"SK10 1LZ",
    "sg:province":"Cheshire",
    "sg:tags":[
        "radio",
        "television",
        "video"
    ],
    "wof:name":"Rogers Video Tv & Sat Services",
    "wof:placetype":"venue"
},
  "geometry": {"coordinates":[-2.1153399944,53.259021759],"type":"Point"}
}