{
  "type": "Feature",
  "properties": {
    "iso:country":"GB",
    "sg:address":"Bolton Rd, Atherton",
    "sg:city":"Manchester",
    "sg:classifiers":[
        {
            "category":"Wholesale",
            "subcategory":"Machinery & Supplies",
            "type":"Manufacturing & Wholesale Goods"
        }
    ],
    "sg:phone":"+44 1942 884799",
    "sg:postcode":"M46 9JZ",
    "sg:province":"Greater Manchester",
    "sg:tags":[
        "hydraulic"
    ],
    "wof:name":"Hydra Services",
    "wof:placetype":"venue"
},
  "geometry": {"coordinates":[-2.472244,53.531593],"type":"Point"}
}