{
  "type": "Feature",
  "properties": {
    "iso:country":"GB",
    "sg:address":"60 Bassnage Road",
    "sg:city":"Halesowen",
    "sg:classifiers":[
        {
            "category":"Manufacturing",
            "subcategory":"Petroleum Products",
            "type":"Manufacturing & Wholesale Goods"
        }
    ],
    "sg:postcode":"B63 4HQ",
    "sg:province":"West Midlands",
    "sg:tags":[
        "double",
        "glazing"
    ],
    "wof:name":"Dale Windows",
    "wof:placetype":"venue"
},
  "geometry": {"coordinates":[-2.069664,52.444817],"type":"Point"}
}