{
  "type": "Feature",
  "properties": {
    "addr:full":"The Garage, Preston Street Fleetwood Lancashire FY7 6JA",
    "addr:postcode":"fy7 6ja",
    "addr:street":"Preston Street",
    "iso:country":"GB",
    "sg:address":"The Garage, Preston Street",
    "sg:city":"Fleetwood",
    "sg:classifiers":[
        {
            "category":"Retail",
            "subcategory":"Auto Repair",
            "type":"Services"
        }
    ],
    "sg:phone":"+44 1253 874916",
    "sg:postcode":"FY7 6JA",
    "sg:province":"Lancashire",
    "sg:tags":[
        "modification",
        "garage",
        "related"
    ],
    "sg:website":"http://www.jjmotors.co.uk",
    "wof:name":"J & J Motors",
    "wof:placetype":"venue"
},
  "geometry": {"coordinates":[-3.013829,53.922955],"type":"Point"}
}