{
  "type": "Feature",
  "properties": {
    "iso:country":"GB",
    "sg:address":"8 Ramsey Colliery Engine Rd",
    "sg:city":"Loanhead",
    "sg:classifiers":[
        {
            "category":"Freight",
            "type":"Transportation"
        }
    ],
    "sg:phone":"+44 131 440 2980",
    "sg:postcode":"EH20 9RF",
    "sg:province":"Midlothian",
    "sg:tags":[
        "haulage",
        "road"
    ],
    "wof:name":"Caspian & Asian Freight Services Ltd",
    "wof:placetype":"venue"
},
  "geometry": {"coordinates":[-3.154689,55.880932],"type":"Point"}
}