{
  "type": "Feature",
  "properties": {
    "iso:country":"GB",
    "sg:address":"19 Elmbridge Road",
    "sg:city":"Cranleigh",
    "sg:classifiers":[
        {
            "category":"Professional",
            "subcategory":"Engineering",
            "type":"Services"
        },
        {
            "category":"Building & Trades",
            "subcategory":"Electrical",
            "type":"Services"
        }
    ],
    "sg:phone":"+44 1483 273642",
    "sg:postcode":"GU6 8NH",
    "sg:province":"Surrey",
    "sg:tags":[
        "engineer",
        "electrician",
        "contractor"
    ],
    "wof:name":"J H Miles",
    "wof:placetype":"venue"
},
  "geometry": {"coordinates":[-0.5094140172,51.1421966553],"type":"Point"}
}