{
  "type": "Feature",
  "properties": {
    "addr:full":"45 Old Chester Road, Tranmere Birkenhead Merseyside CH41 9HQ",
    "addr:housenumber":"45",
    "addr:postcode":"ch41 9hq",
    "addr:street":"Old Chester Road",
    "iso:country":"GB",
    "sg:address":"45 Old Chester Road, Tranmere",
    "sg:city":"Birkenhead",
    "sg:classifiers":[
        {
            "category":"Retail",
            "subcategory":"Auto Repair",
            "type":"Services"
        }
    ],
    "sg:postcode":"CH41 9HQ",
    "sg:province":"Merseyside",
    "sg:tags":[
        "modification",
        "garage"
    ],
    "wof:name":"John Pimley",
    "wof:placetype":"venue"
},
  "geometry": {"coordinates":[-3.0169289112,53.3824005127],"type":"Point"}
}