{
  "type": "Feature",
  "properties": {
    "iso:country":"GB",
    "sg:address":"4 The Grange, High Street",
    "sg:city":"Westerham",
    "sg:classifiers":[
        {
            "category":"Shopping",
            "subcategory":"Antiques",
            "type":"Retail Goods"
        }
    ],
    "sg:postcode":"TN16 1AH",
    "sg:province":"Kent",
    "wof:name":"Speed 9858 Ltd.",
    "wof:placetype":"venue"
},
  "geometry": {"coordinates":[0.071265,51.267075],"type":"Point"}
}