{
  "type": "Feature",
  "properties": {
    "addr:full":"33 Islington Grn Camden Passage, Islington London Greater London N1 8DU",
    "addr:housenumber":"33",
    "addr:postcode":"n1 8du",
    "addr:street":"Islington Grn Camden Passage",
    "iso:country":"GB",
    "sg:address":"33 Islington Grn Camden Passage, Islington",
    "sg:city":"London",
    "sg:classifiers":[
        {
            "category":"Shopping",
            "subcategory":"Comic Books",
            "type":"Retail Goods"
        }
    ],
    "sg:phone":"+44 20 7226 3450",
    "sg:postcode":"N1 8DU",
    "sg:province":"Greater London",
    "sg:tags":[
        "jeweller"
    ],
    "wof:name":"Leolinda Ethnic Jewellery",
    "wof:placetype":"venue"
},
  "geometry": {"coordinates":[-0.1036389992,51.5356254578],"type":"Point"}
}