{
  "type": "Feature",
  "properties": {
    "addr:full":"9 Thurlow Street Bedford Bedfordshire MK40 1LR",
    "addr:housenumber":"9",
    "addr:postcode":"mk40 1lr",
    "addr:street":"Thurlow Street",
    "iso:country":"GB",
    "sg:address":"9 Thurlow Street",
    "sg:city":"Bedford",
    "sg:classifiers":[
        {
            "category":"Professional",
            "subcategory":"Employment Agencies",
            "type":"Services"
        }
    ],
    "sg:phone":"+44 1234 269111",
    "sg:postcode":"MK40 1LR",
    "sg:province":"Bedfordshire",
    "sg:tags":[
        "consultant"
    ],
    "wof:name":"Select Appointments",
    "wof:placetype":"venue"
},
  "geometry": {"coordinates":[-0.470573,52.137165],"type":"Point"}
}