{
  "type": "Feature",
  "properties": {
    "iso:country":"GB",
    "sg:address":"Heasandford Industrial Estate, Balderstone Lane",
    "sg:city":"Burnley",
    "sg:classifiers":[
        {
            "category":"Shopping",
            "subcategory":"Stationery & Office Supplies",
            "type":"Retail Goods"
        },
        {
            "category":"Professional",
            "subcategory":"Business Services",
            "type":"Services"
        }
    ],
    "sg:phone":"+44 1282 835033",
    "sg:postcode":"BB10 2AL",
    "sg:province":"Lancashire",
    "sg:tags":[
        "box",
        "carton",
        "manufacturer"
    ],
    "wof:name":"Lancashire Board & Paper Co Ltd",
    "wof:placetype":"venue"
},
  "geometry": {"coordinates":[-2.222625,53.805622],"type":"Point"}
}