{
  "type": "Feature",
  "properties": {
    "addr:full":"7 Molesworth St Wadebridge Cornwall PL27 7DA",
    "addr:housenumber":"7",
    "addr:postcode":"pl27 7da",
    "addr:street":"Molesworth St",
    "iso:country":"GB",
    "sg:address":"7 Molesworth St",
    "sg:city":"Wadebridge",
    "sg:classifiers":[
        {
            "category":"Real Estate",
            "subcategory":"Real Estate Agent",
            "type":"Services"
        }
    ],
    "sg:phone":"+44 1208 814055",
    "sg:postcode":"PL27 7DA",
    "sg:province":"Cornwall",
    "wof:name":"Kittows Of Wadebridge",
    "wof:placetype":"venue"
},
  "geometry": {"coordinates":[-4.837634,50.516483],"type":"Point"}
}