{
  "type": "Feature",
  "properties": {
    "addr:full":"88, Taverham Road, Taverham Norwich Norfolk NR8 6SB",
    "addr:housenumber":"88",
    "addr:postcode":"nr8 6sb",
    "addr:street":"Taverham Road;Norwich Norfolk",
    "iso:country":"GB",
    "sg:address":"88, Taverham Road, Taverham",
    "sg:city":"Norwich",
    "sg:classifiers":[
        {
            "category":"Building & Trades",
            "subcategory":"Construction",
            "type":"Services"
        }
    ],
    "sg:phone":"+44 1603 867833",
    "sg:postcode":"NR8 6SB",
    "sg:province":"Norfolk",
    "sg:tags":[
        "builder"
    ],
    "wof:name":"J.L Harmer",
    "wof:placetype":"venue"
},
  "geometry": {"coordinates":[1.212911,52.67461],"type":"Point"}
}