{
  "type": "Feature",
  "properties": {
    "addr:full":"Fire Station, Upper Bridge Street Canterbury Kent CT1 2NH",
    "addr:postcode":"ct1 2nh",
    "addr:street":"Upper Bridge Street",
    "iso:country":"GB",
    "sg:address":"Fire Station, Upper Bridge Street",
    "sg:city":"Canterbury",
    "sg:classifiers":[
        {
            "category":"Professional",
            "subcategory":"Computer Services",
            "type":"Services"
        }
    ],
    "sg:postcode":"CT1 2NH",
    "sg:province":"Kent",
    "sg:tags":[
        "information"
    ],
    "wof:name":"Safety District Offices",
    "wof:placetype":"venue"
},
  "geometry": {"coordinates":[1.083511,51.276615],"type":"Point"}
}