{
  "type": "Feature",
  "properties": {
    "iso:country":"GB",
    "sg:address":"Fifth Floor, Capitol Ho, Russell St",
    "sg:city":"Leeds",
    "sg:classifiers":[
        {
            "category":"Real Estate",
            "subcategory":"Surveying",
            "type":"Services"
        }
    ],
    "sg:phone":"+44 113 243 0624",
    "sg:postcode":"LS1 5SP",
    "sg:province":"West Yorkshire",
    "sg:tags":[
        "surveyor",
        "quantity"
    ],
    "wof:name":"Harris,E C,& Partners",
    "wof:placetype":"venue"
},
  "geometry": {"coordinates":[-1.546587,53.794495],"type":"Point"}
}