{
  "type": "Feature",
  "properties": {
    "addr:full":"Unit 2a, The Reeds Business Centre Reeds Road Frensham, Nr Farnham GU10 3BP",
    "addr:housenumber":"unit 2a",
    "addr:postcode":"gu10 3bp",
    "addr:street":"The Reeds;Reeds Road;Nr",
    "iso:country":"GB",
    "sg:address":"Unit 2a, The Reeds Business Centre Reeds Road",
    "sg:city":"Frensham, Nr Farnham",
    "sg:classifiers":[
        {
            "category":"Professional",
            "subcategory":"Computer Services",
            "type":"Services"
        }
    ],
    "sg:postcode":"GU10 3BP",
    "sg:tags":[
        "backup",
        "facebook",
        "twitter"
    ],
    "sg:website":"http://www.socialsafe.net",
    "wof:name":"SocialSafe",
    "wof:placetype":"venue"
},
  "geometry": {"coordinates":[-0.8212037,51.179195],"type":"Point"}
}