{
  "type": "Feature",
  "properties": {
    "addr:full":"Farrington Place Burnley Lancashire BB11 5TY",
    "addr:postcode":"bb11 5ty",
    "addr:street":"Farrington Place",
    "iso:country":"GB",
    "sg:address":"Farrington Place",
    "sg:city":"Burnley",
    "sg:classifiers":[
        {
            "category":"Home & Garden",
            "subcategory":"Carpets & Floor Coverings",
            "type":"Retail Goods"
        }
    ],
    "sg:phone":"+44 1282 415541",
    "sg:postcode":"BB11 5TY",
    "sg:province":"Lancashire",
    "sg:tags":[
        "rubber",
        "plastic"
    ],
    "wof:name":"Envopak Industrials Ltd",
    "wof:placetype":"venue"
},
  "geometry": {"coordinates":[-2.2742540836,53.7783966064],"type":"Point"}
}