{
  "type": "Feature",
  "properties": {
    "addr:full":"1 Hall La Stourbridge West Midlands DY9 9LL",
    "addr:housenumber":"1",
    "addr:postcode":"dy9 9ll",
    "addr:street":"Hall La Stourbridge West",
    "iso:country":"GB",
    "sg:address":"1 Hall La",
    "sg:city":"Stourbridge",
    "sg:classifiers":[
        {
            "category":"Building & Trades",
            "subcategory":"Pest Control",
            "type":"Services"
        }
    ],
    "sg:phone":"+44 1562 885133",
    "sg:postcode":"DY9 9LL",
    "sg:province":"West Midlands",
    "sg:tags":[
        "woodworm"
    ],
    "wof:name":"City Preservation Ltd",
    "wof:placetype":"venue"
},
  "geometry": {"coordinates":[-2.125624,52.426723],"type":"Point"}
}