{
  "type": "Feature",
  "properties": {
    "iso:country":"GB",
    "sg:address":"29 Church St, Conisbrough",
    "sg:city":"Doncaster",
    "sg:classifiers":[
        {
            "category":"Cinema",
            "subcategory":"Movie Rental",
            "type":"Entertainment"
        }
    ],
    "sg:postcode":"DN12 3HP",
    "sg:province":"South Yorkshire",
    "sg:tags":[
        "video",
        "library"
    ],
    "wof:name":"Ashurst,William,",
    "wof:placetype":"venue"
},
  "geometry": {"coordinates":[-1.230085969,53.4832000732],"type":"Point"}
}