{
  "type": "Feature",
  "properties": {
    "addr:full":"514 Bury New Rd, Prestwich Manchester Greater Manchester M25 3AN",
    "addr:housenumber":"514",
    "addr:postcode":"m25 3an",
    "addr:street":"Bury New Rd",
    "iso:country":"GB",
    "sg:address":"514 Bury New Rd, Prestwich",
    "sg:city":"Manchester",
    "sg:classifiers":[
        {
            "category":"Health Services",
            "subcategory":"Nursing And Care Facility",
            "type":"Services"
        }
    ],
    "sg:phone":"+44 161 798 0005",
    "sg:postcode":"M25 3AN",
    "sg:province":"Greater Manchester",
    "sg:tags":[
        "home"
    ],
    "wof:name":"Oak Lodge Residential Home",
    "wof:placetype":"venue"
},
  "geometry": {"coordinates":[-2.2867379189,53.5352058411],"type":"Point"}
}