{
  "type": "Feature",
  "properties": {
    "addr:full":"Unit 4 Atlas Business Centre, Oxgate Lane London Greater London NW2 7HU",
    "addr:housenumber":"unit 4",
    "addr:postcode":"nw2 7hu",
    "addr:street":"Atlas Business;Oxgate Lane",
    "iso:country":"GB",
    "sg:address":"Unit 4 Atlas Business Centre, Oxgate Lane",
    "sg:city":"London",
    "sg:classifiers":[
        {
            "category":"Retail",
            "subcategory":"Auto Repair",
            "type":"Services"
        }
    ],
    "sg:phone":"+44 20 8452 8202",
    "sg:postcode":"NW2 7HU",
    "sg:province":"Greater London",
    "sg:tags":[
        "modification",
        "garage"
    ],
    "wof:name":"V I P Autos",
    "wof:placetype":"venue"
},
  "geometry": {"coordinates":[-0.230959,51.569237],"type":"Point"}
}