{
  "type": "Feature",
  "properties": {
    "addr:full":"25 St Neots Road, Hardwick Cambridge Cambridgeshire CB3 7QH",
    "addr:housenumber":"25",
    "addr:postcode":"cb3 7qh",
    "addr:street":"St Neots Road",
    "iso:country":"GB",
    "sg:address":"25 St Neots Road, Hardwick",
    "sg:city":"Cambridge",
    "sg:classifiers":[
        {
            "category":"Manufacturing",
            "subcategory":"Building Materials",
            "type":"Manufacturing & Wholesale Goods"
        }
    ],
    "sg:phone":"+44 1954 211443",
    "sg:postcode":"CB3 7QH",
    "sg:province":"Cambridgeshire",
    "sg:tags":[
        "merchant",
        "builder"
    ],
    "wof:name":"W T Burden",
    "wof:placetype":"venue"
},
  "geometry": {"coordinates":[0.025939,52.216351],"type":"Point"}
}