{
  "type": "Feature",
  "properties": {
    "addr:full":"61 Regent Street Cambridge Cambridgeshire CB2 1AB",
    "addr:housenumber":"61",
    "addr:postcode":"cb2 1ab",
    "addr:street":"Regent Street",
    "iso:country":"GB",
    "sg:address":"61 Regent Street",
    "sg:city":"Cambridge",
    "sg:classifiers":[
        {
            "category":"Professional",
            "subcategory":"Printing & Photocopies",
            "type":"Services"
        },
        {
            "category":"Government",
            "subcategory":"Post Office",
            "type":"Public Place"
        },
        {
            "category":"Organizations",
            "subcategory":"Professional Association",
            "type":"Services"
        }
    ],
    "sg:phone":"+44 1223 462211",
    "sg:postcode":"CB2 1AB",
    "sg:province":"Cambridgeshire",
    "sg:tags":[
        "soc",
        "research",
        "organisation",
        "institution",
        "photocopier"
    ],
    "wof:name":"Xerox Ltd.",
    "wof:placetype":"venue"
},
  "geometry": {"coordinates":[0.126202,52.200829],"type":"Point"}
}