{
  "type": "Feature",
  "properties": {
    "iso:country":"GB",
    "sg:address":"Newton Stewart Road, Kirkcowan",
    "sg:city":"Newton Stewart",
    "sg:classifiers":[
        {
            "category":"Building & Trades",
            "subcategory":"Construction",
            "type":"Services"
        }
    ],
    "sg:postcode":"DG8 0HA",
    "sg:province":"Dumfries and Galloway",
    "sg:tags":[
        "joiner",
        "carpenter"
    ],
    "wof:name":"John Hanlon",
    "wof:placetype":"venue"
},
  "geometry": {"coordinates":[-4.6083607674,54.9165992737],"type":"Point"}
}