{
  "type": "Feature",
  "properties": {
    "addr:full":"1a Hercules Street London Greater London N7 6AT",
    "addr:housenumber":"1a",
    "addr:postcode":"n7 6at",
    "addr:street":"Hercules Street",
    "iso:country":"GB",
    "sg:address":"1a Hercules Street",
    "sg:city":"London",
    "sg:classifiers":[
        {
            "category":"Arts & Performance",
            "subcategory":"Art Gallery",
            "type":"Entertainment"
        },
        {
            "category":"Shopping",
            "subcategory":"Crafts & Fabrics",
            "type":"Retail Goods"
        }
    ],
    "sg:phone":"+44 20 7281 8870",
    "sg:postcode":"N7 6AT",
    "sg:province":"Greater London",
    "sg:tags":[
        "material",
        "sale",
        "supply"
    ],
    "wof:name":"L Cornelissen & Son Ltd.",
    "wof:placetype":"venue"
},
  "geometry": {"coordinates":[-0.120998,51.559048],"type":"Point"}
}