{
  "type": "Feature",
  "properties": {
    "iso:country":"GB",
    "sg:address":"The Spinney, Old Wood",
    "sg:city":"Lincoln",
    "sg:classifiers":[
        {
            "category":"Professional",
            "subcategory":"Accounting & Tax Preparation",
            "type":"Services"
        }
    ],
    "sg:phone":"+44 1522 696749",
    "sg:postcode":"LN6 5UA",
    "sg:province":"Lincolnshire",
    "sg:tags":[
        "accountant"
    ],
    "wof:name":"D & K Associates",
    "wof:placetype":"venue"
},
  "geometry": {"coordinates":[-0.6343,53.239262],"type":"Point"}
}