{
  "type": "Feature",
  "properties": {
    "addr:full":"Gec Business Park, Blackburn Road Accrington Lancashire BB5 5JW",
    "addr:postcode":"bb5 5jw",
    "addr:street":"Business Park Blackburn Road",
    "iso:country":"GB",
    "sg:address":"Gec Business Park, Blackburn Road",
    "sg:city":"Accrington",
    "sg:classifiers":[
        {
            "category":"Banks & Credit Unions",
            "subcategory":"Financial Services",
            "type":"Services"
        }
    ],
    "sg:phone":"+44 1254 389260",
    "sg:postcode":"BB5 5JW",
    "sg:province":"Lancashire",
    "sg:tags":[
        "adviser"
    ],
    "wof:name":"Mark Jopson Financial Services",
    "wof:placetype":"venue"
},
  "geometry": {"coordinates":[-2.3706440926,53.7553291321],"type":"Point"}
}