{
  "type": "Feature",
  "properties": {
    "iso:country":"GB",
    "sg:address":"88 Baker St",
    "sg:city":"West End",
    "sg:classifiers":[
        {
            "category":"Professional",
            "subcategory":"Management & Consulting",
            "type":"Services"
        }
    ],
    "sg:phone":"+44 171 486 5191",
    "sg:postcode":"W1M 2AX",
    "sg:province":"Hampshire",
    "sg:tags":[
        "consultant",
        "business"
    ],
    "wof:name":"Bdo Hospitality Consulting",
    "wof:placetype":"venue"
},
  "geometry": {"coordinates":[-0.156402,51.520206],"type":"Point"}
}