{
  "type": "Feature",
  "properties": {
    "addr:full":"52 Scholey Road Brighouse West Yorkshire HD6 3EW",
    "addr:housenumber":"52",
    "addr:postcode":"hd6 3ew",
    "addr:street":"Scholey Road",
    "iso:country":"GB",
    "sg:address":"52 Scholey Road",
    "sg:city":"Brighouse",
    "sg:classifiers":[
        {
            "category":"Building & Trades",
            "subcategory":"Construction",
            "type":"Services"
        }
    ],
    "sg:phone":"+44 1484 713522",
    "sg:postcode":"HD6 3EW",
    "sg:province":"West Yorkshire",
    "sg:tags":[
        "decorator",
        "painter"
    ],
    "wof:name":"R & B Decorators",
    "wof:placetype":"venue"
},
  "geometry": {"coordinates":[-1.785671,53.691833],"type":"Point"}
}