{
  "type": "Feature",
  "properties": {
    "iso:country":"GB",
    "sg:address":"Fairhead Farm, Grosmont",
    "sg:city":"Whitby",
    "sg:classifiers":[
        {
            "category":"Home & Garden",
            "subcategory":"Garden Supply",
            "type":"Retail Goods"
        },
        {
            "category":"Farming",
            "subcategory":"Livestock Farm",
            "type":"Manufacturing & Wholesale Goods"
        }
    ],
    "sg:postcode":"YO22 5PN",
    "sg:province":"North Yorkshire",
    "sg:tags":[
        "bulb",
        "grower",
        "others"
    ],
    "wof:name":"William Hodgson & Partners",
    "wof:placetype":"venue"
},
  "geometry": {"coordinates":[-0.725589,54.43594],"type":"Point"}
}