{
  "type": "Feature",
  "properties": {
    "iso:country":"GB",
    "sg:address":"255 Kimberworth Road",
    "sg:city":"Rotherham",
    "sg:classifiers":[
        {
            "category":"Bars & Pubs",
            "type":"Food & Drink"
        }
    ],
    "sg:phone":"+44 1709 551100",
    "sg:postcode":"S61 1HF",
    "sg:province":"South Yorkshire",
    "sg:tags":[
        "pubs",
        "house",
        "inn",
        "public",
        "activity"
    ],
    "wof:name":"The Wilton",
    "wof:placetype":"venue"
},
  "geometry": {"coordinates":[-1.3857120275,53.4331207275],"type":"Point"}
}