{
  "type": "Feature",
  "properties": {
    "iso:country":"GB",
    "sg:address":"High Street, Falkland",
    "sg:city":"Cupar",
    "sg:classifiers":[
        {
            "category":"Travel",
            "subcategory":"Hotels & Motels",
            "type":"Entertainment"
        }
    ],
    "sg:postcode":"KY15 7BU",
    "sg:province":"Fife",
    "wof:name":"George Manzis",
    "wof:placetype":"venue"
},
  "geometry": {"coordinates":[-3.2017700672,56.2522850037],"type":"Point"}
}