{
  "type": "Feature",
  "properties": {
    "addr:full":"Unit 6 Western Clo Leominster Herefordshire HR6 0QD",
    "addr:housenumber":"unit 6",
    "addr:postcode":"hr6 0qd",
    "addr:street":"Western Clo",
    "iso:country":"GB",
    "sg:address":"Unit 6 Western Clo",
    "sg:city":"Leominster",
    "sg:classifiers":[
        {
            "category":"Brewery",
            "type":"Food & Drink"
        }
    ],
    "sg:phone":"+44 1568 611084",
    "sg:postcode":"HR6 0QD",
    "sg:province":"Herefordshire",
    "sg:tags":[
        "brewer"
    ],
    "wof:name":"Marches Ales",
    "wof:placetype":"venue"
},
  "geometry": {"coordinates":[-2.730519,52.220261],"type":"Point"}
}