{
  "type": "Feature",
  "properties": {
    "iso:country":"GB",
    "sg:address":"95 The Straits, Lower Gornal",
    "sg:city":"Dudley",
    "sg:classifiers":[
        {
            "category":"Building & Trades",
            "subcategory":"Construction",
            "type":"Services"
        }
    ],
    "sg:phone":"+44 1902 885813",
    "sg:postcode":"DY3 3AL",
    "sg:province":"Staffordshire",
    "sg:tags":[
        "builder"
    ],
    "wof:name":"R.J Gibbons",
    "wof:placetype":"venue"
},
  "geometry": {"coordinates":[-2.14526,52.523422],"type":"Point"}
}