{
  "type": "Feature",
  "properties": {
    "addr:full":"5 Little Dockray Penrith Cumbria CA11 7HL",
    "addr:housenumber":"5",
    "addr:postcode":"ca11 7hl",
    "addr:street":"Little Dockray",
    "iso:country":"GB",
    "sg:address":"5 Little Dockray",
    "sg:city":"Penrith",
    "sg:classifiers":[
        {
            "category":"Shopping",
            "subcategory":"Gifts & Souvenirs",
            "type":"Retail Goods"
        }
    ],
    "sg:phone":"+44 1768 867299",
    "sg:postcode":"CA11 7HL",
    "sg:province":"Cumbria",
    "sg:tags":[
        "shop"
    ],
    "wof:name":"Lion Gallery",
    "wof:placetype":"venue"
},
  "geometry": {"coordinates":[-2.753118,54.664047],"type":"Point"}
}