{
  "type": "Feature",
  "properties": {
    "addr:full":"D50-52 Fruit & Vegetable Market, New Covent Garden London Greater London SW8 5HH",
    "addr:postcode":"sw8 5hh",
    "addr:street":"New",
    "iso:country":"GB",
    "sg:address":"D50-52 Fruit & Vegetable Market, New Covent Garden",
    "sg:city":"London",
    "sg:classifiers":[
        {
            "category":"Wholesale",
            "subcategory":"Fruits & Vegetables",
            "type":"Manufacturing & Wholesale Goods"
        }
    ],
    "sg:phone":"+44 20 7720 7284",
    "sg:postcode":"SW8 5HH",
    "sg:province":"Greater London",
    "wof:name":"S Thorogood & Sons (Covent Garden) Ltd.",
    "wof:placetype":"venue"
},
  "geometry": {"coordinates":[-0.1372099966,51.4774284363],"type":"Point"}
}