{
  "type": "Feature",
  "properties": {
    "iso:country":"GB",
    "sg:address":"28-30 Longacre Road",
    "sg:city":"Carmarthen",
    "sg:classifiers":[
        {
            "category":"Social Services",
            "subcategory":"Retirement Home",
            "type":"Services"
        }
    ],
    "sg:phone":"+44 1267 236504",
    "sg:postcode":"SA31 1HL",
    "sg:province":"Carmarthenshire",
    "sg:tags":[
        "residential",
        "care"
    ],
    "wof:name":"Erwhir Residential Home",
    "wof:placetype":"venue"
},
  "geometry": {"coordinates":[-4.3055992126,51.8619613647],"type":"Point"}
}