{
  "type": "Feature",
  "properties": {
    "iso:country":"GB",
    "sg:address":"7 Llanthony Road",
    "sg:city":"Gloucester",
    "sg:classifiers":[
        {
            "category":"Home & Garden",
            "subcategory":"Hardware",
            "type":"Retail Goods"
        }
    ],
    "sg:phone":"+44 1452 525800",
    "sg:postcode":"GL2 5QT",
    "sg:province":"Gloucestershire",
    "sg:tags":[
        "device",
        "fixing",
        "fastener",
        "nuts",
        "bolt"
    ],
    "wof:name":"Allcap Ltd.",
    "wof:placetype":"venue"
},
  "geometry": {"coordinates":[-2.252769,51.861271],"type":"Point"}
}