{
  "type": "Feature",
  "properties": {
    "iso:country":"GB",
    "sg:address":"75 Trelowarren Street",
    "sg:city":"Camborne",
    "sg:classifiers":[
        {
            "category":"Manufacturing",
            "subcategory":"Buildings",
            "type":"Manufacturing & Wholesale Goods"
        }
    ],
    "sg:phone":"+44 1209 612738",
    "sg:postcode":"TR14 8AL",
    "sg:province":"Cornwall",
    "sg:tags":[
        "mobile",
        "home"
    ],
    "wof:name":"Tremarle Home Park",
    "wof:placetype":"venue"
},
  "geometry": {"coordinates":[-5.296113,50.214561],"type":"Point"}
}