{
  "type": "Feature",
  "properties": {
    "addr:full":"Unit 24, Station Road Workshops, Station Road Bristol City of Bristol BS15 4PJ",
    "addr:housenumber":"unit 24",
    "addr:postcode":"bs15 4pj",
    "addr:street":"Station Road;Station Road",
    "iso:country":"GB",
    "sg:address":"Unit 24, Station Road Workshops, Station Road",
    "sg:city":"Bristol",
    "sg:classifiers":[
        {
            "category":"Professional",
            "subcategory":"Testing Lab",
            "type":"Services"
        }
    ],
    "sg:postcode":"BS15 4PJ",
    "sg:province":"City of Bristol",
    "sg:tags":[
        "inspection",
        "calibration"
    ],
    "wof:name":"Dynamic Calibration Services Ltd.",
    "wof:placetype":"venue"
},
  "geometry": {"coordinates":[-2.497334,51.478504],"type":"Point"}
}