{
  "type": "Feature",
  "properties": {
    "addr:full":"16 Upper Wickham Lane Welling Kent DA16 3HE",
    "addr:housenumber":"16",
    "addr:postcode":"da16 3he",
    "addr:street":"Upper Wickham Lane",
    "iso:country":"GB",
    "sg:address":"16 Upper Wickham Lane",
    "sg:city":"Welling",
    "sg:classifiers":[
        {
            "category":"Restaurant",
            "type":"Food & Drink"
        }
    ],
    "sg:phone":"+44 20 8303 1503",
    "sg:postcode":"DA16 3HE",
    "sg:province":"Kent",
    "wof:name":"Wimpy",
    "wof:placetype":"venue"
},
  "geometry": {"coordinates":[0.1078689992,51.4629211426],"type":"Point"}
}