{
  "type": "Feature",
  "properties": {
    "addr:full":"The Heath, Metheringham Lincoln Lincolnshire LN4 3DJ",
    "addr:postcode":"ln4 3dj",
    "iso:country":"GB",
    "sg:address":"The Heath, Metheringham",
    "sg:city":"Lincoln",
    "sg:classifiers":[
        {
            "category":"Transit Center",
            "subcategory":"Passenger",
            "type":"Transportation"
        }
    ],
    "sg:phone":"+44 1526 320950",
    "sg:postcode":"LN4 3DJ",
    "sg:province":"Lincolnshire",
    "sg:tags":[
        "boarding",
        "kennel",
        "catteries"
    ],
    "wof:name":"Heath Farm Boarding Kennels",
    "wof:placetype":"venue"
},
  "geometry": {"coordinates":[-0.4050700068,53.1418952942],"type":"Point"}
}