{
  "type": "Feature",
  "properties": {
    "iso:country":"GB",
    "sg:address":"Top Floor Flat, 193 Haydons Rd, Wimbledon",
    "sg:city":"Wimbledon",
    "sg:classifiers":[
        {
            "category":"Health Services",
            "subcategory":"Health Practitioner",
            "type":"Services"
        }
    ],
    "sg:phone":"+44 20 8540 5920",
    "sg:postcode":"SW19 8UA",
    "sg:province":"Greater London",
    "sg:tags":[
        "osteopath"
    ],
    "wof:name":"Adrian Dilworth BSc IIST",
    "wof:placetype":"venue"
},
  "geometry": {"coordinates":[-0.2070239931,51.4209976196],"type":"Point"}
}