{
  "type": "Feature",
  "properties": {
    "iso:country":"GB",
    "sg:address":"Alberton Ho, St. Marys Parsonage",
    "sg:city":"Manchester",
    "sg:classifiers":[
        {
            "category":"Professional",
            "subcategory":"Engineering",
            "type":"Services"
        }
    ],
    "sg:phone":"+44 161 833 4800",
    "sg:postcode":"M3 2WJ",
    "sg:province":"Greater Manchester",
    "sg:tags":[
        "consulting",
        "engineer"
    ],
    "wof:name":"Earthscience Ltd",
    "wof:placetype":"venue"
},
  "geometry": {"coordinates":[-2.248809,53.479622],"type":"Point"}
}