{
  "type": "Feature",
  "properties": {
    "addr:full":"High Road Woodford Green Essex IG8 9HQ",
    "addr:postcode":"ig8 9hq",
    "addr:street":"High Road",
    "iso:country":"GB",
    "sg:address":"High Road",
    "sg:city":"Woodford Green",
    "sg:classifiers":[
        {
            "category":"Bars & Pubs",
            "type":"Food & Drink"
        }
    ],
    "sg:phone":"+44 20 8504 2734",
    "sg:postcode":"IG8 9HQ",
    "sg:province":"Essex",
    "sg:tags":[
        "pubs",
        "inn"
    ],
    "wof:name":"The Cricketers Public Ho",
    "wof:placetype":"venue"
},
  "geometry": {"coordinates":[0.02004,51.607361],"type":"Point"}
}