{
  "type": "Feature",
  "properties": {
    "addr:full":"Regent Ho, 16b Rugby Rd Hinckley Leicestershire LE10 0QD",
    "addr:housenumber":"16b",
    "addr:postcode":"le10 0qd",
    "addr:street":"Rugby Rd",
    "iso:country":"GB",
    "sg:address":"Regent Ho, 16b Rugby Rd",
    "sg:city":"Hinckley",
    "sg:classifiers":[
        {
            "category":"Organizations",
            "subcategory":"Non-profit Organization",
            "type":"Services"
        }
    ],
    "sg:phone":"+44 1455 891878",
    "sg:postcode":"LE10 0QD",
    "sg:province":"Leicestershire",
    "sg:tags":[
        "organisation",
        "voluntary",
        "charity"
    ],
    "wof:name":"Carers Helpline",
    "wof:placetype":"venue"
},
  "geometry": {"coordinates":[-1.372754,52.542439],"type":"Point"}
}