{
  "type": "Feature",
  "properties": {
    "iso:country":"GB",
    "sg:address":"The Counting House, High Street, Minchinhampton",
    "sg:city":"Stroud",
    "sg:classifiers":[
        {
            "category":"Professional",
            "subcategory":"Engineering",
            "type":"Services"
        }
    ],
    "sg:postcode":"GL6 9BN",
    "sg:province":"Gloucestershire",
    "wof:name":"Benson-raine Jig & Fixture Ltd",
    "wof:placetype":"venue"
},
  "geometry": {"coordinates":[-2.1888189316,51.7051315308],"type":"Point"}
}