{
  "type": "Feature",
  "properties": {
    "addr:full":"1 Kiln Ground Hemel Hempstead Hertfordshire HP3 8EZ",
    "addr:housenumber":"1",
    "addr:postcode":"hp3 8ez",
    "addr:street":"Kiln Ground Hemel Hempstead",
    "iso:country":"GB",
    "sg:address":"1 Kiln Ground",
    "sg:city":"Hemel Hempstead",
    "sg:classifiers":[
        {
            "category":"Professional",
            "subcategory":"Printing & Photocopies",
            "type":"Services"
        }
    ],
    "sg:postcode":"HP3 8EZ",
    "sg:province":"Hertfordshire",
    "sg:tags":[
        "embroiderer"
    ],
    "wof:name":"Toprani,M,",
    "wof:placetype":"venue"
},
  "geometry": {"coordinates":[-0.445479,51.744492],"type":"Point"}
}