{
  "type": "Feature",
  "properties": {
    "addr:full":"7 The Haven North Shields Tyne and Wear NE29 6YH",
    "addr:housenumber":"7",
    "addr:postcode":"ne29 6yh",
    "addr:street":"The Haven",
    "iso:country":"GB",
    "sg:address":"7 The Haven",
    "sg:city":"North Shields",
    "sg:classifiers":[
        {
            "category":"Professional",
            "subcategory":"Engineering",
            "type":"Services"
        },
        {
            "category":"Real Estate",
            "subcategory":"Architect",
            "type":"Services"
        }
    ],
    "sg:phone":"+44 191 258 6412",
    "sg:postcode":"NE29 6YH",
    "sg:province":"Tyne and Wear",
    "sg:tags":[
        "industrial",
        "engineer"
    ],
    "wof:name":"Cavan Air Engineering (North East) Ltd.",
    "wof:placetype":"venue"
},
  "geometry": {"coordinates":[-1.452137,54.99741],"type":"Point"}
}