{
  "type": "Feature",
  "properties": {
    "addr:full":"Unit 15 Grand Union Centre, Kensal Rd London Greater London W10 5AS",
    "addr:housenumber":"unit 15",
    "addr:postcode":"w10 5as",
    "addr:street":"Grand Union;Kensal Rd",
    "iso:country":"GB",
    "sg:address":"Unit 15 Grand Union Centre, Kensal Rd",
    "sg:city":"London",
    "sg:classifiers":[
        {
            "category":"Food & Beverages",
            "subcategory":"Bakery",
            "type":"Retail Goods"
        }
    ],
    "sg:postcode":"W10 5AS",
    "sg:province":"Greater London",
    "sg:tags":[
        "confectionery"
    ],
    "wof:name":"Bourne Street Brownies",
    "wof:placetype":"venue"
},
  "geometry": {"coordinates":[-0.2140000015,51.5255203247],"type":"Point"}
}