{
  "type": "Feature",
  "properties": {
    "addr:full":"6 Lodge Place, Thunder Lane Norwich Norfolk NR7 0LA",
    "addr:housenumber":"6",
    "addr:postcode":"nr7 0la",
    "addr:street":"Lodge Place Thunder Lane",
    "iso:country":"GB",
    "sg:address":"6 Lodge Place, Thunder Lane",
    "sg:city":"Norwich",
    "sg:classifiers":[
        {
            "category":"Professional",
            "subcategory":"Accounting & Tax Preparation",
            "type":"Services"
        }
    ],
    "sg:postcode":"NR7 0LA",
    "sg:province":"Norfolk",
    "sg:tags":[
        "accountant"
    ],
    "wof:name":"David Shawyer",
    "wof:placetype":"venue"
},
  "geometry": {"coordinates":[1.3429510593,52.631477356],"type":"Point"}
}