{
  "type": "Feature",
  "properties": {
    "addr:full":"Kinnerton Road, Dodleston Chester Cheshire CH4 9LP",
    "addr:postcode":"ch4 9lp",
    "addr:street":"Kinnerton Road",
    "iso:country":"GB",
    "sg:address":"Kinnerton Road, Dodleston",
    "sg:city":"Chester",
    "sg:classifiers":[
        {
            "category":"Farming",
            "subcategory":"Livestock Farm",
            "type":"Manufacturing & Wholesale Goods"
        }
    ],
    "sg:phone":"+44 1244 660260",
    "sg:postcode":"CH4 9LP",
    "sg:province":"Cheshire",
    "sg:tags":[
        "others"
    ],
    "wof:name":"Pierces",
    "wof:placetype":"venue"
},
  "geometry": {"coordinates":[-2.955361,53.144348],"type":"Point"}
}