{
  "type": "Feature",
  "properties": {
    "addr:full":"6 York Clo Newbury Berkshire RG14 7NL",
    "addr:housenumber":"6",
    "addr:postcode":"rg14 7nl",
    "addr:street":"York Clo",
    "iso:country":"GB",
    "sg:address":"6 York Clo",
    "sg:city":"Newbury",
    "sg:classifiers":[
        {
            "category":"Shopping",
            "subcategory":"Antiques",
            "type":"Retail Goods"
        }
    ],
    "sg:phone":"+44 1635 44667",
    "sg:postcode":"RG14 7NL",
    "sg:province":"Berkshire",
    "wof:name":"J Bell",
    "wof:placetype":"venue"
},
  "geometry": {"coordinates":[-1.316646,51.395626],"type":"Point"}
}