{
  "type": "Feature",
  "properties": {
    "addr:full":"Bradford Road, White Cross Leeds West Yorkshire LS20 8NJ",
    "addr:postcode":"ls20 8nj",
    "addr:street":"Bradford Road White",
    "iso:country":"GB",
    "sg:address":"Bradford Road, White Cross",
    "sg:city":"Leeds",
    "sg:classifiers":[
        {
            "category":"Home & Garden",
            "subcategory":"Hardware",
            "type":"Retail Goods"
        }
    ],
    "sg:phone":"+44 1943 879631",
    "sg:postcode":"LS20 8NJ",
    "sg:province":"West Yorkshire",
    "sg:tags":[
        "centre",
        "improvement"
    ],
    "wof:name":"Magnet Kitchens",
    "wof:placetype":"venue"
},
  "geometry": {"coordinates":[-1.727094,53.879715],"type":"Point"}
}