{
  "type": "Feature",
  "properties": {
    "addr:full":"16 Blakebrook Kidderminster Staffordshire DY11 6AP",
    "addr:housenumber":"16",
    "addr:postcode":"dy11 6ap",
    "addr:street":"Blakebrook",
    "iso:country":"GB",
    "sg:address":"16 Blakebrook",
    "sg:city":"Kidderminster",
    "sg:classifiers":[
        {
            "category":"Health Services",
            "subcategory":"Nursing And Care Facility",
            "type":"Services"
        }
    ],
    "sg:phone":"+44 1562 823063",
    "sg:postcode":"DY11 6AP",
    "sg:province":"Staffordshire",
    "sg:tags":[
        "home"
    ],
    "wof:name":"Brookdale Nursing Home Ltd",
    "wof:placetype":"venue"
},
  "geometry": {"coordinates":[-2.264775,52.389027],"type":"Point"}
}