{
  "type": "Feature",
  "properties": {
    "iso:country":"GB",
    "sg:address":"51 Staplehurst Road",
    "sg:city":"Gillingham",
    "sg:classifiers":[
        {
            "category":"Professional",
            "subcategory":"Detective & Security Services",
            "type":"Services"
        }
    ],
    "sg:phone":"+44 1634 376253",
    "sg:postcode":"ME8 6LF",
    "sg:province":"Kent",
    "sg:tags":[
        "alarm",
        "burglar",
        "system"
    ],
    "wof:name":"P J Services",
    "wof:placetype":"venue"
},
  "geometry": {"coordinates":[0.5806519985,51.3749923706],"type":"Point"}
}