{
  "type": "Feature",
  "properties": {
    "iso:country":"GB",
    "sg:address":"54 Island Street",
    "sg:city":"Galashiels",
    "sg:classifiers":[
        {
            "category":"Real Estate",
            "subcategory":"Architect",
            "type":"Services"
        }
    ],
    "sg:phone":"+44 1896 752760",
    "sg:postcode":"TD1 1NU",
    "sg:province":"Scottish Borders",
    "wof:name":"Aitken & Turnbull",
    "wof:placetype":"venue"
},
  "geometry": {"coordinates":[-2.813535,55.619694],"type":"Point"}
}