{
  "type": "Feature",
  "properties": {
    "addr:full":"34 Heatherdown Road Ferndown Dorset BH22 0BY",
    "addr:housenumber":"34",
    "addr:postcode":"bh22 0by",
    "addr:street":"Heatherdown Road",
    "iso:country":"GB",
    "sg:address":"34 Heatherdown Road",
    "sg:city":"Ferndown",
    "sg:classifiers":[
        {
            "category":"Building & Trades",
            "subcategory":"Construction",
            "type":"Services"
        }
    ],
    "sg:phone":"+44 1202 894237",
    "sg:postcode":"BH22 0BY",
    "sg:province":"Dorset",
    "sg:tags":[
        "builder"
    ],
    "wof:name":"West Moors Upvc Services",
    "wof:placetype":"venue"
},
  "geometry": {"coordinates":[-1.8693720102,50.8199043274],"type":"Point"}
}