{
  "type": "Feature",
  "properties": {
    "iso:country":"GB",
    "sg:address":"Bali Hai, Prospect Place",
    "sg:city":"Swindon",
    "sg:classifiers":[
        {
            "category":"Education",
            "subcategory":"Dance Studio",
            "type":"Public Place"
        }
    ],
    "sg:phone":"+44 1793 527275",
    "sg:postcode":"SN1 3LQ",
    "sg:province":"Wiltshire",
    "sg:tags":[
        "school",
        "dancing"
    ],
    "wof:name":"Judith Hockaday School of Dancing",
    "wof:placetype":"venue"
},
  "geometry": {"coordinates":[-1.779624,51.554966],"type":"Point"}
}