{
  "type": "Feature",
  "properties": {
    "iso:country":"GB",
    "sg:address":"18 Cross Road",
    "sg:city":"Tadworth",
    "sg:classifiers":[
        {
            "category":"Food & Beverages",
            "subcategory":"Fruits & Vegetables",
            "type":"Retail Goods"
        }
    ],
    "sg:phone":"+44 1737 812135",
    "sg:postcode":"KT20 5SR",
    "sg:province":"Surrey",
    "sg:tags":[
        "greengrocer"
    ],
    "wof:name":"Gordon Newman Fruiters",
    "wof:placetype":"venue"
},
  "geometry": {"coordinates":[-0.235226,51.291134],"type":"Point"}
}