{
  "type": "Feature",
  "properties": {
    "iso:country":"GB",
    "sg:address":"16 Woodview, Cuffley",
    "sg:city":"Potters Bar",
    "sg:classifiers":[
        {
            "category":"Coffee & Tea",
            "type":"Food & Drink"
        }
    ],
    "sg:phone":"+44 1707 873814",
    "sg:postcode":"EN6 4RE",
    "sg:province":"Greater London",
    "wof:name":"Courtenay's Tea & Coffee",
    "wof:placetype":"venue"
},
  "geometry": {"coordinates":[-0.1784240007,51.6930122375],"type":"Point"}
}