{
  "type": "Feature",
  "properties": {
    "addr:full":"19 Gages Close, Kingswood Bristol City of Bristol BS15 9UH",
    "addr:housenumber":"19",
    "addr:postcode":"bs15 9uh",
    "addr:street":"Gages Close",
    "iso:country":"GB",
    "sg:address":"19 Gages Close, Kingswood",
    "sg:city":"Bristol",
    "sg:classifiers":[
        {
            "category":"Health Services",
            "subcategory":"Podiatrist",
            "type":"Services"
        }
    ],
    "sg:phone":"+44 117 967 2216",
    "sg:postcode":"BS15 9UH",
    "sg:province":"City of Bristol",
    "sg:tags":[
        "podiatrists",
        "chiropodist"
    ],
    "wof:name":"A 1 Chiropody Services",
    "wof:placetype":"venue"
},
  "geometry": {"coordinates":[-2.4934489727,51.4583511353],"type":"Point"}
}