{
  "type": "Feature",
  "properties": {
    "addr:full":"3 Keighley Rd Skipton Lancashire BD23 2LP",
    "addr:housenumber":"3",
    "addr:postcode":"bd23 2lp",
    "addr:street":"Keighley Rd",
    "iso:country":"GB",
    "sg:address":"3 Keighley Rd",
    "sg:city":"Skipton",
    "sg:classifiers":[
        {
            "category":"Food & Beverages",
            "subcategory":"Candy",
            "type":"Retail Goods"
        }
    ],
    "sg:phone":"+44 1756 700143",
    "sg:postcode":"BD23 2LP",
    "sg:province":"Lancashire",
    "sg:tags":[
        "confectioner"
    ],
    "wof:name":"J Wild Confectioners Ltd",
    "wof:placetype":"venue"
},
  "geometry": {"coordinates":[-2.012504,53.939087],"type":"Point"}
}