{
  "type": "Feature",
  "properties": {
    "iso:country":"GB",
    "sg:address":"92 Station Rd",
    "sg:city":"Ilminster",
    "sg:classifiers":[
        {
            "category":"Autos & Motor Vehicles",
            "subcategory":"Auto Supplies",
            "type":"Retail Goods"
        }
    ],
    "sg:phone":"+44 1460 55773",
    "sg:postcode":"TA19 9BQ",
    "sg:province":"Somerset",
    "sg:tags":[
        "tyre"
    ],
    "wof:name":"J. Brake & Son Ltd",
    "wof:placetype":"venue"
},
  "geometry": {"coordinates":[-2.9234991074,50.9301185608],"type":"Point"}
}