{
  "type": "Feature",
  "properties": {
    "addr:full":"Newtown Industrial Estate, Llantwit Fadre Pontypridd Rhondda, Cynon, Taff CF38 2EE",
    "addr:postcode":"cf38 2ee",
    "addr:street":"Pontypridd;Cynon Taff",
    "iso:country":"GB",
    "sg:address":"Newtown Industrial Estate, Llantwit Fadre",
    "sg:city":"Pontypridd",
    "sg:classifiers":[
        {
            "category":"Bus Charters",
            "type":"Transportation"
        }
    ],
    "sg:postcode":"CF38 2EE",
    "sg:province":"Rhondda, Cynon, Taff",
    "sg:tags":[
        "hire",
        "coach"
    ],
    "wof:name":"Edwards Coaches",
    "wof:placetype":"venue"
},
  "geometry": {"coordinates":[-3.3301808834,51.5597877502],"type":"Point"}
}