{
  "type": "Feature",
  "properties": {
    "addr:full":"45 Trinity Road Wirral Merseyside CH47 2BS",
    "addr:housenumber":"45",
    "addr:postcode":"ch47 2bs",
    "addr:street":"Trinity Road",
    "iso:country":"GB",
    "sg:address":"45 Trinity Road",
    "sg:city":"Wirral",
    "sg:classifiers":[
        {
            "category":"Bus Charters",
            "type":"Transportation"
        }
    ],
    "sg:postcode":"CH47 2BS",
    "sg:province":"Merseyside",
    "sg:tags":[
        "mini",
        "hire",
        "leasing"
    ],
    "wof:name":"J B Travel",
    "wof:placetype":"venue"
},
  "geometry": {"coordinates":[-3.1785030365,53.3962554932],"type":"Point"}
}