{
  "type": "Feature",
  "properties": {
    "addr:full":"Grey Road Altrincham Cheshire WA14 4BU",
    "addr:postcode":"wa14 4bu",
    "addr:street":"Grey Road",
    "iso:country":"GB",
    "sg:address":"Grey Road",
    "sg:city":"Altrincham",
    "sg:classifiers":[
        {
            "category":"Social Services",
            "subcategory":"Retirement Home",
            "type":"Services"
        }
    ],
    "sg:phone":"+44 161 928 2784",
    "sg:postcode":"WA14 4BU",
    "sg:province":"Cheshire",
    "sg:tags":[
        "residential",
        "care"
    ],
    "wof:name":"Kilpeacon House",
    "wof:placetype":"venue"
},
  "geometry": {"coordinates":[-2.3623640537,53.3893737793],"type":"Point"}
}