{
  "type": "Feature",
  "properties": {
    "addr:full":"Hobcroft House Farm, Hobcraft La, Mobber Knutsford Cheshire WA16 7QR",
    "addr:postcode":"wa16 7qr",
    "iso:country":"GB",
    "sg:address":"Hobcroft House Farm, Hobcraft La, Mobber",
    "sg:city":"Knutsford",
    "sg:classifiers":[
        {
            "category":"Insurance",
            "subcategory":"Insurance Agent",
            "type":"Services"
        },
        {
            "category":"Insurance",
            "subcategory":"Life Insurance",
            "type":"Services"
        }
    ],
    "sg:postcode":"WA16 7QR",
    "sg:province":"Cheshire",
    "sg:tags":[
        "broker",
        "assurance"
    ],
    "wof:name":"Monarch Assurance Bureau Ltd",
    "wof:placetype":"venue"
},
  "geometry": {"coordinates":[-2.376240015,53.3042030334],"type":"Point"}
}