{
  "type": "Feature",
  "properties": {
    "addr:full":"Stoney Lane, Rainhill Prescot Cheshire L35 9ND",
    "addr:postcode":"l35 9nd",
    "addr:street":"Stoney Lane",
    "iso:country":"GB",
    "sg:address":"Stoney Lane, Rainhill",
    "sg:city":"Prescot",
    "sg:classifiers":[
        {
            "category":"Professional",
            "subcategory":"Engineering",
            "type":"Services"
        }
    ],
    "sg:postcode":"L35 9ND",
    "sg:province":"Cheshire",
    "wof:name":"Mc Carthy & Jones Engineers Ltd.",
    "wof:placetype":"venue"
},
  "geometry": {"coordinates":[-2.782131,53.418667],"type":"Point"}
}