{
  "type": "Feature",
  "properties": {
    "iso:country":"GB",
    "sg:address":"Mackintosh Road, Rackheath Industrial Estate",
    "sg:city":"Norwich",
    "sg:classifiers":[
        {
            "category":"Social Services",
            "type":"Services"
        }
    ],
    "sg:phone":"+44 1603 720246",
    "sg:postcode":"NR13 6LH",
    "sg:province":"Norfolk",
    "sg:tags":[
        "disability"
    ],
    "wof:name":"Sto-eazy",
    "wof:placetype":"venue"
},
  "geometry": {"coordinates":[1.2949,52.622494],"type":"Point"}
}