{
  "type": "Feature",
  "properties": {
    "addr:full":"47-49 Stubbington Av Portsmouth Hampshire PO2 0HX",
    "addr:housenumber":"47-49",
    "addr:postcode":"po2 0hx",
    "addr:street":"Stubbington Av Portsmouth",
    "iso:country":"GB",
    "sg:address":"47-49 Stubbington Av",
    "sg:city":"Portsmouth",
    "sg:classifiers":[
        {
            "category":"Social Services",
            "subcategory":"Retirement Home",
            "type":"Services"
        }
    ],
    "sg:phone":"+44 23 9264 2064",
    "sg:postcode":"PO2 0HX",
    "sg:province":"Hampshire",
    "sg:tags":[
        "care"
    ],
    "wof:name":"Meadowhouse Carers",
    "wof:placetype":"venue"
},
  "geometry": {"coordinates":[-1.0755560398,50.8170928955],"type":"Point"}
}