{
  "type": "Feature",
  "properties": {
    "addr:full":"Watery Lane, Newchurch Sandown Isle of Wight PO36 0LX",
    "addr:postcode":"po36 0lx",
    "addr:street":"Watery Lane",
    "iso:country":"GB",
    "sg:address":"Watery Lane, Newchurch",
    "sg:city":"Sandown",
    "sg:classifiers":[
        {
            "category":"Home & Garden",
            "subcategory":"Garden Supply",
            "type":"Retail Goods"
        }
    ],
    "sg:phone":"+44 1983 865292",
    "sg:postcode":"PO36 0LX",
    "sg:province":"Isle of Wight",
    "sg:tags":[
        "nursery",
        "centre"
    ],
    "wof:name":"Longlands Nursery",
    "wof:placetype":"venue"
},
  "geometry": {"coordinates":[-1.207279,50.665569],"type":"Point"}
}