{
  "type": "Feature",
  "properties": {
    "addr:full":"Building Mw 02, M O D, Mount Wise Plymouth Devon PL1 4JH",
    "addr:postcode":"pl1 4jh",
    "addr:street":"M;D Mount",
    "iso:country":"GB",
    "sg:address":"Building Mw 02, M O D, Mount Wise",
    "sg:city":"Plymouth",
    "sg:classifiers":[
        {
            "category":"Government",
            "subcategory":"Office",
            "type":"Public Place"
        }
    ],
    "sg:phone":"+44 1752 501081",
    "sg:postcode":"PL1 4JH",
    "sg:province":"Devon",
    "sg:tags":[
        "central"
    ],
    "wof:name":"Defence Estate Organisation",
    "wof:placetype":"venue"
},
  "geometry": {"coordinates":[-4.1681900024,50.3665008545],"type":"Point"}
}