{
  "type": "Feature",
  "properties": {
    "iso:country":"GB",
    "sg:address":"89 Seymour Road, Upper Easton",
    "sg:city":"Bristol",
    "sg:classifiers":[
        {
            "category":"Bars & Pubs",
            "type":"Food & Drink"
        }
    ],
    "sg:phone":"+44 117 939 3324",
    "sg:postcode":"BS5 0UW",
    "sg:province":"City of Bristol",
    "sg:tags":[
        "pubs",
        "inn"
    ],
    "wof:name":"Duke of Cambridge",
    "wof:placetype":"venue"
},
  "geometry": {"coordinates":[-2.6910049915,51.4783248901],"type":"Point"}
}