{
  "type": "Feature",
  "properties": {
    "addr:full":"Hightrees, Robinsons Hill Derby Derbyshire DE73 1DJ",
    "addr:postcode":"de73 1dj",
    "iso:country":"GB",
    "sg:address":"Hightrees, Robinsons Hill",
    "sg:city":"Derby",
    "sg:classifiers":[
        {
            "category":"Building & Trades",
            "subcategory":"Pest Control",
            "type":"Services"
        }
    ],
    "sg:phone":"+44 1332 865522",
    "sg:postcode":"DE73 1DJ",
    "sg:province":"Derbyshire",
    "sg:tags":[
        "vermin"
    ],
    "wof:name":"Dolphin Environmental Services",
    "wof:placetype":"venue"
},
  "geometry": {"coordinates":[-1.439558,52.819397],"type":"Point"}
}