{
  "type": "Feature",
  "properties": {
    "iso:country":"GB",
    "sg:address":"73 Weldbank La",
    "sg:city":"Chorley",
    "sg:classifiers":[
        {
            "category":"Bars & Pubs",
            "type":"Food & Drink"
        }
    ],
    "sg:phone":"+44 1257 275988",
    "sg:postcode":"PR7 3NN",
    "sg:province":"Lancashire",
    "sg:tags":[
        "pubs",
        "inn"
    ],
    "wof:name":"Pub Master Brewery",
    "wof:placetype":"venue"
},
  "geometry": {"coordinates":[-2.6333520412,53.6407661438],"type":"Point"}
}