{
  "type": "Feature",
  "properties": {
    "iso:country":"GB",
    "sg:address":"346-348 Chiswick High Road, Chiswick",
    "sg:city":"London",
    "sg:classifiers":[
        {
            "category":"Home & Garden",
            "subcategory":"Household Appliances",
            "type":"Retail Goods"
        }
    ],
    "sg:phone":"+44 20 8747 1443",
    "sg:postcode":"W4 5TA",
    "sg:province":"Greater London",
    "sg:tags":[
        "electrical",
        "domestic"
    ],
    "wof:name":"Dixons",
    "wof:placetype":"venue"
},
  "geometry": {"coordinates":[-0.262618,51.492344],"type":"Point"}
}