{
  "type": "Feature",
  "properties": {
    "iso:country":"GB",
    "sg:address":"69 Manchester Road, Tythvrington",
    "sg:city":"Macclesfield",
    "sg:classifiers":[
        {
            "category":"Home & Garden",
            "subcategory":"Garden Supply",
            "type":"Retail Goods"
        }
    ],
    "sg:postcode":"SK10 2JW",
    "sg:province":"Cheshire",
    "sg:tags":[
        "nursery",
        "centre"
    ],
    "wof:name":"Mousehole Gardens",
    "wof:placetype":"venue"
},
  "geometry": {"coordinates":[-2.12839,53.277718],"type":"Point"}
}