{
  "type": "Feature",
  "properties": {
    "addr:full":"Norwood, Bentley Lane Ormskirk Lancashire L40 3SN",
    "addr:postcode":"l40 3sn",
    "addr:street":"Bentley Lane",
    "iso:country":"GB",
    "sg:address":"Norwood, Bentley Lane",
    "sg:city":"Ormskirk",
    "sg:classifiers":[
        {
            "category":"Retail",
            "subcategory":"Auto Repair",
            "type":"Services"
        }
    ],
    "sg:phone":"+44 1704 822778",
    "sg:postcode":"L40 3SN",
    "sg:province":"Lancashire",
    "sg:tags":[
        "modification",
        "garage"
    ],
    "wof:name":"R G Sutton Motor Engineers",
    "wof:placetype":"venue"
},
  "geometry": {"coordinates":[-2.7593579292,53.6133613586],"type":"Point"}
}