{
  "type": "Feature",
  "properties": {
    "addr:full":"7 The Hurst, Hollywood Birmingham Worcestershire B47 5DU",
    "addr:housenumber":"7",
    "addr:postcode":"b47 5du",
    "addr:street":"The Hurst",
    "iso:country":"GB",
    "sg:address":"7 The Hurst, Hollywood",
    "sg:city":"Birmingham",
    "sg:classifiers":[
        {
            "category":"Home & Garden",
            "subcategory":"Household Appliances",
            "type":"Retail Goods"
        }
    ],
    "sg:phone":"+44 1564 823724",
    "sg:postcode":"B47 5DU",
    "sg:province":"Worcestershire",
    "sg:tags":[
        "electrical"
    ],
    "wof:name":"Harborne",
    "wof:placetype":"venue"
},
  "geometry": {"coordinates":[-1.878513,52.389561],"type":"Point"}
}