{
  "type": "Feature",
  "properties": {
    "iso:country":"GB",
    "sg:address":"Unit 1 John Samuel Building, Hoo Farm Industrial Estate",
    "sg:city":"Kidderminster",
    "sg:classifiers":[
        {
            "category":"Professional",
            "type":"Services"
        },
        {
            "category":"Professional",
            "subcategory":"Testing Lab",
            "type":"Services"
        }
    ],
    "sg:phone":"+44 1562 822924",
    "sg:postcode":"DY11 7RA",
    "sg:province":"Staffordshire",
    "sg:tags":[
        "equipment",
        "inspection",
        "calibration"
    ],
    "wof:name":"U K Calibrations Ltd",
    "wof:placetype":"venue"
},
  "geometry": {"coordinates":[-2.245644,52.367577],"type":"Point"}
}