{
  "type": "Feature",
  "properties": {
    "addr:full":"Edge Grove, Edge Shrewsbury Shropshire SY5 9PY",
    "addr:postcode":"sy5 9py",
    "addr:street":"Edge Grove Edge",
    "iso:country":"GB",
    "sg:address":"Edge Grove, Edge",
    "sg:city":"Shrewsbury",
    "sg:classifiers":[
        {
            "category":"Farming",
            "subcategory":"Livestock Farm",
            "type":"Manufacturing & Wholesale Goods"
        },
        {
            "category":"Farming",
            "subcategory":"Farm",
            "type":"Manufacturing & Wholesale Goods"
        }
    ],
    "sg:phone":"+44 1743 821287",
    "sg:postcode":"SY5 9PY",
    "sg:province":"Shropshire",
    "sg:tags":[
        "mixed",
        "crop",
        "others"
    ],
    "wof:name":"M G Tudor & Partners",
    "wof:placetype":"venue"
},
  "geometry": {"coordinates":[-2.8910501003,52.6742706299],"type":"Point"}
}