{
  "type": "Feature",
  "properties": {
    "addr:full":"West Holme, Campbeltown Road Tarbert Argyll and Bute PA29 6SX",
    "addr:postcode":"pa29 6sx",
    "addr:street":"West Holme Campbeltown Road",
    "iso:country":"GB",
    "sg:address":"West Holme, Campbeltown Road",
    "sg:city":"Tarbert",
    "sg:classifiers":[
        {
            "category":"Building & Trades",
            "subcategory":"Plumbing",
            "type":"Services"
        }
    ],
    "sg:phone":"+44 1880 820238",
    "sg:postcode":"PA29 6SX",
    "sg:province":"Argyll and Bute",
    "sg:tags":[
        "heating"
    ],
    "wof:name":"Alexander J Macsporran",
    "wof:placetype":"venue"
},
  "geometry": {"coordinates":[-5.4165501595,55.8633842468],"type":"Point"}
}