{
  "type": "Feature",
  "properties": {
    "iso:country":"GB",
    "sg:address":"6 The Quadrant",
    "sg:city":"Richmond",
    "sg:classifiers":[
        {
            "category":"Shopping",
            "subcategory":"Thrift Store",
            "type":"Retail Goods"
        }
    ],
    "sg:postcode":"TW9 1BP",
    "sg:province":"Greater London",
    "sg:tags":[
        "shop",
        "charity"
    ],
    "wof:name":"Oxfam",
    "wof:placetype":"venue"
},
  "geometry": {"coordinates":[-0.303097,51.462025],"type":"Point"}
}