{
  "type": "Feature",
  "properties": {
    "addr:full":"15a Cambridge Rd Aldershot Hampshire GU11 3JZ",
    "addr:housenumber":"15a",
    "addr:postcode":"gu11 3jz",
    "addr:street":"Cambridge Rd",
    "iso:country":"GB",
    "sg:address":"15a Cambridge Rd",
    "sg:city":"Aldershot",
    "sg:classifiers":[
        {
            "category":"Health Services",
            "subcategory":"Dentist",
            "type":"Services"
        }
    ],
    "sg:phone":"+44 1252 662225",
    "sg:postcode":"GU11 3JZ",
    "sg:province":"Hampshire",
    "sg:tags":[
        "technician",
        "dental"
    ],
    "wof:name":"Glenloth Dental Ceramics",
    "wof:placetype":"venue"
},
  "geometry": {"coordinates":[-0.773152,51.247864],"type":"Point"}
}