{
  "type": "Feature",
  "properties": {
    "addr:full":"47 Scrooby Road Doncaster South Yorkshire DN11 8JW",
    "addr:housenumber":"47",
    "addr:postcode":"dn11 8jw",
    "addr:street":"Scrooby Road",
    "iso:country":"GB",
    "sg:address":"47 Scrooby Road",
    "sg:city":"Doncaster",
    "sg:classifiers":[
        {
            "category":"Shopping",
            "subcategory":"Clothing, Apparel, & Fashions",
            "type":"Retail Goods"
        }
    ],
    "sg:phone":"+44 1302 752951",
    "sg:postcode":"DN11 8JW",
    "sg:province":"South Yorkshire",
    "sg:tags":[
        "shop"
    ],
    "wof:name":"Amber Fashions",
    "wof:placetype":"venue"
},
  "geometry": {"coordinates":[-1.0639400482,53.4169578552],"type":"Point"}
}