{
  "type": "Feature",
  "properties": {
    "iso:country":"GB",
    "sg:address":"166 Aycliffe Road",
    "sg:city":"Borehamwood",
    "sg:classifiers":[
        {
            "category":"Restaurant",
            "type":"Food & Drink"
        }
    ],
    "sg:phone":"+44 20 8207 2204",
    "sg:postcode":"WD6 4EG",
    "sg:province":"Hertfordshire",
    "sg:tags":[
        "indian"
    ],
    "wof:name":"Borehamwood Tandoori",
    "wof:placetype":"venue"
},
  "geometry": {"coordinates":[-0.283191,51.668282],"type":"Point"}
}