{
  "type": "Feature",
  "properties": {
    "addr:full":"Ashfield House, Ashfield Crescent Ross-on-wye Gloucestershire HR9 5PH",
    "addr:postcode":"hr9 5ph",
    "addr:street":"Ashfield Crescent",
    "iso:country":"GB",
    "sg:address":"Ashfield House, Ashfield Crescent",
    "sg:city":"Ross-on-wye",
    "sg:classifiers":[
        {
            "category":"Health Services",
            "subcategory":"Chiropractor",
            "type":"Services"
        }
    ],
    "sg:postcode":"HR9 5PH",
    "sg:province":"Gloucestershire",
    "wof:name":"Jennifer T Turvey",
    "wof:placetype":"venue"
},
  "geometry": {"coordinates":[-2.5870139599,51.9094238281],"type":"Point"}
}