{
  "type": "Feature",
  "properties": {
    "iso:country":"GB",
    "sg:address":"Hollbrook Common, Northwich Road, Cranage",
    "sg:city":"Knutsford",
    "sg:classifiers":[
        {
            "category":"Building & Trades",
            "subcategory":"Construction",
            "type":"Services"
        }
    ],
    "sg:phone":"+44 1477 532020",
    "sg:postcode":"WA16 9LD",
    "sg:province":"Cheshire",
    "sg:tags":[
        "ceiling",
        "contractor"
    ],
    "wof:name":"Applied Design",
    "wof:placetype":"venue"
},
  "geometry": {"coordinates":[-2.39177,53.230518],"type":"Point"}
}