{
  "type": "Feature",
  "properties": {
    "iso:country":"GB",
    "sg:address":"132 Bute Street",
    "sg:city":"Treorchy",
    "sg:classifiers":[
        {
            "category":"Shopping",
            "subcategory":"Department Store",
            "type":"Retail Goods"
        }
    ],
    "sg:phone":"+44 1443 775242",
    "sg:postcode":"CF42 6BB",
    "sg:province":"Rhondda, Cynon, Taff",
    "wof:name":"Ann Cole",
    "wof:placetype":"venue"
},
  "geometry": {"coordinates":[-3.509177,51.661289],"type":"Point"}
}