{
  "type": "Feature",
  "properties": {
    "iso:country":"GB",
    "sg:address":"Prenteg",
    "sg:city":"Porthmadog",
    "sg:classifiers":[
        {
            "category":"Travel",
            "subcategory":"Hotels & Motels",
            "type":"Entertainment"
        }
    ],
    "sg:postcode":"LL49 9SP",
    "sg:province":"Gwynedd",
    "wof:name":"Warren,Nigel,",
    "wof:placetype":"venue"
},
  "geometry": {"coordinates":[-4.1436491013,52.9306983948],"type":"Point"}
}