{
  "type": "Feature",
  "properties": {
    "addr:full":"823 The Ridge St Leonards-on-sea East Sussex TN37 7PX",
    "addr:housenumber":"823",
    "addr:postcode":"tn37 7px",
    "addr:street":"The Ridge St",
    "iso:country":"GB",
    "sg:address":"823 The Ridge",
    "sg:city":"St Leonards-on-sea",
    "sg:classifiers":[
        {
            "category":"Shopping",
            "subcategory":"Computers & Home Electronics",
            "type":"Retail Goods"
        },
        {
            "category":"Building & Trades",
            "subcategory":"Construction",
            "type":"Services"
        }
    ],
    "sg:phone":"+44 1424 754060",
    "sg:postcode":"TN37 7PX",
    "sg:province":"East Sussex",
    "sg:tags":[
        "supplier",
        "radio",
        "television",
        "erectors",
        "aerial"
    ],
    "wof:name":"East Sussex Aerials Ltd",
    "wof:placetype":"venue"
},
  "geometry": {"coordinates":[0.5554819703,50.8903388977],"type":"Point"}
}