{
  "type": "Feature",
  "properties": {
    "addr:full":"51 Southport Road Chorley Lancashire PR7 1LF",
    "addr:housenumber":"51",
    "addr:postcode":"pr7 1lf",
    "addr:street":"Southport Road",
    "iso:country":"GB",
    "sg:address":"51 Southport Road",
    "sg:city":"Chorley",
    "sg:classifiers":[
        {
            "category":"Building & Trades",
            "subcategory":"Construction",
            "type":"Services"
        }
    ],
    "sg:phone":"+44 1257 263346",
    "sg:postcode":"PR7 1LF",
    "sg:province":"Lancashire",
    "sg:tags":[
        "monumental",
        "mason"
    ],
    "wof:name":"Rawcliffes of Chorley",
    "wof:placetype":"venue"
},
  "geometry": {"coordinates":[-2.643494,53.654884],"type":"Point"}
}