{
  "type": "Feature",
  "properties": {
    "iso:country":"GB",
    "sg:address":"Central Office, Learning Disability, Chevet Hey",
    "sg:city":"Wrexham",
    "sg:classifiers":[
        {
            "category":"Government",
            "subcategory":"Office",
            "type":"Public Place"
        }
    ],
    "sg:phone":"+44 1978 310143",
    "sg:postcode":"LL11 2ND",
    "sg:province":"Wrexham",
    "sg:tags":[
        "local"
    ],
    "wof:name":"Wrexham County Borough Council",
    "wof:placetype":"venue"
},
  "geometry": {"coordinates":[-2.9963400364,53.0551185608],"type":"Point"}
}