{
  "type": "Feature",
  "properties": {
    "addr:full":"Argyle Business Centre, 8 Leicester St Southport Lancashire PR9 0HA",
    "addr:housenumber":"8",
    "addr:postcode":"pr9 0ha",
    "addr:street":"Leicester St",
    "iso:country":"GB",
    "sg:address":"Argyle Business Centre, 8 Leicester St",
    "sg:city":"Southport",
    "sg:classifiers":[
        {
            "category":"Professional",
            "subcategory":"Secretarial Services",
            "type":"Services"
        }
    ],
    "sg:phone":"+44 1704 540767",
    "sg:postcode":"PR9 0HA",
    "sg:province":"Lancashire",
    "wof:name":"J T A Business Services",
    "wof:placetype":"venue"
},
  "geometry": {"coordinates":[-3.00034,53.652889],"type":"Point"}
}