{
  "type": "Feature",
  "properties": {
    "addr:full":"44 Ryder Road Plymouth Devon PL2 1JA",
    "addr:housenumber":"44",
    "addr:postcode":"pl2 1ja",
    "addr:street":"Ryder Road",
    "iso:country":"GB",
    "sg:address":"44 Ryder Road",
    "sg:city":"Plymouth",
    "sg:classifiers":[
        {
            "category":"Organizations",
            "subcategory":"Non-profit Organization",
            "type":"Services"
        }
    ],
    "sg:postcode":"PL2 1JA",
    "sg:province":"Devon",
    "sg:tags":[
        "organisation",
        "voluntary",
        "charity"
    ],
    "wof:name":"Community Health in Keyham",
    "wof:placetype":"venue"
},
  "geometry": {"coordinates":[-4.17184,50.383854],"type":"Point"}
}