{
  "type": "Feature",
  "properties": {
    "addr:full":"56 Roebuck Lane West Bromwich West Midlands B70 6QP",
    "addr:housenumber":"56",
    "addr:postcode":"b70 6qp",
    "addr:street":"Roebuck Lane West",
    "iso:country":"GB",
    "sg:address":"56 Roebuck Lane",
    "sg:city":"West Bromwich",
    "sg:classifiers":[
        {
            "category":"Animal Shelter",
            "type":"Public Place"
        }
    ],
    "sg:phone":"+44 121 525 1474",
    "sg:postcode":"B70 6QP",
    "sg:province":"West Midlands",
    "sg:tags":[
        "racking",
        "shelving"
    ],
    "wof:name":"N L D Racking Solutions",
    "wof:placetype":"venue"
},
  "geometry": {"coordinates":[-1.97916,52.509521],"type":"Point"}
}