{
  "type": "Feature",
  "properties": {
    "addr:full":"2a Lansdown Industrial Estate, Gloucester Road Cheltenham Gloucestershire GL51 8PL",
    "addr:housenumber":"2a;estate",
    "addr:postcode":"gl51 8pl",
    "addr:street":"Lansdown Industrial;Gloucester Road",
    "iso:country":"GB",
    "sg:address":"2a Lansdown Industrial Estate, Gloucester Road",
    "sg:city":"Cheltenham",
    "sg:classifiers":[
        {
            "category":"Manufacturing",
            "subcategory":"Wood Products",
            "type":"Manufacturing & Wholesale Goods"
        },
        {
            "category":"Farming",
            "subcategory":"Farm & Veterinary Services",
            "type":"Manufacturing & Wholesale Goods"
        }
    ],
    "sg:phone":"+44 1242 263765",
    "sg:postcode":"GL51 8PL",
    "sg:province":"Gloucestershire",
    "sg:tags":[
        "packaging",
        "crate",
        "packagers",
        "pallets"
    ],
    "wof:name":"Gordano Packaging Ltd",
    "wof:placetype":"venue"
},
  "geometry": {"coordinates":[-2.0994699001,51.900138855],"type":"Point"}
}