{
  "type": "Feature",
  "properties": {
    "iso:country":"GB",
    "sg:address":"Unit 9e, Sedgeletch Ind Est, Fencehouses",
    "sg:city":"Houghton Le Spring",
    "sg:classifiers":[
        {
            "category":"Manufacturing",
            "subcategory":"Motor Vehicles & Parts",
            "type":"Manufacturing & Wholesale Goods"
        }
    ],
    "sg:phone":"+44 191 385 2007",
    "sg:postcode":"DH4 6JW",
    "sg:province":"Durham",
    "sg:tags":[
        "bearing"
    ],
    "wof:name":"Washington Bearings & Transmissions Ltd",
    "wof:placetype":"venue"
},
  "geometry": {"coordinates":[-1.5016100407,54.8474006653],"type":"Point"}
}