{
  "type": "Feature",
  "properties": {
    "iso:country":"GB",
    "sg:address":"15 Cross St",
    "sg:city":"Oswestry",
    "sg:classifiers":[
        {
            "category":"Shopping",
            "subcategory":"Clothing, Apparel, & Fashions",
            "type":"Retail Goods"
        }
    ],
    "sg:phone":"+44 1691 653575",
    "sg:postcode":"SY11 2NF",
    "sg:province":"Shropshire",
    "sg:tags":[
        "menswear"
    ],
    "wof:name":"Pritchards Tailors Outfitters Ltd",
    "wof:placetype":"venue"
},
  "geometry": {"coordinates":[-3.05453,52.859585],"type":"Point"}
}