{
  "type": "Feature",
  "properties": {
    "addr:full":"1-2 Bedford Square London Greater London WC1B 3RB",
    "addr:housenumber":"1-2",
    "addr:postcode":"wc1b 3rb",
    "addr:street":"Bedford Square",
    "iso:country":"GB",
    "sg:address":"1-2 Bedford Square",
    "sg:city":"London",
    "sg:classifiers":[
        {
            "category":"Banks & Credit Unions",
            "subcategory":"Financial Services",
            "type":"Services"
        }
    ],
    "sg:phone":"+44 20 7637 8866",
    "sg:postcode":"WC1B 3RB",
    "sg:province":"Greater London",
    "sg:tags":[
        "consultant"
    ],
    "wof:name":"Cameron Mackintosh (Financial Services) Ltd.",
    "wof:placetype":"venue"
},
  "geometry": {"coordinates":[-0.128881,51.519073],"type":"Point"}
}