{
  "type": "Feature",
  "properties": {
    "addr:full":"Inglenook, Plungebrook Macclesfield Cheshire SK10 5TD",
    "addr:postcode":"sk10 5td",
    "iso:country":"GB",
    "sg:address":"Inglenook, Plungebrook",
    "sg:city":"Macclesfield",
    "sg:classifiers":[
        {
            "category":"Professional",
            "subcategory":"Detective & Security Services",
            "type":"Services"
        }
    ],
    "sg:phone":"+44 1625 616638",
    "sg:postcode":"SK10 5TD",
    "sg:province":"Cheshire",
    "wof:name":"Mobile Security Services",
    "wof:placetype":"venue"
},
  "geometry": {"coordinates":[-2.0917999744,53.2723884583],"type":"Point"}
}