{
  "type": "Feature",
  "properties": {
    "iso:country":"GB",
    "sg:address":"7 Hollybank Road, Kings Heath",
    "sg:city":"Birmingham",
    "sg:classifiers":[
        {
            "category":"Home & Garden",
            "subcategory":"Furniture",
            "type":"Retail Goods"
        }
    ],
    "sg:phone":"+44 121 441 1413",
    "sg:postcode":"B13 0RF",
    "sg:province":"West Midlands",
    "wof:name":"Kings Heath Furniture",
    "wof:placetype":"venue"
},
  "geometry": {"coordinates":[-1.877589941,52.4215545654],"type":"Point"}
}