{
  "type": "Feature",
  "properties": {
    "addr:full":"Dogmore Lane, Rushton Tarporley Cheshire CW6 9BB",
    "addr:postcode":"cw6 9bb",
    "addr:street":"Dogmore Lane",
    "iso:country":"GB",
    "sg:address":"Dogmore Lane, Rushton",
    "sg:city":"Tarporley",
    "sg:classifiers":[
        {
            "category":"Wholesale",
            "subcategory":"Fruits & Vegetables",
            "type":"Manufacturing & Wholesale Goods"
        }
    ],
    "sg:phone":"+44 1829 760321",
    "sg:postcode":"CW6 9BB",
    "sg:province":"Cheshire",
    "wof:name":"D S Thornhill (Rushton) Ltd.",
    "wof:placetype":"venue"
},
  "geometry": {"coordinates":[-2.6245601177,53.1709098816],"type":"Point"}
}