{
  "type": "Feature",
  "properties": {
    "addr:full":"24 Wellington Avenue Bristol City of Bristol BS6 5HP",
    "addr:housenumber":"24",
    "addr:postcode":"bs6 5hp",
    "addr:street":"Wellington Avenue",
    "iso:country":"GB",
    "sg:address":"24 Wellington Avenue",
    "sg:city":"Bristol",
    "sg:classifiers":[
        {
            "category":"Social Services",
            "subcategory":"Job Training",
            "type":"Services"
        },
        {
            "category":"Communications",
            "subcategory":"Film & Video Production",
            "type":"Services"
        }
    ],
    "sg:phone":"+44 117 924 8795",
    "sg:postcode":"BS6 5HP",
    "sg:province":"City of Bristol",
    "sg:tags":[
        "translator",
        "interpreter",
        "illustrator",
        "artist"
    ],
    "wof:name":"Charles Everett",
    "wof:placetype":"venue"
},
  "geometry": {"coordinates":[-2.5875489712,51.465877533],"type":"Point"}
}