{
  "type": "Feature",
  "properties": {
    "iso:country":"GB",
    "sg:address":"Hargate Lane",
    "sg:city":"West Bromwich",
    "sg:classifiers":[
        {
            "category":"Bars & Pubs",
            "type":"Food & Drink"
        }
    ],
    "sg:postcode":"B71 1PH",
    "sg:province":"West Midlands",
    "sg:tags":[
        "pubs",
        "inn"
    ],
    "wof:name":"The Hargate Arms",
    "wof:placetype":"venue"
},
  "geometry": {"coordinates":[-1.9923620224,52.5258293152],"type":"Point"}
}