{
  "type": "Feature",
  "properties": {
    "iso:country":"GB",
    "sg:address":"12 Cherwell Avenue",
    "sg:city":"Kidlington",
    "sg:classifiers":[
        {
            "category":"Building & Trades",
            "subcategory":"Plumbing",
            "type":"Services"
        }
    ],
    "sg:phone":"+44 1865 376913",
    "sg:postcode":"OX5 2JL",
    "sg:province":"Buckinghamshire",
    "sg:tags":[
        "central",
        "installation",
        "system",
        "servicing",
        "heating"
    ],
    "wof:name":"M J Fenemore",
    "wof:placetype":"venue"
},
  "geometry": {"coordinates":[-1.276188,51.821171],"type":"Point"}
}