{
  "type": "Feature",
  "properties": {
    "iso:country":"GB",
    "sg:address":"56 High Street",
    "sg:city":"Mold",
    "sg:classifiers":[
        {
            "category":"Restaurant",
            "type":"Food & Drink"
        }
    ],
    "sg:phone":"+44 1352 759225",
    "sg:postcode":"CH7 1BH",
    "sg:province":"Denbighshire",
    "sg:tags":[
        "french"
    ],
    "wof:name":"Chez Colette",
    "wof:placetype":"venue"
},
  "geometry": {"coordinates":[-3.144479,53.169449],"type":"Point"}
}