{
  "type": "Feature",
  "properties": {
    "addr:full":"Unit 3 Wood End Lane Business Park Bromyard Herefordshire HR7 4HQ",
    "addr:housenumber":"unit 3",
    "addr:postcode":"hr7 4hq",
    "addr:street":"Wood End Lane Business Park",
    "iso:country":"GB",
    "sg:address":"Unit 3 Wood End Lane Business Park",
    "sg:city":"Bromyard",
    "sg:classifiers":[
        {
            "category":"Building & Trades",
            "subcategory":"Construction",
            "type":"Services"
        }
    ],
    "sg:phone":"+44 1885 490488",
    "sg:postcode":"HR7 4HQ",
    "sg:province":"Herefordshire",
    "sg:tags":[
        "joinery"
    ],
    "wof:name":"J & J Woodworking",
    "wof:placetype":"venue"
},
  "geometry": {"coordinates":[-2.554751,52.149719],"type":"Point"}
}