{
  "type": "Feature",
  "properties": {
    "addr:full":"Rose Green Road Bristol City of Bristol BS5 7XE",
    "addr:postcode":"bs5 7xe",
    "addr:street":"Rose Green Road",
    "iso:country":"GB",
    "sg:address":"Rose Green Road",
    "sg:city":"Bristol",
    "sg:classifiers":[
        {
            "category":"Shopping",
            "subcategory":"Beauty & Cosmetics",
            "type":"Retail Goods"
        }
    ],
    "sg:phone":"+44 117 951 7344",
    "sg:postcode":"BS5 7XE",
    "sg:province":"City of Bristol",
    "sg:tags":[
        "equipment",
        "supply",
        "hairdressing"
    ],
    "wof:name":"Aston & Fincher Ltd.",
    "wof:placetype":"venue"
},
  "geometry": {"coordinates":[-2.547043,51.469414],"type":"Point"}
}