{
  "type": "Feature",
  "properties": {
    "addr:full":"Torrington Rd Ruislip Greater London HA4 0AS",
    "addr:postcode":"ha4 0as",
    "addr:street":"Torrington Rd",
    "iso:country":"GB",
    "sg:address":"Torrington Rd",
    "sg:city":"Ruislip",
    "sg:classifiers":[
        {
            "category":"Place Of Worship",
            "type":"Public Place"
        }
    ],
    "sg:phone":"+44 1895 632507",
    "sg:postcode":"HA4 0AS",
    "sg:province":"Greater London",
    "wof:name":"Methodist Church",
    "wof:placetype":"venue"
},
  "geometry": {"coordinates":[-0.409044,51.567295],"type":"Point"}
}