{
  "type": "Feature",
  "properties": {
    "iso:country":"GB",
    "sg:address":"Waterside Farm, West Brabourne",
    "sg:city":"Ashford",
    "sg:classifiers":[
        {
            "category":"Building & Trades",
            "subcategory":"Construction",
            "type":"Services"
        }
    ],
    "sg:phone":"+44 1303 813108",
    "sg:postcode":"TN25 5NA",
    "sg:province":"Kent",
    "sg:tags":[
        "builder"
    ],
    "wof:name":"A J Fortescue & Sons Ltd.",
    "wof:placetype":"venue"
},
  "geometry": {"coordinates":[0.97288,51.169609],"type":"Point"}
}