{
  "type": "Feature",
  "properties": {
    "iso:country":"GB",
    "sg:address":"7 Victoria Road",
    "sg:city":"London",
    "sg:classifiers":[
        {
            "category":"Professional",
            "subcategory":"Accounting & Tax Preparation",
            "type":"Services"
        }
    ],
    "sg:phone":"+44 20 8529 2340",
    "sg:postcode":"E4 6BY",
    "sg:province":"Greater London",
    "sg:tags":[
        "accountant",
        "activity"
    ],
    "wof:name":"David J Wenham & Co",
    "wof:placetype":"venue"
},
  "geometry": {"coordinates":[0.0142580001,51.6304626465],"type":"Point"}
}