{
  "type": "Feature",
  "properties": {
    "addr:full":"57 Gilkes Street Middlesbrough North Yorkshire TS1 5EL",
    "addr:housenumber":"57",
    "addr:postcode":"ts1 5el",
    "addr:street":"Gilkes Street",
    "iso:country":"GB",
    "sg:address":"57 Gilkes Street",
    "sg:city":"Middlesbrough",
    "sg:classifiers":[
        {
            "category":"Transit Center",
            "subcategory":"Freight",
            "type":"Transportation"
        }
    ],
    "sg:phone":"+44 1642 226351",
    "sg:postcode":"TS1 5EL",
    "sg:province":"North Yorkshire",
    "sg:tags":[
        "shop",
        "craft",
        "centre"
    ],
    "wof:name":"Cleveland Crafts Centre",
    "wof:placetype":"venue"
},
  "geometry": {"coordinates":[-1.2402420044,54.5756111145],"type":"Point"}
}