{
  "type": "Feature",
  "properties": {
    "addr:full":"10 Salisbury Mews London Greater London SW6 7DS",
    "addr:housenumber":"10",
    "addr:postcode":"sw6 7ds",
    "addr:street":"Salisbury Mews",
    "iso:country":"GB",
    "sg:address":"10 Salisbury Mews",
    "sg:city":"London",
    "sg:classifiers":[
        {
            "category":"Building & Trades",
            "subcategory":"Construction",
            "type":"Services"
        }
    ],
    "sg:phone":"+44 20 7385 9595",
    "sg:postcode":"SW6 7DS",
    "sg:province":"Greater London",
    "sg:tags":[
        "decorator",
        "painter"
    ],
    "wof:name":"B Whitmore",
    "wof:placetype":"venue"
},
  "geometry": {"coordinates":[-0.206864,51.480507],"type":"Point"}
}