{
  "type": "Feature",
  "properties": {
    "iso:country":"GB",
    "sg:address":"215 Harehills Lane",
    "sg:city":"Leeds",
    "sg:classifiers":[
        {
            "category":"Fast Food",
            "type":"Food & Drink"
        }
    ],
    "sg:phone":"+44 113 235 9222",
    "sg:postcode":"LS8 3QH",
    "sg:province":"West Yorkshire",
    "sg:tags":[
        "delivery"
    ],
    "wof:name":"Al Halal Tandoori",
    "wof:placetype":"venue"
},
  "geometry": {"coordinates":[-1.5139100552,53.8148078918],"type":"Point"}
}