{
  "type": "Feature",
  "properties": {
    "iso:country":"GB",
    "sg:address":"Lower Tor, Whitchurch",
    "sg:city":"Tavistock",
    "sg:classifiers":[
        {
            "category":"Farming",
            "subcategory":"Livestock Farm",
            "type":"Manufacturing & Wholesale Goods"
        }
    ],
    "sg:postcode":"PL19 9EQ",
    "sg:province":"Devon",
    "sg:tags":[
        "others"
    ],
    "wof:name":"Stanley C Bellamy",
    "wof:placetype":"venue"
},
  "geometry": {"coordinates":[-4.135029,50.535931],"type":"Point"}
}