{
  "type": "Feature",
  "properties": {
    "addr:full":"Stone Cres Telford Shropshire TF1 2LN",
    "addr:postcode":"tf1 2ln",
    "addr:street":"Stone Cres",
    "iso:country":"GB",
    "sg:address":"Stone Cres",
    "sg:city":"Telford",
    "sg:classifiers":[
        {
            "category":"Arts & Performance",
            "subcategory":"Music",
            "type":"Entertainment"
        }
    ],
    "sg:phone":"+44 1952 416373",
    "sg:postcode":"TF1 2LN",
    "sg:province":"Shropshire",
    "sg:tags":[
        "mobile",
        "disco"
    ],
    "wof:name":"Its No Limit Discos",
    "wof:placetype":"venue"
},
  "geometry": {"coordinates":[-2.498764,52.69326],"type":"Point"}
}