{
  "type": "Feature",
  "properties": {
    "addr:full":"Unit 33 Main Ave, Brackla Indstl Est Bridgend Bridgend CF31 2AG",
    "addr:housenumber":"unit 33",
    "addr:postcode":"cf31 2ag",
    "addr:street":"Main Ave;Indstl Est",
    "iso:country":"GB",
    "sg:address":"Unit 33 Main Ave, Brackla Indstl Est",
    "sg:city":"Bridgend",
    "sg:classifiers":[
        {
            "category":"Autos & Motor Vehicles",
            "subcategory":"Auto Supplies",
            "type":"Retail Goods"
        }
    ],
    "sg:postcode":"CF31 2AG",
    "sg:province":"Bridgend",
    "sg:tags":[
        "taxi",
        "equipment"
    ],
    "wof:name":"Sharp,Verdun,Tarriff Two",
    "wof:placetype":"venue"
},
  "geometry": {"coordinates":[-3.5625729561,51.5205688477],"type":"Point"}
}