{
  "type": "Feature",
  "properties": {
    "iso:country":"GB",
    "sg:address":"Unit 1, Ventura Court, Lowmoor Business Park",
    "sg:city":"Nottingham",
    "sg:classifiers":[
        {
            "category":"Manufacturing",
            "subcategory":"Metals",
            "type":"Manufacturing & Wholesale Goods"
        },
        {
            "category":"Real Estate",
            "subcategory":"Architect",
            "type":"Services"
        }
    ],
    "sg:phone":"+44 1623 721172",
    "sg:postcode":"NG17 7DF",
    "sg:province":"Nottinghamshire",
    "sg:tags":[
        "mnfrs",
        "aluminium",
        "architectural",
        "fabricator"
    ],
    "sg:website":"http://www.absltd.co.uk",
    "wof:name":"Aluminium Bending Specialists Ltd",
    "wof:placetype":"venue"
},
  "geometry": {"coordinates":[-1.243854,53.1105],"type":"Point"}
}