{
  "type": "Feature",
  "properties": {
    "iso:country":"GB",
    "sg:address":"18 Chapel Street, Pontnewydd",
    "sg:city":"Cwmbran",
    "sg:classifiers":[
        {
            "category":"Shopping",
            "subcategory":"Bicycles & Sporting Goods",
            "type":"Retail Goods"
        }
    ],
    "sg:phone":"+44 1633 869961",
    "sg:postcode":"NP44 1DW",
    "sg:province":"Monmouthshire",
    "sg:tags":[
        "cycle",
        "accessory"
    ],
    "wof:name":"Wheels Cwmbran",
    "wof:placetype":"venue"
},
  "geometry": {"coordinates":[-3.025663,51.660427],"type":"Point"}
}