{
  "type": "Feature",
  "properties": {
    "addr:full":"2 Green Way, Colne Engaine Colchester Essex CO6 2HB",
    "addr:housenumber":"2",
    "addr:postcode":"co6 2hb",
    "addr:street":"Green Way",
    "iso:country":"GB",
    "sg:address":"2 Green Way, Colne Engaine",
    "sg:city":"Colchester",
    "sg:classifiers":[
        {
            "category":"Building & Trades",
            "subcategory":"Construction",
            "type":"Services"
        }
    ],
    "sg:phone":"+44 1787 220220",
    "sg:postcode":"CO6 2HB",
    "sg:province":"Essex",
    "sg:tags":[
        "dry",
        "lining",
        "plasterers",
        "screeders"
    ],
    "wof:name":"F H Staton",
    "wof:placetype":"venue"
},
  "geometry": {"coordinates":[0.69279,51.942993],"type":"Point"}
}