{
  "type": "Feature",
  "properties": {
    "iso:country":"GB",
    "sg:address":"Intex Business Park, Wade Road",
    "sg:city":"Basingstoke",
    "sg:classifiers":[
        {
            "category":"Wholesale",
            "subcategory":"Medical Equipment & Supplies",
            "type":"Manufacturing & Wholesale Goods"
        }
    ],
    "sg:phone":"+44 20 7708 3783",
    "sg:postcode":"RG24 8NE",
    "sg:province":"Hampshire",
    "sg:tags":[
        "hospital"
    ],
    "wof:name":"Sunlight Healthcare",
    "wof:placetype":"venue"
},
  "geometry": {"coordinates":[-1.06609,51.27914],"type":"Point"}
}