{
  "type": "Feature",
  "properties": {
    "addr:full":"C O Zeneca, Earls Road, South Site Grangemouth Falkirk FK3 8XG",
    "addr:postcode":"fk3 8xg",
    "addr:street":"Earls Road South Site",
    "iso:country":"GB",
    "sg:address":"C O Zeneca, Earls Road, South Site",
    "sg:city":"Grangemouth",
    "sg:classifiers":[
        {
            "category":"Professional",
            "subcategory":"Engineering",
            "type":"Services"
        }
    ],
    "sg:phone":"+44 1324 494480",
    "sg:postcode":"FK3 8XG",
    "sg:province":"Falkirk",
    "sg:tags":[
        "contractor",
        "electrical",
        "engineer"
    ],
    "wof:name":"Watson Norie Ltd.",
    "wof:placetype":"venue"
},
  "geometry": {"coordinates":[-3.723894,56.009331],"type":"Point"}
}