{
  "type": "Feature",
  "properties": {
    "addr:full":"27 Kent Av East Cowes Isle of Wight PO32 6QN",
    "addr:housenumber":"27",
    "addr:postcode":"po32 6qn",
    "addr:street":"Kent Av East",
    "iso:country":"GB",
    "sg:address":"27 Kent Av",
    "sg:city":"East Cowes",
    "sg:classifiers":[
        {
            "category":"Arena",
            "subcategory":"Sports Club",
            "type":"Entertainment"
        }
    ],
    "sg:phone":"+44 1983 292190",
    "sg:postcode":"PO32 6QN",
    "sg:province":"Isle of Wight",
    "wof:name":"Isle Of Wight Tug Of War Club",
    "wof:placetype":"venue"
},
  "geometry": {"coordinates":[-1.2798899412,50.7527923584],"type":"Point"}
}