{
  "type": "Feature",
  "properties": {
    "iso:country":"GB",
    "sg:address":"65 Bridge Street",
    "sg:city":"Macclesfield",
    "sg:classifiers":[
        {
            "category":"Retail",
            "subcategory":"Auto Repair",
            "type":"Services"
        }
    ],
    "sg:phone":"+44 1625 614702",
    "sg:postcode":"SK11 6PY",
    "sg:province":"Cheshire",
    "sg:tags":[
        "modification",
        "garage"
    ],
    "wof:name":"Paul Dobson Garage",
    "wof:placetype":"venue"
},
  "geometry": {"coordinates":[-2.1300969124,53.2583236694],"type":"Point"}
}