{
  "type": "Feature",
  "properties": {
    "addr:full":"2a Devonshire Road Bexleyheath Kent DA6 8DS",
    "addr:housenumber":"2a",
    "addr:postcode":"da6 8ds",
    "addr:street":"Devonshire Road",
    "iso:country":"GB",
    "sg:address":"2a Devonshire Road",
    "sg:city":"Bexleyheath",
    "sg:classifiers":[
        {
            "category":"Sports & Exercise",
            "subcategory":"Gym",
            "type":"Entertainment"
        }
    ],
    "sg:phone":"+44 20 8304 4919",
    "sg:postcode":"DA6 8DS",
    "sg:province":"Kent",
    "sg:tags":[
        "fitness",
        "health",
        "centre"
    ],
    "wof:name":"Broadways Health & Fitness Club Ltd.",
    "wof:placetype":"venue"
},
  "geometry": {"coordinates":[0.1342760026,51.4579467773],"type":"Point"}
}