{
  "type": "Feature",
  "properties": {
    "iso:country":"GB",
    "sg:address":"Lake Works, Cranleifgh Road Porchester",
    "sg:city":"Fareham",
    "sg:classifiers":[
        {
            "category":"Wholesale",
            "subcategory":"Electrical",
            "type":"Manufacturing & Wholesale Goods"
        }
    ],
    "sg:phone":"+44 1329 286148",
    "sg:postcode":"PO16 9DR",
    "sg:province":"Hampshire",
    "sg:tags":[
        "equipment",
        "refrigeration"
    ],
    "wof:name":"D C I Services Ltd.",
    "wof:placetype":"venue"
},
  "geometry": {"coordinates":[-1.1461,50.84132],"type":"Point"}
}