{
  "type": "Feature",
  "properties": {
    "addr:full":"40 Kestor Dr Exeter Devon EX4 2NH",
    "addr:housenumber":"40",
    "addr:postcode":"ex4 2nh",
    "addr:street":"Kestor Dr",
    "iso:country":"GB",
    "sg:address":"40 Kestor Dr",
    "sg:city":"Exeter",
    "sg:classifiers":[
        {
            "category":"Home & Garden",
            "subcategory":"Carpets & Floor Coverings",
            "type":"Retail Goods"
        }
    ],
    "sg:postcode":"EX4 2NH",
    "sg:province":"Devon",
    "sg:tags":[
        "carpets",
        "rug",
        "matting"
    ],
    "wof:name":"Dove,Paul John,",
    "wof:placetype":"venue"
},
  "geometry": {"coordinates":[-3.559253,50.731987],"type":"Point"}
}