{
  "type": "Feature",
  "properties": {
    "addr:full":"Unit 3g, Redwither Tower, Wrexham Industrial Estate Wrexham Wrexham LL13 9XT",
    "addr:postcode":"ll13 9xt",
    "addr:street":"Industrial Estate",
    "iso:country":"GB",
    "sg:address":"Unit 3g, Redwither Tower, Wrexham Industrial Estate",
    "sg:city":"Wrexham",
    "sg:classifiers":[
        {
            "category":"Professional",
            "subcategory":"Computer Services",
            "type":"Services"
        }
    ],
    "sg:phone":"+44 1978 667120",
    "sg:postcode":"LL13 9XT",
    "sg:province":"Wrexham",
    "sg:tags":[
        "system",
        "software"
    ],
    "wof:name":"Redwither Software Ltd.",
    "wof:placetype":"venue"
},
  "geometry": {"coordinates":[-2.920484066,53.04529953],"type":"Point"}
}