{
  "type": "Feature",
  "properties": {
    "addr:full":"Woods Way, Goring By Sea Worthing West Sussex BN12 4QY",
    "addr:postcode":"bn12 4qy",
    "addr:street":"Woods Way",
    "iso:country":"GB",
    "sg:address":"Woods Way, Goring By Sea",
    "sg:city":"Worthing",
    "sg:classifiers":[
        {
            "category":"Home & Garden",
            "subcategory":"Home Furnishings",
            "type":"Retail Goods"
        }
    ],
    "sg:phone":"+44 1903 700061",
    "sg:postcode":"BN12 4QY",
    "sg:province":"West Sussex",
    "sg:tags":[
        "merchant",
        "diy",
        "decorators'"
    ],
    "wof:name":"C Brewer & Sons Ltd.",
    "wof:placetype":"venue"
},
  "geometry": {"coordinates":[-0.4241290092,50.8150787354],"type":"Point"}
}