{
  "type": "Feature",
  "properties": {
    "iso:country":"GB",
    "sg:address":"Town Hall, 155 Bartholomew Street",
    "sg:city":"Newbury",
    "sg:classifiers":[
        {
            "category":"Professional",
            "subcategory":"Employment Agencies",
            "type":"Services"
        }
    ],
    "sg:phone":"+44 1635 551111",
    "sg:postcode":"RG14 5HB",
    "sg:province":"Berkshire",
    "sg:tags":[
        "consultant"
    ],
    "wof:name":"First Choice Recruitment & Training Ltd.",
    "wof:placetype":"venue"
},
  "geometry": {"coordinates":[-1.3258719444,51.405872345],"type":"Point"}
}