{
  "type": "Feature",
  "properties": {
    "iso:country":"GB",
    "sg:address":"6 China Street",
    "sg:city":"Lancaster",
    "sg:classifiers":[
        {
            "category":"Restaurant",
            "type":"Food & Drink"
        }
    ],
    "sg:phone":"+44 1524 846667",
    "sg:postcode":"LA1 1EX",
    "sg:province":"Lancashire",
    "wof:name":"The Kebab & Stakehouse",
    "wof:placetype":"venue"
},
  "geometry": {"coordinates":[-2.803441,54.049858],"type":"Point"}
}