{
  "type": "Feature",
  "properties": {
    "iso:country":"GB",
    "sg:address":"P O 1291",
    "sg:city":"Rugby",
    "sg:classifiers":[
        {
            "category":"Communications",
            "type":"Services"
        }
    ],
    "sg:phone":"+44 1788 562595",
    "sg:postcode":"CV21 2ZG",
    "sg:province":"Warwickshire",
    "sg:tags":[
        "broadcasting"
    ],
    "wof:name":"Jet FM",
    "wof:placetype":"venue"
},
  "geometry": {"coordinates":[-1.267819,52.375641],"type":"Point"}
}