{
  "type": "Feature",
  "properties": {
    "iso:country":"GB",
    "sg:address":"153 Henry Street",
    "sg:city":"Leigh",
    "sg:classifiers":[
        {
            "category":"Bars & Pubs",
            "type":"Food & Drink"
        }
    ],
    "sg:phone":"+44 1942 677289",
    "sg:postcode":"WN7 3HA",
    "sg:province":"Lancashire",
    "sg:tags":[
        "pubs",
        "inn"
    ],
    "wof:name":"The Pennington",
    "wof:placetype":"venue"
},
  "geometry": {"coordinates":[-2.512458,53.491299],"type":"Point"}
}