{
  "type": "Feature",
  "properties": {
    "addr:full":"Third Floor Lambourne House, 7 Western Road Romford Essex RM1 3LD",
    "addr:housenumber":"third;lambourne;7",
    "addr:postcode":"rm1 3ld",
    "addr:street":"Western Road",
    "iso:country":"GB",
    "sg:address":"Third Floor Lambourne House, 7 Western Road",
    "sg:city":"Romford",
    "sg:classifiers":[
        {
            "category":"Education",
            "subcategory":"Special Training",
            "type":"Public Place"
        }
    ],
    "sg:phone":"+44 1708 726343",
    "sg:postcode":"RM1 3LD",
    "sg:province":"Essex",
    "sg:tags":[
        "product",
        "centre"
    ],
    "wof:name":"J H P Training",
    "wof:placetype":"venue"
},
  "geometry": {"coordinates":[0.184134,51.577351],"type":"Point"}
}