{
  "type": "Feature",
  "properties": {
    "addr:full":"The Garage, Brier Lane Wakefield West Yorkshire WF4 2AT",
    "addr:postcode":"wf4 2at",
    "addr:street":"Brier Lane",
    "iso:country":"GB",
    "sg:address":"The Garage, Brier Lane",
    "sg:city":"Wakefield",
    "sg:classifiers":[
        {
            "category":"Retail",
            "subcategory":"Auto Repair",
            "type":"Services"
        }
    ],
    "sg:postcode":"WF4 2AT",
    "sg:province":"West Yorkshire",
    "sg:tags":[
        "electrician"
    ],
    "wof:name":"Junction Auto Electrics",
    "wof:placetype":"venue"
},
  "geometry": {"coordinates":[-1.420109,53.623066],"type":"Point"}
}