{
  "type": "Feature",
  "properties": {
    "addr:full":"Buckingham Rd Gillingham Dorset SP8 4QF",
    "addr:postcode":"sp8 4qf",
    "addr:street":"Buckingham Rd",
    "iso:country":"GB",
    "sg:address":"Buckingham Rd",
    "sg:city":"Gillingham",
    "sg:classifiers":[
        {
            "category":"Organizations",
            "subcategory":"Non-profit Organization",
            "type":"Services"
        }
    ],
    "sg:phone":"+44 1747 822679",
    "sg:postcode":"SP8 4QF",
    "sg:province":"Dorset",
    "sg:tags":[
        "organisation",
        "animal",
        "welfare"
    ],
    "wof:name":"Cats Protection League",
    "wof:placetype":"venue"
},
  "geometry": {"coordinates":[-2.2738039494,51.0360984802],"type":"Point"}
}