{
  "type": "Feature",
  "properties": {
    "addr:full":"Hammerain House, Hookstone Av Harrogate North Yorkshire HG2 8ER",
    "addr:postcode":"hg2 8er",
    "addr:street":"Hookstone Av",
    "iso:country":"GB",
    "sg:address":"Hammerain House, Hookstone Av",
    "sg:city":"Harrogate",
    "sg:classifiers":[
        {
            "category":"Professional",
            "subcategory":"Employment Agencies",
            "type":"Services"
        }
    ],
    "sg:phone":"+44 1423 870727",
    "sg:postcode":"HG2 8ER",
    "sg:province":"North Yorkshire",
    "sg:tags":[
        "consultant"
    ],
    "wof:name":"Humana International",
    "wof:placetype":"venue"
},
  "geometry": {"coordinates":[-1.5298240185,53.9777793884],"type":"Point"}
}