{
  "type": "Feature",
  "properties": {
    "iso:country":"GB",
    "sg:address":"54a Westfield La",
    "sg:city":"St Leonards On Sea",
    "sg:classifiers":[
        {
            "category":"Building & Trades",
            "subcategory":"Construction",
            "type":"Services"
        }
    ],
    "sg:phone":"+44 1424 753927",
    "sg:postcode":"TN37 7NG",
    "sg:province":"East Sussex",
    "sg:tags":[
        "joiner",
        "carpenter"
    ],
    "wof:name":"Robert Alecock",
    "wof:placetype":"venue"
},
  "geometry": {"coordinates":[0.5621039867,50.8940200806],"type":"Point"}
}