{
  "type": "Feature",
  "properties": {
    "addr:full":"14 Boleyn Avenue, Ewell Epsom Surrey KT17 2QH",
    "addr:housenumber":"14",
    "addr:postcode":"kt17 2qh",
    "addr:street":"Boleyn Avenue",
    "iso:country":"GB",
    "sg:address":"14 Boleyn Avenue, Ewell",
    "sg:city":"Epsom",
    "sg:classifiers":[
        {
            "category":"Professional",
            "subcategory":"Management & Consulting",
            "type":"Services"
        }
    ],
    "sg:postcode":"KT17 2QH",
    "sg:province":"Surrey",
    "sg:tags":[
        "consultant",
        "business"
    ],
    "wof:name":"Fast Cycle Sciences Ltd.",
    "wof:placetype":"venue"
},
  "geometry": {"coordinates":[-0.2419939935,51.3477935791],"type":"Point"}
}