{
  "type": "Feature",
  "properties": {
    "addr:full":"201-203 High St North, East Ham East Ham Greater London E6 1JF",
    "addr:housenumber":"201-203",
    "addr:postcode":"e6 1jf",
    "addr:street":"High St North;Ham",
    "iso:country":"GB",
    "sg:address":"201-203 High St North, East Ham",
    "sg:city":"East Ham",
    "sg:classifiers":[
        {
            "category":"Banks & Credit Unions",
            "subcategory":"Financial Services",
            "type":"Services"
        }
    ],
    "sg:phone":"+44 20 8470 1332",
    "sg:postcode":"E6 1JF",
    "sg:province":"Greater London",
    "sg:tags":[
        "building",
        "society"
    ],
    "wof:name":"Bradford & Bingley Agency",
    "wof:placetype":"venue"
},
  "geometry": {"coordinates":[0.0510360003,51.5389671326],"type":"Point"}
}