{
  "type": "Feature",
  "properties": {
    "iso:country":"GB",
    "sg:address":"Goudhurst High Street, Goudhurst",
    "sg:city":"Cranbrook",
    "sg:classifiers":[
        {
            "category":"Community Center",
            "type":"Public Place"
        }
    ],
    "sg:postcode":"TN17 1AL",
    "sg:province":"Kent",
    "sg:tags":[
        "centre",
        "entertainment"
    ],
    "wof:name":"Garden of England Gallery",
    "wof:placetype":"venue"
},
  "geometry": {"coordinates":[0.458639,51.112839],"type":"Point"}
}