{
  "type": "Feature",
  "properties": {
    "addr:full":"11 Hurst Close Wallingford Oxfordshire OX10 9BQ",
    "addr:housenumber":"11",
    "addr:postcode":"ox10 9bq",
    "addr:street":"Hurst Close",
    "iso:country":"GB",
    "sg:address":"11 Hurst Close",
    "sg:city":"Wallingford",
    "sg:classifiers":[
        {
            "category":"Arena",
            "subcategory":"Sports Club",
            "type":"Entertainment"
        }
    ],
    "sg:postcode":"OX10 9BQ",
    "sg:province":"Oxfordshire",
    "wof:name":"The Elms",
    "wof:placetype":"venue"
},
  "geometry": {"coordinates":[-1.1293410063,51.5952606201],"type":"Point"}
}