{
  "type": "Feature",
  "properties": {
    "addr:full":"12a Kingfisher Court, Hambridge Road Newbury Berkshire RG14 5SJ",
    "addr:housenumber":"12a",
    "addr:postcode":"rg14 5sj",
    "addr:street":"Kingfisher Court Hambridge Road",
    "iso:country":"GB",
    "sg:address":"12a Kingfisher Court, Hambridge Road",
    "sg:city":"Newbury",
    "sg:classifiers":[
        {
            "category":"Organizations",
            "subcategory":"Non-profit Organization",
            "type":"Services"
        }
    ],
    "sg:phone":"+44 1635 40081",
    "sg:postcode":"RG14 5SJ",
    "sg:province":"Berkshire",
    "sg:tags":[
        "charitable",
        "organisation",
        "voluntary",
        "charity"
    ],
    "wof:name":"British Red Cross Society",
    "wof:placetype":"venue"
},
  "geometry": {"coordinates":[-1.3021990061,51.4002456665],"type":"Point"}
}