{
  "type": "Feature",
  "properties": {
    "iso:country":"GB",
    "sg:address":"Unit 2a, Stockton Close",
    "sg:city":"Walsall",
    "sg:classifiers":[
        {
            "category":"Building & Trades",
            "subcategory":"Plumbing",
            "type":"Services"
        }
    ],
    "sg:phone":"+44 1922 703800",
    "sg:postcode":"WS2 8LH",
    "sg:province":"West Midlands",
    "sg:tags":[
        "merchant",
        "plumbers'"
    ],
    "wof:name":"B S S Zenith",
    "wof:placetype":"venue"
},
  "geometry": {"coordinates":[-1.9913289547,52.5962982178],"type":"Point"}
}