{
  "type": "Feature",
  "properties": {
    "addr:full":"55-57 Exeter St Plymouth Devon PL4 0AH",
    "addr:housenumber":"55-57",
    "addr:postcode":"pl4 0ah",
    "addr:street":"Exeter St",
    "iso:country":"GB",
    "sg:address":"55-57 Exeter St",
    "sg:city":"Plymouth",
    "sg:classifiers":[
        {
            "category":"Food & Beverages",
            "subcategory":"Liquor & Beverages",
            "type":"Retail Goods"
        }
    ],
    "sg:phone":"+44 1752 250266",
    "sg:postcode":"PL4 0AH",
    "sg:province":"Devon",
    "sg:tags":[
        "beer",
        "spirit",
        "wines"
    ],
    "wof:name":"Bottoms Up",
    "wof:placetype":"venue"
},
  "geometry": {"coordinates":[-4.134646,50.371826],"type":"Point"}
}