{
  "type": "Feature",
  "properties": {
    "iso:country":"GB",
    "sg:address":"Ibex House, 42-44 Minories",
    "sg:city":"London",
    "sg:classifiers":[
        {
            "category":"Restaurant",
            "type":"Food & Drink"
        }
    ],
    "sg:phone":"+44 20 7481 2170",
    "sg:postcode":"EC3N 1DY",
    "sg:province":"Greater London",
    "wof:name":"John Miguel Marques",
    "wof:placetype":"venue"
},
  "geometry": {"coordinates":[-0.0753540024,51.5119132996],"type":"Point"}
}