{
  "type": "Feature",
  "properties": {
    "addr:full":"375 Chesterfield Road North, Pleasley Mansfield Derbyshire NG19 7RA",
    "addr:housenumber":"375",
    "addr:postcode":"ng19 7ra",
    "addr:street":"Chesterfield Road North",
    "iso:country":"GB",
    "sg:address":"375 Chesterfield Road North, Pleasley",
    "sg:city":"Mansfield",
    "sg:classifiers":[
        {
            "category":"Shopping",
            "subcategory":"Antiques",
            "type":"Retail Goods"
        }
    ],
    "sg:phone":"+44 1623 810480",
    "sg:postcode":"NG19 7RA",
    "sg:province":"Derbyshire",
    "wof:name":"Antique Warehouse",
    "wof:placetype":"venue"
},
  "geometry": {"coordinates":[-1.2363950014,53.1663284302],"type":"Point"}
}