{
  "type": "Feature",
  "properties": {
    "addr:full":"The Lodge, Little Bardfield Hall, Little Bardfield Braintree Essex CM7 4TT",
    "addr:postcode":"cm7 4tt",
    "addr:street":"Little Bardfield",
    "iso:country":"GB",
    "sg:address":"The Lodge, Little Bardfield Hall, Little Bardfield",
    "sg:city":"Braintree",
    "sg:classifiers":[
        {
            "category":"Autos & Motor Vehicles",
            "subcategory":"Auto Supplies",
            "type":"Retail Goods"
        },
        {
            "category":"Retail",
            "subcategory":"Auto Repair",
            "type":"Services"
        }
    ],
    "sg:phone":"+44 1371 811091",
    "sg:postcode":"CM7 4TT",
    "sg:province":"Essex",
    "sg:tags":[
        "car",
        "commercial",
        "windscreen"
    ],
    "wof:name":"County Windscreen Services",
    "wof:placetype":"venue"
},
  "geometry": {"coordinates":[0.419055,51.953224],"type":"Point"}
}