{
  "type": "Feature",
  "properties": {
    "addr:full":"School Road, Minchinhampton Stroud Gloucestershire GL6 9BP",
    "addr:postcode":"gl6 9bp",
    "addr:street":"School Road",
    "iso:country":"GB",
    "sg:address":"School Road, Minchinhampton",
    "sg:city":"Stroud",
    "sg:classifiers":[
        {
            "category":"Education",
            "subcategory":"School",
            "type":"Public Place"
        }
    ],
    "sg:phone":"+44 1453 883273",
    "sg:postcode":"GL6 9BP",
    "sg:province":"Gloucestershire",
    "sg:tags":[
        "college"
    ],
    "wof:name":"Minchinhampton School",
    "wof:placetype":"venue"
},
  "geometry": {"coordinates":[-2.1888189316,51.7051315308],"type":"Point"}
}