{
  "type": "Feature",
  "properties": {
    "iso:country":"GB",
    "sg:address":"18 Holmfield Road",
    "sg:city":"Blackpool",
    "sg:classifiers":[
        {
            "category":"Travel",
            "subcategory":"Hotels & Motels",
            "type":"Entertainment"
        }
    ],
    "sg:postcode":"FY2 9TB",
    "sg:province":"Lancashire",
    "wof:name":"Inglewood Hotel",
    "wof:placetype":"venue"
},
  "geometry": {"coordinates":[-3.052671,53.835152],"type":"Point"}
}