{
  "type": "Feature",
  "properties": {
    "addr:full":"1 Frodsham St Chester Cheshire CH1 3JZ",
    "addr:housenumber":"1",
    "addr:postcode":"ch1 3jz",
    "addr:street":"Frodsham St",
    "iso:country":"GB",
    "sg:address":"1 Frodsham St",
    "sg:city":"Chester",
    "sg:classifiers":[
        {
            "category":"Shopping",
            "subcategory":"Clothing, Apparel, & Fashions",
            "type":"Retail Goods"
        }
    ],
    "sg:phone":"+44 1244 400682",
    "sg:postcode":"CH1 3JZ",
    "sg:province":"Cheshire",
    "sg:tags":[
        "shop"
    ],
    "wof:name":"Hamells",
    "wof:placetype":"venue"
},
  "geometry": {"coordinates":[-2.8881869316,53.1911430359],"type":"Point"}
}