{
  "type": "Feature",
  "properties": {
    "addr:full":"Unit 8 Ivorys Industrial Estate St Albans Hertfordshire WD7 7HU",
    "addr:housenumber":"unit 8",
    "addr:postcode":"wd7 7hu",
    "addr:street":"Ivorys Industrial Estate",
    "iso:country":"GB",
    "sg:address":"Unit 8 Ivorys Industrial Estate",
    "sg:city":"St Albans",
    "sg:classifiers":[
        {
            "category":"Retail",
            "subcategory":"Auto Repair",
            "type":"Services"
        }
    ],
    "sg:phone":"+44 1923 855466",
    "sg:postcode":"WD7 7HU",
    "sg:province":"Hertfordshire",
    "sg:tags":[
        "body",
        "car"
    ],
    "wof:name":"Frogmore Garage & Coachworks",
    "wof:placetype":"venue"
},
  "geometry": {"coordinates":[-0.3177700043,51.6990318298],"type":"Point"}
}