{
  "type": "Feature",
  "properties": {
    "iso:country":"GB",
    "sg:address":"Rear Of 53 Colney Hatch Lane, Muswell Hill",
    "sg:city":"London",
    "sg:classifiers":[
        {
            "category":"Retail",
            "subcategory":"Auto Repair",
            "type":"Services"
        }
    ],
    "sg:phone":"+44 20 8444 5029",
    "sg:postcode":"N10 1LR",
    "sg:province":"Greater London",
    "sg:tags":[
        "modification",
        "garage"
    ],
    "wof:name":"T S Motors",
    "wof:placetype":"venue"
},
  "geometry": {"coordinates":[-0.14779,51.600231],"type":"Point"}
}