{
  "type": "Feature",
  "properties": {
    "iso:country":"GB",
    "sg:address":"Leeming St",
    "sg:city":"Mansfield",
    "sg:classifiers":[
        {
            "category":"Museum",
            "subcategory":"Art Museum",
            "type":"Entertainment"
        }
    ],
    "sg:phone":"+44 1623 463088",
    "sg:postcode":"NG18 1NG",
    "sg:province":"Nottinghamshire",
    "sg:tags":[
        "gallery"
    ],
    "wof:name":"Mansfield Museum & Art Gallery",
    "wof:placetype":"venue"
},
  "geometry": {"coordinates":[-1.194314,53.146469],"type":"Point"}
}