{
  "type": "Feature",
  "properties": {
    "iso:country":"GB",
    "sg:address":"68 Dagenham Road",
    "sg:city":"Romford",
    "sg:classifiers":[
        {
            "category":"Autos & Motor Vehicles",
            "subcategory":"Auto Supplies",
            "type":"Retail Goods"
        }
    ],
    "sg:phone":"+44 1708 720947",
    "sg:postcode":"RM7 0DA",
    "sg:province":"Essex",
    "sg:tags":[
        "tyre"
    ],
    "wof:name":"Rush Green Tyres",
    "wof:placetype":"venue"
},
  "geometry": {"coordinates":[0.1762160063,51.5660552979],"type":"Point"}
}