{
  "type": "Feature",
  "properties": {
    "addr:full":"8 The Meadway Hinckley Leicestershire LE10 2UB",
    "addr:housenumber":"8",
    "addr:postcode":"le10 2ub",
    "addr:street":"The Meadway",
    "iso:country":"GB",
    "sg:address":"8 The Meadway",
    "sg:city":"Hinckley",
    "sg:classifiers":[
        {
            "category":"Professional",
            "subcategory":"Engineering",
            "type":"Services"
        }
    ],
    "sg:phone":"+44 1455 632417",
    "sg:postcode":"LE10 2UB",
    "sg:province":"Leicestershire",
    "sg:tags":[
        "contractor",
        "electrical",
        "engineer"
    ],
    "wof:name":"John David Electrics",
    "wof:placetype":"venue"
},
  "geometry": {"coordinates":[-1.35424,52.537418],"type":"Point"}
}