{
  "type": "Feature",
  "properties": {
    "iso:country":"GB",
    "sg:address":"4 Station Road, Newburn",
    "sg:city":"Newcastle-upon-tyne",
    "sg:classifiers":[
        {
            "category":"Government",
            "subcategory":"Post Office",
            "type":"Public Place"
        }
    ],
    "sg:phone":"+44 191 267 4241",
    "sg:postcode":"NE15 8LS",
    "sg:province":"Northumberland",
    "wof:name":"Newburn Sub Post Office",
    "wof:placetype":"venue"
},
  "geometry": {"coordinates":[-1.743102,54.982723],"type":"Point"}
}