{
  "type": "Feature",
  "properties": {
    "iso:country":"GB",
    "sg:address":"10 Balmossie Avenue, Monifieth",
    "sg:city":"Dundee",
    "sg:classifiers":[
        {
            "category":"Building & Trades",
            "subcategory":"Construction",
            "type":"Services"
        }
    ],
    "sg:postcode":"DD5 4QN",
    "sg:province":"Angus",
    "sg:tags":[
        "roofing",
        "contracting"
    ],
    "wof:name":"A James Ross",
    "wof:placetype":"venue"
},
  "geometry": {"coordinates":[-2.842777,56.478142],"type":"Point"}
}