{
  "type": "Feature",
  "properties": {
    "iso:country":"GB",
    "sg:address":"11 Garrell Road, Kilsyth",
    "sg:city":"Glasgow",
    "sg:classifiers":[
        {
            "category":"Home & Garden",
            "subcategory":"Household Appliances",
            "type":"Retail Goods"
        }
    ],
    "sg:phone":"+44 1236 823811",
    "sg:postcode":"G65 9JX",
    "sg:province":"East Dunbartonshire",
    "sg:tags":[
        "electrical"
    ],
    "wof:name":"McMillan Refrigeration",
    "wof:placetype":"venue"
},
  "geometry": {"coordinates":[-4.0637450218,55.9741897583],"type":"Point"}
}