{
  "type": "Feature",
  "properties": {
    "addr:full":"Lower Croft House Dairy, Shuttleworth St, Earby Barnoldswick Lancashire BB18 6QN",
    "addr:postcode":"bb18 6qn",
    "addr:street":"Lower;Shuttleworth St",
    "iso:country":"GB",
    "sg:address":"Lower Croft House Dairy, Shuttleworth St, Earby",
    "sg:city":"Barnoldswick",
    "sg:classifiers":[
        {
            "category":"Farming",
            "subcategory":"Dairy Farm",
            "type":"Manufacturing & Wholesale Goods"
        }
    ],
    "sg:phone":"+44 1282 844294",
    "sg:postcode":"BB18 6QN",
    "sg:province":"Lancashire",
    "wof:name":"E Clark",
    "wof:placetype":"venue"
},
  "geometry": {"coordinates":[-2.146198988,53.9144859314],"type":"Point"}
}