{
  "type": "Feature",
  "properties": {
    "iso:country":"GB",
    "sg:address":"Unit 1, 32 Holmethorpe Avenue, Holmethorpe Industrial Estate",
    "sg:city":"Redhill",
    "sg:classifiers":[
        {
            "category":"Wholesale",
            "subcategory":"Photographic Equipment",
            "type":"Manufacturing & Wholesale Goods"
        }
    ],
    "sg:phone":"+44 1737 761324",
    "sg:postcode":"RH1 2NL",
    "sg:province":"Surrey",
    "sg:tags":[
        "repair"
    ],
    "wof:name":"Aztech Services Ltd.",
    "wof:placetype":"venue"
},
  "geometry": {"coordinates":[-0.158681,51.250107],"type":"Point"}
}