{
  "type": "Feature",
  "properties": {
    "iso:country":"GB",
    "sg:address":"20 Brookside Clo",
    "sg:city":"Waterlooville",
    "sg:classifiers":[
        {
            "category":"Health Services",
            "subcategory":"Clinic",
            "type":"Services"
        }
    ],
    "sg:phone":"+44 23 9226 6599",
    "sg:postcode":"PO7 6ET",
    "sg:province":"Hampshire",
    "sg:tags":[
        "aromatherapy"
    ],
    "wof:name":"Body Basic",
    "wof:placetype":"venue"
},
  "geometry": {"coordinates":[-1.0656100512,50.8994445801],"type":"Point"}
}