{
  "type": "Feature",
  "properties": {
    "iso:country":"GB",
    "sg:address":"144 High Street",
    "sg:city":"Epping",
    "sg:classifiers":[
        {
            "category":"Professional",
            "subcategory":"Accounting & Tax Preparation",
            "type":"Services"
        }
    ],
    "sg:phone":"+44 1992 574224",
    "sg:postcode":"CM16 4AS",
    "sg:province":"Essex",
    "sg:tags":[
        "accountant",
        "activity"
    ],
    "wof:name":"Gane Jackson Scott Ltd.",
    "wof:placetype":"venue"
},
  "geometry": {"coordinates":[0.111012,51.698475],"type":"Point"}
}