{
  "type": "Feature",
  "properties": {
    "addr:full":"18 Fronks Road Harwich Essex CO12 3RJ",
    "addr:housenumber":"18",
    "addr:postcode":"co12 3rj",
    "addr:street":"Fronks Road",
    "iso:country":"GB",
    "sg:address":"18 Fronks Road",
    "sg:city":"Harwich",
    "sg:classifiers":[
        {
            "category":"Place Of Worship",
            "type":"Public Place"
        },
        {
            "category":"Organizations",
            "subcategory":"Religious Organization",
            "type":"Services"
        }
    ],
    "sg:phone":"+44 1255 506332",
    "sg:postcode":"CO12 3RJ",
    "sg:province":"Essex",
    "sg:tags":[
        "organisation"
    ],
    "wof:name":"Kingsway Evangelical Church",
    "wof:placetype":"venue"
},
  "geometry": {"coordinates":[1.2718800306,51.9321098328],"type":"Point"}
}