{
  "type": "Feature",
  "properties": {
    "addr:full":"Pepper Street, Silverdale Newcastle Staffordshire ST5 6PZ",
    "addr:postcode":"st5 6pz",
    "addr:street":"Pepper Street",
    "iso:country":"GB",
    "sg:address":"Pepper Street, Silverdale",
    "sg:city":"Newcastle",
    "sg:classifiers":[
        {
            "category":"Autos & Motor Vehicles",
            "subcategory":"Automobile Sales",
            "type":"Retail Goods"
        }
    ],
    "sg:postcode":"ST5 6PZ",
    "sg:province":"Staffordshire",
    "sg:tags":[
        "car",
        "specialist",
        "sales",
        "classic"
    ],
    "wof:name":"Keele Classic Cars",
    "wof:placetype":"venue"
},
  "geometry": {"coordinates":[-2.270004034,53.0170783997],"type":"Point"}
}