{
  "type": "Feature",
  "properties": {
    "iso:country":"GB",
    "sg:address":"Felton House, Dinsdale Place, Newcastle",
    "sg:city":"Newcastle Upon Tyne",
    "sg:classifiers":[
        {
            "category":"Professional",
            "subcategory":"Advertising",
            "type":"Services"
        }
    ],
    "sg:phone":"+44 191 261 5000",
    "sg:postcode":"NE2 1BD",
    "sg:province":"Tyne and Wear",
    "sg:tags":[
        "agency"
    ],
    "wof:name":"Factory Cat Ltd",
    "wof:placetype":"venue"
},
  "geometry": {"coordinates":[-1.5975500345,54.9790306091],"type":"Point"}
}