{
  "type": "Feature",
  "properties": {
    "iso:country":"GB",
    "sg:address":"56 Cambridge Rd",
    "sg:city":"Lee On The Solent",
    "sg:classifiers":[
        {
            "category":"Building & Trades",
            "subcategory":"Construction",
            "type":"Services"
        }
    ],
    "sg:phone":"+44 23 9255 4446",
    "sg:postcode":"PO13 9DH",
    "sg:province":"Hampshire",
    "sg:tags":[
        "joiner",
        "carpenter"
    ],
    "wof:name":"D J Wallace",
    "wof:placetype":"venue"
},
  "geometry": {"coordinates":[-1.197794,50.798321],"type":"Point"}
}