{
  "type": "Feature",
  "properties": {
    "addr:full":"Skid Hill Lane Warlingham Kent CR6 9PP",
    "addr:postcode":"cr6 9pp",
    "addr:street":"Skid Hill Lane",
    "iso:country":"GB",
    "sg:address":"Skid Hill Lane",
    "sg:city":"Warlingham",
    "sg:classifiers":[
        {
            "category":"Manufacturing",
            "subcategory":"Building Materials",
            "type":"Manufacturing & Wholesale Goods"
        },
        {
            "category":"Farming",
            "subcategory":"Farm",
            "type":"Manufacturing & Wholesale Goods"
        },
        {
            "category":"Building & Trades",
            "subcategory":"Construction",
            "type":"Services"
        }
    ],
    "sg:phone":"+44 1959 571788",
    "sg:postcode":"CR6 9PP",
    "sg:province":"Kent",
    "sg:tags":[
        "manufacture",
        "scaffolding",
        "work",
        "crop",
        "platform",
        "railing",
        "mixed"
    ],
    "wof:name":"Whelan Plant",
    "wof:placetype":"venue"
},
  "geometry": {"coordinates":[0.002823,51.330677],"type":"Point"}
}