{
  "type": "Feature",
  "properties": {
    "addr:full":"23 West Street Wigton Cumbria CA7 9NP",
    "addr:housenumber":"23",
    "addr:postcode":"ca7 9np",
    "addr:street":"West Street",
    "iso:country":"GB",
    "sg:address":"23 West Street",
    "sg:city":"Wigton",
    "sg:classifiers":[
        {
            "category":"Shopping",
            "subcategory":"Department Store",
            "type":"Retail Goods"
        },
        {
            "category":"Shopping",
            "subcategory":"Bicycles & Sporting Goods",
            "type":"Retail Goods"
        }
    ],
    "sg:postcode":"CA7 9NP",
    "sg:province":"Cumbria",
    "sg:tags":[
        "accessory",
        "cycle"
    ],
    "wof:name":"Wigton Cycle & Sports",
    "wof:placetype":"venue"
},
  "geometry": {"coordinates":[-3.1628239155,54.8240356445],"type":"Point"}
}