{
  "type": "Feature",
  "properties": {
    "addr:full":"The Vicarage, Parsonage St Halstead Essex CO9 2LD",
    "addr:postcode":"co9 2ld",
    "addr:street":"Parsonage St",
    "iso:country":"GB",
    "sg:address":"The Vicarage, Parsonage St",
    "sg:city":"Halstead",
    "sg:classifiers":[
        {
            "category":"Place Of Worship",
            "type":"Public Place"
        }
    ],
    "sg:phone":"+44 1787 472171",
    "sg:postcode":"CO9 2LD",
    "sg:province":"Essex",
    "wof:name":"St James Church Greenstead Green",
    "wof:placetype":"venue"
},
  "geometry": {"coordinates":[0.635825,51.943996],"type":"Point"}
}