{
  "type": "Feature",
  "properties": {
    "addr:full":"Suite E Unitair Centre, Great South West Rd Feltham Greater London TW14 8NT",
    "addr:postcode":"tw14 8nt",
    "addr:street":"Great South West Rd",
    "iso:country":"GB",
    "sg:address":"Suite E Unitair Centre, Great South West Rd",
    "sg:city":"Feltham",
    "sg:classifiers":[
        {
            "category":"Professional",
            "subcategory":"Detective & Security Services",
            "type":"Services"
        }
    ],
    "sg:phone":"+44 20 8893 1767",
    "sg:postcode":"TW14 8NT",
    "sg:province":"Greater London",
    "wof:name":"Initial Aviation Security",
    "wof:placetype":"venue"
},
  "geometry": {"coordinates":[-0.4432300031,51.4561004639],"type":"Point"}
}