{
  "type": "Feature",
  "properties": {
    "addr:full":"Ropewalk Fishguard Pembrokeshire SA65 9BT",
    "addr:postcode":"sa65 9bt",
    "addr:street":"Ropewalk Fishguard Pembrokeshire",
    "iso:country":"GB",
    "sg:address":"Ropewalk",
    "sg:city":"Fishguard",
    "sg:classifiers":[
        {
            "category":"Restaurant",
            "type":"Food & Drink"
        }
    ],
    "sg:phone":"+44 1348 872178",
    "sg:postcode":"SA65 9BT",
    "sg:province":"Pembrokeshire",
    "wof:name":"Golden Grill Restaurant",
    "wof:placetype":"venue"
},
  "geometry": {"coordinates":[-4.978919,51.994736],"type":"Point"}
}