{
  "type": "Feature",
  "properties": {
    "iso:country":"GB",
    "sg:address":"Lyndhurst Avenue, Hazel Gro",
    "sg:city":"Stockport",
    "sg:classifiers":[
        {
            "category":"Education",
            "subcategory":"School",
            "type":"Public Place"
        }
    ],
    "sg:phone":"+44 161 483 4521",
    "sg:postcode":"SK7 5HP",
    "sg:province":"Cheshire",
    "sg:tags":[
        "local",
        "authority"
    ],
    "wof:name":"Moorfield Junior School",
    "wof:placetype":"venue"
},
  "geometry": {"coordinates":[-2.1284871101,53.3730621338],"type":"Point"}
}