{
  "type": "Feature",
  "properties": {
    "addr:full":"65 Canterbury Street Blackburn Lancashire BB2 2HT",
    "addr:housenumber":"65",
    "addr:postcode":"bb2 2ht",
    "addr:street":"Canterbury Street",
    "iso:country":"GB",
    "sg:address":"65 Canterbury Street",
    "sg:city":"Blackburn",
    "sg:classifiers":[
        {
            "category":"Professional",
            "subcategory":"Detective & Security Services",
            "type":"Services"
        }
    ],
    "sg:phone":"+44 1254 697989",
    "sg:postcode":"BB2 2HT",
    "sg:province":"Lancashire",
    "sg:tags":[
        "alarm",
        "burglar",
        "system"
    ],
    "wof:name":"21st Century Crime Prevention Services Ltd.",
    "wof:placetype":"venue"
},
  "geometry": {"coordinates":[-2.487182,53.743317],"type":"Point"}
}