{
  "type": "Feature",
  "properties": {
    "addr:full":"240 High Holborn Bloomsbury Greater London WC1V 7DN",
    "addr:housenumber":"240",
    "addr:postcode":"wc1v 7dn",
    "addr:street":"High Holborn",
    "iso:country":"GB",
    "sg:address":"240 High Holborn",
    "sg:city":"Bloomsbury",
    "sg:classifiers":[
        {
            "category":"Organizations",
            "subcategory":"Membership Organization",
            "type":"Services"
        }
    ],
    "sg:postcode":"WC1V 7DN",
    "sg:province":"Greater London",
    "sg:tags":[
        "club"
    ],
    "wof:name":"The U K Boardsailing Association Ltd",
    "wof:placetype":"venue"
},
  "geometry": {"coordinates":[-0.119024,51.517551],"type":"Point"}
}