{
  "type": "Feature",
  "properties": {
    "iso:country":"GB",
    "sg:address":"14 Chequer Lane",
    "sg:city":"Wigan",
    "sg:classifiers":[
        {
            "category":"Freight",
            "type":"Transportation"
        }
    ],
    "sg:postcode":"WN8 0DE",
    "sg:province":"Lancashire",
    "sg:tags":[
        "haulage",
        "road"
    ],
    "wof:name":"W & J Rigby",
    "wof:placetype":"venue"
},
  "geometry": {"coordinates":[-2.7304389477,53.5412216187],"type":"Point"}
}