{
  "type": "Feature",
  "properties": {
    "iso:country":"GB",
    "sg:address":"53 Avenue Road",
    "sg:city":"Torquay",
    "sg:classifiers":[
        {
            "category":"Travel",
            "subcategory":"Hotels & Motels",
            "type":"Entertainment"
        }
    ],
    "sg:phone":"+44 1803 292723",
    "sg:postcode":"TQ2 5LG",
    "sg:province":"Devon",
    "sg:tags":[
        "house",
        "guest"
    ],
    "wof:name":"Devonia Lodge",
    "wof:placetype":"venue"
},
  "geometry": {"coordinates":[-3.544303,50.469727],"type":"Point"}
}