{
  "type": "Feature",
  "properties": {
    "addr:full":"750 Wimborne Rd Bournemouth Dorset BH9 2DZ",
    "addr:housenumber":"750",
    "addr:postcode":"bh9 2dz",
    "addr:street":"Wimborne Rd",
    "iso:country":"GB",
    "sg:address":"750 Wimborne Rd",
    "sg:city":"Bournemouth",
    "sg:classifiers":[
        {
            "category":"Shopping",
            "subcategory":"Clothing, Apparel, & Fashions",
            "type":"Retail Goods"
        }
    ],
    "sg:postcode":"BH9 2DZ",
    "sg:province":"Dorset",
    "sg:tags":[
        "cap",
        "hat"
    ],
    "wof:name":"Wright,W,& Son (Hat Manufacturers) Ltd",
    "wof:placetype":"venue"
},
  "geometry": {"coordinates":[-1.8773039579,50.7504043579],"type":"Point"}
}