{
  "type": "Feature",
  "properties": {
    "addr:full":"Westfield Street Edinburgh City of Edinburgh EH11 2QY",
    "addr:postcode":"eh11 2qy",
    "addr:street":"Westfield Street",
    "iso:country":"GB",
    "sg:address":"Westfield Street",
    "sg:city":"Edinburgh",
    "sg:classifiers":[
        {
            "category":"Organizations",
            "subcategory":"Membership Organization",
            "type":"Services"
        }
    ],
    "sg:phone":"+44 131 337 6539",
    "sg:postcode":"EH11 2QY",
    "sg:province":"City of Edinburgh",
    "sg:tags":[
        "club"
    ],
    "wof:name":"B M C Club",
    "wof:placetype":"venue"
},
  "geometry": {"coordinates":[-3.238044,55.937317],"type":"Point"}
}