{
  "type": "Feature",
  "properties": {
    "iso:country":"GB",
    "sg:address":"Unit 6 Tower Ct, St Davids Rd",
    "sg:city":"Swansea",
    "sg:classifiers":[
        {
            "category":"Home & Garden",
            "subcategory":"Furniture",
            "type":"Retail Goods"
        }
    ],
    "sg:phone":"+44 1792 781010",
    "sg:postcode":"SA6 8PT",
    "sg:province":"Swansea",
    "wof:name":"Pacific Furniture",
    "wof:placetype":"venue"
},
  "geometry": {"coordinates":[-3.9167430401,51.6607551575],"type":"Point"}
}