{
  "type": "Feature",
  "properties": {
    "iso:country":"GB",
    "sg:address":"Cottage Lane, Westfield",
    "sg:city":"Hastings",
    "sg:classifiers":[
        {
            "category":"Home & Garden",
            "subcategory":"Garden Supply",
            "type":"Retail Goods"
        }
    ],
    "sg:phone":"+44 1424 870186",
    "sg:postcode":"TN35 4RP",
    "sg:province":"East Sussex",
    "sg:tags":[
        "nursery",
        "centre"
    ],
    "wof:name":"The Lodge Nursery",
    "wof:placetype":"venue"
},
  "geometry": {"coordinates":[0.5763,50.910801],"type":"Point"}
}