{
  "type": "Feature",
  "properties": {
    "iso:country":"GB",
    "sg:address":"Fairmount, Innellan",
    "sg:city":"Dunoon",
    "sg:classifiers":[
        {
            "category":"Recreation",
            "subcategory":"Marina",
            "type":"Entertainment"
        }
    ],
    "sg:phone":"+44 1369 830121",
    "sg:postcode":"PA23 7SJ",
    "sg:province":"Argyll and Bute",
    "sg:tags":[
        "mooring",
        "boat"
    ],
    "wof:name":"Toward Moorings & Towage Ltd",
    "wof:placetype":"venue"
},
  "geometry": {"coordinates":[-4.969589,55.883575],"type":"Point"}
}