{
  "type": "Feature",
  "properties": {
    "addr:full":"Union Street Aberdeen Aberdeen City AB10 1JL",
    "addr:postcode":"ab10 1jl",
    "addr:street":"Union Street",
    "iso:country":"GB",
    "sg:address":"Union Street",
    "sg:city":"Aberdeen",
    "sg:classifiers":[
        {
            "category":"Place Of Worship",
            "type":"Public Place"
        }
    ],
    "sg:phone":"+44 1224 643494",
    "sg:postcode":"AB10 1JL",
    "sg:province":"Aberdeen City",
    "wof:name":"KIRK OF ST NICHOLAS",
    "wof:placetype":"venue"
},
  "geometry": {"coordinates":[-2.100154,57.146187],"type":"Point"}
}