{
  "type": "Feature",
  "properties": {
    "addr:full":"165 Chapel Street Airdrie North Lanarkshire ML6 6LN",
    "addr:housenumber":"165",
    "addr:postcode":"ml6 6ln",
    "addr:street":"Chapel Street",
    "iso:country":"GB",
    "sg:address":"165 Chapel Street",
    "sg:city":"Airdrie",
    "sg:classifiers":[
        {
            "category":"Communications",
            "subcategory":"Film & Video Production",
            "type":"Services"
        }
    ],
    "sg:postcode":"ML6 6LN",
    "sg:province":"North Lanarkshire",
    "sg:tags":[
        "tv"
    ],
    "wof:name":"A Perwaiz",
    "wof:placetype":"venue"
},
  "geometry": {"coordinates":[-3.9768691063,55.872631073],"type":"Point"}
}