{
  "type": "Feature",
  "properties": {
    "addr:full":"25 Church Road, Brampton Huntingdon Bedfordshire PE28 4PF",
    "addr:housenumber":"25",
    "addr:postcode":"pe28 4pf",
    "addr:street":"Church Road",
    "iso:country":"GB",
    "sg:address":"25 Church Road, Brampton",
    "sg:city":"Huntingdon",
    "sg:classifiers":[
        {
            "category":"Building & Trades",
            "subcategory":"Construction",
            "type":"Services"
        }
    ],
    "sg:postcode":"PE28 4PF",
    "sg:province":"Bedfordshire",
    "sg:tags":[
        "builder"
    ],
    "wof:name":"A C V Developments Ltd.",
    "wof:placetype":"venue"
},
  "geometry": {"coordinates":[-0.219479993,52.3208007812],"type":"Point"}
}