{
  "type": "Feature",
  "properties": {
    "addr:full":"36 Upperkirkgate Aberdeen Aberdeen City AB10 1BA",
    "addr:housenumber":"36",
    "addr:postcode":"ab10 1ba",
    "addr:street":"Upperkirkgate Aberdeen",
    "iso:country":"GB",
    "sg:address":"36 Upperkirkgate",
    "sg:city":"Aberdeen",
    "sg:classifiers":[
        {
            "category":"Professional",
            "subcategory":"Engineering",
            "type":"Services"
        }
    ],
    "sg:phone":"+44 1224 648651",
    "sg:postcode":"AB10 1BA",
    "sg:province":"Aberdeen City",
    "sg:tags":[
        "consulting",
        "engineer"
    ],
    "wof:name":"Dovra Safetec Ltd",
    "wof:placetype":"venue"
},
  "geometry": {"coordinates":[-2.098607,57.148682],"type":"Point"}
}