{
  "type": "Feature",
  "properties": {
    "iso:country":"GB",
    "sg:address":"Eisteddfa High Street",
    "sg:city":"Harlech",
    "sg:classifiers":[
        {
            "category":"Shopping",
            "subcategory":"Clothing, Apparel, & Fashions",
            "type":"Retail Goods"
        }
    ],
    "sg:phone":"+44 1766 780253",
    "sg:postcode":"LL46 2YA",
    "sg:province":"Gwynedd",
    "sg:tags":[
        "shop"
    ],
    "wof:name":"S & D Roberts",
    "wof:placetype":"venue"
},
  "geometry": {"coordinates":[-4.1106038094,52.860824585],"type":"Point"}
}