{
  "type": "Feature",
  "properties": {
    "addr:full":"Leningrad Square, Civic Centre, Wythenshawe Manchester Greater Manchester M22 5RX",
    "addr:postcode":"m22 5rx",
    "addr:street":"Leningrad Square",
    "iso:country":"GB",
    "sg:address":"Leningrad Square, Civic Centre, Wythenshawe",
    "sg:city":"Manchester",
    "sg:classifiers":[
        {
            "category":"Government",
            "subcategory":"City Hall",
            "type":"Public Place"
        }
    ],
    "sg:phone":"+44 161 935 4010",
    "sg:postcode":"M22 5RX",
    "sg:province":"Greater Manchester",
    "wof:name":"Wythenshawe Forum Halls",
    "wof:placetype":"venue"
},
  "geometry": {"coordinates":[-2.26452,53.380531],"type":"Point"}
}