{
  "type": "Feature",
  "properties": {
    "addr:full":"Johnston Clo Gloucester Gloucestershire GL19 3RR",
    "addr:postcode":"gl19 3rr",
    "iso:country":"GB",
    "sg:address":"Johnston Clo",
    "sg:city":"Gloucester",
    "sg:classifiers":[
        {
            "category":"Government",
            "subcategory":"Office",
            "type":"Public Place"
        }
    ],
    "sg:phone":"+44 1452 840542",
    "sg:postcode":"GL19 3RR",
    "sg:province":"Gloucestershire",
    "sg:tags":[
        "local"
    ],
    "wof:name":"Johnston Close Sheltered Housing",
    "wof:placetype":"venue"
},
  "geometry": {"coordinates":[-2.310229063,51.9582481384],"type":"Point"}
}