{
  "type": "Feature",
  "properties": {
    "addr:full":"50 High Street Paisley Renfrewshire PA1 2DJ",
    "addr:housenumber":"50",
    "addr:postcode":"pa1 2dj",
    "addr:street":"High Street",
    "iso:country":"GB",
    "sg:address":"50 High Street",
    "sg:city":"Paisley",
    "sg:classifiers":[
        {
            "category":"Health Services",
            "subcategory":"Optometrist",
            "type":"Services"
        },
        {
            "category":"Shopping",
            "subcategory":"Optician",
            "type":"Retail Goods"
        }
    ],
    "sg:phone":"+44 141 889 4336",
    "sg:postcode":"PA1 2DJ",
    "sg:province":"Renfrewshire",
    "sg:tags":[
        "ophthalmic"
    ],
    "sg:website":"http://www.moptom.com",
    "wof:name":"Murray Opticians",
    "wof:placetype":"venue"
},
  "geometry": {"coordinates":[-4.4286088943,55.8452224731],"type":"Point"}
}