{
  "type": "Feature",
  "properties": {
    "addr:full":"341 Commercial Rd Whitechapel Greater London E1 2PS",
    "addr:housenumber":"341",
    "addr:postcode":"e1 2ps",
    "addr:street":"Commercial Rd",
    "iso:country":"GB",
    "sg:address":"341 Commercial Rd",
    "sg:city":"Whitechapel",
    "sg:classifiers":[
        {
            "category":"Professional",
            "subcategory":"Lawyer & Legal Services",
            "type":"Services"
        }
    ],
    "sg:phone":"+44 20 7791 0432",
    "sg:postcode":"E1 2PS",
    "sg:province":"Greater London",
    "sg:tags":[
        "solicitor"
    ],
    "wof:name":"The Family Law Practice",
    "wof:placetype":"venue"
},
  "geometry": {"coordinates":[-0.0549490005,51.5142707825],"type":"Point"}
}