{
  "type": "Feature",
  "properties": {
    "iso:country":"GB",
    "sg:address":"39 Pontmorlais",
    "sg:city":"Merthyr Tydfil",
    "sg:classifiers":[
        {
            "category":"Personal",
            "subcategory":"Beauty Salon",
            "type":"Services"
        },
        {
            "category":"Personal",
            "subcategory":"Barber",
            "type":"Services"
        }
    ],
    "sg:phone":"+44 1685 723169",
    "sg:postcode":"CF47 8UN",
    "sg:province":"Merthyr Tydfil",
    "sg:tags":[
        "unisex",
        "hairdresser"
    ],
    "wof:name":"Geraldine's Hairdressers",
    "wof:placetype":"venue"
},
  "geometry": {"coordinates":[-3.379349,51.74905],"type":"Point"}
}