{
  "type": "Feature",
  "properties": {
    "addr:full":"Cardiff Rd Mwyndy Pontyclun Bridgend CF72 8XY",
    "addr:postcode":"cf72 8xy",
    "addr:street":"Cardiff Rd;Pontyclun",
    "iso:country":"GB",
    "sg:address":"Cardiff Rd Mwyndy",
    "sg:city":"Pontyclun",
    "sg:classifiers":[
        {
            "category":"Building & Trades",
            "subcategory":"Equipment Rental",
            "type":"Services"
        }
    ],
    "sg:phone":"+44 1443 238224",
    "sg:postcode":"CF72 8XY",
    "sg:province":"Bridgend",
    "sg:tags":[
        "plant",
        "machinery"
    ],
    "wof:name":"Brunswick Plant Ltd",
    "wof:placetype":"venue"
},
  "geometry": {"coordinates":[-3.3624770641,51.5258865356],"type":"Point"}
}