{
  "type": "Feature",
  "properties": {
    "iso:country":"GB",
    "sg:address":"27 Hammersmith Road",
    "sg:city":"Aberdeen",
    "sg:classifiers":[
        {
            "category":"Communications",
            "subcategory":"Film & Video Production",
            "type":"Services"
        },
        {
            "category":"Professional",
            "subcategory":"Art Services",
            "type":"Services"
        }
    ],
    "sg:phone":"+44 1224 319246",
    "sg:postcode":"AB10 6NA",
    "sg:province":"Aberdeen City",
    "sg:tags":[
        "illustrator",
        "artist"
    ],
    "wof:name":"Bracadale Art",
    "wof:placetype":"venue"
},
  "geometry": {"coordinates":[-2.127954,57.133045],"type":"Point"}
}