{
  "type": "Feature",
  "properties": {
    "iso:country":"GB",
    "sg:address":"16 Linton Dann Close, Hoo",
    "sg:city":"Rochester",
    "sg:classifiers":[
        {
            "category":"Home & Garden",
            "subcategory":"Household Appliances",
            "type":"Retail Goods"
        },
        {
            "category":"Wholesale",
            "subcategory":"Electrical",
            "type":"Manufacturing & Wholesale Goods"
        },
        {
            "category":"Building & Trades",
            "subcategory":"Electrical",
            "type":"Services"
        }
    ],
    "sg:phone":"+44 1634 250915",
    "sg:postcode":"ME3 9DQ",
    "sg:province":"Kent",
    "sg:tags":[
        "equipment",
        "refrigeration",
        "contractor",
        "air conditioning"
    ],
    "wof:name":"C T Refrigeration Services",
    "wof:placetype":"venue"
},
  "geometry": {"coordinates":[0.553025,51.425137],"type":"Point"}
}