{
  "type": "Feature",
  "properties": {
    "addr:full":"Quarrendon School, Weedon Rd Aylesbury Buckinghamshire HP19 3PG",
    "addr:postcode":"hp19 3pg",
    "addr:street":"Weedon Rd",
    "iso:country":"GB",
    "sg:address":"Quarrendon School, Weedon Rd",
    "sg:city":"Aylesbury",
    "sg:classifiers":[
        {
            "category":"Community Center",
            "subcategory":"Youth",
            "type":"Public Place"
        }
    ],
    "sg:phone":"+44 1296 482768",
    "sg:postcode":"HP19 3PG",
    "sg:province":"Buckinghamshire",
    "sg:tags":[
        "organisation",
        "centre"
    ],
    "wof:name":"Quarrendon Youth Centre",
    "wof:placetype":"venue"
},
  "geometry": {"coordinates":[-0.8316699862,51.8263015747],"type":"Point"}
}