{
  "type": "Feature",
  "properties": {
    "iso:country":"GB",
    "sg:address":"153 Tottenham Lane",
    "sg:city":"London",
    "sg:classifiers":[
        {
            "category":"Fast Food",
            "type":"Food & Drink"
        },
        {
            "category":"Restaurant",
            "type":"Food & Drink"
        }
    ],
    "sg:phone":"+44 20 8341 2964",
    "sg:postcode":"N8 9BT",
    "sg:province":"Greater London",
    "sg:tags":[
        "away",
        "indian",
        "take"
    ],
    "wof:name":"Kamil Bengal Restaurant",
    "wof:placetype":"venue"
},
  "geometry": {"coordinates":[-0.119661,51.582035],"type":"Point"}
}