{
  "type": "Feature",
  "properties": {
    "addr:full":"Acorn Ho, Altrincham Rd Wilmslow Cheshire SK9 4JE",
    "addr:postcode":"sk9 4je",
    "addr:street":"Altrincham Rd",
    "iso:country":"GB",
    "sg:address":"Acorn Ho, Altrincham Rd",
    "sg:city":"Wilmslow",
    "sg:classifiers":[
        {
            "category":"Professional",
            "subcategory":"Management & Consulting",
            "type":"Services"
        }
    ],
    "sg:phone":"+44 1625 520763",
    "sg:postcode":"SK9 4JE",
    "sg:province":"Cheshire",
    "sg:tags":[
        "conservation"
    ],
    "wof:name":"National Trust The",
    "wof:placetype":"venue"
},
  "geometry": {"coordinates":[-2.256793,53.337421],"type":"Point"}
}