{
  "type": "Feature",
  "properties": {
    "addr:full":"39b Walton Street Tadworth Surrey KT20 7RR",
    "addr:housenumber":"39b",
    "addr:postcode":"kt20 7rr",
    "addr:street":"Walton Street",
    "iso:country":"GB",
    "sg:address":"39b Walton Street",
    "sg:city":"Tadworth",
    "sg:classifiers":[
        {
            "category":"Home & Garden",
            "subcategory":"Home Furnishings",
            "type":"Retail Goods"
        }
    ],
    "sg:postcode":"KT20 7RR",
    "sg:province":"Surrey",
    "sg:tags":[
        "homefurnishings"
    ],
    "wof:name":"F & R Restoration",
    "wof:placetype":"venue"
},
  "geometry": {"coordinates":[-0.2448270023,51.2829704285],"type":"Point"}
}