{
  "type": "Feature",
  "properties": {
    "iso:country":"GB",
    "sg:address":"7 Flood La",
    "sg:city":"Twickenham",
    "sg:classifiers":[
        {
            "category":"Professional",
            "subcategory":"Art Services",
            "type":"Services"
        }
    ],
    "sg:phone":"+44 20 8892 6236",
    "sg:postcode":"TW1 3NY",
    "sg:province":"Greater London",
    "sg:tags":[
        "graphic",
        "designer"
    ],
    "wof:name":"David Rowley Design",
    "wof:placetype":"venue"
},
  "geometry": {"coordinates":[-0.3259010017,51.4465484619],"type":"Point"}
}