{
  "type": "Feature",
  "properties": {
    "iso:country":"GB",
    "sg:address":"Merrilees Clinic, 18 Kingsdown Road",
    "sg:city":"Epsom",
    "sg:classifiers":[
        {
            "category":"Health Services",
            "subcategory":"Health Practitioner",
            "type":"Services"
        }
    ],
    "sg:phone":"+44 1372 723452",
    "sg:postcode":"KT17 3PU",
    "sg:province":"Surrey",
    "sg:tags":[
        "osteopath"
    ],
    "wof:name":"I J Payne",
    "wof:placetype":"venue"
},
  "geometry": {"coordinates":[-0.24922,51.331329],"type":"Point"}
}