{
  "type": "Feature",
  "properties": {
    "addr:full":"200 Burgess Road Southampton Hampshire SO16 3AY",
    "addr:housenumber":"200",
    "addr:postcode":"so16 3ay",
    "addr:street":"Burgess Road",
    "iso:country":"GB",
    "sg:address":"200 Burgess Road",
    "sg:city":"Southampton",
    "sg:classifiers":[
        {
            "category":"Food & Beverages",
            "subcategory":"Groceries & Convenience Stores",
            "type":"Retail Goods"
        }
    ],
    "sg:phone":"+44 23 8067 8110",
    "sg:postcode":"SO16 3AY",
    "sg:province":"Hampshire",
    "wof:name":"Alldays Stores Ltd.",
    "wof:placetype":"venue"
},
  "geometry": {"coordinates":[-1.391637,50.938293],"type":"Point"}
}