{
  "type": "Feature",
  "properties": {
    "addr:full":"169 Cardiff Road Reading Berkshire RG1 8HD",
    "addr:housenumber":"169",
    "addr:postcode":"rg1 8hd",
    "addr:street":"Cardiff Road",
    "iso:country":"GB",
    "sg:address":"169 Cardiff Road",
    "sg:city":"Reading",
    "sg:classifiers":[
        {
            "category":"Professional",
            "subcategory":"Printing & Photocopies",
            "type":"Services"
        }
    ],
    "sg:phone":"+44 118 939 4111",
    "sg:postcode":"RG1 8HD",
    "sg:province":"Berkshire",
    "sg:tags":[
        "print",
        "finisher"
    ],
    "wof:name":"T & T Print Finishers",
    "wof:placetype":"venue"
},
  "geometry": {"coordinates":[-0.985307,51.461418],"type":"Point"}
}