{
  "type": "Feature",
  "properties": {
    "addr:full":"Collaberie, Welcombe Bideford Devon EX39 6HF",
    "addr:postcode":"ex39 6hf",
    "iso:country":"GB",
    "sg:address":"Collaberie, Welcombe",
    "sg:city":"Bideford",
    "sg:classifiers":[
        {
            "category":"Farming",
            "subcategory":"Livestock Farm",
            "type":"Manufacturing & Wholesale Goods"
        },
        {
            "category":"Farming",
            "subcategory":"Farm",
            "type":"Manufacturing & Wholesale Goods"
        }
    ],
    "sg:phone":"+44 1288 331391",
    "sg:postcode":"EX39 6HF",
    "sg:province":"Devon",
    "sg:tags":[
        "mixed",
        "crop",
        "others"
    ],
    "wof:name":"R J Wade",
    "wof:placetype":"venue"
},
  "geometry": {"coordinates":[-4.522163868,50.9376945496],"type":"Point"}
}