{
  "type": "Feature",
  "properties": {
    "addr:full":"115 Gloucester Place London Greater London W1U 6JS",
    "addr:housenumber":"115",
    "addr:postcode":"w1u 6js",
    "addr:street":"Gloucester Place",
    "iso:country":"GB",
    "sg:address":"115 Gloucester Place",
    "sg:city":"London",
    "sg:classifiers":[
        {
            "category":"Professional",
            "subcategory":"Lawyer & Legal Services",
            "type":"Services"
        }
    ],
    "sg:phone":"+44 20 7224 3300",
    "sg:postcode":"W1U 6JS",
    "sg:province":"Greater London",
    "sg:tags":[
        "solicitor"
    ],
    "wof:name":"Hogan Lisle Solicitors",
    "wof:placetype":"venue"
},
  "geometry": {"coordinates":[-0.159009,51.519001],"type":"Point"}
}