{
  "type": "Feature",
  "properties": {
    "iso:country":"GB",
    "sg:address":"44 Marlbrook Lane, Marlbrook",
    "sg:city":"Bromsgrove",
    "sg:classifiers":[
        {
            "category":"Real Estate",
            "subcategory":"Real Estate Services",
            "type":"Services"
        },
        {
            "category":"Retail",
            "subcategory":"Repair Shop",
            "type":"Services"
        }
    ],
    "sg:phone":"+44 121 445 3618",
    "sg:postcode":"B60 1HN",
    "sg:province":"Worcestershire",
    "sg:tags":[
        "property",
        "maintenance"
    ],
    "wof:name":"Lawton Property Services",
    "wof:placetype":"venue"
},
  "geometry": {"coordinates":[-2.0338480473,52.3718605042],"type":"Point"}
}