{
  "type": "Feature",
  "properties": {
    "addr:full":"Wymering Road Portsmouth Hampshire PO2 7HX",
    "addr:postcode":"hampshire po2 7hx",
    "addr:street":"Wymering Road",
    "iso:country":"GB",
    "sg:address":"Wymering Road",
    "sg:city":"Portsmouth",
    "sg:classifiers":[
        {
            "category":"Education",
            "subcategory":"School",
            "type":"Public Place"
        },
        {
            "category":"Government",
            "subcategory":"Office",
            "type":"Public Place"
        }
    ],
    "sg:phone":"+44 23 9266 9964",
    "sg:postcode":"PO2 7HX",
    "sg:province":"Hampshire",
    "sg:tags":[
        "local",
        "authority"
    ],
    "wof:name":"Portsmouth City Council",
    "wof:placetype":"venue"
},
  "geometry": {"coordinates":[-1.073944,50.812634],"type":"Point"}
}