{
  "type": "Feature",
  "properties": {
    "iso:country":"GB",
    "sg:address":"Arndale Centre, Royalty Mall",
    "sg:city":"Morecambe",
    "sg:classifiers":[
        {
            "category":"Shopping",
            "subcategory":"Catalog Store",
            "type":"Retail Goods"
        }
    ],
    "sg:phone":"+44 1524 832411",
    "sg:postcode":"LA4 5DH",
    "sg:province":"Lancashire",
    "sg:tags":[
        "catalogue",
        "showroom"
    ],
    "wof:name":"Argos Ltd.",
    "wof:placetype":"venue"
},
  "geometry": {"coordinates":[-2.854494,54.070129],"type":"Point"}
}