{
  "type": "Feature",
  "properties": {
    "addr:full":"114 Middlesex St Whitechapel Greater London E1 7JH",
    "addr:housenumber":"114",
    "addr:postcode":"e1 7jh",
    "addr:street":"Middlesex St",
    "iso:country":"GB",
    "sg:address":"114 Middlesex St",
    "sg:city":"Whitechapel",
    "sg:classifiers":[
        {
            "category":"Professional",
            "subcategory":"Employment Agencies",
            "type":"Services"
        }
    ],
    "sg:phone":"+44 20 7806 1420",
    "sg:postcode":"E1 7JH",
    "sg:province":"Greater London",
    "sg:tags":[
        "consultant"
    ],
    "wof:name":"McDougal Boyall",
    "wof:placetype":"venue"
},
  "geometry": {"coordinates":[-0.078427,51.518063],"type":"Point"}
}