{
  "type": "Feature",
  "properties": {
    "addr:full":"14 Affleck Av Tamworth Staffordshire B78 3NJ",
    "addr:housenumber":"14",
    "addr:postcode":"b78 3nj",
    "addr:street":"Affleck Av",
    "iso:country":"GB",
    "sg:address":"14 Affleck Av",
    "sg:city":"Tamworth",
    "sg:classifiers":[
        {
            "category":"Arts & Performance",
            "subcategory":"Music",
            "type":"Entertainment"
        }
    ],
    "sg:phone":"+44 1827 251193",
    "sg:postcode":"B78 3NJ",
    "sg:province":"Staffordshire",
    "sg:tags":[
        "mobile",
        "disco"
    ],
    "wof:name":"Bobby Gee",
    "wof:placetype":"venue"
},
  "geometry": {"coordinates":[-1.7256259918,52.6187934875],"type":"Point"}
}