{
  "type": "Feature",
  "properties": {
    "addr:full":"368 Court Oak Road Birmingham West Midlands B32 2DY",
    "addr:housenumber":"368",
    "addr:postcode":"b32 2dy",
    "addr:street":"Court Oak Road",
    "iso:country":"GB",
    "sg:address":"368 Court Oak Road",
    "sg:city":"Birmingham",
    "sg:classifiers":[
        {
            "category":"Food & Beverages",
            "subcategory":"Supermarket",
            "type":"Retail Goods"
        }
    ],
    "sg:phone":"+44 121 427 2821",
    "sg:postcode":"B32 2DY",
    "sg:province":"West Midlands",
    "wof:name":"Court Oak Stores",
    "wof:placetype":"venue"
},
  "geometry": {"coordinates":[-1.9815330505,52.4604797363],"type":"Point"}
}