{
  "type": "Feature",
  "properties": {
    "iso:country":"GB",
    "sg:address":"432 Poole Road, Branksome",
    "sg:city":"Poole",
    "sg:classifiers":[
        {
            "category":"Real Estate",
            "subcategory":"Real Estate Agent",
            "type":"Services"
        }
    ],
    "sg:phone":"+44 1202 764629",
    "sg:postcode":"BH12 1DF",
    "sg:province":"Dorset",
    "wof:name":"Rosser & Sturman",
    "wof:placetype":"venue"
},
  "geometry": {"coordinates":[-1.920758,50.727104],"type":"Point"}
}