{
  "type": "Feature",
  "properties": {
    "iso:country":"GB",
    "sg:address":"43-47 Upper North Street",
    "sg:city":"Brighton",
    "sg:classifiers":[
        {
            "category":"Shopping",
            "subcategory":"Antiques",
            "type":"Retail Goods"
        }
    ],
    "sg:phone":"+44 1273 328706",
    "sg:postcode":"BN1 3FH",
    "sg:province":"East Sussex",
    "wof:name":"E & B White",
    "wof:placetype":"venue"
},
  "geometry": {"coordinates":[-0.14796,50.825191],"type":"Point"}
}