{
  "type": "Feature",
  "properties": {
    "addr:full":"Gainsborough House, Portland St Manchester Greater Manchester M1 6DN",
    "addr:postcode":"m1 6dn",
    "addr:street":"Portland St",
    "iso:country":"GB",
    "sg:address":"Gainsborough House, Portland St",
    "sg:city":"Manchester",
    "sg:classifiers":[
        {
            "category":"Shopping",
            "subcategory":"Books",
            "type":"Retail Goods"
        }
    ],
    "sg:phone":"+44 161 236 1305",
    "sg:postcode":"M1 6DN",
    "sg:province":"Greater Manchester",
    "wof:name":"Environment Times",
    "wof:placetype":"venue"
},
  "geometry": {"coordinates":[-2.240789,53.47718],"type":"Point"}
}