{
  "type": "Feature",
  "properties": {
    "addr:full":"408 Green Lanes London Greater London N13 5XG",
    "addr:housenumber":"408",
    "addr:postcode":"n13 5xg",
    "addr:street":"Green Lanes",
    "iso:country":"GB",
    "sg:address":"408 Green Lanes",
    "sg:city":"London",
    "sg:classifiers":[
        {
            "category":"Shopping",
            "subcategory":"Clothing, Apparel, & Fashions",
            "type":"Retail Goods"
        }
    ],
    "sg:phone":"+44 20 8804 3289",
    "sg:postcode":"N13 5XG",
    "sg:province":"Greater London",
    "sg:tags":[
        "clothing",
        "fabric"
    ],
    "wof:name":"Lutine Shirt Co",
    "wof:placetype":"venue"
},
  "geometry": {"coordinates":[-0.1052860022,51.6218681335],"type":"Point"}
}