{
  "type": "Feature",
  "properties": {
    "addr:full":"344 Morningside Road Edinburgh City of Edinburgh EH10 4QL",
    "addr:housenumber":"344",
    "addr:postcode":"eh10 4ql",
    "addr:street":"Morningside Road",
    "iso:country":"GB",
    "sg:address":"344 Morningside Road",
    "sg:city":"Edinburgh",
    "sg:classifiers":[
        {
            "category":"Organizations",
            "subcategory":"Non-profit Organization",
            "type":"Services"
        }
    ],
    "sg:phone":"+44 131 452 9610",
    "sg:postcode":"EH10 4QL",
    "sg:province":"City of Edinburgh",
    "sg:tags":[
        "organisation",
        "voluntary",
        "charity"
    ],
    "wof:name":"Disability Scotland",
    "wof:placetype":"venue"
},
  "geometry": {"coordinates":[-3.209309,55.92725],"type":"Point"}
}