{
  "type": "Feature",
  "properties": {
    "iso:country":"GB",
    "sg:address":"199 Thwaites Brow Road",
    "sg:city":"Keighley",
    "sg:classifiers":[
        {
            "category":"Professional",
            "subcategory":"Computer Services",
            "type":"Services"
        }
    ],
    "sg:postcode":"BD21 4SW",
    "sg:province":"West Yorkshire",
    "sg:tags":[
        "system",
        "software"
    ],
    "wof:name":"Ibis Consultants",
    "wof:placetype":"venue"
},
  "geometry": {"coordinates":[-1.8854919672,53.862953186],"type":"Point"}
}