{
  "type": "Feature",
  "properties": {
    "addr:full":"Mattersey Hall, Retford Road, Mattersey Doncaster Lincolnshire DN10 5HD",
    "addr:housenumber":"mattersey",
    "addr:postcode":"dn10 5hd",
    "addr:street":"Retford Road",
    "iso:country":"GB",
    "sg:address":"Mattersey Hall, Retford Road, Mattersey",
    "sg:city":"Doncaster",
    "sg:classifiers":[
        {
            "category":"Education",
            "subcategory":"University",
            "type":"Public Place"
        }
    ],
    "sg:postcode":"DN10 5HD",
    "sg:province":"Lincolnshire",
    "sg:tags":[
        "higher"
    ],
    "wof:name":"Mattersey Hall Bible College",
    "wof:placetype":"venue"
},
  "geometry": {"coordinates":[-0.9649890065,53.3960609436],"type":"Point"}
}