{
  "type": "Feature",
  "properties": {
    "addr:full":"Boothferry Road Goole East Riding of Yorkshire DN14 6SR",
    "addr:postcode":"dn14 6sr",
    "addr:street":"Boothferry Road",
    "iso:country":"GB",
    "sg:address":"Boothferry Road",
    "sg:city":"Goole",
    "sg:classifiers":[
        {
            "category":"Education",
            "subcategory":"University",
            "type":"Public Place"
        }
    ],
    "sg:phone":"+44 1405 762420",
    "sg:postcode":"DN14 6SR",
    "sg:province":"East Riding of Yorkshire",
    "sg:tags":[
        "adult"
    ],
    "wof:name":"Goole College",
    "wof:placetype":"venue"
},
  "geometry": {"coordinates":[-0.8841819763,53.7072982788],"type":"Point"}
}