{
  "type": "Feature",
  "properties": {
    "addr:full":"74 Wheatlands, Heston Hounslow Greater London TW5 0SB",
    "addr:housenumber":"74",
    "addr:postcode":"tw5 0sb",
    "addr:street":"Wheatlands Heston",
    "iso:country":"GB",
    "sg:address":"74 Wheatlands, Heston",
    "sg:city":"Hounslow",
    "sg:classifiers":[
        {
            "category":"Building & Trades",
            "subcategory":"Construction",
            "type":"Services"
        }
    ],
    "sg:phone":"+44 20 8572 1469",
    "sg:postcode":"TW5 0SB",
    "sg:province":"Greater London",
    "sg:tags":[
        "builder"
    ],
    "wof:name":"A R K (U K) Ltd",
    "wof:placetype":"venue"
},
  "geometry": {"coordinates":[-0.36921,51.485634],"type":"Point"}
}