{
  "type": "Feature",
  "properties": {
    "addr:full":"Hindpool Close Hartlepool Durham TS24 0TB",
    "addr:postcode":"ts24 0tb",
    "addr:street":"Hindpool Close",
    "iso:country":"GB",
    "sg:address":"Hindpool Close",
    "sg:city":"Hartlepool",
    "sg:classifiers":[
        {
            "category":"Social Services",
            "subcategory":"Adult Care",
            "type":"Services"
        },
        {
            "category":"Government",
            "subcategory":"Office",
            "type":"Public Place"
        }
    ],
    "sg:phone":"+44 1429 232306",
    "sg:postcode":"TS24 0TB",
    "sg:province":"Durham",
    "sg:tags":[
        "housing",
        "local",
        "sheltered"
    ],
    "wof:name":"Old Boys Field Bungalows Sheltered Housing",
    "wof:placetype":"venue"
},
  "geometry": {"coordinates":[-1.2093789577,54.7015113831],"type":"Point"}
}