{"geometry":{"type":"Point","coordinates":[-2.280119,53.394291]},"type":"Feature","id":102560635,"bbox":[-2.280119,53.394291,-2.280119,53.394291],"properties":{"sg:province":"Cheshire","sg:tags":["chip"],"geom:longitude":-2.280119,"wof:breaches":[],"sg:href":"http://api.simplegeo.com/1.0/features/SG_49nzO7pqWBkWpweVF6YkNX_53.394291_-2.280119@1300740015.json","sg:owner":"simplegeo","sg:postcode":"M23 1EX","geom:latitude":53.394291,"sg:classifiers":[{"category":"Food & Beverages","type":"Retail Goods","subcategory":"Meat & Fish"}],"sg:address":"26 Greenbrow Road","sg:phone":"+44 161 998 3568","wof:hierarchy":[{"locality_id":101913961,"venue_id":102560635,"country_id":85633159,"neighbourhood_id":85785441,"region_id":85683651}],"geom:area":0.000000,"sg:city":"Manchester","wof:lastmodified":1438093315,"iso:country":"GB","wof:geomhash":"f33be87ce354c3141dd31439e31ca441","wof:name":"New Star","wof:belongsto":[101913961,85633159,85785441,85683651],"src:geom":"simplegeo","wof:placetype":"venue","wof:supersedes":[],"wof:id":102560635,"wof:superseded_by":[],"wof:concordances":{"sg:id":"SG_49nzO7pqWBkWpweVF6YkNX_53.394291_-2.280119@1300740015"},"wof:parent_id":85785441}}