{
  "type": "Feature",
  "properties": {
    "iso:country":"GB",
    "sg:address":"26 Greenbrow Road",
    "sg:city":"Manchester",
    "sg:classifiers":[
        {
            "category":"Food & Beverages",
            "subcategory":"Meat & Fish",
            "type":"Retail Goods"
        }
    ],
    "sg:href":"http://api.simplegeo.com/1.0/features/SG_49nzO7pqWBkWpweVF6YkNX_53.394291_-2.280119@1300740015.json",
    "sg:phone":"+44 161 998 3568",
    "sg:postcode":"M23 1EX",
    "sg:province":"Cheshire",
    "sg:tags":[
        "chip"
    ],
    "wof:name":"New Star",
    "wof:placetype":"venue"
},
  "geometry": {"coordinates":[-2.280119,53.394291],"type":"Point"}
}