{
  "type": "Feature",
  "properties": {
    "addr:full":"Gloucester Avenue Slough Berkshire SL1 3AH",
    "addr:postcode":"sl1 3ah",
    "addr:street":"Gloucester Avenue",
    "iso:country":"GB",
    "sg:address":"Gloucester Avenue",
    "sg:city":"Slough",
    "sg:classifiers":[
        {
            "category":"Education",
            "subcategory":"School",
            "type":"Public Place"
        }
    ],
    "sg:phone":"+44 1753 531760",
    "sg:postcode":"SL1 3AH",
    "sg:province":"Berkshire",
    "sg:tags":[
        "local",
        "authority"
    ],
    "wof:name":"Baylis Court School",
    "wof:placetype":"venue"
},
  "geometry": {"coordinates":[-0.609874,51.524815],"type":"Point"}
}