{
  "type": "Feature",
  "properties": {
    "addr:full":"Tavistock Farm, Colchester Rd, Salcott Cum Virley Maldon Essex CM9 8HG",
    "addr:postcode":"cm9 8hg",
    "addr:street":"Colchester Rd;Cum Virley",
    "iso:country":"GB",
    "sg:address":"Tavistock Farm, Colchester Rd, Salcott Cum Virley",
    "sg:city":"Maldon",
    "sg:classifiers":[
        {
            "category":"Utilities",
            "subcategory":"Natural Gas",
            "type":"Services"
        }
    ],
    "sg:phone":"+44 1621 860399",
    "sg:postcode":"CM9 8HG",
    "sg:province":"Essex",
    "sg:tags":[
        "blacksmith"
    ],
    "wof:name":"T & G Fabrications",
    "wof:placetype":"venue"
},
  "geometry": {"coordinates":[0.824056983,51.7883529663],"type":"Point"}
}