{
  "type": "Feature",
  "properties": {
    "addr:full":"Byland Avenue York North Yorkshire YO31 9AA",
    "addr:postcode":"yo31 9aa",
    "addr:street":"Byland Avenue",
    "iso:country":"GB",
    "sg:address":"Byland Avenue",
    "sg:city":"York",
    "sg:classifiers":[
        {
            "category":"Education",
            "subcategory":"Preschool",
            "type":"Public Place"
        }
    ],
    "sg:phone":"+44 1904 625684",
    "sg:postcode":"YO31 9AA",
    "sg:province":"North Yorkshire",
    "sg:tags":[
        "pre-school",
        "playgroups"
    ],
    "wof:name":"Bell Farm Adventure Playground",
    "wof:placetype":"venue"
},
  "geometry": {"coordinates":[-1.0704159737,53.9772148132],"type":"Point"}
}