{
  "type": "Feature",
  "properties": {
    "addr:full":"Unit 6 Priory Works, Priory Avenue Southend On Sea Essex SS2 6LD",
    "addr:housenumber":"unit 6;works",
    "addr:postcode":"ss2 6ld",
    "addr:street":"Priory;Priory Avenue",
    "iso:country":"GB",
    "sg:address":"Unit 6 Priory Works, Priory Avenue",
    "sg:city":"Southend On Sea",
    "sg:classifiers":[
        {
            "category":"Retail",
            "subcategory":"Auto Repair",
            "type":"Services"
        }
    ],
    "sg:phone":"+44 1702 613632",
    "sg:postcode":"SS2 6LD",
    "sg:province":"Essex",
    "sg:tags":[
        "body",
        "car"
    ],
    "wof:name":"R P Auto's",
    "wof:placetype":"venue"
},
  "geometry": {"coordinates":[0.7096499801,51.5503501892],"type":"Point"}
}