{
  "type": "Feature",
  "properties": {
    "addr:full":"5a Parson Street London Greater London NW4 1QD",
    "addr:housenumber":"5a",
    "addr:postcode":"nw4 1qd",
    "addr:street":"Parson Street",
    "iso:country":"GB",
    "sg:address":"5a Parson Street",
    "sg:city":"London",
    "sg:classifiers":[
        {
            "category":"Shopping",
            "subcategory":"Computers & Home Electronics",
            "type":"Retail Goods"
        }
    ],
    "sg:phone":"+44 20 8202 4777",
    "sg:postcode":"NW4 1QD",
    "sg:province":"Greater London",
    "sg:tags":[
        "equipment",
        "video",
        "cctv"
    ],
    "wof:name":"Micro Surveillance Products",
    "wof:placetype":"venue"
},
  "geometry": {"coordinates":[-0.2217810005,51.590259552],"type":"Point"}
}