{
  "type": "Feature",
  "properties": {
    "addr:full":"48 Exeter Road Exmouth Devon EX8 1PY",
    "addr:housenumber":"48",
    "addr:postcode":"ex8 1py",
    "addr:street":"Exeter Road",
    "iso:country":"GB",
    "sg:address":"48 Exeter Road",
    "sg:city":"Exmouth",
    "sg:classifiers":[
        {
            "category":"Food & Beverages",
            "subcategory":"Fruits & Vegetables",
            "type":"Retail Goods"
        }
    ],
    "sg:phone":"+44 1395 272460",
    "sg:postcode":"EX8 1PY",
    "sg:province":"Devon",
    "sg:tags":[
        "greengrocer"
    ],
    "wof:name":"Lakes Stores",
    "wof:placetype":"venue"
},
  "geometry": {"coordinates":[-3.411006,50.62215],"type":"Point"}
}