{
  "type": "Feature",
  "properties": {
    "iso:country":"GB",
    "sg:address":"Mill Hill Corner, 90 Normanton Road",
    "sg:city":"Derby",
    "sg:classifiers":[
        {
            "category":"Home & Garden",
            "subcategory":"Home Furnishings",
            "type":"Retail Goods"
        }
    ],
    "sg:phone":"+44 1332 341155",
    "sg:postcode":"DE1 2GP",
    "sg:province":"Derbyshire",
    "sg:tags":[
        "beds",
        "bedding",
        "blanket"
    ],
    "wof:name":"M H C (Derby) Ltd.",
    "wof:placetype":"venue"
},
  "geometry": {"coordinates":[-1.483684,52.925171],"type":"Point"}
}