{
  "type": "Feature",
  "properties": {
    "addr:full":"3 George Street, Balsall Heath Birmingham West Midlands B12 9RG",
    "addr:housenumber":"3",
    "addr:postcode":"b12 9rg",
    "addr:street":"George Street",
    "iso:country":"GB",
    "sg:address":"3 George Street, Balsall Heath",
    "sg:city":"Birmingham",
    "sg:classifiers":[
        {
            "category":"Professional",
            "subcategory":"Engineering",
            "type":"Services"
        }
    ],
    "sg:phone":"+44 121 446 6776",
    "sg:postcode":"B12 9RG",
    "sg:province":"West Midlands",
    "sg:tags":[
        "contractor",
        "electrical",
        "engineer"
    ],
    "wof:name":"D Groves Ltd.",
    "wof:placetype":"venue"
},
  "geometry": {"coordinates":[-1.8905949593,52.4570503235],"type":"Point"}
}