{
  "type": "Feature",
  "properties": {
    "addr:full":"Regal House, 61 Rodney Road Cheltenham Gloucestershire GL50 1HX",
    "addr:housenumber":"61",
    "addr:postcode":"gl50 1hx",
    "addr:street":"Rodney Road",
    "iso:country":"GB",
    "sg:address":"Regal House, 61 Rodney Road",
    "sg:city":"Cheltenham",
    "sg:classifiers":[
        {
            "category":"Military Area",
            "subcategory":"Air Force Base",
            "type":"Public Place"
        }
    ],
    "sg:phone":"+44 1242 263883",
    "sg:postcode":"GL50 1HX",
    "sg:province":"Gloucestershire",
    "sg:tags":[
        "taxi",
        "hire",
        "private"
    ],
    "wof:name":"Cheltax Ltd.",
    "wof:placetype":"venue"
},
  "geometry": {"coordinates":[-2.0754160881,51.898235321],"type":"Point"}
}