{
  "type": "Feature",
  "properties": {
    "addr:full":"14 Greenbank Av Plymouth Devon PL4 8PT",
    "addr:housenumber":"14",
    "addr:postcode":"pl4 8pt",
    "addr:street":"Greenbank Av",
    "iso:country":"GB",
    "sg:address":"14 Greenbank Av",
    "sg:city":"Plymouth",
    "sg:classifiers":[
        {
            "category":"Health Services",
            "subcategory":"Dentist",
            "type":"Services"
        }
    ],
    "sg:phone":"+44 1752 662986",
    "sg:postcode":"PL4 8PT",
    "sg:province":"Devon",
    "wof:name":"B R Turner",
    "wof:placetype":"venue"
},
  "geometry": {"coordinates":[-4.1265501976,50.3735618591],"type":"Point"}
}