{
  "type": "Feature",
  "properties": {
    "addr:full":"Unit 6/8, Kencot Way Erith Kent DA18 4AB",
    "addr:housenumber":"unit 6 / 8",
    "addr:postcode":"da18 4ab",
    "addr:street":"Kencot Way",
    "iso:country":"GB",
    "sg:address":"Unit 6/8, Kencot Way",
    "sg:city":"Erith",
    "sg:classifiers":[
        {
            "category":"Manufacturing",
            "subcategory":"Metals",
            "type":"Manufacturing & Wholesale Goods"
        }
    ],
    "sg:phone":"+44 20 8312 2411",
    "sg:postcode":"DA18 4AB",
    "sg:province":"Kent",
    "sg:tags":[
        "industry",
        "f-a"
    ],
    "wof:name":"Thames Diecastings",
    "wof:placetype":"venue"
},
  "geometry": {"coordinates":[0.1433950067,51.4954605103],"type":"Point"}
}