{
  "type": "Feature",
  "properties": {
    "addr:full":"31 Sitwell Close Newport Pagnell Buckinghamshire MK16 8QR",
    "addr:housenumber":"31",
    "addr:postcode":"mk16 8qr",
    "addr:street":"Sitwell Close",
    "iso:country":"GB",
    "sg:address":"31 Sitwell Close",
    "sg:city":"Newport Pagnell",
    "sg:classifiers":[
        {
            "category":"Professional",
            "subcategory":"Detective & Security Services",
            "type":"Services"
        }
    ],
    "sg:phone":"+44 1908 612673",
    "sg:postcode":"MK16 8QR",
    "sg:province":"Buckinghamshire",
    "sg:tags":[
        "car"
    ],
    "wof:name":"The Car Alarm Warehouse",
    "wof:placetype":"venue"
},
  "geometry": {"coordinates":[-0.7498409748,52.0904159546],"type":"Point"}
}