{
  "type": "Feature",
  "properties": {
    "iso:country":"GB",
    "sg:address":"Unit F Brooklands Cl",
    "sg:city":"Sunbury On Thames",
    "sg:classifiers":[
        {
            "category":"Communications",
            "type":"Services"
        }
    ],
    "sg:phone":"+44 20 8307 3400",
    "sg:postcode":"TW16 7DX",
    "sg:province":"Surrey",
    "sg:tags":[
        "telecommunication"
    ],
    "wof:name":"Cable & Wireless Communications Ltd",
    "wof:placetype":"venue"
},
  "geometry": {"coordinates":[-0.427229,51.417965],"type":"Point"}
}