{
  "type": "Feature",
  "properties": {
    "iso:country":"GB",
    "sg:address":"5 Heron Court, Craines Farm Road",
    "sg:city":"Basildon",
    "sg:classifiers":[
        {
            "category":"Retail",
            "subcategory":"Storage",
            "type":"Services"
        }
    ],
    "sg:phone":"+44 1268 474608",
    "sg:postcode":"SS14 1DF",
    "sg:province":"Essex",
    "sg:tags":[
        "recording",
        "equipment"
    ],
    "wof:name":"A V Niche Recording Systems",
    "wof:placetype":"venue"
},
  "geometry": {"coordinates":[0.4812380075,51.5726394653],"type":"Point"}
}