{
  "type": "Feature",
  "properties": {
    "iso:country":"GB",
    "sg:address":"Riversdale Way, Newburn Haugh Industrial Estate, Newburn",
    "sg:city":"Newcastle-upon-tyne",
    "sg:classifiers":[
        {
            "category":"Shopping",
            "subcategory":"Stationery & Office Supplies",
            "type":"Retail Goods"
        }
    ],
    "sg:phone":"+44 191 264 5545",
    "sg:postcode":"NE15 8SF",
    "sg:province":"Northumberland",
    "sg:tags":[
        "box",
        "carton"
    ],
    "wof:name":"Integrated Packaging Ltd.",
    "wof:placetype":"venue"
},
  "geometry": {"coordinates":[-1.720794,54.977169],"type":"Point"}
}