{
  "type": "Feature",
  "properties": {
    "iso:country":"GB",
    "sg:address":"31 Eton Wick Road, Eton Wick",
    "sg:city":"Windsor",
    "sg:classifiers":[
        {
            "category":"Shopping",
            "subcategory":"Florist",
            "type":"Retail Goods"
        }
    ],
    "sg:phone":"+44 1753 833225",
    "sg:postcode":"SL4 6LU",
    "sg:province":"Berkshire",
    "wof:name":"Bracken Flowers",
    "wof:placetype":"venue"
},
  "geometry": {"coordinates":[-0.637722,51.497768],"type":"Point"}
}