{
  "type": "Feature",
  "properties": {
    "iso:country":"GB",
    "sg:address":"3-4 St Pauls Buildings",
    "sg:city":"Elland",
    "sg:classifiers":[
        {
            "category":"Food & Beverages",
            "subcategory":"Supermarket",
            "type":"Retail Goods"
        }
    ],
    "sg:phone":"+44 1422 372541",
    "sg:postcode":"HX5 0EX",
    "sg:province":"West Yorkshire",
    "wof:name":"J D Alcock & S",
    "wof:placetype":"venue"
},
  "geometry": {"coordinates":[-1.835879,53.686256],"type":"Point"}
}