{
  "type": "Feature",
  "properties": {
    "iso:country":"GB",
    "sg:address":"274 High Street",
    "sg:city":"Lincoln",
    "sg:classifiers":[
        {
            "category":"Bars & Pubs",
            "type":"Food & Drink"
        }
    ],
    "sg:phone":"+44 1522 589478",
    "sg:postcode":"LN2 1JG",
    "sg:province":"Lincolnshire",
    "sg:tags":[
        "pubs",
        "inn"
    ],
    "wof:name":"Yates' Wine Lodges Ltd.",
    "wof:placetype":"venue"
},
  "geometry": {"coordinates":[-0.539449,53.23151],"type":"Point"}
}