{
  "type": "Feature",
  "properties": {
    "iso:country":"GB",
    "sg:address":"Trendrine Zennor",
    "sg:city":"St Ives",
    "sg:classifiers":[
        {
            "category":"Shopping",
            "subcategory":"Books",
            "type":"Retail Goods"
        }
    ],
    "sg:phone":"+44 1736 796926",
    "sg:postcode":"TR26 3BW",
    "sg:province":"Cornwall",
    "wof:name":"William F Ansell",
    "wof:placetype":"venue"
},
  "geometry": {"coordinates":[-5.5677490234,50.1916732788],"type":"Point"}
}