{
  "type": "Feature",
  "properties": {
    "addr:full":"P O Box 43 Ilkley North Yorkshire LS29 6XA",
    "addr:housenumber":"box 43",
    "addr:postcode":"ls29 6xa",
    "addr:street":"P O",
    "iso:country":"GB",
    "sg:address":"P O Box 43",
    "sg:city":"Ilkley",
    "sg:classifiers":[
        {
            "category":"Shopping",
            "subcategory":"Beauty & Cosmetics",
            "type":"Retail Goods"
        },
        {
            "category":"Communications",
            "type":"Services"
        }
    ],
    "sg:postcode":"LS29 6XA",
    "sg:province":"North Yorkshire",
    "sg:tags":[
        "product",
        "audio-visual"
    ],
    "wof:name":"Styles on Video",
    "wof:placetype":"venue"
},
  "geometry": {"coordinates":[-1.7352739573,53.8953208923],"type":"Point"}
}