{
  "type": "Feature",
  "properties": {
    "iso:country":"GB",
    "sg:address":"128 Essex Rd",
    "sg:city":"Leyton",
    "sg:classifiers":[
        {
            "category":"Place Of Worship",
            "type":"Public Place"
        }
    ],
    "sg:phone":"+44 20 8558 0367",
    "sg:postcode":"E10 6BS",
    "sg:province":"Greater London",
    "wof:name":"Gateway Church Leyton",
    "wof:placetype":"venue"
},
  "geometry": {"coordinates":[-0.004353,51.577003],"type":"Point"}
}