{
  "type": "Feature",
  "properties": {
    "iso:country":"GB",
    "sg:address":"18 Bridge Street",
    "sg:city":"Kington",
    "sg:classifiers":[
        {
            "category":"Professional",
            "subcategory":"Accounting & Tax Preparation",
            "type":"Services"
        }
    ],
    "sg:phone":"+44 1544 230577",
    "sg:postcode":"HR5 3DL",
    "sg:province":"Herefordshire",
    "sg:tags":[
        "accountant"
    ],
    "wof:name":"Bowdler & Co",
    "wof:placetype":"venue"
},
  "geometry": {"coordinates":[-3.0275850296,52.2023048401],"type":"Point"}
}