{
  "type": "Feature",
  "properties": {
    "addr:full":"39a Westgate St Ipswich Suffolk IP1 3DX",
    "addr:housenumber":"39a",
    "addr:postcode":"ip1 3dx",
    "addr:street":"Westgate St",
    "iso:country":"GB",
    "sg:address":"39a Westgate St",
    "sg:city":"Ipswich",
    "sg:classifiers":[
        {
            "category":"Professional",
            "subcategory":"Employment Agencies",
            "type":"Services"
        }
    ],
    "sg:phone":"+44 1473 218789",
    "sg:postcode":"IP1 3DX",
    "sg:province":"Suffolk",
    "sg:tags":[
        "consultant"
    ],
    "wof:name":"Key Executive",
    "wof:placetype":"venue"
},
  "geometry": {"coordinates":[1.150416,52.058613],"type":"Point"}
}