{
  "type": "Feature",
  "properties": {
    "addr:full":"Unit 30 Dinsdale Road, Croft Business Park, Bromborough Wirral Cheshire CH62 3PY",
    "addr:housenumber":"unit 30",
    "addr:postcode":"ch62 3py",
    "addr:street":"Dinsdale Road Croft Business Park",
    "iso:country":"GB",
    "sg:address":"Unit 30 Dinsdale Road, Croft Business Park, Bromborough",
    "sg:city":"Wirral",
    "sg:classifiers":[
        {
            "category":"Wholesale",
            "subcategory":"Machinery & Supplies",
            "type":"Manufacturing & Wholesale Goods"
        }
    ],
    "sg:phone":"+44 151 334 8800",
    "sg:postcode":"CH62 3PY",
    "sg:province":"Cheshire",
    "sg:tags":[
        "hydraulic"
    ],
    "wof:name":"Lorric Hydraumatic (Supplies) Ltd.",
    "wof:placetype":"venue"
},
  "geometry": {"coordinates":[-2.9741590023,53.3394889832],"type":"Point"}
}