{
  "type": "Feature",
  "properties": {
    "addr:full":"3 Wemysshall Road, Ceres Cupar Fife KY15 5LX",
    "addr:housenumber":"3",
    "addr:postcode":"ky15 5lx",
    "addr:street":"Wemysshall Road",
    "iso:country":"GB",
    "sg:address":"3 Wemysshall Road, Ceres",
    "sg:city":"Cupar",
    "sg:classifiers":[
        {
            "category":"Social Services",
            "type":"Services"
        }
    ],
    "sg:phone":"+44 1334 828289",
    "sg:postcode":"KY15 5LX",
    "sg:province":"Fife",
    "sg:tags":[
        "need",
        "disability",
        "special"
    ],
    "wof:name":"Alwyn House",
    "wof:placetype":"venue"
},
  "geometry": {"coordinates":[-2.97894,56.295792],"type":"Point"}
}