{
  "type": "Feature",
  "properties": {
    "addr:full":"1 Interchange Centre, West St Gateshead Tyne and Wear NE8 1BH",
    "addr:housenumber":"1",
    "addr:postcode":"ne8 1bh",
    "addr:street":"Interchange Centre",
    "iso:country":"GB",
    "sg:address":"1 Interchange Centre, West St",
    "sg:city":"Gateshead",
    "sg:classifiers":[
        {
            "category":"Communications",
            "subcategory":"Film & Video Production",
            "type":"Services"
        }
    ],
    "sg:phone":"+44 191 477 2602",
    "sg:postcode":"NE8 1BH",
    "sg:province":"Tyne and Wear",
    "sg:tags":[
        "tv"
    ],
    "wof:name":"Radio Rentals",
    "wof:placetype":"venue"
},
  "geometry": {"coordinates":[-1.6041200161,54.9626693726],"type":"Point"}
}