{
  "type": "Feature",
  "properties": {
    "addr:full":"23 Nyland Road, Nythe Swindon Wiltshire SN3 3RJ",
    "addr:housenumber":"23",
    "addr:postcode":"sn3 3rj",
    "addr:street":"Nyland Road Nythe Swindon",
    "iso:country":"GB",
    "sg:address":"23 Nyland Road, Nythe",
    "sg:city":"Swindon",
    "sg:classifiers":[
        {
            "category":"Freight",
            "type":"Transportation"
        }
    ],
    "sg:postcode":"SN3 3RJ",
    "sg:province":"Wiltshire",
    "sg:tags":[
        "haulage",
        "road"
    ],
    "wof:name":"les Smith Haulage",
    "wof:placetype":"venue"
},
  "geometry": {"coordinates":[-1.7369400263,51.5649719238],"type":"Point"}
}