{
  "type": "Feature",
  "properties": {
    "addr:full":"87 Hampton Rd London Greater London E4 8NP",
    "addr:housenumber":"87",
    "addr:postcode":"e4 8np",
    "addr:street":"Hampton Rd",
    "iso:country":"GB",
    "sg:address":"87 Hampton Rd",
    "sg:city":"London",
    "sg:classifiers":[
        {
            "category":"Home & Garden",
            "subcategory":"Household Appliances",
            "type":"Retail Goods"
        }
    ],
    "sg:postcode":"E4 8NP",
    "sg:province":"Greater London",
    "sg:tags":[
        "electrical"
    ],
    "wof:name":"Socold Refrigeration Services",
    "wof:placetype":"venue"
},
  "geometry": {"coordinates":[-0.024279,51.613472],"type":"Point"}
}