{
  "type": "Feature",
  "properties": {
    "addr:full":"Wind St Aberdare Neath Port Talbot CF44 7LL",
    "addr:postcode":"cf44 7ll",
    "addr:street":"Wind St",
    "iso:country":"GB",
    "sg:address":"Wind St",
    "sg:city":"Aberdare",
    "sg:classifiers":[
        {
            "category":"Organizations",
            "subcategory":"Membership Organization",
            "type":"Services"
        }
    ],
    "sg:phone":"+44 1685 871681",
    "sg:postcode":"CF44 7LL",
    "sg:province":"Neath Port Talbot",
    "sg:tags":[
        "club"
    ],
    "wof:name":"Aberdare United Services Club & Institut",
    "wof:placetype":"venue"
},
  "geometry": {"coordinates":[-3.442059,51.710186],"type":"Point"}
}