{
  "type": "Feature",
  "properties": {
    "addr:full":"Unit 2 Technorth, 9 Harrogate Rd Leeds West Yorkshire LS7 3NB",
    "addr:housenumber":"unit 2;9",
    "addr:postcode":"ls7 3nb",
    "addr:street":"Technorth;Harrogate Rd",
    "iso:country":"GB",
    "sg:address":"Unit 2 Technorth, 9 Harrogate Rd",
    "sg:city":"Leeds",
    "sg:classifiers":[
        {
            "category":"Education",
            "subcategory":"Special Training",
            "type":"Public Place"
        }
    ],
    "sg:phone":"+44 113 295 9595",
    "sg:postcode":"LS7 3NB",
    "sg:province":"West Yorkshire",
    "sg:tags":[
        "product",
        "centre"
    ],
    "wof:name":"F1 Business Support Ltd",
    "wof:placetype":"venue"
},
  "geometry": {"coordinates":[-1.5352699757,53.8262481689],"type":"Point"}
}