{
  "type": "Feature",
  "properties": {
    "iso:country":"GB",
    "sg:address":"Unit 12, Kirkless Industrial Estate",
    "sg:city":"Wigan",
    "sg:classifiers":[
        {
            "category":"Communications",
            "type":"Services"
        }
    ],
    "sg:postcode":"WN2 1HF",
    "sg:province":"Lancashire",
    "sg:tags":[
        "telecommunication"
    ],
    "wof:name":"Freephone Telecommunications",
    "wof:placetype":"venue"
},
  "geometry": {"coordinates":[-2.599568,53.558338],"type":"Point"}
}