{
  "type": "Feature",
  "properties": {
    "addr:full":"105a Winner St Paignton Devon TQ3 3BP",
    "addr:housenumber":"105a",
    "addr:postcode":"tq3 3bp",
    "addr:street":"Winner St",
    "iso:country":"GB",
    "sg:address":"105a Winner St",
    "sg:city":"Paignton",
    "sg:classifiers":[
        {
            "category":"Manufacturing",
            "subcategory":"Signs",
            "type":"Manufacturing & Wholesale Goods"
        }
    ],
    "sg:phone":"+44 1803 524465",
    "sg:postcode":"TQ3 3BP",
    "sg:province":"Devon",
    "sg:tags":[
        "writer"
    ],
    "wof:name":"Amazing Signs",
    "wof:placetype":"venue"
},
  "geometry": {"coordinates":[-3.571692,50.43539],"type":"Point"}
}