{
  "type": "Feature",
  "properties": {
    "addr:full":"94b Sidwell St Exeter Devon EX4 6PH",
    "addr:housenumber":"94b",
    "addr:postcode":"ex4 6ph",
    "addr:street":"Sidwell St",
    "iso:country":"GB",
    "sg:address":"94b Sidwell St",
    "sg:city":"Exeter",
    "sg:classifiers":[
        {
            "category":"Shopping",
            "subcategory":"Pharmacy",
            "type":"Retail Goods"
        }
    ],
    "sg:phone":"+44 1392 433678",
    "sg:postcode":"EX4 6PH",
    "sg:province":"Devon",
    "sg:tags":[
        "medicine",
        "therapy"
    ],
    "wof:name":"Inglewood House Studio",
    "wof:placetype":"venue"
},
  "geometry": {"coordinates":[-3.5217730999,50.7285308838],"type":"Point"}
}