{
  "type": "Feature",
  "properties": {
    "addr:full":"33 Clytha Park Road Newport Newport NP20 4NZ",
    "addr:housenumber":"33",
    "addr:postcode":"np20 4nz",
    "addr:street":"Clytha Park Road",
    "iso:country":"GB",
    "sg:address":"33 Clytha Park Road",
    "sg:city":"Newport",
    "sg:classifiers":[
        {
            "category":"Shopping",
            "subcategory":"News",
            "type":"Retail Goods"
        }
    ],
    "sg:postcode":"NP20 4NZ",
    "sg:province":"Newport",
    "sg:tags":[
        "newsagent"
    ],
    "wof:name":"Clytha Newsagents",
    "wof:placetype":"venue"
},
  "geometry": {"coordinates":[-3.00097,51.587288],"type":"Point"}
}