{
  "type": "Feature",
  "properties": {
    "addr:full":"126 Craigielea Road, Duntocher Glasgow East Dunbartonshire G81 6LA",
    "addr:housenumber":"126",
    "addr:postcode":"g81 6la",
    "addr:street":"Craigielea Road",
    "iso:country":"GB",
    "sg:address":"126 Craigielea Road, Duntocher",
    "sg:city":"Glasgow",
    "sg:classifiers":[
        {
            "category":"Organizations",
            "subcategory":"Membership Organization",
            "type":"Services"
        }
    ],
    "sg:postcode":"G81 6LA",
    "sg:province":"East Dunbartonshire",
    "sg:tags":[
        "club"
    ],
    "wof:name":"Rh Project Management Ltd",
    "wof:placetype":"venue"
},
  "geometry": {"coordinates":[-4.418095,55.927486],"type":"Point"}
}