{
  "type": "Feature",
  "properties": {
    "iso:country":"GB",
    "sg:address":"703 Melton Road, Thurmaston",
    "sg:city":"Leicester",
    "sg:classifiers":[
        {
            "category":"Professional",
            "type":"Services"
        }
    ],
    "sg:postcode":"LE4 8ED",
    "sg:province":"Leicestershire",
    "sg:tags":[
        "repair",
        "tech",
        "maintenance"
    ],
    "wof:name":"Ulysses Ltd.",
    "wof:placetype":"venue"
},
  "geometry": {"coordinates":[-1.09985,52.677807],"type":"Point"}
}