{
  "type": "Feature",
  "properties": {
    "iso:country":"GB",
    "sg:address":"Oakwood Nurseries, Chelford Road, Ollerton",
    "sg:city":"Knutsford",
    "sg:classifiers":[
        {
            "category":"Building & Trades",
            "subcategory":"Landscaping Services",
            "type":"Services"
        }
    ],
    "sg:postcode":"WA16 8SE",
    "sg:province":"Cheshire",
    "sg:tags":[
        "landscape",
        "contractor"
    ],
    "wof:name":"Warburtons Landscapes",
    "wof:placetype":"venue"
},
  "geometry": {"coordinates":[-2.3354439735,53.2866706848],"type":"Point"}
}