{
  "type": "Feature",
  "properties": {
    "iso:country":"GB",
    "sg:address":"620 Crow Road",
    "sg:city":"Glasgow",
    "sg:classifiers":[
        {
            "category":"Food & Beverages",
            "subcategory":"Liquor & Beverages",
            "type":"Retail Goods"
        }
    ],
    "sg:phone":"+44 141 950 1165",
    "sg:postcode":"G13 1NP",
    "sg:province":"Glasgow City",
    "sg:tags":[
        "beer",
        "spirit",
        "wines"
    ],
    "wof:name":"First Quench Retailing Ltd.",
    "wof:placetype":"venue"
},
  "geometry": {"coordinates":[-4.3255858421,55.8854370117],"type":"Point"}
}