{
  "type": "Feature",
  "properties": {
    "iso:country":"GB",
    "sg:address":"54 Orton Clo",
    "sg:city":"Birmingham",
    "sg:classifiers":[
        {
            "category":"Professional",
            "subcategory":"Engineering",
            "type":"Services"
        }
    ],
    "sg:phone":"+44 121 747 4620",
    "sg:postcode":"B46 1SY",
    "sg:province":"Warwickshire",
    "sg:tags":[
        "contractor",
        "electrical",
        "engineer"
    ],
    "wof:name":"K R Hurley",
    "wof:placetype":"venue"
},
  "geometry": {"coordinates":[-1.744332,52.517441],"type":"Point"}
}