{
  "type": "Feature",
  "properties": {
    "iso:country":"GB",
    "sg:address":"Unit 4c Penn Street Works, Penn Street Village",
    "sg:city":"Amersham",
    "sg:classifiers":[
        {
            "category":"Manufacturing",
            "subcategory":"Metals",
            "type":"Manufacturing & Wholesale Goods"
        }
    ],
    "sg:phone":"+44 1494 712029",
    "sg:postcode":"HP7 0PS",
    "sg:province":"Buckinghamshire",
    "sg:tags":[
        "steel",
        "fabricator",
        "erectors"
    ],
    "wof:name":"Structural Steel Supplies Ltd.",
    "wof:placetype":"venue"
},
  "geometry": {"coordinates":[-0.664999,51.657379],"type":"Point"}
}