{
  "type": "Feature",
  "properties": {
    "iso:country":"GB",
    "sg:address":"The Garage, Stockton Lane",
    "sg:city":"York",
    "sg:classifiers":[
        {
            "category":"Bus Charters",
            "type":"Transportation"
        }
    ],
    "sg:postcode":"YO3 9UE",
    "sg:province":"East Riding of Yorkshire",
    "sg:tags":[
        "mini",
        "hire",
        "leasing"
    ],
    "wof:name":"Walls Mini Coaches",
    "wof:placetype":"venue"
},
  "geometry": {"coordinates":[-1.0834200382,53.9533309937],"type":"Point"}
}