{
  "type": "Feature",
  "properties": {
    "addr:full":"Brook Farm, Cotes Road, Barrow On Soar Loughborough Leicestershire LE12 8JT",
    "addr:postcode":"soar;le12 8jt",
    "addr:street":"Brook;Cotes Road",
    "iso:country":"GB",
    "sg:address":"Brook Farm, Cotes Road, Barrow On Soar",
    "sg:city":"Loughborough",
    "sg:classifiers":[
        {
            "category":"Farming",
            "subcategory":"Livestock Farm",
            "type":"Manufacturing & Wholesale Goods"
        }
    ],
    "sg:postcode":"LE12 8JT",
    "sg:province":"Leicestershire",
    "sg:tags":[
        "others"
    ],
    "wof:name":"J E Harvey",
    "wof:placetype":"venue"
},
  "geometry": {"coordinates":[-1.15658,52.760109],"type":"Point"}
}