{
  "type": "Feature",
  "properties": {
    "addr:full":"4 Trood Stables Trood Lane, Matford Exeter Devon EX2 8XX",
    "addr:housenumber":"4",
    "addr:postcode":"ex2 8xx",
    "addr:street":"Trood;Trood Lane",
    "iso:country":"GB",
    "sg:address":"4 Trood Stables Trood Lane, Matford",
    "sg:city":"Exeter",
    "sg:classifiers":[
        {
            "category":"Health Services",
            "subcategory":"Health Practitioner",
            "type":"Services"
        }
    ],
    "sg:postcode":"EX2 8XX",
    "sg:province":"Devon",
    "sg:tags":[
        "psychotherapist"
    ],
    "wof:name":"Gwen Knowles",
    "wof:placetype":"venue"
},
  "geometry": {"coordinates":[-3.522329,50.691917],"type":"Point"}
}