{
  "type": "Feature",
  "properties": {
    "addr:full":"Cheriton Bishop Exeter Devon EX6 6JH",
    "addr:postcode":"ex6 6jh",
    "addr:street":"Bishop",
    "iso:country":"GB",
    "sg:address":"Cheriton Bishop",
    "sg:city":"Exeter",
    "sg:classifiers":[
        {
            "category":"Travel",
            "subcategory":"Hotels & Motels",
            "type":"Entertainment"
        },
        {
            "category":"Community Center",
            "subcategory":"Social",
            "type":"Public Place"
        }
    ],
    "sg:phone":"+44 1647 24204",
    "sg:postcode":"EX6 6JH",
    "sg:province":"Devon",
    "sg:tags":[
        "house",
        "activity"
    ],
    "wof:name":"Old Thatch Inn",
    "wof:placetype":"venue"
},
  "geometry": {"coordinates":[-3.73867,50.723412],"type":"Point"}
}