{
  "type": "Feature",
  "properties": {
    "iso:country":"GB",
    "sg:address":"89 Great North Rd",
    "sg:city":"Milford Haven",
    "sg:classifiers":[
        {
            "category":"Banks & Credit Unions",
            "subcategory":"Bureau De Change",
            "type":"Services"
        },
        {
            "category":"Food & Beverages",
            "subcategory":"Liquor & Beverages",
            "type":"Retail Goods"
        }
    ],
    "sg:phone":"+44 1646 697994",
    "sg:postcode":"SA73 2ND",
    "sg:province":"Pembrokeshire",
    "sg:tags":[
        "beer",
        "wine",
        "spirit",
        "wines"
    ],
    "wof:name":"Victoria Wine",
    "wof:placetype":"venue"
},
  "geometry": {"coordinates":[-5.027626,51.716465],"type":"Point"}
}