{
  "type": "Feature",
  "properties": {
    "addr:full":"Warstones Health Centre, Pinfold Gro Wolverhampton Staffordshire WV4 4PS",
    "addr:postcode":"wv4 4ps",
    "addr:street":"Pinfold Gro",
    "iso:country":"GB",
    "sg:address":"Warstones Health Centre, Pinfold Gro",
    "sg:city":"Wolverhampton",
    "sg:classifiers":[
        {
            "category":"Health Services",
            "subcategory":"Doctor",
            "type":"Services"
        }
    ],
    "sg:phone":"+44 1902 575001",
    "sg:postcode":"WV4 4PS",
    "sg:province":"Staffordshire",
    "sg:tags":[
        "practitioners"
    ],
    "wof:name":"Cuthbert, W H",
    "wof:placetype":"venue"
},
  "geometry": {"coordinates":[-2.168434,52.568531],"type":"Point"}
}