{
  "type": "Feature",
  "properties": {
    "iso:country":"GB",
    "sg:address":"105 Bath Rd, Bridgeyate",
    "sg:city":"Bristol",
    "sg:classifiers":[
        {
            "category":"Retail",
            "subcategory":"Auto Repair",
            "type":"Services"
        }
    ],
    "sg:phone":"+44 117 961 6637",
    "sg:postcode":"BS30 5NJ",
    "sg:province":"Gloucestershire",
    "sg:tags":[
        "modification",
        "garage"
    ],
    "wof:name":"R.T Motors",
    "wof:placetype":"venue"
},
  "geometry": {"coordinates":[-2.4630160332,51.4496612549],"type":"Point"}
}