{
  "type": "Feature",
  "properties": {
    "addr:full":"61-63 Crockhamwell Road, Woodley Reading Berkshire RG5 3JP",
    "addr:housenumber":"61-63",
    "addr:postcode":"rg5 3jp",
    "addr:street":"Crockhamwell Road",
    "iso:country":"GB",
    "sg:address":"61-63 Crockhamwell Road, Woodley",
    "sg:city":"Reading",
    "sg:classifiers":[
        {
            "category":"Communications",
            "subcategory":"Film & Video Production",
            "type":"Services"
        }
    ],
    "sg:phone":"+44 118 969 7900",
    "sg:postcode":"RG5 3JP",
    "sg:province":"Berkshire",
    "sg:tags":[
        "pr",
        "telemarketing"
    ],
    "wof:name":"Rhetorik Ltd.",
    "wof:placetype":"venue"
},
  "geometry": {"coordinates":[-0.906437,51.450798],"type":"Point"}
}