{
  "type": "Feature",
  "properties": {
    "iso:country":"GB",
    "sg:address":"22a Wych Elm",
    "sg:city":"Harlow",
    "sg:classifiers":[
        {
            "category":"Professional",
            "subcategory":"Art Services",
            "type":"Services"
        }
    ],
    "sg:postcode":"CM20 1QR",
    "sg:province":"Essex",
    "sg:tags":[
        "photographer"
    ],
    "wof:name":"Fred Scatley Photography",
    "wof:placetype":"venue"
},
  "geometry": {"coordinates":[0.09044,51.772015],"type":"Point"}
}