{
  "type": "Feature",
  "properties": {
    "addr:full":"39 The Square, Earls Barton Northampton Northamptonshire NN6 0NA",
    "addr:housenumber":"39",
    "addr:postcode":"nn6 0na",
    "addr:street":"The Square",
    "iso:country":"GB",
    "sg:address":"39 The Square, Earls Barton",
    "sg:city":"Northampton",
    "sg:classifiers":[
        {
            "category":"Restaurant",
            "type":"Food & Drink"
        }
    ],
    "sg:phone":"+44 1604 811982",
    "sg:postcode":"NN6 0NA",
    "sg:province":"Northamptonshire",
    "wof:name":"Rafters",
    "wof:placetype":"venue"
},
  "geometry": {"coordinates":[-0.751745,52.264809],"type":"Point"}
}