{
  "type": "Feature",
  "properties": {
    "iso:country":"GB",
    "sg:address":"Hawkins Farm, Hackmans Lane, Cock Clarks",
    "sg:city":"Chelmsford",
    "sg:classifiers":[
        {
            "category":"Professional",
            "subcategory":"Business Services",
            "type":"Services"
        },
        {
            "category":"Government",
            "subcategory":"Post Office",
            "type":"Public Place"
        }
    ],
    "sg:phone":"+44 1621 829595",
    "sg:postcode":"CM3 6RE",
    "sg:province":"Essex",
    "sg:tags":[
        "messenger",
        "courier"
    ],
    "wof:name":"Essex Express Couriers Ltd.",
    "wof:placetype":"venue"
},
  "geometry": {"coordinates":[0.623052001,51.6949195862],"type":"Point"}
}