{
  "type": "Feature",
  "properties": {
    "addr:full":"46 South Street, Titchfield Fareham Hampshire PO14 4DY",
    "addr:housenumber":"46",
    "addr:postcode":"po14 4dy",
    "addr:street":"South Street",
    "iso:country":"GB",
    "sg:address":"46 South Street, Titchfield",
    "sg:city":"Fareham",
    "sg:classifiers":[
        {
            "category":"Retail",
            "subcategory":"Funeral Services",
            "type":"Services"
        }
    ],
    "sg:phone":"+44 1329 842115",
    "sg:postcode":"PO14 4DY",
    "sg:province":"Hampshire",
    "sg:tags":[
        "director"
    ],
    "sg:website":"http://ahfreemantle.co.uk",
    "wof:name":"A H Freemantle",
    "wof:placetype":"venue"
},
  "geometry": {"coordinates":[-1.234552,50.847404],"type":"Point"}
}