{
  "type": "Feature",
  "properties": {
    "addr:full":"Omega House, Electron Way, Chandlesford Eastleigh Hampshire SO53 4SE",
    "addr:postcode":"so53 4se",
    "addr:street":"Electron Way Chandlesford",
    "iso:country":"GB",
    "sg:address":"Omega House, Electron Way, Chandlesford",
    "sg:city":"Eastleigh",
    "sg:classifiers":[
        {
            "category":"Home & Garden",
            "subcategory":"Household Appliances",
            "type":"Retail Goods"
        }
    ],
    "sg:phone":"+44 23 8069 5300",
    "sg:postcode":"SO53 4SE",
    "sg:province":"Hampshire",
    "sg:tags":[
        "refrigeration",
        "air conditioning"
    ],
    "wof:name":"A C Powertech Projects",
    "wof:placetype":"venue"
},
  "geometry": {"coordinates":[-1.387014,50.982777],"type":"Point"}
}