{
  "type": "Feature",
  "properties": {
    "addr:full":"Alveston House, 11 Broad Street Pershore Worcestershire WR10 1BB",
    "addr:housenumber":"11",
    "addr:postcode":"wr10 1bb",
    "addr:street":"Broad Street",
    "iso:country":"GB",
    "sg:address":"Alveston House, 11 Broad Street",
    "sg:city":"Pershore",
    "sg:classifiers":[
        {
            "category":"Professional",
            "subcategory":"Computer Services",
            "type":"Services"
        }
    ],
    "sg:postcode":"WR10 1BB",
    "sg:province":"Worcestershire",
    "sg:tags":[
        "aided",
        "design"
    ],
    "wof:name":"V & R Design Services",
    "wof:placetype":"venue"
},
  "geometry": {"coordinates":[-2.0760169029,52.1098213196],"type":"Point"}
}