{
  "type": "Feature",
  "properties": {
    "iso:country":"GB",
    "sg:address":"74 Commercial St, Ystalyfera",
    "sg:city":"Swansea",
    "sg:classifiers":[
        {
            "category":"Health Services",
            "subcategory":"Optometrist",
            "type":"Services"
        }
    ],
    "sg:phone":"+44 1639 842117",
    "sg:postcode":"SA9 2HS",
    "sg:province":"Carmarthenshire",
    "sg:tags":[
        "optician"
    ],
    "wof:name":"R.D Williams",
    "wof:placetype":"venue"
},
  "geometry": {"coordinates":[-3.784585,51.766121],"type":"Point"}
}