{
  "type": "Feature",
  "properties": {
    "addr:full":"Tatham Street Sunderland Tyne and Wear SR1 2AG",
    "addr:postcode":"sr1 2ag",
    "addr:street":"Tatham Street",
    "iso:country":"GB",
    "sg:address":"Tatham Street",
    "sg:city":"Sunderland",
    "sg:classifiers":[
        {
            "category":"Professional",
            "subcategory":"Engineering",
            "type":"Services"
        }
    ],
    "sg:phone":"+44 191 567 4408",
    "sg:postcode":"SR1 2AG",
    "sg:province":"Tyne and Wear",
    "wof:name":"Jennings Winch & Foundry Co. Ltd.",
    "wof:placetype":"venue"
},
  "geometry": {"coordinates":[-1.376329,54.904469],"type":"Point"}
}