{
  "type": "Feature",
  "properties": {
    "addr:full":"9 The Glades Hemel Hempstead Hertfordshire HP1 2TH",
    "addr:housenumber":"9",
    "addr:postcode":"hp1 2th",
    "addr:street":"Hemel Hempstead",
    "iso:country":"GB",
    "sg:address":"9 The Glades",
    "sg:city":"Hemel Hempstead",
    "sg:classifiers":[
        {
            "category":"Building & Trades",
            "subcategory":"Plumbing",
            "type":"Services"
        }
    ],
    "sg:phone":"+44 1442 217464",
    "sg:postcode":"HP1 2TH",
    "sg:province":"Hertfordshire",
    "sg:tags":[
        "central",
        "installation",
        "heating",
        "servicing",
        "system"
    ],
    "wof:name":"Astral Plumbing",
    "wof:placetype":"venue"
},
  "geometry": {"coordinates":[-0.5031570196,51.7599830627],"type":"Point"}
}