{
  "type": "Feature",
  "properties": {
    "iso:country":"GB",
    "sg:address":"259 Gray's Inn Road",
    "sg:city":"London",
    "sg:classifiers":[
        {
            "category":"Professional",
            "subcategory":"Lawyer & Legal Services",
            "type":"Services"
        }
    ],
    "sg:phone":"+44 20 7833 3747",
    "sg:postcode":"WC1X 8QT",
    "sg:province":"Greater London",
    "sg:tags":[
        "solicitor"
    ],
    "wof:name":"Ned Nwoko Solicitors",
    "wof:placetype":"venue"
},
  "geometry": {"coordinates":[-0.11985,51.52887],"type":"Point"}
}