{
  "type": "Feature",
  "properties": {
    "iso:country":"GB",
    "sg:address":"68 Rosemount Pl",
    "sg:city":"Aberdeen",
    "sg:classifiers":[
        {
            "category":"Education",
            "subcategory":"Library",
            "type":"Public Place"
        }
    ],
    "sg:postcode":"AB25 2XJ",
    "sg:province":"Aberdeen City",
    "sg:tags":[
        "reproduction",
        "furniture"
    ],
    "wof:name":"Classic Reproduction Furniture",
    "wof:placetype":"venue"
},
  "geometry": {"coordinates":[-2.1136,57.150429],"type":"Point"}
}