{
  "type": "Feature",
  "properties": {
    "addr:full":"109c Downs Rd Clapton Greater London E5 8DS",
    "addr:housenumber":"109c",
    "addr:postcode":"e5 8ds",
    "addr:street":"Downs Rd",
    "iso:country":"GB",
    "sg:address":"109c Downs Rd",
    "sg:city":"Clapton",
    "sg:classifiers":[
        {
            "category":"Professional",
            "subcategory":"Accounting & Tax Preparation",
            "type":"Services"
        }
    ],
    "sg:phone":"+44 20 8533 0008",
    "sg:postcode":"E5 8DS",
    "sg:province":"Greater London",
    "sg:tags":[
        "accountant"
    ],
    "wof:name":"Timothy Festus & Co",
    "wof:placetype":"venue"
},
  "geometry": {"coordinates":[-0.0560490005,51.5559310913],"type":"Point"}
}