{
  "type": "Feature",
  "properties": {
    "iso:country":"GB",
    "sg:address":"Matlock & Brown Yard, Bath Road",
    "sg:city":"Kettering",
    "sg:classifiers":[
        {
            "category":"Building & Trades",
            "subcategory":"Construction",
            "type":"Services"
        }
    ],
    "sg:phone":"+44 1536 482010",
    "sg:postcode":"NN16 8NH",
    "sg:province":"Northamptonshire",
    "sg:tags":[
        "decorator",
        "painter"
    ],
    "wof:name":"Christie Rogers",
    "wof:placetype":"venue"
},
  "geometry": {"coordinates":[-0.7195940018,52.4040794373],"type":"Point"}
}