{
  "type": "Feature",
  "properties": {
    "iso:country":"GB",
    "sg:address":"12b Heol-y-graig",
    "sg:city":"Aberdare",
    "sg:classifiers":[
        {
            "category":"Building & Trades",
            "subcategory":"Plumbing",
            "type":"Services"
        }
    ],
    "sg:phone":"+44 1685 811264",
    "sg:postcode":"CF44 9YY",
    "sg:province":"Neath Port Talbot",
    "sg:tags":[
        "central",
        "heating"
    ],
    "wof:name":"N E Barrow",
    "wof:placetype":"venue"
},
  "geometry": {"coordinates":[-3.561422,51.742764],"type":"Point"}
}