{
  "type": "Feature",
  "properties": {
    "addr:full":"Unit 34 Jacks Pill Industrial Estate Newport Newport NP20 2BR",
    "addr:housenumber":"unit 34",
    "addr:postcode":"np20 2br",
    "addr:street":"Pill Industrial Estate",
    "iso:country":"GB",
    "sg:address":"Unit 34 Jacks Pill Industrial Estate",
    "sg:city":"Newport",
    "sg:classifiers":[
        {
            "category":"Retail",
            "subcategory":"Auto Repair",
            "type":"Services"
        }
    ],
    "sg:phone":"+44 1633 221221",
    "sg:postcode":"NP20 2BR",
    "sg:province":"Newport",
    "sg:tags":[
        "modification",
        "garage"
    ],
    "wof:name":"Gwent Windscreens",
    "wof:placetype":"venue"
},
  "geometry": {"coordinates":[-3.0032939911,51.5689468384],"type":"Point"}
}