{
  "type": "Feature",
  "properties": {
    "iso:country":"GB",
    "sg:address":"Ivanhoe, Spalding Common",
    "sg:city":"Spalding",
    "sg:classifiers":[
        {
            "category":"Manufacturing",
            "subcategory":"Metals",
            "type":"Manufacturing & Wholesale Goods"
        }
    ],
    "sg:phone":"+44 1775 722988",
    "sg:postcode":"PE11 3AS",
    "sg:province":"Lincolnshire",
    "sg:tags":[
        "fab",
        "foundry"
    ],
    "wof:name":"South Lincs Patterns",
    "wof:placetype":"venue"
},
  "geometry": {"coordinates":[-0.1736139953,52.7658195496],"type":"Point"}
}