{
  "type": "Feature",
  "properties": {
    "iso:country":"GB",
    "sg:address":"21-22 Dinan Way",
    "sg:city":"Exmouth",
    "sg:classifiers":[
        {
            "category":"Autos & Motor Vehicles",
            "subcategory":"Auto Supplies",
            "type":"Retail Goods"
        },
        {
            "category":"Shopping",
            "type":"Retail Goods"
        }
    ],
    "sg:phone":"+44 1395 265593",
    "sg:postcode":"EX8 4EZ",
    "sg:province":"Devon",
    "sg:tags":[
        "part",
        "accessory",
        "factor"
    ],
    "wof:name":"Als Motor Parts Ltd.",
    "wof:placetype":"venue"
},
  "geometry": {"coordinates":[-3.381009,50.637039],"type":"Point"}
}