{
  "type": "Feature",
  "properties": {
    "iso:country":"GB",
    "sg:address":"21 Lindsay Road, Sprowston",
    "sg:city":"Norwich",
    "sg:classifiers":[
        {
            "category":"Building & Trades",
            "subcategory":"Construction",
            "type":"Services"
        }
    ],
    "sg:postcode":"NR7 8JR",
    "sg:province":"Norfolk",
    "sg:tags":[
        "flooring"
    ],
    "wof:name":"Coman & Bye",
    "wof:placetype":"venue"
},
  "geometry": {"coordinates":[1.3315689564,52.6566085815],"type":"Point"}
}