{
  "type": "Feature",
  "properties": {
    "iso:country":"GB",
    "sg:address":"23 Doulton Dr",
    "sg:city":"Newcastle",
    "sg:classifiers":[
        {
            "category":"Shopping",
            "subcategory":"Party Supplies",
            "type":"Retail Goods"
        }
    ],
    "sg:phone":"+44 1782 634474",
    "sg:postcode":"ST5 8SE",
    "sg:province":"Staffordshire",
    "sg:tags":[
        "inflatables",
        "bouncy",
        "castle"
    ],
    "wof:name":"Abracadabra Bouncy Castles",
    "wof:placetype":"venue"
},
  "geometry": {"coordinates":[-2.2259790897,53.0387535095],"type":"Point"}
}