{
  "type": "Feature",
  "properties": {
    "iso:country":"GB",
    "sg:address":"New Cattle Market, Liliput Road",
    "sg:city":"Northampton",
    "sg:classifiers":[
        {
            "category":"Freight",
            "type":"Transportation"
        }
    ],
    "sg:phone":"+44 1604 700440",
    "sg:postcode":"NN4 7BY",
    "sg:province":"Northamptonshire",
    "sg:tags":[
        "haulage",
        "road"
    ],
    "wof:name":"M A M Transport Services Ltd.",
    "wof:placetype":"venue"
},
  "geometry": {"coordinates":[-0.8515700102,52.2240982056],"type":"Point"}
}