{
  "type": "Feature",
  "properties": {
    "addr:full":"Museum St, Museum Gardens York North Yorkshire YO1 2DR",
    "addr:postcode":"yo1 2dr",
    "addr:street":"Gardens",
    "iso:country":"GB",
    "sg:address":"Museum St, Museum Gardens",
    "sg:city":"York",
    "sg:classifiers":[
        {
            "category":"Museum",
            "subcategory":"Art Museum",
            "type":"Entertainment"
        }
    ],
    "sg:phone":"+44 1904 629745",
    "sg:postcode":"YO1 2DR",
    "sg:province":"North Yorkshire",
    "sg:tags":[
        "gallery"
    ],
    "wof:name":"The Yorkshire Museum",
    "wof:placetype":"venue"
},
  "geometry": {"coordinates":[-1.0813499689,53.958770752],"type":"Point"}
}