{
  "type": "Feature",
  "properties": {
    "addr:full":"95 London Road, Marks Tey Colchester Essex CO6 1EB",
    "addr:housenumber":"95",
    "addr:postcode":"co6 1eb",
    "addr:street":"London Road",
    "iso:country":"GB",
    "sg:address":"95 London Road, Marks Tey",
    "sg:city":"Colchester",
    "sg:classifiers":[
        {
            "category":"Fast Food",
            "type":"Food & Drink"
        }
    ],
    "sg:phone":"+44 1206 213258",
    "sg:postcode":"CO6 1EB",
    "sg:province":"Essex",
    "sg:tags":[
        "away",
        "meal",
        "outlet",
        "take"
    ],
    "wof:name":"Fortune House",
    "wof:placetype":"venue"
},
  "geometry": {"coordinates":[0.799033,51.880299],"type":"Point"}
}