{
  "type": "Feature",
  "properties": {
    "addr:full":"Wells Road, Strood Rochester Kent ME2 2PW",
    "addr:postcode":"me2 2pw",
    "addr:street":"Wells Road",
    "iso:country":"GB",
    "sg:address":"Wells Road, Strood",
    "sg:city":"Rochester",
    "sg:classifiers":[
        {
            "category":"Health Services",
            "subcategory":"Doctor",
            "type":"Services"
        },
        {
            "category":"Health Services",
            "subcategory":"Clinic",
            "type":"Services"
        }
    ],
    "sg:phone":"+44 1634 719692",
    "sg:postcode":"ME2 2PW",
    "sg:province":"Kent",
    "sg:tags":[
        "nh",
        "practitioners"
    ],
    "wof:name":"The Marlowe Park Medical Centre",
    "wof:placetype":"venue"
},
  "geometry": {"coordinates":[0.468618,51.388046],"type":"Point"}
}