{
  "type": "Feature",
  "properties": {
    "addr:full":"Mayflower, Valley Road, Corfe Castle Wareham Dorset BH20 5HU",
    "addr:postcode":"bh20 5hu",
    "addr:street":"Valley Road",
    "iso:country":"GB",
    "sg:address":"Mayflower, Valley Road, Corfe Castle",
    "sg:city":"Wareham",
    "sg:classifiers":[
        {
            "category":"Organizations",
            "subcategory":"Non-profit Organization",
            "type":"Services"
        }
    ],
    "sg:postcode":"BH20 5HU",
    "sg:province":"Dorset",
    "sg:tags":[
        "organisation",
        "voluntary",
        "charity"
    ],
    "wof:name":"Parkinson's Disease Society of the Unite",
    "wof:placetype":"venue"
},
  "geometry": {"coordinates":[-2.053594,50.633839],"type":"Point"}
}