{
  "type": "Feature",
  "properties": {
    "addr:full":"22 Hallgate Wigan Lancashire WN1 1LR",
    "addr:housenumber":"22",
    "addr:postcode":"wn1 1lr",
    "addr:street":"Hallgate",
    "iso:country":"GB",
    "sg:address":"22 Hallgate",
    "sg:city":"Wigan",
    "sg:classifiers":[
        {
            "category":"Education",
            "subcategory":"Special Training",
            "type":"Public Place"
        }
    ],
    "sg:phone":"+44 1942 826099",
    "sg:postcode":"WN1 1LR",
    "sg:province":"Lancashire",
    "sg:tags":[
        "product",
        "centre"
    ],
    "wof:name":"Pitman Traning Centre",
    "wof:placetype":"venue"
},
  "geometry": {"coordinates":[-2.633105,53.546474],"type":"Point"}
}