{
  "type": "Feature",
  "properties": {
    "addr:full":"378 Lillie Road, Fulham London Greater London SW6 7PH",
    "addr:housenumber":"378",
    "addr:postcode":"sw6 7ph",
    "addr:street":"Lillie Road",
    "iso:country":"GB",
    "sg:address":"378 Lillie Road, Fulham",
    "sg:city":"London",
    "sg:classifiers":[
        {
            "category":"Organizations",
            "subcategory":"Non-profit Organization",
            "type":"Services"
        }
    ],
    "sg:postcode":"SW6 7PH",
    "sg:province":"Greater London",
    "sg:tags":[
        "organisation",
        "voluntary",
        "charity"
    ],
    "wof:name":"Bishop Creighton House Settlement",
    "wof:placetype":"venue"
},
  "geometry": {"coordinates":[-0.217769,51.483566],"type":"Point"}
}