{
  "type": "Feature",
  "properties": {
    "iso:country":"GB",
    "sg:address":"Centrefield, The Broadway",
    "sg:city":"Mansfield",
    "sg:classifiers":[
        {
            "category":"Social Services",
            "subcategory":"Job Training",
            "type":"Services"
        },
        {
            "category":"Education",
            "subcategory":"Special Training",
            "type":"Public Place"
        }
    ],
    "sg:phone":"+44 1623 422099",
    "sg:postcode":"NG18 2RL",
    "sg:province":"Nottinghamshire",
    "sg:tags":[
        "product",
        "centre"
    ],
    "sg:website":"http://www.kefax.co.uk",
    "wof:name":"Kefax Ltd",
    "wof:placetype":"venue"
},
  "geometry": {"coordinates":[-1.18838,53.141296],"type":"Point"}
}