{
  "type": "Feature",
  "properties": {
    "addr:full":"346 Acton Lane London Greater London W3 8NX",
    "addr:housenumber":"346",
    "addr:postcode":"w3 8nx",
    "addr:street":"Acton Lane",
    "iso:country":"GB",
    "sg:address":"346 Acton Lane",
    "sg:city":"London",
    "sg:classifiers":[
        {
            "category":"Retail",
            "subcategory":"Veterinary Services",
            "type":"Services"
        }
    ],
    "sg:phone":"+44 20 8992 6000",
    "sg:postcode":"W3 8NX",
    "sg:province":"Greater London",
    "sg:tags":[
        "surgeon"
    ],
    "wof:name":"C J Hall Veterinary Surgeons",
    "wof:placetype":"venue"
},
  "geometry": {"coordinates":[-0.267122,51.504269],"type":"Point"}
}