{
  "type": "Feature",
  "properties": {
    "iso:country":"GB",
    "sg:address":"6 Hayfield Gds",
    "sg:city":"Birmingham",
    "sg:classifiers":[
        {
            "category":"Arts & Performance",
            "subcategory":"Art Gallery",
            "type":"Entertainment"
        }
    ],
    "sg:postcode":"B13 9LE",
    "sg:province":"West Midlands",
    "wof:name":"Caterpillar Trading",
    "wof:placetype":"venue"
},
  "geometry": {"coordinates":[-1.8687590361,52.4409141541],"type":"Point"}
}