{
  "type": "Feature",
  "properties": {
    "iso:country":"GB",
    "sg:address":"51 Southampton Street",
    "sg:city":"Reading",
    "sg:classifiers":[
        {
            "category":"Real Estate",
            "subcategory":"Surveying",
            "type":"Services"
        }
    ],
    "sg:phone":"+44 118 950 5761",
    "sg:postcode":"RG1 2QP",
    "sg:province":"Berkshire",
    "sg:tags":[
        "surveyor",
        "land"
    ],
    "wof:name":"Countrywide Surveyors Ltd.",
    "wof:placetype":"venue"
},
  "geometry": {"coordinates":[-0.970643,51.450905],"type":"Point"}
}