{
  "type": "Feature",
  "properties": {
    "addr:full":"4 Manor Park Crescent Edgware Greater London HA8 7NN",
    "addr:housenumber":"4",
    "addr:postcode":"ha8 7nn",
    "addr:street":"Manor Park Crescent",
    "iso:country":"GB",
    "sg:address":"4 Manor Park Crescent",
    "sg:city":"Edgware",
    "sg:classifiers":[
        {
            "category":"Community Center",
            "subcategory":"Youth",
            "type":"Public Place"
        }
    ],
    "sg:phone":"+44 20 8952 3380",
    "sg:postcode":"HA8 7NN",
    "sg:province":"Greater London",
    "sg:tags":[
        "organisation",
        "centre"
    ],
    "wof:name":"Brady-Maccabi Youth & Community Centre",
    "wof:placetype":"venue"
},
  "geometry": {"coordinates":[-0.279833,51.612415],"type":"Point"}
}