{
  "type": "Feature",
  "properties": {
    "addr:full":"116 Bristol Road, Quedgeley Gloucester Gloucestershire GL2 4NA",
    "addr:housenumber":"116",
    "addr:postcode":"gl2 4na",
    "addr:street":"Bristol Road",
    "iso:country":"GB",
    "sg:address":"116 Bristol Road, Quedgeley",
    "sg:city":"Gloucester",
    "sg:classifiers":[
        {
            "category":"Health Services",
            "subcategory":"Nursing And Care Facility",
            "type":"Services"
        },
        {
            "category":"Social Services",
            "subcategory":"Retirement Home",
            "type":"Services"
        }
    ],
    "sg:phone":"+44 1452 728296",
    "sg:postcode":"GL2 4NA",
    "sg:province":"Gloucestershire",
    "sg:tags":[
        "residential"
    ],
    "wof:name":"The Retreat",
    "wof:placetype":"venue"
},
  "geometry": {"coordinates":[-2.2768270969,51.8293151855],"type":"Point"}
}