{
  "type": "Feature",
  "properties": {
    "iso:country":"GB",
    "sg:address":"73 Station Road",
    "sg:city":"Longfield",
    "sg:classifiers":[
        {
            "category":"Fast Food",
            "type":"Food & Drink"
        }
    ],
    "sg:phone":"+44 1474 703586",
    "sg:postcode":"DA3 7QA",
    "sg:province":"Kent",
    "sg:tags":[
        "away",
        "take"
    ],
    "wof:name":"G Fiore",
    "wof:placetype":"venue"
},
  "geometry": {"coordinates":[0.3000729978,51.396522522],"type":"Point"}
}