{
  "type": "Feature",
  "properties": {
    "iso:country":"GB",
    "sg:address":"15 Davey Ho, 31 St Neots Rd, Eaton Ford",
    "sg:city":"St Neots",
    "sg:classifiers":[
        {
            "category":"Wholesale",
            "subcategory":"Office Equipment",
            "type":"Manufacturing & Wholesale Goods"
        },
        {
            "category":"Building & Trades",
            "subcategory":"Construction",
            "type":"Services"
        }
    ],
    "sg:phone":"+44 1480 211366",
    "sg:postcode":"PE19 7BA",
    "sg:province":"Bedfordshire",
    "sg:tags":[
        "partition",
        "cubicle",
        "refurbishment",
        "restoration"
    ],
    "wof:name":"Oska Moore Interiors Ltd",
    "wof:placetype":"venue"
},
  "geometry": {"coordinates":[-0.282424,52.227955],"type":"Point"}
}