{
  "type": "Feature",
  "properties": {
    "iso:country":"GB",
    "sg:address":"Crieff Rd",
    "sg:city":"Perth",
    "sg:classifiers":[
        {
            "category":"Food & Beverages",
            "subcategory":"Fruits & Vegetables",
            "type":"Retail Goods"
        }
    ],
    "sg:postcode":"PH1 5AF",
    "sg:province":"Perth and Kinross",
    "sg:tags":[
        "greengrocer"
    ],
    "wof:name":"Fresh Fayre",
    "wof:placetype":"venue"
},
  "geometry": {"coordinates":[-3.445583,56.403751],"type":"Point"}
}