{
  "type": "Feature",
  "properties": {
    "addr:full":"41 Hurst Way, Fulwood Preston Lancashire PR2 9TT",
    "addr:housenumber":"41",
    "addr:postcode":"pr2 9tt",
    "addr:street":"Hurst Way",
    "iso:country":"GB",
    "sg:address":"41 Hurst Way, Fulwood",
    "sg:city":"Preston",
    "sg:classifiers":[
        {
            "category":"Professional",
            "subcategory":"Accounting & Tax Preparation",
            "type":"Services"
        }
    ],
    "sg:phone":"+44 1772 774316",
    "sg:postcode":"PR2 9TT",
    "sg:province":"Lancashire",
    "sg:tags":[
        "accountant"
    ],
    "wof:name":"A M D Business Services",
    "wof:placetype":"venue"
},
  "geometry": {"coordinates":[-2.713179,53.790054],"type":"Point"}
}