{
  "type": "Feature",
  "properties": {
    "addr:full":"21a High St Rayleigh Essex SS6 7EW",
    "addr:housenumber":"21a",
    "addr:postcode":"ss6 7ew",
    "addr:street":"High St Rayleigh",
    "iso:country":"GB",
    "sg:address":"21a High St",
    "sg:city":"Rayleigh",
    "sg:classifiers":[
        {
            "category":"Professional",
            "subcategory":"Lawyer & Legal Services",
            "type":"Services"
        }
    ],
    "sg:phone":"+44 1268 743743",
    "sg:postcode":"SS6 7EW",
    "sg:province":"Essex",
    "sg:tags":[
        "advice",
        "counselling"
    ],
    "wof:name":"Off The Record",
    "wof:placetype":"venue"
},
  "geometry": {"coordinates":[0.6074669957,51.587223053],"type":"Point"}
}