{
  "type": "Feature",
  "properties": {
    "iso:country":"GB",
    "sg:address":"Arch 11 Viaduct Estate Road",
    "sg:city":"Carlisle",
    "sg:classifiers":[
        {
            "category":"Shopping",
            "subcategory":"Crafts & Fabrics",
            "type":"Retail Goods"
        },
        {
            "category":"Communications",
            "type":"Services"
        }
    ],
    "sg:phone":"+44 1228 599880",
    "sg:postcode":"CA2 5BN",
    "sg:province":"Cumbria",
    "sg:tags":[
        "knitting",
        "tv",
        "sewing",
        "machine",
        "video",
        "radio"
    ],
    "wof:name":"The Superior Sewing Centre",
    "wof:placetype":"venue"
},
  "geometry": {"coordinates":[-2.944973,54.893913],"type":"Point"}
}