{
  "type": "Feature",
  "properties": {
    "iso:country":"GB",
    "sg:address":"144 New Hey Rd",
    "sg:city":"Huddersfield",
    "sg:classifiers":[
        {
            "category":"Place Of Worship",
            "type":"Public Place"
        },
        {
            "category":"Organizations",
            "subcategory":"Non-profit Organization",
            "type":"Services"
        }
    ],
    "sg:phone":"+44 1484 653408",
    "sg:postcode":"HD3 4BZ",
    "sg:province":"West Yorkshire",
    "sg:tags":[
        "charitable",
        "organisation",
        "charity"
    ],
    "wof:name":"St James The Great R C Church",
    "wof:placetype":"venue"
},
  "geometry": {"coordinates":[-1.8195949793,53.6535491943],"type":"Point"}
}