{
  "type": "Feature",
  "properties": {
    "addr:full":"Staff Club, Freckleton Street Blackburn Lancashire BB2 3QW",
    "addr:postcode":"bb2 3qw",
    "addr:street":"Freckleton Street",
    "iso:country":"GB",
    "sg:address":"Staff Club, Freckleton Street",
    "sg:city":"Blackburn",
    "sg:classifiers":[
        {
            "category":"Train Station",
            "subcategory":"Rail",
            "type":"Transportation"
        }
    ],
    "sg:phone":"+44 1254 51036",
    "sg:postcode":"BB2 3QW",
    "sg:province":"Lancashire",
    "sg:tags":[
        "railway"
    ],
    "wof:name":"B R S A Social Club",
    "wof:placetype":"venue"
},
  "geometry": {"coordinates":[-2.4837288857,53.7413787842],"type":"Point"}
}