{
  "type": "Feature",
  "properties": {
    "iso:country":"GB",
    "sg:address":"Avenue Street",
    "sg:city":"Bolton",
    "sg:classifiers":[
        {
            "category":"Arena",
            "subcategory":"Sports Club",
            "type":"Entertainment"
        }
    ],
    "sg:phone":"+44 1204 363710",
    "sg:postcode":"BL1 3AW",
    "sg:province":"Lancashire",
    "wof:name":"Bolton Rugby Union Club",
    "wof:placetype":"venue"
},
  "geometry": {"coordinates":[-2.445571,53.585346],"type":"Point"}
}