{
  "type": "Feature",
  "properties": {
    "addr:full":"Po Box 969 Lancaster Lancashire LA1 3LD",
    "addr:housenumber":"po",
    "addr:postcode":"la1 3ld",
    "addr:street":"Box 969",
    "iso:country":"GB",
    "sg:address":"Po Box 969",
    "sg:city":"Lancaster",
    "sg:classifiers":[
        {
            "category":"Communications",
            "type":"Services"
        }
    ],
    "sg:phone":"+44 1524 848747",
    "sg:postcode":"LA1 3LD",
    "sg:province":"Lancashire",
    "sg:tags":[
        "broadcasting"
    ],
    "wof:name":"Bay Radio Ltd.",
    "wof:placetype":"venue"
},
  "geometry": {"coordinates":[-2.7990291119,54.0445365906],"type":"Point"}
}