{
  "type": "Feature",
  "properties": {
    "iso:country":"GB",
    "sg:address":"55 Pill Street",
    "sg:city":"Penarth",
    "sg:classifiers":[
        {
            "category":"Personal",
            "subcategory":"Beauty Salon",
            "type":"Services"
        }
    ],
    "sg:postcode":"CF64 2JR",
    "sg:province":"The Vale of Glamorgan",
    "sg:tags":[
        "ladies",
        "lady",
        "hairdresser"
    ],
    "wof:name":"HEAD STATION",
    "wof:placetype":"venue"
},
  "geometry": {"coordinates":[-3.187131,51.444366],"type":"Point"}
}