{
  "type": "Feature",
  "properties": {
    "addr:full":"Rolleston Road, Rolleston On Dove Burton-on-trent Derbyshire DE13 9EA",
    "addr:postcode":"de13 9ea",
    "addr:street":"Rolleston Road",
    "iso:country":"GB",
    "sg:address":"Rolleston Road, Rolleston On Dove",
    "sg:city":"Burton-on-trent",
    "sg:classifiers":[
        {
            "category":"Farming",
            "subcategory":"Livestock Farm",
            "type":"Manufacturing & Wholesale Goods"
        }
    ],
    "sg:phone":"+44 1283 813153",
    "sg:postcode":"DE13 9EA",
    "sg:province":"Derbyshire",
    "sg:tags":[
        "others"
    ],
    "wof:name":"Field Grove Farm",
    "wof:placetype":"venue"
},
  "geometry": {"coordinates":[-1.650579,52.845757],"type":"Point"}
}