{
  "type": "Feature",
  "properties": {
    "addr:full":"29 Norfolk Park Avenue Sheffield South Yorkshire S2 2RA",
    "addr:housenumber":"29",
    "addr:postcode":"s2 2ra",
    "addr:street":"Norfolk Park Avenue",
    "iso:country":"GB",
    "sg:address":"29 Norfolk Park Avenue",
    "sg:city":"Sheffield",
    "sg:classifiers":[
        {
            "category":"Building & Trades",
            "subcategory":"Construction",
            "type":"Services"
        }
    ],
    "sg:postcode":"S2 2RA",
    "sg:province":"South Yorkshire",
    "sg:tags":[
        "dry",
        "lining",
        "plasterers",
        "screeders"
    ],
    "wof:name":"Alexander Plastering",
    "wof:placetype":"venue"
},
  "geometry": {"coordinates":[-1.4529440403,53.3735847473],"type":"Point"}
}