{
  "type": "Feature",
  "properties": {
    "addr:full":"14 High Street Gosport Hampshire PO12 1BX",
    "addr:housenumber":"14",
    "addr:postcode":"po12 1bx",
    "addr:street":"High Street",
    "iso:country":"GB",
    "sg:address":"14 High Street",
    "sg:city":"Gosport",
    "sg:classifiers":[
        {
            "category":"Shopping",
            "subcategory":"News",
            "type":"Retail Goods"
        }
    ],
    "sg:phone":"+44 23 9250 3808",
    "sg:postcode":"PO12 1BX",
    "sg:province":"Hampshire",
    "sg:tags":[
        "newsagent"
    ],
    "wof:name":"News Round",
    "wof:placetype":"venue"
},
  "geometry": {"coordinates":[-1.125454,50.794956],"type":"Point"}
}