{
  "type": "Feature",
  "properties": {
    "addr:full":"Wheelgate House, 20-26 Wheelgate Malton North Yorkshire YO17 7HR",
    "addr:housenumber":"20-26",
    "addr:postcode":"yo17 7hr",
    "addr:street":"Wheelgate;Wheelgate",
    "iso:country":"GB",
    "sg:address":"Wheelgate House, 20-26 Wheelgate",
    "sg:city":"Malton",
    "sg:classifiers":[
        {
            "category":"Travel",
            "subcategory":"Travel Agent",
            "type":"Entertainment"
        }
    ],
    "sg:phone":"+44 1653 695500",
    "sg:postcode":"YO17 7HR",
    "sg:province":"North Yorkshire",
    "wof:name":"Sunwin Travel Ltd.",
    "wof:placetype":"venue"
},
  "geometry": {"coordinates":[-0.796775,54.135113],"type":"Point"}
}