{
  "type": "Feature",
  "properties": {
    "addr:full":"60 Birmingham Street Oldbury West Midlands B69 4DZ",
    "addr:housenumber":"60",
    "addr:postcode":"b69 4dz",
    "addr:street":"Birmingham Street",
    "iso:country":"GB",
    "sg:address":"60 Birmingham Street",
    "sg:city":"Oldbury",
    "sg:classifiers":[
        {
            "category":"Professional",
            "subcategory":"Business Services",
            "type":"Services"
        },
        {
            "category":"Casinos & Gambling",
            "type":"Entertainment"
        }
    ],
    "sg:phone":"+44 121 552 3113",
    "sg:postcode":"B69 4DZ",
    "sg:province":"West Midlands",
    "sg:tags":[
        "turf",
        "accountant",
        "bookmaker"
    ],
    "wof:name":"S T Carpenter & N W Jones",
    "wof:placetype":"venue"
},
  "geometry": {"coordinates":[-2.013121,52.50285],"type":"Point"}
}