{
  "type": "Feature",
  "properties": {
    "iso:country":"GB",
    "sg:address":"2 Trafalgar Square",
    "sg:city":"Scarborough",
    "sg:classifiers":[
        {
            "category":"Social Services",
            "type":"Services"
        },
        {
            "category":"Government",
            "subcategory":"Office",
            "type":"Public Place"
        }
    ],
    "sg:phone":"+44 1723 375694",
    "sg:postcode":"YO12 7PY",
    "sg:province":"North Yorkshire",
    "sg:tags":[
        "local",
        "ds"
    ],
    "wof:name":"Mental Health Resource Unit",
    "wof:placetype":"venue"
},
  "geometry": {"coordinates":[-0.4026780128,54.2878990173],"type":"Point"}
}