{
  "type": "Feature",
  "properties": {
    "addr:full":"Rosewater, St Teath Bodmin Cornwall PL30 3LA",
    "addr:postcode":"pl30 3la",
    "addr:street":"Rosewater St Teath",
    "iso:country":"GB",
    "sg:address":"Rosewater, St Teath",
    "sg:city":"Bodmin",
    "sg:classifiers":[
        {
            "category":"Recreation",
            "subcategory":"Campground",
            "type":"Entertainment"
        }
    ],
    "sg:postcode":"PL30 3LA",
    "sg:province":"Cornwall",
    "sg:tags":[
        "site",
        "camping"
    ],
    "wof:name":"Trepentor Caravans",
    "wof:placetype":"venue"
},
  "geometry": {"coordinates":[-4.74242,50.59388],"type":"Point"}
}