{
  "type": "Feature",
  "properties": {
    "addr:full":"Ashton Road, Long Ashton Bristol City of Bristol BS3 2HB",
    "addr:postcode":"bs3 2hb",
    "addr:street":"Ashton Road",
    "iso:country":"GB",
    "sg:address":"Ashton Road, Long Ashton",
    "sg:city":"Bristol",
    "sg:classifiers":[
        {
            "category":"Community Center",
            "type":"Public Place"
        }
    ],
    "sg:phone":"+44 117 953 1010",
    "sg:postcode":"BS3 2HB",
    "sg:province":"City of Bristol",
    "sg:tags":[
        "recreation",
        "leisure",
        "centre"
    ],
    "wof:name":"The David Lloyd Club",
    "wof:placetype":"venue"
},
  "geometry": {"coordinates":[-2.6299140453,51.4396514893],"type":"Point"}
}