{
  "type": "Feature",
  "properties": {
    "addr:full":"Salisbury House, London Wall London Greater London EC2M 5QU",
    "addr:postcode":"ec2m 5qu",
    "iso:country":"GB",
    "sg:address":"Salisbury House, London Wall",
    "sg:city":"London",
    "sg:classifiers":[
        {
            "category":"Professional",
            "subcategory":"Accounting & Tax Preparation",
            "type":"Services"
        }
    ],
    "sg:phone":"+44 20 7588 3541",
    "sg:postcode":"EC2M 5QU",
    "sg:province":"Greater London",
    "sg:tags":[
        "accountant"
    ],
    "wof:name":"West Wake Price & Co. Ltd.",
    "wof:placetype":"venue"
},
  "geometry": {"coordinates":[-0.088494,51.517296],"type":"Point"}
}