{
  "type": "Feature",
  "properties": {
    "iso:country":"GB",
    "sg:address":"Ferndale Road, Tylorstows",
    "sg:city":"Ferndale",
    "sg:classifiers":[
        {
            "category":"Health Services",
            "subcategory":"Doctor",
            "type":"Services"
        },
        {
            "category":"Health Services",
            "subcategory":"Clinic",
            "type":"Services"
        }
    ],
    "sg:phone":"+44 1443 730169",
    "sg:postcode":"CF43 3HD",
    "sg:province":"Rhondda, Cynon, Taff",
    "sg:tags":[
        "nh",
        "practitioners"
    ],
    "wof:name":"Tylorstows Surgery",
    "wof:placetype":"venue"
},
  "geometry": {"coordinates":[-3.432696,51.642132],"type":"Point"}
}