{
  "type": "Feature",
  "properties": {
    "iso:country":"GB",
    "sg:address":"Station Rd, Coleshill",
    "sg:city":"Birmingham",
    "sg:classifiers":[
        {
            "category":"Retail",
            "subcategory":"Auto Repair",
            "type":"Services"
        }
    ],
    "sg:phone":"+44 1675 467114",
    "sg:postcode":"B46 1JG",
    "sg:province":"Warwickshire",
    "sg:tags":[
        "electrician"
    ],
    "wof:name":"Lynk Technologies Ltd",
    "wof:placetype":"venue"
},
  "geometry": {"coordinates":[-1.707464,52.509323],"type":"Point"}
}