{
  "type": "Feature",
  "properties": {
    "addr:full":"197-199 Gleneagles Road Sunderland Tyne and Wear SR4 8JD",
    "addr:housenumber":"197-199",
    "addr:postcode":"sr4 8jd",
    "addr:street":"Gleneagles Road",
    "iso:country":"GB",
    "sg:address":"197-199 Gleneagles Road",
    "sg:city":"Sunderland",
    "sg:classifiers":[
        {
            "category":"Education",
            "subcategory":"Special Training",
            "type":"Public Place"
        }
    ],
    "sg:postcode":"SR4 8JD",
    "sg:province":"Tyne and Wear",
    "sg:tags":[
        "product",
        "centre"
    ],
    "wof:name":"G A T E S",
    "wof:placetype":"venue"
},
  "geometry": {"coordinates":[-1.4422830343,54.8869400024],"type":"Point"}
}