{
  "type": "Feature",
  "properties": {
    "addr:full":"22 Crellin St Barrow-in-furness Cumbria LA14 1DU",
    "addr:housenumber":"22",
    "addr:postcode":"la14 1du",
    "addr:street":"Crellin St",
    "iso:country":"GB",
    "sg:address":"22 Crellin St",
    "sg:city":"Barrow-in-furness",
    "sg:classifiers":[
        {
            "category":"Personal",
            "subcategory":"Beauty Salon",
            "type":"Services"
        }
    ],
    "sg:postcode":"LA14 1DU",
    "sg:province":"Cumbria",
    "sg:tags":[
        "unisex",
        "hairdresser"
    ],
    "wof:name":"Rawlings,Lisa,",
    "wof:placetype":"venue"
},
  "geometry": {"coordinates":[-3.2241239548,54.1136856079],"type":"Point"}
}