{
  "type": "Feature",
  "properties": {
    "addr:full":"43 West Rd Bridgend Bridgend CF31 4HD",
    "addr:housenumber":"43",
    "addr:postcode":"cf31 4hd",
    "addr:street":"West Rd",
    "iso:country":"GB",
    "sg:address":"43 West Rd",
    "sg:city":"Bridgend",
    "sg:classifiers":[
        {
            "category":"Professional",
            "subcategory":"Engineering",
            "type":"Services"
        }
    ],
    "sg:phone":"+44 1656 663120",
    "sg:postcode":"CF31 4HD",
    "sg:province":"Bridgend",
    "sg:tags":[
        "design",
        "engineer"
    ],
    "wof:name":"S.P.R Hooper",
    "wof:placetype":"venue"
},
  "geometry": {"coordinates":[-3.586971,51.507111],"type":"Point"}
}