{
  "type": "Feature",
  "properties": {
    "addr:full":"12 Seaway Avenue Christchurch Dorset BH23 4EX",
    "addr:housenumber":"12",
    "addr:postcode":"bh23 4ex",
    "addr:street":"Seaway Avenue",
    "iso:country":"GB",
    "sg:address":"12 Seaway Avenue",
    "sg:city":"Christchurch",
    "sg:classifiers":[
        {
            "category":"Professional",
            "type":"Services"
        },
        {
            "category":"Professional",
            "subcategory":"Printing & Photocopies",
            "type":"Services"
        }
    ],
    "sg:phone":"+44 1425 277776",
    "sg:postcode":"BH23 4EX",
    "sg:province":"Dorset",
    "sg:tags":[
        "printer",
        "tag",
        "pub",
        "label",
        "computer",
        "directory"
    ],
    "wof:name":"Namemark",
    "wof:placetype":"venue"
},
  "geometry": {"coordinates":[-1.728101,50.737755],"type":"Point"}
}