{
  "type": "Feature",
  "properties": {
    "addr:full":"2 Winton Road, Bowdon Altrincham Cheshire WA14 2PG",
    "addr:housenumber":"2",
    "addr:postcode":"wa14 2pg",
    "addr:street":"Winton Road",
    "iso:country":"GB",
    "sg:address":"2 Winton Road, Bowdon",
    "sg:city":"Altrincham",
    "sg:classifiers":[
        {
            "category":"Arena",
            "subcategory":"Sports Club",
            "type":"Entertainment"
        }
    ],
    "sg:phone":"+44 161 928 3905",
    "sg:postcode":"WA14 2PG",
    "sg:province":"Cheshire",
    "wof:name":"The Bowdon Bowling & Lawn Tennis Club Ltd.",
    "wof:placetype":"venue"
},
  "geometry": {"coordinates":[-2.360154,53.378891],"type":"Point"}
}