{
  "type": "Feature",
  "properties": {
    "iso:country":"GB",
    "sg:address":"34 Mason Street",
    "sg:city":"Wolverhampton",
    "sg:classifiers":[
        {
            "category":"Shopping",
            "subcategory":"Pharmacy",
            "type":"Retail Goods"
        }
    ],
    "sg:phone":"+44 1902 659887",
    "sg:postcode":"WV2 3AG",
    "sg:province":"West Midlands",
    "sg:tags":[
        "medicine",
        "therapy"
    ],
    "wof:name":"Susan Brock",
    "wof:placetype":"venue"
},
  "geometry": {"coordinates":[-2.128533,52.574932],"type":"Point"}
}