{
  "type": "Feature",
  "properties": {
    "iso:country":"GB",
    "sg:address":"305 Babbacombe Rd",
    "sg:city":"Torquay",
    "sg:classifiers":[
        {
            "category":"Building & Trades",
            "subcategory":"Construction",
            "type":"Services"
        }
    ],
    "sg:phone":"+44 1803 294593",
    "sg:postcode":"TQ1 3TB",
    "sg:province":"Devon",
    "sg:tags":[
        "tile",
        "fitting",
        "tiling",
        "laying",
        "contractor"
    ],
    "wof:name":"Devon Ceramic Tiling",
    "wof:placetype":"venue"
},
  "geometry": {"coordinates":[-3.507608,50.474518],"type":"Point"}
}