{
  "type": "Feature",
  "properties": {
    "iso:country":"GB",
    "sg:address":"44 Main Street, Milngavie",
    "sg:city":"Glasgow",
    "sg:classifiers":[
        {
            "category":"Home & Garden",
            "subcategory":"Home Furnishings",
            "type":"Retail Goods"
        }
    ],
    "sg:phone":"+44 141 955 1473",
    "sg:postcode":"G62 6BU",
    "sg:province":"East Dunbartonshire",
    "sg:tags":[
        "furnishers",
        "planner",
        "kitchen"
    ],
    "wof:name":"Moben Kitchens",
    "wof:placetype":"venue"
},
  "geometry": {"coordinates":[-4.317808,55.939709],"type":"Point"}
}