{
  "type": "Feature",
  "properties": {
    "addr:full":"1 New Road Ware Hertfordshire SG12 7BS",
    "addr:housenumber":"1",
    "addr:postcode":"sg12 7bs",
    "addr:street":"New Road Ware",
    "iso:country":"GB",
    "sg:address":"1 New Road",
    "sg:city":"Ware",
    "sg:classifiers":[
        {
            "category":"Shopping",
            "subcategory":"Pets & Pet Supplies",
            "type":"Retail Goods"
        }
    ],
    "sg:phone":"+44 1920 460984",
    "sg:postcode":"SG12 7BS",
    "sg:province":"Hertfordshire",
    "sg:tags":[
        "shop"
    ],
    "wof:name":"Di's Pet Store",
    "wof:placetype":"venue"
},
  "geometry": {"coordinates":[-0.029543,51.810886],"type":"Point"}
}