{
  "type": "Feature",
  "properties": {
    "addr:full":"131-133 Fountain Road, Tooting London Greater London SW17 0HH",
    "addr:housenumber":"131-133",
    "addr:postcode":"sw17 0hh",
    "addr:street":"Fountain Road",
    "iso:country":"GB",
    "sg:address":"131-133 Fountain Road, Tooting",
    "sg:city":"London",
    "sg:classifiers":[
        {
            "category":"Manufacturing",
            "subcategory":"Building Materials",
            "type":"Manufacturing & Wholesale Goods"
        }
    ],
    "sg:phone":"+44 20 8767 6277",
    "sg:postcode":"SW17 0HH",
    "sg:province":"Greater London",
    "sg:tags":[
        "merchant",
        "builder"
    ],
    "wof:name":"G & G Timber & Builders Merchants Ltd.",
    "wof:placetype":"venue"
},
  "geometry": {"coordinates":[-0.177584,51.427628],"type":"Point"}
}