{
  "type": "Feature",
  "properties": {
    "iso:country":"GB",
    "sg:address":"66 Plaistow Lane",
    "sg:city":"Bromley",
    "sg:classifiers":[
        {
            "category":"Social Services",
            "subcategory":"Retirement Home",
            "type":"Services"
        }
    ],
    "sg:phone":"+44 20 8466 5611",
    "sg:postcode":"BR1 3JE",
    "sg:province":"Kent",
    "sg:tags":[
        "residential",
        "care"
    ],
    "wof:name":"Ashdene Residential Home",
    "wof:placetype":"venue"
},
  "geometry": {"coordinates":[0.024831,51.412991],"type":"Point"}
}