{
  "type": "Feature",
  "properties": {
    "addr:full":"7 Telford Place, Cumbernauld Glasgow Falkirk G67 2NH",
    "addr:housenumber":"7",
    "addr:postcode":"g67 2nh",
    "addr:street":"Telford Place",
    "iso:country":"GB",
    "sg:address":"7 Telford Place, Cumbernauld",
    "sg:city":"Glasgow",
    "sg:classifiers":[
        {
            "category":"Building & Trades",
            "subcategory":"Cleaning & Sanitation",
            "type":"Services"
        }
    ],
    "sg:phone":"+44 1236 451143",
    "sg:postcode":"G67 2NH",
    "sg:province":"Falkirk",
    "sg:tags":[
        "contracting",
        "commercial"
    ],
    "sg:website":"http://www.andron.co.uk",
    "wof:name":"Andron Contract Services Ltd",
    "wof:placetype":"venue"
},
  "geometry": {"coordinates":[-3.981128931,55.9384880066],"type":"Point"}
}