{
  "type": "Feature",
  "properties": {
    "addr:full":"6 Scaitcliffe St Accrington Lancashire BB5 0RF",
    "addr:housenumber":"6",
    "addr:postcode":"bb5 0rf",
    "addr:street":"Scaitcliffe St",
    "iso:country":"GB",
    "sg:address":"6 Scaitcliffe St",
    "sg:city":"Accrington",
    "sg:classifiers":[
        {
            "category":"Utilities",
            "subcategory":"Natural Gas",
            "type":"Services"
        }
    ],
    "sg:phone":"+44 1254 232627",
    "sg:postcode":"BB5 0RF",
    "sg:province":"Lancashire",
    "sg:tags":[
        "control",
        "energy",
        "management",
        "system"
    ],
    "wof:name":"J & T Livesey",
    "wof:placetype":"venue"
},
  "geometry": {"coordinates":[-2.3725690842,53.7530517578],"type":"Point"}
}