{
  "type": "Feature",
  "properties": {
    "addr:full":"26 Market Street Crewe Cheshire CW1 2EL",
    "addr:housenumber":"26",
    "addr:postcode":"cw1 2el",
    "addr:street":"Market Street",
    "iso:country":"GB",
    "sg:address":"26 Market Street",
    "sg:city":"Crewe",
    "sg:classifiers":[
        {
            "category":"Shopping",
            "subcategory":"Books",
            "type":"Retail Goods"
        }
    ],
    "sg:phone":"+44 1270 258507",
    "sg:postcode":"CW1 2EL",
    "sg:province":"Cheshire",
    "sg:tags":[
        "bookseller"
    ],
    "wof:name":"Oracle Books",
    "wof:placetype":"venue"
},
  "geometry": {"coordinates":[-2.441173,53.097702],"type":"Point"}
}