{
  "type": "Feature",
  "properties": {
    "iso:country":"GB",
    "sg:address":"50 Church Street",
    "sg:city":"London",
    "sg:classifiers":[
        {
            "category":"Personal",
            "subcategory":"Beauty Salon",
            "type":"Services"
        }
    ],
    "sg:phone":"+44 20 7724 7727",
    "sg:postcode":"NW8 8EP",
    "sg:province":"Greater London",
    "sg:tags":[
        "unisex",
        "hairdresser"
    ],
    "wof:name":"Snipping Image Hair Workshop",
    "wof:placetype":"venue"
},
  "geometry": {"coordinates":[-0.1701249927,51.5237579346],"type":"Point"}
}