{
  "type": "Feature",
  "properties": {
    "addr:full":"Unit 6, Institute Works Birmingham West Midlands B17 9JT",
    "addr:housenumber":"unit 6",
    "addr:postcode":"b17 9jt",
    "addr:street":"Works",
    "iso:country":"GB",
    "sg:address":"Unit 6, Institute Works",
    "sg:city":"Birmingham",
    "sg:classifiers":[
        {
            "category":"Food & Beverages",
            "subcategory":"Liquor & Beverages",
            "type":"Retail Goods"
        }
    ],
    "sg:phone":"+44 121 687 6969",
    "sg:postcode":"B17 9JT",
    "sg:province":"West Midlands",
    "sg:tags":[
        "beer",
        "spirit",
        "wines"
    ],
    "wof:name":"Devere & Co",
    "wof:placetype":"venue"
},
  "geometry": {"coordinates":[-1.908604,52.478596],"type":"Point"}
}