{
  "type": "Feature",
  "properties": {
    "addr:full":"63 Greaves Lane, Stannington Sheffield South Yorkshire S6 6BB",
    "addr:housenumber":"63",
    "addr:postcode":"s6 6bb",
    "addr:street":"Greaves Lane",
    "iso:country":"GB",
    "sg:address":"63 Greaves Lane, Stannington",
    "sg:city":"Sheffield",
    "sg:classifiers":[
        {
            "category":"Retail",
            "subcategory":"Driving School",
            "type":"Services"
        }
    ],
    "sg:phone":"+44 114 233 9059",
    "sg:postcode":"S6 6BB",
    "sg:province":"South Yorkshire",
    "wof:name":"A School of Motoring",
    "wof:placetype":"venue"
},
  "geometry": {"coordinates":[-1.5423909426,53.396068573],"type":"Point"}
}