{
  "type": "Feature",
  "properties": {
    "addr:full":"The Garage, The Street Diss Norfolk IP22 1BX",
    "addr:postcode":"ip22 1bx",
    "addr:street":"The Street",
    "iso:country":"GB",
    "sg:address":"The Garage, The Street",
    "sg:city":"Diss",
    "sg:classifiers":[
        {
            "category":"Bus Charters",
            "type":"Transportation"
        }
    ],
    "sg:phone":"+44 1379 898202",
    "sg:postcode":"IP22 1BX",
    "sg:province":"Norfolk",
    "sg:tags":[
        "hire",
        "coach"
    ],
    "wof:name":"Simonds of Botesdale Ltd.",
    "wof:placetype":"venue"
},
  "geometry": {"coordinates":[1.004251,52.358227],"type":"Point"}
}