{
  "type": "Feature",
  "properties": {
    "addr:full":"Bilton Road, Bletchley Milton Keynes Buckinghamshire MK1 1HW",
    "addr:postcode":"mk1 1hw",
    "addr:street":"Bilton Road",
    "iso:country":"GB",
    "sg:address":"Bilton Road, Bletchley",
    "sg:city":"Milton Keynes",
    "sg:classifiers":[
        {
            "category":"Autos & Motor Vehicles",
            "subcategory":"Auto Supplies",
            "type":"Retail Goods"
        }
    ],
    "sg:phone":"+44 1908 374030",
    "sg:postcode":"MK1 1HW",
    "sg:province":"Buckinghamshire",
    "sg:tags":[
        "tyre"
    ],
    "wof:name":"National Tyres and Autocare",
    "wof:placetype":"venue"
},
  "geometry": {"coordinates":[-0.718694,52.003296],"type":"Point"}
}