{
  "type": "Feature",
  "properties": {
    "addr:full":"Robin Hood Bay Whitby North Yorkshire YO22 4QH",
    "addr:postcode":"yo22 4qh",
    "addr:street":"Bay",
    "iso:country":"GB",
    "sg:address":"Robin Hood Bay",
    "sg:city":"Whitby",
    "sg:classifiers":[
        {
            "category":"Fast Food",
            "type":"Food & Drink"
        }
    ],
    "sg:phone":"+44 1947 880592",
    "sg:postcode":"YO22 4QH",
    "sg:province":"North Yorkshire",
    "sg:tags":[
        "away",
        "take"
    ],
    "wof:name":"Flask Country Kitchen",
    "wof:placetype":"venue"
},
  "geometry": {"coordinates":[-0.584276,54.424286],"type":"Point"}
}