{
  "type": "Feature",
  "properties": {
    "addr:full":"259 Putney Bridge Road London Greater London SW15 2PU",
    "addr:housenumber":"259",
    "addr:postcode":"sw15 2pu",
    "addr:street":"Putney Bridge Road",
    "iso:country":"GB",
    "sg:address":"259 Putney Bridge Road",
    "sg:city":"London",
    "sg:classifiers":[
        {
            "category":"Retail",
            "subcategory":"Laundry & Dry Cleaning",
            "type":"Services"
        }
    ],
    "sg:phone":"+44 20 8788 2538",
    "sg:postcode":"SW15 2PU",
    "sg:province":"Greater London",
    "sg:tags":[
        "alteration"
    ],
    "wof:name":"Park View Dry Cleaners & Launderers",
    "wof:placetype":"venue"
},
  "geometry": {"coordinates":[-0.211263001,51.4632072449],"type":"Point"}
}