{
  "type": "Feature",
  "properties": {
    "iso:country":"GB",
    "sg:address":"13 West Street",
    "sg:city":"Lewes",
    "sg:classifiers":[
        {
            "category":"Building & Trades",
            "subcategory":"Construction",
            "type":"Services"
        }
    ],
    "sg:phone":"+44 1903 815808",
    "sg:postcode":"BN7 2NZ",
    "sg:province":"East Sussex",
    "sg:tags":[
        "demolition",
        "contractor"
    ],
    "wof:name":"G T Demolition Ltd.",
    "wof:placetype":"venue"
},
  "geometry": {"coordinates":[0.010965,50.874474],"type":"Point"}
}