{
  "type": "Feature",
  "properties": {
    "addr:full":"1c Thoroughfare Woodbridge Suffolk IP12 1AA",
    "addr:housenumber":"1c",
    "addr:postcode":"ip12 1aa",
    "addr:street":"Thoroughfare",
    "iso:country":"GB",
    "sg:address":"1c Thoroughfare",
    "sg:city":"Woodbridge",
    "sg:classifiers":[
        {
            "category":"Health Services",
            "subcategory":"Dentist",
            "type":"Services"
        }
    ],
    "sg:phone":"+44 1394 388150",
    "sg:postcode":"IP12 1AA",
    "sg:province":"Suffolk",
    "sg:tags":[
        "technician",
        "instrument",
        "dental"
    ],
    "wof:name":"A Milton",
    "wof:placetype":"venue"
},
  "geometry": {"coordinates":[1.32182,52.095638],"type":"Point"}
}