{
  "type": "Feature",
  "properties": {
    "iso:country":"GB",
    "sg:address":"121 St Marychurch Road",
    "sg:city":"Torquay",
    "sg:classifiers":[
        {
            "category":"Home & Garden",
            "subcategory":"Carpets & Floor Coverings",
            "type":"Retail Goods"
        }
    ],
    "sg:phone":"+44 1803 327242",
    "sg:postcode":"TQ1 3HL",
    "sg:province":"Devon",
    "sg:tags":[
        "carpets",
        "rug",
        "matting"
    ],
    "wof:name":"Foot's Carpets & Upholsterers",
    "wof:placetype":"venue"
},
  "geometry": {"coordinates":[-3.527604,50.477051],"type":"Point"}
}