{
  "type": "Feature",
  "properties": {
    "addr:full":"51 West Bowling Green Street Edinburgh City of Edinburgh EH6 5NX",
    "addr:housenumber":"51",
    "addr:postcode":"eh6 5nx",
    "addr:street":"West Bowling Green Street",
    "iso:country":"GB",
    "sg:address":"51 West Bowling Green Street",
    "sg:city":"Edinburgh",
    "sg:classifiers":[
        {
            "category":"Professional",
            "subcategory":"Engineering",
            "type":"Services"
        },
        {
            "category":"Home & Garden",
            "subcategory":"Building Materials",
            "type":"Retail Goods"
        },
        {
            "category":"Building & Trades",
            "subcategory":"Electrical",
            "type":"Services"
        }
    ],
    "sg:phone":"+44 131 553 5222",
    "sg:postcode":"EH6 5NX",
    "sg:province":"City of Edinburgh",
    "sg:tags":[
        "garage",
        "engineer",
        "door",
        "electrician",
        "contractor"
    ],
    "wof:name":"Lothian Electric",
    "wof:placetype":"venue"
},
  "geometry": {"coordinates":[-3.1861341,55.9723320007],"type":"Point"}
}