{
  "type": "Feature",
  "properties": {
    "addr:full":"8 High Street Maldon Essex CM9 5PJ",
    "addr:housenumber":"8",
    "addr:postcode":"cm9 5pj",
    "addr:street":"High Street",
    "iso:country":"GB",
    "sg:address":"8 High Street",
    "sg:city":"Maldon",
    "sg:classifiers":[
        {
            "category":"Restaurant",
            "type":"Food & Drink"
        }
    ],
    "sg:postcode":"CM9 5PJ",
    "sg:province":"Essex",
    "sg:tags":[
        "american"
    ],
    "wof:name":"Malones Diner",
    "wof:placetype":"venue"
},
  "geometry": {"coordinates":[0.6751639843,51.7312164307],"type":"Point"}
}