{
  "type": "Feature",
  "properties": {
    "iso:country":"GB",
    "sg:address":"59a The Concourse",
    "sg:city":"Skelmersdale",
    "sg:classifiers":[
        {
            "category":"Travel",
            "subcategory":"Travel Agent",
            "type":"Entertainment"
        }
    ],
    "sg:phone":"+44 1695 722305",
    "sg:postcode":"WN8 6LQ",
    "sg:province":"Lancashire",
    "wof:name":"United Norwest Travel Co-Op",
    "wof:placetype":"venue"
},
  "geometry": {"coordinates":[-2.7701659203,53.5566558838],"type":"Point"}
}