{
  "type": "Feature",
  "properties": {
    "iso:country":"GB",
    "sg:address":"3 Woodfold Close",
    "sg:city":"Blackburn",
    "sg:classifiers":[
        {
            "category":"Building & Trades",
            "subcategory":"Construction",
            "type":"Services"
        }
    ],
    "sg:postcode":"BB2 7NZ",
    "sg:province":"Lancashire",
    "sg:tags":[
        "builder"
    ],
    "wof:name":"J Hill",
    "wof:placetype":"venue"
},
  "geometry": {"coordinates":[-2.547162,53.77533],"type":"Point"}
}