{
  "type": "Feature",
  "properties": {
    "addr:full":"19 Abergele Road Colwyn Bay Conwy LL29 7RS",
    "addr:housenumber":"19",
    "addr:postcode":"ll29 7rs",
    "addr:street":"Abergele Road",
    "iso:country":"GB",
    "sg:address":"19 Abergele Road",
    "sg:city":"Colwyn Bay",
    "sg:classifiers":[
        {
            "category":"Shopping",
            "subcategory":"Department Store",
            "type":"Retail Goods"
        },
        {
            "category":"Transit Center",
            "subcategory":"Freight",
            "type":"Transportation"
        }
    ],
    "sg:phone":"+44 1492 530125",
    "sg:postcode":"LL29 7RS",
    "sg:province":"Conwy",
    "sg:tags":[
        "shop",
        "craft",
        "centre"
    ],
    "wof:name":"Tanias Allsorts",
    "wof:placetype":"venue"
},
  "geometry": {"coordinates":[-3.726491,53.29467],"type":"Point"}
}