{
  "type": "Feature",
  "properties": {
    "iso:country":"GB",
    "sg:address":"157 Fisherton Street",
    "sg:city":"Salisbury",
    "sg:classifiers":[
        {
            "category":"Fast Food",
            "type":"Food & Drink"
        }
    ],
    "sg:postcode":"SP2 7RP",
    "sg:province":"Wiltshire",
    "sg:tags":[
        "away",
        "take"
    ],
    "wof:name":"Shahnoors",
    "wof:placetype":"venue"
},
  "geometry": {"coordinates":[-1.8049850464,51.0717658997],"type":"Point"}
}