{
  "type": "Feature",
  "properties": {
    "addr:full":"23 Willowbrook Close Ashby-de-la-zouch Derbyshire LE65 1JX",
    "addr:housenumber":"23",
    "addr:postcode":"le65 1jx",
    "addr:street":"Willowbrook Close",
    "iso:country":"GB",
    "sg:address":"23 Willowbrook Close",
    "sg:city":"Ashby-de-la-zouch",
    "sg:classifiers":[
        {
            "category":"Health Services",
            "subcategory":"Dentist",
            "type":"Services"
        }
    ],
    "sg:phone":"+44 1530 413976",
    "sg:postcode":"LE65 1JX",
    "sg:province":"Derbyshire",
    "sg:tags":[
        "technician",
        "dental"
    ],
    "wof:name":"Ashby Dental Laboratory",
    "wof:placetype":"venue"
},
  "geometry": {"coordinates":[-1.4711289406,52.7546463013],"type":"Point"}
}