{
  "type": "Feature",
  "properties": {
    "addr:full":"87 Rayleigh Rd Leigh On Sea Essex SS9 5UZ",
    "addr:housenumber":"87",
    "addr:postcode":"ss9 5uz",
    "addr:street":"Rayleigh Rd",
    "iso:country":"GB",
    "sg:address":"87 Rayleigh Rd",
    "sg:city":"Leigh On Sea",
    "sg:classifiers":[
        {
            "category":"Building & Trades",
            "subcategory":"Equipment Rental",
            "type":"Services"
        }
    ],
    "sg:phone":"+44 1702 524371",
    "sg:postcode":"SS9 5UZ",
    "sg:province":"Essex",
    "sg:tags":[
        "plant",
        "machinery"
    ],
    "wof:name":"Tred Plant Hire Ltd",
    "wof:placetype":"venue"
},
  "geometry": {"coordinates":[0.662424,51.565323],"type":"Point"}
}