{
  "type": "Feature",
  "properties": {
    "iso:country":"GB",
    "sg:address":"9 Millbrook Street",
    "sg:city":"Cheltenham",
    "sg:classifiers":[
        {
            "category":"Retail",
            "subcategory":"Auto Repair",
            "type":"Services"
        }
    ],
    "sg:phone":"+44 1242 222710",
    "sg:postcode":"GL50 3RR",
    "sg:province":"Gloucestershire",
    "sg:tags":[
        "modification",
        "garage"
    ],
    "wof:name":"Mark Baynes Motors",
    "wof:placetype":"venue"
},
  "geometry": {"coordinates":[-2.0867569447,51.9025192261],"type":"Point"}
}