{
  "type": "Feature",
  "properties": {
    "iso:country":"GB",
    "sg:address":"311 West Ct, 101 Bull Ring Centre",
    "sg:city":"Birmingham",
    "sg:classifiers":[
        {
            "category":"Bars & Pubs",
            "type":"Food & Drink"
        }
    ],
    "sg:phone":"+44 121 643 3127",
    "sg:postcode":"B5 4NY",
    "sg:province":"West Midlands",
    "sg:tags":[
        "pubs",
        "inn"
    ],
    "wof:name":"Peacocks",
    "wof:placetype":"venue"
},
  "geometry": {"coordinates":[-1.8983,52.475811],"type":"Point"}
}