{
  "type": "Feature",
  "properties": {
    "iso:country":"GB",
    "sg:address":"Wilmslow Road, Withington",
    "sg:city":"Manchester",
    "sg:classifiers":[
        {
            "category":"Health Services",
            "subcategory":"Hospital",
            "type":"Services"
        }
    ],
    "sg:phone":"+44 161 446 3000",
    "sg:postcode":"M20 4BX",
    "sg:province":"Greater Manchester",
    "wof:name":"Christie Hospital N H S Trust",
    "wof:placetype":"venue"
},
  "geometry": {"coordinates":[-2.222094,53.438065],"type":"Point"}
}