{
  "type": "Feature",
  "properties": {
    "addr:full":"145 Godstone Road Whyteleafe Surrey CR3 0EH",
    "addr:housenumber":"145",
    "addr:postcode":"cr3 0eh",
    "addr:street":"Godstone Road",
    "iso:country":"GB",
    "sg:address":"145 Godstone Road",
    "sg:city":"Whyteleafe",
    "sg:classifiers":[
        {
            "category":"Personal",
            "type":"Services"
        }
    ],
    "sg:postcode":"CR3 0EH",
    "sg:province":"Surrey",
    "sg:tags":[
        "consultant",
        "fitness"
    ],
    "wof:name":"Get Sweaty",
    "wof:placetype":"venue"
},
  "geometry": {"coordinates":[-0.079961,51.311211],"type":"Point"}
}