{
  "type": "Feature",
  "properties": {
    "addr:full":"Suite C4 New City Chambers Wakefield West Yorkshire WF1 2EP",
    "addr:postcode":"wf1 2ep",
    "addr:street":"West",
    "iso:country":"GB",
    "sg:address":"Suite C4 New City Chambers",
    "sg:city":"Wakefield",
    "sg:classifiers":[
        {
            "category":"Professional",
            "subcategory":"Employment Agencies",
            "type":"Services"
        }
    ],
    "sg:phone":"+44 1924 377266",
    "sg:postcode":"WF1 2EP",
    "sg:province":"West Yorkshire",
    "sg:tags":[
        "consultant"
    ],
    "wof:name":"Hays Specialist Recruitment Ltd.",
    "wof:placetype":"venue"
},
  "geometry": {"coordinates":[-1.5022369623,53.6983757019],"type":"Point"}
}