{
  "type": "Feature",
  "properties": {
    "addr:full":"Hill Farm, Tasburgh Norwich Norfolk NR15 1NL",
    "addr:postcode":"nr15 1nl",
    "addr:street":"Hill;Norwich",
    "iso:country":"GB",
    "sg:address":"Hill Farm, Tasburgh",
    "sg:city":"Norwich",
    "sg:classifiers":[
        {
            "category":"Farming",
            "subcategory":"Dairy Farm",
            "type":"Manufacturing & Wholesale Goods"
        }
    ],
    "sg:phone":"+44 1508 470338",
    "sg:postcode":"NR15 1NL",
    "sg:province":"Norfolk",
    "wof:name":"J F Bleach",
    "wof:placetype":"venue"
},
  "geometry": {"coordinates":[1.2526049614,52.5151329041],"type":"Point"}
}