{
  "type": "Feature",
  "properties": {
    "iso:country":"GB",
    "sg:address":"Units 9 & 10 Finchwood Farm",
    "sg:city":"Hayling Island",
    "sg:classifiers":[
        {
            "category":"Autos & Motor Vehicles",
            "subcategory":"Auto Supplies",
            "type":"Retail Goods"
        }
    ],
    "sg:postcode":"PO11 0QB",
    "sg:province":"Hampshire",
    "sg:tags":[
        "tyre"
    ],
    "wof:name":"Farmer,Matthew,",
    "wof:placetype":"venue"
},
  "geometry": {"coordinates":[-0.97014,50.812962],"type":"Point"}
}