{
  "type": "Feature",
  "properties": {
    "addr:full":"49 Liverpool Road North, Burscough Ormskirk Lancashire L40 0SA",
    "addr:housenumber":"49",
    "addr:postcode":"l40 0sa",
    "addr:street":"Liverpool Road North",
    "iso:country":"GB",
    "sg:address":"49 Liverpool Road North, Burscough",
    "sg:city":"Ormskirk",
    "sg:classifiers":[
        {
            "category":"Shopping",
            "subcategory":"Florist",
            "type":"Retail Goods"
        }
    ],
    "sg:phone":"+44 1704 895035",
    "sg:postcode":"L40 0SA",
    "sg:province":"Lancashire",
    "wof:name":"Flower Style by Laurie",
    "wof:placetype":"venue"
},
  "geometry": {"coordinates":[-2.8419320583,53.6039657593],"type":"Point"}
}