{
  "type": "Feature",
  "properties": {
    "addr:full":"17-18 Liquorpond Street Boston Lincolnshire PE21 8UF",
    "addr:housenumber":"17-18",
    "addr:postcode":"pe21 8uf",
    "addr:street":"Liquorpond Street",
    "iso:country":"GB",
    "sg:address":"17-18 Liquorpond Street",
    "sg:city":"Boston",
    "sg:classifiers":[
        {
            "category":"Bars & Pubs",
            "type":"Food & Drink"
        }
    ],
    "sg:phone":"+44 1205 354578",
    "sg:postcode":"PE21 8UF",
    "sg:province":"Lincolnshire",
    "sg:tags":[
        "pubs",
        "inn"
    ],
    "wof:name":"The Five Lamps",
    "wof:placetype":"venue"
},
  "geometry": {"coordinates":[-0.026325,52.973743],"type":"Point"}
}