{
  "type": "Feature",
  "properties": {
    "addr:full":"Lodgefield Farm, Blackham Tunbridge Wells East Sussex TN3 9TN",
    "addr:postcode":"tn3 9tn",
    "addr:street":"Blackham",
    "iso:country":"GB",
    "sg:address":"Lodgefield Farm, Blackham",
    "sg:city":"Tunbridge Wells",
    "sg:classifiers":[
        {
            "category":"Professional",
            "subcategory":"Management & Consulting",
            "type":"Services"
        },
        {
            "category":"Conference Center",
            "type":"Public Place"
        }
    ],
    "sg:phone":"+44 1892 740806",
    "sg:postcode":"TN3 9TN",
    "sg:province":"East Sussex",
    "sg:tags":[
        "marketing",
        "consultant"
    ],
    "wof:name":"Live & Direct Ltd.",
    "wof:placetype":"venue"
},
  "geometry": {"coordinates":[0.141633,51.135208],"type":"Point"}
}