{
  "type": "Feature",
  "properties": {
    "iso:country":"GB",
    "sg:address":"Furze Brake, Whitepit Lane",
    "sg:city":"Newport",
    "sg:classifiers":[
        {
            "category":"Social Services",
            "subcategory":"Adult Care",
            "type":"Services"
        },
        {
            "category":"Social Services",
            "subcategory":"Retirement Home",
            "type":"Services"
        }
    ],
    "sg:phone":"+44 1983 521244",
    "sg:postcode":"PO30 1NJ",
    "sg:province":"Isle of Wight",
    "sg:tags":[
        "housing",
        "sheltered",
        "accommodation"
    ],
    "wof:name":"Isle Of Wight Housing Association Ltd",
    "wof:placetype":"venue"
},
  "geometry": {"coordinates":[-1.2959389687,50.7000999451],"type":"Point"}
}