{
  "type": "Feature",
  "properties": {
    "addr:full":"Short Bridge Street Llanidloes Powys SY18 6AD",
    "addr:postcode":"sy18 6ad",
    "addr:street":"Short Bridge Street",
    "iso:country":"GB",
    "sg:address":"Short Bridge Street",
    "sg:city":"Llanidloes",
    "sg:classifiers":[
        {
            "category":"Travel",
            "subcategory":"Hotels & Motels",
            "type":"Entertainment"
        }
    ],
    "sg:phone":"+44 1686 412583",
    "sg:postcode":"SY18 6AD",
    "sg:province":"Powys",
    "wof:name":"The Royal Head Hotel",
    "wof:placetype":"venue"
},
  "geometry": {"coordinates":[-3.542364,52.449097],"type":"Point"}
}