{
  "type": "Feature",
  "properties": {
    "addr:full":"15 The Square, Alvechurch Birmingham Worcestershire B48 7LA",
    "addr:housenumber":"15",
    "addr:postcode":"b48 7la",
    "addr:street":"The Square Alvechurch",
    "iso:country":"GB",
    "sg:address":"15 The Square, Alvechurch",
    "sg:city":"Birmingham",
    "sg:classifiers":[
        {
            "category":"Personal",
            "subcategory":"Beauty Salon",
            "type":"Services"
        }
    ],
    "sg:phone":"+44 121 447 8399",
    "sg:postcode":"B48 7LA",
    "sg:province":"Worcestershire",
    "sg:tags":[
        "unisex",
        "hairdresser"
    ],
    "wof:name":"George Davis Hairdressing",
    "wof:placetype":"venue"
},
  "geometry": {"coordinates":[-1.9594479799,52.3516349792],"type":"Point"}
}