{
  "type": "Feature",
  "properties": {
    "addr:full":"Unit 1 Barton Business Park, 60 Cawdor Street, Eccles Manchester Greater Manchester M30 0QF",
    "addr:housenumber":"unit 1;60",
    "addr:postcode":"m30 0qf",
    "addr:street":"Barton Business Park;Cawdor Street",
    "iso:country":"GB",
    "sg:address":"Unit 1 Barton Business Park, 60 Cawdor Street, Eccles",
    "sg:city":"Manchester",
    "sg:classifiers":[
        {
            "category":"Home & Garden",
            "subcategory":"Hardware",
            "type":"Retail Goods"
        }
    ],
    "sg:postcode":"M30 0QF",
    "sg:province":"Greater Manchester",
    "sg:tags":[
        "equipment",
        "welding"
    ],
    "wof:name":"Excel Welding Supply & Services Ltd.",
    "wof:placetype":"venue"
},
  "geometry": {"coordinates":[-2.3445689678,53.4829788208],"type":"Point"}
}