{
  "type": "Feature",
  "properties": {
    "addr:full":"106 Chase Side Southgate Greater London N14 5PH",
    "addr:housenumber":"106",
    "addr:postcode":"n14 5ph",
    "addr:street":"Chase Side",
    "iso:country":"GB",
    "sg:address":"106 Chase Side",
    "sg:city":"Southgate",
    "sg:classifiers":[
        {
            "category":"Building & Trades",
            "subcategory":"Construction",
            "type":"Services"
        }
    ],
    "sg:phone":"+44 20 8882 1500",
    "sg:postcode":"N14 5PH",
    "sg:province":"Greater London",
    "sg:tags":[
        "contractor",
        "paving",
        "driveway"
    ],
    "wof:name":"Driveway Home Improvements",
    "wof:placetype":"venue"
},
  "geometry": {"coordinates":[-0.132241,51.633732],"type":"Point"}
}