{
  "type": "Feature",
  "properties": {
    "addr:full":"16a Park View Road London Greater London N3 2JB",
    "addr:housenumber":"16a",
    "addr:postcode":"n3 2jb",
    "addr:street":"Park View Road",
    "iso:country":"GB",
    "sg:address":"16a Park View Road",
    "sg:city":"London",
    "sg:classifiers":[
        {
            "category":"Professional",
            "subcategory":"Management & Consulting",
            "type":"Services"
        },
        {
            "category":"Organizations",
            "subcategory":"Non-profit Organization",
            "type":"Services"
        }
    ],
    "sg:phone":"+44 20 8343 4246",
    "sg:postcode":"N3 2JB",
    "sg:province":"Greater London",
    "sg:tags":[
        "consultant",
        "organisation",
        "charity",
        "business",
        "charitable"
    ],
    "wof:name":"MORTIMER ASSOCIATES",
    "wof:placetype":"venue"
},
  "geometry": {"coordinates":[-0.1822240055,51.602722168],"type":"Point"}
}