{
  "type": "Feature",
  "properties": {
    "iso:country":"GB",
    "sg:address":"293 Plumstead High St",
    "sg:city":"Woolwich",
    "sg:classifiers":[
        {
            "category":"Professional",
            "subcategory":"Lawyer & Legal Services",
            "type":"Services"
        }
    ],
    "sg:phone":"+44 20 8312 3773",
    "sg:postcode":"SE18 1JX",
    "sg:province":"Greater London",
    "sg:tags":[
        "solicitor"
    ],
    "wof:name":"Soorii Ayoola & Okri",
    "wof:placetype":"venue"
},
  "geometry": {"coordinates":[0.102801,51.485584],"type":"Point"}
}