{
  "type": "Feature",
  "properties": {
    "addr:full":"Chessels Daws Ho Launceston Cornwall PL15 7JF",
    "addr:postcode":"pl15 7jf",
    "addr:street":"Chessels Daws",
    "iso:country":"GB",
    "sg:address":"Chessels Daws Ho",
    "sg:city":"Launceston",
    "sg:classifiers":[
        {
            "category":"Professional",
            "subcategory":"Management & Consulting",
            "type":"Services"
        }
    ],
    "sg:phone":"+44 1566 777422",
    "sg:postcode":"PL15 7JF",
    "sg:province":"Cornwall",
    "sg:tags":[
        "consultant",
        "business"
    ],
    "wof:name":"Parker,Nigel,& Co",
    "wof:placetype":"venue"
},
  "geometry": {"coordinates":[-4.363344,50.636707],"type":"Point"}
}