{
  "type": "Feature",
  "properties": {
    "iso:country":"GB",
    "sg:address":"Wick Airport",
    "sg:city":"Wick",
    "sg:classifiers":[
        {
            "category":"Retail",
            "subcategory":"Auto Rental",
            "type":"Services"
        }
    ],
    "sg:postcode":"KW1 4QP",
    "sg:province":"Highland",
    "sg:tags":[
        "truck",
        "hire",
        "van"
    ],
    "wof:name":"Practical Car & Van Rental",
    "wof:placetype":"venue"
},
  "geometry": {"coordinates":[-3.08767,58.453812],"type":"Point"}
}