{
  "type": "Feature",
  "properties": {
    "iso:country":"GB",
    "sg:address":"Maitland House, Maitland Street",
    "sg:city":"Preston",
    "sg:classifiers":[
        {
            "category":"Building & Trades",
            "subcategory":"Construction",
            "type":"Services"
        }
    ],
    "sg:phone":"+44 1772 653226",
    "sg:postcode":"PR1 5XR",
    "sg:province":"Lancashire",
    "sg:tags":[
        "builder"
    ],
    "wof:name":"Richard Palmer Building",
    "wof:placetype":"venue"
},
  "geometry": {"coordinates":[-2.6741390228,53.7649307251],"type":"Point"}
}