{
  "type": "Feature",
  "properties": {
    "addr:full":"Harewood Row London Greater London NW1 6SE",
    "addr:postcode":"nw1 6se",
    "addr:street":"Harewood Row",
    "iso:country":"GB",
    "sg:address":"Harewood Row",
    "sg:city":"London",
    "sg:classifiers":[
        {
            "category":"Travel",
            "subcategory":"Hotels & Motels",
            "type":"Entertainment"
        }
    ],
    "sg:phone":"+44 20 7262 2707",
    "sg:postcode":"NW1 6SE",
    "sg:province":"Greater London",
    "wof:name":"Jarvis Marlybone Hotel",
    "wof:placetype":"venue"
},
  "geometry": {"coordinates":[-0.1642989963,51.5219459534],"type":"Point"}
}