{
  "type": "Feature",
  "properties": {
    "iso:country":"GB",
    "sg:address":"13-15 West Church Street",
    "sg:city":"Buckie",
    "sg:classifiers":[
        {
            "category":"Communications",
            "subcategory":"Newspaper",
            "type":"Services"
        },
        {
            "category":"Wholesale",
            "subcategory":"Books, Periodicals, & Newspapers",
            "type":"Manufacturing & Wholesale Goods"
        }
    ],
    "sg:phone":"+44 1542 836493",
    "sg:postcode":"AB56 1BN",
    "sg:province":"Moray",
    "sg:tags":[
        "magazine",
        "publishing"
    ],
    "wof:name":"J & M Publishing Ltd",
    "wof:placetype":"venue"
},
  "geometry": {"coordinates":[-2.9670538902,57.6756019592],"type":"Point"}
}