{
  "type": "Feature",
  "properties": {
    "addr:full":"90 Shaftesbury Drive Heywood Lancashire OL10 2PT",
    "addr:housenumber":"90",
    "addr:postcode":"ol10 2pt",
    "addr:street":"Shaftesbury Drive Heywood",
    "iso:country":"GB",
    "sg:address":"90 Shaftesbury Drive",
    "sg:city":"Heywood",
    "sg:classifiers":[
        {
            "category":"Retail",
            "subcategory":"Repair Shop",
            "type":"Services"
        }
    ],
    "sg:postcode":"OL10 2PT",
    "sg:province":"Lancashire",
    "sg:tags":[
        "radio",
        "television",
        "video"
    ],
    "wof:name":"S Mooney",
    "wof:placetype":"venue"
},
  "geometry": {"coordinates":[-2.223186,53.583256],"type":"Point"}
}