{
  "type": "Feature",
  "properties": {
    "addr:full":"Lakeside Shopping Centre, West Thurrock Grays Essex RM16 1ZH",
    "addr:postcode":"rm16 1zh",
    "addr:street":"West",
    "iso:country":"GB",
    "sg:address":"Lakeside Shopping Centre, West Thurrock",
    "sg:city":"Grays",
    "sg:classifiers":[
        {
            "category":"Travel",
            "subcategory":"Travel Agent",
            "type":"Entertainment"
        }
    ],
    "sg:phone":"+44 1708 861515",
    "sg:postcode":"RM16 1ZH",
    "sg:province":"Essex",
    "wof:name":"Lunn Poly Ltd.",
    "wof:placetype":"venue"
},
  "geometry": {"coordinates":[0.28655,51.48045],"type":"Point"}
}