{
  "type": "Feature",
  "properties": {
    "iso:country":"GB",
    "sg:address":"36 Lynholm Road",
    "sg:city":"Polegate",
    "sg:classifiers":[
        {
            "category":"Professional",
            "subcategory":"Engineering",
            "type":"Services"
        }
    ],
    "sg:postcode":"BN26 6JR",
    "sg:province":"East Sussex",
    "sg:tags":[
        "contractor",
        "electrical",
        "engineer"
    ],
    "wof:name":"A J Hodge Electrical Contractor",
    "wof:placetype":"venue"
},
  "geometry": {"coordinates":[0.256455,50.821209],"type":"Point"}
}