{
  "type": "Feature",
  "properties": {
    "addr:full":"26 Northfield Drive Newcastle-upon-tyne Tyne and Wear NE12 7ED",
    "addr:housenumber":"26",
    "addr:postcode":"ne12 7ed",
    "addr:street":"Northfield Drive",
    "iso:country":"GB",
    "sg:address":"26 Northfield Drive",
    "sg:city":"Newcastle-upon-tyne",
    "sg:classifiers":[
        {
            "category":"Professional",
            "subcategory":"Engineering",
            "type":"Services"
        }
    ],
    "sg:phone":"+44 191 268 9701",
    "sg:postcode":"NE12 7ED",
    "sg:province":"Tyne and Wear",
    "sg:tags":[
        "contractor",
        "electrical",
        "engineer"
    ],
    "wof:name":"A S F Electrical Services",
    "wof:placetype":"venue"
},
  "geometry": {"coordinates":[-1.5813740492,55.0296669006],"type":"Point"}
}