{
  "type": "Feature",
  "properties": {
    "iso:country":"GB",
    "sg:address":"3 Commerce Way, Whitehall Industrial Estate",
    "sg:city":"Colchester",
    "sg:classifiers":[
        {
            "category":"Professional",
            "type":"Services"
        }
    ],
    "sg:phone":"+44 1206 798707",
    "sg:postcode":"CO2 8HR",
    "sg:province":"Essex",
    "sg:tags":[
        "aircraft",
        "-",
        "maintenance"
    ],
    "wof:name":"Aerofloor Ltd",
    "wof:placetype":"venue"
},
  "geometry": {"coordinates":[0.93108,51.875301],"type":"Point"}
}