{
  "type": "Feature",
  "properties": {
    "iso:country":"GB",
    "sg:address":"5 Russell Hill Parade",
    "sg:city":"Purley",
    "sg:classifiers":[
        {
            "category":"Food & Beverages",
            "subcategory":"Bakery",
            "type":"Retail Goods"
        }
    ],
    "sg:phone":"+44 20 8763 1772",
    "sg:postcode":"CR8 2LA",
    "sg:province":"Surrey",
    "sg:tags":[
        "pizza"
    ],
    "wof:name":"City Centre Restaurants (U K) Ltd.",
    "wof:placetype":"venue"
},
  "geometry": {"coordinates":[-0.11782,51.340069],"type":"Point"}
}