{
  "type": "Feature",
  "properties": {
    "addr:full":"9 West Cross Avenue, West Cross Swansea Swansea SA3 5TS",
    "addr:housenumber":"9",
    "addr:postcode":"sa3 5ts",
    "addr:street":"West Cross Avenue West Cross",
    "iso:country":"GB",
    "sg:address":"9 West Cross Avenue, West Cross",
    "sg:city":"Swansea",
    "sg:classifiers":[
        {
            "category":"Shopping",
            "subcategory":"News",
            "type":"Retail Goods"
        }
    ],
    "sg:phone":"+44 1792 405200",
    "sg:postcode":"SA3 5TS",
    "sg:province":"Swansea",
    "sg:tags":[
        "newsagent"
    ],
    "wof:name":"Ian Boyd",
    "wof:placetype":"venue"
},
  "geometry": {"coordinates":[-4.0068387985,51.5840187073],"type":"Point"}
}