{
  "type": "Feature",
  "properties": {
    "addr:full":"Greenock Street Burnley Lancashire BB11 4EY",
    "addr:postcode":"bb11 4ey",
    "addr:street":"Greenock Street",
    "iso:country":"GB",
    "sg:address":"Greenock Street",
    "sg:city":"Burnley",
    "sg:classifiers":[
        {
            "category":"Farming",
            "subcategory":"Nursery",
            "type":"Manufacturing & Wholesale Goods"
        }
    ],
    "sg:phone":"+44 1282 438485",
    "sg:postcode":"BB11 4EY",
    "sg:province":"Lancashire",
    "sg:tags":[
        "creche"
    ],
    "wof:name":"Myrtle Bank Nursery School",
    "wof:placetype":"venue"
},
  "geometry": {"coordinates":[-2.2637441158,53.7818832397],"type":"Point"}
}