{
  "type": "Feature",
  "properties": {
    "addr:full":"Cowglen Rd Glasgow East Renfrewshire G53 6EW",
    "addr:postcode":"g53 6ew",
    "addr:street":"Cowglen Rd",
    "iso:country":"GB",
    "sg:address":"Cowglen Rd",
    "sg:city":"Glasgow",
    "sg:classifiers":[
        {
            "category":"Sports & Exercise",
            "subcategory":"Swimming Pool",
            "type":"Entertainment"
        }
    ],
    "sg:phone":"+44 141 881 3313",
    "sg:postcode":"G53 6EW",
    "sg:province":"East Renfrewshire",
    "wof:name":"Pollok Leisure Pool",
    "wof:placetype":"venue"
},
  "geometry": {"coordinates":[-4.3470659256,55.8224983215],"type":"Point"}
}