{
  "type": "Feature",
  "properties": {
    "addr:full":"86 Fairwood Drive Port Talbot Neath Port Talbot SA12 8NU",
    "addr:housenumber":"86",
    "addr:postcode":"sa12 8nu",
    "addr:street":"Fairwood Drive",
    "iso:country":"GB",
    "sg:address":"86 Fairwood Drive",
    "sg:city":"Port Talbot",
    "sg:classifiers":[
        {
            "category":"Food & Beverages",
            "subcategory":"Meat & Fish",
            "type":"Retail Goods"
        }
    ],
    "sg:phone":"+44 1639 823874",
    "sg:postcode":"SA12 8NU",
    "sg:province":"Neath Port Talbot",
    "sg:tags":[
        "chip"
    ],
    "wof:name":"Trentresbien",
    "wof:placetype":"venue"
},
  "geometry": {"coordinates":[-3.806440115,51.6202888489],"type":"Point"}
}