{
  "type": "Feature",
  "properties": {
    "iso:country":"GB",
    "sg:address":"Stone",
    "sg:city":"Berkeley",
    "sg:classifiers":[
        {
            "category":"Travel",
            "subcategory":"Hotels & Motels",
            "type":"Entertainment"
        }
    ],
    "sg:phone":"+44 1454 260219",
    "sg:postcode":"GL13 9JY",
    "sg:province":"Gloucestershire",
    "wof:name":"Berkeley Vale Hotel",
    "wof:placetype":"venue"
},
  "geometry": {"coordinates":[-2.4595689774,51.6931877136],"type":"Point"}
}