{
  "type": "Feature",
  "properties": {
    "addr:full":"451 Green Lanes Ilford Essex IG3 9TD",
    "addr:housenumber":"451",
    "addr:postcode":"ig3 9td",
    "addr:street":"Green Lanes",
    "iso:country":"GB",
    "sg:address":"451 Green Lanes",
    "sg:city":"Ilford",
    "sg:classifiers":[
        {
            "category":"Personal",
            "type":"Services"
        }
    ],
    "sg:phone":"+44 20 8599 1965",
    "sg:postcode":"IG3 9TD",
    "sg:province":"Essex",
    "sg:tags":[
        "dating",
        "friendship",
        "agency"
    ],
    "wof:name":"Essex Singles",
    "wof:placetype":"venue"
},
  "geometry": {"coordinates":[0.105005,51.562313],"type":"Point"}
}