{
  "type": "Feature",
  "properties": {
    "addr:full":"3 High Street, Warmley Bristol City of Bristol BS15 4ND",
    "addr:housenumber":"3",
    "addr:postcode":"bs15 4nd",
    "addr:street":"High Street",
    "iso:country":"GB",
    "sg:address":"3 High Street, Warmley",
    "sg:city":"Bristol",
    "sg:classifiers":[
        {
            "category":"Travel",
            "subcategory":"Travel Agent",
            "type":"Entertainment"
        }
    ],
    "sg:phone":"+44 117 960 6400",
    "sg:postcode":"BS15 4ND",
    "sg:province":"City of Bristol",
    "wof:name":"Holiday Express",
    "wof:placetype":"venue"
},
  "geometry": {"coordinates":[-2.505671978,51.4624710083],"type":"Point"}
}