{
  "type": "Feature",
  "properties": {
    "addr:full":"Penpole Lane, Shirehampton Bristol City of Bristol BS11 0AU",
    "addr:postcode":"bs11 0au",
    "addr:street":"Penpole Lane",
    "iso:country":"GB",
    "sg:address":"Penpole Lane, Shirehampton",
    "sg:city":"Bristol",
    "sg:classifiers":[
        {
            "category":"Arena",
            "subcategory":"Sports Club",
            "type":"Entertainment"
        }
    ],
    "sg:phone":"+44 117 923 5461",
    "sg:postcode":"BS11 0AU",
    "sg:province":"City of Bristol",
    "wof:name":"Shirehampton Football Club",
    "wof:placetype":"venue"
},
  "geometry": {"coordinates":[-2.680225,51.492729],"type":"Point"}
}