{
  "type": "Feature",
  "properties": {
    "addr:full":"High Street, Burrelton Blairgowrie Angus PH13 9NX",
    "addr:postcode":"ph13 9nx",
    "addr:street":"High Street",
    "iso:country":"GB",
    "sg:address":"High Street, Burrelton",
    "sg:city":"Blairgowrie",
    "sg:classifiers":[
        {
            "category":"Food & Beverages",
            "subcategory":"Meat & Fish",
            "type":"Retail Goods"
        }
    ],
    "sg:phone":"+44 1828 670262",
    "sg:postcode":"PH13 9NX",
    "sg:province":"Angus",
    "sg:tags":[
        "butcher"
    ],
    "wof:name":"David Reid & Son",
    "wof:placetype":"venue"
},
  "geometry": {"coordinates":[-3.3024690151,56.5160331726],"type":"Point"}
}