{
  "type": "Feature",
  "properties": {
    "addr:full":"Mayflower Cottage, Tutts Clump Reading Berkshire RG7 6JU",
    "addr:postcode":"rg7 6ju",
    "addr:street":"Tutts",
    "iso:country":"GB",
    "sg:address":"Mayflower Cottage, Tutts Clump",
    "sg:city":"Reading",
    "sg:classifiers":[
        {
            "category":"Building & Trades",
            "subcategory":"Construction",
            "type":"Services"
        }
    ],
    "sg:postcode":"RG7 6JU",
    "sg:province":"Berkshire",
    "sg:tags":[
        "builder"
    ],
    "wof:name":"Ivan Cork",
    "wof:placetype":"venue"
},
  "geometry": {"coordinates":[-1.1563789845,51.4364738464],"type":"Point"}
}