{
  "type": "Feature",
  "properties": {
    "addr:full":"1 Uphill, Urchfont Devizes Wiltshire SN10 4SA",
    "addr:housenumber":"1",
    "addr:postcode":"sn10 4sa",
    "addr:street":"Uphill Urchfont",
    "iso:country":"GB",
    "sg:address":"1 Uphill, Urchfont",
    "sg:city":"Devizes",
    "sg:classifiers":[
        {
            "category":"Retail",
            "subcategory":"Repair Shop",
            "type":"Services"
        },
        {
            "category":"Farming",
            "subcategory":"Poultry Farm",
            "type":"Manufacturing & Wholesale Goods"
        }
    ],
    "sg:phone":"+44 1380 840285",
    "sg:postcode":"SN10 4SA",
    "sg:province":"Wiltshire",
    "sg:tags":[
        "agricultural",
        "sale",
        "related",
        "machinery"
    ],
    "wof:name":"Uphill Sales & Services",
    "wof:placetype":"venue"
},
  "geometry": {"coordinates":[-1.9416470528,51.3118057251],"type":"Point"}
}