{
  "type": "Feature",
  "properties": {
    "iso:country":"GB",
    "sg:address":"Ruthin Delivery Office, 18 St Peters Square",
    "sg:city":"Ruthin",
    "sg:classifiers":[
        {
            "category":"Personal",
            "type":"Services"
        }
    ],
    "sg:phone":"+44 1824 703226",
    "sg:postcode":"LL15 1YL",
    "sg:province":"Denbighshire",
    "sg:tags":[
        "delivery"
    ],
    "wof:name":"Royal Mail",
    "wof:placetype":"venue"
},
  "geometry": {"coordinates":[-3.304522,53.114017],"type":"Point"}
}