{
  "type": "Feature",
  "properties": {
    "addr:full":"Polhormon Farm Helston Cornwall TR12 7JE",
    "addr:housenumber":"helston",
    "addr:postcode":"tr12 7je",
    "iso:country":"GB",
    "sg:address":"Polhormon Farm",
    "sg:city":"Helston",
    "sg:classifiers":[
        {
            "category":"Farming",
            "subcategory":"Dairy Farm",
            "type":"Manufacturing & Wholesale Goods"
        }
    ],
    "sg:phone":"+44 1326 240304",
    "sg:postcode":"TR12 7JE",
    "sg:province":"Cornwall",
    "wof:name":"Polhormon Farm",
    "wof:placetype":"venue"
},
  "geometry": {"coordinates":[-5.244395,50.033104],"type":"Point"}
}