{
  "type": "Feature",
  "properties": {
    "addr:full":"119 Torriano Avenue Kentish Town Greater London NW5 2RX",
    "addr:housenumber":"119",
    "addr:postcode":"nw5 2rx",
    "addr:street":"Torriano Avenue",
    "iso:country":"GB",
    "sg:address":"119 Torriano Avenue",
    "sg:city":"Kentish Town",
    "sg:classifiers":[
        {
            "category":"Government",
            "subcategory":"Office",
            "type":"Public Place"
        }
    ],
    "sg:phone":"+44 20 7267 6929",
    "sg:postcode":"NW5 2RX",
    "sg:province":"Greater London",
    "sg:tags":[
        "press",
        "cutting",
        "bureau"
    ],
    "wof:name":"George Selwyn",
    "wof:placetype":"venue"
},
  "geometry": {"coordinates":[-0.1330890059,51.5516738892],"type":"Point"}
}