{
  "type": "Feature",
  "properties": {
    "addr:full":"404 Montrose Avenue Slough Berkshire SL1 4TJ",
    "addr:housenumber":"404",
    "addr:postcode":"sl1 4tj",
    "addr:street":"Montrose Avenue",
    "iso:country":"GB",
    "sg:address":"404 Montrose Avenue",
    "sg:city":"Slough",
    "sg:classifiers":[
        {
            "category":"Building & Trades",
            "subcategory":"Construction",
            "type":"Services"
        }
    ],
    "sg:phone":"+44 1494 524435",
    "sg:postcode":"SL1 4TJ",
    "sg:province":"Berkshire",
    "sg:tags":[
        "resurfacing",
        "laying",
        "floor"
    ],
    "wof:name":"E & M Flooring",
    "wof:placetype":"venue"
},
  "geometry": {"coordinates":[-0.6202359796,51.523563385],"type":"Point"}
}