{
  "type": "Feature",
  "properties": {
    "addr:full":"52 Cockton Hill Road Bishop Auckland Durham DL14 6AH",
    "addr:housenumber":"52",
    "addr:postcode":"dl14 6ah",
    "addr:street":"Cockton Hill Road",
    "iso:country":"GB",
    "sg:address":"52 Cockton Hill Road",
    "sg:city":"Bishop Auckland",
    "sg:classifiers":[
        {
            "category":"Health Services",
            "subcategory":"Optometrist",
            "type":"Services"
        }
    ],
    "sg:postcode":"DL14 6AH",
    "sg:province":"Durham",
    "sg:tags":[
        "optician"
    ],
    "wof:name":"T A Boothroyd Opticians",
    "wof:placetype":"venue"
},
  "geometry": {"coordinates":[-1.6781769991,54.6531524658],"type":"Point"}
}