{
  "type": "Feature",
  "properties": {
    "addr:full":"1 Wykeley Road Coventry Warwickshire CV2 3DW",
    "addr:housenumber":"1",
    "addr:postcode":"cv2 3dw",
    "addr:street":"Wykeley Road",
    "iso:country":"GB",
    "sg:address":"1 Wykeley Road",
    "sg:city":"Coventry",
    "sg:classifiers":[
        {
            "category":"Shopping",
            "subcategory":"Beauty & Cosmetics",
            "type":"Retail Goods"
        }
    ],
    "sg:phone":"+44 24 7665 1100",
    "sg:postcode":"CV2 3DW",
    "sg:province":"Warwickshire",
    "sg:tags":[
        "equipment",
        "hairdressing",
        "hairdresser",
        "supply"
    ],
    "wof:name":"G & M King",
    "wof:placetype":"venue"
},
  "geometry": {"coordinates":[-1.469245,52.416115],"type":"Point"}
}