{
  "type": "Feature",
  "properties": {
    "addr:full":"35a Poplar St Southport Lancashire PR8 6DX",
    "addr:housenumber":"35a",
    "addr:postcode":"pr8 6dx",
    "addr:street":"Poplar St",
    "iso:country":"GB",
    "sg:address":"35a Poplar St",
    "sg:city":"Southport",
    "sg:classifiers":[
        {
            "category":"Manufacturing",
            "subcategory":"Signs",
            "type":"Manufacturing & Wholesale Goods"
        }
    ],
    "sg:phone":"+44 1704 544556",
    "sg:postcode":"PR8 6DX",
    "sg:province":"Lancashire",
    "sg:tags":[
        "writer"
    ],
    "wof:name":"Impact",
    "wof:placetype":"venue"
},
  "geometry": {"coordinates":[-2.976915,53.642147],"type":"Point"}
}