{
  "type": "Feature",
  "properties": {
    "addr:full":"41a Warminster Road, Bathampton Bath Somerset BA2 6XJ",
    "addr:housenumber":"41a",
    "addr:postcode":"ba2 6xj",
    "addr:street":"Warminster Road",
    "iso:country":"GB",
    "sg:address":"41a Warminster Road, Bathampton",
    "sg:city":"Bath",
    "sg:classifiers":[
        {
            "category":"Travel",
            "subcategory":"Hotels & Motels",
            "type":"Entertainment"
        }
    ],
    "sg:phone":"+44 1225 466342",
    "sg:postcode":"BA2 6XJ",
    "sg:province":"Somerset",
    "sg:tags":[
        "house",
        "guest"
    ],
    "wof:name":"Lindisfarne Guest House",
    "wof:placetype":"venue"
},
  "geometry": {"coordinates":[-2.323066,51.391811],"type":"Point"}
}