{
  "type": "Feature",
  "properties": {
    "addr:full":"Equity Chambers, 75 King Street Ebbw Vale Blaenau Gwent NP23 4RG",
    "addr:housenumber":"75",
    "addr:postcode":"np23 4rg",
    "addr:street":"King Street",
    "iso:country":"GB",
    "sg:address":"Equity Chambers, 75 King Street",
    "sg:city":"Ebbw Vale",
    "sg:classifiers":[
        {
            "category":"Professional",
            "subcategory":"Lawyer & Legal Services",
            "type":"Services"
        }
    ],
    "sg:phone":"+44 1495 302109",
    "sg:postcode":"NP23 4RG",
    "sg:province":"Blaenau Gwent",
    "sg:tags":[
        "solicitor"
    ],
    "wof:name":"Gartside",
    "wof:placetype":"venue"
},
  "geometry": {"coordinates":[-3.2146859169,51.7970275879],"type":"Point"}
}