{
  "type": "Feature",
  "properties": {
    "addr:full":"Jesperyth Mere Milltown Grdns, Yeolmbridge Launceston Cornwall PL15 8TQ",
    "addr:postcode":"pl15 8tq",
    "addr:street":"Milltown",
    "iso:country":"GB",
    "sg:address":"Jesperyth Mere Milltown Grdns, Yeolmbridge",
    "sg:city":"Launceston",
    "sg:classifiers":[
        {
            "category":"Manufacturing",
            "subcategory":"Petroleum Products",
            "type":"Manufacturing & Wholesale Goods"
        }
    ],
    "sg:phone":"+44 1566 776795",
    "sg:postcode":"PL15 8TQ",
    "sg:province":"Cornwall",
    "sg:tags":[
        "double",
        "glazing"
    ],
    "wof:name":"Werrington Windows",
    "wof:placetype":"venue"
},
  "geometry": {"coordinates":[-4.3633441925,50.6367073059],"type":"Point"}
}