{
  "type": "Feature",
  "properties": {
    "addr:full":"39 Scotland St Sheffield South Yorkshire S3 7BT",
    "addr:housenumber":"39",
    "addr:postcode":"s3 7bt",
    "addr:street":"Scotland St",
    "iso:country":"GB",
    "sg:address":"39 Scotland St",
    "sg:city":"Sheffield",
    "sg:classifiers":[
        {
            "category":"Organizations",
            "subcategory":"Non-profit Organization",
            "type":"Services"
        }
    ],
    "sg:phone":"+44 114 279 6750",
    "sg:postcode":"S3 7BT",
    "sg:province":"South Yorkshire",
    "sg:tags":[
        "organisation",
        "voluntary",
        "charity"
    ],
    "wof:name":"Short Organised Help Service",
    "wof:placetype":"venue"
},
  "geometry": {"coordinates":[-1.47363,53.385216],"type":"Point"}
}