{
  "type": "Feature",
  "properties": {
    "iso:country":"GB",
    "sg:address":"3 The Spendlove Centre, Enstone Road",
    "sg:city":"Chipping Norton",
    "sg:classifiers":[
        {
            "category":"Education",
            "subcategory":"Special Training",
            "type":"Public Place"
        }
    ],
    "sg:postcode":"OX7 3PQ",
    "sg:province":"Gloucestershire",
    "sg:tags":[
        "product",
        "centre"
    ],
    "wof:name":"Heather Bayer",
    "wof:placetype":"venue"
},
  "geometry": {"coordinates":[-1.545912981,51.9404067993],"type":"Point"}
}