{
  "type": "Feature",
  "properties": {
    "addr:full":"Maud's Elm, 320 Swindon Rd Cheltenham Gloucestershire GL51 9JT",
    "addr:housenumber":"320",
    "addr:postcode":"gl51 9jt",
    "addr:street":"Elm;Swindon Rd",
    "iso:country":"GB",
    "sg:address":"Maud's Elm, 320 Swindon Rd",
    "sg:city":"Cheltenham",
    "sg:classifiers":[
        {
            "category":"Freight",
            "type":"Transportation"
        }
    ],
    "sg:postcode":"GL51 9JT",
    "sg:province":"Gloucestershire",
    "sg:tags":[
        "haulage",
        "road"
    ],
    "wof:name":"Jones,J,& Son (Cheltenham) Ltd",
    "wof:placetype":"venue"
},
  "geometry": {"coordinates":[-2.091437,51.911385],"type":"Point"}
}