{
  "type": "Feature",
  "properties": {
    "addr:full":"115 High St West Sunderland Tyne and Wear SR1 1TR",
    "addr:housenumber":"115",
    "addr:postcode":"sr1 1tr",
    "addr:street":"High St",
    "iso:country":"GB",
    "sg:address":"115 High St West",
    "sg:city":"Sunderland",
    "sg:classifiers":[
        {
            "category":"Personal",
            "subcategory":"Beauty Salon",
            "type":"Services"
        }
    ],
    "sg:phone":"+44 191 522 0222",
    "sg:postcode":"SR1 1TR",
    "sg:province":"Tyne and Wear",
    "sg:tags":[
        "unisex",
        "hairdresser"
    ],
    "wof:name":"Ask Hairdressing",
    "wof:placetype":"venue"
},
  "geometry": {"coordinates":[-1.380504,54.907784],"type":"Point"}
}