{
  "type": "Feature",
  "properties": {
    "addr:full":"Pound Farm, Old Lane Cobham Surrey KT11 1NH",
    "addr:postcode":"kt11 1nh",
    "addr:street":"Old Lane",
    "iso:country":"GB",
    "sg:address":"Pound Farm, Old Lane",
    "sg:city":"Cobham",
    "sg:classifiers":[
        {
            "category":"Building & Trades",
            "subcategory":"Construction",
            "type":"Services"
        }
    ],
    "sg:postcode":"KT11 1NH",
    "sg:province":"Surrey",
    "sg:tags":[
        "welder"
    ],
    "wof:name":"J D Scott",
    "wof:placetype":"venue"
},
  "geometry": {"coordinates":[-0.410454005,51.3281173706],"type":"Point"}
}