{
  "type": "Feature",
  "properties": {
    "iso:country":"GB",
    "sg:address":"Fairacre Ballinger",
    "sg:city":"Great Missenden",
    "sg:classifiers":[
        {
            "category":"Professional",
            "subcategory":"Accounting & Tax Preparation",
            "type":"Services"
        }
    ],
    "sg:phone":"+44 1494 837696",
    "sg:postcode":"HP16 9LJ",
    "sg:province":"Buckinghamshire",
    "sg:tags":[
        "accountant"
    ],
    "wof:name":"C E Hill & Co",
    "wof:placetype":"venue"
},
  "geometry": {"coordinates":[-0.709043,51.704067],"type":"Point"}
}