{
  "type": "Feature",
  "properties": {
    "addr:full":"7-11 Lexington Street London Greater London W1F 9AF",
    "addr:housenumber":"7-11",
    "addr:postcode":"w1f 9af",
    "addr:street":"Lexington Street",
    "iso:country":"GB",
    "sg:address":"7-11 Lexington Street",
    "sg:city":"London",
    "sg:classifiers":[
        {
            "category":"Communications",
            "subcategory":"Film & Video Production",
            "type":"Services"
        }
    ],
    "sg:phone":"+44 20 7494 2025",
    "sg:postcode":"W1F 9AF",
    "sg:province":"Greater London",
    "sg:tags":[
        "tv",
        "studio"
    ],
    "wof:name":"Ortmans Young Ltd.",
    "wof:placetype":"venue"
},
  "geometry": {"coordinates":[-0.135486,51.51202],"type":"Point"}
}