{
  "type": "Feature",
  "properties": {
    "addr:full":"75 Salisbury Road, Walmer Deal Kent CT14 7QL",
    "addr:housenumber":"75",
    "addr:postcode":"ct14 7ql",
    "addr:street":"Salisbury Road",
    "iso:country":"GB",
    "sg:address":"75 Salisbury Road, Walmer",
    "sg:city":"Deal",
    "sg:classifiers":[
        {
            "category":"Farming",
            "subcategory":"Nursery",
            "type":"Manufacturing & Wholesale Goods"
        }
    ],
    "sg:phone":"+44 1304 363360",
    "sg:postcode":"CT14 7QL",
    "sg:province":"Kent",
    "sg:tags":[
        "creche"
    ],
    "wof:name":"Lynstead House Nursery School",
    "wof:placetype":"venue"
},
  "geometry": {"coordinates":[1.387551,51.205685],"type":"Point"}
}