{
  "type": "Feature",
  "properties": {
    "addr:full":"408 Lymington Road Christchurch Dorset BH23 5HE",
    "addr:housenumber":"408",
    "addr:postcode":"bh23 5he",
    "addr:street":"Lymington Road",
    "iso:country":"GB",
    "sg:address":"408 Lymington Road",
    "sg:city":"Christchurch",
    "sg:classifiers":[
        {
            "category":"Personal",
            "subcategory":"Beauty Salon",
            "type":"Services"
        }
    ],
    "sg:postcode":"BH23 5HE",
    "sg:province":"Dorset",
    "sg:tags":[
        "unisex",
        "hairdresser"
    ],
    "wof:name":"Serena's Hair Studio",
    "wof:placetype":"venue"
},
  "geometry": {"coordinates":[-1.696341,50.742477],"type":"Point"}
}