{
  "type": "Feature",
  "properties": {
    "addr:full":"Unit 7b Meadow Road Reading Berkshire RG1 8LB",
    "addr:housenumber":"unit 7b",
    "addr:postcode":"rg1 8lb",
    "addr:street":"Meadow Road",
    "iso:country":"GB",
    "sg:address":"Unit 7b Meadow Road",
    "sg:city":"Reading",
    "sg:classifiers":[
        {
            "category":"Manufacturing",
            "subcategory":"Metals",
            "type":"Manufacturing & Wholesale Goods"
        }
    ],
    "sg:phone":"+44 118 939 3413",
    "sg:postcode":"RG1 8LB",
    "sg:province":"Berkshire",
    "sg:tags":[
        "work",
        "sheet"
    ],
    "wof:name":"Acclaim Fabrications",
    "wof:placetype":"venue"
},
  "geometry": {"coordinates":[-0.980048,51.461967],"type":"Point"}
}