{
  "type": "Feature",
  "properties": {
    "iso:country":"GB",
    "sg:address":"Bridge Terrace, Cwmtillery",
    "sg:city":"Abertillery",
    "sg:classifiers":[
        {
            "category":"Education",
            "subcategory":"School",
            "type":"Public Place"
        }
    ],
    "sg:phone":"+44 1495 212412",
    "sg:postcode":"NP13 1LD",
    "sg:province":"Blaenau Gwent",
    "sg:tags":[
        "local",
        "authority"
    ],
    "wof:name":"Blaentillery Infants School",
    "wof:placetype":"venue"
},
  "geometry": {"coordinates":[-3.137623,51.730118],"type":"Point"}
}