{
  "type": "Feature",
  "properties": {
    "iso:country":"GB",
    "sg:address":"42 Station Road, Kirby Muxloe",
    "sg:city":"Leicester",
    "sg:classifiers":[
        {
            "category":"Building & Trades",
            "subcategory":"Construction",
            "type":"Services"
        }
    ],
    "sg:postcode":"LE9 2EJ",
    "sg:province":"Leicestershire",
    "sg:tags":[
        "decorator",
        "painter"
    ],
    "wof:name":"Rowlett Bros",
    "wof:placetype":"venue"
},
  "geometry": {"coordinates":[-1.233828,52.631149],"type":"Point"}
}