{
  "type": "Feature",
  "properties": {
    "addr:full":"27 The Broadway Huntingdon Cambridgeshire PE27 5BX",
    "addr:housenumber":"27",
    "addr:postcode":"pe27 5bx",
    "addr:street":"The Broadway",
    "iso:country":"GB",
    "sg:address":"27 The Broadway",
    "sg:city":"Huntingdon",
    "sg:classifiers":[
        {
            "category":"Bars & Pubs",
            "type":"Food & Drink"
        },
        {
            "category":"Community Center",
            "subcategory":"Social",
            "type":"Public Place"
        }
    ],
    "sg:phone":"+44 1480 467773",
    "sg:postcode":"PE27 5BX",
    "sg:province":"Cambridgeshire",
    "sg:tags":[
        "pubs",
        "house",
        "inn",
        "activity"
    ],
    "wof:name":"Floods Tavern",
    "wof:placetype":"venue"
},
  "geometry": {"coordinates":[-0.0762400031,52.3247489929],"type":"Point"}
}