{
  "type": "Feature",
  "properties": {
    "iso:country":"GB",
    "sg:address":"10 Queens Road, Cheetham",
    "sg:city":"Manchester",
    "sg:classifiers":[
        {
            "category":"Travel",
            "subcategory":"Travel Agent",
            "type":"Entertainment"
        },
        {
            "category":"Organizations",
            "subcategory":"Membership Organization",
            "type":"Services"
        }
    ],
    "sg:phone":"+44 161 205 4007",
    "sg:postcode":"M8 8UF",
    "sg:province":"Greater Manchester",
    "sg:tags":[
        "club"
    ],
    "wof:name":"Irish World Heritage Centre",
    "wof:placetype":"venue"
},
  "geometry": {"coordinates":[-2.234749,53.500263],"type":"Point"}
}