{
  "type": "Feature",
  "properties": {
    "iso:country":"GB",
    "sg:address":"17 Blackmoor Foot, Linthwaite",
    "sg:city":"Huddersfield",
    "sg:classifiers":[
        {
            "category":"Building & Trades",
            "subcategory":"Construction",
            "type":"Services"
        }
    ],
    "sg:phone":"+44 1484 846475",
    "sg:postcode":"HD7 5TR",
    "sg:province":"West Yorkshire",
    "sg:tags":[
        "joiner",
        "carpenter"
    ],
    "wof:name":"Tattersall Joinery",
    "wof:placetype":"venue"
},
  "geometry": {"coordinates":[-1.8791890144,53.6215286255],"type":"Point"}
}