{
  "type": "Feature",
  "properties": {
    "addr:full":"38-40 Crabtree Lane Lancing West Sussex BN15 9PQ",
    "addr:housenumber":"38-40",
    "addr:postcode":"bn15 9pq",
    "addr:street":"Crabtree Lane",
    "iso:country":"GB",
    "sg:address":"38-40 Crabtree Lane",
    "sg:city":"Lancing",
    "sg:classifiers":[
        {
            "category":"Manufacturing",
            "subcategory":"Petroleum Products",
            "type":"Manufacturing & Wholesale Goods"
        }
    ],
    "sg:phone":"+44 1903 756749",
    "sg:postcode":"BN15 9PQ",
    "sg:province":"West Sussex",
    "sg:tags":[
        "double",
        "glazing"
    ],
    "wof:name":"Summit Windows & Conservatories",
    "wof:placetype":"venue"
},
  "geometry": {"coordinates":[-0.320994,50.831959],"type":"Point"}
}