{
  "type": "Feature",
  "properties": {
    "iso:country":"GB",
    "sg:address":"Langford Rd",
    "sg:city":"Biggleswade",
    "sg:classifiers":[
        {
            "category":"Professional",
            "subcategory":"Business Services",
            "type":"Services"
        }
    ],
    "sg:phone":"+44 1767 314035",
    "sg:postcode":"SG18 9RA",
    "sg:province":"Bedfordshire",
    "sg:tags":[
        "import",
        "export",
        "agent"
    ],
    "wof:name":"Langford Road Motor Salvage",
    "wof:placetype":"venue"
},
  "geometry": {"coordinates":[-0.2665289938,52.0730209351],"type":"Point"}
}