{
  "type": "Feature",
  "properties": {
    "addr:full":"31 Meadow Close, Woodley Stockport Cheshire SK6 1QZ",
    "addr:housenumber":"31",
    "addr:postcode":"sk6 1qz",
    "addr:street":"Meadow Close",
    "iso:country":"GB",
    "sg:address":"31 Meadow Close, Woodley",
    "sg:city":"Stockport",
    "sg:classifiers":[
        {
            "category":"Home & Garden",
            "subcategory":"Building Materials",
            "type":"Retail Goods"
        }
    ],
    "sg:postcode":"SK6 1QZ",
    "sg:province":"Cheshire",
    "sg:tags":[
        "shower",
        "unit"
    ],
    "wof:name":"Advanced Shower Services",
    "wof:placetype":"venue"
},
  "geometry": {"coordinates":[-2.1052269936,53.4293861389],"type":"Point"}
}