{
  "type": "Feature",
  "properties": {
    "iso:country":"GB",
    "sg:address":"2 Red Brick Farm, Main Street",
    "sg:city":"Cambridge",
    "sg:classifiers":[
        {
            "category":"Professional",
            "type":"Services"
        }
    ],
    "sg:postcode":"CB3 7QS",
    "sg:province":"Cambridgeshire",
    "sg:tags":[
        "caterer"
    ],
    "wof:name":"Alexia Poole",
    "wof:placetype":"venue"
},
  "geometry": {"coordinates":[0.111565,52.209869],"type":"Point"}
}