{
  "type": "Feature",
  "properties": {
    "iso:country":"GB",
    "sg:address":"Charlston House",
    "sg:city":"Hemel Hempstead",
    "sg:classifiers":[
        {
            "category":"Real Estate",
            "subcategory":"Surveying",
            "type":"Services"
        }
    ],
    "sg:phone":"+44 1442 261270",
    "sg:postcode":"HP1 3AA",
    "sg:province":"Hertfordshire",
    "sg:tags":[
        "building",
        "surveyor"
    ],
    "wof:name":"Balneaves Chadwick Associates Ltd.",
    "wof:placetype":"venue"
},
  "geometry": {"coordinates":[-0.506503,51.793118],"type":"Point"}
}