{
  "type": "Feature",
  "properties": {
    "iso:country":"GB",
    "sg:address":"Aberystwyth Road",
    "sg:city":"Cardigan",
    "sg:classifiers":[
        {
            "category":"Autos & Motor Vehicles",
            "subcategory":"Fuel & Gas Station",
            "type":"Retail Goods"
        }
    ],
    "sg:phone":"+44 1239 613287",
    "sg:postcode":"SA43 1QR",
    "sg:province":"Ceredigion",
    "sg:tags":[
        "petrol",
        "filling"
    ],
    "wof:name":"Cam's Service Station",
    "wof:placetype":"venue"
},
  "geometry": {"coordinates":[-4.6452541351,52.0897636414],"type":"Point"}
}