{
  "type": "Feature",
  "properties": {
    "iso:country":"GB",
    "sg:address":"Unit C, Moravian Road, Kingswood",
    "sg:city":"Bristol",
    "sg:classifiers":[
        {
            "category":"Manufacturing",
            "subcategory":"Lumber",
            "type":"Manufacturing & Wholesale Goods"
        }
    ],
    "sg:phone":"+44 117 960 6813",
    "sg:postcode":"BS15 2NF",
    "sg:province":"City of Bristol",
    "sg:tags":[
        "importer",
        "merchants",
        "agent",
        "timber"
    ],
    "wof:name":"Golding Timber & Board Merchants Ltd.",
    "wof:placetype":"venue"
},
  "geometry": {"coordinates":[-2.50382,51.452309],"type":"Point"}
}