{
  "type": "Feature",
  "properties": {
    "addr:full":"P O Box 37 Goole East Riding of Yorkshire DN14 0HG",
    "addr:housenumber":"box 37",
    "addr:postcode":"dn14 0hg",
    "addr:street":"P O",
    "iso:country":"GB",
    "sg:address":"P O Box 37",
    "sg:city":"Goole",
    "sg:classifiers":[
        {
            "category":"Banks & Credit Unions",
            "subcategory":"Financial Services",
            "type":"Services"
        }
    ],
    "sg:phone":"+44 1405 860937",
    "sg:postcode":"DN14 0HG",
    "sg:province":"East Riding of Yorkshire",
    "sg:tags":[
        "consultant"
    ],
    "wof:name":"Albion Financial Services",
    "wof:placetype":"venue"
},
  "geometry": {"coordinates":[-1.125449,53.6992],"type":"Point"}
}