{
  "type": "Feature",
  "properties": {
    "addr:full":"Church Walk, Weldon Corby Northamptonshire NN17 3JX",
    "addr:postcode":"nn17 3jx",
    "addr:street":"Church Walk",
    "iso:country":"GB",
    "sg:address":"Church Walk, Weldon",
    "sg:city":"Corby",
    "sg:classifiers":[
        {
            "category":"Personal",
            "subcategory":"Barber",
            "type":"Services"
        }
    ],
    "sg:phone":"+44 1536 202496",
    "sg:postcode":"NN17 3JX",
    "sg:province":"Northamptonshire",
    "sg:tags":[
        "men's",
        "hairdresser"
    ],
    "wof:name":"P Kerfoot",
    "wof:placetype":"venue"
},
  "geometry": {"coordinates":[-0.634108,52.495346],"type":"Point"}
}