{
  "type": "Feature",
  "properties": {
    "addr:full":"25 Barnstable St South Molton Devon EX36 3BQ",
    "addr:housenumber":"25",
    "addr:postcode":"ex36 3bq",
    "addr:street":"Barnstable St",
    "iso:country":"GB",
    "sg:address":"25 Barnstable St",
    "sg:city":"South Molton",
    "sg:classifiers":[
        {
            "category":"Building & Trades",
            "subcategory":"Construction",
            "type":"Services"
        }
    ],
    "sg:postcode":"EX36 3BQ",
    "sg:province":"Devon",
    "sg:tags":[
        "builder"
    ],
    "wof:name":"Tucker,S J & K C & B J,",
    "wof:placetype":"venue"
},
  "geometry": {"coordinates":[-3.836028,51.017971],"type":"Point"}
}