{
  "type": "Feature",
  "properties": {
    "iso:country":"GB",
    "sg:address":"Otmoor Pk, Lwr Woods Farm",
    "sg:city":"Oxford",
    "sg:classifiers":[
        {
            "category":"Retail",
            "subcategory":"Auto Repair",
            "type":"Services"
        }
    ],
    "sg:postcode":"OX3 9PJ",
    "sg:province":"Oxfordshire",
    "sg:tags":[
        "modification",
        "garage"
    ],
    "wof:name":"Bishop,S,Auto Services",
    "wof:placetype":"venue"
},
  "geometry": {"coordinates":[-1.180148,51.797623],"type":"Point"}
}