{
  "type": "Feature",
  "properties": {
    "iso:country":"GB",
    "sg:address":"Bransby",
    "sg:city":"Lincoln",
    "sg:classifiers":[
        {
            "category":"Manufacturing",
            "subcategory":"Buildings",
            "type":"Manufacturing & Wholesale Goods"
        }
    ],
    "sg:phone":"+44 1427 788385",
    "sg:postcode":"LN1 2PH",
    "sg:province":"Lincolnshire",
    "sg:tags":[
        "portable"
    ],
    "wof:name":"Bransby Bunny",
    "wof:placetype":"venue"
},
  "geometry": {"coordinates":[-0.6512,53.302502],"type":"Point"}
}