{
  "type": "Feature",
  "properties": {
    "iso:country":"GB",
    "sg:address":"Watery Lane, Much Marcle",
    "sg:city":"Ledbury",
    "sg:classifiers":[
        {
            "category":"Bars & Pubs",
            "type":"Food & Drink"
        }
    ],
    "sg:phone":"+44 1531 660246",
    "sg:postcode":"HR8 2NG",
    "sg:province":"Gloucestershire",
    "sg:tags":[
        "pubs",
        "house",
        "inn",
        "public",
        "activity"
    ],
    "wof:name":"The Slip Tavern",
    "wof:placetype":"venue"
},
  "geometry": {"coordinates":[-2.499424,51.99316],"type":"Point"}
}