{
  "type": "Feature",
  "properties": {
    "iso:country":"GB",
    "sg:address":"Hendy Farm, Pant Rd",
    "sg:city":"Caernarfon",
    "sg:classifiers":[
        {
            "category":"Farming",
            "subcategory":"Dairy Farm",
            "type":"Manufacturing & Wholesale Goods"
        }
    ],
    "sg:phone":"+44 1286 672785",
    "sg:postcode":"LL54 5RL",
    "sg:province":"Gwynedd",
    "wof:name":"Robert Jones",
    "wof:placetype":"venue"
},
  "geometry": {"coordinates":[-4.27549,53.124699],"type":"Point"}
}