{
  "type": "Feature",
  "properties": {
    "addr:full":"Ponteland Rd Newcastle Upon Tyne Tyne and Wear NE3 3TY",
    "addr:postcode":"ne3 3ty",
    "addr:street":"Ponteland Rd",
    "iso:country":"GB",
    "sg:address":"Ponteland Rd",
    "sg:city":"Newcastle Upon Tyne",
    "sg:classifiers":[
        {
            "category":"Travel",
            "subcategory":"Hotels & Motels",
            "type":"Entertainment"
        }
    ],
    "sg:phone":"+44 191 214 0877",
    "sg:postcode":"NE3 3TY",
    "sg:province":"Tyne and Wear",
    "wof:name":"The Toby Carvery At Kenton Bank",
    "wof:placetype":"venue"
},
  "geometry": {"coordinates":[-1.66896,55.007542],"type":"Point"}
}