{
  "type": "Feature",
  "properties": {
    "iso:country":"GB",
    "sg:address":"Whitefield Farm, Red Row",
    "sg:city":"Morpeth",
    "sg:classifiers":[
        {
            "category":"Farming",
            "subcategory":"Farm",
            "type":"Manufacturing & Wholesale Goods"
        }
    ],
    "sg:postcode":"NE61 5AB",
    "sg:province":"Northumberland",
    "sg:tags":[
        "mixed",
        "crop"
    ],
    "wof:name":"J W Thompson (Whitefield) Ltd.",
    "wof:placetype":"venue"
},
  "geometry": {"coordinates":[-1.601162,55.282227],"type":"Point"}
}