{
  "type": "Feature",
  "properties": {
    "iso:country":"GB",
    "sg:address":"The Pavilion, Whitefield Rd",
    "sg:city":"New Milton",
    "sg:classifiers":[
        {
            "category":"Arena",
            "subcategory":"Sports Club",
            "type":"Entertainment"
        }
    ],
    "sg:phone":"+44 1425 610324",
    "sg:postcode":"BH25 6DE",
    "sg:province":"Hampshire",
    "wof:name":"New Milton Indoor Bowling Club",
    "wof:placetype":"venue"
},
  "geometry": {"coordinates":[-1.671652,50.757618],"type":"Point"}
}