{
  "type": "Feature",
  "properties": {
    "addr:full":"32 Lavant Street Petersfield Hampshire GU32 3EG",
    "addr:housenumber":"32",
    "addr:postcode":"gu32 3eg",
    "addr:street":"Lavant Street",
    "iso:country":"GB",
    "sg:address":"32 Lavant Street",
    "sg:city":"Petersfield",
    "sg:classifiers":[
        {
            "category":"Real Estate",
            "subcategory":"Real Estate Agent",
            "type":"Services"
        }
    ],
    "sg:phone":"+44 1730 262801",
    "sg:postcode":"GU32 3EG",
    "sg:province":"Hampshire",
    "wof:name":"Henry Adams & Partners",
    "wof:placetype":"venue"
},
  "geometry": {"coordinates":[-0.941248,51.006691],"type":"Point"}
}