{
  "type": "Feature",
  "properties": {
    "addr:full":"Leadstone, Warren Road Dawlish Devon EX7 0NG",
    "addr:postcode":"ex7 0ng",
    "addr:street":"Warren Road",
    "iso:country":"GB",
    "sg:address":"Leadstone, Warren Road",
    "sg:city":"Dawlish",
    "sg:classifiers":[
        {
            "category":"Retail",
            "subcategory":"Auto Repair",
            "type":"Services"
        }
    ],
    "sg:postcode":"EX7 0NG",
    "sg:province":"Devon",
    "sg:tags":[
        "body",
        "car"
    ],
    "wof:name":"Auto Body Repairs",
    "wof:placetype":"venue"
},
  "geometry": {"coordinates":[-3.444837,50.59795],"type":"Point"}
}