{
  "type": "Feature",
  "properties": {
    "iso:country":"GB",
    "sg:address":"43 Ramsey St, High Spen",
    "sg:city":"Rowlands Gill",
    "sg:classifiers":[
        {
            "category":"Personal",
            "subcategory":"Beauty Salon",
            "type":"Services"
        }
    ],
    "sg:postcode":"NE39 2EJ",
    "sg:province":"Durham",
    "sg:tags":[
        "unisex",
        "hairdresser"
    ],
    "wof:name":"Marshall,Linda,",
    "wof:placetype":"venue"
},
  "geometry": {"coordinates":[-1.78271,54.935009],"type":"Point"}
}