{
  "type": "Feature",
  "properties": {
    "addr:full":"Unit 9 Ironbridge Cl, Off Gt Central Way London Greater London NW10 0UF",
    "addr:housenumber":"unit 9",
    "addr:postcode":"nw10 0uf",
    "addr:street":"Off;Central Way",
    "iso:country":"GB",
    "sg:address":"Unit 9 Ironbridge Cl, Off Gt Central Way",
    "sg:city":"London",
    "sg:classifiers":[
        {
            "category":"Professional",
            "subcategory":"Testing Lab",
            "type":"Services"
        }
    ],
    "sg:postcode":"NW10 0UF",
    "sg:province":"Greater London",
    "sg:tags":[
        "laboratory"
    ],
    "wof:name":"Chemputrix Ltd",
    "wof:placetype":"venue"
},
  "geometry": {"coordinates":[-0.252605,51.55307],"type":"Point"}
}