{
  "type": "Feature",
  "properties": {
    "addr:full":"165 Malden Road New Malden Surrey KT3 6AA",
    "addr:housenumber":"165",
    "addr:postcode":"kt3 6aa",
    "addr:street":"Malden Road",
    "iso:country":"GB",
    "sg:address":"165 Malden Road",
    "sg:city":"New Malden",
    "sg:classifiers":[
        {
            "category":"Government",
            "subcategory":"Office",
            "type":"Public Place"
        }
    ],
    "sg:phone":"+44 20 8336 1811",
    "sg:postcode":"KT3 6AA",
    "sg:province":"Surrey",
    "sg:tags":[
        "education",
        "agency",
        "authority"
    ],
    "wof:name":"S Temple",
    "wof:placetype":"venue"
},
  "geometry": {"coordinates":[-0.25556,51.397285],"type":"Point"}
}