{
  "type": "Feature",
  "properties": {
    "iso:country":"GB",
    "sg:address":"The Council Offices, Fleet Street",
    "sg:city":"Beaminster",
    "sg:classifiers":[
        {
            "category":"Government",
            "subcategory":"Office",
            "type":"Public Place"
        }
    ],
    "sg:phone":"+44 1308 863634",
    "sg:postcode":"DT8 3EH",
    "sg:province":"Dorset",
    "sg:tags":[
        "local"
    ],
    "wof:name":"Beaminster Town Council",
    "wof:placetype":"venue"
},
  "geometry": {"coordinates":[-2.738894,50.809006],"type":"Point"}
}