{
  "type": "Feature",
  "properties": {
    "addr:full":"Unit 3, Great Bridge Industrial Estate Tipton West Midlands DY4 0HR",
    "addr:housenumber":"unit 3",
    "addr:postcode":"dy4 0hr",
    "iso:country":"GB",
    "sg:address":"Unit 3, Great Bridge Industrial Estate",
    "sg:city":"Tipton",
    "sg:classifiers":[
        {
            "category":"Manufacturing",
            "subcategory":"Metals",
            "type":"Manufacturing & Wholesale Goods"
        }
    ],
    "sg:phone":"+44 121 520 6141",
    "sg:postcode":"DY4 0HR",
    "sg:province":"West Midlands",
    "sg:tags":[
        "steel",
        "fabricator",
        "erectors"
    ],
    "wof:name":"Dyer (Structural Steelwork) Ltd.",
    "wof:placetype":"venue"
},
  "geometry": {"coordinates":[-2.0706970692,52.528137207],"type":"Point"}
}