{
  "type": "Feature",
  "properties": {
    "addr:full":"144 North Deeside Rd, Peterculter Aberdeen Aberdeen City AB1 0UD",
    "addr:housenumber":"144",
    "addr:postcode":"ab1 0ud",
    "addr:street":"North Deeside Rd",
    "iso:country":"GB",
    "sg:address":"144 North Deeside Rd, Peterculter",
    "sg:city":"Aberdeen",
    "sg:classifiers":[
        {
            "category":"Professional",
            "subcategory":"Business Services",
            "type":"Services"
        }
    ],
    "sg:postcode":"AB1 0UD",
    "sg:province":"Aberdeen City",
    "sg:tags":[
        "bookmaker"
    ],
    "wof:name":"B & D Bookmakers",
    "wof:placetype":"venue"
},
  "geometry": {"coordinates":[-2.2640900612,57.0962600708],"type":"Point"}
}