{
  "type": "Feature",
  "properties": {
    "iso:country":"GB",
    "sg:address":"188 Exeter Street",
    "sg:city":"Plymouth",
    "sg:classifiers":[
        {
            "category":"Building & Trades",
            "subcategory":"Construction",
            "type":"Services"
        }
    ],
    "sg:phone":"+44 1752 263269",
    "sg:postcode":"PL4 0NQ",
    "sg:province":"Devon",
    "sg:tags":[
        "double",
        "window",
        "glazing",
        "installers",
        "replacement"
    ],
    "wof:name":"A G S Home Improvements Ltd",
    "wof:placetype":"venue"
},
  "geometry": {"coordinates":[-4.1267027855,50.3700332642],"type":"Point"}
}