{
  "type": "Feature",
  "properties": {
    "addr:full":"459 Green Lanes London Greater London N13 4BS",
    "addr:housenumber":"459",
    "addr:postcode":"n13 4bs",
    "addr:street":"Green Lanes",
    "iso:country":"GB",
    "sg:address":"459 Green Lanes",
    "sg:city":"London",
    "sg:classifiers":[
        {
            "category":"Personal",
            "subcategory":"Beauty Salon",
            "type":"Services"
        }
    ],
    "sg:phone":"+44 20 8886 0904",
    "sg:postcode":"N13 4BS",
    "sg:province":"Greater London",
    "sg:tags":[
        "lady",
        "hairdresser"
    ],
    "wof:name":"Hair Flair",
    "wof:placetype":"venue"
},
  "geometry": {"coordinates":[-0.1055559963,51.622089386],"type":"Point"}
}