{
  "type": "Feature",
  "properties": {
    "iso:country":"GB",
    "sg:address":"30 Station Road, Kirkby Moxloe",
    "sg:city":"Leicester",
    "sg:classifiers":[
        {
            "category":"Retail",
            "subcategory":"Storage",
            "type":"Services"
        }
    ],
    "sg:phone":"+44 116 239 2499",
    "sg:postcode":"LE9 2EJ",
    "sg:province":"Leicestershire",
    "sg:tags":[
        "household",
        "activity",
        "domestic",
        "removal"
    ],
    "wof:name":"Abbey Light Haulage & Removals",
    "wof:placetype":"venue"
},
  "geometry": {"coordinates":[-1.234292,52.631626],"type":"Point"}
}