{
  "type": "Feature",
  "properties": {
    "addr:full":"Sibleys Orchard, Bedmond Road Hemel Hempstead Hertfordshire HP3 8LJ",
    "addr:postcode":"hp3 8lj",
    "addr:street":"Sibleys;Bedmond Road",
    "iso:country":"GB",
    "sg:address":"Sibleys Orchard, Bedmond Road",
    "sg:city":"Hemel Hempstead",
    "sg:classifiers":[
        {
            "category":"Organizations",
            "subcategory":"Community Association",
            "type":"Services"
        },
        {
            "category":"Organizations",
            "subcategory":"Non-profit Organization",
            "type":"Services"
        }
    ],
    "sg:phone":"+44 1442 242823",
    "sg:postcode":"HP3 8LJ",
    "sg:province":"Hertfordshire",
    "sg:tags":[
        "society",
        "organisation",
        "charity",
        "housing",
        "charitable"
    ],
    "wof:name":"The Abbeyfield Society Ltd",
    "wof:placetype":"venue"
},
  "geometry": {"coordinates":[-0.4291099906,51.7460212708],"type":"Point"}
}