{
  "type": "Feature",
  "properties": {
    "iso:country":"GB",
    "sg:address":"38 Lyndhurst Road",
    "sg:city":"Worthing",
    "sg:classifiers":[
        {
            "category":"Food & Beverages",
            "subcategory":"Bakery",
            "type":"Retail Goods"
        }
    ],
    "sg:phone":"+44 1903 207259",
    "sg:postcode":"BN11 2DF",
    "sg:province":"West Sussex",
    "sg:tags":[
        "baker"
    ],
    "wof:name":"The Bread Bin",
    "wof:placetype":"venue"
},
  "geometry": {"coordinates":[-0.3589349985,50.8160705566],"type":"Point"}
}