{
  "type": "Feature",
  "properties": {
    "iso:country":"GB",
    "sg:address":"75 Samsons Road, Brightlingsea",
    "sg:city":"Colchester",
    "sg:classifiers":[
        {
            "category":"Recreation",
            "subcategory":"Dog Park",
            "type":"Entertainment"
        }
    ],
    "sg:phone":"+44 1206 303760",
    "sg:postcode":"CO7 0RB",
    "sg:province":"Essex",
    "wof:name":"Suzanne's Mobile Grooming Service",
    "wof:placetype":"venue"
},
  "geometry": {"coordinates":[1.019424,51.824421],"type":"Point"}
}