{
  "type": "Feature",
  "properties": {
    "addr:full":"8 Greyfriars Bridge, Longden Coleham Shrewsbury Shropshire SY3 7DS",
    "addr:housenumber":"8",
    "addr:postcode":"sy3 7ds",
    "addr:street":"Greyfriars Bridge Longden Coleham",
    "iso:country":"GB",
    "sg:address":"8 Greyfriars Bridge, Longden Coleham",
    "sg:city":"Shrewsbury",
    "sg:classifiers":[
        {
            "category":"Personal",
            "subcategory":"Beauty Salon",
            "type":"Services"
        }
    ],
    "sg:phone":"+44 1743 233452",
    "sg:postcode":"SY3 7DS",
    "sg:province":"Shropshire",
    "sg:tags":[
        "unisex",
        "hairdresser"
    ],
    "wof:name":"Chanelle Hair Fashions",
    "wof:placetype":"venue"
},
  "geometry": {"coordinates":[-2.748183012,52.7034187317],"type":"Point"}
}