{
  "type": "Feature",
  "properties": {
    "addr:full":"Rhos Aber Belan Estate Caernarfon Isle of Anglesey LL64 5JF",
    "addr:postcode":"ll64 5jf",
    "iso:country":"GB",
    "sg:address":"Rhos Aber Belan Estate",
    "sg:city":"Caernarfon",
    "sg:classifiers":[
        {
            "category":"Building & Trades",
            "subcategory":"Construction",
            "type":"Services"
        }
    ],
    "sg:phone":"+44 1407 810646",
    "sg:postcode":"LL64 5JF",
    "sg:province":"Isle of Anglesey",
    "sg:tags":[
        "decorator",
        "painter"
    ],
    "wof:name":"Edward Hughes",
    "wof:placetype":"venue"
},
  "geometry": {"coordinates":[-4.5202999115,53.2251586914],"type":"Point"}
}