{
  "type": "Feature",
  "properties": {
    "addr:full":"7 Abbotsford Rd Leicester Leicestershire LE5 4DA",
    "addr:housenumber":"7",
    "addr:postcode":"le5 4da",
    "addr:street":"Abbotsford Rd",
    "iso:country":"GB",
    "sg:address":"7 Abbotsford Rd",
    "sg:city":"Leicester",
    "sg:classifiers":[
        {
            "category":"Organizations",
            "subcategory":"Membership Organization",
            "type":"Services"
        }
    ],
    "sg:phone":"+44 116 246 4273",
    "sg:postcode":"LE5 4DA",
    "sg:province":"Leicestershire",
    "sg:tags":[
        "club"
    ],
    "wof:name":"North Evington Conservative Club",
    "wof:placetype":"venue"
},
  "geometry": {"coordinates":[-1.0874660015,52.6412391663],"type":"Point"}
}