{
  "type": "Feature",
  "properties": {
    "addr:full":"1-2 New Market Grn, Eltham London Greater London SE9 5ER",
    "addr:housenumber":"1-2",
    "addr:postcode":"se9 5er",
    "addr:street":"New Market Grn",
    "iso:country":"GB",
    "sg:address":"1-2 New Market Grn, Eltham",
    "sg:city":"London",
    "sg:classifiers":[
        {
            "category":"Food & Beverages",
            "subcategory":"Supermarket",
            "type":"Retail Goods"
        }
    ],
    "sg:phone":"+44 20 8850 5508",
    "sg:postcode":"SE9 5ER",
    "sg:province":"Greater London",
    "wof:name":"Sun Rise Supermarkets Ltd.",
    "wof:placetype":"venue"
},
  "geometry": {"coordinates":[0.0404100008,51.4455718994],"type":"Point"}
}