{
  "type": "Feature",
  "properties": {
    "addr:full":"15 Azalea Gro, Beachwood Runcorn Cheshire WA7 3HU",
    "addr:housenumber":"15",
    "addr:postcode":"wa7 3hu",
    "addr:street":"Azalea Gro",
    "iso:country":"GB",
    "sg:address":"15 Azalea Gro, Beachwood",
    "sg:city":"Runcorn",
    "sg:classifiers":[
        {
            "category":"Retail",
            "subcategory":"Driving School",
            "type":"Services"
        }
    ],
    "sg:phone":"+44 1928 718197",
    "sg:postcode":"WA7 3HU",
    "sg:province":"Cheshire",
    "wof:name":"Ann's School of Motoring",
    "wof:placetype":"venue"
},
  "geometry": {"coordinates":[-2.6975800991,53.3140830994],"type":"Point"}
}