{
  "type": "Feature",
  "properties": {
    "addr:full":"Station Yard Industrial Estate, Oakwell Road Castle Douglas Dumfries and Galloway DG7 1LA",
    "addr:postcode":"dg7 1la",
    "addr:street":"Industrial Estate Oakwell Road",
    "iso:country":"GB",
    "sg:address":"Station Yard Industrial Estate, Oakwell Road",
    "sg:city":"Castle Douglas",
    "sg:classifiers":[
        {
            "category":"Home & Garden",
            "subcategory":"Garden Supply",
            "type":"Retail Goods"
        },
        {
            "category":"Home & Garden",
            "subcategory":"Hardware",
            "type":"Retail Goods"
        }
    ],
    "sg:phone":"+44 1556 503240",
    "sg:postcode":"DG7 1LA",
    "sg:province":"Dumfries and Galloway",
    "sg:tags":[
        "lawnmowers",
        "sales",
        "machinery"
    ],
    "wof:name":"Galloway Power Equipment",
    "wof:placetype":"venue"
},
  "geometry": {"coordinates":[-3.9287040234,54.941619873],"type":"Point"}
}