{
  "type": "Feature",
  "properties": {
    "addr:full":"Thirsk Industrial Park, York Rd Thirsk North Yorkshire YO7 3TD",
    "addr:postcode":"yo7 3td",
    "addr:street":"York Rd",
    "iso:country":"GB",
    "sg:address":"Thirsk Industrial Park, York Rd",
    "sg:city":"Thirsk",
    "sg:classifiers":[
        {
            "category":"Wholesale",
            "subcategory":"Fruits & Vegetables",
            "type":"Manufacturing & Wholesale Goods"
        }
    ],
    "sg:phone":"+44 1845 524030",
    "sg:postcode":"YO7 3TD",
    "sg:province":"North Yorkshire",
    "wof:name":"Hambleton Fresh Produce",
    "wof:placetype":"venue"
},
  "geometry": {"coordinates":[-1.3286190033,54.2314186096],"type":"Point"}
}