{
  "type": "Feature",
  "properties": {
    "addr:full":"The Old Chapel Hawes North Yorkshire DL8 3PB",
    "addr:postcode":"dl8 3pb",
    "iso:country":"GB",
    "sg:address":"The Old Chapel",
    "sg:city":"Hawes",
    "sg:classifiers":[
        {
            "category":"Military Area",
            "subcategory":"Air Force Base",
            "type":"Public Place"
        }
    ],
    "sg:phone":"+44 1931 715050",
    "sg:postcode":"DL8 3PB",
    "sg:province":"North Yorkshire",
    "sg:tags":[
        "gliding",
        "paragliding",
        "hang"
    ],
    "wof:name":"Lakes Paragliding",
    "wof:placetype":"venue"
},
  "geometry": {"coordinates":[-2.1994268894,54.3041763306],"type":"Point"}
}