{
  "type": "Feature",
  "properties": {
    "iso:country":"GB",
    "sg:address":"P O Box 8",
    "sg:city":"Chesterfield",
    "sg:classifiers":[
        {
            "category":"Professional",
            "subcategory":"Lawyer & Legal Services",
            "type":"Services"
        }
    ],
    "sg:phone":"+44 1246 559431",
    "sg:postcode":"S40 1NY",
    "sg:province":"Derbyshire",
    "sg:tags":[
        "advice",
        "counselling"
    ],
    "wof:name":"Chesterfield Area Lesbian Line",
    "wof:placetype":"venue"
},
  "geometry": {"coordinates":[-1.44194,53.23637],"type":"Point"}
}