{
  "type": "Feature",
  "properties": {
    "addr:full":"33 Manor Road Enfield Greater London EN2 0AN",
    "addr:housenumber":"33",
    "addr:postcode":"en2 0an",
    "addr:street":"Manor Road",
    "iso:country":"GB",
    "sg:address":"33 Manor Road",
    "sg:city":"Enfield",
    "sg:classifiers":[
        {
            "category":"Building & Trades",
            "subcategory":"Construction",
            "type":"Services"
        }
    ],
    "sg:phone":"+44 20 8363 7797",
    "sg:postcode":"EN2 0AN",
    "sg:province":"Greater London",
    "sg:tags":[
        "builder"
    ],
    "wof:name":"Colin Sliman",
    "wof:placetype":"venue"
},
  "geometry": {"coordinates":[-0.085548,51.659481],"type":"Point"}
}