{
  "type": "Feature",
  "properties": {
    "iso:country":"GB",
    "sg:address":"Unit 1 Station Yard, Worcester Road",
    "sg:city":"Leominster",
    "sg:classifiers":[
        {
            "category":"Military Area",
            "subcategory":"Air Force Base",
            "type":"Public Place"
        }
    ],
    "sg:phone":"+44 1568 616694",
    "sg:postcode":"HR6 8AR",
    "sg:province":"Herefordshire",
    "sg:tags":[
        "taxi",
        "hire",
        "private"
    ],
    "wof:name":"Goldline Taxis",
    "wof:placetype":"venue"
},
  "geometry": {"coordinates":[-2.743553,52.227077],"type":"Point"}
}