{
  "type": "Feature",
  "properties": {
    "addr:full":"153 Victoria Dr Eastbourne East Sussex BN20 8NH",
    "addr:housenumber":"153",
    "addr:postcode":"bn20 8nh",
    "addr:street":"Victoria Dr",
    "iso:country":"GB",
    "sg:address":"153 Victoria Dr",
    "sg:city":"Eastbourne",
    "sg:classifiers":[
        {
            "category":"Bars & Pubs",
            "type":"Food & Drink"
        }
    ],
    "sg:postcode":"BN20 8NH",
    "sg:province":"East Sussex",
    "sg:tags":[
        "pubs",
        "inn"
    ],
    "wof:name":"Graham,G C,",
    "wof:placetype":"venue"
},
  "geometry": {"coordinates":[0.2555820048,50.7778663635],"type":"Point"}
}