{
  "type": "Feature",
  "properties": {
    "addr:full":"Paterson Avenue, Logan Cumnock East Ayrshire KA18 3HR",
    "addr:postcode":"ka18 3hr",
    "addr:street":"Paterson Avenue;Cumnock East",
    "iso:country":"GB",
    "sg:address":"Paterson Avenue, Logan",
    "sg:city":"Cumnock",
    "sg:classifiers":[
        {
            "category":"Social Services",
            "subcategory":"Adult Care",
            "type":"Services"
        },
        {
            "category":"Government",
            "subcategory":"Office",
            "type":"Public Place"
        }
    ],
    "sg:phone":"+44 1290 423356",
    "sg:postcode":"KA18 3HR",
    "sg:province":"East Ayrshire",
    "sg:tags":[
        "housing",
        "local",
        "sheltered"
    ],
    "wof:name":"Paterson Ave Sheltered Housing",
    "wof:placetype":"venue"
},
  "geometry": {"coordinates":[-4.2334327698,55.4584732056],"type":"Point"}
}