{
  "type": "Feature",
  "properties": {
    "addr:full":"76 Front Street East Bedlington Northumberland NE22 5AB",
    "addr:housenumber":"76",
    "addr:postcode":"ne22 5ab",
    "addr:street":"Front Street East",
    "iso:country":"GB",
    "sg:address":"76 Front Street East",
    "sg:city":"Bedlington",
    "sg:classifiers":[
        {
            "category":"Shopping",
            "subcategory":"Pets & Pet Supplies",
            "type":"Retail Goods"
        }
    ],
    "sg:phone":"+44 1670 530344",
    "sg:postcode":"NE22 5AB",
    "sg:province":"Northumberland",
    "wof:name":"Feather & Fins",
    "wof:placetype":"venue"
},
  "geometry": {"coordinates":[-1.591336,55.130035],"type":"Point"}
}