{
  "type": "Feature",
  "properties": {
    "addr:full":"Balkerach Street Doune Stirling FK16 6DG",
    "addr:postcode":"fk16 6dg",
    "addr:street":"Balkerach Street",
    "iso:country":"GB",
    "sg:address":"Balkerach Street",
    "sg:city":"Doune",
    "sg:classifiers":[
        {
            "category":"Manufacturing",
            "subcategory":"Lumber",
            "type":"Manufacturing & Wholesale Goods"
        }
    ],
    "sg:phone":"+44 1786 841204",
    "sg:postcode":"FK16 6DG",
    "sg:province":"Stirling",
    "sg:tags":[
        "importer",
        "merchants",
        "agent",
        "timber"
    ],
    "wof:name":"Hugh Campbell & Sons (Doune) Ltd.",
    "wof:placetype":"venue"
},
  "geometry": {"coordinates":[-4.0550627708,56.190952301],"type":"Point"}
}