{
  "type": "Feature",
  "properties": {
    "addr:full":"The Wharf, Buxton Road Stockport Cheshire SK6 8AA",
    "addr:postcode":"sk6 8aa",
    "addr:street":"Buxton Road",
    "iso:country":"GB",
    "sg:address":"The Wharf, Buxton Road",
    "sg:city":"Stockport",
    "sg:classifiers":[
        {
            "category":"Organizations",
            "subcategory":"Membership Organization",
            "type":"Services"
        }
    ],
    "sg:phone":"+44 1663 765581",
    "sg:postcode":"SK6 8AA",
    "sg:province":"Cheshire",
    "sg:tags":[
        "club"
    ],
    "wof:name":"The North Cheshire Cruising Club",
    "wof:placetype":"venue"
},
  "geometry": {"coordinates":[-2.07822,53.365181],"type":"Point"}
}