{
  "type": "Feature",
  "properties": {
    "addr:full":"A505 Baldock Rd Royston Bedfordshire SG8 9NT",
    "addr:postcode":"sg8 9nt",
    "addr:street":"Baldock Rd",
    "iso:country":"GB",
    "sg:address":"A505 Baldock Rd",
    "sg:city":"Royston",
    "sg:classifiers":[
        {
            "category":"Restaurant",
            "type":"Food & Drink"
        }
    ],
    "sg:phone":"+44 1763 241955",
    "sg:postcode":"SG8 9NT",
    "sg:province":"Bedfordshire",
    "wof:name":"Little Chef",
    "wof:placetype":"venue"
},
  "geometry": {"coordinates":[-0.0598790012,52.044342041],"type":"Point"}
}