{
  "type": "Feature",
  "properties": {
    "addr:full":"Orchard Cottage, Huckford La Bristol City of Bristol BS17 1AP",
    "addr:postcode":"bs17 1ap",
    "addr:street":"Huckford La",
    "iso:country":"GB",
    "sg:address":"Orchard Cottage, Huckford La",
    "sg:city":"Bristol",
    "sg:classifiers":[
        {
            "category":"Professional",
            "subcategory":"Engineering",
            "type":"Services"
        }
    ],
    "sg:phone":"+44 1454 773596",
    "sg:postcode":"BS17 1AP",
    "sg:province":"City of Bristol",
    "wof:name":"Quality Products",
    "wof:placetype":"venue"
},
  "geometry": {"coordinates":[-2.4866259098,51.5157966614],"type":"Point"}
}