{
  "type": "Feature",
  "properties": {
    "iso:country":"GB",
    "sg:address":"Unit 3 Albion Park, Armley Rd",
    "sg:city":"Leeds",
    "sg:classifiers":[
        {
            "category":"Manufacturing",
            "subcategory":"Wood Products",
            "type":"Manufacturing & Wholesale Goods"
        }
    ],
    "sg:phone":"+44 113 244 9830",
    "sg:postcode":"LS12 2EJ",
    "sg:province":"West Yorkshire",
    "sg:tags":[
        "packaging",
        "crate",
        "pallets"
    ],
    "wof:name":"Yorkshire Contract Packers Ltd",
    "wof:placetype":"venue"
},
  "geometry": {"coordinates":[-1.571646,53.797646],"type":"Point"}
}