{
  "type": "Feature",
  "properties": {
    "addr:full":"Ashlands, High Cross Lane, Little Canfield Dunmow Essex CM6 1TG",
    "addr:postcode":"cm6 1tg",
    "addr:street":"Cross Lane",
    "iso:country":"GB",
    "sg:address":"Ashlands, High Cross Lane, Little Canfield",
    "sg:city":"Dunmow",
    "sg:classifiers":[
        {
            "category":"Farming",
            "subcategory":"Livestock Farm",
            "type":"Manufacturing & Wholesale Goods"
        }
    ],
    "sg:phone":"+44 1371 872643",
    "sg:postcode":"CM6 1TG",
    "sg:province":"Essex",
    "sg:tags":[
        "others"
    ],
    "wof:name":"John Turner & Partners",
    "wof:placetype":"venue"
},
  "geometry": {"coordinates":[0.364977,51.870613],"type":"Point"}
}