{
  "type": "Feature",
  "properties": {
    "addr:full":"12-14 Bath Street Nottingham Nottinghamshire NG1 1DF",
    "addr:housenumber":"12-14",
    "addr:postcode":"ng1 1df",
    "addr:street":"Bath Street",
    "iso:country":"GB",
    "sg:address":"12-14 Bath Street",
    "sg:city":"Nottingham",
    "sg:classifiers":[
        {
            "category":"Home & Garden",
            "subcategory":"Furniture",
            "type":"Retail Goods"
        }
    ],
    "sg:postcode":"NG1 1DF",
    "sg:province":"Nottinghamshire",
    "wof:name":"Abbey Furniture",
    "wof:placetype":"venue"
},
  "geometry": {"coordinates":[-1.1370689869,52.9542198181],"type":"Point"}
}