{
  "type": "Feature",
  "properties": {
    "iso:country":"GB",
    "sg:address":"Unit 2 Kilfield House, Viking Way, Winchwen Industrial Estate",
    "sg:city":"Swansea",
    "sg:classifiers":[
        {
            "category":"Shopping",
            "subcategory":"Computers & Home Electronics",
            "type":"Retail Goods"
        }
    ],
    "sg:postcode":"SA1 7DA",
    "sg:province":"Neath Port Talbot",
    "sg:tags":[
        "equipment",
        "radio"
    ],
    "wof:name":"A P Logistics Ltd.",
    "wof:placetype":"venue"
},
  "geometry": {"coordinates":[-3.901929,51.655285],"type":"Point"}
}