{
  "type": "Feature",
  "properties": {
    "iso:country":"GB",
    "sg:address":"13 Erroll Street",
    "sg:city":"Peterhead",
    "sg:classifiers":[
        {
            "category":"Cafe",
            "type":"Food & Drink"
        }
    ],
    "sg:phone":"+44 1779 470982",
    "sg:postcode":"AB42 1PU",
    "sg:province":"Aberdeenshire",
    "sg:tags":[
        "tea",
        "snack",
        "bar",
        "room"
    ],
    "wof:name":"Cafe Rio",
    "wof:placetype":"venue"
},
  "geometry": {"coordinates":[-1.78267,57.505051],"type":"Point"}
}