{
  "type": "Feature",
  "properties": {
    "iso:country":"GB",
    "sg:address":"105 Victoria St",
    "sg:city":"Fleetwood",
    "sg:classifiers":[
        {
            "category":"Building & Trades",
            "subcategory":"Construction",
            "type":"Services"
        }
    ],
    "sg:phone":"+44 1253 878181",
    "sg:postcode":"FY7 6EL",
    "sg:province":"Lancashire",
    "sg:tags":[
        "decorator",
        "painter"
    ],
    "wof:name":"A Darlington",
    "wof:placetype":"venue"
},
  "geometry": {"coordinates":[-3.0131599903,53.9253196716],"type":"Point"}
}