{
  "type": "Feature",
  "properties": {
    "iso:country":"GB",
    "sg:address":"25 Farncombe Hill",
    "sg:city":"Godalming",
    "sg:classifiers":[
        {
            "category":"Health Services",
            "subcategory":"Podiatrist",
            "type":"Services"
        }
    ],
    "sg:phone":"+44 1483 421251",
    "sg:postcode":"GU7 2AU",
    "sg:province":"Surrey",
    "sg:tags":[
        "podiatrists",
        "chiropodist"
    ],
    "wof:name":"P R Batten",
    "wof:placetype":"venue"
},
  "geometry": {"coordinates":[-0.61362,51.197617],"type":"Point"}
}