{
  "type": "Feature",
  "properties": {
    "addr:full":"30 Wootton Rd Abingdon Oxfordshire OX14 1JD",
    "addr:housenumber":"30",
    "addr:postcode":"ox14 1jd",
    "addr:street":"Wootton Rd",
    "iso:country":"GB",
    "sg:address":"30 Wootton Rd",
    "sg:city":"Abingdon",
    "sg:classifiers":[
        {
            "category":"Wholesale",
            "subcategory":"Construction Materials",
            "type":"Manufacturing & Wholesale Goods"
        }
    ],
    "sg:phone":"+44 1235 559245",
    "sg:postcode":"OX14 1JD",
    "sg:province":"Oxfordshire",
    "sg:tags":[
        "merchant",
        "glass"
    ],
    "wof:name":"S Bexi Nowak",
    "wof:placetype":"venue"
},
  "geometry": {"coordinates":[-1.2874439955,51.6771507263],"type":"Point"}
}