{
  "type": "Feature",
  "properties": {
    "iso:country":"GB",
    "sg:address":"19 Shildon Close",
    "sg:city":"Wigan",
    "sg:classifiers":[
        {
            "category":"Professional",
            "subcategory":"Engineering",
            "type":"Services"
        }
    ],
    "sg:phone":"+44 1942 239874",
    "sg:postcode":"WN2 1AN",
    "sg:province":"Lancashire",
    "sg:tags":[
        "contractor",
        "electrical",
        "engineer"
    ],
    "wof:name":"Omega Electrical Services",
    "wof:placetype":"venue"
},
  "geometry": {"coordinates":[-2.607293,53.554249],"type":"Point"}
}