{
  "type": "Feature",
  "properties": {
    "addr:full":"Unit 1 201 Belsize Rd Kilburn Greater London NW6 4AA",
    "addr:housenumber":"unit 1",
    "addr:postcode":"201;nw6 4aa",
    "addr:street":"Belsize Rd",
    "iso:country":"GB",
    "sg:address":"Unit 1 201 Belsize Rd",
    "sg:city":"Kilburn",
    "sg:classifiers":[
        {
            "category":"Home & Garden",
            "subcategory":"Carpets & Floor Coverings",
            "type":"Retail Goods"
        }
    ],
    "sg:phone":"+44 20 7813 0232",
    "sg:postcode":"NW6 4AA",
    "sg:province":"Greater London",
    "sg:tags":[
        "cleaner",
        "upholstery"
    ],
    "wof:name":"Firstchoice Cleaning Services",
    "wof:placetype":"venue"
},
  "geometry": {"coordinates":[-0.1903920025,51.538444519],"type":"Point"}
}