{
  "type": "Feature",
  "properties": {
    "iso:country":"GB",
    "sg:address":"157a Sefton Street",
    "sg:city":"Southport",
    "sg:classifiers":[
        {
            "category":"Farming",
            "subcategory":"Dairy Farm",
            "type":"Manufacturing & Wholesale Goods"
        },
        {
            "category":"Food & Beverages",
            "subcategory":"Dairy",
            "type":"Retail Goods"
        }
    ],
    "sg:phone":"+44 1704 538537",
    "sg:postcode":"PR8 5DA",
    "sg:province":"Lancashire",
    "sg:tags":[
        "merchant",
        "produce"
    ],
    "wof:name":"Manor Lodge Dairy Products",
    "wof:placetype":"venue"
},
  "geometry": {"coordinates":[-3.004292,53.636162],"type":"Point"}
}