{
  "type": "Feature",
  "properties": {
    "addr:full":"Muglet Lane, Maltby Rotherham South Yorkshire S66 7JU",
    "addr:postcode":"s66 7ju",
    "addr:street":"Muglet Lane",
    "iso:country":"GB",
    "sg:address":"Muglet Lane, Maltby",
    "sg:city":"Rotherham",
    "sg:classifiers":[
        {
            "category":"Community Center",
            "type":"Public Place"
        },
        {
            "category":"Government",
            "subcategory":"Office",
            "type":"Public Place"
        }
    ],
    "sg:phone":"+44 1709 814104",
    "sg:postcode":"S66 7JU",
    "sg:province":"South Yorkshire",
    "sg:tags":[
        "recreation",
        "local",
        "leisure",
        "centre"
    ],
    "wof:name":"Muglet Lane Recreation Ground",
    "wof:placetype":"venue"
},
  "geometry": {"coordinates":[-1.1944570541,53.420375824],"type":"Point"}
}