{
  "type": "Feature",
  "properties": {
    "addr:full":"Old Chapel School Street, Rhostyllen Wrexham Wrexham LL14 4AN",
    "addr:postcode":"ll14 4an",
    "addr:street":"Old;School Street",
    "iso:country":"GB",
    "sg:address":"Old Chapel School Street, Rhostyllen",
    "sg:city":"Wrexham",
    "sg:classifiers":[
        {
            "category":"Personal",
            "subcategory":"Beauty Salon",
            "type":"Services"
        }
    ],
    "sg:phone":"+44 1978 358093",
    "sg:postcode":"LL14 4AN",
    "sg:province":"Wrexham",
    "sg:tags":[
        "unisex",
        "hairdresser"
    ],
    "wof:name":"Head Waves",
    "wof:placetype":"venue"
},
  "geometry": {"coordinates":[-3.0189139843,53.0321731567],"type":"Point"}
}