{
  "type": "Feature",
  "properties": {
    "addr:full":"Satellite Office, D E R A Pendine, Building 148 Carmarthen Carmarthenshire SA33 4UA",
    "addr:housenumber":"148",
    "addr:postcode":"sa33 4ua",
    "iso:country":"GB",
    "sg:address":"Satellite Office, D E R A Pendine, Building 148",
    "sg:city":"Carmarthen",
    "sg:classifiers":[
        {
            "category":"Professional",
            "subcategory":"Engineering",
            "type":"Services"
        }
    ],
    "sg:phone":"+44 1994 453316",
    "sg:postcode":"SA33 4UA",
    "sg:province":"Carmarthenshire",
    "sg:tags":[
        "consulting",
        "engineer"
    ],
    "wof:name":"Colquhoun E W C Thorburn",
    "wof:placetype":"venue"
},
  "geometry": {"coordinates":[-4.5387401581,51.750629425],"type":"Point"}
}