{
  "type": "Feature",
  "properties": {
    "iso:country":"GB",
    "sg:address":"472 Dumbarton Road",
    "sg:city":"Glasgow",
    "sg:classifiers":[
        {
            "category":"Food & Beverages",
            "subcategory":"Bakery",
            "type":"Retail Goods"
        }
    ],
    "sg:postcode":"G11 6SQ",
    "sg:province":"Glasgow City",
    "sg:tags":[
        "baker"
    ],
    "wof:name":"G & A McHarg",
    "wof:placetype":"venue"
},
  "geometry": {"coordinates":[-4.31235,55.870968],"type":"Point"}
}