{
  "type": "Feature",
  "properties": {
    "iso:country":"GB",
    "sg:address":"Unit 9ma Brookfield Indust Park",
    "sg:city":"Peterborough",
    "sg:classifiers":[
        {
            "category":"Government",
            "subcategory":"Post Office",
            "type":"Public Place"
        }
    ],
    "sg:phone":"+44 1733 322111",
    "sg:postcode":"PE4 6LA",
    "sg:province":"Cambridgeshire",
    "sg:tags":[
        "messenger",
        "courier"
    ],
    "wof:name":"Full Circle Freight",
    "wof:placetype":"venue"
},
  "geometry": {"coordinates":[-0.2798750103,52.6099319458],"type":"Point"}
}