{
  "type": "Feature",
  "properties": {
    "iso:country":"GB",
    "sg:address":"7 Elmbank Terrace",
    "sg:city":"Aberdeen",
    "sg:classifiers":[
        {
            "category":"Personal",
            "subcategory":"Beauty Salon",
            "type":"Services"
        },
        {
            "category":"Personal",
            "subcategory":"Barber",
            "type":"Services"
        }
    ],
    "sg:phone":"+44 1224 633797",
    "sg:postcode":"AB24 3PW",
    "sg:province":"Aberdeen City",
    "sg:tags":[
        "unisex",
        "hairdresser"
    ],
    "wof:name":"Scissors Hair Salon",
    "wof:placetype":"venue"
},
  "geometry": {"coordinates":[-2.106134,57.157337],"type":"Point"}
}