{
  "type": "Feature",
  "properties": {
    "addr:full":"104 Woodfield Street, Morriston Swansea Swansea SA6 8AS",
    "addr:housenumber":"104",
    "addr:postcode":"sa6 8as",
    "addr:street":"Woodfield Street",
    "iso:country":"GB",
    "sg:address":"104 Woodfield Street, Morriston",
    "sg:city":"Swansea",
    "sg:classifiers":[
        {
            "category":"Shopping",
            "subcategory":"Thrift Store",
            "type":"Retail Goods"
        }
    ],
    "sg:phone":"+44 1792 790338",
    "sg:postcode":"SA6 8AS",
    "sg:province":"Swansea",
    "sg:tags":[
        "shop",
        "charity"
    ],
    "wof:name":"British Red Cross Society",
    "wof:placetype":"venue"
},
  "geometry": {"coordinates":[-3.926047,51.664665],"type":"Point"}
}