{
  "type": "Feature",
  "properties": {
    "iso:country":"GB",
    "sg:address":"87 London Road, Cowplain",
    "sg:city":"Waterlooville",
    "sg:classifiers":[
        {
            "category":"Shopping",
            "subcategory":"Computers & Home Electronics",
            "type":"Retail Goods"
        }
    ],
    "sg:postcode":"PO8 8XB",
    "sg:province":"Hampshire",
    "sg:tags":[
        "equipment",
        "video",
        "cctv"
    ],
    "wof:name":"High Mast Video Ltd.",
    "wof:placetype":"venue"
},
  "geometry": {"coordinates":[-1.017705,50.895397],"type":"Point"}
}