{
  "type": "Feature",
  "properties": {
    "addr:full":"26 Truemper Grove, Caversfield Bicester Buckinghamshire OX27 8FD",
    "addr:housenumber":"26",
    "addr:postcode":"ox27 8fd",
    "addr:street":"Truemper Grove",
    "iso:country":"GB",
    "sg:address":"26 Truemper Grove, Caversfield",
    "sg:city":"Bicester",
    "sg:classifiers":[
        {
            "category":"Organizations",
            "subcategory":"Membership Organization",
            "type":"Services"
        }
    ],
    "sg:phone":"+44 1869 321765",
    "sg:postcode":"OX27 8FD",
    "sg:province":"Buckinghamshire",
    "sg:tags":[
        "club"
    ],
    "wof:name":"Stratton Fields Management Ltd.",
    "wof:placetype":"venue"
},
  "geometry": {"coordinates":[-1.1442660093,51.9220161438],"type":"Point"}
}