{
  "type": "Feature",
  "properties": {
    "iso:country":"GB",
    "sg:address":"Kingston Farm, Inchture",
    "sg:city":"Perth",
    "sg:classifiers":[
        {
            "category":"Farming",
            "subcategory":"Livestock Farm",
            "type":"Manufacturing & Wholesale Goods"
        }
    ],
    "sg:phone":"+44 1828 686221",
    "sg:postcode":"PH14 9QR",
    "sg:province":"Perth and Kinross",
    "sg:tags":[
        "others"
    ],
    "wof:name":"J & G Moulton",
    "wof:placetype":"venue"
},
  "geometry": {"coordinates":[-3.168468,56.446461],"type":"Point"}
}