{
  "type": "Feature",
  "properties": {
    "iso:country":"GB",
    "sg:address":"Orchard Works, Backfields, Upton-upon-severn",
    "sg:city":"Worcester",
    "sg:classifiers":[
        {
            "category":"Utilities",
            "subcategory":"Telephone",
            "type":"Services"
        }
    ],
    "sg:phone":"+44 1684 594000",
    "sg:postcode":"WR8 0JH",
    "sg:province":"Gloucestershire",
    "sg:tags":[
        "telecommunication"
    ],
    "wof:name":"Midland Communications Co. Ltd.",
    "wof:placetype":"venue"
},
  "geometry": {"coordinates":[-2.21738,52.063599],"type":"Point"}
}