{
  "type": "Feature",
  "properties": {
    "addr:full":"159 Clarence Road Windsor Berkshire SL4 5AP",
    "addr:housenumber":"159",
    "addr:postcode":"sl4 5ap",
    "addr:street":"Clarence Road",
    "iso:country":"GB",
    "sg:address":"159 Clarence Road",
    "sg:city":"Windsor",
    "sg:classifiers":[
        {
            "category":"Real Estate",
            "subcategory":"Developer",
            "type":"Services"
        }
    ],
    "sg:phone":"+44 1753 621000",
    "sg:postcode":"SL4 5AP",
    "sg:province":"Berkshire",
    "sg:tags":[
        "property"
    ],
    "wof:name":"Park Properties",
    "wof:placetype":"venue"
},
  "geometry": {"coordinates":[-0.6259059906,51.4799156189],"type":"Point"}
}