{
  "type": "Feature",
  "properties": {
    "addr:full":"9 Charles Ct Colchester Essex CO3 5YS",
    "addr:housenumber":"9",
    "addr:postcode":"co3 5ys",
    "addr:street":"Charles Ct Colchester",
    "iso:country":"GB",
    "sg:address":"9 Charles Ct",
    "sg:city":"Colchester",
    "sg:classifiers":[
        {
            "category":"Parking",
            "type":"Transportation"
        }
    ],
    "sg:phone":"+44 1206 769662",
    "sg:postcode":"CO3 5YS",
    "sg:province":"Essex",
    "sg:tags":[
        "car",
        "valet"
    ],
    "wof:name":"Megashine",
    "wof:placetype":"venue"
},
  "geometry": {"coordinates":[0.910528,51.884354],"type":"Point"}
}