{
  "type": "Feature",
  "properties": {
    "addr:full":"Hillfield Rd Hemel Hempstead Hertfordshire HP2 4AA",
    "addr:postcode":"hp2 4aa",
    "addr:street":"Hillfield Rd",
    "iso:country":"GB",
    "sg:address":"Hillfield Rd",
    "sg:city":"Hemel Hempstead",
    "sg:classifiers":[
        {
            "category":"Food & Beverages",
            "subcategory":"Supermarket",
            "type":"Retail Goods"
        }
    ],
    "sg:phone":"+44 1442 212802",
    "sg:postcode":"HP2 4AA",
    "sg:province":"Hertfordshire",
    "wof:name":"Somerfield",
    "wof:placetype":"venue"
},
  "geometry": {"coordinates":[-0.464354,51.752876],"type":"Point"}
}