{
  "type": "Feature",
  "properties": {
    "iso:country":"GB",
    "sg:address":"Flat 6 9 Brunswick Terrace",
    "sg:city":"Hove",
    "sg:classifiers":[
        {
            "category":"Organizations",
            "subcategory":"Membership Organization",
            "type":"Services"
        }
    ],
    "sg:postcode":"BN3 1HL",
    "sg:province":"East Sussex",
    "sg:tags":[
        "club"
    ],
    "wof:name":"9 Brunswick Terrace Management Ltd.",
    "wof:placetype":"venue"
},
  "geometry": {"coordinates":[-0.182449,50.838943],"type":"Point"}
}