{
  "type": "Feature",
  "properties": {
    "iso:country":"GB",
    "sg:address":"335 Bath Road, Cippenham",
    "sg:city":"Slough",
    "sg:classifiers":[
        {
            "category":"Autos & Motor Vehicles",
            "subcategory":"Auto Supplies",
            "type":"Retail Goods"
        }
    ],
    "sg:phone":"+44 1628 664845",
    "sg:postcode":"SL1 5PR",
    "sg:province":"Berkshire",
    "sg:tags":[
        "towing",
        "eqpt",
        "trailer"
    ],
    "wof:name":"K & M Coachworks",
    "wof:placetype":"venue"
},
  "geometry": {"coordinates":[-0.640629,51.514511],"type":"Point"}
}