{
  "type": "Feature",
  "properties": {
    "addr:full":"Oak Tree Inn, Yarm Road, Middleton St George Darlington Durham DL2 1HN",
    "addr:postcode":"dl2 1hn",
    "addr:street":"Yarm Road Middleton",
    "iso:country":"GB",
    "sg:address":"Oak Tree Inn, Yarm Road, Middleton St George",
    "sg:city":"Darlington",
    "sg:classifiers":[
        {
            "category":"Bars & Pubs",
            "type":"Food & Drink"
        }
    ],
    "sg:phone":"+44 1325 332642",
    "sg:postcode":"DL2 1HN",
    "sg:province":"Durham",
    "sg:tags":[
        "pubs",
        "inn"
    ],
    "wof:name":"Pubmaster Ltd.",
    "wof:placetype":"venue"
},
  "geometry": {"coordinates":[-1.4404599667,54.5145187378],"type":"Point"}
}