{
  "type": "Feature",
  "properties": {
    "addr:full":"19 Eastbourne Close, Ingol Preston Lancashire PR2 3YR",
    "addr:housenumber":"19",
    "addr:postcode":"pr2 3yr",
    "addr:street":"Eastbourne Close",
    "iso:country":"GB",
    "sg:address":"19 Eastbourne Close, Ingol",
    "sg:city":"Preston",
    "sg:classifiers":[
        {
            "category":"Bars & Pubs",
            "subcategory":"Nightclub",
            "type":"Food & Drink"
        }
    ],
    "sg:phone":"+44 1772 724252",
    "sg:postcode":"PR2 3YR",
    "sg:province":"Lancashire",
    "sg:tags":[
        "karaoke"
    ],
    "wof:name":"Karaoke Show Time",
    "wof:placetype":"venue"
},
  "geometry": {"coordinates":[-2.747365,53.782784],"type":"Point"}
}