{
  "type": "Feature",
  "properties": {
    "iso:country":"GB",
    "sg:address":"56 East Street",
    "sg:city":"Chichester",
    "sg:classifiers":[
        {
            "category":"Shopping",
            "subcategory":"Luggage & Leather Goods",
            "type":"Retail Goods"
        }
    ],
    "sg:postcode":"PO19 1JG",
    "sg:province":"West Sussex",
    "wof:name":"Gladstone",
    "wof:placetype":"venue"
},
  "geometry": {"coordinates":[-0.774933,50.83606],"type":"Point"}
}