{
  "type": "Feature",
  "properties": {
    "addr:full":"The Forge, Dark Lane, North Wootton Shepton Mallet Somerset BA4 4AQ",
    "addr:postcode":"ba4 4aq",
    "addr:street":"Dark Lane",
    "iso:country":"GB",
    "sg:address":"The Forge, Dark Lane, North Wootton",
    "sg:city":"Shepton Mallet",
    "sg:classifiers":[
        {
            "category":"Professional",
            "subcategory":"Engineering",
            "type":"Services"
        },
        {
            "category":"Wholesale",
            "subcategory":"Machinery & Supplies",
            "type":"Manufacturing & Wholesale Goods"
        }
    ],
    "sg:phone":"+44 1749 890288",
    "sg:postcode":"BA4 4AQ",
    "sg:province":"Somerset",
    "sg:tags":[
        "agricultural",
        "engineer"
    ],
    "wof:name":"O V Garland & Sons Ltd",
    "wof:placetype":"venue"
},
  "geometry": {"coordinates":[-2.5467779636,51.1897315979],"type":"Point"}
}