{
  "type": "Feature",
  "properties": {
    "iso:country":"GB",
    "sg:address":"Richmond House, 3 Horsefair, Boroughbridge",
    "sg:city":"York",
    "sg:classifiers":[
        {
            "category":"Fast Food",
            "type":"Food & Drink"
        }
    ],
    "sg:phone":"+44 1423 323525",
    "sg:postcode":"YO51 9AA",
    "sg:province":"North Yorkshire",
    "sg:tags":[
        "away",
        "take"
    ],
    "wof:name":"Flavours of India",
    "wof:placetype":"venue"
},
  "geometry": {"coordinates":[-1.397669,54.094799],"type":"Point"}
}