{
  "type": "Feature",
  "properties": {
    "iso:country":"GB",
    "sg:address":"Chalcraft Nurseries, Shirehall Road, Hawley",
    "sg:city":"Dartford",
    "sg:classifiers":[
        {
            "category":"Home & Garden",
            "subcategory":"Mobile Homes",
            "type":"Retail Goods"
        },
        {
            "category":"Shopping",
            "subcategory":"Florist",
            "type":"Retail Goods"
        }
    ],
    "sg:phone":"+44 1322 292644",
    "sg:postcode":"DA2 7SE",
    "sg:province":"Kent",
    "sg:tags":[
        "floral",
        "plant",
        "display"
    ],
    "wof:name":"Provincial Planters Ltd",
    "wof:placetype":"venue"
},
  "geometry": {"coordinates":[0.2312040031,51.4222488403],"type":"Point"}
}