{
  "type": "Feature",
  "properties": {
    "addr:full":"Aldeburgh& District Community Hospital, Park Road Aldeburgh Suffolk IP15 5ES",
    "addr:postcode":"ip15 5es",
    "addr:street":"Park Road",
    "iso:country":"GB",
    "sg:address":"Aldeburgh& District Community Hospital, Park Road",
    "sg:city":"Aldeburgh",
    "sg:classifiers":[
        {
            "category":"Health Services",
            "subcategory":"Hospital",
            "type":"Services"
        }
    ],
    "sg:phone":"+44 1728 452778",
    "sg:postcode":"IP15 5ES",
    "sg:province":"Suffolk",
    "wof:name":"Aldeburgh & District Community Hospital",
    "wof:placetype":"venue"
},
  "geometry": {"coordinates":[1.594405055,52.1560173035],"type":"Point"}
}