{
  "type": "Feature",
  "properties": {
    "iso:country":"GB",
    "sg:address":"2 Liss Road, Southsea",
    "sg:city":"Portsmouth",
    "sg:classifiers":[
        {
            "category":"Shopping",
            "subcategory":"Computers & Home Electronics",
            "type":"Retail Goods"
        }
    ],
    "sg:phone":"+44 23 9229 3000",
    "sg:postcode":"PO4 8AR",
    "sg:province":"Hampshire",
    "wof:name":"Systems 2000 Ltd.",
    "wof:placetype":"venue"
},
  "geometry": {"coordinates":[-1.067685008,50.7929153442],"type":"Point"}
}