{
  "type": "Feature",
  "properties": {
    "addr:full":"39 Station Road, Belmont Sutton Surrey SM2 6DF",
    "addr:housenumber":"39",
    "addr:postcode":"sm2 6df",
    "addr:street":"Station Road",
    "iso:country":"GB",
    "sg:address":"39 Station Road, Belmont",
    "sg:city":"Sutton",
    "sg:classifiers":[
        {
            "category":"Shopping",
            "subcategory":"Pharmacy",
            "type":"Retail Goods"
        }
    ],
    "sg:phone":"+44 20 8770 3765",
    "sg:postcode":"SM2 6DF",
    "sg:province":"Surrey",
    "sg:tags":[
        "medicine",
        "therapy"
    ],
    "wof:name":"Natural Healing Centre",
    "wof:placetype":"venue"
},
  "geometry": {"coordinates":[-0.2015459985,51.3440704346],"type":"Point"}
}