{
  "type": "Feature",
  "properties": {
    "iso:country":"GB",
    "sg:address":"67 Plender Street",
    "sg:city":"London",
    "sg:classifiers":[
        {
            "category":"Health Services",
            "subcategory":"Doctor",
            "type":"Services"
        }
    ],
    "sg:phone":"+44 20 7387 1929",
    "sg:postcode":"NW1 0LB",
    "sg:province":"Greater London",
    "sg:tags":[
        "practitioners"
    ],
    "wof:name":"Alfred G Shina",
    "wof:placetype":"venue"
},
  "geometry": {"coordinates":[-0.137515,51.536503],"type":"Point"}
}