{
  "type": "Feature",
  "properties": {
    "addr:full":"11 Medway Road, Bettws Newport Newport NP20 7XA",
    "addr:housenumber":"11",
    "addr:postcode":"np20 7xa",
    "addr:street":"Medway Road",
    "iso:country":"GB",
    "sg:address":"11 Medway Road, Bettws",
    "sg:city":"Newport",
    "sg:classifiers":[
        {
            "category":"Communications",
            "type":"Services"
        }
    ],
    "sg:phone":"+44 1633 856934",
    "sg:postcode":"NP20 7XA",
    "sg:province":"Newport",
    "sg:tags":[
        "audio-visual"
    ],
    "wof:name":"D R Video Productions",
    "wof:placetype":"venue"
},
  "geometry": {"coordinates":[-3.0326669216,51.6140861511],"type":"Point"}
}