{
  "type": "Feature",
  "properties": {
    "addr:full":"36 Dovers View, Weston Subedge Chipping Campden Gloucestershire GL55 6QS",
    "addr:housenumber":"36",
    "addr:postcode":"gl55 6qs",
    "addr:street":"Dovers View",
    "iso:country":"GB",
    "sg:address":"36 Dovers View, Weston Subedge",
    "sg:city":"Chipping Campden",
    "sg:classifiers":[
        {
            "category":"Building & Trades",
            "subcategory":"Construction",
            "type":"Services"
        }
    ],
    "sg:postcode":"GL55 6QS",
    "sg:province":"Gloucestershire",
    "sg:tags":[
        "glazier",
        "decorator",
        "painter"
    ],
    "wof:name":"Norman Richard Hughes",
    "wof:placetype":"venue"
},
  "geometry": {"coordinates":[-1.779454,52.051388],"type":"Point"}
}