{
  "type": "Feature",
  "properties": {
    "iso:country":"GB",
    "sg:address":"6 Museum Place",
    "sg:city":"Cardiff",
    "sg:classifiers":[
        {
            "category":"Banks & Credit Unions",
            "subcategory":"Bureau De Change",
            "type":"Services"
        },
        {
            "category":"Park",
            "subcategory":"Town Common",
            "type":"Public Place"
        }
    ],
    "sg:phone":"+44 29 2023 9550",
    "sg:postcode":"CF10 3BG",
    "sg:province":"Cardiff",
    "sg:tags":[
        "consultant",
        "planning",
        "city"
    ],
    "wof:name":"CHAPMAN WARREN",
    "wof:placetype":"venue"
},
  "geometry": {"coordinates":[-3.175689,51.486481],"type":"Point"}
}