{
  "type": "Feature",
  "properties": {
    "addr:full":"48 Broadway London Greater London E15 1NG",
    "addr:housenumber":"48",
    "addr:postcode":"e15 1ng",
    "addr:street":"Broadway",
    "iso:country":"GB",
    "sg:address":"48 Broadway",
    "sg:city":"London",
    "sg:classifiers":[
        {
            "category":"Fast Food",
            "type":"Food & Drink"
        }
    ],
    "sg:phone":"+44 20 8534 1243",
    "sg:postcode":"E15 1NG",
    "sg:province":"Greater London",
    "sg:tags":[
        "away",
        "take"
    ],
    "wof:name":"K F C",
    "wof:placetype":"venue"
},
  "geometry": {"coordinates":[0.00167,51.541313],"type":"Point"}
}