{
  "type": "Feature",
  "properties": {
    "iso:country":"GB",
    "sg:address":"104 Hill Top",
    "sg:city":"West Bromwich",
    "sg:classifiers":[
        {
            "category":"Shopping",
            "subcategory":"Pets & Pet Supplies",
            "type":"Retail Goods"
        }
    ],
    "sg:postcode":"B70 0SH",
    "sg:province":"West Midlands",
    "wof:name":"Capewell,Sheila,",
    "wof:placetype":"venue"
},
  "geometry": {"coordinates":[-2.0118999481,52.538608551],"type":"Point"}
}