{
  "type": "Feature",
  "properties": {
    "iso:country":"GB",
    "sg:address":"39-47 Lichfield Road, Wednesfield",
    "sg:city":"Wolverhampton",
    "sg:classifiers":[
        {
            "category":"Banks & Credit Unions",
            "subcategory":"Bank",
            "type":"Services"
        }
    ],
    "sg:phone":"+44 1902 727331",
    "sg:postcode":"WV11 1TW",
    "sg:province":"Staffordshire",
    "sg:tags":[
        "stocktaking",
        "inventory"
    ],
    "wof:name":"A G Jones",
    "wof:placetype":"venue"
},
  "geometry": {"coordinates":[-2.079928,52.602367],"type":"Point"}
}