{
  "type": "Feature",
  "properties": {
    "addr:full":"53 Fennels Way, Flackwell Heath High Wycombe Buckinghamshire HP10 9BX",
    "addr:housenumber":"53",
    "addr:postcode":"hp10 9bx",
    "addr:street":"Fennels Way",
    "iso:country":"GB",
    "sg:address":"53 Fennels Way, Flackwell Heath",
    "sg:city":"High Wycombe",
    "sg:classifiers":[
        {
            "category":"Building & Trades",
            "subcategory":"Construction",
            "type":"Services"
        }
    ],
    "sg:phone":"+44 1628 527300",
    "sg:postcode":"HP10 9BX",
    "sg:province":"Buckinghamshire",
    "sg:tags":[
        "roofing",
        "contracting"
    ],
    "wof:name":"Apex Roofing",
    "wof:placetype":"venue"
},
  "geometry": {"coordinates":[-0.711078,51.606579],"type":"Point"}
}