{
  "type": "Feature",
  "properties": {
    "addr:full":"71 Dumbarton Road Clydebank East Dunbartonshire G81 1UE",
    "addr:housenumber":"71",
    "addr:postcode":"g81 1ue",
    "addr:street":"Dumbarton Road",
    "iso:country":"GB",
    "sg:address":"71 Dumbarton Road",
    "sg:city":"Clydebank",
    "sg:classifiers":[
        {
            "category":"Professional",
            "subcategory":"Art Services",
            "type":"Services"
        },
        {
            "category":"Building & Trades",
            "subcategory":"Construction",
            "type":"Services"
        }
    ],
    "sg:phone":"+44 141 941 3998",
    "sg:postcode":"G81 1UE",
    "sg:province":"East Dunbartonshire",
    "sg:tags":[
        "decorator",
        "painter"
    ],
    "wof:name":"Jason Sharp",
    "wof:placetype":"venue"
},
  "geometry": {"coordinates":[-4.409215,55.901691],"type":"Point"}
}