{
  "type": "Feature",
  "properties": {
    "iso:country":"GB",
    "sg:address":"Room 72-c, Southampton House, Southampton Road",
    "sg:city":"Hounslow",
    "sg:classifiers":[
        {
            "category":"Freight",
            "type":"Transportation"
        }
    ],
    "sg:postcode":"TW6 3NE",
    "sg:province":"Greater London",
    "sg:tags":[
        "forwarders"
    ],
    "wof:name":"Tokyo Air Cargo (U K) Ltd.",
    "wof:placetype":"venue"
},
  "geometry": {"coordinates":[-0.4617579877,51.4591636658],"type":"Point"}
}