{
  "type": "Feature",
  "properties": {
    "addr:full":"9 Finway Court, Whippendell Rd Watford Hertfordshire WD1 7EN",
    "addr:housenumber":"9",
    "addr:postcode":"wd1 7en",
    "addr:street":"Finway Court Whippendell Rd",
    "iso:country":"GB",
    "sg:address":"9 Finway Court, Whippendell Rd",
    "sg:city":"Watford",
    "sg:classifiers":[
        {
            "category":"Home & Garden",
            "subcategory":"Home Furnishings",
            "type":"Retail Goods"
        }
    ],
    "sg:phone":"+44 1923 800057",
    "sg:postcode":"WD1 7EN",
    "sg:province":"Hertfordshire",
    "sg:tags":[
        "merchant",
        "diy",
        "decorators'"
    ],
    "wof:name":"Crown Brolac Decorator Centre",
    "wof:placetype":"venue"
},
  "geometry": {"coordinates":[-0.390719,51.652119],"type":"Point"}
}