{
  "type": "Feature",
  "properties": {
    "addr:full":"288 High Road, Leyton London Greater London E10 5PW",
    "addr:housenumber":"288",
    "addr:postcode":"e10 5pw",
    "addr:street":"High Road",
    "iso:country":"GB",
    "sg:address":"288 High Road, Leyton",
    "sg:city":"London",
    "sg:classifiers":[
        {
            "category":"Fast Food",
            "type":"Food & Drink"
        }
    ],
    "sg:phone":"+44 20 8558 9561",
    "sg:postcode":"E10 5PW",
    "sg:province":"Greater London",
    "sg:tags":[
        "away",
        "take"
    ],
    "wof:name":"Orient Kebab House",
    "wof:placetype":"venue"
},
  "geometry": {"coordinates":[-0.0091800001,51.5601615906],"type":"Point"}
}