{
  "type": "Feature",
  "properties": {
    "iso:country":"GB",
    "sg:address":"Gateway Ho, Newbury Business Pk",
    "sg:city":"Newbury",
    "sg:classifiers":[
        {
            "category":"Professional",
            "subcategory":"Computer Services",
            "type":"Services"
        }
    ],
    "sg:phone":"+44 1635 524040",
    "sg:postcode":"RG14 2PZ",
    "sg:province":"Berkshire",
    "sg:tags":[
        "system",
        "software"
    ],
    "wof:name":"Digital Equipment Co Ltd",
    "wof:placetype":"venue"
},
  "geometry": {"coordinates":[-1.325872,51.405872],"type":"Point"}
}