{
  "type": "Feature",
  "properties": {
    "iso:country":"GB",
    "sg:address":"3 Belmont Parade, Green Lane",
    "sg:city":"Chislehurst",
    "sg:classifiers":[
        {
            "category":"Food & Beverages",
            "subcategory":"Liquor & Beverages",
            "type":"Retail Goods"
        }
    ],
    "sg:phone":"+44 20 8467 2879",
    "sg:postcode":"BR7 6AN",
    "sg:province":"Kent",
    "sg:tags":[
        "beer",
        "spirit",
        "wines"
    ],
    "wof:name":"Unwins Wine Merchants",
    "wof:placetype":"venue"
},
  "geometry": {"coordinates":[0.0678149983,51.4215660095],"type":"Point"}
}