{
  "type": "Feature",
  "properties": {
    "iso:country":"GB",
    "sg:address":"Ringway House, Bell Rd",
    "sg:city":"Basingstoke",
    "sg:classifiers":[
        {
            "category":"Professional",
            "subcategory":"Management & Consulting",
            "type":"Services"
        }
    ],
    "sg:phone":"+44 1256 338621",
    "sg:postcode":"RG24 8FB",
    "sg:province":"Hampshire",
    "sg:tags":[
        "consultant",
        "business"
    ],
    "wof:name":"EMA Consultancy Group",
    "wof:placetype":"venue"
},
  "geometry": {"coordinates":[-1.0685210228,51.2728996277],"type":"Point"}
}