{
  "type": "Feature",
  "properties": {
    "iso:country":"GB",
    "sg:address":"37 Chalcot Drive",
    "sg:city":"Cannock",
    "sg:classifiers":[
        {
            "category":"Retail",
            "subcategory":"Driving School",
            "type":"Services"
        }
    ],
    "sg:postcode":"WS12 4SF",
    "sg:province":"Staffordshire",
    "wof:name":"A 1 Road Craft",
    "wof:placetype":"venue"
},
  "geometry": {"coordinates":[-2.016438961,52.716960907],"type":"Point"}
}