{
  "type": "Feature",
  "properties": {
    "addr:full":"Somerset Ho, Lyme St Axminster Devon EX13 5AU",
    "addr:postcode":"ex13 5au",
    "addr:street":"St",
    "iso:country":"GB",
    "sg:address":"Somerset Ho, Lyme St",
    "sg:city":"Axminster",
    "sg:classifiers":[
        {
            "category":"Fast Food",
            "type":"Food & Drink"
        }
    ],
    "sg:phone":"+44 1297 35100",
    "sg:postcode":"EX13 5AU",
    "sg:province":"Devon",
    "sg:tags":[
        "away",
        "take"
    ],
    "wof:name":"Rainbow Takeaway",
    "wof:placetype":"venue"
},
  "geometry": {"coordinates":[-3.000562,50.781277],"type":"Point"}
}