{
  "type": "Feature",
  "properties": {
    "addr:full":"25 Antron Way, Mabe Burnthouse Penryn Cornwall TR10 9HS",
    "addr:housenumber":"25",
    "addr:postcode":"tr10 9hs",
    "addr:street":"Antron Way",
    "iso:country":"GB",
    "sg:address":"25 Antron Way, Mabe Burnthouse",
    "sg:city":"Penryn",
    "sg:classifiers":[
        {
            "category":"Autos & Motor Vehicles",
            "subcategory":"Motorcycle Sales",
            "type":"Retail Goods"
        }
    ],
    "sg:phone":"+44 1326 377644",
    "sg:postcode":"TR10 9HS",
    "sg:province":"Cornwall",
    "sg:tags":[
        "chauffeur",
        "driven",
        "car"
    ],
    "wof:name":"Classic Cars",
    "wof:placetype":"venue"
},
  "geometry": {"coordinates":[-5.134113,50.163082],"type":"Point"}
}