{
  "type": "Feature",
  "properties": {
    "iso:country":"GB",
    "sg:address":"Unity House, Smythe Street",
    "sg:city":"Wakefield",
    "sg:classifiers":[
        {
            "category":"Communications",
            "subcategory":"Newspaper",
            "type":"Services"
        },
        {
            "category":"Shopping",
            "subcategory":"News",
            "type":"Retail Goods"
        }
    ],
    "sg:phone":"+44 1977 552956",
    "sg:postcode":"WF1 1ER",
    "sg:province":"West Yorkshire",
    "sg:tags":[
        "magazine",
        "newsagent"
    ],
    "wof:name":"Yorkshire Post Newspapers Ltd.",
    "wof:placetype":"venue"
},
  "geometry": {"coordinates":[-1.5022649765,53.6805839539],"type":"Point"}
}