{
  "type": "Feature",
  "properties": {
    "addr:full":"27 Bridgegate, Howden Goole East Riding of Yorkshire DN14 7AA",
    "addr:housenumber":"27",
    "addr:postcode":"dn14 7aa",
    "addr:street":"Bridgegate",
    "iso:country":"GB",
    "sg:address":"27 Bridgegate, Howden",
    "sg:city":"Goole",
    "sg:classifiers":[
        {
            "category":"Shopping",
            "subcategory":"Pharmacy",
            "type":"Retail Goods"
        }
    ],
    "sg:phone":"+44 1430 430297",
    "sg:postcode":"DN14 7AA",
    "sg:province":"East Riding of Yorkshire",
    "sg:tags":[
        "pharmacist",
        "chemist"
    ],
    "wof:name":"Moss Chemists",
    "wof:placetype":"venue"
},
  "geometry": {"coordinates":[-0.866391,53.746494],"type":"Point"}
}