{
  "type": "Feature",
  "properties": {
    "addr:full":"Straight Road, Battisford Stowmarket Suffolk IP14 2HD",
    "addr:postcode":"ip14 2hd",
    "addr:street":"Straight Road",
    "iso:country":"GB",
    "sg:address":"Straight Road, Battisford",
    "sg:city":"Stowmarket",
    "sg:classifiers":[
        {
            "category":"Government",
            "subcategory":"Post Office",
            "type":"Public Place"
        }
    ],
    "sg:phone":"+44 1449 676731",
    "sg:postcode":"IP14 2HD",
    "sg:province":"Suffolk",
    "wof:name":"R Tolton",
    "wof:placetype":"venue"
},
  "geometry": {"coordinates":[0.9991260171,52.1494407654],"type":"Point"}
}