{
  "type": "Feature",
  "properties": {
    "addr:full":"Dyffryn Rhondda Port Talbot Neath Port Talbot SA13 3HF",
    "addr:postcode":"sa13 3hf",
    "addr:street":"Dyffryn;Port Talbot",
    "iso:country":"GB",
    "sg:address":"Dyffryn Rhondda",
    "sg:city":"Port Talbot",
    "sg:classifiers":[
        {
            "category":"Education",
            "subcategory":"School",
            "type":"Public Place"
        }
    ],
    "sg:phone":"+44 1639 850342",
    "sg:postcode":"SA13 3HF",
    "sg:province":"Neath Port Talbot",
    "sg:tags":[
        "local",
        "authority"
    ],
    "wof:name":"Duffryn Afan Primary School",
    "wof:placetype":"venue"
},
  "geometry": {"coordinates":[-3.68939,51.64735],"type":"Point"}
}