{
  "type": "Feature",
  "properties": {
    "addr:full":"Garstang Road, Broughton Preston Lancashire PR3 5JE",
    "addr:postcode":"pr3 5je",
    "addr:street":"Garstang Road",
    "iso:country":"GB",
    "sg:address":"Garstang Road, Broughton",
    "sg:city":"Preston",
    "sg:classifiers":[
        {
            "category":"Arena",
            "subcategory":"Sports Club",
            "type":"Entertainment"
        }
    ],
    "sg:phone":"+44 1772 863003",
    "sg:postcode":"PR3 5JE",
    "sg:province":"Lancashire",
    "wof:name":"Fulwood & Broughton Cricket Club",
    "wof:placetype":"venue"
},
  "geometry": {"coordinates":[-2.745216,53.847904],"type":"Point"}
}