{
  "type": "Feature",
  "properties": {
    "iso:country":"GB",
    "sg:address":"1a Seddon Place, Stanley",
    "sg:city":"Skelmersdale",
    "sg:classifiers":[
        {
            "category":"Professional",
            "subcategory":"Printing & Photocopies",
            "type":"Services"
        }
    ],
    "sg:phone":"+44 1695 50460",
    "sg:postcode":"WN8 8EB",
    "sg:province":"Lancashire",
    "sg:tags":[
        "printer"
    ],
    "wof:name":"Chesil Design & Print",
    "wof:placetype":"venue"
},
  "geometry": {"coordinates":[-2.8003730774,53.5590362549],"type":"Point"}
}