{
  "type": "Feature",
  "properties": {
    "iso:country":"GB",
    "sg:address":"Edward St",
    "sg:city":"Norwich",
    "sg:classifiers":[
        {
            "category":"Personal",
            "type":"Services"
        }
    ],
    "sg:phone":"+44 1603 441166",
    "sg:postcode":"NR3 3DD",
    "sg:province":"Norfolk",
    "sg:tags":[
        "delivery"
    ],
    "wof:name":"Taxi Van",
    "wof:placetype":"venue"
},
  "geometry": {"coordinates":[1.2942990065,52.6377906799],"type":"Point"}
}