{
  "type": "Feature",
  "properties": {
    "addr:full":"Unit 8 Corporation Road Industrial E, St Birkenhead Merseyside CH41 9HH",
    "addr:housenumber":"unit 8",
    "addr:postcode":"ch41 9hh",
    "addr:street":"Corporation Road Industrial E St",
    "iso:country":"GB",
    "sg:address":"Unit 8 Corporation Road Industrial E, St",
    "sg:city":"Birkenhead",
    "sg:classifiers":[
        {
            "category":"Professional",
            "subcategory":"Engineering",
            "type":"Services"
        }
    ],
    "sg:phone":"+44 151 653 7677",
    "sg:postcode":"CH41 9HH",
    "sg:province":"Merseyside",
    "wof:name":"Hemmings & Cook",
    "wof:placetype":"venue"
},
  "geometry": {"coordinates":[-3.0407109261,53.4015464783],"type":"Point"}
}