{
  "type": "Feature",
  "properties": {
    "iso:country":"GB",
    "sg:address":"25 Shrubbery Road, Streatham",
    "sg:city":"London",
    "sg:classifiers":[
        {
            "category":"Shopping",
            "subcategory":"Antiques",
            "type":"Retail Goods"
        }
    ],
    "sg:phone":"+44 20 7359 4073",
    "sg:postcode":"SW16 2AS",
    "sg:province":"Greater London",
    "wof:name":"Rapscallion Ltd.",
    "wof:placetype":"venue"
},
  "geometry": {"coordinates":[-0.1284350008,51.4301872253],"type":"Point"}
}