{
  "type": "Feature",
  "properties": {
    "addr:full":"2 Tunnicliffe Pl Keighley North Yorkshire BD20 0DH",
    "addr:housenumber":"2",
    "addr:postcode":"bd20 0dh",
    "addr:street":"Tunnicliffe Pl",
    "iso:country":"GB",
    "sg:address":"2 Tunnicliffe Pl",
    "sg:city":"Keighley",
    "sg:classifiers":[
        {
            "category":"Retail",
            "subcategory":"Repair Shop",
            "type":"Services"
        }
    ],
    "sg:phone":"+44 1535 654704",
    "sg:postcode":"BD20 0DH",
    "sg:province":"North Yorkshire",
    "sg:tags":[
        "clocks",
        "watch"
    ],
    "wof:name":"H & B Bancroft",
    "wof:placetype":"venue"
},
  "geometry": {"coordinates":[-1.9421930313,53.9118118286],"type":"Point"}
}