{
  "type": "Feature",
  "properties": {
    "iso:country":"GB",
    "sg:address":"39 The Gro",
    "sg:city":"Southend-on-sea",
    "sg:classifiers":[
        {
            "category":"Government",
            "subcategory":"Post Office",
            "type":"Public Place"
        }
    ],
    "sg:phone":"+44 1702 530035",
    "sg:postcode":"SS2 4DD",
    "sg:province":"Essex",
    "sg:tags":[
        "messenger",
        "courier"
    ],
    "wof:name":"Julian Courier Services",
    "wof:placetype":"venue"
},
  "geometry": {"coordinates":[0.725656,51.545483],"type":"Point"}
}