{
  "type": "Feature",
  "properties": {
    "iso:country":"GB",
    "sg:address":"14 Dudley Road, Honeybourne",
    "sg:city":"Evesham",
    "sg:classifiers":[
        {
            "category":"Professional",
            "subcategory":"Engineering",
            "type":"Services"
        }
    ],
    "sg:postcode":"WR11 7XP",
    "sg:province":"Gloucestershire",
    "sg:tags":[
        "contractor",
        "electrical",
        "engineer"
    ],
    "wof:name":"R Charles Electrical",
    "wof:placetype":"venue"
},
  "geometry": {"coordinates":[-1.8301850557,52.0984535217],"type":"Point"}
}