{
  "type": "Feature",
  "properties": {
    "addr:full":"520 Seaside Eastbourne East Sussex BN23 6NJ",
    "addr:housenumber":"520",
    "addr:postcode":"bn23 6nj",
    "addr:street":"Seaside",
    "iso:country":"GB",
    "sg:address":"520 Seaside",
    "sg:city":"Eastbourne",
    "sg:classifiers":[
        {
            "category":"Autos & Motor Vehicles",
            "subcategory":"Fuel & Gas Station",
            "type":"Retail Goods"
        }
    ],
    "sg:postcode":"BN23 6NJ",
    "sg:province":"East Sussex",
    "sg:tags":[
        "hr",
        "petrol"
    ],
    "wof:name":"Seaside Service Station",
    "wof:placetype":"venue"
},
  "geometry": {"coordinates":[0.3097150028,50.7892723083],"type":"Point"}
}