{
  "type": "Feature",
  "properties": {
    "iso:country":"GB",
    "sg:address":"10 Aylstone Clo",
    "sg:city":"Stratford Upon Avon",
    "sg:classifiers":[
        {
            "category":"Home & Garden",
            "subcategory":"Household Appliances",
            "type":"Retail Goods"
        }
    ],
    "sg:phone":"+44 1789 720432",
    "sg:postcode":"CV37 8TE",
    "sg:province":"Warwickshire",
    "sg:tags":[
        "electrical"
    ],
    "wof:name":"Mark English Domestic Appliance Services",
    "wof:placetype":"venue"
},
  "geometry": {"coordinates":[-1.741127,52.123066],"type":"Point"}
}