{
  "type": "Feature",
  "properties": {
    "iso:country":"GB",
    "sg:address":"Elstree Film Studios, Elstree",
    "sg:city":"Watford",
    "sg:classifiers":[
        {
            "category":"Shopping",
            "subcategory":"Computers & Home Electronics",
            "type":"Retail Goods"
        }
    ],
    "sg:phone":"+44 20 8324 2726",
    "sg:postcode":"WD6 1JG",
    "sg:province":"Hertfordshire",
    "sg:tags":[
        "equipment",
        "audio-visual"
    ],
    "wof:name":"Everything Audio Ltd.",
    "wof:placetype":"venue"
},
  "geometry": {"coordinates":[-0.26791,51.661812],"type":"Point"}
}