{
  "type": "Feature",
  "properties": {
    "iso:country":"GB",
    "sg:address":"3 The Crescent, Edlington",
    "sg:city":"Doncaster",
    "sg:classifiers":[
        {
            "category":"Retail",
            "subcategory":"Funeral Services",
            "type":"Services"
        }
    ],
    "sg:phone":"+44 1302 841679",
    "sg:postcode":"DN12 1AJ",
    "sg:province":"South Yorkshire",
    "sg:tags":[
        "director"
    ],
    "wof:name":"Charles Carpenter Funeral Services",
    "wof:placetype":"venue"
},
  "geometry": {"coordinates":[-1.1888730526,53.485458374],"type":"Point"}
}