{
  "type": "Feature",
  "properties": {
    "addr:full":"168 Station Road Harpenden Hertfordshire AL5 4RH",
    "addr:housenumber":"168",
    "addr:postcode":"al5 4rh",
    "addr:street":"Station Road",
    "iso:country":"GB",
    "sg:address":"168 Station Road",
    "sg:city":"Harpenden",
    "sg:classifiers":[
        {
            "category":"Professional",
            "subcategory":"Management & Consulting",
            "type":"Services"
        }
    ],
    "sg:phone":"+44 1582 764125",
    "sg:postcode":"AL5 4RH",
    "sg:province":"Hertfordshire",
    "sg:tags":[
        "consultant",
        "business",
        "marketing"
    ],
    "wof:name":"A N D Media",
    "wof:placetype":"venue"
},
  "geometry": {"coordinates":[-0.3402960002,51.8208503723],"type":"Point"}
}