{
  "type": "Feature",
  "properties": {
    "iso:country":"GB",
    "sg:address":"Unit 6 Barshaw Park, Leycroft Road",
    "sg:city":"Leicester",
    "sg:classifiers":[
        {
            "category":"Professional",
            "subcategory":"Detective & Security Services",
            "type":"Services"
        }
    ],
    "sg:phone":"+44 116 236 3599",
    "sg:postcode":"LE4 1ET",
    "sg:province":"Leicestershire",
    "wof:name":"Securicor Security Ltd.",
    "wof:placetype":"venue"
},
  "geometry": {"coordinates":[-1.1580699682,52.6698493958],"type":"Point"}
}