{
  "type": "Feature",
  "properties": {
    "iso:country":"GB",
    "sg:address":"54 Burford Lane",
    "sg:city":"Lymm",
    "sg:classifiers":[
        {
            "category":"Building & Trades",
            "subcategory":"Landscaping Services",
            "type":"Services"
        }
    ],
    "sg:phone":"+44 1925 752046",
    "sg:postcode":"WA13 0SH",
    "sg:province":"Cheshire",
    "sg:tags":[
        "landscape",
        "contractor"
    ],
    "wof:name":"Broomedge Nurseries Ltd.",
    "wof:placetype":"venue"
},
  "geometry": {"coordinates":[-2.4458498955,53.3731422424],"type":"Point"}
}