{
  "type": "Feature",
  "properties": {
    "addr:full":"199 Monument Road, Edgbaston Birmingham West Midlands B16 8UU",
    "addr:housenumber":"199",
    "addr:postcode":"b16 8uu",
    "addr:street":"Monument Road",
    "iso:country":"GB",
    "sg:address":"199 Monument Road, Edgbaston",
    "sg:city":"Birmingham",
    "sg:classifiers":[
        {
            "category":"Shopping",
            "subcategory":"Pharmacy",
            "type":"Retail Goods"
        }
    ],
    "sg:phone":"+44 121 454 1120",
    "sg:postcode":"B16 8UU",
    "sg:province":"West Midlands",
    "sg:tags":[
        "pharmacist",
        "dispensing",
        "chemist"
    ],
    "wof:name":"Noor Pharmacy Ltd.",
    "wof:placetype":"venue"
},
  "geometry": {"coordinates":[-1.9308309555,52.4729576111],"type":"Point"}
}