{
  "type": "Feature",
  "properties": {
    "addr:full":"17 The Lawns Hinckley Leicestershire LE10 1DY",
    "addr:housenumber":"17",
    "addr:postcode":"le10 1dy",
    "addr:street":"The Lawns",
    "iso:country":"GB",
    "sg:address":"17 The Lawns",
    "sg:city":"Hinckley",
    "sg:classifiers":[
        {
            "category":"Shopping",
            "subcategory":"Bicycles & Sporting Goods",
            "type":"Retail Goods"
        },
        {
            "category":"Arts & Performance",
            "subcategory":"Theater",
            "type":"Entertainment"
        }
    ],
    "sg:phone":"+44 1455 615533",
    "sg:postcode":"LE10 1DY",
    "sg:province":"Leicestershire",
    "sg:tags":[
        "dance",
        "dancewear",
        "ballet",
        "balletwear"
    ],
    "wof:name":"Chorus Line Dancewear",
    "wof:placetype":"venue"
},
  "geometry": {"coordinates":[-1.366251,52.541214],"type":"Point"}
}