{
  "type": "Feature",
  "properties": {
    "iso:country":"GB",
    "sg:address":"Highlands, Wooden House Lane",
    "sg:city":"Lymington",
    "sg:classifiers":[
        {
            "category":"Professional",
            "subcategory":"Accounting & Tax Preparation",
            "type":"Services"
        }
    ],
    "sg:postcode":"SO41 5QU",
    "sg:province":"Hampshire",
    "sg:tags":[
        "accountant"
    ],
    "wof:name":"P L Moore",
    "wof:placetype":"venue"
},
  "geometry": {"coordinates":[-1.5236669779,50.7865867615],"type":"Point"}
}