{
  "type": "Feature",
  "properties": {
    "addr:full":"Elms Farm, Elm Lane, Roxwell Chelmsford Essex CM1 4NJ",
    "addr:postcode":"cm1 4nj",
    "addr:street":"Elm Lane",
    "iso:country":"GB",
    "sg:address":"Elms Farm, Elm Lane, Roxwell",
    "sg:city":"Chelmsford",
    "sg:classifiers":[
        {
            "category":"Farming",
            "subcategory":"Crops",
            "type":"Manufacturing & Wholesale Goods"
        },
        {
            "category":"Farming",
            "subcategory":"Livestock Farm",
            "type":"Manufacturing & Wholesale Goods"
        }
    ],
    "sg:phone":"+44 1245 248212",
    "sg:postcode":"CM1 4NJ",
    "sg:province":"Essex",
    "sg:tags":[
        "arable",
        "others"
    ],
    "wof:name":"A & B Emery",
    "wof:placetype":"venue"
},
  "geometry": {"coordinates":[0.378684,51.751102],"type":"Point"}
}