{
  "type": "Feature",
  "properties": {
    "addr:full":"Unit 2 Phoenix House, South Avenue, Clydebank Business Park Clydebank East Dunbartonshire G81 2LG",
    "addr:housenumber":"unit 2",
    "addr:postcode":"g81 2lg",
    "addr:street":"House South Avenue Clydebank Business Park Clydebank",
    "iso:country":"GB",
    "sg:address":"Unit 2 Phoenix House, South Avenue, Clydebank Business Park",
    "sg:city":"Clydebank",
    "sg:classifiers":[
        {
            "category":"Wholesale",
            "subcategory":"Vending Machines",
            "type":"Manufacturing & Wholesale Goods"
        }
    ],
    "sg:phone":"+44 870 600 2030",
    "sg:postcode":"G81 2LG",
    "sg:province":"East Dunbartonshire",
    "sg:tags":[
        "sale"
    ],
    "wof:name":"Klix Drinks",
    "wof:placetype":"venue"
},
  "geometry": {"coordinates":[-4.4138407707,55.9065589905],"type":"Point"}
}