{
  "type": "Feature",
  "properties": {
    "iso:country":"GB",
    "sg:address":"Park La",
    "sg:city":"West End",
    "sg:classifiers":[
        {
            "category":"Retail",
            "subcategory":"Event Space",
            "type":"Services"
        }
    ],
    "sg:phone":"+44 20 7499 6555",
    "sg:postcode":"W1V 9FE",
    "sg:province":"Hampshire",
    "sg:tags":[
        "banqueting",
        "room"
    ],
    "wof:name":"Six Hamilton Place",
    "wof:placetype":"venue"
},
  "geometry": {"coordinates":[-0.150603,51.505428],"type":"Point"}
}