{
  "type": "Feature",
  "properties": {
    "iso:country":"GB",
    "sg:address":"3 Gillinggate",
    "sg:city":"Kendal",
    "sg:classifiers":[
        {
            "category":"Education",
            "subcategory":"Music School",
            "type":"Public Place"
        }
    ],
    "sg:phone":"+44 1539 730849",
    "sg:postcode":"LA9 4JE",
    "sg:province":"Cumbria",
    "wof:name":"Lancaster Stagecoach Theatre Arts",
    "wof:placetype":"venue"
},
  "geometry": {"coordinates":[-2.748931,54.323204],"type":"Point"}
}