{
  "type": "Feature",
  "properties": {
    "addr:full":"2 Bridle Close Kingston-upon-thames Greater London KT1 2JW",
    "addr:housenumber":"2",
    "addr:postcode":"kingston-upon-thames;kt1 2jw",
    "addr:street":"Bridle Close",
    "iso:country":"GB",
    "sg:address":"2 Bridle Close",
    "sg:city":"Kingston-upon-thames",
    "sg:classifiers":[
        {
            "category":"Professional",
            "subcategory":"Detective & Security Services",
            "type":"Services"
        }
    ],
    "sg:phone":"+44 20 8541 4725",
    "sg:postcode":"KT1 2JW",
    "sg:province":"Greater London",
    "sg:tags":[
        "alarm",
        "burglar",
        "system"
    ],
    "wof:name":"Knighthood Security Systems Ltd.",
    "wof:placetype":"venue"
},
  "geometry": {"coordinates":[-0.305419,51.401997],"type":"Point"}
}