{
  "type": "Feature",
  "properties": {
    "iso:country":"GB",
    "sg:address":"81 Shepherd Cross Street",
    "sg:city":"Bolton",
    "sg:classifiers":[
        {
            "category":"Bus Charters",
            "type":"Transportation"
        }
    ],
    "sg:phone":"+44 1204 844992",
    "sg:postcode":"BL1 3BX",
    "sg:province":"Lancashire",
    "sg:tags":[
        "coach"
    ],
    "wof:name":"R Calderley",
    "wof:placetype":"venue"
},
  "geometry": {"coordinates":[-2.448635,53.588074],"type":"Point"}
}