{
  "type": "Feature",
  "properties": {
    "addr:full":"Naid House, 126 Potter St Harlow Essex CM17 9AW",
    "addr:housenumber":"126",
    "addr:postcode":"cm17 9aw",
    "addr:street":"Potter St",
    "iso:country":"GB",
    "sg:address":"Naid House, 126 Potter St",
    "sg:city":"Harlow",
    "sg:classifiers":[
        {
            "category":"Communications",
            "type":"Services"
        }
    ],
    "sg:phone":"+44 1279 424284",
    "sg:postcode":"CM17 9AW",
    "sg:province":"Essex",
    "sg:tags":[
        "data",
        "network"
    ],
    "wof:name":"National Association for Information Destruction",
    "wof:placetype":"venue"
},
  "geometry": {"coordinates":[0.1331200004,51.7567024231],"type":"Point"}
}