{
  "type": "Feature",
  "properties": {
    "addr:full":"Belinda Street Leeds West Yorkshire LS10 2PS",
    "addr:postcode":"ls10 2ps",
    "addr:street":"Belinda Street",
    "iso:country":"GB",
    "sg:address":"Belinda Street",
    "sg:city":"Leeds",
    "sg:classifiers":[
        {
            "category":"Education",
            "subcategory":"School",
            "type":"Public Place"
        }
    ],
    "sg:phone":"+44 113 214 1704",
    "sg:postcode":"LS10 2PS",
    "sg:province":"West Yorkshire",
    "sg:tags":[
        "local",
        "authority"
    ],
    "wof:name":"Low Road Primary School",
    "wof:placetype":"venue"
},
  "geometry": {"coordinates":[-1.5258079767,53.77917099],"type":"Point"}
}