{
  "type": "Feature",
  "properties": {
    "iso:country":"GB",
    "sg:address":"93a Bancroft",
    "sg:city":"Hitchin",
    "sg:classifiers":[
        {
            "category":"Professional",
            "subcategory":"Printing & Photocopies",
            "type":"Services"
        }
    ],
    "sg:phone":"+44 1462 459250",
    "sg:postcode":"SG5 1NQ",
    "sg:province":"Bedfordshire",
    "sg:tags":[
        "printer"
    ],
    "wof:name":"Clearprint",
    "wof:placetype":"venue"
},
  "geometry": {"coordinates":[-0.2763540149,51.9508972168],"type":"Point"}
}