{
  "type": "Feature",
  "properties": {
    "addr:full":"4 Taylor Hall Lane Mirfield West Yorkshire WF14 0HW",
    "addr:housenumber":"4",
    "addr:postcode":"wf14 0hw",
    "addr:street":"Taylor Hall Lane",
    "iso:country":"GB",
    "sg:address":"4 Taylor Hall Lane",
    "sg:city":"Mirfield",
    "sg:classifiers":[
        {
            "category":"Health Services",
            "subcategory":"Dentist",
            "type":"Services"
        }
    ],
    "sg:postcode":"WF14 0HW",
    "sg:province":"West Yorkshire",
    "wof:name":"Dental Care Centre",
    "wof:placetype":"venue"
},
  "geometry": {"coordinates":[-1.6962820292,53.6865692139],"type":"Point"}
}