{
  "type": "Feature",
  "properties": {
    "iso:country":"GB",
    "sg:address":"28-30 Station Road, Rearsby",
    "sg:city":"Leicester",
    "sg:classifiers":[
        {
            "category":"Building & Trades",
            "subcategory":"Construction",
            "type":"Services"
        }
    ],
    "sg:postcode":"LE7 4YY",
    "sg:province":"Leicestershire",
    "sg:tags":[
        "decorator",
        "painter"
    ],
    "wof:name":"Samuel Laurence Mason",
    "wof:placetype":"venue"
},
  "geometry": {"coordinates":[-1.038009,52.722694],"type":"Point"}
}