{
  "type": "Feature",
  "properties": {
    "addr:full":"285 Southmead Road, Westbury-on-trym Bristol City of Bristol BS10 5EL",
    "addr:housenumber":"285",
    "addr:postcode":"bs10 5el",
    "addr:street":"Southmead Road",
    "iso:country":"GB",
    "sg:address":"285 Southmead Road, Westbury-on-trym",
    "sg:city":"Bristol",
    "sg:classifiers":[
        {
            "category":"Bars & Pubs",
            "type":"Food & Drink"
        }
    ],
    "sg:phone":"+44 117 950 0435",
    "sg:postcode":"BS10 5EL",
    "sg:province":"City of Bristol",
    "sg:tags":[
        "pubs",
        "inn"
    ],
    "wof:name":"The Bear & Rugged Staff",
    "wof:placetype":"venue"
},
  "geometry": {"coordinates":[-2.5947830677,51.4988708496],"type":"Point"}
}