{
  "type": "Feature",
  "properties": {
    "addr:full":"367 Rosliston Road Burton-on-trent Derbyshire DE15 9RJ",
    "addr:housenumber":"367",
    "addr:postcode":"de15 9rj",
    "addr:street":"Rosliston Road",
    "iso:country":"GB",
    "sg:address":"367 Rosliston Road",
    "sg:city":"Burton-on-trent",
    "sg:classifiers":[
        {
            "category":"Shopping",
            "subcategory":"Department Store",
            "type":"Retail Goods"
        }
    ],
    "sg:phone":"+44 1283 563133",
    "sg:postcode":"DE15 9RJ",
    "sg:province":"Derbyshire",
    "wof:name":"Kotecha Off Licence",
    "wof:placetype":"venue"
},
  "geometry": {"coordinates":[-1.623253,52.790386],"type":"Point"}
}