{
  "type": "Feature",
  "properties": {
    "iso:country":"GB",
    "sg:address":"Blairmore Centre, Blairmore Road",
    "sg:city":"Greenock",
    "sg:classifiers":[
        {
            "category":"Education",
            "subcategory":"University",
            "type":"Public Place"
        }
    ],
    "sg:phone":"+44 1475 791650",
    "sg:postcode":"PA15 3JT",
    "sg:province":"Inverclyde",
    "sg:tags":[
        "adult"
    ],
    "wof:name":"Second Chance Learning",
    "wof:placetype":"venue"
},
  "geometry": {"coordinates":[-4.741619,55.93317],"type":"Point"}
}