{
  "type": "Feature",
  "properties": {
    "addr:full":"72 Pikes Lane Glossop Derbyshire SK13 8ED",
    "addr:housenumber":"72",
    "addr:postcode":"sk13 8ed",
    "addr:street":"Pikes Lane",
    "iso:country":"GB",
    "sg:address":"72 Pikes Lane",
    "sg:city":"Glossop",
    "sg:classifiers":[
        {
            "category":"Building & Trades",
            "subcategory":"Construction",
            "type":"Services"
        }
    ],
    "sg:postcode":"SK13 8ED",
    "sg:province":"Derbyshire",
    "sg:tags":[
        "roofing"
    ],
    "wof:name":"J P M Roofing & Ventilation",
    "wof:placetype":"venue"
},
  "geometry": {"coordinates":[-1.958327055,53.4408493042],"type":"Point"}
}