{
  "type": "Feature",
  "properties": {
    "iso:country":"GB",
    "sg:address":"Pengwern Farm, Llethryd",
    "sg:city":"Swansea",
    "sg:classifiers":[
        {
            "category":"Farming",
            "subcategory":"Livestock Farm",
            "type":"Manufacturing & Wholesale Goods"
        }
    ],
    "sg:postcode":"SA2 7LH",
    "sg:province":"Swansea",
    "sg:tags":[
        "others"
    ],
    "wof:name":"E Y Jones",
    "wof:placetype":"venue"
},
  "geometry": {"coordinates":[-4.1220998764,51.6025390625],"type":"Point"}
}