{
  "type": "Feature",
  "properties": {
    "iso:country":"GB",
    "sg:address":"7 Alder Mead Close, Admaston",
    "sg:city":"Telford",
    "sg:classifiers":[
        {
            "category":"Building & Trades",
            "subcategory":"Construction",
            "type":"Services"
        }
    ],
    "sg:phone":"+44 1952 256196",
    "sg:postcode":"TF5 0DD",
    "sg:province":"Shropshire",
    "sg:tags":[
        "builder"
    ],
    "wof:name":"Shire Homes",
    "wof:placetype":"venue"
},
  "geometry": {"coordinates":[-2.5423190594,52.7158660889],"type":"Point"}
}