{
  "type": "Feature",
  "properties": {
    "addr:full":"The Pharmacy, High Street Moreton In Marsh Gloucestershire GL56 0AL",
    "addr:postcode":"gl56 0al",
    "addr:street":"High Street",
    "iso:country":"GB",
    "sg:address":"The Pharmacy, High Street",
    "sg:city":"Moreton In Marsh",
    "sg:classifiers":[
        {
            "category":"Personal",
            "subcategory":"Beauty Salon",
            "type":"Services"
        }
    ],
    "sg:phone":"+44 1608 652520",
    "sg:postcode":"GL56 0AL",
    "sg:province":"Gloucestershire",
    "wof:name":"Claire's Beauty & Body Clinic",
    "wof:placetype":"venue"
},
  "geometry": {"coordinates":[-1.703281045,51.9897270203],"type":"Point"}
}