{
  "type": "Feature",
  "properties": {
    "iso:country":"GB",
    "sg:address":"6 Argent Way",
    "sg:city":"Bradford",
    "sg:classifiers":[
        {
            "category":"Bus Charters",
            "type":"Transportation"
        }
    ],
    "sg:phone":"+44 1274 651157",
    "sg:postcode":"BD4 0LW",
    "sg:province":"West Yorkshire",
    "sg:tags":[
        "hire",
        "coach"
    ],
    "wof:name":"E & T Travel",
    "wof:placetype":"venue"
},
  "geometry": {"coordinates":[-1.702702,53.771942],"type":"Point"}
}