{
  "type": "Feature",
  "properties": {
    "addr:full":"5 Station Road Redcar North Yorkshire TS10 1AH",
    "addr:housenumber":"5",
    "addr:postcode":"ts10 1ah",
    "addr:street":"Station Road",
    "iso:country":"GB",
    "sg:address":"5 Station Road",
    "sg:city":"Redcar",
    "sg:classifiers":[
        {
            "category":"Shopping",
            "subcategory":"Books",
            "type":"Retail Goods"
        }
    ],
    "sg:postcode":"TS10 1AH",
    "sg:province":"North Yorkshire",
    "sg:tags":[
        "bookseller"
    ],
    "wof:name":"Books and Magazines",
    "wof:placetype":"venue"
},
  "geometry": {"coordinates":[-1.069964,54.619892],"type":"Point"}
}