{
  "type": "Feature",
  "properties": {
    "iso:country":"GB",
    "sg:address":"Flat 4 Mount Ash, Litchard",
    "sg:city":"Bridgend",
    "sg:classifiers":[
        {
            "category":"Building & Trades",
            "subcategory":"Construction",
            "type":"Services"
        }
    ],
    "sg:phone":"+44 1656 657983",
    "sg:postcode":"CF31 1RD",
    "sg:province":"Bridgend",
    "sg:tags":[
        "builder"
    ],
    "wof:name":"Rees Builders",
    "wof:placetype":"venue"
},
  "geometry": {"coordinates":[-3.578263,51.508835],"type":"Point"}
}