{
  "type": "Feature",
  "properties": {
    "iso:country":"GB",
    "sg:address":"Alma Park Road",
    "sg:city":"Grantham",
    "sg:classifiers":[
        {
            "category":"Building & Trades",
            "subcategory":"Construction",
            "type":"Services"
        }
    ],
    "sg:phone":"+44 1476 573578",
    "sg:postcode":"NG31 9SE",
    "sg:province":"Lincolnshire",
    "sg:tags":[
        "roofing"
    ],
    "wof:name":"Universal Roofing Ltd.",
    "wof:placetype":"venue"
},
  "geometry": {"coordinates":[-0.6053640246,52.9255409241],"type":"Point"}
}