{
  "type": "Feature",
  "properties": {
    "addr:full":"13-15 Lawson Way Middlesbrough North Yorkshire TS3 6LN",
    "addr:housenumber":"13-15",
    "addr:postcode":"ts3 6ln",
    "addr:street":"Lawson Way",
    "iso:country":"GB",
    "sg:address":"13-15 Lawson Way",
    "sg:city":"Middlesbrough",
    "sg:classifiers":[
        {
            "category":"Manufacturing",
            "subcategory":"Metals",
            "type":"Manufacturing & Wholesale Goods"
        }
    ],
    "sg:phone":"+44 1642 244422",
    "sg:postcode":"TS3 6LN",
    "sg:province":"North Yorkshire",
    "sg:tags":[
        "steel",
        "stockholder"
    ],
    "wof:name":"Anchor Metals Ltd.",
    "wof:placetype":"venue"
},
  "geometry": {"coordinates":[-1.206968,54.573811],"type":"Point"}
}