{
  "type": "Feature",
  "properties": {
    "addr:full":"1 Roseburn Terrace Edinburgh City of Edinburgh EH12 5NG",
    "addr:housenumber":"1",
    "addr:postcode":"eh12 5ng",
    "addr:street":"Roseburn Terrace",
    "iso:country":"GB",
    "sg:address":"1 Roseburn Terrace",
    "sg:city":"Edinburgh",
    "sg:classifiers":[
        {
            "category":"Bars & Pubs",
            "type":"Food & Drink"
        }
    ],
    "sg:phone":"+44 131 337 1067",
    "sg:postcode":"EH12 5NG",
    "sg:province":"City of Edinburgh",
    "sg:tags":[
        "pubs",
        "inn"
    ],
    "wof:name":"Roseburn Bar",
    "wof:placetype":"venue"
},
  "geometry": {"coordinates":[-3.2345600128,55.9449234009],"type":"Point"}
}