{
  "type": "Feature",
  "properties": {
    "iso:country":"GB",
    "sg:address":"Armstrong Scarborough & Partners, Sovereign House, 12 Warwick Street",
    "sg:city":"Coventry",
    "sg:classifiers":[
        {
            "category":"Retail",
            "subcategory":"Auto Repair",
            "type":"Services"
        }
    ],
    "sg:postcode":"CV5 6ET",
    "sg:province":"West Midlands",
    "sg:tags":[
        "body",
        "car"
    ],
    "wof:name":"Bj Accident Repair Centre Ltd",
    "wof:placetype":"venue"
},
  "geometry": {"coordinates":[-1.5332130194,52.3992881775],"type":"Point"}
}