{
  "type": "Feature",
  "properties": {
    "addr:full":"56 Bramingham Road Luton Bedfordshire LU3 2SW",
    "addr:housenumber":"56",
    "addr:postcode":"lu3 2sw",
    "addr:street":"Bramingham Road",
    "iso:country":"GB",
    "sg:address":"56 Bramingham Road",
    "sg:city":"Luton",
    "sg:classifiers":[
        {
            "category":"Professional",
            "subcategory":"Engineering",
            "type":"Services"
        }
    ],
    "sg:phone":"+44 1582 490626",
    "sg:postcode":"LU3 2SW",
    "sg:province":"Bedfordshire",
    "sg:tags":[
        "civil",
        "engineer"
    ],
    "wof:name":"P L J Groundworks Ltd.",
    "wof:placetype":"venue"
},
  "geometry": {"coordinates":[-0.4548000097,51.908946991],"type":"Point"}
}