{
  "type": "Feature",
  "properties": {
    "addr:full":"45-46 Charlotte Road London Greater London EC2A 3PD",
    "addr:housenumber":"45-46",
    "addr:postcode":"ec2a 3pd",
    "addr:street":"Charlotte Road",
    "iso:country":"GB",
    "sg:address":"45-46 Charlotte Road",
    "sg:city":"London",
    "sg:classifiers":[
        {
            "category":"Professional",
            "subcategory":"Art Services",
            "type":"Services"
        }
    ],
    "sg:phone":"+44 20 7739 3658",
    "sg:postcode":"EC2A 3PD",
    "sg:province":"Greater London",
    "sg:tags":[
        "graphic",
        "designer"
    ],
    "wof:name":"Nineth Planet",
    "wof:placetype":"venue"
},
  "geometry": {"coordinates":[-0.080891,51.52533],"type":"Point"}
}