{
  "type": "Feature",
  "properties": {
    "iso:country":"GB",
    "sg:address":"26 Steventon Crescent",
    "sg:city":"Ludlow",
    "sg:classifiers":[
        {
            "category":"Arts & Performance",
            "subcategory":"Music",
            "type":"Entertainment"
        }
    ],
    "sg:phone":"+44 1584 877886",
    "sg:postcode":"SY8 1JS",
    "sg:province":"Herefordshire",
    "sg:tags":[
        "mobile",
        "disco"
    ],
    "wof:name":"A Touch of Class",
    "wof:placetype":"venue"
},
  "geometry": {"coordinates":[-2.704944,52.364929],"type":"Point"}
}