{
  "type": "Feature",
  "properties": {
    "addr:full":"78 Southgate Street Gloucester Gloucestershire GL1 2DX",
    "addr:housenumber":"78",
    "addr:postcode":"gl1 2dx",
    "addr:street":"Southgate Street",
    "iso:country":"GB",
    "sg:address":"78 Southgate Street",
    "sg:city":"Gloucester",
    "sg:classifiers":[
        {
            "category":"Shopping",
            "subcategory":"Mobile Phones",
            "type":"Retail Goods"
        },
        {
            "category":"Communications",
            "type":"Services"
        }
    ],
    "sg:phone":"+44 1452 309309",
    "sg:postcode":"GL1 2DX",
    "sg:province":"Gloucestershire",
    "sg:tags":[
        "telecommunication"
    ],
    "wof:name":"Cell Phones Direct",
    "wof:placetype":"venue"
},
  "geometry": {"coordinates":[-2.248391,51.863529],"type":"Point"}
}