{
  "type": "Feature",
  "properties": {
    "iso:country":"GB",
    "sg:address":"20 Chamberlain Street",
    "sg:city":"Wells",
    "sg:classifiers":[
        {
            "category":"Banks & Credit Unions",
            "subcategory":"Financial Services",
            "type":"Services"
        }
    ],
    "sg:postcode":"BA5 2PF",
    "sg:province":"Somerset",
    "sg:tags":[
        "adviser"
    ],
    "wof:name":"A Wills & Co. Ltd.",
    "wof:placetype":"venue"
},
  "geometry": {"coordinates":[-2.648456,51.21006],"type":"Point"}
}