{
  "type": "Feature",
  "properties": {
    "iso:country":"GB",
    "sg:address":"79 Brook Street",
    "sg:city":"Grantham",
    "sg:classifiers":[
        {
            "category":"Bars & Pubs",
            "type":"Food & Drink"
        },
        {
            "category":"Community Center",
            "subcategory":"Social",
            "type":"Public Place"
        }
    ],
    "sg:phone":"+44 1476 400555",
    "sg:postcode":"NG31 6RY",
    "sg:province":"Lincolnshire",
    "sg:tags":[
        "pubs",
        "house",
        "inn",
        "activity"
    ],
    "wof:name":"Five Bells",
    "wof:placetype":"venue"
},
  "geometry": {"coordinates":[-0.641019,52.916553],"type":"Point"}
}