{
  "type": "Feature",
  "properties": {
    "addr:full":"5 Holgate Court, Western Road Romford Essex RM1 3JS",
    "addr:housenumber":"5",
    "addr:postcode":"rm1 3js",
    "addr:street":"Holgate Court Western Road",
    "iso:country":"GB",
    "sg:address":"5 Holgate Court, Western Road",
    "sg:city":"Romford",
    "sg:classifiers":[
        {
            "category":"Professional",
            "subcategory":"Engineering",
            "type":"Services"
        }
    ],
    "sg:phone":"+44 1708 729070",
    "sg:postcode":"RM1 3JS",
    "sg:province":"Essex",
    "sg:tags":[
        "consulting",
        "engineer"
    ],
    "wof:name":"David Miles & Partners Ltd.",
    "wof:placetype":"venue"
},
  "geometry": {"coordinates":[0.183221,51.576496],"type":"Point"}
}