{
  "type": "Feature",
  "properties": {
    "addr:full":"Unit 2 & 3, 108 Edward Road, Balsall Heath Birmingham West Midlands B12 9LS",
    "addr:housenumber":"unit 2 & 3 108",
    "addr:postcode":"b12 9ls",
    "addr:street":"Edward Road",
    "iso:country":"GB",
    "sg:address":"Unit 2 & 3, 108 Edward Road, Balsall Heath",
    "sg:city":"Birmingham",
    "sg:classifiers":[
        {
            "category":"Professional",
            "subcategory":"Engineering",
            "type":"Services"
        }
    ],
    "sg:phone":"+44 121 440 7474",
    "sg:postcode":"B12 9LS",
    "sg:province":"West Midlands",
    "sg:tags":[
        "precision",
        "engineer"
    ],
    "wof:name":"Stirling Precision Ltd.",
    "wof:placetype":"venue"
},
  "geometry": {"coordinates":[-1.8909189701,52.4574928284],"type":"Point"}
}