{
  "type": "Feature",
  "properties": {
    "iso:country":"GB",
    "sg:address":"Unit 1 Beaufort Court, Plasmarl Industrial Estate",
    "sg:city":"Swansea",
    "sg:classifiers":[
        {
            "category":"Professional",
            "subcategory":"Lawyer & Legal Services",
            "type":"Services"
        }
    ],
    "sg:phone":"+44 1792 781110",
    "sg:postcode":"SA6 8JG",
    "sg:province":"Swansea",
    "wof:name":"Lawstore",
    "wof:placetype":"venue"
},
  "geometry": {"coordinates":[-3.923893,51.658905],"type":"Point"}
}