{
  "type": "Feature",
  "properties": {
    "addr:full":"Gleneagles House Derby Derbyshire DE1 1UP",
    "addr:postcode":"de1 1up",
    "iso:country":"GB",
    "sg:address":"Gleneagles House",
    "sg:city":"Derby",
    "sg:classifiers":[
        {
            "category":"Professional",
            "subcategory":"Computer Services",
            "type":"Services"
        }
    ],
    "sg:phone":"+44 1332 206602",
    "sg:postcode":"DE1 1UP",
    "sg:province":"Derbyshire",
    "sg:tags":[
        "information"
    ],
    "wof:name":"Link-Up Supply Chain Services Ltd.",
    "wof:placetype":"venue"
},
  "geometry": {"coordinates":[-1.483684,52.925171],"type":"Point"}
}