{
  "type": "Feature",
  "properties": {
    "addr:full":"38 Hamilton Road, Rutherglen Glasgow Glasgow City G73 3DG",
    "addr:housenumber":"38",
    "addr:postcode":"g73 3dg",
    "addr:street":"Hamilton Road",
    "iso:country":"GB",
    "sg:address":"38 Hamilton Road, Rutherglen",
    "sg:city":"Glasgow",
    "sg:classifiers":[
        {
            "category":"Shopping",
            "subcategory":"Bicycles & Sporting Goods",
            "type":"Retail Goods"
        }
    ],
    "sg:postcode":"G73 3DG",
    "sg:province":"Glasgow City",
    "sg:tags":[
        "dance",
        "balletwear"
    ],
    "wof:name":"D Miss",
    "wof:placetype":"venue"
},
  "geometry": {"coordinates":[-4.2091,55.827232],"type":"Point"}
}