{
  "type": "Feature",
  "properties": {
    "addr:full":"Windmill Street Peterhead Aberdeenshire AB42 1UL",
    "addr:postcode":"ab42 1ul",
    "addr:street":"Windmill Street",
    "iso:country":"GB",
    "sg:address":"Windmill Street",
    "sg:city":"Peterhead",
    "sg:classifiers":[
        {
            "category":"Manufacturing",
            "subcategory":"Building Materials",
            "type":"Manufacturing & Wholesale Goods"
        }
    ],
    "sg:phone":"+44 1779 479393",
    "sg:postcode":"AB42 1UL",
    "sg:province":"Aberdeenshire",
    "sg:tags":[
        "merchant",
        "builder"
    ],
    "wof:name":"Keyline Builders Merchants Ltd.",
    "wof:placetype":"venue"
},
  "geometry": {"coordinates":[-1.7837289572,57.5095443726],"type":"Point"}
}