{
  "type": "Feature",
  "properties": {
    "iso:country":"GB",
    "sg:address":"Horton Road, Stanwell Moor",
    "sg:city":"Staines",
    "sg:classifiers":[
        {
            "category":"Manufacturing",
            "subcategory":"Building Materials",
            "type":"Manufacturing & Wholesale Goods"
        }
    ],
    "sg:phone":"+44 1753 683324",
    "sg:postcode":"TW19 6AQ",
    "sg:province":"Berkshire",
    "sg:tags":[
        "merchant",
        "builder"
    ],
    "wof:name":"Wiggins Transport Ltd.",
    "wof:placetype":"venue"
},
  "geometry": {"coordinates":[-0.5016149879,51.4629478455],"type":"Point"}
}