{
  "type": "Feature",
  "properties": {
    "addr:full":"79 Bute Street Treorchy Rhondda, Cynon, Taff CF42 6AH",
    "addr:housenumber":"79",
    "addr:postcode":"cf42 6ah",
    "addr:street":"Bute Street;Cynon Taff",
    "iso:country":"GB",
    "sg:address":"79 Bute Street",
    "sg:city":"Treorchy",
    "sg:classifiers":[
        {
            "category":"Personal",
            "subcategory":"Shoe Repair & Shine",
            "type":"Services"
        },
        {
            "category":"Shopping",
            "subcategory":"Shoes",
            "type":"Retail Goods"
        }
    ],
    "sg:phone":"+44 1443 774078",
    "sg:postcode":"CF42 6AH",
    "sg:province":"Rhondda, Cynon, Taff",
    "wof:name":"Feet First",
    "wof:placetype":"venue"
},
  "geometry": {"coordinates":[-3.5084080696,51.6611938477],"type":"Point"}
}