{
  "type": "Feature",
  "properties": {
    "addr:full":"Shongwene, Buller Road Crediton Devon EX12 2AY",
    "addr:postcode":"ex12 2ay",
    "addr:street":"Buller Road",
    "iso:country":"GB",
    "sg:address":"Shongwene, Buller Road",
    "sg:city":"Crediton",
    "sg:classifiers":[
        {
            "category":"Building & Trades",
            "subcategory":"Construction",
            "type":"Services"
        }
    ],
    "sg:postcode":"EX12 2AY",
    "sg:province":"Devon",
    "sg:tags":[
        "decorator",
        "painter"
    ],
    "wof:name":"L Milford & Son",
    "wof:placetype":"venue"
},
  "geometry": {"coordinates":[-3.074160099,50.7089614868],"type":"Point"}
}