{
  "type": "Feature",
  "properties": {
    "iso:country":"GB",
    "sg:address":"18 Thames St",
    "sg:city":"Windsor",
    "sg:classifiers":[
        {
            "category":"Manufacturing",
            "subcategory":"Textiles",
            "type":"Manufacturing & Wholesale Goods"
        }
    ],
    "sg:phone":"+44 1753 853405",
    "sg:postcode":"SL4 1PL",
    "sg:province":"Berkshire",
    "sg:tags":[
        "knitwear"
    ],
    "wof:name":"Pitlochry Knitwear",
    "wof:placetype":"venue"
},
  "geometry": {"coordinates":[-0.608645,51.483795],"type":"Point"}
}