{
  "type": "Feature",
  "properties": {
    "iso:country":"GB",
    "sg:address":"14 New Market Square",
    "sg:city":"Basingstoke",
    "sg:classifiers":[
        {
            "category":"Food & Beverages",
            "subcategory":"Meat & Fish",
            "type":"Retail Goods"
        }
    ],
    "sg:postcode":"RG21 7HN",
    "sg:province":"Hampshire",
    "sg:tags":[
        "chip"
    ],
    "wof:name":"The Friary Fish Bar",
    "wof:placetype":"venue"
},
  "geometry": {"coordinates":[-1.083089,51.262444],"type":"Point"}
}