{
  "type": "Feature",
  "properties": {
    "addr:full":"Falmouth Avenue Newmarket Cambridgeshire CB8 0NB",
    "addr:postcode":"cb8 0nb",
    "addr:street":"Falmouth Avenue Newmarket",
    "iso:country":"GB",
    "sg:address":"Falmouth Avenue",
    "sg:city":"Newmarket",
    "sg:classifiers":[
        {
            "category":"Health Services",
            "subcategory":"Nursing And Care Facility",
            "type":"Services"
        }
    ],
    "sg:phone":"+44 1638 561944",
    "sg:postcode":"CB8 0NB",
    "sg:province":"Cambridgeshire",
    "sg:tags":[
        "home"
    ],
    "wof:name":"Premier Care Homes Ltd.",
    "wof:placetype":"venue"
},
  "geometry": {"coordinates":[0.3960910141,52.241809845],"type":"Point"}
}