{
  "type": "Feature",
  "properties": {
    "addr:full":"23 Bridge St, St. Ives Huntingdon Cambridgeshire PE17 4EH",
    "addr:housenumber":"23",
    "addr:postcode":"pe17 4eh",
    "addr:street":"Bridge St",
    "iso:country":"GB",
    "sg:address":"23 Bridge St, St. Ives",
    "sg:city":"Huntingdon",
    "sg:classifiers":[
        {
            "category":"Travel",
            "subcategory":"Travel Agent",
            "type":"Entertainment"
        }
    ],
    "sg:phone":"+44 1480 461447",
    "sg:postcode":"PE17 4EH",
    "sg:province":"Cambridgeshire",
    "wof:name":"Travel World",
    "wof:placetype":"venue"
},
  "geometry": {"coordinates":[-0.1893,52.33514],"type":"Point"}
}