{
  "type": "Feature",
  "properties": {
    "addr:full":"112 Shirley High Street Southampton Hampshire SO16 4EZ",
    "addr:housenumber":"112",
    "addr:postcode":"so16 4ez",
    "addr:street":"Shirley High Street",
    "iso:country":"GB",
    "sg:address":"112 Shirley High Street",
    "sg:city":"Southampton",
    "sg:classifiers":[
        {
            "category":"Recreation",
            "subcategory":"Amusement Park",
            "type":"Entertainment"
        }
    ],
    "sg:phone":"+44 23 8077 1028",
    "sg:postcode":"SO16 4EZ",
    "sg:province":"Hampshire",
    "sg:tags":[
        "arcade"
    ],
    "wof:name":"Richmond Leisure",
    "wof:placetype":"venue"
},
  "geometry": {"coordinates":[-1.4350010157,50.9232635498],"type":"Point"}
}