{
  "type": "Feature",
  "properties": {
    "addr:full":"The Cadet Centre, Finchingfield Av Woodford Green Essex IG8 7JS",
    "addr:postcode":"ig8 7js",
    "addr:street":"Finchingfield Av Woodford Green",
    "iso:country":"GB",
    "sg:address":"The Cadet Centre, Finchingfield Av",
    "sg:city":"Woodford Green",
    "sg:classifiers":[
        {
            "category":"Community Center",
            "subcategory":"Youth",
            "type":"Public Place"
        }
    ],
    "sg:phone":"+44 20 8505 4744",
    "sg:postcode":"IG8 7JS",
    "sg:province":"Essex",
    "sg:tags":[
        "organisation",
        "centre"
    ],
    "wof:name":"Air Training Corps",
    "wof:placetype":"venue"
},
  "geometry": {"coordinates":[0.0289820004,51.6043891907],"type":"Point"}
}