{
  "type": "Feature",
  "properties": {
    "addr:full":"Rectory La, Timsbury Bath Somerset BA2 0LB",
    "addr:postcode":"ba2 0lb",
    "iso:country":"GB",
    "sg:address":"Rectory La, Timsbury",
    "sg:city":"Bath",
    "sg:classifiers":[
        {
            "category":"Personal",
            "type":"Services"
        }
    ],
    "sg:postcode":"BA2 0LB",
    "sg:province":"Somerset",
    "sg:tags":[
        "dressmaker"
    ],
    "wof:name":"Thomson,Susan,",
    "wof:placetype":"venue"
},
  "geometry": {"coordinates":[-2.476349,51.328056],"type":"Point"}
}