{
  "type": "Feature",
  "properties": {
    "iso:country":"GB",
    "sg:address":"40 Woodside Road",
    "sg:city":"London",
    "sg:classifiers":[
        {
            "category":"Home & Garden",
            "subcategory":"Carpets & Floor Coverings",
            "type":"Retail Goods"
        }
    ],
    "sg:postcode":"SE25 5DY",
    "sg:province":"Greater London",
    "sg:tags":[
        "carpets",
        "rug",
        "matting"
    ],
    "wof:name":"Carpet Fitting",
    "wof:placetype":"venue"
},
  "geometry": {"coordinates":[-0.066792,51.387371],"type":"Point"}
}