{
  "type": "Feature",
  "properties": {
    "iso:country":"GB",
    "sg:address":"Cherrydown East",
    "sg:city":"Basildon",
    "sg:classifiers":[
        {
            "category":"Retail",
            "subcategory":"Auto Repair",
            "type":"Services"
        }
    ],
    "sg:phone":"+44 1268 522744",
    "sg:postcode":"SS16 5AQ",
    "sg:province":"Essex",
    "sg:tags":[
        "body",
        "car"
    ],
    "wof:name":"Essex Motors Ltd.",
    "wof:placetype":"venue"
},
  "geometry": {"coordinates":[0.460501,51.567589],"type":"Point"}
}