{
  "type": "Feature",
  "properties": {
    "addr:full":"23 Nelson Road, Greenwich London Greater London SE10 9JB",
    "addr:housenumber":"23",
    "addr:postcode":"se10 9jb",
    "addr:street":"Nelson Road",
    "iso:country":"GB",
    "sg:address":"23 Nelson Road, Greenwich",
    "sg:city":"London",
    "sg:classifiers":[
        {
            "category":"Shopping",
            "subcategory":"Books",
            "type":"Retail Goods"
        }
    ],
    "sg:phone":"+44 20 8853 1727",
    "sg:postcode":"SE10 9JB",
    "sg:province":"Greater London",
    "sg:tags":[
        "second-hand"
    ],
    "wof:name":"Anthony J Simmonds Maritime Books",
    "wof:placetype":"venue"
},
  "geometry": {"coordinates":[-0.0088529997,51.4807853699],"type":"Point"}
}