{
  "type": "Feature",
  "properties": {
    "addr:full":"Unit D2, Maws Craft Centre, Ferry Road Telford Shropshire TF8 7LS",
    "addr:postcode":"tf8 7ls",
    "addr:street":"Ferry Road",
    "iso:country":"GB",
    "sg:address":"Unit D2, Maws Craft Centre, Ferry Road",
    "sg:city":"Telford",
    "sg:classifiers":[
        {
            "category":"Manufacturing",
            "subcategory":"Pottery",
            "type":"Manufacturing & Wholesale Goods"
        }
    ],
    "sg:phone":"+44 1952 884443",
    "sg:postcode":"TF8 7LS",
    "sg:province":"Shropshire",
    "wof:name":"Freda Hoof",
    "wof:placetype":"venue"
},
  "geometry": {"coordinates":[-2.4568800926,52.6205482483],"type":"Point"}
}