{
  "type": "Feature",
  "properties": {
    "iso:country":"GB",
    "sg:address":"14 Jessop Square, Heron Quays",
    "sg:city":"London",
    "sg:classifiers":[
        {
            "category":"Professional",
            "subcategory":"Computer Services",
            "type":"Services"
        }
    ],
    "sg:phone":"+44 20 7515 5414",
    "sg:postcode":"E14 4JB",
    "sg:province":"Greater London",
    "sg:tags":[
        "system",
        "software"
    ],
    "wof:name":"I T C Network Consultants Ltd.",
    "wof:placetype":"venue"
},
  "geometry": {"coordinates":[-0.02439,51.503731],"type":"Point"}
}