{
  "type": "Feature",
  "properties": {
    "iso:country":"GB",
    "sg:address":"Unit 1, Polmeise Park, Stirling Road",
    "sg:city":"Stirling",
    "sg:classifiers":[
        {
            "category":"Shopping",
            "subcategory":"Mobile Phones",
            "type":"Retail Goods"
        }
    ],
    "sg:phone":"+44 1786 818811",
    "sg:postcode":"FK7 7JH",
    "sg:province":"Falkirk",
    "wof:name":"Aa Mobile Communications",
    "wof:placetype":"venue"
},
  "geometry": {"coordinates":[-3.876902,56.107498],"type":"Point"}
}