{
  "type": "Feature",
  "properties": {
    "addr:full":"48a Bisley Old Road Stroud Gloucestershire GL5 1LT",
    "addr:housenumber":"48a",
    "addr:postcode":"gl5 1lt",
    "addr:street":"Bisley Old Road",
    "iso:country":"GB",
    "sg:address":"48a Bisley Old Road",
    "sg:city":"Stroud",
    "sg:classifiers":[
        {
            "category":"Building & Trades",
            "subcategory":"Construction",
            "type":"Services"
        }
    ],
    "sg:postcode":"GL5 1LT",
    "sg:province":"Gloucestershire",
    "sg:tags":[
        "joiner",
        "carpenter"
    ],
    "wof:name":"S A Lennie",
    "wof:placetype":"venue"
},
  "geometry": {"coordinates":[-2.2039570808,51.7443122864],"type":"Point"}
}