{
  "type": "Feature",
  "properties": {
    "iso:country":"GB",
    "sg:address":"Wheels House, Turnpike Road, Red Lodge",
    "sg:city":"Bury St Edmunds",
    "sg:classifiers":[
        {
            "category":"Freight",
            "type":"Transportation"
        }
    ],
    "sg:phone":"+44 1638 750486",
    "sg:postcode":"IP28 8LB",
    "sg:province":"Cambridgeshire",
    "sg:tags":[
        "haulage",
        "road"
    ],
    "wof:name":"Derek Cooper (Transport) Ltd.",
    "wof:placetype":"venue"
},
  "geometry": {"coordinates":[0.4849550128,52.3029899597],"type":"Point"}
}