{
  "type": "Feature",
  "properties": {
    "addr:full":"Unit B Penfold Trading Estate, Imperial Way Watford Hertfordshire WD2 4YY",
    "addr:postcode":"wd2 4yy",
    "addr:street":"Imperial Way",
    "iso:country":"GB",
    "sg:address":"Unit B Penfold Trading Estate, Imperial Way",
    "sg:city":"Watford",
    "sg:classifiers":[
        {
            "category":"Shopping",
            "subcategory":"Clothing, Apparel, & Fashions",
            "type":"Retail Goods"
        }
    ],
    "sg:phone":"+44 1923 254747",
    "sg:postcode":"WD2 4YY",
    "sg:province":"Hertfordshire",
    "sg:tags":[
        "staff",
        "wear",
        "uniform"
    ],
    "wof:name":"Carter Harris",
    "wof:placetype":"venue"
},
  "geometry": {"coordinates":[-0.39072,51.652119],"type":"Point"}
}