{
  "type": "Feature",
  "properties": {
    "iso:country":"GB",
    "sg:address":"Sunrise Business Park, High Street, Wollaston",
    "sg:city":"Stourbridge",
    "sg:classifiers":[
        {
            "category":"Social Services",
            "type":"Services"
        }
    ],
    "sg:phone":"+44 1384 446638",
    "sg:postcode":"DY8 4PS",
    "sg:province":"Staffordshire",
    "sg:tags":[
        "disability"
    ],
    "wof:name":"Sunrise Medical Ltd.",
    "wof:placetype":"venue"
},
  "geometry": {"coordinates":[-2.162896,52.460892],"type":"Point"}
}