{
  "type": "Feature",
  "properties": {
    "iso:country":"GB",
    "sg:address":"Shotts Cottage, Fallin",
    "sg:city":"Stirling",
    "sg:classifiers":[
        {
            "category":"Utilities",
            "subcategory":"Natural Gas",
            "type":"Services"
        }
    ],
    "sg:phone":"+44 1786 461358",
    "sg:postcode":"FK7 7LU",
    "sg:province":"Falkirk",
    "sg:tags":[
        "blacksmith"
    ],
    "wof:name":"B McPhee",
    "wof:placetype":"venue"
},
  "geometry": {"coordinates":[-3.874639,56.104099],"type":"Point"}
}