{
  "type": "Feature",
  "properties": {
    "iso:country":"GB",
    "sg:address":"Swilland",
    "sg:city":"Ipswich",
    "sg:classifiers":[
        {
            "category":"Professional",
            "subcategory":"Engineering",
            "type":"Services"
        }
    ],
    "sg:phone":"+44 1473 785552",
    "sg:postcode":"IP6 9LT",
    "sg:province":"Suffolk",
    "sg:tags":[
        "electronic",
        "engineer"
    ],
    "wof:name":"Newton Hall Electronics Ltd.",
    "wof:placetype":"venue"
},
  "geometry": {"coordinates":[1.20771,52.121841],"type":"Point"}
}