{
  "type": "Feature",
  "properties": {
    "addr:full":"115 Digmoor Shopping Parade, Birleywood Skelmersdale Lancashire WN8 9HR",
    "addr:housenumber":"115",
    "addr:postcode":"wn8 9hr",
    "addr:street":"Digmoor Shopping Parade;Skelmersdale",
    "iso:country":"GB",
    "sg:address":"115 Digmoor Shopping Parade, Birleywood",
    "sg:city":"Skelmersdale",
    "sg:classifiers":[
        {
            "category":"Food & Beverages",
            "subcategory":"Fruits & Vegetables",
            "type":"Retail Goods"
        }
    ],
    "sg:phone":"+44 1695 731361",
    "sg:postcode":"WN8 9HR",
    "sg:province":"Lancashire",
    "sg:tags":[
        "greengrocer"
    ],
    "wof:name":"The Farm Shop",
    "wof:placetype":"venue"
},
  "geometry": {"coordinates":[-2.775784,53.549404],"type":"Point"}
}