{
  "type": "Feature",
  "properties": {
    "iso:country":"GB",
    "sg:address":"196 Brook Street, Broughty Ferry",
    "sg:city":"Dundee",
    "sg:classifiers":[
        {
            "category":"Health Services",
            "subcategory":"Dentist",
            "type":"Services"
        }
    ],
    "sg:phone":"+44 1382 477350",
    "sg:postcode":"DD5 2AH",
    "sg:province":"Angus",
    "wof:name":"I D S Robertson",
    "wof:placetype":"venue"
},
  "geometry": {"coordinates":[-2.875062,56.467213],"type":"Point"}
}