{
  "type": "Feature",
  "properties": {
    "iso:country":"GB",
    "sg:address":"12 New Street, Somercotes",
    "sg:city":"Alfreton",
    "sg:classifiers":[
        {
            "category":"Manufacturing",
            "subcategory":"Tools & Machinery",
            "type":"Manufacturing & Wholesale Goods"
        }
    ],
    "sg:postcode":"DE55 4HW",
    "sg:province":"Derbyshire",
    "wof:name":"In Power Tools",
    "wof:placetype":"venue"
},
  "geometry": {"coordinates":[-1.3668839931,53.0787811279],"type":"Point"}
}