{
  "type": "Feature",
  "properties": {
    "iso:country":"GB",
    "sg:address":"Barclays Bank Chambers, Union St",
    "sg:city":"Newton Abbot",
    "sg:classifiers":[
        {
            "category":"Professional",
            "subcategory":"Detective & Security Services",
            "type":"Services"
        }
    ],
    "sg:phone":"+44 1626 336566",
    "sg:postcode":"TQ12 2JY",
    "sg:province":"Devon",
    "sg:tags":[
        "agency"
    ],
    "wof:name":"Renaissance Business & Investestigation",
    "wof:placetype":"venue"
},
  "geometry": {"coordinates":[-3.607659,50.52887],"type":"Point"}
}