{
  "type": "Feature",
  "properties": {
    "addr:full":"57 New Road Rye East Sussex TN31 7LS",
    "addr:housenumber":"57",
    "addr:postcode":"tn31 7ls",
    "addr:street":"New Road",
    "iso:country":"GB",
    "sg:address":"57 New Road",
    "sg:city":"Rye",
    "sg:classifiers":[
        {
            "category":"Professional",
            "subcategory":"Management & Consulting",
            "type":"Services"
        }
    ],
    "sg:postcode":"TN31 7LS",
    "sg:province":"East Sussex",
    "sg:tags":[
        "consultant",
        "specialist"
    ],
    "wof:name":"Rebecca Booth",
    "wof:placetype":"venue"
},
  "geometry": {"coordinates":[0.7426390052,50.9539299011],"type":"Point"}
}