{
  "type": "Feature",
  "properties": {
    "addr:full":"Clint Grange, Clint Harrogate North Yorkshire HG3 3DT",
    "addr:postcode":"hg3 3dt",
    "iso:country":"GB",
    "sg:address":"Clint Grange, Clint",
    "sg:city":"Harrogate",
    "sg:classifiers":[
        {
            "category":"Farming",
            "subcategory":"Dairy Farm",
            "type":"Manufacturing & Wholesale Goods"
        }
    ],
    "sg:phone":"+44 1423 770282",
    "sg:postcode":"HG3 3DT",
    "sg:province":"North Yorkshire",
    "sg:tags":[
        "farmer"
    ],
    "wof:name":"John C Parker",
    "wof:placetype":"venue"
},
  "geometry": {"coordinates":[-1.6093759537,54.0344047546],"type":"Point"}
}