{
  "type": "Feature",
  "properties": {
    "addr:full":"128a Main Street, Baillieston Glasgow East Dunbartonshire G69 6AA",
    "addr:housenumber":"128a",
    "addr:postcode":"g69 6aa",
    "addr:street":"Main Street",
    "iso:country":"GB",
    "sg:address":"128a Main Street, Baillieston",
    "sg:city":"Glasgow",
    "sg:classifiers":[
        {
            "category":"Ice Cream",
            "type":"Food & Drink"
        }
    ],
    "sg:phone":"+44 141 771 7851",
    "sg:postcode":"G69 6AA",
    "sg:province":"East Dunbartonshire",
    "sg:tags":[
        "shop",
        "mobile",
        "parlour"
    ],
    "wof:name":"Soave's",
    "wof:placetype":"venue"
},
  "geometry": {"coordinates":[-4.1093587875,55.8506393433],"type":"Point"}
}