{
  "type": "Feature",
  "properties": {
    "addr:full":"Swiss Cottage, Acton Scott Church Stretton Shropshire SY6 6QJ",
    "addr:postcode":"sy6 6qj",
    "iso:country":"GB",
    "sg:address":"Swiss Cottage, Acton Scott",
    "sg:city":"Church Stretton",
    "sg:classifiers":[
        {
            "category":"Utilities",
            "subcategory":"Sewage",
            "type":"Services"
        }
    ],
    "sg:phone":"+44 1694 781333",
    "sg:postcode":"SY6 6QJ",
    "sg:province":"Shropshire",
    "sg:tags":[
        "acoustic",
        "consultant"
    ],
    "wof:name":"Worldpanel Ltd.",
    "wof:placetype":"venue"
},
  "geometry": {"coordinates":[-2.8044490814,52.5015335083],"type":"Point"}
}