{
  "type": "Feature",
  "properties": {
    "addr:full":"Mill Ho, Mill Walk Nuneaton Leicestershire CV11 4DL",
    "addr:postcode":"cv11 4dl",
    "addr:street":"Mill Walk",
    "iso:country":"GB",
    "sg:address":"Mill Ho, Mill Walk",
    "sg:city":"Nuneaton",
    "sg:classifiers":[
        {
            "category":"Social Services",
            "type":"Services"
        }
    ],
    "sg:phone":"+44 24 7681 8000",
    "sg:postcode":"CV11 4DL",
    "sg:province":"Leicestershire",
    "sg:tags":[
        "benefit",
        "agency"
    ],
    "wof:name":"Benefits Agency",
    "wof:placetype":"venue"
},
  "geometry": {"coordinates":[-1.465594,52.522141],"type":"Point"}
}