{
  "type": "Feature",
  "properties": {
    "addr:full":"25 Morley St Bradford West Yorkshire BD7 1AG",
    "addr:housenumber":"25",
    "addr:postcode":"bd7 1ag",
    "addr:street":"Morley St",
    "iso:country":"GB",
    "sg:address":"25 Morley St",
    "sg:city":"Bradford",
    "sg:classifiers":[
        {
            "category":"Restaurant",
            "type":"Food & Drink"
        }
    ],
    "sg:phone":"+44 1274 724947",
    "sg:postcode":"BD7 1AG",
    "sg:province":"West Yorkshire",
    "sg:tags":[
        "indian"
    ],
    "wof:name":"Kashmir",
    "wof:placetype":"venue"
},
  "geometry": {"coordinates":[-1.758915,53.790668],"type":"Point"}
}