{
  "type": "Feature",
  "properties": {
    "addr:full":"22 Rossall Road Thornton-cleveleys Lancashire FY5 1DX",
    "addr:housenumber":"22",
    "addr:postcode":"fy5 1dx",
    "addr:street":"Rossall Road",
    "iso:country":"GB",
    "sg:address":"22 Rossall Road",
    "sg:city":"Thornton-cleveleys",
    "sg:classifiers":[
        {
            "category":"Shopping",
            "subcategory":"Bicycles & Sporting Goods",
            "type":"Retail Goods"
        }
    ],
    "sg:postcode":"FY5 1DX",
    "sg:province":"Lancashire",
    "sg:tags":[
        "cycle",
        "accessory"
    ],
    "wof:name":"The Cycle Centre",
    "wof:placetype":"venue"
},
  "geometry": {"coordinates":[-3.039756,53.879261],"type":"Point"}
}