{
  "type": "Feature",
  "properties": {
    "addr:full":"Oak Barn, Goosnargh Lane, Goosnargh Preston Lancashire PR3 2JU",
    "addr:postcode":"pr3 2ju",
    "addr:street":"Goosnargh Lane",
    "iso:country":"GB",
    "sg:address":"Oak Barn, Goosnargh Lane, Goosnargh",
    "sg:city":"Preston",
    "sg:classifiers":[
        {
            "category":"Professional",
            "subcategory":"Advertising",
            "type":"Services"
        }
    ],
    "sg:phone":"+44 1772 863333",
    "sg:postcode":"PR3 2JU",
    "sg:province":"Lancashire",
    "sg:tags":[
        "agency"
    ],
    "wof:name":"Gradelet Advertising Ltd.",
    "wof:placetype":"venue"
},
  "geometry": {"coordinates":[-2.6712839603,53.8220748901],"type":"Point"}
}