{
  "type": "Feature",
  "properties": {
    "iso:country":"GB",
    "sg:address":"Clint Hill Farm, Manor Road, Hanging Houghton",
    "sg:city":"Northampton",
    "sg:classifiers":[
        {
            "category":"Farming",
            "subcategory":"Farm",
            "type":"Manufacturing & Wholesale Goods"
        }
    ],
    "sg:postcode":"NN6 9ES",
    "sg:province":"Northamptonshire",
    "sg:tags":[
        "mixed",
        "crop"
    ],
    "wof:name":"J F Davidson",
    "wof:placetype":"venue"
},
  "geometry": {"coordinates":[-0.8932359815,52.3563919067],"type":"Point"}
}