{
  "type": "Feature",
  "properties": {
    "iso:country":"GB",
    "sg:address":"149 High Street, Gorleston",
    "sg:city":"Great Yarmouth",
    "sg:classifiers":[
        {
            "category":"Real Estate",
            "subcategory":"Real Estate Agent",
            "type":"Services"
        }
    ],
    "sg:phone":"+44 1493 661478",
    "sg:postcode":"NR31 6RB",
    "sg:province":"Norfolk",
    "wof:name":"Black Horse Agencies",
    "wof:placetype":"venue"
},
  "geometry": {"coordinates":[1.727843,52.579018],"type":"Point"}
}