{
  "type": "Feature",
  "properties": {
    "iso:country":"GB",
    "sg:address":"17 Sagar Street",
    "sg:city":"Castleford",
    "sg:classifiers":[
        {
            "category":"Shopping",
            "subcategory":"Department Store",
            "type":"Retail Goods"
        },
        {
            "category":"Shopping",
            "subcategory":"Crafts & Fabrics",
            "type":"Retail Goods"
        }
    ],
    "sg:phone":"+44 1977 553198",
    "sg:postcode":"WF10 1AG",
    "sg:province":"West Yorkshire",
    "sg:tags":[
        "machine",
        "sewing",
        "knitting"
    ],
    "wof:name":"White Rose Sewing Machine Co",
    "wof:placetype":"venue"
},
  "geometry": {"coordinates":[-1.351263,53.726704],"type":"Point"}
}