{
  "type": "Feature",
  "properties": {
    "addr:full":"91 Stamford Hill Stoke Newington Greater London N16 5TP",
    "addr:housenumber":"91",
    "addr:postcode":"n16 5tp",
    "addr:street":"Stamford Hill",
    "iso:country":"GB",
    "sg:address":"91 Stamford Hill",
    "sg:city":"Stoke Newington",
    "sg:classifiers":[
        {
            "category":"Social Services",
            "subcategory":"Child Care",
            "type":"Services"
        },
        {
            "category":"Social Services",
            "subcategory":"Adult Care",
            "type":"Services"
        }
    ],
    "sg:phone":"+44 20 8800 5672",
    "sg:postcode":"N16 5TP",
    "sg:province":"Greater London",
    "sg:tags":[
        "day",
        "centre"
    ],
    "wof:name":"Stamford Hill Community Centre",
    "wof:placetype":"venue"
},
  "geometry": {"coordinates":[-0.072819002,51.5710906982],"type":"Point"}
}