{
  "type": "Feature",
  "properties": {
    "addr:full":"Unit L19-20 Princess Mall, Waverley Bridge Edinburgh City of Edinburgh EH1 1BQ",
    "addr:postcode":"eh1 1bq",
    "addr:street":"Princess Mall;Bridge",
    "iso:country":"GB",
    "sg:address":"Unit L19-20 Princess Mall, Waverley Bridge",
    "sg:city":"Edinburgh",
    "sg:classifiers":[
        {
            "category":"Shopping",
            "subcategory":"Clothing, Apparel, & Fashions",
            "type":"Retail Goods"
        }
    ],
    "sg:phone":"+44 131 556 2031",
    "sg:postcode":"EH1 1BQ",
    "sg:province":"City of Edinburgh",
    "sg:tags":[
        "shop"
    ],
    "wof:name":"Xile Casual Wear",
    "wof:placetype":"venue"
},
  "geometry": {"coordinates":[-3.19198,55.952579],"type":"Point"}
}