{
  "type": "Feature",
  "properties": {
    "addr:full":"Office Furniture House, Potters Lane Wednesbury West Midlands WS10 7LP",
    "addr:postcode":"ws10 7lp",
    "addr:street":"Potters Lane",
    "iso:country":"GB",
    "sg:address":"Office Furniture House, Potters Lane",
    "sg:city":"Wednesbury",
    "sg:classifiers":[
        {
            "category":"Shopping",
            "subcategory":"Stationery & Office Supplies",
            "type":"Retail Goods"
        }
    ],
    "sg:postcode":"WS10 7LP",
    "sg:province":"West Midlands",
    "sg:tags":[
        "equipment"
    ],
    "wof:name":"C I S Office Furniture Ltd.",
    "wof:placetype":"venue"
},
  "geometry": {"coordinates":[-2.026259,52.550331],"type":"Point"}
}