{
  "type": "Feature",
  "properties": {
    "addr:full":"4 Lapwing Lane, West Didbury Manchester Greater Manchester M20 2WS",
    "addr:housenumber":"4",
    "addr:postcode":"m20 2ws",
    "addr:street":"Lapwing Lane West Didbury",
    "iso:country":"GB",
    "sg:address":"4 Lapwing Lane, West Didbury",
    "sg:city":"Manchester",
    "sg:classifiers":[
        {
            "category":"Communications",
            "type":"Services"
        }
    ],
    "sg:postcode":"M20 2WS",
    "sg:province":"Greater Manchester",
    "sg:tags":[
        "audio-visual"
    ],
    "wof:name":"Audio Production Services Ltd.",
    "wof:placetype":"venue"
},
  "geometry": {"coordinates":[-2.240961,53.427948],"type":"Point"}
}