{
  "type": "Feature",
  "properties": {
    "iso:country":"GB",
    "sg:address":"37 Skelgate",
    "sg:city":"Dalton-in-furness",
    "sg:classifiers":[
        {
            "category":"Building & Trades",
            "subcategory":"Construction",
            "type":"Services"
        }
    ],
    "sg:phone":"+44 1229 463745",
    "sg:postcode":"LA15 8BD",
    "sg:province":"Cumbria",
    "sg:tags":[
        "joiner",
        "carpenter"
    ],
    "wof:name":"M E Blamire",
    "wof:placetype":"venue"
},
  "geometry": {"coordinates":[-3.187715,54.156731],"type":"Point"}
}