{
  "type": "Feature",
  "properties": {
    "iso:country":"GB",
    "sg:address":"1 Miranda Court, Regents Park, Asgard Drive",
    "sg:city":"Salford",
    "sg:classifiers":[
        {
            "category":"Professional",
            "subcategory":"Management & Consulting",
            "type":"Services"
        }
    ],
    "sg:phone":"+44 161 832 2492",
    "sg:postcode":"M5 4TN",
    "sg:province":"Greater Manchester",
    "sg:tags":[
        "consultant",
        "business"
    ],
    "wof:name":"M Consulting",
    "wof:placetype":"venue"
},
  "geometry": {"coordinates":[-2.26602,53.475681],"type":"Point"}
}