{
  "type": "Feature",
  "properties": {
    "iso:country":"GB",
    "sg:address":"68 Terminus Road",
    "sg:city":"Eastbourne",
    "sg:classifiers":[
        {
            "category":"Professional",
            "subcategory":"Printing & Photocopies",
            "type":"Services"
        }
    ],
    "sg:phone":"+44 1323 645282",
    "sg:postcode":"BN21 3LX",
    "sg:province":"East Sussex",
    "sg:tags":[
        "printer"
    ],
    "wof:name":"Kall-Kwik",
    "wof:placetype":"venue"
},
  "geometry": {"coordinates":[0.282356,50.768654],"type":"Point"}
}