{
  "type": "Feature",
  "properties": {
    "addr:full":"Main Rd, Giddia Park Romford Essex RM2 6BA",
    "addr:postcode":"rm2 6ba",
    "addr:street":"Main Rd Giddia Park",
    "iso:country":"GB",
    "sg:address":"Main Rd, Giddia Park",
    "sg:city":"Romford",
    "sg:classifiers":[
        {
            "category":"Insurance",
            "subcategory":"Insurance Agent",
            "type":"Services"
        }
    ],
    "sg:phone":"+44 1708 706633",
    "sg:postcode":"RM2 6BA",
    "sg:province":"Essex",
    "sg:tags":[
        "broker"
    ],
    "wof:name":"Brian Sharp Associates",
    "wof:placetype":"venue"
},
  "geometry": {"coordinates":[0.208445,51.58968],"type":"Point"}
}