{
  "type": "Feature",
  "properties": {
    "iso:country":"GB",
    "sg:address":"46 Station Rd, Alvechurch",
    "sg:city":"Birmingham",
    "sg:classifiers":[
        {
            "category":"Shopping",
            "subcategory":"Stationery & Office Supplies",
            "type":"Retail Goods"
        }
    ],
    "sg:postcode":"B48 7SD",
    "sg:province":"Worcestershire",
    "sg:tags":[
        "item",
        "promotional"
    ],
    "wof:name":"Eleda Sales",
    "wof:placetype":"venue"
},
  "geometry": {"coordinates":[-1.9664529562,52.3477363586],"type":"Point"}
}