{
  "type": "Feature",
  "properties": {
    "iso:country":"GB",
    "sg:address":"152 South Parade, Matlock Bath",
    "sg:city":"Matlock",
    "sg:classifiers":[
        {
            "category":"Shopping",
            "subcategory":"Department Store",
            "type":"Retail Goods"
        }
    ],
    "sg:phone":"+44 1629 582726",
    "sg:postcode":"DE4 3NR",
    "sg:province":"Derbyshire",
    "wof:name":"Spice Islands",
    "wof:placetype":"venue"
},
  "geometry": {"coordinates":[-1.563588,53.120316],"type":"Point"}
}