{
  "type": "Feature",
  "properties": {
    "addr:full":"Unit 21-22, The Precinct Blaydon-on-tyne Tyne and Wear NE21 5BT",
    "addr:housenumber":"unit 21-22",
    "addr:postcode":"ne21 5bt",
    "addr:street":"The;Blaydon-On-Tyne",
    "iso:country":"GB",
    "sg:address":"Unit 21-22, The Precinct",
    "sg:city":"Blaydon-on-tyne",
    "sg:classifiers":[
        {
            "category":"Shopping",
            "subcategory":"Pharmacy",
            "type":"Retail Goods"
        }
    ],
    "sg:phone":"+44 191 414 5244",
    "sg:postcode":"NE21 5BT",
    "sg:province":"Tyne and Wear",
    "sg:tags":[
        "store",
        "drug"
    ],
    "wof:name":"Savers",
    "wof:placetype":"venue"
},
  "geometry": {"coordinates":[-1.7079429626,54.9630126953],"type":"Point"}
}