{
  "type": "Feature",
  "properties": {
    "addr:full":"16 Chaucer Road London Greater London E17 4BE",
    "addr:housenumber":"16",
    "addr:postcode":"e17 4be",
    "addr:street":"Chaucer Road",
    "iso:country":"GB",
    "sg:address":"16 Chaucer Road",
    "sg:city":"London",
    "sg:classifiers":[
        {
            "category":"Building & Trades",
            "subcategory":"Construction",
            "type":"Services"
        }
    ],
    "sg:postcode":"E17 4BE",
    "sg:province":"Greater London",
    "sg:tags":[
        "dry",
        "lining",
        "plasterers",
        "screeders"
    ],
    "wof:name":"B Hayden & Co",
    "wof:placetype":"venue"
},
  "geometry": {"coordinates":[-0.0037370001,51.5957336426],"type":"Point"}
}