{
  "type": "Feature",
  "properties": {
    "addr:full":"52 Pinner Grn Pinner Greater London HA5 2AB",
    "addr:housenumber":"52",
    "addr:postcode":"ha5 2ab",
    "addr:street":"Pinner Grn",
    "iso:country":"GB",
    "sg:address":"52 Pinner Grn",
    "sg:city":"Pinner",
    "sg:classifiers":[
        {
            "category":"Building & Trades",
            "subcategory":"Construction",
            "type":"Services"
        }
    ],
    "sg:phone":"+44 20 8868 8684",
    "sg:postcode":"HA5 2AB",
    "sg:province":"Greater London",
    "sg:tags":[
        "builder"
    ],
    "wof:name":"Jax Building Services Ltd.",
    "wof:placetype":"venue"
},
  "geometry": {"coordinates":[-0.394342,51.597984],"type":"Point"}
}