{
  "type": "Feature",
  "properties": {
    "iso:country":"GB",
    "sg:address":"Owls House, Frieston Road, Caythorpe",
    "sg:city":"Grantham",
    "sg:classifiers":[
        {
            "category":"Professional",
            "subcategory":"Computer Services",
            "type":"Services"
        }
    ],
    "sg:postcode":"NG32 3BX",
    "sg:province":"Leicestershire",
    "sg:tags":[
        "system",
        "software"
    ],
    "wof:name":"Mascot Consultants",
    "wof:placetype":"venue"
},
  "geometry": {"coordinates":[-0.6011490226,53.019493103],"type":"Point"}
}