{
  "type": "Feature",
  "properties": {
    "iso:country":"GB",
    "sg:address":"6 Spinningdale, Stonehouse",
    "sg:city":"Larkhall",
    "sg:classifiers":[
        {
            "category":"Building & Trades",
            "subcategory":"Construction",
            "type":"Services"
        }
    ],
    "sg:postcode":"ML9 3QS",
    "sg:province":"South Lanarkshire",
    "sg:tags":[
        "decorator",
        "painter"
    ],
    "wof:name":"James Hood Decor",
    "wof:placetype":"venue"
},
  "geometry": {"coordinates":[-3.9982779026,55.6906776428],"type":"Point"}
}