{
  "type": "Feature",
  "properties": {
    "addr:full":"12 Portland Road, South Norwood London Greater London SE25 4PF",
    "addr:housenumber":"12",
    "addr:postcode":"se25 4pf",
    "addr:street":"Portland Road",
    "iso:country":"GB",
    "sg:address":"12 Portland Road, South Norwood",
    "sg:city":"London",
    "sg:classifiers":[
        {
            "category":"Professional",
            "subcategory":"Art Services",
            "type":"Services"
        }
    ],
    "sg:phone":"+44 20 8662 0251",
    "sg:postcode":"SE25 4PF",
    "sg:province":"Greater London",
    "sg:tags":[
        "photographer"
    ],
    "wof:name":"Photographic Studio",
    "wof:placetype":"venue"
},
  "geometry": {"coordinates":[-0.0733390003,51.3986091614],"type":"Point"}
}