{
  "type": "Feature",
  "properties": {
    "iso:country":"GB",
    "sg:address":"33-35 Queen St",
    "sg:city":"Newton-le-willows",
    "sg:classifiers":[
        {
            "category":"Sports & Exercise",
            "subcategory":"Sports Center",
            "type":"Entertainment"
        }
    ],
    "sg:postcode":"WA12 9AS",
    "sg:province":"Cheshire",
    "sg:tags":[
        "shop",
        "good"
    ],
    "wof:name":"Wright,G,",
    "wof:placetype":"venue"
},
  "geometry": {"coordinates":[-2.6398849487,53.4514503479],"type":"Point"}
}