{
  "type": "Feature",
  "properties": {
    "addr:full":"4-5 Savile Way, Grove Wantage Berkshire OX12 0PT",
    "addr:housenumber":"4-5",
    "addr:postcode":"ox12 0pt",
    "addr:street":"Savile Way Grove",
    "iso:country":"GB",
    "sg:address":"4-5 Savile Way, Grove",
    "sg:city":"Wantage",
    "sg:classifiers":[
        {
            "category":"Shopping",
            "subcategory":"News",
            "type":"Retail Goods"
        }
    ],
    "sg:phone":"+44 1235 762883",
    "sg:postcode":"OX12 0PT",
    "sg:province":"Berkshire",
    "sg:tags":[
        "newsagent"
    ],
    "wof:name":"Forbuoys",
    "wof:placetype":"venue"
},
  "geometry": {"coordinates":[-1.4300630093,51.6075286865],"type":"Point"}
}