{
  "type": "Feature",
  "properties": {
    "addr:full":"Heol Canola, Sarn Bridgend Bridgend CF32 9NU",
    "addr:postcode":"cf32 9nu",
    "addr:street":"Heol Canola Sarn",
    "iso:country":"GB",
    "sg:address":"Heol Canola, Sarn",
    "sg:city":"Bridgend",
    "sg:classifiers":[
        {
            "category":"Health Services",
            "subcategory":"Clinic",
            "type":"Services"
        }
    ],
    "sg:phone":"+44 1656 726032",
    "sg:postcode":"CF32 9NU",
    "sg:province":"Bridgend",
    "sg:tags":[
        "nh"
    ],
    "wof:name":"Bryncethin Clinic",
    "wof:placetype":"venue"
},
  "geometry": {"coordinates":[-3.578999,51.541157],"type":"Point"}
}