{
  "type": "Feature",
  "properties": {
    "iso:country":"GB",
    "sg:address":"486 Railway Arches",
    "sg:city":"London",
    "sg:classifiers":[
        {
            "category":"Retail",
            "subcategory":"Auto Repair",
            "type":"Services"
        }
    ],
    "sg:phone":"+44 20 7377 5655",
    "sg:postcode":"EC2A 3EX",
    "sg:province":"Greater London",
    "sg:tags":[
        "modification",
        "garage"
    ],
    "wof:name":"Harry Mitchell Motors",
    "wof:placetype":"venue"
},
  "geometry": {"coordinates":[-0.07915,51.5243],"type":"Point"}
}