{
  "type": "Feature",
  "properties": {
    "addr:full":"Anchor Business Centre, Beddington Lane Croydon Surrey CR0 4YX",
    "addr:postcode":"cr0 4yx",
    "addr:street":"Beddington Lane",
    "iso:country":"GB",
    "sg:address":"Anchor Business Centre, Beddington Lane",
    "sg:city":"Croydon",
    "sg:classifiers":[
        {
            "category":"Freight",
            "type":"Transportation"
        }
    ],
    "sg:postcode":"CR0 4YX",
    "sg:province":"Surrey",
    "sg:tags":[
        "haulage",
        "road"
    ],
    "wof:name":"C Webster & Sons",
    "wof:placetype":"venue"
},
  "geometry": {"coordinates":[-0.1257639974,51.3676643372],"type":"Point"}
}