{
  "type": "Feature",
  "properties": {
    "iso:country":"GB",
    "sg:address":"152 Wallstone Lane, Hockley",
    "sg:city":"Birmingham",
    "sg:classifiers":[
        {
            "category":"Manufacturing",
            "subcategory":"Glass & Minerals",
            "type":"Manufacturing & Wholesale Goods"
        }
    ],
    "sg:phone":"+44 121 233 1985",
    "sg:postcode":"B18 6NZ",
    "sg:province":"West Midlands",
    "sg:tags":[
        "stained",
        "designer",
        "producer",
        "coloured"
    ],
    "wof:name":"Architectural Glass",
    "wof:placetype":"venue"
},
  "geometry": {"coordinates":[-1.915802,52.487152],"type":"Point"}
}