{
  "type": "Feature",
  "properties": {
    "addr:full":"St Edmunds House, Lower Baxter Street Bury St Edmunds Suffolk IP33 1ET",
    "addr:postcode":"ip33 1et",
    "addr:street":"St;Lower Baxter Street",
    "iso:country":"GB",
    "sg:address":"St Edmunds House, Lower Baxter Street",
    "sg:city":"Bury St Edmunds",
    "sg:classifiers":[
        {
            "category":"Professional",
            "subcategory":"Employment Agencies",
            "type":"Services"
        }
    ],
    "sg:phone":"+44 1284 701302",
    "sg:postcode":"IP33 1ET",
    "sg:province":"Suffolk",
    "sg:tags":[
        "consultant"
    ],
    "wof:name":"Cooper Lomaz Recruitment (Eastern) Ltd.",
    "wof:placetype":"venue"
},
  "geometry": {"coordinates":[0.7147750258,52.2457008362],"type":"Point"}
}