{
  "type": "Feature",
  "properties": {
    "addr:full":"45 East Street Blandford Forum Dorset DT11 7DX",
    "addr:housenumber":"45",
    "addr:postcode":"dt11 7dx",
    "addr:street":"East Street",
    "iso:country":"GB",
    "sg:address":"45 East Street",
    "sg:city":"Blandford Forum",
    "sg:classifiers":[
        {
            "category":"Professional",
            "subcategory":"Lawyer & Legal Services",
            "type":"Services"
        }
    ],
    "sg:phone":"+44 1258 459911",
    "sg:postcode":"DT11 7DX",
    "sg:province":"Dorset",
    "sg:tags":[
        "solicitor"
    ],
    "wof:name":"Grenville J Walker",
    "wof:placetype":"venue"
},
  "geometry": {"coordinates":[-2.1631360054,50.855922699],"type":"Point"}
}