{
  "type": "Feature",
  "properties": {
    "iso:country":"GB",
    "sg:address":"Trenethick Business Park, Water-ma-trout",
    "sg:city":"Helston",
    "sg:classifiers":[
        {
            "category":"Professional",
            "subcategory":"Advertising",
            "type":"Services"
        }
    ],
    "sg:phone":"+44 1326 572636",
    "sg:postcode":"TR13 0LW",
    "sg:province":"Cornwall",
    "sg:tags":[
        "mail",
        "direct"
    ],
    "wof:name":"3 B International Ltd.",
    "wof:placetype":"venue"
},
  "geometry": {"coordinates":[-5.266959,50.10582],"type":"Point"}
}