{
  "type": "Feature",
  "properties": {
    "iso:country":"GB",
    "sg:address":"32 Main Street",
    "sg:city":"Beith",
    "sg:classifiers":[
        {
            "category":"Food & Beverages",
            "subcategory":"Meat & Fish",
            "type":"Retail Goods"
        }
    ],
    "sg:phone":"+44 1505 502616",
    "sg:postcode":"KA15 2AA",
    "sg:province":"North Ayrshire",
    "sg:tags":[
        "butcher"
    ],
    "wof:name":"James T Blackwood (Beith) Ltd.",
    "wof:placetype":"venue"
},
  "geometry": {"coordinates":[-4.6318860054,55.7513999939],"type":"Point"}
}