{
  "type": "Feature",
  "properties": {
    "addr:full":"480 Mumbles Rd Swansea Swansea SA3 4BX",
    "addr:housenumber":"480",
    "addr:postcode":"sa3 4bx",
    "addr:street":"Mumbles Rd",
    "iso:country":"GB",
    "sg:address":"480 Mumbles Rd",
    "sg:city":"Swansea",
    "sg:classifiers":[
        {
            "category":"Restaurant",
            "type":"Food & Drink"
        }
    ],
    "sg:postcode":"SA3 4BX",
    "sg:province":"Swansea",
    "wof:name":"Miah",
    "wof:placetype":"venue"
},
  "geometry": {"coordinates":[-3.9993619919,51.5770378113],"type":"Point"}
}