{
  "type": "Feature",
  "properties": {
    "addr:full":"The Town Hall, North Street, Ashburton Newton Abbot Devon TQ13 7QH",
    "addr:postcode":"tq13 7qh",
    "addr:street":"North Street",
    "iso:country":"GB",
    "sg:address":"The Town Hall, North Street, Ashburton",
    "sg:city":"Newton Abbot",
    "sg:classifiers":[
        {
            "category":"Education",
            "subcategory":"Library",
            "type":"Public Place"
        },
        {
            "category":"Government",
            "subcategory":"Office",
            "type":"Public Place"
        }
    ],
    "sg:phone":"+44 1364 652896",
    "sg:postcode":"TQ13 7QH",
    "sg:province":"Devon",
    "sg:tags":[
        "book",
        "local"
    ],
    "wof:name":"Ashburton Library",
    "wof:placetype":"venue"
},
  "geometry": {"coordinates":[-3.747107029,50.5200424194],"type":"Point"}
}