{
  "type": "Feature",
  "properties": {
    "iso:country":"GB",
    "sg:address":"24 St. Michaels Rd",
    "sg:city":"Canvey Island",
    "sg:classifiers":[
        {
            "category":"Personal",
            "subcategory":"Beauty Salon",
            "type":"Services"
        }
    ],
    "sg:phone":"+44 1268 515464",
    "sg:postcode":"SS8 9NB",
    "sg:province":"Essex",
    "sg:tags":[
        "unisex",
        "hairdresser"
    ],
    "wof:name":"Papinos Hair Studio",
    "wof:placetype":"venue"
},
  "geometry": {"coordinates":[0.561146,51.522938],"type":"Point"}
}