{
  "type": "Feature",
  "properties": {
    "iso:country":"GB",
    "sg:address":"18 Park Road North",
    "sg:city":"Middlesbrough",
    "sg:classifiers":[
        {
            "category":"Social Services",
            "subcategory":"Child Care",
            "type":"Services"
        }
    ],
    "sg:phone":"+44 1642 231806",
    "sg:postcode":"TS1 3LF",
    "sg:province":"North Yorkshire",
    "sg:tags":[
        "agency",
        "nanny"
    ],
    "wof:name":"Kids Incorporated",
    "wof:placetype":"venue"
},
  "geometry": {"coordinates":[-1.239067,54.566936],"type":"Point"}
}