{
  "type": "Feature",
  "properties": {
    "addr:full":"Riverside House, Warwick Road Carlisle Cumbria CA1 2BS",
    "addr:postcode":"ca1 2bs",
    "addr:street":"Warwick Road",
    "iso:country":"GB",
    "sg:address":"Riverside House, Warwick Road",
    "sg:city":"Carlisle",
    "sg:classifiers":[
        {
            "category":"Building & Trades",
            "subcategory":"Cleaning & Sanitation",
            "type":"Services"
        }
    ],
    "sg:phone":"+44 1228 515835",
    "sg:postcode":"CA1 2BS",
    "sg:province":"Cumbria",
    "sg:tags":[
        "commercial"
    ],
    "wof:name":"Masterclean",
    "wof:placetype":"venue"
},
  "geometry": {"coordinates":[-2.911849,54.894444],"type":"Point"}
}