{
  "type": "Feature",
  "properties": {
    "iso:country":"GB",
    "sg:address":"Aylsham Station, Norwich Road, Aylsham",
    "sg:city":"Norwich",
    "sg:classifiers":[
        {
            "category":"Landmark",
            "subcategory":"Tourist Attraction",
            "type":"Public Place"
        }
    ],
    "sg:phone":"+44 1263 733858",
    "sg:postcode":"NR11 6BW",
    "sg:province":"Norfolk",
    "sg:tags":[
        "interest"
    ],
    "wof:name":"Bure Valley Railway (1991) Ltd.",
    "wof:placetype":"venue"
},
  "geometry": {"coordinates":[1.250354,52.795067],"type":"Point"}
}