{
  "type": "Feature",
  "properties": {
    "addr:full":"27 Carcroft Enterprise Park, Carcroft Doncaster North Yorkshire DN6 8DD",
    "addr:housenumber":"27",
    "addr:postcode":"dn6 8dd",
    "addr:street":"Carcroft Enterprise Park",
    "iso:country":"GB",
    "sg:address":"27 Carcroft Enterprise Park, Carcroft",
    "sg:city":"Doncaster",
    "sg:classifiers":[
        {
            "category":"Real Estate",
            "subcategory":"Architect",
            "type":"Services"
        }
    ],
    "sg:phone":"+44 1302 727016",
    "sg:postcode":"DN6 8DD",
    "sg:province":"North Yorkshire",
    "sg:tags":[
        "architectural"
    ],
    "wof:name":"Kingfisher Louvre Systems Ltd.",
    "wof:placetype":"venue"
},
  "geometry": {"coordinates":[-1.1778080463,53.5803909302],"type":"Point"}
}