{
  "type": "Feature",
  "properties": {
    "iso:country":"GB",
    "sg:address":"57 Shilton Lane",
    "sg:city":"Coventry",
    "sg:classifiers":[
        {
            "category":"Transit Center",
            "subcategory":"Passenger",
            "type":"Transportation"
        },
        {
            "category":"Retail",
            "subcategory":"Pet Boarding",
            "type":"Services"
        }
    ],
    "sg:phone":"+44 24 7661 7937",
    "sg:postcode":"CV2 2AB",
    "sg:province":"Warwickshire",
    "sg:tags":[
        "kennel",
        "catteries"
    ],
    "wof:name":"Top Cat",
    "wof:placetype":"venue"
},
  "geometry": {"coordinates":[-1.452197,52.44331],"type":"Point"}
}