{
  "type": "Feature",
  "properties": {
    "iso:country":"GB",
    "sg:address":"Unit 3 Thurrock Enterprise Centr, E",
    "sg:city":"Grays",
    "sg:classifiers":[
        {
            "category":"Shopping",
            "subcategory":"Clothing, Apparel, & Fashions",
            "type":"Retail Goods"
        }
    ],
    "sg:postcode":"RM17 6NF",
    "sg:province":"Essex",
    "sg:tags":[
        "haberdasher"
    ],
    "wof:name":"Oakcraft Supplies Ltd.",
    "wof:placetype":"venue"
},
  "geometry": {"coordinates":[0.33228001,51.4766311646],"type":"Point"}
}