{
  "type": "Feature",
  "properties": {
    "iso:country":"GB",
    "sg:address":"11 Irlami Industrial Estate 654 Liv, Erpool Road",
    "sg:city":"Manchester",
    "sg:classifiers":[
        {
            "category":"Retail",
            "subcategory":"Auto Repair",
            "type":"Services"
        }
    ],
    "sg:postcode":"M44 5AD",
    "sg:province":"Greater Manchester",
    "sg:tags":[
        "modification",
        "garage"
    ],
    "wof:name":"J Tabner",
    "wof:placetype":"venue"
},
  "geometry": {"coordinates":[-2.43271,53.433231],"type":"Point"}
}