{
  "type": "Feature",
  "properties": {
    "addr:full":"97a Bowleaze, Coveway Weymouth Dorset DT3 6PW",
    "addr:housenumber":"97a",
    "addr:postcode":"dt3 6pw",
    "addr:street":"Bowleaze Coveway",
    "iso:country":"GB",
    "sg:address":"97a Bowleaze, Coveway",
    "sg:city":"Weymouth",
    "sg:classifiers":[
        {
            "category":"Retail",
            "subcategory":"Driving School",
            "type":"Services"
        }
    ],
    "sg:postcode":"DT3 6PW",
    "sg:province":"Dorset",
    "wof:name":"Tim Clark",
    "wof:placetype":"venue"
},
  "geometry": {"coordinates":[-2.420429945,50.6376075745],"type":"Point"}
}