{
  "type": "Feature",
  "properties": {
    "addr:full":"Cleveland Ho Queens Sq Middlesbrough Durham TS2 1AA",
    "addr:postcode":"ts2 1aa",
    "addr:street":"Cleveland;Queens Sq",
    "iso:country":"GB",
    "sg:address":"Cleveland Ho Queens Sq",
    "sg:city":"Middlesbrough",
    "sg:classifiers":[
        {
            "category":"Shopping",
            "subcategory":"Crafts & Fabrics",
            "type":"Retail Goods"
        }
    ],
    "sg:postcode":"TS2 1AA",
    "sg:province":"Durham",
    "sg:tags":[
        "upholsterers'",
        "supply"
    ],
    "wof:name":"Chatha,Ajaib Singh,",
    "wof:placetype":"venue"
},
  "geometry": {"coordinates":[-1.233093977,54.581363678],"type":"Point"}
}