{
  "type": "Feature",
  "properties": {
    "addr:full":"Co-operative House, Upper Parliament St Nottingham Nottinghamshire NG1 6LN",
    "addr:postcode":"ng1 6ln",
    "addr:street":"Upper Parliament St",
    "iso:country":"GB",
    "sg:address":"Co-operative House, Upper Parliament St",
    "sg:city":"Nottingham",
    "sg:classifiers":[
        {
            "category":"Health Services",
            "subcategory":"Optometrist",
            "type":"Services"
        }
    ],
    "sg:phone":"+44 115 941 1477",
    "sg:postcode":"NG1 6LN",
    "sg:province":"Nottinghamshire",
    "sg:tags":[
        "optician"
    ],
    "wof:name":"Co-Op Eye Care",
    "wof:placetype":"venue"
},
  "geometry": {"coordinates":[-1.1530539989,52.9547386169],"type":"Point"}
}