{
  "type": "Feature",
  "properties": {
    "addr:full":"3 West Sanquhar Road Ayr South Ayrshire KA8 9HP",
    "addr:housenumber":"3",
    "addr:postcode":"ka8 9hp",
    "addr:street":"West Sanquhar Road",
    "iso:country":"GB",
    "sg:address":"3 West Sanquhar Road",
    "sg:city":"Ayr",
    "sg:classifiers":[
        {
            "category":"Personal",
            "subcategory":"Hair Removal",
            "type":"Services"
        }
    ],
    "sg:postcode":"KA8 9HP",
    "sg:province":"South Ayrshire",
    "sg:tags":[
        "electrolysis"
    ],
    "wof:name":"Joan Mack",
    "wof:placetype":"venue"
},
  "geometry": {"coordinates":[-4.616943,55.47279],"type":"Point"}
}