{
  "type": "Feature",
  "properties": {
    "iso:country":"GB",
    "sg:address":"51 Farnley Lane",
    "sg:city":"Otley",
    "sg:classifiers":[
        {
            "category":"Retail",
            "subcategory":"Storage",
            "type":"Services"
        }
    ],
    "sg:postcode":"LS21 2BH",
    "sg:province":"North Yorkshire",
    "sg:tags":[
        "household",
        "removal"
    ],
    "wof:name":"Ward & Son Carriers",
    "wof:placetype":"venue"
},
  "geometry": {"coordinates":[-1.689448,53.912468],"type":"Point"}
}