{
  "type": "Feature",
  "properties": {
    "iso:country":"GB",
    "sg:address":"West Temple Sheen",
    "sg:city":"London",
    "sg:classifiers":[
        {
            "category":"Education",
            "subcategory":"School",
            "type":"Public Place"
        }
    ],
    "sg:phone":"+44 20 8876 8394",
    "sg:postcode":"SW14 7RT",
    "sg:province":"Greater London",
    "sg:tags":[
        "local",
        "authority"
    ],
    "wof:name":"Sheen Mount Primary School",
    "wof:placetype":"venue"
},
  "geometry": {"coordinates":[-0.2754339874,51.4604759216],"type":"Point"}
}