{
  "type": "Feature",
  "properties": {
    "addr:full":"29-31 St Annes Rd West Lytham St Annes Lancashire FY8 1SB",
    "addr:housenumber":"29-31",
    "addr:postcode":"fy8 1sb",
    "addr:street":"St Annes Rd West;St",
    "iso:country":"GB",
    "sg:address":"29-31 St Annes Rd West",
    "sg:city":"Lytham St Annes",
    "sg:classifiers":[
        {
            "category":"Personal",
            "subcategory":"Beauty Salon",
            "type":"Services"
        }
    ],
    "sg:postcode":"FY8 1SB",
    "sg:province":"Lancashire",
    "wof:name":"Colyton Clinic",
    "wof:placetype":"venue"
},
  "geometry": {"coordinates":[-3.031219,53.751667],"type":"Point"}
}