{
  "type": "Feature",
  "properties": {
    "addr:full":"Portrack Lane Stockton-on-tees Durham TS18 2NR",
    "addr:postcode":"ts18 2nr",
    "addr:street":"Portrack Lane",
    "iso:country":"GB",
    "sg:address":"Portrack Lane",
    "sg:city":"Stockton-on-tees",
    "sg:classifiers":[
        {
            "category":"Building & Trades",
            "subcategory":"Equipment Rental",
            "type":"Services"
        }
    ],
    "sg:phone":"+44 1642 606070",
    "sg:postcode":"TS18 2NR",
    "sg:province":"Durham",
    "sg:tags":[
        "plant",
        "machinery"
    ],
    "wof:name":"Independent Access Supplies Ltd.",
    "wof:placetype":"venue"
},
  "geometry": {"coordinates":[-1.2987190485,54.5704345703],"type":"Point"}
}