{
  "type": "Feature",
  "properties": {
    "iso:country":"GB",
    "sg:address":"7 Ash Ct, Crystal Dr",
    "sg:city":"Smethwick",
    "sg:classifiers":[
        {
            "category":"Building & Trades",
            "subcategory":"Equipment Rental",
            "type":"Services"
        }
    ],
    "sg:phone":"+44 121 552 8626",
    "sg:postcode":"B66 1QG",
    "sg:province":"West Midlands",
    "sg:tags":[
        "hire",
        "centre"
    ],
    "wof:name":"Speedy Hire Centres",
    "wof:placetype":"venue"
},
  "geometry": {"coordinates":[-1.9963409901,52.5047607422],"type":"Point"}
}