{
  "type": "Feature",
  "properties": {
    "addr:full":"43 Stevenson Street Oban Argyll and Bute PA34 5NA",
    "addr:housenumber":"43",
    "addr:postcode":"pa34 5na",
    "addr:street":"Stevenson Street",
    "iso:country":"GB",
    "sg:address":"43 Stevenson Street",
    "sg:city":"Oban",
    "sg:classifiers":[
        {
            "category":"Shopping",
            "subcategory":"Florist",
            "type":"Retail Goods"
        }
    ],
    "sg:phone":"+44 1631 570966",
    "sg:postcode":"PA34 5NA",
    "sg:province":"Argyll and Bute",
    "wof:name":"The Flower House",
    "wof:placetype":"venue"
},
  "geometry": {"coordinates":[-5.4704341888,56.4121551514],"type":"Point"}
}