{
  "type": "Feature",
  "properties": {
    "addr:full":"658 High Road London Greater London E10 6JP",
    "addr:housenumber":"658",
    "addr:postcode":"e10 6jp",
    "addr:street":"High Road",
    "iso:country":"GB",
    "sg:address":"658 High Road",
    "sg:city":"London",
    "sg:classifiers":[
        {
            "category":"Shopping",
            "type":"Retail Goods"
        }
    ],
    "sg:phone":"+44 20 8539 1118",
    "sg:postcode":"E10 6JP",
    "sg:province":"Greater London",
    "sg:tags":[
        "part",
        "accessory"
    ],
    "wof:name":"Fordco",
    "wof:placetype":"venue"
},
  "geometry": {"coordinates":[-0.00821,51.570869],"type":"Point"}
}