{
  "type": "Feature",
  "properties": {
    "iso:country":"GB",
    "sg:address":"13 Maceys Rd",
    "sg:city":"Bristol",
    "sg:classifiers":[
        {
            "category":"Building & Trades",
            "subcategory":"Landscaping Services",
            "type":"Services"
        }
    ],
    "sg:phone":"+44 117 987 7508",
    "sg:postcode":"BS13 0NQ",
    "sg:province":"City of Bristol",
    "sg:tags":[
        "landscape",
        "contractor"
    ],
    "wof:name":"Abbeywood Landscape Services",
    "wof:placetype":"venue"
},
  "geometry": {"coordinates":[-2.5965740681,51.401802063],"type":"Point"}
}