{
  "type": "Feature",
  "properties": {
    "iso:country":"GB",
    "sg:address":"6 Gaddum Rd, Bowdon",
    "sg:city":"Altrincham",
    "sg:classifiers":[
        {
            "category":"Social Services",
            "subcategory":"Job Training",
            "type":"Services"
        }
    ],
    "sg:phone":"+44 161 941 5585",
    "sg:postcode":"WA14 3PB",
    "sg:province":"Cheshire",
    "sg:tags":[
        "translator",
        "interpreter"
    ],
    "wof:name":"Russian Information & Language Services",
    "wof:placetype":"venue"
},
  "geometry": {"coordinates":[-2.366112,53.37561],"type":"Point"}
}