{
  "type": "Feature",
  "properties": {
    "iso:country":"GB",
    "sg:address":"291 Kingsbridge Drive, Kingston",
    "sg:city":"Glasgow",
    "sg:classifiers":[
        {
            "category":"Building & Trades",
            "subcategory":"Construction",
            "type":"Services"
        }
    ],
    "sg:phone":"+44 141 613 1909",
    "sg:postcode":"G73 2BS",
    "sg:province":"Glasgow City",
    "sg:tags":[
        "roofing",
        "contracting"
    ],
    "wof:name":"Bill Marshall Roughcasting",
    "wof:placetype":"venue"
},
  "geometry": {"coordinates":[-4.229025,55.821133],"type":"Point"}
}