{
  "type": "Feature",
  "properties": {
    "iso:country":"GB",
    "sg:address":"20 Edmondson Street",
    "sg:city":"Ulverston",
    "sg:classifiers":[
        {
            "category":"Food & Beverages",
            "subcategory":"Fruits & Vegetables",
            "type":"Retail Goods"
        }
    ],
    "sg:phone":"+44 1229 586746",
    "sg:postcode":"LA12 9AW",
    "sg:province":"Cumbria",
    "sg:tags":[
        "greengrocer"
    ],
    "wof:name":"T Coglan Stores & Off Licence",
    "wof:placetype":"venue"
},
  "geometry": {"coordinates":[-3.0853741169,54.1960754395],"type":"Point"}
}