{
  "type": "Feature",
  "properties": {
    "addr:full":"23 Bruton Street London Greater London W1J 6QD",
    "addr:housenumber":"23",
    "addr:postcode":"w1j 6qd",
    "addr:street":"Bruton Street",
    "iso:country":"GB",
    "sg:address":"23 Bruton Street",
    "sg:city":"London",
    "sg:classifiers":[
        {
            "category":"Banks & Credit Unions",
            "subcategory":"Investment Brokerage",
            "type":"Services"
        }
    ],
    "sg:phone":"+44 20 7629 1880",
    "sg:postcode":"W1J 6QD",
    "sg:province":"Greater London",
    "wof:name":"Gertler Properties Services Ltd.",
    "wof:placetype":"venue"
},
  "geometry": {"coordinates":[-0.1453830004,51.5103607178],"type":"Point"}
}