{
  "type": "Feature",
  "properties": {
    "iso:country":"GB",
    "sg:address":"19 Ainslie Place",
    "sg:city":"Edinburgh",
    "sg:classifiers":[
        {
            "category":"Banks & Credit Unions",
            "subcategory":"Financial Services",
            "type":"Services"
        }
    ],
    "sg:postcode":"EH3 6AU",
    "sg:province":"City of Edinburgh",
    "sg:tags":[
        "consultant"
    ],
    "wof:name":"Hbj Financial Services Ltd",
    "wof:placetype":"venue"
},
  "geometry": {"coordinates":[-3.2098259926,55.9528846741],"type":"Point"}
}