{
  "type": "Feature",
  "properties": {
    "iso:country":"GB",
    "sg:address":"Church Street, Twyford",
    "sg:city":"Buckingham",
    "sg:classifiers":[
        {
            "category":"Education",
            "subcategory":"School",
            "type":"Public Place"
        }
    ],
    "sg:phone":"+44 1296 730305",
    "sg:postcode":"MK18 4EU",
    "sg:province":"Buckinghamshire",
    "sg:tags":[
        "local",
        "authority"
    ],
    "wof:name":"Twyford C of E First School",
    "wof:placetype":"venue"
},
  "geometry": {"coordinates":[-1.034175992,51.9305458069],"type":"Point"}
}