{
  "type": "Feature",
  "properties": {
    "addr:full":"Threegates, Roseville Avenue Scarborough North Yorkshire YO12 7NS",
    "addr:postcode":"yo12 7ns",
    "addr:street":"Threegates Roseville Avenue",
    "iso:country":"GB",
    "sg:address":"Threegates, Roseville Avenue",
    "sg:city":"Scarborough",
    "sg:classifiers":[
        {
            "category":"Shopping",
            "subcategory":"Discount & Variety Stores",
            "type":"Retail Goods"
        }
    ],
    "sg:postcode":"YO12 7NS",
    "sg:province":"North Yorkshire",
    "sg:tags":[
        "cleaning",
        "supply"
    ],
    "wof:name":"Scarborough Disposible & Hygiene Products",
    "wof:placetype":"venue"
},
  "geometry": {"coordinates":[-0.42753,54.280506],"type":"Point"}
}