{
  "type": "Feature",
  "properties": {
    "addr:full":"30 Northfield Pla Aberdeen Aberdeen City AB25 1SD",
    "addr:housenumber":"30",
    "addr:postcode":"ab25 1sd",
    "addr:street":"Northfield Pla",
    "iso:country":"GB",
    "sg:address":"30 Northfield Pla",
    "sg:city":"Aberdeen",
    "sg:classifiers":[
        {
            "category":"Health Services",
            "subcategory":"Dentist",
            "type":"Services"
        }
    ],
    "sg:phone":"+44 1224 620488",
    "sg:postcode":"AB25 1SD",
    "sg:province":"Aberdeen City",
    "sg:tags":[
        "technician",
        "instrument",
        "dental"
    ],
    "wof:name":"Grampian Health Care",
    "wof:placetype":"venue"
},
  "geometry": {"coordinates":[-2.0984239578,57.1520957947],"type":"Point"}
}