{
  "type": "Feature",
  "properties": {
    "addr:full":"Unit 40c Riverdale Shopping Centre Lewisham Greater London SE13 7EP",
    "addr:housenumber":"unit 40c",
    "addr:postcode":"se13 7ep",
    "addr:street":"Shopping Centre",
    "iso:country":"GB",
    "sg:address":"Unit 40c Riverdale Shopping Centre",
    "sg:city":"Lewisham",
    "sg:classifiers":[
        {
            "category":"Shopping",
            "subcategory":"Computers & Home Electronics",
            "type":"Retail Goods"
        }
    ],
    "sg:phone":"+44 20 8297 1223",
    "sg:postcode":"SE13 7EP",
    "sg:province":"Greater London",
    "sg:tags":[
        "telephone"
    ],
    "wof:name":"BT",
    "wof:placetype":"venue"
},
  "geometry": {"coordinates":[-0.012449,51.4588356018],"type":"Point"}
}