{
  "type": "Feature",
  "properties": {
    "iso:country":"GB",
    "sg:address":"Laburnum Cott, Main St, Hoveringham",
    "sg:city":"Nottingham",
    "sg:classifiers":[
        {
            "category":"Building & Trades",
            "subcategory":"Construction",
            "type":"Services"
        }
    ],
    "sg:postcode":"NG14 7JR",
    "sg:province":"Nottinghamshire",
    "sg:tags":[
        "roofing"
    ],
    "wof:name":"Compass Maintenance Services Ltd",
    "wof:placetype":"venue"
},
  "geometry": {"coordinates":[-0.9672390223,53.0121650696],"type":"Point"}
}