{
  "type": "Feature",
  "properties": {
    "addr:full":"15 Church Road London Greater London W3 8PU",
    "addr:housenumber":"15",
    "addr:postcode":"w3 8pu",
    "addr:street":"Church Road",
    "iso:country":"GB",
    "sg:address":"15 Church Road",
    "sg:city":"London",
    "sg:classifiers":[
        {
            "category":"Food & Beverages",
            "subcategory":"Groceries & Convenience Stores",
            "type":"Retail Goods"
        }
    ],
    "sg:postcode":"W3 8PU",
    "sg:province":"Greater London",
    "wof:name":"Faini Supermarket",
    "wof:placetype":"venue"
},
  "geometry": {"coordinates":[-0.270972997,51.5068321228],"type":"Point"}
}