{
  "type": "Feature",
  "properties": {
    "iso:country":"GB",
    "sg:address":"5c Thorpe Way Industrial Estate",
    "sg:city":"Banbury",
    "sg:classifiers":[
        {
            "category":"Freight",
            "type":"Transportation"
        }
    ],
    "sg:phone":"+44 1295 256170",
    "sg:postcode":"OX17 2BZ",
    "sg:province":"Northamptonshire",
    "sg:tags":[
        "haulage",
        "road"
    ],
    "wof:name":"Allens Transport",
    "wof:placetype":"venue"
},
  "geometry": {"coordinates":[-1.281068,52.090488],"type":"Point"}
}