{
  "type": "Feature",
  "properties": {
    "iso:country":"GB",
    "sg:address":"71 Devonshire Road",
    "sg:city":"Bexhill-on-sea",
    "sg:classifiers":[
        {
            "category":"Shopping",
            "subcategory":"Discount & Variety Stores",
            "type":"Retail Goods"
        }
    ],
    "sg:phone":"+44 1424 212974",
    "sg:postcode":"TN40 1BD",
    "sg:province":"East Sussex",
    "sg:tags":[
        "centre"
    ],
    "wof:name":"Catalogue Shop",
    "wof:placetype":"venue"
},
  "geometry": {"coordinates":[0.474201,50.838146],"type":"Point"}
}