{
  "type": "Feature",
  "properties": {
    "iso:country":"GB",
    "sg:address":"7 Wyndham Street",
    "sg:city":"Bridgend",
    "sg:classifiers":[
        {
            "category":"Professional",
            "subcategory":"Lawyer & Legal Services",
            "type":"Services"
        }
    ],
    "sg:phone":"+44 1656 655755",
    "sg:postcode":"CF31 1ED",
    "sg:province":"Bridgend",
    "sg:tags":[
        "solicitor"
    ],
    "wof:name":"Jongmans",
    "wof:placetype":"venue"
},
  "geometry": {"coordinates":[-3.579174,51.507099],"type":"Point"}
}