{
  "type": "Feature",
  "properties": {
    "iso:country":"GB",
    "sg:address":"Unit 9 Southmill Trading Centre, Southmill Road",
    "sg:city":"Bishops Stortford",
    "sg:classifiers":[
        {
            "category":"Professional",
            "subcategory":"Printing & Photocopies",
            "type":"Services"
        }
    ],
    "sg:phone":"+44 1279 653675",
    "sg:postcode":"CM23 3DY",
    "sg:province":"Essex",
    "sg:tags":[
        "computer",
        "tag",
        "label"
    ],
    "wof:name":"Briben Products Ltd.",
    "wof:placetype":"venue"
},
  "geometry": {"coordinates":[0.1640360057,51.8641281128],"type":"Point"}
}