{
  "type": "Feature",
  "properties": {
    "addr:full":"Weir Cottage, Dunkirk Street, Aylsham Norwich Norfolk NR11 6SU",
    "addr:postcode":"nr11 6su",
    "addr:street":"Dunkirk Street;Norwich",
    "iso:country":"GB",
    "sg:address":"Weir Cottage, Dunkirk Street, Aylsham",
    "sg:city":"Norwich",
    "sg:classifiers":[
        {
            "category":"Transit Center",
            "subcategory":"Passenger",
            "type":"Transportation"
        },
        {
            "category":"Retail",
            "subcategory":"Pet Boarding",
            "type":"Services"
        }
    ],
    "sg:phone":"+44 1263 732712",
    "sg:postcode":"NR11 6SU",
    "sg:province":"Norfolk",
    "sg:tags":[
        "kennel",
        "catteries"
    ],
    "wof:name":"A B C Aylsham Boarding Cattery",
    "wof:placetype":"venue"
},
  "geometry": {"coordinates":[1.2503540516,52.7950668335],"type":"Point"}
}