{
  "type": "Feature",
  "properties": {
    "addr:full":"Loxley Manor, Loxley Road, Loxley Sheffield South Yorkshire S6 6RW",
    "addr:postcode":"s6 6rw",
    "addr:street":"Loxley Road",
    "iso:country":"GB",
    "sg:address":"Loxley Manor, Loxley Road, Loxley",
    "sg:city":"Sheffield",
    "sg:classifiers":[
        {
            "category":"Building & Trades",
            "subcategory":"Construction",
            "type":"Services"
        }
    ],
    "sg:phone":"+44 114 251 7702",
    "sg:postcode":"S6 6RW",
    "sg:province":"South Yorkshire",
    "sg:tags":[
        "demolition",
        "contractor"
    ],
    "wof:name":"Euro Dismantling Services Ltd.",
    "wof:placetype":"venue"
},
  "geometry": {"coordinates":[-1.542106,53.40527],"type":"Point"}
}