{
  "type": "Feature",
  "properties": {
    "addr:full":"Franklin Mt Harrogate North Yorkshire HG1 5EJ",
    "addr:postcode":"hg1 5ej",
    "addr:street":"Mt",
    "iso:country":"GB",
    "sg:address":"Franklin Mt",
    "sg:city":"Harrogate",
    "sg:classifiers":[
        {
            "category":"Restaurant",
            "type":"Food & Drink"
        }
    ],
    "sg:phone":"+44 1423 705805",
    "sg:postcode":"HG1 5EJ",
    "sg:province":"North Yorkshire",
    "wof:name":"Villu Toots",
    "wof:placetype":"venue"
},
  "geometry": {"coordinates":[-1.539389,53.999603],"type":"Point"}
}