{
  "type": "Feature",
  "properties": {
    "addr:full":"Forte Posthouse, 500 Saxon Gate West, Central Milton Keynes Milton Keynes Buckinghamshire MK9 2HQ",
    "addr:housenumber":"500",
    "addr:postcode":"mk9 2hq",
    "addr:street":"Saxon Gate West",
    "iso:country":"GB",
    "sg:address":"Forte Posthouse, 500 Saxon Gate West, Central Milton Keynes",
    "sg:city":"Milton Keynes",
    "sg:classifiers":[
        {
            "category":"Sports & Exercise",
            "subcategory":"Gym",
            "type":"Entertainment"
        }
    ],
    "sg:phone":"+44 1908 231381",
    "sg:postcode":"MK9 2HQ",
    "sg:province":"Buckinghamshire",
    "sg:tags":[
        "fitness",
        "health",
        "centre"
    ],
    "wof:name":"Forte Spa Health & Leisure Club",
    "wof:placetype":"venue"
},
  "geometry": {"coordinates":[-0.75862,52.039249],"type":"Point"}
}