{
  "type": "Feature",
  "properties": {
    "addr:full":"60 Victoria Road West Thornton-cleveleys Lancashire FY5 1AG",
    "addr:housenumber":"60",
    "addr:postcode":"fy5 1ag",
    "addr:street":"Victoria Road West Thornton-Cleveleys",
    "iso:country":"GB",
    "sg:address":"60 Victoria Road West",
    "sg:city":"Thornton-cleveleys",
    "sg:classifiers":[
        {
            "category":"Food & Beverages",
            "subcategory":"Meat & Fish",
            "type":"Retail Goods"
        }
    ],
    "sg:phone":"+44 1253 853087",
    "sg:postcode":"FY5 1AG",
    "sg:province":"Lancashire",
    "sg:tags":[
        "butcher"
    ],
    "wof:name":"J Grime & Sons Ltd",
    "wof:placetype":"venue"
},
  "geometry": {"coordinates":[-3.0432240963,53.8772888184],"type":"Point"}
}