{
  "type": "Feature",
  "properties": {
    "addr:full":"2 Baches Street London Greater London N1 6UB",
    "addr:housenumber":"2",
    "addr:postcode":"n1 6ub",
    "addr:street":"Baches Street",
    "iso:country":"GB",
    "sg:address":"2 Baches Street",
    "sg:city":"London",
    "sg:classifiers":[
        {
            "category":"Retail",
            "subcategory":"Driving School",
            "type":"Services"
        }
    ],
    "sg:postcode":"N1 6UB",
    "sg:province":"Greater London",
    "wof:name":"Skillplace Training Limited",
    "wof:placetype":"venue"
},
  "geometry": {"coordinates":[-0.0854939967,51.5275497437],"type":"Point"}
}