{
  "type": "Feature",
  "properties": {
    "addr:full":"Ryefield, Main St Evesham Gloucestershire WR11 4UE",
    "addr:postcode":"wr11 4ue",
    "addr:street":"Main St",
    "iso:country":"GB",
    "sg:address":"Ryefield, Main St",
    "sg:city":"Evesham",
    "sg:classifiers":[
        {
            "category":"Professional",
            "type":"Services"
        }
    ],
    "sg:phone":"+44 1386 871303",
    "sg:postcode":"WR11 4UE",
    "sg:province":"Gloucestershire",
    "sg:tags":[
        "display",
        "maker"
    ],
    "wof:name":"Moving Displays",
    "wof:placetype":"venue"
},
  "geometry": {"coordinates":[-1.943969,52.106392],"type":"Point"}
}