{
  "type": "Feature",
  "properties": {
    "iso:country":"GB",
    "sg:address":"81 Belsize Park Gardens",
    "sg:city":"London",
    "sg:classifiers":[
        {
            "category":"Personal",
            "subcategory":"Sauna",
            "type":"Services"
        }
    ],
    "sg:phone":"+44 20 7483 6800",
    "sg:postcode":"NW3 4NJ",
    "sg:province":"Greater London",
    "wof:name":"Lingfield Health Club Hampstead",
    "wof:placetype":"venue"
},
  "geometry": {"coordinates":[-0.16419,51.54652],"type":"Point"}
}