{
  "type": "Feature",
  "properties": {
    "addr:full":"Stobbcross Farm, Stobb Cross Rd Ferryhill Durham DL17 9HB",
    "addr:postcode":"dl17 9hb",
    "addr:street":"Stobb Cross Rd",
    "iso:country":"GB",
    "sg:address":"Stobbcross Farm, Stobb Cross Rd",
    "sg:city":"Ferryhill",
    "sg:classifiers":[
        {
            "category":"Farming",
            "subcategory":"Livestock Farm",
            "type":"Manufacturing & Wholesale Goods"
        }
    ],
    "sg:phone":"+44 1740 654279",
    "sg:postcode":"DL17 9HB",
    "sg:province":"Durham",
    "sg:tags":[
        "others"
    ],
    "wof:name":"J M Willans",
    "wof:placetype":"venue"
},
  "geometry": {"coordinates":[-1.5180239677,54.6988716125],"type":"Point"}
}