{
  "type": "Feature",
  "properties": {
    "addr:full":"9 Allandale Road, Stoneygate Leicester Leicestershire LE2 2DA",
    "addr:housenumber":"9",
    "addr:postcode":"le2 2da",
    "addr:street":"Allandale Road",
    "iso:country":"GB",
    "sg:address":"9 Allandale Road, Stoneygate",
    "sg:city":"Leicester",
    "sg:classifiers":[
        {
            "category":"Shopping",
            "subcategory":"Gifts & Souvenirs",
            "type":"Retail Goods"
        }
    ],
    "sg:postcode":"LE2 2DA",
    "sg:province":"Leicestershire",
    "sg:tags":[
        "shop"
    ],
    "wof:name":"Artifact",
    "wof:placetype":"venue"
},
  "geometry": {"coordinates":[-1.1003799438,52.6167030334],"type":"Point"}
}