{
  "type": "Feature",
  "properties": {
    "addr:full":"Unit 2 Bayford Indstl Est, Bayford St, Hackney London Greater London E8 3SE",
    "addr:housenumber":"unit 2",
    "addr:postcode":"e8 3se",
    "addr:street":"Indstl;St",
    "iso:country":"GB",
    "sg:address":"Unit 2 Bayford Indstl Est, Bayford St, Hackney",
    "sg:city":"London",
    "sg:classifiers":[
        {
            "category":"Shopping",
            "subcategory":"Stationery & Office Supplies",
            "type":"Retail Goods"
        }
    ],
    "sg:phone":"+44 20 8986 6072",
    "sg:postcode":"E8 3SE",
    "sg:province":"Greater London",
    "sg:tags":[
        "printers'"
    ],
    "wof:name":"Graphic Scanning Ltd",
    "wof:placetype":"venue"
},
  "geometry": {"coordinates":[-0.05654,51.53973],"type":"Point"}
}