{
  "type": "Feature",
  "properties": {
    "addr:full":"Tokyngton Avenue Wembley Greater London HA9 6HT",
    "addr:postcode":"ha9 6ht",
    "addr:street":"Tokyngton Avenue",
    "iso:country":"GB",
    "sg:address":"Tokyngton Avenue",
    "sg:city":"Wembley",
    "sg:classifiers":[
        {
            "category":"Education",
            "subcategory":"School",
            "type":"Public Place"
        }
    ],
    "sg:phone":"+44 20 8902 8003",
    "sg:postcode":"HA9 6HT",
    "sg:province":"Greater London",
    "sg:tags":[
        "local",
        "authority"
    ],
    "wof:name":"Elsley County Primary School",
    "wof:placetype":"venue"
},
  "geometry": {"coordinates":[-0.283119,51.54887],"type":"Point"}
}