{
  "type": "Feature",
  "properties": {
    "iso:country":"GB",
    "sg:address":"25 Sycamores, Dacre Av",
    "sg:city":"South Ockendon",
    "sg:classifiers":[
        {
            "category":"Government",
            "subcategory":"Office",
            "type":"Public Place"
        }
    ],
    "sg:phone":"+44 1708 864776",
    "sg:postcode":"RM15 4TH",
    "sg:province":"Essex",
    "sg:tags":[
        "local"
    ],
    "wof:name":"Sycamores Sheltered Housing",
    "wof:placetype":"venue"
},
  "geometry": {"coordinates":[0.28365,51.502476],"type":"Point"}
}