{
  "type": "Feature",
  "properties": {
    "addr:full":"423-425 Caledonian Rd Holloway Greater London N7 9BQ",
    "addr:housenumber":"423-425",
    "addr:postcode":"n7 9bq",
    "addr:street":"Caledonian Rd",
    "iso:country":"GB",
    "sg:address":"423-425 Caledonian Rd",
    "sg:city":"Holloway",
    "sg:classifiers":[
        {
            "category":"Professional",
            "subcategory":"Business Services",
            "type":"Services"
        }
    ],
    "sg:phone":"+44 20 7607 4335",
    "sg:postcode":"N7 9BQ",
    "sg:province":"Greater London",
    "sg:tags":[
        "distribution"
    ],
    "wof:name":"A P B UK Ltd",
    "wof:placetype":"venue"
},
  "geometry": {"coordinates":[-0.117765,51.546257],"type":"Point"}
}