{
  "type": "Feature",
  "properties": {
    "iso:country":"GB",
    "sg:address":"Sherman Clo, Gillingham Business Pk",
    "sg:city":"Gillingham",
    "sg:classifiers":[
        {
            "category":"Autos & Motor Vehicles",
            "subcategory":"Fuel & Gas Station",
            "type":"Retail Goods"
        }
    ],
    "sg:phone":"+44 1634 377661",
    "sg:postcode":"ME8 0PP",
    "sg:province":"Kent",
    "sg:tags":[
        "injection"
    ],
    "wof:name":"Lucas Automotive Ltd",
    "wof:placetype":"venue"
},
  "geometry": {"coordinates":[0.578097,51.367523],"type":"Point"}
}