{
  "type": "Feature",
  "properties": {
    "iso:country":"GB",
    "sg:address":"Blackhorse Road",
    "sg:city":"Woking",
    "sg:classifiers":[
        {
            "category":"Health Services",
            "subcategory":"Health Practitioner",
            "type":"Services"
        }
    ],
    "sg:postcode":"GU22 0RE",
    "sg:province":"Surrey",
    "sg:tags":[
        "psychotherapist"
    ],
    "wof:name":"Gateways Centre",
    "wof:placetype":"venue"
},
  "geometry": {"coordinates":[-0.613488,51.306477],"type":"Point"}
}