{
  "type": "Feature",
  "properties": {
    "addr:full":"38 Bedford Square London Greater London WC1B 3EL",
    "addr:housenumber":"38",
    "addr:postcode":"wc1b 3el",
    "addr:street":"Bedford Square",
    "iso:country":"GB",
    "sg:address":"38 Bedford Square",
    "sg:city":"London",
    "sg:classifiers":[
        {
            "category":"Real Estate",
            "subcategory":"Developer",
            "type":"Services"
        }
    ],
    "sg:phone":"+44 20 7667 6005",
    "sg:postcode":"WC1B 3EL",
    "sg:province":"Greater London",
    "sg:tags":[
        "property"
    ],
    "wof:name":"Airminster Ltd.",
    "wof:placetype":"venue"
},
  "geometry": {"coordinates":[-0.13059,51.518078],"type":"Point"}
}