{
  "type": "Feature",
  "properties": {
    "iso:country":"GB",
    "sg:address":"210 Broomhill Road, Brislington",
    "sg:city":"Bristol",
    "sg:classifiers":[
        {
            "category":"Shopping",
            "subcategory":"Crafts & Fabrics",
            "type":"Retail Goods"
        }
    ],
    "sg:phone":"+44 117 972 3322",
    "sg:postcode":"BS4 4TU",
    "sg:province":"City of Bristol",
    "sg:tags":[
        "boiler"
    ],
    "wof:name":"Fulton Boiler Works (Great Britain) Ltd.",
    "wof:placetype":"venue"
},
  "geometry": {"coordinates":[-2.532676,51.437397],"type":"Point"}
}