{
  "type": "Feature",
  "properties": {
    "addr:full":"360 Goldington Road Bedford Bedfordshire MK41 9NS",
    "addr:housenumber":"360",
    "addr:postcode":"mk41 9ns",
    "addr:street":"Goldington Road",
    "iso:country":"GB",
    "sg:address":"360 Goldington Road",
    "sg:city":"Bedford",
    "sg:classifiers":[
        {
            "category":"Shopping",
            "subcategory":"Department Store",
            "type":"Retail Goods"
        }
    ],
    "sg:postcode":"MK41 9NS",
    "sg:province":"Bedfordshire",
    "wof:name":"Goldington General Store",
    "wof:placetype":"venue"
},
  "geometry": {"coordinates":[-0.438204,52.141232],"type":"Point"}
}