{
  "type": "Feature",
  "properties": {
    "addr:full":"1 Stoney Street, Hockley Nottingham Nottinghamshire NG1 1LG",
    "addr:housenumber":"1",
    "addr:postcode":"ng1 1lg",
    "addr:street":"Stoney Street Hockley",
    "iso:country":"GB",
    "sg:address":"1 Stoney Street, Hockley",
    "sg:city":"Nottingham",
    "sg:classifiers":[
        {
            "category":"Personal",
            "subcategory":"Beauty Salon",
            "type":"Services"
        }
    ],
    "sg:phone":"+44 115 948 4377",
    "sg:postcode":"NG1 1LG",
    "sg:province":"Nottinghamshire",
    "sg:tags":[
        "unisex",
        "hairdresser"
    ],
    "wof:name":"Arena Hair Studio",
    "wof:placetype":"venue"
},
  "geometry": {"coordinates":[-1.1433370113,52.9531745911],"type":"Point"}
}