{
  "type": "Feature",
  "properties": {
    "addr:full":"92 High Road West Byfleet Surrey KT14 7QT",
    "addr:housenumber":"92",
    "addr:postcode":"kt14 7qt",
    "addr:street":"High Road West",
    "iso:country":"GB",
    "sg:address":"92 High Road",
    "sg:city":"West Byfleet",
    "sg:classifiers":[
        {
            "category":"Fast Food",
            "type":"Food & Drink"
        }
    ],
    "sg:phone":"+44 1932 340155",
    "sg:postcode":"KT14 7QT",
    "sg:province":"Surrey",
    "sg:tags":[
        "away",
        "take"
    ],
    "wof:name":"Honey Fountain",
    "wof:placetype":"venue"
},
  "geometry": {"coordinates":[-0.474962,51.338829],"type":"Point"}
}