{
  "type": "Feature",
  "properties": {
    "iso:country":"GB",
    "sg:address":"The Cottage, 21 Pine Gro",
    "sg:city":"Edenbridge",
    "sg:classifiers":[
        {
            "category":"Building & Trades",
            "subcategory":"Construction",
            "type":"Services"
        }
    ],
    "sg:phone":"+44 1732 868120",
    "sg:postcode":"TN8 5HU",
    "sg:province":"East Sussex",
    "sg:tags":[
        "restoration",
        "refurbishment"
    ],
    "wof:name":"Southern Office Environments",
    "wof:placetype":"venue"
},
  "geometry": {"coordinates":[0.06374,51.195011],"type":"Point"}
}