{
  "type": "Feature",
  "properties": {
    "iso:country":"GB",
    "sg:address":"27 Grazebrook Croft, Bartley Green",
    "sg:city":"Birmingham",
    "sg:classifiers":[
        {
            "category":"Home & Garden",
            "subcategory":"Carpets & Floor Coverings",
            "type":"Retail Goods"
        }
    ],
    "sg:phone":"+44 121 475 8980",
    "sg:postcode":"B32 3NL",
    "sg:province":"West Midlands",
    "sg:tags":[
        "carpets",
        "rug",
        "matting"
    ],
    "wof:name":"John Wright",
    "wof:placetype":"venue"
},
  "geometry": {"coordinates":[-1.9927910566,52.4352836609],"type":"Point"}
}