{
  "type": "Feature",
  "properties": {
    "iso:country":"GB",
    "sg:address":"4a Mosshead Road, Bearsden",
    "sg:city":"Glasgow",
    "sg:classifiers":[
        {
            "category":"Personal",
            "subcategory":"Beauty Salon",
            "type":"Services"
        },
        {
            "category":"Personal",
            "subcategory":"Barber",
            "type":"Services"
        }
    ],
    "sg:phone":"+44 141 942 2777",
    "sg:postcode":"G61 3EP",
    "sg:province":"East Dunbartonshire",
    "sg:tags":[
        "unisex",
        "hairdresser"
    ],
    "wof:name":"Diva",
    "wof:placetype":"venue"
},
  "geometry": {"coordinates":[-4.3168230057,55.9303436279],"type":"Point"}
}