{
  "type": "Feature",
  "properties": {
    "iso:country":"GB",
    "sg:address":"104 Ninfield Road",
    "sg:city":"Bexhill-on-sea",
    "sg:classifiers":[
        {
            "category":"Home & Garden",
            "subcategory":"Home Furnishings",
            "type":"Retail Goods"
        }
    ],
    "sg:phone":"+44 1424 730706",
    "sg:postcode":"TN39 5BB",
    "sg:province":"East Sussex",
    "sg:tags":[
        "furnishers",
        "planner",
        "kitchen"
    ],
    "wof:name":"R & R Kitchens",
    "wof:placetype":"venue"
},
  "geometry": {"coordinates":[0.469447,50.856873],"type":"Point"}
}