{
  "type": "Feature",
  "properties": {
    "iso:country":"GB",
    "sg:address":"14-17 Wells Street",
    "sg:city":"London",
    "sg:classifiers":[
        {
            "category":"Communications",
            "type":"Services"
        }
    ],
    "sg:phone":"+44 20 7323 6603",
    "sg:postcode":"W1T 3PG",
    "sg:province":"Greater London",
    "sg:tags":[
        "audio-visual"
    ],
    "wof:name":"Film Development Corporation Ltd.",
    "wof:placetype":"venue"
},
  "geometry": {"coordinates":[-0.137594,51.5172],"type":"Point"}
}