{
  "type": "Feature",
  "properties": {
    "addr:full":"Rear Of 247 London Road Romford Essex RM7 9NB",
    "addr:postcode":"rm7 9nb",
    "addr:street":"London Road",
    "iso:country":"GB",
    "sg:address":"Rear Of 247 London Road",
    "sg:city":"Romford",
    "sg:classifiers":[
        {
            "category":"Retail",
            "subcategory":"Auto Repair",
            "type":"Services"
        }
    ],
    "sg:phone":"+44 1708 556892",
    "sg:postcode":"RM7 9NB",
    "sg:province":"Essex",
    "sg:tags":[
        "modification",
        "garage"
    ],
    "wof:name":"Ken Hunte Auto Servicing",
    "wof:placetype":"venue"
},
  "geometry": {"coordinates":[0.16279,51.574539],"type":"Point"}
}