{
  "type": "Feature",
  "properties": {
    "iso:country":"GB",
    "sg:address":"2 Woodbury Road",
    "sg:city":"Stockport",
    "sg:classifiers":[
        {
            "category":"Shopping",
            "subcategory":"Computers & Home Electronics",
            "type":"Retail Goods"
        }
    ],
    "sg:phone":"+44 161 428 4191",
    "sg:postcode":"SK3 0SF",
    "sg:province":"Cheshire",
    "sg:tags":[
        "aerial",
        "television",
        "radio"
    ],
    "wof:name":"Howards Aerials (Stockport)",
    "wof:placetype":"venue"
},
  "geometry": {"coordinates":[-2.1872620583,53.3984375],"type":"Point"}
}