{
  "type": "Feature",
  "properties": {
    "iso:country":"GB",
    "sg:address":"Unit E, Sams Lane",
    "sg:city":"West Bromwich",
    "sg:classifiers":[
        {
            "category":"Professional",
            "subcategory":"Printing & Photocopies",
            "type":"Services"
        }
    ],
    "sg:phone":"+44 121 553 2751",
    "sg:postcode":"B70 7EG",
    "sg:province":"West Midlands",
    "sg:tags":[
        "engraving"
    ],
    "wof:name":"Insignia Fabrications",
    "wof:placetype":"venue"
},
  "geometry": {"coordinates":[-1.990224,52.518623],"type":"Point"}
}