{
  "type": "Feature",
  "properties": {
    "iso:country":"GB",
    "sg:address":"1 Holly Grange, Holly Lane, Balsall Common",
    "sg:city":"Coventry",
    "sg:classifiers":[
        {
            "category":"Professional",
            "subcategory":"Employment Agencies",
            "type":"Services"
        }
    ],
    "sg:postcode":"CV7 7EB",
    "sg:province":"Warwickshire",
    "sg:tags":[
        "consultant"
    ],
    "wof:name":"121 Employee Share Trustee Ltd",
    "wof:placetype":"venue"
},
  "geometry": {"coordinates":[-1.650802,52.383141],"type":"Point"}
}