{
  "type": "Feature",
  "properties": {
    "addr:full":"91a London Rd High Wycombe Buckinghamshire HP11 1BU",
    "addr:housenumber":"91a",
    "addr:postcode":"hp11 1bu",
    "addr:street":"London Rd",
    "iso:country":"GB",
    "sg:address":"91a London Rd",
    "sg:city":"High Wycombe",
    "sg:classifiers":[
        {
            "category":"Professional",
            "subcategory":"Employment Agencies",
            "type":"Services"
        }
    ],
    "sg:phone":"+44 1494 471471",
    "sg:postcode":"HP11 1BU",
    "sg:province":"Buckinghamshire",
    "sg:tags":[
        "consultant"
    ],
    "wof:name":"R T C Medical Recruitment Ltd",
    "wof:placetype":"venue"
},
  "geometry": {"coordinates":[-0.736647,51.625595],"type":"Point"}
}