{
  "type": "Feature",
  "properties": {
    "iso:country":"GB",
    "sg:address":"Sunny Mount, Sturton Road, South Wheatley",
    "sg:city":"Retford",
    "sg:classifiers":[
        {
            "category":"Farming",
            "subcategory":"Livestock Farm",
            "type":"Manufacturing & Wholesale Goods"
        }
    ],
    "sg:phone":"+44 1427 880654",
    "sg:postcode":"DN22 9DH",
    "sg:province":"Nottinghamshire",
    "sg:tags":[
        "others"
    ],
    "wof:name":"E Ashton & Sons",
    "wof:placetype":"venue"
},
  "geometry": {"coordinates":[-0.852971,53.360855],"type":"Point"}
}