{
  "type": "Feature",
  "properties": {
    "iso:country":"GB",
    "sg:address":"2 Buckingham Place, Downend",
    "sg:city":"Bristol",
    "sg:classifiers":[
        {
            "category":"Organizations",
            "subcategory":"Community Association",
            "type":"Services"
        }
    ],
    "sg:postcode":"BS16 5TN",
    "sg:province":"City of Bristol",
    "sg:tags":[
        "society",
        "housing"
    ],
    "wof:name":"Magna Housing Association Ltd.",
    "wof:placetype":"venue"
},
  "geometry": {"coordinates":[-2.501879,51.487186],"type":"Point"}
}