{
  "type": "Feature",
  "properties": {
    "iso:country":"GB",
    "sg:address":"Willow Road, Pakefield",
    "sg:city":"Lowestoft",
    "sg:classifiers":[
        {
            "category":"Retail",
            "subcategory":"Storage",
            "type":"Services"
        }
    ],
    "sg:postcode":"NR33 7BJ",
    "sg:province":"Suffolk",
    "sg:tags":[
        "household",
        "removal"
    ],
    "wof:name":"Waveney Removals & Storage",
    "wof:placetype":"venue"
},
  "geometry": {"coordinates":[1.728509,52.446995],"type":"Point"}
}