{
  "type": "Feature",
  "properties": {
    "addr:full":"12 De Montfort Parade, Streatham High Road London Greater London SW16 1BU",
    "addr:postcode":"sw16 1bu",
    "addr:street":"12 De Montfort Parade;High Road",
    "iso:country":"GB",
    "sg:address":"12 De Montfort Parade, Streatham High Road",
    "sg:city":"London",
    "sg:classifiers":[
        {
            "category":"Sports & Exercise",
            "subcategory":"Playing Field",
            "type":"Entertainment"
        }
    ],
    "sg:phone":"+44 20 8677 5333",
    "sg:postcode":"SW16 1BU",
    "sg:province":"Greater London",
    "sg:tags":[
        "ticket",
        "agency",
        "airline"
    ],
    "wof:name":"Angel Travel Ltd.",
    "wof:placetype":"venue"
},
  "geometry": {"coordinates":[-0.130649,51.437378],"type":"Point"}
}