{
  "type": "Feature",
  "properties": {
    "iso:country":"GB",
    "sg:address":"Waterman House, 41 Kingsway",
    "sg:city":"London",
    "sg:classifiers":[
        {
            "category":"Professional",
            "subcategory":"Computer Services",
            "type":"Services"
        }
    ],
    "sg:phone":"+44 20 7497 5511",
    "sg:postcode":"WC2B 6TP",
    "sg:province":"Greater London",
    "sg:tags":[
        "system",
        "software"
    ],
    "wof:name":"Icsa Software International Ltd.",
    "wof:placetype":"venue"
},
  "geometry": {"coordinates":[-0.118685998,51.5146408081],"type":"Point"}
}