{
  "type": "Feature",
  "properties": {
    "iso:country":"GB",
    "sg:address":"Ludlow Hill Road, West Bridgford",
    "sg:city":"Nottingham",
    "sg:classifiers":[
        {
            "category":"Retail",
            "subcategory":"Auto Repair",
            "type":"Services"
        }
    ],
    "sg:phone":"+44 115 923 5044",
    "sg:postcode":"NG2 6HF",
    "sg:province":"Nottinghamshire",
    "sg:tags":[
        "modification",
        "garage"
    ],
    "wof:name":"Avenue Garage",
    "wof:placetype":"venue"
},
  "geometry": {"coordinates":[-1.1268049479,52.9212150574],"type":"Point"}
}