{
  "type": "Feature",
  "properties": {
    "iso:country":"GB",
    "sg:address":"459 London Road",
    "sg:city":"Westcliff-on-sea",
    "sg:classifiers":[
        {
            "category":"Autos & Motor Vehicles",
            "subcategory":"Automobile Sales",
            "type":"Retail Goods"
        }
    ],
    "sg:phone":"+44 1702 339630",
    "sg:postcode":"SS0 9LG",
    "sg:province":"Essex",
    "sg:tags":[
        "car"
    ],
    "wof:name":"Currie Motors Southend Ltd.",
    "wof:placetype":"venue"
},
  "geometry": {"coordinates":[0.691103,51.544163],"type":"Point"}
}