{
  "type": "Feature",
  "properties": {
    "addr:full":"Day House Farm, Nobold Shrewsbury Shropshire SY5 8NL",
    "addr:postcode":"sy5 8nl",
    "addr:street":"Nobold",
    "iso:country":"GB",
    "sg:address":"Day House Farm, Nobold",
    "sg:city":"Shrewsbury",
    "sg:classifiers":[
        {
            "category":"Farming",
            "subcategory":"Livestock Farm",
            "type":"Manufacturing & Wholesale Goods"
        }
    ],
    "sg:postcode":"SY5 8NL",
    "sg:province":"Shropshire",
    "sg:tags":[
        "others"
    ],
    "wof:name":"T H Roberts & Sons",
    "wof:placetype":"venue"
},
  "geometry": {"coordinates":[-2.7840890884,52.6946144104],"type":"Point"}
}