{
  "type": "Feature",
  "properties": {
    "addr:full":"172a Bdwy Bexleyheath Kent DA6 7BS",
    "addr:housenumber":"172a",
    "addr:postcode":"da6 7bs",
    "addr:street":"Bdwy Bexleyheath",
    "iso:country":"GB",
    "sg:address":"172a Bdwy",
    "sg:city":"Bexleyheath",
    "sg:classifiers":[
        {
            "category":"Real Estate",
            "subcategory":"Real Estate Agent",
            "type":"Services"
        }
    ],
    "sg:phone":"+44 20 8303 3531",
    "sg:postcode":"DA6 7BS",
    "sg:province":"Kent",
    "wof:name":"Your-Move Co. U K Ltd.",
    "wof:placetype":"venue"
},
  "geometry": {"coordinates":[0.1412249953,51.4572486877],"type":"Point"}
}