{
  "type": "Feature",
  "properties": {
    "iso:country":"GB",
    "sg:address":"33 Loudoun Street",
    "sg:city":"Mauchline",
    "sg:classifiers":[
        {
            "category":"Communications",
            "type":"Services"
        }
    ],
    "sg:phone":"+44 1290 550067",
    "sg:postcode":"KA5 5BE",
    "sg:province":"East Ayrshire",
    "sg:tags":[
        "tv",
        "video",
        "radio"
    ],
    "wof:name":"Robert Gordon",
    "wof:placetype":"venue"
},
  "geometry": {"coordinates":[-4.380541,55.515263],"type":"Point"}
}