{
  "type": "Feature",
  "properties": {
    "addr:full":"24 Gordon Rd, West Bridgford Nottingham Nottinghamshire NG2 5LN",
    "addr:housenumber":"24",
    "addr:postcode":"ng2 5ln",
    "addr:street":"Gordon Rd",
    "iso:country":"GB",
    "sg:address":"24 Gordon Rd, West Bridgford",
    "sg:city":"Nottingham",
    "sg:classifiers":[
        {
            "category":"Food & Beverages",
            "subcategory":"Bakery",
            "type":"Retail Goods"
        }
    ],
    "sg:postcode":"NG2 5LN",
    "sg:province":"Nottinghamshire",
    "sg:tags":[
        "baker"
    ],
    "wof:name":"Smiths Bakery",
    "wof:placetype":"venue"
},
  "geometry": {"coordinates":[-1.125494,52.929848],"type":"Point"}
}