{
  "type": "Feature",
  "properties": {
    "iso:country":"GB",
    "sg:address":"80 Denmark Villas",
    "sg:city":"Hove",
    "sg:classifiers":[
        {
            "category":"Building & Trades",
            "subcategory":"Construction",
            "type":"Services"
        }
    ],
    "sg:phone":"+44 1273 328712",
    "sg:postcode":"BN3 3TJ",
    "sg:province":"East Sussex",
    "sg:tags":[
        "decorator",
        "painter"
    ],
    "wof:name":"Ace Traditional Decorators",
    "wof:placetype":"venue"
},
  "geometry": {"coordinates":[-0.169377,50.834415],"type":"Point"}
}