{
  "type": "Feature",
  "properties": {
    "addr:full":"Compass House, Compass Road Cardiff Cardiff CF10 4LT",
    "addr:postcode":"cf10 4lt",
    "addr:street":"Compass Road",
    "iso:country":"GB",
    "sg:address":"Compass House, Compass Road",
    "sg:city":"Cardiff",
    "sg:classifiers":[
        {
            "category":"Freight",
            "type":"Transportation"
        }
    ],
    "sg:phone":"+44 29 2045 5419",
    "sg:postcode":"CF10 4LT",
    "sg:province":"Cardiff",
    "sg:tags":[
        "haulage",
        "road",
        "forwarders"
    ],
    "wof:name":"Castle Services (Group)",
    "wof:placetype":"venue"
},
  "geometry": {"coordinates":[-3.153158,51.46339],"type":"Point"}
}