{
  "type": "Feature",
  "properties": {
    "iso:country":"GB",
    "sg:address":"381-383a Barking Rd, Newham",
    "sg:city":"Plaistow",
    "sg:classifiers":[
        {
            "category":"Utilities",
            "type":"Services"
        }
    ],
    "sg:phone":"+44 20 7476 4026",
    "sg:postcode":"E13 8AL",
    "sg:province":"Greater London",
    "sg:tags":[
        "internet"
    ],
    "wof:name":"Network P.C World Ltd",
    "wof:placetype":"venue"
},
  "geometry": {"coordinates":[0.023259,51.52272],"type":"Point"}
}