{
  "type": "Feature",
  "properties": {
    "addr:full":"25 Zouch Avenue Tidworth Hampshire SP9 7LP",
    "addr:housenumber":"25",
    "addr:postcode":"sp9 7lp",
    "addr:street":"Zouch Avenue",
    "iso:country":"GB",
    "sg:address":"25 Zouch Avenue",
    "sg:city":"Tidworth",
    "sg:classifiers":[
        {
            "category":"Recreation",
            "subcategory":"Dog Park",
            "type":"Entertainment"
        }
    ],
    "sg:postcode":"SP9 7LP",
    "sg:province":"Hampshire",
    "wof:name":"L C Wiltshire",
    "wof:placetype":"venue"
},
  "geometry": {"coordinates":[-1.670045,51.243538],"type":"Point"}
}