{
  "type": "Feature",
  "properties": {
    "addr:full":"Wheelers Rise, Croughton Brackley Buckinghamshire NN13 5ND",
    "addr:postcode":"nn13 5nd",
    "addr:street":"Wheelers Rise",
    "iso:country":"GB",
    "sg:address":"Wheelers Rise, Croughton",
    "sg:city":"Brackley",
    "sg:classifiers":[
        {
            "category":"Retail",
            "subcategory":"Auto Repair",
            "type":"Services"
        }
    ],
    "sg:postcode":"NN13 5ND",
    "sg:province":"Buckinghamshire",
    "sg:tags":[
        "modification",
        "garage"
    ],
    "wof:name":"M & G Garage",
    "wof:placetype":"venue"
},
  "geometry": {"coordinates":[-1.207046032,51.9983291626],"type":"Point"}
}