{
  "type": "Feature",
  "properties": {
    "addr:full":"22 Carlisle Rd Colindale Greater London NW9 0HP",
    "addr:housenumber":"22",
    "addr:postcode":"nw9 0hp",
    "addr:street":"Carlisle Rd",
    "iso:country":"GB",
    "sg:address":"22 Carlisle Rd",
    "sg:city":"Colindale",
    "sg:classifiers":[
        {
            "category":"Autos & Motor Vehicles",
            "subcategory":"Fuel & Gas Station",
            "type":"Retail Goods"
        }
    ],
    "sg:phone":"+44 20 8200 6363",
    "sg:postcode":"NW9 0HP",
    "sg:province":"Greater London",
    "sg:tags":[
        "injection"
    ],
    "wof:name":"Leyland Auto Southern",
    "wof:placetype":"venue"
},
  "geometry": {"coordinates":[-0.263725,51.595802],"type":"Point"}
}