{
  "type": "Feature",
  "properties": {
    "iso:country":"GB",
    "sg:address":"Oakdale Coach Ho, 16 Page Heath La",
    "sg:city":"Bromley",
    "sg:classifiers":[
        {
            "category":"Wholesale",
            "subcategory":"Books, Periodicals, & Newspapers",
            "type":"Manufacturing & Wholesale Goods"
        }
    ],
    "sg:phone":"+44 20 8313 1390",
    "sg:postcode":"BR1 2DS",
    "sg:province":"Kent",
    "sg:tags":[
        "publishing"
    ],
    "wof:name":"E & A Publishing Ltd",
    "wof:placetype":"venue"
},
  "geometry": {"coordinates":[0.014928,51.405701],"type":"Point"}
}