{
  "type": "Feature",
  "properties": {
    "iso:country":"GB",
    "sg:address":"32 Coldharbour Lane",
    "sg:city":"Hayes",
    "sg:classifiers":[
        {
            "category":"Retail",
            "subcategory":"Repair Shop",
            "type":"Services"
        }
    ],
    "sg:postcode":"UB3 3EP",
    "sg:province":"Greater London",
    "sg:tags":[
        "radio",
        "television",
        "video"
    ],
    "wof:name":"A Chancy",
    "wof:placetype":"venue"
},
  "geometry": {"coordinates":[-0.416732,51.507668],"type":"Point"}
}