{
  "type": "Feature",
  "properties": {
    "iso:country":"GB",
    "sg:address":"113 Southdown Road",
    "sg:city":"Harpenden",
    "sg:classifiers":[
        {
            "category":"Health Services",
            "subcategory":"Chiropractor",
            "type":"Services"
        }
    ],
    "sg:phone":"+44 1582 766477",
    "sg:postcode":"AL5 1QQ",
    "sg:province":"Hertfordshire",
    "wof:name":"Harpenden Chiropractic Clinic",
    "wof:placetype":"venue"
},
  "geometry": {"coordinates":[-0.34381,51.806866],"type":"Point"}
}