{
  "type": "Feature",
  "properties": {
    "addr:full":"Medlar Tree House, The Street Great Yarmouth Norfolk NR29 5AZ",
    "addr:postcode":"nr29 5az",
    "addr:street":"The Street",
    "iso:country":"GB",
    "sg:address":"Medlar Tree House, The Street",
    "sg:city":"Great Yarmouth",
    "sg:classifiers":[
        {
            "category":"Real Estate",
            "subcategory":"Architect",
            "type":"Services"
        }
    ],
    "sg:postcode":"NR29 5AZ",
    "sg:province":"Norfolk",
    "sg:tags":[
        "architectural"
    ],
    "wof:name":"Rodney Palmer Ltd.",
    "wof:placetype":"venue"
},
  "geometry": {"coordinates":[1.534195,52.741104],"type":"Point"}
}