{
  "type": "Feature",
  "properties": {
    "iso:country":"GB",
    "sg:address":"50 New St",
    "sg:city":"Worcester",
    "sg:classifiers":[
        {
            "category":"Professional",
            "type":"Services"
        }
    ],
    "sg:postcode":"WR1 2DL",
    "sg:province":"Worcestershire",
    "sg:tags":[
        "control",
        "system"
    ],
    "wof:name":"Parkinson McKay Ltd",
    "wof:placetype":"venue"
},
  "geometry": {"coordinates":[-2.218981,52.191277],"type":"Point"}
}