{
  "type": "Feature",
  "properties": {
    "addr:full":"150 Intake Lane Barnsley South Yorkshire S75 2HU",
    "addr:housenumber":"150",
    "addr:postcode":"s75 2hu",
    "addr:street":"Intake Lane;Yorkshire",
    "iso:country":"GB",
    "sg:address":"150 Intake Lane",
    "sg:city":"Barnsley",
    "sg:classifiers":[
        {
            "category":"Social Services",
            "subcategory":"Job Training",
            "type":"Services"
        }
    ],
    "sg:phone":"+44 1226 288034",
    "sg:postcode":"S75 2HU",
    "sg:province":"South Yorkshire",
    "sg:tags":[
        "draughtsman",
        "drawing"
    ],
    "wof:name":"Acechief",
    "wof:placetype":"venue"
},
  "geometry": {"coordinates":[-1.5071519613,53.556350708],"type":"Point"}
}