{
  "type": "Feature",
  "properties": {
    "addr:full":"731 Commercial Rd Poplar Greater London E14 7LA",
    "addr:housenumber":"731",
    "addr:postcode":"e14 7la",
    "addr:street":"Commercial Rd",
    "iso:country":"GB",
    "sg:address":"731 Commercial Rd",
    "sg:city":"Poplar",
    "sg:classifiers":[
        {
            "category":"Autos & Motor Vehicles",
            "subcategory":"Fuel & Gas Station",
            "type":"Retail Goods"
        }
    ],
    "sg:phone":"+44 20 7987 3750",
    "sg:postcode":"E14 7LA",
    "sg:province":"Greater London",
    "sg:tags":[
        "hr",
        "petrol"
    ],
    "wof:name":"Stepney North Service Station",
    "wof:placetype":"venue"
},
  "geometry": {"coordinates":[-0.0545639992,51.520160675],"type":"Point"}
}