{
  "type": "Feature",
  "properties": {
    "addr:full":"611 Garratt Lane London Greater London SW18 4SU",
    "addr:housenumber":"611",
    "addr:postcode":"sw18 4su",
    "addr:street":"Garratt Lane",
    "iso:country":"GB",
    "sg:address":"611 Garratt Lane",
    "sg:city":"London",
    "sg:classifiers":[
        {
            "category":"Organizations",
            "subcategory":"Political Organization",
            "type":"Services"
        }
    ],
    "sg:phone":"+44 20 8946 2641",
    "sg:postcode":"SW18 4SU",
    "sg:province":"Greater London",
    "sg:tags":[
        "party"
    ],
    "wof:name":"Tooting Labour Party",
    "wof:placetype":"venue"
},
  "geometry": {"coordinates":[-0.186602,51.438751],"type":"Point"}
}