{
  "type": "Feature",
  "properties": {
    "addr:full":"Unit 33, New Lydenburg Commercial Estate London Greater London SE7 8NE",
    "addr:housenumber":"unit 33",
    "addr:postcode":"se7 8ne",
    "addr:street":"New Lydenburg Commercial Estate",
    "iso:country":"GB",
    "sg:address":"Unit 33, New Lydenburg Commercial Estate",
    "sg:city":"London",
    "sg:classifiers":[
        {
            "category":"Food & Beverages",
            "subcategory":"Supermarket",
            "type":"Retail Goods"
        }
    ],
    "sg:phone":"+44 20 8293 9756",
    "sg:postcode":"SE7 8NE",
    "sg:province":"Greater London",
    "sg:tags":[
        "frozen"
    ],
    "wof:name":"Lucky Foods",
    "wof:placetype":"venue"
},
  "geometry": {"coordinates":[0.036159,51.493397],"type":"Point"}
}