{
  "type": "Feature",
  "properties": {
    "iso:country":"GB",
    "sg:address":"33 Seven Sisters Road",
    "sg:city":"London",
    "sg:classifiers":[
        {
            "category":"Banks & Credit Unions",
            "subcategory":"Bank",
            "type":"Services"
        }
    ],
    "sg:phone":"+44 20 8445 4490",
    "sg:postcode":"N7 6AY",
    "sg:province":"Greater London",
    "sg:tags":[
        "broker",
        "mortgage"
    ],
    "wof:name":"CHELTENHAM & GLOUCESTER P L C",
    "wof:placetype":"venue"
},
  "geometry": {"coordinates":[-0.117946,51.558804],"type":"Point"}
}