{
  "type": "Feature",
  "properties": {
    "iso:country":"GB",
    "sg:address":"144 Highgate",
    "sg:city":"Kendal",
    "sg:classifiers":[
        {
            "category":"Shopping",
            "subcategory":"Used Merchandise",
            "type":"Retail Goods"
        }
    ],
    "sg:postcode":"LA9 4HW",
    "sg:province":"Cumbria",
    "sg:tags":[
        "shop",
        "second-hand"
    ],
    "wof:name":"Kendal Household & Domestic",
    "wof:placetype":"venue"
},
  "geometry": {"coordinates":[-2.7473490238,54.3237304688],"type":"Point"}
}