{
  "type": "Feature",
  "properties": {
    "addr:full":"Full Sutton York East Riding of Yorkshire YO41 1PS",
    "addr:postcode":"yo41 1ps",
    "iso:country":"GB",
    "sg:address":"Full Sutton",
    "sg:city":"York",
    "sg:classifiers":[
        {
            "category":"Government",
            "subcategory":"Prison",
            "type":"Public Place"
        }
    ],
    "sg:phone":"+44 1759 375100",
    "sg:postcode":"YO41 1PS",
    "sg:province":"East Riding of Yorkshire",
    "wof:name":"Full Sutton Prison",
    "wof:placetype":"venue"
},
  "geometry": {"coordinates":[-0.8685899973,53.9856414795],"type":"Point"}
}