{
  "type": "Feature",
  "properties": {
    "iso:country":"GB",
    "sg:address":"61 Middle Close, Valley Road",
    "sg:city":"Newbury",
    "sg:classifiers":[
        {
            "category":"Building & Trades",
            "subcategory":"Construction",
            "type":"Services"
        }
    ],
    "sg:postcode":"RG14 6HB",
    "sg:province":"Berkshire",
    "sg:tags":[
        "decorator",
        "painter"
    ],
    "wof:name":"Colin Stewart Brown",
    "wof:placetype":"venue"
},
  "geometry": {"coordinates":[-1.343704,51.385696],"type":"Point"}
}