{
  "type": "Feature",
  "properties": {
    "iso:country":"GB",
    "sg:address":"18 Cornwall Road, Cheam",
    "sg:city":"Sutton",
    "sg:classifiers":[
        {
            "category":"Professional",
            "subcategory":"Advertising",
            "type":"Services"
        }
    ],
    "sg:postcode":"SM2 6DT",
    "sg:province":"Surrey",
    "sg:tags":[
        "telemarketing"
    ],
    "wof:name":"Argent Marketing",
    "wof:placetype":"venue"
},
  "geometry": {"coordinates":[-0.2064529955,51.3546257019],"type":"Point"}
}