{
  "type": "Feature",
  "properties": {
    "addr:full":"Bridge Garage, Ness Road, Shoeburyness Hockley Essex SS3 9PG",
    "addr:postcode":"ss3 9pg",
    "addr:street":"Ness Road;Hockley",
    "iso:country":"GB",
    "sg:address":"Bridge Garage, Ness Road, Shoeburyness",
    "sg:city":"Hockley",
    "sg:classifiers":[
        {
            "category":"Autos & Motor Vehicles",
            "subcategory":"Automobile Sales",
            "type":"Retail Goods"
        }
    ],
    "sg:phone":"+44 1702 296109",
    "sg:postcode":"SS3 9PG",
    "sg:province":"Essex",
    "sg:tags":[
        "car"
    ],
    "wof:name":"Neil & Deborah Smith",
    "wof:placetype":"venue"
},
  "geometry": {"coordinates":[0.7820180058,51.5265312195],"type":"Point"}
}