{
  "type": "Feature",
  "properties": {
    "addr:full":"5 Weavers Court Halstead Essex CO9 2JN",
    "addr:housenumber":"5",
    "addr:postcode":"co9 2jn",
    "addr:street":"Weavers Court",
    "iso:country":"GB",
    "sg:address":"5 Weavers Court",
    "sg:city":"Halstead",
    "sg:classifiers":[
        {
            "category":"Shopping",
            "subcategory":"Department Store",
            "type":"Retail Goods"
        },
        {
            "category":"Shopping",
            "subcategory":"Comic Books",
            "type":"Retail Goods"
        }
    ],
    "sg:postcode":"CO9 2JN",
    "sg:province":"Essex",
    "sg:tags":[
        "jeweller"
    ],
    "wof:name":"Weavers Court Jewellers",
    "wof:placetype":"venue"
},
  "geometry": {"coordinates":[0.6354770064,51.9436378479],"type":"Point"}
}