{
  "type": "Feature",
  "properties": {
    "addr:full":"20 The Downs Altrincham Cheshire WA14 2PU",
    "addr:housenumber":"20",
    "addr:postcode":"wa14 2pu",
    "addr:street":"The Downs",
    "iso:country":"GB",
    "sg:address":"20 The Downs",
    "sg:city":"Altrincham",
    "sg:classifiers":[
        {
            "category":"Personal",
            "subcategory":"Beauty Salon",
            "type":"Services"
        }
    ],
    "sg:phone":"+44 161 926 9637",
    "sg:postcode":"WA14 2PU",
    "sg:province":"Cheshire",
    "wof:name":"Le Salon",
    "wof:placetype":"venue"
},
  "geometry": {"coordinates":[-2.353021,53.384319],"type":"Point"}
}