{
  "type": "Feature",
  "properties": {
    "addr:full":"24b Glen Street Edinburgh City of Edinburgh EH3 9JE",
    "addr:housenumber":"24b",
    "addr:postcode":"eh3 9je",
    "addr:street":"Glen Street",
    "iso:country":"GB",
    "sg:address":"24b Glen Street",
    "sg:city":"Edinburgh",
    "sg:classifiers":[
        {
            "category":"Real Estate",
            "subcategory":"Architect",
            "type":"Services"
        }
    ],
    "sg:phone":"+44 131 228 6907",
    "sg:postcode":"EH3 9JE",
    "sg:province":"City of Edinburgh",
    "wof:name":"Rochmankowski Associates",
    "wof:placetype":"venue"
},
  "geometry": {"coordinates":[-3.201841116,55.9437789917],"type":"Point"}
}