{
  "type": "Feature",
  "properties": {
    "addr:full":"82 Duke Street Birkenhead Merseyside CH41 8BS",
    "addr:housenumber":"82",
    "addr:postcode":"ch41 8bs",
    "addr:street":"Duke Street",
    "iso:country":"GB",
    "sg:address":"82 Duke Street",
    "sg:city":"Birkenhead",
    "sg:classifiers":[
        {
            "category":"Autos & Motor Vehicles",
            "subcategory":"Automobile Sales",
            "type":"Retail Goods"
        }
    ],
    "sg:phone":"+44 151 200 5001",
    "sg:postcode":"CH41 8BS",
    "sg:province":"Merseyside",
    "sg:tags":[
        "car"
    ],
    "wof:name":"TRADE PRICE CAR CENTRE",
    "wof:placetype":"venue"
},
  "geometry": {"coordinates":[-3.0380339622,53.3987617493],"type":"Point"}
}