{
  "type": "Feature",
  "properties": {
    "iso:country":"GB",
    "sg:address":"Colne Rd, Brierfield",
    "sg:city":"Nelson",
    "sg:classifiers":[
        {
            "category":"Health Services",
            "subcategory":"Nursing And Care Facility",
            "type":"Services"
        }
    ],
    "sg:phone":"+44 1282 616231",
    "sg:postcode":"BB9 5RH",
    "sg:province":"Lancashire",
    "sg:tags":[
        "home"
    ],
    "wof:name":"Holly Bank House",
    "wof:placetype":"venue"
},
  "geometry": {"coordinates":[-2.234284,53.823605],"type":"Point"}
}