{
  "type": "Feature",
  "properties": {
    "addr:full":"Queens Wharf, Queen Caroline Street, Hammersmith London Greater London W6 9RJ",
    "addr:postcode":"w6 9rj",
    "addr:street":"Queens;Queen Caroline Street",
    "iso:country":"GB",
    "sg:address":"Queens Wharf, Queen Caroline Street, Hammersmith",
    "sg:city":"London",
    "sg:classifiers":[
        {
            "category":"Professional",
            "type":"Services"
        }
    ],
    "sg:phone":"+44 1895 554466",
    "sg:postcode":"W6 9RJ",
    "sg:province":"Greater London",
    "sg:tags":[
        "caterer"
    ],
    "wof:name":"Compass Services (U K) Ltd.",
    "wof:placetype":"venue"
},
  "geometry": {"coordinates":[-0.22822,51.488701],"type":"Point"}
}