{
  "type": "Feature",
  "properties": {
    "iso:country":"GB",
    "sg:address":"Elm Fields Gate, Winslow",
    "sg:city":"Buckingham",
    "sg:classifiers":[
        {
            "category":"Organizations",
            "subcategory":"Membership Organization",
            "type":"Services"
        }
    ],
    "sg:phone":"+44 1296 713287",
    "sg:postcode":"MK18 3JG",
    "sg:province":"Buckinghamshire",
    "sg:tags":[
        "club"
    ],
    "wof:name":"The Royal British Legion Clubs",
    "wof:placetype":"venue"
},
  "geometry": {"coordinates":[-0.877844,51.94437],"type":"Point"}
}