{
  "type": "Feature",
  "properties": {
    "addr:full":"43 Peel Park Avenue Clitheroe Lancashire BB7 1JR",
    "addr:housenumber":"43",
    "addr:postcode":"bb7 1jr",
    "addr:street":"Peel Park Avenue",
    "iso:country":"GB",
    "sg:address":"43 Peel Park Avenue",
    "sg:city":"Clitheroe",
    "sg:classifiers":[
        {
            "category":"Home & Garden",
            "subcategory":"Household Appliances",
            "type":"Retail Goods"
        }
    ],
    "sg:phone":"+44 1200 427973",
    "sg:postcode":"BB7 1JR",
    "sg:province":"Lancashire",
    "sg:tags":[
        "domestic",
        "oven",
        "microwave"
    ],
    "wof:name":"Colcare",
    "wof:placetype":"venue"
},
  "geometry": {"coordinates":[-2.3842790127,53.8662796021],"type":"Point"}
}