{
  "type": "Feature",
  "properties": {
    "addr:full":"Unit 6, The Parade Shifnal Shropshire TF11 8DL",
    "addr:housenumber":"unit 6",
    "addr:postcode":"tf11 8dl",
    "addr:street":"The Parade",
    "iso:country":"GB",
    "sg:address":"Unit 6, The Parade",
    "sg:city":"Shifnal",
    "sg:classifiers":[
        {
            "category":"Sports & Exercise",
            "subcategory":"Gym",
            "type":"Entertainment"
        }
    ],
    "sg:phone":"+44 1952 462522",
    "sg:postcode":"TF11 8DL",
    "sg:province":"Shropshire",
    "sg:tags":[
        "fitness",
        "health",
        "centre"
    ],
    "wof:name":"121 Personal Trainer",
    "wof:placetype":"venue"
},
  "geometry": {"coordinates":[-2.3727788925,52.6654853821],"type":"Point"}
}