{
  "type": "Feature",
  "properties": {
    "addr:full":"6 John Street London Greater London WC1N 2ES",
    "addr:housenumber":"6",
    "addr:postcode":"wc1n 2es",
    "addr:street":"John Street",
    "iso:country":"GB",
    "sg:address":"6 John Street",
    "sg:city":"London",
    "sg:classifiers":[
        {
            "category":"Education",
            "subcategory":"Junior College",
            "type":"Public Place"
        }
    ],
    "sg:phone":"+44 20 7430 8400",
    "sg:postcode":"WC1N 2ES",
    "sg:province":"Greater London",
    "sg:tags":[
        "distance",
        "learning"
    ],
    "wof:name":"Regent Academy of Fine Arts Ltd.",
    "wof:placetype":"venue"
},
  "geometry": {"coordinates":[-0.1148490012,51.5217323303],"type":"Point"}
}