{
  "type": "Feature",
  "properties": {
    "addr:full":"The Site Office Seadell Estate, Beach Road Hemsby Great Yarmouth Norfolk NR29 4HS",
    "addr:postcode":"nr29 4hs",
    "addr:street":"Beach Road;Yarmouth",
    "iso:country":"GB",
    "sg:address":"The Site Office Seadell Estate, Beach Road Hemsby",
    "sg:city":"Great Yarmouth",
    "sg:classifiers":[
        {
            "category":"Travel",
            "subcategory":"Hotels & Motels",
            "type":"Entertainment"
        }
    ],
    "sg:postcode":"NR29 4HS",
    "sg:province":"Norfolk",
    "sg:tags":[
        "self",
        "catering"
    ],
    "wof:name":"Duncan Foley Holidays",
    "wof:placetype":"venue"
},
  "geometry": {"coordinates":[1.6921299696,52.6979560852],"type":"Point"}
}