{
  "type": "Feature",
  "properties": {
    "addr:full":"372 Easter Road Edinburgh City of Edinburgh EH6 8JP",
    "addr:housenumber":"372",
    "addr:postcode":"eh6 8jp",
    "addr:street":"Easter Road",
    "iso:country":"GB",
    "sg:address":"372 Easter Road",
    "sg:city":"Edinburgh",
    "sg:classifiers":[
        {
            "category":"Retail",
            "subcategory":"Auto Repair",
            "type":"Services"
        }
    ],
    "sg:postcode":"EH6 8JP",
    "sg:province":"City of Edinburgh",
    "sg:tags":[
        "modification",
        "garage"
    ],
    "wof:name":"Tuloch,Andrew,",
    "wof:placetype":"venue"
},
  "geometry": {"coordinates":[-3.1693398952,55.9669456482],"type":"Point"}
}