{
  "type": "Feature",
  "properties": {
    "iso:country":"GB",
    "sg:address":"Sheerlands House, Sheerlands Road, Finchhampstead",
    "sg:city":"Wokingham",
    "sg:classifiers":[
        {
            "category":"Building & Trades",
            "subcategory":"Construction",
            "type":"Services"
        }
    ],
    "sg:phone":"+44 118 973 2515",
    "sg:postcode":"RG40 4QX",
    "sg:province":"Berkshire",
    "sg:tags":[
        "installers",
        "gas"
    ],
    "wof:name":"S G Ray & Co. Ltd.",
    "wof:placetype":"venue"
},
  "geometry": {"coordinates":[-0.9019910097,51.3761520386],"type":"Point"}
}