{
  "type": "Feature",
  "properties": {
    "iso:country":"GB",
    "sg:address":"77 North Street",
    "sg:city":"Forfar",
    "sg:classifiers":[
        {
            "category":"Education",
            "subcategory":"College",
            "type":"Public Place"
        },
        {
            "category":"Education",
            "subcategory":"Vocational School",
            "type":"Public Place"
        }
    ],
    "sg:phone":"+44 1307 464033",
    "sg:postcode":"DD8 3BL",
    "sg:province":"Angus",
    "sg:tags":[
        "technical",
        "agricultural"
    ],
    "sg:website":"http://www.sac.ac.uk",
    "wof:name":"S E C Scottish Agricultural College",
    "wof:placetype":"venue"
},
  "geometry": {"coordinates":[-2.884208,56.649563],"type":"Point"}
}