{
  "type": "Feature",
  "properties": {
    "iso:country":"GB",
    "sg:address":"Eaugate Road, Moulton Chapel",
    "sg:city":"Spalding",
    "sg:classifiers":[
        {
            "category":"Education",
            "subcategory":"School",
            "type":"Public Place"
        },
        {
            "category":"Government",
            "subcategory":"Office",
            "type":"Public Place"
        }
    ],
    "sg:phone":"+44 1406 380440",
    "sg:postcode":"PE12 0XZ",
    "sg:province":"Cambridgeshire",
    "sg:tags":[
        "local",
        "authority"
    ],
    "wof:name":"Moulton Chapel County Primary School",
    "wof:placetype":"venue"
},
  "geometry": {"coordinates":[-0.076624,52.746498],"type":"Point"}
}