{
  "type": "Feature",
  "properties": {
    "iso:country":"GB",
    "sg:address":"180 Abbots Road",
    "sg:city":"Selby",
    "sg:classifiers":[
        {
            "category":"Building & Trades",
            "subcategory":"Construction",
            "type":"Services"
        }
    ],
    "sg:phone":"+44 1757 704391",
    "sg:postcode":"YO8 8AZ",
    "sg:province":"East Riding of Yorkshire",
    "sg:tags":[
        "decorator",
        "painter"
    ],
    "wof:name":"Dennis Lord",
    "wof:placetype":"venue"
},
  "geometry": {"coordinates":[-1.0598289967,53.7737846375],"type":"Point"}
}