{
  "type": "Feature",
  "properties": {
    "iso:country":"GB",
    "sg:address":"Desford Road, Kirby Muxloe",
    "sg:city":"Leicester",
    "sg:classifiers":[
        {
            "category":"Professional",
            "subcategory":"Engineering",
            "type":"Services"
        }
    ],
    "sg:phone":"+44 1455 824782",
    "sg:postcode":"LE9 2BG",
    "sg:province":"Leicestershire",
    "sg:tags":[
        "contractor",
        "electrical",
        "engineer"
    ],
    "wof:name":"Sissons & Allen Ltd.",
    "wof:placetype":"venue"
},
  "geometry": {"coordinates":[-1.236659,52.63316],"type":"Point"}
}