{
  "type": "Feature",
  "properties": {
    "addr:full":"10 Field Clo Bury St Edmunds Suffolk IP30 9AW",
    "addr:housenumber":"10",
    "addr:postcode":"ip30 9aw",
    "addr:street":"Field Clo",
    "iso:country":"GB",
    "sg:address":"10 Field Clo",
    "sg:city":"Bury St Edmunds",
    "sg:classifiers":[
        {
            "category":"Retail",
            "subcategory":"Event Space",
            "type":"Services"
        }
    ],
    "sg:phone":"+44 1359 271181",
    "sg:postcode":"IP30 9AW",
    "sg:province":"Suffolk",
    "sg:tags":[
        "exhibition",
        "organiser"
    ],
    "wof:name":"John M Booth Pennine Arts",
    "wof:placetype":"venue"
},
  "geometry": {"coordinates":[0.8280230165,52.2347221375],"type":"Point"}
}