{
  "type": "Feature",
  "properties": {
    "addr:full":"Cathedral Square Dornoch Highland IV25 3SJ",
    "addr:postcode":"iv25 3sj",
    "addr:street":"Cathedral Square Dornoch",
    "iso:country":"GB",
    "sg:address":"Cathedral Square",
    "sg:city":"Dornoch",
    "sg:classifiers":[
        {
            "category":"Personal",
            "subcategory":"Beauty Salon",
            "type":"Services"
        }
    ],
    "sg:phone":"+44 1862 810656",
    "sg:postcode":"IV25 3SJ",
    "sg:province":"Highland",
    "sg:tags":[
        "unisex",
        "hairdresser"
    ],
    "wof:name":"Rainbow Hair Studio",
    "wof:placetype":"venue"
},
  "geometry": {"coordinates":[-4.0278692245,57.8816566467],"type":"Point"}
}