{
  "type": "Feature",
  "properties": {
    "iso:country":"GB",
    "sg:address":"341 High St",
    "sg:city":"Hayes",
    "sg:classifiers":[
        {
            "category":"Building & Trades",
            "subcategory":"Cleaning & Sanitation",
            "type":"Services"
        }
    ],
    "sg:phone":"+44 20 8897 3392",
    "sg:postcode":"UB3 5DQ",
    "sg:province":"Greater London",
    "sg:tags":[
        "commercial"
    ],
    "wof:name":"A J M Office Cleaning Services Ltd",
    "wof:placetype":"venue"
},
  "geometry": {"coordinates":[-0.4349319935,51.4860534668],"type":"Point"}
}