{
  "type": "Feature",
  "properties": {
    "addr:full":"Rear Unit Lancaster Road, Cressex Industrial Estate High Wycombe Buckinghamshire HP12 3NN",
    "addr:housenumber":"unit",
    "addr:postcode":"hp12 3nn",
    "addr:street":"Lancaster Road Cressex Industrial;High",
    "iso:country":"GB",
    "sg:address":"Rear Unit Lancaster Road, Cressex Industrial Estate",
    "sg:city":"High Wycombe",
    "sg:classifiers":[
        {
            "category":"Retail",
            "subcategory":"Emissions Testing",
            "type":"Services"
        },
        {
            "category":"Retail",
            "subcategory":"Auto Repair",
            "type":"Services"
        }
    ],
    "sg:phone":"+44 1494 448158",
    "sg:postcode":"HP12 3NN",
    "sg:province":"Buckinghamshire",
    "sg:tags":[
        "modification",
        "garage",
        "mot"
    ],
    "wof:name":"Miller Commercial Motors",
    "wof:placetype":"venue"
},
  "geometry": {"coordinates":[-0.7682160139,51.6189613342],"type":"Point"}
}