{
  "type": "Feature",
  "properties": {
    "iso:country":"GB",
    "sg:address":"1 Malt Mill Green",
    "sg:city":"Rugby",
    "sg:classifiers":[
        {
            "category":"Professional",
            "subcategory":"Employment Agencies",
            "type":"Services"
        }
    ],
    "sg:phone":"+44 1788 824292",
    "sg:postcode":"CV23 8YW",
    "sg:province":"Northamptonshire",
    "sg:tags":[
        "recr",
        "hire",
        "driver"
    ],
    "wof:name":"G Staff",
    "wof:placetype":"venue"
},
  "geometry": {"coordinates":[-1.174541,52.333549],"type":"Point"}
}