{
  "type": "Feature",
  "properties": {
    "iso:country":"GB",
    "sg:address":"7 Moor Street, Spondon",
    "sg:city":"Derby",
    "sg:classifiers":[
        {
            "category":"Professional",
            "subcategory":"Printing & Photocopies",
            "type":"Services"
        }
    ],
    "sg:phone":"+44 1332 665555",
    "sg:postcode":"DE21 7EA",
    "sg:province":"Derbyshire",
    "sg:tags":[
        "plate",
        "engraver",
        "lithographic",
        "maker"
    ],
    "wof:name":"Spondon Trophies & Engravings",
    "wof:placetype":"venue"
},
  "geometry": {"coordinates":[-1.402692,52.921001],"type":"Point"}
}