{
  "type": "Feature",
  "properties": {
    "iso:country":"GB",
    "sg:address":"Kenny Hill House, Kenny Hill",
    "sg:city":"Bury St Edmunds",
    "sg:classifiers":[
        {
            "category":"Farming",
            "subcategory":"Crops",
            "type":"Manufacturing & Wholesale Goods"
        },
        {
            "category":"Farming",
            "subcategory":"Livestock Farm",
            "type":"Manufacturing & Wholesale Goods"
        }
    ],
    "sg:phone":"+44 1353 675256",
    "sg:postcode":"IP28 8DU",
    "sg:province":"Cambridgeshire",
    "sg:tags":[
        "arable",
        "others"
    ],
    "wof:name":"C J Butcher",
    "wof:placetype":"venue"
},
  "geometry": {"coordinates":[0.45694,52.3923],"type":"Point"}
}