{
  "type": "Feature",
  "properties": {
    "addr:full":"6 Cranborne Road Swanage Dorset BH19 1EA",
    "addr:housenumber":"6",
    "addr:postcode":"bh19 1ea",
    "addr:street":"Cranborne Road",
    "iso:country":"GB",
    "sg:address":"6 Cranborne Road",
    "sg:city":"Swanage",
    "sg:classifiers":[
        {
            "category":"Travel",
            "subcategory":"Hotels & Motels",
            "type":"Entertainment"
        }
    ],
    "sg:phone":"+44 1929 422748",
    "sg:postcode":"BH19 1EA",
    "sg:province":"Dorset",
    "wof:name":"Gainsborough House Hotel",
    "wof:placetype":"venue"
},
  "geometry": {"coordinates":[-1.961403,50.611088],"type":"Point"}
}