{
  "type": "Feature",
  "properties": {
    "iso:country":"GB",
    "sg:address":"Sovereign Court, Office, 21 Wannock Road",
    "sg:city":"Eastbourne",
    "sg:classifiers":[
        {
            "category":"Social Services",
            "subcategory":"Retirement Home",
            "type":"Services"
        }
    ],
    "sg:phone":"+44 1323 725638",
    "sg:postcode":"BN22 7JQ",
    "sg:province":"East Sussex",
    "sg:tags":[
        "rest"
    ],
    "wof:name":"Sovereign Court",
    "wof:placetype":"venue"
},
  "geometry": {"coordinates":[0.3047150075,50.7795295715],"type":"Point"}
}