{
  "type": "Feature",
  "properties": {
    "iso:country":"GB",
    "sg:address":"4 Beaufort Gardens",
    "sg:city":"Usk",
    "sg:classifiers":[
        {
            "category":"Professional",
            "type":"Services"
        }
    ],
    "sg:phone":"+44 1291 690255",
    "sg:postcode":"NP15 2DP",
    "sg:province":"Monmouthshire",
    "sg:tags":[
        "caterer"
    ],
    "wof:name":"Castell Catering",
    "wof:placetype":"venue"
},
  "geometry": {"coordinates":[-2.951337,51.717602],"type":"Point"}
}