{
  "type": "Feature",
  "properties": {
    "addr:full":"57 Idle Rd Bradford West Yorkshire BD2 4NT",
    "addr:housenumber":"57",
    "addr:postcode":"bd2 4nt",
    "addr:street":"Idle Rd",
    "iso:country":"GB",
    "sg:address":"57 Idle Rd",
    "sg:city":"Bradford",
    "sg:classifiers":[
        {
            "category":"Fast Food",
            "type":"Food & Drink"
        }
    ],
    "sg:phone":"+44 1274 630600",
    "sg:postcode":"BD2 4NT",
    "sg:province":"West Yorkshire",
    "sg:tags":[
        "away",
        "take"
    ],
    "wof:name":"Bilal Roti House",
    "wof:placetype":"venue"
},
  "geometry": {"coordinates":[-1.733093977,53.8087348938],"type":"Point"}
}