{
  "type": "Feature",
  "properties": {
    "addr:full":"Hillview Farm Melksham Wiltshire SN12 6NL",
    "addr:postcode":"sn12 6nl",
    "addr:street":"Melksham",
    "iso:country":"GB",
    "sg:address":"Hillview Farm",
    "sg:city":"Melksham",
    "sg:classifiers":[
        {
            "category":"Farming",
            "subcategory":"Farm",
            "type":"Manufacturing & Wholesale Goods"
        }
    ],
    "sg:phone":"+44 1380 828349",
    "sg:postcode":"SN12 6NL",
    "sg:province":"Wiltshire",
    "sg:tags":[
        "mixed",
        "crop"
    ],
    "wof:name":"T Bourne",
    "wof:placetype":"venue"
},
  "geometry": {"coordinates":[-2.1208889484,51.3602790833],"type":"Point"}
}