{
  "type": "Feature",
  "properties": {
    "addr:full":"Chancel House, Neasden Lane London Greater London NW10 2XE",
    "addr:postcode":"nw10 2xe",
    "addr:street":"Neasden Lane",
    "iso:country":"GB",
    "sg:address":"Chancel House, Neasden Lane",
    "sg:city":"London",
    "sg:classifiers":[
        {
            "category":"Professional",
            "subcategory":"Business Services",
            "type":"Services"
        }
    ],
    "sg:phone":"+44 20 8459 8031",
    "sg:postcode":"NW10 2XE",
    "sg:province":"Greater London",
    "sg:tags":[
        "holding"
    ],
    "wof:name":"Ladbroke Leasing (South East) Ltd.",
    "wof:placetype":"venue"
},
  "geometry": {"coordinates":[-0.249214,51.549282],"type":"Point"}
}