{
  "type": "Feature",
  "properties": {
    "iso:country":"GB",
    "sg:address":"Common Rd, Ightham",
    "sg:city":"Sevenoaks",
    "sg:classifiers":[
        {
            "category":"Bars & Pubs",
            "type":"Food & Drink"
        }
    ],
    "sg:phone":"+44 1732 885912",
    "sg:postcode":"TN15 9EB",
    "sg:province":"Kent",
    "sg:tags":[
        "pubs",
        "inn"
    ],
    "wof:name":"The Harrow Inn",
    "wof:placetype":"venue"
},
  "geometry": {"coordinates":[0.286002,51.28661],"type":"Point"}
}