{
  "type": "Feature",
  "properties": {
    "iso:country":"GB",
    "sg:address":"Packham Road, Northfleet",
    "sg:city":"Gravesend",
    "sg:classifiers":[
        {
            "category":"Education",
            "subcategory":"School",
            "type":"Public Place"
        }
    ],
    "sg:phone":"+44 1474 566700",
    "sg:postcode":"DA11 7JF",
    "sg:province":"Kent",
    "sg:tags":[
        "local",
        "authority"
    ],
    "wof:name":"Shears Green County Primary Infants School",
    "wof:placetype":"venue"
},
  "geometry": {"coordinates":[0.364606,51.432827],"type":"Point"}
}