{
  "type": "Feature",
  "properties": {
    "addr:full":"Salway Rd, Gerry Raffles Square, Stratford Stratford Greater London E15 1BX",
    "addr:postcode":"e15 1bx",
    "addr:street":"Salway Rd;Raffles Square",
    "iso:country":"GB",
    "sg:address":"Salway Rd, Gerry Raffles Square, Stratford",
    "sg:city":"Stratford",
    "sg:classifiers":[
        {
            "category":"Cinema",
            "subcategory":"Movie Theater",
            "type":"Entertainment"
        }
    ],
    "sg:phone":"+44 20 8555 3366",
    "sg:postcode":"E15 1BX",
    "sg:province":"Greater London",
    "wof:name":"Stratford Picture House",
    "wof:placetype":"venue"
},
  "geometry": {"coordinates":[0.002085,51.543301],"type":"Point"}
}