{
  "type": "Feature",
  "properties": {
    "iso:country":"GB",
    "sg:address":"Silverdene, Punchbowl Lane",
    "sg:city":"Dorking",
    "sg:classifiers":[
        {
            "category":"Professional",
            "subcategory":"Management & Consulting",
            "type":"Services"
        }
    ],
    "sg:phone":"+44 1306 888428",
    "sg:postcode":"RH5 4BJ",
    "sg:province":"Surrey",
    "sg:tags":[
        "consultant",
        "business"
    ],
    "wof:name":"Fitch & Associates - Europe Ltd.",
    "wof:placetype":"venue"
},
  "geometry": {"coordinates":[-0.3157700002,51.231010437],"type":"Point"}
}