{
  "type": "Feature",
  "properties": {
    "iso:country":"GB",
    "sg:address":"Units 13-15 Osbourne Mill, Busk Road",
    "sg:city":"Oldham",
    "sg:classifiers":[
        {
            "category":"Manufacturing",
            "subcategory":"Wood Products",
            "type":"Manufacturing & Wholesale Goods"
        }
    ],
    "sg:phone":"+44 161 633 3385",
    "sg:postcode":"OL9 6SF",
    "sg:province":"Lancashire",
    "sg:tags":[
        "maker",
        "cabinet"
    ],
    "wof:name":"D & H Woodwork",
    "wof:placetype":"venue"
},
  "geometry": {"coordinates":[-2.1310799122,53.5485992432],"type":"Point"}
}