{
  "type": "Feature",
  "properties": {
    "addr:full":"Newbury Park Health Centre, 40 Perrymans Farm Rd Ilford Essex IG2 7LE",
    "addr:housenumber":"40",
    "addr:postcode":"ig2 7le",
    "addr:street":"Perrymans Farm Rd",
    "iso:country":"GB",
    "sg:address":"Newbury Park Health Centre, 40 Perrymans Farm Rd",
    "sg:city":"Ilford",
    "sg:classifiers":[
        {
            "category":"Health Services",
            "subcategory":"Doctor",
            "type":"Services"
        }
    ],
    "sg:phone":"+44 20 8518 2414",
    "sg:postcode":"IG2 7LE",
    "sg:province":"Essex",
    "sg:tags":[
        "practitioners"
    ],
    "wof:name":"Hanna, N J",
    "wof:placetype":"venue"
},
  "geometry": {"coordinates":[0.08587,51.576542],"type":"Point"}
}