{
  "type": "Feature",
  "properties": {
    "iso:country":"GB",
    "sg:address":"Column Cotts",
    "sg:city":"Llanfairpwllgwyngyll",
    "sg:classifiers":[
        {
            "category":"Government",
            "subcategory":"Post Office",
            "type":"Public Place"
        },
        {
            "category":"Landmark",
            "subcategory":"Tourist Attraction",
            "type":"Public Place"
        }
    ],
    "sg:phone":"+44 1248 714393",
    "sg:postcode":"LL61 5NJ",
    "sg:province":"Isle of Anglesey",
    "sg:tags":[
        "interest"
    ],
    "wof:name":"The Marquess of Anglesey Column",
    "wof:placetype":"venue"
},
  "geometry": {"coordinates":[-4.203199,53.22126],"type":"Point"}
}