{
  "type": "Feature",
  "properties": {
    "addr:full":"37 Acorn Units, Ellough Industrial Estate Beccles Norfolk NR34 7TD",
    "addr:housenumber":"37",
    "addr:postcode":"nr34 7td",
    "addr:street":"Acorn Units;Industrial Estate",
    "iso:country":"GB",
    "sg:address":"37 Acorn Units, Ellough Industrial Estate",
    "sg:city":"Beccles",
    "sg:classifiers":[
        {
            "category":"Professional",
            "subcategory":"Printing & Photocopies",
            "type":"Services"
        }
    ],
    "sg:phone":"+44 1502 714489",
    "sg:postcode":"NR34 7TD",
    "sg:province":"Norfolk",
    "sg:tags":[
        "printer"
    ],
    "wof:name":"The Bidnall Press Ltd.",
    "wof:placetype":"venue"
},
  "geometry": {"coordinates":[1.592325,52.426609],"type":"Point"}
}