{
  "type": "Feature",
  "properties": {
    "iso:country":"GB",
    "sg:address":"21 Sunningdale Road",
    "sg:city":"Middlesbrough",
    "sg:classifiers":[
        {
            "category":"Building & Trades",
            "subcategory":"Construction",
            "type":"Services"
        }
    ],
    "sg:phone":"+44 1642 828719",
    "sg:postcode":"TS4 3HU",
    "sg:province":"North Yorkshire",
    "sg:tags":[
        "joiner",
        "carpenter"
    ],
    "wof:name":"Jim Brown Joinery",
    "wof:placetype":"venue"
},
  "geometry": {"coordinates":[-1.229429,54.548435],"type":"Point"}
}