{
  "type": "Feature",
  "properties": {
    "addr:full":"Butlers Farm, Picklepythe Lane, Beenham Reading Berkshire RG7 5NT",
    "addr:postcode":"rg7 5nt",
    "addr:street":"Picklepythe Lane",
    "iso:country":"GB",
    "sg:address":"Butlers Farm, Picklepythe Lane, Beenham",
    "sg:city":"Reading",
    "sg:classifiers":[
        {
            "category":"Organizations",
            "subcategory":"Community Association",
            "type":"Services"
        },
        {
            "category":"Organizations",
            "subcategory":"Non-profit Organization",
            "type":"Services"
        }
    ],
    "sg:phone":"+44 118 971 3330",
    "sg:postcode":"RG7 5NT",
    "sg:province":"Berkshire",
    "sg:tags":[
        "organisation",
        "care",
        "animal",
        "welfare"
    ],
    "wof:name":"The U K  Wolf Conservation Trust",
    "wof:placetype":"venue"
},
  "geometry": {"coordinates":[-1.158424,51.415966],"type":"Point"}
}