{
  "type": "Feature",
  "properties": {
    "iso:country":"GB",
    "sg:address":"10 Jeremy Close, Penkhull",
    "sg:city":"Stoke-on-trent",
    "sg:classifiers":[
        {
            "category":"Building & Trades",
            "subcategory":"Cleaning & Sanitation",
            "type":"Services"
        }
    ],
    "sg:phone":"+44 1782 848333",
    "sg:postcode":"ST4 5JD",
    "sg:province":"Staffordshire",
    "sg:tags":[
        "cleaner",
        "window"
    ],
    "wof:name":"H & A Wild",
    "wof:placetype":"venue"
},
  "geometry": {"coordinates":[-2.197253,52.999374],"type":"Point"}
}