{
  "type": "Feature",
  "properties": {
    "iso:country":"GB",
    "sg:address":"Caversham House 13-17 Church Street, Caversham",
    "sg:city":"Reading",
    "sg:classifiers":[
        {
            "category":"Real Estate",
            "subcategory":"Real Estate Agent",
            "type":"Services"
        }
    ],
    "sg:phone":"+44 1634 822311",
    "sg:postcode":"RG4 7AA",
    "sg:province":"Berkshire",
    "wof:name":"Service Group International",
    "wof:placetype":"venue"
},
  "geometry": {"coordinates":[-0.977383,51.467609],"type":"Point"}
}