{
  "type": "Feature",
  "properties": {
    "iso:country":"GB",
    "sg:address":"Meadow Green Cottages",
    "sg:city":"Worcester",
    "sg:classifiers":[
        {
            "category":"Real Estate",
            "subcategory":"Surveying",
            "type":"Services"
        }
    ],
    "sg:phone":"+44 1886 821590",
    "sg:postcode":"WR6 5RR",
    "sg:province":"Herefordshire",
    "sg:tags":[
        "surveyor",
        "valuer"
    ],
    "wof:name":"John Mence",
    "wof:placetype":"venue"
},
  "geometry": {"coordinates":[-2.413354,52.208466],"type":"Point"}
}