{
  "type": "Feature",
  "properties": {
    "iso:country":"GB",
    "sg:address":"East Road, Longhorsley",
    "sg:city":"Morpeth",
    "sg:classifiers":[
        {
            "category":"Food & Beverages",
            "subcategory":"Liquor & Beverages",
            "type":"Retail Goods"
        }
    ],
    "sg:phone":"+44 1670 788001",
    "sg:postcode":"NE65 8SY",
    "sg:province":"Northumberland",
    "sg:tags":[
        "beer",
        "spirit",
        "wines"
    ],
    "wof:name":"The Village Shop",
    "wof:placetype":"venue"
},
  "geometry": {"coordinates":[-1.76841,55.24596],"type":"Point"}
}