{
  "type": "Feature",
  "properties": {
    "addr:full":"216-218 Main Road, Biggin Hill Westerham Kent TN16 3BD",
    "addr:housenumber":"216-218",
    "addr:postcode":"tn16 3bd",
    "addr:street":"Main Road",
    "iso:country":"GB",
    "sg:address":"216-218 Main Road, Biggin Hill",
    "sg:city":"Westerham",
    "sg:classifiers":[
        {
            "category":"Recreation",
            "subcategory":"Fishing",
            "type":"Entertainment"
        }
    ],
    "sg:phone":"+44 1959 570265",
    "sg:postcode":"TN16 3BD",
    "sg:province":"Kent",
    "sg:tags":[
        "angling"
    ],
    "wof:name":"Peter James",
    "wof:placetype":"venue"
},
  "geometry": {"coordinates":[0.0406709984,51.3077926636],"type":"Point"}
}