{
  "type": "Feature",
  "properties": {
    "addr:full":"Slippery Gowt Lane, Wyberton Boston Lincolnshire PE21 7AA",
    "addr:postcode":"pe21 7aa",
    "addr:street":"Gowt Lane",
    "iso:country":"GB",
    "sg:address":"Slippery Gowt Lane, Wyberton",
    "sg:city":"Boston",
    "sg:classifiers":[
        {
            "category":"Building & Trades",
            "subcategory":"Construction",
            "type":"Services"
        }
    ],
    "sg:phone":"+44 1205 354629",
    "sg:postcode":"PE21 7AA",
    "sg:province":"Lincolnshire",
    "sg:tags":[
        "joinery"
    ],
    "wof:name":"T Clarke & Sons (Joinery) Ltd.",
    "wof:placetype":"venue"
},
  "geometry": {"coordinates":[-0.0411290005,52.9540977478],"type":"Point"}
}