{
  "type": "Feature",
  "properties": {
    "iso:country":"GB",
    "sg:address":"26-28 Northgate Street",
    "sg:city":"Ipswich",
    "sg:classifiers":[
        {
            "category":"Professional",
            "subcategory":"Employment Agencies",
            "type":"Services"
        },
        {
            "category":"Conference Center",
            "type":"Public Place"
        }
    ],
    "sg:postcode":"IP1 3DB",
    "sg:province":"Suffolk",
    "sg:tags":[
        "consultant",
        "business",
        "centre"
    ],
    "wof:name":"Acorn Recruitment Consultants",
    "wof:placetype":"venue"
},
  "geometry": {"coordinates":[1.156629,52.058784],"type":"Point"}
}