{
  "type": "Feature",
  "properties": {
    "addr:full":"24 Trinity Avenue Enfield Greater London EN1 1HS",
    "addr:housenumber":"24",
    "addr:postcode":"en1 1hs",
    "addr:street":"Trinity Avenue",
    "iso:country":"GB",
    "sg:address":"24 Trinity Avenue",
    "sg:city":"Enfield",
    "sg:classifiers":[
        {
            "category":"Health Services",
            "subcategory":"Doctor",
            "type":"Services"
        }
    ],
    "sg:phone":"+44 20 8363 4493",
    "sg:postcode":"EN1 1HS",
    "sg:province":"Greater London",
    "sg:tags":[
        "practitioners"
    ],
    "wof:name":"The Surgery",
    "wof:placetype":"venue"
},
  "geometry": {"coordinates":[-0.06647,51.640793],"type":"Point"}
}