{
  "type": "Feature",
  "properties": {
    "iso:country":"GB",
    "sg:address":"Hunts Farm, Broad St Common, Aldershot Road",
    "sg:city":"Guildford",
    "sg:classifiers":[
        {
            "category":"Retail",
            "subcategory":"Driving School",
            "type":"Services"
        }
    ],
    "sg:phone":"+44 1483 232063",
    "sg:postcode":"GU3 3HX",
    "sg:province":"Surrey",
    "wof:name":"Autopass School of Motoring",
    "wof:placetype":"venue"
},
  "geometry": {"coordinates":[-0.6169999838,51.2589302063],"type":"Point"}
}