{
  "type": "Feature",
  "properties": {
    "addr:full":"Corsham Regis School, Kings Avenue Corsham Wiltshire SN13 0EG",
    "addr:postcode":"sn13 0eg",
    "addr:street":"Kings Avenue",
    "iso:country":"GB",
    "sg:address":"Corsham Regis School, Kings Avenue",
    "sg:city":"Corsham",
    "sg:classifiers":[
        {
            "category":"Education",
            "subcategory":"Preschool",
            "type":"Public Place"
        }
    ],
    "sg:postcode":"SN13 0EG",
    "sg:province":"Wiltshire",
    "sg:tags":[
        "pre-school",
        "playgroups"
    ],
    "wof:name":"The Honey Pot Pre School",
    "wof:placetype":"venue"
},
  "geometry": {"coordinates":[-2.1872389317,51.4314842224],"type":"Point"}
}