{
  "type": "Feature",
  "properties": {
    "addr:full":"Bixslade Stone Works, Cannop Road, Parkend Lydney Gloucestershire GL15 4JS",
    "addr:postcode":"gl15 4js",
    "addr:street":"Cannop Road",
    "iso:country":"GB",
    "sg:address":"Bixslade Stone Works, Cannop Road, Parkend",
    "sg:city":"Lydney",
    "sg:classifiers":[
        {
            "category":"Manufacturing",
            "subcategory":"Building Materials",
            "type":"Manufacturing & Wholesale Goods"
        }
    ],
    "sg:phone":"+44 1594 562304",
    "sg:postcode":"GL15 4JS",
    "sg:province":"Gloucestershire",
    "sg:tags":[
        "stonemason"
    ],
    "wof:name":"Forest Of Dean Stone Firms Ltd",
    "wof:placetype":"venue"
},
  "geometry": {"coordinates":[-2.5620999336,51.7741889954],"type":"Point"}
}