{
  "type": "Feature",
  "properties": {
    "iso:country":"GB",
    "sg:address":"20 Two Hedges Road, Bishops Cleeve",
    "sg:city":"Cheltenham",
    "sg:classifiers":[
        {
            "category":"Building & Trades",
            "subcategory":"Construction",
            "type":"Services"
        }
    ],
    "sg:phone":"+44 1242 675325",
    "sg:postcode":"GL52 8DT",
    "sg:province":"Gloucestershire",
    "sg:tags":[
        "builder"
    ],
    "wof:name":"D A Loveridge",
    "wof:placetype":"venue"
},
  "geometry": {"coordinates":[-2.060976,51.942783],"type":"Point"}
}