{
  "type": "Feature",
  "properties": {
    "iso:country":"GB",
    "sg:address":"29 Alma Rd",
    "sg:city":"Windsor",
    "sg:classifiers":[
        {
            "category":"Manufacturing",
            "subcategory":"Signs",
            "type":"Manufacturing & Wholesale Goods"
        }
    ],
    "sg:phone":"+44 1753 831430",
    "sg:postcode":"SL4 6JZ",
    "sg:province":"Berkshire",
    "sg:tags":[
        "writer"
    ],
    "wof:name":"Phil Mcgill Signs",
    "wof:placetype":"venue"
},
  "geometry": {"coordinates":[-0.63652,51.498699],"type":"Point"}
}