{
  "type": "Feature",
  "properties": {
    "iso:country":"GB",
    "sg:address":"Meole Brace",
    "sg:city":"Shrewsbury",
    "sg:classifiers":[
        {
            "category":"Government",
            "subcategory":"Office",
            "type":"Public Place"
        },
        {
            "category":"Sports & Exercise",
            "subcategory":"Golf",
            "type":"Entertainment"
        }
    ],
    "sg:phone":"+44 1743 364050",
    "sg:postcode":"SY2 6QQ",
    "sg:province":"Shropshire",
    "sg:tags":[
        "club",
        "course",
        "local"
    ],
    "wof:name":"Meole Brace Golf Course",
    "wof:placetype":"venue"
},
  "geometry": {"coordinates":[-2.7496,52.691261],"type":"Point"}
}