{
  "type": "Feature",
  "properties": {
    "addr:full":"Box Office, The Enade Promenade Llandudno Conwy LL30 1BB",
    "addr:postcode":"ll30 1bb",
    "addr:street":"Promenade",
    "iso:country":"GB",
    "sg:address":"Box Office, The Enade Promenade",
    "sg:city":"Llandudno",
    "sg:classifiers":[
        {
            "category":"Government",
            "subcategory":"Office",
            "type":"Public Place"
        },
        {
            "category":"Community Center",
            "type":"Public Place"
        },
        {
            "category":"Arts & Performance",
            "subcategory":"Theater",
            "type":"Entertainment"
        }
    ],
    "sg:phone":"+44 1492 879771",
    "sg:postcode":"LL30 1BB",
    "sg:province":"Conwy",
    "sg:tags":[
        "conference",
        "concert",
        "theatre",
        "centre",
        "local",
        "hall",
        "room"
    ],
    "wof:name":"North Wales Theatre & Conference Centre",
    "wof:placetype":"venue"
},
  "geometry": {"coordinates":[-3.818764,53.322433],"type":"Point"}
}