{
  "type": "Feature",
  "properties": {
    "iso:country":"GB",
    "sg:address":"9 Galbraith Way",
    "sg:city":"Rochdale",
    "sg:classifiers":[
        {
            "category":"Organizations",
            "subcategory":"Community Association",
            "type":"Services"
        }
    ],
    "sg:phone":"+44 1706 522111",
    "sg:postcode":"OL11 5WE",
    "sg:province":"Lancashire",
    "sg:tags":[
        "emblem",
        "badge"
    ],
    "wof:name":"Badges By Design",
    "wof:placetype":"venue"
},
  "geometry": {"coordinates":[-2.21206,53.620541],"type":"Point"}
}