{
  "type": "Feature",
  "properties": {
    "iso:country":"GB",
    "sg:address":"Chadwick Garage, 636 Birmingham Road, Lydiate Ash",
    "sg:city":"Bromsgrove",
    "sg:classifiers":[
        {
            "category":"Building & Trades",
            "subcategory":"Construction",
            "type":"Services"
        }
    ],
    "sg:phone":"+44 121 457 8995",
    "sg:postcode":"B61 0QB",
    "sg:province":"Worcestershire",
    "sg:tags":[
        "fork",
        "lift",
        "truck"
    ],
    "wof:name":"Quicklift Ltd",
    "wof:placetype":"venue"
},
  "geometry": {"coordinates":[-2.041306,52.376278],"type":"Point"}
}