{
  "type": "Feature",
  "properties": {
    "iso:country":"GB",
    "sg:address":"Lyons Lane",
    "sg:city":"Chorley",
    "sg:classifiers":[
        {
            "category":"Autos & Motor Vehicles",
            "subcategory":"Auto Supplies",
            "type":"Retail Goods"
        }
    ],
    "sg:phone":"+44 1257 269521",
    "sg:postcode":"PR7 3BL",
    "sg:province":"Lancashire",
    "sg:tags":[
        "exhaust",
        "absorber",
        "shock"
    ],
    "wof:name":"Kwik-Fit",
    "wof:placetype":"venue"
},
  "geometry": {"coordinates":[-2.626222,53.649895],"type":"Point"}
}