{
  "type": "Feature",
  "properties": {
    "addr:full":"196 Brighton Rd South Croydon Surrey CR2 6AF",
    "addr:housenumber":"196",
    "addr:postcode":"cr2 6af",
    "addr:street":"Brighton Rd",
    "iso:country":"GB",
    "sg:address":"196 Brighton Rd",
    "sg:city":"South Croydon",
    "sg:classifiers":[
        {
            "category":"Manufacturing",
            "subcategory":"Signs",
            "type":"Manufacturing & Wholesale Goods"
        }
    ],
    "sg:postcode":"CR2 6AF",
    "sg:province":"Surrey",
    "sg:tags":[
        "nameplate"
    ],
    "wof:name":"Borer,Keith,",
    "wof:placetype":"venue"
},
  "geometry": {"coordinates":[-0.0979759991,51.3547821045],"type":"Point"}
}