{
  "type": "Feature",
  "properties": {
    "iso:country":"GB",
    "sg:address":"St. Helens",
    "sg:city":"Glenrothes",
    "sg:classifiers":[
        {
            "category":"Building & Trades",
            "subcategory":"Construction",
            "type":"Services"
        }
    ],
    "sg:phone":"+44 1592 612357",
    "sg:postcode":"KY7 6LB",
    "sg:province":"Fife",
    "sg:tags":[
        "builder"
    ],
    "wof:name":"David R Spacey",
    "wof:placetype":"venue"
},
  "geometry": {"coordinates":[-3.147008,56.20607],"type":"Point"}
}