{
  "type": "Feature",
  "properties": {
    "addr:full":"78 Stockton Lane York North Yorkshire YO31 1BS",
    "addr:housenumber":"78",
    "addr:postcode":"yo31 1bs",
    "addr:street":"Stockton Lane",
    "iso:country":"GB",
    "sg:address":"78 Stockton Lane",
    "sg:city":"York",
    "sg:classifiers":[
        {
            "category":"Travel",
            "subcategory":"Hotels & Motels",
            "type":"Entertainment"
        }
    ],
    "sg:phone":"+44 1904 425556",
    "sg:postcode":"YO31 1BS",
    "sg:province":"North Yorkshire",
    "sg:tags":[
        "house",
        "guest"
    ],
    "wof:name":"Avimore House Hotel",
    "wof:placetype":"venue"
},
  "geometry": {"coordinates":[-1.0592360497,53.9698371887],"type":"Point"}
}