{
  "type": "Feature",
  "properties": {
    "iso:country":"GB",
    "sg:address":"7b Broad Street",
    "sg:city":"Nottingham",
    "sg:classifiers":[
        {
            "category":"Utilities",
            "type":"Services"
        }
    ],
    "sg:phone":"+44 115 952 6060",
    "sg:postcode":"NG1 3AJ",
    "sg:province":"Nottinghamshire",
    "sg:tags":[
        "internet"
    ],
    "wof:name":"A I Design",
    "wof:placetype":"venue"
},
  "geometry": {"coordinates":[-1.144186,52.95401],"type":"Point"}
}