{
  "type": "Feature",
  "properties": {
    "addr:full":"Unit 1b Pelham Bldgs, Pelham St Mansfield Nottinghamshire NG18 2EY",
    "addr:housenumber":"unit 1b",
    "addr:postcode":"ng18 2ey",
    "addr:street":"St",
    "iso:country":"GB",
    "sg:address":"Unit 1b Pelham Bldgs, Pelham St",
    "sg:city":"Mansfield",
    "sg:classifiers":[
        {
            "category":"Retail",
            "subcategory":"Storage",
            "type":"Services"
        }
    ],
    "sg:postcode":"NG18 2EY",
    "sg:province":"Nottinghamshire",
    "sg:tags":[
        "household",
        "removal"
    ],
    "wof:name":"Easy Phones Uk",
    "wof:placetype":"venue"
},
  "geometry": {"coordinates":[-1.1887789965,53.143699646],"type":"Point"}
}