{
  "type": "Feature",
  "properties": {
    "addr:full":"42 Drayton St Wolverhampton West Midlands WV2 3AB",
    "addr:housenumber":"42",
    "addr:postcode":"wv2 3ab",
    "addr:street":"Drayton St",
    "iso:country":"GB",
    "sg:address":"42 Drayton St",
    "sg:city":"Wolverhampton",
    "sg:classifiers":[
        {
            "category":"Shopping",
            "subcategory":"Clothing, Apparel, & Fashions",
            "type":"Retail Goods"
        }
    ],
    "sg:phone":"+44 1902 870223",
    "sg:postcode":"WV2 3AB",
    "sg:province":"West Midlands",
    "sg:tags":[
        "clothing"
    ],
    "wof:name":"Lindsey Dawn Plc",
    "wof:placetype":"venue"
},
  "geometry": {"coordinates":[-2.127424,52.57634],"type":"Point"}
}