{
  "type": "Feature",
  "properties": {
    "addr:full":"57 Tirpenry St, Morriston Swansea Swansea SA6 8EB",
    "addr:housenumber":"57",
    "addr:postcode":"sa6 8eb",
    "addr:street":"Tirpenry St",
    "iso:country":"GB",
    "sg:address":"57 Tirpenry St, Morriston",
    "sg:city":"Swansea",
    "sg:classifiers":[
        {
            "category":"Home & Garden",
            "subcategory":"Building Materials",
            "type":"Retail Goods"
        },
        {
            "category":"Building & Trades",
            "subcategory":"Construction",
            "type":"Services"
        }
    ],
    "sg:postcode":"SA6 8EB",
    "sg:province":"Swansea",
    "sg:tags":[
        "dry",
        "plasterers",
        "installers",
        "lining",
        "insulation",
        "screeders"
    ],
    "wof:name":"Seddon,Mark J,",
    "wof:placetype":"venue"
},
  "geometry": {"coordinates":[-3.9220039845,51.66614151],"type":"Point"}
}