{
  "type": "Feature",
  "properties": {
    "addr:full":"Hubbards La, Boughton Monchelsea Maidstone Kent ME17 4HY",
    "addr:housenumber":"monchelsea",
    "addr:postcode":"me17 4hy",
    "addr:street":"La Boughton",
    "iso:country":"GB",
    "sg:address":"Hubbards La, Boughton Monchelsea",
    "sg:city":"Maidstone",
    "sg:classifiers":[
        {
            "category":"Parking",
            "type":"Transportation"
        }
    ],
    "sg:postcode":"ME17 4HY",
    "sg:province":"Kent",
    "sg:tags":[
        "car",
        "valet"
    ],
    "wof:name":"Young,M W,",
    "wof:placetype":"venue"
},
  "geometry": {"coordinates":[0.5209599733,51.2319793701],"type":"Point"}
}