{
  "type": "Feature",
  "properties": {
    "iso:country":"GB",
    "sg:address":"4 Orchard Cres",
    "sg:city":"Nantwich",
    "sg:classifiers":[
        {
            "category":"Autos & Motor Vehicles",
            "subcategory":"Automobile Sales",
            "type":"Retail Goods"
        }
    ],
    "sg:phone":"+44 1270 625038",
    "sg:postcode":"CW5 7AN",
    "sg:province":"Cheshire",
    "sg:tags":[
        "car"
    ],
    "wof:name":"Autoville Ltd",
    "wof:placetype":"venue"
},
  "geometry": {"coordinates":[-2.5178129673,53.056060791],"type":"Point"}
}