{
  "type": "Feature",
  "properties": {
    "addr:full":"Unit G1 Arundel Business Centre, 49 Station Road Harold Wood Romford Essex RM3 0BS",
    "addr:housenumber":"g1;49",
    "addr:postcode":"rm3 0bs",
    "addr:street":"Arundel Business;Station Road",
    "iso:country":"GB",
    "sg:address":"Unit G1 Arundel Business Centre, 49 Station Road Harold Wood",
    "sg:city":"Romford",
    "sg:classifiers":[
        {
            "category":"Professional",
            "subcategory":"Computer Services",
            "type":"Services"
        }
    ],
    "sg:postcode":"RM3 0BS",
    "sg:province":"Essex",
    "sg:tags":[
        "consultant"
    ],
    "wof:name":"Ultimate Consultancy It Services Ltd.",
    "wof:placetype":"venue"
},
  "geometry": {"coordinates":[0.2328000069,51.5918006897],"type":"Point"}
}