{
  "type": "Feature",
  "properties": {
    "addr:full":"24 Miller Rd Ayr South Ayrshire KA7 2AY",
    "addr:housenumber":"24",
    "addr:postcode":"ka7 2ay",
    "addr:street":"Miller Rd",
    "iso:country":"GB",
    "sg:address":"24 Miller Rd",
    "sg:city":"Ayr",
    "sg:classifiers":[
        {
            "category":"Personal",
            "subcategory":"Beauty Salon",
            "type":"Services"
        }
    ],
    "sg:postcode":"KA7 2AY",
    "sg:province":"South Ayrshire",
    "sg:tags":[
        "lady",
        "hairdresser"
    ],
    "wof:name":"Hastie,Anne,",
    "wof:placetype":"venue"
},
  "geometry": {"coordinates":[-4.632226944,55.4583358765],"type":"Point"}
}