{
  "type": "Feature",
  "properties": {
    "addr:full":"1 High St, Uffculme Cullompton Devon EX15 3AB",
    "addr:housenumber":"1",
    "addr:postcode":"ex15 3ab",
    "addr:street":"High St",
    "iso:country":"GB",
    "sg:address":"1 High St, Uffculme",
    "sg:city":"Cullompton",
    "sg:classifiers":[
        {
            "category":"Health Services",
            "subcategory":"Health Practitioner",
            "type":"Services"
        }
    ],
    "sg:phone":"+44 1884 841700",
    "sg:postcode":"EX15 3AB",
    "sg:province":"Devon",
    "sg:tags":[
        "osteopath"
    ],
    "wof:name":"Jaycroft Clinic",
    "wof:placetype":"venue"
},
  "geometry": {"coordinates":[-3.3270769119,50.9071922302],"type":"Point"}
}