{
  "type": "Feature",
  "properties": {
    "addr:full":"13 Clifton Street Stourbridge Staffordshire DY8 3XR",
    "addr:housenumber":"13",
    "addr:postcode":"dy8 3xr",
    "addr:street":"Clifton Street",
    "iso:country":"GB",
    "sg:address":"13 Clifton Street",
    "sg:city":"Stourbridge",
    "sg:classifiers":[
        {
            "category":"Professional",
            "subcategory":"Art Services",
            "type":"Services"
        }
    ],
    "sg:postcode":"DY8 3XR",
    "sg:province":"Staffordshire",
    "sg:tags":[
        "photographer"
    ],
    "wof:name":"Highlights Photography",
    "wof:placetype":"venue"
},
  "geometry": {"coordinates":[-2.1544029713,52.4544410706],"type":"Point"}
}