{
  "type": "Feature",
  "properties": {
    "addr:full":"101 Dunraven Street Tonypandy Rhondda, Cynon, Taff CF40 1AR",
    "addr:housenumber":"101",
    "addr:postcode":"cf40 1ar",
    "addr:street":"Dunraven Street;Cynon Taff",
    "iso:country":"GB",
    "sg:address":"101 Dunraven Street",
    "sg:city":"Tonypandy",
    "sg:classifiers":[
        {
            "category":"Real Estate",
            "subcategory":"Real Estate Agent",
            "type":"Services"
        }
    ],
    "sg:phone":"+44 1443 433015",
    "sg:postcode":"CF40 1AR",
    "sg:province":"Rhondda, Cynon, Taff",
    "wof:name":"Tudball & Edwards",
    "wof:placetype":"venue"
},
  "geometry": {"coordinates":[-3.4526109695,51.6203689575],"type":"Point"}
}