{
  "type": "Feature",
  "properties": {
    "iso:country":"GB",
    "sg:address":"19 Russell Square",
    "sg:city":"Brighton",
    "sg:classifiers":[
        {
            "category":"Travel",
            "subcategory":"Hotels & Motels",
            "type":"Entertainment"
        }
    ],
    "sg:postcode":"BN1 2EE",
    "sg:province":"East Sussex",
    "sg:tags":[
        "house",
        "guest"
    ],
    "wof:name":"Russell Guest House",
    "wof:placetype":"venue"
},
  "geometry": {"coordinates":[-0.147661,50.823162],"type":"Point"}
}