{
  "type": "Feature",
  "properties": {
    "addr:full":"17 Heghbrok Way Bognor Regis West Sussex PO21 2RF",
    "addr:housenumber":"17",
    "addr:postcode":"po21 2rf",
    "addr:street":"Heghbrok Way",
    "iso:country":"GB",
    "sg:address":"17 Heghbrok Way",
    "sg:city":"Bognor Regis",
    "sg:classifiers":[
        {
            "category":"Building & Trades",
            "subcategory":"Construction",
            "type":"Services"
        }
    ],
    "sg:phone":"+44 1243 861587",
    "sg:postcode":"PO21 2RF",
    "sg:province":"West Sussex",
    "sg:tags":[
        "joiner",
        "carpenter"
    ],
    "wof:name":"D R Winslow",
    "wof:placetype":"venue"
},
  "geometry": {"coordinates":[-0.693808,50.782497],"type":"Point"}
}