{
  "type": "Feature",
  "properties": {
    "addr:full":"29 Holly Tree Croft, Dunnington York North Yorkshire YO19 5RG",
    "addr:housenumber":"29",
    "addr:postcode":"yo19 5rg",
    "addr:street":"Holly Tree Croft",
    "iso:country":"GB",
    "sg:address":"29 Holly Tree Croft, Dunnington",
    "sg:city":"York",
    "sg:classifiers":[
        {
            "category":"Autos & Motor Vehicles",
            "subcategory":"Fuel & Gas Station",
            "type":"Retail Goods"
        },
        {
            "category":"Home & Garden",
            "subcategory":"Building Materials",
            "type":"Retail Goods"
        }
    ],
    "sg:phone":"+44 1904 489560",
    "sg:postcode":"YO19 5RG",
    "sg:province":"North Yorkshire",
    "sg:tags":[
        "supplier",
        "gate",
        "door",
        "fence",
        "barrier"
    ],
    "wof:name":"BRIAN HORNER",
    "wof:placetype":"venue"
},
  "geometry": {"coordinates":[-0.9763410091,53.9681587219],"type":"Point"}
}