{
  "type": "Feature",
  "properties": {
    "addr:full":"Lower Slade Farm House, Doddington Sittingbourne Kent ME9 0NP",
    "addr:postcode":"me9 0np",
    "addr:street":"Lower Slade",
    "iso:country":"GB",
    "sg:address":"Lower Slade Farm House, Doddington",
    "sg:city":"Sittingbourne",
    "sg:classifiers":[
        {
            "category":"Real Estate",
            "subcategory":"Surveying",
            "type":"Services"
        }
    ],
    "sg:postcode":"ME9 0NP",
    "sg:province":"Kent",
    "sg:tags":[
        "building",
        "surveyor"
    ],
    "wof:name":"Geoffrey A Bailey",
    "wof:placetype":"venue"
},
  "geometry": {"coordinates":[0.771395,51.281223],"type":"Point"}
}