{
  "type": "Feature",
  "properties": {
    "addr:full":"Easton Neston Towcester Buckinghamshire NN12 7HS",
    "addr:postcode":"nn12 7hs",
    "iso:country":"GB",
    "sg:address":"Easton Neston",
    "sg:city":"Towcester",
    "sg:classifiers":[
        {
            "category":"Sports & Exercise",
            "subcategory":"Race Track",
            "type":"Entertainment"
        }
    ],
    "sg:phone":"+44 1327 353414",
    "sg:postcode":"NN12 7HS",
    "sg:province":"Buckinghamshire",
    "sg:tags":[
        "racecourse"
    ],
    "wof:name":"The Towcester Racecourse Co. Ltd.",
    "wof:placetype":"venue"
},
  "geometry": {"coordinates":[-0.912199,52.096218],"type":"Point"}
}