{
  "type": "Feature",
  "properties": {
    "addr:full":"Eastbridge Hospital, High Street Canterbury Kent CT1 2BD",
    "addr:postcode":"ct1 2bd",
    "addr:street":"High Street",
    "iso:country":"GB",
    "sg:address":"Eastbridge Hospital, High Street",
    "sg:city":"Canterbury",
    "sg:classifiers":[
        {
            "category":"Place Of Worship",
            "type":"Public Place"
        }
    ],
    "sg:phone":"+44 1227 761374",
    "sg:postcode":"CT1 2BD",
    "sg:province":"Kent",
    "wof:name":"Canterbury Churches Information Centre",
    "wof:placetype":"venue"
},
  "geometry": {"coordinates":[1.0756100416,51.275970459],"type":"Point"}
}