{
  "type": "Feature",
  "properties": {
    "iso:country":"GB",
    "sg:address":"49 Palace Avenue",
    "sg:city":"Paignton",
    "sg:classifiers":[
        {
            "category":"Professional",
            "subcategory":"Accounting & Tax Preparation",
            "type":"Services"
        }
    ],
    "sg:phone":"+44 1803 558431",
    "sg:postcode":"TQ3 3EN",
    "sg:province":"Devon",
    "sg:tags":[
        "accountant"
    ],
    "wof:name":"Trojan Industrial Park Management Co. Ltd.",
    "wof:placetype":"venue"
},
  "geometry": {"coordinates":[-3.570757,50.435513],"type":"Point"}
}