{
  "type": "Feature",
  "properties": {
    "iso:country":"GB",
    "sg:address":"140a Hallgate",
    "sg:city":"Cottingham",
    "sg:classifiers":[
        {
            "category":"Retail",
            "subcategory":"Laundry & Dry Cleaning",
            "type":"Services"
        }
    ],
    "sg:phone":"+44 1482 845898",
    "sg:postcode":"HU16 4BD",
    "sg:province":"East Riding of Yorkshire",
    "sg:tags":[
        "alteration"
    ],
    "wof:name":"Just Sew",
    "wof:placetype":"venue"
},
  "geometry": {"coordinates":[-0.405709,53.78653],"type":"Point"}
}