{
  "type": "Feature",
  "properties": {
    "iso:country":"GB",
    "sg:address":"1 Back Westfield Terrace, Alexandra Road",
    "sg:city":"Gateshead",
    "sg:classifiers":[
        {
            "category":"Professional",
            "subcategory":"Printing & Photocopies",
            "type":"Services"
        }
    ],
    "sg:phone":"+44 191 477 8726",
    "sg:postcode":"NE8 4HX",
    "sg:province":"Tyne and Wear",
    "sg:tags":[
        "printer"
    ],
    "wof:name":"Mike Whaley Ltd.",
    "wof:placetype":"venue"
},
  "geometry": {"coordinates":[-1.603264,54.950619],"type":"Point"}
}