{
  "type": "Feature",
  "properties": {
    "iso:country":"GB",
    "sg:address":"68 Borough Rd, Southwark",
    "sg:city":"Southwark",
    "sg:classifiers":[
        {
            "category":"Bars & Pubs",
            "type":"Food & Drink"
        }
    ],
    "sg:phone":"+44 20 7403 7059",
    "sg:postcode":"SE1 1DX",
    "sg:province":"Greater London",
    "sg:tags":[
        "pubs",
        "inn"
    ],
    "wof:name":"The Ship",
    "wof:placetype":"venue"
},
  "geometry": {"coordinates":[-0.09692,51.499401],"type":"Point"}
}