{
  "type": "Feature",
  "properties": {
    "iso:country":"GB",
    "sg:address":"Homefield Ho, Civic Offices 323 High St",
    "sg:city":"Epping",
    "sg:classifiers":[
        {
            "category":"Organizations",
            "subcategory":"Non-profit Organization",
            "type":"Services"
        }
    ],
    "sg:phone":"+44 1992 564178",
    "sg:postcode":"CM16 4BZ",
    "sg:province":"Essex",
    "sg:tags":[
        "organisation",
        "voluntary",
        "charity"
    ],
    "wof:name":"C V S",
    "wof:placetype":"venue"
},
  "geometry": {"coordinates":[0.111659,51.699299],"type":"Point"}
}