{
  "type": "Feature",
  "properties": {
    "addr:full":"102 Coppergate House, 16 Brune Street London Greater London E1 7NJ",
    "addr:housenumber":"102;16",
    "addr:postcode":"e1 7nj",
    "addr:street":"Coppergate;Brune Street",
    "iso:country":"GB",
    "sg:address":"102 Coppergate House, 16 Brune Street",
    "sg:city":"London",
    "sg:classifiers":[
        {
            "category":"Utilities",
            "type":"Services"
        }
    ],
    "sg:phone":"+44 20 7721 7811",
    "sg:postcode":"E1 7NJ",
    "sg:province":"Greater London",
    "sg:tags":[
        "internet"
    ],
    "wof:name":"4mat Com Ltd.",
    "wof:placetype":"venue"
},
  "geometry": {"coordinates":[-0.0748400018,51.5180892944],"type":"Point"}
}