{
  "type": "Feature",
  "properties": {
    "iso:country":"GB",
    "sg:address":"Streatham Common",
    "sg:city":"London",
    "sg:classifiers":[
        {
            "category":"Social Services",
            "subcategory":"Child Care",
            "type":"Services"
        }
    ],
    "sg:postcode":"SW16 2AN",
    "sg:province":"Greater London",
    "sg:tags":[
        "agency",
        "nanny"
    ],
    "wof:name":"Premier Nannies",
    "wof:placetype":"venue"
},
  "geometry": {"coordinates":[-0.1218499988,51.4245109558],"type":"Point"}
}