{
  "type": "Feature",
  "properties": {
    "addr:full":"25 High St Camberley Berkshire GU15 3RB",
    "addr:housenumber":"25",
    "addr:postcode":"gu15 3rb",
    "addr:street":"High St",
    "iso:country":"GB",
    "sg:address":"25 High St",
    "sg:city":"Camberley",
    "sg:classifiers":[
        {
            "category":"Shopping",
            "subcategory":"Comic Books",
            "type":"Retail Goods"
        }
    ],
    "sg:phone":"+44 1276 65514",
    "sg:postcode":"GU15 3RB",
    "sg:province":"Berkshire",
    "sg:tags":[
        "jeweller"
    ],
    "wof:name":"Walsh Bros The Jewellers",
    "wof:placetype":"venue"
},
  "geometry": {"coordinates":[-0.7445639968,51.3386993408],"type":"Point"}
}