{
  "type": "Feature",
  "properties": {
    "iso:country":"GB",
    "sg:address":"Unit 16 In Shops, The Wellgate",
    "sg:city":"Dundee",
    "sg:classifiers":[
        {
            "category":"Home & Garden",
            "subcategory":"Household Appliances",
            "type":"Retail Goods"
        }
    ],
    "sg:phone":"+44 1382 322800",
    "sg:postcode":"DD1 2DB",
    "sg:province":"Dundee City",
    "sg:tags":[
        "electrical"
    ],
    "wof:name":"Wellgate Electrical",
    "wof:placetype":"venue"
},
  "geometry": {"coordinates":[-2.967609,56.461376],"type":"Point"}
}