{
  "type": "Feature",
  "properties": {
    "addr:full":"4-8 Harcourt Road Sheffield South Yorkshire S10 1DJ",
    "addr:housenumber":"4-8",
    "addr:postcode":"s10 1dj",
    "addr:street":"Harcourt Road",
    "iso:country":"GB",
    "sg:address":"4-8 Harcourt Road",
    "sg:city":"Sheffield",
    "sg:classifiers":[
        {
            "category":"Retail",
            "subcategory":"Auto Repair",
            "type":"Services"
        }
    ],
    "sg:phone":"+44 114 266 4036",
    "sg:postcode":"S10 1DJ",
    "sg:province":"South Yorkshire",
    "sg:tags":[
        "modification",
        "garage"
    ],
    "wof:name":"Simpsons Garage",
    "wof:placetype":"venue"
},
  "geometry": {"coordinates":[-1.493406,53.385029],"type":"Point"}
}