{
  "type": "Feature",
  "properties": {
    "addr:full":"3 St Giles Terrace Northampton Northamptonshire NN1 2BN",
    "addr:housenumber":"3",
    "addr:postcode":"nn1 2bn",
    "addr:street":"St Giles Terrace",
    "iso:country":"GB",
    "sg:address":"3 St Giles Terrace",
    "sg:city":"Northampton",
    "sg:classifiers":[
        {
            "category":"Professional",
            "subcategory":"Lawyer & Legal Services",
            "type":"Services"
        }
    ],
    "sg:postcode":"NN1 2BN",
    "sg:province":"Northamptonshire",
    "sg:tags":[
        "barrister"
    ],
    "wof:name":"Jane Page",
    "wof:placetype":"venue"
},
  "geometry": {"coordinates":[-0.890105,52.238953],"type":"Point"}
}