{
  "type": "Feature",
  "properties": {
    "iso:country":"GB",
    "sg:address":"51 Crabbs Cross Lane, Huntend",
    "sg:city":"Redditch",
    "sg:classifiers":[
        {
            "category":"Professional",
            "subcategory":"Computer Services",
            "type":"Services"
        }
    ],
    "sg:postcode":"B97 5LG",
    "sg:province":"Warwickshire",
    "sg:tags":[
        "consultant"
    ],
    "wof:name":"Modernforce Limited",
    "wof:placetype":"venue"
},
  "geometry": {"coordinates":[-1.943199,52.277451],"type":"Point"}
}