{
  "type": "Feature",
  "properties": {
    "addr:full":"Phoenix House, Barholomewst Newbury Berkshire RG14 5QQ",
    "addr:postcode":"rg14 5qq",
    "addr:street":"Barholomewst Newbury",
    "iso:country":"GB",
    "sg:address":"Phoenix House, Barholomewst",
    "sg:city":"Newbury",
    "sg:classifiers":[
        {
            "category":"Food & Beverages",
            "subcategory":"Meat & Fish",
            "type":"Retail Goods"
        }
    ],
    "sg:postcode":"RG14 5QQ",
    "sg:province":"Berkshire",
    "sg:tags":[
        "butcher"
    ],
    "wof:name":"Yattendon Frozen Foods Ltd",
    "wof:placetype":"venue"
},
  "geometry": {"coordinates":[-1.2901699543,51.3977890015],"type":"Point"}
}