{
  "type": "Feature",
  "properties": {
    "addr:full":"Unit 4 Brook Road Waltham Cross Essex EN8 7NP",
    "addr:housenumber":"unit 4",
    "addr:postcode":"en8 7np",
    "addr:street":"Brook Road",
    "iso:country":"GB",
    "sg:address":"Unit 4 Brook Road",
    "sg:city":"Waltham Cross",
    "sg:classifiers":[
        {
            "category":"Retail",
            "subcategory":"Auto Repair",
            "type":"Services"
        }
    ],
    "sg:phone":"+44 1992 719979",
    "sg:postcode":"EN8 7NP",
    "sg:province":"Essex",
    "sg:tags":[
        "modification",
        "garage"
    ],
    "wof:name":"Autocall",
    "wof:placetype":"venue"
},
  "geometry": {"coordinates":[-0.023254,51.684681],"type":"Point"}
}