{
  "type": "Feature",
  "properties": {
    "iso:country":"GB",
    "sg:address":"Addison Street, Hendon",
    "sg:city":"Sunderland",
    "sg:classifiers":[
        {
            "category":"Wholesale",
            "subcategory":"Non-durable Goods",
            "type":"Manufacturing & Wholesale Goods"
        }
    ],
    "sg:phone":"+44 191 567 1356",
    "sg:postcode":"SR2 8BL",
    "sg:province":"Tyne and Wear",
    "sg:tags":[
        "carry",
        "cash"
    ],
    "wof:name":"Booker Cash & Carry",
    "wof:placetype":"venue"
},
  "geometry": {"coordinates":[-1.366398,54.899982],"type":"Point"}
}