{
  "type": "Feature",
  "properties": {
    "addr:full":"5 Harlaw Road Balerno City of Edinburgh EH14 7BA",
    "addr:housenumber":"5",
    "addr:postcode":"eh14 7ba",
    "addr:street":"Harlaw Road",
    "iso:country":"GB",
    "sg:address":"5 Harlaw Road",
    "sg:city":"Balerno",
    "sg:classifiers":[
        {
            "category":"Utilities",
            "type":"Services"
        }
    ],
    "sg:phone":"+44 131 449 4444",
    "sg:postcode":"EH14 7BA",
    "sg:province":"City of Edinburgh",
    "sg:tags":[
        "internet"
    ],
    "wof:name":"X P T Solutions",
    "wof:placetype":"venue"
},
  "geometry": {"coordinates":[-3.338416,55.881508],"type":"Point"}
}