{
  "type": "Feature",
  "properties": {
    "addr:full":"Unit 8a, Albert Hill Darlington Durham DL1 2NS",
    "addr:housenumber":"unit 8a",
    "addr:postcode":"dl1 2ns",
    "addr:street":"Albert Hill",
    "iso:country":"GB",
    "sg:address":"Unit 8a, Albert Hill",
    "sg:city":"Darlington",
    "sg:classifiers":[
        {
            "category":"Retail",
            "subcategory":"Auto Repair",
            "type":"Services"
        }
    ],
    "sg:phone":"+44 1325 369808",
    "sg:postcode":"DL1 2NS",
    "sg:province":"Durham",
    "sg:tags":[
        "car",
        "specialist",
        "customizing"
    ],
    "wof:name":"Dave Turnbull Tyres",
    "wof:placetype":"venue"
},
  "geometry": {"coordinates":[-1.5522589684,54.5363082886],"type":"Point"}
}