{
  "type": "Feature",
  "properties": {
    "iso:country":"GB",
    "sg:address":"Clifford House, Hampton Heath",
    "sg:city":"Malpas",
    "sg:classifiers":[
        {
            "category":"Organizations",
            "subcategory":"Non-profit Organization",
            "type":"Services"
        }
    ],
    "sg:phone":"+44 1948 820700",
    "sg:postcode":"SY14 8LU",
    "sg:province":"Cheshire",
    "sg:tags":[
        "alarm",
        "system"
    ],
    "wof:name":"Barlows Alarms Ltd.",
    "wof:placetype":"venue"
},
  "geometry": {"coordinates":[-2.766259,53.020981],"type":"Point"}
}