{
  "type": "Feature",
  "properties": {
    "iso:country":"GB",
    "sg:address":"35 Cultins Road",
    "sg:city":"Edinburgh",
    "sg:classifiers":[
        {
            "category":"Home & Garden",
            "subcategory":"Carpets & Floor Coverings",
            "type":"Retail Goods"
        }
    ],
    "sg:phone":"+44 131 442 4544",
    "sg:postcode":"EH11 4DG",
    "sg:province":"City of Edinburgh",
    "sg:tags":[
        "carpets",
        "rug",
        "matting"
    ],
    "wof:name":"Carpetwise",
    "wof:placetype":"venue"
},
  "geometry": {"coordinates":[-3.305282,55.926182],"type":"Point"}
}