{
  "type": "Feature",
  "properties": {
    "iso:country":"GB",
    "sg:address":"11 Apple Industrial Estate, Whittle Avenue, Segensworth West",
    "sg:city":"Fareham",
    "sg:classifiers":[
        {
            "category":"Professional",
            "subcategory":"Detective & Security Services",
            "type":"Services"
        },
        {
            "category":"Manufacturing",
            "subcategory":"Electronics",
            "type":"Manufacturing & Wholesale Goods"
        }
    ],
    "sg:phone":"+44 1489 573888",
    "sg:postcode":"PO15 5SX",
    "sg:province":"Hampshire",
    "sg:tags":[
        "supplier",
        "equipment",
        "manufacturer"
    ],
    "sg:website":"http://www.aspen-international.com",
    "wof:name":"Aspen International Ltd",
    "wof:placetype":"venue"
},
  "geometry": {"coordinates":[-1.257889986,50.8704681396],"type":"Point"}
}