{
  "type": "Feature",
  "properties": {
    "addr:full":"Queensbury Mews Brighton East Sussex BN1 2FE",
    "addr:postcode":"bn1 2fe",
    "addr:street":"Queensbury Mews",
    "iso:country":"GB",
    "sg:address":"Queensbury Mews",
    "sg:city":"Brighton",
    "sg:classifiers":[
        {
            "category":"Bars & Pubs",
            "type":"Food & Drink"
        }
    ],
    "sg:phone":"+44 1273 328159",
    "sg:postcode":"BN1 2FE",
    "sg:province":"East Sussex",
    "sg:tags":[
        "pubs",
        "inn"
    ],
    "wof:name":"Queensbury Arms",
    "wof:placetype":"venue"
},
  "geometry": {"coordinates":[-0.149909,50.822029],"type":"Point"}
}