{
  "type": "Feature",
  "properties": {
    "addr:full":"112 Park Gro Barnsley South Yorkshire S70 1QE",
    "addr:housenumber":"112",
    "addr:postcode":"s70 1qe",
    "addr:street":"Park Gro;Yorkshire",
    "iso:country":"GB",
    "sg:address":"112 Park Gro",
    "sg:city":"Barnsley",
    "sg:classifiers":[
        {
            "category":"Shopping",
            "subcategory":"Clothing, Apparel, & Fashions",
            "type":"Retail Goods"
        }
    ],
    "sg:phone":"+44 1226 296666",
    "sg:postcode":"S70 1QE",
    "sg:province":"South Yorkshire",
    "sg:tags":[
        "clothing",
        "fabric"
    ],
    "wof:name":"Judy Barnsley Garments",
    "wof:placetype":"venue"
},
  "geometry": {"coordinates":[-1.4854700565,53.5470504761],"type":"Point"}
}