{
  "type": "Feature",
  "properties": {
    "addr:full":"29 Hardy Mill Road Bolton Lancashire BL2 4EA",
    "addr:housenumber":"29",
    "addr:postcode":"bl2 4ea",
    "addr:street":"Hardy Mill Road",
    "iso:country":"GB",
    "sg:address":"29 Hardy Mill Road",
    "sg:city":"Bolton",
    "sg:classifiers":[
        {
            "category":"Building & Trades",
            "subcategory":"Construction",
            "type":"Services"
        }
    ],
    "sg:postcode":"BL2 4EA",
    "sg:province":"Lancashire",
    "sg:tags":[
        "builder"
    ],
    "wof:name":"David Peak Builders",
    "wof:placetype":"venue"
},
  "geometry": {"coordinates":[-2.385109,53.60173],"type":"Point"}
}