{
  "type": "Feature",
  "properties": {
    "addr:full":"11 Station Road, Mundesley Norwich Norfolk NR11 8JH",
    "addr:housenumber":"11",
    "addr:postcode":"nr11 8jh",
    "addr:street":"Station Road;Norwich",
    "iso:country":"GB",
    "sg:address":"11 Station Road, Mundesley",
    "sg:city":"Norwich",
    "sg:classifiers":[
        {
            "category":"Real Estate",
            "subcategory":"Real Estate Agent",
            "type":"Services"
        }
    ],
    "sg:phone":"+44 1263 721172",
    "sg:postcode":"NR11 8JH",
    "sg:province":"Norfolk",
    "wof:name":"Howard Page",
    "wof:placetype":"venue"
},
  "geometry": {"coordinates":[1.4333039522,52.876701355],"type":"Point"}
}