{
  "type": "Feature",
  "properties": {
    "iso:country":"GB",
    "sg:address":"2nd Floor",
    "sg:city":"Stockton-on-tees",
    "sg:classifiers":[
        {
            "category":"Professional",
            "subcategory":"Accounting & Tax Preparation",
            "type":"Services"
        }
    ],
    "sg:phone":"+44 1642 675090",
    "sg:postcode":"TS18 1JY",
    "sg:province":"Durham",
    "sg:tags":[
        "accountant"
    ],
    "wof:name":"The Taxation Advice Bureau Ltd.",
    "wof:placetype":"venue"
},
  "geometry": {"coordinates":[-1.323029995,54.5608291626],"type":"Point"}
}