{
  "type": "Feature",
  "properties": {
    "addr:full":"5 Elgerly Terrace London Greater London SW6 6QE",
    "addr:housenumber":"5",
    "addr:postcode":"sw6 6qe",
    "addr:street":"Elgerly Terrace",
    "iso:country":"GB",
    "sg:address":"5 Elgerly Terrace",
    "sg:city":"London",
    "sg:classifiers":[
        {
            "category":"Shopping",
            "subcategory":"Antiques",
            "type":"Retail Goods"
        }
    ],
    "sg:phone":"+44 7956 349510",
    "sg:postcode":"SW6 6QE",
    "sg:province":"Greater London",
    "wof:name":"Robert Barley Antiques",
    "wof:placetype":"venue"
},
  "geometry": {"coordinates":[-0.2135729939,51.4753799438],"type":"Point"}
}