{
  "type": "Feature",
  "properties": {
    "iso:country":"GB",
    "sg:address":"13 Westminster Clo",
    "sg:city":"Basingstoke",
    "sg:classifiers":[
        {
            "category":"Building & Trades",
            "subcategory":"Construction",
            "type":"Services"
        }
    ],
    "sg:phone":"+44 1256 478493",
    "sg:postcode":"RG22 4PP",
    "sg:province":"Hampshire",
    "sg:tags":[
        "decorator",
        "painter"
    ],
    "wof:name":"Paintscape Stencils",
    "wof:placetype":"venue"
},
  "geometry": {"coordinates":[-1.130495,51.241035],"type":"Point"}
}