{
  "type": "Feature",
  "properties": {
    "iso:country":"GB",
    "sg:address":"155a Beaconsfield House, Commercial Street, Pontymister",
    "sg:city":"Newport",
    "sg:classifiers":[
        {
            "category":"Retail",
            "subcategory":"Funeral Services",
            "type":"Services"
        }
    ],
    "sg:postcode":"NP11 6EE",
    "sg:province":"Blaenau Gwent",
    "wof:name":"Tom Phillip & Sons",
    "wof:placetype":"venue"
},
  "geometry": {"coordinates":[-3.09191,51.602772],"type":"Point"}
}