{
  "type": "Feature",
  "properties": {
    "addr:full":"349 Kirkstall Rd Leeds West Yorkshire LS4 2HD",
    "addr:housenumber":"349",
    "addr:postcode":"ls4 2hd",
    "addr:street":"Kirkstall Rd",
    "iso:country":"GB",
    "sg:address":"349 Kirkstall Rd",
    "sg:city":"Leeds",
    "sg:classifiers":[
        {
            "category":"Education",
            "subcategory":"Music School",
            "type":"Public Place"
        }
    ],
    "sg:phone":"+44 113 279 7996",
    "sg:postcode":"LS4 2HD",
    "sg:province":"West Yorkshire",
    "wof:name":"Leeds School of Rock & Jazz",
    "wof:placetype":"venue"
},
  "geometry": {"coordinates":[-1.5839630365,53.8066520691],"type":"Point"}
}