{
  "type": "Feature",
  "properties": {
    "iso:country":"GB",
    "sg:address":"Craigielands Park",
    "sg:city":"Moffat",
    "sg:classifiers":[
        {
            "category":"Food & Beverages",
            "subcategory":"Groceries & Convenience Stores",
            "type":"Retail Goods"
        }
    ],
    "sg:phone":"+44 1683 300223",
    "sg:postcode":"DG10 9RB",
    "sg:province":"Dumfries and Galloway",
    "wof:name":"Beattock Post Office",
    "wof:placetype":"venue"
},
  "geometry": {"coordinates":[-3.442452,55.311562],"type":"Point"}
}