{
  "type": "Feature",
  "properties": {
    "addr:full":"51 Coleshill Road, Curdworth Sutton Coldfield Warwickshire B76 9HA",
    "addr:housenumber":"51",
    "addr:postcode":"b76 9ha",
    "addr:street":"Coleshill Road",
    "iso:country":"GB",
    "sg:address":"51 Coleshill Road, Curdworth",
    "sg:city":"Sutton Coldfield",
    "sg:classifiers":[
        {
            "category":"Building & Trades",
            "subcategory":"Construction",
            "type":"Services"
        }
    ],
    "sg:postcode":"B76 9HA",
    "sg:province":"Warwickshire",
    "sg:tags":[
        "joiner",
        "carpenter"
    ],
    "wof:name":"Avon Enterprises",
    "wof:placetype":"venue"
},
  "geometry": {"coordinates":[-1.736353,52.53236],"type":"Point"}
}