{
  "type": "Feature",
  "properties": {
    "addr:full":"Gorton Retail Market, Gortoncross St Manchester Greater Manchester M18 8LD",
    "addr:postcode":"m18 8ld",
    "addr:street":"Gorton;St",
    "iso:country":"GB",
    "sg:address":"Gorton Retail Market, Gortoncross St",
    "sg:city":"Manchester",
    "sg:classifiers":[
        {
            "category":"Food & Beverages",
            "subcategory":"Meat & Fish",
            "type":"Retail Goods"
        }
    ],
    "sg:phone":"+44 161 223 3495",
    "sg:postcode":"M18 8LD",
    "sg:province":"Greater Manchester",
    "sg:tags":[
        "butcher"
    ],
    "wof:name":"Hamnett's Butchers",
    "wof:placetype":"venue"
},
  "geometry": {"coordinates":[-2.1742339134,53.4618644714],"type":"Point"}
}