{
  "type": "Feature",
  "properties": {
    "iso:country":"GB",
    "sg:address":", Bratton Fleming",
    "sg:city":"Barnstaple",
    "sg:classifiers":[
        {
            "category":"Home & Garden",
            "subcategory":"Building Materials",
            "type":"Retail Goods"
        }
    ],
    "sg:phone":"+44 1598 710493",
    "sg:postcode":"EX31 4SA",
    "sg:province":"Devon",
    "sg:tags":[
        "brick"
    ],
    "wof:name":"Tawside Products",
    "wof:placetype":"venue"
},
  "geometry": {"coordinates":[-4.019449,51.132591],"type":"Point"}
}