{
  "type": "Feature",
  "properties": {
    "iso:country":"GB",
    "sg:address":"51 Haydock St",
    "sg:city":"Warrington",
    "sg:classifiers":[
        {
            "category":"Community Center",
            "type":"Public Place"
        }
    ],
    "sg:phone":"+44 1925 657585",
    "sg:postcode":"WA2 7UW",
    "sg:province":"Cheshire",
    "sg:tags":[
        "centre",
        "entertainment"
    ],
    "wof:name":"Phoenix Production",
    "wof:placetype":"venue"
},
  "geometry": {"coordinates":[-2.591889,53.393951],"type":"Point"}
}