{
  "type": "Feature",
  "properties": {
    "addr:full":"169 Oaks Cross Stevenage Hertfordshire SG2 8NA",
    "addr:housenumber":"169",
    "addr:postcode":"sg2 8na",
    "addr:street":"Oaks Cross",
    "iso:country":"GB",
    "sg:address":"169 Oaks Cross",
    "sg:city":"Stevenage",
    "sg:classifiers":[
        {
            "category":"Communications",
            "type":"Services"
        }
    ],
    "sg:phone":"+44 1438 369373",
    "sg:postcode":"SG2 8NA",
    "sg:province":"Hertfordshire",
    "sg:tags":[
        "telecommunication"
    ],
    "wof:name":"Kelly Communications Ltd",
    "wof:placetype":"venue"
},
  "geometry": {"coordinates":[-0.1715530008,51.8857345581],"type":"Point"}
}