{
  "type": "Feature",
  "properties": {
    "iso:country":"GB",
    "sg:address":"71 Sankey St",
    "sg:city":"Warrington",
    "sg:classifiers":[
        {
            "category":"Professional",
            "subcategory":"Employment Agencies",
            "type":"Services"
        }
    ],
    "sg:phone":"+44 1925 411412",
    "sg:postcode":"WA1 1SL",
    "sg:province":"Cheshire",
    "sg:tags":[
        "consultant"
    ],
    "wof:name":"Hays Public Sector",
    "wof:placetype":"venue"
},
  "geometry": {"coordinates":[-2.5977199078,53.3886566162],"type":"Point"}
}