{
  "type": "Feature",
  "properties": {
    "addr:full":"14 High Street, Burton Latimer Kettering Northamptonshire NN15 5LP",
    "addr:housenumber":"14",
    "addr:postcode":"nn15 5lp",
    "addr:street":"High Street",
    "iso:country":"GB",
    "sg:address":"14 High Street, Burton Latimer",
    "sg:city":"Kettering",
    "sg:classifiers":[
        {
            "category":"Fast Food",
            "type":"Food & Drink"
        }
    ],
    "sg:postcode":"NN15 5LP",
    "sg:province":"Northamptonshire",
    "sg:tags":[
        "away",
        "take"
    ],
    "wof:name":"C R Pizza",
    "wof:placetype":"venue"
},
  "geometry": {"coordinates":[-0.6784890294,52.3637390137],"type":"Point"}
}