{
  "type": "Feature",
  "properties": {
    "iso:country":"GB",
    "sg:address":"Gruinard Pl",
    "sg:city":"Kinross",
    "sg:classifiers":[
        {
            "category":"Building & Trades",
            "subcategory":"Pest Control",
            "type":"Services"
        }
    ],
    "sg:phone":"+44 1577 850296",
    "sg:postcode":"KY13 7LS",
    "sg:province":"Clackmannanshire",
    "sg:tags":[
        "vermin"
    ],
    "wof:name":"P.C.S",
    "wof:placetype":"venue"
},
  "geometry": {"coordinates":[-3.425514,56.211327],"type":"Point"}
}