{
  "type": "Feature",
  "properties": {
    "addr:full":"1260 London Road, Norbury London Greater London SW16 4EG",
    "addr:housenumber":"1260",
    "addr:postcode":"sw16 4eg",
    "addr:street":"London Road",
    "iso:country":"GB",
    "sg:address":"1260 London Road, Norbury",
    "sg:city":"London",
    "sg:classifiers":[
        {
            "category":"Professional",
            "subcategory":"Business Services",
            "type":"Services"
        },
        {
            "category":"Train Station",
            "subcategory":"Rail",
            "type":"Transportation"
        }
    ],
    "sg:phone":"+44 20 8764 5000",
    "sg:postcode":"SW16 4EG",
    "sg:province":"Greater London",
    "sg:tags":[
        "accomodation",
        "railway"
    ],
    "wof:name":"Cavendish Wates Guaranteed Ltd.",
    "wof:placetype":"venue"
},
  "geometry": {"coordinates":[-0.1203410029,51.4060935974],"type":"Point"}
}