{
  "type": "Feature",
  "properties": {
    "addr:full":"Whitegate Road, Whitegate Northwich Cheshire CW8 2AY",
    "addr:postcode":"cw8 2ay",
    "addr:street":"Whitegate Road Whitegate",
    "iso:country":"GB",
    "sg:address":"Whitegate Road, Whitegate",
    "sg:city":"Northwich",
    "sg:classifiers":[
        {
            "category":"Education",
            "subcategory":"School",
            "type":"Public Place"
        },
        {
            "category":"Government",
            "subcategory":"Office",
            "type":"Public Place"
        }
    ],
    "sg:phone":"+44 1606 882006",
    "sg:postcode":"CW8 2AY",
    "sg:province":"Cheshire",
    "sg:tags":[
        "local",
        "authority"
    ],
    "wof:name":"Cheshire County Council",
    "wof:placetype":"venue"
},
  "geometry": {"coordinates":[-2.5673339367,53.2362747192],"type":"Point"}
}