{
  "type": "Feature",
  "properties": {
    "iso:country":"GB",
    "sg:address":"8 Lightborne Road",
    "sg:city":"Sale",
    "sg:classifiers":[
        {
            "category":"Home & Garden",
            "subcategory":"Building Materials",
            "type":"Retail Goods"
        }
    ],
    "sg:phone":"+44 161 973 0816",
    "sg:postcode":"M33 5EA",
    "sg:province":"Cheshire",
    "sg:tags":[
        "fencing"
    ],
    "wof:name":"M & M Fencing Ltd.",
    "wof:placetype":"venue"
},
  "geometry": {"coordinates":[-2.346975,53.424366],"type":"Point"}
}