{
  "type": "Feature",
  "properties": {
    "addr:full":"74 Preston New Road Southport Lancashire PR9 8PH",
    "addr:housenumber":"74",
    "addr:postcode":"pr9 8ph",
    "addr:street":"Preston New Road",
    "iso:country":"GB",
    "sg:address":"74 Preston New Road",
    "sg:city":"Southport",
    "sg:classifiers":[
        {
            "category":"Social Services",
            "subcategory":"Adult Care",
            "type":"Services"
        }
    ],
    "sg:phone":"+44 1704 506969",
    "sg:postcode":"PR9 8PH",
    "sg:province":"Lancashire",
    "sg:tags":[
        "domestic",
        "cleaning"
    ],
    "wof:name":"J J Cleaning Services",
    "wof:placetype":"venue"
},
  "geometry": {"coordinates":[-2.9621250629,53.6651687622],"type":"Point"}
}