{
  "type": "Feature",
  "properties": {
    "iso:country":"GB",
    "sg:address":"Buxton Lane, Blackshaw Moor",
    "sg:city":"Leek",
    "sg:classifiers":[
        {
            "category":"Autos & Motor Vehicles",
            "subcategory":"Fuel & Gas Station",
            "type":"Retail Goods"
        }
    ],
    "sg:phone":"+44 1538 300284",
    "sg:postcode":"ST13 8TL",
    "sg:province":"Staffordshire",
    "sg:tags":[
        "petrol",
        "filling"
    ],
    "wof:name":"J & J Hine",
    "wof:placetype":"venue"
},
  "geometry": {"coordinates":[-1.988398,53.135185],"type":"Point"}
}