{
  "type": "Feature",
  "properties": {
    "addr:full":"Unit 9 Victoria Mill, Victoria Street Accrington Lancashire BB5 0PG",
    "addr:housenumber":"unit 9",
    "addr:postcode":"bb5 0pg",
    "addr:street":"Victoria Mill Victoria Street",
    "iso:country":"GB",
    "sg:address":"Unit 9 Victoria Mill, Victoria Street",
    "sg:city":"Accrington",
    "sg:classifiers":[
        {
            "category":"Autos & Motor Vehicles",
            "subcategory":"Auto Supplies",
            "type":"Retail Goods"
        }
    ],
    "sg:phone":"+44 1254 233515",
    "sg:postcode":"BB5 0PG",
    "sg:province":"Lancashire",
    "sg:tags":[
        "tyre"
    ],
    "wof:name":"Sully's Tyres & Motor Accessories",
    "wof:placetype":"venue"
},
  "geometry": {"coordinates":[-2.3695690632,53.7492408752],"type":"Point"}
}