{
  "type": "Feature",
  "properties": {
    "addr:full":"3 Adelphi Grove Edinburgh City of Edinburgh EH15 1AP",
    "addr:housenumber":"3",
    "addr:postcode":"eh15 1ap",
    "addr:street":"Adelphi Grove",
    "iso:country":"GB",
    "sg:address":"3 Adelphi Grove",
    "sg:city":"Edinburgh",
    "sg:classifiers":[
        {
            "category":"Community Center",
            "type":"Public Place"
        }
    ],
    "sg:phone":"+44 131 669 8275",
    "sg:postcode":"EH15 1AP",
    "sg:province":"City of Edinburgh",
    "sg:tags":[
        "centre"
    ],
    "sg:website":"http://www.portobello.cc",
    "wof:name":"Portobello Community Centre",
    "wof:placetype":"venue"
},
  "geometry": {"coordinates":[-3.11703,55.95438],"type":"Point"}
}