{
  "type": "Feature",
  "properties": {
    "addr:full":"16-22 Baltic Street West Clerkenwell Greater London EC1Y 0UL",
    "addr:housenumber":"16-22",
    "addr:postcode":"ec1y 0ul",
    "addr:street":"Baltic Street West",
    "iso:country":"GB",
    "sg:address":"16-22 Baltic Street West",
    "sg:city":"Clerkenwell",
    "sg:classifiers":[
        {
            "category":"Recreation",
            "subcategory":"Water Park",
            "type":"Entertainment"
        }
    ],
    "sg:phone":"+44 20 7250 0812",
    "sg:postcode":"EC1Y 0UL",
    "sg:province":"Greater London",
    "sg:tags":[
        "merchant",
        "hide",
        "skin"
    ],
    "wof:name":"Theseus (UK) Ltd",
    "wof:placetype":"venue"
},
  "geometry": {"coordinates":[-0.096723,51.523483],"type":"Point"}
}