{
  "type": "Feature",
  "properties": {
    "addr:full":"4 Turnfurlong Lane Aylesbury Buckinghamshire HP21 7PJ",
    "addr:housenumber":"4",
    "addr:postcode":"hp21 7pj",
    "addr:street":"Turnfurlong Lane",
    "iso:country":"GB",
    "sg:address":"4 Turnfurlong Lane",
    "sg:city":"Aylesbury",
    "sg:classifiers":[
        {
            "category":"Home & Garden",
            "subcategory":"Home Furnishings",
            "type":"Retail Goods"
        },
        {
            "category":"Communications",
            "type":"Services"
        }
    ],
    "sg:phone":"+44 1296 487214",
    "sg:postcode":"HP21 7PJ",
    "sg:province":"Buckinghamshire",
    "sg:tags":[
        "planner",
        "tv",
        "furnishers",
        "video",
        "radio",
        "kitchen"
    ],
    "wof:name":"Character Kitchens",
    "wof:placetype":"venue"
},
  "geometry": {"coordinates":[-0.792225,51.807541],"type":"Point"}
}