{
  "type": "Feature",
  "properties": {
    "iso:country":"GB",
    "sg:address":"78-82 Manor Road North",
    "sg:city":"Southampton",
    "sg:classifiers":[
        {
            "category":"Professional",
            "subcategory":"Engineering",
            "type":"Services"
        }
    ],
    "sg:phone":"+44 23 8043 7583",
    "sg:postcode":"SO19 2DU",
    "sg:province":"Hampshire",
    "sg:tags":[
        "contractor",
        "electrical",
        "engineer"
    ],
    "wof:name":"J T Ballard Electrical Contractors",
    "wof:placetype":"venue"
},
  "geometry": {"coordinates":[-1.372867,50.901726],"type":"Point"}
}