{
  "type": "Feature",
  "properties": {
    "iso:country":"GB",
    "sg:address":"23 Green Lane",
    "sg:city":"Dronfield",
    "sg:classifiers":[
        {
            "category":"Shopping",
            "subcategory":"Gifts & Souvenirs",
            "type":"Retail Goods"
        }
    ],
    "sg:phone":"+44 1246 290544",
    "sg:postcode":"S18 2LL",
    "sg:province":"Derbyshire",
    "sg:tags":[
        "shop",
        "giftware"
    ],
    "wof:name":"Stone the Crows",
    "wof:placetype":"venue"
},
  "geometry": {"coordinates":[-1.465498,53.304256],"type":"Point"}
}