{
  "type": "Feature",
  "properties": {
    "iso:country":"GB",
    "sg:address":"5 First Avenue",
    "sg:city":"Wolverhampton",
    "sg:classifiers":[
        {
            "category":"Shopping",
            "subcategory":"News",
            "type":"Retail Goods"
        }
    ],
    "sg:phone":"+44 1902 831514",
    "sg:postcode":"WV10 9SA",
    "sg:province":"Staffordshire",
    "sg:tags":[
        "newsagent"
    ],
    "wof:name":"A & K Newsagents",
    "wof:placetype":"venue"
},
  "geometry": {"coordinates":[-2.1151690483,52.6059684753],"type":"Point"}
}