{
  "type": "Feature",
  "properties": {
    "addr:full":"186b Marsh Road Luton Bedfordshire LU3 2QL",
    "addr:housenumber":"186b",
    "addr:postcode":"lu3 2ql",
    "addr:street":"Marsh Road",
    "iso:country":"GB",
    "sg:address":"186b Marsh Road",
    "sg:city":"Luton",
    "sg:classifiers":[
        {
            "category":"Shopping",
            "subcategory":"Pharmacy",
            "type":"Retail Goods"
        }
    ],
    "sg:phone":"+44 1582 572739",
    "sg:postcode":"LU3 2QL",
    "sg:province":"Bedfordshire",
    "sg:tags":[
        "medical"
    ],
    "wof:name":"Williams Chemists",
    "wof:placetype":"venue"
},
  "geometry": {"coordinates":[-0.453163,51.904671],"type":"Point"}
}