{
  "type": "Feature",
  "properties": {
    "iso:country":"GB",
    "sg:address":"12 Russell Rd",
    "sg:city":"Woking",
    "sg:classifiers":[
        {
            "category":"Sports & Exercise",
            "subcategory":"Swimming Pool",
            "type":"Entertainment"
        }
    ],
    "sg:postcode":"GU21 4UU",
    "sg:province":"Surrey",
    "sg:tags":[
        "bee"
    ],
    "wof:name":"Bees Needs",
    "wof:placetype":"venue"
},
  "geometry": {"coordinates":[-0.5797799826,51.3267288208],"type":"Point"}
}