{
  "type": "Feature",
  "properties": {
    "addr:full":"23 Charlotte Street London Greater London W1T 1RN",
    "addr:housenumber":"23",
    "addr:postcode":"w1t 1rn",
    "addr:street":"Charlotte Street",
    "iso:country":"GB",
    "sg:address":"23 Charlotte Street",
    "sg:city":"London",
    "sg:classifiers":[
        {
            "category":"Organizations",
            "subcategory":"Community Association",
            "type":"Services"
        }
    ],
    "sg:phone":"+44 20 7323 0503",
    "sg:postcode":"W1T 1RN",
    "sg:province":"Greater London",
    "sg:tags":[
        "relation",
        "public"
    ],
    "wof:name":"Maxworks Ltd.",
    "wof:placetype":"venue"
},
  "geometry": {"coordinates":[-0.1351750046,51.518611908],"type":"Point"}
}