{
  "type": "Feature",
  "properties": {
    "iso:country":"GB",
    "sg:address":"84a Kensington High Street",
    "sg:city":"London",
    "sg:classifiers":[
        {
            "category":"Personal",
            "subcategory":"Beauty Salon",
            "type":"Services"
        }
    ],
    "sg:phone":"+44 20 7937 6651",
    "sg:postcode":"W8 4SG",
    "sg:province":"Greater London",
    "sg:tags":[
        "lady",
        "hairdresser"
    ],
    "wof:name":"Kassabis",
    "wof:placetype":"venue"
},
  "geometry": {"coordinates":[-0.1915699989,51.501789093],"type":"Point"}
}