{
  "type": "Feature",
  "properties": {
    "iso:country":"GB",
    "sg:address":"Three Shires Oak Rd, Smethwick",
    "sg:city":"Warley",
    "sg:classifiers":[
        {
            "category":"Shopping",
            "subcategory":"Thrift Store",
            "type":"Retail Goods"
        }
    ],
    "sg:phone":"+44 121 420 2703",
    "sg:postcode":"B67 5BT",
    "sg:province":"West Midlands",
    "sg:tags":[
        "shop",
        "charity"
    ],
    "wof:name":"Animal Welfare Trust",
    "wof:placetype":"venue"
},
  "geometry": {"coordinates":[-1.9740890265,52.4774742126],"type":"Point"}
}