{
  "type": "Feature",
  "properties": {
    "addr:full":"3 Fothergill Street, Treforest Pontypridd Caerphilly CF37 1SG",
    "addr:housenumber":"3",
    "addr:postcode":"cf37 1sg",
    "addr:street":"Fothergill Street",
    "iso:country":"GB",
    "sg:address":"3 Fothergill Street, Treforest",
    "sg:city":"Pontypridd",
    "sg:classifiers":[
        {
            "category":"Personal",
            "subcategory":"Beauty Salon",
            "type":"Services"
        }
    ],
    "sg:postcode":"CF37 1SG",
    "sg:province":"Caerphilly",
    "sg:tags":[
        "unisex",
        "hairdresser"
    ],
    "wof:name":"Keith Hairstylist",
    "wof:placetype":"venue"
},
  "geometry": {"coordinates":[-3.3251988888,51.5940361023],"type":"Point"}
}