{
  "type": "Feature",
  "properties": {
    "iso:country":"GB",
    "sg:address":"44 High Street",
    "sg:city":"Shefford",
    "sg:classifiers":[
        {
            "category":"Manufacturing",
            "subcategory":"Building Materials",
            "type":"Manufacturing & Wholesale Goods"
        }
    ],
    "sg:phone":"+44 1462 813381",
    "sg:postcode":"SG17 5DG",
    "sg:province":"Bedfordshire",
    "sg:tags":[
        "merchant",
        "builder"
    ],
    "wof:name":"Shefford Building Supplies Ltd.",
    "wof:placetype":"venue"
},
  "geometry": {"coordinates":[-0.3359679878,52.0379829407],"type":"Point"}
}