{
  "type": "Feature",
  "properties": {
    "addr:full":"9-21 Shand Street, London Bridge London Greater London SE1 2ES",
    "addr:housenumber":"9-21",
    "addr:postcode":"se1 2es",
    "addr:street":"Shand Street",
    "iso:country":"GB",
    "sg:address":"9-21 Shand Street, London Bridge",
    "sg:city":"London",
    "sg:classifiers":[
        {
            "category":"Government",
            "subcategory":"Post Office",
            "type":"Public Place"
        }
    ],
    "sg:phone":"+44 20 7378 8686",
    "sg:postcode":"SE1 2ES",
    "sg:province":"Greater London",
    "sg:tags":[
        "messenger",
        "courier"
    ],
    "wof:name":"M P C Logistics Ltd.",
    "wof:placetype":"venue"
},
  "geometry": {"coordinates":[-0.080878,51.503307],"type":"Point"}
}