{
  "type": "Feature",
  "properties": {
    "addr:full":"4 Athenaeum Street Sunderland Tyne and Wear SR1 1QX",
    "addr:housenumber":"4",
    "addr:postcode":"sr1 1qx",
    "addr:street":"Athenaeum Street",
    "iso:country":"GB",
    "sg:address":"4 Athenaeum Street",
    "sg:city":"Sunderland",
    "sg:classifiers":[
        {
            "category":"Real Estate",
            "subcategory":"Real Estate Agent",
            "type":"Services"
        }
    ],
    "sg:phone":"+44 191 514 2020",
    "sg:postcode":"SR1 1QX",
    "sg:province":"Tyne and Wear",
    "wof:name":"Thomas Watson",
    "wof:placetype":"venue"
},
  "geometry": {"coordinates":[-1.380381,54.905571],"type":"Point"}
}