{
  "type": "Feature",
  "properties": {
    "addr:full":"416 Lewis Estate, Ixworth Place London Greater London SW3 3QE",
    "addr:housenumber":"416",
    "addr:postcode":"sw3 3qe",
    "addr:street":"Lewis Estate Ixworth Place",
    "iso:country":"GB",
    "sg:address":"416 Lewis Estate, Ixworth Place",
    "sg:city":"London",
    "sg:classifiers":[
        {
            "category":"Personal",
            "subcategory":"Beauty Salon",
            "type":"Services"
        }
    ],
    "sg:phone":"+44 20 7386 5222",
    "sg:postcode":"SW3 3QE",
    "sg:province":"Greater London",
    "wof:name":"Nail Emporium Ltd (The)",
    "wof:placetype":"venue"
},
  "geometry": {"coordinates":[-0.16949,51.491718],"type":"Point"}
}