{
  "type": "Feature",
  "properties": {
    "addr:full":"461 Clarkston Road Glasgow East Renfrewshire G44 3LW",
    "addr:housenumber":"461",
    "addr:postcode":"g44 3lw",
    "addr:street":"Clarkston Road",
    "iso:country":"GB",
    "sg:address":"461 Clarkston Road",
    "sg:city":"Glasgow",
    "sg:classifiers":[
        {
            "category":"Shopping",
            "subcategory":"Clothing, Apparel, & Fashions",
            "type":"Retail Goods"
        }
    ],
    "sg:phone":"+44 141 633 0078",
    "sg:postcode":"G44 3LW",
    "sg:province":"East Renfrewshire",
    "sg:tags":[
        "shop",
        "hat"
    ],
    "wof:name":"Ella Bulloch",
    "wof:placetype":"venue"
},
  "geometry": {"coordinates":[-4.270926,55.809948],"type":"Point"}
}