{
  "type": "Feature",
  "properties": {
    "addr:full":"248 Twickenham Rd Isleworth Greater London TW7 7DT",
    "addr:housenumber":"248",
    "addr:postcode":"tw7 7dt",
    "addr:street":"Twickenham Rd",
    "iso:country":"GB",
    "sg:address":"248 Twickenham Rd",
    "sg:city":"Isleworth",
    "sg:classifiers":[
        {
            "category":"Food & Beverages",
            "subcategory":"Meat & Fish",
            "type":"Retail Goods"
        }
    ],
    "sg:phone":"+44 20 8891 3232",
    "sg:postcode":"TW7 7DT",
    "sg:province":"Greater London",
    "sg:tags":[
        "chip"
    ],
    "wof:name":"Mario's Marvellous Fish & Chips",
    "wof:placetype":"venue"
},
  "geometry": {"coordinates":[-0.3312419951,51.4639816284],"type":"Point"}
}