{
  "type": "Feature",
  "properties": {
    "addr:full":"14 Peveril St Nottingham Nottinghamshire NG7 4AL",
    "addr:housenumber":"14",
    "addr:postcode":"ng7 4al",
    "addr:street":"Peveril St",
    "iso:country":"GB",
    "sg:address":"14 Peveril St",
    "sg:city":"Nottingham",
    "sg:classifiers":[
        {
            "category":"Personal",
            "subcategory":"Barber",
            "type":"Services"
        }
    ],
    "sg:phone":"+44 115 979 2113",
    "sg:postcode":"NG7 4AL",
    "sg:province":"Nottinghamshire",
    "sg:tags":[
        "men's",
        "hairdresser"
    ],
    "wof:name":"Edward's",
    "wof:placetype":"venue"
},
  "geometry": {"coordinates":[-1.167924,52.959572],"type":"Point"}
}