{
  "type": "Feature",
  "properties": {
    "addr:full":"1-6 Raglan Precinct, Town End Caterham Surrey CR3 5UG",
    "addr:housenumber":"1-6",
    "addr:postcode":"cr3 5ug",
    "iso:country":"GB",
    "sg:address":"1-6 Raglan Precinct, Town End",
    "sg:city":"Caterham",
    "sg:classifiers":[
        {
            "category":"Food & Beverages",
            "subcategory":"Groceries & Convenience Stores",
            "type":"Retail Goods"
        }
    ],
    "sg:phone":"+44 1883 347338",
    "sg:postcode":"CR3 5UG",
    "sg:province":"Surrey",
    "wof:name":"Alldays Stores",
    "wof:placetype":"venue"
},
  "geometry": {"coordinates":[-0.076936,51.281578],"type":"Point"}
}