{
  "type": "Feature",
  "properties": {
    "addr:full":"1 Market St Bingley West Yorkshire BD16 2HP",
    "addr:housenumber":"1",
    "addr:postcode":"bd16 2hp",
    "addr:street":"Market St",
    "iso:country":"GB",
    "sg:address":"1 Market St",
    "sg:city":"Bingley",
    "sg:classifiers":[
        {
            "category":"Banks & Credit Unions",
            "subcategory":"Investment Brokerage",
            "type":"Services"
        }
    ],
    "sg:phone":"+44 1274 551101",
    "sg:postcode":"BD16 2HP",
    "sg:province":"West Yorkshire",
    "sg:tags":[
        "overseas",
        "property",
        "agent"
    ],
    "wof:name":"Sol European Property",
    "wof:placetype":"venue"
},
  "geometry": {"coordinates":[-1.8389240503,53.8489112854],"type":"Point"}
}