{
  "type": "Feature",
  "properties": {
    "addr:full":"Block 23 Unit C Landport Road Indust Est Wolverhampton West Midlands WV2 2QJ",
    "addr:housenumber":"unit c",
    "addr:postcode":"wv2 2qj",
    "addr:street":"Landport Road",
    "iso:country":"GB",
    "sg:address":"Block 23 Unit C Landport Road Indust Est",
    "sg:city":"Wolverhampton",
    "sg:classifiers":[
        {
            "category":"Building & Trades",
            "subcategory":"Construction",
            "type":"Services"
        }
    ],
    "sg:phone":"+44 1902 450750",
    "sg:postcode":"WV2 2QJ",
    "sg:province":"West Midlands",
    "sg:tags":[
        "glazier"
    ],
    "wof:name":"Codsall Glass Centre",
    "wof:placetype":"venue"
},
  "geometry": {"coordinates":[-2.1086099148,52.5792694092],"type":"Point"}
}