{
  "type": "Feature",
  "properties": {
    "addr:full":"14-16 Shore Rd Hackney Greater London E9 7TA",
    "addr:housenumber":"14-16",
    "addr:postcode":"e9 7ta",
    "addr:street":"Shore Rd",
    "iso:country":"GB",
    "sg:address":"14-16 Shore Rd",
    "sg:city":"Hackney",
    "sg:classifiers":[
        {
            "category":"Communications",
            "subcategory":"Film & Video Production",
            "type":"Services"
        }
    ],
    "sg:phone":"+44 20 8985 3394",
    "sg:postcode":"E9 7TA",
    "sg:province":"Greater London",
    "sg:tags":[
        "recording",
        "studio"
    ],
    "wof:name":"Omni Studios Ltd",
    "wof:placetype":"venue"
},
  "geometry": {"coordinates":[-0.0527740009,51.5390510559],"type":"Point"}
}