{
  "type": "Feature",
  "properties": {
    "addr:full":"63 Sandgate Rd Folkestone Kent CT20 1RY",
    "addr:housenumber":"63",
    "addr:postcode":"ct20 1ry",
    "addr:street":"Sandgate Rd",
    "iso:country":"GB",
    "sg:address":"63 Sandgate Rd",
    "sg:city":"Folkestone",
    "sg:classifiers":[
        {
            "category":"Shopping",
            "subcategory":"Clothing, Apparel, & Fashions",
            "type":"Retail Goods"
        }
    ],
    "sg:phone":"+44 1303 244784",
    "sg:postcode":"CT20 1RY",
    "sg:province":"Kent",
    "sg:tags":[
        "menswear"
    ],
    "wof:name":"Ciro Citterio",
    "wof:placetype":"venue"
},
  "geometry": {"coordinates":[1.178075,51.078098],"type":"Point"}
}