{
  "type": "Feature",
  "properties": {
    "iso:country":"GB",
    "sg:address":"Low Colwith, Little Langdale",
    "sg:city":"Ambleside",
    "sg:classifiers":[
        {
            "category":"Home & Garden",
            "subcategory":"Home Furnishings",
            "type":"Retail Goods"
        },
        {
            "category":"Home & Garden",
            "subcategory":"Furniture",
            "type":"Retail Goods"
        }
    ],
    "sg:phone":"+44 15394 32847",
    "sg:postcode":"LA22 9NU",
    "sg:province":"Cumbria",
    "sg:tags":[
        "fitted"
    ],
    "wof:name":"Colwith Interiors Ltd",
    "wof:placetype":"venue"
},
  "geometry": {"coordinates":[-2.963089,54.432606],"type":"Point"}
}