{
  "type": "Feature",
  "properties": {
    "addr:full":"Brier Hill Close, Hartshead Moor Cleckheaton West Yorkshire BD19 6ND",
    "addr:postcode":"bd19 6nd",
    "addr:street":"Brier Hill Close Hartshead Moor",
    "iso:country":"GB",
    "sg:address":"Brier Hill Close, Hartshead Moor",
    "sg:city":"Cleckheaton",
    "sg:classifiers":[
        {
            "category":"Professional",
            "subcategory":"Management & Consulting",
            "type":"Services"
        }
    ],
    "sg:phone":"+44 1274 879232",
    "sg:postcode":"BD19 6ND",
    "sg:province":"West Yorkshire",
    "sg:tags":[
        "consultant",
        "business"
    ],
    "wof:name":"Oxford Holt & Co Ltd",
    "wof:placetype":"venue"
},
  "geometry": {"coordinates":[-1.7406109571,53.7181243896],"type":"Point"}
}