{
  "type": "Feature",
  "properties": {
    "iso:country":"GB",
    "sg:address":"9 Hudson Rd",
    "sg:city":"Sunderland",
    "sg:classifiers":[
        {
            "category":"Shopping",
            "subcategory":"News",
            "type":"Retail Goods"
        }
    ],
    "sg:phone":"+44 191 567 3326",
    "sg:postcode":"SR1 2AQ",
    "sg:province":"Tyne and Wear",
    "sg:tags":[
        "newsagent"
    ],
    "wof:name":"Drinkstop Northeast Ltd",
    "wof:placetype":"venue"
},
  "geometry": {"coordinates":[-1.375241,54.904957],"type":"Point"}
}