{
  "type": "Feature",
  "properties": {
    "iso:country":"GB",
    "sg:address":"252a High Street",
    "sg:city":"Kirkcaldy",
    "sg:classifiers":[
        {
            "category":"Personal",
            "subcategory":"Beauty Salon",
            "type":"Services"
        }
    ],
    "sg:phone":"+44 1592 641444",
    "sg:postcode":"KY1 1LA",
    "sg:province":"Fife",
    "sg:tags":[
        "unisex",
        "hairdresser"
    ],
    "wof:name":"R G Hairdressing",
    "wof:placetype":"venue"
},
  "geometry": {"coordinates":[-3.1559400558,56.1124763489],"type":"Point"}
}