{
  "type": "Feature",
  "properties": {
    "addr:full":"27 Queens Road Weybridge Surrey KT13 9UG",
    "addr:housenumber":"27",
    "addr:postcode":"kt13 9ug",
    "addr:street":"Queens Road",
    "iso:country":"GB",
    "sg:address":"27 Queens Road",
    "sg:city":"Weybridge",
    "sg:classifiers":[
        {
            "category":"Home & Garden",
            "subcategory":"Home Furnishings",
            "type":"Retail Goods"
        }
    ],
    "sg:phone":"+44 1932 821448",
    "sg:postcode":"KT13 9UG",
    "sg:province":"Surrey",
    "sg:tags":[
        "furnishers",
        "planner",
        "kitchen"
    ],
    "wof:name":"Re-Design",
    "wof:placetype":"venue"
},
  "geometry": {"coordinates":[-0.4473119974,51.368938446],"type":"Point"}
}