{
  "type": "Feature",
  "properties": {
    "iso:country":"GB",
    "sg:address":"Birkett Lodge, Fourteen Acre La, Three Oaks",
    "sg:city":"Hastings",
    "sg:classifiers":[
        {
            "category":"Home & Garden",
            "subcategory":"Home Furnishings",
            "type":"Retail Goods"
        }
    ],
    "sg:postcode":"TN35 4NB",
    "sg:province":"East Sussex",
    "sg:tags":[
        "beds",
        "bedding",
        "blanket"
    ],
    "wof:name":"Alfresco Distribution",
    "wof:placetype":"venue"
},
  "geometry": {"coordinates":[0.61367,50.901669],"type":"Point"}
}