{
  "type": "Feature",
  "properties": {
    "iso:country":"GB",
    "sg:address":"12 Baker Street",
    "sg:city":"Weston-super-mare",
    "sg:classifiers":[
        {
            "category":"Shopping",
            "subcategory":"Used Merchandise",
            "type":"Retail Goods"
        }
    ],
    "sg:phone":"+44 1934 645882",
    "sg:postcode":"BS23 3AE",
    "sg:province":"Somerset",
    "sg:tags":[
        "shop",
        "second-hand"
    ],
    "wof:name":"Toddys",
    "wof:placetype":"venue"
},
  "geometry": {"coordinates":[-2.972672,51.348923],"type":"Point"}
}