{
  "type": "Feature",
  "properties": {
    "addr:full":"17 Russell Avenue St Albans Hertfordshire AL3 5ES",
    "addr:housenumber":"17",
    "addr:postcode":"al3 5es",
    "addr:street":"Russell Avenue",
    "iso:country":"GB",
    "sg:address":"17 Russell Avenue",
    "sg:city":"St Albans",
    "sg:classifiers":[
        {
            "category":"Personal",
            "subcategory":"Beauty Salon",
            "type":"Services"
        }
    ],
    "sg:phone":"+44 1727 833808",
    "sg:postcode":"AL3 5ES",
    "sg:province":"Hertfordshire",
    "wof:name":"Russell Slimming Clinic",
    "wof:placetype":"venue"
},
  "geometry": {"coordinates":[-0.339996,51.754215],"type":"Point"}
}