{
  "type": "Feature",
  "properties": {
    "addr:full":"26 High Street, Soham Ely Cambridgeshire CB7 5HE",
    "addr:housenumber":"26",
    "addr:postcode":"cb7 5he",
    "addr:street":"High Street",
    "iso:country":"GB",
    "sg:address":"26 High Street, Soham",
    "sg:city":"Ely",
    "sg:classifiers":[
        {
            "category":"Shopping",
            "subcategory":"Used Merchandise",
            "type":"Retail Goods"
        }
    ],
    "sg:postcode":"CB7 5HE",
    "sg:province":"Cambridgeshire",
    "sg:tags":[
        "shop",
        "second-hand"
    ],
    "wof:name":"Fred's Alsorts",
    "wof:placetype":"venue"
},
  "geometry": {"coordinates":[0.3387,52.332302],"type":"Point"}
}