{
  "type": "Feature",
  "properties": {
    "iso:country":"GB",
    "sg:address":"164 Warrington Road",
    "sg:city":"Widnes",
    "sg:classifiers":[
        {
            "category":"Health Services",
            "subcategory":"Nursing And Care Facility",
            "type":"Services"
        }
    ],
    "sg:phone":"+44 151 424 5347",
    "sg:postcode":"WA8 0AT",
    "sg:province":"Cheshire",
    "sg:tags":[
        "home"
    ],
    "wof:name":"Woodcrofts Residential Homes Ltd.",
    "wof:placetype":"venue"
},
  "geometry": {"coordinates":[-2.7122991085,53.3721466064],"type":"Point"}
}