{
  "type": "Feature",
  "properties": {
    "addr:full":"Queenswood House, Eastfield Road Brentwood Essex CM14 4HF",
    "addr:postcode":"cm14 4hf",
    "addr:street":"Eastfield Road",
    "iso:country":"GB",
    "sg:address":"Queenswood House, Eastfield Road",
    "sg:city":"Brentwood",
    "sg:classifiers":[
        {
            "category":"Health Services",
            "subcategory":"Nursing And Care Facility",
            "type":"Services"
        },
        {
            "category":"Organizations",
            "subcategory":"Community Association",
            "type":"Services"
        }
    ],
    "sg:phone":"+44 1277 263226",
    "sg:postcode":"CM14 4HF",
    "sg:province":"Essex",
    "sg:tags":[
        "residential",
        "housing",
        "society"
    ],
    "wof:name":"Warden Housing Association Ltd.",
    "wof:placetype":"venue"
},
  "geometry": {"coordinates":[0.305366,51.618088],"type":"Point"}
}