{
  "type": "Feature",
  "properties": {
    "addr:full":"17 Liverpool Road Warrington Cheshire WA5 1EG",
    "addr:housenumber":"17",
    "addr:postcode":"wa5 1eg",
    "addr:street":"Liverpool Road",
    "iso:country":"GB",
    "sg:address":"17 Liverpool Road",
    "sg:city":"Warrington",
    "sg:classifiers":[
        {
            "category":"Retail",
            "subcategory":"Driving School",
            "type":"Services"
        }
    ],
    "sg:postcode":"WA5 1EG",
    "sg:province":"Cheshire",
    "sg:tags":[
        "instruction",
        "cycling",
        "motor"
    ],
    "wof:name":"Stuart Smith",
    "wof:placetype":"venue"
},
  "geometry": {"coordinates":[-2.6084589958,53.3887405396],"type":"Point"}
}