{
  "type": "Feature",
  "properties": {
    "iso:country":"GB",
    "sg:address":"48 Main Street",
    "sg:city":"Callander",
    "sg:classifiers":[
        {
            "category":"Ice Cream",
            "type":"Food & Drink"
        }
    ],
    "sg:phone":"+44 1877 330109",
    "sg:postcode":"FK17 8BD",
    "sg:province":"Stirling",
    "sg:tags":[
        "shop",
        "mobile",
        "parlour"
    ],
    "wof:name":"Asher's Ice Cream",
    "wof:placetype":"venue"
},
  "geometry": {"coordinates":[-4.215877,56.243896],"type":"Point"}
}