{
  "type": "Feature",
  "properties": {
    "addr:full":"7 Churchill Close, Flackwell Heath High Wycombe Buckinghamshire HP10 9LA",
    "addr:housenumber":"7",
    "addr:postcode":"hp10 9la",
    "addr:street":"Churchill Close",
    "iso:country":"GB",
    "sg:address":"7 Churchill Close, Flackwell Heath",
    "sg:city":"High Wycombe",
    "sg:classifiers":[
        {
            "category":"Retail",
            "subcategory":"Repair Shop",
            "type":"Services"
        }
    ],
    "sg:phone":"+44 1628 530626",
    "sg:postcode":"HP10 9LA",
    "sg:province":"Buckinghamshire",
    "sg:tags":[
        "upholstering",
        "upholsterer"
    ],
    "wof:name":"Steve Ashby Upholstery & Curtain Services",
    "wof:placetype":"venue"
},
  "geometry": {"coordinates":[-0.703602,51.594936],"type":"Point"}
}