{
  "type": "Feature",
  "properties": {
    "addr:full":"Units 22a & 22b Blackmore Park Indust Est, Blackmore Park Worcester Gloucestershire WR8 0EF",
    "addr:housenumber":"units 22a & 22b",
    "addr:postcode":"wr8 0ef",
    "addr:street":"Blackmore Park Indust Est;Park",
    "iso:country":"GB",
    "sg:address":"Units 22a & 22b Blackmore Park Indust Est, Blackmore Park",
    "sg:city":"Worcester",
    "sg:classifiers":[
        {
            "category":"Retail",
            "subcategory":"Auto Repair",
            "type":"Services"
        }
    ],
    "sg:phone":"+44 1684 893730",
    "sg:postcode":"WR8 0EF",
    "sg:province":"Gloucestershire",
    "sg:tags":[
        "modification",
        "garage"
    ],
    "wof:name":"Malvern 2cV Centre",
    "wof:placetype":"venue"
},
  "geometry": {"coordinates":[-2.2969400883,52.0908203125],"type":"Point"}
}