{
  "type": "Feature",
  "properties": {
    "addr:full":"116 Holland Park Avenue London Greater London W11 4UA",
    "addr:housenumber":"116",
    "addr:postcode":"w11 4ua",
    "addr:street":"Holland Park Avenue",
    "iso:country":"GB",
    "sg:address":"116 Holland Park Avenue",
    "sg:city":"London",
    "sg:classifiers":[
        {
            "category":"Fast Food",
            "type":"Food & Drink"
        }
    ],
    "sg:phone":"+44 20 7221 3380",
    "sg:postcode":"W11 4UA",
    "sg:province":"Greater London",
    "sg:tags":[
        "away",
        "meal",
        "outlet",
        "take"
    ],
    "wof:name":"Home Delivery Pizza Co Ltd (The)",
    "wof:placetype":"venue"
},
  "geometry": {"coordinates":[-0.209909,51.50602],"type":"Point"}
}