{
  "type": "Feature",
  "properties": {
    "addr:full":"58 Middle Street Consett Durham DH8 5QJ",
    "addr:housenumber":"58",
    "addr:postcode":"dh8 5qj",
    "addr:street":"Middle Street",
    "iso:country":"GB",
    "sg:address":"58 Middle Street",
    "sg:city":"Consett",
    "sg:classifiers":[
        {
            "category":"Shopping",
            "subcategory":"Clothing, Apparel, & Fashions",
            "type":"Retail Goods"
        }
    ],
    "sg:postcode":"DH8 5QJ",
    "sg:province":"Durham",
    "sg:tags":[
        "shop"
    ],
    "wof:name":"Colins Clobber Cabin",
    "wof:placetype":"venue"
},
  "geometry": {"coordinates":[-1.834414959,54.8531188965],"type":"Point"}
}