{
  "type": "Feature",
  "properties": {
    "addr:full":"Oxford Rd Chipping Norton Gloucestershire OX7 4LG",
    "addr:postcode":"ox7 4lg",
    "addr:street":"Oxford Rd",
    "iso:country":"GB",
    "sg:address":"Oxford Rd",
    "sg:city":"Chipping Norton",
    "sg:classifiers":[
        {
            "category":"Shopping",
            "subcategory":"News",
            "type":"Retail Goods"
        }
    ],
    "sg:phone":"+44 1608 677233",
    "sg:postcode":"OX7 4LG",
    "sg:province":"Gloucestershire",
    "sg:tags":[
        "newsagent"
    ],
    "wof:name":"Enstone Post Office Stores",
    "wof:placetype":"venue"
},
  "geometry": {"coordinates":[-1.457072,51.918789],"type":"Point"}
}