{
  "type": "Feature",
  "properties": {
    "addr:full":"Broadgate, Grasmere Ambleside Cumbria LA22 9TA",
    "addr:postcode":"la22 9ta",
    "addr:street":"Broadgate;Ambleside",
    "iso:country":"GB",
    "sg:address":"Broadgate, Grasmere",
    "sg:city":"Ambleside",
    "sg:classifiers":[
        {
            "category":"Travel",
            "subcategory":"Hotels & Motels",
            "type":"Entertainment"
        }
    ],
    "sg:phone":"+44 15394 35277",
    "sg:postcode":"LA22 9TA",
    "sg:province":"Cumbria",
    "wof:name":"Grasmere Hotel",
    "wof:placetype":"venue"
},
  "geometry": {"coordinates":[-2.963089,54.432606],"type":"Point"}
}