{
  "type": "Feature",
  "properties": {
    "addr:full":"114 Randall Rd London Greater London SE11 5JR",
    "addr:housenumber":"114",
    "addr:postcode":"se11 5jr",
    "addr:street":"Randall Rd",
    "iso:country":"GB",
    "sg:address":"114 Randall Rd",
    "sg:city":"London",
    "sg:classifiers":[
        {
            "category":"Brewery",
            "type":"Food & Drink"
        }
    ],
    "sg:phone":"+44 20 7793 0803",
    "sg:postcode":"SE11 5JR",
    "sg:province":"Greater London",
    "sg:tags":[
        "brewer"
    ],
    "wof:name":"O'Hanlon Brewing Co",
    "wof:placetype":"venue"
},
  "geometry": {"coordinates":[-0.121184,51.490726],"type":"Point"}
}