{
  "type": "Feature",
  "properties": {
    "addr:full":"Bridge Gate Centre, Martinfield Welwyn Garden City Hertfordshire AL7 1JG",
    "addr:postcode":"al7 1jg",
    "addr:street":"Bridge Gate;Martinfield",
    "iso:country":"GB",
    "sg:address":"Bridge Gate Centre, Martinfield",
    "sg:city":"Welwyn Garden City",
    "sg:classifiers":[
        {
            "category":"Professional",
            "subcategory":"Detective & Security Services",
            "type":"Services"
        }
    ],
    "sg:phone":"+44 1707 395980",
    "sg:postcode":"AL7 1JG",
    "sg:province":"Hertfordshire",
    "sg:tags":[
        "equipment"
    ],
    "wof:name":"Sarax Systems Ltd.",
    "wof:placetype":"venue"
},
  "geometry": {"coordinates":[-0.2010609955,51.8025627136],"type":"Point"}
}