{
  "type": "Feature",
  "properties": {
    "addr:full":"317 Prestwick Road Watford Hertfordshire WD19 6UT",
    "addr:housenumber":"317",
    "addr:postcode":"wd19 6ut",
    "addr:street":"Prestwick Road",
    "iso:country":"GB",
    "sg:address":"317 Prestwick Road",
    "sg:city":"Watford",
    "sg:classifiers":[
        {
            "category":"Food & Beverages",
            "subcategory":"Supermarket",
            "type":"Retail Goods"
        }
    ],
    "sg:phone":"+44 20 8428 0891",
    "sg:postcode":"WD19 6UT",
    "sg:province":"Hertfordshire",
    "wof:name":"S & V Food Fare",
    "wof:placetype":"venue"
},
  "geometry": {"coordinates":[-0.394136,51.616776],"type":"Point"}
}