{
  "type": "Feature",
  "properties": {
    "iso:country":"GB",
    "sg:address":"317 Prestwick Road",
    "sg:city":"Watford",
    "sg:classifiers":[
        {
            "category":"Food & Beverages",
            "subcategory":"Supermarket",
            "type":"Retail Goods"
        }
    ],
    "sg:phone":"+44 20 8428 0891",
    "sg:postcode":"WD19 6UT",
    "sg:province":"Hertfordshire",
    "wof:name":"S & V Food Fare",
    "wof:placetype":"venue"
},
  "geometry": {"coordinates":[-0.394136,51.616776],"type":"Point"}
}