{
  "type": "Feature",
  "properties": {
    "iso:country":"GB",
    "sg:address":"The Bridge, New Rd, Newlyn",
    "sg:city":"Penzance",
    "sg:classifiers":[
        {
            "category":"Food & Beverages",
            "subcategory":"Meat & Fish",
            "type":"Retail Goods"
        }
    ],
    "sg:phone":"+44 1736 362760",
    "sg:postcode":"TR18 5PZ",
    "sg:province":"Cornwall",
    "sg:tags":[
        "butcher"
    ],
    "wof:name":"Lentern,Ian,",
    "wof:placetype":"venue"
},
  "geometry": {"coordinates":[-5.552408,50.101761],"type":"Point"}
}