{
  "type": "Feature",
  "properties": {
    "addr:full":"104 Belmont Road Liverpool Merseyside L6 5BJ",
    "addr:housenumber":"104",
    "addr:postcode":"l6 5bj",
    "addr:street":"Belmont Road",
    "iso:country":"GB",
    "sg:address":"104 Belmont Road",
    "sg:city":"Liverpool",
    "sg:classifiers":[
        {
            "category":"Real Estate",
            "subcategory":"Real Estate Agent",
            "type":"Services"
        }
    ],
    "sg:phone":"+44 151 263 1527",
    "sg:postcode":"L6 5BJ",
    "sg:province":"Merseyside",
    "wof:name":"John Parry Estates Ltd.",
    "wof:placetype":"venue"
},
  "geometry": {"coordinates":[-2.951853,53.423836],"type":"Point"}
}