{
  "type": "Feature",
  "properties": {
    "addr:full":"The School House, Port Of Menteith Stirling Stirling FK8 3RA",
    "addr:postcode":"fk8 3ra",
    "addr:street":"Port;Menteith",
    "iso:country":"GB",
    "sg:address":"The School House, Port Of Menteith",
    "sg:city":"Stirling",
    "sg:classifiers":[
        {
            "category":"Building & Trades",
            "subcategory":"Construction",
            "type":"Services"
        }
    ],
    "sg:postcode":"FK8 3RA",
    "sg:province":"Stirling",
    "sg:tags":[
        "joiner",
        "carpenter"
    ],
    "wof:name":"John Johnston",
    "wof:placetype":"venue"
},
  "geometry": {"coordinates":[-4.2605190277,56.1528587341],"type":"Point"}
}