{
  "type": "Feature",
  "properties": {
    "addr:full":"2a The Store, Abercrombie Business Centre High Wycombe Buckinghamshire HP12 3AX",
    "addr:housenumber":"2a",
    "addr:postcode":"hp12 3ax",
    "addr:street":"The;Abercrombie",
    "iso:country":"GB",
    "sg:address":"2a The Store, Abercrombie Business Centre",
    "sg:city":"High Wycombe",
    "sg:classifiers":[
        {
            "category":"Retail",
            "subcategory":"Storage",
            "type":"Services"
        }
    ],
    "sg:phone":"+44 1494 445502",
    "sg:postcode":"HP12 3AX",
    "sg:province":"Buckinghamshire",
    "sg:tags":[
        "household",
        "removal"
    ],
    "wof:name":"A & S.G. James Removals & Storage",
    "wof:placetype":"venue"
},
  "geometry": {"coordinates":[-0.76785,51.634129],"type":"Point"}
}