{
  "type": "Feature",
  "properties": {
    "iso:country":"GB",
    "sg:address":"Gene House, Queenborough Lane, Rayne",
    "sg:city":"Braintree",
    "sg:classifiers":[
        {
            "category":"Professional",
            "subcategory":"Testing Lab",
            "type":"Services"
        }
    ],
    "sg:phone":"+44 1376 332900",
    "sg:postcode":"CM77 6TZ",
    "sg:province":"Essex",
    "sg:tags":[
        "laboratory"
    ],
    "wof:name":"Genetic Research Instrumentation Ltd.",
    "wof:placetype":"venue"
},
  "geometry": {"coordinates":[0.516334,51.872581],"type":"Point"}
}