{
  "type": "Feature",
  "properties": {
    "addr:full":"Green Lane House Gateshead Tyne and Wear NE8 3AH",
    "addr:postcode":"ne8 3ah",
    "addr:street":"Green Lane House",
    "iso:country":"GB",
    "sg:address":"Green Lane House",
    "sg:city":"Gateshead",
    "sg:classifiers":[
        {
            "category":"Retail",
            "subcategory":"Auto Rental",
            "type":"Services"
        }
    ],
    "sg:phone":"+44 191 477 7788",
    "sg:postcode":"NE8 3AH",
    "sg:province":"Tyne and Wear",
    "sg:tags":[
        "truck",
        "hire",
        "van"
    ],
    "wof:name":"Highway Truck Rental Ltd.",
    "wof:placetype":"venue"
},
  "geometry": {"coordinates":[-1.6020460129,54.9610404968],"type":"Point"}
}