{
  "type": "Feature",
  "properties": {
    "iso:country":"GB",
    "sg:address":"Building 32 Bay 4 Second Avenue, Pensnett Trading Estate, Kingswinford",
    "sg:city":"Brierley Hill",
    "sg:classifiers":[
        {
            "category":"Manufacturing",
            "subcategory":"Metals",
            "type":"Manufacturing & Wholesale Goods"
        }
    ],
    "sg:phone":"+44 1384 402558",
    "sg:postcode":"DY6 7PP",
    "sg:province":"Staffordshire",
    "sg:tags":[
        "work",
        "sheet"
    ],
    "wof:name":"B & M Sheet Metal Ltd.",
    "wof:placetype":"venue"
},
  "geometry": {"coordinates":[-2.144964,52.509171],"type":"Point"}
}