{
  "type": "Feature",
  "properties": {
    "addr:full":"106 Teignmouth Rd Torquay Devon TQ1 4EX",
    "addr:housenumber":"106",
    "addr:postcode":"tq1 4ex",
    "addr:street":"Teignmouth Rd",
    "iso:country":"GB",
    "sg:address":"106 Teignmouth Rd",
    "sg:city":"Torquay",
    "sg:classifiers":[
        {
            "category":"Professional",
            "subcategory":"Management & Consulting",
            "type":"Services"
        }
    ],
    "sg:phone":"+44 1803 664296",
    "sg:postcode":"TQ1 4EX",
    "sg:province":"Devon",
    "sg:tags":[
        "consultant",
        "safety"
    ],
    "wof:name":"Safety Services Group",
    "wof:placetype":"venue"
},
  "geometry": {"coordinates":[-3.53699,50.479645],"type":"Point"}
}