{
  "type": "Feature",
  "properties": {
    "iso:country":"GB",
    "sg:address":"90 High St",
    "sg:city":"Harrow",
    "sg:classifiers":[
        {
            "category":"Bus Charters",
            "type":"Transportation"
        }
    ],
    "sg:postcode":"HA1 3LP",
    "sg:province":"Greater London",
    "sg:tags":[
        "coach"
    ],
    "wof:name":"Redbeam Ltd",
    "wof:placetype":"venue"
},
  "geometry": {"coordinates":[-0.339868,51.570225],"type":"Point"}
}