{
  "type": "Feature",
  "properties": {
    "addr:full":"Main Street, Airth Falkirk Falkirk FK2 8JJ",
    "addr:postcode":"fk2 8jj",
    "addr:street":"Main Street",
    "iso:country":"GB",
    "sg:address":"Main Street, Airth",
    "sg:city":"Falkirk",
    "sg:classifiers":[
        {
            "category":"Travel",
            "subcategory":"Hotels & Motels",
            "type":"Entertainment"
        }
    ],
    "sg:phone":"+44 1324 831670",
    "sg:postcode":"FK2 8JJ",
    "sg:province":"Falkirk",
    "wof:name":"Crown Hotel",
    "wof:placetype":"venue"
},
  "geometry": {"coordinates":[-3.769328,56.068302],"type":"Point"}
}