{
  "type": "Feature",
  "properties": {
    "iso:country":"GB",
    "sg:address":"5b Oxenturn Road",
    "sg:city":"Ashford",
    "sg:classifiers":[
        {
            "category":"Health Services",
            "subcategory":"Health Practitioner",
            "type":"Services"
        }
    ],
    "sg:phone":"+44 1233 812196",
    "sg:postcode":"TN25 5BH",
    "sg:province":"Kent",
    "sg:tags":[
        "osteopath"
    ],
    "wof:name":"D Bakowska",
    "wof:placetype":"venue"
},
  "geometry": {"coordinates":[0.938274,51.181778],"type":"Point"}
}