{
  "type": "Feature",
  "properties": {
    "addr:full":"Care Of Y M C A, St Rumbold Street Lincoln Lincolnshire LN2 5AR",
    "addr:postcode":"ln2 5ar",
    "addr:street":"A St Rumbold Street",
    "iso:country":"GB",
    "sg:address":"Care Of Y M C A, St Rumbold Street",
    "sg:city":"Lincoln",
    "sg:classifiers":[
        {
            "category":"Community Center",
            "subcategory":"Youth",
            "type":"Public Place"
        }
    ],
    "sg:phone":"+44 1522 520984",
    "sg:postcode":"LN2 5AR",
    "sg:province":"Lincolnshire",
    "sg:tags":[
        "organisation",
        "centre"
    ],
    "wof:name":"Methodist Church District Youth Office",
    "wof:placetype":"venue"
},
  "geometry": {"coordinates":[-0.5337200165,53.2288818359],"type":"Point"}
}