{
  "type": "Feature",
  "properties": {
    "addr:full":"Tarleton Av Woodhall Spa Lincolnshire LN10 6SE",
    "addr:postcode":"ln10 6se",
    "addr:street":"Tarleton Av Woodhall Spa",
    "iso:country":"GB",
    "sg:address":"Tarleton Av",
    "sg:city":"Woodhall Spa",
    "sg:classifiers":[
        {
            "category":"Place Of Worship",
            "type":"Public Place"
        }
    ],
    "sg:phone":"+44 1526 352247",
    "sg:postcode":"LN10 6SE",
    "sg:province":"Lincolnshire",
    "wof:name":"Unitarian Churches Of Lincolnshire",
    "wof:placetype":"venue"
},
  "geometry": {"coordinates":[-0.2051640004,53.1530303955],"type":"Point"}
}