{
  "type": "Feature",
  "properties": {
    "addr:full":"65 Eastleigh Road Taunton Somerset TA1 2YD",
    "addr:housenumber":"65",
    "addr:postcode":"ta1 2yd",
    "addr:street":"Eastleigh Road",
    "iso:country":"GB",
    "sg:address":"65 Eastleigh Road",
    "sg:city":"Taunton",
    "sg:classifiers":[
        {
            "category":"Professional",
            "subcategory":"Engineering",
            "type":"Services"
        },
        {
            "category":"Building & Trades",
            "subcategory":"Construction",
            "type":"Services"
        }
    ],
    "sg:phone":"+44 1823 277379",
    "sg:postcode":"TA1 2YD",
    "sg:province":"Somerset",
    "sg:tags":[
        "installers",
        "gas",
        "engineer"
    ],
    "wof:name":"Keeble & Lamble",
    "wof:placetype":"venue"
},
  "geometry": {"coordinates":[-3.088625,51.012527],"type":"Point"}
}