{
  "type": "Feature",
  "properties": {
    "addr:full":"4 Town Walk Folkestone Kent CT20 2AD",
    "addr:housenumber":"4",
    "addr:postcode":"ct20 2ad",
    "addr:street":"Town Walk",
    "iso:country":"GB",
    "sg:address":"4 Town Walk",
    "sg:city":"Folkestone",
    "sg:classifiers":[
        {
            "category":"Organizations",
            "subcategory":"Non-profit Organization",
            "type":"Services"
        },
        {
            "category":"Professional",
            "subcategory":"Computer Services",
            "type":"Services"
        },
        {
            "category":"Government",
            "subcategory":"Office",
            "type":"Public Place"
        }
    ],
    "sg:phone":"+44 1303 246000",
    "sg:postcode":"CT20 2AD",
    "sg:province":"Kent",
    "sg:tags":[
        "information",
        "organisation",
        "agency",
        "authority",
        "charitable",
        "education",
        "charity"
    ],
    "sg:website":"http://www.b48s.org.uk",
    "wof:name":"B-4-8's Folkestone Early Years Resource Project",
    "wof:placetype":"venue"
},
  "geometry": {"coordinates":[1.1779450178,51.0844306946],"type":"Point"}
}