{
  "type": "Feature",
  "properties": {
    "addr:full":"Moor Lane Trading Estate, Sherburn-in-elmet Leeds North Yorkshire LS25 6ES",
    "addr:postcode":"ls25 6es",
    "addr:street":"Moor Lane Trading Estate",
    "iso:country":"GB",
    "sg:address":"Moor Lane Trading Estate, Sherburn-in-elmet",
    "sg:city":"Leeds",
    "sg:phone":"+44 1977 681444",
    "sg:postcode":"LS25 6ES",
    "sg:province":"North Yorkshire",
    "wof:name":"Linpac Polymers",
    "wof:placetype":"venue"
},
  "geometry": {"coordinates":[-1.2410769463,53.7976036072],"type":"Point"}
}