{
  "type": "Feature",
  "properties": {
    "iso:country":"GB",
    "sg:address":"19a Nichol Street",
    "sg:city":"Swansea",
    "sg:classifiers":[
        {
            "category":"Retail",
            "subcategory":"Repair Shop",
            "type":"Services"
        }
    ],
    "sg:phone":"+44 1792 473868",
    "sg:postcode":"SA1 4HF",
    "sg:province":"Neath Port Talbot",
    "sg:tags":[
        "upholsterer"
    ],
    "wof:name":"Llewellyn Upholstery",
    "wof:placetype":"venue"
},
  "geometry": {"coordinates":[-3.9525148869,51.619720459],"type":"Point"}
}