{
  "type": "Feature",
  "properties": {
    "addr:full":"2nd Floor, Federation House, Station Road Stoke-on-trent Staffordshire ST4 2TJ",
    "addr:housenumber":"2nd floor federation house",
    "addr:postcode":"st4 2tj",
    "addr:street":"Station Road",
    "iso:country":"GB",
    "sg:address":"2nd Floor, Federation House, Station Road",
    "sg:city":"Stoke-on-trent",
    "sg:classifiers":[
        {
            "category":"Professional",
            "subcategory":"Business Services",
            "type":"Services"
        }
    ],
    "sg:phone":"+44 1782 417777",
    "sg:postcode":"ST4 2TJ",
    "sg:province":"Staffordshire",
    "sg:tags":[
        "trade"
    ],
    "wof:name":"Retread Manufacturers Association",
    "wof:placetype":"venue"
},
  "geometry": {"coordinates":[-2.182892,53.009663],"type":"Point"}
}