{
  "type": "Feature",
  "properties": {
    "addr:full":"Miswell House, Miswell Tring Buckinghamshire HP23 4JT",
    "addr:postcode":"hp23 4jt",
    "addr:street":"Miswell",
    "iso:country":"GB",
    "sg:address":"Miswell House, Miswell",
    "sg:city":"Tring",
    "sg:classifiers":[
        {
            "category":"Professional",
            "subcategory":"Business Services",
            "type":"Services"
        }
    ],
    "sg:phone":"+44 1442 891999",
    "sg:postcode":"HP23 4JT",
    "sg:province":"Buckinghamshire",
    "sg:tags":[
        "planning",
        "design"
    ],
    "wof:name":"Leopard Interior Design Ltd.",
    "wof:placetype":"venue"
},
  "geometry": {"coordinates":[-0.66398,51.79327],"type":"Point"}
}