{
  "type": "Feature",
  "properties": {
    "addr:full":"Mortimer Street London Greater London W1W 7JS",
    "addr:postcode":"w1w 7js",
    "addr:street":"Mortimer Street",
    "iso:country":"GB",
    "sg:address":"Mortimer Street",
    "sg:city":"London",
    "sg:classifiers":[
        {
            "category":"Professional",
            "subcategory":"Employment Agencies",
            "type":"Services"
        }
    ],
    "sg:phone":"+44 20 7580 5151",
    "sg:postcode":"W1W 7JS",
    "sg:province":"Greater London",
    "sg:tags":[
        "consultant"
    ],
    "wof:name":"Network Design International Ltd.",
    "wof:placetype":"venue"
},
  "geometry": {"coordinates":[-0.137379,51.518715],"type":"Point"}
}