{
  "type": "Feature",
  "properties": {
    "addr:full":"Unit F2 Faversham Kent ME13 7SQ",
    "addr:housenumber":"f2",
    "addr:postcode":"me13 7sq",
    "addr:street":"Faversham",
    "iso:country":"GB",
    "sg:address":"Unit F2",
    "sg:city":"Faversham",
    "sg:classifiers":[
        {
            "category":"Professional",
            "subcategory":"Printing & Photocopies",
            "type":"Services"
        }
    ],
    "sg:phone":"+44 1795 531600",
    "sg:postcode":"ME13 7SQ",
    "sg:province":"Kent",
    "sg:tags":[
        "printer"
    ],
    "wof:name":"Design Design Ltd.",
    "wof:placetype":"venue"
},
  "geometry": {"coordinates":[0.8944299817,51.3213996887],"type":"Point"}
}