{
  "type": "Feature",
  "properties": {
    "addr:full":"1 Mansion House Street Newbury Berkshire RG14 5EL",
    "addr:housenumber":"1",
    "addr:postcode":"rg14 5el",
    "addr:street":"Mansion House Street",
    "iso:country":"GB",
    "sg:address":"1 Mansion House Street",
    "sg:city":"Newbury",
    "sg:classifiers":[
        {
            "category":"Banks & Credit Unions",
            "subcategory":"Bank",
            "type":"Services"
        }
    ],
    "sg:phone":"+44 845 740 4404",
    "sg:postcode":"RG14 5EL",
    "sg:province":"Berkshire",
    "wof:name":"H S B C Bank",
    "wof:placetype":"venue"
},
  "geometry": {"coordinates":[-1.3237290382,51.401260376],"type":"Point"}
}