{
  "type": "Feature",
  "properties": {
    "iso:country":"GB",
    "sg:address":"19-21 Scarisbrick Avenue",
    "sg:city":"Southport",
    "sg:classifiers":[
        {
            "category":"Cafe",
            "type":"Food & Drink"
        }
    ],
    "sg:phone":"+44 1704 542703",
    "sg:postcode":"PR8 5AB",
    "sg:province":"Lancashire",
    "sg:tags":[
        "tea",
        "room"
    ],
    "wof:name":"Viking Cafe",
    "wof:placetype":"venue"
},
  "geometry": {"coordinates":[-3.000061,53.647175],"type":"Point"}
}