{
  "type": "Feature",
  "properties": {
    "addr:full":"51 Coronation Road, Crosby Liverpool Merseyside L23 5RE",
    "addr:housenumber":"51",
    "addr:postcode":"l23 5re",
    "addr:street":"Coronation Road",
    "iso:country":"GB",
    "sg:address":"51 Coronation Road, Crosby",
    "sg:city":"Liverpool",
    "sg:classifiers":[
        {
            "category":"Food & Beverages",
            "subcategory":"Candy",
            "type":"Retail Goods"
        }
    ],
    "sg:phone":"+44 151 286 9691",
    "sg:postcode":"L23 5RE",
    "sg:province":"Merseyside",
    "sg:tags":[
        "confectioner"
    ],
    "wof:name":"Satterthwaites Confectioners",
    "wof:placetype":"venue"
},
  "geometry": {"coordinates":[-3.0290811062,53.4898223877],"type":"Point"}
}