{
  "type": "Feature",
  "properties": {
    "iso:country":"GB",
    "sg:address":"Rainbow House, 56 Windsor Avenue, Wimbledon",
    "sg:city":"London",
    "sg:classifiers":[
        {
            "category":"Professional",
            "subcategory":"Management & Consulting",
            "type":"Services"
        }
    ],
    "sg:phone":"+44 20 8545 0700",
    "sg:postcode":"SW19 2RR",
    "sg:province":"Greater London",
    "sg:tags":[
        "consultant",
        "promotion",
        "sale"
    ],
    "wof:name":"Rainbow Productions Ltd.",
    "wof:placetype":"venue"
},
  "geometry": {"coordinates":[-0.185989,51.411163],"type":"Point"}
}