{
  "type": "Feature",
  "properties": {
    "addr:full":"1 Crammond Park, Lovet Road Harlow Essex CM19 5TF",
    "addr:housenumber":"1",
    "addr:postcode":"cm19 5tf",
    "addr:street":"Crammond Park Lovet Road",
    "iso:country":"GB",
    "sg:address":"1 Crammond Park, Lovet Road",
    "sg:city":"Harlow",
    "sg:classifiers":[
        {
            "category":"Professional",
            "subcategory":"Engineering",
            "type":"Services"
        }
    ],
    "sg:phone":"+44 1279 425358",
    "sg:postcode":"CM19 5TF",
    "sg:province":"Essex",
    "sg:tags":[
        "precision",
        "engineer"
    ],
    "wof:name":"Beard & Fitch Ltd",
    "wof:placetype":"venue"
},
  "geometry": {"coordinates":[0.0735210031,51.763507843],"type":"Point"}
}