{
  "type": "Feature",
  "properties": {
    "addr:full":"3 Mill Street Cannock Staffordshire WS11 3DL",
    "addr:housenumber":"3",
    "addr:postcode":"ws11 3dl",
    "addr:street":"Mill Street",
    "iso:country":"GB",
    "sg:address":"3 Mill Street",
    "sg:city":"Cannock",
    "sg:classifiers":[
        {
            "category":"Home & Garden",
            "subcategory":"Hardware",
            "type":"Retail Goods"
        }
    ],
    "sg:phone":"+44 1543 506100",
    "sg:postcode":"WS11 3DL",
    "sg:province":"Staffordshire",
    "sg:tags":[
        "retailer",
        "lighting"
    ],
    "wof:name":"R Beardsmore (Electrical) Ltd.",
    "wof:placetype":"venue"
},
  "geometry": {"coordinates":[-2.027223,52.688519],"type":"Point"}
}