{
  "type": "Feature",
  "properties": {
    "addr:full":"1 Halton Street, Netherton Dudley West Midlands DY2 0PJ",
    "addr:housenumber":"1",
    "addr:postcode":"dy2 0pj",
    "addr:street":"Halton Street",
    "iso:country":"GB",
    "sg:address":"1 Halton Street, Netherton",
    "sg:city":"Dudley",
    "sg:classifiers":[
        {
            "category":"Organizations",
            "subcategory":"Membership Organization",
            "type":"Services"
        }
    ],
    "sg:phone":"+44 1384 255876",
    "sg:postcode":"DY2 0PJ",
    "sg:province":"West Midlands",
    "sg:tags":[
        "club",
        "social"
    ],
    "wof:name":"Netherton Conservative & Unionist Club Ltd.",
    "wof:placetype":"venue"
},
  "geometry": {"coordinates":[-2.087149,52.493351],"type":"Point"}
}