{
  "type": "Feature",
  "properties": {
    "addr:full":"184 Stockport Road Ashton-under-lyne Greater Manchester OL7 0NW",
    "addr:housenumber":"184",
    "addr:postcode":"ol7 0nw",
    "addr:street":"Stockport Road",
    "iso:country":"GB",
    "sg:address":"184 Stockport Road",
    "sg:city":"Ashton-under-lyne",
    "sg:classifiers":[
        {
            "category":"Personal",
            "subcategory":"Beauty Salon",
            "type":"Services"
        },
        {
            "category":"Personal",
            "subcategory":"Barber",
            "type":"Services"
        }
    ],
    "sg:phone":"+44 161 330 8631",
    "sg:postcode":"OL7 0NW",
    "sg:province":"Greater Manchester",
    "sg:tags":[
        "unisex",
        "hairdresser"
    ],
    "wof:name":"Hair Station",
    "wof:placetype":"venue"
},
  "geometry": {"coordinates":[-2.111533,53.477592],"type":"Point"}
}