{
  "type": "Feature",
  "properties": {
    "addr:full":"77a Westow Hill London Greater London SE19 1TZ",
    "addr:housenumber":"77a",
    "addr:postcode":"se19 1tz",
    "addr:street":"Westow Hill",
    "iso:country":"GB",
    "sg:address":"77a Westow Hill",
    "sg:city":"London",
    "sg:classifiers":[
        {
            "category":"Communications",
            "subcategory":"Television Station",
            "type":"Services"
        }
    ],
    "sg:postcode":"SE19 1TZ",
    "sg:province":"Greater London",
    "sg:tags":[
        "audio-visual"
    ],
    "wof:name":"Timelord International Ltd",
    "wof:placetype":"venue"
},
  "geometry": {"coordinates":[-0.0816539973,51.4169273376],"type":"Point"}
}