{
  "type": "Feature",
  "properties": {
    "addr:full":"56 Chapel Street Southport Lancashire PR8 1BZ",
    "addr:housenumber":"56",
    "addr:postcode":"pr8 1bz",
    "addr:street":"Chapel Street",
    "iso:country":"GB",
    "sg:address":"56 Chapel Street",
    "sg:city":"Southport",
    "sg:classifiers":[
        {
            "category":"Shopping",
            "subcategory":"Shoes",
            "type":"Retail Goods"
        }
    ],
    "sg:phone":"+44 1704 530656",
    "sg:postcode":"PR8 1BZ",
    "sg:province":"Lancashire",
    "wof:name":"Timpson Shoe Repairs",
    "wof:placetype":"venue"
},
  "geometry": {"coordinates":[-3.003441,53.647293],"type":"Point"}
}