{
  "type": "Feature",
  "properties": {
    "iso:country":"GB",
    "sg:address":"3-4 New Rd",
    "sg:city":"Chippenham",
    "sg:classifiers":[
        {
            "category":"Social Services",
            "type":"Services"
        }
    ],
    "sg:phone":"+44 1249 460701",
    "sg:postcode":"SN15 1EJ",
    "sg:province":"Wiltshire",
    "sg:tags":[
        "helplines"
    ],
    "wof:name":"Staying Put North Wiltshire",
    "wof:placetype":"venue"
},
  "geometry": {"coordinates":[-2.117853,51.460354],"type":"Point"}
}