{
  "type": "Feature",
  "properties": {
    "addr:full":"294-298 Monkmoor Road Shrewsbury Shropshire SY2 5TX",
    "addr:postcode":"294-298;sy2 5tx",
    "addr:street":"Monkmoor Road",
    "iso:country":"GB",
    "sg:address":"294-298 Monkmoor Road",
    "sg:city":"Shrewsbury",
    "sg:classifiers":[
        {
            "category":"Autos & Motor Vehicles",
            "subcategory":"Automobile Sales",
            "type":"Retail Goods"
        }
    ],
    "sg:postcode":"SY2 5TX",
    "sg:province":"Shropshire",
    "sg:tags":[
        "car"
    ],
    "wof:name":"Jones Car Sales",
    "wof:placetype":"venue"
},
  "geometry": {"coordinates":[-2.7309989929,52.7149009705],"type":"Point"}
}