{
  "type": "Feature",
  "properties": {
    "iso:country":"GB",
    "sg:address":"23 & 30 Pinfold Workshops, Pinfold Lane Industrial Estate",
    "sg:city":"Buckley",
    "sg:classifiers":[
        {
            "category":"Military Area",
            "subcategory":"Air Force Base",
            "type":"Public Place"
        }
    ],
    "sg:phone":"+44 1244 545400",
    "sg:postcode":"CH7 3PL",
    "sg:province":"Denbighshire",
    "sg:tags":[
        "taxi",
        "hire",
        "private"
    ],
    "wof:name":"Ewloe Cars Ltd.",
    "wof:placetype":"venue"
},
  "geometry": {"coordinates":[-3.08404,53.17955],"type":"Point"}
}