{
  "type": "Feature",
  "properties": {
    "iso:country":"GB",
    "sg:address":"Rymlet, Church Lane, Toddington",
    "sg:city":"Cheltenham",
    "sg:classifiers":[
        {
            "category":"Professional",
            "subcategory":"Art Services",
            "type":"Services"
        },
        {
            "category":"Building & Trades",
            "subcategory":"Construction",
            "type":"Services"
        }
    ],
    "sg:phone":"+44 1242 621445",
    "sg:postcode":"GL54 5DQ",
    "sg:province":"Gloucestershire",
    "sg:tags":[
        "glazier",
        "decorator",
        "painter"
    ],
    "wof:name":"HARRY WILLIAM CLARKE",
    "wof:placetype":"venue"
},
  "geometry": {"coordinates":[-1.9494190216,51.9934806824],"type":"Point"}
}