{
  "type": "Feature",
  "properties": {
    "iso:country":"GB",
    "sg:address":"Brookheys Farm Cattery, Sinderland Lane, Dunham Massey",
    "sg:city":"Altrincham",
    "sg:classifiers":[
        {
            "category":"Transit Center",
            "subcategory":"Passenger",
            "type":"Transportation"
        }
    ],
    "sg:postcode":"WA14 5SY",
    "sg:province":"Cheshire",
    "sg:tags":[
        "boarding",
        "kennel",
        "catteries"
    ],
    "wof:name":"Brookheys Farm Cattery",
    "wof:placetype":"venue"
},
  "geometry": {"coordinates":[-2.3865699768,53.4091377258],"type":"Point"}
}