{
  "type": "Feature",
  "properties": {
    "addr:full":"Unit 8, Hurlingham Business Park London Greater London SW6 3DU",
    "addr:housenumber":"unit 8",
    "addr:postcode":"sw6 3du",
    "addr:street":"Hurlingham Business Park",
    "iso:country":"GB",
    "sg:address":"Unit 8, Hurlingham Business Park",
    "sg:city":"London",
    "sg:classifiers":[
        {
            "category":"Professional",
            "subcategory":"Business Services",
            "type":"Services"
        }
    ],
    "sg:phone":"+44 20 7731 8562",
    "sg:postcode":"SW6 3DU",
    "sg:province":"Greater London",
    "sg:tags":[
        "import",
        "export",
        "agent"
    ],
    "wof:name":"W H Everett & Son Ltd.",
    "wof:placetype":"venue"
},
  "geometry": {"coordinates":[-0.196499005,51.4663009644],"type":"Point"}
}