{
  "type": "Feature",
  "properties": {
    "addr:full":"10 Hungerford Newtown Hungerford Berkshire RG17 0PP",
    "addr:housenumber":"10",
    "addr:postcode":"rg17 0pp",
    "addr:street":"Hungerford",
    "iso:country":"GB",
    "sg:address":"10 Hungerford Newtown",
    "sg:city":"Hungerford",
    "sg:classifiers":[
        {
            "category":"Professional",
            "subcategory":"Art Services",
            "type":"Services"
        },
        {
            "category":"Military Area",
            "subcategory":"Air Force Base",
            "type":"Public Place"
        }
    ],
    "sg:phone":"+44 1488 684347",
    "sg:postcode":"RG17 0PP",
    "sg:province":"Berkshire",
    "sg:tags":[
        "picture",
        "frame",
        "restoration",
        "cleaning"
    ],
    "wof:name":"Tracy Tabernacle",
    "wof:placetype":"venue"
},
  "geometry": {"coordinates":[-1.516659,51.41502],"type":"Point"}
}