{
  "type": "Feature",
  "properties": {
    "addr:full":"Blackburn House, Redhouse Road, Seafield Bathgate North Lanarkshire EH47 7AQ",
    "addr:postcode":"eh47 7aq",
    "addr:street":"Redhouse Road;Bathgate",
    "iso:country":"GB",
    "sg:address":"Blackburn House, Redhouse Road, Seafield",
    "sg:city":"Bathgate",
    "sg:classifiers":[
        {
            "category":"Sports & Exercise",
            "subcategory":"Stables",
            "type":"Entertainment"
        }
    ],
    "sg:phone":"+44 1506 855555",
    "sg:postcode":"EH47 7AQ",
    "sg:province":"North Lanarkshire",
    "sg:tags":[
        "education",
        "equestrian"
    ],
    "wof:name":"Holmes Riding Stables",
    "wof:placetype":"venue"
},
  "geometry": {"coordinates":[-3.5926089287,55.8772735596],"type":"Point"}
}