{
  "type": "Feature",
  "properties": {
    "addr:full":"3 Mercatoria St Leonards-on-sea East Sussex TN38 0EB",
    "addr:housenumber":"3",
    "addr:postcode":"tn38 0eb",
    "addr:street":"Mercatoria St",
    "iso:country":"GB",
    "sg:address":"3 Mercatoria",
    "sg:city":"St Leonards-on-sea",
    "sg:classifiers":[
        {
            "category":"Retail",
            "subcategory":"Auto Repair",
            "type":"Services"
        }
    ],
    "sg:postcode":"TN38 0EB",
    "sg:province":"East Sussex",
    "sg:tags":[
        "modification",
        "garage"
    ],
    "wof:name":"Ainsworth Engineering",
    "wof:placetype":"venue"
},
  "geometry": {"coordinates":[0.557123,50.851665],"type":"Point"}
}