{
  "type": "Feature",
  "properties": {
    "iso:country":"GB",
    "sg:address":"Westwell Ho, Main St, Northiam",
    "sg:city":"Rye",
    "sg:classifiers":[
        {
            "category":"Professional",
            "subcategory":"Management & Consulting",
            "type":"Services"
        }
    ],
    "sg:postcode":"TN31 6NB",
    "sg:province":"East Sussex",
    "sg:tags":[
        "consultant",
        "business"
    ],
    "wof:name":"Doucy,J R,",
    "wof:placetype":"venue"
},
  "geometry": {"coordinates":[0.602147,50.997974],"type":"Point"}
}