{
  "type": "Feature",
  "properties": {
    "addr:full":"170 Cherry Hinton Rd Cambridge Cambridgeshire CB1 7AN",
    "addr:housenumber":"170",
    "addr:postcode":"cb1 7an",
    "addr:street":"Cherry Hinton Rd",
    "iso:country":"GB",
    "sg:address":"170 Cherry Hinton Rd",
    "sg:city":"Cambridge",
    "sg:classifiers":[
        {
            "category":"Professional",
            "subcategory":"Art Services",
            "type":"Services"
        }
    ],
    "sg:phone":"+44 1223 575091",
    "sg:postcode":"CB1 7AN",
    "sg:province":"Cambridgeshire",
    "sg:tags":[
        "graphic",
        "designer"
    ],
    "wof:name":"Cherry Design",
    "wof:placetype":"venue"
},
  "geometry": {"coordinates":[0.1455270052,52.1877288818],"type":"Point"}
}