{
  "type": "Feature",
  "properties": {
    "iso:country":"GB",
    "sg:address":"Romford Cottage, Oldfield Road, Honley",
    "sg:city":"Huddersfield",
    "sg:classifiers":[
        {
            "category":"Shopping",
            "subcategory":"Crafts & Fabrics",
            "type":"Retail Goods"
        }
    ],
    "sg:phone":"+44 1484 663295",
    "sg:postcode":"HD7 2RN",
    "sg:province":"West Yorkshire",
    "sg:tags":[
        "shop",
        "linen"
    ],
    "wof:name":"LinenStore",
    "wof:placetype":"venue"
},
  "geometry": {"coordinates":[-1.78268,53.64695],"type":"Point"}
}