{
  "type": "Feature",
  "properties": {
    "addr:full":"29 Albion Square London Greater London E8 4ES",
    "addr:housenumber":"29",
    "addr:postcode":"e8 4es",
    "addr:street":"Albion Square",
    "iso:country":"GB",
    "sg:address":"29 Albion Square",
    "sg:city":"London",
    "sg:classifiers":[
        {
            "category":"Organizations",
            "subcategory":"Community Association",
            "type":"Services"
        }
    ],
    "sg:phone":"+44 20 7923 2500",
    "sg:postcode":"E8 4ES",
    "sg:province":"Greater London",
    "sg:tags":[
        "relation",
        "public"
    ],
    "wof:name":"Bright Light Ltd.",
    "wof:placetype":"venue"
},
  "geometry": {"coordinates":[-0.0681499988,51.5395507812],"type":"Point"}
}