{
  "type": "Feature",
  "properties": {
    "iso:country":"GB",
    "sg:address":"53 Hull Road",
    "sg:city":"Withernsea",
    "sg:classifiers":[
        {
            "category":"Food & Beverages",
            "subcategory":"Supermarket",
            "type":"Retail Goods"
        }
    ],
    "sg:postcode":"HU19 2DY",
    "sg:province":"East Riding of Yorkshire",
    "wof:name":"Hull Road Store",
    "wof:placetype":"venue"
},
  "geometry": {"coordinates":[0.0281109996,53.7308959961],"type":"Point"}
}