{
  "type": "Feature",
  "properties": {
    "addr:full":"53 Hull Road Withernsea East Riding of Yorkshire HU19 2DY",
    "addr:housenumber":"53",
    "addr:postcode":"hu19 2dy",
    "addr:street":"Hull Road",
    "iso:country":"GB",
    "sg:address":"53 Hull Road",
    "sg:city":"Withernsea",
    "sg:classifiers":[
        {
            "category":"Food & Beverages",
            "subcategory":"Supermarket",
            "type":"Retail Goods"
        }
    ],
    "sg:postcode":"HU19 2DY",
    "sg:province":"East Riding of Yorkshire",
    "wof:name":"Hull Road Store",
    "wof:placetype":"venue"
},
  "geometry": {"coordinates":[0.0281109996,53.7308959961],"type":"Point"}
}