{
  "type": "Feature",
  "properties": {
    "addr:full":"1a Court Lane Iver Berkshire SL0 9HL",
    "addr:housenumber":"1a",
    "addr:postcode":"sl0 9hl",
    "addr:street":"Court Lane",
    "iso:country":"GB",
    "sg:address":"1a Court Lane",
    "sg:city":"Iver",
    "sg:classifiers":[
        {
            "category":"Freight",
            "type":"Transportation"
        }
    ],
    "sg:phone":"+44 1753 653023",
    "sg:postcode":"SL0 9HL",
    "sg:province":"Berkshire",
    "sg:tags":[
        "haulage",
        "road"
    ],
    "wof:name":"Ayto Transport Ltd.",
    "wof:placetype":"venue"
},
  "geometry": {"coordinates":[-0.5012490153,51.5098648071],"type":"Point"}
}