{
  "type": "Feature",
  "properties": {
    "addr:full":"11 Upland Mews, East Dulwich London Greater London SE22 9EG",
    "addr:housenumber":"11",
    "addr:postcode":"se22 9eg",
    "addr:street":"Upland Mews",
    "iso:country":"GB",
    "sg:address":"11 Upland Mews, East Dulwich",
    "sg:city":"London",
    "sg:classifiers":[
        {
            "category":"Professional",
            "subcategory":"Engineering",
            "type":"Services"
        },
        {
            "category":"Building & Trades",
            "subcategory":"Construction",
            "type":"Services"
        }
    ],
    "sg:phone":"+44 20 8693 9684",
    "sg:postcode":"SE22 9EG",
    "sg:province":"Greater London",
    "sg:tags":[
        "civil",
        "builder",
        "engineer"
    ],
    "wof:name":"P D Construction Ltd.",
    "wof:placetype":"venue"
},
  "geometry": {"coordinates":[-0.069865,51.45747],"type":"Point"}
}