{
  "type": "Feature",
  "properties": {
    "addr:full":"1 Blunts Farm Cottages, Coopersale Lane, Theydon Bois Epping Essex CM16 7NT",
    "addr:housenumber":"1",
    "addr:postcode":"cm16 7nt",
    "addr:street":"Blunts Farm Cottages Coopersale Lane Theydon",
    "iso:country":"GB",
    "sg:address":"1 Blunts Farm Cottages, Coopersale Lane, Theydon Bois",
    "sg:city":"Epping",
    "sg:classifiers":[
        {
            "category":"Professional",
            "subcategory":"Management & Consulting",
            "type":"Services"
        }
    ],
    "sg:phone":"+44 1992 814293",
    "sg:postcode":"CM16 7NT",
    "sg:province":"Essex",
    "sg:tags":[
        "consultant",
        "transport"
    ],
    "wof:name":"Saxon Contracts Ltd.",
    "wof:placetype":"venue"
},
  "geometry": {"coordinates":[0.1356640011,51.7049293518],"type":"Point"}
}