{
  "type": "Feature",
  "properties": {
    "iso:country":"GB",
    "sg:address":"P O Box 17",
    "sg:city":"Lewes",
    "sg:classifiers":[
        {
            "category":"Manufacturing",
            "subcategory":"Food",
            "type":"Manufacturing & Wholesale Goods"
        }
    ],
    "sg:phone":"+44 1273 474366",
    "sg:postcode":"BN7 3LS",
    "sg:province":"East Sussex",
    "sg:tags":[
        "processing"
    ],
    "wof:name":"Janke & Kunkel (U K) Ltd.",
    "wof:placetype":"venue"
},
  "geometry": {"coordinates":[-0.028649,50.860802],"type":"Point"}
}