{
  "type": "Feature",
  "properties": {
    "addr:full":"Link House, Bolton Road, Kearsley Bolton Lancashire BL4 9BT",
    "addr:postcode":"bl4 9bt",
    "addr:street":"Bolton Road",
    "iso:country":"GB",
    "sg:address":"Link House, Bolton Road, Kearsley",
    "sg:city":"Bolton",
    "sg:classifiers":[
        {
            "category":"Home & Garden",
            "subcategory":"Home Furnishings",
            "type":"Retail Goods"
        }
    ],
    "sg:postcode":"BL4 9BT",
    "sg:province":"Lancashire",
    "sg:tags":[
        "furnishers",
        "planner",
        "kitchen"
    ],
    "wof:name":"Link Design Interior",
    "wof:placetype":"venue"
},
  "geometry": {"coordinates":[-2.385259,53.543167],"type":"Point"}
}