{
  "type": "Feature",
  "properties": {
    "iso:country":"GB",
    "sg:address":"Easthampstead Rd",
    "sg:city":"Bracknell",
    "sg:classifiers":[
        {
            "category":"Manufacturing",
            "subcategory":"Building Materials",
            "type":"Manufacturing & Wholesale Goods"
        }
    ],
    "sg:phone":"+44 1344 421414",
    "sg:postcode":"RG12 1NU",
    "sg:province":"Berkshire",
    "sg:tags":[
        "merchant",
        "builder"
    ],
    "wof:name":"Hall & Co Ltd",
    "wof:placetype":"venue"
},
  "geometry": {"coordinates":[-0.761799,51.41486],"type":"Point"}
}