{
  "type": "Feature",
  "properties": {
    "addr:full":"3 The Shambles Alnwick Northumberland NE66 1TN",
    "addr:housenumber":"3",
    "addr:postcode":"ne66 1tn",
    "addr:street":"The Shambles",
    "iso:country":"GB",
    "sg:address":"3 The Shambles",
    "sg:city":"Alnwick",
    "sg:classifiers":[
        {
            "category":"Shopping",
            "subcategory":"Crafts & Fabrics",
            "type":"Retail Goods"
        }
    ],
    "sg:phone":"+44 1665 602935",
    "sg:postcode":"NE66 1TN",
    "sg:province":"Northumberland",
    "sg:tags":[
        "shop",
        "needlecraft",
        "wool"
    ],
    "wof:name":"The Wool Shop",
    "wof:placetype":"venue"
},
  "geometry": {"coordinates":[-1.7035139799,55.4126014709],"type":"Point"}
}