{
  "type": "Feature",
  "properties": {
    "addr:full":"187 Baillieston Road Glasgow Glasgow City G32 0TN",
    "addr:housenumber":"187",
    "addr:postcode":"g32 0tn",
    "addr:street":"Baillieston Road",
    "iso:country":"GB",
    "sg:address":"187 Baillieston Road",
    "sg:city":"Glasgow",
    "sg:classifiers":[
        {
            "category":"Banks & Credit Unions",
            "subcategory":"Bank",
            "type":"Services"
        }
    ],
    "sg:phone":"+44 141 532 1800",
    "sg:postcode":"G32 0TN",
    "sg:province":"Glasgow City",
    "sg:tags":[
        "financial",
        "institution"
    ],
    "wof:name":"Bank Of Scotland",
    "wof:placetype":"venue"
},
  "geometry": {"coordinates":[-4.1329650879,55.8501663208],"type":"Point"}
}