{
  "type": "Feature",
  "properties": {
    "iso:country":"GB",
    "sg:address":"78 Old Christchurch Road",
    "sg:city":"Bournemouth",
    "sg:classifiers":[
        {
            "category":"Shopping",
            "subcategory":"Clothing, Apparel, & Fashions",
            "type":"Retail Goods"
        }
    ],
    "sg:postcode":"BH1 1EW",
    "sg:province":"Dorset",
    "sg:tags":[
        "menswear"
    ],
    "wof:name":"Object Menswear",
    "wof:placetype":"venue"
},
  "geometry": {"coordinates":[-1.8759169579,50.7214851379],"type":"Point"}
}