{
  "type": "Feature",
  "properties": {
    "addr:full":"Southend Arterial Road, Gallows Corner Romford Essex RM3 0BZ",
    "addr:postcode":"rm3 0bz",
    "addr:street":"Southend Arterial Road Gallows Corner",
    "iso:country":"GB",
    "sg:address":"Southend Arterial Road, Gallows Corner",
    "sg:city":"Romford",
    "sg:classifiers":[
        {
            "category":"Professional",
            "subcategory":"Engineering",
            "type":"Services"
        }
    ],
    "sg:postcode":"RM3 0BZ",
    "sg:province":"Essex",
    "sg:tags":[
        "precision",
        "engineer"
    ],
    "wof:name":"Barclay Engineering Co",
    "wof:placetype":"venue"
},
  "geometry": {"coordinates":[0.2237749994,51.5871887207],"type":"Point"}
}