{
  "type": "Feature",
  "properties": {
    "addr:full":"118b Oxford Road Reading Berkshire RG1 7NL",
    "addr:housenumber":"118b",
    "addr:postcode":"rg1 7nl",
    "addr:street":"Oxford Road",
    "iso:country":"GB",
    "sg:address":"118b Oxford Road",
    "sg:city":"Reading",
    "sg:classifiers":[
        {
            "category":"Communications",
            "type":"Services"
        }
    ],
    "sg:postcode":"RG1 7NL",
    "sg:province":"Berkshire",
    "sg:tags":[
        "data",
        "network"
    ],
    "wof:name":"Output Data Systems Ltd",
    "wof:placetype":"venue"
},
  "geometry": {"coordinates":[-0.983205,51.455166],"type":"Point"}
}