{
  "type": "Feature",
  "properties": {
    "addr:full":"9a Market Place Basingstoke Hampshire RG21 1LZ",
    "addr:housenumber":"9a",
    "addr:postcode":"rg21 1lz",
    "addr:street":"Market Place",
    "iso:country":"GB",
    "sg:address":"9a Market Place",
    "sg:city":"Basingstoke",
    "sg:classifiers":[
        {
            "category":"Manufacturing",
            "subcategory":"Tools & Machinery",
            "type":"Manufacturing & Wholesale Goods"
        }
    ],
    "sg:postcode":"RG21 1LZ",
    "sg:province":"Hampshire",
    "sg:tags":[
        "society",
        "friendly"
    ],
    "wof:name":"Collins Insurance Services",
    "wof:placetype":"venue"
},
  "geometry": {"coordinates":[-1.08711,51.262428],"type":"Point"}
}