{
  "type": "Feature",
  "properties": {
    "iso:country":"GB",
    "sg:address":"22 Adelaide Clo",
    "sg:city":"Derby",
    "sg:classifiers":[
        {
            "category":"Professional",
            "subcategory":"Secretarial Services",
            "type":"Services"
        }
    ],
    "sg:phone":"+44 1332 512041",
    "sg:postcode":"DE3 5JN",
    "sg:province":"Derbyshire",
    "wof:name":"Adelaide Office Services",
    "wof:placetype":"venue"
},
  "geometry": {"coordinates":[-1.538693,52.917725],"type":"Point"}
}