{
  "type": "Feature",
  "properties": {
    "addr:full":"58 Glenfield Road Luton Bedfordshire LU3 2HZ",
    "addr:housenumber":"58",
    "addr:postcode":"lu3 2hz",
    "addr:street":"Glenfield Road",
    "iso:country":"GB",
    "sg:address":"58 Glenfield Road",
    "sg:city":"Luton",
    "sg:classifiers":[
        {
            "category":"Insurance",
            "subcategory":"Hazard Insurance",
            "type":"Services"
        }
    ],
    "sg:phone":"+44 1582 754245",
    "sg:postcode":"LU3 2HZ",
    "sg:province":"Bedfordshire",
    "sg:tags":[
        "fire",
        "water",
        "damage"
    ],
    "wof:name":"Rainbow International",
    "wof:placetype":"venue"
},
  "geometry": {"coordinates":[-0.426142,51.911221],"type":"Point"}
}