{
  "type": "Feature",
  "properties": {
    "addr:full":"59a High St Great Missenden Buckinghamshire HP16 0AL",
    "addr:housenumber":"59a",
    "addr:postcode":"hp16 0al",
    "addr:street":"High St",
    "iso:country":"GB",
    "sg:address":"59a High St",
    "sg:city":"Great Missenden",
    "sg:classifiers":[
        {
            "category":"Shopping",
            "subcategory":"Gifts & Souvenirs",
            "type":"Retail Goods"
        }
    ],
    "sg:phone":"+44 1494 862524",
    "sg:postcode":"HP16 0AL",
    "sg:province":"Buckinghamshire",
    "sg:tags":[
        "shop"
    ],
    "wof:name":"Cobbles",
    "wof:placetype":"venue"
},
  "geometry": {"coordinates":[-0.7069919705,51.7035675049],"type":"Point"}
}