{
  "type": "Feature",
  "properties": {
    "addr:full":"Queen Elizabeth Military Hospital, Stadium Rd Woolwich Greater London SE18 4QH",
    "addr:postcode":"se18 4qh",
    "addr:street":"Stadium Rd",
    "iso:country":"GB",
    "sg:address":"Queen Elizabeth Military Hospital, Stadium Rd",
    "sg:city":"Woolwich",
    "sg:classifiers":[
        {
            "category":"Farming",
            "subcategory":"Nursery",
            "type":"Manufacturing & Wholesale Goods"
        }
    ],
    "sg:phone":"+44 20 8319 3752",
    "sg:postcode":"SE18 4QH",
    "sg:province":"Greater London",
    "sg:tags":[
        "creche"
    ],
    "wof:name":"Brook Day Nursery The",
    "wof:placetype":"venue"
},
  "geometry": {"coordinates":[0.049486,51.471642],"type":"Point"}
}