{
  "type": "Feature",
  "properties": {
    "addr:full":"33b Shaw Rd Stockport Cheshire SK4 4AG",
    "addr:housenumber":"33b",
    "addr:postcode":"sk4 4ag",
    "addr:street":"Shaw Rd",
    "iso:country":"GB",
    "sg:address":"33b Shaw Rd",
    "sg:city":"Stockport",
    "sg:classifiers":[
        {
            "category":"Real Estate",
            "subcategory":"Architect",
            "type":"Services"
        }
    ],
    "sg:postcode":"SK4 4AG",
    "sg:province":"Cheshire",
    "sg:tags":[
        "architectural"
    ],
    "wof:name":"Chadwick Richard Associates",
    "wof:placetype":"venue"
},
  "geometry": {"coordinates":[-2.1856210232,53.4233856201],"type":"Point"}
}