{
  "type": "Feature",
  "properties": {
    "iso:country":"GB",
    "sg:address":"495-497 Liverpool Road",
    "sg:city":"London",
    "sg:classifiers":[
        {
            "category":"Health Services",
            "subcategory":"Nursing And Care Facility",
            "type":"Services"
        },
        {
            "category":"Social Services",
            "subcategory":"Retirement Home",
            "type":"Services"
        }
    ],
    "sg:phone":"+44 20 7700 6264",
    "sg:postcode":"N7 8NS",
    "sg:province":"Greater London",
    "sg:tags":[
        "residential"
    ],
    "wof:name":"MILTON HOUSE TRUST",
    "wof:placetype":"venue"
},
  "geometry": {"coordinates":[-0.109809,51.548119],"type":"Point"}
}