{
  "type": "Feature",
  "properties": {
    "addr:full":"35 High Street Elgin Moray IV30 1EE",
    "addr:housenumber":"35",
    "addr:postcode":"iv30 1ee",
    "addr:street":"High Street",
    "iso:country":"GB",
    "sg:address":"35 High Street",
    "sg:city":"Elgin",
    "sg:classifiers":[
        {
            "category":"Shopping",
            "subcategory":"Antiques",
            "type":"Retail Goods"
        },
        {
            "category":"Shopping",
            "subcategory":"Used Merchandise",
            "type":"Retail Goods"
        }
    ],
    "sg:phone":"+44 1343 547531",
    "sg:postcode":"IV30 1EE",
    "sg:province":"Moray",
    "sg:tags":[
        "shop",
        "second-hand"
    ],
    "wof:name":"West End Antiques",
    "wof:placetype":"venue"
},
  "geometry": {"coordinates":[-3.311717,57.649055],"type":"Point"}
}