{
  "type": "Feature",
  "properties": {
    "iso:country":"GB",
    "sg:address":"Tidings Hill Brewery",
    "sg:city":"Halstead",
    "sg:classifiers":[
        {
            "category":"Food & Beverages",
            "subcategory":"Liquor & Beverages",
            "type":"Retail Goods"
        }
    ],
    "sg:phone":"+44 1787 475501",
    "sg:postcode":"CO9 1BL",
    "sg:province":"Essex",
    "sg:tags":[
        "beer",
        "spirit",
        "wines"
    ],
    "wof:name":"G E Cook & Sons Sales Ltd.",
    "wof:placetype":"venue"
},
  "geometry": {"coordinates":[0.6385,51.939423],"type":"Point"}
}