{
  "type": "Feature",
  "properties": {
    "iso:country":"GB",
    "sg:address":"Brookside Works, Middleton St George",
    "sg:city":"Darlington",
    "sg:classifiers":[
        {
            "category":"Manufacturing",
            "subcategory":"Building Materials",
            "type":"Manufacturing & Wholesale Goods"
        }
    ],
    "sg:phone":"+44 1325 332521",
    "sg:postcode":"DL2 1JX",
    "sg:province":"Durham",
    "sg:tags":[
        "tube",
        "manipulator",
        "bender"
    ],
    "wof:name":"Durham Tube",
    "wof:placetype":"venue"
},
  "geometry": {"coordinates":[-1.4727300406,54.5202713013],"type":"Point"}
}