{
  "type": "Feature",
  "properties": {
    "addr:full":"Grange Farm, Wisbech Road Wisbech Cambridgeshire PE14 9RB",
    "addr:postcode":"pe14 9rb",
    "addr:street":"Wisbech Road",
    "iso:country":"GB",
    "sg:address":"Grange Farm, Wisbech Road",
    "sg:city":"Wisbech",
    "sg:classifiers":[
        {
            "category":"Farming",
            "subcategory":"Farm",
            "type":"Manufacturing & Wholesale Goods"
        }
    ],
    "sg:postcode":"PE14 9RB",
    "sg:province":"Cambridgeshire",
    "sg:tags":[
        "mixed",
        "crop"
    ],
    "wof:name":"P M Bedford",
    "wof:placetype":"venue"
},
  "geometry": {"coordinates":[0.2494100034,52.521270752],"type":"Point"}
}