{
  "type": "Feature",
  "properties": {
    "iso:country":"GB",
    "sg:address":"4 Peascod Street",
    "sg:city":"Windsor",
    "sg:classifiers":[
        {
            "category":"Personal",
            "subcategory":"Beauty Salon",
            "type":"Services"
        }
    ],
    "sg:phone":"+44 1753 621875",
    "sg:postcode":"SL4 1DT",
    "sg:province":"Berkshire",
    "wof:name":"Yves Rocher Uk",
    "wof:placetype":"venue"
},
  "geometry": {"coordinates":[-0.60773,51.482319],"type":"Point"}
}