{
  "type": "Feature",
  "properties": {
    "addr:full":"12a North Pde Bradford West Yorkshire BD1 3HT",
    "addr:housenumber":"12a",
    "addr:postcode":"bd1 3ht",
    "addr:street":"North Pde",
    "iso:country":"GB",
    "sg:address":"12a North Pde",
    "sg:city":"Bradford",
    "sg:classifiers":[
        {
            "category":"Shopping",
            "subcategory":"Clothing, Apparel, & Fashions",
            "type":"Retail Goods"
        }
    ],
    "sg:phone":"+44 1274 741740",
    "sg:postcode":"BD1 3HT",
    "sg:province":"West Yorkshire",
    "sg:tags":[
        "dresswear"
    ],
    "wof:name":"Catwalk Dress Agency The",
    "wof:placetype":"venue"
},
  "geometry": {"coordinates":[-1.7559380531,53.7968978882],"type":"Point"}
}