{
  "type": "Feature",
  "properties": {
    "iso:country":"GB",
    "sg:address":"1 Kilmidyke Lodge, Kilmidyke Dr",
    "sg:city":"Grange-over-sands",
    "sg:classifiers":[
        {
            "category":"Taxi",
            "type":"Transportation"
        }
    ],
    "sg:postcode":"LA11 7AJ",
    "sg:province":"Cumbria",
    "sg:tags":[
        "mini",
        "cab"
    ],
    "wof:name":"Hunter,J M,",
    "wof:placetype":"venue"
},
  "geometry": {"coordinates":[-2.9216399193,54.1841583252],"type":"Point"}
}