{
  "type": "Feature",
  "properties": {
    "addr:full":"10 Charter Way Braintree Essex CM7 8YH",
    "addr:housenumber":"10",
    "addr:postcode":"cm7 8yh",
    "addr:street":"Charter Way",
    "iso:country":"GB",
    "sg:address":"10 Charter Way",
    "sg:city":"Braintree",
    "sg:classifiers":[
        {
            "category":"Retail",
            "subcategory":"Auto Repair",
            "type":"Services"
        }
    ],
    "sg:phone":"+44 1376 551216",
    "sg:postcode":"CM7 8YH",
    "sg:province":"Essex",
    "sg:tags":[
        "modification",
        "garage"
    ],
    "wof:name":"Halfords Service Centre",
    "wof:placetype":"venue"
},
  "geometry": {"coordinates":[0.5682590008,51.871006012],"type":"Point"}
}