{
  "type": "Feature",
  "properties": {
    "iso:country":"GB",
    "sg:address":"68-69 St Johns Street",
    "sg:city":"Bury St Edmunds",
    "sg:classifiers":[
        {
            "category":"Shopping",
            "subcategory":"Bicycles & Sporting Goods",
            "type":"Retail Goods"
        }
    ],
    "sg:phone":"+44 1284 753946",
    "sg:postcode":"IP33 1SJ",
    "sg:province":"Suffolk",
    "sg:tags":[
        "shop",
        "cycle",
        "accessory"
    ],
    "wof:name":"Mick's Cycle Centre",
    "wof:placetype":"venue"
},
  "geometry": {"coordinates":[0.712194,52.247356],"type":"Point"}
}