{
  "type": "Feature",
  "properties": {
    "addr:full":"Strand Approach Road Gillingham Kent ME7 1TT",
    "addr:postcode":"me7 1tt",
    "addr:street":"Strand Approach Road",
    "iso:country":"GB",
    "sg:address":"Strand Approach Road",
    "sg:city":"Gillingham",
    "sg:classifiers":[
        {
            "category":"Utilities",
            "subcategory":"Refuse",
            "type":"Services"
        },
        {
            "category":"Government",
            "subcategory":"Office",
            "type":"Public Place"
        }
    ],
    "sg:phone":"+44 1634 576245",
    "sg:postcode":"ME7 1TT",
    "sg:province":"Kent",
    "sg:tags":[
        "equipment",
        "local",
        "diving"
    ],
    "wof:name":"MEDWAY COUNCIL",
    "wof:placetype":"venue"
},
  "geometry": {"coordinates":[0.5618320107,51.3939323425],"type":"Point"}
}