{
  "type": "Feature",
  "properties": {
    "iso:country":"GB",
    "sg:address":"I C F Offices, Coombe Hill Service Station Coob",
    "sg:city":"Gloucester",
    "sg:classifiers":[
        {
            "category":"Autos & Motor Vehicles",
            "subcategory":"Motorcycle Sales",
            "type":"Retail Goods"
        }
    ],
    "sg:phone":"+44 1242 680223",
    "sg:postcode":"GL19 4BD",
    "sg:province":"Gloucestershire",
    "sg:tags":[
        "chauffeur",
        "driven",
        "car"
    ],
    "wof:name":"Inter County Chauffeur Services",
    "wof:placetype":"venue"
},
  "geometry": {"coordinates":[-2.164399,51.941128],"type":"Point"}
}