{
  "type": "Feature",
  "properties": {
    "iso:country":"GB",
    "sg:address":"The Prince Consort Building, 19 St Thomas Street",
    "sg:city":"Ryde",
    "sg:classifiers":[
        {
            "category":"Sports & Exercise",
            "subcategory":"Gym",
            "type":"Entertainment"
        }
    ],
    "sg:postcode":"PO33 2DL",
    "sg:province":"Isle of Wight",
    "sg:tags":[
        "fitness",
        "health",
        "centre"
    ],
    "wof:name":"Fox's",
    "wof:placetype":"venue"
},
  "geometry": {"coordinates":[-1.168666,50.727566],"type":"Point"}
}