{
  "type": "Feature",
  "properties": {
    "iso:country":"GB",
    "sg:address":"47 Worcester Road",
    "sg:city":"Chipping Norton",
    "sg:classifiers":[
        {
            "category":"Home & Garden",
            "subcategory":"Kitchen Supply",
            "type":"Retail Goods"
        }
    ],
    "sg:phone":"+44 1608 642850",
    "sg:postcode":"OX7 5YF",
    "sg:province":"Gloucestershire",
    "sg:tags":[
        "equipment",
        "catering"
    ],
    "wof:name":"Arnold Smith",
    "wof:placetype":"venue"
},
  "geometry": {"coordinates":[-1.570962,51.940712],"type":"Point"}
}