{
  "type": "Feature",
  "properties": {
    "iso:country":"GB",
    "sg:address":"57 Kennington Park Rd",
    "sg:city":"Lambeth",
    "sg:classifiers":[
        {
            "category":"Place Of Worship",
            "type":"Public Place"
        }
    ],
    "sg:phone":"+44 20 7735 1894",
    "sg:postcode":"SE11 4JQ",
    "sg:province":"Greater London",
    "wof:name":"St Mary C Of E Church",
    "wof:placetype":"venue"
},
  "geometry": {"coordinates":[-0.111449,51.496902],"type":"Point"}
}