{
  "type": "Feature",
  "properties": {
    "addr:full":"Afton Rd, Kildrum, Cumbernauld Glasgow Falkirk G67 2DN",
    "addr:postcode":"g67 2dn",
    "addr:street":"Afton Rd",
    "iso:country":"GB",
    "sg:address":"Afton Rd, Kildrum, Cumbernauld",
    "sg:city":"Glasgow",
    "sg:classifiers":[
        {
            "category":"Community Center",
            "subcategory":"Youth",
            "type":"Public Place"
        }
    ],
    "sg:postcode":"G67 2DN",
    "sg:province":"Falkirk",
    "sg:tags":[
        "organisation",
        "centre"
    ],
    "wof:name":"Cumbernauld Y M C A/Y W C A Charity Shop",
    "wof:placetype":"venue"
},
  "geometry": {"coordinates":[-3.971906,55.954575],"type":"Point"}
}