{
  "type": "Feature",
  "properties": {
    "addr:full":"4th Floor Berwick House Orpington Kent BR6 0EL",
    "addr:housenumber":"4th floor berwick house orpington",
    "addr:postcode":"br6 0el",
    "iso:country":"GB",
    "sg:address":"4th Floor Berwick House",
    "sg:city":"Orpington",
    "sg:classifiers":[
        {
            "category":"Shopping",
            "subcategory":"Mobile Phones",
            "type":"Retail Goods"
        }
    ],
    "sg:phone":"+44 870 444 5540",
    "sg:postcode":"BR6 0EL",
    "sg:province":"Kent",
    "wof:name":"Scott-Wilds Fee Associates",
    "wof:placetype":"venue"
},
  "geometry": {"coordinates":[0.1023700014,51.3776283264],"type":"Point"}
}