{
  "type": "Feature",
  "properties": {
    "addr:full":"184 Chillingham Road Newcastle-upon-tyne Tyne and Wear NE6 5BU",
    "addr:housenumber":"184",
    "addr:postcode":"ne6 5bu",
    "addr:street":"Chillingham Road",
    "iso:country":"GB",
    "sg:address":"184 Chillingham Road",
    "sg:city":"Newcastle-upon-tyne",
    "sg:classifiers":[
        {
            "category":"Professional",
            "subcategory":"Lawyer & Legal Services",
            "type":"Services"
        }
    ],
    "sg:phone":"+44 191 276 9500",
    "sg:postcode":"NE6 5BU",
    "sg:province":"Tyne and Wear",
    "sg:tags":[
        "solicitor"
    ],
    "wof:name":"John McCarthy & Son",
    "wof:placetype":"venue"
},
  "geometry": {"coordinates":[-1.5764770508,54.9857559204],"type":"Point"}
}