{
  "type": "Feature",
  "properties": {
    "addr:full":"6 Lamberts Marsh, Southwick Trowbridge Wiltshire BA14 9PB",
    "addr:housenumber":"6",
    "addr:postcode":"ba14 9pb",
    "addr:street":"Lamberts Marsh",
    "iso:country":"GB",
    "sg:address":"6 Lamberts Marsh, Southwick",
    "sg:city":"Trowbridge",
    "sg:classifiers":[
        {
            "category":"Retail",
            "subcategory":"Funeral Services",
            "type":"Services"
        }
    ],
    "sg:phone":"+44 1225 775259",
    "sg:postcode":"BA14 9PB",
    "sg:province":"Wiltshire",
    "sg:tags":[
        "director"
    ],
    "wof:name":"Elizabeth Snell Funeral Services",
    "wof:placetype":"venue"
},
  "geometry": {"coordinates":[-2.23389,51.296917],"type":"Point"}
}