{
  "type": "Feature",
  "properties": {
    "addr:full":"148 Front St, Arnold Nottingham Nottinghamshire NG5 7EG",
    "addr:housenumber":"148",
    "addr:postcode":"ng5 7eg",
    "addr:street":"Front St",
    "iso:country":"GB",
    "sg:address":"148 Front St, Arnold",
    "sg:city":"Nottingham",
    "sg:classifiers":[
        {
            "category":"Fast Food",
            "type":"Food & Drink"
        }
    ],
    "sg:postcode":"NG5 7EG",
    "sg:province":"Nottinghamshire",
    "sg:tags":[
        "away",
        "take"
    ],
    "wof:name":"Sunflower",
    "wof:placetype":"venue"
},
  "geometry": {"coordinates":[-1.1267969608,53.0055503845],"type":"Point"}
}