{
  "type": "Feature",
  "properties": {
    "iso:country":"GB",
    "sg:address":"Church End, Eversholt",
    "sg:city":"Milton Keynes",
    "sg:classifiers":[
        {
            "category":"Bars & Pubs",
            "type":"Food & Drink"
        }
    ],
    "sg:phone":"+44 1525 280293",
    "sg:postcode":"MK17 9DU",
    "sg:province":"Bedfordshire",
    "sg:tags":[
        "pubs",
        "inn"
    ],
    "wof:name":"The Green Man",
    "wof:placetype":"venue"
},
  "geometry": {"coordinates":[-0.569458,51.981834],"type":"Point"}
}