{
  "type": "Feature",
  "properties": {
    "addr:full":"1a Chipchese Court Seaham Durham SR7 0PP",
    "addr:housenumber":"1a",
    "addr:postcode":"sr7 0pp",
    "addr:street":"Chipchese Court",
    "iso:country":"GB",
    "sg:address":"1a Chipchese Court",
    "sg:city":"Seaham",
    "sg:classifiers":[
        {
            "category":"Shopping",
            "subcategory":"Pets & Pet Supplies",
            "type":"Retail Goods"
        }
    ],
    "sg:phone":"+44 191 521 4600",
    "sg:postcode":"SR7 0PP",
    "sg:province":"Durham",
    "wof:name":"Mainline Pet Supplies",
    "wof:placetype":"venue"
},
  "geometry": {"coordinates":[-1.3681010008,54.8518714905],"type":"Point"}
}