{
  "type": "Feature",
  "properties": {
    "addr:full":"Constables Boat House, 15 Thames Street Hampton Greater London TW12 2EW",
    "addr:housenumber":"15",
    "addr:postcode":"tw12 2ew",
    "addr:street":"Boat House;Thames Street",
    "iso:country":"GB",
    "sg:address":"Constables Boat House, 15 Thames Street",
    "sg:city":"Hampton",
    "sg:classifiers":[
        {
            "category":"Professional",
            "subcategory":"Art Services",
            "type":"Services"
        }
    ],
    "sg:phone":"+44 20 8979 8880",
    "sg:postcode":"TW12 2EW",
    "sg:province":"Greater London",
    "sg:tags":[
        "consultant",
        "design"
    ],
    "wof:name":"Qudos Design Ltd.",
    "wof:placetype":"venue"
},
  "geometry": {"coordinates":[-0.3636539876,51.4133338928],"type":"Point"}
}