{
  "type": "Feature",
  "properties": {
    "iso:country":"GB",
    "sg:address":"12a Moor St",
    "sg:city":"Luton",
    "sg:classifiers":[
        {
            "category":"Professional",
            "subcategory":"Engineering",
            "type":"Services"
        }
    ],
    "sg:phone":"+44 1582 412416",
    "sg:postcode":"LU1 1HA",
    "sg:province":"Bedfordshire",
    "sg:tags":[
        "engineer",
        "mechanical"
    ],
    "wof:name":"Ebor Ltd",
    "wof:placetype":"venue"
},
  "geometry": {"coordinates":[-0.425255,51.884098],"type":"Point"}
}