{
  "type": "Feature",
  "properties": {
    "addr:full":"Unit 1 Memorial Rd Bristol City of Bristol BS15 3JY",
    "addr:housenumber":"unit 1",
    "addr:postcode":"bs15 3jy",
    "addr:street":"Memorial Rd",
    "iso:country":"GB",
    "sg:address":"Unit 1 Memorial Rd",
    "sg:city":"Bristol",
    "sg:classifiers":[
        {
            "category":"Manufacturing",
            "subcategory":"Chemicals & Compounds",
            "type":"Manufacturing & Wholesale Goods"
        }
    ],
    "sg:phone":"+44 117 961 8803",
    "sg:postcode":"BS15 3JY",
    "sg:province":"City of Bristol",
    "sg:tags":[
        "pesticide"
    ],
    "wof:name":"Kingham Chemicals",
    "wof:placetype":"venue"
},
  "geometry": {"coordinates":[-2.516009,51.44751],"type":"Point"}
}