{
  "type": "Feature",
  "properties": {
    "addr:full":"19 Churchward Road Paignton Devon TQ3 3BA",
    "addr:housenumber":"19",
    "addr:postcode":"tq3 3ba",
    "addr:street":"Churchward Road",
    "iso:country":"GB",
    "sg:address":"19 Churchward Road",
    "sg:city":"Paignton",
    "sg:classifiers":[
        {
            "category":"Bus Charters",
            "type":"Transportation"
        }
    ],
    "sg:postcode":"TQ3 3BA",
    "sg:province":"Devon",
    "sg:tags":[
        "hire",
        "coach"
    ],
    "wof:name":"Town & Country Coaches 11",
    "wof:placetype":"venue"
},
  "geometry": {"coordinates":[-3.5689799786,50.4384155273],"type":"Point"}
}