{
  "type": "Feature",
  "properties": {
    "addr:full":"226 Liverpool Road, Longton Preston Lancashire PR4 5YB",
    "addr:housenumber":"226",
    "addr:postcode":"pr4 5yb",
    "addr:street":"Liverpool Road",
    "iso:country":"GB",
    "sg:address":"226 Liverpool Road, Longton",
    "sg:city":"Preston",
    "sg:classifiers":[
        {
            "category":"Organizations",
            "subcategory":"Membership Organization",
            "type":"Services"
        }
    ],
    "sg:postcode":"PR4 5YB",
    "sg:province":"Lancashire",
    "sg:tags":[
        "club"
    ],
    "wof:name":"Shortland Street Consultants Ltd",
    "wof:placetype":"venue"
},
  "geometry": {"coordinates":[-2.7765030861,53.7311058044],"type":"Point"}
}