{
  "type": "Feature",
  "properties": {
    "iso:country":"GB",
    "sg:address":"49 Colley End Park",
    "sg:city":"Paignton",
    "sg:classifiers":[
        {
            "category":"Professional",
            "subcategory":"Business Services",
            "type":"Services"
        }
    ],
    "sg:phone":"+44 1803 559380",
    "sg:postcode":"TQ3 3BY",
    "sg:province":"Devon",
    "sg:tags":[
        "accomodation"
    ],
    "wof:name":"Frederick J Underhay (Paignton) Ltd.",
    "wof:placetype":"venue"
},
  "geometry": {"coordinates":[-3.573657,50.436481],"type":"Point"}
}