{
  "type": "Feature",
  "properties": {
    "addr:full":"1 Woodlands Terr Glasgow Glasgow City G3 6DD",
    "addr:housenumber":"1",
    "addr:postcode":"g3 6dd",
    "addr:street":"Woodlands Terr",
    "iso:country":"GB",
    "sg:address":"1 Woodlands Terr",
    "sg:city":"Glasgow",
    "sg:classifiers":[
        {
            "category":"Organizations",
            "subcategory":"Professional Association",
            "type":"Services"
        }
    ],
    "sg:phone":"+44 141 353 2527",
    "sg:postcode":"G3 6DD",
    "sg:province":"Glasgow City",
    "sg:tags":[
        "union",
        "trade"
    ],
    "wof:name":"UNISON",
    "wof:placetype":"venue"
},
  "geometry": {"coordinates":[-4.277200222,55.8682937622],"type":"Point"}
}