{
  "type": "Feature",
  "properties": {
    "iso:country":"GB",
    "sg:address":"32 Ebble Close, Walton Court",
    "sg:city":"Aylesbury",
    "sg:classifiers":[
        {
            "category":"Professional",
            "type":"Services"
        }
    ],
    "sg:phone":"+44 1296 433144",
    "sg:postcode":"HP21 8RJ",
    "sg:province":"Buckinghamshire",
    "sg:tags":[
        "caterer"
    ],
    "wof:name":"Mosscare Ltd.",
    "wof:placetype":"venue"
},
  "geometry": {"coordinates":[-0.819732,51.797909],"type":"Point"}
}