{
  "type": "Feature",
  "properties": {
    "addr:full":"12 Station Road, Queensferry Deeside Flintshire CH5 1SX",
    "addr:housenumber":"12",
    "addr:postcode":"ch5 1sx",
    "addr:street":"Station Road",
    "iso:country":"GB",
    "sg:address":"12 Station Road, Queensferry",
    "sg:city":"Deeside",
    "sg:classifiers":[
        {
            "category":"Shopping",
            "subcategory":"Comic Books",
            "type":"Retail Goods"
        }
    ],
    "sg:postcode":"CH5 1SX",
    "sg:province":"Flintshire",
    "sg:tags":[
        "jeweller"
    ],
    "wof:name":"Freestyle",
    "wof:placetype":"venue"
},
  "geometry": {"coordinates":[-3.023537,53.206142],"type":"Point"}
}