{
  "type": "Feature",
  "properties": {
    "iso:country":"GB",
    "sg:address":"Eastwick Farm, Eastwick",
    "sg:city":"Ellesmere",
    "sg:classifiers":[
        {
            "category":"Farming",
            "subcategory":"Livestock Farm",
            "type":"Manufacturing & Wholesale Goods"
        }
    ],
    "sg:phone":"+44 1691 690224",
    "sg:postcode":"SY12 9DU",
    "sg:province":"Shropshire",
    "sg:tags":[
        "others"
    ],
    "wof:name":"Madtrax (West) Ltd.",
    "wof:placetype":"venue"
},
  "geometry": {"coordinates":[-2.924869,52.93605],"type":"Point"}
}