{
  "type": "Feature",
  "properties": {
    "iso:country":"GB",
    "sg:address":"9 Wyburn Avenue",
    "sg:city":"Barnet",
    "sg:classifiers":[
        {
            "category":"Communications",
            "type":"Services"
        }
    ],
    "sg:phone":"+44 20 8449 4340",
    "sg:postcode":"EN5 5TG",
    "sg:province":"Hertfordshire",
    "sg:tags":[
        "tv",
        "video",
        "radio"
    ],
    "wof:name":"Deal Communications",
    "wof:placetype":"venue"
},
  "geometry": {"coordinates":[-0.199522,51.657017],"type":"Point"}
}