{
  "type": "Feature",
  "properties": {
    "addr:full":"248 Kings Road Kingston-upon-thames Greater London KT2 5HX",
    "addr:housenumber":"248",
    "addr:postcode":"kt2 5hx",
    "addr:street":"Kings Road",
    "iso:country":"GB",
    "sg:address":"248 Kings Road",
    "sg:city":"Kingston-upon-thames",
    "sg:classifiers":[
        {
            "category":"Building & Trades",
            "subcategory":"Construction",
            "type":"Services"
        }
    ],
    "sg:phone":"+44 20 8546 5470",
    "sg:postcode":"KT2 5HX",
    "sg:province":"Greater London",
    "sg:tags":[
        "builder"
    ],
    "wof:name":"M J Russell",
    "wof:placetype":"venue"
},
  "geometry": {"coordinates":[-0.2902339995,51.4193992615],"type":"Point"}
}