{
  "type": "Feature",
  "properties": {
    "addr:full":"Troedyrhiw Jestyn Farm, Deri Bargoed Caerphilly CF81 9JA",
    "addr:postcode":"cf81 9ja",
    "iso:country":"GB",
    "sg:address":"Troedyrhiw Jestyn Farm, Deri",
    "sg:city":"Bargoed",
    "sg:classifiers":[
        {
            "category":"Farming",
            "subcategory":"Livestock Farm",
            "type":"Manufacturing & Wholesale Goods"
        }
    ],
    "sg:phone":"+44 1443 831717",
    "sg:postcode":"CF81 9JA",
    "sg:province":"Caerphilly",
    "sg:tags":[
        "others"
    ],
    "wof:name":"Ray Powell",
    "wof:placetype":"venue"
},
  "geometry": {"coordinates":[-3.2618350983,51.7073059082],"type":"Point"}
}