{
  "type": "Feature",
  "properties": {
    "addr:full":"Unit 10e Bairds Crescent, Alanshaw Industrial Estate Hamilton South Lanarkshire ML3 9BG",
    "addr:housenumber":"unit 10e",
    "addr:postcode":"ml3 9bg",
    "addr:street":"Bairds Crescent Alanshaw Industrial Estate",
    "iso:country":"GB",
    "sg:address":"Unit 10e Bairds Crescent, Alanshaw Industrial Estate",
    "sg:city":"Hamilton",
    "sg:classifiers":[
        {
            "category":"Bus Charters",
            "type":"Transportation"
        }
    ],
    "sg:phone":"+44 1698 200166",
    "sg:postcode":"ML3 9BG",
    "sg:province":"South Lanarkshire",
    "sg:tags":[
        "hire",
        "coach"
    ],
    "wof:name":"Gem Coaches",
    "wof:placetype":"venue"
},
  "geometry": {"coordinates":[-4.0544290543,55.7763595581],"type":"Point"}
}