{
  "type": "Feature",
  "properties": {
    "iso:country":"GB",
    "sg:address":"134 London Road",
    "sg:city":"St Leonards-on-sea",
    "sg:classifiers":[
        {
            "category":"Professional",
            "subcategory":"Lawyer & Legal Services",
            "type":"Services"
        }
    ],
    "sg:postcode":"TN37 6LT",
    "sg:province":"East Sussex",
    "wof:name":"Capital Costing Services Ltd.",
    "wof:placetype":"venue"
},
  "geometry": {"coordinates":[0.557068,50.861794],"type":"Point"}
}