{
  "type": "Feature",
  "properties": {
    "addr:full":"45 The Moorings, Dalgety Bay Dunfermline Fife KY11 9GP",
    "addr:housenumber":"45",
    "addr:postcode":"ky11 9gp",
    "addr:street":"The Moorings Dalgety Bay",
    "iso:country":"GB",
    "sg:address":"45 The Moorings, Dalgety Bay",
    "sg:city":"Dunfermline",
    "sg:classifiers":[
        {
            "category":"Professional",
            "subcategory":"Art Services",
            "type":"Services"
        },
        {
            "category":"Real Estate",
            "subcategory":"Architect",
            "type":"Services"
        }
    ],
    "sg:postcode":"KY11 9GP",
    "sg:province":"Fife",
    "sg:tags":[
        "photographer"
    ],
    "wof:name":"Les Ironside Photography",
    "wof:placetype":"venue"
},
  "geometry": {"coordinates":[-3.363538,56.042416],"type":"Point"}
}