{
  "type": "Feature",
  "properties": {
    "addr:full":"Wallingford Rd, Uxbridge Trading Est Uxbridge Buckinghamshire UB8 2RW",
    "addr:postcode":"ub8 2rw",
    "addr:street":"Wallingford Rd;Trading Est",
    "iso:country":"GB",
    "sg:address":"Wallingford Rd, Uxbridge Trading Est",
    "sg:city":"Uxbridge",
    "sg:classifiers":[
        {
            "category":"Professional",
            "subcategory":"Engineering",
            "type":"Services"
        }
    ],
    "sg:phone":"+44 1895 256307",
    "sg:postcode":"UB8 2RW",
    "sg:province":"Buckinghamshire",
    "sg:tags":[
        "contractor",
        "electrical",
        "engineer"
    ],
    "wof:name":"Electro Engineering Ltd",
    "wof:placetype":"venue"
},
  "geometry": {"coordinates":[-0.4884339869,51.5373954773],"type":"Point"}
}