{
  "type": "Feature",
  "properties": {
    "iso:country":"GB",
    "sg:address":"225-227 High Street",
    "sg:city":"London",
    "sg:classifiers":[
        {
            "category":"Professional",
            "subcategory":"Lawyer & Legal Services",
            "type":"Services"
        }
    ],
    "sg:phone":"+44 20 8752 1122",
    "sg:postcode":"W3 9BY",
    "sg:province":"Greater London",
    "sg:tags":[
        "solicitor"
    ],
    "wof:name":"Aston Clark Solicitors",
    "wof:placetype":"venue"
},
  "geometry": {"coordinates":[-0.274503,51.508148],"type":"Point"}
}