{
  "type": "Feature",
  "properties": {
    "addr:full":"5 Badminton Road, Downend Bristol City of Bristol BS16 6BB",
    "addr:housenumber":"5",
    "addr:postcode":"bs16 6bb",
    "addr:street":"Badminton Road",
    "iso:country":"GB",
    "sg:address":"5 Badminton Road, Downend",
    "sg:city":"Bristol",
    "sg:classifiers":[
        {
            "category":"Home & Garden",
            "subcategory":"Household Appliances",
            "type":"Retail Goods"
        }
    ],
    "sg:phone":"+44 117 956 0234",
    "sg:postcode":"BS16 6BB",
    "sg:province":"City of Bristol",
    "sg:tags":[
        "electrical",
        "domestic"
    ],
    "wof:name":"Tandy",
    "wof:placetype":"venue"
},
  "geometry": {"coordinates":[-2.5035660267,51.488368988],"type":"Point"}
}