{
  "type": "Feature",
  "properties": {
    "addr:full":"25 Queen Square Bath Bath and North East Somerset BA1 2HX",
    "addr:housenumber":"25",
    "addr:postcode":"ba1 2hx",
    "addr:street":"Queen Square",
    "iso:country":"GB",
    "sg:address":"25 Queen Square",
    "sg:city":"Bath",
    "sg:classifiers":[
        {
            "category":"Professional",
            "subcategory":"Engineering",
            "type":"Services"
        }
    ],
    "sg:phone":"+44 1225 446255",
    "sg:postcode":"BA1 2HX",
    "sg:province":"Bath and North East Somerset",
    "sg:tags":[
        "consulting",
        "engineer"
    ],
    "wof:name":"Brands Leonard",
    "wof:placetype":"venue"
},
  "geometry": {"coordinates":[-2.363592,51.383869],"type":"Point"}
}