{
  "type": "Feature",
  "properties": {
    "addr:full":"44 Regent Street Runcorn Cheshire WA7 1LJ",
    "addr:housenumber":"44",
    "addr:postcode":"wa7 1lj",
    "addr:street":"Regent Street",
    "iso:country":"GB",
    "sg:address":"44 Regent Street",
    "sg:city":"Runcorn",
    "sg:classifiers":[
        {
            "category":"Fast Food",
            "type":"Food & Drink"
        }
    ],
    "sg:phone":"+44 1928 576352",
    "sg:postcode":"WA7 1LJ",
    "sg:province":"Cheshire",
    "sg:tags":[
        "delivery"
    ],
    "wof:name":"Aladin Pizza",
    "wof:placetype":"venue"
},
  "geometry": {"coordinates":[-2.7357280254,53.3418312073],"type":"Point"}
}