{
  "type": "Feature",
  "properties": {
    "addr:full":"Luddington Peterborough Cambridgeshire PE8 5QT",
    "addr:postcode":"pe8 5qt",
    "addr:street":"Peterborough",
    "iso:country":"GB",
    "sg:address":"Luddington",
    "sg:city":"Peterborough",
    "sg:classifiers":[
        {
            "category":"Farming",
            "subcategory":"Livestock Farm",
            "type":"Manufacturing & Wholesale Goods"
        }
    ],
    "sg:phone":"+44 1733 240359",
    "sg:postcode":"PE8 5QT",
    "sg:province":"Cambridgeshire",
    "sg:tags":[
        "others"
    ],
    "wof:name":"B Spendelow & Son",
    "wof:placetype":"venue"
},
  "geometry": {"coordinates":[-0.3732990026,52.4385871887],"type":"Point"}
}