{
  "type": "Feature",
  "properties": {
    "iso:country":"GB",
    "sg:address":"Po Box 143",
    "sg:city":"Northampton",
    "sg:classifiers":[
        {
            "category":"Utilities",
            "subcategory":"Water",
            "type":"Services"
        }
    ],
    "sg:postcode":"NN4 7ZU",
    "sg:province":"Northamptonshire",
    "wof:name":"Aqua-Gas A V K Ltd.",
    "wof:placetype":"venue"
},
  "geometry": {"coordinates":[-0.868619,52.216671],"type":"Point"}
}