{
  "type": "Feature",
  "properties": {
    "iso:country":"GB",
    "sg:address":"1-2 Prospect Terrace",
    "sg:city":"North Shields",
    "sg:classifiers":[
        {
            "category":"Organizations",
            "subcategory":"Non-profit Organization",
            "type":"Services"
        }
    ],
    "sg:phone":"+44 191 296 4222",
    "sg:postcode":"NE30 1DX",
    "sg:province":"Tyne and Wear",
    "sg:tags":[
        "charitable",
        "organisation",
        "voluntary",
        "charity"
    ],
    "wof:name":"Churches Acting Together Furniture Project",
    "wof:placetype":"venue"
},
  "geometry": {"coordinates":[-1.436161,55.012772],"type":"Point"}
}