{
  "type": "Feature",
  "properties": {
    "iso:country":"GB",
    "sg:address":"Hill Top, Bighton Lane, Bishops Sutton",
    "sg:city":"Alresford",
    "sg:classifiers":[
        {
            "category":"Home & Garden",
            "subcategory":"Building Materials",
            "type":"Retail Goods"
        }
    ],
    "sg:phone":"+44 1962 736190",
    "sg:postcode":"SO24 9SW",
    "sg:province":"Hampshire",
    "sg:tags":[
        "ironwork",
        "diy",
        "wrought"
    ],
    "wof:name":"C A D Gates & Railings",
    "wof:placetype":"venue"
},
  "geometry": {"coordinates":[-1.161724,51.090511],"type":"Point"}
}