{
  "type": "Feature",
  "properties": {
    "addr:full":"87 Upper Bristol Road Weston-super-mare Somerset BS22 8DN",
    "addr:housenumber":"87",
    "addr:postcode":"bs22 8dn",
    "addr:street":"Upper Bristol Road",
    "iso:country":"GB",
    "sg:address":"87 Upper Bristol Road",
    "sg:city":"Weston-super-mare",
    "sg:classifiers":[
        {
            "category":"Shopping",
            "subcategory":"Music",
            "type":"Retail Goods"
        }
    ],
    "sg:phone":"+44 1934 621719",
    "sg:postcode":"BS22 8DN",
    "sg:province":"Somerset",
    "sg:tags":[
        "shop"
    ],
    "wof:name":"Key West Music",
    "wof:placetype":"venue"
},
  "geometry": {"coordinates":[-2.948464,51.357269],"type":"Point"}
}