{
  "type": "Feature",
  "properties": {
    "addr:full":"20a St Marys Rd Market Harborough Leicestershire LE16 7DU",
    "addr:housenumber":"20a",
    "addr:postcode":"le16 7du",
    "addr:street":"St Marys Rd",
    "iso:country":"GB",
    "sg:address":"20a St Marys Rd",
    "sg:city":"Market Harborough",
    "sg:classifiers":[
        {
            "category":"Personal",
            "subcategory":"Beauty Salon",
            "type":"Services"
        }
    ],
    "sg:phone":"+44 1858 463616",
    "sg:postcode":"LE16 7DU",
    "sg:province":"Leicestershire",
    "sg:tags":[
        "unisex",
        "hairdresser"
    ],
    "wof:name":"Sarah Jane Hairstylists",
    "wof:placetype":"venue"
},
  "geometry": {"coordinates":[-0.9179980159,52.4779396057],"type":"Point"}
}