{
  "type": "Feature",
  "properties": {
    "iso:country":"GB",
    "sg:address":"Unit 2 Brook Street, Syston",
    "sg:city":"Leicester",
    "sg:classifiers":[
        {
            "category":"Home & Garden",
            "subcategory":"Hardware",
            "type":"Retail Goods"
        }
    ],
    "sg:phone":"+44 116 269 6941",
    "sg:postcode":"LE7 1GD",
    "sg:province":"Leicestershire",
    "sg:tags":[
        "equipment",
        "welding"
    ],
    "wof:name":"Westermans International",
    "wof:placetype":"venue"
},
  "geometry": {"coordinates":[-1.0777050257,52.6996002197],"type":"Point"}
}