{
  "type": "Feature",
  "properties": {
    "iso:country":"GB",
    "sg:address":"Albert Road",
    "sg:city":"Grange-over-sands",
    "sg:classifiers":[
        {
            "category":"Health Services",
            "subcategory":"Nursing And Care Facility",
            "type":"Services"
        },
        {
            "category":"Social Services",
            "subcategory":"Retirement Home",
            "type":"Services"
        }
    ],
    "sg:phone":"+44 15395 33122",
    "sg:postcode":"LA11 7EZ",
    "sg:province":"Cumbria",
    "sg:tags":[
        "rest"
    ],
    "wof:name":"Grange Cottage Retirement Home",
    "wof:placetype":"venue"
},
  "geometry": {"coordinates":[-2.911237,54.192448],"type":"Point"}
}