{
  "type": "Feature",
  "properties": {
    "addr:full":"The Ridges, Abingdon Road, Clifton Hampden Abingdon Oxfordshire OX14 3EG",
    "addr:postcode":"ox14 3eg",
    "addr:street":"Abingdon Road",
    "iso:country":"GB",
    "sg:address":"The Ridges, Abingdon Road, Clifton Hampden",
    "sg:city":"Abingdon",
    "sg:classifiers":[
        {
            "category":"Professional",
            "subcategory":"Art Services",
            "type":"Services"
        }
    ],
    "sg:phone":"+44 1865 407040",
    "sg:postcode":"OX14 3EG",
    "sg:province":"Oxfordshire",
    "sg:tags":[
        "graphic",
        "designer"
    ],
    "wof:name":"Bounce Marketing & Design",
    "wof:placetype":"venue"
},
  "geometry": {"coordinates":[-1.2099440098,51.6568946838],"type":"Point"}
}