{
  "type": "Feature",
  "properties": {
    "addr:full":"4 Locksley Close Torquay Devon TQ1 3HQ",
    "addr:housenumber":"4",
    "addr:postcode":"tq1 3hq",
    "addr:street":"Locksley Close",
    "iso:country":"GB",
    "sg:address":"4 Locksley Close",
    "sg:city":"Torquay",
    "sg:classifiers":[
        {
            "category":"Retail",
            "subcategory":"Repair Shop",
            "type":"Services"
        },
        {
            "category":"Social Services",
            "subcategory":"Child Care",
            "type":"Services"
        },
        {
            "category":"Communications",
            "subcategory":"Film & Video Production",
            "type":"Services"
        }
    ],
    "sg:postcode":"TQ1 3HQ",
    "sg:province":"Devon",
    "sg:tags":[
        "television",
        "good",
        "tv",
        "studio",
        "servicing",
        "maintenance",
        "radio"
    ],
    "wof:name":"John Leitch",
    "wof:placetype":"venue"
},
  "geometry": {"coordinates":[-3.529839,50.475124],"type":"Point"}
}