{
  "type": "Feature",
  "properties": {
    "addr:full":"Unit 3, 4 & 5 The Barn Workshops, The Street Fleet Hampshire GU51 5SD",
    "addr:housenumber":"unit;4 & 5 the;workshops",
    "addr:postcode":"gu51 5sd",
    "addr:street":"The Street",
    "iso:country":"GB",
    "sg:address":"Unit 3, 4 & 5 The Barn Workshops, The Street",
    "sg:city":"Fleet",
    "sg:classifiers":[
        {
            "category":"Professional",
            "subcategory":"Engineering",
            "type":"Services"
        }
    ],
    "sg:phone":"+44 1252 815200",
    "sg:postcode":"GU51 5SD",
    "sg:province":"Hampshire",
    "sg:tags":[
        "engineer",
        "mechanical"
    ],
    "wof:name":"Kestrel Supplies",
    "wof:placetype":"venue"
},
  "geometry": {"coordinates":[-0.85694,51.264969],"type":"Point"}
}