{
  "type": "Feature",
  "properties": {
    "addr:full":"128 The Brdwy Southall Greater London UB1 1QF",
    "addr:housenumber":"128",
    "addr:postcode":"ub1 1qf",
    "addr:street":"The Brdwy",
    "iso:country":"GB",
    "sg:address":"128 The Brdwy",
    "sg:city":"Southall",
    "sg:classifiers":[
        {
            "category":"Wholesale",
            "subcategory":"Non-durable Goods",
            "type":"Manufacturing & Wholesale Goods"
        }
    ],
    "sg:phone":"+44 20 8574 2280",
    "sg:postcode":"UB1 1QF",
    "sg:province":"Greater London",
    "sg:tags":[
        "carry",
        "cash"
    ],
    "wof:name":"Surequote Ltd.",
    "wof:placetype":"venue"
},
  "geometry": {"coordinates":[-0.3783339858,51.5113792419],"type":"Point"}
}