{
  "type": "Feature",
  "properties": {
    "addr:full":"Station App, Wormley Godalming Surrey GU8 5TB",
    "addr:postcode":"gu8 5tb",
    "iso:country":"GB",
    "sg:address":"Station App, Wormley",
    "sg:city":"Godalming",
    "sg:classifiers":[
        {
            "category":"Building & Trades",
            "subcategory":"Construction",
            "type":"Services"
        }
    ],
    "sg:postcode":"GU8 5TB",
    "sg:province":"Surrey",
    "sg:tags":[
        "contractor",
        "paving",
        "driveway"
    ],
    "wof:name":"Surrey Drives & Courtyards",
    "wof:placetype":"venue"
},
  "geometry": {"coordinates":[-0.6453740001,51.1400794983],"type":"Point"}
}