{
  "type": "Feature",
  "properties": {
    "addr:full":"Unit 6 Fleetmarston Farm, Fleetmarston Aylesbury Buckinghamshire HP18 0PZ",
    "addr:housenumber":"unit 6 fleetmarston farm",
    "addr:postcode":"hp18 0pz",
    "addr:street":"Fleetmarston Aylesbury",
    "iso:country":"GB",
    "sg:address":"Unit 6 Fleetmarston Farm, Fleetmarston",
    "sg:city":"Aylesbury",
    "sg:classifiers":[
        {
            "category":"Building & Trades",
            "subcategory":"Construction",
            "type":"Services"
        }
    ],
    "sg:postcode":"HP18 0PZ",
    "sg:province":"Buckinghamshire",
    "sg:tags":[
        "joiner",
        "carpenter"
    ],
    "wof:name":"R & R Display Exhibition Joinery",
    "wof:placetype":"venue"
},
  "geometry": {"coordinates":[-0.8768699765,51.8414916992],"type":"Point"}
}