{
  "type": "Feature",
  "properties": {
    "addr:full":"Starholme Farm Carr Road, North Kelsey Market Rasen Lincolnshire LN7 6LG",
    "addr:postcode":"ln7 6lg",
    "addr:street":"Carr Road North Kelsey",
    "iso:country":"GB",
    "sg:address":"Starholme Farm Carr Road, North Kelsey",
    "sg:city":"Market Rasen",
    "sg:classifiers":[
        {
            "category":"Building & Trades",
            "subcategory":"Plumbing",
            "type":"Services"
        }
    ],
    "sg:phone":"+44 1652 678876",
    "sg:postcode":"LN7 6LG",
    "sg:province":"Lincolnshire",
    "sg:tags":[
        "filtration",
        "system"
    ],
    "wof:name":"Howard Filter Systems",
    "wof:placetype":"venue"
},
  "geometry": {"coordinates":[-0.427096,53.500031],"type":"Point"}
}