{
  "type": "Feature",
  "properties": {
    "addr:full":"77 Fore Street Hertford Hertfordshire SG14 1AL",
    "addr:housenumber":"77",
    "addr:postcode":"sg14 1al",
    "addr:street":"Fore Street",
    "iso:country":"GB",
    "sg:address":"77 Fore Street",
    "sg:city":"Hertford",
    "sg:classifiers":[
        {
            "category":"Retail",
            "subcategory":"Veterinary Services",
            "type":"Services"
        }
    ],
    "sg:phone":"+44 1992 582115",
    "sg:postcode":"SG14 1AL",
    "sg:province":"Hertfordshire",
    "sg:tags":[
        "surgeon"
    ],
    "wof:name":"The Chestnut Veterinary Group",
    "wof:placetype":"venue"
},
  "geometry": {"coordinates":[-0.0757070035,51.7966270447],"type":"Point"}
}