{
  "type": "Feature",
  "properties": {
    "iso:country":"GB",
    "sg:address":"5 Cherry Tree La",
    "sg:city":"St Albans",
    "sg:classifiers":[
        {
            "category":"Government",
            "subcategory":"Fire Station",
            "type":"Public Place"
        }
    ],
    "sg:phone":"+44 1582 833843",
    "sg:postcode":"AL4 8HP",
    "sg:province":"Hertfordshire",
    "sg:tags":[
        "security"
    ],
    "wof:name":"Consort Fire Consultants",
    "wof:placetype":"venue"
},
  "geometry": {"coordinates":[-0.3154450059,51.8176002502],"type":"Point"}
}