{
  "type": "Feature",
  "properties": {
    "addr:full":"16 Greendykes Rd Broxburn City of Edinburgh EH52 5AG",
    "addr:housenumber":"16",
    "addr:postcode":"eh52 5ag",
    "addr:street":"Greendykes Rd",
    "iso:country":"GB",
    "sg:address":"16 Greendykes Rd",
    "sg:city":"Broxburn",
    "sg:classifiers":[
        {
            "category":"Retail",
            "subcategory":"Veterinary Services",
            "type":"Services"
        }
    ],
    "sg:phone":"+44 1506 852498",
    "sg:postcode":"EH52 5AG",
    "sg:province":"City of Edinburgh",
    "sg:tags":[
        "surgeon"
    ],
    "wof:name":"Jamesp W Ford",
    "wof:placetype":"venue"
},
  "geometry": {"coordinates":[-3.4698359966,55.9347648621],"type":"Point"}
}