{
  "type": "Feature",
  "properties": {
    "iso:country":"GB",
    "sg:address":"9 Hebden Rd",
    "sg:city":"Liverpool",
    "sg:classifiers":[
        {
            "category":"Utilities",
            "subcategory":"Fuel Oil & Lpg",
            "type":"Services"
        }
    ],
    "sg:phone":"+44 151 546 1368",
    "sg:postcode":"L11 9AJ",
    "sg:province":"Merseyside",
    "sg:tags":[
        "coal",
        "smokeless"
    ],
    "wof:name":"A Morris & Son",
    "wof:placetype":"venue"
},
  "geometry": {"coordinates":[-2.909613,53.448994],"type":"Point"}
}