{
  "type": "Feature",
  "properties": {
    "addr:full":"33-35 Ilkley Road Otley North Yorkshire LS21 3JN",
    "addr:housenumber":"33-35",
    "addr:postcode":"ls21 3jn",
    "addr:street":"Ilkley Road",
    "iso:country":"GB",
    "sg:address":"33-35 Ilkley Road",
    "sg:city":"Otley",
    "sg:classifiers":[
        {
            "category":"Manufacturing",
            "subcategory":"Metals",
            "type":"Manufacturing & Wholesale Goods"
        }
    ],
    "sg:phone":"+44 1943 850183",
    "sg:postcode":"LS21 3JN",
    "sg:province":"North Yorkshire",
    "sg:tags":[
        "steel",
        "stockholder"
    ],
    "wof:name":"Foy Steel",
    "wof:placetype":"venue"
},
  "geometry": {"coordinates":[-1.7019729614,53.9034996033],"type":"Point"}
}