{
  "type": "Feature",
  "properties": {
    "addr:full":"36 Queslett Rd Birmingham West Midlands B43 6PH",
    "addr:housenumber":"36",
    "addr:postcode":"b43 6ph",
    "addr:street":"Queslett Rd",
    "iso:country":"GB",
    "sg:address":"36 Queslett Rd",
    "sg:city":"Birmingham",
    "sg:classifiers":[
        {
            "category":"Autos & Motor Vehicles",
            "subcategory":"Fuel & Gas Station",
            "type":"Retail Goods"
        }
    ],
    "sg:postcode":"B43 6PH",
    "sg:province":"West Midlands",
    "sg:tags":[
        "petrol",
        "filling"
    ],
    "wof:name":"Beacon Service Station",
    "wof:placetype":"venue"
},
  "geometry": {"coordinates":[-1.9302159548,52.5456886292],"type":"Point"}
}