{
  "type": "Feature",
  "properties": {
    "addr:full":"Wick Lane London Greater London E3 2TB",
    "addr:postcode":"e3 2tb",
    "addr:street":"Wick Lane",
    "iso:country":"GB",
    "sg:address":"Wick Lane",
    "sg:city":"London",
    "sg:classifiers":[
        {
            "category":"Home & Garden",
            "subcategory":"Building Materials",
            "type":"Retail Goods"
        }
    ],
    "sg:phone":"+44 20 8981 8898",
    "sg:postcode":"E3 2TB",
    "sg:province":"Greater London",
    "sg:tags":[
        "ready",
        "mixed",
        "concrete"
    ],
    "wof:name":"Plasmor Ltd.",
    "wof:placetype":"venue"
},
  "geometry": {"coordinates":[-0.026654,51.538895],"type":"Point"}
}