{
  "type": "Feature",
  "properties": {
    "addr:full":"12 Arwenck Street Falmouth Cornwall TR11 3JD",
    "addr:housenumber":"12",
    "addr:postcode":"tr11 3jd",
    "addr:street":"Arwenck Street",
    "iso:country":"GB",
    "sg:address":"12 Arwenck Street",
    "sg:city":"Falmouth",
    "sg:classifiers":[
        {
            "category":"Real Estate",
            "subcategory":"Surveying",
            "type":"Services"
        },
        {
            "category":"Real Estate",
            "subcategory":"Architect",
            "type":"Services"
        }
    ],
    "sg:phone":"+44 1326 318599",
    "sg:postcode":"TR11 3JD",
    "sg:province":"Cornwall",
    "sg:tags":[
        "building",
        "surveyor"
    ],
    "wof:name":"Thomas Richard G Chartered Building Surveyors",
    "wof:placetype":"venue"
},
  "geometry": {"coordinates":[-5.067693,50.153156],"type":"Point"}
}