{
  "type": "Feature",
  "properties": {
    "iso:country":"GB",
    "sg:address":"Foster Hill Road",
    "sg:city":"Bedford",
    "sg:classifiers":[
        {
            "category":"Restaurant",
            "type":"Food & Drink"
        }
    ],
    "sg:phone":"+44 1234 215556",
    "sg:postcode":"MK40 2EN",
    "sg:province":"Bedfordshire",
    "sg:tags":[
        "indian"
    ],
    "wof:name":"Choudhuri Tandoori",
    "wof:placetype":"venue"
},
  "geometry": {"coordinates":[-0.468911,52.1437],"type":"Point"}
}