{
  "type": "Feature",
  "properties": {
    "addr:full":"150 Main Street Bingley West Yorkshire BD16 2HR",
    "addr:housenumber":"150",
    "addr:postcode":"bd16 2hr",
    "addr:street":"Main Street",
    "iso:country":"GB",
    "sg:address":"150 Main Street",
    "sg:city":"Bingley",
    "sg:classifiers":[
        {
            "category":"Real Estate",
            "subcategory":"Real Estate Agent",
            "type":"Services"
        }
    ],
    "sg:phone":"+44 1274 551552",
    "sg:postcode":"BD16 2HR",
    "sg:province":"West Yorkshire",
    "wof:name":"The Green Partnership",
    "wof:placetype":"venue"
},
  "geometry": {"coordinates":[-1.8387730122,53.8488464355],"type":"Point"}
}