{
  "type": "Feature",
  "properties": {
    "iso:country":"GB",
    "sg:address":"Rathbone Ho, High St, Staplehurst",
    "sg:city":"Tonbridge",
    "sg:classifiers":[
        {
            "category":"Real Estate",
            "subcategory":"Architect",
            "type":"Services"
        }
    ],
    "sg:postcode":"TN12 0AD",
    "sg:province":"Kent",
    "wof:name":"Cader Engineering Services Ltd",
    "wof:placetype":"venue"
},
  "geometry": {"coordinates":[0.552592,51.167049],"type":"Point"}
}