{
  "type": "Feature",
  "properties": {
    "iso:country":"GB",
    "sg:address":"30 High Street, Watton",
    "sg:city":"Thetford",
    "sg:classifiers":[
        {
            "category":"Retail",
            "subcategory":"Repair Shop",
            "type":"Services"
        }
    ],
    "sg:postcode":"IP25 6AE",
    "sg:province":"Norfolk",
    "sg:tags":[
        "radio",
        "television",
        "video"
    ],
    "wof:name":"Julian Horn",
    "wof:placetype":"venue"
},
  "geometry": {"coordinates":[0.8246009946,52.5715332031],"type":"Point"}
}