{
  "type": "Feature",
  "properties": {
    "addr:full":"12 Bridge Street Buckingham Buckinghamshire MK18 1AF",
    "addr:housenumber":"12",
    "addr:postcode":"mk18 1af",
    "addr:street":"Bridge Street",
    "iso:country":"GB",
    "sg:address":"12 Bridge Street",
    "sg:city":"Buckingham",
    "sg:classifiers":[
        {
            "category":"Personal",
            "subcategory":"Beauty Salon",
            "type":"Services"
        },
        {
            "category":"Personal",
            "subcategory":"Barber",
            "type":"Services"
        }
    ],
    "sg:phone":"+44 1280 813379",
    "sg:postcode":"MK18 1AF",
    "sg:province":"Buckinghamshire",
    "sg:tags":[
        "unisex",
        "hairdresser"
    ],
    "wof:name":"Lido Romeo",
    "wof:placetype":"venue"
},
  "geometry": {"coordinates":[-0.9872210026,51.9989700317],"type":"Point"}
}