{
  "type": "Feature",
  "properties": {
    "addr:full":"7 Marine Rd Dunbar East Lothian EH42 1AR",
    "addr:housenumber":"7",
    "addr:postcode":"eh42 1ar",
    "addr:street":"Marine Rd",
    "iso:country":"GB",
    "sg:address":"7 Marine Rd",
    "sg:city":"Dunbar",
    "sg:classifiers":[
        {
            "category":"Utilities",
            "type":"Services"
        }
    ],
    "sg:phone":"+44 1368 865444",
    "sg:postcode":"EH42 1AR",
    "sg:province":"East Lothian",
    "sg:tags":[
        "internet"
    ],
    "wof:name":"Expressmedia",
    "wof:placetype":"venue"
},
  "geometry": {"coordinates":[-2.525584,56.004753],"type":"Point"}
}