{
  "type": "Feature",
  "properties": {
    "addr:full":"High Street Beckenham Kent BR3 1AY",
    "addr:postcode":"br3 1ay",
    "addr:street":"High Street",
    "iso:country":"GB",
    "sg:address":"High Street",
    "sg:city":"Beckenham",
    "sg:classifiers":[
        {
            "category":"Health Services",
            "subcategory":"Health Practitioner",
            "type":"Services"
        }
    ],
    "sg:phone":"+44 20 8658 9958",
    "sg:postcode":"BR3 1AY",
    "sg:province":"Kent",
    "sg:tags":[
        "psychotherapist"
    ],
    "wof:name":"The Therapy Place",
    "wof:placetype":"venue"
},
  "geometry": {"coordinates":[-0.0250240006,51.4105567932],"type":"Point"}
}