{
  "type": "Feature",
  "properties": {
    "iso:country":"GB",
    "sg:address":"Priory Gates, Priory Road, Wolston",
    "sg:city":"Coventry",
    "sg:classifiers":[
        {
            "category":"Real Estate",
            "subcategory":"Real Estate Agent",
            "type":"Services"
        }
    ],
    "sg:phone":"+44 24 7654 1000",
    "sg:postcode":"CV8 3TA",
    "sg:province":"Warwickshire",
    "sg:tags":[
        "list",
        "broker"
    ],
    "wof:name":"A D C Marketing Ltd.",
    "wof:placetype":"venue"
},
  "geometry": {"coordinates":[-1.395956,52.377865],"type":"Point"}
}