{
  "type": "Feature",
  "properties": {
    "addr:full":"12 London Road, Oadby Leicester Leicestershire LE2 5DG",
    "addr:housenumber":"12",
    "addr:postcode":"le2 5dg",
    "addr:street":"London Road",
    "iso:country":"GB",
    "sg:address":"12 London Road, Oadby",
    "sg:city":"Leicester",
    "sg:classifiers":[
        {
            "category":"Retail",
            "subcategory":"Funeral Services",
            "type":"Services"
        }
    ],
    "sg:phone":"+44 116 271 2340",
    "sg:postcode":"LE2 5DG",
    "sg:province":"Leicestershire",
    "sg:tags":[
        "director"
    ],
    "wof:name":"A J Adkinson & Son",
    "wof:placetype":"venue"
},
  "geometry": {"coordinates":[-1.0784289837,52.597328186],"type":"Point"}
}