{
  "type": "Feature",
  "properties": {
    "addr:full":"46 Lockfield Avenue, Brimsdown Enfield Greater London EN3 7PX",
    "addr:housenumber":"46",
    "addr:postcode":"en3 7px",
    "addr:street":"Lockfield Avenue Brimsdown",
    "iso:country":"GB",
    "sg:address":"46 Lockfield Avenue, Brimsdown",
    "sg:city":"Enfield",
    "sg:classifiers":[
        {
            "category":"Organizations",
            "subcategory":"Labor Organization",
            "type":"Services"
        },
        {
            "category":"Professional",
            "subcategory":"Business Services",
            "type":"Services"
        }
    ],
    "sg:phone":"+44 20 8805 3344",
    "sg:postcode":"EN3 7PX",
    "sg:province":"Greater London",
    "sg:tags":[
        "import",
        "export",
        "agent"
    ],
    "wof:name":"Mondial Forwarding Ltd",
    "wof:placetype":"venue"
},
  "geometry": {"coordinates":[-0.026052,51.6600837708],"type":"Point"}
}