{
  "type": "Feature",
  "properties": {
    "iso:country":"GB",
    "sg:address":"12 The Mall, Craigshill",
    "sg:city":"Livingston",
    "sg:classifiers":[
        {
            "category":"Shopping",
            "subcategory":"Pharmacy",
            "type":"Retail Goods"
        }
    ],
    "sg:phone":"+44 1506 432504",
    "sg:postcode":"EH54 5ED",
    "sg:province":"West Lothian",
    "sg:tags":[
        "pharmacist",
        "chemist"
    ],
    "wof:name":"Moss Chemists",
    "wof:placetype":"venue"
},
  "geometry": {"coordinates":[-3.492884,55.902233],"type":"Point"}
}