{
  "type": "Feature",
  "properties": {
    "iso:country":"GB",
    "sg:address":"69 Forest Park",
    "sg:city":"Stonehaven",
    "sg:classifiers":[
        {
            "category":"Utilities",
            "subcategory":"Fuel Oil & Lpg",
            "type":"Services"
        }
    ],
    "sg:phone":"+44 1569 764359",
    "sg:postcode":"AB39 2GF",
    "sg:province":"Aberdeenshire",
    "sg:tags":[
        "distributor"
    ],
    "wof:name":"Eddie Harrison Ltd.",
    "wof:placetype":"venue"
},
  "geometry": {"coordinates":[-2.23545,56.962189],"type":"Point"}
}