{
  "type": "Feature",
  "properties": {
    "iso:country":"GB",
    "sg:address":"Factory Rd, Blaydon Haugh Indust Est",
    "sg:city":"Blaydon On Tyne",
    "sg:classifiers":[
        {
            "category":"Freight",
            "type":"Transportation"
        }
    ],
    "sg:phone":"+44 191 414 8581",
    "sg:postcode":"NE21 5SA",
    "sg:province":"Tyne and Wear",
    "sg:tags":[
        "haulage",
        "road"
    ],
    "wof:name":"Short Eric Haulage",
    "wof:placetype":"venue"
},
  "geometry": {"coordinates":[-1.7051000595,54.9665603638],"type":"Point"}
}