{
  "type": "Feature",
  "properties": {
    "addr:full":"Waverley Railway Station Edinburgh City of Edinburgh EH1 1BB",
    "addr:postcode":"eh1 1bb",
    "iso:country":"GB",
    "sg:address":"Waverley Railway Station",
    "sg:city":"Edinburgh",
    "sg:classifiers":[
        {
            "category":"Cafe",
            "type":"Food & Drink"
        }
    ],
    "sg:phone":"+44 131 557 4244",
    "sg:postcode":"EH1 1BB",
    "sg:province":"City of Edinburgh",
    "sg:tags":[
        "tea",
        "room"
    ],
    "wof:name":"Costa",
    "wof:placetype":"venue"
},
  "geometry": {"coordinates":[-3.192149,55.952671],"type":"Point"}
}