{
  "type": "Feature",
  "properties": {
    "addr:full":"Church Road, Quarndon Derby Derbyshire DE22 5JA",
    "addr:postcode":"de22 5ja",
    "addr:street":"Church Road",
    "iso:country":"GB",
    "sg:address":"Church Road, Quarndon",
    "sg:city":"Derby",
    "sg:classifiers":[
        {
            "category":"Education",
            "subcategory":"School",
            "type":"Public Place"
        }
    ],
    "sg:phone":"+44 1332 550172",
    "sg:postcode":"DE22 5JA",
    "sg:province":"Derbyshire",
    "sg:tags":[
        "college"
    ],
    "wof:name":"Curzon C of E Voluntary Aided Primary School",
    "wof:placetype":"venue"
},
  "geometry": {"coordinates":[-1.502269,52.966129],"type":"Point"}
}