{
  "type": "Feature",
  "properties": {
    "iso:country":"GB",
    "sg:address":"36 Petitor Rd",
    "sg:city":"Torquay",
    "sg:classifiers":[
        {
            "category":"Freight",
            "type":"Transportation"
        }
    ],
    "sg:phone":"+44 1803 328706",
    "sg:postcode":"TQ1 4QF",
    "sg:province":"Devon",
    "sg:tags":[
        "haulage",
        "road"
    ],
    "wof:name":"Alex Sim",
    "wof:placetype":"venue"
},
  "geometry": {"coordinates":[-3.5213088989,50.4852371216],"type":"Point"}
}