{
  "type": "Feature",
  "properties": {
    "addr:full":"Station Masters House, Station Road Horsham West Sussex RH12 3SR",
    "addr:postcode":"rh12 3sr",
    "addr:street":"Station Road",
    "iso:country":"GB",
    "sg:address":"Station Masters House, Station Road",
    "sg:city":"Horsham",
    "sg:classifiers":[
        {
            "category":"Freight",
            "type":"Transportation"
        }
    ],
    "sg:postcode":"RH12 3SR",
    "sg:province":"West Sussex",
    "sg:tags":[
        "haulage",
        "road"
    ],
    "wof:name":"K A M Trucking",
    "wof:placetype":"venue"
},
  "geometry": {"coordinates":[-0.3349559903,51.0934867859],"type":"Point"}
}