{
  "type": "Feature",
  "properties": {
    "addr:full":"Gloucester Road, Almondsbury Bristol Gloucestershire BS32 4HY",
    "addr:postcode":"bs32 4hy",
    "addr:street":"Gloucester Road",
    "iso:country":"GB",
    "sg:address":"Gloucester Road, Almondsbury",
    "sg:city":"Bristol",
    "sg:classifiers":[
        {
            "category":"Autos & Motor Vehicles",
            "subcategory":"Fuel & Gas Station",
            "type":"Retail Goods"
        }
    ],
    "sg:phone":"+44 1454 614274",
    "sg:postcode":"BS32 4HY",
    "sg:province":"Gloucestershire",
    "sg:tags":[
        "petrol",
        "filling"
    ],
    "wof:name":"Almondsbury Filling Station",
    "wof:placetype":"venue"
},
  "geometry": {"coordinates":[-2.5646190643,51.5565261841],"type":"Point"}
}