{
  "type": "Feature",
  "properties": {
    "addr:full":"St Andrews House, St Andrews Street St Ives Cornwall TR26 1AH",
    "addr:postcode":"tr26 1ah",
    "addr:street":"St Andrews Street",
    "iso:country":"GB",
    "sg:address":"St Andrews House, St Andrews Street",
    "sg:city":"St Ives",
    "sg:classifiers":[
        {
            "category":"Travel",
            "subcategory":"Hotels & Motels",
            "type":"Entertainment"
        }
    ],
    "sg:phone":"+44 1736 794024",
    "sg:postcode":"TR26 1AH",
    "sg:province":"Cornwall",
    "sg:tags":[
        "self",
        "catering"
    ],
    "wof:name":"Powells Holidays",
    "wof:placetype":"venue"
},
  "geometry": {"coordinates":[-5.4796061516,50.212146759],"type":"Point"}
}