{
  "type": "Feature",
  "properties": {
    "addr:full":"22 Ashleigh Rd Leeds West Yorkshire LS16 5AX",
    "addr:housenumber":"22",
    "addr:postcode":"ls16 5ax",
    "addr:street":"Ashleigh Rd",
    "iso:country":"GB",
    "sg:address":"22 Ashleigh Rd",
    "sg:city":"Leeds",
    "sg:classifiers":[
        {
            "category":"Real Estate",
            "subcategory":"Architect",
            "type":"Services"
        }
    ],
    "sg:postcode":"LS16 5AX",
    "sg:province":"West Yorkshire",
    "wof:name":"Dawson,William J,",
    "wof:placetype":"venue"
},
  "geometry": {"coordinates":[-1.599383,53.834038],"type":"Point"}
}