{
  "type": "Feature",
  "properties": {
    "addr:full":"88-90 Lillie Rd, Fulham, London Greater London SW6 7SR",
    "addr:housenumber":"88-90",
    "addr:postcode":"sw6 7sr",
    "addr:street":"Lillie Rd",
    "iso:country":"GB",
    "sg:address":"88-90 Lillie Rd, Fulham,",
    "sg:city":"London",
    "sg:classifiers":[
        {
            "category":"Food & Beverages",
            "subcategory":"Supermarket",
            "type":"Retail Goods"
        }
    ],
    "sg:postcode":"SW6 7SR",
    "sg:province":"Greater London",
    "wof:name":"Rightmarts Ltd",
    "wof:placetype":"venue"
},
  "geometry": {"coordinates":[-0.209589,51.483261],"type":"Point"}
}