{
  "type": "Feature",
  "properties": {
    "iso:country":"GB",
    "sg:address":"The Street, Braughing",
    "sg:city":"Ware",
    "sg:classifiers":[
        {
            "category":"Education",
            "subcategory":"School",
            "type":"Public Place"
        }
    ],
    "sg:phone":"+44 1920 821461",
    "sg:postcode":"SG11 2QE",
    "sg:province":"Hertfordshire",
    "sg:tags":[
        "local",
        "authority"
    ],
    "wof:name":"Jenyns School",
    "wof:placetype":"venue"
},
  "geometry": {"coordinates":[0.03096,51.908604],"type":"Point"}
}