{
  "type": "Feature",
  "properties": {
    "addr:full":"363 Oxford Street London Greater London W1C 2BJ",
    "addr:housenumber":"363",
    "addr:postcode":"w1c 2bj",
    "addr:street":"Oxford Street",
    "iso:country":"GB",
    "sg:address":"363 Oxford Street",
    "sg:city":"London",
    "sg:classifiers":[
        {
            "category":"Shopping",
            "subcategory":"Music",
            "type":"Retail Goods"
        }
    ],
    "sg:phone":"+44 20 7629 1240",
    "sg:postcode":"W1C 2BJ",
    "sg:province":"Greater London",
    "sg:tags":[
        "record",
        "tape",
        "cd"
    ],
    "wof:name":"H M V (U K) Ltd.",
    "wof:placetype":"venue"
},
  "geometry": {"coordinates":[-0.148279,51.5145],"type":"Point"}
}