{
  "type": "Feature",
  "properties": {
    "addr:full":"26-28 Low Street Keighley West Yorkshire BD21 3PP",
    "addr:housenumber":"26-28",
    "addr:postcode":"bd21 3pp",
    "addr:street":"Low Street",
    "iso:country":"GB",
    "sg:address":"26-28 Low Street",
    "sg:city":"Keighley",
    "sg:classifiers":[
        {
            "category":"Shopping",
            "subcategory":"Baby Store",
            "type":"Retail Goods"
        }
    ],
    "sg:phone":"+44 1535 691783",
    "sg:postcode":"BD21 3PP",
    "sg:province":"West Yorkshire",
    "sg:tags":[
        "babywear",
        "childrens"
    ],
    "wof:name":"Ethel Austin",
    "wof:placetype":"venue"
},
  "geometry": {"coordinates":[-1.908605,53.86581],"type":"Point"}
}