{
  "type": "Feature",
  "properties": {
    "iso:country":"GB",
    "sg:address":"14 Nelson Road",
    "sg:city":"Bishops Stortford",
    "sg:classifiers":[
        {
            "category":"Retail",
            "subcategory":"Repair Shop",
            "type":"Services"
        }
    ],
    "sg:phone":"+44 1279 503836",
    "sg:postcode":"CM23 3LH",
    "sg:province":"Essex",
    "sg:tags":[
        "clocks",
        "watch"
    ],
    "wof:name":"P C Adam Watch & Clock Repairs",
    "wof:placetype":"venue"
},
  "geometry": {"coordinates":[0.16342,51.859039],"type":"Point"}
}