{
  "type": "Feature",
  "properties": {
    "iso:country":"GB",
    "sg:address":"190 Green Lane, Palmers Grn",
    "sg:city":"London",
    "sg:classifiers":[
        {
            "category":"Social Services",
            "subcategory":"Child Care",
            "type":"Services"
        },
        {
            "category":"Social Services",
            "subcategory":"Adult Care",
            "type":"Services"
        },
        {
            "category":"Government",
            "subcategory":"Office",
            "type":"Public Place"
        }
    ],
    "sg:phone":"+44 20 8886 5346",
    "sg:postcode":"N13 5UE",
    "sg:province":"Greater London",
    "sg:tags":[
        "local",
        "day",
        "centre"
    ],
    "wof:name":"Ruth Winston House",
    "wof:placetype":"venue"
},
  "geometry": {"coordinates":[-0.109297,51.616131],"type":"Point"}
}