{
  "type": "Feature",
  "properties": {
    "iso:country":"GB",
    "sg:address":"2 Woodside Walk, Woodside Road",
    "sg:city":"Amersham",
    "sg:classifiers":[
        {
            "category":"Professional",
            "subcategory":"Accounting & Tax Preparation",
            "type":"Services"
        }
    ],
    "sg:phone":"+44 1494 721656",
    "sg:postcode":"HP6 6AY",
    "sg:province":"Buckinghamshire",
    "sg:tags":[
        "accountant"
    ],
    "wof:name":"C D Nash Aca",
    "wof:placetype":"venue"
},
  "geometry": {"coordinates":[-0.5992410183,51.6844329834],"type":"Point"}
}