{
  "type": "Feature",
  "properties": {
    "iso:country":"GB",
    "sg:address":"37 Clifton Street",
    "sg:city":"Cardiff",
    "sg:classifiers":[
        {
            "category":"Food & Beverages",
            "subcategory":"Meat & Fish",
            "type":"Retail Goods"
        },
        {
            "category":"Food & Beverages",
            "subcategory":"Groceries & Convenience Stores",
            "type":"Retail Goods"
        }
    ],
    "sg:phone":"+44 29 2048 2303",
    "sg:postcode":"CF24 1LR",
    "sg:province":"Cardiff",
    "sg:tags":[
        "shop",
        "chip"
    ],
    "wof:name":"Clarks Fish Fryers",
    "wof:placetype":"venue"
},
  "geometry": {"coordinates":[-3.1573519707,51.4851608276],"type":"Point"}
}