{
  "type": "Feature",
  "properties": {
    "iso:country":"GB",
    "sg:address":"126 Penn Rd",
    "sg:city":"Wolverhampton",
    "sg:classifiers":[
        {
            "category":"Travel",
            "subcategory":"Hotels & Motels",
            "type":"Entertainment"
        }
    ],
    "sg:phone":"+44 1902 429216",
    "sg:postcode":"WV3 0ER",
    "sg:province":"Staffordshire",
    "wof:name":"Quality Hotel Wolverhampton",
    "wof:placetype":"venue"
},
  "geometry": {"coordinates":[-2.137354,52.574413],"type":"Point"}
}