{
  "type": "Feature",
  "properties": {
    "addr:full":"5 Upper Wimpole Street London Greater London W1G 6HQ",
    "addr:housenumber":"5",
    "addr:postcode":"w1g 6hq",
    "addr:street":"Upper Wimpole Street",
    "iso:country":"GB",
    "sg:address":"5 Upper Wimpole Street",
    "sg:city":"London",
    "sg:classifiers":[
        {
            "category":"Professional",
            "subcategory":"Lawyer & Legal Services",
            "type":"Services"
        }
    ],
    "sg:postcode":"W1G 6HQ",
    "sg:province":"Greater London",
    "sg:tags":[
        "solicitor"
    ],
    "wof:name":"Southcombe & Hayley",
    "wof:placetype":"venue"
},
  "geometry": {"coordinates":[-0.1491210014,51.5206718445],"type":"Point"}
}