{
  "type": "Feature",
  "properties": {
    "iso:country":"GB",
    "sg:address":"8 Elmwood Close, Balsall Common",
    "sg:city":"Coventry",
    "sg:classifiers":[
        {
            "category":"Home & Garden",
            "subcategory":"Home Furnishings",
            "type":"Retail Goods"
        }
    ],
    "sg:postcode":"CV7 7DP",
    "sg:province":"Warwickshire",
    "sg:tags":[
        "furnishers",
        "planner",
        "kitchen"
    ],
    "wof:name":"Intex",
    "wof:placetype":"venue"
},
  "geometry": {"coordinates":[-1.648662,52.390156],"type":"Point"}
}