{
  "type": "Feature",
  "properties": {
    "addr:full":"137 Victoria St Blackburn Lancashire BB1 6DS",
    "addr:housenumber":"137",
    "addr:postcode":"bb1 6ds",
    "addr:street":"Victoria St",
    "iso:country":"GB",
    "sg:address":"137 Victoria St",
    "sg:city":"Blackburn",
    "sg:classifiers":[
        {
            "category":"Organizations",
            "subcategory":"Non-profit Organization",
            "type":"Services"
        }
    ],
    "sg:postcode":"BB1 6DS",
    "sg:province":"Lancashire",
    "sg:tags":[
        "organisation",
        "voluntary",
        "charity"
    ],
    "wof:name":"Pakistan Welfare Association",
    "wof:placetype":"venue"
},
  "geometry": {"coordinates":[-2.4823789597,53.7519111633],"type":"Point"}
}