{
  "type": "Feature",
  "properties": {
    "iso:country":"GB",
    "sg:address":"Lauder Road",
    "sg:city":"Dalkeith",
    "sg:classifiers":[
        {
            "category":"Education",
            "subcategory":"School",
            "type":"Public Place"
        },
        {
            "category":"Government",
            "subcategory":"Office",
            "type":"Public Place"
        }
    ],
    "sg:phone":"+44 131 663 2002",
    "sg:postcode":"EH22 2PU",
    "sg:province":"City of Edinburgh",
    "sg:tags":[
        "local",
        "authority"
    ],
    "wof:name":"St. David's R C Primary School",
    "wof:placetype":"venue"
},
  "geometry": {"coordinates":[-3.055539,55.890308],"type":"Point"}
}