{
  "type": "Feature",
  "properties": {
    "iso:country":"GB",
    "sg:address":"Healing Road, Stallingborough",
    "sg:city":"Grimsby",
    "sg:classifiers":[
        {
            "category":"Autos & Motor Vehicles",
            "subcategory":"Automobile Sales",
            "type":"Retail Goods"
        }
    ],
    "sg:phone":"+44 1472 885785",
    "sg:postcode":"DN41 8BJ",
    "sg:province":"Lincolnshire",
    "sg:tags":[
        "car"
    ],
    "wof:name":"Stallingborough Car Centre Ltd.",
    "wof:placetype":"venue"
},
  "geometry": {"coordinates":[-0.188119,53.585716],"type":"Point"}
}