{
  "type": "Feature",
  "properties": {
    "iso:country":"GB",
    "sg:address":"St Peter Street",
    "sg:city":"Maidstone",
    "sg:classifiers":[
        {
            "category":"Home & Garden",
            "subcategory":"Household Appliances",
            "type":"Retail Goods"
        },
        {
            "category":"Home & Garden",
            "subcategory":"Furniture",
            "type":"Retail Goods"
        }
    ],
    "sg:phone":"+44 1622 695981",
    "sg:postcode":"ME16 0SU",
    "sg:province":"Kent",
    "sg:tags":[
        "electrical",
        "domestic"
    ],
    "wof:name":"Courts Electrical",
    "wof:placetype":"venue"
},
  "geometry": {"coordinates":[0.5136150122,51.2772789001],"type":"Point"}
}