{
  "type": "Feature",
  "properties": {
    "iso:country":"GB",
    "sg:address":"Clerkenleap Barn, Broomhall",
    "sg:city":"Worcester",
    "sg:classifiers":[
        {
            "category":"Government",
            "subcategory":"Office",
            "type":"Public Place"
        }
    ],
    "sg:phone":"+44 870 240 1319",
    "sg:postcode":"WR5 3HR",
    "sg:province":"Worcestershire",
    "sg:tags":[
        "central"
    ],
    "wof:name":"Dvla",
    "wof:placetype":"venue"
},
  "geometry": {"coordinates":[-2.214396,52.16711],"type":"Point"}
}