{
  "type": "Feature",
  "properties": {
    "addr:full":"The Forge, Wickmere Norwich Norfolk NR11 7NA",
    "addr:postcode":"nr11 7na",
    "addr:street":"Norwich",
    "iso:country":"GB",
    "sg:address":"The Forge, Wickmere",
    "sg:city":"Norwich",
    "sg:classifiers":[
        {
            "category":"Manufacturing",
            "subcategory":"Metals",
            "type":"Manufacturing & Wholesale Goods"
        }
    ],
    "sg:phone":"+44 1263 768807",
    "sg:postcode":"NR11 7NA",
    "sg:province":"Norfolk",
    "sg:tags":[
        "steel",
        "fabricator",
        "merchant"
    ],
    "wof:name":"WORLD METAL TRADING LTD",
    "wof:placetype":"venue"
},
  "geometry": {"coordinates":[1.2261179686,52.8539581299],"type":"Point"}
}