{
  "type": "Feature",
  "properties": {
    "addr:full":"16 Didcot Rd Poole Dorset BH17 0GD",
    "addr:housenumber":"16",
    "addr:postcode":"bh17 0gd",
    "addr:street":"Didcot Rd",
    "iso:country":"GB",
    "sg:address":"16 Didcot Rd",
    "sg:city":"Poole",
    "sg:classifiers":[
        {
            "category":"Government",
            "subcategory":"Post Office",
            "type":"Public Place"
        }
    ],
    "sg:phone":"+44 1202 672304",
    "sg:postcode":"BH17 0GD",
    "sg:province":"Dorset",
    "sg:tags":[
        "print",
        "typesetter"
    ],
    "wof:name":"Get Set Graphics",
    "wof:placetype":"venue"
},
  "geometry": {"coordinates":[-1.9779969454,50.7407836914],"type":"Point"}
}