{
  "type": "Feature",
  "properties": {
    "iso:country":"GB",
    "sg:address":"Trostrey Court Farm, Trostrey",
    "sg:city":"Usk",
    "sg:classifiers":[
        {
            "category":"Building & Trades",
            "subcategory":"Construction",
            "type":"Services"
        }
    ],
    "sg:phone":"+44 1873 880809",
    "sg:postcode":"NP15 1HT",
    "sg:province":"Monmouthshire",
    "sg:tags":[
        "roofing"
    ],
    "wof:name":"Complete Roofing Company",
    "wof:placetype":"venue"
},
  "geometry": {"coordinates":[-2.902849,51.703735],"type":"Point"}
}