{
  "type": "Feature",
  "properties": {
    "addr:full":"The Warehouse, Beech Road Benfleet Essex SS7 2AZ",
    "addr:postcode":"ss7 2az",
    "addr:street":"Beech Road",
    "iso:country":"GB",
    "sg:address":"The Warehouse, Beech Road",
    "sg:city":"Benfleet",
    "sg:classifiers":[
        {
            "category":"Home & Garden",
            "subcategory":"Hardware",
            "type":"Retail Goods"
        }
    ],
    "sg:postcode":"SS7 2AZ",
    "sg:province":"Essex",
    "wof:name":"Risha Products (Hardware) Ltd.",
    "wof:placetype":"venue"
},
  "geometry": {"coordinates":[0.56264,51.543316],"type":"Point"}
}