{
  "type": "Feature",
  "properties": {
    "addr:full":"Kingston Park Centre, Newcastle Newcastle Upon Tyne Tyne and Wear NE3 2FP",
    "addr:postcode":"ne3 2fp",
    "addr:street":"Kingston Park",
    "iso:country":"GB",
    "sg:address":"Kingston Park Centre, Newcastle",
    "sg:city":"Newcastle Upon Tyne",
    "sg:classifiers":[
        {
            "category":"Bars & Pubs",
            "type":"Food & Drink"
        }
    ],
    "sg:phone":"+44 191 286 5054",
    "sg:postcode":"NE3 2FP",
    "sg:province":"Tyne and Wear",
    "sg:tags":[
        "pubs",
        "inn"
    ],
    "wof:name":"Kings Court",
    "wof:placetype":"venue"
},
  "geometry": {"coordinates":[-1.667394042,55.0130691528],"type":"Point"}
}