{
  "type": "Feature",
  "properties": {
    "addr:full":"Unit 4 Riverside Place, Paddock Holme Industrial Estate Kilbirnie North Ayrshire KA25 7EW",
    "addr:housenumber":"unit 4;estate",
    "addr:postcode":"ka25 7ew",
    "addr:street":"Riverside Place Paddock Holme Industrial",
    "iso:country":"GB",
    "sg:address":"Unit 4 Riverside Place, Paddock Holme Industrial Estate",
    "sg:city":"Kilbirnie",
    "sg:classifiers":[
        {
            "category":"Professional",
            "subcategory":"Engineering",
            "type":"Services"
        }
    ],
    "sg:postcode":"KA25 7EW",
    "sg:province":"North Ayrshire",
    "sg:tags":[
        "gas",
        "engineer"
    ],
    "wof:name":"Garnock Valley Services",
    "wof:placetype":"venue"
},
  "geometry": {"coordinates":[-4.6840720177,55.7513618469],"type":"Point"}
}