{
  "type": "Feature",
  "properties": {
    "addr:full":"Marlborough House, Silverdale Road Falmouth Cornwall TR11 4HW",
    "addr:postcode":"tr11 4hw",
    "addr:street":"Silverdale Road",
    "iso:country":"GB",
    "sg:address":"Marlborough House, Silverdale Road",
    "sg:city":"Falmouth",
    "sg:classifiers":[
        {
            "category":"Banks & Credit Unions",
            "subcategory":"Financial Services",
            "type":"Services"
        }
    ],
    "sg:postcode":"TR11 4HW",
    "sg:province":"Cornwall",
    "sg:tags":[
        "adviser"
    ],
    "wof:name":"Taylor Money",
    "wof:placetype":"venue"
},
  "geometry": {"coordinates":[-5.079729,50.145641],"type":"Point"}
}