{
  "type": "Feature",
  "properties": {
    "addr:full":"Classic House, 174-180 Old Street London Greater London EC1V 9BP",
    "addr:housenumber":"174-180",
    "addr:postcode":"ec1v 9bp",
    "addr:street":"Old Street",
    "iso:country":"GB",
    "sg:address":"Classic House, 174-180 Old Street",
    "sg:city":"London",
    "sg:classifiers":[
        {
            "category":"Real Estate",
            "subcategory":"Real Estate Agent",
            "type":"Services"
        }
    ],
    "sg:postcode":"EC1V 9BP",
    "sg:province":"Greater London",
    "wof:name":"David Jaffe Residential Lettings Limited",
    "wof:placetype":"venue"
},
  "geometry": {"coordinates":[-0.104557,51.498447],"type":"Point"}
}