{
  "type": "Feature",
  "properties": {
    "iso:country":"GB",
    "sg:address":"The Hay Loft, Nox Ho",
    "sg:city":"Shrewsbury",
    "sg:classifiers":[
        {
            "category":"Shopping",
            "subcategory":"Florist",
            "type":"Retail Goods"
        }
    ],
    "sg:phone":"+44 1743 821341",
    "sg:postcode":"SY5 8PU",
    "sg:province":"Shropshire",
    "wof:name":"Garden Interiors",
    "wof:placetype":"venue"
},
  "geometry": {"coordinates":[-2.87213,52.68803],"type":"Point"}
}