{
  "type": "Feature",
  "properties": {
    "addr:full":"201 Bellgrove Road Welling Kent DA16 3RA",
    "addr:housenumber":"201",
    "addr:postcode":"da16 3ra",
    "addr:street":"Bellgrove Road",
    "iso:country":"GB",
    "sg:address":"201 Bellgrove Road",
    "sg:city":"Welling",
    "sg:classifiers":[
        {
            "category":"Health Services",
            "subcategory":"Dentist",
            "type":"Services"
        }
    ],
    "sg:postcode":"DA16 3RA",
    "sg:province":"Kent",
    "wof:name":"Carl Bains",
    "wof:placetype":"venue"
},
  "geometry": {"coordinates":[0.1117099971,51.4620018005],"type":"Point"}
}