{
  "type": "Feature",
  "properties": {
    "addr:full":"4 Cathedral Road Cardiff Cardiff CF11 9LJ",
    "addr:housenumber":"4",
    "addr:postcode":"cf11 9lj",
    "addr:street":"Cathedral Road",
    "iso:country":"GB",
    "sg:address":"4 Cathedral Road",
    "sg:city":"Cardiff",
    "sg:classifiers":[
        {
            "category":"Shopping",
            "subcategory":"Stationery & Office Supplies",
            "type":"Retail Goods"
        },
        {
            "category":"Education",
            "subcategory":"University",
            "type":"Public Place"
        }
    ],
    "sg:phone":"+44 29 2037 4333",
    "sg:postcode":"CF11 9LJ",
    "sg:province":"Cardiff",
    "sg:tags":[
        "equipment",
        "educational",
        "school"
    ],
    "wof:name":"Consortium Cymru",
    "wof:placetype":"venue"
},
  "geometry": {"coordinates":[-3.189211,51.481991],"type":"Point"}
}