{
  "type": "Feature",
  "properties": {
    "addr:full":"45 Gordon Rd Aldershot Hampshire GU11 1ND",
    "addr:housenumber":"45",
    "addr:postcode":"gu11 1nd",
    "addr:street":"Gordon Rd",
    "iso:country":"GB",
    "sg:address":"45 Gordon Rd",
    "sg:city":"Aldershot",
    "sg:classifiers":[
        {
            "category":"Health Services",
            "subcategory":"Doctor",
            "type":"Services"
        },
        {
            "category":"Health Services",
            "subcategory":"Health Practitioner",
            "type":"Services"
        }
    ],
    "sg:phone":"+44 1252 322419",
    "sg:postcode":"GU11 1ND",
    "sg:province":"Hampshire",
    "sg:tags":[
        "osteopath"
    ],
    "wof:name":"Christine Clements",
    "wof:placetype":"venue"
},
  "geometry": {"coordinates":[-0.7637619972,51.2464904785],"type":"Point"}
}