{
  "type": "Feature",
  "properties": {
    "addr:full":"93 Berrow Rd Burnham On Sea Somerset TA8 2NY",
    "addr:housenumber":"93",
    "addr:postcode":"ta8 2ny",
    "addr:street":"Berrow Rd",
    "iso:country":"GB",
    "sg:address":"93 Berrow Rd",
    "sg:city":"Burnham On Sea",
    "sg:classifiers":[
        {
            "category":"Education",
            "subcategory":"School",
            "type":"Public Place"
        }
    ],
    "sg:phone":"+44 1278 782234",
    "sg:postcode":"TA8 2NY",
    "sg:province":"Somerset",
    "sg:tags":[
        "independent",
        "preparatory"
    ],
    "wof:name":"St Christopher's School",
    "wof:placetype":"venue"
},
  "geometry": {"coordinates":[-2.99852705,51.2509040833],"type":"Point"}
}