{
  "type": "Feature",
  "properties": {
    "iso:country":"GB",
    "sg:address":"Teviot Terrace",
    "sg:city":"Johnstone",
    "sg:classifiers":[
        {
            "category":"Education",
            "subcategory":"School",
            "type":"Public Place"
        }
    ],
    "sg:phone":"+44 1505 702153",
    "sg:postcode":"PA5 0NP",
    "sg:province":"Renfrewshire",
    "sg:tags":[
        "local",
        "authority"
    ],
    "wof:name":"Fordbank Primary School",
    "wof:placetype":"venue"
},
  "geometry": {"coordinates":[-4.532186985,55.8238487244],"type":"Point"}
}