{
  "type": "Feature",
  "properties": {
    "addr:full":"1 Burns Avenue South Houghton Le Spring Durham DH5 8HD",
    "addr:housenumber":"1",
    "addr:postcode":"dh5 8hd",
    "addr:street":"Burns Avenue South;Spring",
    "iso:country":"GB",
    "sg:address":"1 Burns Avenue South",
    "sg:city":"Houghton Le Spring",
    "sg:classifiers":[
        {
            "category":"Food & Beverages",
            "subcategory":"Liquor & Beverages",
            "type":"Retail Goods"
        }
    ],
    "sg:phone":"+44 191 584 1469",
    "sg:postcode":"DH5 8HD",
    "sg:province":"Durham",
    "sg:tags":[
        "beer",
        "spirit",
        "wines"
    ],
    "wof:name":"S & E A Bowden",
    "wof:placetype":"venue"
},
  "geometry": {"coordinates":[-1.464435,54.838741],"type":"Point"}
}