{
  "type": "Feature",
  "properties": {
    "addr:full":"29 St Dunstans Road Feltham Greater London TW13 4JY",
    "addr:housenumber":"29",
    "addr:postcode":"tw13 4jy",
    "addr:street":"St Dunstans Road",
    "iso:country":"GB",
    "sg:address":"29 St Dunstans Road",
    "sg:city":"Feltham",
    "sg:classifiers":[
        {
            "category":"Retail",
            "subcategory":"Auto Repair",
            "type":"Services"
        }
    ],
    "sg:phone":"+44 20 8890 7820",
    "sg:postcode":"TW13 4JY",
    "sg:province":"Greater London",
    "sg:tags":[
        "body",
        "car",
        "repairer"
    ],
    "wof:name":"S S Coachworks",
    "wof:placetype":"venue"
},
  "geometry": {"coordinates":[-0.420357,51.439468],"type":"Point"}
}