{
  "type": "Feature",
  "properties": {
    "iso:country":"GB",
    "sg:address":"Bridleway, The Green",
    "sg:city":"King's Lynn",
    "sg:classifiers":[
        {
            "category":"Communications",
            "type":"Services"
        }
    ],
    "sg:postcode":"PE33 0RB",
    "sg:province":"Norfolk",
    "sg:tags":[
        "data",
        "network"
    ],
    "wof:name":"Teonik Products",
    "wof:placetype":"venue"
},
  "geometry": {"coordinates":[0.4367800057,52.7147407532],"type":"Point"}
}