{
  "type": "Feature",
  "properties": {
    "iso:country":"GB",
    "sg:address":"95 Whitchurch Road",
    "sg:city":"Cardiff",
    "sg:classifiers":[
        {
            "category":"Utilities",
            "subcategory":"Fuel Oil & Lpg",
            "type":"Services"
        }
    ],
    "sg:phone":"+44 1829 260438",
    "sg:postcode":"CF14 3JP",
    "sg:province":"Cardiff",
    "wof:name":"L D Ltd",
    "wof:placetype":"venue"
},
  "geometry": {"coordinates":[-3.191931,51.503193],"type":"Point"}
}