{
  "type": "Feature",
  "properties": {
    "iso:country":"GB",
    "sg:address":"4 Back Riggs",
    "sg:city":"Morpeth",
    "sg:classifiers":[
        {
            "category":"Government",
            "subcategory":"Office",
            "type":"Public Place"
        }
    ],
    "sg:postcode":"NE61 1NU",
    "sg:province":"Northumberland",
    "sg:tags":[
        "inland",
        "revenue"
    ],
    "wof:name":"Board of Inland Revenue",
    "wof:placetype":"venue"
},
  "geometry": {"coordinates":[-1.6880379915,55.1682052612],"type":"Point"}
}