{
  "type": "Feature",
  "properties": {
    "iso:country":"GB",
    "sg:address":"Alston House, White Cross Industrial Estate, South Road",
    "sg:city":"Lancaster",
    "sg:classifiers":[
        {
            "category":"Communications",
            "type":"Services"
        }
    ],
    "sg:phone":"+44 1524 849010",
    "sg:postcode":"LA1 4XQ",
    "sg:province":"Lancashire",
    "sg:tags":[
        "audio-visual"
    ],
    "wof:name":"Axis Creative Communication Ltd.",
    "wof:placetype":"venue"
},
  "geometry": {"coordinates":[-2.799029,54.044537],"type":"Point"}
}