{
  "type": "Feature",
  "properties": {
    "addr:full":"1a Perseverance Road Hereford Herefordshire HR4 9SN",
    "addr:housenumber":"1a",
    "addr:postcode":"hr4 9sn",
    "addr:street":"Perseverance Road",
    "iso:country":"GB",
    "sg:address":"1a Perseverance Road",
    "sg:city":"Hereford",
    "sg:classifiers":[
        {
            "category":"Retail",
            "subcategory":"Auto Repair",
            "type":"Services"
        }
    ],
    "sg:phone":"+44 1432 355354",
    "sg:postcode":"HR4 9SN",
    "sg:province":"Herefordshire",
    "sg:tags":[
        "modification",
        "garage"
    ],
    "wof:name":"Alan Williams & David Stringer",
    "wof:placetype":"venue"
},
  "geometry": {"coordinates":[-2.7183389664,52.0676383972],"type":"Point"}
}