{
  "type": "Feature",
  "properties": {
    "iso:country":"GB",
    "sg:address":"Lowfields Business Park",
    "sg:city":"Elland",
    "sg:classifiers":[
        {
            "category":"Building & Trades",
            "subcategory":"Plumbing",
            "type":"Services"
        }
    ],
    "sg:phone":"+44 1422 377367",
    "sg:postcode":"HX5 9DN",
    "sg:province":"West Yorkshire",
    "sg:tags":[
        "filtration",
        "system"
    ],
    "wof:name":"Prosep Filter Systems Ltd.",
    "wof:placetype":"venue"
},
  "geometry": {"coordinates":[-1.828322,53.692169],"type":"Point"}
}