{
  "type": "Feature",
  "properties": {
    "addr:full":"295-297 Rochdale Road Oldham Lancashire OL1 2HG",
    "addr:housenumber":"295-297",
    "addr:postcode":"ol1 2hg",
    "addr:street":"Rochdale Road",
    "iso:country":"GB",
    "sg:address":"295-297 Rochdale Road",
    "sg:city":"Oldham",
    "sg:classifiers":[
        {
            "category":"Health Services",
            "subcategory":"Dentist",
            "type":"Services"
        }
    ],
    "sg:phone":"+44 161 627 0004",
    "sg:postcode":"OL1 2HG",
    "sg:province":"Lancashire",
    "wof:name":"The Dental Surgery",
    "wof:placetype":"venue"
},
  "geometry": {"coordinates":[-2.1204710007,53.5500335693],"type":"Point"}
}