{
  "type": "Feature",
  "properties": {
    "addr:full":"53-55 Stockfield Road Birmingham West Midlands B27 6AR",
    "addr:housenumber":"53-55",
    "addr:postcode":"b27 6ar",
    "addr:street":"Stockfield Road",
    "iso:country":"GB",
    "sg:address":"53-55 Stockfield Road",
    "sg:city":"Birmingham",
    "sg:classifiers":[
        {
            "category":"Social Services",
            "subcategory":"Retirement Home",
            "type":"Services"
        }
    ],
    "sg:phone":"+44 121 764 4231",
    "sg:postcode":"B27 6AR",
    "sg:province":"West Midlands",
    "sg:tags":[
        "residential",
        "care"
    ],
    "wof:name":"Westbourne Care Home",
    "wof:placetype":"venue"
},
  "geometry": {"coordinates":[-1.829981,52.453754],"type":"Point"}
}