{
  "type": "Feature",
  "properties": {
    "addr:full":"Glenelg Huntly Road Aboyne Aberdeenshire AB34 5HE",
    "addr:postcode":"ab34 5he",
    "addr:street":"Huntly Road",
    "iso:country":"GB",
    "sg:address":"Glenelg Huntly Road",
    "sg:city":"Aboyne",
    "sg:classifiers":[
        {
            "category":"Organizations",
            "subcategory":"Membership Organization",
            "type":"Services"
        }
    ],
    "sg:phone":"+44 1339 887317",
    "sg:postcode":"AB34 5HE",
    "sg:province":"Aberdeenshire",
    "sg:tags":[
        "club"
    ],
    "wof:name":"Struan Project Management Ltd",
    "wof:placetype":"venue"
},
  "geometry": {"coordinates":[-2.7800590992,57.0761795044],"type":"Point"}
}