{
  "type": "Feature",
  "properties": {
    "addr:full":"Unit 2, Mount Road Burntwood Staffordshire WS7 0AJ",
    "addr:housenumber":"unit 2",
    "addr:postcode":"ws7 0aj",
    "addr:street":"Mount Road",
    "iso:country":"GB",
    "sg:address":"Unit 2, Mount Road",
    "sg:city":"Burntwood",
    "sg:classifiers":[
        {
            "category":"Professional",
            "subcategory":"Engineering",
            "type":"Services"
        }
    ],
    "sg:phone":"+44 1543 682202",
    "sg:postcode":"WS7 0AJ",
    "sg:province":"Staffordshire",
    "wof:name":"Pelican Anew Ltd.",
    "wof:placetype":"venue"
},
  "geometry": {"coordinates":[-1.918714,52.674889],"type":"Point"}
}