{
  "type": "Feature",
  "properties": {
    "addr:full":"Hereford Works, Hallcar Street Sheffield South Yorkshire S4 7JY",
    "addr:postcode":"s4 7jy",
    "addr:street":"Hallcar Street",
    "iso:country":"GB",
    "sg:address":"Hereford Works, Hallcar Street",
    "sg:city":"Sheffield",
    "sg:classifiers":[
        {
            "category":"Home & Garden",
            "subcategory":"Kitchen Supply",
            "type":"Retail Goods"
        }
    ],
    "sg:postcode":"S4 7JY",
    "sg:province":"South Yorkshire",
    "sg:tags":[
        "supplier",
        "cutlery"
    ],
    "wof:name":"Geo H Greensmith & Co.",
    "wof:placetype":"venue"
},
  "geometry": {"coordinates":[-1.4556000233,53.3929786682],"type":"Point"}
}