{
  "type": "Feature",
  "properties": {
    "addr:full":"Grenville Meadows, Grenville Rd Lostwithiel Cornwall PL22 0RA",
    "addr:postcode":"pl22 0ra",
    "addr:street":"Grenville Rd",
    "iso:country":"GB",
    "sg:address":"Grenville Meadows, Grenville Rd",
    "sg:city":"Lostwithiel",
    "sg:classifiers":[
        {
            "category":"Building & Trades",
            "subcategory":"Construction",
            "type":"Services"
        }
    ],
    "sg:phone":"+44 1208 872222",
    "sg:postcode":"PL22 0RA",
    "sg:province":"Cornwall",
    "sg:tags":[
        "builder"
    ],
    "wof:name":"Rosemullion Homes",
    "wof:placetype":"venue"
},
  "geometry": {"coordinates":[-4.669903,50.408272],"type":"Point"}
}