{
  "type": "Feature",
  "properties": {
    "addr:full":"The Old Kiln, Willow Chase High Wycombe Buckinghamshire HP15 7QP",
    "addr:postcode":"hp15 7qp",
    "addr:street":"Willow Chase",
    "iso:country":"GB",
    "sg:address":"The Old Kiln, Willow Chase",
    "sg:city":"High Wycombe",
    "sg:classifiers":[
        {
            "category":"Professional",
            "subcategory":"Printing & Photocopies",
            "type":"Services"
        }
    ],
    "sg:phone":"+44 1494 520851",
    "sg:postcode":"HP15 7QP",
    "sg:province":"Buckinghamshire",
    "sg:tags":[
        "printer"
    ],
    "wof:name":"Chiltern Print Services",
    "wof:placetype":"venue"
},
  "geometry": {"coordinates":[-0.710044,51.658989],"type":"Point"}
}