{
  "type": "Feature",
  "properties": {
    "addr:full":"2 Boswell St Bloomsbury Greater London WC1N 3BW",
    "addr:housenumber":"2",
    "addr:postcode":"wc1n 3bw",
    "addr:street":"Boswell St",
    "iso:country":"GB",
    "sg:address":"2 Boswell St",
    "sg:city":"Bloomsbury",
    "sg:classifiers":[
        {
            "category":"Personal",
            "subcategory":"Beauty Salon",
            "type":"Services"
        }
    ],
    "sg:phone":"+44 20 7404 9280",
    "sg:postcode":"WC1N 3BW",
    "sg:province":"Greater London",
    "wof:name":"Treatment Rooms The",
    "wof:placetype":"venue"
},
  "geometry": {"coordinates":[-0.1209269986,51.5207061768],"type":"Point"}
}