{
  "type": "Feature",
  "properties": {
    "addr:full":"10 Feckenham Road Astwood Bank Redditch Warwickshire B96 6DS",
    "addr:housenumber":"10",
    "addr:postcode":"b96 6ds",
    "addr:street":"Feckenham Road",
    "iso:country":"GB",
    "sg:address":"10 Feckenham Road Astwood Bank",
    "sg:city":"Redditch",
    "sg:classifiers":[
        {
            "category":"Professional",
            "subcategory":"Detective & Security Services",
            "type":"Services"
        }
    ],
    "sg:phone":"+44 1527 894123",
    "sg:postcode":"B96 6DS",
    "sg:province":"Warwickshire",
    "sg:tags":[
        "equipment",
        "installers"
    ],
    "wof:name":"Executive Security",
    "wof:placetype":"venue"
},
  "geometry": {"coordinates":[-1.93885,52.260323],"type":"Point"}
}