{
  "type": "Feature",
  "properties": {
    "addr:full":"23 Parbrook Close Manchester Greater Manchester M40 8GL",
    "addr:housenumber":"23",
    "addr:postcode":"m40 8gl",
    "addr:street":"Parbrook Close",
    "iso:country":"GB",
    "sg:address":"23 Parbrook Close",
    "sg:city":"Manchester",
    "sg:classifiers":[
        {
            "category":"Professional",
            "subcategory":"Computer Services",
            "type":"Services"
        }
    ],
    "sg:phone":"+44 161 236 7222",
    "sg:postcode":"M40 8GL",
    "sg:province":"Greater Manchester",
    "sg:tags":[
        "information"
    ],
    "wof:name":"Monsall Access Project",
    "wof:placetype":"venue"
},
  "geometry": {"coordinates":[-2.2117040157,53.4963035583],"type":"Point"}
}