{
  "type": "Feature",
  "properties": {
    "addr:full":"171 Richmond Park Road Bournemouth Dorset BH8 8UB",
    "addr:housenumber":"171",
    "addr:postcode":"bh8 8ub",
    "addr:street":"Richmond Park Road",
    "iso:country":"GB",
    "sg:address":"171 Richmond Park Road",
    "sg:city":"Bournemouth",
    "sg:classifiers":[
        {
            "category":"Professional",
            "subcategory":"Engineering",
            "type":"Services"
        }
    ],
    "sg:phone":"+44 1202 523499",
    "sg:postcode":"BH8 8UB",
    "sg:province":"Dorset",
    "sg:tags":[
        "contractor",
        "electrical",
        "engineer"
    ],
    "wof:name":"Brown's Electrical Contractors",
    "wof:placetype":"venue"
},
  "geometry": {"coordinates":[-1.862129,50.736664],"type":"Point"}
}