{
  "type": "Feature",
  "properties": {
    "addr:full":"9 Meridian Gro Horley Surrey RH6 9XF",
    "addr:housenumber":"9",
    "addr:postcode":"rh6 9xf",
    "addr:street":"Meridian Gro Horley",
    "iso:country":"GB",
    "sg:address":"9 Meridian Gro",
    "sg:city":"Horley",
    "sg:classifiers":[
        {
            "category":"Building & Trades",
            "subcategory":"Construction",
            "type":"Services"
        }
    ],
    "sg:postcode":"RH6 9XF",
    "sg:province":"Surrey",
    "sg:tags":[
        "decorator",
        "painter"
    ],
    "wof:name":"Woodhams,Greg,",
    "wof:placetype":"venue"
},
  "geometry": {"coordinates":[-0.151299,51.177975],"type":"Point"}
}