{
  "type": "Feature",
  "properties": {
    "addr:full":"Manvers Street Trowbridge Wiltshire BA14 8EH",
    "addr:postcode":"ba14 8eh",
    "addr:street":"Manvers Street",
    "iso:country":"GB",
    "sg:address":"Manvers Street",
    "sg:city":"Trowbridge",
    "sg:classifiers":[
        {
            "category":"Home & Garden",
            "subcategory":"Carpets & Floor Coverings",
            "type":"Retail Goods"
        }
    ],
    "sg:postcode":"BA14 8EH",
    "sg:province":"Wiltshire",
    "sg:tags":[
        "carpets",
        "rug",
        "matting"
    ],
    "wof:name":"Trowbridge Discount Carpets",
    "wof:placetype":"venue"
},
  "geometry": {"coordinates":[-2.209172,51.321751],"type":"Point"}
}