{
  "type": "Feature",
  "properties": {
    "addr:full":"6 Lime Avenue Buckingham Buckinghamshire MK18 7JJ",
    "addr:housenumber":"6",
    "addr:postcode":"mk18 7jj",
    "addr:street":"Lime Avenue",
    "iso:country":"GB",
    "sg:address":"6 Lime Avenue",
    "sg:city":"Buckingham",
    "sg:classifiers":[
        {
            "category":"Professional",
            "subcategory":"Computer Services",
            "type":"Services"
        }
    ],
    "sg:phone":"+44 1280 823382",
    "sg:postcode":"MK18 7JJ",
    "sg:province":"Buckinghamshire",
    "sg:tags":[
        "system",
        "software"
    ],
    "wof:name":"Accolade Systems",
    "wof:placetype":"venue"
},
  "geometry": {"coordinates":[-0.9711620212,51.9919509888],"type":"Point"}
}