{
  "type": "Feature",
  "properties": {
    "addr:full":"39 Greenfield Close Dunstable Bedfordshire LU6 1TS",
    "addr:housenumber":"39",
    "addr:postcode":"lu6 1ts",
    "addr:street":"Greenfield Close",
    "iso:country":"GB",
    "sg:address":"39 Greenfield Close",
    "sg:city":"Dunstable",
    "sg:classifiers":[
        {
            "category":"Professional",
            "subcategory":"Printing & Photocopies",
            "type":"Services"
        }
    ],
    "sg:phone":"+44 1582 671160",
    "sg:postcode":"LU6 1TS",
    "sg:province":"Bedfordshire",
    "sg:tags":[
        "plate",
        "lithographic",
        "maker"
    ],
    "wof:name":"Ward Print Services",
    "wof:placetype":"venue"
},
  "geometry": {"coordinates":[-0.5450639725,51.8886985779],"type":"Point"}
}