{
  "type": "Feature",
  "properties": {
    "iso:country":"GB",
    "sg:address":"125 St Marys, Off King Edward Road",
    "sg:city":"Barking",
    "sg:classifiers":[
        {
            "category":"Shopping",
            "subcategory":"Pharmacy",
            "type":"Retail Goods"
        }
    ],
    "sg:phone":"+44 20 8594 6188",
    "sg:postcode":"IG11 7TF",
    "sg:province":"Essex",
    "sg:tags":[
        "pharmacist",
        "dispensing",
        "chemist"
    ],
    "wof:name":"Kalsi Pharmacy",
    "wof:placetype":"venue"
},
  "geometry": {"coordinates":[0.0837159976,51.5317878723],"type":"Point"}
}