{
  "type": "Feature",
  "properties": {
    "iso:country":"GB",
    "sg:address":"84 Parkside Road, Bebington",
    "sg:city":"Wirral",
    "sg:classifiers":[
        {
            "category":"Sports & Exercise",
            "subcategory":"Sports Center",
            "type":"Entertainment"
        }
    ],
    "sg:phone":"+44 151 644 1611",
    "sg:postcode":"CH63 7NR",
    "sg:province":"Merseyside",
    "sg:tags":[
        "game",
        "combat"
    ],
    "wof:name":"S W A T Paintball Activities Ltd.",
    "wof:placetype":"venue"
},
  "geometry": {"coordinates":[-3.0035,53.354813],"type":"Point"}
}