{
  "type": "Feature",
  "properties": {
    "addr:full":"The Malt House Princes Risborough Buckinghamshire HP27 9AB",
    "addr:postcode":"hp27 9ab",
    "iso:country":"GB",
    "sg:address":"The Malt House",
    "sg:city":"Princes Risborough",
    "sg:classifiers":[
        {
            "category":"Shopping",
            "subcategory":"Stationery & Office Supplies",
            "type":"Retail Goods"
        }
    ],
    "sg:phone":"+44 1844 275588",
    "sg:postcode":"HP27 9AB",
    "sg:province":"Buckinghamshire",
    "sg:tags":[
        "printers'"
    ],
    "wof:name":"Foto Graphics Ltd.",
    "wof:placetype":"venue"
},
  "geometry": {"coordinates":[-0.816004,51.738628],"type":"Point"}
}