{
  "type": "Feature",
  "properties": {
    "iso:country":"GB",
    "sg:address":"7 Kettering Terr, Mile End",
    "sg:city":"Portsmouth",
    "sg:classifiers":[
        {
            "category":"Professional",
            "type":"Services"
        }
    ],
    "sg:phone":"+44 23 9282 4210",
    "sg:postcode":"PO2 7AE",
    "sg:province":"Hampshire",
    "sg:tags":[
        "marine"
    ],
    "wof:name":"Dredgeco Ltd",
    "wof:placetype":"venue"
},
  "geometry": {"coordinates":[-1.0880680084,50.8096466064],"type":"Point"}
}