{
  "type": "Feature",
  "properties": {
    "addr:full":"65 Bold Street Liverpool Merseyside L1 4EZ",
    "addr:housenumber":"65",
    "addr:postcode":"l1 4ez",
    "addr:street":"Bold Street",
    "iso:country":"GB",
    "sg:address":"65 Bold Street",
    "sg:city":"Liverpool",
    "sg:classifiers":[
        {
            "category":"Food & Beverages",
            "subcategory":"Groceries & Convenience Stores",
            "type":"Retail Goods"
        }
    ],
    "sg:phone":"+44 151 707 8251",
    "sg:postcode":"L1 4EZ",
    "sg:province":"Merseyside",
    "wof:name":"Coopers Food Hall",
    "wof:placetype":"venue"
},
  "geometry": {"coordinates":[-2.9775381088,53.4029083252],"type":"Point"}
}