{
  "type": "Feature",
  "properties": {
    "addr:full":"10 Maddox Street London Greater London W1S 1PF",
    "addr:housenumber":"10",
    "addr:postcode":"w1s 1pf",
    "addr:street":"Maddox Street",
    "iso:country":"GB",
    "sg:address":"10 Maddox Street",
    "sg:city":"London",
    "sg:classifiers":[
        {
            "category":"Travel",
            "subcategory":"Travel Agent",
            "type":"Entertainment"
        }
    ],
    "sg:phone":"+44 20 7491 1866",
    "sg:postcode":"W1S 1PF",
    "sg:province":"Greater London",
    "wof:name":"Allison Brothers Ltd.",
    "wof:placetype":"venue"
},
  "geometry": {"coordinates":[-0.1417739987,51.5135536194],"type":"Point"}
}