{
  "type": "Feature",
  "properties": {
    "addr:full":"Hawksworth Road Didcot Oxfordshire OX11 7HR",
    "addr:postcode":"ox11 7hr",
    "addr:street":"Hawksworth Road",
    "iso:country":"GB",
    "sg:address":"Hawksworth Road",
    "sg:city":"Didcot",
    "sg:classifiers":[
        {
            "category":"Wholesale",
            "subcategory":"Scrap",
            "type":"Manufacturing & Wholesale Goods"
        },
        {
            "category":"Manufacturing",
            "subcategory":"Food",
            "type":"Manufacturing & Wholesale Goods"
        }
    ],
    "sg:phone":"+44 1235 511611",
    "sg:postcode":"OX11 7HR",
    "sg:province":"Oxfordshire",
    "sg:tags":[
        "frozen",
        "distributor",
        "waste",
        "metal",
        "processor"
    ],
    "wof:name":"SALVESEN LOGISTICS LTD",
    "wof:placetype":"venue"
},
  "geometry": {"coordinates":[-1.251686,51.620495],"type":"Point"}
}