{
  "type": "Feature",
  "properties": {
    "iso:country":"GB",
    "sg:address":"21 Brachelston Street",
    "sg:city":"Greenock",
    "sg:classifiers":[
        {
            "category":"Health Services",
            "subcategory":"Nursing And Care Facility",
            "type":"Services"
        },
        {
            "category":"Social Services",
            "subcategory":"Retirement Home",
            "type":"Services"
        }
    ],
    "sg:phone":"+44 1475 720856",
    "sg:postcode":"PA16 9AE",
    "sg:province":"Inverclyde",
    "sg:tags":[
        "residential"
    ],
    "wof:name":"Caladh House Association",
    "wof:placetype":"venue"
},
  "geometry": {"coordinates":[-4.774031,55.945675],"type":"Point"}
}