{
  "type": "Feature",
  "properties": {
    "iso:country":"GB",
    "sg:address":"11 Clarendon Street",
    "sg:city":"Nottingham",
    "sg:classifiers":[
        {
            "category":"Banks & Credit Unions",
            "subcategory":"Financial Services",
            "type":"Services"
        }
    ],
    "sg:phone":"+44 115 988 6300",
    "sg:postcode":"NG1 5HR",
    "sg:province":"Nottinghamshire",
    "sg:tags":[
        "adviser"
    ],
    "wof:name":"Russell Ulyatt Financial Services Ltd.",
    "wof:placetype":"venue"
},
  "geometry": {"coordinates":[-1.157302,52.956673],"type":"Point"}
}