{
  "type": "Feature",
  "properties": {
    "addr:full":"24 Grafton Rd Worthing West Sussex BN11 1QP",
    "addr:housenumber":"24",
    "addr:postcode":"bn11 1qp",
    "addr:street":"Grafton Rd",
    "iso:country":"GB",
    "sg:address":"24 Grafton Rd",
    "sg:city":"Worthing",
    "sg:classifiers":[
        {
            "category":"Professional",
            "subcategory":"Lawyer & Legal Services",
            "type":"Services"
        }
    ],
    "sg:phone":"+44 1903 823559",
    "sg:postcode":"BN11 1QP",
    "sg:province":"West Sussex",
    "sg:tags":[
        "advice",
        "counselling"
    ],
    "wof:name":"Sussex Alcohol Advice Service",
    "wof:placetype":"venue"
},
  "geometry": {"coordinates":[-0.373593986,50.8113288879],"type":"Point"}
}