{
  "type": "Feature",
  "properties": {
    "addr:full":"10 Swanpool Ct Lincoln Lincolnshire LN5 7AN",
    "addr:housenumber":"10",
    "addr:postcode":"ln5 7an",
    "addr:street":"Swanpool Ct",
    "iso:country":"GB",
    "sg:address":"10 Swanpool Ct",
    "sg:city":"Lincoln",
    "sg:classifiers":[
        {
            "category":"Personal",
            "subcategory":"Beauty Salon",
            "type":"Services"
        }
    ],
    "sg:postcode":"LN5 7AN",
    "sg:province":"Lincolnshire",
    "sg:tags":[
        "unisex",
        "hairdresser"
    ],
    "wof:name":"Ugly Ducklings",
    "wof:placetype":"venue"
},
  "geometry": {"coordinates":[-0.541354,53.227261],"type":"Point"}
}