{
  "type": "Feature",
  "properties": {
    "addr:full":"9 The Parade, Willowhayne Crescent Littlehampton West Sussex BN16 1NS",
    "addr:housenumber":"9",
    "addr:postcode":"bn16 1ns",
    "addr:street":"The Parade Willowhayne Crescent",
    "iso:country":"GB",
    "sg:address":"9 The Parade, Willowhayne Crescent",
    "sg:city":"Littlehampton",
    "sg:classifiers":[
        {
            "category":"Fast Food",
            "type":"Food & Drink"
        }
    ],
    "sg:postcode":"BN16 1NS",
    "sg:province":"West Sussex",
    "sg:tags":[
        "away",
        "take"
    ],
    "wof:name":"H Tog",
    "wof:placetype":"venue"
},
  "geometry": {"coordinates":[-0.4803580046,50.8052940369],"type":"Point"}
}