{
  "type": "Feature",
  "properties": {
    "addr:full":"3 Woodville Gardens, Sedgley Dudley Staffordshire DY3 1LB",
    "addr:housenumber":"3",
    "addr:postcode":"dy3 1lb",
    "addr:street":"Woodville Gardens",
    "iso:country":"GB",
    "sg:address":"3 Woodville Gardens, Sedgley",
    "sg:city":"Dudley",
    "sg:classifiers":[
        {
            "category":"Organizations",
            "subcategory":"Non-profit Organization",
            "type":"Services"
        }
    ],
    "sg:phone":"+44 1902 883675",
    "sg:postcode":"DY3 1LB",
    "sg:province":"Staffordshire",
    "sg:tags":[
        "organisation",
        "voluntary",
        "charity"
    ],
    "wof:name":"The Parkinsons Disease Society",
    "wof:placetype":"venue"
},
  "geometry": {"coordinates":[-2.1088550091,52.5440711975],"type":"Point"}
}