{
  "type": "Feature",
  "properties": {
    "iso:country":"GB",
    "sg:address":"220 Tower Bridge Road",
    "sg:city":"Southwark",
    "sg:classifiers":[
        {
            "category":"Professional",
            "subcategory":"Art Services",
            "type":"Services"
        }
    ],
    "sg:phone":"+44 800 026 5888",
    "sg:postcode":"SE1 2UP",
    "sg:province":"Greater London",
    "sg:tags":[
        "consultant",
        "design"
    ],
    "wof:name":"Condition Green Developments",
    "wof:placetype":"venue"
},
  "geometry": {"coordinates":[-0.076622,51.5033],"type":"Point"}
}