{
  "type": "Feature",
  "properties": {
    "addr:full":"Davidstowe Bodyworks Camelford Cornwall PL32 9YD",
    "addr:postcode":"pl32 9yd",
    "iso:country":"GB",
    "sg:address":"Davidstowe Bodyworks",
    "sg:city":"Camelford",
    "sg:classifiers":[
        {
            "category":"Farming",
            "subcategory":"Dairy Farm",
            "type":"Manufacturing & Wholesale Goods"
        }
    ],
    "sg:phone":"+44 1840 261494",
    "sg:postcode":"PL32 9YD",
    "sg:province":"Cornwall",
    "wof:name":"Mike Dickinson Dairy & Milking Supplies",
    "wof:placetype":"venue"
},
  "geometry": {"coordinates":[-4.678636,50.623116],"type":"Point"}
}