{
  "type": "Feature",
  "properties": {
    "iso:country":"GB",
    "sg:address":"125 Commercial Road",
    "sg:city":"London",
    "sg:classifiers":[
        {
            "category":"Wholesale",
            "subcategory":"Apparel",
            "type":"Manufacturing & Wholesale Goods"
        },
        {
            "category":"Wholesale",
            "subcategory":"Wine & Distilled Alcoholic Beverages",
            "type":"Manufacturing & Wholesale Goods"
        }
    ],
    "sg:phone":"+44 20 7247 7272",
    "sg:postcode":"E1 1RD",
    "sg:province":"Greater London",
    "sg:tags":[
        "w'sale",
        "lady",
        "fashionwear",
        "ladieswear"
    ],
    "wof:name":"Perfect Fashions Ltd",
    "wof:placetype":"venue"
},
  "geometry": {"coordinates":[-0.063049,51.514828],"type":"Point"}
}