{
  "type": "Feature",
  "properties": {
    "addr:full":"49 St Stephens Road, Selly Oak Birmingham West Midlands B29 7RR",
    "addr:housenumber":"49",
    "addr:postcode":"b29 7rr",
    "addr:street":"St Stephens Road",
    "iso:country":"GB",
    "sg:address":"49 St Stephens Road, Selly Oak",
    "sg:city":"Birmingham",
    "sg:classifiers":[
        {
            "category":"Retail",
            "subcategory":"Auto Repair",
            "type":"Services"
        }
    ],
    "sg:phone":"+44 121 472 1217",
    "sg:postcode":"B29 7RR",
    "sg:province":"West Midlands",
    "sg:tags":[
        "modification",
        "garage",
        "related"
    ],
    "wof:name":"Townsend Bros & Co",
    "wof:placetype":"venue"
},
  "geometry": {"coordinates":[-1.9202309847,52.4344902039],"type":"Point"}
}