{
  "type": "Feature",
  "properties": {
    "iso:country":"GB",
    "sg:address":"1 Southernhay West",
    "sg:city":"Exeter",
    "sg:classifiers":[
        {
            "category":"Professional",
            "subcategory":"Lawyer & Legal Services",
            "type":"Services"
        }
    ],
    "sg:postcode":"EX1 1JG",
    "sg:province":"Devon",
    "wof:name":"Rego Smith & Ferreira Advogados",
    "wof:placetype":"venue"
},
  "geometry": {"coordinates":[-3.527731,50.721558],"type":"Point"}
}