{
  "type": "Feature",
  "properties": {
    "iso:country":"GB",
    "sg:address":"Kinnaird Head Works, Bath Street",
    "sg:city":"Fraserburgh",
    "sg:classifiers":[
        {
            "category":"Manufacturing",
            "subcategory":"Food",
            "type":"Manufacturing & Wholesale Goods"
        },
        {
            "category":"Food & Beverages",
            "subcategory":"Supermarket",
            "type":"Retail Goods"
        }
    ],
    "sg:phone":"+44 1346 513191",
    "sg:postcode":"AB43 9DY",
    "sg:province":"Aberdeenshire",
    "sg:tags":[
        "frozen",
        "product",
        "manufacturer"
    ],
    "sg:website":"http://www.intfishcan.com",
    "wof:name":"International Fish Canners (Scotland) Ltd.",
    "wof:placetype":"venue"
},
  "geometry": {"coordinates":[-2.0158441067,57.6944198608],"type":"Point"}
}