{
  "type": "Feature",
  "properties": {
    "iso:country":"GB",
    "sg:address":"162 Sneinton Blvd",
    "sg:city":"Nottingham",
    "sg:classifiers":[
        {
            "category":"Personal",
            "subcategory":"Barber",
            "type":"Services"
        }
    ],
    "sg:postcode":"NG2 4FY",
    "sg:province":"Nottinghamshire",
    "sg:tags":[
        "men's",
        "hairdresser"
    ],
    "wof:name":"Sweeney Todd",
    "wof:placetype":"venue"
},
  "geometry": {"coordinates":[-1.12272,52.951752],"type":"Point"}
}