{
  "type": "Feature",
  "properties": {
    "addr:full":"67 Burton Rd Nottingham Nottinghamshire NG4 3DL",
    "addr:housenumber":"67",
    "addr:postcode":"ng4 3dl",
    "addr:street":"Burton Rd",
    "iso:country":"GB",
    "sg:address":"67 Burton Rd",
    "sg:city":"Nottingham",
    "sg:classifiers":[
        {
            "category":"Health Services",
            "subcategory":"Dentist",
            "type":"Services"
        }
    ],
    "sg:phone":"+44 115 961 9434",
    "sg:postcode":"NG4 3DL",
    "sg:province":"Nottinghamshire",
    "wof:name":"M J Shiekh",
    "wof:placetype":"venue"
},
  "geometry": {"coordinates":[-1.081016,52.968864],"type":"Point"}
}