{
  "type": "Feature",
  "properties": {
    "addr:full":"685 Field End Rd Ruislip Greater London HA4 0RG",
    "addr:housenumber":"685",
    "addr:postcode":"ha4 0rg",
    "addr:street":"Field End Rd",
    "iso:country":"GB",
    "sg:address":"685 Field End Rd",
    "sg:city":"Ruislip",
    "sg:classifiers":[
        {
            "category":"Professional",
            "subcategory":"Detective & Security Services",
            "type":"Services"
        }
    ],
    "sg:postcode":"HA4 0RG",
    "sg:province":"Greater London",
    "sg:tags":[
        "alarm",
        "burglar",
        "system"
    ],
    "wof:name":"Cooper,Stephen,",
    "wof:placetype":"venue"
},
  "geometry": {"coordinates":[-0.3823629916,51.5629768372],"type":"Point"}
}