{
  "type": "Feature",
  "properties": {
    "addr:full":"The Celtic House Port Ellen Argyll and Bute PA43 7LD",
    "addr:postcode":"pa43 7ld",
    "iso:country":"GB",
    "sg:address":"The Celtic House",
    "sg:city":"Port Ellen",
    "sg:classifiers":[
        {
            "category":"Shopping",
            "subcategory":"Department Store",
            "type":"Retail Goods"
        }
    ],
    "sg:postcode":"PA43 7LD",
    "sg:province":"Argyll and Bute",
    "wof:name":"C & E Roy",
    "wof:placetype":"venue"
},
  "geometry": {"coordinates":[-6.28806,55.75732],"type":"Point"}
}