{
  "type": "Feature",
  "properties": {
    "addr:full":"Railway Hotel, 38 Station Rd Edgware Greater London HA8 7AD",
    "addr:housenumber":"38",
    "addr:postcode":"ha8 7ad",
    "addr:street":"Station Rd",
    "iso:country":"GB",
    "sg:address":"Railway Hotel, 38 Station Rd",
    "sg:city":"Edgware",
    "sg:classifiers":[
        {
            "category":"Bars & Pubs",
            "type":"Food & Drink"
        }
    ],
    "sg:phone":"+44 20 8952 1560",
    "sg:postcode":"HA8 7AD",
    "sg:province":"Greater London",
    "sg:tags":[
        "pubs",
        "inn"
    ],
    "wof:name":"Country Carvery",
    "wof:placetype":"venue"
},
  "geometry": {"coordinates":[-0.277564,51.612083],"type":"Point"}
}