{
  "type": "Feature",
  "properties": {
    "addr:full":"7th Floor, The Rotunda, 150 New St Birmingham West Midlands B2 4PA",
    "addr:housenumber":"7th floor;150",
    "addr:postcode":"b2 4pa",
    "addr:street":"The Rotunda;New St",
    "iso:country":"GB",
    "sg:address":"7th Floor, The Rotunda, 150 New St",
    "sg:city":"Birmingham",
    "sg:classifiers":[
        {
            "category":"Professional",
            "subcategory":"Employment Agencies",
            "type":"Services"
        }
    ],
    "sg:phone":"+44 121 643 2721",
    "sg:postcode":"B2 4PA",
    "sg:province":"West Midlands",
    "sg:tags":[
        "consultant"
    ],
    "wof:name":"Griffin Commercial",
    "wof:placetype":"venue"
},
  "geometry": {"coordinates":[-1.90218,52.479351],"type":"Point"}
}