{
  "type": "Feature",
  "properties": {
    "iso:country":"GB",
    "sg:address":"Rear Of 33 Chorley Road",
    "sg:city":"Bolton",
    "sg:classifiers":[
        {
            "category":"Taxi",
            "type":"Transportation"
        }
    ],
    "sg:phone":"+44 1942 810401",
    "sg:postcode":"BL5 3PD",
    "sg:province":"Lancashire",
    "sg:tags":[
        "mini",
        "cab"
    ],
    "wof:name":"401 24 Hour Private Hire",
    "wof:placetype":"venue"
},
  "geometry": {"coordinates":[-2.5258100033,53.560798645],"type":"Point"}
}