{
  "type": "Feature",
  "properties": {
    "addr:full":"30 Chesthunte Road Tottenham Greater London N17 7PU",
    "addr:housenumber":"30",
    "addr:postcode":"n17 7pu",
    "addr:street":"Chesthunte Road",
    "iso:country":"GB",
    "sg:address":"30 Chesthunte Road",
    "sg:city":"Tottenham",
    "sg:classifiers":[
        {
            "category":"Professional",
            "subcategory":"Computer Services",
            "type":"Services"
        }
    ],
    "sg:phone":"+44 20 8885 1222",
    "sg:postcode":"N17 7PU",
    "sg:province":"Greater London",
    "sg:tags":[
        "system",
        "software"
    ],
    "wof:name":"Abg & Co",
    "wof:placetype":"venue"
},
  "geometry": {"coordinates":[-0.0900020003,51.5993728638],"type":"Point"}
}