{
  "type": "Feature",
  "properties": {
    "addr:full":"Unit 1 24-28 Queen Anne Road, St Phillip Bristol City of Bristol BS5 9TX",
    "addr:housenumber":"unit 1 24-28",
    "addr:postcode":"bs5 9tx",
    "addr:street":"Queen Anne Road St",
    "iso:country":"GB",
    "sg:address":"Unit 1 24-28 Queen Anne Road, St Phillip",
    "sg:city":"Bristol",
    "sg:classifiers":[
        {
            "category":"Freight",
            "type":"Transportation"
        }
    ],
    "sg:phone":"+44 117 941 4080",
    "sg:postcode":"BS5 9TX",
    "sg:province":"City of Bristol",
    "sg:tags":[
        "overseas",
        "shipping",
        "removal"
    ],
    "wof:name":"Beauvais Transport",
    "wof:placetype":"venue"
},
  "geometry": {"coordinates":[-2.567289,51.452179],"type":"Point"}
}