{
  "type": "Feature",
  "properties": {
    "addr:full":"29c London Road Croydon Surrey CR0 2RE",
    "addr:housenumber":"29c",
    "addr:postcode":"cr0 2re",
    "addr:street":"London Road",
    "iso:country":"GB",
    "sg:address":"29c London Road",
    "sg:city":"Croydon",
    "sg:classifiers":[
        {
            "category":"Shopping",
            "subcategory":"Catalog Store",
            "type":"Retail Goods"
        }
    ],
    "sg:phone":"+44 20 8688 0419",
    "sg:postcode":"CR0 2RE",
    "sg:province":"Surrey",
    "sg:tags":[
        "mail",
        "order"
    ],
    "wof:name":"Spellbound Records",
    "wof:placetype":"venue"
},
  "geometry": {"coordinates":[-0.1045309976,51.3797416687],"type":"Point"}
}