{
  "type": "Feature",
  "properties": {
    "addr:full":"73 Connaught Avenue Frinton On Sea Essex CO13 9PP",
    "addr:housenumber":"73",
    "addr:postcode":"co13 9pp",
    "addr:street":"Connaught Avenue",
    "iso:country":"GB",
    "sg:address":"73 Connaught Avenue",
    "sg:city":"Frinton On Sea",
    "sg:classifiers":[
        {
            "category":"Real Estate",
            "subcategory":"Real Estate Agent",
            "type":"Services"
        }
    ],
    "sg:phone":"+44 1255 851185",
    "sg:postcode":"CO13 9PP",
    "sg:province":"Essex",
    "wof:name":"Gordon Suckling",
    "wof:placetype":"venue"
},
  "geometry": {"coordinates":[1.2452379465,51.8317947388],"type":"Point"}
}