{
  "type": "Feature",
  "properties": {
    "iso:country":"GB",
    "sg:address":"Unit 3/5 Woodland Park Industria, L Estate, Shortthorn Road Stratton Strawl",
    "sg:city":"Norwich",
    "sg:classifiers":[
        {
            "category":"Manufacturing",
            "subcategory":"Glass & Minerals",
            "type":"Manufacturing & Wholesale Goods"
        }
    ],
    "sg:phone":"+44 1603 754845",
    "sg:postcode":"NR10 5NU",
    "sg:province":"Norfolk",
    "sg:tags":[
        "fibre",
        "moulding"
    ],
    "wof:name":"Alexander Developments",
    "wof:placetype":"venue"
},
  "geometry": {"coordinates":[1.2500699759,52.7283706665],"type":"Point"}
}