{
  "type": "Feature",
  "properties": {
    "addr:full":"52 New Road, Yeadon Leeds West Yorkshire LS19 7NA",
    "addr:housenumber":"52",
    "addr:postcode":"ls19 7na",
    "addr:street":"New Road",
    "iso:country":"GB",
    "sg:address":"52 New Road, Yeadon",
    "sg:city":"Leeds",
    "sg:classifiers":[
        {
            "category":"Shopping",
            "subcategory":"Musical Instruments",
            "type":"Retail Goods"
        }
    ],
    "sg:phone":"+44 113 250 3602",
    "sg:postcode":"LS19 7NA",
    "sg:province":"West Yorkshire",
    "wof:name":"Ian R Horner-Glister",
    "wof:placetype":"venue"
},
  "geometry": {"coordinates":[-1.695881,53.862999],"type":"Point"}
}