{
  "type": "Feature",
  "properties": {
    "addr:full":"64 Bradford Road, East Ardsley Wakefield West Yorkshire WF3 2EY",
    "addr:housenumber":"64",
    "addr:postcode":"wf3 2ey",
    "addr:street":"Bradford Road",
    "iso:country":"GB",
    "sg:address":"64 Bradford Road, East Ardsley",
    "sg:city":"Wakefield",
    "sg:classifiers":[
        {
            "category":"Banks & Credit Unions",
            "subcategory":"Financial Services",
            "type":"Services"
        }
    ],
    "sg:postcode":"WF3 2EY",
    "sg:province":"West Yorkshire",
    "sg:tags":[
        "consultant"
    ],
    "wof:name":"Paul Dodd",
    "wof:placetype":"venue"
},
  "geometry": {"coordinates":[-1.541323,53.721451],"type":"Point"}
}