{
  "type": "Feature",
  "properties": {
    "addr:full":"77 Whyke Lane Chichester West Sussex PO19 7PD",
    "addr:housenumber":"77",
    "addr:postcode":"po19 7pd",
    "addr:street":"Whyke Lane",
    "iso:country":"GB",
    "sg:address":"77 Whyke Lane",
    "sg:city":"Chichester",
    "sg:classifiers":[
        {
            "category":"Shopping",
            "subcategory":"Comic Books",
            "type":"Retail Goods"
        }
    ],
    "sg:phone":"+44 1243 783755",
    "sg:postcode":"PO19 7PD",
    "sg:province":"West Sussex",
    "sg:tags":[
        "jeweller"
    ],
    "wof:name":"D M J",
    "wof:placetype":"venue"
},
  "geometry": {"coordinates":[-0.769277,50.83226],"type":"Point"}
}