{
  "type": "Feature",
  "properties": {
    "iso:country":"GB",
    "sg:address":"49 The Rough, Newick",
    "sg:city":"Lewes",
    "sg:classifiers":[
        {
            "category":"Retail",
            "subcategory":"Repair Shop",
            "type":"Services"
        }
    ],
    "sg:postcode":"BN8 4NS",
    "sg:province":"East Sussex",
    "sg:tags":[
        "radio",
        "television",
        "video"
    ],
    "wof:name":"Ray Linton Tv & Video",
    "wof:placetype":"venue"
},
  "geometry": {"coordinates":[0.007405,50.972935],"type":"Point"}
}