{
  "type": "Feature",
  "properties": {
    "iso:country":"GB",
    "sg:address":"191 Archway Road",
    "sg:city":"London",
    "sg:classifiers":[
        {
            "category":"Shopping",
            "subcategory":"Computers & Home Electronics",
            "type":"Retail Goods"
        }
    ],
    "sg:phone":"+44 20 8341 7322",
    "sg:postcode":"N6 5BN",
    "sg:province":"Greater London",
    "wof:name":"Stocker Furniture",
    "wof:placetype":"venue"
},
  "geometry": {"coordinates":[-0.1415340006,51.573802948],"type":"Point"}
}