{
  "type": "Feature",
  "properties": {
    "iso:country":"GB",
    "sg:address":"68 Westhill",
    "sg:city":"Wandsworth",
    "sg:classifiers":[
        {
            "category":"Health Services",
            "subcategory":"Dentist",
            "type":"Services"
        }
    ],
    "sg:phone":"+44 20 8870 9616",
    "sg:postcode":"SW18 1RU",
    "sg:province":"Greater London",
    "wof:name":"Westhill Dental Centre",
    "wof:placetype":"venue"
},
  "geometry": {"coordinates":[-0.2005379945,51.4514541626],"type":"Point"}
}