{
  "type": "Feature",
  "properties": {
    "iso:country":"GB",
    "sg:address":"17 Larch Crescent",
    "sg:city":"Tonbridge",
    "sg:classifiers":[
        {
            "category":"Building & Trades",
            "subcategory":"Construction",
            "type":"Services"
        }
    ],
    "sg:phone":"+44 1732 350534",
    "sg:postcode":"TN10 3NN",
    "sg:province":"Kent",
    "sg:tags":[
        "builder"
    ],
    "wof:name":"Peter J Browning",
    "wof:placetype":"venue"
},
  "geometry": {"coordinates":[0.2815159857,51.2165603638],"type":"Point"}
}