{
  "type": "Feature",
  "properties": {
    "iso:country":"GB",
    "sg:address":"169 York Road, Haxby",
    "sg:city":"York",
    "sg:classifiers":[
        {
            "category":"Restaurant",
            "type":"Food & Drink"
        }
    ],
    "sg:postcode":"YO32 3HB",
    "sg:province":"North Yorkshire",
    "wof:name":"Haxby Court Hotel",
    "wof:placetype":"venue"
},
  "geometry": {"coordinates":[-1.073665,54.005581],"type":"Point"}
}