{
  "type": "Feature",
  "properties": {
    "addr:full":"Oakfield Industrial Estate, Eynsham Witney Oxfordshire OX29 4TS",
    "addr:housenumber":"estate",
    "addr:postcode":"ox29 4ts",
    "addr:street":"Industrial",
    "iso:country":"GB",
    "sg:address":"Oakfield Industrial Estate, Eynsham",
    "sg:city":"Witney",
    "sg:classifiers":[
        {
            "category":"Health Services",
            "subcategory":"Clinic",
            "type":"Services"
        }
    ],
    "sg:phone":"+44 1865 884234",
    "sg:postcode":"OX29 4TS",
    "sg:province":"Oxfordshire",
    "sg:tags":[
        "medical"
    ],
    "wof:name":"Suntech Medical Ltd.",
    "wof:placetype":"venue"
},
  "geometry": {"coordinates":[-1.3778389692,51.7730979919],"type":"Point"}
}