{
  "type": "Feature",
  "properties": {
    "addr:full":"29 Old Shoreham Road Shoreham-by-sea West Sussex BN43 5TA",
    "addr:housenumber":"29",
    "addr:postcode":"bn43 5ta",
    "addr:street":"Old Shoreham Road",
    "iso:country":"GB",
    "sg:address":"29 Old Shoreham Road",
    "sg:city":"Shoreham-by-sea",
    "sg:classifiers":[
        {
            "category":"Autos & Motor Vehicles",
            "subcategory":"Automobile Sales",
            "type":"Retail Goods"
        }
    ],
    "sg:phone":"+44 1273 464687",
    "sg:postcode":"BN43 5TA",
    "sg:province":"West Sussex",
    "sg:tags":[
        "car"
    ],
    "wof:name":"M & S Car Sales",
    "wof:placetype":"venue"
},
  "geometry": {"coordinates":[-0.2800459862,50.8346099854],"type":"Point"}
}