{
  "type": "Feature",
  "properties": {
    "iso:country":"GB",
    "sg:address":"8 The Lynxway",
    "sg:city":"Liverpool",
    "sg:classifiers":[
        {
            "category":"Professional",
            "subcategory":"Art Services",
            "type":"Services"
        }
    ],
    "sg:phone":"+44 151 228 7462",
    "sg:postcode":"L12 3HR",
    "sg:province":"Merseyside",
    "sg:tags":[
        "photographer"
    ],
    "wof:name":"Gemini Photography",
    "wof:placetype":"venue"
},
  "geometry": {"coordinates":[-2.8895471096,53.4210472107],"type":"Point"}
}