{
  "type": "Feature",
  "properties": {
    "addr:full":"Chell Heath Rd Stoke On Trent Staffordshire ST6 7LP",
    "addr:postcode":"st6 7lp",
    "addr:street":"Chell Heath Rd",
    "iso:country":"GB",
    "sg:address":"Chell Heath Rd",
    "sg:city":"Stoke On Trent",
    "sg:classifiers":[
        {
            "category":"Community Center",
            "type":"Public Place"
        }
    ],
    "sg:phone":"+44 1782 234618",
    "sg:postcode":"ST6 7LP",
    "sg:province":"Staffordshire",
    "sg:tags":[
        "centre"
    ],
    "wof:name":"Burnwood Youth & Adult Centre",
    "wof:placetype":"venue"
},
  "geometry": {"coordinates":[-2.1786088943,53.0634002686],"type":"Point"}
}