{
  "type": "Feature",
  "properties": {
    "iso:country":"GB",
    "sg:address":"Building 300 World Freight Terminal, Manchester Airport",
    "sg:city":"Manchester",
    "sg:classifiers":[
        {
            "category":"Professional",
            "type":"Services"
        },
        {
            "category":"Professional",
            "subcategory":"Business Services",
            "type":"Services"
        }
    ],
    "sg:phone":"+44 161 489 3266",
    "sg:postcode":"M90 5SA",
    "sg:province":"Greater Manchester",
    "sg:tags":[
        "import",
        "aircraft",
        "export",
        "maintenance",
        "agent"
    ],
    "wof:name":"Serviceair",
    "wof:placetype":"venue"
},
  "geometry": {"coordinates":[-2.28783,53.363098],"type":"Point"}
}