{
  "type": "Feature",
  "properties": {
    "iso:country":"GB",
    "sg:address":"11/41 Trafalgar Lane, Leith",
    "sg:city":"Edinburgh",
    "sg:classifiers":[
        {
            "category":"Building & Trades",
            "subcategory":"Construction",
            "type":"Services"
        }
    ],
    "sg:phone":"+44 131 553 4747",
    "sg:postcode":"EH6 4DQ",
    "sg:province":"City of Edinburgh",
    "sg:tags":[
        "roofing"
    ],
    "wof:name":"T & G Louden (Roofing) Ltd.",
    "wof:placetype":"venue"
},
  "geometry": {"coordinates":[-3.18393,55.974083],"type":"Point"}
}