{
  "type": "Feature",
  "properties": {
    "addr:full":"Unit 2 Mill Lane Newbury Berkshire RG14 5LE",
    "addr:housenumber":"unit 2",
    "addr:postcode":"rg14 5le",
    "addr:street":"Mill Lane",
    "iso:country":"GB",
    "sg:address":"Unit 2 Mill Lane",
    "sg:city":"Newbury",
    "sg:classifiers":[
        {
            "category":"Building & Trades",
            "subcategory":"Construction",
            "type":"Services"
        }
    ],
    "sg:phone":"+44 1635 551144",
    "sg:postcode":"RG14 5LE",
    "sg:province":"Berkshire",
    "sg:tags":[
        "builder"
    ],
    "wof:name":"Romar Construction (Newbury) Ltd.",
    "wof:placetype":"venue"
},
  "geometry": {"coordinates":[-1.3157609701,51.4010658264],"type":"Point"}
}