{
  "type": "Feature",
  "properties": {
    "iso:country":"GB",
    "sg:address":"Miles Gray Road",
    "sg:city":"Basildon",
    "sg:classifiers":[
        {
            "category":"Professional",
            "subcategory":"Printing & Photocopies",
            "type":"Services"
        }
    ],
    "sg:phone":"+44 1268 534444",
    "sg:postcode":"SS14 3AR",
    "sg:province":"Essex",
    "sg:tags":[
        "photocopier"
    ],
    "wof:name":"Konica Minolta Business Solutions (Uk) Ltd.",
    "wof:placetype":"venue"
},
  "geometry": {"coordinates":[0.455097,51.58643],"type":"Point"}
}