{
  "type": "Feature",
  "properties": {
    "addr:full":"Station Road, Bagworth Coalville Leicestershire LE67 1BH",
    "addr:postcode":"le67 1bh",
    "addr:street":"Station Road",
    "iso:country":"GB",
    "sg:address":"Station Road, Bagworth",
    "sg:city":"Coalville",
    "sg:classifiers":[
        {
            "category":"Home & Garden",
            "subcategory":"Building Materials",
            "type":"Retail Goods"
        }
    ],
    "sg:phone":"+44 1455 457414",
    "sg:postcode":"LE67 1BH",
    "sg:province":"Leicestershire",
    "sg:tags":[
        "shower",
        "unit"
    ],
    "wof:name":"C A Electrics",
    "wof:placetype":"venue"
},
  "geometry": {"coordinates":[-1.342431,52.672234],"type":"Point"}
}