{
  "type": "Feature",
  "properties": {
    "addr:full":"151-152 Maybury Road Woking Surrey GU21 5LJ",
    "addr:postcode":"151-152;gu21 5lj",
    "addr:street":"Maybury Road",
    "iso:country":"GB",
    "sg:address":"151-152 Maybury Road",
    "sg:city":"Woking",
    "sg:classifiers":[
        {
            "category":"Shopping",
            "subcategory":"Clothing, Apparel, & Fashions",
            "type":"Retail Goods"
        }
    ],
    "sg:phone":"+44 1483 757677",
    "sg:postcode":"GU21 5LJ",
    "sg:province":"Surrey",
    "sg:tags":[
        "sport",
        "clothing"
    ],
    "wof:name":"Mercian Sports Co. Ltd.",
    "wof:placetype":"venue"
},
  "geometry": {"coordinates":[-0.5429109931,51.3246841431],"type":"Point"}
}