{
  "type": "Feature",
  "properties": {
    "addr:full":"2 St Marys Square York North Yorkshire YO1 9WY",
    "addr:housenumber":"2",
    "addr:postcode":"yo1 9wy",
    "addr:street":"St Marys Square",
    "iso:country":"GB",
    "sg:address":"2 St Marys Square",
    "sg:city":"York",
    "sg:classifiers":[
        {
            "category":"Shopping",
            "subcategory":"Department Store",
            "type":"Retail Goods"
        }
    ],
    "sg:phone":"+44 1904 643322",
    "sg:postcode":"YO1 9WY",
    "sg:province":"North Yorkshire",
    "wof:name":"Fenwick",
    "wof:placetype":"venue"
},
  "geometry": {"coordinates":[-1.080046,53.957413],"type":"Point"}
}