{
  "type": "Feature",
  "properties": {
    "addr:full":"Prion Road, Llanynys Denbigh Conwy LL16 4RW",
    "addr:postcode":"ll16 4rw",
    "addr:street":"Prion Road",
    "iso:country":"GB",
    "sg:address":"Prion Road, Llanynys",
    "sg:city":"Denbigh",
    "sg:classifiers":[
        {
            "category":"Education",
            "subcategory":"School",
            "type":"Public Place"
        },
        {
            "category":"Government",
            "subcategory":"Office",
            "type":"Public Place"
        }
    ],
    "sg:phone":"+44 1745 890331",
    "sg:postcode":"LL16 4RW",
    "sg:province":"Conwy",
    "sg:tags":[
        "local",
        "authority"
    ],
    "wof:name":"Prion Controlled School",
    "wof:placetype":"venue"
},
  "geometry": {"coordinates":[-3.3442289829,53.1544189453],"type":"Point"}
}