{
  "type": "Feature",
  "properties": {
    "addr:full":"36 Main St Kilwinning East Ayrshire KA13 6AQ",
    "addr:housenumber":"36",
    "addr:postcode":"ka13 6aq",
    "addr:street":"Main St",
    "iso:country":"GB",
    "sg:address":"36 Main St",
    "sg:city":"Kilwinning",
    "sg:classifiers":[
        {
            "category":"Sports & Exercise",
            "subcategory":"Stables",
            "type":"Entertainment"
        }
    ],
    "sg:phone":"+44 1294 559960",
    "sg:postcode":"KA13 6AQ",
    "sg:province":"East Ayrshire",
    "sg:tags":[
        "equipment",
        "equestrian"
    ],
    "wof:name":"Equico",
    "wof:placetype":"venue"
},
  "geometry": {"coordinates":[-4.7161889076,55.6519203186],"type":"Point"}
}