{
  "type": "Feature",
  "properties": {
    "addr:full":"Stocks Warehouse Kirkcaldy Fife KY1 1SG",
    "addr:postcode":"ky1 1sg",
    "addr:street":"Kirkcaldy",
    "iso:country":"GB",
    "sg:address":"Stocks Warehouse",
    "sg:city":"Kirkcaldy",
    "sg:classifiers":[
        {
            "category":"Home & Garden",
            "subcategory":"Furniture",
            "type":"Retail Goods"
        }
    ],
    "sg:postcode":"KY1 1SG",
    "sg:province":"Fife",
    "wof:name":"David Cunningham",
    "wof:placetype":"venue"
},
  "geometry": {"coordinates":[-3.1630289555,56.1095962524],"type":"Point"}
}