{
  "type": "Feature",
  "properties": {
    "addr:full":"7 Aldgate, Ketton Stamford Cambridgeshire PE9 3TD",
    "addr:housenumber":"7",
    "addr:postcode":"pe9 3td",
    "addr:street":"Aldgate Ketton",
    "iso:country":"GB",
    "sg:address":"7 Aldgate, Ketton",
    "sg:city":"Stamford",
    "sg:classifiers":[
        {
            "category":"Professional",
            "subcategory":"Art Services",
            "type":"Services"
        }
    ],
    "sg:postcode":"PE9 3TD",
    "sg:province":"Cambridgeshire",
    "sg:tags":[
        "framing"
    ],
    "wof:name":"The Portofolio Collection",
    "wof:placetype":"venue"
},
  "geometry": {"coordinates":[-0.48029,52.652084],"type":"Point"}
}