{
  "type": "Feature",
  "properties": {
    "addr:full":"Cherry Lee Ho, Oxford St Great Missenden Buckinghamshire HP16 9JP",
    "addr:postcode":"hp16 9jp",
    "addr:street":"Oxford St",
    "iso:country":"GB",
    "sg:address":"Cherry Lee Ho, Oxford St",
    "sg:city":"Great Missenden",
    "sg:classifiers":[
        {
            "category":"Wholesale",
            "subcategory":"Vending Machines",
            "type":"Manufacturing & Wholesale Goods"
        }
    ],
    "sg:phone":"+44 1494 837342",
    "sg:postcode":"HP16 9JP",
    "sg:province":"Buckinghamshire",
    "sg:tags":[
        "sale"
    ],
    "wof:name":"Kwik Drink",
    "wof:placetype":"venue"
},
  "geometry": {"coordinates":[-0.709043,51.704067],"type":"Point"}
}