{
  "type": "Feature",
  "properties": {
    "addr:full":"Room, 5, 367 Ucd Building Liverpool Merseyside L7 8XP",
    "addr:housenumber":"5 367;building",
    "addr:postcode":"l7 8xp",
    "iso:country":"GB",
    "sg:address":"Room, 5, 367 Ucd Building",
    "sg:city":"Liverpool",
    "sg:classifiers":[
        {
            "category":"Organizations",
            "subcategory":"Non-profit Organization",
            "type":"Services"
        }
    ],
    "sg:phone":"+44 151 706 3598",
    "sg:postcode":"L7 8XP",
    "sg:province":"Merseyside",
    "sg:tags":[
        "organisation",
        "voluntary",
        "charity"
    ],
    "wof:name":"Mersey Kidney Research",
    "wof:placetype":"venue"
},
  "geometry": {"coordinates":[-2.96483,53.4095],"type":"Point"}
}