{
  "type": "Feature",
  "properties": {
    "iso:country":"GB",
    "sg:address":"White La Farm, Tongham",
    "sg:city":"Farnham",
    "sg:classifiers":[
        {
            "category":"Building & Trades",
            "subcategory":"Construction",
            "type":"Services"
        }
    ],
    "sg:phone":"+44 1252 724120",
    "sg:postcode":"GU10 1BW",
    "sg:province":"Hampshire",
    "sg:tags":[
        "roofing"
    ],
    "wof:name":"Specialist Felt Roofing Ltd",
    "wof:placetype":"venue"
},
  "geometry": {"coordinates":[-0.7297899723,51.2333030701],"type":"Point"}
}