{
  "type": "Feature",
  "properties": {
    "addr:full":"124 High Street Southend-on-sea Essex SS1 1LH",
    "addr:housenumber":"124",
    "addr:postcode":"ss1 1lh",
    "addr:street":"High Street",
    "iso:country":"GB",
    "sg:address":"124 High Street",
    "sg:city":"Southend-on-sea",
    "sg:classifiers":[
        {
            "category":"Home & Garden",
            "subcategory":"Furniture",
            "type":"Retail Goods"
        }
    ],
    "sg:phone":"+44 1702 464722",
    "sg:postcode":"SS1 1LH",
    "sg:province":"Essex",
    "wof:name":"Sharp Fitted Bedrooms",
    "wof:placetype":"venue"
},
  "geometry": {"coordinates":[0.713313,51.538422],"type":"Point"}
}