{
  "type": "Feature",
  "properties": {
    "iso:country":"GB",
    "sg:address":"85 Tolmers Road, Cuffley",
    "sg:city":"Potters Bar",
    "sg:classifiers":[
        {
            "category":"Professional",
            "subcategory":"Accounting & Tax Preparation",
            "type":"Services"
        }
    ],
    "sg:postcode":"EN6 4JJ",
    "sg:province":"Greater London",
    "sg:tags":[
        "accountant"
    ],
    "wof:name":"L Golding",
    "wof:placetype":"venue"
},
  "geometry": {"coordinates":[-0.115002,51.714237],"type":"Point"}
}