{
  "type": "Feature",
  "properties": {
    "iso:country":"GB",
    "sg:address":"Progress House, Brimington Road North",
    "sg:city":"Chesterfield",
    "sg:classifiers":[
        {
            "category":"Shopping",
            "subcategory":"Baby Store",
            "type":"Retail Goods"
        }
    ],
    "sg:phone":"+44 1246 454498",
    "sg:postcode":"S41 9AP",
    "sg:province":"Derbyshire",
    "sg:tags":[
        "nursery",
        "accessory"
    ],
    "wof:name":"Chesterfield Baby Care Centre",
    "wof:placetype":"venue"
},
  "geometry": {"coordinates":[-1.4217989445,53.2585296631],"type":"Point"}
}