{
  "type": "Feature",
  "properties": {
    "addr:full":"Rear Of 99 Cheyne Way Farnborough Hampshire GU14 8RZ",
    "addr:housenumber":"rear of 99",
    "addr:postcode":"gu14 8rz",
    "addr:street":"Cheyne Way",
    "iso:country":"GB",
    "sg:address":"Rear Of 99 Cheyne Way",
    "sg:city":"Farnborough",
    "sg:classifiers":[
        {
            "category":"Shopping",
            "subcategory":"Department Store",
            "type":"Retail Goods"
        },
        {
            "category":"Sports & Exercise",
            "subcategory":"Sports Center",
            "type":"Entertainment"
        }
    ],
    "sg:phone":"+44 1252 373960",
    "sg:postcode":"GU14 8RZ",
    "sg:province":"Hampshire",
    "sg:tags":[
        "shop"
    ],
    "wof:name":"First Choice Martial Arts Suppliers",
    "wof:placetype":"venue"
},
  "geometry": {"coordinates":[-0.7555689812,51.2937240601],"type":"Point"}
}