{
  "type": "Feature",
  "properties": {
    "addr:full":"19 New Bond St Bath Bath and North East Somerset BA1 1BB",
    "addr:housenumber":"19",
    "addr:postcode":"ba1 1bb",
    "addr:street":"New Bond St",
    "iso:country":"GB",
    "sg:address":"19 New Bond St",
    "sg:city":"Bath",
    "sg:classifiers":[
        {
            "category":"Shopping",
            "subcategory":"Shoes",
            "type":"Retail Goods"
        }
    ],
    "sg:phone":"+44 1225 420214",
    "sg:postcode":"BA1 1BB",
    "sg:province":"Bath and North East Somerset",
    "sg:tags":[
        "shop"
    ],
    "wof:name":"Charles Ashley",
    "wof:placetype":"venue"
},
  "geometry": {"coordinates":[-2.3604130745,51.383140564],"type":"Point"}
}