{
  "type": "Feature",
  "properties": {
    "iso:country":"GB",
    "sg:address":"Services To Deaf People, 49 Fonnereau Rd",
    "sg:city":"Ipswich",
    "sg:classifiers":[
        {
            "category":"Government",
            "subcategory":"Office",
            "type":"Public Place"
        }
    ],
    "sg:phone":"+44 1473 583545",
    "sg:postcode":"IP1 3JN",
    "sg:province":"Suffolk",
    "sg:tags":[
        "local"
    ],
    "wof:name":"Suffolk County Council",
    "wof:placetype":"venue"
},
  "geometry": {"coordinates":[1.1437879801,52.0577774048],"type":"Point"}
}