{
  "type": "Feature",
  "properties": {
    "iso:country":"GB",
    "sg:address":"North Market Road, Winterton-on-sea",
    "sg:city":"Great Yarmouth",
    "sg:classifiers":[
        {
            "category":"Building & Trades",
            "subcategory":"Electrical",
            "type":"Services"
        }
    ],
    "sg:phone":"+44 1493 393555",
    "sg:postcode":"NR29 4BH",
    "sg:province":"Norfolk",
    "sg:tags":[
        "heating"
    ],
    "wof:name":"Thermaglow Ltd.",
    "wof:placetype":"venue"
},
  "geometry": {"coordinates":[1.6915450096,52.7177810669],"type":"Point"}
}