{
  "type": "Feature",
  "properties": {
    "addr:full":"Claremont Crescent Kilwinning East Ayrshire KA13 7HD",
    "addr:postcode":"ka13 7hd",
    "addr:street":"Claremont Crescent",
    "iso:country":"GB",
    "sg:address":"Claremont Crescent",
    "sg:city":"Kilwinning",
    "sg:classifiers":[
        {
            "category":"Education",
            "subcategory":"School",
            "type":"Public Place"
        },
        {
            "category":"Government",
            "subcategory":"Office",
            "type":"Public Place"
        }
    ],
    "sg:phone":"+44 1294 552251",
    "sg:postcode":"KA13 7HD",
    "sg:province":"East Ayrshire",
    "sg:tags":[
        "local",
        "authority"
    ],
    "wof:name":"Abbey Primary School",
    "wof:placetype":"venue"
},
  "geometry": {"coordinates":[-4.707475,55.655777],"type":"Point"}
}