{
  "type": "Feature",
  "properties": {
    "iso:country":"GB",
    "sg:address":"534 Sauchiehall St",
    "sg:city":"Glasgow",
    "sg:classifiers":[
        {
            "category":"Professional",
            "subcategory":"Employment Agencies",
            "type":"Services"
        }
    ],
    "sg:phone":"+44 141 331 2383",
    "sg:postcode":"G2 3LX",
    "sg:province":"Glasgow City",
    "sg:tags":[
        "consultant"
    ],
    "wof:name":"Parc Uk Ltd",
    "wof:placetype":"venue"
},
  "geometry": {"coordinates":[-4.2699551582,55.866317749],"type":"Point"}
}