{
  "type": "Feature",
  "properties": {
    "addr:full":"Walnut Tree Barn, Walnut Tree Lane Canterbury Kent CT2 0HG",
    "addr:postcode":"ct2 0hg",
    "addr:street":"Walnut;Walnut Tree Lane",
    "iso:country":"GB",
    "sg:address":"Walnut Tree Barn, Walnut Tree Lane",
    "sg:city":"Canterbury",
    "sg:classifiers":[
        {
            "category":"Arts & Performance",
            "subcategory":"Music",
            "type":"Entertainment"
        }
    ],
    "sg:postcode":"CT2 0HG",
    "sg:province":"Kent",
    "sg:tags":[
        "mobile",
        "disco"
    ],
    "wof:name":"Louis Hurst",
    "wof:placetype":"venue"
},
  "geometry": {"coordinates":[1.1485899687,51.306060791],"type":"Point"}
}