{
  "type": "Feature",
  "properties": {
    "addr:full":"Dental Surgery, 58 Clarence Av Ilford Essex IG2 6JE",
    "addr:housenumber":"58",
    "addr:postcode":"ig2 6je",
    "addr:street":"Clarence Av Ilford",
    "iso:country":"GB",
    "sg:address":"Dental Surgery, 58 Clarence Av",
    "sg:city":"Ilford",
    "sg:classifiers":[
        {
            "category":"Health Services",
            "subcategory":"Dentist",
            "type":"Services"
        }
    ],
    "sg:phone":"+44 20 8554 9226",
    "sg:postcode":"IG2 6JE",
    "sg:province":"Essex",
    "wof:name":"J Pope",
    "wof:placetype":"venue"
},
  "geometry": {"coordinates":[0.0655400008,51.5760803223],"type":"Point"}
}