{
  "type": "Feature",
  "properties": {
    "addr:full":"103 Corbets Tey Road Upminster Essex RM14 2AH",
    "addr:housenumber":"103",
    "addr:postcode":"rm14 2ah",
    "addr:street":"Corbets Tey Road",
    "iso:country":"GB",
    "sg:address":"103 Corbets Tey Road",
    "sg:city":"Upminster",
    "sg:classifiers":[
        {
            "category":"Home & Garden",
            "subcategory":"Home Furnishings",
            "type":"Retail Goods"
        }
    ],
    "sg:postcode":"RM14 2AH",
    "sg:province":"Essex",
    "sg:tags":[
        "mantelpiece",
        "fireplace"
    ],
    "wof:name":"Grate Charm",
    "wof:placetype":"venue"
},
  "geometry": {"coordinates":[0.2475930005,51.5531082153],"type":"Point"}
}