{
  "type": "Feature",
  "properties": {
    "iso:country":"GB",
    "sg:address":"Dentholme, Cragg Rd",
    "sg:city":"Cleator Moor",
    "sg:classifiers":[
        {
            "category":"Social Services",
            "subcategory":"Retirement Home",
            "type":"Services"
        }
    ],
    "sg:phone":"+44 1946 810831",
    "sg:postcode":"CA25 5PR",
    "sg:province":"Cumbria",
    "sg:tags":[
        "residential",
        "care"
    ],
    "wof:name":"Cumbria Care",
    "wof:placetype":"venue"
},
  "geometry": {"coordinates":[-3.5158090591,54.5213699341],"type":"Point"}
}