{
  "type": "Feature",
  "properties": {
    "addr:full":"760 High Road Ilford Essex IG3 8SY",
    "addr:housenumber":"760",
    "addr:postcode":"ig3 8sy",
    "addr:street":"High Road",
    "iso:country":"GB",
    "sg:address":"760 High Road",
    "sg:city":"Ilford",
    "sg:classifiers":[
        {
            "category":"Cafe",
            "type":"Food & Drink"
        }
    ],
    "sg:phone":"+44 20 8503 8143",
    "sg:postcode":"IG3 8SY",
    "sg:province":"Essex",
    "sg:tags":[
        "tea",
        "snack",
        "bar",
        "room"
    ],
    "wof:name":"GOODMAYS CAFE",
    "wof:placetype":"venue"
},
  "geometry": {"coordinates":[0.108552,51.566204],"type":"Point"}
}