{
  "type": "Feature",
  "properties": {
    "iso:country":"GB",
    "sg:address":"Brook Lane",
    "sg:city":"Thame",
    "sg:classifiers":[
        {
            "category":"Education",
            "subcategory":"School",
            "type":"Public Place"
        }
    ],
    "sg:phone":"+44 1844 214278",
    "sg:postcode":"OX9 2AB",
    "sg:province":"Buckinghamshire",
    "sg:tags":[
        "local",
        "authority"
    ],
    "wof:name":"St Joseph R C Primary School",
    "wof:placetype":"venue"
},
  "geometry": {"coordinates":[-0.982954,51.748066],"type":"Point"}
}