{
  "type": "Feature",
  "properties": {
    "addr:full":"6 North Gate Place Nottingham Nottinghamshire NG7 7JT",
    "addr:housenumber":"6",
    "addr:postcode":"ng7 7jt",
    "addr:street":"North Gate Place",
    "iso:country":"GB",
    "sg:address":"6 North Gate Place",
    "sg:city":"Nottingham",
    "sg:classifiers":[
        {
            "category":"Retail",
            "subcategory":"Auto Repair",
            "type":"Services"
        }
    ],
    "sg:phone":"+44 115 978 0004",
    "sg:postcode":"NG7 7JT",
    "sg:province":"Nottinghamshire",
    "sg:tags":[
        "modification",
        "garage"
    ],
    "wof:name":"Kerry J Christie",
    "wof:placetype":"venue"
},
  "geometry": {"coordinates":[-1.168294,52.975189],"type":"Point"}
}