{
  "type": "Feature",
  "properties": {
    "iso:country":"GB",
    "sg:address":"38 Lower Way",
    "sg:city":"Weymouth",
    "sg:classifiers":[
        {
            "category":"Food & Beverages",
            "subcategory":"Fruits & Vegetables",
            "type":"Retail Goods"
        }
    ],
    "sg:phone":"+44 1305 772468",
    "sg:postcode":"DT3 4AR",
    "sg:province":"Dorset",
    "sg:tags":[
        "greengrocer"
    ],
    "wof:name":"S & B Taylor",
    "wof:placetype":"venue"
},
  "geometry": {"coordinates":[-2.502491,50.624207],"type":"Point"}
}