{
  "type": "Feature",
  "properties": {
    "addr:full":"Blackwood Hill Farm, Rushton Spencer Macclesfield Cheshire SK11 0RU",
    "addr:postcode":"sk11 0ru",
    "addr:street":"Blackwood Hill",
    "iso:country":"GB",
    "sg:address":"Blackwood Hill Farm, Rushton Spencer",
    "sg:city":"Macclesfield",
    "sg:classifiers":[
        {
            "category":"Building & Trades",
            "subcategory":"Cleaning & Sanitation",
            "type":"Services"
        }
    ],
    "sg:phone":"+44 1260 226552",
    "sg:postcode":"SK11 0RU",
    "sg:province":"Cheshire",
    "sg:tags":[
        "facility"
    ],
    "wof:name":"A D & L",
    "wof:placetype":"venue"
},
  "geometry": {"coordinates":[-2.0920870304,53.1584205627],"type":"Point"}
}