{
  "type": "Feature",
  "properties": {
    "iso:country":"GB",
    "sg:address":"23 Town Road, Croston",
    "sg:city":"Preston",
    "sg:classifiers":[
        {
            "category":"Banks & Credit Unions",
            "subcategory":"Bank",
            "type":"Services"
        }
    ],
    "sg:phone":"+44 1772 600574",
    "sg:postcode":"PR26 9RA",
    "sg:province":"Lancashire",
    "sg:tags":[
        "financial",
        "institution"
    ],
    "wof:name":"The Royal Bank of Scotland Plc",
    "wof:placetype":"venue"
},
  "geometry": {"coordinates":[-2.774896,53.661591],"type":"Point"}
}