{
  "type": "Feature",
  "properties": {
    "addr:full":"33 Onslow Rd Southampton Hampshire SO14 0JH",
    "addr:housenumber":"33",
    "addr:postcode":"so14 0jh",
    "addr:street":"Onslow Rd",
    "iso:country":"GB",
    "sg:address":"33 Onslow Rd",
    "sg:city":"Southampton",
    "sg:classifiers":[
        {
            "category":"Health Services",
            "subcategory":"Dentist",
            "type":"Services"
        }
    ],
    "sg:phone":"+44 23 8022 5870",
    "sg:postcode":"SO14 0JH",
    "sg:province":"Hampshire",
    "sg:tags":[
        "technician",
        "dental"
    ],
    "wof:name":"Shirley Dental Laboratory",
    "wof:placetype":"venue"
},
  "geometry": {"coordinates":[-1.398794055,50.9140396118],"type":"Point"}
}