{
  "type": "Feature",
  "properties": {
    "addr:full":"117 Briscoe Lane, Newton Heath Manchester Greater Manchester M40 2TP",
    "addr:housenumber":"117",
    "addr:postcode":"m40 2tp",
    "addr:street":"Briscoe Lane",
    "iso:country":"GB",
    "sg:address":"117 Briscoe Lane, Newton Heath",
    "sg:city":"Manchester",
    "sg:classifiers":[
        {
            "category":"Travel",
            "subcategory":"Travel Agent",
            "type":"Entertainment"
        }
    ],
    "sg:phone":"+44 161 682 4003",
    "sg:postcode":"M40 2TP",
    "sg:province":"Greater Manchester",
    "wof:name":"Addison Travel Ltd.",
    "wof:placetype":"venue"
},
  "geometry": {"coordinates":[-2.1830129623,53.4979476929],"type":"Point"}
}