{
  "type": "Feature",
  "properties": {
    "iso:country":"GB",
    "sg:address":"104 Station Road",
    "sg:city":"Ibstock",
    "sg:classifiers":[
        {
            "category":"Real Estate",
            "subcategory":"Real Estate Agent",
            "type":"Services"
        }
    ],
    "sg:phone":"+44 1530 263696",
    "sg:postcode":"LE67 6JJ",
    "sg:province":"Leicestershire",
    "wof:name":"Stephen M Clarke",
    "wof:placetype":"venue"
},
  "geometry": {"coordinates":[-1.405749,52.686218],"type":"Point"}
}