{
  "type": "Feature",
  "properties": {
    "iso:country":"GB",
    "sg:address":"2 High Street",
    "sg:city":"Sidmouth",
    "sg:classifiers":[
        {
            "category":"Professional",
            "subcategory":"Lawyer & Legal Services",
            "type":"Services"
        }
    ],
    "sg:postcode":"EX10 8EL",
    "sg:province":"Devon",
    "sg:tags":[
        "solicitor"
    ],
    "wof:name":"Shirley May Yard Solicitor",
    "wof:placetype":"venue"
},
  "geometry": {"coordinates":[-3.237378,50.680119],"type":"Point"}
}