{
  "type": "Feature",
  "properties": {
    "addr:full":"671-673 Bradford Road, Oakenshaw Bradford West Yorkshire BD12 7DT",
    "addr:housenumber":"671-673;bradford",
    "addr:postcode":"bd12 7dt",
    "addr:street":"Bradford Road Oakenshaw",
    "iso:country":"GB",
    "sg:address":"671-673 Bradford Road, Oakenshaw",
    "sg:city":"Bradford",
    "sg:classifiers":[
        {
            "category":"Cinema",
            "subcategory":"Movie Rental",
            "type":"Entertainment"
        }
    ],
    "sg:phone":"+44 1274 676651",
    "sg:postcode":"BD12 7DT",
    "sg:province":"West Yorkshire",
    "sg:tags":[
        "video",
        "library"
    ],
    "wof:name":"Future General Off Licence & Video Store",
    "wof:placetype":"venue"
},
  "geometry": {"coordinates":[-1.738607,53.74699],"type":"Point"}
}