{
  "type": "Feature",
  "properties": {
    "addr:full":"Oldham Rd Ashton-under-lyne Greater Manchester OL7 9ND",
    "addr:postcode":"ol7 9nd",
    "addr:street":"Oldham Rd",
    "iso:country":"GB",
    "sg:address":"Oldham Rd",
    "sg:city":"Ashton-under-lyne",
    "sg:classifiers":[
        {
            "category":"Retail",
            "subcategory":"Laundry & Dry Cleaning",
            "type":"Services"
        }
    ],
    "sg:postcode":"OL7 9ND",
    "sg:province":"Greater Manchester",
    "sg:tags":[
        "launderette"
    ],
    "wof:name":"Torkinton,G,",
    "wof:placetype":"venue"
},
  "geometry": {"coordinates":[-2.101954,53.495979],"type":"Point"}
}