{
  "type": "Feature",
  "properties": {
    "addr:full":"62 Broadview Stevenage Hertfordshire SG1 3TR",
    "addr:housenumber":"62",
    "addr:postcode":"sg1 3tr",
    "addr:street":"Broadview",
    "iso:country":"GB",
    "sg:address":"62 Broadview",
    "sg:city":"Stevenage",
    "sg:classifiers":[
        {
            "category":"Manufacturing",
            "subcategory":"Petroleum Products",
            "type":"Manufacturing & Wholesale Goods"
        }
    ],
    "sg:phone":"+44 1438 759201",
    "sg:postcode":"SG1 3TR",
    "sg:province":"Hertfordshire",
    "sg:tags":[
        "double",
        "glazing"
    ],
    "wof:name":"Broadview Windows",
    "wof:placetype":"venue"
},
  "geometry": {"coordinates":[-0.192781,51.906239],"type":"Point"}
}