{
  "type": "Feature",
  "properties": {
    "addr:full":"1 Thompson Street Bridlington East Riding of Yorkshire YO16 4JU",
    "addr:housenumber":"1",
    "addr:postcode":"yo16 4ju",
    "addr:street":"Thompson Street",
    "iso:country":"GB",
    "sg:address":"1 Thompson Street",
    "sg:city":"Bridlington",
    "sg:classifiers":[
        {
            "category":"Home & Garden",
            "subcategory":"Household Appliances",
            "type":"Retail Goods"
        }
    ],
    "sg:phone":"+44 1262 674865",
    "sg:postcode":"YO16 4JU",
    "sg:province":"East Riding of Yorkshire",
    "sg:tags":[
        "electrical"
    ],
    "wof:name":"East Riding Refrigeration Ltd.",
    "wof:placetype":"venue"
},
  "geometry": {"coordinates":[-0.1978780031,54.087310791],"type":"Point"}
}