{
  "type": "Feature",
  "properties": {
    "iso:country":"GB",
    "sg:address":"110-112 Mansfield Road, Intake",
    "sg:city":"Sheffield",
    "sg:classifiers":[
        {
            "category":"Food & Beverages",
            "subcategory":"Bakery",
            "type":"Retail Goods"
        }
    ],
    "sg:phone":"+44 114 239 9646",
    "sg:postcode":"S12 2AP",
    "sg:province":"Derbyshire",
    "sg:tags":[
        "baker"
    ],
    "wof:name":"F A Smith & Sons",
    "wof:placetype":"venue"
},
  "geometry": {"coordinates":[-1.4209029675,53.3586502075],"type":"Point"}
}