{
  "type": "Feature",
  "properties": {
    "iso:country":"GB",
    "sg:address":"Ranskill Gardens",
    "sg:city":"Nottingham",
    "sg:classifiers":[
        {
            "category":"Social Services",
            "subcategory":"Child Care",
            "type":"Services"
        }
    ],
    "sg:phone":"+44 115 927 6551",
    "sg:postcode":"NG5 9DX",
    "sg:province":"Nottinghamshire",
    "sg:tags":[
        "children's",
        "home"
    ],
    "wof:name":"Farmlands Childrens Community Home",
    "wof:placetype":"venue"
},
  "geometry": {"coordinates":[-1.1633939743,53.0054855347],"type":"Point"}
}