{
  "type": "Feature",
  "properties": {
    "addr:full":"9 Eden Street Kingston-upon-thames Greater London KT1 1BQ",
    "addr:housenumber":"9",
    "addr:postcode":"kt1 1bq",
    "addr:street":"Eden Street",
    "iso:country":"GB",
    "sg:address":"9 Eden Street",
    "sg:city":"Kingston-upon-thames",
    "sg:classifiers":[
        {
            "category":"Professional",
            "subcategory":"Employment Agencies",
            "type":"Services"
        }
    ],
    "sg:phone":"+44 20 8546 4586",
    "sg:postcode":"KT1 1BQ",
    "sg:province":"Greater London",
    "sg:tags":[
        "consultant"
    ],
    "wof:name":"Brook Street",
    "wof:placetype":"venue"
},
  "geometry": {"coordinates":[-0.3057419956,51.4088973999],"type":"Point"}
}