{
  "type": "Feature",
  "properties": {
    "iso:country":"GB",
    "sg:address":"Dean Lane",
    "sg:city":"Redhill",
    "sg:classifiers":[
        {
            "category":"Recreation",
            "subcategory":"Campground",
            "type":"Entertainment"
        }
    ],
    "sg:phone":"+44 1737 644629",
    "sg:postcode":"RH1 3AH",
    "sg:province":"Surrey",
    "sg:tags":[
        "caravan",
        "park"
    ],
    "wof:name":"Alderstead Heath Caravan Club Site",
    "wof:placetype":"venue"
},
  "geometry": {"coordinates":[-0.153339,51.287052],"type":"Point"}
}