{
  "type": "Feature",
  "properties": {
    "addr:full":"99 High Street North Berwick East Lothian EH39 4HD",
    "addr:housenumber":"99",
    "addr:postcode":"eh39 4hd",
    "addr:street":"High Street",
    "iso:country":"GB",
    "sg:address":"99 High Street",
    "sg:city":"North Berwick",
    "sg:classifiers":[
        {
            "category":"Deli",
            "type":"Food & Drink"
        }
    ],
    "sg:phone":"+44 1620 895383",
    "sg:postcode":"EH39 4HD",
    "sg:province":"East Lothian",
    "sg:tags":[
        "delicatessen"
    ],
    "wof:name":"Nature's Larder",
    "wof:placetype":"venue"
},
  "geometry": {"coordinates":[-2.7217049599,56.0581207275],"type":"Point"}
}