{
  "type": "Feature",
  "properties": {
    "addr:full":"The Corner Shop Cafe, 73 Nutley La Reigate Surrey RH2 9HS",
    "addr:housenumber":"73",
    "addr:postcode":"rh2 9hs",
    "addr:street":"Nutley La Reigate",
    "iso:country":"GB",
    "sg:address":"The Corner Shop Cafe, 73 Nutley La",
    "sg:city":"Reigate",
    "sg:classifiers":[
        {
            "category":"Utilities",
            "subcategory":"Fuel Oil & Lpg",
            "type":"Services"
        }
    ],
    "sg:phone":"+44 1737 245684",
    "sg:postcode":"RH2 9HS",
    "sg:province":"Surrey",
    "sg:tags":[
        "peat",
        "firewood",
        "logs"
    ],
    "wof:name":"Logs & Coal",
    "wof:placetype":"venue"
},
  "geometry": {"coordinates":[-0.204779,51.235744],"type":"Point"}
}