{
  "type": "Feature",
  "properties": {
    "iso:country":"GB",
    "sg:address":"41 Old Slade La",
    "sg:city":"Iver",
    "sg:classifiers":[
        {
            "category":"Sports & Exercise",
            "subcategory":"Stables",
            "type":"Entertainment"
        }
    ],
    "sg:phone":"+44 1753 654823",
    "sg:postcode":"SL0 9DX",
    "sg:province":"Berkshire",
    "sg:tags":[
        "education",
        "equestrian"
    ],
    "wof:name":"Richings Park",
    "wof:placetype":"venue"
},
  "geometry": {"coordinates":[-0.5101289749,51.497051239],"type":"Point"}
}