{
  "type": "Feature",
  "properties": {
    "addr:full":"13 Clarke Road Milton Keynes Buckinghamshire MK1 1LG",
    "addr:housenumber":"13",
    "addr:postcode":"mk1 1lg",
    "addr:street":"Clarke Road",
    "iso:country":"GB",
    "sg:address":"13 Clarke Road",
    "sg:city":"Milton Keynes",
    "sg:classifiers":[
        {
            "category":"Professional",
            "subcategory":"Detective & Security Services",
            "type":"Services"
        }
    ],
    "sg:postcode":"MK1 1LG",
    "sg:province":"Buckinghamshire",
    "wof:name":"Cdv Ltd",
    "wof:placetype":"venue"
},
  "geometry": {"coordinates":[-0.7234990001,52.0120811462],"type":"Point"}
}