{
  "type": "Feature",
  "properties": {
    "addr:full":"2 Market Square Waltham Abbey Essex EN9 1DL",
    "addr:housenumber":"2",
    "addr:postcode":"en9 1dl",
    "addr:street":"Market Square",
    "iso:country":"GB",
    "sg:address":"2 Market Square",
    "sg:city":"Waltham Abbey",
    "sg:classifiers":[
        {
            "category":"Shopping",
            "subcategory":"Pharmacy",
            "type":"Retail Goods"
        }
    ],
    "sg:phone":"+44 1992 713320",
    "sg:postcode":"EN9 1DL",
    "sg:province":"Essex",
    "sg:tags":[
        "pharmacist",
        "chemist"
    ],
    "wof:name":"Stephen Collins Chemist",
    "wof:placetype":"venue"
},
  "geometry": {"coordinates":[0.0014900001,51.6864204407],"type":"Point"}
}