{
  "type": "Feature",
  "properties": {
    "addr:full":"Clovelly Road, Southbourne Industrial Estate, Southbourne Emsworth Hampshire PO10 8PE",
    "addr:postcode":"po10 8pe",
    "addr:street":"Clovelly Road;Industrial Estate Southbourne",
    "iso:country":"GB",
    "sg:address":"Clovelly Road, Southbourne Industrial Estate, Southbourne",
    "sg:city":"Emsworth",
    "sg:classifiers":[
        {
            "category":"Professional",
            "subcategory":"Engineering",
            "type":"Services"
        }
    ],
    "sg:phone":"+44 1243 377751",
    "sg:postcode":"PO10 8PE",
    "sg:province":"Hampshire",
    "sg:tags":[
        "precision",
        "engineer"
    ],
    "wof:name":"Hyspeed (C N C) Ltd.",
    "wof:placetype":"venue"
},
  "geometry": {"coordinates":[-0.910219,50.855724],"type":"Point"}
}