{
  "type": "Feature",
  "properties": {
    "iso:country":"GB",
    "sg:address":"337 Shirley Road",
    "sg:city":"Southampton",
    "sg:classifiers":[
        {
            "category":"Real Estate",
            "subcategory":"Real Estate Agent",
            "type":"Services"
        }
    ],
    "sg:phone":"+44 23 8078 9424",
    "sg:postcode":"SO15 3JD",
    "sg:province":"Hampshire",
    "wof:name":"Mann & Co",
    "wof:placetype":"venue"
},
  "geometry": {"coordinates":[-1.428003,50.918289],"type":"Point"}
}