{
  "type": "Feature",
  "properties": {
    "addr:full":"Wynard's Works, Old Rydon Lane Exeter Devon EX2 4HX",
    "addr:postcode":"ex2 4hx",
    "addr:street":"Old Rydon Lane",
    "iso:country":"GB",
    "sg:address":"Wynard's Works, Old Rydon Lane",
    "sg:city":"Exeter",
    "sg:classifiers":[
        {
            "category":"Professional",
            "subcategory":"Accounting & Tax Preparation",
            "type":"Services"
        }
    ],
    "sg:postcode":"EX2 4HX",
    "sg:province":"Devon",
    "sg:tags":[
        "accountant"
    ],
    "wof:name":"St.Margaret's Court (Topsham) Ltd.",
    "wof:placetype":"venue"
},
  "geometry": {"coordinates":[-3.5264000893,50.7205085754],"type":"Point"}
}