{
  "type": "Feature",
  "properties": {
    "addr:full":"27 Arkwright Road London Greater London NW3 6BJ",
    "addr:housenumber":"27",
    "addr:postcode":"nw3 6bj",
    "addr:street":"Arkwright Road",
    "iso:country":"GB",
    "sg:address":"27 Arkwright Road",
    "sg:city":"London",
    "sg:classifiers":[
        {
            "category":"Wholesale",
            "subcategory":"Music Publishers",
            "type":"Manufacturing & Wholesale Goods"
        }
    ],
    "sg:phone":"+44 20 7435 9601",
    "sg:postcode":"NW3 6BJ",
    "sg:province":"Greater London",
    "wof:name":"Axle Music",
    "wof:placetype":"venue"
},
  "geometry": {"coordinates":[-0.180788,51.551685],"type":"Point"}
}