{
  "type": "Feature",
  "properties": {
    "iso:country":"GB",
    "sg:address":"61 Peel St, Thornaby",
    "sg:city":"Stockton On Tees",
    "sg:classifiers":[
        {
            "category":"Building & Trades",
            "subcategory":"Construction",
            "type":"Services"
        }
    ],
    "sg:phone":"+44 1642 612057",
    "sg:postcode":"TS17 6JN",
    "sg:province":"Durham",
    "sg:tags":[
        "joiner",
        "carpenter"
    ],
    "wof:name":"House & About",
    "wof:placetype":"venue"
},
  "geometry": {"coordinates":[-1.304055,54.553715],"type":"Point"}
}