{
  "type": "Feature",
  "properties": {
    "addr:full":"Gordano Services Area, Junction 19 M5 Portbury Bristol Somerset BS20 7XG",
    "addr:housenumber":"19 m5",
    "addr:postcode":"bs20 7xg",
    "iso:country":"GB",
    "sg:address":"Gordano Services Area, Junction 19 M5 Portbury",
    "sg:city":"Bristol",
    "sg:classifiers":[
        {
            "category":"Landmark",
            "subcategory":"Tourist Information",
            "type":"Public Place"
        }
    ],
    "sg:phone":"+44 1275 375516",
    "sg:postcode":"BS20 7XG",
    "sg:province":"Somerset",
    "wof:name":"Tourist Information Centre",
    "wof:placetype":"venue"
},
  "geometry": {"coordinates":[-2.7173190117,51.4746360779],"type":"Point"}
}