{
  "type": "Feature",
  "properties": {
    "iso:country":"GB",
    "sg:address":"84 Ditton Fields",
    "sg:city":"Cambridge",
    "sg:classifiers":[
        {
            "category":"Professional",
            "subcategory":"Engineering",
            "type":"Services"
        }
    ],
    "sg:phone":"+44 1223 415440",
    "sg:postcode":"CB5 8QL",
    "sg:province":"Cambridgeshire",
    "sg:tags":[
        "contractor",
        "electrical",
        "engineer"
    ],
    "wof:name":"Quest Services",
    "wof:placetype":"venue"
},
  "geometry": {"coordinates":[0.1607239991,52.2155914307],"type":"Point"}
}