{
  "type": "Feature",
  "properties": {
    "iso:country":"GB",
    "sg:address":"22 Mountney Bridge Business Park, Eastbourne Road, Westham",
    "sg:city":"Pevensey",
    "sg:classifiers":[
        {
            "category":"Building & Trades",
            "subcategory":"Cleaning & Sanitation",
            "type":"Services"
        }
    ],
    "sg:phone":"+44 1323 767951",
    "sg:postcode":"BN24 5NH",
    "sg:province":"East Sussex",
    "sg:tags":[
        "commercial"
    ],
    "wof:name":"Denma Cleaning Services Ltd.",
    "wof:placetype":"venue"
},
  "geometry": {"coordinates":[0.3407459855,50.8211021423],"type":"Point"}
}