{
  "type": "Feature",
  "properties": {
    "iso:country":"GB",
    "sg:address":"Bunyan Lodge, 8 Wood End, Bluntisham",
    "sg:city":"Huntingdon",
    "sg:classifiers":[
        {
            "category":"Health Services",
            "subcategory":"Podiatrist",
            "type":"Services"
        }
    ],
    "sg:phone":"+44 1487 841080",
    "sg:postcode":"PE28 3LE",
    "sg:province":"Bedfordshire",
    "sg:tags":[
        "podiatrists",
        "chiropodist"
    ],
    "wof:name":"Elizabeth Pinnock MSSCh MBChA",
    "wof:placetype":"venue"
},
  "geometry": {"coordinates":[0.0095250001,52.3510818481],"type":"Point"}
}