{
  "type": "Feature",
  "properties": {
    "iso:country":"GB",
    "sg:address":"Monkwood House, Elgar Business Ctr",
    "sg:city":"Worcester",
    "sg:classifiers":[
        {
            "category":"Professional",
            "subcategory":"Computer Services",
            "type":"Services"
        }
    ],
    "sg:phone":"+44 1905 641515",
    "sg:postcode":"WR2 6NJ",
    "sg:province":"Worcestershire",
    "sg:tags":[
        "system",
        "software"
    ],
    "wof:name":"Ccl Software Ltd.",
    "wof:placetype":"venue"
},
  "geometry": {"coordinates":[-2.26791,52.232391],"type":"Point"}
}