{
  "type": "Feature",
  "properties": {
    "iso:country":"GB",
    "sg:address":"53 Old Birley St",
    "sg:city":"Manchester",
    "sg:classifiers":[
        {
            "category":"Food & Beverages",
            "subcategory":"Specialty",
            "type":"Retail Goods"
        }
    ],
    "sg:phone":"+44 161 226 4777",
    "sg:postcode":"M15 5RF",
    "sg:province":"Cheshire",
    "sg:tags":[
        "product",
        "health"
    ],
    "wof:name":"Limited Resources",
    "wof:placetype":"venue"
},
  "geometry": {"coordinates":[-2.248678,53.464264],"type":"Point"}
}