{
  "type": "Feature",
  "properties": {
    "addr:full":"101 High Street Marlow Berkshire SL7 1AB",
    "addr:housenumber":"101",
    "addr:postcode":"sl7 1ab",
    "addr:street":"High Street",
    "iso:country":"GB",
    "sg:address":"101 High Street",
    "sg:city":"Marlow",
    "sg:classifiers":[
        {
            "category":"Restaurant",
            "type":"Food & Drink"
        }
    ],
    "sg:phone":"+44 1628 482180",
    "sg:postcode":"SL7 1AB",
    "sg:province":"Berkshire",
    "sg:tags":[
        "italian"
    ],
    "wof:name":"De Ciro Italian Restaurant",
    "wof:placetype":"venue"
},
  "geometry": {"coordinates":[-0.7742030025,51.5694847107],"type":"Point"}
}