{
  "type": "Feature",
  "properties": {
    "addr:full":"43 Wether Riggs Road, Salterbeck Workington Cumbria CA14 5HS",
    "addr:housenumber":"43",
    "addr:postcode":"ca14 5hs",
    "addr:street":"Wether Riggs Road Salterbeck",
    "iso:country":"GB",
    "sg:address":"43 Wether Riggs Road, Salterbeck",
    "sg:city":"Workington",
    "sg:classifiers":[
        {
            "category":"Professional",
            "subcategory":"Management & Consulting",
            "type":"Services"
        }
    ],
    "sg:postcode":"CA14 5HS",
    "sg:province":"Cumbria",
    "sg:tags":[
        "consultant",
        "business"
    ],
    "wof:name":"Applied Consulting Ltd",
    "wof:placetype":"venue"
},
  "geometry": {"coordinates":[-3.5627000332,54.6224479675],"type":"Point"}
}