{
  "type": "Feature",
  "properties": {
    "iso:country":"GB",
    "sg:address":"Ladies Walk",
    "sg:city":"Stranraer",
    "sg:classifiers":[
        {
            "category":"Education",
            "subcategory":"School",
            "type":"Public Place"
        }
    ],
    "sg:phone":"+44 1776 704195",
    "sg:postcode":"DG9 8BW",
    "sg:province":"Dumfries and Galloway",
    "sg:tags":[
        "local",
        "authority"
    ],
    "wof:name":"Rephad Primary School",
    "wof:placetype":"venue"
},
  "geometry": {"coordinates":[-5.011154,54.906979],"type":"Point"}
}