{
  "type": "Feature",
  "properties": {
    "addr:full":"Cemetry Road, Darlaston Wednesbury West Midlands WS10 8NA",
    "addr:postcode":"ws10 8na",
    "addr:street":"Cemetry Road",
    "iso:country":"GB",
    "sg:address":"Cemetry Road, Darlaston",
    "sg:city":"Wednesbury",
    "sg:classifiers":[
        {
            "category":"Retail",
            "subcategory":"Auto Repair",
            "type":"Services"
        }
    ],
    "sg:postcode":"WS10 8NA",
    "sg:province":"West Midlands",
    "sg:tags":[
        "modification",
        "garage"
    ],
    "wof:name":"Steven Whitehouse",
    "wof:placetype":"venue"
},
  "geometry": {"coordinates":[-2.0190091133,52.5760192871],"type":"Point"}
}