{
  "type": "Feature",
  "properties": {
    "iso:country":"GB",
    "sg:address":"41 Beach Road",
    "sg:city":"Littlehampton",
    "sg:classifiers":[
        {
            "category":"Professional",
            "subcategory":"Engineering",
            "type":"Services"
        },
        {
            "category":"Building & Trades",
            "subcategory":"Electrical",
            "type":"Services"
        }
    ],
    "sg:phone":"+44 1903 733033",
    "sg:postcode":"BN17 5JA",
    "sg:province":"West Sussex",
    "sg:tags":[
        "engineer",
        "electrician",
        "contractor"
    ],
    "wof:name":"Weller Electrical Ltd",
    "wof:placetype":"venue"
},
  "geometry": {"coordinates":[-0.539511,50.808151],"type":"Point"}
}