{
  "type": "Feature",
  "properties": {
    "iso:country":"GB",
    "sg:address":"Midland Sheds, Scotland Road",
    "sg:city":"Carnforth",
    "sg:classifiers":[
        {
            "category":"Building & Trades",
            "subcategory":"Construction",
            "type":"Services"
        }
    ],
    "sg:phone":"+44 1524 736199",
    "sg:postcode":"LA5 9RE",
    "sg:province":"Cumbria",
    "sg:tags":[
        "roofing"
    ],
    "wof:name":"Roof Rite (Carnforth) Ltd.",
    "wof:placetype":"venue"
},
  "geometry": {"coordinates":[-2.768059,54.128479],"type":"Point"}
}