{
  "type": "Feature",
  "properties": {
    "iso:country":"GB",
    "sg:address":"29 Bretton Rd, Ravenshead",
    "sg:city":"Nottingham",
    "sg:classifiers":[
        {
            "category":"Banks & Credit Unions",
            "subcategory":"Financial Services",
            "type":"Services"
        }
    ],
    "sg:postcode":"NG15 9DB",
    "sg:province":"Nottinghamshire",
    "sg:tags":[
        "consultant"
    ],
    "wof:name":"Thompsons of Arnold Ltd",
    "wof:placetype":"venue"
},
  "geometry": {"coordinates":[-1.156452,53.091499],"type":"Point"}
}