{
  "type": "Feature",
  "properties": {
    "iso:country":"GB",
    "sg:address":"181 Brampton Rd",
    "sg:city":"Rotherham",
    "sg:classifiers":[
        {
            "category":"Insurance",
            "subcategory":"Insurance Agent",
            "type":"Services"
        }
    ],
    "sg:phone":"+44 1709 876409",
    "sg:postcode":"S63 6BE",
    "sg:province":"South Yorkshire",
    "wof:name":"Order Of Druids Friendly Society The",
    "wof:placetype":"venue"
},
  "geometry": {"coordinates":[-1.3755220175,53.5081863403],"type":"Point"}
}