{
  "type": "Feature",
  "properties": {
    "addr:full":"Roughwood Cottage, Rocky Lane St Agnes Cornwall TR5 0SR",
    "addr:postcode":"tr5 0sr",
    "addr:street":"Rocky Lane",
    "iso:country":"GB",
    "sg:address":"Roughwood Cottage, Rocky Lane",
    "sg:city":"St Agnes",
    "sg:classifiers":[
        {
            "category":"Travel",
            "subcategory":"Hotels & Motels",
            "type":"Entertainment"
        }
    ],
    "sg:phone":"+44 1872 553160",
    "sg:postcode":"TR5 0SR",
    "sg:province":"Cornwall",
    "sg:tags":[
        "self",
        "catering"
    ],
    "wof:name":"Wheal Friendly Chalets",
    "wof:placetype":"venue"
},
  "geometry": {"coordinates":[-5.1991991997,50.3120994568],"type":"Point"}
}