{
  "type": "Feature",
  "properties": {
    "addr:full":"Reflex House, Taine Valley Industrial Estate Tamworth Staffordshire B77 5DQ",
    "addr:housenumber":"estate",
    "addr:postcode":"b77 5dq",
    "addr:street":"Taine Valley Industrial",
    "iso:country":"GB",
    "sg:address":"Reflex House, Taine Valley Industrial Estate",
    "sg:city":"Tamworth",
    "sg:classifiers":[
        {
            "category":"Manufacturing",
            "subcategory":"Signs",
            "type":"Manufacturing & Wholesale Goods"
        }
    ],
    "sg:phone":"+44 1827 260266",
    "sg:postcode":"B77 5DQ",
    "sg:province":"Staffordshire",
    "sg:tags":[
        "nameplate"
    ],
    "wof:name":"Reflex Project Support Services Ltd.",
    "wof:placetype":"venue"
},
  "geometry": {"coordinates":[-1.6772539616,52.6002159119],"type":"Point"}
}