{
  "type": "Feature",
  "properties": {
    "iso:country":"GB",
    "sg:address":"172 Livesey Branch Road",
    "sg:city":"Blackburn",
    "sg:classifiers":[
        {
            "category":"Shopping",
            "subcategory":"Department Store",
            "type":"Retail Goods"
        },
        {
            "category":"Food & Beverages",
            "subcategory":"Supermarket",
            "type":"Retail Goods"
        },
        {
            "category":"Food & Beverages",
            "subcategory":"Groceries & Convenience Stores",
            "type":"Retail Goods"
        }
    ],
    "sg:phone":"+44 1254 262497",
    "sg:postcode":"BB2 4QR",
    "sg:province":"Lancashire",
    "wof:name":"Nilus Mini Market",
    "wof:placetype":"venue"
},
  "geometry": {"coordinates":[-2.5004,53.728546],"type":"Point"}
}