{
  "type": "Feature",
  "properties": {
    "iso:country":"GB",
    "sg:address":"P O Box 60",
    "sg:city":"Cramlington",
    "sg:classifiers":[
        {
            "category":"Manufacturing",
            "subcategory":"Wood Products",
            "type":"Manufacturing & Wholesale Goods"
        }
    ],
    "sg:phone":"+44 1670 737008",
    "sg:postcode":"NE23 3ZD",
    "sg:province":"Northumberland",
    "sg:tags":[
        "packaging",
        "crate",
        "pallets"
    ],
    "wof:name":"Advanced Packaging Materials Ltd.",
    "wof:placetype":"venue"
},
  "geometry": {"coordinates":[-1.573419,55.10463],"type":"Point"}
}