{
  "type": "Feature",
  "properties": {
    "iso:country":"GB",
    "sg:address":"Regent House, 291 Kirkdale, Sydenham",
    "sg:city":"London",
    "sg:classifiers":[
        {
            "category":"Utilities",
            "subcategory":"Natural Gas",
            "type":"Services"
        }
    ],
    "sg:phone":"+44 20 8659 2262",
    "sg:postcode":"SE26 4QE",
    "sg:province":"Greater London",
    "sg:tags":[
        "control",
        "energy",
        "management",
        "system"
    ],
    "wof:name":"Energy Cost Management Partnership",
    "wof:placetype":"venue"
},
  "geometry": {"coordinates":[-0.0563700013,51.4277153015],"type":"Point"}
}