{
  "type": "Feature",
  "properties": {
    "addr:full":"58 Aldermans Hill London Greater London N13 4PP",
    "addr:housenumber":"58",
    "addr:postcode":"n13 4pp",
    "addr:street":"Aldermans Hill",
    "iso:country":"GB",
    "sg:address":"58 Aldermans Hill",
    "sg:city":"London",
    "sg:classifiers":[
        {
            "category":"Food & Beverages",
            "subcategory":"Fruits & Vegetables",
            "type":"Retail Goods"
        }
    ],
    "sg:phone":"+44 20 8886 0322",
    "sg:postcode":"N13 4PP",
    "sg:province":"Greater London",
    "sg:tags":[
        "greengrocer"
    ],
    "wof:name":"Peters Fruiterers",
    "wof:placetype":"venue"
},
  "geometry": {"coordinates":[-0.112499997,51.6190261841],"type":"Point"}
}