{
  "type": "Feature",
  "properties": {
    "addr:full":"39 Carlisle Road Biggar Dumfries and Galloway ML12 6TP",
    "addr:housenumber":"39",
    "addr:postcode":"ml12 6tp",
    "addr:street":"Carlisle Road",
    "iso:country":"GB",
    "sg:address":"39 Carlisle Road",
    "sg:city":"Biggar",
    "sg:classifiers":[
        {
            "category":"Building & Trades",
            "subcategory":"Construction",
            "type":"Services"
        }
    ],
    "sg:postcode":"ML12 6TP",
    "sg:province":"Dumfries and Galloway",
    "sg:tags":[
        "joinery"
    ],
    "wof:name":"Pallet Recycling Services",
    "wof:placetype":"venue"
},
  "geometry": {"coordinates":[-3.6639609337,55.469329834],"type":"Point"}
}