{
  "type": "Feature",
  "properties": {
    "iso:country":"GB",
    "sg:address":"379 Cowley Road",
    "sg:city":"Oxford",
    "sg:classifiers":[
        {
            "category":"Retail",
            "subcategory":"Auto Repair",
            "type":"Services"
        }
    ],
    "sg:phone":"+44 1865 776760",
    "sg:postcode":"OX4 2BS",
    "sg:province":"Oxfordshire",
    "sg:tags":[
        "modification",
        "garage",
        "related"
    ],
    "wof:name":"French and Italian Car Centre",
    "wof:placetype":"venue"
},
  "geometry": {"coordinates":[-1.225131,51.741619],"type":"Point"}
}