{
  "type": "Feature",
  "properties": {
    "addr:full":"12 The Mall Bristol City of Bristol BS8 4DR",
    "addr:housenumber":"12",
    "addr:postcode":"bs8 4dr",
    "addr:street":"The Mall",
    "iso:country":"GB",
    "sg:address":"12 The Mall",
    "sg:city":"Bristol",
    "sg:classifiers":[
        {
            "category":"Professional",
            "subcategory":"Art Services",
            "type":"Services"
        }
    ],
    "sg:phone":"+44 117 973 7865",
    "sg:postcode":"BS8 4DR",
    "sg:province":"City of Bristol",
    "sg:tags":[
        "consultant",
        "design"
    ],
    "wof:name":"Design Emporium",
    "wof:placetype":"venue"
},
  "geometry": {"coordinates":[-2.6204929352,51.454864502],"type":"Point"}
}