{
  "type": "Feature",
  "properties": {
    "addr:full":"Budlake Road, Marsh Barton Trading Estate Exeter Devon EX2 8PY",
    "addr:housenumber":"trading estate",
    "addr:postcode":"ex2 8py",
    "addr:street":"Budlake Road",
    "iso:country":"GB",
    "sg:address":"Budlake Road, Marsh Barton Trading Estate",
    "sg:city":"Exeter",
    "sg:classifiers":[
        {
            "category":"Autos & Motor Vehicles",
            "subcategory":"Recreational Vehicle Sales",
            "type":"Retail Goods"
        },
        {
            "category":"Retail",
            "subcategory":"Auto Repair",
            "type":"Services"
        }
    ],
    "sg:phone":"+44 1392 435455",
    "sg:postcode":"EX2 8PY",
    "sg:province":"Devon",
    "sg:tags":[
        "truck",
        "repairer",
        "van",
        "bodybuilder"
    ],
    "wof:name":"Hill's Bodyworks Ltd.",
    "wof:placetype":"venue"
},
  "geometry": {"coordinates":[-3.526638031,50.7008590698],"type":"Point"}
}