{
  "type": "Feature",
  "properties": {
    "iso:country":"GB",
    "sg:address":"14-15 Ladford Covert, Seighford",
    "sg:city":"Stafford",
    "sg:classifiers":[
        {
            "category":"Military Area",
            "subcategory":"Air Force Base",
            "type":"Public Place"
        }
    ],
    "sg:phone":"+44 1785 282088",
    "sg:postcode":"ST18 9QG",
    "sg:province":"Staffordshire",
    "sg:tags":[
        "water",
        "treatment"
    ],
    "wof:name":"Abacus Water Treatment Ltd.",
    "wof:placetype":"venue"
},
  "geometry": {"coordinates":[-2.166856,52.808376],"type":"Point"}
}