{
  "type": "Feature",
  "properties": {
    "addr:full":"37 Harden Drive, Harwood Bolton Lancashire BL2 5BX",
    "addr:housenumber":"37",
    "addr:postcode":"bl2 5bx",
    "addr:street":"Harden Drive",
    "iso:country":"GB",
    "sg:address":"37 Harden Drive, Harwood",
    "sg:city":"Bolton",
    "sg:classifiers":[
        {
            "category":"Home & Garden",
            "subcategory":"Household Appliances",
            "type":"Retail Goods"
        }
    ],
    "sg:phone":"+44 1204 526844",
    "sg:postcode":"BL2 5BX",
    "sg:province":"Lancashire",
    "sg:tags":[
        "electrical"
    ],
    "wof:name":"Atlas Refrigeration",
    "wof:placetype":"venue"
},
  "geometry": {"coordinates":[-2.3956859112,53.5920791626],"type":"Point"}
}