{
  "type": "Feature",
  "properties": {
    "iso:country":"GB",
    "sg:address":"127 Poole Road",
    "sg:city":"Bournemouth",
    "sg:classifiers":[
        {
            "category":"Restaurant",
            "type":"Food & Drink"
        }
    ],
    "sg:phone":"+44 1202 761317",
    "sg:postcode":"BH4 9BG",
    "sg:province":"Dorset",
    "sg:tags":[
        "italian"
    ],
    "wof:name":"la Bettola",
    "wof:placetype":"venue"
},
  "geometry": {"coordinates":[-1.905554,50.723442],"type":"Point"}
}