{
  "type": "Feature",
  "properties": {
    "iso:country":"GB",
    "sg:address":"5-10 Munro House",
    "sg:city":"Leeds",
    "sg:classifiers":[
        {
            "category":"Professional",
            "subcategory":"Credit Reporting & Collection",
            "type":"Services"
        }
    ],
    "sg:postcode":"LS9 8AG",
    "sg:province":"West Yorkshire",
    "sg:tags":[
        "collecting",
        "agency"
    ],
    "wof:name":"Able Business Centre Ltd.",
    "wof:placetype":"venue"
},
  "geometry": {"coordinates":[-1.53392,53.79678],"type":"Point"}
}