{
  "type": "Feature",
  "properties": {
    "addr:full":"26 High Street Northallerton North Yorkshire DL7 8EE",
    "addr:housenumber":"26",
    "addr:postcode":"dl7 8ee",
    "addr:street":"High Street",
    "iso:country":"GB",
    "sg:address":"26 High Street",
    "sg:city":"Northallerton",
    "sg:classifiers":[
        {
            "category":"Farming",
            "subcategory":"Nursery",
            "type":"Manufacturing & Wholesale Goods"
        }
    ],
    "sg:postcode":"DL7 8EE",
    "sg:province":"North Yorkshire",
    "sg:tags":[
        "creche"
    ],
    "wof:name":"E Bell",
    "wof:placetype":"venue"
},
  "geometry": {"coordinates":[-1.438273,54.344662],"type":"Point"}
}