{
  "type": "Feature",
  "properties": {
    "addr:full":"4 Market Square Flint Flintshire CH6 5NW",
    "addr:housenumber":"4",
    "addr:postcode":"ch6 5nw",
    "addr:street":"Market Square",
    "iso:country":"GB",
    "sg:address":"4 Market Square",
    "sg:city":"Flint",
    "sg:classifiers":[
        {
            "category":"Fast Food",
            "type":"Food & Drink"
        },
        {
            "category":"Food & Beverages",
            "subcategory":"Meat & Fish",
            "type":"Retail Goods"
        }
    ],
    "sg:postcode":"CH6 5NW",
    "sg:province":"Flintshire",
    "sg:tags":[
        "chip",
        "away",
        "take"
    ],
    "wof:name":"The C Nicolaides Fry Inn",
    "wof:placetype":"venue"
},
  "geometry": {"coordinates":[-3.133659,53.25021],"type":"Point"}
}