{
  "type": "Feature",
  "properties": {
    "addr:full":"45 Sycamore Road, Brookhouse Lancaster Lancashire LA2 9PE",
    "addr:housenumber":"45",
    "addr:postcode":"la2 9pe",
    "addr:street":"Sycamore Road",
    "iso:country":"GB",
    "sg:address":"45 Sycamore Road, Brookhouse",
    "sg:city":"Lancaster",
    "sg:classifiers":[
        {
            "category":"Real Estate",
            "subcategory":"Real Estate Services",
            "type":"Services"
        },
        {
            "category":"Retail",
            "subcategory":"Funeral Services",
            "type":"Services"
        },
        {
            "category":"Building & Trades",
            "subcategory":"Equipment Rental",
            "type":"Services"
        }
    ],
    "sg:phone":"+44 1524 770674",
    "sg:postcode":"LA2 9PE",
    "sg:province":"Lancashire",
    "sg:tags":[
        "hire",
        "leasing",
        "cemetery",
        "plant",
        "crematorium",
        "machinery"
    ],
    "sg:website":"http://www.jdlawson.co.uk",
    "wof:name":"John D Lawson",
    "wof:placetype":"venue"
},
  "geometry": {"coordinates":[-2.707162,54.07518],"type":"Point"}
}