{
  "type": "Feature",
  "properties": {
    "iso:country":"GB",
    "sg:address":"Wisbech Road, Walpole St Andrew",
    "sg:city":"Wisbech",
    "sg:classifiers":[
        {
            "category":"Farming",
            "subcategory":"Farm",
            "type":"Manufacturing & Wholesale Goods"
        }
    ],
    "sg:phone":"+44 1945 780356",
    "sg:postcode":"PE14 7LH",
    "sg:province":"Cambridgeshire",
    "sg:tags":[
        "mixed",
        "crop"
    ],
    "wof:name":"Cherry Tree Farm",
    "wof:placetype":"venue"
},
  "geometry": {"coordinates":[0.174684,52.683903],"type":"Point"}
}