{
  "type": "Feature",
  "properties": {
    "addr:full":"16 Market Street Huddersfield West Yorkshire HD1 2ET",
    "addr:housenumber":"16",
    "addr:postcode":"hd1 2et",
    "addr:street":"Market Street",
    "iso:country":"GB",
    "sg:address":"16 Market Street",
    "sg:city":"Huddersfield",
    "sg:classifiers":[
        {
            "category":"Shopping",
            "subcategory":"Hobbies, Toys, & Games",
            "type":"Retail Goods"
        }
    ],
    "sg:phone":"+44 1484 544664",
    "sg:postcode":"HD1 2ET",
    "sg:province":"West Yorkshire",
    "sg:tags":[
        "shop",
        "toy"
    ],
    "wof:name":"Toymaster Superstore",
    "wof:placetype":"venue"
},
  "geometry": {"coordinates":[-1.784428,53.646263],"type":"Point"}
}