{
  "type": "Feature",
  "properties": {
    "iso:country":"GB",
    "sg:address":"Unit 1 & 5 Watlington Industrial Estate",
    "sg:city":"Watlington",
    "sg:classifiers":[
        {
            "category":"Professional",
            "subcategory":"Business Services",
            "type":"Services"
        }
    ],
    "sg:phone":"+44 1491 612790",
    "sg:postcode":"OX49 5LU",
    "sg:province":"Oxfordshire",
    "sg:tags":[
        "distribution"
    ],
    "wof:name":"H & H General Carriers (Oxford) Ltd.",
    "wof:placetype":"venue"
},
  "geometry": {"coordinates":[-0.990006,51.658249],"type":"Point"}
}