{
  "type": "Feature",
  "properties": {
    "addr:full":"133 Pearce Way Gloucester Gloucestershire GL2 5YD",
    "addr:housenumber":"133",
    "addr:postcode":"gl2 5yd",
    "addr:street":"Pearce Way",
    "iso:country":"GB",
    "sg:address":"133 Pearce Way",
    "sg:city":"Gloucester",
    "sg:classifiers":[
        {
            "category":"Professional",
            "type":"Services"
        }
    ],
    "sg:phone":"+44 1452 524281",
    "sg:postcode":"GL2 5YD",
    "sg:province":"Gloucestershire",
    "sg:tags":[
        "caterer"
    ],
    "wof:name":"Glevum Auto Trade Ltd.",
    "wof:placetype":"venue"
},
  "geometry": {"coordinates":[-2.2651879787,51.8402557373],"type":"Point"}
}