{
  "type": "Feature",
  "properties": {
    "addr:full":"165 Queen Victoria Street London Greater London EC4V 4DD",
    "addr:housenumber":"165",
    "addr:postcode":"ec4v 4dd",
    "addr:street":"Queen Victoria Street",
    "iso:country":"GB",
    "sg:address":"165 Queen Victoria Street",
    "sg:city":"London",
    "sg:classifiers":[
        {
            "category":"Professional",
            "subcategory":"Management & Consulting",
            "type":"Services"
        }
    ],
    "sg:postcode":"EC4V 4DD",
    "sg:province":"Greater London",
    "sg:tags":[
        "consultant",
        "business"
    ],
    "wof:name":"Usertech Uk Ltd",
    "wof:placetype":"venue"
},
  "geometry": {"coordinates":[-0.1032840014,51.5118980408],"type":"Point"}
}