{
  "type": "Feature",
  "properties": {
    "addr:full":"Second Floor Regatta House, Clippers Quay Salford Greater Manchester M5 2XP",
    "addr:housenumber":"second",
    "addr:postcode":"m5 2xp",
    "addr:street":"Clippers Quay",
    "iso:country":"GB",
    "sg:address":"Second Floor Regatta House, Clippers Quay",
    "sg:city":"Salford",
    "sg:classifiers":[
        {
            "category":"Real Estate",
            "subcategory":"Surveying",
            "type":"Services"
        },
        {
            "category":"Building & Trades",
            "subcategory":"Construction",
            "type":"Services"
        }
    ],
    "sg:phone":"+44 161 877 8577",
    "sg:postcode":"M5 2XP",
    "sg:province":"Greater Manchester",
    "sg:tags":[
        "surveyor",
        "management",
        "quantity"
    ],
    "wof:name":"Turner & Townsend Project Management Ltd.",
    "wof:placetype":"venue"
},
  "geometry": {"coordinates":[-2.285378,53.467319],"type":"Point"}
}