{
  "type": "Feature",
  "properties": {
    "iso:country":"GB",
    "sg:address":"C/o Miller & Co, 86 Princess Street",
    "sg:city":"Luton",
    "sg:classifiers":[
        {
            "category":"Organizations",
            "subcategory":"Membership Organization",
            "type":"Services"
        }
    ],
    "sg:postcode":"LU1 5AT",
    "sg:province":"Bedfordshire",
    "sg:tags":[
        "club"
    ],
    "wof:name":"Holland Court Management (Luton) Limited",
    "wof:placetype":"venue"
},
  "geometry": {"coordinates":[-0.4214000106,51.8771514893],"type":"Point"}
}