{
  "type": "Feature",
  "properties": {
    "iso:country":"GB",
    "sg:address":"Kinderton Lodge Farm, Holmes Chapel Rd",
    "sg:city":"Middlewich",
    "sg:classifiers":[
        {
            "category":"Building & Trades",
            "subcategory":"Cleaning & Sanitation",
            "type":"Services"
        }
    ],
    "sg:postcode":"CW10 0JB",
    "sg:province":"Cheshire",
    "sg:tags":[
        "blast"
    ],
    "wof:name":"Mid Cheshire Blast",
    "wof:placetype":"venue"
},
  "geometry": {"coordinates":[-2.453134,53.192299],"type":"Point"}
}