{
  "type": "Feature",
  "properties": {
    "addr:full":"The Community Centreclays Lanestratfor London Greater London E15 2HJ",
    "addr:postcode":"e15 2hj",
    "iso:country":"GB",
    "sg:address":"The Community Centreclays Lanestratfor",
    "sg:city":"London",
    "sg:classifiers":[
        {
            "category":"Real Estate",
            "subcategory":"Real Estate Operator",
            "type":"Services"
        }
    ],
    "sg:postcode":"E15 2HJ",
    "sg:province":"Greater London",
    "sg:tags":[
        "letting",
        "agent"
    ],
    "wof:name":"Clays Lane Housing Co-Operative Ltd",
    "wof:placetype":"venue"
},
  "geometry": {"coordinates":[-0.01067,51.54958],"type":"Point"}
}