{
  "type": "Feature",
  "properties": {
    "iso:country":"GB",
    "sg:address":"15 Heathfield",
    "sg:city":"Chorley",
    "sg:classifiers":[
        {
            "category":"Government",
            "subcategory":"Office",
            "type":"Public Place"
        }
    ],
    "sg:phone":"+44 1257 480157",
    "sg:postcode":"PR6 9LA",
    "sg:province":"Lancashire",
    "sg:tags":[
        "local"
    ],
    "wof:name":"Heathfield Sheltered Housing",
    "wof:placetype":"venue"
},
  "geometry": {"coordinates":[-2.601639,53.629749],"type":"Point"}
}