{
  "type": "Feature",
  "properties": {
    "iso:country":"GB",
    "sg:address":"193 Elliott St, Tyldesley",
    "sg:city":"Manchester",
    "sg:classifiers":[
        {
            "category":"Cafe",
            "type":"Food & Drink"
        }
    ],
    "sg:phone":"+44 1942 888474",
    "sg:postcode":"M29 8DR",
    "sg:province":"Greater Manchester",
    "sg:tags":[
        "tea",
        "room"
    ],
    "wof:name":"Jo's Cafe",
    "wof:placetype":"venue"
},
  "geometry": {"coordinates":[-2.466025,53.514168],"type":"Point"}
}