{
  "type": "Feature",
  "properties": {
    "iso:country":"GB",
    "sg:address":"18 Shepherds House Lane, Earley",
    "sg:city":"Reading",
    "sg:classifiers":[
        {
            "category":"Professional",
            "type":"Services"
        }
    ],
    "sg:phone":"+44 118 966 6482",
    "sg:postcode":"RG6 1AD",
    "sg:province":"Berkshire",
    "sg:tags":[
        "interior",
        "furnishers",
        "designer"
    ],
    "wof:name":"P.P Watt",
    "wof:placetype":"venue"
},
  "geometry": {"coordinates":[-0.93251,51.457516],"type":"Point"}
}