{
  "type": "Feature",
  "properties": {
    "addr:full":"29 Pine Gro London Greater London SW19 7HD",
    "addr:housenumber":"29",
    "addr:postcode":"sw19 7hd",
    "addr:street":"Pine Gro",
    "iso:country":"GB",
    "sg:address":"29 Pine Gro",
    "sg:city":"London",
    "sg:classifiers":[
        {
            "category":"Food & Beverages",
            "subcategory":"Meat & Fish",
            "type":"Retail Goods"
        }
    ],
    "sg:postcode":"SW19 7HD",
    "sg:province":"Greater London",
    "sg:tags":[
        "merchant"
    ],
    "wof:name":"Robinson Fisheries",
    "wof:placetype":"venue"
},
  "geometry": {"coordinates":[-0.2092519999,51.4254112244],"type":"Point"}
}