{
  "type": "Feature",
  "properties": {
    "addr:full":"219-221 Derby Road, Stapleford Nottingham Nottinghamshire NG9 7AZ",
    "addr:housenumber":"219-221",
    "addr:postcode":"ng9 7az",
    "addr:street":"Derby Road",
    "iso:country":"GB",
    "sg:address":"219-221 Derby Road, Stapleford",
    "sg:city":"Nottingham",
    "sg:classifiers":[
        {
            "category":"Home & Garden",
            "subcategory":"Household Appliances",
            "type":"Retail Goods"
        }
    ],
    "sg:postcode":"NG9 7AZ",
    "sg:province":"Nottinghamshire",
    "sg:tags":[
        "electrical"
    ],
    "wof:name":"Sandiacre Domestic Appliances",
    "wof:placetype":"venue"
},
  "geometry": {"coordinates":[-1.28072,52.923851],"type":"Point"}
}