{
  "type": "Feature",
  "properties": {
    "addr:full":"Fallings Park Childrens Day Centre, 22 Helenny Clo Wolverhampton Staffordshire WV11 1SN",
    "addr:housenumber":"22",
    "addr:postcode":"wv11 1sn",
    "addr:street":"Helenny Clo",
    "iso:country":"GB",
    "sg:address":"Fallings Park Childrens Day Centre, 22 Helenny Clo",
    "sg:city":"Wolverhampton",
    "sg:classifiers":[
        {
            "category":"Government",
            "subcategory":"Office",
            "type":"Public Place"
        }
    ],
    "sg:phone":"+44 1902 553285",
    "sg:postcode":"WV11 1SN",
    "sg:province":"Staffordshire",
    "sg:tags":[
        "local"
    ],
    "wof:name":"Wolverhampton Borough Council",
    "wof:placetype":"venue"
},
  "geometry": {"coordinates":[-2.121669,52.58865],"type":"Point"}
}