{
  "type": "Feature",
  "properties": {
    "iso:country":"GB",
    "sg:address":"48 Kirkfield Rise",
    "sg:city":"Ambleside",
    "sg:classifiers":[
        {
            "category":"Building & Trades",
            "subcategory":"Construction",
            "type":"Services"
        }
    ],
    "sg:postcode":"LA22 9DX",
    "sg:province":"Cumbria",
    "sg:tags":[
        "joiner",
        "carpenter"
    ],
    "wof:name":"White,P,",
    "wof:placetype":"venue"
},
  "geometry": {"coordinates":[-2.958445,54.435715],"type":"Point"}
}