{
  "type": "Feature",
  "properties": {
    "iso:country":"GB",
    "sg:address":"The Railway House, The Street, West Horsley",
    "sg:city":"Leatherhead",
    "sg:classifiers":[
        {
            "category":"Professional",
            "subcategory":"Management & Consulting",
            "type":"Services"
        }
    ],
    "sg:phone":"+44 1483 281291",
    "sg:postcode":"KT24 6HP",
    "sg:province":"Surrey",
    "sg:tags":[
        "marketing",
        "consultant"
    ],
    "wof:name":"Y",
    "wof:placetype":"venue"
},
  "geometry": {"coordinates":[-0.450717,51.273994],"type":"Point"}
}