{
  "type": "Feature",
  "properties": {
    "addr:full":"223 Marine Road Morecambe Lancashire LA4 4BQ",
    "addr:housenumber":"223",
    "addr:postcode":"la4 4bq",
    "addr:street":"Marine Road",
    "iso:country":"GB",
    "sg:address":"223 Marine Road",
    "sg:city":"Morecambe",
    "sg:classifiers":[
        {
            "category":"Restaurant",
            "type":"Food & Drink"
        }
    ],
    "sg:phone":"+44 1524 412772",
    "sg:postcode":"LA4 4BQ",
    "sg:province":"Lancashire",
    "wof:name":"Fletcher's Restaurant",
    "wof:placetype":"venue"
},
  "geometry": {"coordinates":[-2.870129,54.072521],"type":"Point"}
}