{
  "type": "Feature",
  "properties": {
    "addr:full":"35 Piccadilly London Greater London W1V 9PB",
    "addr:housenumber":"35",
    "addr:postcode":"w1v 9pb",
    "addr:street":"Piccadilly",
    "iso:country":"GB",
    "sg:address":"35 Piccadilly",
    "sg:city":"London",
    "sg:classifiers":[
        {
            "category":"Banks & Credit Unions",
            "subcategory":"Financial Services",
            "type":"Services"
        }
    ],
    "sg:postcode":"W1V 9PB",
    "sg:province":"Greater London",
    "sg:tags":[
        "consultant"
    ],
    "wof:name":"M & A Financial Services Ltd.",
    "wof:placetype":"venue"
},
  "geometry": {"coordinates":[-0.137038,51.509029],"type":"Point"}
}