{
  "type": "Feature",
  "properties": {
    "addr:full":"64 Bolton Street Brixham Devon TQ5 9DH",
    "addr:housenumber":"64",
    "addr:postcode":"tq5 9dh",
    "addr:street":"Bolton Street",
    "iso:country":"GB",
    "sg:address":"64 Bolton Street",
    "sg:city":"Brixham",
    "sg:classifiers":[
        {
            "category":"Food & Beverages",
            "subcategory":"Meat & Fish",
            "type":"Retail Goods"
        }
    ],
    "sg:postcode":"TQ5 9DH",
    "sg:province":"Devon",
    "sg:tags":[
        "chip"
    ],
    "wof:name":"David's Fish & Chips",
    "wof:placetype":"venue"
},
  "geometry": {"coordinates":[-3.5145521164,50.3913726807],"type":"Point"}
}