{
  "type": "Feature",
  "properties": {
    "addr:full":"111 Botley Road Oxford Oxfordshire OX2 0LF",
    "addr:housenumber":"111",
    "addr:postcode":"ox2 0lf",
    "addr:street":"Botley Road",
    "iso:country":"GB",
    "sg:address":"111 Botley Road",
    "sg:city":"Oxford",
    "sg:classifiers":[
        {
            "category":"Retail",
            "subcategory":"Veterinary Services",
            "type":"Services"
        }
    ],
    "sg:phone":"+44 1865 243225",
    "sg:postcode":"OX2 0LF",
    "sg:province":"Oxfordshire",
    "sg:tags":[
        "surgeon"
    ],
    "wof:name":"The Beaumont Veterinary Hospital",
    "wof:placetype":"venue"
},
  "geometry": {"coordinates":[-1.281457,51.75243],"type":"Point"}
}