{
  "type": "Feature",
  "properties": {
    "iso:country":"GB",
    "sg:address":"Unit 1c Thirsk Industrial Park, Severfield Clo",
    "sg:city":"Thirsk",
    "sg:classifiers":[
        {
            "category":"Autos & Motor Vehicles",
            "subcategory":"Auto Supplies",
            "type":"Retail Goods"
        }
    ],
    "sg:phone":"+44 1845 524784",
    "sg:postcode":"YO7 3BX",
    "sg:province":"North Yorkshire",
    "sg:tags":[
        "tyre"
    ],
    "wof:name":"Bobs Tyres & Batteries",
    "wof:placetype":"venue"
},
  "geometry": {"coordinates":[-1.328619,54.231419],"type":"Point"}
}