{
  "type": "Feature",
  "properties": {
    "addr:full":"19 Stanbury Avenue Bristol City of Bristol BS16 5AL",
    "addr:housenumber":"19",
    "addr:postcode":"bs16 5al",
    "addr:street":"Stanbury Avenue",
    "iso:country":"GB",
    "sg:address":"19 Stanbury Avenue",
    "sg:city":"Bristol",
    "sg:classifiers":[
        {
            "category":"Professional",
            "type":"Services"
        }
    ],
    "sg:postcode":"BS16 5AL",
    "sg:province":"City of Bristol",
    "sg:tags":[
        "caterer"
    ],
    "wof:name":"Griffin Quality Catering",
    "wof:placetype":"venue"
},
  "geometry": {"coordinates":[-2.5196819305,51.4824180603],"type":"Point"}
}