{
  "type": "Feature",
  "properties": {
    "iso:country":"GB",
    "sg:address":"69 Shakespeare Drive, Shirley",
    "sg:city":"Solihull",
    "sg:classifiers":[
        {
            "category":"Professional",
            "subcategory":"Art Services",
            "type":"Services"
        },
        {
            "category":"Building & Trades",
            "subcategory":"Construction",
            "type":"Services"
        }
    ],
    "sg:phone":"+44 121 744 1125",
    "sg:postcode":"B90 2AN",
    "sg:province":"West Midlands",
    "sg:tags":[
        "decorator",
        "painter"
    ],
    "wof:name":"Modern Painting Contractors",
    "wof:placetype":"venue"
},
  "geometry": {"coordinates":[-1.82696,52.40115],"type":"Point"}
}