{
  "type": "Feature",
  "properties": {
    "addr:full":"Blackberry House, Berghers Hill High Wycombe Buckinghamshire HP10 0JP",
    "addr:postcode":"hp10 0jp",
    "addr:street":"Berghers Hill",
    "iso:country":"GB",
    "sg:address":"Blackberry House, Berghers Hill",
    "sg:city":"High Wycombe",
    "sg:classifiers":[
        {
            "category":"Professional",
            "subcategory":"Management & Consulting",
            "type":"Services"
        }
    ],
    "sg:postcode":"HP10 0JP",
    "sg:province":"Buckinghamshire",
    "sg:tags":[
        "consultant",
        "business"
    ],
    "wof:name":"Fellows Associates Ltd.",
    "wof:placetype":"venue"
},
  "geometry": {"coordinates":[-0.6750169992,51.5805244446],"type":"Point"}
}