{
  "type": "Feature",
  "properties": {
    "addr:full":"Bucknall Garage, Pennell Street Stoke-on-trent Staffordshire ST2 9BD",
    "addr:postcode":"st2 9bd",
    "addr:street":"Pennell Street",
    "iso:country":"GB",
    "sg:address":"Bucknall Garage, Pennell Street",
    "sg:city":"Stoke-on-trent",
    "sg:classifiers":[
        {
            "category":"Bus Charters",
            "type":"Transportation"
        }
    ],
    "sg:phone":"+44 1782 213832",
    "sg:postcode":"ST2 9BD",
    "sg:province":"Staffordshire",
    "sg:tags":[
        "hire",
        "coach"
    ],
    "wof:name":"Scraggs Coaches",
    "wof:placetype":"venue"
},
  "geometry": {"coordinates":[-2.1398599148,53.0246391296],"type":"Point"}
}