{
  "type": "Feature",
  "properties": {
    "iso:country":"GB",
    "sg:address":"Caxton Clo, Drayton Field Indust Est",
    "sg:city":"Daventry",
    "sg:classifiers":[
        {
            "category":"Professional",
            "subcategory":"Management & Consulting",
            "type":"Services"
        }
    ],
    "sg:phone":"+44 1327 876080",
    "sg:postcode":"NN11 5RT",
    "sg:province":"Northamptonshire",
    "sg:tags":[
        "consultant",
        "business"
    ],
    "wof:name":"Franklin Covey Europe",
    "wof:placetype":"venue"
},
  "geometry": {"coordinates":[-1.1804790497,52.2695083618],"type":"Point"}
}