{
  "type": "Feature",
  "properties": {
    "addr:full":"421 Ecclesall Road Sheffield Derbyshire S11 8PG",
    "addr:housenumber":"421",
    "addr:postcode":"s11 8pg",
    "addr:street":"Ecclesall Road",
    "iso:country":"GB",
    "sg:address":"421 Ecclesall Road",
    "sg:city":"Sheffield",
    "sg:classifiers":[
        {
            "category":"Shopping",
            "subcategory":"Pharmacy",
            "type":"Retail Goods"
        }
    ],
    "sg:phone":"+44 114 266 0976",
    "sg:postcode":"S11 8PG",
    "sg:province":"Derbyshire",
    "sg:tags":[
        "pharmacist",
        "chemist"
    ],
    "wof:name":"Peel Chemists",
    "wof:placetype":"venue"
},
  "geometry": {"coordinates":[-1.492452,53.370102],"type":"Point"}
}