{
  "type": "Feature",
  "properties": {
    "addr:full":"Flight Way, Dunkeswell Industrial Estate Honiton Devon EX14 4LN",
    "addr:postcode":"ex14 4ln",
    "addr:street":"Flight Way;Industrial Estate",
    "iso:country":"GB",
    "sg:address":"Flight Way, Dunkeswell Industrial Estate",
    "sg:city":"Honiton",
    "sg:classifiers":[
        {
            "category":"Education",
            "subcategory":"Music School",
            "type":"Public Place"
        },
        {
            "category":"Building & Trades",
            "subcategory":"Construction",
            "type":"Services"
        }
    ],
    "sg:phone":"+44 1404 891144",
    "sg:postcode":"EX14 4LN",
    "sg:province":"Devon",
    "sg:tags":[
        "conservatory",
        "glazing",
        "double",
        "window",
        "installers",
        "replacement"
    ],
    "wof:name":"Country Window Systems Ltd.",
    "wof:placetype":"venue"
},
  "geometry": {"coordinates":[-3.226680994,50.865234375],"type":"Point"}
}