{
  "type": "Feature",
  "properties": {
    "addr:full":"57 Broomhill Avenue Burntisland Fife KY3 0BP",
    "addr:housenumber":"57",
    "addr:postcode":"ky3 0bp",
    "addr:street":"Broomhill Avenue Burntisland",
    "iso:country":"GB",
    "sg:address":"57 Broomhill Avenue",
    "sg:city":"Burntisland",
    "sg:classifiers":[
        {
            "category":"Professional",
            "subcategory":"Art Services",
            "type":"Services"
        },
        {
            "category":"Building & Trades",
            "subcategory":"Construction",
            "type":"Services"
        },
        {
            "category":"Manufacturing",
            "subcategory":"Paper Products",
            "type":"Manufacturing & Wholesale Goods"
        }
    ],
    "sg:phone":"+44 1592 873195",
    "sg:postcode":"KY3 0BP",
    "sg:province":"Fife",
    "sg:tags":[
        "cardboard",
        "decorator",
        "painter"
    ],
    "wof:name":"ALEX SINCLAIR",
    "wof:placetype":"venue"
},
  "geometry": {"coordinates":[-3.234124,56.061749],"type":"Point"}
}