{
  "type": "Feature",
  "properties": {
    "addr:full":"41 Margaret Rd Barnsley South Yorkshire S73 9QF",
    "addr:housenumber":"41",
    "addr:postcode":"s73 9qf",
    "addr:street":"Margaret Rd;Yorkshire",
    "iso:country":"GB",
    "sg:address":"41 Margaret Rd",
    "sg:city":"Barnsley",
    "sg:classifiers":[
        {
            "category":"Military Area",
            "subcategory":"Air Force Base",
            "type":"Public Place"
        }
    ],
    "sg:phone":"+44 1226 341124",
    "sg:postcode":"S73 9QF",
    "sg:province":"South Yorkshire",
    "sg:tags":[
        "taxi",
        "hire",
        "private"
    ],
    "wof:name":"Chops Taxis",
    "wof:placetype":"venue"
},
  "geometry": {"coordinates":[-1.3863790035,53.5324745178],"type":"Point"}
}