{
  "type": "Feature",
  "properties": {
    "addr:full":"Kristin House, 5 Hyde Road Watford Hertfordshire WD17 4WA",
    "addr:housenumber":"5",
    "addr:postcode":"wd17 4wa",
    "addr:street":"Hyde Road",
    "iso:country":"GB",
    "sg:address":"Kristin House, 5 Hyde Road",
    "sg:city":"Watford",
    "sg:classifiers":[
        {
            "category":"Real Estate",
            "subcategory":"Architect",
            "type":"Services"
        }
    ],
    "sg:postcode":"WD17 4WA",
    "sg:province":"Hertfordshire",
    "wof:name":"Ashe (Leavesden) Limited",
    "wof:placetype":"venue"
},
  "geometry": {"coordinates":[-0.4047299922,51.6610488892],"type":"Point"}
}