{
  "type": "Feature",
  "properties": {
    "addr:full":"8 The Street, Radstock Bath Somerset BA3 3PL",
    "addr:housenumber":"8",
    "addr:postcode":"ba3 3pl",
    "addr:street":"The Street",
    "iso:country":"GB",
    "sg:address":"8 The Street, Radstock",
    "sg:city":"Bath",
    "sg:classifiers":[
        {
            "category":"Personal",
            "subcategory":"Beauty Salon",
            "type":"Services"
        }
    ],
    "sg:postcode":"BA3 3PL",
    "sg:province":"Somerset",
    "sg:tags":[
        "unisex",
        "hairdresser"
    ],
    "wof:name":"Harlequin",
    "wof:placetype":"venue"
},
  "geometry": {"coordinates":[-2.447542,51.291615],"type":"Point"}
}