{
  "type": "Feature",
  "properties": {
    "addr:full":"420 Upper Elmers End Road Beckenham Kent BR3 3HG",
    "addr:housenumber":"420",
    "addr:postcode":"br3 3hg",
    "addr:street":"Upper Elmers End Road",
    "iso:country":"GB",
    "sg:address":"420 Upper Elmers End Road",
    "sg:city":"Beckenham",
    "sg:classifiers":[
        {
            "category":"Autos & Motor Vehicles",
            "subcategory":"Auto Supplies",
            "type":"Retail Goods"
        }
    ],
    "sg:phone":"+44 20 8658 3738",
    "sg:postcode":"BR3 3HG",
    "sg:province":"Kent",
    "sg:tags":[
        "exhaust",
        "absorber",
        "shock"
    ],
    "wof:name":"Eden Park Tyres",
    "wof:placetype":"venue"
},
  "geometry": {"coordinates":[-0.027463,51.390255],"type":"Point"}
}