{
  "type": "Feature",
  "properties": {
    "iso:country":"GB",
    "sg:address":"Hindley Business Centre, Platt La, Hindley",
    "sg:city":"Wigan",
    "sg:classifiers":[
        {
            "category":"Professional",
            "subcategory":"Management & Consulting",
            "type":"Services"
        }
    ],
    "sg:postcode":"WN2 3PA",
    "sg:province":"Lancashire",
    "sg:tags":[
        "consultant",
        "safety"
    ],
    "wof:name":"Gas Safety Initiative(The)",
    "wof:placetype":"venue"
},
  "geometry": {"coordinates":[-2.5808238983,53.5336112976],"type":"Point"}
}