{
  "type": "Feature",
  "properties": {
    "iso:country":"GB",
    "sg:address":"Salterton Road",
    "sg:city":"Exmouth",
    "sg:classifiers":[
        {
            "category":"Home & Garden",
            "subcategory":"Building Materials",
            "type":"Retail Goods"
        },
        {
            "category":"Building & Trades",
            "subcategory":"Construction",
            "type":"Services"
        }
    ],
    "sg:phone":"+44 1395 263898",
    "sg:postcode":"EX8 2NS",
    "sg:province":"Devon",
    "sg:tags":[
        "furnishers",
        "builder",
        "planner",
        "bathroom"
    ],
    "wof:name":"Homes by Design",
    "wof:placetype":"venue"
},
  "geometry": {"coordinates":[-3.375697,50.630142],"type":"Point"}
}