{
  "type": "Feature",
  "properties": {
    "iso:country":"GB",
    "sg:address":"Woodbine Street",
    "sg:city":"Rochdale",
    "sg:classifiers":[
        {
            "category":"Building & Trades",
            "subcategory":"Construction",
            "type":"Services"
        }
    ],
    "sg:phone":"+44 1706 860155",
    "sg:postcode":"OL16 5JB",
    "sg:province":"Lancashire",
    "sg:tags":[
        "builder"
    ],
    "wof:name":"Rochdale & Manor (Builders)",
    "wof:placetype":"venue"
},
  "geometry": {"coordinates":[-2.146724,53.607281],"type":"Point"}
}