{
  "type": "Feature",
  "properties": {
    "addr:full":"1 Littledale Road, Wallasey Wirral Merseyside CH44 8EE",
    "addr:housenumber":"1",
    "addr:postcode":"ch44 8ee",
    "addr:street":"Littledale Road",
    "iso:country":"GB",
    "sg:address":"1 Littledale Road, Wallasey",
    "sg:city":"Wirral",
    "sg:classifiers":[
        {
            "category":"Real Estate",
            "subcategory":"Surveying",
            "type":"Services"
        }
    ],
    "sg:phone":"+44 151 630 7369",
    "sg:postcode":"CH44 8EE",
    "sg:province":"Merseyside",
    "sg:tags":[
        "building",
        "surveyor"
    ],
    "wof:name":"Pace Property Reports & Project Management Ltd.",
    "wof:placetype":"venue"
},
  "geometry": {"coordinates":[-3.024719,53.416451],"type":"Point"}
}