{
  "type": "Feature",
  "properties": {
    "addr:full":"Invicta House, Armstrong Road Maidstone Kent ME15 6TY",
    "addr:postcode":"me15 6ty",
    "addr:street":"Armstrong Road",
    "iso:country":"GB",
    "sg:address":"Invicta House, Armstrong Road",
    "sg:city":"Maidstone",
    "sg:classifiers":[
        {
            "category":"Bus Charters",
            "type":"Transportation"
        }
    ],
    "sg:phone":"+44 1622 697000",
    "sg:postcode":"ME15 6TY",
    "sg:province":"Kent",
    "sg:tags":[
        "coach"
    ],
    "wof:name":"Arriva Southern Counties Ltd.",
    "wof:placetype":"venue"
},
  "geometry": {"coordinates":[0.526275,51.261089],"type":"Point"}
}