{
  "type": "Feature",
  "properties": {
    "iso:country":"GB",
    "sg:address":"77 Park Avenue",
    "sg:city":"Abergavenny",
    "sg:classifiers":[
        {
            "category":"Building & Trades",
            "subcategory":"Construction",
            "type":"Services"
        }
    ],
    "sg:phone":"+44 1873 854198",
    "sg:postcode":"NP7 5SP",
    "sg:province":"Herefordshire",
    "sg:tags":[
        "monumental",
        "mason"
    ],
    "wof:name":"W O Bevan",
    "wof:placetype":"venue"
},
  "geometry": {"coordinates":[-3.013048,51.827507],"type":"Point"}
}