{
  "type": "Feature",
  "properties": {
    "addr:full":"New Bungalow, Station Road, Johnshaven Montrose Aberdeenshire DD10 0HQ",
    "addr:postcode":"dd10 0hq",
    "addr:street":"Station Road Johnshaven",
    "iso:country":"GB",
    "sg:address":"New Bungalow, Station Road, Johnshaven",
    "sg:city":"Montrose",
    "sg:classifiers":[
        {
            "category":"Building & Trades",
            "subcategory":"Construction",
            "type":"Services"
        }
    ],
    "sg:postcode":"DD10 0HQ",
    "sg:province":"Aberdeenshire",
    "sg:tags":[
        "joiner",
        "carpenter"
    ],
    "wof:name":"Michael Sangster",
    "wof:placetype":"venue"
},
  "geometry": {"coordinates":[-2.3301279545,56.8019294739],"type":"Point"}
}