{
  "type": "Feature",
  "properties": {
    "addr:full":"201 Talgarth Rd Hammersmith Greater London W6 8BN",
    "addr:housenumber":"201",
    "addr:postcode":"w6 8bn",
    "addr:street":"Talgarth Rd",
    "iso:country":"GB",
    "sg:address":"201 Talgarth Rd",
    "sg:city":"Hammersmith",
    "sg:classifiers":[
        {
            "category":"Community Center",
            "type":"Public Place"
        }
    ],
    "sg:phone":"+44 20 8250 1197",
    "sg:postcode":"W6 8BN",
    "sg:province":"Greater London",
    "sg:tags":[
        "recreation",
        "leisure",
        "centre"
    ],
    "wof:name":"Universal Studios Florida",
    "wof:placetype":"venue"
},
  "geometry": {"coordinates":[-0.2224189937,51.4913406372],"type":"Point"}
}