{
  "type": "Feature",
  "properties": {
    "addr:full":"15 Cuthbert Rd Inverness Highland IV2 3RU",
    "addr:housenumber":"15",
    "addr:postcode":"iv2 3ru",
    "addr:street":"Cuthbert Rd",
    "iso:country":"GB",
    "sg:address":"15 Cuthbert Rd",
    "sg:city":"Inverness",
    "sg:classifiers":[
        {
            "category":"Organizations",
            "subcategory":"Political Organization",
            "type":"Services"
        }
    ],
    "sg:phone":"+44 1463 713663",
    "sg:postcode":"IV2 3RU",
    "sg:province":"Highland",
    "sg:tags":[
        "party"
    ],
    "wof:name":"The Highland Green Party",
    "wof:placetype":"venue"
},
  "geometry": {"coordinates":[-4.1961722374,57.4706916809],"type":"Point"}
}