{
  "type": "Feature",
  "properties": {
    "iso:country":"GB",
    "sg:address":"75 High Street",
    "sg:city":"Banchory",
    "sg:classifiers":[
        {
            "category":"Health Services",
            "subcategory":"Dentist",
            "type":"Services"
        }
    ],
    "sg:phone":"+44 1330 822788",
    "sg:postcode":"AB31 5TJ",
    "sg:province":"Aberdeen City",
    "wof:name":"R H Bain",
    "wof:placetype":"venue"
},
  "geometry": {"coordinates":[-2.502674,57.051388],"type":"Point"}
}