{
  "type": "Feature",
  "properties": {
    "iso:country":"GB",
    "sg:address":"Unit 5 Craven St",
    "sg:city":"Birkenhead",
    "sg:classifiers":[
        {
            "category":"Manufacturing",
            "subcategory":"Petroleum Products",
            "type":"Manufacturing & Wholesale Goods"
        }
    ],
    "sg:phone":"+44 151 666 1223",
    "sg:postcode":"L41 4BR",
    "sg:province":"Merseyside",
    "sg:tags":[
        "double",
        "glazing"
    ],
    "wof:name":"Wholesale Windows",
    "wof:placetype":"venue"
},
  "geometry": {"coordinates":[-3.031614,53.393147],"type":"Point"}
}