{
  "type": "Feature",
  "properties": {
    "iso:country":"GB",
    "sg:address":"49 Todmorden Road",
    "sg:city":"Burnley",
    "sg:classifiers":[
        {
            "category":"Bars & Pubs",
            "type":"Food & Drink"
        }
    ],
    "sg:postcode":"BB10 4AB",
    "sg:province":"Lancashire",
    "sg:tags":[
        "pubs",
        "inn"
    ],
    "wof:name":"Paramount Plc",
    "wof:placetype":"venue"
},
  "geometry": {"coordinates":[-2.232742,53.786732],"type":"Point"}
}