{
  "type": "Feature",
  "properties": {
    "addr:full":"32 Wicker Sheffield South Yorkshire S3 8JB",
    "addr:housenumber":"32",
    "addr:postcode":"s3 8jb",
    "addr:street":"Wicker Sheffield South",
    "iso:country":"GB",
    "sg:address":"32 Wicker",
    "sg:city":"Sheffield",
    "sg:classifiers":[
        {
            "category":"Shopping",
            "subcategory":"Music",
            "type":"Retail Goods"
        }
    ],
    "sg:postcode":"S3 8JB",
    "sg:province":"South Yorkshire",
    "sg:tags":[
        "record",
        "tape",
        "cd"
    ],
    "wof:name":"Kenny's Records",
    "wof:placetype":"venue"
},
  "geometry": {"coordinates":[-1.463113,53.386471],"type":"Point"}
}