{
  "type": "Feature",
  "properties": {
    "iso:country":"GB",
    "sg:address":"Erindale",
    "sg:city":"London",
    "sg:classifiers":[
        {
            "category":"Education",
            "subcategory":"Library",
            "type":"Public Place"
        },
        {
            "category":"Government",
            "subcategory":"Office",
            "type":"Public Place"
        }
    ],
    "sg:phone":"+44 20 8854 7900",
    "sg:postcode":"SE18 2QQ",
    "sg:province":"Greater London",
    "sg:tags":[
        "book",
        "local"
    ],
    "wof:name":"Slade Library",
    "wof:placetype":"venue"
},
  "geometry": {"coordinates":[0.085782,51.479137],"type":"Point"}
}