{
  "type": "Feature",
  "properties": {
    "iso:country":"GB",
    "sg:address":"9 Market Square, Kirby Lonsdale",
    "sg:city":"Carnforth",
    "sg:classifiers":[
        {
            "category":"Shopping",
            "subcategory":"Department Store",
            "type":"Retail Goods"
        }
    ],
    "sg:phone":"+44 15242 71289",
    "sg:postcode":"LA6 2AN",
    "sg:province":"Cumbria",
    "wof:name":"K & M Harrison",
    "wof:placetype":"venue"
},
  "geometry": {"coordinates":[-2.5961329937,54.2019691467],"type":"Point"}
}