{
  "type": "Feature",
  "properties": {
    "addr:full":"59 Auckland Rd Kingston-upon-thames Greater London KT1 3BQ",
    "addr:housenumber":"59",
    "addr:postcode":"kt1 3bq",
    "addr:street":"Auckland Rd",
    "iso:country":"GB",
    "sg:address":"59 Auckland Rd",
    "sg:city":"Kingston-upon-thames",
    "sg:classifiers":[
        {
            "category":"Home & Garden",
            "subcategory":"Household Appliances",
            "type":"Retail Goods"
        }
    ],
    "sg:phone":"+44 20 8547 3945",
    "sg:postcode":"KT1 3BQ",
    "sg:province":"Greater London",
    "sg:tags":[
        "electrical"
    ],
    "wof:name":"Green Machine Ltd",
    "wof:placetype":"venue"
},
  "geometry": {"coordinates":[-0.2938010097,51.4018249512],"type":"Point"}
}