{
  "type": "Feature",
  "properties": {
    "addr:full":"The Grange, Swan Road, Worlingworth Woodbridge Suffolk IP13 7HZ",
    "addr:postcode":"ip13 7hz",
    "addr:street":"Swan Road",
    "iso:country":"GB",
    "sg:address":"The Grange, Swan Road, Worlingworth",
    "sg:city":"Woodbridge",
    "sg:classifiers":[
        {
            "category":"Manufacturing",
            "subcategory":"Tools & Machinery",
            "type":"Manufacturing & Wholesale Goods"
        }
    ],
    "sg:phone":"+44 1728 627923",
    "sg:postcode":"IP13 7HZ",
    "sg:province":"Suffolk",
    "sg:tags":[
        "society",
        "friendly"
    ],
    "wof:name":"Woodfield Insurance Services Ltd.",
    "wof:placetype":"venue"
},
  "geometry": {"coordinates":[1.271272,52.270428],"type":"Point"}
}