{
  "type": "Feature",
  "properties": {
    "addr:full":"197 Philip Lane London Greater London N15 4HQ",
    "addr:housenumber":"197",
    "addr:postcode":"n15 4hq",
    "addr:street":"Philip Lane",
    "iso:country":"GB",
    "sg:address":"197 Philip Lane",
    "sg:city":"London",
    "sg:classifiers":[
        {
            "category":"Bars & Pubs",
            "type":"Food & Drink"
        },
        {
            "category":"Community Center",
            "subcategory":"Social",
            "type":"Public Place"
        }
    ],
    "sg:phone":"+44 20 8808 1673",
    "sg:postcode":"N15 4HQ",
    "sg:province":"Greater London",
    "sg:tags":[
        "pubs",
        "house",
        "inn",
        "activity"
    ],
    "wof:name":"The Lord Palmerston",
    "wof:placetype":"venue"
},
  "geometry": {"coordinates":[-0.083136,51.588425],"type":"Point"}
}