{
  "type": "Feature",
  "properties": {
    "addr:full":"Calleva Park, Aldermaston Reading Berkshire RG7 8AA",
    "addr:postcode":"rg7 8aa",
    "iso:country":"GB",
    "sg:address":"Calleva Park, Aldermaston",
    "sg:city":"Reading",
    "sg:classifiers":[
        {
            "category":"Professional",
            "subcategory":"Art Services",
            "type":"Services"
        }
    ],
    "sg:phone":"+44 118 981 2101",
    "sg:postcode":"RG7 8AA",
    "sg:province":"Berkshire",
    "sg:tags":[
        "graphic",
        "designer"
    ],
    "wof:name":"G M S",
    "wof:placetype":"venue"
},
  "geometry": {"coordinates":[-1.1632299423,51.3615188599],"type":"Point"}
}