{
  "type": "Feature",
  "properties": {
    "iso:country":"GB",
    "sg:address":"2-4 Eversholt Road, Ridgmont",
    "sg:city":"Bedford",
    "sg:classifiers":[
        {
            "category":"Retail",
            "subcategory":"Auto Repair",
            "type":"Services"
        }
    ],
    "sg:phone":"+44 1525 280269",
    "sg:postcode":"MK43 0TT",
    "sg:province":"Bedfordshire",
    "sg:tags":[
        "modification",
        "garage"
    ],
    "wof:name":"M J Janes",
    "wof:placetype":"venue"
},
  "geometry": {"coordinates":[-0.579876,52.012714],"type":"Point"}
}