{
  "type": "Feature",
  "properties": {
    "addr:full":"Sandtoft Road, Belton Doncaster Lincolnshire DN9 1PN",
    "addr:postcode":"dn9 1pn",
    "addr:street":"Sandtoft Road",
    "iso:country":"GB",
    "sg:address":"Sandtoft Road, Belton",
    "sg:city":"Doncaster",
    "sg:classifiers":[
        {
            "category":"Bars & Pubs",
            "type":"Food & Drink"
        }
    ],
    "sg:postcode":"DN9 1PN",
    "sg:province":"Lincolnshire",
    "sg:tags":[
        "pubs",
        "inn"
    ],
    "wof:name":"Trevor Cole",
    "wof:placetype":"venue"
},
  "geometry": {"coordinates":[-0.8166390061,53.5528640747],"type":"Point"}
}