{
  "type": "Feature",
  "properties": {
    "addr:full":"Po Box 129 Cannock Staffordshire WS12 5WX",
    "addr:housenumber":"po",
    "addr:postcode":"ws12 5wx",
    "addr:street":"Box 129",
    "iso:country":"GB",
    "sg:address":"Po Box 129",
    "sg:city":"Cannock",
    "sg:classifiers":[
        {
            "category":"Professional",
            "type":"Services"
        }
    ],
    "sg:phone":"+44 1543 459911",
    "sg:postcode":"WS12 5WX",
    "sg:province":"Staffordshire",
    "sg:tags":[
        "entertainer"
    ],
    "wof:name":"Stuart Rhodes Entertainments",
    "wof:placetype":"venue"
},
  "geometry": {"coordinates":[-1.990659,52.699478],"type":"Point"}
}