{
  "type": "Feature",
  "properties": {
    "iso:country":"GB",
    "sg:address":"South Portway Business Park",
    "sg:city":"Salisbury",
    "sg:classifiers":[
        {
            "category":"Food & Beverages",
            "subcategory":"Supermarket",
            "type":"Retail Goods"
        }
    ],
    "sg:phone":"+44 1722 416333",
    "sg:postcode":"SP4 6EB",
    "sg:province":"Hampshire",
    "sg:tags":[
        "frozen"
    ],
    "wof:name":"P K Foods",
    "wof:placetype":"venue"
},
  "geometry": {"coordinates":[-1.78047,51.10247],"type":"Point"}
}