{
  "type": "Feature",
  "properties": {
    "iso:country":"GB",
    "sg:address":"65 Stirling Road, Tullibody",
    "sg:city":"Alloa",
    "sg:classifiers":[
        {
            "category":"Building & Trades",
            "subcategory":"Construction",
            "type":"Services"
        }
    ],
    "sg:phone":"+44 1259 721780",
    "sg:postcode":"FK10 2QD",
    "sg:province":"Clackmannanshire",
    "sg:tags":[
        "roofing",
        "builder",
        "repairer",
        "chimney",
        "contracting"
    ],
    "wof:name":"Donald Henderson",
    "wof:placetype":"venue"
},
  "geometry": {"coordinates":[-3.840185,56.135284],"type":"Point"}
}