{
  "type": "Feature",
  "properties": {
    "addr:full":"197b Barton Road Luton Bedfordshire LU3 2BN",
    "addr:housenumber":"197b",
    "addr:postcode":"lu3 2bn",
    "addr:street":"Barton Road",
    "iso:country":"GB",
    "sg:address":"197b Barton Road",
    "sg:city":"Luton",
    "sg:classifiers":[
        {
            "category":"Fast Food",
            "type":"Food & Drink"
        }
    ],
    "sg:phone":"+44 1582 493853",
    "sg:postcode":"LU3 2BN",
    "sg:province":"Bedfordshire",
    "sg:tags":[
        "away",
        "take"
    ],
    "wof:name":"A Bite on the Side",
    "wof:placetype":"venue"
},
  "geometry": {"coordinates":[-0.4282790124,51.9209823608],"type":"Point"}
}