{
  "type": "Feature",
  "properties": {
    "iso:country":"GB",
    "sg:address":"Newberry House, 51 Southgate St",
    "sg:city":"Winchester",
    "sg:classifiers":[
        {
            "category":"Insurance",
            "subcategory":"Insurance Agent",
            "type":"Services"
        }
    ],
    "sg:postcode":"SO23 9EH",
    "sg:province":"Hampshire",
    "sg:tags":[
        "broker"
    ],
    "wof:name":"Newberry,Paul,",
    "wof:placetype":"venue"
},
  "geometry": {"coordinates":[-1.318078,51.06052],"type":"Point"}
}