{
  "type": "Feature",
  "properties": {
    "iso:country":"GB",
    "sg:address":"The Turrett, Withybush Road",
    "sg:city":"Haverfordwest",
    "sg:classifiers":[
        {
            "category":"Building & Trades",
            "subcategory":"Construction",
            "type":"Services"
        }
    ],
    "sg:postcode":"SA62 4BW",
    "sg:province":"Pembrokeshire",
    "sg:tags":[
        "builder"
    ],
    "wof:name":"Withybush Patio Slabs",
    "wof:placetype":"venue"
},
  "geometry": {"coordinates":[-4.95843,51.82753],"type":"Point"}
}