{
  "type": "Feature",
  "properties": {
    "addr:full":"Station Road, Ten Mile Bank Downham Market Cambridgeshire PE38 0EP",
    "addr:postcode":"pe38 0ep",
    "addr:street":"Station Road Ten;Downham Market",
    "iso:country":"GB",
    "sg:address":"Station Road, Ten Mile Bank",
    "sg:city":"Downham Market",
    "sg:classifiers":[
        {
            "category":"Education",
            "subcategory":"School",
            "type":"Public Place"
        }
    ],
    "sg:phone":"+44 1366 377310",
    "sg:postcode":"PE38 0EP",
    "sg:province":"Cambridgeshire",
    "sg:tags":[
        "local",
        "authority"
    ],
    "wof:name":"Norfolk County Council",
    "wof:placetype":"venue"
},
  "geometry": {"coordinates":[0.3625459969,52.6036453247],"type":"Point"}
}