{
  "type": "Feature",
  "properties": {
    "iso:country":"GB",
    "sg:address":"Newchurch Road",
    "sg:city":"Tadley",
    "sg:classifiers":[
        {
            "category":"Education",
            "subcategory":"School",
            "type":"Public Place"
        }
    ],
    "sg:phone":"+44 118 981 4498",
    "sg:postcode":"RG26 4HN",
    "sg:province":"Berkshire",
    "sg:tags":[
        "local",
        "authority"
    ],
    "wof:name":"Burnham Copse Infant School",
    "wof:placetype":"venue"
},
  "geometry": {"coordinates":[-1.149764,51.356449],"type":"Point"}
}