{
  "type": "Feature",
  "properties": {
    "iso:country":"GB",
    "sg:address":"Old Newtown Road",
    "sg:city":"Newbury",
    "sg:classifiers":[
        {
            "category":"Social Services",
            "subcategory":"Adult Care",
            "type":"Services"
        }
    ],
    "sg:phone":"+44 1635 47323",
    "sg:postcode":"RG14 7DR",
    "sg:province":"Berkshire",
    "sg:tags":[
        "housing",
        "sheltered"
    ],
    "wof:name":"Malvern Court",
    "wof:placetype":"venue"
},
  "geometry": {"coordinates":[-1.326839,51.394382],"type":"Point"}
}