{
  "type": "Feature",
  "properties": {
    "iso:country":"GB",
    "sg:address":"43 Parsons Street",
    "sg:city":"Banbury",
    "sg:classifiers":[
        {
            "category":"Fast Food",
            "type":"Food & Drink"
        }
    ],
    "sg:postcode":"OX16 5NA",
    "sg:province":"Oxfordshire",
    "sg:tags":[
        "away",
        "take"
    ],
    "wof:name":"Take Away Sandwich Bar",
    "wof:placetype":"venue"
},
  "geometry": {"coordinates":[-1.3384059668,52.062297821],"type":"Point"}
}