{
  "type": "Feature",
  "properties": {
    "addr:full":"15 Slindon Avenue Peacehaven East Sussex BN10 8NJ",
    "addr:housenumber":"15",
    "addr:postcode":"bn10 8nj",
    "addr:street":"Slindon Avenue Peacehaven",
    "iso:country":"GB",
    "sg:address":"15 Slindon Avenue",
    "sg:city":"Peacehaven",
    "sg:classifiers":[
        {
            "category":"Retail",
            "subcategory":"Auto Rental",
            "type":"Services"
        }
    ],
    "sg:phone":"+44 1273 583062",
    "sg:postcode":"BN10 8NJ",
    "sg:province":"East Sussex",
    "sg:tags":[
        "car"
    ],
    "wof:name":"Bernards Chauffeur Services",
    "wof:placetype":"venue"
},
  "geometry": {"coordinates":[0.006852,50.7890510559],"type":"Point"}
}