{
  "type": "Feature",
  "properties": {
    "iso:country":"GB",
    "sg:address":"Unit, 50, Washington Centre",
    "sg:city":"Washington",
    "sg:classifiers":[
        {
            "category":"Shopping",
            "subcategory":"Stationery & Office Supplies",
            "type":"Retail Goods"
        }
    ],
    "sg:phone":"+44 191 419 0969",
    "sg:postcode":"NE38 7SD",
    "sg:province":"Durham",
    "sg:tags":[
        "recording",
        "machine",
        "time"
    ],
    "wof:name":"Timecheck",
    "wof:placetype":"venue"
},
  "geometry": {"coordinates":[-1.53271,54.90012],"type":"Point"}
}