{
  "type": "Feature",
  "properties": {
    "addr:full":"56 Bury New Rd, Prestwich Manchester Greater Manchester M25 0JU",
    "addr:housenumber":"56",
    "addr:postcode":"m25 0ju",
    "addr:street":"Bury New Rd",
    "iso:country":"GB",
    "sg:address":"56 Bury New Rd, Prestwich",
    "sg:city":"Manchester",
    "sg:classifiers":[
        {
            "category":"Professional",
            "subcategory":"Lawyer & Legal Services",
            "type":"Services"
        }
    ],
    "sg:phone":"+44 161 798 9520",
    "sg:postcode":"M25 0JU",
    "sg:province":"Greater Manchester",
    "sg:tags":[
        "solicitor"
    ],
    "wof:name":"Rosenberg,Charles,& Co",
    "wof:placetype":"venue"
},
  "geometry": {"coordinates":[-2.271816,53.519199],"type":"Point"}
}