{
  "type": "Feature",
  "properties": {
    "iso:country":"GB",
    "sg:address":"2 Stocks Hill, Ketton",
    "sg:city":"Stamford",
    "sg:classifiers":[
        {
            "category":"Personal",
            "subcategory":"Beauty Salon",
            "type":"Services"
        }
    ],
    "sg:postcode":"PE9 3TF",
    "sg:province":"Cambridgeshire",
    "sg:tags":[
        "unisex",
        "hairdresser"
    ],
    "wof:name":"Melanie Annes",
    "wof:placetype":"venue"
},
  "geometry": {"coordinates":[-0.552853,52.628342],"type":"Point"}
}