{
  "type": "Feature",
  "properties": {
    "iso:country":"GB",
    "sg:address":"178 New Rd",
    "sg:city":"Chatham",
    "sg:classifiers":[
        {
            "category":"Retail",
            "subcategory":"Auto Repair",
            "type":"Services"
        }
    ],
    "sg:phone":"+44 1634 845585",
    "sg:postcode":"ME4 4PY",
    "sg:province":"Kent",
    "sg:tags":[
        "body",
        "car"
    ],
    "wof:name":"New Road Garage (Chatham) Ltd",
    "wof:placetype":"venue"
},
  "geometry": {"coordinates":[0.52679,51.379292],"type":"Point"}
}