{
  "type": "Feature",
  "properties": {
    "addr:full":"Mill Lane Newcastle-upon-tyne Tyne and Wear NE4 6QA",
    "addr:postcode":"ne4 6qa",
    "addr:street":"Mill Lane",
    "iso:country":"GB",
    "sg:address":"Mill Lane",
    "sg:city":"Newcastle-upon-tyne",
    "sg:classifiers":[
        {
            "category":"Education",
            "subcategory":"Special Training",
            "type":"Public Place"
        }
    ],
    "sg:postcode":"NE4 6QA",
    "sg:province":"Tyne and Wear",
    "sg:tags":[
        "product",
        "centre"
    ],
    "wof:name":"Industrial Training Services Ltd.",
    "wof:placetype":"venue"
},
  "geometry": {"coordinates":[-1.6405789852,54.9731483459],"type":"Point"}
}