{
  "type": "Feature",
  "properties": {
    "iso:country":"GB",
    "sg:address":"2 North St",
    "sg:city":"Hailsham",
    "sg:classifiers":[
        {
            "category":"Real Estate",
            "subcategory":"Developer",
            "type":"Services"
        }
    ],
    "sg:postcode":"BN27 1DQ",
    "sg:province":"East Sussex",
    "sg:tags":[
        "property"
    ],
    "wof:name":"Oakley Land & Development Ltd",
    "wof:placetype":"venue"
},
  "geometry": {"coordinates":[0.257512,50.862499],"type":"Point"}
}