{
  "type": "Feature",
  "properties": {
    "addr:full":"Hart Lane Hartlepool Durham TS26 8NL",
    "addr:postcode":"ts26 8nl",
    "addr:street":"Hart Lane",
    "iso:country":"GB",
    "sg:address":"Hart Lane",
    "sg:city":"Hartlepool",
    "sg:classifiers":[
        {
            "category":"Education",
            "subcategory":"School",
            "type":"Public Place"
        },
        {
            "category":"Government",
            "subcategory":"Office",
            "type":"Public Place"
        }
    ],
    "sg:phone":"+44 1429 860372",
    "sg:postcode":"TS26 8NL",
    "sg:province":"Durham",
    "sg:tags":[
        "local",
        "authority"
    ],
    "wof:name":"Sacred Heart R C Primary School",
    "wof:placetype":"venue"
},
  "geometry": {"coordinates":[-1.233069,54.690876],"type":"Point"}
}