{
  "type": "Feature",
  "properties": {
    "addr:full":"46 Crooked Mile Waltham Abbey Essex EN9 1QD",
    "addr:housenumber":"46",
    "addr:postcode":"en9 1qd",
    "addr:street":"Crooked Mile Waltham Abbey",
    "iso:country":"GB",
    "sg:address":"46 Crooked Mile",
    "sg:city":"Waltham Abbey",
    "sg:classifiers":[
        {
            "category":"Community Center",
            "type":"Public Place"
        }
    ],
    "sg:phone":"+44 1992 711188",
    "sg:postcode":"EN9 1QD",
    "sg:province":"Essex",
    "sg:tags":[
        "centre"
    ],
    "wof:name":"Waltham Abbey Community Centre",
    "wof:placetype":"venue"
},
  "geometry": {"coordinates":[0.00111,51.6887207031],"type":"Point"}
}