{
  "type": "Feature",
  "properties": {
    "addr:full":"353 Two Mile Hill Road, Kingswood Bristol City of Bristol BS15 1AF",
    "addr:housenumber":"353",
    "addr:postcode":"bs15 1af",
    "addr:street":"Two Mile Hill Road",
    "iso:country":"GB",
    "sg:address":"353 Two Mile Hill Road, Kingswood",
    "sg:city":"Bristol",
    "sg:classifiers":[
        {
            "category":"Bakery",
            "type":"Food & Drink"
        }
    ],
    "sg:postcode":"BS15 1AF",
    "sg:province":"City of Bristol",
    "sg:tags":[
        "cake",
        "maker"
    ],
    "wof:name":"Confectionery Supplies",
    "wof:placetype":"venue"
},
  "geometry": {"coordinates":[-2.514919,51.463234],"type":"Point"}
}