{
  "type": "Feature",
  "properties": {
    "addr:full":"3 Grange Estate, Cossall Nottingham Derbyshire NG16 2SL",
    "addr:housenumber":"3",
    "addr:postcode":"ng16 2sl",
    "addr:street":"Grange Estate",
    "iso:country":"GB",
    "sg:address":"3 Grange Estate, Cossall",
    "sg:city":"Nottingham",
    "sg:classifiers":[
        {
            "category":"Building & Trades",
            "subcategory":"Plumbing",
            "type":"Services"
        }
    ],
    "sg:phone":"+44 115 932 1620",
    "sg:postcode":"NG16 2SL",
    "sg:province":"Derbyshire",
    "sg:tags":[
        "central",
        "installation",
        "system",
        "servicing",
        "heating"
    ],
    "wof:name":"Bramcote Heating & Plumbing Co",
    "wof:placetype":"venue"
},
  "geometry": {"coordinates":[-1.281036,52.975155],"type":"Point"}
}