{
  "type": "Feature",
  "properties": {
    "addr:full":"613 Manchester Road, Linthwaite Huddersfield West Yorkshire HD7 5QX",
    "addr:housenumber":"613",
    "addr:postcode":"hd7 5qx",
    "addr:street":"Manchester Road;West",
    "iso:country":"GB",
    "sg:address":"613 Manchester Road, Linthwaite",
    "sg:city":"Huddersfield",
    "sg:classifiers":[
        {
            "category":"Health Services",
            "subcategory":"Dentist",
            "type":"Services"
        }
    ],
    "sg:postcode":"HD7 5QX",
    "sg:province":"West Yorkshire",
    "wof:name":"Linthwaite Dental Health Surgery",
    "wof:placetype":"venue"
},
  "geometry": {"coordinates":[-1.8420089483,53.6336593628],"type":"Point"}
}