{
  "type": "Feature",
  "properties": {
    "addr:full":"Shardlow Rd, Alvaston Derby Derbyshire DE24 0JH",
    "addr:postcode":"de24 0jh",
    "addr:street":"Shardlow Rd",
    "iso:country":"GB",
    "sg:address":"Shardlow Rd, Alvaston",
    "sg:city":"Derby",
    "sg:classifiers":[
        {
            "category":"Bars & Pubs",
            "type":"Food & Drink"
        }
    ],
    "sg:phone":"+44 1332 576921",
    "sg:postcode":"DE24 0JH",
    "sg:province":"Derbyshire",
    "sg:tags":[
        "pubs",
        "inn"
    ],
    "wof:name":"Blue Peter Bass Tavern",
    "wof:placetype":"venue"
},
  "geometry": {"coordinates":[-1.426445,52.898651],"type":"Point"}
}