{
  "type": "Feature",
  "properties": {
    "iso:country":"GB",
    "sg:address":"20 Vicarage Road",
    "sg:city":"Verwood",
    "sg:classifiers":[
        {
            "category":"Retail",
            "subcategory":"Funeral Services",
            "type":"Services"
        }
    ],
    "sg:postcode":"BH31 6DR",
    "sg:province":"Dorset",
    "wof:name":"Nicholas O'Hara",
    "wof:placetype":"venue"
},
  "geometry": {"coordinates":[-1.877426,50.880009],"type":"Point"}
}