{
  "type": "Feature",
  "properties": {
    "addr:full":"Pink Neaz Farm, Botley Southampton Hampshire SO30 2HA",
    "addr:postcode":"so30 2ha",
    "iso:country":"GB",
    "sg:address":"Pink Neaz Farm, Botley",
    "sg:city":"Southampton",
    "sg:classifiers":[
        {
            "category":"Utilities",
            "subcategory":"Fuel Oil & Lpg",
            "type":"Services"
        }
    ],
    "sg:phone":"+44 1489 796590",
    "sg:postcode":"SO30 2HA",
    "sg:province":"Hampshire",
    "sg:tags":[
        "peat",
        "firewood",
        "logs"
    ],
    "wof:name":"L C K  (Southern) Ltd.",
    "wof:placetype":"venue"
},
  "geometry": {"coordinates":[-1.270219,50.914333],"type":"Point"}
}