{
  "type": "Feature",
  "properties": {
    "addr:full":"27a Baldock Street Ware Hertfordshire SG12 9DH",
    "addr:housenumber":"27a",
    "addr:postcode":"sg12 9dh",
    "addr:street":"Baldock Street Ware",
    "iso:country":"GB",
    "sg:address":"27a Baldock Street",
    "sg:city":"Ware",
    "sg:classifiers":[
        {
            "category":"Personal",
            "type":"Services"
        }
    ],
    "sg:phone":"+44 1920 462049",
    "sg:postcode":"SG12 9DH",
    "sg:province":"Hertfordshire",
    "sg:tags":[
        "wedding"
    ],
    "wof:name":"The Dressing Room",
    "wof:placetype":"venue"
},
  "geometry": {"coordinates":[-0.0347030014,51.8127250671],"type":"Point"}
}