{
  "type": "Feature",
  "properties": {
    "iso:country":"GB",
    "sg:address":"213a Station Road",
    "sg:city":"Harrow",
    "sg:classifiers":[
        {
            "category":"Wholesale",
            "subcategory":"Machinery & Supplies",
            "type":"Manufacturing & Wholesale Goods"
        }
    ],
    "sg:phone":"+44 20 8930 9966",
    "sg:postcode":"HA1 2TP",
    "sg:province":"Greater London",
    "sg:tags":[
        "industrial",
        "commercial"
    ],
    "wof:name":"Anslip (U K) Ltd.",
    "wof:placetype":"venue"
},
  "geometry": {"coordinates":[-0.332209,51.584522],"type":"Point"}
}