{
  "type": "Feature",
  "properties": {
    "addr:full":"University Of Manchester, Jodrell Bank, Lower Withington Macclesfield Cheshire SK11 9DL",
    "addr:postcode":"sk11 9dl",
    "addr:street":"Lower",
    "iso:country":"GB",
    "sg:address":"University Of Manchester, Jodrell Bank, Lower Withington",
    "sg:city":"Macclesfield",
    "sg:classifiers":[
        {
            "category":"Professional",
            "subcategory":"Testing Lab",
            "type":"Services"
        }
    ],
    "sg:phone":"+44 1477 571321",
    "sg:postcode":"SK11 9DL",
    "sg:province":"Cheshire",
    "sg:tags":[
        "laboratory"
    ],
    "wof:name":"Nuffield Radio Astronomy Laboratories",
    "wof:placetype":"venue"
},
  "geometry": {"coordinates":[-2.2839388847,53.225528717],"type":"Point"}
}