{
  "type": "Feature",
  "properties": {
    "iso:country":"GB",
    "sg:address":"Stanford Business Court, High Street",
    "sg:city":"Faringdon",
    "sg:classifiers":[
        {
            "category":"Education",
            "subcategory":"School",
            "type":"Public Place"
        },
        {
            "category":"Government",
            "subcategory":"Office",
            "type":"Public Place"
        }
    ],
    "sg:phone":"+44 1367 710474",
    "sg:postcode":"SN7 8LH",
    "sg:province":"Oxfordshire",
    "sg:tags":[
        "local",
        "authority"
    ],
    "wof:name":"Peyton Ltd.",
    "wof:placetype":"venue"
},
  "geometry": {"coordinates":[-1.454779,51.686325],"type":"Point"}
}