{
  "type": "Feature",
  "properties": {
    "addr:full":"16 Beck Road Leeds West Yorkshire LS8 4EJ",
    "addr:housenumber":"16",
    "addr:postcode":"ls8 4ej",
    "addr:street":"Beck Road",
    "iso:country":"GB",
    "sg:address":"16 Beck Road",
    "sg:city":"Leeds",
    "sg:classifiers":[
        {
            "category":"Personal",
            "subcategory":"Beauty Salon",
            "type":"Services"
        },
        {
            "category":"Personal",
            "subcategory":"Barber",
            "type":"Services"
        }
    ],
    "sg:phone":"+44 113 226 7576",
    "sg:postcode":"LS8 4EJ",
    "sg:province":"West Yorkshire",
    "sg:tags":[
        "unisex",
        "hairdresser"
    ],
    "wof:name":"Unique Touch Unisex Hair Salon",
    "wof:placetype":"venue"
},
  "geometry": {"coordinates":[-1.5175989866,53.8172531128],"type":"Point"}
}