{
  "type": "Feature",
  "properties": {
    "addr:full":"Great Lea Farm, Great Lea Common Reading Berkshire RG7 1JL",
    "addr:postcode":"rg7 1jl",
    "addr:street":"Great Lea Common",
    "iso:country":"GB",
    "sg:address":"Great Lea Farm, Great Lea Common",
    "sg:city":"Reading",
    "sg:classifiers":[
        {
            "category":"Farming",
            "subcategory":"Livestock Farm",
            "type":"Manufacturing & Wholesale Goods"
        }
    ],
    "sg:phone":"+44 118 988 3283",
    "sg:postcode":"RG7 1JL",
    "sg:province":"Berkshire",
    "sg:tags":[
        "others"
    ],
    "wof:name":"W J Hayes",
    "wof:placetype":"venue"
},
  "geometry": {"coordinates":[-0.9763820171,51.4090499878],"type":"Point"}
}