{
  "type": "Feature",
  "properties": {
    "addr:full":"56 Norwood High Street London Greater London SE27 9NR",
    "addr:housenumber":"56",
    "addr:postcode":"se27 9nr",
    "addr:street":"Norwood High Street",
    "iso:country":"GB",
    "sg:address":"56 Norwood High Street",
    "sg:city":"London",
    "sg:classifiers":[
        {
            "category":"Shopping",
            "subcategory":"News",
            "type":"Retail Goods"
        }
    ],
    "sg:phone":"+44 20 8766 0388",
    "sg:postcode":"SE27 9NR",
    "sg:province":"Greater London",
    "sg:tags":[
        "newsagent"
    ],
    "wof:name":"K P Newsagents",
    "wof:placetype":"venue"
},
  "geometry": {"coordinates":[-0.1018539965,51.4308242798],"type":"Point"}
}