{
  "type": "Feature",
  "properties": {
    "addr:full":"Windmill Lane, Gentleshaw Rugeley Staffordshire WS15 4NF",
    "addr:postcode":"ws15 4nf",
    "addr:street":"Windmill Lane",
    "iso:country":"GB",
    "sg:address":"Windmill Lane, Gentleshaw",
    "sg:city":"Rugeley",
    "sg:classifiers":[
        {
            "category":"Bars & Pubs",
            "type":"Food & Drink"
        }
    ],
    "sg:phone":"+44 1543 682468",
    "sg:postcode":"WS15 4NF",
    "sg:province":"Staffordshire",
    "sg:tags":[
        "pubs",
        "inn"
    ],
    "wof:name":"The Ye Olde Windmill",
    "wof:placetype":"venue"
},
  "geometry": {"coordinates":[-1.9180959463,52.7050285339],"type":"Point"}
}