{
  "type": "Feature",
  "properties": {
    "addr:full":"11 Chapal Street Lancaster Lancashire LA1 1NZ",
    "addr:housenumber":"11",
    "addr:postcode":"la1 1nz",
    "addr:street":"Chapal Street",
    "iso:country":"GB",
    "sg:address":"11 Chapal Street",
    "sg:city":"Lancaster",
    "sg:classifiers":[
        {
            "category":"Recreation",
            "subcategory":"Fishing",
            "type":"Entertainment"
        }
    ],
    "sg:phone":"+44 1524 63043",
    "sg:postcode":"LA1 1NZ",
    "sg:province":"Lancashire",
    "sg:tags":[
        "angling"
    ],
    "wof:name":"Charlton & Bagnall Ltd.",
    "wof:placetype":"venue"
},
  "geometry": {"coordinates":[-2.799947,54.050682],"type":"Point"}
}