{
  "type": "Feature",
  "properties": {
    "addr:full":"191 London Rd Stoke-on-trent Staffordshire ST4 5RW",
    "addr:housenumber":"191",
    "addr:postcode":"st4 5rw",
    "addr:street":"London Rd",
    "iso:country":"GB",
    "sg:address":"191 London Rd",
    "sg:city":"Stoke-on-trent",
    "sg:classifiers":[
        {
            "category":"Shopping",
            "subcategory":"Florist",
            "type":"Retail Goods"
        }
    ],
    "sg:postcode":"ST4 5RW",
    "sg:province":"Staffordshire",
    "wof:name":"Broomfield,Shiela,",
    "wof:placetype":"venue"
},
  "geometry": {"coordinates":[-2.1886999607,52.999710083],"type":"Point"}
}