{
  "type": "Feature",
  "properties": {
    "addr:full":"Lane Brea House, Coventry Street Birmingham West Midlands B5 5NJ",
    "addr:postcode":"b5 5nj",
    "addr:street":"Lane;Coventry Street",
    "iso:country":"GB",
    "sg:address":"Lane Brea House, Coventry Street",
    "sg:city":"Birmingham",
    "sg:classifiers":[
        {
            "category":"Building & Trades",
            "subcategory":"Construction",
            "type":"Services"
        }
    ],
    "sg:phone":"+44 121 643 1846",
    "sg:postcode":"B5 5NJ",
    "sg:province":"West Midlands",
    "sg:tags":[
        "builder"
    ],
    "wof:name":"General Refurbishment & Building Services Ltd.",
    "wof:placetype":"venue"
},
  "geometry": {"coordinates":[-1.889619,52.477322],"type":"Point"}
}