{
  "type": "Feature",
  "properties": {
    "addr:full":"Fotorama House, Icknield Way Estate Tring Buckinghamshire HP23 4NU",
    "addr:postcode":"hp23 4nu",
    "addr:street":"Icknield Way Estate",
    "iso:country":"GB",
    "sg:address":"Fotorama House, Icknield Way Estate",
    "sg:city":"Tring",
    "sg:classifiers":[
        {
            "category":"Organizations",
            "subcategory":"Community Association",
            "type":"Services"
        }
    ],
    "sg:phone":"+44 1442 828383",
    "sg:postcode":"HP23 4NU",
    "sg:province":"Buckinghamshire",
    "sg:tags":[
        "relation",
        "public"
    ],
    "wof:name":"Herts Tring Uk Ltd.",
    "wof:placetype":"venue"
},
  "geometry": {"coordinates":[-0.6639800072,51.7932701111],"type":"Point"}
}