{
  "type": "Feature",
  "properties": {
    "addr:full":"6 Keele St Stoke On Trent Staffordshire ST6 5AR",
    "addr:housenumber":"6",
    "addr:postcode":"st6 5ar",
    "addr:street":"Keele St",
    "iso:country":"GB",
    "sg:address":"6 Keele St",
    "sg:city":"Stoke On Trent",
    "sg:classifiers":[
        {
            "category":"Home & Garden",
            "subcategory":"Building Materials",
            "type":"Retail Goods"
        }
    ],
    "sg:phone":"+44 1782 825288",
    "sg:postcode":"ST6 5AR",
    "sg:province":"Staffordshire",
    "sg:tags":[
        "furnishers",
        "bathroom",
        "planner"
    ],
    "wof:name":"A P F Distribution",
    "wof:placetype":"venue"
},
  "geometry": {"coordinates":[-2.211688,53.061108],"type":"Point"}
}