{
  "type": "Feature",
  "properties": {
    "iso:country":"GB",
    "sg:address":"Ystrad Service Station, Rear Of 14-15 Cross St, Ystrad",
    "sg:city":"Pentre",
    "sg:classifiers":[
        {
            "category":"Retail",
            "subcategory":"Auto Repair",
            "type":"Services"
        }
    ],
    "sg:phone":"+44 1443 433330",
    "sg:postcode":"CF41 7RF",
    "sg:province":"Rhondda, Cynon, Taff",
    "sg:tags":[
        "modification",
        "garage"
    ],
    "wof:name":"F.M.Motors",
    "wof:placetype":"venue"
},
  "geometry": {"coordinates":[-3.4928939342,51.6553268433],"type":"Point"}
}