{
  "type": "Feature",
  "properties": {
    "addr:full":"Unit 216, St Nicholas Centre Sutton Surrey SM1 1AY",
    "addr:housenumber":"216",
    "addr:postcode":"sm1 1ay",
    "addr:street":"St Nicholas Centre Sutton",
    "iso:country":"GB",
    "sg:address":"Unit 216, St Nicholas Centre",
    "sg:city":"Sutton",
    "sg:classifiers":[
        {
            "category":"Shopping",
            "subcategory":"Books",
            "type":"Retail Goods"
        }
    ],
    "sg:phone":"+44 20 8255 7744",
    "sg:postcode":"SM1 1AY",
    "sg:province":"Surrey",
    "sg:tags":[
        "bookseller"
    ],
    "wof:name":"Kendrake Childrens Bookshop",
    "wof:placetype":"venue"
},
  "geometry": {"coordinates":[-0.193554,51.362579],"type":"Point"}
}