{
  "type": "Feature",
  "properties": {
    "addr:full":"Anchor Works, Glebe Road Chelmsford Essex CM1 1QG",
    "addr:postcode":"cm1 1qg",
    "addr:street":"Glebe Road",
    "iso:country":"GB",
    "sg:address":"Anchor Works, Glebe Road",
    "sg:city":"Chelmsford",
    "sg:classifiers":[
        {
            "category":"Professional",
            "subcategory":"Printing & Photocopies",
            "type":"Services"
        }
    ],
    "sg:phone":"+44 1245 264522",
    "sg:postcode":"CM1 1QG",
    "sg:province":"Essex",
    "sg:tags":[
        "plate",
        "computer",
        "lithographic",
        "label",
        "tag",
        "maker"
    ],
    "wof:name":"Brit Labels",
    "wof:placetype":"venue"
},
  "geometry": {"coordinates":[0.4676,51.738762],"type":"Point"}
}