{
  "type": "Feature",
  "properties": {
    "addr:full":"Springfield House, Chapel Row, Middleton-in-teesdalrow Barnard Castle Cumbria DL12 0SN",
    "addr:postcode":"dl12 0sn",
    "addr:street":"Chapel Row Middleton-In-Teesdalrow",
    "iso:country":"GB",
    "sg:address":"Springfield House, Chapel Row, Middleton-in-teesdalrow",
    "sg:city":"Barnard Castle",
    "sg:classifiers":[
        {
            "category":"Communications",
            "type":"Services"
        }
    ],
    "sg:phone":"+44 1833 640567",
    "sg:postcode":"DL12 0SN",
    "sg:province":"Cumbria",
    "sg:tags":[
        "audio-visual"
    ],
    "wof:name":"A T V Productions",
    "wof:placetype":"venue"
},
  "geometry": {"coordinates":[-2.0811839104,54.6237716675],"type":"Point"}
}