{
  "type": "Feature",
  "properties": {
    "iso:country":"GB",
    "sg:address":"Care Of Kwik Save, 103-111 Northgate Street",
    "sg:city":"Gloucester",
    "sg:classifiers":[
        {
            "category":"Home & Garden",
            "subcategory":"Furniture",
            "type":"Retail Goods"
        }
    ],
    "sg:phone":"+44 1452 530138",
    "sg:postcode":"GL1 2AA",
    "sg:province":"Gloucestershire",
    "wof:name":"Final Touches",
    "wof:placetype":"venue"
},
  "geometry": {"coordinates":[-2.249624,51.863811],"type":"Point"}
}