{
  "type": "Feature",
  "properties": {
    "addr:full":"40 High Street, Brownhills Walsall Staffordshire WS8 6EL",
    "addr:housenumber":"40",
    "addr:postcode":"ws8 6el",
    "addr:street":"High Street",
    "iso:country":"GB",
    "sg:address":"40 High Street, Brownhills",
    "sg:city":"Walsall",
    "sg:classifiers":[
        {
            "category":"Manufacturing",
            "subcategory":"Tools & Machinery",
            "type":"Manufacturing & Wholesale Goods"
        },
        {
            "category":"Insurance",
            "subcategory":"Insurance Agent",
            "type":"Services"
        }
    ],
    "sg:phone":"+44 1543 379151",
    "sg:postcode":"WS8 6EL",
    "sg:province":"Staffordshire",
    "sg:tags":[
        "society",
        "broker",
        "friendly"
    ],
    "wof:name":"Obc Insurance Consultants",
    "wof:placetype":"venue"
},
  "geometry": {"coordinates":[-1.933228,52.64703],"type":"Point"}
}