{
  "type": "Feature",
  "properties": {
    "iso:country":"GB",
    "sg:address":"Northway Ho, 1379-1401 High Rd",
    "sg:city":"Totteridge",
    "sg:classifiers":[
        {
            "category":"Travel",
            "subcategory":"Travel Agent",
            "type":"Entertainment"
        }
    ],
    "sg:phone":"+44 20 8446 8040",
    "sg:postcode":"N20 9LS",
    "sg:province":"Greater London",
    "wof:name":"Ticket To Ride",
    "wof:placetype":"venue"
},
  "geometry": {"coordinates":[-0.176060006,51.6338005066],"type":"Point"}
}