{
  "type": "Feature",
  "properties": {
    "iso:country":"GB",
    "sg:address":"109-125 Newchurch Road",
    "sg:city":"Bacup",
    "sg:classifiers":[
        {
            "category":"Home & Garden",
            "subcategory":"Furniture",
            "type":"Retail Goods"
        }
    ],
    "sg:phone":"+44 1706 877547",
    "sg:postcode":"OL13 0DL",
    "sg:province":"Lancashire",
    "sg:tags":[
        "outlet"
    ],
    "wof:name":"LEE MILL FURNISHINGS",
    "wof:placetype":"venue"
},
  "geometry": {"coordinates":[-2.209892,53.692989],"type":"Point"}
}