{
  "type": "Feature",
  "properties": {
    "addr:full":"30 Montague Road, Saltford Bristol City of Bristol BS31 3LA",
    "addr:housenumber":"30",
    "addr:postcode":"bs31 3la",
    "addr:street":"Montague Road",
    "iso:country":"GB",
    "sg:address":"30 Montague Road, Saltford",
    "sg:city":"Bristol",
    "sg:classifiers":[
        {
            "category":"Professional",
            "type":"Services"
        }
    ],
    "sg:postcode":"BS31 3LA",
    "sg:province":"City of Bristol",
    "sg:tags":[
        "entertainer"
    ],
    "wof:name":"John Isaacs",
    "wof:placetype":"venue"
},
  "geometry": {"coordinates":[-2.4667980671,51.3995857239],"type":"Point"}
}