{
  "type": "Feature",
  "properties": {
    "addr:full":"Weldon Road Castleford West Yorkshire WF10 2JT",
    "addr:postcode":"wf10 2jt",
    "addr:street":"Weldon Road",
    "iso:country":"GB",
    "sg:address":"Weldon Road",
    "sg:city":"Castleford",
    "sg:classifiers":[
        {
            "category":"Building & Trades",
            "subcategory":"Landscaping Services",
            "type":"Services"
        }
    ],
    "sg:phone":"+44 1977 714000",
    "sg:postcode":"WF10 2JT",
    "sg:province":"West Yorkshire",
    "sg:tags":[
        "preservation",
        "timber"
    ],
    "wof:name":"Hickson Timber Products Ltd.",
    "wof:placetype":"venue"
},
  "geometry": {"coordinates":[-1.3420289755,53.7301902771],"type":"Point"}
}