{
  "type": "Feature",
  "properties": {
    "addr:full":"Ripley Drive Normanton West Yorkshire WF6 1QT",
    "addr:postcode":"wf6 1qt",
    "addr:street":"Ripley Drive Normanton West",
    "iso:country":"GB",
    "sg:address":"Ripley Drive",
    "sg:city":"Normanton",
    "sg:classifiers":[
        {
            "category":"Manufacturing",
            "subcategory":"Wood Products",
            "type":"Manufacturing & Wholesale Goods"
        }
    ],
    "sg:phone":"+44 1924 898801",
    "sg:postcode":"WF6 1QT",
    "sg:province":"West Yorkshire",
    "sg:tags":[
        "packaging",
        "crate",
        "pallets"
    ],
    "wof:name":"Thorpe Packaging",
    "wof:placetype":"venue"
},
  "geometry": {"coordinates":[-1.412878,53.698082],"type":"Point"}
}