{
  "type": "Feature",
  "properties": {
    "iso:country":"GB",
    "sg:address":"7 Bradbury Clo",
    "sg:city":"Derby",
    "sg:classifiers":[
        {
            "category":"Retail",
            "subcategory":"Repair Shop",
            "type":"Services"
        }
    ],
    "sg:phone":"+44 1509 670747",
    "sg:postcode":"DE72 3GY",
    "sg:province":"Derbyshire",
    "sg:tags":[
        "clocks",
        "watch"
    ],
    "wof:name":"Fletchers",
    "wof:placetype":"venue"
},
  "geometry": {"coordinates":[-1.3722000122,52.9045257568],"type":"Point"}
}