{
  "type": "Feature",
  "properties": {
    "addr:full":"Basingstoke Road, Riseley Reading Berkshire RG7 1QS",
    "addr:postcode":"rg7 1qs",
    "addr:street":"Basingstoke Road",
    "iso:country":"GB",
    "sg:address":"Basingstoke Road, Riseley",
    "sg:city":"Reading",
    "sg:classifiers":[
        {
            "category":"Bars & Pubs",
            "type":"Food & Drink"
        }
    ],
    "sg:postcode":"RG7 1QS",
    "sg:province":"Berkshire",
    "sg:tags":[
        "pubs",
        "inn"
    ],
    "wof:name":"The Dog & Partridge",
    "wof:placetype":"venue"
},
  "geometry": {"coordinates":[-0.9731490016,51.411113739],"type":"Point"}
}