{
  "type": "Feature",
  "properties": {
    "addr:full":"19 High St Hoddesdon Essex EN11 8ST",
    "addr:housenumber":"19",
    "addr:postcode":"en11 8st",
    "addr:street":"High St",
    "iso:country":"GB",
    "sg:address":"19 High St",
    "sg:city":"Hoddesdon",
    "sg:classifiers":[
        {
            "category":"Retail",
            "subcategory":"Auto Repair",
            "type":"Services"
        }
    ],
    "sg:phone":"+44 1992 470404",
    "sg:postcode":"EN11 8ST",
    "sg:province":"Essex",
    "sg:tags":[
        "modification",
        "garage"
    ],
    "wof:name":"Mr Unique Tyres & Exhausts",
    "wof:placetype":"venue"
},
  "geometry": {"coordinates":[-0.0128049999,51.757686615],"type":"Point"}
}