{
  "type": "Feature",
  "properties": {
    "addr:full":"71 Cog La Burnley Lancashire BB11 5BG",
    "addr:housenumber":"71",
    "addr:postcode":"bb11 5bg",
    "addr:street":"Cog La Burnley",
    "iso:country":"GB",
    "sg:address":"71 Cog La",
    "sg:city":"Burnley",
    "sg:classifiers":[
        {
            "category":"Bars & Pubs",
            "type":"Food & Drink"
        }
    ],
    "sg:phone":"+44 1282 451462",
    "sg:postcode":"BB11 5BG",
    "sg:province":"Lancashire",
    "sg:tags":[
        "pubs",
        "inn"
    ],
    "wof:name":"Shepherds Arms",
    "wof:placetype":"venue"
},
  "geometry": {"coordinates":[-2.267351,53.785526],"type":"Point"}
}