{
  "type": "Feature",
  "properties": {
    "iso:country":"GB",
    "sg:address":"5 Polsham Park",
    "sg:city":"Paignton",
    "sg:classifiers":[
        {
            "category":"Travel",
            "subcategory":"Hotels & Motels",
            "type":"Entertainment"
        }
    ],
    "sg:phone":"+44 1803 558402",
    "sg:postcode":"TQ3 2AD",
    "sg:province":"Devon",
    "sg:tags":[
        "house",
        "guest"
    ],
    "wof:name":"The Clydesdale",
    "wof:placetype":"venue"
},
  "geometry": {"coordinates":[-3.564696,50.440094],"type":"Point"}
}