{
  "type": "Feature",
  "properties": {
    "iso:country":"GB",
    "sg:address":"27 Cheap Street",
    "sg:city":"Sherborne",
    "sg:classifiers":[
        {
            "category":"Shopping",
            "subcategory":"Bicycles & Sporting Goods",
            "type":"Retail Goods"
        },
        {
            "category":"Sports & Exercise",
            "subcategory":"Sports Center",
            "type":"Entertainment"
        }
    ],
    "sg:phone":"+44 1935 812232",
    "sg:postcode":"DT9 3PU",
    "sg:province":"Dorset",
    "sg:tags":[
        "shop",
        "sale"
    ],
    "wof:name":"Sporting Classics Ltd",
    "wof:placetype":"venue"
},
  "geometry": {"coordinates":[-2.5163109303,50.9491424561],"type":"Point"}
}