{
  "type": "Feature",
  "properties": {
    "addr:full":"Tor Park Road Torquay Devon TQ2 5BQ",
    "addr:postcode":"tq2 5bq",
    "addr:street":"Park Road",
    "iso:country":"GB",
    "sg:address":"Tor Park Road",
    "sg:city":"Torquay",
    "sg:classifiers":[
        {
            "category":"Travel",
            "subcategory":"Hotels & Motels",
            "type":"Entertainment"
        }
    ],
    "sg:phone":"+44 1803 292187",
    "sg:postcode":"TQ2 5BQ",
    "sg:province":"Devon",
    "sg:tags":[
        "house",
        "guest"
    ],
    "wof:name":"B Knott",
    "wof:placetype":"venue"
},
  "geometry": {"coordinates":[-3.5424180031,50.471446991],"type":"Point"}
}