{
  "type": "Feature",
  "properties": {
    "addr:full":"434 Clifton Drive North Lytham St Annes Lancashire FY8 2PW",
    "addr:housenumber":"434",
    "addr:postcode":"fy8 2pw",
    "addr:street":"Clifton Drive North;St",
    "iso:country":"GB",
    "sg:address":"434 Clifton Drive North",
    "sg:city":"Lytham St Annes",
    "sg:classifiers":[
        {
            "category":"Education",
            "subcategory":"Dance Studio",
            "type":"Public Place"
        }
    ],
    "sg:phone":"+44 1253 739213",
    "sg:postcode":"FY8 2PW",
    "sg:province":"Lancashire",
    "sg:tags":[
        "school",
        "dancing"
    ],
    "wof:name":"Rainbow Dance Studios",
    "wof:placetype":"venue"
},
  "geometry": {"coordinates":[-3.0415930748,53.7578773499],"type":"Point"}
}