{
  "type": "Feature",
  "properties": {
    "addr:full":"Westbrook Industrial Park, 227 Sea Street Herne Bay Kent CT6 8JZ",
    "addr:housenumber":"227",
    "addr:postcode":"ct6 8jz",
    "addr:street":"Sea Street",
    "iso:country":"GB",
    "sg:address":"Westbrook Industrial Park, 227 Sea Street",
    "sg:city":"Herne Bay",
    "sg:classifiers":[
        {
            "category":"Building & Trades",
            "subcategory":"Construction",
            "type":"Services"
        }
    ],
    "sg:phone":"+44 1227 374583",
    "sg:postcode":"CT6 8JZ",
    "sg:province":"Kent",
    "sg:tags":[
        "builder"
    ],
    "wof:name":"G S Joiner & Sons Ltd.",
    "wof:placetype":"venue"
},
  "geometry": {"coordinates":[1.1251000166,51.3712158203],"type":"Point"}
}