{
  "type": "Feature",
  "properties": {
    "addr:full":"22 Althorpe Road, St James Northampton Northamptonshire NN5 5EF",
    "addr:housenumber":"22",
    "addr:postcode":"nn5 5ef",
    "addr:street":"Althorpe Road St",
    "iso:country":"GB",
    "sg:address":"22 Althorpe Road, St James",
    "sg:city":"Northampton",
    "sg:classifiers":[
        {
            "category":"Health Services",
            "subcategory":"Nursing And Care Facility",
            "type":"Services"
        },
        {
            "category":"Social Services",
            "subcategory":"Retirement Home",
            "type":"Services"
        }
    ],
    "sg:phone":"+44 1604 750329",
    "sg:postcode":"NN5 5EF",
    "sg:province":"Northamptonshire",
    "sg:tags":[
        "residential",
        "rest"
    ],
    "wof:name":"Hastings Lodge",
    "wof:placetype":"venue"
},
  "geometry": {"coordinates":[-0.9135149717,52.2400093079],"type":"Point"}
}