{
  "type": "Feature",
  "properties": {
    "iso:country":"GB",
    "sg:address":"16 Avenue Road",
    "sg:city":"Malvern",
    "sg:classifiers":[
        {
            "category":"Travel",
            "subcategory":"Hotels & Motels",
            "type":"Entertainment"
        }
    ],
    "sg:postcode":"WR14 3AR",
    "sg:province":"Herefordshire",
    "wof:name":"Thornbury House Hotel",
    "wof:placetype":"venue"
},
  "geometry": {"coordinates":[-2.3198258877,52.1099281311],"type":"Point"}
}