{
  "type": "Feature",
  "properties": {
    "addr:full":"Warmsworth Halt Industrial Estate, Edlington Lane Doncaster South Yorkshire DN4 9LS",
    "addr:postcode":"dn4 9ls",
    "addr:street":"Industrial Estate Edlington Lane",
    "iso:country":"GB",
    "sg:address":"Warmsworth Halt Industrial Estate, Edlington Lane",
    "sg:city":"Doncaster",
    "sg:classifiers":[
        {
            "category":"Manufacturing",
            "subcategory":"Building Materials",
            "type":"Manufacturing & Wholesale Goods"
        }
    ],
    "sg:phone":"+44 1302 853972",
    "sg:postcode":"DN4 9LS",
    "sg:province":"South Yorkshire",
    "sg:tags":[
        "extrusion"
    ],
    "wof:name":"Concept",
    "wof:placetype":"venue"
},
  "geometry": {"coordinates":[-1.184097,53.492977],"type":"Point"}
}