{
  "type": "Feature",
  "properties": {
    "iso:country":"GB",
    "sg:address":"116 Dashwood Avenue",
    "sg:city":"High Wycombe",
    "sg:classifiers":[
        {
            "category":"Retail",
            "subcategory":"Driving School",
            "type":"Services"
        }
    ],
    "sg:phone":"+44 1494 528464",
    "sg:postcode":"HP12 3EB",
    "sg:province":"Buckinghamshire",
    "wof:name":"Ali Driving School",
    "wof:placetype":"venue"
},
  "geometry": {"coordinates":[-0.773048,51.633789],"type":"Point"}
}