{
  "type": "Feature",
  "properties": {
    "addr:full":"16 Streeton Way, Earls Barton Northampton Northamptonshire NN6 0HX",
    "addr:housenumber":"16",
    "addr:postcode":"nn6 0hx",
    "addr:street":"Streeton Way",
    "iso:country":"GB",
    "sg:address":"16 Streeton Way, Earls Barton",
    "sg:city":"Northampton",
    "sg:classifiers":[
        {
            "category":"Retail",
            "subcategory":"Driving School",
            "type":"Services"
        }
    ],
    "sg:postcode":"NN6 0HX",
    "sg:province":"Northamptonshire",
    "wof:name":"Jim's School of Motoring",
    "wof:placetype":"venue"
},
  "geometry": {"coordinates":[-0.7544530034,52.2696762085],"type":"Point"}
}