{
  "type": "Feature",
  "properties": {
    "addr:full":"80 Wardles La Walsall Staffordshire WS6 6DY",
    "addr:housenumber":"80",
    "addr:postcode":"ws6 6dy",
    "addr:street":"Wardles La",
    "iso:country":"GB",
    "sg:address":"80 Wardles La",
    "sg:city":"Walsall",
    "sg:classifiers":[
        {
            "category":"Shopping",
            "subcategory":"Florist",
            "type":"Retail Goods"
        }
    ],
    "sg:phone":"+44 1922 410562",
    "sg:postcode":"WS6 6DY",
    "sg:province":"Staffordshire",
    "wof:name":"The Window Box",
    "wof:placetype":"venue"
},
  "geometry": {"coordinates":[-2.0180199146,52.6580238342],"type":"Point"}
}