{
  "type": "Feature",
  "properties": {
    "addr:full":"121 Ashford Road, Laleham Staines Berkshire TW18 1RS",
    "addr:housenumber":"121",
    "addr:postcode":"tw18 1rs",
    "addr:street":"Ashford Road",
    "iso:country":"GB",
    "sg:address":"121 Ashford Road, Laleham",
    "sg:city":"Staines",
    "sg:classifiers":[
        {
            "category":"Autos & Motor Vehicles",
            "subcategory":"Automobile Sales",
            "type":"Retail Goods"
        }
    ],
    "sg:phone":"+44 1784 242217",
    "sg:postcode":"TW18 1RS",
    "sg:province":"Berkshire",
    "sg:tags":[
        "commercial"
    ],
    "wof:name":"Jap 4x4 Centre Ltd.",
    "wof:placetype":"venue"
},
  "geometry": {"coordinates":[-0.4838779867,51.4154319763],"type":"Point"}
}