{
  "type": "Feature",
  "properties": {
    "addr:full":"R/o St Peters C Of E Primary Sc, Hool, Cowfold Horsham West Sussex RH13 8DA",
    "addr:postcode":"rh13 8da",
    "addr:street":"/ O;Cowfold",
    "iso:country":"GB",
    "sg:address":"R/o St Peters C Of E Primary Sc, Hool, Cowfold",
    "sg:city":"Horsham",
    "sg:classifiers":[
        {
            "category":"Education",
            "subcategory":"Preschool",
            "type":"Public Place"
        }
    ],
    "sg:phone":"+44 1403 864011",
    "sg:postcode":"RH13 8DA",
    "sg:province":"West Sussex",
    "sg:tags":[
        "pre-school",
        "playgroups"
    ],
    "wof:name":"Country Mice Cowfold Pre School Group",
    "wof:placetype":"venue"
},
  "geometry": {"coordinates":[-0.272624,50.990219],"type":"Point"}
}