{
  "type": "Feature",
  "properties": {
    "addr:full":"10 Friars Road Stafford Staffordshire ST17 4AA",
    "addr:housenumber":"10",
    "addr:postcode":"st17 4aa",
    "addr:street":"Friars Road",
    "iso:country":"GB",
    "sg:address":"10 Friars Road",
    "sg:city":"Stafford",
    "sg:classifiers":[
        {
            "category":"Professional",
            "subcategory":"Accounting & Tax Preparation",
            "type":"Services"
        }
    ],
    "sg:phone":"+44 1785 223388",
    "sg:postcode":"ST17 4AA",
    "sg:province":"Staffordshire",
    "sg:tags":[
        "accountant"
    ],
    "wof:name":"John Hulse & Co",
    "wof:placetype":"venue"
},
  "geometry": {"coordinates":[-2.116067,52.803101],"type":"Point"}
}