{
  "type": "Feature",
  "properties": {
    "addr:full":"Hainault Forest Community Centre, Manford Way Chigwell Essex IG7 4DF",
    "addr:postcode":"ig7 4df",
    "addr:street":"Manford Way",
    "iso:country":"GB",
    "sg:address":"Hainault Forest Community Centre, Manford Way",
    "sg:city":"Chigwell",
    "sg:classifiers":[
        {
            "category":"Professional",
            "subcategory":"Lawyer & Legal Services",
            "type":"Services"
        }
    ],
    "sg:phone":"+44 20 8500 3281",
    "sg:postcode":"IG7 4DF",
    "sg:province":"Essex",
    "sg:tags":[
        "advice",
        "counselling"
    ],
    "wof:name":"Citizens Advice Bureau",
    "wof:placetype":"venue"
},
  "geometry": {"coordinates":[0.0750949979,51.6189460754],"type":"Point"}
}