{
  "type": "Feature",
  "properties": {
    "iso:country":"GB",
    "sg:address":"Waterloo House, Bath Place",
    "sg:city":"Leamington Spa",
    "sg:classifiers":[
        {
            "category":"Professional",
            "subcategory":"Computer Services",
            "type":"Services"
        }
    ],
    "sg:phone":"+44 1926 888076",
    "sg:postcode":"CV31 3RJ",
    "sg:province":"Warwickshire",
    "sg:tags":[
        "system",
        "software"
    ],
    "wof:name":"Seskin Sytems",
    "wof:placetype":"venue"
},
  "geometry": {"coordinates":[-1.5332779884,52.284538269],"type":"Point"}
}