{
  "type": "Feature",
  "properties": {
    "addr:full":"23 Cardigan Dr Bury Lancashire BL9 9LG",
    "addr:housenumber":"23",
    "addr:postcode":"bl9 9lg",
    "addr:street":"Cardigan Dr",
    "iso:country":"GB",
    "sg:address":"23 Cardigan Dr",
    "sg:city":"Bury",
    "sg:classifiers":[
        {
            "category":"Building & Trades",
            "subcategory":"Construction",
            "type":"Services"
        }
    ],
    "sg:postcode":"BL9 9LG",
    "sg:province":"Lancashire",
    "sg:tags":[
        "bricklaying"
    ],
    "wof:name":"Acorn Construction & Building Contractor",
    "wof:placetype":"venue"
},
  "geometry": {"coordinates":[-2.3014729023,53.5798912048],"type":"Point"}
}