{
  "type": "Feature",
  "properties": {
    "addr:full":"12 Alloway Place Ayr South Ayrshire KA7 2AG",
    "addr:housenumber":"12",
    "addr:postcode":"ka7 2ag",
    "addr:street":"Alloway Place",
    "iso:country":"GB",
    "sg:address":"12 Alloway Place",
    "sg:city":"Ayr",
    "sg:classifiers":[
        {
            "category":"Professional",
            "subcategory":"Lawyer & Legal Services",
            "type":"Services"
        },
        {
            "category":"Real Estate",
            "subcategory":"Real Estate Agent",
            "type":"Services"
        }
    ],
    "sg:phone":"+44 1292 264696",
    "sg:postcode":"KA7 2AG",
    "sg:province":"South Ayrshire",
    "sg:tags":[
        "solicitor"
    ],
    "wof:name":"Mcmillan Kilpatrick",
    "wof:placetype":"venue"
},
  "geometry": {"coordinates":[-4.6354908943,55.4589958191],"type":"Point"}
}