{
  "type": "Feature",
  "properties": {
    "addr:full":"Crediton Rd Okehampton Devon EX20 1LS",
    "addr:postcode":"ex20 1ls",
    "addr:street":"Crediton Rd",
    "iso:country":"GB",
    "sg:address":"Crediton Rd",
    "sg:city":"Okehampton",
    "sg:classifiers":[
        {
            "category":"Manufacturing",
            "subcategory":"Chemicals & Compounds",
            "type":"Manufacturing & Wholesale Goods"
        }
    ],
    "sg:phone":"+44 1837 53999",
    "sg:postcode":"EX20 1LS",
    "sg:province":"Devon",
    "sg:tags":[
        "pesticide"
    ],
    "wof:name":"Gillbanks",
    "wof:placetype":"venue"
},
  "geometry": {"coordinates":[-3.9899139404,50.7445640564],"type":"Point"}
}