{
  "type": "Feature",
  "properties": {
    "addr:full":"Ardreigh, Beaconsfield Road Slough Berkshire SL2 3BP",
    "addr:postcode":"sl2 3bp",
    "addr:street":"Ardreigh Beaconsfield Road",
    "iso:country":"GB",
    "sg:address":"Ardreigh, Beaconsfield Road",
    "sg:city":"Slough",
    "sg:classifiers":[
        {
            "category":"Professional",
            "subcategory":"Employment Agencies",
            "type":"Services"
        }
    ],
    "sg:phone":"+44 1753 646348",
    "sg:postcode":"SL2 3BP",
    "sg:province":"Berkshire",
    "sg:tags":[
        "modelling"
    ],
    "wof:name":"Bubblegum Model Agency",
    "wof:placetype":"venue"
},
  "geometry": {"coordinates":[-0.615799,51.551899],"type":"Point"}
}