{
  "type": "Feature",
  "properties": {
    "addr:full":"Watercrof, Church Road, Penn High Wycombe Buckinghamshire HP10 8NX",
    "addr:postcode":"hp10 8nx",
    "addr:street":"Church Road",
    "iso:country":"GB",
    "sg:address":"Watercrof, Church Road, Penn",
    "sg:city":"High Wycombe",
    "sg:classifiers":[
        {
            "category":"Building & Trades",
            "subcategory":"Landscaping Services",
            "type":"Services"
        }
    ],
    "sg:postcode":"HP10 8NX",
    "sg:province":"Buckinghamshire",
    "sg:tags":[
        "forestry",
        "tree"
    ],
    "wof:name":"Penn Tree Services",
    "wof:placetype":"venue"
},
  "geometry": {"coordinates":[-0.676358,51.631306],"type":"Point"}
}