{
  "type": "Feature",
  "properties": {
    "addr:full":"3 West Ct Buntsford Pk Rd Bromsgrove Worcestershire B60 3DX",
    "addr:housenumber":"3",
    "addr:postcode":"b60 3dx",
    "addr:street":"West Ct Buntsford Pk Rd",
    "iso:country":"GB",
    "sg:address":"3 West Ct Buntsford Pk Rd",
    "sg:city":"Bromsgrove",
    "sg:classifiers":[
        {
            "category":"Building & Trades",
            "subcategory":"Construction",
            "type":"Services"
        }
    ],
    "sg:postcode":"B60 3DX",
    "sg:province":"Worcestershire",
    "sg:tags":[
        "waterproofing"
    ],
    "wof:name":"Llewellyn,Walter,& Sons Ltd",
    "wof:placetype":"venue"
},
  "geometry": {"coordinates":[-2.063649,52.31567],"type":"Point"}
}