{
  "type": "Feature",
  "properties": {
    "iso:country":"GB",
    "sg:address":"High St",
    "sg:city":"Bath",
    "sg:classifiers":[
        {
            "category":"Farming",
            "subcategory":"Nursery",
            "type":"Manufacturing & Wholesale Goods"
        }
    ],
    "sg:phone":"+44 1225 339843",
    "sg:postcode":"BA2 6SY",
    "sg:province":"Somerset",
    "sg:tags":[
        "creche"
    ],
    "wof:name":"Mulberry House Day Nursery",
    "wof:placetype":"venue"
},
  "geometry": {"coordinates":[-2.359129,51.38205],"type":"Point"}
}