{
  "type": "Feature",
  "properties": {
    "addr:full":"Po Box 10 Barry The Vale of Glamorgan CF63 1YE",
    "addr:housenumber":"po box 10",
    "addr:postcode":"cf63 1ye",
    "addr:street":"Barry The Vale",
    "iso:country":"GB",
    "sg:address":"Po Box 10",
    "sg:city":"Barry",
    "sg:classifiers":[
        {
            "category":"Professional",
            "subcategory":"Management & Consulting",
            "type":"Services"
        }
    ],
    "sg:postcode":"CF63 1YE",
    "sg:province":"The Vale of Glamorgan",
    "sg:tags":[
        "sport"
    ],
    "wof:name":"Merlin Leisure Ltd",
    "wof:placetype":"venue"
},
  "geometry": {"coordinates":[-3.25094,51.420212],"type":"Point"}
}