{
  "type": "Feature",
  "properties": {
    "iso:country":"GB",
    "sg:address":"4 Scotts Close, Churchstow",
    "sg:city":"Kingsbridge",
    "sg:classifiers":[
        {
            "category":"Building & Trades",
            "subcategory":"Construction",
            "type":"Services"
        }
    ],
    "sg:phone":"+44 1548 852277",
    "sg:postcode":"TQ7 3RB",
    "sg:province":"Devon",
    "sg:tags":[
        "builder"
    ],
    "wof:name":"Peter C Todd",
    "wof:placetype":"venue"
},
  "geometry": {"coordinates":[-3.8104250431,50.2980728149],"type":"Point"}
}