{
  "type": "Feature",
  "properties": {
    "iso:country":"GB",
    "sg:address":"South Farm, Shipton Oliffe",
    "sg:city":"Cheltenham",
    "sg:classifiers":[
        {
            "category":"Farming",
            "subcategory":"Livestock Farm",
            "type":"Manufacturing & Wholesale Goods"
        }
    ],
    "sg:postcode":"GL54 4JF",
    "sg:province":"Gloucestershire",
    "sg:tags":[
        "others"
    ],
    "wof:name":"Shipton Downs Farm",
    "wof:placetype":"venue"
},
  "geometry": {"coordinates":[-1.940404,51.866417],"type":"Point"}
}