{
  "type": "Feature",
  "properties": {
    "iso:country":"GB",
    "sg:address":"291 Rockingham Road",
    "sg:city":"Corby",
    "sg:classifiers":[
        {
            "category":"Professional",
            "subcategory":"Business Services",
            "type":"Services"
        }
    ],
    "sg:phone":"+44 1536 264433",
    "sg:postcode":"NN17 2AE",
    "sg:province":"Northamptonshire",
    "sg:tags":[
        "import",
        "export",
        "agent"
    ],
    "wof:name":"K Phones",
    "wof:placetype":"venue"
},
  "geometry": {"coordinates":[-0.708056,52.507286],"type":"Point"}
}