{
  "type": "Feature",
  "properties": {
    "addr:full":"Mousden Farm House, Halls Hole Road Tunbridge Wells East Sussex TN2 4RF",
    "addr:postcode":"tn2 4rf",
    "addr:street":"Hole Road",
    "iso:country":"GB",
    "sg:address":"Mousden Farm House, Halls Hole Road",
    "sg:city":"Tunbridge Wells",
    "sg:classifiers":[
        {
            "category":"Farming",
            "subcategory":"Livestock Farm",
            "type":"Manufacturing & Wholesale Goods"
        }
    ],
    "sg:phone":"+44 1892 823304",
    "sg:postcode":"TN2 4RF",
    "sg:province":"East Sussex",
    "sg:tags":[
        "others"
    ],
    "wof:name":"Cheveley Farms",
    "wof:placetype":"venue"
},
  "geometry": {"coordinates":[0.286133,51.13031],"type":"Point"}
}