{
  "type": "Feature",
  "properties": {
    "addr:full":"22 Woodstock Street London Greater London W1C 2AP",
    "addr:housenumber":"22",
    "addr:postcode":"w1c 2ap",
    "addr:street":"Woodstock Street",
    "iso:country":"GB",
    "sg:address":"22 Woodstock Street",
    "sg:city":"London",
    "sg:classifiers":[
        {
            "category":"Bars & Pubs",
            "type":"Food & Drink"
        }
    ],
    "sg:phone":"+44 20 7647 8931",
    "sg:postcode":"W1C 2AP",
    "sg:province":"Greater London",
    "sg:tags":[
        "pubs",
        "inn"
    ],
    "wof:name":"O'Neills",
    "wof:placetype":"venue"
},
  "geometry": {"coordinates":[-0.1472769976,51.5138931274],"type":"Point"}
}