{
  "type": "Feature",
  "properties": {
    "iso:country":"GB",
    "sg:address":"Kintyre Place",
    "sg:city":"Tarbert",
    "sg:classifiers":[
        {
            "category":"Bus Charters",
            "type":"Transportation"
        },
        {
            "category":"Military Area",
            "subcategory":"Air Force Base",
            "type":"Public Place"
        }
    ],
    "sg:phone":"+44 1880 820220",
    "sg:postcode":"PA29 6UL",
    "sg:province":"Argyll and Bute",
    "sg:tags":[
        "taxi",
        "hire",
        "coach",
        "private"
    ],
    "wof:name":"Henderson Hiring",
    "wof:placetype":"venue"
},
  "geometry": {"coordinates":[-5.414889,55.86311],"type":"Point"}
}