{
  "type": "Feature",
  "properties": {
    "iso:country":"GB",
    "sg:address":"27 Durham Road, Sacriston",
    "sg:city":"Durham",
    "sg:classifiers":[
        {
            "category":"Professional",
            "subcategory":"Printing & Photocopies",
            "type":"Services"
        }
    ],
    "sg:phone":"+44 191 371 9371",
    "sg:postcode":"DH7 6LN",
    "sg:province":"Durham",
    "sg:tags":[
        "embroiderer"
    ],
    "wof:name":"Sagittarian Embroidery Ltd.",
    "wof:placetype":"venue"
},
  "geometry": {"coordinates":[-1.6248860359,54.8165740967],"type":"Point"}
}