{
  "type": "Feature",
  "properties": {
    "iso:country":"GB",
    "sg:address":"1 Park Lane, Colney Heath",
    "sg:city":"St Albans",
    "sg:classifiers":[
        {
            "category":"Shopping",
            "subcategory":"Department Store",
            "type":"Retail Goods"
        }
    ],
    "sg:phone":"+44 1727 822662",
    "sg:postcode":"AL4 0NR",
    "sg:province":"Hertfordshire",
    "wof:name":"Colney Heath Store",
    "wof:placetype":"venue"
},
  "geometry": {"coordinates":[-0.2621150017,51.7399902344],"type":"Point"}
}