{
  "type": "Feature",
  "properties": {
    "iso:country":"GB",
    "sg:address":"Dukesway Teesside Indust Est",
    "sg:city":"Stockton-on-tees",
    "sg:classifiers":[
        {
            "category":"Professional",
            "subcategory":"Computer Services",
            "type":"Services"
        }
    ],
    "sg:postcode":"TS17 9LT",
    "sg:province":"Durham",
    "sg:tags":[
        "system",
        "software"
    ],
    "wof:name":"Cendris 1 Ltd",
    "wof:placetype":"venue"
},
  "geometry": {"coordinates":[-1.292764,54.51828],"type":"Point"}
}