{
  "type": "Feature",
  "properties": {
    "addr:full":"1 Nayworth Cotts, Cross Street Sudbury Essex CO10 2DS",
    "addr:housenumber":"1",
    "addr:postcode":"co10 2ds",
    "addr:street":"Nayworth Cotts Cross Street",
    "iso:country":"GB",
    "sg:address":"1 Nayworth Cotts, Cross Street",
    "sg:city":"Sudbury",
    "sg:classifiers":[
        {
            "category":"Retail",
            "subcategory":"Driving School",
            "type":"Services"
        }
    ],
    "sg:postcode":"CO10 2DS",
    "sg:province":"Essex",
    "wof:name":"P G M School of Motoring",
    "wof:placetype":"venue"
},
  "geometry": {"coordinates":[0.7343900204,52.0386047363],"type":"Point"}
}