{
  "type": "Feature",
  "properties": {
    "addr:full":"14 High Street Glenrothes Fife KY7 6DQ",
    "addr:housenumber":"14",
    "addr:postcode":"ky7 6dq",
    "addr:street":"High Street",
    "iso:country":"GB",
    "sg:address":"14 High Street",
    "sg:city":"Glenrothes",
    "sg:classifiers":[
        {
            "category":"Real Estate",
            "subcategory":"Surveying",
            "type":"Services"
        }
    ],
    "sg:phone":"+44 1592 610130",
    "sg:postcode":"KY7 6DQ",
    "sg:province":"Fife",
    "sg:tags":[
        "surveyor",
        "land"
    ],
    "wof:name":"Laimar Engineering Ltd.",
    "wof:placetype":"venue"
},
  "geometry": {"coordinates":[-3.131582,56.20203],"type":"Point"}
}