{
  "type": "Feature",
  "properties": {
    "addr:full":"Glasgow Road Cross Mill, Barrhead Glasgow East Ayrshire G78 1TH",
    "addr:postcode":"g78 1th",
    "addr:street":"Glasgow Road",
    "iso:country":"GB",
    "sg:address":"Glasgow Road Cross Mill, Barrhead",
    "sg:city":"Glasgow",
    "sg:classifiers":[
        {
            "category":"Autos & Motor Vehicles",
            "subcategory":"Auto Supplies",
            "type":"Retail Goods"
        },
        {
            "category":"Retail",
            "subcategory":"Auto Repair",
            "type":"Services"
        }
    ],
    "sg:phone":"+44 141 881 5651",
    "sg:postcode":"G78 1TH",
    "sg:province":"East Ayrshire",
    "sg:tags":[
        "car",
        "specialist",
        "tyre",
        "customizing"
    ],
    "wof:name":"Ats",
    "wof:placetype":"venue"
},
  "geometry": {"coordinates":[-4.4044981003,55.7953147888],"type":"Point"}
}