{
  "type": "Feature",
  "properties": {
    "addr:full":"Frodesley, Dorrington Shrewsbury Shrewsbury Shropshire SY5 7HA",
    "addr:housenumber":"frodesley",
    "addr:postcode":"sy5 7ha",
    "addr:street":"Dorrington Shrewsbury",
    "iso:country":"GB",
    "sg:address":"Frodesley, Dorrington Shrewsbury",
    "sg:city":"Shrewsbury",
    "sg:classifiers":[
        {
            "category":"Retail",
            "subcategory":"Auto Repair",
            "type":"Services"
        }
    ],
    "sg:phone":"+44 1694 731679",
    "sg:postcode":"SY5 7HA",
    "sg:province":"Shropshire",
    "sg:tags":[
        "modification",
        "garage"
    ],
    "wof:name":"Jasmine Cottage Garage",
    "wof:placetype":"venue"
},
  "geometry": {"coordinates":[-2.7733991146,52.6224136353],"type":"Point"}
}