{
  "type": "Feature",
  "properties": {
    "addr:full":"121 High Street Staines Berkshire TW18 4PD",
    "addr:housenumber":"121",
    "addr:postcode":"tw18 4pd",
    "addr:street":"High Street",
    "iso:country":"GB",
    "sg:address":"121 High Street",
    "sg:city":"Staines",
    "sg:classifiers":[
        {
            "category":"Shopping",
            "subcategory":"Books",
            "type":"Retail Goods"
        }
    ],
    "sg:phone":"+44 1784 457194",
    "sg:postcode":"TW18 4PD",
    "sg:province":"Berkshire",
    "sg:tags":[
        "bookseller",
        "retailer"
    ],
    "wof:name":"Canaan Christian Centre",
    "wof:placetype":"venue"
},
  "geometry": {"coordinates":[-0.5085870028,51.4349327087],"type":"Point"}
}