{
  "type": "Feature",
  "properties": {
    "addr:full":"Unit 17 The Food Centre, Central Milton Keynes Milton Keynes Buckinghamshire MK9 3NT",
    "addr:housenumber":"unit 17 the",
    "addr:postcode":"mk9 3nt",
    "iso:country":"GB",
    "sg:address":"Unit 17 The Food Centre, Central Milton Keynes",
    "sg:city":"Milton Keynes",
    "sg:classifiers":[
        {
            "category":"Food & Beverages",
            "subcategory":"Specialty",
            "type":"Retail Goods"
        }
    ],
    "sg:phone":"+44 1908 690721",
    "sg:postcode":"MK9 3NT",
    "sg:province":"Buckinghamshire",
    "sg:tags":[
        "product",
        "health"
    ],
    "wof:name":"Holland & Barrett",
    "wof:placetype":"venue"
},
  "geometry": {"coordinates":[-0.7545589805,52.0413551331],"type":"Point"}
}