{
  "type": "Feature",
  "properties": {
    "addr:full":"Cameron Street, Splott Cardiff Cardiff CF24 2NX",
    "addr:postcode":"cf24 2nx",
    "addr:street":"Cameron Street",
    "iso:country":"GB",
    "sg:address":"Cameron Street, Splott",
    "sg:city":"Cardiff",
    "sg:classifiers":[
        {
            "category":"Place Of Worship",
            "type":"Public Place"
        }
    ],
    "sg:phone":"+44 29 2046 3219",
    "sg:postcode":"CF24 2NX",
    "sg:province":"Cardiff",
    "wof:name":"St Albans R C Church",
    "wof:placetype":"venue"
},
  "geometry": {"coordinates":[-3.1510539055,51.4831504822],"type":"Point"}
}