{
  "type": "Feature",
  "properties": {
    "iso:country":"GB",
    "sg:address":"4 Copley Road",
    "sg:city":"Doncaster",
    "sg:classifiers":[
        {
            "category":"Restaurant",
            "type":"Food & Drink"
        }
    ],
    "sg:phone":"+44 1302 818700",
    "sg:postcode":"DN1 2PF",
    "sg:province":"South Yorkshire",
    "sg:tags":[
        "indian"
    ],
    "wof:name":"Raaj Indian Cuisine",
    "wof:placetype":"venue"
},
  "geometry": {"coordinates":[-1.1308059692,53.5255508423],"type":"Point"}
}