{
  "type": "Feature",
  "properties": {
    "addr:full":"Church Road, Felsham Bury St Edmunds Suffolk IP30 0PJ",
    "addr:postcode":"ip30 0pj",
    "addr:street":"Church Road",
    "iso:country":"GB",
    "sg:address":"Church Road, Felsham",
    "sg:city":"Bury St Edmunds",
    "sg:classifiers":[
        {
            "category":"Bars & Pubs",
            "type":"Food & Drink"
        },
        {
            "category":"Community Center",
            "subcategory":"Social",
            "type":"Public Place"
        }
    ],
    "sg:phone":"+44 1449 737268",
    "sg:postcode":"IP30 0PJ",
    "sg:province":"Suffolk",
    "sg:tags":[
        "pubs",
        "house",
        "inn",
        "activity"
    ],
    "wof:name":"The Six Bells",
    "wof:placetype":"venue"
},
  "geometry": {"coordinates":[0.793889,52.204624],"type":"Point"}
}