{
  "type": "Feature",
  "properties": {
    "iso:country":"GB",
    "sg:address":"205 Broadmarsh Centre",
    "sg:city":"Nottingham",
    "sg:classifiers":[
        {
            "category":"Shopping",
            "subcategory":"Pets & Pet Supplies",
            "type":"Retail Goods"
        }
    ],
    "sg:phone":"+44 115 959 9071",
    "sg:postcode":"NG1 7LR",
    "sg:province":"Nottinghamshire",
    "wof:name":"Care for Pets Ltd.",
    "wof:placetype":"venue"
},
  "geometry": {"coordinates":[-1.146438,52.949715],"type":"Point"}
}