{
  "type": "Feature",
  "properties": {
    "addr:full":"Unit 5 & 8 Chalon Industrial Estate, Chalon Way St Helens Merseyside WA10 1AU",
    "addr:housenumber":"unit 5 & 8",
    "addr:postcode":"wa10 1au",
    "addr:street":"Chalon Industrial;Chalon Way",
    "iso:country":"GB",
    "sg:address":"Unit 5 & 8 Chalon Industrial Estate, Chalon Way",
    "sg:city":"St Helens",
    "sg:classifiers":[
        {
            "category":"Manufacturing",
            "subcategory":"Building Materials",
            "type":"Manufacturing & Wholesale Goods"
        }
    ],
    "sg:phone":"+44 1744 617340",
    "sg:postcode":"WA10 1AU",
    "sg:province":"Merseyside",
    "sg:tags":[
        "merchant",
        "builder"
    ],
    "wof:name":"Kestral Construction Products",
    "wof:placetype":"venue"
},
  "geometry": {"coordinates":[-2.73341,53.44923],"type":"Point"}
}