{
  "type": "Feature",
  "properties": {
    "addr:full":"Unit 7, Handlemaker Road, Marston Trading Estate Frome Somerset BA11 4RW",
    "addr:housenumber":"unit 7",
    "addr:postcode":"ba11 4rw",
    "addr:street":"Handlemaker Road;Trading Estate",
    "iso:country":"GB",
    "sg:address":"Unit 7, Handlemaker Road, Marston Trading Estate",
    "sg:city":"Frome",
    "sg:classifiers":[
        {
            "category":"Personal",
            "type":"Services"
        }
    ],
    "sg:postcode":"BA11 4RW",
    "sg:province":"Somerset",
    "sg:tags":[
        "delivery"
    ],
    "wof:name":"Frome Delivery Service",
    "wof:placetype":"venue"
},
  "geometry": {"coordinates":[-2.3281910419,51.2193641663],"type":"Point"}
}