{
  "type": "Feature",
  "properties": {
    "addr:full":"Hanslope County Combined School, Long Street Road, Hanslope Milton Keynes Buckinghamshire MK19 7BL",
    "addr:postcode":"buckinghamshire mk19 7bl",
    "addr:street":"Long Street Road",
    "iso:country":"GB",
    "sg:address":"Hanslope County Combined School, Long Street Road, Hanslope",
    "sg:city":"Milton Keynes",
    "sg:classifiers":[
        {
            "category":"Farming",
            "subcategory":"Nursery",
            "type":"Manufacturing & Wholesale Goods"
        }
    ],
    "sg:phone":"+44 1908 511810",
    "sg:postcode":"MK19 7BL",
    "sg:province":"Buckinghamshire",
    "sg:tags":[
        "creche"
    ],
    "wof:name":"Little Meadows Day Nursery",
    "wof:placetype":"venue"
},
  "geometry": {"coordinates":[-0.8279889822,52.1151390076],"type":"Point"}
}