{
  "type": "Feature",
  "properties": {
    "addr:full":"48 High Street Brierley Hill West Midlands DY5 3AE",
    "addr:housenumber":"48",
    "addr:postcode":"dy5 3ae",
    "addr:street":"High Street",
    "iso:country":"GB",
    "sg:address":"48 High Street",
    "sg:city":"Brierley Hill",
    "sg:classifiers":[
        {
            "category":"Food & Beverages",
            "subcategory":"Meat & Fish",
            "type":"Retail Goods"
        }
    ],
    "sg:phone":"+44 1384 262982",
    "sg:postcode":"DY5 3AE",
    "sg:province":"West Midlands",
    "sg:tags":[
        "chip"
    ],
    "wof:name":"Concord Fish Bar",
    "wof:placetype":"venue"
},
  "geometry": {"coordinates":[-2.12191,52.479759],"type":"Point"}
}