{
  "type": "Feature",
  "properties": {
    "addr:full":"The Old Bakery, Cherry St Woking Surrey GU21 1EE",
    "addr:postcode":"gu21 1ee",
    "addr:street":"Cherry St",
    "iso:country":"GB",
    "sg:address":"The Old Bakery, Cherry St",
    "sg:city":"Woking",
    "sg:classifiers":[
        {
            "category":"Real Estate",
            "subcategory":"Developer",
            "type":"Services"
        }
    ],
    "sg:postcode":"GU21 1EE",
    "sg:province":"Surrey",
    "sg:tags":[
        "property"
    ],
    "wof:name":"Hg Construction Ltd",
    "wof:placetype":"venue"
},
  "geometry": {"coordinates":[-0.5585500002,51.3220748901],"type":"Point"}
}