{
  "type": "Feature",
  "properties": {
    "addr:full":"Bromley Farm, Bromley Bridgnorth Shropshire WV15 5JP",
    "addr:postcode":"wv15 5jp",
    "iso:country":"GB",
    "sg:address":"Bromley Farm, Bromley",
    "sg:city":"Bridgnorth",
    "sg:classifiers":[
        {
            "category":"Farming",
            "subcategory":"Livestock Farm",
            "type":"Manufacturing & Wholesale Goods"
        }
    ],
    "sg:phone":"+44 1746 762257",
    "sg:postcode":"WV15 5JP",
    "sg:province":"Shropshire",
    "sg:tags":[
        "others"
    ],
    "wof:name":"R & B Rochelle",
    "wof:placetype":"venue"
},
  "geometry": {"coordinates":[-2.3941190243,52.5555038452],"type":"Point"}
}