{
  "type": "Feature",
  "properties": {
    "addr:full":"Avondale, Dorking Road Tadworth Surrey KT20 5SA",
    "addr:postcode":"kt20 5sa",
    "addr:street":"Dorking Road",
    "iso:country":"GB",
    "sg:address":"Avondale, Dorking Road",
    "sg:city":"Tadworth",
    "sg:classifiers":[
        {
            "category":"Shopping",
            "subcategory":"Clothing, Apparel, & Fashions",
            "type":"Retail Goods"
        }
    ],
    "sg:phone":"+44 1737 814992",
    "sg:postcode":"KT20 5SA",
    "sg:province":"Surrey",
    "sg:tags":[
        "shop"
    ],
    "wof:name":"Hoot Ltd.",
    "wof:placetype":"venue"
},
  "geometry": {"coordinates":[-0.235149,51.291538],"type":"Point"}
}