{
  "type": "Feature",
  "properties": {
    "addr:full":"Cheney Hill Farm, Edgmond Newport Shropshire TF10 8EH",
    "addr:postcode":"tf10 8eh",
    "addr:street":"Cheney Hill",
    "iso:country":"GB",
    "sg:address":"Cheney Hill Farm, Edgmond",
    "sg:city":"Newport",
    "sg:classifiers":[
        {
            "category":"Professional",
            "subcategory":"Engineering",
            "type":"Services"
        }
    ],
    "sg:phone":"+44 1952 810157",
    "sg:postcode":"TF10 8EH",
    "sg:province":"Shropshire",
    "sg:tags":[
        "civil",
        "engineer"
    ],
    "wof:name":"O'Connell Construction Ltd.",
    "wof:placetype":"venue"
},
  "geometry": {"coordinates":[-2.4108490944,52.7730445862],"type":"Point"}
}