{
  "type": "Feature",
  "properties": {
    "addr:full":"The Street Ashford Kent TN24 9HA",
    "addr:postcode":"tn24 9ha",
    "addr:street":"The Street",
    "iso:country":"GB",
    "sg:address":"The Street",
    "sg:city":"Ashford",
    "sg:classifiers":[
        {
            "category":"Place Of Worship",
            "type":"Public Place"
        }
    ],
    "sg:phone":"+44 1233 664820",
    "sg:postcode":"TN24 9HA",
    "sg:province":"Kent",
    "wof:name":"St Mary Church Kennington",
    "wof:placetype":"venue"
},
  "geometry": {"coordinates":[0.8949750066,51.1678962708],"type":"Point"}
}