{
  "type": "Feature",
  "properties": {
    "iso:country":"GB",
    "sg:address":"22 Evison Road, Rothwell",
    "sg:city":"Kettering",
    "sg:classifiers":[
        {
            "category":"Retail",
            "subcategory":"Driving School",
            "type":"Services"
        }
    ],
    "sg:phone":"+44 1536 713033",
    "sg:postcode":"NN14 6AL",
    "sg:province":"Northamptonshire",
    "wof:name":"Just-Be-Safe",
    "wof:placetype":"venue"
},
  "geometry": {"coordinates":[-0.8038110137,52.4192428589],"type":"Point"}
}