{
  "type": "Feature",
  "properties": {
    "iso:country":"GB",
    "sg:address":"Woodside Farm, Wreay",
    "sg:city":"Carlisle",
    "sg:classifiers":[
        {
            "category":"Farming",
            "subcategory":"Dairy Farm",
            "type":"Manufacturing & Wholesale Goods"
        }
    ],
    "sg:phone":"+44 16974 73223",
    "sg:postcode":"CA4 0RJ",
    "sg:province":"Cumbria",
    "sg:tags":[
        "farmer"
    ],
    "wof:name":"R J WILSON",
    "wof:placetype":"venue"
},
  "geometry": {"coordinates":[-2.8803539276,54.8319702148],"type":"Point"}
}