{
  "type": "Feature",
  "properties": {
    "iso:country":"GB",
    "sg:address":"10 Lynedoch Crescent",
    "sg:city":"Glasgow",
    "sg:classifiers":[
        {
            "category":"Real Estate",
            "subcategory":"Surveying",
            "type":"Services"
        }
    ],
    "sg:phone":"+44 141 332 6466",
    "sg:postcode":"G3 6EQ",
    "sg:province":"Glasgow City",
    "sg:tags":[
        "surveyor",
        "valuer"
    ],
    "wof:name":"Fotheringham & Co.",
    "wof:placetype":"venue"
},
  "geometry": {"coordinates":[-4.274698,55.869015],"type":"Point"}
}