{
  "type": "Feature",
  "properties": {
    "addr:full":"10 St Swithins Street Worcester Worcestershire WR1 2PS",
    "addr:housenumber":"10",
    "addr:postcode":"wr1 2ps",
    "addr:street":"St Swithins Street",
    "iso:country":"GB",
    "sg:address":"10 St Swithins Street",
    "sg:city":"Worcester",
    "sg:classifiers":[
        {
            "category":"Health Services",
            "subcategory":"Optometrist",
            "type":"Services"
        }
    ],
    "sg:phone":"+44 1905 613037",
    "sg:postcode":"WR1 2PS",
    "sg:province":"Worcestershire",
    "sg:tags":[
        "optician"
    ],
    "wof:name":"Specexpress",
    "wof:placetype":"venue"
},
  "geometry": {"coordinates":[-2.220048,52.192841],"type":"Point"}
}