{
  "type": "Feature",
  "properties": {
    "addr:full":"Cholerford Bridge, South Station, Hexham-on-tyne Hexham Northumberland NE46 4EW",
    "addr:postcode":"ne46 4ew",
    "addr:street":"Bridge South Station Hexham-On-Tyne",
    "iso:country":"GB",
    "sg:address":"Cholerford Bridge, South Station, Hexham-on-tyne",
    "sg:city":"Hexham",
    "sg:classifiers":[
        {
            "category":"Autos & Motor Vehicles",
            "subcategory":"Fuel & Gas Station",
            "type":"Retail Goods"
        },
        {
            "category":"Bus Charters",
            "type":"Transportation"
        }
    ],
    "sg:postcode":"NE46 4EW",
    "sg:province":"Northumberland",
    "sg:tags":[
        "petrol",
        "filling",
        "coach",
        "hire"
    ],
    "wof:name":"A A Jewitt & Sons",
    "wof:placetype":"venue"
},
  "geometry": {"coordinates":[-2.12728,55.029942],"type":"Point"}
}