{
  "type": "Feature",
  "properties": {
    "iso:country":"GB",
    "sg:address":"Green Team Works, Tillbridge Road, Sturton By Stow",
    "sg:city":"Lincoln",
    "sg:classifiers":[
        {
            "category":"Building & Trades",
            "subcategory":"Plumbing",
            "type":"Services"
        },
        {
            "category":"Building & Trades",
            "subcategory":"Construction",
            "type":"Services"
        }
    ],
    "sg:postcode":"LN1 2BP",
    "sg:province":"Lincolnshire",
    "sg:tags":[
        "central",
        "installation",
        "system",
        "servicing",
        "heating"
    ],
    "wof:name":"B G Green",
    "wof:placetype":"venue"
},
  "geometry": {"coordinates":[-0.676354,53.327076],"type":"Point"}
}