{
  "type": "Feature",
  "properties": {
    "addr:full":"131 Silbury Arcade Milton Keynes Buckinghamshire MK9 3AQ",
    "addr:housenumber":"131",
    "addr:postcode":"mk9 3aq",
    "addr:street":"Silbury Arcade",
    "iso:country":"GB",
    "sg:address":"131 Silbury Arcade",
    "sg:city":"Milton Keynes",
    "sg:classifiers":[
        {
            "category":"Sports & Exercise",
            "subcategory":"Sports Center",
            "type":"Entertainment"
        }
    ],
    "sg:phone":"+44 1908 604284",
    "sg:postcode":"MK9 3AQ",
    "sg:province":"Buckinghamshire",
    "sg:tags":[
        "shop",
        "good"
    ],
    "wof:name":"J J B Sports Plc",
    "wof:placetype":"venue"
},
  "geometry": {"coordinates":[-0.759709,52.043072],"type":"Point"}
}