{
  "type": "Feature",
  "properties": {
    "addr:full":"139 Anns Hill Road Gosport Hampshire PO12 3RE",
    "addr:housenumber":"139",
    "addr:postcode":"po12 3re",
    "addr:street":"Anns Hill Road",
    "iso:country":"GB",
    "sg:address":"139 Anns Hill Road",
    "sg:city":"Gosport",
    "sg:classifiers":[
        {
            "category":"Personal",
            "subcategory":"Beauty Salon",
            "type":"Services"
        }
    ],
    "sg:phone":"+44 23 9258 0855",
    "sg:postcode":"PO12 3RE",
    "sg:province":"Hampshire",
    "sg:tags":[
        "ladies",
        "lady",
        "hairdresser"
    ],
    "wof:name":"Lady Ann",
    "wof:placetype":"venue"
},
  "geometry": {"coordinates":[-1.1483999491,50.7962150574],"type":"Point"}
}