{
  "type": "Feature",
  "properties": {
    "iso:country":"GB",
    "sg:address":"High Street, Oakhill",
    "sg:city":"Bath",
    "sg:classifiers":[
        {
            "category":"Government",
            "subcategory":"Post Office",
            "type":"Public Place"
        }
    ],
    "sg:phone":"+44 1749 840201",
    "sg:postcode":"BA3 5AS",
    "sg:province":"Somerset",
    "wof:name":"Oakhill Stores",
    "wof:placetype":"venue"
},
  "geometry": {"coordinates":[-2.525944,51.223583],"type":"Point"}
}