{
  "type": "Feature",
  "properties": {
    "addr:full":"37 Camelot Street Nottingham Nottinghamshire NG11 6AS",
    "addr:housenumber":"37",
    "addr:postcode":"ng11 6as",
    "addr:street":"Camelot Street",
    "iso:country":"GB",
    "sg:address":"37 Camelot Street",
    "sg:city":"Nottingham",
    "sg:classifiers":[
        {
            "category":"Manufacturing",
            "subcategory":"Wood Products",
            "type":"Manufacturing & Wholesale Goods"
        }
    ],
    "sg:phone":"+44 115 984 7034",
    "sg:postcode":"NG11 6AS",
    "sg:province":"Nottinghamshire",
    "sg:tags":[
        "woodturning"
    ],
    "wof:name":"Brian Wroughton",
    "wof:placetype":"venue"
},
  "geometry": {"coordinates":[-1.162456,52.976826],"type":"Point"}
}