{
  "type": "Feature",
  "properties": {
    "iso:country":"GB",
    "sg:address":"62 Sunningdale Way, Bletchley",
    "sg:city":"Milton Keynes",
    "sg:classifiers":[
        {
            "category":"Home & Garden",
            "subcategory":"Carpets & Floor Coverings",
            "type":"Retail Goods"
        }
    ],
    "sg:postcode":"MK3 7SB",
    "sg:province":"Buckinghamshire",
    "sg:tags":[
        "carpets",
        "rug",
        "matting"
    ],
    "wof:name":"Carpet Craft Mk",
    "wof:placetype":"venue"
},
  "geometry": {"coordinates":[-0.7692400217,51.9949531555],"type":"Point"}
}