{
  "type": "Feature",
  "properties": {
    "addr:full":"Methil Power Station, The Docks Leven Fife KY8 3RE",
    "addr:postcode":"ky8 3re",
    "iso:country":"GB",
    "sg:address":"Methil Power Station, The Docks",
    "sg:city":"Leven",
    "sg:classifiers":[
        {
            "category":"Utilities",
            "subcategory":"Electric",
            "type":"Services"
        }
    ],
    "sg:phone":"+44 1333 423163",
    "sg:postcode":"KY8 3RE",
    "sg:province":"Fife",
    "sg:tags":[
        "electricity"
    ],
    "wof:name":"ScottishPower",
    "wof:placetype":"venue"
},
  "geometry": {"coordinates":[-3.0226891041,56.1882286072],"type":"Point"}
}