{
  "type": "Feature",
  "properties": {
    "addr:full":"210 Moor St West Bromwich West Midlands B70 7AR",
    "addr:housenumber":"210",
    "addr:postcode":"b70 7ar",
    "addr:street":"Moor St West",
    "iso:country":"GB",
    "sg:address":"210 Moor St",
    "sg:city":"West Bromwich",
    "sg:classifiers":[
        {
            "category":"Retail",
            "subcategory":"Laundry & Dry Cleaning",
            "type":"Services"
        }
    ],
    "sg:postcode":"B70 7AR",
    "sg:province":"West Midlands",
    "sg:tags":[
        "launderette"
    ],
    "wof:name":"Washeteria",
    "wof:placetype":"venue"
},
  "geometry": {"coordinates":[-1.9985749722,52.5160293579],"type":"Point"}
}