{
  "type": "Feature",
  "properties": {
    "addr:full":"Oxpens Road Oxford Oxfordshire OX1 1RX",
    "addr:postcode":"ox1 1rx",
    "addr:street":"Oxpens Road",
    "iso:country":"GB",
    "sg:address":"Oxpens Road",
    "sg:city":"Oxford",
    "sg:classifiers":[
        {
            "category":"Retail",
            "subcategory":"Auto Repair",
            "type":"Services"
        }
    ],
    "sg:postcode":"OX1 1RX",
    "sg:province":"Oxfordshire",
    "sg:tags":[
        "modification",
        "garage"
    ],
    "wof:name":"Apples Car Clinic",
    "wof:placetype":"venue"
},
  "geometry": {"coordinates":[-1.266100049,51.7495918274],"type":"Point"}
}