{
  "type": "Feature",
  "properties": {
    "addr:full":"114 Beckenham Lane Bromley Kent BR2 0DU",
    "addr:housenumber":"114",
    "addr:postcode":"br2 0du",
    "addr:street":"Beckenham Lane",
    "iso:country":"GB",
    "sg:address":"114 Beckenham Lane",
    "sg:city":"Bromley",
    "sg:classifiers":[
        {
            "category":"Retail",
            "subcategory":"Repair Shop",
            "type":"Services"
        }
    ],
    "sg:phone":"+44 20 8460 8921",
    "sg:postcode":"BR2 0DU",
    "sg:province":"Kent",
    "sg:tags":[
        "radio",
        "television",
        "video"
    ],
    "wof:name":"Radio Vision (Bromley) Ltd.",
    "wof:placetype":"venue"
},
  "geometry": {"coordinates":[0.002185,51.406334],"type":"Point"}
}