{
  "type": "Feature",
  "properties": {
    "addr:full":"19 Moat Drive, Lochfoot Dumfries Dumfries and Galloway DG2 8NW",
    "addr:housenumber":"19",
    "addr:postcode":"dg2 8nw",
    "addr:street":"Moat Drive",
    "iso:country":"GB",
    "sg:address":"19 Moat Drive, Lochfoot",
    "sg:city":"Dumfries",
    "sg:classifiers":[
        {
            "category":"Freight",
            "type":"Transportation"
        }
    ],
    "sg:postcode":"DG2 8NW",
    "sg:province":"Dumfries and Galloway",
    "sg:tags":[
        "haulage",
        "road"
    ],
    "wof:name":"Nithcree Haulage & Distribution",
    "wof:placetype":"venue"
},
  "geometry": {"coordinates":[-3.725812,55.045811],"type":"Point"}
}