{
  "type": "Feature",
  "properties": {
    "addr:full":"34 Bridge Street Leatherhead Surrey KT22 8BZ",
    "addr:housenumber":"34",
    "addr:postcode":"kt22 8bz",
    "addr:street":"Bridge Street",
    "iso:country":"GB",
    "sg:address":"34 Bridge Street",
    "sg:city":"Leatherhead",
    "sg:classifiers":[
        {
            "category":"Real Estate",
            "subcategory":"Architect",
            "type":"Services"
        }
    ],
    "sg:phone":"+44 1372 374755",
    "sg:postcode":"KT22 8BZ",
    "sg:province":"Surrey",
    "wof:name":"William Larkin Associates",
    "wof:placetype":"venue"
},
  "geometry": {"coordinates":[-0.331856,51.294567],"type":"Point"}
}