{
  "type": "Feature",
  "properties": {
    "addr:full":"11 Rushdean Road, Strood Rochester Kent ME2 2PA",
    "addr:housenumber":"11",
    "addr:postcode":"me2 2pa",
    "addr:street":"Rushdean Road",
    "iso:country":"GB",
    "sg:address":"11 Rushdean Road, Strood",
    "sg:city":"Rochester",
    "sg:classifiers":[
        {
            "category":"Home & Garden",
            "subcategory":"Building Materials",
            "type":"Retail Goods"
        }
    ],
    "sg:phone":"+44 1634 710108",
    "sg:postcode":"ME2 2PA",
    "sg:province":"Kent",
    "sg:tags":[
        "insulation",
        "installers"
    ],
    "wof:name":"Albert S Taylor",
    "wof:placetype":"venue"
},
  "geometry": {"coordinates":[0.472028,51.385853],"type":"Point"}
}