{
  "type": "Feature",
  "properties": {
    "addr:full":"Dollis Park London Greater London N3 1BT",
    "addr:postcode":"n3 1bt",
    "addr:street":"Dollis Park",
    "iso:country":"GB",
    "sg:address":"Dollis Park",
    "sg:city":"London",
    "sg:classifiers":[
        {
            "category":"Education",
            "subcategory":"School",
            "type":"Public Place"
        }
    ],
    "sg:phone":"+44 20 8343 0866",
    "sg:postcode":"N3 1BT",
    "sg:province":"Greater London",
    "sg:tags":[
        "local",
        "authority"
    ],
    "wof:name":"St. Marys Primary School",
    "wof:placetype":"venue"
},
  "geometry": {"coordinates":[-0.201867,51.604015],"type":"Point"}
}