{
  "type": "Feature",
  "properties": {
    "iso:country":"GB",
    "sg:address":"Unit 9/10, Brunswick Place",
    "sg:city":"Basingstoke",
    "sg:classifiers":[
        {
            "category":"Organizations",
            "subcategory":"Non-profit Organization",
            "type":"Services"
        }
    ],
    "sg:phone":"+44 1256 352058",
    "sg:postcode":"RG21 3NN",
    "sg:province":"Hampshire",
    "sg:tags":[
        "organisation",
        "voluntary",
        "charity"
    ],
    "wof:name":"Loddon (Charitable Trust) Ltd.",
    "wof:placetype":"venue"
},
  "geometry": {"coordinates":[-1.0995960236,51.2497291565],"type":"Point"}
}