{
  "type": "Feature",
  "properties": {
    "addr:full":"367 Stamford Road Kettering Northamptonshire NN16 9SY",
    "addr:housenumber":"367",
    "addr:postcode":"nn16 9sy",
    "addr:street":"Stamford Road",
    "iso:country":"GB",
    "sg:address":"367 Stamford Road",
    "sg:city":"Kettering",
    "sg:classifiers":[
        {
            "category":"Retail",
            "subcategory":"Driving School",
            "type":"Services"
        }
    ],
    "sg:phone":"+44 1536 515882",
    "sg:postcode":"NN16 9SY",
    "sg:province":"Northamptonshire",
    "wof:name":"Clarks Driving School",
    "wof:placetype":"venue"
},
  "geometry": {"coordinates":[-0.703091979,52.4118766785],"type":"Point"}
}