{
  "type": "Feature",
  "properties": {
    "addr:full":"6 Manvers Street Bath Bath and North East Somerset BA1 1JQ",
    "addr:housenumber":"6",
    "addr:postcode":"ba1 1jq",
    "addr:street":"Manvers Street",
    "iso:country":"GB",
    "sg:address":"6 Manvers Street",
    "sg:city":"Bath",
    "sg:classifiers":[
        {
            "category":"Travel",
            "subcategory":"Hotels & Motels",
            "type":"Entertainment"
        }
    ],
    "sg:phone":"+44 1225 330133",
    "sg:postcode":"BA1 1JQ",
    "sg:province":"Bath and North East Somerset",
    "sg:tags":[
        "house",
        "guest"
    ],
    "wof:name":"AIMEE'S GUEST HOUSE",
    "wof:placetype":"venue"
},
  "geometry": {"coordinates":[-2.3573219776,51.379234314],"type":"Point"}
}