{
  "type": "Feature",
  "properties": {
    "addr:full":"3 High Street East Linton East Lothian EH40 3AA",
    "addr:housenumber":"3",
    "addr:postcode":"eh40 3aa",
    "addr:street":"High Street",
    "iso:country":"GB",
    "sg:address":"3 High Street",
    "sg:city":"East Linton",
    "sg:classifiers":[
        {
            "category":"Cafe",
            "type":"Food & Drink"
        }
    ],
    "sg:phone":"+44 1620 860018",
    "sg:postcode":"EH40 3AA",
    "sg:province":"East Lothian",
    "sg:tags":[
        "tea",
        "room"
    ],
    "wof:name":"Shirley Westlake",
    "wof:placetype":"venue"
},
  "geometry": {"coordinates":[-2.6562619209,55.986240387],"type":"Point"}
}