{
  "type": "Feature",
  "properties": {
    "iso:country":"GB",
    "sg:address":"Market Pl, Esh Winning",
    "sg:city":"Durham",
    "sg:classifiers":[
        {
            "category":"Bars & Pubs",
            "type":"Food & Drink"
        }
    ],
    "sg:phone":"+44 191 373 4139",
    "sg:postcode":"DH7 9HT",
    "sg:province":"Durham",
    "sg:tags":[
        "pubs",
        "inn"
    ],
    "wof:name":"Local Pub Co Ltd (The)",
    "wof:placetype":"venue"
},
  "geometry": {"coordinates":[-1.702088,54.771286],"type":"Point"}
}