{
  "type": "Feature",
  "properties": {
    "addr:full":"12 Lisko Close Brierley Hill West Midlands DY5 3FN",
    "addr:housenumber":"12",
    "addr:postcode":"dy5 3fn",
    "addr:street":"Lisko Close Brierley Hill",
    "iso:country":"GB",
    "sg:address":"12 Lisko Close",
    "sg:city":"Brierley Hill",
    "sg:classifiers":[
        {
            "category":"Manufacturing",
            "subcategory":"Tools & Machinery",
            "type":"Manufacturing & Wholesale Goods"
        }
    ],
    "sg:phone":"+44 1384 868641",
    "sg:postcode":"DY5 3FN",
    "sg:province":"West Midlands",
    "wof:name":"Stuart Wyre Machine Tools Ltd.",
    "wof:placetype":"venue"
},
  "geometry": {"coordinates":[-2.1424720287,52.4709281921],"type":"Point"}
}