{
  "type": "Feature",
  "properties": {
    "addr:full":"73 High St Barnsley South Yorkshire S70 4SQ",
    "addr:housenumber":"73",
    "addr:postcode":"s70 4sq",
    "addr:street":"High St;Yorkshire",
    "iso:country":"GB",
    "sg:address":"73 High St",
    "sg:city":"Barnsley",
    "sg:classifiers":[
        {
            "category":"Food & Beverages",
            "subcategory":"Supermarket",
            "type":"Retail Goods"
        }
    ],
    "sg:postcode":"S70 4SQ",
    "sg:province":"South Yorkshire",
    "wof:name":"Dunn's Mini Market",
    "wof:placetype":"venue"
},
  "geometry": {"coordinates":[-1.448917985,53.5677642822],"type":"Point"}
}