{
  "type": "Feature",
  "properties": {
    "addr:full":"238 Arkwrights Harlow Essex CM20 3NE",
    "addr:housenumber":"238",
    "addr:postcode":"cm20 3ne",
    "addr:street":"Arkwrights",
    "iso:country":"GB",
    "sg:address":"238 Arkwrights",
    "sg:city":"Harlow",
    "sg:classifiers":[
        {
            "category":"Professional",
            "subcategory":"Computer Services",
            "type":"Services"
        }
    ],
    "sg:postcode":"CM20 3NE",
    "sg:province":"Essex",
    "sg:tags":[
        "system",
        "software"
    ],
    "wof:name":"Nyma Ltd",
    "wof:placetype":"venue"
},
  "geometry": {"coordinates":[0.1094949991,51.7708587646],"type":"Point"}
}