{
  "type": "Feature",
  "properties": {
    "iso:country":"GB",
    "sg:address":"7 Emerald St",
    "sg:city":"York",
    "sg:classifiers":[
        {
            "category":"Retail",
            "subcategory":"Driving School",
            "type":"Services"
        }
    ],
    "sg:phone":"+44 1904 633864",
    "sg:postcode":"YO3 7LQ",
    "sg:province":"East Riding of Yorkshire",
    "wof:name":"Success School Of Motoring",
    "wof:placetype":"venue"
},
  "geometry": {"coordinates":[-1.0746870041,53.9680175781],"type":"Point"}
}