{
  "type": "Feature",
  "properties": {
    "addr:full":"85 Lower Clapton Road London Greater London E5 0NP",
    "addr:housenumber":"85",
    "addr:postcode":"e5 0np",
    "addr:street":"Lower Clapton Road",
    "iso:country":"GB",
    "sg:address":"85 Lower Clapton Road",
    "sg:city":"London",
    "sg:classifiers":[
        {
            "category":"Professional",
            "subcategory":"Lawyer & Legal Services",
            "type":"Services"
        }
    ],
    "sg:phone":"+44 20 8986 3911",
    "sg:postcode":"E5 0NP",
    "sg:province":"Greater London",
    "sg:tags":[
        "solicitor"
    ],
    "wof:name":"Hutchins & Co.",
    "wof:placetype":"venue"
},
  "geometry": {"coordinates":[-0.0524640009,51.5519561768],"type":"Point"}
}