{
  "type": "Feature",
  "properties": {
    "addr:full":"28 Church Road Stanmore Greater London HA7 4XR",
    "addr:housenumber":"28",
    "addr:postcode":"ha7 4xr",
    "addr:street":"Church Road",
    "iso:country":"GB",
    "sg:address":"28 Church Road",
    "sg:city":"Stanmore",
    "sg:classifiers":[
        {
            "category":"Building & Trades",
            "subcategory":"Construction",
            "type":"Services"
        }
    ],
    "sg:postcode":"HA7 4XR",
    "sg:province":"Greater London",
    "sg:tags":[
        "builder"
    ],
    "wof:name":"Adkel Ltd",
    "wof:placetype":"venue"
},
  "geometry": {"coordinates":[-0.3130140007,51.6168746948],"type":"Point"}
}