{
  "type": "Feature",
  "properties": {
    "addr:full":"Quakers Drove Farm, Quakers Drove, Whittlesey Peterborough Cambridgeshire PE7 2DR",
    "addr:postcode":"pe7 2dr",
    "addr:street":"Quakers Drove;Quakers Drove",
    "iso:country":"GB",
    "sg:address":"Quakers Drove Farm, Quakers Drove, Whittlesey",
    "sg:city":"Peterborough",
    "sg:classifiers":[
        {
            "category":"Home & Garden",
            "subcategory":"Garden Supply",
            "type":"Retail Goods"
        },
        {
            "category":"Farming",
            "subcategory":"Livestock Farm",
            "type":"Manufacturing & Wholesale Goods"
        }
    ],
    "sg:phone":"+44 1733 840573",
    "sg:postcode":"PE7 2DR",
    "sg:province":"Cambridgeshire",
    "sg:tags":[
        "bulb",
        "grower",
        "others"
    ],
    "wof:name":"Timothy J Fletcher",
    "wof:placetype":"venue"
},
  "geometry": {"coordinates":[-0.0269000009,52.5455131531],"type":"Point"}
}