{
  "type": "Feature",
  "properties": {
    "iso:country":"GB",
    "sg:address":"Head Office, Emlyn St",
    "sg:city":"Bolton",
    "sg:classifiers":[
        {
            "category":"Food & Beverages",
            "subcategory":"Fruits & Vegetables",
            "type":"Retail Goods"
        }
    ],
    "sg:phone":"+44 1204 571231",
    "sg:postcode":"BL4 7EB",
    "sg:province":"Lancashire",
    "sg:tags":[
        "greengrocer"
    ],
    "wof:name":"Hanburys Ltd",
    "wof:placetype":"venue"
},
  "geometry": {"coordinates":[-2.4070401192,53.5535812378],"type":"Point"}
}