{
  "type": "Feature",
  "properties": {
    "addr:full":"185 High St Herne Bay Kent CT6 5AF",
    "addr:housenumber":"185",
    "addr:postcode":"ct6 5af",
    "addr:street":"High St",
    "iso:country":"GB",
    "sg:address":"185 High St",
    "sg:city":"Herne Bay",
    "sg:classifiers":[
        {
            "category":"Shopping",
            "subcategory":"News",
            "type":"Retail Goods"
        }
    ],
    "sg:postcode":"CT6 5AF",
    "sg:province":"Kent",
    "sg:tags":[
        "newsagent"
    ],
    "wof:name":"Sims,J,",
    "wof:placetype":"venue"
},
  "geometry": {"coordinates":[1.131319,51.371544],"type":"Point"}
}