{
  "type": "Feature",
  "properties": {
    "addr:full":"Delvine Perth Perth and Kinross PH1 4LD",
    "addr:postcode":"ph1 4ld",
    "iso:country":"GB",
    "sg:address":"Delvine",
    "sg:city":"Perth",
    "sg:classifiers":[
        {
            "category":"Farming",
            "subcategory":"Farm",
            "type":"Manufacturing & Wholesale Goods"
        }
    ],
    "sg:phone":"+44 1738 710245",
    "sg:postcode":"PH1 4LD",
    "sg:province":"Perth and Kinross",
    "sg:tags":[
        "mixed",
        "crop"
    ],
    "wof:name":"D S Gemell",
    "wof:placetype":"venue"
},
  "geometry": {"coordinates":[-3.4167900085,56.545791626],"type":"Point"}
}