{
  "type": "Feature",
  "properties": {
    "addr:full":"20 Connaught Street London Greater London W2 2AF",
    "addr:housenumber":"20",
    "addr:postcode":"w2 2af",
    "addr:street":"Connaught Street",
    "iso:country":"GB",
    "sg:address":"20 Connaught Street",
    "sg:city":"London",
    "sg:classifiers":[
        {
            "category":"Home & Garden",
            "subcategory":"Building Materials",
            "type":"Retail Goods"
        }
    ],
    "sg:phone":"+44 20 7723 2263",
    "sg:postcode":"W2 2AF",
    "sg:province":"Greater London",
    "sg:tags":[
        "furnishers",
        "bathroom",
        "planner"
    ],
    "wof:name":"Hyde Park Bathrooms",
    "wof:placetype":"venue"
},
  "geometry": {"coordinates":[-0.165553,51.514706],"type":"Point"}
}