{
  "type": "Feature",
  "properties": {
    "addr:full":"4 Hurley Close, Wylde Grn Sutton Coldfield West Midlands B72 1HU",
    "addr:housenumber":"4",
    "addr:postcode":"b72 1hu",
    "addr:street":"Hurley Close Wylde Grn",
    "iso:country":"GB",
    "sg:address":"4 Hurley Close, Wylde Grn",
    "sg:city":"Sutton Coldfield",
    "sg:classifiers":[
        {
            "category":"Shopping",
            "subcategory":"Department Store",
            "type":"Retail Goods"
        }
    ],
    "sg:phone":"+44 121 354 9512",
    "sg:postcode":"B72 1HU",
    "sg:province":"West Midlands",
    "wof:name":"The Corner Shop",
    "wof:placetype":"venue"
},
  "geometry": {"coordinates":[-1.823985,52.548542],"type":"Point"}
}