{
  "type": "Feature",
  "properties": {
    "addr:full":"White Chapel Road Wick Highland KW1 5AE",
    "addr:postcode":"kw1 5ae",
    "addr:street":"White Chapel Road",
    "iso:country":"GB",
    "sg:address":"White Chapel Road",
    "sg:city":"Wick",
    "sg:classifiers":[
        {
            "category":"Home & Garden",
            "subcategory":"Household Appliances",
            "type":"Retail Goods"
        },
        {
            "category":"Shopping",
            "subcategory":"Hobbies, Toys, & Games",
            "type":"Retail Goods"
        }
    ],
    "sg:phone":"+44 1955 603091",
    "sg:postcode":"KW1 5AE",
    "sg:province":"Highland",
    "sg:tags":[
        "shop",
        "electrical",
        "toy",
        "domestic"
    ],
    "wof:name":"Graham Begg Ltd.",
    "wof:placetype":"venue"
},
  "geometry": {"coordinates":[-3.092469,58.442936],"type":"Point"}
}