{
  "type": "Feature",
  "properties": {
    "iso:country":"GB",
    "sg:address":"Leeside Wharf, Clapton",
    "sg:city":"London",
    "sg:classifiers":[
        {
            "category":"Manufacturing",
            "subcategory":"Lumber",
            "type":"Manufacturing & Wholesale Goods"
        }
    ],
    "sg:phone":"+44 20 8806 3333",
    "sg:postcode":"E5 9NG",
    "sg:province":"Greater London",
    "sg:tags":[
        "importer",
        "merchants",
        "agent",
        "timber"
    ],
    "wof:name":"James Latham Trustee Ltd.",
    "wof:placetype":"venue"
},
  "geometry": {"coordinates":[-0.0539060012,51.5587921143],"type":"Point"}
}