{
  "type": "Feature",
  "properties": {
    "iso:country":"GB",
    "sg:address":"65 Quarry, Rigg Lake Rd",
    "sg:city":"Windermere",
    "sg:classifiers":[
        {
            "category":"Shopping",
            "subcategory":"Florist",
            "type":"Retail Goods"
        }
    ],
    "sg:phone":"+44 15394 42869",
    "sg:postcode":"LA23 3DH",
    "sg:province":"Cumbria",
    "wof:name":"The Four Seasons",
    "wof:placetype":"venue"
},
  "geometry": {"coordinates":[-2.9224359989,54.3628692627],"type":"Point"}
}