{
  "type": "Feature",
  "properties": {
    "iso:country":"GB",
    "sg:address":"Sea View Works, Main Street, Spittal",
    "sg:city":"Berwick-upon-tweed",
    "sg:classifiers":[
        {
            "category":"Manufacturing",
            "subcategory":"Printing",
            "type":"Manufacturing & Wholesale Goods"
        },
        {
            "category":"Professional",
            "subcategory":"Printing & Photocopies",
            "type":"Services"
        }
    ],
    "sg:phone":"+44 1289 306006",
    "sg:postcode":"TD15 1RS",
    "sg:province":"Northumberland",
    "sg:tags":[
        "bookbinder",
        "printer"
    ],
    "wof:name":"Martins The Printers Ltd",
    "wof:placetype":"venue"
},
  "geometry": {"coordinates":[-2.0070240498,55.7714347839],"type":"Point"}
}