{
  "type": "Feature",
  "properties": {
    "iso:country":"GB",
    "sg:address":"8 The Chestnuts, Countesthorpe",
    "sg:city":"Leicester",
    "sg:classifiers":[
        {
            "category":"Professional",
            "subcategory":"Engineering",
            "type":"Services"
        },
        {
            "category":"Building & Trades",
            "subcategory":"Electrical",
            "type":"Services"
        }
    ],
    "sg:phone":"+44 116 277 6440",
    "sg:postcode":"LE8 5TL",
    "sg:province":"Leicestershire",
    "sg:tags":[
        "engineer",
        "electrician",
        "contractor"
    ],
    "wof:name":"Thomas N Gardner",
    "wof:placetype":"venue"
},
  "geometry": {"coordinates":[-1.137859,52.552349],"type":"Point"}
}