{
  "type": "Feature",
  "properties": {
    "iso:country":"GB",
    "sg:address":"115 Grampian Road",
    "sg:city":"Aviemore",
    "sg:classifiers":[
        {
            "category":"Fast Food",
            "type":"Food & Drink"
        }
    ],
    "sg:phone":"+44 1479 810799",
    "sg:postcode":"PH22 1RH",
    "sg:province":"Highland",
    "sg:tags":[
        "away",
        "take"
    ],
    "wof:name":"The Buttery",
    "wof:placetype":"venue"
},
  "geometry": {"coordinates":[-3.829722,57.188354],"type":"Point"}
}