{
  "type": "Feature",
  "properties": {
    "addr:full":"7 Station Road March Cambridgeshire PE15 8LB",
    "addr:housenumber":"7",
    "addr:postcode":"pe15 8lb",
    "addr:street":"Station Road",
    "iso:country":"GB",
    "sg:address":"7 Station Road",
    "sg:city":"March",
    "sg:classifiers":[
        {
            "category":"Restaurant",
            "type":"Food & Drink"
        }
    ],
    "sg:postcode":"PE15 8LB",
    "sg:province":"Cambridgeshire",
    "wof:name":"Classics",
    "wof:placetype":"venue"
},
  "geometry": {"coordinates":[0.0888840035,52.5511207581],"type":"Point"}
}