{
  "type": "Feature",
  "properties": {
    "addr:full":"7 Chester Court, Albany Street London Greater London NW1 4BU",
    "addr:housenumber":"7",
    "addr:postcode":"nw1 4bu",
    "addr:street":"Chester Court Albany Street",
    "iso:country":"GB",
    "sg:address":"7 Chester Court, Albany Street",
    "sg:city":"London",
    "sg:classifiers":[
        {
            "category":"Shopping",
            "subcategory":"Musical Instruments",
            "type":"Retail Goods"
        }
    ],
    "sg:phone":"+44 20 7935 8682",
    "sg:postcode":"NW1 4BU",
    "sg:province":"Greater London",
    "wof:name":"Markson Pianos Ltd.",
    "wof:placetype":"venue"
},
  "geometry": {"coordinates":[-0.144511,51.528709],"type":"Point"}
}