{
  "type": "Feature",
  "properties": {
    "iso:country":"GB",
    "sg:address":"The Conifers, 1a Whitewater Road, New Ollerton",
    "sg:city":"Newark",
    "sg:classifiers":[
        {
            "category":"Social Services",
            "subcategory":"Adult Care",
            "type":"Services"
        }
    ],
    "sg:phone":"+44 1623 836650",
    "sg:postcode":"NG22 9XF",
    "sg:province":"Nottinghamshire",
    "sg:tags":[
        "housing",
        "sheltered"
    ],
    "wof:name":"North British Housing Association",
    "wof:placetype":"venue"
},
  "geometry": {"coordinates":[-1.0120259523,53.2034416199],"type":"Point"}
}