{
  "type": "Feature",
  "properties": {
    "addr:full":"74 Featherbed Lane Rugby Warwickshire CV21 4LE",
    "addr:housenumber":"74",
    "addr:postcode":"cv21 4le",
    "addr:street":"Featherbed Lane",
    "iso:country":"GB",
    "sg:address":"74 Featherbed Lane",
    "sg:city":"Rugby",
    "sg:classifiers":[
        {
            "category":"Food & Beverages",
            "subcategory":"Supermarket",
            "type":"Retail Goods"
        },
        {
            "category":"Food & Beverages",
            "subcategory":"Groceries & Convenience Stores",
            "type":"Retail Goods"
        }
    ],
    "sg:phone":"+44 1788 576966",
    "sg:postcode":"CV21 4LE",
    "sg:province":"Warwickshire",
    "wof:name":"Hillmorton News Food & Wine",
    "wof:placetype":"venue"
},
  "geometry": {"coordinates":[-1.221855,52.362247],"type":"Point"}
}