{
  "type": "Feature",
  "properties": {
    "addr:full":"30 Old Bailey London Greater London EC4M 7HS",
    "addr:housenumber":"30",
    "addr:postcode":"ec4m 7hs",
    "addr:street":"Old Bailey",
    "iso:country":"GB",
    "sg:address":"30 Old Bailey",
    "sg:city":"London",
    "sg:classifiers":[
        {
            "category":"Cafe",
            "type":"Food & Drink"
        }
    ],
    "sg:phone":"+44 20 7248 1482",
    "sg:postcode":"EC4M 7HS",
    "sg:province":"Greater London",
    "sg:tags":[
        "tea",
        "room"
    ],
    "wof:name":"Morris's",
    "wof:placetype":"venue"
},
  "geometry": {"coordinates":[-0.1026329994,51.5145797729],"type":"Point"}
}