{
  "type": "Feature",
  "properties": {
    "addr:full":"313 Bury New Road Salford Greater Manchester M7 9YN",
    "addr:housenumber":"313",
    "addr:postcode":"m7 9yn",
    "addr:street":"Bury New Road",
    "iso:country":"GB",
    "sg:address":"313 Bury New Road",
    "sg:city":"Salford",
    "sg:classifiers":[
        {
            "category":"Sports & Exercise",
            "subcategory":"Athletic Track",
            "type":"Entertainment"
        }
    ],
    "sg:phone":"+44 161 708 9541",
    "sg:postcode":"M7 9YN",
    "sg:province":"Greater Manchester",
    "sg:tags":[
        "bags",
        "accessory",
        "belt"
    ],
    "wof:name":"Joseph Segal Ltd.",
    "wof:placetype":"venue"
},
  "geometry": {"coordinates":[-2.257972002,53.5017433167],"type":"Point"}
}