{
  "type": "Feature",
  "properties": {
    "addr:full":"19 New St Stourport-on-severn Worcestershire DY13 8UW",
    "addr:housenumber":"19",
    "addr:postcode":"dy13 8uw",
    "addr:street":"New St",
    "iso:country":"GB",
    "sg:address":"19 New St",
    "sg:city":"Stourport-on-severn",
    "sg:classifiers":[
        {
            "category":"Bars & Pubs",
            "type":"Food & Drink"
        }
    ],
    "sg:postcode":"DY13 8UW",
    "sg:province":"Worcestershire",
    "sg:tags":[
        "pubs",
        "inn"
    ],
    "wof:name":"Hope & Anchor (The)",
    "wof:placetype":"venue"
},
  "geometry": {"coordinates":[-2.2806589603,52.3392791748],"type":"Point"}
}