{
  "type": "Feature",
  "properties": {
    "iso:country":"GB",
    "sg:address":"12-13 Wells Street",
    "sg:city":"London",
    "sg:classifiers":[
        {
            "category":"Bars & Pubs",
            "type":"Food & Drink"
        }
    ],
    "sg:postcode":"W1T 3PG",
    "sg:province":"Greater London",
    "sg:tags":[
        "pubs",
        "inn"
    ],
    "wof:name":"The Champion",
    "wof:placetype":"venue"
},
  "geometry": {"coordinates":[-0.137506,51.51712],"type":"Point"}
}