{
  "type": "Feature",
  "properties": {
    "addr:full":"13 London Road Stanford-le-hope Essex SS17 0LL",
    "addr:housenumber":"13",
    "addr:postcode":"ss17 0ll",
    "addr:street":"London Road",
    "iso:country":"GB",
    "sg:address":"13 London Road",
    "sg:city":"Stanford-le-hope",
    "sg:classifiers":[
        {
            "category":"Shopping",
            "subcategory":"Used Merchandise",
            "type":"Retail Goods"
        }
    ],
    "sg:phone":"+44 1375 644428",
    "sg:postcode":"SS17 0LL",
    "sg:province":"Essex",
    "sg:tags":[
        "shop",
        "second-hand"
    ],
    "wof:name":"Stanford Second Hand",
    "wof:placetype":"venue"
},
  "geometry": {"coordinates":[0.4202339947,51.5139122009],"type":"Point"}
}