{
  "type": "Feature",
  "properties": {
    "iso:country":"GB",
    "sg:address":"45 Stonegarth, Morton Park",
    "sg:city":"Carlisle",
    "sg:classifiers":[
        {
            "category":"Building & Trades",
            "subcategory":"Landscaping Services",
            "type":"Services"
        }
    ],
    "sg:phone":"+44 1228 524306",
    "sg:postcode":"CA2 6PQ",
    "sg:province":"Cumbria",
    "sg:tags":[
        "gardening"
    ],
    "wof:name":"James Ruddick Landscape Services",
    "wof:placetype":"venue"
},
  "geometry": {"coordinates":[-2.965669,54.88203],"type":"Point"}
}