{
  "type": "Feature",
  "properties": {
    "iso:country":"GB",
    "sg:address":"1 Bishop Street",
    "sg:city":"Bradford",
    "sg:classifiers":[
        {
            "category":"Food & Beverages",
            "subcategory":"Supermarket",
            "type":"Retail Goods"
        },
        {
            "category":"Food & Beverages",
            "subcategory":"Groceries & Convenience Stores",
            "type":"Retail Goods"
        }
    ],
    "sg:postcode":"BD9 4PH",
    "sg:province":"West Yorkshire",
    "wof:name":"NASIM FOOD STORE",
    "wof:placetype":"venue"
},
  "geometry": {"coordinates":[-1.777037,53.810642],"type":"Point"}
}