{
  "type": "Feature",
  "properties": {
    "addr:full":"45 Bath Street Leamington Spa Warwickshire CV31 3AG",
    "addr:housenumber":"45",
    "addr:postcode":"cv31 3ag",
    "addr:street":"Bath Street",
    "iso:country":"GB",
    "sg:address":"45 Bath Street",
    "sg:city":"Leamington Spa",
    "sg:classifiers":[
        {
            "category":"Organizations",
            "subcategory":"Membership Organization",
            "type":"Services"
        }
    ],
    "sg:phone":"+44 1926 312568",
    "sg:postcode":"CV31 3AG",
    "sg:province":"Warwickshire",
    "sg:tags":[
        "club"
    ],
    "wof:name":"Tj's",
    "wof:placetype":"venue"
},
  "geometry": {"coordinates":[-1.5321350098,52.2844429016],"type":"Point"}
}