{
  "type": "Feature",
  "properties": {
    "addr:full":"32 New John Street West Birmingham West Midlands B19 3NB",
    "addr:housenumber":"32",
    "addr:postcode":"b19 3nb",
    "addr:street":"New John Street West",
    "iso:country":"GB",
    "sg:address":"32 New John Street West",
    "sg:city":"Birmingham",
    "sg:classifiers":[
        {
            "category":"Professional",
            "subcategory":"Employment Agencies",
            "type":"Services"
        }
    ],
    "sg:postcode":"B19 3NB",
    "sg:province":"West Midlands",
    "sg:tags":[
        "mnfs",
        "regalia"
    ],
    "wof:name":"Light & Boston Ltd.",
    "wof:placetype":"venue"
},
  "geometry": {"coordinates":[-1.8971459866,52.4923820496],"type":"Point"}
}