{
  "type": "Feature",
  "properties": {
    "addr:full":"990 Abbeydale Rd Sheffield South Yorkshire S7 2QF",
    "addr:housenumber":"990",
    "addr:postcode":"s7 2qf",
    "addr:street":"Abbeydale Rd",
    "iso:country":"GB",
    "sg:address":"990 Abbeydale Rd",
    "sg:city":"Sheffield",
    "sg:classifiers":[
        {
            "category":"Fast Food",
            "type":"Food & Drink"
        }
    ],
    "sg:phone":"+44 114 236 7070",
    "sg:postcode":"S7 2QF",
    "sg:province":"South Yorkshire",
    "sg:tags":[
        "away",
        "take"
    ],
    "wof:name":"Fast Eddy Pizza",
    "wof:placetype":"venue"
},
  "geometry": {"coordinates":[-1.4966820478,53.3461952209],"type":"Point"}
}