{
  "type": "Feature",
  "properties": {
    "addr:full":"7-13 George Street Grays Essex RM17 6LY",
    "addr:housenumber":"7-13",
    "addr:postcode":"rm17 6ly",
    "addr:street":"George Street",
    "iso:country":"GB",
    "sg:address":"7-13 George Street",
    "sg:city":"Grays",
    "sg:classifiers":[
        {
            "category":"Restaurant",
            "type":"Food & Drink"
        }
    ],
    "sg:phone":"+44 1375 394080",
    "sg:postcode":"RM17 6LY",
    "sg:province":"Essex",
    "wof:name":"Star Express",
    "wof:placetype":"venue"
},
  "geometry": {"coordinates":[0.32217,51.47736],"type":"Point"}
}