{
  "type": "Feature",
  "properties": {
    "addr:full":"413b Crofton Rd Orpington Kent BR6 8NL",
    "addr:housenumber":"413b",
    "addr:postcode":"br6 8nl",
    "addr:street":"Crofton Rd",
    "iso:country":"GB",
    "sg:address":"413b Crofton Rd",
    "sg:city":"Orpington",
    "sg:classifiers":[
        {
            "category":"Travel",
            "subcategory":"Travel Agent",
            "type":"Entertainment"
        }
    ],
    "sg:postcode":"BR6 8NL",
    "sg:province":"Kent",
    "wof:name":"Travel Shop (The)",
    "wof:placetype":"venue"
},
  "geometry": {"coordinates":[0.054606,51.366871],"type":"Point"}
}