{
  "type": "Feature",
  "properties": {
    "iso:country":"GB",
    "sg:address":"92 Market Street, Hindley",
    "sg:city":"Wigan",
    "sg:classifiers":[
        {
            "category":"Professional",
            "subcategory":"Lawyer & Legal Services",
            "type":"Services"
        }
    ],
    "sg:phone":"+44 1942 255343",
    "sg:postcode":"WN2 3AN",
    "sg:province":"Lancashire",
    "sg:tags":[
        "solicitor"
    ],
    "wof:name":"Knightingale & Co.",
    "wof:placetype":"venue"
},
  "geometry": {"coordinates":[-2.578344,53.535458],"type":"Point"}
}