{
  "type": "Feature",
  "properties": {
    "addr:full":"Unit 30 The Brooks, Middlebrook Street Winchester Hampshire SO23 8QY",
    "addr:housenumber":"unit 30",
    "addr:postcode":"so23 8qy",
    "addr:street":"The Brooks Middlebrook Street",
    "iso:country":"GB",
    "sg:address":"Unit 30 The Brooks, Middlebrook Street",
    "sg:city":"Winchester",
    "sg:classifiers":[
        {
            "category":"Farming",
            "subcategory":"Fish & Marine Products",
            "type":"Manufacturing & Wholesale Goods"
        }
    ],
    "sg:postcode":"SO23 8QY",
    "sg:province":"Hampshire",
    "sg:tags":[
        "fishmonger"
    ],
    "wof:name":"Kippers",
    "wof:placetype":"venue"
},
  "geometry": {"coordinates":[-1.312174,51.063484],"type":"Point"}
}