{
  "type": "Feature",
  "properties": {
    "addr:full":"47 New Canal Salisbury Wiltshire SP1 2AA",
    "addr:housenumber":"47",
    "addr:postcode":"sp1 2aa",
    "addr:street":"New Canal",
    "iso:country":"GB",
    "sg:address":"47 New Canal",
    "sg:city":"Salisbury",
    "sg:classifiers":[
        {
            "category":"Shopping",
            "subcategory":"Clothing, Apparel, & Fashions",
            "type":"Retail Goods"
        }
    ],
    "sg:phone":"+44 1722 333005",
    "sg:postcode":"SP1 2AA",
    "sg:province":"Wiltshire",
    "sg:tags":[
        "shop"
    ],
    "wof:name":"Jaeger Ladieswear",
    "wof:placetype":"venue"
},
  "geometry": {"coordinates":[-1.7952920198,51.0683021545],"type":"Point"}
}