{
  "type": "Feature",
  "properties": {
    "addr:full":"Recovery House, Sheffield Road Barnsley South Yorkshire S70 4PJ",
    "addr:postcode":"s70 4pj",
    "addr:street":"Sheffield Road;Yorkshire",
    "iso:country":"GB",
    "sg:address":"Recovery House, Sheffield Road",
    "sg:city":"Barnsley",
    "sg:classifiers":[
        {
            "category":"Autos & Motor Vehicles",
            "subcategory":"Fuel & Gas Station",
            "type":"Retail Goods"
        }
    ],
    "sg:phone":"+44 1226 298953",
    "sg:postcode":"S70 4PJ",
    "sg:province":"South Yorkshire",
    "sg:tags":[
        "petrol",
        "filling"
    ],
    "wof:name":"Action Stations Ltd.",
    "wof:placetype":"venue"
},
  "geometry": {"coordinates":[-1.473679,53.546471],"type":"Point"}
}