{
  "type": "Feature",
  "properties": {
    "addr:full":"Hamdden Glanrhyd Farm, Pentir Bangor Gwynedd LL57 4EB",
    "addr:postcode":"ll57 4eb",
    "iso:country":"GB",
    "sg:address":"Hamdden Glanrhyd Farm, Pentir",
    "sg:city":"Bangor",
    "sg:classifiers":[
        {
            "category":"Farming",
            "subcategory":"Farm",
            "type":"Manufacturing & Wholesale Goods"
        },
        {
            "category":"Food & Beverages",
            "subcategory":"Groceries & Convenience Stores",
            "type":"Retail Goods"
        }
    ],
    "sg:phone":"+44 1248 353389",
    "sg:postcode":"LL57 4EB",
    "sg:province":"Gwynedd",
    "sg:tags":[
        "merchant",
        "egg",
        "producer"
    ],
    "wof:name":"I W & D Owen",
    "wof:placetype":"venue"
},
  "geometry": {"coordinates":[-4.1366739273,53.179889679],"type":"Point"}
}