{
  "type": "Feature",
  "properties": {
    "addr:full":"139 Trinity Street Huddersfield West Yorkshire HD1 4DZ",
    "addr:housenumber":"139",
    "addr:postcode":"hd1 4dz",
    "addr:street":"Trinity Street",
    "iso:country":"GB",
    "sg:address":"139 Trinity Street",
    "sg:city":"Huddersfield",
    "sg:classifiers":[
        {
            "category":"Government",
            "subcategory":"Office",
            "type":"Public Place"
        }
    ],
    "sg:phone":"+44 1484 424646",
    "sg:postcode":"HD1 4DZ",
    "sg:province":"West Yorkshire",
    "sg:tags":[
        "education",
        "agency",
        "authority"
    ],
    "wof:name":"139 Project",
    "wof:placetype":"venue"
},
  "geometry": {"coordinates":[-1.7966259718,53.6502876282],"type":"Point"}
}