{
  "type": "Feature",
  "properties": {
    "addr:full":"70 Privett Road Fareham Hampshire PO15 6SP",
    "addr:housenumber":"70",
    "addr:postcode":"po15 6sp",
    "addr:street":"Privett Road",
    "iso:country":"GB",
    "sg:address":"70 Privett Road",
    "sg:city":"Fareham",
    "sg:classifiers":[
        {
            "category":"Shopping",
            "subcategory":"News",
            "type":"Retail Goods"
        }
    ],
    "sg:postcode":"PO15 6SP",
    "sg:province":"Hampshire",
    "sg:tags":[
        "newsagent"
    ],
    "wof:name":"I & M Tizzard",
    "wof:placetype":"venue"
},
  "geometry": {"coordinates":[-1.2166099548,50.8589859009],"type":"Point"}
}