{
  "type": "Feature",
  "properties": {
    "addr:full":"8 Morton Terrace Tonypandy Rhondda, Cynon, Taff CF40 2DP",
    "addr:housenumber":"8",
    "addr:postcode":"cf40 2dp",
    "addr:street":"Morton Terrace;Cynon Taff",
    "iso:country":"GB",
    "sg:address":"8 Morton Terrace",
    "sg:city":"Tonypandy",
    "sg:classifiers":[
        {
            "category":"Bus Charters",
            "type":"Transportation"
        }
    ],
    "sg:phone":"+44 1443 435830",
    "sg:postcode":"CF40 2DP",
    "sg:province":"Rhondda, Cynon, Taff",
    "sg:tags":[
        "mini",
        "hire",
        "leasing"
    ],
    "wof:name":"K & A Minibus Hire",
    "wof:placetype":"venue"
},
  "geometry": {"coordinates":[-3.4817430973,51.627117157],"type":"Point"}
}