{
  "type": "Feature",
  "properties": {
    "addr:full":"45 Montague Drive Loughborough Leicestershire LE11 3SB",
    "addr:housenumber":"45",
    "addr:postcode":"le11 3sb",
    "addr:street":"Montague Drive",
    "iso:country":"GB",
    "sg:address":"45 Montague Drive",
    "sg:city":"Loughborough",
    "sg:classifiers":[
        {
            "category":"Professional",
            "subcategory":"Management & Consulting",
            "type":"Services"
        }
    ],
    "sg:phone":"+44 1509 237218",
    "sg:postcode":"LE11 3SB",
    "sg:province":"Leicestershire",
    "sg:tags":[
        "fire",
        "consultant",
        "protection"
    ],
    "wof:name":"John Worrall Fire Safety Management",
    "wof:placetype":"venue"
},
  "geometry": {"coordinates":[-1.245726,52.754299],"type":"Point"}
}