{
  "type": "Feature",
  "properties": {
    "addr:full":"28-30 High Street Annan Dumfries and Galloway DG12 6AJ",
    "addr:housenumber":"28-30",
    "addr:postcode":"dg12 6aj",
    "addr:street":"High Street",
    "iso:country":"GB",
    "sg:address":"28-30 High Street",
    "sg:city":"Annan",
    "sg:classifiers":[
        {
            "category":"Organizations",
            "subcategory":"Non-profit Organization",
            "type":"Services"
        }
    ],
    "sg:phone":"+44 1461 203944",
    "sg:postcode":"DG12 6AJ",
    "sg:province":"Dumfries and Galloway",
    "sg:tags":[
        "organisation",
        "voluntary",
        "charity"
    ],
    "wof:name":"Red Cross Centre",
    "wof:placetype":"venue"
},
  "geometry": {"coordinates":[-3.2645390034,54.9871520996],"type":"Point"}
}