{
  "type": "Feature",
  "properties": {
    "addr:full":"Soul Jazz Restaurant, 34-38 Eversholt St Camden Greater London NW1 1DA",
    "addr:housenumber":"34-38",
    "addr:postcode":"nw1 1da",
    "addr:street":"Eversholt St",
    "iso:country":"GB",
    "sg:address":"Soul Jazz Restaurant, 34-38 Eversholt St",
    "sg:city":"Camden",
    "sg:classifiers":[
        {
            "category":"Restaurant",
            "type":"Food & Drink"
        }
    ],
    "sg:phone":"+44 20 7388 6487",
    "sg:postcode":"NW1 1DA",
    "sg:province":"Greater London",
    "wof:name":"Manatiys",
    "wof:placetype":"venue"
},
  "geometry": {"coordinates":[-0.127944,51.532581],"type":"Point"}
}