{
  "type": "Feature",
  "properties": {
    "addr:full":"159 Lynchford Rd Farnborough Hampshire GU14 6HD",
    "addr:housenumber":"159",
    "addr:postcode":"gu14 6hd",
    "addr:street":"Lynchford Rd",
    "iso:country":"GB",
    "sg:address":"159 Lynchford Rd",
    "sg:city":"Farnborough",
    "sg:classifiers":[
        {
            "category":"Autos & Motor Vehicles",
            "subcategory":"Automobile Sales",
            "type":"Retail Goods"
        }
    ],
    "sg:phone":"+44 1252 517509",
    "sg:postcode":"GU14 6HD",
    "sg:province":"Hampshire",
    "sg:tags":[
        "car"
    ],
    "wof:name":"Wigley,Guy,",
    "wof:placetype":"venue"
},
  "geometry": {"coordinates":[-0.7434309721,51.2752075195],"type":"Point"}
}