{
  "type": "Feature",
  "properties": {
    "addr:full":"114 Ringwood Road Poole Dorset BH14 0RW",
    "addr:housenumber":"114",
    "addr:postcode":"bh14 0rw",
    "addr:street":"Ringwood Road",
    "iso:country":"GB",
    "sg:address":"114 Ringwood Road",
    "sg:city":"Poole",
    "sg:classifiers":[
        {
            "category":"Building & Trades",
            "subcategory":"Construction",
            "type":"Services"
        }
    ],
    "sg:phone":"+44 1202 680249",
    "sg:postcode":"BH14 0RW",
    "sg:province":"Dorset",
    "sg:tags":[
        "joiner",
        "carpenter"
    ],
    "wof:name":"Danny Keith Sullivan",
    "wof:placetype":"venue"
},
  "geometry": {"coordinates":[-1.9637700319,50.7297744751],"type":"Point"}
}