{
  "type": "Feature",
  "properties": {
    "addr:full":"83 Weston Road Stoke-on-trent Staffordshire ST3 6AJ",
    "addr:housenumber":"83",
    "addr:postcode":"st3 6aj",
    "addr:street":"Weston Road",
    "iso:country":"GB",
    "sg:address":"83 Weston Road",
    "sg:city":"Stoke-on-trent",
    "sg:classifiers":[
        {
            "category":"Organizations",
            "subcategory":"Non-profit Organization",
            "type":"Services"
        }
    ],
    "sg:phone":"+44 1782 313704",
    "sg:postcode":"ST3 6AJ",
    "sg:province":"Staffordshire",
    "sg:tags":[
        "organisation",
        "voluntary",
        "charity"
    ],
    "wof:name":"The Church of England Children Society )",
    "wof:placetype":"venue"
},
  "geometry": {"coordinates":[-2.1019029617,52.9792861938],"type":"Point"}
}