{
  "type": "Feature",
  "properties": {
    "iso:country":"GB",
    "sg:address":"65 Parkway Grange",
    "sg:city":"Leeds",
    "sg:classifiers":[
        {
            "category":"Education",
            "subcategory":"Music School",
            "type":"Public Place"
        }
    ],
    "sg:phone":"+44 113 294 5600",
    "sg:postcode":"LS14 6UR",
    "sg:province":"West Yorkshire",
    "sg:tags":[
        "teacher"
    ],
    "wof:name":"Academy Guitar Studio",
    "wof:placetype":"venue"
},
  "geometry": {"coordinates":[-1.479186058,53.8117828369],"type":"Point"}
}