{
  "type": "Feature",
  "properties": {
    "addr:full":"Shingles, Nazeing Road Waltham Abbey Essex EN9 2HY",
    "addr:postcode":"en9 2hy",
    "addr:street":"Nazeing Road",
    "iso:country":"GB",
    "sg:address":"Shingles, Nazeing Road",
    "sg:city":"Waltham Abbey",
    "sg:classifiers":[
        {
            "category":"Home & Garden",
            "subcategory":"Garden Supply",
            "type":"Retail Goods"
        }
    ],
    "sg:postcode":"EN9 2HY",
    "sg:province":"Essex",
    "sg:tags":[
        "sand",
        "gravel"
    ],
    "wof:name":"Holt's Transport Co. Ltd.",
    "wof:placetype":"venue"
},
  "geometry": {"coordinates":[0.048448,51.738914],"type":"Point"}
}