{
  "type": "Feature",
  "properties": {
    "addr:full":"15-17 Idmiston Croft, Maypole Birmingham West Midlands B14 5NJ",
    "addr:housenumber":"15-17",
    "addr:postcode":"b14 5nj",
    "addr:street":"Idmiston Croft",
    "iso:country":"GB",
    "sg:address":"15-17 Idmiston Croft, Maypole",
    "sg:city":"Birmingham",
    "sg:classifiers":[
        {
            "category":"Cinema",
            "subcategory":"Movie Rental",
            "type":"Entertainment"
        }
    ],
    "sg:phone":"+44 121 430 2737",
    "sg:postcode":"B14 5NJ",
    "sg:province":"West Midlands",
    "sg:tags":[
        "video",
        "library"
    ],
    "wof:name":"Videorama & Licensed Food Store",
    "wof:placetype":"venue"
},
  "geometry": {"coordinates":[-1.889868021,52.4072914124],"type":"Point"}
}