{
  "type": "Feature",
  "properties": {
    "iso:country":"GB",
    "sg:address":"Goldhawk Rd",
    "sg:city":"Hammersmith",
    "sg:classifiers":[
        {
            "category":"Organizations",
            "subcategory":"Non-profit Organization",
            "type":"Services"
        }
    ],
    "sg:phone":"+44 20 8383 3924",
    "sg:postcode":"W6 0XG",
    "sg:province":"Greater London",
    "sg:tags":[
        "organisation",
        "voluntary",
        "charity"
    ],
    "wof:name":"Karim Centre For Meningitis Research",
    "wof:placetype":"venue"
},
  "geometry": {"coordinates":[-0.2294200063,51.4961509705],"type":"Point"}
}