{
  "type": "Feature",
  "properties": {
    "addr:full":"Chimneys, Gull Road Wisbech Cambridgeshire PE13 4EP",
    "addr:postcode":"pe13 4ep",
    "addr:street":"Gull Road",
    "iso:country":"GB",
    "sg:address":"Chimneys, Gull Road",
    "sg:city":"Wisbech",
    "sg:classifiers":[
        {
            "category":"Banks & Credit Unions",
            "subcategory":"Investment Brokerage",
            "type":"Services"
        }
    ],
    "sg:phone":"+44 1945 700033",
    "sg:postcode":"PE13 4EP",
    "sg:province":"Cambridgeshire",
    "sg:tags":[
        "contractor"
    ],
    "wof:name":"Graham Fowler",
    "wof:placetype":"venue"
},
  "geometry": {"coordinates":[0.1020860001,52.6527252197],"type":"Point"}
}