{
  "type": "Feature",
  "properties": {
    "addr:full":"13 High Street, Stanton Hill Sutton-in-ashfield Nottinghamshire NG17 3GG",
    "addr:housenumber":"13",
    "addr:postcode":"ng17 3gg",
    "addr:street":"High Street",
    "iso:country":"GB",
    "sg:address":"13 High Street, Stanton Hill",
    "sg:city":"Sutton-in-ashfield",
    "sg:classifiers":[
        {
            "category":"Autos & Motor Vehicles",
            "subcategory":"Motorcycle Sales",
            "type":"Retail Goods"
        }
    ],
    "sg:phone":"+44 1623 441478",
    "sg:postcode":"NG17 3GG",
    "sg:province":"Nottinghamshire",
    "sg:tags":[
        "scooter",
        "cycle"
    ],
    "wof:name":"Ashfield Bike Breakers",
    "wof:placetype":"venue"
},
  "geometry": {"coordinates":[-1.278365016,53.141204834],"type":"Point"}
}