{
  "type": "Feature",
  "properties": {
    "addr:full":"Unit 3 Birch Indust Est Eastbourne East Sussex BN23 6PH",
    "addr:housenumber":"unit 3",
    "addr:postcode":"bn23 6ph",
    "addr:street":"Birch Indust Est",
    "iso:country":"GB",
    "sg:address":"Unit 3 Birch Indust Est",
    "sg:city":"Eastbourne",
    "sg:classifiers":[
        {
            "category":"Professional",
            "subcategory":"Advertising",
            "type":"Services"
        }
    ],
    "sg:phone":"+44 1323 430431",
    "sg:postcode":"BN23 6PH",
    "sg:province":"East Sussex",
    "wof:name":"Pic A Pro (UK) Ltd",
    "wof:placetype":"venue"
},
  "geometry": {"coordinates":[0.3043499887,50.7873344421],"type":"Point"}
}