{
  "type": "Feature",
  "properties": {
    "addr:full":"Gatton Side Melrose Scottish Borders TD6 9LZ",
    "addr:postcode":"td6 9lz",
    "addr:street":"Side",
    "iso:country":"GB",
    "sg:address":"Gatton Side",
    "sg:city":"Melrose",
    "sg:classifiers":[
        {
            "category":"Bars & Pubs",
            "type":"Food & Drink"
        },
        {
            "category":"Restaurant",
            "type":"Food & Drink"
        }
    ],
    "sg:phone":"+44 1896 823082",
    "sg:postcode":"TD6 9LZ",
    "sg:province":"Scottish Borders",
    "sg:tags":[
        "-"
    ],
    "wof:name":"Hoebridge Inn Restaurant",
    "wof:placetype":"venue"
},
  "geometry": {"coordinates":[-2.737578,55.598831],"type":"Point"}
}