{
  "type": "Feature",
  "properties": {
    "addr:full":"429-431 Brixton Rd Brixton Greater London SW9 8HE",
    "addr:housenumber":"429-431",
    "addr:postcode":"sw9 8he",
    "addr:street":"Brixton Rd",
    "iso:country":"GB",
    "sg:address":"429-431 Brixton Rd",
    "sg:city":"Brixton",
    "sg:classifiers":[
        {
            "category":"Shopping",
            "subcategory":"Gifts & Souvenirs",
            "type":"Retail Goods"
        }
    ],
    "sg:phone":"+44 20 7326 1268",
    "sg:postcode":"SW9 8HE",
    "sg:province":"Greater London",
    "sg:tags":[
        "shop"
    ],
    "wof:name":"Robills",
    "wof:placetype":"venue"
},
  "geometry": {"coordinates":[-0.1148689985,51.4627876282],"type":"Point"}
}