{
  "type": "Feature",
  "properties": {
    "addr:full":"25 Henry Street, Hetton Le Hole Houghton Le Spring Durham DH5 9BA",
    "addr:housenumber":"25",
    "addr:postcode":"dh5 9ba",
    "addr:street":"Henry Street;Le Spring",
    "iso:country":"GB",
    "sg:address":"25 Henry Street, Hetton Le Hole",
    "sg:city":"Houghton Le Spring",
    "sg:classifiers":[
        {
            "category":"Professional",
            "type":"Services"
        }
    ],
    "sg:phone":"+44 191 517 2833",
    "sg:postcode":"DH5 9BA",
    "sg:province":"Durham",
    "sg:tags":[
        "entertainer"
    ],
    "wof:name":"Ice Entertainment",
    "wof:placetype":"venue"
},
  "geometry": {"coordinates":[-1.4496020079,54.8303489685],"type":"Point"}
}