{
  "type": "Feature",
  "properties": {
    "addr:full":"Lydstep Haven Tenby Pembrokeshire SA70 7SB",
    "addr:postcode":"sa70 7sb",
    "addr:street":"Lydstep Haven",
    "iso:country":"GB",
    "sg:address":"Lydstep Haven",
    "sg:city":"Tenby",
    "sg:classifiers":[
        {
            "category":"Recreation",
            "subcategory":"Campground",
            "type":"Entertainment"
        }
    ],
    "sg:phone":"+44 1834 871871",
    "sg:postcode":"SA70 7SB",
    "sg:province":"Pembrokeshire",
    "sg:tags":[
        "holiday",
        "centre",
        "camp"
    ],
    "wof:name":"Lydstep Beach Holiday Park",
    "wof:placetype":"venue"
},
  "geometry": {"coordinates":[-4.7692241669,51.6511039734],"type":"Point"}
}