{
  "type": "Feature",
  "properties": {
    "iso:country":"GB",
    "sg:address":"10 Wells Street",
    "sg:city":"Chelmsford",
    "sg:classifiers":[
        {
            "category":"Personal",
            "type":"Services"
        },
        {
            "category":"Shopping",
            "subcategory":"Bridal",
            "type":"Retail Goods"
        }
    ],
    "sg:phone":"+44 1245 357471",
    "sg:postcode":"CM1 1HZ",
    "sg:province":"Essex",
    "sg:tags":[
        "shop",
        "gown",
        "wedding"
    ],
    "wof:name":"Divine Bride Ltd",
    "wof:placetype":"venue"
},
  "geometry": {"coordinates":[0.467393,51.736916],"type":"Point"}
}