{
  "type": "Feature",
  "properties": {
    "addr:full":"Kingwood, 44 Kingsley Ave Camberley Berkshire GU15 2NB",
    "addr:housenumber":"44",
    "addr:postcode":"gu15 2nb",
    "addr:street":"Kingwood;Kingsley Ave",
    "iso:country":"GB",
    "sg:address":"Kingwood, 44 Kingsley Ave",
    "sg:city":"Camberley",
    "sg:classifiers":[
        {
            "category":"Freight",
            "type":"Transportation"
        }
    ],
    "sg:phone":"+44 1276 671954",
    "sg:postcode":"GU15 2NB",
    "sg:province":"Berkshire",
    "sg:tags":[
        "haulage",
        "road"
    ],
    "wof:name":"J & B Transport (U K) Ltd",
    "wof:placetype":"venue"
},
  "geometry": {"coordinates":[-0.7342299819,51.3362159729],"type":"Point"}
}