{
  "type": "Feature",
  "properties": {
    "iso:country":"GB",
    "sg:address":"Education Office, Esher Ho, 48 St Leonards Rd",
    "sg:city":"Eastbourne",
    "sg:classifiers":[
        {
            "category":"Government",
            "subcategory":"Office",
            "type":"Public Place"
        }
    ],
    "sg:phone":"+44 1323 411490",
    "sg:postcode":"BN21 3UF",
    "sg:province":"East Sussex",
    "sg:tags":[
        "local"
    ],
    "wof:name":"East Sussex County Council",
    "wof:placetype":"venue"
},
  "geometry": {"coordinates":[0.2853499949,50.766910553],"type":"Point"}
}