{
  "type": "Feature",
  "properties": {
    "iso:country":"GB",
    "sg:address":"Eastern Rd Surgery, Eastern Rd",
    "sg:city":"Newton Abbot",
    "sg:classifiers":[
        {
            "category":"Health Services",
            "subcategory":"Doctor",
            "type":"Services"
        }
    ],
    "sg:phone":"+44 1364 652731",
    "sg:postcode":"TQ13 7AP",
    "sg:province":"Devon",
    "sg:tags":[
        "practitioners"
    ],
    "wof:name":"Burmey, P",
    "wof:placetype":"venue"
},
  "geometry": {"coordinates":[-3.748344,50.519024],"type":"Point"}
}