{
  "type": "Feature",
  "properties": {
    "iso:country":"GB",
    "sg:address":"10 Belmont Hill, Lewisham",
    "sg:city":"London",
    "sg:classifiers":[
        {
            "category":"Professional",
            "subcategory":"Lawyer & Legal Services",
            "type":"Services"
        }
    ],
    "sg:phone":"+44 20 8852 2921",
    "sg:postcode":"SE13 5BD",
    "sg:province":"Greater London",
    "sg:tags":[
        "solicitor"
    ],
    "wof:name":"Straker Holford & Co.",
    "wof:placetype":"venue"
},
  "geometry": {"coordinates":[-0.008198,51.462708],"type":"Point"}
}