{
  "type": "Feature",
  "properties": {
    "iso:country":"GB",
    "sg:address":"Frogmoor Wharf, Harefield Road",
    "sg:city":"Rickmansworth",
    "sg:classifiers":[
        {
            "category":"Food & Beverages",
            "subcategory":"Supermarket",
            "type":"Retail Goods"
        }
    ],
    "sg:phone":"+44 1923 480400",
    "sg:postcode":"WD3 1LX",
    "sg:province":"Hertfordshire",
    "wof:name":"Tesco Stores Ltd.",
    "wof:placetype":"venue"
},
  "geometry": {"coordinates":[-0.4721359909,51.6329421997],"type":"Point"}
}