{
  "type": "Feature",
  "properties": {
    "addr:full":"32 Lynmouth Road, Hucclecote Gloucester Gloucestershire GL3 3JD",
    "addr:housenumber":"32",
    "addr:postcode":"gl3 3jd",
    "addr:street":"Lynmouth Road",
    "iso:country":"GB",
    "sg:address":"32 Lynmouth Road, Hucclecote",
    "sg:city":"Gloucester",
    "sg:classifiers":[
        {
            "category":"Professional",
            "subcategory":"Engineering",
            "type":"Services"
        }
    ],
    "sg:phone":"+44 1452 615181",
    "sg:postcode":"GL3 3JD",
    "sg:province":"Gloucestershire",
    "sg:tags":[
        "hydraulic",
        "engineer"
    ],
    "wof:name":"N E Hydraulics",
    "wof:placetype":"venue"
},
  "geometry": {"coordinates":[-2.1923370361,51.8519134521],"type":"Point"}
}