{
  "type": "Feature",
  "properties": {
    "addr:full":"B M Lire London Greater London WC1N 3XX",
    "addr:postcode":"wc1n 3xx",
    "iso:country":"GB",
    "sg:address":"B M Lire",
    "sg:city":"London",
    "sg:classifiers":[
        {
            "category":"Government",
            "subcategory":"Post Office",
            "type":"Public Place"
        }
    ],
    "sg:phone":"+44 20 7267 8003",
    "sg:postcode":"WC1N 3XX",
    "sg:province":"Greater London",
    "sg:tags":[
        "organisation",
        "soc",
        "research"
    ],
    "wof:name":"London International Research Exchange",
    "wof:placetype":"venue"
},
  "geometry": {"coordinates":[-0.12198,51.52063],"type":"Point"}
}