{
  "type": "Feature",
  "properties": {
    "addr:full":"48 Lubnaig Rd, Newlands Glasgow Glasgow City G43 2RX",
    "addr:housenumber":"48",
    "addr:postcode":"g43 2rx",
    "addr:street":"Lubnaig Rd",
    "iso:country":"GB",
    "sg:address":"48 Lubnaig Rd, Newlands",
    "sg:city":"Glasgow",
    "sg:classifiers":[
        {
            "category":"Professional",
            "type":"Services"
        }
    ],
    "sg:phone":"+44 141 637 3388",
    "sg:postcode":"G43 2RX",
    "sg:province":"Glasgow City",
    "sg:tags":[
        "reflexologists"
    ],
    "wof:name":"Sheilagh White",
    "wof:placetype":"venue"
},
  "geometry": {"coordinates":[-4.2806019783,55.8148727417],"type":"Point"}
}