{
  "type": "Feature",
  "properties": {
    "addr:full":"26 Wakefield Rd Normanton West Yorkshire WF6 2BT",
    "addr:housenumber":"26",
    "addr:postcode":"wf6 2bt",
    "addr:street":"Wakefield Rd",
    "iso:country":"GB",
    "sg:address":"26 Wakefield Rd",
    "sg:city":"Normanton",
    "sg:classifiers":[
        {
            "category":"Retail",
            "subcategory":"Repair Shop",
            "type":"Services"
        }
    ],
    "sg:phone":"+44 1924 893791",
    "sg:postcode":"WF6 2BT",
    "sg:province":"West Yorkshire",
    "sg:tags":[
        "upholsterer"
    ],
    "wof:name":"M G Upholstery",
    "wof:placetype":"venue"
},
  "geometry": {"coordinates":[-1.422973,53.698719],"type":"Point"}
}