{
  "type": "Feature",
  "properties": {
    "addr:full":"105 Winn Road London Greater London SE12 9EZ",
    "addr:housenumber":"105",
    "addr:postcode":"se12 9ez",
    "addr:street":"Winn Road",
    "iso:country":"GB",
    "sg:address":"105 Winn Road",
    "sg:city":"London",
    "sg:classifiers":[
        {
            "category":"Professional",
            "subcategory":"Art Services",
            "type":"Services"
        }
    ],
    "sg:phone":"+44 20 8857 0127",
    "sg:postcode":"SE12 9EZ",
    "sg:province":"Greater London",
    "sg:tags":[
        "stone",
        "restoration",
        "cleaning"
    ],
    "wof:name":"Opalstone",
    "wof:placetype":"venue"
},
  "geometry": {"coordinates":[0.0282189995,51.4415893555],"type":"Point"}
}