{
  "type": "Feature",
  "properties": {
    "addr:full":"The Mockett S Wood Broadstairs Kent CT10 2TR",
    "addr:postcode":"ct10 2tr",
    "addr:street":"S Wood",
    "iso:country":"GB",
    "sg:address":"The Mockett S Wood",
    "sg:city":"Broadstairs",
    "sg:classifiers":[
        {
            "category":"Health Services",
            "subcategory":"Doctor",
            "type":"Services"
        }
    ],
    "sg:phone":"+44 1843 862996",
    "sg:postcode":"CT10 2TR",
    "sg:province":"Kent",
    "sg:tags":[
        "practitioners"
    ],
    "wof:name":"David Marshall",
    "wof:placetype":"venue"
},
  "geometry": {"coordinates":[1.44106,51.358604],"type":"Point"}
}