{
  "type": "Feature",
  "properties": {
    "addr:full":"2 The Parade, Brighton Road, Burgh Heath Tadworth Surrey KT20 6AT",
    "addr:housenumber":"2",
    "addr:postcode":"kt20 6at",
    "addr:street":"The Parade Brighton Road",
    "iso:country":"GB",
    "sg:address":"2 The Parade, Brighton Road, Burgh Heath",
    "sg:city":"Tadworth",
    "sg:classifiers":[
        {
            "category":"Retail",
            "subcategory":"Auto Repair",
            "type":"Services"
        }
    ],
    "sg:postcode":"KT20 6AT",
    "sg:province":"Surrey",
    "sg:tags":[
        "modification",
        "garage"
    ],
    "wof:name":"C J S Landscapes",
    "wof:placetype":"venue"
},
  "geometry": {"coordinates":[-0.2188899964,51.3063087463],"type":"Point"}
}