{
  "type": "Feature",
  "properties": {
    "iso:country":"GB",
    "sg:address":"64 Hall Lane, Armley",
    "sg:city":"Leeds",
    "sg:classifiers":[
        {
            "category":"Home & Garden",
            "subcategory":"Building Materials",
            "type":"Retail Goods"
        },
        {
            "category":"Building & Trades",
            "subcategory":"Construction",
            "type":"Services"
        }
    ],
    "sg:phone":"+44 113 231 9910",
    "sg:postcode":"LS12 2LH",
    "sg:province":"West Yorkshire",
    "sg:tags":[
        "shutter",
        "joinery",
        "door"
    ],
    "wof:name":"Lenco Joinery",
    "wof:placetype":"venue"
},
  "geometry": {"coordinates":[-1.5808559656,53.7958641052],"type":"Point"}
}