{
  "type": "Feature",
  "properties": {
    "iso:country":"GB",
    "sg:address":"6 Royds Ave",
    "sg:city":"Huddersfield",
    "sg:classifiers":[
        {
            "category":"Professional",
            "subcategory":"Engineering",
            "type":"Services"
        }
    ],
    "sg:postcode":"HD3 4HB",
    "sg:province":"West Yorkshire",
    "sg:tags":[
        "contractor",
        "electrical",
        "engineer"
    ],
    "wof:name":"Dyson,Martin,",
    "wof:placetype":"venue"
},
  "geometry": {"coordinates":[-1.817756,53.644531],"type":"Point"}
}