{
  "type": "Feature",
  "properties": {
    "addr:full":"Brantrigg, Gatebeck Road, Endmoor Kendal Cumbria LA8 0HH",
    "addr:postcode":"la8 0hh",
    "addr:street":"Gatebeck Road Endmoor",
    "iso:country":"GB",
    "sg:address":"Brantrigg, Gatebeck Road, Endmoor",
    "sg:city":"Kendal",
    "sg:classifiers":[
        {
            "category":"Building & Trades",
            "subcategory":"Construction",
            "type":"Services"
        }
    ],
    "sg:phone":"+44 15395 67405",
    "sg:postcode":"LA8 0HH",
    "sg:province":"Cumbria",
    "sg:tags":[
        "builder"
    ],
    "wof:name":"Mace Construction",
    "wof:placetype":"venue"
},
  "geometry": {"coordinates":[-2.708229,54.257839],"type":"Point"}
}