{
  "type": "Feature",
  "properties": {
    "iso:country":"GB",
    "sg:address":"Cambridge House, 180 Upper Richmond Road, Putney",
    "sg:city":"London",
    "sg:classifiers":[
        {
            "category":"Real Estate",
            "subcategory":"Architect",
            "type":"Services"
        }
    ],
    "sg:phone":"+44 20 8785 0303",
    "sg:postcode":"SW15 2SH",
    "sg:province":"Greater London",
    "wof:name":"Vassallo Mellor Parris",
    "wof:placetype":"venue"
},
  "geometry": {"coordinates":[-0.2160129994,51.4606819153],"type":"Point"}
}