{
  "type": "Feature",
  "properties": {
    "addr:full":"Westfield Road Burnham-on-sea Somerset TA8 2AF",
    "addr:postcode":"ta8 2af",
    "addr:street":"Westfield Road",
    "iso:country":"GB",
    "sg:address":"Westfield Road",
    "sg:city":"Burnham-on-sea",
    "sg:classifiers":[
        {
            "category":"Recreation",
            "subcategory":"Campground",
            "type":"Entertainment"
        }
    ],
    "sg:phone":"+44 1278 782154",
    "sg:postcode":"TA8 2AF",
    "sg:province":"Somerset",
    "sg:tags":[
        "caravan",
        "park"
    ],
    "wof:name":"Newcombe Caravan Park",
    "wof:placetype":"venue"
},
  "geometry": {"coordinates":[-2.994173,51.241276],"type":"Point"}
}