{
  "type": "Feature",
  "properties": {
    "iso:country":"GB",
    "sg:address":"Elkington Lodge, Welford",
    "sg:city":"Northampton",
    "sg:classifiers":[
        {
            "category":"Wholesale",
            "subcategory":"Electrical",
            "type":"Manufacturing & Wholesale Goods"
        }
    ],
    "sg:postcode":"NN6 6HE",
    "sg:province":"Northamptonshire",
    "sg:tags":[
        "equipment",
        "refrigeration"
    ],
    "wof:name":"J E Mechanical Services Ltd.",
    "wof:placetype":"venue"
},
  "geometry": {"coordinates":[-1.083421,52.38372],"type":"Point"}
}