{
  "type": "Feature",
  "properties": {
    "iso:country":"GB",
    "sg:address":"8 Watersmeet Road",
    "sg:city":"Lynmouth",
    "sg:classifiers":[
        {
            "category":"Travel",
            "subcategory":"Hotels & Motels",
            "type":"Entertainment"
        }
    ],
    "sg:postcode":"EX35 6EP",
    "sg:province":"Devon",
    "wof:name":"Shelley's Hotel & River Restaurant",
    "wof:placetype":"venue"
},
  "geometry": {"coordinates":[-3.820416,51.22723],"type":"Point"}
}