{
  "type": "Feature",
  "properties": {
    "iso:country":"GB",
    "sg:address":"New Lane",
    "sg:city":"Thornton-cleveleys",
    "sg:classifiers":[
        {
            "category":"Shopping",
            "subcategory":"Department Store",
            "type":"Retail Goods"
        },
        {
            "category":"Home & Garden",
            "subcategory":"Hardware",
            "type":"Retail Goods"
        }
    ],
    "sg:phone":"+44 1253 864290",
    "sg:postcode":"FY5 5NH",
    "sg:province":"Lancashire",
    "sg:tags":[
        "lawnmowers",
        "machinery"
    ],
    "wof:name":"Mowercare",
    "wof:placetype":"venue"
},
  "geometry": {"coordinates":[-3.003825,53.862057],"type":"Point"}
}