{
  "type": "Feature",
  "properties": {
    "addr:full":"133 Bevan Street East Lowestoft Suffolk NR32 2AQ",
    "addr:housenumber":"133",
    "addr:postcode":"nr32 2aq",
    "addr:street":"Bevan Street East",
    "iso:country":"GB",
    "sg:address":"133 Bevan Street East",
    "sg:city":"Lowestoft",
    "sg:classifiers":[
        {
            "category":"Shopping",
            "subcategory":"Clothing, Apparel, & Fashions",
            "type":"Retail Goods"
        }
    ],
    "sg:phone":"+44 1502 565170",
    "sg:postcode":"NR32 2AQ",
    "sg:province":"Suffolk",
    "sg:tags":[
        "menswear"
    ],
    "wof:name":"The Yarmouth Stores Ltd.",
    "wof:placetype":"venue"
},
  "geometry": {"coordinates":[1.750642,52.474846],"type":"Point"}
}