{
  "type": "Feature",
  "properties": {
    "iso:country":"GB",
    "sg:address":"Low Cleveland Street, Liverton",
    "sg:city":"Saltburn-by-the-sea",
    "sg:classifiers":[
        {
            "category":"Organizations",
            "subcategory":"Membership Organization",
            "type":"Services"
        }
    ],
    "sg:phone":"+44 1287 640335",
    "sg:postcode":"TS13 4QY",
    "sg:province":"North Yorkshire",
    "sg:tags":[
        "club"
    ],
    "wof:name":"Liverton Working Men's Club & Institute Ltd.",
    "wof:placetype":"venue"
},
  "geometry": {"coordinates":[-0.901561,54.552479],"type":"Point"}
}