{
  "type": "Feature",
  "properties": {
    "addr:full":"115 Southbridge Rd Croydon Surrey CR0 1AJ",
    "addr:housenumber":"115",
    "addr:postcode":"cr0 1aj",
    "addr:street":"Southbridge Rd",
    "iso:country":"GB",
    "sg:address":"115 Southbridge Rd",
    "sg:city":"Croydon",
    "sg:classifiers":[
        {
            "category":"Autos & Motor Vehicles",
            "subcategory":"Auto Supplies",
            "type":"Retail Goods"
        }
    ],
    "sg:postcode":"CR0 1AJ",
    "sg:province":"Surrey",
    "sg:tags":[
        "tyre"
    ],
    "wof:name":"Fritz,M,",
    "wof:placetype":"venue"
},
  "geometry": {"coordinates":[-0.0998750031,51.3657569885],"type":"Point"}
}