{
  "type": "Feature",
  "properties": {
    "addr:full":"99 Conway Road Colwyn Bay Conwy LL29 7LW",
    "addr:housenumber":"99",
    "addr:postcode":"ll29 7lw",
    "addr:street":"Conway Road",
    "iso:country":"GB",
    "sg:address":"99 Conway Road",
    "sg:city":"Colwyn Bay",
    "sg:classifiers":[
        {
            "category":"Fast Food",
            "type":"Food & Drink"
        }
    ],
    "sg:phone":"+44 1492 535300",
    "sg:postcode":"LL29 7LW",
    "sg:province":"Conwy",
    "sg:tags":[
        "away",
        "meal",
        "outlet",
        "take"
    ],
    "wof:name":"Rozis Tandoori House",
    "wof:placetype":"venue"
},
  "geometry": {"coordinates":[-3.7387518883,53.2993011475],"type":"Point"}
}