{
  "type": "Feature",
  "properties": {
    "addr:full":"Chester Rd Warrington Cheshire WA6 0JE",
    "addr:postcode":"wa6 0je",
    "addr:street":"Chester Rd",
    "iso:country":"GB",
    "sg:address":"Chester Rd",
    "sg:city":"Warrington",
    "sg:classifiers":[
        {
            "category":"Bars & Pubs",
            "type":"Food & Drink"
        }
    ],
    "sg:phone":"+44 1928 722165",
    "sg:postcode":"WA6 0JE",
    "sg:province":"Cheshire",
    "sg:tags":[
        "pubs",
        "inn"
    ],
    "wof:name":"The Helsby Arms",
    "wof:placetype":"venue"
},
  "geometry": {"coordinates":[-2.7707641125,53.2694511414],"type":"Point"}
}