{
  "type": "Feature",
  "properties": {
    "addr:full":"3-3a Occleshaw House, 2 Worden Lane, Leyland Preston Lancashire PR5 1EL",
    "addr:housenumber":"3-3a;2",
    "addr:postcode":"pr5 1el",
    "addr:street":"Worden Lane",
    "iso:country":"GB",
    "sg:address":"3-3a Occleshaw House, 2 Worden Lane, Leyland",
    "sg:city":"Preston",
    "sg:classifiers":[
        {
            "category":"Professional",
            "subcategory":"Lawyer & Legal Services",
            "type":"Services"
        }
    ],
    "sg:phone":"+44 1772 622227",
    "sg:postcode":"PR5 1EL",
    "sg:province":"Lancashire",
    "sg:tags":[
        "solicitor"
    ],
    "wof:name":"Derek Wharton",
    "wof:placetype":"venue"
},
  "geometry": {"coordinates":[-2.69349,53.695339],"type":"Point"}
}