{
  "type": "Feature",
  "properties": {
    "addr:full":"Moorends Farm, Goole Road, Moorends Doncaster East Riding of Yorkshire DN8 4JY",
    "addr:postcode":"dn8 4jy",
    "addr:street":"Goole Road;Riding",
    "iso:country":"GB",
    "sg:address":"Moorends Farm, Goole Road, Moorends",
    "sg:city":"Doncaster",
    "sg:classifiers":[
        {
            "category":"Farming",
            "subcategory":"Farm",
            "type":"Manufacturing & Wholesale Goods"
        }
    ],
    "sg:phone":"+44 1405 740642",
    "sg:postcode":"DN8 4JY",
    "sg:province":"East Riding of Yorkshire",
    "sg:tags":[
        "mixed",
        "crop"
    ],
    "wof:name":"Sam Longthorp Ltd.",
    "wof:placetype":"venue"
},
  "geometry": {"coordinates":[-0.9515540004,53.6278648376],"type":"Point"}
}