{
  "type": "Feature",
  "properties": {
    "addr:full":"161 Buxton Road Stockport Cheshire SK2 6EQ",
    "addr:housenumber":"161",
    "addr:postcode":"sk2 6eq",
    "addr:street":"Buxton Road",
    "iso:country":"GB",
    "sg:address":"161 Buxton Road",
    "sg:city":"Stockport",
    "sg:classifiers":[
        {
            "category":"Home & Garden",
            "subcategory":"Kitchen Supply",
            "type":"Retail Goods"
        }
    ],
    "sg:phone":"+44 161 483 6256",
    "sg:postcode":"SK2 6EQ",
    "sg:province":"Cheshire",
    "sg:tags":[
        "equipment",
        "catering"
    ],
    "wof:name":"H G Stephenson Ltd",
    "wof:placetype":"venue"
},
  "geometry": {"coordinates":[-2.146406889,53.3932609558],"type":"Point"}
}