{
  "type": "Feature",
  "properties": {
    "addr:full":"9 Fulford Park, Fulford York North Yorkshire YO10 4QE",
    "addr:housenumber":"9",
    "addr:postcode":"yo10 4qe",
    "addr:street":"Fulford Park",
    "iso:country":"GB",
    "sg:address":"9 Fulford Park, Fulford",
    "sg:city":"York",
    "sg:classifiers":[
        {
            "category":"Organizations",
            "subcategory":"Community Association",
            "type":"Services"
        }
    ],
    "sg:phone":"+44 1904 626117",
    "sg:postcode":"YO10 4QE",
    "sg:province":"North Yorkshire",
    "sg:tags":[
        "relation",
        "public"
    ],
    "wof:name":"David Rymer Public Relations Adviser",
    "wof:placetype":"venue"
},
  "geometry": {"coordinates":[-1.074704051,53.9373855591],"type":"Point"}
}