{
  "type": "Feature",
  "properties": {
    "iso:country":"GB",
    "sg:address":"Old Hall Farm",
    "sg:city":"North Walsham",
    "sg:classifiers":[
        {
            "category":"Farming",
            "subcategory":"Livestock Farm",
            "type":"Manufacturing & Wholesale Goods"
        }
    ],
    "sg:phone":"+44 1692 402047",
    "sg:postcode":"NR28 9QQ",
    "sg:province":"Norfolk",
    "sg:tags":[
        "others"
    ],
    "wof:name":"Alston & Donald",
    "wof:placetype":"venue"
},
  "geometry": {"coordinates":[1.4388109446,52.8173522949],"type":"Point"}
}