{
  "type": "Feature",
  "properties": {
    "addr:full":"86 Trentham Street London Greater London SW18 5DJ",
    "addr:housenumber":"86",
    "addr:postcode":"sw18 5dj",
    "addr:street":"Trentham Street",
    "iso:country":"GB",
    "sg:address":"86 Trentham Street",
    "sg:city":"London",
    "sg:classifiers":[
        {
            "category":"Professional",
            "subcategory":"Lawyer & Legal Services",
            "type":"Services"
        }
    ],
    "sg:postcode":"SW18 5DJ",
    "sg:province":"Greater London",
    "sg:tags":[
        "advice",
        "counselling"
    ],
    "wof:name":"David Hawley Counselling",
    "wof:placetype":"venue"
},
  "geometry": {"coordinates":[-0.200313,51.442093],"type":"Point"}
}