{
  "type": "Feature",
  "properties": {
    "addr:full":"64 Pentley Park Welwyn Garden City Hertfordshire AL8 7SG",
    "addr:housenumber":"64",
    "addr:postcode":"al8 7sg",
    "addr:street":"Pentley Park Welwyn",
    "iso:country":"GB",
    "sg:address":"64 Pentley Park",
    "sg:city":"Welwyn Garden City",
    "sg:classifiers":[
        {
            "category":"Professional",
            "subcategory":"Management & Consulting",
            "type":"Services"
        }
    ],
    "sg:phone":"+44 1707 376275",
    "sg:postcode":"AL8 7SG",
    "sg:province":"Hertfordshire",
    "sg:tags":[
        "consultant",
        "business"
    ],
    "wof:name":"Arabel Consultants Ltd.",
    "wof:placetype":"venue"
},
  "geometry": {"coordinates":[-0.20874,51.812088],"type":"Point"}
}