{
  "type": "Feature",
  "properties": {
    "iso:country":"GB",
    "sg:address":"Lodel Farm, Overcote Lane, Needingworth",
    "sg:city":"St Ives",
    "sg:classifiers":[
        {
            "category":"Farming",
            "subcategory":"Livestock Farm",
            "type":"Manufacturing & Wholesale Goods"
        }
    ],
    "sg:phone":"+44 1480 465628",
    "sg:postcode":"PE27 4TN",
    "sg:province":"Cambridgeshire",
    "sg:tags":[
        "others"
    ],
    "wof:name":"J D Hudson",
    "wof:placetype":"venue"
},
  "geometry": {"coordinates":[-0.029699,52.330704],"type":"Point"}
}