{
  "type": "Feature",
  "properties": {
    "addr:full":"Tarn Lodge Eye Hospital, Heads Nook Brampton Cumbria CA8 9BT",
    "addr:postcode":"ca8 9bt",
    "iso:country":"GB",
    "sg:address":"Tarn Lodge Eye Hospital, Heads Nook",
    "sg:city":"Brampton",
    "sg:classifiers":[
        {
            "category":"Health Services",
            "subcategory":"Hospital",
            "type":"Services"
        }
    ],
    "sg:phone":"+44 1228 670114",
    "sg:postcode":"CA8 9BT",
    "sg:province":"Cumbria",
    "wof:name":"Tarn Lodge",
    "wof:placetype":"venue"
},
  "geometry": {"coordinates":[-2.790884,54.889664],"type":"Point"}
}