{
  "type": "Feature",
  "properties": {
    "addr:full":"137 8 Bonnington Road, Leith Edinburgh City of Edinburgh EH6 5JP",
    "addr:housenumber":"137 8",
    "addr:postcode":"eh6 5jp",
    "addr:street":"Bonnington Road",
    "iso:country":"GB",
    "sg:address":"137 8 Bonnington Road, Leith",
    "sg:city":"Edinburgh",
    "sg:classifiers":[
        {
            "category":"Manufacturing",
            "subcategory":"Petroleum Products",
            "type":"Manufacturing & Wholesale Goods"
        }
    ],
    "sg:phone":"+44 131 554 3934",
    "sg:postcode":"EH6 5JP",
    "sg:province":"City of Edinburgh",
    "sg:tags":[
        "double",
        "glazing"
    ],
    "wof:name":"Shore Joinery",
    "wof:placetype":"venue"
},
  "geometry": {"coordinates":[-3.1793010235,55.9709472656],"type":"Point"}
}