{
  "type": "Feature",
  "properties": {
    "addr:full":"38-40 High Street Orpington Kent BR6 6BJ",
    "addr:housenumber":"38-40",
    "addr:postcode":"br6 6bj",
    "addr:street":"High Street",
    "iso:country":"GB",
    "sg:address":"38-40 High Street",
    "sg:city":"Orpington",
    "sg:classifiers":[
        {
            "category":"Professional",
            "subcategory":"Printing & Photocopies",
            "type":"Services"
        }
    ],
    "sg:postcode":"BR6 6BJ",
    "sg:province":"Kent",
    "sg:tags":[
        "duplicating",
        "copying"
    ],
    "wof:name":"Mister Print",
    "wof:placetype":"venue"
},
  "geometry": {"coordinates":[0.0893059969,51.3520736694],"type":"Point"}
}