{
  "type": "Feature",
  "properties": {
    "iso:country":"GB",
    "sg:address":"One Central House",
    "sg:city":"Exeter",
    "sg:classifiers":[
        {
            "category":"Utilities",
            "subcategory":"Telephone",
            "type":"Services"
        }
    ],
    "sg:postcode":"EX4 3ER",
    "sg:province":"Devon",
    "sg:tags":[
        "telecommunication"
    ],
    "wof:name":"Mike Smith",
    "wof:placetype":"venue"
},
  "geometry": {"coordinates":[-3.5333,50.72509],"type":"Point"}
}