{
  "type": "Feature",
  "properties": {
    "addr:full":"30a Sarum Business Park, The Portway Salisbury Hampshire SP4 6EA",
    "addr:housenumber":"30a",
    "addr:postcode":"sp4 6ea",
    "addr:street":"Business Park The Portway",
    "iso:country":"GB",
    "sg:address":"30a Sarum Business Park, The Portway",
    "sg:city":"Salisbury",
    "sg:classifiers":[
        {
            "category":"Retail",
            "subcategory":"Repair Shop",
            "type":"Services"
        }
    ],
    "sg:phone":"+44 1722 414844",
    "sg:postcode":"SP4 6EA",
    "sg:province":"Hampshire",
    "sg:tags":[
        "maintenance"
    ],
    "wof:name":"Celtic Infrastructure Services Ltd",
    "wof:placetype":"venue"
},
  "geometry": {"coordinates":[-1.7863,51.10022],"type":"Point"}
}