{
  "type": "Feature",
  "properties": {
    "iso:country":"GB",
    "sg:address":"66 Oaston Road",
    "sg:city":"Nuneaton",
    "sg:classifiers":[
        {
            "category":"Social Services",
            "subcategory":"Retirement Home",
            "type":"Services"
        },
        {
            "category":"Organizations",
            "subcategory":"Non-profit Organization",
            "type":"Services"
        }
    ],
    "sg:postcode":"CV11 6JZ",
    "sg:province":"Leicestershire",
    "sg:tags":[
        "residential",
        "organisation",
        "charity",
        "voluntary",
        "care"
    ],
    "wof:name":"P A K S Trust",
    "wof:placetype":"venue"
},
  "geometry": {"coordinates":[-1.4565930367,52.5248069763],"type":"Point"}
}