{
  "type": "Feature",
  "properties": {
    "iso:country":"GB",
    "sg:address":"48 Bowleymead, Eldene",
    "sg:city":"Swindon",
    "sg:classifiers":[
        {
            "category":"Professional",
            "subcategory":"Engineering",
            "type":"Services"
        }
    ],
    "sg:phone":"+44 1793 511292",
    "sg:postcode":"SN3 3TD",
    "sg:province":"Wiltshire",
    "sg:tags":[
        "contractor",
        "electrical",
        "engineer"
    ],
    "wof:name":"Gerrys Electrical",
    "wof:placetype":"venue"
},
  "geometry": {"coordinates":[-1.734464,51.558262],"type":"Point"}
}