{
  "type": "Feature",
  "properties": {
    "iso:country":"GB",
    "sg:address":"46 Bridge St",
    "sg:city":"Godalming",
    "sg:classifiers":[
        {
            "category":"Professional",
            "subcategory":"Computer Services",
            "type":"Services"
        }
    ],
    "sg:phone":"+44 1483 414147",
    "sg:postcode":"GU7 1HL",
    "sg:province":"Surrey",
    "sg:tags":[
        "information"
    ],
    "wof:name":"Halon Users National Consortium",
    "wof:placetype":"venue"
},
  "geometry": {"coordinates":[-0.610335,51.186131],"type":"Point"}
}