{
  "type": "Feature",
  "properties": {
    "addr:full":"13b Heath Rd Petersfield Hampshire GU31 4JE",
    "addr:housenumber":"13b",
    "addr:postcode":"gu31 4je",
    "addr:street":"Heath Rd",
    "iso:country":"GB",
    "sg:address":"13b Heath Rd",
    "sg:city":"Petersfield",
    "sg:classifiers":[
        {
            "category":"Place Of Worship",
            "type":"Public Place"
        }
    ],
    "sg:phone":"+44 1730 263317",
    "sg:postcode":"GU31 4JE",
    "sg:province":"Hampshire",
    "wof:name":"Petersfield Methodist Church",
    "wof:placetype":"venue"
},
  "geometry": {"coordinates":[-0.9338030219,51.0034599304],"type":"Point"}
}