{
  "type": "Feature",
  "properties": {
    "addr:full":"Bottom Farm, Brook Street, Hargrave Wellingborough Northamptonshire NN9 6BP",
    "addr:postcode":"nn9 6bp",
    "addr:street":"Brook Street",
    "iso:country":"GB",
    "sg:address":"Bottom Farm, Brook Street, Hargrave",
    "sg:city":"Wellingborough",
    "sg:classifiers":[
        {
            "category":"Home & Garden",
            "subcategory":"Home Furnishings",
            "type":"Retail Goods"
        },
        {
            "category":"Building & Trades",
            "subcategory":"Construction",
            "type":"Services"
        }
    ],
    "sg:phone":"+44 1933 461145",
    "sg:postcode":"NN9 6BP",
    "sg:province":"Northamptonshire",
    "sg:tags":[
        "mantelpiece",
        "fireplace"
    ],
    "wof:name":"CHILTERN HOMES DEVELOPMENTS",
    "wof:placetype":"venue"
},
  "geometry": {"coordinates":[-0.4800589979,52.324016571],"type":"Point"}
}