{
  "type": "Feature",
  "properties": {
    "addr:full":"Care Of Bethel Baptist Church, Penlline Rd Cardiff Cardiff CF4 2AA",
    "addr:postcode":"cf4 2aa",
    "addr:street":"Penlline Rd",
    "iso:country":"GB",
    "sg:address":"Care Of Bethel Baptist Church, Penlline Rd",
    "sg:city":"Cardiff",
    "sg:classifiers":[
        {
            "category":"Personal",
            "type":"Services"
        }
    ],
    "sg:phone":"+44 29 2064 5125",
    "sg:postcode":"CF4 2AA",
    "sg:province":"Cardiff",
    "sg:tags":[
        "slimming",
        "product"
    ],
    "wof:name":"Slimming World",
    "wof:placetype":"venue"
},
  "geometry": {"coordinates":[-3.180670023,51.4812583923],"type":"Point"}
}