{
  "type": "Feature",
  "properties": {
    "addr:full":"37 The Broadway, Stratford London Greater London E15 4BQ",
    "addr:housenumber":"37",
    "addr:postcode":"e15 4bq",
    "addr:street":"The Broadway",
    "iso:country":"GB",
    "sg:address":"37 The Broadway, Stratford",
    "sg:city":"London",
    "sg:classifiers":[
        {
            "category":"Freight",
            "type":"Transportation"
        }
    ],
    "sg:postcode":"E15 4BQ",
    "sg:province":"Greater London",
    "sg:tags":[
        "haulage",
        "road"
    ],
    "wof:name":"Smith, A G, Transport Services Ltd",
    "wof:placetype":"venue"
},
  "geometry": {"coordinates":[0.00192,51.5408706665],"type":"Point"}
}