{
  "type": "Feature",
  "properties": {
    "addr:full":"5 Tower Rd Hereford Herefordshire HR4 0LF",
    "addr:housenumber":"5",
    "addr:postcode":"hr4 0lf",
    "addr:street":"Tower Rd",
    "iso:country":"GB",
    "sg:address":"5 Tower Rd",
    "sg:city":"Hereford",
    "sg:classifiers":[
        {
            "category":"Education",
            "subcategory":"Dance Studio",
            "type":"Public Place"
        }
    ],
    "sg:phone":"+44 1432 351314",
    "sg:postcode":"HR4 0LF",
    "sg:province":"Herefordshire",
    "sg:tags":[
        "school",
        "dancing"
    ],
    "wof:name":"Sarah-Jane School Of Dancing",
    "wof:placetype":"venue"
},
  "geometry": {"coordinates":[-2.731494,52.05341],"type":"Point"}
}