{
  "type": "Feature",
  "properties": {
    "iso:country":"GB",
    "sg:address":"164 Kirkstall Hill",
    "sg:city":"Leeds",
    "sg:classifiers":[
        {
            "category":"Shopping",
            "subcategory":"Florist",
            "type":"Retail Goods"
        }
    ],
    "sg:postcode":"LS4 2SX",
    "sg:province":"West Yorkshire",
    "wof:name":"Carol's Flower Bowl",
    "wof:placetype":"venue"
},
  "geometry": {"coordinates":[-1.589613,53.813301],"type":"Point"}
}