{
  "type": "Feature",
  "properties": {
    "iso:country":"GB",
    "sg:address":"Q S Stores 44 Belle Vale Shopping Centre",
    "sg:city":"Liverpool",
    "sg:classifiers":[
        {
            "category":"Shopping",
            "subcategory":"Gifts & Souvenirs",
            "type":"Retail Goods"
        }
    ],
    "sg:phone":"+44 151 488 0560",
    "sg:postcode":"L25 2RQ",
    "sg:province":"Merseyside",
    "sg:tags":[
        "poster",
        "card"
    ],
    "wof:name":"Card And Gift Department",
    "wof:placetype":"venue"
},
  "geometry": {"coordinates":[-2.852214,53.390301],"type":"Point"}
}