{
  "type": "Feature",
  "properties": {
    "addr:full":"11-13 Orlando Road London Greater London SW4 0LE",
    "addr:housenumber":"11-13",
    "addr:postcode":"sw4 0le",
    "addr:street":"Orlando Road",
    "iso:country":"GB",
    "sg:address":"11-13 Orlando Road",
    "sg:city":"London",
    "sg:classifiers":[
        {
            "category":"Arts & Performance",
            "subcategory":"Theater",
            "type":"Entertainment"
        }
    ],
    "sg:phone":"+44 20 7622 0314",
    "sg:postcode":"SW4 0LE",
    "sg:province":"Greater London",
    "sg:tags":[
        "theatrical",
        "agency"
    ],
    "wof:name":"Cochrane Elspeth Agency",
    "wof:placetype":"venue"
},
  "geometry": {"coordinates":[-0.1435309947,51.4653701782],"type":"Point"}
}