{
  "type": "Feature",
  "properties": {
    "iso:country":"GB",
    "sg:address":"258 South Road",
    "sg:city":"Sheffield",
    "sg:classifiers":[
        {
            "category":"Professional",
            "type":"Services"
        }
    ],
    "sg:phone":"+44 114 285 3269",
    "sg:postcode":"S6 3TB",
    "sg:province":"South Yorkshire",
    "sg:tags":[
        "caterer"
    ],
    "wof:name":"Carol's Catering Service",
    "wof:placetype":"venue"
},
  "geometry": {"coordinates":[-1.499773,53.392376],"type":"Point"}
}