{
  "type": "Feature",
  "properties": {
    "addr:full":"113a Warbro Road Torquay Devon TQ1 3QZ",
    "addr:housenumber":"113a",
    "addr:postcode":"tq1 3qz",
    "addr:street":"Warbro Road",
    "iso:country":"GB",
    "sg:address":"113a Warbro Road",
    "sg:city":"Torquay",
    "sg:classifiers":[
        {
            "category":"Autos & Motor Vehicles",
            "subcategory":"Auto Supplies",
            "type":"Retail Goods"
        }
    ],
    "sg:phone":"+44 1803 327568",
    "sg:postcode":"TQ1 3QZ",
    "sg:province":"Devon",
    "sg:tags":[
        "windscreen"
    ],
    "wof:name":"Carcraft",
    "wof:placetype":"venue"
},
  "geometry": {"coordinates":[-3.5208530426,50.4759712219],"type":"Point"}
}