{
  "type": "Feature",
  "properties": {
    "iso:country":"GB",
    "sg:address":"12 Kent Dr, Hibaldstow",
    "sg:city":"Brigg",
    "sg:classifiers":[
        {
            "category":"Freight",
            "type":"Transportation"
        }
    ],
    "sg:postcode":"DN20 9PP",
    "sg:province":"Lincolnshire",
    "sg:tags":[
        "haulage",
        "road"
    ],
    "wof:name":"Plumedraft Ltd",
    "wof:placetype":"venue"
},
  "geometry": {"coordinates":[-0.5213400126,53.5106964111],"type":"Point"}
}