{
  "type": "Feature",
  "properties": {
    "addr:full":"9 The Old Church Norwich Norfolk NR1 1SP",
    "addr:housenumber":"9",
    "addr:postcode":"nr1 1sp",
    "addr:street":"Norwich Norfolk",
    "iso:country":"GB",
    "sg:address":"9 The Old Church",
    "sg:city":"Norwich",
    "sg:classifiers":[
        {
            "category":"Organizations",
            "subcategory":"Non-profit Organization",
            "type":"Services"
        }
    ],
    "sg:phone":"+44 1603 629048",
    "sg:postcode":"NR1 1SP",
    "sg:province":"Norfolk",
    "sg:tags":[
        "organisation",
        "voluntary",
        "charity"
    ],
    "wof:name":"Norfolk Historic Buildings Trust",
    "wof:placetype":"venue"
},
  "geometry": {"coordinates":[1.2948999405,52.6224937439],"type":"Point"}
}