{
  "type": "Feature",
  "properties": {
    "iso:country":"GB",
    "sg:address":"Southminster Rd",
    "sg:city":"Cardiff",
    "sg:classifiers":[
        {
            "category":"Social Services",
            "type":"Services"
        }
    ],
    "sg:phone":"+44 29 2046 2717",
    "sg:postcode":"CF2 5AT",
    "sg:province":"Cardiff",
    "wof:name":"Ty Mawr Resource Centre",
    "wof:placetype":"venue"
},
  "geometry": {"coordinates":[-3.154139,51.492546],"type":"Point"}
}