{
  "type": "Feature",
  "properties": {
    "addr:full":"Wylcwm Place Knighton Shropshire LD7 1AE",
    "addr:postcode":"ld7 1ae",
    "addr:street":"Place",
    "iso:country":"GB",
    "sg:address":"Wylcwm Place",
    "sg:city":"Knighton",
    "sg:classifiers":[
        {
            "category":"Bars & Pubs",
            "type":"Food & Drink"
        },
        {
            "category":"Restaurant",
            "type":"Food & Drink"
        }
    ],
    "sg:phone":"+44 1547 520062",
    "sg:postcode":"LD7 1AE",
    "sg:province":"Shropshire",
    "sg:tags":[
        "pubs",
        "inn"
    ],
    "wof:name":"Horse & Jockey",
    "wof:placetype":"venue"
},
  "geometry": {"coordinates":[-3.04771,52.343067],"type":"Point"}
}