{
  "type": "Feature",
  "properties": {
    "addr:full":"Gingerbread House, 34 Grainger Park Road Newcastle-upon-tyne Tyne and Wear NE4 8RY",
    "addr:housenumber":"34",
    "addr:postcode":"ne4 8ry",
    "addr:street":"Grainger Park Road",
    "iso:country":"GB",
    "sg:address":"Gingerbread House, 34 Grainger Park Road",
    "sg:city":"Newcastle-upon-tyne",
    "sg:classifiers":[
        {
            "category":"Organizations",
            "subcategory":"Non-profit Organization",
            "type":"Services"
        }
    ],
    "sg:phone":"+44 191 272 4414",
    "sg:postcode":"NE4 8RY",
    "sg:province":"Tyne and Wear",
    "sg:tags":[
        "organisation",
        "voluntary",
        "charity"
    ],
    "wof:name":"West End Community Wardens",
    "wof:placetype":"venue"
},
  "geometry": {"coordinates":[-1.647458,54.971661],"type":"Point"}
}