{
  "type": "Feature",
  "properties": {
    "addr:full":"15 Holden Road London Greater London N12 8HP",
    "addr:housenumber":"15",
    "addr:postcode":"n12 8hp",
    "addr:street":"Holden Road",
    "iso:country":"GB",
    "sg:address":"15 Holden Road",
    "sg:city":"London",
    "sg:classifiers":[
        {
            "category":"Social Services",
            "subcategory":"Child Care",
            "type":"Services"
        }
    ],
    "sg:postcode":"N12 8HP",
    "sg:province":"Greater London",
    "sg:tags":[
        "agency",
        "nanny"
    ],
    "wof:name":"Tinies Nanny Agency",
    "wof:placetype":"venue"
},
  "geometry": {"coordinates":[-0.18297,51.616089],"type":"Point"}
}