{
  "type": "Feature",
  "properties": {
    "iso:country":"GB",
    "sg:address":"1 Station Road, Haslingden",
    "sg:city":"Rossendale",
    "sg:classifiers":[
        {
            "category":"Manufacturing",
            "subcategory":"Building Materials",
            "type":"Manufacturing & Wholesale Goods"
        }
    ],
    "sg:phone":"+44 1706 212521",
    "sg:postcode":"BB4 5HX",
    "sg:province":"Lancashire",
    "sg:tags":[
        "merchant",
        "builder"
    ],
    "wof:name":"Valley Building Supplies",
    "wof:placetype":"venue"
},
  "geometry": {"coordinates":[-2.325394,53.704639],"type":"Point"}
}