{
  "type": "Feature",
  "properties": {
    "iso:country":"GB",
    "sg:address":"11 East St",
    "sg:city":"Blandford Forum",
    "sg:classifiers":[
        {
            "category":"Restaurant",
            "type":"Food & Drink"
        }
    ],
    "sg:phone":"+44 1258 455324",
    "sg:postcode":"DT11 7DU",
    "sg:province":"Dorset",
    "wof:name":"White Boar Restaurant",
    "wof:placetype":"venue"
},
  "geometry": {"coordinates":[-2.1608600616,50.8567123413],"type":"Point"}
}