{
  "type": "Feature",
  "properties": {
    "iso:country":"GB",
    "sg:address":"Hillcrest Wheal, Venture Road, Treylyon",
    "sg:city":"St Ives",
    "sg:classifiers":[
        {
            "category":"Shopping",
            "subcategory":"Stationery & Office Supplies",
            "type":"Retail Goods"
        }
    ],
    "sg:phone":"+44 1736 793377",
    "sg:postcode":"TR26 2PQ",
    "sg:province":"Cornwall",
    "sg:tags":[
        "equipment"
    ],
    "wof:name":"P J Services",
    "wof:placetype":"venue"
},
  "geometry": {"coordinates":[-5.475312,50.199558],"type":"Point"}
}