{
  "type": "Feature",
  "properties": {
    "addr:full":"Semi-open Market Ground Floor, Upper Charter Arcade Barnsley South Yorkshire S70 1RF",
    "addr:housenumber":"ground floor",
    "addr:postcode":"s70 1rf",
    "addr:street":"Upper Charter;Yorkshire",
    "iso:country":"GB",
    "sg:address":"Semi-open Market Ground Floor, Upper Charter Arcade",
    "sg:city":"Barnsley",
    "sg:classifiers":[
        {
            "category":"Home & Garden",
            "subcategory":"Carpets & Floor Coverings",
            "type":"Retail Goods"
        }
    ],
    "sg:phone":"+44 1226 203808",
    "sg:postcode":"S70 1RF",
    "sg:province":"South Yorkshire",
    "sg:tags":[
        "floorcoverings"
    ],
    "wof:name":"R Wilshire",
    "wof:placetype":"venue"
},
  "geometry": {"coordinates":[-1.4847379923,53.5531921387],"type":"Point"}
}