{
  "type": "Feature",
  "properties": {
    "addr:full":"Hengist Court, Marsham Street Maidstone Kent ME14 1BT",
    "addr:postcode":"me14 1bt",
    "addr:street":"Marsham Street",
    "iso:country":"GB",
    "sg:address":"Hengist Court, Marsham Street",
    "sg:city":"Maidstone",
    "sg:classifiers":[
        {
            "category":"Health Services",
            "subcategory":"Nursing And Care Facility",
            "type":"Services"
        }
    ],
    "sg:phone":"+44 1622 674734",
    "sg:postcode":"ME14 1BT",
    "sg:province":"Kent",
    "sg:tags":[
        "home"
    ],
    "wof:name":"Hengist Court",
    "wof:placetype":"venue"
},
  "geometry": {"coordinates":[0.5280900002,51.2743110657],"type":"Point"}
}