{
  "type": "Feature",
  "properties": {
    "iso:country":"GB",
    "sg:address":"29 County Place",
    "sg:city":"Perth",
    "sg:classifiers":[
        {
            "category":"Education",
            "subcategory":"Junior College",
            "type":"Public Place"
        }
    ],
    "sg:phone":"+44 1738 444222",
    "sg:postcode":"PH2 8EE",
    "sg:province":"Perth and Kinross",
    "sg:tags":[
        "educational",
        "resource"
    ],
    "wof:name":"Formative Fun",
    "wof:placetype":"venue"
},
  "geometry": {"coordinates":[-3.4357368946,56.3955917358],"type":"Point"}
}