{
  "type": "Feature",
  "properties": {
    "addr:full":"8 Harbour Street Broadstairs Kent CT10 1ET",
    "addr:housenumber":"8",
    "addr:postcode":"ct10 1et",
    "addr:street":"Harbour Street",
    "iso:country":"GB",
    "sg:address":"8 Harbour Street",
    "sg:city":"Broadstairs",
    "sg:classifiers":[
        {
            "category":"Restaurant",
            "type":"Food & Drink"
        }
    ],
    "sg:phone":"+44 1843 602494",
    "sg:postcode":"CT10 1ET",
    "sg:province":"Kent",
    "wof:name":"Kellys Wine Bar Ltd.",
    "wof:placetype":"venue"
},
  "geometry": {"coordinates":[1.4440330267,51.3592758179],"type":"Point"}
}