{
  "type": "Feature",
  "properties": {
    "addr:full":"17 Darby Road, Brynteg Wrexham Wrexham LL11 6LW",
    "addr:housenumber":"17",
    "addr:postcode":"ll11 6lw",
    "addr:street":"Darby Road",
    "iso:country":"GB",
    "sg:address":"17 Darby Road, Brynteg",
    "sg:city":"Wrexham",
    "sg:classifiers":[
        {
            "category":"Cinema",
            "subcategory":"Movie Rental",
            "type":"Entertainment"
        },
        {
            "category":"Organizations",
            "subcategory":"Membership Organization",
            "type":"Services"
        }
    ],
    "sg:postcode":"LL11 6LW",
    "sg:province":"Wrexham",
    "sg:tags":[
        "video",
        "library"
    ],
    "wof:name":"MOVIELAND 4",
    "wof:placetype":"venue"
},
  "geometry": {"coordinates":[-3.0349969864,53.0626335144],"type":"Point"}
}