{
  "type": "Feature",
  "properties": {
    "iso:country":"GB",
    "sg:address":"Horsham Farm, Tamerton Foliot",
    "sg:city":"Plymouth",
    "sg:classifiers":[
        {
            "category":"Farming",
            "subcategory":"Dairy Farm",
            "type":"Manufacturing & Wholesale Goods"
        }
    ],
    "sg:postcode":"PL5 4LH",
    "sg:province":"Devon",
    "wof:name":"F A Baker & Son",
    "wof:placetype":"venue"
},
  "geometry": {"coordinates":[-4.151189,50.432095],"type":"Point"}
}