{
  "type": "Feature",
  "properties": {
    "addr:full":"11a Wheatacre Road, Stocksbridge Sheffield South Yorkshire S36 2GB",
    "addr:housenumber":"11a",
    "addr:postcode":"s36 2gb",
    "addr:street":"Wheatacre Road",
    "iso:country":"GB",
    "sg:address":"11a Wheatacre Road, Stocksbridge",
    "sg:city":"Sheffield",
    "sg:classifiers":[
        {
            "category":"Building & Trades",
            "subcategory":"Construction",
            "type":"Services"
        }
    ],
    "sg:phone":"+44 114 288 2859",
    "sg:postcode":"S36 2GB",
    "sg:province":"South Yorkshire",
    "sg:tags":[
        "builder"
    ],
    "wof:name":"Anthony I Rutherford",
    "wof:placetype":"venue"
},
  "geometry": {"coordinates":[-1.588345,53.479198],"type":"Point"}
}