{
  "type": "Feature",
  "properties": {
    "iso:country":"GB",
    "sg:address":"425 Stone Road",
    "sg:city":"Stafford",
    "sg:classifiers":[
        {
            "category":"Building & Trades",
            "subcategory":"Construction",
            "type":"Services"
        }
    ],
    "sg:phone":"+44 1785 242041",
    "sg:postcode":"ST16 1LW",
    "sg:province":"Staffordshire",
    "sg:tags":[
        "decorator",
        "painter"
    ],
    "wof:name":"R & M Bayston",
    "wof:placetype":"venue"
},
  "geometry": {"coordinates":[-2.1308948994,52.8296012878],"type":"Point"}
}