{
  "type": "Feature",
  "properties": {
    "addr:full":"Unit 1, 76a St Marys Road Market Harborough Leicestershire LE16 7DX",
    "addr:housenumber":"unit;76a",
    "addr:postcode":"le16 7dx",
    "addr:street":"St Marys Road",
    "iso:country":"GB",
    "sg:address":"Unit 1, 76a St Marys Road",
    "sg:city":"Market Harborough",
    "sg:classifiers":[
        {
            "category":"Manufacturing",
            "subcategory":"Wood Products",
            "type":"Manufacturing & Wholesale Goods"
        },
        {
            "category":"Home & Garden",
            "subcategory":"Home Furnishings",
            "type":"Retail Goods"
        }
    ],
    "sg:phone":"+44 1858 434343",
    "sg:postcode":"LE16 7DX",
    "sg:province":"Leicestershire",
    "sg:tags":[
        "furnishers",
        "planner",
        "maker",
        "kitchen",
        "cabinet"
    ],
    "wof:name":"Harborough Kitchens & Bedrooms",
    "wof:placetype":"venue"
},
  "geometry": {"coordinates":[-0.9160659909,52.477897644],"type":"Point"}
}