{
  "type": "Feature",
  "properties": {
    "iso:country":"GB",
    "sg:address":"Bank House, 8 High Street, Prestbury",
    "sg:city":"Cheltenham",
    "sg:classifiers":[
        {
            "category":"Banks & Credit Unions",
            "subcategory":"Financial Services",
            "type":"Services"
        }
    ],
    "sg:phone":"+44 1242 520074",
    "sg:postcode":"GL52 3AS",
    "sg:province":"Gloucestershire",
    "sg:tags":[
        "adviser"
    ],
    "wof:name":"Lbi Automotive Ltd.",
    "wof:placetype":"venue"
},
  "geometry": {"coordinates":[-2.044861,51.913429],"type":"Point"}
}