{
  "type": "Feature",
  "properties": {
    "iso:country":"GB",
    "sg:address":"12 Bridgewater Street",
    "sg:city":"Lymm",
    "sg:classifiers":[
        {
            "category":"Professional",
            "subcategory":"Business Services",
            "type":"Services"
        }
    ],
    "sg:phone":"+44 1925 758811",
    "sg:postcode":"WA13 0AB",
    "sg:province":"Cheshire",
    "sg:tags":[
        "planning",
        "supervisor"
    ],
    "wof:name":"Clarke & Associates Ltd.",
    "wof:placetype":"venue"
},
  "geometry": {"coordinates":[-2.4789330959,53.381111145],"type":"Point"}
}