{
  "type": "Feature",
  "properties": {
    "iso:country":"GB",
    "sg:address":"Denby Hall, Lower Denby, Flockton",
    "sg:city":"Wakefield",
    "sg:classifiers":[
        {
            "category":"Farming",
            "subcategory":"Farm",
            "type":"Manufacturing & Wholesale Goods"
        }
    ],
    "sg:phone":"+44 1924 848770",
    "sg:postcode":"WF4 4BJ",
    "sg:province":"West Yorkshire",
    "sg:tags":[
        "mixed",
        "crop"
    ],
    "wof:name":"George Robert Hensby",
    "wof:placetype":"venue"
},
  "geometry": {"coordinates":[-1.635486,53.630836],"type":"Point"}
}