{
  "type": "Feature",
  "properties": {
    "iso:country":"GB",
    "sg:address":"Renshaw Industrial Estate, Mill Mead",
    "sg:city":"Staines",
    "sg:classifiers":[
        {
            "category":"Manufacturing",
            "subcategory":"Chemicals & Compounds",
            "type":"Manufacturing & Wholesale Goods"
        }
    ],
    "sg:phone":"+44 1784 449966",
    "sg:postcode":"TW18 4UZ",
    "sg:province":"Berkshire",
    "wof:name":"Sychem (U K) Ltd.",
    "wof:placetype":"venue"
},
  "geometry": {"coordinates":[-0.506604,51.435162],"type":"Point"}
}