{
  "type": "Feature",
  "properties": {
    "addr:full":"Trinity Ho, School Hill Lewes East Sussex BN7 2NN",
    "addr:postcode":"bn7 2nn",
    "addr:street":"Hill",
    "iso:country":"GB",
    "sg:address":"Trinity Ho, School Hill",
    "sg:city":"Lewes",
    "sg:classifiers":[
        {
            "category":"Banks & Credit Unions",
            "subcategory":"Financial Services",
            "type":"Services"
        }
    ],
    "sg:postcode":"BN7 2NN",
    "sg:province":"East Sussex",
    "sg:tags":[
        "consultant"
    ],
    "wof:name":"Firle Place Preservation Trust Ltd",
    "wof:placetype":"venue"
},
  "geometry": {"coordinates":[0.01062,50.873203],"type":"Point"}
}