{
  "type": "Feature",
  "properties": {
    "iso:country":"GB",
    "sg:address":"27 Newman Street",
    "sg:city":"London",
    "sg:classifiers":[
        {
            "category":"Communications",
            "subcategory":"Film & Video Production",
            "type":"Services"
        }
    ],
    "sg:phone":"+44 20 7323 9466",
    "sg:postcode":"W1T 1PP",
    "sg:province":"Greater London",
    "sg:tags":[
        "tv",
        "studio"
    ],
    "wof:name":"Hot Property Films Ltd.",
    "wof:placetype":"venue"
},
  "geometry": {"coordinates":[-0.1357910037,51.5180282593],"type":"Point"}
}