{
  "type": "Feature",
  "properties": {
    "addr:full":"Burnley Wood Mill, Parliament Street Burnley Lancashire BB11 3JT",
    "addr:postcode":"bb11 3jt",
    "addr:street":"Parliament Street",
    "iso:country":"GB",
    "sg:address":"Burnley Wood Mill, Parliament Street",
    "sg:city":"Burnley",
    "sg:classifiers":[
        {
            "category":"Home & Garden",
            "subcategory":"Home Furnishings",
            "type":"Retail Goods"
        }
    ],
    "sg:phone":"+44 1282 724600",
    "sg:postcode":"BB11 3JT",
    "sg:province":"Lancashire",
    "sg:tags":[
        "furnishers",
        "planner",
        "kitchen"
    ],
    "wof:name":"Red Rose Plastics (Burnley) Ltd.",
    "wof:placetype":"venue"
},
  "geometry": {"coordinates":[-2.243809,53.78801],"type":"Point"}
}