{
  "type": "Feature",
  "properties": {
    "addr:full":"Colchester House, Burn Hall Industrial Estate, Venture Road Fleetwood Lancashire FY7 8RS",
    "addr:postcode":"fy7 8rs",
    "addr:street":"Burn;Industrial Estate Venture Road",
    "iso:country":"GB",
    "sg:address":"Colchester House, Burn Hall Industrial Estate, Venture Road",
    "sg:city":"Fleetwood",
    "sg:classifiers":[
        {
            "category":"Banks & Credit Unions",
            "subcategory":"Financial Services",
            "type":"Services"
        }
    ],
    "sg:phone":"+44 1253 823488",
    "sg:postcode":"FY7 8RS",
    "sg:province":"Lancashire",
    "sg:tags":[
        "claim",
        "assessor"
    ],
    "wof:name":"Accident Loss Assessment Scheme Ltd.",
    "wof:placetype":"venue"
},
  "geometry": {"coordinates":[-3.014669,53.92128],"type":"Point"}
}