{
  "type": "Feature",
  "properties": {
    "addr:full":"Church Farm, Church Lane, Evercreech Shepton Mallet Somerset BA4 6HU",
    "addr:postcode":"ba4 6hu",
    "addr:street":"Church Lane",
    "iso:country":"GB",
    "sg:address":"Church Farm, Church Lane, Evercreech",
    "sg:city":"Shepton Mallet",
    "sg:classifiers":[
        {
            "category":"Farming",
            "subcategory":"Dairy Farm",
            "type":"Manufacturing & Wholesale Goods"
        },
        {
            "category":"Farming",
            "subcategory":"Livestock Farm",
            "type":"Manufacturing & Wholesale Goods"
        }
    ],
    "sg:postcode":"BA4 6HU",
    "sg:province":"Somerset",
    "sg:tags":[
        "others",
        "farmer"
    ],
    "wof:name":"Corp & Jenkins",
    "wof:placetype":"venue"
},
  "geometry": {"coordinates":[-2.505548954,51.1483039856],"type":"Point"}
}