{
  "type": "Feature",
  "properties": {
    "iso:country":"GB",
    "sg:address":"271 Portland Road, South Norwood",
    "sg:city":"London",
    "sg:classifiers":[
        {
            "category":"Autos & Motor Vehicles",
            "subcategory":"Auto Supplies",
            "type":"Retail Goods"
        }
    ],
    "sg:phone":"+44 20 8656 9992",
    "sg:postcode":"SE25 4XB",
    "sg:province":"Greater London",
    "sg:tags":[
        "tyre"
    ],
    "wof:name":"Tyretrax",
    "wof:placetype":"venue"
},
  "geometry": {"coordinates":[-0.0666590035,51.3932914734],"type":"Point"}
}