{
  "type": "Feature",
  "properties": {
    "addr:full":"76a High Street Fareham Hampshire PO16 7AW",
    "addr:housenumber":"76a",
    "addr:postcode":"po16 7aw",
    "addr:street":"High Street",
    "iso:country":"GB",
    "sg:address":"76a High Street",
    "sg:city":"Fareham",
    "sg:classifiers":[
        {
            "category":"Farming",
            "subcategory":"Livestock Farm",
            "type":"Manufacturing & Wholesale Goods"
        },
        {
            "category":"Shopping",
            "subcategory":"Florist",
            "type":"Retail Goods"
        }
    ],
    "sg:phone":"+44 1329 280276",
    "sg:postcode":"PO16 7AW",
    "sg:province":"Hampshire",
    "sg:tags":[
        "breeder"
    ],
    "wof:name":"Joan Kail Florist",
    "wof:placetype":"venue"
},
  "geometry": {"coordinates":[-1.174152,50.852345],"type":"Point"}
}