{
  "type": "Feature",
  "properties": {
    "addr:full":"172 Stoke Newington Church Street London Greater London N16 0JL",
    "addr:housenumber":"172",
    "addr:postcode":"n16 0jl",
    "addr:street":"Stoke Newington Church Street",
    "iso:country":"GB",
    "sg:address":"172 Stoke Newington Church Street",
    "sg:city":"London",
    "sg:classifiers":[
        {
            "category":"Professional",
            "subcategory":"Art Services",
            "type":"Services"
        }
    ],
    "sg:postcode":"N16 0JL",
    "sg:province":"Greater London",
    "sg:tags":[
        "framing"
    ],
    "wof:name":"S'graffiti",
    "wof:placetype":"venue"
},
  "geometry": {"coordinates":[-0.08209,51.561588],"type":"Point"}
}