{
  "type": "Feature",
  "properties": {
    "iso:country":"GB",
    "sg:address":"239 Charlton Road, Charlton Village",
    "sg:city":"Shepperton",
    "sg:classifiers":[
        {
            "category":"Retail",
            "subcategory":"Storage",
            "type":"Services"
        }
    ],
    "sg:phone":"+44 1932 785223",
    "sg:postcode":"TW17 0SH",
    "sg:province":"Surrey",
    "sg:tags":[
        "household",
        "removal"
    ],
    "wof:name":"Thames Valley Removals",
    "wof:placetype":"venue"
},
  "geometry": {"coordinates":[-0.443365,51.414654],"type":"Point"}
}