{
  "type": "Feature",
  "properties": {
    "iso:country":"GB",
    "sg:address":"Carlisle Road, Birkenshaw",
    "sg:city":"Larkhall",
    "sg:classifiers":[
        {
            "category":"Government",
            "subcategory":"City Hall",
            "type":"Public Place"
        },
        {
            "category":"Government",
            "subcategory":"Office",
            "type":"Public Place"
        }
    ],
    "sg:phone":"+44 1698 881127",
    "sg:postcode":"ML9 2TP",
    "sg:province":"South Lanarkshire",
    "sg:tags":[
        "local"
    ],
    "wof:name":"Birkenshaw Hall",
    "wof:placetype":"venue"
},
  "geometry": {"coordinates":[-3.9636490345,55.7222900391],"type":"Point"}
}