{
  "type": "Feature",
  "properties": {
    "iso:country":"GB",
    "sg:address":"59 School Lane",
    "sg:city":"Herne Bay",
    "sg:classifiers":[
        {
            "category":"Shopping",
            "subcategory":"Party Supplies",
            "type":"Retail Goods"
        },
        {
            "category":"Arts & Performance",
            "subcategory":"Music",
            "type":"Entertainment"
        }
    ],
    "sg:phone":"+44 1227 363503",
    "sg:postcode":"CT6 7AR",
    "sg:province":"Kent",
    "sg:tags":[
        "mobile",
        "operator",
        "disco"
    ],
    "wof:name":"Rogers Mobile Discos",
    "wof:placetype":"venue"
},
  "geometry": {"coordinates":[1.136719,51.352062],"type":"Point"}
}