{
  "type": "Feature",
  "properties": {
    "addr:full":"19 Barrie Ct Livingston West Lothian EH54 5NJ",
    "addr:housenumber":"19",
    "addr:postcode":"eh54 5nj",
    "addr:street":"Barrie Ct",
    "iso:country":"GB",
    "sg:address":"19 Barrie Ct",
    "sg:city":"Livingston",
    "sg:classifiers":[
        {
            "category":"Retail",
            "subcategory":"Repair Shop",
            "type":"Services"
        }
    ],
    "sg:phone":"+44 1506 497497",
    "sg:postcode":"EH54 5NJ",
    "sg:province":"West Lothian",
    "sg:tags":[
        "maintenance"
    ],
    "wof:name":"Will Do Multi Trades",
    "wof:placetype":"venue"
},
  "geometry": {"coordinates":[-3.483845,55.897408],"type":"Point"}
}