{
  "type": "Feature",
  "properties": {
    "addr:full":"Maid Street, Haugh Of Urr Castle Douglas Dumfries and Galloway DG7 3YA",
    "addr:postcode":"dg7 3ya",
    "addr:street":"Maid Street",
    "iso:country":"GB",
    "sg:address":"Maid Street, Haugh Of Urr",
    "sg:city":"Castle Douglas",
    "sg:classifiers":[
        {
            "category":"Government",
            "subcategory":"Post Office",
            "type":"Public Place"
        }
    ],
    "sg:phone":"+44 1556 660201",
    "sg:postcode":"DG7 3YA",
    "sg:province":"Dumfries and Galloway",
    "wof:name":"Haugh of Urr Post Office & Stores",
    "wof:placetype":"venue"
},
  "geometry": {"coordinates":[-3.8581190109,54.9755554199],"type":"Point"}
}