{
  "type": "Feature",
  "properties": {
    "iso:country":"GB",
    "sg:address":"8 Northgate, Almondbury",
    "sg:city":"Huddersfield",
    "sg:classifiers":[
        {
            "category":"Government",
            "subcategory":"Office",
            "type":"Public Place"
        }
    ],
    "sg:phone":"+44 1484 223878",
    "sg:postcode":"HD5 8RX",
    "sg:province":"West Yorkshire",
    "sg:tags":[
        "local"
    ],
    "wof:name":"Kirklees Housing Services (Almondbury)",
    "wof:placetype":"venue"
},
  "geometry": {"coordinates":[-1.7435660362,53.6324195862],"type":"Point"}
}