{
  "type": "Feature",
  "properties": {
    "addr:full":"Unit 15, Stanley Wharf Mill, Kirkebrook Road Bolton Lancashire BL3 4JE",
    "addr:housenumber":"unit 15",
    "addr:postcode":"bl3 4je",
    "addr:street":"Stanley Wharf Mill Kirkebrook Road",
    "iso:country":"GB",
    "sg:address":"Unit 15, Stanley Wharf Mill, Kirkebrook Road",
    "sg:city":"Bolton",
    "sg:classifiers":[
        {
            "category":"Manufacturing",
            "subcategory":"Building Materials",
            "type":"Manufacturing & Wholesale Goods"
        }
    ],
    "sg:phone":"+44 1204 656755",
    "sg:postcode":"BL3 4JE",
    "sg:province":"Lancashire",
    "sg:tags":[
        "shutter",
        "supp",
        "door"
    ],
    "wof:name":"A D G Shutters",
    "wof:placetype":"venue"
},
  "geometry": {"coordinates":[-2.4618999958,53.5665588379],"type":"Point"}
}