{
  "type": "Feature",
  "properties": {
    "addr:full":"325 Kingsland Road London Greater London E8 4DL",
    "addr:housenumber":"325",
    "addr:postcode":"e8 4dl",
    "addr:street":"Kingsland Road",
    "iso:country":"GB",
    "sg:address":"325 Kingsland Road",
    "sg:city":"London",
    "sg:classifiers":[
        {
            "category":"Home & Garden",
            "subcategory":"Kitchen Supply",
            "type":"Retail Goods"
        }
    ],
    "sg:phone":"+44 20 7254 3792",
    "sg:postcode":"E8 4DL",
    "sg:province":"Greater London",
    "sg:tags":[
        "equipment",
        "catering"
    ],
    "wof:name":"Trade Price Catering Equipment",
    "wof:placetype":"venue"
},
  "geometry": {"coordinates":[-0.076834,51.538719],"type":"Point"}
}