{
  "type": "Feature",
  "properties": {
    "addr:full":"181 Bank Street Coatbridge North Lanarkshire ML5 1HA",
    "addr:housenumber":"181",
    "addr:postcode":"ml5 1ha",
    "addr:street":"Bank Street",
    "iso:country":"GB",
    "sg:address":"181 Bank Street",
    "sg:city":"Coatbridge",
    "sg:classifiers":[
        {
            "category":"Fast Food",
            "type":"Food & Drink"
        }
    ],
    "sg:phone":"+44 1236 435338",
    "sg:postcode":"ML5 1HA",
    "sg:province":"North Lanarkshire",
    "sg:tags":[
        "away",
        "take"
    ],
    "wof:name":"Wong's Takeaway",
    "wof:placetype":"venue"
},
  "geometry": {"coordinates":[-4.0393848419,55.858921051],"type":"Point"}
}