{
  "type": "Feature",
  "properties": {
    "addr:full":"Unit 9 The Pace Centre, Stephenson Rd Clacton-on-sea Essex CO15 4XA",
    "addr:housenumber":"unit 9 the",
    "addr:postcode":"co15 4xa",
    "addr:street":"Stephenson Rd",
    "iso:country":"GB",
    "sg:address":"Unit 9 The Pace Centre, Stephenson Rd",
    "sg:city":"Clacton-on-sea",
    "sg:classifiers":[
        {
            "category":"Communications",
            "subcategory":"Film & Video Production",
            "type":"Services"
        }
    ],
    "sg:postcode":"CO15 4XA",
    "sg:province":"Essex",
    "sg:tags":[
        "recording",
        "studio"
    ],
    "wof:name":"Cater,Tony,",
    "wof:placetype":"venue"
},
  "geometry": {"coordinates":[1.1532700062,51.8018264771],"type":"Point"}
}