{
  "type": "Feature",
  "properties": {
    "iso:country":"GB",
    "sg:address":"The Lions Den, Manaccan",
    "sg:city":"Helston",
    "sg:classifiers":[
        {
            "category":"Professional",
            "subcategory":"Computer Services",
            "type":"Services"
        }
    ],
    "sg:postcode":"TR12 6HR",
    "sg:province":"Cornwall",
    "sg:tags":[
        "system",
        "software"
    ],
    "wof:name":"Cornwall Rural Oppurtunities Workshop Ltd.",
    "wof:placetype":"venue"
},
  "geometry": {"coordinates":[-5.127954,50.082745],"type":"Point"}
}