{
  "type": "Feature",
  "properties": {
    "addr:full":"8 Davids Road, Whitchurch Bristol City of Bristol BS14 9JJ",
    "addr:housenumber":"8",
    "addr:postcode":"bs14 9jj",
    "addr:street":"Davids Road",
    "iso:country":"GB",
    "sg:address":"8 Davids Road, Whitchurch",
    "sg:city":"Bristol",
    "sg:classifiers":[
        {
            "category":"Building & Trades",
            "subcategory":"Construction",
            "type":"Services"
        }
    ],
    "sg:phone":"+44 1275 837033",
    "sg:postcode":"BS14 9JJ",
    "sg:province":"City of Bristol",
    "sg:tags":[
        "roofing"
    ],
    "wof:name":"J P Roofing",
    "wof:placetype":"venue"
},
  "geometry": {"coordinates":[-2.5578780174,51.4186096191],"type":"Point"}
}