{
  "type": "Feature",
  "properties": {
    "iso:country":"GB",
    "sg:address":"Bungay Road",
    "sg:city":"Beccles",
    "sg:classifiers":[
        {
            "category":"Home & Garden",
            "subcategory":"Home Furnishings",
            "type":"Retail Goods"
        }
    ],
    "sg:phone":"+44 1508 518652",
    "sg:postcode":"NR34 0HG",
    "sg:province":"Norfolk",
    "sg:tags":[
        "homefurnishings"
    ],
    "wof:name":"David Paton Designer Craftsmen",
    "wof:placetype":"venue"
},
  "geometry": {"coordinates":[1.513585,52.4884],"type":"Point"}
}