{
  "type": "Feature",
  "properties": {
    "addr:full":"Woodside Business Park, Bayton Kidderminster Shropshire DY14 9NE",
    "addr:postcode":"dy14 9ne",
    "iso:country":"GB",
    "sg:address":"Woodside Business Park, Bayton",
    "sg:city":"Kidderminster",
    "sg:classifiers":[
        {
            "category":"Autos & Motor Vehicles",
            "subcategory":"Auto Supplies",
            "type":"Retail Goods"
        }
    ],
    "sg:postcode":"DY14 9NE",
    "sg:province":"Shropshire",
    "sg:tags":[
        "caravan",
        "accessory"
    ],
    "wof:name":"Richard T Marshall",
    "wof:placetype":"venue"
},
  "geometry": {"coordinates":[-2.4483289719,52.3563194275],"type":"Point"}
}