{
  "type": "Feature",
  "properties": {
    "iso:country":"GB",
    "sg:address":"Rock Cottage Farm, Tunstall Rd",
    "sg:city":"Sunderland",
    "sg:classifiers":[
        {
            "category":"Museum",
            "subcategory":"Zoo",
            "type":"Entertainment"
        }
    ],
    "sg:phone":"+44 191 528 4186",
    "sg:postcode":"SR3 1AA",
    "sg:province":"Tyne and Wear",
    "sg:tags":[
        "cat"
    ],
    "wof:name":"Anzani Breeding Cattery",
    "wof:placetype":"venue"
},
  "geometry": {"coordinates":[-1.3967200518,54.8859786987],"type":"Point"}
}