{
  "type": "Feature",
  "properties": {
    "addr:full":"26 Eversham Walk, Kingfisher Centre Redditch Warwickshire B97 4EX",
    "addr:housenumber":"26",
    "addr:postcode":"b97 4ex",
    "addr:street":"Eversham Walk",
    "iso:country":"GB",
    "sg:address":"26 Eversham Walk, Kingfisher Centre",
    "sg:city":"Redditch",
    "sg:classifiers":[
        {
            "category":"Shopping",
            "subcategory":"Gifts & Souvenirs",
            "type":"Retail Goods"
        }
    ],
    "sg:phone":"+44 1527 585177",
    "sg:postcode":"B97 4EX",
    "sg:province":"Warwickshire",
    "sg:tags":[
        "poster",
        "card"
    ],
    "wof:name":"Papertree Ltd.",
    "wof:placetype":"venue"
},
  "geometry": {"coordinates":[-1.9462349415,52.2943000793],"type":"Point"}
}