{
  "type": "Feature",
  "properties": {
    "addr:full":"1a Kingsbury Lane Ringwood Dorset BH24 1EL",
    "addr:housenumber":"1a",
    "addr:postcode":"bh24 1el",
    "addr:street":"Kingsbury Lane",
    "iso:country":"GB",
    "sg:address":"1a Kingsbury Lane",
    "sg:city":"Ringwood",
    "sg:classifiers":[
        {
            "category":"Professional",
            "subcategory":"Computer Services",
            "type":"Services"
        }
    ],
    "sg:phone":"+44 1425 480264",
    "sg:postcode":"BH24 1EL",
    "sg:province":"Dorset",
    "sg:tags":[
        "system",
        "software"
    ],
    "wof:name":"Micro Nav (Software) Ltd.",
    "wof:placetype":"venue"
},
  "geometry": {"coordinates":[-1.791339,50.845188],"type":"Point"}
}