{
  "type": "Feature",
  "properties": {
    "addr:full":"157 Aldershot Road, Church Crookham Fleet Hampshire GU52 8JS",
    "addr:housenumber":"157",
    "addr:postcode":"gu52 8js",
    "addr:street":"Aldershot Road",
    "iso:country":"GB",
    "sg:address":"157 Aldershot Road, Church Crookham",
    "sg:city":"Fleet",
    "sg:classifiers":[
        {
            "category":"Personal",
            "subcategory":"Beauty Salon",
            "type":"Services"
        }
    ],
    "sg:postcode":"GU52 8JS",
    "sg:province":"Hampshire",
    "sg:tags":[
        "lady",
        "hairdresser"
    ],
    "wof:name":"Country Hair",
    "wof:placetype":"venue"
},
  "geometry": {"coordinates":[-0.8225960135,51.2771911621],"type":"Point"}
}