{
  "type": "Feature",
  "properties": {
    "iso:country":"GB",
    "sg:address":"23 Templesheen Road",
    "sg:city":"Bognor Regis",
    "sg:classifiers":[
        {
            "category":"Health Services",
            "subcategory":"Health Practitioner",
            "type":"Services"
        }
    ],
    "sg:postcode":"PO22 6JB",
    "sg:province":"West Sussex",
    "sg:tags":[
        "hypnotherapists"
    ],
    "wof:name":"Neil Gibson",
    "wof:placetype":"venue"
},
  "geometry": {"coordinates":[-0.601515,50.792389],"type":"Point"}
}