{
  "type": "Feature",
  "properties": {
    "addr:full":"12 Derby Road, Longridge Preston Lancashire PR3 3NP",
    "addr:housenumber":"12",
    "addr:postcode":"pr3 3np",
    "addr:street":"Derby Road",
    "iso:country":"GB",
    "sg:address":"12 Derby Road, Longridge",
    "sg:city":"Preston",
    "sg:classifiers":[
        {
            "category":"Wholesale",
            "subcategory":"Painting Supplies",
            "type":"Manufacturing & Wholesale Goods"
        },
        {
            "category":"Professional",
            "subcategory":"Art Services",
            "type":"Services"
        }
    ],
    "sg:phone":"+44 1772 782246",
    "sg:postcode":"PR3 3NP",
    "sg:province":"Lancashire",
    "sg:tags":[
        "merchant",
        "supplier",
        "decorating"
    ],
    "wof:name":"T & G Miller",
    "wof:placetype":"venue"
},
  "geometry": {"coordinates":[-2.6070930958,53.8330345154],"type":"Point"}
}