{
  "type": "Feature",
  "properties": {
    "addr:full":"18 Block D, Watermark Way, Foxholes Business Park Hertford Hertfordshire SG13 7TZ",
    "addr:housenumber":"18;d;business",
    "addr:postcode":"sg13 7tz",
    "addr:street":"Block;Watermark Way;Park Hertford",
    "iso:country":"GB",
    "sg:address":"18 Block D, Watermark Way, Foxholes Business Park",
    "sg:city":"Hertford",
    "sg:classifiers":[
        {
            "category":"Shopping",
            "subcategory":"Computers & Home Electronics",
            "type":"Retail Goods"
        }
    ],
    "sg:phone":"+44 1992 501641",
    "sg:postcode":"SG13 7TZ",
    "sg:province":"Hertfordshire",
    "sg:tags":[
        "electrical"
    ],
    "wof:name":"Hager Ltd.",
    "wof:placetype":"venue"
},
  "geometry": {"coordinates":[-0.045925,51.782917],"type":"Point"}
}