{
  "type": "Feature",
  "properties": {
    "iso:country":"GB",
    "sg:address":"Ropergate House, Ropergate",
    "sg:city":"Pontefract",
    "sg:classifiers":[
        {
            "category":"Professional",
            "subcategory":"Lawyer & Legal Services",
            "type":"Services"
        }
    ],
    "sg:phone":"+44 1977 703321",
    "sg:postcode":"WF8 1LB",
    "sg:province":"North Yorkshire",
    "sg:tags":[
        "solicitor"
    ],
    "wof:name":"Clayton Smith W E & Son",
    "wof:placetype":"venue"
},
  "geometry": {"coordinates":[-1.3129630089,53.6902198792],"type":"Point"}
}