{
  "type": "Feature",
  "properties": {
    "addr:full":"71 High Street Canvey Island Essex SS8 7RD",
    "addr:housenumber":"71",
    "addr:postcode":"ss8 7rd",
    "addr:street":"High Street",
    "iso:country":"GB",
    "sg:address":"71 High Street",
    "sg:city":"Canvey Island",
    "sg:classifiers":[
        {
            "category":"Retail",
            "subcategory":"Funeral Services",
            "type":"Services"
        }
    ],
    "sg:phone":"+44 1268 683177",
    "sg:postcode":"SS8 7RD",
    "sg:province":"Essex",
    "wof:name":"W Thorp & Son",
    "wof:placetype":"venue"
},
  "geometry": {"coordinates":[0.596858,51.522858],"type":"Point"}
}