{
  "type": "Feature",
  "properties": {
    "addr:full":"The Loft, 77 Montgomery St Edinburgh City of Edinburgh EH7 5HZ",
    "addr:housenumber":"77",
    "addr:postcode":"eh7 5hz",
    "addr:street":"Montgomery St Edinburgh",
    "iso:country":"GB",
    "sg:address":"The Loft, 77 Montgomery St",
    "sg:city":"Edinburgh",
    "sg:classifiers":[
        {
            "category":"Retail",
            "subcategory":"Event Space",
            "type":"Services"
        }
    ],
    "sg:phone":"+44 131 556 6482",
    "sg:postcode":"EH7 5HZ",
    "sg:province":"City of Edinburgh",
    "sg:tags":[
        "exhibition",
        "organiser"
    ],
    "wof:name":"V J McLellan",
    "wof:placetype":"venue"
},
  "geometry": {"coordinates":[-3.173801899,55.9573478699],"type":"Point"}
}