{
  "type": "Feature",
  "properties": {
    "iso:country":"GB",
    "sg:address":"409 Poulton Road",
    "sg:city":"Fleetwood",
    "sg:classifiers":[
        {
            "category":"Health Services",
            "subcategory":"Nursing And Care Facility",
            "type":"Services"
        }
    ],
    "sg:phone":"+44 1253 776073",
    "sg:postcode":"FY7 7JY",
    "sg:province":"Lancashire",
    "sg:tags":[
        "home"
    ],
    "wof:name":"Guys Court",
    "wof:placetype":"venue"
},
  "geometry": {"coordinates":[-3.033201,53.918526],"type":"Point"}
}