{
  "type": "Feature",
  "properties": {
    "iso:country":"GB",
    "sg:address":"20 Western Approach",
    "sg:city":"Plymouth",
    "sg:classifiers":[
        {
            "category":"Real Estate",
            "subcategory":"Surveying",
            "type":"Services"
        }
    ],
    "sg:phone":"+44 1752 663341",
    "sg:postcode":"PL1 1TG",
    "sg:province":"Devon",
    "sg:tags":[
        "surveyor",
        "valuer"
    ],
    "sg:website":"http://www.shobrook.co.uk",
    "wof:name":"G S Shobrook & Co.",
    "wof:placetype":"venue"
},
  "geometry": {"coordinates":[-4.1482810974,50.3706893921],"type":"Point"}
}