{
  "type": "Feature",
  "properties": {
    "addr:full":"New Enterprise House, 149-151 High Road, Chadwell Heath Romford Essex RM6 6PJ",
    "addr:housenumber":"149-151",
    "addr:postcode":"rm6 6pj",
    "addr:street":"High Road",
    "iso:country":"GB",
    "sg:address":"New Enterprise House, 149-151 High Road, Chadwell Heath",
    "sg:city":"Romford",
    "sg:classifiers":[
        {
            "category":"Freight",
            "type":"Transportation"
        }
    ],
    "sg:phone":"+44 20 8983 8282",
    "sg:postcode":"RM6 6PJ",
    "sg:province":"Essex",
    "sg:tags":[
        "shipping"
    ],
    "wof:name":"Pakistan National Shipping Corporation",
    "wof:placetype":"venue"
},
  "geometry": {"coordinates":[0.1366599947,51.5720481873],"type":"Point"}
}