{
  "type": "Feature",
  "properties": {
    "iso:country":"GB",
    "sg:address":"2 Regency Mews, Off High St",
    "sg:city":"Northallerton",
    "sg:classifiers":[
        {
            "category":"Military Area",
            "subcategory":"Air Force Base",
            "type":"Public Place"
        }
    ],
    "sg:phone":"+44 1609 777766",
    "sg:postcode":"DL7 8PE",
    "sg:province":"North Yorkshire",
    "sg:tags":[
        "taxi",
        "hire",
        "private"
    ],
    "wof:name":"Apollo Taxis",
    "wof:placetype":"venue"
},
  "geometry": {"coordinates":[-1.43356,54.337219],"type":"Point"}
}