{
  "type": "Feature",
  "properties": {
    "iso:country":"GB",
    "sg:address":"Charles House, 328 Low Lane, Horsforth",
    "sg:city":"Leeds",
    "sg:classifiers":[
        {
            "category":"Insurance",
            "subcategory":"Insurance Agent",
            "type":"Services"
        }
    ],
    "sg:phone":"+44 113 258 5891",
    "sg:postcode":"LS18 5DE",
    "sg:province":"West Yorkshire",
    "wof:name":"Avon Insurance Plc",
    "wof:placetype":"venue"
},
  "geometry": {"coordinates":[-1.62058,53.838383],"type":"Point"}
}