{
  "type": "Feature",
  "properties": {
    "addr:full":"12 Rossmore Rd Camden Greater London NW1 6NJ",
    "addr:housenumber":"12",
    "addr:postcode":"nw1 6nj",
    "addr:street":"Rossmore Rd",
    "iso:country":"GB",
    "sg:address":"12 Rossmore Rd",
    "sg:city":"Camden",
    "sg:classifiers":[
        {
            "category":"Community Center",
            "subcategory":"Youth",
            "type":"Public Place"
        }
    ],
    "sg:phone":"+44 20 7723 8308",
    "sg:postcode":"NW1 6NJ",
    "sg:province":"Greater London",
    "sg:tags":[
        "organisation",
        "centre"
    ],
    "wof:name":"Fourth Feathers The",
    "wof:placetype":"venue"
},
  "geometry": {"coordinates":[-0.164676,51.52491],"type":"Point"}
}