{
  "type": "Feature",
  "properties": {
    "iso:country":"GB",
    "sg:address":"3 Station Road",
    "sg:city":"Ilkley",
    "sg:classifiers":[
        {
            "category":"Shopping",
            "subcategory":"Clothing, Apparel, & Fashions",
            "type":"Retail Goods"
        }
    ],
    "sg:phone":"+44 1943 600091",
    "sg:postcode":"LS29 8HA",
    "sg:province":"North Yorkshire",
    "sg:tags":[
        "shop"
    ],
    "wof:name":"Style",
    "wof:placetype":"venue"
},
  "geometry": {"coordinates":[-1.731839,53.890553],"type":"Point"}
}