{
  "type": "Feature",
  "properties": {
    "iso:country":"GB",
    "sg:address":"Cloth Hall Ct, Infirmary St",
    "sg:city":"Leeds",
    "sg:classifiers":[
        {
            "category":"Professional",
            "subcategory":"Business Services",
            "type":"Services"
        }
    ],
    "sg:postcode":"LS1 2JB",
    "sg:province":"West Yorkshire",
    "sg:tags":[
        "holding"
    ],
    "wof:name":"Camrass,S,& Sons (Holdings) Ltd",
    "wof:placetype":"venue"
},
  "geometry": {"coordinates":[-1.548653,53.797508],"type":"Point"}
}