{
  "type": "Feature",
  "properties": {
    "iso:country":"GB",
    "sg:address":"188-190 New North Road",
    "sg:city":"London",
    "sg:classifiers":[
        {
            "category":"Bars & Pubs",
            "type":"Food & Drink"
        },
        {
            "category":"Community Center",
            "subcategory":"Social",
            "type":"Public Place"
        }
    ],
    "sg:postcode":"N1 7BJ",
    "sg:province":"Greater London",
    "sg:tags":[
        "pubs",
        "house",
        "inn",
        "activity"
    ],
    "wof:name":"The Puzzle Pub Co.",
    "wof:placetype":"venue"
},
  "geometry": {"coordinates":[-0.09114,51.53754],"type":"Point"}
}