{
  "type": "Feature",
  "properties": {
    "iso:country":"GB",
    "sg:address":"37 Upton La, Forest Gate",
    "sg:city":"Forest Gate",
    "sg:classifiers":[
        {
            "category":"Retail",
            "subcategory":"Funeral Services",
            "type":"Services"
        }
    ],
    "sg:phone":"+44 20 8472 3062",
    "sg:postcode":"E7 9PA",
    "sg:province":"Greater London",
    "wof:name":"Hindu Funeral Service",
    "wof:placetype":"venue"
},
  "geometry": {"coordinates":[0.026198,51.544796],"type":"Point"}
}