{
  "type": "Feature",
  "properties": {
    "addr:full":"9 High Street, Strathmiglo Cupar Fife KY14 7QA",
    "addr:housenumber":"9",
    "addr:postcode":"ky14 7qa",
    "addr:street":"High Street",
    "iso:country":"GB",
    "sg:address":"9 High Street, Strathmiglo",
    "sg:city":"Cupar",
    "sg:classifiers":[
        {
            "category":"Retail",
            "subcategory":"Auto Repair",
            "type":"Services"
        }
    ],
    "sg:phone":"+44 1337 860255",
    "sg:postcode":"KY14 7QA",
    "sg:province":"Fife",
    "sg:tags":[
        "modification",
        "garage",
        "related"
    ],
    "wof:name":"Strath Garage",
    "wof:placetype":"venue"
},
  "geometry": {"coordinates":[-3.2317419052,56.2919464111],"type":"Point"}
}