{
  "type": "Feature",
  "properties": {
    "addr:full":"83 Cantelupe Road Bexhill-on-sea East Sussex TN40 1PP",
    "addr:housenumber":"83",
    "addr:postcode":"tn40 1pp",
    "addr:street":"Cantelupe Road",
    "iso:country":"GB",
    "sg:address":"83 Cantelupe Road",
    "sg:city":"Bexhill-on-sea",
    "sg:classifiers":[
        {
            "category":"Social Services",
            "subcategory":"Retirement Home",
            "type":"Services"
        }
    ],
    "sg:postcode":"TN40 1PP",
    "sg:province":"East Sussex",
    "sg:tags":[
        "residential",
        "care"
    ],
    "wof:name":"Ashlodge Rest Home",
    "wof:placetype":"venue"
},
  "geometry": {"coordinates":[0.4864340127,50.8411598206],"type":"Point"}
}