{
  "type": "Feature",
  "properties": {
    "addr:full":"1a Bowrons Avenue Wembley Greater London HA0 4QS",
    "addr:housenumber":"1a",
    "addr:postcode":"ha0 4qs",
    "addr:street":"Bowrons Avenue",
    "iso:country":"GB",
    "sg:address":"1a Bowrons Avenue",
    "sg:city":"Wembley",
    "sg:classifiers":[
        {
            "category":"Manufacturing",
            "subcategory":"Tools & Machinery",
            "type":"Manufacturing & Wholesale Goods"
        },
        {
            "category":"Insurance",
            "subcategory":"Insurance Agent",
            "type":"Services"
        }
    ],
    "sg:phone":"+44 20 8900 0538",
    "sg:postcode":"HA0 4QS",
    "sg:province":"Greater London",
    "sg:tags":[
        "society",
        "friendly"
    ],
    "wof:name":"Arbil Agencies Ltd",
    "wof:placetype":"venue"
},
  "geometry": {"coordinates":[-0.2975940108,51.5448760986],"type":"Point"}
}