{
  "type": "Feature",
  "properties": {
    "iso:country":"GB",
    "sg:address":"60/62",
    "sg:city":"London",
    "sg:classifiers":[
        {
            "category":"Organizations",
            "subcategory":"Membership Organization",
            "type":"Services"
        }
    ],
    "sg:postcode":"KT2 6QA",
    "sg:province":"Greater London",
    "sg:tags":[
        "club"
    ],
    "wof:name":"St. Ann's Hill Management Company Limite",
    "wof:placetype":"venue"
},
  "geometry": {"coordinates":[-0.2979510128,51.4105529785],"type":"Point"}
}