{
  "type": "Feature",
  "properties": {
    "iso:country":"GB",
    "sg:address":"Victoria Road, Fenton",
    "sg:city":"Stoke-on-trent",
    "sg:classifiers":[
        {
            "category":"Home & Garden",
            "subcategory":"Home Furnishings",
            "type":"Retail Goods"
        },
        {
            "category":"Home & Garden",
            "subcategory":"Hardware",
            "type":"Retail Goods"
        }
    ],
    "sg:phone":"+44 1782 746028",
    "sg:postcode":"ST4 2HX",
    "sg:province":"Staffordshire",
    "sg:tags":[
        "merchant",
        "paint",
        "diy",
        "decorators'"
    ],
    "wof:name":"Dulux Decorator Centre",
    "wof:placetype":"venue"
},
  "geometry": {"coordinates":[-2.1630539894,53.0044288635],"type":"Point"}
}