{
  "type": "Feature",
  "properties": {
    "iso:country":"GB",
    "sg:address":"38 Church Street",
    "sg:city":"Cromer",
    "sg:classifiers":[
        {
            "category":"Shopping",
            "subcategory":"Comic Books",
            "type":"Retail Goods"
        }
    ],
    "sg:phone":"+44 1263 512379",
    "sg:postcode":"NR27 9ES",
    "sg:province":"Norfolk",
    "sg:tags":[
        "jeweller"
    ],
    "wof:name":"Brigg's Jewellers",
    "wof:placetype":"venue"
},
  "geometry": {"coordinates":[1.301672,52.931],"type":"Point"}
}