{
  "type": "Feature",
  "properties": {
    "addr:full":"46 Mildred Avenue Watford Hertfordshire WD18 7DZ",
    "addr:housenumber":"46",
    "addr:postcode":"wd18 7dz",
    "addr:street":"Mildred Avenue",
    "iso:country":"GB",
    "sg:address":"46 Mildred Avenue",
    "sg:city":"Watford",
    "sg:classifiers":[
        {
            "category":"Health Services",
            "subcategory":"Health Practitioner",
            "type":"Services"
        }
    ],
    "sg:phone":"+44 1923 249239",
    "sg:postcode":"WD18 7DZ",
    "sg:province":"Hertfordshire",
    "sg:tags":[
        "acupuncture"
    ],
    "wof:name":"Acupuncture Centre",
    "wof:placetype":"venue"
},
  "geometry": {"coordinates":[-0.409295,51.655285],"type":"Point"}
}