{
  "type": "Feature",
  "properties": {
    "addr:full":"Station Rd Cardiff Cardiff CF4 5UX",
    "addr:postcode":"cf4 5ux",
    "addr:street":"Station Rd",
    "iso:country":"GB",
    "sg:address":"Station Rd",
    "sg:city":"Cardiff",
    "sg:classifiers":[
        {
            "category":"Place Of Worship",
            "type":"Public Place"
        }
    ],
    "sg:phone":"+44 29 2075 2545",
    "sg:postcode":"CF4 5UX",
    "sg:province":"Cardiff",
    "wof:name":"St Isan (Llanishen) Church",
    "wof:placetype":"venue"
},
  "geometry": {"coordinates":[-3.1713469028,51.4829597473],"type":"Point"}
}