{
  "type": "Feature",
  "properties": {
    "iso:country":"GB",
    "sg:address":"Plymouth Road",
    "sg:city":"South Brent",
    "sg:classifiers":[
        {
            "category":"Bars & Pubs",
            "type":"Food & Drink"
        }
    ],
    "sg:postcode":"TQ10 9BH",
    "sg:province":"Devon",
    "sg:tags":[
        "pubs",
        "inn"
    ],
    "wof:name":"The Pack Horse",
    "wof:placetype":"venue"
},
  "geometry": {"coordinates":[-3.833807,50.425526],"type":"Point"}
}