{
  "type": "Feature",
  "properties": {
    "iso:country":"GB",
    "sg:address":"Kelly Street",
    "sg:city":"Greenock",
    "sg:classifiers":[
        {
            "category":"Place Of Worship",
            "type":"Public Place"
        },
        {
            "category":"Organizations",
            "subcategory":"Non-profit Organization",
            "type":"Services"
        }
    ],
    "sg:phone":"+44 1475 787177",
    "sg:postcode":"PA16 8TR",
    "sg:province":"Inverclyde",
    "sg:tags":[
        "charitable",
        "organisation",
        "charity"
    ],
    "wof:name":"ELIM PENTECOSTAL CHURCH",
    "wof:placetype":"venue"
},
  "geometry": {"coordinates":[-4.764814,55.952271],"type":"Point"}
}