{
  "type": "Feature",
  "properties": {
    "iso:country":"GB",
    "sg:address":"Troedrhiwrhwch, Bangor Teifi",
    "sg:city":"Llandysul",
    "sg:classifiers":[
        {
            "category":"Farming",
            "subcategory":"Dairy Farm",
            "type":"Manufacturing & Wholesale Goods"
        }
    ],
    "sg:phone":"+44 1559 363206",
    "sg:postcode":"SA44 5BS",
    "sg:province":"Carmarthenshire",
    "wof:name":"A M & E W Griffiths",
    "wof:placetype":"venue"
},
  "geometry": {"coordinates":[-4.3608961105,52.0357627869],"type":"Point"}
}