{
  "type": "Feature",
  "properties": {
    "addr:full":"8 Stapledon Lane, Ashburton Newton Abbot Devon TQ13 7AE",
    "addr:housenumber":"8",
    "addr:postcode":"tq13 7ae",
    "addr:street":"Stapledon Lane",
    "iso:country":"GB",
    "sg:address":"8 Stapledon Lane, Ashburton",
    "sg:city":"Newton Abbot",
    "sg:classifiers":[
        {
            "category":"Autos & Motor Vehicles",
            "subcategory":"Boat Sales",
            "type":"Retail Goods"
        }
    ],
    "sg:postcode":"TQ13 7AE",
    "sg:province":"Devon",
    "sg:tags":[
        "surveyor",
        "yacht"
    ],
    "wof:name":"Robin Feloy",
    "wof:placetype":"venue"
},
  "geometry": {"coordinates":[-3.755687,50.516163],"type":"Point"}
}