{
  "type": "Feature",
  "properties": {
    "addr:full":"67 Peach Street Wokingham Berkshire RG40 1XP",
    "addr:housenumber":"67",
    "addr:postcode":"rg40 1xp",
    "addr:street":"Peach Street",
    "iso:country":"GB",
    "sg:address":"67 Peach Street",
    "sg:city":"Wokingham",
    "sg:classifiers":[
        {
            "category":"Restaurant",
            "type":"Food & Drink"
        }
    ],
    "sg:phone":"+44 118 978 5679",
    "sg:postcode":"RG40 1XP",
    "sg:province":"Berkshire",
    "sg:tags":[
        "italian"
    ],
    "wof:name":"Sorrento's",
    "wof:placetype":"venue"
},
  "geometry": {"coordinates":[-0.829951,51.411205],"type":"Point"}
}