{
  "type": "Feature",
  "properties": {
    "addr:full":"6 Higher Ridgeway Ottery St Mary Devon EX11 1TH",
    "addr:housenumber":"6",
    "addr:postcode":"ex11 1th",
    "addr:street":"Higher Ridgeway",
    "iso:country":"GB",
    "sg:address":"6 Higher Ridgeway",
    "sg:city":"Ottery St Mary",
    "sg:classifiers":[
        {
            "category":"Shopping",
            "type":"Retail Goods"
        }
    ],
    "sg:phone":"+44 1404 812932",
    "sg:postcode":"EX11 1TH",
    "sg:province":"Devon",
    "sg:tags":[
        "med",
        "scientific",
        "apparatus"
    ],
    "wof:name":"G L Instruments",
    "wof:placetype":"venue"
},
  "geometry": {"coordinates":[-3.283026,50.751137],"type":"Point"}
}