{
  "type": "Feature",
  "properties": {
    "addr:full":"Derw Mill North, Pentre-cwrt Llandysul Carmarthenshire SA44 5DB",
    "addr:postcode":"sa44 5db",
    "addr:street":"Derw;North;Llandysul",
    "iso:country":"GB",
    "sg:address":"Derw Mill North, Pentre-cwrt",
    "sg:city":"Llandysul",
    "sg:classifiers":[
        {
            "category":"Communications",
            "type":"Services"
        }
    ],
    "sg:phone":"+44 1559 363190",
    "sg:postcode":"SA44 5DB",
    "sg:province":"Carmarthenshire",
    "sg:tags":[
        "audio-visual"
    ],
    "wof:name":"Kdg Mediatech",
    "wof:placetype":"venue"
},
  "geometry": {"coordinates":[-4.3551030159,52.024017334],"type":"Point"}
}