{
  "type": "Feature",
  "properties": {
    "iso:country":"GB",
    "sg:address":"The Glass House, Glassford Street",
    "sg:city":"Glasgow",
    "sg:classifiers":[
        {
            "category":"Professional",
            "subcategory":"Business Services",
            "type":"Services"
        }
    ],
    "sg:phone":"+44 141 553 1788",
    "sg:postcode":"G1 1UL",
    "sg:province":"Glasgow City",
    "sg:tags":[
        "fashion",
        "agent"
    ],
    "wof:name":"The Designer Room Ltd.",
    "wof:placetype":"venue"
},
  "geometry": {"coordinates":[-4.2486391068,55.8595466614],"type":"Point"}
}