{
  "type": "Feature",
  "properties": {
    "iso:country":"GB",
    "sg:address":"Main Road, Terrington St John",
    "sg:city":"Wisbech",
    "sg:classifiers":[
        {
            "category":"Retail",
            "subcategory":"Auto Repair",
            "type":"Services"
        }
    ],
    "sg:phone":"+44 1945 881292",
    "sg:postcode":"PE14 7RR",
    "sg:province":"Cambridgeshire",
    "sg:tags":[
        "modification",
        "garage",
        "related"
    ],
    "wof:name":"A J's Garage",
    "wof:placetype":"venue"
},
  "geometry": {"coordinates":[0.260452,52.705238],"type":"Point"}
}