{
  "type": "Feature",
  "properties": {
    "iso:country":"GB",
    "sg:address":"6-10 Titchfield Street",
    "sg:city":"Kilmarnock",
    "sg:classifiers":[
        {
            "category":"Restaurant",
            "type":"Food & Drink"
        }
    ],
    "sg:postcode":"KA1 1PH",
    "sg:province":"East Ayrshire",
    "wof:name":"Pollyanna's",
    "wof:placetype":"venue"
},
  "geometry": {"coordinates":[-4.497038,55.606575],"type":"Point"}
}