{
  "type": "Feature",
  "properties": {
    "addr:full":"The Storage Premises, 42 Monk Street Derby Derbyshire DE22 3QB",
    "addr:housenumber":"42",
    "addr:postcode":"de22 3qb",
    "addr:street":"Monk Street",
    "iso:country":"GB",
    "sg:address":"The Storage Premises, 42 Monk Street",
    "sg:city":"Derby",
    "sg:classifiers":[
        {
            "category":"Building & Trades",
            "subcategory":"Construction",
            "type":"Services"
        }
    ],
    "sg:postcode":"DE22 3QB",
    "sg:province":"Derbyshire",
    "sg:tags":[
        "platform",
        "work",
        "scaffolding"
    ],
    "wof:name":"A B C Scaffolding",
    "wof:placetype":"venue"
},
  "geometry": {"coordinates":[-1.4836200476,52.9205207825],"type":"Point"}
}