{
  "type": "Feature",
  "properties": {
    "iso:country":"GB",
    "sg:address":"56 Ledmore Drive",
    "sg:city":"Glasgow",
    "sg:classifiers":[
        {
            "category":"Education",
            "subcategory":"School",
            "type":"Public Place"
        },
        {
            "category":"Government",
            "subcategory":"Office",
            "type":"Public Place"
        }
    ],
    "sg:phone":"+44 141 944 0340",
    "sg:postcode":"G15 7AQ",
    "sg:province":"Glasgow City",
    "sg:tags":[
        "local",
        "authority"
    ],
    "wof:name":"Langfaulds Primary School",
    "wof:placetype":"venue"
},
  "geometry": {"coordinates":[-4.371127,55.914497],"type":"Point"}
}