{
  "type": "Feature",
  "properties": {
    "iso:country":"GB",
    "sg:address":"52 Terminus Rd",
    "sg:city":"Eastbourne",
    "sg:classifiers":[
        {
            "category":"Communications",
            "type":"Services"
        }
    ],
    "sg:phone":"+44 1483 306306",
    "sg:postcode":"BN21 3LX",
    "sg:province":"East Sussex",
    "sg:tags":[
        "broadcasting"
    ],
    "wof:name":"BBC Southern Counties Radio",
    "wof:placetype":"venue"
},
  "geometry": {"coordinates":[0.281776,50.768768],"type":"Point"}
}