{
  "type": "Feature",
  "properties": {
    "addr:full":"Finstall Road, Finstall Bromsgrove Worcestershire B60 3DH",
    "addr:postcode":"b60 3dh",
    "addr:street":"Finstall Road",
    "iso:country":"GB",
    "sg:address":"Finstall Road, Finstall",
    "sg:city":"Bromsgrove",
    "sg:classifiers":[
        {
            "category":"Arena",
            "subcategory":"Sports Club",
            "type":"Entertainment"
        }
    ],
    "sg:phone":"+44 1527 874690",
    "sg:postcode":"B60 3DH",
    "sg:province":"Worcestershire",
    "wof:name":"Bromsgrove Rugby Football Club",
    "wof:placetype":"venue"
},
  "geometry": {"coordinates":[-2.039406,52.326912],"type":"Point"}
}