{
  "type": "Feature",
  "properties": {
    "iso:country":"GB",
    "sg:address":"Unit 32, Snedshill Industrial Estate, Snedshill",
    "sg:city":"Telford",
    "sg:classifiers":[
        {
            "category":"Home & Garden",
            "subcategory":"Building Materials",
            "type":"Retail Goods"
        }
    ],
    "sg:postcode":"TF2 9NH",
    "sg:province":"Shropshire",
    "sg:tags":[
        "window",
        "frame"
    ],
    "wof:name":"Window Warehouse",
    "wof:placetype":"venue"
},
  "geometry": {"coordinates":[-2.44074,52.686684],"type":"Point"}
}