{
  "type": "Feature",
  "properties": {
    "addr:full":"171 Haymoor Road Poole Dorset BH15 3NT",
    "addr:housenumber":"171",
    "addr:postcode":"bh15 3nt",
    "addr:street":"Haymoor Road",
    "iso:country":"GB",
    "sg:address":"171 Haymoor Road",
    "sg:city":"Poole",
    "sg:classifiers":[
        {
            "category":"Building & Trades",
            "subcategory":"Construction",
            "type":"Services"
        }
    ],
    "sg:postcode":"BH15 3NT",
    "sg:province":"Dorset",
    "sg:tags":[
        "roofing"
    ],
    "wof:name":"Bob Terrell Roofing",
    "wof:placetype":"venue"
},
  "geometry": {"coordinates":[-1.9553489685,50.7359657288],"type":"Point"}
}