{
  "type": "Feature",
  "properties": {
    "addr:full":"Mead Lane Hertford Hertfordshire SG13 7AU",
    "addr:postcode":"sg13 7au",
    "addr:street":"Mead Lane",
    "iso:country":"GB",
    "sg:address":"Mead Lane",
    "sg:city":"Hertford",
    "sg:classifiers":[
        {
            "category":"Building & Trades",
            "subcategory":"Construction",
            "type":"Services"
        }
    ],
    "sg:phone":"+44 1992 587778",
    "sg:postcode":"SG13 7AU",
    "sg:province":"Hertfordshire",
    "sg:tags":[
        "roofing"
    ],
    "wof:name":"Marley Floors & Waterproofing",
    "wof:placetype":"venue"
},
  "geometry": {"coordinates":[-0.061766,51.801926],"type":"Point"}
}