{
  "type": "Feature",
  "properties": {
    "iso:country":"GB",
    "sg:address":"86 Church Street",
    "sg:city":"Guisborough",
    "sg:classifiers":[
        {
            "category":"Professional",
            "type":"Services"
        },
        {
            "category":"Arts & Performance",
            "subcategory":"Music",
            "type":"Entertainment"
        }
    ],
    "sg:postcode":"TS14 6BX",
    "sg:province":"North Yorkshire",
    "sg:tags":[
        "mobile",
        "entertainer",
        "disco"
    ],
    "wof:name":"Ace Disco",
    "wof:placetype":"venue"
},
  "geometry": {"coordinates":[-1.0492349863,54.5373191833],"type":"Point"}
}