{
  "type": "Feature",
  "properties": {
    "addr:full":"3 Robins Ln Newport Newport NP20 1EZ",
    "addr:housenumber":"3",
    "addr:postcode":"np20 1ez",
    "addr:street":"Robins Ln",
    "iso:country":"GB",
    "sg:address":"3 Robins Ln",
    "sg:city":"Newport",
    "sg:classifiers":[
        {
            "category":"Manufacturing",
            "subcategory":"Furniture",
            "type":"Manufacturing & Wholesale Goods"
        }
    ],
    "sg:phone":"+44 1633 255580",
    "sg:postcode":"NP20 1EZ",
    "sg:province":"Newport",
    "sg:tags":[
        "polishing",
        "french"
    ],
    "wof:name":"Stephen Evans",
    "wof:placetype":"venue"
},
  "geometry": {"coordinates":[-2.9911520481,51.5825538635],"type":"Point"}
}