{
  "type": "Feature",
  "properties": {
    "addr:full":"Scheibler House, Westcarr Road Retford Nottinghamshire DN22 7ZE",
    "addr:postcode":"dn22 7ze",
    "addr:street":"Westcarr Road",
    "iso:country":"GB",
    "sg:address":"Scheibler House, Westcarr Road",
    "sg:city":"Retford",
    "sg:classifiers":[
        {
            "category":"Bus Stop",
            "subcategory":"None",
            "type":"Transportation"
        }
    ],
    "sg:phone":"+44 1777 702355",
    "sg:postcode":"DN22 7ZE",
    "sg:province":"Nottinghamshire",
    "sg:tags":[
        "filter"
    ],
    "wof:name":"Larox Uk Ltd.",
    "wof:placetype":"venue"
},
  "geometry": {"coordinates":[-0.9532539845,53.3216934204],"type":"Point"}
}