{
  "type": "Feature",
  "properties": {
    "addr:full":"408 Corporation Road Newport Newport NP19 0GA",
    "addr:housenumber":"408",
    "addr:postcode":"np19 0ga",
    "addr:street":"Corporation Road",
    "iso:country":"GB",
    "sg:address":"408 Corporation Road",
    "sg:city":"Newport",
    "sg:classifiers":[
        {
            "category":"Shopping",
            "subcategory":"Discount & Variety Stores",
            "type":"Retail Goods"
        }
    ],
    "sg:phone":"+44 1633 216673",
    "sg:postcode":"NP19 0GA",
    "sg:province":"Newport",
    "sg:tags":[
        "cleaning",
        "supply"
    ],
    "wof:name":"Thomas & Strong Ltd.",
    "wof:placetype":"venue"
},
  "geometry": {"coordinates":[-2.974497,51.582531],"type":"Point"}
}