{
  "type": "Feature",
  "properties": {
    "addr:full":"Honiton Rd Exeter Devon EX1 3RS",
    "addr:postcode":"ex1 3rs",
    "addr:street":"Honiton Rd",
    "iso:country":"GB",
    "sg:address":"Honiton Rd",
    "sg:city":"Exeter",
    "sg:classifiers":[
        {
            "category":"Retail",
            "subcategory":"Auto Repair",
            "type":"Services"
        }
    ],
    "sg:phone":"+44 1392 203801",
    "sg:postcode":"EX1 3RS",
    "sg:province":"Devon",
    "sg:tags":[
        "modification",
        "garage"
    ],
    "wof:name":"Sewards Ltd",
    "wof:placetype":"venue"
},
  "geometry": {"coordinates":[-3.4620890617,50.7289848328],"type":"Point"}
}