{
  "type": "Feature",
  "properties": {
    "iso:country":"GB",
    "sg:address":"Unit 5, Market Industrial Estate",
    "sg:city":"Bristol",
    "sg:classifiers":[
        {
            "category":"Professional",
            "type":"Services"
        }
    ],
    "sg:postcode":"BS49 4RF",
    "sg:province":"Somerset",
    "sg:tags":[
        "control",
        "system"
    ],
    "wof:name":"T E S A (Western) Ltd.",
    "wof:placetype":"venue"
},
  "geometry": {"coordinates":[-2.82561,51.39233],"type":"Point"}
}