{
  "type": "Feature",
  "properties": {
    "addr:full":"45 Sopers Lane, Broadstone Poole Dorset BH17 7EW",
    "addr:housenumber":"45",
    "addr:postcode":"bh17 7ew",
    "addr:street":"Sopers Lane",
    "iso:country":"GB",
    "sg:address":"45 Sopers Lane, Broadstone",
    "sg:city":"Poole",
    "sg:classifiers":[
        {
            "category":"Building & Trades",
            "subcategory":"Plumbing",
            "type":"Services"
        }
    ],
    "sg:postcode":"BH17 7EW",
    "sg:province":"Dorset",
    "sg:tags":[
        "drain",
        "clearance",
        "sewer"
    ],
    "wof:name":"Libra Drain Maintenance",
    "wof:placetype":"venue"
},
  "geometry": {"coordinates":[-1.988634,50.746796],"type":"Point"}
}