{
  "type": "Feature",
  "properties": {
    "addr:full":"Unit 5, Bridle Close Kingston-upon-thames Greater London KT1 2JW",
    "addr:housenumber":"unit 5",
    "addr:postcode":"kt1 2jw",
    "addr:street":"Bridle Close",
    "iso:country":"GB",
    "sg:address":"Unit 5, Bridle Close",
    "sg:city":"Kingston-upon-thames",
    "sg:classifiers":[
        {
            "category":"Organizations",
            "subcategory":"Community Association",
            "type":"Services"
        }
    ],
    "sg:phone":"+44 20 8549 7575",
    "sg:postcode":"KT1 2JW",
    "sg:province":"Greater London",
    "sg:tags":[
        "fire",
        "alarm",
        "system"
    ],
    "wof:name":"Insaf Ltd.",
    "wof:placetype":"venue"
},
  "geometry": {"coordinates":[-0.305741,51.401997],"type":"Point"}
}