{
  "type": "Feature",
  "properties": {
    "iso:country":"GB",
    "sg:address":"287 Lillie Road",
    "sg:city":"London",
    "sg:classifiers":[
        {
            "category":"Shopping",
            "subcategory":"Antiques",
            "type":"Retail Goods"
        }
    ],
    "sg:phone":"+44 20 7385 9025",
    "sg:postcode":"SW6 7LL",
    "sg:province":"Greater London",
    "wof:name":"Andrew Bewick",
    "wof:placetype":"venue"
},
  "geometry": {"coordinates":[-0.2118130028,51.4828567505],"type":"Point"}
}