{
  "type": "Feature",
  "properties": {
    "addr:full":"Railway App Ormskirk Lancashire L39 2DD",
    "addr:postcode":"l39 2dd",
    "iso:country":"GB",
    "sg:address":"Railway App",
    "sg:city":"Ormskirk",
    "sg:classifiers":[
        {
            "category":"Professional",
            "subcategory":"Testing Lab",
            "type":"Services"
        }
    ],
    "sg:phone":"+44 1695 572029",
    "sg:postcode":"L39 2DD",
    "sg:province":"Lancashire",
    "sg:tags":[
        "mot"
    ],
    "wof:name":"Heaton Craig",
    "wof:placetype":"venue"
},
  "geometry": {"coordinates":[-2.882178,53.569042],"type":"Point"}
}