{
  "type": "Feature",
  "properties": {
    "addr:full":"16 Henblas Street Wrexham Wrexham LL13 8AD",
    "addr:housenumber":"16",
    "addr:postcode":"ll13 8ad",
    "addr:street":"Henblas Street",
    "iso:country":"GB",
    "sg:address":"16 Henblas Street",
    "sg:city":"Wrexham",
    "sg:classifiers":[
        {
            "category":"Shopping",
            "subcategory":"Florist",
            "type":"Retail Goods"
        }
    ],
    "sg:phone":"+44 1978 355318",
    "sg:postcode":"LL13 8AD",
    "sg:province":"Wrexham",
    "wof:name":"Choice Flowers",
    "wof:placetype":"venue"
},
  "geometry": {"coordinates":[-2.9925990105,53.0460891724],"type":"Point"}
}