{
  "type": "Feature",
  "properties": {
    "addr:full":"42 St Marys Drive Crawley Surrey RH10 3BN",
    "addr:housenumber":"42",
    "addr:postcode":"rh10 3bn",
    "addr:street":"St Marys Drive",
    "iso:country":"GB",
    "sg:address":"42 St Marys Drive",
    "sg:city":"Crawley",
    "sg:classifiers":[
        {
            "category":"Professional",
            "subcategory":"Employment Agencies",
            "type":"Services"
        }
    ],
    "sg:phone":"+44 1293 432790",
    "sg:postcode":"RH10 3BN",
    "sg:province":"Surrey",
    "sg:tags":[
        "cv"
    ],
    "wof:name":"Impact Cv's",
    "wof:placetype":"venue"
},
  "geometry": {"coordinates":[-0.1592340022,51.1207427979],"type":"Point"}
}