{
  "type": "Feature",
  "properties": {
    "addr:full":"12 Jeans Way Dunstable Bedfordshire LU5 4PW",
    "addr:housenumber":"12",
    "addr:postcode":"lu5 4pw",
    "addr:street":"Jeans Way",
    "iso:country":"GB",
    "sg:address":"12 Jeans Way",
    "sg:city":"Dunstable",
    "sg:classifiers":[
        {
            "category":"Home & Garden",
            "subcategory":"Household Appliances",
            "type":"Retail Goods"
        }
    ],
    "sg:phone":"+44 1582 667953",
    "sg:postcode":"LU5 4PW",
    "sg:province":"Bedfordshire",
    "sg:tags":[
        "electrical"
    ],
    "wof:name":"J Mead",
    "wof:placetype":"venue"
},
  "geometry": {"coordinates":[-0.5004190207,51.8857765198],"type":"Point"}
}