{
  "type": "Feature",
  "properties": {
    "addr:full":"Bushbury Lane, Bushbury Wolverhampton Staffordshire WV10 8JP",
    "addr:postcode":"wv10 8jp",
    "addr:street":"Bushbury Lane",
    "iso:country":"GB",
    "sg:address":"Bushbury Lane, Bushbury",
    "sg:city":"Wolverhampton",
    "sg:classifiers":[
        {
            "category":"Education",
            "subcategory":"Library",
            "type":"Public Place"
        },
        {
            "category":"Government",
            "subcategory":"Office",
            "type":"Public Place"
        }
    ],
    "sg:phone":"+44 1902 556302",
    "sg:postcode":"WV10 8JP",
    "sg:province":"Staffordshire",
    "sg:tags":[
        "book",
        "local"
    ],
    "wof:name":"Collingwood Library",
    "wof:placetype":"venue"
},
  "geometry": {"coordinates":[-2.1168320179,52.6227378845],"type":"Point"}
}