{
  "type": "Feature",
  "properties": {
    "iso:country":"GB",
    "sg:address":"3 Binford Place",
    "sg:city":"Bridgwater",
    "sg:classifiers":[
        {
            "category":"Cafe",
            "type":"Food & Drink"
        }
    ],
    "sg:phone":"+44 1278 451666",
    "sg:postcode":"TA6 3NJ",
    "sg:province":"Somerset",
    "sg:tags":[
        "tea",
        "room"
    ],
    "wof:name":"Poppy's",
    "wof:placetype":"venue"
},
  "geometry": {"coordinates":[-3.0013380051,51.1284751892],"type":"Point"}
}