{
  "type": "Feature",
  "properties": {
    "iso:country":"GB",
    "sg:address":"2 Intake Avenue",
    "sg:city":"York",
    "sg:classifiers":[
        {
            "category":"Food & Beverages",
            "subcategory":"Bakery",
            "type":"Retail Goods"
        }
    ],
    "sg:phone":"+44 1904 623409",
    "sg:postcode":"YO30 6HB",
    "sg:province":"North Yorkshire",
    "sg:tags":[
        "baker"
    ],
    "wof:name":"Bridge Bakery Catering Eqpt",
    "wof:placetype":"venue"
},
  "geometry": {"coordinates":[-1.0952349901,53.9680557251],"type":"Point"}
}