{
  "type": "Feature",
  "properties": {
    "addr:full":"11-13 Great Square Braintree Essex CM7 7TX",
    "addr:housenumber":"11-13",
    "addr:postcode":"cm7 7tx",
    "addr:street":"Great Square",
    "iso:country":"GB",
    "sg:address":"11-13 Great Square",
    "sg:city":"Braintree",
    "sg:classifiers":[
        {
            "category":"Retail",
            "subcategory":"Photofinishing",
            "type":"Services"
        },
        {
            "category":"Retail",
            "subcategory":"Laundry & Dry Cleaning",
            "type":"Services"
        }
    ],
    "sg:phone":"+44 1376 340467",
    "sg:postcode":"CM7 7TX",
    "sg:province":"Essex",
    "sg:tags":[
        "photographic",
        "alteration",
        "processor"
    ],
    "wof:name":"Sketchley Retail Ltd.",
    "wof:placetype":"venue"
},
  "geometry": {"coordinates":[0.5516560078,51.8786964417],"type":"Point"}
}