{
  "type": "Feature",
  "properties": {
    "addr:full":"3 Station Rd, Chadwell Heath Romford Essex RM6 4BE",
    "addr:housenumber":"3",
    "addr:postcode":"rm6 4be",
    "addr:street":"Station Rd",
    "iso:country":"GB",
    "sg:address":"3 Station Rd, Chadwell Heath",
    "sg:city":"Romford",
    "sg:classifiers":[
        {
            "category":"Food & Beverages",
            "subcategory":"Liquor & Beverages",
            "type":"Retail Goods"
        }
    ],
    "sg:phone":"+44 20 8597 0393",
    "sg:postcode":"RM6 4BE",
    "sg:province":"Essex",
    "sg:tags":[
        "beer",
        "spirit",
        "wines"
    ],
    "wof:name":"Wines & Spirits",
    "wof:placetype":"venue"
},
  "geometry": {"coordinates":[0.130589,51.570332],"type":"Point"}
}