{
  "type": "Feature",
  "properties": {
    "iso:country":"GB",
    "sg:address":"Molesey Road, Hersham",
    "sg:city":"Walton-on-thames",
    "sg:classifiers":[
        {
            "category":"Community Center",
            "type":"Public Place"
        }
    ],
    "sg:phone":"+44 1932 223037",
    "sg:postcode":"KT12 4QZ",
    "sg:province":"Surrey",
    "sg:tags":[
        "recreation",
        "leisure",
        "centre"
    ],
    "wof:name":"Coronation Recreation Ground",
    "wof:placetype":"venue"
},
  "geometry": {"coordinates":[-0.390419,51.376457],"type":"Point"}
}