{
  "type": "Feature",
  "properties": {
    "iso:country":"GB",
    "sg:address":"1 St Chads Court",
    "sg:city":"Rochdale",
    "sg:classifiers":[
        {
            "category":"Professional",
            "subcategory":"Accounting & Tax Preparation",
            "type":"Services"
        }
    ],
    "sg:phone":"+44 1706 860255",
    "sg:postcode":"OL16 1QU",
    "sg:province":"Lancashire",
    "sg:tags":[
        "accountant"
    ],
    "wof:name":"M C A",
    "wof:placetype":"venue"
},
  "geometry": {"coordinates":[-2.1554639339,53.6138267517],"type":"Point"}
}