{
  "type": "Feature",
  "properties": {
    "addr:full":"Chapeltown Business Centre, Chapeltown Road Leeds West Yorkshire LS7 3DX",
    "addr:postcode":"ls7 3dx",
    "addr:street":"Chapeltown Road",
    "iso:country":"GB",
    "sg:address":"Chapeltown Business Centre, Chapeltown Road",
    "sg:city":"Leeds",
    "sg:classifiers":[
        {
            "category":"Home & Garden",
            "subcategory":"Building Materials",
            "type":"Retail Goods"
        }
    ],
    "sg:phone":"+44 113 239 2030",
    "sg:postcode":"LS7 3DX",
    "sg:province":"West Yorkshire",
    "sg:tags":[
        "ironwork",
        "diy",
        "wrought"
    ],
    "wof:name":"Arc & Craft Training Services",
    "wof:placetype":"venue"
},
  "geometry": {"coordinates":[-1.53182,53.816109],"type":"Point"}
}