{
  "type": "Feature",
  "properties": {
    "addr:full":"10 South Parade, Bawtry Doncaster Lincolnshire DN10 6JH",
    "addr:housenumber":"10",
    "addr:postcode":"dn10 6jh",
    "addr:street":"South Parade",
    "iso:country":"GB",
    "sg:address":"10 South Parade, Bawtry",
    "sg:city":"Doncaster",
    "sg:classifiers":[
        {
            "category":"Professional",
            "subcategory":"Accounting & Tax Preparation",
            "type":"Services"
        }
    ],
    "sg:phone":"+44 1302 711550",
    "sg:postcode":"DN10 6JH",
    "sg:province":"Lincolnshire",
    "sg:tags":[
        "accountant"
    ],
    "wof:name":"John Daley",
    "wof:placetype":"venue"
},
  "geometry": {"coordinates":[-1.0056480169,53.4401512146],"type":"Point"}
}