{
  "type": "Feature",
  "properties": {
    "iso:country":"GB",
    "sg:address":"Unit 29a Hartlebury Trading Estate, Hartlebury",
    "sg:city":"Kidderminster",
    "sg:classifiers":[
        {
            "category":"Retail",
            "subcategory":"Auto Repair",
            "type":"Services"
        }
    ],
    "sg:phone":"+44 1299 251329",
    "sg:postcode":"DY10 4JB",
    "sg:province":"Staffordshire",
    "sg:tags":[
        "modification",
        "garage"
    ],
    "wof:name":"G T Motors (Hartlebury) Ltd.",
    "wof:placetype":"venue"
},
  "geometry": {"coordinates":[-2.211575985,52.3237495422],"type":"Point"}
}