{
  "type": "Feature",
  "properties": {
    "iso:country":"GB",
    "sg:address":"3 Knightstone Road",
    "sg:city":"Weston-super-mare",
    "sg:classifiers":[
        {
            "category":"Travel",
            "subcategory":"Hotels & Motels",
            "type":"Entertainment"
        }
    ],
    "sg:postcode":"BS23 2AH",
    "sg:province":"Somerset",
    "sg:tags":[
        "self",
        "catering"
    ],
    "wof:name":"Sealawn Holiday Flatlets",
    "wof:placetype":"venue"
},
  "geometry": {"coordinates":[-2.98172,51.350346],"type":"Point"}
}