{
  "type": "Feature",
  "properties": {
    "addr:full":"Kings Cross Station, Euston Rd Islington Greater London N1 9AL",
    "addr:postcode":"n1 9al",
    "addr:street":"Euston Rd",
    "iso:country":"GB",
    "sg:address":"Kings Cross Station, Euston Rd",
    "sg:city":"Islington",
    "sg:classifiers":[
        {
            "category":"Home & Garden",
            "subcategory":"Building Materials",
            "type":"Retail Goods"
        }
    ],
    "sg:phone":"+44 20 7278 5606",
    "sg:postcode":"N1 9AL",
    "sg:province":"Greater London",
    "sg:tags":[
        "hinge"
    ],
    "wof:name":"Timpson Ltd",
    "wof:placetype":"venue"
},
  "geometry": {"coordinates":[-0.118897,51.530735],"type":"Point"}
}