{
  "type": "Feature",
  "properties": {
    "iso:country":"GB",
    "sg:address":"Beach Road",
    "sg:city":"Clacton-on-sea",
    "sg:classifiers":[
        {
            "category":"Farming",
            "subcategory":"Livestock Farm",
            "type":"Manufacturing & Wholesale Goods"
        }
    ],
    "sg:postcode":"CO16 8SB",
    "sg:province":"Essex",
    "sg:tags":[
        "others"
    ],
    "wof:name":"Richard J Ford",
    "wof:placetype":"venue"
},
  "geometry": {"coordinates":[1.054385,51.771603],"type":"Point"}
}