{
  "type": "Feature",
  "properties": {
    "iso:country":"GB",
    "sg:address":"35 Forman Street",
    "sg:city":"Nottingham",
    "sg:classifiers":[
        {
            "category":"Restaurant",
            "type":"Food & Drink"
        }
    ],
    "sg:phone":"+44 115 941 1965",
    "sg:postcode":"NG1 4AA",
    "sg:province":"Nottinghamshire",
    "wof:name":"Punchinello",
    "wof:placetype":"venue"
},
  "geometry": {"coordinates":[-1.150909,52.955311],"type":"Point"}
}