{
  "type": "Feature",
  "properties": {
    "addr:full":"Muchelney Ham Farm, Muchelney Ham Langport Somerset TA10 0DJ",
    "addr:housenumber":"muchelney;langport",
    "addr:postcode":"ta10 0dj",
    "addr:street":"Ham",
    "iso:country":"GB",
    "sg:address":"Muchelney Ham Farm, Muchelney Ham",
    "sg:city":"Langport",
    "sg:classifiers":[
        {
            "category":"Farming",
            "subcategory":"Livestock Farm",
            "type":"Manufacturing & Wholesale Goods"
        },
        {
            "category":"Farming",
            "subcategory":"Farm",
            "type":"Manufacturing & Wholesale Goods"
        }
    ],
    "sg:postcode":"TA10 0DJ",
    "sg:province":"Somerset",
    "sg:tags":[
        "mixed",
        "crop",
        "others"
    ],
    "wof:name":"W J Woodborne",
    "wof:placetype":"venue"
},
  "geometry": {"coordinates":[-2.7991940975,51.0098571777],"type":"Point"}
}