{
  "type": "Feature",
  "properties": {
    "iso:country":"GB",
    "sg:address":"44 Prince Albert Street, Bordesley Grn",
    "sg:city":"Birmingham",
    "sg:classifiers":[
        {
            "category":"Professional",
            "type":"Services"
        },
        {
            "category":"Organizations",
            "subcategory":"Community Association",
            "type":"Services"
        }
    ],
    "sg:phone":"+44 121 766 8267",
    "sg:postcode":"B9 5AZ",
    "sg:province":"West Midlands",
    "sg:tags":[
        "specialist",
        "coating"
    ],
    "wof:name":"Midland Paint & Powder Coaters Ltd",
    "wof:placetype":"venue"
},
  "geometry": {"coordinates":[-1.8575279713,52.4755783081],"type":"Point"}
}