{
  "type": "Feature",
  "properties": {
    "iso:country":"GB",
    "sg:address":"Central Garage, Barnsley Road, Darton",
    "sg:city":"Barnsley",
    "sg:classifiers":[
        {
            "category":"Retail",
            "subcategory":"Auto Repair",
            "type":"Services"
        }
    ],
    "sg:postcode":"S75 5NN",
    "sg:province":"South Yorkshire",
    "sg:tags":[
        "modification",
        "garage"
    ],
    "wof:name":"Darton van Hire Ltd.",
    "wof:placetype":"venue"
},
  "geometry": {"coordinates":[-1.524886,53.585812],"type":"Point"}
}