{
  "type": "Feature",
  "properties": {
    "addr:full":"Unit 4 St Johns House, St Johns Court, Square Street Bradford West Yorkshire BD4 7NQ",
    "addr:housenumber":"unit 4",
    "addr:postcode":"bd4 7nq",
    "addr:street":"St;St Johns Court Square Street",
    "iso:country":"GB",
    "sg:address":"Unit 4 St Johns House, St Johns Court, Square Street",
    "sg:city":"Bradford",
    "sg:classifiers":[
        {
            "category":"Professional",
            "subcategory":"Engineering",
            "type":"Services"
        },
        {
            "category":"Banks & Credit Unions",
            "subcategory":"Financial Services",
            "type":"Services"
        }
    ],
    "sg:phone":"+44 1274 391574",
    "sg:postcode":"BD4 7NQ",
    "sg:province":"West Yorkshire",
    "sg:tags":[
        "claim",
        "consulting",
        "assessor",
        "engineer"
    ],
    "wof:name":"AUTOMOTIVE CONSULTING ENGINEERING LTD",
    "wof:placetype":"venue"
},
  "geometry": {"coordinates":[-1.736805,53.786171],"type":"Point"}
}