{
  "type": "Feature",
  "properties": {
    "addr:full":"Highfield Lodge, Providence Hill Southampton Hampshire SO31 8AT",
    "addr:postcode":"so31 8at",
    "addr:street":"Providence Hill",
    "iso:country":"GB",
    "sg:address":"Highfield Lodge, Providence Hill",
    "sg:city":"Southampton",
    "sg:classifiers":[
        {
            "category":"Banks & Credit Unions",
            "subcategory":"Financial Services",
            "type":"Services"
        }
    ],
    "sg:phone":"+44 23 8040 4111",
    "sg:postcode":"SO31 8AT",
    "sg:province":"Hampshire",
    "sg:tags":[
        "consultant"
    ],
    "wof:name":"Anglo Scottish",
    "wof:placetype":"venue"
},
  "geometry": {"coordinates":[-1.3149199486,50.8923797607],"type":"Point"}
}