{
  "type": "Feature",
  "properties": {
    "addr:full":"Church Road Truro Cornwall TR4 9DD",
    "addr:postcode":"tr4 9dd",
    "addr:street":"Church Road",
    "iso:country":"GB",
    "sg:address":"Church Road",
    "sg:city":"Truro",
    "sg:classifiers":[
        {
            "category":"Retail",
            "subcategory":"Auto Repair",
            "type":"Services"
        }
    ],
    "sg:postcode":"TR4 9DD",
    "sg:province":"Cornwall",
    "sg:tags":[
        "modification",
        "garage"
    ],
    "wof:name":"Shortlanesend Garage",
    "wof:placetype":"venue"
},
  "geometry": {"coordinates":[-5.080379,50.289749],"type":"Point"}
}