{
  "type": "Feature",
  "properties": {
    "addr:full":"32 Malcolmson Close, Edgbaston Birmingham West Midlands B15 3LS",
    "addr:housenumber":"32",
    "addr:postcode":"b15 3ls",
    "addr:street":"Malcolmson Close",
    "iso:country":"GB",
    "sg:address":"32 Malcolmson Close, Edgbaston",
    "sg:city":"Birmingham",
    "sg:classifiers":[
        {
            "category":"Professional",
            "subcategory":"Detective & Security Services",
            "type":"Services"
        }
    ],
    "sg:postcode":"B15 3LS",
    "sg:province":"West Midlands",
    "wof:name":"Birmingham Citywatch Trust",
    "wof:placetype":"venue"
},
  "geometry": {"coordinates":[-1.933789,52.469109],"type":"Point"}
}