{
  "type": "Feature",
  "properties": {
    "addr:full":"Aberford Road, Garforth Leeds North Yorkshire LS25 2ET",
    "addr:postcode":"ls25 2et",
    "addr:street":"Aberford Road",
    "iso:country":"GB",
    "sg:address":"Aberford Road, Garforth",
    "sg:city":"Leeds",
    "sg:classifiers":[
        {
            "category":"Retail",
            "subcategory":"Auto Rental",
            "type":"Services"
        },
        {
            "category":"Building & Trades",
            "subcategory":"Equipment Rental",
            "type":"Services"
        }
    ],
    "sg:phone":"+44 113 287 4874",
    "sg:postcode":"LS25 2ET",
    "sg:province":"North Yorkshire",
    "sg:tags":[
        "crane",
        "truck",
        "hire",
        "van",
        "sales"
    ],
    "wof:name":"Dawsonrentals Ltd",
    "wof:placetype":"venue"
},
  "geometry": {"coordinates":[-1.3751189709,53.7969741821],"type":"Point"}
}