{
  "type": "Feature",
  "properties": {
    "addr:full":"8 Vernon Pl, Northern Ct Nottingham Nottinghamshire NG6 0DE",
    "addr:housenumber":"8",
    "addr:postcode":"ng6 0de",
    "addr:street":"Vernon Pl Northern Ct",
    "iso:country":"GB",
    "sg:address":"8 Vernon Pl, Northern Ct",
    "sg:city":"Nottingham",
    "sg:classifiers":[
        {
            "category":"Professional",
            "type":"Services"
        }
    ],
    "sg:phone":"+44 115 976 1990",
    "sg:postcode":"NG6 0DE",
    "sg:province":"Nottinghamshire",
    "sg:tags":[
        "shopfitters"
    ],
    "wof:name":"Split Products Ltd",
    "wof:placetype":"venue"
},
  "geometry": {"coordinates":[-1.178702,52.982964],"type":"Point"}
}