{
  "type": "Feature",
  "properties": {
    "iso:country":"GB",
    "sg:address":"Brook House Farm, Newcastle Road",
    "sg:city":"Crewe",
    "sg:classifiers":[
        {
            "category":"Shopping",
            "type":"Retail Goods"
        }
    ],
    "sg:postcode":"CW3 9JT",
    "sg:province":"Cheshire",
    "sg:tags":[
        "merchant"
    ],
    "wof:name":"Brook House Agricultural Services",
    "wof:placetype":"venue"
},
  "geometry": {"coordinates":[-2.387479,52.978588],"type":"Point"}
}