{
  "type": "Feature",
  "properties": {
    "addr:full":"144 High Road London Greater London E18 2QS",
    "addr:housenumber":"144",
    "addr:postcode":"e18 2qs",
    "addr:street":"High Road",
    "iso:country":"GB",
    "sg:address":"144 High Road",
    "sg:city":"London",
    "sg:classifiers":[
        {
            "category":"Shopping",
            "subcategory":"Optician",
            "type":"Retail Goods"
        }
    ],
    "sg:phone":"+44 20 8504 8817",
    "sg:postcode":"E18 2QS",
    "sg:province":"Greater London",
    "sg:tags":[
        "dispensing"
    ],
    "wof:name":"Bird & Harris",
    "wof:placetype":"venue"
},
  "geometry": {"coordinates":[0.0212459993,51.596824646],"type":"Point"}
}