{
  "type": "Feature",
  "properties": {
    "iso:country":"GB",
    "sg:address":"Saunders House, 52-53 The Mall",
    "sg:city":"London",
    "sg:classifiers":[
        {
            "category":"Professional",
            "subcategory":"Employment Agencies",
            "type":"Services"
        }
    ],
    "sg:phone":"+44 20 8579 1540",
    "sg:postcode":"W5 3TE",
    "sg:province":"Greater London",
    "sg:tags":[
        "career",
        "guidance"
    ],
    "wof:name":"C F B T West London Careers",
    "wof:placetype":"venue"
},
  "geometry": {"coordinates":[-0.299526,51.513809],"type":"Point"}
}