{
  "type": "Feature",
  "properties": {
    "addr:full":"Unit 18 Culver Precinct Colchester Essex CO1 1XJ",
    "addr:housenumber":"unit 18",
    "addr:postcode":"co1 1xj",
    "iso:country":"GB",
    "sg:address":"Unit 18 Culver Precinct",
    "sg:city":"Colchester",
    "sg:classifiers":[
        {
            "category":"Shopping",
            "subcategory":"Baby Store",
            "type":"Retail Goods"
        }
    ],
    "sg:phone":"+44 1206 761726",
    "sg:postcode":"CO1 1XJ",
    "sg:province":"Essex",
    "sg:tags":[
        "babywear",
        "childrens"
    ],
    "wof:name":"Adams Childrenswear Ltd.",
    "wof:placetype":"venue"
},
  "geometry": {"coordinates":[0.9019150138,51.889213562],"type":"Point"}
}