{
  "type": "Feature",
  "properties": {
    "iso:country":"GB",
    "sg:address":"Hambleton Place",
    "sg:city":"Thirsk",
    "sg:classifiers":[
        {
            "category":"Education",
            "subcategory":"School",
            "type":"Public Place"
        },
        {
            "category":"Government",
            "subcategory":"Office",
            "type":"Public Place"
        }
    ],
    "sg:phone":"+44 1845 524349",
    "sg:postcode":"YO7 1SL",
    "sg:province":"North Yorkshire",
    "sg:tags":[
        "local",
        "authority"
    ],
    "wof:name":"Thirsk County Primary School",
    "wof:placetype":"venue"
},
  "geometry": {"coordinates":[-1.333739,54.236565],"type":"Point"}
}