{
  "type": "Feature",
  "properties": {
    "iso:country":"GB",
    "sg:address":"10 Blandfield Rd",
    "sg:city":"London",
    "sg:classifiers":[
        {
            "category":"Shopping",
            "subcategory":"Hobbies, Toys, & Games",
            "type":"Retail Goods"
        }
    ],
    "sg:postcode":"SW12 8BG",
    "sg:province":"Greater London",
    "sg:tags":[
        "kite"
    ],
    "wof:name":"Murray,Karen,",
    "wof:placetype":"venue"
},
  "geometry": {"coordinates":[-0.154957,51.450516],"type":"Point"}
}