{
  "type": "Feature",
  "properties": {
    "addr:full":"102 Chepstow Rd Newport Newport NP19 8XA",
    "addr:housenumber":"102",
    "addr:postcode":"np19 8xa",
    "addr:street":"Chepstow Rd",
    "iso:country":"GB",
    "sg:address":"102 Chepstow Rd",
    "sg:city":"Newport",
    "sg:classifiers":[
        {
            "category":"Government",
            "subcategory":"Post Office",
            "type":"Public Place"
        }
    ],
    "sg:phone":"+44 1633 222317",
    "sg:postcode":"NP19 8XA",
    "sg:province":"Newport",
    "wof:name":"Spa",
    "wof:placetype":"venue"
},
  "geometry": {"coordinates":[-2.981372118,51.5900611877],"type":"Point"}
}