{
  "type": "Feature",
  "properties": {
    "addr:full":"13 Sinclair Court, Canning Road Croydon Surrey CR0 6QA",
    "addr:housenumber":"13",
    "addr:postcode":"cr0 6qa",
    "addr:street":"Sinclair Court Canning Road",
    "iso:country":"GB",
    "sg:address":"13 Sinclair Court, Canning Road",
    "sg:city":"Croydon",
    "sg:classifiers":[
        {
            "category":"Professional",
            "subcategory":"Management & Consulting",
            "type":"Services"
        }
    ],
    "sg:postcode":"CR0 6QA",
    "sg:province":"Surrey",
    "sg:tags":[
        "consultant",
        "business"
    ],
    "wof:name":"T A A Consulting Ltd",
    "wof:placetype":"venue"
},
  "geometry": {"coordinates":[-0.08244,51.3755],"type":"Point"}
}