{
  "type": "Feature",
  "properties": {
    "iso:country":"GB",
    "sg:address":"51 Wellfield Road, Roath Park",
    "sg:city":"Cardiff",
    "sg:classifiers":[
        {
            "category":"Shopping",
            "subcategory":"Baby Store",
            "type":"Retail Goods"
        }
    ],
    "sg:phone":"+44 29 2049 6702",
    "sg:postcode":"CF24 3PA",
    "sg:province":"Cardiff",
    "sg:tags":[
        "babywear",
        "childrens"
    ],
    "wof:name":"Wendy & William",
    "wof:placetype":"venue"
},
  "geometry": {"coordinates":[-3.1654350758,51.4956588745],"type":"Point"}
}