{
  "type": "Feature",
  "properties": {
    "addr:full":"Wheatsheaf Workshop, High Street, Rhosymedre Wrexham Wrexham LL14 3YE",
    "addr:postcode":"ll14 3ye",
    "addr:street":"High Street Rhosymedre",
    "iso:country":"GB",
    "sg:address":"Wheatsheaf Workshop, High Street, Rhosymedre",
    "sg:city":"Wrexham",
    "sg:classifiers":[
        {
            "category":"Communications",
            "subcategory":"Film & Video Production",
            "type":"Services"
        }
    ],
    "sg:phone":"+44 1978 810473",
    "sg:postcode":"LL14 3YE",
    "sg:province":"Wrexham",
    "sg:tags":[
        "microfilming"
    ],
    "wof:name":"C D I Microfilms",
    "wof:placetype":"venue"
},
  "geometry": {"coordinates":[-3.06827,52.975399],"type":"Point"}
}