{
  "type": "Feature",
  "properties": {
    "iso:country":"GB",
    "sg:address":"The Grn, Deanshanger",
    "sg:city":"Milton Keynes",
    "sg:classifiers":[
        {
            "category":"Organizations",
            "subcategory":"Community Association",
            "type":"Services"
        },
        {
            "category":"Organizations",
            "subcategory":"Membership Organization",
            "type":"Services"
        }
    ],
    "sg:phone":"+44 1908 567109",
    "sg:postcode":"MK19 6HH",
    "sg:province":"Buckinghamshire",
    "sg:tags":[
        "club",
        "social"
    ],
    "wof:name":"DEANSHANGER & DISTRICT CONSERVATIVE CLUB",
    "wof:placetype":"venue"
},
  "geometry": {"coordinates":[-0.8928490281,52.0520248413],"type":"Point"}
}