{
  "type": "Feature",
  "properties": {
    "addr:full":"2 Castle Meadow Norwich Norfolk NR1 3PY",
    "addr:housenumber":"2",
    "addr:postcode":"nr1 3py",
    "addr:street":"Castle Meadow Norwich Norfolk",
    "iso:country":"GB",
    "sg:address":"2 Castle Meadow",
    "sg:city":"Norwich",
    "sg:classifiers":[
        {
            "category":"Retail",
            "subcategory":"Laundry & Dry Cleaning",
            "type":"Services"
        }
    ],
    "sg:phone":"+44 1603 621036",
    "sg:postcode":"NR1 3PY",
    "sg:province":"Norfolk",
    "sg:tags":[
        "alteration"
    ],
    "wof:name":"Sketchley Dry Cleaners",
    "wof:placetype":"venue"
},
  "geometry": {"coordinates":[1.2951209545,52.6279411316],"type":"Point"}
}