{
  "type": "Feature",
  "properties": {
    "iso:country":"GB",
    "sg:address":"10 Rhodesia Avenue, Allerton",
    "sg:city":"Bradford",
    "sg:classifiers":[
        {
            "category":"Professional",
            "subcategory":"Management & Consulting",
            "type":"Services"
        },
        {
            "category":"Sports & Exercise",
            "subcategory":"Sports Center",
            "type":"Entertainment"
        }
    ],
    "sg:phone":"+44 1274 490998",
    "sg:postcode":"BD15 7RL",
    "sg:province":"West Yorkshire",
    "sg:tags":[
        "consultant",
        "investigation",
        "site"
    ],
    "wof:name":"Geoinvestigate Ltd.",
    "wof:placetype":"venue"
},
  "geometry": {"coordinates":[-1.815564,53.80125],"type":"Point"}
}