{
  "type": "Feature",
  "properties": {
    "addr:full":"90 Grove Lane Ipswich Suffolk IP4 1NY",
    "addr:housenumber":"90",
    "addr:postcode":"ip4 1ny",
    "addr:street":"Grove Lane",
    "iso:country":"GB",
    "sg:address":"90 Grove Lane",
    "sg:city":"Ipswich",
    "sg:classifiers":[
        {
            "category":"Personal",
            "subcategory":"Beauty Salon",
            "type":"Services"
        }
    ],
    "sg:postcode":"IP4 1NY",
    "sg:province":"Suffolk",
    "sg:tags":[
        "unisex",
        "hairdresser"
    ],
    "wof:name":"Huw Adam Hair Studio",
    "wof:placetype":"venue"
},
  "geometry": {"coordinates":[1.1723419428,52.0537109375],"type":"Point"}
}