{
  "type": "Feature",
  "properties": {
    "addr:full":"343b Benwell La Newcastle Upon Tyne Northumberland NE15 6LX",
    "addr:housenumber":"343b",
    "addr:postcode":"ne15 6lx",
    "addr:street":"Benwell La",
    "iso:country":"GB",
    "sg:address":"343b Benwell La",
    "sg:city":"Newcastle Upon Tyne",
    "sg:classifiers":[
        {
            "category":"Personal",
            "subcategory":"Beauty Salon",
            "type":"Services"
        }
    ],
    "sg:phone":"+44 191 274 7770",
    "sg:postcode":"NE15 6LX",
    "sg:province":"Northumberland",
    "sg:tags":[
        "unisex",
        "hairdresser"
    ],
    "wof:name":"Klub Kut One",
    "wof:placetype":"venue"
},
  "geometry": {"coordinates":[-1.673211,54.973457],"type":"Point"}
}