{
  "type": "Feature",
  "properties": {
    "addr:full":"89-95 Blackburn Road Accrington Lancashire BB5 1JJ",
    "addr:housenumber":"89-95",
    "addr:postcode":"bb5 1jj",
    "addr:street":"Blackburn Road",
    "iso:country":"GB",
    "sg:address":"89-95 Blackburn Road",
    "sg:city":"Accrington",
    "sg:classifiers":[
        {
            "category":"Home & Garden",
            "subcategory":"Furniture",
            "type":"Retail Goods"
        }
    ],
    "sg:phone":"+44 1254 394378",
    "sg:postcode":"BB5 1JJ",
    "sg:province":"Lancashire",
    "sg:tags":[
        "outlet"
    ],
    "wof:name":"Davies Of Accrington Ltd",
    "wof:placetype":"venue"
},
  "geometry": {"coordinates":[-2.3668150902,53.7531852722],"type":"Point"}
}