{
  "type": "Feature",
  "properties": {
    "addr:full":"Gover Rd St. Austell Cornwall PL25 5NE",
    "addr:postcode":"pl25 5ne",
    "addr:street":"Gover Rd",
    "iso:country":"GB",
    "sg:address":"Gover Rd",
    "sg:city":"St. Austell",
    "sg:classifiers":[
        {
            "category":"Manufacturing",
            "subcategory":"Wood Products",
            "type":"Manufacturing & Wholesale Goods"
        }
    ],
    "sg:phone":"+44 1726 64488",
    "sg:postcode":"PL25 5NE",
    "sg:province":"Cornwall",
    "sg:tags":[
        "maker",
        "cabinet"
    ],
    "wof:name":"Sovereign Design",
    "wof:placetype":"venue"
},
  "geometry": {"coordinates":[-4.807979,50.342106],"type":"Point"}
}