{
  "type": "Feature",
  "properties": {
    "addr:full":"18 Essex Road London Greater London W3 9JA",
    "addr:housenumber":"18",
    "addr:postcode":"w3 9ja",
    "addr:street":"Essex Road",
    "iso:country":"GB",
    "sg:address":"18 Essex Road",
    "sg:city":"London",
    "sg:classifiers":[
        {
            "category":"Building & Trades",
            "subcategory":"Cleaning & Sanitation",
            "type":"Services"
        }
    ],
    "sg:phone":"+44 20 8992 9457",
    "sg:postcode":"W3 9JA",
    "sg:province":"Greater London",
    "sg:tags":[
        "commercial"
    ],
    "wof:name":"Alan Helps Cleaning Ltd.",
    "wof:placetype":"venue"
},
  "geometry": {"coordinates":[-0.2702749968,51.514705658],"type":"Point"}
}