{
  "type": "Feature",
  "properties": {
    "addr:full":"Appleton House, Hornby Bedale North Yorkshire DL8 1NN",
    "addr:postcode":"dl8 1nn",
    "iso:country":"GB",
    "sg:address":"Appleton House, Hornby",
    "sg:city":"Bedale",
    "sg:classifiers":[
        {
            "category":"Communications",
            "type":"Services"
        }
    ],
    "sg:phone":"+44 1748 818042",
    "sg:postcode":"DL8 1NN",
    "sg:province":"North Yorkshire",
    "sg:tags":[
        "broadcasting"
    ],
    "wof:name":"Keith Richardson",
    "wof:placetype":"venue"
},
  "geometry": {"coordinates":[-1.592346,54.288811],"type":"Point"}
}