{
  "type": "Feature",
  "properties": {
    "iso:country":"GB",
    "sg:address":"69a Sidwell St",
    "sg:city":"Exeter",
    "sg:classifiers":[
        {
            "category":"Taxi",
            "type":"Transportation"
        }
    ],
    "sg:phone":"+44 1392 666666",
    "sg:postcode":"EX4 6PH",
    "sg:province":"Devon",
    "sg:tags":[
        "mini",
        "cab"
    ],
    "wof:name":"Gemini Cab Co",
    "wof:placetype":"venue"
},
  "geometry": {"coordinates":[-3.5227971077,50.7280387878],"type":"Point"}
}