{
  "type": "Feature",
  "properties": {
    "iso:country":"GB",
    "sg:address":"71 Enderby Rd",
    "sg:city":"Scunthorpe",
    "sg:classifiers":[
        {
            "category":"Shopping",
            "subcategory":"News",
            "type":"Retail Goods"
        },
        {
            "category":"Food & Beverages",
            "subcategory":"Groceries & Convenience Stores",
            "type":"Retail Goods"
        }
    ],
    "sg:phone":"+44 1724 844400",
    "sg:postcode":"DN17 2HE",
    "sg:province":"Lincolnshire",
    "sg:tags":[
        "newsagent"
    ],
    "wof:name":"LINEBUSH LTD",
    "wof:placetype":"venue"
},
  "geometry": {"coordinates":[-0.674168,53.561863],"type":"Point"}
}