{
  "type": "Feature",
  "properties": {
    "addr:full":"Upper Farm Chipping Norton Gloucestershire OX7 6QL",
    "addr:housenumber":"norton",
    "addr:postcode":"ox7 6ql",
    "addr:street":"Upper",
    "iso:country":"GB",
    "sg:address":"Upper Farm",
    "sg:city":"Chipping Norton",
    "sg:classifiers":[
        {
            "category":"Farming",
            "subcategory":"Farm",
            "type":"Manufacturing & Wholesale Goods"
        }
    ],
    "sg:phone":"+44 1993 830363",
    "sg:postcode":"OX7 6QL",
    "sg:province":"Gloucestershire",
    "sg:tags":[
        "mixed",
        "crop"
    ],
    "wof:name":"A F Izod",
    "wof:placetype":"venue"
},
  "geometry": {"coordinates":[-1.598984,51.850426],"type":"Point"}
}