{
  "type": "Feature",
  "properties": {
    "addr:full":"Wheatland Rd Leicester Leicestershire LE4 2NJ",
    "addr:postcode":"le4 2nj",
    "addr:street":"Wheatland Rd",
    "iso:country":"GB",
    "sg:address":"Wheatland Rd",
    "sg:city":"Leicester",
    "sg:classifiers":[
        {
            "category":"Community Center",
            "type":"Public Place"
        }
    ],
    "sg:phone":"+44 116 235 6920",
    "sg:postcode":"LE4 2NJ",
    "sg:province":"Leicestershire",
    "sg:tags":[
        "recreation",
        "leisure",
        "centre"
    ],
    "wof:name":"Mowmacre Recreation Centre",
    "wof:placetype":"venue"
},
  "geometry": {"coordinates":[-1.147868,52.667839],"type":"Point"}
}