{
  "type": "Feature",
  "properties": {
    "iso:country":"GB",
    "sg:address":"Victoria Ho, Victoria Rd",
    "sg:city":"Bicester",
    "sg:classifiers":[
        {
            "category":"Health Services",
            "subcategory":"Doctor",
            "type":"Services"
        }
    ],
    "sg:phone":"+44 1869 248585",
    "sg:postcode":"OX6 7PB",
    "sg:province":"Oxfordshire",
    "sg:tags":[
        "practitioners"
    ],
    "wof:name":"J Galuszka & Partners",
    "wof:placetype":"venue"
},
  "geometry": {"coordinates":[-1.15354,51.898022],"type":"Point"}
}