{
  "type": "Feature",
  "properties": {
    "iso:country":"GB",
    "sg:address":"444 Ashton Road",
    "sg:city":"Oldham",
    "sg:classifiers":[
        {
            "category":"Food & Beverages",
            "subcategory":"Fruits & Vegetables",
            "type":"Retail Goods"
        }
    ],
    "sg:postcode":"OL8 3HF",
    "sg:province":"Lancashire",
    "sg:tags":[
        "greengrocer"
    ],
    "wof:name":"Shahid Grocers Ltd",
    "wof:placetype":"venue"
},
  "geometry": {"coordinates":[-2.110909,53.524418],"type":"Point"}
}