{
  "type": "Feature",
  "properties": {
    "iso:country":"GB",
    "sg:address":"Ravensdale, Tunstall",
    "sg:city":"Newcastle",
    "sg:classifiers":[
        {
            "category":"Professional",
            "subcategory":"Computer Services",
            "type":"Services"
        }
    ],
    "sg:phone":"+44 1782 832328",
    "sg:postcode":"ST6 4NU",
    "sg:province":"Staffordshire",
    "sg:tags":[
        "system",
        "software"
    ],
    "wof:name":"H T C Solutions Ltd.",
    "wof:placetype":"venue"
},
  "geometry": {"coordinates":[-2.220220089,53.0539283752],"type":"Point"}
}