{
  "type": "Feature",
  "properties": {
    "iso:country":"GB",
    "sg:address":"Unit 6 Waterside, Wharside Commerce Park, Trafford Park",
    "sg:city":"Manchester",
    "sg:classifiers":[
        {
            "category":"Shopping",
            "subcategory":"Clothing, Apparel, & Fashions",
            "type":"Retail Goods"
        }
    ],
    "sg:phone":"+44 161 931 2550",
    "sg:postcode":"M17 1WD",
    "sg:province":"Cheshire",
    "sg:tags":[
        "menswear"
    ],
    "wof:name":"The Flannels Group Ltd.",
    "wof:placetype":"venue"
},
  "geometry": {"coordinates":[-2.3083589077,53.4681396484],"type":"Point"}
}