{
  "type": "Feature",
  "properties": {
    "iso:country":"GB",
    "sg:address":"The Great Barn, Chalford Park",
    "sg:city":"Oxford",
    "sg:classifiers":[
        {
            "category":"Professional",
            "subcategory":"Management & Consulting",
            "type":"Services"
        }
    ],
    "sg:postcode":"OX7 5QR",
    "sg:province":"Gloucestershire",
    "sg:tags":[
        "consultant",
        "business"
    ],
    "wof:name":"Oxford Resources Ltd.",
    "wof:placetype":"venue"
},
  "geometry": {"coordinates":[-1.5200699568,51.9382591248],"type":"Point"}
}