{
  "type": "Feature",
  "properties": {
    "addr:full":"2 Lincoln Square Hunstanton Norfolk PE36 6DL",
    "addr:housenumber":"2",
    "addr:postcode":"pe36 6dl",
    "addr:street":"Lincoln Square",
    "iso:country":"GB",
    "sg:address":"2 Lincoln Square",
    "sg:city":"Hunstanton",
    "sg:classifiers":[
        {
            "category":"Social Services",
            "subcategory":"Retirement Home",
            "type":"Services"
        }
    ],
    "sg:phone":"+44 1485 534570",
    "sg:postcode":"PE36 6DL",
    "sg:province":"Norfolk",
    "sg:tags":[
        "rest"
    ],
    "wof:name":"Lincoln Lodge Residential",
    "wof:placetype":"venue"
},
  "geometry": {"coordinates":[0.491562,52.942402],"type":"Point"}
}