{
  "type": "Feature",
  "properties": {
    "iso:country":"GB",
    "sg:address":"1 The Close",
    "sg:city":"Salisbury",
    "sg:classifiers":[
        {
            "category":"Education",
            "subcategory":"School",
            "type":"Public Place"
        }
    ],
    "sg:postcode":"SP1 2EQ",
    "sg:province":"Wiltshire",
    "sg:tags":[
        "independent",
        "preparatory"
    ],
    "wof:name":"Salisbury Catherdral School",
    "wof:placetype":"venue"
},
  "geometry": {"coordinates":[-1.791793,51.065205],"type":"Point"}
}