{
  "type": "Feature",
  "properties": {
    "iso:country":"GB",
    "sg:address":"55 Dougrie Drive",
    "sg:city":"Glasgow",
    "sg:classifiers":[
        {
            "category":"Health Services",
            "subcategory":"Dentist",
            "type":"Services"
        }
    ],
    "sg:phone":"+44 141 634 0015",
    "sg:postcode":"G45 9AD",
    "sg:province":"Glasgow City",
    "wof:name":"Dental Surgery",
    "wof:placetype":"venue"
},
  "geometry": {"coordinates":[-4.2346878052,55.8074378967],"type":"Point"}
}