{
  "type": "Feature",
  "properties": {
    "addr:full":"Imperial House, 2-14 High Street Margate Kent CT9 1DH",
    "addr:housenumber":"2-14",
    "addr:postcode":"ct9 1dh",
    "addr:street":"High Street",
    "iso:country":"GB",
    "sg:address":"Imperial House, 2-14 High Street",
    "sg:city":"Margate",
    "sg:classifiers":[
        {
            "category":"Professional",
            "type":"Services"
        }
    ],
    "sg:phone":"+44 1843 226677",
    "sg:postcode":"CT9 1DH",
    "sg:province":"Kent",
    "sg:tags":[
        "directory",
        "pub"
    ],
    "wof:name":"Kent Business Media Ltd.",
    "wof:placetype":"venue"
},
  "geometry": {"coordinates":[1.355318,51.379154],"type":"Point"}
}