{
  "type": "Feature",
  "properties": {
    "addr:full":"15 Court Road, Broomfield Chelmsford Essex CM1 7EW",
    "addr:housenumber":"15",
    "addr:postcode":"cm1 7ew",
    "addr:street":"Court Road",
    "iso:country":"GB",
    "sg:address":"15 Court Road, Broomfield",
    "sg:city":"Chelmsford",
    "sg:classifiers":[
        {
            "category":"Home & Garden",
            "subcategory":"Hardware",
            "type":"Retail Goods"
        }
    ],
    "sg:phone":"+44 1245 442288",
    "sg:postcode":"CM1 7EW",
    "sg:province":"Essex",
    "sg:tags":[
        "lawnmowers",
        "machinery"
    ],
    "wof:name":"A T L Mower Man",
    "wof:placetype":"venue"
},
  "geometry": {"coordinates":[0.472385,51.768372],"type":"Point"}
}