{
  "type": "Feature",
  "properties": {
    "addr:full":"The Dock Office, Trafford Road Salford Greater Manchester M5 2XB",
    "addr:postcode":"m5 2xb",
    "addr:street":"Trafford Road",
    "iso:country":"GB",
    "sg:address":"The Dock Office, Trafford Road",
    "sg:city":"Salford",
    "sg:classifiers":[
        {
            "category":"Shopping",
            "subcategory":"Computers & Home Electronics",
            "type":"Retail Goods"
        }
    ],
    "sg:phone":"+44 161 869 1700",
    "sg:postcode":"M5 2XB",
    "sg:province":"Greater Manchester",
    "wof:name":"Data Connectivity Services",
    "wof:placetype":"venue"
},
  "geometry": {"coordinates":[-2.32564,53.468399],"type":"Point"}
}