{
  "type": "Feature",
  "properties": {
    "addr:full":"Unit 7 Penketh Business Pk, Off Liverpool Rd Warrington Cheshire WA5 2TJ",
    "addr:housenumber":"unit 7 penketh",
    "addr:postcode":"wa5 2tj",
    "addr:street":"Business Pk Off Liverpool Rd",
    "iso:country":"GB",
    "sg:address":"Unit 7 Penketh Business Pk, Off Liverpool Rd",
    "sg:city":"Warrington",
    "sg:classifiers":[
        {
            "category":"Manufacturing",
            "subcategory":"Petroleum Products",
            "type":"Manufacturing & Wholesale Goods"
        }
    ],
    "sg:postcode":"WA5 2TJ",
    "sg:province":"Cheshire",
    "sg:tags":[
        "double",
        "glazing"
    ],
    "wof:name":"P R Panels (Warrington) Ltd",
    "wof:placetype":"venue"
},
  "geometry": {"coordinates":[-2.6385300159,53.3864212036],"type":"Point"}
}