{
  "type": "Feature",
  "properties": {
    "iso:country":"GB",
    "sg:address":"Unit 10 County Walk",
    "sg:city":"Taunton",
    "sg:classifiers":[
        {
            "category":"Food & Beverages",
            "subcategory":"Fruits & Vegetables",
            "type":"Retail Goods"
        }
    ],
    "sg:phone":"+44 1823 332893",
    "sg:postcode":"TA1 3TZ",
    "sg:province":"Somerset",
    "sg:tags":[
        "greengrocer"
    ],
    "wof:name":"Sanders Retail",
    "wof:placetype":"venue"
},
  "geometry": {"coordinates":[-3.0988540649,51.014465332],"type":"Point"}
}