{
  "type": "Feature",
  "properties": {
    "addr:full":"Castle Vale, Off Railway Street Berwick-upon-tweed Northumberland TD15 1NF",
    "addr:postcode":"td15 1nf",
    "addr:street":"Off Railway Street;Northumberland",
    "iso:country":"GB",
    "sg:address":"Castle Vale, Off Railway Street",
    "sg:city":"Berwick-upon-tweed",
    "sg:classifiers":[
        {
            "category":"Organizations",
            "subcategory":"Community Association",
            "type":"Services"
        }
    ],
    "sg:phone":"+44 1289 304266",
    "sg:postcode":"TD15 1NF",
    "sg:province":"Northumberland",
    "sg:tags":[
        "society",
        "housing"
    ],
    "wof:name":"Castle Vale",
    "wof:placetype":"venue"
},
  "geometry": {"coordinates":[-2.0117239952,55.7794265747],"type":"Point"}
}