{
  "type": "Feature",
  "properties": {
    "iso:country":"GB",
    "sg:address":"Unit 5 Caldervale Road, Caldervale Industrial Estate",
    "sg:city":"Wakefield",
    "sg:classifiers":[
        {
            "category":"Manufacturing",
            "subcategory":"Metals",
            "type":"Manufacturing & Wholesale Goods"
        }
    ],
    "sg:phone":"+44 1924 266635",
    "sg:postcode":"WF4 5ER",
    "sg:province":"West Yorkshire",
    "sg:tags":[
        "steel",
        "fabricator",
        "erectors"
    ],
    "wof:name":"A & T Fabrication Ltd.",
    "wof:placetype":"venue"
},
  "geometry": {"coordinates":[-1.542091,53.654537],"type":"Point"}
}