{
  "type": "Feature",
  "properties": {
    "addr:full":"129 Hunsworth Lane Cleckheaton West Yorkshire BD19 4DR",
    "addr:housenumber":"129",
    "addr:postcode":"bd19 4dr",
    "addr:street":"Hunsworth Lane",
    "iso:country":"GB",
    "sg:address":"129 Hunsworth Lane",
    "sg:city":"Cleckheaton",
    "sg:classifiers":[
        {
            "category":"Retail",
            "subcategory":"Auto Repair",
            "type":"Services"
        }
    ],
    "sg:postcode":"BD19 4DR",
    "sg:province":"West Yorkshire",
    "sg:tags":[
        "modification",
        "garage"
    ],
    "wof:name":"West Riding Lubrication Co",
    "wof:placetype":"venue"
},
  "geometry": {"coordinates":[-1.7153710127,53.7389144897],"type":"Point"}
}