{
  "type": "Feature",
  "properties": {
    "iso:country":"GB",
    "sg:address":"North Road",
    "sg:city":"Minehead",
    "sg:classifiers":[
        {
            "category":"Organizations",
            "subcategory":"Non-profit Organization",
            "type":"Services"
        }
    ],
    "sg:phone":"+44 1643 702400",
    "sg:postcode":"TA24 5QW",
    "sg:province":"Somerset",
    "sg:tags":[
        "organisation",
        "voluntary",
        "charity"
    ],
    "wof:name":"St Johns Ambulance Brigade",
    "wof:placetype":"venue"
},
  "geometry": {"coordinates":[-3.4734869003,51.2082290649],"type":"Point"}
}