{
  "type": "Feature",
  "properties": {
    "addr:full":"Moray Street, Blackford Auchterarder Perth and Kinross PH4 1PY",
    "addr:postcode":"ph4 1py",
    "addr:street":"Moray Street",
    "iso:country":"GB",
    "sg:address":"Moray Street, Blackford",
    "sg:city":"Auchterarder",
    "sg:classifiers":[
        {
            "category":"Government",
            "subcategory":"Post Office",
            "type":"Public Place"
        }
    ],
    "sg:phone":"+44 1764 682245",
    "sg:postcode":"PH4 1PY",
    "sg:province":"Perth and Kinross",
    "wof:name":"Blackford Post Office",
    "wof:placetype":"venue"
},
  "geometry": {"coordinates":[-3.7805140018,56.2610397339],"type":"Point"}
}