{
  "type": "Feature",
  "properties": {
    "iso:country":"GB",
    "sg:address":"Unit A1 Haybrook Industrial, Estate Halesfield 9",
    "sg:city":"Telford",
    "sg:classifiers":[
        {
            "category":"Building & Trades",
            "subcategory":"Plumbing",
            "type":"Services"
        }
    ],
    "sg:phone":"+44 1952 242341",
    "sg:postcode":"TF9 4QW",
    "sg:province":"Shropshire",
    "sg:tags":[
        "merchant",
        "plumbers'"
    ],
    "wof:name":"Framexpress Ltd.",
    "wof:placetype":"venue"
},
  "geometry": {"coordinates":[-2.38915,52.925415],"type":"Point"}
}