{
  "type": "Feature",
  "properties": {
    "iso:country":"GB",
    "sg:address":"8 The Cent Crescent, Borough Grn",
    "sg:city":"Sevenoaks",
    "sg:classifiers":[
        {
            "category":"Retail",
            "subcategory":"Driving School",
            "type":"Services"
        }
    ],
    "sg:postcode":"TN15 8EE",
    "sg:province":"Kent",
    "wof:name":"M & M's School of Motoring",
    "wof:placetype":"venue"
},
  "geometry": {"coordinates":[0.310682,51.294777],"type":"Point"}
}