{
  "type": "Feature",
  "properties": {
    "iso:country":"GB",
    "sg:address":"127 Engineer Road, West Wilts Trading Estate",
    "sg:city":"Westbury",
    "sg:classifiers":[
        {
            "category":"Autos & Motor Vehicles",
            "subcategory":"Automobile Sales",
            "type":"Retail Goods"
        }
    ],
    "sg:phone":"+44 1373 823603",
    "sg:postcode":"BA13 4JW",
    "sg:province":"Wiltshire",
    "sg:tags":[
        "specialist",
        "sales",
        "car",
        "classic"
    ],
    "sg:website":"http://-",
    "wof:name":"T T Workshops Ltd",
    "wof:placetype":"venue"
},
  "geometry": {"coordinates":[-2.210266,51.276215],"type":"Point"}
}