{
  "type": "Feature",
  "properties": {
    "addr:full":"Deakin Leas Tonbridge Kent TN9 2JR",
    "addr:postcode":"tn9 2jr",
    "iso:country":"GB",
    "sg:address":"Deakin Leas",
    "sg:city":"Tonbridge",
    "sg:classifiers":[
        {
            "category":"Education",
            "subcategory":"School",
            "type":"Public Place"
        }
    ],
    "sg:phone":"+44 1732 365125",
    "sg:postcode":"TN9 2JR",
    "sg:province":"Kent",
    "sg:tags":[
        "college",
        "local",
        "authority"
    ],
    "sg:website":"http://www.tgs.kent.sch.uk",
    "wof:name":"Tonbridge Grammar School for Girls",
    "wof:placetype":"venue"
},
  "geometry": {"coordinates":[0.273506,51.184998],"type":"Point"}
}