{
  "type": "Feature",
  "properties": {
    "addr:full":"178 Shirley Rd Southampton Hampshire SO15 3FN",
    "addr:housenumber":"178",
    "addr:postcode":"so15 3fn",
    "addr:street":"Shirley Rd",
    "iso:country":"GB",
    "sg:address":"178 Shirley Rd",
    "sg:city":"Southampton",
    "sg:classifiers":[
        {
            "category":"Fast Food",
            "type":"Food & Drink"
        }
    ],
    "sg:postcode":"SO15 3FN",
    "sg:province":"Hampshire",
    "sg:tags":[
        "away",
        "take"
    ],
    "wof:name":"Kalirai,S,",
    "wof:placetype":"venue"
},
  "geometry": {"coordinates":[-1.4229079485,50.9138870239],"type":"Point"}
}