{
  "type": "Feature",
  "properties": {
    "iso:country":"GB",
    "sg:address":"Lovers Leap",
    "sg:city":"Gretna",
    "sg:classifiers":[
        {
            "category":"Restaurant",
            "type":"Food & Drink"
        }
    ],
    "sg:phone":"+44 1461 337917",
    "sg:postcode":"DG16 5EA",
    "sg:province":"Cumbria",
    "wof:name":"Anvil Inn The",
    "wof:placetype":"venue"
},
  "geometry": {"coordinates":[-3.0654540062,54.9954414368],"type":"Point"}
}