{
  "type": "Feature",
  "properties": {
    "addr:full":"8 Holywell Close Poole Dorset BH17 9BG",
    "addr:housenumber":"8",
    "addr:postcode":"bh17 9bg",
    "addr:street":"Holywell Close",
    "iso:country":"GB",
    "sg:address":"8 Holywell Close",
    "sg:city":"Poole",
    "sg:classifiers":[
        {
            "category":"Professional",
            "subcategory":"Engineering",
            "type":"Services"
        },
        {
            "category":"Building & Trades",
            "subcategory":"Electrical",
            "type":"Services"
        }
    ],
    "sg:phone":"+44 1202 697537",
    "sg:postcode":"BH17 9BG",
    "sg:province":"Dorset",
    "sg:tags":[
        "engineer",
        "electrician",
        "contractor"
    ],
    "wof:name":"H Kellaway Electrical Contractors",
    "wof:placetype":"venue"
},
  "geometry": {"coordinates":[-1.974256,50.755405],"type":"Point"}
}