{
  "type": "Feature",
  "properties": {
    "iso:country":"GB",
    "sg:address":"Staffords Grn Farm, Staffords Grn, Corton Denham",
    "sg:city":"Sherborne",
    "sg:classifiers":[
        {
            "category":"Farming",
            "subcategory":"Livestock Farm",
            "type":"Manufacturing & Wholesale Goods"
        }
    ],
    "sg:postcode":"DT9 4LY",
    "sg:province":"Dorset",
    "sg:tags":[
        "others"
    ],
    "wof:name":"David Jeffrey Foxwell",
    "wof:placetype":"venue"
},
  "geometry": {"coordinates":[-2.521419,50.997807],"type":"Point"}
}