{
  "type": "Feature",
  "properties": {
    "iso:country":"GB",
    "sg:address":"16 Osram Road, East Lane",
    "sg:city":"Wembley",
    "sg:classifiers":[
        {
            "category":"Home & Garden",
            "subcategory":"Hardware",
            "type":"Retail Goods"
        }
    ],
    "sg:phone":"+44 20 8908 3003",
    "sg:postcode":"HA9 7NG",
    "sg:province":"Greater London",
    "sg:tags":[
        "component",
        "electronic"
    ],
    "wof:name":"Sontranic Ltd.",
    "wof:placetype":"venue"
},
  "geometry": {"coordinates":[-0.295539,51.552963],"type":"Point"}
}