{
  "type": "Feature",
  "properties": {
    "iso:country":"GB",
    "sg:address":"Paragon Centre, Australia Rd",
    "sg:city":"Shepherd's Bush",
    "sg:classifiers":[
        {
            "category":"Professional",
            "subcategory":"Secretarial Services",
            "type":"Services"
        }
    ],
    "sg:phone":"+44 20 8749 9557",
    "sg:postcode":"W12 7PH",
    "sg:province":"Greater London",
    "wof:name":"Business Progress",
    "wof:placetype":"venue"
},
  "geometry": {"coordinates":[-0.2316399962,51.5106086731],"type":"Point"}
}