{
  "type": "Feature",
  "properties": {
    "iso:country":"GB",
    "sg:address":"61 Halesowen Road, Netherton",
    "sg:city":"Dudley",
    "sg:classifiers":[
        {
            "category":"Personal",
            "subcategory":"Beauty Salon",
            "type":"Services"
        },
        {
            "category":"Personal",
            "subcategory":"Barber",
            "type":"Services"
        }
    ],
    "sg:phone":"+44 1384 868888",
    "sg:postcode":"DY2 9PY",
    "sg:province":"West Midlands",
    "sg:tags":[
        "unisex",
        "hairdresser"
    ],
    "wof:name":"Tracey Smith",
    "wof:placetype":"venue"
},
  "geometry": {"coordinates":[-2.0810649395,52.4887619019],"type":"Point"}
}