{
  "type": "Feature",
  "properties": {
    "iso:country":"GB",
    "sg:address":"9 Peaks Avenue, New Waltham",
    "sg:city":"Grimsby",
    "sg:classifiers":[
        {
            "category":"Building & Trades",
            "subcategory":"Construction",
            "type":"Services"
        }
    ],
    "sg:phone":"+44 1472 816058",
    "sg:postcode":"DN36 4LJ",
    "sg:province":"Lincolnshire",
    "sg:tags":[
        "glazier",
        "decorator",
        "painter"
    ],
    "wof:name":"R Chamberlain",
    "wof:placetype":"venue"
},
  "geometry": {"coordinates":[-0.062513,53.527687],"type":"Point"}
}