{
  "type": "Feature",
  "properties": {
    "iso:country":"GB",
    "sg:address":"11 Lismore Place, Newton Mearns",
    "sg:city":"Glasgow",
    "sg:classifiers":[
        {
            "category":"Professional",
            "subcategory":"Business Services",
            "type":"Services"
        }
    ],
    "sg:phone":"+44 141 616 3385",
    "sg:postcode":"G77 6UQ",
    "sg:province":"East Ayrshire",
    "sg:tags":[
        "import",
        "export",
        "agent"
    ],
    "wof:name":"Pearl Lion Ltd.",
    "wof:placetype":"venue"
},
  "geometry": {"coordinates":[-4.348043,55.779655],"type":"Point"}
}