{
  "type": "Feature",
  "properties": {
    "addr:full":"6 Echo Square Gravesend Kent DA12 1NP",
    "addr:housenumber":"6",
    "addr:postcode":"da12 1np",
    "addr:street":"Echo Square",
    "iso:country":"GB",
    "sg:address":"6 Echo Square",
    "sg:city":"Gravesend",
    "sg:classifiers":[
        {
            "category":"Autos & Motor Vehicles",
            "subcategory":"Auto Supplies",
            "type":"Retail Goods"
        },
        {
            "category":"Shopping",
            "type":"Retail Goods"
        }
    ],
    "sg:phone":"+44 1474 325920",
    "sg:postcode":"DA12 1NP",
    "sg:province":"Kent",
    "sg:tags":[
        "car",
        "part",
        "accessory"
    ],
    "wof:name":"BIG M MOTOR SPARES LTD",
    "wof:placetype":"venue"
},
  "geometry": {"coordinates":[0.37466,51.431423],"type":"Point"}
}