{
  "type": "Feature",
  "properties": {
    "iso:country":"GB",
    "sg:address":"18 Furzehill",
    "sg:city":"Chard",
    "sg:classifiers":[
        {
            "category":"Arts & Performance",
            "subcategory":"Music",
            "type":"Entertainment"
        }
    ],
    "sg:postcode":"TA20 1AS",
    "sg:province":"Devon",
    "sg:tags":[
        "mobile",
        "disco"
    ],
    "wof:name":"M D Roadshow",
    "wof:placetype":"venue"
},
  "geometry": {"coordinates":[-2.9589269161,50.8785476685],"type":"Point"}
}