{
  "type": "Feature",
  "properties": {
    "addr:full":"Rear Of 96 Broadway Bexleyheath Kent DA6 7DE",
    "addr:housenumber":"rear of 96",
    "addr:postcode":"da6 7de",
    "addr:street":"Broadway",
    "iso:country":"GB",
    "sg:address":"Rear Of 96 Broadway",
    "sg:city":"Bexleyheath",
    "sg:classifiers":[
        {
            "category":"Professional",
            "subcategory":"Detective & Security Services",
            "type":"Services"
        }
    ],
    "sg:phone":"+44 20 8857 4444",
    "sg:postcode":"DA6 7DE",
    "sg:province":"Kent",
    "wof:name":"Bexley Security Services Ltd",
    "wof:placetype":"venue"
},
  "geometry": {"coordinates":[0.1451600045,51.4566917419],"type":"Point"}
}