{
  "type": "Feature",
  "properties": {
    "iso:country":"GB",
    "sg:address":"14 High Street, Overstrand",
    "sg:city":"Cromer",
    "sg:classifiers":[
        {
            "category":"Health Services",
            "subcategory":"Nursing And Care Facility",
            "type":"Services"
        }
    ],
    "sg:phone":"+44 1263 579221",
    "sg:postcode":"NR27 0AB",
    "sg:province":"Norfolk",
    "sg:tags":[
        "home"
    ],
    "wof:name":"Elizabeth Fitzroy",
    "wof:placetype":"venue"
},
  "geometry": {"coordinates":[1.343724,52.91695],"type":"Point"}
}