{
  "type": "Feature",
  "properties": {
    "iso:country":"GB",
    "sg:address":"347 Burgess, Bassett",
    "sg:city":"Southampton",
    "sg:classifiers":[
        {
            "category":"Building & Trades",
            "subcategory":"Construction",
            "type":"Services"
        }
    ],
    "sg:postcode":"SO16 3BA",
    "sg:province":"Hampshire",
    "sg:tags":[
        "builder"
    ],
    "wof:name":"R Stone",
    "wof:placetype":"venue"
},
  "geometry": {"coordinates":[-1.388231,50.938702],"type":"Point"}
}