{
  "type": "Feature",
  "properties": {
    "addr:full":"69 Paynesholm Peterborough Cambridgeshire PE4 7BQ",
    "addr:housenumber":"69",
    "addr:postcode":"pe4 7bq",
    "addr:street":"Paynesholm Peterborough",
    "iso:country":"GB",
    "sg:address":"69 Paynesholm",
    "sg:city":"Peterborough",
    "sg:classifiers":[
        {
            "category":"Professional",
            "subcategory":"Engineering",
            "type":"Services"
        }
    ],
    "sg:phone":"+44 1733 573534",
    "sg:postcode":"PE4 7BQ",
    "sg:province":"Cambridgeshire",
    "sg:tags":[
        "consulting",
        "engineer"
    ],
    "wof:name":"K & M Assessors",
    "wof:placetype":"venue"
},
  "geometry": {"coordinates":[-0.2404430062,52.6045532227],"type":"Point"}
}