{
  "type": "Feature",
  "properties": {
    "addr:full":"1 Osborne Place Todmorden Lancashire OL14 5BQ",
    "addr:housenumber":"1",
    "addr:postcode":"ol14 5bq",
    "addr:street":"Osborne Place",
    "iso:country":"GB",
    "sg:address":"1 Osborne Place",
    "sg:city":"Todmorden",
    "sg:classifiers":[
        {
            "category":"Professional",
            "subcategory":"Computer Services",
            "type":"Services"
        }
    ],
    "sg:phone":"+44 1706 816854",
    "sg:postcode":"OL14 5BQ",
    "sg:province":"Lancashire",
    "sg:tags":[
        "system",
        "software"
    ],
    "wof:name":"David Jackson",
    "wof:placetype":"venue"
},
  "geometry": {"coordinates":[-2.0906829834,53.7146453857],"type":"Point"}
}