{
  "type": "Feature",
  "properties": {
    "iso:country":"GB",
    "sg:address":"5 Anchor Crescent, Knaphill",
    "sg:city":"Woking",
    "sg:classifiers":[
        {
            "category":"Food & Beverages",
            "subcategory":"Bakery",
            "type":"Retail Goods"
        }
    ],
    "sg:phone":"+44 1483 481616",
    "sg:postcode":"GU21 2PD",
    "sg:province":"Surrey",
    "sg:tags":[
        "baker"
    ],
    "wof:name":"Homebake",
    "wof:placetype":"venue"
},
  "geometry": {"coordinates":[-0.615927,51.318832],"type":"Point"}
}