{
  "type": "Feature",
  "properties": {
    "addr:full":"4 Newbiggin Richmond North Yorkshire DL10 4DT",
    "addr:housenumber":"4",
    "addr:postcode":"dl10 4dt",
    "addr:street":"Newbiggin Richmond",
    "iso:country":"GB",
    "sg:address":"4 Newbiggin",
    "sg:city":"Richmond",
    "sg:classifiers":[
        {
            "category":"Food & Beverages",
            "subcategory":"Meat & Fish",
            "type":"Retail Goods"
        }
    ],
    "sg:phone":"+44 1748 822937",
    "sg:postcode":"DL10 4DT",
    "sg:province":"North Yorkshire",
    "sg:tags":[
        "chip"
    ],
    "wof:name":"Richmond Fisheries",
    "wof:placetype":"venue"
},
  "geometry": {"coordinates":[-1.739727,54.40387],"type":"Point"}
}