{
  "type": "Feature",
  "properties": {
    "addr:full":"29 Gerrard Road London Greater London N1 8BA",
    "addr:housenumber":"29",
    "addr:postcode":"n1 8ba",
    "addr:street":"Gerrard Road",
    "iso:country":"GB",
    "sg:address":"29 Gerrard Road",
    "sg:city":"London",
    "sg:classifiers":[
        {
            "category":"Professional",
            "subcategory":"Art Services",
            "type":"Services"
        }
    ],
    "sg:postcode":"N1 8BA",
    "sg:province":"Greater London",
    "sg:tags":[
        "consultant",
        "design"
    ],
    "wof:name":"Tim Cross Design Associates",
    "wof:placetype":"venue"
},
  "geometry": {"coordinates":[-0.099957,51.533718],"type":"Point"}
}