{
  "type": "Feature",
  "properties": {
    "iso:country":"GB",
    "sg:address":"156 Grays Inn Rd",
    "sg:city":"Bloomsbury",
    "sg:classifiers":[
        {
            "category":"Professional",
            "subcategory":"Advertising",
            "type":"Services"
        }
    ],
    "sg:phone":"+44 20 7209 5073",
    "sg:postcode":"WC1X 8ED",
    "sg:province":"Greater London",
    "sg:tags":[
        "agency"
    ],
    "wof:name":"Rockwell Advertising",
    "wof:placetype":"venue"
},
  "geometry": {"coordinates":[-0.112999,51.521049],"type":"Point"}
}