{
  "type": "Feature",
  "properties": {
    "addr:full":"1 The Furlong Ringwood Dorset BH24 1AT",
    "addr:housenumber":"1",
    "addr:postcode":"bh24 1at",
    "addr:street":"The Furlong",
    "iso:country":"GB",
    "sg:address":"1 The Furlong",
    "sg:city":"Ringwood",
    "sg:classifiers":[
        {
            "category":"Shopping",
            "subcategory":"Shoes",
            "type":"Retail Goods"
        }
    ],
    "sg:phone":"+44 1425 476399",
    "sg:postcode":"BH24 1AT",
    "sg:province":"Dorset",
    "sg:tags":[
        "shop"
    ],
    "wof:name":"Stead & Simpson Ltd.",
    "wof:placetype":"venue"
},
  "geometry": {"coordinates":[-1.7929890156,50.8463287354],"type":"Point"}
}