{
  "type": "Feature",
  "properties": {
    "iso:country":"GB",
    "sg:address":"102 Wolrbury Road, Wolbury",
    "sg:city":"Weston-super-mare",
    "sg:classifiers":[
        {
            "category":"Building & Trades",
            "subcategory":"Construction",
            "type":"Services"
        }
    ],
    "sg:postcode":"BS22 9TG",
    "sg:province":"Somerset",
    "sg:tags":[
        "roofing"
    ],
    "wof:name":"Woodspring Roofing",
    "wof:placetype":"venue"
},
  "geometry": {"coordinates":[-2.94041,51.36393],"type":"Point"}
}