{
  "type": "Feature",
  "properties": {
    "addr:full":"Unit 2 Great Grovehurst Farm, Grovehurst Road Sittingbourne Kent ME9 8RB",
    "addr:housenumber":"unit 2",
    "addr:postcode":"me9 8rb",
    "addr:street":"Great Grovehurst Farm Grovehurst Road",
    "iso:country":"GB",
    "sg:address":"Unit 2 Great Grovehurst Farm, Grovehurst Road",
    "sg:city":"Sittingbourne",
    "sg:classifiers":[
        {
            "category":"Shopping",
            "subcategory":"Pets & Pet Supplies",
            "type":"Retail Goods"
        }
    ],
    "sg:phone":"+44 1795 476561",
    "sg:postcode":"ME9 8RB",
    "sg:province":"Kent",
    "sg:tags":[
        "food"
    ],
    "wof:name":"Unipet International Ltd.",
    "wof:placetype":"venue"
},
  "geometry": {"coordinates":[0.7340260148,51.3671226501],"type":"Point"}
}