{
  "type": "Feature",
  "properties": {
    "iso:country":"GB",
    "sg:address":"79 Josephs Road",
    "sg:city":"Guildford",
    "sg:classifiers":[
        {
            "category":"Professional",
            "subcategory":"Computer Services",
            "type":"Services"
        }
    ],
    "sg:phone":"+44 1483 599700",
    "sg:postcode":"GU1 1DN",
    "sg:province":"Surrey",
    "sg:tags":[
        "system",
        "software"
    ],
    "wof:name":"London Computer Solution Ltd.",
    "wof:placetype":"venue"
},
  "geometry": {"coordinates":[-0.5767800212,51.2478065491],"type":"Point"}
}