{
  "type": "Feature",
  "properties": {
    "iso:country":"GB",
    "sg:address":"5 Hudson Close, Lidlington",
    "sg:city":"Bedford",
    "sg:classifiers":[
        {
            "category":"Professional",
            "subcategory":"Computer Services",
            "type":"Services"
        }
    ],
    "sg:phone":"+44 1525 840496",
    "sg:postcode":"MK43 0RE",
    "sg:province":"Bedfordshire",
    "sg:tags":[
        "system",
        "software"
    ],
    "wof:name":"Petibonum Ltd.",
    "wof:placetype":"venue"
},
  "geometry": {"coordinates":[-0.559561,52.042358],"type":"Point"}
}