{
  "type": "Feature",
  "properties": {
    "addr:full":"Windsor Center, Windsor Street London Greater London N1 8QH",
    "addr:postcode":"n1 8qh",
    "addr:street":"Windsor Street",
    "iso:country":"GB",
    "sg:address":"Windsor Center, Windsor Street",
    "sg:city":"London",
    "sg:classifiers":[
        {
            "category":"Communications",
            "subcategory":"Film & Video Production",
            "type":"Services"
        }
    ],
    "sg:phone":"+44 20 7359 3986",
    "sg:postcode":"N1 8QH",
    "sg:province":"Greater London",
    "sg:tags":[
        "recording",
        "studio"
    ],
    "wof:name":"Alchemea Ltd.",
    "wof:placetype":"venue"
},
  "geometry": {"coordinates":[-0.0988859981,51.5375022888],"type":"Point"}
}