{
  "type": "Feature",
  "properties": {
    "iso:country":"GB",
    "sg:address":"174 London Road",
    "sg:city":"Southend-on-sea",
    "sg:classifiers":[
        {
            "category":"Professional",
            "subcategory":"Printing & Photocopies",
            "type":"Services"
        }
    ],
    "sg:phone":"+44 1702 338754",
    "sg:postcode":"SS1 1PH",
    "sg:province":"Essex",
    "sg:tags":[
        "engraving"
    ],
    "wof:name":"E J Woods",
    "wof:placetype":"venue"
},
  "geometry": {"coordinates":[0.7028719783,51.5399208069],"type":"Point"}
}