{
  "type": "Feature",
  "properties": {
    "addr:full":"30 The Medway, Summit Heywood Lancashire OL10 4SP",
    "addr:housenumber":"30",
    "addr:postcode":"ol10 4sp",
    "addr:street":"The",
    "iso:country":"GB",
    "sg:address":"30 The Medway, Summit",
    "sg:city":"Heywood",
    "sg:classifiers":[
        {
            "category":"Professional",
            "subcategory":"Detective & Security Services",
            "type":"Services"
        }
    ],
    "sg:postcode":"OL10 4SP",
    "sg:province":"Lancashire",
    "sg:tags":[
        "alarm",
        "burglar",
        "system"
    ],
    "wof:name":"Bradley,James & John,",
    "wof:placetype":"venue"
},
  "geometry": {"coordinates":[-2.2341439724,53.5976982117],"type":"Point"}
}