{
  "type": "Feature",
  "properties": {
    "iso:country":"GB",
    "sg:address":"122 Birch Grove, Hempstead",
    "sg:city":"Gillingham",
    "sg:classifiers":[
        {
            "category":"Arts & Performance",
            "subcategory":"Music",
            "type":"Entertainment"
        }
    ],
    "sg:phone":"+44 1634 233723",
    "sg:postcode":"ME7 3RG",
    "sg:province":"Kent",
    "sg:tags":[
        "mobile",
        "disco"
    ],
    "wof:name":"Hi-lite",
    "wof:placetype":"venue"
},
  "geometry": {"coordinates":[0.571678,51.346203],"type":"Point"}
}