{
  "type": "Feature",
  "properties": {
    "addr:full":"Castleton Quarry Lane, Kelsall Tarporley Cheshire CW6 0PD",
    "addr:postcode":"cw6 0pd",
    "addr:street":"Quarry Lane",
    "iso:country":"GB",
    "sg:address":"Castleton Quarry Lane, Kelsall",
    "sg:city":"Tarporley",
    "sg:classifiers":[
        {
            "category":"Shopping",
            "type":"Retail Goods"
        }
    ],
    "sg:postcode":"CW6 0PD",
    "sg:province":"Cheshire",
    "sg:tags":[
        "merchant"
    ],
    "wof:name":"David Glover Seedsman",
    "wof:placetype":"venue"
},
  "geometry": {"coordinates":[-2.668755,53.159355],"type":"Point"}
}