{
  "type": "Feature",
  "properties": {
    "iso:country":"GB",
    "sg:address":"Unit 33, Suttons Business Park, Sutton Park Avenue",
    "sg:city":"Reading",
    "sg:classifiers":[
        {
            "category":"Professional",
            "subcategory":"Printing & Photocopies",
            "type":"Services"
        }
    ],
    "sg:phone":"+44 118 966 9859",
    "sg:postcode":"RG6 1AZ",
    "sg:province":"Berkshire",
    "sg:tags":[
        "process",
        "screen",
        "printer"
    ],
    "wof:name":"A P Screen Printers Ltd.",
    "wof:placetype":"venue"
},
  "geometry": {"coordinates":[-0.94141,51.457748],"type":"Point"}
}