{
  "type": "Feature",
  "properties": {
    "addr:full":"Telegraph Farm, Hill Road, Carleton Rode Norwich Norfolk NR16 1NG",
    "addr:postcode":"nr16 1ng",
    "addr:street":"Farm Hill Road;Norwich",
    "iso:country":"GB",
    "sg:address":"Telegraph Farm, Hill Road, Carleton Rode",
    "sg:city":"Norwich",
    "sg:classifiers":[
        {
            "category":"Home & Garden",
            "subcategory":"Garden Supply",
            "type":"Retail Goods"
        },
        {
            "category":"Farming",
            "subcategory":"Livestock Farm",
            "type":"Manufacturing & Wholesale Goods"
        }
    ],
    "sg:phone":"+44 1953 789204",
    "sg:postcode":"NR16 1NG",
    "sg:province":"Norfolk",
    "sg:tags":[
        "bulb",
        "grower",
        "others"
    ],
    "wof:name":"William Jackson & Son",
    "wof:placetype":"venue"
},
  "geometry": {"coordinates":[1.099605,52.495911],"type":"Point"}
}