{
  "type": "Feature",
  "properties": {
    "addr:full":"Derby Road, Wirksworth Matlock Derbyshire DE4 4BG",
    "addr:postcode":"de4 4bg",
    "addr:street":"Derby Road",
    "iso:country":"GB",
    "sg:address":"Derby Road, Wirksworth",
    "sg:city":"Matlock",
    "sg:classifiers":[
        {
            "category":"Retail",
            "subcategory":"Auto Repair",
            "type":"Services"
        }
    ],
    "sg:postcode":"DE4 4BG",
    "sg:province":"Derbyshire",
    "sg:tags":[
        "body",
        "car"
    ],
    "wof:name":"Terry Mills",
    "wof:placetype":"venue"
},
  "geometry": {"coordinates":[-1.5740560293,53.0822143555],"type":"Point"}
}