{
  "type": "Feature",
  "properties": {
    "addr:full":"The Lodge, 42 Moss Rd, Style Wilmslow Stockport Cheshire SK7 1EH",
    "addr:housenumber":"42",
    "addr:postcode":"sk7 1eh",
    "addr:street":"Moss Rd",
    "iso:country":"GB",
    "sg:address":"The Lodge, 42 Moss Rd, Style Wilmslow",
    "sg:city":"Stockport",
    "sg:classifiers":[
        {
            "category":"Building & Trades",
            "subcategory":"Landscaping Services",
            "type":"Services"
        }
    ],
    "sg:phone":"+44 161 439 3806",
    "sg:postcode":"SK7 1EH",
    "sg:province":"Cheshire",
    "sg:tags":[
        "designer",
        "architect",
        "landscape"
    ],
    "wof:name":"Clive Scott Garden Designers",
    "wof:placetype":"venue"
},
  "geometry": {"coordinates":[-2.1804499626,53.3555793762],"type":"Point"}
}