{
  "type": "Feature",
  "properties": {
    "iso:country":"GB",
    "sg:address":"8 Henry Street",
    "sg:city":"Lytham St Annes",
    "sg:classifiers":[
        {
            "category":"Retail",
            "subcategory":"Laundry & Dry Cleaning",
            "type":"Services"
        }
    ],
    "sg:phone":"+44 1253 730456",
    "sg:postcode":"FY8 5LE",
    "sg:province":"Lancashire",
    "sg:tags":[
        "cleaner",
        "alteration"
    ],
    "wof:name":"A Haddock",
    "wof:placetype":"venue"
},
  "geometry": {"coordinates":[-2.963838,53.736389],"type":"Point"}
}