{
  "type": "Feature",
  "properties": {
    "addr:full":"20 Manchester Road Burnley Lancashire BB11 1HH",
    "addr:housenumber":"20",
    "addr:postcode":"bb11 1hh",
    "addr:street":"Manchester Road",
    "iso:country":"GB",
    "sg:address":"20 Manchester Road",
    "sg:city":"Burnley",
    "sg:classifiers":[
        {
            "category":"Real Estate",
            "subcategory":"Real Estate Agent",
            "type":"Services"
        }
    ],
    "sg:phone":"+44 1282 429191",
    "sg:postcode":"BB11 1HH",
    "sg:province":"Lancashire",
    "wof:name":"Reeds Rains Ltd.",
    "wof:placetype":"venue"
},
  "geometry": {"coordinates":[-2.243127,53.788418],"type":"Point"}
}