{
  "type": "Feature",
  "properties": {
    "iso:country":"GB",
    "sg:address":"26 The Broadway",
    "sg:city":"Haywards Heath",
    "sg:classifiers":[
        {
            "category":"Shopping",
            "subcategory":"Thrift Store",
            "type":"Retail Goods"
        }
    ],
    "sg:phone":"+44 1444 412247",
    "sg:postcode":"RH16 3AL",
    "sg:province":"East Sussex",
    "sg:tags":[
        "shop",
        "charity"
    ],
    "wof:name":"St. Catherine's Hospice Charity Shop",
    "wof:placetype":"venue"
},
  "geometry": {"coordinates":[-0.105475001,51.0007820129],"type":"Point"}
}