{
  "type": "Feature",
  "properties": {
    "iso:country":"GB",
    "sg:address":"Brooksden, High Street",
    "sg:city":"Cranbrook",
    "sg:classifiers":[
        {
            "category":"Retail",
            "subcategory":"Veterinary Services",
            "type":"Services"
        }
    ],
    "sg:phone":"+44 1580 713381",
    "sg:postcode":"TN17 3DT",
    "sg:province":"Kent",
    "sg:tags":[
        "surgeon",
        "activity"
    ],
    "wof:name":"Pierson Stewart & Partners",
    "wof:placetype":"venue"
},
  "geometry": {"coordinates":[0.535245,51.0965],"type":"Point"}
}