{
  "type": "Feature",
  "properties": {
    "addr:full":"Underlyn Farm, Marden Tonbridge Kent TN12 9BQ",
    "addr:postcode":"tn12 9bq",
    "addr:street":"Tonbridge",
    "iso:country":"GB",
    "sg:address":"Underlyn Farm, Marden",
    "sg:city":"Tonbridge",
    "sg:classifiers":[
        {
            "category":"Organizations",
            "subcategory":"Community Association",
            "type":"Services"
        }
    ],
    "sg:postcode":"TN12 9BQ",
    "sg:province":"Kent",
    "sg:tags":[
        "relation",
        "public"
    ],
    "wof:name":"Pearson Young Ltd",
    "wof:placetype":"venue"
},
  "geometry": {"coordinates":[0.489726007,51.176322937],"type":"Point"}
}