{
  "type": "Feature",
  "properties": {
    "addr:full":"24 Bankhead Drive Edinburgh City of Edinburgh EH11 4DJ",
    "addr:housenumber":"24",
    "addr:postcode":"eh11 4dj",
    "addr:street":"Bankhead Drive",
    "iso:country":"GB",
    "sg:address":"24 Bankhead Drive",
    "sg:city":"Edinburgh",
    "sg:classifiers":[
        {
            "category":"Retail",
            "subcategory":"Auto Repair",
            "type":"Services"
        }
    ],
    "sg:phone":"+44 131 453 6333",
    "sg:postcode":"EH11 4DJ",
    "sg:province":"City of Edinburgh",
    "sg:tags":[
        "body",
        "car"
    ],
    "wof:name":"Belmont Accident Repair Centre",
    "wof:placetype":"venue"
},
  "geometry": {"coordinates":[-3.292299,55.924416],"type":"Point"}
}