{
  "type": "Feature",
  "properties": {
    "addr:full":"A46 Gloucester Road Bath Bath and North East Somerset BA1 8BJ",
    "addr:postcode":"ba1 8bj",
    "addr:street":"Gloucester Road",
    "iso:country":"GB",
    "sg:address":"A46 Gloucester Road",
    "sg:city":"Bath",
    "sg:classifiers":[
        {
            "category":"Autos & Motor Vehicles",
            "subcategory":"Automobile Sales",
            "type":"Retail Goods"
        }
    ],
    "sg:phone":"+44 1225 858252",
    "sg:postcode":"BA1 8BJ",
    "sg:province":"Bath and North East Somerset",
    "sg:tags":[
        "car"
    ],
    "wof:name":"Free Shires Four by Four",
    "wof:placetype":"venue"
},
  "geometry": {"coordinates":[-2.368137,51.43679],"type":"Point"}
}