{
  "type": "Feature",
  "properties": {
    "iso:country":"GB",
    "sg:address":"Cordell Road, Steads Meadow, Longmelford",
    "sg:city":"Sudbury",
    "sg:classifiers":[
        {
            "category":"Organizations",
            "subcategory":"Community Association",
            "type":"Services"
        },
        {
            "category":"Organizations",
            "subcategory":"Membership Organization",
            "type":"Services"
        }
    ],
    "sg:phone":"+44 1787 377567",
    "sg:postcode":"CO10 9EH",
    "sg:province":"Essex",
    "sg:tags":[
        "club",
        "social"
    ],
    "wof:name":"The Royal British Legion",
    "wof:placetype":"venue"
},
  "geometry": {"coordinates":[0.7199760079,52.078754425],"type":"Point"}
}