{
  "type": "Feature",
  "properties": {
    "iso:country":"GB",
    "sg:address":"South Hill Farm, Aston Munslow",
    "sg:city":"Craven Arms",
    "sg:classifiers":[
        {
            "category":"Farming",
            "subcategory":"Farm",
            "type":"Manufacturing & Wholesale Goods"
        }
    ],
    "sg:phone":"+44 1584 841268",
    "sg:postcode":"SY7 9ER",
    "sg:province":"Herefordshire",
    "sg:tags":[
        "mixed",
        "crop"
    ],
    "wof:name":"E J P Thomas",
    "wof:placetype":"venue"
},
  "geometry": {"coordinates":[-2.836239,52.439388],"type":"Point"}
}