{
  "type": "Feature",
  "properties": {
    "addr:full":"117 Walsall Street Wednesbury West Midlands WS10 9BY",
    "addr:housenumber":"117",
    "addr:postcode":"ws10 9by",
    "addr:street":"Walsall Street",
    "iso:country":"GB",
    "sg:address":"117 Walsall Street",
    "sg:city":"Wednesbury",
    "sg:classifiers":[
        {
            "category":"Personal",
            "subcategory":"Beauty Salon",
            "type":"Services"
        }
    ],
    "sg:phone":"+44 121 556 1692",
    "sg:postcode":"WS10 9BY",
    "sg:province":"West Midlands",
    "sg:tags":[
        "unisex",
        "hairdresser"
    ],
    "wof:name":"Paolo's",
    "wof:placetype":"venue"
},
  "geometry": {"coordinates":[-2.028357029,52.5687980652],"type":"Point"}
}