{
  "type": "Feature",
  "properties": {
    "addr:full":"The Green Slough Berkshire SL3 9JW",
    "addr:postcode":"sl3 9jw",
    "addr:street":"The Green",
    "iso:country":"GB",
    "sg:address":"The Green",
    "sg:city":"Slough",
    "sg:classifiers":[
        {
            "category":"Place Of Worship",
            "type":"Public Place"
        }
    ],
    "sg:phone":"+44 1753 580379",
    "sg:postcode":"SL3 9JW",
    "sg:province":"Berkshire",
    "wof:name":"St Mary The Virgin Church",
    "wof:placetype":"venue"
},
  "geometry": {"coordinates":[-0.5910649896,51.4981651306],"type":"Point"}
}