{
  "type": "Feature",
  "properties": {
    "iso:country":"GB",
    "sg:address":"15 Sandy Lane, Winterley",
    "sg:city":"Sandbach",
    "sg:classifiers":[
        {
            "category":"Retail",
            "subcategory":"Repair Shop",
            "type":"Services"
        },
        {
            "category":"Military Area",
            "subcategory":"Air Force Base",
            "type":"Public Place"
        }
    ],
    "sg:phone":"+44 1270 759390",
    "sg:postcode":"CW11 4RH",
    "sg:province":"Cheshire",
    "sg:tags":[
        "groundwork",
        "maintenance",
        "contractor"
    ],
    "wof:name":"Clive Nash Landscape",
    "wof:placetype":"venue"
},
  "geometry": {"coordinates":[-2.381974,53.111359],"type":"Point"}
}