{
  "type": "Feature",
  "properties": {
    "addr:full":"249a Belvoir Rd Coalville Leicestershire LE67 3PL",
    "addr:housenumber":"249a",
    "addr:postcode":"le67 3pl",
    "addr:street":"Belvoir Rd",
    "iso:country":"GB",
    "sg:address":"249a Belvoir Rd",
    "sg:city":"Coalville",
    "sg:classifiers":[
        {
            "category":"Autos & Motor Vehicles",
            "subcategory":"Motorcycle Sales",
            "type":"Retail Goods"
        }
    ],
    "sg:phone":"+44 1530 817070",
    "sg:postcode":"LE67 3PL",
    "sg:province":"Leicestershire",
    "wof:name":"K T M Racing",
    "wof:placetype":"venue"
},
  "geometry": {"coordinates":[-1.374514,52.724922],"type":"Point"}
}