{
  "type": "Feature",
  "properties": {
    "addr:full":"Perranwell Station Truro Cornwall TR3 7PT",
    "addr:postcode":"tr3 7pt",
    "iso:country":"GB",
    "sg:address":"Perranwell Station",
    "sg:city":"Truro",
    "sg:classifiers":[
        {
            "category":"Retail",
            "subcategory":"Auto Repair",
            "type":"Services"
        }
    ],
    "sg:phone":"+44 1872 863037",
    "sg:postcode":"TR3 7PT",
    "sg:province":"Cornwall",
    "sg:tags":[
        "modification",
        "garage"
    ],
    "wof:name":"A R & M E A Ireland",
    "wof:placetype":"venue"
},
  "geometry": {"coordinates":[-5.11897,50.213341],"type":"Point"}
}