{
  "type": "Feature",
  "properties": {
    "addr:full":"Woodside Road Glenrothes Fife KY7 4AH",
    "addr:postcode":"ky7 4ah",
    "addr:street":"Woodside Road",
    "iso:country":"GB",
    "sg:address":"Woodside Road",
    "sg:city":"Glenrothes",
    "sg:classifiers":[
        {
            "category":"Organizations",
            "subcategory":"Community Association",
            "type":"Services"
        },
        {
            "category":"Organizations",
            "subcategory":"Membership Organization",
            "type":"Services"
        }
    ],
    "sg:phone":"+44 1592 752632",
    "sg:postcode":"KY7 4AH",
    "sg:province":"Fife",
    "sg:tags":[
        "club",
        "social"
    ],
    "wof:name":"The Royal British Legion",
    "wof:placetype":"venue"
},
  "geometry": {"coordinates":[-3.1663138866,56.1951332092],"type":"Point"}
}