{
  "type": "Feature",
  "properties": {
    "addr:full":"454-460 Moseley Road Birmingham West Midlands B12 9AN",
    "addr:postcode":"454-460;b12 9an",
    "addr:street":"Moseley Road",
    "iso:country":"GB",
    "sg:address":"454-460 Moseley Road",
    "sg:city":"Birmingham",
    "sg:classifiers":[
        {
            "category":"Autos & Motor Vehicles",
            "subcategory":"Auto Supplies",
            "type":"Retail Goods"
        }
    ],
    "sg:phone":"+44 121 440 4411",
    "sg:postcode":"B12 9AN",
    "sg:province":"West Midlands",
    "sg:tags":[
        "tyre"
    ],
    "wof:name":"Wheel Works",
    "wof:placetype":"venue"
},
  "geometry": {"coordinates":[-1.885649,52.45863],"type":"Point"}
}