{
  "type": "Feature",
  "properties": {
    "iso:country":"GB",
    "sg:address":"6 Crescent Avenue, The Hoe",
    "sg:city":"Plymouth",
    "sg:classifiers":[
        {
            "category":"Travel",
            "subcategory":"Hotels & Motels",
            "type":"Entertainment"
        }
    ],
    "sg:postcode":"PL1 3AN",
    "sg:province":"Devon",
    "sg:tags":[
        "house",
        "guest"
    ],
    "wof:name":"The Crescent",
    "wof:placetype":"venue"
},
  "geometry": {"coordinates":[-4.146403,50.367863],"type":"Point"}
}