{
  "type": "Feature",
  "properties": {
    "addr:full":"32 Clwyd Street Ruthin Denbighshire LL15 1HW",
    "addr:housenumber":"32",
    "addr:postcode":"ll15 1hw",
    "addr:street":"Clwyd Street",
    "iso:country":"GB",
    "sg:address":"32 Clwyd Street",
    "sg:city":"Ruthin",
    "sg:classifiers":[
        {
            "category":"Shopping",
            "subcategory":"Department Store",
            "type":"Retail Goods"
        },
        {
            "category":"Bars & Pubs",
            "type":"Food & Drink"
        }
    ],
    "sg:phone":"+44 1824 702423",
    "sg:postcode":"LL15 1HW",
    "sg:province":"Denbighshire",
    "sg:tags":[
        "pubs",
        "inn"
    ],
    "wof:name":"Eagles Restaurant",
    "wof:placetype":"venue"
},
  "geometry": {"coordinates":[-3.3131289482,53.1137199402],"type":"Point"}
}