{
  "type": "Feature",
  "properties": {
    "addr:full":"Hilltop Farm Stables, Main Rd Burton On Trent Derbyshire DE13 9QE",
    "addr:postcode":"de13 9qe",
    "addr:street":"Main Rd",
    "iso:country":"GB",
    "sg:address":"Hilltop Farm Stables, Main Rd",
    "sg:city":"Burton On Trent",
    "sg:classifiers":[
        {
            "category":"Sports & Exercise",
            "subcategory":"Stables",
            "type":"Entertainment"
        }
    ],
    "sg:phone":"+44 1283 520024",
    "sg:postcode":"DE13 9QE",
    "sg:province":"Derbyshire",
    "sg:tags":[
        "education",
        "equestrian"
    ],
    "wof:name":"Hilltop Farm",
    "wof:placetype":"venue"
},
  "geometry": {"coordinates":[-1.68123,52.827068],"type":"Point"}
}