{
  "type": "Feature",
  "properties": {
    "addr:full":"20 Pontmorlais Merthyr Tydfil Merthyr Tydfil CF47 8UB",
    "addr:housenumber":"20",
    "addr:postcode":"cf47 8ub",
    "addr:street":"Pontmorlais Merthyr Tydfil",
    "iso:country":"GB",
    "sg:address":"20 Pontmorlais",
    "sg:city":"Merthyr Tydfil",
    "sg:classifiers":[
        {
            "category":"Autos & Motor Vehicles",
            "subcategory":"Motorcycle Sales",
            "type":"Retail Goods"
        }
    ],
    "sg:phone":"+44 1685 385201",
    "sg:postcode":"CF47 8UB",
    "sg:province":"Merthyr Tydfil",
    "sg:tags":[
        "scooter",
        "cycle"
    ],
    "wof:name":"Bob Wilding Motorcycles",
    "wof:placetype":"venue"
},
  "geometry": {"coordinates":[-3.380949,51.748718],"type":"Point"}
}