{
  "type": "Feature",
  "properties": {
    "addr:full":"Harlington Manor, Station Road, Harlington Dunstable Bedfordshire LU5 6LD",
    "addr:postcode":"lu5 6ld",
    "addr:street":"Station Road",
    "iso:country":"GB",
    "sg:address":"Harlington Manor, Station Road, Harlington",
    "sg:city":"Dunstable",
    "sg:classifiers":[
        {
            "category":"Freight",
            "type":"Transportation"
        }
    ],
    "sg:phone":"+44 1525 873731",
    "sg:postcode":"LU5 6LD",
    "sg:province":"Bedfordshire",
    "sg:tags":[
        "haulage",
        "transport",
        "road"
    ],
    "sg:website":"http://www.chrisbrooksaudio.com",
    "wof:name":"Chris Brooks Commercials",
    "wof:placetype":"venue"
},
  "geometry": {"coordinates":[-0.493244,51.962662],"type":"Point"}
}