{
  "type": "Feature",
  "properties": {
    "iso:country":"GB",
    "sg:address":"83 Tidings Hill",
    "sg:city":"Halstead",
    "sg:classifiers":[
        {
            "category":"Freight",
            "type":"Transportation"
        }
    ],
    "sg:phone":"+44 1787 477787",
    "sg:postcode":"CO9 1ND",
    "sg:province":"Essex",
    "sg:tags":[
        "haulage",
        "road"
    ],
    "wof:name":"Norman Engineering",
    "wof:placetype":"venue"
},
  "geometry": {"coordinates":[0.636070013,51.9346733093],"type":"Point"}
}