{
  "type": "Feature",
  "properties": {
    "iso:country":"GB",
    "sg:address":"63 Oakworth Hall, Oakworth",
    "sg:city":"Keighley",
    "sg:classifiers":[
        {
            "category":"Personal",
            "subcategory":"Beauty Salon",
            "type":"Services"
        },
        {
            "category":"Personal",
            "subcategory":"Barber",
            "type":"Services"
        }
    ],
    "sg:phone":"+44 1535 646085",
    "sg:postcode":"BD22 7HZ",
    "sg:province":"North Yorkshire",
    "sg:tags":[
        "unisex",
        "hairdresser"
    ],
    "wof:name":"Eclipse Sun & Hair Salon",
    "wof:placetype":"venue"
},
  "geometry": {"coordinates":[-1.9458390474,53.8447418213],"type":"Point"}
}