{
  "type": "Feature",
  "properties": {
    "addr:full":"Lennox House, Almondvale Boulevard Livingston West Lothian EH54 6QP",
    "addr:postcode":"eh54 6qp",
    "addr:street":"Almondvale Boulevard",
    "iso:country":"GB",
    "sg:address":"Lennox House, Almondvale Boulevard",
    "sg:city":"Livingston",
    "sg:classifiers":[
        {
            "category":"Sports & Exercise",
            "subcategory":"Swimming Pool",
            "type":"Entertainment"
        }
    ],
    "sg:phone":"+44 1506 777907",
    "sg:postcode":"EH54 6QP",
    "sg:province":"West Lothian",
    "wof:name":"Bubbles Leisure Pool",
    "wof:placetype":"venue"
},
  "geometry": {"coordinates":[-3.5115289688,55.8858833313],"type":"Point"}
}