{
  "type": "Feature",
  "properties": {
    "addr:full":"Express House, Church Road, Tarleton Preston Lancashire PR4 6UP",
    "addr:postcode":"pr4 6up",
    "addr:street":"Church Road",
    "iso:country":"GB",
    "sg:address":"Express House, Church Road, Tarleton",
    "sg:city":"Preston",
    "sg:classifiers":[
        {
            "category":"Professional",
            "subcategory":"Detective & Security Services",
            "type":"Services"
        }
    ],
    "sg:phone":"+44 1772 816220",
    "sg:postcode":"PR4 6UP",
    "sg:province":"Lancashire",
    "sg:tags":[
        "alarm",
        "burglar",
        "system"
    ],
    "wof:name":"Hawthorn Estates Ltd.",
    "wof:placetype":"venue"
},
  "geometry": {"coordinates":[-2.83061,53.679756],"type":"Point"}
}