{
  "type": "Feature",
  "properties": {
    "iso:country":"GB",
    "sg:address":"293 Chingford Rd",
    "sg:city":"Walthamstow",
    "sg:classifiers":[
        {
            "category":"Building & Trades",
            "subcategory":"Plumbing",
            "type":"Services"
        }
    ],
    "sg:phone":"+44 20 8523 5755",
    "sg:postcode":"E17 5AD",
    "sg:province":"Greater London",
    "sg:tags":[
        "merchant",
        "plumbers'"
    ],
    "wof:name":"J Hard",
    "wof:placetype":"venue"
},
  "geometry": {"coordinates":[-0.015595,51.596886],"type":"Point"}
}