{
  "type": "Feature",
  "properties": {
    "addr:full":"7 Kings Road Grangemouth Falkirk FK3 9BB",
    "addr:housenumber":"7",
    "addr:postcode":"fk3 9bb",
    "addr:street":"Kings Road",
    "iso:country":"GB",
    "sg:address":"7 Kings Road",
    "sg:city":"Grangemouth",
    "sg:classifiers":[
        {
            "category":"Food & Beverages",
            "subcategory":"Supermarket",
            "type":"Retail Goods"
        },
        {
            "category":"Food & Beverages",
            "subcategory":"Fruits & Vegetables",
            "type":"Retail Goods"
        }
    ],
    "sg:phone":"+44 1324 665640",
    "sg:postcode":"FK3 9BB",
    "sg:province":"Falkirk",
    "sg:tags":[
        "greengrocer"
    ],
    "wof:name":"M & M Foodstore",
    "wof:placetype":"venue"
},
  "geometry": {"coordinates":[-3.7086410522,56.0173301697],"type":"Point"}
}