{
  "type": "Feature",
  "properties": {
    "iso:country":"GB",
    "sg:address":"17 Cotton Street",
    "sg:city":"Liverpool",
    "sg:classifiers":[
        {
            "category":"Home & Garden",
            "subcategory":"Home Furnishings",
            "type":"Retail Goods"
        }
    ],
    "sg:phone":"+44 151 638 5953",
    "sg:postcode":"L3 7DY",
    "sg:province":"Merseyside",
    "sg:tags":[
        "furnishers",
        "planner",
        "kitchen"
    ],
    "wof:name":"Imperial Kitchens",
    "wof:placetype":"venue"
},
  "geometry": {"coordinates":[-2.996954,53.419125],"type":"Point"}
}