{
  "type": "Feature",
  "properties": {
    "iso:country":"GB",
    "sg:address":"30 Beacon Gro",
    "sg:city":"Carshalton",
    "sg:classifiers":[
        {
            "category":"Shopping",
            "subcategory":"Gifts & Souvenirs",
            "type":"Retail Goods"
        }
    ],
    "sg:phone":"+44 1737 222222",
    "sg:postcode":"SM5 3BA",
    "sg:province":"Surrey",
    "sg:tags":[
        "shop"
    ],
    "wof:name":"Yesteryears Charm",
    "wof:placetype":"venue"
},
  "geometry": {"coordinates":[-0.161094,51.365288],"type":"Point"}
}