{
  "type": "Feature",
  "properties": {
    "iso:country":"GB",
    "sg:address":"86 Darwen Street",
    "sg:city":"Blackburn",
    "sg:classifiers":[
        {
            "category":"Shopping",
            "subcategory":"Computers & Home Electronics",
            "type":"Retail Goods"
        }
    ],
    "sg:phone":"+44 1254 673806",
    "sg:postcode":"BB2 2AJ",
    "sg:province":"Lancashire",
    "wof:name":"Nybble Information Systems",
    "wof:placetype":"venue"
},
  "geometry": {"coordinates":[-2.4826369286,53.7448387146],"type":"Point"}
}