{
  "type": "Feature",
  "properties": {
    "addr:full":"8 Chinbrook Rd Grove Park Greater London SE12 9TH",
    "addr:housenumber":"8",
    "addr:postcode":"se12 9th",
    "addr:street":"Chinbrook Rd",
    "iso:country":"GB",
    "sg:address":"8 Chinbrook Rd",
    "sg:city":"Grove Park",
    "sg:classifiers":[
        {
            "category":"Health Services",
            "subcategory":"Dentist",
            "type":"Services"
        }
    ],
    "sg:phone":"+44 20 8857 0251",
    "sg:postcode":"SE12 9TH",
    "sg:province":"Greater London",
    "wof:name":"Grovepark Dental Surgery",
    "wof:placetype":"venue"
},
  "geometry": {"coordinates":[0.023192,51.431416],"type":"Point"}
}