{
  "type": "Feature",
  "properties": {
    "addr:full":"29 Wetherby Road Knaresborough North Yorkshire HG5 8LH",
    "addr:housenumber":"29",
    "addr:postcode":"hg5 8lh",
    "addr:street":"Wetherby Road",
    "iso:country":"GB",
    "sg:address":"29 Wetherby Road",
    "sg:city":"Knaresborough",
    "sg:classifiers":[
        {
            "category":"Retail",
            "subcategory":"Auto Repair",
            "type":"Services"
        }
    ],
    "sg:phone":"+44 1423 862215",
    "sg:postcode":"HG5 8LH",
    "sg:province":"North Yorkshire",
    "sg:tags":[
        "modification",
        "garage",
        "related"
    ],
    "wof:name":"Manse Services",
    "wof:placetype":"venue"
},
  "geometry": {"coordinates":[-1.4513659477,54.0037918091],"type":"Point"}
}