{
  "type": "Feature",
  "properties": {
    "addr:full":"1 Lukes Close Truro Cornwall TR1 1XF",
    "addr:housenumber":"1",
    "addr:postcode":"tr1 1xf",
    "addr:street":"Lukes Close",
    "iso:country":"GB",
    "sg:address":"1 Lukes Close",
    "sg:city":"Truro",
    "sg:classifiers":[
        {
            "category":"Building & Trades",
            "subcategory":"Construction",
            "type":"Services"
        }
    ],
    "sg:phone":"+44 1872 276226",
    "sg:postcode":"TR1 1XF",
    "sg:province":"Cornwall",
    "sg:tags":[
        "builder"
    ],
    "wof:name":"Highshore Construction",
    "wof:placetype":"venue"
},
  "geometry": {"coordinates":[-5.038189888,50.2690505981],"type":"Point"}
}