{
  "type": "Feature",
  "properties": {
    "iso:country":"GB",
    "sg:address":"29 Greenbank Road",
    "sg:city":"Liverpool",
    "sg:classifiers":[
        {
            "category":"Health Services",
            "subcategory":"Doctor",
            "type":"Services"
        }
    ],
    "sg:phone":"+44 151 733 3224",
    "sg:postcode":"L18 1HG",
    "sg:province":"Merseyside",
    "sg:tags":[
        "practitioners"
    ],
    "wof:name":"R Barnett L Barnett J Siddell & J Thomas",
    "wof:placetype":"venue"
},
  "geometry": {"coordinates":[-2.9248330593,53.3874778748],"type":"Point"}
}