{
  "type": "Feature",
  "properties": {
    "addr:full":"Long Load, Long Sutton Langport Somerset TA10 9JU",
    "addr:postcode":"ta10 9ju",
    "iso:country":"GB",
    "sg:address":"Long Load, Long Sutton",
    "sg:city":"Langport",
    "sg:classifiers":[
        {
            "category":"Sports & Exercise",
            "subcategory":"Golf",
            "type":"Entertainment"
        }
    ],
    "sg:phone":"+44 1458 241017",
    "sg:postcode":"TA10 9JU",
    "sg:province":"Somerset",
    "sg:tags":[
        "club",
        "course"
    ],
    "wof:name":"Long Sutton Golf Club",
    "wof:placetype":"venue"
},
  "geometry": {"coordinates":[-2.8242840767,51.042049408],"type":"Point"}
}