{
  "type": "Feature",
  "properties": {
    "addr:full":"8-11 St Johns Road Bootle Merseyside L20 8BH",
    "addr:housenumber":"8-11",
    "addr:postcode":"l20 8bh",
    "addr:street":"St Johns Road",
    "iso:country":"GB",
    "sg:address":"8-11 St Johns Road",
    "sg:city":"Bootle",
    "sg:classifiers":[
        {
            "category":"Manufacturing",
            "subcategory":"Wood Products",
            "type":"Manufacturing & Wholesale Goods"
        }
    ],
    "sg:phone":"+44 151 933 9552",
    "sg:postcode":"L20 8BH",
    "sg:province":"Merseyside",
    "sg:tags":[
        "maker",
        "cabinet"
    ],
    "wof:name":"Tudor Cabinet Makers Ltd.",
    "wof:placetype":"venue"
},
  "geometry": {"coordinates":[-2.995809,53.444157],"type":"Point"}
}