{
  "type": "Feature",
  "properties": {
    "addr:full":"Lower Culham Farm, Remenham Hill Henley-on-thames Berkshire RG9 3DP",
    "addr:housenumber":"remenham",
    "addr:postcode":"rg9 3dp",
    "addr:street":"Lower Culham;Hill Henley-On-Thames",
    "iso:country":"GB",
    "sg:address":"Lower Culham Farm, Remenham Hill",
    "sg:city":"Henley-on-thames",
    "sg:classifiers":[
        {
            "category":"Autos & Motor Vehicles",
            "subcategory":"Boat Sales",
            "type":"Retail Goods"
        }
    ],
    "sg:postcode":"RG9 3DP",
    "sg:province":"Berkshire",
    "sg:tags":[
        "repair",
        "builder"
    ],
    "wof:name":"T Green & Co",
    "wof:placetype":"venue"
},
  "geometry": {"coordinates":[-0.889575,51.550949],"type":"Point"}
}