{
  "type": "Feature",
  "properties": {
    "iso:country":"GB",
    "sg:address":"1 Ripston Road",
    "sg:city":"Ashford",
    "sg:classifiers":[
        {
            "category":"Professional",
            "subcategory":"Management & Consulting",
            "type":"Services"
        }
    ],
    "sg:phone":"+44 20 8941 8090",
    "sg:postcode":"TW15 1PQ",
    "sg:province":"Greater London",
    "sg:tags":[
        "consultant",
        "safety"
    ],
    "wof:name":"Personal Safety Associates",
    "wof:placetype":"venue"
},
  "geometry": {"coordinates":[-0.4368540049,51.4278259277],"type":"Point"}
}