{
  "type": "Feature",
  "properties": {
    "addr:full":"1 Bulwer Street Rochdale Lancashire OL16 2EU",
    "addr:housenumber":"1",
    "addr:postcode":"ol16 2eu",
    "addr:street":"Bulwer Street",
    "iso:country":"GB",
    "sg:address":"1 Bulwer Street",
    "sg:city":"Rochdale",
    "sg:classifiers":[
        {
            "category":"Health Services",
            "subcategory":"Doctor",
            "type":"Services"
        }
    ],
    "sg:phone":"+44 1706 356422",
    "sg:postcode":"OL16 2EU",
    "sg:province":"Lancashire",
    "sg:tags":[
        "practitioners"
    ],
    "wof:name":"Bulwer Street Surgery",
    "wof:placetype":"venue"
},
  "geometry": {"coordinates":[-2.145568,53.620224],"type":"Point"}
}