{
  "type": "Feature",
  "properties": {
    "iso:country":"GB",
    "sg:address":"107 Crompton Road",
    "sg:city":"Macclesfield",
    "sg:classifiers":[
        {
            "category":"Professional",
            "subcategory":"Engineering",
            "type":"Services"
        }
    ],
    "sg:postcode":"SK11 8EH",
    "sg:province":"Cheshire",
    "sg:tags":[
        "contractor",
        "electrical",
        "engineer"
    ],
    "wof:name":"Michael Arnold",
    "wof:placetype":"venue"
},
  "geometry": {"coordinates":[-2.135507,53.257153],"type":"Point"}
}