{
  "type": "Feature",
  "properties": {
    "addr:full":"Birmingham Road Warwick Warwickshire CV34 5XW",
    "addr:postcode":"cv34 5xw",
    "addr:street":"Birmingham Road",
    "iso:country":"GB",
    "sg:address":"Birmingham Road",
    "sg:city":"Warwick",
    "sg:classifiers":[
        {
            "category":"Retail",
            "subcategory":"Funeral Services",
            "type":"Services"
        },
        {
            "category":"Government",
            "subcategory":"Office",
            "type":"Public Place"
        }
    ],
    "sg:phone":"+44 1926 651418",
    "sg:postcode":"CV34 5XW",
    "sg:province":"Warwickshire",
    "sg:tags":[
        "local",
        "cemetery",
        "crematorium"
    ],
    "wof:name":"Warwick Cemetery",
    "wof:placetype":"venue"
},
  "geometry": {"coordinates":[-1.6084090471,52.2893791199],"type":"Point"}
}