{
  "type": "Feature",
  "properties": {
    "addr:full":"1c Hillview Industrial Estate, Bagborough Taunton Devon TA4 3EW",
    "addr:housenumber":"1c",
    "addr:postcode":"ta4 3ew",
    "addr:street":"Hillview Industrial Estate Bagborough",
    "iso:country":"GB",
    "sg:address":"1c Hillview Industrial Estate, Bagborough",
    "sg:city":"Taunton",
    "sg:classifiers":[
        {
            "category":"Building & Trades",
            "subcategory":"Construction",
            "type":"Services"
        }
    ],
    "sg:phone":"+44 1823 433705",
    "sg:postcode":"TA4 3EW",
    "sg:province":"Devon",
    "sg:tags":[
        "joinery",
        "joiner",
        "carpenter",
        "carpentry"
    ],
    "wof:name":"G Sedgbeer",
    "wof:placetype":"venue"
},
  "geometry": {"coordinates":[-3.198549,51.092751],"type":"Point"}
}