{
  "type": "Feature",
  "properties": {
    "addr:full":"289 Bearsden Road Glasgow Glasgow City G13 1EQ",
    "addr:housenumber":"289",
    "addr:postcode":"g13 1eq",
    "addr:street":"Bearsden Road",
    "iso:country":"GB",
    "sg:address":"289 Bearsden Road",
    "sg:city":"Glasgow",
    "sg:classifiers":[
        {
            "category":"Autos & Motor Vehicles",
            "subcategory":"Fuel & Gas Station",
            "type":"Retail Goods"
        }
    ],
    "sg:phone":"+44 141 958 1200",
    "sg:postcode":"G13 1EQ",
    "sg:province":"Glasgow City",
    "sg:tags":[
        "hr",
        "petrol"
    ],
    "wof:name":"Shell U K Ltd.",
    "wof:placetype":"venue"
},
  "geometry": {"coordinates":[-4.3235850334,55.8942222595],"type":"Point"}
}