{
  "type": "Feature",
  "properties": {
    "addr:full":"686 Wolverhampton Road, Olbury, Warley Smethwick West Midlands B68 8DB",
    "addr:housenumber":"686",
    "addr:postcode":"b68 8db",
    "addr:street":"Wolverhampton Road Olbury",
    "iso:country":"GB",
    "sg:address":"686 Wolverhampton Road, Olbury, Warley",
    "sg:city":"Smethwick",
    "sg:classifiers":[
        {
            "category":"Food & Beverages",
            "subcategory":"Meat & Fish",
            "type":"Retail Goods"
        }
    ],
    "sg:phone":"+44 121 552 1210",
    "sg:postcode":"B68 8DB",
    "sg:province":"West Midlands",
    "sg:tags":[
        "butcher"
    ],
    "wof:name":"W E & M Bowkett",
    "wof:placetype":"venue"
},
  "geometry": {"coordinates":[-2.01415,52.482121],"type":"Point"}
}