{
  "type": "Feature",
  "properties": {
    "iso:country":"GB",
    "sg:address":"15a Stamford New Road",
    "sg:city":"Altrincham",
    "sg:classifiers":[
        {
            "category":"Personal",
            "subcategory":"Beauty Salon",
            "type":"Services"
        }
    ],
    "sg:phone":"+44 161 941 6167",
    "sg:postcode":"WA14 1BN",
    "sg:province":"Cheshire",
    "sg:tags":[
        "unisex",
        "hairdresser"
    ],
    "wof:name":"Saxs",
    "wof:placetype":"venue"
},
  "geometry": {"coordinates":[-2.3489201069,53.3867263794],"type":"Point"}
}