{
  "type": "Feature",
  "properties": {
    "addr:full":"6 Henrietta Street London Greater London WC2E 8PU",
    "addr:housenumber":"6",
    "addr:postcode":"wc2e 8pu",
    "addr:street":"Henrietta Street",
    "iso:country":"GB",
    "sg:address":"6 Henrietta Street",
    "sg:city":"London",
    "sg:classifiers":[
        {
            "category":"Government",
            "subcategory":"Post Office",
            "type":"Public Place"
        }
    ],
    "sg:phone":"+44 20 7557 7500",
    "sg:postcode":"WC2E 8PU",
    "sg:province":"Greater London",
    "sg:tags":[
        "organisation",
        "soc",
        "research"
    ],
    "wof:name":"M V M Ltd.",
    "wof:placetype":"venue"
},
  "geometry": {"coordinates":[-0.124211,51.510761],"type":"Point"}
}