{
  "type": "Feature",
  "properties": {
    "addr:full":"Dunroamin, Falkirk Road Falkirk Falkirk FK1 2LU",
    "addr:postcode":"fk1 2lu",
    "addr:street":"Dunroamin Falkirk Road",
    "iso:country":"GB",
    "sg:address":"Dunroamin, Falkirk Road",
    "sg:city":"Falkirk",
    "sg:classifiers":[
        {
            "category":"Freight",
            "type":"Transportation"
        }
    ],
    "sg:phone":"+44 1324 861648",
    "sg:postcode":"FK1 2LU",
    "sg:province":"Falkirk",
    "sg:tags":[
        "haulage",
        "road"
    ],
    "wof:name":"T & J Wilson (Hauliers)",
    "wof:placetype":"venue"
},
  "geometry": {"coordinates":[-3.778592,55.987492],"type":"Point"}
}