{
  "type": "Feature",
  "properties": {
    "iso:country":"GB",
    "sg:address":"34 High Street, Borough Green",
    "sg:city":"Sevenoaks",
    "sg:classifiers":[
        {
            "category":"Personal",
            "subcategory":"Beauty Salon",
            "type":"Services"
        }
    ],
    "sg:phone":"+44 1732 886722",
    "sg:postcode":"TN15 8BJ",
    "sg:province":"Kent",
    "wof:name":"Body & Soul",
    "wof:placetype":"venue"
},
  "geometry": {"coordinates":[0.305288,51.291615],"type":"Point"}
}