{
  "type": "Feature",
  "properties": {
    "addr:full":"Leeds Road Dewsbury West Yorkshire WF12 7RB",
    "addr:postcode":"wf12 7rb",
    "addr:street":"Leeds Road",
    "iso:country":"GB",
    "sg:address":"Leeds Road",
    "sg:city":"Dewsbury",
    "sg:classifiers":[
        {
            "category":"Government",
            "subcategory":"Department Of Motor Vehicles",
            "type":"Public Place"
        },
        {
            "category":"Retail",
            "subcategory":"Auto Repair",
            "type":"Services"
        }
    ],
    "sg:phone":"+44 1924 472660",
    "sg:postcode":"WF12 7RB",
    "sg:province":"West Yorkshire",
    "sg:tags":[
        "breakdown",
        "truck",
        "van",
        "recovery"
    ],
    "wof:name":"Heybeck Garage Ltd",
    "wof:placetype":"venue"
},
  "geometry": {"coordinates":[-1.592429,53.717636],"type":"Point"}
}