{
  "type": "Feature",
  "properties": {
    "addr:full":"Station House, College Road, Ardingly Haywards Heath East Sussex RH17 6SH",
    "addr:postcode":"rh17 6sh",
    "addr:street":"College Road",
    "iso:country":"GB",
    "sg:address":"Station House, College Road, Ardingly",
    "sg:city":"Haywards Heath",
    "sg:classifiers":[
        {
            "category":"Wholesale",
            "subcategory":"Construction Materials",
            "type":"Manufacturing & Wholesale Goods"
        }
    ],
    "sg:phone":"+44 1444 892661",
    "sg:postcode":"RH17 6SH",
    "sg:province":"East Sussex",
    "sg:tags":[
        "whole",
        "asphalt",
        "macadam"
    ],
    "wof:name":"Arc Southern",
    "wof:placetype":"venue"
},
  "geometry": {"coordinates":[-0.0784810036,51.0478019714],"type":"Point"}
}