{
  "type": "Feature",
  "properties": {
    "addr:full":"44 Tenter Road, Moulton Park Industrial Estate Northampton Northamptonshire NN3 6AX",
    "addr:housenumber":"44;estate",
    "addr:postcode":"nn3 6ax",
    "addr:street":"Tenter Road",
    "iso:country":"GB",
    "sg:address":"44 Tenter Road, Moulton Park Industrial Estate",
    "sg:city":"Northampton",
    "sg:classifiers":[
        {
            "category":"Professional",
            "subcategory":"Management & Consulting",
            "type":"Services"
        }
    ],
    "sg:postcode":"NN3 6AX",
    "sg:province":"Northamptonshire",
    "sg:tags":[
        "consultant",
        "business"
    ],
    "wof:name":"Applied Business Consultants",
    "wof:placetype":"venue"
},
  "geometry": {"coordinates":[-0.8759800196,52.2798690796],"type":"Point"}
}