{
  "type": "Feature",
  "properties": {
    "iso:country":"GB",
    "sg:address":"354 Burnley Road East",
    "sg:city":"Rossendale",
    "sg:classifiers":[
        {
            "category":"Retail",
            "subcategory":"Auto Repair",
            "type":"Services"
        }
    ],
    "sg:phone":"+44 1706 214947",
    "sg:postcode":"BB4 9HU",
    "sg:province":"Lancashire",
    "sg:tags":[
        "modification",
        "garage",
        "related"
    ],
    "wof:name":"Scout Garage",
    "wof:placetype":"venue"
},
  "geometry": {"coordinates":[-2.2496790886,53.700630188],"type":"Point"}
}