{
  "type": "Feature",
  "properties": {
    "iso:country":"GB",
    "sg:address":"Essendine Road",
    "sg:city":"London",
    "sg:classifiers":[
        {
            "category":"Education",
            "subcategory":"School",
            "type":"Public Place"
        }
    ],
    "sg:phone":"+44 20 7641 4382",
    "sg:postcode":"W9 2LR",
    "sg:province":"Greater London",
    "sg:tags":[
        "local",
        "authority"
    ],
    "wof:name":"Essendine Primary School",
    "wof:placetype":"venue"
},
  "geometry": {"coordinates":[-0.193816,51.52903],"type":"Point"}
}