{
  "type": "Feature",
  "properties": {
    "addr:full":"82 Compstall Road Stockport Cheshire SK6 4DE",
    "addr:housenumber":"82",
    "addr:postcode":"sk6 4de",
    "addr:street":"Compstall Road",
    "iso:country":"GB",
    "sg:address":"82 Compstall Road",
    "sg:city":"Stockport",
    "sg:classifiers":[
        {
            "category":"Food & Beverages",
            "subcategory":"Meat & Fish",
            "type":"Retail Goods"
        }
    ],
    "sg:phone":"+44 161 430 3252",
    "sg:postcode":"SK6 4DE",
    "sg:province":"Cheshire",
    "sg:tags":[
        "butcher"
    ],
    "wof:name":"R W Chandler",
    "wof:placetype":"venue"
},
  "geometry": {"coordinates":[-2.0835449696,53.4141197205],"type":"Point"}
}