{
  "type": "Feature",
  "properties": {
    "addr:full":"Chantry Road Saxmundham Suffolk IP17 1DJ",
    "addr:postcode":"ip17 1dj",
    "addr:street":"Chantry Road",
    "iso:country":"GB",
    "sg:address":"Chantry Road",
    "sg:city":"Saxmundham",
    "sg:classifiers":[
        {
            "category":"Organizations",
            "subcategory":"Community Association",
            "type":"Services"
        }
    ],
    "sg:postcode":"IP17 1DJ",
    "sg:province":"Suffolk",
    "sg:tags":[
        "society",
        "housing"
    ],
    "wof:name":"Chantry House",
    "wof:placetype":"venue"
},
  "geometry": {"coordinates":[1.48963,52.213955],"type":"Point"}
}