{
  "type": "Feature",
  "properties": {
    "addr:full":"31 Furtherwick Road Canvey Island Essex SS8 7AG",
    "addr:housenumber":"31",
    "addr:postcode":"ss8 7ag",
    "addr:street":"Furtherwick Road",
    "iso:country":"GB",
    "sg:address":"31 Furtherwick Road",
    "sg:city":"Canvey Island",
    "sg:classifiers":[
        {
            "category":"Wholesale",
            "subcategory":"Fruits & Vegetables",
            "type":"Manufacturing & Wholesale Goods"
        }
    ],
    "sg:phone":"+44 1268 682792",
    "sg:postcode":"SS8 7AG",
    "sg:province":"Essex",
    "wof:name":"Peacheys Freshfare",
    "wof:placetype":"venue"
},
  "geometry": {"coordinates":[0.5926430225,51.5222167969],"type":"Point"}
}