{
  "type": "Feature",
  "properties": {
    "iso:country":"GB",
    "sg:address":"Pinchington Lane, Greenham",
    "sg:city":"Newbury",
    "sg:classifiers":[
        {
            "category":"Travel",
            "subcategory":"Hotels & Motels",
            "type":"Entertainment"
        }
    ],
    "sg:phone":"+44 1635 529000",
    "sg:postcode":"RG14 7HL",
    "sg:province":"Berkshire",
    "wof:name":"Hilton National",
    "wof:placetype":"venue"
},
  "geometry": {"coordinates":[-1.320404,51.38446],"type":"Point"}
}