{
  "type": "Feature",
  "properties": {
    "iso:country":"GB",
    "sg:address":"Meadow Street, Chesterton",
    "sg:city":"Newcastle",
    "sg:classifiers":[
        {
            "category":"Retail",
            "subcategory":"Auto Repair",
            "type":"Services"
        }
    ],
    "sg:postcode":"ST5 7HU",
    "sg:province":"Staffordshire",
    "sg:tags":[
        "modification",
        "garage"
    ],
    "wof:name":"Ian Gilmore",
    "wof:placetype":"venue"
},
  "geometry": {"coordinates":[-2.245824,53.03492],"type":"Point"}
}