{
  "type": "Feature",
  "properties": {
    "addr:full":"The Carers Centre, Sucklings Yd, Church St Ware Hertfordshire SG12 9EN",
    "addr:postcode":"sg12 9en",
    "addr:street":"Yd;St",
    "iso:country":"GB",
    "sg:address":"The Carers Centre, Sucklings Yd, Church St",
    "sg:city":"Ware",
    "sg:classifiers":[
        {
            "category":"Organizations",
            "subcategory":"Non-profit Organization",
            "type":"Services"
        }
    ],
    "sg:postcode":"SG12 9EN",
    "sg:province":"Hertfordshire",
    "sg:tags":[
        "organisation",
        "voluntary",
        "charity"
    ],
    "wof:name":"Crossroads",
    "wof:placetype":"venue"
},
  "geometry": {"coordinates":[-0.035126999,51.8163375854],"type":"Point"}
}