{
  "type": "Feature",
  "properties": {
    "iso:country":"GB",
    "sg:address":"82 Deansgate",
    "sg:city":"Bolton",
    "sg:classifiers":[
        {
            "category":"Retail",
            "subcategory":"Photofinishing",
            "type":"Services"
        }
    ],
    "sg:phone":"+44 1204 524064",
    "sg:postcode":"BL1 1BD",
    "sg:province":"Lancashire",
    "sg:tags":[
        "photographic",
        "processor"
    ],
    "wof:name":"Foto Processing",
    "wof:placetype":"venue"
},
  "geometry": {"coordinates":[-2.430978,53.579613],"type":"Point"}
}