{
  "type": "Feature",
  "properties": {
    "addr:full":"Veldon, Wilby Road, Stradbroke Eye Norfolk IP21 5JN",
    "addr:postcode":"ip21 5jn",
    "addr:street":"Wilby Road",
    "iso:country":"GB",
    "sg:address":"Veldon, Wilby Road, Stradbroke",
    "sg:city":"Eye",
    "sg:classifiers":[
        {
            "category":"Professional",
            "subcategory":"Engineering",
            "type":"Services"
        },
        {
            "category":"Building & Trades",
            "subcategory":"Electrical",
            "type":"Services"
        }
    ],
    "sg:postcode":"IP21 5JN",
    "sg:province":"Norfolk",
    "sg:tags":[
        "engineer",
        "electrician",
        "contractor"
    ],
    "wof:name":"Donald E Lummis",
    "wof:placetype":"venue"
},
  "geometry": {"coordinates":[1.2721370459,52.3178520203],"type":"Point"}
}