{
  "type": "Feature",
  "properties": {
    "addr:full":"40-42 Scrutton Street London Greater London EC2A 4QL",
    "addr:housenumber":"40-42",
    "addr:postcode":"ec2a 4ql",
    "addr:street":"Scrutton Street",
    "iso:country":"GB",
    "sg:address":"40-42 Scrutton Street",
    "sg:city":"London",
    "sg:classifiers":[
        {
            "category":"Professional",
            "subcategory":"Art Services",
            "type":"Services"
        }
    ],
    "sg:phone":"+44 20 7247 2999",
    "sg:postcode":"EC2A 4QL",
    "sg:province":"Greater London",
    "sg:tags":[
        "consultant",
        "design"
    ],
    "wof:name":"Deepend Italy Ltd.",
    "wof:placetype":"venue"
},
  "geometry": {"coordinates":[-0.0813940018,51.5232696533],"type":"Point"}
}