{
  "type": "Feature",
  "properties": {
    "addr:full":"Centerfield, The Broadway, Greater Central Road Mansfield Nottinghamshire NG18 2RL",
    "addr:postcode":"ng18 2rl",
    "addr:street":"The Broadway;Central Road",
    "iso:country":"GB",
    "sg:address":"Centerfield, The Broadway, Greater Central Road",
    "sg:city":"Mansfield",
    "sg:classifiers":[
        {
            "category":"Professional",
            "subcategory":"Engineering",
            "type":"Services"
        }
    ],
    "sg:phone":"+44 1623 628687",
    "sg:postcode":"NG18 2RL",
    "sg:province":"Nottinghamshire",
    "sg:tags":[
        "consulting",
        "engineer"
    ],
    "wof:name":"Kombilift Ltd.",
    "wof:placetype":"venue"
},
  "geometry": {"coordinates":[-1.201743,53.144024],"type":"Point"}
}