{
  "type": "Feature",
  "properties": {
    "addr:full":"10 Spring Garden Lane Gosport Hampshire PO12 1HY",
    "addr:housenumber":"10",
    "addr:postcode":"po12 1hy",
    "addr:street":"Spring Garden Lane",
    "iso:country":"GB",
    "sg:address":"10 Spring Garden Lane",
    "sg:city":"Gosport",
    "sg:classifiers":[
        {
            "category":"Place Of Worship",
            "type":"Public Place"
        }
    ],
    "sg:phone":"+44 23 9250 3140",
    "sg:postcode":"PO12 1HY",
    "sg:province":"Hampshire",
    "wof:name":"St.Johns Forton",
    "wof:placetype":"venue"
},
  "geometry": {"coordinates":[-1.1293720007,50.7967529297],"type":"Point"}
}