{
  "type": "Feature",
  "properties": {
    "addr:full":"2 Abbotsmede Close Twickenham Greater London TW1 4RL",
    "addr:housenumber":"2",
    "addr:postcode":"tw1 4rl",
    "addr:street":"Abbotsmede Close",
    "iso:country":"GB",
    "sg:address":"2 Abbotsmede Close",
    "sg:city":"Twickenham",
    "sg:classifiers":[
        {
            "category":"Real Estate",
            "subcategory":"Architect",
            "type":"Services"
        }
    ],
    "sg:postcode":"TW1 4RL",
    "sg:province":"Greater London",
    "wof:name":"H X Engineering Ltd",
    "wof:placetype":"venue"
},
  "geometry": {"coordinates":[-0.3368940055,51.4414634705],"type":"Point"}
}