{
  "type": "Feature",
  "properties": {
    "iso:country":"GB",
    "sg:address":"Crown Building, Shrubland Road, Mistley",
    "sg:city":"Manningtree",
    "sg:classifiers":[
        {
            "category":"Museum",
            "subcategory":"Art Museum",
            "type":"Entertainment"
        }
    ],
    "sg:phone":"+44 1206 392271",
    "sg:postcode":"CO11 1HS",
    "sg:province":"Essex",
    "sg:tags":[
        "gallery"
    ],
    "wof:name":"Essex Secret Bunker",
    "wof:placetype":"venue"
},
  "geometry": {"coordinates":[1.06304,51.945381],"type":"Point"}
}