{
  "type": "Feature",
  "properties": {
    "iso:country":"GB",
    "sg:address":"42 High Street, Cheshunt",
    "sg:city":"Waltham Cross",
    "sg:classifiers":[
        {
            "category":"Manufacturing",
            "subcategory":"Tools & Machinery",
            "type":"Manufacturing & Wholesale Goods"
        }
    ],
    "sg:phone":"+44 1992 621411",
    "sg:postcode":"EN8 0AQ",
    "sg:province":"Essex",
    "sg:tags":[
        "society",
        "friendly"
    ],
    "wof:name":"Cheshunt Central Insurance",
    "wof:placetype":"venue"
},
  "geometry": {"coordinates":[-0.036191,51.709328],"type":"Point"}
}