{
  "type": "Feature",
  "properties": {
    "iso:country":"GB",
    "sg:address":"Station Road",
    "sg:city":"Tidworth",
    "sg:classifiers":[
        {
            "category":"Fast Food",
            "type":"Food & Drink"
        }
    ],
    "sg:phone":"+44 1980 843039",
    "sg:postcode":"SP9 7NW",
    "sg:province":"Hampshire",
    "sg:tags":[
        "away",
        "take"
    ],
    "wof:name":"China Town",
    "wof:placetype":"venue"
},
  "geometry": {"coordinates":[-1.659516,51.234459],"type":"Point"}
}