{
  "type": "Feature",
  "properties": {
    "addr:full":"White Oak Cottage, Eardisley Hereford Herefordshire HR3 6LU",
    "addr:housenumber":"eardisley",
    "addr:postcode":"hr3 6lu",
    "iso:country":"GB",
    "sg:address":"White Oak Cottage, Eardisley",
    "sg:city":"Hereford",
    "sg:classifiers":[
        {
            "category":"Health Services",
            "subcategory":"Doctor",
            "type":"Services"
        }
    ],
    "sg:phone":"+44 1544 327756",
    "sg:postcode":"HR3 6LU",
    "sg:province":"Herefordshire",
    "sg:tags":[
        "practitioners"
    ],
    "wof:name":"Murphy, B J",
    "wof:placetype":"venue"
},
  "geometry": {"coordinates":[-3.0071730614,52.1388511658],"type":"Point"}
}