{
  "type": "Feature",
  "properties": {
    "iso:country":"GB",
    "sg:address":"72 Westminster Way",
    "sg:city":"Oxford",
    "sg:classifiers":[
        {
            "category":"Autos & Motor Vehicles",
            "subcategory":"Auto Supplies",
            "type":"Retail Goods"
        }
    ],
    "sg:phone":"+44 800 169 3021",
    "sg:postcode":"OX2 0LW",
    "sg:province":"Oxfordshire",
    "sg:tags":[
        "windscreen"
    ],
    "wof:name":"Botley Windscreens",
    "wof:placetype":"venue"
},
  "geometry": {"coordinates":[-1.294306,51.749249],"type":"Point"}
}