{
  "type": "Feature",
  "properties": {
    "addr:full":"90a Brecon Rd Swansea Carmarthenshire SA9 1HJ",
    "addr:housenumber":"90a",
    "addr:postcode":"sa9 1hj",
    "addr:street":"Brecon Rd",
    "iso:country":"GB",
    "sg:address":"90a Brecon Rd",
    "sg:city":"Swansea",
    "sg:classifiers":[
        {
            "category":"Shopping",
            "subcategory":"Clothing, Apparel, & Fashions",
            "type":"Retail Goods"
        }
    ],
    "sg:phone":"+44 1639 843553",
    "sg:postcode":"SA9 1HJ",
    "sg:province":"Carmarthenshire",
    "sg:tags":[
        "shop"
    ],
    "wof:name":"Elena's Leisurewear",
    "wof:placetype":"venue"
},
  "geometry": {"coordinates":[-3.752943,51.779736],"type":"Point"}
}