{
  "type": "Feature",
  "properties": {
    "addr:full":"Hartfield House, 173 Hartfield Road London Greater London SW19 3TH",
    "addr:housenumber":"173",
    "addr:postcode":"sw19 3th",
    "addr:street":"Hartfield Road",
    "iso:country":"GB",
    "sg:address":"Hartfield House, 173 Hartfield Road",
    "sg:city":"London",
    "sg:classifiers":[
        {
            "category":"Recreation",
            "subcategory":"Gun Range",
            "type":"Entertainment"
        }
    ],
    "sg:postcode":"SW19 3TH",
    "sg:province":"Greater London",
    "sg:tags":[
        "operator",
        "tour"
    ],
    "wof:name":"Interest & Activity Holidays Ltd.",
    "wof:placetype":"venue"
},
  "geometry": {"coordinates":[-0.202381,51.414951],"type":"Point"}
}