{
  "type": "Feature",
  "properties": {
    "addr:full":"1 Printing House Yard London Greater London E2 7PR",
    "addr:postcode":"e2 7pr",
    "addr:street":"Yard",
    "iso:country":"GB",
    "sg:address":"1 Printing House Yard",
    "sg:city":"London",
    "sg:classifiers":[
        {
            "category":"Real Estate",
            "subcategory":"Real Estate Agent",
            "type":"Services"
        }
    ],
    "sg:postcode":"E2 7PR",
    "sg:province":"Greater London",
    "wof:name":"President Industries U K Services Ltd",
    "wof:placetype":"venue"
},
  "geometry": {"coordinates":[-0.0771799982,51.5274505615],"type":"Point"}
}