{
  "type": "Feature",
  "properties": {
    "addr:full":"86 Blae-y-maes Drive, Blaen-y-maes Swansea Swansea SA5 5NR",
    "addr:housenumber":"86",
    "addr:postcode":"sa5 5nr",
    "addr:street":"Blae-Y-Maes Drive",
    "iso:country":"GB",
    "sg:address":"86 Blae-y-maes Drive, Blaen-y-maes",
    "sg:city":"Swansea",
    "sg:classifiers":[
        {
            "category":"Organizations",
            "subcategory":"Non-profit Organization",
            "type":"Services"
        }
    ],
    "sg:phone":"+44 1792 580905",
    "sg:postcode":"SA5 5NR",
    "sg:province":"Swansea",
    "sg:tags":[
        "organisation",
        "voluntary",
        "charity"
    ],
    "wof:name":"Drop in Centre",
    "wof:placetype":"venue"
},
  "geometry": {"coordinates":[-3.9806239605,51.6554832458],"type":"Point"}
}