{
  "type": "Feature",
  "properties": {
    "addr:full":"P O Box 26 St Albans Hertfordshire AL2 1BF",
    "addr:housenumber":"box 26",
    "addr:postcode":"al2 1bf",
    "addr:street":"P O",
    "iso:country":"GB",
    "sg:address":"P O Box 26",
    "sg:city":"St Albans",
    "sg:classifiers":[
        {
            "category":"Professional",
            "subcategory":"Computer Services",
            "type":"Services"
        }
    ],
    "sg:phone":"+44 1727 826321",
    "sg:postcode":"AL2 1BF",
    "sg:province":"Hertfordshire",
    "sg:tags":[
        "system",
        "software"
    ],
    "wof:name":"Haverly Systems Europe Ltd.",
    "wof:placetype":"venue"
},
  "geometry": {"coordinates":[-0.2910099924,51.717880249],"type":"Point"}
}