{
  "type": "Feature",
  "properties": {
    "addr:full":"Market Street, Edenfield, Ramsbottom Bury Lancashire BL0 0JL",
    "addr:postcode":"bl0 0jl",
    "addr:street":"Market Street",
    "iso:country":"GB",
    "sg:address":"Market Street, Edenfield, Ramsbottom",
    "sg:city":"Bury",
    "sg:classifiers":[
        {
            "category":"Organizations",
            "subcategory":"Membership Organization",
            "type":"Services"
        }
    ],
    "sg:phone":"+44 1706 825597",
    "sg:postcode":"BL0 0JL",
    "sg:province":"Lancashire",
    "sg:tags":[
        "club",
        "social"
    ],
    "wof:name":"Edenfield Conservative Club",
    "wof:placetype":"venue"
},
  "geometry": {"coordinates":[-2.3068540096,53.6656150818],"type":"Point"}
}