{
  "type": "Feature",
  "properties": {
    "iso:country":"GB",
    "sg:address":"213 Station Road, Rainham",
    "sg:city":"Gillingham",
    "sg:classifiers":[
        {
            "category":"Bars & Pubs",
            "type":"Food & Drink"
        },
        {
            "category":"Community Center",
            "subcategory":"Social",
            "type":"Public Place"
        }
    ],
    "sg:phone":"+44 1634 232178",
    "sg:postcode":"ME8 7PS",
    "sg:province":"Kent",
    "sg:tags":[
        "pubs",
        "house",
        "inn",
        "activity"
    ],
    "wof:name":"David & Janet Ward",
    "wof:placetype":"venue"
},
  "geometry": {"coordinates":[0.6144670248,51.3681259155],"type":"Point"}
}