{
  "type": "Feature",
  "properties": {
    "iso:country":"GB",
    "sg:address":"15 Princess Rd, Strathclyde Business Centre",
    "sg:city":"Motherwell",
    "sg:classifiers":[
        {
            "category":"Manufacturing",
            "subcategory":"Wood Products",
            "type":"Manufacturing & Wholesale Goods"
        }
    ],
    "sg:phone":"+44 1698 734535",
    "sg:postcode":"ML1 4JF",
    "sg:province":"North Lanarkshire",
    "sg:tags":[
        "packaging",
        "crate",
        "pallets"
    ],
    "wof:name":"T C L Total Concept Logistics",
    "wof:placetype":"venue"
},
  "geometry": {"coordinates":[-3.982881,55.813408],"type":"Point"}
}