{
  "type": "Feature",
  "properties": {
    "iso:country":"GB",
    "sg:address":"28 Boston Rd",
    "sg:city":"Sleaford",
    "sg:classifiers":[
        {
            "category":"Retail",
            "subcategory":"Funeral Services",
            "type":"Services"
        }
    ],
    "sg:phone":"+44 1529 307707",
    "sg:postcode":"NG34 7ET",
    "sg:province":"Lincolnshire",
    "wof:name":"David Holland & Son",
    "wof:placetype":"venue"
},
  "geometry": {"coordinates":[-0.40716,52.996845],"type":"Point"}
}