{
  "type": "Feature",
  "properties": {
    "iso:country":"GB",
    "sg:address":"26 Post House, Wynd",
    "sg:city":"Darlington",
    "sg:classifiers":[
        {
            "category":"Shopping",
            "subcategory":"Optician",
            "type":"Retail Goods"
        },
        {
            "category":"Health Services",
            "subcategory":"Optometrist",
            "type":"Services"
        }
    ],
    "sg:phone":"+44 1325 481627",
    "sg:postcode":"DL3 7LP",
    "sg:province":"Durham",
    "wof:name":"G Y D Services",
    "wof:placetype":"venue"
},
  "geometry": {"coordinates":[-1.55683,54.525101],"type":"Point"}
}