{
  "type": "Feature",
  "properties": {
    "iso:country":"GB",
    "sg:address":"18 Wolsey Walk",
    "sg:city":"Woking",
    "sg:classifiers":[
        {
            "category":"Shopping",
            "subcategory":"Books",
            "type":"Retail Goods"
        }
    ],
    "sg:phone":"+44 1483 726938",
    "sg:postcode":"GU21 6XU",
    "sg:province":"Surrey",
    "sg:tags":[
        "bookseller"
    ],
    "wof:name":"Hammicks Bookshops",
    "wof:placetype":"venue"
},
  "geometry": {"coordinates":[-0.55855,51.322075],"type":"Point"}
}