{
  "type": "Feature",
  "properties": {
    "iso:country":"GB",
    "sg:address":"Park Lane",
    "sg:city":"Salford",
    "sg:classifiers":[
        {
            "category":"Education",
            "subcategory":"School",
            "type":"Public Place"
        }
    ],
    "sg:phone":"+44 161 736 3944",
    "sg:postcode":"M6 7RQ",
    "sg:province":"Greater Manchester",
    "sg:tags":[
        "local",
        "authority"
    ],
    "wof:name":"Oakwood High School",
    "wof:placetype":"venue"
},
  "geometry": {"coordinates":[-2.3146839142,53.5003433228],"type":"Point"}
}