{
  "type": "Feature",
  "properties": {
    "iso:country":"GB",
    "sg:address":"154 High Road",
    "sg:city":"Romford",
    "sg:classifiers":[
        {
            "category":"Autos & Motor Vehicles",
            "subcategory":"Automobile Sales",
            "type":"Retail Goods"
        }
    ],
    "sg:phone":"+44 20 8590 5050",
    "sg:postcode":"RM6 6NT",
    "sg:province":"Essex",
    "sg:tags":[
        "car"
    ],
    "wof:name":"David James",
    "wof:placetype":"venue"
},
  "geometry": {"coordinates":[0.138471,51.571918],"type":"Point"}
}