{
  "type": "Feature",
  "properties": {
    "iso:country":"GB",
    "sg:address":"440 Dumbarton Road, Partick",
    "sg:city":"Glasgow",
    "sg:classifiers":[
        {
            "category":"Shopping",
            "subcategory":"Clothing, Apparel, & Fashions",
            "type":"Retail Goods"
        }
    ],
    "sg:postcode":"G11 6SE",
    "sg:province":"Glasgow City",
    "sg:tags":[
        "shop"
    ],
    "wof:name":"Clobber Clothing",
    "wof:placetype":"venue"
},
  "geometry": {"coordinates":[-4.3114228249,55.8709793091],"type":"Point"}
}