{
  "type": "Feature",
  "properties": {
    "addr:full":"156 South Street Dorking Surrey RH4 2HF",
    "addr:housenumber":"156",
    "addr:postcode":"rh4 2hf",
    "addr:street":"South Street",
    "iso:country":"GB",
    "sg:address":"156 South Street",
    "sg:city":"Dorking",
    "sg:classifiers":[
        {
            "category":"Banks & Credit Unions",
            "subcategory":"Financial Services",
            "type":"Services"
        }
    ],
    "sg:phone":"+44 1306 880880",
    "sg:postcode":"RH4 2HF",
    "sg:province":"Surrey",
    "sg:tags":[
        "consultant"
    ],
    "wof:name":"Edwards Securities Ltd.",
    "wof:placetype":"venue"
},
  "geometry": {"coordinates":[-0.3347490132,51.2280387878],"type":"Point"}
}