{
  "type": "Feature",
  "properties": {
    "addr:full":"29 Queen Mary Ave Clydebank East Dunbartonshire G81 2LS",
    "addr:housenumber":"29",
    "addr:postcode":"g81 2ls",
    "addr:street":"Queen Mary Ave",
    "iso:country":"GB",
    "sg:address":"29 Queen Mary Ave",
    "sg:city":"Clydebank",
    "sg:classifiers":[
        {
            "category":"Shopping",
            "subcategory":"Department Store",
            "type":"Retail Goods"
        }
    ],
    "sg:postcode":"G81 2LS",
    "sg:province":"East Dunbartonshire",
    "wof:name":"G & G Stores",
    "wof:placetype":"venue"
},
  "geometry": {"coordinates":[-4.3909549713,55.9071121216],"type":"Point"}
}