{
  "type": "Feature",
  "properties": {
    "addr:full":"Bakers Yard Wantage Berkshire OX12 8PT",
    "addr:postcode":"ox12 8pt",
    "addr:street":"Bakers",
    "iso:country":"GB",
    "sg:address":"Bakers Yard",
    "sg:city":"Wantage",
    "sg:classifiers":[
        {
            "category":"Professional",
            "subcategory":"Art Services",
            "type":"Services"
        }
    ],
    "sg:postcode":"OX12 8PT",
    "sg:province":"Berkshire",
    "sg:tags":[
        "graphic",
        "designer"
    ],
    "wof:name":"Ampersand Design Ltd.",
    "wof:placetype":"venue"
},
  "geometry": {"coordinates":[-1.4236390591,51.5917472839],"type":"Point"}
}