{
  "type": "Feature",
  "properties": {
    "addr:full":"86 Polsloe Road Exeter Devon EX1 2NF",
    "addr:housenumber":"86",
    "addr:postcode":"ex1 2nf",
    "addr:street":"Polsloe Road",
    "iso:country":"GB",
    "sg:address":"86 Polsloe Road",
    "sg:city":"Exeter",
    "sg:classifiers":[
        {
            "category":"Social Services",
            "subcategory":"Retirement Home",
            "type":"Services"
        }
    ],
    "sg:phone":"+44 1392 277451",
    "sg:postcode":"EX1 2NF",
    "sg:province":"Devon",
    "sg:tags":[
        "rest"
    ],
    "wof:name":"Holne Chase",
    "wof:placetype":"venue"
},
  "geometry": {"coordinates":[-3.512028,50.723808],"type":"Point"}
}