{
  "type": "Feature",
  "properties": {
    "addr:full":"153 Dukes Road London Greater London W3 0SL",
    "addr:housenumber":"153",
    "addr:postcode":"w3 0sl",
    "addr:street":"Dukes Road",
    "iso:country":"GB",
    "sg:address":"153 Dukes Road",
    "sg:city":"London",
    "sg:classifiers":[
        {
            "category":"Shopping",
            "subcategory":"Clothing, Apparel, & Fashions",
            "type":"Retail Goods"
        }
    ],
    "sg:phone":"+44 20 8752 1815",
    "sg:postcode":"W3 0SL",
    "sg:province":"Greater London",
    "sg:tags":[
        "clothing"
    ],
    "wof:name":"Nak Trading Co. Ltd.",
    "wof:placetype":"venue"
},
  "geometry": {"coordinates":[-0.282543987,51.5260429382],"type":"Point"}
}