{
  "type": "Feature",
  "properties": {
    "iso:country":"GB",
    "sg:address":"32 Hazel Rd",
    "sg:city":"Camberley",
    "sg:classifiers":[
        {
            "category":"Building & Trades",
            "subcategory":"Construction",
            "type":"Services"
        }
    ],
    "sg:phone":"+44 1252 547869",
    "sg:postcode":"GU16 6BB",
    "sg:province":"Hampshire",
    "sg:tags":[
        "builder"
    ],
    "wof:name":"E K Building Services",
    "wof:placetype":"venue"
},
  "geometry": {"coordinates":[-0.723717,51.284279],"type":"Point"}
}