{
  "type": "Feature",
  "properties": {
    "addr:full":"Netherley Road, Tarbock Grn Prescot Cheshire L35 1QG",
    "addr:postcode":"l35 1qg",
    "addr:street":"Netherley Road",
    "iso:country":"GB",
    "sg:address":"Netherley Road, Tarbock Grn",
    "sg:city":"Prescot",
    "sg:classifiers":[
        {
            "category":"Bars & Pubs",
            "type":"Food & Drink"
        }
    ],
    "sg:postcode":"L35 1QG",
    "sg:province":"Cheshire",
    "sg:tags":[
        "pubs",
        "inn"
    ],
    "wof:name":"Brickwall Inn",
    "wof:placetype":"venue"
},
  "geometry": {"coordinates":[-2.8139309883,53.3836097717],"type":"Point"}
}