{
  "type": "Feature",
  "properties": {
    "iso:country":"GB",
    "sg:address":"Delmeade Road",
    "sg:city":"Chesham",
    "sg:classifiers":[
        {
            "category":"Building & Trades",
            "subcategory":"Construction",
            "type":"Services"
        }
    ],
    "sg:phone":"+44 1494 782392",
    "sg:postcode":"HP5 1JS",
    "sg:province":"Buckinghamshire",
    "sg:tags":[
        "builder"
    ],
    "wof:name":"T Y Evans & Sons",
    "wof:placetype":"venue"
},
  "geometry": {"coordinates":[-0.619888,51.700588],"type":"Point"}
}