{
  "type": "Feature",
  "properties": {
    "addr:full":"80 Drake Street Rochdale Lancashire OL16 1PQ",
    "addr:housenumber":"80",
    "addr:postcode":"ol16 1pq",
    "addr:street":"Drake Street",
    "iso:country":"GB",
    "sg:address":"80 Drake Street",
    "sg:city":"Rochdale",
    "sg:classifiers":[
        {
            "category":"Fast Food",
            "type":"Food & Drink"
        }
    ],
    "sg:phone":"+44 1706 712221",
    "sg:postcode":"OL16 1PQ",
    "sg:province":"Lancashire",
    "sg:tags":[
        "away",
        "meal",
        "outlet",
        "take"
    ],
    "wof:name":"Spice Of Asia",
    "wof:placetype":"venue"
},
  "geometry": {"coordinates":[-2.1544210911,53.6152000427],"type":"Point"}
}