{
  "type": "Feature",
  "properties": {
    "iso:country":"GB",
    "sg:address":"80 Victoria Road",
    "sg:city":"Widnes",
    "sg:classifiers":[
        {
            "category":"Insurance",
            "subcategory":"Insurance Agent",
            "type":"Services"
        }
    ],
    "sg:phone":"+44 151 420 1795",
    "sg:postcode":"WA8 7RH",
    "sg:province":"Cheshire",
    "wof:name":"Halton Insurance Services Ltd.",
    "wof:placetype":"venue"
},
  "geometry": {"coordinates":[-2.7338171005,53.3614196777],"type":"Point"}
}