{
  "type": "Feature",
  "properties": {
    "iso:country":"GB",
    "sg:address":"22 Kendrick Street",
    "sg:city":"Stroud",
    "sg:classifiers":[
        {
            "category":"Food & Beverages",
            "subcategory":"Bakery",
            "type":"Retail Goods"
        }
    ],
    "sg:phone":"+44 1453 762441",
    "sg:postcode":"GL5 1AQ",
    "sg:province":"Gloucestershire",
    "sg:tags":[
        "shop",
        "baker"
    ],
    "wof:name":"Walkers The Bakers",
    "wof:placetype":"venue"
},
  "geometry": {"coordinates":[-2.216186,51.745064],"type":"Point"}
}