{
  "type": "Feature",
  "properties": {
    "iso:country":"GB",
    "sg:address":"6 Langdon Close",
    "sg:city":"Camberley",
    "sg:classifiers":[
        {
            "category":"Taxi",
            "type":"Transportation"
        }
    ],
    "sg:phone":"+44 1276 681871",
    "sg:postcode":"GU15 1AQ",
    "sg:province":"Berkshire",
    "sg:tags":[
        "mini",
        "cab"
    ],
    "wof:name":"Victory Minibus & Taxi Services",
    "wof:placetype":"venue"
},
  "geometry": {"coordinates":[-0.707396,51.331669],"type":"Point"}
}