{
  "type": "Feature",
  "properties": {
    "addr:full":"6 North Street, Titchmarsh Kettering Northamptonshire NN14 3DH",
    "addr:housenumber":"6",
    "addr:postcode":"nn14 3dh",
    "addr:street":"North Street",
    "iso:country":"GB",
    "sg:address":"6 North Street, Titchmarsh",
    "sg:city":"Kettering",
    "sg:classifiers":[
        {
            "category":"Arena",
            "subcategory":"Sports Club",
            "type":"Entertainment"
        }
    ],
    "sg:postcode":"NN14 3DH",
    "sg:province":"Northamptonshire",
    "wof:name":"The British Sub-Aqua Club",
    "wof:placetype":"venue"
},
  "geometry": {"coordinates":[-0.4947429895,52.4050750732],"type":"Point"}
}