{
  "type": "Feature",
  "properties": {
    "addr:full":"Greenleaf House, Darkes Lane Potters Bar Greater London EN6 1AE",
    "addr:postcode":"en6 1ae",
    "addr:street":"Darkes Lane",
    "iso:country":"GB",
    "sg:address":"Greenleaf House, Darkes Lane",
    "sg:city":"Potters Bar",
    "sg:classifiers":[
        {
            "category":"Travel",
            "subcategory":"Travel Agent",
            "type":"Entertainment"
        }
    ],
    "sg:phone":"+44 1707 660011",
    "sg:postcode":"EN6 1AE",
    "sg:province":"Greater London",
    "wof:name":"Partners in Travel Ltd.",
    "wof:placetype":"venue"
},
  "geometry": {"coordinates":[-0.188094005,51.7016601562],"type":"Point"}
}