{
  "type": "Feature",
  "properties": {
    "addr:full":"The Beacons, 1 School Lane Liverpool Lancashire L37 3LN",
    "addr:housenumber":"1",
    "addr:postcode":"l37 3ln",
    "addr:street":"School Lane",
    "iso:country":"GB",
    "sg:address":"The Beacons, 1 School Lane",
    "sg:city":"Liverpool",
    "sg:classifiers":[
        {
            "category":"Professional",
            "subcategory":"Lawyer & Legal Services",
            "type":"Services"
        }
    ],
    "sg:postcode":"L37 3LN",
    "sg:province":"Lancashire",
    "sg:tags":[
        "solicitor"
    ],
    "wof:name":"Andrew Norton Solicitors",
    "wof:placetype":"venue"
},
  "geometry": {"coordinates":[-3.0583899021,53.5578804016],"type":"Point"}
}