{
  "type": "Feature",
  "properties": {
    "iso:country":"GB",
    "sg:address":"57 Albert Road",
    "sg:city":"Tamworth",
    "sg:classifiers":[
        {
            "category":"Health Services",
            "subcategory":"Dentist",
            "type":"Services"
        }
    ],
    "sg:phone":"+44 1827 66435",
    "sg:postcode":"B79 7JN",
    "sg:province":"Staffordshire",
    "wof:name":"NIGEL P HARRISON",
    "wof:placetype":"venue"
},
  "geometry": {"coordinates":[-1.68818295,52.6364860535],"type":"Point"}
}