{
  "type": "Feature",
  "properties": {
    "iso:country":"GB",
    "sg:address":"Hipley Close, Woodley",
    "sg:city":"Stockport",
    "sg:classifiers":[
        {
            "category":"Social Services",
            "subcategory":"Child Care",
            "type":"Services"
        },
        {
            "category":"Social Services",
            "subcategory":"Adult Care",
            "type":"Services"
        }
    ],
    "sg:phone":"+44 161 430 4871",
    "sg:postcode":"SK6 1ES",
    "sg:province":"Cheshire",
    "sg:tags":[
        "day",
        "centre"
    ],
    "wof:name":"Arthur Greenwood Day Centre",
    "wof:placetype":"venue"
},
  "geometry": {"coordinates":[-2.097542,53.426571],"type":"Point"}
}