{
  "type": "Feature",
  "properties": {
    "iso:country":"GB",
    "sg:address":"501b Sipson Road, Sipson",
    "sg:city":"West Drayton",
    "sg:classifiers":[
        {
            "category":"Sports & Exercise",
            "subcategory":"Tennis Court",
            "type":"Entertainment"
        }
    ],
    "sg:postcode":"UB7 0JB",
    "sg:province":"Greater London",
    "sg:tags":[
        "breakdown",
        "recovery"
    ],
    "wof:name":"Middlesex Recovery",
    "wof:placetype":"venue"
},
  "geometry": {"coordinates":[-0.453711,51.485397],"type":"Point"}
}