{
  "type": "Feature",
  "properties": {
    "iso:country":"GB",
    "sg:address":"249 Birmingham Road",
    "sg:city":"Sutton Coldfield",
    "sg:classifiers":[
        {
            "category":"Organizations",
            "subcategory":"Non-profit Organization",
            "type":"Services"
        }
    ],
    "sg:phone":"+44 121 355 2707",
    "sg:postcode":"B72 1EA",
    "sg:province":"West Midlands",
    "sg:tags":[
        "charitable",
        "organisation",
        "voluntary",
        "charity"
    ],
    "wof:name":"Kids",
    "wof:placetype":"venue"
},
  "geometry": {"coordinates":[-1.826818943,52.5576896667],"type":"Point"}
}