{
  "type": "Feature",
  "properties": {
    "addr:full":"48 Church Way, Whetstone London Greater London N20 0LA",
    "addr:housenumber":"48",
    "addr:postcode":"n20 0la",
    "addr:street":"Church Way",
    "iso:country":"GB",
    "sg:address":"48 Church Way, Whetstone",
    "sg:city":"London",
    "sg:classifiers":[
        {
            "category":"Real Estate",
            "subcategory":"Real Estate Agent",
            "type":"Services"
        }
    ],
    "sg:phone":"+44 20 8361 6910",
    "sg:postcode":"N20 0LA",
    "sg:province":"Greater London",
    "wof:name":"Plan of Action",
    "wof:placetype":"venue"
},
  "geometry": {"coordinates":[-0.1646029949,51.6236915588],"type":"Point"}
}