{
  "type": "Feature",
  "properties": {
    "addr:full":"120 Elm Lane Sheffield South Yorkshire S5 7TW",
    "addr:housenumber":"120",
    "addr:postcode":"s5 7tw",
    "addr:street":"Elm Lane",
    "iso:country":"GB",
    "sg:address":"120 Elm Lane",
    "sg:city":"Sheffield",
    "sg:classifiers":[
        {
            "category":"Building & Trades",
            "subcategory":"Landscaping Services",
            "type":"Services"
        }
    ],
    "sg:phone":"+44 114 246 4649",
    "sg:postcode":"S5 7TW",
    "sg:province":"South Yorkshire",
    "sg:tags":[
        "pond",
        "aquarium"
    ],
    "wof:name":"Elm Lane Tropicals",
    "wof:placetype":"venue"
},
  "geometry": {"coordinates":[-1.4607440233,53.4215545654],"type":"Point"}
}