{
  "type": "Feature",
  "properties": {
    "iso:country":"GB",
    "sg:address":"36 Warrington Avenue",
    "sg:city":"Slough",
    "sg:classifiers":[
        {
            "category":"Manufacturing",
            "subcategory":"Pottery",
            "type":"Manufacturing & Wholesale Goods"
        }
    ],
    "sg:phone":"+44 1753 573606",
    "sg:postcode":"SL1 3BQ",
    "sg:province":"Berkshire",
    "wof:name":"Butterfly Ceramics",
    "wof:placetype":"venue"
},
  "geometry": {"coordinates":[-0.611547,51.523827],"type":"Point"}
}