{
  "type": "Feature",
  "properties": {
    "addr:full":"Unit 17a, 12 Brunel Plaza Swindon Wiltshire SN1 1LS",
    "addr:housenumber":"unit 17a 12;plaza",
    "addr:postcode":"sn1 1ls",
    "addr:street":"Brunel",
    "iso:country":"GB",
    "sg:address":"Unit 17a, 12 Brunel Plaza",
    "sg:city":"Swindon",
    "sg:classifiers":[
        {
            "category":"Sports & Exercise",
            "subcategory":"Sports Center",
            "type":"Entertainment"
        }
    ],
    "sg:phone":"+44 1793 430331",
    "sg:postcode":"SN1 1LS",
    "sg:province":"Wiltshire",
    "sg:tags":[
        "shop",
        "good"
    ],
    "wof:name":"Hargreaves Sports",
    "wof:placetype":"venue"
},
  "geometry": {"coordinates":[-1.784979,51.563229],"type":"Point"}
}