{
  "type": "Feature",
  "properties": {
    "addr:full":"8 Whitburn Place, Downfield Dundee Dundee City DD3 0SA",
    "addr:housenumber":"8",
    "addr:postcode":"dd3 0sa",
    "addr:street":"Whitburn Place Downfield",
    "iso:country":"GB",
    "sg:address":"8 Whitburn Place, Downfield",
    "sg:city":"Dundee",
    "sg:classifiers":[
        {
            "category":"Building & Trades",
            "subcategory":"Construction",
            "type":"Services"
        }
    ],
    "sg:phone":"+44 1382 816626",
    "sg:postcode":"DD3 0SA",
    "sg:province":"Dundee City",
    "sg:tags":[
        "heating",
        "contractor"
    ],
    "wof:name":"Flame-on Combustion Services",
    "wof:placetype":"venue"
},
  "geometry": {"coordinates":[-2.9915618896,56.4963417053],"type":"Point"}
}