{
  "type": "Feature",
  "properties": {
    "addr:full":"The Cottage, Bolton Junction Bradford West Yorkshire BD2 4JY",
    "addr:postcode":"bd2 4jy",
    "iso:country":"GB",
    "sg:address":"The Cottage, Bolton Junction",
    "sg:city":"Bradford",
    "sg:classifiers":[
        {
            "category":"Personal",
            "type":"Services"
        }
    ],
    "sg:postcode":"BD2 4JY",
    "sg:province":"West Yorkshire",
    "sg:tags":[
        "wedding"
    ],
    "wof:name":"Jackson,Maureen,",
    "wof:placetype":"venue"
},
  "geometry": {"coordinates":[-1.7341599464,53.8163795471],"type":"Point"}
}