{
  "type": "Feature",
  "properties": {
    "iso:country":"GB",
    "sg:address":"Orwell Pit Farm, Downham Road",
    "sg:city":"Ely",
    "sg:classifiers":[
        {
            "category":"Farming",
            "subcategory":"Livestock Farm",
            "type":"Manufacturing & Wholesale Goods"
        }
    ],
    "sg:phone":"+44 1353 662316",
    "sg:postcode":"CB6 2SJ",
    "sg:province":"Cambridgeshire",
    "sg:tags":[
        "others"
    ],
    "wof:name":"W R Jackson & Son",
    "wof:placetype":"venue"
},
  "geometry": {"coordinates":[0.25776,52.418812],"type":"Point"}
}