{
  "type": "Feature",
  "properties": {
    "addr:full":"Unit 2b, Alderdiscott Road Industrial Estate Bideford Devon EX39 4LX",
    "addr:housenumber":"unit 2b",
    "addr:postcode":"ex39 4lx",
    "addr:street":"Alderdiscott Road Industrial Estate",
    "iso:country":"GB",
    "sg:address":"Unit 2b, Alderdiscott Road Industrial Estate",
    "sg:city":"Bideford",
    "sg:classifiers":[
        {
            "category":"Retail",
            "subcategory":"Auto Repair",
            "type":"Services"
        }
    ],
    "sg:phone":"+44 1237 471953",
    "sg:postcode":"EX39 4LX",
    "sg:province":"Devon",
    "sg:tags":[
        "modification",
        "garage"
    ],
    "wof:name":"Bideford Auto Services",
    "wof:placetype":"venue"
},
  "geometry": {"coordinates":[-4.1843438148,51.0125732422],"type":"Point"}
}