{
  "type": "Feature",
  "properties": {
    "iso:country":"GB",
    "sg:address":"59 Glebe Street",
    "sg:city":"Stranraer",
    "sg:classifiers":[
        {
            "category":"Bars & Pubs",
            "type":"Food & Drink"
        }
    ],
    "sg:postcode":"DG9 7LR",
    "sg:province":"Dumfries and Galloway",
    "sg:tags":[
        "pubs",
        "inn"
    ],
    "wof:name":"Sheuchan Arms",
    "wof:placetype":"venue"
},
  "geometry": {"coordinates":[-5.034329,54.902859],"type":"Point"}
}