{
  "type": "Feature",
  "properties": {
    "addr:full":"83 Lomond Gro, Camberwell London Greater London SE5 7HN",
    "addr:housenumber":"83",
    "addr:postcode":"se5 7hn",
    "addr:street":"Lomond Gro",
    "iso:country":"GB",
    "sg:address":"83 Lomond Gro, Camberwell",
    "sg:city":"London",
    "sg:classifiers":[
        {
            "category":"Shopping",
            "subcategory":"Computers & Home Electronics",
            "type":"Retail Goods"
        }
    ],
    "sg:phone":"+44 20 7703 0888",
    "sg:postcode":"SE5 7HN",
    "sg:province":"Greater London",
    "sg:tags":[
        "electrical"
    ],
    "wof:name":"Walsall Electrical",
    "wof:placetype":"venue"
},
  "geometry": {"coordinates":[-0.091646,51.476608],"type":"Point"}
}