{
  "type": "Feature",
  "properties": {
    "addr:full":"37 Clyde Square Hemel Hempstead Hertfordshire HP2 6EF",
    "addr:housenumber":"37",
    "addr:postcode":"hp2 6ef",
    "addr:street":"Clyde Square",
    "iso:country":"GB",
    "sg:address":"37 Clyde Square",
    "sg:city":"Hemel Hempstead",
    "sg:classifiers":[
        {
            "category":"Building & Trades",
            "subcategory":"Construction",
            "type":"Services"
        }
    ],
    "sg:phone":"+44 1442 251823",
    "sg:postcode":"HP2 6EF",
    "sg:province":"Hertfordshire",
    "sg:tags":[
        "builder"
    ],
    "wof:name":"I D Golding",
    "wof:placetype":"venue"
},
  "geometry": {"coordinates":[-0.4532279968,51.776725769],"type":"Point"}
}