{
  "type": "Feature",
  "properties": {
    "iso:country":"GB",
    "sg:address":"201 Gainsborough Crescent, Oscott",
    "sg:city":"Birmingham",
    "sg:classifiers":[
        {
            "category":"Building & Trades",
            "subcategory":"Construction",
            "type":"Services"
        }
    ],
    "sg:phone":"+44 121 360 7923",
    "sg:postcode":"B43 7TX",
    "sg:province":"West Midlands",
    "sg:tags":[
        "decorator",
        "painter"
    ],
    "wof:name":"P Cornfield",
    "wof:placetype":"venue"
},
  "geometry": {"coordinates":[-1.898892,52.562138],"type":"Point"}
}