{
  "type": "Feature",
  "properties": {
    "addr:full":"Unit 15, Yates Ind Est, Lime Lane, Pelsall Walsall Staffordshire WS3 5AS",
    "addr:housenumber":"unit 15",
    "addr:postcode":"ws3 5as",
    "addr:street":"Lime Lane",
    "iso:country":"GB",
    "sg:address":"Unit 15, Yates Ind Est, Lime Lane, Pelsall",
    "sg:city":"Walsall",
    "sg:classifiers":[
        {
            "category":"Wholesale",
            "subcategory":"Scrap",
            "type":"Manufacturing & Wholesale Goods"
        }
    ],
    "sg:phone":"+44 1543 370077",
    "sg:postcode":"WS3 5AS",
    "sg:province":"Staffordshire",
    "sg:tags":[
        "car",
        "breaker",
        "dismantlers"
    ],
    "wof:name":"P & S Vauxhall Spares",
    "wof:placetype":"venue"
},
  "geometry": {"coordinates":[-1.9674,52.62904],"type":"Point"}
}