{
  "type": "Feature",
  "properties": {
    "iso:country":"GB",
    "sg:address":"1 Silk House, Park Grn",
    "sg:city":"Macclesfield",
    "sg:classifiers":[
        {
            "category":"Home & Garden",
            "subcategory":"Household Appliances",
            "type":"Retail Goods"
        }
    ],
    "sg:phone":"+44 1625 500789",
    "sg:postcode":"SK11 7QJ",
    "sg:province":"Cheshire",
    "sg:tags":[
        "gas"
    ],
    "wof:name":"The Gas Man",
    "wof:placetype":"venue"
},
  "geometry": {"coordinates":[-2.1257560253,53.2556686401],"type":"Point"}
}