{
  "type": "Feature",
  "properties": {
    "addr:full":"Wainwright Street Dukinfield Greater Manchester SK16 5PL",
    "addr:postcode":"sk16 5pl",
    "addr:street":"Wainwright Street",
    "iso:country":"GB",
    "sg:address":"Wainwright Street",
    "sg:city":"Dukinfield",
    "sg:classifiers":[
        {
            "category":"Manufacturing",
            "subcategory":"Glass & Minerals",
            "type":"Manufacturing & Wholesale Goods"
        }
    ],
    "sg:postcode":"SK16 5PL",
    "sg:province":"Greater Manchester",
    "sg:tags":[
        "fibre",
        "material"
    ],
    "wof:name":"Resin Glass Products Ltd.",
    "wof:placetype":"venue"
},
  "geometry": {"coordinates":[-2.0773990154,53.4814491272],"type":"Point"}
}