{
  "type": "Feature",
  "properties": {
    "iso:country":"GB",
    "sg:address":"1 Adam St",
    "sg:city":"Stockton-on-tees",
    "sg:classifiers":[
        {
            "category":"Bars & Pubs",
            "type":"Food & Drink"
        }
    ],
    "sg:postcode":"TS18 3HQ",
    "sg:province":"Durham",
    "sg:tags":[
        "pubs",
        "inn"
    ],
    "wof:name":"Cook,C B,",
    "wof:placetype":"venue"
},
  "geometry": {"coordinates":[-1.316608,54.54863],"type":"Point"}
}