{
  "type": "Feature",
  "properties": {
    "addr:full":"Raf Buchan Sta, Boddam Peterhead Aberdeenshire AB42 3AR",
    "addr:postcode":"ab42 3ar",
    "iso:country":"GB",
    "sg:address":"Raf Buchan Sta, Boddam",
    "sg:city":"Peterhead",
    "sg:classifiers":[
        {
            "category":"Professional",
            "subcategory":"Management & Consulting",
            "type":"Services"
        },
        {
            "category":"Building & Trades",
            "subcategory":"Cleaning & Sanitation",
            "type":"Services"
        },
        {
            "category":"Real Estate",
            "subcategory":"Real Estate Services",
            "type":"Services"
        }
    ],
    "sg:phone":"+44 1779 490422",
    "sg:postcode":"AB42 3AR",
    "sg:province":"Aberdeenshire",
    "sg:tags":[
        "project",
        "facility"
    ],
    "wof:name":"Turner Facilities Management Ltd.",
    "wof:placetype":"venue"
},
  "geometry": {"coordinates":[-1.7826039791,57.4727363586],"type":"Point"}
}