{
  "type": "Feature",
  "properties": {
    "iso:country":"GB",
    "sg:address":"Delta Close",
    "sg:city":"Norwich",
    "sg:classifiers":[
        {
            "category":"Professional",
            "subcategory":"Engineering",
            "type":"Services"
        },
        {
            "category":"Building & Trades",
            "subcategory":"Electrical",
            "type":"Services"
        }
    ],
    "sg:phone":"+44 1603 482288",
    "sg:postcode":"NR6 6BG",
    "sg:province":"Norfolk",
    "sg:tags":[
        "engineer",
        "electrician",
        "contractor"
    ],
    "wof:name":"Dodd Group Eastern Ltd",
    "wof:placetype":"venue"
},
  "geometry": {"coordinates":[1.287095,52.6586],"type":"Point"}
}