{
  "type": "Feature",
  "properties": {
    "iso:country":"GB",
    "sg:address":"Myrtle Cottage, Station Road",
    "sg:city":"Newport",
    "sg:classifiers":[
        {
            "category":"Building & Trades",
            "subcategory":"Construction",
            "type":"Services"
        }
    ],
    "sg:phone":"+44 1633 413660",
    "sg:postcode":"NP18 2DW",
    "sg:province":"Monmouthshire",
    "sg:tags":[
        "roofing"
    ],
    "wof:name":"Clode G E Felt Roofing Specialist & Services",
    "wof:placetype":"venue"
},
  "geometry": {"coordinates":[-2.9147601128,51.5869293213],"type":"Point"}
}