{
  "type": "Feature",
  "properties": {
    "addr:full":"Fiveways Garage, Chester High Rd South Wirral Cheshire CH64 3RY",
    "addr:postcode":"ch64 3ry",
    "addr:street":"High Rd South",
    "iso:country":"GB",
    "sg:address":"Fiveways Garage, Chester High Rd",
    "sg:city":"South Wirral",
    "sg:classifiers":[
        {
            "category":"Retail",
            "subcategory":"Auto Repair",
            "type":"Services"
        }
    ],
    "sg:phone":"+44 151 353 0999",
    "sg:postcode":"CH64 3RY",
    "sg:province":"Cheshire",
    "sg:tags":[
        "modification",
        "garage"
    ],
    "wof:name":"Mitchell Neston",
    "wof:placetype":"venue"
},
  "geometry": {"coordinates":[-3.0556099415,53.3062705994],"type":"Point"}
}