{
  "type": "Feature",
  "properties": {
    "iso:country":"GB",
    "sg:address":"71 West Street",
    "sg:city":"Boston",
    "sg:classifiers":[
        {
            "category":"Bars & Pubs",
            "type":"Food & Drink"
        },
        {
            "category":"Community Center",
            "subcategory":"Social",
            "type":"Public Place"
        }
    ],
    "sg:phone":"+44 1205 361436",
    "sg:postcode":"PE21 8QZ",
    "sg:province":"Lincolnshire",
    "sg:tags":[
        "pubs",
        "house",
        "inn",
        "activity"
    ],
    "wof:name":"The Jolly Crispin",
    "wof:placetype":"venue"
},
  "geometry": {"coordinates":[-0.0291799996,52.9762077332],"type":"Point"}
}