{
  "type": "Feature",
  "properties": {
    "iso:country":"GB",
    "sg:address":"Harbour Head",
    "sg:city":"Glenrothes",
    "sg:classifiers":[
        {
            "category":"Landmark",
            "subcategory":"Tourist Information",
            "type":"Public Place"
        }
    ],
    "sg:phone":"+44 1333 311073",
    "sg:postcode":"KY7 6AQ",
    "sg:province":"Fife",
    "wof:name":"Kingdom Of Fife Tourist",
    "wof:placetype":"venue"
},
  "geometry": {"coordinates":[-3.1737439632,56.1972084045],"type":"Point"}
}