{
  "type": "Feature",
  "properties": {
    "addr:full":"Unit 9 Marshall Road, Hillmead Swindon Wiltshire SN5 5YY",
    "addr:housenumber":"unit 9",
    "addr:postcode":"sn5 5yy",
    "addr:street":"Marshall Road",
    "iso:country":"GB",
    "sg:address":"Unit 9 Marshall Road, Hillmead",
    "sg:city":"Swindon",
    "sg:classifiers":[
        {
            "category":"Manufacturing",
            "subcategory":"Buildings",
            "type":"Manufacturing & Wholesale Goods"
        },
        {
            "category":"Professional",
            "type":"Services"
        }
    ],
    "sg:phone":"+44 1793 898700",
    "sg:postcode":"SN5 5YY",
    "sg:province":"Wiltshire",
    "sg:tags":[
        "control",
        "system",
        "air conditioning"
    ],
    "wof:name":"Johnson Control Systems Ltd.",
    "wof:placetype":"venue"
},
  "geometry": {"coordinates":[-1.830922,51.571823],"type":"Point"}
}