{
  "type": "Feature",
  "properties": {
    "addr:full":"Scotts Green Close, Russells Hall Dudley West Midlands DY1 2DU",
    "addr:postcode":"russells;dy1 2du",
    "addr:street":"Scotts Green Close",
    "iso:country":"GB",
    "sg:address":"Scotts Green Close, Russells Hall",
    "sg:city":"Dudley",
    "sg:classifiers":[
        {
            "category":"Education",
            "subcategory":"School",
            "type":"Public Place"
        },
        {
            "category":"Government",
            "subcategory":"Office",
            "type":"Public Place"
        }
    ],
    "sg:phone":"+44 1384 818670",
    "sg:postcode":"DY1 2DU",
    "sg:province":"West Midlands",
    "sg:tags":[
        "local",
        "authority"
    ],
    "wof:name":"Sutton School",
    "wof:placetype":"venue"
},
  "geometry": {"coordinates":[-2.101954937,52.5062103271],"type":"Point"}
}