{
  "type": "Feature",
  "properties": {
    "addr:full":"Attleborough House, Townsend Drive, Attleborough Fields Industrial E Nuneaton Leicestershire CV11 6RU",
    "addr:postcode":"cv11 6ru",
    "addr:street":"Townsend Drive;Fields Industrial E",
    "iso:country":"GB",
    "sg:address":"Attleborough House, Townsend Drive, Attleborough Fields Industrial E",
    "sg:city":"Nuneaton",
    "sg:classifiers":[
        {
            "category":"Shopping",
            "subcategory":"Clothing, Apparel, & Fashions",
            "type":"Retail Goods"
        },
        {
            "category":"Shopping",
            "subcategory":"Baby Store",
            "type":"Retail Goods"
        }
    ],
    "sg:phone":"+44 24 7635 1000",
    "sg:postcode":"CV11 6RU",
    "sg:province":"Leicestershire",
    "sg:tags":[
        "child",
        "childrens",
        "babywear"
    ],
    "sg:website":"http://www.adams.co.uk",
    "wof:name":"Adams Childrenswear Ltd",
    "wof:placetype":"venue"
},
  "geometry": {"coordinates":[-1.3938699961,52.5067329407],"type":"Point"}
}