{
  "type": "Feature",
  "properties": {
    "iso:country":"GB",
    "sg:address":"8 Park Avenue, Woodthorpe",
    "sg:city":"Nottingham",
    "sg:classifiers":[
        {
            "category":"Professional",
            "subcategory":"Engineering",
            "type":"Services"
        }
    ],
    "sg:postcode":"NG5 4HS",
    "sg:province":"Nottinghamshire",
    "sg:tags":[
        "contractor",
        "electrical",
        "engineer"
    ],
    "wof:name":"A J Gilbert",
    "wof:placetype":"venue"
},
  "geometry": {"coordinates":[-1.134654,52.993221],"type":"Point"}
}