{
  "type": "Feature",
  "properties": {
    "addr:full":"7 George Hse, Kings Ct, Manor Rd Chichester West Sussex PO20 0RZ",
    "addr:housenumber":"7",
    "addr:postcode":"po20 0rz",
    "addr:street":"George Hse Kings Ct Manor Rd",
    "iso:country":"GB",
    "sg:address":"7 George Hse, Kings Ct, Manor Rd",
    "sg:city":"Chichester",
    "sg:classifiers":[
        {
            "category":"Building & Trades",
            "subcategory":"Landscaping Services",
            "type":"Services"
        }
    ],
    "sg:phone":"+44 1243 604642",
    "sg:postcode":"PO20 0RZ",
    "sg:province":"West Sussex",
    "sg:tags":[
        "landscape",
        "contractor"
    ],
    "wof:name":"CGS Landscapes (Incorporating Complete Garden Services)",
    "wof:placetype":"venue"
},
  "geometry": {"coordinates":[-0.783190012,50.7364501953],"type":"Point"}
}