{
  "type": "Feature",
  "properties": {
    "addr:full":"Brent Terrace N. Circular Rd, Hendon Cricklewood Greater London NW2 1LN",
    "addr:postcode":"nw2 1ln",
    "addr:street":"Brent Terrace N. Circular Rd",
    "iso:country":"GB",
    "sg:address":"Brent Terrace N. Circular Rd, Hendon",
    "sg:city":"Cricklewood",
    "sg:classifiers":[
        {
            "category":"Home & Garden",
            "subcategory":"Building Materials",
            "type":"Retail Goods"
        }
    ],
    "sg:phone":"+44 20 8452 1738",
    "sg:postcode":"NW2 1LN",
    "sg:province":"Greater London",
    "sg:tags":[
        "ready",
        "mixed",
        "concrete"
    ],
    "wof:name":"Ready Mixed Concrete Ltd",
    "wof:placetype":"venue"
},
  "geometry": {"coordinates":[-0.225717,51.57106],"type":"Point"}
}