{
  "type": "Feature",
  "properties": {
    "addr:full":"773 London Road High Wycombe Buckinghamshire HP11 1HW",
    "addr:housenumber":"773",
    "addr:postcode":"hp11 1hw",
    "addr:street":"London Road",
    "iso:country":"GB",
    "sg:address":"773 London Road",
    "sg:city":"High Wycombe",
    "sg:classifiers":[
        {
            "category":"Retail",
            "subcategory":"Auto Repair",
            "type":"Services"
        }
    ],
    "sg:phone":"+44 1494 445829",
    "sg:postcode":"HP11 1HW",
    "sg:province":"Buckinghamshire",
    "sg:tags":[
        "engine",
        "specialist",
        "diagnostic",
        "tuning",
        "car"
    ],
    "wof:name":"Mobile Electronic Tuning Services",
    "wof:placetype":"venue"
},
  "geometry": {"coordinates":[-0.7040389776,51.6127128601],"type":"Point"}
}