{
  "type": "Feature",
  "properties": {
    "iso:country":"GB",
    "sg:address":"Unit 2etrecurus Indust Est",
    "sg:city":"Padstow",
    "sg:classifiers":[
        {
            "category":"Sports & Exercise",
            "subcategory":"Gym",
            "type":"Entertainment"
        }
    ],
    "sg:phone":"+44 1841 533465",
    "sg:postcode":"PL28 8RW",
    "sg:province":"Cornwall",
    "sg:tags":[
        "fitness",
        "health",
        "centre"
    ],
    "wof:name":"Geneo All American Fitness Studio",
    "wof:placetype":"venue"
},
  "geometry": {"coordinates":[-4.941839,50.537365],"type":"Point"}
}