{
  "type": "Feature",
  "properties": {
    "iso:country":"GB",
    "sg:address":"Rainbow Shaw, Holford Road, Linford",
    "sg:city":"Stanford-le-hope",
    "sg:classifiers":[
        {
            "category":"Home & Garden",
            "subcategory":"Garden Supply",
            "type":"Retail Goods"
        },
        {
            "category":"Mining & Drilling",
            "type":"Manufacturing & Wholesale Goods"
        }
    ],
    "sg:phone":"+44 1375 644445",
    "sg:postcode":"SS17 0PJ",
    "sg:province":"Essex",
    "sg:tags":[
        "sand",
        "gravel",
        "quarry"
    ],
    "wof:name":"Clearserve Ltd.",
    "wof:placetype":"venue"
},
  "geometry": {"coordinates":[0.41475,51.513645],"type":"Point"}
}