{
  "type": "Feature",
  "properties": {
    "addr:full":"Unit 62, Anne Rd Smethwick West Midlands B66 2NZ",
    "addr:housenumber":"unit 62",
    "addr:postcode":"b66 2nz",
    "addr:street":"Anne Rd",
    "iso:country":"GB",
    "sg:address":"Unit 62, Anne Rd",
    "sg:city":"Smethwick",
    "sg:classifiers":[
        {
            "category":"Autos & Motor Vehicles",
            "subcategory":"Auto Supplies",
            "type":"Retail Goods"
        }
    ],
    "sg:phone":"+44 121 555 8801",
    "sg:postcode":"B66 2NZ",
    "sg:province":"West Midlands",
    "sg:tags":[
        "towing",
        "eqpt",
        "trailer"
    ],
    "wof:name":"Ejectors UK Ltd",
    "wof:placetype":"venue"
},
  "geometry": {"coordinates":[-1.94816,52.500179],"type":"Point"}
}