{
  "type": "Feature",
  "properties": {
    "iso:country":"GB",
    "sg:address":"53 Burrell Close",
    "sg:city":"Edgware",
    "sg:classifiers":[
        {
            "category":"Building & Trades",
            "subcategory":"Plumbing",
            "type":"Services"
        }
    ],
    "sg:phone":"+44 20 8958 1582",
    "sg:postcode":"HA8 8YZ",
    "sg:province":"Greater London",
    "sg:tags":[
        "heating"
    ],
    "wof:name":"A J C Plumbing",
    "wof:placetype":"venue"
},
  "geometry": {"coordinates":[-0.268074,51.630611],"type":"Point"}
}