{
  "type": "Feature",
  "properties": {
    "iso:country":"GB",
    "sg:address":"41 King St",
    "sg:city":"Wigan",
    "sg:classifiers":[
        {
            "category":"Professional",
            "subcategory":"Engineering",
            "type":"Services"
        }
    ],
    "sg:phone":"+44 1942 767600",
    "sg:postcode":"WN1 1DY",
    "sg:province":"Lancashire",
    "sg:tags":[
        "consulting",
        "engineer"
    ],
    "wof:name":"C L Associates",
    "wof:placetype":"venue"
},
  "geometry": {"coordinates":[-2.6306490898,53.5438652039],"type":"Point"}
}