{
  "type": "Feature",
  "properties": {
    "iso:country":"GB",
    "sg:address":"19 Market Place",
    "sg:city":"Bideford",
    "sg:classifiers":[
        {
            "category":"Shopping",
            "subcategory":"Antiques",
            "type":"Retail Goods"
        }
    ],
    "sg:phone":"+44 1237 420909",
    "sg:postcode":"EX39 2DR",
    "sg:province":"Devon",
    "wof:name":"Old Bridge Antiques Centre",
    "wof:placetype":"venue"
},
  "geometry": {"coordinates":[-4.206949,51.016933],"type":"Point"}
}