{
  "type": "Feature",
  "properties": {
    "addr:full":"Unit 8 Haslemere Industrial Estate, The Pinnacles Harlow Essex CM19 5SZ",
    "addr:housenumber":"unit 8;estate",
    "addr:postcode":"cm19 5sz",
    "addr:street":"Industrial;The Pinnacles",
    "iso:country":"GB",
    "sg:address":"Unit 8 Haslemere Industrial Estate, The Pinnacles",
    "sg:city":"Harlow",
    "sg:classifiers":[
        {
            "category":"Wholesale",
            "subcategory":"Electrical",
            "type":"Manufacturing & Wholesale Goods"
        }
    ],
    "sg:phone":"+44 1279 634700",
    "sg:postcode":"CM19 5SZ",
    "sg:province":"Essex",
    "sg:tags":[
        "equipment",
        "refrigeration"
    ],
    "wof:name":"Costan (U K) Ltd.",
    "wof:placetype":"venue"
},
  "geometry": {"coordinates":[0.0651210025,51.7622375488],"type":"Point"}
}