{
  "type": "Feature",
  "properties": {
    "addr:full":"Weston Lawns Farm, Bedworth Road, Bulkington Nuneaton Warwickshire CV12 9JA",
    "addr:postcode":"cv12 9ja",
    "addr:street":"Bedworth Road",
    "iso:country":"GB",
    "sg:address":"Weston Lawns Farm, Bedworth Road, Bulkington",
    "sg:city":"Nuneaton",
    "sg:classifiers":[
        {
            "category":"Farming",
            "subcategory":"Crops",
            "type":"Manufacturing & Wholesale Goods"
        },
        {
            "category":"Farming",
            "subcategory":"Livestock Farm",
            "type":"Manufacturing & Wholesale Goods"
        }
    ],
    "sg:phone":"+44 24 7664 3595",
    "sg:postcode":"CV12 9JA",
    "sg:province":"Warwickshire",
    "sg:tags":[
        "arable",
        "others"
    ],
    "wof:name":"B & M Wells Farming",
    "wof:placetype":"venue"
},
  "geometry": {"coordinates":[-1.422995,52.47628],"type":"Point"}
}