{
  "type": "Feature",
  "properties": {
    "addr:full":"7a Caston Industrial Estate, Salhouse Road Norwich Norfolk NR7 9AQ",
    "addr:housenumber":"7a",
    "addr:postcode":"nr7 9aq",
    "addr:street":"Caston Industrial Estate Salhouse Road Norwich Norfolk",
    "iso:country":"GB",
    "sg:address":"7a Caston Industrial Estate, Salhouse Road",
    "sg:city":"Norwich",
    "sg:classifiers":[
        {
            "category":"Retail",
            "subcategory":"Auto Repair",
            "type":"Services"
        }
    ],
    "sg:phone":"+44 1603 702400",
    "sg:postcode":"NR7 9AQ",
    "sg:province":"Norfolk",
    "sg:tags":[
        "engine",
        "specialist",
        "diagnostic",
        "tuning",
        "car"
    ],
    "wof:name":"Clive Atthowe Engine Tuning",
    "wof:placetype":"venue"
},
  "geometry": {"coordinates":[1.3477699757,52.6402015686],"type":"Point"}
}