{
  "type": "Feature",
  "properties": {
    "iso:country":"GB",
    "sg:address":"Enterprise House, 18 Eastern Road",
    "sg:city":"Romford",
    "sg:classifiers":[
        {
            "category":"Professional",
            "subcategory":"Computer Services",
            "type":"Services"
        }
    ],
    "sg:phone":"+44 1708 761900",
    "sg:postcode":"RM1 3PJ",
    "sg:province":"Essex",
    "sg:tags":[
        "bureau",
        "facility"
    ],
    "wof:name":"Capita Business Services",
    "wof:placetype":"venue"
},
  "geometry": {"coordinates":[0.184707,51.575531],"type":"Point"}
}