{
  "type": "Feature",
  "properties": {
    "iso:country":"GB",
    "sg:address":"119 St Peters Street",
    "sg:city":"St Albans",
    "sg:classifiers":[
        {
            "category":"Organizations",
            "subcategory":"Non-profit Organization",
            "type":"Services"
        }
    ],
    "sg:phone":"+44 1727 865773",
    "sg:postcode":"AL1 3EY",
    "sg:province":"Hertfordshire",
    "sg:tags":[
        "organisation",
        "voluntary",
        "charity"
    ],
    "wof:name":"ADVENTIST RISK MANAGEMENT SERVICE",
    "wof:placetype":"venue"
},
  "geometry": {"coordinates":[-0.334899,51.756378],"type":"Point"}
}