{
  "type": "Feature",
  "properties": {
    "addr:full":"48 Wootton Road Abingdon Oxfordshire OX14 1JD",
    "addr:housenumber":"48",
    "addr:postcode":"ox14 1jd",
    "addr:street":"Wootton Road",
    "iso:country":"GB",
    "sg:address":"48 Wootton Road",
    "sg:city":"Abingdon",
    "sg:classifiers":[
        {
            "category":"Sports & Exercise",
            "subcategory":"Sports Center",
            "type":"Entertainment"
        }
    ],
    "sg:phone":"+44 1235 521405",
    "sg:postcode":"OX14 1JD",
    "sg:province":"Oxfordshire",
    "sg:tags":[
        "shop",
        "good"
    ],
    "wof:name":"Topsport (Sports Goods) Ltd.",
    "wof:placetype":"venue"
},
  "geometry": {"coordinates":[-1.2871090174,51.6779403687],"type":"Point"}
}