{
  "type": "Feature",
  "properties": {
    "iso:country":"GB",
    "sg:address":"26 Nutgrove Road, Nutgrove",
    "sg:city":"St Helens",
    "sg:classifiers":[
        {
            "category":"Personal",
            "subcategory":"Beauty Salon",
            "type":"Services"
        }
    ],
    "sg:phone":"+44 1744 812186",
    "sg:postcode":"WA9 5PL",
    "sg:province":"Cheshire",
    "sg:tags":[
        "unisex",
        "hairdresser"
    ],
    "wof:name":"First Hair Limited",
    "wof:placetype":"venue"
},
  "geometry": {"coordinates":[-2.75959,53.43206],"type":"Point"}
}