{
  "type": "Feature",
  "properties": {
    "addr:full":"Unit 9 Manor Building, Holywell Road Flint Flintshire CH6 5RR",
    "addr:housenumber":"unit 9",
    "addr:postcode":"ch6 5rr",
    "addr:street":"Holywell Road",
    "iso:country":"GB",
    "sg:address":"Unit 9 Manor Building, Holywell Road",
    "sg:city":"Flint",
    "sg:classifiers":[
        {
            "category":"Professional",
            "type":"Services"
        }
    ],
    "sg:phone":"+44 1352 762227",
    "sg:postcode":"CH6 5RR",
    "sg:province":"Flintshire",
    "sg:tags":[
        "interior",
        "furnishers",
        "designer"
    ],
    "wof:name":"The Furnished Home Co. Ltd.",
    "wof:placetype":"venue"
},
  "geometry": {"coordinates":[-3.1554789543,53.2596855164],"type":"Point"}
}