{
  "type": "Feature",
  "properties": {
    "addr:full":"Rose Cottage, Workhouse Hill Colchester Essex CO4 5TZ",
    "addr:postcode":"co4 5tz",
    "addr:street":"Workhouse Hill Colchester",
    "iso:country":"GB",
    "sg:address":"Rose Cottage, Workhouse Hill",
    "sg:city":"Colchester",
    "sg:classifiers":[
        {
            "category":"Building & Trades",
            "subcategory":"Construction",
            "type":"Services"
        }
    ],
    "sg:postcode":"CO4 5TZ",
    "sg:province":"Essex",
    "sg:tags":[
        "builder"
    ],
    "wof:name":"J M Ramplin",
    "wof:placetype":"venue"
},
  "geometry": {"coordinates":[0.8903300166,51.9045639038],"type":"Point"}
}