{
  "type": "Feature",
  "properties": {
    "iso:country":"GB",
    "sg:address":"2 Wilkinson Avenue, New Rossington",
    "sg:city":"Doncaster",
    "sg:classifiers":[
        {
            "category":"Shopping",
            "subcategory":"Florist",
            "type":"Retail Goods"
        }
    ],
    "sg:postcode":"DN11 0AJ",
    "sg:province":"South Yorkshire",
    "wof:name":"Floretina",
    "wof:placetype":"venue"
},
  "geometry": {"coordinates":[-1.0648670197,53.4740486145],"type":"Point"}
}