{
  "type": "Feature",
  "properties": {
    "iso:country":"GB",
    "sg:address":"477 Seaside",
    "sg:city":"Eastbourne",
    "sg:classifiers":[
        {
            "category":"Manufacturing",
            "subcategory":"Tools & Machinery",
            "type":"Manufacturing & Wholesale Goods"
        }
    ],
    "sg:phone":"+44 1323 728010",
    "sg:postcode":"BN22 7SA",
    "sg:province":"East Sussex",
    "wof:name":"The Tool Centre",
    "wof:placetype":"venue"
},
  "geometry": {"coordinates":[0.305487,50.784615],"type":"Point"}
}