{
  "type": "Feature",
  "properties": {
    "iso:country":"GB",
    "sg:address":"19 Duke St",
    "sg:city":"Galston",
    "sg:classifiers":[
        {
            "category":"Military Area",
            "subcategory":"Air Force Base",
            "type":"Public Place"
        }
    ],
    "sg:postcode":"KA4 8JD",
    "sg:province":"East Ayrshire",
    "sg:tags":[
        "taxi",
        "hire",
        "private"
    ],
    "wof:name":"McKechan,David,",
    "wof:placetype":"venue"
},
  "geometry": {"coordinates":[-4.3768320084,55.5983848572],"type":"Point"}
}