{
  "type": "Feature",
  "properties": {
    "iso:country":"GB",
    "sg:address":"121 Kings Road",
    "sg:city":"London",
    "sg:classifiers":[
        {
            "category":"Shopping",
            "subcategory":"Clothing, Apparel, & Fashions",
            "type":"Retail Goods"
        }
    ],
    "sg:phone":"+44 20 7823 3117",
    "sg:postcode":"SW3 4PL",
    "sg:province":"Greater London",
    "sg:tags":[
        "shop"
    ],
    "wof:name":"The Common Market",
    "wof:placetype":"venue"
},
  "geometry": {"coordinates":[-0.165895,51.488491],"type":"Point"}
}