{
  "type": "Feature",
  "properties": {
    "iso:country":"GB",
    "sg:address":"29 Tiffany Gardens, East Hunsbury",
    "sg:city":"Northampton",
    "sg:classifiers":[
        {
            "category":"Manufacturing",
            "subcategory":"Petroleum Products",
            "type":"Manufacturing & Wholesale Goods"
        }
    ],
    "sg:postcode":"NN4 0TJ",
    "sg:province":"Northamptonshire",
    "sg:tags":[
        "double",
        "glazing"
    ],
    "wof:name":"Independent Double Glazing",
    "wof:placetype":"venue"
},
  "geometry": {"coordinates":[-0.897054,52.205582],"type":"Point"}
}