{
  "type": "Feature",
  "properties": {
    "addr:full":"56 Fishtonft Road Boston Lincolnshire PE21 0AL",
    "addr:housenumber":"56",
    "addr:postcode":"pe21 0al",
    "addr:street":"Fishtonft Road",
    "iso:country":"GB",
    "sg:address":"56 Fishtonft Road",
    "sg:city":"Boston",
    "sg:classifiers":[
        {
            "category":"Food & Beverages",
            "subcategory":"Meat & Fish",
            "type":"Retail Goods"
        }
    ],
    "sg:phone":"+44 1205 364545",
    "sg:postcode":"PE21 0AL",
    "sg:province":"Lincolnshire",
    "sg:tags":[
        "chip"
    ],
    "wof:name":"Ann's",
    "wof:placetype":"venue"
},
  "geometry": {"coordinates":[-0.0143050002,52.9791564941],"type":"Point"}
}