{
  "type": "Feature",
  "properties": {
    "iso:country":"GB",
    "sg:address":"62 Springbank Close, Farsley",
    "sg:city":"Pudsey",
    "sg:classifiers":[
        {
            "category":"Freight",
            "type":"Transportation"
        }
    ],
    "sg:phone":"+44 113 255 6318",
    "sg:postcode":"LS28 5EW",
    "sg:province":"West Yorkshire",
    "sg:tags":[
        "haulage",
        "transport",
        "road"
    ],
    "wof:name":"G T Freight",
    "wof:placetype":"venue"
},
  "geometry": {"coordinates":[-1.6650179625,53.8111076355],"type":"Point"}
}