{
  "type": "Feature",
  "properties": {
    "addr:full":"208-210 Edgware Road London Greater London W2 1DH",
    "addr:housenumber":"208-210",
    "addr:postcode":"w2 1dh",
    "addr:street":"Edgware Road",
    "iso:country":"GB",
    "sg:address":"208-210 Edgware Road",
    "sg:city":"London",
    "sg:classifiers":[
        {
            "category":"Travel",
            "subcategory":"Hotels & Motels",
            "type":"Entertainment"
        },
        {
            "category":"Real Estate",
            "subcategory":"Real Estate Agent",
            "type":"Services"
        }
    ],
    "sg:phone":"+44 20 7834 4052",
    "sg:postcode":"W2 1DH",
    "sg:province":"Greater London",
    "wof:name":"Warwicka Enterprises",
    "wof:placetype":"venue"
},
  "geometry": {"coordinates":[-0.167541,51.518375],"type":"Point"}
}