{
  "type": "Feature",
  "properties": {
    "addr:full":"Unit 16 Third Floor, Albert Bridge Dewsbury West Yorkshire WF12 9PP",
    "addr:housenumber":"unit 16;floor",
    "addr:postcode":"wf12 9pp",
    "addr:street":"Third",
    "iso:country":"GB",
    "sg:address":"Unit 16 Third Floor, Albert Bridge",
    "sg:city":"Dewsbury",
    "sg:classifiers":[
        {
            "category":"Retail",
            "subcategory":"Laundry & Dry Cleaning",
            "type":"Services"
        }
    ],
    "sg:postcode":"WF12 9PP",
    "sg:province":"West Yorkshire",
    "sg:tags":[
        "product",
        "disposable"
    ],
    "wof:name":"Yorkshire Disposables",
    "wof:placetype":"venue"
},
  "geometry": {"coordinates":[-1.613049,53.699295],"type":"Point"}
}