{
  "type": "Feature",
  "properties": {
    "iso:country":"GB",
    "sg:address":"10 Meadow Clo",
    "sg:city":"Reading",
    "sg:classifiers":[
        {
            "category":"Health Services",
            "subcategory":"Health Practitioner",
            "type":"Services"
        }
    ],
    "sg:phone":"+44 1491 875555",
    "sg:postcode":"RG8 0AP",
    "sg:province":"Berkshire",
    "sg:tags":[
        "osteopath"
    ],
    "wof:name":"N M J Swan",
    "wof:placetype":"venue"
},
  "geometry": {"coordinates":[-1.1294699907,51.5241775513],"type":"Point"}
}