{
  "type": "Feature",
  "properties": {
    "addr:full":"6 The Grange, Earl Shilton Leicester Leicestershire LE9 7GT",
    "addr:housenumber":"6;grange",
    "addr:postcode":"le9 7gt",
    "addr:street":"The",
    "iso:country":"GB",
    "sg:address":"6 The Grange, Earl Shilton",
    "sg:city":"Leicester",
    "sg:classifiers":[
        {
            "category":"Building & Trades",
            "subcategory":"Plumbing",
            "type":"Services"
        }
    ],
    "sg:phone":"+44 1455 848890",
    "sg:postcode":"LE9 7GT",
    "sg:province":"Leicestershire",
    "sg:tags":[
        "plumber",
        "heating"
    ],
    "wof:name":"Chris Grace Plumbing & Heating",
    "wof:placetype":"venue"
},
  "geometry": {"coordinates":[-1.316393,52.570732],"type":"Point"}
}