{
  "type": "Feature",
  "properties": {
    "addr:full":"3 Arncliffe Rd Leeds West Yorkshire LS16 5JE",
    "addr:housenumber":"3",
    "addr:postcode":"ls16 5je",
    "addr:street":"Arncliffe Rd",
    "iso:country":"GB",
    "sg:address":"3 Arncliffe Rd",
    "sg:city":"Leeds",
    "sg:classifiers":[
        {
            "category":"Health Services",
            "subcategory":"Nursing And Care Facility",
            "type":"Services"
        }
    ],
    "sg:phone":"+44 113 278 9567",
    "sg:postcode":"LS16 5JE",
    "sg:province":"West Yorkshire",
    "sg:tags":[
        "home"
    ],
    "wof:name":"Castleton Court Nursing Home",
    "wof:placetype":"venue"
},
  "geometry": {"coordinates":[-1.5946999788,53.8328056335],"type":"Point"}
}