{
  "type": "Feature",
  "properties": {
    "iso:country":"GB",
    "sg:address":"128 The Broadway",
    "sg:city":"London",
    "sg:classifiers":[
        {
            "category":"Personal",
            "type":"Services"
        }
    ],
    "sg:phone":"+44 20 8540 3388",
    "sg:postcode":"SW19 1RH",
    "sg:province":"Greater London",
    "sg:tags":[
        "tailor"
    ],
    "wof:name":"K Paul Tailors & Outfitters",
    "wof:placetype":"venue"
},
  "geometry": {"coordinates":[-0.20053,51.419403],"type":"Point"}
}