{
  "type": "Feature",
  "properties": {
    "addr:full":"782-784 Manchester Rd, Castleton Rochdale Lancashire OL11 3AW",
    "addr:housenumber":"782-784",
    "addr:postcode":"ol11 3aw",
    "addr:street":"Manchester Rd",
    "iso:country":"GB",
    "sg:address":"782-784 Manchester Rd, Castleton",
    "sg:city":"Rochdale",
    "sg:classifiers":[
        {
            "category":"Home & Garden",
            "subcategory":"Furniture",
            "type":"Retail Goods"
        }
    ],
    "sg:postcode":"OL11 3AW",
    "sg:province":"Lancashire",
    "wof:name":"Summers Textiles",
    "wof:placetype":"venue"
},
  "geometry": {"coordinates":[-2.1806619167,53.5927963257],"type":"Point"}
}