{
  "type": "Feature",
  "properties": {
    "addr:full":"Britannia Stores Porthmadog Gwynedd LL49 9NG",
    "addr:postcode":"ll49 9ng",
    "addr:street":"Porthmadog",
    "iso:country":"GB",
    "sg:address":"Britannia Stores",
    "sg:city":"Porthmadog",
    "sg:classifiers":[
        {
            "category":"Professional",
            "type":"Services"
        }
    ],
    "sg:phone":"+44 1766 512124",
    "sg:postcode":"LL49 9NG",
    "sg:province":"Gwynedd",
    "sg:tags":[
        "auctioneer"
    ],
    "wof:name":"R & G Jones",
    "wof:placetype":"venue"
},
  "geometry": {"coordinates":[-4.1329889297,52.9277381897],"type":"Point"}
}