{
  "type": "Feature",
  "properties": {
    "addr:full":"282 Daws Heath Road Benfleet Essex SS7 2TY",
    "addr:housenumber":"282",
    "addr:postcode":"ss7 2ty",
    "addr:street":"Daws Heath Road",
    "iso:country":"GB",
    "sg:address":"282 Daws Heath Road",
    "sg:city":"Benfleet",
    "sg:classifiers":[
        {
            "category":"Food & Beverages",
            "subcategory":"Liquor & Beverages",
            "type":"Retail Goods"
        }
    ],
    "sg:postcode":"SS7 2TY",
    "sg:province":"Essex",
    "sg:tags":[
        "beer",
        "spirit",
        "wines"
    ],
    "wof:name":"Corner Stores & Off Licence",
    "wof:placetype":"venue"
},
  "geometry": {"coordinates":[0.6125,51.569145],"type":"Point"}
}