{
  "type": "Feature",
  "properties": {
    "iso:country":"GB",
    "sg:address":"24 Lidget La",
    "sg:city":"Rotherham",
    "sg:classifiers":[
        {
            "category":"Shopping",
            "subcategory":"Baby Store",
            "type":"Retail Goods"
        }
    ],
    "sg:phone":"+44 1709 880267",
    "sg:postcode":"S63 0BU",
    "sg:province":"South Yorkshire",
    "sg:tags":[
        "babywear",
        "childrens"
    ],
    "wof:name":"Janet & Jills",
    "wof:placetype":"venue"
},
  "geometry": {"coordinates":[-1.305965,53.544216],"type":"Point"}
}