{
  "type": "Feature",
  "properties": {
    "addr:full":"114 Dale House Fold, Poynton Stockport Cheshire SK12 1DG",
    "addr:housenumber":"114",
    "addr:postcode":"sk12 1dg",
    "addr:street":"Dale House Fold Poynton",
    "iso:country":"GB",
    "sg:address":"114 Dale House Fold, Poynton",
    "sg:city":"Stockport",
    "sg:classifiers":[
        {
            "category":"Building & Trades",
            "subcategory":"Construction",
            "type":"Services"
        }
    ],
    "sg:phone":"+44 1625 877083",
    "sg:postcode":"SK12 1DG",
    "sg:province":"Cheshire",
    "sg:tags":[
        "contractor",
        "paving",
        "driveway"
    ],
    "wof:name":"Diamond Driveways",
    "wof:placetype":"venue"
},
  "geometry": {"coordinates":[-2.122479,53.34866],"type":"Point"}
}