{
  "type": "Feature",
  "properties": {
    "iso:country":"GB",
    "sg:address":"292 Hob Moor Road",
    "sg:city":"Birmingham",
    "sg:classifiers":[
        {
            "category":"Government",
            "subcategory":"Post Office",
            "type":"Public Place"
        }
    ],
    "sg:phone":"+44 121 783 2315",
    "sg:postcode":"B10 9HH",
    "sg:province":"West Midlands",
    "wof:name":"Heybarnes Post Office",
    "wof:placetype":"venue"
},
  "geometry": {"coordinates":[-1.830081,52.470734],"type":"Point"}
}