{
  "type": "Feature",
  "properties": {
    "addr:full":"8 Baker St London East Sussex TN8 6HQ",
    "addr:housenumber":"8",
    "addr:postcode":"tn8 6hq",
    "addr:street":"Baker St",
    "iso:country":"GB",
    "sg:address":"8 Baker St",
    "sg:city":"London",
    "sg:classifiers":[
        {
            "category":"Personal",
            "subcategory":"Beauty Salon",
            "type":"Services"
        }
    ],
    "sg:phone":"+44 1732 862824",
    "sg:postcode":"TN8 6HQ",
    "sg:province":"East Sussex",
    "sg:tags":[
        "unisex",
        "hairdresser"
    ],
    "wof:name":"Knc Ltd",
    "wof:placetype":"venue"
},
  "geometry": {"coordinates":[0.06212,51.206242],"type":"Point"}
}