{
  "type": "Feature",
  "properties": {
    "addr:full":"North Carbrain Road, Cumbernauld Glasgow Falkirk G67 1BJ",
    "addr:postcode":"g67 1bj",
    "addr:street":"North Carbrain Road",
    "iso:country":"GB",
    "sg:address":"North Carbrain Road, Cumbernauld",
    "sg:city":"Glasgow",
    "sg:classifiers":[
        {
            "category":"Health Services",
            "subcategory":"Clinic",
            "type":"Services"
        }
    ],
    "sg:phone":"+44 1236 731738",
    "sg:postcode":"G67 1BJ",
    "sg:province":"Falkirk",
    "sg:tags":[
        "nh"
    ],
    "wof:name":"Dr K Sorooshian",
    "wof:placetype":"venue"
},
  "geometry": {"coordinates":[-3.9932539463,55.942440033],"type":"Point"}
}