{
  "type": "Feature",
  "properties": {
    "iso:country":"GB",
    "sg:address":"26a Westway",
    "sg:city":"Caterham",
    "sg:classifiers":[
        {
            "category":"Professional",
            "subcategory":"Art Services",
            "type":"Services"
        }
    ],
    "sg:postcode":"CR3 5TP",
    "sg:province":"Surrey",
    "sg:tags":[
        "photographer"
    ],
    "wof:name":"Perfection Art",
    "wof:placetype":"venue"
},
  "geometry": {"coordinates":[-0.096273,51.287922],"type":"Point"}
}