{
  "type": "Feature",
  "properties": {
    "addr:full":"Little Combes, Green Hailey, Speen Princes Risborough Buckinghamshire HP27 0RP",
    "addr:postcode":"hp27 0rp",
    "addr:street":"Green",
    "iso:country":"GB",
    "sg:address":"Little Combes, Green Hailey, Speen",
    "sg:city":"Princes Risborough",
    "sg:classifiers":[
        {
            "category":"Organizations",
            "subcategory":"Non-profit Organization",
            "type":"Services"
        }
    ],
    "sg:postcode":"HP27 0RP",
    "sg:province":"Buckinghamshire",
    "sg:tags":[
        "organisation",
        "voluntary",
        "charity"
    ],
    "wof:name":"Honourable Society Of Knights Of The Round Table",
    "wof:placetype":"venue"
},
  "geometry": {"coordinates":[-0.8329520226,51.721622467],"type":"Point"}
}