{
  "type": "Feature",
  "properties": {
    "addr:full":"46 Arpley Street Warrington Cheshire WA1 1LX",
    "addr:housenumber":"46",
    "addr:postcode":"wa1 1lx",
    "addr:street":"Arpley Street",
    "iso:country":"GB",
    "sg:address":"46 Arpley Street",
    "sg:city":"Warrington",
    "sg:classifiers":[
        {
            "category":"Personal",
            "type":"Services"
        },
        {
            "category":"Organizations",
            "subcategory":"Non-profit Organization",
            "type":"Services"
        }
    ],
    "sg:phone":"+44 1925 235000",
    "sg:postcode":"WA1 1LX",
    "sg:province":"Cheshire",
    "sg:tags":[
        "advice",
        "organisation",
        "voluntary",
        "counselling",
        "charity"
    ],
    "wof:name":"The Samaritans",
    "wof:placetype":"venue"
},
  "geometry": {"coordinates":[-2.600412,53.386669],"type":"Point"}
}