{
  "type": "Feature",
  "properties": {
    "iso:country":"GB",
    "sg:address":"Unit 81, Bradley Hall Trading Estate, Bradley Lane",
    "sg:city":"Wigan",
    "sg:classifiers":[
        {
            "category":"Freight",
            "type":"Transportation"
        }
    ],
    "sg:phone":"+44 1257 422668",
    "sg:postcode":"WN6 0XQ",
    "sg:province":"Lancashire",
    "sg:tags":[
        "haulage",
        "road"
    ],
    "wof:name":"Steve Parr Haulage",
    "wof:placetype":"venue"
},
  "geometry": {"coordinates":[-2.650462,53.591576],"type":"Point"}
}