{
  "type": "Feature",
  "properties": {
    "iso:country":"GB",
    "sg:address":"39a St Michaels Lane",
    "sg:city":"Leeds",
    "sg:classifiers":[
        {
            "category":"Wholesale",
            "subcategory":"Medical Equipment & Supplies",
            "type":"Manufacturing & Wholesale Goods"
        },
        {
            "category":"Building & Trades",
            "subcategory":"Equipment Rental",
            "type":"Services"
        }
    ],
    "sg:phone":"+44 113 293 8180",
    "sg:postcode":"LS6 3BR",
    "sg:province":"West Yorkshire",
    "sg:tags":[
        "supplier",
        "dental"
    ],
    "wof:name":"Technovent Ltd.",
    "wof:placetype":"venue"
},
  "geometry": {"coordinates":[-1.579462,53.81715],"type":"Point"}
}