{
  "type": "Feature",
  "properties": {
    "addr:full":"Beechmead, Alton Pancras Dorchester Dorset DT2 7RT",
    "addr:postcode":"dt2 7rt",
    "addr:street":"Dorset",
    "iso:country":"GB",
    "sg:address":"Beechmead, Alton Pancras",
    "sg:city":"Dorchester",
    "sg:classifiers":[
        {
            "category":"Organizations",
            "subcategory":"Membership Organization",
            "type":"Services"
        }
    ],
    "sg:phone":"+44 1300 345297",
    "sg:postcode":"DT2 7RT",
    "sg:province":"Dorset",
    "sg:tags":[
        "club"
    ],
    "wof:name":"South Dorset Hunt",
    "wof:placetype":"venue"
},
  "geometry": {"coordinates":[-2.428029,50.825565],"type":"Point"}
}