{
  "type": "Feature",
  "properties": {
    "addr:full":"Woodside Birmingham West Midlands B37 6LY",
    "addr:postcode":"b37 6ly",
    "addr:street":"Woodside",
    "iso:country":"GB",
    "sg:address":"Woodside",
    "sg:city":"Birmingham",
    "sg:classifiers":[
        {
            "category":"Home & Garden",
            "subcategory":"Building Materials",
            "type":"Retail Goods"
        }
    ],
    "sg:phone":"+44 121 788 3559",
    "sg:postcode":"B37 6LY",
    "sg:province":"West Midlands",
    "sg:tags":[
        "ironwork",
        "wrought"
    ],
    "wof:name":"Morris's",
    "wof:placetype":"venue"
},
  "geometry": {"coordinates":[-1.758639,52.489044],"type":"Point"}
}