{
  "type": "Feature",
  "properties": {
    "iso:country":"GB",
    "sg:address":"The Cottage, Trout Rise",
    "sg:city":"Rickmansworth",
    "sg:classifiers":[
        {
            "category":"Home & Garden",
            "subcategory":"Furniture",
            "type":"Retail Goods"
        }
    ],
    "sg:phone":"+44 1727 858727",
    "sg:postcode":"WD3 4JS",
    "sg:province":"Hertfordshire",
    "wof:name":"Holywells Soft Furnishings",
    "wof:placetype":"venue"
},
  "geometry": {"coordinates":[-0.468275,51.641438],"type":"Point"}
}