{
  "type": "Feature",
  "properties": {
    "iso:country":"GB",
    "sg:address":"2 School St",
    "sg:city":"Weymouth",
    "sg:classifiers":[
        {
            "category":"Professional",
            "subcategory":"Art Services",
            "type":"Services"
        }
    ],
    "sg:phone":"+44 1305 779726",
    "sg:postcode":"DT4 8NH",
    "sg:province":"Dorset",
    "sg:tags":[
        "framing"
    ],
    "wof:name":"Change Of Seen",
    "wof:placetype":"venue"
},
  "geometry": {"coordinates":[-2.45487,50.61071],"type":"Point"}
}