{
  "type": "Feature",
  "properties": {
    "iso:country":"GB",
    "sg:address":"Dundee West Delivery Office, 43 Baird Avenue",
    "sg:city":"Dundee",
    "sg:classifiers":[
        {
            "category":"Personal",
            "type":"Services"
        }
    ],
    "sg:phone":"+44 1382 858543",
    "sg:postcode":"DD2 3UX",
    "sg:province":"Dundee City",
    "sg:tags":[
        "delivery"
    ],
    "wof:name":"The Post Office",
    "wof:placetype":"venue"
},
  "geometry": {"coordinates":[-3.0148000717,56.4832992554],"type":"Point"}
}