{
  "type": "Feature",
  "properties": {
    "iso:country":"GB",
    "sg:address":"29 Church Street",
    "sg:city":"Croydon",
    "sg:classifiers":[
        {
            "category":"Professional",
            "subcategory":"Engineering",
            "type":"Services"
        }
    ],
    "sg:phone":"+44 20 8760 9118",
    "sg:postcode":"CR0 1RH",
    "sg:province":"Surrey",
    "sg:tags":[
        "consulting",
        "design",
        "engineer"
    ],
    "wof:name":"The Sinnett Partnership Ltd.",
    "wof:placetype":"venue"
},
  "geometry": {"coordinates":[-0.103708,51.373341],"type":"Point"}
}