{
  "type": "Feature",
  "properties": {
    "addr:full":"Unit 1 North Pontypool Industrial P Pontypool Monmouthshire NP4 6PB",
    "addr:housenumber":"unit 1",
    "addr:postcode":"np4 6pb",
    "addr:street":"North Pontypool Industrial P Pontypool",
    "iso:country":"GB",
    "sg:address":"Unit 1 North Pontypool Industrial P",
    "sg:city":"Pontypool",
    "sg:classifiers":[
        {
            "category":"Shopping",
            "subcategory":"Clothing, Apparel, & Fashions",
            "type":"Retail Goods"
        }
    ],
    "sg:phone":"+44 1495 763401",
    "sg:postcode":"NP4 6PB",
    "sg:province":"Monmouthshire",
    "sg:tags":[
        "tie",
        "neckwear"
    ],
    "wof:name":"All Court (Leisure)",
    "wof:placetype":"venue"
},
  "geometry": {"coordinates":[-3.052949,51.709805],"type":"Point"}
}