{
  "type": "Feature",
  "properties": {
    "addr:full":"51 Abbey St Nottingham Nottinghamshire NG7 2NZ",
    "addr:housenumber":"51",
    "addr:postcode":"ng7 2nz",
    "addr:street":"Abbey St",
    "iso:country":"GB",
    "sg:address":"51 Abbey St",
    "sg:city":"Nottingham",
    "sg:classifiers":[
        {
            "category":"Fast Food",
            "type":"Food & Drink"
        }
    ],
    "sg:phone":"+44 115 978 7977",
    "sg:postcode":"NG7 2NZ",
    "sg:province":"Nottinghamshire",
    "sg:tags":[
        "away",
        "take"
    ],
    "wof:name":"Miami Pizzas",
    "wof:placetype":"venue"
},
  "geometry": {"coordinates":[-1.180003047,52.942855835],"type":"Point"}
}