{
  "type": "Feature",
  "properties": {
    "iso:country":"GB",
    "sg:address":"256 Old Street",
    "sg:city":"London",
    "sg:classifiers":[
        {
            "category":"Bars & Pubs",
            "subcategory":"Nightclub",
            "type":"Food & Drink"
        }
    ],
    "sg:phone":"+44 20 7251 6136",
    "sg:postcode":"EC1V 9DD",
    "sg:province":"Greater London",
    "sg:tags":[
        "club",
        "night"
    ],
    "wof:name":"Aquarium Management Ltd.",
    "wof:placetype":"venue"
},
  "geometry": {"coordinates":[-0.085599,51.526161],"type":"Point"}
}