{
  "type": "Feature",
  "properties": {
    "addr:full":"175 Stamford Street Ashton Under Lyne Greater Manchester OL6 6PS",
    "addr:housenumber":"175",
    "addr:postcode":"ol6 6ps",
    "addr:street":"Stamford Street;Under Lyne",
    "iso:country":"GB",
    "sg:address":"175 Stamford Street",
    "sg:city":"Ashton Under Lyne",
    "sg:classifiers":[
        {
            "category":"Insurance",
            "subcategory":"Insurance Agent",
            "type":"Services"
        }
    ],
    "sg:phone":"+44 161 330 4549",
    "sg:postcode":"OL6 6PS",
    "sg:province":"Greater Manchester",
    "wof:name":"Hill House Hammond Ltd",
    "wof:placetype":"venue"
},
  "geometry": {"coordinates":[-2.0859289169,53.4879684448],"type":"Point"}
}