{
  "type": "Feature",
  "properties": {
    "addr:full":"12 Isis Lakes, South Cerney Cirencester Gloucestershire GL7 5TL",
    "addr:housenumber":"12",
    "addr:postcode":"gl7 5tl",
    "addr:street":"Isis Lakes",
    "iso:country":"GB",
    "sg:address":"12 Isis Lakes, South Cerney",
    "sg:city":"Cirencester",
    "sg:classifiers":[
        {
            "category":"Education",
            "subcategory":"Special Training",
            "type":"Public Place"
        }
    ],
    "sg:phone":"+44 1285 861549",
    "sg:postcode":"GL7 5TL",
    "sg:province":"Gloucestershire",
    "sg:tags":[
        "product",
        "centre"
    ],
    "wof:name":"T2 Training Ltd.",
    "wof:placetype":"venue"
},
  "geometry": {"coordinates":[-1.953541,51.718548],"type":"Point"}
}