{
  "type": "Feature",
  "properties": {
    "addr:full":"Burnden Works, Burnden Road Bolton Lancashire BL3 2RB",
    "addr:postcode":"bl3 2rb",
    "addr:street":"Burnden Road",
    "iso:country":"GB",
    "sg:address":"Burnden Works, Burnden Road",
    "sg:city":"Bolton",
    "sg:classifiers":[
        {
            "category":"Professional",
            "subcategory":"Engineering",
            "type":"Services"
        }
    ],
    "sg:phone":"+44 1204 554550",
    "sg:postcode":"BL3 2RB",
    "sg:province":"Lancashire",
    "wof:name":"Automated Stone Machinery Ltd.",
    "wof:placetype":"venue"
},
  "geometry": {"coordinates":[-2.4152,53.566978],"type":"Point"}
}