{
  "type": "Feature",
  "properties": {
    "iso:country":"GB",
    "sg:address":"Newells Joinery 56 Spencer St",
    "sg:city":"Bognor Regis",
    "sg:classifiers":[
        {
            "category":"Autos & Motor Vehicles",
            "subcategory":"Automobile Sales",
            "type":"Retail Goods"
        }
    ],
    "sg:phone":"+44 1243 828021",
    "sg:postcode":"PO21 1AN",
    "sg:province":"West Sussex",
    "sg:tags":[
        "commercial"
    ],
    "wof:name":"Newells Autos",
    "wof:placetype":"venue"
},
  "geometry": {"coordinates":[-0.6753489971,50.7829666138],"type":"Point"}
}