{
  "type": "Feature",
  "properties": {
    "iso:country":"GB",
    "sg:address":"137 High Street, Pensnett",
    "sg:city":"Brierley Hill",
    "sg:classifiers":[
        {
            "category":"Fast Food",
            "type":"Food & Drink"
        }
    ],
    "sg:phone":"+44 1384 261628",
    "sg:postcode":"DY5 4EA",
    "sg:province":"West Midlands",
    "sg:tags":[
        "away",
        "take"
    ],
    "wof:name":"The Greedy Pig",
    "wof:placetype":"venue"
},
  "geometry": {"coordinates":[-2.13345,52.500957],"type":"Point"}
}