{
  "type": "Feature",
  "properties": {
    "iso:country":"GB",
    "sg:address":"186a Brook Street, Broughty Ferry",
    "sg:city":"Dundee",
    "sg:classifiers":[
        {
            "category":"Deli",
            "type":"Food & Drink"
        }
    ],
    "sg:postcode":"DD5 2AH",
    "sg:province":"Angus",
    "sg:tags":[
        "delicatessen"
    ],
    "wof:name":"Quality Foods",
    "wof:placetype":"venue"
},
  "geometry": {"coordinates":[-2.875249,56.46735],"type":"Point"}
}