{
  "type": "Feature",
  "properties": {
    "addr:full":"26 Perimeter Road, Pinefield Industrial Estate Elgin Moray IV30 6AF",
    "addr:housenumber":"26",
    "addr:postcode":"iv30 6af",
    "addr:street":"Perimeter Road;Industrial Estate",
    "iso:country":"GB",
    "sg:address":"26 Perimeter Road, Pinefield Industrial Estate",
    "sg:city":"Elgin",
    "sg:classifiers":[
        {
            "category":"Autos & Motor Vehicles",
            "subcategory":"Automobile Sales",
            "type":"Retail Goods"
        }
    ],
    "sg:phone":"+44 1343 550010",
    "sg:postcode":"IV30 6AF",
    "sg:province":"Moray",
    "sg:tags":[
        "car"
    ],
    "wof:name":"Clifton Motors",
    "wof:placetype":"venue"
},
  "geometry": {"coordinates":[-3.292093,57.646095],"type":"Point"}
}