{
  "type": "Feature",
  "properties": {
    "addr:full":"Tantallon Terrace North Berwick East Lothian EH39 4LE",
    "addr:postcode":"eh39 4le",
    "addr:street":"Tantallon Terrace;Berwick",
    "iso:country":"GB",
    "sg:address":"Tantallon Terrace",
    "sg:city":"North Berwick",
    "sg:classifiers":[
        {
            "category":"Sports & Exercise",
            "subcategory":"Golf",
            "type":"Entertainment"
        }
    ],
    "sg:phone":"+44 1620 892221",
    "sg:postcode":"EH39 4LE",
    "sg:province":"East Lothian",
    "sg:tags":[
        "club",
        "course"
    ],
    "wof:name":"Glen Golf Club",
    "wof:placetype":"venue"
},
  "geometry": {"coordinates":[-2.7056159973,56.0576477051],"type":"Point"}
}