{
  "type": "Feature",
  "properties": {
    "addr:full":"Hollybank Works, Rochdale Road, Greetland Halifax West Yorkshire HX4 8HB",
    "addr:postcode":"hx4 8hb",
    "addr:street":"Rochdale Road",
    "iso:country":"GB",
    "sg:address":"Hollybank Works, Rochdale Road, Greetland",
    "sg:city":"Halifax",
    "sg:classifiers":[
        {
            "category":"Wholesale",
            "subcategory":"Electrical",
            "type":"Manufacturing & Wholesale Goods"
        }
    ],
    "sg:phone":"+44 1422 378131",
    "sg:postcode":"HX4 8HB",
    "sg:province":"West Yorkshire",
    "sg:tags":[
        "equipment",
        "refrigeration"
    ],
    "wof:name":"Fan Systems Group Ltd.",
    "wof:placetype":"venue"
},
  "geometry": {"coordinates":[-1.855994,53.68692],"type":"Point"}
}