{
  "type": "Feature",
  "properties": {
    "addr:full":"Lyngate Road Industrial Estate, Cornish Way North Walsham Norfolk NR28 0AJ",
    "addr:housenumber":"estate",
    "addr:postcode":"nr28 0aj",
    "addr:street":"Lyngate Road Industrial;Cornish Way",
    "iso:country":"GB",
    "sg:address":"Lyngate Road Industrial Estate, Cornish Way",
    "sg:city":"North Walsham",
    "sg:classifiers":[
        {
            "category":"Utilities",
            "subcategory":"Refuse",
            "type":"Services"
        }
    ],
    "sg:phone":"+44 1692 407710",
    "sg:postcode":"NR28 0AJ",
    "sg:province":"Norfolk",
    "sg:tags":[
        "disposal",
        "waste"
    ],
    "wof:name":"Serviceteam Ltd.",
    "wof:placetype":"venue"
},
  "geometry": {"coordinates":[1.3899600506,52.8293457031],"type":"Point"}
}