{
  "type": "Feature",
  "properties": {
    "addr:full":"40 Bosmere Gardens Emsworth Hampshire PO10 7NP",
    "addr:housenumber":"40",
    "addr:postcode":"po10 7np",
    "addr:street":"Bosmere Gardens",
    "iso:country":"GB",
    "sg:address":"40 Bosmere Gardens",
    "sg:city":"Emsworth",
    "sg:classifiers":[
        {
            "category":"Military Area",
            "subcategory":"Air Force Base",
            "type":"Public Place"
        }
    ],
    "sg:phone":"+44 1243 370370",
    "sg:postcode":"PO10 7NP",
    "sg:province":"Hampshire",
    "sg:tags":[
        "taxi",
        "hire",
        "private"
    ],
    "wof:name":"Johns Cars",
    "wof:placetype":"venue"
},
  "geometry": {"coordinates":[-0.94261,50.849373],"type":"Point"}
}