{
  "type": "Feature",
  "properties": {
    "iso:country":"GB",
    "sg:address":"61 Brasenose Road",
    "sg:city":"Bootle",
    "sg:classifiers":[
        {
            "category":"Home & Garden",
            "subcategory":"Home Furnishings",
            "type":"Retail Goods"
        }
    ],
    "sg:phone":"+44 151 922 7403",
    "sg:postcode":"L20 8HE",
    "sg:province":"Merseyside",
    "sg:tags":[
        "furnishers",
        "planner",
        "bedroom"
    ],
    "wof:name":"B Tomes & M Murray",
    "wof:placetype":"venue"
},
  "geometry": {"coordinates":[-2.995255,53.442432],"type":"Point"}
}