{
  "type": "Feature",
  "properties": {
    "iso:country":"GB",
    "sg:address":"Unit 3 Bretton Centre, Bretton",
    "sg:city":"Peterborough",
    "sg:classifiers":[
        {
            "category":"Shopping",
            "subcategory":"Stationery & Office Supplies",
            "type":"Retail Goods"
        }
    ],
    "sg:postcode":"PE3 8DX",
    "sg:province":"Cambridgeshire",
    "sg:tags":[
        "equipment",
        "school"
    ],
    "wof:name":"Formative Fun",
    "wof:placetype":"venue"
},
  "geometry": {"coordinates":[-0.282004,52.587963],"type":"Point"}
}