{
  "type": "Feature",
  "properties": {
    "addr:full":"398 Garstang Rd Preston Lancashire PR3 5JE",
    "addr:housenumber":"398",
    "addr:postcode":"pr3 5je",
    "addr:street":"Garstang Rd",
    "iso:country":"GB",
    "sg:address":"398 Garstang Rd",
    "sg:city":"Preston",
    "sg:classifiers":[
        {
            "category":"Bars & Pubs",
            "type":"Food & Drink"
        }
    ],
    "sg:phone":"+44 1772 866066",
    "sg:postcode":"PR3 5JE",
    "sg:province":"Lancashire",
    "sg:tags":[
        "pubs",
        "inn"
    ],
    "wof:name":"Tavern Fayre",
    "wof:placetype":"venue"
},
  "geometry": {"coordinates":[-2.718449,53.803001],"type":"Point"}
}