{
  "type": "Feature",
  "properties": {
    "iso:country":"GB",
    "sg:address":"16 Jubilee Close",
    "sg:city":"Greenhithe",
    "sg:classifiers":[
        {
            "category":"Wholesale",
            "subcategory":"Vending Machines",
            "type":"Manufacturing & Wholesale Goods"
        }
    ],
    "sg:phone":"+44 1322 380919",
    "sg:postcode":"DA9 9HR",
    "sg:province":"Kent",
    "sg:tags":[
        "sale"
    ],
    "wof:name":"Coffee-Mac Beverage Systems South East",
    "wof:placetype":"venue"
},
  "geometry": {"coordinates":[0.289435,51.446552],"type":"Point"}
}