{
  "type": "Feature",
  "properties": {
    "iso:country":"GB",
    "sg:address":"63 Vineyard",
    "sg:city":"Abingdon",
    "sg:classifiers":[
        {
            "category":"Bars & Pubs",
            "type":"Food & Drink"
        },
        {
            "category":"Home & Garden",
            "subcategory":"Home Furnishings",
            "type":"Retail Goods"
        }
    ],
    "sg:phone":"+44 1235 521128",
    "sg:postcode":"OX14 3PG",
    "sg:province":"Oxfordshire",
    "sg:tags":[
        "blind",
        "pubs",
        "inn",
        "fitting",
        "curtain"
    ],
    "wof:name":"Greene King Leasing No 1 Ltd.",
    "wof:placetype":"venue"
},
  "geometry": {"coordinates":[-1.2792700529,51.6735534668],"type":"Point"}
}