{
  "type": "Feature",
  "properties": {
    "addr:full":"94 Locksley Road Eastleigh Hampshire SO50 5DS",
    "addr:housenumber":"94",
    "addr:postcode":"so50 5ds",
    "addr:street":"Locksley Road",
    "iso:country":"GB",
    "sg:address":"94 Locksley Road",
    "sg:city":"Eastleigh",
    "sg:classifiers":[
        {
            "category":"Building & Trades",
            "subcategory":"Construction",
            "type":"Services"
        }
    ],
    "sg:phone":"+44 23 8061 2489",
    "sg:postcode":"SO50 5DS",
    "sg:province":"Hampshire",
    "sg:tags":[
        "decorator",
        "painter"
    ],
    "wof:name":"D S Woodhouse",
    "wof:placetype":"venue"
},
  "geometry": {"coordinates":[-1.3697179556,50.9632148743],"type":"Point"}
}