{
  "type": "Feature",
  "properties": {
    "addr:full":"33 West End, Stokesley Middlesbrough North Yorkshire TS9 5BL",
    "addr:housenumber":"33",
    "addr:postcode":"ts9 5bl",
    "addr:street":"West End",
    "iso:country":"GB",
    "sg:address":"33 West End, Stokesley",
    "sg:city":"Middlesbrough",
    "sg:classifiers":[
        {
            "category":"Health Services",
            "subcategory":"Nursing And Care Facility",
            "type":"Services"
        }
    ],
    "sg:postcode":"TS9 5BL",
    "sg:province":"North Yorkshire",
    "sg:tags":[
        "home"
    ],
    "wof:name":"Oaklands Nursing Home",
    "wof:placetype":"venue"
},
  "geometry": {"coordinates":[-1.19664,54.467697],"type":"Point"}
}