{
  "type": "Feature",
  "properties": {
    "addr:full":"Bryncelynog, Cwm Prysor, Trawsfynydd Blaenau Ffestiniog Gwynedd LL41 4TR",
    "addr:postcode":"ll41 4tr",
    "addr:street":"Cwm;Trawsfynydd",
    "iso:country":"GB",
    "sg:address":"Bryncelynog, Cwm Prysor, Trawsfynydd",
    "sg:city":"Blaenau Ffestiniog",
    "sg:classifiers":[
        {
            "category":"Farming",
            "subcategory":"Livestock Farm",
            "type":"Manufacturing & Wholesale Goods"
        }
    ],
    "sg:phone":"+44 1766 540378",
    "sg:postcode":"LL41 4TR",
    "sg:province":"Gwynedd",
    "sg:tags":[
        "others"
    ],
    "wof:name":"J E G E & D Hughes",
    "wof:placetype":"venue"
},
  "geometry": {"coordinates":[-3.9315590858,52.9613494873],"type":"Point"}
}