{
  "type": "Feature",
  "properties": {
    "iso:country":"GB",
    "sg:address":"34 Surrey Street",
    "sg:city":"Croydon",
    "sg:classifiers":[
        {
            "category":"Restaurant",
            "type":"Food & Drink"
        }
    ],
    "sg:phone":"+44 20 8256 0007",
    "sg:postcode":"CR0 1RJ",
    "sg:province":"Surrey",
    "sg:tags":[
        "oriental"
    ],
    "wof:name":"Jim Thompson S Oriental Bar",
    "wof:placetype":"venue"
},
  "geometry": {"coordinates":[-0.1013899967,51.3733863831],"type":"Point"}
}