{
  "type": "Feature",
  "properties": {
    "iso:country":"GB",
    "sg:address":"40 Bridwell Road, Weston Mill",
    "sg:city":"Plymouth",
    "sg:classifiers":[
        {
            "category":"Personal",
            "subcategory":"Beauty Salon",
            "type":"Services"
        }
    ],
    "sg:phone":"+44 1752 361002",
    "sg:postcode":"PL5 1AA",
    "sg:province":"Devon",
    "sg:tags":[
        "lady",
        "hairdresser"
    ],
    "wof:name":"Lynne's Salon",
    "wof:placetype":"venue"
},
  "geometry": {"coordinates":[-4.180488,50.398586],"type":"Point"}
}