{
  "type": "Feature",
  "properties": {
    "addr:full":"194 Renfrew Street Glasgow Glasgow City G3 6TX",
    "addr:housenumber":"194",
    "addr:postcode":"g3 6tx",
    "addr:street":"Renfrew Street",
    "iso:country":"GB",
    "sg:address":"194 Renfrew Street",
    "sg:city":"Glasgow",
    "sg:classifiers":[
        {
            "category":"Travel",
            "subcategory":"Hotels & Motels",
            "type":"Entertainment"
        }
    ],
    "sg:phone":"+44 141 334 8886",
    "sg:postcode":"G3 6TX",
    "sg:province":"Glasgow City",
    "wof:name":"Old School House Hotel",
    "wof:placetype":"venue"
},
  "geometry": {"coordinates":[-4.2647109032,55.8664855957],"type":"Point"}
}