{
  "type": "Feature",
  "properties": {
    "addr:full":"Cefncyfronydd Farm, Cyfronydd Welshpool Shropshire SY21 9ER",
    "addr:postcode":"sy21 9er",
    "iso:country":"GB",
    "sg:address":"Cefncyfronydd Farm, Cyfronydd",
    "sg:city":"Welshpool",
    "sg:classifiers":[
        {
            "category":"Banks & Credit Unions",
            "subcategory":"Investment Brokerage",
            "type":"Services"
        },
        {
            "category":"Professional",
            "subcategory":"Employment Agencies",
            "type":"Services"
        }
    ],
    "sg:postcode":"SY21 9ER",
    "sg:province":"Shropshire",
    "sg:tags":[
        "agricultural",
        "advice",
        "contractor"
    ],
    "wof:name":"C V & E M Lewis",
    "wof:placetype":"venue"
},
  "geometry": {"coordinates":[-3.2677268982,52.6615447998],"type":"Point"}
}