{
  "type": "Feature",
  "properties": {
    "iso:country":"GB",
    "sg:address":"61 Church Street",
    "sg:city":"Falmouth",
    "sg:classifiers":[
        {
            "category":"Sports & Exercise",
            "subcategory":"Sports Center",
            "type":"Entertainment"
        }
    ],
    "sg:postcode":"TR11 3DS",
    "sg:province":"Cornwall",
    "sg:tags":[
        "shop",
        "good"
    ],
    "wof:name":"Sportsworld",
    "wof:placetype":"venue"
},
  "geometry": {"coordinates":[-5.068434,50.154758],"type":"Point"}
}