{
  "type": "Feature",
  "properties": {
    "addr:full":"457 Fulham Rd West Brompton Greater London SW10 9UZ",
    "addr:housenumber":"457",
    "addr:postcode":"sw10 9uz",
    "addr:street":"Fulham Rd",
    "iso:country":"GB",
    "sg:address":"457 Fulham Rd",
    "sg:city":"West Brompton",
    "sg:classifiers":[
        {
            "category":"Restaurant",
            "type":"Food & Drink"
        }
    ],
    "sg:phone":"+44 20 7352 0206",
    "sg:postcode":"SW10 9UZ",
    "sg:province":"Greater London",
    "sg:tags":[
        "chinese"
    ],
    "wof:name":"Kingdom Chinese Cuisine",
    "wof:placetype":"venue"
},
  "geometry": {"coordinates":[-0.18567,51.483105],"type":"Point"}
}