{
  "type": "Feature",
  "properties": {
    "iso:country":"GB",
    "sg:address":"457 Fulham Rd",
    "sg:city":"West Brompton",
    "sg:classifiers":[
        {
            "category":"Restaurant",
            "type":"Food & Drink"
        }
    ],
    "sg:phone":"+44 20 7352 0206",
    "sg:postcode":"SW10 9UZ",
    "sg:province":"Greater London",
    "sg:tags":[
        "chinese"
    ],
    "wof:name":"Kingdom Chinese Cuisine",
    "wof:placetype":"venue"
},
  "geometry": {"coordinates":[-0.18567,51.483105],"type":"Point"}
}