{
  "type": "Feature",
  "properties": {
    "addr:full":"Huntly Business Centre Huntly Aberdeenshire AB54 8FG",
    "addr:postcode":"ab54 8fg",
    "addr:street":"Huntly",
    "iso:country":"GB",
    "sg:address":"Huntly Business Centre",
    "sg:city":"Huntly",
    "sg:classifiers":[
        {
            "category":"Banks & Credit Unions",
            "subcategory":"Financial Services",
            "type":"Services"
        }
    ],
    "sg:postcode":"AB54 8FG",
    "sg:province":"Aberdeenshire",
    "sg:tags":[
        "building",
        "society"
    ],
    "wof:name":"Stuart Wilson Dickson & Co.",
    "wof:placetype":"venue"
},
  "geometry": {"coordinates":[-2.7934091091,57.4425811768],"type":"Point"}
}