{
  "type": "Feature",
  "properties": {
    "iso:country":"GB",
    "sg:address":"181 Rookery Road, Handsworth",
    "sg:city":"Birmingham",
    "sg:classifiers":[
        {
            "category":"Shopping",
            "subcategory":"Comic Books",
            "type":"Retail Goods"
        }
    ],
    "sg:phone":"+44 121 554 3573",
    "sg:postcode":"B21 9QZ",
    "sg:province":"West Midlands",
    "sg:tags":[
        "jeweller"
    ],
    "wof:name":"Yash Jewellers",
    "wof:placetype":"venue"
},
  "geometry": {"coordinates":[-1.9401839972,52.5105781555],"type":"Point"}
}