{
  "type": "Feature",
  "properties": {
    "addr:full":"144 Station Rd, Beeston Nottingham Nottinghamshire NG9 2AY",
    "addr:housenumber":"144",
    "addr:postcode":"ng9 2ay",
    "addr:street":"Station Rd",
    "iso:country":"GB",
    "sg:address":"144 Station Rd, Beeston",
    "sg:city":"Nottingham",
    "sg:classifiers":[
        {
            "category":"Professional",
            "subcategory":"Advertising",
            "type":"Services"
        }
    ],
    "sg:phone":"+44 115 943 6464",
    "sg:postcode":"NG9 2AY",
    "sg:province":"Nottinghamshire",
    "sg:tags":[
        "telemarketing"
    ],
    "wof:name":"P.D.L Holidays",
    "wof:placetype":"venue"
},
  "geometry": {"coordinates":[-1.2111439705,52.9239463806],"type":"Point"}
}