{
  "type": "Feature",
  "properties": {
    "iso:country":"GB",
    "sg:address":"15 Douglas Cres",
    "sg:city":"Dunstable",
    "sg:classifiers":[
        {
            "category":"Communications",
            "type":"Services"
        }
    ],
    "sg:phone":"+44 1582 607880",
    "sg:postcode":"LU5 5AS",
    "sg:province":"Bedfordshire",
    "sg:tags":[
        "audio-visual"
    ],
    "wof:name":"Eurotech Video Ltd",
    "wof:placetype":"venue"
},
  "geometry": {"coordinates":[-0.5269399881,51.8971099854],"type":"Point"}
}