{
  "type": "Feature",
  "properties": {
    "iso:country":"GB",
    "sg:address":"22 Buckhurst Road",
    "sg:city":"Bexhill-on-sea",
    "sg:classifiers":[
        {
            "category":"Health Services",
            "subcategory":"Nursing And Care Facility",
            "type":"Services"
        }
    ],
    "sg:phone":"+44 1424 223460",
    "sg:postcode":"TN40 1QE",
    "sg:province":"East Sussex",
    "sg:tags":[
        "home"
    ],
    "wof:name":"St Georges Nursing Home",
    "wof:placetype":"venue"
},
  "geometry": {"coordinates":[0.47467,50.84222],"type":"Point"}
}