{
  "type": "Feature",
  "properties": {
    "iso:country":"GB",
    "sg:address":"Highbridge House, 9 Station Road, Williton",
    "sg:city":"Taunton",
    "sg:classifiers":[
        {
            "category":"Food & Beverages",
            "subcategory":"Fruits & Vegetables",
            "type":"Retail Goods"
        },
        {
            "category":"Shopping",
            "subcategory":"Florist",
            "type":"Retail Goods"
        }
    ],
    "sg:phone":"+44 1984 632323",
    "sg:postcode":"TA4 4RJ",
    "sg:province":"Devon",
    "sg:tags":[
        "greengrocer"
    ],
    "wof:name":"J JONES & SONS",
    "wof:placetype":"venue"
},
  "geometry": {"coordinates":[-3.306835,51.166409],"type":"Point"}
}