{
  "type": "Feature",
  "properties": {
    "addr:full":"3 Fornham Road Bury St Edmunds Suffolk IP32 6AH",
    "addr:housenumber":"3",
    "addr:postcode":"ip32 6ah",
    "addr:street":"Fornham Road",
    "iso:country":"GB",
    "sg:address":"3 Fornham Road",
    "sg:city":"Bury St Edmunds",
    "sg:classifiers":[
        {
            "category":"Professional",
            "subcategory":"Engineering",
            "type":"Services"
        }
    ],
    "sg:phone":"+44 1284 761015",
    "sg:postcode":"IP32 6AH",
    "sg:province":"Suffolk",
    "sg:tags":[
        "contractor",
        "electrical",
        "engineer"
    ],
    "wof:name":"Drake & Scull Technical Services",
    "wof:placetype":"venue"
},
  "geometry": {"coordinates":[0.7142599821,52.2538490295],"type":"Point"}
}