{
  "type": "Feature",
  "properties": {
    "iso:country":"GB",
    "sg:address":"The Old Chapel, Back Road",
    "sg:city":"Wisbech",
    "sg:classifiers":[
        {
            "category":"Wholesale",
            "subcategory":"Meat",
            "type":"Manufacturing & Wholesale Goods"
        }
    ],
    "sg:phone":"+44 1945 860797",
    "sg:postcode":"PE13 5ED",
    "sg:province":"Cambridgeshire",
    "sg:tags":[
        "product"
    ],
    "wof:name":"T Dewey Quality Meats",
    "wof:placetype":"venue"
},
  "geometry": {"coordinates":[0.157228,52.669689],"type":"Point"}
}