{
  "type": "Feature",
  "properties": {
    "addr:full":"13 Brewer Street Maidstone Kent ME14 1RU",
    "addr:postcode":"me14 1ru",
    "addr:street":"13 Brewer Street",
    "iso:country":"GB",
    "sg:address":"13 Brewer Street",
    "sg:city":"Maidstone",
    "sg:classifiers":[
        {
            "category":"Professional",
            "subcategory":"Testing Lab",
            "type":"Services"
        }
    ],
    "sg:postcode":"ME14 1RU",
    "sg:province":"Kent",
    "sg:tags":[
        "pregnancy"
    ],
    "wof:name":"Life Pregnancy Care Service",
    "wof:placetype":"venue"
},
  "geometry": {"coordinates":[0.5225099921,51.2769317627],"type":"Point"}
}