{
  "type": "Feature",
  "properties": {
    "addr:full":"6 Clinton Terrace, Derby Road Nottingham Nottinghamshire NG7 1LZ",
    "addr:housenumber":"6",
    "addr:postcode":"ng7 1lz",
    "addr:street":"Clinton Terrace Derby Road",
    "iso:country":"GB",
    "sg:address":"6 Clinton Terrace, Derby Road",
    "sg:city":"Nottingham",
    "sg:classifiers":[
        {
            "category":"Organizations",
            "subcategory":"Non-profit Organization",
            "type":"Services"
        }
    ],
    "sg:phone":"+44 115 941 1015",
    "sg:postcode":"NG7 1LZ",
    "sg:province":"Nottinghamshire",
    "sg:tags":[
        "organisation",
        "voluntary",
        "charity"
    ],
    "wof:name":"The Army Benevolent Fund",
    "wof:placetype":"venue"
},
  "geometry": {"coordinates":[-1.1644400358,52.9548912048],"type":"Point"}
}