{
  "type": "Feature",
  "properties": {
    "addr:full":"Skircoat Moor Road, Saville Park Halifax West Yorkshire HX3 0HG",
    "addr:postcode":"hx3 0hg",
    "addr:street":"Skircoat Moor Road Saville Park",
    "iso:country":"GB",
    "sg:address":"Skircoat Moor Road, Saville Park",
    "sg:city":"Halifax",
    "sg:classifiers":[
        {
            "category":"Education",
            "subcategory":"School",
            "type":"Public Place"
        }
    ],
    "sg:phone":"+44 1422 360272",
    "sg:postcode":"HX3 0HG",
    "sg:province":"West Yorkshire",
    "sg:tags":[
        "college"
    ],
    "wof:name":"Crossley Heath School",
    "wof:placetype":"venue"
},
  "geometry": {"coordinates":[-1.8807179928,53.7125167847],"type":"Point"}
}