{
  "type": "Feature",
  "properties": {
    "addr:full":"21 Albion Place Leeds West Yorkshire LS1 6JS",
    "addr:housenumber":"21",
    "addr:postcode":"ls1 6js",
    "addr:street":"Albion Place",
    "iso:country":"GB",
    "sg:address":"21 Albion Place",
    "sg:city":"Leeds",
    "sg:classifiers":[
        {
            "category":"Shopping",
            "subcategory":"Department Store",
            "type":"Retail Goods"
        }
    ],
    "sg:phone":"+44 113 245 8261",
    "sg:postcode":"LS1 6JS",
    "sg:province":"West Yorkshire",
    "wof:name":"Bentleyfilms Ltd.",
    "wof:placetype":"venue"
},
  "geometry": {"coordinates":[-1.5429860353,53.7976799011],"type":"Point"}
}