{
  "type": "Feature",
  "properties": {
    "addr:full":"146 Westmount Road London Greater London SE9 1XA",
    "addr:housenumber":"146",
    "addr:postcode":"se9 1xa",
    "addr:street":"Westmount Road",
    "iso:country":"GB",
    "sg:address":"146 Westmount Road",
    "sg:city":"London",
    "sg:classifiers":[
        {
            "category":"Retail",
            "subcategory":"Laundry & Dry Cleaning",
            "type":"Services"
        }
    ],
    "sg:phone":"+44 20 8850 5616",
    "sg:postcode":"SE9 1XA",
    "sg:province":"Greater London",
    "sg:tags":[
        "cleaner",
        "alteration"
    ],
    "wof:name":"Westmount Dry Cleaners",
    "wof:placetype":"venue"
},
  "geometry": {"coordinates":[0.059014,51.458431],"type":"Point"}
}