{
  "type": "Feature",
  "properties": {
    "addr:full":"33 Woodside Avenue Amersham Buckinghamshire HP6 6BQ",
    "addr:housenumber":"33",
    "addr:postcode":"hp6 6bq",
    "addr:street":"Woodside Avenue Amersham",
    "iso:country":"GB",
    "sg:address":"33 Woodside Avenue",
    "sg:city":"Amersham",
    "sg:classifiers":[
        {
            "category":"Building & Trades",
            "subcategory":"Construction",
            "type":"Services"
        }
    ],
    "sg:phone":"+44 1494 728411",
    "sg:postcode":"HP6 6BQ",
    "sg:province":"Buckinghamshire",
    "sg:tags":[
        "heating",
        "contractor"
    ],
    "wof:name":"A C T Plumbing",
    "wof:placetype":"venue"
},
  "geometry": {"coordinates":[-0.597975,51.683517],"type":"Point"}
}