{
  "type": "Feature",
  "properties": {
    "iso:country":"GB",
    "sg:address":"70-72 Abergele Road",
    "sg:city":"Colwyn Bay",
    "sg:classifiers":[
        {
            "category":"Sports & Exercise",
            "subcategory":"Sports Center",
            "type":"Entertainment"
        }
    ],
    "sg:phone":"+44 1492 532151",
    "sg:postcode":"LL29 7PP",
    "sg:province":"Conwy",
    "sg:tags":[
        "shop",
        "good"
    ],
    "wof:name":"Gilbert Emery Sports Ltd.",
    "wof:placetype":"venue"
},
  "geometry": {"coordinates":[-3.723568,53.292934],"type":"Point"}
}