{
  "type": "Feature",
  "properties": {
    "iso:country":"GB",
    "sg:address":"The Bungalow, Great Snoring Road, Hindringham",
    "sg:city":"Fakenham",
    "sg:classifiers":[
        {
            "category":"Manufacturing",
            "subcategory":"Tools & Machinery",
            "type":"Manufacturing & Wholesale Goods"
        },
        {
            "category":"Home & Garden",
            "subcategory":"Building Materials",
            "type":"Retail Goods"
        }
    ],
    "sg:phone":"+44 1328 878389",
    "sg:postcode":"NR21 0PG",
    "sg:province":"Norfolk",
    "sg:tags":[
        "supplier"
    ],
    "wof:name":"T J Hawes & Son",
    "wof:placetype":"venue"
},
  "geometry": {"coordinates":[0.943698,52.884281],"type":"Point"}
}