{
  "type": "Feature",
  "properties": {
    "iso:country":"GB",
    "sg:address":"80 Baberton Mains Dr",
    "sg:city":"Edinburgh",
    "sg:classifiers":[
        {
            "category":"Building & Trades",
            "subcategory":"Construction",
            "type":"Services"
        }
    ],
    "sg:phone":"+44 131 442 3791",
    "sg:postcode":"EH14 3BT",
    "sg:province":"City of Edinburgh",
    "sg:tags":[
        "heating",
        "contractor"
    ],
    "wof:name":"Forth Heating Services",
    "wof:placetype":"venue"
},
  "geometry": {"coordinates":[-3.2885138988,55.9089546204],"type":"Point"}
}