{
  "type": "Feature",
  "properties": {
    "addr:full":"23-27 Market Street Watford Hertfordshire WD18 0PH",
    "addr:housenumber":"23-27",
    "addr:postcode":"wd18 0ph",
    "addr:street":"Market Street",
    "iso:country":"GB",
    "sg:address":"23-27 Market Street",
    "sg:city":"Watford",
    "sg:classifiers":[
        {
            "category":"Home & Garden",
            "subcategory":"Furniture",
            "type":"Retail Goods"
        }
    ],
    "sg:phone":"+44 1923 227788",
    "sg:postcode":"WD18 0PH",
    "sg:province":"Hertfordshire",
    "wof:name":"Kingsway Scotland Ltd.",
    "wof:placetype":"venue"
},
  "geometry": {"coordinates":[-0.397879,51.654827],"type":"Point"}
}