{
  "type": "Feature",
  "properties": {
    "iso:country":"GB",
    "sg:address":"Scarr Hall, Pollard Lane",
    "sg:city":"Bradford",
    "sg:classifiers":[
        {
            "category":"Sports & Exercise",
            "subcategory":"Golf",
            "type":"Entertainment"
        }
    ],
    "sg:phone":"+44 1274 771693",
    "sg:postcode":"BD2 4RW",
    "sg:province":"West Yorkshire",
    "sg:tags":[
        "club",
        "course"
    ],
    "wof:name":"Bradford Moor Golf Club",
    "wof:placetype":"venue"
},
  "geometry": {"coordinates":[-1.72835,53.805279],"type":"Point"}
}