{
  "type": "Feature",
  "properties": {
    "iso:country":"GB",
    "sg:address":"Unit 7 21 Bondgate",
    "sg:city":"Selby",
    "sg:classifiers":[
        {
            "category":"Retail",
            "subcategory":"Laundry & Dry Cleaning",
            "type":"Services"
        }
    ],
    "sg:phone":"+44 1757 210548",
    "sg:postcode":"YO8 3LX",
    "sg:province":"East Riding of Yorkshire",
    "sg:tags":[
        "launderette"
    ],
    "wof:name":"Kleen Line Direct",
    "wof:placetype":"venue"
},
  "geometry": {"coordinates":[-1.0752240419,53.7910118103],"type":"Point"}
}