{
  "type": "Feature",
  "properties": {
    "iso:country":"GB",
    "sg:address":"55-57 Napier Avenue",
    "sg:city":"Blackpool",
    "sg:classifiers":[
        {
            "category":"Social Services",
            "subcategory":"Retirement Home",
            "type":"Services"
        }
    ],
    "sg:postcode":"FY4 1PB",
    "sg:province":"Lancashire",
    "sg:tags":[
        "rest"
    ],
    "wof:name":"Tudor Crest Rest Home",
    "wof:placetype":"venue"
},
  "geometry": {"coordinates":[-3.054925,53.785236],"type":"Point"}
}