{
  "type": "Feature",
  "properties": {
    "iso:country":"GB",
    "sg:address":"Kempsford Quarry Washpool Lane, Kempsford",
    "sg:city":"Fairford",
    "sg:classifiers":[
        {
            "category":"Home & Garden",
            "subcategory":"Garden Supply",
            "type":"Retail Goods"
        }
    ],
    "sg:phone":"+44 1285 810029",
    "sg:postcode":"GL7 4NJ",
    "sg:province":"Gloucestershire",
    "sg:tags":[
        "sand",
        "gravel"
    ],
    "wof:name":"Multi-Agg Ltd.",
    "wof:placetype":"venue"
},
  "geometry": {"coordinates":[-1.7794879675,51.7071800232],"type":"Point"}
}