{
  "type": "Feature",
  "properties": {
    "addr:full":"Heysham Rd Bootle Merseyside L30 6YJ",
    "addr:postcode":"l30 6yj",
    "addr:street":"Heysham Rd",
    "iso:country":"GB",
    "sg:address":"Heysham Rd",
    "sg:city":"Bootle",
    "sg:classifiers":[
        {
            "category":"Building & Trades",
            "subcategory":"Equipment Rental",
            "type":"Services"
        }
    ],
    "sg:phone":"+44 151 286 8888",
    "sg:postcode":"L30 6YJ",
    "sg:province":"Merseyside",
    "sg:tags":[
        "plant",
        "machinery"
    ],
    "wof:name":"Aintree Plant",
    "wof:placetype":"venue"
},
  "geometry": {"coordinates":[-2.9614989758,53.483001709],"type":"Point"}
}