{
  "type": "Feature",
  "properties": {
    "addr:full":"58 Clarence Avenue, Gants Hill Ilford Essex IG2 6JE",
    "addr:housenumber":"58",
    "addr:postcode":"ig2 6je",
    "addr:street":"Clarence Avenue Gants Hill",
    "iso:country":"GB",
    "sg:address":"58 Clarence Avenue, Gants Hill",
    "sg:city":"Ilford",
    "sg:classifiers":[
        {
            "category":"Health Services",
            "subcategory":"Dentist",
            "type":"Services"
        }
    ],
    "sg:phone":"+44 20 8554 8727",
    "sg:postcode":"IG2 6JE",
    "sg:province":"Essex",
    "wof:name":"Clarence House Dental Health Centre",
    "wof:placetype":"venue"
},
  "geometry": {"coordinates":[0.065572001,51.5760269165],"type":"Point"}
}