{
  "type": "Feature",
  "properties": {
    "iso:country":"GB",
    "sg:address":"Unit 8 North Way, Walworth Industrial Estate",
    "sg:city":"Andover",
    "sg:classifiers":[
        {
            "category":"Farming",
            "subcategory":"Fish & Marine Products",
            "type":"Manufacturing & Wholesale Goods"
        }
    ],
    "sg:phone":"+44 1264 357357",
    "sg:postcode":"SP10 5AZ",
    "sg:province":"Hampshire",
    "sg:tags":[
        "equipment",
        "electrical"
    ],
    "wof:name":"Scientific Management Associates (U K) Ltd.",
    "wof:placetype":"venue"
},
  "geometry": {"coordinates":[-1.4520139694,51.2203865051],"type":"Point"}
}