{
  "type": "Feature",
  "properties": {
    "iso:country":"GB",
    "sg:address":"172 Whittingham Lane, Goosnargh",
    "sg:city":"Preston",
    "sg:classifiers":[
        {
            "category":"Building & Trades",
            "subcategory":"Equipment Rental",
            "type":"Services"
        }
    ],
    "sg:phone":"+44 1772 866487",
    "sg:postcode":"PR3 2JJ",
    "sg:province":"Lancashire",
    "sg:tags":[
        "plant",
        "machinery"
    ],
    "wof:name":"J R Plant",
    "wof:placetype":"venue"
},
  "geometry": {"coordinates":[-2.702959,53.81702],"type":"Point"}
}