{
  "type": "Feature",
  "properties": {
    "iso:country":"GB",
    "sg:address":"36-38 East Port",
    "sg:city":"Dunfermline",
    "sg:classifiers":[
        {
            "category":"Professional",
            "subcategory":"Lawyer & Legal Services",
            "type":"Services"
        },
        {
            "category":"Real Estate",
            "subcategory":"Real Estate Agent",
            "type":"Services"
        }
    ],
    "sg:phone":"+44 1383 626200",
    "sg:postcode":"KY12 7JB",
    "sg:province":"Fife",
    "sg:tags":[
        "solicitor"
    ],
    "wof:name":"Ross & Connel",
    "wof:placetype":"venue"
},
  "geometry": {"coordinates":[-3.4582090378,56.0718650818],"type":"Point"}
}