{
  "type": "Feature",
  "properties": {
    "iso:country":"GB",
    "sg:address":"Market Place, Couching Street",
    "sg:city":"Watlington",
    "sg:classifiers":[
        {
            "category":"Shopping",
            "subcategory":"Pharmacy",
            "type":"Retail Goods"
        }
    ],
    "sg:phone":"+44 1491 612248",
    "sg:postcode":"OX49 5PU",
    "sg:province":"Oxfordshire",
    "sg:tags":[
        "pharmacist",
        "dispensing",
        "chemist"
    ],
    "wof:name":"Watlington Pharmacy Ltd.",
    "wof:placetype":"venue"
},
  "geometry": {"coordinates":[-1.0056810379,51.6440849304],"type":"Point"}
}