{
  "type": "Feature",
  "properties": {
    "addr:full":"Chapelhall Industrial Estate Airdrie North Lanarkshire ML6 8QH",
    "addr:postcode":"ml6 8qh",
    "addr:street":"Estate Airdrie",
    "iso:country":"GB",
    "sg:address":"Chapelhall Industrial Estate",
    "sg:city":"Airdrie",
    "sg:classifiers":[
        {
            "category":"Home & Garden",
            "subcategory":"Home Furnishings",
            "type":"Retail Goods"
        }
    ],
    "sg:phone":"+44 1236 747646",
    "sg:postcode":"ML6 8QH",
    "sg:province":"North Lanarkshire",
    "sg:tags":[
        "furnishers",
        "planner",
        "kitchen"
    ],
    "wof:name":"F M Woodcraft",
    "wof:placetype":"venue"
},
  "geometry": {"coordinates":[-3.9504139423,55.8420333862],"type":"Point"}
}