{
  "type": "Feature",
  "properties": {
    "iso:country":"GB",
    "sg:address":"Halifax Road",
    "sg:city":"Todmorden",
    "sg:classifiers":[
        {
            "category":"Wholesale",
            "subcategory":"Machinery & Supplies",
            "type":"Manufacturing & Wholesale Goods"
        }
    ],
    "sg:phone":"+44 1706 814251",
    "sg:postcode":"OL14 5RT",
    "sg:province":"Lancashire",
    "sg:tags":[
        "pump"
    ],
    "wof:name":"Weir Warman Ltd.",
    "wof:placetype":"venue"
},
  "geometry": {"coordinates":[-2.081419,53.716614],"type":"Point"}
}