{
  "type": "Feature",
  "properties": {
    "addr:full":"15 Beeston View Stoke-on-trent Cheshire ST7 4TB",
    "addr:housenumber":"15",
    "addr:postcode":"st7 4tb",
    "addr:street":"Beeston View",
    "iso:country":"GB",
    "sg:address":"15 Beeston View",
    "sg:city":"Stoke-on-trent",
    "sg:classifiers":[
        {
            "category":"Building & Trades",
            "subcategory":"Construction",
            "type":"Services"
        }
    ],
    "sg:phone":"+44 1782 772336",
    "sg:postcode":"ST7 4TB",
    "sg:province":"Cheshire",
    "sg:tags":[
        "builder"
    ],
    "wof:name":"Mark A Hopkins",
    "wof:placetype":"venue"
},
  "geometry": {"coordinates":[-2.2359850407,53.0770568848],"type":"Point"}
}