{
  "type": "Feature",
  "properties": {
    "addr:full":"Nursling House, Church Lane, Nursling Southampton Hampshire SO16 0YB",
    "addr:postcode":"so16 0yb",
    "addr:street":"Church Lane",
    "iso:country":"GB",
    "sg:address":"Nursling House, Church Lane, Nursling",
    "sg:city":"Southampton",
    "sg:classifiers":[
        {
            "category":"Place Of Worship",
            "type":"Public Place"
        }
    ],
    "sg:phone":"+44 23 8073 8293",
    "sg:postcode":"SO16 0YB",
    "sg:province":"Hampshire",
    "wof:name":"St Boniface C Of E Church",
    "wof:placetype":"venue"
},
  "geometry": {"coordinates":[-1.489665,50.946384],"type":"Point"}
}