{
  "type": "Feature",
  "properties": {
    "iso:country":"GB",
    "sg:address":"1 Roydon Rd",
    "sg:city":"Diss",
    "sg:classifiers":[
        {
            "category":"Health Services",
            "subcategory":"Podiatrist",
            "type":"Services"
        }
    ],
    "sg:phone":"+44 1379 640370",
    "sg:postcode":"IP22 3LN",
    "sg:province":"Norfolk",
    "sg:tags":[
        "podiatrists",
        "chiropodist"
    ],
    "wof:name":"J Lambley",
    "wof:placetype":"venue"
},
  "geometry": {"coordinates":[1.1026,52.37801],"type":"Point"}
}