{
  "type": "Feature",
  "properties": {
    "addr:full":"N T L House, Bartley Wood Business Park, Hook Berkshire RG27 9UP",
    "addr:postcode":"rg27 9up",
    "addr:street":"N T L House Bartley Wood Business Park",
    "iso:country":"GB",
    "sg:address":"N T L House, Bartley Wood Business Park,",
    "sg:city":"Hook",
    "sg:classifiers":[
        {
            "category":"Utilities",
            "subcategory":"Cable",
            "type":"Services"
        }
    ],
    "sg:postcode":"RG27 9UP",
    "sg:province":"Berkshire",
    "sg:tags":[
        "tv"
    ],
    "wof:name":"Metro South Wales Ltd",
    "wof:placetype":"venue"
},
  "geometry": {"coordinates":[-0.965719,51.281361],"type":"Point"}
}