{
  "type": "Feature",
  "properties": {
    "addr:full":"52 Coventry Street Southam Warwickshire CV47 0EP",
    "addr:housenumber":"52",
    "addr:postcode":"cv47 0ep",
    "addr:street":"Coventry Street",
    "iso:country":"GB",
    "sg:address":"52 Coventry Street",
    "sg:city":"Southam",
    "sg:classifiers":[
        {
            "category":"Health Services",
            "subcategory":"Optometrist",
            "type":"Services"
        }
    ],
    "sg:phone":"+44 1926 813113",
    "sg:postcode":"CV47 0EP",
    "sg:province":"Warwickshire",
    "sg:tags":[
        "optician"
    ],
    "wof:name":"Janet A Porter",
    "wof:placetype":"venue"
},
  "geometry": {"coordinates":[-1.387414,52.253864],"type":"Point"}
}