{
  "type": "Feature",
  "properties": {
    "addr:full":"57 Broad St Worcester Worcestershire WR1 3LY",
    "addr:housenumber":"57",
    "addr:postcode":"wr1 3ly",
    "addr:street":"Broad St",
    "iso:country":"GB",
    "sg:address":"57 Broad St",
    "sg:city":"Worcester",
    "sg:classifiers":[
        {
            "category":"Manufacturing",
            "subcategory":"Textiles",
            "type":"Manufacturing & Wholesale Goods"
        }
    ],
    "sg:phone":"+44 1905 22031",
    "sg:postcode":"WR1 3LY",
    "sg:province":"Worcestershire",
    "sg:tags":[
        "made-up"
    ],
    "wof:name":"Brentfords",
    "wof:placetype":"venue"
},
  "geometry": {"coordinates":[-2.2223069668,52.1926345825],"type":"Point"}
}