{
  "type": "Feature",
  "properties": {
    "addr:full":"25 High Street, Storrington Pulborough West Sussex RH20 4DR",
    "addr:housenumber":"25",
    "addr:postcode":"rh20 4dr",
    "addr:street":"High Street",
    "iso:country":"GB",
    "sg:address":"25 High Street, Storrington",
    "sg:city":"Pulborough",
    "sg:classifiers":[
        {
            "category":"Shopping",
            "subcategory":"Pharmacy",
            "type":"Retail Goods"
        }
    ],
    "sg:phone":"+44 1903 742411",
    "sg:postcode":"RH20 4DR",
    "sg:province":"West Sussex",
    "sg:tags":[
        "pharmacist",
        "chemist"
    ],
    "wof:name":"Colonnade Pharmacy",
    "wof:placetype":"venue"
},
  "geometry": {"coordinates":[-0.452705,50.91777],"type":"Point"}
}