{
  "type": "Feature",
  "properties": {
    "iso:country":"GB",
    "sg:address":"Unit 1 The Pavilions, Avroe Crescent",
    "sg:city":"Blackpool",
    "sg:classifiers":[
        {
            "category":"Professional",
            "subcategory":"Management & Consulting",
            "type":"Services"
        }
    ],
    "sg:phone":"+44 1253 336200",
    "sg:postcode":"FY4 2DP",
    "sg:province":"Lancashire",
    "sg:tags":[
        "marketing",
        "consultant"
    ],
    "wof:name":"Boe Publishing Holdings Ltd.",
    "wof:placetype":"venue"
},
  "geometry": {"coordinates":[-3.045379,53.778446],"type":"Point"}
}