{
  "type": "Feature",
  "properties": {
    "iso:country":"GB",
    "sg:address":"18-22 Wigmore Street",
    "sg:city":"London",
    "sg:classifiers":[
        {
            "category":"Food & Beverages",
            "subcategory":"Bakery",
            "type":"Retail Goods"
        }
    ],
    "sg:postcode":"W14 9DE",
    "sg:province":"Greater London",
    "sg:tags":[
        "baker"
    ],
    "wof:name":"Just Right (Uk) Ltd",
    "wof:placetype":"venue"
},
  "geometry": {"coordinates":[-0.147148,51.516788],"type":"Point"}
}