{
  "type": "Feature",
  "properties": {
    "addr:full":"282-284 Hoe St Walthamstow Greater London E17 9PL",
    "addr:housenumber":"282-284",
    "addr:postcode":"e17 9pl",
    "addr:street":"Hoe St",
    "iso:country":"GB",
    "sg:address":"282-284 Hoe St",
    "sg:city":"Walthamstow",
    "sg:classifiers":[
        {
            "category":"Professional",
            "subcategory":"Lawyer & Legal Services",
            "type":"Services"
        }
    ],
    "sg:phone":"+44 20 8520 1021",
    "sg:postcode":"E17 9PL",
    "sg:province":"Greater London",
    "sg:tags":[
        "solicitor"
    ],
    "wof:name":"John Williams",
    "wof:placetype":"venue"
},
  "geometry": {"coordinates":[-0.018677,51.5823898315],"type":"Point"}
}