{
  "type": "Feature",
  "properties": {
    "addr:full":"239a Bromley Road, Catford London Greater London SE6 2RA",
    "addr:housenumber":"239a",
    "addr:postcode":"se6 2ra",
    "addr:street":"Bromley Road",
    "iso:country":"GB",
    "sg:address":"239a Bromley Road, Catford",
    "sg:city":"London",
    "sg:classifiers":[
        {
            "category":"Shopping",
            "subcategory":"Computers & Home Electronics",
            "type":"Retail Goods"
        }
    ],
    "sg:postcode":"SE6 2RA",
    "sg:province":"Greater London",
    "wof:name":"Haider A Charania",
    "wof:placetype":"venue"
},
  "geometry": {"coordinates":[-0.017207,51.433086],"type":"Point"}
}