{
  "type": "Feature",
  "properties": {
    "addr:full":"Harrison House, Hawthorn Terrace Durham Durham DH1 4EL",
    "addr:postcode":"dh1 4el",
    "addr:street":"Hawthorn Terrace",
    "iso:country":"GB",
    "sg:address":"Harrison House, Hawthorn Terrace",
    "sg:city":"Durham",
    "sg:classifiers":[
        {
            "category":"Bars & Pubs",
            "type":"Food & Drink"
        },
        {
            "category":"Community Center",
            "subcategory":"Social",
            "type":"Public Place"
        }
    ],
    "sg:phone":"+44 191 386 9913",
    "sg:postcode":"DH1 4EL",
    "sg:province":"Durham",
    "sg:tags":[
        "pubs",
        "house",
        "inn",
        "activity"
    ],
    "wof:name":"Colpitts Hotel",
    "wof:placetype":"venue"
},
  "geometry": {"coordinates":[-1.5860990286,54.7757415771],"type":"Point"}
}