{
  "type": "Feature",
  "properties": {
    "addr:full":"1 Main St Newcastle Upon Tyne Northumberland NE20 9NH",
    "addr:housenumber":"1",
    "addr:postcode":"ne20 9nh",
    "addr:street":"Main St",
    "iso:country":"GB",
    "sg:address":"1 Main St",
    "sg:city":"Newcastle Upon Tyne",
    "sg:classifiers":[
        {
            "category":"Airline",
            "type":"Transportation"
        }
    ],
    "sg:phone":"+44 1661 871237",
    "sg:postcode":"NE20 9NH",
    "sg:province":"Northumberland",
    "sg:tags":[
        "aircraft",
        "charter"
    ],
    "wof:name":"Eagle Helicopters",
    "wof:placetype":"venue"
},
  "geometry": {"coordinates":[-1.743886,55.049664],"type":"Point"}
}