{
  "type": "Feature",
  "properties": {
    "iso:country":"GB",
    "sg:address":"113-115 High Street",
    "sg:city":"Swansea",
    "sg:classifiers":[
        {
            "category":"Restaurant",
            "type":"Food & Drink"
        }
    ],
    "sg:postcode":"SA8 4JN",
    "sg:province":"Neath Port Talbot",
    "wof:name":"Black Knight Hotel & Restaurant",
    "wof:placetype":"venue"
},
  "geometry": {"coordinates":[-3.847519,51.723721],"type":"Point"}
}