{
  "type": "Feature",
  "properties": {
    "iso:country":"GB",
    "sg:address":"Oakfield House, Oakfield Road",
    "sg:city":"Altrincham",
    "sg:classifiers":[
        {
            "category":"Home & Garden",
            "subcategory":"Household Appliances",
            "type":"Retail Goods"
        }
    ],
    "sg:postcode":"WA15 8EW",
    "sg:province":"Cheshire",
    "sg:tags":[
        "refrigeration",
        "air conditioning"
    ],
    "wof:name":"Spencer Control Systems",
    "wof:placetype":"venue"
},
  "geometry": {"coordinates":[-2.345434,53.386894],"type":"Point"}
}