{
  "type": "Feature",
  "properties": {
    "iso:country":"GB",
    "sg:address":"43 Cross Tree Gro",
    "sg:city":"Bristol",
    "sg:classifiers":[
        {
            "category":"Home & Garden",
            "subcategory":"Carpets & Floor Coverings",
            "type":"Retail Goods"
        }
    ],
    "sg:phone":"+44 1454 620414",
    "sg:postcode":"BS32 9BH",
    "sg:province":"Gloucestershire",
    "sg:tags":[
        "cleaner",
        "upholstery"
    ],
    "wof:name":"S M Andrews",
    "wof:placetype":"venue"
},
  "geometry": {"coordinates":[-2.5514171124,51.5327415466],"type":"Point"}
}