{
  "type": "Feature",
  "properties": {
    "addr:full":"86 Anerley Road London Greater London SE19 2AH",
    "addr:housenumber":"86",
    "addr:postcode":"se19 2ah",
    "addr:street":"Anerley Road",
    "iso:country":"GB",
    "sg:address":"86 Anerley Road",
    "sg:city":"London",
    "sg:classifiers":[
        {
            "category":"Fast Food",
            "type":"Food & Drink"
        }
    ],
    "sg:phone":"+44 20 8778 9997",
    "sg:postcode":"SE19 2AH",
    "sg:province":"Greater London",
    "sg:tags":[
        "away",
        "take"
    ],
    "wof:name":"Golden Curry Tandoori (U K) Ltd.",
    "wof:placetype":"venue"
},
  "geometry": {"coordinates":[-0.0732979998,51.4167366028],"type":"Point"}
}