{
  "type": "Feature",
  "properties": {
    "addr:full":"Newport Market, High Street Newport Newport NP20 1FS",
    "addr:postcode":"np20 1fs",
    "addr:street":"High Street",
    "iso:country":"GB",
    "sg:address":"Newport Market, High Street",
    "sg:city":"Newport",
    "sg:classifiers":[
        {
            "category":"Food & Beverages",
            "subcategory":"Meat & Fish",
            "type":"Retail Goods"
        }
    ],
    "sg:phone":"+44 1633 265839",
    "sg:postcode":"NP20 1FS",
    "sg:province":"Newport",
    "sg:tags":[
        "butcher"
    ],
    "wof:name":"The Ranch House",
    "wof:placetype":"venue"
},
  "geometry": {"coordinates":[-2.9975590706,51.5889015198],"type":"Point"}
}