{
  "type": "Feature",
  "properties": {
    "iso:country":"GB",
    "sg:address":"Pound Court, Pound Street",
    "sg:city":"Newbury",
    "sg:classifiers":[
        {
            "category":"Communications",
            "type":"Services"
        }
    ],
    "sg:phone":"+44 1635 569558",
    "sg:postcode":"RG14 6AA",
    "sg:province":"Berkshire",
    "sg:tags":[
        "telecommunication"
    ],
    "wof:name":"Vsat",
    "wof:placetype":"venue"
},
  "geometry": {"coordinates":[-1.3283389807,51.3967208862],"type":"Point"}
}