{
  "type": "Feature",
  "properties": {
    "iso:country":"GB",
    "sg:address":"6 Kingston Way",
    "sg:city":"Shoreham By Sea",
    "sg:classifiers":[
        {
            "category":"Professional",
            "subcategory":"Engineering",
            "type":"Services"
        }
    ],
    "sg:phone":"+44 1273 591464",
    "sg:postcode":"BN43 6YA",
    "sg:province":"West Sussex",
    "sg:tags":[
        "contractor",
        "electrical",
        "engineer"
    ],
    "wof:name":"D.W Electrical",
    "wof:placetype":"venue"
},
  "geometry": {"coordinates":[-0.2453940064,50.8408851624],"type":"Point"}
}