{
  "type": "Feature",
  "properties": {
    "addr:full":"Ffith Lon, Maenan Llanrwst Conwy LL26 0YH",
    "addr:postcode":"ll26 0yh",
    "addr:street":"Lon Maenan",
    "iso:country":"GB",
    "sg:address":"Ffith Lon, Maenan",
    "sg:city":"Llanrwst",
    "sg:classifiers":[
        {
            "category":"Farming",
            "subcategory":"Livestock Farm",
            "type":"Manufacturing & Wholesale Goods"
        }
    ],
    "sg:postcode":"LL26 0YH",
    "sg:province":"Conwy",
    "sg:tags":[
        "others"
    ],
    "wof:name":"D S Hughes",
    "wof:placetype":"venue"
},
  "geometry": {"coordinates":[-3.7976999283,53.1376609802],"type":"Point"}
}