{
  "type": "Feature",
  "properties": {
    "addr:full":"Unit 26 Forrest Business Park, South Access Road, Walthamstow London Greater London E17 8BA",
    "addr:housenumber":"unit 26 forrest",
    "addr:postcode":"e17 8ba",
    "addr:street":"Business Park South Access Road",
    "iso:country":"GB",
    "sg:address":"Unit 26 Forrest Business Park, South Access Road, Walthamstow",
    "sg:city":"London",
    "sg:classifiers":[
        {
            "category":"Shopping",
            "subcategory":"Stationery & Office Supplies",
            "type":"Retail Goods"
        }
    ],
    "sg:phone":"+44 20 8521 0010",
    "sg:postcode":"E17 8BA",
    "sg:province":"Greater London",
    "sg:tags":[
        "printers'"
    ],
    "wof:name":"B R M Colour Printers Ltd.",
    "wof:placetype":"venue"
},
  "geometry": {"coordinates":[-0.04108,51.571899],"type":"Point"}
}