{
  "type": "Feature",
  "properties": {
    "addr:full":"Coney Park, Harrogate Rd Leeds West Yorkshire LS19 7XS",
    "addr:postcode":"yorkshire ls19 7xs",
    "addr:street":"Harrogate Rd",
    "iso:country":"GB",
    "sg:address":"Coney Park, Harrogate Rd",
    "sg:city":"Leeds",
    "sg:classifiers":[
        {
            "category":"Parking",
            "type":"Transportation"
        }
    ],
    "sg:phone":"+44 113 250 2255",
    "sg:postcode":"LS19 7XS",
    "sg:province":"West Yorkshire",
    "sg:tags":[
        "car",
        "park"
    ],
    "wof:name":"Sentinel",
    "wof:placetype":"venue"
},
  "geometry": {"coordinates":[-1.6611440182,53.8767814636],"type":"Point"}
}