{
  "type": "Feature",
  "properties": {
    "addr:full":"Wolfe Road Norwich Norfolk NR1 4HT",
    "addr:postcode":"nr1 4ht",
    "addr:street":"Wolfe Road Norwich Norfolk",
    "iso:country":"GB",
    "sg:address":"Wolfe Road",
    "sg:city":"Norwich",
    "sg:classifiers":[
        {
            "category":"Education",
            "subcategory":"School",
            "type":"Public Place"
        }
    ],
    "sg:phone":"+44 1603 433014",
    "sg:postcode":"NR1 4HT",
    "sg:province":"Norfolk",
    "sg:tags":[
        "local",
        "authority"
    ],
    "wof:name":"Thorpe Hamlet Middle School",
    "wof:placetype":"venue"
},
  "geometry": {"coordinates":[1.3188229799,52.6329231262],"type":"Point"}
}