{
  "type": "Feature",
  "properties": {
    "addr:full":"Unit 1, Eastern Road Aldershot Hampshire GU12 4TE",
    "addr:housenumber":"unit 1",
    "addr:postcode":"gu12 4te",
    "addr:street":"Eastern Road",
    "iso:country":"GB",
    "sg:address":"Unit 1, Eastern Road",
    "sg:city":"Aldershot",
    "sg:classifiers":[
        {
            "category":"Shopping",
            "subcategory":"Crafts & Fabrics",
            "type":"Retail Goods"
        }
    ],
    "sg:phone":"+44 1252 342626",
    "sg:postcode":"GU12 4TE",
    "sg:province":"Hampshire",
    "sg:tags":[
        "material",
        "art"
    ],
    "wof:name":"Smit & Co. Ltd.",
    "wof:placetype":"venue"
},
  "geometry": {"coordinates":[-0.740037024,51.2494087219],"type":"Point"}
}