{
  "type": "Feature",
  "properties": {
    "addr:full":"9 Brook Road, Flixton, Urmston Manchester Cheshire M41 5RQ",
    "addr:housenumber":"9",
    "addr:postcode":"m41 5rq",
    "addr:street":"Brook Road",
    "iso:country":"GB",
    "sg:address":"9 Brook Road, Flixton, Urmston",
    "sg:city":"Manchester",
    "sg:classifiers":[
        {
            "category":"Building & Trades",
            "subcategory":"Construction",
            "type":"Services"
        }
    ],
    "sg:phone":"+44 161 747 9981",
    "sg:postcode":"M41 5RQ",
    "sg:province":"Cheshire",
    "sg:tags":[
        "window",
        "replacement"
    ],
    "wof:name":"Pearson's of Flixton",
    "wof:placetype":"venue"
},
  "geometry": {"coordinates":[-2.3747189045,53.4492988586],"type":"Point"}
}