{
  "type": "Feature",
  "properties": {
    "iso:country":"GB",
    "sg:address":"16 Bennett Road, Crumpsall",
    "sg:city":"Manchester",
    "sg:classifiers":[
        {
            "category":"Food & Beverages",
            "subcategory":"Liquor & Beverages",
            "type":"Retail Goods"
        },
        {
            "category":"Travel",
            "subcategory":"Hostel",
            "type":"Entertainment"
        },
        {
            "category":"Social Services",
            "subcategory":"Retirement Home",
            "type":"Services"
        }
    ],
    "sg:phone":"+44 161 795 4003",
    "sg:postcode":"M8 5DX",
    "sg:province":"Greater Manchester",
    "sg:tags":[
        "residential",
        "advice",
        "help",
        "alcohol",
        "care"
    ],
    "wof:name":"Bennett House",
    "wof:placetype":"venue"
},
  "geometry": {"coordinates":[-2.2461390495,53.5171470642],"type":"Point"}
}