{
  "type": "Feature",
  "properties": {
    "iso:country":"GB",
    "sg:address":"80 Commercial Street",
    "sg:city":"Edinburgh",
    "sg:classifiers":[
        {
            "category":"Real Estate",
            "subcategory":"Architect",
            "type":"Services"
        }
    ],
    "sg:phone":"+44 131 468 6800",
    "sg:postcode":"EH6 6LX",
    "sg:province":"City of Edinburgh",
    "wof:name":"Campbell & Arnott Ltd.",
    "wof:placetype":"venue"
},
  "geometry": {"coordinates":[-3.175125,55.977158],"type":"Point"}
}