{
  "type": "Feature",
  "properties": {
    "iso:country":"GB",
    "sg:address":"Brookhouse",
    "sg:city":"Bradford",
    "sg:classifiers":[
        {
            "category":"Manufacturing",
            "subcategory":"Rubber & Plastics",
            "type":"Manufacturing & Wholesale Goods"
        }
    ],
    "sg:phone":"+44 1274 707030",
    "sg:postcode":"BD4 8SJ",
    "sg:province":"West Yorkshire",
    "sg:tags":[
        "product"
    ],
    "wof:name":"Francis Ward Ltd.",
    "wof:placetype":"venue"
},
  "geometry": {"coordinates":[-1.717356,53.78656],"type":"Point"}
}