{
  "type": "Feature",
  "properties": {
    "iso:country":"GB",
    "sg:address":"Crewkerne Delivery Office, Blacknell Lane",
    "sg:city":"Crewkerne",
    "sg:classifiers":[
        {
            "category":"Professional",
            "type":"Services"
        },
        {
            "category":"Personal",
            "type":"Services"
        }
    ],
    "sg:phone":"+44 1460 72026",
    "sg:postcode":"TA18 7HE",
    "sg:province":"Dorset",
    "sg:tags":[
        "delivery",
        "good"
    ],
    "wof:name":"Royal Mail Group Ltd",
    "wof:placetype":"venue"
},
  "geometry": {"coordinates":[-2.7867150307,50.882194519],"type":"Point"}
}