{
  "type": "Feature",
  "properties": {
    "addr:full":"Business Village, 3-9 Broomhill Road London Greater London SW18 4JQ",
    "addr:housenumber":"3-9",
    "addr:postcode":"sw18 4jq",
    "addr:street":"Broomhill Road",
    "iso:country":"GB",
    "sg:address":"Business Village, 3-9 Broomhill Road",
    "sg:city":"London",
    "sg:classifiers":[
        {
            "category":"Communications",
            "subcategory":"Film & Video Production",
            "type":"Services"
        },
        {
            "category":"Shopping",
            "subcategory":"Computers & Home Electronics",
            "type":"Retail Goods"
        }
    ],
    "sg:phone":"+44 20 8875 0984",
    "sg:postcode":"SW18 4JQ",
    "sg:province":"Greater London",
    "sg:tags":[
        "equipment",
        "cctv",
        "mnfr"
    ],
    "wof:name":"Overview Ltd.",
    "wof:placetype":"venue"
},
  "geometry": {"coordinates":[-0.19831,51.45686],"type":"Point"}
}