{
  "type": "Feature",
  "properties": {
    "addr:full":"Unit 5 Cotswold Mews, 30 Battersea Sq Battersea Greater London SW11 3RA",
    "addr:housenumber":"unit 5;30",
    "addr:postcode":"sw11 3ra",
    "addr:street":"Cotswold;Battersea Sq",
    "iso:country":"GB",
    "sg:address":"Unit 5 Cotswold Mews, 30 Battersea Sq",
    "sg:city":"Battersea",
    "sg:classifiers":[
        {
            "category":"Personal",
            "subcategory":"Beauty Salon",
            "type":"Services"
        }
    ],
    "sg:phone":"+44 20 7228 2673",
    "sg:postcode":"SW11 3RA",
    "sg:province":"Greater London",
    "sg:tags":[
        "unisex",
        "hairdresser"
    ],
    "wof:name":"Shortcuts",
    "wof:placetype":"venue"
},
  "geometry": {"coordinates":[-0.162839,51.467464],"type":"Point"}
}