{
  "type": "Feature",
  "properties": {
    "addr:full":"21 Hough Lane Preston Lancashire PR25 2SB",
    "addr:housenumber":"21",
    "addr:postcode":"pr25 2sb",
    "addr:street":"Hough Lane",
    "iso:country":"GB",
    "sg:address":"21 Hough Lane",
    "sg:city":"Preston",
    "sg:classifiers":[
        {
            "category":"Shopping",
            "subcategory":"Florist",
            "type":"Retail Goods"
        }
    ],
    "sg:postcode":"PR25 2SB",
    "sg:province":"Lancashire",
    "wof:name":"Poppy's",
    "wof:placetype":"venue"
},
  "geometry": {"coordinates":[-2.693489,53.695347],"type":"Point"}
}