{
  "type": "Feature",
  "properties": {
    "addr:full":"Castle Square Ludlow Herefordshire SY8 1GD",
    "addr:postcode":"sy8 1gd",
    "addr:street":"Castle Square",
    "iso:country":"GB",
    "sg:address":"Castle Square",
    "sg:city":"Ludlow",
    "sg:classifiers":[
        {
            "category":"Education",
            "subcategory":"University",
            "type":"Public Place"
        }
    ],
    "sg:phone":"+44 1584 872846",
    "sg:postcode":"SY8 1GD",
    "sg:province":"Herefordshire",
    "sg:tags":[
        "higher"
    ],
    "wof:name":"Ludlow College",
    "wof:placetype":"venue"
},
  "geometry": {"coordinates":[-2.7205240726,52.3673439026],"type":"Point"}
}