{
  "type": "Feature",
  "properties": {
    "addr:full":"51 Feather Dell Hatfield Hertfordshire AL10 8DE",
    "addr:housenumber":"51",
    "addr:postcode":"al10 8de",
    "addr:street":"Feather Dell",
    "iso:country":"GB",
    "sg:address":"51 Feather Dell",
    "sg:city":"Hatfield",
    "sg:classifiers":[
        {
            "category":"Professional",
            "subcategory":"Art Services",
            "type":"Services"
        },
        {
            "category":"Building & Trades",
            "subcategory":"Construction",
            "type":"Services"
        },
        {
            "category":"Manufacturing",
            "subcategory":"Paper Products",
            "type":"Manufacturing & Wholesale Goods"
        }
    ],
    "sg:phone":"+44 1707 268136",
    "sg:postcode":"AL10 8DE",
    "sg:province":"Hertfordshire",
    "sg:tags":[
        "cardboard",
        "decorator",
        "painter"
    ],
    "wof:name":"MARK BAILEY",
    "wof:placetype":"venue"
},
  "geometry": {"coordinates":[-0.234537,51.760361],"type":"Point"}
}