{
  "type": "Feature",
  "properties": {
    "iso:country":"GB",
    "sg:address":"26b Watton Road, Ware",
    "sg:city":"Hertford",
    "sg:classifiers":[
        {
            "category":"Building & Trades",
            "subcategory":"Construction",
            "type":"Services"
        }
    ],
    "sg:postcode":"SG12 0AD",
    "sg:province":"Hertfordshire",
    "sg:tags":[
        "builder"
    ],
    "wof:name":"J C Builders",
    "wof:placetype":"venue"
},
  "geometry": {"coordinates":[-0.0374209993,51.814666748],"type":"Point"}
}