{
  "type": "Feature",
  "properties": {
    "addr:full":"4 Stamford Road, Bowden Altrincham Cheshire WA14 2JU",
    "addr:housenumber":"4",
    "addr:postcode":"wa14 2ju",
    "addr:street":"Stamford Road",
    "iso:country":"GB",
    "sg:address":"4 Stamford Road, Bowden",
    "sg:city":"Altrincham",
    "sg:classifiers":[
        {
            "category":"Shopping",
            "subcategory":"Department Store",
            "type":"Retail Goods"
        }
    ],
    "sg:postcode":"WA14 2JU",
    "sg:province":"Cheshire",
    "wof:name":"Bowdon Post Office",
    "wof:placetype":"venue"
},
  "geometry": {"coordinates":[-2.3621270657,53.3778076172],"type":"Point"}
}