{
  "type": "Feature",
  "properties": {
    "addr:full":"Honey Pot Lane, Colsterworth Grantham Leicestershire NG33 5LT",
    "addr:postcode":"ng33 5lt",
    "addr:street":"Pot Lane",
    "iso:country":"GB",
    "sg:address":"Honey Pot Lane, Colsterworth",
    "sg:city":"Grantham",
    "sg:classifiers":[
        {
            "category":"Retail",
            "subcategory":"Storage",
            "type":"Services"
        }
    ],
    "sg:phone":"+44 1476 860983",
    "sg:postcode":"NG33 5LT",
    "sg:province":"Leicestershire",
    "sg:tags":[
        "household",
        "removal"
    ],
    "wof:name":"C E P Potatoes Ltd.",
    "wof:placetype":"venue"
},
  "geometry": {"coordinates":[-0.6105340123,52.7864761353],"type":"Point"}
}