{
  "type": "Feature",
  "properties": {
    "addr:full":"16 Nicholas St Manchester Greater Manchester M1 4EJ",
    "addr:housenumber":"16",
    "addr:postcode":"m1 4ej",
    "addr:street":"Nicholas St",
    "iso:country":"GB",
    "sg:address":"16 Nicholas St",
    "sg:city":"Manchester",
    "sg:classifiers":[
        {
            "category":"Health Services",
            "subcategory":"Health Practitioner",
            "type":"Services"
        }
    ],
    "sg:phone":"+44 161 228 2280",
    "sg:postcode":"M1 4EJ",
    "sg:province":"Greater Manchester",
    "sg:tags":[
        "acupuncture"
    ],
    "wof:name":"Chinese Direct Line",
    "wof:placetype":"venue"
},
  "geometry": {"coordinates":[-2.240666,53.478638],"type":"Point"}
}