{
  "type": "Feature",
  "properties": {
    "iso:country":"GB",
    "sg:address":"Tunwells Clo",
    "sg:city":"Cambridge",
    "sg:classifiers":[
        {
            "category":"Government",
            "subcategory":"Police Station",
            "type":"Public Place"
        }
    ],
    "sg:phone":"+44 1223 842211",
    "sg:postcode":"CB2 5LL",
    "sg:province":"Cambridgeshire",
    "sg:tags":[
        "support"
    ],
    "wof:name":"Shelford Police Station",
    "wof:placetype":"venue"
},
  "geometry": {"coordinates":[0.1361300051,52.1499900818],"type":"Point"}
}