{
  "type": "Feature",
  "properties": {
    "iso:country":"GB",
    "sg:address":"Sandy Lane, Chapel Brampton",
    "sg:city":"Northampton",
    "sg:classifiers":[
        {
            "category":"Sports & Exercise",
            "subcategory":"Golf",
            "type":"Entertainment"
        }
    ],
    "sg:phone":"+44 1604 843939",
    "sg:postcode":"NN6 8AX",
    "sg:province":"Northamptonshire",
    "sg:tags":[
        "club",
        "course"
    ],
    "wof:name":"Brampton Heath Golf Centre",
    "wof:placetype":"venue"
},
  "geometry": {"coordinates":[-0.930693984,52.2816123962],"type":"Point"}
}