{
  "type": "Feature",
  "properties": {
    "iso:country":"GB",
    "sg:address":"120-122 Canal St",
    "sg:city":"Nottingham",
    "sg:classifiers":[
        {
            "category":"Shopping",
            "subcategory":"Computers & Home Electronics",
            "type":"Retail Goods"
        }
    ],
    "sg:phone":"+44 115 958 0407",
    "sg:postcode":"NG1 7JA",
    "sg:province":"Nottinghamshire",
    "sg:tags":[
        "electrical"
    ],
    "wof:name":"Reliance Engineering",
    "wof:placetype":"venue"
},
  "geometry": {"coordinates":[-1.144368,52.949062],"type":"Point"}
}