{
  "type": "Feature",
  "properties": {
    "iso:country":"GB",
    "sg:address":"12 Summerfield Road, Woodthorpe",
    "sg:city":"York",
    "sg:classifiers":[
        {
            "category":"Retail",
            "subcategory":"Repair Shop",
            "type":"Services"
        }
    ],
    "sg:postcode":"YO24 2RU",
    "sg:province":"North Yorkshire",
    "sg:tags":[
        "upholsterer"
    ],
    "wof:name":"W Liddle",
    "wof:placetype":"venue"
},
  "geometry": {"coordinates":[-1.1273390055,53.9375267029],"type":"Point"}
}