{
  "type": "Feature",
  "properties": {
    "iso:country":"GB",
    "sg:address":"340 East Lancashire Road",
    "sg:city":"Liverpool",
    "sg:classifiers":[
        {
            "category":"Cinema",
            "subcategory":"Movie Theater",
            "type":"Entertainment"
        }
    ],
    "sg:phone":"+44 151 549 2044",
    "sg:postcode":"L11 9YJ",
    "sg:province":"Merseyside",
    "wof:name":"Showcase Cinema",
    "wof:placetype":"venue"
},
  "geometry": {"coordinates":[-2.978481,53.409775],"type":"Point"}
}