{
  "type": "Feature",
  "properties": {
    "addr:full":"28 Devonshire Street Keighley West Yorkshire BD21 2AU",
    "addr:housenumber":"28",
    "addr:postcode":"bd21 2au",
    "addr:street":"Devonshire Street",
    "iso:country":"GB",
    "sg:address":"28 Devonshire Street",
    "sg:city":"Keighley",
    "sg:classifiers":[
        {
            "category":"Professional",
            "subcategory":"Accounting & Tax Preparation",
            "type":"Services"
        }
    ],
    "sg:phone":"+44 1535 681427",
    "sg:postcode":"BD21 2AU",
    "sg:province":"West Yorkshire",
    "sg:tags":[
        "accountant",
        "activity"
    ],
    "wof:name":"Glenn J Wrighton & Co.",
    "wof:placetype":"venue"
},
  "geometry": {"coordinates":[-1.911697,53.867661],"type":"Point"}
}