{
  "type": "Feature",
  "properties": {
    "iso:country":"GB",
    "sg:address":"Sealand Road",
    "sg:city":"Chester",
    "sg:classifiers":[
        {
            "category":"Home & Garden",
            "subcategory":"Home Furnishings",
            "type":"Retail Goods"
        }
    ],
    "sg:phone":"+44 1244 382028",
    "sg:postcode":"CH1 4QQ",
    "sg:province":"Cheshire",
    "sg:tags":[
        "wall",
        "wallpaper",
        "covering"
    ],
    "wof:name":"Homestyle by Fads",
    "wof:placetype":"venue"
},
  "geometry": {"coordinates":[-2.929534,53.195629],"type":"Point"}
}