{
  "type": "Feature",
  "properties": {
    "addr:full":"Victoria Rd Glasgow Glasgow City G42 7AD",
    "addr:postcode":"g42 7ad",
    "addr:street":"Victoria Rd",
    "iso:country":"GB",
    "sg:address":"Victoria Rd",
    "sg:city":"Glasgow",
    "sg:classifiers":[
        {
            "category":"Education",
            "subcategory":"Dance Studio",
            "type":"Public Place"
        }
    ],
    "sg:phone":"+44 141 639 8300",
    "sg:postcode":"G42 7AD",
    "sg:province":"Glasgow City",
    "sg:tags":[
        "school",
        "dancing"
    ],
    "wof:name":"D School Of Latin American & Ballroom Dancing",
    "wof:placetype":"venue"
},
  "geometry": {"coordinates":[-4.263719,55.839725],"type":"Point"}
}