{
  "type": "Feature",
  "properties": {
    "iso:country":"GB",
    "sg:address":"Care Of Austin Rover",
    "sg:city":"Oxford",
    "sg:classifiers":[
        {
            "category":"Professional",
            "subcategory":"Engineering",
            "type":"Services"
        }
    ],
    "sg:postcode":"OX4 6NL",
    "sg:province":"Oxfordshire",
    "sg:tags":[
        "contractor",
        "electrical",
        "engineer"
    ],
    "wof:name":"I D S Electrical",
    "wof:placetype":"venue"
},
  "geometry": {"coordinates":[-1.19793,51.730061],"type":"Point"}
}