{
  "type": "Feature",
  "properties": {
    "iso:country":"GB",
    "sg:address":"2 Main St",
    "sg:city":"Falkirk",
    "sg:classifiers":[
        {
            "category":"Home & Garden",
            "subcategory":"Furniture",
            "type":"Retail Goods"
        }
    ],
    "sg:phone":"+44 1324 611660",
    "sg:postcode":"FK2 7PB",
    "sg:province":"Falkirk",
    "wof:name":"Now Home Furnishings",
    "wof:placetype":"venue"
},
  "geometry": {"coordinates":[-3.787569046,56.012348175],"type":"Point"}
}