{
  "type": "Feature",
  "properties": {
    "addr:full":"15 Royal Avenue Scarborough North Yorkshire YO11 2LS",
    "addr:housenumber":"15",
    "addr:postcode":"yo11 2ls",
    "addr:street":"Royal Avenue",
    "iso:country":"GB",
    "sg:address":"15 Royal Avenue",
    "sg:city":"Scarborough",
    "sg:classifiers":[
        {
            "category":"Travel",
            "subcategory":"Hotels & Motels",
            "type":"Entertainment"
        }
    ],
    "sg:postcode":"YO11 2LS",
    "sg:province":"North Yorkshire",
    "sg:tags":[
        "self",
        "catering"
    ],
    "wof:name":"Chevron Holiday Flats",
    "wof:placetype":"venue"
},
  "geometry": {"coordinates":[-0.4042260051,54.2741355896],"type":"Point"}
}