{
  "type": "Feature",
  "properties": {
    "addr:full":"57 Sittingbourne Ave Enfield Greater London EN1 2DB",
    "addr:housenumber":"57",
    "addr:postcode":"en1 2db",
    "addr:street":"Sittingbourne Ave",
    "iso:country":"GB",
    "sg:address":"57 Sittingbourne Ave",
    "sg:city":"Enfield",
    "sg:classifiers":[
        {
            "category":"Building & Trades",
            "subcategory":"Plumbing",
            "type":"Services"
        }
    ],
    "sg:postcode":"EN1 2DB",
    "sg:province":"Greater London",
    "sg:tags":[
        "heating"
    ],
    "wof:name":"Jobber,Jim,",
    "wof:placetype":"venue"
},
  "geometry": {"coordinates":[-0.080167,51.641041],"type":"Point"}
}