{
  "type": "Feature",
  "properties": {
    "addr:full":"7 Ascot Court, White Horse Business Park Trowbridge Wiltshire BA14 0XA",
    "addr:housenumber":"7",
    "addr:postcode":"ba14 0xa",
    "addr:street":"Ascot Court;Business Park",
    "iso:country":"GB",
    "sg:address":"7 Ascot Court, White Horse Business Park",
    "sg:city":"Trowbridge",
    "sg:classifiers":[
        {
            "category":"Professional",
            "subcategory":"Employment Agencies",
            "type":"Services"
        }
    ],
    "sg:phone":"+44 1225 716000",
    "sg:postcode":"BA14 0XA",
    "sg:province":"Wiltshire",
    "sg:tags":[
        "career",
        "guidance"
    ],
    "wof:name":"Lifetime Careers Wiltshire Ltd.",
    "wof:placetype":"venue"
},
  "geometry": {"coordinates":[-2.1983690262,51.3008651733],"type":"Point"}
}