{
  "type": "Feature",
  "properties": {
    "addr:full":"Unit 6 Brickyard Rd,, Empire Pk, Aldridge, Walsall Staffordshire WS9 8SR",
    "addr:housenumber":"unit 6",
    "addr:postcode":"ws9 8sr",
    "addr:street":"Brickyard Rd",
    "iso:country":"GB",
    "sg:address":"Unit 6 Brickyard Rd,, Empire Pk, Aldridge,",
    "sg:city":"Walsall",
    "sg:classifiers":[
        {
            "category":"Manufacturing",
            "subcategory":"Building Materials",
            "type":"Manufacturing & Wholesale Goods"
        }
    ],
    "sg:phone":"+44 1922 453341",
    "sg:postcode":"WS9 8SR",
    "sg:province":"Staffordshire",
    "sg:tags":[
        "merchant",
        "builder"
    ],
    "wof:name":"Shepherds Hardware Ltd",
    "wof:placetype":"venue"
},
  "geometry": {"coordinates":[-1.927602,52.610226],"type":"Point"}
}