{
  "type": "Feature",
  "properties": {
    "iso:country":"GB",
    "sg:address":"37 Lodge Road, Orrell",
    "sg:city":"Wigan",
    "sg:classifiers":[
        {
            "category":"Shopping",
            "subcategory":"News",
            "type":"Retail Goods"
        }
    ],
    "sg:phone":"+44 1695 633133",
    "sg:postcode":"WN5 7AT",
    "sg:province":"Lancashire",
    "sg:tags":[
        "newsagent"
    ],
    "wof:name":"Collier's Newsagents",
    "wof:placetype":"venue"
},
  "geometry": {"coordinates":[-2.70892,53.528202],"type":"Point"}
}