{
  "type": "Feature",
  "properties": {
    "addr:full":"Sparfield, Regil La, Winford Bristol Somerset BS40 8AX",
    "addr:postcode":"bs40 8ax",
    "iso:country":"GB",
    "sg:address":"Sparfield, Regil La, Winford",
    "sg:city":"Bristol",
    "sg:classifiers":[
        {
            "category":"Professional",
            "subcategory":"Engineering",
            "type":"Services"
        }
    ],
    "sg:phone":"+44 1275 472279",
    "sg:postcode":"BS40 8AX",
    "sg:province":"Somerset",
    "wof:name":"Patch,M J,",
    "wof:placetype":"venue"
},
  "geometry": {"coordinates":[-2.6620140076,51.3826217651],"type":"Point"}
}