{
  "type": "Feature",
  "properties": {
    "iso:country":"GB",
    "sg:address":"20-28 London Road",
    "sg:city":"Barking",
    "sg:classifiers":[
        {
            "category":"Bars & Pubs",
            "subcategory":"Nightclub",
            "type":"Food & Drink"
        }
    ],
    "sg:phone":"+44 20 8594 3051",
    "sg:postcode":"IG11 8AJ",
    "sg:province":"Essex",
    "sg:tags":[
        "club",
        "night"
    ],
    "wof:name":"Legends Restaurant & Night Club",
    "wof:placetype":"venue"
},
  "geometry": {"coordinates":[0.0783170015,51.5382385254],"type":"Point"}
}