{
  "type": "Feature",
  "properties": {
    "iso:country":"GB",
    "sg:address":"Runavey Farm, Glenshee",
    "sg:city":"Blairgowrie",
    "sg:classifiers":[
        {
            "category":"Farming",
            "subcategory":"Livestock Farm",
            "type":"Manufacturing & Wholesale Goods"
        }
    ],
    "sg:postcode":"PH10 7QD",
    "sg:province":"Perth and Kinross",
    "sg:tags":[
        "others"
    ],
    "wof:name":"J & A Lindsay",
    "wof:placetype":"venue"
},
  "geometry": {"coordinates":[-3.460931,56.814148],"type":"Point"}
}