{
  "type": "Feature",
  "properties": {
    "addr:full":"Beardwood Bank, Preston New Road Blackburn Lancashire BB2 7AA",
    "addr:postcode":"bb2 7aa",
    "addr:street":"Preston New Road",
    "iso:country":"GB",
    "sg:address":"Beardwood Bank, Preston New Road",
    "sg:city":"Blackburn",
    "sg:classifiers":[
        {
            "category":"Education",
            "subcategory":"School",
            "type":"Public Place"
        }
    ],
    "sg:phone":"+44 1254 667611",
    "sg:postcode":"BB2 7AA",
    "sg:province":"Lancashire",
    "sg:tags":[
        "independent",
        "preparatory"
    ],
    "wof:name":"Westholme Middle School",
    "wof:placetype":"venue"
},
  "geometry": {"coordinates":[-2.5125610828,53.762172699],"type":"Point"}
}