{
  "type": "Feature",
  "properties": {
    "iso:country":"GB",
    "sg:address":"13 Depot Road",
    "sg:city":"Newmarket",
    "sg:classifiers":[
        {
            "category":"Manufacturing",
            "subcategory":"Metals",
            "type":"Manufacturing & Wholesale Goods"
        },
        {
            "category":"Professional",
            "subcategory":"Engineering",
            "type":"Services"
        }
    ],
    "sg:phone":"+44 1638 664596",
    "sg:postcode":"CB8 0AL",
    "sg:province":"Cambridgeshire",
    "sg:tags":[
        "steel",
        "fabricator"
    ],
    "wof:name":"Anglia Fabrication & Design Ltd.",
    "wof:placetype":"venue"
},
  "geometry": {"coordinates":[0.3942550123,52.2554321289],"type":"Point"}
}