{
  "type": "Feature",
  "properties": {
    "addr:full":"31 Avern Road West Molesey Greater London KT8 2JB",
    "addr:housenumber":"31",
    "addr:postcode":"kt8 2jb",
    "addr:street":"Avern Road",
    "iso:country":"GB",
    "sg:address":"31 Avern Road",
    "sg:city":"West Molesey",
    "sg:classifiers":[
        {
            "category":"Manufacturing",
            "subcategory":"Petroleum Products",
            "type":"Manufacturing & Wholesale Goods"
        }
    ],
    "sg:phone":"+44 20 8941 0075",
    "sg:postcode":"KT8 2JB",
    "sg:province":"Greater London",
    "sg:tags":[
        "double",
        "glazing"
    ],
    "wof:name":"C & G Services",
    "wof:placetype":"venue"
},
  "geometry": {"coordinates":[-0.3639830053,51.4006996155],"type":"Point"}
}