{
  "type": "Feature",
  "properties": {
    "addr:full":"Higher Heathfield, East Allington Totnes Devon TQ9 7RN",
    "addr:postcode":"tq9 7rn",
    "addr:street":"East",
    "iso:country":"GB",
    "sg:address":"Higher Heathfield, East Allington",
    "sg:city":"Totnes",
    "sg:classifiers":[
        {
            "category":"Farming",
            "subcategory":"Dairy Farm",
            "type":"Manufacturing & Wholesale Goods"
        }
    ],
    "sg:phone":"+44 1548 521251",
    "sg:postcode":"TQ9 7RN",
    "sg:province":"Devon",
    "wof:name":"B R & L M Hallett",
    "wof:placetype":"venue"
},
  "geometry": {"coordinates":[-3.729589,50.32452],"type":"Point"}
}