{
  "type": "Feature",
  "properties": {
    "iso:country":"GB",
    "sg:address":"Main Street",
    "sg:city":"York",
    "sg:classifiers":[
        {
            "category":"Home & Garden",
            "subcategory":"Home Furnishings",
            "type":"Retail Goods"
        }
    ],
    "sg:phone":"+44 1757 248777",
    "sg:postcode":"YO4 6QE",
    "sg:province":"East Riding of Yorkshire",
    "sg:tags":[
        "mantelpiece",
        "fireplace"
    ],
    "wof:name":"J P David's (Heat'it)",
    "wof:placetype":"venue"
},
  "geometry": {"coordinates":[-0.9310340285,53.839515686],"type":"Point"}
}