{
  "type": "Feature",
  "properties": {
    "iso:country":"GB",
    "sg:address":"Portview Rd",
    "sg:city":"Bristol",
    "sg:classifiers":[
        {
            "category":"Retail",
            "subcategory":"Auto Repair",
            "type":"Services"
        }
    ],
    "sg:postcode":"BS11 9LB",
    "sg:province":"City of Bristol",
    "sg:tags":[
        "modification",
        "garage"
    ],
    "wof:name":"Portview Motorcare",
    "wof:placetype":"venue"
},
  "geometry": {"coordinates":[-2.698684,51.499699],"type":"Point"}
}