{
  "type": "Feature",
  "properties": {
    "iso:country":"GB",
    "sg:address":"76 Fellows Rd, Isle Of Wight",
    "sg:city":"Cowes",
    "sg:classifiers":[
        {
            "category":"Building & Trades",
            "subcategory":"Construction",
            "type":"Services"
        }
    ],
    "sg:phone":"+44 1983 291668",
    "sg:postcode":"PO31 7JW",
    "sg:province":"Isle of Wight",
    "sg:tags":[
        "roofing"
    ],
    "wof:name":"Barnes Quality Roofing Services",
    "wof:placetype":"venue"
},
  "geometry": {"coordinates":[-1.3030040264,50.7563362122],"type":"Point"}
}