{
  "type": "Feature",
  "properties": {
    "addr:full":"Market Street Bromsgrove Worcestershire B61 8DA",
    "addr:postcode":"b61 8da",
    "addr:street":"Market Street",
    "iso:country":"GB",
    "sg:address":"Market Street",
    "sg:city":"Bromsgrove",
    "sg:classifiers":[
        {
            "category":"Shopping",
            "subcategory":"Stationery & Office Supplies",
            "type":"Retail Goods"
        }
    ],
    "sg:phone":"+44 1527 872582",
    "sg:postcode":"B61 8DA",
    "sg:province":"Worcestershire",
    "wof:name":"Central Office Services",
    "wof:placetype":"venue"
},
  "geometry": {"coordinates":[-2.059344,52.336842],"type":"Point"}
}