{
  "type": "Feature",
  "properties": {
    "iso:country":"GB",
    "sg:address":"13 Taylor Street",
    "sg:city":"Consett",
    "sg:classifiers":[
        {
            "category":"Home & Garden",
            "subcategory":"Household Appliances",
            "type":"Retail Goods"
        }
    ],
    "sg:phone":"+44 1207 502863",
    "sg:postcode":"DH8 5RQ",
    "sg:province":"Durham",
    "sg:tags":[
        "electrical",
        "domestic"
    ],
    "wof:name":"L Furness",
    "wof:placetype":"venue"
},
  "geometry": {"coordinates":[-1.8307390213,54.8509178162],"type":"Point"}
}