{
  "type": "Feature",
  "properties": {
    "iso:country":"GB",
    "sg:address":"75 Murdock Road",
    "sg:city":"Bedford",
    "sg:classifiers":[
        {
            "category":"Building & Trades",
            "subcategory":"Cleaning & Sanitation",
            "type":"Services"
        }
    ],
    "sg:phone":"+44 1480 403404",
    "sg:postcode":"MK41 7PL",
    "sg:province":"Bedfordshire",
    "sg:tags":[
        "commercial"
    ],
    "wof:name":"We Are Cleaning (Home Counties) Ltd.",
    "wof:placetype":"venue"
},
  "geometry": {"coordinates":[-0.47374,52.154465],"type":"Point"}
}