{
  "type": "Feature",
  "properties": {
    "addr:full":"64 Market Place Warwick Warwickshire CV34 4SD",
    "addr:housenumber":"64",
    "addr:postcode":"cv34 4sd",
    "addr:street":"Market Place",
    "iso:country":"GB",
    "sg:address":"64 Market Place",
    "sg:city":"Warwick",
    "sg:classifiers":[
        {
            "category":"Manufacturing",
            "subcategory":"Metals",
            "type":"Manufacturing & Wholesale Goods"
        }
    ],
    "sg:phone":"+44 1926 492470",
    "sg:postcode":"CV34 4SD",
    "sg:province":"Warwickshire",
    "sg:tags":[
        "merchant"
    ],
    "wof:name":"Period House Shop",
    "wof:placetype":"venue"
},
  "geometry": {"coordinates":[-1.5903329849,52.2815055847],"type":"Point"}
}