{
  "type": "Feature",
  "properties": {
    "iso:country":"GB",
    "sg:address":"Dukinfield Road",
    "sg:city":"Hyde",
    "sg:classifiers":[
        {
            "category":"Retail",
            "subcategory":"Auto Repair",
            "type":"Services"
        }
    ],
    "sg:phone":"+44 161 366 1379",
    "sg:postcode":"SK14 2BQ",
    "sg:province":"Cheshire",
    "sg:tags":[
        "car",
        "specialist",
        "customizing"
    ],
    "wof:name":"Supatread",
    "wof:placetype":"venue"
},
  "geometry": {"coordinates":[-2.084458,53.454479],"type":"Point"}
}