{
  "type": "Feature",
  "properties": {
    "iso:country":"GB",
    "sg:address":"6 Bruce Grove, Tottenham",
    "sg:city":"London",
    "sg:classifiers":[
        {
            "category":"Shopping",
            "subcategory":"News",
            "type":"Retail Goods"
        }
    ],
    "sg:phone":"+44 20 8801 3480",
    "sg:postcode":"N17 6RA",
    "sg:province":"Greater London",
    "sg:tags":[
        "newsagent"
    ],
    "wof:name":"Nelhart Ltd.",
    "wof:placetype":"venue"
},
  "geometry": {"coordinates":[-0.070196,51.594261],"type":"Point"}
}