{
  "type": "Feature",
  "properties": {
    "addr:full":"78 Park Road, Stretford Manchester Cheshire M32 8FD",
    "addr:housenumber":"78",
    "addr:postcode":"m32 8fd",
    "addr:street":"Park Road",
    "iso:country":"GB",
    "sg:address":"78 Park Road, Stretford",
    "sg:city":"Manchester",
    "sg:classifiers":[
        {
            "category":"Food & Beverages",
            "subcategory":"Groceries & Convenience Stores",
            "type":"Retail Goods"
        }
    ],
    "sg:phone":"+44 161 865 2166",
    "sg:postcode":"M32 8FD",
    "sg:province":"Cheshire",
    "wof:name":"L M & D Jones",
    "wof:placetype":"venue"
},
  "geometry": {"coordinates":[-2.3148500919,53.4510536194],"type":"Point"}
}