{
  "type": "Feature",
  "properties": {
    "iso:country":"GB",
    "sg:address":"4 Little Croft",
    "sg:city":"Yateley",
    "sg:classifiers":[
        {
            "category":"Professional",
            "subcategory":"Lawyer & Legal Services",
            "type":"Services"
        }
    ],
    "sg:phone":"+44 1252 875892",
    "sg:postcode":"GU46 6BU",
    "sg:province":"Hampshire",
    "wof:name":"CPJ Williams Legal Adviser",
    "wof:placetype":"venue"
},
  "geometry": {"coordinates":[-0.8271089792,51.3332710266],"type":"Point"}
}