{
  "type": "Feature",
  "properties": {
    "iso:country":"GB",
    "sg:address":"Children Only, Hoddesdon Health Centre, High St",
    "sg:city":"Hoddesdon",
    "sg:classifiers":[
        {
            "category":"Health Services",
            "subcategory":"Clinic",
            "type":"Services"
        }
    ],
    "sg:phone":"+44 1992 444125",
    "sg:postcode":"EN11 8BE",
    "sg:province":"Essex",
    "sg:tags":[
        "nh"
    ],
    "wof:name":"Hoddesdon Community Dental Clinic",
    "wof:placetype":"venue"
},
  "geometry": {"coordinates":[-0.013255,51.767841],"type":"Point"}
}