{
  "type": "Feature",
  "properties": {
    "iso:country":"GB",
    "sg:address":"140 Park Road, Spixworth",
    "sg:city":"Norwich",
    "sg:classifiers":[
        {
            "category":"Professional",
            "subcategory":"Engineering",
            "type":"Services"
        },
        {
            "category":"Building & Trades",
            "subcategory":"Electrical",
            "type":"Services"
        }
    ],
    "sg:phone":"+44 1603 898512",
    "sg:postcode":"NR10 3NP",
    "sg:province":"Norfolk",
    "sg:tags":[
        "engineer",
        "electrician",
        "contractor"
    ],
    "wof:name":"H A Lambert",
    "wof:placetype":"venue"
},
  "geometry": {"coordinates":[1.325973,52.685425],"type":"Point"}
}