{
  "type": "Feature",
  "properties": {
    "iso:country":"GB",
    "sg:address":"100 Gloucester Rd",
    "sg:city":"Exeter",
    "sg:classifiers":[
        {
            "category":"Building & Trades",
            "subcategory":"Construction",
            "type":"Services"
        }
    ],
    "sg:postcode":"EX4 2ED",
    "sg:province":"Devon",
    "sg:tags":[
        "builder"
    ],
    "wof:name":"A J White",
    "wof:placetype":"venue"
},
  "geometry": {"coordinates":[-3.555501,50.726788],"type":"Point"}
}