{
  "type": "Feature",
  "properties": {
    "iso:country":"GB",
    "sg:address":"10 Lakedale Road, Plumstead",
    "sg:city":"London",
    "sg:classifiers":[
        {
            "category":"Retail",
            "subcategory":"Repair Shop",
            "type":"Services"
        }
    ],
    "sg:postcode":"SE18 1PP",
    "sg:province":"Greater London",
    "sg:tags":[
        "radio",
        "television",
        "video"
    ],
    "wof:name":"T V Marden",
    "wof:placetype":"venue"
},
  "geometry": {"coordinates":[0.0908640027,51.4871673584],"type":"Point"}
}