{
  "type": "Feature",
  "properties": {
    "addr:full":"Hillmarton Garage, Hilmarton Calne Wiltshire SN11 8SD",
    "addr:postcode":"sn11 8sd",
    "iso:country":"GB",
    "sg:address":"Hillmarton Garage, Hilmarton",
    "sg:city":"Calne",
    "sg:classifiers":[
        {
            "category":"Autos & Motor Vehicles",
            "subcategory":"Automobile Sales",
            "type":"Retail Goods"
        }
    ],
    "sg:phone":"+44 1249 760552",
    "sg:postcode":"SN11 8SD",
    "sg:province":"Wiltshire",
    "sg:tags":[
        "car"
    ],
    "wof:name":"Saint Cars",
    "wof:placetype":"venue"
},
  "geometry": {"coordinates":[-1.9733769894,51.4774475098],"type":"Point"}
}