{
  "type": "Feature",
  "properties": {
    "addr:full":"8 Alpha Road, Hillingdon Uxbridge Greater London UB10 0QP",
    "addr:housenumber":"8",
    "addr:postcode":"ub10 0qp",
    "addr:street":"Alpha Road",
    "iso:country":"GB",
    "sg:address":"8 Alpha Road, Hillingdon",
    "sg:city":"Uxbridge",
    "sg:classifiers":[
        {
            "category":"Communications",
            "type":"Services"
        }
    ],
    "sg:postcode":"UB10 0QP",
    "sg:province":"Greater London",
    "sg:tags":[
        "data",
        "network"
    ],
    "wof:name":"Ayssis Data Systems Ltd",
    "wof:placetype":"venue"
},
  "geometry": {"coordinates":[-0.4443680048,51.5301856995],"type":"Point"}
}