{
  "type": "Feature",
  "properties": {
    "iso:country":"GB",
    "sg:address":"48-50 Ashton Road, Droylsden",
    "sg:city":"Manchester",
    "sg:classifiers":[
        {
            "category":"Shopping",
            "subcategory":"Optician",
            "type":"Retail Goods"
        },
        {
            "category":"Health Services",
            "subcategory":"Optometrist",
            "type":"Services"
        },
        {
            "category":"Health Services",
            "subcategory":"Doctor",
            "type":"Services"
        }
    ],
    "sg:phone":"+44 161 370 2037",
    "sg:postcode":"M43 7BP",
    "sg:province":"Greater Manchester",
    "sg:tags":[
        "ophthalmic"
    ],
    "wof:name":"C H WAS & SON",
    "wof:placetype":"venue"
},
  "geometry": {"coordinates":[-2.1431438923,53.4791984558],"type":"Point"}
}