{
  "type": "Feature",
  "properties": {
    "iso:country":"GB",
    "sg:address":"Boghead Farm, Greenhill",
    "sg:city":"Lockerbie",
    "sg:classifiers":[
        {
            "category":"Shopping",
            "subcategory":"Party Supplies",
            "type":"Retail Goods"
        }
    ],
    "sg:phone":"+44 1387 811334",
    "sg:postcode":"DG11 1JB",
    "sg:province":"Dumfries and Galloway",
    "sg:tags":[
        "inflatables",
        "bouncy",
        "castle"
    ],
    "wof:name":"Happy Days",
    "wof:placetype":"venue"
},
  "geometry": {"coordinates":[-3.4192790985,55.0973739624],"type":"Point"}
}