{
  "type": "Feature",
  "properties": {
    "iso:country":"GB",
    "sg:address":"45 Lord St",
    "sg:city":"Colne",
    "sg:classifiers":[
        {
            "category":"Shopping",
            "subcategory":"Department Store",
            "type":"Retail Goods"
        }
    ],
    "sg:phone":"+44 1282 869785",
    "sg:postcode":"BB8 9AR",
    "sg:province":"Lancashire",
    "wof:name":"Lordstreet Larder",
    "wof:placetype":"venue"
},
  "geometry": {"coordinates":[-2.1788840294,53.8570022583],"type":"Point"}
}