{
  "type": "Feature",
  "properties": {
    "addr:full":"Pilley Street Lymington Hampshire SO41 5QP",
    "addr:postcode":"so41 5qp",
    "addr:street":"Pilley Street",
    "iso:country":"GB",
    "sg:address":"Pilley Street",
    "sg:city":"Lymington",
    "sg:classifiers":[
        {
            "category":"Shopping",
            "subcategory":"Department Store",
            "type":"Retail Goods"
        }
    ],
    "sg:phone":"+44 1590 673380",
    "sg:postcode":"SO41 5QP",
    "sg:province":"Hampshire",
    "wof:name":"Pilley Stores & Post Office",
    "wof:placetype":"venue"
},
  "geometry": {"coordinates":[-1.5347690582,50.7828788757],"type":"Point"}
}