{
  "type": "Feature",
  "properties": {
    "iso:country":"GB",
    "sg:address":"Lennox Road, Bletchley",
    "sg:city":"Milton Keynes",
    "sg:classifiers":[
        {
            "category":"Education",
            "subcategory":"Music School",
            "type":"Public Place"
        }
    ],
    "sg:phone":"+44 1908 377040",
    "sg:postcode":"MK2 2HH",
    "sg:province":"Buckinghamshire",
    "sg:tags":[
        "conservatory"
    ],
    "wof:name":"Ian Mills Ltd.",
    "wof:placetype":"venue"
},
  "geometry": {"coordinates":[-0.7270169854,51.9948005676],"type":"Point"}
}