{
  "type": "Feature",
  "properties": {
    "addr:full":"Suite 33, 10 Regent St Barnsley South Yorkshire S70 2EJ",
    "addr:housenumber":"10",
    "addr:postcode":"s70 2ej",
    "addr:street":"Suite 33;Regent St;Yorkshire",
    "iso:country":"GB",
    "sg:address":"Suite 33, 10 Regent St",
    "sg:city":"Barnsley",
    "sg:classifiers":[
        {
            "category":"Shopping",
            "subcategory":"Beauty & Cosmetics",
            "type":"Retail Goods"
        }
    ],
    "sg:postcode":"S70 2EJ",
    "sg:province":"South Yorkshire",
    "sg:tags":[
        "wig",
        "hairpiece"
    ],
    "wof:name":"Roman Hair",
    "wof:placetype":"venue"
},
  "geometry": {"coordinates":[-1.481125,53.554493],"type":"Point"}
}