{
  "type": "Feature",
  "properties": {
    "addr:full":"16 Egbert Road Winchester Hampshire SO23 7EB",
    "addr:housenumber":"16",
    "addr:postcode":"so23 7eb",
    "addr:street":"Egbert Road",
    "iso:country":"GB",
    "sg:address":"16 Egbert Road",
    "sg:city":"Winchester",
    "sg:classifiers":[
        {
            "category":"Government",
            "subcategory":"Post Office",
            "type":"Public Place"
        }
    ],
    "sg:postcode":"SO23 7EB",
    "sg:province":"Hampshire",
    "wof:name":"Hyde Post Office & Stores",
    "wof:placetype":"venue"
},
  "geometry": {"coordinates":[-1.3138970137,51.0700836182],"type":"Point"}
}