{
  "type": "Feature",
  "properties": {
    "addr:full":"The Bungalow, Birchall Lane, Cole Grn Hertford Hertfordshire SG14 2NR",
    "addr:postcode":"sg14 2nr",
    "addr:street":"Birchall Lane Cole Grn Hertford",
    "iso:country":"GB",
    "sg:address":"The Bungalow, Birchall Lane, Cole Grn",
    "sg:city":"Hertford",
    "sg:classifiers":[
        {
            "category":"Building & Trades",
            "subcategory":"Construction",
            "type":"Services"
        }
    ],
    "sg:phone":"+44 1707 393644",
    "sg:postcode":"SG14 2NR",
    "sg:province":"Hertfordshire",
    "sg:tags":[
        "builder"
    ],
    "wof:name":"M J Maguire Ltd.",
    "wof:placetype":"venue"
},
  "geometry": {"coordinates":[-0.082699,51.796341],"type":"Point"}
}