{
  "type": "Feature",
  "properties": {
    "iso:country":"GB",
    "sg:address":"Unit 5g Atlas Business Centre, Oxgate La",
    "sg:city":"London",
    "sg:classifiers":[
        {
            "category":"Manufacturing",
            "subcategory":"Petroleum Products",
            "type":"Manufacturing & Wholesale Goods"
        }
    ],
    "sg:postcode":"NW2 7HJ",
    "sg:province":"Greater London",
    "sg:tags":[
        "double",
        "glazing"
    ],
    "wof:name":"Varsani,R,",
    "wof:placetype":"venue"
},
  "geometry": {"coordinates":[-0.230959,51.569237],"type":"Point"}
}