{
  "type": "Feature",
  "properties": {
    "iso:country":"GB",
    "sg:address":"217-223 Kentish Town Road",
    "sg:city":"London",
    "sg:classifiers":[
        {
            "category":"Food & Beverages",
            "subcategory":"Supermarket",
            "type":"Retail Goods"
        }
    ],
    "sg:phone":"+44 20 7267 7668",
    "sg:postcode":"NW5 2JU",
    "sg:province":"Greater London",
    "wof:name":"Kwik Save Stores Ltd.",
    "wof:placetype":"venue"
},
  "geometry": {"coordinates":[-0.141671,51.547531],"type":"Point"}
}