{
  "type": "Feature",
  "properties": {
    "addr:full":"28 Northwood Drive Sittingbourne Kent ME10 4QR",
    "addr:housenumber":"28",
    "addr:postcode":"me10 4qr",
    "addr:street":"Northwood Drive",
    "iso:country":"GB",
    "sg:address":"28 Northwood Drive",
    "sg:city":"Sittingbourne",
    "sg:classifiers":[
        {
            "category":"Retail",
            "subcategory":"Driving School",
            "type":"Services"
        }
    ],
    "sg:phone":"+44 1795 478427",
    "sg:postcode":"ME10 4QR",
    "sg:province":"Kent",
    "wof:name":"Excel School Of Motoring",
    "wof:placetype":"venue"
},
  "geometry": {"coordinates":[0.7339360118,51.3298835754],"type":"Point"}
}