{
  "type": "Feature",
  "properties": {
    "iso:country":"GB",
    "sg:address":"174 Fore Street",
    "sg:city":"Exeter",
    "sg:classifiers":[
        {
            "category":"Shopping",
            "subcategory":"Department Store",
            "type":"Retail Goods"
        }
    ],
    "sg:phone":"+44 1392 426191",
    "sg:postcode":"EX4 3AX",
    "sg:province":"Devon",
    "wof:name":"Freewheel",
    "wof:placetype":"venue"
},
  "geometry": {"coordinates":[-3.53358,50.721897],"type":"Point"}
}