{
  "type": "Feature",
  "properties": {
    "iso:country":"GB",
    "sg:address":"Harpur Hill Industrial Estate, Harpur Hill Road",
    "sg:city":"Buxton",
    "sg:classifiers":[
        {
            "category":"Utilities",
            "subcategory":"Fuel Oil & Lpg",
            "type":"Services"
        }
    ],
    "sg:phone":"+44 1298 22200",
    "sg:postcode":"SK17 9JL",
    "sg:province":"Derbyshire",
    "sg:tags":[
        "coal",
        "smokeless"
    ],
    "wof:name":"Read Pre Packed Fuels & Products",
    "wof:placetype":"venue"
},
  "geometry": {"coordinates":[-1.9057199955,53.2368431091],"type":"Point"}
}