{
  "type": "Feature",
  "properties": {
    "addr:full":"1 Orchard House, Northend Road Erith Kent DA8 3PY",
    "addr:housenumber":"1",
    "addr:postcode":"da8 3py",
    "addr:street":"Orchard;Northend Road",
    "iso:country":"GB",
    "sg:address":"1 Orchard House, Northend Road",
    "sg:city":"Erith",
    "sg:classifiers":[
        {
            "category":"Social Services",
            "subcategory":"Adult Care",
            "type":"Services"
        }
    ],
    "sg:phone":"+44 1322 338819",
    "sg:postcode":"DA8 3PY",
    "sg:province":"Kent",
    "sg:tags":[
        "housing",
        "sheltered"
    ],
    "wof:name":"Orchard House Sheltered Housing",
    "wof:placetype":"venue"
},
  "geometry": {"coordinates":[0.180495,51.479221],"type":"Point"}
}