{
  "type": "Feature",
  "properties": {
    "iso:country":"GB",
    "sg:address":"106 Minard Road, Shawlands",
    "sg:city":"Glasgow",
    "sg:classifiers":[
        {
            "category":"Shopping",
            "subcategory":"News",
            "type":"Retail Goods"
        }
    ],
    "sg:phone":"+44 141 632 1398",
    "sg:postcode":"G41 2DL",
    "sg:province":"Glasgow City",
    "sg:tags":[
        "newsagent"
    ],
    "wof:name":"Young's",
    "wof:placetype":"venue"
},
  "geometry": {"coordinates":[-4.283051,55.834061],"type":"Point"}
}