{
  "type": "Feature",
  "properties": {
    "iso:country":"GB",
    "sg:address":"White Hill Farm, Sawood, Oxenhope",
    "sg:city":"Keighley",
    "sg:classifiers":[
        {
            "category":"Building & Trades",
            "subcategory":"Construction",
            "type":"Services"
        }
    ],
    "sg:postcode":"BD22 9SP",
    "sg:province":"North Yorkshire",
    "sg:tags":[
        "builder"
    ],
    "wof:name":"Harry D Jones Builder",
    "wof:placetype":"venue"
},
  "geometry": {"coordinates":[-1.951091,53.81324],"type":"Point"}
}