{
  "type": "Feature",
  "properties": {
    "iso:country":"GB",
    "sg:address":"8 Wrotham Rd",
    "sg:city":"Gravesend",
    "sg:classifiers":[
        {
            "category":"Professional",
            "subcategory":"Engineering",
            "type":"Services"
        }
    ],
    "sg:phone":"+44 1474 564100",
    "sg:postcode":"DA11 0PA",
    "sg:province":"Kent",
    "sg:tags":[
        "civil",
        "engineer"
    ],
    "wof:name":"Corstone Construction Ltd",
    "wof:placetype":"venue"
},
  "geometry": {"coordinates":[0.368054,51.440273],"type":"Point"}
}