{
  "type": "Feature",
  "properties": {
    "addr:full":"The Willows, St.georges Hospital Hornchurch Essex RM12 6RS",
    "addr:postcode":"rm12 6rs",
    "iso:country":"GB",
    "sg:address":"The Willows, St.georges Hospital",
    "sg:city":"Hornchurch",
    "sg:classifiers":[
        {
            "category":"Health Services",
            "subcategory":"Clinic",
            "type":"Services"
        }
    ],
    "sg:phone":"+44 1708 465438",
    "sg:postcode":"RM12 6RS",
    "sg:province":"Essex",
    "sg:tags":[
        "nh"
    ],
    "wof:name":"Community Dental Service",
    "wof:placetype":"venue"
},
  "geometry": {"coordinates":[0.2175299972,51.5474891663],"type":"Point"}
}