{
  "type": "Feature",
  "properties": {
    "iso:country":"GB",
    "sg:address":"10 Mundesley Close",
    "sg:city":"Stevenage",
    "sg:classifiers":[
        {
            "category":"Recreation",
            "subcategory":"Dog Park",
            "type":"Entertainment"
        }
    ],
    "sg:phone":"+44 1438 728660",
    "sg:postcode":"SG1 2JZ",
    "sg:province":"Hertfordshire",
    "wof:name":"Dereks Dirty Dogs",
    "wof:placetype":"venue"
},
  "geometry": {"coordinates":[-0.2192409933,51.9194259644],"type":"Point"}
}