{
  "type": "Feature",
  "properties": {
    "addr:full":"1201 High Road, Whetstone London Greater London N20 0PD",
    "addr:housenumber":"1201",
    "addr:postcode":"n20 0pd",
    "addr:street":"High Road",
    "iso:country":"GB",
    "sg:address":"1201 High Road, Whetstone",
    "sg:city":"London",
    "sg:classifiers":[
        {
            "category":"Home & Garden",
            "subcategory":"Hardware",
            "type":"Retail Goods"
        }
    ],
    "sg:phone":"+44 20 8445 3696",
    "sg:postcode":"N20 0PD",
    "sg:province":"Greater London",
    "sg:tags":[
        "retailer",
        "diy"
    ],
    "wof:name":"B & Q Supercentre",
    "wof:placetype":"venue"
},
  "geometry": {"coordinates":[-0.174849,51.628407],"type":"Point"}
}