{
  "type": "Feature",
  "properties": {
    "addr:full":"69 Dog Kennel Lane Oldbury West Midlands B68 9LZ",
    "addr:housenumber":"69",
    "addr:postcode":"b68 9lz",
    "addr:street":"Dog Kennel Lane",
    "iso:country":"GB",
    "sg:address":"69 Dog Kennel Lane",
    "sg:city":"Oldbury",
    "sg:classifiers":[
        {
            "category":"Building & Trades",
            "subcategory":"Construction",
            "type":"Services"
        }
    ],
    "sg:phone":"+44 121 552 7230",
    "sg:postcode":"B68 9LZ",
    "sg:province":"West Midlands",
    "sg:tags":[
        "decorator",
        "painter"
    ],
    "wof:name":"Adam Shilton Painters & Decorators",
    "wof:placetype":"venue"
},
  "geometry": {"coordinates":[-1.995922,52.489975],"type":"Point"}
}