{
  "type": "Feature",
  "properties": {
    "iso:country":"GB",
    "sg:address":"16 High Street, Market Weighton",
    "sg:city":"York",
    "sg:classifiers":[
        {
            "category":"Shopping",
            "subcategory":"Clothing, Apparel, & Fashions",
            "type":"Retail Goods"
        }
    ],
    "sg:phone":"+44 1430 872903",
    "sg:postcode":"YO43 3AH",
    "sg:province":"East Riding of Yorkshire",
    "sg:tags":[
        "shop"
    ],
    "wof:name":"Looks & Legs",
    "wof:placetype":"venue"
},
  "geometry": {"coordinates":[-0.665562,53.864307],"type":"Point"}
}