{
  "type": "Feature",
  "properties": {
    "addr:full":"Hawthorn Cottage, Twyn-yr-odyn Cardiff Cardiff CF5 6BG",
    "addr:postcode":"cf5 6bg",
    "addr:street":"Twyn-Yr-Odyn",
    "iso:country":"GB",
    "sg:address":"Hawthorn Cottage, Twyn-yr-odyn",
    "sg:city":"Cardiff",
    "sg:classifiers":[
        {
            "category":"Professional",
            "type":"Services"
        }
    ],
    "sg:phone":"+44 29 2059 4775",
    "sg:postcode":"CF5 6BG",
    "sg:province":"Cardiff",
    "sg:tags":[
        "caterer"
    ],
    "wof:name":"Anna's Caterers",
    "wof:placetype":"venue"
},
  "geometry": {"coordinates":[-3.27336,51.456329],"type":"Point"}
}