{
  "type": "Feature",
  "properties": {
    "addr:full":"21 Dovedales Norwich Norfolk NR6 7QE",
    "addr:housenumber":"21",
    "addr:postcode":"nr6 7qe",
    "addr:street":"Dovedales Norwich Norfolk",
    "iso:country":"GB",
    "sg:address":"21 Dovedales",
    "sg:city":"Norwich",
    "sg:classifiers":[
        {
            "category":"Professional",
            "subcategory":"Accounting & Tax Preparation",
            "type":"Services"
        }
    ],
    "sg:phone":"+44 1603 414440",
    "sg:postcode":"NR6 7QE",
    "sg:province":"Norfolk",
    "sg:tags":[
        "accountant"
    ],
    "wof:name":"Stuart Ferguson",
    "wof:placetype":"venue"
},
  "geometry": {"coordinates":[1.309148,52.657188],"type":"Point"}
}