{
  "type": "Feature",
  "properties": {
    "addr:full":"170 St Michael Street Dumfries Dumfries and Galloway DG1 2PR",
    "addr:housenumber":"170",
    "addr:postcode":"dg1 2pr",
    "addr:street":"St Michael Street",
    "iso:country":"GB",
    "sg:address":"170 St Michael Street",
    "sg:city":"Dumfries",
    "sg:classifiers":[
        {
            "category":"Organizations",
            "subcategory":"Community Association",
            "type":"Services"
        }
    ],
    "sg:phone":"+44 1387 247466",
    "sg:postcode":"DG1 2PR",
    "sg:province":"Dumfries and Galloway",
    "sg:tags":[
        "society",
        "housing"
    ],
    "wof:name":"Key Housing Community Living Service",
    "wof:placetype":"venue"
},
  "geometry": {"coordinates":[-3.608509,55.065979],"type":"Point"}
}