{
  "type": "Feature",
  "properties": {
    "iso:country":"GB",
    "sg:address":"32 Elm Grove Rd",
    "sg:city":"Farnborough",
    "sg:classifiers":[
        {
            "category":"Travel",
            "subcategory":"Hotels & Motels",
            "type":"Entertainment"
        }
    ],
    "sg:phone":"+44 1252 653446",
    "sg:postcode":"GU14 7RD",
    "sg:province":"Hampshire",
    "sg:tags":[
        "house",
        "guest"
    ],
    "wof:name":"Elm Grove",
    "wof:placetype":"venue"
},
  "geometry": {"coordinates":[-0.758189,51.295292],"type":"Point"}
}