{
  "type": "Feature",
  "properties": {
    "iso:country":"GB",
    "sg:address":"Siemens Way, Swansea Enterprise Park, Llansamlet",
    "sg:city":"Swansea",
    "sg:classifiers":[
        {
            "category":"Home & Garden",
            "subcategory":"Garden Supply",
            "type":"Retail Goods"
        }
    ],
    "sg:phone":"+44 1792 310052",
    "sg:postcode":"SA7 9FT",
    "sg:province":"Neath Port Talbot",
    "sg:tags":[
        "nursery",
        "centre"
    ],
    "wof:name":"Wyevale Garden Centres",
    "wof:placetype":"venue"
},
  "geometry": {"coordinates":[-3.918689,51.650372],"type":"Point"}
}