{
  "type": "Feature",
  "properties": {
    "addr:full":"Hilton Hotel, Old Common Rd Basingstoke Hampshire RG21 3PR",
    "addr:postcode":"rg21 3pr",
    "addr:street":"Old Common Rd",
    "iso:country":"GB",
    "sg:address":"Hilton Hotel, Old Common Rd",
    "sg:city":"Basingstoke",
    "sg:classifiers":[
        {
            "category":"Restaurant",
            "type":"Food & Drink"
        }
    ],
    "sg:phone":"+44 1256 460460",
    "sg:postcode":"RG21 3PR",
    "sg:province":"Hampshire",
    "wof:name":"Frontiers Restaurant & Bar",
    "wof:placetype":"venue"
},
  "geometry": {"coordinates":[-1.083089,51.262444],"type":"Point"}
}