{
  "type": "Feature",
  "properties": {
    "iso:country":"GB",
    "sg:address":"11 Chiltern End",
    "sg:city":"Ashford",
    "sg:classifiers":[
        {
            "category":"Professional",
            "subcategory":"Art Services",
            "type":"Services"
        }
    ],
    "sg:postcode":"TN24 8QJ",
    "sg:province":"Kent",
    "sg:tags":[
        "photographer"
    ],
    "wof:name":"Jonathans Photography",
    "wof:placetype":"venue"
},
  "geometry": {"coordinates":[0.8673149943,51.1550674438],"type":"Point"}
}