{
  "type": "Feature",
  "properties": {
    "addr:full":"Unit 31 The Business Centre, Ross Road, Weedon Road Industrial Estate Northampton Northamptonshire NN5 5AX",
    "addr:housenumber":"unit 31",
    "addr:postcode":"nn5 5ax",
    "addr:street":"The;Ross Road Weedon Road Industrial Estate",
    "iso:country":"GB",
    "sg:address":"Unit 31 The Business Centre, Ross Road, Weedon Road Industrial Estate",
    "sg:city":"Northampton",
    "sg:classifiers":[
        {
            "category":"Professional",
            "subcategory":"Detective & Security Services",
            "type":"Services"
        }
    ],
    "sg:phone":"+44 1604 588114",
    "sg:postcode":"NN5 5AX",
    "sg:province":"Northamptonshire",
    "sg:tags":[
        "supplier",
        "equipment",
        "manufacturer"
    ],
    "wof:name":"Gardiner Security Ltd",
    "wof:placetype":"venue"
},
  "geometry": {"coordinates":[-0.928203,52.240067],"type":"Point"}
}