{
  "type": "Feature",
  "properties": {
    "addr:full":"15 River Walk Great Yarmouth Norfolk NR30 4BZ",
    "addr:housenumber":"15",
    "addr:postcode":"nr30 4bz",
    "addr:street":"River Walk",
    "iso:country":"GB",
    "sg:address":"15 River Walk",
    "sg:city":"Great Yarmouth",
    "sg:classifiers":[
        {
            "category":"Building & Trades",
            "subcategory":"Plumbing",
            "type":"Services"
        }
    ],
    "sg:postcode":"NR30 4BZ",
    "sg:province":"Norfolk",
    "sg:tags":[
        "heating"
    ],
    "wof:name":"Cooks Electrical & Plumbing",
    "wof:placetype":"venue"
},
  "geometry": {"coordinates":[1.7269589901,52.6255264282],"type":"Point"}
}