{
  "type": "Feature",
  "properties": {
    "addr:full":"40 Station Road, Chingford London Greater London E4 7BE",
    "addr:housenumber":"40",
    "addr:postcode":"e4 7be",
    "addr:street":"Station Road",
    "iso:country":"GB",
    "sg:address":"40 Station Road, Chingford",
    "sg:city":"London",
    "sg:classifiers":[
        {
            "category":"Home & Garden",
            "subcategory":"Home Furnishings",
            "type":"Retail Goods"
        }
    ],
    "sg:phone":"+44 20 8559 4861",
    "sg:postcode":"E4 7BE",
    "sg:province":"Greater London",
    "sg:tags":[
        "blind",
        "curtain",
        "fitting"
    ],
    "wof:name":"The Orion Textiles",
    "wof:placetype":"venue"
},
  "geometry": {"coordinates":[0.005337,51.631935],"type":"Point"}
}