{
  "type": "Feature",
  "properties": {
    "addr:full":"143 Market Street, Atherton Manchester Greater Manchester M46 0DF",
    "addr:housenumber":"143",
    "addr:postcode":"m46 0df",
    "addr:street":"Market Street",
    "iso:country":"GB",
    "sg:address":"143 Market Street, Atherton",
    "sg:city":"Manchester",
    "sg:classifiers":[
        {
            "category":"Fast Food",
            "type":"Food & Drink"
        },
        {
            "category":"Restaurant",
            "type":"Food & Drink"
        }
    ],
    "sg:phone":"+44 1942 895931",
    "sg:postcode":"M46 0DF",
    "sg:province":"Greater Manchester",
    "sg:tags":[
        "away",
        "indian",
        "meal",
        "outlet",
        "take"
    ],
    "wof:name":"The Balti Cuisine",
    "wof:placetype":"venue"
},
  "geometry": {"coordinates":[-2.497033,53.523602],"type":"Point"}
}