{
  "type": "Feature",
  "properties": {
    "iso:country":"GB",
    "sg:address":"Sunningdale, Coychurch Road",
    "sg:city":"Bridgend",
    "sg:classifiers":[
        {
            "category":"Health Services",
            "subcategory":"Podiatrist",
            "type":"Services"
        }
    ],
    "sg:postcode":"CF35 5LP",
    "sg:province":"Bridgend",
    "sg:tags":[
        "podiatrists",
        "chiropodist"
    ],
    "wof:name":"Mark Rees",
    "wof:placetype":"venue"
},
  "geometry": {"coordinates":[-3.526348,51.507538],"type":"Point"}
}