{
  "type": "Feature",
  "properties": {
    "addr:full":"26 Tower Street King's Lynn Norfolk PE30 1EJ",
    "addr:housenumber":"26",
    "addr:postcode":"pe30 1ej",
    "addr:street":"Tower Street",
    "iso:country":"GB",
    "sg:address":"26 Tower Street",
    "sg:city":"King's Lynn",
    "sg:classifiers":[
        {
            "category":"Deli",
            "type":"Food & Drink"
        }
    ],
    "sg:phone":"+44 1553 762804",
    "sg:postcode":"PE30 1EJ",
    "sg:province":"Norfolk",
    "sg:tags":[
        "delicatessen"
    ],
    "wof:name":"Norbury's Fine Foods",
    "wof:placetype":"venue"
},
  "geometry": {"coordinates":[0.3977409899,52.7524795532],"type":"Point"}
}