{
  "type": "Feature",
  "properties": {
    "iso:country":"GB",
    "sg:address":"Old School House, Queen Square, Saltford",
    "sg:city":"Bristol",
    "sg:classifiers":[
        {
            "category":"Professional",
            "subcategory":"Computer Services",
            "type":"Services"
        }
    ],
    "sg:phone":"+44 1225 873117",
    "sg:postcode":"BS31 3EL",
    "sg:province":"City of Bristol",
    "sg:tags":[
        "system",
        "software"
    ],
    "wof:name":"M O S Computers Ltd.",
    "wof:placetype":"venue"
},
  "geometry": {"coordinates":[-2.45817,51.402184],"type":"Point"}
}