{
  "type": "Feature",
  "properties": {
    "addr:full":"52 Little Gaynes Lane Upminster Essex RM14 2JR",
    "addr:housenumber":"52",
    "addr:postcode":"rm14 2jr",
    "addr:street":"Little Gaynes Lane",
    "iso:country":"GB",
    "sg:address":"52 Little Gaynes Lane",
    "sg:city":"Upminster",
    "sg:classifiers":[
        {
            "category":"Building & Trades",
            "subcategory":"Construction",
            "type":"Services"
        }
    ],
    "sg:phone":"+44 1708 225440",
    "sg:postcode":"RM14 2JR",
    "sg:province":"Essex",
    "sg:tags":[
        "decorator",
        "painter"
    ],
    "wof:name":"Ralph D Cossington",
    "wof:placetype":"venue"
},
  "geometry": {"coordinates":[0.24217,51.548679],"type":"Point"}
}