{
  "type": "Feature",
  "properties": {
    "addr:full":"34 Station Rd Harpenden Hertfordshire AL5 4SE",
    "addr:housenumber":"34",
    "addr:postcode":"al5 4se",
    "addr:street":"Station Rd",
    "iso:country":"GB",
    "sg:address":"34 Station Rd",
    "sg:city":"Harpenden",
    "sg:classifiers":[
        {
            "category":"Food & Beverages",
            "subcategory":"Meat & Fish",
            "type":"Retail Goods"
        }
    ],
    "sg:phone":"+44 1582 769602",
    "sg:postcode":"AL5 4SE",
    "sg:province":"Hertfordshire",
    "sg:tags":[
        "chip"
    ],
    "wof:name":"Trawlerman Fish Bar",
    "wof:placetype":"venue"
},
  "geometry": {"coordinates":[-0.3529840112,51.8152236938],"type":"Point"}
}