{
  "type": "Feature",
  "properties": {
    "addr:full":"Banbury Road Chipping Norton Gloucestershire OX7 5SY",
    "addr:postcode":"ox7 5sy",
    "addr:street":"Banbury Road",
    "iso:country":"GB",
    "sg:address":"Banbury Road",
    "sg:city":"Chipping Norton",
    "sg:classifiers":[
        {
            "category":"Home & Garden",
            "subcategory":"Garden Supply",
            "type":"Retail Goods"
        }
    ],
    "sg:phone":"+44 1608 641642",
    "sg:postcode":"OX7 5SY",
    "sg:province":"Gloucestershire",
    "sg:tags":[
        "nursery",
        "centre"
    ],
    "wof:name":"Applegarth Nurseries",
    "wof:placetype":"venue"
},
  "geometry": {"coordinates":[-1.5366469622,51.9466667175],"type":"Point"}
}