{
  "type": "Feature",
  "properties": {
    "addr:full":"P O Box 89 Welwyn Garden City Hertfordshire AL8 6YX",
    "addr:housenumber":"box 89",
    "addr:postcode":"al8 6yx",
    "addr:street":"P O",
    "iso:country":"GB",
    "sg:address":"P O Box 89",
    "sg:city":"Welwyn Garden City",
    "sg:classifiers":[
        {
            "category":"Personal",
            "type":"Services"
        }
    ],
    "sg:postcode":"AL8 6YX",
    "sg:province":"Hertfordshire",
    "sg:tags":[
        "wedding"
    ],
    "wof:name":"Gatsby Automobiles",
    "wof:placetype":"venue"
},
  "geometry": {"coordinates":[-0.2057289928,51.8014297485],"type":"Point"}
}