{
  "type": "Feature",
  "properties": {
    "iso:country":"GB",
    "sg:address":"58 The Kingsway",
    "sg:city":"Swansea",
    "sg:classifiers":[
        {
            "category":"Shopping",
            "subcategory":"Baby Store",
            "type":"Retail Goods"
        }
    ],
    "sg:phone":"+44 1792 652999",
    "sg:postcode":"SA1 5HJ",
    "sg:province":"Neath Port Talbot",
    "sg:tags":[
        "nursery",
        "accessory"
    ],
    "wof:name":"Mothercare Uk",
    "wof:placetype":"venue"
},
  "geometry": {"coordinates":[-3.945929,51.620682],"type":"Point"}
}