{
  "type": "Feature",
  "properties": {
    "addr:full":"36 James Street London Greater London W1U 1AP",
    "addr:housenumber":"36",
    "addr:postcode":"w1u 1ap",
    "addr:street":"James Street",
    "iso:country":"GB",
    "sg:address":"36 James Street",
    "sg:city":"London",
    "sg:classifiers":[
        {
            "category":"Real Estate",
            "subcategory":"Real Estate Operator",
            "type":"Services"
        }
    ],
    "sg:phone":"+44 20 7935 9512",
    "sg:postcode":"W1U 1AP",
    "sg:province":"Greater London",
    "sg:tags":[
        "letting",
        "agent"
    ],
    "wof:name":"Globe Apartments",
    "wof:placetype":"venue"
},
  "geometry": {"coordinates":[-0.1505399942,51.5153007507],"type":"Point"}
}