{
  "type": "Feature",
  "properties": {
    "addr:full":"Burlington Ho, Barrington Rd Altrincham Cheshire WA14 1HB",
    "addr:postcode":"wa14 1hb",
    "addr:street":"Barrington Rd",
    "iso:country":"GB",
    "sg:address":"Burlington Ho, Barrington Rd",
    "sg:city":"Altrincham",
    "sg:classifiers":[
        {
            "category":"Professional",
            "subcategory":"Accounting & Tax Preparation",
            "type":"Services"
        }
    ],
    "sg:postcode":"WA14 1HB",
    "sg:province":"Cheshire",
    "sg:tags":[
        "accountant"
    ],
    "wof:name":"Assets Accountancy",
    "wof:placetype":"venue"
},
  "geometry": {"coordinates":[-2.3495700359,53.3919334412],"type":"Point"}
}