{
  "type": "Feature",
  "properties": {
    "iso:country":"GB",
    "sg:address":"13 Chapel Hill",
    "sg:city":"Huddersfield",
    "sg:classifiers":[
        {
            "category":"Shopping",
            "subcategory":"News",
            "type":"Retail Goods"
        }
    ],
    "sg:postcode":"HD1 3ED",
    "sg:province":"West Yorkshire",
    "sg:tags":[
        "newsagent"
    ],
    "wof:name":"Ahmed,M,",
    "wof:placetype":"venue"
},
  "geometry": {"coordinates":[-1.784951,53.641453],"type":"Point"}
}