{
  "type": "Feature",
  "properties": {
    "iso:country":"GB",
    "sg:address":"Tower House, 139 Station Road, Beeston",
    "sg:city":"Nottingham",
    "sg:classifiers":[
        {
            "category":"Professional",
            "subcategory":"Accounting & Tax Preparation",
            "type":"Services"
        }
    ],
    "sg:phone":"+44 115 922 8899",
    "sg:postcode":"NG9 2AZ",
    "sg:province":"Nottinghamshire",
    "sg:tags":[
        "accountant"
    ],
    "wof:name":"Dobb White & Co.",
    "wof:placetype":"venue"
},
  "geometry": {"coordinates":[-1.2112790346,52.9246063232],"type":"Point"}
}