{
  "type": "Feature",
  "properties": {
    "addr:full":"Clough St Leeds West Yorkshire LS27 8DH",
    "addr:postcode":"ls27 8dh",
    "addr:street":"Clough St",
    "iso:country":"GB",
    "sg:address":"Clough St",
    "sg:city":"Leeds",
    "sg:classifiers":[
        {
            "category":"Community Center",
            "subcategory":"Youth",
            "type":"Public Place"
        }
    ],
    "sg:phone":"+44 113 252 0724",
    "sg:postcode":"LS27 8DH",
    "sg:province":"West Yorkshire",
    "sg:tags":[
        "organisation",
        "centre"
    ],
    "wof:name":"Lewisham Youth & Community Centre",
    "wof:placetype":"venue"
},
  "geometry": {"coordinates":[-1.59276,53.747513],"type":"Point"}
}