{
  "type": "Feature",
  "properties": {
    "addr:full":"Braehead Cottage, Braehead Cromarty Highland IV11 8XR",
    "addr:housenumber":"braehead;braehead",
    "addr:postcode":"iv11 8xr",
    "addr:street":"Cromarty",
    "iso:country":"GB",
    "sg:address":"Braehead Cottage, Braehead",
    "sg:city":"Cromarty",
    "sg:classifiers":[
        {
            "category":"Building & Trades",
            "subcategory":"Plumbing",
            "type":"Services"
        }
    ],
    "sg:phone":"+44 1381 620124",
    "sg:postcode":"IV11 8XR",
    "sg:province":"Highland",
    "sg:tags":[
        "heating"
    ],
    "wof:name":"Rose & Maclean",
    "wof:placetype":"venue"
},
  "geometry": {"coordinates":[-4.0335521698,57.6817893982],"type":"Point"}
}