{
  "type": "Feature",
  "properties": {
    "addr:full":"20a Westgate Street, Blakeney Holt Norfolk NR25 6NQ",
    "addr:housenumber":"20a",
    "addr:postcode":"nr25 6nq",
    "addr:street":"Westgate Street",
    "iso:country":"GB",
    "sg:address":"20a Westgate Street, Blakeney",
    "sg:city":"Holt",
    "sg:classifiers":[
        {
            "category":"Food & Beverages",
            "subcategory":"Supermarket",
            "type":"Retail Goods"
        }
    ],
    "sg:phone":"+44 1263 740339",
    "sg:postcode":"NR25 6NQ",
    "sg:province":"Norfolk",
    "wof:name":"Bardales Ltd.",
    "wof:placetype":"venue"
},
  "geometry": {"coordinates":[1.0899460316,52.9030570984],"type":"Point"}
}