{
  "type": "Feature",
  "properties": {
    "addr:full":"184 Newport Road Caldicot Monmouthshire NP26 4AA",
    "addr:housenumber":"184",
    "addr:postcode":"np26 4aa",
    "addr:street":"Newport Road",
    "iso:country":"GB",
    "sg:address":"184 Newport Road",
    "sg:city":"Caldicot",
    "sg:classifiers":[
        {
            "category":"Shopping",
            "subcategory":"Department Store",
            "type":"Retail Goods"
        }
    ],
    "sg:postcode":"NP26 4AA",
    "sg:province":"Monmouthshire",
    "wof:name":"West End Stores",
    "wof:placetype":"venue"
},
  "geometry": {"coordinates":[-2.7598860264,51.5886383057],"type":"Point"}
}