{
  "type": "Feature",
  "properties": {
    "addr:full":"188 Birchgrove Road Swansea Neath Port Talbot SA7 9JU",
    "addr:housenumber":"188",
    "addr:postcode":"sa7 9ju",
    "addr:street":"Birchgrove Road",
    "iso:country":"GB",
    "sg:address":"188 Birchgrove Road",
    "sg:city":"Swansea",
    "sg:classifiers":[
        {
            "category":"Farming",
            "subcategory":"Dairy Farm",
            "type":"Manufacturing & Wholesale Goods"
        }
    ],
    "sg:postcode":"SA7 9JU",
    "sg:province":"Neath Port Talbot",
    "wof:name":"Birch Grove Dairies",
    "wof:placetype":"venue"
},
  "geometry": {"coordinates":[-3.8732481003,51.6670303345],"type":"Point"}
}