{
  "type": "Feature",
  "properties": {
    "iso:country":"GB",
    "sg:address":"Mill Lane, Padworth",
    "sg:city":"Reading",
    "sg:classifiers":[
        {
            "category":"Social Services",
            "type":"Services"
        },
        {
            "category":"Health Services",
            "subcategory":"Nursing And Care Facility",
            "type":"Services"
        }
    ],
    "sg:phone":"+44 118 971 3951",
    "sg:postcode":"RG7 4JU",
    "sg:province":"Berkshire",
    "sg:tags":[
        "need",
        "residential",
        "disability",
        "special"
    ],
    "wof:name":"ST LUKES TRUST (BERKSHIRE)",
    "wof:placetype":"venue"
},
  "geometry": {"coordinates":[-1.136184,51.400814],"type":"Point"}
}