{
  "type": "Feature",
  "properties": {
    "addr:full":"27 Mitchell Crescent Alloa Clackmannanshire FK10 1NN",
    "addr:housenumber":"27",
    "addr:postcode":"fk10 1nn",
    "addr:street":"Mitchell Crescent",
    "iso:country":"GB",
    "sg:address":"27 Mitchell Crescent",
    "sg:city":"Alloa",
    "sg:classifiers":[
        {
            "category":"Building & Trades",
            "subcategory":"Construction",
            "type":"Services"
        }
    ],
    "sg:phone":"+44 1259 217731",
    "sg:postcode":"FK10 1NN",
    "sg:province":"Clackmannanshire",
    "sg:tags":[
        "tiling",
        "contractor"
    ],
    "wof:name":"D Godward Joiners & Tilers",
    "wof:placetype":"venue"
},
  "geometry": {"coordinates":[-3.808664,56.11668],"type":"Point"}
}