{
  "type": "Feature",
  "properties": {
    "iso:country":"GB",
    "sg:address":"68 Humberstone Gate",
    "sg:city":"Leicester",
    "sg:classifiers":[
        {
            "category":"Fast Food",
            "type":"Food & Drink"
        }
    ],
    "sg:postcode":"LE1 3PL",
    "sg:province":"Leicestershire",
    "sg:tags":[
        "away",
        "take"
    ],
    "wof:name":"City Eating House",
    "wof:placetype":"venue"
},
  "geometry": {"coordinates":[-1.129318,52.636398],"type":"Point"}
}