{
  "type": "Feature",
  "properties": {
    "addr:full":"Unit 2a, Hicks Road, Markyate St Albans Hertfordshire AL3 8LG",
    "addr:housenumber":"unit 2a",
    "addr:postcode":"al3 8lg",
    "addr:street":"Hicks Road",
    "iso:country":"GB",
    "sg:address":"Unit 2a, Hicks Road, Markyate",
    "sg:city":"St Albans",
    "sg:classifiers":[
        {
            "category":"Manufacturing",
            "subcategory":"Metals",
            "type":"Manufacturing & Wholesale Goods"
        }
    ],
    "sg:phone":"+44 1582 841419",
    "sg:postcode":"AL3 8LG",
    "sg:province":"Hertfordshire",
    "sg:tags":[
        "steel",
        "fabricator",
        "erectors",
        "stockholder"
    ],
    "wof:name":"Hewitt Fabrications",
    "wof:placetype":"venue"
},
  "geometry": {"coordinates":[-0.453696,51.837349],"type":"Point"}
}