{
  "type": "Feature",
  "properties": {
    "addr:full":"15 Surrey Road Bristol City of Bristol BS7 9DJ",
    "addr:housenumber":"15",
    "addr:postcode":"bs7 9dj",
    "addr:street":"Surrey Road",
    "iso:country":"GB",
    "sg:address":"15 Surrey Road",
    "sg:city":"Bristol",
    "sg:classifiers":[
        {
            "category":"Professional",
            "subcategory":"Management & Consulting",
            "type":"Services"
        }
    ],
    "sg:postcode":"BS7 9DJ",
    "sg:province":"City of Bristol",
    "sg:tags":[
        "consultant",
        "business"
    ],
    "wof:name":"Eras",
    "wof:placetype":"venue"
},
  "geometry": {"coordinates":[-2.5854449272,51.4757843018],"type":"Point"}
}