{
  "type": "Feature",
  "properties": {
    "iso:country":"GB",
    "sg:address":"4 Parker Lane",
    "sg:city":"Burnley",
    "sg:classifiers":[
        {
            "category":"Shopping",
            "subcategory":"Optician",
            "type":"Retail Goods"
        }
    ],
    "sg:phone":"+44 1282 432020",
    "sg:postcode":"BB11 2BY",
    "sg:province":"Lancashire",
    "sg:tags":[
        "dispensing"
    ],
    "wof:name":"Direct Optik International",
    "wof:placetype":"venue"
},
  "geometry": {"coordinates":[-2.240914,53.788937],"type":"Point"}
}