{
  "type": "Feature",
  "properties": {
    "addr:full":"Kingsfield Centre, Moulton Park Northampton Northamptonshire NN3 6RB",
    "addr:postcode":"nn3 6rb",
    "iso:country":"GB",
    "sg:address":"Kingsfield Centre, Moulton Park",
    "sg:city":"Northampton",
    "sg:classifiers":[
        {
            "category":"Professional",
            "subcategory":"Computer Services",
            "type":"Services"
        }
    ],
    "sg:phone":"+44 870 888 8430",
    "sg:postcode":"NN3 6RB",
    "sg:province":"Northamptonshire",
    "sg:tags":[
        "system",
        "software"
    ],
    "wof:name":"Kingsfield Computer Products Ltd.",
    "wof:placetype":"venue"
},
  "geometry": {"coordinates":[-0.86357,52.27647],"type":"Point"}
}