{
  "type": "Feature",
  "properties": {
    "addr:full":"Valley Cottage, Goyt Valley Stockport Cheshire SK6 3LQ",
    "addr:postcode":"sk6 3lq",
    "addr:street":"Goyt Valley",
    "iso:country":"GB",
    "sg:address":"Valley Cottage, Goyt Valley",
    "sg:city":"Stockport",
    "sg:classifiers":[
        {
            "category":"Recreation",
            "subcategory":"Dog Park",
            "type":"Entertainment"
        }
    ],
    "sg:phone":"+44 161 427 1088",
    "sg:postcode":"SK6 3LQ",
    "sg:province":"Cheshire",
    "wof:name":"Shear Delight",
    "wof:placetype":"venue"
},
  "geometry": {"coordinates":[-2.0935220718,53.4101219177],"type":"Point"}
}