{
  "type": "Feature",
  "properties": {
    "addr:full":"577 Goffs Lane, Cheshunt Waltham Cross Greater London EN7 5HJ",
    "addr:housenumber":"577",
    "addr:postcode":"en7 5hj",
    "addr:street":"Goffs Lane",
    "iso:country":"GB",
    "sg:address":"577 Goffs Lane, Cheshunt",
    "sg:city":"Waltham Cross",
    "sg:classifiers":[
        {
            "category":"Military Area",
            "subcategory":"Air Force Base",
            "type":"Public Place"
        }
    ],
    "sg:phone":"+44 1707 875551",
    "sg:postcode":"EN7 5HJ",
    "sg:province":"Greater London",
    "sg:tags":[
        "taxi",
        "hire",
        "private"
    ],
    "wof:name":"Ace Cabs",
    "wof:placetype":"venue"
},
  "geometry": {"coordinates":[-0.084638,51.709667],"type":"Point"}
}