{
  "type": "Feature",
  "properties": {
    "addr:full":"29a St Johns Road Chelmsford Essex CM2 9PD",
    "addr:housenumber":"29a",
    "addr:postcode":"cm2 9pd",
    "addr:street":"St Johns Road",
    "iso:country":"GB",
    "sg:address":"29a St Johns Road",
    "sg:city":"Chelmsford",
    "sg:classifiers":[
        {
            "category":"Freight",
            "type":"Transportation"
        }
    ],
    "sg:postcode":"CM2 9PD",
    "sg:province":"Essex",
    "sg:tags":[
        "overseas",
        "shipping",
        "removal"
    ],
    "wof:name":"R Downie",
    "wof:placetype":"venue"
},
  "geometry": {"coordinates":[0.47041,51.726334],"type":"Point"}
}