{
  "type": "Feature",
  "properties": {
    "addr:full":"Brookside, Rearsby Leicester Leicestershire LE7 4YB",
    "addr:postcode":"le7 4yb",
    "iso:country":"GB",
    "sg:address":"Brookside, Rearsby",
    "sg:city":"Leicester",
    "sg:classifiers":[
        {
            "category":"Education",
            "subcategory":"School",
            "type":"Public Place"
        }
    ],
    "sg:phone":"+44 1664 424453",
    "sg:postcode":"LE7 4YB",
    "sg:province":"Leicestershire",
    "sg:tags":[
        "local",
        "authority"
    ],
    "wof:name":"Rearsby St Michael & All Angels C of E Primary School",
    "wof:placetype":"venue"
},
  "geometry": {"coordinates":[-1.033165,52.72504],"type":"Point"}
}