{
  "type": "Feature",
  "properties": {
    "addr:full":"The Leats Truro Cornwall TR1 3AG",
    "addr:postcode":"tr1 3ag",
    "iso:country":"GB",
    "sg:address":"The Leats",
    "sg:city":"Truro",
    "sg:classifiers":[
        {
            "category":"Arts & Performance",
            "subcategory":"Art Gallery",
            "type":"Entertainment"
        }
    ],
    "sg:phone":"+44 1872 240567",
    "sg:postcode":"TR1 3AG",
    "sg:province":"Cornwall",
    "wof:name":"Gluvian Galleries",
    "wof:placetype":"venue"
},
  "geometry": {"coordinates":[-5.055159,50.263981],"type":"Point"}
}