{
  "type": "Feature",
  "properties": {
    "iso:country":"GB",
    "sg:address":"224 Chingford Mount Road",
    "sg:city":"London",
    "sg:classifiers":[
        {
            "category":"Professional",
            "subcategory":"Detective & Security Services",
            "type":"Services"
        }
    ],
    "sg:phone":"+44 20 8523 8864",
    "sg:postcode":"E4 8JL",
    "sg:province":"Greater London",
    "sg:tags":[
        "car"
    ],
    "wof:name":"Music on Wheels",
    "wof:placetype":"venue"
},
  "geometry": {"coordinates":[-0.0173560008,51.6160163879],"type":"Point"}
}