{
  "type": "Feature",
  "properties": {
    "addr:full":"2 Tan Lane, Caister On Sea Great Yarmouth Norfolk NR30 5DN",
    "addr:housenumber":"2",
    "addr:postcode":"nr30 5dn",
    "addr:street":"Tan Lane",
    "iso:country":"GB",
    "sg:address":"2 Tan Lane, Caister On Sea",
    "sg:city":"Great Yarmouth",
    "sg:classifiers":[
        {
            "category":"Manufacturing",
            "subcategory":"Petroleum Products",
            "type":"Manufacturing & Wholesale Goods"
        }
    ],
    "sg:phone":"+44 1493 377311",
    "sg:postcode":"NR30 5DN",
    "sg:province":"Norfolk",
    "sg:tags":[
        "double",
        "glazing"
    ],
    "wof:name":"Caister Windows Ltd",
    "wof:placetype":"venue"
},
  "geometry": {"coordinates":[1.7292079926,52.645816803],"type":"Point"}
}