{
  "type": "Feature",
  "properties": {
    "iso:country":"GB",
    "sg:address":"30h Newmarket Street",
    "sg:city":"Falkirk",
    "sg:classifiers":[
        {
            "category":"Professional",
            "subcategory":"Lawyer & Legal Services",
            "type":"Services"
        }
    ],
    "sg:phone":"+44 1324 633433",
    "sg:postcode":"FK1 1JQ",
    "sg:province":"Falkirk",
    "sg:tags":[
        "advice",
        "counselling"
    ],
    "wof:name":"Falkirk District Victim Support",
    "wof:placetype":"venue"
},
  "geometry": {"coordinates":[-3.785306,56.000889],"type":"Point"}
}