{
  "type": "Feature",
  "properties": {
    "addr:full":"Warehouse Ecton Road Northampton Northamptonshire NN1 5RA",
    "addr:postcode":"nn1 5ra",
    "addr:street":"Ecton Road",
    "iso:country":"GB",
    "sg:address":"Warehouse Ecton Road",
    "sg:city":"Northampton",
    "sg:classifiers":[
        {
            "category":"Manufacturing",
            "subcategory":"Apparel",
            "type":"Manufacturing & Wholesale Goods"
        }
    ],
    "sg:postcode":"NN1 5RA",
    "sg:province":"Northamptonshire",
    "sg:tags":[
        "mnfr",
        "footwear"
    ],
    "wof:name":"S S Shoes",
    "wof:placetype":"venue"
},
  "geometry": {"coordinates":[-0.8952839971,52.2339401245],"type":"Point"}
}