{
  "type": "Feature",
  "properties": {
    "addr:full":"449 Leatherhead Road Chessington Surrey KT9 2NQ",
    "addr:housenumber":"449",
    "addr:postcode":"kt9 2nq",
    "addr:street":"Leatherhead Road",
    "iso:country":"GB",
    "sg:address":"449 Leatherhead Road",
    "sg:city":"Chessington",
    "sg:classifiers":[
        {
            "category":"Professional",
            "subcategory":"Business Services",
            "type":"Services"
        }
    ],
    "sg:postcode":"KT9 2NQ",
    "sg:province":"Surrey",
    "sg:tags":[
        "food",
        "import",
        "export",
        "agent"
    ],
    "wof:name":"International Brand Marketing Ltd.",
    "wof:placetype":"venue"
},
  "geometry": {"coordinates":[-0.3256669939,51.3282814026],"type":"Point"}
}