{
  "type": "Feature",
  "properties": {
    "addr:full":"201 Deansgate Manchester Greater Manchester M60 2AT",
    "addr:housenumber":"201",
    "addr:postcode":"m60 2at",
    "addr:street":"Deansgate",
    "iso:country":"GB",
    "sg:address":"201 Deansgate",
    "sg:city":"Manchester",
    "sg:classifiers":[
        {
            "category":"Professional",
            "subcategory":"Business Services",
            "type":"Services"
        }
    ],
    "sg:postcode":"M60 2AT",
    "sg:province":"Greater Manchester",
    "sg:tags":[
        "accomodation"
    ],
    "wof:name":"Win Hanverky (Europe) Ltd",
    "wof:placetype":"venue"
},
  "geometry": {"coordinates":[-2.24507,53.4771],"type":"Point"}
}