{
  "type": "Feature",
  "properties": {
    "addr:full":"687 Fulham Road London Greater London SW6 5UJ",
    "addr:housenumber":"687",
    "addr:postcode":"sw6 5uj",
    "addr:street":"Fulham Road",
    "iso:country":"GB",
    "sg:address":"687 Fulham Road",
    "sg:city":"London",
    "sg:classifiers":[
        {
            "category":"Building & Trades",
            "subcategory":"Construction",
            "type":"Services"
        }
    ],
    "sg:phone":"+44 20 7736 8798",
    "sg:postcode":"SW6 5UJ",
    "sg:province":"Greater London",
    "sg:tags":[
        "joiner",
        "carpenter"
    ],
    "wof:name":"Peter Franklin",
    "wof:placetype":"venue"
},
  "geometry": {"coordinates":[-0.1863600016,51.4826393127],"type":"Point"}
}