{
  "type": "Feature",
  "properties": {
    "addr:full":"117a Liverpool Road Newcastle Staffordshire ST5 9EW",
    "addr:housenumber":"117a",
    "addr:postcode":"st5 9ew",
    "addr:street":"Liverpool Road",
    "iso:country":"GB",
    "sg:address":"117a Liverpool Road",
    "sg:city":"Newcastle",
    "sg:classifiers":[
        {
            "category":"Autos & Motor Vehicles",
            "subcategory":"Auto Supplies",
            "type":"Retail Goods"
        }
    ],
    "sg:phone":"+44 1782 617331",
    "sg:postcode":"ST5 9EW",
    "sg:province":"Staffordshire",
    "sg:tags":[
        "tyre"
    ],
    "wof:name":"National Tyres and Autocare",
    "wof:placetype":"venue"
},
  "geometry": {"coordinates":[-2.2307209969,53.0180511475],"type":"Point"}
}