{
  "type": "Feature",
  "properties": {
    "iso:country":"GB",
    "sg:address":"265 Warsash Road, Locks Heath",
    "sg:city":"Southampton",
    "sg:classifiers":[
        {
            "category":"Social Services",
            "subcategory":"Retirement Home",
            "type":"Services"
        }
    ],
    "sg:postcode":"SO31 9NY",
    "sg:province":"Hampshire",
    "sg:tags":[
        "rest"
    ],
    "wof:name":"West Dene Residential Home",
    "wof:placetype":"venue"
},
  "geometry": {"coordinates":[-1.273005,50.855354],"type":"Point"}
}