{
  "type": "Feature",
  "properties": {
    "addr:full":"13 Kershaw Dr Halifax West Yorkshire HX2 6PD",
    "addr:housenumber":"13",
    "addr:postcode":"hx2 6pd",
    "addr:street":"Kershaw Dr",
    "iso:country":"GB",
    "sg:address":"13 Kershaw Dr",
    "sg:city":"Halifax",
    "sg:classifiers":[
        {
            "category":"Social Services",
            "subcategory":"Adult Care",
            "type":"Services"
        }
    ],
    "sg:phone":"+44 1422 883379",
    "sg:postcode":"HX2 6PD",
    "sg:province":"West Yorkshire",
    "sg:tags":[
        "housing",
        "sheltered"
    ],
    "wof:name":"Kershaw Drive Sheltered Housing",
    "wof:placetype":"venue"
},
  "geometry": {"coordinates":[-1.943573,53.72657],"type":"Point"}
}