{
  "type": "Feature",
  "properties": {
    "iso:country":"GB",
    "sg:address":"34 Towngate, Heptonstall",
    "sg:city":"Hebden Bridge",
    "sg:classifiers":[
        {
            "category":"Food & Beverages",
            "subcategory":"Meat & Fish",
            "type":"Retail Goods"
        }
    ],
    "sg:postcode":"HX7 7NB",
    "sg:province":"West Yorkshire",
    "sg:tags":[
        "chip"
    ],
    "wof:name":"Towngate Fisheries",
    "wof:placetype":"venue"
},
  "geometry": {"coordinates":[-2.0170209408,53.745174408],"type":"Point"}
}