{
  "type": "Feature",
  "properties": {
    "addr:full":"276 Biscot Road Luton Bedfordshire LU3 1AZ",
    "addr:housenumber":"276",
    "addr:postcode":"lu3 1az",
    "addr:street":"Biscot Road",
    "iso:country":"GB",
    "sg:address":"276 Biscot Road",
    "sg:city":"Luton",
    "sg:classifiers":[
        {
            "category":"Autos & Motor Vehicles",
            "subcategory":"Automobile Sales",
            "type":"Retail Goods"
        }
    ],
    "sg:postcode":"LU3 1AZ",
    "sg:province":"Bedfordshire",
    "sg:tags":[
        "car"
    ],
    "wof:name":"Sheridan",
    "wof:placetype":"venue"
},
  "geometry": {"coordinates":[-0.4314770103,51.8944969177],"type":"Point"}
}