{
  "type": "Feature",
  "properties": {
    "addr:full":"Suite 3, 6th Floor, Berkeley Square House London Greater London W1J 6BR",
    "addr:housenumber":"suite 3 6th floor",
    "addr:postcode":"w1j 6br",
    "addr:street":"Berkeley Square House",
    "iso:country":"GB",
    "sg:address":"Suite 3, 6th Floor, Berkeley Square House",
    "sg:city":"London",
    "sg:classifiers":[
        {
            "category":"Real Estate",
            "subcategory":"Developer",
            "type":"Services"
        }
    ],
    "sg:phone":"+44 20 7629 4333",
    "sg:postcode":"W1J 6BR",
    "sg:province":"Greater London",
    "sg:tags":[
        "property"
    ],
    "wof:name":"Hilstone Corporation Ltd.",
    "wof:placetype":"venue"
},
  "geometry": {"coordinates":[-0.14456,51.509819],"type":"Point"}
}