{
  "type": "Feature",
  "properties": {
    "iso:country":"GB",
    "sg:address":"1a The Maltings, Railway Place",
    "sg:city":"Hertford",
    "sg:classifiers":[
        {
            "category":"Professional",
            "subcategory":"Accounting & Tax Preparation",
            "type":"Services"
        }
    ],
    "sg:phone":"+44 1992 550836",
    "sg:postcode":"SG13 7JT",
    "sg:province":"Hertfordshire",
    "sg:tags":[
        "accountant"
    ],
    "wof:name":"J V Wilson & Co",
    "wof:placetype":"venue"
},
  "geometry": {"coordinates":[-0.0459249988,51.7829170227],"type":"Point"}
}