{
  "type": "Feature",
  "properties": {
    "iso:country":"GB",
    "sg:address":"40 Upper Breeze Hill, Benllech",
    "sg:city":"Tyn-y-gongl",
    "sg:classifiers":[
        {
            "category":"Building & Trades",
            "subcategory":"Construction",
            "type":"Services"
        }
    ],
    "sg:phone":"+44 1248 853077",
    "sg:postcode":"LL74 8XA",
    "sg:province":"Isle of Anglesey",
    "sg:tags":[
        "decorator",
        "painter"
    ],
    "wof:name":"Colortone",
    "wof:placetype":"venue"
},
  "geometry": {"coordinates":[-4.231719,53.313999],"type":"Point"}
}