{
  "type": "Feature",
  "properties": {
    "iso:country":"GB",
    "sg:address":"2-4 Gloucester Road, Bishopston",
    "sg:city":"Bristol",
    "sg:classifiers":[
        {
            "category":"Recreation",
            "type":"Entertainment"
        }
    ],
    "sg:phone":"+44 117 942 1955",
    "sg:postcode":"BS7 8AE",
    "sg:province":"City of Bristol",
    "sg:tags":[
        "snooker",
        "billiards",
        "pool"
    ],
    "wof:name":"The Masters Snooker Club",
    "wof:placetype":"venue"
},
  "geometry": {"coordinates":[-2.593696,51.470676],"type":"Point"}
}