{
  "type": "Feature",
  "properties": {
    "iso:country":"GB",
    "sg:address":"39 Pirbright Road, Southfields",
    "sg:city":"London",
    "sg:classifiers":[
        {
            "category":"Professional",
            "type":"Services"
        }
    ],
    "sg:postcode":"SW18 5ND",
    "sg:province":"Greater London",
    "sg:tags":[
        "reflexologists"
    ],
    "wof:name":"Susan Mehmet",
    "wof:placetype":"venue"
},
  "geometry": {"coordinates":[-0.203441,51.445862],"type":"Point"}
}