{
  "type": "Feature",
  "properties": {
    "addr:full":"9 Farr Road Enfield Greater London EN2 0DE",
    "addr:housenumber":"9",
    "addr:postcode":"en2 0de",
    "addr:street":"Farr Road",
    "iso:country":"GB",
    "sg:address":"9 Farr Road",
    "sg:city":"Enfield",
    "sg:classifiers":[
        {
            "category":"Personal",
            "type":"Services"
        },
        {
            "category":"Professional",
            "subcategory":"Art Services",
            "type":"Services"
        }
    ],
    "sg:phone":"+44 20 8363 8350",
    "sg:postcode":"EN2 0DE",
    "sg:province":"Greater London",
    "sg:tags":[
        "photographer",
        "wedding"
    ],
    "wof:name":"Michael O'Sullivan Photography",
    "wof:placetype":"venue"
},
  "geometry": {"coordinates":[-0.080294,51.661846],"type":"Point"}
}