{
  "type": "Feature",
  "properties": {
    "iso:country":"GB",
    "sg:address":"73 Kempston Street",
    "sg:city":"Liverpool",
    "sg:classifiers":[
        {
            "category":"Restaurant",
            "type":"Food & Drink"
        }
    ],
    "sg:phone":"+44 151 207 1388",
    "sg:postcode":"L3 8NR",
    "sg:province":"Merseyside",
    "wof:name":"Hughes Bros (Toys) Ltd.",
    "wof:placetype":"venue"
},
  "geometry": {"coordinates":[-2.9700191021,53.4108810425],"type":"Point"}
}