{
  "type": "Feature",
  "properties": {
    "iso:country":"GB",
    "sg:address":"The Fairway",
    "sg:city":"Cambridge",
    "sg:classifiers":[
        {
            "category":"Real Estate",
            "subcategory":"Surveying",
            "type":"Services"
        }
    ],
    "sg:postcode":"CB3 8SR",
    "sg:province":"Cambridgeshire",
    "sg:tags":[
        "surveyor",
        "quantity"
    ],
    "wof:name":"G P Thompson",
    "wof:placetype":"venue"
},
  "geometry": {"coordinates":[0.0300650001,52.2492599487],"type":"Point"}
}