{
  "type": "Feature",
  "properties": {
    "iso:country":"GB",
    "sg:address":"128a Stratford Road, Shirley",
    "sg:city":"Solihull",
    "sg:classifiers":[
        {
            "category":"Professional",
            "subcategory":"Employment Agencies",
            "type":"Services"
        }
    ],
    "sg:phone":"+44 1564 822306",
    "sg:postcode":"B90 3BB",
    "sg:province":"West Midlands",
    "sg:tags":[
        "consultant",
        "recruitment"
    ],
    "wof:name":"Bond Management & Design",
    "wof:placetype":"venue"
},
  "geometry": {"coordinates":[-1.828695,52.414326],"type":"Point"}
}