{
  "type": "Feature",
  "properties": {
    "iso:country":"GB",
    "sg:address":"High Street, Twyford",
    "sg:city":"Winchester",
    "sg:classifiers":[
        {
            "category":"Shopping",
            "subcategory":"Department Store",
            "type":"Retail Goods"
        }
    ],
    "sg:phone":"+44 1962 712168",
    "sg:postcode":"SO21 1NH",
    "sg:province":"Hampshire",
    "wof:name":"Twyford Post Office & Stores",
    "wof:placetype":"venue"
},
  "geometry": {"coordinates":[-1.316149,51.016869],"type":"Point"}
}