{
  "type": "Feature",
  "properties": {
    "iso:country":"GB",
    "sg:address":"192 High St",
    "sg:city":"Guildford",
    "sg:classifiers":[
        {
            "category":"Banks & Credit Unions",
            "subcategory":"Financial Services",
            "type":"Services"
        }
    ],
    "sg:phone":"+44 1483 562677",
    "sg:postcode":"GU1 3HW",
    "sg:province":"Surrey",
    "sg:tags":[
        "consultant"
    ],
    "wof:name":"Frazers Financial Services",
    "wof:placetype":"venue"
},
  "geometry": {"coordinates":[-0.569512,51.236481],"type":"Point"}
}