{
  "type": "Feature",
  "properties": {
    "addr:full":"120 Church Street, Audley Stoke-on-trent Cheshire ST7 8EE",
    "addr:housenumber":"120",
    "addr:postcode":"st7 8ee",
    "addr:street":"Church Street",
    "iso:country":"GB",
    "sg:address":"120 Church Street, Audley",
    "sg:city":"Stoke-on-trent",
    "sg:classifiers":[
        {
            "category":"Fast Food",
            "type":"Food & Drink"
        }
    ],
    "sg:phone":"+44 1782 720313",
    "sg:postcode":"ST7 8EE",
    "sg:province":"Cheshire",
    "sg:tags":[
        "away",
        "take"
    ],
    "wof:name":"Oriental Chef",
    "wof:placetype":"venue"
},
  "geometry": {"coordinates":[-2.302567,53.052059],"type":"Point"}
}