{
  "type": "Feature",
  "properties": {
    "iso:country":"GB",
    "sg:address":"Planet House, 1 Canbury Park Road",
    "sg:city":"Kingston-upon-thames",
    "sg:classifiers":[
        {
            "category":"Communications",
            "subcategory":"Film & Video Production",
            "type":"Services"
        }
    ],
    "sg:phone":"+44 20 8974 6050",
    "sg:postcode":"KT2 6JX",
    "sg:province":"Greater London",
    "sg:tags":[
        "tv"
    ],
    "wof:name":"Planet Television",
    "wof:placetype":"venue"
},
  "geometry": {"coordinates":[-0.2997690141,51.4129600525],"type":"Point"}
}