{
  "type": "Feature",
  "properties": {
    "addr:full":"The Vicarage, Wilbraham Rd Manchester Greater Manchester M14 7DN",
    "addr:postcode":"m14 7dn",
    "addr:street":"Wilbraham Rd",
    "iso:country":"GB",
    "sg:address":"The Vicarage, Wilbraham Rd",
    "sg:city":"Manchester",
    "sg:classifiers":[
        {
            "category":"Place Of Worship",
            "type":"Public Place"
        }
    ],
    "sg:phone":"+44 161 224 6048",
    "sg:postcode":"M14 7DN",
    "sg:province":"Greater Manchester",
    "wof:name":"Platt Lane Methodist Church",
    "wof:placetype":"venue"
},
  "geometry": {"coordinates":[-2.24881,53.479622],"type":"Point"}
}