{
  "type": "Feature",
  "properties": {
    "addr:full":"4 High Boreland, Glenluce Newton Stewart Dumfries and Galloway DG8 0NW",
    "addr:housenumber":"4",
    "addr:postcode":"dg8 0nw",
    "addr:street":"High Boreland Glenluce;Stewart",
    "iso:country":"GB",
    "sg:address":"4 High Boreland, Glenluce",
    "sg:city":"Newton Stewart",
    "sg:classifiers":[
        {
            "category":"Farming",
            "subcategory":"Farm",
            "type":"Manufacturing & Wholesale Goods"
        }
    ],
    "sg:phone":"+44 1581 400218",
    "sg:postcode":"DG8 0NW",
    "sg:province":"Dumfries and Galloway",
    "sg:tags":[
        "mixed",
        "crop"
    ],
    "wof:name":"W & S Kerr",
    "wof:placetype":"venue"
},
  "geometry": {"coordinates":[-4.8121027946,54.8781166077],"type":"Point"}
}