{
  "type": "Feature",
  "properties": {
    "addr:full":"Three Trees, Wilsden Old Road, Harden Bingley West Yorkshire BD16 1JD",
    "addr:postcode":"bd16 1jd",
    "addr:street":"Wilsden Old Road",
    "iso:country":"GB",
    "sg:address":"Three Trees, Wilsden Old Road, Harden",
    "sg:city":"Bingley",
    "sg:classifiers":[
        {
            "category":"Social Services",
            "subcategory":"Adult Care",
            "type":"Services"
        }
    ],
    "sg:postcode":"BD16 1JD",
    "sg:province":"West Yorkshire",
    "sg:tags":[
        "domestic",
        "cleaning"
    ],
    "wof:name":"Dial A Char",
    "wof:placetype":"venue"
},
  "geometry": {"coordinates":[-1.870124,53.839371],"type":"Point"}
}