{
  "type": "Feature",
  "properties": {
    "addr:full":"50 Westgate Cleckheaton West Yorkshire BD19 5EY",
    "addr:housenumber":"50",
    "addr:postcode":"bd19 5ey",
    "addr:street":"Westgate Cleckheaton West",
    "iso:country":"GB",
    "sg:address":"50 Westgate",
    "sg:city":"Cleckheaton",
    "sg:classifiers":[
        {
            "category":"Manufacturing",
            "subcategory":"Tools & Machinery",
            "type":"Manufacturing & Wholesale Goods"
        }
    ],
    "sg:phone":"+44 1274 871204",
    "sg:postcode":"BD19 5EY",
    "sg:province":"West Yorkshire",
    "sg:tags":[
        "society",
        "friendly"
    ],
    "wof:name":"Paul Child",
    "wof:placetype":"venue"
},
  "geometry": {"coordinates":[-1.7257889509,53.7223510742],"type":"Point"}
}