{
  "type": "Feature",
  "properties": {
    "addr:full":"5 Sawtells Terrace, Pontnewynydd Pontypool Monmouthshire NP4 6RA",
    "addr:housenumber":"5",
    "addr:postcode":"np4 6ra",
    "addr:street":"Sawtells Terrace",
    "iso:country":"GB",
    "sg:address":"5 Sawtells Terrace, Pontnewynydd",
    "sg:city":"Pontypool",
    "sg:classifiers":[
        {
            "category":"Building & Trades",
            "subcategory":"Construction",
            "type":"Services"
        }
    ],
    "sg:phone":"+44 1495 753564",
    "sg:postcode":"NP4 6RA",
    "sg:province":"Monmouthshire",
    "sg:tags":[
        "ceiling",
        "contractor"
    ],
    "wof:name":"Alan Nash",
    "wof:placetype":"venue"
},
  "geometry": {"coordinates":[-3.060608,51.711929],"type":"Point"}
}