{
  "type": "Feature",
  "properties": {
    "addr:full":"364 Kingsway Hove East Sussex BN3 4PQ",
    "addr:housenumber":"364",
    "addr:postcode":"bn3 4pq",
    "addr:street":"Kingsway Hove",
    "iso:country":"GB",
    "sg:address":"364 Kingsway",
    "sg:city":"Hove",
    "sg:classifiers":[
        {
            "category":"Shopping",
            "subcategory":"Stationery & Office Supplies",
            "type":"Retail Goods"
        }
    ],
    "sg:phone":"+44 1273 422842",
    "sg:postcode":"BN3 4PQ",
    "sg:province":"East Sussex",
    "sg:tags":[
        "equipment"
    ],
    "wof:name":"Sussex Typewriters",
    "wof:placetype":"venue"
},
  "geometry": {"coordinates":[-0.203031,50.828743],"type":"Point"}
}