{
  "type": "Feature",
  "properties": {
    "addr:full":"59 Clerkhill Road Peterhead Aberdeenshire AB42 6XF",
    "addr:housenumber":"59",
    "addr:postcode":"ab42 6xf",
    "addr:street":"Clerkhill Road",
    "iso:country":"GB",
    "sg:address":"59 Clerkhill Road",
    "sg:city":"Peterhead",
    "sg:classifiers":[
        {
            "category":"Home & Garden",
            "subcategory":"Home Furnishings",
            "type":"Retail Goods"
        }
    ],
    "sg:phone":"+44 1779 470350",
    "sg:postcode":"AB42 6XF",
    "sg:province":"Aberdeenshire",
    "sg:tags":[
        "awning",
        "canopy",
        "blinds"
    ],
    "wof:name":"Forbes Blinds",
    "wof:placetype":"venue"
},
  "geometry": {"coordinates":[-1.8007559776,57.5014648438],"type":"Point"}
}