{
  "type": "Feature",
  "properties": {
    "iso:country":"GB",
    "sg:address":"1 Browning Avenue, Thornhill Park",
    "sg:city":"Southampton",
    "sg:classifiers":[
        {
            "category":"Wholesale",
            "subcategory":"Toys & Hobbies",
            "type":"Manufacturing & Wholesale Goods"
        }
    ],
    "sg:phone":"+44 23 8046 4117",
    "sg:postcode":"SO19 6PW",
    "sg:province":"Hampshire",
    "sg:tags":[
        "balloon",
        "novelty"
    ],
    "wof:name":"Specials",
    "wof:placetype":"venue"
},
  "geometry": {"coordinates":[-1.336462,50.913643],"type":"Point"}
}