{
  "type": "Feature",
  "properties": {
    "addr:full":"Middle Third Auchterarder Perth and Kinross PH3 1NJ",
    "addr:postcode":"ph3 1nj",
    "addr:street":"Middle;Auchterarder",
    "iso:country":"GB",
    "sg:address":"Middle Third",
    "sg:city":"Auchterarder",
    "sg:classifiers":[
        {
            "category":"Building & Trades",
            "subcategory":"Landscaping Services",
            "type":"Services"
        }
    ],
    "sg:phone":"+44 1764 663521",
    "sg:postcode":"PH3 1NJ",
    "sg:province":"Perth and Kinross",
    "sg:tags":[
        "horticultural",
        "consultant"
    ],
    "wof:name":"S A I Horticulture Ltd.",
    "wof:placetype":"venue"
},
  "geometry": {"coordinates":[-3.7113690376,56.294834137],"type":"Point"}
}