{
  "type": "Feature",
  "properties": {
    "addr:full":"44 Sollershott East Letchworth Hertfordshire SG6 3JW",
    "addr:housenumber":"44",
    "addr:postcode":"sg6 3jw",
    "addr:street":"Sollershott East Letchworth",
    "iso:country":"GB",
    "sg:address":"44 Sollershott East",
    "sg:city":"Letchworth",
    "sg:classifiers":[
        {
            "category":"Health Services",
            "subcategory":"Doctor",
            "type":"Services"
        }
    ],
    "sg:phone":"+44 1462 683637",
    "sg:postcode":"SG6 3JW",
    "sg:province":"Hertfordshire",
    "sg:tags":[
        "practitioners"
    ],
    "wof:name":"Drs Nevard Irvine & Davy",
    "wof:placetype":"venue"
},
  "geometry": {"coordinates":[-0.225679,51.972198],"type":"Point"}
}