{
  "type": "Feature",
  "properties": {
    "iso:country":"GB",
    "sg:address":"70 Machrie Road, Castlemilk",
    "sg:city":"Glasgow",
    "sg:classifiers":[
        {
            "category":"Organizations",
            "subcategory":"Community Association",
            "type":"Services"
        }
    ],
    "sg:phone":"+44 141 634 2673",
    "sg:postcode":"G45 0AS",
    "sg:province":"Glasgow City",
    "sg:tags":[
        "society",
        "housing"
    ],
    "wof:name":"Castlemilk East Housing Co-Operative",
    "wof:placetype":"venue"
},
  "geometry": {"coordinates":[-4.222514,55.808144],"type":"Point"}
}