{
  "type": "Feature",
  "properties": {
    "addr:full":"Europa House, Greenfield Road Colwyn Bay Conwy LL29 8EP",
    "addr:postcode":"ll29 8ep",
    "addr:street":"Greenfield Road",
    "iso:country":"GB",
    "sg:address":"Europa House, Greenfield Road",
    "sg:city":"Colwyn Bay",
    "sg:classifiers":[
        {
            "category":"Building & Trades",
            "subcategory":"Construction",
            "type":"Services"
        }
    ],
    "sg:postcode":"LL29 8EP",
    "sg:province":"Conwy",
    "sg:tags":[
        "builder"
    ],
    "wof:name":"R S Davies Ltd.",
    "wof:placetype":"venue"
},
  "geometry": {"coordinates":[-3.7215769291,53.2941513062],"type":"Point"}
}