{
  "type": "Feature",
  "properties": {
    "addr:full":"The School House, St Ives Road Huntingdon Bedfordshire PE28 9DU",
    "addr:postcode":"pe28 9du",
    "addr:street":"St Ives Road",
    "iso:country":"GB",
    "sg:address":"The School House, St Ives Road",
    "sg:city":"Huntingdon",
    "sg:classifiers":[
        {
            "category":"Education",
            "subcategory":"School",
            "type":"Public Place"
        }
    ],
    "sg:postcode":"PE28 9DU",
    "sg:province":"Bedfordshire",
    "sg:tags":[
        "local",
        "authority"
    ],
    "wof:name":"Flexo Consultancy & Training Ltd.",
    "wof:placetype":"venue"
},
  "geometry": {"coordinates":[-0.096418,52.31871],"type":"Point"}
}