{
  "type": "Feature",
  "properties": {
    "addr:full":"32 Westgate Shipley West Yorkshire BD18 3QX",
    "addr:housenumber":"32",
    "addr:postcode":"bd18 3qx",
    "addr:street":"Westgate Shipley West",
    "iso:country":"GB",
    "sg:address":"32 Westgate",
    "sg:city":"Shipley",
    "sg:classifiers":[
        {
            "category":"Shopping",
            "subcategory":"Pets & Pet Supplies",
            "type":"Retail Goods"
        }
    ],
    "sg:phone":"+44 1274 770588",
    "sg:postcode":"BD18 3QX",
    "sg:province":"West Yorkshire",
    "sg:tags":[
        "shop"
    ],
    "wof:name":"J Sager & Co",
    "wof:placetype":"venue"
},
  "geometry": {"coordinates":[-1.778608,53.834389],"type":"Point"}
}