{
  "type": "Feature",
  "properties": {
    "addr:full":"St. Michaels Works, 141 Blandford Rd, Hamworthy Poole Dorset BH15 4AT",
    "addr:housenumber":"141",
    "addr:postcode":"bh15 4at",
    "addr:street":"Blandford Rd",
    "iso:country":"GB",
    "sg:address":"St. Michaels Works, 141 Blandford Rd, Hamworthy",
    "sg:city":"Poole",
    "sg:classifiers":[
        {
            "category":"Building & Trades",
            "subcategory":"Equipment Rental",
            "type":"Services"
        }
    ],
    "sg:phone":"+44 1202 469812",
    "sg:postcode":"BH15 4AT",
    "sg:province":"Dorset",
    "sg:tags":[
        "diver"
    ],
    "wof:name":"Predator Custom Wetsuits",
    "wof:placetype":"venue"
},
  "geometry": {"coordinates":[-2.011234,50.721481],"type":"Point"}
}