{
  "type": "Feature",
  "properties": {
    "addr:full":"14 Hampden Square London Greater London N14 5JR",
    "addr:housenumber":"14",
    "addr:postcode":"n14 5jr",
    "addr:street":"Hampden Square",
    "iso:country":"GB",
    "sg:address":"14 Hampden Square",
    "sg:city":"London",
    "sg:classifiers":[
        {
            "category":"Shopping",
            "subcategory":"Baby Store",
            "type":"Retail Goods"
        }
    ],
    "sg:phone":"+44 20 8361 5808",
    "sg:postcode":"N14 5JR",
    "sg:province":"Greater London",
    "sg:tags":[
        "babywear",
        "childrens"
    ],
    "wof:name":"Street Boys",
    "wof:placetype":"venue"
},
  "geometry": {"coordinates":[-0.1428470016,51.6314964294],"type":"Point"}
}