{
  "type": "Feature",
  "properties": {
    "addr:full":"53 Rose Street Glasgow Glasgow City G3 6SF",
    "addr:housenumber":"53",
    "addr:postcode":"g3 6sf",
    "addr:street":"Rose Street",
    "iso:country":"GB",
    "sg:address":"53 Rose Street",
    "sg:city":"Glasgow",
    "sg:classifiers":[
        {
            "category":"Organizations",
            "subcategory":"Non-profit Organization",
            "type":"Services"
        }
    ],
    "sg:phone":"+44 141 332 3978",
    "sg:postcode":"G3 6SF",
    "sg:province":"Glasgow City",
    "sg:tags":[
        "charitable",
        "organisation",
        "voluntary",
        "charity"
    ],
    "wof:name":"San-Jai Chinese Project",
    "wof:placetype":"venue"
},
  "geometry": {"coordinates":[-4.2610898018,55.8675918579],"type":"Point"}
}