{
  "type": "Feature",
  "properties": {
    "addr:full":"Unit 20-21 Eastgate Centre Basildon Essex SS14 1AG",
    "addr:housenumber":"unit 20-21",
    "addr:postcode":"ss14 1ag",
    "addr:street":"Eastgate Centre",
    "iso:country":"GB",
    "sg:address":"Unit 20-21 Eastgate Centre",
    "sg:city":"Basildon",
    "sg:classifiers":[
        {
            "category":"Shopping",
            "subcategory":"Books",
            "type":"Retail Goods"
        }
    ],
    "sg:postcode":"SS14 1AG",
    "sg:province":"Essex",
    "sg:tags":[
        "bookseller"
    ],
    "wof:name":"Eastgate Christian Bookshop Ltd",
    "wof:placetype":"venue"
},
  "geometry": {"coordinates":[0.46053,51.569389],"type":"Point"}
}