{
  "type": "Feature",
  "properties": {
    "addr:full":"120 Cleethorpe Rd Grimsby Lincolnshire DN31 3HW",
    "addr:housenumber":"120",
    "addr:postcode":"dn31 3hw",
    "addr:street":"Cleethorpe Rd",
    "iso:country":"GB",
    "sg:address":"120 Cleethorpe Rd",
    "sg:city":"Grimsby",
    "sg:classifiers":[
        {
            "category":"Organizations",
            "subcategory":"Membership Organization",
            "type":"Services"
        }
    ],
    "sg:phone":"+44 1472 269610",
    "sg:postcode":"DN31 3HW",
    "sg:province":"Lincolnshire",
    "sg:tags":[
        "club"
    ],
    "wof:name":"Barons Members Club",
    "wof:placetype":"venue"
},
  "geometry": {"coordinates":[-0.0716010034,53.5748214722],"type":"Point"}
}