{
  "type": "Feature",
  "properties": {
    "addr:full":"Halton Business Forum, Victoria Square Widnes Cheshire WA8 7QZ",
    "addr:postcode":"wa8 7qz",
    "addr:street":"Victoria Square",
    "iso:country":"GB",
    "sg:address":"Halton Business Forum, Victoria Square",
    "sg:city":"Widnes",
    "sg:classifiers":[
        {
            "category":"Government",
            "subcategory":"Office",
            "type":"Public Place"
        }
    ],
    "sg:phone":"+44 151 420 9400",
    "sg:postcode":"WA8 7QZ",
    "sg:province":"Cheshire",
    "sg:tags":[
        "chamber",
        "commerce"
    ],
    "wof:name":"Halton Chamber of Commerce & Enterprise",
    "wof:placetype":"venue"
},
  "geometry": {"coordinates":[-2.7332439423,53.3740310669],"type":"Point"}
}