{
  "type": "Feature",
  "properties": {
    "iso:country":"GB",
    "sg:address":"50 High Street",
    "sg:city":"Salisbury",
    "sg:classifiers":[
        {
            "category":"Professional",
            "subcategory":"Lawyer & Legal Services",
            "type":"Services"
        }
    ],
    "sg:phone":"+44 1722 322272",
    "sg:postcode":"SP1 2NT",
    "sg:province":"Wiltshire",
    "sg:tags":[
        "solicitor"
    ],
    "wof:name":"David H N Davies",
    "wof:placetype":"venue"
},
  "geometry": {"coordinates":[-1.797714,51.067478],"type":"Point"}
}