{
  "type": "Feature",
  "properties": {
    "addr:full":"Finch House, 8 Finch Place Liverpool Merseyside L3 8PN",
    "addr:housenumber":"8",
    "addr:postcode":"l3 8pn",
    "addr:street":"Finch Place",
    "iso:country":"GB",
    "sg:address":"Finch House, 8 Finch Place",
    "sg:city":"Liverpool",
    "sg:classifiers":[
        {
            "category":"Shopping",
            "subcategory":"Stationery & Office Supplies",
            "type":"Retail Goods"
        },
        {
            "category":"Shopping",
            "subcategory":"Pharmacy",
            "type":"Retail Goods"
        }
    ],
    "sg:phone":"+44 151 298 2211",
    "sg:postcode":"L3 8PN",
    "sg:province":"Merseyside",
    "sg:tags":[
        "item",
        "pharmacist",
        "chemist",
        "promotional"
    ],
    "wof:name":"Barry Elman (Wholesale) Ltd.",
    "wof:placetype":"venue"
},
  "geometry": {"coordinates":[-2.9686539173,53.4110908508],"type":"Point"}
}