{
  "type": "Feature",
  "properties": {
    "addr:full":"Ermine Street, Little Stukeley Huntingdon Bedfordshire PE28 4BE",
    "addr:postcode":"pe28 4be",
    "addr:street":"Ermine Street",
    "iso:country":"GB",
    "sg:address":"Ermine Street, Little Stukeley",
    "sg:city":"Huntingdon",
    "sg:classifiers":[
        {
            "category":"Building & Trades",
            "subcategory":"Landscaping Services",
            "type":"Services"
        }
    ],
    "sg:postcode":"PE28 4BE",
    "sg:province":"Bedfordshire",
    "sg:tags":[
        "landscape",
        "contractor"
    ],
    "wof:name":"Team Plant Ltd.",
    "wof:placetype":"venue"
},
  "geometry": {"coordinates":[-0.2094659954,52.3554534912],"type":"Point"}
}