{
  "type": "Feature",
  "properties": {
    "addr:full":"2 & 2a Church Lane Banbury Oxfordshire OX16 5LR",
    "addr:housenumber":"2 & 2a",
    "addr:postcode":"ox16 5lr",
    "addr:street":"Church Lane",
    "iso:country":"GB",
    "sg:address":"2 & 2a Church Lane",
    "sg:city":"Banbury",
    "sg:classifiers":[
        {
            "category":"Food & Beverages",
            "subcategory":"Meat & Fish",
            "type":"Retail Goods"
        }
    ],
    "sg:phone":"+44 1295 262387",
    "sg:postcode":"OX16 5LR",
    "sg:province":"Oxfordshire",
    "sg:tags":[
        "butcher"
    ],
    "wof:name":"STEPHEN W BETTS",
    "wof:placetype":"venue"
},
  "geometry": {"coordinates":[-1.3372700214,52.0616188049],"type":"Point"}
}