{
  "type": "Feature",
  "properties": {
    "iso:country":"GB",
    "sg:address":"Bedford Rd",
    "sg:city":"Bedford",
    "sg:classifiers":[
        {
            "category":"Place Of Worship",
            "type":"Public Place"
        }
    ],
    "sg:phone":"+44 1234 854788",
    "sg:postcode":"MK42 8QB",
    "sg:province":"Bedfordshire",
    "wof:name":"Church Of The Transfiguration C Of E",
    "wof:placetype":"venue"
},
  "geometry": {"coordinates":[-0.480479,52.125832],"type":"Point"}
}