{
  "type": "Feature",
  "properties": {
    "addr:full":"Hazeley Farm, Hazeley Heath, Hook Basingstoke Berkshire RG27 8NA",
    "addr:postcode":"rg27 8na",
    "addr:street":"Hook",
    "iso:country":"GB",
    "sg:address":"Hazeley Farm, Hazeley Heath, Hook",
    "sg:city":"Basingstoke",
    "sg:classifiers":[
        {
            "category":"Farming",
            "subcategory":"Dairy Farm",
            "type":"Manufacturing & Wholesale Goods"
        },
        {
            "category":"Professional",
            "subcategory":"Business Services",
            "type":"Services"
        }
    ],
    "sg:postcode":"RG27 8NA",
    "sg:province":"Berkshire",
    "sg:tags":[
        "hospitality",
        "corporate"
    ],
    "wof:name":"Bowman Leisure",
    "wof:placetype":"venue"
},
  "geometry": {"coordinates":[-0.915549,51.314274],"type":"Point"}
}