{
  "type": "Feature",
  "properties": {
    "addr:full":"Rear Of 314 Eastcote Lane Harrow Greater London HA2 9AH",
    "addr:postcode":"ha2 9ah",
    "addr:street":"Eastcote Lane",
    "iso:country":"GB",
    "sg:address":"Rear Of 314 Eastcote Lane",
    "sg:city":"Harrow",
    "sg:classifiers":[
        {
            "category":"Autos & Motor Vehicles",
            "subcategory":"Motorcycle Sales",
            "type":"Retail Goods"
        }
    ],
    "sg:phone":"+44 20 8423 3122",
    "sg:postcode":"HA2 9AH",
    "sg:province":"Greater London",
    "wof:name":"A P C Motor Services Ltd",
    "wof:placetype":"venue"
},
  "geometry": {"coordinates":[-0.369274,51.568596],"type":"Point"}
}