{
  "type": "Feature",
  "properties": {
    "addr:full":"Berthabley, Nantmel Rhayader Powys LD6 5NL",
    "addr:postcode":"ld6 5nl",
    "addr:street":"Rhayader",
    "iso:country":"GB",
    "sg:address":"Berthabley, Nantmel",
    "sg:city":"Rhayader",
    "sg:classifiers":[
        {
            "category":"Farming",
            "subcategory":"Livestock Farm",
            "type":"Manufacturing & Wholesale Goods"
        }
    ],
    "sg:phone":"+44 1597 810249",
    "sg:postcode":"LD6 5NL",
    "sg:province":"Powys",
    "sg:tags":[
        "others"
    ],
    "wof:name":"G E J Rees & Sons",
    "wof:placetype":"venue"
},
  "geometry": {"coordinates":[-3.51158,52.302761],"type":"Point"}
}