{
  "type": "Feature",
  "properties": {
    "addr:full":"The Sawmill, Harewood Bridge Leeds North Yorkshire LS17 9LW",
    "addr:postcode":"ls17 9lw",
    "addr:street":"Harewood Bridge",
    "iso:country":"GB",
    "sg:address":"The Sawmill, Harewood Bridge",
    "sg:city":"Leeds",
    "sg:classifiers":[
        {
            "category":"Home & Garden",
            "subcategory":"Building Materials",
            "type":"Retail Goods"
        }
    ],
    "sg:phone":"+44 113 288 6323",
    "sg:postcode":"LS17 9LW",
    "sg:province":"North Yorkshire",
    "sg:tags":[
        "fencing"
    ],
    "wof:name":"Fadeable Ltd.",
    "wof:placetype":"venue"
},
  "geometry": {"coordinates":[-1.511964,53.90234],"type":"Point"}
}