{
  "type": "Feature",
  "properties": {
    "iso:country":"GB",
    "sg:address":"42 Ashgrove Crescent, Billinge",
    "sg:city":"Wigan",
    "sg:classifiers":[
        {
            "category":"Professional",
            "subcategory":"Engineering",
            "type":"Services"
        }
    ],
    "sg:postcode":"WN5 7NH",
    "sg:province":"Lancashire",
    "sg:tags":[
        "contractor",
        "electrical",
        "engineer"
    ],
    "wof:name":"Ash Electrical Services",
    "wof:placetype":"venue"
},
  "geometry": {"coordinates":[-2.710824,53.500069],"type":"Point"}
}