{
  "type": "Feature",
  "properties": {
    "iso:country":"GB",
    "sg:address":"Unit 1, Foundry Industrial Estate, Rickshaw Lane",
    "sg:city":"Pudsey",
    "sg:classifiers":[
        {
            "category":"Home & Garden",
            "subcategory":"Building Materials",
            "type":"Retail Goods"
        }
    ],
    "sg:phone":"+44 113 256 3403",
    "sg:postcode":"LS28 6BN",
    "sg:province":"West Yorkshire",
    "sg:tags":[
        "insulation",
        "installers"
    ],
    "wof:name":"John Alderson & Son Ltd.",
    "wof:placetype":"venue"
},
  "geometry": {"coordinates":[-1.6562689543,53.7976837158],"type":"Point"}
}