{
  "type": "Feature",
  "properties": {
    "addr:full":"Station Street Stockton-on-tees Durham TS20 2AB",
    "addr:postcode":"ts20 2ab",
    "addr:street":"Station Street",
    "iso:country":"GB",
    "sg:address":"Station Street",
    "sg:city":"Stockton-on-tees",
    "sg:classifiers":[
        {
            "category":"Home & Garden",
            "subcategory":"Building Materials",
            "type":"Retail Goods"
        }
    ],
    "sg:phone":"+44 1642 251292",
    "sg:postcode":"TS20 2AB",
    "sg:province":"Durham",
    "sg:tags":[
        "ready",
        "mixed",
        "concrete"
    ],
    "wof:name":"Tarmac",
    "wof:placetype":"venue"
},
  "geometry": {"coordinates":[-1.3102289438,54.5714988708],"type":"Point"}
}