{
  "type": "Feature",
  "properties": {
    "addr:full":"18 Sutton Court Road Uxbridge Greater London UB10 9HP",
    "addr:housenumber":"18",
    "addr:postcode":"ub10 9hp",
    "addr:street":"Sutton Court Road",
    "iso:country":"GB",
    "sg:address":"18 Sutton Court Road",
    "sg:city":"Uxbridge",
    "sg:classifiers":[
        {
            "category":"Home & Garden",
            "subcategory":"Hardware",
            "type":"Retail Goods"
        }
    ],
    "sg:phone":"+44 1895 235215",
    "sg:postcode":"UB10 9HP",
    "sg:province":"Greater London",
    "wof:name":"Elmwood Hardware",
    "wof:placetype":"venue"
},
  "geometry": {"coordinates":[-0.449202,51.541111],"type":"Point"}
}