{
  "type": "Feature",
  "properties": {
    "addr:full":"9 Derby St Manchester Greater Manchester M8 8QE",
    "addr:housenumber":"9",
    "addr:postcode":"m8 8qe",
    "addr:street":"Derby St",
    "iso:country":"GB",
    "sg:address":"9 Derby St",
    "sg:city":"Manchester",
    "sg:classifiers":[
        {
            "category":"Professional",
            "subcategory":"Computer Services",
            "type":"Services"
        }
    ],
    "sg:phone":"+44 161 839 8220",
    "sg:postcode":"M8 8QE",
    "sg:province":"Greater Manchester",
    "sg:tags":[
        "consultant"
    ],
    "wof:name":"Centralteam Ltd",
    "wof:placetype":"venue"
},
  "geometry": {"coordinates":[-2.237958,53.493923],"type":"Point"}
}