{
  "type": "Feature",
  "properties": {
    "addr:full":"9 Blenheim Chase Leigh On Sea Essex SS9 3BZ",
    "addr:housenumber":"9",
    "addr:postcode":"ss9 3bz",
    "addr:street":"Blenheim Chase",
    "iso:country":"GB",
    "sg:address":"9 Blenheim Chase",
    "sg:city":"Leigh On Sea",
    "sg:classifiers":[
        {
            "category":"Health Services",
            "subcategory":"Doctor",
            "type":"Services"
        }
    ],
    "sg:phone":"+44 1702 470336",
    "sg:postcode":"SS9 3BZ",
    "sg:province":"Essex",
    "sg:tags":[
        "practitioners"
    ],
    "wof:name":"Sathanandan, S",
    "wof:placetype":"venue"
},
  "geometry": {"coordinates":[0.6481770277,51.5551452637],"type":"Point"}
}