{
  "type": "Feature",
  "properties": {
    "addr:full":"56 Harford St Trowbridge Wiltshire BA14 7HJ",
    "addr:housenumber":"56",
    "addr:postcode":"ba14 7hj",
    "addr:street":"Harford St",
    "iso:country":"GB",
    "sg:address":"56 Harford St",
    "sg:city":"Trowbridge",
    "sg:classifiers":[
        {
            "category":"Retail",
            "subcategory":"Driving School",
            "type":"Services"
        }
    ],
    "sg:phone":"+44 1225 766656",
    "sg:postcode":"BA14 7HJ",
    "sg:province":"Wiltshire",
    "sg:tags":[
        "instruction",
        "cycling",
        "motor"
    ],
    "wof:name":"Phoenix Motorcycle Training",
    "wof:placetype":"venue"
},
  "geometry": {"coordinates":[-2.2010960579,51.3213653564],"type":"Point"}
}