{
  "type": "Feature",
  "properties": {
    "addr:full":"Sunlight House, Pobox 85, Quay Street Manchester Greater Manchester M60 3JA",
    "addr:housenumber":"85",
    "addr:postcode":"m60 3ja",
    "addr:street":"Pobox;Quay Street",
    "iso:country":"GB",
    "sg:address":"Sunlight House, Pobox 85, Quay Street",
    "sg:city":"Manchester",
    "sg:classifiers":[
        {
            "category":"Building & Trades",
            "subcategory":"Construction",
            "type":"Services"
        },
        {
            "category":"Professional",
            "subcategory":"Art Services",
            "type":"Services"
        },
        {
            "category":"Communications",
            "type":"Services"
        },
        {
            "category":"Real Estate",
            "subcategory":"Architect",
            "type":"Services"
        }
    ],
    "sg:phone":"+44 161 834 8441",
    "sg:postcode":"M60 3JA",
    "sg:province":"Greater Manchester",
    "sg:tags":[
        "roofing",
        "broadcasting",
        "design",
        "consultant"
    ],
    "wof:name":"BDP DUBLIN LTD",
    "wof:placetype":"venue"
},
  "geometry": {"coordinates":[-2.2504498959,53.4804992676],"type":"Point"}
}