{
  "type": "Feature",
  "properties": {
    "iso:country":"GB",
    "sg:address":"518 Stratford Road, Sparkhill",
    "sg:city":"Birmingham",
    "sg:classifiers":[
        {
            "category":"Professional",
            "subcategory":"Computer Services",
            "type":"Services"
        }
    ],
    "sg:phone":"+44 121 472 4955",
    "sg:postcode":"B11 4AJ",
    "sg:province":"West Midlands",
    "sg:tags":[
        "information"
    ],
    "wof:name":"Community Forum",
    "wof:placetype":"venue"
},
  "geometry": {"coordinates":[-1.865708,52.453091],"type":"Point"}
}