{
  "type": "Feature",
  "properties": {
    "addr:full":"103 Scott Road Sheffield South Yorkshire S4 7BG",
    "addr:housenumber":"103",
    "addr:postcode":"s4 7bg",
    "addr:street":"Scott Road",
    "iso:country":"GB",
    "sg:address":"103 Scott Road",
    "sg:city":"Sheffield",
    "sg:classifiers":[
        {
            "category":"Shopping",
            "subcategory":"Department Store",
            "type":"Retail Goods"
        }
    ],
    "sg:phone":"+44 114 242 6284",
    "sg:postcode":"S4 7BG",
    "sg:province":"South Yorkshire",
    "wof:name":"Khan Bros",
    "wof:placetype":"venue"
},
  "geometry": {"coordinates":[-1.4562280178,53.4012908936],"type":"Point"}
}