{
  "type": "Feature",
  "properties": {
    "addr:full":"The Woodyard, The Gears, Goldsithney Penzance Cornwall TR20 9LD",
    "addr:postcode":"tr20 9ld",
    "iso:country":"GB",
    "sg:address":"The Woodyard, The Gears, Goldsithney",
    "sg:city":"Penzance",
    "sg:classifiers":[
        {
            "category":"Building & Trades",
            "subcategory":"Landscaping Services",
            "type":"Services"
        }
    ],
    "sg:phone":"+44 1736 710972",
    "sg:postcode":"TR20 9LD",
    "sg:province":"Cornwall",
    "sg:tags":[
        "forestry",
        "tree"
    ],
    "wof:name":"Nick Berryman Tree Surgery",
    "wof:placetype":"venue"
},
  "geometry": {"coordinates":[-5.436754,50.125099],"type":"Point"}
}