{
  "type": "Feature",
  "properties": {
    "addr:full":"12 Church Avenue, Falfield Wotton-under-edge Gloucestershire GL12 8BY",
    "addr:housenumber":"12",
    "addr:postcode":"gl12 8by",
    "addr:street":"Church Avenue",
    "iso:country":"GB",
    "sg:address":"12 Church Avenue, Falfield",
    "sg:city":"Wotton-under-edge",
    "sg:classifiers":[
        {
            "category":"Utilities",
            "subcategory":"Natural Gas",
            "type":"Services"
        }
    ],
    "sg:postcode":"GL12 8BY",
    "sg:province":"Gloucestershire",
    "sg:tags":[
        "control",
        "energy",
        "management",
        "system"
    ],
    "wof:name":"G L Heating & Plumbing",
    "wof:placetype":"venue"
},
  "geometry": {"coordinates":[-2.4620380402,51.6361122131],"type":"Point"}
}