{
  "type": "Feature",
  "properties": {
    "iso:country":"GB",
    "sg:address":"22 Main Street",
    "sg:city":"Cumnock",
    "sg:classifiers":[
        {
            "category":"Food & Beverages",
            "subcategory":"Meat & Fish",
            "type":"Retail Goods"
        }
    ],
    "sg:postcode":"KA18 3RA",
    "sg:province":"East Ayrshire",
    "sg:tags":[
        "butcher"
    ],
    "wof:name":"Dunlop Butchers",
    "wof:placetype":"venue"
},
  "geometry": {"coordinates":[-4.067333,55.521374],"type":"Point"}
}