{
  "type": "Feature",
  "properties": {
    "addr:full":"3 Lairum Rise, Clifford Wetherby West Yorkshire LS23 6HG",
    "addr:housenumber":"3",
    "addr:postcode":"ls23 6hg",
    "addr:street":"Lairum Rise",
    "iso:country":"GB",
    "sg:address":"3 Lairum Rise, Clifford",
    "sg:city":"Wetherby",
    "sg:classifiers":[
        {
            "category":"Farming",
            "subcategory":"Dairy Farm",
            "type":"Manufacturing & Wholesale Goods"
        }
    ],
    "sg:phone":"+44 1937 842259",
    "sg:postcode":"LS23 6HG",
    "sg:province":"West Yorkshire",
    "wof:name":"Stewart Cornforth",
    "wof:placetype":"venue"
},
  "geometry": {"coordinates":[-1.3536969423,53.8948631287],"type":"Point"}
}