{
  "type": "Feature",
  "properties": {
    "iso:country":"GB",
    "sg:address":"146 Upper St",
    "sg:city":"Islington",
    "sg:classifiers":[
        {
            "category":"Shopping",
            "subcategory":"Clothing, Apparel, & Fashions",
            "type":"Retail Goods"
        }
    ],
    "sg:phone":"+44 20 7704 2131",
    "sg:postcode":"N1 1QY",
    "sg:province":"Greater London",
    "sg:tags":[
        "ladieswear"
    ],
    "wof:name":"Phase Two",
    "wof:placetype":"venue"
},
  "geometry": {"coordinates":[-0.102698,51.540115],"type":"Point"}
}