{
  "type": "Feature",
  "properties": {
    "addr:full":"45 West Street Leek Staffordshire ST13 8AW",
    "addr:housenumber":"45",
    "addr:postcode":"st13 8aw",
    "addr:street":"West Street",
    "iso:country":"GB",
    "sg:address":"45 West Street",
    "sg:city":"Leek",
    "sg:classifiers":[
        {
            "category":"Professional",
            "subcategory":"Art Services",
            "type":"Services"
        }
    ],
    "sg:phone":"+44 1538 399919",
    "sg:postcode":"ST13 8AW",
    "sg:province":"Staffordshire",
    "sg:tags":[
        "decorating",
        "painting"
    ],
    "wof:name":"Decorite",
    "wof:placetype":"venue"
},
  "geometry": {"coordinates":[-2.032404,53.106316],"type":"Point"}
}