{
  "type": "Feature",
  "properties": {
    "iso:country":"GB",
    "sg:address":"Sovereign House, 242 Charminster Road",
    "sg:city":"Bournemouth",
    "sg:classifiers":[
        {
            "category":"Professional",
            "subcategory":"Computer Services",
            "type":"Services"
        }
    ],
    "sg:phone":"+44 1202 548888",
    "sg:postcode":"BH8 9RP",
    "sg:province":"Dorset",
    "sg:tags":[
        "development",
        "system",
        "software"
    ],
    "wof:name":"Aspect Systems",
    "wof:placetype":"venue"
},
  "geometry": {"coordinates":[-1.8635519743,50.7395706177],"type":"Point"}
}