{
  "type": "Feature",
  "properties": {
    "iso:country":"GB",
    "sg:address":"66 Daisy Hill",
    "sg:city":"Dewsbury",
    "sg:classifiers":[
        {
            "category":"Professional",
            "subcategory":"Lawyer & Legal Services",
            "type":"Services"
        }
    ],
    "sg:phone":"+44 1924 455515",
    "sg:postcode":"WF13 1LS",
    "sg:province":"West Yorkshire",
    "sg:tags":[
        "solicitor"
    ],
    "wof:name":"Hellewell Pasley & Brewer",
    "wof:placetype":"venue"
},
  "geometry": {"coordinates":[-1.631183,53.691151],"type":"Point"}
}