{
  "type": "Feature",
  "properties": {
    "iso:country":"GB",
    "sg:address":"57 Surbiton Road",
    "sg:city":"Kingston-upon-thames",
    "sg:classifiers":[
        {
            "category":"Shopping",
            "subcategory":"Clothing, Apparel, & Fashions",
            "type":"Retail Goods"
        }
    ],
    "sg:phone":"+44 20 8549 9266",
    "sg:postcode":"KT1 2HG",
    "sg:province":"Greater London",
    "sg:tags":[
        "shop"
    ],
    "wof:name":"Rockdale Trading Co. Ltd.",
    "wof:placetype":"venue"
},
  "geometry": {"coordinates":[-0.303847,51.401382],"type":"Point"}
}