{
  "type": "Feature",
  "properties": {
    "iso:country":"GB",
    "sg:address":"Oakwood Rd",
    "sg:city":"Woking",
    "sg:classifiers":[
        {
            "category":"Education",
            "subcategory":"School",
            "type":"Public Place"
        }
    ],
    "sg:phone":"+44 1483 474938",
    "sg:postcode":"GU21 1UU",
    "sg:province":"Surrey",
    "sg:tags":[
        "local",
        "authority"
    ],
    "wof:name":"Hermitage & Oak Tree School Kitchen",
    "wof:placetype":"venue"
},
  "geometry": {"coordinates":[-0.608084,51.308701],"type":"Point"}
}