{
  "type": "Feature",
  "properties": {
    "addr:full":"Brunswick Mill Macclesfield Cheshire SK11 6JN",
    "addr:postcode":"sk11 6jn",
    "addr:street":"Brunswick",
    "iso:country":"GB",
    "sg:address":"Brunswick Mill",
    "sg:city":"Macclesfield",
    "sg:classifiers":[
        {
            "category":"Professional",
            "type":"Services"
        }
    ],
    "sg:phone":"+44 1625 435030",
    "sg:postcode":"SK11 6JN",
    "sg:province":"Cheshire",
    "sg:tags":[
        "exhibition"
    ],
    "wof:name":"A R C Exhibitions",
    "wof:placetype":"venue"
},
  "geometry": {"coordinates":[-2.125756,53.255669],"type":"Point"}
}