{
  "type": "Feature",
  "properties": {
    "addr:full":"Tudor Close, Polegate Road Hailsham East Sussex BN27 3PG",
    "addr:postcode":"bn27 3pg",
    "addr:street":"Tudor Close Polegate Road",
    "iso:country":"GB",
    "sg:address":"Tudor Close, Polegate Road",
    "sg:city":"Hailsham",
    "sg:classifiers":[
        {
            "category":"Building & Trades",
            "subcategory":"Construction",
            "type":"Services"
        }
    ],
    "sg:phone":"+44 1323 845822",
    "sg:postcode":"BN27 3PG",
    "sg:province":"East Sussex",
    "sg:tags":[
        "builder"
    ],
    "wof:name":"M J Keeley",
    "wof:placetype":"venue"
},
  "geometry": {"coordinates":[0.2565200031,50.8653831482],"type":"Point"}
}