{
  "type": "Feature",
  "properties": {
    "iso:country":"GB",
    "sg:address":"44 Arndale Centre",
    "sg:city":"Manchester",
    "sg:classifiers":[
        {
            "category":"Food & Beverages",
            "subcategory":"Fruits & Vegetables",
            "type":"Retail Goods"
        }
    ],
    "sg:postcode":"M4 2HU",
    "sg:province":"Greater Manchester",
    "sg:tags":[
        "greengrocer"
    ],
    "wof:name":"Weigh & Save",
    "wof:placetype":"venue"
},
  "geometry": {"coordinates":[-2.24037,53.485359],"type":"Point"}
}