{
  "type": "Feature",
  "properties": {
    "addr:full":"Dewsbury Road, Off Victoria Road, Fenton Stoke-on-trent Staffordshire ST4 2HS",
    "addr:postcode":"staffordshire st4 2hs",
    "addr:street":"Dewsbury Road Off Victoria Road",
    "iso:country":"GB",
    "sg:address":"Dewsbury Road, Off Victoria Road, Fenton",
    "sg:city":"Stoke-on-trent",
    "sg:classifiers":[
        {
            "category":"Shopping",
            "subcategory":"Gifts & Souvenirs",
            "type":"Retail Goods"
        }
    ],
    "sg:phone":"+44 1782 743460",
    "sg:postcode":"ST4 2HS",
    "sg:province":"Staffordshire",
    "sg:tags":[
        "shop"
    ],
    "wof:name":"Portmeirion Factory Shop",
    "wof:placetype":"venue"
},
  "geometry": {"coordinates":[-2.1593110561,53.0113792419],"type":"Point"}
}