{
  "type": "Feature",
  "properties": {
    "addr:full":"Office, 71 The Close Salisbury Wiltshire SP1 2ER",
    "addr:housenumber":"71",
    "addr:postcode":"sp1 2er",
    "addr:street":"The Close",
    "iso:country":"GB",
    "sg:address":"Office, 71 The Close",
    "sg:city":"Salisbury",
    "sg:classifiers":[
        {
            "category":"Place Of Worship",
            "type":"Public Place"
        }
    ],
    "sg:phone":"+44 1722 334031",
    "sg:postcode":"SP1 2ER",
    "sg:province":"Wiltshire",
    "wof:name":"Salisbury Bishop Of",
    "wof:placetype":"venue"
},
  "geometry": {"coordinates":[-1.7922600508,51.0653953552],"type":"Point"}
}