{
  "type": "Feature",
  "properties": {
    "addr:full":"63 Station Road Taunton Somerset TA1 1PA",
    "addr:housenumber":"63",
    "addr:postcode":"ta1 1pa",
    "addr:street":"Station Road",
    "iso:country":"GB",
    "sg:address":"63 Station Road",
    "sg:city":"Taunton",
    "sg:classifiers":[
        {
            "category":"Recreation",
            "subcategory":"Fishing",
            "type":"Entertainment"
        }
    ],
    "sg:phone":"+44 1823 282518",
    "sg:postcode":"TA1 1PA",
    "sg:province":"Somerset",
    "sg:tags":[
        "angling"
    ],
    "wof:name":"Topp Tackle",
    "wof:placetype":"venue"
},
  "geometry": {"coordinates":[-3.103851,51.020947],"type":"Point"}
}