{
  "type": "Feature",
  "properties": {
    "addr:full":"192 Lancaster Road Enfield Greater London EN2 0JH",
    "addr:housenumber":"192",
    "addr:postcode":"en2 0jh",
    "addr:street":"Lancaster Road",
    "iso:country":"GB",
    "sg:address":"192 Lancaster Road",
    "sg:city":"Enfield",
    "sg:classifiers":[
        {
            "category":"Military Area",
            "subcategory":"Army Base",
            "type":"Public Place"
        },
        {
            "category":"Shopping",
            "subcategory":"Crafts & Fabrics",
            "type":"Retail Goods"
        }
    ],
    "sg:phone":"+44 20 8363 3112",
    "sg:postcode":"EN2 0JH",
    "sg:province":"Greater London",
    "sg:tags":[
        "supplier",
        "joinery",
        "centre"
    ],
    "wof:name":"Lancaster Joinery Works",
    "wof:placetype":"venue"
},
  "geometry": {"coordinates":[-0.0854270011,51.6638221741],"type":"Point"}
}