{
  "type": "Feature",
  "properties": {
    "iso:country":"GB",
    "sg:address":"59-61 Knights Hill",
    "sg:city":"Tulse Hill",
    "sg:classifiers":[
        {
            "category":"Autos & Motor Vehicles",
            "subcategory":"Automobile Sales",
            "type":"Retail Goods"
        }
    ],
    "sg:phone":"+44 20 8670 4020",
    "sg:postcode":"SE27 0HN",
    "sg:province":"Greater London",
    "sg:tags":[
        "car"
    ],
    "wof:name":"Quality Used Cars",
    "wof:placetype":"venue"
},
  "geometry": {"coordinates":[-0.104131,51.429974],"type":"Point"}
}