{
  "type": "Feature",
  "properties": {
    "addr:full":"Hill Top Community Centre, Hill Top West Bromwich West Midlands B70 0RZ",
    "addr:postcode":"b70 0rz",
    "addr:street":"Hill Top West",
    "iso:country":"GB",
    "sg:address":"Hill Top Community Centre, Hill Top",
    "sg:city":"West Bromwich",
    "sg:classifiers":[
        {
            "category":"Health Services",
            "subcategory":"Nursing And Care Facility",
            "type":"Services"
        }
    ],
    "sg:phone":"+44 121 505 7799",
    "sg:postcode":"B70 0RZ",
    "sg:province":"West Midlands",
    "sg:tags":[
        "agency"
    ],
    "wof:name":"Pioneer Care Ltd.",
    "wof:placetype":"venue"
},
  "geometry": {"coordinates":[-2.0112140179,52.5369567871],"type":"Point"}
}