{
  "type": "Feature",
  "properties": {
    "addr:full":"93 Dorset Road Christchurch Dorset BH23 3DE",
    "addr:housenumber":"93",
    "addr:postcode":"bh23 3de",
    "addr:street":"Dorset Road",
    "iso:country":"GB",
    "sg:address":"93 Dorset Road",
    "sg:city":"Christchurch",
    "sg:classifiers":[
        {
            "category":"Retail",
            "subcategory":"Auto Repair",
            "type":"Services"
        }
    ],
    "sg:phone":"+44 1202 475809",
    "sg:postcode":"BH23 3DE",
    "sg:province":"Dorset",
    "sg:tags":[
        "modification",
        "garage"
    ],
    "wof:name":"Ace Mobile Autos",
    "wof:placetype":"venue"
},
  "geometry": {"coordinates":[-1.752535,50.743008],"type":"Point"}
}