{
  "type": "Feature",
  "properties": {
    "addr:full":"85 Poole Rd, Westbourne Bournemouth Dorset BH4 9BB",
    "addr:housenumber":"85",
    "addr:postcode":"bh4 9bb",
    "addr:street":"Poole Rd",
    "iso:country":"GB",
    "sg:address":"85 Poole Rd, Westbourne",
    "sg:city":"Bournemouth",
    "sg:classifiers":[
        {
            "category":"Professional",
            "subcategory":"Management & Consulting",
            "type":"Services"
        }
    ],
    "sg:phone":"+44 1202 752751",
    "sg:postcode":"BH4 9BB",
    "sg:province":"Dorset",
    "sg:tags":[
        "marketing",
        "consultant"
    ],
    "wof:name":"IMS Ltd",
    "wof:placetype":"venue"
},
  "geometry": {"coordinates":[-1.90361,50.72303],"type":"Point"}
}