{
  "type": "Feature",
  "properties": {
    "addr:full":"Unit 16, North Quay, Shipyard Estate Faversham Kent ME13 7DL",
    "addr:housenumber":"unit 16",
    "addr:postcode":"me13 7dl",
    "addr:street":"North Quay Shipyard Estate",
    "iso:country":"GB",
    "sg:address":"Unit 16, North Quay, Shipyard Estate",
    "sg:city":"Faversham",
    "sg:classifiers":[
        {
            "category":"Building & Trades",
            "subcategory":"Construction",
            "type":"Services"
        }
    ],
    "sg:phone":"+44 1795 591476",
    "sg:postcode":"ME13 7DL",
    "sg:province":"Kent",
    "sg:tags":[
        "joinery"
    ],
    "wof:name":"North Quay Trading Ltd.",
    "wof:placetype":"venue"
},
  "geometry": {"coordinates":[0.8893799782,51.3169975281],"type":"Point"}
}