{
  "type": "Feature",
  "properties": {
    "iso:country":"GB",
    "sg:address":"1 St Marys Garth, Great Urswick",
    "sg:city":"Ulverston",
    "sg:classifiers":[
        {
            "category":"Building & Trades",
            "subcategory":"Construction",
            "type":"Services"
        }
    ],
    "sg:phone":"+44 1229 581667",
    "sg:postcode":"LA12 0TD",
    "sg:province":"Cumbria",
    "sg:tags":[
        "glazier"
    ],
    "wof:name":"E Woodend",
    "wof:placetype":"venue"
},
  "geometry": {"coordinates":[-3.120568037,54.1627426147],"type":"Point"}
}