{
  "type": "Feature",
  "properties": {
    "addr:full":"103 Reddish Lane, Denton Manchester Greater Manchester M34 2NF",
    "addr:housenumber":"103",
    "addr:postcode":"m34 2nf",
    "addr:street":"Reddish Lane",
    "iso:country":"GB",
    "sg:address":"103 Reddish Lane, Denton",
    "sg:city":"Manchester",
    "sg:classifiers":[
        {
            "category":"Travel",
            "subcategory":"Travel Agent",
            "type":"Entertainment"
        }
    ],
    "sg:phone":"+44 161 223 1952",
    "sg:postcode":"M34 2NF",
    "sg:province":"Greater Manchester",
    "wof:name":"Going Places",
    "wof:placetype":"venue"
},
  "geometry": {"coordinates":[-2.248809,53.479622],"type":"Point"}
}