{
  "type": "Feature",
  "properties": {
    "iso:country":"GB",
    "sg:address":"102 Loddon Bridge Road, Woodley",
    "sg:city":"Reading",
    "sg:classifiers":[
        {
            "category":"Communications",
            "type":"Services"
        }
    ],
    "sg:phone":"+44 118 961 8441",
    "sg:postcode":"RG5 4AW",
    "sg:province":"Berkshire",
    "sg:tags":[
        "telecommunication"
    ],
    "wof:name":"Freephone U K Ltd.",
    "wof:placetype":"venue"
},
  "geometry": {"coordinates":[-0.898355,51.442909],"type":"Point"}
}