{
  "type": "Feature",
  "properties": {
    "addr:full":"5 Tolpits Lane Caravan Site Watford Hertfordshire WD18 9SW",
    "addr:housenumber":"5",
    "addr:postcode":"wd18 9sw",
    "addr:street":"Tolpits Lane",
    "iso:country":"GB",
    "sg:address":"5 Tolpits Lane Caravan Site",
    "sg:city":"Watford",
    "sg:classifiers":[
        {
            "category":"Building & Trades",
            "subcategory":"Landscaping Services",
            "type":"Services"
        }
    ],
    "sg:phone":"+44 1923 241709",
    "sg:postcode":"WD18 9SW",
    "sg:province":"Hertfordshire",
    "sg:tags":[
        "forestry",
        "tree"
    ],
    "wof:name":"Tree Topping & Fencing Services",
    "wof:placetype":"venue"
},
  "geometry": {"coordinates":[-0.42204,51.640961],"type":"Point"}
}