{
  "type": "Feature",
  "properties": {
    "addr:full":"Clarks Hay, South Cerney Cirencester Gloucestershire GL7 5UA",
    "addr:postcode":"gl7 5ua",
    "addr:street":"Hay",
    "iso:country":"GB",
    "sg:address":"Clarks Hay, South Cerney",
    "sg:city":"Cirencester",
    "sg:classifiers":[
        {
            "category":"Government",
            "subcategory":"Post Office",
            "type":"Public Place"
        }
    ],
    "sg:postcode":"GL7 5UA",
    "sg:province":"Gloucestershire",
    "wof:name":"South Cerney Post Office",
    "wof:placetype":"venue"
},
  "geometry": {"coordinates":[-1.9535410404,51.718547821],"type":"Point"}
}