{
  "type": "Feature",
  "properties": {
    "iso:country":"GB",
    "sg:address":"36-38 Heathcoat Street",
    "sg:city":"Nottingham",
    "sg:classifiers":[
        {
            "category":"Restaurant",
            "type":"Food & Drink"
        },
        {
            "category":"Home & Garden",
            "subcategory":"Hardware",
            "type":"Retail Goods"
        }
    ],
    "sg:phone":"+44 115 959 9800",
    "sg:postcode":"NG1 3AA",
    "sg:province":"Nottinghamshire",
    "sg:tags":[
        "part",
        "accessory"
    ],
    "wof:name":"Bentons Brasserie Ltd.",
    "wof:placetype":"venue"
},
  "geometry": {"coordinates":[-1.14329,52.954956],"type":"Point"}
}