{
  "type": "Feature",
  "properties": {
    "addr:full":"Horncastle Road, Wragby Market Rasen Lincolnshire LN8 5RB",
    "addr:postcode":"ln8 5rb",
    "addr:street":"Horncastle Road;Rasen",
    "iso:country":"GB",
    "sg:address":"Horncastle Road, Wragby",
    "sg:city":"Market Rasen",
    "sg:classifiers":[
        {
            "category":"Manufacturing",
            "subcategory":"Tools & Machinery",
            "type":"Manufacturing & Wholesale Goods"
        },
        {
            "category":"Retail",
            "subcategory":"Repair Shop",
            "type":"Services"
        }
    ],
    "sg:phone":"+44 1673 857777",
    "sg:postcode":"LN8 5RB",
    "sg:province":"Lincolnshire",
    "sg:tags":[
        "restored",
        "furniture"
    ],
    "wof:name":"A & P Nutting",
    "wof:placetype":"venue"
},
  "geometry": {"coordinates":[-0.295913,53.286419],"type":"Point"}
}