{
  "type": "Feature",
  "properties": {
    "iso:country":"GB",
    "sg:address":"10 Longford Road",
    "sg:city":"Stockport",
    "sg:classifiers":[
        {
            "category":"Shopping",
            "subcategory":"Clothing, Apparel, & Fashions",
            "type":"Retail Goods"
        },
        {
            "category":"Banks & Credit Unions",
            "subcategory":"Investment Brokerage",
            "type":"Services"
        }
    ],
    "sg:phone":"+44 161 432 8602",
    "sg:postcode":"SK5 6UX",
    "sg:province":"Cheshire",
    "sg:tags":[
        "agency",
        "dress",
        "dresswear"
    ],
    "wof:name":"Number Ten Dress Agency",
    "wof:placetype":"venue"
},
  "geometry": {"coordinates":[-2.1565670967,53.4450111389],"type":"Point"}
}