{
  "type": "Feature",
  "properties": {
    "addr:full":"9 Padgate La Warrington Cheshire WA1 3RS",
    "addr:housenumber":"9",
    "addr:postcode":"wa1 3rs",
    "addr:street":"Padgate La Warrington Cheshire",
    "iso:country":"GB",
    "sg:address":"9 Padgate La",
    "sg:city":"Warrington",
    "sg:classifiers":[
        {
            "category":"Home & Garden",
            "subcategory":"Carpets & Floor Coverings",
            "type":"Retail Goods"
        }
    ],
    "sg:phone":"+44 1925 480078",
    "sg:postcode":"WA1 3RS",
    "sg:province":"Cheshire",
    "sg:tags":[
        "carpets",
        "rug",
        "matting"
    ],
    "wof:name":"Town 'n' Country Carpets (UK)",
    "wof:placetype":"venue"
},
  "geometry": {"coordinates":[-2.5731461048,53.3972434998],"type":"Point"}
}