{
  "type": "Feature",
  "properties": {
    "addr:full":"2a Union Close, Kettlebrook Tamworth Staffordshire B77 1BB",
    "addr:housenumber":"2a",
    "addr:postcode":"b77 1bb",
    "addr:street":"Union Close",
    "iso:country":"GB",
    "sg:address":"2a Union Close, Kettlebrook",
    "sg:city":"Tamworth",
    "sg:classifiers":[
        {
            "category":"Building & Trades",
            "subcategory":"Construction",
            "type":"Services"
        }
    ],
    "sg:phone":"+44 1827 700387",
    "sg:postcode":"B77 1BB",
    "sg:province":"Staffordshire",
    "sg:tags":[
        "joiner",
        "carpenter"
    ],
    "wof:name":"Alldridge Bros",
    "wof:placetype":"venue"
},
  "geometry": {"coordinates":[-1.686815,52.629372],"type":"Point"}
}