{
  "type": "Feature",
  "properties": {
    "addr:full":"Priory Cotts, Featherbed Lane, Wighill Park Tadcaster North Yorkshire LS24 8BN",
    "addr:postcode":"ls24 8bn",
    "addr:street":"Featherbed Lane",
    "iso:country":"GB",
    "sg:address":"Priory Cotts, Featherbed Lane, Wighill Park",
    "sg:city":"Tadcaster",
    "sg:classifiers":[
        {
            "category":"Farming",
            "subcategory":"Livestock Farm",
            "type":"Manufacturing & Wholesale Goods"
        },
        {
            "category":"Farming",
            "subcategory":"Farm",
            "type":"Manufacturing & Wholesale Goods"
        }
    ],
    "sg:phone":"+44 1937 835830",
    "sg:postcode":"LS24 8BN",
    "sg:province":"North Yorkshire",
    "sg:tags":[
        "mixed",
        "others"
    ],
    "wof:name":"D A & S Rawlings",
    "wof:placetype":"venue"
},
  "geometry": {"coordinates":[-1.2783639431,53.9163856506],"type":"Point"}
}