{
  "type": "Feature",
  "properties": {
    "addr:full":"14 Coopers Row Monument Greater London EC3N 2BQ",
    "addr:housenumber":"14",
    "addr:postcode":"ec3n 2bq",
    "addr:street":"Coopers Row",
    "iso:country":"GB",
    "sg:address":"14 Coopers Row",
    "sg:city":"Monument",
    "sg:classifiers":[
        {
            "category":"Professional",
            "subcategory":"Lawyer & Legal Services",
            "type":"Services"
        }
    ],
    "sg:phone":"+44 20 7481 2232",
    "sg:postcode":"EC3N 2BQ",
    "sg:province":"Greater London",
    "sg:tags":[
        "advice",
        "counselling"
    ],
    "wof:name":"International Student Advisory Service",
    "wof:placetype":"venue"
},
  "geometry": {"coordinates":[-0.077108,51.511337],"type":"Point"}
}