{
  "type": "Feature",
  "properties": {
    "addr:full":"13 Grassy Lane Sevenoaks Kent TN13 1PN",
    "addr:housenumber":"13",
    "addr:postcode":"tn13 1pn",
    "addr:street":"Grassy Lane",
    "iso:country":"GB",
    "sg:address":"13 Grassy Lane",
    "sg:city":"Sevenoaks",
    "sg:classifiers":[
        {
            "category":"Professional",
            "subcategory":"Engineering",
            "type":"Services"
        }
    ],
    "sg:phone":"+44 1732 458200",
    "sg:postcode":"TN13 1PN",
    "sg:province":"Kent",
    "sg:tags":[
        "design",
        "engineer"
    ],
    "wof:name":"Barrie Maxwell Associates",
    "wof:placetype":"venue"
},
  "geometry": {"coordinates":[0.187561,51.264748],"type":"Point"}
}