{
  "type": "Feature",
  "properties": {
    "iso:country":"GB",
    "sg:address":"Mill Street",
    "sg:city":"Crediton",
    "sg:classifiers":[
        {
            "category":"Wholesale",
            "subcategory":"Groceries",
            "type":"Manufacturing & Wholesale Goods"
        }
    ],
    "sg:postcode":"EX17 1HB",
    "sg:province":"Devon",
    "sg:tags":[
        "food",
        "supplier",
        "drink"
    ],
    "wof:name":"Pepscene Ltd.",
    "wof:placetype":"venue"
},
  "geometry": {"coordinates":[-3.648239,50.789284],"type":"Point"}
}