{
  "type": "Feature",
  "properties": {
    "addr:full":"32 Fowler Road, Mainault Industrial Estate Ilford Essex IG6 3UT",
    "addr:housenumber":"32",
    "addr:postcode":"ig6 3ut",
    "addr:street":"Fowler Road Mainault Industrial Estate",
    "iso:country":"GB",
    "sg:address":"32 Fowler Road, Mainault Industrial Estate",
    "sg:city":"Ilford",
    "sg:classifiers":[
        {
            "category":"Shopping",
            "subcategory":"Stationery & Office Supplies",
            "type":"Retail Goods"
        },
        {
            "category":"Wholesale",
            "subcategory":"Vending Machines",
            "type":"Manufacturing & Wholesale Goods"
        }
    ],
    "sg:phone":"+44 20 8559 8331",
    "sg:postcode":"IG6 3UT",
    "sg:province":"Essex",
    "sg:tags":[
        "equipment",
        "copying",
        "furniture"
    ],
    "sg:website":"http://www.maxfield.co.uk",
    "wof:name":"Maxfield Business Equipment & Stationery Ltd",
    "wof:placetype":"venue"
},
  "geometry": {"coordinates":[0.121682,51.607838],"type":"Point"}
}