{
  "type": "Feature",
  "properties": {
    "addr:full":"Royal Mews, Buckinham Palace Road London Greater London SW1W 0QH",
    "addr:postcode":"sw1w 0qh",
    "addr:street":"Royal Mews;Palace Road",
    "iso:country":"GB",
    "sg:address":"Royal Mews, Buckinham Palace Road",
    "sg:city":"London",
    "sg:classifiers":[
        {
            "category":"Sports & Exercise",
            "subcategory":"Stables",
            "type":"Entertainment"
        }
    ],
    "sg:postcode":"SW1W 0QH",
    "sg:province":"Greater London",
    "sg:tags":[
        "education",
        "equestrian"
    ],
    "wof:name":"Civil Service Riding Club",
    "wof:placetype":"venue"
},
  "geometry": {"coordinates":[-0.144404,51.497345],"type":"Point"}
}