{
  "type": "Feature",
  "properties": {
    "addr:full":"Hazel Farm, Alveston Bristol Gloucestershire BS35 3PS",
    "addr:postcode":"bs35 3ps",
    "iso:country":"GB",
    "sg:address":"Hazel Farm, Alveston",
    "sg:city":"Bristol",
    "sg:classifiers":[
        {
            "category":"Home & Garden",
            "subcategory":"Garden Supply",
            "type":"Retail Goods"
        },
        {
            "category":"Farming",
            "subcategory":"Crops",
            "type":"Manufacturing & Wholesale Goods"
        },
        {
            "category":"Farming",
            "subcategory":"Farm",
            "type":"Manufacturing & Wholesale Goods"
        }
    ],
    "sg:phone":"+44 1454 411837",
    "sg:postcode":"BS35 3PS",
    "sg:province":"Gloucestershire",
    "sg:tags":[
        "mixed",
        "bulb",
        "arable",
        "grower"
    ],
    "wof:name":"M G Spratt & Son",
    "wof:placetype":"venue"
},
  "geometry": {"coordinates":[-2.532049,51.592155],"type":"Point"}
}