{
  "type": "Feature",
  "properties": {
    "addr:full":"Lamberts Road, North Farm Estate Tunbridge Wells East Sussex TN2 3EL",
    "addr:postcode":"tn2 3el",
    "addr:street":"Lamberts Road North;Wells",
    "iso:country":"GB",
    "sg:address":"Lamberts Road, North Farm Estate",
    "sg:city":"Tunbridge Wells",
    "sg:classifiers":[
        {
            "category":"Retail",
            "subcategory":"Auto Repair",
            "type":"Services"
        }
    ],
    "sg:phone":"+44 1892 515700",
    "sg:postcode":"TN2 3EL",
    "sg:province":"East Sussex",
    "sg:tags":[
        "modification",
        "garage"
    ],
    "wof:name":"Piper Group Holding Ltd.",
    "wof:placetype":"venue"
},
  "geometry": {"coordinates":[0.2837,51.152786],"type":"Point"}
}