{
  "type": "Feature",
  "properties": {
    "addr:full":"Dellers Wharf Taunton Somerset TA1 1DX",
    "addr:postcode":"ta1 1dx",
    "iso:country":"GB",
    "sg:address":"Dellers Wharf",
    "sg:city":"Taunton",
    "sg:classifiers":[
        {
            "category":"Food & Beverages",
            "subcategory":"Supermarket",
            "type":"Retail Goods"
        }
    ],
    "sg:phone":"+44 1823 351598",
    "sg:postcode":"TA1 1DX",
    "sg:province":"Somerset",
    "wof:name":"Safeway Stores",
    "wof:placetype":"venue"
},
  "geometry": {"coordinates":[-3.1021420956,51.0202178955],"type":"Point"}
}