{
  "type": "Feature",
  "properties": {
    "addr:full":"173 Nuthall Road Nottingham Nottinghamshire NG8 5BN",
    "addr:housenumber":"173",
    "addr:postcode":"ng8 5bn",
    "addr:street":"Nuthall Road",
    "iso:country":"GB",
    "sg:address":"173 Nuthall Road",
    "sg:city":"Nottingham",
    "sg:classifiers":[
        {
            "category":"Food & Beverages",
            "subcategory":"Meat & Fish",
            "type":"Retail Goods"
        }
    ],
    "sg:postcode":"NG8 5BN",
    "sg:province":"Nottinghamshire",
    "sg:tags":[
        "chip"
    ],
    "wof:name":"Island Fish Bar",
    "wof:placetype":"venue"
},
  "geometry": {"coordinates":[-1.1860090494,52.9727706909],"type":"Point"}
}