{
  "type": "Feature",
  "properties": {
    "iso:country":"GB",
    "sg:address":"22 Replingham Road",
    "sg:city":"London",
    "sg:classifiers":[
        {
            "category":"Bars & Pubs",
            "type":"Food & Drink"
        }
    ],
    "sg:phone":"+44 20 8874 8460",
    "sg:postcode":"SW18 5LS",
    "sg:province":"Greater London",
    "sg:tags":[
        "pubs",
        "inn"
    ],
    "wof:name":"The Grid Inn",
    "wof:placetype":"venue"
},
  "geometry": {"coordinates":[-0.204953,51.444759],"type":"Point"}
}