{
  "type": "Feature",
  "properties": {
    "addr:full":"Main Street Milton Keynes Buckinghamshire MK19 7JP",
    "addr:postcode":"mk19 7jp",
    "addr:street":"Main Street",
    "iso:country":"GB",
    "sg:address":"Main Street",
    "sg:city":"Milton Keynes",
    "sg:classifiers":[
        {
            "category":"Recreation",
            "subcategory":"Campground",
            "type":"Entertainment"
        }
    ],
    "sg:phone":"+44 1908 563360",
    "sg:postcode":"MK19 7JP",
    "sg:province":"Buckinghamshire",
    "sg:tags":[
        "caravan",
        "park"
    ],
    "wof:name":"Cosgrove Leisure Park",
    "wof:placetype":"venue"
},
  "geometry": {"coordinates":[-0.840759,52.077099],"type":"Point"}
}