{
  "type": "Feature",
  "properties": {
    "iso:country":"GB",
    "sg:address":"Old Station Yard, Marlesford",
    "sg:city":"Woodbridge",
    "sg:classifiers":[
        {
            "category":"Manufacturing",
            "subcategory":"Rubber & Plastics",
            "type":"Manufacturing & Wholesale Goods"
        }
    ],
    "sg:phone":"+44 1728 747900",
    "sg:postcode":"IP13 0AG",
    "sg:province":"Suffolk",
    "sg:tags":[
        "product"
    ],
    "wof:name":"Bradleys Plastic Finishers",
    "wof:placetype":"venue"
},
  "geometry": {"coordinates":[1.398567,52.173435],"type":"Point"}
}