{
  "type": "Feature",
  "properties": {
    "addr:full":"9 Market Place, Marsden Huddersfield West Yorkshire HD7 6BY",
    "addr:housenumber":"9",
    "addr:postcode":"hd7 6by",
    "addr:street":"Market Place;West",
    "iso:country":"GB",
    "sg:address":"9 Market Place, Marsden",
    "sg:city":"Huddersfield",
    "sg:classifiers":[
        {
            "category":"Food & Beverages",
            "subcategory":"Meat & Fish",
            "type":"Retail Goods"
        }
    ],
    "sg:phone":"+44 1484 844340",
    "sg:postcode":"HD7 6BY",
    "sg:province":"West Yorkshire",
    "sg:tags":[
        "butcher"
    ],
    "wof:name":"R & E Knight",
    "wof:placetype":"venue"
},
  "geometry": {"coordinates":[-1.9270190001,53.6010704041],"type":"Point"}
}