{
  "type": "Feature",
  "properties": {
    "iso:country":"GB",
    "sg:address":"106 Meols Drive, West Kirby",
    "sg:city":"Wirral",
    "sg:classifiers":[
        {
            "category":"Health Services",
            "subcategory":"Dentist",
            "type":"Services"
        }
    ],
    "sg:phone":"+44 151 632 3693",
    "sg:postcode":"CH48 5DA",
    "sg:province":"Merseyside",
    "wof:name":"N J Driver & Associates",
    "wof:placetype":"venue"
},
  "geometry": {"coordinates":[-3.1857669353,53.3746833801],"type":"Point"}
}