{
  "type": "Feature",
  "properties": {
    "addr:full":"Ashford Road Fordingbridge Dorset SP6 3BT",
    "addr:postcode":"sp6 3bt",
    "addr:street":"Ashford Road",
    "iso:country":"GB",
    "sg:address":"Ashford Road",
    "sg:city":"Fordingbridge",
    "sg:classifiers":[
        {
            "category":"Farming",
            "subcategory":"Farm",
            "type":"Manufacturing & Wholesale Goods"
        }
    ],
    "sg:postcode":"SP6 3BT",
    "sg:province":"Dorset",
    "sg:tags":[
        "hatchery"
    ],
    "wof:name":"Ashford Water Trout Farm",
    "wof:placetype":"venue"
},
  "geometry": {"coordinates":[-1.811496973,50.9227256775],"type":"Point"}
}