{
  "type": "Feature",
  "properties": {
    "addr:full":"The Kennels, Shelt Hill, Woodborough Nottingham Nottinghamshire NG14 6DG",
    "addr:postcode":"ng14 6dg",
    "addr:street":"Shelt Hill",
    "iso:country":"GB",
    "sg:address":"The Kennels, Shelt Hill, Woodborough",
    "sg:city":"Nottingham",
    "sg:classifiers":[
        {
            "category":"Recreation",
            "subcategory":"Dog Park",
            "type":"Entertainment"
        }
    ],
    "sg:phone":"+44 115 966 4029",
    "sg:postcode":"NG14 6DG",
    "sg:province":"Nottinghamshire",
    "wof:name":"L Cook Racing Kennels",
    "wof:placetype":"venue"
},
  "geometry": {"coordinates":[-1.0646929741,53.0237808228],"type":"Point"}
}