{
  "type": "Feature",
  "properties": {
    "addr:full":"Towers Lawn, Cheshire Street Market Drayton Shropshire TF9 3AA",
    "addr:postcode":"tf9 3aa",
    "addr:street":"Lawn Cheshire Street",
    "iso:country":"GB",
    "sg:address":"Towers Lawn, Cheshire Street",
    "sg:city":"Market Drayton",
    "sg:classifiers":[
        {
            "category":"Autos & Motor Vehicles",
            "subcategory":"Automobile Sales",
            "type":"Retail Goods"
        }
    ],
    "sg:phone":"+44 1630 653338",
    "sg:postcode":"TF9 3AA",
    "sg:province":"Shropshire",
    "sg:tags":[
        "car"
    ],
    "wof:name":"L J Motors",
    "wof:placetype":"venue"
},
  "geometry": {"coordinates":[-2.4861719608,52.9040908813],"type":"Point"}
}