{
  "type": "Feature",
  "properties": {
    "addr:full":"232 Earlsfield Road London Greater London SW18 3DX",
    "addr:housenumber":"232",
    "addr:postcode":"sw18 3dx",
    "addr:street":"Earlsfield Road",
    "iso:country":"GB",
    "sg:address":"232 Earlsfield Road",
    "sg:city":"London",
    "sg:classifiers":[
        {
            "category":"Fast Food",
            "type":"Food & Drink"
        }
    ],
    "sg:phone":"+44 20 8877 1990",
    "sg:postcode":"SW18 3DX",
    "sg:province":"Greater London",
    "sg:tags":[
        "away",
        "take"
    ],
    "wof:name":"Tanim's Indian Takeaway",
    "wof:placetype":"venue"
},
  "geometry": {"coordinates":[-0.1856819987,51.4459762573],"type":"Point"}
}