{
  "type": "Feature",
  "properties": {
    "iso:country":"GB",
    "sg:address":"47 Newdown Rd",
    "sg:city":"Scunthorpe",
    "sg:classifiers":[
        {
            "category":"Train Station",
            "subcategory":"Rail",
            "type":"Transportation"
        }
    ],
    "sg:phone":"+44 1724 271707",
    "sg:postcode":"DN17 2TX",
    "sg:province":"Lincolnshire",
    "sg:tags":[
        "caravan"
    ],
    "wof:name":"Caravan Rentals Ltd",
    "wof:placetype":"venue"
},
  "geometry": {"coordinates":[-0.6713290215,53.555229187],"type":"Point"}
}