{
  "type": "Feature",
  "properties": {
    "iso:country":"GB",
    "sg:address":"Old Regent Works",
    "sg:city":"Sheffield",
    "sg:classifiers":[
        {
            "category":"Retail",
            "subcategory":"Auto Repair",
            "type":"Services"
        }
    ],
    "sg:phone":"+44 114 272 4343",
    "sg:postcode":"S3 8BX",
    "sg:province":"South Yorkshire",
    "sg:tags":[
        "modification",
        "garage"
    ],
    "wof:name":"J C Cars",
    "wof:placetype":"venue"
},
  "geometry": {"coordinates":[-1.474965,53.389275],"type":"Point"}
}