{
  "type": "Feature",
  "properties": {
    "addr:full":"Darby Green Road, Blackwater Camberley Hampshire GU17 0DT",
    "addr:postcode":"gu17 0dt",
    "addr:street":"Darby Green Road",
    "iso:country":"GB",
    "sg:address":"Darby Green Road, Blackwater",
    "sg:city":"Camberley",
    "sg:classifiers":[
        {
            "category":"Banks & Credit Unions",
            "subcategory":"Financial Services",
            "type":"Services"
        }
    ],
    "sg:phone":"+44 1252 877404",
    "sg:postcode":"GU17 0DT",
    "sg:province":"Hampshire",
    "sg:tags":[
        "adviser"
    ],
    "wof:name":"A S P Financial Services Ltd.",
    "wof:placetype":"venue"
},
  "geometry": {"coordinates":[-0.803034,51.336617],"type":"Point"}
}