{
  "type": "Feature",
  "properties": {
    "addr:full":"Barrington Industrial Estate Bedlington Northumberland NE22 7DQ",
    "addr:postcode":"ne22 7dq",
    "addr:street":"Estate;Northumberland",
    "iso:country":"GB",
    "sg:address":"Barrington Industrial Estate",
    "sg:city":"Bedlington",
    "sg:classifiers":[
        {
            "category":"Shopping",
            "subcategory":"Computers & Home Electronics",
            "type":"Retail Goods"
        }
    ],
    "sg:postcode":"NE22 7DQ",
    "sg:province":"Northumberland",
    "sg:tags":[
        "equipment",
        "video",
        "cctv"
    ],
    "wof:name":"Singcare Ltd.",
    "wof:placetype":"venue"
},
  "geometry": {"coordinates":[-1.5894739628,55.1450691223],"type":"Point"}
}