{
  "type": "Feature",
  "properties": {
    "iso:country":"GB",
    "sg:address":"585 Stratford Rd, Sparkhill",
    "sg:city":"Birmingham",
    "sg:classifiers":[
        {
            "category":"Shopping",
            "subcategory":"Baby Store",
            "type":"Retail Goods"
        }
    ],
    "sg:phone":"+44 121 766 7743",
    "sg:postcode":"B11 4LS",
    "sg:province":"West Midlands",
    "sg:tags":[
        "babywear",
        "childrens"
    ],
    "wof:name":"J & G Fashions",
    "wof:placetype":"venue"
},
  "geometry": {"coordinates":[-1.8653860092,52.4520530701],"type":"Point"}
}