{
  "type": "Feature",
  "properties": {
    "addr:full":"38 Hall Moss Lane Stockport Cheshire SK7 1RD",
    "addr:housenumber":"38",
    "addr:postcode":"sk7 1rd",
    "addr:street":"Hall Moss Lane",
    "iso:country":"GB",
    "sg:address":"38 Hall Moss Lane",
    "sg:city":"Stockport",
    "sg:classifiers":[
        {
            "category":"Home & Garden",
            "subcategory":"Garden Supply",
            "type":"Retail Goods"
        }
    ],
    "sg:postcode":"SK7 1RD",
    "sg:province":"Cheshire",
    "sg:tags":[
        "nursery",
        "centre"
    ],
    "wof:name":"Andertons Nursery",
    "wof:placetype":"venue"
},
  "geometry": {"coordinates":[-2.1792969704,53.350315094],"type":"Point"}
}