{
  "type": "Feature",
  "properties": {
    "iso:country":"GB",
    "sg:address":"25 Phoenix Street",
    "sg:city":"Brighouse",
    "sg:classifiers":[
        {
            "category":"Restaurant",
            "type":"Food & Drink"
        }
    ],
    "sg:phone":"+44 1484 400114",
    "sg:postcode":"HD6 1PD",
    "sg:province":"West Yorkshire",
    "sg:tags":[
        "-",
        "italian"
    ],
    "wof:name":"La Romantica",
    "wof:placetype":"venue"
},
  "geometry": {"coordinates":[-1.777118,53.701931],"type":"Point"}
}