{
  "type": "Feature",
  "properties": {
    "addr:full":"St Marys Ho, 9 Church Walk Bideford Devon EX39 2BP",
    "addr:housenumber":"9",
    "addr:postcode":"ex39 2bp",
    "addr:street":"Church Walk",
    "iso:country":"GB",
    "sg:address":"St Marys Ho, 9 Church Walk",
    "sg:city":"Bideford",
    "sg:classifiers":[
        {
            "category":"Place Of Worship",
            "type":"Public Place"
        }
    ],
    "sg:phone":"+44 1237 474078",
    "sg:postcode":"EX39 2BP",
    "sg:province":"Devon",
    "wof:name":"St Marys & St Peters Bideford",
    "wof:placetype":"venue"
},
  "geometry": {"coordinates":[-4.2042589188,51.0192489624],"type":"Point"}
}