{
  "type": "Feature",
  "properties": {
    "addr:full":"Brook House, Cranbrook Road Cranbrook East Sussex TN18 5EE",
    "addr:postcode":"tn18 5ee",
    "addr:street":"Cranbrook Road",
    "iso:country":"GB",
    "sg:address":"Brook House, Cranbrook Road",
    "sg:city":"Cranbrook",
    "sg:classifiers":[
        {
            "category":"Professional",
            "subcategory":"Engineering",
            "type":"Services"
        }
    ],
    "sg:phone":"+44 1580 754747",
    "sg:postcode":"TN18 5EE",
    "sg:province":"East Sussex",
    "sg:tags":[
        "consulting",
        "engineer"
    ],
    "wof:name":"Quartis Ltd.",
    "wof:placetype":"venue"
},
  "geometry": {"coordinates":[0.5071210265,51.064491272],"type":"Point"}
}