{
  "type": "Feature",
  "properties": {
    "iso:country":"GB",
    "sg:address":"16 Bramley Park Road",
    "sg:city":"Sheffield",
    "sg:classifiers":[
        {
            "category":"Personal",
            "subcategory":"Beauty Salon",
            "type":"Services"
        },
        {
            "category":"Personal",
            "subcategory":"Barber",
            "type":"Services"
        }
    ],
    "sg:phone":"+44 114 269 4508",
    "sg:postcode":"S13 8UA",
    "sg:province":"South Yorkshire",
    "sg:tags":[
        "unisex",
        "hairdresser"
    ],
    "wof:name":"Hair Design",
    "wof:placetype":"venue"
},
  "geometry": {"coordinates":[-1.3896780014,53.3700256348],"type":"Point"}
}