{
  "type": "Feature",
  "properties": {
    "iso:country":"GB",
    "sg:address":"102 Union St",
    "sg:city":"Maidstone",
    "sg:classifiers":[
        {
            "category":"Restaurant",
            "type":"Food & Drink"
        }
    ],
    "sg:postcode":"ME14 1EH",
    "sg:province":"Kent",
    "wof:name":"Zambrana,Linda,",
    "wof:placetype":"venue"
},
  "geometry": {"coordinates":[0.526709,51.276012],"type":"Point"}
}