{
  "type": "Feature",
  "properties": {
    "iso:country":"GB",
    "sg:address":"20 Lansdowne Avenue",
    "sg:city":"Fareham",
    "sg:classifiers":[
        {
            "category":"Manufacturing",
            "subcategory":"Wood Products",
            "type":"Manufacturing & Wholesale Goods"
        }
    ],
    "sg:phone":"+44 23 9237 6025",
    "sg:postcode":"PO16 9NN",
    "sg:province":"Hampshire",
    "sg:tags":[
        "pallet",
        "crate",
        "packaging",
        "packing",
        "pallets",
        "supplier"
    ],
    "wof:name":"Lionheart Pallets",
    "wof:placetype":"venue"
},
  "geometry": {"coordinates":[-1.126709,50.838333],"type":"Point"}
}