{
  "type": "Feature",
  "properties": {
    "addr:full":"Prescot Trade Centre, Oliver Lyme Road Prescot Merseyside L34 2SH",
    "addr:postcode":"l34 2sh",
    "addr:street":"Lyme Road",
    "iso:country":"GB",
    "sg:address":"Prescot Trade Centre, Oliver Lyme Road",
    "sg:city":"Prescot",
    "sg:classifiers":[
        {
            "category":"Shopping",
            "subcategory":"Pharmacy",
            "type":"Retail Goods"
        }
    ],
    "sg:phone":"+44 151 430 8248",
    "sg:postcode":"L34 2SH",
    "sg:province":"Merseyside",
    "sg:tags":[
        "store",
        "drug",
        "outlet"
    ],
    "sg:website":"http://www.superdrug.com",
    "wof:name":"Superdrug Stores plc",
    "wof:placetype":"venue"
},
  "geometry": {"coordinates":[-2.7977290154,53.4287757874],"type":"Point"}
}