{
  "type": "Feature",
  "properties": {
    "addr:full":"Unit 4 Gararin, Lichfield Rd Tamworth Staffordshire B79 7TA",
    "addr:housenumber":"unit 4",
    "addr:postcode":"b79 7ta",
    "addr:street":"Gararin Lichfield Rd",
    "iso:country":"GB",
    "sg:address":"Unit 4 Gararin, Lichfield Rd",
    "sg:city":"Tamworth",
    "sg:classifiers":[
        {
            "category":"Shopping",
            "type":"Retail Goods"
        }
    ],
    "sg:phone":"+44 1827 54422",
    "sg:postcode":"B79 7TA",
    "sg:province":"Staffordshire",
    "sg:tags":[
        "part",
        "accessory"
    ],
    "wof:name":"Vec Parts (sales) Ltd",
    "wof:placetype":"venue"
},
  "geometry": {"coordinates":[-1.7115390301,52.6349487305],"type":"Point"}
}