{
  "type": "Feature",
  "properties": {
    "addr:full":"10 Armoury Terr Ebbw Vale Blaenau Gwent NP3 6BD",
    "addr:housenumber":"10",
    "addr:postcode":"np3 6bd",
    "addr:street":"Armoury Terr",
    "iso:country":"GB",
    "sg:address":"10 Armoury Terr",
    "sg:city":"Ebbw Vale",
    "sg:classifiers":[
        {
            "category":"Insurance",
            "subcategory":"Insurance Agent",
            "type":"Services"
        }
    ],
    "sg:phone":"+44 1495 302347",
    "sg:postcode":"NP3 6BD",
    "sg:province":"Blaenau Gwent",
    "wof:name":"Hill House Hammond Ltd",
    "wof:placetype":"venue"
},
  "geometry": {"coordinates":[-3.207606,51.77541],"type":"Point"}
}