{
  "type": "Feature",
  "properties": {
    "addr:full":"46 Greendale Rd Coventry West Midlands CV5 8LN",
    "addr:housenumber":"46",
    "addr:postcode":"cv5 8ln",
    "addr:street":"Greendale Rd",
    "iso:country":"GB",
    "sg:address":"46 Greendale Rd",
    "sg:city":"Coventry",
    "sg:classifiers":[
        {
            "category":"Building & Trades",
            "subcategory":"Construction",
            "type":"Services"
        }
    ],
    "sg:phone":"+44 24 7667 3891",
    "sg:postcode":"CV5 8LN",
    "sg:province":"West Midlands",
    "sg:tags":[
        "decorator",
        "painter"
    ],
    "wof:name":"Whailing,David,",
    "wof:placetype":"venue"
},
  "geometry": {"coordinates":[-1.5514110327,52.4107666016],"type":"Point"}
}