{
  "type": "Feature",
  "properties": {
    "addr:full":"Graig Farm, Penylan Wrexham Wrexham LL14 6HR",
    "addr:postcode":"ll14 6hr",
    "addr:street":"Graig;Penylan",
    "iso:country":"GB",
    "sg:address":"Graig Farm, Penylan",
    "sg:city":"Wrexham",
    "sg:classifiers":[
        {
            "category":"Farming",
            "subcategory":"Farm",
            "type":"Manufacturing & Wholesale Goods"
        }
    ],
    "sg:phone":"+44 1978 821247",
    "sg:postcode":"LL14 6HR",
    "sg:province":"Wrexham",
    "sg:tags":[
        "mixed",
        "crop"
    ],
    "wof:name":"Philip K Richards",
    "wof:placetype":"venue"
},
  "geometry": {"coordinates":[-2.9916899204,52.9627609253],"type":"Point"}
}