{
  "type": "Feature",
  "properties": {
    "addr:full":"58 New Road Newbury Berkshire RG14 7RU",
    "addr:housenumber":"58",
    "addr:postcode":"rg14 7ru",
    "addr:street":"New Road",
    "iso:country":"GB",
    "sg:address":"58 New Road",
    "sg:city":"Newbury",
    "sg:classifiers":[
        {
            "category":"Professional",
            "subcategory":"Computer Services",
            "type":"Services"
        }
    ],
    "sg:postcode":"RG14 7RU",
    "sg:province":"Berkshire",
    "sg:tags":[
        "system",
        "software"
    ],
    "wof:name":"Trekallied Ltd",
    "wof:placetype":"venue"
},
  "geometry": {"coordinates":[-1.3078609705,51.3917121887],"type":"Point"}
}