{
  "type": "Feature",
  "properties": {
    "iso:country":"GB",
    "sg:address":"91 Hermitage Road",
    "sg:city":"Hitchin",
    "sg:classifiers":[
        {
            "category":"Shopping",
            "subcategory":"Florist",
            "type":"Retail Goods"
        }
    ],
    "sg:phone":"+44 1462 456741",
    "sg:postcode":"SG5 1DG",
    "sg:province":"Bedfordshire",
    "wof:name":"House of Flowers",
    "wof:placetype":"venue"
},
  "geometry": {"coordinates":[-0.27648,51.94944],"type":"Point"}
}