{
  "type": "Feature",
  "properties": {
    "iso:country":"GB",
    "sg:address":"841 High Street",
    "sg:city":"Stoke-on-trent",
    "sg:classifiers":[
        {
            "category":"Shopping",
            "subcategory":"Clothing, Apparel, & Fashions",
            "type":"Retail Goods"
        }
    ],
    "sg:phone":"+44 1782 510410",
    "sg:postcode":"ST6 5QH",
    "sg:province":"Staffordshire",
    "sg:tags":[
        "protective",
        "clothing"
    ],
    "wof:name":"Simon Snee",
    "wof:placetype":"venue"
},
  "geometry": {"coordinates":[-2.2208230495,53.0759124756],"type":"Point"}
}