{
  "type": "Feature",
  "properties": {
    "iso:country":"GB",
    "sg:address":"Tregamere, Brookside, Stretton On Dunsmore",
    "sg:city":"Rugby",
    "sg:classifiers":[
        {
            "category":"Professional",
            "subcategory":"Art Services",
            "type":"Services"
        },
        {
            "category":"Building & Trades",
            "subcategory":"Construction",
            "type":"Services"
        }
    ],
    "sg:postcode":"CV23 9NH",
    "sg:province":"Northamptonshire",
    "sg:tags":[
        "decorator",
        "painter"
    ],
    "wof:name":"ALLEN F HEMMING",
    "wof:placetype":"venue"
},
  "geometry": {"coordinates":[-1.398421,52.348896],"type":"Point"}
}