{
  "type": "Feature",
  "properties": {
    "addr:full":"Maesneuadd, Caio Llanwrda Carmarthenshire SA19 8PF",
    "addr:postcode":"sa19 8pf",
    "iso:country":"GB",
    "sg:address":"Maesneuadd, Caio",
    "sg:city":"Llanwrda",
    "sg:classifiers":[
        {
            "category":"Farming",
            "subcategory":"Livestock Farm",
            "type":"Manufacturing & Wholesale Goods"
        }
    ],
    "sg:phone":"+44 1558 650264",
    "sg:postcode":"SA19 8PF",
    "sg:province":"Carmarthenshire",
    "sg:tags":[
        "others"
    ],
    "wof:name":"Sidney R Watkins",
    "wof:placetype":"venue"
},
  "geometry": {"coordinates":[-3.874174118,51.9666900635],"type":"Point"}
}