{
  "type": "Feature",
  "properties": {
    "iso:country":"GB",
    "sg:address":"Sewell Ct, 2 Langhill Rd",
    "sg:city":"Plymouth",
    "sg:classifiers":[
        {
            "category":"Organizations",
            "subcategory":"Community Association",
            "type":"Services"
        }
    ],
    "sg:phone":"+44 1752 268051",
    "sg:postcode":"PL3 4JH",
    "sg:province":"Devon",
    "sg:tags":[
        "co-operatives",
        "society",
        "housing",
        "trust"
    ],
    "wof:name":"Guinness Trust The",
    "wof:placetype":"venue"
},
  "geometry": {"coordinates":[-4.1393,50.38575],"type":"Point"}
}