{
  "type": "Feature",
  "properties": {
    "addr:full":"Midland Way, Balborough Chesterfield Derbyshire S43 4XA",
    "addr:postcode":"s43 4xa",
    "addr:street":"Midland Way Balborough",
    "iso:country":"GB",
    "sg:address":"Midland Way, Balborough",
    "sg:city":"Chesterfield",
    "sg:classifiers":[
        {
            "category":"Building & Trades",
            "subcategory":"Construction",
            "type":"Services"
        }
    ],
    "sg:phone":"+44 1246 570060",
    "sg:postcode":"S43 4XA",
    "sg:province":"Derbyshire",
    "sg:tags":[
        "builder"
    ],
    "wof:name":"Wilcon Homes (Northern)",
    "wof:placetype":"venue"
},
  "geometry": {"coordinates":[-1.2899639606,53.2835350037],"type":"Point"}
}