{
  "type": "Feature",
  "properties": {
    "iso:country":"GB",
    "sg:address":"3a Raynsford Road",
    "sg:city":"Ware",
    "sg:classifiers":[
        {
            "category":"Shopping",
            "subcategory":"Pets & Pet Supplies",
            "type":"Retail Goods"
        }
    ],
    "sg:phone":"+44 1920 462348",
    "sg:postcode":"SG12 7AJ",
    "sg:province":"Hertfordshire",
    "wof:name":"Pads",
    "wof:placetype":"venue"
},
  "geometry": {"coordinates":[-0.023387,51.8102798462],"type":"Point"}
}