{
  "type": "Feature",
  "properties": {
    "addr:full":"Guildford Rd Leatherhead Surrey KT23 4HB",
    "addr:postcode":"kt23 4hb",
    "addr:street":"Guildford Rd",
    "iso:country":"GB",
    "sg:address":"Guildford Rd",
    "sg:city":"Leatherhead",
    "sg:classifiers":[
        {
            "category":"Sports & Exercise",
            "subcategory":"Stables",
            "type":"Entertainment"
        }
    ],
    "sg:phone":"+44 1372 454339",
    "sg:postcode":"KT23 4HB",
    "sg:province":"Surrey",
    "sg:tags":[
        "education",
        "equestrian"
    ],
    "wof:name":"Wyvenhoe Equestrian Club",
    "wof:placetype":"venue"
},
  "geometry": {"coordinates":[-0.3746039867,51.2767486572],"type":"Point"}
}