{
  "type": "Feature",
  "properties": {
    "addr:full":"5 Heworth Village York North Yorkshire YO31 1AE",
    "addr:housenumber":"5",
    "addr:postcode":"yo31 1ae",
    "addr:street":"Heworth Village",
    "iso:country":"GB",
    "sg:address":"5 Heworth Village",
    "sg:city":"York",
    "sg:classifiers":[
        {
            "category":"Shopping",
            "subcategory":"Pharmacy",
            "type":"Retail Goods"
        }
    ],
    "sg:phone":"+44 1904 423760",
    "sg:postcode":"YO31 1AE",
    "sg:province":"North Yorkshire",
    "sg:tags":[
        "pharmacist",
        "dispensing",
        "chemist"
    ],
    "wof:name":"Moss Pharmacy",
    "wof:placetype":"venue"
},
  "geometry": {"coordinates":[-1.0539089441,53.9674186707],"type":"Point"}
}