{
  "type": "Feature",
  "properties": {
    "addr:full":"168 Ballards Lane London Greater London N3 2PA",
    "addr:housenumber":"168",
    "addr:postcode":"n3 2pa",
    "addr:street":"Ballards Lane",
    "iso:country":"GB",
    "sg:address":"168 Ballards Lane",
    "sg:city":"London",
    "sg:classifiers":[
        {
            "category":"Bars & Pubs",
            "subcategory":"Wine Bar",
            "type":"Food & Drink"
        }
    ],
    "sg:phone":"+44 20 8343 1377",
    "sg:postcode":"N3 2PA",
    "sg:province":"Greater London",
    "wof:name":"Olivers Wine Bar",
    "wof:placetype":"venue"
},
  "geometry": {"coordinates":[-0.1874260008,51.6055908203],"type":"Point"}
}