{
  "type": "Feature",
  "properties": {
    "iso:country":"GB",
    "sg:address":"15 The Evergreens, Stretton",
    "sg:city":"Burton-on-trent",
    "sg:classifiers":[
        {
            "category":"Shopping",
            "subcategory":"Computers & Home Electronics",
            "type":"Retail Goods"
        }
    ],
    "sg:postcode":"DE13 0BE",
    "sg:province":"Derbyshire",
    "sg:tags":[
        "aerial",
        "television",
        "radio"
    ],
    "wof:name":"Rushton T V & Aerial Services",
    "wof:placetype":"venue"
},
  "geometry": {"coordinates":[-1.616189,52.827606],"type":"Point"}
}