{
  "type": "Feature",
  "properties": {
    "addr:full":"Brodrick Close Eastbourne East Sussex BN22 9NQ",
    "addr:postcode":"bn22 9nq",
    "addr:street":"Brodrick Close",
    "iso:country":"GB",
    "sg:address":"Brodrick Close",
    "sg:city":"Eastbourne",
    "sg:classifiers":[
        {
            "category":"Health Services",
            "subcategory":"Clinic",
            "type":"Services"
        }
    ],
    "sg:phone":"+44 1323 507373",
    "sg:postcode":"BN22 9NQ",
    "sg:province":"East Sussex",
    "sg:tags":[
        "nh"
    ],
    "wof:name":"Hampden Park Surgery",
    "wof:placetype":"venue"
},
  "geometry": {"coordinates":[0.277783,50.797688],"type":"Point"}
}