{
  "type": "Feature",
  "properties": {
    "iso:country":"GB",
    "sg:address":"183-185 Green Lane, Stoneycroft",
    "sg:city":"Liverpool",
    "sg:classifiers":[
        {
            "category":"Cafe",
            "type":"Food & Drink"
        }
    ],
    "sg:phone":"+44 151 252 0678",
    "sg:postcode":"L13 6RQ",
    "sg:province":"Merseyside",
    "sg:tags":[
        "tea",
        "room"
    ],
    "wof:name":"Paulines Cafe",
    "wof:placetype":"venue"
},
  "geometry": {"coordinates":[-2.922122,53.418541],"type":"Point"}
}