{
  "type": "Feature",
  "properties": {
    "iso:country":"GB",
    "sg:address":"212 High Street",
    "sg:city":"Treorchy",
    "sg:classifiers":[
        {
            "category":"Shopping",
            "subcategory":"Jewelry",
            "type":"Retail Goods"
        },
        {
            "category":"Shopping",
            "subcategory":"Comic Books",
            "type":"Retail Goods"
        }
    ],
    "sg:phone":"+44 1443 776033",
    "sg:postcode":"CF42 6AS",
    "sg:province":"Rhondda, Cynon, Taff",
    "sg:tags":[
        "jeweller",
        "sale",
        "jewellery"
    ],
    "wof:name":"D & M Davies",
    "wof:placetype":"venue"
},
  "geometry": {"coordinates":[-3.506275,51.659695],"type":"Point"}
}