{
  "type": "Feature",
  "properties": {
    "addr:full":"Berry Street Conwy Conwy LL32 8DG",
    "addr:postcode":"ll32 8dg",
    "addr:street":"Berry Street",
    "iso:country":"GB",
    "sg:address":"Berry Street",
    "sg:city":"Conwy",
    "sg:classifiers":[
        {
            "category":"Organizations",
            "subcategory":"Non-profit Organization",
            "type":"Services"
        }
    ],
    "sg:phone":"+44 1492 592724",
    "sg:postcode":"LL32 8DG",
    "sg:province":"Conwy",
    "sg:tags":[
        "organisation",
        "voluntary",
        "charity"
    ],
    "wof:name":"Clwb Yr Efail",
    "wof:placetype":"venue"
},
  "geometry": {"coordinates":[-3.82951,53.282459],"type":"Point"}
}