{
  "type": "Feature",
  "properties": {
    "addr:full":"12 Woodpecker Glade Gillingham Kent ME8 0JR",
    "addr:housenumber":"12",
    "addr:postcode":"me8 0jr",
    "addr:street":"Woodpecker Glade",
    "iso:country":"GB",
    "sg:address":"12 Woodpecker Glade",
    "sg:city":"Gillingham",
    "sg:classifiers":[
        {
            "category":"Retail",
            "subcategory":"Driving School",
            "type":"Services"
        }
    ],
    "sg:phone":"+44 1634 234716",
    "sg:postcode":"ME8 0JR",
    "sg:province":"Kent",
    "wof:name":"Vertex School Of Motoring",
    "wof:placetype":"venue"
},
  "geometry": {"coordinates":[0.591528,51.351288],"type":"Point"}
}