{
  "type": "Feature",
  "properties": {
    "addr:full":"278 Alcester Rd South, Kings Heath Birmingham West Midlands B14 6EN",
    "addr:housenumber":"278",
    "addr:postcode":"b14 6en",
    "addr:street":"Alcester Rd South",
    "iso:country":"GB",
    "sg:address":"278 Alcester Rd South, Kings Heath",
    "sg:city":"Birmingham",
    "sg:classifiers":[
        {
            "category":"Food & Beverages",
            "subcategory":"Liquor & Beverages",
            "type":"Retail Goods"
        }
    ],
    "sg:phone":"+44 121 444 2862",
    "sg:postcode":"B14 6EN",
    "sg:province":"West Midlands",
    "sg:tags":[
        "beer",
        "spirit",
        "wines"
    ],
    "wof:name":"Drinks Cabin",
    "wof:placetype":"venue"
},
  "geometry": {"coordinates":[-1.899739,52.420567],"type":"Point"}
}