{
  "type": "Feature",
  "properties": {
    "addr:full":"Begbies Traynor, St James's House 28 Park Place Leeds West Yorkshire LS1 2SP",
    "addr:housenumber":"28",
    "addr:postcode":"ls1 2sp",
    "addr:street":"Park Place",
    "iso:country":"GB",
    "sg:address":"Begbies Traynor, St James's House 28 Park Place",
    "sg:city":"Leeds",
    "sg:classifiers":[
        {
            "category":"Freight",
            "type":"Transportation"
        }
    ],
    "sg:postcode":"LS1 2SP",
    "sg:province":"West Yorkshire",
    "sg:tags":[
        "haulage",
        "road"
    ],
    "wof:name":"Heaton Transport Ltd",
    "wof:placetype":"venue"
},
  "geometry": {"coordinates":[-1.5536390543,53.7977676392],"type":"Point"}
}