{
  "type": "Feature",
  "properties": {
    "iso:country":"GB",
    "sg:address":"Grindlay St Court",
    "sg:city":"Edinburgh",
    "sg:classifiers":[
        {
            "category":"Arts & Performance",
            "subcategory":"Art Gallery",
            "type":"Entertainment"
        }
    ],
    "sg:phone":"+44 131 221 0721",
    "sg:postcode":"EH3 9AR",
    "sg:province":"City of Edinburgh",
    "wof:name":"The Contact Gallery",
    "wof:placetype":"venue"
},
  "geometry": {"coordinates":[-3.204578,55.946304],"type":"Point"}
}