{
  "type": "Feature",
  "properties": {
    "iso:country":"GB",
    "sg:address":"3 Angel Pl",
    "sg:city":"Worcester",
    "sg:classifiers":[
        {
            "category":"Food & Beverages",
            "subcategory":"Fruits & Vegetables",
            "type":"Retail Goods"
        }
    ],
    "sg:phone":"+44 1905 22912",
    "sg:postcode":"WR1 3QN",
    "sg:province":"Worcestershire",
    "sg:tags":[
        "greengrocer"
    ],
    "wof:name":"Housewives Choice",
    "wof:placetype":"venue"
},
  "geometry": {"coordinates":[-2.223377,52.193966],"type":"Point"}
}