{
  "type": "Feature",
  "properties": {
    "iso:country":"GB",
    "sg:address":"501 Newton Rd",
    "sg:city":"Warrington",
    "sg:classifiers":[
        {
            "category":"Manufacturing",
            "subcategory":"Tools & Machinery",
            "type":"Manufacturing & Wholesale Goods"
        }
    ],
    "sg:phone":"+44 1925 221345",
    "sg:postcode":"WA3 1PE",
    "sg:province":"Cheshire",
    "sg:tags":[
        "society",
        "friendly"
    ],
    "wof:name":"Hill House Hammond Ltd",
    "wof:placetype":"venue"
},
  "geometry": {"coordinates":[-2.5986599922,53.457862854],"type":"Point"}
}