{
  "type": "Feature",
  "properties": {
    "addr:full":"266 Whitehall Rd Leeds West Yorkshire LS12 4TG",
    "addr:housenumber":"266",
    "addr:postcode":"ls12 4tg",
    "addr:street":"Whitehall Rd",
    "iso:country":"GB",
    "sg:address":"266 Whitehall Rd",
    "sg:city":"Leeds",
    "sg:classifiers":[
        {
            "category":"Professional",
            "subcategory":"Art Services",
            "type":"Services"
        }
    ],
    "sg:postcode":"LS12 4TG",
    "sg:province":"West Yorkshire",
    "sg:tags":[
        "photographer"
    ],
    "wof:name":"Shillito,Paul A,",
    "wof:placetype":"venue"
},
  "geometry": {"coordinates":[-1.594273,53.781727],"type":"Point"}
}