{
  "type": "Feature",
  "properties": {
    "addr:full":"5 Barn Street Strathaven South Lanarkshire ML10 6LU",
    "addr:housenumber":"5",
    "addr:postcode":"ml10 6lu",
    "addr:street":"Barn Street",
    "iso:country":"GB",
    "sg:address":"5 Barn Street",
    "sg:city":"Strathaven",
    "sg:classifiers":[
        {
            "category":"Shopping",
            "subcategory":"News",
            "type":"Retail Goods"
        }
    ],
    "sg:phone":"+44 1357 522540",
    "sg:postcode":"ML10 6LU",
    "sg:province":"South Lanarkshire",
    "sg:tags":[
        "newsagent"
    ],
    "wof:name":"Barn Newsagents",
    "wof:placetype":"venue"
},
  "geometry": {"coordinates":[-4.0657968521,55.6783790588],"type":"Point"}
}