{
  "type": "Feature",
  "properties": {
    "addr:full":"18 Murray Street Duns East Lothian TD11 3DE",
    "addr:housenumber":"18",
    "addr:postcode":"td11 3de",
    "addr:street":"Murray Street",
    "iso:country":"GB",
    "sg:address":"18 Murray Street",
    "sg:city":"Duns",
    "sg:classifiers":[
        {
            "category":"Travel",
            "subcategory":"Hotels & Motels",
            "type":"Entertainment"
        }
    ],
    "sg:postcode":"TD11 3DE",
    "sg:province":"East Lothian",
    "wof:name":"Barniken House Hotel",
    "wof:placetype":"venue"
},
  "geometry": {"coordinates":[-2.3420660496,55.7771034241],"type":"Point"}
}