{
  "type": "Feature",
  "properties": {
    "addr:full":"51 Stamford Avenue Coventry Warwickshire CV3 5BW",
    "addr:housenumber":"51",
    "addr:postcode":"cv3 5bw",
    "addr:street":"Stamford Avenue",
    "iso:country":"GB",
    "sg:address":"51 Stamford Avenue",
    "sg:city":"Coventry",
    "sg:classifiers":[
        {
            "category":"Health Services",
            "subcategory":"Podiatrist",
            "type":"Services"
        }
    ],
    "sg:postcode":"CV3 5BW",
    "sg:province":"Warwickshire",
    "sg:tags":[
        "podiatrists",
        "chiropodist"
    ],
    "wof:name":"Robert H Fawkes",
    "wof:placetype":"venue"
},
  "geometry": {"coordinates":[-1.5128170252,52.388092041],"type":"Point"}
}