{
  "type": "Feature",
  "properties": {
    "addr:full":"80 Manley Rd Sale Cheshire M33 4EW",
    "addr:housenumber":"80",
    "addr:postcode":"m33 4ew",
    "addr:street":"Manley Rd",
    "iso:country":"GB",
    "sg:address":"80 Manley Rd",
    "sg:city":"Sale",
    "sg:classifiers":[
        {
            "category":"Building & Trades",
            "subcategory":"Construction",
            "type":"Services"
        }
    ],
    "sg:phone":"+44 161 962 5440",
    "sg:postcode":"M33 4EW",
    "sg:province":"Cheshire",
    "sg:tags":[
        "decorator",
        "painter"
    ],
    "wof:name":"Ray Twist",
    "wof:placetype":"venue"
},
  "geometry": {"coordinates":[-2.341965,53.407955],"type":"Point"}
}