{
  "type": "Feature",
  "properties": {
    "addr:full":"10 Herdsdown Rochester Kent ME3 9HN",
    "addr:housenumber":"10",
    "addr:postcode":"me3 9hn",
    "addr:street":"Herdsdown Rochester",
    "iso:country":"GB",
    "sg:address":"10 Herdsdown",
    "sg:city":"Rochester",
    "sg:classifiers":[
        {
            "category":"Building & Trades",
            "subcategory":"Construction",
            "type":"Services"
        }
    ],
    "sg:phone":"+44 1634 251053",
    "sg:postcode":"ME3 9HN",
    "sg:province":"Kent",
    "sg:tags":[
        "builder"
    ],
    "wof:name":"Modat Contractors",
    "wof:placetype":"venue"
},
  "geometry": {"coordinates":[0.5522779822,51.4211654663],"type":"Point"}
}