{
  "type": "Feature",
  "properties": {
    "addr:full":"Po Box 313 Torquay Devon TQ1 2WD",
    "addr:housenumber":"po",
    "addr:postcode":"tq1 2wd",
    "addr:street":"Box 313",
    "iso:country":"GB",
    "sg:address":"Po Box 313",
    "sg:city":"Torquay",
    "sg:classifiers":[
        {
            "category":"Manufacturing",
            "subcategory":"Chemicals & Compounds",
            "type":"Manufacturing & Wholesale Goods"
        }
    ],
    "sg:phone":"+44 1803 296595",
    "sg:postcode":"TQ1 2WD",
    "sg:province":"Devon",
    "sg:tags":[
        "abrasive",
        "product",
        "cleaning"
    ],
    "wof:name":"Thorncraft Trading Co. Ltd.",
    "wof:placetype":"venue"
},
  "geometry": {"coordinates":[-3.5264201164,50.4645996094],"type":"Point"}
}