{
  "type": "Feature",
  "properties": {
    "addr:full":"Melrose Ho, 4 Saville Row London Greater London W1S 3PF",
    "addr:housenumber":"4",
    "addr:postcode":"w1s 3pf",
    "addr:street":"Saville Row",
    "iso:country":"GB",
    "sg:address":"Melrose Ho, 4 Saville Row",
    "sg:city":"London",
    "sg:classifiers":[
        {
            "category":"Organizations",
            "subcategory":"Membership Organization",
            "type":"Services"
        }
    ],
    "sg:postcode":"W1S 3PF",
    "sg:province":"Greater London",
    "sg:tags":[
        "club"
    ],
    "wof:name":"Tower Management Ltd",
    "wof:placetype":"venue"
},
  "geometry": {"coordinates":[-0.13981,51.510422],"type":"Point"}
}