{
  "type": "Feature",
  "properties": {
    "iso:country":"GB",
    "sg:address":"80 Burgh Rd, Gorleston",
    "sg:city":"Great Yarmouth",
    "sg:classifiers":[
        {
            "category":"Professional",
            "subcategory":"Engineering",
            "type":"Services"
        }
    ],
    "sg:phone":"+44 1493 668315",
    "sg:postcode":"NR31 8BD",
    "sg:province":"Norfolk",
    "sg:tags":[
        "civil",
        "engineer"
    ],
    "wof:name":"Shift Close Ltd",
    "wof:placetype":"venue"
},
  "geometry": {"coordinates":[1.7183580399,52.5864486694],"type":"Point"}
}