{
  "type": "Feature",
  "properties": {
    "iso:country":"GB",
    "sg:address":"30 Woodlands Road",
    "sg:city":"Romford",
    "sg:classifiers":[
        {
            "category":"Building & Trades",
            "subcategory":"Construction",
            "type":"Services"
        }
    ],
    "sg:phone":"+44 1708 372717",
    "sg:postcode":"RM3 0QX",
    "sg:province":"Essex",
    "sg:tags":[
        "roofing"
    ],
    "wof:name":"D & R Roofing Co.",
    "wof:placetype":"venue"
},
  "geometry": {"coordinates":[0.2385639995,51.5942497253],"type":"Point"}
}