{
  "type": "Feature",
  "properties": {
    "iso:country":"GB",
    "sg:address":"12 Allhalland Street",
    "sg:city":"Bideford",
    "sg:classifiers":[
        {
            "category":"Shopping",
            "subcategory":"Crafts & Fabrics",
            "type":"Retail Goods"
        }
    ],
    "sg:phone":"+44 1237 423437",
    "sg:postcode":"EX39 2JD",
    "sg:province":"Devon",
    "sg:tags":[
        "material",
        "art"
    ],
    "wof:name":"Garlans Art",
    "wof:placetype":"venue"
},
  "geometry": {"coordinates":[-4.205363,51.017647],"type":"Point"}
}