{
  "type": "Feature",
  "properties": {
    "iso:country":"GB",
    "sg:address":"65 St Johns",
    "sg:city":"Worcester",
    "sg:classifiers":[
        {
            "category":"Fast Food",
            "type":"Food & Drink"
        }
    ],
    "sg:phone":"+44 1905 748188",
    "sg:postcode":"WR2 5AG",
    "sg:province":"Worcestershire",
    "sg:tags":[
        "away",
        "take"
    ],
    "wof:name":"Fortune House Chinese Take-Away",
    "wof:placetype":"venue"
},
  "geometry": {"coordinates":[-2.235079,52.187332],"type":"Point"}
}