{
  "type": "Feature",
  "properties": {
    "addr:full":"Burton Rd, Rosliston Swadlincote Derbyshire DE12 8JU",
    "addr:postcode":"de12 8ju",
    "addr:street":"Burton Rd",
    "iso:country":"GB",
    "sg:address":"Burton Rd, Rosliston",
    "sg:city":"Swadlincote",
    "sg:classifiers":[
        {
            "category":"Bars & Pubs",
            "type":"Food & Drink"
        }
    ],
    "sg:phone":"+44 1283 761705",
    "sg:postcode":"DE12 8JU",
    "sg:province":"Derbyshire",
    "sg:tags":[
        "pubs",
        "inn"
    ],
    "wof:name":"The Bulls Head",
    "wof:placetype":"venue"
},
  "geometry": {"coordinates":[-1.642307,52.748905],"type":"Point"}
}