{
  "type": "Feature",
  "properties": {
    "addr:full":"18 High Street, Sunninghill Ascot Berkshire SL5 9NE",
    "addr:housenumber":"18",
    "addr:postcode":"sl5 9ne",
    "addr:street":"High Street",
    "iso:country":"GB",
    "sg:address":"18 High Street, Sunninghill",
    "sg:city":"Ascot",
    "sg:classifiers":[
        {
            "category":"Restaurant",
            "type":"Food & Drink"
        }
    ],
    "sg:phone":"+44 1344 873062",
    "sg:postcode":"SL5 9NE",
    "sg:province":"Berkshire",
    "wof:name":"The Viceroy",
    "wof:placetype":"venue"
},
  "geometry": {"coordinates":[-0.6549969912,51.4019966125],"type":"Point"}
}