{
  "type": "Feature",
  "properties": {
    "addr:full":"819 Liverpool Road, Eccles Manchester Greater Manchester M30 7LH",
    "addr:housenumber":"819",
    "addr:postcode":"m30 7lh",
    "addr:street":"Liverpool Road",
    "iso:country":"GB",
    "sg:address":"819 Liverpool Road, Eccles",
    "sg:city":"Manchester",
    "sg:classifiers":[
        {
            "category":"Shopping",
            "subcategory":"News",
            "type":"Retail Goods"
        }
    ],
    "sg:phone":"+44 161 789 3574",
    "sg:postcode":"M30 7LH",
    "sg:province":"Greater Manchester",
    "sg:tags":[
        "newsagent"
    ],
    "wof:name":"P & A News",
    "wof:placetype":"venue"
},
  "geometry": {"coordinates":[-2.3752400875,53.4745025635],"type":"Point"}
}