{
  "type": "Feature",
  "properties": {
    "iso:country":"GB",
    "sg:address":"Brookside, Weston Rhyn",
    "sg:city":"Oswestry",
    "sg:classifiers":[
        {
            "category":"Building & Trades",
            "subcategory":"Construction",
            "type":"Services"
        }
    ],
    "sg:phone":"+44 1691 774612",
    "sg:postcode":"SY10 7LY",
    "sg:province":"Shropshire",
    "sg:tags":[
        "builder"
    ],
    "wof:name":"Brookside Building & Developments Ltd.",
    "wof:placetype":"venue"
},
  "geometry": {"coordinates":[-3.054109,52.917259],"type":"Point"}
}