{
  "type": "Feature",
  "properties": {
    "iso:country":"GB",
    "sg:address":"31 Queens Road",
    "sg:city":"Aberdeen",
    "sg:classifiers":[
        {
            "category":"Health Services",
            "subcategory":"Nursing And Care Facility",
            "type":"Services"
        }
    ],
    "sg:phone":"+44 1224 312255",
    "sg:postcode":"AB15 4ZN",
    "sg:province":"Aberdeen City",
    "sg:tags":[
        "home"
    ],
    "wof:name":"Maryfield West Nursing Home",
    "wof:placetype":"venue"
},
  "geometry": {"coordinates":[-2.134097,57.141453],"type":"Point"}
}