{
  "type": "Feature",
  "properties": {
    "iso:country":"GB",
    "sg:address":"140 Crabtree Lane",
    "sg:city":"Lancing",
    "sg:classifiers":[
        {
            "category":"Bars & Pubs",
            "type":"Food & Drink"
        }
    ],
    "sg:phone":"+44 1903 875901",
    "sg:postcode":"BN15 9NQ",
    "sg:province":"West Sussex",
    "sg:tags":[
        "pubs",
        "inn"
    ],
    "wof:name":"The Crabtree",
    "wof:placetype":"venue"
},
  "geometry": {"coordinates":[-0.328709,50.832256],"type":"Point"}
}