{
  "type": "Feature",
  "properties": {
    "addr:full":"Lawes House, 66-68 Bristol Road Bristol Somerset BS20 6QG",
    "addr:housenumber":"66-68",
    "addr:postcode":"bs20 6qg",
    "addr:street":"Bristol Road",
    "iso:country":"GB",
    "sg:address":"Lawes House, 66-68 Bristol Road",
    "sg:city":"Bristol",
    "sg:classifiers":[
        {
            "category":"Autos & Motor Vehicles",
            "subcategory":"Fuel & Gas Station",
            "type":"Retail Goods"
        }
    ],
    "sg:phone":"+44 1275 843121",
    "sg:postcode":"BS20 6QG",
    "sg:province":"Somerset",
    "sg:tags":[
        "hr",
        "petrol"
    ],
    "wof:name":"S G P Trading Ltd.",
    "wof:placetype":"venue"
},
  "geometry": {"coordinates":[-2.760959,51.476143],"type":"Point"}
}