{
  "type": "Feature",
  "properties": {
    "addr:full":"6 Bayley Street London Greater London WC1B 3HE",
    "addr:housenumber":"6",
    "addr:postcode":"wc1b 3he",
    "addr:street":"Bayley Street",
    "iso:country":"GB",
    "sg:address":"6 Bayley Street",
    "sg:city":"London",
    "sg:classifiers":[
        {
            "category":"Organizations",
            "subcategory":"Professional Association",
            "type":"Services"
        }
    ],
    "sg:phone":"+44 20 7304 4100",
    "sg:postcode":"WC1B 3HE",
    "sg:province":"Greater London",
    "sg:tags":[
        "literary",
        "agent"
    ],
    "wof:name":"Ed Victor Ltd.",
    "wof:placetype":"venue"
},
  "geometry": {"coordinates":[-0.131381,51.518955],"type":"Point"}
}