{
  "type": "Feature",
  "properties": {
    "addr:full":"Telephone Exchange, Alverton Lane Northallerton North Yorkshire DL7 8TR",
    "addr:postcode":"dl7 8tr",
    "addr:street":"Alverton Lane",
    "iso:country":"GB",
    "sg:address":"Telephone Exchange, Alverton Lane",
    "sg:city":"Northallerton",
    "sg:classifiers":[
        {
            "category":"Freight",
            "type":"Transportation"
        }
    ],
    "sg:phone":"+44 1609 777200",
    "sg:postcode":"DL7 8TR",
    "sg:province":"North Yorkshire",
    "sg:tags":[
        "haulage",
        "road"
    ],
    "wof:name":"Schott Transport & Removals",
    "wof:placetype":"venue"
},
  "geometry": {"coordinates":[-1.43524,54.337009],"type":"Point"}
}