{
  "type": "Feature",
  "properties": {
    "addr:full":"36 Green St Ayr South Ayrshire KA8 8BQ",
    "addr:housenumber":"36",
    "addr:postcode":"ka8 8bq",
    "addr:street":"Green St",
    "iso:country":"GB",
    "sg:address":"36 Green St",
    "sg:city":"Ayr",
    "sg:classifiers":[
        {
            "category":"Manufacturing",
            "subcategory":"Building Materials",
            "type":"Manufacturing & Wholesale Goods"
        }
    ],
    "sg:phone":"+44 1292 611291",
    "sg:postcode":"KA8 8BQ",
    "sg:province":"South Ayrshire",
    "sg:tags":[
        "merchant",
        "builder"
    ],
    "wof:name":"Graham Builders Merchants",
    "wof:placetype":"venue"
},
  "geometry": {"coordinates":[-4.632830143,55.4688301086],"type":"Point"}
}