{
  "type": "Feature",
  "properties": {
    "iso:country":"GB",
    "sg:address":"87 Rowan Way",
    "sg:city":"Yeovil",
    "sg:classifiers":[
        {
            "category":"Building & Trades",
            "subcategory":"Construction",
            "type":"Services"
        }
    ],
    "sg:phone":"+44 1935 472567",
    "sg:postcode":"BA20 2NS",
    "sg:province":"Somerset",
    "sg:tags":[
        "roofing",
        "contracting"
    ],
    "wof:name":"Burden & Best",
    "wof:placetype":"venue"
},
  "geometry": {"coordinates":[-2.644399,50.93399],"type":"Point"}
}