{
  "type": "Feature",
  "properties": {
    "addr:full":"Middlegrove, Woodwater Lane Exeter Devon EX2 5JY",
    "addr:postcode":"ex2 5jy",
    "addr:street":"Woodwater Lane",
    "iso:country":"GB",
    "sg:address":"Middlegrove, Woodwater Lane",
    "sg:city":"Exeter",
    "sg:classifiers":[
        {
            "category":"Retail",
            "subcategory":"Auto Repair",
            "type":"Services"
        }
    ],
    "sg:phone":"+44 1392 221668",
    "sg:postcode":"EX2 5JY",
    "sg:province":"Devon",
    "sg:tags":[
        "modification",
        "garage"
    ],
    "wof:name":"Auto Sales & Repairs",
    "wof:placetype":"venue"
},
  "geometry": {"coordinates":[-3.4933900833,50.7167205811],"type":"Point"}
}