{
  "type": "Feature",
  "properties": {
    "iso:country":"GB",
    "sg:address":"74a Station Road East",
    "sg:city":"Oxted",
    "sg:classifiers":[
        {
            "category":"Real Estate",
            "subcategory":"Real Estate Agent",
            "type":"Services"
        }
    ],
    "sg:postcode":"RH8 0PG",
    "sg:province":"Surrey",
    "wof:name":"Horizon Properties Ltd",
    "wof:placetype":"venue"
},
  "geometry": {"coordinates":[-0.003067,51.257996],"type":"Point"}
}