{
  "type": "Feature",
  "properties": {
    "iso:country":"GB",
    "sg:address":"21 Churchill Precinct",
    "sg:city":"Dudley",
    "sg:classifiers":[
        {
            "category":"Personal",
            "subcategory":"Beauty Salon",
            "type":"Services"
        }
    ],
    "sg:phone":"+44 1384 258856",
    "sg:postcode":"DY2 7BL",
    "sg:province":"West Midlands",
    "sg:tags":[
        "unisex",
        "hairdresser"
    ],
    "wof:name":"Martanne Hair Designers",
    "wof:placetype":"venue"
},
  "geometry": {"coordinates":[-2.127294,52.53846],"type":"Point"}
}