{
  "type": "Feature",
  "properties": {
    "addr:full":"8 Douglas Street Dunfermline Fife KY12 7EB",
    "addr:housenumber":"8",
    "addr:postcode":"ky12 7eb",
    "addr:street":"Douglas Street",
    "iso:country":"GB",
    "sg:address":"8 Douglas Street",
    "sg:city":"Dunfermline",
    "sg:classifiers":[
        {
            "category":"Shopping",
            "subcategory":"Gifts & Souvenirs",
            "type":"Retail Goods"
        }
    ],
    "sg:postcode":"KY12 7EB",
    "sg:province":"Fife",
    "sg:tags":[
        "shop"
    ],
    "wof:name":"Gift Set & Match",
    "wof:placetype":"venue"
},
  "geometry": {"coordinates":[-3.4605810642,56.0717277527],"type":"Point"}
}