{
  "type": "Feature",
  "properties": {
    "addr:full":"183 Barnbygate Newark Nottinghamshire NG24 1RJ",
    "addr:housenumber":"183",
    "addr:postcode":"ng24 1rj",
    "addr:street":"Barnbygate",
    "iso:country":"GB",
    "sg:address":"183 Barnbygate",
    "sg:city":"Newark",
    "sg:classifiers":[
        {
            "category":"Shopping",
            "subcategory":"Computers & Home Electronics",
            "type":"Retail Goods"
        }
    ],
    "sg:postcode":"NG24 1RJ",
    "sg:province":"Nottinghamshire",
    "sg:tags":[
        "aerial",
        "television",
        "radio"
    ],
    "wof:name":"Richard Miller Audio Systems",
    "wof:placetype":"venue"
},
  "geometry": {"coordinates":[-0.805941,53.076717],"type":"Point"}
}