{
  "type": "Feature",
  "properties": {
    "addr:full":"17 Atlantic Way, Porthtowan Truro Cornwall TR4 8AH",
    "addr:housenumber":"17",
    "addr:postcode":"tr4 8ah",
    "addr:street":"Atlantic Way",
    "iso:country":"GB",
    "sg:address":"17 Atlantic Way, Porthtowan",
    "sg:city":"Truro",
    "sg:classifiers":[
        {
            "category":"Autos & Motor Vehicles",
            "subcategory":"Auto Supplies",
            "type":"Retail Goods"
        }
    ],
    "sg:postcode":"TR4 8AH",
    "sg:province":"Cornwall",
    "sg:tags":[
        "towbars"
    ],
    "wof:name":"Kernow Towbar Services",
    "wof:placetype":"venue"
},
  "geometry": {"coordinates":[-5.236554,50.28611],"type":"Point"}
}