{
  "type": "Feature",
  "properties": {
    "addr:full":"46a Albert Road North Reigate Surrey RH2 9EL",
    "addr:housenumber":"46a",
    "addr:postcode":"rh2 9el",
    "addr:street":"Albert Road North Reigate",
    "iso:country":"GB",
    "sg:address":"46a Albert Road North",
    "sg:city":"Reigate",
    "sg:classifiers":[
        {
            "category":"Building & Trades",
            "subcategory":"Construction",
            "type":"Services"
        }
    ],
    "sg:phone":"+44 1737 243243",
    "sg:postcode":"RH2 9EL",
    "sg:province":"Surrey",
    "sg:tags":[
        "builder"
    ],
    "wof:name":"Telling (UK) Ltd",
    "wof:placetype":"venue"
},
  "geometry": {"coordinates":[-0.2136660069,51.2426795959],"type":"Point"}
}