{
  "type": "Feature",
  "properties": {
    "addr:full":"West End Studios, Warley Road Halifax West Yorkshire HX1 3TG",
    "addr:postcode":"hx1 3tg",
    "addr:street":"Warley Road",
    "iso:country":"GB",
    "sg:address":"West End Studios, Warley Road",
    "sg:city":"Halifax",
    "sg:classifiers":[
        {
            "category":"Home & Garden",
            "subcategory":"Home Furnishings",
            "type":"Retail Goods"
        }
    ],
    "sg:postcode":"HX1 3TG",
    "sg:province":"West Yorkshire",
    "sg:tags":[
        "blind",
        "curtain",
        "fitting"
    ],
    "wof:name":"F Lucas & Co.",
    "wof:placetype":"venue"
},
  "geometry": {"coordinates":[-1.880069,53.716911],"type":"Point"}
}