{
  "type": "Feature",
  "properties": {
    "addr:full":"Moss Rose Mill, Springfield Road, Bearsley Bolton Lancashire BL4 8JW",
    "addr:postcode":"bl4 8jw",
    "addr:street":"Moss Rose Mill Springfield Road Bearsley",
    "iso:country":"GB",
    "sg:address":"Moss Rose Mill, Springfield Road, Bearsley",
    "sg:city":"Bolton",
    "sg:classifiers":[
        {
            "category":"Professional",
            "subcategory":"Printing & Photocopies",
            "type":"Services"
        }
    ],
    "sg:phone":"+44 1204 571686",
    "sg:postcode":"BL4 8JW",
    "sg:province":"Lancashire",
    "sg:tags":[
        "embroiderer"
    ],
    "wof:name":"Felicity Rose Ltd.",
    "wof:placetype":"venue"
},
  "geometry": {"coordinates":[-2.3748700619,53.5387611389],"type":"Point"}
}