{
  "type": "Feature",
  "properties": {
    "addr:full":"24-25 East Side London Greater London W12 8DG",
    "addr:housenumber":"24-25",
    "addr:postcode":"w12 8dg",
    "addr:street":"East",
    "iso:country":"GB",
    "sg:address":"24-25 East Side",
    "sg:city":"London",
    "sg:classifiers":[
        {
            "category":"Communications",
            "type":"Services"
        }
    ],
    "sg:phone":"+44 20 8743 3891",
    "sg:postcode":"W12 8DG",
    "sg:province":"Greater London",
    "sg:tags":[
        "broadcasting"
    ],
    "wof:name":"E Mills & Son (Linoleum) Ltd.",
    "wof:placetype":"venue"
},
  "geometry": {"coordinates":[-0.22666,51.504318],"type":"Point"}
}