{
  "type": "Feature",
  "properties": {
    "addr:full":"Wobage Farm Ross-on-wye Gloucestershire HR9 7QP",
    "addr:postcode":"hr9 7qp",
    "iso:country":"GB",
    "sg:address":"Wobage Farm",
    "sg:city":"Ross-on-wye",
    "sg:classifiers":[
        {
            "category":"Manufacturing",
            "subcategory":"Wood Products",
            "type":"Manufacturing & Wholesale Goods"
        }
    ],
    "sg:postcode":"HR9 7QP",
    "sg:province":"Gloucestershire",
    "sg:tags":[
        "maker",
        "cabinet"
    ],
    "wof:name":"B W Casson",
    "wof:placetype":"venue"
},
  "geometry": {"coordinates":[-2.581733,51.916481],"type":"Point"}
}