{
  "type": "Feature",
  "properties": {
    "addr:full":"9-10 Charlotte Road 1st Floor London EC2A3DH ",
    "addr:housenumber":"9-10",
    "addr:postcode":"ec2a3dh",
    "addr:street":"Charlotte Road 1St Floor",
    "iso:country":"GB",
    "sg:address":"9-10 Charlotte Road 1st Floor",
    "sg:city":"London",
    "sg:classifiers":[
        {
            "category":"Professional",
            "subcategory":"Computer Services",
            "type":"Services"
        }
    ],
    "sg:postcode":"EC2A3DH ",
    "sg:tags":[
        "shutl",
        "e-commerce",
        "logistics",
        "retail",
        "multi-channel",
        "saas",
        "cloud-courier",
        "web-service",
        "delivery-platform",
        "ceo",
        "delivery",
        "entrepreneur",
        "british-entrepreneur",
        "london",
        "dartmouth",
        "courier",
        "british",
        "swiss",
        "bermudian",
        "switzerland",
        "bermuda",
        "shoreditch",
        "ecourier"
    ],
    "sg:website":"http://shutl.co.uk",
    "wof:name":"Shutl",
    "wof:placetype":"venue"
},
  "geometry": {"coordinates":[-0.1020265,51.5196135],"type":"Point"}
}