{
  "type": "Feature",
  "properties": {
    "addr:full":"Oare Road, Luddenham Faversham Kent ME13 7TJ",
    "addr:postcode":"me13 7tj",
    "addr:street":"Oare Road",
    "iso:country":"GB",
    "sg:address":"Oare Road, Luddenham",
    "sg:city":"Faversham",
    "sg:classifiers":[
        {
            "category":"Bars & Pubs",
            "type":"Food & Drink"
        }
    ],
    "sg:phone":"+44 1795 534291",
    "sg:postcode":"ME13 7TJ",
    "sg:province":"Kent",
    "sg:tags":[
        "pubs",
        "inn"
    ],
    "wof:name":"Windmill Inn",
    "wof:placetype":"venue"
},
  "geometry": {"coordinates":[0.8833709955,51.3241920471],"type":"Point"}
}