{
  "type": "Feature",
  "properties": {
    "iso:country":"GB",
    "sg:address":"Wendene",
    "sg:city":"Norwich",
    "sg:classifiers":[
        {
            "category":"Food & Beverages",
            "subcategory":"Supermarket",
            "type":"Retail Goods"
        }
    ],
    "sg:phone":"+44 1603 748944",
    "sg:postcode":"NR5 9HA",
    "sg:province":"Norfolk",
    "wof:name":"Powerleague Group Ltd.",
    "wof:placetype":"venue"
},
  "geometry": {"coordinates":[1.219763,52.640804],"type":"Point"}
}