{
  "type": "Feature",
  "properties": {
    "iso:country":"GB",
    "sg:address":"Hunholme Garage, Boot",
    "sg:city":"Holmrook",
    "sg:classifiers":[
        {
            "category":"Bus Charters",
            "type":"Transportation"
        }
    ],
    "sg:phone":"+44 19467 23227",
    "sg:postcode":"CA19 1TF",
    "sg:province":"Cumbria",
    "sg:tags":[
        "hire",
        "coach"
    ],
    "wof:name":"WILLIAM SIM & SON",
    "wof:placetype":"venue"
},
  "geometry": {"coordinates":[-3.419796,54.385403],"type":"Point"}
}