{
  "type": "Feature",
  "properties": {
    "addr:full":"Birchwood House, Uvedale Road Oxted Surrey RH8 0EW",
    "addr:postcode":"rh8 0ew",
    "addr:street":"Uvedale Road",
    "iso:country":"GB",
    "sg:address":"Birchwood House, Uvedale Road",
    "sg:city":"Oxted",
    "sg:classifiers":[
        {
            "category":"Manufacturing",
            "subcategory":"Electronics",
            "type":"Manufacturing & Wholesale Goods"
        }
    ],
    "sg:phone":"+44 1883 716925",
    "sg:postcode":"RH8 0EW",
    "sg:province":"Surrey",
    "sg:tags":[
        "control",
        "component",
        "-",
        "electronic"
    ],
    "wof:name":"Blue Chip Semiconductors (Uk) Ltd",
    "wof:placetype":"venue"
},
  "geometry": {"coordinates":[0.001451,51.255005],"type":"Point"}
}