{
  "type": "Feature",
  "properties": {
    "addr:full":"Wobage Farm, Upton Bishop Ross-on-wye Gloucestershire HR9 7QP",
    "addr:housenumber":"upton",
    "addr:postcode":"hr9 7qp",
    "addr:street":"Bishop Ross-On-Wye Gloucestershire",
    "iso:country":"GB",
    "sg:address":"Wobage Farm, Upton Bishop",
    "sg:city":"Ross-on-wye",
    "sg:classifiers":[
        {
            "category":"Manufacturing",
            "subcategory":"Pottery",
            "type":"Manufacturing & Wholesale Goods"
        }
    ],
    "sg:postcode":"HR9 7QP",
    "sg:province":"Gloucestershire",
    "wof:name":"Patia Davis",
    "wof:placetype":"venue"
},
  "geometry": {"coordinates":[-2.581733,51.916481],"type":"Point"}
}