{
  "type": "Feature",
  "properties": {
    "iso:country":"GB",
    "sg:address":"Third Floor, Adamson House",
    "sg:city":"Manchester",
    "sg:classifiers":[
        {
            "category":"Professional",
            "subcategory":"Detective & Security Services",
            "type":"Services"
        }
    ],
    "sg:phone":"+44 161 872 0999",
    "sg:postcode":"M16 0TT",
    "sg:province":"Cheshire",
    "wof:name":"Reliance Security Services Ltd.",
    "wof:placetype":"venue"
},
  "geometry": {"coordinates":[-2.2733490467,53.4528884888],"type":"Point"}
}