{
  "type": "Feature",
  "properties": {
    "iso:country":"GB",
    "sg:address":"Moorfield House, The Common, Evershot",
    "sg:city":"Dorchester",
    "sg:classifiers":[
        {
            "category":"Professional",
            "subcategory":"Management & Consulting",
            "type":"Services"
        }
    ],
    "sg:phone":"+44 1935 83556",
    "sg:postcode":"DT2 0JY",
    "sg:province":"Dorset",
    "sg:tags":[
        "marketing",
        "consultant"
    ],
    "wof:name":"Tangram Creative Marketing Consultancy",
    "wof:placetype":"venue"
},
  "geometry": {"coordinates":[-2.605637,50.838596],"type":"Point"}
}