{
  "type": "Feature",
  "properties": {
    "addr:full":"Unit 9, Westfield Farm, Medmenham Marlow Berkshire SL7 2HE",
    "addr:housenumber":"unit 9 westfield farm medmenham",
    "addr:postcode":"sl7 2he",
    "iso:country":"GB",
    "sg:address":"Unit 9, Westfield Farm, Medmenham",
    "sg:city":"Marlow",
    "sg:classifiers":[
        {
            "category":"Communications",
            "subcategory":"Film & Video Production",
            "type":"Services"
        },
        {
            "category":"Professional",
            "subcategory":"Printing & Photocopies",
            "type":"Services"
        }
    ],
    "sg:phone":"+44 1491 414345",
    "sg:postcode":"SL7 2HE",
    "sg:province":"Berkshire",
    "sg:tags":[
        "supplier",
        "duplicating",
        "copying",
        "photocopier"
    ],
    "wof:name":"International Copiers Ltd.",
    "wof:placetype":"venue"
},
  "geometry": {"coordinates":[-0.8230670094,51.5571708679],"type":"Point"}
}