{
  "type": "Feature",
  "properties": {
    "addr:full":"46 High Street Totnes Devon TQ9 5SH",
    "addr:housenumber":"46",
    "addr:postcode":"tq9 5sh",
    "addr:street":"High Street",
    "iso:country":"GB",
    "sg:address":"46 High Street",
    "sg:city":"Totnes",
    "sg:classifiers":[
        {
            "category":"Restaurant",
            "type":"Food & Drink"
        }
    ],
    "sg:phone":"+44 1803 863159",
    "sg:postcode":"TQ9 5SH",
    "sg:province":"Devon",
    "sg:tags":[
        "italian"
    ],
    "wof:name":"Amalfi Italian Restaurant",
    "wof:placetype":"venue"
},
  "geometry": {"coordinates":[-3.6894669533,50.4314498901],"type":"Point"}
}