{
  "type": "Feature",
  "properties": {
    "addr:full":"54 Seymour Road Trowbridge Wiltshire BA14 8LT",
    "addr:housenumber":"54",
    "addr:postcode":"ba14 8lt",
    "addr:street":"Seymour Road",
    "iso:country":"GB",
    "sg:address":"54 Seymour Road",
    "sg:city":"Trowbridge",
    "sg:classifiers":[
        {
            "category":"Professional",
            "subcategory":"Art Services",
            "type":"Services"
        }
    ],
    "sg:postcode":"BA14 8LT",
    "sg:province":"Wiltshire",
    "sg:tags":[
        "photographer"
    ],
    "wof:name":"Michael Padbury Photography",
    "wof:placetype":"venue"
},
  "geometry": {"coordinates":[-2.210177,51.325684],"type":"Point"}
}