{
  "type": "Feature",
  "properties": {
    "iso:country":"GB",
    "sg:address":"41 Inchmurrin Drive, Rutherglen",
    "sg:city":"Glasgow",
    "sg:classifiers":[
        {
            "category":"Banks & Credit Unions",
            "subcategory":"Financial Services",
            "type":"Services"
        }
    ],
    "sg:phone":"+44 141 631 3300",
    "sg:postcode":"G73 5RT",
    "sg:province":"Glasgow City",
    "sg:tags":[
        "adviser"
    ],
    "wof:name":"Dixon Forsyth & Co Independent Financial Advisors",
    "wof:placetype":"venue"
},
  "geometry": {"coordinates":[-4.1945319176,55.8025550842],"type":"Point"}
}