{
  "type": "Feature",
  "properties": {
    "addr:full":"23 St Catherine St Banff Aberdeenshire AB45 1JQ",
    "addr:housenumber":"23",
    "addr:postcode":"ab45 1jq",
    "addr:street":"St Catherine St",
    "iso:country":"GB",
    "sg:address":"23 St Catherine St",
    "sg:city":"Banff",
    "sg:classifiers":[
        {
            "category":"Building & Trades",
            "subcategory":"Construction",
            "type":"Services"
        }
    ],
    "sg:phone":"+44 1261 812716",
    "sg:postcode":"AB45 1JQ",
    "sg:province":"Aberdeenshire",
    "sg:tags":[
        "decorator",
        "painter"
    ],
    "wof:name":"Cameron & Nicol",
    "wof:placetype":"venue"
},
  "geometry": {"coordinates":[-2.5267920494,57.6679000854],"type":"Point"}
}