{
  "type": "Feature",
  "properties": {
    "iso:country":"GB",
    "sg:address":"Christ Church, Tacket Street",
    "sg:city":"Ipswich",
    "sg:classifiers":[
        {
            "category":"Place Of Worship",
            "type":"Public Place"
        }
    ],
    "sg:phone":"+44 1473 281430",
    "sg:postcode":"IP4 1AU",
    "sg:province":"Suffolk",
    "wof:name":"East Anglia Baptist Youth",
    "wof:placetype":"venue"
},
  "geometry": {"coordinates":[1.1567699909,52.0560188293],"type":"Point"}
}