{
  "type": "Feature",
  "properties": {
    "addr:full":"Westfield Nurseries Scarborough, Road, Norton Malton North Yorkshire YO17 8AE",
    "addr:postcode":"yo17 8ae",
    "addr:street":"Scarborough Road",
    "iso:country":"GB",
    "sg:address":"Westfield Nurseries Scarborough, Road, Norton",
    "sg:city":"Malton",
    "sg:classifiers":[
        {
            "category":"Shopping",
            "subcategory":"Florist",
            "type":"Retail Goods"
        }
    ],
    "sg:phone":"+44 1653 692234",
    "sg:postcode":"YO17 8AE",
    "sg:province":"North Yorkshire",
    "wof:name":"W P Horsley",
    "wof:placetype":"venue"
},
  "geometry": {"coordinates":[-0.7728379965,54.1334991455],"type":"Point"}
}