{
  "type": "Feature",
  "properties": {
    "addr:full":"Club House Brynteg Isle of Anglesey LL78 8JY",
    "addr:postcode":"ll78 8jy",
    "addr:street":"Club",
    "iso:country":"GB",
    "sg:address":"Club House",
    "sg:city":"Brynteg",
    "sg:classifiers":[
        {
            "category":"Sports & Exercise",
            "subcategory":"Golf",
            "type":"Entertainment"
        }
    ],
    "sg:phone":"+44 1248 852673",
    "sg:postcode":"LL78 8JY",
    "sg:province":"Isle of Anglesey",
    "sg:tags":[
        "club",
        "course"
    ],
    "wof:name":"Storws Wen Golf Club",
    "wof:placetype":"venue"
},
  "geometry": {"coordinates":[-4.2594590187,53.319606781],"type":"Point"}
}