{
  "type": "Feature",
  "properties": {
    "iso:country":"GB",
    "sg:address":"Grn Lane, Stoneycroft",
    "sg:city":"Liverpool",
    "sg:classifiers":[
        {
            "category":"Education",
            "subcategory":"Library",
            "type":"Public Place"
        }
    ],
    "sg:phone":"+44 151 228 3004",
    "sg:postcode":"L13 7EB",
    "sg:province":"Merseyside",
    "sg:tags":[
        "book"
    ],
    "wof:name":"Lister Drive Library",
    "wof:placetype":"venue"
},
  "geometry": {"coordinates":[-2.929154,53.424259],"type":"Point"}
}