{
  "type": "Feature",
  "properties": {
    "iso:country":"GB",
    "sg:address":"1 Bellefield Avenue",
    "sg:city":"Dundee",
    "sg:classifiers":[
        {
            "category":"Wholesale",
            "subcategory":"Books, Periodicals, & Newspapers",
            "type":"Manufacturing & Wholesale Goods"
        }
    ],
    "sg:phone":"+44 1382 205154",
    "sg:postcode":"DD1 4NG",
    "sg:province":"Dundee City",
    "sg:tags":[
        "publishing"
    ],
    "wof:name":"Gaels Blue Associates",
    "wof:placetype":"venue"
},
  "geometry": {"coordinates":[-2.987511,56.453316],"type":"Point"}
}