{
  "type": "Feature",
  "properties": {
    "iso:country":"GB",
    "sg:address":"21 West Street",
    "sg:city":"Wareham",
    "sg:classifiers":[
        {
            "category":"Food & Beverages",
            "subcategory":"Meat & Fish",
            "type":"Retail Goods"
        }
    ],
    "sg:postcode":"BH20 4JS",
    "sg:province":"Dorset",
    "sg:tags":[
        "chip"
    ],
    "wof:name":"Long Johns Fish & Chips",
    "wof:placetype":"venue"
},
  "geometry": {"coordinates":[-2.111018,50.685535],"type":"Point"}
}