{
  "type": "Feature",
  "properties": {
    "addr:full":"Orchard Surgery, Dragwell Derby Leicestershire DE74 2EL",
    "addr:postcode":"de74 2el",
    "iso:country":"GB",
    "sg:address":"Orchard Surgery, Dragwell",
    "sg:city":"Derby",
    "sg:classifiers":[
        {
            "category":"Health Services",
            "subcategory":"Doctor",
            "type":"Services"
        }
    ],
    "sg:phone":"+44 1509 672419",
    "sg:postcode":"DE74 2EL",
    "sg:province":"Leicestershire",
    "sg:tags":[
        "practitioners"
    ],
    "wof:name":"Foster, N J",
    "wof:placetype":"venue"
},
  "geometry": {"coordinates":[-1.3456720114,52.8419456482],"type":"Point"}
}