{
  "type": "Feature",
  "properties": {
    "addr:full":"92 Dalston Lane London Greater London E8 1NG",
    "addr:housenumber":"92",
    "addr:postcode":"e8 1ng",
    "addr:street":"Dalston Lane",
    "iso:country":"GB",
    "sg:address":"92 Dalston Lane",
    "sg:city":"London",
    "sg:classifiers":[
        {
            "category":"Organizations",
            "subcategory":"Non-profit Organization",
            "type":"Services"
        }
    ],
    "sg:phone":"+44 20 7254 2110",
    "sg:postcode":"E8 1NG",
    "sg:province":"Greater London",
    "sg:tags":[
        "organisation",
        "voluntary",
        "charity"
    ],
    "wof:name":"British Red Cross",
    "wof:placetype":"venue"
},
  "geometry": {"coordinates":[-0.069463,51.54641],"type":"Point"}
}