{
  "type": "Feature",
  "properties": {
    "iso:country":"GB",
    "sg:address":"52 Upper St",
    "sg:city":"Islington",
    "sg:classifiers":[
        {
            "category":"Sports & Exercise",
            "subcategory":"Playing Field",
            "type":"Entertainment"
        }
    ],
    "sg:phone":"+44 20 7288 6198",
    "sg:postcode":"N1 0QH",
    "sg:province":"Greater London",
    "sg:tags":[
        "sanitary",
        "hygiene",
        "appliance"
    ],
    "wof:name":"Clean Concepts",
    "wof:placetype":"venue"
},
  "geometry": {"coordinates":[-0.1043369994,51.5353736877],"type":"Point"}
}