{
  "type": "Feature",
  "properties": {
    "addr:full":"15, Capital Pl, Lovet Rd, Pinnacles Harlow Essex CM19 5AS",
    "addr:housenumber":"15",
    "addr:postcode":"cm19 5as",
    "addr:street":"Capital Pl Lovet Rd",
    "iso:country":"GB",
    "sg:address":"15, Capital Pl, Lovet Rd, Pinnacles",
    "sg:city":"Harlow",
    "sg:classifiers":[
        {
            "category":"Shopping",
            "subcategory":"Computers & Home Electronics",
            "type":"Retail Goods"
        }
    ],
    "sg:postcode":"CM19 5AS",
    "sg:province":"Essex",
    "sg:tags":[
        "electrical"
    ],
    "wof:name":"Thornhill Electrical Distributors (Harlo",
    "wof:placetype":"venue"
},
  "geometry": {"coordinates":[0.0743250027,51.7650108337],"type":"Point"}
}