{
  "type": "Feature",
  "properties": {
    "addr:full":"2-4 Kathleen Road Southampton Hampshire SO19 8EX",
    "addr:housenumber":"2-4",
    "addr:postcode":"so19 8ex",
    "addr:street":"Kathleen Road",
    "iso:country":"GB",
    "sg:address":"2-4 Kathleen Road",
    "sg:city":"Southampton",
    "sg:classifiers":[
        {
            "category":"Professional",
            "subcategory":"Printing & Photocopies",
            "type":"Services"
        }
    ],
    "sg:phone":"+44 23 8043 8888",
    "sg:postcode":"SO19 8EX",
    "sg:province":"Hampshire",
    "sg:tags":[
        "trophy"
    ],
    "wof:name":"Trophyman Supplies Ltd.",
    "wof:placetype":"venue"
},
  "geometry": {"coordinates":[-1.355745,50.899387],"type":"Point"}
}