{
  "type": "Feature",
  "properties": {
    "addr:full":"12 Dougall Place, Mayfield Dalkeith City of Edinburgh EH22 5PX",
    "addr:housenumber":"12",
    "addr:postcode":"eh22 5px",
    "addr:street":"Dougall Place",
    "iso:country":"GB",
    "sg:address":"12 Dougall Place, Mayfield",
    "sg:city":"Dalkeith",
    "sg:classifiers":[
        {
            "category":"Professional",
            "subcategory":"Art Services",
            "type":"Services"
        },
        {
            "category":"Building & Trades",
            "subcategory":"Construction",
            "type":"Services"
        }
    ],
    "sg:phone":"+44 131 660 2934",
    "sg:postcode":"EH22 5PX",
    "sg:province":"City of Edinburgh",
    "sg:tags":[
        "decorator",
        "painter"
    ],
    "wof:name":"J Gillies",
    "wof:placetype":"venue"
},
  "geometry": {"coordinates":[-3.04267,55.867119],"type":"Point"}
}