{
  "type": "Feature",
  "properties": {
    "iso:country":"GB",
    "sg:address":"Glanywern Farm, St Martins",
    "sg:city":"Oswestry",
    "sg:classifiers":[
        {
            "category":"Farming",
            "subcategory":"Dairy Farm",
            "type":"Manufacturing & Wholesale Goods"
        }
    ],
    "sg:postcode":"SY11 3HJ",
    "sg:province":"Shropshire",
    "wof:name":"C D & M Whitticase",
    "wof:placetype":"venue"
},
  "geometry": {"coordinates":[-3.012889,52.920219],"type":"Point"}
}