{
  "type": "Feature",
  "properties": {
    "addr:full":"24 Springfield Green Chelmsford Essex CM1 7HS",
    "addr:housenumber":"24",
    "addr:postcode":"cm1 7hs",
    "addr:street":"Springfield Green",
    "iso:country":"GB",
    "sg:address":"24 Springfield Green",
    "sg:city":"Chelmsford",
    "sg:classifiers":[
        {
            "category":"Education",
            "subcategory":"School",
            "type":"Public Place"
        }
    ],
    "sg:phone":"+44 1245 380751",
    "sg:postcode":"CM1 7HS",
    "sg:province":"Essex",
    "sg:tags":[
        "private",
        "tuition"
    ],
    "wof:name":"M J Matthews",
    "wof:placetype":"venue"
},
  "geometry": {"coordinates":[0.492578,51.743797],"type":"Point"}
}