{
  "type": "Feature",
  "properties": {
    "addr:full":"7 Grange Avenue, Ben Rhydding Ilkley North Yorkshire LS29 8NU",
    "addr:housenumber":"7",
    "addr:postcode":"ls29 8nu",
    "addr:street":"Grange Avenue",
    "iso:country":"GB",
    "sg:address":"7 Grange Avenue, Ben Rhydding",
    "sg:city":"Ilkley",
    "sg:classifiers":[
        {
            "category":"Building & Trades",
            "subcategory":"Construction",
            "type":"Services"
        }
    ],
    "sg:postcode":"LS29 8NU",
    "sg:province":"North Yorkshire",
    "sg:tags":[
        "roofing"
    ],
    "wof:name":"Stephen J Mitchell",
    "wof:placetype":"venue"
},
  "geometry": {"coordinates":[-1.803371,53.926575],"type":"Point"}
}