{
  "type": "Feature",
  "properties": {
    "iso:country":"GB",
    "sg:address":"Units 2-6 Romney Enterprise Cent, Re",
    "sg:city":"New Romney",
    "sg:classifiers":[
        {
            "category":"Military Area",
            "subcategory":"Air Force Base",
            "type":"Public Place"
        }
    ],
    "sg:postcode":"TN28 8DW",
    "sg:province":"Kent",
    "sg:tags":[
        "taxi",
        "hire",
        "private"
    ],
    "wof:name":"Keith Baldwin",
    "wof:placetype":"venue"
},
  "geometry": {"coordinates":[0.9464799762,50.9867668152],"type":"Point"}
}