{
  "type": "Feature",
  "properties": {
    "addr:full":"Po Box 46 Wallingford Oxfordshire OX10 0XP",
    "addr:housenumber":"po box 46",
    "addr:postcode":"ox10 0xp",
    "iso:country":"GB",
    "sg:address":"Po Box 46",
    "sg:city":"Wallingford",
    "sg:classifiers":[
        {
            "category":"Professional",
            "subcategory":"Management & Consulting",
            "type":"Services"
        }
    ],
    "sg:postcode":"OX10 0XP",
    "sg:province":"Oxfordshire",
    "sg:tags":[
        "consultant",
        "business"
    ],
    "wof:name":"Point Promotions",
    "wof:placetype":"venue"
},
  "geometry": {"coordinates":[-1.1360889673,51.6046295166],"type":"Point"}
}