{
  "type": "Feature",
  "properties": {
    "iso:country":"GB",
    "sg:address":"10 Canal Street",
    "sg:city":"Stockport",
    "sg:classifiers":[
        {
            "category":"Building & Trades",
            "subcategory":"Electrical",
            "type":"Services"
        }
    ],
    "sg:phone":"+44 161 480 6262",
    "sg:postcode":"SK1 3BZ",
    "sg:province":"Cheshire",
    "sg:tags":[
        "consultant",
        "lighting"
    ],
    "wof:name":"Deanhurst Associates",
    "wof:placetype":"venue"
},
  "geometry": {"coordinates":[-2.1540820599,53.4029388428],"type":"Point"}
}