{
  "type": "Feature",
  "properties": {
    "iso:country":"GB",
    "sg:address":"Unit B & E, John St Arcade, John Street",
    "sg:city":"Porthcawl",
    "sg:classifiers":[
        {
            "category":"Food & Beverages",
            "subcategory":"Bakery",
            "type":"Retail Goods"
        }
    ],
    "sg:phone":"+44 1656 773164",
    "sg:postcode":"CF36 3BD",
    "sg:province":"Bridgend",
    "sg:tags":[
        "baker"
    ],
    "wof:name":"Wyn Jones Dairy Delicatessen",
    "wof:placetype":"venue"
},
  "geometry": {"coordinates":[-3.70405,51.47821],"type":"Point"}
}