{
  "type": "Feature",
  "properties": {
    "addr:full":"3 New Street Retford Nottinghamshire DN22 6EG",
    "addr:housenumber":"3",
    "addr:postcode":"dn22 6eg",
    "addr:street":"New Street",
    "iso:country":"GB",
    "sg:address":"3 New Street",
    "sg:city":"Retford",
    "sg:classifiers":[
        {
            "category":"Real Estate",
            "subcategory":"Real Estate Agent",
            "type":"Services"
        }
    ],
    "sg:phone":"+44 1777 705647",
    "sg:postcode":"DN22 6EG",
    "sg:province":"Nottinghamshire",
    "wof:name":"Town & Country Property",
    "wof:placetype":"venue"
},
  "geometry": {"coordinates":[-0.940491,53.320389],"type":"Point"}
}