{
  "type": "Feature",
  "properties": {
    "addr:full":"73 Holland Rd, Ampthill Bedford Bedfordshire MK45 2RR",
    "addr:housenumber":"73",
    "addr:postcode":"mk45 2rr",
    "addr:street":"Holland Rd",
    "iso:country":"GB",
    "sg:address":"73 Holland Rd, Ampthill",
    "sg:city":"Bedford",
    "sg:classifiers":[
        {
            "category":"Building & Trades",
            "subcategory":"Plumbing",
            "type":"Services"
        }
    ],
    "sg:phone":"+44 1525 403386",
    "sg:postcode":"MK45 2RR",
    "sg:province":"Bedfordshire",
    "sg:tags":[
        "heating"
    ],
    "wof:name":"A.W Cherry",
    "wof:placetype":"venue"
},
  "geometry": {"coordinates":[-0.5022339821,52.0240821838],"type":"Point"}
}