{
  "type": "Feature",
  "properties": {
    "iso:country":"GB",
    "sg:address":"Lon Uchaf, Morfa Nefyn",
    "sg:city":"Pwllheli",
    "sg:classifiers":[
        {
            "category":"Health Services",
            "subcategory":"Nursing And Care Facility",
            "type":"Services"
        },
        {
            "category":"Social Services",
            "subcategory":"Retirement Home",
            "type":"Services"
        }
    ],
    "sg:phone":"+44 1758 720283",
    "sg:postcode":"LL53 6AD",
    "sg:province":"Gwynedd",
    "sg:tags":[
        "residential"
    ],
    "wof:name":"Plas Madryn Residential Home For The Elderly",
    "wof:placetype":"venue"
},
  "geometry": {"coordinates":[-4.550509,52.932377],"type":"Point"}
}