{
  "type": "Feature",
  "properties": {
    "iso:country":"GB",
    "sg:address":"158 Clapton Common",
    "sg:city":"London",
    "sg:classifiers":[
        {
            "category":"Shopping",
            "subcategory":"Gifts & Souvenirs",
            "type":"Retail Goods"
        }
    ],
    "sg:postcode":"E5 9AG",
    "sg:province":"Greater London",
    "sg:tags":[
        "shop"
    ],
    "wof:name":"Abraham,Al,",
    "wof:placetype":"venue"
},
  "geometry": {"coordinates":[-0.071056,51.573032],"type":"Point"}
}