{
  "type": "Feature",
  "properties": {
    "addr:full":"Unit 1, Acton Vale Industrial Park, Cowley Road London Greater London W3 7QE",
    "addr:housenumber":"unit 1",
    "addr:postcode":"w3 7qe",
    "addr:street":"Vale Industrial Park Cowley Road",
    "iso:country":"GB",
    "sg:address":"Unit 1, Acton Vale Industrial Park, Cowley Road",
    "sg:city":"London",
    "sg:classifiers":[
        {
            "category":"Home & Garden",
            "subcategory":"Kitchen Supply",
            "type":"Retail Goods"
        }
    ],
    "sg:phone":"+44 20 8746 0808",
    "sg:postcode":"W3 7QE",
    "sg:province":"Greater London",
    "sg:tags":[
        "equipment",
        "catering"
    ],
    "wof:name":"Court Catering Equipment Ltd.",
    "wof:placetype":"venue"
},
  "geometry": {"coordinates":[-0.2615540028,51.5060997009],"type":"Point"}
}