{
  "type": "Feature",
  "properties": {
    "addr:full":"59a Greenside Rd Shepherd's Bush Greater London W12 9JQ",
    "addr:housenumber":"59a",
    "addr:postcode":"w12 9jq",
    "addr:street":"Greenside Rd",
    "iso:country":"GB",
    "sg:address":"59a Greenside Rd",
    "sg:city":"Shepherd's Bush",
    "sg:classifiers":[
        {
            "category":"Health Services",
            "subcategory":"Health Practitioner",
            "type":"Services"
        }
    ],
    "sg:phone":"+44 20 8743 3064",
    "sg:postcode":"W12 9JQ",
    "sg:province":"Greater London",
    "sg:tags":[
        "therapist",
        "speech"
    ],
    "wof:name":"Andrew Smith MANLP MNCH",
    "wof:placetype":"venue"
},
  "geometry": {"coordinates":[-0.2380480021,51.5019264221],"type":"Point"}
}