{
  "type": "Feature",
  "properties": {
    "addr:full":"Medley Street Castleford West Yorkshire WF10 4BB",
    "addr:postcode":"wf10 4bb",
    "addr:street":"Medley Street",
    "iso:country":"GB",
    "sg:address":"Medley Street",
    "sg:city":"Castleford",
    "sg:classifiers":[
        {
            "category":"Education",
            "subcategory":"School",
            "type":"Public Place"
        },
        {
            "category":"Government",
            "subcategory":"Office",
            "type":"Public Place"
        }
    ],
    "sg:phone":"+44 1977 722995",
    "sg:postcode":"WF10 4BB",
    "sg:province":"West Yorkshire",
    "sg:tags":[
        "local",
        "authority"
    ],
    "wof:name":"Park Junior School",
    "wof:placetype":"venue"
},
  "geometry": {"coordinates":[-1.3443739414,53.7233161926],"type":"Point"}
}