{
  "type": "Feature",
  "properties": {
    "addr:full":"The Bell Surgery York Rd Henley-on-thames Berkshire RG9 2DR",
    "addr:postcode":"rg9 2dr",
    "addr:street":"York Rd",
    "iso:country":"GB",
    "sg:address":"The Bell Surgery York Rd",
    "sg:city":"Henley-on-thames",
    "sg:classifiers":[
        {
            "category":"Health Services",
            "subcategory":"Doctor",
            "type":"Services"
        }
    ],
    "sg:postcode":"RG9 2DR",
    "sg:province":"Berkshire",
    "sg:tags":[
        "practitioners"
    ],
    "wof:name":"Melhuish,A H,",
    "wof:placetype":"venue"
},
  "geometry": {"coordinates":[-0.903189,51.535297],"type":"Point"}
}