{
  "type": "Feature",
  "properties": {
    "iso:country":"GB",
    "sg:address":"Manor Oaks Road",
    "sg:city":"Sheffield",
    "sg:classifiers":[
        {
            "category":"Community Center",
            "type":"Public Place"
        }
    ],
    "sg:phone":"+44 114 273 0433",
    "sg:postcode":"S2 5EA",
    "sg:province":"South Yorkshire",
    "sg:tags":[
        "recreation",
        "leisure",
        "centre"
    ],
    "wof:name":"Wybourn Communtiy Centre",
    "wof:placetype":"venue"
},
  "geometry": {"coordinates":[-1.4469640255,53.3803863525],"type":"Point"}
}