{
  "type": "Feature",
  "properties": {
    "addr:full":"Unit 10 Wheelbarrow Park Est, Pattenden La Tonbridge Kent TN12 9QJ",
    "addr:housenumber":"unit 10",
    "addr:postcode":"tn12 9qj",
    "addr:street":"Wheelbarrow Park Est;La Tonbridge",
    "iso:country":"GB",
    "sg:address":"Unit 10 Wheelbarrow Park Est, Pattenden La",
    "sg:city":"Tonbridge",
    "sg:classifiers":[
        {
            "category":"Manufacturing",
            "subcategory":"Chemicals & Compounds",
            "type":"Manufacturing & Wholesale Goods"
        }
    ],
    "sg:phone":"+44 1622 833012",
    "sg:postcode":"TN12 9QJ",
    "sg:province":"Kent",
    "wof:name":"H L Hutchinson (Produce Packaging) Ltd",
    "wof:placetype":"venue"
},
  "geometry": {"coordinates":[0.4900099933,51.1776313782],"type":"Point"}
}