{
  "type": "Feature",
  "properties": {
    "addr:full":"Larch Street Dundee Dundee City DD1 5NP",
    "addr:postcode":"dd1 5np",
    "addr:street":"Larch Street",
    "iso:country":"GB",
    "sg:address":"Larch Street",
    "sg:city":"Dundee",
    "sg:classifiers":[
        {
            "category":"Wholesale",
            "subcategory":"Scrap",
            "type":"Manufacturing & Wholesale Goods"
        }
    ],
    "sg:phone":"+44 1382 322300",
    "sg:postcode":"DD1 5NP",
    "sg:province":"Dundee City",
    "sg:tags":[
        "waste",
        "metal"
    ],
    "wof:name":"Tayside Recyclers",
    "wof:placetype":"venue"
},
  "geometry": {"coordinates":[-2.9853439331,56.4606246948],"type":"Point"}
}