{
  "type": "Feature",
  "properties": {
    "iso:country":"GB",
    "sg:address":"105 High Street",
    "sg:city":"Eastleigh",
    "sg:classifiers":[
        {
            "category":"Bars & Pubs",
            "type":"Food & Drink"
        }
    ],
    "sg:phone":"+44 23 8061 2067",
    "sg:postcode":"SO50 5LS",
    "sg:province":"Hampshire",
    "sg:tags":[
        "pubs",
        "inn"
    ],
    "wof:name":"The Chamberlayne Arms",
    "wof:placetype":"venue"
},
  "geometry": {"coordinates":[-1.354196,50.965897],"type":"Point"}
}