{
  "type": "Feature",
  "properties": {
    "addr:full":"Suite 8 Eastbourne East Sussex BN21 1QN",
    "addr:housenumber":"suite 8",
    "addr:postcode":"bn21 1qn",
    "iso:country":"GB",
    "sg:address":"Suite 8",
    "sg:city":"Eastbourne",
    "sg:classifiers":[
        {
            "category":"Real Estate",
            "subcategory":"Real Estate Agent",
            "type":"Services"
        }
    ],
    "sg:phone":"+44 1323 727090",
    "sg:postcode":"BN21 1QN",
    "sg:province":"East Sussex",
    "wof:name":"J P C Property Management",
    "wof:placetype":"venue"
},
  "geometry": {"coordinates":[0.2853499949,50.766910553],"type":"Point"}
}