{
  "type": "Feature",
  "properties": {
    "iso:country":"GB",
    "sg:address":"Gurnos",
    "sg:city":"Swansea",
    "sg:classifiers":[
        {
            "category":"Bars & Pubs",
            "type":"Food & Drink"
        }
    ],
    "sg:phone":"+44 1639 842211",
    "sg:postcode":"SA9 2LA",
    "sg:province":"Carmarthenshire",
    "sg:tags":[
        "pubs",
        "inn"
    ],
    "wof:name":"Aubrey Arms",
    "wof:placetype":"venue"
},
  "geometry": {"coordinates":[-3.776819,51.768631],"type":"Point"}
}