{
  "type": "Feature",
  "properties": {
    "addr:full":"70 London Street Reading Berkshire RG1 4AT",
    "addr:housenumber":"70",
    "addr:postcode":"rg1 4at",
    "addr:street":"London Street",
    "iso:country":"GB",
    "sg:address":"70 London Street",
    "sg:city":"Reading",
    "sg:classifiers":[
        {
            "category":"Real Estate",
            "subcategory":"Architect",
            "type":"Services"
        }
    ],
    "sg:phone":"+44 1734 596596",
    "sg:postcode":"RG1 4AT",
    "sg:province":"Berkshire",
    "wof:name":"Extensions",
    "wof:placetype":"venue"
},
  "geometry": {"coordinates":[-0.968304,51.452141],"type":"Point"}
}