{
  "type": "Feature",
  "properties": {
    "addr:full":"7 Standings Close, Nine Elms Swindon Wiltshire SN5 9UG",
    "addr:housenumber":"7",
    "addr:postcode":"sn5 9ug",
    "addr:street":"Standings Close",
    "iso:country":"GB",
    "sg:address":"7 Standings Close, Nine Elms",
    "sg:city":"Swindon",
    "sg:classifiers":[
        {
            "category":"Food & Beverages",
            "subcategory":"Specialty",
            "type":"Retail Goods"
        }
    ],
    "sg:phone":"+44 1793 872372",
    "sg:postcode":"SN5 9UG",
    "sg:province":"Wiltshire",
    "sg:tags":[
        "dietetic",
        "homogenised"
    ],
    "wof:name":"Bioelectric Shield Ltd",
    "wof:placetype":"venue"
},
  "geometry": {"coordinates":[-1.842869997,51.5716514587],"type":"Point"}
}