{
  "type": "Feature",
  "properties": {
    "iso:country":"GB",
    "sg:address":"Beechie House, 94 Glamis Rd",
    "sg:city":"Kirriemuir",
    "sg:classifiers":[
        {
            "category":"Organizations",
            "subcategory":"Non-profit Organization",
            "type":"Services"
        }
    ],
    "sg:phone":"+44 1575 575555",
    "sg:postcode":"DD8 5DF",
    "sg:province":"Angus",
    "sg:tags":[
        "organisation",
        "voluntary",
        "charity"
    ],
    "wof:name":"Lippen Care",
    "wof:placetype":"venue"
},
  "geometry": {"coordinates":[-3.003505,56.667011],"type":"Point"}
}