{
  "type": "Feature",
  "properties": {
    "iso:country":"GB",
    "sg:address":"Hawbushes Farm, Windmill Lane",
    "sg:city":"High Wycombe",
    "sg:classifiers":[
        {
            "category":"Manufacturing",
            "subcategory":"Tools & Machinery",
            "type":"Manufacturing & Wholesale Goods"
        }
    ],
    "sg:postcode":"HP15 6NX",
    "sg:province":"Buckinghamshire",
    "wof:name":"Giles Machine Tools Ltd.",
    "wof:placetype":"venue"
},
  "geometry": {"coordinates":[-0.71944,51.668522],"type":"Point"}
}