{
  "type": "Feature",
  "properties": {
    "iso:country":"GB",
    "sg:address":"11 Castle Mews",
    "sg:city":"London",
    "sg:classifiers":[
        {
            "category":"Communications",
            "subcategory":"Film & Video Production",
            "type":"Services"
        },
        {
            "category":"Professional",
            "subcategory":"Printing & Photocopies",
            "type":"Services"
        }
    ],
    "sg:phone":"+44 20 8446 9999",
    "sg:postcode":"N12 9EH",
    "sg:province":"Greater London",
    "sg:tags":[
        "supplier",
        "duplicating",
        "copying",
        "photocopier"
    ],
    "wof:name":"Black & White Systems",
    "wof:placetype":"venue"
},
  "geometry": {"coordinates":[-0.1754730046,51.6138534546],"type":"Point"}
}