{
  "type": "Feature",
  "properties": {
    "addr:full":"3 Brownside Road Burnley Lancashire BB10 3JU",
    "addr:housenumber":"3",
    "addr:postcode":"bb10 3ju",
    "addr:street":"Brownside Road",
    "iso:country":"GB",
    "sg:address":"3 Brownside Road",
    "sg:city":"Burnley",
    "sg:classifiers":[
        {
            "category":"Food & Beverages",
            "subcategory":"Meat & Fish",
            "type":"Retail Goods"
        }
    ],
    "sg:postcode":"BB10 3JU",
    "sg:province":"Lancashire",
    "sg:tags":[
        "butcher"
    ],
    "wof:name":"Graham Allison",
    "wof:placetype":"venue"
},
  "geometry": {"coordinates":[-2.210317,53.786835],"type":"Point"}
}