{
  "type": "Feature",
  "properties": {
    "addr:full":"60 Long Meadows, Dovercourt Harwich Essex CO12 4TU",
    "addr:housenumber":"60",
    "addr:postcode":"co12 4tu",
    "addr:street":"Long Meadows",
    "iso:country":"GB",
    "sg:address":"60 Long Meadows, Dovercourt",
    "sg:city":"Harwich",
    "sg:classifiers":[
        {
            "category":"Home & Garden",
            "subcategory":"Home Furnishings",
            "type":"Retail Goods"
        },
        {
            "category":"Communications",
            "type":"Services"
        }
    ],
    "sg:phone":"+44 1255 503399",
    "sg:postcode":"CO12 4TU",
    "sg:province":"Essex",
    "sg:tags":[
        "planner",
        "tv",
        "furnishers",
        "video",
        "radio",
        "kitchen"
    ],
    "wof:name":"Alex's Kitchens",
    "wof:placetype":"venue"
},
  "geometry": {"coordinates":[1.2490949631,51.9292907715],"type":"Point"}
}