{
  "type": "Feature",
  "properties": {
    "addr:full":"658a High Rd North Finchley Greater London N12 0NL",
    "addr:housenumber":"658a",
    "addr:postcode":"n12 0nl",
    "addr:street":"High Rd",
    "iso:country":"GB",
    "sg:address":"658a High Rd",
    "sg:city":"North Finchley",
    "sg:classifiers":[
        {
            "category":"Home & Garden",
            "subcategory":"Household Appliances",
            "type":"Retail Goods"
        },
        {
            "category":"Retail",
            "subcategory":"Repair Shop",
            "type":"Services"
        }
    ],
    "sg:phone":"+44 20 8446 6812",
    "sg:postcode":"N12 0NL",
    "sg:province":"Greater London",
    "sg:tags":[
        "machine",
        "electrical",
        "washing"
    ],
    "wof:name":"New Era",
    "wof:placetype":"venue"
},
  "geometry": {"coordinates":[-0.1754679978,51.6120796204],"type":"Point"}
}