{
  "type": "Feature",
  "properties": {
    "addr:full":"Bucknalls Lane, Garston Watford Hertfordshire WD25 9XX",
    "addr:postcode":"wd25 9xx",
    "addr:street":"Bucknalls Lane",
    "iso:country":"GB",
    "sg:address":"Bucknalls Lane, Garston",
    "sg:city":"Watford",
    "sg:classifiers":[
        {
            "category":"Building & Trades",
            "subcategory":"Landscaping Services",
            "type":"Services"
        }
    ],
    "sg:phone":"+44 1923 664000",
    "sg:postcode":"WD25 9XX",
    "sg:province":"Hertfordshire",
    "sg:tags":[
        "consultant"
    ],
    "wof:name":"Building Research Establishment",
    "wof:placetype":"venue"
},
  "geometry": {"coordinates":[-0.375033,51.698574],"type":"Point"}
}