{
  "type": "Feature",
  "properties": {
    "addr:full":"3 Woodfield Road Welwyn Garden City Hertfordshire AL7 1JQ",
    "addr:housenumber":"3",
    "addr:postcode":"al7 1jq",
    "addr:street":"Woodfield Road",
    "iso:country":"GB",
    "sg:address":"3 Woodfield Road",
    "sg:city":"Welwyn Garden City",
    "sg:classifiers":[
        {
            "category":"Manufacturing",
            "subcategory":"Leather Goods",
            "type":"Manufacturing & Wholesale Goods"
        },
        {
            "category":"Personal",
            "subcategory":"Skin Care",
            "type":"Services"
        }
    ],
    "sg:phone":"+44 1707 332433",
    "sg:postcode":"AL7 1JQ",
    "sg:province":"Hertfordshire",
    "sg:tags":[
        "merchant",
        "manufacture",
        "product",
        "hide",
        "supply"
    ],
    "wof:name":"Welwyn Handles Ltd.",
    "wof:placetype":"venue"
},
  "geometry": {"coordinates":[-0.1892340034,51.7994346619],"type":"Point"}
}