{
  "type": "Feature",
  "properties": {
    "addr:full":"6-8 Cheetham Parade, Bury Old Road Manchester Greater Manchester M8 6DJ",
    "addr:housenumber":"6-8",
    "addr:postcode":"m8 6dj",
    "addr:street":"Cheetham Parade Bury Old Road",
    "iso:country":"GB",
    "sg:address":"6-8 Cheetham Parade, Bury Old Road",
    "sg:city":"Manchester",
    "sg:classifiers":[
        {
            "category":"Shopping",
            "subcategory":"News",
            "type":"Retail Goods"
        }
    ],
    "sg:phone":"+44 161 795 9199",
    "sg:postcode":"M8 6DJ",
    "sg:province":"Greater Manchester",
    "sg:tags":[
        "newsagent"
    ],
    "wof:name":"A & B Newsagents",
    "wof:placetype":"venue"
},
  "geometry": {"coordinates":[-2.2386300564,53.5134811401],"type":"Point"}
}