{
  "type": "Feature",
  "properties": {
    "addr:full":"Kingswood House, Kingswood Estate Dulwich Greater London SE21 8QN",
    "addr:postcode":"se21 8qn",
    "addr:street":"Kingswood Estate",
    "iso:country":"GB",
    "sg:address":"Kingswood House, Kingswood Estate",
    "sg:city":"Dulwich",
    "sg:classifiers":[
        {
            "category":"Organizations",
            "subcategory":"Non-profit Organization",
            "type":"Services"
        }
    ],
    "sg:phone":"+44 20 8761 5454",
    "sg:postcode":"SE21 8QN",
    "sg:province":"Greater London",
    "sg:tags":[
        "organisation",
        "voluntary",
        "charity"
    ],
    "wof:name":"Dulwich Homelink",
    "wof:placetype":"venue"
},
  "geometry": {"coordinates":[-0.0888490006,51.4409751892],"type":"Point"}
}