{
  "type": "Feature",
  "properties": {
    "iso:country":"GB",
    "sg:address":"Unit 8, Warrenby Court",
    "sg:city":"Redcar",
    "sg:classifiers":[
        {
            "category":"Professional",
            "subcategory":"Engineering",
            "type":"Services"
        }
    ],
    "sg:phone":"+44 1642 485975",
    "sg:postcode":"TS10 5AT",
    "sg:province":"North Yorkshire",
    "sg:tags":[
        "contractor",
        "electrical",
        "engineer"
    ],
    "wof:name":"Redcar Electrical Services",
    "wof:placetype":"venue"
},
  "geometry": {"coordinates":[-1.068344,54.614059],"type":"Point"}
}