{
  "type": "Feature",
  "properties": {
    "addr:full":"Council Chambers, King Street Harrogate North Yorkshire HG3 5LE",
    "addr:postcode":"hg3 5le",
    "addr:street":"King Street",
    "iso:country":"GB",
    "sg:address":"Council Chambers, King Street",
    "sg:city":"Harrogate",
    "sg:classifiers":[
        {
            "category":"Professional",
            "subcategory":"Computer Services",
            "type":"Services"
        }
    ],
    "sg:postcode":"HG3 5LE",
    "sg:province":"North Yorkshire",
    "sg:tags":[
        "system",
        "software"
    ],
    "wof:name":"Microtrend Ltd.",
    "wof:placetype":"venue"
},
  "geometry": {"coordinates":[-1.7593799829,54.0877113342],"type":"Point"}
}