{
  "type": "Feature",
  "properties": {
    "addr:full":"8 Carlyles Court, Fisher Street Carlisle Cumbria CA3 8RN",
    "addr:housenumber":"8",
    "addr:postcode":"ca3 8rn",
    "addr:street":"Carlyles Court Fisher Street",
    "iso:country":"GB",
    "sg:address":"8 Carlyles Court, Fisher Street",
    "sg:city":"Carlisle",
    "sg:classifiers":[
        {
            "category":"Personal",
            "subcategory":"Beauty Salon",
            "type":"Services"
        }
    ],
    "sg:phone":"+44 1228 596106",
    "sg:postcode":"CA3 8RN",
    "sg:province":"Cumbria",
    "sg:tags":[
        "unisex",
        "hairdresser"
    ],
    "wof:name":"Sonata's Hair Design Studios",
    "wof:placetype":"venue"
},
  "geometry": {"coordinates":[-2.9374940395,54.8953018188],"type":"Point"}
}