{
  "type": "Feature",
  "properties": {
    "addr:full":"Wyre Piddle Pershore Worcestershire WR10 2HR",
    "addr:postcode":"wr10 2hr",
    "iso:country":"GB",
    "sg:address":"Wyre Piddle",
    "sg:city":"Pershore",
    "sg:classifiers":[
        {
            "category":"Autos & Motor Vehicles",
            "subcategory":"Fuel & Gas Station",
            "type":"Retail Goods"
        }
    ],
    "sg:phone":"+44 1386 552629",
    "sg:postcode":"WR10 2HR",
    "sg:province":"Worcestershire",
    "sg:tags":[
        "petrol",
        "filling"
    ],
    "wof:name":"Wyre Piddle Filling Station",
    "wof:placetype":"venue"
},
  "geometry": {"coordinates":[-2.0571260452,52.1266899109],"type":"Point"}
}