{
  "type": "Feature",
  "properties": {
    "addr:full":"Unit 5g Cockshades Entrprse Works, Stocks Lane, Wybunbury Nantwich Cheshire CW5 7HA",
    "addr:postcode":"cw5 7ha",
    "addr:street":"Stocks Lane",
    "iso:country":"GB",
    "sg:address":"Unit 5g Cockshades Entrprse Works, Stocks Lane, Wybunbury",
    "sg:city":"Nantwich",
    "sg:classifiers":[
        {
            "category":"Manufacturing",
            "subcategory":"Furniture",
            "type":"Manufacturing & Wholesale Goods"
        }
    ],
    "sg:phone":"+44 1270 842123",
    "sg:postcode":"CW5 7HA",
    "sg:province":"Cheshire",
    "sg:tags":[
        "mnfr",
        "upholsterer"
    ],
    "wof:name":"J B H Coach Trimmers & Upholsters",
    "wof:placetype":"venue"
},
  "geometry": {"coordinates":[-2.458512,53.046329],"type":"Point"}
}