{
  "type": "Feature",
  "properties": {
    "iso:country":"GB",
    "sg:address":"Colmore Gate, 2 Colmore Row",
    "sg:city":"Birmingham",
    "sg:classifiers":[
        {
            "category":"Professional",
            "subcategory":"Accounting & Tax Preparation",
            "type":"Services"
        }
    ],
    "sg:postcode":"B3 2BN",
    "sg:province":"West Midlands",
    "sg:tags":[
        "accountant"
    ],
    "wof:name":"Pensions Research Accountants Group",
    "wof:placetype":"venue"
},
  "geometry": {"coordinates":[-1.89704,52.482399],"type":"Point"}
}