{
  "type": "Feature",
  "properties": {
    "addr:full":"177-181 Great Bridge Street West Bromwich West Midlands B70 0DJ",
    "addr:housenumber":"177-181",
    "addr:postcode":"b70 0dj",
    "addr:street":"Great Bridge Street",
    "iso:country":"GB",
    "sg:address":"177-181 Great Bridge Street",
    "sg:city":"West Bromwich",
    "sg:classifiers":[
        {
            "category":"Shopping",
            "subcategory":"Clothing, Apparel, & Fashions",
            "type":"Retail Goods"
        }
    ],
    "sg:phone":"+44 121 522 2484",
    "sg:postcode":"B70 0DJ",
    "sg:province":"West Midlands",
    "sg:tags":[
        "clothing",
        "fabric"
    ],
    "wof:name":"Classic Garments Ltd.",
    "wof:placetype":"venue"
},
  "geometry": {"coordinates":[-2.02581,52.528862],"type":"Point"}
}