{
  "type": "Feature",
  "properties": {
    "addr:full":"376 South Coast Road, Telscombe Cliffs Peacehaven East Sussex BN10 7ET",
    "addr:housenumber":"376",
    "addr:postcode":"bn10 7et",
    "addr:street":"South Coast Road;Cliffs Peacehaven",
    "iso:country":"GB",
    "sg:address":"376 South Coast Road, Telscombe Cliffs",
    "sg:city":"Peacehaven",
    "sg:classifiers":[
        {
            "category":"Autos & Motor Vehicles",
            "subcategory":"Fuel & Gas Station",
            "type":"Retail Goods"
        }
    ],
    "sg:postcode":"BN10 7ET",
    "sg:province":"East Sussex",
    "sg:tags":[
        "petrol",
        "filling"
    ],
    "wof:name":"Star Service Stations",
    "wof:placetype":"venue"
},
  "geometry": {"coordinates":[-0.012549,50.793652],"type":"Point"}
}