{
  "type": "Feature",
  "properties": {
    "addr:full":"10 Ilkeston Drive, Aspull Wigan Lancashire WN2 1QZ",
    "addr:housenumber":"10",
    "addr:postcode":"wn2 1qz",
    "addr:street":"Ilkeston Drive",
    "iso:country":"GB",
    "sg:address":"10 Ilkeston Drive, Aspull",
    "sg:city":"Wigan",
    "sg:classifiers":[
        {
            "category":"Shopping",
            "subcategory":"Gifts & Souvenirs",
            "type":"Retail Goods"
        }
    ],
    "sg:postcode":"WN2 1QZ",
    "sg:province":"Lancashire",
    "sg:tags":[
        "diy"
    ],
    "wof:name":"Bay Manufacturing Ltd",
    "wof:placetype":"venue"
},
  "geometry": {"coordinates":[-2.5847139359,53.5694503784],"type":"Point"}
}