{
  "type": "Feature",
  "properties": {
    "iso:country":"GB",
    "sg:address":"1 Station Road, Great Sankey",
    "sg:city":"Warrington",
    "sg:classifiers":[
        {
            "category":"Government",
            "subcategory":"Post Office",
            "type":"Public Place"
        }
    ],
    "sg:phone":"+44 1925 723100",
    "sg:postcode":"WA5 1RH",
    "sg:province":"Cheshire",
    "wof:name":"Great Sankey Post Office",
    "wof:placetype":"venue"
},
  "geometry": {"coordinates":[-2.649559021,53.390789032],"type":"Point"}
}