{
  "type": "Feature",
  "properties": {
    "addr:full":"22 St Peters Park Road Broadstairs Kent CT10 2BL",
    "addr:housenumber":"22",
    "addr:postcode":"ct10 2bl",
    "addr:street":"St Peters Park Road",
    "iso:country":"GB",
    "sg:address":"22 St Peters Park Road",
    "sg:city":"Broadstairs",
    "sg:classifiers":[
        {
            "category":"Building & Trades",
            "subcategory":"Equipment Rental",
            "type":"Services"
        }
    ],
    "sg:phone":"+44 1843 604888",
    "sg:postcode":"CT10 2BL",
    "sg:province":"Kent",
    "sg:tags":[
        "hire",
        "machinery",
        "plant",
        "centre"
    ],
    "wof:name":"Hewden Plant Hire Ltd.",
    "wof:placetype":"venue"
},
  "geometry": {"coordinates":[1.431995,51.361382],"type":"Point"}
}