{
  "type": "Feature",
  "properties": {
    "iso:country":"GB",
    "sg:address":"307 Burton Road",
    "sg:city":"Derby",
    "sg:classifiers":[
        {
            "category":"Health Services",
            "subcategory":"Hospital",
            "type":"Services"
        }
    ],
    "sg:phone":"+44 1332 341193",
    "sg:postcode":"DE23 6AG",
    "sg:province":"Derbyshire",
    "wof:name":"CRAIGMORE HOSTEL",
    "wof:placetype":"venue"
},
  "geometry": {"coordinates":[-1.4904530048,52.9108352661],"type":"Point"}
}