{
  "type": "Feature",
  "properties": {
    "addr:full":"Hendry Rd Kirkcaldy Fife KY2 5DS",
    "addr:postcode":"ky2 5ds",
    "addr:street":"Hendry Rd",
    "iso:country":"GB",
    "sg:address":"Hendry Rd",
    "sg:city":"Kirkcaldy",
    "sg:classifiers":[
        {
            "category":"Autos & Motor Vehicles",
            "subcategory":"Auto Supplies",
            "type":"Retail Goods"
        }
    ],
    "sg:phone":"+44 1592 264131",
    "sg:postcode":"KY2 5DS",
    "sg:province":"Fife",
    "sg:tags":[
        "tyre"
    ],
    "wof:name":"Motorway Tyres & Autocentres",
    "wof:placetype":"venue"
},
  "geometry": {"coordinates":[-3.1707,56.125134],"type":"Point"}
}