{
  "type": "Feature",
  "properties": {
    "addr:full":"Hall Lane Walton-on-the-naze Essex CO14 8HL",
    "addr:postcode":"co14 8hl",
    "addr:street":"Hall Lane",
    "iso:country":"GB",
    "sg:address":"Hall Lane",
    "sg:city":"Walton-on-the-naze",
    "sg:classifiers":[
        {
            "category":"Travel",
            "subcategory":"Hotels & Motels",
            "type":"Entertainment"
        },
        {
            "category":"Food & Beverages",
            "subcategory":"Groceries & Convenience Stores",
            "type":"Retail Goods"
        }
    ],
    "sg:phone":"+44 1255 672746",
    "sg:postcode":"CO14 8HL",
    "sg:province":"Essex",
    "sg:tags":[
        "self",
        "catering"
    ],
    "wof:name":"Naze Marine Holiday Park",
    "wof:placetype":"venue"
},
  "geometry": {"coordinates":[1.278504014,51.8583183289],"type":"Point"}
}