{
  "type": "Feature",
  "properties": {
    "addr:full":"Jubilee Wharf, Commercial Rd Penryn Cornwall TR10 8AQ",
    "addr:postcode":"tr10 8aq",
    "addr:street":"Commercial Rd",
    "iso:country":"GB",
    "sg:address":"Jubilee Wharf, Commercial Rd",
    "sg:city":"Penryn",
    "sg:classifiers":[
        {
            "category":"Manufacturing",
            "subcategory":"Watercraft",
            "type":"Manufacturing & Wholesale Goods"
        }
    ],
    "sg:phone":"+44 1326 376277",
    "sg:postcode":"TR10 8AQ",
    "sg:province":"Cornwall",
    "sg:tags":[
        "repairer",
        "sailmaker"
    ],
    "wof:name":"Patrick Selman The Sailmaker",
    "wof:placetype":"venue"
},
  "geometry": {"coordinates":[-5.104809,50.168575],"type":"Point"}
}