{
  "type": "Feature",
  "properties": {
    "iso:country":"GB",
    "sg:address":"52 Haymarket",
    "sg:city":"London",
    "sg:classifiers":[
        {
            "category":"Cafe",
            "type":"Food & Drink"
        }
    ],
    "sg:phone":"+44 20 7839 2747",
    "sg:postcode":"SW1Y 4RP",
    "sg:province":"Greater London",
    "sg:tags":[
        "tea",
        "room"
    ],
    "wof:name":"A Pret Manger",
    "wof:placetype":"venue"
},
  "geometry": {"coordinates":[-0.1327220052,51.5094413757],"type":"Point"}
}