{
  "type": "Feature",
  "properties": {
    "iso:country":"GB",
    "sg:address":"55c Parsonage Street",
    "sg:city":"Dursley",
    "sg:classifiers":[
        {
            "category":"Professional",
            "subcategory":"Accounting & Tax Preparation",
            "type":"Services"
        }
    ],
    "sg:postcode":"GL11 4BP",
    "sg:province":"Gloucestershire",
    "sg:tags":[
        "accountant"
    ],
    "wof:name":"C K Accountants",
    "wof:placetype":"venue"
},
  "geometry": {"coordinates":[-2.356699,51.681911],"type":"Point"}
}