{
  "type": "Feature",
  "properties": {
    "addr:full":"4 Bull St Burnley Lancashire BB11 1DW",
    "addr:housenumber":"4",
    "addr:postcode":"bb11 1dw",
    "addr:street":"Bull St",
    "iso:country":"GB",
    "sg:address":"4 Bull St",
    "sg:city":"Burnley",
    "sg:classifiers":[
        {
            "category":"Professional",
            "subcategory":"Lawyer & Legal Services",
            "type":"Services"
        }
    ],
    "sg:phone":"+44 1282 416655",
    "sg:postcode":"BB11 1DW",
    "sg:province":"Lancashire",
    "sg:tags":[
        "advice",
        "counselling"
    ],
    "wof:name":"Alcohol Information Centre",
    "wof:placetype":"venue"
},
  "geometry": {"coordinates":[-2.243275,53.788555],"type":"Point"}
}