{
  "type": "Feature",
  "properties": {
    "addr:full":"Unit 55a The Merry Hill Centre Brierley Hill West Midlands DY5 1SR",
    "addr:housenumber":"unit 55a",
    "addr:postcode":"dy5 1sr",
    "addr:street":"The;Hill;Brierley Hill",
    "iso:country":"GB",
    "sg:address":"Unit 55a The Merry Hill Centre",
    "sg:city":"Brierley Hill",
    "sg:classifiers":[
        {
            "category":"Travel",
            "subcategory":"Travel Agent",
            "type":"Entertainment"
        }
    ],
    "sg:phone":"+44 1384 553700",
    "sg:postcode":"DY5 1SR",
    "sg:province":"West Midlands",
    "wof:name":"The Thomas Cook Group Ltd.",
    "wof:placetype":"venue"
},
  "geometry": {"coordinates":[-2.1127500534,52.4818382263],"type":"Point"}
}