{
  "type": "Feature",
  "properties": {
    "iso:country":"GB",
    "sg:address":"18 Mount Road, South Benfleet",
    "sg:city":"Benfleet",
    "sg:classifiers":[
        {
            "category":"Retail",
            "subcategory":"Storage",
            "type":"Services"
        }
    ],
    "sg:phone":"+44 1268 794117",
    "sg:postcode":"SS7 1HA",
    "sg:province":"Essex",
    "sg:tags":[
        "household",
        "removal"
    ],
    "wof:name":"Delivermore",
    "wof:placetype":"venue"
},
  "geometry": {"coordinates":[0.575115025,51.5578231812],"type":"Point"}
}