{
  "type": "Feature",
  "properties": {
    "iso:country":"GB",
    "sg:address":"50 Greenwood Street",
    "sg:city":"Altrincham",
    "sg:classifiers":[
        {
            "category":"Shopping",
            "subcategory":"Department Store",
            "type":"Retail Goods"
        }
    ],
    "sg:phone":"+44 161 929 8837",
    "sg:postcode":"WA14 1RZ",
    "sg:province":"Cheshire",
    "wof:name":"Green Ginger Fabrics",
    "wof:placetype":"venue"
},
  "geometry": {"coordinates":[-2.351472,53.387287],"type":"Point"}
}