{
  "type": "Feature",
  "properties": {
    "iso:country":"GB",
    "sg:address":"66 Longford Road, Melksham",
    "sg:city":"Melksham",
    "sg:classifiers":[
        {
            "category":"Shopping",
            "subcategory":"Photographic Equipment",
            "type":"Retail Goods"
        }
    ],
    "sg:phone":"+44 1225 705636",
    "sg:postcode":"SN12 6AU",
    "sg:province":"Wiltshire",
    "wof:name":"Andy York Photography",
    "wof:placetype":"venue"
},
  "geometry": {"coordinates":[-2.135098,51.364567],"type":"Point"}
}