{
  "type": "Feature",
  "properties": {
    "addr:full":"Unit 14 The Almshouses Arc, The Hornet Chichester West Sussex PO19 4JL",
    "addr:housenumber":"unit 14",
    "addr:postcode":"po19 4jl",
    "addr:street":"The Almshouses Arc The Hornet",
    "iso:country":"GB",
    "sg:address":"Unit 14 The Almshouses Arc, The Hornet",
    "sg:city":"Chichester",
    "sg:classifiers":[
        {
            "category":"Shopping",
            "subcategory":"Baby Store",
            "type":"Retail Goods"
        }
    ],
    "sg:phone":"+44 1243 774613",
    "sg:postcode":"PO19 4JL",
    "sg:province":"West Sussex",
    "sg:tags":[
        "babywear",
        "childrens"
    ],
    "wof:name":"Rascals Baby Clothes",
    "wof:placetype":"venue"
},
  "geometry": {"coordinates":[-0.775429,50.836166],"type":"Point"}
}