{
  "type": "Feature",
  "properties": {
    "addr:full":"23 Weydon Hill Close Farnham Surrey GU9 8PA",
    "addr:housenumber":"23",
    "addr:postcode":"gu9 8pa",
    "addr:street":"Weydon Hill Close",
    "iso:country":"GB",
    "sg:address":"23 Weydon Hill Close",
    "sg:city":"Farnham",
    "sg:classifiers":[
        {
            "category":"Professional",
            "subcategory":"Engineering",
            "type":"Services"
        }
    ],
    "sg:phone":"+44 1252 725157",
    "sg:postcode":"GU9 8PA",
    "sg:province":"Surrey",
    "sg:tags":[
        "contractor",
        "electrical",
        "engineer"
    ],
    "wof:name":"J Tilbury",
    "wof:placetype":"venue"
},
  "geometry": {"coordinates":[-0.8005920053,51.2070350647],"type":"Point"}
}