{
  "type": "Feature",
  "properties": {
    "addr:full":"18 West Street Retford Nottinghamshire DN22 6ES",
    "addr:housenumber":"18",
    "addr:postcode":"dn22 6es",
    "addr:street":"West Street",
    "iso:country":"GB",
    "sg:address":"18 West Street",
    "sg:city":"Retford",
    "sg:classifiers":[
        {
            "category":"Building & Trades",
            "subcategory":"Construction",
            "type":"Services"
        }
    ],
    "sg:phone":"+44 1777 708337",
    "sg:postcode":"DN22 6ES",
    "sg:province":"Nottinghamshire",
    "sg:tags":[
        "builder"
    ],
    "wof:name":"F & N Ieronimo",
    "wof:placetype":"venue"
},
  "geometry": {"coordinates":[-0.943039,53.320454],"type":"Point"}
}