{
  "type": "Feature",
  "properties": {
    "iso:country":"GB",
    "sg:address":"113-115 Broadway West",
    "sg:city":"Leigh On Sea",
    "sg:classifiers":[
        {
            "category":"Shopping",
            "subcategory":"Antiques",
            "type":"Retail Goods"
        }
    ],
    "sg:phone":"+44 1702 710747",
    "sg:postcode":"SS9 2BU",
    "sg:province":"Essex",
    "wof:name":"Wrenn Richard Antiques",
    "wof:placetype":"venue"
},
  "geometry": {"coordinates":[0.650995,51.548481],"type":"Point"}
}