{
  "type": "Feature",
  "properties": {
    "addr:full":"St Margaret Street Dunfermline Fife KY12 7PE",
    "addr:postcode":"ky12 7pe",
    "addr:street":"Margaret Street",
    "iso:country":"GB",
    "sg:address":"St Margaret Street",
    "sg:city":"Dunfermline",
    "sg:classifiers":[
        {
            "category":"Landmark",
            "subcategory":"Tourist Information",
            "type":"Public Place"
        },
        {
            "category":"Landmark",
            "subcategory":"Tourist Attraction",
            "type":"Public Place"
        }
    ],
    "sg:phone":"+44 1383 739026",
    "sg:postcode":"KY12 7PE",
    "sg:province":"Fife",
    "sg:tags":[
        "tour",
        "guide",
        "interest",
        "sightseeing"
    ],
    "wof:name":"Historic Scotland",
    "wof:placetype":"venue"
},
  "geometry": {"coordinates":[-3.461604,56.070278],"type":"Point"}
}