{
  "type": "Feature",
  "properties": {
    "iso:country":"GB",
    "sg:address":"60 Baghill Ct",
    "sg:city":"Pontefract",
    "sg:classifiers":[
        {
            "category":"Building & Trades",
            "subcategory":"Construction",
            "type":"Services"
        }
    ],
    "sg:phone":"+44 1977 797414",
    "sg:postcode":"WF8 2NN",
    "sg:province":"North Yorkshire",
    "sg:tags":[
        "builder"
    ],
    "wof:name":"Rollinson Builders & Joiners",
    "wof:placetype":"venue"
},
  "geometry": {"coordinates":[-1.292671,53.691612],"type":"Point"}
}