{
  "type": "Feature",
  "properties": {
    "addr:full":"9 Parkview Road London Greater London SE9 3QP",
    "addr:housenumber":"9",
    "addr:postcode":"se9 3qp",
    "addr:street":"Parkview Road",
    "iso:country":"GB",
    "sg:address":"9 Parkview Road",
    "sg:city":"London",
    "sg:classifiers":[
        {
            "category":"Building & Trades",
            "subcategory":"Construction",
            "type":"Services"
        }
    ],
    "sg:phone":"+44 20 8859 5170",
    "sg:postcode":"SE9 3QP",
    "sg:province":"Greater London",
    "sg:tags":[
        "roofing"
    ],
    "wof:name":"Peter J Wiffen Roofing",
    "wof:placetype":"venue"
},
  "geometry": {"coordinates":[0.064743,51.437119],"type":"Point"}
}