{
  "type": "Feature",
  "properties": {
    "iso:country":"GB",
    "sg:address":"5 Miller Way, Exminster",
    "sg:city":"Exeter",
    "sg:classifiers":[
        {
            "category":"Building & Trades",
            "subcategory":"Plumbing",
            "type":"Services"
        }
    ],
    "sg:phone":"+44 1392 824868",
    "sg:postcode":"EX6 8TH",
    "sg:province":"Devon",
    "sg:tags":[
        "central",
        "installation",
        "system",
        "servicing",
        "heating"
    ],
    "wof:name":"Heatrite Installations",
    "wof:placetype":"venue"
},
  "geometry": {"coordinates":[-3.503448,50.683838],"type":"Point"}
}