{
  "type": "Feature",
  "properties": {
    "addr:full":"102 Lee High Road London Greater London SE13 5PT",
    "addr:housenumber":"102",
    "addr:postcode":"se13 5pt",
    "addr:street":"Lee High Road",
    "iso:country":"GB",
    "sg:address":"102 Lee High Road",
    "sg:city":"London",
    "sg:classifiers":[
        {
            "category":"Professional",
            "subcategory":"Accounting & Tax Preparation",
            "type":"Services"
        }
    ],
    "sg:phone":"+44 20 8318 9909",
    "sg:postcode":"SE13 5PT",
    "sg:province":"Greater London",
    "sg:tags":[
        "accountant"
    ],
    "wof:name":"Andrew Cross & Co",
    "wof:placetype":"venue"
},
  "geometry": {"coordinates":[-0.006367,51.461258],"type":"Point"}
}