{
  "type": "Feature",
  "properties": {
    "iso:country":"GB",
    "sg:address":"90 Salisbury Avenue",
    "sg:city":"Broadstairs",
    "sg:classifiers":[
        {
            "category":"Building & Trades",
            "subcategory":"Landscaping Services",
            "type":"Services"
        }
    ],
    "sg:phone":"+44 1843 865738",
    "sg:postcode":"CT10 2DX",
    "sg:province":"Kent",
    "sg:tags":[
        "landscape",
        "contractor"
    ],
    "wof:name":"A K Bray",
    "wof:placetype":"venue"
},
  "geometry": {"coordinates":[1.42936,51.350399],"type":"Point"}
}