{
  "type": "Feature",
  "properties": {
    "addr:full":"376 Silbury Boulevard, Central Milton Keynes Milton Keynes Buckinghamshire MK9 2AF",
    "addr:housenumber":"376",
    "addr:postcode":"mk9 2af",
    "addr:street":"Silbury Boulevard",
    "iso:country":"GB",
    "sg:address":"376 Silbury Boulevard, Central Milton Keynes",
    "sg:city":"Milton Keynes",
    "sg:classifiers":[
        {
            "category":"Professional",
            "subcategory":"Lawyer & Legal Services",
            "type":"Services"
        }
    ],
    "sg:phone":"+44 1908 696002",
    "sg:postcode":"MK9 2AF",
    "sg:province":"Buckinghamshire",
    "sg:tags":[
        "solicitor"
    ],
    "wof:name":"Borneo Martell",
    "wof:placetype":"venue"
},
  "geometry": {"coordinates":[-0.763171,52.041241],"type":"Point"}
}