{
  "type": "Feature",
  "properties": {
    "iso:country":"GB",
    "sg:address":"107 Cricklewood Bdwy",
    "sg:city":"London",
    "sg:classifiers":[
        {
            "category":"Professional",
            "subcategory":"Business Services",
            "type":"Services"
        }
    ],
    "sg:postcode":"NW2 3JG",
    "sg:province":"Greater London",
    "sg:tags":[
        "answering"
    ],
    "wof:name":"Quick & Cheap",
    "wof:placetype":"venue"
},
  "geometry": {"coordinates":[-0.21327,51.554852],"type":"Point"}
}