{
  "type": "Feature",
  "properties": {
    "iso:country":"GB",
    "sg:address":"142 Nangreave Road",
    "sg:city":"Stockport",
    "sg:classifiers":[
        {
            "category":"Fast Food",
            "type":"Food & Drink"
        }
    ],
    "sg:phone":"+44 161 456 5758",
    "sg:postcode":"SK2 6DG",
    "sg:province":"Cheshire",
    "sg:tags":[
        "away",
        "take"
    ],
    "wof:name":"A Uddin",
    "wof:placetype":"venue"
},
  "geometry": {"coordinates":[-2.13882,53.396557],"type":"Point"}
}