{
  "type": "Feature",
  "properties": {
    "addr:full":"111 New Road London Greater London E1 1HJ",
    "addr:housenumber":"111",
    "addr:postcode":"e1 1hj",
    "addr:street":"New Road",
    "iso:country":"GB",
    "sg:address":"111 New Road",
    "sg:city":"London",
    "sg:classifiers":[
        {
            "category":"Shopping",
            "subcategory":"Clothing, Apparel, & Fashions",
            "type":"Retail Goods"
        }
    ],
    "sg:phone":"+44 20 7247 4491",
    "sg:postcode":"E1 1HJ",
    "sg:province":"Greater London",
    "sg:tags":[
        "clothing"
    ],
    "wof:name":"Young Image",
    "wof:placetype":"venue"
},
  "geometry": {"coordinates":[-0.062793,51.517551],"type":"Point"}
}