{
  "type": "Feature",
  "properties": {
    "addr:full":"Blackley New Road Manchester Greater Manchester M9 8ER",
    "addr:postcode":"m9 8er",
    "addr:street":"New Road",
    "iso:country":"GB",
    "sg:address":"Blackley New Road",
    "sg:city":"Manchester",
    "sg:classifiers":[
        {
            "category":"Manufacturing",
            "subcategory":"Textiles",
            "type":"Manufacturing & Wholesale Goods"
        }
    ],
    "sg:postcode":"M9 8ER",
    "sg:province":"Greater Manchester",
    "sg:tags":[
        "dyer"
    ],
    "wof:name":"Tonge & Young Ltd.",
    "wof:placetype":"venue"
},
  "geometry": {"coordinates":[-2.247564,53.525768],"type":"Point"}
}