{
  "type": "Feature",
  "properties": {
    "iso:country":"GB",
    "sg:address":"Ivy House, 7 Lonsdale Road",
    "sg:city":"Newton Abbot",
    "sg:classifiers":[
        {
            "category":"Building & Trades",
            "subcategory":"Construction",
            "type":"Services"
        }
    ],
    "sg:postcode":"TQ12 1DT",
    "sg:province":"Devon",
    "sg:tags":[
        "glazier",
        "decorator",
        "painter"
    ],
    "wof:name":"J T Bristowe",
    "wof:placetype":"venue"
},
  "geometry": {"coordinates":[-3.60066,50.523716],"type":"Point"}
}