{
  "type": "Feature",
  "properties": {
    "iso:country":"GB",
    "sg:address":"Woodhouse Farm, Easby, Great Ayton",
    "sg:city":"Middlesbrough",
    "sg:classifiers":[
        {
            "category":"Banks & Credit Unions",
            "subcategory":"Investment Brokerage",
            "type":"Services"
        }
    ],
    "sg:phone":"+44 1642 722266",
    "sg:postcode":"TS9 6JN",
    "sg:province":"North Yorkshire",
    "sg:tags":[
        "contractor"
    ],
    "wof:name":"Derek Welford Farming Services",
    "wof:placetype":"venue"
},
  "geometry": {"coordinates":[-1.141065,54.489876],"type":"Point"}
}