{
  "type": "Feature",
  "properties": {
    "addr:full":"48 Cranbourn St Holborn Greater London WC2H 7AN",
    "addr:housenumber":"48",
    "addr:postcode":"wc2h 7an",
    "addr:street":"Cranbourn St",
    "iso:country":"GB",
    "sg:address":"48 Cranbourn St",
    "sg:city":"Holborn",
    "sg:classifiers":[
        {
            "category":"Banks & Credit Unions",
            "subcategory":"Bureau De Change",
            "type":"Services"
        }
    ],
    "sg:phone":"+44 20 7494 0390",
    "sg:postcode":"WC2H 7AN",
    "sg:province":"Greater London",
    "wof:name":"West End Bureau De Change",
    "wof:placetype":"venue"
},
  "geometry": {"coordinates":[-0.129362002,51.5110359192],"type":"Point"}
}