{
  "type": "Feature",
  "properties": {
    "iso:country":"GB",
    "sg:address":"1 Abbots Close",
    "sg:city":"Ilminster",
    "sg:classifiers":[
        {
            "category":"Building & Trades",
            "subcategory":"Landscaping Services",
            "type":"Services"
        }
    ],
    "sg:phone":"+44 1460 55252",
    "sg:postcode":"TA19 0EF",
    "sg:province":"Somerset",
    "sg:tags":[
        "landscape",
        "contractor"
    ],
    "wof:name":"Miles & Widdows Landscape Construction",
    "wof:placetype":"venue"
},
  "geometry": {"coordinates":[-2.914199,50.925777],"type":"Point"}
}