{
  "type": "Feature",
  "properties": {
    "iso:country":"GB",
    "sg:address":"11 Windmill Hill Dr",
    "sg:city":"Milton Keynes",
    "sg:classifiers":[
        {
            "category":"Manufacturing",
            "subcategory":"Petroleum Products",
            "type":"Manufacturing & Wholesale Goods"
        }
    ],
    "sg:phone":"+44 1908 378332",
    "sg:postcode":"MK3 7RE",
    "sg:province":"Buckinghamshire",
    "sg:tags":[
        "double",
        "glazing"
    ],
    "wof:name":"D & C White",
    "wof:placetype":"venue"
},
  "geometry": {"coordinates":[-0.766129,51.992268],"type":"Point"}
}