{
  "type": "Feature",
  "properties": {
    "addr:full":"Craven House, 121 Kingsway London Greater London WC2B 6PA",
    "addr:housenumber":"121",
    "addr:postcode":"wc2b 6pa",
    "addr:street":"Kingsway",
    "iso:country":"GB",
    "sg:address":"Craven House, 121 Kingsway",
    "sg:city":"London",
    "sg:classifiers":[
        {
            "category":"Education",
            "subcategory":"Special Training",
            "type":"Public Place"
        }
    ],
    "sg:phone":"+44 20 7721 8036",
    "sg:postcode":"WC2B 6PA",
    "sg:province":"Greater London",
    "sg:tags":[
        "product",
        "centre"
    ],
    "wof:name":"One to One Computing",
    "wof:placetype":"venue"
},
  "geometry": {"coordinates":[-0.120219,51.516918],"type":"Point"}
}