{
  "type": "Feature",
  "properties": {
    "iso:country":"GB",
    "sg:address":"North House, 5 North Road, Stokesley",
    "sg:city":"Middlesbrough",
    "sg:classifiers":[
        {
            "category":"Professional",
            "subcategory":"Advertising",
            "type":"Services"
        }
    ],
    "sg:postcode":"TS9 5DU",
    "sg:province":"North Yorkshire",
    "sg:tags":[
        "agency"
    ],
    "wof:name":"Mills Advertising & Publicity",
    "wof:placetype":"venue"
},
  "geometry": {"coordinates":[-1.192826,54.470684],"type":"Point"}
}