{
  "type": "Feature",
  "properties": {
    "iso:country":"GB",
    "sg:address":"Unit 17 Fairwater Industrial Estate, Norbury Road, Fairwater",
    "sg:city":"Cardiff",
    "sg:classifiers":[
        {
            "category":"Wholesale",
            "subcategory":"Vending Machines",
            "type":"Manufacturing & Wholesale Goods"
        }
    ],
    "sg:phone":"+44 29 2057 6611",
    "sg:postcode":"CF5 3BG",
    "sg:province":"Cardiff",
    "wof:name":"Flavour Cup Thornbury Vending",
    "wof:placetype":"venue"
},
  "geometry": {"coordinates":[-3.244994,51.489716],"type":"Point"}
}