{
  "type": "Feature",
  "properties": {
    "iso:country":"GB",
    "sg:address":"Red Marley Road",
    "sg:city":"Newent",
    "sg:classifiers":[
        {
            "category":"Farming",
            "subcategory":"Farm",
            "type":"Manufacturing & Wholesale Goods"
        }
    ],
    "sg:phone":"+44 1531 820568",
    "sg:postcode":"GL18 1LJ",
    "sg:province":"Gloucestershire",
    "sg:tags":[
        "egg",
        "producer"
    ],
    "wof:name":"Stallard Bros Ltd.",
    "wof:placetype":"venue"
},
  "geometry": {"coordinates":[-2.406134,51.930828],"type":"Point"}
}