{
  "type": "Feature",
  "properties": {
    "addr:full":"319 Two Mile Hill Road Bristol City of Bristol BS15 1AP",
    "addr:housenumber":"319",
    "addr:postcode":"bs15 1ap",
    "addr:street":"Two Mile Hill Road",
    "iso:country":"GB",
    "sg:address":"319 Two Mile Hill Road",
    "sg:city":"Bristol",
    "sg:classifiers":[
        {
            "category":"Personal",
            "subcategory":"Beauty Salon",
            "type":"Services"
        }
    ],
    "sg:phone":"+44 117 967 5761",
    "sg:postcode":"BS15 1AP",
    "sg:province":"City of Bristol",
    "sg:tags":[
        "unisex",
        "hairdresser"
    ],
    "wof:name":"Giggles Hair Studio",
    "wof:placetype":"venue"
},
  "geometry": {"coordinates":[-2.514919,51.463234],"type":"Point"}
}