{
  "type": "Feature",
  "properties": {
    "addr:full":"Kirkwood, Arkholme Carnforth Cumbria LA6 1BG",
    "addr:postcode":"la6 1bg",
    "addr:street":"Carnforth",
    "iso:country":"GB",
    "sg:address":"Kirkwood, Arkholme",
    "sg:city":"Carnforth",
    "sg:classifiers":[
        {
            "category":"Building & Trades",
            "subcategory":"Construction",
            "type":"Services"
        }
    ],
    "sg:postcode":"LA6 1BG",
    "sg:province":"Cumbria",
    "sg:tags":[
        "dry",
        "lining",
        "plasterers",
        "screeders"
    ],
    "wof:name":"W P Benson",
    "wof:placetype":"venue"
},
  "geometry": {"coordinates":[-2.6379890442,54.1444168091],"type":"Point"}
}