{
  "type": "Feature",
  "properties": {
    "addr:full":"71 Church Lane, Anstey Leicester Leicestershire LE7 7AF",
    "addr:housenumber":"71",
    "addr:postcode":"le7 7af",
    "addr:street":"Church Lane",
    "iso:country":"GB",
    "sg:address":"71 Church Lane, Anstey",
    "sg:city":"Leicester",
    "sg:classifiers":[
        {
            "category":"Home & Garden",
            "subcategory":"Home Furnishings",
            "type":"Retail Goods"
        },
        {
            "category":"Home & Garden",
            "subcategory":"Furniture",
            "type":"Retail Goods"
        }
    ],
    "sg:phone":"+44 116 236 4221",
    "sg:postcode":"LE7 7AF",
    "sg:province":"Leicestershire",
    "sg:tags":[
        "soft",
        "sale"
    ],
    "wof:name":"Graham Botterill",
    "wof:placetype":"venue"
},
  "geometry": {"coordinates":[-1.1902509928,52.67212677],"type":"Point"}
}