{
  "type": "Feature",
  "properties": {
    "addr:full":"2a Leeland Road London Greater London W13 9HH",
    "addr:housenumber":"2a",
    "addr:postcode":"w13 9hh",
    "addr:street":"Leeland Road",
    "iso:country":"GB",
    "sg:address":"2a Leeland Road",
    "sg:city":"London",
    "sg:classifiers":[
        {
            "category":"Shopping",
            "subcategory":"Florist",
            "type":"Retail Goods"
        }
    ],
    "sg:postcode":"W13 9HH",
    "sg:province":"Greater London",
    "wof:name":"The House of Flowers",
    "wof:placetype":"venue"
},
  "geometry": {"coordinates":[-0.3233599961,51.5101318359],"type":"Point"}
}