{
  "type": "Feature",
  "properties": {
    "iso:country":"GB",
    "sg:address":"14 Mayfield Gardens",
    "sg:city":"London",
    "sg:classifiers":[
        {
            "category":"Professional",
            "subcategory":"Accounting & Tax Preparation",
            "type":"Services"
        }
    ],
    "sg:phone":"+44 20 8202 8864",
    "sg:postcode":"NW4 2QA",
    "sg:province":"Greater London",
    "sg:tags":[
        "accountant"
    ],
    "wof:name":"Chaim Pearlman",
    "wof:placetype":"venue"
},
  "geometry": {"coordinates":[-0.216088,51.580231],"type":"Point"}
}