{
  "type": "Feature",
  "properties": {
    "iso:country":"GB",
    "sg:address":"43 Spring Gardens",
    "sg:city":"Watford",
    "sg:classifiers":[
        {
            "category":"Building & Trades",
            "subcategory":"Construction",
            "type":"Services"
        }
    ],
    "sg:phone":"+44 1923 677267",
    "sg:postcode":"WD2 6JJ",
    "sg:province":"Hertfordshire",
    "sg:tags":[
        "tiling",
        "contractor"
    ],
    "wof:name":"D A Aldrich",
    "wof:placetype":"venue"
},
  "geometry": {"coordinates":[-0.394801,51.683449],"type":"Point"}
}