{
  "type": "Feature",
  "properties": {
    "addr:full":"6 Pooley Clo, Stamfordham Road Indust Est Newcastle Upon Tyne Tyne and Wear NE5 2TF",
    "addr:housenumber":"6",
    "addr:postcode":"ne5 2tf",
    "addr:street":"Pooley Clo Stamfordham Road",
    "iso:country":"GB",
    "sg:address":"6 Pooley Clo, Stamfordham Road Indust Est",
    "sg:city":"Newcastle Upon Tyne",
    "sg:classifiers":[
        {
            "category":"Home & Garden",
            "subcategory":"Home Furnishings",
            "type":"Retail Goods"
        }
    ],
    "sg:phone":"+44 191 214 0284",
    "sg:postcode":"NE5 2TF",
    "sg:province":"Tyne and Wear",
    "sg:tags":[
        "merchant",
        "diy",
        "decorators'"
    ],
    "wof:name":"McDougall Rose",
    "wof:placetype":"venue"
},
  "geometry": {"coordinates":[-1.6757600307,54.9905395508],"type":"Point"}
}