{
  "type": "Feature",
  "properties": {
    "addr:full":"242 Louth Road Grimsby Lincolnshire DN33 2LF",
    "addr:housenumber":"242",
    "addr:postcode":"dn33 2lf",
    "addr:street":"Louth Road",
    "iso:country":"GB",
    "sg:address":"242 Louth Road",
    "sg:city":"Grimsby",
    "sg:classifiers":[
        {
            "category":"Building & Trades",
            "subcategory":"Plumbing",
            "type":"Services"
        }
    ],
    "sg:phone":"+44 1472 822291",
    "sg:postcode":"DN33 2LF",
    "sg:province":"Lincolnshire",
    "sg:tags":[
        "heating"
    ],
    "wof:name":"Steve Wilkinson Plumbing & Heating",
    "wof:placetype":"venue"
},
  "geometry": {"coordinates":[-0.084764,53.530769],"type":"Point"}
}