{
  "type": "Feature",
  "properties": {
    "iso:country":"GB",
    "sg:address":"124 High Street, Strood",
    "sg:city":"Rochester",
    "sg:classifiers":[
        {
            "category":"Home & Garden",
            "subcategory":"Carpets & Floor Coverings",
            "type":"Retail Goods"
        }
    ],
    "sg:phone":"+44 1634 720680",
    "sg:postcode":"ME2 4TR",
    "sg:province":"Kent",
    "sg:tags":[
        "carpets",
        "retailer",
        "rug",
        "matting"
    ],
    "wof:name":"THE CARPET STORES",
    "wof:placetype":"venue"
},
  "geometry": {"coordinates":[0.493002,51.39595],"type":"Point"}
}