{
  "type": "Feature",
  "properties": {
    "iso:country":"GB",
    "sg:address":"The Athletic Ground, Kew Foot Rd",
    "sg:city":"Richmond",
    "sg:classifiers":[
        {
            "category":"Arena",
            "subcategory":"Sports Club",
            "type":"Entertainment"
        }
    ],
    "sg:phone":"+44 20 8948 5929",
    "sg:postcode":"TW9 2SS",
    "sg:province":"Greater London",
    "wof:name":"London Scottish Rugby Club",
    "wof:placetype":"venue"
},
  "geometry": {"coordinates":[-0.302784,51.462349],"type":"Point"}
}