{
  "type": "Feature",
  "properties": {
    "iso:country":"GB",
    "sg:address":"St Fillans Medical Centre, 2 Liverpool Road, Penwortham",
    "sg:city":"Preston",
    "sg:classifiers":[
        {
            "category":"Health Services",
            "subcategory":"Doctor",
            "type":"Services"
        }
    ],
    "sg:phone":"+44 1772 745427",
    "sg:postcode":"PR1 0AD",
    "sg:province":"Lancashire",
    "sg:tags":[
        "practitioners"
    ],
    "wof:name":"T P O'Connor",
    "wof:placetype":"venue"
},
  "geometry": {"coordinates":[-2.72927,53.75013],"type":"Point"}
}