{
  "type": "Feature",
  "properties": {
    "iso:country":"GB",
    "sg:address":"35a Victoria Road",
    "sg:city":"Surbiton",
    "sg:classifiers":[
        {
            "category":"Real Estate",
            "subcategory":"Real Estate Agent",
            "type":"Services"
        }
    ],
    "sg:phone":"+44 20 8390 8888",
    "sg:postcode":"KT6 4JT",
    "sg:province":"Surrey",
    "wof:name":"Udry Properties Ltd.",
    "wof:placetype":"venue"
},
  "geometry": {"coordinates":[-0.310954,51.390247],"type":"Point"}
}