{
  "type": "Feature",
  "properties": {
    "iso:country":"GB",
    "sg:address":"1 Bowers Row",
    "sg:city":"Nantwich",
    "sg:classifiers":[
        {
            "category":"Personal",
            "subcategory":"Beauty Salon",
            "type":"Services"
        }
    ],
    "sg:postcode":"CW5 5DZ",
    "sg:province":"Cheshire",
    "sg:tags":[
        "unisex",
        "hairdresser"
    ],
    "wof:name":"Hair Gardeners",
    "wof:placetype":"venue"
},
  "geometry": {"coordinates":[-2.523274,53.06665],"type":"Point"}
}