{
  "type": "Feature",
  "properties": {
    "iso:country":"GB",
    "sg:address":"5a Main Street, Greasbrough",
    "sg:city":"Rotherham",
    "sg:classifiers":[
        {
            "category":"Health Services",
            "subcategory":"Dentist",
            "type":"Services"
        }
    ],
    "sg:postcode":"S61 4PX",
    "sg:province":"South Yorkshire",
    "wof:name":"Grayes Dental Practise",
    "wof:placetype":"venue"
},
  "geometry": {"coordinates":[-1.368677,53.45536],"type":"Point"}
}