{
  "type": "Feature",
  "properties": {
    "addr:full":"Unit 8 Leyton Business Centre London Greater London E10 7BT",
    "addr:housenumber":"unit 8;business",
    "addr:postcode":"e10 7bt",
    "addr:street":"Leyton",
    "iso:country":"GB",
    "sg:address":"Unit 8 Leyton Business Centre",
    "sg:city":"London",
    "sg:classifiers":[
        {
            "category":"Shopping",
            "subcategory":"Stationery & Office Supplies",
            "type":"Retail Goods"
        }
    ],
    "sg:phone":"+44 20 8532 8944",
    "sg:postcode":"E10 7BT",
    "sg:province":"Greater London",
    "sg:tags":[
        "printers'"
    ],
    "wof:name":"Scorpio Embossing",
    "wof:placetype":"venue"
},
  "geometry": {"coordinates":[-0.02159,51.568748],"type":"Point"}
}