{
  "type": "Feature",
  "properties": {
    "iso:country":"GB",
    "sg:address":"2 Bell Clough Road, Droylsden",
    "sg:city":"Manchester",
    "sg:classifiers":[
        {
            "category":"Shopping",
            "subcategory":"News",
            "type":"Retail Goods"
        }
    ],
    "sg:postcode":"M43 7WR",
    "sg:province":"Greater Manchester",
    "sg:tags":[
        "newsagent"
    ],
    "wof:name":"Oppals",
    "wof:placetype":"venue"
},
  "geometry": {"coordinates":[-2.14418,53.48753],"type":"Point"}
}