{
  "type": "Feature",
  "properties": {
    "iso:country":"GB",
    "sg:address":"57 Sun Lane",
    "sg:city":"Gravesend",
    "sg:classifiers":[
        {
            "category":"Personal",
            "subcategory":"Beauty Salon",
            "type":"Services"
        }
    ],
    "sg:postcode":"DA12 5HQ",
    "sg:province":"Kent",
    "sg:tags":[
        "unisex",
        "hairdresser"
    ],
    "wof:name":"The Hair Studio",
    "wof:placetype":"venue"
},
  "geometry": {"coordinates":[0.374979,51.428764],"type":"Point"}
}