{
  "type": "Feature",
  "properties": {
    "iso:country":"GB",
    "sg:address":"First Avenue, Southbourne",
    "sg:city":"Emsworth",
    "sg:classifiers":[
        {
            "category":"Community Center",
            "type":"Public Place"
        }
    ],
    "sg:phone":"+44 1243 371715",
    "sg:postcode":"PO10 8HN",
    "sg:province":"Hampshire",
    "sg:tags":[
        "centre"
    ],
    "wof:name":"Southbourne Village Hall",
    "wof:placetype":"venue"
},
  "geometry": {"coordinates":[-0.910219,50.855724],"type":"Point"}
}