{
  "type": "Feature",
  "properties": {
    "iso:country":"GB",
    "sg:address":"Station Rd",
    "sg:city":"Totnes",
    "sg:classifiers":[
        {
            "category":"Education",
            "subcategory":"Special Training",
            "type":"Public Place"
        }
    ],
    "sg:phone":"+44 1803 868383",
    "sg:postcode":"TQ9 5HW",
    "sg:province":"Devon",
    "sg:tags":[
        "aid",
        "first"
    ],
    "wof:name":"St. John Ambulance",
    "wof:placetype":"venue"
},
  "geometry": {"coordinates":[-3.685299,50.433636],"type":"Point"}
}