{
  "type": "Feature",
  "properties": {
    "addr:full":"Unit 46 Portmanmoor Rd Industrial Estate Cardiff Cardiff CF2 2HB",
    "addr:housenumber":"unit 46",
    "addr:postcode":"cf2 2hb",
    "addr:street":"Portmanmoor Rd Industrial Estate",
    "iso:country":"GB",
    "sg:address":"Unit 46 Portmanmoor Rd Industrial Estate",
    "sg:city":"Cardiff",
    "sg:classifiers":[
        {
            "category":"Home & Garden",
            "subcategory":"Hardware",
            "type":"Retail Goods"
        }
    ],
    "sg:phone":"+44 29 2046 1767",
    "sg:postcode":"CF2 2HB",
    "sg:province":"Cardiff",
    "sg:tags":[
        "device",
        "fixing",
        "fastener"
    ],
    "wof:name":"Jay Fasteners",
    "wof:placetype":"venue"
},
  "geometry": {"coordinates":[-3.146789,51.475033],"type":"Point"}
}