{
  "type": "Feature",
  "properties": {
    "iso:country":"GB",
    "sg:address":"Stoney Brow Quarry",
    "sg:city":"Wigan",
    "sg:classifiers":[
        {
            "category":"Wholesale",
            "subcategory":"Construction Materials",
            "type":"Manufacturing & Wholesale Goods"
        }
    ],
    "sg:postcode":"WN8 0QE",
    "sg:province":"Lancashire",
    "sg:tags":[
        "merchant",
        "stone"
    ],
    "wof:name":"Hardrock Ltd.",
    "wof:placetype":"venue"
},
  "geometry": {"coordinates":[-2.7292098999,53.557849884],"type":"Point"}
}