{
  "type": "Feature",
  "properties": {
    "addr:full":"319 Long Lane, Hillingdon Uxbridge Greater London UB10 9JU",
    "addr:housenumber":"319",
    "addr:postcode":"ub10 9ju",
    "addr:street":"Long Lane",
    "iso:country":"GB",
    "sg:address":"319 Long Lane, Hillingdon",
    "sg:city":"Uxbridge",
    "sg:classifiers":[
        {
            "category":"Food & Beverages",
            "subcategory":"Meat & Fish",
            "type":"Retail Goods"
        }
    ],
    "sg:phone":"+44 1895 270620",
    "sg:postcode":"UB10 9JU",
    "sg:province":"Greater London",
    "sg:tags":[
        "butcher"
    ],
    "wof:name":"Ray J Garner",
    "wof:placetype":"venue"
},
  "geometry": {"coordinates":[-0.449373,51.551342],"type":"Point"}
}