{
  "type": "Feature",
  "properties": {
    "addr:full":"Unit 2 4 Holford Way, Holford Birmingham West Midlands B6 7AX",
    "addr:housenumber":"unit;4",
    "addr:postcode":"b6 7ax",
    "addr:street":"Holford Way",
    "iso:country":"GB",
    "sg:address":"Unit 2 4 Holford Way, Holford",
    "sg:city":"Birmingham",
    "sg:classifiers":[
        {
            "category":"Professional",
            "subcategory":"Computer Services",
            "type":"Services"
        }
    ],
    "sg:phone":"+44 121 356 0831",
    "sg:postcode":"B6 7AX",
    "sg:province":"West Midlands",
    "sg:tags":[
        "system",
        "software"
    ],
    "wof:name":"Eidos Interactive Ltd.",
    "wof:placetype":"venue"
},
  "geometry": {"coordinates":[-1.88314,52.518425],"type":"Point"}
}