{
  "type": "Feature",
  "properties": {
    "iso:country":"GB",
    "sg:address":"Sutton Road",
    "sg:city":"Maidstone",
    "sg:classifiers":[
        {
            "category":"Education",
            "subcategory":"School",
            "type":"Public Place"
        }
    ],
    "sg:phone":"+44 1622 677471",
    "sg:postcode":"ME15 9DT",
    "sg:province":"Kent",
    "sg:tags":[
        "college"
    ],
    "wof:name":"Senacre Technology College",
    "wof:placetype":"venue"
},
  "geometry": {"coordinates":[0.5320379734,51.2564926147],"type":"Point"}
}