{
  "type": "Feature",
  "properties": {
    "addr:full":"20 Easedale Close Coventry Warwickshire CV3 6LH",
    "addr:housenumber":"20",
    "addr:postcode":"cv3 6lh",
    "addr:street":"Easedale Close",
    "iso:country":"GB",
    "sg:address":"20 Easedale Close",
    "sg:city":"Coventry",
    "sg:classifiers":[
        {
            "category":"Shopping",
            "subcategory":"Pharmacy",
            "type":"Retail Goods"
        }
    ],
    "sg:phone":"+44 24 7641 4887",
    "sg:postcode":"CV3 6LH",
    "sg:province":"Warwickshire",
    "sg:tags":[
        "medicine",
        "therapy"
    ],
    "wof:name":"Roy Gunn",
    "wof:placetype":"venue"
},
  "geometry": {"coordinates":[-1.5224629641,52.386089325],"type":"Point"}
}