{
  "type": "Feature",
  "properties": {
    "addr:full":"Glenwood, Headley Heath Approach Tadworth Surrey KT20 7LG",
    "addr:postcode":"kt20 7lg",
    "addr:street":"Glenwood",
    "iso:country":"GB",
    "sg:address":"Glenwood, Headley Heath Approach",
    "sg:city":"Tadworth",
    "sg:classifiers":[
        {
            "category":"Building & Trades",
            "subcategory":"Landscaping Services",
            "type":"Services"
        }
    ],
    "sg:phone":"+44 1737 843232",
    "sg:postcode":"KT20 7LG",
    "sg:province":"Surrey",
    "sg:tags":[
        "gardening",
        "landscape",
        "contractor"
    ],
    "wof:name":"Richard Everett",
    "wof:placetype":"venue"
},
  "geometry": {"coordinates":[-0.2878299952,51.2538757324],"type":"Point"}
}