{
  "type": "Feature",
  "properties": {
    "addr:full":"48 Sturla Rd Chatham Kent ME4 5QL",
    "addr:housenumber":"48",
    "addr:postcode":"me4 5ql",
    "addr:street":"Sturla Rd",
    "iso:country":"GB",
    "sg:address":"48 Sturla Rd",
    "sg:city":"Chatham",
    "sg:classifiers":[
        {
            "category":"Building & Trades",
            "subcategory":"Equipment Rental",
            "type":"Services"
        }
    ],
    "sg:phone":"+44 1634 403175",
    "sg:postcode":"ME4 5QL",
    "sg:province":"Kent",
    "sg:tags":[
        "plant",
        "machinery"
    ],
    "wof:name":"C R B Engineering Ltd",
    "wof:placetype":"venue"
},
  "geometry": {"coordinates":[0.531571,51.375858],"type":"Point"}
}