{
  "type": "Feature",
  "properties": {
    "addr:full":"Morrison Street Castleford West Yorkshire WF10 4BE",
    "addr:postcode":"wf10 4be",
    "addr:street":"Morrison Street",
    "iso:country":"GB",
    "sg:address":"Morrison Street",
    "sg:city":"Castleford",
    "sg:classifiers":[
        {
            "category":"Community Center",
            "subcategory":"Senior",
            "type":"Public Place"
        }
    ],
    "sg:postcode":"WF10 4BE",
    "sg:province":"West Yorkshire",
    "sg:tags":[
        "seating"
    ],
    "wof:name":"Castleford Chair Frameworks",
    "wof:placetype":"venue"
},
  "geometry": {"coordinates":[-1.3440090418,53.7227516174],"type":"Point"}
}