{
  "type": "Feature",
  "properties": {
    "addr:full":"Unit 2, Little Eastfields, Wolf Lane Alton Hampshire GU34 3HJ",
    "addr:housenumber":"unit 2",
    "addr:postcode":"gu34 3hj",
    "addr:street":"Little;Wolf Lane",
    "iso:country":"GB",
    "sg:address":"Unit 2, Little Eastfields, Wolf Lane",
    "sg:city":"Alton",
    "sg:classifiers":[
        {
            "category":"Retail",
            "subcategory":"Auto Rental",
            "type":"Services"
        }
    ],
    "sg:postcode":"GU34 3HJ",
    "sg:province":"Hampshire",
    "sg:tags":[
        "car"
    ],
    "wof:name":"Impulse Fleet Management Ltd.",
    "wof:placetype":"venue"
},
  "geometry": {"coordinates":[-0.974329,51.14756],"type":"Point"}
}