{
  "type": "Feature",
  "properties": {
    "addr:full":"29 North Rd Cardigan Ceredigion SA43 1LS",
    "addr:housenumber":"29",
    "addr:postcode":"sa43 1ls",
    "addr:street":"North Rd",
    "iso:country":"GB",
    "sg:address":"29 North Rd",
    "sg:city":"Cardigan",
    "sg:classifiers":[
        {
            "category":"Communications",
            "type":"Services"
        }
    ],
    "sg:phone":"+44 1239 612484",
    "sg:postcode":"SA43 1LS",
    "sg:province":"Ceredigion",
    "sg:tags":[
        "tv",
        "video",
        "radio"
    ],
    "wof:name":"Glan's Radio & T.V",
    "wof:placetype":"venue"
},
  "geometry": {"coordinates":[-4.6572480202,52.0860671997],"type":"Point"}
}