{
  "type": "Feature",
  "properties": {
    "addr:full":"5 Heol Goffa Llanelli Carmarthenshire SA15 3NB",
    "addr:housenumber":"5",
    "addr:postcode":"sa15 3nb",
    "addr:street":"Heol Goffa;Carmarthenshire",
    "iso:country":"GB",
    "sg:address":"5 Heol Goffa",
    "sg:city":"Llanelli",
    "sg:classifiers":[
        {
            "category":"Shopping",
            "subcategory":"Musical Instruments",
            "type":"Retail Goods"
        }
    ],
    "sg:postcode":"SA15 3NB",
    "sg:province":"Carmarthenshire",
    "wof:name":"Clifton Chris Electronic & Keyboard Services",
    "wof:placetype":"venue"
},
  "geometry": {"coordinates":[-4.1505208015,51.688785553],"type":"Point"}
}