{
  "type": "Feature",
  "properties": {
    "iso:country":"GB",
    "sg:address":"Springfield House, The Deerings",
    "sg:city":"Harpenden",
    "sg:classifiers":[
        {
            "category":"Professional",
            "subcategory":"Employment Agencies",
            "type":"Services"
        },
        {
            "category":"Travel",
            "subcategory":"Travel Agent",
            "type":"Entertainment"
        }
    ],
    "sg:postcode":"AL5 2PF",
    "sg:province":"Hertfordshire",
    "sg:tags":[
        "introduction"
    ],
    "wof:name":"J LACEY",
    "wof:placetype":"venue"
},
  "geometry": {"coordinates":[-0.356739,51.795422],"type":"Point"}
}