{
  "type": "Feature",
  "properties": {
    "iso:country":"GB",
    "sg:address":"Copyhold Lane, Winterbourne Abbas",
    "sg:city":"Dorchester",
    "sg:classifiers":[
        {
            "category":"Professional",
            "type":"Services"
        }
    ],
    "sg:phone":"+44 1305 889206",
    "sg:postcode":"DT2 9LT",
    "sg:province":"Dorset",
    "sg:tags":[
        "caterer"
    ],
    "wof:name":"Whitefriars Catering",
    "wof:placetype":"venue"
},
  "geometry": {"coordinates":[-2.542241,50.714188],"type":"Point"}
}