{
  "type": "Feature",
  "properties": {
    "addr:full":"Allen House Farm, Old Allen Road, Thornton Bradford West Yorkshire BD13 3RY",
    "addr:postcode":"bd13 3ry",
    "addr:street":"Old Allen Road",
    "iso:country":"GB",
    "sg:address":"Allen House Farm, Old Allen Road, Thornton",
    "sg:city":"Bradford",
    "sg:classifiers":[
        {
            "category":"Farming",
            "subcategory":"Dairy Farm",
            "type":"Manufacturing & Wholesale Goods"
        }
    ],
    "sg:phone":"+44 1535 272244",
    "sg:postcode":"BD13 3RY",
    "sg:province":"West Yorkshire",
    "wof:name":"A W Hardy",
    "wof:placetype":"venue"
},
  "geometry": {"coordinates":[-1.8494340181,53.7902336121],"type":"Point"}
}