{
  "type": "Feature",
  "properties": {
    "iso:country":"GB",
    "sg:address":"65 Atlantic Rd",
    "sg:city":"Brixton",
    "sg:classifiers":[
        {
            "category":"Shopping",
            "subcategory":"Musical Instruments",
            "type":"Retail Goods"
        }
    ],
    "sg:phone":"+44 20 7924 9002",
    "sg:postcode":"SW9 8PU",
    "sg:province":"Greater London",
    "sg:tags":[
        "music",
        "sheet"
    ],
    "wof:name":"Hun",
    "wof:placetype":"venue"
},
  "geometry": {"coordinates":[-0.1110669971,51.4613037109],"type":"Point"}
}