{
  "type": "Feature",
  "properties": {
    "addr:full":"7-11 Paraton Building, Ford Road Totnes Devon TQ9 5LQ",
    "addr:housenumber":"7-11",
    "addr:postcode":"tq9 5lq",
    "addr:street":"Ford Road",
    "iso:country":"GB",
    "sg:address":"7-11 Paraton Building, Ford Road",
    "sg:city":"Totnes",
    "sg:classifiers":[
        {
            "category":"Professional",
            "subcategory":"Engineering",
            "type":"Services"
        }
    ],
    "sg:phone":"+44 1803 847735",
    "sg:postcode":"TQ9 5LQ",
    "sg:province":"Devon",
    "sg:tags":[
        "precision",
        "engineer"
    ],
    "wof:name":"South Western Engineering Co. Ltd.",
    "wof:placetype":"venue"
},
  "geometry": {"coordinates":[-3.688092947,50.4341468811],"type":"Point"}
}