{
  "type": "Feature",
  "properties": {
    "addr:full":"Beeching Park, Kelley Bray Callington Cornwall PL17 8EQ",
    "addr:postcode":"pl17 8eq",
    "iso:country":"GB",
    "sg:address":"Beeching Park, Kelley Bray",
    "sg:city":"Callington",
    "sg:classifiers":[
        {
            "category":"Bus Charters",
            "type":"Transportation"
        }
    ],
    "sg:phone":"+44 1579 383432",
    "sg:postcode":"PL17 8EQ",
    "sg:province":"Cornwall",
    "sg:tags":[
        "hire",
        "coach"
    ],
    "wof:name":"Dial A Cab",
    "wof:placetype":"venue"
},
  "geometry": {"coordinates":[-4.3138480186,50.5201072693],"type":"Point"}
}