{
  "type": "Feature",
  "properties": {
    "iso:country":"GB",
    "sg:address":"199 Butcher Hill",
    "sg:city":"Leeds",
    "sg:classifiers":[
        {
            "category":"Shopping",
            "subcategory":"Pets & Pet Supplies",
            "type":"Retail Goods"
        }
    ],
    "sg:phone":"+44 113 278 3199",
    "sg:postcode":"LS16 5BQ",
    "sg:province":"West Yorkshire",
    "sg:tags":[
        "shop"
    ],
    "wof:name":"Four Paws Pet Shop",
    "wof:placetype":"venue"
},
  "geometry": {"coordinates":[-1.604092,53.833248],"type":"Point"}
}