{
  "type": "Feature",
  "properties": {
    "iso:country":"GB",
    "sg:address":"Poulson St",
    "sg:city":"Stoke-on-trent",
    "sg:classifiers":[
        {
            "category":"Professional",
            "subcategory":"Engineering",
            "type":"Services"
        }
    ],
    "sg:postcode":"ST4 1LU",
    "sg:province":"Staffordshire",
    "sg:tags":[
        "civil",
        "engineer"
    ],
    "wof:name":"Cooper Beale & Ross",
    "wof:placetype":"venue"
},
  "geometry": {"coordinates":[-2.1867489815,53.0037536621],"type":"Point"}
}