{
  "type": "Feature",
  "properties": {
    "addr:full":"31 Finlayson Street Fraserburgh Aberdeenshire AB43 9JQ",
    "addr:housenumber":"31",
    "addr:postcode":"ab43 9jq",
    "addr:street":"Finlayson Street",
    "iso:country":"GB",
    "sg:address":"31 Finlayson Street",
    "sg:city":"Fraserburgh",
    "sg:classifiers":[
        {
            "category":"Shopping",
            "subcategory":"Baby Store",
            "type":"Retail Goods"
        }
    ],
    "sg:phone":"+44 1346 510228",
    "sg:postcode":"AB43 9JQ",
    "sg:province":"Aberdeenshire",
    "sg:tags":[
        "nursery",
        "accessory"
    ],
    "wof:name":"Summers Baby Centre",
    "wof:placetype":"venue"
},
  "geometry": {"coordinates":[-2.0143930912,57.692691803],"type":"Point"}
}