{
  "type": "Feature",
  "properties": {
    "addr:full":"18 Almorah Rd Hounslow Greater London TW5 9AD",
    "addr:housenumber":"18",
    "addr:postcode":"tw5 9ad",
    "addr:street":"Almorah Rd",
    "iso:country":"GB",
    "sg:address":"18 Almorah Rd",
    "sg:city":"Hounslow",
    "sg:classifiers":[
        {
            "category":"Wholesale",
            "subcategory":"Toys & Hobbies",
            "type":"Manufacturing & Wholesale Goods"
        }
    ],
    "sg:postcode":"TW5 9AD",
    "sg:province":"Greater London",
    "sg:tags":[
        "balloon",
        "novelty"
    ],
    "wof:name":"Balloon Inspirations",
    "wof:placetype":"venue"
},
  "geometry": {"coordinates":[-0.389192,51.477825],"type":"Point"}
}