{
  "type": "Feature",
  "properties": {
    "addr:full":"Dewfain, Guildford Road, Normandy Guildford Surrey GU3 2AS",
    "addr:postcode":"gu3 2as",
    "addr:street":"Guildford Road",
    "iso:country":"GB",
    "sg:address":"Dewfain, Guildford Road, Normandy",
    "sg:city":"Guildford",
    "sg:classifiers":[
        {
            "category":"Building & Trades",
            "subcategory":"Construction",
            "type":"Services"
        }
    ],
    "sg:postcode":"GU3 2AS",
    "sg:province":"Surrey",
    "sg:tags":[
        "builder"
    ],
    "wof:name":"Angus Property Services",
    "wof:placetype":"venue"
},
  "geometry": {"coordinates":[-0.6669890285,51.2567558289],"type":"Point"}
}