{
  "type": "Feature",
  "properties": {
    "addr:full":"Sir G B Hunter Memorial Hospital, The Green Wallsend Tyne and Wear NE28 7PE",
    "addr:postcode":"ne28 7pe",
    "addr:street":"Sir G B;The",
    "iso:country":"GB",
    "sg:address":"Sir G B Hunter Memorial Hospital, The Green",
    "sg:city":"Wallsend",
    "sg:classifiers":[
        {
            "category":"Organizations",
            "subcategory":"Non-profit Organization",
            "type":"Services"
        }
    ],
    "sg:phone":"+44 191 263 0276",
    "sg:postcode":"NE28 7PE",
    "sg:province":"Tyne and Wear",
    "sg:tags":[
        "organisation",
        "voluntary",
        "charity"
    ],
    "wof:name":"British Lung Foundation (Breathe North Branch)",
    "wof:placetype":"venue"
},
  "geometry": {"coordinates":[-1.533224,54.99128],"type":"Point"}
}