{
  "type": "Feature",
  "properties": {
    "iso:country":"GB",
    "sg:address":"40 Cardiff Rd",
    "sg:city":"Pwllheli",
    "sg:classifiers":[
        {
            "category":"Fast Food",
            "type":"Food & Drink"
        }
    ],
    "sg:phone":"+44 1758 614666",
    "sg:postcode":"LL53 5NT",
    "sg:province":"Gwynedd",
    "sg:tags":[
        "away",
        "take"
    ],
    "wof:name":"West End Baltihouse The",
    "wof:placetype":"venue"
},
  "geometry": {"coordinates":[-4.419724,52.887699],"type":"Point"}
}