{
  "type": "Feature",
  "properties": {
    "addr:full":"19 Alexandra Street Southend-on-sea Essex SS1 1BX",
    "addr:housenumber":"19",
    "addr:postcode":"ss1 1bx",
    "addr:street":"Alexandra Street",
    "iso:country":"GB",
    "sg:address":"19 Alexandra Street",
    "sg:city":"Southend-on-sea",
    "sg:classifiers":[
        {
            "category":"Restaurant",
            "type":"Food & Drink"
        }
    ],
    "sg:phone":"+44 1702 332889",
    "sg:postcode":"SS1 1BX",
    "sg:province":"Essex",
    "wof:name":"Inane Leisure Ltd.",
    "wof:placetype":"venue"
},
  "geometry": {"coordinates":[0.713553,51.535149],"type":"Point"}
}