{
  "type": "Feature",
  "properties": {
    "iso:country":"GB",
    "sg:address":"19 Commercial Road",
    "sg:city":"Hereford",
    "sg:classifiers":[
        {
            "category":"Fast Food",
            "type":"Food & Drink"
        },
        {
            "category":"Restaurant",
            "type":"Food & Drink"
        }
    ],
    "sg:phone":"+44 1432 275302",
    "sg:postcode":"HR1 2BD",
    "sg:province":"Herefordshire",
    "sg:tags":[
        "away",
        "-",
        "take",
        "chinese"
    ],
    "wof:name":"The Palace Chinese Restaurant",
    "wof:placetype":"venue"
},
  "geometry": {"coordinates":[-2.711144,52.058323],"type":"Point"}
}