{
  "type": "Feature",
  "properties": {
    "addr:full":"95 Channel View Rd Eastbourne East Sussex BN22 7LL",
    "addr:housenumber":"95",
    "addr:postcode":"bn22 7ll",
    "addr:street":"Channel View Rd",
    "iso:country":"GB",
    "sg:address":"95 Channel View Rd",
    "sg:city":"Eastbourne",
    "sg:classifiers":[
        {
            "category":"Professional",
            "subcategory":"Lawyer & Legal Services",
            "type":"Services"
        }
    ],
    "sg:phone":"+44 1323 733926",
    "sg:postcode":"BN22 7LL",
    "sg:province":"East Sussex",
    "sg:tags":[
        "advice",
        "counselling"
    ],
    "wof:name":"L Langton",
    "wof:placetype":"venue"
},
  "geometry": {"coordinates":[0.3067759871,50.7792243958],"type":"Point"}
}