{
  "type": "Feature",
  "properties": {
    "addr:full":"Winker Green Mill, Stanningley Road Leeds West Yorkshire LS12 3BB",
    "addr:postcode":"ls12 3bb",
    "addr:street":"Winker Green;Stanningley Road",
    "iso:country":"GB",
    "sg:address":"Winker Green Mill, Stanningley Road",
    "sg:city":"Leeds",
    "sg:classifiers":[
        {
            "category":"Retail",
            "subcategory":"Repair Shop",
            "type":"Services"
        }
    ],
    "sg:phone":"+44 113 279 7329",
    "sg:postcode":"LS12 3BB",
    "sg:province":"West Yorkshire",
    "sg:tags":[
        "upholsterer"
    ],
    "wof:name":"Robert Burns Upholstery",
    "wof:placetype":"venue"
},
  "geometry": {"coordinates":[-1.546587,53.794495],"type":"Point"}
}