{
  "type": "Feature",
  "properties": {
    "addr:full":"52 Newlands Pershore Worcestershire WR10 1BW",
    "addr:housenumber":"52",
    "addr:postcode":"wr10 1bw",
    "addr:street":"Newlands Pershore",
    "iso:country":"GB",
    "sg:address":"52 Newlands",
    "sg:city":"Pershore",
    "sg:classifiers":[
        {
            "category":"Bars & Pubs",
            "type":"Food & Drink"
        }
    ],
    "sg:postcode":"WR10 1BW",
    "sg:province":"Worcestershire",
    "sg:tags":[
        "pubs",
        "inn"
    ],
    "wof:name":"The Talbot Inn",
    "wof:placetype":"venue"
},
  "geometry": {"coordinates":[-2.0806679726,52.1116981506],"type":"Point"}
}