{
  "type": "Feature",
  "properties": {
    "addr:full":"(surgery), 52 Wimpole Rd Colchester Essex CO1 2DL",
    "addr:housenumber":"52",
    "addr:postcode":"co1 2dl",
    "addr:street":"Wimpole Rd",
    "iso:country":"GB",
    "sg:address":"(surgery), 52 Wimpole Rd",
    "sg:city":"Colchester",
    "sg:classifiers":[
        {
            "category":"Health Services",
            "subcategory":"Doctor",
            "type":"Services"
        }
    ],
    "sg:phone":"+44 1206 794794",
    "sg:postcode":"CO1 2DL",
    "sg:province":"Essex",
    "sg:tags":[
        "practitioners"
    ],
    "wof:name":"Drs Ward Jeffries Sherifi Davidson & Claridge",
    "wof:placetype":"venue"
},
  "geometry": {"coordinates":[0.9136999846,51.8810005188],"type":"Point"}
}