{
  "type": "Feature",
  "properties": {
    "iso:country":"GB",
    "sg:address":"13 Honeycroft Hill",
    "sg:city":"Uxbridge",
    "sg:classifiers":[
        {
            "category":"Professional",
            "subcategory":"Secretarial Services",
            "type":"Services"
        }
    ],
    "sg:phone":"+44 1895 251424",
    "sg:postcode":"UB10 9NQ",
    "sg:province":"Greater London",
    "wof:name":"Ace Secretarial Services",
    "wof:placetype":"venue"
},
  "geometry": {"coordinates":[-0.469565,51.547836],"type":"Point"}
}