{
  "type": "Feature",
  "properties": {
    "iso:country":"GB",
    "sg:address":"Grove House, 55 Lowlands Road",
    "sg:city":"Harrow",
    "sg:classifiers":[
        {
            "category":"Professional",
            "subcategory":"Lawyer & Legal Services",
            "type":"Services"
        }
    ],
    "sg:phone":"+44 20 8872 8600",
    "sg:postcode":"HA1 3AP",
    "sg:province":"Greater London",
    "sg:tags":[
        "solicitor"
    ],
    "wof:name":"Thompsons",
    "wof:placetype":"venue"
},
  "geometry": {"coordinates":[-0.338594,51.578876],"type":"Point"}
}