{
  "type": "Feature",
  "properties": {
    "iso:country":"GB",
    "sg:address":"124 Stockton Rd",
    "sg:city":"Newport",
    "sg:classifiers":[
        {
            "category":"Building & Trades",
            "subcategory":"Construction",
            "type":"Services"
        }
    ],
    "sg:phone":"+44 1633 213569",
    "sg:postcode":"NP9 7HG",
    "sg:province":"East Riding of Yorkshire",
    "sg:tags":[
        "decorator",
        "painter"
    ],
    "wof:name":"Poyner W.J. Decorator",
    "wof:placetype":"venue"
},
  "geometry": {"coordinates":[-2.983778,51.602871],"type":"Point"}
}