{
  "type": "Feature",
  "properties": {
    "iso:country":"GB",
    "sg:address":"Unit 3 Old Town Yard, Hud Hey Road Haslingden",
    "sg:city":"Rossendale",
    "sg:classifiers":[
        {
            "category":"Shopping",
            "subcategory":"Shoes",
            "type":"Retail Goods"
        }
    ],
    "sg:postcode":"BB4 5JH",
    "sg:province":"Lancashire",
    "sg:tags":[
        "footwear"
    ],
    "wof:name":"J W Shoes Ltd",
    "wof:placetype":"venue"
},
  "geometry": {"coordinates":[-2.325394,53.704639],"type":"Point"}
}