{
  "type": "Feature",
  "properties": {
    "iso:country":"GB",
    "sg:address":"65 Bridge Street",
    "sg:city":"Evesham",
    "sg:classifiers":[
        {
            "category":"Recreation",
            "subcategory":"Amusement Park",
            "type":"Entertainment"
        }
    ],
    "sg:phone":"+44 1386 446525",
    "sg:postcode":"WR11 4SF",
    "sg:province":"Gloucestershire",
    "sg:tags":[
        "arcade"
    ],
    "wof:name":"Glos Leisure",
    "wof:placetype":"venue"
},
  "geometry": {"coordinates":[-1.943602,52.091755],"type":"Point"}
}