{
  "type": "Feature",
  "properties": {
    "addr:full":"Cornishway West, Galmington Trading Estate Taunton Somerset TA1 5NA",
    "addr:postcode":"ta1 5na",
    "addr:street":"West;Trading Estate",
    "iso:country":"GB",
    "sg:address":"Cornishway West, Galmington Trading Estate",
    "sg:city":"Taunton",
    "sg:classifiers":[
        {
            "category":"Shopping",
            "type":"Retail Goods"
        },
        {
            "category":"Retail",
            "subcategory":"Auto Repair",
            "type":"Services"
        }
    ],
    "sg:phone":"+44 1823 254548",
    "sg:postcode":"TA1 5NA",
    "sg:province":"Somerset",
    "sg:tags":[
        "body",
        "car",
        "part",
        "accessory"
    ],
    "wof:name":"Whites of Taunton Auto Body Repair Centre",
    "wof:placetype":"venue"
},
  "geometry": {"coordinates":[-3.110699,51.01049],"type":"Point"}
}