{
  "type": "Feature",
  "properties": {
    "addr:full":"15 Front Street, Framwellgate Moor Durham Durham DH1 5EJ",
    "addr:housenumber":"15",
    "addr:postcode":"dh1 5ej",
    "addr:street":"Front Street",
    "iso:country":"GB",
    "sg:address":"15 Front Street, Framwellgate Moor",
    "sg:city":"Durham",
    "sg:classifiers":[
        {
            "category":"Shopping",
            "subcategory":"Beauty & Cosmetics",
            "type":"Retail Goods"
        },
        {
            "category":"Personal",
            "subcategory":"Hair Removal",
            "type":"Services"
        }
    ],
    "sg:phone":"+44 191 384 2529",
    "sg:postcode":"DH1 5EJ",
    "sg:province":"Durham",
    "sg:tags":[
        "wig",
        "hairpiece"
    ],
    "wof:name":"Executive Hair Replacements (1927)",
    "wof:placetype":"venue"
},
  "geometry": {"coordinates":[-1.590473,54.7948],"type":"Point"}
}