{
  "type": "Feature",
  "properties": {
    "iso:country":"GB",
    "sg:address":"23 Bircherley Green",
    "sg:city":"Hertford",
    "sg:classifiers":[
        {
            "category":"Professional",
            "subcategory":"Art Services",
            "type":"Services"
        }
    ],
    "sg:postcode":"SG14 1BN",
    "sg:province":"Hertfordshire",
    "sg:tags":[
        "framing"
    ],
    "wof:name":"Crafty Frames",
    "wof:placetype":"venue"
},
  "geometry": {"coordinates":[-0.075873,51.798073],"type":"Point"}
}