{
  "type": "Feature",
  "properties": {
    "addr:full":"205 Station Road, Stechford Birmingham West Midlands B33 8BB",
    "addr:housenumber":"205",
    "addr:postcode":"b33 8bb",
    "addr:street":"Station Road",
    "iso:country":"GB",
    "sg:address":"205 Station Road, Stechford",
    "sg:city":"Birmingham",
    "sg:classifiers":[
        {
            "category":"Cafe",
            "type":"Food & Drink"
        }
    ],
    "sg:postcode":"B33 8BB",
    "sg:province":"West Midlands",
    "sg:tags":[
        "tea",
        "room"
    ],
    "wof:name":"Mikes Diner",
    "wof:placetype":"venue"
},
  "geometry": {"coordinates":[-1.809664011,52.4830055237],"type":"Point"}
}