{
  "type": "Feature",
  "properties": {
    "iso:country":"GB",
    "sg:address":"248 High Street",
    "sg:city":"Jarrow",
    "sg:classifiers":[
        {
            "category":"Bars & Pubs",
            "type":"Food & Drink"
        }
    ],
    "sg:phone":"+44 191 420 0348",
    "sg:postcode":"NE32 3BQ",
    "sg:province":"Tyne and Wear",
    "sg:tags":[
        "pubs",
        "inn"
    ],
    "wof:name":"O'Malleys",
    "wof:placetype":"venue"
},
  "geometry": {"coordinates":[-1.482394,54.981117],"type":"Point"}
}