{
  "type": "Feature",
  "properties": {
    "addr:full":"Tymaen Farm, Llangynwyd Bridgend Bridgend CF34 0EH",
    "addr:postcode":"cf34 0eh",
    "addr:street":"Llangynwyd Bridgend",
    "iso:country":"GB",
    "sg:address":"Tymaen Farm, Llangynwyd",
    "sg:city":"Bridgend",
    "sg:classifiers":[
        {
            "category":"Farming",
            "subcategory":"Livestock Farm",
            "type":"Manufacturing & Wholesale Goods"
        },
        {
            "category":"Farming",
            "subcategory":"Farm",
            "type":"Manufacturing & Wholesale Goods"
        }
    ],
    "sg:phone":"+44 1656 733505",
    "sg:postcode":"CF34 0EH",
    "sg:province":"Bridgend",
    "sg:tags":[
        "mixed",
        "others"
    ],
    "wof:name":"ERENEST JONES",
    "wof:placetype":"venue"
},
  "geometry": {"coordinates":[-3.6282699108,51.5907707214],"type":"Point"}
}