{
  "type": "Feature",
  "properties": {
    "addr:full":"Peascod Street Windsor Berkshire SL4 6JD",
    "addr:postcode":"sl4 6jd",
    "addr:street":"Peascod Street",
    "iso:country":"GB",
    "sg:address":"Peascod Street",
    "sg:city":"Windsor",
    "sg:classifiers":[
        {
            "category":"Food & Beverages",
            "subcategory":"Fruits & Vegetables",
            "type":"Retail Goods"
        }
    ],
    "sg:phone":"+44 1753 866265",
    "sg:postcode":"SL4 6JD",
    "sg:province":"Berkshire",
    "sg:tags":[
        "greengrocer"
    ],
    "wof:name":"Cannavan Ltd.",
    "wof:placetype":"venue"
},
  "geometry": {"coordinates":[-0.608019,51.482361],"type":"Point"}
}