{
  "type": "Feature",
  "properties": {
    "addr:full":"145 Westpole Avenue Barnet Hertfordshire EN4 0BB",
    "addr:housenumber":"145",
    "addr:postcode":"en4 0bb",
    "addr:street":"Westpole Avenue",
    "iso:country":"GB",
    "sg:address":"145 Westpole Avenue",
    "sg:city":"Barnet",
    "sg:classifiers":[
        {
            "category":"Building & Trades",
            "subcategory":"Plumbing",
            "type":"Services"
        }
    ],
    "sg:phone":"+44 20 8440 9850",
    "sg:postcode":"EN4 0BB",
    "sg:province":"Hertfordshire",
    "sg:tags":[
        "heating"
    ],
    "wof:name":"L Libonati",
    "wof:placetype":"venue"
},
  "geometry": {"coordinates":[-0.1450999975,51.649181366],"type":"Point"}
}