{
  "type": "Feature",
  "properties": {
    "iso:country":"GB",
    "sg:address":"Swarland",
    "sg:city":"Morpeth",
    "sg:classifiers":[
        {
            "category":"Recreation",
            "subcategory":"Campground",
            "type":"Entertainment"
        }
    ],
    "sg:phone":"+44 1670 787649",
    "sg:postcode":"NE65 9JW",
    "sg:province":"Northumberland",
    "sg:tags":[
        "caravan",
        "park"
    ],
    "wof:name":"Percy Wood Caravan Park",
    "wof:placetype":"venue"
},
  "geometry": {"coordinates":[-1.7452399731,55.3305282593],"type":"Point"}
}