{
  "type": "Feature",
  "properties": {
    "addr:full":"16 Hartley Way Thatcham Berkshire RG18 4QU",
    "addr:housenumber":"16",
    "addr:postcode":"rg18 4qu",
    "addr:street":"Hartley Way",
    "iso:country":"GB",
    "sg:address":"16 Hartley Way",
    "sg:city":"Thatcham",
    "sg:classifiers":[
        {
            "category":"Wholesale",
            "subcategory":"Office Equipment",
            "type":"Manufacturing & Wholesale Goods"
        }
    ],
    "sg:phone":"+44 1635 827679",
    "sg:postcode":"RG18 4QU",
    "sg:province":"Berkshire",
    "sg:tags":[
        "partition",
        "cubicle"
    ],
    "wof:name":"Kennet Commercial Interiors Ltd",
    "wof:placetype":"venue"
},
  "geometry": {"coordinates":[-1.2520890236,51.4051208496],"type":"Point"}
}