{
  "type": "Feature",
  "properties": {
    "addr:full":"22a Middle Rd, Park Gate Southampton Hampshire SO31 7GH",
    "addr:housenumber":"22a",
    "addr:postcode":"so31 7gh",
    "addr:street":"Middle Rd Park Gate",
    "iso:country":"GB",
    "sg:address":"22a Middle Rd, Park Gate",
    "sg:city":"Southampton",
    "sg:classifiers":[
        {
            "category":"Organizations",
            "subcategory":"Non-profit Organization",
            "type":"Services"
        }
    ],
    "sg:phone":"+44 1489 574477",
    "sg:postcode":"SO31 7GH",
    "sg:province":"Hampshire",
    "sg:tags":[
        "alarm",
        "system"
    ],
    "wof:name":"Harrison Cook Technical Services",
    "wof:placetype":"venue"
},
  "geometry": {"coordinates":[-1.268298,50.872597],"type":"Point"}
}