{
  "type": "Feature",
  "properties": {
    "iso:country":"GB",
    "sg:address":"2 Claremont Crescent, Whitley Lodge Estate",
    "sg:city":"Whitley Bay",
    "sg:classifiers":[
        {
            "category":"Restaurant",
            "type":"Food & Drink"
        }
    ],
    "sg:phone":"+44 191 251 3110",
    "sg:postcode":"NE26 3HL",
    "sg:province":"Northumberland",
    "sg:tags":[
        "-",
        "italian"
    ],
    "wof:name":"Picassos Restaurant",
    "wof:placetype":"venue"
},
  "geometry": {"coordinates":[-1.4622839689,55.0545158386],"type":"Point"}
}