{
  "type": "Feature",
  "properties": {
    "addr:full":"2 Claremont Crescent, Whitley Lodge Estate Whitley Bay Northumberland NE26 3HL",
    "addr:housenumber":"2",
    "addr:postcode":"ne26 3hl",
    "addr:street":"Claremont Crescent;Northumberland",
    "iso:country":"GB",
    "sg:address":"2 Claremont Crescent, Whitley Lodge Estate",
    "sg:city":"Whitley Bay",
    "sg:classifiers":[
        {
            "category":"Restaurant",
            "type":"Food & Drink"
        }
    ],
    "sg:phone":"+44 191 251 3110",
    "sg:postcode":"NE26 3HL",
    "sg:province":"Northumberland",
    "sg:tags":[
        "-",
        "italian"
    ],
    "wof:name":"Picassos Restaurant",
    "wof:placetype":"venue"
},
  "geometry": {"coordinates":[-1.4622839689,55.0545158386],"type":"Point"}
}