{
  "type": "Feature",
  "properties": {
    "iso:country":"GB",
    "sg:address":"4 Elm Gro, Brize Norton",
    "sg:city":"Carterton",
    "sg:classifiers":[
        {
            "category":"Building & Trades",
            "subcategory":"Construction",
            "type":"Services"
        }
    ],
    "sg:postcode":"OX18 3NE",
    "sg:province":"Gloucestershire",
    "sg:tags":[
        "builder"
    ],
    "wof:name":"Patrick A Timms",
    "wof:placetype":"venue"
},
  "geometry": {"coordinates":[-1.5936559439,51.7592811584],"type":"Point"}
}