{
  "type": "Feature",
  "properties": {
    "addr:full":"Unit 7 Waverley Shopping Centre, Lorraine Perkins Edinburgh City of Edinburgh EH1 1BQ",
    "addr:housenumber":"unit 7",
    "addr:postcode":"eh1 1bq",
    "addr:street":"Shopping",
    "iso:country":"GB",
    "sg:address":"Unit 7 Waverley Shopping Centre, Lorraine Perkins",
    "sg:city":"Edinburgh",
    "sg:classifiers":[
        {
            "category":"Shopping",
            "subcategory":"Clothing, Apparel, & Fashions",
            "type":"Retail Goods"
        }
    ],
    "sg:phone":"+44 131 556 2063",
    "sg:postcode":"EH1 1BQ",
    "sg:province":"City of Edinburgh",
    "sg:tags":[
        "shop"
    ],
    "wof:name":"Jeffrey Rogers",
    "wof:placetype":"venue"
},
  "geometry": {"coordinates":[-3.19198,55.952579],"type":"Point"}
}