{
  "type": "Feature",
  "properties": {
    "iso:country":"GB",
    "sg:address":"1a Sadlers La, Tivoli Walk",
    "sg:city":"Cheltenham",
    "sg:classifiers":[
        {
            "category":"Professional",
            "subcategory":"Management & Consulting",
            "type":"Services"
        }
    ],
    "sg:phone":"+44 1242 252611",
    "sg:postcode":"GL50 2UX",
    "sg:province":"Gloucestershire",
    "sg:tags":[
        "marketing",
        "consultant"
    ],
    "wof:name":"Helen Charlton",
    "wof:placetype":"venue"
},
  "geometry": {"coordinates":[-2.087553978,51.8915481567],"type":"Point"}
}