{
  "type": "Feature",
  "properties": {
    "iso:country":"GB",
    "sg:address":"Higham Road, Burton Latimer",
    "sg:city":"Kettering",
    "sg:classifiers":[
        {
            "category":"Freight",
            "type":"Transportation"
        },
        {
            "category":"Train Station",
            "subcategory":"Rail",
            "type":"Transportation"
        }
    ],
    "sg:phone":"+44 1536 726444",
    "sg:postcode":"NN15 5PU",
    "sg:province":"Northamptonshire",
    "sg:tags":[
        "haulage",
        "consultant",
        "road"
    ],
    "wof:name":"Nene Valley Transport Services",
    "wof:placetype":"venue"
},
  "geometry": {"coordinates":[-0.678621,52.360146],"type":"Point"}
}