{
  "type": "Feature",
  "properties": {
    "iso:country":"GB",
    "sg:address":"42 Vyse Street, Hockley",
    "sg:city":"Birmingham",
    "sg:classifiers":[
        {
            "category":"Shopping",
            "subcategory":"Comic Books",
            "type":"Retail Goods"
        }
    ],
    "sg:phone":"+44 121 507 1477",
    "sg:postcode":"B18 6HF",
    "sg:province":"West Midlands",
    "sg:tags":[
        "jeweller"
    ],
    "wof:name":"Barnt Green Jewellers Ltd.",
    "wof:placetype":"venue"
},
  "geometry": {"coordinates":[-1.91261,52.490414],"type":"Point"}
}