{
  "type": "Feature",
  "properties": {
    "addr:full":"Gladstone Road, Kings Heath Industrial Estate Northampton Northamptonshire NN5 7RX",
    "addr:postcode":"nn5 7rx",
    "addr:street":"Gladstone Road;Industrial Estate",
    "iso:country":"GB",
    "sg:address":"Gladstone Road, Kings Heath Industrial Estate",
    "sg:city":"Northampton",
    "sg:classifiers":[
        {
            "category":"Building & Trades",
            "subcategory":"Cleaning & Sanitation",
            "type":"Services"
        }
    ],
    "sg:phone":"+44 1604 583191",
    "sg:postcode":"NN5 7RX",
    "sg:province":"Northamptonshire",
    "sg:tags":[
        "floor",
        "distributor",
        "-",
        "equipment",
        "polishing",
        "mnfrs"
    ],
    "wof:name":"Walter-Broadley Ltd.",
    "wof:placetype":"venue"
},
  "geometry": {"coordinates":[-0.9124289751,52.2502708435],"type":"Point"}
}