{
  "type": "Feature",
  "properties": {
    "addr:full":"109 Upper Tooting Rd Tooting Greater London SW17 7TW",
    "addr:housenumber":"109",
    "addr:postcode":"sw17 7tw",
    "addr:street":"Upper Tooting Rd",
    "iso:country":"GB",
    "sg:address":"109 Upper Tooting Rd",
    "sg:city":"Tooting",
    "sg:classifiers":[
        {
            "category":"Travel",
            "subcategory":"Travel Agent",
            "type":"Entertainment"
        }
    ],
    "sg:phone":"+44 20 8767 3111",
    "sg:postcode":"SW17 7TW",
    "sg:province":"Greater London",
    "wof:name":"Zaks Enterprises",
    "wof:placetype":"venue"
},
  "geometry": {"coordinates":[-0.162435,51.433819],"type":"Point"}
}