{
  "type": "Feature",
  "properties": {
    "iso:country":"GB",
    "sg:address":"5 North Rd",
    "sg:city":"West Kilbride",
    "sg:classifiers":[
        {
            "category":"Personal",
            "type":"Services"
        }
    ],
    "sg:phone":"+44 1294 823184",
    "sg:postcode":"KA23 9AQ",
    "sg:province":"North Ayrshire",
    "sg:tags":[
        "wedding"
    ],
    "wof:name":"Cake Carriage The",
    "wof:placetype":"venue"
},
  "geometry": {"coordinates":[-4.858865,55.697472],"type":"Point"}
}