{
  "type": "Feature",
  "properties": {
    "addr:full":"28 Watling Street London Greater London EC4M 9BR",
    "addr:housenumber":"28",
    "addr:postcode":"ec4m 9br",
    "addr:street":"Watling Street",
    "iso:country":"GB",
    "sg:address":"28 Watling Street",
    "sg:city":"London",
    "sg:classifiers":[
        {
            "category":"Shopping",
            "subcategory":"Pharmacy",
            "type":"Retail Goods"
        }
    ],
    "sg:phone":"+44 20 7489 1682",
    "sg:postcode":"EC4M 9BR",
    "sg:province":"Greater London",
    "sg:tags":[
        "pharmacist",
        "chemist"
    ],
    "wof:name":"Boots the Chemist",
    "wof:placetype":"venue"
},
  "geometry": {"coordinates":[-0.0938140005,51.5129547119],"type":"Point"}
}