{
  "type": "Feature",
  "properties": {
    "addr:full":"70 Stour Street Canterbury Kent CT1 2NW",
    "addr:housenumber":"70",
    "addr:postcode":"ct1 2nw",
    "addr:street":"Stour Street",
    "iso:country":"GB",
    "sg:address":"70 Stour Street",
    "sg:city":"Canterbury",
    "sg:classifiers":[
        {
            "category":"Social Services",
            "type":"Services"
        }
    ],
    "sg:phone":"+44 1227 451741",
    "sg:postcode":"CT1 2NW",
    "sg:province":"Kent",
    "wof:name":"Canterbury Social Services",
    "wof:placetype":"venue"
},
  "geometry": {"coordinates":[1.076199,51.277748],"type":"Point"}
}