{
  "type": "Feature",
  "properties": {
    "addr:full":"111 Swan Street, Sileby Loughborough Leicestershire LE12 7NN",
    "addr:housenumber":"111",
    "addr:postcode":"le12 7nn",
    "addr:street":"Swan Street",
    "iso:country":"GB",
    "sg:address":"111 Swan Street, Sileby",
    "sg:city":"Loughborough",
    "sg:classifiers":[
        {
            "category":"Shopping",
            "subcategory":"News",
            "type":"Retail Goods"
        }
    ],
    "sg:phone":"+44 1509 812429",
    "sg:postcode":"LE12 7NN",
    "sg:province":"Leicestershire",
    "sg:tags":[
        "newsagent"
    ],
    "wof:name":"Forbuoys Ltd.",
    "wof:placetype":"venue"
},
  "geometry": {"coordinates":[-1.104525,52.731468],"type":"Point"}
}