{
  "type": "Feature",
  "properties": {
    "iso:country":"GB",
    "sg:address":"2 Chobham Road, Ottershaw",
    "sg:city":"Chertsey",
    "sg:classifiers":[
        {
            "category":"Real Estate",
            "subcategory":"Real Estate Agent",
            "type":"Services"
        }
    ],
    "sg:phone":"+44 1932 874488",
    "sg:postcode":"KT16 0NL",
    "sg:province":"Surrey",
    "wof:name":"Curchods",
    "wof:placetype":"venue"
},
  "geometry": {"coordinates":[-0.5336890221,51.3651008606],"type":"Point"}
}