{
  "type": "Feature",
  "properties": {
    "addr:full":"38 Bayswater Road Plymouth Devon PL1 5BX",
    "addr:housenumber":"38",
    "addr:postcode":"pl1 5bx",
    "addr:street":"Bayswater Road",
    "iso:country":"GB",
    "sg:address":"38 Bayswater Road",
    "sg:city":"Plymouth",
    "sg:classifiers":[
        {
            "category":"Personal",
            "subcategory":"Beauty Salon",
            "type":"Services"
        },
        {
            "category":"Personal",
            "subcategory":"Barber",
            "type":"Services"
        }
    ],
    "sg:phone":"+44 1752 663496",
    "sg:postcode":"PL1 5BX",
    "sg:province":"Devon",
    "sg:tags":[
        "unisex",
        "hairdresser"
    ],
    "wof:name":"Haircraft",
    "wof:placetype":"venue"
},
  "geometry": {"coordinates":[-4.1468281746,50.3764381409],"type":"Point"}
}