{
  "type": "Feature",
  "properties": {
    "iso:country":"GB",
    "sg:address":"27 Rufford Road, Crossens",
    "sg:city":"Southport",
    "sg:classifiers":[
        {
            "category":"Shopping",
            "subcategory":"Clothing, Apparel, & Fashions",
            "type":"Retail Goods"
        }
    ],
    "sg:phone":"+44 1704 224223",
    "sg:postcode":"PR9 8LE",
    "sg:province":"Lancashire",
    "sg:tags":[
        "dresswear"
    ],
    "wof:name":"Simply the Best",
    "wof:placetype":"venue"
},
  "geometry": {"coordinates":[-2.949756,53.668095],"type":"Point"}
}