{
  "type": "Feature",
  "properties": {
    "addr:full":"312 Lewisham High Street London Greater London SE13 6JZ",
    "addr:housenumber":"312",
    "addr:postcode":"se13 6jz",
    "addr:street":"Lewisham High Street",
    "iso:country":"GB",
    "sg:address":"312 Lewisham High Street",
    "sg:city":"London",
    "sg:classifiers":[
        {
            "category":"Fast Food",
            "type":"Food & Drink"
        }
    ],
    "sg:phone":"+44 20 8690 0880",
    "sg:postcode":"SE13 6JZ",
    "sg:province":"Greater London",
    "sg:tags":[
        "away",
        "take"
    ],
    "wof:name":"Morleys Fried Chicken",
    "wof:placetype":"venue"
},
  "geometry": {"coordinates":[-0.0141960001,51.4569015503],"type":"Point"}
}