{
  "type": "Feature",
  "properties": {
    "addr:full":"33-41 The Pantiles Tunbridge Wells East Sussex TN2 5TE",
    "addr:housenumber":"33-41",
    "addr:postcode":"tn2 5te",
    "addr:street":"The Pantiles",
    "iso:country":"GB",
    "sg:address":"33-41 The Pantiles",
    "sg:city":"Tunbridge Wells",
    "sg:classifiers":[
        {
            "category":"Home & Garden",
            "subcategory":"Household Appliances",
            "type":"Retail Goods"
        },
        {
            "category":"Home & Garden",
            "subcategory":"Kitchen Supply",
            "type":"Retail Goods"
        }
    ],
    "sg:phone":"+44 1892 538915",
    "sg:postcode":"TN2 5TE",
    "sg:province":"East Sussex",
    "sg:tags":[
        "ware",
        "kitchenware"
    ],
    "wof:name":"Trevor Mottram Ltd",
    "wof:placetype":"venue"
},
  "geometry": {"coordinates":[0.2576659918,51.1255950928],"type":"Point"}
}