{
  "type": "Feature",
  "properties": {
    "iso:country":"GB",
    "sg:address":"2 Sherford Road",
    "sg:city":"Taunton",
    "sg:classifiers":[
        {
            "category":"Manufacturing",
            "subcategory":"Furniture",
            "type":"Manufacturing & Wholesale Goods"
        }
    ],
    "sg:phone":"+44 1823 277179",
    "sg:postcode":"TA1 3QY",
    "sg:province":"Somerset",
    "sg:tags":[
        "polishing",
        "french"
    ],
    "wof:name":"M C Nash",
    "wof:placetype":"venue"
},
  "geometry": {"coordinates":[-3.1104090214,51.0043907166],"type":"Point"}
}