{
  "type": "Feature",
  "properties": {
    "iso:country":"GB",
    "sg:address":"Moore Street",
    "sg:city":"Redcar",
    "sg:classifiers":[
        {
            "category":"Education",
            "subcategory":"Dance Studio",
            "type":"Public Place"
        }
    ],
    "sg:phone":"+44 1642 491056",
    "sg:postcode":"TS10 3DX",
    "sg:province":"North Yorkshire",
    "sg:tags":[
        "school",
        "dancing"
    ],
    "wof:name":"Dance Magic",
    "wof:placetype":"venue"
},
  "geometry": {"coordinates":[-1.063629,54.61832],"type":"Point"}
}