{
  "type": "Feature",
  "properties": {
    "iso:country":"GB",
    "sg:address":"15 Castle Road",
    "sg:city":"Kendal",
    "sg:classifiers":[
        {
            "category":"Travel",
            "subcategory":"Hotels & Motels",
            "type":"Entertainment"
        },
        {
            "category":"Travel",
            "subcategory":"Hostel",
            "type":"Entertainment"
        }
    ],
    "sg:phone":"+44 1539 720313",
    "sg:postcode":"LA9 7AU",
    "sg:province":"Cumbria",
    "wof:name":"West Morland Association for Social & Moral Welfare",
    "wof:placetype":"venue"
},
  "geometry": {"coordinates":[-2.734132,54.329178],"type":"Point"}
}