{
  "type": "Feature",
  "properties": {
    "addr:full":"161 Praed Street London Greater London W2 1RL",
    "addr:housenumber":"161",
    "addr:postcode":"w2 1rl",
    "addr:street":"Praed Street",
    "iso:country":"GB",
    "sg:address":"161 Praed Street",
    "sg:city":"London",
    "sg:classifiers":[
        {
            "category":"Shopping",
            "subcategory":"News",
            "type":"Retail Goods"
        }
    ],
    "sg:phone":"+44 20 7706 0324",
    "sg:postcode":"W2 1RL",
    "sg:province":"Greater London",
    "sg:tags":[
        "newsagent"
    ],
    "wof:name":"Paddington Gift Centre",
    "wof:placetype":"venue"
},
  "geometry": {"coordinates":[-0.174695,51.515968],"type":"Point"}
}