{
  "type": "Feature",
  "properties": {
    "addr:full":"Deakins Business Park, Blackburn Rd, Egerton Bolton Lancashire BL7 9RP",
    "addr:postcode":"bl7 9rp",
    "addr:street":"Business Park Blackburn Rd",
    "iso:country":"GB",
    "sg:address":"Deakins Business Park, Blackburn Rd, Egerton",
    "sg:city":"Bolton",
    "sg:classifiers":[
        {
            "category":"Cafe",
            "type":"Food & Drink"
        }
    ],
    "sg:phone":"+44 1204 303968",
    "sg:postcode":"BL7 9RP",
    "sg:province":"Lancashire",
    "sg:tags":[
        "tea",
        "room"
    ],
    "wof:name":"The Butty Box",
    "wof:placetype":"venue"
},
  "geometry": {"coordinates":[-2.435991,53.623886],"type":"Point"}
}