{
  "type": "Feature",
  "properties": {
    "addr:full":"Ardnagowan Shore Road, St Catherines Cairndow Argyll and Bute PA25 8BA",
    "addr:postcode":"pa25 8ba",
    "addr:street":"Ardnagowan Shore Road",
    "iso:country":"GB",
    "sg:address":"Ardnagowan Shore Road, St Catherines",
    "sg:city":"Cairndow",
    "sg:classifiers":[
        {
            "category":"Real Estate",
            "subcategory":"Real Estate Services",
            "type":"Services"
        },
        {
            "category":"Building & Trades",
            "subcategory":"Equipment Rental",
            "type":"Services"
        }
    ],
    "sg:phone":"+44 1369 860766",
    "sg:postcode":"PA25 8BA",
    "sg:province":"Argyll and Bute",
    "sg:tags":[
        "hire",
        "leasing",
        "plant",
        "machinery"
    ],
    "wof:name":"Ian Turner",
    "wof:placetype":"venue"
},
  "geometry": {"coordinates":[-5.0660500526,56.2003593445],"type":"Point"}
}