{
  "type": "Feature",
  "properties": {
    "addr:full":"16 Market Place Stevenage Hertfordshire SG1 1DB",
    "addr:housenumber":"16",
    "addr:postcode":"sg1 1db",
    "addr:street":"Market Place",
    "iso:country":"GB",
    "sg:address":"16 Market Place",
    "sg:city":"Stevenage",
    "sg:classifiers":[
        {
            "category":"Personal",
            "subcategory":"Beauty Salon",
            "type":"Services"
        }
    ],
    "sg:phone":"+44 1438 351723",
    "sg:postcode":"SG1 1DB",
    "sg:province":"Hertfordshire",
    "sg:tags":[
        "unisex",
        "hairdresser"
    ],
    "wof:name":"Daryl B",
    "wof:placetype":"venue"
},
  "geometry": {"coordinates":[-0.2005310059,51.9022064209],"type":"Point"}
}