{
  "type": "Feature",
  "properties": {
    "iso:country":"GB",
    "sg:address":"Unit 36-38 Laurence Indust Est, Eastwoodbury La",
    "sg:city":"Southend On Sea",
    "sg:classifiers":[
        {
            "category":"Home & Garden",
            "subcategory":"Hardware",
            "type":"Retail Goods"
        }
    ],
    "sg:phone":"+44 1702 512516",
    "sg:postcode":"SS2 6RH",
    "sg:province":"Essex",
    "sg:tags":[
        "paint",
        "coating"
    ],
    "wof:name":"Colour Coat",
    "wof:placetype":"venue"
},
  "geometry": {"coordinates":[0.68176,51.567719],"type":"Point"}
}