{
  "type": "Feature",
  "properties": {
    "iso:country":"GB",
    "sg:address":"Swanchuchill Court, 58 Station Rad",
    "sg:city":"Harrow",
    "sg:classifiers":[
        {
            "category":"Shopping",
            "subcategory":"Computers & Home Electronics",
            "type":"Retail Goods"
        }
    ],
    "sg:phone":"+44 20 8515 6000",
    "sg:postcode":"HA2 7SA",
    "sg:province":"Greater London",
    "sg:tags":[
        "sound",
        "equipment",
        "system"
    ],
    "wof:name":"Spectris Uk Ltd",
    "wof:placetype":"venue"
},
  "geometry": {"coordinates":[-0.35925,51.588341],"type":"Point"}
}