{
  "type": "Feature",
  "properties": {
    "iso:country":"GB",
    "sg:address":"21 The Marlowes, St Johns Wood",
    "sg:city":"London",
    "sg:classifiers":[
        {
            "category":"Banks & Credit Unions",
            "subcategory":"Financial Services",
            "type":"Services"
        }
    ],
    "sg:phone":"+44 20 7586 2236",
    "sg:postcode":"NW8 6NB",
    "sg:province":"Greater London",
    "sg:tags":[
        "claim",
        "assessor"
    ],
    "wof:name":"Sidney Balcombe & Co.",
    "wof:placetype":"venue"
},
  "geometry": {"coordinates":[-0.175102,51.538567],"type":"Point"}
}