{
  "type": "Feature",
  "properties": {
    "iso:country":"GB",
    "sg:address":"6 The Parade, Mead Place",
    "sg:city":"Croydon",
    "sg:classifiers":[
        {
            "category":"Personal",
            "subcategory":"Beauty Salon",
            "type":"Services"
        }
    ],
    "sg:phone":"+44 20 8680 4901",
    "sg:postcode":"CR0 3SQ",
    "sg:province":"Surrey",
    "sg:tags":[
        "unisex",
        "hairdresser"
    ],
    "wof:name":"The Hair Shop",
    "wof:placetype":"venue"
},
  "geometry": {"coordinates":[-0.10413,51.378979],"type":"Point"}
}