{
  "type": "Feature",
  "properties": {
    "addr:full":"25 The Square Birmingham Worcestershire B48 7LA",
    "addr:housenumber":"25",
    "addr:postcode":"b48 7la",
    "addr:street":"The Square",
    "iso:country":"GB",
    "sg:address":"25 The Square",
    "sg:city":"Birmingham",
    "sg:classifiers":[
        {
            "category":"Shopping",
            "subcategory":"Department Store",
            "type":"Retail Goods"
        }
    ],
    "sg:phone":"+44 121 445 2865",
    "sg:postcode":"B48 7LA",
    "sg:province":"Worcestershire",
    "wof:name":"Les's",
    "wof:placetype":"venue"
},
  "geometry": {"coordinates":[-1.9595279694,52.3516769409],"type":"Point"}
}