{
  "type": "Feature",
  "properties": {
    "addr:full":"5 Aylsham Way Norwich Norfolk NR3 2RF",
    "addr:housenumber":"5",
    "addr:postcode":"nr3 2rf",
    "addr:street":"Aylsham Way",
    "iso:country":"GB",
    "sg:address":"5 Aylsham Way",
    "sg:city":"Norwich",
    "sg:classifiers":[
        {
            "category":"Home & Garden",
            "subcategory":"Hardware",
            "type":"Retail Goods"
        }
    ],
    "sg:phone":"+44 1603 429295",
    "sg:postcode":"NR3 2RF",
    "sg:province":"Norfolk",
    "sg:tags":[
        "paint"
    ],
    "wof:name":"Dulux Decorator Centre",
    "wof:placetype":"venue"
},
  "geometry": {"coordinates":[1.2872799635,52.6421012878],"type":"Point"}
}