{
  "type": "Feature",
  "properties": {
    "iso:country":"GB",
    "sg:address":"28a Eastgate Street",
    "sg:city":"Stafford",
    "sg:classifiers":[
        {
            "category":"Organizations",
            "subcategory":"Non-profit Organization",
            "type":"Services"
        }
    ],
    "sg:phone":"+44 1785 227590",
    "sg:postcode":"ST16 2LZ",
    "sg:province":"Staffordshire",
    "sg:tags":[
        "organisation",
        "voluntary",
        "charity"
    ],
    "wof:name":"W R V S",
    "wof:placetype":"venue"
},
  "geometry": {"coordinates":[-2.113383,52.806622],"type":"Point"}
}