{
  "type": "Feature",
  "properties": {
    "iso:country":"GB",
    "sg:address":"Siding Road",
    "sg:city":"Fleetwood",
    "sg:classifiers":[
        {
            "category":"Cafe",
            "type":"Food & Drink"
        }
    ],
    "sg:phone":"+44 1253 772703",
    "sg:postcode":"FY7 6NS",
    "sg:province":"Lancashire",
    "sg:tags":[
        "tea",
        "snack",
        "bar",
        "room"
    ],
    "wof:name":"The Works Canteen Cafe",
    "wof:placetype":"venue"
},
  "geometry": {"coordinates":[-3.01745,53.918064],"type":"Point"}
}