{
  "type": "Feature",
  "properties": {
    "addr:full":"1-1a Liverpool Buildings, Liverpool Road Worthing West Sussex BN11 1SY",
    "addr:housenumber":"1-1a",
    "addr:postcode":"bn11 1sy",
    "addr:street":"Liverpool Buildings Liverpool Road",
    "iso:country":"GB",
    "sg:address":"1-1a Liverpool Buildings, Liverpool Road",
    "sg:city":"Worthing",
    "sg:classifiers":[
        {
            "category":"Health Services",
            "subcategory":"Optometrist",
            "type":"Services"
        }
    ],
    "sg:phone":"+44 1903 821015",
    "sg:postcode":"BN11 1SY",
    "sg:province":"West Sussex",
    "sg:tags":[
        "optician"
    ],
    "wof:name":"T H Collison",
    "wof:placetype":"venue"
},
  "geometry": {"coordinates":[-0.372102,50.811691],"type":"Point"}
}