{
  "type": "Feature",
  "properties": {
    "iso:country":"GB",
    "sg:address":"29-31 Baker Street, Gorleston",
    "sg:city":"Great Yarmouth",
    "sg:classifiers":[
        {
            "category":"Professional",
            "type":"Services"
        }
    ],
    "sg:postcode":"NR31 6QT",
    "sg:province":"Norfolk",
    "sg:tags":[
        "interior",
        "furnishers",
        "designer"
    ],
    "wof:name":"Furnishings",
    "wof:placetype":"venue"
},
  "geometry": {"coordinates":[1.728781,52.577568],"type":"Point"}
}