{
  "type": "Feature",
  "properties": {
    "addr:full":"876 High Road London Greater London N12 9RN",
    "addr:housenumber":"876",
    "addr:postcode":"n12 9rn",
    "addr:street":"High Road",
    "iso:country":"GB",
    "sg:address":"876 High Road",
    "sg:city":"London",
    "sg:classifiers":[
        {
            "category":"Food & Beverages",
            "subcategory":"Liquor & Beverages",
            "type":"Retail Goods"
        }
    ],
    "sg:phone":"+44 20 8445 8549",
    "sg:postcode":"N12 9RN",
    "sg:province":"Greater London",
    "sg:tags":[
        "beer",
        "spirit",
        "wines"
    ],
    "wof:name":"Nectar Wines",
    "wof:placetype":"venue"
},
  "geometry": {"coordinates":[-0.1764969975,51.618888855],"type":"Point"}
}