{
  "type": "Feature",
  "properties": {
    "addr:full":"Nethergate Farm, Guestwick Dereham Norfolk NR20 5QR",
    "addr:housenumber":"guestwick",
    "addr:postcode":"nr20 5qr",
    "addr:street":"Nethergate;Dereham Norfolk",
    "iso:country":"GB",
    "sg:address":"Nethergate Farm, Guestwick",
    "sg:city":"Dereham",
    "sg:classifiers":[
        {
            "category":"Professional",
            "type":"Services"
        },
        {
            "category":"Farming",
            "subcategory":"Livestock Farm",
            "type":"Manufacturing & Wholesale Goods"
        }
    ],
    "sg:phone":"+44 1263 861386",
    "sg:postcode":"NR20 5QR",
    "sg:province":"Norfolk",
    "sg:tags":[
        "entertainer",
        "others"
    ],
    "wof:name":"Winston the Singing Farmer",
    "wof:placetype":"venue"
},
  "geometry": {"coordinates":[1.0561709404,52.8009719849],"type":"Point"}
}