{
  "type": "Feature",
  "properties": {
    "iso:country":"GB",
    "sg:address":"Suffolk House, 1 Park Road",
    "sg:city":"Wallington",
    "sg:classifiers":[
        {
            "category":"Shopping",
            "subcategory":"Stationery & Office Supplies",
            "type":"Retail Goods"
        }
    ],
    "sg:phone":"+44 20 8669 9317",
    "sg:postcode":"SM6 7ER",
    "sg:province":"Surrey",
    "sg:tags":[
        "printers'"
    ],
    "wof:name":"Baker's Trade Finishers",
    "wof:placetype":"venue"
},
  "geometry": {"coordinates":[-0.154365,51.375191],"type":"Point"}
}