{
  "type": "Feature",
  "properties": {
    "addr:full":"461a Manchester Road, Stocksbridge Sheffield South Yorkshire S36 1DH",
    "addr:housenumber":"461a",
    "addr:postcode":"s36 1dh",
    "addr:street":"Manchester Road",
    "iso:country":"GB",
    "sg:address":"461a Manchester Road, Stocksbridge",
    "sg:city":"Sheffield",
    "sg:classifiers":[
        {
            "category":"Personal",
            "subcategory":"Beauty Salon",
            "type":"Services"
        },
        {
            "category":"Personal",
            "subcategory":"Barber",
            "type":"Services"
        }
    ],
    "sg:phone":"+44 114 283 0300",
    "sg:postcode":"S36 1DH",
    "sg:province":"South Yorkshire",
    "sg:tags":[
        "unisex",
        "hairdresser"
    ],
    "wof:name":"The Business Hair Salon",
    "wof:placetype":"venue"
},
  "geometry": {"coordinates":[-1.591037035,53.4818229675],"type":"Point"}
}