{
  "type": "Feature",
  "properties": {
    "addr:full":"The Folly, Grendon Underwood Aylesbury Buckinghamshire HP18 0ST",
    "addr:postcode":"hp18 0st",
    "addr:street":"Grendon",
    "iso:country":"GB",
    "sg:address":"The Folly, Grendon Underwood",
    "sg:city":"Aylesbury",
    "sg:classifiers":[
        {
            "category":"Building & Trades",
            "subcategory":"Construction",
            "type":"Services"
        }
    ],
    "sg:postcode":"HP18 0ST",
    "sg:province":"Buckinghamshire",
    "sg:tags":[
        "builder"
    ],
    "wof:name":"B E Portergill",
    "wof:placetype":"venue"
},
  "geometry": {"coordinates":[-1.01463,51.882309],"type":"Point"}
}