{
  "type": "Feature",
  "properties": {
    "addr:full":"Thorney Bank Farm, Jinny Lane, Roughlee Burnley Lancashire BB12 9LL",
    "addr:housenumber":"thorney",
    "addr:postcode":"bb12 9ll",
    "addr:street":"Jinny Lane",
    "iso:country":"GB",
    "sg:address":"Thorney Bank Farm, Jinny Lane, Roughlee",
    "sg:city":"Burnley",
    "sg:classifiers":[
        {
            "category":"Farming",
            "subcategory":"Livestock Farm",
            "type":"Manufacturing & Wholesale Goods"
        }
    ],
    "sg:postcode":"BB12 9LL",
    "sg:province":"Lancashire",
    "sg:tags":[
        "others"
    ],
    "wof:name":"R & D W Palmer",
    "wof:placetype":"venue"
},
  "geometry": {"coordinates":[-2.253271,53.856724],"type":"Point"}
}