{
  "type": "Feature",
  "properties": {
    "iso:country":"GB",
    "sg:address":"Western Regional Office, Chilcombe House, Chilcombe Lane",
    "sg:city":"Winchester",
    "sg:classifiers":[
        {
            "category":"Museum",
            "subcategory":"Art Museum",
            "type":"Entertainment"
        }
    ],
    "sg:phone":"+44 1962 844909",
    "sg:postcode":"SO23 8RD",
    "sg:province":"Hampshire",
    "sg:tags":[
        "gallery"
    ],
    "wof:name":"South Eastern Museums Service",
    "wof:placetype":"venue"
},
  "geometry": {"coordinates":[-1.301487,51.052769],"type":"Point"}
}