{
  "type": "Feature",
  "properties": {
    "addr:full":"5 Euston Avenue Watford Hertfordshire WD18 7SZ",
    "addr:housenumber":"5",
    "addr:postcode":"wd18 7sz",
    "addr:street":"Euston Avenue",
    "iso:country":"GB",
    "sg:address":"5 Euston Avenue",
    "sg:city":"Watford",
    "sg:classifiers":[
        {
            "category":"Personal",
            "subcategory":"Barber",
            "type":"Services"
        }
    ],
    "sg:phone":"+44 1923 239949",
    "sg:postcode":"WD18 7SZ",
    "sg:province":"Hertfordshire",
    "sg:tags":[
        "men's",
        "hairdresser"
    ],
    "wof:name":"Esquire",
    "wof:placetype":"venue"
},
  "geometry": {"coordinates":[-0.4117699862,51.6504173279],"type":"Point"}
}