{
  "type": "Feature",
  "properties": {
    "addr:full":"Unit 45 Charter Pl Watford Hertfordshire WD1 2RX",
    "addr:housenumber":"unit 45",
    "addr:postcode":"wd1 2rx",
    "addr:street":"Charter Pl",
    "iso:country":"GB",
    "sg:address":"Unit 45 Charter Pl",
    "sg:city":"Watford",
    "sg:classifiers":[
        {
            "category":"Shopping",
            "subcategory":"Clothing, Apparel, & Fashions",
            "type":"Retail Goods"
        }
    ],
    "sg:phone":"+44 1923 228022",
    "sg:postcode":"WD1 2RX",
    "sg:province":"Hertfordshire",
    "sg:tags":[
        "menswear"
    ],
    "wof:name":"Nashmo Ltd",
    "wof:placetype":"venue"
},
  "geometry": {"coordinates":[-0.396648,51.657326],"type":"Point"}
}