{
  "type": "Feature",
  "properties": {
    "addr:full":"Centurion Indstl Est Centurion Way, Farington Leyland Lancashire PR25 3GR",
    "addr:postcode":"pr25 3gr",
    "addr:street":"Centurion Way",
    "iso:country":"GB",
    "sg:address":"Centurion Indstl Est Centurion Way, Farington",
    "sg:city":"Leyland",
    "sg:classifiers":[
        {
            "category":"Manufacturing",
            "subcategory":"Building Materials",
            "type":"Manufacturing & Wholesale Goods"
        }
    ],
    "sg:postcode":"PR25 3GR",
    "sg:province":"Lancashire",
    "sg:tags":[
        "concrete",
        "product"
    ],
    "wof:name":"Fisher,Mark,",
    "wof:placetype":"venue"
},
  "geometry": {"coordinates":[-2.68755,53.7075],"type":"Point"}
}