{
  "type": "Feature",
  "properties": {
    "addr:full":"18 Court Drive, Shenstone Lichfield Staffordshire WS14 0JG",
    "addr:housenumber":"18",
    "addr:postcode":"ws14 0jg",
    "addr:street":"Court Drive",
    "iso:country":"GB",
    "sg:address":"18 Court Drive, Shenstone",
    "sg:city":"Lichfield",
    "sg:classifiers":[
        {
            "category":"Manufacturing",
            "subcategory":"Building Materials",
            "type":"Manufacturing & Wholesale Goods"
        }
    ],
    "sg:phone":"+44 1543 480611",
    "sg:postcode":"WS14 0JG",
    "sg:province":"Staffordshire",
    "sg:tags":[
        "stonemason"
    ],
    "wof:name":"Birchall's Masonry & Sculpture Group",
    "wof:placetype":"venue"
},
  "geometry": {"coordinates":[-1.8436470032,52.6339378357],"type":"Point"}
}