{
  "type": "Feature",
  "properties": {
    "addr:full":"Unit 8 Hawksworth Didcot Oxfordshire OX11 7HR",
    "addr:housenumber":"unit 8",
    "addr:postcode":"ox11 7hr",
    "iso:country":"GB",
    "sg:address":"Unit 8 Hawksworth",
    "sg:city":"Didcot",
    "sg:classifiers":[
        {
            "category":"Utilities",
            "subcategory":"Water",
            "type":"Services"
        },
        {
            "category":"Military Area",
            "subcategory":"Air Force Base",
            "type":"Public Place"
        }
    ],
    "sg:phone":"+44 1235 512000",
    "sg:postcode":"OX11 7HR",
    "sg:province":"Oxfordshire",
    "sg:tags":[
        "treatment"
    ],
    "wof:name":"SEVERN TRENT SERVICES LTD",
    "wof:placetype":"venue"
},
  "geometry": {"coordinates":[-1.251686,51.620495],"type":"Point"}
}