{
  "type": "Feature",
  "properties": {
    "addr:full":"222 Station Road Addlestone Surrey KT15 2PH",
    "addr:housenumber":"222",
    "addr:postcode":"kt15 2ph",
    "addr:street":"Station Road",
    "iso:country":"GB",
    "sg:address":"222 Station Road",
    "sg:city":"Addlestone",
    "sg:classifiers":[
        {
            "category":"Building & Trades",
            "subcategory":"Cleaning & Sanitation",
            "type":"Services"
        }
    ],
    "sg:phone":"+44 1932 848802",
    "sg:postcode":"KT15 2PH",
    "sg:province":"Surrey",
    "sg:tags":[
        "commercial"
    ],
    "wof:name":"Germ Busters",
    "wof:placetype":"venue"
},
  "geometry": {"coordinates":[-0.482934,51.373707],"type":"Point"}
}