{
  "type": "Feature",
  "properties": {
    "addr:full":"5 Kemble Parade, High Street Potters Bar Greater London EN6 5AP",
    "addr:housenumber":"5",
    "addr:postcode":"en6 5ap",
    "addr:street":"Kemble Parade High Street",
    "iso:country":"GB",
    "sg:address":"5 Kemble Parade, High Street",
    "sg:city":"Potters Bar",
    "sg:classifiers":[
        {
            "category":"Sports & Exercise",
            "subcategory":"Sports Center",
            "type":"Entertainment"
        }
    ],
    "sg:postcode":"EN6 5AP",
    "sg:province":"Greater London",
    "sg:tags":[
        "shop",
        "good"
    ],
    "wof:name":"Potters Bar Sport & Leisure",
    "wof:placetype":"venue"
},
  "geometry": {"coordinates":[-0.1695539951,51.6916122437],"type":"Point"}
}