{
  "type": "Feature",
  "properties": {
    "iso:country":"GB",
    "sg:address":"Scholars Lane",
    "sg:city":"Stratford-upon-avon",
    "sg:classifiers":[
        {
            "category":"Health Services",
            "subcategory":"Doctor",
            "type":"Services"
        }
    ],
    "sg:phone":"+44 1789 292201",
    "sg:postcode":"CV37 6HE",
    "sg:province":"Warwickshire",
    "sg:tags":[
        "practitioners"
    ],
    "wof:name":"Bridge House Medical Centre",
    "wof:placetype":"venue"
},
  "geometry": {"coordinates":[-1.7084759474,52.1906318665],"type":"Point"}
}