{
  "type": "Feature",
  "properties": {
    "addr:full":"90 Waterfall Lane, Old Hill Warley Cradley Heath West Midlands B64 6RJ",
    "addr:housenumber":"90",
    "addr:postcode":"b64 6rj",
    "addr:street":"Waterfall Lane",
    "iso:country":"GB",
    "sg:address":"90 Waterfall Lane, Old Hill Warley",
    "sg:city":"Cradley Heath",
    "sg:classifiers":[
        {
            "category":"Shopping",
            "subcategory":"Bicycles & Sporting Goods",
            "type":"Retail Goods"
        }
    ],
    "sg:phone":"+44 121 559 3659",
    "sg:postcode":"B64 6RJ",
    "sg:province":"West Midlands",
    "sg:tags":[
        "equipment",
        "leisure"
    ],
    "wof:name":"Comdean Ltd.",
    "wof:placetype":"venue"
},
  "geometry": {"coordinates":[-2.056794,52.471916],"type":"Point"}
}