{
  "type": "Feature",
  "properties": {
    "iso:country":"GB",
    "sg:address":"59 Broadwood Rise, Broadfields",
    "sg:city":"Crawley",
    "sg:classifiers":[
        {
            "category":"Building & Trades",
            "subcategory":"Cleaning & Sanitation",
            "type":"Services"
        }
    ],
    "sg:phone":"+44 1293 523775",
    "sg:postcode":"RH11 9SE",
    "sg:province":"West Sussex",
    "sg:tags":[
        "cleaner",
        "window"
    ],
    "wof:name":"A Perryclean Window Cleaners",
    "wof:placetype":"venue"
},
  "geometry": {"coordinates":[-0.213409,51.094276],"type":"Point"}
}