{
  "type": "Feature",
  "properties": {
    "addr:full":"Picketts Hill, Sleaford, Headley Bordon Hampshire GU35 8TE",
    "addr:postcode":"gu35 8te",
    "addr:street":"Picketts Hill Sleaford",
    "iso:country":"GB",
    "sg:address":"Picketts Hill, Sleaford, Headley",
    "sg:city":"Bordon",
    "sg:classifiers":[
        {
            "category":"Arena",
            "subcategory":"Sports Club",
            "type":"Entertainment"
        }
    ],
    "sg:phone":"+44 1420 488184",
    "sg:postcode":"GU35 8TE",
    "sg:province":"Hampshire",
    "sg:tags":[
        "country"
    ],
    "wof:name":"Lithuanian House Ltd.",
    "wof:placetype":"venue"
},
  "geometry": {"coordinates":[-0.8207899928,51.1196250916],"type":"Point"}
}