{
  "type": "Feature",
  "properties": {
    "iso:country":"GB",
    "sg:address":"37a Silver Street",
    "sg:city":"Bradford-on-avon",
    "sg:classifiers":[
        {
            "category":"Real Estate",
            "subcategory":"Architect",
            "type":"Services"
        }
    ],
    "sg:phone":"+44 1225 866987",
    "sg:postcode":"BA15 1JX",
    "sg:province":"Wiltshire",
    "wof:name":"Slade Smith & Winrow",
    "wof:placetype":"venue"
},
  "geometry": {"coordinates":[-2.250434,51.347748],"type":"Point"}
}