{
  "type": "Feature",
  "properties": {
    "addr:full":"Titford Road, Langley, Warley Oldbury West Midlands B69 4PZ",
    "addr:postcode":"b69 4pz",
    "addr:street":"Titford Road",
    "iso:country":"GB",
    "sg:address":"Titford Road, Langley, Warley",
    "sg:city":"Oldbury",
    "sg:classifiers":[
        {
            "category":"Bars & Pubs",
            "type":"Food & Drink"
        },
        {
            "category":"Community Center",
            "subcategory":"Social",
            "type":"Public Place"
        }
    ],
    "sg:phone":"+44 121 532 0090",
    "sg:postcode":"B69 4PZ",
    "sg:province":"West Midlands",
    "sg:tags":[
        "pubs",
        "house",
        "inn",
        "activity"
    ],
    "wof:name":"The Model",
    "wof:placetype":"venue"
},
  "geometry": {"coordinates":[-2.013909,52.492603],"type":"Point"}
}