{
  "type": "Feature",
  "properties": {
    "iso:country":"GB",
    "sg:address":"203 White Lane",
    "sg:city":"Sheffield",
    "sg:classifiers":[
        {
            "category":"Health Services",
            "subcategory":"Doctor",
            "type":"Services"
        }
    ],
    "sg:phone":"+44 114 239 8125",
    "sg:postcode":"S12 3GG",
    "sg:province":"Derbyshire",
    "sg:tags":[
        "practitioners"
    ],
    "wof:name":"Drs Porteous Pascoe Kell Freudenstein Whitehurst & Jeff",
    "wof:placetype":"venue"
},
  "geometry": {"coordinates":[-1.4265630245,53.3447685242],"type":"Point"}
}