{
  "type": "Feature",
  "properties": {
    "addr:full":"2 Anstice Square Telford Shropshire TF7 5BD",
    "addr:housenumber":"2",
    "addr:postcode":"tf7 5bd",
    "addr:street":"Anstice Square",
    "iso:country":"GB",
    "sg:address":"2 Anstice Square",
    "sg:city":"Telford",
    "sg:classifiers":[
        {
            "category":"Food & Beverages",
            "subcategory":"Supermarket",
            "type":"Retail Goods"
        }
    ],
    "sg:phone":"+44 1952 586068",
    "sg:postcode":"TF7 5BD",
    "sg:province":"Shropshire",
    "wof:name":"Leo's",
    "wof:placetype":"venue"
},
  "geometry": {"coordinates":[-2.4539659023,52.6342277527],"type":"Point"}
}