{
  "type": "Feature",
  "properties": {
    "addr:full":"6 Parkhead Gardens Edinburgh City of Edinburgh EH11 4SQ",
    "addr:housenumber":"6",
    "addr:postcode":"eh11 4sq",
    "addr:street":"Parkhead Gardens",
    "iso:country":"GB",
    "sg:address":"6 Parkhead Gardens",
    "sg:city":"Edinburgh",
    "sg:classifiers":[
        {
            "category":"Food & Beverages",
            "subcategory":"Meat & Fish",
            "type":"Retail Goods"
        }
    ],
    "sg:phone":"+44 131 444 2197",
    "sg:postcode":"EH11 4SQ",
    "sg:province":"City of Edinburgh",
    "sg:tags":[
        "chip"
    ],
    "wof:name":"Sun Rise Fish Bar",
    "wof:placetype":"venue"
},
  "geometry": {"coordinates":[-3.292299,55.924416],"type":"Point"}
}