{
  "type": "Feature",
  "properties": {
    "iso:country":"GB",
    "sg:address":"Unit D2 Cumberland Road Trading Es",
    "sg:city":"Loughborough",
    "sg:classifiers":[
        {
            "category":"Professional",
            "subcategory":"Testing Lab",
            "type":"Services"
        }
    ],
    "sg:phone":"+44 1509 232360",
    "sg:postcode":"LE11 5DF",
    "sg:province":"Leicestershire",
    "sg:tags":[
        "mot"
    ],
    "wof:name":"G N Hogg",
    "wof:placetype":"venue"
},
  "geometry": {"coordinates":[-1.2221590281,52.7741851807],"type":"Point"}
}