{
  "type": "Feature",
  "properties": {
    "addr:full":"342 Wolseley Road, Camels Head Plymouth Devon PL2 2EB",
    "addr:housenumber":"342",
    "addr:postcode":"pl2 2eb",
    "addr:street":"Wolseley Road Camels Head",
    "iso:country":"GB",
    "sg:address":"342 Wolseley Road, Camels Head",
    "sg:city":"Plymouth",
    "sg:classifiers":[
        {
            "category":"Personal",
            "subcategory":"Barber",
            "type":"Services"
        }
    ],
    "sg:phone":"+44 1752 362153",
    "sg:postcode":"PL2 2EB",
    "sg:province":"Devon",
    "sg:tags":[
        "men's",
        "hairdresser"
    ],
    "wof:name":"Tony's Barber Shop",
    "wof:placetype":"venue"
},
  "geometry": {"coordinates":[-4.176047802,50.394153595],"type":"Point"}
}