{
  "type": "Feature",
  "properties": {
    "iso:country":"GB",
    "sg:address":"Burrington Way",
    "sg:city":"Plymouth",
    "sg:classifiers":[
        {
            "category":"Communications",
            "subcategory":"Newspaper",
            "type":"Services"
        }
    ],
    "sg:phone":"+44 1752 704242",
    "sg:postcode":"PL5 3LN",
    "sg:province":"Devon",
    "sg:tags":[
        "magazine"
    ],
    "wof:name":"Sunday Independent",
    "wof:placetype":"venue"
},
  "geometry": {"coordinates":[-4.16182,50.403027],"type":"Point"}
}