{
  "type": "Feature",
  "properties": {
    "addr:full":"11 Bath Road Cheltenham Gloucestershire GL53 7HG",
    "addr:housenumber":"11",
    "addr:postcode":"gl53 7hg",
    "addr:street":"Bath Road",
    "iso:country":"GB",
    "sg:address":"11 Bath Road",
    "sg:city":"Cheltenham",
    "sg:classifiers":[
        {
            "category":"Real Estate",
            "subcategory":"Real Estate Agent",
            "type":"Services"
        }
    ],
    "sg:phone":"+44 1242 253123",
    "sg:postcode":"GL53 7HG",
    "sg:province":"Gloucestershire",
    "wof:name":"Andrews Estate Agents Ltd",
    "wof:placetype":"venue"
},
  "geometry": {"coordinates":[-2.0726010799,51.897731781],"type":"Point"}
}