{
  "type": "Feature",
  "properties": {
    "iso:country":"GB",
    "sg:address":"96 High Street",
    "sg:city":"Witney",
    "sg:classifiers":[
        {
            "category":"Personal",
            "subcategory":"Beauty Salon",
            "type":"Services"
        }
    ],
    "sg:postcode":"OX28 6BW",
    "sg:province":"Oxfordshire",
    "sg:tags":[
        "unisex",
        "hairdresser"
    ],
    "wof:name":"Attendadult Ltd",
    "wof:placetype":"venue"
},
  "geometry": {"coordinates":[-1.482981,51.78828],"type":"Point"}
}