{
  "type": "Feature",
  "properties": {
    "addr:full":"Unit B43 & B54 Birkenhead Market, Grange Rd Birkenhead Merseyside L41 2PF",
    "addr:housenumber":"b54 birkenhead",
    "addr:postcode":"l41 2pf",
    "addr:street":"Market Grange Rd",
    "iso:country":"GB",
    "sg:address":"Unit B43 & B54 Birkenhead Market, Grange Rd",
    "sg:city":"Birkenhead",
    "sg:classifiers":[
        {
            "category":"Shopping",
            "subcategory":"Clothing, Apparel, & Fashions",
            "type":"Retail Goods"
        }
    ],
    "sg:phone":"+44 151 647 5001",
    "sg:postcode":"L41 2PF",
    "sg:province":"Merseyside",
    "sg:tags":[
        "shop"
    ],
    "wof:name":"Anonymous",
    "wof:placetype":"venue"
},
  "geometry": {"coordinates":[-3.0249149799,53.3897590637],"type":"Point"}
}