{
  "type": "Feature",
  "properties": {
    "iso:country":"GB",
    "sg:address":"9 Alandale Road, Sholing",
    "sg:city":"Southampton",
    "sg:classifiers":[
        {
            "category":"Professional",
            "subcategory":"Computer Services",
            "type":"Services"
        }
    ],
    "sg:phone":"+44 23 8032 2212",
    "sg:postcode":"SO19 1DG",
    "sg:province":"Hampshire",
    "sg:tags":[
        "consultant"
    ],
    "wof:name":"Interface (Mjc) Ltd.",
    "wof:placetype":"venue"
},
  "geometry": {"coordinates":[-1.3385269642,50.9041633606],"type":"Point"}
}