{
  "type": "Feature",
  "properties": {
    "addr:full":"4 High Street, Rookery Stoke-on-trent Cheshire ST7 4RL",
    "addr:housenumber":"4",
    "addr:postcode":"st7 4rl",
    "addr:street":"High Street",
    "iso:country":"GB",
    "sg:address":"4 High Street, Rookery",
    "sg:city":"Stoke-on-trent",
    "sg:classifiers":[
        {
            "category":"Food & Beverages",
            "subcategory":"Meat & Fish",
            "type":"Retail Goods"
        }
    ],
    "sg:phone":"+44 1782 776664",
    "sg:postcode":"ST7 4RL",
    "sg:province":"Cheshire",
    "sg:tags":[
        "chip"
    ],
    "wof:name":"Rookery Fish Bar",
    "wof:placetype":"venue"
},
  "geometry": {"coordinates":[-2.208922,53.099541],"type":"Point"}
}