{
  "type": "Feature",
  "properties": {
    "addr:full":"13 The Royals, High Street Southend-on-sea Essex SS1 1DQ",
    "addr:housenumber":"13",
    "addr:postcode":"ss1 1dq",
    "addr:street":"The;High Street",
    "iso:country":"GB",
    "sg:address":"13 The Royals, High Street",
    "sg:city":"Southend-on-sea",
    "sg:classifiers":[
        {
            "category":"Shopping",
            "subcategory":"Shoes",
            "type":"Retail Goods"
        }
    ],
    "sg:phone":"+44 1702 611886",
    "sg:postcode":"SS1 1DQ",
    "sg:province":"Essex",
    "sg:tags":[
        "shop"
    ],
    "wof:name":"Shoe World",
    "wof:placetype":"venue"
},
  "geometry": {"coordinates":[0.70516,51.540386],"type":"Point"}
}