{
  "type": "Feature",
  "properties": {
    "addr:full":"217 London Rd, Rainham Gillingham Kent ME8 7HH",
    "addr:housenumber":"217",
    "addr:postcode":"me8 7hh",
    "addr:street":"London Rd",
    "iso:country":"GB",
    "sg:address":"217 London Rd, Rainham",
    "sg:city":"Gillingham",
    "sg:classifiers":[
        {
            "category":"Building & Trades",
            "subcategory":"Construction",
            "type":"Services"
        }
    ],
    "sg:phone":"+44 1634 230544",
    "sg:postcode":"ME8 7HH",
    "sg:province":"Kent",
    "sg:tags":[
        "decorator",
        "painter"
    ],
    "wof:name":"Holley & Frost",
    "wof:placetype":"venue"
},
  "geometry": {"coordinates":[0.591316998,51.3668556213],"type":"Point"}
}