{
  "type": "Feature",
  "properties": {
    "addr:full":"St Herberts, Oak Avenue, Crays Hill Billericay Essex CM11 2YD",
    "addr:postcode":"cm11 2yd",
    "addr:street":"St Herberts Oak Avenue Crays Hill",
    "iso:country":"GB",
    "sg:address":"St Herberts, Oak Avenue, Crays Hill",
    "sg:city":"Billericay",
    "sg:classifiers":[
        {
            "category":"Personal",
            "type":"Services"
        }
    ],
    "sg:postcode":"CM11 2YD",
    "sg:province":"Essex",
    "sg:tags":[
        "delivery"
    ],
    "wof:name":"R Kearsey Transport",
    "wof:placetype":"venue"
},
  "geometry": {"coordinates":[0.4732249975,51.6032409668],"type":"Point"}
}