{
  "type": "Feature",
  "properties": {
    "addr:full":"Porlock, Collingwood Road, St Margarets At Cliffe Dover Kent CT15 6EX",
    "addr:postcode":"ct15 6ex",
    "addr:street":"Collingwood Road",
    "iso:country":"GB",
    "sg:address":"Porlock, Collingwood Road, St Margarets At Cliffe",
    "sg:city":"Dover",
    "sg:classifiers":[
        {
            "category":"Real Estate",
            "subcategory":"Real Estate Services",
            "type":"Services"
        },
        {
            "category":"Building & Trades",
            "subcategory":"Equipment Rental",
            "type":"Services"
        }
    ],
    "sg:phone":"+44 1304 853289",
    "sg:postcode":"CT15 6EX",
    "sg:province":"Kent",
    "sg:tags":[
        "hire",
        "leasing",
        "plant",
        "machinery"
    ],
    "wof:name":"Rhino Plant Hire Ltd",
    "wof:placetype":"venue"
},
  "geometry": {"coordinates":[1.3819830418,51.1533470154],"type":"Point"}
}