{
  "type": "Feature",
  "properties": {
    "addr:full":"Gainsborough Ho, Bath Rd Cheltenham Gloucestershire GL53 7HJ",
    "addr:postcode":"gl53 7hj",
    "addr:street":"Gainsborough;Bath Rd",
    "iso:country":"GB",
    "sg:address":"Gainsborough Ho, Bath Rd",
    "sg:city":"Cheltenham",
    "sg:classifiers":[
        {
            "category":"Professional",
            "subcategory":"Engineering",
            "type":"Services"
        }
    ],
    "sg:phone":"+44 1242 257799",
    "sg:postcode":"GL53 7HJ",
    "sg:province":"Gloucestershire",
    "wof:name":"Design Installation Services (Environmental) Ltd",
    "wof:placetype":"venue"
},
  "geometry": {"coordinates":[-2.0741,51.89637],"type":"Point"}
}