{
  "type": "Feature",
  "properties": {
    "iso:country":"GB",
    "sg:address":"74 High Street",
    "sg:city":"Gosport",
    "sg:classifiers":[
        {
            "category":"Bars & Pubs",
            "type":"Food & Drink"
        }
    ],
    "sg:phone":"+44 23 9251 1128",
    "sg:postcode":"PO12 1DR",
    "sg:province":"Hampshire",
    "sg:tags":[
        "pubs",
        "inn"
    ],
    "wof:name":"Connolly Leisure Ltd.",
    "wof:placetype":"venue"
},
  "geometry": {"coordinates":[-1.11883,50.794979],"type":"Point"}
}