{
  "type": "Feature",
  "properties": {
    "addr:full":"12 Farm Road Redditch Warwickshire B98 8LB",
    "addr:housenumber":"12",
    "addr:postcode":"b98 8lb",
    "addr:street":"Farm Road",
    "iso:country":"GB",
    "sg:address":"12 Farm Road",
    "sg:city":"Redditch",
    "sg:classifiers":[
        {
            "category":"Social Services",
            "subcategory":"Adult Care",
            "type":"Services"
        }
    ],
    "sg:postcode":"B98 8LB",
    "sg:province":"Warwickshire",
    "sg:tags":[
        "domestic",
        "cleaning"
    ],
    "wof:name":"Noels Cleaning Co",
    "wof:placetype":"venue"
},
  "geometry": {"coordinates":[-1.925229,52.303047],"type":"Point"}
}