{
  "type": "Feature",
  "properties": {
    "iso:country":"GB",
    "sg:address":"Deer Park Rd",
    "sg:city":"Wimbledon",
    "sg:classifiers":[
        {
            "category":"Food & Beverages",
            "subcategory":"Bakery",
            "type":"Retail Goods"
        }
    ],
    "sg:phone":"+44 181 543 6695",
    "sg:postcode":"SW19 3UQ",
    "sg:province":"Greater London",
    "sg:tags":[
        "confectionery"
    ],
    "wof:name":"Rayners Group Bakers",
    "wof:placetype":"venue"
},
  "geometry": {"coordinates":[-0.1898200065,51.406879425],"type":"Point"}
}