{
  "type": "Feature",
  "properties": {
    "iso:country":"GB",
    "sg:address":"380 Ringwood Road",
    "sg:city":"Ferndown",
    "sg:classifiers":[
        {
            "category":"Manufacturing",
            "subcategory":"Petroleum Products",
            "type":"Manufacturing & Wholesale Goods"
        }
    ],
    "sg:phone":"+44 1202 897788",
    "sg:postcode":"BH22 9AU",
    "sg:province":"Dorset",
    "sg:tags":[
        "double",
        "glazing"
    ],
    "wof:name":"D P R Windows",
    "wof:placetype":"venue"
},
  "geometry": {"coordinates":[-1.8910410404,50.8005447388],"type":"Point"}
}