{
  "type": "Feature",
  "properties": {
    "iso:country":"GB",
    "sg:address":"Rear Of 85 Hook Road",
    "sg:city":"Epsom",
    "sg:classifiers":[
        {
            "category":"Retail",
            "subcategory":"Auto Repair",
            "type":"Services"
        }
    ],
    "sg:postcode":"KT19 8TP",
    "sg:province":"Surrey",
    "sg:tags":[
        "modification",
        "garage"
    ],
    "wof:name":"Greenglade Coach Works",
    "wof:placetype":"venue"
},
  "geometry": {"coordinates":[-0.271106,51.333008],"type":"Point"}
}