{
  "type": "Feature",
  "properties": {
    "addr:full":"Rettendon View, Memorial Park Wickford Essex SS11 8HU",
    "addr:postcode":"ss11 8hu",
    "addr:street":"Rettendon;Wickford",
    "iso:country":"GB",
    "sg:address":"Rettendon View, Memorial Park",
    "sg:city":"Wickford",
    "sg:classifiers":[
        {
            "category":"Education",
            "subcategory":"Preschool",
            "type":"Public Place"
        }
    ],
    "sg:phone":"+44 1268 768100",
    "sg:postcode":"SS11 8HU",
    "sg:province":"Essex",
    "sg:tags":[
        "pre-school",
        "playgroups"
    ],
    "wof:name":"Rainbow Pre-School",
    "wof:placetype":"venue"
},
  "geometry": {"coordinates":[0.5345500112,51.6171913147],"type":"Point"}
}