{
  "type": "Feature",
  "properties": {
    "iso:country":"GB",
    "sg:address":"26 Glen Road, Boscombe Manor",
    "sg:city":"Bournemouth",
    "sg:classifiers":[
        {
            "category":"Travel",
            "subcategory":"Hotels & Motels",
            "type":"Entertainment"
        }
    ],
    "sg:postcode":"BH5 1HS",
    "sg:province":"Dorset",
    "wof:name":"Morwena Private Hotel",
    "wof:placetype":"venue"
},
  "geometry": {"coordinates":[-1.836846,50.723755],"type":"Point"}
}