{
  "type": "Feature",
  "properties": {
    "addr:full":"73 Camden Rd Camden Greater London NW1 9EU",
    "addr:housenumber":"73",
    "addr:postcode":"nw1 9eu",
    "addr:street":"Camden Rd",
    "iso:country":"GB",
    "sg:address":"73 Camden Rd",
    "sg:city":"Camden",
    "sg:classifiers":[
        {
            "category":"Food & Beverages",
            "subcategory":"Supermarket",
            "type":"Retail Goods"
        }
    ],
    "sg:phone":"+44 20 7267 7212",
    "sg:postcode":"NW1 9EU",
    "sg:province":"Greater London",
    "wof:name":"Casablanca Supermarket",
    "wof:placetype":"venue"
},
  "geometry": {"coordinates":[-0.1379259974,51.5424880981],"type":"Point"}
}