{
  "type": "Feature",
  "properties": {
    "addr:full":"Church Hill Farm, Church Lane Brockenhurst Hampshire SO42 7UB",
    "addr:postcode":"so42 7ub",
    "addr:street":"Church Hill;Church Lane",
    "iso:country":"GB",
    "sg:address":"Church Hill Farm, Church Lane",
    "sg:city":"Brockenhurst",
    "sg:classifiers":[
        {
            "category":"Utilities",
            "subcategory":"Fuel Oil & Lpg",
            "type":"Services"
        }
    ],
    "sg:phone":"+44 1590 622947",
    "sg:postcode":"SO42 7UB",
    "sg:province":"Hampshire",
    "sg:tags":[
        "distributor"
    ],
    "wof:name":"Upton Oil Co. Ltd.",
    "wof:placetype":"venue"
},
  "geometry": {"coordinates":[-1.570097,50.815281],"type":"Point"}
}