{
  "type": "Feature",
  "properties": {
    "addr:full":"122 Fazeley Street Birmingham West Midlands B5 5RX",
    "addr:housenumber":"122",
    "addr:postcode":"b5 5rx",
    "addr:street":"Fazeley Street",
    "iso:country":"GB",
    "sg:address":"122 Fazeley Street",
    "sg:city":"Birmingham",
    "sg:classifiers":[
        {
            "category":"Home & Garden",
            "subcategory":"Building Materials",
            "type":"Retail Goods"
        },
        {
            "category":"Home & Garden",
            "subcategory":"Carpets & Floor Coverings",
            "type":"Retail Goods"
        }
    ],
    "sg:phone":"+44 121 643 4907",
    "sg:postcode":"B5 5RX",
    "sg:province":"West Midlands",
    "sg:tags":[
        "ready",
        "concrete",
        "mixed",
        "asphalt",
        "macadam"
    ],
    "wof:name":"Lafarge Aggregates Ltd.",
    "wof:placetype":"venue"
},
  "geometry": {"coordinates":[-1.8844599724,52.4790458679],"type":"Point"}
}