{
  "type": "Feature",
  "properties": {
    "addr:full":"12 High Street Shefford Bedfordshire SG17 5DG",
    "addr:housenumber":"12",
    "addr:postcode":"sg17 5dg",
    "addr:street":"High Street",
    "iso:country":"GB",
    "sg:address":"12 High Street",
    "sg:city":"Shefford",
    "sg:classifiers":[
        {
            "category":"Fast Food",
            "type":"Food & Drink"
        }
    ],
    "sg:phone":"+44 1462 814909",
    "sg:postcode":"SG17 5DG",
    "sg:province":"Bedfordshire",
    "sg:tags":[
        "away",
        "take"
    ],
    "wof:name":"Shapla Tandoori Take Away",
    "wof:placetype":"venue"
},
  "geometry": {"coordinates":[-0.3346469998,52.0385742188],"type":"Point"}
}