{
  "type": "Feature",
  "properties": {
    "addr:full":"21 Stephens Street London Greater London W1T 1LN",
    "addr:housenumber":"21",
    "addr:postcode":"w1t 1ln",
    "addr:street":"Stephens Street",
    "iso:country":"GB",
    "sg:address":"21 Stephens Street",
    "sg:city":"London",
    "sg:classifiers":[
        {
            "category":"Professional",
            "subcategory":"Business Services",
            "type":"Services"
        }
    ],
    "sg:phone":"+44 20 7957 8957",
    "sg:postcode":"W1T 1LN",
    "sg:province":"Greater London",
    "sg:tags":[
        "distribution"
    ],
    "wof:name":"Connoisseur Video Ltd.",
    "wof:placetype":"venue"
},
  "geometry": {"coordinates":[-0.13315,51.517555],"type":"Point"}
}