{
  "type": "Feature",
  "properties": {
    "iso:country":"GB",
    "sg:address":"Bantley Jennison, Chapel House, Westmead Drive, Westlea",
    "sg:city":"Swindon",
    "sg:classifiers":[
        {
            "category":"Professional",
            "subcategory":"Advertising",
            "type":"Services"
        }
    ],
    "sg:postcode":"SN5 7UN",
    "sg:province":"Wiltshire",
    "sg:tags":[
        "agency"
    ],
    "wof:name":"Origin Design Consultants Ltd",
    "wof:placetype":"venue"
},
  "geometry": {"coordinates":[-1.819489,51.563339],"type":"Point"}
}