{
  "type": "Feature",
  "properties": {
    "iso:country":"GB",
    "sg:address":"40 Village Road",
    "sg:city":"Enfield",
    "sg:classifiers":[
        {
            "category":"Education",
            "subcategory":"Special Training",
            "type":"Public Place"
        }
    ],
    "sg:phone":"+44 20 8360 4118",
    "sg:postcode":"EN1 2EN",
    "sg:province":"Greater London",
    "sg:tags":[
        "school",
        "language"
    ],
    "wof:name":"English & Cultural Studies Centres",
    "wof:placetype":"venue"
},
  "geometry": {"coordinates":[-0.075801,51.643345],"type":"Point"}
}