{
  "type": "Feature",
  "properties": {
    "addr:full":"3 Kingly Street London Greater London W1R 5LF",
    "addr:housenumber":"3",
    "addr:postcode":"w1r 5lf",
    "addr:street":"Kingly Street",
    "iso:country":"GB",
    "sg:address":"3 Kingly Street",
    "sg:city":"London",
    "sg:classifiers":[
        {
            "category":"Bars & Pubs",
            "type":"Food & Drink"
        }
    ],
    "sg:phone":"+44 20 7439 1007",
    "sg:postcode":"W1R 5LF",
    "sg:province":"Greater London",
    "sg:tags":[
        "pubs",
        "inn"
    ],
    "wof:name":"Two Floors",
    "wof:placetype":"venue"
},
  "geometry": {"coordinates":[-0.138495,51.512184],"type":"Point"}
}