{
  "type": "Feature",
  "properties": {
    "addr:full":"Dorking Road, Warnham Horsham West Sussex RH12 3RZ",
    "addr:postcode":"rh12 3rz",
    "addr:street":"Dorking Road",
    "iso:country":"GB",
    "sg:address":"Dorking Road, Warnham",
    "sg:city":"Horsham",
    "sg:classifiers":[
        {
            "category":"Professional",
            "type":"Services"
        }
    ],
    "sg:phone":"+44 1403 255699",
    "sg:postcode":"RH12 3RZ",
    "sg:province":"West Sussex",
    "sg:tags":[
        "auctioneer"
    ],
    "wof:name":"Denhams",
    "wof:placetype":"venue"
},
  "geometry": {"coordinates":[-0.348049,51.089951],"type":"Point"}
}