{
  "type": "Feature",
  "properties": {
    "iso:country":"GB",
    "sg:address":"Colshaw Close East, Pilkington Rd, Radcliffe",
    "sg:city":"Manchester",
    "sg:classifiers":[
        {
            "category":"Bars & Pubs",
            "type":"Food & Drink"
        }
    ],
    "sg:phone":"+44 161 724 5937",
    "sg:postcode":"M26 3PE",
    "sg:province":"Greater Manchester",
    "sg:tags":[
        "pubs",
        "inn"
    ],
    "wof:name":"The Boro",
    "wof:placetype":"venue"
},
  "geometry": {"coordinates":[-2.3397090435,53.5669021606],"type":"Point"}
}