{
  "type": "Feature",
  "properties": {
    "addr:full":"30 Keats Place Dundee Dundee City DD3 6QH",
    "addr:housenumber":"30",
    "addr:postcode":"dd3 6qh",
    "addr:street":"Keats Place",
    "iso:country":"GB",
    "sg:address":"30 Keats Place",
    "sg:city":"Dundee",
    "sg:classifiers":[
        {
            "category":"Banks & Credit Unions",
            "subcategory":"Bank",
            "type":"Services"
        },
        {
            "category":"Professional",
            "subcategory":"Business Services",
            "type":"Services"
        }
    ],
    "sg:phone":"+44 1382 812612",
    "sg:postcode":"DD3 6QH",
    "sg:province":"Dundee City",
    "sg:tags":[
        "stocktaking",
        "inventory"
    ],
    "wof:name":"M A Kidd",
    "wof:placetype":"venue"
},
  "geometry": {"coordinates":[-2.984246,56.472416],"type":"Point"}
}