{
  "type": "Feature",
  "properties": {
    "iso:country":"GB",
    "sg:address":"1 South Street",
    "sg:city":"Rochford",
    "sg:classifiers":[
        {
            "category":"Professional",
            "subcategory":"Computer Services",
            "type":"Services"
        }
    ],
    "sg:phone":"+44 1621 776006",
    "sg:postcode":"SS4 1BL",
    "sg:province":"Essex",
    "sg:tags":[
        "consultant"
    ],
    "wof:name":"Woods Computer Consultants Ltd.",
    "wof:placetype":"venue"
},
  "geometry": {"coordinates":[0.707379,51.581863],"type":"Point"}
}