{
  "type": "Feature",
  "properties": {
    "iso:country":"GB",
    "sg:address":"Culliford Cre",
    "sg:city":"Poole",
    "sg:classifiers":[
        {
            "category":"Community Center",
            "type":"Public Place"
        }
    ],
    "sg:phone":"+44 1202 600897",
    "sg:postcode":"BH17 9DW",
    "sg:province":"Dorset",
    "sg:tags":[
        "centre"
    ],
    "wof:name":"Creekmoor Community Centre & Social Club",
    "wof:placetype":"venue"
},
  "geometry": {"coordinates":[-1.966312,50.753689],"type":"Point"}
}