{
  "type": "Feature",
  "properties": {
    "addr:full":"8 Angel St Worcester Worcestershire WR1 3QT",
    "addr:housenumber":"8",
    "addr:postcode":"wr1 3qt",
    "addr:street":"Angel St",
    "iso:country":"GB",
    "sg:address":"8 Angel St",
    "sg:city":"Worcester",
    "sg:classifiers":[
        {
            "category":"Food & Beverages",
            "subcategory":"Supermarket",
            "type":"Retail Goods"
        }
    ],
    "sg:phone":"+44 1905 23585",
    "sg:postcode":"WR1 3QT",
    "sg:province":"Worcestershire",
    "wof:name":"Kwik Save Foodstores",
    "wof:placetype":"venue"
},
  "geometry": {"coordinates":[-2.2218410969,52.1937828064],"type":"Point"}
}