{
  "type": "Feature",
  "properties": {
    "addr:full":"39 Charles Street Sheffield South Yorkshire S1 2HU",
    "addr:housenumber":"39",
    "addr:postcode":"s1 2hu",
    "addr:street":"Charles Street",
    "iso:country":"GB",
    "sg:address":"39 Charles Street",
    "sg:city":"Sheffield",
    "sg:classifiers":[
        {
            "category":"Banks & Credit Unions",
            "subcategory":"Bank",
            "type":"Services"
        }
    ],
    "sg:phone":"+44 114 276 9823",
    "sg:postcode":"S1 2HU",
    "sg:province":"South Yorkshire",
    "wof:name":"H F C Bank Plc",
    "wof:placetype":"venue"
},
  "geometry": {"coordinates":[-1.470949,53.37888],"type":"Point"}
}