{
  "type": "Feature",
  "properties": {
    "addr:full":"85 Welling High Street Welling Kent DA16 1TY",
    "addr:housenumber":"85",
    "addr:postcode":"da16 1ty",
    "addr:street":"Welling High Street",
    "iso:country":"GB",
    "sg:address":"85 Welling High Street",
    "sg:city":"Welling",
    "sg:classifiers":[
        {
            "category":"Professional",
            "subcategory":"Management & Consulting",
            "type":"Services"
        }
    ],
    "sg:postcode":"DA16 1TY",
    "sg:province":"Kent",
    "sg:tags":[
        "consultant",
        "business"
    ],
    "wof:name":"Longman Consultancy Services",
    "wof:placetype":"venue"
},
  "geometry": {"coordinates":[0.1100379974,51.4622650146],"type":"Point"}
}