{
  "type": "Feature",
  "properties": {
    "addr:full":"Verndale, Leys Hill Frome Somerset BA11 2JZ",
    "addr:postcode":"ba11 2jz",
    "addr:street":"Verndale Leys Hill",
    "iso:country":"GB",
    "sg:address":"Verndale, Leys Hill",
    "sg:city":"Frome",
    "sg:classifiers":[
        {
            "category":"Building & Trades",
            "subcategory":"Construction",
            "type":"Services"
        }
    ],
    "sg:postcode":"BA11 2JZ",
    "sg:province":"Somerset",
    "sg:tags":[
        "builder"
    ],
    "wof:name":"Ken Vernon Property Repairs",
    "wof:placetype":"venue"
},
  "geometry": {"coordinates":[-2.3188068867,51.2285575867],"type":"Point"}
}