{
  "type": "Feature",
  "properties": {
    "addr:full":"Unit 15b, Grn Hill Mills, Grange Road Batley West Yorkshire WF17 6LH",
    "addr:housenumber":"unit 15b",
    "addr:postcode":"wf17 6lh",
    "addr:street":"Grn Hill Mills Grange Road",
    "iso:country":"GB",
    "sg:address":"Unit 15b, Grn Hill Mills, Grange Road",
    "sg:city":"Batley",
    "sg:classifiers":[
        {
            "category":"Home & Garden",
            "subcategory":"Furniture",
            "type":"Retail Goods"
        }
    ],
    "sg:postcode":"WF17 6LH",
    "sg:province":"West Yorkshire",
    "wof:name":"Lawrence Joinery Pine Specialists",
    "wof:placetype":"venue"
},
  "geometry": {"coordinates":[-1.654499054,53.7264213562],"type":"Point"}
}