{
  "type": "Feature",
  "properties": {
    "iso:country":"GB",
    "sg:address":"32 Preston Way",
    "sg:city":"Barnsley",
    "sg:classifiers":[
        {
            "category":"Taxi",
            "type":"Transportation"
        },
        {
            "category":"Military Area",
            "subcategory":"Air Force Base",
            "type":"Public Place"
        }
    ],
    "sg:phone":"+44 1226 285583",
    "sg:postcode":"S71 2RU",
    "sg:province":"South Yorkshire",
    "sg:tags":[
        "hire",
        "private"
    ],
    "wof:name":"K G Private Hire",
    "wof:placetype":"venue"
},
  "geometry": {"coordinates":[-1.44647,53.572929],"type":"Point"}
}