{
  "type": "Feature",
  "properties": {
    "addr:full":"Heol-y-gyfraith, Talbot Green Pontyclun Bridgend CF72 8AJ",
    "addr:postcode":"cf72 8aj",
    "iso:country":"GB",
    "sg:address":"Heol-y-gyfraith, Talbot Green",
    "sg:city":"Pontyclun",
    "sg:classifiers":[
        {
            "category":"Education",
            "subcategory":"Library",
            "type":"Public Place"
        }
    ],
    "sg:phone":"+44 1443 237844",
    "sg:postcode":"CF72 8AJ",
    "sg:province":"Bridgend",
    "sg:tags":[
        "book"
    ],
    "wof:name":"Talbot Green Public Library",
    "wof:placetype":"venue"
},
  "geometry": {"coordinates":[-3.3839199543,51.5333976746],"type":"Point"}
}