{
  "type": "Feature",
  "properties": {
    "iso:country":"GB",
    "sg:address":"West Way House",
    "sg:city":"Oxford",
    "sg:classifiers":[
        {
            "category":"Professional",
            "subcategory":"Lawyer & Legal Services",
            "type":"Services"
        }
    ],
    "sg:postcode":"OX2 9LL",
    "sg:province":"Oxfordshire",
    "sg:tags":[
        "solicitor"
    ],
    "wof:name":"Neil Morgan",
    "wof:placetype":"venue"
},
  "geometry": {"coordinates":[-1.3106490374,51.7462997437],"type":"Point"}
}