{
  "type": "Feature",
  "properties": {
    "iso:country":"GB",
    "sg:address":"Whitehouse Farm, Green Lane, Seagrave",
    "sg:city":"Loughborough",
    "sg:classifiers":[
        {
            "category":"Farming",
            "subcategory":"Livestock Farm",
            "type":"Manufacturing & Wholesale Goods"
        }
    ],
    "sg:phone":"+44 1509 812569",
    "sg:postcode":"LE12 7LU",
    "sg:province":"Leicestershire",
    "sg:tags":[
        "others"
    ],
    "wof:name":"John James",
    "wof:placetype":"venue"
},
  "geometry": {"coordinates":[-1.085974,52.751884],"type":"Point"}
}