{
  "type": "Feature",
  "properties": {
    "addr:full":"13 High Street Bracknell Berkshire RG12 1DL",
    "addr:housenumber":"13",
    "addr:postcode":"rg12 1dl",
    "addr:street":"High Street",
    "iso:country":"GB",
    "sg:address":"13 High Street",
    "sg:city":"Bracknell",
    "sg:classifiers":[
        {
            "category":"Utilities",
            "subcategory":"Water",
            "type":"Services"
        }
    ],
    "sg:phone":"+44 1344 302100",
    "sg:postcode":"RG12 1DL",
    "sg:province":"Berkshire",
    "wof:name":"Mid Southern Water Plc",
    "wof:placetype":"venue"
},
  "geometry": {"coordinates":[-0.751599,51.416882],"type":"Point"}
}