{
  "type": "Feature",
  "properties": {
    "addr:full":"32 Kintillo Place, Bridge Of Earn Perth Perth and Kinross PH2 9AP",
    "addr:housenumber":"32",
    "addr:postcode":"ph2 9ap",
    "addr:street":"Kintillo Place",
    "iso:country":"GB",
    "sg:address":"32 Kintillo Place, Bridge Of Earn",
    "sg:city":"Perth",
    "sg:classifiers":[
        {
            "category":"Professional",
            "subcategory":"Art Services",
            "type":"Services"
        },
        {
            "category":"Building & Trades",
            "subcategory":"Construction",
            "type":"Services"
        }
    ],
    "sg:phone":"+44 1738 812958",
    "sg:postcode":"PH2 9AP",
    "sg:province":"Perth and Kinross",
    "sg:tags":[
        "decorator",
        "painter"
    ],
    "wof:name":"W Gilmore & Son",
    "wof:placetype":"venue"
},
  "geometry": {"coordinates":[-3.403580904,56.3424682617],"type":"Point"}
}