{
  "type": "Feature",
  "properties": {
    "addr:full":"28 Galston Road Luton Bedfordshire LU3 3JZ",
    "addr:housenumber":"28",
    "addr:postcode":"lu3 3jz",
    "addr:street":"Galston Road",
    "iso:country":"GB",
    "sg:address":"28 Galston Road",
    "sg:city":"Luton",
    "sg:classifiers":[
        {
            "category":"Building & Trades",
            "subcategory":"Construction",
            "type":"Services"
        }
    ],
    "sg:phone":"+44 1582 599425",
    "sg:postcode":"LU3 3JZ",
    "sg:province":"Bedfordshire",
    "sg:tags":[
        "decorator",
        "painter"
    ],
    "wof:name":"Colin H Short",
    "wof:placetype":"venue"
},
  "geometry": {"coordinates":[-0.462952,51.922112],"type":"Point"}
}