{
  "type": "Feature",
  "properties": {
    "addr:full":"Room 0820 King's Reach Tower, Stamford Street London Greater London SE1 9LS",
    "addr:housenumber":"0820",
    "addr:postcode":"se1 9ls",
    "addr:street":"King'S Reach;Stamford Street",
    "iso:country":"GB",
    "sg:address":"Room 0820 King's Reach Tower, Stamford Street",
    "sg:city":"London",
    "sg:classifiers":[
        {
            "category":"Communications",
            "subcategory":"Newspaper",
            "type":"Services"
        }
    ],
    "sg:postcode":"SE1 9LS",
    "sg:province":"Greater London",
    "sg:tags":[
        "magazine"
    ],
    "wof:name":"Country Life Ltd.",
    "wof:placetype":"venue"
},
  "geometry": {"coordinates":[-0.10674,51.507339],"type":"Point"}
}