{
  "type": "Feature",
  "properties": {
    "addr:full":"Unit 13-14 Hastingwood Trad Est, Harbet Rd London Greater London N18 3LP",
    "addr:housenumber":"unit 13-14",
    "addr:postcode":"n18 3lp",
    "addr:street":"Trad Est Harbet Rd",
    "iso:country":"GB",
    "sg:address":"Unit 13-14 Hastingwood Trad Est, Harbet Rd",
    "sg:city":"London",
    "sg:classifiers":[
        {
            "category":"Retail",
            "subcategory":"Auto Repair",
            "type":"Services"
        }
    ],
    "sg:postcode":"N18 3LP",
    "sg:province":"Greater London",
    "sg:tags":[
        "car",
        "upholsterer"
    ],
    "wof:name":"Extreme Trim",
    "wof:placetype":"venue"
},
  "geometry": {"coordinates":[-0.0423,51.61327],"type":"Point"}
}