{
  "type": "Feature",
  "properties": {
    "addr:full":"Shipley Village Horsham West Sussex RH13 8PH",
    "addr:postcode":"rh13 8ph",
    "iso:country":"GB",
    "sg:address":"Shipley Village",
    "sg:city":"Horsham",
    "sg:classifiers":[
        {
            "category":"Place Of Worship",
            "type":"Public Place"
        }
    ],
    "sg:phone":"+44 1403 741238",
    "sg:postcode":"RH13 8PH",
    "sg:province":"West Sussex",
    "wof:name":"St Mary C Of E Church",
    "wof:placetype":"venue"
},
  "geometry": {"coordinates":[-0.3775910139,50.9875831604],"type":"Point"}
}