{
  "type": "Feature",
  "properties": {
    "iso:country":"GB",
    "sg:address":"Stanley Street, Ynysddu",
    "sg:city":"Newport",
    "sg:classifiers":[
        {
            "category":"Health Services",
            "subcategory":"Clinic",
            "type":"Services"
        }
    ],
    "sg:phone":"+44 1495 200218",
    "sg:postcode":"NP1 7HF",
    "sg:province":"East Riding of Yorkshire",
    "sg:tags":[
        "private"
    ],
    "wof:name":"Cwmfelinfach Clinic",
    "wof:placetype":"venue"
},
  "geometry": {"coordinates":[-3.18475,51.624722],"type":"Point"}
}