{
  "type": "Feature",
  "properties": {
    "iso:country":"GB",
    "sg:address":"150 Stockton La",
    "sg:city":"York",
    "sg:classifiers":[
        {
            "category":"Professional",
            "subcategory":"Lawyer & Legal Services",
            "type":"Services"
        }
    ],
    "sg:postcode":"YO31 1BX",
    "sg:province":"North Yorkshire",
    "wof:name":"Paul Topham Associates Ltd",
    "wof:placetype":"venue"
},
  "geometry": {"coordinates":[-1.0542160273,53.9708023071],"type":"Point"}
}