{
  "type": "Feature",
  "properties": {
    "addr:full":"150 Stockton La York North Yorkshire YO31 1BX",
    "addr:housenumber":"150",
    "addr:postcode":"yo31 1bx",
    "addr:street":"Stockton La York",
    "iso:country":"GB",
    "sg:address":"150 Stockton La",
    "sg:city":"York",
    "sg:classifiers":[
        {
            "category":"Professional",
            "subcategory":"Lawyer & Legal Services",
            "type":"Services"
        }
    ],
    "sg:postcode":"YO31 1BX",
    "sg:province":"North Yorkshire",
    "wof:name":"Paul Topham Associates Ltd",
    "wof:placetype":"venue"
},
  "geometry": {"coordinates":[-1.0542160273,53.9708023071],"type":"Point"}
}