{
  "type": "Feature",
  "properties": {
    "addr:full":"12 Windmill Rd, Headington Oxford Oxfordshire OX3 7BX",
    "addr:housenumber":"12",
    "addr:postcode":"ox3 7bx",
    "addr:street":"Windmill Rd",
    "iso:country":"GB",
    "sg:address":"12 Windmill Rd, Headington",
    "sg:city":"Oxford",
    "sg:classifiers":[
        {
            "category":"Building & Trades",
            "subcategory":"Construction",
            "type":"Services"
        }
    ],
    "sg:phone":"+44 1865 763629",
    "sg:postcode":"OX3 7BX",
    "sg:province":"Oxfordshire",
    "sg:tags":[
        "paint",
        "household",
        "spraying"
    ],
    "wof:name":"Headington Arts & Graphics",
    "wof:placetype":"venue"
},
  "geometry": {"coordinates":[-1.20984,51.75853],"type":"Point"}
}