{
  "type": "Feature",
  "properties": {
    "iso:country":"GB",
    "sg:address":"5th Floor Crawford House, Precinct Centre, Oxford Road",
    "sg:city":"Manchester",
    "sg:classifiers":[
        {
            "category":"Professional",
            "subcategory":"Employment Agencies",
            "type":"Services"
        }
    ],
    "sg:phone":"+44 161 272 8611",
    "sg:postcode":"M13 9GH",
    "sg:province":"Greater Manchester",
    "sg:tags":[
        "consultant"
    ],
    "wof:name":"Csu Higher Education Careers Services Unit",
    "wof:placetype":"venue"
},
  "geometry": {"coordinates":[-2.2357299328,53.4686012268],"type":"Point"}
}