{
  "type": "Feature",
  "properties": {
    "addr:full":"355 Ladbroke Grove London Greater London W10 5AA",
    "addr:housenumber":"355",
    "addr:postcode":"w10 5aa",
    "addr:street":"Ladbroke Grove",
    "iso:country":"GB",
    "sg:address":"355 Ladbroke Grove",
    "sg:city":"London",
    "sg:classifiers":[
        {
            "category":"Bars & Pubs",
            "type":"Food & Drink"
        }
    ],
    "sg:phone":"+44 20 8969 2053",
    "sg:postcode":"W10 5AA",
    "sg:province":"Greater London",
    "sg:tags":[
        "pubs",
        "inn"
    ],
    "wof:name":"The Admiral Blake",
    "wof:placetype":"venue"
},
  "geometry": {"coordinates":[-0.2141949981,51.5242347717],"type":"Point"}
}