{
  "type": "Feature",
  "properties": {
    "iso:country":"GB",
    "sg:address":"152 Hanover Rd",
    "sg:city":"Willesden",
    "sg:classifiers":[
        {
            "category":"Travel",
            "subcategory":"Travel Agent",
            "type":"Entertainment"
        }
    ],
    "sg:phone":"+44 7771 562201",
    "sg:postcode":"NW10 3DP",
    "sg:province":"Greater London",
    "wof:name":"Link Agency",
    "wof:placetype":"venue"
},
  "geometry": {"coordinates":[-0.2248460054,51.5419578552],"type":"Point"}
}