{
  "type": "Feature",
  "properties": {
    "iso:country":"GB",
    "sg:address":"37 Wilbury Crescent",
    "sg:city":"Hove",
    "sg:classifiers":[
        {
            "category":"Building & Trades",
            "subcategory":"Construction",
            "type":"Services"
        }
    ],
    "sg:postcode":"BN3 6FJ",
    "sg:province":"East Sussex",
    "sg:tags":[
        "roofing"
    ],
    "wof:name":"Jay Bros Roofing Contractors",
    "wof:placetype":"venue"
},
  "geometry": {"coordinates":[-0.1611,50.834068],"type":"Point"}
}