{
  "type": "Feature",
  "properties": {
    "addr:full":"King Street, Melton Mowbray Leicester Leicestershire LE13 1XA",
    "addr:postcode":"le13 1xa",
    "addr:street":"King Street",
    "iso:country":"GB",
    "sg:address":"King Street, Melton Mowbray",
    "sg:city":"Leicester",
    "sg:classifiers":[
        {
            "category":"Bars & Pubs",
            "type":"Food & Drink"
        }
    ],
    "sg:postcode":"LE13 1XA",
    "sg:province":"Leicestershire",
    "sg:tags":[
        "pubs",
        "inn"
    ],
    "wof:name":"D Jordan",
    "wof:placetype":"venue"
},
  "geometry": {"coordinates":[-0.8842290044,52.7655410767],"type":"Point"}
}