{
  "type": "Feature",
  "properties": {
    "addr:full":"10 Darley Rd, Old Trafford Manchester Cheshire M16 0DQ",
    "addr:housenumber":"10",
    "addr:postcode":"m16 0dq",
    "addr:street":"Darley Rd",
    "iso:country":"GB",
    "sg:address":"10 Darley Rd, Old Trafford",
    "sg:city":"Manchester",
    "sg:classifiers":[
        {
            "category":"Health Services",
            "subcategory":"Health Practitioner",
            "type":"Services"
        }
    ],
    "sg:phone":"+44 161 860 6716",
    "sg:postcode":"M16 0DQ",
    "sg:province":"Cheshire",
    "sg:tags":[
        "homoeopathic"
    ],
    "wof:name":"Annette Bond B.Sc M.N.W.C.H R.S.Hom",
    "wof:placetype":"venue"
},
  "geometry": {"coordinates":[-2.272236,53.451775],"type":"Point"}
}