{
  "type": "Feature",
  "properties": {
    "addr:full":"67 High St, Brotton Saltburn-by-the-sea North Yorkshire TS12 2PP",
    "addr:housenumber":"67",
    "addr:postcode":"ts12 2pp",
    "addr:street":"High St;Saltburn-By-The-Sea",
    "iso:country":"GB",
    "sg:address":"67 High St, Brotton",
    "sg:city":"Saltburn-by-the-sea",
    "sg:classifiers":[
        {
            "category":"Bars & Pubs",
            "type":"Food & Drink"
        }
    ],
    "sg:postcode":"TS12 2PP",
    "sg:province":"North Yorkshire",
    "sg:tags":[
        "pubs",
        "inn"
    ],
    "wof:name":"Queens Arms Hotel",
    "wof:placetype":"venue"
},
  "geometry": {"coordinates":[-0.9358580112,54.5687332153],"type":"Point"}
}