{
  "type": "Feature",
  "properties": {
    "iso:country":"GB",
    "sg:address":"Gandria, Endwood Drive",
    "sg:city":"Sutton Coldfield",
    "sg:classifiers":[
        {
            "category":"Professional",
            "subcategory":"Accounting & Tax Preparation",
            "type":"Services"
        }
    ],
    "sg:phone":"+44 121 353 1327",
    "sg:postcode":"B74 3AJ",
    "sg:province":"Staffordshire",
    "sg:tags":[
        "accountant"
    ],
    "wof:name":"Sandhu",
    "wof:placetype":"venue"
},
  "geometry": {"coordinates":[-1.8627799749,52.5936889648],"type":"Point"}
}