{
  "type": "Feature",
  "properties": {
    "addr:full":"Hewenden Lodge, Collingworth Road, Collingworth Bradford West Yorkshire BD13 5BP",
    "addr:postcode":"bd13 5bp",
    "addr:street":"Collingworth Road Collingworth Bradford West",
    "iso:country":"GB",
    "sg:address":"Hewenden Lodge, Collingworth Road, Collingworth",
    "sg:city":"Bradford",
    "sg:classifiers":[
        {
            "category":"Shopping",
            "subcategory":"Stationery & Office Supplies",
            "type":"Retail Goods"
        },
        {
            "category":"Professional",
            "subcategory":"Business Services",
            "type":"Services"
        }
    ],
    "sg:phone":"+44 1535 271456",
    "sg:postcode":"BD13 5BP",
    "sg:province":"West Yorkshire",
    "sg:tags":[
        "equipment",
        "planning",
        "design"
    ],
    "wof:name":"Bradford Typewriter & Furniture Co. Ltd.",
    "wof:placetype":"venue"
},
  "geometry": {"coordinates":[-1.88399,53.820412],"type":"Point"}
}