{
  "type": "Feature",
  "properties": {
    "addr:full":"6 Whitesands Dumfries Dumfries and Galloway DG1 2RR",
    "addr:housenumber":"6",
    "addr:postcode":"dg1 2rr",
    "addr:street":"Whitesands",
    "iso:country":"GB",
    "sg:address":"6 Whitesands",
    "sg:city":"Dumfries",
    "sg:classifiers":[
        {
            "category":"Government",
            "subcategory":"Police Station",
            "type":"Public Place"
        }
    ],
    "sg:phone":"+44 1387 269211",
    "sg:postcode":"DG1 2RR",
    "sg:province":"Dumfries and Galloway",
    "sg:tags":[
        "force",
        "officer",
        "sheriff"
    ],
    "wof:name":"Stirling Park",
    "wof:placetype":"venue"
},
  "geometry": {"coordinates":[-3.612439,55.067261],"type":"Point"}
}