{
  "type": "Feature",
  "properties": {
    "iso:country":"GB",
    "sg:address":"2 Oak Lodge Lane",
    "sg:city":"Westerham",
    "sg:classifiers":[
        {
            "category":"Personal",
            "type":"Services"
        }
    ],
    "sg:phone":"+44 1959 562934",
    "sg:postcode":"TN16 1DS",
    "sg:province":"Kent",
    "sg:tags":[
        "wedding"
    ],
    "wof:name":"Minster Carriage Co",
    "wof:placetype":"venue"
},
  "geometry": {"coordinates":[0.0754309967,51.2724990845],"type":"Point"}
}