{
  "type": "Feature",
  "properties": {
    "iso:country":"GB",
    "sg:address":"25-27 South Dr, Wavertree",
    "sg:city":"Liverpool",
    "sg:classifiers":[
        {
            "category":"Organizations",
            "subcategory":"Community Association",
            "type":"Services"
        },
        {
            "category":"Organizations",
            "subcategory":"Non-profit Organization",
            "type":"Services"
        }
    ],
    "sg:phone":"+44 151 733 6150",
    "sg:postcode":"L15 8JJ",
    "sg:province":"Merseyside",
    "sg:tags":[
        "society",
        "organisation",
        "charity",
        "housing",
        "charitable"
    ],
    "wof:name":"Abbeyfield Liverpool Society Ltd (The)",
    "wof:placetype":"venue"
},
  "geometry": {"coordinates":[-2.917272,53.400379],"type":"Point"}
}