{
  "type": "Feature",
  "properties": {
    "iso:country":"GB",
    "sg:address":"Green Gables, Tidmarsh La, Pangbourne",
    "sg:city":"Reading",
    "sg:classifiers":[
        {
            "category":"Home & Garden",
            "subcategory":"Home Furnishings",
            "type":"Retail Goods"
        }
    ],
    "sg:postcode":"RG8 8HG",
    "sg:province":"Berkshire",
    "sg:tags":[
        "furnishers",
        "planner",
        "bedroom"
    ],
    "wof:name":"Klarence Kitchens",
    "wof:placetype":"venue"
},
  "geometry": {"coordinates":[-1.086989,51.468849],"type":"Point"}
}