{
  "type": "Feature",
  "properties": {
    "iso:country":"GB",
    "sg:address":"Erleigh Road",
    "sg:city":"Reading",
    "sg:classifiers":[
        {
            "category":"Education",
            "subcategory":"School",
            "type":"Public Place"
        }
    ],
    "sg:phone":"+44 118 901 5600",
    "sg:postcode":"RG1 5LW",
    "sg:province":"Berkshire",
    "sg:tags":[
        "college"
    ],
    "wof:name":"Reading School",
    "wof:placetype":"venue"
},
  "geometry": {"coordinates":[-0.9557440281,51.4508132935],"type":"Point"}
}