{
  "type": "Feature",
  "properties": {
    "addr:full":"Classic Ho, Sutton Rd Walsall West Midlands WS5 3AQ",
    "addr:postcode":"ws5 3aq",
    "addr:street":"Sutton Rd",
    "iso:country":"GB",
    "sg:address":"Classic Ho, Sutton Rd",
    "sg:city":"Walsall",
    "sg:classifiers":[
        {
            "category":"Professional",
            "type":"Services"
        }
    ],
    "sg:phone":"+44 1922 453435",
    "sg:postcode":"WS5 3AQ",
    "sg:province":"West Midlands",
    "sg:tags":[
        "caterer"
    ],
    "wof:name":"Sandwich House",
    "wof:placetype":"venue"
},
  "geometry": {"coordinates":[-1.9579000473,52.5785102844],"type":"Point"}
}