{
  "type": "Feature",
  "properties": {
    "iso:country":"GB",
    "sg:address":"Courthouse Street",
    "sg:city":"Otley",
    "sg:classifiers":[
        {
            "category":"Building & Trades",
            "subcategory":"Construction",
            "type":"Services"
        }
    ],
    "sg:phone":"+44 1943 467945",
    "sg:postcode":"LS21 1AQ",
    "sg:province":"North Yorkshire",
    "sg:tags":[
        "contractor"
    ],
    "wof:name":"Lotus Construction Ltd.",
    "wof:placetype":"venue"
},
  "geometry": {"coordinates":[-1.6902569532,53.9064331055],"type":"Point"}
}