{
  "type": "Feature",
  "properties": {
    "addr:full":"20 St Andrews Road Sheffield Derbyshire S11 9AL",
    "addr:housenumber":"20",
    "addr:postcode":"s11 9al",
    "addr:street":"St Andrews Road",
    "iso:country":"GB",
    "sg:address":"20 St Andrews Road",
    "sg:city":"Sheffield",
    "sg:classifiers":[
        {
            "category":"Health Services",
            "subcategory":"Doctor",
            "type":"Services"
        },
        {
            "category":"Health Services",
            "subcategory":"Clinic",
            "type":"Services"
        }
    ],
    "sg:phone":"+44 114 255 5937",
    "sg:postcode":"S11 9AL",
    "sg:province":"Derbyshire",
    "sg:tags":[
        "nh",
        "practitioners"
    ],
    "wof:name":"The Hollies Medical Centre",
    "wof:placetype":"venue"
},
  "geometry": {"coordinates":[-1.4948010445,53.3634872437],"type":"Point"}
}