{
  "type": "Feature",
  "properties": {
    "addr:full":"72 Goldhawk Road London Greater London W12 8HA",
    "addr:housenumber":"72",
    "addr:postcode":"w12 8ha",
    "addr:street":"Goldhawk Road",
    "iso:country":"GB",
    "sg:address":"72 Goldhawk Road",
    "sg:city":"London",
    "sg:classifiers":[
        {
            "category":"Food & Beverages",
            "subcategory":"Meat & Fish",
            "type":"Retail Goods"
        }
    ],
    "sg:phone":"+44 20 8743 0353",
    "sg:postcode":"W12 8HA",
    "sg:province":"Greater London",
    "sg:tags":[
        "butcher"
    ],
    "wof:name":"The Irish Meat Market",
    "wof:placetype":"venue"
},
  "geometry": {"coordinates":[-0.2281389982,51.5022544861],"type":"Point"}
}