{
  "type": "Feature",
  "properties": {
    "iso:country":"GB",
    "sg:address":"67 Smallbrook, Queensway",
    "sg:city":"Birmingham",
    "sg:classifiers":[
        {
            "category":"Shopping",
            "subcategory":"Computers & Home Electronics",
            "type":"Retail Goods"
        }
    ],
    "sg:phone":"+44 121 631 2675",
    "sg:postcode":"B5 4HX",
    "sg:province":"West Midlands",
    "sg:tags":[
        "hi-fi",
        "centre"
    ],
    "wof:name":"Superfi Birmingham",
    "wof:placetype":"venue"
},
  "geometry": {"coordinates":[-1.896959,52.47604],"type":"Point"}
}