{
  "type": "Feature",
  "properties": {
    "addr:full":"44-48 Buckland Road Leicester Leicestershire LE5 0NT",
    "addr:housenumber":"44-48",
    "addr:postcode":"le5 0nt",
    "addr:street":"Buckland Road",
    "iso:country":"GB",
    "sg:address":"44-48 Buckland Road",
    "sg:city":"Leicester",
    "sg:classifiers":[
        {
            "category":"Building & Trades",
            "subcategory":"Construction",
            "type":"Services"
        }
    ],
    "sg:phone":"+44 116 274 1146",
    "sg:postcode":"LE5 0NT",
    "sg:province":"Leicestershire",
    "sg:tags":[
        "window",
        "replacement"
    ],
    "wof:name":"Kingfisher Replacement Windows Ltd.",
    "wof:placetype":"venue"
},
  "geometry": {"coordinates":[-1.1033660173,52.6472969055],"type":"Point"}
}