{
  "type": "Feature",
  "properties": {
    "addr:full":"108 High Street Street Somerset BA16 0EW",
    "addr:housenumber":"108",
    "addr:postcode":"ba16 0ew",
    "addr:street":"High Street Street",
    "iso:country":"GB",
    "sg:address":"108 High Street",
    "sg:city":"Street",
    "sg:classifiers":[
        {
            "category":"Shopping",
            "subcategory":"Shoes",
            "type":"Retail Goods"
        }
    ],
    "sg:phone":"+44 1458 442730",
    "sg:postcode":"BA16 0EW",
    "sg:province":"Somerset",
    "sg:tags":[
        "shop",
        "retailer",
        "footwear"
    ],
    "wof:name":"CEBO LTD",
    "wof:placetype":"venue"
},
  "geometry": {"coordinates":[-2.741546,51.126064],"type":"Point"}
}