{
  "type": "Feature",
  "properties": {
    "addr:full":"26 West Street Glasgow Glasgow City G5 8LP",
    "addr:housenumber":"26",
    "addr:postcode":"g5 8lp",
    "addr:street":"West Street",
    "iso:country":"GB",
    "sg:address":"26 West Street",
    "sg:city":"Glasgow",
    "sg:classifiers":[
        {
            "category":"Wholesale",
            "subcategory":"Non-durable Goods",
            "type":"Manufacturing & Wholesale Goods"
        }
    ],
    "sg:phone":"+44 141 429 2531",
    "sg:postcode":"G5 8LP",
    "sg:province":"Glasgow City",
    "sg:tags":[
        "carry",
        "cash"
    ],
    "wof:name":"Bonnypack (Scotland) Ltd.",
    "wof:placetype":"venue"
},
  "geometry": {"coordinates":[-4.264528,55.854252],"type":"Point"}
}