{
  "type": "Feature",
  "properties": {
    "addr:full":"10 Bridge St Maidenhead Berkshire SL6 8BJ",
    "addr:housenumber":"10",
    "addr:postcode":"sl6 8bj",
    "addr:street":"Bridge St",
    "iso:country":"GB",
    "sg:address":"10 Bridge St",
    "sg:city":"Maidenhead",
    "sg:classifiers":[
        {
            "category":"Professional",
            "subcategory":"Business Services",
            "type":"Services"
        }
    ],
    "sg:postcode":"SL6 8BJ",
    "sg:province":"Berkshire",
    "sg:tags":[
        "bookmaker"
    ],
    "wof:name":"Wilkes,Ken,",
    "wof:placetype":"venue"
},
  "geometry": {"coordinates":[-0.7159320116,51.5231361389],"type":"Point"}
}