{
  "type": "Feature",
  "properties": {
    "iso:country":"GB",
    "sg:address":"Bron Seiont",
    "sg:city":"Caernarfon",
    "sg:classifiers":[
        {
            "category":"Health Services",
            "subcategory":"Doctor",
            "type":"Services"
        },
        {
            "category":"Health Services",
            "subcategory":"Clinic",
            "type":"Services"
        }
    ],
    "sg:phone":"+44 1286 673144",
    "sg:postcode":"LL55 2PH",
    "sg:province":"Gwynedd",
    "sg:tags":[
        "nh",
        "practitioners"
    ],
    "wof:name":"J G Evans & Partners",
    "wof:placetype":"venue"
},
  "geometry": {"coordinates":[-4.258709,53.132877],"type":"Point"}
}