{
  "type": "Feature",
  "properties": {
    "iso:country":"GB",
    "sg:address":"Medart Place, Cross Keys",
    "sg:city":"Newport",
    "sg:classifiers":[
        {
            "category":"Autos & Motor Vehicles",
            "subcategory":"Auto Supplies",
            "type":"Retail Goods"
        },
        {
            "category":"Taxi",
            "type":"Transportation"
        }
    ],
    "sg:phone":"+44 1495 272032",
    "sg:postcode":"NP11 7DJ",
    "sg:province":"Blaenau Gwent",
    "sg:tags":[
        "mini",
        "tyre",
        "cab"
    ],
    "wof:name":"Crosskeys Tyres",
    "wof:placetype":"venue"
},
  "geometry": {"coordinates":[-3.1182539463,51.6174659729],"type":"Point"}
}