{
  "type": "Feature",
  "properties": {
    "addr:full":"46 High Street Wanstead London Greater London E11 2RJ",
    "addr:housenumber":"46",
    "addr:postcode":"e11 2rj",
    "addr:street":"High Street",
    "iso:country":"GB",
    "sg:address":"46 High Street Wanstead",
    "sg:city":"London",
    "sg:classifiers":[
        {
            "category":"Food & Beverages",
            "subcategory":"Candy",
            "type":"Retail Goods"
        }
    ],
    "sg:phone":"+44 20 8989 4443",
    "sg:postcode":"E11 2RJ",
    "sg:province":"Greater London",
    "sg:tags":[
        "confectioner"
    ],
    "wof:name":"Truffles Luxury Chocolate",
    "wof:placetype":"venue"
},
  "geometry": {"coordinates":[0.0273000002,51.5760993958],"type":"Point"}
}