{
  "type": "Feature",
  "properties": {
    "addr:full":"17 Reculver Walk Maidstone Kent ME15 8QE",
    "addr:housenumber":"17",
    "addr:postcode":"me15 8qe",
    "addr:street":"Reculver Walk",
    "iso:country":"GB",
    "sg:address":"17 Reculver Walk",
    "sg:city":"Maidstone",
    "sg:classifiers":[
        {
            "category":"Building & Trades",
            "subcategory":"Construction",
            "type":"Services"
        }
    ],
    "sg:phone":"+44 1622 755255",
    "sg:postcode":"ME15 8QE",
    "sg:province":"Kent",
    "sg:tags":[
        "roofing",
        "contracting"
    ],
    "wof:name":"Robert D Latter",
    "wof:placetype":"venue"
},
  "geometry": {"coordinates":[0.5586,51.252331],"type":"Point"}
}