{
  "type": "Feature",
  "properties": {
    "iso:country":"GB",
    "sg:address":"397 Brighton Road",
    "sg:city":"Lancing",
    "sg:classifiers":[
        {
            "category":"Food & Beverages",
            "subcategory":"Fruits & Vegetables",
            "type":"Retail Goods"
        }
    ],
    "sg:postcode":"BN15 8JX",
    "sg:province":"West Sussex",
    "sg:tags":[
        "greengrocer"
    ],
    "wof:name":"The Fruit Shop",
    "wof:placetype":"venue"
},
  "geometry": {"coordinates":[-0.297399,50.825699],"type":"Point"}
}