{
  "type": "Feature",
  "properties": {
    "iso:country":"GB",
    "sg:address":"5th Floor 1 Nine Elms Lane, Market Towers",
    "sg:city":"London",
    "sg:classifiers":[
        {
            "category":"Professional",
            "subcategory":"Business Services",
            "type":"Services"
        }
    ],
    "sg:phone":"+44 20 7720 8544",
    "sg:postcode":"SW8 5NQ",
    "sg:province":"Greater London",
    "sg:tags":[
        "import",
        "export",
        "agent"
    ],
    "wof:name":"Westfalia Marketing (U K) Ltd.",
    "wof:placetype":"venue"
},
  "geometry": {"coordinates":[-0.127335,51.484436],"type":"Point"}
}