{
  "type": "Feature",
  "properties": {
    "iso:country":"GB",
    "sg:address":"Lupin Works, Worcester Road",
    "sg:city":"Kidderminster",
    "sg:classifiers":[
        {
            "category":"Building & Trades",
            "subcategory":"Construction",
            "type":"Services"
        }
    ],
    "sg:phone":"+44 1562 60561",
    "sg:postcode":"DY10 1JR",
    "sg:province":"Staffordshire",
    "sg:tags":[
        "glazier"
    ],
    "wof:name":"West Midland Glass Centre Ltd",
    "wof:placetype":"venue"
},
  "geometry": {"coordinates":[-2.245782,52.38596],"type":"Point"}
}