{
  "type": "Feature",
  "properties": {
    "iso:country":"GB",
    "sg:address":"16 North Street",
    "sg:city":"Spennymoor",
    "sg:classifiers":[
        {
            "category":"Professional",
            "subcategory":"Engineering",
            "type":"Services"
        }
    ],
    "sg:phone":"+44 1388 816308",
    "sg:postcode":"DL16 6AW",
    "sg:province":"Durham",
    "sg:tags":[
        "contractor",
        "electrical",
        "engineer"
    ],
    "wof:name":"M G Electrics",
    "wof:placetype":"venue"
},
  "geometry": {"coordinates":[-1.604477,54.700226],"type":"Point"}
}