{
  "type": "Feature",
  "properties": {
    "addr:full":"Avery Way, Allhallows Rochester Kent ME3 9QW",
    "addr:postcode":"me3 9qw",
    "addr:street":"Avery Way",
    "iso:country":"GB",
    "sg:address":"Avery Way, Allhallows",
    "sg:city":"Rochester",
    "sg:classifiers":[
        {
            "category":"Bars & Pubs",
            "type":"Food & Drink"
        }
    ],
    "sg:phone":"+44 1634 272198",
    "sg:postcode":"ME3 9QW",
    "sg:province":"Kent",
    "sg:tags":[
        "pubs",
        "inn"
    ],
    "wof:name":"The British Pilot",
    "wof:placetype":"venue"
},
  "geometry": {"coordinates":[0.6414880157,51.4679298401],"type":"Point"}
}