{
  "type": "Feature",
  "properties": {
    "addr:full":"5 Periwood Lane, Millhouses Sheffield Derbyshire S8 0HP",
    "addr:housenumber":"5",
    "addr:postcode":"s8 0hp",
    "addr:street":"Periwood Lane",
    "iso:country":"GB",
    "sg:address":"5 Periwood Lane, Millhouses",
    "sg:city":"Sheffield",
    "sg:classifiers":[
        {
            "category":"Building & Trades",
            "subcategory":"Plumbing",
            "type":"Services"
        }
    ],
    "sg:postcode":"S8 0HP",
    "sg:province":"Derbyshire",
    "sg:tags":[
        "central",
        "heating"
    ],
    "wof:name":"I J Flint Heating & Plumbing",
    "wof:placetype":"venue"
},
  "geometry": {"coordinates":[-1.488897,53.344456],"type":"Point"}
}