{
  "type": "Feature",
  "properties": {
    "iso:country":"GB",
    "sg:address":"95 The Broadway",
    "sg:city":"London",
    "sg:classifiers":[
        {
            "category":"Shopping",
            "subcategory":"News",
            "type":"Retail Goods"
        }
    ],
    "sg:phone":"+44 20 8542 7627",
    "sg:postcode":"SW19 1QG",
    "sg:province":"Greater London",
    "sg:tags":[
        "newsagent"
    ],
    "wof:name":"Pats Candy Shop",
    "wof:placetype":"venue"
},
  "geometry": {"coordinates":[-0.19926,51.419285],"type":"Point"}
}