{
  "type": "Feature",
  "properties": {
    "iso:country":"GB",
    "sg:address":"Dog Lane, Bodymoor Heath",
    "sg:city":"Sutton Coldfield",
    "sg:classifiers":[
        {
            "category":"Bars & Pubs",
            "type":"Food & Drink"
        },
        {
            "category":"Community Center",
            "subcategory":"Social",
            "type":"Public Place"
        }
    ],
    "sg:phone":"+44 1827 872374",
    "sg:postcode":"B76 9JD",
    "sg:province":"Warwickshire",
    "sg:tags":[
        "pubs",
        "house",
        "inn",
        "activity"
    ],
    "wof:name":"Dog & Doublet Inn",
    "wof:placetype":"venue"
},
  "geometry": {"coordinates":[-1.7081500292,52.5605049133],"type":"Point"}
}