{
  "type": "Feature",
  "properties": {
    "addr:full":"77 College Road, Harrow On The Hill Harrow Greater London HA1 1BD",
    "addr:housenumber":"77",
    "addr:postcode":"ha1 1bd",
    "addr:street":"College Road",
    "iso:country":"GB",
    "sg:address":"77 College Road, Harrow On The Hill",
    "sg:city":"Harrow",
    "sg:classifiers":[
        {
            "category":"Retail",
            "subcategory":"Laundry & Dry Cleaning",
            "type":"Services"
        }
    ],
    "sg:postcode":"HA1 1BD",
    "sg:province":"Greater London",
    "sg:tags":[
        "alteration"
    ],
    "wof:name":"Elegance Dry Cleaners",
    "wof:placetype":"venue"
},
  "geometry": {"coordinates":[-0.3381890059,51.5800170898],"type":"Point"}
}