{
  "type": "Feature",
  "properties": {
    "iso:country":"GB",
    "sg:address":"Calmore Community Centre, Totton",
    "sg:city":"Southampton",
    "sg:classifiers":[
        {
            "category":"Arena",
            "subcategory":"Sports Club",
            "type":"Entertainment"
        }
    ],
    "sg:phone":"+44 23 8066 3483",
    "sg:postcode":"SO4 2ZU",
    "sg:province":"Hampshire",
    "wof:name":"Totton Weightlifting Club",
    "wof:placetype":"venue"
},
  "geometry": {"coordinates":[-1.4911899567,50.9199104309],"type":"Point"}
}