{
  "type": "Feature",
  "properties": {
    "addr:full":"Flat 23 Old Court House, 24 Old Court Place London Greater London W8 4PD",
    "addr:housenumber":"flat 23;24",
    "addr:postcode":"w8 4pd",
    "addr:street":"Old Court House;Old Court Place",
    "iso:country":"GB",
    "sg:address":"Flat 23 Old Court House, 24 Old Court Place",
    "sg:city":"London",
    "sg:classifiers":[
        {
            "category":"Professional",
            "subcategory":"Business Services",
            "type":"Services"
        }
    ],
    "sg:phone":"+44 20 7938 4099",
    "sg:postcode":"W8 4PD",
    "sg:province":"Greater London",
    "sg:tags":[
        "import",
        "export",
        "agent"
    ],
    "wof:name":"Perhome Ltd.",
    "wof:placetype":"venue"
},
  "geometry": {"coordinates":[-0.1899199933,51.5023002625],"type":"Point"}
}