{
  "type": "Feature",
  "properties": {
    "iso:country":"GB",
    "sg:address":"Old Foundary Polmorla Rd",
    "sg:city":"Wadebridge",
    "sg:classifiers":[
        {
            "category":"Retail",
            "subcategory":"Laundry & Dry Cleaning",
            "type":"Services"
        }
    ],
    "sg:phone":"+44 1208 812692",
    "sg:postcode":"PL27 7NB",
    "sg:province":"Cornwall",
    "sg:tags":[
        "launderette"
    ],
    "wof:name":"Wadebridge Laundrette",
    "wof:placetype":"venue"
},
  "geometry": {"coordinates":[-4.8380241394,50.5181884766],"type":"Point"}
}