{
  "type": "Feature",
  "properties": {
    "iso:country":"GB",
    "sg:address":"25 Gosfield St",
    "sg:city":"West End",
    "sg:classifiers":[
        {
            "category":"Professional",
            "subcategory":"Management & Consulting",
            "type":"Services"
        }
    ],
    "sg:phone":"+44 20 7637 3262",
    "sg:postcode":"W1P 7HB",
    "sg:province":"Hampshire",
    "sg:tags":[
        "project"
    ],
    "wof:name":"Leonard Stace",
    "wof:placetype":"venue"
},
  "geometry": {"coordinates":[-0.142036,51.519756],"type":"Point"}
}