{
  "type": "Feature",
  "properties": {
    "addr:full":"50 Parc-y-coed Cardiff Cardiff CF4 8LY",
    "addr:housenumber":"50",
    "addr:postcode":"cf4 8ly",
    "addr:street":"Parc-Y-Coed Cardiff",
    "iso:country":"GB",
    "sg:address":"50 Parc-y-coed",
    "sg:city":"Cardiff",
    "sg:classifiers":[
        {
            "category":"Arts & Performance",
            "subcategory":"Music",
            "type":"Entertainment"
        }
    ],
    "sg:phone":"+44 29 2089 2388",
    "sg:postcode":"CF4 8LY",
    "sg:province":"Cardiff",
    "sg:tags":[
        "musician",
        "composer"
    ],
    "wof:name":"C Vale",
    "wof:placetype":"venue"
},
  "geometry": {"coordinates":[-3.3262450695,51.5226974487],"type":"Point"}
}