{
  "type": "Feature",
  "properties": {
    "iso:country":"GB",
    "sg:address":"Burton Road",
    "sg:city":"Barnsley",
    "sg:classifiers":[
        {
            "category":"Bars & Pubs",
            "type":"Food & Drink"
        }
    ],
    "sg:phone":"+44 1226 281068",
    "sg:postcode":"S71 2HG",
    "sg:province":"South Yorkshire",
    "sg:tags":[
        "pubs",
        "house",
        "inn",
        "public",
        "activity"
    ],
    "wof:name":"The Norman Inn",
    "wof:placetype":"venue"
},
  "geometry": {"coordinates":[-1.44023,53.570007],"type":"Point"}
}