{
  "type": "Feature",
  "properties": {
    "addr:full":"Higher Farm, Sutton Mallet Bridgwater Somerset TA7 9AW",
    "addr:postcode":"ta7 9aw",
    "addr:street":"Mallet",
    "iso:country":"GB",
    "sg:address":"Higher Farm, Sutton Mallet",
    "sg:city":"Bridgwater",
    "sg:classifiers":[
        {
            "category":"Farming",
            "subcategory":"Livestock Farm",
            "type":"Manufacturing & Wholesale Goods"
        }
    ],
    "sg:phone":"+44 1278 722385",
    "sg:postcode":"TA7 9AW",
    "sg:province":"Somerset",
    "sg:tags":[
        "others"
    ],
    "wof:name":"G L Groves & Son",
    "wof:placetype":"venue"
},
  "geometry": {"coordinates":[-2.895662,51.128361],"type":"Point"}
}