{
  "type": "Feature",
  "properties": {
    "addr:full":"Waplington Manor, Allerthorpe York East Riding of Yorkshire YO42 4RS",
    "addr:postcode":"yo42 4rs",
    "iso:country":"GB",
    "sg:address":"Waplington Manor, Allerthorpe",
    "sg:city":"York",
    "sg:classifiers":[
        {
            "category":"Farming",
            "subcategory":"Livestock Farm",
            "type":"Manufacturing & Wholesale Goods"
        }
    ],
    "sg:phone":"+44 1759 305678",
    "sg:postcode":"YO42 4RS",
    "sg:province":"East Riding of Yorkshire",
    "sg:tags":[
        "stud"
    ],
    "wof:name":"Waplington Manor Stables",
    "wof:placetype":"venue"
},
  "geometry": {"coordinates":[-0.805594027,53.9172592163],"type":"Point"}
}