{
  "type": "Feature",
  "properties": {
    "addr:full":"22-30 Greyfriars Bedford Bedfordshire MK40 1HP",
    "addr:housenumber":"22-30",
    "addr:postcode":"mk40 1hp",
    "addr:street":"Greyfriars",
    "iso:country":"GB",
    "sg:address":"22-30 Greyfriars",
    "sg:city":"Bedford",
    "sg:classifiers":[
        {
            "category":"Home & Garden",
            "subcategory":"Home Furnishings",
            "type":"Retail Goods"
        }
    ],
    "sg:postcode":"MK40 1HP",
    "sg:province":"Bedfordshire",
    "sg:tags":[
        "beds",
        "bedding",
        "blanket"
    ],
    "wof:name":"Uk Bed Centres",
    "wof:placetype":"venue"
},
  "geometry": {"coordinates":[-0.472091,52.136539],"type":"Point"}
}