{
  "type": "Feature",
  "properties": {
    "addr:full":"Hatton Court Country House Hotel, Bullington End Milton Keynes Buckinghamshire MK19 7BQ",
    "addr:postcode":"mk19 7bq",
    "addr:street":"Hatton Court;End",
    "iso:country":"GB",
    "sg:address":"Hatton Court Country House Hotel, Bullington End",
    "sg:city":"Milton Keynes",
    "sg:classifiers":[
        {
            "category":"Personal",
            "subcategory":"Beauty Salon",
            "type":"Services"
        }
    ],
    "sg:phone":"+44 1908 504441",
    "sg:postcode":"MK19 7BQ",
    "sg:province":"Buckinghamshire",
    "wof:name":"Gatehouse The",
    "wof:placetype":"venue"
},
  "geometry": {"coordinates":[-0.8298770189,52.0943145752],"type":"Point"}
}