{
  "type": "Feature",
  "properties": {
    "addr:full":"4b East Mill, Bridge Foot Belper Derbyshire DE56 2UA",
    "addr:housenumber":"4b",
    "addr:postcode":"de56 2ua",
    "addr:street":"East Mill Bridge;Belper",
    "iso:country":"GB",
    "sg:address":"4b East Mill, Bridge Foot",
    "sg:city":"Belper",
    "sg:classifiers":[
        {
            "category":"Professional",
            "subcategory":"Computer Services",
            "type":"Services"
        }
    ],
    "sg:postcode":"DE56 2UA",
    "sg:province":"Derbyshire",
    "sg:tags":[
        "system",
        "software"
    ],
    "wof:name":"Micro Connect Ltd.",
    "wof:placetype":"venue"
},
  "geometry": {"coordinates":[-1.4471800327,53.048576355],"type":"Point"}
}