{
  "type": "Feature",
  "properties": {
    "addr:full":"7 Frascati Way Maidenhead Berkshire SL6 4UY",
    "addr:housenumber":"7",
    "addr:postcode":"sl6 4uy",
    "addr:street":"Frascati Way",
    "iso:country":"GB",
    "sg:address":"7 Frascati Way",
    "sg:city":"Maidenhead",
    "sg:classifiers":[
        {
            "category":"Manufacturing",
            "subcategory":"Electronics",
            "type":"Manufacturing & Wholesale Goods"
        }
    ],
    "sg:phone":"+44 1628 783688",
    "sg:postcode":"SL6 4UY",
    "sg:province":"Berkshire",
    "sg:tags":[
        "control",
        "component",
        "-",
        "electronic"
    ],
    "wof:name":"E B V-Elektronik Vertriebsgesellschaft mit Beschrankter Haftung",
    "wof:placetype":"venue"
},
  "geometry": {"coordinates":[-0.7240419984,51.5207901001],"type":"Point"}
}