{
  "type": "Feature",
  "properties": {
    "addr:full":"71 Warwick Street Leamington Spa Warwickshire CV32 4RQ",
    "addr:housenumber":"71",
    "addr:postcode":"cv32 4rq",
    "addr:street":"Warwick Street",
    "iso:country":"GB",
    "sg:address":"71 Warwick Street",
    "sg:city":"Leamington Spa",
    "sg:classifiers":[
        {
            "category":"Shopping",
            "subcategory":"Used Merchandise",
            "type":"Retail Goods"
        }
    ],
    "sg:phone":"+44 1926 426144",
    "sg:postcode":"CV32 4RQ",
    "sg:province":"Warwickshire",
    "sg:tags":[
        "shop",
        "second-hand"
    ],
    "wof:name":"Cargo Homeshop",
    "wof:placetype":"venue"
},
  "geometry": {"coordinates":[-1.534994,52.29211],"type":"Point"}
}