{
  "type": "Feature",
  "properties": {
    "iso:country":"GB",
    "sg:address":"213 Ashby Road",
    "sg:city":"Coalville",
    "sg:classifiers":[
        {
            "category":"Retail",
            "subcategory":"Auto Repair",
            "type":"Services"
        }
    ],
    "sg:postcode":"LE67 3LG",
    "sg:province":"Leicestershire",
    "sg:tags":[
        "modification",
        "garage",
        "related"
    ],
    "wof:name":"Pitstop (U K) Ltd",
    "wof:placetype":"venue"
},
  "geometry": {"coordinates":[-1.395185,52.731468],"type":"Point"}
}