{
  "type": "Feature",
  "properties": {
    "addr:full":"5 Newport Place London Greater London WC2H 7JN",
    "addr:housenumber":"5",
    "addr:postcode":"wc2h 7jn",
    "addr:street":"Newport Place",
    "iso:country":"GB",
    "sg:address":"5 Newport Place",
    "sg:city":"London",
    "sg:classifiers":[
        {
            "category":"Travel",
            "subcategory":"Travel Agent",
            "type":"Entertainment"
        }
    ],
    "sg:phone":"+44 20 7734 7721",
    "sg:postcode":"WC2H 7JN",
    "sg:province":"Greater London",
    "wof:name":"Jade Travel Ltd.",
    "wof:placetype":"venue"
},
  "geometry": {"coordinates":[-0.129646,51.511852],"type":"Point"}
}