{
  "type": "Feature",
  "properties": {
    "iso:country":"GB",
    "sg:address":"Customer Operation Centre, South Boundry Road",
    "sg:city":"Liverpool",
    "sg:classifiers":[
        {
            "category":"Communications",
            "type":"Services"
        }
    ],
    "sg:phone":"+44 151 551 2500",
    "sg:postcode":"L70 2QA",
    "sg:province":"Merseyside",
    "sg:tags":[
        "broadcasting"
    ],
    "wof:name":"Q V C",
    "wof:placetype":"venue"
},
  "geometry": {"coordinates":[-2.85828,53.472462],"type":"Point"}
}