{
  "type": "Feature",
  "properties": {
    "addr:full":"14 Lower Richmond Road, Putney London Greater London SW15 1JP",
    "addr:housenumber":"14",
    "addr:postcode":"sw15 1jp",
    "addr:street":"Lower Richmond Road",
    "iso:country":"GB",
    "sg:address":"14 Lower Richmond Road, Putney",
    "sg:city":"London",
    "sg:classifiers":[
        {
            "category":"Home & Garden",
            "subcategory":"Building Materials",
            "type":"Retail Goods"
        }
    ],
    "sg:phone":"+44 20 8788 8853",
    "sg:postcode":"SW15 1JP",
    "sg:province":"Greater London",
    "sg:tags":[
        "door",
        "domestic"
    ],
    "wof:name":"A.D.S Home Security",
    "wof:placetype":"venue"
},
  "geometry": {"coordinates":[-0.2173070014,51.4670181274],"type":"Point"}
}