{
  "type": "Feature",
  "properties": {
    "addr:full":"32 Eskdaill Court Dalkeith City of Edinburgh EH22 1AG",
    "addr:housenumber":"32",
    "addr:postcode":"eh22 1ag",
    "addr:street":"Eskdaill Court",
    "iso:country":"GB",
    "sg:address":"32 Eskdaill Court",
    "sg:city":"Dalkeith",
    "sg:classifiers":[
        {
            "category":"Professional",
            "subcategory":"Art Services",
            "type":"Services"
        }
    ],
    "sg:phone":"+44 131 663 5014",
    "sg:postcode":"EH22 1AG",
    "sg:province":"City of Edinburgh",
    "sg:tags":[
        "photographer"
    ],
    "wof:name":"William Thomson",
    "wof:placetype":"venue"
},
  "geometry": {"coordinates":[-3.0968089104,55.9043502808],"type":"Point"}
}