{
  "type": "Feature",
  "properties": {
    "addr:full":"63 Bawtry Road, Bramley Rotherham South Yorkshire S66 2TN",
    "addr:housenumber":"63",
    "addr:postcode":"s66 2tn",
    "addr:street":"Bawtry Road",
    "iso:country":"GB",
    "sg:address":"63 Bawtry Road, Bramley",
    "sg:city":"Rotherham",
    "sg:phone":"+44 1709 703707",
    "sg:postcode":"S66 2TN",
    "sg:province":"South Yorkshire",
    "wof:name":"Alan M Thompson Ltd.",
    "wof:placetype":"venue"
},
  "geometry": {"coordinates":[-1.267171979,53.4230804443],"type":"Point"}
}