{
  "type": "Feature",
  "properties": {
    "iso:country":"GB",
    "sg:address":"127 Cole Valley Road, Hall Grn",
    "sg:city":"Birmingham",
    "sg:classifiers":[
        {
            "category":"Building & Trades",
            "subcategory":"Locksmith",
            "type":"Services"
        }
    ],
    "sg:postcode":"B28 0DG",
    "sg:province":"West Midlands",
    "wof:name":"M Williams Carpentry & Locksmith Services",
    "wof:placetype":"venue"
},
  "geometry": {"coordinates":[-1.8567370176,52.4262542725],"type":"Point"}
}