{
  "type": "Feature",
  "properties": {
    "iso:country":"GB",
    "sg:address":"Leven Road",
    "sg:city":"London",
    "sg:classifiers":[
        {
            "category":"Home & Garden",
            "subcategory":"Building Materials",
            "type":"Retail Goods"
        }
    ],
    "sg:phone":"+44 20 7987 6461",
    "sg:postcode":"E14 0LN",
    "sg:province":"Greater London",
    "sg:tags":[
        "polythene",
        "plastic"
    ],
    "wof:name":"Ashwood Timber & Plastics Ltd.",
    "wof:placetype":"venue"
},
  "geometry": {"coordinates":[-0.007724,51.517063],"type":"Point"}
}