{
  "type": "Feature",
  "properties": {
    "iso:country":"GB",
    "sg:address":"16 Lindsey Road Industrial Estate",
    "sg:city":"Edinburgh",
    "sg:classifiers":[
        {
            "category":"Professional",
            "subcategory":"Engineering",
            "type":"Services"
        }
    ],
    "sg:postcode":"EH6 4ER",
    "sg:province":"City of Edinburgh",
    "sg:tags":[
        "merchant",
        "engineers'"
    ],
    "wof:name":"Industrial Fixing Systems Ltd.",
    "wof:placetype":"venue"
},
  "geometry": {"coordinates":[-3.1857059002,55.9790077209],"type":"Point"}
}