{
  "type": "Feature",
  "properties": {
    "iso:country":"GB",
    "sg:address":"Cooks La",
    "sg:city":"Birmingham",
    "sg:classifiers":[
        {
            "category":"Farming",
            "subcategory":"Nursery",
            "type":"Manufacturing & Wholesale Goods"
        }
    ],
    "sg:phone":"+44 121 779 2380",
    "sg:postcode":"B37 6NZ",
    "sg:province":"West Midlands",
    "sg:tags":[
        "creche"
    ],
    "wof:name":"Techno Tots Day Nursery Ltd",
    "wof:placetype":"venue"
},
  "geometry": {"coordinates":[-1.739829,52.490246],"type":"Point"}
}