{
  "type": "Feature",
  "properties": {
    "iso:country":"GB",
    "sg:address":"2b Humphrey La, Urmston",
    "sg:city":"Manchester",
    "sg:classifiers":[
        {
            "category":"Shopping",
            "subcategory":"Florist",
            "type":"Retail Goods"
        }
    ],
    "sg:postcode":"M41 9PE",
    "sg:province":"Cheshire",
    "wof:name":"Worthington,David,",
    "wof:placetype":"venue"
},
  "geometry": {"coordinates":[-2.331615,53.446217],"type":"Point"}
}