{
  "type": "Feature",
  "properties": {
    "iso:country":"GB",
    "sg:address":"20 Kingsway, Waterloo",
    "sg:city":"Liverpool",
    "sg:classifiers":[
        {
            "category":"Health Services",
            "subcategory":"Doctor",
            "type":"Services"
        }
    ],
    "sg:phone":"+44 151 920 9000",
    "sg:postcode":"L22 4RQ",
    "sg:province":"Merseyside",
    "sg:tags":[
        "practitioners"
    ],
    "wof:name":"Margaret Tatum",
    "wof:placetype":"venue"
},
  "geometry": {"coordinates":[-3.021451,53.481129],"type":"Point"}
}