{
  "type": "Feature",
  "properties": {
    "iso:country":"GB",
    "sg:address":"5a Thorpe Close",
    "sg:city":"Banbury",
    "sg:classifiers":[
        {
            "category":"Professional",
            "subcategory":"Engineering",
            "type":"Services"
        }
    ],
    "sg:phone":"+44 1295 273179",
    "sg:postcode":"OX16 4SW",
    "sg:province":"Oxfordshire",
    "sg:tags":[
        "electronic",
        "engineer"
    ],
    "wof:name":"Orbis Technologies Ltd.",
    "wof:placetype":"venue"
},
  "geometry": {"coordinates":[-1.316401,52.061501],"type":"Point"}
}