{
  "type": "Feature",
  "properties": {
    "iso:country":"GB",
    "sg:address":"56 South Street",
    "sg:city":"Bridport",
    "sg:classifiers":[
        {
            "category":"Home & Garden",
            "subcategory":"Household Appliances",
            "type":"Retail Goods"
        },
        {
            "category":"Retail",
            "subcategory":"Repair Shop",
            "type":"Services"
        }
    ],
    "sg:postcode":"DT6 3NN",
    "sg:province":"Dorset",
    "sg:tags":[
        "electrical",
        "television",
        "video",
        "radio"
    ],
    "wof:name":"Teleman",
    "wof:placetype":"venue"
},
  "geometry": {"coordinates":[-2.7582,50.731709],"type":"Point"}
}