{
  "type": "Feature",
  "properties": {
    "iso:country":"GB",
    "sg:address":"28 Carlyle Rd",
    "sg:city":"Cambridge",
    "sg:classifiers":[
        {
            "category":"Travel",
            "subcategory":"Hostel",
            "type":"Entertainment"
        },
        {
            "category":"Organizations",
            "subcategory":"Non-profit Organization",
            "type":"Services"
        }
    ],
    "sg:postcode":"CB4 3DN",
    "sg:province":"Cambridgeshire",
    "sg:tags":[
        "organisation",
        "voluntary",
        "charity"
    ],
    "wof:name":"Cambridge Cyrenians Ltd",
    "wof:placetype":"venue"
},
  "geometry": {"coordinates":[0.1196440011,52.214012146],"type":"Point"}
}