{
  "type": "Feature",
  "properties": {
    "iso:country":"GB",
    "sg:address":"Hazel Gardens",
    "sg:city":"Wisbech",
    "sg:classifiers":[
        {
            "category":"Food & Beverages",
            "subcategory":"Candy",
            "type":"Retail Goods"
        }
    ],
    "sg:postcode":"PE13 2AS",
    "sg:province":"Cambridgeshire",
    "sg:tags":[
        "confectioner"
    ],
    "wof:name":"Alan James Short Coded Products",
    "wof:placetype":"venue"
},
  "geometry": {"coordinates":[0.167497,52.661694],"type":"Point"}
}