{
  "type": "Feature",
  "properties": {
    "iso:country":"GB",
    "sg:address":"Jericho Farm, Grn Lane, Lambley",
    "sg:city":"Nottingham",
    "sg:classifiers":[
        {
            "category":"Farming",
            "subcategory":"Livestock Farm",
            "type":"Manufacturing & Wholesale Goods"
        }
    ],
    "sg:postcode":"NG4 4QE",
    "sg:province":"Nottinghamshire",
    "sg:tags":[
        "others"
    ],
    "wof:name":"Hardy W & Sons",
    "wof:placetype":"venue"
},
  "geometry": {"coordinates":[-1.064794,53.000622],"type":"Point"}
}