{
  "type": "Feature",
  "properties": {
    "addr:full":"356/357 Railway Arches, Yorkshire Road London Greater London E14 7LR",
    "addr:housenumber":"356 / 357",
    "addr:postcode":"e14 7lr",
    "addr:street":"Railway Arches Yorkshire Road",
    "iso:country":"GB",
    "sg:address":"356/357 Railway Arches, Yorkshire Road",
    "sg:city":"London",
    "sg:classifiers":[
        {
            "category":"Building & Trades",
            "subcategory":"Construction",
            "type":"Services"
        }
    ],
    "sg:phone":"+44 20 7702 8820",
    "sg:postcode":"E14 7LR",
    "sg:province":"Greater London",
    "sg:tags":[
        "demolition",
        "contractor"
    ],
    "wof:name":"Attfield & Co.  Ltd.",
    "wof:placetype":"venue"
},
  "geometry": {"coordinates":[-0.0390999988,51.5127906799],"type":"Point"}
}