{
  "type": "Feature",
  "properties": {
    "addr:full":"10 Gwendoline Rd, Risca Newport Blaenau Gwent NP11 6DD",
    "addr:housenumber":"10",
    "addr:postcode":"np11 6dd",
    "addr:street":"Gwendoline Rd",
    "iso:country":"GB",
    "sg:address":"10 Gwendoline Rd, Risca",
    "sg:city":"Newport",
    "sg:classifiers":[
        {
            "category":"Building & Trades",
            "subcategory":"Construction",
            "type":"Services"
        }
    ],
    "sg:phone":"+44 1633 612503",
    "sg:postcode":"NP11 6DD",
    "sg:province":"Blaenau Gwent",
    "sg:tags":[
        "roofing"
    ],
    "wof:name":"M Bartlett",
    "wof:placetype":"venue"
},
  "geometry": {"coordinates":[-3.1031730175,51.6074333191],"type":"Point"}
}