{
  "type": "Feature",
  "properties": {
    "addr:full":"Fir Lane, Steeple Aston Bicester Oxfordshire OX25 4SF",
    "addr:postcode":"ox25 4sf",
    "addr:street":"Fir Lane",
    "iso:country":"GB",
    "sg:address":"Fir Lane, Steeple Aston",
    "sg:city":"Bicester",
    "sg:classifiers":[
        {
            "category":"Education",
            "subcategory":"School",
            "type":"Public Place"
        }
    ],
    "sg:phone":"+44 1869 340204",
    "sg:postcode":"OX25 4SF",
    "sg:province":"Oxfordshire",
    "sg:tags":[
        "local",
        "authority"
    ],
    "wof:name":"Dr Radcliffe's C of E Primary School",
    "wof:placetype":"venue"
},
  "geometry": {"coordinates":[-1.313006,51.92836],"type":"Point"}
}