{
  "type": "Feature",
  "properties": {
    "addr:full":"6 Oldhams Hill, Winnington Street Northwich Cheshire CW8 1AJ",
    "addr:housenumber":"6",
    "addr:postcode":"cw8 1aj",
    "addr:street":"Oldhams Hill Winnington Street",
    "iso:country":"GB",
    "sg:address":"6 Oldhams Hill, Winnington Street",
    "sg:city":"Northwich",
    "sg:classifiers":[
        {
            "category":"Retail",
            "subcategory":"Auto Repair",
            "type":"Services"
        }
    ],
    "sg:postcode":"CW8 1AJ",
    "sg:province":"Cheshire",
    "sg:tags":[
        "modification",
        "garage"
    ],
    "wof:name":"J Shaughnessy",
    "wof:placetype":"venue"
},
  "geometry": {"coordinates":[-2.517624,53.262295],"type":"Point"}
}