{
  "type": "Feature",
  "properties": {
    "addr:full":"6 Casselbank Street, Leith Edinburgh City of Edinburgh EH6 5HA",
    "addr:housenumber":"6",
    "addr:postcode":"eh6 5ha",
    "addr:street":"Casselbank Street",
    "iso:country":"GB",
    "sg:address":"6 Casselbank Street, Leith",
    "sg:city":"Edinburgh",
    "sg:classifiers":[
        {
            "category":"Travel",
            "subcategory":"Hostel",
            "type":"Entertainment"
        }
    ],
    "sg:postcode":"EH6 5HA",
    "sg:province":"City of Edinburgh",
    "wof:name":"Bethany Christian Centre",
    "wof:placetype":"venue"
},
  "geometry": {"coordinates":[-3.174144,55.970245],"type":"Point"}
}