{
  "type": "Feature",
  "properties": {
    "iso:country":"GB",
    "sg:address":"85 St. Johns",
    "sg:city":"Worcester",
    "sg:classifiers":[
        {
            "category":"Professional",
            "subcategory":"Printing & Photocopies",
            "type":"Services"
        }
    ],
    "sg:phone":"+44 1905 429928",
    "sg:postcode":"WR2 5AG",
    "sg:province":"Worcestershire",
    "sg:tags":[
        "printer"
    ],
    "wof:name":"First Paige",
    "wof:placetype":"venue"
},
  "geometry": {"coordinates":[-2.235396,52.186947],"type":"Point"}
}