{
  "type": "Feature",
  "properties": {
    "addr:full":"Park Cottage, High Gosforth Park, Newcastle Newcastle Upon Tyne Tyne and Wear NE3 5EJ",
    "addr:postcode":"ne3 5ej",
    "addr:street":"Gosforth Park",
    "iso:country":"GB",
    "sg:address":"Park Cottage, High Gosforth Park, Newcastle",
    "sg:city":"Newcastle Upon Tyne",
    "sg:classifiers":[
        {
            "category":"Recreation",
            "type":"Entertainment"
        }
    ],
    "sg:phone":"+44 191 217 1277",
    "sg:postcode":"NE3 5EJ",
    "sg:province":"Tyne and Wear",
    "sg:tags":[
        "corporate",
        "leisure"
    ],
    "wof:name":"Jix-sing Helicopter Training",
    "wof:placetype":"venue"
},
  "geometry": {"coordinates":[-1.613139987,55.0354003906],"type":"Point"}
}