{
  "type": "Feature",
  "properties": {
    "addr:full":"Unit 6, Edison Business Centre, Edison Rd Aylesbury Buckinghamshire HP19 8TE",
    "addr:housenumber":"unit 6",
    "addr:postcode":"hp19 8te",
    "addr:street":"Edison Business Centre Edison Rd",
    "iso:country":"GB",
    "sg:address":"Unit 6, Edison Business Centre, Edison Rd",
    "sg:city":"Aylesbury",
    "sg:classifiers":[
        {
            "category":"Manufacturing",
            "subcategory":"Rubber & Plastics",
            "type":"Manufacturing & Wholesale Goods"
        }
    ],
    "sg:postcode":"HP19 8TE",
    "sg:province":"Buckinghamshire",
    "sg:tags":[
        "mould"
    ],
    "wof:name":"Jones,Trevor,",
    "wof:placetype":"venue"
},
  "geometry": {"coordinates":[-0.8507500291,51.8222312927],"type":"Point"}
}