{
  "type": "Feature",
  "properties": {
    "addr:full":"20 Plashet Grove, East Ham London Greater London E6 1AE",
    "addr:housenumber":"20",
    "addr:postcode":"e6 1ae",
    "addr:street":"Plashet Grove",
    "iso:country":"GB",
    "sg:address":"20 Plashet Grove, East Ham",
    "sg:city":"London",
    "sg:classifiers":[
        {
            "category":"Wholesale",
            "subcategory":"Meat",
            "type":"Manufacturing & Wholesale Goods"
        }
    ],
    "sg:phone":"+44 20 8471 0031",
    "sg:postcode":"E6 1AE",
    "sg:province":"Greater London",
    "sg:tags":[
        "-"
    ],
    "wof:name":"Graham Meats (Wholesale) Ltd.",
    "wof:placetype":"venue"
},
  "geometry": {"coordinates":[0.0362609997,51.5370521545],"type":"Point"}
}