{
  "type": "Feature",
  "properties": {
    "addr:full":"Unit 3 K G Business Centre, Kingsfield Close Northampton Northamptonshire NN5 7QS",
    "addr:housenumber":"unit 3 k g business centre",
    "addr:postcode":"nn5 7qs",
    "addr:street":"Kingsfield Close",
    "iso:country":"GB",
    "sg:address":"Unit 3 K G Business Centre, Kingsfield Close",
    "sg:city":"Northampton",
    "sg:classifiers":[
        {
            "category":"Professional",
            "subcategory":"Detective & Security Services",
            "type":"Services"
        },
        {
            "category":"Organizations",
            "subcategory":"Non-profit Organization",
            "type":"Services"
        }
    ],
    "sg:postcode":"NN5 7QS",
    "sg:province":"Northamptonshire",
    "sg:tags":[
        "equipment",
        "alarm",
        "system",
        "installers"
    ],
    "wof:name":"J B Alarms",
    "wof:placetype":"venue"
},
  "geometry": {"coordinates":[-0.9178199768,52.2521095276],"type":"Point"}
}