{
  "type": "Feature",
  "properties": {
    "addr:full":"The Lodge Residential Home York North Yorkshire YO1 5DX",
    "addr:postcode":"yo1 5dx",
    "iso:country":"GB",
    "sg:address":"The Lodge Residential Home",
    "sg:city":"York",
    "sg:classifiers":[
        {
            "category":"Social Services",
            "subcategory":"Retirement Home",
            "type":"Services"
        }
    ],
    "sg:phone":"+44 1904 430781",
    "sg:postcode":"YO1 5DX",
    "sg:province":"North Yorkshire",
    "sg:tags":[
        "residential",
        "care"
    ],
    "wof:name":"Lodge Residential Home The",
    "wof:placetype":"venue"
},
  "geometry": {"coordinates":[-1.0813499689,53.958770752],"type":"Point"}
}