{
  "type": "Feature",
  "properties": {
    "iso:country":"GB",
    "sg:address":"Newfield Farm, Firbank",
    "sg:city":"Sedbergh",
    "sg:classifiers":[
        {
            "category":"Home & Garden",
            "subcategory":"Garden Supply",
            "type":"Retail Goods"
        },
        {
            "category":"Farming",
            "subcategory":"Farm",
            "type":"Manufacturing & Wholesale Goods"
        }
    ],
    "sg:postcode":"LA10 5EN",
    "sg:province":"Cumbria",
    "sg:tags":[
        "mixed",
        "bulb",
        "crop",
        "grower"
    ],
    "wof:name":"Thomas Metcalfe",
    "wof:placetype":"venue"
},
  "geometry": {"coordinates":[-2.527837038,54.3219451904],"type":"Point"}
}