{
  "type": "Feature",
  "properties": {
    "addr:full":"69 Wardwick Derby Derbyshire DE1 1HJ",
    "addr:housenumber":"69",
    "addr:postcode":"de1 1hj",
    "addr:street":"Wardwick Derby",
    "iso:country":"GB",
    "sg:address":"69 Wardwick",
    "sg:city":"Derby",
    "sg:classifiers":[
        {
            "category":"Real Estate",
            "subcategory":"Real Estate Agent",
            "type":"Services"
        }
    ],
    "sg:postcode":"DE1 1HJ",
    "sg:province":"Derbyshire",
    "wof:name":"W Plant",
    "wof:placetype":"venue"
},
  "geometry": {"coordinates":[-1.480969,52.922771],"type":"Point"}
}