{
  "type": "Feature",
  "properties": {
    "addr:full":"Kingsbridge Dartmouth Rd, Chillington Kingsbridge Devon TQ7 2JS",
    "addr:postcode":"tq7 2js",
    "addr:street":"Dartmouth Rd",
    "iso:country":"GB",
    "sg:address":"Kingsbridge Dartmouth Rd, Chillington",
    "sg:city":"Kingsbridge",
    "sg:classifiers":[
        {
            "category":"Bars & Pubs",
            "type":"Food & Drink"
        }
    ],
    "sg:postcode":"TQ7 2JS",
    "sg:province":"Devon",
    "sg:tags":[
        "pubs",
        "inn"
    ],
    "wof:name":"Chillington Inn (The)",
    "wof:placetype":"venue"
},
  "geometry": {"coordinates":[-3.6954190731,50.2729797363],"type":"Point"}
}