{
  "type": "Feature",
  "properties": {
    "iso:country":"GB",
    "sg:address":"3 Mill Road, Willingham",
    "sg:city":"Cambridge",
    "sg:classifiers":[
        {
            "category":"Shopping",
            "subcategory":"Department Store",
            "type":"Retail Goods"
        }
    ],
    "sg:postcode":"CB4 5LA",
    "sg:province":"Cambridgeshire",
    "wof:name":"A Hayden & Son",
    "wof:placetype":"venue"
},
  "geometry": {"coordinates":[-0.0543330014,52.2945213318],"type":"Point"}
}