{
  "type": "Feature",
  "properties": {
    "addr:full":"Wood Close Windsor Berkshire SL4 3LL",
    "addr:postcode":"sl4 3ll",
    "addr:street":"Wood Close",
    "iso:country":"GB",
    "sg:address":"Wood Close",
    "sg:city":"Windsor",
    "sg:classifiers":[
        {
            "category":"Education",
            "subcategory":"School",
            "type":"Public Place"
        }
    ],
    "sg:postcode":"SL4 3LL",
    "sg:province":"Berkshire",
    "sg:tags":[
        "local",
        "authority"
    ],
    "wof:name":"Trevelyan Middle School",
    "wof:placetype":"venue"
},
  "geometry": {"coordinates":[-0.611746,51.470329],"type":"Point"}
}