{
  "type": "Feature",
  "properties": {
    "addr:full":"1-4 Long Causeway Peterborough Cambridgeshire PE1 1YD",
    "addr:housenumber":"1-4",
    "addr:postcode":"pe1 1yd",
    "addr:street":"Long Causeway",
    "iso:country":"GB",
    "sg:address":"1-4 Long Causeway",
    "sg:city":"Peterborough",
    "sg:classifiers":[
        {
            "category":"Banks & Credit Unions",
            "subcategory":"Bank",
            "type":"Services"
        }
    ],
    "sg:phone":"+44 845 765 4321",
    "sg:postcode":"PE1 1YD",
    "sg:province":"Cambridgeshire",
    "wof:name":"Abbey National Plc",
    "wof:placetype":"venue"
},
  "geometry": {"coordinates":[-0.2424809933,52.5729408264],"type":"Point"}
}