{
  "type": "Feature",
  "properties": {
    "addr:full":"15 Bencombe Road Purley Surrey CR8 4DR",
    "addr:housenumber":"15",
    "addr:postcode":"cr8 4dr",
    "addr:street":"Bencombe Road",
    "iso:country":"GB",
    "sg:address":"15 Bencombe Road",
    "sg:city":"Purley",
    "sg:classifiers":[
        {
            "category":"Professional",
            "subcategory":"Accounting & Tax Preparation",
            "type":"Services"
        }
    ],
    "sg:phone":"+44 20 8668 5815",
    "sg:postcode":"CR8 4DR",
    "sg:province":"Surrey",
    "sg:tags":[
        "accountant",
        "activity"
    ],
    "wof:name":"Malcolm Prior & Co",
    "wof:placetype":"venue"
},
  "geometry": {"coordinates":[-0.1198659986,51.32762146],"type":"Point"}
}