{
  "type": "Feature",
  "properties": {
    "addr:full":"9 Wivelsfield Road Doncaster South Yorkshire DN4 0UY",
    "addr:housenumber":"9",
    "addr:postcode":"dn4 0uy",
    "addr:street":"Wivelsfield Road",
    "iso:country":"GB",
    "sg:address":"9 Wivelsfield Road",
    "sg:city":"Doncaster",
    "sg:classifiers":[
        {
            "category":"Shopping",
            "subcategory":"News",
            "type":"Retail Goods"
        }
    ],
    "sg:phone":"+44 1302 812023",
    "sg:postcode":"DN4 0UY",
    "sg:province":"South Yorkshire",
    "sg:tags":[
        "newsagent"
    ],
    "wof:name":"M & N News",
    "wof:placetype":"venue"
},
  "geometry": {"coordinates":[-1.170740962,53.5009384155],"type":"Point"}
}