{
  "type": "Feature",
  "properties": {
    "addr:full":"16 Church Street Twickenham Greater London TW1 3NJ",
    "addr:housenumber":"16",
    "addr:postcode":"tw1 3nj",
    "addr:street":"Church Street",
    "iso:country":"GB",
    "sg:address":"16 Church Street",
    "sg:city":"Twickenham",
    "sg:classifiers":[
        {
            "category":"Shopping",
            "subcategory":"Clothing, Apparel, & Fashions",
            "type":"Retail Goods"
        }
    ],
    "sg:phone":"+44 20 8892 0707",
    "sg:postcode":"TW1 3NJ",
    "sg:province":"Greater London",
    "sg:tags":[
        "dresswear"
    ],
    "wof:name":"Avonmore Enterprises Ltd.",
    "wof:placetype":"venue"
},
  "geometry": {"coordinates":[-0.3268739879,51.4469871521],"type":"Point"}
}