{
  "type": "Feature",
  "properties": {
    "addr:full":"Cartwright House, Springwell Road Leeds West Yorkshire LS12 1AX",
    "addr:postcode":"ls12 1ax",
    "addr:street":"Springwell Road",
    "iso:country":"GB",
    "sg:address":"Cartwright House, Springwell Road",
    "sg:city":"Leeds",
    "sg:classifiers":[
        {
            "category":"Wholesale",
            "subcategory":"Hardware",
            "type":"Manufacturing & Wholesale Goods"
        },
        {
            "category":"Home & Garden",
            "subcategory":"Hardware",
            "type":"Retail Goods"
        }
    ],
    "sg:phone":"+44 113 243 6931",
    "sg:postcode":"LS12 1AX",
    "sg:province":"West Yorkshire",
    "sg:tags":[
        "merchant",
        "ironmonger"
    ],
    "wof:name":"Cartwright Hardware Ltd.",
    "wof:placetype":"venue"
},
  "geometry": {"coordinates":[-1.5590690374,53.7900695801],"type":"Point"}
}