{
  "type": "Feature",
  "properties": {
    "addr:full":"208 Station Road Seaham Durham SR7 0BL",
    "addr:housenumber":"208",
    "addr:postcode":"sr7 0bl",
    "addr:street":"Station Road",
    "iso:country":"GB",
    "sg:address":"208 Station Road",
    "sg:city":"Seaham",
    "sg:classifiers":[
        {
            "category":"Organizations",
            "subcategory":"Membership Organization",
            "type":"Services"
        }
    ],
    "sg:phone":"+44 191 581 2738",
    "sg:postcode":"SR7 0BL",
    "sg:province":"Durham",
    "sg:tags":[
        "club"
    ],
    "wof:name":"New Seaham Conservative Club",
    "wof:placetype":"venue"
},
  "geometry": {"coordinates":[-1.361234,54.841194],"type":"Point"}
}