{
  "type": "Feature",
  "properties": {
    "iso:country":"GB",
    "sg:address":"21 Dave Barrie Av",
    "sg:city":"Larkhall",
    "sg:classifiers":[
        {
            "category":"Professional",
            "subcategory":"Detective & Security Services",
            "type":"Services"
        }
    ],
    "sg:phone":"+44 1698 881125",
    "sg:postcode":"ML9 1DW",
    "sg:province":"South Lanarkshire",
    "sg:tags":[
        "alarm",
        "burglar",
        "system"
    ],
    "wof:name":"Multi Link Technology",
    "wof:placetype":"venue"
},
  "geometry": {"coordinates":[-3.9793150425,55.7473907471],"type":"Point"}
}