{
  "type": "Feature",
  "properties": {
    "addr:full":"Moreton Green First School, 18 Llanthony Rd Morden Surrey SM4 6DX",
    "addr:housenumber":"18",
    "addr:postcode":"sm4 6dx",
    "addr:street":"Llanthony Rd",
    "iso:country":"GB",
    "sg:address":"Moreton Green First School, 18 Llanthony Rd",
    "sg:city":"Morden",
    "sg:classifiers":[
        {
            "category":"Government",
            "subcategory":"Office",
            "type":"Public Place"
        }
    ],
    "sg:phone":"+44 20 8648 1856",
    "sg:postcode":"SM4 6DX",
    "sg:province":"Surrey",
    "sg:tags":[
        "local"
    ],
    "wof:name":"Morden Borough Council",
    "wof:placetype":"venue"
},
  "geometry": {"coordinates":[-0.188834995,51.4005279541],"type":"Point"}
}