{
  "type": "Feature",
  "properties": {
    "iso:country":"GB",
    "sg:address":"Home Farm, Longbridge",
    "sg:city":"Warwick",
    "sg:classifiers":[
        {
            "category":"Wholesale",
            "subcategory":"Fruits & Vegetables",
            "type":"Manufacturing & Wholesale Goods"
        }
    ],
    "sg:postcode":"CV34 6RB",
    "sg:province":"Warwickshire",
    "wof:name":"H A Webb",
    "wof:placetype":"venue"
},
  "geometry": {"coordinates":[-1.606059,52.26133],"type":"Point"}
}