{
  "type": "Feature",
  "properties": {
    "addr:full":"84 Hudrake, Haslingden Rossendale Lancashire BB4 5AF",
    "addr:housenumber":"84",
    "addr:postcode":"bb4 5af",
    "addr:street":"Hudrake",
    "iso:country":"GB",
    "sg:address":"84 Hudrake, Haslingden",
    "sg:city":"Rossendale",
    "sg:classifiers":[
        {
            "category":"Bars & Pubs",
            "type":"Food & Drink"
        }
    ],
    "sg:phone":"+44 1706 214021",
    "sg:postcode":"BB4 5AF",
    "sg:province":"Lancashire",
    "sg:tags":[
        "pubs",
        "inn"
    ],
    "wof:name":"The Griffin Inn",
    "wof:placetype":"venue"
},
  "geometry": {"coordinates":[-2.325899,53.709122],"type":"Point"}
}