{
  "type": "Feature",
  "properties": {
    "addr:full":"426 High Street Winsford Cheshire CW7 2DS",
    "addr:housenumber":"426",
    "addr:postcode":"cw7 2ds",
    "addr:street":"High Street",
    "iso:country":"GB",
    "sg:address":"426 High Street",
    "sg:city":"Winsford",
    "sg:classifiers":[
        {
            "category":"Insurance",
            "subcategory":"Insurance Agent",
            "type":"Services"
        }
    ],
    "sg:phone":"+44 1606 863400",
    "sg:postcode":"CW7 2DS",
    "sg:province":"Cheshire",
    "wof:name":"Premier Insurance Centre Ltd.",
    "wof:placetype":"venue"
},
  "geometry": {"coordinates":[-2.534911,53.191212],"type":"Point"}
}