{
  "type": "Feature",
  "properties": {
    "iso:country":"GB",
    "sg:address":"Stilebrridge Boarding Kennels, Whitehouse Farm",
    "sg:city":"Maidstone",
    "sg:classifiers":[
        {
            "category":"Transit Center",
            "subcategory":"Passenger",
            "type":"Transportation"
        }
    ],
    "sg:phone":"+44 1622 746280",
    "sg:postcode":"ME17 4DE",
    "sg:province":"Kent",
    "sg:tags":[
        "boarding",
        "kennel",
        "catteries"
    ],
    "wof:name":"Supeter (Svn) Ltd.",
    "wof:placetype":"venue"
},
  "geometry": {"coordinates":[0.522823,51.20789],"type":"Point"}
}