{
  "type": "Feature",
  "properties": {
    "addr:full":"13 Breach Road Grays Essex RM20 3NR",
    "addr:housenumber":"13",
    "addr:postcode":"rm20 3nr",
    "addr:street":"Breach Road",
    "iso:country":"GB",
    "sg:address":"13 Breach Road",
    "sg:city":"Grays",
    "sg:classifiers":[
        {
            "category":"Shopping",
            "type":"Retail Goods"
        }
    ],
    "sg:phone":"+44 1708 861827",
    "sg:postcode":"RM20 3NR",
    "sg:province":"Essex",
    "sg:tags":[
        "part",
        "accessory"
    ],
    "wof:name":"Big Boys Toys",
    "wof:placetype":"venue"
},
  "geometry": {"coordinates":[0.271964,51.475372],"type":"Point"}
}