{
  "type": "Feature",
  "properties": {
    "iso:country":"GB",
    "sg:address":"112 Street Lane, Denby, Ripley",
    "sg:city":"Derby",
    "sg:classifiers":[
        {
            "category":"Freight",
            "type":"Transportation"
        }
    ],
    "sg:phone":"+44 1773 512327",
    "sg:postcode":"DE5 8NF",
    "sg:province":"Derbyshire",
    "sg:tags":[
        "haulage",
        "road"
    ],
    "wof:name":"R H Cottam Haulage Contractors",
    "wof:placetype":"venue"
},
  "geometry": {"coordinates":[-1.425777,53.025291],"type":"Point"}
}