{
  "type": "Feature",
  "properties": {
    "addr:full":"Stonyhill, 313a Liverpool Road Southport Lancashire PR8 3DE",
    "addr:housenumber":"313a",
    "addr:postcode":"pr8 3de",
    "addr:street":"Stonyhill;Liverpool Road",
    "iso:country":"GB",
    "sg:address":"Stonyhill, 313a Liverpool Road",
    "sg:city":"Southport",
    "sg:classifiers":[
        {
            "category":"Organizations",
            "subcategory":"Professional Association",
            "type":"Services"
        }
    ],
    "sg:postcode":"PR8 3DE",
    "sg:province":"Lancashire",
    "sg:tags":[
        "institute"
    ],
    "wof:name":"The Slurry Surfacing Contractors Associa",
    "wof:placetype":"venue"
},
  "geometry": {"coordinates":[-3.006304,53.647915],"type":"Point"}
}