{
  "type": "Feature",
  "properties": {
    "addr:full":"39 Foxhall Road Blackpool Lancashire FY1 5AD",
    "addr:housenumber":"39",
    "addr:postcode":"fy1 5ad",
    "addr:street":"Foxhall Road",
    "iso:country":"GB",
    "sg:address":"39 Foxhall Road",
    "sg:city":"Blackpool",
    "sg:classifiers":[
        {
            "category":"Community Center",
            "subcategory":"Senior",
            "type":"Public Place"
        },
        {
            "category":"Professional",
            "subcategory":"Business Services",
            "type":"Services"
        }
    ],
    "sg:phone":"+44 1253 620454",
    "sg:postcode":"FY1 5AD",
    "sg:province":"Lancashire",
    "sg:tags":[
        "operator",
        "stall",
        "market"
    ],
    "wof:name":"T W Jeffries",
    "wof:placetype":"venue"
},
  "geometry": {"coordinates":[-3.055218,53.809986],"type":"Point"}
}