{
  "type": "Feature",
  "properties": {
    "addr:full":"The Neighbourhood Centre, 44a Sydenham Road London Greater London SE26 5AX",
    "addr:housenumber":"44a",
    "addr:postcode":"se26 5ax",
    "addr:street":"Sydenham Road",
    "iso:country":"GB",
    "sg:address":"The Neighbourhood Centre, 44a Sydenham Road",
    "sg:city":"London",
    "sg:classifiers":[
        {
            "category":"Organizations",
            "subcategory":"Non-profit Organization",
            "type":"Services"
        }
    ],
    "sg:postcode":"SE26 5AX",
    "sg:province":"Greater London",
    "sg:tags":[
        "organisation",
        "voluntary",
        "charity"
    ],
    "wof:name":"Shaiba Age Care",
    "wof:placetype":"venue"
},
  "geometry": {"coordinates":[-0.051268,51.425987],"type":"Point"}
}