{
  "type": "Feature",
  "properties": {
    "addr:full":"152 Northgate Hartlepool Durham TS24 0EJ",
    "addr:housenumber":"152",
    "addr:postcode":"ts24 0ej",
    "addr:street":"Northgate",
    "iso:country":"GB",
    "sg:address":"152 Northgate",
    "sg:city":"Hartlepool",
    "sg:classifiers":[
        {
            "category":"Shopping",
            "subcategory":"Thrift Store",
            "type":"Retail Goods"
        }
    ],
    "sg:postcode":"TS24 0EJ",
    "sg:province":"Durham",
    "sg:tags":[
        "shop",
        "charity"
    ],
    "wof:name":"Hartlepool & District Hospice Shop",
    "wof:placetype":"venue"
},
  "geometry": {"coordinates":[-1.192588,54.701214],"type":"Point"}
}