{
  "type": "Feature",
  "properties": {
    "iso:country":"GB",
    "sg:address":"Wouldham Road",
    "sg:city":"Grays",
    "sg:classifiers":[
        {
            "category":"Freight",
            "type":"Transportation"
        }
    ],
    "sg:phone":"+44 1375 391919",
    "sg:postcode":"RM20 4XQ",
    "sg:province":"Essex",
    "sg:tags":[
        "forwarders"
    ],
    "wof:name":"Premier Freight Services Ltd.",
    "wof:placetype":"venue"
},
  "geometry": {"coordinates":[0.307065,51.477184],"type":"Point"}
}