{
  "type": "Feature",
  "properties": {
    "iso:country":"GB",
    "sg:address":"Cams Hall, Cams Hill",
    "sg:city":"Fareham",
    "sg:classifiers":[
        {
            "category":"Professional",
            "subcategory":"Computer Services",
            "type":"Services"
        }
    ],
    "sg:phone":"+44 1329 233400",
    "sg:postcode":"PO16 8AB",
    "sg:province":"Hampshire",
    "sg:tags":[
        "consultant"
    ],
    "wof:name":"Lava Systems Europe Ltd",
    "wof:placetype":"venue"
},
  "geometry": {"coordinates":[-1.174099,50.852734],"type":"Point"}
}