{
  "type": "Feature",
  "properties": {
    "addr:full":"Horns Farm, Chester Road, Helsby Warrington Cheshire WA6 0JF",
    "addr:postcode":"wa6 0jf",
    "addr:street":"Horns;Chester Road",
    "iso:country":"GB",
    "sg:address":"Horns Farm, Chester Road, Helsby",
    "sg:city":"Warrington",
    "sg:classifiers":[
        {
            "category":"Sports & Exercise",
            "subcategory":"Tennis Court",
            "type":"Entertainment"
        }
    ],
    "sg:phone":"+44 1928 726328",
    "sg:postcode":"WA6 0JF",
    "sg:province":"Cheshire",
    "sg:tags":[
        "breakdown",
        "recovery"
    ],
    "wof:name":"Frodsham Rescue Services",
    "wof:placetype":"venue"
},
  "geometry": {"coordinates":[-2.7687609196,53.2743034363],"type":"Point"}
}