{
  "type": "Feature",
  "properties": {
    "addr:full":"Derby Road Belper Derbyshire DE56 0RA",
    "addr:postcode":"de56 0ra",
    "addr:street":"Derby Road",
    "iso:country":"GB",
    "sg:address":"Derby Road",
    "sg:city":"Belper",
    "sg:classifiers":[
        {
            "category":"Fast Food",
            "type":"Food & Drink"
        },
        {
            "category":"Retail",
            "subcategory":"Event Space",
            "type":"Services"
        }
    ],
    "sg:phone":"+44 1332 841423",
    "sg:postcode":"DE56 0RA",
    "sg:province":"Derbyshire",
    "sg:tags":[
        "function",
        "away",
        "take",
        "room"
    ],
    "wof:name":"Nealies Private Function Room",
    "wof:placetype":"venue"
},
  "geometry": {"coordinates":[-1.442804,53.00824],"type":"Point"}
}