{
  "type": "Feature",
  "properties": {
    "iso:country":"GB",
    "sg:address":"Nansen Village, 21 Woodside Avenue",
    "sg:city":"London",
    "sg:classifiers":[
        {
            "category":"Organizations",
            "subcategory":"Community Association",
            "type":"Services"
        }
    ],
    "sg:phone":"+44 20 8445 8644",
    "sg:postcode":"N12 8AQ",
    "sg:province":"Greater London",
    "sg:tags":[
        "society",
        "housing"
    ],
    "wof:name":"Barnet Overseas Student Housing Association Ltd.",
    "wof:placetype":"venue"
},
  "geometry": {"coordinates":[-0.18121,51.619541],"type":"Point"}
}