{
  "type": "Feature",
  "properties": {
    "addr:full":"Fourth Floor, Centre Heights, 137 Finchley Rd London Greater London NW3 6JG",
    "addr:housenumber":"137",
    "addr:postcode":"nw3 6jg",
    "addr:street":"Heights;Finchley Rd",
    "iso:country":"GB",
    "sg:address":"Fourth Floor, Centre Heights, 137 Finchley Rd",
    "sg:city":"London",
    "sg:classifiers":[
        {
            "category":"Fast Food",
            "type":"Food & Drink"
        }
    ],
    "sg:postcode":"NW3 6JG",
    "sg:province":"Greater London",
    "sg:tags":[
        "away",
        "take"
    ],
    "wof:name":"Crown Restaurants Ltd",
    "wof:placetype":"venue"
},
  "geometry": {"coordinates":[-0.17559,51.543869],"type":"Point"}
}