{
  "type": "Feature",
  "properties": {
    "iso:country":"GB",
    "sg:address":"White Rose Works, 61 Eyre Lane",
    "sg:city":"Sheffield",
    "sg:classifiers":[
        {
            "category":"Home & Garden",
            "subcategory":"Kitchen Supply",
            "type":"Retail Goods"
        }
    ],
    "sg:phone":"+44 114 249 0969",
    "sg:postcode":"S1 3GF",
    "sg:province":"South Yorkshire",
    "sg:tags":[
        "supplier",
        "cutlery"
    ],
    "wof:name":"Chimo Holdings",
    "wof:placetype":"venue"
},
  "geometry": {"coordinates":[-1.4645440578,53.3831100464],"type":"Point"}
}