{
  "type": "Feature",
  "properties": {
    "addr:full":"751 Hessle Road Hull East Riding of Yorkshire HU4 6PJ",
    "addr:housenumber":"751",
    "addr:postcode":"hu4 6pj",
    "addr:street":"Hessle Road",
    "iso:country":"GB",
    "sg:address":"751 Hessle Road",
    "sg:city":"Hull",
    "sg:classifiers":[
        {
            "category":"Professional",
            "type":"Services"
        },
        {
            "category":"Food & Beverages",
            "subcategory":"Bakery",
            "type":"Retail Goods"
        }
    ],
    "sg:phone":"+44 1482 572055",
    "sg:postcode":"HU4 6PJ",
    "sg:province":"East Riding of Yorkshire",
    "sg:tags":[
        "baker",
        "display",
        "maker"
    ],
    "wof:name":"Bakery",
    "wof:placetype":"venue"
},
  "geometry": {"coordinates":[-0.387612,53.732319],"type":"Point"}
}