{
  "type": "Feature",
  "properties": {
    "addr:full":"3 Holt Park Gro, Cookeridge Leeds West Yorkshire LS16 7SW",
    "addr:housenumber":"3",
    "addr:postcode":"ls16 7sw",
    "addr:street":"Holt Park Gro Cookeridge Leeds West",
    "iso:country":"GB",
    "sg:address":"3 Holt Park Gro, Cookeridge",
    "sg:city":"Leeds",
    "sg:classifiers":[
        {
            "category":"Building & Trades",
            "subcategory":"Construction",
            "type":"Services"
        }
    ],
    "sg:phone":"+44 113 226 0352",
    "sg:postcode":"LS16 7SW",
    "sg:province":"West Yorkshire",
    "sg:tags":[
        "decorator",
        "painter"
    ],
    "wof:name":"Bob Rice Painting & Decorating",
    "wof:placetype":"venue"
},
  "geometry": {"coordinates":[-1.599755,53.857262],"type":"Point"}
}