{
  "type": "Feature",
  "properties": {
    "addr:full":"Willow Walk, Commercial Rd Spalding Lincolnshire PE11 1UP",
    "addr:postcode":"pe11 1up",
    "addr:street":"Willow Walk Commercial Rd",
    "iso:country":"GB",
    "sg:address":"Willow Walk, Commercial Rd",
    "sg:city":"Spalding",
    "sg:classifiers":[
        {
            "category":"Retail",
            "subcategory":"Auto Repair",
            "type":"Services"
        }
    ],
    "sg:phone":"+44 1775 724747",
    "sg:postcode":"PE11 1UP",
    "sg:province":"Lincolnshire",
    "sg:tags":[
        "car",
        "servicing",
        "radiator"
    ],
    "wof:name":"Serck Marston",
    "wof:placetype":"venue"
},
  "geometry": {"coordinates":[-0.151488,52.788342],"type":"Point"}
}