{
  "type": "Feature",
  "properties": {
    "addr:full":"Unit 8 Leighton Centre Indust Est Welshpool Shropshire SY21 8HJ",
    "addr:housenumber":"unit 8",
    "addr:postcode":"sy21 8hj",
    "addr:street":"Leighton Centre Indust Est",
    "iso:country":"GB",
    "sg:address":"Unit 8 Leighton Centre Indust Est",
    "sg:city":"Welshpool",
    "sg:classifiers":[
        {
            "category":"Shopping",
            "subcategory":"Gifts & Souvenirs",
            "type":"Retail Goods"
        }
    ],
    "sg:phone":"+44 1938 555514",
    "sg:postcode":"SY21 8HJ",
    "sg:province":"Shropshire",
    "sg:tags":[
        "giftware"
    ],
    "wof:name":"Craftmaker UK Ltd",
    "wof:placetype":"venue"
},
  "geometry": {"coordinates":[-3.1536099911,52.6343307495],"type":"Point"}
}