{
  "type": "Feature",
  "properties": {
    "addr:full":"32 West Hill Road Ryde Isle of Wight PO33 1LQ",
    "addr:housenumber":"32",
    "addr:postcode":"po33 1lq",
    "addr:street":"West Hill Road",
    "iso:country":"GB",
    "sg:address":"32 West Hill Road",
    "sg:city":"Ryde",
    "sg:classifiers":[
        {
            "category":"Building & Trades",
            "subcategory":"Cleaning & Sanitation",
            "type":"Services"
        },
        {
            "category":"Professional",
            "subcategory":"Business Services",
            "type":"Services"
        }
    ],
    "sg:phone":"+44 1983 567725",
    "sg:postcode":"PO33 1LQ",
    "sg:province":"Isle of Wight",
    "sg:tags":[
        "shop",
        "contracting",
        "commercial"
    ],
    "wof:name":"Eric John Buckman",
    "wof:placetype":"venue"
},
  "geometry": {"coordinates":[-1.1506390572,50.7256813049],"type":"Point"}
}