{
  "type": "Feature",
  "properties": {
    "iso:country":"GB",
    "sg:address":"6 Avenue Road",
    "sg:city":"Ilfracombe",
    "sg:classifiers":[
        {
            "category":"Travel",
            "subcategory":"Hotels & Motels",
            "type":"Entertainment"
        }
    ],
    "sg:postcode":"EX34 9AT",
    "sg:province":"Devon",
    "wof:name":"Kinvara Hotel",
    "wof:placetype":"venue"
},
  "geometry": {"coordinates":[-4.12315,51.208981],"type":"Point"}
}