{
  "type": "Feature",
  "properties": {
    "addr:full":"156 Old Milton Road New Milton Hampshire BH25 6EB",
    "addr:housenumber":"156",
    "addr:postcode":"bh25 6eb",
    "addr:street":"Old Milton Road",
    "iso:country":"GB",
    "sg:address":"156 Old Milton Road",
    "sg:city":"New Milton",
    "sg:classifiers":[
        {
            "category":"Manufacturing",
            "subcategory":"Petroleum Products",
            "type":"Manufacturing & Wholesale Goods"
        }
    ],
    "sg:phone":"+44 1425 622855",
    "sg:postcode":"BH25 6EB",
    "sg:province":"Hampshire",
    "sg:tags":[
        "double",
        "glazing"
    ],
    "wof:name":"Thermal Glazing Systems Ltd.",
    "wof:placetype":"venue"
},
  "geometry": {"coordinates":[-1.6621949673,50.748298645],"type":"Point"}
}