{
  "type": "Feature",
  "properties": {
    "addr:full":"Shamblehurst Lane, Hedge End Southampton Hampshire SO30 2FP",
    "addr:postcode":"so30 2fp",
    "addr:street":"Shamblehurst Lane",
    "iso:country":"GB",
    "sg:address":"Shamblehurst Lane, Hedge End",
    "sg:city":"Southampton",
    "sg:classifiers":[
        {
            "category":"Manufacturing",
            "subcategory":"Buildings",
            "type":"Manufacturing & Wholesale Goods"
        }
    ],
    "sg:phone":"+44 1489 783895",
    "sg:postcode":"SO30 2FP",
    "sg:province":"Hampshire",
    "sg:tags":[
        "mobile",
        "home"
    ],
    "wof:name":"Grange Mobile Home Park",
    "wof:placetype":"venue"
},
  "geometry": {"coordinates":[-1.294555,50.931541],"type":"Point"}
}