{
  "type": "Feature",
  "properties": {
    "addr:full":"Stanley Rd, Cheriton Folkestone Kent CT19 4LQ",
    "addr:postcode":"ct19 4lq",
    "addr:street":"Stanley Rd",
    "iso:country":"GB",
    "sg:address":"Stanley Rd, Cheriton",
    "sg:city":"Folkestone",
    "sg:classifiers":[
        {
            "category":"Farming",
            "subcategory":"Dairy Farm",
            "type":"Manufacturing & Wholesale Goods"
        }
    ],
    "sg:phone":"+44 1303 276259",
    "sg:postcode":"CT19 4LQ",
    "sg:province":"Kent",
    "wof:name":"Unigate Dairies Ltd",
    "wof:placetype":"venue"
},
  "geometry": {"coordinates":[1.1419860125,51.0898971558],"type":"Point"}
}