{
  "type": "Feature",
  "properties": {
    "iso:country":"GB",
    "sg:address":"Texaco Petrol Station, 112 Greenlands Rd, Chelmsley Wood",
    "sg:city":"Birmingham",
    "sg:classifiers":[
        {
            "category":"Retail",
            "subcategory":"Auto Repair",
            "type":"Services"
        }
    ],
    "sg:phone":"+44 121 788 1612",
    "sg:postcode":"B37 7XB",
    "sg:province":"West Midlands",
    "sg:tags":[
        "modification",
        "garage"
    ],
    "wof:name":"D J Motors",
    "wof:placetype":"venue"
},
  "geometry": {"coordinates":[-1.7209219933,52.4690284729],"type":"Point"}
}