{
  "type": "Feature",
  "properties": {
    "iso:country":"GB",
    "sg:address":"Unit 10",
    "sg:city":"Ormskirk",
    "sg:classifiers":[
        {
            "category":"Wholesale",
            "subcategory":"Construction Materials",
            "type":"Manufacturing & Wholesale Goods"
        }
    ],
    "sg:postcode":"L40 5TN",
    "sg:province":"Lancashire",
    "sg:tags":[
        "coating",
        "powder"
    ],
    "wof:name":"Burscoug Powder Coatings",
    "wof:placetype":"venue"
},
  "geometry": {"coordinates":[-2.839449,53.59536],"type":"Point"}
}