{
  "type": "Feature",
  "properties": {
    "addr:full":"Victoria House, Victoria Square Llanwrtyd Wells Powys LD5 4SS",
    "addr:postcode":"ld5 4ss",
    "addr:street":"Victoria Square",
    "iso:country":"GB",
    "sg:address":"Victoria House, Victoria Square",
    "sg:city":"Llanwrtyd Wells",
    "sg:classifiers":[
        {
            "category":"Shopping",
            "subcategory":"News",
            "type":"Retail Goods"
        }
    ],
    "sg:phone":"+44 1591 610316",
    "sg:postcode":"LD5 4SS",
    "sg:province":"Powys",
    "sg:tags":[
        "newsagent"
    ],
    "wof:name":"B Jones",
    "wof:placetype":"venue"
},
  "geometry": {"coordinates":[-3.6393969059,52.1066894531],"type":"Point"}
}