{
  "type": "Feature",
  "properties": {
    "iso:country":"GB",
    "sg:address":"The Old Church Studio, Deddington",
    "sg:city":"Banbury",
    "sg:classifiers":[
        {
            "category":"Building & Trades",
            "subcategory":"Electrical",
            "type":"Services"
        }
    ],
    "sg:phone":"+44 1869 337412",
    "sg:postcode":"OX15 0PE",
    "sg:province":"Oxfordshire",
    "sg:tags":[
        "consultant",
        "lighting"
    ],
    "wof:name":"D P A Lighting Consultants",
    "wof:placetype":"venue"
},
  "geometry": {"coordinates":[-1.323404,51.981804],"type":"Point"}
}