{
  "type": "Feature",
  "properties": {
    "addr:full":"107 High Street Dumbarton Argyll and Bute G82 1LF",
    "addr:housenumber":"107",
    "addr:postcode":"g82 1lf",
    "addr:street":"High Street",
    "iso:country":"GB",
    "sg:address":"107 High Street",
    "sg:city":"Dumbarton",
    "sg:classifiers":[
        {
            "category":"Food & Beverages",
            "subcategory":"Liquor & Beverages",
            "type":"Retail Goods"
        }
    ],
    "sg:phone":"+44 1389 767688",
    "sg:postcode":"G82 1LF",
    "sg:province":"Argyll and Bute",
    "sg:tags":[
        "beer",
        "spirit",
        "wines"
    ],
    "wof:name":"Haddows",
    "wof:placetype":"venue"
},
  "geometry": {"coordinates":[-4.571961,55.943489],"type":"Point"}
}