{
  "type": "Feature",
  "properties": {
    "addr:full":"7d George Road Birmingham West Midlands B23 7RJ",
    "addr:housenumber":"7d",
    "addr:postcode":"b23 7rj",
    "addr:street":"George Road",
    "iso:country":"GB",
    "sg:address":"7d George Road",
    "sg:city":"Birmingham",
    "sg:classifiers":[
        {
            "category":"Military Area",
            "subcategory":"Air Force Base",
            "type":"Public Place"
        }
    ],
    "sg:phone":"+44 121 350 8787",
    "sg:postcode":"B23 7RJ",
    "sg:province":"West Midlands",
    "sg:tags":[
        "taxi",
        "hire",
        "private"
    ],
    "wof:name":"Yenton Cars",
    "wof:placetype":"venue"
},
  "geometry": {"coordinates":[-1.857814,52.515141],"type":"Point"}
}