{
  "type": "Feature",
  "properties": {
    "iso:country":"GB",
    "sg:address":"Merlins Studio, Mill Drive",
    "sg:city":"Crowborough",
    "sg:classifiers":[
        {
            "category":"Real Estate",
            "subcategory":"Surveying",
            "type":"Services"
        },
        {
            "category":"Real Estate",
            "subcategory":"Architect",
            "type":"Services"
        }
    ],
    "sg:phone":"+44 1892 665535",
    "sg:postcode":"TN6 2RR",
    "sg:province":"East Sussex",
    "sg:tags":[
        "building",
        "surveyor",
        "architectural"
    ],
    "sg:website":"http://www.euronet.nl",
    "wof:name":"James & Coombs Associates",
    "wof:placetype":"venue"
},
  "geometry": {"coordinates":[0.171893,51.053196],"type":"Point"}
}