{
  "type": "Feature",
  "properties": {
    "addr:full":"173 Sutton Road, Mile Oak Tamworth Staffordshire B78 3PF",
    "addr:housenumber":"173",
    "addr:postcode":"b78 3pf",
    "addr:street":"Sutton Road",
    "iso:country":"GB",
    "sg:address":"173 Sutton Road, Mile Oak",
    "sg:city":"Tamworth",
    "sg:classifiers":[
        {
            "category":"Building & Trades",
            "subcategory":"Plumbing",
            "type":"Services"
        }
    ],
    "sg:phone":"+44 1827 284927",
    "sg:postcode":"B78 3PF",
    "sg:province":"Staffordshire",
    "sg:tags":[
        "heating"
    ],
    "wof:name":"Indexcall",
    "wof:placetype":"venue"
},
  "geometry": {"coordinates":[-1.739974,52.614468],"type":"Point"}
}