{
  "type": "Feature",
  "properties": {
    "addr:full":"Hellihole Road Stromness Orkney Islands KW16 3DY",
    "addr:postcode":"kw16 3dy",
    "addr:street":"Hellihole Road",
    "iso:country":"GB",
    "sg:address":"Hellihole Road",
    "sg:city":"Stromness",
    "sg:classifiers":[
        {
            "category":"Travel",
            "subcategory":"Hotels & Motels",
            "type":"Entertainment"
        }
    ],
    "sg:postcode":"KW16 3DY",
    "sg:province":"Orkney Islands",
    "wof:name":"M & S Tait",
    "wof:placetype":"venue"
},
  "geometry": {"coordinates":[-3.3025000095,58.9601554871],"type":"Point"}
}