{
  "type": "Feature",
  "properties": {
    "addr:full":"Grosvenor Gardens House, 35-37 Grosvenor Gardens London Greater London SW1W 0BY",
    "addr:housenumber":"35-37",
    "addr:postcode":"sw1w 0by",
    "addr:street":"Grosvenor;Grosvenor Gardens",
    "iso:country":"GB",
    "sg:address":"Grosvenor Gardens House, 35-37 Grosvenor Gardens",
    "sg:city":"London",
    "sg:classifiers":[
        {
            "category":"Professional",
            "subcategory":"Accounting & Tax Preparation",
            "type":"Services"
        }
    ],
    "sg:postcode":"SW1W 0BY",
    "sg:province":"Greater London",
    "sg:tags":[
        "accountant"
    ],
    "wof:name":"Helmore Helmore & Co.",
    "wof:placetype":"venue"
},
  "geometry": {"coordinates":[-0.14535,51.496948],"type":"Point"}
}