{
  "type": "Feature",
  "properties": {
    "addr:full":"209 Honeydown Cottages, Northchapel Petworth West Sussex GU28 9JD",
    "addr:housenumber":"209",
    "addr:postcode":"gu28 9jd",
    "addr:street":"Honeydown",
    "iso:country":"GB",
    "sg:address":"209 Honeydown Cottages, Northchapel",
    "sg:city":"Petworth",
    "sg:classifiers":[
        {
            "category":"Building & Trades",
            "subcategory":"Construction",
            "type":"Services"
        }
    ],
    "sg:phone":"+44 1428 707106",
    "sg:postcode":"GU28 9JD",
    "sg:province":"West Sussex",
    "sg:tags":[
        "builder"
    ],
    "wof:name":"Marshall Construction",
    "wof:placetype":"venue"
},
  "geometry": {"coordinates":[-0.644059,51.055706],"type":"Point"}
}