{
  "type": "Feature",
  "properties": {
    "addr:full":"Independent House 54 Larkshall, Road, Chingford London Greater London E4 6PD",
    "addr:housenumber":"54",
    "addr:postcode":"e4 6pd",
    "addr:street":"Larkshall Road",
    "iso:country":"GB",
    "sg:address":"Independent House 54 Larkshall, Road, Chingford",
    "sg:city":"London",
    "sg:classifiers":[
        {
            "category":"Wholesale",
            "subcategory":"Music Publishers",
            "type":"Manufacturing & Wholesale Goods"
        }
    ],
    "sg:postcode":"E4 6PD",
    "sg:province":"Greater London",
    "wof:name":"Independent Music Group Ltd",
    "wof:placetype":"venue"
},
  "geometry": {"coordinates":[0.002611,51.625053],"type":"Point"}
}