{
  "type": "Feature",
  "properties": {
    "iso:country":"GB",
    "sg:address":"St Chads School, St Chads Road",
    "sg:city":"Tilbury",
    "sg:classifiers":[
        {
            "category":"Government",
            "subcategory":"Office",
            "type":"Public Place"
        }
    ],
    "sg:phone":"+44 1375 851367",
    "sg:postcode":"RM18 8LJ",
    "sg:province":"Essex",
    "sg:tags":[
        "education",
        "agency",
        "authority"
    ],
    "wof:name":"Tilbury Family Centre",
    "wof:placetype":"venue"
},
  "geometry": {"coordinates":[0.4161599874,51.4813728333],"type":"Point"}
}