{
  "type": "Feature",
  "properties": {
    "addr:full":"17 Cricklade St Cirencester Gloucestershire GL7 1HY",
    "addr:housenumber":"17",
    "addr:postcode":"gl7 1hy",
    "addr:street":"Cricklade St",
    "iso:country":"GB",
    "sg:address":"17 Cricklade St",
    "sg:city":"Cirencester",
    "sg:classifiers":[
        {
            "category":"Shopping",
            "subcategory":"Shoes",
            "type":"Retail Goods"
        }
    ],
    "sg:phone":"+44 1285 658174",
    "sg:postcode":"GL7 1HY",
    "sg:province":"Gloucestershire",
    "wof:name":"Gullivers",
    "wof:placetype":"venue"
},
  "geometry": {"coordinates":[-1.967909,51.716564],"type":"Point"}
}