{
  "type": "Feature",
  "properties": {
    "addr:full":"8 St. Marys Place Newcastle Upon Tyne Tyne and Wear NE1 7PG",
    "addr:housenumber":"8",
    "addr:postcode":"ne1 7pg",
    "addr:street":"St. Marys Place",
    "iso:country":"GB",
    "sg:address":"8 St. Marys Place",
    "sg:city":"Newcastle Upon Tyne",
    "sg:classifiers":[
        {
            "category":"Professional",
            "subcategory":"Art Services",
            "type":"Services"
        }
    ],
    "sg:phone":"+44 191 261 5121",
    "sg:postcode":"NE1 7PG",
    "sg:province":"Tyne and Wear",
    "sg:tags":[
        "photographer"
    ],
    "wof:name":"Fuji Image Service",
    "wof:placetype":"venue"
},
  "geometry": {"coordinates":[-1.6124099493,54.9777793884],"type":"Point"}
}