{
  "type": "Feature",
  "properties": {
    "iso:country":"GB",
    "sg:address":"1 South Street, Wendover",
    "sg:city":"Aylesbury",
    "sg:classifiers":[
        {
            "category":"Shopping",
            "subcategory":"Antiques",
            "type":"Retail Goods"
        }
    ],
    "sg:postcode":"HP22 6EF",
    "sg:province":"Buckinghamshire",
    "wof:name":"Wendover Antiques",
    "wof:placetype":"venue"
},
  "geometry": {"coordinates":[-0.744282,51.761696],"type":"Point"}
}