{
  "type": "Feature",
  "properties": {
    "iso:country":"GB",
    "sg:address":"1 Station Buildings, Catford Road",
    "sg:city":"London",
    "sg:classifiers":[
        {
            "category":"Insurance",
            "subcategory":"Insurance Agent",
            "type":"Services"
        }
    ],
    "sg:phone":"+44 20 8314 1551",
    "sg:postcode":"SE6 4QZ",
    "sg:province":"Greater London",
    "wof:name":"Swinton",
    "wof:placetype":"venue"
},
  "geometry": {"coordinates":[-0.02363,51.444691],"type":"Point"}
}