{
  "type": "Feature",
  "properties": {
    "addr:full":"6 & 7 Worcester Court, Mannesmann Close, Llansamlet Enterprise Zone Swansea Neath Port Talbot SA7 9AH",
    "addr:housenumber":"6 & 7",
    "addr:postcode":"sa7 9ah",
    "addr:street":"Worcester Court Mannesmann Close",
    "iso:country":"GB",
    "sg:address":"6 & 7 Worcester Court, Mannesmann Close, Llansamlet Enterprise Zone",
    "sg:city":"Swansea",
    "sg:classifiers":[
        {
            "category":"Sports & Exercise",
            "subcategory":"Golf",
            "type":"Entertainment"
        }
    ],
    "sg:phone":"+44 1792 700364",
    "sg:postcode":"SA7 9AH",
    "sg:province":"Neath Port Talbot",
    "sg:tags":[
        "equipment"
    ],
    "wof:name":"Golf King & Ultra Golf",
    "wof:placetype":"venue"
},
  "geometry": {"coordinates":[-3.9051399231,51.6591415405],"type":"Point"}
}