{
  "type": "Feature",
  "properties": {
    "addr:full":"Longrock-by-pass Penzance Cornwall TR18 3AR",
    "addr:postcode":"tr18 3ar",
    "iso:country":"GB",
    "sg:address":"Longrock-by-pass",
    "sg:city":"Penzance",
    "sg:classifiers":[
        {
            "category":"Home & Garden",
            "subcategory":"Hardware",
            "type":"Retail Goods"
        }
    ],
    "sg:phone":"+44 1736 350450",
    "sg:postcode":"TR18 3AR",
    "sg:province":"Cornwall",
    "sg:tags":[
        "retailer",
        "diy"
    ],
    "wof:name":"B & Q Diy & Garden Supercentres",
    "wof:placetype":"venue"
},
  "geometry": {"coordinates":[-5.534919,50.119808],"type":"Point"}
}