{
  "type": "Feature",
  "properties": {
    "addr:full":"Little Orchard, Aveton Gifford Kingsbridge Devon TQ7 4NT",
    "addr:postcode":"tq7 4nt",
    "addr:street":"Aveton",
    "iso:country":"GB",
    "sg:address":"Little Orchard, Aveton Gifford",
    "sg:city":"Kingsbridge",
    "sg:classifiers":[
        {
            "category":"Home & Garden",
            "subcategory":"Carpets & Floor Coverings",
            "type":"Retail Goods"
        }
    ],
    "sg:postcode":"TQ7 4NT",
    "sg:province":"Devon",
    "sg:tags":[
        "cleaner",
        "upholstery"
    ],
    "wof:name":"Fineshine",
    "wof:placetype":"venue"
},
  "geometry": {"coordinates":[-3.839934,50.315063],"type":"Point"}
}