{
  "type": "Feature",
  "properties": {
    "iso:country":"GB",
    "sg:address":"6 Wallace Street",
    "sg:city":"Exeter",
    "sg:classifiers":[
        {
            "category":"Professional",
            "subcategory":"Advertising",
            "type":"Services"
        }
    ],
    "sg:phone":"+44 1392 213894",
    "sg:postcode":"EX4 8DB",
    "sg:province":"Devon",
    "wof:name":"The Space Agency",
    "wof:placetype":"venue"
},
  "geometry": {"coordinates":[-3.4908719063,50.7341156006],"type":"Point"}
}