{
  "type": "Feature",
  "properties": {
    "addr:full":"Bissoe Truro Cornwall TR4 8QZ",
    "addr:postcode":"tr4 8qz",
    "addr:street":"Bissoe",
    "iso:country":"GB",
    "sg:address":"Bissoe",
    "sg:city":"Truro",
    "sg:classifiers":[
        {
            "category":"Professional",
            "subcategory":"Management & Consulting",
            "type":"Services"
        }
    ],
    "sg:phone":"+44 1872 865804",
    "sg:postcode":"TR4 8QZ",
    "sg:province":"Cornwall",
    "sg:tags":[
        "consultant",
        "investigation",
        "site"
    ],
    "wof:name":"Jay Mineral Services Ltd.",
    "wof:placetype":"venue"
},
  "geometry": {"coordinates":[-5.1239299774,50.2311782837],"type":"Point"}
}