{
  "type": "Feature",
  "properties": {
    "addr:full":"Saxon Way, Chelmsley Wood Birmingham West Midlands B37 5AY",
    "addr:postcode":"b37 5ay",
    "addr:street":"Saxon Way",
    "iso:country":"GB",
    "sg:address":"Saxon Way, Chelmsley Wood",
    "sg:city":"Birmingham",
    "sg:classifiers":[
        {
            "category":"Retail",
            "subcategory":"Auto Repair",
            "type":"Services"
        }
    ],
    "sg:postcode":"B37 5AY",
    "sg:province":"West Midlands",
    "sg:tags":[
        "engine",
        "car",
        "specialist"
    ],
    "wof:name":"Kingshurst Automotive",
    "wof:placetype":"venue"
},
  "geometry": {"coordinates":[-1.7555650473,52.4834518433],"type":"Point"}
}