{
  "type": "Feature",
  "properties": {
    "addr:full":"6 Sherburn Street, Cawood Selby East Riding of Yorkshire YO8 0SS",
    "addr:housenumber":"6",
    "addr:postcode":"yo8 0ss",
    "addr:street":"Sherburn Street",
    "iso:country":"GB",
    "sg:address":"6 Sherburn Street, Cawood",
    "sg:city":"Selby",
    "sg:classifiers":[
        {
            "category":"Bars & Pubs",
            "type":"Food & Drink"
        }
    ],
    "sg:phone":"+44 1757 268555",
    "sg:postcode":"YO8 0SS",
    "sg:province":"East Riding of Yorkshire",
    "sg:tags":[
        "pubs",
        "inn"
    ],
    "wof:name":"The Bay Horse",
    "wof:placetype":"venue"
},
  "geometry": {"coordinates":[-1.0703459978,53.783908844],"type":"Point"}
}