{
  "type": "Feature",
  "properties": {
    "addr:full":"Unit 103b Northwick Busns Cntr, Blockley Moreton-in-marsh Gloucestershire GL56 9RF",
    "addr:housenumber":"103b",
    "addr:postcode":"gl56 9rf",
    "addr:street":"Northwick Busns Cntr",
    "iso:country":"GB",
    "sg:address":"Unit 103b Northwick Busns Cntr, Blockley",
    "sg:city":"Moreton-in-marsh",
    "sg:classifiers":[
        {
            "category":"Manufacturing",
            "subcategory":"Wood Products",
            "type":"Manufacturing & Wholesale Goods"
        }
    ],
    "sg:phone":"+44 1386 700709",
    "sg:postcode":"GL56 9RF",
    "sg:province":"Gloucestershire",
    "sg:tags":[
        "packaging",
        "crate",
        "pallets"
    ],
    "wof:name":"Northwick Manufacturing",
    "wof:placetype":"venue"
},
  "geometry": {"coordinates":[-1.703281045,51.9897270203],"type":"Point"}
}