{
  "type": "Feature",
  "properties": {
    "iso:country":"GB",
    "sg:address":"129 Highgate Street",
    "sg:city":"Birmingham",
    "sg:classifiers":[
        {
            "category":"Food & Beverages",
            "subcategory":"Meat & Fish",
            "type":"Retail Goods"
        }
    ],
    "sg:phone":"+44 121 440 1705",
    "sg:postcode":"B12 0XR",
    "sg:province":"West Midlands",
    "sg:tags":[
        "butcher"
    ],
    "wof:name":"Bill Cox",
    "wof:placetype":"venue"
},
  "geometry": {"coordinates":[-1.8914630413,52.4655761719],"type":"Point"}
}