{
  "type": "Feature",
  "properties": {
    "iso:country":"GB",
    "sg:address":"11 Selwood Clo, Stanwell",
    "sg:city":"Staines",
    "sg:classifiers":[
        {
            "category":"Professional",
            "subcategory":"Secretarial Services",
            "type":"Services"
        }
    ],
    "sg:phone":"+44 1784 880481",
    "sg:postcode":"TW19 7NU",
    "sg:province":"Berkshire",
    "wof:name":"Selwood Office Services",
    "wof:placetype":"venue"
},
  "geometry": {"coordinates":[-0.487476,51.457035],"type":"Point"}
}