{
  "type": "Feature",
  "properties": {
    "addr:full":"51 Hyndland St Glasgow Glasgow City G11 5QF",
    "addr:housenumber":"51",
    "addr:postcode":"g11 5qf",
    "addr:street":"Hyndland St",
    "iso:country":"GB",
    "sg:address":"51 Hyndland St",
    "sg:city":"Glasgow",
    "sg:classifiers":[
        {
            "category":"Food & Beverages",
            "subcategory":"Bakery",
            "type":"Retail Goods"
        }
    ],
    "sg:postcode":"G11 5QF",
    "sg:province":"Glasgow City",
    "sg:tags":[
        "baker"
    ],
    "wof:name":"Wichmann,Karl,",
    "wof:placetype":"venue"
},
  "geometry": {"coordinates":[-4.302602,55.87215],"type":"Point"}
}