{
  "type": "Feature",
  "properties": {
    "addr:full":"80 Camden High St London Greater London NW1 0LT",
    "addr:housenumber":"80",
    "addr:postcode":"nw1 0lt",
    "addr:street":"Camden High St",
    "iso:country":"GB",
    "sg:address":"80 Camden High St",
    "sg:city":"London",
    "sg:classifiers":[
        {
            "category":"Personal",
            "subcategory":"Beauty Salon",
            "type":"Services"
        }
    ],
    "sg:postcode":"NW1 0LT",
    "sg:province":"Greater London",
    "sg:tags":[
        "unisex",
        "hairdresser"
    ],
    "wof:name":"Robuck Browns Hair Salon",
    "wof:placetype":"venue"
},
  "geometry": {"coordinates":[-0.137744,51.538345],"type":"Point"}
}