{
  "type": "Feature",
  "properties": {
    "addr:full":"Usan House Montrose Aberdeenshire DD10 9SE",
    "addr:postcode":"dd10 9se",
    "iso:country":"GB",
    "sg:address":"Usan House",
    "sg:city":"Montrose",
    "sg:classifiers":[
        {
            "category":"Farming",
            "subcategory":"Farm",
            "type":"Manufacturing & Wholesale Goods"
        }
    ],
    "sg:phone":"+44 1674 673605",
    "sg:postcode":"DD10 9SE",
    "sg:province":"Aberdeenshire",
    "sg:tags":[
        "mixed",
        "crop"
    ],
    "wof:name":"Usan Estate",
    "wof:placetype":"venue"
},
  "geometry": {"coordinates":[-2.484189,56.722439],"type":"Point"}
}