{
  "type": "Feature",
  "properties": {
    "iso:country":"GB",
    "sg:address":"36 Bromsgrove Road, Romsley",
    "sg:city":"Halesowen",
    "sg:classifiers":[
        {
            "category":"Professional",
            "subcategory":"Art Services",
            "type":"Services"
        }
    ],
    "sg:phone":"+44 1562 710566",
    "sg:postcode":"B62 0LF",
    "sg:province":"West Midlands",
    "sg:tags":[
        "photographer"
    ],
    "wof:name":"Robert Hemming",
    "wof:placetype":"venue"
},
  "geometry": {"coordinates":[-2.057917,52.412361],"type":"Point"}
}