{
  "type": "Feature",
  "properties": {
    "addr:full":"Middlefield Rd, Sawtry Huntingdon Bedfordshire PE28 5SH",
    "addr:postcode":"pe28 5sh",
    "addr:street":"Middlefield Rd",
    "iso:country":"GB",
    "sg:address":"Middlefield Rd, Sawtry",
    "sg:city":"Huntingdon",
    "sg:classifiers":[
        {
            "category":"Education",
            "subcategory":"School",
            "type":"Public Place"
        }
    ],
    "sg:phone":"+44 1487 830204",
    "sg:postcode":"PE28 5SH",
    "sg:province":"Bedfordshire",
    "sg:tags":[
        "local",
        "authority"
    ],
    "wof:name":"Sawtry County Junior School",
    "wof:placetype":"venue"
},
  "geometry": {"coordinates":[-0.275309,52.436729],"type":"Point"}
}