{
  "type": "Feature",
  "properties": {
    "addr:full":"Wildgates, Underhill, Kilkhampton Bude Cornwall EX23 9QP",
    "addr:postcode":"ex23 9qp",
    "addr:street":"Wildgates",
    "iso:country":"GB",
    "sg:address":"Wildgates, Underhill, Kilkhampton",
    "sg:city":"Bude",
    "sg:classifiers":[
        {
            "category":"Shopping",
            "subcategory":"Books",
            "type":"Retail Goods"
        }
    ],
    "sg:phone":"+44 1288 321591",
    "sg:postcode":"EX23 9QP",
    "sg:province":"Cornwall",
    "sg:tags":[
        "maps",
        "globe",
        "chart"
    ],
    "wof:name":"Mr A M Dustan",
    "wof:placetype":"venue"
},
  "geometry": {"coordinates":[-4.4843740463,50.873714447],"type":"Point"}
}