{
  "type": "Feature",
  "properties": {
    "iso:country":"GB",
    "sg:address":"Newton Rd",
    "sg:city":"Wick",
    "sg:classifiers":[
        {
            "category":"Professional",
            "subcategory":"Engineering",
            "type":"Services"
        },
        {
            "category":"Communications",
            "type":"Services"
        }
    ],
    "sg:phone":"+44 1955 602271",
    "sg:postcode":"KW1 5LT",
    "sg:province":"Highland",
    "sg:tags":[
        "engineer",
        "electrical",
        "telecommunication",
        "contractor"
    ],
    "wof:name":"Bt Maritime Radio Services",
    "wof:placetype":"venue"
},
  "geometry": {"coordinates":[-3.0974450111,58.4397163391],"type":"Point"}
}