{
  "type": "Feature",
  "properties": {
    "addr:full":"P O Box 224 Newport Newport NP20 4YE",
    "addr:housenumber":"224",
    "addr:postcode":"np20 4ye",
    "addr:street":"P O Box",
    "iso:country":"GB",
    "sg:address":"P O Box 224",
    "sg:city":"Newport",
    "sg:classifiers":[
        {
            "category":"Shopping",
            "type":"Retail Goods"
        }
    ],
    "sg:phone":"+44 1633 262155",
    "sg:postcode":"NP20 4YE",
    "sg:province":"Newport",
    "sg:tags":[
        "bag"
    ],
    "wof:name":"Stokes Packaging",
    "wof:placetype":"venue"
},
  "geometry": {"coordinates":[-3.00605,51.58292],"type":"Point"}
}