{
  "type": "Feature",
  "properties": {
    "iso:country":"GB",
    "sg:address":"2 King Street",
    "sg:city":"London",
    "sg:classifiers":[
        {
            "category":"Banks & Credit Unions",
            "subcategory":"Investment Brokerage",
            "type":"Services"
        }
    ],
    "sg:postcode":"SW1Y 6QL",
    "sg:province":"Greater London",
    "wof:name":"Rupert Loewenstein Ltd.",
    "wof:placetype":"venue"
},
  "geometry": {"coordinates":[-0.137236,51.506657],"type":"Point"}
}