{
  "type": "Feature",
  "properties": {
    "addr:full":"Overton Lane, Burntwood Walsall Staffordshire WS7 0LL",
    "addr:postcode":"ws7 0ll",
    "addr:street":"Overton Lane",
    "iso:country":"GB",
    "sg:address":"Overton Lane, Burntwood",
    "sg:city":"Walsall",
    "sg:classifiers":[
        {
            "category":"Retail",
            "subcategory":"Auto Repair",
            "type":"Services"
        }
    ],
    "sg:postcode":"WS7 0LL",
    "sg:province":"Staffordshire",
    "sg:tags":[
        "modification",
        "garage"
    ],
    "wof:name":"Mile Oak Garage",
    "wof:placetype":"venue"
},
  "geometry": {"coordinates":[-1.901369,52.671726],"type":"Point"}
}