{
  "type": "Feature",
  "properties": {
    "iso:country":"GB",
    "sg:address":"380 Lwr Falinge",
    "sg:city":"Rochdale",
    "sg:classifiers":[
        {
            "category":"Food & Beverages",
            "subcategory":"Meat & Fish",
            "type":"Retail Goods"
        }
    ],
    "sg:postcode":"OL12 6RE",
    "sg:province":"Lancashire",
    "sg:tags":[
        "butcher"
    ],
    "wof:name":"Chrimes,E & M,",
    "wof:placetype":"venue"
},
  "geometry": {"coordinates":[-2.162766,53.619007],"type":"Point"}
}