{
  "type": "Feature",
  "properties": {
    "iso:country":"GB",
    "sg:address":"16a Salisbury Drive, Prestwich",
    "sg:city":"Manchester",
    "sg:classifiers":[
        {
            "category":"Retail",
            "subcategory":"Storage",
            "type":"Services"
        }
    ],
    "sg:phone":"+44 161 773 9661",
    "sg:postcode":"M25 0HU",
    "sg:province":"Greater Manchester",
    "sg:tags":[
        "household",
        "removal"
    ],
    "wof:name":"Great Rate Removals",
    "wof:placetype":"venue"
},
  "geometry": {"coordinates":[-2.266127,53.520367],"type":"Point"}
}