{
  "type": "Feature",
  "properties": {
    "iso:country":"GB",
    "sg:address":"P O Box 457",
    "sg:city":"Luton",
    "sg:classifiers":[
        {
            "category":"Shopping",
            "subcategory":"Stationery & Office Supplies",
            "type":"Retail Goods"
        }
    ],
    "sg:postcode":"LU1 4ND",
    "sg:province":"Bedfordshire",
    "sg:tags":[
        "equipment",
        "printing",
        "mech"
    ],
    "wof:name":"Creo Products (Uk) Imagesetters Manufact",
    "wof:placetype":"venue"
},
  "geometry": {"coordinates":[-0.439539,51.859329],"type":"Point"}
}