{
  "type": "Feature",
  "properties": {
    "addr:full":"Caeau Brychion, Penrallt Pwllheli Gwynedd LL53 5UE",
    "addr:postcode":"ll53 5ue",
    "iso:country":"GB",
    "sg:address":"Caeau Brychion, Penrallt",
    "sg:city":"Pwllheli",
    "sg:classifiers":[
        {
            "category":"Farming",
            "subcategory":"Livestock Farm",
            "type":"Manufacturing & Wholesale Goods"
        }
    ],
    "sg:phone":"+44 1758 612642",
    "sg:postcode":"LL53 5UE",
    "sg:province":"Gwynedd",
    "sg:tags":[
        "others"
    ],
    "wof:name":"J G Williams",
    "wof:placetype":"venue"
},
  "geometry": {"coordinates":[-4.4143137932,52.8898468018],"type":"Point"}
}