{
  "type": "Feature",
  "properties": {
    "addr:full":"Fifth Floor, 15/16 New Burlington St, London Greater London W1X 2PY",
    "addr:housenumber":"15 / 16",
    "addr:postcode":"w1x 2py",
    "addr:street":"New Burlington St",
    "iso:country":"GB",
    "sg:address":"Fifth Floor, 15/16 New Burlington St,",
    "sg:city":"London",
    "sg:classifiers":[
        {
            "category":"Real Estate",
            "subcategory":"Real Estate Agent",
            "type":"Services"
        }
    ],
    "sg:postcode":"W1X 2PY",
    "sg:province":"Greater London",
    "wof:name":"Adagio Properties Ltd",
    "wof:placetype":"venue"
},
  "geometry": {"coordinates":[-0.1409540027,51.5117988586],"type":"Point"}
}