{
  "type": "Feature",
  "properties": {
    "iso:country":"GB",
    "sg:address":"293 Stanley Road",
    "sg:city":"Bootle",
    "sg:classifiers":[
        {
            "category":"Sports & Exercise",
            "subcategory":"Sports Center",
            "type":"Entertainment"
        }
    ],
    "sg:phone":"+44 151 933 1611",
    "sg:postcode":"L20 3LQ",
    "sg:province":"Merseyside",
    "sg:tags":[
        "shop",
        "good"
    ],
    "wof:name":"Dirty Sports Ltd.",
    "wof:placetype":"venue"
},
  "geometry": {"coordinates":[-2.990646,53.450489],"type":"Point"}
}