{
  "type": "Feature",
  "properties": {
    "addr:full":"The Rocks Studio, Plump Hill Mitcheldean Gloucestershire GL17 0HF",
    "addr:postcode":"gl17 0hf",
    "iso:country":"GB",
    "sg:address":"The Rocks Studio, Plump Hill",
    "sg:city":"Mitcheldean",
    "sg:classifiers":[
        {
            "category":"Communications",
            "subcategory":"Film & Video Production",
            "type":"Services"
        },
        {
            "category":"Communications",
            "type":"Services"
        }
    ],
    "sg:phone":"+44 1594 544382",
    "sg:postcode":"GL17 0HF",
    "sg:province":"Gloucestershire",
    "sg:tags":[
        "tv",
        "broadcasting",
        "studio"
    ],
    "wof:name":"Belfocal Video Production",
    "wof:placetype":"venue"
},
  "geometry": {"coordinates":[-2.4890880585,51.8653831482],"type":"Point"}
}