{
  "type": "Feature",
  "properties": {
    "addr:full":"Eastney Rd, Milton Park Southsea Hampshire PO4 8PR",
    "addr:postcode":"po4 8pr",
    "addr:street":"Eastney Rd;Park",
    "iso:country":"GB",
    "sg:address":"Eastney Rd, Milton Park",
    "sg:city":"Southsea",
    "sg:classifiers":[
        {
            "category":"Autos & Motor Vehicles",
            "subcategory":"Automobile Sales",
            "type":"Retail Goods"
        }
    ],
    "sg:phone":"+44 23 9283 8838",
    "sg:postcode":"PO4 8PR",
    "sg:province":"Hampshire",
    "sg:tags":[
        "car"
    ],
    "wof:name":"White House Motor Co",
    "wof:placetype":"venue"
},
  "geometry": {"coordinates":[-1.056276,50.791851],"type":"Point"}
}