{
  "type": "Feature",
  "properties": {
    "addr:full":"1 Damon House, Sylvan Avenue London Greater London NW7 2JT",
    "addr:housenumber":"1",
    "addr:postcode":"nw7 2jt",
    "addr:street":"Damon House Sylvan Avenue",
    "iso:country":"GB",
    "sg:address":"1 Damon House, Sylvan Avenue",
    "sg:city":"London",
    "sg:classifiers":[
        {
            "category":"Professional",
            "subcategory":"Computer Services",
            "type":"Services"
        }
    ],
    "sg:postcode":"NW7 2JT",
    "sg:province":"Greater London",
    "sg:tags":[
        "system",
        "software"
    ],
    "wof:name":"Halfteck Associates Ltd",
    "wof:placetype":"venue"
},
  "geometry": {"coordinates":[-0.24765,51.61264],"type":"Point"}
}