{
  "type": "Feature",
  "properties": {
    "addr:full":"Widemarsh Street Hereford Herefordshire HR4 9EW",
    "addr:postcode":"hr4 9ew",
    "addr:street":"Widemarsh Street",
    "iso:country":"GB",
    "sg:address":"Widemarsh Street",
    "sg:city":"Hereford",
    "sg:classifiers":[
        {
            "category":"Transit Center",
            "subcategory":"Freight",
            "type":"Transportation"
        }
    ],
    "sg:postcode":"HR4 9EW",
    "sg:province":"Herefordshire",
    "sg:tags":[
        "shop",
        "craft",
        "centre"
    ],
    "wof:name":"Dale Kupris",
    "wof:placetype":"venue"
},
  "geometry": {"coordinates":[-2.7140328884,52.0634803772],"type":"Point"}
}