{
  "type": "Feature",
  "properties": {
    "addr:full":"65a-67 The Cut London Greater London SE1 8LL",
    "addr:housenumber":"65a-67",
    "addr:postcode":"se1 8ll",
    "addr:street":"The Cut",
    "iso:country":"GB",
    "sg:address":"65a-67 The Cut",
    "sg:city":"London",
    "sg:classifiers":[
        {
            "category":"Food & Beverages",
            "subcategory":"Groceries & Convenience Stores",
            "type":"Retail Goods"
        }
    ],
    "sg:phone":"+44 20 7928 6213",
    "sg:postcode":"SE1 8LL",
    "sg:province":"Greater London",
    "wof:name":"Supercut Mini-Market",
    "wof:placetype":"venue"
},
  "geometry": {"coordinates":[-0.1078950018,51.5027236938],"type":"Point"}
}