{
  "type": "Feature",
  "properties": {
    "iso:country":"GB",
    "sg:address":"5 Rastrick Close",
    "sg:city":"Burgess Hill",
    "sg:classifiers":[
        {
            "category":"Social Services",
            "subcategory":"Job Training",
            "type":"Services"
        }
    ],
    "sg:phone":"+44 1444 243313",
    "sg:postcode":"RH15 9UW",
    "sg:province":"East Sussex",
    "sg:tags":[
        "translator",
        "interpreter"
    ],
    "wof:name":"Amanda Avenell",
    "wof:placetype":"venue"
},
  "geometry": {"coordinates":[-0.143318,50.948669],"type":"Point"}
}