{
  "type": "Feature",
  "properties": {
    "iso:country":"GB",
    "sg:address":"257 Kingstanding Road",
    "sg:city":"Birmingham",
    "sg:classifiers":[
        {
            "category":"Autos & Motor Vehicles",
            "subcategory":"Automobile Sales",
            "type":"Retail Goods"
        }
    ],
    "sg:phone":"+44 121 382 8181",
    "sg:postcode":"B44 8LB",
    "sg:province":"West Midlands",
    "sg:tags":[
        "commercial"
    ],
    "wof:name":"Topvan",
    "wof:placetype":"venue"
},
  "geometry": {"coordinates":[-1.885514,52.540897],"type":"Point"}
}