{
  "type": "Feature",
  "properties": {
    "addr:full":"21 Bedford Road, Denton Northampton Buckinghamshire NN7 1DR",
    "addr:housenumber":"21",
    "addr:postcode":"nn7 1dr",
    "addr:street":"Bedford Road",
    "iso:country":"GB",
    "sg:address":"21 Bedford Road, Denton",
    "sg:city":"Northampton",
    "sg:classifiers":[
        {
            "category":"Education",
            "subcategory":"Special Training",
            "type":"Public Place"
        }
    ],
    "sg:phone":"+44 1604 890832",
    "sg:postcode":"NN7 1DR",
    "sg:province":"Buckinghamshire",
    "sg:tags":[
        "school",
        "language"
    ],
    "wof:name":"Clarke Export Services",
    "wof:placetype":"venue"
},
  "geometry": {"coordinates":[-0.799341,52.220345],"type":"Point"}
}