{
  "type": "Feature",
  "properties": {
    "addr:full":"25 Oulder Hill Drive Rochdale Lancashire OL11 5LB",
    "addr:postcode":"ol11 5lb",
    "addr:street":"Hill Drive",
    "iso:country":"GB",
    "sg:address":"25 Oulder Hill Drive",
    "sg:city":"Rochdale",
    "sg:classifiers":[
        {
            "category":"Education",
            "subcategory":"Music School",
            "type":"Public Place"
        }
    ],
    "sg:postcode":"OL11 5LB",
    "sg:province":"Lancashire",
    "sg:tags":[
        "teacher"
    ],
    "wof:name":"R M L Collins",
    "wof:placetype":"venue"
},
  "geometry": {"coordinates":[-2.1879079342,53.613899231],"type":"Point"}
}