{
  "type": "Feature",
  "properties": {
    "iso:country":"GB",
    "sg:address":"Hollins Gro Mill, Hollins Gro Street",
    "sg:city":"Darwen",
    "sg:classifiers":[
        {
            "category":"Structure",
            "subcategory":"Warehouse",
            "type":"Public Place"
        }
    ],
    "sg:phone":"+44 1254 703292",
    "sg:postcode":"BB3 1HG",
    "sg:province":"Lancashire",
    "wof:name":"Hisoms Sheet Metals Ltd.",
    "wof:placetype":"venue"
},
  "geometry": {"coordinates":[-2.473354,53.706551],"type":"Point"}
}