{
  "type": "Feature",
  "properties": {
    "addr:full":"31 Carrington Way Braintree Essex CM7 5LX",
    "addr:housenumber":"31",
    "addr:postcode":"cm7 5lx",
    "addr:street":"Carrington Way",
    "iso:country":"GB",
    "sg:address":"31 Carrington Way",
    "sg:city":"Braintree",
    "sg:classifiers":[
        {
            "category":"Retail",
            "subcategory":"Driving School",
            "type":"Services"
        }
    ],
    "sg:postcode":"CM7 5LX",
    "sg:province":"Essex",
    "wof:name":"Diamond Driving Academy",
    "wof:placetype":"venue"
},
  "geometry": {"coordinates":[0.5552020073,51.901599884],"type":"Point"}
}