{
  "type": "Feature",
  "properties": {
    "iso:country":"GB",
    "sg:address":"Chimney Corner, Ampthill Road, Kempston Hardwick",
    "sg:city":"Bedford",
    "sg:classifiers":[
        {
            "category":"Wholesale",
            "subcategory":"Scrap",
            "type":"Manufacturing & Wholesale Goods"
        }
    ],
    "sg:phone":"+44 1234 851187",
    "sg:postcode":"MK45 3JF",
    "sg:province":"Bedfordshire",
    "sg:tags":[
        "breaker",
        "dismantlers"
    ],
    "wof:name":"Japanese Car Breakers",
    "wof:placetype":"venue"
},
  "geometry": {"coordinates":[-0.48994,52.08588],"type":"Point"}
}