{
  "type": "Feature",
  "properties": {
    "addr:full":"12a Deardengate, Haslingden Rossendale Lancashire BB4 5QJ",
    "addr:housenumber":"12a",
    "addr:postcode":"bb4 5qj",
    "addr:street":"Deardengate",
    "iso:country":"GB",
    "sg:address":"12a Deardengate, Haslingden",
    "sg:city":"Rossendale",
    "sg:classifiers":[
        {
            "category":"Bus Charters",
            "type":"Transportation"
        }
    ],
    "sg:phone":"+44 1706 222200",
    "sg:postcode":"BB4 5QJ",
    "sg:province":"Lancashire",
    "sg:tags":[
        "coach"
    ],
    "wof:name":"Compass Travel",
    "wof:placetype":"venue"
},
  "geometry": {"coordinates":[-2.325899,53.709122],"type":"Point"}
}