{
  "type": "Feature",
  "properties": {
    "iso:country":"GB",
    "sg:address":"Vincent House, 92-93 Edward Street",
    "sg:city":"Birmingham",
    "sg:classifiers":[
        {
            "category":"Organizations",
            "subcategory":"Community Association",
            "type":"Services"
        }
    ],
    "sg:phone":"+44 121 236 7532",
    "sg:postcode":"B1 2RA",
    "sg:province":"West Midlands",
    "sg:tags":[
        "relation",
        "public"
    ],
    "wof:name":"Harrison Cowley Public Relations",
    "wof:placetype":"venue"
},
  "geometry": {"coordinates":[-1.914349,52.48061],"type":"Point"}
}