{
  "type": "Feature",
  "properties": {
    "iso:country":"GB",
    "sg:address":"81-83 Albany Road",
    "sg:city":"Cardiff",
    "sg:classifiers":[
        {
            "category":"Shopping",
            "subcategory":"Pharmacy",
            "type":"Retail Goods"
        }
    ],
    "sg:phone":"+44 29 2049 0442",
    "sg:postcode":"CF24 3LN",
    "sg:province":"Cardiff",
    "sg:tags":[
        "store",
        "drug",
        "outlet"
    ],
    "sg:website":"http://www.superdrug.com",
    "wof:name":"Superdrug Stores Plc",
    "wof:placetype":"venue"
},
  "geometry": {"coordinates":[-3.1677970886,51.4937171936],"type":"Point"}
}