{
  "type": "Feature",
  "properties": {
    "addr:full":"Unit 4 Cofton Road Exeter Devon EX2 8QW",
    "addr:housenumber":"unit 4",
    "addr:postcode":"ex2 8qw",
    "addr:street":"Cofton Road",
    "iso:country":"GB",
    "sg:address":"Unit 4 Cofton Road",
    "sg:city":"Exeter",
    "sg:classifiers":[
        {
            "category":"Manufacturing",
            "subcategory":"Petroleum Products",
            "type":"Manufacturing & Wholesale Goods"
        }
    ],
    "sg:phone":"+44 1392 666670",
    "sg:postcode":"EX2 8QW",
    "sg:province":"Devon",
    "sg:tags":[
        "double",
        "glazing"
    ],
    "wof:name":"Aark Windows",
    "wof:placetype":"venue"
},
  "geometry": {"coordinates":[-3.5202000141,50.7011947632],"type":"Point"}
}