{
  "type": "Feature",
  "properties": {
    "iso:country":"GB",
    "sg:address":"7 Garden Court, Wheathampstead",
    "sg:city":"St Albans",
    "sg:classifiers":[
        {
            "category":"Professional",
            "subcategory":"Computer Services",
            "type":"Services"
        }
    ],
    "sg:phone":"+44 1582 834477",
    "sg:postcode":"AL4 8RE",
    "sg:province":"Hertfordshire",
    "sg:tags":[
        "consultant"
    ],
    "wof:name":"Business Interface Ltd.",
    "wof:placetype":"venue"
},
  "geometry": {"coordinates":[-0.293341,51.815956],"type":"Point"}
}