{
  "type": "Feature",
  "properties": {
    "iso:country":"GB",
    "sg:address":"55-57 Bridge Street",
    "sg:city":"Berwick-upon-tweed",
    "sg:classifiers":[
        {
            "category":"Real Estate",
            "subcategory":"Real Estate Agent",
            "type":"Services"
        }
    ],
    "sg:postcode":"TD15 1ES",
    "sg:province":"Northumberland",
    "wof:name":"Loveday's",
    "wof:placetype":"venue"
},
  "geometry": {"coordinates":[-2.005367,55.768627],"type":"Point"}
}