{
  "type": "Feature",
  "properties": {
    "iso:country":"GB",
    "sg:address":"Wood Farm, Witnesham",
    "sg:city":"Ipswich",
    "sg:classifiers":[
        {
            "category":"Professional",
            "subcategory":"Art Services",
            "type":"Services"
        },
        {
            "category":"Building & Trades",
            "subcategory":"Construction",
            "type":"Services"
        }
    ],
    "sg:phone":"+44 1473 785215",
    "sg:postcode":"IP6 9EW",
    "sg:province":"Suffolk",
    "sg:tags":[
        "glazier",
        "decorator",
        "painter"
    ],
    "wof:name":"Neville C Parken",
    "wof:placetype":"venue"
},
  "geometry": {"coordinates":[1.187881,52.113987],"type":"Point"}
}