{
  "type": "Feature",
  "properties": {
    "addr:full":"Moyles Court, Rockford Ringwood Dorset BH24 3NF",
    "addr:postcode":"bh24 3nf",
    "addr:street":"Moyles Court",
    "iso:country":"GB",
    "sg:address":"Moyles Court, Rockford",
    "sg:city":"Ringwood",
    "sg:classifiers":[
        {
            "category":"Education",
            "subcategory":"School",
            "type":"Public Place"
        }
    ],
    "sg:phone":"+44 1425 472856",
    "sg:postcode":"BH24 3NF",
    "sg:province":"Dorset",
    "sg:tags":[
        "independent",
        "preparatory"
    ],
    "wof:name":"Manor House School Trust Ltd.",
    "wof:placetype":"venue"
},
  "geometry": {"coordinates":[-1.773727,50.871365],"type":"Point"}
}