{
  "type": "Feature",
  "properties": {
    "iso:country":"GB",
    "sg:address":"202 Dean Street, Town Centre",
    "sg:city":"Telford",
    "sg:classifiers":[
        {
            "category":"Home & Garden",
            "subcategory":"Kitchen Supply",
            "type":"Retail Goods"
        }
    ],
    "sg:phone":"+44 1952 291349",
    "sg:postcode":"TF3 4BT",
    "sg:province":"Shropshire",
    "sg:tags":[
        "glassware",
        "china"
    ],
    "wof:name":"Chinacave",
    "wof:placetype":"venue"
},
  "geometry": {"coordinates":[-2.444159,52.673939],"type":"Point"}
}