{
  "type": "Feature",
  "properties": {
    "iso:country":"GB",
    "sg:address":"3 Portland Street",
    "sg:city":"Lancaster",
    "sg:classifiers":[
        {
            "category":"Building & Trades",
            "subcategory":"Landscaping Services",
            "type":"Services"
        }
    ],
    "sg:phone":"+44 1524 381669",
    "sg:postcode":"LA1 1SZ",
    "sg:province":"Lancashire",
    "sg:tags":[
        "design",
        "garden"
    ],
    "wof:name":"David Redmore Garden Design",
    "wof:placetype":"venue"
},
  "geometry": {"coordinates":[-2.802886,54.044956],"type":"Point"}
}