{
  "type": "Feature",
  "properties": {
    "iso:country":"GB",
    "sg:address":"22 Leopold Rd",
    "sg:city":"Felixstowe",
    "sg:classifiers":[
        {
            "category":"Government",
            "subcategory":"Office",
            "type":"Public Place"
        }
    ],
    "sg:postcode":"IP11 7NP",
    "sg:province":"Suffolk",
    "sg:tags":[
        "central"
    ],
    "wof:name":"Foreman,Carol Christine,",
    "wof:placetype":"venue"
},
  "geometry": {"coordinates":[1.3490790129,51.9626960754],"type":"Point"}
}