{
  "type": "Feature",
  "properties": {
    "iso:country":"GB",
    "sg:address":"59d Ship Street",
    "sg:city":"Brighton",
    "sg:classifiers":[
        {
            "category":"Shopping",
            "subcategory":"Antiques",
            "type":"Retail Goods"
        }
    ],
    "sg:postcode":"BN1 1AE",
    "sg:province":"East Sussex",
    "wof:name":"J F J Sturmey",
    "wof:placetype":"venue"
},
  "geometry": {"coordinates":[-0.141566,50.82164],"type":"Point"}
}