{
  "type": "Feature",
  "properties": {
    "iso:country":"GB",
    "sg:address":"10 Fitzwilliam Road",
    "sg:city":"Rotherham",
    "sg:classifiers":[
        {
            "category":"Health Services",
            "subcategory":"Podiatrist",
            "type":"Services"
        },
        {
            "category":"Health Services",
            "subcategory":"Chiropractor",
            "type":"Services"
        }
    ],
    "sg:phone":"+44 1709 370480",
    "sg:postcode":"S65 1PT",
    "sg:province":"South Yorkshire",
    "sg:tags":[
        "podiatrists",
        "chiropodist"
    ],
    "wof:name":"Paul R Wigginton",
    "wof:placetype":"venue"
},
  "geometry": {"coordinates":[-1.3493249416,53.4357185364],"type":"Point"}
}