{
  "type": "Feature",
  "properties": {
    "iso:country":"GB",
    "sg:address":"13 Cateswell Road, Hall Grn",
    "sg:city":"Birmingham",
    "sg:classifiers":[
        {
            "category":"Real Estate",
            "subcategory":"Real Estate Services",
            "type":"Services"
        },
        {
            "category":"Building & Trades",
            "subcategory":"Equipment Rental",
            "type":"Services"
        }
    ],
    "sg:phone":"+44 121 778 4596",
    "sg:postcode":"B28 8NF",
    "sg:province":"West Midlands",
    "sg:tags":[
        "hire",
        "leasing",
        "plant",
        "machinery"
    ],
    "wof:name":"JOHN HUGHES",
    "wof:placetype":"venue"
},
  "geometry": {"coordinates":[-1.846407,52.437721],"type":"Point"}
}