{
  "type": "Feature",
  "properties": {
    "iso:country":"GB",
    "sg:address":"1a High Street",
    "sg:city":"Walton-on-thames",
    "sg:classifiers":[
        {
            "category":"Shopping",
            "subcategory":"Mobile Phones",
            "type":"Retail Goods"
        },
        {
            "category":"Communications",
            "type":"Services"
        }
    ],
    "sg:phone":"+44 20 8549 3300",
    "sg:postcode":"KT12 1DG",
    "sg:province":"Surrey",
    "sg:tags":[
        "telecommunication"
    ],
    "wof:name":"Chatter Box Telecommunication",
    "wof:placetype":"venue"
},
  "geometry": {"coordinates":[-0.419492,51.386238],"type":"Point"}
}