{
  "type": "Feature",
  "properties": {
    "iso:country":"GB",
    "sg:address":"5 Mulberry Close, Mildenhall",
    "sg:city":"Bury St Edmunds",
    "sg:classifiers":[
        {
            "category":"Building & Trades",
            "subcategory":"Landscaping Services",
            "type":"Services"
        }
    ],
    "sg:phone":"+44 1638 718048",
    "sg:postcode":"IP28 7LL",
    "sg:province":"Cambridgeshire",
    "sg:tags":[
        "gardening"
    ],
    "wof:name":"T L Cultivation",
    "wof:placetype":"venue"
},
  "geometry": {"coordinates":[0.527073,52.344543],"type":"Point"}
}