{
  "type": "Feature",
  "properties": {
    "iso:country":"GB",
    "sg:address":"49 Tonstall Road",
    "sg:city":"Mitcham",
    "sg:classifiers":[
        {
            "category":"Building & Trades",
            "subcategory":"Construction",
            "type":"Services"
        }
    ],
    "sg:phone":"+44 20 8648 6981",
    "sg:postcode":"CR4 2LR",
    "sg:province":"Greater London",
    "sg:tags":[
        "joiner",
        "carpenter"
    ],
    "wof:name":"Carpentry Plus",
    "wof:placetype":"venue"
},
  "geometry": {"coordinates":[-0.156393,51.407742],"type":"Point"}
}