{
  "type": "Feature",
  "properties": {
    "iso:country":"GB",
    "sg:address":"Hilton Cottage, Broomieknowe",
    "sg:city":"Lasswade",
    "sg:classifiers":[
        {
            "category":"Social Services",
            "subcategory":"Job Training",
            "type":"Services"
        }
    ],
    "sg:phone":"+44 131 660 5856",
    "sg:postcode":"EH18 1LN",
    "sg:province":"City of Edinburgh",
    "wof:name":"The Financial Training Co. Ltd.",
    "wof:placetype":"venue"
},
  "geometry": {"coordinates":[-3.114514,55.883186],"type":"Point"}
}