{
  "type": "Feature",
  "properties": {
    "iso:country":"GB",
    "sg:address":"Unit 4-5 The Alcorns, Cambridge Road",
    "sg:city":"Stansted Mountfitchet",
    "sg:classifiers":[
        {
            "category":"Freight",
            "type":"Transportation"
        }
    ],
    "sg:phone":"+44 1279 815322",
    "sg:postcode":"CM24 8DF",
    "sg:province":"Essex",
    "sg:tags":[
        "forwarders"
    ],
    "wof:name":"Big Boss Cargo Ltd.",
    "wof:placetype":"venue"
},
  "geometry": {"coordinates":[0.197115,51.902512],"type":"Point"}
}