{
  "type": "Feature",
  "properties": {
    "iso:country":"GB",
    "sg:address":"193 Wardour St",
    "sg:city":"London",
    "sg:classifiers":[
        {
            "category":"Communications",
            "type":"Services"
        }
    ],
    "sg:postcode":"W1F 8ZD",
    "sg:province":"Greater London",
    "sg:tags":[
        "audio-visual"
    ],
    "wof:name":"Bareham,Ron,Productions",
    "wof:placetype":"venue"
},
  "geometry": {"coordinates":[-0.135811,51.515484],"type":"Point"}
}