{
  "type": "Feature",
  "properties": {
    "iso:country":"GB",
    "sg:address":"Unit 3 28 Beckford St",
    "sg:city":"Hamilton",
    "sg:classifiers":[
        {
            "category":"Professional",
            "subcategory":"Art Services",
            "type":"Services"
        }
    ],
    "sg:phone":"+44 1698 327673",
    "sg:postcode":"ML3 0BT",
    "sg:province":"South Lanarkshire",
    "sg:tags":[
        "photographer"
    ],
    "wof:name":"Lensman Photography",
    "wof:placetype":"venue"
},
  "geometry": {"coordinates":[-4.0503640175,55.7801971436],"type":"Point"}
}