{
  "type": "Feature",
  "properties": {
    "addr:full":"32a High Street, Stokesley Middlesbrough North Yorkshire TS9 5DQ",
    "addr:housenumber":"32a",
    "addr:postcode":"ts9 5dq",
    "addr:street":"High Street",
    "iso:country":"GB",
    "sg:address":"32a High Street, Stokesley",
    "sg:city":"Middlesbrough",
    "sg:classifiers":[
        {
            "category":"Food & Beverages",
            "subcategory":"Meat & Fish",
            "type":"Retail Goods"
        }
    ],
    "sg:phone":"+44 1642 710458",
    "sg:postcode":"TS9 5DQ",
    "sg:province":"North Yorkshire",
    "sg:tags":[
        "butcher"
    ],
    "wof:name":"A Vickers Butchers",
    "wof:placetype":"venue"
},
  "geometry": {"coordinates":[-1.1928060055,54.4700965881],"type":"Point"}
}