{
  "type": "Feature",
  "properties": {
    "addr:full":"92a Dickson Rd Blackpool Lancashire FY1 2BU",
    "addr:housenumber":"92a",
    "addr:postcode":"fy1 2bu",
    "addr:street":"Dickson Rd",
    "iso:country":"GB",
    "sg:address":"92a Dickson Rd",
    "sg:city":"Blackpool",
    "sg:classifiers":[
        {
            "category":"Shopping",
            "subcategory":"Used Merchandise",
            "type":"Retail Goods"
        }
    ],
    "sg:phone":"+44 1253 316632",
    "sg:postcode":"FY1 2BU",
    "sg:province":"Lancashire",
    "sg:tags":[
        "shop",
        "second-hand"
    ],
    "wof:name":"Cash Connections",
    "wof:placetype":"venue"
},
  "geometry": {"coordinates":[-3.054181,53.823746],"type":"Point"}
}