{
  "type": "Feature",
  "properties": {
    "iso:country":"GB",
    "sg:address":"Mountbatten Gallery",
    "sg:city":"Romsey",
    "sg:classifiers":[
        {
            "category":"Arts & Performance",
            "subcategory":"Art Gallery",
            "type":"Entertainment"
        }
    ],
    "sg:phone":"+44 23 8073 3574",
    "sg:postcode":"SO51 9LE",
    "sg:province":"Hampshire",
    "wof:name":"Romsey Art Group The",
    "wof:placetype":"venue"
},
  "geometry": {"coordinates":[-1.495391,50.988583],"type":"Point"}
}