{
  "type": "Feature",
  "properties": {
    "iso:country":"GB",
    "sg:address":"76 Coleford Bridge Road, Mytchett",
    "sg:city":"Camberley",
    "sg:classifiers":[
        {
            "category":"Home & Garden",
            "subcategory":"Garden Supply",
            "type":"Retail Goods"
        }
    ],
    "sg:phone":"+44 1252 517683",
    "sg:postcode":"GU16 6DT",
    "sg:province":"Hampshire",
    "sg:tags":[
        "turfing"
    ],
    "wof:name":"Southdown Landscapes",
    "wof:placetype":"venue"
},
  "geometry": {"coordinates":[-0.731545,51.291302],"type":"Point"}
}