{
  "type": "Feature",
  "properties": {
    "addr:full":"10 Parkside Rd Blairgowrie Angus PH11 8BX",
    "addr:housenumber":"10",
    "addr:postcode":"ph11 8bx",
    "addr:street":"Parkside Rd",
    "iso:country":"GB",
    "sg:address":"10 Parkside Rd",
    "sg:city":"Blairgowrie",
    "sg:classifiers":[
        {
            "category":"Building & Trades",
            "subcategory":"Plumbing",
            "type":"Services"
        }
    ],
    "sg:phone":"+44 1828 632158",
    "sg:postcode":"PH11 8BX",
    "sg:province":"Angus",
    "sg:tags":[
        "central",
        "heating"
    ],
    "wof:name":"David McKiddie",
    "wof:placetype":"venue"
},
  "geometry": {"coordinates":[-3.229128,56.627853],"type":"Point"}
}