{
  "type": "Feature",
  "properties": {
    "iso:country":"GB",
    "sg:address":"Unit 9, Phoenix Building, Rushock Trading Estate",
    "sg:city":"Droitwich",
    "sg:classifiers":[
        {
            "category":"Building & Trades",
            "subcategory":"Construction",
            "type":"Services"
        }
    ],
    "sg:phone":"+44 1299 250055",
    "sg:postcode":"WR9 0NR",
    "sg:province":"Worcestershire",
    "sg:tags":[
        "joinery"
    ],
    "wof:name":"Commercial & Retail Interiors Ltd.",
    "wof:placetype":"venue"
},
  "geometry": {"coordinates":[-2.172187,52.338905],"type":"Point"}
}