{
  "type": "Feature",
  "properties": {
    "addr:full":"21 Manor Clo Wakefield West Yorkshire WF4 2NH",
    "addr:housenumber":"21",
    "addr:postcode":"wf4 2nh",
    "addr:street":"Manor Clo",
    "iso:country":"GB",
    "sg:address":"21 Manor Clo",
    "sg:city":"Wakefield",
    "sg:classifiers":[
        {
            "category":"Organizations",
            "subcategory":"Community Association",
            "type":"Services"
        }
    ],
    "sg:phone":"+44 1226 726741",
    "sg:postcode":"WF4 2NH",
    "sg:province":"West Yorkshire",
    "sg:tags":[
        "relation",
        "public"
    ],
    "wof:name":"Construction Publicity",
    "wof:placetype":"venue"
},
  "geometry": {"coordinates":[-1.4774349928,53.6131896973],"type":"Point"}
}