{
  "type": "Feature",
  "properties": {
    "iso:country":"GB",
    "sg:address":"1 Mill Rd, Great Gransden",
    "sg:city":"Sandy",
    "sg:classifiers":[
        {
            "category":"Building & Trades",
            "subcategory":"Cleaning & Sanitation",
            "type":"Services"
        }
    ],
    "sg:phone":"+44 1767 677910",
    "sg:postcode":"SG19 3AG",
    "sg:province":"Bedfordshire",
    "sg:tags":[
        "steam"
    ],
    "wof:name":"Eastern Mobile Steam Cleaning",
    "wof:placetype":"venue"
},
  "geometry": {"coordinates":[-0.1400289983,52.1858024597],"type":"Point"}
}