{
  "type": "Feature",
  "properties": {
    "addr:full":"Diplocks Farm House, Western Road Hailsham East Sussex BN27 3EJ",
    "addr:postcode":"bn27 3ej",
    "addr:street":"Western Road",
    "iso:country":"GB",
    "sg:address":"Diplocks Farm House, Western Road",
    "sg:city":"Hailsham",
    "sg:classifiers":[
        {
            "category":"Building & Trades",
            "subcategory":"Construction",
            "type":"Services"
        }
    ],
    "sg:postcode":"BN27 3EJ",
    "sg:province":"East Sussex",
    "sg:tags":[
        "conservation",
        "craft",
        "thatching"
    ],
    "wof:name":"Master Thatcher South",
    "wof:placetype":"venue"
},
  "geometry": {"coordinates":[0.2524560094,50.8628730774],"type":"Point"}
}