{
  "type": "Feature",
  "properties": {
    "addr:full":"28 Barnton Grove Edinburgh City of Edinburgh EH4 6BT",
    "addr:housenumber":"28",
    "addr:postcode":"eh4 6bt",
    "addr:street":"Barnton Grove",
    "iso:country":"GB",
    "sg:address":"28 Barnton Grove",
    "sg:city":"Edinburgh",
    "sg:classifiers":[
        {
            "category":"Travel",
            "subcategory":"Travel Agent",
            "type":"Entertainment"
        }
    ],
    "sg:phone":"+44 20 8748 2000",
    "sg:postcode":"EH4 6BT",
    "sg:province":"City of Edinburgh",
    "wof:name":"Monteith Travel Services Ltd.",
    "wof:placetype":"venue"
},
  "geometry": {"coordinates":[-3.305586,55.961506],"type":"Point"}
}