{
  "type": "Feature",
  "properties": {
    "iso:country":"GB",
    "sg:address":"1 Lower Hammersley Lane, Loudwater",
    "sg:city":"High Wycombe",
    "sg:classifiers":[
        {
            "category":"Building & Trades",
            "subcategory":"Landscaping Services",
            "type":"Services"
        }
    ],
    "sg:phone":"+44 1494 461793",
    "sg:postcode":"HP13 7DA",
    "sg:province":"Buckinghamshire",
    "sg:tags":[
        "landscape",
        "contractor"
    ],
    "wof:name":"Jerry Edwards Gardening Services",
    "wof:placetype":"venue"
},
  "geometry": {"coordinates":[-0.707729,51.616211],"type":"Point"}
}