{
  "type": "Feature",
  "properties": {
    "iso:country":"GB",
    "sg:address":"Anglian House",
    "sg:city":"Great Yarmouth",
    "sg:classifiers":[
        {
            "category":"Retail",
            "subcategory":"Repair Shop",
            "type":"Services"
        }
    ],
    "sg:postcode":"NR30 3DY",
    "sg:province":"Norfolk",
    "sg:tags":[
        "upholsterer"
    ],
    "wof:name":"J & K Upholsterers",
    "wof:placetype":"venue"
},
  "geometry": {"coordinates":[1.72399,52.612415],"type":"Point"}
}