{
  "type": "Feature",
  "properties": {
    "iso:country":"GB",
    "sg:address":"80 Inverness Terrace",
    "sg:city":"London",
    "sg:classifiers":[
        {
            "category":"Travel",
            "subcategory":"Hotels & Motels",
            "type":"Entertainment"
        }
    ],
    "sg:phone":"+44 20 7243 0142",
    "sg:postcode":"W2 3LD",
    "sg:province":"Greater London",
    "wof:name":"Britannia Court Hotel",
    "wof:placetype":"venue"
},
  "geometry": {"coordinates":[-0.186418,51.513134],"type":"Point"}
}