{
  "type": "Feature",
  "properties": {
    "addr:full":"Gypsy Lodge, Blackborough Cullompton Devon EX15 2HZ",
    "addr:postcode":"ex15 2hz",
    "addr:street":"Blackborough",
    "iso:country":"GB",
    "sg:address":"Gypsy Lodge, Blackborough",
    "sg:city":"Cullompton",
    "sg:classifiers":[
        {
            "category":"Farming",
            "subcategory":"Dairy Farm",
            "type":"Manufacturing & Wholesale Goods"
        },
        {
            "category":"Farming",
            "subcategory":"Livestock Farm",
            "type":"Manufacturing & Wholesale Goods"
        }
    ],
    "sg:phone":"+44 1823 680563",
    "sg:postcode":"EX15 2HZ",
    "sg:province":"Devon",
    "sg:tags":[
        "others",
        "farmer"
    ],
    "wof:name":"R O M R & P A DOBLE",
    "wof:placetype":"venue"
},
  "geometry": {"coordinates":[-3.286112,50.871834],"type":"Point"}
}