{
  "type": "Feature",
  "properties": {
    "addr:full":"4 Fernside Walk Hamilton South Lanarkshire ML3 7PT",
    "addr:housenumber":"4",
    "addr:postcode":"ml3 7pt",
    "addr:street":"Fernside Walk",
    "iso:country":"GB",
    "sg:address":"4 Fernside Walk",
    "sg:city":"Hamilton",
    "sg:classifiers":[
        {
            "category":"Building & Trades",
            "subcategory":"Construction",
            "type":"Services"
        }
    ],
    "sg:phone":"+44 1698 286755",
    "sg:postcode":"ML3 7PT",
    "sg:province":"South Lanarkshire",
    "sg:tags":[
        "joiner",
        "carpenter"
    ],
    "wof:name":"K A L Joinery",
    "wof:placetype":"venue"
},
  "geometry": {"coordinates":[-4.0528907776,55.7773208618],"type":"Point"}
}