{
  "type": "Feature",
  "properties": {
    "iso:country":"GB",
    "sg:address":"85 Elstow Road",
    "sg:city":"Bedford",
    "sg:classifiers":[
        {
            "category":"Retail",
            "subcategory":"Repair Shop",
            "type":"Services"
        }
    ],
    "sg:postcode":"MK42 9NS",
    "sg:province":"Bedfordshire",
    "sg:tags":[
        "radio",
        "television",
        "video"
    ],
    "wof:name":"Aldo's Electrical Repairs",
    "wof:placetype":"venue"
},
  "geometry": {"coordinates":[-0.4676319957,52.1210098267],"type":"Point"}
}