{
  "type": "Feature",
  "properties": {
    "addr:full":"24 Longcause Plymouth Devon PL7 1JB",
    "addr:housenumber":"24",
    "addr:postcode":"pl7 1jb",
    "addr:street":"Longcause",
    "iso:country":"GB",
    "sg:address":"24 Longcause",
    "sg:city":"Plymouth",
    "sg:classifiers":[
        {
            "category":"Home & Garden",
            "subcategory":"Home Furnishings",
            "type":"Retail Goods"
        },
        {
            "category":"Building & Trades",
            "subcategory":"Construction",
            "type":"Services"
        }
    ],
    "sg:phone":"+44 1752 336125",
    "sg:postcode":"PL7 1JB",
    "sg:province":"Devon",
    "sg:tags":[
        "fitting",
        "flooring",
        "carpet"
    ],
    "wof:name":"A R Jenkins",
    "wof:placetype":"venue"
},
  "geometry": {"coordinates":[-4.0445342064,50.3838119507],"type":"Point"}
}