{
  "type": "Feature",
  "properties": {
    "addr:full":"Weir Bank, Monkey Island Lane Maidenhead Berkshire SL6 2ED",
    "addr:postcode":"sl6 2ed",
    "addr:street":"Island Lane",
    "iso:country":"GB",
    "sg:address":"Weir Bank, Monkey Island Lane",
    "sg:city":"Maidenhead",
    "sg:classifiers":[
        {
            "category":"Wholesale",
            "subcategory":"Chemicals & Plastics",
            "type":"Manufacturing & Wholesale Goods"
        }
    ],
    "sg:phone":"+44 1628 762740",
    "sg:postcode":"SL6 2ED",
    "sg:province":"Berkshire",
    "sg:tags":[
        "product",
        "allied"
    ],
    "wof:name":"Fosplant",
    "wof:placetype":"venue"
},
  "geometry": {"coordinates":[-0.6927989721,51.5063781738],"type":"Point"}
}