{
  "type": "Feature",
  "properties": {
    "addr:full":"85 Main Street, Kinglassie Lochgelly Fife KY5 0YE",
    "addr:housenumber":"85",
    "addr:postcode":"ky5 0ye",
    "addr:street":"Main Street;Lochgelly",
    "iso:country":"GB",
    "sg:address":"85 Main Street, Kinglassie",
    "sg:city":"Lochgelly",
    "sg:classifiers":[
        {
            "category":"Education",
            "subcategory":"Library",
            "type":"Public Place"
        },
        {
            "category":"Education",
            "subcategory":"School",
            "type":"Public Place"
        },
        {
            "category":"Government",
            "subcategory":"Office",
            "type":"Public Place"
        }
    ],
    "sg:phone":"+44 1592 882245",
    "sg:postcode":"KY5 0YE",
    "sg:province":"Fife",
    "sg:tags":[
        "book",
        "local",
        "authority"
    ],
    "wof:name":"Kinglassie Primary School",
    "wof:placetype":"venue"
},
  "geometry": {"coordinates":[-3.237672,56.175331],"type":"Point"}
}