{
  "type": "Feature",
  "properties": {
    "addr:full":"62 Sedlescombe Rd North St Leonards-on-sea East Sussex TN37 7DT",
    "addr:housenumber":"62",
    "addr:postcode":"tn37 7dt",
    "addr:street":"Sedlescombe Rd;Leonards-On-Sea",
    "iso:country":"GB",
    "sg:address":"62 Sedlescombe Rd North",
    "sg:city":"St Leonards-on-sea",
    "sg:classifiers":[
        {
            "category":"Fast Food",
            "type":"Food & Drink"
        }
    ],
    "sg:postcode":"TN37 7DT",
    "sg:province":"East Sussex",
    "sg:tags":[
        "away",
        "take"
    ],
    "wof:name":"Los Amigos",
    "wof:placetype":"venue"
},
  "geometry": {"coordinates":[0.556909,50.869724],"type":"Point"}
}