{
  "type": "Feature",
  "properties": {
    "addr:full":"109 New Union Street Coventry West Midlands CV1 2NT",
    "addr:housenumber":"109",
    "addr:postcode":"cv1 2nt",
    "addr:street":"New Union Street",
    "iso:country":"GB",
    "sg:address":"109 New Union Street",
    "sg:city":"Coventry",
    "sg:classifiers":[
        {
            "category":"Real Estate",
            "subcategory":"Real Estate Agent",
            "type":"Services"
        }
    ],
    "sg:phone":"+44 24 7663 3221",
    "sg:postcode":"CV1 2NT",
    "sg:province":"West Midlands",
    "wof:name":"Castles",
    "wof:placetype":"venue"
},
  "geometry": {"coordinates":[-1.510231,52.404922],"type":"Point"}
}