{
  "type": "Feature",
  "properties": {
    "addr:full":"57 Peel Road, Wolverton Milton Keynes Buckinghamshire MK12 5AX",
    "addr:housenumber":"57",
    "addr:postcode":"mk12 5ax",
    "addr:street":"Peel Road",
    "iso:country":"GB",
    "sg:address":"57 Peel Road, Wolverton",
    "sg:city":"Milton Keynes",
    "sg:classifiers":[
        {
            "category":"Building & Trades",
            "subcategory":"Construction",
            "type":"Services"
        }
    ],
    "sg:phone":"+44 1908 315799",
    "sg:postcode":"MK12 5AX",
    "sg:province":"Buckinghamshire",
    "sg:tags":[
        "joinery",
        "joiner",
        "carpenter",
        "carpentry"
    ],
    "wof:name":"Paul Baron Lathwell",
    "wof:placetype":"venue"
},
  "geometry": {"coordinates":[-0.814754,52.059151],"type":"Point"}
}