{
  "type": "Feature",
  "properties": {
    "addr:full":"21 Dumbarton Rd Lancaster Lancashire LA1 3BX",
    "addr:housenumber":"21",
    "addr:postcode":"la1 3bx",
    "addr:street":"Dumbarton Rd",
    "iso:country":"GB",
    "sg:address":"21 Dumbarton Rd",
    "sg:city":"Lancaster",
    "sg:classifiers":[
        {
            "category":"Food & Beverages",
            "subcategory":"Groceries & Convenience Stores",
            "type":"Retail Goods"
        }
    ],
    "sg:phone":"+44 1524 32097",
    "sg:postcode":"LA1 3BX",
    "sg:province":"Lancashire",
    "wof:name":"Spar",
    "wof:placetype":"venue"
},
  "geometry": {"coordinates":[-2.7930400372,54.0454216003],"type":"Point"}
}