{
  "type": "Feature",
  "properties": {
    "iso:country":"GB",
    "sg:address":"900 Herries Rd",
    "sg:city":"Sheffield",
    "sg:classifiers":[
        {
            "category":"Brewery",
            "type":"Food & Drink"
        }
    ],
    "sg:postcode":"S6 1QX",
    "sg:province":"South Yorkshire",
    "sg:tags":[
        "brewer"
    ],
    "wof:name":"Carlsberg-Tetley Brewing Ltd",
    "wof:placetype":"venue"
},
  "geometry": {"coordinates":[-1.495559,53.412636],"type":"Point"}
}