{
  "type": "Feature",
  "properties": {
    "addr:full":"900 Herries Rd Sheffield South Yorkshire S6 1QX",
    "addr:housenumber":"900",
    "addr:postcode":"s6 1qx",
    "addr:street":"Herries Rd",
    "iso:country":"GB",
    "sg:address":"900 Herries Rd",
    "sg:city":"Sheffield",
    "sg:classifiers":[
        {
            "category":"Brewery",
            "type":"Food & Drink"
        }
    ],
    "sg:postcode":"S6 1QX",
    "sg:province":"South Yorkshire",
    "sg:tags":[
        "brewer"
    ],
    "wof:name":"Carlsberg-Tetley Brewing Ltd",
    "wof:placetype":"venue"
},
  "geometry": {"coordinates":[-1.495559,53.412636],"type":"Point"}
}