{
  "type": "Feature",
  "properties": {
    "iso:country":"GB",
    "sg:address":"Holyhead Road",
    "sg:city":"Shrewsbury",
    "sg:classifiers":[
        {
            "category":"Home & Garden",
            "subcategory":"Hardware",
            "type":"Retail Goods"
        }
    ],
    "sg:phone":"+44 1743 850369",
    "sg:postcode":"SY3 8EQ",
    "sg:province":"Shropshire",
    "sg:tags":[
        "lawnmowers",
        "machinery"
    ],
    "wof:name":"Home & Auto",
    "wof:placetype":"venue"
},
  "geometry": {"coordinates":[-2.8154940605,52.7255516052],"type":"Point"}
}