{
  "type": "Feature",
  "properties": {
    "addr:full":"Warren Rd Burnham On Sea Somerset TA8 2RR",
    "addr:postcode":"ta8 2rr",
    "addr:street":"Warren Rd",
    "iso:country":"GB",
    "sg:address":"Warren Rd",
    "sg:city":"Burnham On Sea",
    "sg:classifiers":[
        {
            "category":"Fast Food",
            "type":"Food & Drink"
        }
    ],
    "sg:phone":"+44 1278 751212",
    "sg:postcode":"TA8 2RR",
    "sg:province":"Somerset",
    "sg:tags":[
        "away",
        "meal",
        "outlet",
        "take"
    ],
    "wof:name":"Sunnyside Fish Bar",
    "wof:placetype":"venue"
},
  "geometry": {"coordinates":[-3.0097880363,51.3064575195],"type":"Point"}
}