{
  "type": "Feature",
  "properties": {
    "addr:full":"29a Stone Lane, Lydiard Millicent Swindon Wiltshire SN5 3LD",
    "addr:housenumber":"29a",
    "addr:postcode":"sn5 3ld",
    "addr:street":"Stone Lane",
    "iso:country":"GB",
    "sg:address":"29a Stone Lane, Lydiard Millicent",
    "sg:city":"Swindon",
    "sg:classifiers":[
        {
            "category":"Building & Trades",
            "subcategory":"Construction",
            "type":"Services"
        },
        {
            "category":"Manufacturing",
            "subcategory":"Building Materials",
            "type":"Manufacturing & Wholesale Goods"
        }
    ],
    "sg:phone":"+44 1793 770071",
    "sg:postcode":"SN5 3LD",
    "sg:province":"Wiltshire",
    "sg:tags":[
        "concrete",
        "product",
        "paving",
        "contractor"
    ],
    "wof:name":"BARRETT PAVING",
    "wof:placetype":"venue"
},
  "geometry": {"coordinates":[-1.864369,51.573498],"type":"Point"}
}