{
  "type": "Feature",
  "properties": {
    "addr:full":"39 High Street Saxmundham Suffolk IP17 1AJ",
    "addr:housenumber":"39",
    "addr:postcode":"ip17 1aj",
    "addr:street":"High Street",
    "iso:country":"GB",
    "sg:address":"39 High Street",
    "sg:city":"Saxmundham",
    "sg:classifiers":[
        {
            "category":"Home & Garden",
            "subcategory":"Hardware",
            "type":"Retail Goods"
        }
    ],
    "sg:phone":"+44 1728 602154",
    "sg:postcode":"IP17 1AJ",
    "sg:province":"Suffolk",
    "sg:tags":[
        "merchant",
        "retailer",
        "ironmonger",
        "diy"
    ],
    "wof:name":"B C Fisher",
    "wof:placetype":"venue"
},
  "geometry": {"coordinates":[1.492125,52.215611],"type":"Point"}
}