{
  "type": "Feature",
  "properties": {
    "addr:full":"18 Ashcombe Gardens Edgware Greater London HA8 8HS",
    "addr:housenumber":"18",
    "addr:postcode":"ha8 8hs",
    "addr:street":"Ashcombe Gardens",
    "iso:country":"GB",
    "sg:address":"18 Ashcombe Gardens",
    "sg:city":"Edgware",
    "sg:classifiers":[
        {
            "category":"Banks & Credit Unions",
            "subcategory":"Financial Services",
            "type":"Services"
        }
    ],
    "sg:phone":"+44 20 8958 8080",
    "sg:postcode":"HA8 8HS",
    "sg:province":"Greater London",
    "sg:tags":[
        "adviser",
        "independent"
    ],
    "wof:name":"J S Independent",
    "wof:placetype":"venue"
},
  "geometry": {"coordinates":[-0.2793259919,51.6205635071],"type":"Point"}
}