{
  "type": "Feature",
  "properties": {
    "addr:full":"28-30 Bristol St Birmingham West Midlands B5 7AA",
    "addr:housenumber":"28-30",
    "addr:postcode":"b5 7aa",
    "addr:street":"Bristol St",
    "iso:country":"GB",
    "sg:address":"28-30 Bristol St",
    "sg:city":"Birmingham",
    "sg:classifiers":[
        {
            "category":"Bars & Pubs",
            "subcategory":"Nightclub",
            "type":"Food & Drink"
        }
    ],
    "sg:phone":"+44 121 685 8301",
    "sg:postcode":"B5 7AA",
    "sg:province":"West Midlands",
    "sg:tags":[
        "club",
        "night"
    ],
    "wof:name":"Amen Night Club",
    "wof:placetype":"venue"
},
  "geometry": {"coordinates":[-1.899312973,52.4733772278],"type":"Point"}
}