{
  "type": "Feature",
  "properties": {
    "addr:full":"Theydon House, Oakwood Hill Industrial Estate Loughton Essex IG10 3TZ",
    "addr:postcode":"ig10 3tz",
    "addr:street":"Oakwood Hill Industrial Estate",
    "iso:country":"GB",
    "sg:address":"Theydon House, Oakwood Hill Industrial Estate",
    "sg:city":"Loughton",
    "sg:classifiers":[
        {
            "category":"Real Estate",
            "subcategory":"Surveying",
            "type":"Services"
        }
    ],
    "sg:phone":"+44 20 8508 4011",
    "sg:postcode":"IG10 3TZ",
    "sg:province":"Essex",
    "sg:tags":[
        "surveyor",
        "quantity"
    ],
    "wof:name":"Penman & Gore Ltd.",
    "wof:placetype":"venue"
},
  "geometry": {"coordinates":[0.080392,51.64341],"type":"Point"}
}