{
  "type": "Feature",
  "properties": {
    "iso:country":"GB",
    "sg:address":"1 Wood Street",
    "sg:city":"Maryport",
    "sg:classifiers":[
        {
            "category":"Building & Trades",
            "subcategory":"Construction",
            "type":"Services"
        }
    ],
    "sg:phone":"+44 1900 818533",
    "sg:postcode":"CA15 6EG",
    "sg:province":"Cumbria",
    "sg:tags":[
        "builder"
    ],
    "wof:name":"William & Elaine Richardson",
    "wof:placetype":"venue"
},
  "geometry": {"coordinates":[-3.4995400906,54.7156906128],"type":"Point"}
}