{
  "type": "Feature",
  "properties": {
    "iso:country":"GB",
    "sg:address":"175a Sunderland Road",
    "sg:city":"South Shields",
    "sg:classifiers":[
        {
            "category":"Building & Trades",
            "subcategory":"Landscaping Services",
            "type":"Services"
        },
        {
            "category":"Shopping",
            "subcategory":"Pets & Pet Supplies",
            "type":"Retail Goods"
        }
    ],
    "sg:phone":"+44 191 455 2066",
    "sg:postcode":"NE34 6AD",
    "sg:province":"Tyne and Wear",
    "sg:tags":[
        "supplier",
        "pond",
        "aquarium"
    ],
    "wof:name":"The Aquatic Centre",
    "wof:placetype":"venue"
},
  "geometry": {"coordinates":[-1.413236,54.977547],"type":"Point"}
}