{
  "type": "Feature",
  "properties": {
    "addr:full":"14 Queens Park Road Caterham Surrey CR3 5RB",
    "addr:housenumber":"14",
    "addr:postcode":"cr3 5rb",
    "addr:street":"Queens Park Road",
    "iso:country":"GB",
    "sg:address":"14 Queens Park Road",
    "sg:city":"Caterham",
    "sg:classifiers":[
        {
            "category":"Health Services",
            "subcategory":"Nursing And Care Facility",
            "type":"Services"
        }
    ],
    "sg:phone":"+44 1883 345993",
    "sg:postcode":"CR3 5RB",
    "sg:province":"Surrey",
    "sg:tags":[
        "home"
    ],
    "wof:name":"Coombe Dingle Nursing Home",
    "wof:placetype":"venue"
},
  "geometry": {"coordinates":[-0.087759,51.283779],"type":"Point"}
}