{
  "type": "Feature",
  "properties": {
    "addr:full":"74 College Rd Bromley Kent BR1 3PE",
    "addr:housenumber":"74",
    "addr:postcode":"br1 3pe",
    "addr:street":"College Rd",
    "iso:country":"GB",
    "sg:address":"74 College Rd",
    "sg:city":"Bromley",
    "sg:classifiers":[
        {
            "category":"Real Estate",
            "subcategory":"Real Estate Agent",
            "type":"Services"
        }
    ],
    "sg:phone":"+44 20 8290 5555",
    "sg:postcode":"BR1 3PE",
    "sg:province":"Kent",
    "wof:name":"Ridgeway Estate Agents",
    "wof:placetype":"venue"
},
  "geometry": {"coordinates":[0.0146019999,51.4115447998],"type":"Point"}
}