{
  "type": "Feature",
  "properties": {
    "addr:full":"278 East Park Road Leicester Leicestershire LE5 5AY",
    "addr:housenumber":"278",
    "addr:postcode":"le5 5ay",
    "addr:street":"East Park Road",
    "iso:country":"GB",
    "sg:address":"278 East Park Road",
    "sg:city":"Leicester",
    "sg:classifiers":[
        {
            "category":"Organizations",
            "subcategory":"Non-profit Organization",
            "type":"Services"
        }
    ],
    "sg:phone":"+44 116 248 7424",
    "sg:postcode":"LE5 5AY",
    "sg:province":"Leicestershire",
    "sg:tags":[
        "organisation",
        "voluntary",
        "charity"
    ],
    "wof:name":"Church of England Board of Mission & Social Responsibility",
    "wof:placetype":"venue"
},
  "geometry": {"coordinates":[-1.105921,52.632153],"type":"Point"}
}