{
  "type": "Feature",
  "properties": {
    "iso:country":"GB",
    "sg:address":"Unit 2 The Sling",
    "sg:city":"Dudley",
    "sg:classifiers":[
        {
            "category":"Professional",
            "subcategory":"Printing & Photocopies",
            "type":"Services"
        }
    ],
    "sg:postcode":"DY2 9AJ",
    "sg:province":"West Midlands",
    "sg:tags":[
        "printer"
    ],
    "wof:name":"Dudley Print",
    "wof:placetype":"venue"
},
  "geometry": {"coordinates":[-2.087675,52.498802],"type":"Point"}
}