{
  "type": "Feature",
  "properties": {
    "iso:country":"GB",
    "sg:address":"Ardiemannoch",
    "sg:city":"Keith",
    "sg:classifiers":[
        {
            "category":"Farming",
            "subcategory":"Farm",
            "type":"Manufacturing & Wholesale Goods"
        }
    ],
    "sg:phone":"+44 1542 882716",
    "sg:postcode":"AB55 5NS",
    "sg:province":"Moray",
    "sg:tags":[
        "mixed",
        "crop"
    ],
    "wof:name":"A S Shaw",
    "wof:placetype":"venue"
},
  "geometry": {"coordinates":[-2.95042,57.543236],"type":"Point"}
}