{
  "type": "Feature",
  "properties": {
    "iso:country":"GB",
    "sg:address":"6 Cutshill Close",
    "sg:city":"Birmingham",
    "sg:classifiers":[
        {
            "category":"Professional",
            "type":"Services"
        }
    ],
    "sg:phone":"+44 121 748 3518",
    "sg:postcode":"B36 9SQ",
    "sg:province":"West Midlands",
    "sg:tags":[
        "entertainer"
    ],
    "wof:name":"Nodrog the Clown",
    "wof:placetype":"venue"
},
  "geometry": {"coordinates":[-1.777865,52.506554],"type":"Point"}
}