{
  "type": "Feature",
  "properties": {
    "addr:full":"Belville Farm Coldstream Northumberland TD12 4JB",
    "addr:postcode":"td12 4jb",
    "addr:street":"Northumberland",
    "iso:country":"GB",
    "sg:address":"Belville Farm",
    "sg:city":"Coldstream",
    "sg:classifiers":[
        {
            "category":"Farming",
            "subcategory":"Farm",
            "type":"Manufacturing & Wholesale Goods"
        }
    ],
    "sg:phone":"+44 1890 840265",
    "sg:postcode":"TD12 4JB",
    "sg:province":"Northumberland",
    "sg:tags":[
        "mixed",
        "crop"
    ],
    "wof:name":"James R White",
    "wof:placetype":"venue"
},
  "geometry": {"coordinates":[-2.2516510487,55.6515769958],"type":"Point"}
}