{
  "type": "Feature",
  "properties": {
    "addr:full":"92 Church Road Mitcham Greater London CR4 3XT",
    "addr:housenumber":"92",
    "addr:postcode":"cr4 3xt",
    "addr:street":"Church Road",
    "iso:country":"GB",
    "sg:address":"92 Church Road",
    "sg:city":"Mitcham",
    "sg:classifiers":[
        {
            "category":"Personal",
            "type":"Services"
        }
    ],
    "sg:phone":"+44 20 8648 4119",
    "sg:postcode":"CR4 3XT",
    "sg:province":"Greater London",
    "sg:tags":[
        "delivery"
    ],
    "wof:name":"The Post Office",
    "wof:placetype":"venue"
},
  "geometry": {"coordinates":[-0.177459,51.40736],"type":"Point"}
}