{
  "type": "Feature",
  "properties": {
    "addr:full":"21 Lusher Rise Norwich Norfolk NR6 5ED",
    "addr:housenumber":"21",
    "addr:postcode":"nr6 5ed",
    "addr:street":"Lusher Rise Norwich Norfolk",
    "iso:country":"GB",
    "sg:address":"21 Lusher Rise",
    "sg:city":"Norwich",
    "sg:classifiers":[
        {
            "category":"Retail",
            "subcategory":"Event Space",
            "type":"Services"
        }
    ],
    "sg:phone":"+44 1603 610831",
    "sg:postcode":"NR6 5ED",
    "sg:province":"Norfolk",
    "sg:tags":[
        "exhibition",
        "organiser"
    ],
    "wof:name":"Multiscreen Display Hire",
    "wof:placetype":"venue"
},
  "geometry": {"coordinates":[1.2488460541,52.6386947632],"type":"Point"}
}