{
  "type": "Feature",
  "properties": {
    "iso:country":"GB",
    "sg:address":"16 Gladstone Street",
    "sg:city":"Aberdare",
    "sg:classifiers":[
        {
            "category":"Taxi",
            "type":"Transportation"
        }
    ],
    "sg:phone":"+44 1685 886666",
    "sg:postcode":"CF44 6SB",
    "sg:province":"Neath Port Talbot",
    "sg:tags":[
        "mini",
        "cab"
    ],
    "wof:name":"P A Davies",
    "wof:placetype":"venue"
},
  "geometry": {"coordinates":[-3.4246070385,51.6979103088],"type":"Point"}
}