{
  "type": "Feature",
  "properties": {
    "addr:full":"401 Hertford Rd Enfield Greater London EN3 5PR",
    "addr:housenumber":"401",
    "addr:postcode":"en3 5pr",
    "addr:street":"Hertford Rd",
    "iso:country":"GB",
    "sg:address":"401 Hertford Rd",
    "sg:city":"Enfield",
    "sg:classifiers":[
        {
            "category":"Real Estate",
            "subcategory":"Real Estate Agent",
            "type":"Services"
        }
    ],
    "sg:phone":"+44 20 8245 4455",
    "sg:postcode":"EN3 5PR",
    "sg:province":"Greater London",
    "wof:name":"Keys",
    "wof:placetype":"venue"
},
  "geometry": {"coordinates":[-0.044194,51.664284],"type":"Point"}
}