{
  "type": "Feature",
  "properties": {
    "iso:country":"GB",
    "sg:address":"Caister Holiday Centre, Ormesby Road, Caister On Sea",
    "sg:city":"Great Yarmouth",
    "sg:classifiers":[
        {
            "category":"Autos & Motor Vehicles",
            "subcategory":"Recreational Vehicle Sales",
            "type":"Retail Goods"
        }
    ],
    "sg:phone":"+44 1493 720405",
    "sg:postcode":"NR30 5NQ",
    "sg:province":"Norfolk",
    "sg:tags":[
        "caravan"
    ],
    "wof:name":"Haven Caravan Sales",
    "wof:placetype":"venue"
},
  "geometry": {"coordinates":[1.71362,52.652054],"type":"Point"}
}