{
  "type": "Feature",
  "properties": {
    "addr:full":"Care Of Tollard Royal Post Office, 31 High St Salisbury Dorset SP5 5PP",
    "addr:housenumber":"31",
    "addr:postcode":"sp5 5pp",
    "addr:street":"High St",
    "iso:country":"GB",
    "sg:address":"Care Of Tollard Royal Post Office, 31 High St",
    "sg:city":"Salisbury",
    "sg:classifiers":[
        {
            "category":"Shopping",
            "subcategory":"Department Store",
            "type":"Retail Goods"
        }
    ],
    "sg:phone":"+44 1725 516454",
    "sg:postcode":"SP5 5PP",
    "sg:province":"Dorset",
    "wof:name":"Tollard Royal General Store",
    "wof:placetype":"venue"
},
  "geometry": {"coordinates":[-2.0802299976,50.9592399597],"type":"Point"}
}