{
  "type": "Feature",
  "properties": {
    "addr:full":"59 Belgrave Road Coventry Warwickshire CV2 5BG",
    "addr:housenumber":"59",
    "addr:postcode":"cv2 5bg",
    "addr:street":"Belgrave Road",
    "iso:country":"GB",
    "sg:address":"59 Belgrave Road",
    "sg:city":"Coventry",
    "sg:classifiers":[
        {
            "category":"Food & Beverages",
            "subcategory":"Supermarket",
            "type":"Retail Goods"
        }
    ],
    "sg:phone":"+44 24 7644 3604",
    "sg:postcode":"CV2 5BG",
    "sg:province":"Warwickshire",
    "wof:name":"Dougall Store",
    "wof:placetype":"venue"
},
  "geometry": {"coordinates":[-1.455327,52.415051],"type":"Point"}
}