{
  "type": "Feature",
  "properties": {
    "addr:full":"21 Hardengreen Business Centre Dalkeith City of Edinburgh EH22 3NX",
    "addr:housenumber":"21",
    "addr:postcode":"eh22 3nx",
    "addr:street":"Hardengreen Business Centre",
    "iso:country":"GB",
    "sg:address":"21 Hardengreen Business Centre",
    "sg:city":"Dalkeith",
    "sg:classifiers":[
        {
            "category":"Wholesale",
            "subcategory":"Machinery & Supplies",
            "type":"Manufacturing & Wholesale Goods"
        }
    ],
    "sg:phone":"+44 131 654 0200",
    "sg:postcode":"EH22 3NX",
    "sg:province":"City of Edinburgh",
    "sg:tags":[
        "hydraulic"
    ],
    "wof:name":"Air Accessories",
    "wof:placetype":"venue"
},
  "geometry": {"coordinates":[-3.0837869644,55.8827552795],"type":"Point"}
}