{
  "type": "Feature",
  "properties": {
    "addr:full":"Rear Of 39-51 High St Staines Berkshire TW19 7LJ",
    "addr:housenumber":"rear of 39-51",
    "addr:postcode":"tw19 7lj",
    "addr:street":"High St",
    "iso:country":"GB",
    "sg:address":"Rear Of 39-51 High St",
    "sg:city":"Staines",
    "sg:classifiers":[
        {
            "category":"Professional",
            "type":"Services"
        }
    ],
    "sg:phone":"+44 1784 423388",
    "sg:postcode":"TW19 7LJ",
    "sg:province":"Berkshire",
    "sg:tags":[
        "services",
        "belt",
        "conveyor"
    ],
    "wof:name":"Lonergan Handling",
    "wof:placetype":"venue"
},
  "geometry": {"coordinates":[-0.47891,51.45739],"type":"Point"}
}