{
  "type": "Feature",
  "properties": {
    "iso:country":"GB",
    "sg:address":"5 The Bridge",
    "sg:city":"Chippenham",
    "sg:classifiers":[
        {
            "category":"Shopping",
            "subcategory":"Thrift Store",
            "type":"Retail Goods"
        }
    ],
    "sg:phone":"+44 1249 447061",
    "sg:postcode":"SN15 1HA",
    "sg:province":"Wiltshire",
    "sg:tags":[
        "shop",
        "charity"
    ],
    "sg:website":"http://www.oxfam.org.uk",
    "wof:name":"Oxfam",
    "wof:placetype":"venue"
},
  "geometry": {"coordinates":[-2.117507,51.459465],"type":"Point"}
}