{
  "type": "Feature",
  "properties": {
    "addr:full":"Court Close, North Wraxall Chippenham Gloucestershire SN14 7AD",
    "addr:postcode":"sn14 7ad",
    "addr:street":"Court Close North Wraxall",
    "iso:country":"GB",
    "sg:address":"Court Close, North Wraxall",
    "sg:city":"Chippenham",
    "sg:classifiers":[
        {
            "category":"Shopping",
            "subcategory":"Antiques",
            "type":"Retail Goods"
        }
    ],
    "sg:phone":"+44 1225 891505",
    "sg:postcode":"SN14 7AD",
    "sg:province":"Gloucestershire",
    "wof:name":"Delomosne & Son Ltd.",
    "wof:placetype":"venue"
},
  "geometry": {"coordinates":[-2.26229,51.473351],"type":"Point"}
}