{
  "type": "Feature",
  "properties": {
    "iso:country":"GB",
    "sg:address":"P O Box 220",
    "sg:city":"Cobham",
    "sg:classifiers":[
        {
            "category":"Professional",
            "subcategory":"Computer Services",
            "type":"Services"
        }
    ],
    "sg:phone":"+44 1932 866933",
    "sg:postcode":"KT11 2YU",
    "sg:province":"Surrey",
    "sg:tags":[
        "system",
        "software"
    ],
    "wof:name":"Comware International Ltd.",
    "wof:placetype":"venue"
},
  "geometry": {"coordinates":[-0.410454,51.328117],"type":"Point"}
}