{
  "type": "Feature",
  "properties": {
    "iso:country":"GB",
    "sg:address":"10 Manning Walk, The Rugby Centre",
    "sg:city":"Rugby",
    "sg:classifiers":[
        {
            "category":"Home & Garden",
            "subcategory":"Household Appliances",
            "type":"Retail Goods"
        }
    ],
    "sg:postcode":"CV21 2JT",
    "sg:province":"Warwickshire",
    "sg:tags":[
        "electrical",
        "domestic"
    ],
    "wof:name":"Antika Retail Ltd",
    "wof:placetype":"venue"
},
  "geometry": {"coordinates":[-1.26363,52.37355],"type":"Point"}
}