{
  "type": "Feature",
  "properties": {
    "addr:full":"2 Sharoe Green Shopping Centre, Fulwood Preston Lancashire PR2 4HD",
    "addr:housenumber":"2",
    "addr:postcode":"pr2 4hd",
    "addr:street":"Sharoe Green Shopping",
    "iso:country":"GB",
    "sg:address":"2 Sharoe Green Shopping Centre, Fulwood",
    "sg:city":"Preston",
    "sg:classifiers":[
        {
            "category":"Shopping",
            "subcategory":"News",
            "type":"Retail Goods"
        }
    ],
    "sg:phone":"+44 1772 718996",
    "sg:postcode":"PR2 4HD",
    "sg:province":"Lancashire",
    "sg:tags":[
        "newsagent"
    ],
    "wof:name":"Forbuoys Ltd.",
    "wof:placetype":"venue"
},
  "geometry": {"coordinates":[-2.71318,53.790051],"type":"Point"}
}