{
  "type": "Feature",
  "properties": {
    "addr:full":"Leadgate Consett Durham DH8 7SZ",
    "addr:postcode":"dh8 7sz",
    "addr:street":"Leadgate Consett",
    "iso:country":"GB",
    "sg:address":"Leadgate",
    "sg:city":"Consett",
    "sg:classifiers":[
        {
            "category":"Farming",
            "subcategory":"Livestock Farm",
            "type":"Manufacturing & Wholesale Goods"
        }
    ],
    "sg:phone":"+44 1207 520938",
    "sg:postcode":"DH8 7SZ",
    "sg:province":"Durham",
    "sg:tags":[
        "others"
    ],
    "wof:name":"G & E A Herdman",
    "wof:placetype":"venue"
},
  "geometry": {"coordinates":[-1.7743599415,54.8453903198],"type":"Point"}
}