{
  "type": "Feature",
  "properties": {
    "iso:country":"GB",
    "sg:address":"20 Bank Street",
    "sg:city":"Wetherby",
    "sg:classifiers":[
        {
            "category":"Shopping",
            "subcategory":"Clothing, Apparel, & Fashions",
            "type":"Retail Goods"
        }
    ],
    "sg:phone":"+44 1937 585478",
    "sg:postcode":"LS22 6NQ",
    "sg:province":"North Yorkshire",
    "sg:tags":[
        "shop"
    ],
    "wof:name":"Space",
    "wof:placetype":"venue"
},
  "geometry": {"coordinates":[-1.386796,53.928921],"type":"Point"}
}