{
  "type": "Feature",
  "properties": {
    "addr:full":"Harefield Marina, Moorhall Road, Harefield Uxbridge Buckinghamshire UB9 6PD",
    "addr:postcode":"ub9 6pd",
    "addr:street":"Moorhall Road",
    "iso:country":"GB",
    "sg:address":"Harefield Marina, Moorhall Road, Harefield",
    "sg:city":"Uxbridge",
    "sg:classifiers":[
        {
            "category":"Recreation",
            "subcategory":"Marina",
            "type":"Entertainment"
        }
    ],
    "sg:phone":"+44 1895 822036",
    "sg:postcode":"UB9 6PD",
    "sg:province":"Buckinghamshire",
    "wof:name":"Musk Marine Ltd.",
    "wof:placetype":"venue"
},
  "geometry": {"coordinates":[-0.4820719957,51.604019165],"type":"Point"}
}