{
  "type": "Feature",
  "properties": {
    "addr:full":"The Broadway Dagenham Essex RM8 1DZ",
    "addr:postcode":"rm8 1dz",
    "addr:street":"The Broadway",
    "iso:country":"GB",
    "sg:address":"The Broadway",
    "sg:city":"Dagenham",
    "sg:classifiers":[
        {
            "category":"Place Of Worship",
            "type":"Public Place"
        }
    ],
    "sg:phone":"+44 20 8595 4611",
    "sg:postcode":"RM8 1DZ",
    "sg:province":"Essex",
    "wof:name":"Beacontree Heath Methodist Church",
    "wof:placetype":"venue"
},
  "geometry": {"coordinates":[0.148438,51.561726],"type":"Point"}
}