{
  "type": "Feature",
  "properties": {
    "addr:full":"Whitehills Terrace, Murray, East Kilbride Glasgow South Lanarkshire G75 0NF",
    "addr:postcode":"g75 0nf",
    "addr:street":"Whitehills Terrace Murray",
    "iso:country":"GB",
    "sg:address":"Whitehills Terrace, Murray, East Kilbride",
    "sg:city":"Glasgow",
    "sg:classifiers":[
        {
            "category":"Education",
            "subcategory":"School",
            "type":"Public Place"
        },
        {
            "category":"Government",
            "subcategory":"Office",
            "type":"Public Place"
        }
    ],
    "sg:phone":"+44 1355 230804",
    "sg:postcode":"G75 0NF",
    "sg:province":"South Lanarkshire",
    "sg:tags":[
        "local",
        "authority"
    ],
    "wof:name":"St Louise's Primary School",
    "wof:placetype":"venue"
},
  "geometry": {"coordinates":[-4.1816592216,55.7522163391],"type":"Point"}
}