{
  "type": "Feature",
  "properties": {
    "addr:full":"1560 Dumbarton Road Glasgow Glasgow City G14 9DB",
    "addr:housenumber":"1560",
    "addr:postcode":"g14 9db",
    "addr:street":"Dumbarton Road",
    "iso:country":"GB",
    "sg:address":"1560 Dumbarton Road",
    "sg:city":"Glasgow",
    "sg:classifiers":[
        {
            "category":"Food & Beverages",
            "subcategory":"Liquor & Beverages",
            "type":"Retail Goods"
        }
    ],
    "sg:phone":"+44 141 959 8850",
    "sg:postcode":"G14 9DB",
    "sg:province":"Glasgow City",
    "sg:tags":[
        "beer",
        "wine",
        "spirit",
        "wines"
    ],
    "wof:name":"Food & Wine Cellar",
    "wof:placetype":"venue"
},
  "geometry": {"coordinates":[-4.3518939018,55.8798103333],"type":"Point"}
}