{
  "type": "Feature",
  "properties": {
    "addr:full":"Care Of Asda Superstore Coventry Warwickshire CV2 3PN",
    "addr:postcode":"cv2 3pn",
    "iso:country":"GB",
    "sg:address":"Care Of Asda Superstore",
    "sg:city":"Coventry",
    "sg:classifiers":[
        {
            "category":"Farming",
            "subcategory":"Livestock Farm",
            "type":"Manufacturing & Wholesale Goods"
        },
        {
            "category":"Shopping",
            "subcategory":"Florist",
            "type":"Retail Goods"
        }
    ],
    "sg:postcode":"CV2 3PN",
    "sg:province":"Warwickshire",
    "sg:tags":[
        "breeder"
    ],
    "wof:name":"Steve Davies Wholesale Flowers Ltd.",
    "wof:placetype":"venue"
},
  "geometry": {"coordinates":[-1.4652899504,52.422000885],"type":"Point"}
}