{
  "type": "Feature",
  "properties": {
    "iso:country":"GB",
    "sg:address":"152a Central Drive",
    "sg:city":"Blackpool",
    "sg:classifiers":[
        {
            "category":"Personal",
            "subcategory":"Beauty Salon",
            "type":"Services"
        }
    ],
    "sg:phone":"+44 1253 622579",
    "sg:postcode":"FY1 5EA",
    "sg:province":"Lancashire",
    "sg:tags":[
        "unisex",
        "lady",
        "hairdresser"
    ],
    "wof:name":"Innovate Hair Salon",
    "wof:placetype":"venue"
},
  "geometry": {"coordinates":[-3.048122,53.8111],"type":"Point"}
}