{
  "type": "Feature",
  "properties": {
    "addr:full":"Rear Of 9-11 Jubilee Road Weston-super-mare Somerset BS23 3AW",
    "addr:postcode":"bs23 3aw",
    "addr:street":"Jubilee Road",
    "iso:country":"GB",
    "sg:address":"Rear Of 9-11 Jubilee Road",
    "sg:city":"Weston-super-mare",
    "sg:classifiers":[
        {
            "category":"Manufacturing",
            "subcategory":"Glass & Minerals",
            "type":"Manufacturing & Wholesale Goods"
        }
    ],
    "sg:postcode":"BS23 3AW",
    "sg:province":"Somerset",
    "sg:tags":[
        "fibre",
        "moulding"
    ],
    "wof:name":"Craft & Commercial Mouldings",
    "wof:placetype":"venue"
},
  "geometry": {"coordinates":[-2.977184,51.346191],"type":"Point"}
}