{
  "type": "Feature",
  "properties": {
    "addr:full":"Newborough Farm, Oxhill Warwick Warwickshire CV35 0RJ",
    "addr:postcode":"cv35 0rj",
    "addr:street":"Newborough",
    "iso:country":"GB",
    "sg:address":"Newborough Farm, Oxhill",
    "sg:city":"Warwick",
    "sg:classifiers":[
        {
            "category":"Farming",
            "subcategory":"Livestock Farm",
            "type":"Manufacturing & Wholesale Goods"
        }
    ],
    "sg:postcode":"CV35 0RJ",
    "sg:province":"Warwickshire",
    "sg:tags":[
        "others"
    ],
    "wof:name":"Saw,R,",
    "wof:placetype":"venue"
},
  "geometry": {"coordinates":[-1.539107,52.108727],"type":"Point"}
}