{
  "type": "Feature",
  "properties": {
    "addr:full":"The Woodlands Centre Liverpool Merseyside L36 6AD",
    "addr:postcode":"l36 6ad",
    "iso:country":"GB",
    "sg:address":"The Woodlands Centre",
    "sg:city":"Liverpool",
    "sg:classifiers":[
        {
            "category":"Home & Garden",
            "subcategory":"Carpets & Floor Coverings",
            "type":"Retail Goods"
        }
    ],
    "sg:phone":"+44 151 443 0088",
    "sg:postcode":"L36 6AD",
    "sg:province":"Merseyside",
    "sg:tags":[
        "carpets",
        "rug",
        "matting"
    ],
    "wof:name":"Carpeting Merseyside",
    "wof:placetype":"venue"
},
  "geometry": {"coordinates":[-2.81583,53.40097],"type":"Point"}
}