{
  "type": "Feature",
  "properties": {
    "iso:country":"GB",
    "sg:address":"21 Mulberry Court, Goring Road, Goring By Sea",
    "sg:city":"Worthing",
    "sg:classifiers":[
        {
            "category":"Manufacturing",
            "subcategory":"Apparel",
            "type":"Manufacturing & Wholesale Goods"
        }
    ],
    "sg:phone":"+44 1903 245270",
    "sg:postcode":"BN12 4PF",
    "sg:province":"West Sussex",
    "sg:tags":[
        "garment",
        "designer"
    ],
    "wof:name":"Spencer of Banbury",
    "wof:placetype":"venue"
},
  "geometry": {"coordinates":[-0.420817,50.813026],"type":"Point"}
}