{
  "type": "Feature",
  "properties": {
    "addr:full":"Poppystones, 6 Bennett Close, Stoke Golding Nuneaton Leicestershire CV13 6JE",
    "addr:housenumber":"6",
    "addr:postcode":"cv13 6je",
    "addr:street":"Poppystones;Bennett Close;Golding",
    "iso:country":"GB",
    "sg:address":"Poppystones, 6 Bennett Close, Stoke Golding",
    "sg:city":"Nuneaton",
    "sg:classifiers":[
        {
            "category":"Professional",
            "type":"Services"
        }
    ],
    "sg:postcode":"CV13 6JE",
    "sg:province":"Leicestershire",
    "sg:tags":[
        "interior",
        "furnishers",
        "designer"
    ],
    "wof:name":"Poppystone Interiors",
    "wof:placetype":"venue"
},
  "geometry": {"coordinates":[-1.40812397,52.5707397461],"type":"Point"}
}