{
  "type": "Feature",
  "properties": {
    "addr:full":"31 Gidley Way Oxford Buckinghamshire OX33 1RQ",
    "addr:housenumber":"31",
    "addr:postcode":"ox33 1rq",
    "addr:street":"Gidley Way",
    "iso:country":"GB",
    "sg:address":"31 Gidley Way",
    "sg:city":"Oxford",
    "sg:classifiers":[
        {
            "category":"Social Services",
            "subcategory":"Retirement Home",
            "type":"Services"
        }
    ],
    "sg:phone":"+44 1865 875413",
    "sg:postcode":"OX33 1RQ",
    "sg:province":"Buckinghamshire",
    "sg:tags":[
        "care"
    ],
    "wof:name":"Oxford Private Care Ltd",
    "wof:placetype":"venue"
},
  "geometry": {"coordinates":[-1.1687120199,51.7385902405],"type":"Point"}
}