{
  "type": "Feature",
  "properties": {
    "addr:full":"43 York Place Perth Perth and Kinross PH2 8EH",
    "addr:housenumber":"43",
    "addr:postcode":"ph2 8eh",
    "addr:street":"York Place",
    "iso:country":"GB",
    "sg:address":"43 York Place",
    "sg:city":"Perth",
    "sg:classifiers":[
        {
            "category":"Travel",
            "subcategory":"Hotels & Motels",
            "type":"Entertainment"
        }
    ],
    "sg:phone":"+44 1738 635031",
    "sg:postcode":"PH2 8EH",
    "sg:province":"Perth and Kinross",
    "sg:tags":[
        "house",
        "guest"
    ],
    "wof:name":"The Heidl Guest House",
    "wof:placetype":"venue"
},
  "geometry": {"coordinates":[-3.439696,56.395706],"type":"Point"}
}