{
  "type": "Feature",
  "properties": {
    "addr:full":"Tiverton Park, Primary Care Centre Sheffield South Yorkshire S26 6QU",
    "addr:postcode":"s26 6qu",
    "addr:street":"Yorkshire",
    "iso:country":"GB",
    "sg:address":"Tiverton Park, Primary Care Centre",
    "sg:city":"Sheffield",
    "sg:classifiers":[
        {
            "category":"Personal",
            "type":"Services"
        }
    ],
    "sg:phone":"+44 1909 772238",
    "sg:postcode":"S26 6QU",
    "sg:province":"South Yorkshire",
    "sg:tags":[
        "slimming",
        "product"
    ],
    "wof:name":"Slimming World",
    "wof:placetype":"venue"
},
  "geometry": {"coordinates":[-1.2700999975,53.3392715454],"type":"Point"}
}