{
  "type": "Feature",
  "properties": {
    "addr:full":"16 Greenacre Gardens Waterlooville Hampshire PO7 5HG",
    "addr:housenumber":"16",
    "addr:postcode":"po7 5hg",
    "addr:street":"Greenacre Gardens",
    "iso:country":"GB",
    "sg:address":"16 Greenacre Gardens",
    "sg:city":"Waterlooville",
    "sg:classifiers":[
        {
            "category":"Wholesale",
            "subcategory":"Medical Equipment & Supplies",
            "type":"Manufacturing & Wholesale Goods"
        }
    ],
    "sg:phone":"+44 23 9223 0112",
    "sg:postcode":"PO7 5HG",
    "sg:province":"Hampshire",
    "sg:tags":[
        "hospital"
    ],
    "wof:name":"Benmore Medical",
    "wof:placetype":"venue"
},
  "geometry": {"coordinates":[-1.04162,50.863083],"type":"Point"}
}