{
  "type": "Feature",
  "properties": {
    "addr:full":"47 Brantfell Drive Burnley Lancashire BB12 8AW",
    "addr:housenumber":"47",
    "addr:postcode":"bb12 8aw",
    "addr:street":"Brantfell Drive",
    "iso:country":"GB",
    "sg:address":"47 Brantfell Drive",
    "sg:city":"Burnley",
    "sg:classifiers":[
        {
            "category":"Museum",
            "subcategory":"Art Museum",
            "type":"Entertainment"
        },
        {
            "category":"Museum",
            "type":"Entertainment"
        }
    ],
    "sg:phone":"+44 1282 413179",
    "sg:postcode":"BB12 8AW",
    "sg:province":"Lancashire",
    "sg:tags":[
        "gallery"
    ],
    "sg:website":"http://www.kbmt.org.uk",
    "wof:name":"Keighley Bus Museum Trust Limited",
    "wof:placetype":"venue"
},
  "geometry": {"coordinates":[-2.2785320282,53.7971038818],"type":"Point"}
}