{
  "type": "Feature",
  "properties": {
    "iso:country":"GB",
    "sg:address":"25 Andrews Lane",
    "sg:city":"Liverpool",
    "sg:classifiers":[
        {
            "category":"Professional",
            "subcategory":"Art Services",
            "type":"Services"
        },
        {
            "category":"Building & Trades",
            "subcategory":"Construction",
            "type":"Services"
        }
    ],
    "sg:phone":"+44 1704 875209",
    "sg:postcode":"L37 2EP",
    "sg:province":"Lancashire",
    "sg:tags":[
        "glazier",
        "decorator",
        "painter"
    ],
    "wof:name":"Greenwood Artexer",
    "wof:placetype":"venue"
},
  "geometry": {"coordinates":[-3.071014,53.548489],"type":"Point"}
}