{
  "type": "Feature",
  "properties": {
    "addr:full":"24 Orkney Road Portsmouth Hampshire PO6 3UE",
    "addr:housenumber":"24",
    "addr:postcode":"hampshire po6 3ue",
    "addr:street":"Orkney Road",
    "iso:country":"GB",
    "sg:address":"24 Orkney Road",
    "sg:city":"Portsmouth",
    "sg:classifiers":[
        {
            "category":"Health Services",
            "subcategory":"Podiatrist",
            "type":"Services"
        }
    ],
    "sg:postcode":"PO6 3UE",
    "sg:province":"Hampshire",
    "sg:tags":[
        "podiatrists",
        "chiropodist"
    ],
    "wof:name":"David Goodall",
    "wof:placetype":"venue"
},
  "geometry": {"coordinates":[-1.0637600422,50.8514823914],"type":"Point"}
}