{
  "type": "Feature",
  "properties": {
    "iso:country":"GB",
    "sg:address":"12 North Parade",
    "sg:city":"Skegness",
    "sg:classifiers":[
        {
            "category":"Travel",
            "subcategory":"Hotels & Motels",
            "type":"Entertainment"
        }
    ],
    "sg:postcode":"PE25 2UB",
    "sg:province":"Lincolnshire",
    "wof:name":"The Savoy",
    "wof:placetype":"venue"
},
  "geometry": {"coordinates":[0.345296,53.146465],"type":"Point"}
}