{
  "type": "Feature",
  "properties": {
    "addr:full":"Westfield Farm, Pateley Bridge Harrogate North Yorkshire HG3 5BX",
    "addr:housenumber":"pateley",
    "addr:postcode":"hg3 5bx",
    "addr:street":"Bridge",
    "iso:country":"GB",
    "sg:address":"Westfield Farm, Pateley Bridge",
    "sg:city":"Harrogate",
    "sg:classifiers":[
        {
            "category":"Recreation",
            "subcategory":"Campground",
            "type":"Entertainment"
        }
    ],
    "sg:phone":"+44 1423 711410",
    "sg:postcode":"HG3 5BX",
    "sg:province":"North Yorkshire",
    "sg:tags":[
        "site",
        "camping"
    ],
    "wof:name":"Westfield Caravan Site",
    "wof:placetype":"venue"
},
  "geometry": {"coordinates":[-1.759024,54.086426],"type":"Point"}
}