{
  "type": "Feature",
  "properties": {
    "addr:full":"469 Bromley Rd, Downham Bromley Kent BR1 4PH",
    "addr:housenumber":"469",
    "addr:postcode":"br1 4ph",
    "addr:street":"Bromley Rd",
    "iso:country":"GB",
    "sg:address":"469 Bromley Rd, Downham",
    "sg:city":"Bromley",
    "sg:classifiers":[
        {
            "category":"Travel",
            "subcategory":"Travel Agent",
            "type":"Entertainment"
        }
    ],
    "sg:phone":"+44 20 8698 0074",
    "sg:postcode":"BR1 4PH",
    "sg:province":"Kent",
    "wof:name":"Worldchoice Carlson",
    "wof:placetype":"venue"
},
  "geometry": {"coordinates":[-0.0039329999,51.4245605469],"type":"Point"}
}