{
  "type": "Feature",
  "properties": {
    "addr:full":"8 Osborne Road Bath Bath and North East Somerset BA1 3JR",
    "addr:housenumber":"8",
    "addr:postcode":"ba1 3jr",
    "addr:street":"Osborne Road",
    "iso:country":"GB",
    "sg:address":"8 Osborne Road",
    "sg:city":"Bath",
    "sg:classifiers":[
        {
            "category":"Retail",
            "subcategory":"Driving School",
            "type":"Services"
        }
    ],
    "sg:postcode":"BA1 3JR",
    "sg:province":"Bath and North East Somerset",
    "wof:name":"Hicks School of Motoring",
    "wof:placetype":"venue"
},
  "geometry": {"coordinates":[-2.395079,51.383327],"type":"Point"}
}