{
  "type": "Feature",
  "properties": {
    "iso:country":"GB",
    "sg:address":"18 Ballards Lane, Church End",
    "sg:city":"London",
    "sg:classifiers":[
        {
            "category":"Banks & Credit Unions",
            "subcategory":"Bank",
            "type":"Services"
        }
    ],
    "sg:phone":"+44 845 740 4404",
    "sg:postcode":"N3 2BH",
    "sg:province":"Greater London",
    "sg:tags":[
        "financial",
        "institution"
    ],
    "sg:website":"http://www.hsbc.co.uk",
    "wof:name":"HSBC Bank plc",
    "wof:placetype":"venue"
},
  "geometry": {"coordinates":[-0.192639,51.601994],"type":"Point"}
}