{
  "type": "Feature",
  "properties": {
    "addr:full":"Tanglewood, High Oakham Road Mansfield Nottinghamshire NG18 5AJ",
    "addr:postcode":"ng18 5aj",
    "addr:street":"Oakham Road",
    "iso:country":"GB",
    "sg:address":"Tanglewood, High Oakham Road",
    "sg:city":"Mansfield",
    "sg:classifiers":[
        {
            "category":"Building & Trades",
            "subcategory":"Construction",
            "type":"Services"
        }
    ],
    "sg:phone":"+44 1623 427760",
    "sg:postcode":"NG18 5AJ",
    "sg:province":"Nottinghamshire",
    "sg:tags":[
        "builder"
    ],
    "wof:name":"Daw Construction Ltd.",
    "wof:placetype":"venue"
},
  "geometry": {"coordinates":[-1.201743,53.144024],"type":"Point"}
}