{
  "type": "Feature",
  "properties": {
    "iso:country":"GB",
    "sg:address":"24 Bridge Street",
    "sg:city":"Pinner",
    "sg:classifiers":[
        {
            "category":"Shopping",
            "subcategory":"Pharmacy",
            "type":"Retail Goods"
        }
    ],
    "sg:postcode":"HA5 3JF",
    "sg:province":"Greater London",
    "sg:tags":[
        "pharmacist",
        "chemist"
    ],
    "wof:name":"Carters",
    "wof:placetype":"venue"
},
  "geometry": {"coordinates":[-0.3832660019,51.5948753357],"type":"Point"}
}