{
  "type": "Feature",
  "properties": {
    "addr:full":"19 Crowhurst Peterborough Cambridgeshire PE4 6JY",
    "addr:housenumber":"19",
    "addr:postcode":"pe4 6jy",
    "addr:street":"Crowhurst Peterborough",
    "iso:country":"GB",
    "sg:address":"19 Crowhurst",
    "sg:city":"Peterborough",
    "sg:classifiers":[
        {
            "category":"Retail",
            "subcategory":"Auto Repair",
            "type":"Services"
        }
    ],
    "sg:phone":"+44 7774 422499",
    "sg:postcode":"PE4 6JY",
    "sg:province":"Cambridgeshire",
    "sg:tags":[
        "modification",
        "garage"
    ],
    "wof:name":"Auto Service Group",
    "wof:placetype":"venue"
},
  "geometry": {"coordinates":[-0.26898,52.622887],"type":"Point"}
}