{
  "type": "Feature",
  "properties": {
    "iso:country":"GB",
    "sg:address":"92-94 Fleet Street",
    "sg:city":"Ashton-under-lyne",
    "sg:classifiers":[
        {
            "category":"Autos & Motor Vehicles",
            "subcategory":"Auto Supplies",
            "type":"Retail Goods"
        }
    ],
    "sg:postcode":"OL6 7QE",
    "sg:province":"Greater Manchester",
    "sg:tags":[
        "car",
        "audio"
    ],
    "wof:name":"Ashton Car Alarm Centre",
    "wof:placetype":"venue"
},
  "geometry": {"coordinates":[-2.0953290462,53.4864082336],"type":"Point"}
}