{
  "type": "Feature",
  "properties": {
    "iso:country":"GB",
    "sg:address":"42 Western Road",
    "sg:city":"Lymington",
    "sg:classifiers":[
        {
            "category":"Professional",
            "subcategory":"Computer Services",
            "type":"Services"
        }
    ],
    "sg:postcode":"SO41 9HL",
    "sg:province":"Hampshire",
    "sg:tags":[
        "consultant"
    ],
    "wof:name":"Carrington Network Services Ltd.",
    "wof:placetype":"venue"
},
  "geometry": {"coordinates":[-1.553235,50.759117],"type":"Point"}
}