{
  "type": "Feature",
  "properties": {
    "addr:full":"Wilton House Marlborough Berkshire SN8 2AA",
    "addr:postcode":"sn8 2aa",
    "iso:country":"GB",
    "sg:address":"Wilton House",
    "sg:city":"Marlborough",
    "sg:classifiers":[
        {
            "category":"Professional",
            "subcategory":"Lawyer & Legal Services",
            "type":"Services"
        }
    ],
    "sg:phone":"+44 1672 515411",
    "sg:postcode":"SN8 2AA",
    "sg:province":"Berkshire",
    "wof:name":"M E Clarke",
    "wof:placetype":"venue"
},
  "geometry": {"coordinates":[-1.6496189833,51.4443588257],"type":"Point"}
}