{
  "type": "Feature",
  "properties": {
    "addr:full":"1-3 Tithe Barn Street, Horbury Wakefield West Yorkshire WF4 6HN",
    "addr:housenumber":"1-3",
    "addr:postcode":"wf4 6hn",
    "addr:street":"Tithe Barn Street;West",
    "iso:country":"GB",
    "sg:address":"1-3 Tithe Barn Street, Horbury",
    "sg:city":"Wakefield",
    "sg:classifiers":[
        {
            "category":"Education",
            "subcategory":"Special Training",
            "type":"Public Place"
        }
    ],
    "sg:phone":"+44 1924 280410",
    "sg:postcode":"WF4 6HN",
    "sg:province":"West Yorkshire",
    "sg:tags":[
        "product",
        "centre"
    ],
    "wof:name":"Spot-on Electronic Publishing Ltd.",
    "wof:placetype":"venue"
},
  "geometry": {"coordinates":[-1.5593390465,53.660785675],"type":"Point"}
}