{
  "type": "Feature",
  "properties": {
    "addr:full":"No : 8 Theatre Yard, Low Pavement Chesterfield Derbyshire S40 1PF",
    "addr:postcode":"s40 1pf",
    "addr:street":"Low Pavement",
    "iso:country":"GB",
    "sg:address":"No : 8 Theatre Yard, Low Pavement",
    "sg:city":"Chesterfield",
    "sg:classifiers":[
        {
            "category":"Wholesale",
            "subcategory":"Toys & Hobbies",
            "type":"Manufacturing & Wholesale Goods"
        }
    ],
    "sg:phone":"+44 1246 556071",
    "sg:postcode":"S40 1PF",
    "sg:province":"Derbyshire",
    "sg:tags":[
        "balloon",
        "novelty"
    ],
    "wof:name":"The Party Shop",
    "wof:placetype":"venue"
},
  "geometry": {"coordinates":[-1.4275000095,53.2348213196],"type":"Point"}
}