{
  "type": "Feature",
  "properties": {
    "iso:country":"GB",
    "sg:address":"Lochrigghead Farm, Parkgate",
    "sg:city":"Dumfries",
    "sg:classifiers":[
        {
            "category":"Home & Garden",
            "subcategory":"Garden Supply",
            "type":"Retail Goods"
        }
    ],
    "sg:postcode":"DG1 3NG",
    "sg:province":"Dumfries and Galloway",
    "sg:tags":[
        "bulb",
        "grower"
    ],
    "wof:name":"Fisher,S & J,",
    "wof:placetype":"venue"
},
  "geometry": {"coordinates":[-3.544029,55.172501],"type":"Point"}
}