{
  "type": "Feature",
  "properties": {
    "iso:country":"GB",
    "sg:address":"Unit 7 Racecourse Rd",
    "sg:city":"Pershore",
    "sg:classifiers":[
        {
            "category":"Retail",
            "subcategory":"Auto Repair",
            "type":"Services"
        }
    ],
    "sg:postcode":"WR10 2EY",
    "sg:province":"Worcestershire",
    "sg:tags":[
        "modification",
        "garage"
    ],
    "wof:name":"Edney,F,",
    "wof:placetype":"venue"
},
  "geometry": {"coordinates":[-2.072894,52.12928],"type":"Point"}
}