{
  "type": "Feature",
  "properties": {
    "iso:country":"GB",
    "sg:address":"137 Water Street",
    "sg:city":"Port Talbot",
    "sg:classifiers":[
        {
            "category":"Building & Trades",
            "subcategory":"Equipment Rental",
            "type":"Services"
        }
    ],
    "sg:phone":"+44 1639 894567",
    "sg:postcode":"SA12 6LF",
    "sg:province":"Neath Port Talbot",
    "sg:tags":[
        "plant",
        "tool",
        "hire",
        "centre"
    ],
    "wof:name":"Brandon Hire Plc",
    "wof:placetype":"venue"
},
  "geometry": {"coordinates":[-3.787838,51.595047],"type":"Point"}
}