{
  "type": "Feature",
  "properties": {
    "addr:full":"9 Fishers Clo Northampton Northamptonshire NN3 9SR",
    "addr:housenumber":"9",
    "addr:postcode":"nn3 9sr",
    "addr:street":"Fishers Clo",
    "iso:country":"GB",
    "sg:address":"9 Fishers Clo",
    "sg:city":"Northampton",
    "sg:classifiers":[
        {
            "category":"Professional",
            "subcategory":"Lawyer & Legal Services",
            "type":"Services"
        }
    ],
    "sg:phone":"+44 1604 416800",
    "sg:postcode":"NN3 9SR",
    "sg:province":"Northamptonshire",
    "sg:tags":[
        "advice",
        "counselling"
    ],
    "wof:name":"CRUSE Bereavement Care",
    "wof:placetype":"venue"
},
  "geometry": {"coordinates":[-0.8183220029,52.2505607605],"type":"Point"}
}