{
  "type": "Feature",
  "properties": {
    "iso:country":"GB",
    "sg:address":"Railway Bookstall",
    "sg:city":"Grange-over-sands",
    "sg:classifiers":[
        {
            "category":"Shopping",
            "subcategory":"News",
            "type":"Retail Goods"
        }
    ],
    "sg:phone":"+44 15395 33021",
    "sg:postcode":"LA11 7JR",
    "sg:province":"Cumbria",
    "sg:tags":[
        "newsagent"
    ],
    "wof:name":"J N Brennard",
    "wof:placetype":"venue"
},
  "geometry": {"coordinates":[-2.92164,54.184158],"type":"Point"}
}