{
  "type": "Feature",
  "properties": {
    "iso:country":"GB",
    "sg:address":"7-8 New Road Avenue",
    "sg:city":"Chatham",
    "sg:classifiers":[
        {
            "category":"Travel",
            "subcategory":"Hotels & Motels",
            "type":"Entertainment"
        }
    ],
    "sg:phone":"+44 1634 841012",
    "sg:postcode":"ME4 6BB",
    "sg:province":"Kent",
    "wof:name":"ST. GEORGE HOTEL (CHATHAM) LTD",
    "wof:placetype":"venue"
},
  "geometry": {"coordinates":[0.5180400014,51.3823890686],"type":"Point"}
}