{
  "type": "Feature",
  "properties": {
    "iso:country":"GB",
    "sg:address":"48 Main Street, Bothwell",
    "sg:city":"Glasgow",
    "sg:classifiers":[
        {
            "category":"Personal",
            "subcategory":"Beauty Salon",
            "type":"Services"
        },
        {
            "category":"Personal",
            "subcategory":"Barber",
            "type":"Services"
        }
    ],
    "sg:phone":"+44 1698 853885",
    "sg:postcode":"G71 8EX",
    "sg:province":"Glasgow City",
    "sg:tags":[
        "unisex",
        "hairdresser"
    ],
    "wof:name":"Paolo's Hair Salon",
    "wof:placetype":"venue"
},
  "geometry": {"coordinates":[-4.068588,55.8032],"type":"Point"}
}