{
  "type": "Feature",
  "properties": {
    "iso:country":"GB",
    "sg:address":"109 High Street",
    "sg:city":"Tewkesbury",
    "sg:classifiers":[
        {
            "category":"Professional",
            "subcategory":"Management & Consulting",
            "type":"Services"
        }
    ],
    "sg:postcode":"GL20 5JZ",
    "sg:province":"Gloucestershire",
    "sg:tags":[
        "consultant",
        "specialist"
    ],
    "wof:name":"Jays",
    "wof:placetype":"venue"
},
  "geometry": {"coordinates":[-2.156371,51.994984],"type":"Point"}
}