{
  "type": "Feature",
  "properties": {
    "iso:country":"GB",
    "sg:address":"3 Langdale Road",
    "sg:city":"Sale",
    "sg:classifiers":[
        {
            "category":"Retail",
            "subcategory":"Driving School",
            "type":"Services"
        }
    ],
    "sg:postcode":"M33 4EN",
    "sg:province":"Cheshire",
    "wof:name":"Sue Foster School of Motoring",
    "wof:placetype":"venue"
},
  "geometry": {"coordinates":[-2.340738,53.410351],"type":"Point"}
}