{
  "type": "Feature",
  "properties": {
    "addr:full":"44 Town Lane, Hale Liverpool Merseyside L24 4AQ",
    "addr:housenumber":"44",
    "addr:postcode":"l24 4aq",
    "addr:street":"Town Lane",
    "iso:country":"GB",
    "sg:address":"44 Town Lane, Hale",
    "sg:city":"Liverpool",
    "sg:classifiers":[
        {
            "category":"Shopping",
            "subcategory":"Stationery & Office Supplies",
            "type":"Retail Goods"
        }
    ],
    "sg:postcode":"L24 4AQ",
    "sg:province":"Merseyside",
    "sg:tags":[
        "recording",
        "machine",
        "time"
    ],
    "wof:name":"Hale Antique Clock Restoration",
    "wof:placetype":"venue"
},
  "geometry": {"coordinates":[-2.7969880104,53.3383102417],"type":"Point"}
}