{
  "type": "Feature",
  "properties": {
    "addr:full":"1 Angel Walk Tonbridge Kent TN9 1TJ",
    "addr:housenumber":"1",
    "addr:postcode":"tn9 1tj",
    "addr:street":"Angel Walk",
    "iso:country":"GB",
    "sg:address":"1 Angel Walk",
    "sg:city":"Tonbridge",
    "sg:classifiers":[
        {
            "category":"Shopping",
            "subcategory":"Comic Books",
            "type":"Retail Goods"
        }
    ],
    "sg:phone":"+44 1732 360109",
    "sg:postcode":"TN9 1TJ",
    "sg:province":"Kent",
    "sg:tags":[
        "jeweller",
        "sale",
        "jewellery"
    ],
    "wof:name":"Heasmans the Jewellers Ltd.",
    "wof:placetype":"venue"
},
  "geometry": {"coordinates":[0.273905009,51.1929702759],"type":"Point"}
}