{
  "type": "Feature",
  "properties": {
    "addr:full":"Unit 2a Newson Buildings Buckfastleigh Devon TQ11 0NR",
    "addr:housenumber":"unit 2a",
    "addr:postcode":"tq11 0nr",
    "addr:street":"Newson Buildings",
    "iso:country":"GB",
    "sg:address":"Unit 2a Newson Buildings",
    "sg:city":"Buckfastleigh",
    "sg:classifiers":[
        {
            "category":"Food & Beverages",
            "subcategory":"Supermarket",
            "type":"Retail Goods"
        }
    ],
    "sg:phone":"+44 1364 642700",
    "sg:postcode":"TQ11 0NR",
    "sg:province":"Devon",
    "sg:tags":[
        "frozen"
    ],
    "wof:name":"Dragonfly Foods Ltd.",
    "wof:placetype":"venue"
},
  "geometry": {"coordinates":[-3.779209,50.481369],"type":"Point"}
}