{
  "type": "Feature",
  "properties": {
    "addr:full":"128 Woodfield Street, Morriston Swansea Swansea SA6 8AL",
    "addr:housenumber":"128",
    "addr:postcode":"sa6 8al",
    "addr:street":"Woodfield Street",
    "iso:country":"GB",
    "sg:address":"128 Woodfield Street, Morriston",
    "sg:city":"Swansea",
    "sg:classifiers":[
        {
            "category":"Cafe",
            "type":"Food & Drink"
        }
    ],
    "sg:phone":"+44 1792 410748",
    "sg:postcode":"SA6 8AL",
    "sg:province":"Swansea",
    "sg:tags":[
        "tea",
        "room"
    ],
    "wof:name":"Cafe Supreme & Fish Bar",
    "wof:placetype":"venue"
},
  "geometry": {"coordinates":[-3.925343,51.665993],"type":"Point"}
}