{
  "type": "Feature",
  "properties": {
    "addr:full":"Unit 5, Millennia Park, Thornes Road Wakefield West Yorkshire WF2 8PW",
    "addr:housenumber":"unit 5",
    "addr:postcode":"wf2 8pw",
    "addr:street":"Millennia Park Thornes Road",
    "iso:country":"GB",
    "sg:address":"Unit 5, Millennia Park, Thornes Road",
    "sg:city":"Wakefield",
    "sg:classifiers":[
        {
            "category":"Recreation",
            "subcategory":"Amusement Park",
            "type":"Entertainment"
        },
        {
            "category":"Recreation",
            "subcategory":"Go Karts",
            "type":"Entertainment"
        }
    ],
    "sg:phone":"+44 1924 201808",
    "sg:postcode":"WF2 8PW",
    "sg:province":"West Yorkshire",
    "sg:tags":[
        "karting",
        "corporate",
        "hospitality"
    ],
    "sg:website":"http://www.f1-karting.co.uk",
    "wof:name":"F 1 Indoor Karting Ltd.",
    "wof:placetype":"venue"
},
  "geometry": {"coordinates":[-1.5102740526,53.6799697876],"type":"Point"}
}