{
  "type": "Feature",
  "properties": {
    "addr:full":"72 Broadway Bexleyheath Kent DA6 7DF",
    "addr:housenumber":"72",
    "addr:postcode":"da6 7df",
    "addr:street":"Broadway",
    "iso:country":"GB",
    "sg:address":"72 Broadway",
    "sg:city":"Bexleyheath",
    "sg:classifiers":[
        {
            "category":"Food & Beverages",
            "subcategory":"Supermarket",
            "type":"Retail Goods"
        }
    ],
    "sg:phone":"+44 20 8298 0376",
    "sg:postcode":"DA6 7DF",
    "sg:province":"Kent",
    "wof:name":"J Sainsbury Plc",
    "wof:placetype":"venue"
},
  "geometry": {"coordinates":[0.14488,51.456436],"type":"Point"}
}