{
  "type": "Feature",
  "properties": {
    "addr:full":"476 Felixstowe Road Ipswich Suffolk IP3 8SU",
    "addr:housenumber":"476",
    "addr:postcode":"ip3 8su",
    "addr:street":"Felixstowe Road",
    "iso:country":"GB",
    "sg:address":"476 Felixstowe Road",
    "sg:city":"Ipswich",
    "sg:classifiers":[
        {
            "category":"Building & Trades",
            "subcategory":"Plumbing",
            "type":"Services"
        }
    ],
    "sg:phone":"+44 1473 623111",
    "sg:postcode":"IP3 8SU",
    "sg:province":"Suffolk",
    "sg:tags":[
        "shower",
        "plumber",
        "accessory"
    ],
    "wof:name":"THE SHOWER SHOP",
    "wof:placetype":"venue"
},
  "geometry": {"coordinates":[1.1976310015,52.042049408],"type":"Point"}
}