{
  "type": "Feature",
  "properties": {
    "iso:country":"GB",
    "sg:address":"137-143 Stand Lane, Radcliffe",
    "sg:city":"Manchester",
    "sg:classifiers":[
        {
            "category":"Travel",
            "subcategory":"Hotels & Motels",
            "type":"Entertainment"
        }
    ],
    "sg:phone":"+44 161 723 2706",
    "sg:postcode":"M26 1JR",
    "sg:province":"Greater Manchester",
    "wof:name":"The Hawthorn Hotel",
    "wof:placetype":"venue"
},
  "geometry": {"coordinates":[-2.3196110725,53.5556335449],"type":"Point"}
}