{
  "type": "Feature",
  "properties": {
    "addr:full":"Red Star Parcels, Station Yard Liskeard Cornwall PL14 4DX",
    "addr:postcode":"pl14 4dx",
    "iso:country":"GB",
    "sg:address":"Red Star Parcels, Station Yard",
    "sg:city":"Liskeard",
    "sg:classifiers":[
        {
            "category":"Train Station",
            "subcategory":"Rail",
            "type":"Transportation"
        }
    ],
    "sg:phone":"+44 1579 345509",
    "sg:postcode":"PL14 4DX",
    "sg:province":"Cornwall",
    "sg:tags":[
        "railway"
    ],
    "wof:name":"British Rail",
    "wof:placetype":"venue"
},
  "geometry": {"coordinates":[-4.465834,50.453796],"type":"Point"}
}