{
  "type": "Feature",
  "properties": {
    "iso:country":"GB",
    "sg:address":"28-29 West, Sunniside",
    "sg:city":"Sunderland",
    "sg:classifiers":[
        {
            "category":"Professional",
            "subcategory":"Accounting & Tax Preparation",
            "type":"Services"
        }
    ],
    "sg:phone":"+44 191 567 3694",
    "sg:postcode":"SR1 1BX",
    "sg:province":"Tyne and Wear",
    "sg:tags":[
        "accountant"
    ],
    "wof:name":"West Waters",
    "wof:placetype":"venue"
},
  "geometry": {"coordinates":[-1.378213,54.905872],"type":"Point"}
}