{
  "type": "Feature",
  "properties": {
    "addr:full":"1st Floor Black Horse House, 91 Sandyford Road Newcastle-upon-tyne Tyne and Wear NE1 8HQ",
    "addr:housenumber":"91",
    "addr:postcode":"ne1 8hq",
    "addr:street":"Sandyford Road",
    "iso:country":"GB",
    "sg:address":"1st Floor Black Horse House, 91 Sandyford Road",
    "sg:city":"Newcastle-upon-tyne",
    "sg:classifiers":[
        {
            "category":"Banks & Credit Unions",
            "subcategory":"Bank",
            "type":"Services"
        }
    ],
    "sg:phone":"+44 191 255 1500",
    "sg:postcode":"NE1 8HQ",
    "sg:province":"Tyne and Wear",
    "wof:name":"Lloyds Tsb Bank Plc",
    "wof:placetype":"venue"
},
  "geometry": {"coordinates":[-1.609267,54.980457],"type":"Point"}
}