{
  "type": "Feature",
  "properties": {
    "addr:full":"5 Satley Road Billingham Durham TS23 3RU",
    "addr:housenumber":"5",
    "addr:postcode":"ts23 3ru",
    "addr:street":"Satley Road",
    "iso:country":"GB",
    "sg:address":"5 Satley Road",
    "sg:city":"Billingham",
    "sg:classifiers":[
        {
            "category":"Building & Trades",
            "subcategory":"Plumbing",
            "type":"Services"
        }
    ],
    "sg:postcode":"TS23 3RU",
    "sg:province":"Durham",
    "sg:tags":[
        "central",
        "heating"
    ],
    "wof:name":"Adams & McGlade",
    "wof:placetype":"venue"
},
  "geometry": {"coordinates":[-1.279537,54.623489],"type":"Point"}
}