{
  "type": "Feature",
  "properties": {
    "iso:country":"GB",
    "sg:address":"20 Stafford Street",
    "sg:city":"Edinburgh",
    "sg:classifiers":[
        {
            "category":"Professional",
            "subcategory":"Accounting & Tax Preparation",
            "type":"Services"
        }
    ],
    "sg:postcode":"EH3 7BD",
    "sg:province":"City of Edinburgh",
    "sg:tags":[
        "accountant"
    ],
    "wof:name":"Stephen Hay & Associates Ltd",
    "wof:placetype":"venue"
},
  "geometry": {"coordinates":[-3.211596,55.949772],"type":"Point"}
}