{
  "type": "Feature",
  "properties": {
    "addr:full":"22 Laurie Street Edinburgh City of Edinburgh EH6 7AB",
    "addr:housenumber":"22",
    "addr:postcode":"eh6 7ab",
    "addr:street":"Laurie Street",
    "iso:country":"GB",
    "sg:address":"22 Laurie Street",
    "sg:city":"Edinburgh",
    "sg:classifiers":[
        {
            "category":"Building & Trades",
            "subcategory":"Construction",
            "type":"Services"
        }
    ],
    "sg:phone":"+44 131 553 1244",
    "sg:postcode":"EH6 7AB",
    "sg:province":"City of Edinburgh",
    "sg:tags":[
        "ventilation",
        "contractor"
    ],
    "wof:name":"Macfadyen Preservation Ltd.",
    "wof:placetype":"venue"
},
  "geometry": {"coordinates":[-3.1698439121,55.971157074],"type":"Point"}
}