{
  "type": "Feature",
  "properties": {
    "addr:full":"Low Grn, Staveley Kendal Cumbria LA8 9RA",
    "addr:postcode":"la8 9ra",
    "addr:street":"Low Grn",
    "iso:country":"GB",
    "sg:address":"Low Grn, Staveley",
    "sg:city":"Kendal",
    "sg:classifiers":[
        {
            "category":"Home & Garden",
            "subcategory":"Furniture",
            "type":"Retail Goods"
        }
    ],
    "sg:postcode":"LA8 9RA",
    "sg:province":"Cumbria",
    "wof:name":"Roberts,Paul,Kitchens",
    "wof:placetype":"venue"
},
  "geometry": {"coordinates":[-2.8192470074,54.3721847534],"type":"Point"}
}