{
  "type": "Feature",
  "properties": {
    "iso:country":"GB",
    "sg:address":"86 Van Diemans Road, Wombourne",
    "sg:city":"Wolverhampton",
    "sg:classifiers":[
        {
            "category":"Freight",
            "type":"Transportation"
        }
    ],
    "sg:postcode":"WV5 0DE",
    "sg:province":"Shropshire",
    "sg:tags":[
        "haulage",
        "road"
    ],
    "wof:name":"M & M Transport",
    "wof:placetype":"venue"
},
  "geometry": {"coordinates":[-2.196929,52.52755],"type":"Point"}
}