{
  "type": "Feature",
  "properties": {
    "addr:full":"Sudbury Avenue Hereford Herefordshire HR1 1UN",
    "addr:postcode":"hr1 1un",
    "addr:street":"Sudbury Avenue",
    "iso:country":"GB",
    "sg:address":"Sudbury Avenue",
    "sg:city":"Hereford",
    "sg:classifiers":[
        {
            "category":"Health Services",
            "subcategory":"Doctor",
            "type":"Services"
        }
    ],
    "sg:phone":"+44 1432 264016",
    "sg:postcode":"HR1 1UN",
    "sg:province":"Herefordshire",
    "sg:tags":[
        "practitioners"
    ],
    "wof:name":"Hampton Dene Surgery",
    "wof:placetype":"venue"
},
  "geometry": {"coordinates":[-2.68122,52.05164],"type":"Point"}
}