{
  "type": "Feature",
  "properties": {
    "iso:country":"GB",
    "sg:address":"Cornwallis Road",
    "sg:city":"Rugby",
    "sg:classifiers":[
        {
            "category":"Education",
            "subcategory":"School",
            "type":"Public Place"
        }
    ],
    "sg:phone":"+44 1788 811392",
    "sg:postcode":"CV22 7HN",
    "sg:province":"Warwickshire",
    "sg:tags":[
        "local",
        "authority"
    ],
    "wof:name":"Henry Hinde Junior School",
    "wof:placetype":"venue"
},
  "geometry": {"coordinates":[-1.292976,52.370087],"type":"Point"}
}