{
  "type": "Feature",
  "properties": {
    "iso:country":"GB",
    "sg:address":"Unit 1/2",
    "sg:city":"Settle",
    "sg:classifiers":[
        {
            "category":"Cinema",
            "subcategory":"Movie Rental",
            "type":"Entertainment"
        }
    ],
    "sg:phone":"+44 1729 823281",
    "sg:postcode":"BD24 9EH",
    "sg:province":"North Yorkshire",
    "sg:tags":[
        "video",
        "library"
    ],
    "wof:name":"VISTA VIDEO",
    "wof:placetype":"venue"
},
  "geometry": {"coordinates":[-2.272949,54.080441],"type":"Point"}
}