{
  "type": "Feature",
  "properties": {
    "iso:country":"GB",
    "sg:address":"78 High St",
    "sg:city":"Aberlour",
    "sg:classifiers":[
        {
            "category":"Shopping",
            "subcategory":"Pets & Pet Supplies",
            "type":"Retail Goods"
        }
    ],
    "sg:postcode":"AB38 9QA",
    "sg:province":"Moray",
    "wof:name":"Anderson,A M,",
    "wof:placetype":"venue"
},
  "geometry": {"coordinates":[-3.2237288952,57.4715385437],"type":"Point"}
}