{
  "type": "Feature",
  "properties": {
    "iso:country":"GB",
    "sg:address":"The Square, Praze",
    "sg:city":"Camborne",
    "sg:classifiers":[
        {
            "category":"Food & Beverages",
            "subcategory":"Meat & Fish",
            "type":"Retail Goods"
        }
    ],
    "sg:postcode":"TR14 0JR",
    "sg:province":"Cornwall",
    "sg:tags":[
        "chip"
    ],
    "wof:name":"Hart's Fish & Shop",
    "wof:placetype":"venue"
},
  "geometry": {"coordinates":[-5.311992,50.174599],"type":"Point"}
}