{
  "type": "Feature",
  "properties": {
    "iso:country":"GB",
    "sg:address":"Unit 1 Cauldwell Ct, Cauldwell Walk",
    "sg:city":"Bedford",
    "sg:classifiers":[
        {
            "category":"Building & Trades",
            "subcategory":"Construction",
            "type":"Services"
        }
    ],
    "sg:phone":"+44 1234 360015",
    "sg:postcode":"MK42 9DT",
    "sg:province":"Bedfordshire",
    "sg:tags":[
        "builder"
    ],
    "wof:name":"Owlswood Building & Decorating Contractors",
    "wof:placetype":"venue"
},
  "geometry": {"coordinates":[-0.4674699903,52.132522583],"type":"Point"}
}