{
  "type": "Feature",
  "properties": {
    "iso:country":"GB",
    "sg:address":"4 Midhurst Gardens",
    "sg:city":"Luton",
    "sg:classifiers":[
        {
            "category":"Building & Trades",
            "subcategory":"Construction",
            "type":"Services"
        }
    ],
    "sg:phone":"+44 1582 419450",
    "sg:postcode":"LU3 1UG",
    "sg:province":"Bedfordshire",
    "sg:tags":[
        "roofing"
    ],
    "wof:name":"Dyjon Roofing",
    "wof:placetype":"venue"
},
  "geometry": {"coordinates":[-0.425209,51.903694],"type":"Point"}
}