{
  "type": "Feature",
  "properties": {
    "addr:full":"732 Ecclesall Road Sheffield Derbyshire S11 8TB",
    "addr:housenumber":"732",
    "addr:postcode":"s11 8tb",
    "addr:street":"Ecclesall Road",
    "iso:country":"GB",
    "sg:address":"732 Ecclesall Road",
    "sg:city":"Sheffield",
    "sg:classifiers":[
        {
            "category":"Fast Food",
            "type":"Food & Drink"
        }
    ],
    "sg:phone":"+44 114 268 1168",
    "sg:postcode":"S11 8TB",
    "sg:province":"Derbyshire",
    "sg:tags":[
        "away",
        "meal",
        "outlet",
        "take"
    ],
    "wof:name":"China Kitchen",
    "wof:placetype":"venue"
},
  "geometry": {"coordinates":[-1.5068320036,53.3664703369],"type":"Point"}
}