{
  "type": "Feature",
  "properties": {
    "iso:country":"GB",
    "sg:address":"40 Queen Square",
    "sg:city":"Bristol",
    "sg:classifiers":[
        {
            "category":"Professional",
            "subcategory":"Lawyer & Legal Services",
            "type":"Services"
        }
    ],
    "sg:phone":"+44 117 925 3030",
    "sg:postcode":"BS1 4LE",
    "sg:province":"City of Bristol",
    "sg:tags":[
        "patent",
        "agent"
    ],
    "wof:name":"Withers & Rogers",
    "wof:placetype":"venue"
},
  "geometry": {"coordinates":[-2.595246,51.449745],"type":"Point"}
}