{
  "type": "Feature",
  "properties": {
    "iso:country":"GB",
    "sg:address":"Tan Y Lan Farm, St Mary Hill",
    "sg:city":"Bridgend",
    "sg:classifiers":[
        {
            "category":"Farming",
            "subcategory":"Livestock Farm",
            "type":"Manufacturing & Wholesale Goods"
        }
    ],
    "sg:postcode":"CF35 5BY",
    "sg:province":"Bridgend",
    "sg:tags":[
        "others"
    ],
    "wof:name":"P J Rees",
    "wof:placetype":"venue"
},
  "geometry": {"coordinates":[-3.5053300858,51.5057907104],"type":"Point"}
}