{
  "type": "Feature",
  "properties": {
    "addr:full":"Barn Way, Lodge Farm Industrial Estate, Duston Northampton Northamptonshire NN5 7UW",
    "addr:housenumber":"estate",
    "addr:postcode":"nn5 7uw",
    "addr:street":"Barn Way Lodge Farm Industrial",
    "iso:country":"GB",
    "sg:address":"Barn Way, Lodge Farm Industrial Estate, Duston",
    "sg:city":"Northampton",
    "sg:classifiers":[
        {
            "category":"Manufacturing",
            "subcategory":"Lumber",
            "type":"Manufacturing & Wholesale Goods"
        }
    ],
    "sg:phone":"+44 1604 759222",
    "sg:postcode":"NN5 7UW",
    "sg:province":"Northamptonshire",
    "sg:tags":[
        "importer",
        "merchants",
        "agent",
        "timber"
    ],
    "wof:name":"Eco Timber Panels Ltd.",
    "wof:placetype":"venue"
},
  "geometry": {"coordinates":[-0.945029,52.259708],"type":"Point"}
}