{
  "type": "Feature",
  "properties": {
    "iso:country":"GB",
    "sg:address":"Cotton Abbotts, Guy Lane, Waverton",
    "sg:city":"Chester",
    "sg:classifiers":[
        {
            "category":"Retail",
            "subcategory":"Repair Shop",
            "type":"Services"
        },
        {
            "category":"Wholesale",
            "subcategory":"Machinery & Supplies",
            "type":"Manufacturing & Wholesale Goods"
        }
    ],
    "sg:phone":"+44 1244 335753",
    "sg:postcode":"CH3 7PH",
    "sg:province":"Cheshire",
    "sg:tags":[
        "agricultural",
        "sale"
    ],
    "sg:website":"http://www.zeroagri.co.uk",
    "wof:name":"Zero",
    "wof:placetype":"venue"
},
  "geometry": {"coordinates":[-2.8212890625,53.1696586609],"type":"Point"}
}