{
  "type": "Feature",
  "properties": {
    "iso:country":"GB",
    "sg:address":"16 Orchard Lane",
    "sg:city":"Leighton Buzzard",
    "sg:classifiers":[
        {
            "category":"Home & Garden",
            "subcategory":"Home Furnishings",
            "type":"Retail Goods"
        }
    ],
    "sg:phone":"+44 1525 240410",
    "sg:postcode":"LU7 0HS",
    "sg:province":"Bedfordshire",
    "sg:tags":[
        "awning",
        "canopy",
        "blinds"
    ],
    "wof:name":"Belusi",
    "wof:placetype":"venue"
},
  "geometry": {"coordinates":[-0.7606390119,51.9211997986],"type":"Point"}
}