{
  "type": "Feature",
  "properties": {
    "addr:full":"29 Bury Hill Woodbridge Suffolk IP12 1JD",
    "addr:housenumber":"29",
    "addr:postcode":"ip12 1jd",
    "addr:street":"Bury Hill",
    "iso:country":"GB",
    "sg:address":"29 Bury Hill",
    "sg:city":"Woodbridge",
    "sg:classifiers":[
        {
            "category":"Professional",
            "subcategory":"Computer Services",
            "type":"Services"
        }
    ],
    "sg:phone":"+44 1394 384935",
    "sg:postcode":"IP12 1JD",
    "sg:province":"Suffolk",
    "sg:tags":[
        "system",
        "software"
    ],
    "wof:name":"K Software",
    "wof:placetype":"venue"
},
  "geometry": {"coordinates":[1.3179539442,52.104221344],"type":"Point"}
}