{
  "type": "Feature",
  "properties": {
    "iso:country":"GB",
    "sg:address":"Cromwell Road",
    "sg:city":"Grimsby",
    "sg:classifiers":[
        {
            "category":"Food & Beverages",
            "subcategory":"Supermarket",
            "type":"Retail Goods"
        }
    ],
    "sg:phone":"+44 1472 358489",
    "sg:postcode":"DN31 2BB",
    "sg:province":"Lincolnshire",
    "wof:name":"Presto",
    "wof:placetype":"venue"
},
  "geometry": {"coordinates":[-0.108529,53.567959],"type":"Point"}
}