{
  "type": "Feature",
  "properties": {
    "addr:full":"16-18 Hollen Street London Greater London W1F 8BF",
    "addr:housenumber":"16-18",
    "addr:postcode":"w1f 8bf",
    "addr:street":"Hollen Street",
    "iso:country":"GB",
    "sg:address":"16-18 Hollen Street",
    "sg:city":"London",
    "sg:classifiers":[
        {
            "category":"Professional",
            "subcategory":"Art Services",
            "type":"Services"
        },
        {
            "category":"Banks & Credit Unions",
            "subcategory":"Financial Services",
            "type":"Services"
        }
    ],
    "sg:phone":"+44 20 7287 0044",
    "sg:postcode":"W1F 8BF",
    "sg:province":"Greater London",
    "sg:tags":[
        "consultant",
        "design"
    ],
    "wof:name":"Select First (London) Ltd.",
    "wof:placetype":"venue"
},
  "geometry": {"coordinates":[-0.135112,51.515537],"type":"Point"}
}