{
  "type": "Feature",
  "properties": {
    "addr:full":"Ned Lane, Tong Bradford West Yorkshire BD4 0RQ",
    "addr:postcode":"bd4 0rq",
    "addr:street":"Ned Lane",
    "iso:country":"GB",
    "sg:address":"Ned Lane, Tong",
    "sg:city":"Bradford",
    "sg:classifiers":[
        {
            "category":"Transit Center",
            "subcategory":"Passenger",
            "type":"Transportation"
        }
    ],
    "sg:phone":"+44 1274 778055",
    "sg:postcode":"BD4 0RQ",
    "sg:province":"West Yorkshire",
    "sg:tags":[
        "boarding",
        "kennel",
        "catteries"
    ],
    "wof:name":"K9 Rehoming",
    "wof:placetype":"venue"
},
  "geometry": {"coordinates":[-1.663764,53.772091],"type":"Point"}
}