{
  "type": "Feature",
  "properties": {
    "addr:full":"23 Vernon Street Swansea Neath Port Talbot SA1 2EZ",
    "addr:housenumber":"23",
    "addr:postcode":"sa1 2ez",
    "addr:street":"Vernon Street",
    "iso:country":"GB",
    "sg:address":"23 Vernon Street",
    "sg:city":"Swansea",
    "sg:classifiers":[
        {
            "category":"Building & Trades",
            "subcategory":"Plumbing",
            "type":"Services"
        }
    ],
    "sg:phone":"+44 1792 468255",
    "sg:postcode":"SA1 2EZ",
    "sg:province":"Neath Port Talbot",
    "sg:tags":[
        "heating"
    ],
    "wof:name":"C S Plumbing Services",
    "wof:placetype":"venue"
},
  "geometry": {"coordinates":[-3.9389240742,51.6298789978],"type":"Point"}
}