{
  "type": "Feature",
  "properties": {
    "addr:full":"55 Wellesley Road Great Yarmouth Norfolk NR30 1EX",
    "addr:housenumber":"55",
    "addr:postcode":"nr30 1ex",
    "addr:street":"Wellesley Road",
    "iso:country":"GB",
    "sg:address":"55 Wellesley Road",
    "sg:city":"Great Yarmouth",
    "sg:classifiers":[
        {
            "category":"Travel",
            "subcategory":"Hotels & Motels",
            "type":"Entertainment"
        }
    ],
    "sg:phone":"+44 1493 843960",
    "sg:postcode":"NR30 1EX",
    "sg:province":"Norfolk",
    "wof:name":"Cleasewood Hotel",
    "wof:placetype":"venue"
},
  "geometry": {"coordinates":[1.734946,52.612591],"type":"Point"}
}