{
  "type": "Feature",
  "properties": {
    "iso:country":"GB",
    "sg:address":"141 High Street, Hampton Hill",
    "sg:city":"Hampton",
    "sg:classifiers":[
        {
            "category":"Personal",
            "subcategory":"Beauty Salon",
            "type":"Services"
        }
    ],
    "sg:phone":"+44 20 8941 6684",
    "sg:postcode":"TW12 1NJ",
    "sg:province":"Greater London",
    "sg:tags":[
        "unisex",
        "hairdresser"
    ],
    "wof:name":"Scruples Hairdressers",
    "wof:placetype":"venue"
},
  "geometry": {"coordinates":[-0.3562420011,51.4267349243],"type":"Point"}
}