{
  "type": "Feature",
  "properties": {
    "iso:country":"GB",
    "sg:address":"The Cottage, Leicester Lane",
    "sg:city":"Leicester",
    "sg:classifiers":[
        {
            "category":"Building & Trades",
            "subcategory":"Equipment Rental",
            "type":"Services"
        }
    ],
    "sg:postcode":"LE9 9JJ",
    "sg:province":"Leicestershire",
    "sg:tags":[
        "plant",
        "machinery"
    ],
    "wof:name":"Forest Driveways & Plant Hire",
    "wof:placetype":"venue"
},
  "geometry": {"coordinates":[-1.298286,52.627647],"type":"Point"}
}