{
  "type": "Feature",
  "properties": {
    "addr:full":"Raglan Rd Plymouth Devon PL1 4NQ",
    "addr:postcode":"pl1 4nq",
    "addr:street":"Raglan Rd",
    "iso:country":"GB",
    "sg:address":"Raglan Rd",
    "sg:city":"Plymouth",
    "sg:classifiers":[
        {
            "category":"Place Of Worship",
            "type":"Public Place"
        }
    ],
    "sg:phone":"+44 1752 562976",
    "sg:postcode":"PL1 4NQ",
    "sg:province":"Devon",
    "wof:name":"St Joseph R C Church",
    "wof:placetype":"venue"
},
  "geometry": {"coordinates":[-4.1735448837,50.3719825745],"type":"Point"}
}