{
  "type": "Feature",
  "properties": {
    "iso:country":"GB",
    "sg:address":"Merchant Street",
    "sg:city":"Peterhead",
    "sg:classifiers":[
        {
            "category":"Travel",
            "subcategory":"Hotels & Motels",
            "type":"Entertainment"
        }
    ],
    "sg:phone":"+44 1779 474457",
    "sg:postcode":"AB42 1BU",
    "sg:province":"Aberdeenshire",
    "wof:name":"Pub Com Group Ltd.",
    "wof:placetype":"venue"
},
  "geometry": {"coordinates":[-1.7777689695,57.504486084],"type":"Point"}
}