{
  "type": "Feature",
  "properties": {
    "addr:full":"23-27 High Street Buckie Moray AB56 1AL",
    "addr:housenumber":"23-27",
    "addr:postcode":"ab56 1al",
    "addr:street":"High Street",
    "iso:country":"GB",
    "sg:address":"23-27 High Street",
    "sg:city":"Buckie",
    "sg:classifiers":[
        {
            "category":"Building & Trades",
            "subcategory":"Plumbing",
            "type":"Services"
        }
    ],
    "sg:phone":"+44 1542 832158",
    "sg:postcode":"AB56 1AL",
    "sg:province":"Moray",
    "sg:tags":[
        "plumber",
        "heating"
    ],
    "wof:name":"Peter Reid",
    "wof:placetype":"venue"
},
  "geometry": {"coordinates":[-2.963735,57.675426],"type":"Point"}
}