{
  "type": "Feature",
  "properties": {
    "iso:country":"GB",
    "sg:address":"Dental Practice, 70 Church St",
    "sg:city":"Shildon",
    "sg:classifiers":[
        {
            "category":"Health Services",
            "subcategory":"Dentist",
            "type":"Services"
        }
    ],
    "sg:phone":"+44 1388 775104",
    "sg:postcode":"DL4 1DY",
    "sg:province":"Durham",
    "wof:name":"S W Atkinson",
    "wof:placetype":"venue"
},
  "geometry": {"coordinates":[-1.651709,54.628571],"type":"Point"}
}