{
  "type": "Feature",
  "properties": {
    "iso:country":"GB",
    "sg:address":"Foley Industrial Park, Stourport Rd",
    "sg:city":"Kidderminster",
    "sg:classifiers":[
        {
            "category":"Professional",
            "subcategory":"Management & Consulting",
            "type":"Services"
        }
    ],
    "sg:phone":"+44 1562 823399",
    "sg:postcode":"DY11 7QL",
    "sg:province":"Staffordshire",
    "sg:tags":[
        "consultant",
        "training"
    ],
    "wof:name":"Newlife Training Consultancy",
    "wof:placetype":"venue"
},
  "geometry": {"coordinates":[-2.260479,52.37302],"type":"Point"}
}