{
  "type": "Feature",
  "properties": {
    "iso:country":"GB",
    "sg:address":"Pindar Distrubution Depot",
    "sg:city":"Hoddesdon",
    "sg:classifiers":[
        {
            "category":"Professional",
            "subcategory":"Business Services",
            "type":"Services"
        },
        {
            "category":"Food & Beverages",
            "subcategory":"Supermarket",
            "type":"Retail Goods"
        }
    ],
    "sg:phone":"+44 1992 455700",
    "sg:postcode":"EN11 0DG",
    "sg:province":"Essex",
    "sg:tags":[
        "distribution"
    ],
    "wof:name":"J Sainsburys",
    "wof:placetype":"venue"
},
  "geometry": {"coordinates":[0.001471,51.7642059326],"type":"Point"}
}