{
  "type": "Feature",
  "properties": {
    "addr:full":"Unit 8b Sheridale Centre, Knight Road Rochester Kent ME2 2EL",
    "addr:housenumber":"unit 8b",
    "addr:postcode":"me2 2el",
    "addr:street":"Sheridale Centre Knight Road Rochester",
    "iso:country":"GB",
    "sg:address":"Unit 8b Sheridale Centre, Knight Road",
    "sg:city":"Rochester",
    "sg:classifiers":[
        {
            "category":"Fast Food",
            "type":"Food & Drink"
        }
    ],
    "sg:postcode":"ME2 2EL",
    "sg:province":"Kent",
    "sg:tags":[
        "away",
        "take"
    ],
    "wof:name":"Dial Indian Curry",
    "wof:placetype":"venue"
},
  "geometry": {"coordinates":[0.488783,51.39637],"type":"Point"}
}