{
  "type": "Feature",
  "properties": {
    "addr:full":"Mildmay Road Bootle Merseyside L20 5EW",
    "addr:postcode":"l20 5ew",
    "addr:street":"Mildmay Road",
    "iso:country":"GB",
    "sg:address":"Mildmay Road",
    "sg:city":"Bootle",
    "sg:classifiers":[
        {
            "category":"Retail",
            "subcategory":"Laundry & Dry Cleaning",
            "type":"Services"
        }
    ],
    "sg:phone":"+44 151 933 6161",
    "sg:postcode":"L20 5EW",
    "sg:province":"Merseyside",
    "sg:tags":[
        "alteration"
    ],
    "wof:name":"Johnson Cleaners U K Ltd.",
    "wof:placetype":"venue"
},
  "geometry": {"coordinates":[-2.9966990948,53.4601097107],"type":"Point"}
}