{
  "type": "Feature",
  "properties": {
    "addr:full":"Po Box 60 Wickford Essex SS11 8BU",
    "addr:housenumber":"po box 60",
    "addr:postcode":"ss11 8bu",
    "iso:country":"GB",
    "sg:address":"Po Box 60",
    "sg:city":"Wickford",
    "sg:classifiers":[
        {
            "category":"Manufacturing",
            "subcategory":"Metals",
            "type":"Manufacturing & Wholesale Goods"
        }
    ],
    "sg:phone":"+44 1268 572103",
    "sg:postcode":"SS11 8BU",
    "sg:province":"Essex",
    "sg:tags":[
        "steel",
        "stockholder"
    ],
    "wof:name":"C Downhill Steels",
    "wof:placetype":"venue"
},
  "geometry": {"coordinates":[0.574755,51.611469],"type":"Point"}
}