{
  "type": "Feature",
  "properties": {
    "iso:country":"GB",
    "sg:address":"1 Lonsdale Rd, Hest Bank",
    "sg:city":"Lancaster",
    "sg:classifiers":[
        {
            "category":"Health Services",
            "subcategory":"Nursing And Care Facility",
            "type":"Services"
        }
    ],
    "sg:phone":"+44 1524 823251",
    "sg:postcode":"LA2 6DS",
    "sg:province":"Lancashire",
    "sg:tags":[
        "home"
    ],
    "wof:name":"Lonsdale House Residential Home",
    "wof:placetype":"venue"
},
  "geometry": {"coordinates":[-2.814695,54.090401],"type":"Point"}
}