{
  "type": "Feature",
  "properties": {
    "addr:full":"Reeves Way, Chestfield Whitstable Kent CT5 3QS",
    "addr:postcode":"ct5 3qs",
    "addr:street":"Reeves Way;Whitstable",
    "iso:country":"GB",
    "sg:address":"Reeves Way, Chestfield",
    "sg:city":"Whitstable",
    "sg:classifiers":[
        {
            "category":"Arena",
            "subcategory":"Sports Club",
            "type":"Entertainment"
        }
    ],
    "sg:phone":"+44 1227 794343",
    "sg:postcode":"CT5 3QS",
    "sg:province":"Kent",
    "wof:name":"WHITSTABLE RUGBY CLUB",
    "wof:placetype":"venue"
},
  "geometry": {"coordinates":[1.0642819405,51.3547019958],"type":"Point"}
}