{
  "type": "Feature",
  "properties": {
    "iso:country":"GB",
    "sg:address":"Unit 12 The Admiral Park, Airport Service Road",
    "sg:city":"Portsmouth",
    "sg:classifiers":[
        {
            "category":"Shopping",
            "subcategory":"Clothing, Apparel, & Fashions",
            "type":"Retail Goods"
        }
    ],
    "sg:phone":"+44 23 9269 3924",
    "sg:postcode":"PO3 5RQ",
    "sg:province":"Hampshire",
    "sg:tags":[
        "clothing",
        "fabric"
    ],
    "wof:name":"Cloke (Menswear) Ltd.",
    "wof:placetype":"venue"
},
  "geometry": {"coordinates":[-1.056743,50.830654],"type":"Point"}
}