{
  "type": "Feature",
  "properties": {
    "addr:full":"7 Bluebell Court, Wych Hill Park Woking Surrey GU22 0HQ",
    "addr:housenumber":"7",
    "addr:postcode":"gu22 0hq",
    "addr:street":"Bluebell Court Wych Hill Park",
    "iso:country":"GB",
    "sg:address":"7 Bluebell Court, Wych Hill Park",
    "sg:city":"Woking",
    "sg:classifiers":[
        {
            "category":"Professional",
            "subcategory":"Business Services",
            "type":"Services"
        },
        {
            "category":"Utilities",
            "type":"Services"
        }
    ],
    "sg:phone":"+44 1483 762943",
    "sg:postcode":"GU22 0HQ",
    "sg:province":"Surrey",
    "sg:tags":[
        "equipment",
        "software",
        "code",
        "bar",
        "bar-code"
    ],
    "wof:name":"Scanner Services Ltd",
    "wof:placetype":"venue"
},
  "geometry": {"coordinates":[-0.570644,51.311947],"type":"Point"}
}