{
  "type": "Feature",
  "properties": {
    "iso:country":"GB",
    "sg:address":"50 Wrose Road",
    "sg:city":"Shipley",
    "sg:classifiers":[
        {
            "category":"Food & Beverages",
            "subcategory":"Meat & Fish",
            "type":"Retail Goods"
        },
        {
            "category":"Food & Beverages",
            "subcategory":"Groceries & Convenience Stores",
            "type":"Retail Goods"
        }
    ],
    "sg:phone":"+44 1274 581473",
    "sg:postcode":"BD18 1NT",
    "sg:province":"West Yorkshire",
    "sg:tags":[
        "shop",
        "chip"
    ],
    "wof:name":"Wrose Fisheries",
    "wof:placetype":"venue"
},
  "geometry": {"coordinates":[-1.75891,53.828655],"type":"Point"}
}