{
  "type": "Feature",
  "properties": {
    "iso:country":"GB",
    "sg:address":"1 Station Road, Crynant",
    "sg:city":"Neath",
    "sg:classifiers":[
        {
            "category":"Food & Beverages",
            "subcategory":"Supermarket",
            "type":"Retail Goods"
        }
    ],
    "sg:phone":"+44 1639 750654",
    "sg:postcode":"SA10 8NW",
    "sg:province":"Neath Port Talbot",
    "wof:name":"Gwyn Price",
    "wof:placetype":"venue"
},
  "geometry": {"coordinates":[-3.7476270199,51.7295799255],"type":"Point"}
}