{
  "type": "Feature",
  "properties": {
    "addr:full":"Unit 7 Victoria Business Centre, Neilston St Leamington Spa Warwickshire CV31 2AZ",
    "addr:housenumber":"unit 7",
    "addr:postcode":"cv31 2az",
    "addr:street":"Victoria Business Centre Neilston St",
    "iso:country":"GB",
    "sg:address":"Unit 7 Victoria Business Centre, Neilston St",
    "sg:city":"Leamington Spa",
    "sg:classifiers":[
        {
            "category":"Real Estate",
            "subcategory":"Architect",
            "type":"Services"
        }
    ],
    "sg:postcode":"CV31 2AZ",
    "sg:province":"Warwickshire",
    "wof:name":"Legg,Michael J,",
    "wof:placetype":"venue"
},
  "geometry": {"coordinates":[-1.528118968,52.2830467224],"type":"Point"}
}