{
  "type": "Feature",
  "properties": {
    "addr:full":"Unit 6-7 The Enterprise Centre, Dryden Road Loanhead Midlothian EH20 9LZ",
    "addr:housenumber":"unit 6-7 the enterprise centre",
    "addr:postcode":"eh20 9lz",
    "addr:street":"Dryden Road",
    "iso:country":"GB",
    "sg:address":"Unit 6-7 The Enterprise Centre, Dryden Road",
    "sg:city":"Loanhead",
    "sg:classifiers":[
        {
            "category":"Professional",
            "subcategory":"Detective & Security Services",
            "type":"Services"
        }
    ],
    "sg:phone":"+44 131 440 2204",
    "sg:postcode":"EH20 9LZ",
    "sg:province":"Midlothian",
    "sg:tags":[
        "alarm",
        "burglar",
        "system"
    ],
    "wof:name":"M & E Services",
    "wof:placetype":"venue"
},
  "geometry": {"coordinates":[-3.14922,55.877697],"type":"Point"}
}