{
  "type": "Feature",
  "properties": {
    "addr:full":"142 Wakefield Road, Horbury Wakefield West Yorkshire WF4 5HG",
    "addr:housenumber":"142",
    "addr:postcode":"wf4 5hg",
    "addr:street":"Wakefield Road;West",
    "iso:country":"GB",
    "sg:address":"142 Wakefield Road, Horbury",
    "sg:city":"Wakefield",
    "sg:classifiers":[
        {
            "category":"Health Services",
            "subcategory":"Nursing And Care Facility",
            "type":"Services"
        },
        {
            "category":"Social Services",
            "subcategory":"Retirement Home",
            "type":"Services"
        }
    ],
    "sg:phone":"+44 1924 272159",
    "sg:postcode":"WF4 5HG",
    "sg:province":"West Yorkshire",
    "sg:tags":[
        "residential"
    ],
    "wof:name":"Inwood Residential Home",
    "wof:placetype":"venue"
},
  "geometry": {"coordinates":[-1.5466550589,53.6626396179],"type":"Point"}
}