{
  "type": "Feature",
  "properties": {
    "addr:full":"1 Armoury Terrace Ebbw Vale Blaenau Gwent NP3 6XL",
    "addr:housenumber":"1",
    "addr:postcode":"np3 6xl",
    "addr:street":"Armoury Terrace",
    "iso:country":"GB",
    "sg:address":"1 Armoury Terrace",
    "sg:city":"Ebbw Vale",
    "sg:classifiers":[
        {
            "category":"Banks & Credit Unions",
            "subcategory":"Bank",
            "type":"Services"
        }
    ],
    "sg:phone":"+44 1495 302731",
    "sg:postcode":"NP3 6XL",
    "sg:province":"Blaenau Gwent",
    "wof:name":"Lloyds Tsb Bank Plc",
    "wof:placetype":"venue"
},
  "geometry": {"coordinates":[-3.207544,51.776058],"type":"Point"}
}