{
  "type": "Feature",
  "properties": {
    "iso:country":"GB",
    "sg:address":"16 Romford Clo",
    "sg:city":"Birmingham",
    "sg:classifiers":[
        {
            "category":"Real Estate",
            "subcategory":"Architect",
            "type":"Services"
        }
    ],
    "sg:postcode":"B26 3TR",
    "sg:province":"West Midlands",
    "wof:name":"Arthur,K,",
    "wof:placetype":"venue"
},
  "geometry": {"coordinates":[-1.780976,52.458904],"type":"Point"}
}