{
  "type": "Feature",
  "properties": {
    "iso:country":"GB",
    "sg:address":"97 Streatham Hill",
    "sg:city":"London",
    "sg:classifiers":[
        {
            "category":"Food & Beverages",
            "subcategory":"Liquor & Beverages",
            "type":"Retail Goods"
        }
    ],
    "sg:phone":"+44 20 8674 5666",
    "sg:postcode":"SW2 4UD",
    "sg:province":"Greater London",
    "sg:tags":[
        "beer",
        "spirit",
        "wines"
    ],
    "wof:name":"Hardy's Wine",
    "wof:placetype":"venue"
},
  "geometry": {"coordinates":[-0.126102,51.438755],"type":"Point"}
}