{
  "type": "Feature",
  "properties": {
    "addr:full":"11 Eton Garages, Lambolle Place London Greater London NW3 4PE",
    "addr:housenumber":"11",
    "addr:postcode":"nw3 4pe",
    "addr:street":"Eton;Place",
    "iso:country":"GB",
    "sg:address":"11 Eton Garages, Lambolle Place",
    "sg:city":"London",
    "sg:classifiers":[
        {
            "category":"Real Estate",
            "subcategory":"Architect",
            "type":"Services"
        }
    ],
    "sg:phone":"+44 20 7433 3561",
    "sg:postcode":"NW3 4PE",
    "sg:province":"Greater London",
    "wof:name":"Robert Savage & Associates",
    "wof:placetype":"venue"
},
  "geometry": {"coordinates":[-0.1650940031,51.5457305908],"type":"Point"}
}