{
  "type": "Feature",
  "properties": {
    "addr:full":"Shrubbery Walk Weston-super-mare Somerset BS23 2JE",
    "addr:postcode":"bs23 2je",
    "addr:street":"Shrubbery Walk",
    "iso:country":"GB",
    "sg:address":"Shrubbery Walk",
    "sg:city":"Weston-super-mare",
    "sg:classifiers":[
        {
            "category":"Retail",
            "subcategory":"Auto Repair",
            "type":"Services"
        }
    ],
    "sg:phone":"+44 1934 636080",
    "sg:postcode":"BS23 2JE",
    "sg:province":"Somerset",
    "sg:tags":[
        "modification",
        "garage"
    ],
    "wof:name":"Seaview Garage",
    "wof:placetype":"venue"
},
  "geometry": {"coordinates":[-2.9839890003,51.3543968201],"type":"Point"}
}