{
  "type": "Feature",
  "properties": {
    "iso:country":"GB",
    "sg:address":"18 Lime Rd",
    "sg:city":"Ferryhill",
    "sg:classifiers":[
        {
            "category":"Building & Trades",
            "subcategory":"Construction",
            "type":"Services"
        }
    ],
    "sg:phone":"+44 1740 650160",
    "sg:postcode":"DL17 8DJ",
    "sg:province":"Durham",
    "sg:tags":[
        "decorator",
        "painter"
    ],
    "wof:name":"A & D Decorators",
    "wof:placetype":"venue"
},
  "geometry": {"coordinates":[-1.551338,54.68531],"type":"Point"}
}