{
  "type": "Feature",
  "properties": {
    "iso:country":"GB",
    "sg:address":"36 Church Rd, Platt Bridge",
    "sg:city":"Wigan",
    "sg:classifiers":[
        {
            "category":"Building & Trades",
            "subcategory":"Construction",
            "type":"Services"
        }
    ],
    "sg:phone":"+44 1942 861580",
    "sg:postcode":"WN2 3TB",
    "sg:province":"Lancashire",
    "sg:tags":[
        "conversion",
        "loft"
    ],
    "wof:name":"A-z Building Contractors",
    "wof:placetype":"venue"
},
  "geometry": {"coordinates":[-2.59477,53.523373],"type":"Point"}
}