{
  "type": "Feature",
  "properties": {
    "addr:full":"Birch Heath Road Tarporley Cheshire CW6 9UU",
    "addr:postcode":"cw6 9uu",
    "addr:street":"Birch Heath Road",
    "iso:country":"GB",
    "sg:address":"Birch Heath Road",
    "sg:city":"Tarporley",
    "sg:classifiers":[
        {
            "category":"Retail",
            "subcategory":"Veterinary Services",
            "type":"Services"
        }
    ],
    "sg:postcode":"CW6 9UU",
    "sg:province":"Cheshire",
    "sg:tags":[
        "surgeon"
    ],
    "wof:name":"Birch Heath Veterinary Clinic",
    "wof:placetype":"venue"
},
  "geometry": {"coordinates":[-2.668317,53.154339],"type":"Point"}
}