{
  "type": "Feature",
  "properties": {
    "iso:country":"GB",
    "sg:address":"Rear Of",
    "sg:city":"Sheffield",
    "sg:classifiers":[
        {
            "category":"Food & Beverages",
            "subcategory":"Bakery",
            "type":"Retail Goods"
        }
    ],
    "sg:phone":"+44 114 255 0295",
    "sg:postcode":"S2 3AY",
    "sg:province":"South Yorkshire",
    "sg:tags":[
        "baker"
    ],
    "wof:name":"The Real Bread Bakehouse",
    "wof:placetype":"venue"
},
  "geometry": {"coordinates":[-1.457039,53.36198],"type":"Point"}
}