{
  "type": "Feature",
  "properties": {
    "iso:country":"GB",
    "sg:address":"Balloch Road, Cumbernauld",
    "sg:city":"Glasgow",
    "sg:classifiers":[
        {
            "category":"Bars & Pubs",
            "type":"Food & Drink"
        }
    ],
    "sg:phone":"+44 1236 728419",
    "sg:postcode":"G68 9DN",
    "sg:province":"East Dunbartonshire",
    "sg:tags":[
        "pubs",
        "inn"
    ],
    "wof:name":"Smiddy Inn",
    "wof:placetype":"venue"
},
  "geometry": {"coordinates":[-4.0295357704,55.9377861023],"type":"Point"}
}