{
  "type": "Feature",
  "properties": {
    "addr:full":"28 Circuit Lane, Southcote Reading Berkshire RG30 3HA",
    "addr:housenumber":"28",
    "addr:postcode":"rg30 3ha",
    "addr:street":"Circuit Lane",
    "iso:country":"GB",
    "sg:address":"28 Circuit Lane, Southcote",
    "sg:city":"Reading",
    "sg:classifiers":[
        {
            "category":"Building & Trades",
            "subcategory":"Landscaping Services",
            "type":"Services"
        }
    ],
    "sg:phone":"+44 118 958 1599",
    "sg:postcode":"RG30 3HA",
    "sg:province":"Berkshire",
    "sg:tags":[
        "gardening"
    ],
    "wof:name":"A J Garden Services",
    "wof:placetype":"venue"
},
  "geometry": {"coordinates":[-1.007597,51.443783],"type":"Point"}
}