{
  "type": "Feature",
  "properties": {
    "addr:full":"16 Southwood Gardens, Cookham Maidenhead Berkshire SL6 9EB",
    "addr:housenumber":"16",
    "addr:postcode":"sl6 9eb",
    "addr:street":"Southwood Gardens",
    "iso:country":"GB",
    "sg:address":"16 Southwood Gardens, Cookham",
    "sg:city":"Maidenhead",
    "sg:classifiers":[
        {
            "category":"Professional",
            "subcategory":"Business Services",
            "type":"Services"
        }
    ],
    "sg:phone":"+44 1628 524454",
    "sg:postcode":"SL6 9EB",
    "sg:province":"Berkshire",
    "sg:tags":[
        "house",
        "mailing"
    ],
    "wof:name":"Colwood Services Ltd.",
    "wof:placetype":"venue"
},
  "geometry": {"coordinates":[-0.728153,51.549225],"type":"Point"}
}