{
  "type": "Feature",
  "properties": {
    "addr:full":"38 Springfield Avenue, Shirebrook Mansfield Derbyshire NG20 8LG",
    "addr:housenumber":"38",
    "addr:postcode":"ng20 8lg",
    "addr:street":"Springfield Avenue",
    "iso:country":"GB",
    "sg:address":"38 Springfield Avenue, Shirebrook",
    "sg:city":"Mansfield",
    "sg:classifiers":[
        {
            "category":"Arts & Performance",
            "subcategory":"Music",
            "type":"Entertainment"
        }
    ],
    "sg:postcode":"NG20 8LG",
    "sg:province":"Derbyshire",
    "sg:tags":[
        "mobile",
        "disco"
    ],
    "wof:name":"Starlight Discotheque",
    "wof:placetype":"venue"
},
  "geometry": {"coordinates":[-1.217356,53.207333],"type":"Point"}
}