{
  "type": "Feature",
  "properties": {
    "iso:country":"GB",
    "sg:address":"Chester Rd",
    "sg:city":"Knutsford",
    "sg:classifiers":[
        {
            "category":"Personal",
            "type":"Services"
        }
    ],
    "sg:phone":"+44 1565 830612",
    "sg:postcode":"WA16 6RE",
    "sg:province":"Cheshire",
    "sg:tags":[
        "tailor"
    ],
    "wof:name":"Phil Cohen & Son Ltd",
    "wof:placetype":"venue"
},
  "geometry": {"coordinates":[-2.405279,53.345177],"type":"Point"}
}