{
  "type": "Feature",
  "properties": {
    "iso:country":"GB",
    "sg:address":"Edensor Road",
    "sg:city":"London",
    "sg:classifiers":[
        {
            "category":"Sports & Exercise",
            "subcategory":"Swimming Pool",
            "type":"Entertainment"
        }
    ],
    "sg:phone":"+44 20 8747 8811",
    "sg:postcode":"W4 2RG",
    "sg:province":"Greater London",
    "wof:name":"New Chiswick Pool",
    "wof:placetype":"venue"
},
  "geometry": {"coordinates":[-0.256219,51.481998],"type":"Point"}
}