{
  "type": "Feature",
  "properties": {
    "addr:full":"9 Frederick Road, Edgbaston Birmingham West Midlands B15 1JD",
    "addr:housenumber":"9",
    "addr:postcode":"b15 1jd",
    "addr:street":"Frederick Road",
    "iso:country":"GB",
    "sg:address":"9 Frederick Road, Edgbaston",
    "sg:city":"Birmingham",
    "sg:classifiers":[
        {
            "category":"Professional",
            "subcategory":"Accounting & Tax Preparation",
            "type":"Services"
        }
    ],
    "sg:postcode":"B15 1JD",
    "sg:province":"West Midlands",
    "sg:tags":[
        "accountant"
    ],
    "wof:name":"Jeeves & Co. Ltd.",
    "wof:placetype":"venue"
},
  "geometry": {"coordinates":[-1.916382,52.471748],"type":"Point"}
}