{
  "type": "Feature",
  "properties": {
    "addr:full":"Unit 9 Newporte Business Park, Bishops Rd Lincoln Lincolnshire LN2 4NT",
    "addr:housenumber":"unit 9",
    "addr:postcode":"ln2 4nt",
    "addr:street":"Newporte Business Park Bishops Rd",
    "iso:country":"GB",
    "sg:address":"Unit 9 Newporte Business Park, Bishops Rd",
    "sg:city":"Lincoln",
    "sg:classifiers":[
        {
            "category":"Autos & Motor Vehicles",
            "subcategory":"Auto Supplies",
            "type":"Retail Goods"
        }
    ],
    "sg:phone":"+44 1522 525500",
    "sg:postcode":"LN2 4NT",
    "sg:province":"Lincolnshire",
    "sg:tags":[
        "component"
    ],
    "wof:name":"Bancrofts Ltd",
    "wof:placetype":"venue"
},
  "geometry": {"coordinates":[-0.5002800226,53.246421814],"type":"Point"}
}