{
  "type": "Feature",
  "properties": {
    "addr:full":"Bear La Newbury Berkshire RG14 5QR",
    "addr:postcode":"rg14 5qr",
    "addr:street":"Bear;Newbury",
    "iso:country":"GB",
    "sg:address":"Bear La",
    "sg:city":"Newbury",
    "sg:classifiers":[
        {
            "category":"Building & Trades",
            "subcategory":"Plumbing",
            "type":"Services"
        }
    ],
    "sg:phone":"+44 1635 580999",
    "sg:postcode":"RG14 5QR",
    "sg:province":"Berkshire",
    "sg:tags":[
        "heating"
    ],
    "wof:name":"A Direct Line Plumbing & Heating Service",
    "wof:placetype":"venue"
},
  "geometry": {"coordinates":[-1.3211439848,51.4004058838],"type":"Point"}
}