{
  "type": "Feature",
  "properties": {
    "addr:full":"Springfield Cottage, Hall Pl Cranleigh Surrey GU6 8LA",
    "addr:postcode":"gu6 8la",
    "addr:street":"Hall Pl",
    "iso:country":"GB",
    "sg:address":"Springfield Cottage, Hall Pl",
    "sg:city":"Cranleigh",
    "sg:classifiers":[
        {
            "category":"Personal",
            "type":"Services"
        },
        {
            "category":"Professional",
            "subcategory":"Art Services",
            "type":"Services"
        }
    ],
    "sg:postcode":"GU6 8LA",
    "sg:province":"Surrey",
    "sg:tags":[
        "photographer",
        "wedding"
    ],
    "wof:name":"Turner,Y H,",
    "wof:placetype":"venue"
},
  "geometry": {"coordinates":[-0.482998997,51.1415405273],"type":"Point"}
}