{
  "type": "Feature",
  "properties": {
    "iso:country":"GB",
    "sg:address":"Pertenhall Road",
    "sg:city":"Cambridge",
    "sg:classifiers":[
        {
            "category":"Education",
            "subcategory":"Music School",
            "type":"Public Place"
        }
    ],
    "sg:postcode":"PE19 5BE",
    "sg:province":"Bedfordshire",
    "sg:tags":[
        "conservatory"
    ],
    "wof:name":"Gsn Conservatories",
    "wof:placetype":"venue"
},
  "geometry": {"coordinates":[-0.3647400141,52.2656593323],"type":"Point"}
}