{
  "type": "Feature",
  "properties": {
    "addr:full":"40 The Mall, Ealing London Greater London W5 3TJ",
    "addr:housenumber":"40",
    "addr:postcode":"w5 3tj",
    "addr:street":"The Mall",
    "iso:country":"GB",
    "sg:address":"40 The Mall, Ealing",
    "sg:city":"London",
    "sg:classifiers":[
        {
            "category":"Professional",
            "subcategory":"Business Services",
            "type":"Services"
        }
    ],
    "sg:phone":"+44 20 8840 2323",
    "sg:postcode":"W5 3TJ",
    "sg:province":"Greater London",
    "sg:tags":[
        "import",
        "export",
        "agent"
    ],
    "wof:name":"N S G Exports Ltd.",
    "wof:placetype":"venue"
},
  "geometry": {"coordinates":[-0.298016,51.513367],"type":"Point"}
}