{
  "type": "Feature",
  "properties": {
    "addr:full":"46 Pevensey Road Eastbourne East Sussex BN21 3HP",
    "addr:housenumber":"46",
    "addr:postcode":"bn21 3hp",
    "addr:street":"Pevensey Road",
    "iso:country":"GB",
    "sg:address":"46 Pevensey Road",
    "sg:city":"Eastbourne",
    "sg:classifiers":[
        {
            "category":"Autos & Motor Vehicles",
            "subcategory":"Automobile Sales",
            "type":"Retail Goods"
        }
    ],
    "sg:postcode":"BN21 3HP",
    "sg:province":"East Sussex",
    "sg:tags":[
        "car"
    ],
    "wof:name":"K & P Car Sales",
    "wof:placetype":"venue"
},
  "geometry": {"coordinates":[0.290684,50.769321],"type":"Point"}
}