{
  "type": "Feature",
  "properties": {
    "addr:full":"Unit 8c Beechcroft Farm Industrial Estat, Chapel Wood Road, Ash Sevenoaks Kent TN15 7HX",
    "addr:housenumber":"unit 8c beechcroft farm",
    "addr:postcode":"tn15 7hx",
    "addr:street":"Industrial Estat Chapel Wood Road",
    "iso:country":"GB",
    "sg:address":"Unit 8c Beechcroft Farm Industrial Estat, Chapel Wood Road, Ash",
    "sg:city":"Sevenoaks",
    "sg:classifiers":[
        {
            "category":"Manufacturing",
            "subcategory":"Signs",
            "type":"Manufacturing & Wholesale Goods"
        }
    ],
    "sg:phone":"+44 1474 874060",
    "sg:postcode":"TN15 7HX",
    "sg:province":"Kent",
    "sg:tags":[
        "nameplate"
    ],
    "wof:name":"Syrett Neon International",
    "wof:placetype":"venue"
},
  "geometry": {"coordinates":[0.29591,51.363701],"type":"Point"}
}