{
  "type": "Feature",
  "properties": {
    "addr:full":"16 Baptist Street, Penygroes Caernarfon Gwynedd LL54 6NU",
    "addr:housenumber":"16",
    "addr:postcode":"ll54 6nu",
    "addr:street":"Baptist Street",
    "iso:country":"GB",
    "sg:address":"16 Baptist Street, Penygroes",
    "sg:city":"Caernarfon",
    "sg:classifiers":[
        {
            "category":"Building & Trades",
            "subcategory":"Plumbing",
            "type":"Services"
        },
        {
            "category":"Building & Trades",
            "subcategory":"Construction",
            "type":"Services"
        }
    ],
    "sg:phone":"+44 1286 881994",
    "sg:postcode":"LL54 6NU",
    "sg:province":"Gwynedd",
    "sg:tags":[
        "central",
        "installation",
        "system",
        "servicing",
        "heating"
    ],
    "wof:name":"Kevin Roberts Plumbing & Heating",
    "wof:placetype":"venue"
},
  "geometry": {"coordinates":[-4.2850341797,53.0537910461],"type":"Point"}
}