{
  "type": "Feature",
  "properties": {
    "iso:country":"GB",
    "sg:address":"Newcastle Bowl, Westgate Road",
    "sg:city":"Newcastle-upon-tyne",
    "sg:classifiers":[
        {
            "category":"Sports & Exercise",
            "subcategory":"Bowling",
            "type":"Entertainment"
        }
    ],
    "sg:phone":"+44 191 273 0236",
    "sg:postcode":"NE4 8RN",
    "sg:province":"Tyne and Wear",
    "wof:name":"Amf Newcastle",
    "wof:placetype":"venue"
},
  "geometry": {"coordinates":[-1.6423900127,54.973739624],"type":"Point"}
}