{
  "type": "Feature",
  "properties": {
    "addr:full":"No 4 Three Horseshoe Marle Warminster Somerset BA12 9BT",
    "addr:postcode":"ba12 9bt",
    "addr:street":"Three",
    "iso:country":"GB",
    "sg:address":"No 4 Three Horseshoe Marle",
    "sg:city":"Warminster",
    "sg:classifiers":[
        {
            "category":"Building & Trades",
            "subcategory":"Construction",
            "type":"Services"
        }
    ],
    "sg:phone":"+44 1985 847519",
    "sg:postcode":"BA12 9BT",
    "sg:province":"Somerset",
    "sg:tags":[
        "builder"
    ],
    "wof:name":"Butchers of Warminster Ltd.",
    "wof:placetype":"venue"
},
  "geometry": {"coordinates":[-2.1831250191,51.2053642273],"type":"Point"}
}