{
  "type": "Feature",
  "properties": {
    "addr:full":"17 Battery End Newbury Berkshire RG14 6NX",
    "addr:housenumber":"17",
    "addr:postcode":"rg14 6nx",
    "addr:street":"Battery End",
    "iso:country":"GB",
    "sg:address":"17 Battery End",
    "sg:city":"Newbury",
    "sg:classifiers":[
        {
            "category":"Health Services",
            "subcategory":"Health Practitioner",
            "type":"Services"
        }
    ],
    "sg:phone":"+44 1635 43430",
    "sg:postcode":"RG14 6NX",
    "sg:province":"Berkshire",
    "sg:tags":[
        "hypnotherapists"
    ],
    "wof:name":"Jenny Cutler",
    "wof:placetype":"venue"
},
  "geometry": {"coordinates":[-1.3438709974,51.3802070618],"type":"Point"}
}