{
  "type": "Feature",
  "properties": {
    "addr:full":"Mayhill Cottage, Mayhill Lane, Upper Swanmore Southampton Hampshire SO32 2QW",
    "addr:postcode":"so32 2qw",
    "addr:street":"Mayhill Lane",
    "iso:country":"GB",
    "sg:address":"Mayhill Cottage, Mayhill Lane, Upper Swanmore",
    "sg:city":"Southampton",
    "sg:classifiers":[
        {
            "category":"Home & Garden",
            "subcategory":"Hardware",
            "type":"Retail Goods"
        }
    ],
    "sg:phone":"+44 1489 877217",
    "sg:postcode":"SO32 2QW",
    "sg:province":"Hampshire",
    "wof:name":"The Blagg Trading Co. Ltd.",
    "wof:placetype":"venue"
},
  "geometry": {"coordinates":[-1.156579,50.954819],"type":"Point"}
}