{
  "type": "Feature",
  "properties": {
    "addr:full":"Unit 12 Newlands House, Newlands Centre Hull East Riding of Yorkshire HU6 7TQ",
    "addr:housenumber":"unit 12",
    "addr:postcode":"hu6 7tq",
    "addr:street":"Newlands House Newlands",
    "iso:country":"GB",
    "sg:address":"Unit 12 Newlands House, Newlands Centre",
    "sg:city":"Hull",
    "sg:classifiers":[
        {
            "category":"Wholesale",
            "subcategory":"Books, Periodicals, & Newspapers",
            "type":"Manufacturing & Wholesale Goods"
        }
    ],
    "sg:phone":"+44 1482 851858",
    "sg:postcode":"HU6 7TQ",
    "sg:province":"East Riding of Yorkshire",
    "sg:tags":[
        "publishing"
    ],
    "wof:name":"Worldwide Websights Ltd.",
    "wof:placetype":"venue"
},
  "geometry": {"coordinates":[-0.3629589975,53.7691001892],"type":"Point"}
}