{
  "type": "Feature",
  "properties": {
    "iso:country":"GB",
    "sg:address":"Unit 2a, Glover Industrial Estate",
    "sg:city":"Washington",
    "sg:classifiers":[
        {
            "category":"Professional",
            "subcategory":"Engineering",
            "type":"Services"
        }
    ],
    "sg:phone":"+44 191 415 4500",
    "sg:postcode":"NE37 3ES",
    "sg:province":"Tyne and Wear",
    "sg:tags":[
        "precision",
        "engineer"
    ],
    "wof:name":"P C Precision Components Ltd.",
    "wof:placetype":"venue"
},
  "geometry": {"coordinates":[-1.502969,54.912971],"type":"Point"}
}