{
  "type": "Feature",
  "properties": {
    "addr:full":"The Surrey Canal Office, Rope Street London Greater London SE16 7TX",
    "addr:postcode":"se16 7tx",
    "addr:street":"Rope Street",
    "iso:country":"GB",
    "sg:address":"The Surrey Canal Office, Rope Street",
    "sg:city":"London",
    "sg:classifiers":[
        {
            "category":"Building & Trades",
            "subcategory":"Construction",
            "type":"Services"
        }
    ],
    "sg:phone":"+44 20 7394 9444",
    "sg:postcode":"SE16 7TX",
    "sg:province":"Greater London",
    "sg:tags":[
        "builder"
    ],
    "wof:name":"Gilby Construction Ltd.",
    "wof:placetype":"venue"
},
  "geometry": {"coordinates":[-0.03864,51.49313],"type":"Point"}
}