{
  "type": "Feature",
  "properties": {
    "iso:country":"GB",
    "sg:address":"P O Box 12, West St",
    "sg:city":"Haslemere",
    "sg:classifiers":[
        {
            "category":"Professional",
            "subcategory":"Secretarial Services",
            "type":"Services"
        }
    ],
    "sg:phone":"+44 1428 654011",
    "sg:postcode":"GU27 2AB",
    "sg:province":"Hampshire",
    "wof:name":"Leonie Onslow Secretarial Services",
    "wof:placetype":"venue"
},
  "geometry": {"coordinates":[-0.7087240219,51.0887908936],"type":"Point"}
}