{
  "type": "Feature",
  "properties": {
    "addr:full":"304 London Road Westcliff-on-sea Essex SS0 7JJ",
    "addr:housenumber":"304",
    "addr:postcode":"ss0 7jj",
    "addr:street":"London Road",
    "iso:country":"GB",
    "sg:address":"304 London Road",
    "sg:city":"Westcliff-on-sea",
    "sg:classifiers":[
        {
            "category":"Professional",
            "subcategory":"Detective & Security Services",
            "type":"Services"
        }
    ],
    "sg:phone":"+44 1702 338843",
    "sg:postcode":"SS0 7JJ",
    "sg:province":"Essex",
    "sg:tags":[
        "locksmith"
    ],
    "wof:name":"Leigh Lock & Safe Co.",
    "wof:placetype":"venue"
},
  "geometry": {"coordinates":[0.698081,51.541027],"type":"Point"}
}