{
  "type": "Feature",
  "properties": {
    "iso:country":"GB",
    "sg:address":"Five Bars, Tally House Road",
    "sg:city":"Ashford",
    "sg:classifiers":[
        {
            "category":"Building & Trades",
            "subcategory":"Construction",
            "type":"Services"
        }
    ],
    "sg:postcode":"TN26 1HW",
    "sg:province":"Kent",
    "sg:tags":[
        "excavation",
        "groundwork",
        "contractor"
    ],
    "wof:name":"Rummery Plant Services",
    "wof:placetype":"venue"
},
  "geometry": {"coordinates":[0.8433870077,51.097366333],"type":"Point"}
}