{
  "type": "Feature",
  "properties": {
    "addr:full":"Belle Vue House, Market Place Leyburn North Yorkshire DL8 5AW",
    "addr:postcode":"dl8 5aw",
    "addr:street":"Belle;Market Place",
    "iso:country":"GB",
    "sg:address":"Belle Vue House, Market Place",
    "sg:city":"Leyburn",
    "sg:classifiers":[
        {
            "category":"Cafe",
            "type":"Food & Drink"
        }
    ],
    "sg:postcode":"DL8 5AW",
    "sg:province":"North Yorkshire",
    "sg:tags":[
        "tea",
        "room"
    ],
    "wof:name":"Posthorn Cafe",
    "wof:placetype":"venue"
},
  "geometry": {"coordinates":[-1.829477,54.309643],"type":"Point"}
}