{
  "type": "Feature",
  "properties": {
    "addr:full":"109 Queen Street Newton Abbot Devon TQ12 2BG",
    "addr:housenumber":"109",
    "addr:postcode":"tq12 2bg",
    "addr:street":"Queen Street",
    "iso:country":"GB",
    "sg:address":"109 Queen Street",
    "sg:city":"Newton Abbot",
    "sg:classifiers":[
        {
            "category":"Farming",
            "subcategory":"Farm",
            "type":"Manufacturing & Wholesale Goods"
        }
    ],
    "sg:postcode":"TQ12 2BG",
    "sg:province":"Devon",
    "sg:tags":[
        "mixed",
        "crop"
    ],
    "wof:name":"Gateshire Ltd.",
    "wof:placetype":"venue"
},
  "geometry": {"coordinates":[-3.604252,50.53096],"type":"Point"}
}