{
  "type": "Feature",
  "properties": {
    "iso:country":"GB",
    "sg:address":"Recreation Rd",
    "sg:city":"Haverhill",
    "sg:classifiers":[
        {
            "category":"Farming",
            "subcategory":"Fish & Marine Products",
            "type":"Manufacturing & Wholesale Goods"
        }
    ],
    "sg:postcode":"CB9 8BH",
    "sg:province":"Essex",
    "sg:tags":[
        "fishmonger"
    ],
    "wof:name":"Gilbey,John,",
    "wof:placetype":"venue"
},
  "geometry": {"coordinates":[0.435945,52.080944],"type":"Point"}
}