{
  "type": "Feature",
  "properties": {
    "addr:full":"95 Kings Hill Bude Cornwall EX23 8QL",
    "addr:housenumber":"95",
    "addr:postcode":"ex23 8ql",
    "addr:street":"Kings Hill",
    "iso:country":"GB",
    "sg:address":"95 Kings Hill",
    "sg:city":"Bude",
    "sg:classifiers":[
        {
            "category":"Home & Garden",
            "subcategory":"Furniture",
            "type":"Retail Goods"
        }
    ],
    "sg:phone":"+44 1288 353353",
    "sg:postcode":"EX23 8QL",
    "sg:province":"Cornwall",
    "wof:name":"Tracindon Pine",
    "wof:placetype":"venue"
},
  "geometry": {"coordinates":[-4.5337948799,50.8203392029],"type":"Point"}
}