{
  "type": "Feature",
  "properties": {
    "addr:full":"Liverpool Road Manchester Greater Manchester M44 5DB",
    "addr:postcode":"m44 5db",
    "addr:street":"Liverpool Road",
    "iso:country":"GB",
    "sg:address":"Liverpool Road",
    "sg:city":"Manchester",
    "sg:classifiers":[
        {
            "category":"Home & Garden",
            "subcategory":"Furniture",
            "type":"Retail Goods"
        }
    ],
    "sg:phone":"+44 161 776 1316",
    "sg:postcode":"M44 5DB",
    "sg:province":"Greater Manchester",
    "wof:name":"Pineappeal",
    "wof:placetype":"venue"
},
  "geometry": {"coordinates":[-2.438554,53.42453],"type":"Point"}
}