{
  "type": "Feature",
  "properties": {
    "addr:full":"15 Wilson Street Largs North Ayrshire KA30 9AQ",
    "addr:housenumber":"15",
    "addr:postcode":"ka30 9aq",
    "addr:street":"Wilson Street",
    "iso:country":"GB",
    "sg:address":"15 Wilson Street",
    "sg:city":"Largs",
    "sg:classifiers":[
        {
            "category":"Arena",
            "subcategory":"Sports Club",
            "type":"Entertainment"
        }
    ],
    "sg:phone":"+44 1475 674745",
    "sg:postcode":"KA30 9AQ",
    "sg:province":"North Ayrshire",
    "wof:name":"Halkshill Bowling Club",
    "wof:placetype":"venue"
},
  "geometry": {"coordinates":[-4.8645582199,55.7952766418],"type":"Point"}
}