{
  "type": "Feature",
  "properties": {
    "iso:country":"GB",
    "sg:address":"Crossrig, Hutton",
    "sg:city":"Berwick-upon-tweed",
    "sg:classifiers":[
        {
            "category":"Farming",
            "subcategory":"Farm",
            "type":"Manufacturing & Wholesale Goods"
        }
    ],
    "sg:postcode":"TD15 1XG",
    "sg:province":"Northumberland",
    "sg:tags":[
        "mixed",
        "crop"
    ],
    "wof:name":"R A Sloan & Son",
    "wof:placetype":"venue"
},
  "geometry": {"coordinates":[-2.007024,55.771435],"type":"Point"}
}