{
  "type": "Feature",
  "properties": {
    "addr:full":"308 Preston Road, Standish Wigan Lancashire WN6 0QH",
    "addr:housenumber":"308",
    "addr:postcode":"wn6 0qh",
    "addr:street":"Preston Road",
    "iso:country":"GB",
    "sg:address":"308 Preston Road, Standish",
    "sg:city":"Wigan",
    "sg:classifiers":[
        {
            "category":"Food & Beverages",
            "subcategory":"Liquor & Beverages",
            "type":"Retail Goods"
        }
    ],
    "sg:phone":"+44 1257 402224",
    "sg:postcode":"WN6 0QH",
    "sg:province":"Lancashire",
    "sg:tags":[
        "beer",
        "spirit",
        "wines"
    ],
    "wof:name":"The Wine Cellar",
    "wof:placetype":"venue"
},
  "geometry": {"coordinates":[-2.67251,53.595074],"type":"Point"}
}