{
  "type": "Feature",
  "properties": {
    "addr:full":"19 Old Bridge St Truro Cornwall TR1 2AH",
    "addr:housenumber":"19",
    "addr:postcode":"tr1 2ah",
    "addr:street":"Old Bridge St",
    "iso:country":"GB",
    "sg:address":"19 Old Bridge St",
    "sg:city":"Truro",
    "sg:classifiers":[
        {
            "category":"Transit Center",
            "subcategory":"Freight",
            "type":"Transportation"
        }
    ],
    "sg:postcode":"TR1 2AH",
    "sg:province":"Cornwall",
    "sg:tags":[
        "shop",
        "craft",
        "centre"
    ],
    "wof:name":"Guild of Ten",
    "wof:placetype":"venue"
},
  "geometry": {"coordinates":[-5.049615,50.264336],"type":"Point"}
}