{
  "type": "Feature",
  "properties": {
    "addr:full":"46 Avondale Road North Southport Lancashire PR9 0NE",
    "addr:housenumber":"46",
    "addr:postcode":"pr9 0ne",
    "addr:street":"Avondale Road North",
    "iso:country":"GB",
    "sg:address":"46 Avondale Road North",
    "sg:city":"Southport",
    "sg:classifiers":[
        {
            "category":"Professional",
            "type":"Services"
        }
    ],
    "sg:postcode":"PR9 0NE",
    "sg:province":"Lancashire",
    "sg:tags":[
        "exhibition"
    ],
    "wof:name":"Edge Exhibition",
    "wof:placetype":"venue"
},
  "geometry": {"coordinates":[-2.9972419739,53.6563224792],"type":"Point"}
}