{
  "type": "Feature",
  "properties": {
    "addr:full":"Mintsfeet Trading Estate, Mintsfeet Rd North Kendal Cumbria LA9 6LZ",
    "addr:postcode":"la9 6lz",
    "addr:street":"Mintsfeet Rd North Kendal",
    "iso:country":"GB",
    "sg:address":"Mintsfeet Trading Estate, Mintsfeet Rd North",
    "sg:city":"Kendal",
    "sg:classifiers":[
        {
            "category":"Retail",
            "subcategory":"Auto Repair",
            "type":"Services"
        }
    ],
    "sg:phone":"+44 1539 730830",
    "sg:postcode":"LA9 6LZ",
    "sg:province":"Cumbria",
    "sg:tags":[
        "car",
        "upholsterer"
    ],
    "wof:name":"Twinkleen Car Valeting",
    "wof:placetype":"venue"
},
  "geometry": {"coordinates":[-2.7480840683,54.3240013123],"type":"Point"}
}