{
  "type": "Feature",
  "properties": {
    "iso:country":"GB",
    "sg:address":"675 Chorley New Road, Horwich",
    "sg:city":"Bolton",
    "sg:classifiers":[
        {
            "category":"Professional",
            "subcategory":"Engineering",
            "type":"Services"
        }
    ],
    "sg:phone":"+44 1204 692429",
    "sg:postcode":"BL6 6HR",
    "sg:province":"Lancashire",
    "sg:tags":[
        "contractor",
        "electrical",
        "engineer"
    ],
    "wof:name":"M & J Electrics",
    "wof:placetype":"venue"
},
  "geometry": {"coordinates":[-2.526057,53.586159],"type":"Point"}
}