{
  "type": "Feature",
  "properties": {
    "addr:full":"3 The Ridgeway Sandy Bedfordshire SG19 2PS",
    "addr:housenumber":"3",
    "addr:postcode":"sg19 2ps",
    "addr:street":"The Ridgeway",
    "iso:country":"GB",
    "sg:address":"3 The Ridgeway",
    "sg:city":"Sandy",
    "sg:classifiers":[
        {
            "category":"Education",
            "subcategory":"School",
            "type":"Public Place"
        }
    ],
    "sg:phone":"+44 1767 261401",
    "sg:postcode":"SG19 2PS",
    "sg:province":"Bedfordshire",
    "sg:tags":[
        "private",
        "tuition"
    ],
    "wof:name":"Bedfordshire Tuition",
    "wof:placetype":"venue"
},
  "geometry": {"coordinates":[-0.2184599936,52.1263618469],"type":"Point"}
}