{
  "type": "Feature",
  "properties": {
    "addr:full":"6a St Marys Row, Moseley Birmingham West Midlands B13 8JG",
    "addr:housenumber":"6a",
    "addr:postcode":"b13 8jg",
    "addr:street":"St Marys Row",
    "iso:country":"GB",
    "sg:address":"6a St Marys Row, Moseley",
    "sg:city":"Birmingham",
    "sg:classifiers":[
        {
            "category":"Military Area",
            "subcategory":"Air Force Base",
            "type":"Public Place"
        }
    ],
    "sg:phone":"+44 121 472 8888",
    "sg:postcode":"B13 8JG",
    "sg:province":"West Midlands",
    "sg:tags":[
        "taxi",
        "hire",
        "private"
    ],
    "wof:name":"Royal Cars",
    "wof:placetype":"venue"
},
  "geometry": {"coordinates":[-1.8880280256,52.4463882446],"type":"Point"}
}