{
  "type": "Feature",
  "properties": {
    "addr:full":"The Maltings, Roydon Rd Ware Hertfordshire SG12 8HG",
    "addr:postcode":"sg12 8hg",
    "addr:street":"The Maltings Roydon Rd",
    "iso:country":"GB",
    "sg:address":"The Maltings, Roydon Rd",
    "sg:city":"Ware",
    "sg:classifiers":[
        {
            "category":"Retail",
            "subcategory":"Storage",
            "type":"Services"
        }
    ],
    "sg:phone":"+44 1992 501441",
    "sg:postcode":"SG12 8HG",
    "sg:province":"Hertfordshire",
    "sg:tags":[
        "household",
        "removal"
    ],
    "wof:name":"C E T Removals",
    "wof:placetype":"venue"
},
  "geometry": {"coordinates":[0.0083149998,51.7874412537],"type":"Point"}
}