{
  "type": "Feature",
  "properties": {
    "addr:full":"22 Leyton Road Harpenden Hertfordshire AL5 2HU",
    "addr:housenumber":"22",
    "addr:postcode":"al5 2hu",
    "addr:street":"Leyton Road",
    "iso:country":"GB",
    "sg:address":"22 Leyton Road",
    "sg:city":"Harpenden",
    "sg:classifiers":[
        {
            "category":"Travel",
            "subcategory":"Hotels & Motels",
            "type":"Entertainment"
        }
    ],
    "sg:phone":"+44 1582 712226",
    "sg:postcode":"AL5 2HU",
    "sg:province":"Hertfordshire",
    "sg:tags":[
        "house",
        "guest"
    ],
    "wof:name":"The Laurels Guest House",
    "wof:placetype":"venue"
},
  "geometry": {"coordinates":[-0.3556010127,51.8136062622],"type":"Point"}
}