{
  "type": "Feature",
  "properties": {
    "addr:full":"35 Silkham Road Oxted Surrey RH8 0NS",
    "addr:housenumber":"35",
    "addr:postcode":"rh8 0ns",
    "addr:street":"Silkham Road",
    "iso:country":"GB",
    "sg:address":"35 Silkham Road",
    "sg:city":"Oxted",
    "sg:classifiers":[
        {
            "category":"Building & Trades",
            "subcategory":"Construction",
            "type":"Services"
        }
    ],
    "sg:phone":"+44 1883 714486",
    "sg:postcode":"RH8 0NS",
    "sg:province":"Surrey",
    "sg:tags":[
        "glazier"
    ],
    "wof:name":"The Oxted Glass & Window Co",
    "wof:placetype":"venue"
},
  "geometry": {"coordinates":[-0.008699,51.264347],"type":"Point"}
}