{
  "type": "Feature",
  "properties": {
    "addr:full":"Trinder Ho, Free St Southampton Hampshire SO32 1EE",
    "addr:postcode":"so32 1ee",
    "addr:street":"St",
    "iso:country":"GB",
    "sg:address":"Trinder Ho, Free St",
    "sg:city":"Southampton",
    "sg:classifiers":[
        {
            "category":"Real Estate",
            "subcategory":"Surveying",
            "type":"Services"
        }
    ],
    "sg:phone":"+44 1489 894348",
    "sg:postcode":"SO32 1EE",
    "sg:province":"Hampshire",
    "sg:tags":[
        "building",
        "surveyor"
    ],
    "wof:name":"McAndrew Martin Partnership",
    "wof:placetype":"venue"
},
  "geometry": {"coordinates":[-1.2082899809,50.9563407898],"type":"Point"}
}