{
  "type": "Feature",
  "properties": {
    "addr:full":"Unit 2, Bankside Industrial Estate, Sumner Street London Greater London SE1 9JZ",
    "addr:housenumber":"unit 2;estate",
    "addr:postcode":"se1 9jz",
    "addr:street":"Bankside Industrial;Sumner Street",
    "iso:country":"GB",
    "sg:address":"Unit 2, Bankside Industrial Estate, Sumner Street",
    "sg:city":"London",
    "sg:classifiers":[
        {
            "category":"Food & Beverages",
            "subcategory":"Liquor & Beverages",
            "type":"Retail Goods"
        }
    ],
    "sg:phone":"+44 20 7589 5753",
    "sg:postcode":"SE1 9JZ",
    "sg:province":"Greater London",
    "sg:tags":[
        "beer",
        "spirit",
        "wines"
    ],
    "wof:name":"Morris & Verdin Ltd.",
    "wof:placetype":"venue"
},
  "geometry": {"coordinates":[-0.0960299969,51.5064697266],"type":"Point"}
}