{
  "type": "Feature",
  "properties": {
    "addr:full":"696 Dumbarton Road Glasgow Glasgow City G11 6RB",
    "addr:housenumber":"696",
    "addr:postcode":"g11 6rb",
    "addr:street":"Dumbarton Road",
    "iso:country":"GB",
    "sg:address":"696 Dumbarton Road",
    "sg:city":"Glasgow",
    "sg:classifiers":[
        {
            "category":"Shopping",
            "subcategory":"Department Store",
            "type":"Retail Goods"
        },
        {
            "category":"Food & Beverages",
            "subcategory":"Groceries & Convenience Stores",
            "type":"Retail Goods"
        }
    ],
    "sg:phone":"+44 141 334 2367",
    "sg:postcode":"G11 6RB",
    "sg:province":"Glasgow City",
    "wof:name":"Stardust",
    "wof:placetype":"venue"
},
  "geometry": {"coordinates":[-4.3209338188,55.8710899353],"type":"Point"}
}