{
  "type": "Feature",
  "properties": {
    "iso:country":"GB",
    "sg:address":"289 Oxford Road",
    "sg:city":"Reading",
    "sg:classifiers":[
        {
            "category":"Home & Garden",
            "subcategory":"Furniture",
            "type":"Retail Goods"
        }
    ],
    "sg:phone":"+44 118 939 3555",
    "sg:postcode":"RG30 1AS",
    "sg:province":"Berkshire",
    "wof:name":"Dreams Bed Superstores",
    "wof:placetype":"venue"
},
  "geometry": {"coordinates":[-0.993856,51.456451],"type":"Point"}
}