{
  "type": "Feature",
  "properties": {
    "addr:full":"Riverside Manor, 77 Castle St Swansea Carmarthenshire SA4 6TS",
    "addr:housenumber":"77",
    "addr:postcode":"sa4 6ts",
    "addr:street":"Castle St",
    "iso:country":"GB",
    "sg:address":"Riverside Manor, 77 Castle St",
    "sg:city":"Swansea",
    "sg:classifiers":[
        {
            "category":"Shopping",
            "subcategory":"Party Supplies",
            "type":"Retail Goods"
        }
    ],
    "sg:phone":"+44 1792 893392",
    "sg:postcode":"SA4 6TS",
    "sg:province":"Carmarthenshire",
    "sg:tags":[
        "inflatables",
        "bouncy",
        "castle"
    ],
    "wof:name":"Bounce About",
    "wof:placetype":"venue"
},
  "geometry": {"coordinates":[-4.0760002136,51.6629486084],"type":"Point"}
}