{
  "type": "Feature",
  "properties": {
    "addr:full":"Thorofare St Marys Cornwall TR21 0LN",
    "addr:postcode":"tr21 0ln",
    "addr:street":"Thorofare",
    "iso:country":"GB",
    "sg:address":"Thorofare",
    "sg:city":"St Marys",
    "sg:classifiers":[
        {
            "category":"Travel",
            "subcategory":"Hotels & Motels",
            "type":"Entertainment"
        }
    ],
    "sg:phone":"+44 1720 422688",
    "sg:postcode":"TR21 0LN",
    "sg:province":"Cornwall",
    "sg:tags":[
        "house",
        "guest"
    ],
    "wof:name":"The Boat House",
    "wof:placetype":"venue"
},
  "geometry": {"coordinates":[-6.31514,49.914501],"type":"Point"}
}