{
  "type": "Feature",
  "properties": {
    "addr:full":"112-114 Witton St Northwich Cheshire CW9 5DY",
    "addr:housenumber":"112-114",
    "addr:postcode":"cw9 5dy",
    "addr:street":"Witton St",
    "iso:country":"GB",
    "sg:address":"112-114 Witton St",
    "sg:city":"Northwich",
    "sg:classifiers":[
        {
            "category":"Cinema",
            "subcategory":"Movie Rental",
            "type":"Entertainment"
        }
    ],
    "sg:phone":"+44 1606 42344",
    "sg:postcode":"CW9 5DY",
    "sg:province":"Cheshire",
    "sg:tags":[
        "video",
        "library"
    ],
    "wof:name":"Channel 40 Video",
    "wof:placetype":"venue"
},
  "geometry": {"coordinates":[-2.508036,53.26218],"type":"Point"}
}