{
  "type": "Feature",
  "properties": {
    "addr:full":"384 Bowes Road London Greater London N11 1AH",
    "addr:housenumber":"384",
    "addr:postcode":"n11 1ah",
    "addr:street":"Bowes Road",
    "iso:country":"GB",
    "sg:address":"384 Bowes Road",
    "sg:city":"London",
    "sg:classifiers":[
        {
            "category":"Personal",
            "subcategory":"Beauty Salon",
            "type":"Services"
        },
        {
            "category":"Personal",
            "subcategory":"Barber",
            "type":"Services"
        }
    ],
    "sg:phone":"+44 20 8361 0526",
    "sg:postcode":"N11 1AH",
    "sg:province":"Greater London",
    "sg:tags":[
        "unisex",
        "hairdresser"
    ],
    "wof:name":"Diva",
    "wof:placetype":"venue"
},
  "geometry": {"coordinates":[-0.13596,51.616364],"type":"Point"}
}