{
  "type": "Feature",
  "properties": {
    "addr:full":"Cranbrook Road, Staplehurst Tonbridge Kent TN12 0ER",
    "addr:postcode":"tn12 0er",
    "addr:street":"Cranbrook Road",
    "iso:country":"GB",
    "sg:address":"Cranbrook Road, Staplehurst",
    "sg:city":"Tonbridge",
    "sg:classifiers":[
        {
            "category":"Social Services",
            "subcategory":"Retirement Home",
            "type":"Services"
        }
    ],
    "sg:postcode":"TN12 0ER",
    "sg:province":"Kent",
    "sg:tags":[
        "residential",
        "care"
    ],
    "wof:name":"St.Mary's Residential Home",
    "wof:placetype":"venue"
},
  "geometry": {"coordinates":[0.552592,51.167049],"type":"Point"}
}