{
  "type": "Feature",
  "properties": {
    "iso:country":"GB",
    "sg:address":"2 Beatty Ave",
    "sg:city":"Brighton",
    "sg:classifiers":[
        {
            "category":"Food & Beverages",
            "subcategory":"Meat & Fish",
            "type":"Retail Goods"
        }
    ],
    "sg:postcode":"BN1 9ED",
    "sg:province":"East Sussex",
    "sg:tags":[
        "butcher"
    ],
    "wof:name":"Adams,A,",
    "wof:placetype":"venue"
},
  "geometry": {"coordinates":[-0.112492,50.862762],"type":"Point"}
}