{
  "type": "Feature",
  "properties": {
    "iso:country":"GB",
    "sg:address":"75 Hermitage Rd",
    "sg:city":"Hitchin",
    "sg:classifiers":[
        {
            "category":"Home & Garden",
            "subcategory":"Home Furnishings",
            "type":"Retail Goods"
        }
    ],
    "sg:phone":"+44 1462 458860",
    "sg:postcode":"SG5 1DB",
    "sg:province":"Bedfordshire",
    "sg:tags":[
        "furnishers",
        "planner",
        "kitchen"
    ],
    "wof:name":"Planfit Kitchens Ltd",
    "wof:placetype":"venue"
},
  "geometry": {"coordinates":[-0.275623,51.949211],"type":"Point"}
}