{
  "type": "Feature",
  "properties": {
    "iso:country":"GB",
    "sg:address":"Whites Place, Main Road, Margaretting",
    "sg:city":"Ingatestone",
    "sg:classifiers":[
        {
            "category":"Farming",
            "subcategory":"Livestock Farm",
            "type":"Manufacturing & Wholesale Goods"
        }
    ],
    "sg:postcode":"CM4 0ES",
    "sg:province":"Essex",
    "sg:tags":[
        "others"
    ],
    "wof:name":"Andrew J Magness",
    "wof:placetype":"venue"
},
  "geometry": {"coordinates":[0.383585,51.669922],"type":"Point"}
}