{
  "type": "Feature",
  "properties": {
    "addr:full":"148 High St Redcar North Yorkshire TS10 3DH",
    "addr:housenumber":"148",
    "addr:postcode":"ts10 3dh",
    "addr:street":"High St",
    "iso:country":"GB",
    "sg:address":"148 High St",
    "sg:city":"Redcar",
    "sg:classifiers":[
        {
            "category":"Shopping",
            "subcategory":"Clothing, Apparel, & Fashions",
            "type":"Retail Goods"
        }
    ],
    "sg:phone":"+44 1642 479968",
    "sg:postcode":"TS10 3DH",
    "sg:province":"North Yorkshire",
    "sg:tags":[
        "haberdasher"
    ],
    "wof:name":"Kreative Korner",
    "wof:placetype":"venue"
},
  "geometry": {"coordinates":[-1.060005,54.617306],"type":"Point"}
}