{
  "type": "Feature",
  "properties": {
    "addr:full":"20 Aldermary Rd Bromley Kent BR1 3PH",
    "addr:housenumber":"20",
    "addr:postcode":"br1 3ph",
    "addr:street":"Aldermary Rd",
    "iso:country":"GB",
    "sg:address":"20 Aldermary Rd",
    "sg:city":"Bromley",
    "sg:classifiers":[
        {
            "category":"Building & Trades",
            "subcategory":"Landscaping Services",
            "type":"Services"
        }
    ],
    "sg:postcode":"BR1 3PH",
    "sg:province":"Kent",
    "sg:tags":[
        "forestry",
        "tree"
    ],
    "wof:name":"Marshall's Tree Services",
    "wof:placetype":"venue"
},
  "geometry": {"coordinates":[0.015834,51.4108276367],"type":"Point"}
}