{
  "type": "Feature",
  "properties": {
    "addr:full":"6 Wood St Bath Bath and North East Somerset BA1 2JQ",
    "addr:housenumber":"6",
    "addr:postcode":"ba1 2jq",
    "addr:street":"Wood St",
    "iso:country":"GB",
    "sg:address":"6 Wood St",
    "sg:city":"Bath",
    "sg:classifiers":[
        {
            "category":"Food & Beverages",
            "subcategory":"Liquor & Beverages",
            "type":"Retail Goods"
        }
    ],
    "sg:phone":"+44 1225 460099",
    "sg:postcode":"BA1 2JQ",
    "sg:province":"Bath and North East Somerset",
    "sg:tags":[
        "beer",
        "spirit",
        "wines"
    ],
    "wof:name":"Euroweins Ltd",
    "wof:placetype":"venue"
},
  "geometry": {"coordinates":[-2.362283,51.383316],"type":"Point"}
}