{
  "type": "Feature",
  "properties": {
    "addr:full":"Newdigate Street, Kimberley Nottingham Derbyshire NG16 2NJ",
    "addr:postcode":"ng16 2nj",
    "addr:street":"Newdigate Street",
    "iso:country":"GB",
    "sg:address":"Newdigate Street, Kimberley",
    "sg:city":"Nottingham",
    "sg:classifiers":[
        {
            "category":"Government",
            "subcategory":"City Hall",
            "type":"Public Place"
        }
    ],
    "sg:postcode":"NG16 2NJ",
    "sg:province":"Derbyshire",
    "wof:name":"Kimberley Parish Hall",
    "wof:placetype":"venue"
},
  "geometry": {"coordinates":[-1.256824,52.997456],"type":"Point"}
}