{
  "type": "Feature",
  "properties": {
    "addr:full":"Unit 10, Howden Industrial Estate Tiverton Devon EX16 5HW",
    "addr:housenumber":"unit 10",
    "addr:postcode":"ex16 5hw",
    "addr:street":"Howden Industrial Estate",
    "iso:country":"GB",
    "sg:address":"Unit 10, Howden Industrial Estate",
    "sg:city":"Tiverton",
    "sg:classifiers":[
        {
            "category":"Shopping",
            "subcategory":"Gifts & Souvenirs",
            "type":"Retail Goods"
        }
    ],
    "sg:phone":"+44 1884 254331",
    "sg:postcode":"EX16 5HW",
    "sg:province":"Devon",
    "sg:tags":[
        "ducting"
    ],
    "wof:name":"G R Pook Engineering Ltd",
    "wof:placetype":"venue"
},
  "geometry": {"coordinates":[-3.496119,50.90435],"type":"Point"}
}