{
  "type": "Feature",
  "properties": {
    "addr:full":"53 Cherington Close Redditch Warwickshire B98 0BB",
    "addr:housenumber":"53",
    "addr:postcode":"b98 0bb",
    "addr:street":"Cherington Close",
    "iso:country":"GB",
    "sg:address":"53 Cherington Close",
    "sg:city":"Redditch",
    "sg:classifiers":[
        {
            "category":"Professional",
            "subcategory":"Engineering",
            "type":"Services"
        },
        {
            "category":"Building & Trades",
            "subcategory":"Electrical",
            "type":"Services"
        }
    ],
    "sg:phone":"+44 1527 500957",
    "sg:postcode":"B98 0BB",
    "sg:province":"Warwickshire",
    "sg:tags":[
        "engineer",
        "electrician",
        "contractor"
    ],
    "wof:name":"Shirley Electrical Services",
    "wof:placetype":"venue"
},
  "geometry": {"coordinates":[-1.888062,52.294697],"type":"Point"}
}