{
  "type": "Feature",
  "properties": {
    "iso:country":"GB",
    "sg:address":"James Watt Way",
    "sg:city":"Erith",
    "sg:classifiers":[
        {
            "category":"Organizations",
            "subcategory":"Community Association",
            "type":"Services"
        },
        {
            "category":"Organizations",
            "subcategory":"Membership Organization",
            "type":"Services"
        }
    ],
    "sg:phone":"+44 1322 332188",
    "sg:postcode":"DA8 1RW",
    "sg:province":"Kent",
    "sg:tags":[
        "club",
        "social"
    ],
    "wof:name":"Erith Trade & Social Club Ltd.",
    "wof:placetype":"venue"
},
  "geometry": {"coordinates":[0.181957,51.479202],"type":"Point"}
}