{
  "type": "Feature",
  "properties": {
    "addr:full":"5 Acacia Gro Berkhamsted Bedfordshire HP4 3AJ",
    "addr:housenumber":"5",
    "addr:postcode":"hp4 3aj",
    "addr:street":"Acacia Gro",
    "iso:country":"GB",
    "sg:address":"5 Acacia Gro",
    "sg:city":"Berkhamsted",
    "sg:classifiers":[
        {
            "category":"Professional",
            "subcategory":"Management & Consulting",
            "type":"Services"
        }
    ],
    "sg:postcode":"HP4 3AJ",
    "sg:province":"Bedfordshire",
    "sg:tags":[
        "consultant",
        "business"
    ],
    "wof:name":"Toptrend Ltd.",
    "wof:placetype":"venue"
},
  "geometry": {"coordinates":[-0.5673019886,51.7550544739],"type":"Point"}
}