{
  "type": "Feature",
  "properties": {
    "addr:full":"84 Standon Road Sheffield South Yorkshire S9 1PF",
    "addr:housenumber":"84",
    "addr:postcode":"s9 1pf",
    "addr:street":"Standon Road",
    "iso:country":"GB",
    "sg:address":"84 Standon Road",
    "sg:city":"Sheffield",
    "sg:classifiers":[
        {
            "category":"Manufacturing",
            "subcategory":"Metals",
            "type":"Manufacturing & Wholesale Goods"
        }
    ],
    "sg:phone":"+44 114 244 8428",
    "sg:postcode":"S9 1PF",
    "sg:province":"South Yorkshire",
    "sg:tags":[
        "steel",
        "fabricator",
        "erectors"
    ],
    "wof:name":"Anvil Specialist Steel Works Repairs & Maintenance",
    "wof:placetype":"venue"
},
  "geometry": {"coordinates":[-1.421841,53.423626],"type":"Point"}
}