{
  "type": "Feature",
  "properties": {
    "addr:full":"General Enquiries, Tuckswood Surgery, Hall Rd Norwich Norfolk NR4 6NE",
    "addr:postcode":"nr4 6ne",
    "addr:street":"Hall Rd",
    "iso:country":"GB",
    "sg:address":"General Enquiries, Tuckswood Surgery, Hall Rd",
    "sg:city":"Norwich",
    "sg:classifiers":[
        {
            "category":"Health Services",
            "subcategory":"Doctor",
            "type":"Services"
        }
    ],
    "sg:phone":"+44 1603 447766",
    "sg:postcode":"NR4 6NE",
    "sg:province":"Norfolk",
    "sg:tags":[
        "practitioners"
    ],
    "wof:name":"Hutchinson, C T",
    "wof:placetype":"venue"
},
  "geometry": {"coordinates":[1.2892,52.609669],"type":"Point"}
}