{
  "type": "Feature",
  "properties": {
    "iso:country":"GB",
    "sg:address":"3 Tennyson Avenue, Four Oaks",
    "sg:city":"Sutton Coldfield",
    "sg:classifiers":[
        {
            "category":"Professional",
            "subcategory":"Employment Agencies",
            "type":"Services"
        }
    ],
    "sg:postcode":"B74 4YG",
    "sg:province":"Staffordshire",
    "sg:tags":[
        "consultant"
    ],
    "wof:name":"Staff Cover Ltd",
    "wof:placetype":"venue"
},
  "geometry": {"coordinates":[-1.841724,52.605072],"type":"Point"}
}