{
  "type": "Feature",
  "properties": {
    "iso:country":"GB",
    "sg:address":"91 Woodfield Street",
    "sg:city":"Swansea",
    "sg:classifiers":[
        {
            "category":"Home & Garden",
            "subcategory":"Home Furnishings",
            "type":"Retail Goods"
        }
    ],
    "sg:phone":"+44 1792 797762",
    "sg:postcode":"SA6 8BA",
    "sg:province":"Swansea",
    "sg:tags":[
        "beds",
        "bedding",
        "blanket"
    ],
    "wof:name":"Carolyn",
    "wof:placetype":"venue"
},
  "geometry": {"coordinates":[-3.9259068966,51.6637191772],"type":"Point"}
}