{
  "type": "Feature",
  "properties": {
    "iso:country":"GB",
    "sg:address":"North Drumboy Farm, Glasgow Road, Fenwick",
    "sg:city":"Kilmarnock",
    "sg:classifiers":[
        {
            "category":"Farming",
            "subcategory":"Livestock Farm",
            "type":"Manufacturing & Wholesale Goods"
        }
    ],
    "sg:phone":"+44 1355 500236",
    "sg:postcode":"KA3 6EU",
    "sg:province":"East Ayrshire",
    "sg:tags":[
        "others"
    ],
    "wof:name":"Robert Dunlop & Son",
    "wof:placetype":"venue"
},
  "geometry": {"coordinates":[-4.4435968399,55.6620635986],"type":"Point"}
}