{
  "type": "Feature",
  "properties": {
    "addr:full":"225a South Coast Road Peacehaven East Sussex BN10 8LB",
    "addr:housenumber":"225a",
    "addr:postcode":"bn10 8lb",
    "addr:street":"South Coast Road Peacehaven",
    "iso:country":"GB",
    "sg:address":"225a South Coast Road",
    "sg:city":"Peacehaven",
    "sg:classifiers":[
        {
            "category":"Shopping",
            "subcategory":"Florist",
            "type":"Retail Goods"
        }
    ],
    "sg:phone":"+44 1273 583704",
    "sg:postcode":"BN10 8LB",
    "sg:province":"East Sussex",
    "wof:name":"Arlettes",
    "wof:placetype":"venue"
},
  "geometry": {"coordinates":[-0.001357,50.7910995483],"type":"Point"}
}