{
  "type": "Feature",
  "properties": {
    "addr:full":"4c Lawnswood Houghton Le Spring Durham DH5 8JB",
    "addr:housenumber":"4c",
    "addr:postcode":"dh5 8jb",
    "addr:street":"Lawnswood Houghton Le Spring",
    "iso:country":"GB",
    "sg:address":"4c Lawnswood",
    "sg:city":"Houghton Le Spring",
    "sg:classifiers":[
        {
            "category":"Home & Garden",
            "subcategory":"Household Appliances",
            "type":"Retail Goods"
        }
    ],
    "sg:phone":"+44 191 584 6162",
    "sg:postcode":"DH5 8JB",
    "sg:province":"Durham",
    "sg:tags":[
        "cleaner",
        "domestic",
        "vacuum"
    ],
    "wof:name":"M Benson",
    "wof:placetype":"venue"
},
  "geometry": {"coordinates":[-1.4633020163,54.837638855],"type":"Point"}
}