{
  "type": "Feature",
  "properties": {
    "iso:country":"GB",
    "sg:address":"7 High Street",
    "sg:city":"Wooler",
    "sg:classifiers":[
        {
            "category":"Food & Beverages",
            "subcategory":"Bakery",
            "type":"Retail Goods"
        }
    ],
    "sg:postcode":"NE71 6LD",
    "sg:province":"Northumberland",
    "sg:tags":[
        "baker"
    ],
    "wof:name":"James G Fairbairn",
    "wof:placetype":"venue"
},
  "geometry": {"coordinates":[-2.015473,55.546078],"type":"Point"}
}