{
  "type": "Feature",
  "properties": {
    "iso:country":"GB",
    "sg:address":"5 Grove Road, Redland",
    "sg:city":"Bristol",
    "sg:classifiers":[
        {
            "category":"Professional",
            "subcategory":"Detective & Security Services",
            "type":"Services"
        }
    ],
    "sg:phone":"+44 1275 540282",
    "sg:postcode":"BS6 6UJ",
    "sg:province":"City of Bristol",
    "sg:tags":[
        "agency"
    ],
    "wof:name":"John Nunn",
    "wof:placetype":"venue"
},
  "geometry": {"coordinates":[-2.613924,51.469814],"type":"Point"}
}