{
  "type": "Feature",
  "properties": {
    "iso:country":"GB",
    "sg:address":"Downderry Garage, Downderry",
    "sg:city":"Torpoint",
    "sg:classifiers":[
        {
            "category":"Shopping",
            "type":"Retail Goods"
        }
    ],
    "sg:postcode":"PL11 3LN",
    "sg:province":"Cornwall",
    "sg:tags":[
        "part",
        "accessory"
    ],
    "wof:name":"Motor Mania",
    "wof:placetype":"venue"
},
  "geometry": {"coordinates":[-4.36952,50.361847],"type":"Point"}
}