{
  "type": "Feature",
  "properties": {
    "addr:full":"Unit 19 12 Horn La Greenwich Greater London SE10 0RT",
    "addr:housenumber":"unit;12",
    "addr:postcode":"se10 0rt",
    "addr:street":"Horn La Greenwich",
    "iso:country":"GB",
    "sg:address":"Unit 19 12 Horn La",
    "sg:city":"Greenwich",
    "sg:classifiers":[
        {
            "category":"Home & Garden",
            "subcategory":"Carpets & Floor Coverings",
            "type":"Retail Goods"
        }
    ],
    "sg:phone":"+44 20 8305 2259",
    "sg:postcode":"SE10 0RT",
    "sg:province":"Greater London",
    "sg:tags":[
        "carpets",
        "rug",
        "matting"
    ],
    "wof:name":"Quickseam",
    "wof:placetype":"venue"
},
  "geometry": {"coordinates":[0.0184480008,51.4889945984],"type":"Point"}
}