{
  "type": "Feature",
  "properties": {
    "addr:full":"78a Westborough Scarborough North Yorkshire YO11 2JN",
    "addr:housenumber":"78a",
    "addr:postcode":"yo11 2jn",
    "addr:street":"Westborough",
    "iso:country":"GB",
    "sg:address":"78a Westborough",
    "sg:city":"Scarborough",
    "sg:classifiers":[
        {
            "category":"Personal",
            "subcategory":"Beauty Salon",
            "type":"Services"
        }
    ],
    "sg:phone":"+44 1723 375944",
    "sg:postcode":"YO11 2JN",
    "sg:province":"North Yorkshire",
    "sg:tags":[
        "unisex",
        "hairdresser"
    ],
    "wof:name":"Hair by Helena",
    "wof:placetype":"venue"
},
  "geometry": {"coordinates":[-0.406731993,54.279712677],"type":"Point"}
}