{
  "type": "Feature",
  "properties": {
    "iso:country":"GB",
    "sg:address":"Owls Barn, Birkhouse, Bailiffe Bridge",
    "sg:city":"Brighouse",
    "sg:classifiers":[
        {
            "category":"Professional",
            "subcategory":"Engineering",
            "type":"Services"
        }
    ],
    "sg:postcode":"HD6 4JL",
    "sg:province":"West Yorkshire",
    "sg:tags":[
        "contractor",
        "electrical",
        "engineer"
    ],
    "wof:name":"P T Electrical",
    "wof:placetype":"venue"
},
  "geometry": {"coordinates":[-1.773737,53.702194],"type":"Point"}
}