{
  "type": "Feature",
  "properties": {
    "iso:country":"GB",
    "sg:address":"422 Gorton Road, Reddish",
    "sg:city":"Stockport",
    "sg:classifiers":[
        {
            "category":"Food & Beverages",
            "subcategory":"Liquor & Beverages",
            "type":"Retail Goods"
        }
    ],
    "sg:phone":"+44 161 432 7866",
    "sg:postcode":"SK5 6RS",
    "sg:province":"Cheshire",
    "sg:tags":[
        "beer",
        "spirit",
        "wines"
    ],
    "wof:name":"Carole & Keith's Wines",
    "wof:placetype":"venue"
},
  "geometry": {"coordinates":[-2.157314,53.448765],"type":"Point"}
}