{
  "type": "Feature",
  "properties": {
    "iso:country":"GB",
    "sg:address":"The Engine House, White House Road, Little Ouse",
    "sg:city":"Ely",
    "sg:classifiers":[
        {
            "category":"Home & Garden",
            "subcategory":"Home Furnishings",
            "type":"Retail Goods"
        },
        {
            "category":"Home & Garden",
            "subcategory":"Building Materials",
            "type":"Retail Goods"
        }
    ],
    "sg:phone":"+44 1353 676227",
    "sg:postcode":"CB7 4TG",
    "sg:province":"Cambridgeshire",
    "sg:tags":[
        "installers",
        "planner",
        "kitchen",
        "furnishers"
    ],
    "wof:name":"New From Old-Kitchen Furniture",
    "wof:placetype":"venue"
},
  "geometry": {"coordinates":[0.380475,52.47504],"type":"Point"}
}