{
  "type": "Feature",
  "properties": {
    "iso:country":"GB",
    "sg:address":"1-3 Furmston Court",
    "sg:city":"Letchworth",
    "sg:classifiers":[
        {
            "category":"Home & Garden",
            "subcategory":"Carpets & Floor Coverings",
            "type":"Retail Goods"
        }
    ],
    "sg:phone":"+44 1462 485044",
    "sg:postcode":"SG6 1UJ",
    "sg:province":"Hertfordshire",
    "sg:tags":[
        "textile",
        "floorcoverings"
    ],
    "wof:name":"Garden City Flooring",
    "wof:placetype":"venue"
},
  "geometry": {"coordinates":[-0.220626995,51.9848670959],"type":"Point"}
}