{
  "type": "Feature",
  "properties": {
    "iso:country":"GB",
    "sg:address":"The Square, Talgarth",
    "sg:city":"Brecon",
    "sg:classifiers":[
        {
            "category":"Travel",
            "subcategory":"Hotels & Motels",
            "type":"Entertainment"
        }
    ],
    "sg:phone":"+44 1874 711253",
    "sg:postcode":"LD3 0BW",
    "sg:province":"Powys",
    "wof:name":"Tower Hotel",
    "wof:placetype":"venue"
},
  "geometry": {"coordinates":[-3.2329919338,51.9960823059],"type":"Point"}
}