{
  "type": "Feature",
  "properties": {
    "iso:country":"GB",
    "sg:address":"151 Lydalls Rd",
    "sg:city":"Didcot",
    "sg:classifiers":[
        {
            "category":"Building & Trades",
            "subcategory":"Construction",
            "type":"Services"
        }
    ],
    "sg:phone":"+44 1235 512795",
    "sg:postcode":"OX11 7EA",
    "sg:province":"Oxfordshire",
    "sg:tags":[
        "builder"
    ],
    "wof:name":"O A J Brown",
    "wof:placetype":"venue"
},
  "geometry": {"coordinates":[-1.251935,51.610001],"type":"Point"}
}