{
  "type": "Feature",
  "properties": {
    "iso:country":"GB",
    "sg:address":"23 Derby Road, Swanwick",
    "sg:city":"Alfreton",
    "sg:classifiers":[
        {
            "category":"Bakery",
            "type":"Food & Drink"
        }
    ],
    "sg:phone":"+44 1773 512585",
    "sg:postcode":"DE55 1AB",
    "sg:province":"Derbyshire",
    "sg:tags":[
        "cake",
        "maker"
    ],
    "wof:name":"Country Larder",
    "wof:placetype":"venue"
},
  "geometry": {"coordinates":[-1.3992209435,53.0768966675],"type":"Point"}
}