{
  "type": "Feature",
  "properties": {
    "addr:full":"3 High Street Nairn Highland IV12 4AG",
    "addr:housenumber":"3",
    "addr:postcode":"iv12 4ag",
    "addr:street":"High Street",
    "iso:country":"GB",
    "sg:address":"3 High Street",
    "sg:city":"Nairn",
    "sg:classifiers":[
        {
            "category":"Personal",
            "subcategory":"Beauty Salon",
            "type":"Services"
        },
        {
            "category":"Personal",
            "subcategory":"Barber",
            "type":"Services"
        },
        {
            "category":"Health Services",
            "subcategory":"Podiatrist",
            "type":"Services"
        }
    ],
    "sg:phone":"+44 1667 453494",
    "sg:postcode":"IV12 4AG",
    "sg:province":"Highland",
    "sg:tags":[
        "unisex",
        "podiatrists",
        "chiropodist",
        "hairdresser"
    ],
    "wof:name":"Mr Edward",
    "wof:placetype":"venue"
},
  "geometry": {"coordinates":[-3.8704469204,57.5834541321],"type":"Point"}
}