{
  "type": "Feature",
  "properties": {
    "addr:full":"6 The Mount Drive Reigate Surrey RH2 0EZ",
    "addr:housenumber":"6",
    "addr:postcode":"rh2 0ez",
    "addr:street":"The Mount Drive",
    "iso:country":"GB",
    "sg:address":"6 The Mount Drive",
    "sg:city":"Reigate",
    "sg:classifiers":[
        {
            "category":"Utilities",
            "subcategory":"Electric",
            "type":"Services"
        },
        {
            "category":"Building & Trades",
            "subcategory":"Construction",
            "type":"Services"
        }
    ],
    "sg:phone":"+44 1737 247992",
    "sg:postcode":"RH2 0EZ",
    "sg:province":"Surrey",
    "sg:tags":[
        "equipment",
        "builder",
        "heating",
        "sale"
    ],
    "wof:name":"A Haylock & Son Building Services Ltd",
    "wof:placetype":"venue"
},
  "geometry": {"coordinates":[-0.187428996,51.2480545044],"type":"Point"}
}