{
  "type": "Feature",
  "properties": {
    "addr:full":"Warden, 56 Brownhill Avenue Burnley Lancashire BB10 4QD",
    "addr:housenumber":"56",
    "addr:postcode":"bb10 4qd",
    "addr:street":"Warden;Brownhill Avenue",
    "iso:country":"GB",
    "sg:address":"Warden, 56 Brownhill Avenue",
    "sg:city":"Burnley",
    "sg:classifiers":[
        {
            "category":"Social Services",
            "subcategory":"Adult Care",
            "type":"Services"
        },
        {
            "category":"Government",
            "subcategory":"Office",
            "type":"Public Place"
        }
    ],
    "sg:phone":"+44 1282 454836",
    "sg:postcode":"BB10 4QD",
    "sg:province":"Lancashire",
    "sg:tags":[
        "housing",
        "local",
        "sheltered"
    ],
    "wof:name":"Brownhill Avenue Sheltered Housing",
    "wof:placetype":"venue"
},
  "geometry": {"coordinates":[-2.22558,53.789299],"type":"Point"}
}