{
  "type": "Feature",
  "properties": {
    "addr:full":"The Beeches, Mill Lane Cheadle Cheshire SK8 2PY",
    "addr:postcode":"sk8 2py",
    "addr:street":"Beeches Mill Lane Cheadle",
    "iso:country":"GB",
    "sg:address":"The Beeches, Mill Lane",
    "sg:city":"Cheadle",
    "sg:classifiers":[
        {
            "category":"Health Services",
            "subcategory":"Doctor",
            "type":"Services"
        }
    ],
    "sg:phone":"+44 161 491 2606",
    "sg:postcode":"SK8 2PY",
    "sg:province":"Cheshire",
    "sg:tags":[
        "surgeon",
        "practitioners"
    ],
    "wof:name":"G A Morewood",
    "wof:placetype":"venue"
},
  "geometry": {"coordinates":[-2.212272,53.395248],"type":"Point"}
}