{
  "type": "Feature",
  "properties": {
    "iso:country":"GB",
    "sg:address":"78-80 Hollemeadow Avenue",
    "sg:city":"Walsall",
    "sg:classifiers":[
        {
            "category":"Food & Beverages",
            "subcategory":"Supermarket",
            "type":"Retail Goods"
        }
    ],
    "sg:phone":"+44 1922 476473",
    "sg:postcode":"WS3 1JB",
    "sg:province":"Staffordshire",
    "wof:name":"Rams Superstore",
    "wof:placetype":"venue"
},
  "geometry": {"coordinates":[-1.990023,52.610363],"type":"Point"}
}