{
  "type": "Feature",
  "properties": {
    "addr:full":"7 Sandy Meade, Prestwich Manchester Greater Manchester M25 9PR",
    "addr:housenumber":"7",
    "addr:postcode":"m25 9pr",
    "addr:street":"Sandy Meade",
    "iso:country":"GB",
    "sg:address":"7 Sandy Meade, Prestwich",
    "sg:city":"Manchester",
    "sg:classifiers":[
        {
            "category":"Shopping",
            "subcategory":"Clothing, Apparel, & Fashions",
            "type":"Retail Goods"
        }
    ],
    "sg:postcode":"M25 9PR",
    "sg:province":"Greater Manchester",
    "sg:tags":[
        "accessory"
    ],
    "wof:name":"David Lee Wholesale Fashion Jewellery",
    "wof:placetype":"venue"
},
  "geometry": {"coordinates":[-2.288214,53.524559],"type":"Point"}
}