{
  "type": "Feature",
  "properties": {
    "addr:full":"26 Soundwell Road Bristol City of Bristol BS16 4QW",
    "addr:housenumber":"26",
    "addr:postcode":"bs16 4qw",
    "addr:street":"Soundwell Road",
    "iso:country":"GB",
    "sg:address":"26 Soundwell Road",
    "sg:city":"Bristol",
    "sg:classifiers":[
        {
            "category":"Food & Beverages",
            "subcategory":"Liquor & Beverages",
            "type":"Retail Goods"
        }
    ],
    "sg:postcode":"BS16 4QW",
    "sg:province":"City of Bristol",
    "sg:tags":[
        "beer",
        "spirit",
        "wines"
    ],
    "wof:name":"Humpers Off Licence",
    "wof:placetype":"venue"
},
  "geometry": {"coordinates":[-2.5078659058,51.4781990051],"type":"Point"}
}