{
  "type": "Feature",
  "properties": {
    "addr:full":"12 Park Street Lytham St Annes Lancashire FY8 5LU",
    "addr:housenumber":"12",
    "addr:postcode":"fy8 5lu",
    "addr:street":"Park Street",
    "iso:country":"GB",
    "sg:address":"12 Park Street",
    "sg:city":"Lytham St Annes",
    "sg:classifiers":[
        {
            "category":"Professional",
            "subcategory":"Accounting & Tax Preparation",
            "type":"Services"
        }
    ],
    "sg:phone":"+44 1253 735888",
    "sg:postcode":"FY8 5LU",
    "sg:province":"Lancashire",
    "sg:tags":[
        "accountant",
        "activity"
    ],
    "wof:name":"Latham Lees Costa",
    "wof:placetype":"venue"
},
  "geometry": {"coordinates":[-2.963432,53.738235],"type":"Point"}
}