{
  "type": "Feature",
  "properties": {
    "iso:country":"GB",
    "sg:address":"162-166 Longwood Gardens",
    "sg:city":"Ilford",
    "sg:classifiers":[
        {
            "category":"Shopping",
            "subcategory":"Pharmacy",
            "type":"Retail Goods"
        }
    ],
    "sg:phone":"+44 20 8252 6602",
    "sg:postcode":"IG5 0EW",
    "sg:province":"Essex",
    "sg:tags":[
        "pharmacist",
        "chemist"
    ],
    "wof:name":"H L Rodkoff",
    "wof:placetype":"venue"
},
  "geometry": {"coordinates":[0.068284,51.586784],"type":"Point"}
}