{
  "type": "Feature",
  "properties": {
    "addr:full":"Pioneer Buildings, 65-67 Dale St Liverpool Merseyside L2 2NS",
    "addr:housenumber":"65-67",
    "addr:postcode":"l2 2ns",
    "addr:street":"Dale St",
    "iso:country":"GB",
    "sg:address":"Pioneer Buildings, 65-67 Dale St",
    "sg:city":"Liverpool",
    "sg:classifiers":[
        {
            "category":"Professional",
            "subcategory":"Lawyer & Legal Services",
            "type":"Services"
        }
    ],
    "sg:phone":"+44 151 227 3351",
    "sg:postcode":"L2 2NS",
    "sg:province":"Merseyside",
    "sg:tags":[
        "solicitor"
    ],
    "wof:name":"Bermans  (Contact John Hall)",
    "wof:placetype":"venue"
},
  "geometry": {"coordinates":[-2.98768,53.408298],"type":"Point"}
}