{
  "type": "Feature",
  "properties": {
    "iso:country":"GB",
    "sg:address":"44 Victoria Rd",
    "sg:city":"Burgess Hill",
    "sg:classifiers":[
        {
            "category":"Wholesale",
            "subcategory":"Construction Materials",
            "type":"Manufacturing & Wholesale Goods"
        }
    ],
    "sg:phone":"+44 1444 254404",
    "sg:postcode":"RH15 9LR",
    "sg:province":"East Sussex",
    "sg:tags":[
        "supplier",
        "double",
        "glazing"
    ],
    "wof:name":"Doublequick Supplyline",
    "wof:placetype":"venue"
},
  "geometry": {"coordinates":[-0.140696,50.95393],"type":"Point"}
}