{
  "type": "Feature",
  "properties": {
    "addr:full":"Elm Close Northallerton North Yorkshire DL6 1LY",
    "addr:postcode":"dl6 1ly",
    "addr:street":"Elm Close",
    "iso:country":"GB",
    "sg:address":"Elm Close",
    "sg:city":"Northallerton",
    "sg:classifiers":[
        {
            "category":"Home & Garden",
            "subcategory":"Household Appliances",
            "type":"Retail Goods"
        }
    ],
    "sg:postcode":"DL6 1LY",
    "sg:province":"North Yorkshire",
    "sg:tags":[
        "electrical"
    ],
    "wof:name":"Sparky's",
    "wof:placetype":"venue"
},
  "geometry": {"coordinates":[-1.423729,54.34082],"type":"Point"}
}