{
  "type": "Feature",
  "properties": {
    "iso:country":"GB",
    "sg:address":"121 Lynn Road",
    "sg:city":"Wisbech",
    "sg:classifiers":[
        {
            "category":"Bars & Pubs",
            "type":"Food & Drink"
        }
    ],
    "sg:phone":"+44 1945 584291",
    "sg:postcode":"PE13 3DQ",
    "sg:province":"Cambridgeshire",
    "sg:tags":[
        "pubs",
        "inn"
    ],
    "wof:name":"The Clarkson Arms",
    "wof:placetype":"venue"
},
  "geometry": {"coordinates":[0.167102,52.669476],"type":"Point"}
}