{
  "type": "Feature",
  "properties": {
    "iso:country":"GB",
    "sg:address":"49 Marine Parade, Gorleston",
    "sg:city":"Great Yarmouth",
    "sg:classifiers":[
        {
            "category":"Health Services",
            "subcategory":"Nursing And Care Facility",
            "type":"Services"
        }
    ],
    "sg:phone":"+44 1493 440481",
    "sg:postcode":"NR31 6EX",
    "sg:province":"Norfolk",
    "sg:tags":[
        "home",
        "agency"
    ],
    "wof:name":"Seahorses Investments Ltd.",
    "wof:placetype":"venue"
},
  "geometry": {"coordinates":[1.730445981,52.5629653931],"type":"Point"}
}