{
  "type": "Feature",
  "properties": {
    "iso:country":"GB",
    "sg:address":"5 Wimberley Avenue, North Anston",
    "sg:city":"Sheffield",
    "sg:classifiers":[
        {
            "category":"Building & Trades",
            "subcategory":"Construction",
            "type":"Services"
        }
    ],
    "sg:postcode":"S25 4GZ",
    "sg:province":"South Yorkshire",
    "sg:tags":[
        "decorator",
        "painter"
    ],
    "wof:name":"Martyn Fearnley Painter & Decorator",
    "wof:placetype":"venue"
},
  "geometry": {"coordinates":[-1.214524,53.362122],"type":"Point"}
}