{
  "type": "Feature",
  "properties": {
    "addr:full":"238 Kingston Road New Malden Surrey KT3 3RN",
    "addr:housenumber":"238",
    "addr:postcode":"kt3 3rn",
    "addr:street":"Kingston Road",
    "iso:country":"GB",
    "sg:address":"238 Kingston Road",
    "sg:city":"New Malden",
    "sg:classifiers":[
        {
            "category":"Building & Trades",
            "subcategory":"Construction",
            "type":"Services"
        }
    ],
    "sg:phone":"+44 20 8949 2798",
    "sg:postcode":"KT3 3RN",
    "sg:province":"Surrey",
    "sg:tags":[
        "disposal",
        "waste",
        "unit"
    ],
    "wof:name":"T W T Services Ltd.",
    "wof:placetype":"venue"
},
  "geometry": {"coordinates":[-0.273918,51.403156],"type":"Point"}
}