{
  "type": "Feature",
  "properties": {
    "iso:country":"GB",
    "sg:address":"123 High St, Coleshill",
    "sg:city":"Birmingham",
    "sg:classifiers":[
        {
            "category":"Freight",
            "type":"Transportation"
        }
    ],
    "sg:phone":"+44 1675 462118",
    "sg:postcode":"B46 3BT",
    "sg:province":"Warwickshire",
    "sg:tags":[
        "haulage",
        "road"
    ],
    "wof:name":"Royal Mail",
    "wof:placetype":"venue"
},
  "geometry": {"coordinates":[-1.705905,52.498074],"type":"Point"}
}