{
  "type": "Feature",
  "properties": {
    "iso:country":"GB",
    "sg:address":"126-128 Heaton Road",
    "sg:city":"Newcastle-upon-tyne",
    "sg:classifiers":[
        {
            "category":"Building & Trades",
            "subcategory":"Construction",
            "type":"Services"
        }
    ],
    "sg:phone":"+44 191 265 2123",
    "sg:postcode":"NE6 5HN",
    "sg:province":"Tyne and Wear",
    "sg:tags":[
        "roofing",
        "contracting"
    ],
    "wof:name":"Thomas Headley & Sons",
    "wof:placetype":"venue"
},
  "geometry": {"coordinates":[-1.581252,54.981964],"type":"Point"}
}