{
  "type": "Feature",
  "properties": {
    "addr:full":"6 Belsay Av Whitley Bay Northumberland NE25 8PZ",
    "addr:housenumber":"6",
    "addr:postcode":"ne25 8pz",
    "addr:street":"Belsay Av",
    "iso:country":"GB",
    "sg:address":"6 Belsay Av",
    "sg:city":"Whitley Bay",
    "sg:classifiers":[
        {
            "category":"Organizations",
            "subcategory":"Religious Organization",
            "type":"Services"
        }
    ],
    "sg:phone":"+44 191 251 9775",
    "sg:postcode":"NE25 8PZ",
    "sg:province":"Northumberland",
    "sg:tags":[
        "organisation"
    ],
    "wof:name":"Baha'i Faith",
    "wof:placetype":"venue"
},
  "geometry": {"coordinates":[-1.4398260117,55.0381851196],"type":"Point"}
}