{
  "type": "Feature",
  "properties": {
    "addr:full":"Barteliver Farm, Grampound Truro Cornwall TR2 4DE",
    "addr:postcode":"tr2 4de",
    "iso:country":"GB",
    "sg:address":"Barteliver Farm, Grampound",
    "sg:city":"Truro",
    "sg:classifiers":[
        {
            "category":"Farming",
            "subcategory":"Farm",
            "type":"Manufacturing & Wholesale Goods"
        }
    ],
    "sg:phone":"+44 1726 882410",
    "sg:postcode":"TR2 4DE",
    "sg:province":"Cornwall",
    "sg:tags":[
        "mixed",
        "crop"
    ],
    "wof:name":"J R C James",
    "wof:placetype":"venue"
},
  "geometry": {"coordinates":[-4.899034,50.298214],"type":"Point"}
}