{
  "type": "Feature",
  "properties": {
    "iso:country":"GB",
    "sg:address":"1 Birch Road",
    "sg:city":"Ellesmere",
    "sg:classifiers":[
        {
            "category":"Fast Food",
            "type":"Food & Drink"
        }
    ],
    "sg:phone":"+44 1691 623689",
    "sg:postcode":"SY12 0ET",
    "sg:province":"Shropshire",
    "sg:tags":[
        "away",
        "take"
    ],
    "wof:name":"The Curry Pot",
    "wof:placetype":"venue"
},
  "geometry": {"coordinates":[-2.892415,52.906982],"type":"Point"}
}