{
  "type": "Feature",
  "properties": {
    "iso:country":"GB",
    "sg:address":"The Surgeries, Fairwater Square",
    "sg:city":"Cwmbran",
    "sg:classifiers":[
        {
            "category":"Health Services",
            "subcategory":"Dentist",
            "type":"Services"
        }
    ],
    "sg:phone":"+44 1633 865056",
    "sg:postcode":"NP44 4TA",
    "sg:province":"Monmouthshire",
    "wof:name":"Gwent Healthcare N H S Trust",
    "wof:placetype":"venue"
},
  "geometry": {"coordinates":[-3.025864,51.657467],"type":"Point"}
}