{
  "type": "Feature",
  "properties": {
    "iso:country":"GB",
    "sg:address":"Woden House, Market Place",
    "sg:city":"Wednesbury",
    "sg:classifiers":[
        {
            "category":"Professional",
            "subcategory":"Employment Agencies",
            "type":"Services"
        }
    ],
    "sg:phone":"+44 121 480 3000",
    "sg:postcode":"WS10 7AG",
    "sg:province":"West Midlands",
    "sg:tags":[
        "consultant"
    ],
    "wof:name":"Wednesbury Jobcentre",
    "wof:placetype":"venue"
},
  "geometry": {"coordinates":[-2.018984,52.552509],"type":"Point"}
}