{
  "type": "Feature",
  "properties": {
    "iso:country":"GB",
    "sg:address":"249 High Street",
    "sg:city":"Bangor",
    "sg:classifiers":[
        {
            "category":"Communications",
            "type":"Services"
        }
    ],
    "sg:postcode":"LL57 1PA",
    "sg:province":"Gwynedd",
    "sg:tags":[
        "telecommunication"
    ],
    "wof:name":"The Phone People Plc",
    "wof:placetype":"venue"
},
  "geometry": {"coordinates":[-4.1145119667,53.2309417725],"type":"Point"}
}