{
  "type": "Feature",
  "properties": {
    "iso:country":"GB",
    "sg:address":"56 Albert Road",
    "sg:city":"Ashford",
    "sg:classifiers":[
        {
            "category":"Professional",
            "subcategory":"Management & Consulting",
            "type":"Services"
        }
    ],
    "sg:phone":"+44 1422 207574",
    "sg:postcode":"TN24 8NU",
    "sg:province":"Kent",
    "sg:tags":[
        "consultant",
        "training"
    ],
    "wof:name":"Irm Training Ltd.",
    "wof:placetype":"venue"
},
  "geometry": {"coordinates":[0.869892,51.152637],"type":"Point"}
}