{
  "type": "Feature",
  "properties": {
    "iso:country":"GB",
    "sg:address":"Cairngorm Gate, Winterhill",
    "sg:city":"Milton Keynes",
    "sg:classifiers":[
        {
            "category":"Home & Garden",
            "subcategory":"Furniture",
            "type":"Retail Goods"
        }
    ],
    "sg:phone":"+44 1908 676737",
    "sg:postcode":"MK6 1AZ",
    "sg:province":"Buckinghamshire",
    "wof:name":"Dreams",
    "wof:placetype":"venue"
},
  "geometry": {"coordinates":[-0.764069,52.030193],"type":"Point"}
}