{
  "type": "Feature",
  "properties": {
    "iso:country":"GB",
    "sg:address":"12 Glanydon Industrial Estate",
    "sg:city":"Pwllheli",
    "sg:classifiers":[
        {
            "category":"Wholesale",
            "subcategory":"Electrical",
            "type":"Manufacturing & Wholesale Goods"
        },
        {
            "category":"Shopping",
            "subcategory":"Computers & Home Electronics",
            "type":"Retail Goods"
        }
    ],
    "sg:phone":"+44 1758 701401",
    "sg:postcode":"LL53 5YT",
    "sg:province":"Gwynedd",
    "sg:tags":[
        "wholesaler"
    ],
    "wof:name":"Round Deakin Electrical",
    "wof:placetype":"venue"
},
  "geometry": {"coordinates":[-4.4059000015,52.8896026611],"type":"Point"}
}