{
  "type": "Feature",
  "properties": {
    "addr:full":"222 Wellington Road North, Heaton Chapel Stockport Cheshire SK4 2QN",
    "addr:housenumber":"222",
    "addr:postcode":"sk4 2qn",
    "addr:street":"Wellington Road North",
    "iso:country":"GB",
    "sg:address":"222 Wellington Road North, Heaton Chapel",
    "sg:city":"Stockport",
    "sg:classifiers":[
        {
            "category":"Place Of Worship",
            "type":"Public Place"
        }
    ],
    "sg:phone":"+44 161 432 5604",
    "sg:postcode":"SK4 2QN",
    "sg:province":"Cheshire",
    "wof:name":"Heaton Chapel Christian Church",
    "wof:placetype":"venue"
},
  "geometry": {"coordinates":[-2.172437,53.421158],"type":"Point"}
}