{
  "type": "Feature",
  "properties": {
    "addr:full":"West Gate, Humber Road, Immingham Dock Grimsby Lincolnshire DN40 2QX",
    "addr:postcode":"dn40 2qx",
    "addr:street":"West Gate Humber Road;Dock Grimsby",
    "iso:country":"GB",
    "sg:address":"West Gate, Humber Road, Immingham Dock",
    "sg:city":"Grimsby",
    "sg:classifiers":[
        {
            "category":"Retail",
            "subcategory":"Storage",
            "type":"Services"
        }
    ],
    "sg:phone":"+44 1469 578336",
    "sg:postcode":"DN40 2QX",
    "sg:province":"Lincolnshire",
    "sg:tags":[
        "household",
        "removal"
    ],
    "wof:name":"Grosvenor Grain & Co",
    "wof:placetype":"venue"
},
  "geometry": {"coordinates":[-0.2289270014,53.633731842],"type":"Point"}
}