{
  "type": "Feature",
  "properties": {
    "addr:full":"Church St, Woodhurst Huntingdon Bedfordshire PE28 3BN",
    "addr:postcode":"pe28 3bn",
    "addr:street":"Church St",
    "iso:country":"GB",
    "sg:address":"Church St, Woodhurst",
    "sg:city":"Huntingdon",
    "sg:classifiers":[
        {
            "category":"Shopping",
            "subcategory":"Catalog Store",
            "type":"Retail Goods"
        }
    ],
    "sg:postcode":"PE28 3BN",
    "sg:province":"Bedfordshire",
    "sg:tags":[
        "mail",
        "order"
    ],
    "wof:name":"Polhill,A,",
    "wof:placetype":"venue"
},
  "geometry": {"coordinates":[-0.0700900033,52.3670425415],"type":"Point"}
}