{
  "type": "Feature",
  "properties": {
    "iso:country":"GB",
    "sg:address":"78 Main St",
    "sg:city":"Keswick",
    "sg:classifiers":[
        {
            "category":"Shopping",
            "subcategory":"Gifts & Souvenirs",
            "type":"Retail Goods"
        }
    ],
    "sg:phone":"+44 17687 73655",
    "sg:postcode":"CA12 5DX",
    "sg:province":"Cumbria",
    "sg:tags":[
        "shop"
    ],
    "wof:name":"Papillon",
    "wof:placetype":"venue"
},
  "geometry": {"coordinates":[-3.139911,54.602234],"type":"Point"}
}