{
  "type": "Feature",
  "properties": {
    "iso:country":"GB",
    "sg:address":"Stretton Ave",
    "sg:city":"Coventry",
    "sg:classifiers":[
        {
            "category":"Education",
            "subcategory":"Preschool",
            "type":"Public Place"
        }
    ],
    "sg:postcode":"CV3 3AH",
    "sg:province":"Warwickshire",
    "sg:tags":[
        "pre-school",
        "playgroups"
    ],
    "wof:name":"Spurgeons Family Centre",
    "wof:placetype":"venue"
},
  "geometry": {"coordinates":[-1.4654599428,52.3882102966],"type":"Point"}
}