{
  "type": "Feature",
  "properties": {
    "iso:country":"GB",
    "sg:address":"Tamworth Town Stadium, Marlborough Way, Glascote",
    "sg:city":"Tamworth",
    "sg:classifiers":[
        {
            "category":"Arena",
            "subcategory":"Sports Club",
            "type":"Entertainment"
        }
    ],
    "sg:phone":"+44 1827 260897",
    "sg:postcode":"B77 2HA",
    "sg:province":"Staffordshire",
    "wof:name":"Tamworth Athletic Club",
    "wof:placetype":"venue"
},
  "geometry": {"coordinates":[-1.6619540453,52.6247711182],"type":"Point"}
}