{
  "type": "Feature",
  "properties": {
    "iso:country":"GB",
    "sg:address":"54 Hurdsfield Road",
    "sg:city":"Macclesfield",
    "sg:classifiers":[
        {
            "category":"Building & Trades",
            "subcategory":"Construction",
            "type":"Services"
        }
    ],
    "sg:postcode":"SK10 2QJ",
    "sg:province":"Cheshire",
    "sg:tags":[
        "builder"
    ],
    "wof:name":"B J Mannion",
    "wof:placetype":"venue"
},
  "geometry": {"coordinates":[-2.119426,53.263435],"type":"Point"}
}