{
  "type": "Feature",
  "properties": {
    "addr:full":"5 Hill View York East Riding of Yorkshire YO5 9BE",
    "addr:housenumber":"5",
    "addr:postcode":"yo5 9be",
    "addr:street":"Hill View",
    "iso:country":"GB",
    "sg:address":"5 Hill View",
    "sg:city":"York",
    "sg:classifiers":[
        {
            "category":"Museum",
            "subcategory":"Zoo",
            "type":"Entertainment"
        }
    ],
    "sg:phone":"+44 1423 323679",
    "sg:postcode":"YO5 9BE",
    "sg:province":"East Riding of Yorkshire",
    "sg:tags":[
        "cat"
    ],
    "wof:name":"Portrait Persians",
    "wof:placetype":"venue"
},
  "geometry": {"coordinates":[-1.4049069881,54.1055870056],"type":"Point"}
}