{
  "type": "Feature",
  "properties": {
    "addr:full":"2a Bellevue Road, Friern Barnet London Greater London N11 3ER",
    "addr:housenumber":"2a",
    "addr:postcode":"n11 3er",
    "addr:street":"Bellevue Road",
    "iso:country":"GB",
    "sg:address":"2a Bellevue Road, Friern Barnet",
    "sg:city":"London",
    "sg:classifiers":[
        {
            "category":"Professional",
            "subcategory":"Detective & Security Services",
            "type":"Services"
        },
        {
            "category":"Shopping",
            "subcategory":"Computers & Home Electronics",
            "type":"Retail Goods"
        }
    ],
    "sg:phone":"+44 20 8368 7887",
    "sg:postcode":"N11 3ER",
    "sg:province":"Greater London",
    "sg:tags":[
        "equipment",
        "video",
        "cctv"
    ],
    "wof:name":"Luminite Electronics Ltd.",
    "wof:placetype":"venue"
},
  "geometry": {"coordinates":[-0.1588090062,51.6130027771],"type":"Point"}
}