{
  "type": "Feature",
  "properties": {
    "addr:full":"Hambrook Hall, Cheesemans Lane, Hambrook Chichester West Sussex PO18 8UE",
    "addr:postcode":"po18 8ue",
    "addr:street":"Cheesemans Lane",
    "iso:country":"GB",
    "sg:address":"Hambrook Hall, Cheesemans Lane, Hambrook",
    "sg:city":"Chichester",
    "sg:classifiers":[
        {
            "category":"Professional",
            "subcategory":"Computer Services",
            "type":"Services"
        }
    ],
    "sg:phone":"+44 1243 573920",
    "sg:postcode":"PO18 8UE",
    "sg:province":"West Sussex",
    "sg:tags":[
        "system",
        "software"
    ],
    "wof:name":"Beach Compix (Holdings) Ltd.",
    "wof:placetype":"venue"
},
  "geometry": {"coordinates":[-0.88295,50.856594],"type":"Point"}
}