{
  "type": "Feature",
  "properties": {
    "addr:full":"Cottage Lane Wirral Merseyside CH60 8PB",
    "addr:postcode":"ch60 8pb",
    "addr:street":"Cottage Lane",
    "iso:country":"GB",
    "sg:address":"Cottage Lane",
    "sg:city":"Wirral",
    "sg:classifiers":[
        {
            "category":"Sports & Exercise",
            "subcategory":"Golf",
            "type":"Entertainment"
        }
    ],
    "sg:phone":"+44 151 342 1237",
    "sg:postcode":"CH60 8PB",
    "sg:province":"Merseyside",
    "sg:tags":[
        "club",
        "course"
    ],
    "wof:name":"Heswall Golf Club",
    "wof:placetype":"venue"
},
  "geometry": {"coordinates":[-3.099064,53.315006],"type":"Point"}
}