{
  "type": "Feature",
  "properties": {
    "iso:country":"GB",
    "sg:address":"108 Yardley Rd",
    "sg:city":"Birmingham",
    "sg:classifiers":[
        {
            "category":"Home & Garden",
            "subcategory":"Furniture",
            "type":"Retail Goods"
        }
    ],
    "sg:phone":"+44 121 628 4300",
    "sg:postcode":"B27 6LG",
    "sg:province":"West Midlands",
    "wof:name":"Pinecraft",
    "wof:placetype":"venue"
},
  "geometry": {"coordinates":[-1.818033,52.452644],"type":"Point"}
}