{
  "type": "Feature",
  "properties": {
    "addr:full":"Burton Medical Centre, 123 Salisbury Rd Christchurch Dorset BH23 7JN",
    "addr:housenumber":"123",
    "addr:postcode":"bh23 7jn",
    "addr:street":"Salisbury Rd",
    "iso:country":"GB",
    "sg:address":"Burton Medical Centre, 123 Salisbury Rd",
    "sg:city":"Christchurch",
    "sg:classifiers":[
        {
            "category":"Health Services",
            "subcategory":"Doctor",
            "type":"Services"
        }
    ],
    "sg:phone":"+44 1202 474311",
    "sg:postcode":"BH23 7JN",
    "sg:province":"Dorset",
    "sg:tags":[
        "practitioners"
    ],
    "wof:name":"Longley, A",
    "wof:placetype":"venue"
},
  "geometry": {"coordinates":[-1.776564,50.73407],"type":"Point"}
}