{
  "type": "Feature",
  "properties": {
    "iso:country":"GB",
    "sg:address":"190 Rye Lane",
    "sg:city":"London",
    "sg:classifiers":[
        {
            "category":"Building & Trades",
            "subcategory":"Construction",
            "type":"Services"
        }
    ],
    "sg:phone":"+44 20 7252 8787",
    "sg:postcode":"SE15 4NF",
    "sg:province":"Greater London",
    "sg:tags":[
        "demolition",
        "contractor"
    ],
    "wof:name":"Christmas Demolition Ltd.",
    "wof:placetype":"venue"
},
  "geometry": {"coordinates":[-0.067048,51.467556],"type":"Point"}
}