{
  "type": "Feature",
  "properties": {
    "iso:country":"GB",
    "sg:address":"221 Chesterfield Road South",
    "sg:city":"Mansfield",
    "sg:classifiers":[
        {
            "category":"Fast Food",
            "type":"Food & Drink"
        }
    ],
    "sg:postcode":"NG19 7EQ",
    "sg:province":"Derbyshire",
    "sg:tags":[
        "away",
        "take"
    ],
    "wof:name":"New Sunmo",
    "wof:placetype":"venue"
},
  "geometry": {"coordinates":[-1.20971,53.154503],"type":"Point"}
}