{
  "type": "Feature",
  "properties": {
    "addr:full":"35a Corberhill Road Edinburgh City of Edinburgh EH4 5AT",
    "addr:housenumber":"35a",
    "addr:postcode":"eh4 5at",
    "addr:street":"Corberhill Road",
    "iso:country":"GB",
    "sg:address":"35a Corberhill Road",
    "sg:city":"Edinburgh",
    "sg:classifiers":[
        {
            "category":"Building & Trades",
            "subcategory":"Construction",
            "type":"Services"
        }
    ],
    "sg:phone":"+44 131 538 7540",
    "sg:postcode":"EH4 5AT",
    "sg:province":"City of Edinburgh",
    "sg:tags":[
        "joiner",
        "carpenter"
    ],
    "wof:name":"D & S Joiners & Builders",
    "wof:placetype":"venue"
},
  "geometry": {"coordinates":[-3.2689919472,55.9649200439],"type":"Point"}
}