{
  "type": "Feature",
  "properties": {
    "addr:full":"27 Church Street Ilkley North Yorkshire LS29 9DR",
    "addr:housenumber":"27",
    "addr:postcode":"ls29 9dr",
    "addr:street":"Church Street",
    "iso:country":"GB",
    "sg:address":"27 Church Street",
    "sg:city":"Ilkley",
    "sg:classifiers":[
        {
            "category":"Shopping",
            "subcategory":"Clothing, Apparel, & Fashions",
            "type":"Retail Goods"
        }
    ],
    "sg:phone":"+44 1943 600133",
    "sg:postcode":"LS29 9DR",
    "sg:province":"North Yorkshire",
    "sg:tags":[
        "menswear"
    ],
    "wof:name":"Eric Spencer Countrywear",
    "wof:placetype":"venue"
},
  "geometry": {"coordinates":[-1.8246389627,53.9261322021],"type":"Point"}
}