{
  "type": "Feature",
  "properties": {
    "iso:country":"GB",
    "sg:address":"Hillside Grange, Sunderland Rd",
    "sg:city":"Gateshead",
    "sg:classifiers":[
        {
            "category":"Health Services",
            "subcategory":"Nursing And Care Facility",
            "type":"Services"
        }
    ],
    "sg:phone":"+44 191 438 6000",
    "sg:postcode":"NE10 0BU",
    "sg:province":"Tyne and Wear",
    "sg:tags":[
        "home"
    ],
    "wof:name":"Golcere Ltd",
    "wof:placetype":"venue"
},
  "geometry": {"coordinates":[-1.57611,54.9534],"type":"Point"}
}