{
  "type": "Feature",
  "properties": {
    "addr:full":"7 Bushbys Park, Formby Liverpool Lancashire L37 2EE",
    "addr:housenumber":"7",
    "addr:postcode":"l37 2ee",
    "addr:street":"Bushbys Park",
    "iso:country":"GB",
    "sg:address":"7 Bushbys Park, Formby",
    "sg:city":"Liverpool",
    "sg:classifiers":[
        {
            "category":"Shopping",
            "subcategory":"Pets & Pet Supplies",
            "type":"Retail Goods"
        }
    ],
    "sg:phone":"+44 1704 878922",
    "sg:postcode":"L37 2EE",
    "sg:province":"Lancashire",
    "wof:name":"Trophy Pet Foods",
    "wof:placetype":"venue"
},
  "geometry": {"coordinates":[-3.07938,53.551842],"type":"Point"}
}