{
  "type": "Feature",
  "properties": {
    "addr:full":"Room 24 Routemaster Building, Walton Av Felixstowe Suffolk IP11 8HE",
    "addr:housenumber":"24;building",
    "addr:postcode":"ip11 8he",
    "addr:street":"Walton Av",
    "iso:country":"GB",
    "sg:address":"Room 24 Routemaster Building, Walton Av",
    "sg:city":"Felixstowe",
    "sg:classifiers":[
        {
            "category":"Military Area",
            "subcategory":"Air Force Base",
            "type":"Public Place"
        }
    ],
    "sg:phone":"+44 1394 678888",
    "sg:postcode":"IP11 8HE",
    "sg:province":"Suffolk",
    "sg:tags":[
        "taxi",
        "hire",
        "private"
    ],
    "wof:name":"A A A Taxis",
    "wof:placetype":"venue"
},
  "geometry": {"coordinates":[1.342465,51.961369],"type":"Point"}
}