{
  "type": "Feature",
  "properties": {
    "addr:full":"115 Penshurst Road Ipswich Suffolk IP3 8QB",
    "addr:housenumber":"115",
    "addr:postcode":"ip3 8qb",
    "addr:street":"Penshurst Road",
    "iso:country":"GB",
    "sg:address":"115 Penshurst Road",
    "sg:city":"Ipswich",
    "sg:classifiers":[
        {
            "category":"Sports & Exercise",
            "subcategory":"Gym",
            "type":"Entertainment"
        }
    ],
    "sg:phone":"+44 1473 724196",
    "sg:postcode":"IP3 8QB",
    "sg:province":"Suffolk",
    "sg:tags":[
        "club",
        "fitness",
        "health",
        "centre"
    ],
    "wof:name":"Helsinki Health Centre",
    "wof:placetype":"venue"
},
  "geometry": {"coordinates":[1.204761982,52.0456390381],"type":"Point"}
}