{
  "type": "Feature",
  "properties": {
    "iso:country":"GB",
    "sg:address":"4 Beaumont Gro",
    "sg:city":"Aldershot",
    "sg:classifiers":[
        {
            "category":"Shopping",
            "subcategory":"Computers & Home Electronics",
            "type":"Retail Goods"
        }
    ],
    "sg:phone":"+44 1252 319228",
    "sg:postcode":"GU11 1UH",
    "sg:province":"Hampshire",
    "sg:tags":[
        "electrical"
    ],
    "wof:name":"Matthew Woolly",
    "wof:placetype":"venue"
},
  "geometry": {"coordinates":[-0.7780140042,51.2487564087],"type":"Point"}
}