{
  "type": "Feature",
  "properties": {
    "iso:country":"GB",
    "sg:address":"The Ridings",
    "sg:city":"Birkenhead",
    "sg:classifiers":[
        {
            "category":"Education",
            "subcategory":"School",
            "type":"Public Place"
        }
    ],
    "sg:phone":"+44 151 677 9960",
    "sg:postcode":"L43 9XZ",
    "sg:province":"Merseyside",
    "sg:tags":[
        "local",
        "authority"
    ],
    "wof:name":"Hillside Junior School",
    "wof:placetype":"venue"
},
  "geometry": {"coordinates":[-3.0751109123,53.3866271973],"type":"Point"}
}