{
  "type": "Feature",
  "properties": {
    "addr:full":"Westwood Road Leek Staffordshire ST13 8DN",
    "addr:postcode":"st13 8dn",
    "addr:street":"Westwood Road",
    "iso:country":"GB",
    "sg:address":"Westwood Road",
    "sg:city":"Leek",
    "sg:classifiers":[
        {
            "category":"Education",
            "subcategory":"School",
            "type":"Public Place"
        },
        {
            "category":"Government",
            "subcategory":"Office",
            "type":"Public Place"
        }
    ],
    "sg:phone":"+44 1538 483218",
    "sg:postcode":"ST13 8DN",
    "sg:province":"Staffordshire",
    "sg:tags":[
        "local",
        "authority"
    ],
    "wof:name":"St Edwards C of E (Aided) Middle School",
    "wof:placetype":"venue"
},
  "geometry": {"coordinates":[-2.0329139233,53.1061515808],"type":"Point"}
}