{
  "type": "Feature",
  "properties": {
    "iso:country":"GB",
    "sg:address":"100-102 Station Lane",
    "sg:city":"Pontefract",
    "sg:classifiers":[
        {
            "category":"Shopping",
            "subcategory":"Party Supplies",
            "type":"Retail Goods"
        },
        {
            "category":"Arts & Performance",
            "subcategory":"Music",
            "type":"Entertainment"
        }
    ],
    "sg:phone":"+44 1977 793222",
    "sg:postcode":"WF7 5BA",
    "sg:province":"West Yorkshire",
    "sg:tags":[
        "mobile",
        "equipment",
        "disco"
    ],
    "wof:name":"Tony Sykes Sound Ltd.",
    "wof:placetype":"venue"
},
  "geometry": {"coordinates":[-1.358224,53.678391],"type":"Point"}
}