{
  "type": "Feature",
  "properties": {
    "addr:full":"14 Chamberlayne Road London Greater London NW10 3NA",
    "addr:housenumber":"14",
    "addr:postcode":"nw10 3na",
    "addr:street":"Chamberlayne Road",
    "iso:country":"GB",
    "sg:address":"14 Chamberlayne Road",
    "sg:city":"London",
    "sg:classifiers":[
        {
            "category":"Shopping",
            "subcategory":"Florist",
            "type":"Retail Goods"
        }
    ],
    "sg:phone":"+44 20 8969 8133",
    "sg:postcode":"NW10 3NA",
    "sg:province":"Greater London",
    "wof:name":"Four Seasons",
    "wof:placetype":"venue"
},
  "geometry": {"coordinates":[-0.216414,51.530247],"type":"Point"}
}