{
  "type": "Feature",
  "properties": {
    "iso:country":"GB",
    "sg:address":"25 Dudley Road",
    "sg:city":"Clacton-on-sea",
    "sg:classifiers":[
        {
            "category":"Professional",
            "subcategory":"Advertising",
            "type":"Services"
        }
    ],
    "sg:phone":"+44 1255 431712",
    "sg:postcode":"CO15 3DN",
    "sg:province":"Essex",
    "sg:tags":[
        "outdoor",
        "agency"
    ],
    "wof:name":"Classic Sites Ltd.",
    "wof:placetype":"venue"
},
  "geometry": {"coordinates":[1.143677,51.794449],"type":"Point"}
}