{
  "type": "Feature",
  "properties": {
    "addr:full":"Po Box 26 Leicester Leicestershire LE1 1AA",
    "addr:housenumber":"po box 26",
    "addr:postcode":"le1 1aa",
    "iso:country":"GB",
    "sg:address":"Po Box 26",
    "sg:city":"Leicester",
    "sg:classifiers":[
        {
            "category":"Organizations",
            "subcategory":"Non-profit Organization",
            "type":"Services"
        }
    ],
    "sg:phone":"+44 116 244 0169",
    "sg:postcode":"LE1 1AA",
    "sg:province":"Leicestershire",
    "sg:tags":[
        "organisation",
        "voluntary",
        "charity"
    ],
    "wof:name":"Womens Aid Leicestershire",
    "wof:placetype":"venue"
},
  "geometry": {"coordinates":[-1.1403650045,52.6378860474],"type":"Point"}
}