{
  "type": "Feature",
  "properties": {
    "iso:country":"GB",
    "sg:address":"Shop 2, New Market Hall",
    "sg:city":"Warrington",
    "sg:classifiers":[
        {
            "category":"Food & Beverages",
            "subcategory":"Meat & Fish",
            "type":"Retail Goods"
        }
    ],
    "sg:phone":"+44 1925 634748",
    "sg:postcode":"WA1 2EN",
    "sg:province":"Cheshire",
    "sg:tags":[
        "butcher"
    ],
    "wof:name":"Heath Butchers",
    "wof:placetype":"venue"
},
  "geometry": {"coordinates":[-2.59178,53.38802],"type":"Point"}
}