{
  "type": "Feature",
  "properties": {
    "iso:country":"GB",
    "sg:address":"21 Barlow Moor Road, Didsbury",
    "sg:city":"Manchester",
    "sg:classifiers":[
        {
            "category":"Shopping",
            "subcategory":"News",
            "type":"Retail Goods"
        }
    ],
    "sg:phone":"+44 161 445 3679",
    "sg:postcode":"M20 6TN",
    "sg:province":"Greater Manchester",
    "sg:tags":[
        "newsagent"
    ],
    "wof:name":"Chiny News",
    "wof:placetype":"venue"
},
  "geometry": {"coordinates":[-2.2328350544,53.4178886414],"type":"Point"}
}