{
  "type": "Feature",
  "properties": {
    "iso:country":"GB",
    "sg:address":"Tyr Y Berth Industrial Estate, Tyr Y Berth",
    "sg:city":"Hengoed",
    "sg:classifiers":[
        {
            "category":"Autos & Motor Vehicles",
            "subcategory":"Auto Supplies",
            "type":"Retail Goods"
        }
    ],
    "sg:phone":"+44 1443 813670",
    "sg:postcode":"CF82 8AU",
    "sg:province":"Caerphilly",
    "sg:tags":[
        "tyre"
    ],
    "wof:name":"Alkod Trade International U K Ltd.",
    "wof:placetype":"venue"
},
  "geometry": {"coordinates":[-3.231799,51.648319],"type":"Point"}
}