{
  "type": "Feature",
  "properties": {
    "addr:full":"Station App Bexleyheath Kent DA7 4QP",
    "addr:postcode":"da7 4qp",
    "iso:country":"GB",
    "sg:address":"Station App",
    "sg:city":"Bexleyheath",
    "sg:classifiers":[
        {
            "category":"Professional",
            "subcategory":"Detective & Security Services",
            "type":"Services"
        }
    ],
    "sg:postcode":"DA7 4QP",
    "sg:province":"Kent",
    "sg:tags":[
        "locksmith"
    ],
    "wof:name":"P Rogers",
    "wof:placetype":"venue"
},
  "geometry": {"coordinates":[0.138045,51.460136],"type":"Point"}
}