{
  "type": "Feature",
  "properties": {
    "addr:full":"470-472 Bowes Road, New Southgate London Greater London N11 1NL",
    "addr:housenumber":"470-472",
    "addr:postcode":"n11 1nl",
    "addr:street":"Bowes Road",
    "iso:country":"GB",
    "sg:address":"470-472 Bowes Road, New Southgate",
    "sg:city":"London",
    "sg:classifiers":[
        {
            "category":"Autos & Motor Vehicles",
            "subcategory":"Automobile Sales",
            "type":"Retail Goods"
        }
    ],
    "sg:phone":"+44 20 8372 3121",
    "sg:postcode":"N11 1NL",
    "sg:province":"Greater London",
    "sg:tags":[
        "car"
    ],
    "wof:name":"Penridge Cars Ltd.",
    "wof:placetype":"venue"
},
  "geometry": {"coordinates":[-0.1405979991,51.6168632507],"type":"Point"}
}