{
  "type": "Feature",
  "properties": {
    "addr:full":"20 Crabble Road, River Dover Kent CT17 0QE",
    "addr:housenumber":"20",
    "addr:postcode":"ct17 0qe",
    "addr:street":"Crabble Road",
    "iso:country":"GB",
    "sg:address":"20 Crabble Road, River",
    "sg:city":"Dover",
    "sg:classifiers":[
        {
            "category":"Building & Trades",
            "subcategory":"Construction",
            "type":"Services"
        }
    ],
    "sg:postcode":"CT17 0QE",
    "sg:province":"Kent",
    "sg:tags":[
        "builder"
    ],
    "wof:name":"Valiant Builders Ltd",
    "wof:placetype":"venue"
},
  "geometry": {"coordinates":[1.2862670422,51.1396827698],"type":"Point"}
}