{
  "type": "Feature",
  "properties": {
    "addr:full":"Idless Truro Cornwall TR4 9QT",
    "addr:postcode":"tr4 9qt",
    "addr:street":"Idless",
    "iso:country":"GB",
    "sg:address":"Idless",
    "sg:city":"Truro",
    "sg:classifiers":[
        {
            "category":"Building & Trades",
            "subcategory":"Landscaping Services",
            "type":"Services"
        }
    ],
    "sg:phone":"+44 1872 271619",
    "sg:postcode":"TR4 9QT",
    "sg:province":"Cornwall",
    "sg:tags":[
        "gardening"
    ],
    "wof:name":"The Orchard Barn",
    "wof:placetype":"venue"
},
  "geometry": {"coordinates":[-5.0632200241,50.2899703979],"type":"Point"}
}