{
  "type": "Feature",
  "properties": {
    "iso:country":"GB",
    "sg:address":"The Runway, South Ruislip",
    "sg:city":"Ruislip",
    "sg:classifiers":[
        {
            "category":"Real Estate",
            "subcategory":"Architect",
            "type":"Services"
        }
    ],
    "sg:postcode":"HA4 6SJ",
    "sg:province":"Greater London",
    "sg:tags":[
        "architectural"
    ],
    "wof:name":"Architectural Advisory Service Centre",
    "wof:placetype":"venue"
},
  "geometry": {"coordinates":[-0.407864,51.557594],"type":"Point"}
}