{
  "type": "Feature",
  "properties": {
    "iso:country":"GB",
    "sg:address":"Jubilee Garage",
    "sg:city":"London",
    "sg:classifiers":[
        {
            "category":"Retail",
            "subcategory":"Auto Repair",
            "type":"Services"
        }
    ],
    "sg:postcode":"CW4 7BG",
    "sg:province":"Cheshire",
    "sg:tags":[
        "modification",
        "garage"
    ],
    "wof:name":"S & R Motor Services Ltd",
    "wof:placetype":"venue"
},
  "geometry": {"coordinates":[-2.356254,53.199566],"type":"Point"}
}