{
  "type": "Feature",
  "properties": {
    "addr:full":"Wickford Avenue Basildon Essex SS13 3HT",
    "addr:postcode":"ss13 3ht",
    "addr:street":"Wickford Avenue",
    "iso:country":"GB",
    "sg:address":"Wickford Avenue",
    "sg:city":"Basildon",
    "sg:classifiers":[
        {
            "category":"Social Services",
            "subcategory":"Adult Care",
            "type":"Services"
        },
        {
            "category":"Government",
            "subcategory":"Office",
            "type":"Public Place"
        }
    ],
    "sg:phone":"+44 1268 583021",
    "sg:postcode":"SS13 3HT",
    "sg:province":"Essex",
    "sg:tags":[
        "housing",
        "local",
        "sheltered"
    ],
    "wof:name":"Oakwood Grove Sheltered Housing",
    "wof:placetype":"venue"
},
  "geometry": {"coordinates":[0.5093899965,51.5679283142],"type":"Point"}
}