{
  "type": "Feature",
  "properties": {
    "addr:full":"526 Kilmarnock Road Glasgow Glasgow City G43 2BL",
    "addr:housenumber":"526",
    "addr:postcode":"g43 2bl",
    "addr:street":"Kilmarnock Road",
    "iso:country":"GB",
    "sg:address":"526 Kilmarnock Road",
    "sg:city":"Glasgow",
    "sg:classifiers":[
        {
            "category":"Fast Food",
            "type":"Food & Drink"
        }
    ],
    "sg:phone":"+44 141 637 0887",
    "sg:postcode":"G43 2BL",
    "sg:province":"Glasgow City",
    "sg:tags":[
        "away",
        "meal",
        "outlet",
        "take"
    ],
    "wof:name":"Sun Hei",
    "wof:placetype":"venue"
},
  "geometry": {"coordinates":[-4.2912511826,55.8140335083],"type":"Point"}
}