{
  "type": "Feature",
  "properties": {
    "iso:country":"GB",
    "sg:address":"19-20 Tudor Square",
    "sg:city":"Dalton-in-furness",
    "sg:classifiers":[
        {
            "category":"Professional",
            "type":"Services"
        }
    ],
    "sg:postcode":"LA15 8RH",
    "sg:province":"Cumbria",
    "sg:tags":[
        "caterer"
    ],
    "wof:name":"The Loft Restaurant",
    "wof:placetype":"venue"
},
  "geometry": {"coordinates":[-3.181139,54.156364],"type":"Point"}
}