{
  "type": "Feature",
  "properties": {
    "iso:country":"GB",
    "sg:address":"Sedlescombe Road North",
    "sg:city":"St Leonards-on-sea",
    "sg:classifiers":[
        {
            "category":"Autos & Motor Vehicles",
            "subcategory":"Fuel & Gas Station",
            "type":"Retail Goods"
        }
    ],
    "sg:phone":"+44 1424 751086",
    "sg:postcode":"TN37 7PB",
    "sg:province":"East Sussex",
    "sg:tags":[
        "hr",
        "petrol"
    ],
    "wof:name":"Elva Service Station",
    "wof:placetype":"venue"
},
  "geometry": {"coordinates":[0.5505120158,50.8845481873],"type":"Point"}
}