{
  "type": "Feature",
  "properties": {
    "addr:full":"76 Mill St Congleton Cheshire CW12 1AG",
    "addr:housenumber":"76",
    "addr:postcode":"cw12 1ag",
    "addr:street":"Mill St",
    "iso:country":"GB",
    "sg:address":"76 Mill St",
    "sg:city":"Congleton",
    "sg:classifiers":[
        {
            "category":"Building & Trades",
            "subcategory":"Construction",
            "type":"Services"
        }
    ],
    "sg:postcode":"CW12 1AG",
    "sg:province":"Cheshire",
    "sg:tags":[
        "builder"
    ],
    "wof:name":"Parker,Graham,",
    "wof:placetype":"venue"
},
  "geometry": {"coordinates":[-2.212709,53.166149],"type":"Point"}
}