{
  "type": "Feature",
  "properties": {
    "iso:country":"GB",
    "sg:address":"206 Great West Road",
    "sg:city":"Hounslow",
    "sg:classifiers":[
        {
            "category":"Communications",
            "type":"Services"
        }
    ],
    "sg:phone":"+44 20 8572 9843",
    "sg:postcode":"TW5 9AW",
    "sg:province":"Greater London",
    "sg:tags":[
        "data",
        "network"
    ],
    "wof:name":"Micropoint Systems Ltd.",
    "wof:placetype":"venue"
},
  "geometry": {"coordinates":[-0.385329,51.476437],"type":"Point"}
}