{
  "type": "Feature",
  "properties": {
    "addr:full":"Moor La Business Centre, Moor La Widnes Cheshire WA8 7AQ",
    "addr:postcode":"wa8 7aq",
    "addr:street":"Moor;Moor La Widnes Cheshire",
    "iso:country":"GB",
    "sg:address":"Moor La Business Centre, Moor La",
    "sg:city":"Widnes",
    "sg:classifiers":[
        {
            "category":"Professional",
            "subcategory":"Printing & Photocopies",
            "type":"Services"
        }
    ],
    "sg:postcode":"WA8 7AQ",
    "sg:province":"Cheshire",
    "sg:tags":[
        "printer"
    ],
    "wof:name":"Wilde,H,",
    "wof:placetype":"venue"
},
  "geometry": {"coordinates":[-2.7408440113,53.3619003296],"type":"Point"}
}