{
  "type": "Feature",
  "properties": {
    "iso:country":"GB",
    "sg:address":"284-286 Perth Road",
    "sg:city":"Dundee",
    "sg:classifiers":[
        {
            "category":"Banks & Credit Unions",
            "subcategory":"Bank",
            "type":"Services"
        }
    ],
    "sg:phone":"+44 845 072 3333",
    "sg:postcode":"DD2 1AN",
    "sg:province":"Dundee City",
    "sg:tags":[
        "financial",
        "institution"
    ],
    "sg:website":"http://www.lloydstsb.com",
    "wof:name":"Lloyds T S B Bank Plc",
    "wof:placetype":"venue"
},
  "geometry": {"coordinates":[-2.993393,56.456181],"type":"Point"}
}