{
  "type": "Feature",
  "properties": {
    "iso:country":"GB",
    "sg:address":"Regents Bridge Gardens",
    "sg:city":"London",
    "sg:classifiers":[
        {
            "category":"Professional",
            "subcategory":"Management & Consulting",
            "type":"Services"
        }
    ],
    "sg:postcode":"SW8 1JR",
    "sg:province":"Greater London",
    "sg:tags":[
        "consultant",
        "business"
    ],
    "wof:name":"Fentiman Consultants Ltd.",
    "wof:placetype":"venue"
},
  "geometry": {"coordinates":[-0.1229299977,51.4808387756],"type":"Point"}
}