{
  "type": "Feature",
  "properties": {
    "addr:full":"Higher Penwartha Farm, Penhallow Truro Cornwall TR4 9ND",
    "addr:postcode":"tr4 9nd",
    "iso:country":"GB",
    "sg:address":"Higher Penwartha Farm, Penhallow",
    "sg:city":"Truro",
    "sg:classifiers":[
        {
            "category":"Farming",
            "subcategory":"Livestock Farm",
            "type":"Manufacturing & Wholesale Goods"
        }
    ],
    "sg:phone":"+44 1872 552562",
    "sg:postcode":"TR4 9ND",
    "sg:province":"Cornwall",
    "sg:tags":[
        "others"
    ],
    "wof:name":"A D & D J Freeman",
    "wof:placetype":"venue"
},
  "geometry": {"coordinates":[-5.136567,50.31636],"type":"Point"}
}