{
  "type": "Feature",
  "properties": {
    "iso:country":"GB",
    "sg:address":"High Street",
    "sg:city":"Buckie",
    "sg:classifiers":[
        {
            "category":"Autos & Motor Vehicles",
            "subcategory":"Automobile Sales",
            "type":"Retail Goods"
        }
    ],
    "sg:phone":"+44 1542 833977",
    "sg:postcode":"AB56 4AD",
    "sg:province":"Moray",
    "sg:tags":[
        "car"
    ],
    "wof:name":"Moravian Motors",
    "wof:placetype":"venue"
},
  "geometry": {"coordinates":[-2.8619379997,57.702331543],"type":"Point"}
}