{
  "type": "Feature",
  "properties": {
    "iso:country":"GB",
    "sg:address":"11 Chequer Rd",
    "sg:city":"Doncaster",
    "sg:classifiers":[
        {
            "category":"Organizations",
            "subcategory":"Non-profit Organization",
            "type":"Services"
        }
    ],
    "sg:postcode":"DN1 2AA",
    "sg:province":"South Yorkshire",
    "sg:tags":[
        "organisation",
        "voluntary",
        "charity"
    ],
    "wof:name":"Yorkshire Compensation Recovery Service",
    "wof:placetype":"venue"
},
  "geometry": {"coordinates":[-1.127813,53.520359],"type":"Point"}
}