{
  "type": "Feature",
  "properties": {
    "iso:country":"GB",
    "sg:address":"2 Carrs Rd",
    "sg:city":"Cheadle",
    "sg:classifiers":[
        {
            "category":"Banks & Credit Unions",
            "subcategory":"Financial Services",
            "type":"Services"
        }
    ],
    "sg:phone":"+44 161 495 6000",
    "sg:postcode":"SK8 2HN",
    "sg:province":"Cheshire",
    "sg:tags":[
        "consultant"
    ],
    "wof:name":"Lombard Business Finance",
    "wof:placetype":"venue"
},
  "geometry": {"coordinates":[-2.1963610649,53.3973045349],"type":"Point"}
}