{
  "type": "Feature",
  "properties": {
    "iso:country":"GB",
    "sg:address":"Catherine House, 88 Victoria Road",
    "sg:city":"Aldershot",
    "sg:classifiers":[
        {
            "category":"Professional",
            "subcategory":"Business Services",
            "type":"Services"
        },
        {
            "category":"Organizations",
            "subcategory":"Membership Organization",
            "type":"Services"
        }
    ],
    "sg:phone":"+44 1252 318251",
    "sg:postcode":"GU11 1SS",
    "sg:province":"Hampshire",
    "sg:tags":[
        "club",
        "trade"
    ],
    "wof:name":"National Caravan Council Ltd.",
    "wof:placetype":"venue"
},
  "geometry": {"coordinates":[-0.759713,51.248283],"type":"Point"}
}