{
  "type": "Feature",
  "properties": {
    "addr:full":"House-in-the-hollow, Logie By Cupar Cupar Fife KY15 4SJ",
    "addr:postcode":"ky15 4sj",
    "addr:street":"Cupar",
    "iso:country":"GB",
    "sg:address":"House-in-the-hollow, Logie By Cupar",
    "sg:city":"Cupar",
    "sg:classifiers":[
        {
            "category":"Professional",
            "type":"Services"
        }
    ],
    "sg:postcode":"KY15 4SJ",
    "sg:province":"Fife",
    "sg:tags":[
        "interior",
        "furnishers",
        "designer"
    ],
    "wof:name":"Fowler & Fowler Contracts",
    "wof:placetype":"venue"
},
  "geometry": {"coordinates":[-3.0117590427,56.3194961548],"type":"Point"}
}