{
  "type": "Feature",
  "properties": {
    "iso:country":"GB",
    "sg:address":"7 Heol Y Wylan, Aberporth",
    "sg:city":"Cardigan",
    "sg:classifiers":[
        {
            "category":"Education",
            "subcategory":"Music School",
            "type":"Public Place"
        }
    ],
    "sg:phone":"+44 1239 810601",
    "sg:postcode":"SA43 2HE",
    "sg:province":"Ceredigion",
    "sg:tags":[
        "teacher"
    ],
    "wof:name":"Sue Kemp",
    "wof:placetype":"venue"
},
  "geometry": {"coordinates":[-4.5434231758,52.1325035095],"type":"Point"}
}