{
  "type": "Feature",
  "properties": {
    "addr:full":"10 Reculver Rd Herne Bay Kent CT6 6LD",
    "addr:housenumber":"10",
    "addr:postcode":"ct6 6ld",
    "addr:street":"Reculver Rd",
    "iso:country":"GB",
    "sg:address":"10 Reculver Rd",
    "sg:city":"Herne Bay",
    "sg:classifiers":[
        {
            "category":"Shopping",
            "subcategory":"Musical Instruments",
            "type":"Retail Goods"
        }
    ],
    "sg:phone":"+44 1227 368808",
    "sg:postcode":"CT6 6LD",
    "sg:province":"Kent",
    "wof:name":"Pianoforte Tuners Association",
    "wof:placetype":"venue"
},
  "geometry": {"coordinates":[1.1456199884,51.3640365601],"type":"Point"}
}