{
  "type": "Feature",
  "properties": {
    "addr:full":"137-139 High Street Orpington Kent BR6 0LQ",
    "addr:housenumber":"137-139",
    "addr:postcode":"br6 0lq",
    "addr:street":"High Street",
    "iso:country":"GB",
    "sg:address":"137-139 High Street",
    "sg:city":"Orpington",
    "sg:classifiers":[
        {
            "category":"Shopping",
            "subcategory":"Clothing, Apparel, & Fashions",
            "type":"Retail Goods"
        }
    ],
    "sg:phone":"+44 1689 873105",
    "sg:postcode":"BR6 0LQ",
    "sg:province":"Kent",
    "sg:tags":[
        "shop"
    ],
    "wof:name":"Mark-One",
    "wof:placetype":"venue"
},
  "geometry": {"coordinates":[0.101302,51.378006],"type":"Point"}
}