{
  "type": "Feature",
  "properties": {
    "iso:country":"GB",
    "sg:address":"Unit 11, 9 Munro Road, Springkerse Industrial Estate",
    "sg:city":"Stirling",
    "sg:classifiers":[
        {
            "category":"Manufacturing",
            "subcategory":"Tools & Machinery",
            "type":"Manufacturing & Wholesale Goods"
        }
    ],
    "sg:phone":"+44 1786 460255",
    "sg:postcode":"FK7 7XQ",
    "sg:province":"Falkirk",
    "wof:name":"Espresso Services",
    "wof:placetype":"venue"
},
  "geometry": {"coordinates":[-3.9107789993,56.1170158386],"type":"Point"}
}