{
  "type": "Feature",
  "properties": {
    "addr:full":"57 Whitethorn Dv Liverpool Merseyside L28 1NX",
    "addr:housenumber":"57",
    "addr:postcode":"l28 1nx",
    "addr:street":"Whitethorn Dv",
    "iso:country":"GB",
    "sg:address":"57 Whitethorn Dv",
    "sg:city":"Liverpool",
    "sg:classifiers":[
        {
            "category":"Building & Trades",
            "subcategory":"Cleaning & Sanitation",
            "type":"Services"
        }
    ],
    "sg:phone":"+44 151 482 0600",
    "sg:postcode":"L28 1NX",
    "sg:province":"Merseyside",
    "sg:tags":[
        "cleaner",
        "window"
    ],
    "wof:name":"1st Class Window Cleaning",
    "wof:placetype":"venue"
},
  "geometry": {"coordinates":[-2.8624970913,53.4351463318],"type":"Point"}
}