{
  "type": "Feature",
  "properties": {
    "addr:full":"10 Knightsridge Indstl Est, Knightsridge East Livingston West Lothian EH54 8RA",
    "addr:housenumber":"10",
    "addr:postcode":"eh54 8ra",
    "addr:street":"Knightsridge Indstl Est Knightsridge East",
    "iso:country":"GB",
    "sg:address":"10 Knightsridge Indstl Est, Knightsridge East",
    "sg:city":"Livingston",
    "sg:classifiers":[
        {
            "category":"Professional",
            "type":"Services"
        }
    ],
    "sg:postcode":"EH54 8RA",
    "sg:province":"West Lothian",
    "sg:tags":[
        "repair",
        "tech",
        "maintenance"
    ],
    "wof:name":"Smart Terminals Ltd",
    "wof:placetype":"venue"
},
  "geometry": {"coordinates":[-3.5098340511,55.8862457275],"type":"Point"}
}