{
  "type": "Feature",
  "properties": {
    "addr:full":"211 Timberlog Lane Basildon Essex SS14 1PB",
    "addr:housenumber":"211",
    "addr:postcode":"ss14 1pb",
    "addr:street":"Timberlog Lane",
    "iso:country":"GB",
    "sg:address":"211 Timberlog Lane",
    "sg:city":"Basildon",
    "sg:classifiers":[
        {
            "category":"Fast Food",
            "type":"Food & Drink"
        }
    ],
    "sg:phone":"+44 1268 552057",
    "sg:postcode":"SS14 1PB",
    "sg:province":"Essex",
    "sg:tags":[
        "away",
        "take"
    ],
    "wof:name":"Foodstop",
    "wof:placetype":"venue"
},
  "geometry": {"coordinates":[0.485390991,51.5706787109],"type":"Point"}
}