{
  "type": "Feature",
  "properties": {
    "addr:full":"45 Minster Road Westgate-on-sea Kent CT8 8DA",
    "addr:housenumber":"45",
    "addr:postcode":"ct8 8da",
    "addr:street":"Minster Road Westgate-On-Sea",
    "iso:country":"GB",
    "sg:address":"45 Minster Road",
    "sg:city":"Westgate-on-sea",
    "sg:classifiers":[
        {
            "category":"Education",
            "subcategory":"School",
            "type":"Public Place"
        }
    ],
    "sg:phone":"+44 1843 831716",
    "sg:postcode":"CT8 8DA",
    "sg:province":"Kent",
    "sg:tags":[
        "independent",
        "preparatory"
    ],
    "wof:name":"Chartfield School",
    "wof:placetype":"venue"
},
  "geometry": {"coordinates":[1.340153,51.377434],"type":"Point"}
}