{
  "type": "Feature",
  "properties": {
    "addr:full":"18 Second Avenue, Penparcau Aberystwyth Ceredigion SY23 1RD",
    "addr:housenumber":"18",
    "addr:postcode":"sy23 1rd",
    "addr:street":"Second Avenue",
    "iso:country":"GB",
    "sg:address":"18 Second Avenue, Penparcau",
    "sg:city":"Aberystwyth",
    "sg:classifiers":[
        {
            "category":"Professional",
            "subcategory":"Engineering",
            "type":"Services"
        }
    ],
    "sg:postcode":"SY23 1RD",
    "sg:province":"Ceredigion",
    "sg:tags":[
        "contractor",
        "electrical",
        "engineer"
    ],
    "wof:name":"D Griffiths",
    "wof:placetype":"venue"
},
  "geometry": {"coordinates":[-4.0746788979,52.4042549133],"type":"Point"}
}