{
  "type": "Feature",
  "properties": {
    "addr:full":"12 Nelson Street Greenock Inverclyde PA15 1TS",
    "addr:housenumber":"12",
    "addr:postcode":"pa15 1ts",
    "addr:street":"Nelson Street Greenock",
    "iso:country":"GB",
    "sg:address":"12 Nelson Street",
    "sg:city":"Greenock",
    "sg:classifiers":[
        {
            "category":"Health Services",
            "subcategory":"Hospice",
            "type":"Services"
        }
    ],
    "sg:phone":"+44 1475 726830",
    "sg:postcode":"PA15 1TS",
    "sg:province":"Inverclyde",
    "wof:name":"Ardgowan Hospice Ltd.",
    "wof:placetype":"venue"
},
  "geometry": {"coordinates":[-4.76631,55.949615],"type":"Point"}
}