{
  "type": "Feature",
  "properties": {
    "addr:full":"18 Lexham Mews Kensington Greater London W8 6JW",
    "addr:housenumber":"18",
    "addr:postcode":"w8 6jw",
    "addr:street":"Lexham Mews",
    "iso:country":"GB",
    "sg:address":"18 Lexham Mews",
    "sg:city":"Kensington",
    "sg:classifiers":[
        {
            "category":"Airline",
            "type":"Transportation"
        }
    ],
    "sg:phone":"+44 20 7937 9299",
    "sg:postcode":"W8 6JW",
    "sg:province":"Greater London",
    "sg:tags":[
        "airport"
    ],
    "wof:name":"Maiden Aviation",
    "wof:placetype":"venue"
},
  "geometry": {"coordinates":[-0.192269,51.49588],"type":"Point"}
}