{
  "type": "Feature",
  "properties": {
    "addr:full":"Unit 2, Halesfield 17 Telford Shropshire TF7 4PW",
    "addr:housenumber":"unit 2;17",
    "addr:postcode":"tf7 4pw",
    "addr:street":"Halesfield",
    "iso:country":"GB",
    "sg:address":"Unit 2, Halesfield 17",
    "sg:city":"Telford",
    "sg:classifiers":[
        {
            "category":"Manufacturing",
            "subcategory":"Electronics",
            "type":"Manufacturing & Wholesale Goods"
        }
    ],
    "sg:phone":"+44 1952 582482",
    "sg:postcode":"TF7 4PW",
    "sg:province":"Shropshire",
    "sg:tags":[
        "control",
        "manufacture",
        "-",
        "component",
        "distribution",
        "electronic"
    ],
    "sg:website":"http://www.electrofit-zapi.com",
    "wof:name":"Electrofit Zapi Ltd",
    "wof:placetype":"venue"
},
  "geometry": {"coordinates":[-2.432259,52.6394],"type":"Point"}
}