{
  "type": "Feature",
  "properties": {
    "addr:full":"Longcauseway, Farnworth Bolton Lancashire BL4 9BD",
    "addr:postcode":"bl4 9bd",
    "iso:country":"GB",
    "sg:address":"Longcauseway, Farnworth",
    "sg:city":"Bolton",
    "sg:classifiers":[
        {
            "category":"Shopping",
            "subcategory":"Pharmacy",
            "type":"Retail Goods"
        }
    ],
    "sg:phone":"+44 1204 701775",
    "sg:postcode":"BL4 9BD",
    "sg:province":"Lancashire",
    "sg:tags":[
        "store",
        "drug"
    ],
    "wof:name":"Superdrug Stores Plc",
    "wof:placetype":"venue"
},
  "geometry": {"coordinates":[-2.391589,53.544476],"type":"Point"}
}