{
  "type": "Feature",
  "properties": {
    "addr:full":"1-2 Wainman Road Peterborough Cambridgeshire PE2 7BU",
    "addr:housenumber":"1-2",
    "addr:postcode":"pe2 7bu",
    "addr:street":"Wainman Road",
    "iso:country":"GB",
    "sg:address":"1-2 Wainman Road",
    "sg:city":"Peterborough",
    "sg:classifiers":[
        {
            "category":"Professional",
            "subcategory":"Printing & Photocopies",
            "type":"Services"
        }
    ],
    "sg:postcode":"PE2 7BU",
    "sg:province":"Cambridgeshire",
    "sg:tags":[
        "printer"
    ],
    "wof:name":"Jacqueline Littlejohn",
    "wof:placetype":"venue"
},
  "geometry": {"coordinates":[-0.264329,52.55397],"type":"Point"}
}