{
  "type": "Feature",
  "properties": {
    "addr:full":"35 Whitworth Street West Manchester Greater Manchester M1 5NG",
    "addr:housenumber":"35",
    "addr:postcode":"m1 5ng",
    "addr:street":"Whitworth Street",
    "iso:country":"GB",
    "sg:address":"35 Whitworth Street West",
    "sg:city":"Manchester",
    "sg:classifiers":[
        {
            "category":"Professional",
            "subcategory":"Management & Consulting",
            "type":"Services"
        }
    ],
    "sg:postcode":"M1 5NG",
    "sg:province":"Greater Manchester",
    "sg:tags":[
        "consultant",
        "business"
    ],
    "wof:name":"Crea Consultants Ltd",
    "wof:placetype":"venue"
},
  "geometry": {"coordinates":[-2.2446610928,53.4741134644],"type":"Point"}
}