{
  "type": "Feature",
  "properties": {
    "addr:full":"125 Pasture Road Wirral Merseyside CH46 4TH",
    "addr:housenumber":"125",
    "addr:postcode":"ch46 4th",
    "addr:street":"Pasture Road",
    "iso:country":"GB",
    "sg:address":"125 Pasture Road",
    "sg:city":"Wirral",
    "sg:classifiers":[
        {
            "category":"Professional",
            "subcategory":"Detective & Security Services",
            "type":"Services"
        }
    ],
    "sg:phone":"+44 151 606 9595",
    "sg:postcode":"CH46 4TH",
    "sg:province":"Merseyside",
    "sg:tags":[
        "alarm",
        "burglar",
        "system"
    ],
    "wof:name":"C Q R Security Components Ltd",
    "wof:placetype":"venue"
},
  "geometry": {"coordinates":[-3.117644,53.412567],"type":"Point"}
}