{
  "type": "Feature",
  "properties": {
    "iso:country":"GB",
    "sg:address":"Shaw Walls, Whiston",
    "sg:city":"Stoke-on-trent",
    "sg:classifiers":[
        {
            "category":"Farming",
            "subcategory":"Livestock Farm",
            "type":"Manufacturing & Wholesale Goods"
        }
    ],
    "sg:phone":"+44 1538 266240",
    "sg:postcode":"ST10 2HS",
    "sg:province":"Staffordshire",
    "sg:tags":[
        "others"
    ],
    "wof:name":"G E & R Lees",
    "wof:placetype":"venue"
},
  "geometry": {"coordinates":[-1.935716,53.038589],"type":"Point"}
}