{
  "type": "Feature",
  "properties": {
    "iso:country":"GB",
    "sg:address":"The Priory Cosgrove",
    "sg:city":"Milton Keynes",
    "sg:classifiers":[
        {
            "category":"Manufacturing",
            "subcategory":"Electronics",
            "type":"Manufacturing & Wholesale Goods"
        }
    ],
    "sg:phone":"+44 1908 265533",
    "sg:postcode":"MK19 7JT",
    "sg:province":"Buckinghamshire",
    "sg:tags":[
        "control",
        "component",
        "-",
        "electronic"
    ],
    "wof:name":"Pericom Infosystems Ltd.",
    "wof:placetype":"venue"
},
  "geometry": {"coordinates":[-0.8478369713,52.0758781433],"type":"Point"}
}