{
  "type": "Feature",
  "properties": {
    "addr:full":"Unit 11-12 Tavener Trad Est, Caerleon Newport Newport NP20 1GG",
    "addr:housenumber":"unit 11-12",
    "addr:postcode":"np20 1gg",
    "addr:street":"Trad",
    "iso:country":"GB",
    "sg:address":"Unit 11-12 Tavener Trad Est, Caerleon",
    "sg:city":"Newport",
    "sg:classifiers":[
        {
            "category":"Communications",
            "type":"Services"
        }
    ],
    "sg:postcode":"NP20 1GG",
    "sg:province":"Newport",
    "sg:tags":[
        "tv",
        "video",
        "radio"
    ],
    "wof:name":"Ramsey,Robert,",
    "wof:placetype":"venue"
},
  "geometry": {"coordinates":[-2.9967501163,51.5886688232],"type":"Point"}
}