{
  "type": "Feature",
  "properties": {
    "addr:full":"Hardenhuish Lane Chippenham Gloucestershire SN14 6HJ",
    "addr:postcode":"sn14 6hj",
    "addr:street":"Hardenhuish Lane",
    "iso:country":"GB",
    "sg:address":"Hardenhuish Lane",
    "sg:city":"Chippenham",
    "sg:classifiers":[
        {
            "category":"Community Center",
            "type":"Public Place"
        }
    ],
    "sg:phone":"+44 1249 651056",
    "sg:postcode":"SN14 6HJ",
    "sg:province":"Gloucestershire",
    "sg:tags":[
        "recreation",
        "leisure",
        "centre"
    ],
    "wof:name":"Sheldon Sports Hall",
    "wof:placetype":"venue"
},
  "geometry": {"coordinates":[-2.128662,51.474911],"type":"Point"}
}