{
  "type": "Feature",
  "properties": {
    "addr:full":"Whistleberry Industrial Estate, Whistleberry Road Hamilton South Lanarkshire ML3 0EJ",
    "addr:postcode":"ml3 0ej",
    "addr:street":"Estate Whistleberry Road",
    "iso:country":"GB",
    "sg:address":"Whistleberry Industrial Estate, Whistleberry Road",
    "sg:city":"Hamilton",
    "sg:classifiers":[
        {
            "category":"Manufacturing",
            "subcategory":"Chemicals & Compounds",
            "type":"Manufacturing & Wholesale Goods"
        },
        {
            "category":"Banks & Credit Unions",
            "subcategory":"Investment Brokerage",
            "type":"Services"
        }
    ],
    "sg:phone":"+44 1698 710344",
    "sg:postcode":"ML3 0EJ",
    "sg:province":"South Lanarkshire",
    "sg:tags":[
        "pesticide",
        "additive",
        "colouring",
        "flavouring"
    ],
    "wof:name":"Sensient Colors U K Ltd.",
    "wof:placetype":"venue"
},
  "geometry": {"coordinates":[-4.052891,55.777321],"type":"Point"}
}