{
  "type": "Feature",
  "properties": {
    "addr:full":"Malcolm House Dunfermline Fife KY12 7NU",
    "addr:postcode":"ky12 7nu",
    "addr:street":"Dunfermline",
    "iso:country":"GB",
    "sg:address":"Malcolm House",
    "sg:city":"Dunfermline",
    "sg:classifiers":[
        {
            "category":"Professional",
            "subcategory":"Accounting & Tax Preparation",
            "type":"Services"
        }
    ],
    "sg:phone":"+44 1383 624622",
    "sg:postcode":"KY12 7NU",
    "sg:province":"Fife",
    "sg:tags":[
        "accountant"
    ],
    "wof:name":"Frick & Co.",
    "wof:placetype":"venue"
},
  "geometry": {"coordinates":[-3.4613740444,56.0748443604],"type":"Point"}
}