{
  "type": "Feature",
  "properties": {
    "addr:full":"52 High Street Reigate Surrey RH2 9AT",
    "addr:housenumber":"52",
    "addr:postcode":"rh2 9at",
    "addr:street":"High Street",
    "iso:country":"GB",
    "sg:address":"52 High Street",
    "sg:city":"Reigate",
    "sg:classifiers":[
        {
            "category":"Shopping",
            "subcategory":"Mobile Phones",
            "type":"Retail Goods"
        }
    ],
    "sg:postcode":"RH2 9AT",
    "sg:province":"Surrey",
    "wof:name":"Phone Alone",
    "wof:placetype":"venue"
},
  "geometry": {"coordinates":[-0.2079740018,51.2377891541],"type":"Point"}
}