{
  "type": "Feature",
  "properties": {
    "iso:country":"GB",
    "sg:address":"23 Market Place, Longridge",
    "sg:city":"Preston",
    "sg:classifiers":[
        {
            "category":"Food & Beverages",
            "subcategory":"Meat & Fish",
            "type":"Retail Goods"
        }
    ],
    "sg:postcode":"PR3 3RR",
    "sg:province":"Lancashire",
    "sg:tags":[
        "chip"
    ],
    "wof:name":"Happy Haddock",
    "wof:placetype":"venue"
},
  "geometry": {"coordinates":[-2.599846,53.829422],"type":"Point"}
}