{
  "type": "Feature",
  "properties": {
    "addr:full":"Torrisholme Square Morecambe Lancashire LA4 6NJ",
    "addr:postcode":"la4 6nj",
    "addr:street":"Torrisholme Square Morecambe",
    "iso:country":"GB",
    "sg:address":"Torrisholme Square",
    "sg:city":"Morecambe",
    "sg:classifiers":[
        {
            "category":"Home & Garden",
            "subcategory":"Hardware",
            "type":"Retail Goods"
        }
    ],
    "sg:postcode":"LA4 6NJ",
    "sg:province":"Lancashire",
    "sg:tags":[
        "retailer",
        "diy"
    ],
    "wof:name":"John Cole",
    "wof:placetype":"venue"
},
  "geometry": {"coordinates":[-2.830683,54.067047],"type":"Point"}
}