{
  "type": "Feature",
  "properties": {
    "addr:full":"Grendon Lodge, 22 St Johns Rd Clevedon Somerset BS21 7TG",
    "addr:housenumber":"grendon;22",
    "addr:postcode":"bs21 7tg",
    "addr:street":"St Johns Rd",
    "iso:country":"GB",
    "sg:address":"Grendon Lodge, 22 St Johns Rd",
    "sg:city":"Clevedon",
    "sg:classifiers":[
        {
            "category":"Health Services",
            "subcategory":"Dentist",
            "type":"Services"
        }
    ],
    "sg:phone":"+44 1275 342183",
    "sg:postcode":"BS21 7TG",
    "sg:province":"Somerset",
    "wof:name":"Nigel J Smith",
    "wof:placetype":"venue"
},
  "geometry": {"coordinates":[-2.855039,51.435925],"type":"Point"}
}