{
  "type": "Feature",
  "properties": {
    "addr:full":"Moray House, 23-31 Great Titchfield St West End Hampshire W1P 7FE",
    "addr:housenumber":"23-31",
    "addr:postcode":"w1p 7fe",
    "addr:street":"Great Titchfield St",
    "iso:country":"GB",
    "sg:address":"Moray House, 23-31 Great Titchfield St",
    "sg:city":"West End",
    "sg:classifiers":[
        {
            "category":"Manufacturing",
            "subcategory":"Apparel",
            "type":"Manufacturing & Wholesale Goods"
        }
    ],
    "sg:phone":"+44 20 7637 3851",
    "sg:postcode":"W1P 7FE",
    "sg:province":"Hampshire",
    "sg:tags":[
        "shirt",
        "maker"
    ],
    "wof:name":"New Man",
    "wof:placetype":"venue"
},
  "geometry": {"coordinates":[-0.1398770064,51.5164527893],"type":"Point"}
}