{
  "type": "Feature",
  "properties": {
    "iso:country":"GB",
    "sg:address":"2a Herring Arm Road Industrial Estate, Wyre Dock",
    "sg:city":"Fleetwood",
    "sg:classifiers":[
        {
            "category":"Freight",
            "type":"Transportation"
        }
    ],
    "sg:phone":"+44 1253 876716",
    "sg:postcode":"FY7 6NB",
    "sg:province":"Lancashire",
    "sg:tags":[
        "overseas",
        "shipping",
        "removal"
    ],
    "wof:name":"John Ward Agency (Fleetwood) Ltd.",
    "wof:placetype":"venue"
},
  "geometry": {"coordinates":[-3.014669,53.92128],"type":"Point"}
}