{
  "type": "Feature",
  "properties": {
    "iso:country":"GB",
    "sg:address":"First Floor, 29 The Square",
    "sg:city":"Retford",
    "sg:classifiers":[
        {
            "category":"Shopping",
            "subcategory":"Clothing, Apparel, & Fashions",
            "type":"Retail Goods"
        }
    ],
    "sg:postcode":"DN22 6DQ",
    "sg:province":"Nottinghamshire",
    "sg:tags":[
        "ladieswear"
    ],
    "wof:name":"Jay-Elle Clothing",
    "wof:placetype":"venue"
},
  "geometry": {"coordinates":[-0.937129,53.326488],"type":"Point"}
}