{
  "type": "Feature",
  "properties": {
    "addr:full":"Threshers Yard West Street, Kingham Chipping Norton Gloucestershire OX7 6YF",
    "addr:housenumber":"norton",
    "addr:postcode":"ox7 6yf",
    "addr:street":"West Street",
    "iso:country":"GB",
    "sg:address":"Threshers Yard West Street, Kingham",
    "sg:city":"Chipping Norton",
    "sg:classifiers":[
        {
            "category":"Professional",
            "subcategory":"Computer Services",
            "type":"Services"
        }
    ],
    "sg:phone":"+44 1608 648200",
    "sg:postcode":"OX7 6YF",
    "sg:province":"Gloucestershire",
    "sg:tags":[
        "system",
        "software"
    ],
    "wof:name":"Interact Business Solutions Ltd.",
    "wof:placetype":"venue"
},
  "geometry": {"coordinates":[-1.6222770214,51.9145584106],"type":"Point"}
}