{
  "type": "Feature",
  "properties": {
    "addr:full":"4 Glenluce Court Cramlington Northumberland NE23 6YA",
    "addr:housenumber":"4",
    "addr:postcode":"ne23 6ya",
    "addr:street":"Glenluce Court;Northumberland",
    "iso:country":"GB",
    "sg:address":"4 Glenluce Court",
    "sg:city":"Cramlington",
    "sg:classifiers":[
        {
            "category":"Food & Beverages",
            "subcategory":"Supermarket",
            "type":"Retail Goods"
        }
    ],
    "sg:phone":"+44 1670 717389",
    "sg:postcode":"NE23 6YA",
    "sg:province":"Northumberland",
    "wof:name":"Costcutter",
    "wof:placetype":"venue"
},
  "geometry": {"coordinates":[-1.588983,55.072308],"type":"Point"}
}