{
  "type": "Feature",
  "properties": {
    "addr:full":"Reform Works, Reform Road Maidenhead Berkshire SL6 8BY",
    "addr:postcode":"sl6 8by",
    "addr:street":"Reform Road",
    "iso:country":"GB",
    "sg:address":"Reform Works, Reform Road",
    "sg:city":"Maidenhead",
    "sg:classifiers":[
        {
            "category":"Manufacturing",
            "subcategory":"Metals",
            "type":"Manufacturing & Wholesale Goods"
        }
    ],
    "sg:phone":"+44 1628 630211",
    "sg:postcode":"SL6 8BY",
    "sg:province":"Berkshire",
    "sg:tags":[
        "fab",
        "foundry"
    ],
    "wof:name":"Ferndowne Casting Co. Ltd.",
    "wof:placetype":"venue"
},
  "geometry": {"coordinates":[-0.7272570133,51.5223731995],"type":"Point"}
}