{
  "type": "Feature",
  "properties": {
    "addr:full":"Bedworth Bypass, A444 Nuneaton Leicestershire CV10 7DA",
    "addr:housenumber":"a444",
    "addr:postcode":"cv10 7da",
    "addr:street":"Bedworth Bypass",
    "iso:country":"GB",
    "sg:address":"Bedworth Bypass, A444",
    "sg:city":"Nuneaton",
    "sg:classifiers":[
        {
            "category":"Restaurant",
            "type":"Food & Drink"
        }
    ],
    "sg:phone":"+44 24 7637 5287",
    "sg:postcode":"CV10 7DA",
    "sg:province":"Leicestershire",
    "wof:name":"Little Chef",
    "wof:placetype":"venue"
},
  "geometry": {"coordinates":[-1.4803849459,52.493221283],"type":"Point"}
}