{
  "type": "Feature",
  "properties": {
    "addr:full":"Ritherup Lane, Rainhill Prescot Cheshire L35 4NZ",
    "addr:postcode":"l35 4nz",
    "addr:street":"Ritherup Lane",
    "iso:country":"GB",
    "sg:address":"Ritherup Lane, Rainhill",
    "sg:city":"Prescot",
    "sg:classifiers":[
        {
            "category":"Wholesale",
            "subcategory":"Scrap",
            "type":"Manufacturing & Wholesale Goods"
        }
    ],
    "sg:phone":"+44 151 493 9100",
    "sg:postcode":"L35 4NZ",
    "sg:province":"Cheshire",
    "sg:tags":[
        "car",
        "breaker",
        "dismantlers"
    ],
    "wof:name":"M & J Auto Breakers",
    "wof:placetype":"venue"
},
  "geometry": {"coordinates":[-2.765704,53.416473],"type":"Point"}
}