{
  "type": "Feature",
  "properties": {
    "addr:full":"Strebla House, Beach Road Clacton-on-sea Essex CO15 1UE",
    "addr:postcode":"co15 1ue",
    "addr:street":"Beach Road",
    "iso:country":"GB",
    "sg:address":"Strebla House, Beach Road",
    "sg:city":"Clacton-on-sea",
    "sg:classifiers":[
        {
            "category":"Retail",
            "subcategory":"Auto Repair",
            "type":"Services"
        }
    ],
    "sg:phone":"+44 1255 474666",
    "sg:postcode":"CO15 1UE",
    "sg:province":"Essex",
    "sg:tags":[
        "body",
        "car",
        "repairer"
    ],
    "wof:name":"Darren Penny",
    "wof:placetype":"venue"
},
  "geometry": {"coordinates":[1.1563249826,51.7891845703],"type":"Point"}
}