{
  "type": "Feature",
  "properties": {
    "addr:full":"18 Curzon Street Maryport Cumbria CA15 6LN",
    "addr:housenumber":"18",
    "addr:postcode":"ca15 6ln",
    "addr:street":"Curzon Street",
    "iso:country":"GB",
    "sg:address":"18 Curzon Street",
    "sg:city":"Maryport",
    "sg:classifiers":[
        {
            "category":"Retail",
            "subcategory":"Veterinary Services",
            "type":"Services"
        }
    ],
    "sg:phone":"+44 1900 816666",
    "sg:postcode":"CA15 6LN",
    "sg:province":"Cumbria",
    "sg:tags":[
        "surgeon",
        "activity"
    ],
    "wof:name":"CROFT VETERINARY GROUP",
    "wof:placetype":"venue"
},
  "geometry": {"coordinates":[-3.495696,54.713776],"type":"Point"}
}