{
  "type": "Feature",
  "properties": {
    "addr:full":"5a Brandon Road, Binley Coventry Warwickshire CV3 2JD",
    "addr:housenumber":"5a",
    "addr:postcode":"cv3 2jd",
    "addr:street":"Brandon Road",
    "iso:country":"GB",
    "sg:address":"5a Brandon Road, Binley",
    "sg:city":"Coventry",
    "sg:classifiers":[
        {
            "category":"Professional",
            "subcategory":"Business Services",
            "type":"Services"
        },
        {
            "category":"Casinos & Gambling",
            "type":"Entertainment"
        }
    ],
    "sg:phone":"+44 24 7645 6958",
    "sg:postcode":"CV3 2JD",
    "sg:province":"Warwickshire",
    "sg:tags":[
        "turf",
        "accountant",
        "bookmaker"
    ],
    "wof:name":"Michael Cole",
    "wof:placetype":"venue"
},
  "geometry": {"coordinates":[-1.4460020065,52.4022331238],"type":"Point"}
}