{
  "type": "Feature",
  "properties": {
    "iso:country":"GB",
    "sg:address":"12 North Street, Stanground",
    "sg:city":"Peterborough",
    "sg:classifiers":[
        {
            "category":"Retail",
            "subcategory":"Auto Repair",
            "type":"Services"
        }
    ],
    "sg:phone":"+44 7747 692179",
    "sg:postcode":"PE2 8HR",
    "sg:province":"Cambridgeshire",
    "sg:tags":[
        "body",
        "car"
    ],
    "wof:name":"Yaxley Motors",
    "wof:placetype":"venue"
},
  "geometry": {"coordinates":[-0.2281190008,52.5620765686],"type":"Point"}
}