{
  "type": "Feature",
  "properties": {
    "addr:full":"13 Hardy Crescent Wimborne Dorset BH21 2AR",
    "addr:housenumber":"13",
    "addr:postcode":"bh21 2ar",
    "addr:street":"Hardy Crescent",
    "iso:country":"GB",
    "sg:address":"13 Hardy Crescent",
    "sg:city":"Wimborne",
    "sg:classifiers":[
        {
            "category":"Shopping",
            "subcategory":"Party Supplies",
            "type":"Retail Goods"
        },
        {
            "category":"Arts & Performance",
            "subcategory":"Music",
            "type":"Entertainment"
        }
    ],
    "sg:phone":"+44 1202 885696",
    "sg:postcode":"BH21 2AR",
    "sg:province":"Dorset",
    "sg:tags":[
        "mobile",
        "operator",
        "disco"
    ],
    "wof:name":"Paul Jones",
    "wof:placetype":"venue"
},
  "geometry": {"coordinates":[-1.972965,50.796913],"type":"Point"}
}