{
  "type": "Feature",
  "properties": {
    "addr:full":"3rd Floor, Arundel Court, 177 Arundel Street Sheffield South Yorkshire S1 2NU",
    "addr:housenumber":"3rd floor;177",
    "addr:postcode":"s1 2nu",
    "addr:street":"Arundel;Arundel Street",
    "iso:country":"GB",
    "sg:address":"3rd Floor, Arundel Court, 177 Arundel Street",
    "sg:city":"Sheffield",
    "sg:classifiers":[
        {
            "category":"Organizations",
            "subcategory":"Non-profit Organization",
            "type":"Services"
        }
    ],
    "sg:phone":"+44 114 278 7088",
    "sg:postcode":"S1 2NU",
    "sg:province":"South Yorkshire",
    "sg:tags":[
        "organisation",
        "voluntary",
        "charity"
    ],
    "wof:name":"Law Centres Federation",
    "wof:placetype":"venue"
},
  "geometry": {"coordinates":[-1.4678399563,53.3770484924],"type":"Point"}
}