{
  "type": "Feature",
  "properties": {
    "addr:full":"1 Minster Court, Mincing London Greater London EC3R 7FE",
    "addr:housenumber":"1",
    "addr:postcode":"ec3r 7fe",
    "addr:street":"Minster Court",
    "iso:country":"GB",
    "sg:address":"1 Minster Court, Mincing",
    "sg:city":"London",
    "sg:classifiers":[
        {
            "category":"Professional",
            "subcategory":"Business Services",
            "type":"Services"
        }
    ],
    "sg:postcode":"EC3R 7FE",
    "sg:province":"Greater London",
    "sg:tags":[
        "broker",
        "commodity"
    ],
    "wof:name":"Brandeis (Brokers) Ltd.",
    "wof:placetype":"venue"
},
  "geometry": {"coordinates":[-0.081619,51.510464],"type":"Point"}
}