{
  "type": "Feature",
  "properties": {
    "iso:country":"GB",
    "sg:address":"19 Waylen Street",
    "sg:city":"Reading",
    "sg:classifiers":[
        {
            "category":"Organizations",
            "subcategory":"Non-profit Organization",
            "type":"Services"
        }
    ],
    "sg:phone":"+44 118 956 0362",
    "sg:postcode":"RG1 7UP",
    "sg:province":"Berkshire",
    "sg:tags":[
        "charitable",
        "organisation",
        "voluntary",
        "charity"
    ],
    "wof:name":"READING SINGLE HOMELESS PROJECT",
    "wof:placetype":"venue"
},
  "geometry": {"coordinates":[-0.981206,51.454426],"type":"Point"}
}