{
  "type": "Feature",
  "properties": {
    "addr:full":"Ridgeway Sedbergh Cumbria LA10 5HJ",
    "addr:postcode":"la10 5hj",
    "addr:street":"Ridgeway",
    "iso:country":"GB",
    "sg:address":"Ridgeway",
    "sg:city":"Sedbergh",
    "sg:classifiers":[
        {
            "category":"Retail",
            "subcategory":"Auto Repair",
            "type":"Services"
        }
    ],
    "sg:postcode":"LA10 5HJ",
    "sg:province":"Cumbria",
    "sg:tags":[
        "modification",
        "garage"
    ],
    "wof:name":"D T Close",
    "wof:placetype":"venue"
},
  "geometry": {"coordinates":[-2.527837,54.321945],"type":"Point"}
}