{
  "type": "Feature",
  "properties": {
    "iso:country":"GB",
    "sg:address":"8 Heath Road",
    "sg:city":"Sheringham",
    "sg:classifiers":[
        {
            "category":"Personal",
            "type":"Services"
        },
        {
            "category":"Professional",
            "subcategory":"Art Services",
            "type":"Services"
        }
    ],
    "sg:phone":"+44 1263 825305",
    "sg:postcode":"NR26 8JH",
    "sg:province":"Norfolk",
    "sg:tags":[
        "graphic",
        "designer",
        "wedding"
    ],
    "wof:name":"Moving Memories",
    "wof:placetype":"venue"
},
  "geometry": {"coordinates":[1.213383,52.938118],"type":"Point"}
}