{
  "type": "Feature",
  "properties": {
    "addr:full":"56 Field St Wolverhampton Staffordshire WV10 0JH",
    "addr:housenumber":"56",
    "addr:postcode":"wv10 0jh",
    "addr:street":"Field St",
    "iso:country":"GB",
    "sg:address":"56 Field St",
    "sg:city":"Wolverhampton",
    "sg:classifiers":[
        {
            "category":"Professional",
            "subcategory":"Detective & Security Services",
            "type":"Services"
        }
    ],
    "sg:phone":"+44 1902 569424",
    "sg:postcode":"WV10 0JH",
    "sg:province":"Staffordshire",
    "wof:name":"R T Secuities",
    "wof:placetype":"venue"
},
  "geometry": {"coordinates":[-2.117331028,52.5901603699],"type":"Point"}
}