{
  "type": "Feature",
  "properties": {
    "addr:full":"Waltham Forest Club, Harvey Rd Wanstead Greater London E11 3DB",
    "addr:postcode":"e11 3db",
    "addr:street":"Harvey Rd",
    "iso:country":"GB",
    "sg:address":"Waltham Forest Club, Harvey Rd",
    "sg:city":"Wanstead",
    "sg:classifiers":[
        {
            "category":"Social Services",
            "subcategory":"Adult Care",
            "type":"Services"
        }
    ],
    "sg:phone":"+44 20 8556 5652",
    "sg:postcode":"E11 3DB",
    "sg:province":"Greater London",
    "sg:tags":[
        "day",
        "centre"
    ],
    "wof:name":"Forest House",
    "wof:placetype":"venue"
},
  "geometry": {"coordinates":[0.01085,51.567848],"type":"Point"}
}