{
  "type": "Feature",
  "properties": {
    "addr:full":"4 St Giles Walk, High St Chalfont St Giles Buckinghamshire HP8 4QA",
    "addr:housenumber":"4",
    "addr:postcode":"hp8 4qa",
    "addr:street":"St Giles Walk High St",
    "iso:country":"GB",
    "sg:address":"4 St Giles Walk, High St",
    "sg:city":"Chalfont St Giles",
    "sg:classifiers":[
        {
            "category":"Food & Beverages",
            "subcategory":"Specialty",
            "type":"Retail Goods"
        }
    ],
    "sg:postcode":"HP8 4QA",
    "sg:province":"Buckinghamshire",
    "sg:tags":[
        "product",
        "health"
    ],
    "wof:name":"Village Wholefoods",
    "wof:placetype":"venue"
},
  "geometry": {"coordinates":[-0.576628983,51.6299247742],"type":"Point"}
}