{
  "type": "Feature",
  "properties": {
    "iso:country":"GB",
    "sg:address":"1 Victoria Crescent, Cullercoats",
    "sg:city":"North Shields",
    "sg:classifiers":[
        {
            "category":"Food & Beverages",
            "subcategory":"Candy",
            "type":"Retail Goods"
        }
    ],
    "sg:phone":"+44 191 291 0222",
    "sg:postcode":"NE30 4PN",
    "sg:province":"Tyne and Wear",
    "sg:tags":[
        "confectioner"
    ],
    "wof:name":"Candyman",
    "wof:placetype":"venue"
},
  "geometry": {"coordinates":[-1.4331409931,55.0350532532],"type":"Point"}
}