{
  "type": "Feature",
  "properties": {
    "addr:full":"37 The Strand Dawlish Devon EX7 9PT",
    "addr:housenumber":"37",
    "addr:postcode":"ex7 9pt",
    "addr:street":"The Strand",
    "iso:country":"GB",
    "sg:address":"37 The Strand",
    "sg:city":"Dawlish",
    "sg:classifiers":[
        {
            "category":"Health Services",
            "subcategory":"Health Practitioner",
            "type":"Services"
        }
    ],
    "sg:phone":"+44 1626 863256",
    "sg:postcode":"EX7 9PT",
    "sg:province":"Devon",
    "sg:tags":[
        "osteopath"
    ],
    "wof:name":"Peter Hands",
    "wof:placetype":"venue"
},
  "geometry": {"coordinates":[-3.470462,50.581272],"type":"Point"}
}