{
  "type": "Feature",
  "properties": {
    "addr:full":"40 High Road, South Woodford London Greater London E18 2QL",
    "addr:housenumber":"40",
    "addr:postcode":"e18 2ql",
    "addr:street":"High Road",
    "iso:country":"GB",
    "sg:address":"40 High Road, South Woodford",
    "sg:city":"London",
    "sg:classifiers":[
        {
            "category":"Banks & Credit Unions",
            "subcategory":"Financial Services",
            "type":"Services"
        },
        {
            "category":"Social Services",
            "subcategory":"Retirement Home",
            "type":"Services"
        }
    ],
    "sg:phone":"+44 20 8530 5031",
    "sg:postcode":"E18 2QL",
    "sg:province":"Greater London",
    "sg:tags":[
        "consultant",
        "leasing"
    ],
    "wof:name":"Finance & Leasing London Ltd",
    "wof:placetype":"venue"
},
  "geometry": {"coordinates":[0.0225760005,51.593875885],"type":"Point"}
}