{
  "type": "Feature",
  "properties": {
    "addr:full":"111 High St Tarporley Cheshire CW6 0AY",
    "addr:housenumber":"111",
    "addr:postcode":"cw6 0ay",
    "addr:street":"High St",
    "iso:country":"GB",
    "sg:address":"111 High St",
    "sg:city":"Tarporley",
    "sg:classifiers":[
        {
            "category":"Retail",
            "subcategory":"Funeral Services",
            "type":"Services"
        }
    ],
    "sg:phone":"+44 1829 733808",
    "sg:postcode":"CW6 0AY",
    "sg:province":"Cheshire",
    "wof:name":"U K Funerals Ltd",
    "wof:placetype":"venue"
},
  "geometry": {"coordinates":[-2.667022,53.156399],"type":"Point"}
}