{
  "type": "Feature",
  "properties": {
    "addr:full":"Baton Road Shotts North Lanarkshire ML7 4EY",
    "addr:postcode":"ml7 4ey",
    "addr:street":"Baton Road",
    "iso:country":"GB",
    "sg:address":"Baton Road",
    "sg:city":"Shotts",
    "sg:classifiers":[
        {
            "category":"Arena",
            "subcategory":"Sports Club",
            "type":"Entertainment"
        }
    ],
    "sg:phone":"+44 1501 821542",
    "sg:postcode":"ML7 4EY",
    "sg:province":"North Lanarkshire",
    "wof:name":"Shotts Bon Accord Football Club",
    "wof:placetype":"venue"
},
  "geometry": {"coordinates":[-3.8086190224,55.8267364502],"type":"Point"}
}