{
  "type": "Feature",
  "properties": {
    "iso:country":"GB",
    "sg:address":"Wren Ho, Ballards Hill, Crowhurst",
    "sg:city":"Battle",
    "sg:classifiers":[
        {
            "category":"Banks & Credit Unions",
            "subcategory":"Investment Brokerage",
            "type":"Services"
        }
    ],
    "sg:postcode":"TN33 9DA",
    "sg:province":"East Sussex",
    "sg:tags":[
        "overseas",
        "property",
        "agent"
    ],
    "wof:name":"Wren Properties International",
    "wof:placetype":"venue"
},
  "geometry": {"coordinates":[0.499597013,50.8900718689],"type":"Point"}
}