{
  "type": "Feature",
  "properties": {
    "iso:country":"GB",
    "sg:address":"Limbrick Road",
    "sg:city":"Sheffield",
    "sg:classifiers":[
        {
            "category":"Health Services",
            "subcategory":"Clinic",
            "type":"Services"
        }
    ],
    "sg:phone":"+44 114 271 6074",
    "sg:postcode":"S6 2PE",
    "sg:province":"South Yorkshire",
    "sg:tags":[
        "nh"
    ],
    "wof:name":"Limbrick Community Health Centre",
    "wof:placetype":"venue"
},
  "geometry": {"coordinates":[-1.501109,53.40176],"type":"Point"}
}