{
  "type": "Feature",
  "properties": {
    "iso:country":"GB",
    "sg:address":"47-51 Perry Vale",
    "sg:city":"Forest Hill",
    "sg:classifiers":[
        {
            "category":"Autos & Motor Vehicles",
            "subcategory":"Auto Supplies",
            "type":"Retail Goods"
        }
    ],
    "sg:phone":"+44 20 8291 1221",
    "sg:postcode":"SE23 2NE",
    "sg:province":"Greater London",
    "sg:tags":[
        "car",
        "audio"
    ],
    "wof:name":"G & S Car Audio's",
    "wof:placetype":"venue"
},
  "geometry": {"coordinates":[-0.052684,51.438705],"type":"Point"}
}