{
  "type": "Feature",
  "properties": {
    "addr:full":"Audley House, North Bridge Rd Berkhamsted Bedfordshire HP4 1EH",
    "addr:postcode":"hp4 1eh",
    "addr:street":"North Bridge Rd",
    "iso:country":"GB",
    "sg:address":"Audley House, North Bridge Rd",
    "sg:city":"Berkhamsted",
    "sg:classifiers":[
        {
            "category":"Professional",
            "subcategory":"Engineering",
            "type":"Services"
        }
    ],
    "sg:phone":"+44 1442 878999",
    "sg:postcode":"HP4 1EH",
    "sg:province":"Bedfordshire",
    "sg:tags":[
        "ge",
        "engineer",
        "mechanical"
    ],
    "wof:name":"Ruscoes & Ford Ltd",
    "wof:placetype":"venue"
},
  "geometry": {"coordinates":[-0.580807,51.767838],"type":"Point"}
}