{
  "type": "Feature",
  "properties": {
    "addr:full":"33 Rathmore Crescent Southport Lancashire PR9 8PN",
    "addr:housenumber":"33",
    "addr:postcode":"pr9 8pn",
    "addr:street":"Rathmore Crescent",
    "iso:country":"GB",
    "sg:address":"33 Rathmore Crescent",
    "sg:city":"Southport",
    "sg:classifiers":[
        {
            "category":"Building & Trades",
            "subcategory":"Construction",
            "type":"Services"
        }
    ],
    "sg:phone":"+44 1704 232657",
    "sg:postcode":"PR9 8PN",
    "sg:province":"Lancashire",
    "sg:tags":[
        "decorator",
        "painter"
    ],
    "wof:name":"Topcoat Decorating",
    "wof:placetype":"venue"
},
  "geometry": {"coordinates":[-2.9572060108,53.6675453186],"type":"Point"}
}