{
  "type": "Feature",
  "properties": {
    "addr:full":"2 Ashwood Place, Bean Dartford Kent DA2 8BD",
    "addr:housenumber":"2",
    "addr:postcode":"da2 8bd",
    "addr:street":"Ashwood Place",
    "iso:country":"GB",
    "sg:address":"2 Ashwood Place, Bean",
    "sg:city":"Dartford",
    "sg:classifiers":[
        {
            "category":"Professional",
            "type":"Services"
        }
    ],
    "sg:phone":"+44 1474 709784",
    "sg:postcode":"DA2 8BD",
    "sg:province":"Kent",
    "sg:tags":[
        "services",
        "belt",
        "conveyor"
    ],
    "wof:name":"M T S S",
    "wof:placetype":"venue"
},
  "geometry": {"coordinates":[0.2833879888,51.4270210266],"type":"Point"}
}