{
  "type": "Feature",
  "properties": {
    "iso:country":"GB",
    "sg:address":"St Peters Church Hall, St Peters Road",
    "sg:city":"Dudley",
    "sg:classifiers":[
        {
            "category":"Education",
            "subcategory":"Dance Studio",
            "type":"Public Place"
        }
    ],
    "sg:phone":"+44 121 550 6245",
    "sg:postcode":"DY2 9HX",
    "sg:province":"West Midlands",
    "sg:tags":[
        "school",
        "dancing"
    ],
    "wof:name":"Ace Midland Dance Studio",
    "wof:placetype":"venue"
},
  "geometry": {"coordinates":[-2.0835089684,52.5095214844],"type":"Point"}
}