{
  "type": "Feature",
  "properties": {
    "iso:country":"GB",
    "sg:address":"84 Colman Road",
    "sg:city":"Norwich",
    "sg:classifiers":[
        {
            "category":"Home & Garden",
            "subcategory":"Hardware",
            "type":"Retail Goods"
        }
    ],
    "sg:phone":"+44 1603 452295",
    "sg:postcode":"NR4 7EH",
    "sg:province":"Norfolk",
    "sg:tags":[
        "merchant",
        "ironmonger"
    ],
    "wof:name":"WOOD'S OF NORWICH",
    "wof:placetype":"venue"
},
  "geometry": {"coordinates":[1.262413,52.621864],"type":"Point"}
}