{
  "type": "Feature",
  "properties": {
    "addr:full":"634 Coventry Road Birmingham West Midlands B10 0UT",
    "addr:housenumber":"634",
    "addr:postcode":"b10 0ut",
    "addr:street":"Coventry Road",
    "iso:country":"GB",
    "sg:address":"634 Coventry Road",
    "sg:city":"Birmingham",
    "sg:classifiers":[
        {
            "category":"Shopping",
            "subcategory":"Clothing, Apparel, & Fashions",
            "type":"Retail Goods"
        }
    ],
    "sg:phone":"+44 121 772 8290",
    "sg:postcode":"B10 0UT",
    "sg:province":"West Midlands",
    "sg:tags":[
        "shop"
    ],
    "wof:name":"Medina Trading Co",
    "wof:placetype":"venue"
},
  "geometry": {"coordinates":[-1.85162,52.467518],"type":"Point"}
}