{
  "type": "Feature",
  "properties": {
    "iso:country":"GB",
    "sg:address":"Glamorgan Ho, David St",
    "sg:city":"Cardiff",
    "sg:classifiers":[
        {
            "category":"Place Of Worship",
            "type":"Public Place"
        }
    ],
    "sg:phone":"+44 29 2025 5255",
    "sg:postcode":"CF1 2EH",
    "sg:province":"Cardiff",
    "wof:name":"Cardiff Christian Life Centre",
    "wof:placetype":"venue"
},
  "geometry": {"coordinates":[-3.18067,51.481258],"type":"Point"}
}