{
  "type": "Feature",
  "properties": {
    "iso:country":"GB",
    "sg:address":"41 Devonshire Rd",
    "sg:city":"Bexhill On Sea",
    "sg:classifiers":[
        {
            "category":"Personal",
            "subcategory":"Beauty Salon",
            "type":"Services"
        }
    ],
    "sg:phone":"+44 1424 217999",
    "sg:postcode":"TN40 1BD",
    "sg:province":"East Sussex",
    "sg:tags":[
        "unisex",
        "hairdresser"
    ],
    "wof:name":"Fantasia Hairdressing Salon",
    "wof:placetype":"venue"
},
  "geometry": {"coordinates":[0.474075,50.838711],"type":"Point"}
}