{
  "type": "Feature",
  "properties": {
    "iso:country":"GB",
    "sg:address":"Gretton House, Waterside Court, Third Avenue, Centrum 100",
    "sg:city":"Burton On Trent",
    "sg:classifiers":[
        {
            "category":"Banks & Credit Unions",
            "subcategory":"Financial Services",
            "type":"Services"
        }
    ],
    "sg:phone":"+44 1283 740600",
    "sg:postcode":"DE14 2WQ",
    "sg:province":"Derbyshire",
    "sg:tags":[
        "adviser"
    ],
    "wof:name":"B E Keates FCA FIFP CFP",
    "wof:placetype":"venue"
},
  "geometry": {"coordinates":[-1.642079,52.813171],"type":"Point"}
}