{
  "type": "Feature",
  "properties": {
    "iso:country":"GB",
    "sg:address":"Chapel Lane, Coppenhall",
    "sg:city":"Crewe",
    "sg:classifiers":[
        {
            "category":"Wholesale",
            "subcategory":"Scrap",
            "type":"Manufacturing & Wholesale Goods"
        }
    ],
    "sg:phone":"+44 1270 585496",
    "sg:postcode":"CW1 4PR",
    "sg:province":"Cheshire",
    "sg:tags":[
        "breaker",
        "dismantlers"
    ],
    "wof:name":"S I Gregory",
    "wof:placetype":"venue"
},
  "geometry": {"coordinates":[-2.446105,53.100578],"type":"Point"}
}