{
  "type": "Feature",
  "properties": {
    "addr:full":"139 Sussex Gardens Bayswater Greater London W2 2RX",
    "addr:housenumber":"139",
    "addr:postcode":"w2 2rx",
    "addr:street":"Sussex Gardens",
    "iso:country":"GB",
    "sg:address":"139 Sussex Gardens",
    "sg:city":"Bayswater",
    "sg:classifiers":[
        {
            "category":"Travel",
            "subcategory":"Hotels & Motels",
            "type":"Entertainment"
        }
    ],
    "sg:phone":"+44 20 7724 9346",
    "sg:postcode":"W2 2RX",
    "sg:province":"Greater London",
    "wof:name":"Kingsway Park Hotel",
    "wof:placetype":"venue"
},
  "geometry": {"coordinates":[-0.172308,51.514988],"type":"Point"}
}