{
  "type": "Feature",
  "properties": {
    "iso:country":"GB",
    "sg:address":"Colthrop Lane",
    "sg:city":"Thatcham",
    "sg:classifiers":[
        {
            "category":"Shopping",
            "subcategory":"Stationery & Office Supplies",
            "type":"Retail Goods"
        }
    ],
    "sg:phone":"+44 1635 864444",
    "sg:postcode":"RG19 4NL",
    "sg:province":"Berkshire",
    "sg:tags":[
        "box",
        "carton"
    ],
    "wof:name":"Field Packaging",
    "wof:placetype":"venue"
},
  "geometry": {"coordinates":[-1.224984,51.394341],"type":"Point"}
}