{
  "type": "Feature",
  "properties": {
    "addr:full":"43 Heaton Close, Heaton Grange Romford Essex RM3 7HP",
    "addr:housenumber":"43",
    "addr:postcode":"rm3 7hp",
    "addr:street":"Heaton Close",
    "iso:country":"GB",
    "sg:address":"43 Heaton Close, Heaton Grange",
    "sg:city":"Romford",
    "sg:classifiers":[
        {
            "category":"Autos & Motor Vehicles",
            "subcategory":"Auto Supplies",
            "type":"Retail Goods"
        }
    ],
    "sg:phone":"+44 1708 384022",
    "sg:postcode":"RM3 7HP",
    "sg:province":"Essex",
    "sg:tags":[
        "windscreen"
    ],
    "wof:name":"Andy Joule Windscreens",
    "wof:placetype":"venue"
},
  "geometry": {"coordinates":[0.2100059986,51.5977210999],"type":"Point"}
}