{
  "type": "Feature",
  "properties": {
    "iso:country":"GB",
    "sg:address":"329 Wellington Road, Heaton Chapel",
    "sg:city":"Stockport",
    "sg:classifiers":[
        {
            "category":"Health Services",
            "subcategory":"Dentist",
            "type":"Services"
        }
    ],
    "sg:postcode":"SK4 4QG",
    "sg:province":"Cheshire",
    "wof:name":"G M Pickles",
    "wof:placetype":"venue"
},
  "geometry": {"coordinates":[-2.178427,53.428768],"type":"Point"}
}