{
  "type": "Feature",
  "properties": {
    "iso:country":"GB",
    "sg:address":"94 Craigentinny Road",
    "sg:city":"Edinburgh",
    "sg:classifiers":[
        {
            "category":"Food & Beverages",
            "subcategory":"Supermarket",
            "type":"Retail Goods"
        },
        {
            "category":"Food & Beverages",
            "subcategory":"Groceries & Convenience Stores",
            "type":"Retail Goods"
        }
    ],
    "sg:phone":"+44 131 669 8720",
    "sg:postcode":"EH7 6RN",
    "sg:province":"City of Edinburgh",
    "wof:name":"Craigentinny Bargain Stores",
    "wof:placetype":"venue"
},
  "geometry": {"coordinates":[-3.138306,55.960129],"type":"Point"}
}