{
  "type": "Feature",
  "properties": {
    "iso:country":"GB",
    "sg:address":"116 Bridge Street",
    "sg:city":"Warrington",
    "sg:classifiers":[
        {
            "category":"Restaurant",
            "type":"Food & Drink"
        }
    ],
    "sg:phone":"+44 1925 639895",
    "sg:postcode":"WA1 2RU",
    "sg:province":"Cheshire",
    "sg:tags":[
        "thai"
    ],
    "wof:name":"Sian Galaxy",
    "wof:placetype":"venue"
},
  "geometry": {"coordinates":[-2.5923480988,53.3867835999],"type":"Point"}
}