{
  "type": "Feature",
  "properties": {
    "iso:country":"GB",
    "sg:address":"48 Lower Bond Street",
    "sg:city":"Hinckley",
    "sg:classifiers":[
        {
            "category":"Retail",
            "subcategory":"Funeral Services",
            "type":"Services"
        }
    ],
    "sg:postcode":"LE10 1QU",
    "sg:province":"Leicestershire",
    "wof:name":"A J Murray",
    "wof:placetype":"venue"
},
  "geometry": {"coordinates":[-1.3739880323,52.5436592102],"type":"Point"}
}