{
  "type": "Feature",
  "properties": {
    "iso:country":"GB",
    "sg:address":"House Of Fraser, 140-142 Briggate",
    "sg:city":"Leeds",
    "sg:classifiers":[
        {
            "category":"Shopping",
            "subcategory":"Clothing, Apparel, & Fashions",
            "type":"Retail Goods"
        }
    ],
    "sg:postcode":"LS1 6LS",
    "sg:province":"West Yorkshire",
    "sg:tags":[
        "ladieswear"
    ],
    "wof:name":"Coast",
    "wof:placetype":"venue"
},
  "geometry": {"coordinates":[-1.546587,53.794495],"type":"Point"}
}