{
  "type": "Feature",
  "properties": {
    "iso:country":"GB",
    "sg:address":"82 Bradwell Road, Loughton",
    "sg:city":"Milton Keynes",
    "sg:classifiers":[
        {
            "category":"Retail",
            "subcategory":"Storage",
            "type":"Services"
        }
    ],
    "sg:postcode":"MK5 8AL",
    "sg:province":"Buckinghamshire",
    "sg:tags":[
        "household",
        "removal"
    ],
    "wof:name":"Richard Knight",
    "wof:placetype":"venue"
},
  "geometry": {"coordinates":[-0.783059001,52.033870697],"type":"Point"}
}