{
  "type": "Feature",
  "properties": {
    "iso:country":"GB",
    "sg:address":"28 Cheap Street",
    "sg:city":"Newbury",
    "sg:classifiers":[
        {
            "category":"Shopping",
            "subcategory":"Clothing, Apparel, & Fashions",
            "type":"Retail Goods"
        }
    ],
    "sg:phone":"+44 1635 550012",
    "sg:postcode":"RG14 5DB",
    "sg:province":"Berkshire",
    "sg:tags":[
        "ladieswear"
    ],
    "wof:name":"Sunflower",
    "wof:placetype":"venue"
},
  "geometry": {"coordinates":[-1.322965,51.399658],"type":"Point"}
}