{
  "type": "Feature",
  "properties": {
    "addr:full":"167 Bath Road Bridgwater Somerset TA6 4PP",
    "addr:housenumber":"167",
    "addr:postcode":"ta6 4pp",
    "addr:street":"Bath Road",
    "iso:country":"GB",
    "sg:address":"167 Bath Road",
    "sg:city":"Bridgwater",
    "sg:classifiers":[
        {
            "category":"Shopping",
            "subcategory":"News",
            "type":"Retail Goods"
        }
    ],
    "sg:phone":"+44 1278 424307",
    "sg:postcode":"TA6 4PP",
    "sg:province":"Somerset",
    "sg:tags":[
        "newsagent"
    ],
    "wof:name":"Bath Road News",
    "wof:placetype":"venue"
},
  "geometry": {"coordinates":[-2.9866659641,51.1364974976],"type":"Point"}
}