{
  "type": "Feature",
  "properties": {
    "addr:full":"41 High Street South Dunstable Bedfordshire LU6 3RZ",
    "addr:housenumber":"41",
    "addr:postcode":"lu6 3rz",
    "addr:street":"High Street South",
    "iso:country":"GB",
    "sg:address":"41 High Street South",
    "sg:city":"Dunstable",
    "sg:classifiers":[
        {
            "category":"Fast Food",
            "type":"Food & Drink"
        }
    ],
    "sg:phone":"+44 1582 476476",
    "sg:postcode":"LU6 3RZ",
    "sg:province":"Bedfordshire",
    "sg:tags":[
        "away",
        "take"
    ],
    "wof:name":"Southern Fried Chicken & Pizza Direct",
    "wof:placetype":"venue"
},
  "geometry": {"coordinates":[-0.5189980268,51.8848114014],"type":"Point"}
}