{
  "type": "Feature",
  "properties": {
    "iso:country":"GB",
    "sg:address":"Unit 1, Denton Slipways, Wharf Road",
    "sg:city":"Gravesend",
    "sg:classifiers":[
        {
            "category":"Wholesale",
            "subcategory":"Office Equipment",
            "type":"Manufacturing & Wholesale Goods"
        }
    ],
    "sg:postcode":"DA12 2RW",
    "sg:province":"Kent",
    "sg:tags":[
        "partition",
        "cubicle"
    ],
    "wof:name":"Firco Construction Ltd.",
    "wof:placetype":"venue"
},
  "geometry": {"coordinates":[0.38272,51.443562],"type":"Point"}
}