{
  "type": "Feature",
  "properties": {
    "addr:full":"43 Derwent Drive, Purley Croydon Surrey CR8 1ER",
    "addr:housenumber":"43",
    "addr:postcode":"cr8 1er",
    "addr:street":"Derwent Drive",
    "iso:country":"GB",
    "sg:address":"43 Derwent Drive, Purley",
    "sg:city":"Croydon",
    "sg:classifiers":[
        {
            "category":"Professional",
            "subcategory":"Management & Consulting",
            "type":"Services"
        }
    ],
    "sg:postcode":"CR8 1ER",
    "sg:province":"Surrey",
    "sg:tags":[
        "consultant",
        "business"
    ],
    "wof:name":"Professional Conference Support Group",
    "wof:placetype":"venue"
},
  "geometry": {"coordinates":[-0.0918679982,51.3280639648],"type":"Point"}
}