{
  "type": "Feature",
  "properties": {
    "addr:full":"15 London Road Burgess Hill East Sussex RH15 9QU",
    "addr:housenumber":"15",
    "addr:postcode":"rh15 9qu",
    "addr:street":"London Road",
    "iso:country":"GB",
    "sg:address":"15 London Road",
    "sg:city":"Burgess Hill",
    "sg:classifiers":[
        {
            "category":"Fast Food",
            "type":"Food & Drink"
        }
    ],
    "sg:phone":"+44 1444 236345",
    "sg:postcode":"RH15 9QU",
    "sg:province":"East Sussex",
    "sg:tags":[
        "away",
        "meal",
        "outlet",
        "take"
    ],
    "wof:name":"M Amed & Dursun Twinch",
    "wof:placetype":"venue"
},
  "geometry": {"coordinates":[-0.1393319964,50.9566726685],"type":"Point"}
}