{
  "type": "Feature",
  "properties": {
    "iso:country":"GB",
    "sg:address":"3 Bracken Lea",
    "sg:city":"Chatham",
    "sg:classifiers":[
        {
            "category":"Building & Trades",
            "subcategory":"Construction",
            "type":"Services"
        }
    ],
    "sg:postcode":"ME5 0BZ",
    "sg:province":"Kent",
    "sg:tags":[
        "builder"
    ],
    "wof:name":"Terry E Feist",
    "wof:placetype":"venue"
},
  "geometry": {"coordinates":[0.543397,51.367378],"type":"Point"}
}