{
  "type": "Feature",
  "properties": {
    "addr:full":"275 Commercial Rd London Greater London E1 2PS",
    "addr:housenumber":"275",
    "addr:postcode":"e1 2ps",
    "addr:street":"Commercial Rd",
    "iso:country":"GB",
    "sg:address":"275 Commercial Rd",
    "sg:city":"London",
    "sg:classifiers":[
        {
            "category":"Professional",
            "subcategory":"Lawyer & Legal Services",
            "type":"Services"
        }
    ],
    "sg:postcode":"E1 2PS",
    "sg:province":"Greater London",
    "sg:tags":[
        "solicitor"
    ],
    "wof:name":"Michaels & Co",
    "wof:placetype":"venue"
},
  "geometry": {"coordinates":[-0.0561259985,51.5145225525],"type":"Point"}
}