{
  "type": "Feature",
  "properties": {
    "addr:full":"23 Longbrook Street Exeter Devon EX4 6AD",
    "addr:housenumber":"23",
    "addr:postcode":"ex4 6ad",
    "addr:street":"Longbrook Street",
    "iso:country":"GB",
    "sg:address":"23 Longbrook Street",
    "sg:city":"Exeter",
    "sg:classifiers":[
        {
            "category":"Professional",
            "subcategory":"Accounting & Tax Preparation",
            "type":"Services"
        }
    ],
    "sg:phone":"+44 1392 277325",
    "sg:postcode":"EX4 6AD",
    "sg:province":"Devon",
    "sg:tags":[
        "accountant"
    ],
    "wof:name":"Beer Aplin Ltd.",
    "wof:placetype":"venue"
},
  "geometry": {"coordinates":[-3.5273439884,50.7268638611],"type":"Point"}
}