{
  "type": "Feature",
  "properties": {
    "iso:country":"GB",
    "sg:address":"37 Dunkeld Street",
    "sg:city":"Aberfeldy",
    "sg:classifiers":[
        {
            "category":"Food & Beverages",
            "subcategory":"Bakery",
            "type":"Retail Goods"
        }
    ],
    "sg:phone":"+44 1887 820481",
    "sg:postcode":"PH15 2AF",
    "sg:province":"Perth and Kinross",
    "sg:tags":[
        "shop",
        "baker"
    ],
    "wof:name":"Breadalbane Bakery",
    "wof:placetype":"venue"
},
  "geometry": {"coordinates":[-3.862798,56.620586],"type":"Point"}
}