{
  "type": "Feature",
  "properties": {
    "addr:full":"247 Uppingham Road Leicester Leicestershire LE5 4DG",
    "addr:housenumber":"247",
    "addr:postcode":"le5 4dg",
    "addr:street":"Uppingham Road",
    "iso:country":"GB",
    "sg:address":"247 Uppingham Road",
    "sg:city":"Leicester",
    "sg:classifiers":[
        {
            "category":"Travel",
            "subcategory":"Travel Agent",
            "type":"Entertainment"
        },
        {
            "category":"Retail",
            "subcategory":"Auto Repair",
            "type":"Services"
        }
    ],
    "sg:phone":"+44 116 276 0640",
    "sg:postcode":"LE5 4DG",
    "sg:province":"Leicestershire",
    "sg:tags":[
        "body",
        "car"
    ],
    "wof:name":"Midlands Co-Op Travel",
    "wof:placetype":"venue"
},
  "geometry": {"coordinates":[-1.0897690058,52.6421585083],"type":"Point"}
}