{
  "type": "Feature",
  "properties": {
    "iso:country":"GB",
    "sg:address":"45 Nottingham Street",
    "sg:city":"Melton Mowbray",
    "sg:classifiers":[
        {
            "category":"Shopping",
            "subcategory":"Thrift Store",
            "type":"Retail Goods"
        }
    ],
    "sg:phone":"+44 1664 410099",
    "sg:postcode":"LE13 1NN",
    "sg:province":"Leicestershire",
    "sg:tags":[
        "shop",
        "charity"
    ],
    "wof:name":"Age Concern Shops Ltd.",
    "wof:placetype":"venue"
},
  "geometry": {"coordinates":[-0.8878520131,52.7662620544],"type":"Point"}
}