{
  "type": "Feature",
  "properties": {
    "addr:full":"16 Wedlands Taunton Somerset TA2 7AE",
    "addr:housenumber":"16",
    "addr:postcode":"ta2 7ae",
    "addr:street":"Wedlands",
    "iso:country":"GB",
    "sg:address":"16 Wedlands",
    "sg:city":"Taunton",
    "sg:classifiers":[
        {
            "category":"Shopping",
            "subcategory":"Party Supplies",
            "type":"Retail Goods"
        },
        {
            "category":"Arts & Performance",
            "subcategory":"Music",
            "type":"Entertainment"
        }
    ],
    "sg:phone":"+44 1823 288118",
    "sg:postcode":"TA2 7AE",
    "sg:province":"Somerset",
    "sg:tags":[
        "mobile",
        "operator",
        "disco"
    ],
    "wof:name":"Pandora's Box Roadshow",
    "wof:placetype":"venue"
},
  "geometry": {"coordinates":[-3.1002299786,51.0292816162],"type":"Point"}
}