{
  "type": "Feature",
  "properties": {
    "addr:full":"48 Falstone Dr Chester-le-street Durham DH2 3ST",
    "addr:housenumber":"48",
    "addr:postcode":"dh2 3st",
    "addr:street":"Falstone Dr Chester-Le-Street",
    "iso:country":"GB",
    "sg:address":"48 Falstone Dr",
    "sg:city":"Chester-le-street",
    "sg:classifiers":[
        {
            "category":"Home & Garden",
            "subcategory":"Home Furnishings",
            "type":"Retail Goods"
        }
    ],
    "sg:postcode":"DH2 3ST",
    "sg:province":"Durham",
    "sg:tags":[
        "blind",
        "curtain",
        "fitting"
    ],
    "wof:name":"Fleur Fabrics",
    "wof:placetype":"venue"
},
  "geometry": {"coordinates":[-1.5990630388,54.8470077515],"type":"Point"}
}