{
  "type": "Feature",
  "properties": {
    "addr:full":"Unit 4 Kingsland Court, Three Bridges Road Crawley Surrey RH10 1HL",
    "addr:housenumber":"unit 4",
    "addr:postcode":"rh10 1hl",
    "addr:street":"Kingsland Court Three Bridges Road",
    "iso:country":"GB",
    "sg:address":"Unit 4 Kingsland Court, Three Bridges Road",
    "sg:city":"Crawley",
    "sg:classifiers":[
        {
            "category":"Professional",
            "subcategory":"Computer Services",
            "type":"Services"
        }
    ],
    "sg:phone":"+44 1293 522052",
    "sg:postcode":"RH10 1HL",
    "sg:province":"Surrey",
    "sg:tags":[
        "system",
        "software"
    ],
    "wof:name":"Advanced Topographic Development & Images Ltd.",
    "wof:placetype":"venue"
},
  "geometry": {"coordinates":[-0.1636510044,51.1178741455],"type":"Point"}
}