{
  "type": "Feature",
  "properties": {
    "addr:full":"42 Cheshire Ct Bury Lancashire BL0 0BL",
    "addr:housenumber":"42",
    "addr:postcode":"bl0 0bl",
    "addr:street":"Cheshire Ct",
    "iso:country":"GB",
    "sg:address":"42 Cheshire Ct",
    "sg:city":"Bury",
    "sg:classifiers":[
        {
            "category":"Retail",
            "subcategory":"Driving School",
            "type":"Services"
        }
    ],
    "sg:phone":"+44 161 773 4720",
    "sg:postcode":"BL0 0BL",
    "sg:province":"Lancashire",
    "wof:name":"Flying Lancashire Lass The",
    "wof:placetype":"venue"
},
  "geometry": {"coordinates":[-2.305505991,53.6483802795],"type":"Point"}
}