{
  "type": "Feature",
  "properties": {
    "addr:full":"8 Radley Close Bolton Lancashire BL1 5ND",
    "addr:housenumber":"8",
    "addr:postcode":"bl1 5nd",
    "addr:street":"Radley Close",
    "iso:country":"GB",
    "sg:address":"8 Radley Close",
    "sg:city":"Bolton",
    "sg:classifiers":[
        {
            "category":"Professional",
            "subcategory":"Engineering",
            "type":"Services"
        }
    ],
    "sg:phone":"+44 1204 840111",
    "sg:postcode":"BL1 5ND",
    "sg:province":"Lancashire",
    "sg:tags":[
        "merchant",
        "engineers'"
    ],
    "wof:name":"Machine Tool Supplies Ltd.",
    "wof:placetype":"venue"
},
  "geometry": {"coordinates":[-2.464652,53.587345],"type":"Point"}
}