{
  "type": "Feature",
  "properties": {
    "iso:country":"GB",
    "sg:address":"33 Tombridge Crescent, Kinsley",
    "sg:city":"Pontefract",
    "sg:classifiers":[
        {
            "category":"Building & Trades",
            "subcategory":"Construction",
            "type":"Services"
        }
    ],
    "sg:phone":"+44 1977 616038",
    "sg:postcode":"WF9 5HB",
    "sg:province":"West Yorkshire",
    "sg:tags":[
        "decorator",
        "painter"
    ],
    "wof:name":"John Sayles Decorators",
    "wof:placetype":"venue"
},
  "geometry": {"coordinates":[-1.372668,53.625248],"type":"Point"}
}