{
  "type": "Feature",
  "properties": {
    "addr:full":"2 Oakfield Rd, Penge Penge Greater London SE20 8QT",
    "addr:housenumber":"2",
    "addr:postcode":"se20 8qt",
    "addr:street":"Oakfield Rd",
    "iso:country":"GB",
    "sg:address":"2 Oakfield Rd, Penge",
    "sg:city":"Penge",
    "sg:classifiers":[
        {
            "category":"Bars & Pubs",
            "type":"Food & Drink"
        }
    ],
    "sg:phone":"+44 20 8659 1965",
    "sg:postcode":"SE20 8QT",
    "sg:province":"Greater London",
    "sg:tags":[
        "pubs",
        "inn"
    ],
    "wof:name":"Royal Oak",
    "wof:placetype":"venue"
},
  "geometry": {"coordinates":[-0.0633419976,51.4124641418],"type":"Point"}
}