{
  "type": "Feature",
  "properties": {
    "addr:full":"Waveney, Radfall Road Whitstable Kent CT5 3EN",
    "addr:postcode":"ct5 3en",
    "addr:street":"Radfall Road",
    "iso:country":"GB",
    "sg:address":"Waveney, Radfall Road",
    "sg:city":"Whitstable",
    "sg:classifiers":[
        {
            "category":"Retail",
            "subcategory":"Event Space",
            "type":"Services"
        },
        {
            "category":"Building & Trades",
            "subcategory":"Construction",
            "type":"Services"
        }
    ],
    "sg:phone":"+44 1227 792678",
    "sg:postcode":"CT5 3EN",
    "sg:province":"Kent",
    "sg:tags":[
        "product",
        "joiner",
        "electrical",
        "sales",
        "carpenter"
    ],
    "wof:name":"John Pepper",
    "wof:placetype":"venue"
},
  "geometry": {"coordinates":[1.066809,51.338306],"type":"Point"}
}