{
  "type": "Feature",
  "properties": {
    "iso:country":"GB",
    "sg:address":"Ludwell",
    "sg:city":"Shaftesbury",
    "sg:classifiers":[
        {
            "category":"Travel",
            "subcategory":"Hotels & Motels",
            "type":"Entertainment"
        }
    ],
    "sg:phone":"+44 1747 828365",
    "sg:postcode":"SP7 9ND",
    "sg:province":"Dorset",
    "wof:name":"Grove House Hotel",
    "wof:placetype":"venue"
},
  "geometry": {"coordinates":[-2.128044,51.004456],"type":"Point"}
}