{
  "type": "Feature",
  "properties": {
    "addr:full":"96-96a Hamilton Road Felixstowe Suffolk IP11 7AD",
    "addr:housenumber":"96-96a",
    "addr:postcode":"ip11 7ad",
    "addr:street":"Hamilton Road",
    "iso:country":"GB",
    "sg:address":"96-96a Hamilton Road",
    "sg:city":"Felixstowe",
    "sg:classifiers":[
        {
            "category":"Autos & Motor Vehicles",
            "subcategory":"Auto Supplies",
            "type":"Retail Goods"
        },
        {
            "category":"Shopping",
            "type":"Retail Goods"
        }
    ],
    "sg:phone":"+44 1394 279738",
    "sg:postcode":"IP11 7AD",
    "sg:province":"Suffolk",
    "sg:tags":[
        "car",
        "part",
        "accessory"
    ],
    "sg:website":"http://www.halfords.com",
    "wof:name":"Halfords",
    "wof:placetype":"venue"
},
  "geometry": {"coordinates":[1.352153,51.964092],"type":"Point"}
}