{
  "type": "Feature",
  "properties": {
    "addr:full":"9 Spence Street Edinburgh City of Edinburgh EH16 5AG",
    "addr:housenumber":"9",
    "addr:postcode":"eh16 5ag",
    "addr:street":"Spence Street",
    "iso:country":"GB",
    "sg:address":"9 Spence Street",
    "sg:city":"Edinburgh",
    "sg:classifiers":[
        {
            "category":"Travel",
            "subcategory":"Hotels & Motels",
            "type":"Entertainment"
        }
    ],
    "sg:phone":"+44 131 667 1368",
    "sg:postcode":"EH16 5AG",
    "sg:province":"City of Edinburgh",
    "sg:tags":[
        "house",
        "guest"
    ],
    "sg:website":"http://www.gildun.co.uk",
    "wof:name":"The Gildun",
    "wof:placetype":"venue"
},
  "geometry": {"coordinates":[-3.170429,55.93618],"type":"Point"}
}