{
  "type": "Feature",
  "properties": {
    "addr:full":"203 East Lane Wembley Greater London HA0 3NG",
    "addr:housenumber":"203",
    "addr:postcode":"ha0 3ng",
    "addr:street":"East Lane",
    "iso:country":"GB",
    "sg:address":"203 East Lane",
    "sg:city":"Wembley",
    "sg:classifiers":[
        {
            "category":"Shopping",
            "subcategory":"Pharmacy",
            "type":"Retail Goods"
        }
    ],
    "sg:phone":"+44 20 8904 4197",
    "sg:postcode":"HA0 3NG",
    "sg:province":"Greater London",
    "sg:tags":[
        "pharmacist",
        "dispensing",
        "chemist"
    ],
    "wof:name":"G Lowe Chemist",
    "wof:placetype":"venue"
},
  "geometry": {"coordinates":[-0.3055590093,51.5624961853],"type":"Point"}
}