{
  "type": "Feature",
  "properties": {
    "addr:full":"St. Martins, Lavant Chichester West Sussex PO18 0BG",
    "addr:postcode":"po18 0bg",
    "addr:street":"Lavant",
    "iso:country":"GB",
    "sg:address":"St. Martins, Lavant",
    "sg:city":"Chichester",
    "sg:classifiers":[
        {
            "category":"Health Services",
            "subcategory":"Health Practitioner",
            "type":"Services"
        }
    ],
    "sg:phone":"+44 1243 774473",
    "sg:postcode":"PO18 0BG",
    "sg:province":"West Sussex",
    "sg:tags":[
        "psychologist"
    ],
    "wof:name":"Ron Bracey",
    "wof:placetype":"venue"
},
  "geometry": {"coordinates":[-0.783448,50.866352],"type":"Point"}
}