{
  "type": "Feature",
  "properties": {
    "addr:full":"305 Uxbridge Road, Mill End Rickmansworth Hertfordshire WD3 8DS",
    "addr:housenumber":"305",
    "addr:postcode":"wd3 8ds",
    "addr:street":"Uxbridge Road Mill End",
    "iso:country":"GB",
    "sg:address":"305 Uxbridge Road, Mill End",
    "sg:city":"Rickmansworth",
    "sg:classifiers":[
        {
            "category":"Autos & Motor Vehicles",
            "subcategory":"Automobile Sales",
            "type":"Retail Goods"
        }
    ],
    "sg:postcode":"WD3 8DS",
    "sg:province":"Hertfordshire",
    "sg:tags":[
        "car"
    ],
    "wof:name":"Mill End Motor Co",
    "wof:placetype":"venue"
},
  "geometry": {"coordinates":[-0.5008260012,51.6304512024],"type":"Point"}
}