{
  "type": "Feature",
  "properties": {
    "iso:country":"GB",
    "sg:address":"5/7 Bath Old Rd, Radstock",
    "sg:city":"Bath",
    "sg:classifiers":[
        {
            "category":"Building & Trades",
            "subcategory":"Construction",
            "type":"Services"
        }
    ],
    "sg:postcode":"BA3 3PW",
    "sg:province":"Somerset",
    "sg:tags":[
        "restoration",
        "refurbishment"
    ],
    "wof:name":"Keyford Construction Ltd",
    "wof:placetype":"venue"
},
  "geometry": {"coordinates":[-2.44598,51.293793],"type":"Point"}
}