{
  "type": "Feature",
  "properties": {
    "iso:country":"GB",
    "sg:address":"1st Floor, 12 Church Mews",
    "sg:city":"Knutsford",
    "sg:classifiers":[
        {
            "category":"Professional",
            "subcategory":"Accounting & Tax Preparation",
            "type":"Services"
        }
    ],
    "sg:postcode":"WA16 8HX",
    "sg:province":"Cheshire",
    "sg:tags":[
        "accountant"
    ],
    "wof:name":"Mellor,A D G,",
    "wof:placetype":"venue"
},
  "geometry": {"coordinates":[-2.365623,53.303673],"type":"Point"}
}