{
  "type": "Feature",
  "properties": {
    "addr:full":"Blacketyside Farm Leven Fife KY8 5PX",
    "addr:postcode":"ky8 5px",
    "iso:country":"GB",
    "sg:address":"Blacketyside Farm",
    "sg:city":"Leven",
    "sg:classifiers":[
        {
            "category":"Farming",
            "subcategory":"Livestock Farm",
            "type":"Manufacturing & Wholesale Goods"
        }
    ],
    "sg:phone":"+44 1333 423034",
    "sg:postcode":"KY8 5PX",
    "sg:province":"Fife",
    "sg:tags":[
        "others"
    ],
    "wof:name":"R Todd & Co.",
    "wof:placetype":"venue"
},
  "geometry": {"coordinates":[-3.0381989479,56.2106590271],"type":"Point"}
}