{
  "type": "Feature",
  "properties": {
    "addr:full":"378 Hornsey Road London Greater London N19 4HT",
    "addr:housenumber":"378",
    "addr:postcode":"n19 4ht",
    "addr:street":"Hornsey Road",
    "iso:country":"GB",
    "sg:address":"378 Hornsey Road",
    "sg:city":"London",
    "sg:classifiers":[
        {
            "category":"Health Services",
            "subcategory":"Dentist",
            "type":"Services"
        }
    ],
    "sg:phone":"+44 20 7263 0353",
    "sg:postcode":"N19 4HT",
    "sg:province":"Greater London",
    "wof:name":"A K Haricharin",
    "wof:placetype":"venue"
},
  "geometry": {"coordinates":[-0.1193730012,51.5646324158],"type":"Point"}
}