{
  "type": "Feature",
  "properties": {
    "iso:country":"GB",
    "sg:address":"5 Berkeley Avenue",
    "sg:city":"Chesham",
    "sg:classifiers":[
        {
            "category":"Retail",
            "subcategory":"Auto Repair",
            "type":"Services"
        }
    ],
    "sg:postcode":"HP5 2RN",
    "sg:province":"Buckinghamshire",
    "sg:tags":[
        "modification",
        "garage"
    ],
    "wof:name":"Chiltern Autocare",
    "wof:placetype":"venue"
},
  "geometry": {"coordinates":[-0.625864,51.713051],"type":"Point"}
}