{
  "type": "Feature",
  "properties": {
    "iso:country":"GB",
    "sg:address":"Romans Castle, Tiers Cross",
    "sg:city":"Haverfordwest",
    "sg:classifiers":[
        {
            "category":"Farming",
            "subcategory":"Livestock Farm",
            "type":"Manufacturing & Wholesale Goods"
        }
    ],
    "sg:phone":"+44 1437 890074",
    "sg:postcode":"SA62 3EG",
    "sg:province":"Pembrokeshire",
    "sg:tags":[
        "others"
    ],
    "wof:name":"Stephen C Thomas",
    "wof:placetype":"venue"
},
  "geometry": {"coordinates":[-5.036426,51.755154],"type":"Point"}
}