{
  "type": "Feature",
  "properties": {
    "addr:full":"35 Aigburth Drive Liverpool Merseyside L17 4JE",
    "addr:housenumber":"35",
    "addr:postcode":"l17 4je",
    "addr:street":"Aigburth Drive",
    "iso:country":"GB",
    "sg:address":"35 Aigburth Drive",
    "sg:city":"Liverpool",
    "sg:classifiers":[
        {
            "category":"Travel",
            "subcategory":"Hotels & Motels",
            "type":"Entertainment"
        }
    ],
    "sg:postcode":"L17 4JE",
    "sg:province":"Merseyside",
    "sg:tags":[
        "house",
        "guest"
    ],
    "wof:name":"Evesham Guest House",
    "wof:placetype":"venue"
},
  "geometry": {"coordinates":[-2.9382030964,53.3755645752],"type":"Point"}
}