{
  "type": "Feature",
  "properties": {
    "iso:country":"GB",
    "sg:address":"Cokesford Farm, Tittleshall",
    "sg:city":"King's Lynn",
    "sg:classifiers":[
        {
            "category":"Insurance",
            "subcategory":"Insurance Agent",
            "type":"Services"
        }
    ],
    "sg:phone":"+44 1263 860388",
    "sg:postcode":"PE32 2RQ",
    "sg:province":"Norfolk",
    "sg:tags":[
        "broker"
    ],
    "wof:name":"Cliverton Ltd.",
    "wof:placetype":"venue"
},
  "geometry": {"coordinates":[0.80854,52.75288],"type":"Point"}
}