{
  "type": "Feature",
  "properties": {
    "iso:country":"GB",
    "sg:address":"Davids Fields, Gloucester Road, Staverton",
    "sg:city":"Cheltenham",
    "sg:classifiers":[
        {
            "category":"Home & Garden",
            "subcategory":"Building Materials",
            "type":"Retail Goods"
        }
    ],
    "sg:phone":"+44 1452 855975",
    "sg:postcode":"GL51 0SS",
    "sg:province":"Gloucestershire",
    "sg:tags":[
        "access",
        "equipment"
    ],
    "wof:name":"Miles Robinson Ltd.",
    "wof:placetype":"venue"
},
  "geometry": {"coordinates":[-2.1583740711,51.9068565369],"type":"Point"}
}