{
  "type": "Feature",
  "properties": {
    "addr:full":"176 High Street, Gorleston Great Yarmouth Norfolk NR31 6RG",
    "addr:housenumber":"176",
    "addr:postcode":"nr31 6rg",
    "addr:street":"High Street",
    "iso:country":"GB",
    "sg:address":"176 High Street, Gorleston",
    "sg:city":"Great Yarmouth",
    "sg:classifiers":[
        {
            "category":"Autos & Motor Vehicles",
            "subcategory":"Automobile Sales",
            "type":"Retail Goods"
        }
    ],
    "sg:phone":"+44 1493 662730",
    "sg:postcode":"NR31 6RG",
    "sg:province":"Norfolk",
    "sg:tags":[
        "car"
    ],
    "wof:name":"G T Motors",
    "wof:placetype":"venue"
},
  "geometry": {"coordinates":[1.728481,52.58091],"type":"Point"}
}