{
  "type": "Feature",
  "properties": {
    "addr:full":"Wood Grange, Henfield Road, Cowfold Horsham West Sussex RH13 8DT",
    "addr:postcode":"rh13 8dt",
    "addr:street":"Henfield Road",
    "iso:country":"GB",
    "sg:address":"Wood Grange, Henfield Road, Cowfold",
    "sg:city":"Horsham",
    "sg:classifiers":[
        {
            "category":"Communications",
            "subcategory":"Film & Video Production",
            "type":"Services"
        }
    ],
    "sg:phone":"+44 1403 864786",
    "sg:postcode":"RH13 8DT",
    "sg:province":"West Sussex",
    "sg:tags":[
        "recording",
        "sound",
        "studio"
    ],
    "sg:website":"http://www.811studio.co.uk",
    "wof:name":"811 Studios",
    "wof:placetype":"venue"
},
  "geometry": {"coordinates":[-0.272624,50.990219],"type":"Point"}
}