{
  "type": "Feature",
  "properties": {
    "addr:full":"Castle Way Southampton Hampshire SO14 2AU",
    "addr:postcode":"so14 2au",
    "addr:street":"Castle Way",
    "iso:country":"GB",
    "sg:address":"Castle Way",
    "sg:city":"Southampton",
    "sg:classifiers":[
        {
            "category":"Education",
            "subcategory":"School",
            "type":"Public Place"
        }
    ],
    "sg:phone":"+44 23 8022 6545",
    "sg:postcode":"SO14 2AU",
    "sg:province":"Hampshire",
    "sg:tags":[
        "local",
        "authority"
    ],
    "wof:name":"St John's Infant & Nursery School",
    "wof:placetype":"venue"
},
  "geometry": {"coordinates":[-1.404978,50.901596],"type":"Point"}
}