{
  "type": "Feature",
  "properties": {
    "iso:country":"GB",
    "sg:address":"Units 8, 9-10 Roman Way",
    "sg:city":"Holloway",
    "sg:classifiers":[
        {
            "category":"Home & Garden",
            "subcategory":"Kitchen Supply",
            "type":"Retail Goods"
        }
    ],
    "sg:phone":"+44 20 7700 4582",
    "sg:postcode":"N7 8XH",
    "sg:province":"Greater London",
    "sg:tags":[
        "equipment",
        "bakery"
    ],
    "wof:name":"Donuts & Co",
    "wof:placetype":"venue"
},
  "geometry": {"coordinates":[-0.11423,51.543228],"type":"Point"}
}