{
  "type": "Feature",
  "properties": {
    "addr:full":"18 Upper Shirley Road Croydon Surrey CR0 5EA",
    "addr:housenumber":"18",
    "addr:postcode":"cr0 5ea",
    "addr:street":"Upper Shirley Road",
    "iso:country":"GB",
    "sg:address":"18 Upper Shirley Road",
    "sg:city":"Croydon",
    "sg:classifiers":[
        {
            "category":"Professional",
            "subcategory":"Employment Agencies",
            "type":"Services"
        }
    ],
    "sg:postcode":"CR0 5EA",
    "sg:province":"Surrey",
    "sg:tags":[
        "cv"
    ],
    "wof:name":"Quality C V's",
    "wof:placetype":"venue"
},
  "geometry": {"coordinates":[-0.0556220002,51.3727226257],"type":"Point"}
}