{
  "type": "Feature",
  "properties": {
    "addr:full":"31 Shakespeare Drive, Totton Southampton Hampshire SO40 3NU",
    "addr:housenumber":"31",
    "addr:postcode":"so40 3nu",
    "addr:street":"Shakespeare Drive",
    "iso:country":"GB",
    "sg:address":"31 Shakespeare Drive, Totton",
    "sg:city":"Southampton",
    "sg:classifiers":[
        {
            "category":"Building & Trades",
            "subcategory":"Construction",
            "type":"Services"
        }
    ],
    "sg:phone":"+44 23 8066 3133",
    "sg:postcode":"SO40 3NU",
    "sg:province":"Hampshire",
    "sg:tags":[
        "joiner",
        "carpenter"
    ],
    "wof:name":"C Property Care",
    "wof:placetype":"venue"
},
  "geometry": {"coordinates":[-1.505458951,50.9300422668],"type":"Point"}
}