{
  "type": "Feature",
  "properties": {
    "addr:full":"288 Upper Richmond Road West, East Sheen London Greater London SW14 7JG",
    "addr:housenumber":"288",
    "addr:postcode":"sw14 7jg",
    "addr:street":"Upper Richmond Road West",
    "iso:country":"GB",
    "sg:address":"288 Upper Richmond Road West, East Sheen",
    "sg:city":"London",
    "sg:classifiers":[
        {
            "category":"Professional",
            "subcategory":"Computer Services",
            "type":"Services"
        }
    ],
    "sg:phone":"+44 20 8878 4695",
    "sg:postcode":"SW14 7JG",
    "sg:province":"Greater London",
    "sg:tags":[
        "consultant"
    ],
    "wof:name":"Cobalt Sky Ltd.",
    "wof:placetype":"venue"
},
  "geometry": {"coordinates":[-0.2686670125,51.4644355774],"type":"Point"}
}