{
  "type": "Feature",
  "properties": {
    "addr:full":"Colinton House, Leicester Road Bedworth Warwickshire CV12 8AB",
    "addr:postcode":"cv12 8ab",
    "addr:street":"Leicester Road",
    "iso:country":"GB",
    "sg:address":"Colinton House, Leicester Road",
    "sg:city":"Bedworth",
    "sg:classifiers":[
        {
            "category":"Professional",
            "subcategory":"Accounting & Tax Preparation",
            "type":"Services"
        }
    ],
    "sg:phone":"+44 24 7631 2335",
    "sg:postcode":"CV12 8AB",
    "sg:province":"Warwickshire",
    "sg:tags":[
        "accountant",
        "activity"
    ],
    "wof:name":"Leonard Wilson & Co",
    "wof:placetype":"venue"
},
  "geometry": {"coordinates":[-1.47386,52.484455],"type":"Point"}
}