{
  "type": "Feature",
  "properties": {
    "addr:full":"Hutton Poplars Lodge, Poplar Drive, Hutton Brentwood Essex CM13 1BA",
    "addr:housenumber":"lodge",
    "addr:postcode":"cm13 1ba",
    "addr:street":"Hutton Poplars;Poplar Drive Hutton",
    "iso:country":"GB",
    "sg:address":"Hutton Poplars Lodge, Poplar Drive, Hutton",
    "sg:city":"Brentwood",
    "sg:classifiers":[
        {
            "category":"Organizations",
            "subcategory":"Non-profit Organization",
            "type":"Services"
        }
    ],
    "sg:phone":"+44 1277 214210",
    "sg:postcode":"CM13 1BA",
    "sg:province":"Essex",
    "sg:tags":[
        "charitable",
        "organisation",
        "voluntary",
        "charity"
    ],
    "wof:name":"Batias Independent Advocacy Service",
    "wof:placetype":"venue"
},
  "geometry": {"coordinates":[0.3558380008,51.6332130432],"type":"Point"}
}