{
  "type": "Feature",
  "properties": {
    "iso:country":"GB",
    "sg:address":"12-14 Moss Street, Low Hill",
    "sg:city":"Liverpool",
    "sg:classifiers":[
        {
            "category":"Professional",
            "type":"Services"
        }
    ],
    "sg:phone":"+44 151 263 6472",
    "sg:postcode":"L6 1HF",
    "sg:province":"Merseyside",
    "sg:tags":[
        "auctioneer"
    ],
    "wof:name":"Hartley & Co.",
    "wof:placetype":"venue"
},
  "geometry": {"coordinates":[-2.967749,53.411327],"type":"Point"}
}