{
  "type": "Feature",
  "properties": {
    "addr:full":"Holly Avenue, Worsley Manchester Greater Manchester M28 3DW",
    "addr:postcode":"m28 3dw",
    "addr:street":"Holly Avenue",
    "iso:country":"GB",
    "sg:address":"Holly Avenue, Worsley",
    "sg:city":"Manchester",
    "sg:classifiers":[
        {
            "category":"Education",
            "subcategory":"School",
            "type":"Public Place"
        }
    ],
    "sg:phone":"+44 161 790 4329",
    "sg:postcode":"M28 3DW",
    "sg:province":"Greater Manchester",
    "sg:tags":[
        "local",
        "authority"
    ],
    "wof:name":"Christ the King R C Primary School",
    "wof:placetype":"venue"
},
  "geometry": {"coordinates":[-2.3908190727,53.5219993591],"type":"Point"}
}