{
  "type": "Feature",
  "properties": {
    "iso:country":"GB",
    "sg:address":"Livingston Drive",
    "sg:city":"Liverpool",
    "sg:classifiers":[
        {
            "category":"Place Of Worship",
            "type":"Public Place"
        }
    ],
    "sg:phone":"+44 151 728 8031",
    "sg:postcode":"L17 6AE",
    "sg:province":"Merseyside",
    "wof:name":"Hamlet Baptist Church",
    "wof:placetype":"venue"
},
  "geometry": {"coordinates":[-2.9447870255,53.3790473938],"type":"Point"}
}