{
  "type": "Feature",
  "properties": {
    "addr:full":"Pointer Court, Ashton Road Lancaster Lancashire LA1 4JT",
    "addr:postcode":"la1 4jt",
    "addr:street":"Pointer Court Ashton Road",
    "iso:country":"GB",
    "sg:address":"Pointer Court, Ashton Road",
    "sg:city":"Lancaster",
    "sg:classifiers":[
        {
            "category":"Shopping",
            "subcategory":"Pharmacy",
            "type":"Retail Goods"
        }
    ],
    "sg:phone":"+44 1524 846871",
    "sg:postcode":"LA1 4JT",
    "sg:province":"Lancashire",
    "sg:tags":[
        "store",
        "drug"
    ],
    "wof:name":"T G Maddison Pharmacy",
    "wof:placetype":"venue"
},
  "geometry": {"coordinates":[-2.800474,54.038639],"type":"Point"}
}