{
  "type": "Feature",
  "properties": {
    "iso:country":"GB",
    "sg:address":"2 Lower Bourne Gardens",
    "sg:city":"Ware",
    "sg:classifiers":[
        {
            "category":"Retail",
            "subcategory":"Driving School",
            "type":"Services"
        }
    ],
    "sg:phone":"+44 1920 467798",
    "sg:postcode":"SG12 0BL",
    "sg:province":"Hertfordshire",
    "wof:name":"Ware School Of Motoring",
    "wof:placetype":"venue"
},
  "geometry": {"coordinates":[-0.036802,51.817223],"type":"Point"}
}