{
  "type": "Feature",
  "properties": {
    "addr:full":"Humber Rd London Greater London NW2 6EN",
    "addr:postcode":"nw2 6en",
    "addr:street":"Humber Rd",
    "iso:country":"GB",
    "sg:address":"Humber Rd",
    "sg:city":"London",
    "sg:classifiers":[
        {
            "category":"Professional",
            "subcategory":"Engineering",
            "type":"Services"
        },
        {
            "category":"Building & Trades",
            "subcategory":"Equipment Rental",
            "type":"Services"
        }
    ],
    "sg:phone":"+44 20 8452 0074",
    "sg:postcode":"NW2 6EN",
    "sg:province":"Greater London",
    "sg:tags":[
        "plant",
        "engineer",
        "precision",
        "machinery"
    ],
    "wof:name":"Hydroseal Hire Ltd",
    "wof:placetype":"venue"
},
  "geometry": {"coordinates":[-0.2276490033,51.5670318604],"type":"Point"}
}