{
  "type": "Feature",
  "properties": {
    "iso:country":"GB",
    "sg:address":"Unit B, Edwardson Road, Meadowfield",
    "sg:city":"Durham",
    "sg:classifiers":[
        {
            "category":"Building & Trades",
            "subcategory":"Construction",
            "type":"Services"
        }
    ],
    "sg:phone":"+44 191 384 1788",
    "sg:postcode":"DH7 8RL",
    "sg:province":"Durham",
    "sg:tags":[
        "joiner",
        "carpenter"
    ],
    "wof:name":"Jopling Bros",
    "wof:placetype":"venue"
},
  "geometry": {"coordinates":[-1.622674,54.748734],"type":"Point"}
}