{
  "type": "Feature",
  "properties": {
    "iso:country":"GB",
    "sg:address":"69 Cricklewood Bdwy",
    "sg:city":"London",
    "sg:classifiers":[
        {
            "category":"Home & Garden",
            "subcategory":"Household Appliances",
            "type":"Retail Goods"
        }
    ],
    "sg:phone":"+44 20 8452 8709",
    "sg:postcode":"NW2 3JR",
    "sg:province":"Greater London",
    "sg:tags":[
        "domestic",
        "centre"
    ],
    "wof:name":"The New Cooker Centre Ltd.",
    "wof:placetype":"venue"
},
  "geometry": {"coordinates":[-0.21262,51.554321],"type":"Point"}
}