{
  "type": "Feature",
  "properties": {
    "addr:full":"188 Grange Road, Bermondsey London Greater London SE1 3AA",
    "addr:housenumber":"188",
    "addr:postcode":"se1 3aa",
    "addr:street":"Grange Road",
    "iso:country":"GB",
    "sg:address":"188 Grange Road, Bermondsey",
    "sg:city":"London",
    "sg:classifiers":[
        {
            "category":"Restaurant",
            "type":"Food & Drink"
        }
    ],
    "sg:postcode":"SE1 3AA",
    "sg:province":"Greater London",
    "wof:name":"Grange Cafe & Restaurant",
    "wof:placetype":"venue"
},
  "geometry": {"coordinates":[-0.0788900033,51.4959144592],"type":"Point"}
}