{
  "type": "Feature",
  "properties": {
    "addr:full":"Unit 5 Burnley Retail Park, Curzon Street Burnley Lancashire BB11 1BX",
    "addr:housenumber":"unit 5 burnley retail",
    "addr:postcode":"bb11 1bx",
    "addr:street":"Park Curzon Street",
    "iso:country":"GB",
    "sg:address":"Unit 5 Burnley Retail Park, Curzon Street",
    "sg:city":"Burnley",
    "sg:classifiers":[
        {
            "category":"Home & Garden",
            "subcategory":"Home Furnishings",
            "type":"Retail Goods"
        }
    ],
    "sg:phone":"+44 1282 416292",
    "sg:postcode":"BB11 1BX",
    "sg:province":"Lancashire",
    "sg:tags":[
        "beds",
        "bedding",
        "blanket"
    ],
    "wof:name":"Bensons Bed Centre (Northern) Ltd.",
    "wof:placetype":"venue"
},
  "geometry": {"coordinates":[-2.243809,53.78801],"type":"Point"}
}