{
  "type": "Feature",
  "properties": {
    "addr:full":"32 Brookthorpe Avenue, Burnage Manchester Greater Manchester M19 1AD",
    "addr:housenumber":"32",
    "addr:postcode":"m19 1ad",
    "addr:street":"Brookthorpe Avenue",
    "iso:country":"GB",
    "sg:address":"32 Brookthorpe Avenue, Burnage",
    "sg:city":"Manchester",
    "sg:classifiers":[
        {
            "category":"Building & Trades",
            "subcategory":"Plumbing",
            "type":"Services"
        }
    ],
    "sg:postcode":"M19 1AD",
    "sg:province":"Greater Manchester",
    "sg:tags":[
        "heating"
    ],
    "wof:name":"Ronald Richmond Heating & Plumbing",
    "wof:placetype":"venue"
},
  "geometry": {"coordinates":[-2.2039940357,53.4334373474],"type":"Point"}
}