{
  "type": "Feature",
  "properties": {
    "addr:full":"10-12 Sandwich Road, Whitfield Dover Kent CT16 3LG",
    "addr:housenumber":"10-12",
    "addr:postcode":"ct16 3lg",
    "addr:street":"Sandwich Road;Dover",
    "iso:country":"GB",
    "sg:address":"10-12 Sandwich Road, Whitfield",
    "sg:city":"Dover",
    "sg:classifiers":[
        {
            "category":"Food & Beverages",
            "subcategory":"Meat & Fish",
            "type":"Retail Goods"
        },
        {
            "category":"Food & Beverages",
            "subcategory":"Groceries & Convenience Stores",
            "type":"Retail Goods"
        }
    ],
    "sg:phone":"+44 1304 822277",
    "sg:postcode":"CT16 3LG",
    "sg:province":"Kent",
    "sg:tags":[
        "shop",
        "chip"
    ],
    "wof:name":"Whitfield Fish & Chips",
    "wof:placetype":"venue"
},
  "geometry": {"coordinates":[1.2892940044,51.1557235718],"type":"Point"}
}