{
  "type": "Feature",
  "properties": {
    "addr:full":"3 Gloucester Street Bath Bath and North East Somerset BA1 2SE",
    "addr:housenumber":"3",
    "addr:postcode":"ba1 2se",
    "addr:street":"Gloucester Street",
    "iso:country":"GB",
    "sg:address":"3 Gloucester Street",
    "sg:city":"Bath",
    "sg:classifiers":[
        {
            "category":"Professional",
            "subcategory":"Secretarial Services",
            "type":"Services"
        },
        {
            "category":"Professional",
            "subcategory":"Art Services",
            "type":"Services"
        }
    ],
    "sg:phone":"+44 1225 442552",
    "sg:postcode":"BA1 2SE",
    "sg:province":"Bath and North East Somerset",
    "sg:tags":[
        "photographer"
    ],
    "wof:name":"Gloucester Street Services",
    "wof:placetype":"venue"
},
  "geometry": {"coordinates":[-2.3643960953,51.3878440857],"type":"Point"}
}