{
  "type": "Feature",
  "properties": {
    "iso:country":"GB",
    "sg:address":"50 Fernhill Road",
    "sg:city":"Bootle",
    "sg:classifiers":[
        {
            "category":"Retail",
            "subcategory":"Emissions Testing",
            "type":"Services"
        },
        {
            "category":"Professional",
            "subcategory":"Testing Lab",
            "type":"Services"
        }
    ],
    "sg:phone":"+44 151 933 3234",
    "sg:postcode":"L20 9HH",
    "sg:province":"Merseyside",
    "sg:tags":[
        "mot"
    ],
    "wof:name":"FERNHILL MOTORS",
    "wof:placetype":"venue"
},
  "geometry": {"coordinates":[-2.979757,53.456165],"type":"Point"}
}