{
  "type": "Feature",
  "properties": {
    "iso:country":"GB",
    "sg:address":"18 Grafton Avenue",
    "sg:city":"Rochester",
    "sg:classifiers":[
        {
            "category":"Building & Trades",
            "subcategory":"Construction",
            "type":"Services"
        }
    ],
    "sg:phone":"+44 1634 813879",
    "sg:postcode":"ME1 2RP",
    "sg:province":"Kent",
    "sg:tags":[
        "roofing",
        "contracting"
    ],
    "wof:name":"Browns",
    "wof:placetype":"venue"
},
  "geometry": {"coordinates":[0.513107,51.364811],"type":"Point"}
}