{
  "type": "Feature",
  "properties": {
    "addr:full":"Curuian Vale, Nanpean St Austell Cornwall PL26 7XG",
    "addr:postcode":"pl26 7xg",
    "addr:street":"Curuian;Nanpean",
    "iso:country":"GB",
    "sg:address":"Curuian Vale, Nanpean",
    "sg:city":"St Austell",
    "sg:classifiers":[
        {
            "category":"Freight",
            "type":"Transportation"
        }
    ],
    "sg:phone":"+44 1726 822461",
    "sg:postcode":"PL26 7XG",
    "sg:province":"Cornwall",
    "sg:tags":[
        "haulage",
        "road"
    ],
    "wof:name":"G Julian Haulage",
    "wof:placetype":"venue"
},
  "geometry": {"coordinates":[-4.870201,50.369648],"type":"Point"}
}