{
  "type": "Feature",
  "properties": {
    "addr:full":"80 Ducks Hill Rd Northwood Greater London HA6 2SD",
    "addr:housenumber":"80",
    "addr:postcode":"ha6 2sd",
    "addr:street":"Ducks Hill Rd",
    "iso:country":"GB",
    "sg:address":"80 Ducks Hill Rd",
    "sg:city":"Northwood",
    "sg:classifiers":[
        {
            "category":"Professional",
            "subcategory":"Engineering",
            "type":"Services"
        }
    ],
    "sg:postcode":"HA6 2SD",
    "sg:province":"Greater London",
    "sg:tags":[
        "contractor",
        "electrical",
        "engineer"
    ],
    "wof:name":"Grant Marshall",
    "wof:placetype":"venue"
},
  "geometry": {"coordinates":[-0.441801,51.608837],"type":"Point"}
}