{
  "type": "Feature",
  "properties": {
    "iso:country":"GB",
    "sg:address":"13 Hull Road",
    "sg:city":"York",
    "sg:classifiers":[
        {
            "category":"Recreation",
            "subcategory":"Fishing",
            "type":"Entertainment"
        }
    ],
    "sg:phone":"+44 1904 411210",
    "sg:postcode":"YO1 3JL",
    "sg:province":"North Yorkshire",
    "sg:tags":[
        "angling"
    ],
    "wof:name":"York Tackle Shop",
    "wof:placetype":"venue"
},
  "geometry": {"coordinates":[-1.058288,53.954239],"type":"Point"}
}