{
  "type": "Feature",
  "properties": {
    "addr:full":"Norwich Road Swaffham Norfolk PE37 7QS",
    "addr:postcode":"pe37 7qs",
    "addr:street":"Norwich Road",
    "iso:country":"GB",
    "sg:address":"Norwich Road",
    "sg:city":"Swaffham",
    "sg:classifiers":[
        {
            "category":"Travel",
            "subcategory":"Hotels & Motels",
            "type":"Entertainment"
        }
    ],
    "sg:phone":"+44 1760 723355",
    "sg:postcode":"PE37 7QS",
    "sg:province":"Norfolk",
    "wof:name":"Lydney House Hotel",
    "wof:placetype":"venue"
},
  "geometry": {"coordinates":[0.6922150254,52.6484031677],"type":"Point"}
}