{
  "type": "Feature",
  "properties": {
    "addr:full":"22 Faircross Avenue Barking Essex IG11 8RD",
    "addr:housenumber":"22",
    "addr:postcode":"ig11 8rd",
    "addr:street":"Faircross Avenue",
    "iso:country":"GB",
    "sg:address":"22 Faircross Avenue",
    "sg:city":"Barking",
    "sg:classifiers":[
        {
            "category":"Banks & Credit Unions",
            "subcategory":"Financial Services",
            "type":"Services"
        }
    ],
    "sg:postcode":"IG11 8RD",
    "sg:province":"Essex",
    "sg:tags":[
        "consultant"
    ],
    "wof:name":"Isbjorn Ltd",
    "wof:placetype":"venue"
},
  "geometry": {"coordinates":[0.083462,51.541969],"type":"Point"}
}