{
  "type": "Feature",
  "properties": {
    "addr:full":"13 Manchester Road Buxton Derbyshire SK17 6TQ",
    "addr:housenumber":"13",
    "addr:postcode":"sk17 6tq",
    "addr:street":"Manchester Road",
    "iso:country":"GB",
    "sg:address":"13 Manchester Road",
    "sg:city":"Buxton",
    "sg:classifiers":[
        {
            "category":"Travel",
            "subcategory":"Hotels & Motels",
            "type":"Entertainment"
        }
    ],
    "sg:phone":"+44 1298 23002",
    "sg:postcode":"SK17 6TQ",
    "sg:province":"Derbyshire",
    "wof:name":"Leewood Hotel",
    "wof:placetype":"venue"
},
  "geometry": {"coordinates":[-1.920113,53.261658],"type":"Point"}
}