{
  "type": "Feature",
  "properties": {
    "iso:country":"GB",
    "sg:address":"Chapel St, Church Gresley",
    "sg:city":"Swadlincote",
    "sg:classifiers":[
        {
            "category":"Education",
            "subcategory":"Dance Studio",
            "type":"Public Place"
        }
    ],
    "sg:phone":"+44 1283 212332",
    "sg:postcode":"DE11 9LX",
    "sg:province":"Derbyshire",
    "sg:tags":[
        "school",
        "dancing"
    ],
    "wof:name":"Joan Ross School Of Dancing",
    "wof:placetype":"venue"
},
  "geometry": {"coordinates":[-1.566809,52.760155],"type":"Point"}
}