{
  "type": "Feature",
  "properties": {
    "iso:country":"GB",
    "sg:address":"Berrys Lane, Burghfield",
    "sg:city":"Reading",
    "sg:classifiers":[
        {
            "category":"Manufacturing",
            "subcategory":"Electronics",
            "type":"Manufacturing & Wholesale Goods"
        }
    ],
    "sg:postcode":"RG30 3XD",
    "sg:province":"Berkshire",
    "sg:tags":[
        "printed",
        "circuit"
    ],
    "wof:name":"Ace Pcb Design",
    "wof:placetype":"venue"
},
  "geometry": {"coordinates":[-1.0257220268,51.4253501892],"type":"Point"}
}