{
  "type": "Feature",
  "properties": {
    "addr:full":"1 Duke Street Millom Cumbria LA18 5BB",
    "addr:housenumber":"1",
    "addr:postcode":"la18 5bb",
    "addr:street":"Duke Street",
    "iso:country":"GB",
    "sg:address":"1 Duke Street",
    "sg:city":"Millom",
    "sg:classifiers":[
        {
            "category":"Retail",
            "subcategory":"Auto Repair",
            "type":"Services"
        }
    ],
    "sg:phone":"+44 1229 773771",
    "sg:postcode":"LA18 5BB",
    "sg:province":"Cumbria",
    "sg:tags":[
        "modification",
        "garage",
        "related"
    ],
    "wof:name":"Whartons Garage Ltd.",
    "wof:placetype":"venue"
},
  "geometry": {"coordinates":[-3.2727890015,54.2113037109],"type":"Point"}
}