{
  "type": "Feature",
  "properties": {
    "iso:country":"GB",
    "sg:address":"70 Wilcot Rd",
    "sg:city":"Pewsey",
    "sg:classifiers":[
        {
            "category":"Retail",
            "subcategory":"Veterinary Services",
            "type":"Services"
        }
    ],
    "sg:phone":"+44 1672 563646",
    "sg:postcode":"SN9 5EL",
    "sg:province":"Wiltshire",
    "sg:tags":[
        "surgeon"
    ],
    "wof:name":"Belmont House Veterinary Surgery",
    "wof:placetype":"venue"
},
  "geometry": {"coordinates":[-1.771066,51.341034],"type":"Point"}
}