{
  "type": "Feature",
  "properties": {
    "addr:full":"Halwell Totnes Devon TQ9 7LE",
    "addr:postcode":"tq9 7le",
    "iso:country":"GB",
    "sg:address":"Halwell",
    "sg:city":"Totnes",
    "sg:classifiers":[
        {
            "category":"Travel",
            "subcategory":"Hotels & Motels",
            "type":"Entertainment"
        }
    ],
    "sg:phone":"+44 1803 732255",
    "sg:postcode":"TQ9 7LE",
    "sg:province":"Devon",
    "sg:tags":[
        "self",
        "catering"
    ],
    "wof:name":"Higher Poulston Farm",
    "wof:placetype":"venue"
},
  "geometry": {"coordinates":[-3.7209119797,50.3659896851],"type":"Point"}
}