{
  "type": "Feature",
  "properties": {
    "addr:full":"10 Nasmyth Row, Elsecar Heritage Centre Barnsley South Yorkshire S74 8HJ",
    "addr:housenumber":"10",
    "addr:postcode":"s74 8hj",
    "addr:street":"Nasmyth Row Elsecar;Yorkshire",
    "iso:country":"GB",
    "sg:address":"10 Nasmyth Row, Elsecar Heritage Centre",
    "sg:city":"Barnsley",
    "sg:classifiers":[
        {
            "category":"Wholesale",
            "subcategory":"Chemicals & Plastics",
            "type":"Manufacturing & Wholesale Goods"
        }
    ],
    "sg:postcode":"S74 8HJ",
    "sg:province":"South Yorkshire",
    "sg:tags":[
        "supplier",
        "w'sale",
        "perfume"
    ],
    "wof:name":"Capella Altair Ltd",
    "wof:placetype":"venue"
},
  "geometry": {"coordinates":[-1.4186500311,53.4962348938],"type":"Point"}
}