{
  "type": "Feature",
  "properties": {
    "addr:full":"South Bar Banbury Oxfordshire OX16 9AE",
    "addr:postcode":"ox16 9ae",
    "iso:country":"GB",
    "sg:address":"South Bar",
    "sg:city":"Banbury",
    "sg:classifiers":[
        {
            "category":"Place Of Worship",
            "type":"Public Place"
        }
    ],
    "sg:phone":"+44 1295 262073",
    "sg:postcode":"OX16 9AE",
    "sg:province":"Oxfordshire",
    "wof:name":"St Johns RC Church",
    "wof:placetype":"venue"
},
  "geometry": {"coordinates":[-1.3409399986,52.0584411621],"type":"Point"}
}