{
  "type": "Feature",
  "properties": {
    "addr:full":"160 Cromwell Road Grimsby Lincolnshire DN31 2BA",
    "addr:housenumber":"160",
    "addr:postcode":"dn31 2ba",
    "addr:street":"Cromwell Road",
    "iso:country":"GB",
    "sg:address":"160 Cromwell Road",
    "sg:city":"Grimsby",
    "sg:classifiers":[
        {
            "category":"Shopping",
            "subcategory":"Pets & Pet Supplies",
            "type":"Retail Goods"
        }
    ],
    "sg:postcode":"DN31 2BA",
    "sg:province":"Lincolnshire",
    "wof:name":"Cromwell Pet Stores",
    "wof:placetype":"venue"
},
  "geometry": {"coordinates":[-0.102125,53.565983],"type":"Point"}
}