{
  "type": "Feature",
  "properties": {
    "addr:full":"3 Bond Street Cromer Norfolk NR27 9DA",
    "addr:housenumber":"3",
    "addr:postcode":"nr27 9da",
    "addr:street":"Bond Street",
    "iso:country":"GB",
    "sg:address":"3 Bond Street",
    "sg:city":"Cromer",
    "sg:classifiers":[
        {
            "category":"Real Estate",
            "subcategory":"Architect",
            "type":"Services"
        }
    ],
    "sg:phone":"+44 1263 513868",
    "sg:postcode":"NR27 9DA",
    "sg:province":"Norfolk",
    "sg:tags":[
        "technologist",
        "architectural"
    ],
    "wof:name":"Famebyte Ltd.",
    "wof:placetype":"venue"
},
  "geometry": {"coordinates":[1.301542,52.930801],"type":"Point"}
}