{
  "type": "Feature",
  "properties": {
    "addr:full":"Yew Tree House, Wharf Rd, Biddulph Stoke On Trent Staffordshire ST8 6AQ",
    "addr:postcode":"st8 6aq",
    "addr:street":"Yew;Wharf Rd",
    "iso:country":"GB",
    "sg:address":"Yew Tree House, Wharf Rd, Biddulph",
    "sg:city":"Stoke On Trent",
    "sg:classifiers":[
        {
            "category":"Health Services",
            "subcategory":"Dentist",
            "type":"Services"
        }
    ],
    "sg:phone":"+44 1782 515805",
    "sg:postcode":"ST8 6AQ",
    "sg:province":"Staffordshire",
    "wof:name":"A.J Wolverson",
    "wof:placetype":"venue"
},
  "geometry": {"coordinates":[-2.176175,53.116741],"type":"Point"}
}