{
  "type": "Feature",
  "properties": {
    "iso:country":"GB",
    "sg:address":"156a Chiswick High Road",
    "sg:city":"London",
    "sg:classifiers":[
        {
            "category":"Restaurant",
            "type":"Food & Drink"
        }
    ],
    "sg:phone":"+44 20 8995 1398",
    "sg:postcode":"W4 1PR",
    "sg:province":"Greater London",
    "sg:tags":[
        "french"
    ],
    "wof:name":"Streamgift Ltd.",
    "wof:placetype":"venue"
},
  "geometry": {"coordinates":[-0.254653,51.492859],"type":"Point"}
}