{
  "type": "Feature",
  "properties": {
    "addr:full":"4 Trumpington Street Cambridge Cambridgeshire CB2 1QA",
    "addr:housenumber":"4",
    "addr:postcode":"cb2 1qa",
    "addr:street":"Trumpington Street",
    "iso:country":"GB",
    "sg:address":"4 Trumpington Street",
    "sg:city":"Cambridge",
    "sg:classifiers":[
        {
            "category":"Cafe",
            "type":"Food & Drink"
        }
    ],
    "sg:phone":"+44 1223 361757",
    "sg:postcode":"CB2 1QA",
    "sg:province":"Cambridgeshire",
    "sg:tags":[
        "tea",
        "snack",
        "bar",
        "room"
    ],
    "wof:name":"Martin's Coffee House",
    "wof:placetype":"venue"
},
  "geometry": {"coordinates":[0.122043,52.198387],"type":"Point"}
}