{
  "type": "Feature",
  "properties": {
    "addr:full":"48 All Saints Road Cheltenham Gloucestershire GL52 2HA",
    "addr:housenumber":"48",
    "addr:postcode":"gl52 2ha",
    "addr:street":"All Saints Road",
    "iso:country":"GB",
    "sg:address":"48 All Saints Road",
    "sg:city":"Cheltenham",
    "sg:classifiers":[
        {
            "category":"Building & Trades",
            "subcategory":"Plumbing",
            "type":"Services"
        }
    ],
    "sg:phone":"+44 1242 238991",
    "sg:postcode":"GL52 2HA",
    "sg:province":"Gloucestershire",
    "sg:tags":[
        "plumber",
        "heating"
    ],
    "wof:name":"M R Whittaker",
    "wof:placetype":"venue"
},
  "geometry": {"coordinates":[-2.065151,51.901382],"type":"Point"}
}