{
  "type": "Feature",
  "properties": {
    "addr:full":"Patricia Way, Pysons Road Broadstairs Kent CT10 2XZ",
    "addr:postcode":"ct10 2xz",
    "addr:street":"Patricia Way Pysons Road",
    "iso:country":"GB",
    "sg:address":"Patricia Way, Pysons Road",
    "sg:city":"Broadstairs",
    "sg:classifiers":[
        {
            "category":"Manufacturing",
            "subcategory":"Signs",
            "type":"Manufacturing & Wholesale Goods"
        }
    ],
    "sg:phone":"+44 1843 601075",
    "sg:postcode":"CT10 2XZ",
    "sg:province":"Kent",
    "sg:tags":[
        "nameplate"
    ],
    "wof:name":"Blaze Neon Ltd.",
    "wof:placetype":"venue"
},
  "geometry": {"coordinates":[1.4125560522,51.3559341431],"type":"Point"}
}