{
  "type": "Feature",
  "properties": {
    "iso:country":"GB",
    "sg:address":"Preston School, Monks Dale",
    "sg:city":"Yeovil",
    "sg:classifiers":[
        {
            "category":"Farming",
            "subcategory":"Nursery",
            "type":"Manufacturing & Wholesale Goods"
        }
    ],
    "sg:phone":"+44 1935 433365",
    "sg:postcode":"BA21 3JD",
    "sg:province":"Somerset",
    "sg:tags":[
        "creche"
    ],
    "wof:name":"Jane Bowdich",
    "wof:placetype":"venue"
},
  "geometry": {"coordinates":[-2.639292,50.948441],"type":"Point"}
}