{
  "type": "Feature",
  "properties": {
    "iso:country":"GB",
    "sg:address":"8 Market Square, Farley Hill",
    "sg:city":"Luton",
    "sg:classifiers":[
        {
            "category":"Food & Beverages",
            "subcategory":"Fruits & Vegetables",
            "type":"Retail Goods"
        }
    ],
    "sg:phone":"+44 1582 724597",
    "sg:postcode":"LU1 5HJ",
    "sg:province":"Bedfordshire",
    "sg:tags":[
        "greengrocer"
    ],
    "wof:name":"Baldwins Greengrocers",
    "wof:placetype":"venue"
},
  "geometry": {"coordinates":[-0.4386770129,51.8750267029],"type":"Point"}
}