{
  "type": "Feature",
  "properties": {
    "addr:full":"Unit 7, Millfield House, Woodshots Meadow Watford Hertfordshire WD18 8YX",
    "addr:housenumber":"unit 7 millfield house woodshots",
    "addr:postcode":"wd18 8yx",
    "addr:street":"Meadow",
    "iso:country":"GB",
    "sg:address":"Unit 7, Millfield House, Woodshots Meadow",
    "sg:city":"Watford",
    "sg:classifiers":[
        {
            "category":"Manufacturing",
            "subcategory":"Tools & Machinery",
            "type":"Manufacturing & Wholesale Goods"
        }
    ],
    "sg:phone":"+44 1923 256262",
    "sg:postcode":"WD18 8YX",
    "sg:province":"Hertfordshire",
    "wof:name":"Amada United Kingdom Ltd.",
    "wof:placetype":"venue"
},
  "geometry": {"coordinates":[-0.4290690124,51.6478118896],"type":"Point"}
}