{
  "type": "Feature",
  "properties": {
    "addr:full":"28 Hazel Walk Bromley Kent BR2 8DF",
    "addr:housenumber":"28",
    "addr:postcode":"br2 8df",
    "addr:street":"Hazel Walk",
    "iso:country":"GB",
    "sg:address":"28 Hazel Walk",
    "sg:city":"Bromley",
    "sg:classifiers":[
        {
            "category":"Personal",
            "subcategory":"Beauty Salon",
            "type":"Services"
        }
    ],
    "sg:postcode":"BR2 8DF",
    "sg:province":"Kent",
    "sg:tags":[
        "unisex",
        "hairdresser"
    ],
    "wof:name":"C Egan",
    "wof:placetype":"venue"
},
  "geometry": {"coordinates":[0.058308,51.384647],"type":"Point"}
}