{
  "type": "Feature",
  "properties": {
    "addr:full":"17 Tower Row, Drummond Rd Skegness Lincolnshire PE25 3EA",
    "addr:housenumber":"17",
    "addr:postcode":"pe25 3ea",
    "addr:street":"Tower Row Drummond Rd",
    "iso:country":"GB",
    "sg:address":"17 Tower Row, Drummond Rd",
    "sg:city":"Skegness",
    "sg:classifiers":[
        {
            "category":"Communications",
            "subcategory":"Newspaper",
            "type":"Services"
        }
    ],
    "sg:phone":"+44 1754 611123",
    "sg:postcode":"PE25 3EA",
    "sg:province":"Lincolnshire",
    "sg:tags":[
        "magazine"
    ],
    "wof:name":"Skegness Target Newspaper",
    "wof:placetype":"venue"
},
  "geometry": {"coordinates":[0.3370000124,53.1452713013],"type":"Point"}
}