{
  "type": "Feature",
  "properties": {
    "addr:full":"196 Station Road Addlestone Surrey KT15 2PD",
    "addr:housenumber":"196",
    "addr:postcode":"kt15 2pd",
    "addr:street":"Station Road",
    "iso:country":"GB",
    "sg:address":"196 Station Road",
    "sg:city":"Addlestone",
    "sg:classifiers":[
        {
            "category":"Shopping",
            "subcategory":"Department Store",
            "type":"Retail Goods"
        }
    ],
    "sg:phone":"+44 1932 857776",
    "sg:postcode":"KT15 2PD",
    "sg:province":"Surrey",
    "wof:name":"Archive Records",
    "wof:placetype":"venue"
},
  "geometry": {"coordinates":[-0.484145999,51.3727111816],"type":"Point"}
}