{
  "type": "Feature",
  "properties": {
    "addr:full":"127-129 King Street Castle Douglas Dumfries and Galloway DG7 1LZ",
    "addr:housenumber":"127-129",
    "addr:postcode":"dg7 1lz",
    "addr:street":"King Street",
    "iso:country":"GB",
    "sg:address":"127-129 King Street",
    "sg:city":"Castle Douglas",
    "sg:classifiers":[
        {
            "category":"Shopping",
            "subcategory":"Clothing, Apparel, & Fashions",
            "type":"Retail Goods"
        }
    ],
    "sg:phone":"+44 1556 502532",
    "sg:postcode":"DG7 1LZ",
    "sg:province":"Dumfries and Galloway",
    "sg:tags":[
        "shop"
    ],
    "wof:name":"Mackays Stores Ltd.",
    "wof:placetype":"venue"
},
  "geometry": {"coordinates":[-3.9300711155,54.9403686523],"type":"Point"}
}