{
  "type": "Feature",
  "properties": {
    "addr:full":"207 Witton Rd Birmingham West Midlands B6 6JR",
    "addr:housenumber":"207",
    "addr:postcode":"b6 6jr",
    "addr:street":"Witton Rd",
    "iso:country":"GB",
    "sg:address":"207 Witton Rd",
    "sg:city":"Birmingham",
    "sg:classifiers":[
        {
            "category":"Professional",
            "subcategory":"Accounting & Tax Preparation",
            "type":"Services"
        }
    ],
    "sg:phone":"+44 121 327 3284",
    "sg:postcode":"B6 6JR",
    "sg:province":"West Midlands",
    "sg:tags":[
        "accountant"
    ],
    "wof:name":"Aston Accountancy Services",
    "wof:placetype":"venue"
},
  "geometry": {"coordinates":[-1.891684,52.507912],"type":"Point"}
}