{
  "type": "Feature",
  "properties": {
    "iso:country":"GB",
    "sg:address":"The Lodge, Garthmyl Hall, Garthmyl",
    "sg:city":"Montgomery",
    "sg:classifiers":[
        {
            "category":"Shopping",
            "subcategory":"Pets & Pet Supplies",
            "type":"Retail Goods"
        }
    ],
    "sg:phone":"+44 1686 640385",
    "sg:postcode":"SY15 6RS",
    "sg:province":"Shropshire",
    "sg:tags":[
        "food"
    ],
    "wof:name":"C D Crowe",
    "wof:placetype":"venue"
},
  "geometry": {"coordinates":[-3.1464788914,52.5635643005],"type":"Point"}
}