{
  "type": "Feature",
  "properties": {
    "iso:country":"GB",
    "sg:address":"7 The Rickyard, Clifton Reynes",
    "sg:city":"Olney",
    "sg:classifiers":[
        {
            "category":"Professional",
            "subcategory":"Management & Consulting",
            "type":"Services"
        }
    ],
    "sg:phone":"+44 1234 240055",
    "sg:postcode":"MK46 5LQ",
    "sg:province":"Buckinghamshire",
    "sg:tags":[
        "consultant",
        "energy",
        "conservation"
    ],
    "wof:name":"Dragon Energy Systems Ltd.",
    "wof:placetype":"venue"
},
  "geometry": {"coordinates":[-0.68045,52.152237],"type":"Point"}
}