{
  "type": "Feature",
  "properties": {
    "iso:country":"GB",
    "sg:address":"18 Grange Road",
    "sg:city":"Wellingborough",
    "sg:classifiers":[
        {
            "category":"Personal",
            "type":"Services"
        }
    ],
    "sg:phone":"+44 1933 460308",
    "sg:postcode":"NN9 6PZ",
    "sg:province":"Northamptonshire",
    "sg:tags":[
        "wedding"
    ],
    "wof:name":"Satin & Lace of Stanwick",
    "wof:placetype":"venue"
},
  "geometry": {"coordinates":[-0.5620589852,52.3300743103],"type":"Point"}
}