{
  "type": "Feature",
  "properties": {
    "iso:country":"GB",
    "sg:address":"Verdemar House, 230 Park View",
    "sg:city":"Whitley Bay",
    "sg:classifiers":[
        {
            "category":"Communications",
            "subcategory":"Radio Station",
            "type":"Services"
        }
    ],
    "sg:postcode":"NE26 3QR",
    "sg:province":"Northumberland",
    "sg:tags":[
        "consultant",
        "medium"
    ],
    "wof:name":"Ether Interactive Ltd",
    "wof:placetype":"venue"
},
  "geometry": {"coordinates":[-1.451984,55.045193],"type":"Point"}
}