{
  "type": "Feature",
  "properties": {
    "addr:full":"22 Joseph St Manchester Greater Manchester M26 1JX",
    "addr:housenumber":"22",
    "addr:postcode":"m26 1jx",
    "addr:street":"Joseph St",
    "iso:country":"GB",
    "sg:address":"22 Joseph St",
    "sg:city":"Manchester",
    "sg:classifiers":[
        {
            "category":"Professional",
            "type":"Services"
        }
    ],
    "sg:phone":"+44 161 723 4048",
    "sg:postcode":"M26 1JX",
    "sg:province":"Greater Manchester",
    "sg:tags":[
        "caterer"
    ],
    "wof:name":"Karlisas Catering",
    "wof:placetype":"venue"
},
  "geometry": {"coordinates":[-2.3221969604,53.5560798645],"type":"Point"}
}