{
  "type": "Feature",
  "properties": {
    "addr:full":"5 Payn Close, Hemingford Grey Huntingdon Bedfordshire PE28 9WL",
    "addr:housenumber":"5",
    "addr:postcode":"pe28 9wl",
    "addr:street":"Payn Close Hemingford Grey",
    "iso:country":"GB",
    "sg:address":"5 Payn Close, Hemingford Grey",
    "sg:city":"Huntingdon",
    "sg:classifiers":[
        {
            "category":"Banks & Credit Unions",
            "subcategory":"Bank",
            "type":"Services"
        },
        {
            "category":"Professional",
            "subcategory":"Business Services",
            "type":"Services"
        }
    ],
    "sg:phone":"+44 1480 466877",
    "sg:postcode":"PE28 9WL",
    "sg:province":"Bedfordshire",
    "sg:tags":[
        "stocktaking",
        "inventory"
    ],
    "wof:name":"D J Mercer & Co",
    "wof:placetype":"venue"
},
  "geometry": {"coordinates":[-0.1036249995,52.3145561218],"type":"Point"}
}