{
  "type": "Feature",
  "properties": {
    "addr:full":"30 Cowley Road, Littlemore Oxford Oxfordshire OX4 4LD",
    "addr:housenumber":"30",
    "addr:postcode":"ox4 4ld",
    "addr:street":"Cowley Road",
    "iso:country":"GB",
    "sg:address":"30 Cowley Road, Littlemore",
    "sg:city":"Oxford",
    "sg:classifiers":[
        {
            "category":"Home & Garden",
            "subcategory":"Kitchen Supply",
            "type":"Retail Goods"
        }
    ],
    "sg:phone":"+44 1865 778136",
    "sg:postcode":"OX4 4LD",
    "sg:province":"Oxfordshire",
    "sg:tags":[
        "equipment",
        "catering"
    ],
    "wof:name":"Taylors Catering Equipment Ltd",
    "wof:placetype":"venue"
},
  "geometry": {"coordinates":[-1.220873,51.723366],"type":"Point"}
}