{
  "type": "Feature",
  "properties": {
    "iso:country":"GB",
    "sg:address":"20 Grove Rd",
    "sg:city":"Colwyn Bay",
    "sg:classifiers":[
        {
            "category":"Retail",
            "subcategory":"Auto Repair",
            "type":"Services"
        }
    ],
    "sg:phone":"+44 1492 532227",
    "sg:postcode":"LL29 8ER",
    "sg:province":"Conwy",
    "sg:tags":[
        "body",
        "car"
    ],
    "wof:name":"Autohous Body",
    "wof:placetype":"venue"
},
  "geometry": {"coordinates":[-3.7216858864,53.2933540344],"type":"Point"}
}