{
  "type": "Feature",
  "properties": {
    "addr:full":"33 Devonshire Arcade, Devonshire Street Penrith Cumbria CA11 7SS",
    "addr:housenumber":"33;arcade",
    "addr:postcode":"ca11 7ss",
    "addr:street":"Devonshire;Devonshire Street",
    "iso:country":"GB",
    "sg:address":"33 Devonshire Arcade, Devonshire Street",
    "sg:city":"Penrith",
    "sg:classifiers":[
        {
            "category":"Shopping",
            "subcategory":"Florist",
            "type":"Retail Goods"
        }
    ],
    "sg:phone":"+44 1768 891717",
    "sg:postcode":"CA11 7SS",
    "sg:province":"Cumbria",
    "wof:name":"Flower Designs",
    "wof:placetype":"venue"
},
  "geometry": {"coordinates":[-2.7574689388,54.6643028259],"type":"Point"}
}