{
  "type": "Feature",
  "properties": {
    "addr:full":"Shawsdale Road (firs Estate), Castle Bromwich Birmingham West Midlands B36 8NG",
    "addr:postcode":"b36 8ng",
    "addr:street":"Shawsdale Road Firs Estate",
    "iso:country":"GB",
    "sg:address":"Shawsdale Road (firs Estate), Castle Bromwich",
    "sg:city":"Birmingham",
    "sg:classifiers":[
        {
            "category":"Organizations",
            "subcategory":"Membership Organization",
            "type":"Services"
        }
    ],
    "sg:phone":"+44 121 747 5360",
    "sg:postcode":"B36 8NG",
    "sg:province":"West Midlands",
    "sg:tags":[
        "club"
    ],
    "wof:name":"Firs Royal British Legion Club Ltd.",
    "wof:placetype":"venue"
},
  "geometry": {"coordinates":[-1.8006440401,52.5034141541],"type":"Point"}
}