{
  "type": "Feature",
  "properties": {
    "addr:full":"65 Talbot Road Blackpool Lancashire FY1 1LL",
    "addr:housenumber":"65",
    "addr:postcode":"fy1 1ll",
    "addr:street":"Talbot Road",
    "iso:country":"GB",
    "sg:address":"65 Talbot Road",
    "sg:city":"Blackpool",
    "sg:classifiers":[
        {
            "category":"Shopping",
            "subcategory":"Shoes",
            "type":"Retail Goods"
        }
    ],
    "sg:phone":"+44 1253 623823",
    "sg:postcode":"FY1 1LL",
    "sg:province":"Lancashire",
    "sg:tags":[
        "shop"
    ],
    "wof:name":"Shoemarket Ltd.",
    "wof:placetype":"venue"
},
  "geometry": {"coordinates":[-3.051575,53.820198],"type":"Point"}
}