{
  "type": "Feature",
  "properties": {
    "iso:country":"GB",
    "sg:address":"Highfield, Bartholomew Grn",
    "sg:city":"Chelmsford",
    "sg:classifiers":[
        {
            "category":"Building & Trades",
            "subcategory":"Construction",
            "type":"Services"
        }
    ],
    "sg:postcode":"CM3 1QG",
    "sg:province":"Essex",
    "sg:tags":[
        "joiner",
        "carpenter"
    ],
    "wof:name":"Stephen Lawrence Richardson",
    "wof:placetype":"venue"
},
  "geometry": {"coordinates":[0.49698,51.86095],"type":"Point"}
}