{
  "type": "Feature",
  "properties": {
    "addr:full":"Hare Law Industrial Estate Stanley Durham DH9 8UR",
    "addr:postcode":"dh9 8ur",
    "addr:street":"Stanley",
    "iso:country":"GB",
    "sg:address":"Hare Law Industrial Estate",
    "sg:city":"Stanley",
    "sg:classifiers":[
        {
            "category":"Professional",
            "subcategory":"Engineering",
            "type":"Services"
        }
    ],
    "sg:phone":"+44 1207 237793",
    "sg:postcode":"DH9 8UR",
    "sg:province":"Durham",
    "sg:tags":[
        "precision",
        "engineer"
    ],
    "wof:name":"C Zang Engineering",
    "wof:placetype":"venue"
},
  "geometry": {"coordinates":[-1.749244,54.86903],"type":"Point"}
}