{
  "type": "Feature",
  "properties": {
    "addr:full":"170 Kingsley Road, Kingsley Northampton Northamptonshire NN2 7BN",
    "addr:housenumber":"170",
    "addr:postcode":"nn2 7bn",
    "addr:street":"Kingsley Road",
    "iso:country":"GB",
    "sg:address":"170 Kingsley Road, Kingsley",
    "sg:city":"Northampton",
    "sg:classifiers":[
        {
            "category":"Freight",
            "type":"Transportation"
        }
    ],
    "sg:postcode":"NN2 7BN",
    "sg:province":"Northamptonshire",
    "sg:tags":[
        "haulage",
        "road"
    ],
    "wof:name":"Midland Haulage",
    "wof:placetype":"venue"
},
  "geometry": {"coordinates":[-0.886802,52.25502],"type":"Point"}
}