{
  "type": "Feature",
  "properties": {
    "addr:full":"Dicconson Lane, Aspull Wigan Lancashire WN2 1QD",
    "addr:postcode":"wn2 1qd",
    "addr:street":"Dicconson Lane",
    "iso:country":"GB",
    "sg:address":"Dicconson Lane, Aspull",
    "sg:city":"Wigan",
    "sg:classifiers":[
        {
            "category":"Sports & Exercise",
            "subcategory":"Stables",
            "type":"Entertainment"
        }
    ],
    "sg:phone":"+44 1942 831329",
    "sg:postcode":"WN2 1QD",
    "sg:province":"Lancashire",
    "sg:tags":[
        "education",
        "equestrian"
    ],
    "wof:name":"Landlords Farm Riding Centre",
    "wof:placetype":"venue"
},
  "geometry": {"coordinates":[-2.5847139359,53.5694503784],"type":"Point"}
}