{
  "type": "Feature",
  "properties": {
    "addr:full":"Spring Street, Easingwold York North Yorkshire YO61 3BJ",
    "addr:postcode":"yo61 3bj",
    "addr:street":"Spring Street",
    "iso:country":"GB",
    "sg:address":"Spring Street, Easingwold",
    "sg:city":"York",
    "sg:classifiers":[
        {
            "category":"Shopping",
            "subcategory":"Clothing, Apparel, & Fashions",
            "type":"Retail Goods"
        }
    ],
    "sg:phone":"+44 1347 821545",
    "sg:postcode":"YO61 3BJ",
    "sg:province":"North Yorkshire",
    "sg:tags":[
        "menswear"
    ],
    "wof:name":"Charles Hobson of Easingwold",
    "wof:placetype":"venue"
},
  "geometry": {"coordinates":[-1.190724,54.123596],"type":"Point"}
}