{
  "type": "Feature",
  "properties": {
    "addr:full":"Brenzett Romney Marsh Kent TN29 9UA",
    "addr:postcode":"tn29 9ua",
    "addr:street":"Brenzett",
    "iso:country":"GB",
    "sg:address":"Brenzett",
    "sg:city":"Romney Marsh",
    "sg:classifiers":[
        {
            "category":"Autos & Motor Vehicles",
            "subcategory":"Motorcycle Sales",
            "type":"Retail Goods"
        }
    ],
    "sg:phone":"+44 1797 344273",
    "sg:postcode":"TN29 9UA",
    "sg:province":"Kent",
    "wof:name":"J V H Motorcycles",
    "wof:placetype":"venue"
},
  "geometry": {"coordinates":[0.89921,50.949902],"type":"Point"}
}