{
  "type": "Feature",
  "properties": {
    "addr:full":"130 Crossgates Road Leeds West Yorkshire LS15 7NG",
    "addr:housenumber":"130",
    "addr:postcode":"ls15 7ng",
    "addr:street":"Crossgates Road",
    "iso:country":"GB",
    "sg:address":"130 Crossgates Road",
    "sg:city":"Leeds",
    "sg:classifiers":[
        {
            "category":"Retail",
            "subcategory":"Auto Rental",
            "type":"Services"
        }
    ],
    "sg:postcode":"LS15 7NG",
    "sg:province":"West Yorkshire",
    "sg:tags":[
        "car"
    ],
    "wof:name":"A Hugh Walker (Leeds) Ltd.",
    "wof:placetype":"venue"
},
  "geometry": {"coordinates":[-1.454015,53.80806],"type":"Point"}
}