{
  "type": "Feature",
  "properties": {
    "addr:full":"19 Chipstead Valley Road Coulsdon Surrey CR5 2RB",
    "addr:housenumber":"19",
    "addr:postcode":"cr5 2rb",
    "addr:street":"Chipstead Valley Road",
    "iso:country":"GB",
    "sg:address":"19 Chipstead Valley Road",
    "sg:city":"Coulsdon",
    "sg:classifiers":[
        {
            "category":"Shopping",
            "subcategory":"Clothing, Apparel, & Fashions",
            "type":"Retail Goods"
        }
    ],
    "sg:postcode":"CR5 2RB",
    "sg:province":"Surrey",
    "sg:tags":[
        "shop"
    ],
    "wof:name":"M Decker",
    "wof:placetype":"venue"
},
  "geometry": {"coordinates":[-0.139075,51.320568],"type":"Point"}
}