{
  "type": "Feature",
  "properties": {
    "iso:country":"GB",
    "sg:address":"222 High Street",
    "sg:city":"Dudley",
    "sg:classifiers":[
        {
            "category":"Shopping",
            "subcategory":"Clothing, Apparel, & Fashions",
            "type":"Retail Goods"
        }
    ],
    "sg:phone":"+44 1384 211793",
    "sg:postcode":"DY1 1PD",
    "sg:province":"West Midlands",
    "sg:tags":[
        "shop"
    ],
    "wof:name":"River Island Clothing Co Ltd",
    "wof:placetype":"venue"
},
  "geometry": {"coordinates":[-2.082822,52.510506],"type":"Point"}
}