{
  "type": "Feature",
  "properties": {
    "addr:full":"89 New St Huddersfield West Yorkshire HD1 2TW",
    "addr:housenumber":"89",
    "addr:postcode":"hd1 2tw",
    "addr:street":"New St",
    "iso:country":"GB",
    "sg:address":"89 New St",
    "sg:city":"Huddersfield",
    "sg:classifiers":[
        {
            "category":"Communications",
            "subcategory":"Film & Video Production",
            "type":"Services"
        }
    ],
    "sg:phone":"+44 1484 428233",
    "sg:postcode":"HD1 2TW",
    "sg:province":"West Yorkshire",
    "sg:tags":[
        "tv"
    ],
    "wof:name":"Radio Rentals",
    "wof:placetype":"venue"
},
  "geometry": {"coordinates":[-1.7832939625,53.6440811157],"type":"Point"}
}