{
  "type": "Feature",
  "properties": {
    "addr:full":"Railway Arches, Colindeep Lane London Greater London NW9 6HD",
    "addr:postcode":"nw9 6hd",
    "addr:street":"Railway Arches Colindeep Lane",
    "iso:country":"GB",
    "sg:address":"Railway Arches, Colindeep Lane",
    "sg:city":"London",
    "sg:classifiers":[
        {
            "category":"Wholesale",
            "subcategory":"Scrap",
            "type":"Manufacturing & Wholesale Goods"
        }
    ],
    "sg:phone":"+44 20 8205 2100",
    "sg:postcode":"NW9 6HD",
    "sg:province":"Greater London",
    "sg:tags":[
        "breaker",
        "dismantlers"
    ],
    "wof:name":"Metro Breakers",
    "wof:placetype":"venue"
},
  "geometry": {"coordinates":[-0.2403900027,51.5875015259],"type":"Point"}
}