{
  "type": "Feature",
  "properties": {
    "iso:country":"GB",
    "sg:address":"125 Dover Road",
    "sg:city":"Sandwich",
    "sg:classifiers":[
        {
            "category":"Building & Trades",
            "subcategory":"Construction",
            "type":"Services"
        }
    ],
    "sg:phone":"+44 1304 617358",
    "sg:postcode":"CT13 0DA",
    "sg:province":"Kent",
    "sg:tags":[
        "joiner",
        "carpenter"
    ],
    "wof:name":"Alan E G Langstaff",
    "wof:placetype":"venue"
},
  "geometry": {"coordinates":[1.333392024,51.2641792297],"type":"Point"}
}