{
  "type": "Feature",
  "properties": {
    "addr:full":"Moorcourt, Fieldway Ilkley North Yorkshire LS29 8NA",
    "addr:postcode":"ls29 8na",
    "iso:country":"GB",
    "sg:address":"Moorcourt, Fieldway",
    "sg:city":"Ilkley",
    "sg:classifiers":[
        {
            "category":"Organizations",
            "subcategory":"Community Association",
            "type":"Services"
        },
        {
            "category":"Government",
            "subcategory":"Office",
            "type":"Public Place"
        }
    ],
    "sg:phone":"+44 1943 609734",
    "sg:postcode":"LS29 8NA",
    "sg:province":"North Yorkshire",
    "sg:tags":[
        "associations",
        "project",
        "gov",
        "housing",
        "co-operatives",
        "trust",
        "societies"
    ],
    "wof:name":"Community Mental Health Team",
    "wof:placetype":"venue"
},
  "geometry": {"coordinates":[-1.821754,53.924461],"type":"Point"}
}