{
  "type": "Feature",
  "properties": {
    "addr:full":"Castle Hill Hospital, Castle Road Hull East Riding of Yorkshire HU16 5JQ",
    "addr:postcode":"hu16 5jq",
    "addr:street":"Castle Road",
    "iso:country":"GB",
    "sg:address":"Castle Hill Hospital, Castle Road",
    "sg:city":"Hull",
    "sg:classifiers":[
        {
            "category":"Health Services",
            "subcategory":"Hospital",
            "type":"Services"
        }
    ],
    "sg:phone":"+44 1482 674214",
    "sg:postcode":"HU16 5JQ",
    "sg:province":"East Riding of Yorkshire",
    "wof:name":"Castle Hill Hospital",
    "wof:placetype":"venue"
},
  "geometry": {"coordinates":[-0.345919013,53.7431907654],"type":"Point"}
}