{
  "type": "Feature",
  "properties": {
    "addr:full":"220 The Street, Boughton Under Blean Faversham Kent ME13 9AL",
    "addr:housenumber":"220",
    "addr:postcode":"me13 9al",
    "addr:street":"The Street",
    "iso:country":"GB",
    "sg:address":"220 The Street, Boughton Under Blean",
    "sg:city":"Faversham",
    "sg:classifiers":[
        {
            "category":"Shopping",
            "subcategory":"News",
            "type":"Retail Goods"
        }
    ],
    "sg:phone":"+44 1227 750220",
    "sg:postcode":"ME13 9AL",
    "sg:province":"Kent",
    "sg:tags":[
        "newsagent"
    ],
    "wof:name":"Boughton Newsagents",
    "wof:placetype":"venue"
},
  "geometry": {"coordinates":[0.963155,51.294151],"type":"Point"}
}