{
  "type": "Feature",
  "properties": {
    "addr:full":"157 French St Sunbury-on-thames Surrey TW16 5JY",
    "addr:housenumber":"157",
    "addr:postcode":"tw16 5jy",
    "addr:street":"French St",
    "iso:country":"GB",
    "sg:address":"157 French St",
    "sg:city":"Sunbury-on-thames",
    "sg:classifiers":[
        {
            "category":"Professional",
            "subcategory":"Detective & Security Services",
            "type":"Services"
        }
    ],
    "sg:postcode":"TW16 5JY",
    "sg:province":"Surrey",
    "sg:tags":[
        "alarm",
        "burglar",
        "system"
    ],
    "wof:name":"Kirk,Andy,",
    "wof:placetype":"venue"
},
  "geometry": {"coordinates":[-0.4029139876,51.4099884033],"type":"Point"}
}