{
  "type": "Feature",
  "properties": {
    "addr:full":"Oxford Road, Cowley Oxford Oxfordshire OX4 2LF",
    "addr:postcode":"ox4 2lf",
    "addr:street":"Oxford Road",
    "iso:country":"GB",
    "sg:address":"Oxford Road, Cowley",
    "sg:city":"Oxford",
    "sg:classifiers":[
        {
            "category":"Education",
            "subcategory":"School",
            "type":"Public Place"
        }
    ],
    "sg:phone":"+44 1865 779176",
    "sg:postcode":"OX4 2LF",
    "sg:province":"Oxfordshire",
    "sg:tags":[
        "local",
        "authority"
    ],
    "wof:name":"Our Lady's R C First School",
    "wof:placetype":"venue"
},
  "geometry": {"coordinates":[-1.2195990086,51.7379989624],"type":"Point"}
}