{
  "type": "Feature",
  "properties": {
    "iso:country":"GB",
    "sg:address":"120 West Heath Rd",
    "sg:city":"Hampstead",
    "sg:classifiers":[
        {
            "category":"Health Services",
            "subcategory":"Health Practitioner",
            "type":"Services"
        }
    ],
    "sg:phone":"+44 20 8458 1609",
    "sg:postcode":"NW3 7TY",
    "sg:province":"Greater London",
    "sg:tags":[
        "psychotherapist"
    ],
    "wof:name":"Association of Child Psychotherapists",
    "wof:placetype":"venue"
},
  "geometry": {"coordinates":[-0.1930570006,51.5665779114],"type":"Point"}
}