{
  "type": "Feature",
  "properties": {
    "iso:country":"GB",
    "sg:address":"Kingshill Estate, Kingsway",
    "sg:city":"Ware",
    "sg:classifiers":[
        {
            "category":"Autos & Motor Vehicles",
            "subcategory":"Auto Supplies",
            "type":"Retail Goods"
        }
    ],
    "sg:phone":"+44 1920 466996",
    "sg:postcode":"SG12 0QT",
    "sg:province":"Hertfordshire",
    "sg:tags":[
        "tyre"
    ],
    "wof:name":"Charlie Brown",
    "wof:placetype":"venue"
},
  "geometry": {"coordinates":[-0.035127,51.816338],"type":"Point"}
}