{
  "type": "Feature",
  "properties": {
    "iso:country":"GB",
    "sg:address":"85 Welland Lodge Rd",
    "sg:city":"Cheltenham",
    "sg:classifiers":[
        {
            "category":"Building & Trades",
            "subcategory":"Construction",
            "type":"Services"
        }
    ],
    "sg:postcode":"GL52 3HH",
    "sg:province":"Gloucestershire",
    "sg:tags":[
        "builder"
    ],
    "wof:name":"Bevan,William,",
    "wof:placetype":"venue"
},
  "geometry": {"coordinates":[-2.060618,51.912273],"type":"Point"}
}