{
  "type": "Feature",
  "properties": {
    "addr:full":"16 Northway, Eccles Manchester Greater Manchester M30 0LL",
    "addr:housenumber":"16",
    "addr:postcode":"m30 0ll",
    "addr:street":"Northway",
    "iso:country":"GB",
    "sg:address":"16 Northway, Eccles",
    "sg:city":"Manchester",
    "sg:classifiers":[
        {
            "category":"Retail",
            "subcategory":"Laundry & Dry Cleaning",
            "type":"Services"
        }
    ],
    "sg:postcode":"M30 0LL",
    "sg:province":"Greater Manchester",
    "sg:tags":[
        "alteration"
    ],
    "wof:name":"Brown,Yvonne,",
    "wof:placetype":"venue"
},
  "geometry": {"coordinates":[-2.3380589485,53.483379364],"type":"Point"}
}