{
  "type": "Feature",
  "properties": {
    "addr:full":"Quarry Garage, Stainton Penrith Cumbria CA11 0EB",
    "addr:postcode":"ca11 0eb",
    "iso:country":"GB",
    "sg:address":"Quarry Garage, Stainton",
    "sg:city":"Penrith",
    "sg:classifiers":[
        {
            "category":"Freight",
            "type":"Transportation"
        }
    ],
    "sg:phone":"+44 1768 868284",
    "sg:postcode":"CA11 0EB",
    "sg:province":"Cumbria",
    "sg:tags":[
        "haulage",
        "road"
    ],
    "wof:name":"Connect UK",
    "wof:placetype":"venue"
},
  "geometry": {"coordinates":[-2.8004739285,54.6444168091],"type":"Point"}
}