{
  "type": "Feature",
  "properties": {
    "addr:full":"45 Cinque Ports Street Rye East Sussex TN31 7AD",
    "addr:housenumber":"45",
    "addr:postcode":"tn31 7ad",
    "addr:street":"Cinque Ports Street",
    "iso:country":"GB",
    "sg:address":"45 Cinque Ports Street",
    "sg:city":"Rye",
    "sg:classifiers":[
        {
            "category":"Cafe",
            "type":"Food & Drink"
        }
    ],
    "sg:phone":"+44 1797 223986",
    "sg:postcode":"TN31 7AD",
    "sg:province":"East Sussex",
    "sg:tags":[
        "tea",
        "room"
    ],
    "wof:name":"Stephen & Andrew Jempson",
    "wof:placetype":"venue"
},
  "geometry": {"coordinates":[0.7306820154,50.9508666992],"type":"Point"}
}