{
  "type": "Feature",
  "properties": {
    "addr:full":"11 Wesley Walk, Charford Bromsgrove Worcestershire B60 3NU",
    "addr:housenumber":"11",
    "addr:postcode":"b60 3nu",
    "addr:street":"Wesley Walk Charford",
    "iso:country":"GB",
    "sg:address":"11 Wesley Walk, Charford",
    "sg:city":"Bromsgrove",
    "sg:classifiers":[
        {
            "category":"Building & Trades",
            "subcategory":"Construction",
            "type":"Services"
        }
    ],
    "sg:postcode":"B60 3NU",
    "sg:province":"Worcestershire",
    "sg:tags":[
        "builder"
    ],
    "wof:name":"Richardson,John,",
    "wof:placetype":"venue"
},
  "geometry": {"coordinates":[-2.0736300945,52.3213310242],"type":"Point"}
}