{
  "type": "Feature",
  "properties": {
    "iso:country":"GB",
    "sg:address":"11 Wesley Walk, Charford",
    "sg:city":"Bromsgrove",
    "sg:classifiers":[
        {
            "category":"Building & Trades",
            "subcategory":"Construction",
            "type":"Services"
        }
    ],
    "sg:postcode":"B60 3NU",
    "sg:province":"Worcestershire",
    "sg:tags":[
        "builder"
    ],
    "wof:name":"Richardson,John,",
    "wof:placetype":"venue"
},
  "geometry": {"coordinates":[-2.0736300945,52.3213310242],"type":"Point"}
}