{
  "type": "Feature",
  "properties": {
    "addr:full":"28 Far Street, Wymeswold Loughborough Leicestershire LE12 6TZ",
    "addr:housenumber":"28",
    "addr:postcode":"le12 6tz",
    "addr:street":"Far Street",
    "iso:country":"GB",
    "sg:address":"28 Far Street, Wymeswold",
    "sg:city":"Loughborough",
    "sg:classifiers":[
        {
            "category":"Shopping",
            "subcategory":"Antiques",
            "type":"Retail Goods"
        }
    ],
    "sg:postcode":"LE12 6TZ",
    "sg:province":"Leicestershire",
    "wof:name":"Bryan Peach Antiques",
    "wof:placetype":"venue"
},
  "geometry": {"coordinates":[-1.109087,52.806145],"type":"Point"}
}