{
  "type": "Feature",
  "properties": {
    "iso:country":"GB",
    "sg:address":"25 Steeple Street, Kilbarchan",
    "sg:city":"Johnstone",
    "sg:classifiers":[
        {
            "category":"Transit Center",
            "subcategory":"Freight",
            "type":"Transportation"
        },
        {
            "category":"Shopping",
            "subcategory":"Crafts & Fabrics",
            "type":"Retail Goods"
        }
    ],
    "sg:phone":"+44 1505 705509",
    "sg:postcode":"PA10 2JF",
    "sg:province":"Renfrewshire",
    "sg:tags":[
        "shop",
        "outlet",
        "centre"
    ],
    "wof:name":"Bobbins",
    "wof:placetype":"venue"
},
  "geometry": {"coordinates":[-4.552213,55.836285],"type":"Point"}
}