{
  "type": "Feature",
  "properties": {
    "iso:country":"GB",
    "sg:address":"Unit 1 Broomhill Rd,, Spurryhillock Indstl Est,",
    "sg:city":"Stonehaven",
    "sg:classifiers":[
        {
            "category":"Home & Garden",
            "subcategory":"Carpets & Floor Coverings",
            "type":"Retail Goods"
        }
    ],
    "sg:postcode":"AB3 2NH",
    "sg:province":"Aberdeenshire",
    "sg:tags":[
        "rubber",
        "plastic"
    ],
    "wof:name":"Lothian Mouldings Ltd",
    "wof:placetype":"venue"
},
  "geometry": {"coordinates":[-2.20875,56.963848],"type":"Point"}
}