{
  "type": "Feature",
  "properties": {
    "addr:full":"3 Forval Close Mitcham Greater London CR4 4NE",
    "addr:housenumber":"3",
    "addr:postcode":"cr4 4ne",
    "addr:street":"Forval Close",
    "iso:country":"GB",
    "sg:address":"3 Forval Close",
    "sg:city":"Mitcham",
    "sg:classifiers":[
        {
            "category":"Freight",
            "type":"Transportation"
        }
    ],
    "sg:phone":"+44 20 8687 2066",
    "sg:postcode":"CR4 4NE",
    "sg:province":"Greater London",
    "sg:tags":[
        "haulage",
        "road"
    ],
    "wof:name":"Triumph Transport Ltd.",
    "wof:placetype":"venue"
},
  "geometry": {"coordinates":[-0.165684998,51.3949966431],"type":"Point"}
}