{
  "type": "Feature",
  "properties": {
    "iso:country":"GB",
    "sg:address":"St James's Court Hotel, Buckingham Gate",
    "sg:city":"Westminster",
    "sg:classifiers":[
        {
            "category":"Restaurant",
            "type":"Food & Drink"
        }
    ],
    "sg:phone":"+44 20 7821 1899",
    "sg:postcode":"SW1E 6AF",
    "sg:province":"Greater London",
    "sg:tags":[
        "french"
    ],
    "wof:name":"Auberge De Provence",
    "wof:placetype":"venue"
},
  "geometry": {"coordinates":[-0.13693,51.49852],"type":"Point"}
}