{
  "type": "Feature",
  "properties": {
    "addr:full":"14a Imex Business Park, Shobnall Road Burton On Trent Derbyshire DE14 2AU",
    "addr:housenumber":"14a",
    "addr:postcode":"de14 2au",
    "addr:street":"Imex Business Park Shobnall Road",
    "iso:country":"GB",
    "sg:address":"14a Imex Business Park, Shobnall Road",
    "sg:city":"Burton On Trent",
    "sg:classifiers":[
        {
            "category":"Professional",
            "type":"Services"
        }
    ],
    "sg:phone":"+44 1283 509384",
    "sg:postcode":"DE14 2AU",
    "sg:province":"Derbyshire",
    "sg:tags":[
        "directory",
        "pub"
    ],
    "wof:name":"Ken Harrington",
    "wof:placetype":"venue"
},
  "geometry": {"coordinates":[-1.647701025,52.8043518066],"type":"Point"}
}