{
  "type": "Feature",
  "properties": {
    "addr:full":"6-7 Hall Street Carmarthen Carmarthenshire SA31 1PL",
    "addr:housenumber":"6-7",
    "addr:postcode":"sa31 1pl",
    "addr:street":"Hall Street",
    "iso:country":"GB",
    "sg:address":"6-7 Hall Street",
    "sg:city":"Carmarthen",
    "sg:classifiers":[
        {
            "category":"Shopping",
            "subcategory":"Department Store",
            "type":"Retail Goods"
        }
    ],
    "sg:phone":"+44 1267 237230",
    "sg:postcode":"SA31 1PL",
    "sg:province":"Carmarthenshire",
    "wof:name":"Woolworths Plc",
    "wof:placetype":"venue"
},
  "geometry": {"coordinates":[-4.3014059067,51.8618011475],"type":"Point"}
}