{
  "type": "Feature",
  "properties": {
    "iso:country":"GB",
    "sg:address":"Nuttall Lane, Ramsbottom",
    "sg:city":"Bury",
    "sg:classifiers":[
        {
            "category":"Health Services",
            "subcategory":"Hospital",
            "type":"Services"
        }
    ],
    "sg:phone":"+44 1706 823123",
    "sg:postcode":"BL0 9JZ",
    "sg:province":"Lancashire",
    "wof:name":"Ramsbottom Cottage Hospital",
    "wof:placetype":"venue"
},
  "geometry": {"coordinates":[-2.320299,53.641842],"type":"Point"}
}