{
  "type": "Feature",
  "properties": {
    "iso:country":"GB",
    "sg:address":"Wilson Ho, John Wilson Business Pk",
    "sg:city":"Whitstable",
    "sg:classifiers":[
        {
            "category":"Autos & Motor Vehicles",
            "subcategory":"Automobile Sales",
            "type":"Retail Goods"
        }
    ],
    "sg:postcode":"CT5 3QU",
    "sg:province":"Kent",
    "sg:tags":[
        "car"
    ],
    "wof:name":"Eurostock Tax Free Car Sales",
    "wof:placetype":"venue"
},
  "geometry": {"coordinates":[1.026406,51.362247],"type":"Point"}
}