{
  "type": "Feature",
  "properties": {
    "addr:full":"5 The Viaduct St. James Lane Muswell Hill Greater London N10 3QX",
    "addr:housenumber":"5",
    "addr:postcode":"n10 3qx",
    "addr:street":"The Viaduct St. James Lane",
    "iso:country":"GB",
    "sg:address":"5 The Viaduct St. James Lane",
    "sg:city":"Muswell Hill",
    "sg:classifiers":[
        {
            "category":"Retail",
            "subcategory":"Auto Repair",
            "type":"Services"
        }
    ],
    "sg:phone":"+44 20 8365 3375",
    "sg:postcode":"N10 3QX",
    "sg:province":"Greater London",
    "sg:tags":[
        "modification",
        "garage"
    ],
    "wof:name":"Beetlemania",
    "wof:placetype":"venue"
},
  "geometry": {"coordinates":[-0.14169,51.58886],"type":"Point"}
}