{
  "type": "Feature",
  "properties": {
    "addr:full":"60 Woodrow Lane, Catshill Bromsgrove Worcestershire B61 0PL",
    "addr:housenumber":"60",
    "addr:postcode":"b61 0pl",
    "addr:street":"Woodrow Lane Catshill",
    "iso:country":"GB",
    "sg:address":"60 Woodrow Lane, Catshill",
    "sg:city":"Bromsgrove",
    "sg:classifiers":[
        {
            "category":"Retail",
            "subcategory":"Auto Repair",
            "type":"Services"
        }
    ],
    "sg:postcode":"B61 0PL",
    "sg:province":"Worcestershire",
    "sg:tags":[
        "modification",
        "garage"
    ],
    "wof:name":"M  R  D  Ltd.",
    "wof:placetype":"venue"
},
  "geometry": {"coordinates":[-2.0522379875,52.3684501648],"type":"Point"}
}