{
  "type": "Feature",
  "properties": {
    "iso:country":"GB",
    "sg:address":"18 Bayton Road, Exhall",
    "sg:city":"Coventry",
    "sg:classifiers":[
        {
            "category":"Manufacturing",
            "subcategory":"Electronics",
            "type":"Manufacturing & Wholesale Goods"
        }
    ],
    "sg:phone":"+44 24 7636 5553",
    "sg:postcode":"CV7 9EJ",
    "sg:province":"Warwickshire",
    "sg:tags":[
        "mnfrs",
        "transformer"
    ],
    "wof:name":"Transformer Cores",
    "wof:placetype":"venue"
},
  "geometry": {"coordinates":[-1.477573,52.463467],"type":"Point"}
}