{
  "type": "Feature",
  "properties": {
    "addr:full":"6-8 Castle Street Clitheroe Lancashire BB7 2BX",
    "addr:housenumber":"6-8",
    "addr:postcode":"bb7 2bx",
    "addr:street":"Castle Street",
    "iso:country":"GB",
    "sg:address":"6-8 Castle Street",
    "sg:city":"Clitheroe",
    "sg:classifiers":[
        {
            "category":"Travel",
            "subcategory":"Travel Agent",
            "type":"Entertainment"
        }
    ],
    "sg:phone":"+44 845 071 3710",
    "sg:postcode":"BB7 2BX",
    "sg:province":"Lancashire",
    "sg:tags":[
        "agency",
        "activity"
    ],
    "wof:name":"LUNN POLY LTD",
    "wof:placetype":"venue"
},
  "geometry": {"coordinates":[-2.391988039,53.8715629578],"type":"Point"}
}