{
  "type": "Feature",
  "properties": {
    "iso:country":"GB",
    "sg:address":"The Homestead, Kirton Road, Egmanton",
    "sg:city":"Newark",
    "sg:classifiers":[
        {
            "category":"Banks & Credit Unions",
            "subcategory":"Investment Brokerage",
            "type":"Services"
        }
    ],
    "sg:postcode":"NG22 0HF",
    "sg:province":"Nottinghamshire",
    "sg:tags":[
        "contractor"
    ],
    "wof:name":"H A Oliver",
    "wof:placetype":"venue"
},
  "geometry": {"coordinates":[-0.902663,53.211414],"type":"Point"}
}