{
  "type": "Feature",
  "properties": {
    "iso:country":"GB",
    "sg:address":"7 Kingfisher Close, Huntington",
    "sg:city":"York",
    "sg:classifiers":[
        {
            "category":"Professional",
            "subcategory":"Accounting & Tax Preparation",
            "type":"Services"
        }
    ],
    "sg:postcode":"YO32 9GL",
    "sg:province":"North Yorkshire",
    "sg:tags":[
        "consultant"
    ],
    "wof:name":"Personal Tax Services",
    "wof:placetype":"venue"
},
  "geometry": {"coordinates":[-1.060889,53.999176],"type":"Point"}
}