{
  "type": "Feature",
  "properties": {
    "addr:full":"Kings Farm, Parkers Farm Road, Orsett Grays Essex RM16 3HX",
    "addr:postcode":"rm16 3hx",
    "addr:street":"Farm Road",
    "iso:country":"GB",
    "sg:address":"Kings Farm, Parkers Farm Road, Orsett",
    "sg:city":"Grays",
    "sg:classifiers":[
        {
            "category":"Airport",
            "subcategory":"General Aviation",
            "type":"Transportation"
        }
    ],
    "sg:postcode":"RM16 3HX",
    "sg:province":"Essex",
    "wof:name":"General Aero Services",
    "wof:placetype":"venue"
},
  "geometry": {"coordinates":[0.3667750061,51.5123214722],"type":"Point"}
}