{
  "type": "Feature",
  "properties": {
    "iso:country":"GB",
    "sg:address":"64 Thorpe Road",
    "sg:city":"Peterborough",
    "sg:classifiers":[
        {
            "category":"Health Services",
            "subcategory":"Doctor",
            "type":"Services"
        }
    ],
    "sg:phone":"+44 1733 310070",
    "sg:postcode":"PE3 6AP",
    "sg:province":"Cambridgeshire",
    "sg:tags":[
        "practitioners"
    ],
    "wof:name":"Thorpe Road Surgery",
    "wof:placetype":"venue"
},
  "geometry": {"coordinates":[-0.257036,52.572914],"type":"Point"}
}