{
  "type": "Feature",
  "properties": {
    "addr:full":"13 Edinburgh Road Portsmouth Hampshire PO1 1DE",
    "addr:housenumber":"13",
    "addr:postcode":"hampshire po1 1de",
    "addr:street":"Edinburgh Road",
    "iso:country":"GB",
    "sg:address":"13 Edinburgh Road",
    "sg:city":"Portsmouth",
    "sg:classifiers":[
        {
            "category":"Fast Food",
            "type":"Food & Drink"
        }
    ],
    "sg:phone":"+44 23 9281 4665",
    "sg:postcode":"PO1 1DE",
    "sg:province":"Hampshire",
    "sg:tags":[
        "away",
        "take"
    ],
    "wof:name":"Sophies Restaurant",
    "wof:placetype":"venue"
},
  "geometry": {"coordinates":[-1.0922659636,50.8002243042],"type":"Point"}
}