{
  "type": "Feature",
  "properties": {
    "iso:country":"GB",
    "sg:address":"Greenhill Industrial Estate, Greenhill Lane, Riddings",
    "sg:city":"Derby",
    "sg:classifiers":[
        {
            "category":"Retail",
            "subcategory":"Repair Shop",
            "type":"Services"
        }
    ],
    "sg:phone":"+44 1773 607900",
    "sg:postcode":"DE55 4BR",
    "sg:province":"Derbyshire",
    "sg:tags":[
        "upholsterer"
    ],
    "wof:name":"Leabrooks Upholstery Ltd.",
    "wof:placetype":"venue"
},
  "geometry": {"coordinates":[-1.3624720573,53.067489624],"type":"Point"}
}