{
  "type": "Feature",
  "properties": {
    "addr:full":"6 Toynbee Street London Greater London E1 7NE",
    "addr:housenumber":"6",
    "addr:postcode":"e1 7ne",
    "addr:street":"Toynbee Street",
    "iso:country":"GB",
    "sg:address":"6 Toynbee Street",
    "sg:city":"London",
    "sg:classifiers":[
        {
            "category":"Government",
            "subcategory":"Post Office",
            "type":"Public Place"
        }
    ],
    "sg:phone":"+44 20 7377 1620",
    "sg:postcode":"E1 7NE",
    "sg:province":"Greater London",
    "sg:tags":[
        "messenger",
        "courier"
    ],
    "wof:name":"Leopards Couriers Ltd.",
    "wof:placetype":"venue"
},
  "geometry": {"coordinates":[-0.0746650025,51.5178260803],"type":"Point"}
}