{
  "type": "Feature",
  "properties": {
    "iso:country":"GB",
    "sg:address":"18 Hill Drive",
    "sg:city":"Wilmslow",
    "sg:classifiers":[
        {
            "category":"Building & Trades",
            "subcategory":"Construction",
            "type":"Services"
        }
    ],
    "sg:phone":"+44 1625 529063",
    "sg:postcode":"SK9 3AR",
    "sg:province":"Cheshire",
    "sg:tags":[
        "builder"
    ],
    "wof:name":"Keith H Turner",
    "wof:placetype":"venue"
},
  "geometry": {"coordinates":[-2.204565,53.344925],"type":"Point"}
}