{
  "type": "Feature",
  "properties": {
    "iso:country":"GB",
    "sg:address":"8-12 Church Street",
    "sg:city":"Ripley",
    "sg:classifiers":[
        {
            "category":"Banks & Credit Unions",
            "subcategory":"Financial Services",
            "type":"Services"
        }
    ],
    "sg:phone":"+44 1773 744044",
    "sg:postcode":"DE5 3BU",
    "sg:province":"Derbyshire",
    "sg:tags":[
        "adviser",
        "independent"
    ],
    "wof:name":"Paragon Financial Consultants Ltd.",
    "wof:placetype":"venue"
},
  "geometry": {"coordinates":[-1.406502,53.050747],"type":"Point"}
}