{
  "type": "Feature",
  "properties": {
    "iso:country":"GB",
    "sg:address":"10 Toward Rd, Wearside",
    "sg:city":"Sunderland",
    "sg:classifiers":[
        {
            "category":"Professional",
            "subcategory":"Detective & Security Services",
            "type":"Services"
        }
    ],
    "sg:phone":"+44 191 510 3636",
    "sg:postcode":"SR1 2QF",
    "sg:province":"Tyne and Wear",
    "sg:tags":[
        "equipment",
        "installers"
    ],
    "wof:name":"C.C.T.V.",
    "wof:placetype":"venue"
},
  "geometry": {"coordinates":[-1.37804,54.902222],"type":"Point"}
}