{
  "type": "Feature",
  "properties": {
    "addr:full":"15 Heath Road, Hale Altrincham Cheshire WA14 2UJ",
    "addr:housenumber":"15",
    "addr:postcode":"wa14 2uj",
    "addr:street":"Heath Road",
    "iso:country":"GB",
    "sg:address":"15 Heath Road, Hale",
    "sg:city":"Altrincham",
    "sg:classifiers":[
        {
            "category":"Bus Charters",
            "type":"Transportation"
        }
    ],
    "sg:postcode":"WA14 2UJ",
    "sg:province":"Cheshire",
    "sg:tags":[
        "hire",
        "coach"
    ],
    "wof:name":"Fiesta Group Travel",
    "wof:placetype":"venue"
},
  "geometry": {"coordinates":[-2.3477818966,53.3765869141],"type":"Point"}
}