{
  "type": "Feature",
  "properties": {
    "addr:full":"455 Christchurch Road Bournemouth Dorset BH1 4AD",
    "addr:housenumber":"455",
    "addr:postcode":"bh1 4ad",
    "addr:street":"Christchurch Road",
    "iso:country":"GB",
    "sg:address":"455 Christchurch Road",
    "sg:city":"Bournemouth",
    "sg:classifiers":[
        {
            "category":"Professional",
            "subcategory":"Art Services",
            "type":"Services"
        }
    ],
    "sg:postcode":"BH1 4AD",
    "sg:province":"Dorset",
    "sg:tags":[
        "photographer"
    ],
    "wof:name":"Morris Benjamin Photographic Studio",
    "wof:placetype":"venue"
},
  "geometry": {"coordinates":[-1.8460609913,50.7247009277],"type":"Point"}
}