{
  "type": "Feature",
  "properties": {
    "addr:full":"2 Five Acres, Windmill Hill Hailsham East Sussex BN27 4RZ",
    "addr:housenumber":"2",
    "addr:postcode":"bn27 4rz",
    "addr:street":"Five Acres",
    "iso:country":"GB",
    "sg:address":"2 Five Acres, Windmill Hill",
    "sg:city":"Hailsham",
    "sg:classifiers":[
        {
            "category":"Building & Trades",
            "subcategory":"Construction",
            "type":"Services"
        }
    ],
    "sg:postcode":"BN27 4RZ",
    "sg:province":"East Sussex",
    "sg:tags":[
        "builder"
    ],
    "wof:name":"P Jarrett & Son Ltd.",
    "wof:placetype":"venue"
},
  "geometry": {"coordinates":[0.2565200031,50.8653831482],"type":"Point"}
}