{
  "type": "Feature",
  "properties": {
    "addr:full":"Furzedown View, Green Hill Tavistock Devon PL19 8RJ",
    "addr:postcode":"pl19 8rj",
    "addr:street":"Furzedown View",
    "iso:country":"GB",
    "sg:address":"Furzedown View, Green Hill",
    "sg:city":"Tavistock",
    "sg:classifiers":[
        {
            "category":"Communications",
            "type":"Services"
        }
    ],
    "sg:phone":"+44 1822 618861",
    "sg:postcode":"PL19 8RJ",
    "sg:province":"Devon",
    "sg:tags":[
        "tv",
        "video",
        "radio"
    ],
    "wof:name":"Aerialmasters Satellite Specialist",
    "wof:placetype":"venue"
},
  "geometry": {"coordinates":[-4.144739,50.549934],"type":"Point"}
}