{
  "type": "Feature",
  "properties": {
    "iso:country":"GB",
    "sg:address":"Daley House, 64 Tithebarn St",
    "sg:city":"Liverpool",
    "sg:classifiers":[
        {
            "category":"Professional",
            "subcategory":"Engineering",
            "type":"Services"
        }
    ],
    "sg:phone":"+44 151 236 0633",
    "sg:postcode":"L2 2EE",
    "sg:province":"Merseyside",
    "sg:tags":[
        "consulting",
        "engineer"
    ],
    "wof:name":"Miller Walmsley Partnership",
    "wof:placetype":"venue"
},
  "geometry": {"coordinates":[-2.989046,53.410072],"type":"Point"}
}