{
  "type": "Feature",
  "properties": {
    "addr:full":"7-9 Roberts Road Southampton Hampshire SO15 5DF",
    "addr:housenumber":"7-9",
    "addr:postcode":"so15 5df",
    "addr:street":"Roberts Road",
    "iso:country":"GB",
    "sg:address":"7-9 Roberts Road",
    "sg:city":"Southampton",
    "sg:classifiers":[
        {
            "category":"Farming",
            "subcategory":"Nursery",
            "type":"Manufacturing & Wholesale Goods"
        }
    ],
    "sg:phone":"+44 23 8021 1103",
    "sg:postcode":"SO15 5DF",
    "sg:province":"Hampshire",
    "sg:tags":[
        "creche"
    ],
    "wof:name":"Fledglings Day Nursery",
    "wof:placetype":"venue"
},
  "geometry": {"coordinates":[-1.416199,50.910713],"type":"Point"}
}