{
  "type": "Feature",
  "properties": {
    "addr:full":"Risborough Rd, Terrick Aylesbury Buckinghamshire HP22 5XL",
    "addr:postcode":"hp22 5xl",
    "addr:street":"Risborough Rd",
    "iso:country":"GB",
    "sg:address":"Risborough Rd, Terrick",
    "sg:city":"Aylesbury",
    "sg:classifiers":[
        {
            "category":"Autos & Motor Vehicles",
            "subcategory":"Automobile Sales",
            "type":"Retail Goods"
        }
    ],
    "sg:postcode":"HP22 5XL",
    "sg:province":"Buckinghamshire",
    "sg:tags":[
        "car"
    ],
    "wof:name":"Cardy,Lionel,",
    "wof:placetype":"venue"
},
  "geometry": {"coordinates":[-0.7908689976,51.7853431702],"type":"Point"}
}