{
  "type": "Feature",
  "properties": {
    "addr:full":"7b Arrow Trading Estate, Corporation Road, Audenshaw Manchester Greater Manchester M34 5LR",
    "addr:housenumber":"7b;estate",
    "addr:postcode":"m34 5lr",
    "addr:street":"Arrow Trading;Corporation Road",
    "iso:country":"GB",
    "sg:address":"7b Arrow Trading Estate, Corporation Road, Audenshaw",
    "sg:city":"Manchester",
    "sg:classifiers":[
        {
            "category":"Professional",
            "subcategory":"Business Services",
            "type":"Services"
        }
    ],
    "sg:phone":"+44 161 335 0900",
    "sg:postcode":"M34 5LR",
    "sg:province":"Greater Manchester",
    "sg:tags":[
        "distribution"
    ],
    "wof:name":"Northern Packaging Components",
    "wof:placetype":"venue"
},
  "geometry": {"coordinates":[-2.1232039928,53.4637184143],"type":"Point"}
}