{
  "type": "Feature",
  "properties": {
    "addr:full":"80 Queensway London Greater London W2 3RL",
    "addr:housenumber":"80",
    "addr:postcode":"w2 3rl",
    "addr:street":"Queensway",
    "iso:country":"GB",
    "sg:address":"80 Queensway",
    "sg:city":"London",
    "sg:classifiers":[
        {
            "category":"Cafe",
            "type":"Food & Drink"
        }
    ],
    "sg:phone":"+44 20 7229 4459",
    "sg:postcode":"W2 3RL",
    "sg:province":"Greater London",
    "sg:tags":[
        "tea",
        "room"
    ],
    "wof:name":"D P Pechon",
    "wof:placetype":"venue"
},
  "geometry": {"coordinates":[-0.18744,51.512894],"type":"Point"}
}