{
  "type": "Feature",
  "properties": {
    "addr:full":"Elm Cottage, 75 Sutton Lane Middlewich Cheshire CW10 0DA",
    "addr:housenumber":"75",
    "addr:postcode":"cw10 0da",
    "addr:street":"Sutton Lane",
    "iso:country":"GB",
    "sg:address":"Elm Cottage, 75 Sutton Lane",
    "sg:city":"Middlewich",
    "sg:classifiers":[
        {
            "category":"Organizations",
            "subcategory":"Non-profit Organization",
            "type":"Services"
        }
    ],
    "sg:phone":"+44 1606 737359",
    "sg:postcode":"CW10 0DA",
    "sg:province":"Cheshire",
    "sg:tags":[
        "charitable",
        "organisation",
        "voluntary",
        "charity"
    ],
    "wof:name":"Richmond Fellowship For Community Mental Health",
    "wof:placetype":"venue"
},
  "geometry": {"coordinates":[-2.4531340599,53.1922988892],"type":"Point"}
}