{
  "type": "Feature",
  "properties": {
    "iso:country":"GB",
    "sg:address":"Prospect House, Broad Oak Road",
    "sg:city":"Canterbury",
    "sg:classifiers":[
        {
            "category":"Autos & Motor Vehicles",
            "subcategory":"Auto Supplies",
            "type":"Retail Goods"
        }
    ],
    "sg:phone":"+44 1227 766001",
    "sg:postcode":"CT2 7PX",
    "sg:province":"Kent",
    "sg:tags":[
        "component"
    ],
    "wof:name":"L C P Automotive Components",
    "wof:placetype":"venue"
},
  "geometry": {"coordinates":[1.0886050463,51.2901763916],"type":"Point"}
}