{
  "type": "Feature",
  "properties": {
    "addr:full":"58 Henderson Street, Bridge Of Allan Stirling Clackmannanshire FK9 4HS",
    "addr:housenumber":"58",
    "addr:postcode":"fk9 4hs",
    "addr:street":"Henderson Street",
    "iso:country":"GB",
    "sg:address":"58 Henderson Street, Bridge Of Allan",
    "sg:city":"Stirling",
    "sg:classifiers":[
        {
            "category":"Shopping",
            "subcategory":"Gifts & Souvenirs",
            "type":"Retail Goods"
        }
    ],
    "sg:phone":"+44 1786 833295",
    "sg:postcode":"FK9 4HS",
    "sg:province":"Clackmannanshire",
    "sg:tags":[
        "shop"
    ],
    "wof:name":"Collections",
    "wof:placetype":"venue"
},
  "geometry": {"coordinates":[-3.94711,56.154747],"type":"Point"}
}