{
  "type": "Feature",
  "properties": {
    "iso:country":"GB",
    "sg:address":"82 Westbourne Gro, Bayswater",
    "sg:city":"London",
    "sg:classifiers":[
        {
            "category":"Home & Garden",
            "subcategory":"Furniture",
            "type":"Retail Goods"
        }
    ],
    "sg:phone":"+44 20 7229 1691",
    "sg:postcode":"W2 5RT",
    "sg:province":"Greater London",
    "wof:name":"Magpie",
    "wof:placetype":"venue"
},
  "geometry": {"coordinates":[-0.193252,51.515381],"type":"Point"}
}