{
  "type": "Feature",
  "properties": {
    "iso:country":"GB",
    "sg:address":"19b George St",
    "sg:city":"Walsall",
    "sg:classifiers":[
        {
            "category":"Professional",
            "subcategory":"Employment Agencies",
            "type":"Services"
        }
    ],
    "sg:phone":"+44 1922 634472",
    "sg:postcode":"WS1 1RS",
    "sg:province":"West Midlands",
    "sg:tags":[
        "consultant"
    ],
    "wof:name":"Swift Personnel Services",
    "wof:placetype":"venue"
},
  "geometry": {"coordinates":[-1.981555,52.581669],"type":"Point"}
}