{
  "type": "Feature",
  "properties": {
    "addr:full":"Pond House, Blandford Heights Blandford Forum Dorset DT11 7TF",
    "addr:postcode":"dorset dt11 7tf",
    "addr:street":"Blandford Heights",
    "iso:country":"GB",
    "sg:address":"Pond House, Blandford Heights",
    "sg:city":"Blandford Forum",
    "sg:classifiers":[
        {
            "category":"Professional",
            "subcategory":"Management & Consulting",
            "type":"Services"
        },
        {
            "category":"Organizations",
            "subcategory":"Community Association",
            "type":"Services"
        }
    ],
    "sg:phone":"+44 1258 454341",
    "sg:postcode":"DT11 7TF",
    "sg:province":"Dorset",
    "sg:tags":[
        "organisation",
        "conservation"
    ],
    "wof:name":"Vincent Wild Life Trust",
    "wof:placetype":"venue"
},
  "geometry": {"coordinates":[-2.159354,50.870708],"type":"Point"}
}