{
  "type": "Feature",
  "properties": {
    "iso:country":"GB",
    "sg:address":"12 Bulverhythe Road",
    "sg:city":"St Leonards-on-sea",
    "sg:classifiers":[
        {
            "category":"Home & Garden",
            "subcategory":"Home Furnishings",
            "type":"Retail Goods"
        }
    ],
    "sg:postcode":"TN38 8AD",
    "sg:province":"East Sussex",
    "sg:tags":[
        "blind",
        "curtain",
        "fitting"
    ],
    "wof:name":"Jane's Interiors",
    "wof:placetype":"venue"
},
  "geometry": {"coordinates":[0.528464,50.850914],"type":"Point"}
}