{
  "type": "Feature",
  "properties": {
    "addr:full":"Wentworth Drive Bedford Bedfordshire MK41 8QA",
    "addr:postcode":"mk41 8qa",
    "addr:street":"Wentworth Drive",
    "iso:country":"GB",
    "sg:address":"Wentworth Drive",
    "sg:city":"Bedford",
    "sg:classifiers":[
        {
            "category":"Arena",
            "subcategory":"Sports Club",
            "type":"Entertainment"
        }
    ],
    "sg:phone":"+44 1234 350874",
    "sg:postcode":"MK41 8QA",
    "sg:province":"Bedfordshire",
    "wof:name":"Bedford Athletic Rugby Club",
    "wof:placetype":"venue"
},
  "geometry": {"coordinates":[-0.4514189959,52.160572052],"type":"Point"}
}