{
  "type": "Feature",
  "properties": {
    "iso:country":"GB",
    "sg:address":"49 Kingswood Firs, Grayshott",
    "sg:city":"Hindhead",
    "sg:classifiers":[
        {
            "category":"Shopping",
            "subcategory":"Computers & Home Electronics",
            "type":"Retail Goods"
        }
    ],
    "sg:phone":"+44 1428 609050",
    "sg:postcode":"GU26 6ES",
    "sg:province":"Hampshire",
    "sg:tags":[
        "equipment",
        "video",
        "cctv"
    ],
    "wof:name":"King,Stuart,",
    "wof:placetype":"venue"
},
  "geometry": {"coordinates":[-0.753105,51.1035],"type":"Point"}
}