{
  "type": "Feature",
  "properties": {
    "iso:country":"GB",
    "sg:address":"Peddars Close, Ixworth",
    "sg:city":"Bury St Edmunds",
    "sg:classifiers":[
        {
            "category":"Health Services",
            "subcategory":"Doctor",
            "type":"Services"
        }
    ],
    "sg:phone":"+44 1359 230252",
    "sg:postcode":"IP31 2HD",
    "sg:province":"Suffolk",
    "sg:tags":[
        "practitioners"
    ],
    "wof:name":"Ixworth Surgery",
    "wof:placetype":"venue"
},
  "geometry": {"coordinates":[0.8306930065,52.302482605],"type":"Point"}
}