{
  "type": "Feature",
  "properties": {
    "addr:full":"36a Leicester Street Melton Mowbray Leicestershire LE13 0PP",
    "addr:housenumber":"36a",
    "addr:postcode":"le13 0pp",
    "addr:street":"Leicester Street",
    "iso:country":"GB",
    "sg:address":"36a Leicester Street",
    "sg:city":"Melton Mowbray",
    "sg:classifiers":[
        {
            "category":"Health Services",
            "subcategory":"Health Practitioner",
            "type":"Services"
        }
    ],
    "sg:phone":"+44 1664 470037",
    "sg:postcode":"LE13 0PP",
    "sg:province":"Leicestershire",
    "sg:tags":[
        "physiotherapist"
    ],
    "wof:name":"Melton Mowbray Physiotherapy & Sports Injury Clinic",
    "wof:placetype":"venue"
},
  "geometry": {"coordinates":[-0.8887410164,52.7644958496],"type":"Point"}
}