{
  "type": "Feature",
  "properties": {
    "addr:full":"Unit 12 Vale Mill Blackburn Lancashire BB1 9QJ",
    "addr:housenumber":"unit 12",
    "addr:postcode":"bb1 9qj",
    "addr:street":"Vale Mill",
    "iso:country":"GB",
    "sg:address":"Unit 12 Vale Mill",
    "sg:city":"Blackburn",
    "sg:classifiers":[
        {
            "category":"Professional",
            "subcategory":"Testing Lab",
            "type":"Services"
        }
    ],
    "sg:postcode":"BB1 9QJ",
    "sg:province":"Lancashire",
    "sg:tags":[
        "mot"
    ],
    "wof:name":"Autosave",
    "wof:placetype":"venue"
},
  "geometry": {"coordinates":[-2.4803988934,53.7485160828],"type":"Point"}
}