{
  "type": "Feature",
  "properties": {
    "addr:full":"Thorburn Road, Norley Hall Wigan Lancashire WN5 9LW",
    "addr:postcode":"wn5 9lw",
    "addr:street":"Thorburn Road Norley Hall",
    "iso:country":"GB",
    "sg:address":"Thorburn Road, Norley Hall",
    "sg:city":"Wigan",
    "sg:classifiers":[
        {
            "category":"Education",
            "subcategory":"School",
            "type":"Public Place"
        }
    ],
    "sg:phone":"+44 1942 222721",
    "sg:postcode":"WN5 9LW",
    "sg:province":"Lancashire",
    "sg:tags":[
        "local",
        "authority"
    ],
    "wof:name":"Wigan Metropolitan Borough Council",
    "wof:placetype":"venue"
},
  "geometry": {"coordinates":[-2.673835,53.539005],"type":"Point"}
}