{
  "type": "Feature",
  "properties": {
    "addr:full":"Landsdowne House, 77 East Street Bridport Dorset DT6 3LB",
    "addr:housenumber":"77",
    "addr:postcode":"dt6 3lb",
    "addr:street":"East Street",
    "iso:country":"GB",
    "sg:address":"Landsdowne House, 77 East Street",
    "sg:city":"Bridport",
    "sg:classifiers":[
        {
            "category":"Professional",
            "subcategory":"Computer Services",
            "type":"Services"
        }
    ],
    "sg:postcode":"DT6 3LB",
    "sg:province":"Dorset",
    "sg:tags":[
        "consultant"
    ],
    "wof:name":"Lewesdon Systems Ltd.",
    "wof:placetype":"venue"
},
  "geometry": {"coordinates":[-2.753616,50.733196],"type":"Point"}
}