{
  "type": "Feature",
  "properties": {
    "addr:full":"1 New St Ossett West Yorkshire WF5 8BH",
    "addr:housenumber":"1",
    "addr:postcode":"wf5 8bh",
    "addr:street":"New St",
    "iso:country":"GB",
    "sg:address":"1 New St",
    "sg:city":"Ossett",
    "sg:classifiers":[
        {
            "category":"Real Estate",
            "subcategory":"Architect",
            "type":"Services"
        }
    ],
    "sg:phone":"+44 1924 262122",
    "sg:postcode":"WF5 8BH",
    "sg:province":"West Yorkshire",
    "wof:name":"Booton Farmer & Clay",
    "wof:placetype":"venue"
},
  "geometry": {"coordinates":[-1.5782599449,53.6795806885],"type":"Point"}
}