{
  "type": "Feature",
  "properties": {
    "addr:full":"Unit 44, The Marlowes Centre, Marlowes Hemel Hempstead Hertfordshire HP1 1DX",
    "addr:housenumber":"unit 44",
    "addr:postcode":"hp1 1dx",
    "addr:street":"The Marlowes Centre Marlowes;Hempstead",
    "iso:country":"GB",
    "sg:address":"Unit 44, The Marlowes Centre, Marlowes",
    "sg:city":"Hemel Hempstead",
    "sg:classifiers":[
        {
            "category":"Shopping",
            "subcategory":"Discount & Variety Stores",
            "type":"Retail Goods"
        }
    ],
    "sg:phone":"+44 1442 253691",
    "sg:postcode":"HP1 1DX",
    "sg:province":"Hertfordshire",
    "sg:tags":[
        "shop",
        "model"
    ],
    "wof:name":"Beatties",
    "wof:placetype":"venue"
},
  "geometry": {"coordinates":[-0.4750840068,51.7490005493],"type":"Point"}
}