{
  "type": "Feature",
  "properties": {
    "iso:country":"GB",
    "sg:address":"319 Penarth Rd",
    "sg:city":"Cardiff",
    "sg:classifiers":[
        {
            "category":"Retail",
            "subcategory":"Auto Rental",
            "type":"Services"
        }
    ],
    "sg:phone":"+44 29 2030 0200",
    "sg:postcode":"CF1 7TT",
    "sg:province":"Cardiff",
    "sg:tags":[
        "truck",
        "hire",
        "van"
    ],
    "wof:name":"Barry Van Hire (Cardiff) Ltd",
    "wof:placetype":"venue"
},
  "geometry": {"coordinates":[-3.196075,51.460239],"type":"Point"}
}