{
  "type": "Feature",
  "properties": {
    "iso:country":"GB",
    "sg:address":"5 North Drive",
    "sg:city":"Great Yarmouth",
    "sg:classifiers":[
        {
            "category":"Travel",
            "subcategory":"Hotels & Motels",
            "type":"Entertainment"
        }
    ],
    "sg:phone":"+44 1493 843759",
    "sg:postcode":"NR30 1ED",
    "sg:province":"Norfolk",
    "wof:name":"Regency Hotel",
    "wof:placetype":"venue"
},
  "geometry": {"coordinates":[1.737472,52.611416],"type":"Point"}
}