{
  "type": "Feature",
  "properties": {
    "addr:full":"11 George Lane London Greater London SE13 6HQ",
    "addr:housenumber":"11",
    "addr:postcode":"se13 6hq",
    "addr:street":"George Lane",
    "iso:country":"GB",
    "sg:address":"11 George Lane",
    "sg:city":"London",
    "sg:classifiers":[
        {
            "category":"Taxi",
            "type":"Transportation"
        }
    ],
    "sg:postcode":"SE13 6HQ",
    "sg:province":"Greater London",
    "sg:tags":[
        "mini",
        "cab"
    ],
    "wof:name":"Easyrider",
    "wof:placetype":"venue"
},
  "geometry": {"coordinates":[-0.015408,51.4505004883],"type":"Point"}
}