{
  "type": "Feature",
  "properties": {
    "iso:country":"GB",
    "sg:address":"20 Market Street",
    "sg:city":"Wigan",
    "sg:classifiers":[
        {
            "category":"Food & Beverages",
            "subcategory":"Meat & Fish",
            "type":"Retail Goods"
        }
    ],
    "sg:phone":"+44 1942 245460",
    "sg:postcode":"WN1 1HX",
    "sg:province":"Lancashire",
    "sg:tags":[
        "chip"
    ],
    "wof:name":"Chippery",
    "wof:placetype":"venue"
},
  "geometry": {"coordinates":[-2.632901,53.546822],"type":"Point"}
}