{
  "type": "Feature",
  "properties": {
    "addr:full":"23 Parkhill Place, Northmuir Kirriemuir Angus DD8 4TA",
    "addr:housenumber":"23",
    "addr:postcode":"dd8 4ta",
    "addr:street":"Parkhill Place Northmuir",
    "iso:country":"GB",
    "sg:address":"23 Parkhill Place, Northmuir",
    "sg:city":"Kirriemuir",
    "sg:classifiers":[
        {
            "category":"Professional",
            "subcategory":"Management & Consulting",
            "type":"Services"
        },
        {
            "category":"Organizations",
            "subcategory":"Community Association",
            "type":"Services"
        }
    ],
    "sg:phone":"+44 1575 574515",
    "sg:postcode":"DD8 4TA",
    "sg:province":"Angus",
    "sg:tags":[
        "consultant",
        "relation",
        "public"
    ],
    "wof:name":"Linksland Communications",
    "wof:placetype":"venue"
},
  "geometry": {"coordinates":[-3.003223896,56.6849403381],"type":"Point"}
}