{
  "type": "Feature",
  "properties": {
    "iso:country":"GB",
    "sg:address":"130 Gosport Road",
    "sg:city":"Fareham",
    "sg:classifiers":[
        {
            "category":"Retail",
            "subcategory":"Repair Shop",
            "type":"Services"
        },
        {
            "category":"Shopping",
            "subcategory":"Computers & Home Electronics",
            "type":"Retail Goods"
        }
    ],
    "sg:phone":"+44 1329 220162",
    "sg:postcode":"PO16 0QL",
    "sg:province":"Hampshire",
    "sg:tags":[
        "radio",
        "television",
        "video",
        "sale"
    ],
    "wof:name":"Solent Televison & Video Centre",
    "wof:placetype":"venue"
},
  "geometry": {"coordinates":[-1.182989,50.842888],"type":"Point"}
}