{
  "type": "Feature",
  "properties": {
    "addr:full":"2 St. Peters St Sandwich Kent CT13 9BW",
    "addr:housenumber":"2",
    "addr:postcode":"ct13 9bw",
    "addr:street":"St. Peters St",
    "iso:country":"GB",
    "sg:address":"2 St. Peters St",
    "sg:city":"Sandwich",
    "sg:classifiers":[
        {
            "category":"Shopping",
            "subcategory":"Clothing, Apparel, & Fashions",
            "type":"Retail Goods"
        }
    ],
    "sg:phone":"+44 1304 614556",
    "sg:postcode":"CT13 9BW",
    "sg:province":"Kent",
    "sg:tags":[
        "dresswear"
    ],
    "wof:name":"Castaways",
    "wof:placetype":"venue"
},
  "geometry": {"coordinates":[1.3411879539,51.2742004395],"type":"Point"}
}