{
  "type": "Feature",
  "properties": {
    "iso:country":"GB",
    "sg:address":"Honeysuckle Cottage, Ardleigh Rd, Dedham",
    "sg:city":"Colchester",
    "sg:classifiers":[
        {
            "category":"Organizations",
            "subcategory":"Community Association",
            "type":"Services"
        }
    ],
    "sg:postcode":"CO7 6EQ",
    "sg:province":"Essex",
    "sg:tags":[
        "relation",
        "public"
    ],
    "wof:name":"Clive Livermore Public Relations Consultant",
    "wof:placetype":"venue"
},
  "geometry": {"coordinates":[0.989513,51.957706],"type":"Point"}
}