{
  "type": "Feature",
  "properties": {
    "addr:full":"Lanyon Farm Penzance Cornwall TR20 8NY",
    "addr:postcode":"tr20 8ny",
    "iso:country":"GB",
    "sg:address":"Lanyon Farm",
    "sg:city":"Penzance",
    "sg:classifiers":[
        {
            "category":"Farming",
            "subcategory":"Dairy Farm",
            "type":"Manufacturing & Wholesale Goods"
        }
    ],
    "sg:phone":"+44 1736 362177",
    "sg:postcode":"TR20 8NY",
    "sg:province":"Cornwall",
    "wof:name":"M C Bone",
    "wof:placetype":"venue"
},
  "geometry": {"coordinates":[-5.6048698425,50.1507606506],"type":"Point"}
}