{
  "type": "Feature",
  "properties": {
    "addr:full":"Rosemount Ho, Rosemount Av West Byfleet Surrey KT14 6LB",
    "addr:postcode":"kt14 6lb",
    "addr:street":"Av West Byfleet",
    "iso:country":"GB",
    "sg:address":"Rosemount Ho, Rosemount Av",
    "sg:city":"West Byfleet",
    "sg:classifiers":[
        {
            "category":"Real Estate",
            "subcategory":"Architect",
            "type":"Services"
        }
    ],
    "sg:phone":"+44 1932 352111",
    "sg:postcode":"KT14 6LB",
    "sg:province":"Surrey",
    "wof:name":"O S E L",
    "wof:placetype":"venue"
},
  "geometry": {"coordinates":[-0.496921,51.338421],"type":"Point"}
}