{
  "type": "Feature",
  "properties": {
    "addr:full":"Church House, Swarkestone Derby Derbyshire DE73 1JB",
    "addr:postcode":"de73 1jb",
    "iso:country":"GB",
    "sg:address":"Church House, Swarkestone",
    "sg:city":"Derby",
    "sg:classifiers":[
        {
            "category":"Shopping",
            "subcategory":"Department Store",
            "type":"Retail Goods"
        }
    ],
    "sg:phone":"+44 1332 702321",
    "sg:postcode":"DE73 1JB",
    "sg:province":"Derbyshire",
    "wof:name":"Robert Taylor",
    "wof:placetype":"venue"
},
  "geometry": {"coordinates":[-1.4504300356,52.855052948],"type":"Point"}
}