{
  "type": "Feature",
  "properties": {
    "iso:country":"GB",
    "sg:address":"1 The Grn, Ryhope",
    "sg:city":"Sunderland",
    "sg:classifiers":[
        {
            "category":"Retail",
            "subcategory":"Funeral Services",
            "type":"Services"
        }
    ],
    "sg:phone":"+44 191 521 0385",
    "sg:postcode":"SR2 0HN",
    "sg:province":"Tyne and Wear",
    "wof:name":"Co-Operative Funeral Services Ltd.",
    "wof:placetype":"venue"
},
  "geometry": {"coordinates":[-1.363809,54.866879],"type":"Point"}
}