{
  "type": "Feature",
  "properties": {
    "iso:country":"GB",
    "sg:address":"146 The Street, West Horsley",
    "sg:city":"Leatherhead",
    "sg:classifiers":[
        {
            "category":"Organizations",
            "subcategory":"Professional Association",
            "type":"Services"
        }
    ],
    "sg:postcode":"KT24 6JA",
    "sg:province":"Surrey",
    "sg:tags":[
        "institute"
    ],
    "wof:name":"The Surrey Law Society",
    "wof:placetype":"venue"
},
  "geometry": {"coordinates":[-0.450717,51.273994],"type":"Point"}
}