{
  "type": "Feature",
  "properties": {
    "iso:country":"GB",
    "sg:address":"32 St Stephens Rd",
    "sg:city":"Saltash",
    "sg:classifiers":[
        {
            "category":"Organizations",
            "subcategory":"Non-profit Organization",
            "type":"Services"
        }
    ],
    "sg:phone":"+44 1752 843417",
    "sg:postcode":"PL12 4BQ",
    "sg:province":"Cornwall",
    "sg:tags":[
        "organisation",
        "voluntary",
        "charity"
    ],
    "wof:name":"Saltash Age Concern",
    "wof:placetype":"venue"
},
  "geometry": {"coordinates":[-4.2187671661,50.4084320068],"type":"Point"}
}