{
  "type": "Feature",
  "properties": {
    "iso:country":"GB",
    "sg:address":"Keswick Drive",
    "sg:city":"Chesterfield",
    "sg:classifiers":[
        {
            "category":"Bars & Pubs",
            "type":"Food & Drink"
        }
    ],
    "sg:postcode":"S41 8HQ",
    "sg:province":"Derbyshire",
    "sg:tags":[
        "pubs",
        "inn"
    ],
    "wof:name":"Moonrakers Hotel",
    "wof:placetype":"venue"
},
  "geometry": {"coordinates":[-1.4492490292,53.2580566406],"type":"Point"}
}