{
  "type": "Feature",
  "properties": {
    "addr:full":"35 Hough La Preston Lancashire PR5 1SB",
    "addr:housenumber":"35",
    "addr:postcode":"pr5 1sb",
    "addr:street":"Hough La Preston",
    "iso:country":"GB",
    "sg:address":"35 Hough La",
    "sg:city":"Preston",
    "sg:classifiers":[
        {
            "category":"Retail",
            "subcategory":"Laundry & Dry Cleaning",
            "type":"Services"
        }
    ],
    "sg:phone":"+44 1772 421257",
    "sg:postcode":"PR5 1SB",
    "sg:province":"Lancashire",
    "sg:tags":[
        "alteration"
    ],
    "wof:name":"Johnson Cleaners UK Ltd",
    "wof:placetype":"venue"
},
  "geometry": {"coordinates":[-2.63084,53.745762],"type":"Point"}
}