{
  "type": "Feature",
  "properties": {
    "iso:country":"GB",
    "sg:address":"Wrawby Road",
    "sg:city":"Brigg",
    "sg:classifiers":[
        {
            "category":"Education",
            "subcategory":"School",
            "type":"Public Place"
        }
    ],
    "sg:phone":"+44 1652 653135",
    "sg:postcode":"DN20 8DS",
    "sg:province":"Lincolnshire",
    "sg:tags":[
        "local",
        "authority"
    ],
    "wof:name":"Sir John Nelthorpe Lower School",
    "wof:placetype":"venue"
},
  "geometry": {"coordinates":[-0.47844401,53.5577201843],"type":"Point"}
}