{
  "type": "Feature",
  "properties": {
    "addr:full":"60 Church Street Flint Flintshire CH6 5AE",
    "addr:housenumber":"60",
    "addr:postcode":"ch6 5ae",
    "addr:street":"Church Street",
    "iso:country":"GB",
    "sg:address":"60 Church Street",
    "sg:city":"Flint",
    "sg:classifiers":[
        {
            "category":"Bars & Pubs",
            "type":"Food & Drink"
        }
    ],
    "sg:phone":"+44 1352 732196",
    "sg:postcode":"CH6 5AE",
    "sg:province":"Flintshire",
    "sg:tags":[
        "pubs",
        "inn"
    ],
    "wof:name":"George & Dragon",
    "wof:placetype":"venue"
},
  "geometry": {"coordinates":[-3.1366689205,53.2482452393],"type":"Point"}
}