{
  "type": "Feature",
  "properties": {
    "iso:country":"GB",
    "sg:address":"61 Chorley Road",
    "sg:city":"Blackpool",
    "sg:classifiers":[
        {
            "category":"Manufacturing",
            "subcategory":"Metals",
            "type":"Manufacturing & Wholesale Goods"
        }
    ],
    "sg:phone":"+44 1253 398000",
    "sg:postcode":"FY3 7XQ",
    "sg:province":"Lancashire",
    "sg:tags":[
        "product",
        "fabricated"
    ],
    "wof:name":"Max Carlyle",
    "wof:placetype":"venue"
},
  "geometry": {"coordinates":[-3.022995,53.83897],"type":"Point"}
}