{
  "type": "Feature",
  "properties": {
    "addr:full":"224 Union Street Aberdeen Aberdeen City AB10 1TL",
    "addr:housenumber":"224",
    "addr:postcode":"ab10 1tl",
    "addr:street":"Union Street",
    "iso:country":"GB",
    "sg:address":"224 Union Street",
    "sg:city":"Aberdeen",
    "sg:classifiers":[
        {
            "category":"Cafe",
            "type":"Food & Drink"
        }
    ],
    "sg:phone":"+44 1224 624040",
    "sg:postcode":"AB10 1TL",
    "sg:province":"Aberdeen City",
    "sg:tags":[
        "tea",
        "room"
    ],
    "wof:name":"Neil Fotheringham",
    "wof:placetype":"venue"
},
  "geometry": {"coordinates":[-2.1064729691,57.1445808411],"type":"Point"}
}