{
  "type": "Feature",
  "properties": {
    "iso:country":"GB",
    "sg:address":"255 Wellington Road North, Heaton Chapel",
    "sg:city":"Stockport",
    "sg:classifiers":[
        {
            "category":"Travel",
            "subcategory":"Hotels & Motels",
            "type":"Entertainment"
        }
    ],
    "sg:postcode":"SK4 5BS",
    "sg:province":"Cheshire",
    "sg:tags":[
        "house",
        "guest"
    ],
    "wof:name":"Heaton Guest House",
    "wof:placetype":"venue"
},
  "geometry": {"coordinates":[-2.174989,53.424389],"type":"Point"}
}