{
  "type": "Feature",
  "properties": {
    "addr:full":"55-57 Commercial Rd Bournemouth Dorset BH2 5RH",
    "addr:housenumber":"55-57",
    "addr:postcode":"bh2 5rh",
    "addr:street":"Commercial Rd",
    "iso:country":"GB",
    "sg:address":"55-57 Commercial Rd",
    "sg:city":"Bournemouth",
    "sg:classifiers":[
        {
            "category":"Communications",
            "subcategory":"Film & Video Production",
            "type":"Services"
        }
    ],
    "sg:phone":"+44 1202 555743",
    "sg:postcode":"BH2 5RH",
    "sg:province":"Dorset",
    "sg:tags":[
        "tv"
    ],
    "wof:name":"Radio Rentals",
    "wof:placetype":"venue"
},
  "geometry": {"coordinates":[-1.883367,50.720387],"type":"Point"}
}