{
  "type": "Feature",
  "properties": {
    "addr:full":"10 Cotlands Avenue Longniddry East Lothian EH32 0QU",
    "addr:housenumber":"10",
    "addr:postcode":"eh32 0qu",
    "addr:street":"Cotlands Avenue",
    "iso:country":"GB",
    "sg:address":"10 Cotlands Avenue",
    "sg:city":"Longniddry",
    "sg:classifiers":[
        {
            "category":"Building & Trades",
            "subcategory":"Cleaning & Sanitation",
            "type":"Services"
        }
    ],
    "sg:phone":"+44 1875 852733",
    "sg:postcode":"EH32 0QU",
    "sg:province":"East Lothian",
    "sg:tags":[
        "sweep",
        "chimney"
    ],
    "wof:name":"Lothian Borders Chimney Sweep Specialists",
    "wof:placetype":"venue"
},
  "geometry": {"coordinates":[-2.9064669609,55.9708137512],"type":"Point"}
}