{
  "type": "Feature",
  "properties": {
    "addr:full":"34-42 Abington Avenue Northampton Northamptonshire NN1 4NY",
    "addr:housenumber":"34-42",
    "addr:postcode":"nn1 4ny",
    "addr:street":"Abington Avenue",
    "iso:country":"GB",
    "sg:address":"34-42 Abington Avenue",
    "sg:city":"Northampton",
    "sg:classifiers":[
        {
            "category":"Autos & Motor Vehicles",
            "subcategory":"Automobile Sales",
            "type":"Retail Goods"
        }
    ],
    "sg:phone":"+44 1604 639000",
    "sg:postcode":"NN1 4NY",
    "sg:province":"Northamptonshire",
    "sg:tags":[
        "car"
    ],
    "wof:name":"Internova Motors",
    "wof:placetype":"venue"
},
  "geometry": {"coordinates":[-0.880626,52.246891],"type":"Point"}
}