{
  "type": "Feature",
  "properties": {
    "iso:country":"GB",
    "sg:address":"2 Whitegates, Flaxpits Lane",
    "sg:city":"Bristol",
    "sg:classifiers":[
        {
            "category":"Shopping",
            "subcategory":"Clothing, Apparel, & Fashions",
            "type":"Retail Goods"
        }
    ],
    "sg:phone":"+44 1454 778453",
    "sg:postcode":"BS36 1JX",
    "sg:province":"Gloucestershire",
    "sg:tags":[
        "shop"
    ],
    "wof:name":"Peter Davies",
    "wof:placetype":"venue"
},
  "geometry": {"coordinates":[-2.50793,51.522469],"type":"Point"}
}