{
  "type": "Feature",
  "properties": {
    "addr:full":"3 Barb Mews London Greater London W6 7PA",
    "addr:housenumber":"3",
    "addr:postcode":"w6 7pa",
    "addr:street":"Barb Mews",
    "iso:country":"GB",
    "sg:address":"3 Barb Mews",
    "sg:city":"London",
    "sg:classifiers":[
        {
            "category":"Wholesale",
            "subcategory":"Books, Periodicals, & Newspapers",
            "type":"Manufacturing & Wholesale Goods"
        }
    ],
    "sg:phone":"+44 20 7610 4676",
    "sg:postcode":"W6 7PA",
    "sg:province":"Greater London",
    "sg:tags":[
        "publishing"
    ],
    "wof:name":"Gregory & Co.",
    "wof:placetype":"venue"
},
  "geometry": {"coordinates":[-0.223072,51.497982],"type":"Point"}
}