{
  "type": "Feature",
  "properties": {
    "iso:country":"GB",
    "sg:address":"Prospect House, Crendon Street",
    "sg:city":"High Wycombe",
    "sg:classifiers":[
        {
            "category":"Building & Trades",
            "subcategory":"Cleaning & Sanitation",
            "type":"Services"
        }
    ],
    "sg:phone":"+44 1494 522367",
    "sg:postcode":"HP13 6LS",
    "sg:province":"Buckinghamshire",
    "sg:tags":[
        "facility"
    ],
    "wof:name":"Europa Facility Services Ltd.",
    "wof:placetype":"venue"
},
  "geometry": {"coordinates":[-0.747789,51.628944],"type":"Point"}
}