{
  "type": "Feature",
  "properties": {
    "addr:full":"The Holmes, Luddendenfoot Halifax West Yorkshire HX2 7RT",
    "addr:postcode":"hx2 7rt",
    "addr:street":"West",
    "iso:country":"GB",
    "sg:address":"The Holmes, Luddendenfoot",
    "sg:city":"Halifax",
    "sg:classifiers":[
        {
            "category":"Organizations",
            "subcategory":"Membership Organization",
            "type":"Services"
        },
        {
            "category":"Arena",
            "subcategory":"Sports Club",
            "type":"Entertainment"
        }
    ],
    "sg:postcode":"HX2 7RT",
    "sg:province":"West Yorkshire",
    "wof:name":"Luddendenfoot Bowling Club",
    "wof:placetype":"venue"
},
  "geometry": {"coordinates":[-1.9295719862,53.752696991],"type":"Point"}
}