{
  "type": "Feature",
  "properties": {
    "iso:country":"GB",
    "sg:address":"76 Freeman Street",
    "sg:city":"Grimsby",
    "sg:classifiers":[
        {
            "category":"Professional",
            "subcategory":"Art Services",
            "type":"Services"
        }
    ],
    "sg:postcode":"DN32 7AG",
    "sg:province":"Lincolnshire",
    "sg:tags":[
        "photographer"
    ],
    "wof:name":"Catchlights",
    "wof:placetype":"venue"
},
  "geometry": {"coordinates":[-0.073315,53.573223],"type":"Point"}
}