{
  "type": "Feature",
  "properties": {
    "addr:full":"296 Chester Road Birmingham West Midlands B36 0LB",
    "addr:housenumber":"296",
    "addr:postcode":"b36 0lb",
    "addr:street":"Chester Road",
    "iso:country":"GB",
    "sg:address":"296 Chester Road",
    "sg:city":"Birmingham",
    "sg:classifiers":[
        {
            "category":"Autos & Motor Vehicles",
            "subcategory":"Fuel & Gas Station",
            "type":"Retail Goods"
        }
    ],
    "sg:phone":"+44 121 749 5630",
    "sg:postcode":"B36 0LB",
    "sg:province":"West Midlands",
    "sg:tags":[
        "petrol",
        "filling"
    ],
    "wof:name":"Timberley Service Station",
    "wof:placetype":"venue"
},
  "geometry": {"coordinates":[-1.75998,52.500729],"type":"Point"}
}