{
  "type": "Feature",
  "properties": {
    "iso:country":"GB",
    "sg:address":"26-28 Park Road",
    "sg:city":"Chesterfield",
    "sg:classifiers":[
        {
            "category":"Bus Charters",
            "type":"Transportation"
        }
    ],
    "sg:phone":"+44 1246 222202",
    "sg:postcode":"S40 1XZ",
    "sg:province":"Derbyshire",
    "sg:tags":[
        "hire",
        "coach"
    ],
    "wof:name":"Dawson Group Travel",
    "wof:placetype":"venue"
},
  "geometry": {"coordinates":[-1.430677,53.234665],"type":"Point"}
}