{
  "type": "Feature",
  "properties": {
    "addr:full":"Unit 2 & 3 Mile Oak Indust Est, Maesbury Rd Oswestry Shropshire SY10 8GA",
    "addr:housenumber":"unit 2 &",
    "addr:postcode":"sy10 8ga",
    "addr:street":"3 Mile Oak Indust Est Maesbury Rd",
    "iso:country":"GB",
    "sg:address":"Unit 2 & 3 Mile Oak Indust Est, Maesbury Rd",
    "sg:city":"Oswestry",
    "sg:classifiers":[
        {
            "category":"Building & Trades",
            "subcategory":"Cleaning & Sanitation",
            "type":"Services"
        }
    ],
    "sg:phone":"+44 1691 653850",
    "sg:postcode":"SY10 8GA",
    "sg:province":"Shropshire",
    "sg:tags":[
        "steam"
    ],
    "wof:name":"Force Pressure Washers",
    "wof:placetype":"venue"
},
  "geometry": {"coordinates":[-3.04046,52.843441],"type":"Point"}
}