{
  "type": "Feature",
  "properties": {
    "iso:country":"GB",
    "sg:address":"Unit 2 Churchill Court, 58 Station Road",
    "sg:city":"Harrow",
    "sg:classifiers":[
        {
            "category":"Professional",
            "subcategory":"Accounting & Tax Preparation",
            "type":"Services"
        }
    ],
    "sg:phone":"+44 20 8427 9936",
    "sg:postcode":"HA2 7SA",
    "sg:province":"Greater London",
    "sg:tags":[
        "accountant"
    ],
    "wof:name":"Slipper & Co",
    "wof:placetype":"venue"
},
  "geometry": {"coordinates":[-0.361564,51.585182],"type":"Point"}
}