{
  "type": "Feature",
  "properties": {
    "iso:country":"GB",
    "sg:address":"125 Stockport Road, Marple",
    "sg:city":"Stockport",
    "sg:classifiers":[
        {
            "category":"Manufacturing",
            "subcategory":"Wood Products",
            "type":"Manufacturing & Wholesale Goods"
        },
        {
            "category":"Manufacturing",
            "subcategory":"Paper Products",
            "type":"Manufacturing & Wholesale Goods"
        }
    ],
    "sg:phone":"+44 161 427 7734",
    "sg:postcode":"SK6 6AF",
    "sg:province":"Cheshire",
    "sg:tags":[
        "packaging",
        "material",
        "crate",
        "pallets",
        "manufacturer"
    ],
    "wof:name":"Mallard Packaging Ltd",
    "wof:placetype":"venue"
},
  "geometry": {"coordinates":[-2.068031,53.395184],"type":"Point"}
}