{
  "type": "Feature",
  "properties": {
    "addr:full":"10 King St Bathgate West Lothian EH48 1AY",
    "addr:housenumber":"10",
    "addr:postcode":"eh48 1ay",
    "addr:street":"King St Bathgate",
    "iso:country":"GB",
    "sg:address":"10 King St",
    "sg:city":"Bathgate",
    "sg:classifiers":[
        {
            "category":"Professional",
            "subcategory":"Business Services",
            "type":"Services"
        }
    ],
    "sg:phone":"+44 1506 652294",
    "sg:postcode":"EH48 1AY",
    "sg:province":"West Lothian",
    "sg:tags":[
        "bookmaker"
    ],
    "wof:name":"P R Barrett",
    "wof:placetype":"venue"
},
  "geometry": {"coordinates":[-3.64055,55.900253],"type":"Point"}
}