{
  "type": "Feature",
  "properties": {
    "iso:country":"GB",
    "sg:address":"63 Dover Street",
    "sg:city":"Canterbury",
    "sg:classifiers":[
        {
            "category":"Fast Food",
            "type":"Food & Drink"
        }
    ],
    "sg:phone":"+44 1227 450620",
    "sg:postcode":"CT1 3HD",
    "sg:province":"Kent",
    "sg:tags":[
        "away",
        "take"
    ],
    "wof:name":"The Lunch Box",
    "wof:placetype":"venue"
},
  "geometry": {"coordinates":[1.08348,51.276424],"type":"Point"}
}