{
  "type": "Feature",
  "properties": {
    "addr:full":"104 Hurley Road Carlisle Cumbria CA4 8QF",
    "addr:housenumber":"104",
    "addr:postcode":"ca4 8qf",
    "addr:street":"Hurley Road",
    "iso:country":"GB",
    "sg:address":"104 Hurley Road",
    "sg:city":"Carlisle",
    "sg:classifiers":[
        {
            "category":"Building & Trades",
            "subcategory":"Construction",
            "type":"Services"
        }
    ],
    "sg:phone":"+44 1228 562117",
    "sg:postcode":"CA4 8QF",
    "sg:province":"Cumbria",
    "sg:tags":[
        "builder"
    ],
    "wof:name":"Quality Work",
    "wof:placetype":"venue"
},
  "geometry": {"coordinates":[-2.812435,54.907322],"type":"Point"}
}