{
  "type": "Feature",
  "properties": {
    "addr:full":"Quadrant Court, 50 Calthorpe Rd Birmingham West Midlands B15 1TH",
    "addr:housenumber":"50",
    "addr:postcode":"b15 1th",
    "addr:street":"Calthorpe Rd",
    "iso:country":"GB",
    "sg:address":"Quadrant Court, 50 Calthorpe Rd",
    "sg:city":"Birmingham",
    "sg:classifiers":[
        {
            "category":"Professional",
            "subcategory":"Employment Agencies",
            "type":"Services"
        }
    ],
    "sg:phone":"+44 121 410 4040",
    "sg:postcode":"B15 1TH",
    "sg:province":"West Midlands",
    "sg:tags":[
        "consultant"
    ],
    "wof:name":"Reynell Legal Recruitment",
    "wof:placetype":"venue"
},
  "geometry": {"coordinates":[-1.9199850559,52.4702796936],"type":"Point"}
}