{
  "type": "Feature",
  "properties": {
    "addr:full":"421 Newmarket Road Cambridge Cambridgeshire CB5 8JJ",
    "addr:housenumber":"421",
    "addr:postcode":"cb5 8jj",
    "addr:street":"Newmarket Road",
    "iso:country":"GB",
    "sg:address":"421 Newmarket Road",
    "sg:city":"Cambridge",
    "sg:classifiers":[
        {
            "category":"Food & Beverages",
            "subcategory":"Liquor & Beverages",
            "type":"Retail Goods"
        }
    ],
    "sg:phone":"+44 1223 566678",
    "sg:postcode":"CB5 8JJ",
    "sg:province":"Cambridgeshire",
    "sg:tags":[
        "beer",
        "spirit",
        "wines"
    ],
    "wof:name":"The Grapevine",
    "wof:placetype":"venue"
},
  "geometry": {"coordinates":[0.1631200016,52.2124481201],"type":"Point"}
}