{
  "type": "Feature",
  "properties": {
    "iso:country":"GB",
    "sg:address":"57 Marshfoot La",
    "sg:city":"Hailsham",
    "sg:classifiers":[
        {
            "category":"Building & Trades",
            "subcategory":"Construction",
            "type":"Services"
        }
    ],
    "sg:phone":"+44 1323 845105",
    "sg:postcode":"BN27 2RB",
    "sg:province":"East Sussex",
    "sg:tags":[
        "builder"
    ],
    "wof:name":"Paul S Henty",
    "wof:placetype":"venue"
},
  "geometry": {"coordinates":[0.267435,50.864601],"type":"Point"}
}