{
  "type": "Feature",
  "properties": {
    "addr:full":"The Strand Barnstaple Devon EX31 1EX",
    "addr:postcode":"ex31 1ex",
    "addr:street":"The Strand",
    "iso:country":"GB",
    "sg:address":"The Strand",
    "sg:city":"Barnstaple",
    "sg:classifiers":[
        {
            "category":"Banks & Credit Unions",
            "subcategory":"Financial Services",
            "type":"Services"
        }
    ],
    "sg:phone":"+44 1271 342101",
    "sg:postcode":"EX31 1EX",
    "sg:province":"Devon",
    "sg:tags":[
        "building",
        "society"
    ],
    "wof:name":"Britannia Building Society",
    "wof:placetype":"venue"
},
  "geometry": {"coordinates":[-4.059393,51.078247],"type":"Point"}
}