{
  "type": "Feature",
  "properties": {
    "iso:country":"GB",
    "sg:address":"16 Justice Mill Lane",
    "sg:city":"Aberdeen",
    "sg:classifiers":[
        {
            "category":"Bars & Pubs",
            "type":"Food & Drink"
        }
    ],
    "sg:phone":"+44 1224 575040",
    "sg:postcode":"AB11 6EP",
    "sg:province":"Aberdeen City",
    "sg:tags":[
        "pubs",
        "inn"
    ],
    "wof:name":"O'Donoghue's Irish Pub",
    "wof:placetype":"venue"
},
  "geometry": {"coordinates":[-2.1091020107,57.1429214478],"type":"Point"}
}