{
  "type": "Feature",
  "properties": {
    "addr:full":"68-78 South Bridge Street Airdrie North Lanarkshire ML6 6JD",
    "addr:housenumber":"68-78",
    "addr:postcode":"ml6 6jd",
    "addr:street":"South Bridge Street",
    "iso:country":"GB",
    "sg:address":"68-78 South Bridge Street",
    "sg:city":"Airdrie",
    "sg:classifiers":[
        {
            "category":"Shopping",
            "subcategory":"Department Store",
            "type":"Retail Goods"
        }
    ],
    "sg:phone":"+44 1236 762875",
    "sg:postcode":"ML6 6JD",
    "sg:province":"North Lanarkshire",
    "wof:name":"John Orr & Sons (Airdrie) Ltd.",
    "wof:placetype":"venue"
},
  "geometry": {"coordinates":[-3.9817790985,55.8675270081],"type":"Point"}
}