{
  "type": "Feature",
  "properties": {
    "addr:full":"The Maying Field, Gallowstree Common Reading Berkshire RG4 7HU",
    "addr:postcode":"rg4 7hu",
    "addr:street":"Common",
    "iso:country":"GB",
    "sg:address":"The Maying Field, Gallowstree Common",
    "sg:city":"Reading",
    "sg:classifiers":[
        {
            "category":"Arena",
            "subcategory":"Sports Club",
            "type":"Entertainment"
        }
    ],
    "sg:phone":"+44 118 972 4143",
    "sg:postcode":"RG4 7HU",
    "sg:province":"Berkshire",
    "wof:name":"Kidmore End Cricket Club The",
    "wof:placetype":"venue"
},
  "geometry": {"coordinates":[-1.00832,51.488602],"type":"Point"}
}