{
  "type": "Feature",
  "properties": {
    "addr:full":"77 Main Street Keswick Cumbria CA12 5DS",
    "addr:housenumber":"77",
    "addr:postcode":"ca12 5ds",
    "addr:street":"Main Street",
    "iso:country":"GB",
    "sg:address":"77 Main Street",
    "sg:city":"Keswick",
    "sg:classifiers":[
        {
            "category":"Food & Beverages",
            "subcategory":"Meat & Fish",
            "type":"Retail Goods"
        },
        {
            "category":"Food & Beverages",
            "subcategory":"Groceries & Convenience Stores",
            "type":"Retail Goods"
        }
    ],
    "sg:phone":"+44 17687 73106",
    "sg:postcode":"CA12 5DS",
    "sg:province":"Cumbria",
    "sg:tags":[
        "shop",
        "chip"
    ],
    "wof:name":"The Kingfisher",
    "wof:placetype":"venue"
},
  "geometry": {"coordinates":[-3.139405,54.601864],"type":"Point"}
}