{
  "type": "Feature",
  "properties": {
    "addr:full":"42 Earlesfield Lane Grantham Lincolnshire NG31 7NY",
    "addr:housenumber":"42",
    "addr:postcode":"ng31 7ny",
    "addr:street":"Earlesfield Lane",
    "iso:country":"GB",
    "sg:address":"42 Earlesfield Lane",
    "sg:city":"Grantham",
    "sg:classifiers":[
        {
            "category":"Social Services",
            "type":"Services"
        },
        {
            "category":"Government",
            "subcategory":"Office",
            "type":"Public Place"
        }
    ],
    "sg:phone":"+44 1476 563984",
    "sg:postcode":"NG31 7NY",
    "sg:province":"Lincolnshire",
    "sg:tags":[
        "local"
    ],
    "wof:name":"Grantham Family Centre",
    "wof:placetype":"venue"
},
  "geometry": {"coordinates":[-0.652617991,52.9054145813],"type":"Point"}
}