{
  "type": "Feature",
  "properties": {
    "addr:full":"Lindpet Ho, 5 Market Pl Grantham Lincolnshire NG31 6LJ",
    "addr:housenumber":"5",
    "addr:postcode":"ng31 6lj",
    "addr:street":"Market Pl",
    "iso:country":"GB",
    "sg:address":"Lindpet Ho, 5 Market Pl",
    "sg:city":"Grantham",
    "sg:classifiers":[
        {
            "category":"Banks & Credit Unions",
            "subcategory":"Financial Services",
            "type":"Services"
        }
    ],
    "sg:postcode":"NG31 6LJ",
    "sg:province":"Lincolnshire",
    "sg:tags":[
        "adviser"
    ],
    "wof:name":"Dean,Andrew,",
    "wof:placetype":"venue"
},
  "geometry": {"coordinates":[-0.6428589821,52.9131965637],"type":"Point"}
}