{
  "type": "Feature",
  "properties": {
    "iso:country":"GB",
    "sg:address":"10 Wellington Road, Donnington",
    "sg:city":"Telford",
    "sg:classifiers":[
        {
            "category":"Shopping",
            "subcategory":"Pets & Pet Supplies",
            "type":"Retail Goods"
        }
    ],
    "sg:phone":"+44 1952 270060",
    "sg:postcode":"TF2 8AE",
    "sg:province":"Shropshire",
    "wof:name":"Donnington Pet & Household Supplies",
    "wof:placetype":"venue"
},
  "geometry": {"coordinates":[-2.441438,52.719566],"type":"Point"}
}