{
  "type": "Feature",
  "properties": {
    "addr:full":"40 Foxland Rd, Gatley Cheadle Cheshire SK8 4QB",
    "addr:housenumber":"40",
    "addr:postcode":"sk8 4qb",
    "addr:street":"Foxland Rd;Cheadle",
    "iso:country":"GB",
    "sg:address":"40 Foxland Rd, Gatley",
    "sg:city":"Cheadle",
    "sg:classifiers":[
        {
            "category":"Sports & Exercise",
            "subcategory":"Gym",
            "type":"Entertainment"
        }
    ],
    "sg:phone":"+44 161 491 6320",
    "sg:postcode":"SK8 4QB",
    "sg:province":"Cheshire",
    "sg:tags":[
        "fitness",
        "health",
        "centre"
    ],
    "wof:name":"Yasmin's Health & Beauty Clinic",
    "wof:placetype":"venue"
},
  "geometry": {"coordinates":[-2.230126,53.387794],"type":"Point"}
}