{
  "type": "Feature",
  "properties": {
    "iso:country":"GB",
    "sg:address":"85 Aldrich Drive, Willen",
    "sg:city":"Milton Keynes",
    "sg:classifiers":[
        {
            "category":"Farming",
            "subcategory":"Farm",
            "type":"Manufacturing & Wholesale Goods"
        }
    ],
    "sg:phone":"+44 1908 605760",
    "sg:postcode":"MK15 9LH",
    "sg:province":"Buckinghamshire",
    "sg:tags":[
        "agricultural"
    ],
    "wof:name":"Auto Protools",
    "wof:placetype":"venue"
},
  "geometry": {"coordinates":[-0.716506,52.063198],"type":"Point"}
}