{
  "type": "Feature",
  "properties": {
    "addr:full":"45 Dovecote Lane Oldham Lancashire OL4 4SN",
    "addr:housenumber":"45",
    "addr:postcode":"ol4 4sn",
    "addr:street":"Dovecote Lane",
    "iso:country":"GB",
    "sg:address":"45 Dovecote Lane",
    "sg:city":"Oldham",
    "sg:classifiers":[
        {
            "category":"Building & Trades",
            "subcategory":"Plumbing",
            "type":"Services"
        }
    ],
    "sg:phone":"+44 161 652 5674",
    "sg:postcode":"OL4 4SN",
    "sg:province":"Lancashire",
    "sg:tags":[
        "central",
        "heating"
    ],
    "wof:name":"Springhead Plumbing",
    "wof:placetype":"venue"
},
  "geometry": {"coordinates":[-2.066083,53.546467],"type":"Point"}
}