{
  "type": "Feature",
  "properties": {
    "iso:country":"GB",
    "sg:address":"30 Thorney Lane South",
    "sg:city":"Iver",
    "sg:classifiers":[
        {
            "category":"Wholesale",
            "subcategory":"Scrap",
            "type":"Manufacturing & Wholesale Goods"
        }
    ],
    "sg:phone":"+44 1753 631181",
    "sg:postcode":"SL0 9AE",
    "sg:province":"Berkshire",
    "sg:tags":[
        "waste",
        "metal"
    ],
    "wof:name":"Nine Elms Recycling Waste Paper Ltd",
    "wof:placetype":"venue"
},
  "geometry": {"coordinates":[-0.503142,51.515926],"type":"Point"}
}