{
  "type": "Feature",
  "properties": {
    "addr:full":"99-103 Albion Street Leeds West Yorkshire LS1 5AP",
    "addr:housenumber":"99-103",
    "addr:postcode":"ls1 5ap",
    "addr:street":"Albion Street",
    "iso:country":"GB",
    "sg:address":"99-103 Albion Street",
    "sg:city":"Leeds",
    "sg:classifiers":[
        {
            "category":"Travel",
            "subcategory":"Travel Agent",
            "type":"Entertainment"
        }
    ],
    "sg:phone":"+44 113 214 7000",
    "sg:postcode":"LS1 5AP",
    "sg:province":"West Yorkshire",
    "wof:name":"Thomas Cook",
    "wof:placetype":"venue"
},
  "geometry": {"coordinates":[-1.545282,53.799114],"type":"Point"}
}