{
  "type": "Feature",
  "properties": {
    "iso:country":"GB",
    "sg:address":"Unit 16, Stacey Bushes Business Park",
    "sg:city":"Milton Keynes",
    "sg:classifiers":[
        {
            "category":"Professional",
            "subcategory":"Business Services",
            "type":"Services"
        }
    ],
    "sg:phone":"+44 1908 225225",
    "sg:postcode":"MK12 6HS",
    "sg:province":"Buckinghamshire",
    "sg:tags":[
        "tile",
        "stockist"
    ],
    "wof:name":"Avanti Tiles Ltd.",
    "wof:placetype":"venue"
},
  "geometry": {"coordinates":[-0.798549,52.050484],"type":"Point"}
}