{
  "type": "Feature",
  "properties": {
    "addr:full":"2 High St Dover Kent CT16 1DE",
    "addr:housenumber":"2",
    "addr:postcode":"ct16 1de",
    "addr:street":"High St",
    "iso:country":"GB",
    "sg:address":"2 High St",
    "sg:city":"Dover",
    "sg:classifiers":[
        {
            "category":"Farming",
            "subcategory":"Fish & Marine Products",
            "type":"Manufacturing & Wholesale Goods"
        }
    ],
    "sg:postcode":"CT16 1DE",
    "sg:province":"Kent",
    "sg:tags":[
        "fishmonger"
    ],
    "wof:name":"Parks,R,",
    "wof:placetype":"venue"
},
  "geometry": {"coordinates":[1.2692389488,51.1524810791],"type":"Point"}
}