{
  "type": "Feature",
  "properties": {
    "addr:full":"Crickhowell Rd Abergavenny Herefordshire NP7 0DY",
    "addr:postcode":"np7 0dy",
    "addr:street":"Crickhowell Rd",
    "iso:country":"GB",
    "sg:address":"Crickhowell Rd",
    "sg:city":"Abergavenny",
    "sg:classifiers":[
        {
            "category":"Health Services",
            "subcategory":"Nursing And Care Facility",
            "type":"Services"
        }
    ],
    "sg:phone":"+44 1873 830218",
    "sg:postcode":"NP7 0DY",
    "sg:province":"Herefordshire",
    "sg:tags":[
        "home"
    ],
    "wof:name":"Glaslyn Court Nursing Home",
    "wof:placetype":"venue"
},
  "geometry": {"coordinates":[-3.097569,51.82798],"type":"Point"}
}