{
  "type": "Feature",
  "properties": {
    "addr:full":"138 Cainscross Road Stroud Gloucestershire GL5 4HR",
    "addr:housenumber":"138",
    "addr:postcode":"gl5 4hr",
    "addr:street":"Cainscross Road",
    "iso:country":"GB",
    "sg:address":"138 Cainscross Road",
    "sg:city":"Stroud",
    "sg:classifiers":[
        {
            "category":"Professional",
            "type":"Services"
        }
    ],
    "sg:phone":"+44 1453 764367",
    "sg:postcode":"GL5 4HR",
    "sg:province":"Gloucestershire",
    "sg:tags":[
        "shopfitters"
    ],
    "wof:name":"Dee Kay Shopfitting Services",
    "wof:placetype":"venue"
},
  "geometry": {"coordinates":[-2.2344989777,51.7451667786],"type":"Point"}
}