{
  "type": "Feature",
  "properties": {
    "addr:full":"38 Cot Lane, Wordsley Stourbridge Staffordshire DY8 5PR",
    "addr:housenumber":"38",
    "addr:postcode":"dy8 5pr",
    "addr:street":"Cot Lane",
    "iso:country":"GB",
    "sg:address":"38 Cot Lane, Wordsley",
    "sg:city":"Stourbridge",
    "sg:classifiers":[
        {
            "category":"Building & Trades",
            "subcategory":"Landscaping Services",
            "type":"Services"
        }
    ],
    "sg:postcode":"DY8 5PR",
    "sg:province":"Staffordshire",
    "sg:tags":[
        "landscape",
        "contractor"
    ],
    "wof:name":"Home & Garden",
    "wof:placetype":"venue"
},
  "geometry": {"coordinates":[-2.16939,52.485077],"type":"Point"}
}