{
  "type": "Feature",
  "properties": {
    "addr:full":"10 Sawtry Rd, Glatton Huntingdon Bedfordshire PE28 5RZ",
    "addr:housenumber":"10",
    "addr:postcode":"pe28 5rz",
    "addr:street":"Sawtry Rd",
    "iso:country":"GB",
    "sg:address":"10 Sawtry Rd, Glatton",
    "sg:city":"Huntingdon",
    "sg:classifiers":[
        {
            "category":"Government",
            "subcategory":"Post Office",
            "type":"Public Place"
        }
    ],
    "sg:phone":"+44 1487 830243",
    "sg:postcode":"PE28 5RZ",
    "sg:province":"Bedfordshire",
    "wof:name":"Glatton Post Office",
    "wof:placetype":"venue"
},
  "geometry": {"coordinates":[-0.29878,52.455681],"type":"Point"}
}