{
  "type": "Feature",
  "properties": {
    "addr:full":"10a Outram Street Sutton-in-ashfield Nottinghamshire NG17 4AX",
    "addr:housenumber":"10a",
    "addr:postcode":"ng17 4ax",
    "addr:street":"Outram Street",
    "iso:country":"GB",
    "sg:address":"10a Outram Street",
    "sg:city":"Sutton-in-ashfield",
    "sg:classifiers":[
        {
            "category":"Home & Garden",
            "subcategory":"Hardware",
            "type":"Retail Goods"
        }
    ],
    "sg:phone":"+44 1623 553245",
    "sg:postcode":"NG17 4AX",
    "sg:province":"Nottinghamshire",
    "sg:tags":[
        "merchant",
        "plumber",
        "retailer",
        "diy"
    ],
    "sg:website":"http://www.ic24.co.uk",
    "wof:name":"F G Walton Plumbers Merchants",
    "wof:placetype":"venue"
},
  "geometry": {"coordinates":[-1.2588160038,53.1262435913],"type":"Point"}
}