{
  "type": "Feature",
  "properties": {
    "iso:country":"GB",
    "sg:address":"297a Lichfield Road, Four Oaks",
    "sg:city":"Sutton Coldfield",
    "sg:classifiers":[
        {
            "category":"Shopping",
            "subcategory":"Stationery & Office Supplies",
            "type":"Retail Goods"
        }
    ],
    "sg:phone":"+44 121 323 3041",
    "sg:postcode":"B74 4BZ",
    "sg:province":"Staffordshire",
    "sg:tags":[
        "item",
        "promotional"
    ],
    "wof:name":"City Business Gifts Ltd.",
    "wof:placetype":"venue"
},
  "geometry": {"coordinates":[-1.830836,52.588154],"type":"Point"}
}