{
  "type": "Feature",
  "properties": {
    "addr:full":"Green Street Gillingham Kent ME7 5TJ",
    "addr:postcode":"me7 5tj",
    "addr:street":"Green Street",
    "iso:country":"GB",
    "sg:address":"Green Street",
    "sg:city":"Gillingham",
    "sg:classifiers":[
        {
            "category":"Place Of Worship",
            "type":"Public Place"
        }
    ],
    "sg:phone":"+44 1634 578453",
    "sg:postcode":"ME7 5TJ",
    "sg:province":"Kent",
    "wof:name":"Gillingham baptist Church",
    "wof:placetype":"venue"
},
  "geometry": {"coordinates":[0.5462639928,51.3861732483],"type":"Point"}
}