{
  "type": "Feature",
  "properties": {
    "addr:full":"Greenacres, Burned House Lane, Preesall Poulton-le-fylde Lancashire FY6 0PQ",
    "addr:postcode":"fy6 0pq",
    "addr:street":"House Lane;Poulton-Le-Fylde",
    "iso:country":"GB",
    "sg:address":"Greenacres, Burned House Lane, Preesall",
    "sg:city":"Poulton-le-fylde",
    "sg:classifiers":[
        {
            "category":"Farming",
            "subcategory":"Livestock Farm",
            "type":"Manufacturing & Wholesale Goods"
        }
    ],
    "sg:postcode":"FY6 0PQ",
    "sg:province":"Lancashire",
    "sg:tags":[
        "stud"
    ],
    "wof:name":"Burned House Arabian stud",
    "wof:placetype":"venue"
},
  "geometry": {"coordinates":[-2.994659,53.84808],"type":"Point"}
}