{
  "type": "Feature",
  "properties": {
    "iso:country":"GB",
    "sg:address":"97 Lindisfarne, Glascote",
    "sg:city":"Tamworth",
    "sg:classifiers":[
        {
            "category":"Personal",
            "type":"Services"
        }
    ],
    "sg:phone":"+44 1827 312044",
    "sg:postcode":"B77 2QW",
    "sg:province":"Staffordshire",
    "sg:tags":[
        "wedding"
    ],
    "wof:name":"Beautiful Bomboniera & Stationery",
    "wof:placetype":"venue"
},
  "geometry": {"coordinates":[-1.67108,52.620968],"type":"Point"}
}