{
  "type": "Feature",
  "properties": {
    "addr:full":"71 Holgate Road York North Yorkshire YO24 4AA",
    "addr:housenumber":"71",
    "addr:postcode":"yo24 4aa",
    "addr:street":"Holgate Road",
    "iso:country":"GB",
    "sg:address":"71 Holgate Road",
    "sg:city":"York",
    "sg:classifiers":[
        {
            "category":"Professional",
            "subcategory":"Computer Services",
            "type":"Services"
        }
    ],
    "sg:phone":"+44 1904 540932",
    "sg:postcode":"YO24 4AA",
    "sg:province":"North Yorkshire",
    "sg:tags":[
        "system",
        "software"
    ],
    "wof:name":"Unwin Technology Ltd.",
    "wof:placetype":"venue"
},
  "geometry": {"coordinates":[-1.0972189903,53.9537467957],"type":"Point"}
}