{
  "type": "Feature",
  "properties": {
    "addr:full":"47 Warrior Square St Leonards-on-sea East Sussex TN37 6BG",
    "addr:housenumber":"47",
    "addr:postcode":"tn37 6bg",
    "addr:street":"Warrior Square St",
    "iso:country":"GB",
    "sg:address":"47 Warrior Square",
    "sg:city":"St Leonards-on-sea",
    "sg:classifiers":[
        {
            "category":"Education",
            "subcategory":"School",
            "type":"Public Place"
        }
    ],
    "sg:phone":"+44 1424 440889",
    "sg:postcode":"TN37 6BG",
    "sg:province":"East Sussex",
    "sg:tags":[
        "independent",
        "preparatory"
    ],
    "wof:name":"Majors School of English",
    "wof:placetype":"venue"
},
  "geometry": {"coordinates":[0.561949,50.853386],"type":"Point"}
}