{
  "type": "Feature",
  "properties": {
    "addr:full":"127 London Rd Camberley Berkshire GU15 3JY",
    "addr:housenumber":"127",
    "addr:postcode":"gu15 3jy",
    "addr:street":"London Rd",
    "iso:country":"GB",
    "sg:address":"127 London Rd",
    "sg:city":"Camberley",
    "sg:classifiers":[
        {
            "category":"Recreation",
            "subcategory":"Amusement Park",
            "type":"Entertainment"
        }
    ],
    "sg:phone":"+44 1276 27393",
    "sg:postcode":"GU15 3JY",
    "sg:province":"Berkshire",
    "sg:tags":[
        "arcade"
    ],
    "wof:name":"Pooladdy Ltd",
    "wof:placetype":"venue"
},
  "geometry": {"coordinates":[-0.7460409999,51.3396072388],"type":"Point"}
}