{
  "type": "Feature",
  "properties": {
    "iso:country":"GB",
    "sg:address":"Unit 4 Crownfield Works, Wycombe Rd, Saunderton",
    "sg:city":"Princes Risborough",
    "sg:classifiers":[
        {
            "category":"Home & Garden",
            "subcategory":"Hardware",
            "type":"Retail Goods"
        }
    ],
    "sg:phone":"+44 1844 344337",
    "sg:postcode":"HP27 9NR",
    "sg:province":"Buckinghamshire",
    "sg:tags":[
        "paint",
        "coating"
    ],
    "wof:name":"Atlantic Coatings",
    "wof:placetype":"venue"
},
  "geometry": {"coordinates":[-0.8505380154,51.711265564],"type":"Point"}
}