{
  "type": "Feature",
  "properties": {
    "addr:full":"Unit 4, 1b Packington Square London Greater London N1 7UA",
    "addr:housenumber":"unit 4 1b",
    "addr:postcode":"n1 7ua",
    "addr:street":"Packington Square",
    "iso:country":"GB",
    "sg:address":"Unit 4, 1b Packington Square",
    "sg:city":"London",
    "sg:classifiers":[
        {
            "category":"Shopping",
            "subcategory":"Gifts & Souvenirs",
            "type":"Retail Goods"
        }
    ],
    "sg:phone":"+44 20 7704 0446",
    "sg:postcode":"N1 7UA",
    "sg:province":"Greater London",
    "sg:tags":[
        "giftware"
    ],
    "wof:name":"Cold Christmas Designs",
    "wof:placetype":"venue"
},
  "geometry": {"coordinates":[-0.095373,51.535015],"type":"Point"}
}