{
  "type": "Feature",
  "properties": {
    "addr:full":"70 Newington Rd Edinburgh City of Edinburgh EH9 1RD",
    "addr:housenumber":"70",
    "addr:postcode":"eh9 1rd",
    "addr:street":"Newington Rd",
    "iso:country":"GB",
    "sg:address":"70 Newington Rd",
    "sg:city":"Edinburgh",
    "sg:classifiers":[
        {
            "category":"Banks & Credit Unions",
            "subcategory":"Bank",
            "type":"Services"
        }
    ],
    "sg:postcode":"EH9 1RD",
    "sg:province":"City of Edinburgh",
    "wof:name":"Halifax Plc",
    "wof:placetype":"venue"
},
  "geometry": {"coordinates":[-3.1785869598,55.93775177],"type":"Point"}
}