{
  "type": "Feature",
  "properties": {
    "addr:full":"1st Floor Hanger 45, Yatesbury Road Calne Wiltshire SN11 8YR",
    "addr:housenumber":"45",
    "addr:postcode":"sn11 8yr",
    "addr:street":"Yatesbury Road",
    "iso:country":"GB",
    "sg:address":"1st Floor Hanger 45, Yatesbury Road",
    "sg:city":"Calne",
    "sg:classifiers":[
        {
            "category":"Freight",
            "type":"Transportation"
        }
    ],
    "sg:phone":"+44 1249 819230",
    "sg:postcode":"SN11 8YR",
    "sg:province":"Wiltshire",
    "sg:tags":[
        "haulage",
        "road"
    ],
    "wof:name":"J J & S Transport Ltd.",
    "wof:placetype":"venue"
},
  "geometry": {"coordinates":[-2.004912,51.437672],"type":"Point"}
}