{
  "type": "Feature",
  "properties": {
    "addr:full":"23 Main Street, Kirkcolm Stranraer Dumfries and Galloway DG9 0NL",
    "addr:housenumber":"23",
    "addr:postcode":"dg9 0nl",
    "addr:street":"Main Street",
    "iso:country":"GB",
    "sg:address":"23 Main Street, Kirkcolm",
    "sg:city":"Stranraer",
    "sg:classifiers":[
        {
            "category":"Travel",
            "subcategory":"Hotels & Motels",
            "type":"Entertainment"
        }
    ],
    "sg:phone":"+44 1776 853221",
    "sg:postcode":"DG9 0NL",
    "sg:province":"Dumfries and Galloway",
    "wof:name":"Blue Peter Hotel",
    "wof:placetype":"venue"
},
  "geometry": {"coordinates":[-5.0809588432,54.9745597839],"type":"Point"}
}