{
  "type": "Feature",
  "properties": {
    "iso:country":"GB",
    "sg:address":"42 Hornsey Road",
    "sg:city":"London",
    "sg:classifiers":[
        {
            "category":"Personal",
            "subcategory":"Sauna",
            "type":"Services"
        },
        {
            "category":"Retail",
            "subcategory":"Auto Repair",
            "type":"Services"
        }
    ],
    "sg:phone":"+44 20 7700 5393",
    "sg:postcode":"N7 7BP",
    "sg:province":"Greater London",
    "sg:tags":[
        "garage",
        "related"
    ],
    "wof:name":"Aqua Sauna",
    "wof:placetype":"venue"
},
  "geometry": {"coordinates":[-0.110826,51.554043],"type":"Point"}
}