{
  "type": "Feature",
  "properties": {
    "iso:country":"GB",
    "sg:address":"31 Castle Street",
    "sg:city":"East Cowes",
    "sg:classifiers":[
        {
            "category":"Real Estate",
            "subcategory":"Architect",
            "type":"Services"
        }
    ],
    "sg:postcode":"PO32 6RD",
    "sg:province":"Isle of Wight",
    "sg:tags":[
        "technician",
        "architectural"
    ],
    "wof:name":"Richard Mazillius",
    "wof:placetype":"venue"
},
  "geometry": {"coordinates":[-1.289129,50.758373],"type":"Point"}
}