{
  "type": "Feature",
  "properties": {
    "addr:full":"2 Fairview, Bull Street Taunton Devon TA3 5PW",
    "addr:housenumber":"2",
    "addr:postcode":"ta3 5pw",
    "addr:street":"Fairview Bull Street",
    "iso:country":"GB",
    "sg:address":"2 Fairview, Bull Street",
    "sg:city":"Taunton",
    "sg:classifiers":[
        {
            "category":"Building & Trades",
            "subcategory":"Construction",
            "type":"Services"
        }
    ],
    "sg:phone":"+44 1823 443695",
    "sg:postcode":"TA3 5PW",
    "sg:province":"Devon",
    "sg:tags":[
        "builder"
    ],
    "wof:name":"J Hatim & L I Gibbs",
    "wof:placetype":"venue"
},
  "geometry": {"coordinates":[-3.0345699787,51.0218887329],"type":"Point"}
}