{
  "type": "Feature",
  "properties": {
    "iso:country":"GB",
    "sg:address":"Cranford House, 24a Longley Road, Rainham",
    "sg:city":"Gillingham",
    "sg:classifiers":[
        {
            "category":"Freight",
            "type":"Transportation"
        }
    ],
    "sg:phone":"+44 1634 263100",
    "sg:postcode":"ME8 7RT",
    "sg:province":"Kent",
    "sg:tags":[
        "forwarders"
    ],
    "wof:name":"Export Consolidation Services Ltd.",
    "wof:placetype":"venue"
},
  "geometry": {"coordinates":[0.606753,51.364708],"type":"Point"}
}