{
  "type": "Feature",
  "properties": {
    "addr:full":"7 Barton Street Tewkesbury Gloucestershire GL20 5PP",
    "addr:housenumber":"7",
    "addr:postcode":"gl20 5pp",
    "addr:street":"Barton Street",
    "iso:country":"GB",
    "sg:address":"7 Barton Street",
    "sg:city":"Tewkesbury",
    "sg:classifiers":[
        {
            "category":"Building & Trades",
            "subcategory":"Construction",
            "type":"Services"
        }
    ],
    "sg:postcode":"GL20 5PP",
    "sg:province":"Gloucestershire",
    "sg:tags":[
        "builder"
    ],
    "wof:name":"Michael Powles Builders (Welland) Ltd",
    "wof:placetype":"venue"
},
  "geometry": {"coordinates":[-2.1530098915,51.9931259155],"type":"Point"}
}