{
  "type": "Feature",
  "properties": {
    "addr:full":"378 Western Road Leicester Leicestershire LE3 0ED",
    "addr:housenumber":"378",
    "addr:postcode":"le3 0ed",
    "addr:street":"Western Road",
    "iso:country":"GB",
    "sg:address":"378 Western Road",
    "sg:city":"Leicester",
    "sg:classifiers":[
        {
            "category":"Shopping",
            "subcategory":"Clothing, Apparel, & Fashions",
            "type":"Retail Goods"
        }
    ],
    "sg:phone":"+44 116 254 8471",
    "sg:postcode":"LE3 0ED",
    "sg:province":"Leicestershire",
    "sg:tags":[
        "clothing",
        "fabric"
    ],
    "wof:name":"P & G Fashions (Leicester) Ltd.",
    "wof:placetype":"venue"
},
  "geometry": {"coordinates":[-1.149699,52.622051],"type":"Point"}
}