{
  "type": "Feature",
  "properties": {
    "addr:full":"Alexandra Way, Ashchurch Tewkesbury Gloucestershire GL20 8NB",
    "addr:postcode":"gl20 8nb",
    "addr:street":"Alexandra Way",
    "iso:country":"GB",
    "sg:address":"Alexandra Way, Ashchurch",
    "sg:city":"Tewkesbury",
    "sg:classifiers":[
        {
            "category":"Wholesale",
            "subcategory":"Metals & Minerals",
            "type":"Manufacturing & Wholesale Goods"
        },
        {
            "category":"Wholesale",
            "subcategory":"Construction Materials",
            "type":"Manufacturing & Wholesale Goods"
        }
    ],
    "sg:phone":"+44 1684 853500",
    "sg:postcode":"GL20 8NB",
    "sg:province":"Gloucestershire",
    "sg:tags":[
        "supplier",
        "double",
        "aluminium",
        "glazing",
        "stockholder"
    ],
    "wof:name":"Sapa Building Systems Ltd",
    "wof:placetype":"venue"
},
  "geometry": {"coordinates":[-2.1043479443,51.9973754883],"type":"Point"}
}