{
  "type": "Feature",
  "properties": {
    "addr:full":"Marsh Street Stafford Staffordshire ST16 3BG",
    "addr:postcode":"st16 3bg",
    "addr:street":"Marsh Street",
    "iso:country":"GB",
    "sg:address":"Marsh Street",
    "sg:city":"Stafford",
    "sg:classifiers":[
        {
            "category":"Retail",
            "subcategory":"Storage",
            "type":"Services"
        }
    ],
    "sg:phone":"+44 1785 252121",
    "sg:postcode":"ST16 3BG",
    "sg:province":"Staffordshire",
    "sg:tags":[
        "household",
        "removal"
    ],
    "wof:name":"Horsleys of Stafford",
    "wof:placetype":"venue"
},
  "geometry": {"coordinates":[-2.121724,52.816067],"type":"Point"}
}