{
  "type": "Feature",
  "properties": {
    "iso:country":"GB",
    "sg:address":"Hilson Road, Bottings Industrial Estate, Botley",
    "sg:city":"Southampton",
    "sg:classifiers":[
        {
            "category":"Manufacturing",
            "subcategory":"Metals",
            "type":"Manufacturing & Wholesale Goods"
        }
    ],
    "sg:phone":"+44 1489 795559",
    "sg:postcode":"SO30 2GE",
    "sg:province":"Hampshire",
    "sg:tags":[
        "steel",
        "fabricator",
        "erectors"
    ],
    "wof:name":"M & B Metalcraft",
    "wof:placetype":"venue"
},
  "geometry": {"coordinates":[-1.261182,50.916065],"type":"Point"}
}