{
  "type": "Feature",
  "properties": {
    "iso:country":"GB",
    "sg:address":"Newhaven Business Pk, Barton La, Eccles",
    "sg:city":"Manchester",
    "sg:classifiers":[
        {
            "category":"Freight",
            "type":"Transportation"
        }
    ],
    "sg:phone":"+44 161 707 7879",
    "sg:postcode":"M30 0HH",
    "sg:province":"Greater Manchester",
    "sg:tags":[
        "forwarders"
    ],
    "wof:name":"Sureway Logistics Ltd",
    "wof:placetype":"venue"
},
  "geometry": {"coordinates":[-2.340709,53.483456],"type":"Point"}
}