{
  "type": "Feature",
  "properties": {
    "addr:full":"69 Grosvenor Road Tunbridge Wells Kent TN1 2AY",
    "addr:housenumber":"69",
    "addr:postcode":"tn1 2ay",
    "addr:street":"Grosvenor Road",
    "iso:country":"GB",
    "sg:address":"69 Grosvenor Road",
    "sg:city":"Tunbridge Wells",
    "sg:classifiers":[
        {
            "category":"Deli",
            "type":"Food & Drink"
        }
    ],
    "sg:phone":"+44 1892 540334",
    "sg:postcode":"TN1 2AY",
    "sg:province":"Kent",
    "sg:tags":[
        "delivery",
        "sandwich"
    ],
    "wof:name":"The Picnic Basket",
    "wof:placetype":"venue"
},
  "geometry": {"coordinates":[0.261906,51.136662],"type":"Point"}
}