{
  "type": "Feature",
  "properties": {
    "addr:full":"Unit E, Franklin Industrial Estate, 20 Franklin Road London Greater London SE20 8HW",
    "addr:housenumber":"20",
    "addr:postcode":"se20 8hw",
    "addr:street":"Estate;Franklin Road",
    "iso:country":"GB",
    "sg:address":"Unit E, Franklin Industrial Estate, 20 Franklin Road",
    "sg:city":"London",
    "sg:classifiers":[
        {
            "category":"Professional",
            "subcategory":"Engineering",
            "type":"Services"
        }
    ],
    "sg:phone":"+44 20 8676 0710",
    "sg:postcode":"SE20 8HW",
    "sg:province":"Greater London",
    "sg:tags":[
        "precision",
        "engineer"
    ],
    "wof:name":"Paramount Products",
    "wof:placetype":"venue"
},
  "geometry": {"coordinates":[-0.05437,51.41267],"type":"Point"}
}