{
  "type": "Feature",
  "properties": {
    "addr:full":"58 Wrotham Road Welling Kent DA16 1LN",
    "addr:housenumber":"58",
    "addr:postcode":"da16 1ln",
    "addr:street":"Wrotham Road",
    "iso:country":"GB",
    "sg:address":"58 Wrotham Road",
    "sg:city":"Welling",
    "sg:classifiers":[
        {
            "category":"Personal",
            "subcategory":"Beauty Salon",
            "type":"Services"
        },
        {
            "category":"Personal",
            "subcategory":"Barber",
            "type":"Services"
        }
    ],
    "sg:phone":"+44 20 8303 2935",
    "sg:postcode":"DA16 1LN",
    "sg:province":"Kent",
    "sg:tags":[
        "unisex",
        "hairdresser"
    ],
    "wof:name":"One Step Beyond",
    "wof:placetype":"venue"
},
  "geometry": {"coordinates":[0.121278,51.468884],"type":"Point"}
}