{
  "type": "Feature",
  "properties": {
    "iso:country":"GB",
    "sg:address":"Brentwood Road",
    "sg:city":"Romford",
    "sg:classifiers":[
        {
            "category":"Place Of Worship",
            "type":"Public Place"
        }
    ],
    "sg:phone":"+44 1708 769868",
    "sg:postcode":"RM1 2RT",
    "sg:province":"Essex",
    "wof:name":"Romford Evangelical Free Church",
    "wof:placetype":"venue"
},
  "geometry": {"coordinates":[0.19912,51.574314],"type":"Point"}
}