{
  "type": "Feature",
  "properties": {
    "addr:full":"24 Mottingham Rd Eltham Greater London SE9 4QW",
    "addr:housenumber":"24",
    "addr:postcode":"se9 4qw",
    "addr:street":"Mottingham Rd",
    "iso:country":"GB",
    "sg:address":"24 Mottingham Rd",
    "sg:city":"Eltham",
    "sg:classifiers":[
        {
            "category":"Bars & Pubs",
            "type":"Food & Drink"
        }
    ],
    "sg:phone":"+44 20 8857 6901",
    "sg:postcode":"SE9 4QW",
    "sg:province":"Greater London",
    "sg:tags":[
        "pubs",
        "house",
        "inn",
        "public",
        "activity"
    ],
    "wof:name":"The Porcupine",
    "wof:placetype":"venue"
},
  "geometry": {"coordinates":[0.04318,51.43729],"type":"Point"}
}