{
  "type": "Feature",
  "properties": {
    "addr:full":"79 St James Avenue Ramsgate Kent CT12 6DZ",
    "addr:housenumber":"79",
    "addr:postcode":"ct12 6dz",
    "addr:street":"St James Avenue Ramsgate",
    "iso:country":"GB",
    "sg:address":"79 St James Avenue",
    "sg:city":"Ramsgate",
    "sg:classifiers":[
        {
            "category":"Building & Trades",
            "subcategory":"Plumbing",
            "type":"Services"
        }
    ],
    "sg:phone":"+44 1843 593181",
    "sg:postcode":"CT12 6DZ",
    "sg:province":"Kent",
    "sg:tags":[
        "plumber",
        "heating"
    ],
    "wof:name":"JOHN R DORKINGS",
    "wof:placetype":"venue"
},
  "geometry": {"coordinates":[1.401385,51.347519],"type":"Point"}
}