{
  "type": "Feature",
  "properties": {
    "addr:full":"18 Red Cat Lane, Burscough Ormskirk Ormskirk Lancashire L40 0RD",
    "addr:housenumber":"18",
    "addr:postcode":"l40 0rd",
    "addr:street":"Red Cat Lane",
    "iso:country":"GB",
    "sg:address":"18 Red Cat Lane, Burscough Ormskirk",
    "sg:city":"Ormskirk",
    "sg:classifiers":[
        {
            "category":"Home & Garden",
            "subcategory":"Hardware",
            "type":"Retail Goods"
        }
    ],
    "sg:phone":"+44 1704 896656",
    "sg:postcode":"L40 0RD",
    "sg:province":"Lancashire",
    "sg:tags":[
        "heat",
        "mech",
        "exchanger"
    ],
    "wof:name":"Lydiate Associates",
    "wof:placetype":"venue"
},
  "geometry": {"coordinates":[-2.8414039612,53.6061553955],"type":"Point"}
}