{
  "type": "Feature",
  "properties": {
    "iso:country":"GB",
    "sg:address":"1340 London Rd",
    "sg:city":"Leigh On Sea",
    "sg:classifiers":[
        {
            "category":"Personal",
            "type":"Services"
        }
    ],
    "sg:phone":"+44 1702 480567",
    "sg:postcode":"SS9 2UH",
    "sg:province":"Essex",
    "sg:tags":[
        "wedding"
    ],
    "wof:name":"Bridal Workshop The",
    "wof:placetype":"venue"
},
  "geometry": {"coordinates":[0.6391389966,51.5477638245],"type":"Point"}
}