{
  "type": "Feature",
  "properties": {
    "iso:country":"GB",
    "sg:address":"47 Park Street",
    "sg:city":"Leamington Spa",
    "sg:classifiers":[
        {
            "category":"Professional",
            "subcategory":"Art Services",
            "type":"Services"
        }
    ],
    "sg:phone":"+44 1926 422248",
    "sg:postcode":"CV32 4QN",
    "sg:province":"Warwickshire",
    "sg:tags":[
        "framing"
    ],
    "wof:name":"Pendragon Studio",
    "wof:placetype":"venue"
},
  "geometry": {"coordinates":[-1.5332700014,52.2908058167],"type":"Point"}
}