{
  "type": "Feature",
  "properties": {
    "addr:full":"The Hoath Farm, Bekesbourne La Canterbury Kent CT3 4AB",
    "addr:postcode":"ct3 4ab",
    "addr:street":"Bekesbourne La Canterbury",
    "iso:country":"GB",
    "sg:address":"The Hoath Farm, Bekesbourne La",
    "sg:city":"Canterbury",
    "sg:classifiers":[
        {
            "category":"Farming",
            "subcategory":"Livestock Farm",
            "type":"Manufacturing & Wholesale Goods"
        }
    ],
    "sg:postcode":"CT3 4AB",
    "sg:province":"Kent",
    "sg:tags":[
        "others"
    ],
    "wof:name":"Rickards Farms",
    "wof:placetype":"venue"
},
  "geometry": {"coordinates":[1.15446,51.333824],"type":"Point"}
}