{
  "type": "Feature",
  "properties": {
    "iso:country":"GB",
    "sg:address":"7 Lavant Street",
    "sg:city":"Petersfield",
    "sg:classifiers":[
        {
            "category":"Shopping",
            "subcategory":"Books",
            "type":"Retail Goods"
        },
        {
            "category":"Utilities",
            "subcategory":"Sewage",
            "type":"Services"
        }
    ],
    "sg:phone":"+44 1730 261199",
    "sg:postcode":"GU32 3EL",
    "sg:province":"Hampshire",
    "sg:tags":[
        "forestry",
        "adviser",
        "bookseller"
    ],
    "wof:name":"One Tree Books",
    "wof:placetype":"venue"
},
  "geometry": {"coordinates":[-0.938706,51.005436],"type":"Point"}
}