{
  "type": "Feature",
  "properties": {
    "iso:country":"GB",
    "sg:address":"Unit 2-3 Brook Farm",
    "sg:city":"Reigate",
    "sg:classifiers":[
        {
            "category":"Shopping",
            "subcategory":"Computers & Home Electronics",
            "type":"Retail Goods"
        }
    ],
    "sg:postcode":"RH2 8NR",
    "sg:province":"Surrey",
    "wof:name":"Darek Kubik",
    "wof:placetype":"venue"
},
  "geometry": {"coordinates":[-0.2097190022,51.2242393494],"type":"Point"}
}