{
  "type": "Feature",
  "properties": {
    "iso:country":"GB",
    "sg:address":"13 Hawthorne Road",
    "sg:city":"Bootle",
    "sg:classifiers":[
        {
            "category":"Personal",
            "subcategory":"Nail Salon",
            "type":"Services"
        }
    ],
    "sg:phone":"+44 151 933 4217",
    "sg:postcode":"L20 2DG",
    "sg:province":"Merseyside",
    "sg:tags":[
        "solarium",
        "tanning"
    ],
    "wof:name":"Sea Breeze",
    "wof:placetype":"venue"
},
  "geometry": {"coordinates":[-2.9815139771,53.4427490234],"type":"Point"}
}