{
  "type": "Feature",
  "properties": {
    "addr:full":"137 Sydenham Road London Greater London SE26 5HB",
    "addr:housenumber":"137",
    "addr:postcode":"se26 5hb",
    "addr:street":"Sydenham Road",
    "iso:country":"GB",
    "sg:address":"137 Sydenham Road",
    "sg:city":"London",
    "sg:classifiers":[
        {
            "category":"Fast Food",
            "type":"Food & Drink"
        }
    ],
    "sg:phone":"+44 20 8778 5806",
    "sg:postcode":"SE26 5HB",
    "sg:province":"Greater London",
    "sg:tags":[
        "away",
        "take"
    ],
    "wof:name":"Sydenham Kebab House",
    "wof:placetype":"venue"
},
  "geometry": {"coordinates":[-0.0481240004,51.4258460999],"type":"Point"}
}