{
  "type": "Feature",
  "properties": {
    "iso:country":"GB",
    "sg:address":"68 High Street",
    "sg:city":"Dalbeattie",
    "sg:classifiers":[
        {
            "category":"Shopping",
            "subcategory":"Jewelry",
            "type":"Retail Goods"
        }
    ],
    "sg:phone":"+44 1556 610700",
    "sg:postcode":"DG5 4HB",
    "sg:province":"Dumfries and Galloway",
    "sg:tags":[
        "gold",
        "silversmith"
    ],
    "wof:name":"Heather Glen of Scotland",
    "wof:placetype":"venue"
},
  "geometry": {"coordinates":[-3.821053,54.932114],"type":"Point"}
}