{
  "type": "Feature",
  "properties": {
    "iso:country":"GB",
    "sg:address":"London Rd",
    "sg:city":"Sevenoaks",
    "sg:classifiers":[
        {
            "category":"Autos & Motor Vehicles",
            "subcategory":"Fuel & Gas Station",
            "type":"Retail Goods"
        }
    ],
    "sg:phone":"+44 1732 780132",
    "sg:postcode":"TN15 7RR",
    "sg:province":"Kent",
    "sg:tags":[
        "hr",
        "petrol"
    ],
    "wof:name":"Total Wrothan",
    "wof:placetype":"venue"
},
  "geometry": {"coordinates":[0.285105,51.328121],"type":"Point"}
}