{
  "type": "Feature",
  "properties": {
    "addr:full":"51 Connor Road Dagenham Essex RM9 5UL",
    "addr:housenumber":"51",
    "addr:postcode":"rm9 5ul",
    "addr:street":"Connor Road",
    "iso:country":"GB",
    "sg:address":"51 Connor Road",
    "sg:city":"Dagenham",
    "sg:classifiers":[
        {
            "category":"Building & Trades",
            "subcategory":"Construction",
            "type":"Services"
        }
    ],
    "sg:postcode":"RM9 5UL",
    "sg:province":"Essex",
    "sg:tags":[
        "builder"
    ],
    "wof:name":"D & T Builders",
    "wof:placetype":"venue"
},
  "geometry": {"coordinates":[0.144165,51.552357],"type":"Point"}
}