{
  "type": "Feature",
  "properties": {
    "addr:full":"514 Westhorne Ave Eltham Greater London SE9 6DH",
    "addr:housenumber":"514",
    "addr:postcode":"se9 6dh",
    "addr:street":"Westhorne Ave",
    "iso:country":"GB",
    "sg:address":"514 Westhorne Ave",
    "sg:city":"Eltham",
    "sg:classifiers":[
        {
            "category":"Utilities",
            "subcategory":"Refuse",
            "type":"Services"
        }
    ],
    "sg:phone":"+44 20 8265 4245",
    "sg:postcode":"SE9 6DH",
    "sg:province":"Greater London",
    "sg:tags":[
        "disposal",
        "waste"
    ],
    "wof:name":"C L Clearance",
    "wof:placetype":"venue"
},
  "geometry": {"coordinates":[0.038048,51.453945],"type":"Point"}
}