{
  "type": "Feature",
  "properties": {
    "addr:full":"Unit 1 Prospect Works, 216 Sydenham Road Croydon Surrey CR0 2EB",
    "addr:housenumber":"unit 1;216",
    "addr:postcode":"cr0 2eb",
    "addr:street":"Prospect Works;Sydenham Road",
    "iso:country":"GB",
    "sg:address":"Unit 1 Prospect Works, 216 Sydenham Road",
    "sg:city":"Croydon",
    "sg:classifiers":[
        {
            "category":"Retail",
            "subcategory":"Auto Repair",
            "type":"Services"
        }
    ],
    "sg:phone":"+44 20 8684 2002",
    "sg:postcode":"CR0 2EB",
    "sg:province":"Surrey",
    "sg:tags":[
        "modification",
        "garage"
    ],
    "wof:name":"P D Motors",
    "wof:placetype":"venue"
},
  "geometry": {"coordinates":[-0.0934500024,51.3830490112],"type":"Point"}
}