{
  "type": "Feature",
  "properties": {
    "addr:full":"23 Coronation Crescent Crewe Cheshire CW1 4EP",
    "addr:housenumber":"23",
    "addr:postcode":"cw1 4ep",
    "addr:street":"Coronation Crescent",
    "iso:country":"GB",
    "sg:address":"23 Coronation Crescent",
    "sg:city":"Crewe",
    "sg:classifiers":[
        {
            "category":"Shopping",
            "subcategory":"News",
            "type":"Retail Goods"
        }
    ],
    "sg:phone":"+44 1270 584745",
    "sg:postcode":"CW1 4EP",
    "sg:province":"Cheshire",
    "sg:tags":[
        "newsagent"
    ],
    "wof:name":"Crescent Newsagents",
    "wof:placetype":"venue"
},
  "geometry": {"coordinates":[-2.4333090782,53.106464386],"type":"Point"}
}