{
  "type": "Feature",
  "properties": {
    "addr:full":"147 Heol Y Llwynau, Trebanos Pontardawe Swansea Neath Port Talbot SA8 4DB",
    "addr:housenumber":"147",
    "addr:postcode":"sa8 4db",
    "addr:street":"Heol Y Llwynau Trebanos",
    "iso:country":"GB",
    "sg:address":"147 Heol Y Llwynau, Trebanos Pontardawe",
    "sg:city":"Swansea",
    "sg:classifiers":[
        {
            "category":"Utilities",
            "subcategory":"Fuel Oil & Lpg",
            "type":"Services"
        }
    ],
    "sg:phone":"+44 1792 846602",
    "sg:postcode":"SA8 4DB",
    "sg:province":"Neath Port Talbot",
    "wof:name":"Thomas Brothers",
    "wof:placetype":"venue"
},
  "geometry": {"coordinates":[-3.8703649044,51.7061538696],"type":"Point"}
}