{
  "type": "Feature",
  "properties": {
    "iso:country":"GB",
    "sg:address":"11 Alexandra Road",
    "sg:city":"Sale",
    "sg:classifiers":[
        {
            "category":"Organizations",
            "subcategory":"Non-profit Organization",
            "type":"Services"
        }
    ],
    "sg:phone":"+44 161 905 3344",
    "sg:postcode":"M33 3EF",
    "sg:province":"Cheshire",
    "sg:tags":[
        "alarm",
        "system"
    ],
    "wof:name":"A S I",
    "wof:placetype":"venue"
},
  "geometry": {"coordinates":[-2.3105180264,53.420085907],"type":"Point"}
}