{
  "type": "Feature",
  "properties": {
    "iso:country":"GB",
    "sg:address":"58 John Street",
    "sg:city":"Penicuik",
    "sg:classifiers":[
        {
            "category":"Organizations",
            "subcategory":"Professional Association",
            "type":"Services"
        }
    ],
    "sg:phone":"+44 1968 673409",
    "sg:postcode":"EH26 8NE",
    "sg:province":"Midlothian",
    "sg:tags":[
        "literary",
        "agent"
    ],
    "wof:name":"David Fletcher Associates",
    "wof:placetype":"venue"
},
  "geometry": {"coordinates":[-3.223409,55.829529],"type":"Point"}
}