{
  "type": "Feature",
  "properties": {
    "iso:country":"GB",
    "sg:address":"10 Grange Road",
    "sg:city":"Rhyl",
    "sg:classifiers":[
        {
            "category":"Shopping",
            "subcategory":"News",
            "type":"Retail Goods"
        }
    ],
    "sg:phone":"+44 1745 350050",
    "sg:postcode":"LL18 4RF",
    "sg:province":"Conwy",
    "sg:tags":[
        "newsagent"
    ],
    "wof:name":"V A & S E McGuire",
    "wof:placetype":"venue"
},
  "geometry": {"coordinates":[-3.481457,53.320553],"type":"Point"}
}