{
  "type": "Feature",
  "properties": {
    "addr:full":"77 Harrington Road, Loddington Kettering Northamptonshire NN14 1JZ",
    "addr:housenumber":"77",
    "addr:postcode":"nn14 1jz",
    "addr:street":"Harrington Road",
    "iso:country":"GB",
    "sg:address":"77 Harrington Road, Loddington",
    "sg:city":"Kettering",
    "sg:classifiers":[
        {
            "category":"Wholesale",
            "subcategory":"Sporting Goods",
            "type":"Manufacturing & Wholesale Goods"
        }
    ],
    "sg:postcode":"NN14 1JZ",
    "sg:province":"Northamptonshire",
    "sg:tags":[
        "mnfr",
        "sport",
        "equipment"
    ],
    "wof:name":"Clan Marketing Co",
    "wof:placetype":"venue"
},
  "geometry": {"coordinates":[-0.8024640083,52.3959579468],"type":"Point"}
}