{
  "type": "Feature",
  "properties": {
    "iso:country":"GB",
    "sg:address":"10 Twist Lane",
    "sg:city":"Leigh",
    "sg:classifiers":[
        {
            "category":"Home & Garden",
            "subcategory":"Household Appliances",
            "type":"Retail Goods"
        }
    ],
    "sg:phone":"+44 1942 676110",
    "sg:postcode":"WN7 4DA",
    "sg:province":"Lancashire",
    "sg:tags":[
        "electrical"
    ],
    "wof:name":"Leigh Washers & Vacuum Cleaners",
    "wof:placetype":"venue"
},
  "geometry": {"coordinates":[-2.520488,53.495174],"type":"Point"}
}