{
  "type": "Feature",
  "properties": {
    "addr:full":"17 Upper King Street Norwich Norfolk NR3 1RB",
    "addr:housenumber":"17",
    "addr:postcode":"nr3 1rb",
    "addr:street":"Upper King Street",
    "iso:country":"GB",
    "sg:address":"17 Upper King Street",
    "sg:city":"Norwich",
    "sg:classifiers":[
        {
            "category":"Organizations",
            "subcategory":"Membership Organization",
            "type":"Services"
        }
    ],
    "sg:phone":"+44 1603 610652",
    "sg:postcode":"NR3 1RB",
    "sg:province":"Norfolk",
    "sg:tags":[
        "club"
    ],
    "wof:name":"Norfolk Club",
    "wof:placetype":"venue"
},
  "geometry": {"coordinates":[1.2990260124,52.629863739],"type":"Point"}
}