{
  "type": "Feature",
  "properties": {
    "addr:full":"19 Station Road Birchington Kent CT7 9DJ",
    "addr:housenumber":"19",
    "addr:postcode":"ct7 9dj",
    "addr:street":"Station Road",
    "iso:country":"GB",
    "sg:address":"19 Station Road",
    "sg:city":"Birchington",
    "sg:classifiers":[
        {
            "category":"Real Estate",
            "subcategory":"Real Estate Agent",
            "type":"Services"
        }
    ],
    "sg:phone":"+44 1843 296748",
    "sg:postcode":"CT7 9DJ",
    "sg:province":"Kent",
    "wof:name":"Village Property Services",
    "wof:placetype":"venue"
},
  "geometry": {"coordinates":[1.30629,51.374451],"type":"Point"}
}