{
  "type": "Feature",
  "properties": {
    "iso:country":"GB",
    "sg:address":"The Green, High Street, Bugbrooke",
    "sg:city":"Northampton",
    "sg:classifiers":[
        {
            "category":"Shopping",
            "subcategory":"Florist",
            "type":"Retail Goods"
        }
    ],
    "sg:phone":"+44 1604 830084",
    "sg:postcode":"NN7 3PG",
    "sg:province":"Buckinghamshire",
    "wof:name":"Cherrenee",
    "wof:placetype":"venue"
},
  "geometry": {"coordinates":[-1.010495,52.212185],"type":"Point"}
}