{
  "type": "Feature",
  "properties": {
    "iso:country":"GB",
    "sg:address":"404 Kingsland Rd",
    "sg:city":"Hackney",
    "sg:classifiers":[
        {
            "category":"Food & Beverages",
            "subcategory":"Bakery",
            "type":"Retail Goods"
        }
    ],
    "sg:phone":"+44 20 7923 7575",
    "sg:postcode":"E8 4AA",
    "sg:province":"Greater London",
    "sg:tags":[
        "pizza"
    ],
    "wof:name":"Orlando Pizza",
    "wof:placetype":"venue"
},
  "geometry": {"coordinates":[-0.0759949982,51.5415306091],"type":"Point"}
}