{
  "type": "Feature",
  "properties": {
    "iso:country":"GB",
    "sg:address":"107 Clearwater Road",
    "sg:city":"Newport",
    "sg:classifiers":[
        {
            "category":"Manufacturing",
            "subcategory":"Motor Vehicles & Parts",
            "type":"Manufacturing & Wholesale Goods"
        }
    ],
    "sg:phone":"+44 1633 272766",
    "sg:postcode":"NP19 4ST",
    "sg:province":"Newport",
    "sg:tags":[
        "bearing"
    ],
    "wof:name":"Mecro",
    "wof:placetype":"venue"
},
  "geometry": {"coordinates":[-2.944134,51.569065],"type":"Point"}
}