{
  "type": "Feature",
  "properties": {
    "addr:full":"413 Harrow Road London Greater London W9 3QJ",
    "addr:housenumber":"413",
    "addr:postcode":"w9 3qj",
    "addr:street":"Harrow Road",
    "iso:country":"GB",
    "sg:address":"413 Harrow Road",
    "sg:city":"London",
    "sg:classifiers":[
        {
            "category":"Fast Food",
            "type":"Food & Drink"
        }
    ],
    "sg:phone":"+44 20 8960 5552",
    "sg:postcode":"W9 3QJ",
    "sg:province":"Greater London",
    "sg:tags":[
        "away",
        "take"
    ],
    "wof:name":"Anam Tandoori Home Delivery",
    "wof:placetype":"venue"
},
  "geometry": {"coordinates":[-0.2044419944,51.5255470276],"type":"Point"}
}