{
  "type": "Feature",
  "properties": {
    "iso:country":"GB",
    "sg:address":"637 Birmingham New Rd, Coseley",
    "sg:city":"Bilston",
    "sg:classifiers":[
        {
            "category":"Freight",
            "type":"Transportation"
        }
    ],
    "sg:postcode":"WV14 9JL",
    "sg:province":"West Midlands",
    "sg:tags":[
        "haulage",
        "road"
    ],
    "wof:name":"Interfresh Transport Ltd",
    "wof:placetype":"venue"
},
  "geometry": {"coordinates":[-2.090112,52.542358],"type":"Point"}
}