{
  "type": "Feature",
  "properties": {
    "addr:full":"Unit 3 Novershill Trading Estate, Bedminster Bristol City of Bristol BS3 5QY",
    "addr:housenumber":"unit 3",
    "addr:postcode":"bs3 5qy",
    "addr:street":"Trading Estate",
    "iso:country":"GB",
    "sg:address":"Unit 3 Novershill Trading Estate, Bedminster",
    "sg:city":"Bristol",
    "sg:classifiers":[
        {
            "category":"Professional",
            "subcategory":"Engineering",
            "type":"Services"
        }
    ],
    "sg:phone":"+44 117 966 1224",
    "sg:postcode":"BS3 5QY",
    "sg:province":"City of Bristol",
    "sg:tags":[
        "engineer",
        "mechanical"
    ],
    "wof:name":"West of England Group Ltd.",
    "wof:placetype":"venue"
},
  "geometry": {"coordinates":[-2.6006810665,51.4285354614],"type":"Point"}
}