{
  "type": "Feature",
  "properties": {
    "iso:country":"GB",
    "sg:address":"154 Haxby Road",
    "sg:city":"York",
    "sg:classifiers":[
        {
            "category":"Education",
            "subcategory":"School",
            "type":"Public Place"
        },
        {
            "category":"Government",
            "subcategory":"Office",
            "type":"Public Place"
        }
    ],
    "sg:phone":"+44 1904 653218",
    "sg:postcode":"YO31 8JN",
    "sg:province":"North Yorkshire",
    "sg:tags":[
        "local",
        "authority"
    ],
    "wof:name":"Haxby Road Primary School",
    "wof:placetype":"venue"
},
  "geometry": {"coordinates":[-1.077769,53.972202],"type":"Point"}
}