{
  "type": "Feature",
  "properties": {
    "addr:full":"28 Hightown Crewe Cheshire CW1 3BS",
    "addr:housenumber":"28",
    "addr:postcode":"cw1 3bs",
    "addr:street":"Hightown",
    "iso:country":"GB",
    "sg:address":"28 Hightown",
    "sg:city":"Crewe",
    "sg:classifiers":[
        {
            "category":"Community Center",
            "subcategory":"Youth",
            "type":"Public Place"
        }
    ],
    "sg:phone":"+44 1270 587543",
    "sg:postcode":"CW1 3BS",
    "sg:province":"Cheshire",
    "sg:tags":[
        "organisation",
        "centre"
    ],
    "wof:name":"The Information Shop for Young People Crewe Ltd.",
    "wof:placetype":"venue"
},
  "geometry": {"coordinates":[-2.4472138882,53.0997123718],"type":"Point"}
}