{
  "type": "Feature",
  "properties": {
    "addr:full":"Tongland Kirkcudbright Dumfries and Galloway DG6 4NA",
    "addr:postcode":"dg6 4na",
    "iso:country":"GB",
    "sg:address":"Tongland",
    "sg:city":"Kirkcudbright",
    "sg:classifiers":[
        {
            "category":"Home & Garden",
            "subcategory":"Garden Supply",
            "type":"Retail Goods"
        }
    ],
    "sg:phone":"+44 1557 330798",
    "sg:postcode":"DG6 4NA",
    "sg:province":"Dumfries and Galloway",
    "sg:tags":[
        "nursery",
        "centre"
    ],
    "wof:name":"Meikle Yett Nursery",
    "wof:placetype":"venue"
},
  "geometry": {"coordinates":[-4.0422539711,54.84375],"type":"Point"}
}