{
  "type": "Feature",
  "properties": {
    "addr:full":"22 Corfton Road London Greater London W5 2HT",
    "addr:housenumber":"22",
    "addr:postcode":"w5 2ht",
    "addr:street":"Corfton Road",
    "iso:country":"GB",
    "sg:address":"22 Corfton Road",
    "sg:city":"London",
    "sg:classifiers":[
        {
            "category":"Health Services",
            "subcategory":"Doctor",
            "type":"Services"
        }
    ],
    "sg:phone":"+44 20 8991 6699",
    "sg:postcode":"W5 2HT",
    "sg:province":"Greater London",
    "sg:tags":[
        "psychiatrist"
    ],
    "wof:name":"Cygnet Hospital Ealing",
    "wof:placetype":"venue"
},
  "geometry": {"coordinates":[-0.2982310057,51.5198745728],"type":"Point"}
}