{
  "type": "Feature",
  "properties": {
    "addr:full":"207 Warsash Road, Warsash Southampton Hampshire SO31 9JE",
    "addr:housenumber":"207",
    "addr:postcode":"so31 9je",
    "addr:street":"Warsash Road",
    "iso:country":"GB",
    "sg:address":"207 Warsash Road, Warsash",
    "sg:city":"Southampton",
    "sg:classifiers":[
        {
            "category":"Manufacturing",
            "subcategory":"Building Materials",
            "type":"Manufacturing & Wholesale Goods"
        }
    ],
    "sg:phone":"+44 1489 573406",
    "sg:postcode":"SO31 9JE",
    "sg:province":"Hampshire",
    "sg:tags":[
        "flag",
        "banner"
    ],
    "wof:name":"Needlespar Ltd.",
    "wof:placetype":"venue"
},
  "geometry": {"coordinates":[-1.292609,50.851372],"type":"Point"}
}