{
  "type": "Feature",
  "properties": {
    "iso:country":"GB",
    "sg:address":"Bevan House 9-11 Bancroft Court",
    "sg:city":"Hitchin",
    "sg:classifiers":[
        {
            "category":"Government",
            "subcategory":"Post Office",
            "type":"Public Place"
        }
    ],
    "sg:postcode":"SG5 1LH",
    "sg:province":"Bedfordshire",
    "sg:tags":[
        "organisation",
        "soc",
        "research"
    ],
    "wof:name":"Statwood Ltd.",
    "wof:placetype":"venue"
},
  "geometry": {"coordinates":[-0.2778809965,51.9491996765],"type":"Point"}
}