{
  "type": "Feature",
  "properties": {
    "addr:full":"10 Repton Avenue, Gidea Park Romford Essex RM2 5LU",
    "addr:housenumber":"10",
    "addr:postcode":"rm2 5lu",
    "addr:street":"Repton Avenue",
    "iso:country":"GB",
    "sg:address":"10 Repton Avenue, Gidea Park",
    "sg:city":"Romford",
    "sg:classifiers":[
        {
            "category":"Building & Trades",
            "subcategory":"Cleaning & Sanitation",
            "type":"Services"
        }
    ],
    "sg:phone":"+44 1708 744600",
    "sg:postcode":"RM2 5LU",
    "sg:province":"Essex",
    "sg:tags":[
        "commercial"
    ],
    "wof:name":"Gidea Park Cleaning Services Ltd.",
    "wof:placetype":"venue"
},
  "geometry": {"coordinates":[0.19667,51.584381],"type":"Point"}
}