{
  "type": "Feature",
  "properties": {
    "addr:full":"Frobisher House, 3 High Street, Sawtry Huntingdon Bedfordshire PE28 5SR",
    "addr:housenumber":"3",
    "addr:postcode":"pe28 5sr",
    "addr:street":"High Street",
    "iso:country":"GB",
    "sg:address":"Frobisher House, 3 High Street, Sawtry",
    "sg:city":"Huntingdon",
    "sg:classifiers":[
        {
            "category":"Farming",
            "subcategory":"Farm",
            "type":"Manufacturing & Wholesale Goods"
        }
    ],
    "sg:phone":"+44 1487 830968",
    "sg:postcode":"PE28 5SR",
    "sg:province":"Bedfordshire",
    "sg:tags":[
        "agricultural"
    ],
    "wof:name":"R J C Commercial Food Equipment",
    "wof:placetype":"venue"
},
  "geometry": {"coordinates":[-0.284575,52.439129],"type":"Point"}
}