{
  "type": "Feature",
  "properties": {
    "addr:full":"40 Repps Rd, Martham Great Yarmouth Norfolk NR29 4QT",
    "addr:housenumber":"40",
    "addr:postcode":"nr29 4qt",
    "addr:street":"Repps Rd",
    "iso:country":"GB",
    "sg:address":"40 Repps Rd, Martham",
    "sg:city":"Great Yarmouth",
    "sg:classifiers":[
        {
            "category":"Professional",
            "subcategory":"Detective & Security Services",
            "type":"Services"
        }
    ],
    "sg:phone":"+44 1493 748606",
    "sg:postcode":"NR29 4QT",
    "sg:province":"Norfolk",
    "wof:name":"Manned Security",
    "wof:placetype":"venue"
},
  "geometry": {"coordinates":[1.630589,52.702568],"type":"Point"}
}