{
  "type": "Feature",
  "properties": {
    "addr:full":"Meadow House, London Road, West Kingsdown Sevenoaks Kent TN15 6ER",
    "addr:postcode":"tn15 6er",
    "addr:street":"London Road West",
    "iso:country":"GB",
    "sg:address":"Meadow House, London Road, West Kingsdown",
    "sg:city":"Sevenoaks",
    "sg:classifiers":[
        {
            "category":"Autos & Motor Vehicles",
            "subcategory":"Automobile Sales",
            "type":"Retail Goods"
        }
    ],
    "sg:phone":"+44 1474 854288",
    "sg:postcode":"TN15 6ER",
    "sg:province":"Kent",
    "sg:tags":[
        "commercial"
    ],
    "wof:name":"Nelson R King",
    "wof:placetype":"venue"
},
  "geometry": {"coordinates":[0.2795459926,51.3325767517],"type":"Point"}
}