{
  "type": "Feature",
  "properties": {
    "addr:full":"Rice Lane, Flaxton York North Yorkshire YO60 7PZ",
    "addr:postcode":"yo60 7pz",
    "addr:street":"Rice Lane",
    "iso:country":"GB",
    "sg:address":"Rice Lane, Flaxton",
    "sg:city":"York",
    "sg:classifiers":[
        {
            "category":"Autos & Motor Vehicles",
            "subcategory":"Motorcycle Sales",
            "type":"Retail Goods"
        }
    ],
    "sg:phone":"+44 1904 468692",
    "sg:postcode":"YO60 7PZ",
    "sg:province":"North Yorkshire",
    "wof:name":"Yortech Racing",
    "wof:placetype":"venue"
},
  "geometry": {"coordinates":[-0.965227,54.05344],"type":"Point"}
}