{
  "type": "Feature",
  "properties": {
    "addr:full":"Unit 2 Eastlands Court, Wade Road Basingstoke Hampshire RG24 8PL",
    "addr:housenumber":"unit 2",
    "addr:postcode":"rg24 8pl",
    "addr:street":"Eastlands Court Wade Road",
    "iso:country":"GB",
    "sg:address":"Unit 2 Eastlands Court, Wade Road",
    "sg:city":"Basingstoke",
    "sg:classifiers":[
        {
            "category":"Insurance",
            "subcategory":"Insurance Agent",
            "type":"Services"
        }
    ],
    "sg:phone":"+44 1256 816366",
    "sg:postcode":"RG24 8PL",
    "sg:province":"Hampshire",
    "wof:name":"Choice Quote Insurances",
    "wof:placetype":"venue"
},
  "geometry": {"coordinates":[-1.0626649857,51.2837257385],"type":"Point"}
}