{
  "type": "Feature",
  "properties": {
    "addr:full":"32 St Andrews Road Bridport Dorset DT6 3BQ",
    "addr:housenumber":"32",
    "addr:postcode":"dt6 3bq",
    "addr:street":"St Andrews Road",
    "iso:country":"GB",
    "sg:address":"32 St Andrews Road",
    "sg:city":"Bridport",
    "sg:classifiers":[
        {
            "category":"Social Services",
            "type":"Services"
        },
        {
            "category":"Health Services",
            "subcategory":"Nursing And Care Facility",
            "type":"Services"
        }
    ],
    "sg:phone":"+44 1308 422159",
    "sg:postcode":"DT6 3BQ",
    "sg:province":"Dorset",
    "sg:tags":[
        "home",
        "disability"
    ],
    "wof:name":"Dorset Nursing Residential Home",
    "wof:placetype":"venue"
},
  "geometry": {"coordinates":[-2.750968,50.73497],"type":"Point"}
}