{
  "type": "Feature",
  "properties": {
    "iso:country":"GB",
    "sg:address":"35 Grenville Road, Hazel Gro",
    "sg:city":"Stockport",
    "sg:classifiers":[
        {
            "category":"Building & Trades",
            "subcategory":"Construction",
            "type":"Services"
        }
    ],
    "sg:phone":"+44 161 487 1299",
    "sg:postcode":"SK7 5AF",
    "sg:province":"Cheshire",
    "sg:tags":[
        "decorator",
        "painter"
    ],
    "wof:name":"Kevin Donnelly",
    "wof:placetype":"venue"
},
  "geometry": {"coordinates":[-2.128037,53.382],"type":"Point"}
}