{
  "type": "Feature",
  "properties": {
    "addr:full":"12-14 Pittville Lawn Cheltenham Gloucestershire GL52 2BD",
    "addr:housenumber":"12-14",
    "addr:postcode":"gl52 2bd",
    "addr:street":"Pittville Lawn",
    "iso:country":"GB",
    "sg:address":"12-14 Pittville Lawn",
    "sg:city":"Cheltenham",
    "sg:classifiers":[
        {
            "category":"Health Services",
            "subcategory":"Nursing And Care Facility",
            "type":"Services"
        }
    ],
    "sg:phone":"+44 1242 221922",
    "sg:postcode":"GL52 2BD",
    "sg:province":"Gloucestershire",
    "sg:tags":[
        "home"
    ],
    "wof:name":"Pittville Lawn Nursing Home",
    "wof:placetype":"venue"
},
  "geometry": {"coordinates":[-2.0692660809,51.9051475525],"type":"Point"}
}