{
  "type": "Feature",
  "properties": {
    "addr:full":"163 High Street Arbroath Angus DD11 1DU",
    "addr:housenumber":"163",
    "addr:postcode":"dd11 1du",
    "addr:street":"High Street",
    "iso:country":"GB",
    "sg:address":"163 High Street",
    "sg:city":"Arbroath",
    "sg:classifiers":[
        {
            "category":"Shopping",
            "subcategory":"Department Store",
            "type":"Retail Goods"
        }
    ],
    "sg:phone":"+44 1241 873396",
    "sg:postcode":"DD11 1DU",
    "sg:province":"Angus",
    "wof:name":"Woolworths Plc",
    "wof:placetype":"venue"
},
  "geometry": {"coordinates":[-2.5808460712,56.5597305298],"type":"Point"}
}