{
  "type": "Feature",
  "properties": {
    "addr:full":"Vindis Ho, Low Rd Huntingdon Cambridgeshire PE17 4ET",
    "addr:postcode":"pe17 4et",
    "addr:street":"Low Rd",
    "iso:country":"GB",
    "sg:address":"Vindis Ho, Low Rd",
    "sg:city":"Huntingdon",
    "sg:classifiers":[
        {
            "category":"Shopping",
            "subcategory":"Stationery & Office Supplies",
            "type":"Retail Goods"
        }
    ],
    "sg:phone":"+44 1480 495718",
    "sg:postcode":"PE17 4ET",
    "sg:province":"Cambridgeshire",
    "wof:name":"Stealth Stationers & Office Equipment",
    "wof:placetype":"venue"
},
  "geometry": {"coordinates":[-0.1893,52.33514],"type":"Point"}
}