{
  "type": "Feature",
  "properties": {
    "addr:full":"Heath Road, Ramsden Heath Billericay Essex CM11 1HS",
    "addr:postcode":"cm11 1hs",
    "addr:street":"Heath Road",
    "iso:country":"GB",
    "sg:address":"Heath Road, Ramsden Heath",
    "sg:city":"Billericay",
    "sg:classifiers":[
        {
            "category":"Shopping",
            "subcategory":"News",
            "type":"Retail Goods"
        },
        {
            "category":"Government",
            "subcategory":"Post Office",
            "type":"Public Place"
        }
    ],
    "sg:phone":"+44 1268 710440",
    "sg:postcode":"CM11 1HS",
    "sg:province":"Essex",
    "sg:tags":[
        "newsagent"
    ],
    "wof:name":"Souden Stores",
    "wof:placetype":"venue"
},
  "geometry": {"coordinates":[0.442715,51.637371],"type":"Point"}
}