{
  "type": "Feature",
  "properties": {
    "addr:full":"Easington, Ashton St Peterlee Durham SR8 3QQ",
    "addr:housenumber":"easington",
    "addr:postcode":"sr8 3qq",
    "addr:street":"Ashton St",
    "iso:country":"GB",
    "sg:address":"Easington, Ashton St",
    "sg:city":"Peterlee",
    "sg:classifiers":[
        {
            "category":"Health Services",
            "subcategory":"Hospital",
            "type":"Services"
        }
    ],
    "sg:phone":"+44 191 527 2899",
    "sg:postcode":"SR8 3QQ",
    "sg:province":"Durham",
    "sg:tags":[
        "ambulance"
    ],
    "wof:name":"St. John Ambulance",
    "wof:placetype":"venue"
},
  "geometry": {"coordinates":[-1.351969,54.784546],"type":"Point"}
}