{
  "type": "Feature",
  "properties": {
    "addr:full":"Lyndhurst, Carnkie Redruth Cornwall TR16 6SP",
    "addr:postcode":"tr16 6sp",
    "iso:country":"GB",
    "sg:address":"Lyndhurst, Carnkie",
    "sg:city":"Redruth",
    "sg:classifiers":[
        {
            "category":"Transit Center",
            "subcategory":"Passenger",
            "type":"Transportation"
        }
    ],
    "sg:postcode":"TR16 6SP",
    "sg:province":"Cornwall",
    "sg:tags":[
        "boarding",
        "kennel",
        "catteries"
    ],
    "wof:name":"Carnkie Cattery",
    "wof:placetype":"venue"
},
  "geometry": {"coordinates":[-5.2529492378,50.2130889893],"type":"Point"}
}