{
  "type": "Feature",
  "properties": {
    "iso:country":"GB",
    "sg:address":"Forest Lane",
    "sg:city":"Walsall",
    "sg:classifiers":[
        {
            "category":"Freight",
            "type":"Transportation"
        }
    ],
    "sg:phone":"+44 1922 638364",
    "sg:postcode":"WS2 7AF",
    "sg:province":"West Midlands",
    "sg:tags":[
        "haulage",
        "road"
    ],
    "wof:name":"Tranzit Light Haulage",
    "wof:placetype":"venue"
},
  "geometry": {"coordinates":[-1.986312,52.602787],"type":"Point"}
}