{
  "type": "Feature",
  "properties": {
    "addr:full":"Park Farm, Staunton On Arrow Leominster Herefordshire HR6 9LE",
    "addr:postcode":"hr6 9le",
    "iso:country":"GB",
    "sg:address":"Park Farm, Staunton On Arrow",
    "sg:city":"Leominster",
    "sg:classifiers":[
        {
            "category":"Farming",
            "subcategory":"Livestock Farm",
            "type":"Manufacturing & Wholesale Goods"
        },
        {
            "category":"Farming",
            "subcategory":"Farm",
            "type":"Manufacturing & Wholesale Goods"
        }
    ],
    "sg:phone":"+44 1544 388481",
    "sg:postcode":"HR6 9LE",
    "sg:province":"Herefordshire",
    "sg:tags":[
        "mixed",
        "crop"
    ],
    "wof:name":"Margaret Edwards Phyllis",
    "wof:placetype":"venue"
},
  "geometry": {"coordinates":[-2.923306,52.235058],"type":"Point"}
}