{
  "type": "Feature",
  "properties": {
    "iso:country":"GB",
    "sg:address":"Richmonds Works, Richmond Road",
    "sg:city":"London",
    "sg:classifiers":[
        {
            "category":"Shopping",
            "subcategory":"Luggage & Leather Goods",
            "type":"Retail Goods"
        }
    ],
    "sg:phone":"+44 20 8458 5775",
    "sg:postcode":"E8 3QR",
    "sg:province":"Greater London",
    "wof:name":"Vanguard Luggage Ltd.",
    "wof:placetype":"venue"
},
  "geometry": {"coordinates":[-0.05591,51.543308],"type":"Point"}
}