{
  "type": "Feature",
  "properties": {
    "iso:country":"GB",
    "sg:address":"4 Tatton Buildings, Gatley",
    "sg:city":"Cheadle",
    "sg:classifiers":[
        {
            "category":"Personal",
            "subcategory":"Beauty Salon",
            "type":"Services"
        }
    ],
    "sg:phone":"+44 161 428 3821",
    "sg:postcode":"SK8 4BD",
    "sg:province":"Cheshire",
    "sg:tags":[
        "unisex",
        "hairdresser"
    ],
    "wof:name":"The Head Shop",
    "wof:placetype":"venue"
},
  "geometry": {"coordinates":[-2.2350730896,53.3926391602],"type":"Point"}
}