{
  "type": "Feature",
  "properties": {
    "addr:full":"Unit 15, Bright St Mill Bright St Bury Lancashire BL9 6AQ",
    "addr:housenumber":"unit 15",
    "addr:postcode":"bl9 6aq",
    "addr:street":"Bright St;Bright St",
    "iso:country":"GB",
    "sg:address":"Unit 15, Bright St Mill Bright St",
    "sg:city":"Bury",
    "sg:classifiers":[
        {
            "category":"Manufacturing",
            "subcategory":"Textiles",
            "type":"Manufacturing & Wholesale Goods"
        }
    ],
    "sg:phone":"+44 161 763 9859",
    "sg:postcode":"BL9 6AQ",
    "sg:province":"Lancashire",
    "sg:tags":[
        "merchant",
        "agent"
    ],
    "wof:name":"Almodale Uk Ltd",
    "wof:placetype":"venue"
},
  "geometry": {"coordinates":[-2.2839939594,53.598865509],"type":"Point"}
}