{
  "type": "Feature",
  "properties": {
    "addr:full":"6 The Gleve, Saline Dunfermline Fife KY12 9UT",
    "addr:housenumber":"6",
    "addr:postcode":"ky12 9ut",
    "addr:street":"The Gleve",
    "iso:country":"GB",
    "sg:address":"6 The Gleve, Saline",
    "sg:city":"Dunfermline",
    "sg:classifiers":[
        {
            "category":"Manufacturing",
            "subcategory":"Petroleum Products",
            "type":"Manufacturing & Wholesale Goods"
        }
    ],
    "sg:phone":"+44 1738 813132",
    "sg:postcode":"KY12 9UT",
    "sg:province":"Fife",
    "sg:tags":[
        "double",
        "glazing"
    ],
    "wof:name":"Bargain Windows",
    "wof:placetype":"venue"
},
  "geometry": {"coordinates":[-3.575151,56.117191],"type":"Point"}
}