{
  "type": "Feature",
  "properties": {
    "addr:full":"32 James Street London Greater London W1U 1EU",
    "addr:housenumber":"32",
    "addr:postcode":"w1u 1eu",
    "addr:street":"James Street",
    "iso:country":"GB",
    "sg:address":"32 James Street",
    "sg:city":"London",
    "sg:classifiers":[
        {
            "category":"Restaurant",
            "type":"Food & Drink"
        }
    ],
    "sg:phone":"+44 20 7935 0416",
    "sg:postcode":"W1U 1EU",
    "sg:province":"Greater London",
    "sg:tags":[
        "italian"
    ],
    "wof:name":"Christi Restauranti Italiano",
    "wof:placetype":"venue"
},
  "geometry": {"coordinates":[-0.150620997,51.5155410767],"type":"Point"}
}