{
  "type": "Feature",
  "properties": {
    "addr:full":"Stainsacre Lane Industrial Estat, E, Fairfield Way Whitby North Yorkshire YO22 4PU",
    "addr:postcode":"yo22 4pu",
    "addr:street":"Stainsacre Lane Industrial Estat E Fairfield Way",
    "iso:country":"GB",
    "sg:address":"Stainsacre Lane Industrial Estat, E, Fairfield Way",
    "sg:city":"Whitby",
    "sg:classifiers":[
        {
            "category":"Utilities",
            "subcategory":"Refuse",
            "type":"Services"
        }
    ],
    "sg:phone":"+44 1947 821048",
    "sg:postcode":"YO22 4PU",
    "sg:province":"North Yorkshire",
    "sg:tags":[
        "disposal",
        "waste"
    ],
    "wof:name":"Richardson Marcus Waste Management",
    "wof:placetype":"venue"
},
  "geometry": {"coordinates":[-0.604286,54.473671],"type":"Point"}
}