{
  "type": "Feature",
  "properties": {
    "addr:full":"Henry St East Sunderland Tyne and Wear SR2 8AU",
    "addr:postcode":"sr2 8au",
    "addr:street":"Henry St",
    "iso:country":"GB",
    "sg:address":"Henry St East",
    "sg:city":"Sunderland",
    "sg:classifiers":[
        {
            "category":"Utilities",
            "subcategory":"Refuse",
            "type":"Services"
        }
    ],
    "sg:phone":"+44 191 514 3595",
    "sg:postcode":"SR2 8AU",
    "sg:province":"Tyne and Wear",
    "sg:tags":[
        "disposal",
        "waste"
    ],
    "wof:name":"Lakeman Haulage",
    "wof:placetype":"venue"
},
  "geometry": {"coordinates":[-1.364971,54.90321],"type":"Point"}
}