{
  "type": "Feature",
  "properties": {
    "addr:full":"Kings Pk Canvey Island Essex SS8 8HE",
    "addr:postcode":"ss8 8he",
    "addr:street":"Kings Pk Canvey Island",
    "iso:country":"GB",
    "sg:address":"Kings Pk",
    "sg:city":"Canvey Island",
    "sg:classifiers":[
        {
            "category":"Professional",
            "subcategory":"Printing & Photocopies",
            "type":"Services"
        }
    ],
    "sg:phone":"+44 1268 510555",
    "sg:postcode":"SS8 8HE",
    "sg:province":"Essex",
    "sg:tags":[
        "printer"
    ],
    "wof:name":"Design 2 Print Ltd",
    "wof:placetype":"venue"
},
  "geometry": {"coordinates":[0.55177,51.519764],"type":"Point"}
}