{
  "type": "Feature",
  "properties": {
    "addr:full":"Hoyland Road, Hoyland Common Barnsley South Yorkshire S74 0PB",
    "addr:postcode":"s74 0pb",
    "addr:street":"Hoyland Road;Yorkshire",
    "iso:country":"GB",
    "sg:address":"Hoyland Road, Hoyland Common",
    "sg:city":"Barnsley",
    "sg:classifiers":[
        {
            "category":"Bars & Pubs",
            "type":"Food & Drink"
        }
    ],
    "sg:phone":"+44 1226 744468",
    "sg:postcode":"S74 0PB",
    "sg:province":"South Yorkshire",
    "sg:tags":[
        "pubs",
        "inn"
    ],
    "wof:name":"The Star",
    "wof:placetype":"venue"
},
  "geometry": {"coordinates":[-1.457358,53.500225],"type":"Point"}
}