{
  "type": "Feature",
  "properties": {
    "addr:full":"Worthington Way, Hawkely Brook Trading Estate Wigan Lancashire WN3 6XE",
    "addr:postcode":"wn3 6xe",
    "addr:street":"Worthington Way Hawkely Brook Trading Estate",
    "iso:country":"GB",
    "sg:address":"Worthington Way, Hawkely Brook Trading Estate",
    "sg:city":"Wigan",
    "sg:classifiers":[
        {
            "category":"Manufacturing",
            "subcategory":"Aerospace",
            "type":"Manufacturing & Wholesale Goods"
        }
    ],
    "sg:phone":"+44 1942 821205",
    "sg:postcode":"WN3 6XE",
    "sg:province":"Lancashire",
    "sg:tags":[
        "aircraft",
        "component"
    ],
    "wof:name":"B H W (Components) Ltd.",
    "wof:placetype":"venue"
},
  "geometry": {"coordinates":[-2.6538341045,53.5196113586],"type":"Point"}
}