{
  "type": "Feature",
  "properties": {
    "iso:country":"GB",
    "sg:address":"80 Bull Street",
    "sg:city":"Birmingham",
    "sg:classifiers":[
        {
            "category":"Retail",
            "subcategory":"Laundry & Dry Cleaning",
            "type":"Services"
        }
    ],
    "sg:phone":"+44 121 236 0822",
    "sg:postcode":"B4 6AB",
    "sg:province":"West Midlands",
    "sg:tags":[
        "alteration"
    ],
    "wof:name":"Quick Stitch Ltd.",
    "wof:placetype":"venue"
},
  "geometry": {"coordinates":[-1.896085,52.481697],"type":"Point"}
}