{
  "type": "Feature",
  "properties": {
    "iso:country":"GB",
    "sg:address":"1 Old Market",
    "sg:city":"Halifax",
    "sg:classifiers":[
        {
            "category":"Manufacturing",
            "subcategory":"Wood Products",
            "type":"Manufacturing & Wholesale Goods"
        }
    ],
    "sg:phone":"+44 1422 341015",
    "sg:postcode":"HX1 1TN",
    "sg:province":"West Yorkshire",
    "sg:tags":[
        "maker",
        "cabinet"
    ],
    "wof:name":"Moben Kitchens",
    "wof:placetype":"venue"
},
  "geometry": {"coordinates":[-1.8595579863,53.7234535217],"type":"Point"}
}