{
  "type": "Feature",
  "properties": {
    "iso:country":"GB",
    "sg:address":"114 Pier Avenue",
    "sg:city":"Clacton-on-sea",
    "sg:classifiers":[
        {
            "category":"Home & Garden",
            "subcategory":"Furniture",
            "type":"Retail Goods"
        }
    ],
    "sg:postcode":"CO15 1NJ",
    "sg:province":"Essex",
    "sg:tags":[
        "outlet"
    ],
    "wof:name":"JONNERS FURNITURE CENTRE",
    "wof:placetype":"venue"
},
  "geometry": {"coordinates":[1.1487330198,51.7925262451],"type":"Point"}
}