{
  "type": "Feature",
  "properties": {
    "addr:full":"The Former Magistrate's Court, Church Street Romsey Hampshire SO51 8AQ",
    "addr:postcode":"so51 8aq",
    "addr:street":"Church Street",
    "iso:country":"GB",
    "sg:address":"The Former Magistrate's Court, Church Street",
    "sg:city":"Romsey",
    "sg:classifiers":[
        {
            "category":"Social Services",
            "type":"Services"
        }
    ],
    "sg:phone":"+44 1794 526000",
    "sg:postcode":"SO51 8AQ",
    "sg:province":"Hampshire",
    "wof:name":"Romsey Area Office",
    "wof:placetype":"venue"
},
  "geometry": {"coordinates":[-1.5004800558,50.9899711609],"type":"Point"}
}