{
  "type": "Feature",
  "properties": {
    "addr:full":"Unit A, 45 Addison Gardens London Greater London W14 0DP",
    "addr:housenumber":"unit a 45",
    "addr:postcode":"w14 0dp",
    "addr:street":"Addison Gardens",
    "iso:country":"GB",
    "sg:address":"Unit A, 45 Addison Gardens",
    "sg:city":"London",
    "sg:classifiers":[
        {
            "category":"Utilities",
            "subcategory":"Telephone",
            "type":"Services"
        }
    ],
    "sg:postcode":"W14 0DP",
    "sg:province":"Greater London",
    "sg:tags":[
        "telecommunication"
    ],
    "wof:name":"Vantage Corporate Consulting Ltd.",
    "wof:placetype":"venue"
},
  "geometry": {"coordinates":[-0.21592,51.501869],"type":"Point"}
}