{
  "type": "Feature",
  "properties": {
    "iso:country":"GB",
    "sg:address":"4 Low Rd, Illington",
    "sg:city":"Thetford",
    "sg:classifiers":[
        {
            "category":"Building & Trades",
            "subcategory":"Cleaning & Sanitation",
            "type":"Services"
        }
    ],
    "sg:phone":"+44 1953 498840",
    "sg:postcode":"IP24 1RS",
    "sg:province":"Norfolk",
    "sg:tags":[
        "sweep",
        "chimney"
    ],
    "wof:name":"Charlie the Chimney",
    "wof:placetype":"venue"
},
  "geometry": {"coordinates":[0.860565,52.47113],"type":"Point"}
}