{
  "type": "Feature",
  "properties": {
    "addr:full":"13 Graham Street Edinburgh City of Edinburgh EH6 5QN",
    "addr:housenumber":"13",
    "addr:postcode":"eh6 5qn",
    "addr:street":"Graham Street",
    "iso:country":"GB",
    "sg:address":"13 Graham Street",
    "sg:city":"Edinburgh",
    "sg:classifiers":[
        {
            "category":"Communications",
            "type":"Services"
        }
    ],
    "sg:phone":"+44 131 553 5433",
    "sg:postcode":"EH6 5QN",
    "sg:province":"City of Edinburgh",
    "sg:tags":[
        "audio-visual"
    ],
    "wof:name":"Whitehouse Digital Productions Ltd.",
    "wof:placetype":"venue"
},
  "geometry": {"coordinates":[-3.186594,55.972713],"type":"Point"}
}