{
  "type": "Feature",
  "properties": {
    "iso:country":"GB",
    "sg:address":"Jansel House",
    "sg:city":"Luton",
    "sg:classifiers":[
        {
            "category":"Real Estate",
            "subcategory":"Developer",
            "type":"Services"
        }
    ],
    "sg:phone":"+44 1582 729851",
    "sg:postcode":"LU2 7XN",
    "sg:province":"Bedfordshire",
    "sg:tags":[
        "property"
    ],
    "wof:name":"Cross Oak (Berkhamsted) Developments Ltd.",
    "wof:placetype":"venue"
},
  "geometry": {"coordinates":[-0.394659996,51.9025802612],"type":"Point"}
}