{
  "type": "Feature",
  "properties": {
    "addr:full":"Armchair House, Commerce Road Brentford Greater London TW8 8LZ",
    "addr:postcode":"tw8 8lz",
    "addr:street":"Commerce Road",
    "iso:country":"GB",
    "sg:address":"Armchair House, Commerce Road",
    "sg:city":"Brentford",
    "sg:classifiers":[
        {
            "category":"Recreation",
            "subcategory":"Gun Range",
            "type":"Entertainment"
        }
    ],
    "sg:phone":"+44 20 8847 5000",
    "sg:postcode":"TW8 8LZ",
    "sg:province":"Greater London",
    "sg:tags":[
        "operator",
        "tour"
    ],
    "wof:name":"Armchair Tours Ltd.",
    "wof:placetype":"venue"
},
  "geometry": {"coordinates":[-0.3148359954,51.4841499329],"type":"Point"}
}