{
  "type": "Feature",
  "properties": {
    "addr:full":"1a Seymour Ave Luton Bedfordshire LU1 3NR",
    "addr:housenumber":"1a",
    "addr:postcode":"lu1 3nr",
    "addr:street":"Seymour Ave",
    "iso:country":"GB",
    "sg:address":"1a Seymour Ave",
    "sg:city":"Luton",
    "sg:classifiers":[
        {
            "category":"Fast Food",
            "type":"Food & Drink"
        },
        {
            "category":"Food & Beverages",
            "subcategory":"Meat & Fish",
            "type":"Retail Goods"
        }
    ],
    "sg:postcode":"LU1 3NR",
    "sg:province":"Bedfordshire",
    "sg:tags":[
        "chip",
        "away",
        "take"
    ],
    "wof:name":"No 2 Bluebird",
    "wof:placetype":"venue"
},
  "geometry": {"coordinates":[-0.408933,51.872227],"type":"Point"}
}