{
  "type": "Feature",
  "properties": {
    "addr:full":"51-53 Camberwell Church Street London Greater London SE5 8TR",
    "addr:housenumber":"51-53",
    "addr:postcode":"se5 8tr",
    "addr:street":"Camberwell Church Street",
    "iso:country":"GB",
    "sg:address":"51-53 Camberwell Church Street",
    "sg:city":"London",
    "sg:classifiers":[
        {
            "category":"Travel",
            "subcategory":"Hotels & Motels",
            "type":"Entertainment"
        }
    ],
    "sg:phone":"+44 20 7703 5262",
    "sg:postcode":"SE5 8TR",
    "sg:province":"Greater London",
    "wof:name":"Kingspride Investments Ltd.",
    "wof:placetype":"venue"
},
  "geometry": {"coordinates":[-0.0896750018,51.4739723206],"type":"Point"}
}