{
  "type": "Feature",
  "properties": {
    "addr:full":"8 Race Hill Launceston Cornwall PL15 9BA",
    "addr:housenumber":"8",
    "addr:postcode":"pl15 9ba",
    "addr:street":"Race Hill",
    "iso:country":"GB",
    "sg:address":"8 Race Hill",
    "sg:city":"Launceston",
    "sg:classifiers":[
        {
            "category":"Shopping",
            "subcategory":"Books",
            "type":"Retail Goods"
        }
    ],
    "sg:postcode":"PL15 9BA",
    "sg:province":"Cornwall",
    "sg:tags":[
        "second-hand"
    ],
    "wof:name":"Hutton Books",
    "wof:placetype":"venue"
},
  "geometry": {"coordinates":[-4.3579788208,50.6352996826],"type":"Point"}
}