{
  "type": "Feature",
  "properties": {
    "addr:full":"35 Thirlmere Drive St Albans Hertfordshire AL1 5QU",
    "addr:housenumber":"35",
    "addr:postcode":"al1 5qu",
    "addr:street":"Thirlmere Drive",
    "iso:country":"GB",
    "sg:address":"35 Thirlmere Drive",
    "sg:city":"St Albans",
    "sg:classifiers":[
        {
            "category":"Professional",
            "subcategory":"Engineering",
            "type":"Services"
        }
    ],
    "sg:postcode":"AL1 5QU",
    "sg:province":"Hertfordshire",
    "sg:tags":[
        "contractor",
        "electrical",
        "engineer"
    ],
    "wof:name":"Steve Greaney Electrical Services",
    "wof:placetype":"venue"
},
  "geometry": {"coordinates":[-0.309823,51.74332],"type":"Point"}
}