{
  "type": "Feature",
  "properties": {
    "addr:full":"492 Hempshaw Lane Stockport Cheshire SK2 5TL",
    "addr:housenumber":"492",
    "addr:postcode":"sk2 5tl",
    "addr:street":"Hempshaw Lane",
    "iso:country":"GB",
    "sg:address":"492 Hempshaw Lane",
    "sg:city":"Stockport",
    "sg:classifiers":[
        {
            "category":"Professional",
            "subcategory":"Engineering",
            "type":"Services"
        }
    ],
    "sg:postcode":"SK2 5TL",
    "sg:province":"Cheshire",
    "sg:tags":[
        "contractor",
        "electrical",
        "engineer"
    ],
    "wof:name":"McL Electrical Ltd",
    "wof:placetype":"venue"
},
  "geometry": {"coordinates":[-2.1336910725,53.4011726379],"type":"Point"}
}