{
  "type": "Feature",
  "properties": {
    "addr:full":"The Workshop Vicarage La, Elworth Sandbach Cheshire CW11 3BW",
    "addr:postcode":"cw11 3bw",
    "addr:street":"La Elworth",
    "iso:country":"GB",
    "sg:address":"The Workshop Vicarage La, Elworth",
    "sg:city":"Sandbach",
    "sg:classifiers":[
        {
            "category":"Shopping",
            "subcategory":"Department Store",
            "type":"Retail Goods"
        }
    ],
    "sg:postcode":"CW11 3BW",
    "sg:province":"Cheshire",
    "wof:name":"Cooper,D,",
    "wof:placetype":"venue"
},
  "geometry": {"coordinates":[-2.3891580105,53.1498069763],"type":"Point"}
}