{
  "type": "Feature",
  "properties": {
    "addr:full":"151 Ley St Ilford Essex IG1 4BL",
    "addr:housenumber":"151",
    "addr:postcode":"ig1 4bl",
    "addr:street":"Ley St",
    "iso:country":"GB",
    "sg:address":"151 Ley St",
    "sg:city":"Ilford",
    "sg:classifiers":[
        {
            "category":"Professional",
            "subcategory":"Accounting & Tax Preparation",
            "type":"Services"
        }
    ],
    "sg:phone":"+44 20 8478 3111",
    "sg:postcode":"IG1 4BL",
    "sg:province":"Essex",
    "sg:tags":[
        "accountant"
    ],
    "wof:name":"Dacosta Chartered Accountants",
    "wof:placetype":"venue"
},
  "geometry": {"coordinates":[0.0774289966,51.5620307922],"type":"Point"}
}