{
  "type": "Feature",
  "properties": {
    "addr:full":"Willow House, 43a Mersey View Liverpool Merseyside L22 6QA",
    "addr:housenumber":"43a",
    "addr:postcode":"l22 6qa",
    "addr:street":"Mersey View",
    "iso:country":"GB",
    "sg:address":"Willow House, 43a Mersey View",
    "sg:city":"Liverpool",
    "sg:classifiers":[
        {
            "category":"Autos & Motor Vehicles",
            "subcategory":"Auto Supplies",
            "type":"Retail Goods"
        }
    ],
    "sg:phone":"+44 151 931 3104",
    "sg:postcode":"L22 6QA",
    "sg:province":"Merseyside",
    "sg:tags":[
        "tyre"
    ],
    "wof:name":"Willow Tyres (Crosby) Ltd.",
    "wof:placetype":"venue"
},
  "geometry": {"coordinates":[-3.037819,53.481285],"type":"Point"}
}