{
  "type": "Feature",
  "properties": {
    "addr:full":"28 Eldon Road Reading Berkshire RG1 4DL",
    "addr:housenumber":"28",
    "addr:postcode":"rg1 4dl",
    "addr:street":"Eldon Road",
    "iso:country":"GB",
    "sg:address":"28 Eldon Road",
    "sg:city":"Reading",
    "sg:classifiers":[
        {
            "category":"Communications",
            "subcategory":"Newspaper",
            "type":"Services"
        }
    ],
    "sg:postcode":"RG1 4DL",
    "sg:province":"Berkshire",
    "sg:tags":[
        "magazine"
    ],
    "wof:name":"E B Aherne",
    "wof:placetype":"venue"
},
  "geometry": {"coordinates":[-0.9587680101,51.4523086548],"type":"Point"}
}