{
  "type": "Feature",
  "properties": {
    "iso:country":"GB",
    "sg:address":"5 Lodge Way",
    "sg:city":"Thetford",
    "sg:classifiers":[
        {
            "category":"Building & Trades",
            "subcategory":"Construction",
            "type":"Services"
        }
    ],
    "sg:phone":"+44 1842 755195",
    "sg:postcode":"IP24 1HE",
    "sg:province":"Norfolk",
    "sg:tags":[
        "heating",
        "contractor"
    ],
    "wof:name":"DEREK AUSTIN HEATING LTD",
    "wof:placetype":"venue"
},
  "geometry": {"coordinates":[0.746257,52.429375],"type":"Point"}
}