{
  "type": "Feature",
  "properties": {
    "addr:full":"38 Manor Road, Dersingham King's Lynn Norfolk PE31 6LH",
    "addr:housenumber":"38",
    "addr:postcode":"pe31 6lh",
    "addr:street":"Manor Road;Lynn",
    "iso:country":"GB",
    "sg:address":"38 Manor Road, Dersingham",
    "sg:city":"King's Lynn",
    "sg:classifiers":[
        {
            "category":"Retail",
            "subcategory":"Funeral Services",
            "type":"Services"
        }
    ],
    "sg:phone":"+44 1485 540270",
    "sg:postcode":"PE31 6LH",
    "sg:province":"Norfolk",
    "sg:tags":[
        "director"
    ],
    "wof:name":"John Lincoln",
    "wof:placetype":"venue"
},
  "geometry": {"coordinates":[0.50802,52.839859],"type":"Point"}
}