{
  "type": "Feature",
  "properties": {
    "addr:full":"3 Douglas Street Hamilton South Lanarkshire ML3 0BP",
    "addr:housenumber":"3",
    "addr:postcode":"ml3 0bp",
    "addr:street":"Douglas Street",
    "iso:country":"GB",
    "sg:address":"3 Douglas Street",
    "sg:city":"Hamilton",
    "sg:classifiers":[
        {
            "category":"Personal",
            "subcategory":"Barber",
            "type":"Services"
        }
    ],
    "sg:phone":"+44 1698 327411",
    "sg:postcode":"ML3 0BP",
    "sg:province":"South Lanarkshire",
    "sg:tags":[
        "men's",
        "hairdresser"
    ],
    "wof:name":"Upper Cut",
    "wof:placetype":"venue"
},
  "geometry": {"coordinates":[-4.0518689156,55.7795295715],"type":"Point"}
}