{
  "type": "Feature",
  "properties": {
    "addr:full":"Mardale, Quernmore Lancaster Lancashire LA2 9EG",
    "addr:postcode":"la2 9eg",
    "iso:country":"GB",
    "sg:address":"Mardale, Quernmore",
    "sg:city":"Lancaster",
    "sg:classifiers":[
        {
            "category":"Professional",
            "subcategory":"Engineering",
            "type":"Services"
        }
    ],
    "sg:phone":"+44 1524 66914",
    "sg:postcode":"LA2 9EG",
    "sg:province":"Lancashire",
    "sg:tags":[
        "agricultural",
        "engineer"
    ],
    "wof:name":"A E Huddleston",
    "wof:placetype":"venue"
},
  "geometry": {"coordinates":[-2.7349390984,54.02551651],"type":"Point"}
}