{
  "type": "Feature",
  "properties": {
    "iso:country":"GB",
    "sg:address":"1 Ernald Avenue, East Ham",
    "sg:city":"London",
    "sg:classifiers":[
        {
            "category":"Health Services",
            "subcategory":"Health Practitioner",
            "type":"Services"
        }
    ],
    "sg:postcode":"E6 3AL",
    "sg:province":"Greater London",
    "sg:tags":[
        "osteopath"
    ],
    "wof:name":"Alison R Brown",
    "wof:placetype":"venue"
},
  "geometry": {"coordinates":[0.050361,51.5321044922],"type":"Point"}
}