{
  "type": "Feature",
  "properties": {
    "iso:country":"GB",
    "sg:address":"G T House, 24/26 Rothsay Road",
    "sg:city":"Luton",
    "sg:classifiers":[
        {
            "category":"Professional",
            "subcategory":"Management & Consulting",
            "type":"Services"
        }
    ],
    "sg:phone":"+44 1582 400184",
    "sg:postcode":"LU1 1QX",
    "sg:province":"Bedfordshire",
    "sg:tags":[
        "consultant",
        "business"
    ],
    "wof:name":"P M A Ltd.",
    "wof:placetype":"venue"
},
  "geometry": {"coordinates":[-0.422369,51.87846],"type":"Point"}
}