{
  "type": "Feature",
  "properties": {
    "addr:full":"115 Gilders Road Chessington Surrey KT9 2AJ",
    "addr:housenumber":"115",
    "addr:postcode":"kt9 2aj",
    "addr:street":"Gilders Road",
    "iso:country":"GB",
    "sg:address":"115 Gilders Road",
    "sg:city":"Chessington",
    "sg:classifiers":[
        {
            "category":"Autos & Motor Vehicles",
            "subcategory":"Auto Supplies",
            "type":"Retail Goods"
        }
    ],
    "sg:phone":"+44 20 8397 3269",
    "sg:postcode":"KT9 2AJ",
    "sg:province":"Surrey",
    "sg:tags":[
        "tyre"
    ],
    "wof:name":"Chessington Tyres Ltd.",
    "wof:placetype":"venue"
},
  "geometry": {"coordinates":[-0.294888,51.358894],"type":"Point"}
}