{
  "type": "Feature",
  "properties": {
    "addr:full":"59 Pepper Road Leeds West Yorkshire LS10 2TH",
    "addr:housenumber":"59",
    "addr:postcode":"ls10 2th",
    "addr:street":"Pepper Road",
    "iso:country":"GB",
    "sg:address":"59 Pepper Road",
    "sg:city":"Leeds",
    "sg:classifiers":[
        {
            "category":"Home & Garden",
            "subcategory":"Building Materials",
            "type":"Retail Goods"
        },
        {
            "category":"Manufacturing",
            "subcategory":"Furniture",
            "type":"Manufacturing & Wholesale Goods"
        }
    ],
    "sg:phone":"+44 113 271 8311",
    "sg:postcode":"LS10 2TH",
    "sg:province":"West Yorkshire",
    "sg:tags":[
        "wooden",
        "veneer"
    ],
    "wof:name":"Spa Laminates Ltd",
    "wof:placetype":"venue"
},
  "geometry": {"coordinates":[-1.522374,53.773838],"type":"Point"}
}