{
  "type": "Feature",
  "properties": {
    "addr:full":"55-59 Great Pulteney Street Bath Somerset BA2 4DW",
    "addr:housenumber":"55-59",
    "addr:postcode":"ba2 4dw",
    "addr:street":"Great Pulteney Street",
    "iso:country":"GB",
    "sg:address":"55-59 Great Pulteney Street",
    "sg:city":"Bath",
    "sg:classifiers":[
        {
            "category":"Social Services",
            "subcategory":"Retirement Home",
            "type":"Services"
        },
        {
            "category":"Organizations",
            "subcategory":"Community Association",
            "type":"Services"
        }
    ],
    "sg:phone":"+44 1225 462004",
    "sg:postcode":"BA2 4DW",
    "sg:province":"Somerset",
    "sg:tags":[
        "society",
        "housing",
        "sheltered",
        "accommodation"
    ],
    "wof:name":"Fitzroy House",
    "wof:placetype":"venue"
},
  "geometry": {"coordinates":[-2.3518989086,51.3853492737],"type":"Point"}
}