{
  "type": "Feature",
  "properties": {
    "addr:full":"Imperial Chambers, 24 Widemarsh Street Hereford Herefordshire HR4 9EP",
    "addr:housenumber":"24",
    "addr:postcode":"hr4 9ep",
    "addr:street":"Widemarsh Street",
    "iso:country":"GB",
    "sg:address":"Imperial Chambers, 24 Widemarsh Street",
    "sg:city":"Hereford",
    "sg:classifiers":[
        {
            "category":"Health Services",
            "subcategory":"Dentist",
            "type":"Services"
        }
    ],
    "sg:phone":"+44 1432 356891",
    "sg:postcode":"HR4 9EP",
    "sg:province":"Herefordshire",
    "wof:name":"Widemarsh Dental Surgery",
    "wof:placetype":"venue"
},
  "geometry": {"coordinates":[-2.7317609787,52.0592041016],"type":"Point"}
}