{
  "type": "Feature",
  "properties": {
    "iso:country":"GB",
    "sg:address":"5 Ferry Terminal Building, Kirkwall Pier",
    "sg:city":"Kirkwall",
    "sg:classifiers":[
        {
            "category":"Professional",
            "subcategory":"Business Services",
            "type":"Services"
        }
    ],
    "sg:phone":"+44 1856 871818",
    "sg:postcode":"KW15 1HU",
    "sg:province":"Orkney Islands",
    "sg:tags":[
        "trade"
    ],
    "wof:name":"Orkney Inshore Shellfisheries Management Organisation",
    "wof:placetype":"venue"
},
  "geometry": {"coordinates":[-2.960419,58.981731],"type":"Point"}
}