{
  "type": "Feature",
  "properties": {
    "addr:full":"35a Waterside Gardens Fareham Hampshire PO16 8SD",
    "addr:housenumber":"35a",
    "addr:postcode":"po16 8sd",
    "addr:street":"Waterside Gardens",
    "iso:country":"GB",
    "sg:address":"35a Waterside Gardens",
    "sg:city":"Fareham",
    "sg:classifiers":[
        {
            "category":"Professional",
            "subcategory":"Advertising",
            "type":"Services"
        }
    ],
    "sg:phone":"+44 1329 825852",
    "sg:postcode":"PO16 8SD",
    "sg:province":"Hampshire",
    "sg:tags":[
        "agency"
    ],
    "wof:name":"Christianson Hoper Norman Ltd.",
    "wof:placetype":"venue"
},
  "geometry": {"coordinates":[-1.167362,50.854595],"type":"Point"}
}