{
  "type": "Feature",
  "properties": {
    "addr:full":"91 Carnglas Road, Tycoch Swansea Swansea SA2 9BN",
    "addr:housenumber":"91",
    "addr:postcode":"sa2 9bn",
    "addr:street":"Carnglas Road Tycoch",
    "iso:country":"GB",
    "sg:address":"91 Carnglas Road, Tycoch",
    "sg:city":"Swansea",
    "sg:classifiers":[
        {
            "category":"Food & Beverages",
            "subcategory":"Liquor & Beverages",
            "type":"Retail Goods"
        }
    ],
    "sg:postcode":"SA2 9BN",
    "sg:province":"Swansea",
    "sg:tags":[
        "beer",
        "spirit",
        "wines"
    ],
    "wof:name":"Tycoch Off Licence",
    "wof:placetype":"venue"
},
  "geometry": {"coordinates":[-3.991792,51.622864],"type":"Point"}
}