{
  "type": "Feature",
  "properties": {
    "iso:country":"GB",
    "sg:address":"20 East Causeway Vale",
    "sg:city":"Leeds",
    "sg:classifiers":[
        {
            "category":"Home & Garden",
            "subcategory":"Hardware",
            "type":"Retail Goods"
        },
        {
            "category":"Manufacturing",
            "subcategory":"Textiles",
            "type":"Manufacturing & Wholesale Goods"
        }
    ],
    "sg:phone":"+44 113 261 0695",
    "sg:postcode":"LS16 8LG",
    "sg:province":"West Yorkshire",
    "sg:tags":[
        "made-up",
        "tarpaulin"
    ],
    "wof:name":"Thoroughbred Covers Ltd.",
    "wof:placetype":"venue"
},
  "geometry": {"coordinates":[-1.5767760277,53.8549919128],"type":"Point"}
}