{
  "type": "Feature",
  "properties": {
    "addr:full":"The Annexe, 12 Crescent Rd, Crouch End London Greater London N8 8AT",
    "addr:housenumber":"12",
    "addr:postcode":"n8 8at",
    "addr:street":"Crescent Rd",
    "iso:country":"GB",
    "sg:address":"The Annexe, 12 Crescent Rd, Crouch End",
    "sg:city":"London",
    "sg:classifiers":[
        {
            "category":"Health Services",
            "subcategory":"Nursing And Care Facility",
            "type":"Services"
        },
        {
            "category":"Organizations",
            "subcategory":"Community Association",
            "type":"Services"
        }
    ],
    "sg:phone":"+44 20 8348 0387",
    "sg:postcode":"N8 8AT",
    "sg:province":"Greater London",
    "sg:tags":[
        "co-operatives",
        "residential",
        "housing",
        "trust",
        "society"
    ],
    "wof:name":"HARINGEY EDUCATIONAL HOUSING ASSOCIATION LTD",
    "wof:placetype":"venue"
},
  "geometry": {"coordinates":[-0.128732,51.575405],"type":"Point"}
}