{
  "type": "Feature",
  "properties": {
    "iso:country":"GB",
    "sg:address":"28 Warwick Row",
    "sg:city":"Aylesbury",
    "sg:classifiers":[
        {
            "category":"Health Services",
            "subcategory":"Health Practitioner",
            "type":"Services"
        }
    ],
    "sg:phone":"+44 1296 426176",
    "sg:postcode":"HP20 1HD",
    "sg:province":"Buckinghamshire",
    "sg:tags":[
        "physiotherapist"
    ],
    "wof:name":"Aylesbury Sports Injury Clinic",
    "wof:placetype":"venue"
},
  "geometry": {"coordinates":[-0.7963089943,51.8223342896],"type":"Point"}
}