{
  "type": "Feature",
  "properties": {
    "iso:country":"GB",
    "sg:address":"Gable House",
    "sg:city":"London",
    "sg:classifiers":[
        {
            "category":"Taxi",
            "type":"Transportation"
        }
    ],
    "sg:phone":"+44 20 8299 4000",
    "sg:postcode":"N3 3LF",
    "sg:province":"Greater London",
    "sg:tags":[
        "mini",
        "cab"
    ],
    "wof:name":"Cts International Ltd.",
    "wof:placetype":"venue"
},
  "geometry": {"coordinates":[-0.192198,51.591347],"type":"Point"}
}