{
  "type": "Feature",
  "properties": {
    "iso:country":"GB",
    "sg:address":"21 Silk Street",
    "sg:city":"Salford",
    "sg:classifiers":[
        {
            "category":"Community Center",
            "subcategory":"Youth",
            "type":"Public Place"
        }
    ],
    "sg:phone":"+44 161 834 5439",
    "sg:postcode":"M3 6LZ",
    "sg:province":"Greater Manchester",
    "sg:tags":[
        "organisation",
        "centre"
    ],
    "wof:name":"Oasis Youth Centre",
    "wof:placetype":"venue"
},
  "geometry": {"coordinates":[-2.2622220516,53.4880867004],"type":"Point"}
}