{
  "type": "Feature",
  "properties": {
    "addr:full":"1 Trusham Rd, Marsh Barton Ind Est Exeter Devon EX2 8NW",
    "addr:housenumber":"1",
    "addr:postcode":"ex2 8nw",
    "addr:street":"Trusham Rd",
    "iso:country":"GB",
    "sg:address":"1 Trusham Rd, Marsh Barton Ind Est",
    "sg:city":"Exeter",
    "sg:classifiers":[
        {
            "category":"Deli",
            "type":"Food & Drink"
        }
    ],
    "sg:phone":"+44 1392 421663",
    "sg:postcode":"EX2 8NW",
    "sg:province":"Devon",
    "sg:tags":[
        "delivery",
        "sandwich"
    ],
    "wof:name":"LORD SANDWICH",
    "wof:placetype":"venue"
},
  "geometry": {"coordinates":[-3.5303530693,50.7089424133],"type":"Point"}
}