{
  "type": "Feature",
  "properties": {
    "addr:full":"Hillside Nill, Swaffham Bulbeck Cambridge Cambridgeshire CB5 0LU",
    "addr:postcode":"cb5 0lu",
    "iso:country":"GB",
    "sg:address":"Hillside Nill, Swaffham Bulbeck",
    "sg:city":"Cambridge",
    "sg:classifiers":[
        {
            "category":"Building & Trades",
            "subcategory":"Landscaping Services",
            "type":"Services"
        }
    ],
    "sg:phone":"+44 1223 812729",
    "sg:postcode":"CB5 0LU",
    "sg:province":"Cambridgeshire",
    "sg:tags":[
        "horticultural",
        "consultant"
    ],
    "wof:name":"Newbrook Products Ltd.",
    "wof:placetype":"venue"
},
  "geometry": {"coordinates":[0.2780350149,52.2397994995],"type":"Point"}
}