{
  "type": "Feature",
  "properties": {
    "iso:country":"GB",
    "sg:address":"1 Cambridge Clo, Lawn",
    "sg:city":"Swindon",
    "sg:classifiers":[
        {
            "category":"Banks & Credit Unions",
            "subcategory":"Bank",
            "type":"Services"
        }
    ],
    "sg:postcode":"SN3 1JQ",
    "sg:province":"Wiltshire",
    "sg:tags":[
        "stocktaking",
        "inventory"
    ],
    "wof:name":"Moore,Richard,",
    "wof:placetype":"venue"
},
  "geometry": {"coordinates":[-1.7586430311,51.5502967834],"type":"Point"}
}