{
  "type": "Feature",
  "properties": {
    "addr:full":"7 Roods Kirriemuir Angus DD8 4EZ",
    "addr:housenumber":"7",
    "addr:postcode":"dd8 4ez",
    "addr:street":"Roods Kirriemuir",
    "iso:country":"GB",
    "sg:address":"7 Roods",
    "sg:city":"Kirriemuir",
    "sg:classifiers":[
        {
            "category":"Shopping",
            "subcategory":"Gifts & Souvenirs",
            "type":"Retail Goods"
        }
    ],
    "sg:postcode":"DD8 4EZ",
    "sg:province":"Angus",
    "sg:tags":[
        "shop"
    ],
    "wof:name":"Facets",
    "wof:placetype":"venue"
},
  "geometry": {"coordinates":[-3.0045740604,56.6737823486],"type":"Point"}
}