{
  "type": "Feature",
  "properties": {
    "addr:full":"34 Northumberland Road Bristol City of Bristol BS6 7BD",
    "addr:housenumber":"34",
    "addr:postcode":"bs6 7bd",
    "addr:street":"Northumberland Road",
    "iso:country":"GB",
    "sg:address":"34 Northumberland Road",
    "sg:city":"Bristol",
    "sg:classifiers":[
        {
            "category":"Farming",
            "subcategory":"Nursery",
            "type":"Manufacturing & Wholesale Goods"
        }
    ],
    "sg:phone":"+44 117 924 0431",
    "sg:postcode":"BS6 7BD",
    "sg:province":"City of Bristol",
    "sg:tags":[
        "creche"
    ],
    "wof:name":"The Rocking Horse Day Nursery",
    "wof:placetype":"venue"
},
  "geometry": {"coordinates":[-2.5993080139,51.4715118408],"type":"Point"}
}