{
  "type": "Feature",
  "properties": {
    "addr:full":"15 Shaftesbury Av Bedford Bedfordshire MK40 3SA",
    "addr:housenumber":"15",
    "addr:postcode":"mk40 3sa",
    "addr:street":"Shaftesbury Av",
    "iso:country":"GB",
    "sg:address":"15 Shaftesbury Av",
    "sg:city":"Bedford",
    "sg:classifiers":[
        {
            "category":"Organizations",
            "subcategory":"Non-profit Organization",
            "type":"Services"
        }
    ],
    "sg:phone":"+44 1234 357760",
    "sg:postcode":"MK40 3SA",
    "sg:province":"Bedfordshire",
    "sg:tags":[
        "organisation",
        "voluntary",
        "charity"
    ],
    "wof:name":"The G K Chesterton Study Centre",
    "wof:placetype":"venue"
},
  "geometry": {"coordinates":[-0.4482469857,52.1342773438],"type":"Point"}
}