{
  "type": "Feature",
  "properties": {
    "iso:country":"GB",
    "sg:address":"77 High Street, Lochee",
    "sg:city":"Dundee",
    "sg:classifiers":[
        {
            "category":"Personal",
            "subcategory":"Beauty Salon",
            "type":"Services"
        }
    ],
    "sg:phone":"+44 1382 612646",
    "sg:postcode":"DD2 3BL",
    "sg:province":"Dundee City",
    "sg:tags":[
        "unisex",
        "hairdresser"
    ],
    "wof:name":"Eclips",
    "wof:placetype":"venue"
},
  "geometry": {"coordinates":[-3.009413,56.471642],"type":"Point"}
}