{
  "type": "Feature",
  "properties": {
    "iso:country":"GB",
    "sg:address":"Hillsborough, Old Main Road, Fosdyke",
    "sg:city":"Boston",
    "sg:classifiers":[
        {
            "category":"Building & Trades",
            "subcategory":"Landscaping Services",
            "type":"Services"
        }
    ],
    "sg:phone":"+44 1205 260381",
    "sg:postcode":"PE20 2BU",
    "sg:province":"Lincolnshire",
    "sg:tags":[
        "landscape",
        "contractor"
    ],
    "wof:name":"Cardwell Landscapes",
    "wof:placetype":"venue"
},
  "geometry": {"coordinates":[-0.045289,52.879494],"type":"Point"}
}