{
  "type": "Feature",
  "properties": {
    "addr:full":"9 Ellisland Drive Kilmarnock East Ayrshire KA3 7DL",
    "addr:housenumber":"9",
    "addr:postcode":"ka3 7dl",
    "addr:street":"Ellisland Drive",
    "iso:country":"GB",
    "sg:address":"9 Ellisland Drive",
    "sg:city":"Kilmarnock",
    "sg:classifiers":[
        {
            "category":"Manufacturing",
            "subcategory":"Building Materials",
            "type":"Manufacturing & Wholesale Goods"
        }
    ],
    "sg:phone":"+44 1563 536589",
    "sg:postcode":"KA3 7DL",
    "sg:province":"East Ayrshire",
    "sg:tags":[
        "stonemason"
    ],
    "wof:name":"Crafted in Stone",
    "wof:placetype":"venue"
},
  "geometry": {"coordinates":[-4.473028183,55.6062164307],"type":"Point"}
}