{
  "type": "Feature",
  "properties": {
    "addr:full":"7 Limbrick Corner, Limbrick Lane, Goring-by-sea Worthing West Sussex BN12 6JL",
    "addr:housenumber":"7",
    "addr:postcode":"bn12 6jl",
    "addr:street":"Limbrick Corner Limbrick Lane",
    "iso:country":"GB",
    "sg:address":"7 Limbrick Corner, Limbrick Lane, Goring-by-sea",
    "sg:city":"Worthing",
    "sg:classifiers":[
        {
            "category":"Building & Trades",
            "subcategory":"Construction",
            "type":"Services"
        }
    ],
    "sg:phone":"+44 1903 240413",
    "sg:postcode":"BN12 6JL",
    "sg:province":"West Sussex",
    "sg:tags":[
        "resurfacing",
        "laying",
        "floor"
    ],
    "wof:name":"G J Vagg Flooring Ltd.",
    "wof:placetype":"venue"
},
  "geometry": {"coordinates":[-0.4238489866,50.8199920654],"type":"Point"}
}