{
  "type": "Feature",
  "properties": {
    "iso:country":"GB",
    "sg:address":"24 Ashville St Huntingdon Rd",
    "sg:city":"York",
    "sg:classifiers":[
        {
            "category":"Building & Trades",
            "subcategory":"Construction",
            "type":"Services"
        }
    ],
    "sg:phone":"+44 1904 640856",
    "sg:postcode":"YO31 8RY",
    "sg:province":"North Yorkshire",
    "sg:tags":[
        "decorator",
        "painter"
    ],
    "wof:name":"Karl Brown Quality Painting & Decorating",
    "wof:placetype":"venue"
},
  "geometry": {"coordinates":[-1.074371,53.972908],"type":"Point"}
}