{
  "type": "Feature",
  "properties": {
    "iso:country":"GB",
    "sg:address":"Desborough Rd",
    "sg:city":"High Wycombe",
    "sg:classifiers":[
        {
            "category":"Place Of Worship",
            "type":"Public Place"
        }
    ],
    "sg:phone":"+44 1494 529586",
    "sg:postcode":"HP11 2QW",
    "sg:province":"Buckinghamshire",
    "wof:name":"St John The Evangelist C Of E Church",
    "wof:placetype":"venue"
},
  "geometry": {"coordinates":[-0.764274,51.632423],"type":"Point"}
}