{
  "type": "Feature",
  "properties": {
    "addr:full":"262 Slade Rd Birmingham West Midlands B23 7RH",
    "addr:housenumber":"262",
    "addr:postcode":"b23 7rh",
    "addr:street":"Slade Rd",
    "iso:country":"GB",
    "sg:address":"262 Slade Rd",
    "sg:city":"Birmingham",
    "sg:classifiers":[
        {
            "category":"Shopping",
            "subcategory":"Used Merchandise",
            "type":"Retail Goods"
        }
    ],
    "sg:phone":"+44 121 377 7566",
    "sg:postcode":"B23 7RH",
    "sg:province":"West Midlands",
    "sg:tags":[
        "shop",
        "second-hand"
    ],
    "wof:name":"Bob's Antiques",
    "wof:placetype":"venue"
},
  "geometry": {"coordinates":[-1.85625,52.516933],"type":"Point"}
}