{
  "type": "Feature",
  "properties": {
    "addr:full":"3 Crown Walk, High Street Oakham Leicestershire LE15 6BZ",
    "addr:housenumber":"3",
    "addr:postcode":"le15 6bz",
    "addr:street":"Crown Walk High Street",
    "iso:country":"GB",
    "sg:address":"3 Crown Walk, High Street",
    "sg:city":"Oakham",
    "sg:classifiers":[
        {
            "category":"Shopping",
            "subcategory":"Shoes",
            "type":"Retail Goods"
        }
    ],
    "sg:phone":"+44 1572 771717",
    "sg:postcode":"LE15 6BZ",
    "sg:province":"Leicestershire",
    "sg:tags":[
        "shop"
    ],
    "wof:name":"Maxelle Shoes",
    "wof:placetype":"venue"
},
  "geometry": {"coordinates":[-0.72788,52.66864],"type":"Point"}
}