{
  "type": "Feature",
  "properties": {
    "iso:country":"GB",
    "sg:address":"Doncaster Road, Dalton",
    "sg:city":"Rotherham",
    "sg:classifiers":[
        {
            "category":"Travel",
            "subcategory":"Hotels & Motels",
            "type":"Entertainment"
        }
    ],
    "sg:phone":"+44 1709 852534",
    "sg:postcode":"S65 3EW",
    "sg:province":"South Yorkshire",
    "wof:name":"Aldersyde Hotel",
    "wof:placetype":"venue"
},
  "geometry": {"coordinates":[-1.314139,53.443604],"type":"Point"}
}