{
  "type": "Feature",
  "properties": {
    "addr:full":"238 Upper Chobham Road, Chobham Woking Berkshire GU15 1HJ",
    "addr:housenumber":"238",
    "addr:postcode":"gu15 1hj",
    "addr:street":"Upper Chobham Road",
    "iso:country":"GB",
    "sg:address":"238 Upper Chobham Road, Chobham",
    "sg:city":"Woking",
    "sg:classifiers":[
        {
            "category":"Professional",
            "subcategory":"Computer Services",
            "type":"Services"
        }
    ],
    "sg:phone":"+44 118 377 6060",
    "sg:postcode":"GU15 1HJ",
    "sg:province":"Berkshire",
    "sg:tags":[
        "system",
        "software"
    ],
    "wof:name":"Silicon Systems Ltd.",
    "wof:placetype":"venue"
},
  "geometry": {"coordinates":[-0.6061800122,51.3536605835],"type":"Point"}
}