{
  "type": "Feature",
  "properties": {
    "addr:full":"7 Langdale Avenue Harpenden Hertfordshire AL5 5QU",
    "addr:housenumber":"7",
    "addr:postcode":"al5 5qu",
    "addr:street":"Langdale Avenue",
    "iso:country":"GB",
    "sg:address":"7 Langdale Avenue",
    "sg:city":"Harpenden",
    "sg:classifiers":[
        {
            "category":"Building & Trades",
            "subcategory":"Construction",
            "type":"Services"
        }
    ],
    "sg:phone":"+44 1582 760480",
    "sg:postcode":"AL5 5QU",
    "sg:province":"Hertfordshire",
    "sg:tags":[
        "decorator",
        "painter"
    ],
    "wof:name":"Petticoat Painters",
    "wof:placetype":"venue"
},
  "geometry": {"coordinates":[-0.3394140005,51.8201217651],"type":"Point"}
}