{
  "type": "Feature",
  "properties": {
    "iso:country":"GB",
    "sg:address":"The Triangle, Smarts Lane",
    "sg:city":"Loughton",
    "sg:classifiers":[
        {
            "category":"Home & Garden",
            "subcategory":"Hardware",
            "type":"Retail Goods"
        }
    ],
    "sg:phone":"+44 20 8508 7746",
    "sg:postcode":"IG10 4BU",
    "sg:province":"Essex",
    "sg:tags":[
        "lawnmowers",
        "machinery"
    ],
    "wof:name":"Buxted Ltd.",
    "wof:placetype":"venue"
},
  "geometry": {"coordinates":[0.055179,51.647373],"type":"Point"}
}