{
  "type": "Feature",
  "properties": {
    "addr:full":"5 Market St Carlisle Cumbria CA3 8QJ",
    "addr:housenumber":"5",
    "addr:postcode":"ca3 8qj",
    "addr:street":"Market St",
    "iso:country":"GB",
    "sg:address":"5 Market St",
    "sg:city":"Carlisle",
    "sg:classifiers":[
        {
            "category":"Place Of Worship",
            "type":"Public Place"
        }
    ],
    "sg:phone":"+44 1228 545540",
    "sg:postcode":"CA3 8QJ",
    "sg:province":"Cumbria",
    "wof:name":"Central Methodist Church",
    "wof:placetype":"venue"
},
  "geometry": {"coordinates":[-2.9371650219,54.8962745667],"type":"Point"}
}