{
  "type": "Feature",
  "properties": {
    "addr:full":"Fruit Exchange Building, 10-12 Victoria St Liverpool Merseyside L2 6QU",
    "addr:housenumber":"10-12",
    "addr:postcode":"l2 6qu",
    "addr:street":"Victoria St",
    "iso:country":"GB",
    "sg:address":"Fruit Exchange Building, 10-12 Victoria St",
    "sg:city":"Liverpool",
    "sg:classifiers":[
        {
            "category":"Building & Trades",
            "subcategory":"Construction",
            "type":"Services"
        }
    ],
    "sg:phone":"+44 151 227 1672",
    "sg:postcode":"L2 6QU",
    "sg:province":"Merseyside",
    "sg:tags":[
        "builder"
    ],
    "wof:name":"B & M Roofing & Building Contractors",
    "wof:placetype":"venue"
},
  "geometry": {"coordinates":[-2.98789,53.406658],"type":"Point"}
}