{
  "type": "Feature",
  "properties": {
    "addr:full":"Annbank Road, Belston-by-ayr Ayr East Ayrshire KA6 5JD",
    "addr:postcode":"ka6 5jd",
    "addr:street":"Annbank Road Belston-By-Ayr;East",
    "iso:country":"GB",
    "sg:address":"Annbank Road, Belston-by-ayr",
    "sg:city":"Ayr",
    "sg:classifiers":[
        {
            "category":"Transit Center",
            "subcategory":"Passenger",
            "type":"Transportation"
        }
    ],
    "sg:postcode":"KA6 5JD",
    "sg:province":"East Ayrshire",
    "sg:tags":[
        "boarding",
        "kennel",
        "catteries"
    ],
    "wof:name":"Little Acres Pets Hotel",
    "wof:placetype":"venue"
},
  "geometry": {"coordinates":[-4.5222439766,55.4756813049],"type":"Point"}
}