{
  "type": "Feature",
  "properties": {
    "addr:full":"8 Holgate Court, Western Road Romford Essex RM1 3JS",
    "addr:housenumber":"8",
    "addr:postcode":"rm1 3js",
    "addr:street":"Holgate Court Western Road",
    "iso:country":"GB",
    "sg:address":"8 Holgate Court, Western Road",
    "sg:city":"Romford",
    "sg:classifiers":[
        {
            "category":"Professional",
            "subcategory":"Lawyer & Legal Services",
            "type":"Services"
        }
    ],
    "sg:phone":"+44 1708 757577",
    "sg:postcode":"RM1 3JS",
    "sg:province":"Essex",
    "sg:tags":[
        "solicitor"
    ],
    "wof:name":"N B M Charle Whiting",
    "wof:placetype":"venue"
},
  "geometry": {"coordinates":[0.183221,51.576496],"type":"Point"}
}