{
  "type": "Feature",
  "properties": {
    "iso:country":"GB",
    "sg:address":"Maryfield Farm, New Abbey",
    "sg:city":"Dumfries",
    "sg:classifiers":[
        {
            "category":"Farming",
            "subcategory":"Dairy Farm",
            "type":"Manufacturing & Wholesale Goods"
        }
    ],
    "sg:phone":"+44 1387 850220",
    "sg:postcode":"DG2 8HH",
    "sg:province":"Dumfries and Galloway",
    "sg:tags":[
        "farmer"
    ],
    "wof:name":"I Burgess",
    "wof:placetype":"venue"
},
  "geometry": {"coordinates":[-3.615859,54.977261],"type":"Point"}
}