{
  "type": "Feature",
  "properties": {
    "iso:country":"GB",
    "sg:address":"19-21 Musters Road, West Bridgford",
    "sg:city":"Nottingham",
    "sg:classifiers":[
        {
            "category":"Banks & Credit Unions",
            "subcategory":"Financial Services",
            "type":"Services"
        }
    ],
    "sg:phone":"+44 115 982 2505",
    "sg:postcode":"NG2 7PP",
    "sg:province":"Nottinghamshire",
    "sg:tags":[
        "adviser"
    ],
    "wof:name":"Frank S Ulyatt",
    "wof:placetype":"venue"
},
  "geometry": {"coordinates":[-1.132782,52.934784],"type":"Point"}
}