{
  "type": "Feature",
  "properties": {
    "iso:country":"GB",
    "sg:address":"Barmpton Hall, Barmpton",
    "sg:city":"Darlington",
    "sg:classifiers":[
        {
            "category":"Farming",
            "subcategory":"Farm",
            "type":"Manufacturing & Wholesale Goods"
        }
    ],
    "sg:phone":"+44 1325 380713",
    "sg:postcode":"DL1 3JG",
    "sg:province":"Durham",
    "sg:tags":[
        "mixed",
        "crop"
    ],
    "wof:name":"R B Welch",
    "wof:placetype":"venue"
},
  "geometry": {"coordinates":[-1.5095740557,54.5563964844],"type":"Point"}
}