{
  "type": "Feature",
  "properties": {
    "iso:country":"GB",
    "sg:address":"56b Jubilee Road",
    "sg:city":"Aberdare",
    "sg:classifiers":[
        {
            "category":"Food & Beverages",
            "subcategory":"Meat & Fish",
            "type":"Retail Goods"
        }
    ],
    "sg:phone":"+44 1685 879166",
    "sg:postcode":"CF44 6DD",
    "sg:province":"Neath Port Talbot",
    "sg:tags":[
        "butcher"
    ],
    "wof:name":"John's Family Butcher",
    "wof:placetype":"venue"
},
  "geometry": {"coordinates":[-3.427126,51.697414],"type":"Point"}
}