{
  "type": "Feature",
  "properties": {
    "addr:full":"Unit 20 Podington Airfield Wellingborough Bedfordshire NN29 7JQ",
    "addr:housenumber":"unit 20",
    "addr:postcode":"nn29 7jq",
    "iso:country":"GB",
    "sg:address":"Unit 20 Podington Airfield",
    "sg:city":"Wellingborough",
    "sg:classifiers":[
        {
            "category":"Personal",
            "type":"Services"
        }
    ],
    "sg:postcode":"NN29 7JQ",
    "sg:province":"Bedfordshire",
    "sg:tags":[
        "wedding"
    ],
    "wof:name":"High Top Limousines",
    "wof:placetype":"venue"
},
  "geometry": {"coordinates":[-0.669829011,52.2580795288],"type":"Point"}
}