{
  "type": "Feature",
  "properties": {
    "iso:country":"GB",
    "sg:address":"2 Rising Bridge Road, Haslingden",
    "sg:city":"Rossendale",
    "sg:classifiers":[
        {
            "category":"Health Services",
            "subcategory":"Nursing And Care Facility",
            "type":"Services"
        },
        {
            "category":"Social Services",
            "subcategory":"Retirement Home",
            "type":"Services"
        }
    ],
    "sg:phone":"+44 1706 224580",
    "sg:postcode":"BB4 5BL",
    "sg:province":"Lancashire",
    "sg:tags":[
        "residential",
        "rest"
    ],
    "wof:name":"The Hollies",
    "wof:placetype":"venue"
},
  "geometry": {"coordinates":[-2.330164,53.718407],"type":"Point"}
}