{
  "type": "Feature",
  "properties": {
    "iso:country":"GB",
    "sg:address":"Trafford Park Road, Trafford Park",
    "sg:city":"Manchester",
    "sg:classifiers":[
        {
            "category":"Retail",
            "subcategory":"Event Space",
            "type":"Services"
        }
    ],
    "sg:phone":"+44 161 872 2381",
    "sg:postcode":"M17 1HP",
    "sg:province":"Cheshire",
    "sg:tags":[
        "abrasive",
        "product"
    ],
    "wof:name":"Carborundum Abrasives G B Ltd.",
    "wof:placetype":"venue"
},
  "geometry": {"coordinates":[-2.3219900131,53.4765434265],"type":"Point"}
}