{
  "type": "Feature",
  "properties": {
    "iso:country":"GB",
    "sg:address":"3 Wath Lane",
    "sg:city":"York",
    "sg:classifiers":[
        {
            "category":"Military Area",
            "subcategory":"Air Force Base",
            "type":"Public Place"
        }
    ],
    "sg:phone":"+44 1423 360000",
    "sg:postcode":"YO61 2RY",
    "sg:province":"North Yorkshire",
    "sg:tags":[
        "taxi",
        "hire",
        "private"
    ],
    "wof:name":"G B S & Telcars",
    "wof:placetype":"venue"
},
  "geometry": {"coordinates":[-1.35341,54.118568],"type":"Point"}
}