{
  "type": "Feature",
  "properties": {
    "addr:full":"The Coach House, Coombe Park Road, Whitchurch On Thames Reading Berkshire RG8 7QT",
    "addr:postcode":"rg8 7qt",
    "addr:street":"Coombe Park Road",
    "iso:country":"GB",
    "sg:address":"The Coach House, Coombe Park Road, Whitchurch On Thames",
    "sg:city":"Reading",
    "sg:classifiers":[
        {
            "category":"Personal",
            "subcategory":"Adult",
            "type":"Services"
        }
    ],
    "sg:phone":"+44 118 984 1317",
    "sg:postcode":"RG8 7QT",
    "sg:province":"Berkshire",
    "sg:tags":[
        "equestrian"
    ],
    "wof:name":"Willonyx Racing Ltd.",
    "wof:placetype":"venue"
},
  "geometry": {"coordinates":[-1.087613,51.491974],"type":"Point"}
}