{
  "type": "Feature",
  "properties": {
    "addr:full":"159 Minories London Greater London EC3N 1LE",
    "addr:housenumber":"159",
    "addr:postcode":"ec3n 1le",
    "addr:street":"Minories",
    "iso:country":"GB",
    "sg:address":"159 Minories",
    "sg:city":"London",
    "sg:classifiers":[
        {
            "category":"Banks & Credit Unions",
            "subcategory":"Bank",
            "type":"Services"
        }
    ],
    "sg:phone":"+44 20 8301 7324",
    "sg:postcode":"EC3N 1LE",
    "sg:province":"Greater London",
    "wof:name":"Woolwich Ltd.",
    "wof:placetype":"venue"
},
  "geometry": {"coordinates":[-0.0754489973,51.5119590759],"type":"Point"}
}