{
  "type": "Feature",
  "properties": {
    "addr:full":"Chestnut Farm Camping& Caravan Park, Moor End, Acaster Malbis York North Yorkshire YO23 2UQ",
    "addr:postcode":"yo23 2uq",
    "addr:street":"Moor End",
    "iso:country":"GB",
    "sg:address":"Chestnut Farm Camping& Caravan Park, Moor End, Acaster Malbis",
    "sg:city":"York",
    "sg:classifiers":[
        {
            "category":"Bars & Pubs",
            "subcategory":"Hookah Bar",
            "type":"Food & Drink"
        },
        {
            "category":"Recreation",
            "subcategory":"Campground",
            "type":"Entertainment"
        }
    ],
    "sg:phone":"+44 1904 704676",
    "sg:postcode":"YO23 2UQ",
    "sg:province":"North Yorkshire",
    "sg:tags":[
        "holiday",
        "self",
        "camp",
        "catering",
        "centre"
    ],
    "wof:name":"Chestnut Farm Caravan Park",
    "wof:placetype":"venue"
},
  "geometry": {"coordinates":[-1.1129870415,53.9151802063],"type":"Point"}
}