{
  "type": "Feature",
  "properties": {
    "addr:full":"2 Cross La, Braunston Daventry Northamptonshire NN11 7HH",
    "addr:housenumber":"2",
    "addr:postcode":"nn11 7hh",
    "addr:street":"Cross La Braunston",
    "iso:country":"GB",
    "sg:address":"2 Cross La, Braunston",
    "sg:city":"Daventry",
    "sg:classifiers":[
        {
            "category":"Personal",
            "subcategory":"Beauty Salon",
            "type":"Services"
        }
    ],
    "sg:postcode":"NN11 7HH",
    "sg:province":"Northamptonshire",
    "sg:tags":[
        "unisex",
        "hairdresser"
    ],
    "wof:name":"Mirror Image",
    "wof:placetype":"venue"
},
  "geometry": {"coordinates":[-1.208084,52.29118],"type":"Point"}
}