{
  "type": "Feature",
  "properties": {
    "addr:full":"84 Moorfield Drive Sutton Coldfield West Midlands B73 5LQ",
    "addr:housenumber":"84",
    "addr:postcode":"b73 5lq",
    "addr:street":"Moorfield Drive",
    "iso:country":"GB",
    "sg:address":"84 Moorfield Drive",
    "sg:city":"Sutton Coldfield",
    "sg:classifiers":[
        {
            "category":"Shopping",
            "subcategory":"Party Supplies",
            "type":"Retail Goods"
        },
        {
            "category":"Arts & Performance",
            "subcategory":"Music",
            "type":"Entertainment"
        }
    ],
    "sg:phone":"+44 121 350 4426",
    "sg:postcode":"B73 5LQ",
    "sg:province":"West Midlands",
    "sg:tags":[
        "mobile",
        "operator",
        "disco"
    ],
    "wof:name":"A & S Disco",
    "wof:placetype":"venue"
},
  "geometry": {"coordinates":[-1.8401249647,52.5404777527],"type":"Point"}
}