{
  "type": "Feature",
  "properties": {
    "iso:country":"GB",
    "sg:address":"50 Mostyn Street",
    "sg:city":"Llandudno",
    "sg:classifiers":[
        {
            "category":"Banks & Credit Unions",
            "subcategory":"Bank",
            "type":"Services"
        }
    ],
    "sg:phone":"+44 1492 860099",
    "sg:postcode":"LL30 2RP",
    "sg:province":"Conwy",
    "sg:tags":[
        "financial",
        "institution"
    ],
    "wof:name":"WOOLWICH LTD",
    "wof:placetype":"venue"
},
  "geometry": {"coordinates":[-3.829345,53.323799],"type":"Point"}
}