{
  "type": "Feature",
  "properties": {
    "addr:full":"Francis Avenue Southsea Hampshire PO4 0AG",
    "addr:postcode":"po4 0ag",
    "addr:street":"Francis Avenue",
    "iso:country":"GB",
    "sg:address":"Francis Avenue",
    "sg:city":"Southsea",
    "sg:classifiers":[
        {
            "category":"Education",
            "subcategory":"School",
            "type":"Public Place"
        },
        {
            "category":"Government",
            "subcategory":"Office",
            "type":"Public Place"
        }
    ],
    "sg:phone":"+44 23 9273 4902",
    "sg:postcode":"PO4 0AG",
    "sg:province":"Hampshire",
    "sg:tags":[
        "local",
        "authority"
    ],
    "sg:website":"http://www.devonshire.portsmouth.sch.uk",
    "wof:name":"Devonshire Infant School",
    "wof:placetype":"venue"
},
  "geometry": {"coordinates":[-1.070234,50.792885],"type":"Point"}
}