{
  "type": "Feature",
  "properties": {
    "iso:country":"GB",
    "sg:address":"Salbrook Rd, Salfords",
    "sg:city":"Redhill",
    "sg:classifiers":[
        {
            "category":"Freight",
            "type":"Transportation"
        }
    ],
    "sg:postcode":"RH1 5HB",
    "sg:province":"Surrey",
    "sg:tags":[
        "haulage",
        "road"
    ],
    "wof:name":"Hammond Transport Group Ltd",
    "wof:placetype":"venue"
},
  "geometry": {"coordinates":[-0.1657579988,51.1982498169],"type":"Point"}
}