{
  "type": "Feature",
  "properties": {
    "addr:full":"22 Bromley Street York North Yorkshire YO26 4YQ",
    "addr:housenumber":"22",
    "addr:postcode":"yo26 4yq",
    "addr:street":"Bromley Street",
    "iso:country":"GB",
    "sg:address":"22 Bromley Street",
    "sg:city":"York",
    "sg:classifiers":[
        {
            "category":"Shopping",
            "subcategory":"Department Store",
            "type":"Retail Goods"
        },
        {
            "category":"Food & Beverages",
            "subcategory":"Groceries & Convenience Stores",
            "type":"Retail Goods"
        }
    ],
    "sg:phone":"+44 1904 629524",
    "sg:postcode":"YO26 4YQ",
    "sg:province":"North Yorkshire",
    "wof:name":"The General Store",
    "wof:placetype":"venue"
},
  "geometry": {"coordinates":[-1.106887,53.964306],"type":"Point"}
}