{
  "type": "Feature",
  "properties": {
    "addr:full":"Orchard Cottage Northwich Cheshire CW9 7SN",
    "addr:postcode":"cw9 7sn",
    "iso:country":"GB",
    "sg:address":"Orchard Cottage",
    "sg:city":"Northwich",
    "sg:classifiers":[
        {
            "category":"Building & Trades",
            "subcategory":"Landscaping Services",
            "type":"Services"
        }
    ],
    "sg:phone":"+44 1606 331777",
    "sg:postcode":"CW9 7SN",
    "sg:province":"Cheshire",
    "sg:tags":[
        "forestry",
        "tree"
    ],
    "wof:name":"Roger Parker Tree Surgeon",
    "wof:placetype":"venue"
},
  "geometry": {"coordinates":[-2.501564,53.260666],"type":"Point"}
}