{
  "type": "Feature",
  "properties": {
    "addr:full":"126 Montague Street Worthing West Sussex BN11 3HG",
    "addr:housenumber":"126",
    "addr:postcode":"bn11 3hg",
    "addr:street":"Montague Street",
    "iso:country":"GB",
    "sg:address":"126 Montague Street",
    "sg:city":"Worthing",
    "sg:classifiers":[
        {
            "category":"Shopping",
            "subcategory":"Thrift Store",
            "type":"Retail Goods"
        }
    ],
    "sg:phone":"+44 1903 207595",
    "sg:postcode":"BN11 3HG",
    "sg:province":"West Sussex",
    "sg:tags":[
        "shop",
        "charity"
    ],
    "wof:name":"Imperial Cancer Research Fund",
    "wof:placetype":"venue"
},
  "geometry": {"coordinates":[-0.37702,50.809978],"type":"Point"}
}