{
  "type": "Feature",
  "properties": {
    "addr:full":"9 Swan Court, High Street Waltham Cross Essex EN8 7BH",
    "addr:housenumber":"9",
    "addr:postcode":"en8 7bh",
    "addr:street":"Swan Court High Street",
    "iso:country":"GB",
    "sg:address":"9 Swan Court, High Street",
    "sg:city":"Waltham Cross",
    "sg:classifiers":[
        {
            "category":"Shopping",
            "subcategory":"Comic Books",
            "type":"Retail Goods"
        }
    ],
    "sg:phone":"+44 1992 717432",
    "sg:postcode":"EN8 7BH",
    "sg:province":"Essex",
    "sg:tags":[
        "jeweller"
    ],
    "wof:name":"Stuarts (Waltham) Ltd.",
    "wof:placetype":"venue"
},
  "geometry": {"coordinates":[-0.0338140018,51.6905097961],"type":"Point"}
}