{
  "type": "Feature",
  "properties": {
    "iso:country":"GB",
    "sg:address":"Jewry House, Jewry St",
    "sg:city":"Winchester",
    "sg:classifiers":[
        {
            "category":"Manufacturing",
            "subcategory":"Tools & Machinery",
            "type":"Manufacturing & Wholesale Goods"
        }
    ],
    "sg:phone":"+44 1962 877818",
    "sg:postcode":"SO23 8RZ",
    "sg:province":"Hampshire",
    "sg:tags":[
        "society",
        "friendly"
    ],
    "wof:name":"Client Insurance Management",
    "wof:placetype":"venue"
},
  "geometry": {"coordinates":[-1.315899,51.065723],"type":"Point"}
}