{
  "type": "Feature",
  "properties": {
    "iso:country":"GB",
    "sg:address":"Dumb Hall Farm, Steetley",
    "sg:city":"Worksop",
    "sg:classifiers":[
        {
            "category":"Farming",
            "subcategory":"Livestock Farm",
            "type":"Manufacturing & Wholesale Goods"
        }
    ],
    "sg:postcode":"S80 3DZ",
    "sg:province":"Nottinghamshire",
    "sg:tags":[
        "others"
    ],
    "wof:name":"Ken Hall Farming",
    "wof:placetype":"venue"
},
  "geometry": {"coordinates":[-1.193117,53.307995],"type":"Point"}
}