{
  "type": "Feature",
  "properties": {
    "iso:country":"GB",
    "sg:address":"435 Park Rd",
    "sg:city":"Kingston Upon Thames",
    "sg:classifiers":[
        {
            "category":"Professional",
            "subcategory":"Accounting & Tax Preparation",
            "type":"Services"
        }
    ],
    "sg:phone":"+44 20 8549 3533",
    "sg:postcode":"KT2 5RL",
    "sg:province":"Greater London",
    "sg:tags":[
        "accountant"
    ],
    "wof:name":"Penny Wright",
    "wof:placetype":"venue"
},
  "geometry": {"coordinates":[-0.291825,51.428059],"type":"Point"}
}