{
  "type": "Feature",
  "properties": {
    "iso:country":"GB",
    "sg:address":"Collier Row La",
    "sg:city":"Romford",
    "sg:classifiers":[
        {
            "category":"Place Of Worship",
            "type":"Public Place"
        }
    ],
    "sg:phone":"+44 1708 745626",
    "sg:postcode":"RM5 3BA",
    "sg:province":"Essex",
    "wof:name":"Church Of The Good Shepherd",
    "wof:placetype":"venue"
},
  "geometry": {"coordinates":[0.1633349955,51.5986557007],"type":"Point"}
}