{
  "type": "Feature",
  "properties": {
    "addr:full":"7 Church Lane West Bromwich West Midlands B71 1DD",
    "addr:housenumber":"7",
    "addr:postcode":"b71 1dd",
    "addr:street":"Church Lane",
    "iso:country":"GB",
    "sg:address":"7 Church Lane",
    "sg:city":"West Bromwich",
    "sg:classifiers":[
        {
            "category":"Home & Garden",
            "subcategory":"Hardware",
            "type":"Retail Goods"
        }
    ],
    "sg:phone":"+44 121 553 6216",
    "sg:postcode":"B71 1DD",
    "sg:province":"West Midlands",
    "sg:tags":[
        "compressor",
        "air"
    ],
    "wof:name":"Economatics (Industrial) Ltd.",
    "wof:placetype":"venue"
},
  "geometry": {"coordinates":[-2.0070478916,52.5299606323],"type":"Point"}
}