{
  "type": "Feature",
  "properties": {
    "addr:full":"85 Orrell La Liverpool Merseyside L9 8BL",
    "addr:housenumber":"85",
    "addr:postcode":"l9 8bl",
    "addr:street":"Orrell La",
    "iso:country":"GB",
    "sg:address":"85 Orrell La",
    "sg:city":"Liverpool",
    "sg:classifiers":[
        {
            "category":"Shopping",
            "subcategory":"Florist",
            "type":"Retail Goods"
        }
    ],
    "sg:postcode":"L9 8BL",
    "sg:province":"Merseyside",
    "wof:name":"Esther's Florists",
    "wof:placetype":"venue"
},
  "geometry": {"coordinates":[-2.96734,53.46447],"type":"Point"}
}