{
  "type": "Feature",
  "properties": {
    "iso:country":"GB",
    "sg:address":"39 Cassillis Road",
    "sg:city":"Maybole",
    "sg:classifiers":[
        {
            "category":"Retail",
            "subcategory":"Funeral Services",
            "type":"Services"
        }
    ],
    "sg:phone":"+44 1655 882127",
    "sg:postcode":"KA19 7HF",
    "sg:province":"East Ayrshire",
    "wof:name":"Co-Operative Funeral Services",
    "wof:placetype":"venue"
},
  "geometry": {"coordinates":[-4.678745,55.355713],"type":"Point"}
}