{
  "type": "Feature",
  "properties": {
    "iso:country":"GB",
    "sg:address":"8-10 Liscard Way",
    "sg:city":"Wallasey",
    "sg:classifiers":[
        {
            "category":"Recreation",
            "subcategory":"Amusement Park",
            "type":"Entertainment"
        }
    ],
    "sg:phone":"+44 151 638 2279",
    "sg:postcode":"L44 5TP",
    "sg:province":"Merseyside",
    "sg:tags":[
        "arcade"
    ],
    "wof:name":"Reel Time",
    "wof:placetype":"venue"
},
  "geometry": {"coordinates":[-3.042746067,53.4192581177],"type":"Point"}
}