{
  "type": "Feature",
  "properties": {
    "iso:country":"GB",
    "sg:address":"1 Kingsbridge Rd",
    "sg:city":"Reading",
    "sg:classifiers":[
        {
            "category":"Professional",
            "subcategory":"Detective & Security Services",
            "type":"Services"
        }
    ],
    "sg:phone":"+44 118 975 1416",
    "sg:postcode":"RG2 7RE",
    "sg:province":"Berkshire",
    "sg:tags":[
        "car"
    ],
    "wof:name":"Globalcom",
    "wof:placetype":"venue"
},
  "geometry": {"coordinates":[-0.966756,51.432945],"type":"Point"}
}