{
  "type": "Feature",
  "properties": {
    "iso:country":"GB",
    "sg:address":"223 London Road",
    "sg:city":"Benfleet",
    "sg:classifiers":[
        {
            "category":"Manufacturing",
            "subcategory":"Building Materials",
            "type":"Manufacturing & Wholesale Goods"
        }
    ],
    "sg:phone":"+44 1268 566566",
    "sg:postcode":"SS7 5UN",
    "sg:province":"Essex",
    "sg:tags":[
        "merchant",
        "builder"
    ],
    "wof:name":"Canvey Supply Co",
    "wof:placetype":"venue"
},
  "geometry": {"coordinates":[0.557087,51.567013],"type":"Point"}
}