{
  "type": "Feature",
  "properties": {
    "addr:full":"The Elms New Road, Purton Swindon Wiltshire SN5 4HG",
    "addr:postcode":"sn5 4hg",
    "addr:street":"New Road",
    "iso:country":"GB",
    "sg:address":"The Elms New Road, Purton",
    "sg:city":"Swindon",
    "sg:classifiers":[
        {
            "category":"Utilities",
            "subcategory":"Refuse",
            "type":"Services"
        }
    ],
    "sg:phone":"+44 1793 771977",
    "sg:postcode":"SN5 4HG",
    "sg:province":"Wiltshire",
    "sg:tags":[
        "retail",
        "skip",
        "hire",
        "waste",
        "disposal"
    ],
    "wof:name":"Hills Aggregates",
    "wof:placetype":"venue"
},
  "geometry": {"coordinates":[-1.8660390377,51.5903739929],"type":"Point"}
}