{
  "type": "Feature",
  "properties": {
    "iso:country":"GB",
    "sg:address":"1 Talbot Avenue",
    "sg:city":"Bristol",
    "sg:classifiers":[
        {
            "category":"Building & Trades",
            "subcategory":"Construction",
            "type":"Services"
        }
    ],
    "sg:postcode":"BS15 1HE",
    "sg:province":"City of Bristol",
    "sg:tags":[
        "joiner",
        "carpenter"
    ],
    "wof:name":"Alan George Fisher",
    "wof:placetype":"venue"
},
  "geometry": {"coordinates":[-2.520665884,51.4648666382],"type":"Point"}
}