{
  "type": "Feature",
  "properties": {
    "addr:full":"39 Wide Bargate Boston Lincolnshire PE21 6SR",
    "addr:housenumber":"39",
    "addr:postcode":"pe21 6sr",
    "addr:street":"Wide Bargate",
    "iso:country":"GB",
    "sg:address":"39 Wide Bargate",
    "sg:city":"Boston",
    "sg:classifiers":[
        {
            "category":"Personal",
            "subcategory":"Beauty Salon",
            "type":"Services"
        },
        {
            "category":"Personal",
            "subcategory":"Barber",
            "type":"Services"
        },
        {
            "category":"Professional",
            "subcategory":"Management & Consulting",
            "type":"Services"
        }
    ],
    "sg:phone":"+44 1205 369830",
    "sg:postcode":"PE21 6SR",
    "sg:province":"Lincolnshire",
    "sg:tags":[
        "unisex",
        "specialist",
        "hairdresser",
        "consultant"
    ],
    "wof:name":"Sandra Edmonds",
    "wof:placetype":"venue"
},
  "geometry": {"coordinates":[-0.020156,52.980011],"type":"Point"}
}