{
  "type": "Feature",
  "properties": {
    "addr:full":"Moydog Fawr Welshpool Shropshire SY21 9BD",
    "addr:postcode":"sy21 9bd",
    "iso:country":"GB",
    "sg:address":"Moydog Fawr",
    "sg:city":"Welshpool",
    "sg:classifiers":[
        {
            "category":"Farming",
            "subcategory":"Livestock Farm",
            "type":"Manufacturing & Wholesale Goods"
        }
    ],
    "sg:phone":"+44 1938 850248",
    "sg:postcode":"SY21 9BD",
    "sg:province":"Shropshire",
    "sg:tags":[
        "others"
    ],
    "wof:name":"F Humphreys & Son",
    "wof:placetype":"venue"
},
  "geometry": {"coordinates":[-3.1879971027,52.6795959473],"type":"Point"}
}