{
  "type": "Feature",
  "properties": {
    "addr:full":"Annsdale, Coote La, Whitestake Preston Lancashire PR4 4LJ",
    "addr:postcode":"pr4 4lj",
    "addr:street":"Preston",
    "iso:country":"GB",
    "sg:address":"Annsdale, Coote La, Whitestake",
    "sg:city":"Preston",
    "sg:classifiers":[
        {
            "category":"Professional",
            "subcategory":"Accounting & Tax Preparation",
            "type":"Services"
        }
    ],
    "sg:postcode":"PR4 4LJ",
    "sg:province":"Lancashire",
    "sg:tags":[
        "accountant"
    ],
    "wof:name":"L H C Westerbeek",
    "wof:placetype":"venue"
},
  "geometry": {"coordinates":[-2.70715,53.722969],"type":"Point"}
}