{
  "type": "Feature",
  "properties": {
    "addr:full":"25 Moonpenny Way Dronfield Derbyshire S18 1SA",
    "addr:housenumber":"25",
    "addr:postcode":"s18 1sa",
    "addr:street":"Moonpenny Way",
    "iso:country":"GB",
    "sg:address":"25 Moonpenny Way",
    "sg:city":"Dronfield",
    "sg:classifiers":[
        {
            "category":"Banks & Credit Unions",
            "subcategory":"Financial Services",
            "type":"Services"
        }
    ],
    "sg:phone":"+44 1246 415780",
    "sg:postcode":"S18 1SA",
    "sg:province":"Derbyshire",
    "sg:tags":[
        "consultant"
    ],
    "wof:name":"Charles James & Co",
    "wof:placetype":"venue"
},
  "geometry": {"coordinates":[-1.473514,53.299152],"type":"Point"}
}