{
  "type": "Feature",
  "properties": {
    "iso:country":"GB",
    "sg:address":"2 Mount Nod Way",
    "sg:city":"Coventry",
    "sg:classifiers":[
        {
            "category":"Professional",
            "subcategory":"Engineering",
            "type":"Services"
        }
    ],
    "sg:postcode":"CV5 7GX",
    "sg:province":"West Midlands",
    "sg:tags":[
        "contractor",
        "electrical",
        "engineer"
    ],
    "wof:name":"Interlec Services",
    "wof:placetype":"venue"
},
  "geometry": {"coordinates":[-1.563935,52.409218],"type":"Point"}
}