{
  "type": "Feature",
  "properties": {
    "addr:full":"Ashenbottom Farm, Ewood Bridge Rossendale Lancashire BB4 6JY",
    "addr:postcode":"bb4 6jy",
    "addr:street":"Ewood Bridge",
    "iso:country":"GB",
    "sg:address":"Ashenbottom Farm, Ewood Bridge",
    "sg:city":"Rossendale",
    "sg:classifiers":[
        {
            "category":"Farming",
            "subcategory":"Livestock Farm",
            "type":"Manufacturing & Wholesale Goods"
        }
    ],
    "sg:phone":"+44 1706 217427",
    "sg:postcode":"BB4 6JY",
    "sg:province":"Lancashire",
    "sg:tags":[
        "stud"
    ],
    "wof:name":"W Smith (General Contractors) Ltd.",
    "wof:placetype":"venue"
},
  "geometry": {"coordinates":[-2.274823904,53.7089614868],"type":"Point"}
}