{
  "type": "Feature",
  "properties": {
    "iso:country":"GB",
    "sg:address":"Peerless House, Talbot Road",
    "sg:city":"Wellingborough",
    "sg:classifiers":[
        {
            "category":"Professional",
            "subcategory":"Engineering",
            "type":"Services"
        },
        {
            "category":"Building & Trades",
            "subcategory":"Electrical",
            "type":"Services"
        }
    ],
    "sg:phone":"+44 1933 442525",
    "sg:postcode":"NN8 1QH",
    "sg:province":"Northamptonshire",
    "sg:tags":[
        "engineer",
        "electrician",
        "contractor"
    ],
    "wof:name":"J Memoli Ltd",
    "wof:placetype":"venue"
},
  "geometry": {"coordinates":[-0.677884,52.305161],"type":"Point"}
}