{
  "type": "Feature",
  "properties": {
    "addr:full":"7 Chestnut Drive, Bushby Leicester Leicestershire LE7 9RB",
    "addr:housenumber":"7",
    "addr:postcode":"le7 9rb",
    "addr:street":"Chestnut Drive",
    "iso:country":"GB",
    "sg:address":"7 Chestnut Drive, Bushby",
    "sg:city":"Leicester",
    "sg:classifiers":[
        {
            "category":"Home & Garden",
            "subcategory":"Carpets & Floor Coverings",
            "type":"Retail Goods"
        }
    ],
    "sg:postcode":"LE7 9RB",
    "sg:province":"Leicestershire",
    "sg:tags":[
        "carpets",
        "rug",
        "matting"
    ],
    "wof:name":"David Screaton Carpets",
    "wof:placetype":"venue"
},
  "geometry": {"coordinates":[-1.0356199741,52.6292991638],"type":"Point"}
}