{
  "type": "Feature",
  "properties": {
    "addr:full":"Holme Lane, Townsend Fold Rossendale Lancashire BB4 6JB",
    "addr:postcode":"bb4 6jb",
    "addr:street":"Holme Lane Townsend Fold",
    "iso:country":"GB",
    "sg:address":"Holme Lane, Townsend Fold",
    "sg:city":"Rossendale",
    "sg:classifiers":[
        {
            "category":"Social Services",
            "subcategory":"Retirement Home",
            "type":"Services"
        }
    ],
    "sg:postcode":"BB4 6JB",
    "sg:province":"Lancashire",
    "sg:tags":[
        "rest"
    ],
    "wof:name":"Holme Manor",
    "wof:placetype":"venue"
},
  "geometry": {"coordinates":[-2.2990989685,53.692325592],"type":"Point"}
}