{
  "type": "Feature",
  "properties": {
    "addr:full":"52 Park Lane, Poynton Stockport Cheshire SK12 1RE",
    "addr:housenumber":"52",
    "addr:postcode":"sk12 1re",
    "addr:street":"Park Lane",
    "iso:country":"GB",
    "sg:address":"52 Park Lane, Poynton",
    "sg:city":"Stockport",
    "sg:classifiers":[
        {
            "category":"Fast Food",
            "type":"Food & Drink"
        }
    ],
    "sg:phone":"+44 1625 858889",
    "sg:postcode":"SK12 1RE",
    "sg:province":"Cheshire",
    "sg:tags":[
        "away",
        "take"
    ],
    "wof:name":"D Richards",
    "wof:placetype":"venue"
},
  "geometry": {"coordinates":[-2.120631,53.348759],"type":"Point"}
}