{
  "type": "Feature",
  "properties": {
    "addr:full":"125 Upper Commercial Street Batley West Yorkshire WF17 5DQ",
    "addr:housenumber":"125",
    "addr:postcode":"wf17 5dq",
    "addr:street":"Upper Commercial Street",
    "iso:country":"GB",
    "sg:address":"125 Upper Commercial Street",
    "sg:city":"Batley",
    "sg:classifiers":[
        {
            "category":"Communications",
            "type":"Services"
        }
    ],
    "sg:phone":"+44 1924 441894",
    "sg:postcode":"WF17 5DQ",
    "sg:province":"West Yorkshire",
    "sg:tags":[
        "tv",
        "video",
        "radio"
    ],
    "wof:name":"G Marshall",
    "wof:placetype":"venue"
},
  "geometry": {"coordinates":[-1.6370990276,53.7150650024],"type":"Point"}
}