{
  "type": "Feature",
  "properties": {
    "iso:country":"GB",
    "sg:address":"12 Dennington Lane, Crigglestone",
    "sg:city":"Wakefield",
    "sg:classifiers":[
        {
            "category":"Organizations",
            "subcategory":"Non-profit Organization",
            "type":"Services"
        }
    ],
    "sg:phone":"+44 1924 254433",
    "sg:postcode":"WF4 3ET",
    "sg:province":"West Yorkshire",
    "sg:tags":[
        "organisation",
        "voluntary",
        "charity"
    ],
    "wof:name":"National Pure Water Association",
    "wof:placetype":"venue"
},
  "geometry": {"coordinates":[-1.5413780212,53.6348457336],"type":"Point"}
}