{
  "type": "Feature",
  "properties": {
    "addr:full":"80 Imperial Avenue, Maylandsea Chelmsford Essex CM3 6AH",
    "addr:housenumber":"80",
    "addr:postcode":"cm3 6ah",
    "addr:street":"Imperial Avenue Maylandsea",
    "iso:country":"GB",
    "sg:address":"80 Imperial Avenue, Maylandsea",
    "sg:city":"Chelmsford",
    "sg:classifiers":[
        {
            "category":"Building & Trades",
            "subcategory":"Construction",
            "type":"Services"
        }
    ],
    "sg:phone":"+44 1621 741618",
    "sg:postcode":"CM3 6AH",
    "sg:province":"Essex",
    "sg:tags":[
        "builder"
    ],
    "wof:name":"A K W Enterprise",
    "wof:placetype":"venue"
},
  "geometry": {"coordinates":[0.753743,51.686874],"type":"Point"}
}