{
  "type": "Feature",
  "properties": {
    "addr:full":"6 Hillside Crescent Edinburgh City of Edinburgh EH7 5DY",
    "addr:housenumber":"6",
    "addr:postcode":"eh7 5dy",
    "addr:street":"Hillside Crescent",
    "iso:country":"GB",
    "sg:address":"6 Hillside Crescent",
    "sg:city":"Edinburgh",
    "sg:classifiers":[
        {
            "category":"Organizations",
            "subcategory":"Professional Association",
            "type":"Services"
        }
    ],
    "sg:phone":"+44 131 556 0407",
    "sg:postcode":"EH7 5DY",
    "sg:province":"City of Edinburgh",
    "sg:tags":[
        "union",
        "trade"
    ],
    "wof:name":"Public and Commercial Services Union",
    "wof:placetype":"venue"
},
  "geometry": {"coordinates":[-3.180336,55.958153],"type":"Point"}
}