{
  "type": "Feature",
  "properties": {
    "addr:full":"32 Well Road, Chartsutton Maidstone Kent ME14 1XL",
    "addr:housenumber":"32",
    "addr:postcode":"me14 1xl",
    "addr:street":"Well Road Chartsutton",
    "iso:country":"GB",
    "sg:address":"32 Well Road, Chartsutton",
    "sg:city":"Maidstone",
    "sg:classifiers":[
        {
            "category":"Travel",
            "subcategory":"Travel Agent",
            "type":"Entertainment"
        }
    ],
    "sg:phone":"+44 845 230 9870",
    "sg:postcode":"ME14 1XL",
    "sg:province":"Kent",
    "sg:tags":[
        "agency",
        "activity"
    ],
    "wof:name":"Ray Clark Travel Ltd.",
    "wof:placetype":"venue"
},
  "geometry": {"coordinates":[0.526613,51.278717],"type":"Point"}
}