{
  "type": "Feature",
  "properties": {
    "iso:country":"GB",
    "sg:address":"28 Easter Road",
    "sg:city":"Edinburgh",
    "sg:classifiers":[
        {
            "category":"Fast Food",
            "type":"Food & Drink"
        }
    ],
    "sg:phone":"+44 131 661 1946",
    "sg:postcode":"EH7 5RG",
    "sg:province":"City of Edinburgh",
    "sg:tags":[
        "away",
        "take"
    ],
    "wof:name":"Lotus House",
    "wof:placetype":"venue"
},
  "geometry": {"coordinates":[-3.171712,55.958141],"type":"Point"}
}