{
  "type": "Feature",
  "properties": {
    "iso:country":"GB",
    "sg:address":"30 Almond Avenue, Shaw",
    "sg:city":"Newbury",
    "sg:classifiers":[
        {
            "category":"Building & Trades",
            "subcategory":"Construction",
            "type":"Services"
        }
    ],
    "sg:postcode":"RG14 1LT",
    "sg:province":"Berkshire",
    "sg:tags":[
        "contractor",
        "paving",
        "driveway"
    ],
    "wof:name":"Malcolm J Flitter",
    "wof:placetype":"venue"
},
  "geometry": {"coordinates":[-1.323952,51.410572],"type":"Point"}
}