{
  "type": "Feature",
  "properties": {
    "addr:full":"Harpur Street Bedford Bedfordshire MK40 1BA",
    "addr:postcode":"mk40 1ba",
    "addr:street":"Harpur Street",
    "iso:country":"GB",
    "sg:address":"Harpur Street",
    "sg:city":"Bedford",
    "sg:classifiers":[
        {
            "category":"Retail",
            "subcategory":"Storage",
            "type":"Services"
        }
    ],
    "sg:postcode":"MK40 1BA",
    "sg:province":"Bedfordshire",
    "sg:tags":[
        "household",
        "removal"
    ],
    "wof:name":"Arnolds Removals",
    "wof:placetype":"venue"
},
  "geometry": {"coordinates":[-0.4683409929,52.1362342834],"type":"Point"}
}