{
  "type": "Feature",
  "properties": {
    "addr:full":"Town Hall, Manchester Rd, Stocksbridge Sheffield South Yorkshire S36 2DT",
    "addr:postcode":"s36 2dt",
    "addr:street":"Manchester Rd",
    "iso:country":"GB",
    "sg:address":"Town Hall, Manchester Rd, Stocksbridge",
    "sg:city":"Sheffield",
    "sg:classifiers":[
        {
            "category":"Organizations",
            "subcategory":"Non-profit Organization",
            "type":"Services"
        }
    ],
    "sg:phone":"+44 114 288 5550",
    "sg:postcode":"S36 2DT",
    "sg:province":"South Yorkshire",
    "sg:tags":[
        "organisation",
        "voluntary",
        "charity"
    ],
    "wof:name":"Stocksbridge Community Trust",
    "wof:placetype":"venue"
},
  "geometry": {"coordinates":[-1.6185990572,53.4912261963],"type":"Point"}
}