{
  "type": "Feature",
  "properties": {
    "iso:country":"GB",
    "sg:address":"245 Rossmore Road, Parkstone",
    "sg:city":"Poole",
    "sg:classifiers":[
        {
            "category":"Manufacturing",
            "subcategory":"Electronics",
            "type":"Manufacturing & Wholesale Goods"
        }
    ],
    "sg:postcode":"BH12 2HQ",
    "sg:province":"Dorset",
    "sg:tags":[
        "mnfrs",
        "transformer"
    ],
    "wof:name":"Majestic Transformer Co.",
    "wof:placetype":"venue"
},
  "geometry": {"coordinates":[-1.927661,50.736038],"type":"Point"}
}