{
  "type": "Feature",
  "properties": {
    "iso:country":"GB",
    "sg:address":"89 Alexandra Road",
    "sg:city":"Peterborough",
    "sg:classifiers":[
        {
            "category":"Real Estate",
            "subcategory":"Architect",
            "type":"Services"
        }
    ],
    "sg:postcode":"PE1 3DG",
    "sg:province":"Cambridgeshire",
    "sg:tags":[
        "kilt",
        "accessory"
    ],
    "wof:name":"House of Tartans Kilt Making Specialists",
    "wof:placetype":"venue"
},
  "geometry": {"coordinates":[-0.245644,52.590023],"type":"Point"}
}