{
  "type": "Feature",
  "properties": {
    "iso:country":"GB",
    "sg:address":"Hurst Knowle, Almondbury",
    "sg:city":"Huddersfield",
    "sg:classifiers":[
        {
            "category":"Bars & Pubs",
            "type":"Food & Drink"
        }
    ],
    "sg:postcode":"HD5 8TQ",
    "sg:province":"West Yorkshire",
    "sg:tags":[
        "pubs",
        "inn"
    ],
    "wof:name":"The Lion Hotel",
    "wof:placetype":"venue"
},
  "geometry": {"coordinates":[-1.7485829592,53.6340827942],"type":"Point"}
}