{
  "type": "Feature",
  "properties": {
    "addr:full":"22a Park Road Cromer Norfolk NR27 0EA",
    "addr:housenumber":"22a",
    "addr:postcode":"nr27 0ea",
    "addr:street":"Park Road",
    "iso:country":"GB",
    "sg:address":"22a Park Road",
    "sg:city":"Cromer",
    "sg:classifiers":[
        {
            "category":"Building & Trades",
            "subcategory":"Construction",
            "type":"Services"
        }
    ],
    "sg:postcode":"NR27 0EA",
    "sg:province":"Norfolk",
    "sg:tags":[
        "decorator",
        "painter"
    ],
    "wof:name":"Platton Daniel M Traditional Architectural Finishe",
    "wof:placetype":"venue"
},
  "geometry": {"coordinates":[1.314554,52.920918],"type":"Point"}
}