{
  "type": "Feature",
  "properties": {
    "addr:full":"207 Clapham Park Road London Greater London SW4 7EX",
    "addr:housenumber":"207",
    "addr:postcode":"sw4 7ex",
    "addr:street":"Clapham Park Road",
    "iso:country":"GB",
    "sg:address":"207 Clapham Park Road",
    "sg:city":"London",
    "sg:classifiers":[
        {
            "category":"Food & Beverages",
            "subcategory":"Bakery",
            "type":"Retail Goods"
        }
    ],
    "sg:phone":"+44 20 7627 3000",
    "sg:postcode":"SW4 7EX",
    "sg:province":"Greater London",
    "sg:tags":[
        "pizza"
    ],
    "wof:name":"T G F Pizza",
    "wof:placetype":"venue"
},
  "geometry": {"coordinates":[-0.13216,51.459648],"type":"Point"}
}