{
  "type": "Feature",
  "properties": {
    "addr:full":"Wood Farm, Newton Road, Hainford Norwich Norfolk NR10 3LY",
    "addr:postcode":"nr10 3ly",
    "addr:street":"Newton Road;Norwich",
    "iso:country":"GB",
    "sg:address":"Wood Farm, Newton Road, Hainford",
    "sg:city":"Norwich",
    "sg:classifiers":[
        {
            "category":"Farming",
            "subcategory":"Farm",
            "type":"Manufacturing & Wholesale Goods"
        }
    ],
    "sg:postcode":"NR10 3LY",
    "sg:province":"Norfolk",
    "sg:tags":[
        "mixed",
        "crop"
    ],
    "wof:name":"M J Williamson",
    "wof:placetype":"venue"
},
  "geometry": {"coordinates":[1.2921799421,52.7189712524],"type":"Point"}
}