{
  "type": "Feature",
  "properties": {
    "addr:full":"50 Academy Street Dumfries Dumfries and Galloway DG1 1BZ",
    "addr:housenumber":"50",
    "addr:postcode":"dg1 1bz",
    "addr:street":"Academy Street",
    "iso:country":"GB",
    "sg:address":"50 Academy Street",
    "sg:city":"Dumfries",
    "sg:classifiers":[
        {
            "category":"Government",
            "subcategory":"Police Station",
            "type":"Public Place"
        }
    ],
    "sg:phone":"+44 1387 263622",
    "sg:postcode":"DG1 1BZ",
    "sg:province":"Dumfries and Galloway",
    "sg:tags":[
        "officer",
        "sheriff"
    ],
    "wof:name":"J & M M Booth",
    "wof:placetype":"venue"
},
  "geometry": {"coordinates":[-3.610442,55.071651],"type":"Point"}
}