{
  "type": "Feature",
  "properties": {
    "addr:full":"5 Hendham Road London Greater London SW17 7DH",
    "addr:housenumber":"5",
    "addr:postcode":"sw17 7dh",
    "addr:street":"Hendham Road",
    "iso:country":"GB",
    "sg:address":"5 Hendham Road",
    "sg:city":"London",
    "sg:classifiers":[
        {
            "category":"Building & Trades",
            "subcategory":"Landscaping Services",
            "type":"Services"
        }
    ],
    "sg:phone":"+44 20 8672 4134",
    "sg:postcode":"SW17 7DH",
    "sg:province":"Greater London",
    "sg:tags":[
        "landscape",
        "contractor"
    ],
    "wof:name":"Christopher Bellow Garden Design & Care Ltd.",
    "wof:placetype":"venue"
},
  "geometry": {"coordinates":[-0.1679939926,51.439250946],"type":"Point"}
}