{
  "type": "Feature",
  "properties": {
    "iso:country":"GB",
    "sg:address":"49 Wanstead Park Rd",
    "sg:city":"Ilford",
    "sg:classifiers":[
        {
            "category":"Wholesale",
            "subcategory":"Scrap",
            "type":"Manufacturing & Wholesale Goods"
        }
    ],
    "sg:phone":"+44 20 8478 3323",
    "sg:postcode":"IG1 3TQ",
    "sg:province":"Essex",
    "sg:tags":[
        "car",
        "breaker",
        "dismantlers"
    ],
    "wof:name":"I & K Spares",
    "wof:placetype":"venue"
},
  "geometry": {"coordinates":[0.061356999,51.5602035522],"type":"Point"}
}