{
  "type": "Feature",
  "properties": {
    "iso:country":"GB",
    "sg:address":"Reighton House Farm, Church Hill",
    "sg:city":"Filey",
    "sg:classifiers":[
        {
            "category":"Farming",
            "subcategory":"Livestock Farm",
            "type":"Manufacturing & Wholesale Goods"
        }
    ],
    "sg:postcode":"YO14 9RX",
    "sg:province":"North Yorkshire",
    "sg:tags":[
        "others"
    ],
    "wof:name":"Norman Marshall & Sons",
    "wof:placetype":"venue"
},
  "geometry": {"coordinates":[-0.2907490134,54.2118453979],"type":"Point"}
}