{
  "type": "Feature",
  "properties": {
    "addr:full":"Yeovil Road Crewkerne Dorset TA18 7NS",
    "addr:postcode":"ta18 7ns",
    "addr:street":"Yeovil Road",
    "iso:country":"GB",
    "sg:address":"Yeovil Road",
    "sg:city":"Crewkerne",
    "sg:classifiers":[
        {
            "category":"Manufacturing",
            "subcategory":"Lumber",
            "type":"Manufacturing & Wholesale Goods"
        }
    ],
    "sg:phone":"+44 1460 73201",
    "sg:postcode":"TA18 7NS",
    "sg:province":"Dorset",
    "sg:tags":[
        "importer",
        "merchants",
        "agent",
        "timber"
    ],
    "wof:name":"Somerset Lumber Mill",
    "wof:placetype":"venue"
},
  "geometry": {"coordinates":[-2.7742640972,50.8927841187],"type":"Point"}
}