{
  "type": "Feature",
  "properties": {
    "addr:full":"58 Bankhouse Road Bury Lancashire BL8 1DS",
    "addr:housenumber":"58",
    "addr:postcode":"bl8 1ds",
    "addr:street":"Bankhouse Road",
    "iso:country":"GB",
    "sg:address":"58 Bankhouse Road",
    "sg:city":"Bury",
    "sg:classifiers":[
        {
            "category":"Building & Trades",
            "subcategory":"Construction",
            "type":"Services"
        }
    ],
    "sg:phone":"+44 161 761 3550",
    "sg:postcode":"BL8 1DS",
    "sg:province":"Lancashire",
    "sg:tags":[
        "contractor",
        "paving",
        "driveway"
    ],
    "wof:name":"Heritage by Design",
    "wof:placetype":"venue"
},
  "geometry": {"coordinates":[-2.3153550625,53.6034088135],"type":"Point"}
}