{
  "type": "Feature",
  "properties": {
    "addr:full":"The Common Dewsbury West Yorkshire WF12 0LJ",
    "addr:postcode":"wf12 0lj",
    "addr:street":"The Common",
    "iso:country":"GB",
    "sg:address":"The Common",
    "sg:city":"Dewsbury",
    "sg:classifiers":[
        {
            "category":"Health Services",
            "subcategory":"Clinic",
            "type":"Services"
        }
    ],
    "sg:postcode":"WF12 0LJ",
    "sg:province":"West Yorkshire",
    "sg:tags":[
        "nh"
    ],
    "wof:name":"Thornhill Health Clinic",
    "wof:placetype":"venue"
},
  "geometry": {"coordinates":[-1.620203,53.668972],"type":"Point"}
}