{
  "type": "Feature",
  "properties": {
    "addr:full":"Bakers Cottage, 50 Staploe Huntingdon Bedfordshire PE19 4JA",
    "addr:housenumber":"50",
    "addr:postcode":"pe19 4ja",
    "addr:street":"Staploe",
    "iso:country":"GB",
    "sg:address":"Bakers Cottage, 50 Staploe",
    "sg:city":"Huntingdon",
    "sg:classifiers":[
        {
            "category":"Manufacturing",
            "subcategory":"Furniture",
            "type":"Manufacturing & Wholesale Goods"
        }
    ],
    "sg:phone":"+44 1480 405397",
    "sg:postcode":"PE19 4JA",
    "sg:province":"Bedfordshire",
    "sg:tags":[
        "polishing",
        "french"
    ],
    "wof:name":"MeadowCraft Antique & Pine Workshop",
    "wof:placetype":"venue"
},
  "geometry": {"coordinates":[-0.27204,52.246269],"type":"Point"}
}