{
  "type": "Feature",
  "properties": {
    "addr:full":"Laggon Newtonmore Highland PH20 1AT",
    "addr:postcode":"ph20 1at",
    "iso:country":"GB",
    "sg:address":"Laggon",
    "sg:city":"Newtonmore",
    "sg:classifiers":[
        {
            "category":"Real Estate",
            "subcategory":"Developer",
            "type":"Services"
        }
    ],
    "sg:phone":"+44 1528 544383",
    "sg:postcode":"PH20 1AT",
    "sg:province":"Highland",
    "sg:tags":[
        "property"
    ],
    "wof:name":"Lagon Forestry Initiative",
    "wof:placetype":"venue"
},
  "geometry": {"coordinates":[-4.1192,57.065556],"type":"Point"}
}