{
  "type": "Feature",
  "properties": {
    "iso:country":"GB",
    "sg:address":"82-86 Fowler Street",
    "sg:city":"South Shields",
    "sg:classifiers":[
        {
            "category":"Home & Garden",
            "subcategory":"Hardware",
            "type":"Retail Goods"
        }
    ],
    "sg:phone":"+44 191 455 4826",
    "sg:postcode":"NE33 1PF",
    "sg:province":"Tyne and Wear",
    "wof:name":"Frank Lake & Sons Ltd.",
    "wof:placetype":"venue"
},
  "geometry": {"coordinates":[-1.430725,54.996456],"type":"Point"}
}