{
  "type": "Feature",
  "properties": {
    "addr:full":"St Peters Avenue Cleethorpes Lincolnshire DN35 8HQ",
    "addr:postcode":"dn35 8hq",
    "addr:street":"St Peters Avenue",
    "iso:country":"GB",
    "sg:address":"St Peters Avenue",
    "sg:city":"Cleethorpes",
    "sg:classifiers":[
        {
            "category":"Professional",
            "subcategory":"Art Services",
            "type":"Services"
        }
    ],
    "sg:postcode":"DN35 8HQ",
    "sg:province":"Lincolnshire",
    "sg:tags":[
        "photographer"
    ],
    "wof:name":"S G Davis",
    "wof:placetype":"venue"
},
  "geometry": {"coordinates":[-0.0324640013,53.5601539612],"type":"Point"}
}