{
  "type": "Feature",
  "properties": {
    "iso:country":"GB",
    "sg:address":"Fliskmillan Cotts, Newburgh",
    "sg:city":"Cupar",
    "sg:classifiers":[
        {
            "category":"Manufacturing",
            "subcategory":"Wood Products",
            "type":"Manufacturing & Wholesale Goods"
        }
    ],
    "sg:phone":"+44 1337 870209",
    "sg:postcode":"KY14 6HN",
    "sg:province":"Fife",
    "sg:tags":[
        "packaging",
        "crate",
        "pallets"
    ],
    "wof:name":"Boxright",
    "wof:placetype":"venue"
},
  "geometry": {"coordinates":[-3.2417840958,56.3507232666],"type":"Point"}
}