{
  "type": "Feature",
  "properties": {
    "addr:full":"1-3 Springkerse Retail Park, Off Murton Road Stirling Falkirk FK7 7TL",
    "addr:housenumber":"1-3",
    "addr:postcode":"fk7 7tl",
    "addr:street":"Springkerse Retail Park Off Murton Road",
    "iso:country":"GB",
    "sg:address":"1-3 Springkerse Retail Park, Off Murton Road",
    "sg:city":"Stirling",
    "sg:classifiers":[
        {
            "category":"Home & Garden",
            "subcategory":"Hardware",
            "type":"Retail Goods"
        }
    ],
    "sg:phone":"+44 1786 449559",
    "sg:postcode":"FK7 7TL",
    "sg:province":"Falkirk",
    "sg:tags":[
        "retailer",
        "diy"
    ],
    "wof:name":"B & Q Diy Supercentre",
    "wof:placetype":"venue"
},
  "geometry": {"coordinates":[-3.9204568863,56.113986969],"type":"Point"}
}