{
  "type": "Feature",
  "properties": {
    "addr:full":"12 Cefn Road, Old Colwyn Colwyn Bay Conwy LL29 9PN",
    "addr:housenumber":"12",
    "addr:postcode":"ll29 9pn",
    "addr:street":"Cefn Road",
    "iso:country":"GB",
    "sg:address":"12 Cefn Road, Old Colwyn",
    "sg:city":"Colwyn Bay",
    "sg:classifiers":[
        {
            "category":"Personal",
            "subcategory":"Beauty Salon",
            "type":"Services"
        },
        {
            "category":"Personal",
            "subcategory":"Barber",
            "type":"Services"
        }
    ],
    "sg:phone":"+44 1492 515130",
    "sg:postcode":"LL29 9PN",
    "sg:province":"Conwy",
    "sg:tags":[
        "unisex",
        "hairdresser"
    ],
    "wof:name":"Caprice Hairstylist",
    "wof:placetype":"venue"
},
  "geometry": {"coordinates":[-3.6983718872,53.289642334],"type":"Point"}
}