{
  "type": "Feature",
  "properties": {
    "iso:country":"GB",
    "sg:address":"53 Hindle St",
    "sg:city":"Darwen",
    "sg:classifiers":[
        {
            "category":"Building & Trades",
            "subcategory":"Construction",
            "type":"Services"
        }
    ],
    "sg:postcode":"BB3 1NF",
    "sg:province":"Lancashire",
    "sg:tags":[
        "roofing"
    ],
    "wof:name":"D Parker",
    "wof:placetype":"venue"
},
  "geometry": {"coordinates":[-2.475276,53.699207],"type":"Point"}
}