{
  "type": "Feature",
  "properties": {
    "iso:country":"GB",
    "sg:address":"17 Broomhouse St North",
    "sg:city":"Edinburgh",
    "sg:classifiers":[
        {
            "category":"Building & Trades",
            "subcategory":"Construction",
            "type":"Services"
        }
    ],
    "sg:phone":"+44 131 444 1020",
    "sg:postcode":"EH11 3RR",
    "sg:province":"City of Edinburgh",
    "sg:tags":[
        "roofing"
    ],
    "wof:name":"John Reid",
    "wof:placetype":"venue"
},
  "geometry": {"coordinates":[-3.2768099308,55.9263458252],"type":"Point"}
}