{
  "type": "Feature",
  "properties": {
    "addr:full":"The Mount, Paris Street Exeter Devon EX1 2JZ",
    "addr:postcode":"ex1 2jz",
    "addr:street":"The Mount Paris Street",
    "iso:country":"GB",
    "sg:address":"The Mount, Paris Street",
    "sg:city":"Exeter",
    "sg:classifiers":[
        {
            "category":"Organizations",
            "subcategory":"Community Association",
            "type":"Services"
        }
    ],
    "sg:phone":"+44 1392 252566",
    "sg:postcode":"EX1 2JZ",
    "sg:province":"Devon",
    "sg:tags":[
        "co-operatives",
        "society",
        "housing",
        "trust"
    ],
    "sg:website":"http://www.dcha.co.uk",
    "wof:name":"Devon & Cornwall Housing Association Ltd.",
    "wof:placetype":"venue"
},
  "geometry": {"coordinates":[-3.531644,50.719906],"type":"Point"}
}