{
  "type": "Feature",
  "properties": {
    "iso:country":"GB",
    "sg:address":"Barling Road, Barling Magna",
    "sg:city":"Southend-on-sea",
    "sg:classifiers":[
        {
            "category":"Shopping",
            "subcategory":"Luggage & Leather Goods",
            "type":"Retail Goods"
        }
    ],
    "sg:phone":"+44 1702 216222",
    "sg:postcode":"SS3 0LZ",
    "sg:province":"Essex",
    "wof:name":"Logicline",
    "wof:placetype":"venue"
},
  "geometry": {"coordinates":[0.75837,51.554592],"type":"Point"}
}