{
  "type": "Feature",
  "properties": {
    "iso:country":"GB",
    "sg:address":"2152 Coventry Road, Sheldon",
    "sg:city":"Birmingham",
    "sg:classifiers":[
        {
            "category":"Organizations",
            "subcategory":"Non-profit Organization",
            "type":"Services"
        }
    ],
    "sg:phone":"+44 121 722 2550",
    "sg:postcode":"B26 3JB",
    "sg:province":"West Midlands",
    "sg:tags":[
        "organisation",
        "voluntary",
        "charity"
    ],
    "wof:name":"Barnardo's",
    "wof:placetype":"venue"
},
  "geometry": {"coordinates":[-1.785028,52.452667],"type":"Point"}
}