{
  "type": "Feature",
  "properties": {
    "addr:full":"Greylands, Laurels Road, Offenham Evesham Gloucestershire WR11 8RE",
    "addr:postcode":"wr11 8re",
    "addr:street":"Laurels Road",
    "iso:country":"GB",
    "sg:address":"Greylands, Laurels Road, Offenham",
    "sg:city":"Evesham",
    "sg:phone":"+44 1386 421422",
    "sg:postcode":"WR11 8RE",
    "sg:province":"Gloucestershire",
    "wof:name":"Greyland Plastics Ltd.",
    "wof:placetype":"venue"
},
  "geometry": {"coordinates":[-1.9213459492,52.1116752625],"type":"Point"}
}