{
  "type": "Feature",
  "properties": {
    "addr:full":"38 Shrewsbury Road Worksop Nottinghamshire S80 2PA",
    "addr:housenumber":"38",
    "addr:postcode":"s80 2pa",
    "addr:street":"Shrewsbury Road",
    "iso:country":"GB",
    "sg:address":"38 Shrewsbury Road",
    "sg:city":"Worksop",
    "sg:classifiers":[
        {
            "category":"Bars & Pubs",
            "type":"Food & Drink"
        }
    ],
    "sg:postcode":"S80 2PA",
    "sg:province":"Nottinghamshire",
    "sg:tags":[
        "pubs",
        "inn"
    ],
    "wof:name":"Forresters Arms",
    "wof:placetype":"venue"
},
  "geometry": {"coordinates":[-1.1071610451,53.3000717163],"type":"Point"}
}