{
  "type": "Feature",
  "properties": {
    "iso:country":"GB",
    "sg:address":"22 Castle Street",
    "sg:city":"Macclesfield",
    "sg:classifiers":[
        {
            "category":"Shopping",
            "subcategory":"Stationery & Office Supplies",
            "type":"Retail Goods"
        }
    ],
    "sg:phone":"+44 1625 503262",
    "sg:postcode":"SK11 6AF",
    "sg:province":"Cheshire",
    "wof:name":"Stationery Box Ltd.",
    "wof:placetype":"venue"
},
  "geometry": {"coordinates":[-2.127684,53.259705],"type":"Point"}
}