{
  "type": "Feature",
  "properties": {
    "addr:full":"Ashcombe Ho, Queen St Godalming Surrey GU7 1BB",
    "addr:postcode":"gu7 1bb",
    "addr:street":"Queen St",
    "iso:country":"GB",
    "sg:address":"Ashcombe Ho, Queen St",
    "sg:city":"Godalming",
    "sg:classifiers":[
        {
            "category":"Home & Garden",
            "subcategory":"Home Furnishings",
            "type":"Retail Goods"
        }
    ],
    "sg:postcode":"GU7 1BB",
    "sg:province":"Surrey",
    "sg:tags":[
        "homefurnishings"
    ],
    "wof:name":"Brydon,Alexander,Ltd",
    "wof:placetype":"venue"
},
  "geometry": {"coordinates":[-0.6183840036,51.1839561462],"type":"Point"}
}