{
  "type": "Feature",
  "properties": {
    "addr:full":"Parndon Wood Road Harlow Essex CM19 4SF",
    "addr:postcode":"cm19 4sf",
    "addr:street":"Parndon Wood Road",
    "iso:country":"GB",
    "sg:address":"Parndon Wood Road",
    "sg:city":"Harlow",
    "sg:classifiers":[
        {
            "category":"Government",
            "subcategory":"Office",
            "type":"Public Place"
        },
        {
            "category":"Retail",
            "subcategory":"Funeral Services",
            "type":"Services"
        },
        {
            "category":"Landmark",
            "subcategory":"Tourist Attraction",
            "type":"Public Place"
        }
    ],
    "sg:phone":"+44 1279 430005",
    "sg:postcode":"CM19 4SF",
    "sg:province":"Essex",
    "sg:tags":[
        "local",
        "cemetery",
        "interest",
        "crematorium"
    ],
    "wof:name":"Parndon Wood Nature Reserve",
    "wof:placetype":"venue"
},
  "geometry": {"coordinates":[0.0867770016,51.7460403442],"type":"Point"}
}