{
  "type": "Feature",
  "properties": {
    "addr:full":"372-374 Harlaxton Road Grantham Lincolnshire NG31 7JX",
    "addr:postcode":"372-374;ng31 7jx",
    "addr:street":"Harlaxton Road",
    "iso:country":"GB",
    "sg:address":"372-374 Harlaxton Road",
    "sg:city":"Grantham",
    "sg:classifiers":[
        {
            "category":"Autos & Motor Vehicles",
            "subcategory":"Automobile Sales",
            "type":"Retail Goods"
        }
    ],
    "sg:phone":"+44 1476 565009",
    "sg:postcode":"NG31 7JX",
    "sg:province":"Lincolnshire",
    "sg:tags":[
        "car",
        "commercial"
    ],
    "wof:name":"H R S S",
    "wof:placetype":"venue"
},
  "geometry": {"coordinates":[-0.662417,52.898106],"type":"Point"}
}