{
  "type": "Feature",
  "properties": {
    "addr:full":"Fishponds House, Dunkeswell Honiton Devon EX14 4SH",
    "addr:postcode":"ex14 4sh",
    "iso:country":"GB",
    "sg:address":"Fishponds House, Dunkeswell",
    "sg:city":"Honiton",
    "sg:classifiers":[
        {
            "category":"Home & Garden",
            "subcategory":"Kitchen Supply",
            "type":"Retail Goods"
        }
    ],
    "sg:postcode":"EX14 4SH",
    "sg:province":"Devon",
    "sg:tags":[
        "equipment",
        "bakery"
    ],
    "wof:name":"Beachman Ltd",
    "wof:placetype":"venue"
},
  "geometry": {"coordinates":[-3.195659,50.847591],"type":"Point"}
}