{
  "type": "Feature",
  "properties": {
    "addr:full":"16 Kinrossie Terrace Dundee Dundee City DD3 9RL",
    "addr:housenumber":"16",
    "addr:postcode":"dd3 9rl",
    "addr:street":"Kinrossie Terrace",
    "iso:country":"GB",
    "sg:address":"16 Kinrossie Terrace",
    "sg:city":"Dundee",
    "sg:classifiers":[
        {
            "category":"Professional",
            "subcategory":"Art Services",
            "type":"Services"
        }
    ],
    "sg:postcode":"DD3 9RL",
    "sg:province":"Dundee City",
    "sg:tags":[
        "photographer"
    ],
    "wof:name":"Commercial Photographer",
    "wof:placetype":"venue"
},
  "geometry": {"coordinates":[-3.00675,56.498638],"type":"Point"}
}