{
  "type": "Feature",
  "properties": {
    "addr:full":"52 Musgrave View Leeds West Yorkshire LS13 2QN",
    "addr:housenumber":"52",
    "addr:postcode":"ls13 2qn",
    "addr:street":"Musgrave View",
    "iso:country":"GB",
    "sg:address":"52 Musgrave View",
    "sg:city":"Leeds",
    "sg:classifiers":[
        {
            "category":"Building & Trades",
            "subcategory":"Construction",
            "type":"Services"
        }
    ],
    "sg:phone":"+44 113 275 7767",
    "sg:postcode":"LS13 2QN",
    "sg:province":"West Yorkshire",
    "sg:tags":[
        "joiner",
        "carpenter"
    ],
    "wof:name":"M.B. Joinery",
    "wof:placetype":"venue"
},
  "geometry": {"coordinates":[-1.615191,53.809887],"type":"Point"}
}