{
  "type": "Feature",
  "properties": {
    "addr:full":"14 The Pavement Clapham Greater London SW4 0HY",
    "addr:housenumber":"14",
    "addr:postcode":"sw4 0hy",
    "addr:street":"The Pavement",
    "iso:country":"GB",
    "sg:address":"14 The Pavement",
    "sg:city":"Clapham",
    "sg:classifiers":[
        {
            "category":"Food & Beverages",
            "subcategory":"Groceries & Convenience Stores",
            "type":"Retail Goods"
        }
    ],
    "sg:phone":"+44 20 7498 7537",
    "sg:postcode":"SW4 0HY",
    "sg:province":"Greater London",
    "wof:name":"Portland Food & Wine",
    "wof:placetype":"venue"
},
  "geometry": {"coordinates":[-0.1394380033,51.4618453979],"type":"Point"}
}