{
  "type": "Feature",
  "properties": {
    "addr:full":"Glass & Glazing Div, 26 Orwell Terrace Edinburgh City of Edinburgh EH11 2ET",
    "addr:housenumber":"26",
    "addr:postcode":"eh11 2et",
    "addr:street":"Orwell Terrace",
    "iso:country":"GB",
    "sg:address":"Glass & Glazing Div, 26 Orwell Terrace",
    "sg:city":"Edinburgh",
    "sg:classifiers":[
        {
            "category":"Manufacturing",
            "subcategory":"Metals",
            "type":"Manufacturing & Wholesale Goods"
        }
    ],
    "sg:phone":"+44 1224 634257",
    "sg:postcode":"EH11 2ET",
    "sg:province":"City of Edinburgh",
    "sg:tags":[
        "fabricator",
        "aluminium"
    ],
    "wof:name":"Solaglas Ltd.",
    "wof:placetype":"venue"
},
  "geometry": {"coordinates":[-3.2205901146,55.9420394897],"type":"Point"}
}