{
  "type": "Feature",
  "properties": {
    "iso:country":"GB",
    "sg:address":"57 Crossgate Centre",
    "sg:city":"Leeds",
    "sg:classifiers":[
        {
            "category":"Home & Garden",
            "subcategory":"Home Furnishings",
            "type":"Retail Goods"
        }
    ],
    "sg:phone":"+44 113 264 4834",
    "sg:postcode":"LS15 8EU",
    "sg:province":"West Yorkshire",
    "sg:tags":[
        "blind",
        "curtain",
        "fitting"
    ],
    "wof:name":"Curtain Flair",
    "wof:placetype":"venue"
},
  "geometry": {"coordinates":[-1.448844,53.802238],"type":"Point"}
}