{
  "type": "Feature",
  "properties": {
    "addr:full":"Nuneaton Rd, Mancetter Atherstone Leicestershire CV9 1NW",
    "addr:postcode":"cv9 1nw",
    "addr:street":"Nuneaton Rd",
    "iso:country":"GB",
    "sg:address":"Nuneaton Rd, Mancetter",
    "sg:city":"Atherstone",
    "sg:classifiers":[
        {
            "category":"Professional",
            "subcategory":"Management & Consulting",
            "type":"Services"
        }
    ],
    "sg:postcode":"CV9 1NW",
    "sg:province":"Leicestershire",
    "sg:tags":[
        "consultant",
        "transport"
    ],
    "wof:name":"Midland Fleet Management Ltd",
    "wof:placetype":"venue"
},
  "geometry": {"coordinates":[-1.5178890228,52.5605125427],"type":"Point"}
}