{
  "type": "Feature",
  "properties": {
    "iso:country":"GB",
    "sg:address":"Cuckfield Ho, High St, Cuckfield",
    "sg:city":"Haywards Heath",
    "sg:classifiers":[
        {
            "category":"Professional",
            "subcategory":"Testing Lab",
            "type":"Services"
        },
        {
            "category":"Professional",
            "subcategory":"Business Services",
            "type":"Services"
        }
    ],
    "sg:phone":"+44 1444 472901",
    "sg:postcode":"RH17 5EL",
    "sg:province":"East Sussex",
    "sg:tags":[
        "inspection",
        "assessment",
        "quality",
        "calibration"
    ],
    "wof:name":"Moody International Ltd",
    "wof:placetype":"venue"
},
  "geometry": {"coordinates":[-0.165884003,50.9812850952],"type":"Point"}
}