{
  "type": "Feature",
  "properties": {
    "addr:full":"The Ives, Clay Lane, Jacobs Well Guildford Surrey GU4 7NZ",
    "addr:postcode":"gu4 7nz",
    "addr:street":"Clay Lane",
    "iso:country":"GB",
    "sg:address":"The Ives, Clay Lane, Jacobs Well",
    "sg:city":"Guildford",
    "sg:classifiers":[
        {
            "category":"Personal",
            "subcategory":"Beauty Salon",
            "type":"Services"
        }
    ],
    "sg:postcode":"GU4 7NZ",
    "sg:province":"Surrey",
    "sg:tags":[
        "unisex",
        "hairdresser"
    ],
    "wof:name":"Jane Ingram Studio",
    "wof:placetype":"venue"
},
  "geometry": {"coordinates":[-0.5751050115,51.265953064],"type":"Point"}
}