{
  "type": "Feature",
  "properties": {
    "addr:full":"Moors Farm, Bourton-on-the-waterfarm Cheltenham Gloucestershire GL54 2HA",
    "addr:postcode":"gl54 2ha",
    "addr:street":"Bourton-On-The-Waterfarm",
    "iso:country":"GB",
    "sg:address":"Moors Farm, Bourton-on-the-waterfarm",
    "sg:city":"Cheltenham",
    "sg:classifiers":[
        {
            "category":"Professional",
            "type":"Services"
        },
        {
            "category":"Banks & Credit Unions",
            "subcategory":"Investment Brokerage",
            "type":"Services"
        }
    ],
    "sg:phone":"+44 1451 821292",
    "sg:postcode":"GL54 2HA",
    "sg:province":"Gloucestershire",
    "sg:tags":[
        "farm",
        "agricultural",
        "contractor"
    ],
    "wof:name":"Agrihire",
    "wof:placetype":"venue"
},
  "geometry": {"coordinates":[-1.7609159946,51.8867797852],"type":"Point"}
}