{
  "type": "Feature",
  "properties": {
    "iso:country":"GB",
    "sg:address":"203 Main Street, Rutherglen",
    "sg:city":"Glasgow",
    "sg:classifiers":[
        {
            "category":"Banks & Credit Unions",
            "subcategory":"Bank",
            "type":"Services"
        }
    ],
    "sg:phone":"+44 141 951 7119",
    "sg:postcode":"G73 2HG",
    "sg:province":"Glasgow City",
    "wof:name":"Clydesdale Bank Plc",
    "wof:placetype":"venue"
},
  "geometry": {"coordinates":[-4.2117562294,55.8286247253],"type":"Point"}
}