{
  "type": "Feature",
  "properties": {
    "addr:full":"Greenhill Sherborne Dorset DT9 4EW",
    "addr:postcode":"dt9 4ew",
    "addr:street":"Greenhill",
    "iso:country":"GB",
    "sg:address":"Greenhill",
    "sg:city":"Sherborne",
    "sg:classifiers":[
        {
            "category":"Professional",
            "subcategory":"Business Services",
            "type":"Services"
        }
    ],
    "sg:postcode":"DT9 4EW",
    "sg:province":"Dorset",
    "sg:tags":[
        "bookmaker"
    ],
    "wof:name":"Sherborne Turf Accountants",
    "wof:placetype":"venue"
},
  "geometry": {"coordinates":[-2.5193378925,50.9502944946],"type":"Point"}
}