{
  "type": "Feature",
  "properties": {
    "iso:country":"GB",
    "sg:address":"2-12 New Cleveland Street",
    "sg:city":"Hull",
    "sg:classifiers":[
        {
            "category":"Professional",
            "subcategory":"Engineering",
            "type":"Services"
        }
    ],
    "sg:phone":"+44 1482 323606",
    "sg:postcode":"HU8 7ER",
    "sg:province":"East Riding of Yorkshire",
    "sg:tags":[
        "contractor",
        "electrical",
        "engineer"
    ],
    "wof:name":"Pete Galloway Electronic Services",
    "wof:placetype":"venue"
},
  "geometry": {"coordinates":[-0.32816,53.748276],"type":"Point"}
}