{
  "type": "Feature",
  "properties": {
    "addr:full":"6 Woodcroft Avenue Stanmore Greater London HA7 3PS",
    "addr:housenumber":"6",
    "addr:postcode":"ha7 3ps",
    "addr:street":"Woodcroft Avenue",
    "iso:country":"GB",
    "sg:address":"6 Woodcroft Avenue",
    "sg:city":"Stanmore",
    "sg:classifiers":[
        {
            "category":"Professional",
            "subcategory":"Engineering",
            "type":"Services"
        }
    ],
    "sg:phone":"+44 20 8954 5619",
    "sg:postcode":"HA7 3PS",
    "sg:province":"Greater London",
    "sg:tags":[
        "contractor",
        "electrical",
        "engineer"
    ],
    "wof:name":"J E H Electrical",
    "wof:placetype":"venue"
},
  "geometry": {"coordinates":[-0.3255339861,51.6052703857],"type":"Point"}
}