{
  "type": "Feature",
  "properties": {
    "iso:country":"GB",
    "sg:address":"27 High St",
    "sg:city":"Fishguard",
    "sg:classifiers":[
        {
            "category":"Taxi",
            "type":"Transportation"
        }
    ],
    "sg:phone":"+44 1348 873774",
    "sg:postcode":"SA65 9AW",
    "sg:province":"Pembrokeshire",
    "sg:tags":[
        "mini",
        "cab"
    ],
    "wof:name":"A.P. Taxis",
    "wof:placetype":"venue"
},
  "geometry": {"coordinates":[-4.977842,51.99284],"type":"Point"}
}