{
  "type": "Feature",
  "properties": {
    "addr:full":"200 London Rd Sheffield South Yorkshire S2 4LN",
    "addr:housenumber":"200",
    "addr:postcode":"s2 4ln",
    "addr:street":"London Rd",
    "iso:country":"GB",
    "sg:address":"200 London Rd",
    "sg:city":"Sheffield",
    "sg:classifiers":[
        {
            "category":"Shopping",
            "subcategory":"Pets & Pet Supplies",
            "type":"Retail Goods"
        }
    ],
    "sg:phone":"+44 114 255 7915",
    "sg:postcode":"S2 4LN",
    "sg:province":"South Yorkshire",
    "wof:name":"London Road Pet Supplies",
    "wof:placetype":"venue"
},
  "geometry": {"coordinates":[-1.4760620594,53.3684158325],"type":"Point"}
}