{
  "type": "Feature",
  "properties": {
    "addr:full":"Hazel Bank Farm, Snaith Road, Rawcliffe Goole East Riding of Yorkshire DN14 8NA",
    "addr:postcode":"dn14 8na",
    "addr:street":"Snaith Road",
    "iso:country":"GB",
    "sg:address":"Hazel Bank Farm, Snaith Road, Rawcliffe",
    "sg:city":"Goole",
    "sg:classifiers":[
        {
            "category":"Farming",
            "subcategory":"Farm",
            "type":"Manufacturing & Wholesale Goods"
        }
    ],
    "sg:phone":"+44 1405 839228",
    "sg:postcode":"DN14 8NA",
    "sg:province":"East Riding of Yorkshire",
    "sg:tags":[
        "mixed",
        "crop"
    ],
    "wof:name":"J E & C Lewis",
    "wof:placetype":"venue"
},
  "geometry": {"coordinates":[-0.9627460241,53.6993980408],"type":"Point"}
}