{
  "type": "Feature",
  "properties": {
    "iso:country":"GB",
    "sg:address":"Bootham Lane Industrial Estate, Bootham Lane, Dunscroft",
    "sg:city":"Doncaster",
    "sg:classifiers":[
        {
            "category":"Freight",
            "type":"Transportation"
        }
    ],
    "sg:phone":"+44 1302 351378",
    "sg:postcode":"DN7 4JU",
    "sg:province":"South Yorkshire",
    "sg:tags":[
        "haulage",
        "road"
    ],
    "wof:name":"Perthdown Ltd.",
    "wof:placetype":"venue"
},
  "geometry": {"coordinates":[-1.011509,53.582443],"type":"Point"}
}