{
  "type": "Feature",
  "properties": {
    "iso:country":"GB",
    "sg:address":"Sco Ruston Hall, Sco Ruston",
    "sg:city":"Norwich",
    "sg:classifiers":[
        {
            "category":"Farming",
            "subcategory":"Livestock Farm",
            "type":"Manufacturing & Wholesale Goods"
        }
    ],
    "sg:phone":"+44 1603 737218",
    "sg:postcode":"NR12 8EY",
    "sg:province":"Norfolk",
    "sg:tags":[
        "others"
    ],
    "wof:name":"Gavin Alston",
    "wof:placetype":"venue"
},
  "geometry": {"coordinates":[1.381715,52.748581],"type":"Point"}
}