{
  "type": "Feature",
  "properties": {
    "iso:country":"GB",
    "sg:address":"2 Manor Drive, Royton",
    "sg:city":"Oldham",
    "sg:classifiers":[
        {
            "category":"Building & Trades",
            "subcategory":"Construction",
            "type":"Services"
        }
    ],
    "sg:postcode":"OL2 6EZ",
    "sg:province":"Lancashire",
    "sg:tags":[
        "dry",
        "lining",
        "plasterers",
        "screeders"
    ],
    "wof:name":"Hall & Harland",
    "wof:placetype":"venue"
},
  "geometry": {"coordinates":[-2.1175351143,53.5621261597],"type":"Point"}
}