{
  "type": "Feature",
  "properties": {
    "addr:full":"The Old Shop, Hook Swindon Wiltshire SN4 8EA",
    "addr:postcode":"sn4 8ea",
    "iso:country":"GB",
    "sg:address":"The Old Shop, Hook",
    "sg:city":"Swindon",
    "sg:classifiers":[
        {
            "category":"Building & Trades",
            "subcategory":"Construction",
            "type":"Services"
        }
    ],
    "sg:postcode":"SN4 8EA",
    "sg:province":"Wiltshire",
    "sg:tags":[
        "roofing"
    ],
    "wof:name":"K J & L Cottrell",
    "wof:placetype":"venue"
},
  "geometry": {"coordinates":[-1.889253974,51.5612945557],"type":"Point"}
}