{
  "type": "Feature",
  "properties": {
    "addr:full":"Southwell Park Road Camberley Berkshire GU15 3QQ",
    "addr:postcode":"gu15 3qq",
    "addr:street":"Park Road",
    "iso:country":"GB",
    "sg:address":"Southwell Park Road",
    "sg:city":"Camberley",
    "sg:classifiers":[
        {
            "category":"Arena",
            "subcategory":"Sports Club",
            "type":"Entertainment"
        }
    ],
    "sg:phone":"+44 1276 691012",
    "sg:postcode":"GU15 3QQ",
    "sg:province":"Berkshire",
    "wof:name":"Camberley Bowling Club",
    "wof:placetype":"venue"
},
  "geometry": {"coordinates":[-0.749669,51.335831],"type":"Point"}
}