{
  "type": "Feature",
  "properties": {
    "iso:country":"GB",
    "sg:address":"74b Station Lane",
    "sg:city":"Hornchurch",
    "sg:classifiers":[
        {
            "category":"Organizations",
            "subcategory":"Non-profit Organization",
            "type":"Services"
        }
    ],
    "sg:phone":"+44 1708 451000",
    "sg:postcode":"RM12 6NA",
    "sg:province":"Essex",
    "sg:tags":[
        "organisation",
        "voluntary",
        "charity"
    ],
    "wof:name":"Havering Victim Support Scheme",
    "wof:placetype":"venue"
},
  "geometry": {"coordinates":[0.2203,51.559219],"type":"Point"}
}