{
  "type": "Feature",
  "properties": {
    "addr:full":"96 Townfoot, Dreghorn Irvine East Ayrshire KA11 4EZ",
    "addr:housenumber":"96",
    "addr:postcode":"ka11 4ez",
    "addr:street":"Townfoot Dreghorn",
    "iso:country":"GB",
    "sg:address":"96 Townfoot, Dreghorn",
    "sg:city":"Irvine",
    "sg:classifiers":[
        {
            "category":"Food & Beverages",
            "subcategory":"Groceries & Convenience Stores",
            "type":"Retail Goods"
        }
    ],
    "sg:phone":"+44 1294 222300",
    "sg:postcode":"KA11 4EZ",
    "sg:province":"East Ayrshire",
    "wof:name":"Alldays",
    "wof:placetype":"venue"
},
  "geometry": {"coordinates":[-4.627049,55.607281],"type":"Point"}
}