{
  "type": "Feature",
  "properties": {
    "addr:full":"6 High St, Swaffham Prior Cambridge Cambridgeshire CB5 0LD",
    "addr:housenumber":"6",
    "addr:postcode":"cb5 0ld",
    "addr:street":"High St",
    "iso:country":"GB",
    "sg:address":"6 High St, Swaffham Prior",
    "sg:city":"Cambridge",
    "sg:classifiers":[
        {
            "category":"Professional",
            "subcategory":"Management & Consulting",
            "type":"Services"
        }
    ],
    "sg:phone":"+44 1638 742224",
    "sg:postcode":"CB5 0LD",
    "sg:province":"Cambridgeshire",
    "sg:tags":[
        "consultant",
        "business"
    ],
    "wof:name":"Morton Hodson Management Consultants",
    "wof:placetype":"venue"
},
  "geometry": {"coordinates":[0.3295120001,52.2683067322],"type":"Point"}
}