{
  "type": "Feature",
  "properties": {
    "iso:country":"GB",
    "sg:address":"164 West Wycombe Rd",
    "sg:city":"High Wycombe",
    "sg:classifiers":[
        {
            "category":"Education",
            "subcategory":"Special Training",
            "type":"Public Place"
        }
    ],
    "sg:phone":"+44 1494 474200",
    "sg:postcode":"HP12 3AE",
    "sg:province":"Buckinghamshire",
    "sg:tags":[
        "product",
        "centre"
    ],
    "wof:name":"Interface Training",
    "wof:placetype":"venue"
},
  "geometry": {"coordinates":[-0.770078,51.636749],"type":"Point"}
}