{
  "type": "Feature",
  "properties": {
    "iso:country":"GB",
    "sg:address":"Po Box 117, Fulwood",
    "sg:city":"Preston",
    "sg:classifiers":[
        {
            "category":"Building & Trades",
            "subcategory":"Plumbing",
            "type":"Services"
        }
    ],
    "sg:phone":"+44 1772 794225",
    "sg:postcode":"PR2 5TE",
    "sg:province":"Lancashire",
    "sg:tags":[
        "central",
        "heating"
    ],
    "wof:name":"George Beesley Domestic Gas Services",
    "wof:placetype":"venue"
},
  "geometry": {"coordinates":[-2.7131800652,53.7900505066],"type":"Point"}
}