{
  "type": "Feature",
  "properties": {
    "addr:full":"Acorn Works, Broad Lane Pudsey West Yorkshire LS28 6PB",
    "addr:postcode":"ls28 6pb",
    "addr:street":"Broad Lane",
    "iso:country":"GB",
    "sg:address":"Acorn Works, Broad Lane",
    "sg:city":"Pudsey",
    "sg:classifiers":[
        {
            "category":"Professional",
            "subcategory":"Printing & Photocopies",
            "type":"Services"
        }
    ],
    "sg:phone":"+44 113 256 4202",
    "sg:postcode":"LS28 6PB",
    "sg:province":"West Yorkshire",
    "sg:tags":[
        "printer"
    ],
    "wof:name":"Nutt & Co Ltd",
    "wof:placetype":"venue"
},
  "geometry": {"coordinates":[-1.656269,53.797684],"type":"Point"}
}