{
  "type": "Feature",
  "properties": {
    "iso:country":"GB",
    "sg:address":"111/115 John Bright St",
    "sg:city":"Birmingham",
    "sg:classifiers":[
        {
            "category":"Home & Garden",
            "subcategory":"Kitchen Supply",
            "type":"Retail Goods"
        }
    ],
    "sg:phone":"+44 121 643 4214",
    "sg:postcode":"B1 1BE",
    "sg:province":"West Midlands",
    "sg:tags":[
        "equipment",
        "catering"
    ],
    "wof:name":"C.N.A Catering Equipment",
    "wof:placetype":"venue"
},
  "geometry": {"coordinates":[-1.9017750025,52.477596283],"type":"Point"}
}