{
  "type": "Feature",
  "properties": {
    "addr:full":"24 Chester Road West, Shotton Deeside Flintshire CH5 1BX",
    "addr:housenumber":"24",
    "addr:postcode":"ch5 1bx",
    "addr:street":"Chester Road West",
    "iso:country":"GB",
    "sg:address":"24 Chester Road West, Shotton",
    "sg:city":"Deeside",
    "sg:classifiers":[
        {
            "category":"Shopping",
            "subcategory":"Clothing, Apparel, & Fashions",
            "type":"Retail Goods"
        }
    ],
    "sg:phone":"+44 1244 821535",
    "sg:postcode":"CH5 1BX",
    "sg:province":"Flintshire",
    "sg:tags":[
        "ladieswear"
    ],
    "wof:name":"Gems",
    "wof:placetype":"venue"
},
  "geometry": {"coordinates":[-3.038754,53.211182],"type":"Point"}
}