{
  "type": "Feature",
  "properties": {
    "addr:full":"178 Portland Road Hove East Sussex BN3 5QN",
    "addr:housenumber":"178",
    "addr:postcode":"bn3 5qn",
    "addr:street":"Portland Road",
    "iso:country":"GB",
    "sg:address":"178 Portland Road",
    "sg:city":"Hove",
    "sg:classifiers":[
        {
            "category":"Banks & Credit Unions",
            "subcategory":"Bank",
            "type":"Services"
        },
        {
            "category":"Banks & Credit Unions",
            "subcategory":"Financial Services",
            "type":"Services"
        }
    ],
    "sg:postcode":"BN3 5QN",
    "sg:province":"East Sussex",
    "sg:tags":[
        "consultant",
        "broker",
        "mortgage"
    ],
    "wof:name":"Dial-A-Mortgage",
    "wof:placetype":"venue"
},
  "geometry": {"coordinates":[-0.1864400059,50.8332977295],"type":"Point"}
}