{
  "type": "Feature",
  "properties": {
    "iso:country":"GB",
    "sg:address":"Remercie Road, Mistley",
    "sg:city":"Manningtree",
    "sg:classifiers":[
        {
            "category":"Education",
            "subcategory":"School",
            "type":"Public Place"
        }
    ],
    "sg:phone":"+44 1206 392675",
    "sg:postcode":"CO11 1LS",
    "sg:province":"Essex",
    "sg:tags":[
        "local",
        "authority"
    ],
    "wof:name":"The Essex Racial Equality Council",
    "wof:placetype":"venue"
},
  "geometry": {"coordinates":[1.0630400181,51.9453811646],"type":"Point"}
}