{
  "type": "Feature",
  "properties": {
    "addr:full":"Bonehill Road Tamworth Staffordshire B78 3HE",
    "addr:postcode":"b78 3he",
    "addr:street":"Bonehill Road",
    "iso:country":"GB",
    "sg:address":"Bonehill Road",
    "sg:city":"Tamworth",
    "sg:classifiers":[
        {
            "category":"Building & Trades",
            "subcategory":"Construction",
            "type":"Services"
        }
    ],
    "sg:phone":"+44 1827 50622",
    "sg:postcode":"B78 3HE",
    "sg:province":"Staffordshire",
    "sg:tags":[
        "builder"
    ],
    "wof:name":"Cover Brothers",
    "wof:placetype":"venue"
},
  "geometry": {"coordinates":[-1.706972,52.629242],"type":"Point"}
}