{
  "type": "Feature",
  "properties": {
    "addr:full":"36 Market Street Abergele Conwy LL22 7AA",
    "addr:housenumber":"36",
    "addr:postcode":"ll22 7aa",
    "addr:street":"Market Street",
    "iso:country":"GB",
    "sg:address":"36 Market Street",
    "sg:city":"Abergele",
    "sg:classifiers":[
        {
            "category":"Travel",
            "subcategory":"Travel Agent",
            "type":"Entertainment"
        }
    ],
    "sg:phone":"+44 1745 822920",
    "sg:postcode":"LL22 7AA",
    "sg:province":"Conwy",
    "wof:name":"Global Vacations Ltd.",
    "wof:placetype":"venue"
},
  "geometry": {"coordinates":[-3.5836849213,53.2846336365],"type":"Point"}
}