{
  "type": "Feature",
  "properties": {
    "addr:full":"Montgomery Way, Rosehill Business Park Carlisle Cumbria CA1 2RW",
    "addr:postcode":"ca1 2rw",
    "addr:street":"Montgomery Way Rosehill Business Park",
    "iso:country":"GB",
    "sg:address":"Montgomery Way, Rosehill Business Park",
    "sg:city":"Carlisle",
    "sg:classifiers":[
        {
            "category":"Banks & Credit Unions",
            "subcategory":"Bank",
            "type":"Services"
        }
    ],
    "sg:phone":"+44 1228 515331",
    "sg:postcode":"CA1 2RW",
    "sg:province":"Cumbria",
    "wof:name":"NatWest",
    "wof:placetype":"venue"
},
  "geometry": {"coordinates":[-2.8956201077,54.8949966431],"type":"Point"}
}