{
  "type": "Feature",
  "properties": {
    "iso:country":"GB",
    "sg:address":"131 Bute Street",
    "sg:city":"Treorchy",
    "sg:classifiers":[
        {
            "category":"Shopping",
            "subcategory":"Department Store",
            "type":"Retail Goods"
        }
    ],
    "sg:phone":"+44 1443 776877",
    "sg:postcode":"CF42 6BB",
    "sg:province":"Rhondda, Cynon, Taff",
    "wof:name":"Treorchy Spar",
    "wof:placetype":"venue"
},
  "geometry": {"coordinates":[-3.51023,51.661819],"type":"Point"}
}