{
  "type": "Feature",
  "properties": {
    "addr:full":"702 Burnage La, Burnage Manchester Greater Manchester M19 1NA",
    "addr:housenumber":"702",
    "addr:postcode":"m19 1na",
    "addr:street":"Burnage La Burnage",
    "iso:country":"GB",
    "sg:address":"702 Burnage La, Burnage",
    "sg:city":"Manchester",
    "sg:classifiers":[
        {
            "category":"Professional",
            "subcategory":"Accounting & Tax Preparation",
            "type":"Services"
        }
    ],
    "sg:postcode":"M19 1NA",
    "sg:province":"Greater Manchester",
    "sg:tags":[
        "accountant"
    ],
    "wof:name":"Mason,Stephen J,",
    "wof:placetype":"venue"
},
  "geometry": {"coordinates":[-2.211594,53.42078],"type":"Point"}
}