{
  "type": "Feature",
  "properties": {
    "iso:country":"GB",
    "sg:address":"Poplar Nurseries, Coggeshall Road, Marks Tey",
    "sg:city":"Colchester",
    "sg:classifiers":[
        {
            "category":"Home & Garden",
            "subcategory":"Garden Supply",
            "type":"Retail Goods"
        }
    ],
    "sg:phone":"+44 1206 210374",
    "sg:postcode":"CO6 1HR",
    "sg:province":"Essex",
    "sg:tags":[
        "nursery",
        "centre"
    ],
    "wof:name":"Poplar Nurseries Ltd.",
    "wof:placetype":"venue"
},
  "geometry": {"coordinates":[0.6910380125,51.8712997437],"type":"Point"}
}