{
  "type": "Feature",
  "properties": {
    "addr:full":"5c Love Lane Andover Hampshire SP10 2AF",
    "addr:housenumber":"5c",
    "addr:postcode":"sp10 2af",
    "addr:street":"Love Lane",
    "iso:country":"GB",
    "sg:address":"5c Love Lane",
    "sg:city":"Andover",
    "sg:classifiers":[
        {
            "category":"Retail",
            "subcategory":"Storage",
            "type":"Services"
        }
    ],
    "sg:phone":"+44 1264 332986",
    "sg:postcode":"SP10 2AF",
    "sg:province":"Hampshire",
    "sg:tags":[
        "household",
        "removal"
    ],
    "wof:name":"Man N Van",
    "wof:placetype":"venue"
},
  "geometry": {"coordinates":[-1.475629,51.204426],"type":"Point"}
}