{
  "type": "Feature",
  "properties": {
    "iso:country":"GB",
    "sg:address":"31 The Murray Square, East Kilbride",
    "sg:city":"Glasgow",
    "sg:classifiers":[
        {
            "category":"Professional",
            "subcategory":"Business Services",
            "type":"Services"
        }
    ],
    "sg:phone":"+44 1355 247077",
    "sg:postcode":"G75 0BH",
    "sg:province":"South Lanarkshire",
    "sg:tags":[
        "hospitality",
        "corporate"
    ],
    "wof:name":"Dexters House of Fun",
    "wof:placetype":"venue"
},
  "geometry": {"coordinates":[-4.18438,55.752911],"type":"Point"}
}