{
  "type": "Feature",
  "properties": {
    "iso:country":"GB",
    "sg:address":"38 Albert St",
    "sg:city":"Dundee",
    "sg:classifiers":[
        {
            "category":"Shopping",
            "subcategory":"Used Merchandise",
            "type":"Retail Goods"
        }
    ],
    "sg:postcode":"DD4 6QQ",
    "sg:province":"Dundee City",
    "sg:tags":[
        "shop",
        "second-hand"
    ],
    "wof:name":"Douris,George,",
    "wof:placetype":"venue"
},
  "geometry": {"coordinates":[-2.957984,56.469139],"type":"Point"}
}