{
  "type": "Feature",
  "properties": {
    "addr:full":"20 Birmingham Road Walsall West Midlands WS1 2LT",
    "addr:housenumber":"20",
    "addr:postcode":"ws1 2lt",
    "addr:street":"Birmingham Road",
    "iso:country":"GB",
    "sg:address":"20 Birmingham Road",
    "sg:city":"Walsall",
    "sg:classifiers":[
        {
            "category":"Education",
            "subcategory":"Special Training",
            "type":"Public Place"
        }
    ],
    "sg:postcode":"WS1 2LT",
    "sg:province":"West Midlands",
    "sg:tags":[
        "product",
        "centre"
    ],
    "wof:name":"Deemac Training Services Ltd",
    "wof:placetype":"venue"
},
  "geometry": {"coordinates":[-1.970089,52.577713],"type":"Point"}
}