{
  "type": "Feature",
  "properties": {
    "iso:country":"GB",
    "sg:address":"14 Market Square, Wellington",
    "sg:city":"Telford",
    "sg:classifiers":[
        {
            "category":"Food & Beverages",
            "subcategory":"Bakery",
            "type":"Retail Goods"
        }
    ],
    "sg:phone":"+44 1952 247677",
    "sg:postcode":"TF1 1BU",
    "sg:province":"Shropshire",
    "sg:tags":[
        "baker"
    ],
    "wof:name":"Three Cooks Ltd.",
    "wof:placetype":"venue"
},
  "geometry": {"coordinates":[-2.51962,52.701134],"type":"Point"}
}