{
  "type": "Feature",
  "properties": {
    "iso:country":"GB",
    "sg:address":"Unit 44, Colbourne Crescent",
    "sg:city":"Cramlington",
    "sg:classifiers":[
        {
            "category":"Home & Garden",
            "subcategory":"Furniture",
            "type":"Retail Goods"
        }
    ],
    "sg:phone":"+44 1670 590556",
    "sg:postcode":"NE23 1WB",
    "sg:province":"Northumberland",
    "wof:name":"Browns Bedrooms & Kitchens Ltd.",
    "wof:placetype":"venue"
},
  "geometry": {"coordinates":[-1.605622,55.099472],"type":"Point"}
}