{
  "type": "Feature",
  "properties": {
    "addr:full":"4 Hills Road Cambridge Cambridgeshire CB2 1JP",
    "addr:housenumber":"4",
    "addr:postcode":"cb2 1jp",
    "addr:street":"Hills Road",
    "iso:country":"GB",
    "sg:address":"4 Hills Road",
    "sg:city":"Cambridge",
    "sg:classifiers":[
        {
            "category":"Insurance",
            "subcategory":"Insurance Agent",
            "type":"Services"
        }
    ],
    "sg:phone":"+44 1223 353713",
    "sg:postcode":"CB2 1JP",
    "sg:province":"Cambridgeshire",
    "wof:name":"Britannic Assurance Plc",
    "wof:placetype":"venue"
},
  "geometry": {"coordinates":[0.12833,52.198051],"type":"Point"}
}