{
  "type": "Feature",
  "properties": {
    "addr:full":"Bethine House, 88 West Street Farnham Surrey GU9 7EN",
    "addr:housenumber":"88",
    "addr:postcode":"gu9 7en",
    "addr:street":"West Street",
    "iso:country":"GB",
    "sg:address":"Bethine House, 88 West Street",
    "sg:city":"Farnham",
    "sg:classifiers":[
        {
            "category":"Professional",
            "subcategory":"Computer Services",
            "type":"Services"
        }
    ],
    "sg:phone":"+44 1252 721112",
    "sg:postcode":"GU9 7EN",
    "sg:province":"Surrey",
    "sg:tags":[
        "bureau",
        "facility"
    ],
    "wof:name":"Computab Ltd.",
    "wof:placetype":"venue"
},
  "geometry": {"coordinates":[-0.8037089705,51.213722229],"type":"Point"}
}