{
  "type": "Feature",
  "properties": {
    "addr:full":"2 Hoton Road, Wymeswold Loughborough Leicestershire LE12 6UA",
    "addr:housenumber":"2",
    "addr:postcode":"le12 6ua",
    "addr:street":"Hoton Road",
    "iso:country":"GB",
    "sg:address":"2 Hoton Road, Wymeswold",
    "sg:city":"Loughborough",
    "sg:classifiers":[
        {
            "category":"Farming",
            "subcategory":"Farm",
            "type":"Manufacturing & Wholesale Goods"
        }
    ],
    "sg:postcode":"LE12 6UA",
    "sg:province":"Leicestershire",
    "sg:tags":[
        "mixed",
        "crop"
    ],
    "wof:name":"R Hubbard",
    "wof:placetype":"venue"
},
  "geometry": {"coordinates":[-1.110408,52.804176],"type":"Point"}
}