{
  "type": "Feature",
  "properties": {
    "addr:full":"32 Gloucester Road Brighton East Sussex BN1 4AQ",
    "addr:housenumber":"32",
    "addr:postcode":"bn1 4aq",
    "addr:street":"Gloucester Road",
    "iso:country":"GB",
    "sg:address":"32 Gloucester Road",
    "sg:city":"Brighton",
    "sg:classifiers":[
        {
            "category":"Professional",
            "subcategory":"Business Services",
            "type":"Services"
        }
    ],
    "sg:postcode":"BN1 4AQ",
    "sg:province":"East Sussex",
    "sg:tags":[
        "tile",
        "stockist"
    ],
    "wof:name":"The Floor Ltd.",
    "wof:placetype":"venue"
},
  "geometry": {"coordinates":[-0.1390620023,50.8269348145],"type":"Point"}
}