{
  "type": "Feature",
  "properties": {
    "addr:full":"Tolmers Lodge, Tolmers House Hertford Hertfordshire SG13 8RB",
    "addr:postcode":"sg13 8rb",
    "addr:street":"Hertford",
    "iso:country":"GB",
    "sg:address":"Tolmers Lodge, Tolmers House",
    "sg:city":"Hertford",
    "sg:classifiers":[
        {
            "category":"Home & Garden",
            "subcategory":"Home Furnishings",
            "type":"Retail Goods"
        }
    ],
    "sg:postcode":"SG13 8RB",
    "sg:province":"Hertfordshire",
    "sg:tags":[
        "awning",
        "canopy",
        "blinds"
    ],
    "wof:name":"Choice Window Blinds",
    "wof:placetype":"venue"
},
  "geometry": {"coordinates":[-0.094444,51.77795],"type":"Point"}
}