{
  "type": "Feature",
  "properties": {
    "iso:country":"GB",
    "sg:address":"17 Bonington Rise, Marple Bridge",
    "sg:city":"Stockport",
    "sg:classifiers":[
        {
            "category":"Real Estate",
            "subcategory":"Architect",
            "type":"Services"
        }
    ],
    "sg:postcode":"SK6 5DW",
    "sg:province":"Cheshire",
    "wof:name":"Graham Hill Associates Ltd.",
    "wof:placetype":"venue"
},
  "geometry": {"coordinates":[-2.0489699841,53.4046287537],"type":"Point"}
}