{
  "type": "Feature",
  "properties": {
    "addr:full":"32 Crawford St Birmingham West Midlands B8 1JL",
    "addr:housenumber":"32",
    "addr:postcode":"b8 1jl",
    "addr:street":"Crawford St",
    "iso:country":"GB",
    "sg:address":"32 Crawford St",
    "sg:city":"Birmingham",
    "sg:classifiers":[
        {
            "category":"Wholesale",
            "subcategory":"Scrap",
            "type":"Manufacturing & Wholesale Goods"
        }
    ],
    "sg:phone":"+44 1564 702269",
    "sg:postcode":"B8 1JL",
    "sg:province":"West Midlands",
    "sg:tags":[
        "breaker",
        "dismantlers"
    ],
    "wof:name":"Olympic",
    "wof:placetype":"venue"
},
  "geometry": {"coordinates":[-1.8623050451,52.4905471802],"type":"Point"}
}