{
  "type": "Feature",
  "properties": {
    "addr:full":"10 Mandervell Road, Oadby Leicester Leicestershire LE2 5LQ",
    "addr:housenumber":"10",
    "addr:postcode":"le2 5lq",
    "addr:street":"Mandervell Road",
    "iso:country":"GB",
    "sg:address":"10 Mandervell Road, Oadby",
    "sg:city":"Leicester",
    "sg:classifiers":[
        {
            "category":"Home & Garden",
            "subcategory":"Hardware",
            "type":"Retail Goods"
        }
    ],
    "sg:phone":"+44 116 271 3763",
    "sg:postcode":"LE2 5LQ",
    "sg:province":"Leicestershire",
    "sg:tags":[
        "paint"
    ],
    "wof:name":"Emusol Products (Leicester) Ltd.",
    "wof:placetype":"venue"
},
  "geometry": {"coordinates":[-1.093091011,52.5975265503],"type":"Point"}
}