{
  "type": "Feature",
  "properties": {
    "iso:country":"GB",
    "sg:address":"86 High Street",
    "sg:city":"Rye",
    "sg:classifiers":[
        {
            "category":"Shopping",
            "subcategory":"Clothing, Apparel, & Fashions",
            "type":"Retail Goods"
        }
    ],
    "sg:phone":"+44 1797 223229",
    "sg:postcode":"TN31 7JN",
    "sg:province":"East Sussex",
    "sg:tags":[
        "shop"
    ],
    "wof:name":"Frank Golden",
    "wof:placetype":"venue"
},
  "geometry": {"coordinates":[0.7329499722,50.9507484436],"type":"Point"}
}