{
  "type": "Feature",
  "properties": {
    "addr:full":"18 Redworth Rd Shildon Durham DL4 2JE",
    "addr:housenumber":"18",
    "addr:postcode":"dl4 2je",
    "addr:street":"Redworth Rd",
    "iso:country":"GB",
    "sg:address":"18 Redworth Rd",
    "sg:city":"Shildon",
    "sg:classifiers":[
        {
            "category":"Food & Beverages",
            "subcategory":"Supermarket",
            "type":"Retail Goods"
        }
    ],
    "sg:phone":"+44 1388 772189",
    "sg:postcode":"DL4 2JE",
    "sg:province":"Durham",
    "wof:name":"Walter Willson Ltd",
    "wof:placetype":"venue"
},
  "geometry": {"coordinates":[-1.64585495,54.6250724792],"type":"Point"}
}