{
  "type": "Feature",
  "properties": {
    "addr:full":"International Base, Greenwell Rd, East Tullos Indstl Est Aberdeen Aberdeen City AB12 3AX",
    "addr:postcode":"ab12 3ax",
    "addr:street":"Greenwell Rd",
    "iso:country":"GB",
    "sg:address":"International Base, Greenwell Rd, East Tullos Indstl Est",
    "sg:city":"Aberdeen",
    "sg:classifiers":[
        {
            "category":"Professional",
            "subcategory":"Engineering",
            "type":"Services"
        }
    ],
    "sg:phone":"+44 1224 895333",
    "sg:postcode":"AB12 3AX",
    "sg:province":"Aberdeen City",
    "sg:tags":[
        "consulting",
        "design",
        "engineer"
    ],
    "wof:name":"Stuart Projects Ltd",
    "wof:placetype":"venue"
},
  "geometry": {"coordinates":[-2.0732989311,57.1290283203],"type":"Point"}
}