{
  "type": "Feature",
  "properties": {
    "addr:full":"Cliffton Hill Pudsey West Yorkshire LS28 7EB",
    "addr:postcode":"ls28 7eb",
    "addr:street":"Cliffton;West",
    "iso:country":"GB",
    "sg:address":"Cliffton Hill",
    "sg:city":"Pudsey",
    "sg:classifiers":[
        {
            "category":"Shopping",
            "subcategory":"Pets & Pet Supplies",
            "type":"Retail Goods"
        }
    ],
    "sg:phone":"+44 113 256 4686",
    "sg:postcode":"LS28 7EB",
    "sg:province":"West Yorkshire",
    "wof:name":"Sharpes Pet World",
    "wof:placetype":"venue"
},
  "geometry": {"coordinates":[-1.6612290144,53.7979736328],"type":"Point"}
}