{
  "type": "Feature",
  "properties": {
    "iso:country":"GB",
    "sg:address":"26 Spital Sq",
    "sg:city":"Whitechapel",
    "sg:classifiers":[
        {
            "category":"Building & Trades",
            "subcategory":"Construction",
            "type":"Services"
        }
    ],
    "sg:phone":"+44 20 7375 1176",
    "sg:postcode":"E1 6DX",
    "sg:province":"Greater London",
    "sg:tags":[
        "worker",
        "metal"
    ],
    "wof:name":"Hilliard & Sparey",
    "wof:placetype":"venue"
},
  "geometry": {"coordinates":[-0.0776489973,51.5203590393],"type":"Point"}
}