{
  "type": "Feature",
  "properties": {
    "iso:country":"GB",
    "sg:address":"Annwood House, Nutley",
    "sg:city":"Uckfield",
    "sg:classifiers":[
        {
            "category":"Travel",
            "subcategory":"Travel Agent",
            "type":"Entertainment"
        },
        {
            "category":"Recreation",
            "subcategory":"Gun Range",
            "type":"Entertainment"
        }
    ],
    "sg:phone":"+44 1825 740676",
    "sg:postcode":"TN22 3HH",
    "sg:province":"East Sussex",
    "sg:tags":[
        "operator",
        "tour"
    ],
    "sg:website":"http://www.thetraveladventure.co.uk",
    "wof:name":"Travel Adventure Ltd",
    "wof:placetype":"venue"
},
  "geometry": {"coordinates":[0.055425,51.031563],"type":"Point"}
}