{
  "type": "Feature",
  "properties": {
    "addr:full":"Castle House Farm, Danby Whitby North Yorkshire YO21 2NP",
    "addr:postcode":"yo21 2np",
    "iso:country":"GB",
    "sg:address":"Castle House Farm, Danby",
    "sg:city":"Whitby",
    "sg:classifiers":[
        {
            "category":"Farming",
            "subcategory":"Livestock Farm",
            "type":"Manufacturing & Wholesale Goods"
        }
    ],
    "sg:postcode":"YO21 2NP",
    "sg:province":"North Yorkshire",
    "sg:tags":[
        "others"
    ],
    "wof:name":"David Tindall",
    "wof:placetype":"venue"
},
  "geometry": {"coordinates":[-0.909539,54.469341],"type":"Point"}
}