{
  "type": "Feature",
  "properties": {
    "addr:full":"Commandree Gaston Street, East Bergholt Colchester Essex CO7 6SE",
    "addr:postcode":"co7 6se",
    "addr:street":"Gaston Street",
    "iso:country":"GB",
    "sg:address":"Commandree Gaston Street, East Bergholt",
    "sg:city":"Colchester",
    "sg:classifiers":[
        {
            "category":"Wholesale",
            "subcategory":"Fruits & Vegetables",
            "type":"Manufacturing & Wholesale Goods"
        }
    ],
    "sg:postcode":"CO7 6SE",
    "sg:province":"Essex",
    "wof:name":"Associated Fruits  &  Flavours Ltd",
    "wof:placetype":"venue"
},
  "geometry": {"coordinates":[1.0205390453,51.9783401489],"type":"Point"}
}