{
  "type": "Feature",
  "properties": {
    "addr:full":"29-31 Y-manes Caelnarson Caernarfon Gwynedd LL55 2HN",
    "addr:housenumber":"29-31",
    "addr:postcode":"ll55 2hn",
    "addr:street":"Y-Manes Caelnarson",
    "iso:country":"GB",
    "sg:address":"29-31 Y-manes Caelnarson",
    "sg:city":"Caernarfon",
    "sg:classifiers":[
        {
            "category":"Education",
            "subcategory":"University",
            "type":"Public Place"
        }
    ],
    "sg:phone":"+44 1286 673450",
    "sg:postcode":"LL55 2HN",
    "sg:province":"Gwynedd",
    "sg:tags":[
        "higher"
    ],
    "wof:name":"Coleg Menai",
    "wof:placetype":"venue"
},
  "geometry": {"coordinates":[-4.2749938965,53.1396865845],"type":"Point"}
}