{
  "type": "Feature",
  "properties": {
    "iso:country":"GB",
    "sg:address":"104 Cable Depot Rd",
    "sg:city":"Clydebank",
    "sg:classifiers":[
        {
            "category":"Military Area",
            "subcategory":"Coast Guard Base",
            "type":"Public Place"
        }
    ],
    "sg:phone":"+44 141 951 4043",
    "sg:postcode":"G81 1UF",
    "sg:province":"East Dunbartonshire",
    "sg:tags":[
        "equipment",
        "bar",
        "accessory"
    ],
    "wof:name":"W & J Cruickshank & Co",
    "wof:placetype":"venue"
},
  "geometry": {"coordinates":[-4.419407,55.904251],"type":"Point"}
}