{
  "type": "Feature",
  "properties": {
    "iso:country":"GB",
    "sg:address":"64 High Street",
    "sg:city":"Laurencekirk",
    "sg:classifiers":[
        {
            "category":"Retail",
            "subcategory":"Funeral Services",
            "type":"Services"
        }
    ],
    "sg:postcode":"AB30 1BJ",
    "sg:province":"Aberdeenshire",
    "sg:tags":[
        "director"
    ],
    "wof:name":"Emslie S Collier",
    "wof:placetype":"venue"
},
  "geometry": {"coordinates":[-2.466094,56.833084],"type":"Point"}
}