{
  "type": "Feature",
  "properties": {
    "addr:full":"743 London Road, North Cheam Sutton Surrey SM3 9DL",
    "addr:housenumber":"743",
    "addr:postcode":"sm3 9dl",
    "addr:street":"London Road",
    "iso:country":"GB",
    "sg:address":"743 London Road, North Cheam",
    "sg:city":"Sutton",
    "sg:classifiers":[
        {
            "category":"Health Services",
            "subcategory":"Dentist",
            "type":"Services"
        }
    ],
    "sg:phone":"+44 20 8337 0629",
    "sg:postcode":"SM3 9DL",
    "sg:province":"Surrey",
    "wof:name":"Williams Dental Practice",
    "wof:placetype":"venue"
},
  "geometry": {"coordinates":[-0.2211620063,51.3776359558],"type":"Point"}
}