{
  "type": "Feature",
  "properties": {
    "addr:full":"Unit 32 Tyock Industrial Estate Elgin Moray IV30 1XY",
    "addr:housenumber":"unit 32",
    "addr:postcode":"iv30 1xy",
    "addr:street":"Tyock Industrial Estate",
    "iso:country":"GB",
    "sg:address":"Unit 32 Tyock Industrial Estate",
    "sg:city":"Elgin",
    "sg:classifiers":[
        {
            "category":"Shopping",
            "subcategory":"Computers & Home Electronics",
            "type":"Retail Goods"
        }
    ],
    "sg:phone":"+44 1343 544040",
    "sg:postcode":"IV30 1XY",
    "sg:province":"Moray",
    "sg:tags":[
        "electrical"
    ],
    "wof:name":"Cable Management Centre Ltd.",
    "wof:placetype":"venue"
},
  "geometry": {"coordinates":[-3.317869,57.649368],"type":"Point"}
}