{
  "type": "Feature",
  "properties": {
    "addr:full":"36 Sharon Street Dalry North Ayrshire KA24 5DT",
    "addr:housenumber":"36",
    "addr:postcode":"ka24 5dt",
    "addr:street":"Sharon Street",
    "iso:country":"GB",
    "sg:address":"36 Sharon Street",
    "sg:city":"Dalry",
    "sg:classifiers":[
        {
            "category":"Retail",
            "subcategory":"Funeral Services",
            "type":"Services"
        }
    ],
    "sg:phone":"+44 1294 832426",
    "sg:postcode":"KA24 5DT",
    "sg:province":"North Ayrshire",
    "wof:name":"Co-Operative Funeral Services",
    "wof:placetype":"venue"
},
  "geometry": {"coordinates":[-4.724656,55.708641],"type":"Point"}
}