{
  "type": "Feature",
  "properties": {
    "iso:country":"GB",
    "sg:address":"139 Devonshire Street",
    "sg:city":"Keighley",
    "sg:classifiers":[
        {
            "category":"Fast Food",
            "type":"Food & Drink"
        }
    ],
    "sg:phone":"+44 1535 662310",
    "sg:postcode":"BD21 2LT",
    "sg:province":"West Yorkshire",
    "sg:tags":[
        "away",
        "take"
    ],
    "wof:name":"Bruce Saxton",
    "wof:placetype":"venue"
},
  "geometry": {"coordinates":[-1.919632,53.867485],"type":"Point"}
}