{
  "type": "Feature",
  "properties": {
    "iso:country":"GB",
    "sg:address":"Unit 3 Maida Vale Business Centre, Maida Vale Road, Leckhampton",
    "sg:city":"Cheltenham",
    "sg:classifiers":[
        {
            "category":"Retail",
            "subcategory":"Laundry & Dry Cleaning",
            "type":"Services"
        }
    ],
    "sg:phone":"+44 1242 244129",
    "sg:postcode":"GL53 7ER",
    "sg:province":"Gloucestershire",
    "sg:tags":[
        "launderette"
    ],
    "wof:name":"Cotswold Linen Care Ltd.",
    "wof:placetype":"venue"
},
  "geometry": {"coordinates":[-2.0764501095,51.8837013245],"type":"Point"}
}