{
  "type": "Feature",
  "properties": {
    "iso:country":"GB",
    "sg:address":"15 The Row",
    "sg:city":"Longfield",
    "sg:classifiers":[
        {
            "category":"Food & Beverages",
            "subcategory":"Specialty",
            "type":"Retail Goods"
        }
    ],
    "sg:phone":"+44 1474 872583",
    "sg:postcode":"DA3 8JB",
    "sg:province":"Kent",
    "sg:tags":[
        "product",
        "health"
    ],
    "wof:name":"New Ash Green Health Food Centre",
    "wof:placetype":"venue"
},
  "geometry": {"coordinates":[0.29851,51.36657],"type":"Point"}
}