{
  "type": "Feature",
  "properties": {
    "iso:country":"GB",
    "sg:address":"Causeway Bridges Farm, Alder Lane, Burtonwood",
    "sg:city":"Warrington",
    "sg:classifiers":[
        {
            "category":"Farming",
            "subcategory":"Farm",
            "type":"Manufacturing & Wholesale Goods"
        }
    ],
    "sg:phone":"+44 1925 630625",
    "sg:postcode":"WA5 4BN",
    "sg:province":"Cheshire",
    "sg:tags":[
        "mixed",
        "crop"
    ],
    "wof:name":"H H Fairclough & Sons",
    "wof:placetype":"venue"
},
  "geometry": {"coordinates":[-2.6593739986,53.4310760498],"type":"Point"}
}