{
  "type": "Feature",
  "properties": {
    "iso:country":"GB",
    "sg:address":"Millgate, Hollins",
    "sg:city":"Oldham",
    "sg:classifiers":[
        {
            "category":"Shopping",
            "subcategory":"Catalog Store",
            "type":"Retail Goods"
        }
    ],
    "sg:phone":"+44 161 652 3431",
    "sg:postcode":"OL8 4JX",
    "sg:province":"Lancashire",
    "sg:tags":[
        "mail",
        "order"
    ],
    "wof:name":"Littlewoods Stores Ltd",
    "wof:placetype":"venue"
},
  "geometry": {"coordinates":[-2.12957,53.5247],"type":"Point"}
}