{
  "type": "Feature",
  "properties": {
    "iso:country":"GB",
    "sg:address":"6 Archery St",
    "sg:city":"Leeds",
    "sg:classifiers":[
        {
            "category":"Professional",
            "subcategory":"Engineering",
            "type":"Services"
        }
    ],
    "sg:phone":"+44 113 243 9736",
    "sg:postcode":"LS2 9AS",
    "sg:province":"West Yorkshire",
    "sg:tags":[
        "consulting",
        "engineer"
    ],
    "wof:name":"Winds Of Change Projects",
    "wof:placetype":"venue"
},
  "geometry": {"coordinates":[-1.549006,53.807995],"type":"Point"}
}