{
  "type": "Feature",
  "properties": {
    "iso:country":"GB",
    "sg:address":"Buncefield Terminal, Green Lane",
    "sg:city":"Hemel Hempstead",
    "sg:classifiers":[
        {
            "category":"Utilities",
            "subcategory":"Fuel Oil & Lpg",
            "type":"Services"
        }
    ],
    "sg:phone":"+44 1442 251217",
    "sg:postcode":"HP2 7HZ",
    "sg:province":"Hertfordshire",
    "sg:tags":[
        "distributor"
    ],
    "wof:name":"Able Adams Fuel Oils",
    "wof:placetype":"venue"
},
  "geometry": {"coordinates":[-0.4261789918,51.7641563416],"type":"Point"}
}