{
  "type": "Feature",
  "properties": {
    "addr:full":"St Johns Vicarage, 1 St Johns Rd Clevedon Somerset BS21 7TG",
    "addr:housenumber":"1",
    "addr:postcode":"bs21 7tg",
    "addr:street":"St Johns Rd",
    "iso:country":"GB",
    "sg:address":"St Johns Vicarage, 1 St Johns Rd",
    "sg:city":"Clevedon",
    "sg:classifiers":[
        {
            "category":"Place Of Worship",
            "type":"Public Place"
        }
    ],
    "sg:phone":"+44 1275 872410",
    "sg:postcode":"BS21 7TG",
    "sg:province":"Somerset",
    "wof:name":"St John Evangelist",
    "wof:placetype":"venue"
},
  "geometry": {"coordinates":[-2.855039,51.435925],"type":"Point"}
}