{
  "type": "Feature",
  "properties": {
    "addr:full":"Manby Road Immingham Lincolnshire DN40 2LJ",
    "addr:postcode":"dn40 2lj",
    "addr:street":"Manby Road",
    "iso:country":"GB",
    "sg:address":"Manby Road",
    "sg:city":"Immingham",
    "sg:classifiers":[
        {
            "category":"Autos & Motor Vehicles",
            "subcategory":"Automobile Sales",
            "type":"Retail Goods"
        }
    ],
    "sg:phone":"+44 1469 571150",
    "sg:postcode":"DN40 2LJ",
    "sg:province":"Lincolnshire",
    "sg:tags":[
        "commercial"
    ],
    "wof:name":"North East Truck & Van",
    "wof:placetype":"venue"
},
  "geometry": {"coordinates":[-0.2064139992,53.6199264526],"type":"Point"}
}