{
  "type": "Feature",
  "properties": {
    "addr:full":"10 Beach Road Penarth The Vale of Glamorgan CF64 1JX",
    "addr:housenumber":"10",
    "addr:postcode":"cf64 1jx",
    "addr:street":"Beach Road;Vale",
    "iso:country":"GB",
    "sg:address":"10 Beach Road",
    "sg:city":"Penarth",
    "sg:classifiers":[
        {
            "category":"Arts & Performance",
            "subcategory":"Music",
            "type":"Entertainment"
        }
    ],
    "sg:phone":"+44 29 2071 1462",
    "sg:postcode":"CF64 1JX",
    "sg:province":"The Vale of Glamorgan",
    "sg:tags":[
        "musician",
        "composer"
    ],
    "wof:name":"Danny Chang Music Composer",
    "wof:placetype":"venue"
},
  "geometry": {"coordinates":[-3.1676540375,51.4369010925],"type":"Point"}
}