{
  "type": "Feature",
  "properties": {
    "iso:country":"GB",
    "sg:address":"Leythorne Nursery, Vinnetrow Road, Runcton",
    "sg:city":"Chichester",
    "sg:classifiers":[
        {
            "category":"Farming",
            "subcategory":"Nursery",
            "type":"Manufacturing & Wholesale Goods"
        },
        {
            "category":"Home & Garden",
            "subcategory":"Garden Supply",
            "type":"Retail Goods"
        }
    ],
    "sg:phone":"+44 1243 532077",
    "sg:postcode":"PO20 1QD",
    "sg:province":"West Sussex",
    "sg:tags":[
        "planting",
        "tree",
        "shrub",
        "centre"
    ],
    "wof:name":"Cleangro Ltd",
    "wof:placetype":"venue"
},
  "geometry": {"coordinates":[-0.74875,50.820042],"type":"Point"}
}