{
  "type": "Feature",
  "properties": {
    "addr:full":"2-4 New Market, Academy Street Inverness Highland IV1 1PG",
    "addr:housenumber":"2-4",
    "addr:postcode":"iv1 1pg",
    "addr:street":"Academy Street",
    "iso:country":"GB",
    "sg:address":"2-4 New Market, Academy Street",
    "sg:city":"Inverness",
    "sg:classifiers":[
        {
            "category":"Shopping",
            "subcategory":"Beauty & Cosmetics",
            "type":"Retail Goods"
        }
    ],
    "sg:phone":"+44 1463 224705",
    "sg:postcode":"IV1 1PG",
    "sg:province":"Highland",
    "sg:tags":[
        "product"
    ],
    "wof:name":"The Body & Face Place",
    "wof:placetype":"venue"
},
  "geometry": {"coordinates":[-4.22486,57.479191],"type":"Point"}
}