{
  "type": "Feature",
  "properties": {
    "iso:country":"GB",
    "sg:address":"120 Bonllwyn",
    "sg:city":"Ammanford",
    "sg:classifiers":[
        {
            "category":"Building & Trades",
            "subcategory":"Landscaping Services",
            "type":"Services"
        }
    ],
    "sg:phone":"+44 1269 596953",
    "sg:postcode":"SA18 2EF",
    "sg:province":"Carmarthenshire",
    "sg:tags":[
        "pond",
        "aquarium"
    ],
    "wof:name":"Bonllwyn Aquatic World",
    "wof:placetype":"venue"
},
  "geometry": {"coordinates":[-3.995369,51.8046],"type":"Point"}
}