{
  "type": "Feature",
  "properties": {
    "addr:full":"103 Northern Rd Newark Nottinghamshire NG24 2EU",
    "addr:housenumber":"103",
    "addr:postcode":"ng24 2eu",
    "addr:street":"Northern Rd",
    "iso:country":"GB",
    "sg:address":"103 Northern Rd",
    "sg:city":"Newark",
    "sg:classifiers":[
        {
            "category":"Retail",
            "subcategory":"Auto Repair",
            "type":"Services"
        }
    ],
    "sg:phone":"+44 1636 611117",
    "sg:postcode":"NG24 2EU",
    "sg:province":"Nottinghamshire",
    "sg:tags":[
        "modification",
        "garage"
    ],
    "wof:name":"Stewart East",
    "wof:placetype":"venue"
},
  "geometry": {"coordinates":[-0.7985320091,53.0832633972],"type":"Point"}
}