{
  "type": "Feature",
  "properties": {
    "iso:country":"GB",
    "sg:address":"Monkton Industrial Estate, Denby Dale Road",
    "sg:city":"Wakefield",
    "sg:classifiers":[
        {
            "category":"Shopping",
            "subcategory":"Pets & Pet Supplies",
            "type":"Retail Goods"
        }
    ],
    "sg:phone":"+44 1924 382820",
    "sg:postcode":"WF2 7BP",
    "sg:province":"West Yorkshire",
    "sg:tags":[
        "food"
    ],
    "wof:name":"Baileys Horse Feeds",
    "wof:placetype":"venue"
},
  "geometry": {"coordinates":[-1.508654,53.66573],"type":"Point"}
}