{
  "type": "Feature",
  "properties": {
    "addr:full":"4 Arndale Centre Bradford West Yorkshire BD1 1TG",
    "addr:housenumber":"4",
    "addr:postcode":"bd1 1tg",
    "addr:street":"Arndale Centre Bradford West",
    "iso:country":"GB",
    "sg:address":"4 Arndale Centre",
    "sg:city":"Bradford",
    "sg:classifiers":[
        {
            "category":"Sports & Exercise",
            "subcategory":"Sports Center",
            "type":"Entertainment"
        }
    ],
    "sg:phone":"+44 1274 722622",
    "sg:postcode":"BD1 1TG",
    "sg:province":"West Yorkshire",
    "sg:tags":[
        "shop",
        "good"
    ],
    "wof:name":"Stylo Instep Ltd",
    "wof:placetype":"venue"
},
  "geometry": {"coordinates":[-1.7583060265,53.7957382202],"type":"Point"}
}