{
  "type": "Feature",
  "properties": {
    "iso:country":"GB",
    "sg:address":"277-279 Pershore Road South",
    "sg:city":"Birmingham",
    "sg:classifiers":[
        {
            "category":"Building & Trades",
            "subcategory":"Construction",
            "type":"Services"
        }
    ],
    "sg:postcode":"B30 3EX",
    "sg:province":"West Midlands",
    "sg:tags":[
        "monumental",
        "mason"
    ],
    "wof:name":"The Memorial Co.",
    "wof:placetype":"venue"
},
  "geometry": {"coordinates":[-1.928058,52.408981],"type":"Point"}
}