{
  "type": "Feature",
  "properties": {
    "addr:full":"Kew Bridge Distribution Centre, Lionel Rd Brentford Greater London TW8 9QR",
    "addr:postcode":"tw8 9qr",
    "addr:street":"Kew;Lionel Rd",
    "iso:country":"GB",
    "sg:address":"Kew Bridge Distribution Centre, Lionel Rd",
    "sg:city":"Brentford",
    "sg:classifiers":[
        {
            "category":"Education",
            "subcategory":"Special Training",
            "type":"Public Place"
        }
    ],
    "sg:postcode":"TW8 9QR",
    "sg:province":"Greater London",
    "sg:tags":[
        "product",
        "centre"
    ],
    "wof:name":"Manda Consultancy & Training Ltd",
    "wof:placetype":"venue"
},
  "geometry": {"coordinates":[-0.306724,51.484135],"type":"Point"}
}