{
  "type": "Feature",
  "properties": {
    "addr:full":"501-507 Christchurch Road Bournemouth Dorset BH1 4AF",
    "addr:housenumber":"501-507",
    "addr:postcode":"bh1 4af",
    "addr:street":"Christchurch Road",
    "iso:country":"GB",
    "sg:address":"501-507 Christchurch Road",
    "sg:city":"Bournemouth",
    "sg:classifiers":[
        {
            "category":"Shopping",
            "subcategory":"Catalog Store",
            "type":"Retail Goods"
        }
    ],
    "sg:phone":"+44 1202 309345",
    "sg:postcode":"BH1 4AF",
    "sg:province":"Dorset",
    "sg:tags":[
        "shop",
        "catalogue",
        "showroom"
    ],
    "sg:website":"http://www.argos.co.uk",
    "wof:name":"Argos Ltd",
    "wof:placetype":"venue"
},
  "geometry": {"coordinates":[-1.8436609507,50.7253227234],"type":"Point"}
}