{
  "type": "Feature",
  "properties": {
    "iso:country":"GB",
    "sg:address":"18a Market Place",
    "sg:city":"Blandford Forum",
    "sg:classifiers":[
        {
            "category":"Fast Food",
            "type":"Food & Drink"
        }
    ],
    "sg:postcode":"DT11 7EB",
    "sg:province":"Dorset",
    "sg:tags":[
        "away",
        "take"
    ],
    "wof:name":"Wareham Chipperies Limited",
    "wof:placetype":"venue"
},
  "geometry": {"coordinates":[-2.1645960808,50.8558883667],"type":"Point"}
}