{
  "type": "Feature",
  "properties": {
    "addr:full":"Charleston Drive Dundee Dundee City DD2 4AD",
    "addr:postcode":"dd2 4ad",
    "addr:street":"Charleston Drive",
    "iso:country":"GB",
    "sg:address":"Charleston Drive",
    "sg:city":"Dundee",
    "sg:classifiers":[
        {
            "category":"Health Services",
            "subcategory":"Doctor",
            "type":"Services"
        },
        {
            "category":"Health Services",
            "subcategory":"Clinic",
            "type":"Services"
        }
    ],
    "sg:phone":"+44 1382 642335",
    "sg:postcode":"DD2 4AD",
    "sg:province":"Dundee City",
    "sg:tags":[
        "nh",
        "practitioners"
    ],
    "wof:name":"West Gate Health Centre",
    "wof:placetype":"venue"
},
  "geometry": {"coordinates":[-3.030631,56.470322],"type":"Point"}
}