{
  "type": "Feature",
  "properties": {
    "iso:country":"GB",
    "sg:address":"Duval Wks, St. Thomas Rd",
    "sg:city":"Stoke-on-trent",
    "sg:classifiers":[
        {
            "category":"Professional",
            "subcategory":"Engineering",
            "type":"Services"
        }
    ],
    "sg:postcode":"ST10 4DS",
    "sg:province":"Staffordshire",
    "wof:name":"Shaw,Roy,",
    "wof:placetype":"venue"
},
  "geometry": {"coordinates":[-1.986575,52.955128],"type":"Point"}
}