{
  "type": "Feature",
  "properties": {
    "iso:country":"GB",
    "sg:address":"36 Call Lane",
    "sg:city":"Leeds",
    "sg:classifiers":[
        {
            "category":"Restaurant",
            "type":"Food & Drink"
        }
    ],
    "sg:phone":"+44 113 234 3988",
    "sg:postcode":"LS1 6DT",
    "sg:province":"West Yorkshire",
    "sg:tags":[
        "-",
        "japanese"
    ],
    "sg:website":"http://www.normans.co.uk",
    "wof:name":"Normans",
    "wof:placetype":"venue"
},
  "geometry": {"coordinates":[-1.5408170223,53.795501709],"type":"Point"}
}