{
  "type": "Feature",
  "properties": {
    "addr:full":"Harelaw Industrial Estate, Annfield Plane Stanley Durham DH9 8UR",
    "addr:postcode":"dh9 8ur",
    "addr:street":"Estate Annfield Plane Stanley",
    "iso:country":"GB",
    "sg:address":"Harelaw Industrial Estate, Annfield Plane",
    "sg:city":"Stanley",
    "sg:classifiers":[
        {
            "category":"Home & Garden",
            "subcategory":"Kitchen Supply",
            "type":"Retail Goods"
        }
    ],
    "sg:phone":"+44 1207 230621",
    "sg:postcode":"DH9 8UR",
    "sg:province":"Durham",
    "sg:tags":[
        "equipment",
        "catering"
    ],
    "wof:name":"du Mont C S Ltd.",
    "wof:placetype":"venue"
},
  "geometry": {"coordinates":[-1.74817,54.87397],"type":"Point"}
}