{
  "type": "Feature",
  "properties": {
    "addr:full":"5 Queens Avenue Widnes Cheshire WA8 8HR",
    "addr:housenumber":"5",
    "addr:postcode":"wa8 8hr",
    "addr:street":"Queens Avenue",
    "iso:country":"GB",
    "sg:address":"5 Queens Avenue",
    "sg:city":"Widnes",
    "sg:classifiers":[
        {
            "category":"Shopping",
            "subcategory":"Clothing, Apparel, & Fashions",
            "type":"Retail Goods"
        }
    ],
    "sg:postcode":"WA8 8HR",
    "sg:province":"Cheshire",
    "sg:tags":[
        "shop"
    ],
    "wof:name":"Marie",
    "wof:placetype":"venue"
},
  "geometry": {"coordinates":[-2.7691709995,53.367313385],"type":"Point"}
}