{
  "type": "Feature",
  "properties": {
    "iso:country":"GB",
    "sg:address":"60 Cato Street, Nechells",
    "sg:city":"Birmingham",
    "sg:classifiers":[
        {
            "category":"Building & Trades",
            "subcategory":"Construction",
            "type":"Services"
        }
    ],
    "sg:postcode":"B7 4TS",
    "sg:province":"West Midlands",
    "sg:tags":[
        "roofing"
    ],
    "wof:name":"Apex Asphalt & Paving Co. Ltd.",
    "wof:placetype":"venue"
},
  "geometry": {"coordinates":[-1.869501,52.490807],"type":"Point"}
}