{
  "type": "Feature",
  "properties": {
    "addr:full":"16 Whitefield Road New Milton Hampshire BH25 6DF",
    "addr:housenumber":"16",
    "addr:postcode":"bh25 6df",
    "addr:street":"Whitefield Road",
    "iso:country":"GB",
    "sg:address":"16 Whitefield Road",
    "sg:city":"New Milton",
    "sg:classifiers":[
        {
            "category":"Insurance",
            "subcategory":"Insurance Agent",
            "type":"Services"
        },
        {
            "category":"Banks & Credit Unions",
            "subcategory":"Financial Services",
            "type":"Services"
        }
    ],
    "sg:postcode":"BH25 6DF",
    "sg:province":"Hampshire",
    "sg:tags":[
        "adviser"
    ],
    "wof:name":"Beresford Brokers",
    "wof:placetype":"venue"
},
  "geometry": {"coordinates":[-1.657703,50.755051],"type":"Point"}
}