{
  "type": "Feature",
  "properties": {
    "iso:country":"GB",
    "sg:address":"25 Rowlands Hill",
    "sg:city":"Wimborne",
    "sg:classifiers":[
        {
            "category":"Home & Garden",
            "subcategory":"Carpets & Floor Coverings",
            "type":"Retail Goods"
        }
    ],
    "sg:postcode":"BH21 2QQ",
    "sg:province":"Dorset",
    "sg:tags":[
        "carpets",
        "rug",
        "matting"
    ],
    "wof:name":"David R Sturgess",
    "wof:placetype":"venue"
},
  "geometry": {"coordinates":[-1.9766999483,50.8052101135],"type":"Point"}
}