{
  "type": "Feature",
  "properties": {
    "addr:full":"Rectory Close Shepperton Surrey TW17 0QE",
    "addr:postcode":"tw17 0qe",
    "addr:street":"Rectory Close",
    "iso:country":"GB",
    "sg:address":"Rectory Close",
    "sg:city":"Shepperton",
    "sg:classifiers":[
        {
            "category":"Place Of Worship",
            "type":"Public Place"
        }
    ],
    "sg:phone":"+44 1932 562249",
    "sg:postcode":"TW17 0QE",
    "sg:province":"Surrey",
    "wof:name":"St Mary Magdalene C Of E Church",
    "wof:placetype":"venue"
},
  "geometry": {"coordinates":[-0.461046,51.406456],"type":"Point"}
}