{
  "type": "Feature",
  "properties": {
    "addr:full":"178 High Street Ongar Essex CM5 9JJ",
    "addr:housenumber":"178",
    "addr:postcode":"cm5 9jj",
    "addr:street":"High Street",
    "iso:country":"GB",
    "sg:address":"178 High Street",
    "sg:city":"Ongar",
    "sg:classifiers":[
        {
            "category":"Shopping",
            "subcategory":"Clothing, Apparel, & Fashions",
            "type":"Retail Goods"
        }
    ],
    "sg:phone":"+44 1277 362582",
    "sg:postcode":"CM5 9JJ",
    "sg:province":"Essex",
    "sg:tags":[
        "haberdasher"
    ],
    "wof:name":"Blinds Bobbins & Spools",
    "wof:placetype":"venue"
},
  "geometry": {"coordinates":[0.245782,51.704739],"type":"Point"}
}