{
  "type": "Feature",
  "properties": {
    "addr:full":"7 Hillheads Road Whitley Bay Northumberland NE25 8HZ",
    "addr:housenumber":"7",
    "addr:postcode":"ne25 8hz",
    "addr:street":"Hillheads Road",
    "iso:country":"GB",
    "sg:address":"7 Hillheads Road",
    "sg:city":"Whitley Bay",
    "sg:classifiers":[
        {
            "category":"Building & Trades",
            "subcategory":"Construction",
            "type":"Services"
        }
    ],
    "sg:phone":"+44 191 252 0399",
    "sg:postcode":"NE25 8HZ",
    "sg:province":"Northumberland",
    "sg:tags":[
        "builder"
    ],
    "wof:name":"D & L Building Services",
    "wof:placetype":"venue"
},
  "geometry": {"coordinates":[-1.456172,55.035625],"type":"Point"}
}