{
  "type": "Feature",
  "properties": {
    "addr:full":"Po Box Hh35 Leeds West Yorkshire LS8 1XF",
    "addr:housenumber":"po",
    "addr:postcode":"ls8 1xf",
    "addr:street":"Box Hh35",
    "iso:country":"GB",
    "sg:address":"Po Box Hh35",
    "sg:city":"Leeds",
    "sg:classifiers":[
        {
            "category":"Sports & Exercise",
            "subcategory":"Race Track",
            "type":"Entertainment"
        }
    ],
    "sg:phone":"+44 113 237 0445",
    "sg:postcode":"LS8 1XF",
    "sg:province":"West Yorkshire",
    "sg:tags":[
        "motor"
    ],
    "wof:name":"Corsa Sport",
    "wof:placetype":"venue"
},
  "geometry": {"coordinates":[-1.51768,53.83543],"type":"Point"}
}