{
  "type": "Feature",
  "properties": {
    "iso:country":"GB",
    "sg:address":"New Bath Street",
    "sg:city":"Colne",
    "sg:classifiers":[
        {
            "category":"Autos & Motor Vehicles",
            "subcategory":"Automobile Sales",
            "type":"Retail Goods"
        }
    ],
    "sg:phone":"+44 1282 863896",
    "sg:postcode":"BB8 9LJ",
    "sg:province":"Lancashire",
    "sg:tags":[
        "car"
    ],
    "wof:name":"C J HARDIE & SON LTD",
    "wof:placetype":"venue"
},
  "geometry": {"coordinates":[-2.163399,53.860683],"type":"Point"}
}