{
  "type": "Feature",
  "properties": {
    "addr:full":"56-58 Westfield Lane Mansfield Derbyshire NG19 6AQ",
    "addr:housenumber":"56-58",
    "addr:postcode":"ng19 6aq",
    "addr:street":"Westfield Lane",
    "iso:country":"GB",
    "sg:address":"56-58 Westfield Lane",
    "sg:city":"Mansfield",
    "sg:classifiers":[
        {
            "category":"Shopping",
            "subcategory":"News",
            "type":"Retail Goods"
        }
    ],
    "sg:postcode":"NG19 6AQ",
    "sg:province":"Derbyshire",
    "sg:tags":[
        "newsagent"
    ],
    "wof:name":"Egginton News",
    "wof:placetype":"venue"
},
  "geometry": {"coordinates":[-1.2091289759,53.1497688293],"type":"Point"}
}