{
  "type": "Feature",
  "properties": {
    "iso:country":"GB",
    "sg:address":"343 Hall Road",
    "sg:city":"Sheffield",
    "sg:classifiers":[
        {
            "category":"Retail",
            "subcategory":"Repair Shop",
            "type":"Services"
        }
    ],
    "sg:postcode":"S9 4AF",
    "sg:province":"South Yorkshire",
    "sg:tags":[
        "upholsterer"
    ],
    "wof:name":"P James",
    "wof:placetype":"venue"
},
  "geometry": {"coordinates":[-1.3978190422,53.3803939819],"type":"Point"}
}