{
  "type": "Feature",
  "properties": {
    "iso:country":"GB",
    "sg:address":"120b High Street",
    "sg:city":"Maldon",
    "sg:classifiers":[
        {
            "category":"Organizations",
            "subcategory":"Political Organization",
            "type":"Services"
        }
    ],
    "sg:phone":"+44 1621 855663",
    "sg:postcode":"CM9 5ET",
    "sg:province":"Essex",
    "sg:tags":[
        "party"
    ],
    "wof:name":"Maldon & East Chelmsford Conservative Assocation",
    "wof:placetype":"venue"
},
  "geometry": {"coordinates":[0.681034,51.730679],"type":"Point"}
}