{
  "type": "Feature",
  "properties": {
    "iso:country":"GB",
    "sg:address":"122 High Street",
    "sg:city":"Burford",
    "sg:classifiers":[
        {
            "category":"Shopping",
            "subcategory":"Books",
            "type":"Retail Goods"
        }
    ],
    "sg:phone":"+44 1993 822539",
    "sg:postcode":"OX18 4QJ",
    "sg:province":"Gloucestershire",
    "sg:tags":[
        "bookseller",
        "retailer"
    ],
    "wof:name":"Red Lion Bookshop",
    "wof:placetype":"venue"
},
  "geometry": {"coordinates":[-1.636858,51.807423],"type":"Point"}
}