{
  "type": "Feature",
  "properties": {
    "addr:full":"64 & 64a Far Gosford Street Coventry West Midlands CV1 5DZ",
    "addr:housenumber":"64 & 64a",
    "addr:postcode":"cv1 5dz",
    "addr:street":"Far Gosford Street",
    "iso:country":"GB",
    "sg:address":"64 & 64a Far Gosford Street",
    "sg:city":"Coventry",
    "sg:classifiers":[
        {
            "category":"Building & Trades",
            "subcategory":"Plumbing",
            "type":"Services"
        }
    ],
    "sg:phone":"+44 24 7622 2314",
    "sg:postcode":"CV1 5DZ",
    "sg:province":"West Midlands",
    "sg:tags":[
        "merchant",
        "plumbers'"
    ],
    "wof:name":"Gosford Enterprises",
    "wof:placetype":"venue"
},
  "geometry": {"coordinates":[-1.494537,52.408096],"type":"Point"}
}