{
  "type": "Feature",
  "properties": {
    "addr:full":"1 Feus Rd Perth Perth and Kinross PH1 2AS",
    "addr:housenumber":"1",
    "addr:postcode":"ph1 2as",
    "addr:street":"Feus Rd",
    "iso:country":"GB",
    "sg:address":"1 Feus Rd",
    "sg:city":"Perth",
    "sg:classifiers":[
        {
            "category":"Shopping",
            "type":"Retail Goods"
        }
    ],
    "sg:postcode":"PH1 2AS",
    "sg:province":"Perth and Kinross",
    "sg:tags":[
        "merchant"
    ],
    "wof:name":"Holmes,Robert Alan,",
    "wof:placetype":"venue"
},
  "geometry": {"coordinates":[-3.45097,56.402554],"type":"Point"}
}