{
  "type": "Feature",
  "properties": {
    "addr:full":"Provost Sinclair Road Thurso Highland KW14 7AS",
    "addr:postcode":"kw14 7as",
    "addr:street":"Sinclair Road",
    "iso:country":"GB",
    "sg:address":"Provost Sinclair Road",
    "sg:city":"Thurso",
    "sg:classifiers":[
        {
            "category":"Food & Beverages",
            "subcategory":"Groceries & Convenience Stores",
            "type":"Retail Goods"
        }
    ],
    "sg:phone":"+44 1847 895266",
    "sg:postcode":"KW14 7AS",
    "sg:province":"Highland",
    "wof:name":"Murray Retail",
    "wof:placetype":"venue"
},
  "geometry": {"coordinates":[-3.540669,58.58868],"type":"Point"}
}