{
  "type": "Feature",
  "properties": {
    "iso:country":"GB",
    "sg:address":"The Ridge",
    "sg:city":"Hastings",
    "sg:classifiers":[
        {
            "category":"Retail",
            "subcategory":"Funeral Services",
            "type":"Services"
        }
    ],
    "sg:phone":"+44 1424 781302",
    "sg:postcode":"TN34 2AE",
    "sg:province":"East Sussex",
    "sg:tags":[
        "cemetery",
        "crematorium"
    ],
    "wof:name":"Hastings Crematorium",
    "wof:placetype":"venue"
},
  "geometry": {"coordinates":[0.570536,50.885952],"type":"Point"}
}