{
  "type": "Feature",
  "properties": {
    "addr:full":"35 Stanley Drive, Humberston Leicester Leicestershire LE5 1EB",
    "addr:housenumber":"35",
    "addr:postcode":"le5 1eb",
    "addr:street":"Stanley Drive",
    "iso:country":"GB",
    "sg:address":"35 Stanley Drive, Humberston",
    "sg:city":"Leicester",
    "sg:classifiers":[
        {
            "category":"Professional",
            "subcategory":"Engineering",
            "type":"Services"
        }
    ],
    "sg:phone":"+44 116 276 8196",
    "sg:postcode":"LE5 1EB",
    "sg:province":"Leicestershire",
    "sg:tags":[
        "gas",
        "engineer"
    ],
    "wof:name":"Colin Brown",
    "wof:placetype":"venue"
},
  "geometry": {"coordinates":[-1.0778460503,52.6449394226],"type":"Point"}
}