{
  "type": "Feature",
  "properties": {
    "addr:full":"Kings Mill, Kings Mill Lane, South Nutfield Redhill Surrey RH1 5NB",
    "addr:postcode":"rh1 5nb",
    "addr:street":"Kings Mill Kings Mill Lane",
    "iso:country":"GB",
    "sg:address":"Kings Mill, Kings Mill Lane, South Nutfield",
    "sg:city":"Redhill",
    "sg:classifiers":[
        {
            "category":"Professional",
            "subcategory":"Employment Agencies",
            "type":"Services"
        },
        {
            "category":"Professional",
            "subcategory":"Computer Services",
            "type":"Services"
        }
    ],
    "sg:phone":"+44 1737 822000",
    "sg:postcode":"RH1 5NB",
    "sg:province":"Surrey",
    "sg:tags":[
        "recruitment",
        "information",
        "consultant"
    ],
    "wof:name":"Butler International Ltd.",
    "wof:placetype":"venue"
},
  "geometry": {"coordinates":[-0.1413799971,51.225818634],"type":"Point"}
}