{
  "type": "Feature",
  "properties": {
    "addr:full":"West Marsh Road Spalding Lincolnshire PE11 2BB",
    "addr:postcode":"pe11 2bb",
    "addr:street":"West Marsh Road",
    "iso:country":"GB",
    "sg:address":"West Marsh Road",
    "sg:city":"Spalding",
    "sg:classifiers":[
        {
            "category":"Utilities",
            "subcategory":"Refuse",
            "type":"Services"
        }
    ],
    "sg:postcode":"PE11 2BB",
    "sg:province":"Lincolnshire",
    "sg:tags":[
        "disposal",
        "waste"
    ],
    "wof:name":"Cleanaway Ltd.",
    "wof:placetype":"venue"
},
  "geometry": {"coordinates":[-0.1333940029,52.80235672],"type":"Point"}
}