{
  "type": "Feature",
  "properties": {
    "addr:full":"Little Gilberts, Chapel Lane, Bransford Worcester Herefordshire WR6 5JQ",
    "addr:postcode":"wr6 5jq",
    "addr:street":"Little;Chapel Lane",
    "iso:country":"GB",
    "sg:address":"Little Gilberts, Chapel Lane, Bransford",
    "sg:city":"Worcester",
    "sg:classifiers":[
        {
            "category":"Banks & Credit Unions",
            "subcategory":"Investment Brokerage",
            "type":"Services"
        }
    ],
    "sg:postcode":"WR6 5JQ",
    "sg:province":"Herefordshire",
    "sg:tags":[
        "contractor"
    ],
    "wof:name":"David Pritchard",
    "wof:placetype":"venue"
},
  "geometry": {"coordinates":[-2.300011,52.171642],"type":"Point"}
}