{
  "type": "Feature",
  "properties": {
    "addr:full":"Moorswater Liskeard Cornwall PL14 4LG",
    "addr:postcode":"pl14 4lg",
    "addr:street":"Moorswater",
    "iso:country":"GB",
    "sg:address":"Moorswater",
    "sg:city":"Liskeard",
    "sg:classifiers":[
        {
            "category":"Professional",
            "subcategory":"Art Services",
            "type":"Services"
        }
    ],
    "sg:phone":"+44 1579 340340",
    "sg:postcode":"PL14 4LG",
    "sg:province":"Cornwall",
    "sg:tags":[
        "framing"
    ],
    "wof:name":"Manuscript Ltd.",
    "wof:placetype":"venue"
},
  "geometry": {"coordinates":[-4.465834,50.453796],"type":"Point"}
}