{
  "type": "Feature",
  "properties": {
    "addr:full":"36 Nelson St Dunfermline Fife KY11 2JU",
    "addr:housenumber":"36",
    "addr:postcode":"ky11 2ju",
    "addr:street":"Nelson St",
    "iso:country":"GB",
    "sg:address":"36 Nelson St",
    "sg:city":"Dunfermline",
    "sg:classifiers":[
        {
            "category":"Retail",
            "subcategory":"Driving School",
            "type":"Services"
        }
    ],
    "sg:phone":"+44 1383 418810",
    "sg:postcode":"KY11 2JU",
    "sg:province":"Fife",
    "wof:name":"Roadcraft Driving School",
    "wof:placetype":"venue"
},
  "geometry": {"coordinates":[-3.4246640205,56.0443534851],"type":"Point"}
}