{
  "type": "Feature",
  "properties": {
    "addr:full":"The Manse Wood Lane Dagenham Essex RM9 5SL",
    "addr:postcode":"rm9 5sl",
    "addr:street":"Wood Lane",
    "iso:country":"GB",
    "sg:address":"The Manse Wood Lane",
    "sg:city":"Dagenham",
    "sg:classifiers":[
        {
            "category":"Place Of Worship",
            "type":"Public Place"
        },
        {
            "category":"Organizations",
            "subcategory":"Non-profit Organization",
            "type":"Services"
        }
    ],
    "sg:phone":"+44 20 8592 4908",
    "sg:postcode":"RM9 5SL",
    "sg:province":"Essex",
    "sg:tags":[
        "charitable",
        "organisation",
        "charity"
    ],
    "sg:website":"http://www.woodlane.co.uk",
    "wof:name":"Wood Lane Baptist Church",
    "wof:placetype":"venue"
},
  "geometry": {"coordinates":[0.1312,51.5518],"type":"Point"}
}