{
  "type": "Feature",
  "properties": {
    "addr:full":"Plot 6 Sandgate Industrial Est, Mainsforth Terrace Hartlepool Durham TS25 1TZ",
    "addr:housenumber":"plot 6",
    "addr:postcode":"ts25 1tz",
    "addr:street":"Sandgate Industrial Est Mainsforth Terrace",
    "iso:country":"GB",
    "sg:address":"Plot 6 Sandgate Industrial Est, Mainsforth Terrace",
    "sg:city":"Hartlepool",
    "sg:classifiers":[
        {
            "category":"Professional",
            "type":"Services"
        }
    ],
    "sg:postcode":"TS25 1TZ",
    "sg:province":"Durham",
    "sg:tags":[
        "specialist",
        "coating"
    ],
    "wof:name":"Highlander Ltd",
    "wof:placetype":"venue"
},
  "geometry": {"coordinates":[-1.20121,54.676651],"type":"Point"}
}