{
  "type": "Feature",
  "properties": {
    "addr:full":"58 Cresswell Road Twickenham Greater London TW1 2DZ",
    "addr:housenumber":"58",
    "addr:postcode":"tw1 2dz",
    "addr:street":"Cresswell Road",
    "iso:country":"GB",
    "sg:address":"58 Cresswell Road",
    "sg:city":"Twickenham",
    "sg:classifiers":[
        {
            "category":"Banks & Credit Unions",
            "subcategory":"Bureau De Change",
            "type":"Services"
        }
    ],
    "sg:phone":"+44 20 8296 9110",
    "sg:postcode":"TW1 2DZ",
    "sg:province":"Greater London",
    "sg:tags":[
        "town",
        "consultant",
        "planning"
    ],
    "wof:name":"Rod Hamilton Associates",
    "wof:placetype":"venue"
},
  "geometry": {"coordinates":[-0.3081789911,51.4540710449],"type":"Point"}
}