{
  "type": "Feature",
  "properties": {
    "addr:full":"1 Tower Court, West Tower Street Carlisle Cumbria CA3 8QT",
    "addr:housenumber":"1",
    "addr:postcode":"ca3 8qt",
    "addr:street":"Tower Court West Tower Street",
    "iso:country":"GB",
    "sg:address":"1 Tower Court, West Tower Street",
    "sg:city":"Carlisle",
    "sg:classifiers":[
        {
            "category":"Manufacturing",
            "subcategory":"Tools & Machinery",
            "type":"Manufacturing & Wholesale Goods"
        }
    ],
    "sg:phone":"+44 1228 590055",
    "sg:postcode":"CA3 8QT",
    "sg:province":"Cumbria",
    "sg:tags":[
        "society",
        "friendly"
    ],
    "wof:name":"Insurewright (U K) Ltd.",
    "wof:placetype":"venue"
},
  "geometry": {"coordinates":[-2.9362390041,54.8963851929],"type":"Point"}
}