{
  "type": "Feature",
  "properties": {
    "iso:country":"GB",
    "sg:address":"3 Fentham Road, Hampton In Arden",
    "sg:city":"Solihull",
    "sg:classifiers":[
        {
            "category":"Professional",
            "subcategory":"Accounting & Tax Preparation",
            "type":"Services"
        }
    ],
    "sg:phone":"+44 1675 443001",
    "sg:postcode":"B92 0AY",
    "sg:province":"West Midlands",
    "sg:tags":[
        "accountant"
    ],
    "wof:name":"M D Mcferran & Co",
    "wof:placetype":"venue"
},
  "geometry": {"coordinates":[-1.69975,52.426292],"type":"Point"}
}