{
  "type": "Feature",
  "properties": {
    "addr:full":"38a Drury Lane Solihull West Midlands B91 3BG",
    "addr:housenumber":"38a",
    "addr:postcode":"b91 3bg",
    "addr:street":"Drury Lane",
    "iso:country":"GB",
    "sg:address":"38a Drury Lane",
    "sg:city":"Solihull",
    "sg:classifiers":[
        {
            "category":"Shopping",
            "subcategory":"Discount & Variety Stores",
            "type":"Retail Goods"
        }
    ],
    "sg:postcode":"B91 3BG",
    "sg:province":"West Midlands",
    "sg:tags":[
        "cleaning",
        "supply"
    ],
    "wof:name":"Allinson (Cleaning Materials) Ltd.",
    "wof:placetype":"venue"
},
  "geometry": {"coordinates":[-1.775445,52.413467],"type":"Point"}
}