{
  "type": "Feature",
  "properties": {
    "iso:country":"GB",
    "sg:address":"38a Drury Lane",
    "sg:city":"Solihull",
    "sg:classifiers":[
        {
            "category":"Shopping",
            "subcategory":"Discount & Variety Stores",
            "type":"Retail Goods"
        }
    ],
    "sg:postcode":"B91 3BG",
    "sg:province":"West Midlands",
    "sg:tags":[
        "cleaning",
        "supply"
    ],
    "wof:name":"Allinson (Cleaning Materials) Ltd.",
    "wof:placetype":"venue"
},
  "geometry": {"coordinates":[-1.775445,52.413467],"type":"Point"}
}