{
  "type": "Feature",
  "properties": {
    "addr:full":"15 The Hawthorns Epsom Surrey KT17 2QA",
    "addr:housenumber":"15",
    "addr:postcode":"kt17 2qa",
    "addr:street":"The Hawthorns",
    "iso:country":"GB",
    "sg:address":"15 The Hawthorns",
    "sg:city":"Epsom",
    "sg:classifiers":[
        {
            "category":"Professional",
            "subcategory":"Engineering",
            "type":"Services"
        }
    ],
    "sg:phone":"+44 20 8393 0403",
    "sg:postcode":"KT17 2QA",
    "sg:province":"Surrey",
    "sg:tags":[
        "contractor",
        "electrical",
        "engineer"
    ],
    "wof:name":"Humber,Dennis,",
    "wof:placetype":"venue"
},
  "geometry": {"coordinates":[-0.2485930026,51.3565940857],"type":"Point"}
}