{
  "type": "Feature",
  "properties": {
    "iso:country":"GB",
    "sg:address":"Parsonage Farm Oast, Seed Road, Newnham",
    "sg:city":"Sittingbourne",
    "sg:classifiers":[
        {
            "category":"Farming",
            "subcategory":"Vineyard",
            "type":"Manufacturing & Wholesale Goods"
        }
    ],
    "sg:phone":"+44 1795 890711",
    "sg:postcode":"ME9 0NA",
    "sg:province":"Kent",
    "wof:name":"Syndale Valley Vineyards",
    "wof:placetype":"venue"
},
  "geometry": {"coordinates":[0.800333,51.284489],"type":"Point"}
}