{
  "type": "Feature",
  "properties": {
    "iso:country":"GB",
    "sg:address":"39 Painswick Road",
    "sg:city":"Cheltenham",
    "sg:classifiers":[
        {
            "category":"Bars & Pubs",
            "type":"Food & Drink"
        }
    ],
    "sg:phone":"+44 1242 512176",
    "sg:postcode":"GL50 2EZ",
    "sg:province":"Gloucestershire",
    "sg:tags":[
        "pubs",
        "inn"
    ],
    "wof:name":"The Jolly Brewmaster",
    "wof:placetype":"venue"
},
  "geometry": {"coordinates":[-2.0829548836,51.8900871277],"type":"Point"}
}