{
  "type": "Feature",
  "properties": {
    "iso:country":"GB",
    "sg:address":"Unit, 1",
    "sg:city":"Leyton",
    "sg:classifiers":[
        {
            "category":"Manufacturing",
            "subcategory":"Food",
            "type":"Manufacturing & Wholesale Goods"
        }
    ],
    "sg:phone":"+44 20 8539 0232",
    "sg:postcode":"E10 7QP",
    "sg:province":"Greater London",
    "sg:tags":[
        "mnfr",
        "drink",
        "soft"
    ],
    "wof:name":"Toyo Ltd",
    "wof:placetype":"venue"
},
  "geometry": {"coordinates":[-0.038834,51.572708],"type":"Point"}
}