{
  "type": "Feature",
  "properties": {
    "iso:country":"GB",
    "sg:address":"32-38 Newbury St",
    "sg:city":"Wantage",
    "sg:classifiers":[
        {
            "category":"Shopping",
            "type":"Retail Goods"
        }
    ],
    "sg:phone":"+44 1235 770030",
    "sg:postcode":"OX12 8DD",
    "sg:province":"Berkshire",
    "sg:tags":[
        "part",
        "accessory"
    ],
    "wof:name":"Motorworld Volvo",
    "wof:placetype":"venue"
},
  "geometry": {"coordinates":[-1.426388979,51.586856842],"type":"Point"}
}