{
  "type": "Feature",
  "properties": {
    "addr:full":"Slitting Mill Waste Disposal, Eckington Road, Staverley Chesterfield Derbyshire S43 3YG",
    "addr:postcode":"s43 3yg",
    "addr:street":"Slitting;Eckington Road Staverley",
    "iso:country":"GB",
    "sg:address":"Slitting Mill Waste Disposal, Eckington Road, Staverley",
    "sg:city":"Chesterfield",
    "sg:classifiers":[
        {
            "category":"Utilities",
            "subcategory":"Refuse",
            "type":"Services"
        }
    ],
    "sg:phone":"+44 1246 202599",
    "sg:postcode":"S43 3YG",
    "sg:province":"Derbyshire",
    "sg:tags":[
        "skip",
        "hire"
    ],
    "wof:name":"M T Skips",
    "wof:placetype":"venue"
},
  "geometry": {"coordinates":[-1.3481600285,53.2756385803],"type":"Point"}
}