{
  "type": "Feature",
  "properties": {
    "addr:full":"Berry La Rickmansworth Hertfordshire WD3 2HG",
    "addr:postcode":"wd3 2hg",
    "addr:street":"Berry;Rickmansworth",
    "iso:country":"GB",
    "sg:address":"Berry La",
    "sg:city":"Rickmansworth",
    "sg:classifiers":[
        {
            "category":"Place Of Worship",
            "type":"Public Place"
        }
    ],
    "sg:phone":"+44 1923 779890",
    "sg:postcode":"WD3 2HG",
    "sg:province":"Hertfordshire",
    "wof:name":"St Johns The Evangelist",
    "wof:placetype":"venue"
},
  "geometry": {"coordinates":[-0.4970490038,51.6472587585],"type":"Point"}
}