{
  "type": "Feature",
  "properties": {
    "iso:country":"GB",
    "sg:address":"Evegate Craft Centre, Station Road, Smeeth",
    "sg:city":"Ashford",
    "sg:classifiers":[
        {
            "category":"Deli",
            "type":"Food & Drink"
        }
    ],
    "sg:phone":"+44 1303 814692",
    "sg:postcode":"TN25 6SX",
    "sg:province":"Kent",
    "sg:tags":[
        "delicatessen"
    ],
    "wof:name":"Mrs Beaton's Coffee Shop",
    "wof:placetype":"venue"
},
  "geometry": {"coordinates":[0.959259,51.118454],"type":"Point"}
}