{
  "type": "Feature",
  "properties": {
    "addr:full":"22 Wharfside, Bletchley Milton Keynes Buckinghamshire MK2 2AZ",
    "addr:housenumber":"22",
    "addr:postcode":"mk2 2az",
    "addr:street":"Wharfside",
    "iso:country":"GB",
    "sg:address":"22 Wharfside, Bletchley",
    "sg:city":"Milton Keynes",
    "sg:classifiers":[
        {
            "category":"Professional",
            "subcategory":"Advertising",
            "type":"Services"
        }
    ],
    "sg:phone":"+44 1908 640579",
    "sg:postcode":"MK2 2AZ",
    "sg:province":"Buckinghamshire",
    "sg:tags":[
        "agency"
    ],
    "wof:name":"Plascraft Design & Marketing Ltd",
    "wof:placetype":"venue"
},
  "geometry": {"coordinates":[-0.71526,51.997253],"type":"Point"}
}