{
  "type": "Feature",
  "properties": {
    "iso:country":"GB",
    "sg:address":"178 Robin Hood Lane, Hall Grn",
    "sg:city":"Birmingham",
    "sg:classifiers":[
        {
            "category":"Farming",
            "subcategory":"Nursery",
            "type":"Manufacturing & Wholesale Goods"
        },
        {
            "category":"Social Services",
            "subcategory":"Child Care",
            "type":"Services"
        }
    ],
    "sg:phone":"+44 121 608 5552",
    "sg:postcode":"B28 0LG",
    "sg:province":"West Midlands",
    "sg:tags":[
        "creche"
    ],
    "wof:name":"Little Robins Day Nursery",
    "wof:placetype":"venue"
},
  "geometry": {"coordinates":[-1.847530961,52.4236907959],"type":"Point"}
}