{
  "type": "Feature",
  "properties": {
    "addr:full":"Ombersley Way Droitwich Worcestershire WR9 0AA",
    "addr:postcode":"wr9 0aa",
    "addr:street":"Ombersley Way",
    "iso:country":"GB",
    "sg:address":"Ombersley Way",
    "sg:city":"Droitwich",
    "sg:classifiers":[
        {
            "category":"Education",
            "subcategory":"School",
            "type":"Public Place"
        }
    ],
    "sg:phone":"+44 1905 772795",
    "sg:postcode":"WR9 0AA",
    "sg:province":"Worcestershire",
    "sg:tags":[
        "local",
        "authority"
    ],
    "wof:name":"Westacre Middle School",
    "wof:placetype":"venue"
},
  "geometry": {"coordinates":[-2.176369,52.263199],"type":"Point"}
}