{
  "type": "Feature",
  "properties": {
    "addr:full":"Horn Hill Lowestoft Suffolk NR33 0PX",
    "addr:postcode":"nr33 0px",
    "addr:street":"Horn Hill",
    "iso:country":"GB",
    "sg:address":"Horn Hill",
    "sg:city":"Lowestoft",
    "sg:classifiers":[
        {
            "category":"Autos & Motor Vehicles",
            "subcategory":"Automobile Sales",
            "type":"Retail Goods"
        }
    ],
    "sg:phone":"+44 1502 573955",
    "sg:postcode":"NR33 0PX",
    "sg:province":"Suffolk",
    "sg:tags":[
        "car"
    ],
    "wof:name":"M R King & Sons",
    "wof:placetype":"venue"
},
  "geometry": {"coordinates":[1.7415499687,52.4706382751],"type":"Point"}
}