{
  "type": "Feature",
  "properties": {
    "addr:full":"Farm Shop, Holbeach Road Spalding Cambridgeshire PE12 6JR",
    "addr:postcode":"pe12 6jr",
    "addr:street":"Holbeach Road Spalding",
    "iso:country":"GB",
    "sg:address":"Farm Shop, Holbeach Road",
    "sg:city":"Spalding",
    "sg:classifiers":[
        {
            "category":"Food & Beverages",
            "subcategory":"Farmers Market",
            "type":"Retail Goods"
        }
    ],
    "sg:phone":"+44 1775 761699",
    "sg:postcode":"PE12 6JR",
    "sg:province":"Cambridgeshire",
    "sg:tags":[
        "farm",
        "shop",
        "pyo"
    ],
    "wof:name":"T & B Holden",
    "wof:placetype":"venue"
},
  "geometry": {"coordinates":[-0.1108300015,52.8013000488],"type":"Point"}
}