{
  "type": "Feature",
  "properties": {
    "iso:country":"GB",
    "sg:address":"2 Bendon Valley, Wandsworth",
    "sg:city":"London",
    "sg:classifiers":[
        {
            "category":"Wholesale",
            "subcategory":"Scrap",
            "type":"Manufacturing & Wholesale Goods"
        }
    ],
    "sg:phone":"+44 20 8874 1523",
    "sg:postcode":"SW18 4LZ",
    "sg:province":"Greater London",
    "sg:tags":[
        "waste",
        "metal"
    ],
    "wof:name":"D Goldsmith Ltd.",
    "wof:placetype":"venue"
},
  "geometry": {"coordinates":[-0.191315,51.446495],"type":"Point"}
}