{
  "type": "Feature",
  "properties": {
    "iso:country":"GB",
    "sg:address":"Factory 6 Maidstone Road",
    "sg:city":"Leicester",
    "sg:classifiers":[
        {
            "category":"Building & Trades",
            "subcategory":"Construction",
            "type":"Services"
        }
    ],
    "sg:phone":"+44 116 262 6492",
    "sg:postcode":"LE2 0BA",
    "sg:province":"Leicestershire",
    "sg:tags":[
        "welder",
        "welding"
    ],
    "wof:name":"A J Sosbe",
    "wof:placetype":"venue"
},
  "geometry": {"coordinates":[-1.11706,52.63586],"type":"Point"}
}