{
  "type": "Feature",
  "properties": {
    "addr:full":"37 London Road Portsmouth Hampshire PO2 0BH",
    "addr:housenumber":"37",
    "addr:postcode":"hampshire po2 0bh",
    "addr:street":"London Road",
    "iso:country":"GB",
    "sg:address":"37 London Road",
    "sg:city":"Portsmouth",
    "sg:classifiers":[
        {
            "category":"Shopping",
            "subcategory":"Comic Books",
            "type":"Retail Goods"
        }
    ],
    "sg:phone":"+44 23 9269 8714",
    "sg:postcode":"PO2 0BH",
    "sg:province":"Hampshire",
    "sg:tags":[
        "jeweller",
        "sale",
        "jewellery"
    ],
    "wof:name":"Goulds Jewellers",
    "wof:placetype":"venue"
},
  "geometry": {"coordinates":[-1.080094,50.814377],"type":"Point"}
}