{
  "type": "Feature",
  "properties": {
    "addr:full":"18 Lansdowne Circus Leamington Spa Warwickshire CV32 4SW",
    "addr:housenumber":"18",
    "addr:postcode":"cv32 4sw",
    "addr:street":"Lansdowne Circus",
    "iso:country":"GB",
    "sg:address":"18 Lansdowne Circus",
    "sg:city":"Leamington Spa",
    "sg:classifiers":[
        {
            "category":"Professional",
            "subcategory":"Computer Services",
            "type":"Services"
        }
    ],
    "sg:phone":"+44 1926 452315",
    "sg:postcode":"CV32 4SW",
    "sg:province":"Warwickshire",
    "sg:tags":[
        "system",
        "software"
    ],
    "wof:name":"Leamington Database Programming",
    "wof:placetype":"venue"
},
  "geometry": {"coordinates":[-1.5276069641,52.292224884],"type":"Point"}
}