{
  "type": "Feature",
  "properties": {
    "addr:full":"11 Market Place, Thorne Doncaster East Riding of Yorkshire DN8 5DG",
    "addr:housenumber":"11",
    "addr:postcode":"dn8 5dg",
    "addr:street":"Market Place;Riding",
    "iso:country":"GB",
    "sg:address":"11 Market Place, Thorne",
    "sg:city":"Doncaster",
    "sg:classifiers":[
        {
            "category":"Cafe",
            "type":"Food & Drink"
        }
    ],
    "sg:phone":"+44 1405 814045",
    "sg:postcode":"DN8 5DG",
    "sg:province":"East Riding of Yorkshire",
    "sg:tags":[
        "tea",
        "snack",
        "bar",
        "room"
    ],
    "wof:name":"Treadle Cafe",
    "wof:placetype":"venue"
},
  "geometry": {"coordinates":[-0.961637,53.611591],"type":"Point"}
}