{
  "type": "Feature",
  "properties": {
    "iso:country":"GB",
    "sg:address":"The End Barn, Milland La, Milland",
    "sg:city":"Liphook",
    "sg:classifiers":[
        {
            "category":"Professional",
            "subcategory":"Management & Consulting",
            "type":"Services"
        }
    ],
    "sg:postcode":"GU30 7JN",
    "sg:province":"Hampshire",
    "sg:tags":[
        "consultant",
        "business"
    ],
    "wof:name":"Lumley,Sarah,",
    "wof:placetype":"venue"
},
  "geometry": {"coordinates":[-0.7991999984,51.0776405334],"type":"Point"}
}