{
  "type": "Feature",
  "properties": {
    "iso:country":"GB",
    "sg:address":"227 Iffley Rd",
    "sg:city":"Oxford",
    "sg:classifiers":[
        {
            "category":"Travel",
            "subcategory":"Hotels & Motels",
            "type":"Entertainment"
        }
    ],
    "sg:phone":"+44 1865 249520",
    "sg:postcode":"OX4 1SQ",
    "sg:province":"Oxfordshire",
    "sg:tags":[
        "house",
        "guest"
    ],
    "wof:name":"Melcombe House",
    "wof:placetype":"venue"
},
  "geometry": {"coordinates":[-1.237948,51.742138],"type":"Point"}
}