{
  "type": "Feature",
  "properties": {
    "addr:full":"12-14 Camden Road Tunbridge Wells Kent TN1 2PT",
    "addr:housenumber":"12-14",
    "addr:postcode":"tn1 2pt",
    "addr:street":"Camden Road",
    "iso:country":"GB",
    "sg:address":"12-14 Camden Road",
    "sg:city":"Tunbridge Wells",
    "sg:classifiers":[
        {
            "category":"Restaurant",
            "type":"Food & Drink"
        }
    ],
    "sg:postcode":"TN1 2PT",
    "sg:province":"Kent",
    "wof:name":"Delicious 2",
    "wof:placetype":"venue"
},
  "geometry": {"coordinates":[0.2674320042,51.1344947815],"type":"Point"}
}