{
  "type": "Feature",
  "properties": {
    "addr:full":"26 Buxton Street, Ardwick Manchester Greater Manchester M1 2PT",
    "addr:housenumber":"26",
    "addr:postcode":"m1 2pt",
    "addr:street":"Buxton Street",
    "iso:country":"GB",
    "sg:address":"26 Buxton Street, Ardwick",
    "sg:city":"Manchester",
    "sg:classifiers":[
        {
            "category":"Professional",
            "subcategory":"Printing & Photocopies",
            "type":"Services"
        }
    ],
    "sg:phone":"+44 161 273 5830",
    "sg:postcode":"M1 2PT",
    "sg:province":"Greater Manchester",
    "sg:tags":[
        "process",
        "screen",
        "printer"
    ],
    "wof:name":"Delprint Display Ltd.",
    "wof:placetype":"venue"
},
  "geometry": {"coordinates":[-2.229152,53.474842],"type":"Point"}
}