{
  "type": "Feature",
  "properties": {
    "iso:country":"GB",
    "sg:address":"122 Hatherley Court, Hatherley Grove",
    "sg:city":"London",
    "sg:classifiers":[
        {
            "category":"Professional",
            "subcategory":"Computer Services",
            "type":"Services"
        }
    ],
    "sg:postcode":"W2 5RG",
    "sg:province":"Greater London",
    "sg:tags":[
        "system",
        "software"
    ],
    "wof:name":"Sabreen Ltd",
    "wof:placetype":"venue"
},
  "geometry": {"coordinates":[-0.18925,51.515984],"type":"Point"}
}