{
  "type": "Feature",
  "properties": {
    "addr:full":"19 Southwell Rd Rochester Kent ME2 2RS",
    "addr:housenumber":"19",
    "addr:postcode":"me2 2rs",
    "addr:street":"Southwell Rd",
    "iso:country":"GB",
    "sg:address":"19 Southwell Rd",
    "sg:city":"Rochester",
    "sg:classifiers":[
        {
            "category":"Professional",
            "subcategory":"Computer Services",
            "type":"Services"
        }
    ],
    "sg:phone":"+44 1634 717444",
    "sg:postcode":"ME2 2RS",
    "sg:province":"Kent",
    "sg:tags":[
        "consultant"
    ],
    "wof:name":"Infinite IT Ltd",
    "wof:placetype":"venue"
},
  "geometry": {"coordinates":[0.462975,51.390911],"type":"Point"}
}