{
  "type": "Feature",
  "properties": {
    "addr:full":"41 Matlock Crescent Sutton Surrey SM3 9SS",
    "addr:housenumber":"41",
    "addr:postcode":"sm3 9ss",
    "addr:street":"Matlock Crescent",
    "iso:country":"GB",
    "sg:address":"41 Matlock Crescent",
    "sg:city":"Sutton",
    "sg:classifiers":[
        {
            "category":"Building & Trades",
            "subcategory":"Construction",
            "type":"Services"
        }
    ],
    "sg:phone":"+44 20 8395 0833",
    "sg:postcode":"SM3 9SS",
    "sg:province":"Surrey",
    "sg:tags":[
        "builder"
    ],
    "wof:name":"Gary Cook Carpenter & Builder",
    "wof:placetype":"venue"
},
  "geometry": {"coordinates":[-0.2149319947,51.3676643372],"type":"Point"}
}