{
  "type": "Feature",
  "properties": {
    "addr:full":"44-45 Church Street Twickenham Greater London TW1 2NT",
    "addr:housenumber":"44-45",
    "addr:postcode":"tw1 2nt",
    "addr:street":"Church Street",
    "iso:country":"GB",
    "sg:address":"44-45 Church Street",
    "sg:city":"Twickenham",
    "sg:classifiers":[
        {
            "category":"Shopping",
            "subcategory":"Books",
            "type":"Retail Goods"
        }
    ],
    "sg:phone":"+44 20 8892 3800",
    "sg:postcode":"TW1 2NT",
    "sg:province":"Greater London",
    "sg:tags":[
        "bookseller"
    ],
    "wof:name":"Douglas Jeffers",
    "wof:placetype":"venue"
},
  "geometry": {"coordinates":[-0.3268,51.446716],"type":"Point"}
}