{
  "type": "Feature",
  "properties": {
    "addr:full":"Threshers, Hastingwood Road Harlow Essex CM17 9JT",
    "addr:postcode":"cm17 9jt",
    "addr:street":"Hastingwood Road",
    "iso:country":"GB",
    "sg:address":"Threshers, Hastingwood Road",
    "sg:city":"Harlow",
    "sg:classifiers":[
        {
            "category":"Home & Garden",
            "subcategory":"Garden Supply",
            "type":"Retail Goods"
        }
    ],
    "sg:phone":"+44 1279 422978",
    "sg:postcode":"CM17 9JT",
    "sg:province":"Essex",
    "sg:tags":[
        "sand",
        "gravel"
    ],
    "wof:name":"F Darlington Ltd.",
    "wof:placetype":"venue"
},
  "geometry": {"coordinates":[0.1556899995,51.7497825623],"type":"Point"}
}