{
  "type": "Feature",
  "properties": {
    "addr:full":"30 Burrel Road St Ives Cambridgeshire PE27 3NF",
    "addr:housenumber":"30",
    "addr:postcode":"pe27 3nf",
    "addr:street":"Burrel Road",
    "iso:country":"GB",
    "sg:address":"30 Burrel Road",
    "sg:city":"St Ives",
    "sg:classifiers":[
        {
            "category":"Manufacturing",
            "subcategory":"Electronics",
            "type":"Manufacturing & Wholesale Goods"
        },
        {
            "category":"Shopping",
            "subcategory":"Computers & Home Electronics",
            "type":"Retail Goods"
        }
    ],
    "sg:phone":"+44 1480 462225",
    "sg:postcode":"PE27 3NF",
    "sg:province":"Cambridgeshire",
    "sg:tags":[
        "component",
        "mnfr",
        "assembly",
        "electronic",
        "equipment"
    ],
    "wof:name":"Prism Electronics Ltd.",
    "wof:placetype":"venue"
},
  "geometry": {"coordinates":[-0.0645439997,52.33826828],"type":"Point"}
}