{
  "type": "Feature",
  "properties": {
    "addr:full":"10 Glanvilles Rd Ivybridge Devon PL21 9PS",
    "addr:housenumber":"10",
    "addr:postcode":"pl21 9ps",
    "addr:street":"Glanvilles Rd",
    "iso:country":"GB",
    "sg:address":"10 Glanvilles Rd",
    "sg:city":"Ivybridge",
    "sg:classifiers":[
        {
            "category":"Shopping",
            "subcategory":"News",
            "type":"Retail Goods"
        }
    ],
    "sg:postcode":"PL21 9PS",
    "sg:province":"Devon",
    "sg:tags":[
        "newsagent"
    ],
    "wof:name":"Riverside News",
    "wof:placetype":"venue"
},
  "geometry": {"coordinates":[-3.9208319187,50.3888626099],"type":"Point"}
}