{
  "type": "Feature",
  "properties": {
    "addr:full":"Bepton Rd Midhurst West Sussex GU29 9QX",
    "addr:postcode":"gu29 9qx",
    "addr:street":"Bepton Rd",
    "iso:country":"GB",
    "sg:address":"Bepton Rd",
    "sg:city":"Midhurst",
    "sg:classifiers":[
        {
            "category":"Professional",
            "subcategory":"Management & Consulting",
            "type":"Services"
        }
    ],
    "sg:phone":"+44 1730 810935",
    "sg:postcode":"GU29 9QX",
    "sg:province":"West Sussex",
    "sg:tags":[
        "conservation"
    ],
    "wof:name":"Rother Valley Project",
    "wof:placetype":"venue"
},
  "geometry": {"coordinates":[-0.7401419878,50.9853134155],"type":"Point"}
}