{
  "type": "Feature",
  "properties": {
    "iso:country":"GB",
    "sg:address":"Leese Hill, Kingstone",
    "sg:city":"Uttoxeter",
    "sg:classifiers":[
        {
            "category":"Sports & Exercise",
            "subcategory":"Golf",
            "type":"Entertainment"
        }
    ],
    "sg:phone":"+44 1889 563234",
    "sg:postcode":"ST14 8QT",
    "sg:province":"Derbyshire",
    "sg:tags":[
        "club",
        "course"
    ],
    "wof:name":"The Manor Golf Club",
    "wof:placetype":"venue"
},
  "geometry": {"coordinates":[-1.912179,52.863819],"type":"Point"}
}