{
  "type": "Feature",
  "properties": {
    "addr:full":"Centurion Park, Northam Bridge Road Southampton Hampshire SO18 1UB",
    "addr:postcode":"so18 1ub",
    "addr:street":"Park;Bridge Road",
    "iso:country":"GB",
    "sg:address":"Centurion Park, Northam Bridge Road",
    "sg:city":"Southampton",
    "sg:classifiers":[
        {
            "category":"Sports & Exercise",
            "subcategory":"Gym",
            "type":"Entertainment"
        }
    ],
    "sg:postcode":"SO18 1UB",
    "sg:province":"Hampshire",
    "sg:tags":[
        "fitness",
        "health",
        "centre"
    ],
    "wof:name":"Zone Aerobic & Fitness Centre",
    "wof:placetype":"venue"
},
  "geometry": {"coordinates":[-1.38536,50.916889],"type":"Point"}
}