{
  "type": "Feature",
  "properties": {
    "addr:full":"6 High Street Menai Bridge Isle of Anglesey LL59 5ED",
    "addr:housenumber":"6",
    "addr:postcode":"ll59 5ed",
    "addr:street":"High Street",
    "iso:country":"GB",
    "sg:address":"6 High Street",
    "sg:city":"Menai Bridge",
    "sg:classifiers":[
        {
            "category":"Home & Garden",
            "subcategory":"Hardware",
            "type":"Retail Goods"
        }
    ],
    "sg:phone":"+44 1248 712388",
    "sg:postcode":"LL59 5ED",
    "sg:province":"Isle of Anglesey",
    "sg:tags":[
        "merchant",
        "ironmonger"
    ],
    "wof:name":"Evans Bros",
    "wof:placetype":"venue"
},
  "geometry": {"coordinates":[-4.162164,53.227379],"type":"Point"}
}