{
  "type": "Feature",
  "properties": {
    "iso:country":"GB",
    "sg:address":">, 20 Bridge Street",
    "sg:city":"Bridlington",
    "sg:classifiers":[
        {
            "category":"Shopping",
            "subcategory":"Jewelry",
            "type":"Retail Goods"
        },
        {
            "category":"Shopping",
            "subcategory":"Comic Books",
            "type":"Retail Goods"
        }
    ],
    "sg:phone":"+44 1262 673893",
    "sg:postcode":"YO15 3AJ",
    "sg:province":"East Riding of Yorkshire",
    "sg:tags":[
        "jeweller",
        "sale",
        "jewellery"
    ],
    "wof:name":"Brittons Jewellers",
    "wof:placetype":"venue"
},
  "geometry": {"coordinates":[-0.193085,54.081879],"type":"Point"}
}