{
  "type": "Feature",
  "properties": {
    "iso:country":"GB",
    "sg:address":"92 Elthorne Park Rd",
    "sg:city":"Hanwell",
    "sg:classifiers":[
        {
            "category":"Shopping",
            "subcategory":"Pharmacy",
            "type":"Retail Goods"
        }
    ],
    "sg:phone":"+44 20 8567 1711",
    "sg:postcode":"W7 2JD",
    "sg:province":"Greater London",
    "sg:tags":[
        "pharmacist",
        "chemist"
    ],
    "wof:name":"Midhurst Pharmacy",
    "wof:placetype":"venue"
},
  "geometry": {"coordinates":[-0.327104,51.503582],"type":"Point"}
}