{
  "type": "Feature",
  "properties": {
    "addr:full":"Greenhill Health Centre, Church Street Lichfield Staffordshire WS13 6JL",
    "addr:postcode":"ws13 6jl",
    "addr:street":"Church Street",
    "iso:country":"GB",
    "sg:address":"Greenhill Health Centre, Church Street",
    "sg:city":"Lichfield",
    "sg:classifiers":[
        {
            "category":"Shopping",
            "subcategory":"Pharmacy",
            "type":"Retail Goods"
        }
    ],
    "sg:phone":"+44 1922 721255",
    "sg:postcode":"WS13 6JL",
    "sg:province":"Staffordshire",
    "sg:tags":[
        "pharmacist",
        "chemist"
    ],
    "wof:name":"Lichpharm Ltd.",
    "wof:placetype":"venue"
},
  "geometry": {"coordinates":[-1.8196599483,52.6840286255],"type":"Point"}
}