{
  "type": "Feature",
  "properties": {
    "iso:country":"GB",
    "sg:address":"6 Cambridge Pde, Great Cambridge Rd",
    "sg:city":"Enfield",
    "sg:classifiers":[
        {
            "category":"Health Services",
            "subcategory":"Health Practitioner",
            "type":"Services"
        }
    ],
    "sg:phone":"+44 20 8367 0321",
    "sg:postcode":"EN1 4JU",
    "sg:province":"Greater London",
    "sg:tags":[
        "physiotherapist"
    ],
    "wof:name":"Varney Physiotherapy Clinic The",
    "wof:placetype":"venue"
},
  "geometry": {"coordinates":[-0.058219,51.660648],"type":"Point"}
}