{
  "type": "Feature",
  "properties": {
    "iso:country":"GB",
    "sg:address":"The Versapak Centre, Centurion Way",
    "sg:city":"Erith",
    "sg:classifiers":[
        {
            "category":"Shopping",
            "subcategory":"Stationery & Office Supplies",
            "type":"Retail Goods"
        },
        {
            "category":"Professional",
            "subcategory":"Printing & Photocopies",
            "type":"Services"
        }
    ],
    "sg:postcode":"DA18 4AF",
    "sg:province":"Kent",
    "sg:tags":[
        "printer"
    ],
    "wof:name":"Versapak (Management Services) Ltd.",
    "wof:placetype":"venue"
},
  "geometry": {"coordinates":[0.1449500024,51.4939689636],"type":"Point"}
}