{
  "type": "Feature",
  "properties": {
    "iso:country":"GB",
    "sg:address":"53 Tonbridge Road, Hildenborough",
    "sg:city":"Tonbridge",
    "sg:classifiers":[
        {
            "category":"Building & Trades",
            "subcategory":"Construction",
            "type":"Services"
        }
    ],
    "sg:phone":"+44 1732 838635",
    "sg:postcode":"TN11 9BH",
    "sg:province":"Kent",
    "sg:tags":[
        "decorator",
        "painter"
    ],
    "wof:name":"J B Crisp",
    "wof:placetype":"venue"
},
  "geometry": {"coordinates":[0.25854,51.208267],"type":"Point"}
}