{
  "type": "Feature",
  "properties": {
    "addr:full":"356 Sharrow Vale Road Sheffield Derbyshire S11 8ZP",
    "addr:housenumber":"356",
    "addr:postcode":"s11 8zp",
    "addr:street":"Sharrow Vale Road",
    "iso:country":"GB",
    "sg:address":"356 Sharrow Vale Road",
    "sg:city":"Sheffield",
    "sg:classifiers":[
        {
            "category":"Banks & Credit Unions",
            "subcategory":"Financial Services",
            "type":"Services"
        }
    ],
    "sg:phone":"+44 114 268 4300",
    "sg:postcode":"S11 8ZP",
    "sg:province":"Derbyshire",
    "sg:tags":[
        "consultant"
    ],
    "wof:name":"Chantrey Financial Management",
    "wof:placetype":"venue"
},
  "geometry": {"coordinates":[-1.499875,53.367447],"type":"Point"}
}