{
  "type": "Feature",
  "properties": {
    "iso:country":"GB",
    "sg:address":"3 Elm Grove",
    "sg:city":"Hayling Island",
    "sg:classifiers":[
        {
            "category":"Professional",
            "subcategory":"Printing & Photocopies",
            "type":"Services"
        }
    ],
    "sg:phone":"+44 23 9246 3247",
    "sg:postcode":"PO11 9EA",
    "sg:province":"Hampshire",
    "sg:tags":[
        "printer"
    ],
    "wof:name":"Gridley Printers Ltd",
    "wof:placetype":"venue"
},
  "geometry": {"coordinates":[-0.977267,50.788292],"type":"Point"}
}