{
  "type": "Feature",
  "properties": {
    "addr:full":"238 Moorfields Sheffield South Yorkshire S3 8UH",
    "addr:housenumber":"238",
    "addr:postcode":"s3 8uh",
    "addr:street":"Moorfields",
    "iso:country":"GB",
    "sg:address":"238 Moorfields",
    "sg:city":"Sheffield",
    "sg:classifiers":[
        {
            "category":"Cafe",
            "type":"Food & Drink"
        }
    ],
    "sg:phone":"+44 114 275 5133",
    "sg:postcode":"S3 8UH",
    "sg:province":"South Yorkshire",
    "sg:tags":[
        "tea",
        "room"
    ],
    "wof:name":"Shalesmoor Cafe",
    "wof:placetype":"venue"
},
  "geometry": {"coordinates":[-1.4743260145,53.3875465393],"type":"Point"}
}