{
  "type": "Feature",
  "properties": {
    "addr:full":"12 Bosworgey Close St Columb Cornwall TR9 6SH",
    "addr:housenumber":"12",
    "addr:postcode":"tr9 6sh",
    "addr:street":"Bosworgey Close",
    "iso:country":"GB",
    "sg:address":"12 Bosworgey Close",
    "sg:city":"St Columb",
    "sg:classifiers":[
        {
            "category":"Professional",
            "subcategory":"Engineering",
            "type":"Services"
        }
    ],
    "sg:postcode":"TR9 6SH",
    "sg:province":"Cornwall",
    "sg:tags":[
        "gas",
        "engineer"
    ],
    "wof:name":"Cornish Gas Services",
    "wof:placetype":"venue"
},
  "geometry": {"coordinates":[-4.947814,50.432915],"type":"Point"}
}