{
  "type": "Feature",
  "properties": {
    "iso:country":"GB",
    "sg:address":"Nether Ley Avenue, Chapeltown",
    "sg:city":"Sheffield",
    "sg:classifiers":[
        {
            "category":"Education",
            "subcategory":"Library",
            "type":"Public Place"
        },
        {
            "category":"Government",
            "subcategory":"Office",
            "type":"Public Place"
        }
    ],
    "sg:phone":"+44 114 203 7000",
    "sg:postcode":"S35 1AE",
    "sg:province":"South Yorkshire",
    "sg:tags":[
        "book",
        "local"
    ],
    "wof:name":"SHEFFIELD CITY COUNCIL",
    "wof:placetype":"venue"
},
  "geometry": {"coordinates":[-1.480164,53.461819],"type":"Point"}
}