{
  "type": "Feature",
  "properties": {
    "iso:country":"GB",
    "sg:address":"Craven House, 16 Northumberland Avenue",
    "sg:city":"London",
    "sg:classifiers":[
        {
            "category":"Professional",
            "subcategory":"Accounting & Tax Preparation",
            "type":"Services"
        }
    ],
    "sg:phone":"+44 20 7930 7700",
    "sg:postcode":"WC2N 5AP",
    "sg:province":"Greater London",
    "sg:tags":[
        "accountant"
    ],
    "wof:name":"Charles P Fairweather",
    "wof:placetype":"venue"
},
  "geometry": {"coordinates":[-0.123997,51.506927],"type":"Point"}
}