{
  "type": "Feature",
  "properties": {
    "iso:country":"GB",
    "sg:address":"Long Furlong Farm, Coton Road",
    "sg:city":"Swadlincote",
    "sg:classifiers":[
        {
            "category":"Farming",
            "subcategory":"Livestock Farm",
            "type":"Manufacturing & Wholesale Goods"
        }
    ],
    "sg:postcode":"DE12 8HN",
    "sg:province":"Derbyshire",
    "sg:tags":[
        "others"
    ],
    "wof:name":"Philip Hill & Co.",
    "wof:placetype":"venue"
},
  "geometry": {"coordinates":[-1.63712,52.74017],"type":"Point"}
}