{
  "type": "Feature",
  "properties": {
    "iso:country":"GB",
    "sg:address":"Station Road, Greenfield",
    "sg:city":"Holywell",
    "sg:classifiers":[
        {
            "category":"Wholesale",
            "subcategory":"Scrap",
            "type":"Manufacturing & Wholesale Goods"
        }
    ],
    "sg:phone":"+44 1352 714495",
    "sg:postcode":"CH8 7EL",
    "sg:province":"Denbighshire",
    "sg:tags":[
        "waste",
        "metal"
    ],
    "wof:name":"J Chadwick Scrap Matals",
    "wof:placetype":"venue"
},
  "geometry": {"coordinates":[-3.225195,53.274548],"type":"Point"}
}