{
  "type": "Feature",
  "properties": {
    "iso:country":"GB",
    "sg:address":"16 High St",
    "sg:city":"Rhyl",
    "sg:classifiers":[
        {
            "category":"Sports & Exercise",
            "subcategory":"Sports Center",
            "type":"Entertainment"
        }
    ],
    "sg:postcode":"LL18 1ES",
    "sg:province":"Conwy",
    "sg:tags":[
        "shop",
        "good"
    ],
    "wof:name":"Sports Stop Ltd",
    "wof:placetype":"venue"
},
  "geometry": {"coordinates":[-3.491662,53.321747],"type":"Point"}
}