{
  "type": "Feature",
  "properties": {
    "addr:full":"Unit 9, Bankfield Mill, Quebec Street Bolton Lancashire BL3 5JN",
    "addr:housenumber":"unit 9",
    "addr:postcode":"bl3 5jn",
    "addr:street":"Bankfield Mill Quebec Street",
    "iso:country":"GB",
    "sg:address":"Unit 9, Bankfield Mill, Quebec Street",
    "sg:city":"Bolton",
    "sg:classifiers":[
        {
            "category":"Manufacturing",
            "subcategory":"Tools & Machinery",
            "type":"Manufacturing & Wholesale Goods"
        }
    ],
    "sg:phone":"+44 1204 62999",
    "sg:postcode":"BL3 5JN",
    "sg:province":"Lancashire",
    "wof:name":"Bolton Machine Tools",
    "wof:placetype":"venue"
},
  "geometry": {"coordinates":[-2.446793,53.568764],"type":"Point"}
}