{
  "type": "Feature",
  "properties": {
    "addr:full":"Clegyrn, Letterston Haverfordwest Pembrokeshire SA62 5XA",
    "addr:postcode":"sa62 5xa",
    "addr:street":"Letterston;Pembrokeshire",
    "iso:country":"GB",
    "sg:address":"Clegyrn, Letterston",
    "sg:city":"Haverfordwest",
    "sg:classifiers":[
        {
            "category":"Home & Garden",
            "subcategory":"Garden Supply",
            "type":"Retail Goods"
        },
        {
            "category":"Farming",
            "subcategory":"Farm",
            "type":"Manufacturing & Wholesale Goods"
        }
    ],
    "sg:postcode":"SA62 5XA",
    "sg:province":"Pembrokeshire",
    "sg:tags":[
        "mixed",
        "bulb",
        "crop",
        "grower"
    ],
    "wof:name":"T & D M Beynon & Sons",
    "wof:placetype":"venue"
},
  "geometry": {"coordinates":[-4.991322,51.928284],"type":"Point"}
}