{
  "type": "Feature",
  "properties": {
    "iso:country":"GB",
    "sg:address":"9 St Andrews Road",
    "sg:city":"Bootle",
    "sg:classifiers":[
        {
            "category":"Social Services",
            "subcategory":"Retirement Home",
            "type":"Services"
        }
    ],
    "sg:phone":"+44 151 933 9757",
    "sg:postcode":"L20 5EX",
    "sg:province":"Merseyside",
    "sg:tags":[
        "rest"
    ],
    "wof:name":"Linacre Grange",
    "wof:placetype":"venue"
},
  "geometry": {"coordinates":[-2.994965,53.461288],"type":"Point"}
}