{
  "type": "Feature",
  "properties": {
    "addr:full":"180 Old Bedford Road Luton Bedfordshire LU2 7HW",
    "addr:housenumber":"180",
    "addr:postcode":"lu2 7hw",
    "addr:street":"Old Bedford Road",
    "iso:country":"GB",
    "sg:address":"180 Old Bedford Road",
    "sg:city":"Luton",
    "sg:classifiers":[
        {
            "category":"Health Services",
            "subcategory":"Podiatrist",
            "type":"Services"
        }
    ],
    "sg:phone":"+44 1582 415494",
    "sg:postcode":"LU2 7HW",
    "sg:province":"Bedfordshire",
    "sg:tags":[
        "podiatrists",
        "chiropodist"
    ],
    "wof:name":"Joan Hamilton-Wilson",
    "wof:placetype":"venue"
},
  "geometry": {"coordinates":[-0.416855,51.892574],"type":"Point"}
}