{
  "type": "Feature",
  "properties": {
    "iso:country":"GB",
    "sg:address":"Wiclif Way, Stockingford",
    "sg:city":"Nuneaton",
    "sg:classifiers":[
        {
            "category":"Education",
            "subcategory":"School",
            "type":"Public Place"
        }
    ],
    "sg:phone":"+44 24 7638 3323",
    "sg:postcode":"CV10 8NH",
    "sg:province":"Leicestershire",
    "sg:tags":[
        "local",
        "authority"
    ],
    "wof:name":"St Paul's C Of E Primary School",
    "wof:placetype":"venue"
},
  "geometry": {"coordinates":[-1.510794,52.519058],"type":"Point"}
}