{
  "type": "Feature",
  "properties": {
    "addr:full":"129 Woodcock Hill Harrow Greater London HA3 0JW",
    "addr:housenumber":"129",
    "addr:postcode":"ha3 0jw",
    "addr:street":"Woodcock Hill",
    "iso:country":"GB",
    "sg:address":"129 Woodcock Hill",
    "sg:city":"Harrow",
    "sg:classifiers":[
        {
            "category":"Professional",
            "subcategory":"Management & Consulting",
            "type":"Services"
        }
    ],
    "sg:phone":"+44 20 8909 1560",
    "sg:postcode":"HA3 0JW",
    "sg:province":"Greater London",
    "sg:tags":[
        "marketing",
        "consultant"
    ],
    "wof:name":"Netgain Marketing",
    "wof:placetype":"venue"
},
  "geometry": {"coordinates":[-0.30589,51.577602],"type":"Point"}
}