{
  "type": "Feature",
  "properties": {
    "iso:country":"GB",
    "sg:address":"20 Oakham Road",
    "sg:city":"Dudley",
    "sg:classifiers":[
        {
            "category":"Social Services",
            "subcategory":"Retirement Home",
            "type":"Services"
        }
    ],
    "sg:postcode":"DY2 7TB",
    "sg:province":"West Midlands",
    "sg:tags":[
        "rest"
    ],
    "wof:name":"Edmore Ho",
    "wof:placetype":"venue"
},
  "geometry": {"coordinates":[-2.072279,52.503468],"type":"Point"}
}