{
  "type": "Feature",
  "properties": {
    "iso:country":"GB",
    "sg:address":"1c Station Road, Pinhoe",
    "sg:city":"Exeter",
    "sg:classifiers":[
        {
            "category":"Shopping",
            "subcategory":"News",
            "type":"Retail Goods"
        }
    ],
    "sg:phone":"+44 1392 467031",
    "sg:postcode":"EX1 3SA",
    "sg:province":"Devon",
    "sg:tags":[
        "newsagent"
    ],
    "wof:name":"F ROGERS & CO",
    "wof:placetype":"venue"
},
  "geometry": {"coordinates":[-3.4693410397,50.7402076721],"type":"Point"}
}