{
  "type": "Feature",
  "properties": {
    "iso:country":"GB",
    "sg:address":"2 Longmeadow Gro, West Heath",
    "sg:city":"Birmingham",
    "sg:classifiers":[
        {
            "category":"Professional",
            "subcategory":"Management & Consulting",
            "type":"Services"
        },
        {
            "category":"Banks & Credit Unions",
            "subcategory":"Bank",
            "type":"Services"
        }
    ],
    "sg:postcode":"B31 4SU",
    "sg:province":"West Midlands",
    "sg:tags":[
        "consultant",
        "broker",
        "business",
        "mortgage"
    ],
    "wof:name":"The Corporate Network",
    "wof:placetype":"venue"
},
  "geometry": {"coordinates":[-1.969058,52.390541],"type":"Point"}
}