{
  "type": "Feature",
  "properties": {
    "iso:country":"GB",
    "sg:address":"Bridge Square",
    "sg:city":"Ballater",
    "sg:classifiers":[
        {
            "category":"Restaurant",
            "type":"Food & Drink"
        }
    ],
    "sg:phone":"+44 1339 755999",
    "sg:postcode":"AB35 5QJ",
    "sg:province":"Aberdeenshire",
    "wof:name":"HAYLOFT RESTAURANT",
    "wof:placetype":"venue"
},
  "geometry": {"coordinates":[-3.03743,57.047783],"type":"Point"}
}