{
  "type": "Feature",
  "properties": {
    "addr:full":"Victoria Road Pottery, Victoria Rd Stoke On Trent Staffordshire ST4 2HS",
    "addr:postcode":"st4 2hs",
    "addr:street":"Victoria Road;Rd",
    "iso:country":"GB",
    "sg:address":"Victoria Road Pottery, Victoria Rd",
    "sg:city":"Stoke On Trent",
    "sg:classifiers":[
        {
            "category":"Manufacturing",
            "subcategory":"Pottery",
            "type":"Manufacturing & Wholesale Goods"
        }
    ],
    "sg:phone":"+44 1782 847486",
    "sg:postcode":"ST4 2HS",
    "sg:province":"Staffordshire",
    "wof:name":"W H Thompson",
    "wof:placetype":"venue"
},
  "geometry": {"coordinates":[-2.1630539894,53.0044288635],"type":"Point"}
}