{
  "type": "Feature",
  "properties": {
    "addr:full":"33 Rosebery Av Eastbourne East Sussex BN22 9QB",
    "addr:housenumber":"33",
    "addr:postcode":"bn22 9qb",
    "addr:street":"Rosebery Av",
    "iso:country":"GB",
    "sg:address":"33 Rosebery Av",
    "sg:city":"Eastbourne",
    "sg:classifiers":[
        {
            "category":"Health Services",
            "subcategory":"Podiatrist",
            "type":"Services"
        }
    ],
    "sg:phone":"+44 1323 521120",
    "sg:postcode":"BN22 9QB",
    "sg:province":"East Sussex",
    "sg:tags":[
        "podiatrists",
        "chiropodist"
    ],
    "wof:name":"M A Upton & Associates",
    "wof:placetype":"venue"
},
  "geometry": {"coordinates":[0.2761589885,50.7962913513],"type":"Point"}
}