{
  "type": "Feature",
  "properties": {
    "addr:full":"53 Windsor Rd Maidenhead Berkshire SL6 2DN",
    "addr:housenumber":"53",
    "addr:postcode":"sl6 2dn",
    "addr:street":"Windsor Rd",
    "iso:country":"GB",
    "sg:address":"53 Windsor Rd",
    "sg:city":"Maidenhead",
    "sg:classifiers":[
        {
            "category":"Building & Trades",
            "subcategory":"Construction",
            "type":"Services"
        }
    ],
    "sg:postcode":"SL6 2DN",
    "sg:province":"Berkshire",
    "sg:tags":[
        "builder"
    ],
    "wof:name":"M J Herridge",
    "wof:placetype":"venue"
},
  "geometry": {"coordinates":[-0.7081490159,51.5021400452],"type":"Point"}
}