{
  "type": "Feature",
  "properties": {
    "addr:full":"Hamilton House, 5 Kestral Road Mansfield Nottinghamshire NG18 5FT",
    "addr:housenumber":"5",
    "addr:postcode":"ng18 5ft",
    "addr:street":"Kestral Road",
    "iso:country":"GB",
    "sg:address":"Hamilton House, 5 Kestral Road",
    "sg:city":"Mansfield",
    "sg:classifiers":[
        {
            "category":"Building & Trades",
            "subcategory":"Construction",
            "type":"Services"
        }
    ],
    "sg:phone":"+44 1623 421217",
    "sg:postcode":"NG18 5FT",
    "sg:province":"Nottinghamshire",
    "sg:tags":[
        "dry",
        "plasterers",
        "lining",
        "contractor",
        "tiling",
        "screeders"
    ],
    "wof:name":"East Midlands Plastering Ltd.",
    "wof:placetype":"venue"
},
  "geometry": {"coordinates":[-1.216619,53.131088],"type":"Point"}
}