{
  "type": "Feature",
  "properties": {
    "addr:full":"34 Onslow Drive Thame Buckinghamshire OX9 3YY",
    "addr:housenumber":"34",
    "addr:postcode":"ox9 3yy",
    "addr:street":"Onslow Drive",
    "iso:country":"GB",
    "sg:address":"34 Onslow Drive",
    "sg:city":"Thame",
    "sg:classifiers":[
        {
            "category":"Retail",
            "subcategory":"Driving School",
            "type":"Services"
        }
    ],
    "sg:phone":"+44 1844 213569",
    "sg:postcode":"OX9 3YY",
    "sg:province":"Buckinghamshire",
    "wof:name":"Lea Park School of Motoring",
    "wof:placetype":"venue"
},
  "geometry": {"coordinates":[-0.964603,51.747684],"type":"Point"}
}