{
  "type": "Feature",
  "properties": {
    "addr:full":"Kenilworth Rd Southport Lancashire PR8 3PH",
    "addr:postcode":"pr8 3ph",
    "addr:street":"Kenilworth Rd",
    "iso:country":"GB",
    "sg:address":"Kenilworth Rd",
    "sg:city":"Southport",
    "sg:classifiers":[
        {
            "category":"Bars & Pubs",
            "type":"Food & Drink"
        }
    ],
    "sg:phone":"+44 1704 579800",
    "sg:postcode":"PR8 3PH",
    "sg:province":"Lancashire",
    "sg:tags":[
        "pubs",
        "inn"
    ],
    "wof:name":"Arion Hotel The",
    "wof:placetype":"venue"
},
  "geometry": {"coordinates":[-3.0436499119,53.5983657837],"type":"Point"}
}