{
  "type": "Feature",
  "properties": {
    "addr:full":"The Nurseries, Splash Lane, Wyton Huntingdon Bedfordshire PE28 2AF",
    "addr:postcode":"pe28 2af",
    "addr:street":"The;Splash Lane",
    "iso:country":"GB",
    "sg:address":"The Nurseries, Splash Lane, Wyton",
    "sg:city":"Huntingdon",
    "sg:classifiers":[
        {
            "category":"Building & Trades",
            "subcategory":"Landscaping Services",
            "type":"Services"
        }
    ],
    "sg:phone":"+44 1480 453451",
    "sg:postcode":"PE28 2AF",
    "sg:province":"Bedfordshire",
    "sg:tags":[
        "designer",
        "architect",
        "landscape"
    ],
    "wof:name":"T.W Cursley & Son",
    "wof:placetype":"venue"
},
  "geometry": {"coordinates":[-0.131229,52.336124],"type":"Point"}
}