{
  "type": "Feature",
  "properties": {
    "iso:country":"GB",
    "sg:address":"Rosewood, Raemoir Road",
    "sg:city":"Banchory",
    "sg:classifiers":[
        {
            "category":"Real Estate",
            "subcategory":"Architect",
            "type":"Services"
        }
    ],
    "sg:postcode":"AB31 3XU",
    "sg:province":"Aberdeen City",
    "wof:name":"Douglas Barr Associates Ltd",
    "wof:placetype":"venue"
},
  "geometry": {"coordinates":[-2.5013890266,57.0511741638],"type":"Point"}
}