{
  "type": "Feature",
  "properties": {
    "addr:full":"62 High Street, Beighton Sheffield South Yorkshire S20 1ED",
    "addr:housenumber":"62",
    "addr:postcode":"s20 1ed",
    "addr:street":"High Street",
    "iso:country":"GB",
    "sg:address":"62 High Street, Beighton",
    "sg:city":"Sheffield",
    "sg:classifiers":[
        {
            "category":"Home & Garden",
            "subcategory":"Hardware",
            "type":"Retail Goods"
        },
        {
            "category":"Shopping",
            "subcategory":"Discount & Variety Stores",
            "type":"Retail Goods"
        }
    ],
    "sg:phone":"+44 114 269 7060",
    "sg:postcode":"S20 1ED",
    "sg:province":"South Yorkshire",
    "sg:tags":[
        "equipment",
        "material",
        "cleaning",
        "supply"
    ],
    "wof:name":"Analan Supplies Ltd",
    "wof:placetype":"venue"
},
  "geometry": {"coordinates":[-1.3359810114,53.3499298096],"type":"Point"}
}