{
  "type": "Feature",
  "properties": {
    "iso:country":"GB",
    "sg:address":"Cairncry Road",
    "sg:city":"Aberdeen",
    "sg:classifiers":[
        {
            "category":"Bars & Pubs",
            "type":"Food & Drink"
        }
    ],
    "sg:phone":"+44 1224 695876",
    "sg:postcode":"AB2 5UR",
    "sg:province":"Aberdeen City",
    "sg:tags":[
        "pubs",
        "inn"
    ],
    "wof:name":"Murdos",
    "wof:placetype":"venue"
},
  "geometry": {"coordinates":[-2.127464,57.160931],"type":"Point"}
}