{
  "type": "Feature",
  "properties": {
    "iso:country":"GB",
    "sg:address":"Wesley St Chambers",
    "sg:city":"Otley",
    "sg:classifiers":[
        {
            "category":"Arts & Performance",
            "subcategory":"Art Gallery",
            "type":"Entertainment"
        }
    ],
    "sg:phone":"+44 1943 464656",
    "sg:postcode":"LS21 1AZ",
    "sg:province":"North Yorkshire",
    "wof:name":"The Picture Shop",
    "wof:placetype":"venue"
},
  "geometry": {"coordinates":[-1.6920490265,53.9060401917],"type":"Point"}
}