{
  "type": "Feature",
  "properties": {
    "addr:full":"Nye Bevan House, Dent St Blyth Northumberland NE24 3ED",
    "addr:postcode":"ne24 3ed",
    "addr:street":"Nye;Dent St;Northumberland",
    "iso:country":"GB",
    "sg:address":"Nye Bevan House, Dent St",
    "sg:city":"Blyth",
    "sg:classifiers":[
        {
            "category":"Government",
            "subcategory":"Office",
            "type":"Public Place"
        }
    ],
    "sg:phone":"+44 1670 353472",
    "sg:postcode":"NE24 3ED",
    "sg:province":"Northumberland",
    "sg:tags":[
        "local"
    ],
    "wof:name":"Blyth Valley Sheltered Housing",
    "wof:placetype":"venue"
},
  "geometry": {"coordinates":[-1.503479,55.119057],"type":"Point"}
}