{
  "type": "Feature",
  "properties": {
    "iso:country":"GB",
    "sg:address":"66 Wigmore St",
    "sg:city":"London",
    "sg:classifiers":[
        {
            "category":"Organizations",
            "subcategory":"Membership Organization",
            "type":"Services"
        }
    ],
    "sg:postcode":"W1U 2HQ",
    "sg:province":"Greater London",
    "sg:tags":[
        "club"
    ],
    "wof:name":"D I M (Drajcott International Management",
    "wof:placetype":"venue"
},
  "geometry": {"coordinates":[-0.147519,51.51659],"type":"Point"}
}