{
  "type": "Feature",
  "properties": {
    "iso:country":"GB",
    "sg:address":"242 London Rd",
    "sg:city":"Brandon",
    "sg:classifiers":[
        {
            "category":"Bus Charters",
            "type":"Transportation"
        }
    ],
    "sg:phone":"+44 1842 810442",
    "sg:postcode":"IP27 0LX",
    "sg:province":"Norfolk",
    "sg:tags":[
        "hire",
        "coach"
    ],
    "wof:name":"Travel The Wright Way",
    "wof:placetype":"venue"
},
  "geometry": {"coordinates":[0.611044,52.441341],"type":"Point"}
}