{
  "type": "Feature",
  "properties": {
    "iso:country":"GB",
    "sg:address":"Tresare Farm, Square & Compass, Mathry",
    "sg:city":"Haverfordwest",
    "sg:classifiers":[
        {
            "category":"Farming",
            "subcategory":"Dairy Farm",
            "type":"Manufacturing & Wholesale Goods"
        }
    ],
    "sg:phone":"+44 1348 831214",
    "sg:postcode":"SA62 5JJ",
    "sg:province":"Pembrokeshire",
    "wof:name":"Linden Nicholas Richards",
    "wof:placetype":"venue"
},
  "geometry": {"coordinates":[-4.989964,51.926956],"type":"Point"}
}