{
  "type": "Feature",
  "properties": {
    "addr:full":"66 Burnbridge Road Chesterfield Derbyshire S41 9LR",
    "addr:housenumber":"66",
    "addr:postcode":"s41 9lr",
    "addr:street":"Burnbridge Road",
    "iso:country":"GB",
    "sg:address":"66 Burnbridge Road",
    "sg:city":"Chesterfield",
    "sg:classifiers":[
        {
            "category":"Social Services",
            "subcategory":"Adult Care",
            "type":"Services"
        }
    ],
    "sg:postcode":"S41 9LR",
    "sg:province":"Derbyshire",
    "sg:tags":[
        "domestic",
        "cleaning"
    ],
    "wof:name":"Helping Hands",
    "wof:placetype":"venue"
},
  "geometry": {"coordinates":[-1.413321,53.270351],"type":"Point"}
}