{
  "type": "Feature",
  "properties": {
    "iso:country":"GB",
    "sg:address":"Common Road",
    "sg:city":"Evesham",
    "sg:classifiers":[
        {
            "category":"Home & Garden",
            "subcategory":"Building Materials",
            "type":"Retail Goods"
        },
        {
            "category":"Building & Trades",
            "subcategory":"Construction",
            "type":"Services"
        }
    ],
    "sg:phone":"+44 1386 41775",
    "sg:postcode":"WR11 4PU",
    "sg:province":"Gloucestershire",
    "sg:tags":[
        "ironwork",
        "builder",
        "diy",
        "wrought"
    ],
    "wof:name":"Porter Metal Work",
    "wof:placetype":"venue"
},
  "geometry": {"coordinates":[-1.940304,52.095737],"type":"Point"}
}