{
  "type": "Feature",
  "properties": {
    "iso:country":"GB",
    "sg:address":"30 Lyndhurst Road",
    "sg:city":"London",
    "sg:classifiers":[
        {
            "category":"Banks & Credit Unions",
            "subcategory":"Bureau De Change",
            "type":"Services"
        }
    ],
    "sg:postcode":"E4 9JU",
    "sg:province":"Greater London",
    "sg:tags":[
        "town",
        "consultant",
        "planning"
    ],
    "wof:name":"Howard J Green",
    "wof:placetype":"venue"
},
  "geometry": {"coordinates":[-0.0037209999,51.6033287048],"type":"Point"}
}