{
  "type": "Feature",
  "properties": {
    "addr:full":"105 Queensway, Bletchley Milton Keynes Buckinghamshire MK2 2DN",
    "addr:housenumber":"105",
    "addr:postcode":"mk2 2dn",
    "addr:street":"Queensway",
    "iso:country":"GB",
    "sg:address":"105 Queensway, Bletchley",
    "sg:city":"Milton Keynes",
    "sg:classifiers":[
        {
            "category":"Organizations",
            "subcategory":"Membership Organization",
            "type":"Services"
        }
    ],
    "sg:phone":"+44 1908 372258",
    "sg:postcode":"MK2 2DN",
    "sg:province":"Buckinghamshire",
    "sg:tags":[
        "club"
    ],
    "wof:name":"Bletchley Conservative Club Ltd.",
    "wof:placetype":"venue"
},
  "geometry": {"coordinates":[-0.729427,51.994919],"type":"Point"}
}