{
  "type": "Feature",
  "properties": {
    "iso:country":"GB",
    "sg:address":"Marley Street",
    "sg:city":"Keighley",
    "sg:classifiers":[
        {
            "category":"Manufacturing",
            "subcategory":"Petroleum Products",
            "type":"Manufacturing & Wholesale Goods"
        }
    ],
    "sg:phone":"+44 1535 667747",
    "sg:postcode":"BD21 5JX",
    "sg:province":"West Yorkshire",
    "sg:tags":[
        "double",
        "glazing"
    ],
    "wof:name":"David Brunskill",
    "wof:placetype":"venue"
},
  "geometry": {"coordinates":[-1.910943985,53.8627281189],"type":"Point"}
}