{
  "type": "Feature",
  "properties": {
    "addr:full":"77 Louth Rd Grimsby Lincolnshire DN36 5AA",
    "addr:housenumber":"77",
    "addr:postcode":"dn36 5aa",
    "addr:street":"Louth Rd",
    "iso:country":"GB",
    "sg:address":"77 Louth Rd",
    "sg:city":"Grimsby",
    "sg:classifiers":[
        {
            "category":"Retail",
            "subcategory":"Auto Repair",
            "type":"Services"
        }
    ],
    "sg:phone":"+44 1472 823350",
    "sg:postcode":"DN36 5AA",
    "sg:province":"Lincolnshire",
    "sg:tags":[
        "modification",
        "garage"
    ],
    "wof:name":"Holton-le-clay Po",
    "wof:placetype":"venue"
},
  "geometry": {"coordinates":[-0.0627790019,53.5045928955],"type":"Point"}
}