{
  "type": "Feature",
  "properties": {
    "iso:country":"GB",
    "sg:address":"Burford School Cheltenham Road",
    "sg:city":"Burford",
    "sg:classifiers":[
        {
            "category":"Travel",
            "subcategory":"Travel Agent",
            "type":"Entertainment"
        }
    ],
    "sg:postcode":"OX18 4PL",
    "sg:province":"Gloucestershire",
    "wof:name":"Wysdom Touring Park Ltd",
    "wof:placetype":"venue"
},
  "geometry": {"coordinates":[-1.6350229979,51.8023376465],"type":"Point"}
}