{
  "type": "Feature",
  "properties": {
    "iso:country":"GB",
    "sg:address":"114 High Street",
    "sg:city":"Dorking",
    "sg:classifiers":[
        {
            "category":"Health Services",
            "subcategory":"Optometrist",
            "type":"Services"
        }
    ],
    "sg:phone":"+44 1306 882787",
    "sg:postcode":"RH4 1BA",
    "sg:province":"Surrey",
    "sg:tags":[
        "optician"
    ],
    "wof:name":"G C Bateman",
    "wof:placetype":"venue"
},
  "geometry": {"coordinates":[-0.3310669959,51.2321205139],"type":"Point"}
}