{
  "type": "Feature",
  "properties": {
    "addr:full":"Waun-y-pound Road Ebbw Vale Blaenau Gwent NP23 6LE",
    "addr:postcode":"np23 6le",
    "addr:street":"Waun-Y-Pound Road",
    "iso:country":"GB",
    "sg:address":"Waun-y-pound Road",
    "sg:city":"Ebbw Vale",
    "sg:classifiers":[
        {
            "category":"Education",
            "subcategory":"School",
            "type":"Public Place"
        }
    ],
    "sg:phone":"+44 1495 303409",
    "sg:postcode":"NP23 6LE",
    "sg:province":"Blaenau Gwent",
    "sg:tags":[
        "local",
        "authority"
    ],
    "wof:name":"Ebbw Vale Comprehensive School",
    "wof:placetype":"venue"
},
  "geometry": {"coordinates":[-3.219979,51.789173],"type":"Point"}
}