{
  "type": "Feature",
  "properties": {
    "addr:full":"232 Chorley Rd, Swinton Manchester Greater Manchester M27 6UN",
    "addr:housenumber":"232",
    "addr:postcode":"m27 6un",
    "addr:street":"Chorley Rd",
    "iso:country":"GB",
    "sg:address":"232 Chorley Rd, Swinton",
    "sg:city":"Manchester",
    "sg:classifiers":[
        {
            "category":"Building & Trades",
            "subcategory":"Construction",
            "type":"Services"
        }
    ],
    "sg:postcode":"M27 6UN",
    "sg:province":"Greater Manchester",
    "sg:tags":[
        "builder"
    ],
    "wof:name":"David,Keith,",
    "wof:placetype":"venue"
},
  "geometry": {"coordinates":[-2.343691,53.514233],"type":"Point"}
}