{
  "type": "Feature",
  "properties": {
    "addr:full":"6 Coldbath Square Clerkenwell Greater London EC1R 5HL",
    "addr:housenumber":"6",
    "addr:postcode":"ec1r 5hl",
    "addr:street":"Coldbath Square",
    "iso:country":"GB",
    "sg:address":"6 Coldbath Square",
    "sg:city":"Clerkenwell",
    "sg:classifiers":[
        {
            "category":"Manufacturing",
            "subcategory":"Metals",
            "type":"Manufacturing & Wholesale Goods"
        }
    ],
    "sg:postcode":"EC1R 5HL",
    "sg:province":"Greater London",
    "sg:tags":[
        "anodisers",
        "mnfrs"
    ],
    "wof:name":"Setech Ltd",
    "wof:placetype":"venue"
},
  "geometry": {"coordinates":[-0.110379,51.524143],"type":"Point"}
}