{
  "type": "Feature",
  "properties": {
    "iso:country":"GB",
    "sg:address":"The Barn Cottage, Great Hinton",
    "sg:city":"Trowbridge",
    "sg:classifiers":[
        {
            "category":"Professional",
            "subcategory":"Employment Agencies",
            "type":"Services"
        }
    ],
    "sg:postcode":"BA14 6BY",
    "sg:province":"Wiltshire",
    "sg:tags":[
        "agricultural",
        "advice"
    ],
    "wof:name":"Cemac",
    "wof:placetype":"venue"
},
  "geometry": {"coordinates":[-2.134404,51.330212],"type":"Point"}
}