{
  "type": "Feature",
  "properties": {
    "iso:country":"GB",
    "sg:address":"66 Becmead Avenue",
    "sg:city":"London",
    "sg:classifiers":[
        {
            "category":"Travel",
            "subcategory":"Hotels & Motels",
            "type":"Entertainment"
        }
    ],
    "sg:phone":"+44 20 8677 6013",
    "sg:postcode":"SW16 1UQ",
    "sg:province":"Greater London",
    "wof:name":"Hotel Britannia",
    "wof:placetype":"venue"
},
  "geometry": {"coordinates":[-0.1350730062,51.431438446],"type":"Point"}
}