{
  "type": "Feature",
  "properties": {
    "addr:full":"53 Rooker Avenue Wolverhampton West Midlands WV2 2DT",
    "addr:housenumber":"53",
    "addr:postcode":"wv2 2dt",
    "addr:street":"Rooker Avenue",
    "iso:country":"GB",
    "sg:address":"53 Rooker Avenue",
    "sg:city":"Wolverhampton",
    "sg:classifiers":[
        {
            "category":"Food & Beverages",
            "subcategory":"Fruits & Vegetables",
            "type":"Retail Goods"
        }
    ],
    "sg:phone":"+44 1902 402250",
    "sg:postcode":"WV2 2DT",
    "sg:province":"West Midlands",
    "sg:tags":[
        "greengrocer"
    ],
    "wof:name":"V E Cotton",
    "wof:placetype":"venue"
},
  "geometry": {"coordinates":[-2.1111819744,52.5704498291],"type":"Point"}
}