{
  "type": "Feature",
  "properties": {
    "addr:full":"Unit 16 Imex Business Park, Western Road, Hockley Birmingham West Midlands B18 7QD",
    "addr:housenumber":"unit 16",
    "addr:postcode":"b18 7qd",
    "addr:street":"Imex Business Park Western Road Hockley",
    "iso:country":"GB",
    "sg:address":"Unit 16 Imex Business Park, Western Road, Hockley",
    "sg:city":"Birmingham",
    "sg:classifiers":[
        {
            "category":"Retail",
            "subcategory":"Auto Repair",
            "type":"Services"
        }
    ],
    "sg:phone":"+44 121 551 5441",
    "sg:postcode":"B18 7QD",
    "sg:province":"West Midlands",
    "sg:tags":[
        "modification",
        "garage"
    ],
    "wof:name":"C & G Motors",
    "wof:placetype":"venue"
},
  "geometry": {"coordinates":[-1.9284700155,52.4878082275],"type":"Point"}
}