{
  "type": "Feature",
  "properties": {
    "addr:full":"15 Burlington Gardens Leyland Lancashire PR25 3PX",
    "addr:housenumber":"15",
    "addr:postcode":"pr25 3px",
    "addr:street":"Burlington Gardens Leyland",
    "iso:country":"GB",
    "sg:address":"15 Burlington Gardens",
    "sg:city":"Leyland",
    "sg:classifiers":[
        {
            "category":"Education",
            "subcategory":"Special Training",
            "type":"Public Place"
        }
    ],
    "sg:postcode":"PR25 3PX",
    "sg:province":"Lancashire",
    "sg:tags":[
        "product",
        "centre"
    ],
    "wof:name":"Micky Zekavica",
    "wof:placetype":"venue"
},
  "geometry": {"coordinates":[-2.689554,53.689987],"type":"Point"}
}