{
  "type": "Feature",
  "properties": {
    "addr:full":"23 Hotel Street Leicester Leicestershire LE1 5AW",
    "addr:housenumber":"23",
    "addr:postcode":"le1 5aw",
    "addr:street":"Hotel Street",
    "iso:country":"GB",
    "sg:address":"23 Hotel Street",
    "sg:city":"Leicester",
    "sg:classifiers":[
        {
            "category":"Fast Food",
            "type":"Food & Drink"
        }
    ],
    "sg:phone":"+44 116 251 5010",
    "sg:postcode":"LE1 5AW",
    "sg:province":"Leicestershire",
    "sg:tags":[
        "away",
        "take"
    ],
    "wof:name":"Paul Johal Ltd.",
    "wof:placetype":"venue"
},
  "geometry": {"coordinates":[-1.1345779896,52.6338653564],"type":"Point"}
}