{
  "type": "Feature",
  "properties": {
    "addr:full":"55 Victoria Road, Ruislip Manor Ruislip Greater London HA4 0JH",
    "addr:housenumber":"55",
    "addr:postcode":"ha4 0jh",
    "addr:street":"Victoria Road",
    "iso:country":"GB",
    "sg:address":"55 Victoria Road, Ruislip Manor",
    "sg:city":"Ruislip",
    "sg:classifiers":[
        {
            "category":"Shopping",
            "subcategory":"Bicycles & Sporting Goods",
            "type":"Retail Goods"
        }
    ],
    "sg:phone":"+44 1895 634244",
    "sg:postcode":"HA4 0JH",
    "sg:province":"Greater London",
    "sg:tags":[
        "equipment",
        "camping"
    ],
    "wof:name":"Hartex",
    "wof:placetype":"venue"
},
  "geometry": {"coordinates":[-0.404869,51.563881],"type":"Point"}
}