{
  "type": "Feature",
  "properties": {
    "iso:country":"GB",
    "sg:address":"Milstrete House, 29 New Street",
    "sg:city":"Chelmsford",
    "sg:classifiers":[
        {
            "category":"Banks & Credit Unions",
            "subcategory":"Bank",
            "type":"Services"
        },
        {
            "category":"Banks & Credit Unions",
            "subcategory":"Financial Services",
            "type":"Services"
        }
    ],
    "sg:phone":"+44 1245 267770",
    "sg:postcode":"CM1 1NT",
    "sg:province":"Essex",
    "sg:tags":[
        "adviser",
        "broker",
        "mortgage",
        "independent"
    ],
    "wof:name":"Robert Sacre Associates",
    "wof:placetype":"venue"
},
  "geometry": {"coordinates":[0.47364,51.737019],"type":"Point"}
}