{
  "type": "Feature",
  "properties": {
    "addr:full":"Trinity Hospital, Trinity Street Salisbury Wiltshire SP1 2BE",
    "addr:postcode":"sp1 2be",
    "addr:street":"Trinity Street",
    "iso:country":"GB",
    "sg:address":"Trinity Hospital, Trinity Street",
    "sg:city":"Salisbury",
    "sg:classifiers":[
        {
            "category":"Organizations",
            "subcategory":"Non-profit Organization",
            "type":"Services"
        }
    ],
    "sg:phone":"+44 1722 325640",
    "sg:postcode":"SP1 2BE",
    "sg:province":"Wiltshire",
    "sg:tags":[
        "organisation",
        "voluntary",
        "charity"
    ],
    "wof:name":"Salisbury City Almshouse & Welfare Charities",
    "wof:placetype":"venue"
},
  "geometry": {"coordinates":[-1.78888,51.065571],"type":"Point"}
}