{
  "type": "Feature",
  "properties": {
    "iso:country":"GB",
    "sg:address":"Bugle St",
    "sg:city":"Southampton",
    "sg:classifiers":[
        {
            "category":"Professional",
            "subcategory":"Business Services",
            "type":"Services"
        }
    ],
    "sg:phone":"+44 23 8063 7069",
    "sg:postcode":"SO14 2AL",
    "sg:province":"Hampshire",
    "sg:tags":[
        "import",
        "export",
        "agent"
    ],
    "wof:name":"Petromac (Overseas) Ltd",
    "wof:placetype":"venue"
},
  "geometry": {"coordinates":[-1.406009,50.898724],"type":"Point"}
}