{
  "type": "Feature",
  "properties": {
    "iso:country":"GB",
    "sg:address":"35 The Broadway",
    "sg:city":"London",
    "sg:classifiers":[
        {
            "category":"Shopping",
            "subcategory":"News",
            "type":"Retail Goods"
        }
    ],
    "sg:phone":"+44 20 8807 3854",
    "sg:postcode":"N9 0TJ",
    "sg:province":"Greater London",
    "sg:tags":[
        "newsagent"
    ],
    "wof:name":"Dexters Newsagents",
    "wof:placetype":"venue"
},
  "geometry": {"coordinates":[-0.0611229986,51.623790741],"type":"Point"}
}