{
  "type": "Feature",
  "properties": {
    "addr:full":"Milton Heath House, Westcott Road Dorking Surrey RH4 3NB",
    "addr:postcode":"rh4 3nb",
    "addr:street":"Milton Heath House Westcott Road",
    "iso:country":"GB",
    "sg:address":"Milton Heath House, Westcott Road",
    "sg:city":"Dorking",
    "sg:classifiers":[
        {
            "category":"Professional",
            "subcategory":"Management & Consulting",
            "type":"Services"
        }
    ],
    "sg:phone":"+44 1306 877000",
    "sg:postcode":"RH4 3NB",
    "sg:province":"Surrey",
    "sg:tags":[
        "marketing",
        "consultant"
    ],
    "sg:website":"http://www.motivation.co.uk",
    "wof:name":"Motivation Business Ltd",
    "wof:placetype":"venue"
},
  "geometry": {"coordinates":[-0.338747,51.231678],"type":"Point"}
}