{
  "type": "Feature",
  "properties": {
    "iso:country":"GB",
    "sg:address":"17 Horton Downs, Downswood",
    "sg:city":"Maidstone",
    "sg:classifiers":[
        {
            "category":"Professional",
            "subcategory":"Engineering",
            "type":"Services"
        }
    ],
    "sg:postcode":"ME15 8TN",
    "sg:province":"Kent",
    "sg:tags":[
        "contractor",
        "electrical",
        "engineer"
    ],
    "wof:name":"R Jeffery Eletrical",
    "wof:placetype":"venue"
},
  "geometry": {"coordinates":[0.561838,51.258507],"type":"Point"}
}