{
  "type": "Feature",
  "properties": {
    "addr:full":"263 Union Street Aberdeen Aberdeen City AB1 2BR",
    "addr:housenumber":"263",
    "addr:postcode":"ab1 2br",
    "addr:street":"Union Street",
    "iso:country":"GB",
    "sg:address":"263 Union Street",
    "sg:city":"Aberdeen",
    "sg:classifiers":[
        {
            "category":"Shopping",
            "subcategory":"Shoes",
            "type":"Retail Goods"
        }
    ],
    "sg:phone":"+44 1224 585045",
    "sg:postcode":"AB1 2BR",
    "sg:province":"Aberdeen City",
    "sg:tags":[
        "shop"
    ],
    "wof:name":"Jones Bootmakers",
    "wof:placetype":"venue"
},
  "geometry": {"coordinates":[-2.106096,57.144382],"type":"Point"}
}