{
  "type": "Feature",
  "properties": {
    "addr:full":"Gwel Y Don, Trefor Caernarfon Gwynedd LL54 5PS",
    "addr:postcode":"ll54 5ps",
    "iso:country":"GB",
    "sg:address":"Gwel Y Don, Trefor",
    "sg:city":"Caernarfon",
    "sg:classifiers":[
        {
            "category":"Mining & Drilling",
            "type":"Manufacturing & Wholesale Goods"
        },
        {
            "category":"Manufacturing",
            "subcategory":"Glass & Minerals",
            "type":"Manufacturing & Wholesale Goods"
        }
    ],
    "sg:phone":"+44 1286 660619",
    "sg:postcode":"LL54 5PS",
    "sg:province":"Gwynedd",
    "sg:tags":[
        "chalk",
        "stone",
        "slate",
        "quarry"
    ],
    "wof:name":"Richard Trevor Davies",
    "wof:placetype":"venue"
},
  "geometry": {"coordinates":[-4.423268,52.994747],"type":"Point"}
}