{
  "type": "Feature",
  "properties": {
    "addr:full":"Hamsey Road, Sharpthorne East Grinstead East Sussex RH19 4PB",
    "addr:postcode":"rh19 4pb",
    "addr:street":"Hamsey Road",
    "iso:country":"GB",
    "sg:address":"Hamsey Road, Sharpthorne",
    "sg:city":"East Grinstead",
    "sg:classifiers":[
        {
            "category":"Home & Garden",
            "subcategory":"Building Materials",
            "type":"Retail Goods"
        }
    ],
    "sg:phone":"+44 1530 261999",
    "sg:postcode":"RH19 4PB",
    "sg:province":"East Sussex",
    "sg:tags":[
        "brick"
    ],
    "wof:name":"Ibstock Brick Hudsons Ltd.",
    "wof:placetype":"venue"
},
  "geometry": {"coordinates":[-0.0428539999,51.0786705017],"type":"Point"}
}