{
  "type": "Feature",
  "properties": {
    "addr:full":"Unit 108 Ellingham Indstl Est, Ellingham Way Ashford Kent TN23 6LZ",
    "addr:housenumber":"108",
    "addr:postcode":"tn23 6lz",
    "addr:street":"Ellingham Indstl Est Ellingham Way",
    "iso:country":"GB",
    "sg:address":"Unit 108 Ellingham Indstl Est, Ellingham Way",
    "sg:city":"Ashford",
    "sg:classifiers":[
        {
            "category":"Professional",
            "type":"Services"
        },
        {
            "category":"Professional",
            "subcategory":"Printing & Photocopies",
            "type":"Services"
        }
    ],
    "sg:postcode":"TN23 6LZ",
    "sg:province":"Kent",
    "sg:tags":[
        "directory",
        "printer",
        "pub"
    ],
    "wof:name":"Oddell,Ray,",
    "wof:placetype":"venue"
},
  "geometry": {"coordinates":[0.8760370016,51.1466331482],"type":"Point"}
}