{
  "type": "Feature",
  "properties": {
    "addr:full":"16 Ashton Walk, St Nicholas Arcade Lancaster Lancashire LA1 1ND",
    "addr:housenumber":"16",
    "addr:postcode":"la1 1nd",
    "addr:street":"Ashton Walk St",
    "iso:country":"GB",
    "sg:address":"16 Ashton Walk, St Nicholas Arcade",
    "sg:city":"Lancaster",
    "sg:classifiers":[
        {
            "category":"Shopping",
            "subcategory":"Music",
            "type":"Retail Goods"
        }
    ],
    "sg:phone":"+44 1524 844644",
    "sg:postcode":"LA1 1ND",
    "sg:province":"Lancashire",
    "sg:tags":[
        "record",
        "tape",
        "cd"
    ],
    "wof:name":"Andys Records Ltd.",
    "wof:placetype":"venue"
},
  "geometry": {"coordinates":[-2.799029,54.044537],"type":"Point"}
}