{
  "type": "Feature",
  "properties": {
    "addr:full":"22 Mythop Road Lytham St Annes Lancashire FY8 4JD",
    "addr:housenumber":"22",
    "addr:postcode":"fy8 4jd",
    "addr:street":"Mythop Road",
    "iso:country":"GB",
    "sg:address":"22 Mythop Road",
    "sg:city":"Lytham St Annes",
    "sg:classifiers":[
        {
            "category":"Health Services",
            "subcategory":"Health Practitioner",
            "type":"Services"
        }
    ],
    "sg:phone":"+44 1253 739916",
    "sg:postcode":"FY8 4JD",
    "sg:province":"Lancashire",
    "sg:tags":[
        "hypnotherapists"
    ],
    "wof:name":"David Haworth",
    "wof:placetype":"venue"
},
  "geometry": {"coordinates":[-2.9554951191,53.741519928],"type":"Point"}
}