{
  "type": "Feature",
  "properties": {
    "addr:full":"6 London Road Stroud Gloucestershire GL5 2AG",
    "addr:housenumber":"6",
    "addr:postcode":"gl5 2ag",
    "addr:street":"London Road",
    "iso:country":"GB",
    "sg:address":"6 London Road",
    "sg:city":"Stroud",
    "sg:classifiers":[
        {
            "category":"Manufacturing",
            "subcategory":"Textiles",
            "type":"Manufacturing & Wholesale Goods"
        }
    ],
    "sg:phone":"+44 1453 755280",
    "sg:postcode":"GL5 2AG",
    "sg:province":"Gloucestershire",
    "sg:tags":[
        "mnfr",
        "rug",
        "carpet"
    ],
    "wof:name":"1a Cleaning Chaps",
    "wof:placetype":"venue"
},
  "geometry": {"coordinates":[-2.215883,51.743641],"type":"Point"}
}