{
  "type": "Feature",
  "properties": {
    "iso:country":"GB",
    "sg:address":"Scotstown Road, Bridge Of Don",
    "sg:city":"Aberdeen",
    "sg:classifiers":[
        {
            "category":"Education",
            "subcategory":"Library",
            "type":"Public Place"
        },
        {
            "category":"Government",
            "subcategory":"Office",
            "type":"Public Place"
        }
    ],
    "sg:phone":"+44 1224 702800",
    "sg:postcode":"AB22 8HH",
    "sg:province":"Aberdeen City",
    "sg:tags":[
        "book",
        "local"
    ],
    "wof:name":"Bridge of Don Library",
    "wof:placetype":"venue"
},
  "geometry": {"coordinates":[-2.100368,57.182037],"type":"Point"}
}