{
  "type": "Feature",
  "properties": {
    "addr:full":"61 Manchester Road, Pendlebury Manchester Greater Manchester M27 5SX",
    "addr:housenumber":"61",
    "addr:postcode":"m27 5sx",
    "addr:street":"Manchester Road",
    "iso:country":"GB",
    "sg:address":"61 Manchester Road, Pendlebury",
    "sg:city":"Manchester",
    "sg:classifiers":[
        {
            "category":"Shopping",
            "subcategory":"Clothing, Apparel, & Fashions",
            "type":"Retail Goods"
        }
    ],
    "sg:phone":"+44 161 737 1323",
    "sg:postcode":"M27 5SX",
    "sg:province":"Greater Manchester",
    "sg:tags":[
        "ladieswear"
    ],
    "wof:name":"Silks 'N' Threads",
    "wof:placetype":"venue"
},
  "geometry": {"coordinates":[-2.315279,53.503914],"type":"Point"}
}