{
  "type": "Feature",
  "properties": {
    "iso:country":"GB",
    "sg:address":"46 Armley Rd",
    "sg:city":"Leeds",
    "sg:classifiers":[
        {
            "category":"Retail",
            "subcategory":"Auto Repair",
            "type":"Services"
        }
    ],
    "sg:phone":"+44 113 242 6403",
    "sg:postcode":"LS12 2DR",
    "sg:province":"West Yorkshire",
    "sg:tags":[
        "car",
        "sprayer",
        "painter"
    ],
    "wof:name":"Castleton Cars",
    "wof:placetype":"venue"
},
  "geometry": {"coordinates":[-1.567215,53.795544],"type":"Point"}
}