{
  "type": "Feature",
  "properties": {
    "addr:full":"6 Conway Drive Leeds West Yorkshire LS8 5JG",
    "addr:housenumber":"6",
    "addr:postcode":"ls8 5jg",
    "addr:street":"Conway Drive",
    "iso:country":"GB",
    "sg:address":"6 Conway Drive",
    "sg:city":"Leeds",
    "sg:classifiers":[
        {
            "category":"Building & Trades",
            "subcategory":"Construction",
            "type":"Services"
        }
    ],
    "sg:phone":"+44 113 249 1812",
    "sg:postcode":"LS8 5JG",
    "sg:province":"West Yorkshire",
    "sg:tags":[
        "decorator",
        "painter"
    ],
    "wof:name":"C & S Rose",
    "wof:placetype":"venue"
},
  "geometry": {"coordinates":[-1.516886,53.812805],"type":"Point"}
}