{
  "type": "Feature",
  "properties": {
    "addr:full":"Windward House, Coronation Road Salcombe Devon TQ8 8EA",
    "addr:postcode":"tq8 8ea",
    "addr:street":"Coronation Road",
    "iso:country":"GB",
    "sg:address":"Windward House, Coronation Road",
    "sg:city":"Salcombe",
    "sg:classifiers":[
        {
            "category":"Recreation",
            "subcategory":"Water Park",
            "type":"Entertainment"
        }
    ],
    "sg:phone":"+44 1548 842727",
    "sg:postcode":"TQ8 8EA",
    "sg:province":"Devon",
    "sg:tags":[
        "sport"
    ],
    "wof:name":"Jon Clift's Powerboat School",
    "wof:placetype":"venue"
},
  "geometry": {"coordinates":[-3.772521019,50.2392425537],"type":"Point"}
}