{
  "type": "Feature",
  "properties": {
    "iso:country":"GB",
    "sg:address":"10 Stucley Pl",
    "sg:city":"Camden",
    "sg:classifiers":[
        {
            "category":"Communications",
            "type":"Services"
        }
    ],
    "sg:phone":"+44 20 7482 2020",
    "sg:postcode":"NW1 8NS",
    "sg:province":"Greater London",
    "sg:tags":[
        "audio-visual"
    ],
    "wof:name":"Twenty Twenty Productions",
    "wof:placetype":"venue"
},
  "geometry": {"coordinates":[-0.1434620023,51.5403823853],"type":"Point"}
}