{
  "type": "Feature",
  "properties": {
    "addr:full":"12 High Street Walsall West Midlands WS1 1QW",
    "addr:housenumber":"12",
    "addr:postcode":"ws1 1qw",
    "addr:street":"High Street",
    "iso:country":"GB",
    "sg:address":"12 High Street",
    "sg:city":"Walsall",
    "sg:classifiers":[
        {
            "category":"Cafe",
            "type":"Food & Drink"
        }
    ],
    "sg:phone":"+44 1922 613661",
    "sg:postcode":"WS1 1QW",
    "sg:province":"West Midlands",
    "sg:tags":[
        "tea",
        "room"
    ],
    "wof:name":"Ye Olde Coffee Shop",
    "wof:placetype":"venue"
},
  "geometry": {"coordinates":[-1.9790320396,52.5829772949],"type":"Point"}
}