{
  "type": "Feature",
  "properties": {
    "addr:full":"15 Allen Street Mountain Ash Rhondda, Cynon, Taff CF45 4BD",
    "addr:housenumber":"15",
    "addr:postcode":"cf45 4bd",
    "addr:street":"Allen Street;Cynon Taff",
    "iso:country":"GB",
    "sg:address":"15 Allen Street",
    "sg:city":"Mountain Ash",
    "sg:classifiers":[
        {
            "category":"Building & Trades",
            "subcategory":"Construction",
            "type":"Services"
        }
    ],
    "sg:phone":"+44 1443 473190",
    "sg:postcode":"CF45 4BD",
    "sg:province":"Rhondda, Cynon, Taff",
    "sg:tags":[
        "builder"
    ],
    "wof:name":"R J Building Contractors",
    "wof:placetype":"venue"
},
  "geometry": {"coordinates":[-3.378567,51.68494],"type":"Point"}
}