{
  "type": "Feature",
  "properties": {
    "iso:country":"GB",
    "sg:address":"110 Lindsey Avenue",
    "sg:city":"York",
    "sg:classifiers":[
        {
            "category":"Building & Trades",
            "subcategory":"Construction",
            "type":"Services"
        }
    ],
    "sg:phone":"+44 1904 796003",
    "sg:postcode":"YO26 4RL",
    "sg:province":"North Yorkshire",
    "sg:tags":[
        "decorator",
        "painter"
    ],
    "wof:name":"K Tate",
    "wof:placetype":"venue"
},
  "geometry": {"coordinates":[-1.118717,53.960499],"type":"Point"}
}