{
  "type": "Feature",
  "properties": {
    "addr:full":"Bunbury Lane, Bunbury Tarporley Cheshire CW6 9QU",
    "addr:postcode":"cw6 9qu",
    "addr:street":"Bunbury Lane",
    "iso:country":"GB",
    "sg:address":"Bunbury Lane, Bunbury",
    "sg:city":"Tarporley",
    "sg:classifiers":[
        {
            "category":"Farming",
            "subcategory":"Livestock Farm",
            "type":"Manufacturing & Wholesale Goods"
        }
    ],
    "sg:phone":"+44 1829 260968",
    "sg:postcode":"CW6 9QU",
    "sg:province":"Cheshire",
    "sg:tags":[
        "others"
    ],
    "wof:name":"Warwickshire Quality Calves",
    "wof:placetype":"venue"
},
  "geometry": {"coordinates":[-2.661644,53.121246],"type":"Point"}
}