{
  "type": "Feature",
  "properties": {
    "addr:full":"213 Church Street Blackpool Lancashire FY1 3PA",
    "addr:housenumber":"213",
    "addr:postcode":"fy1 3pa",
    "addr:street":"Church Street",
    "iso:country":"GB",
    "sg:address":"213 Church Street",
    "sg:city":"Blackpool",
    "sg:classifiers":[
        {
            "category":"Banks & Credit Unions",
            "subcategory":"Financial Services",
            "type":"Services"
        }
    ],
    "sg:phone":"+44 1253 293883",
    "sg:postcode":"FY1 3PA",
    "sg:province":"Lancashire",
    "sg:tags":[
        "adviser"
    ],
    "wof:name":"Edwin Kelly & Co.",
    "wof:placetype":"venue"
},
  "geometry": {"coordinates":[-3.04333,53.818485],"type":"Point"}
}