{
  "type": "Feature",
  "properties": {
    "addr:full":"56 Charnwood Road, Whitchurch Bristol City of Bristol BS14 0JY",
    "addr:housenumber":"56",
    "addr:postcode":"bs14 0jy",
    "addr:street":"Charnwood Road",
    "iso:country":"GB",
    "sg:address":"56 Charnwood Road, Whitchurch",
    "sg:city":"Bristol",
    "sg:classifiers":[
        {
            "category":"Building & Trades",
            "subcategory":"Construction",
            "type":"Services"
        }
    ],
    "sg:postcode":"BS14 0JY",
    "sg:province":"City of Bristol",
    "sg:tags":[
        "builder"
    ],
    "wof:name":"H C Cuff & Son",
    "wof:placetype":"venue"
},
  "geometry": {"coordinates":[-2.568519,51.405174],"type":"Point"}
}