{
  "type": "Feature",
  "properties": {
    "addr:full":"10 Barb Mews Hammersmith Greater London W6 7PA",
    "addr:housenumber":"10",
    "addr:postcode":"w6 7pa",
    "addr:street":"Barb Mews",
    "iso:country":"GB",
    "sg:address":"10 Barb Mews",
    "sg:city":"Hammersmith",
    "sg:classifiers":[
        {
            "category":"Organizations",
            "subcategory":"Community Association",
            "type":"Services"
        }
    ],
    "sg:phone":"+44 20 7602 0958",
    "sg:postcode":"W6 7PA",
    "sg:province":"Greater London",
    "sg:tags":[
        "relation",
        "public"
    ],
    "wof:name":"Elliott Service & Co",
    "wof:placetype":"venue"
},
  "geometry": {"coordinates":[-0.22305,51.497505],"type":"Point"}
}