{
  "type": "Feature",
  "properties": {
    "addr:full":"64 Newport Road Cowes Isle of Wight PO31 7PN",
    "addr:housenumber":"64",
    "addr:postcode":"po31 7pn",
    "addr:street":"Newport Road",
    "iso:country":"GB",
    "sg:address":"64 Newport Road",
    "sg:city":"Cowes",
    "sg:classifiers":[
        {
            "category":"Real Estate",
            "subcategory":"Architect",
            "type":"Services"
        }
    ],
    "sg:postcode":"PO31 7PN",
    "sg:province":"Isle of Wight",
    "wof:name":"Peter Ferns",
    "wof:placetype":"venue"
},
  "geometry": {"coordinates":[-1.2975970507,50.7548789978],"type":"Point"}
}