{
  "type": "Feature",
  "properties": {
    "iso:country":"GB",
    "sg:address":"Unit 2b",
    "sg:city":"Lichfield",
    "sg:classifiers":[
        {
            "category":"Wholesale",
            "subcategory":"Chemicals & Plastics",
            "type":"Manufacturing & Wholesale Goods"
        }
    ],
    "sg:phone":"+44 1543 374150",
    "sg:postcode":"WS13 7AU",
    "sg:province":"Staffordshire",
    "sg:tags":[
        "glass",
        "metal"
    ],
    "wof:name":"Adante",
    "wof:placetype":"venue"
},
  "geometry": {"coordinates":[-1.81966,52.684029],"type":"Point"}
}