{
  "type": "Feature",
  "properties": {
    "addr:full":"High Street Kirkcudbright Dumfries and Galloway DG6 4JG",
    "addr:postcode":"dg6 4jg",
    "addr:street":"High Street",
    "iso:country":"GB",
    "sg:address":"High Street",
    "sg:city":"Kirkcudbright",
    "sg:classifiers":[
        {
            "category":"Travel",
            "subcategory":"Hotels & Motels",
            "type":"Entertainment"
        }
    ],
    "sg:phone":"+44 1557 330402",
    "sg:postcode":"DG6 4JG",
    "sg:province":"Dumfries and Galloway",
    "wof:name":"Selkirk Arms Hotel",
    "wof:placetype":"venue"
},
  "geometry": {"coordinates":[-4.0540790558,54.8370780945],"type":"Point"}
}