{
  "type": "Feature",
  "properties": {
    "addr:full":"11-15 Wharf St Sowerby Bridge West Yorkshire HX6 2EG",
    "addr:housenumber":"11-15",
    "addr:postcode":"hx6 2eg",
    "addr:street":"Wharf St;West",
    "iso:country":"GB",
    "sg:address":"11-15 Wharf St",
    "sg:city":"Sowerby Bridge",
    "sg:classifiers":[
        {
            "category":"Food & Beverages",
            "subcategory":"Fruits & Vegetables",
            "type":"Retail Goods"
        }
    ],
    "sg:postcode":"HX6 2EG",
    "sg:province":"West Yorkshire",
    "sg:tags":[
        "greengrocer"
    ],
    "wof:name":"Ransley,Lesley M,",
    "wof:placetype":"venue"
},
  "geometry": {"coordinates":[-1.9094530344,53.7091674805],"type":"Point"}
}