{
  "type": "Feature",
  "properties": {
    "addr:full":"28 Beacon Grove Bradford West Yorkshire BD6 3EB",
    "addr:housenumber":"28",
    "addr:postcode":"bd6 3eb",
    "addr:street":"Beacon Grove",
    "iso:country":"GB",
    "sg:address":"28 Beacon Grove",
    "sg:city":"Bradford",
    "sg:classifiers":[
        {
            "category":"Home & Garden",
            "subcategory":"Building Materials",
            "type":"Retail Goods"
        }
    ],
    "sg:phone":"+44 1274 690625",
    "sg:postcode":"BD6 3EB",
    "sg:province":"West Yorkshire",
    "sg:tags":[
        "garage",
        "door"
    ],
    "wof:name":"Bradford Garage Doors",
    "wof:placetype":"venue"
},
  "geometry": {"coordinates":[-1.807171,53.771545],"type":"Point"}
}