{
  "type": "Feature",
  "properties": {
    "iso:country":"GB",
    "sg:address":"10-12 Hamilton Place",
    "sg:city":"Edinburgh",
    "sg:classifiers":[
        {
            "category":"Communications",
            "type":"Services"
        }
    ],
    "sg:phone":"+44 131 225 1771",
    "sg:postcode":"EH3 5AU",
    "sg:province":"City of Edinburgh",
    "sg:tags":[
        "tv",
        "video",
        "radio"
    ],
    "wof:name":"Carl Dyson Rentals",
    "wof:placetype":"venue"
},
  "geometry": {"coordinates":[-3.208168,55.957977],"type":"Point"}
}