{
  "type": "Feature",
  "properties": {
    "addr:full":"The Map Partnership, Ground Floor Goodyear House, 52-56 Osnab London Greater London NW1 3NS",
    "addr:housenumber":"floor goodyear;52-56",
    "addr:postcode":"nw1 3ns",
    "addr:street":"Ground;Osnab",
    "iso:country":"GB",
    "sg:address":"The Map Partnership, Ground Floor Goodyear House, 52-56 Osnab",
    "sg:city":"London",
    "sg:classifiers":[
        {
            "category":"Professional",
            "subcategory":"Management & Consulting",
            "type":"Services"
        }
    ],
    "sg:postcode":"NW1 3NS",
    "sg:province":"Greater London",
    "sg:tags":[
        "marketing",
        "consultant"
    ],
    "wof:name":"Rainmaker Database Ltd",
    "wof:placetype":"venue"
},
  "geometry": {"coordinates":[-0.142771,51.525414],"type":"Point"}
}