{
  "type": "Feature",
  "properties": {
    "iso:country":"GB",
    "sg:address":"65 Leicester Road, Groby",
    "sg:city":"Leicester",
    "sg:classifiers":[
        {
            "category":"Real Estate",
            "subcategory":"Architect",
            "type":"Services"
        }
    ],
    "sg:phone":"+44 116 287 2597",
    "sg:postcode":"LE6 0DQ",
    "sg:province":"Leicestershire",
    "wof:name":"DAVID M HAYNES",
    "wof:placetype":"venue"
},
  "geometry": {"coordinates":[-1.2229479551,52.6623344421],"type":"Point"}
}