{
  "type": "Feature",
  "properties": {
    "iso:country":"GB",
    "sg:address":"20 Powderham Crescent",
    "sg:city":"Exeter",
    "sg:classifiers":[
        {
            "category":"Health Services",
            "subcategory":"Clinic",
            "type":"Services"
        }
    ],
    "sg:phone":"+44 1392 426779",
    "sg:postcode":"EX4 6DA",
    "sg:province":"Devon",
    "sg:tags":[
        "aromatherapy"
    ],
    "wof:name":"Trisha Woods",
    "wof:placetype":"venue"
},
  "geometry": {"coordinates":[-3.5228419304,50.7314414978],"type":"Point"}
}