{
  "type": "Feature",
  "properties": {
    "addr:full":"Unit 2 126 Weymouth Street Leicester Leicestershire LE4 6FQ",
    "addr:housenumber":"unit 2 126",
    "addr:postcode":"le4 6fq",
    "addr:street":"Weymouth Street",
    "iso:country":"GB",
    "sg:address":"Unit 2 126 Weymouth Street",
    "sg:city":"Leicester",
    "sg:classifiers":[
        {
            "category":"Shopping",
            "subcategory":"Clothing, Apparel, & Fashions",
            "type":"Retail Goods"
        }
    ],
    "sg:phone":"+44 116 258 2880",
    "sg:postcode":"LE4 6FQ",
    "sg:province":"Leicestershire",
    "sg:tags":[
        "ladieswear"
    ],
    "wof:name":"Tik Tak Clothing Co. Ltd.",
    "wof:placetype":"venue"
},
  "geometry": {"coordinates":[-1.112358,52.647488],"type":"Point"}
}