{
  "type": "Feature",
  "properties": {
    "addr:full":"240a Spring Rd, Tyseley Birmingham West Midlands B11 3DW",
    "addr:housenumber":"240a",
    "addr:postcode":"b11 3dw",
    "addr:street":"Spring Rd",
    "iso:country":"GB",
    "sg:address":"240a Spring Rd, Tyseley",
    "sg:city":"Birmingham",
    "sg:classifiers":[
        {
            "category":"Military Area",
            "subcategory":"Air Force Base",
            "type":"Public Place"
        }
    ],
    "sg:phone":"+44 121 766 6662",
    "sg:postcode":"B11 3DW",
    "sg:province":"West Midlands",
    "sg:tags":[
        "taxi",
        "hire",
        "private"
    ],
    "wof:name":"S & C Cars",
    "wof:placetype":"venue"
},
  "geometry": {"coordinates":[-1.835335,52.444744],"type":"Point"}
}