{
  "type": "Feature",
  "properties": {
    "addr:full":"1a Hulton Lane Bolton Lancashire BL3 4JB",
    "addr:housenumber":"1a",
    "addr:postcode":"bl3 4jb",
    "addr:street":"Hulton Lane",
    "iso:country":"GB",
    "sg:address":"1a Hulton Lane",
    "sg:city":"Bolton",
    "sg:classifiers":[
        {
            "category":"Communications",
            "type":"Services"
        }
    ],
    "sg:postcode":"BL3 4JB",
    "sg:province":"Lancashire",
    "sg:tags":[
        "tv",
        "video",
        "radio"
    ],
    "wof:name":"Taylorvision",
    "wof:placetype":"venue"
},
  "geometry": {"coordinates":[-2.4648339748,53.5665550232],"type":"Point"}
}