{
  "type": "Feature",
  "properties": {
    "iso:country":"GB",
    "sg:address":"33 Roslin Street",
    "sg:city":"Aberdeen",
    "sg:classifiers":[
        {
            "category":"Personal",
            "type":"Services"
        },
        {
            "category":"Professional",
            "subcategory":"Lawyer & Legal Services",
            "type":"Services"
        }
    ],
    "sg:phone":"+44 845 644 1598",
    "sg:postcode":"AB24 5PE",
    "sg:province":"Aberdeen City",
    "sg:tags":[
        "advice",
        "counselling"
    ],
    "wof:name":"Eileen Freeman",
    "wof:placetype":"venue"
},
  "geometry": {"coordinates":[-2.090067,57.15567],"type":"Point"}
}