{
  "type": "Feature",
  "properties": {
    "iso:country":"GB",
    "sg:address":"34 Tintern Close, Popley 4",
    "sg:city":"Basingstoke",
    "sg:classifiers":[
        {
            "category":"Home & Garden",
            "subcategory":"Carpets & Floor Coverings",
            "type":"Retail Goods"
        }
    ],
    "sg:postcode":"RG24 9HE",
    "sg:province":"Hampshire",
    "sg:tags":[
        "carpets",
        "rug",
        "matting"
    ],
    "wof:name":"Wall to Wall Flooring",
    "wof:placetype":"venue"
},
  "geometry": {"coordinates":[-1.10724,51.293118],"type":"Point"}
}