{
  "type": "Feature",
  "properties": {
    "addr:full":"Stadium Way, Retail World Rotherham South Yorkshire S60 1TG",
    "addr:postcode":"s60 1tg",
    "addr:street":"Stadium Way;South",
    "iso:country":"GB",
    "sg:address":"Stadium Way, Retail World",
    "sg:city":"Rotherham",
    "sg:classifiers":[
        {
            "category":"Shopping",
            "subcategory":"Shoes",
            "type":"Retail Goods"
        }
    ],
    "sg:phone":"+44 1709 780010",
    "sg:postcode":"S60 1TG",
    "sg:province":"South Yorkshire",
    "sg:tags":[
        "shop"
    ],
    "wof:name":"Shoe City Ltd.",
    "wof:placetype":"venue"
},
  "geometry": {"coordinates":[-1.3429039717,53.4451713562],"type":"Point"}
}