{
  "type": "Feature",
  "properties": {
    "iso:country":"GB",
    "sg:address":"Unit 38 Gravelly Park Indstl Est, Jarvis Way, Tyburn Rd",
    "sg:city":"Birmingham",
    "sg:classifiers":[
        {
            "category":"Brewery",
            "type":"Food & Drink"
        }
    ],
    "sg:phone":"+44 121 327 1133",
    "sg:postcode":"B24 8TG",
    "sg:province":"West Midlands",
    "sg:tags":[
        "brewer"
    ],
    "wof:name":"Carlsberg-Tetley Plc",
    "wof:placetype":"venue"
},
  "geometry": {"coordinates":[-1.8518340588,52.512966156],"type":"Point"}
}