{
  "type": "Feature",
  "properties": {
    "addr:full":"14 The Triangle, Brackla Bridgend Bridgend CF31 4LL",
    "addr:housenumber":"14",
    "addr:postcode":"cf31 4ll",
    "addr:street":"The Triangle",
    "iso:country":"GB",
    "sg:address":"14 The Triangle, Brackla",
    "sg:city":"Bridgend",
    "sg:classifiers":[
        {
            "category":"Retail",
            "subcategory":"Laundry & Dry Cleaning",
            "type":"Services"
        }
    ],
    "sg:phone":"+44 1656 668928",
    "sg:postcode":"CF31 4LL",
    "sg:province":"Bridgend",
    "sg:tags":[
        "alteration"
    ],
    "wof:name":"Sapphire Quality Dry Cleaners & Launderers",
    "wof:placetype":"venue"
},
  "geometry": {"coordinates":[-3.583337,51.508541],"type":"Point"}
}