{
  "type": "Feature",
  "properties": {
    "iso:country":"GB",
    "sg:address":"Brigydon, High Street",
    "sg:city":"Tywyn",
    "sg:classifiers":[
        {
            "category":"Shopping",
            "subcategory":"Shoes",
            "type":"Retail Goods"
        }
    ],
    "sg:phone":"+44 1654 710570",
    "sg:postcode":"LL36 9AD",
    "sg:province":"Gwynedd",
    "sg:tags":[
        "shop",
        "retailer",
        "footwear"
    ],
    "wof:name":"Shoe Box",
    "wof:placetype":"venue"
},
  "geometry": {"coordinates":[-4.088419,52.586586],"type":"Point"}
}