{
  "type": "Feature",
  "properties": {
    "iso:country":"GB",
    "sg:address":"56 Harwich Rd",
    "sg:city":"Colchester",
    "sg:classifiers":[
        {
            "category":"Professional",
            "subcategory":"Accounting & Tax Preparation",
            "type":"Services"
        }
    ],
    "sg:phone":"+44 1206 393972",
    "sg:postcode":"CO4 3BW",
    "sg:province":"Essex",
    "sg:tags":[
        "accountant"
    ],
    "wof:name":"P D Finnigan & Co",
    "wof:placetype":"venue"
},
  "geometry": {"coordinates":[0.92134,51.89106],"type":"Point"}
}