{
  "type": "Feature",
  "properties": {
    "addr:full":"56 Harwich Rd Colchester Essex CO4 3BW",
    "addr:housenumber":"56",
    "addr:postcode":"co4 3bw",
    "addr:street":"Harwich Rd",
    "iso:country":"GB",
    "sg:address":"56 Harwich Rd",
    "sg:city":"Colchester",
    "sg:classifiers":[
        {
            "category":"Professional",
            "subcategory":"Accounting & Tax Preparation",
            "type":"Services"
        }
    ],
    "sg:phone":"+44 1206 393972",
    "sg:postcode":"CO4 3BW",
    "sg:province":"Essex",
    "sg:tags":[
        "accountant"
    ],
    "wof:name":"P D Finnigan & Co",
    "wof:placetype":"venue"
},
  "geometry": {"coordinates":[0.92134,51.89106],"type":"Point"}
}