{
  "type": "Feature",
  "properties": {
    "addr:full":"16 Chesshire Avenue, Areley Kings Stourport-on-severn Worcestershire DY13 0EA",
    "addr:housenumber":"16",
    "addr:postcode":"dy13 0ea",
    "addr:street":"Chesshire Avenue;Kings",
    "iso:country":"GB",
    "sg:address":"16 Chesshire Avenue, Areley Kings",
    "sg:city":"Stourport-on-severn",
    "sg:classifiers":[
        {
            "category":"Building & Trades",
            "subcategory":"Construction",
            "type":"Services"
        }
    ],
    "sg:phone":"+44 1299 826536",
    "sg:postcode":"DY13 0EA",
    "sg:province":"Worcestershire",
    "sg:tags":[
        "repair",
        "guttering"
    ],
    "wof:name":"Stourport Seamless Gutters",
    "wof:placetype":"venue"
},
  "geometry": {"coordinates":[-2.290648,52.326729],"type":"Point"}
}