{
  "type": "Feature",
  "properties": {
    "iso:country":"GB",
    "sg:address":"Lynchborough Road, Passfield",
    "sg:city":"Liphook",
    "sg:classifiers":[
        {
            "category":"Communications",
            "subcategory":"Newspaper",
            "type":"Services"
        }
    ],
    "sg:phone":"+44 1428 751188",
    "sg:postcode":"GU30 7SB",
    "sg:province":"Hampshire",
    "sg:tags":[
        "magazine"
    ],
    "wof:name":"Process Products Ltd.",
    "wof:placetype":"venue"
},
  "geometry": {"coordinates":[-0.7992,51.077641],"type":"Point"}
}