{
  "type": "Feature",
  "properties": {
    "addr:full":"Unit A4 Egham Surrey TW20 8RN",
    "addr:postcode":"tw20 8rn",
    "iso:country":"GB",
    "sg:address":"Unit A4",
    "sg:city":"Egham",
    "sg:classifiers":[
        {
            "category":"Wholesale",
            "subcategory":"Construction Materials",
            "type":"Manufacturing & Wholesale Goods"
        },
        {
            "category":"Building & Trades",
            "subcategory":"Equipment Rental",
            "type":"Services"
        }
    ],
    "sg:phone":"+44 1784 438127",
    "sg:postcode":"TW20 8RN",
    "sg:province":"Surrey",
    "sg:tags":[
        "lift",
        "lifting"
    ],
    "wof:name":"C & M Welding Services",
    "wof:placetype":"venue"
},
  "geometry": {"coordinates":[-0.5284590125,51.4173202515],"type":"Point"}
}