{
  "type": "Feature",
  "properties": {
    "iso:country":"GB",
    "sg:address":"Main Road, Abercynon",
    "sg:city":"Mountain Ash",
    "sg:classifiers":[
        {
            "category":"Travel",
            "subcategory":"Hotels & Motels",
            "type":"Entertainment"
        }
    ],
    "sg:postcode":"CF45 4BX",
    "sg:province":"Rhondda, Cynon, Taff",
    "wof:name":"Ynys Boeth Hotel",
    "wof:placetype":"venue"
},
  "geometry": {"coordinates":[-3.3789639473,51.6843986511],"type":"Point"}
}