{
  "type": "Feature",
  "properties": {
    "iso:country":"GB",
    "sg:address":"22 Palmerston Rd",
    "sg:city":"Southsea",
    "sg:classifiers":[
        {
            "category":"Communications",
            "subcategory":"Film & Video Production",
            "type":"Services"
        }
    ],
    "sg:phone":"+44 23 9282 5981",
    "sg:postcode":"PO5 3QH",
    "sg:province":"Hampshire",
    "sg:tags":[
        "tv"
    ],
    "wof:name":"Granada Home Technology",
    "wof:placetype":"venue"
},
  "geometry": {"coordinates":[-1.0888290405,50.7849197388],"type":"Point"}
}