{
  "type": "Feature",
  "properties": {
    "iso:country":"GB",
    "sg:address":"Unit 7 Tom Thumb Industrial Estate, English Street",
    "sg:city":"Hull",
    "sg:classifiers":[
        {
            "category":"Home & Garden",
            "subcategory":"Home Furnishings",
            "type":"Retail Goods"
        }
    ],
    "sg:phone":"+44 1482 620040",
    "sg:postcode":"HU3 2BT",
    "sg:province":"East Riding of Yorkshire",
    "sg:tags":[
        "tubing",
        "fitting"
    ],
    "wof:name":"Arma Hydraulic Engineering Ltd.",
    "wof:placetype":"venue"
},
  "geometry": {"coordinates":[-0.3506200016,53.7364387512],"type":"Point"}
}