{
  "type": "Feature",
  "properties": {
    "addr:full":", Achaphubil Fort William Highland PH33 7AL",
    "addr:postcode":"ph33 7al",
    "addr:street":"Fort William",
    "iso:country":"GB",
    "sg:address":", Achaphubil",
    "sg:city":"Fort William",
    "sg:classifiers":[
        {
            "category":"Education",
            "subcategory":"School",
            "type":"Public Place"
        }
    ],
    "sg:phone":"+44 1397 772748",
    "sg:postcode":"PH33 7AL",
    "sg:province":"Highland",
    "sg:tags":[
        "local",
        "authority"
    ],
    "wof:name":"Achaphubil Primary School",
    "wof:placetype":"venue"
},
  "geometry": {"coordinates":[-5.108459,56.818432],"type":"Point"}
}