{
  "type": "Feature",
  "properties": {
    "addr:full":"The Lone, Clydach Swansea Swansea SA6 5SU",
    "addr:postcode":"sa6 5su",
    "addr:street":"Clydach",
    "iso:country":"GB",
    "sg:address":"The Lone, Clydach",
    "sg:city":"Swansea",
    "sg:classifiers":[
        {
            "category":"Bars & Pubs",
            "type":"Food & Drink"
        }
    ],
    "sg:postcode":"SA6 5SU",
    "sg:province":"Swansea",
    "sg:tags":[
        "pubs",
        "inn"
    ],
    "wof:name":"The New Inn",
    "wof:placetype":"venue"
},
  "geometry": {"coordinates":[-3.891829,51.69585],"type":"Point"}
}