{
  "type": "Feature",
  "properties": {
    "addr:full":"2a Chester Road, Whitby Ellesmere Port Cheshire CH65 6RU",
    "addr:housenumber":"2a",
    "addr:postcode":"ch65 6ru",
    "addr:street":"Chester Road",
    "iso:country":"GB",
    "sg:address":"2a Chester Road, Whitby",
    "sg:city":"Ellesmere Port",
    "sg:classifiers":[
        {
            "category":"Organizations",
            "subcategory":"Non-profit Organization",
            "type":"Services"
        }
    ],
    "sg:phone":"+44 151 356 8899",
    "sg:postcode":"CH65 6RU",
    "sg:province":"Cheshire",
    "sg:tags":[
        "charitable",
        "organisation",
        "voluntary",
        "charity"
    ],
    "wof:name":"Hospice Of The Good Shepherd Promotions Ltd",
    "wof:placetype":"venue"
},
  "geometry": {"coordinates":[-2.9104139805,53.2731361389],"type":"Point"}
}