{
  "type": "Feature",
  "properties": {
    "addr:full":"Depots 1 & 2 Meat Market, Upper Hollingdean Road Brighton East Sussex BN1 7GW",
    "addr:housenumber":"1 & 2",
    "addr:postcode":"bn1 7gw",
    "addr:street":"Depots;Upper Hollingdean Road",
    "iso:country":"GB",
    "sg:address":"Depots 1 & 2 Meat Market, Upper Hollingdean Road",
    "sg:city":"Brighton",
    "sg:classifiers":[
        {
            "category":"Food & Beverages",
            "subcategory":"Meat & Fish",
            "type":"Retail Goods"
        }
    ],
    "sg:phone":"+44 1273 552109",
    "sg:postcode":"BN1 7GW",
    "sg:province":"East Sussex",
    "sg:tags":[
        "butcher"
    ],
    "wof:name":"Wholesale Meat Specialists",
    "wof:placetype":"venue"
},
  "geometry": {"coordinates":[-0.1310500056,50.838760376],"type":"Point"}
}