{
  "type": "Feature",
  "properties": {
    "iso:country":"GB",
    "sg:address":"41 Warwick Rd",
    "sg:city":"Solihull",
    "sg:classifiers":[
        {
            "category":"Taxi",
            "type":"Transportation"
        }
    ],
    "sg:phone":"+44 121 764 4000",
    "sg:postcode":"B92 7HS",
    "sg:province":"West Midlands",
    "sg:tags":[
        "mini",
        "cab"
    ],
    "wof:name":"Gold Cabs",
    "wof:placetype":"venue"
},
  "geometry": {"coordinates":[-1.810477,52.441559],"type":"Point"}
}