{
  "type": "Feature",
  "properties": {
    "iso:country":"GB",
    "sg:address":"Park Road Industrial Estate, West Timperley",
    "sg:city":"Altrincham",
    "sg:classifiers":[
        {
            "category":"Professional",
            "subcategory":"Printing & Photocopies",
            "type":"Services"
        }
    ],
    "sg:phone":"+44 161 962 2227",
    "sg:postcode":"WA14 5QH",
    "sg:province":"Cheshire",
    "sg:tags":[
        "printer"
    ],
    "wof:name":"Martini Printers & Stationers Ltd.",
    "wof:placetype":"venue"
},
  "geometry": {"coordinates":[-2.3466489315,53.4059486389],"type":"Point"}
}