{
  "type": "Feature",
  "properties": {
    "addr:full":"Crab Cottage, Church Street, Shapwick Blandford Forum Dorset DT11 9LA",
    "addr:postcode":"dt11 9la",
    "addr:street":"Church Street",
    "iso:country":"GB",
    "sg:address":"Crab Cottage, Church Street, Shapwick",
    "sg:city":"Blandford Forum",
    "sg:classifiers":[
        {
            "category":"Government",
            "subcategory":"Post Office",
            "type":"Public Place"
        }
    ],
    "sg:phone":"+44 1258 858430",
    "sg:postcode":"DT11 9LA",
    "sg:province":"Dorset",
    "wof:name":"Shapwick Post Office",
    "wof:placetype":"venue"
},
  "geometry": {"coordinates":[-2.0829319954,50.8173675537],"type":"Point"}
}