{
  "type": "Feature",
  "properties": {
    "iso:country":"GB",
    "sg:address":"Abbey Lane, Darley Abbey",
    "sg:city":"Derby",
    "sg:classifiers":[
        {
            "category":"Personal",
            "subcategory":"Beauty Salon",
            "type":"Services"
        }
    ],
    "sg:postcode":"DE22 1DG",
    "sg:province":"Derbyshire",
    "wof:name":"Forever Young",
    "wof:placetype":"venue"
},
  "geometry": {"coordinates":[-1.479403019,52.9426574707],"type":"Point"}
}