{
  "type": "Feature",
  "properties": {
    "addr:full":"Claydons Lane Rayleigh Essex SS6 7UP",
    "addr:postcode":"ss6 7up",
    "addr:street":"Claydons Lane",
    "iso:country":"GB",
    "sg:address":"Claydons Lane",
    "sg:city":"Rayleigh",
    "sg:classifiers":[
        {
            "category":"Professional",
            "subcategory":"Accounting & Tax Preparation",
            "type":"Services"
        },
        {
            "category":"Professional",
            "subcategory":"Printing & Photocopies",
            "type":"Services"
        }
    ],
    "sg:phone":"+44 1268 774999",
    "sg:postcode":"SS6 7UP",
    "sg:province":"Essex",
    "sg:tags":[
        "print",
        "accountant",
        "finisher"
    ],
    "wof:name":"A & S B S Accounts",
    "wof:placetype":"venue"
},
  "geometry": {"coordinates":[0.60148,51.575981],"type":"Point"}
}