{
  "type": "Feature",
  "properties": {
    "addr:full":"1 Station App Buxton Derbyshire SK17 6AQ",
    "addr:housenumber":"1",
    "addr:postcode":"sk17 6aq",
    "iso:country":"GB",
    "sg:address":"1 Station App",
    "sg:city":"Buxton",
    "sg:classifiers":[
        {
            "category":"Health Services",
            "subcategory":"Clinic",
            "type":"Services"
        }
    ],
    "sg:phone":"+44 1298 72260",
    "sg:postcode":"SK17 6AQ",
    "sg:province":"Derbyshire",
    "sg:tags":[
        "aromatherapy"
    ],
    "wof:name":"The Aromatherapy & Reflexology Centre",
    "wof:placetype":"venue"
},
  "geometry": {"coordinates":[-1.9130489826,53.2603874207],"type":"Point"}
}