{
  "type": "Feature",
  "properties": {
    "addr:full":"50 Petts Wood Road Orpington Kent BR5 1LD",
    "addr:housenumber":"50",
    "addr:postcode":"br5 1ld",
    "addr:street":"Petts Wood Road",
    "iso:country":"GB",
    "sg:address":"50 Petts Wood Road",
    "sg:city":"Orpington",
    "sg:classifiers":[
        {
            "category":"Professional",
            "subcategory":"Printing & Photocopies",
            "type":"Services"
        }
    ],
    "sg:postcode":"BR5 1LD",
    "sg:province":"Kent",
    "sg:tags":[
        "printer"
    ],
    "wof:name":"Foil Printers of Kent",
    "wof:placetype":"venue"
},
  "geometry": {"coordinates":[0.0852909982,51.3909378052],"type":"Point"}
}