{
  "type": "Feature",
  "properties": {
    "iso:country":"GB",
    "sg:address":"120 Burley Rd",
    "sg:city":"Leeds",
    "sg:classifiers":[
        {
            "category":"Professional",
            "subcategory":"Art Services",
            "type":"Services"
        }
    ],
    "sg:phone":"+44 113 245 7880",
    "sg:postcode":"LS3 1JP",
    "sg:province":"West Yorkshire",
    "sg:tags":[
        "graphic",
        "designer"
    ],
    "wof:name":"Paint Factory The",
    "wof:placetype":"venue"
},
  "geometry": {"coordinates":[-1.568482,53.804417],"type":"Point"}
}