{
  "type": "Feature",
  "properties": {
    "iso:country":"GB",
    "sg:address":"138 Christchurch Drive, Blackwater",
    "sg:city":"Camberley",
    "sg:classifiers":[
        {
            "category":"Manufacturing",
            "subcategory":"Textiles",
            "type":"Manufacturing & Wholesale Goods"
        },
        {
            "category":"Home & Garden",
            "subcategory":"Carpets & Floor Coverings",
            "type":"Retail Goods"
        }
    ],
    "sg:phone":"+44 1276 35703",
    "sg:postcode":"GU17 0HN",
    "sg:province":"Hampshire",
    "sg:tags":[
        "cleaner",
        "upholstery",
        "rug",
        "mnfr"
    ],
    "wof:name":"Pristine Clean",
    "wof:placetype":"venue"
},
  "geometry": {"coordinates":[-0.7865809798,51.3349380493],"type":"Point"}
}