{
  "type": "Feature",
  "properties": {
    "iso:country":"GB",
    "sg:address":"Cronulla, Witney Road, Finstock",
    "sg:city":"Chipping Norton",
    "sg:classifiers":[
        {
            "category":"Professional",
            "subcategory":"Engineering",
            "type":"Services"
        }
    ],
    "sg:phone":"+44 1993 868326",
    "sg:postcode":"OX7 3DF",
    "sg:province":"Gloucestershire",
    "sg:tags":[
        "contractor",
        "electrical",
        "engineer"
    ],
    "wof:name":"Brian Claridge",
    "wof:placetype":"venue"
},
  "geometry": {"coordinates":[-1.476287,51.848042],"type":"Point"}
}