{
  "type": "Feature",
  "properties": {
    "iso:country":"GB",
    "sg:address":"Newlands Road Garage, Newlands Road",
    "sg:city":"Corsham",
    "sg:classifiers":[
        {
            "category":"Autos & Motor Vehicles",
            "subcategory":"Auto Supplies",
            "type":"Retail Goods"
        },
        {
            "category":"Retail",
            "subcategory":"Auto Repair",
            "type":"Services"
        }
    ],
    "sg:phone":"+44 1249 712440",
    "sg:postcode":"SN13 0BH",
    "sg:province":"Wiltshire",
    "sg:tags":[
        "garage",
        "related",
        "tyre"
    ],
    "wof:name":"Corsham Tyre Service",
    "wof:placetype":"venue"
},
  "geometry": {"coordinates":[-2.1848390102,51.4358787537],"type":"Point"}
}