{
  "type": "Feature",
  "properties": {
    "iso:country":"GB",
    "sg:address":"133 Goswell Road",
    "sg:city":"London",
    "sg:classifiers":[
        {
            "category":"Food & Beverages",
            "subcategory":"Liquor & Beverages",
            "type":"Retail Goods"
        }
    ],
    "sg:phone":"+44 20 7253 7451",
    "sg:postcode":"EC1V 7JY",
    "sg:province":"Greater London",
    "sg:tags":[
        "beer",
        "spirit",
        "wines"
    ],
    "wof:name":"Goswell Wines",
    "wof:placetype":"venue"
},
  "geometry": {"coordinates":[-0.100731,51.527473],"type":"Point"}
}