{
  "type": "Feature",
  "properties": {
    "addr:full":"Higher Wraxall Dorchester Dorset DT2 0HR",
    "addr:postcode":"dt2 0hr",
    "addr:street":"Dorset",
    "iso:country":"GB",
    "sg:address":"Higher Wraxall",
    "sg:city":"Dorchester",
    "sg:classifiers":[
        {
            "category":"Shopping",
            "subcategory":"Catalog Store",
            "type":"Retail Goods"
        }
    ],
    "sg:phone":"+44 1935 83638",
    "sg:postcode":"DT2 0HR",
    "sg:province":"Dorset",
    "sg:tags":[
        "mail",
        "order"
    ],
    "wof:name":"Denewear",
    "wof:placetype":"venue"
},
  "geometry": {"coordinates":[-2.620519,50.789986],"type":"Point"}
}