{
  "type": "Feature",
  "properties": {
    "iso:country":"GB",
    "sg:address":"Care Of 24 Beresford Rd",
    "sg:city":"Chingford",
    "sg:classifiers":[
        {
            "category":"Organizations",
            "subcategory":"Religious Organization",
            "type":"Services"
        }
    ],
    "sg:phone":"+44 20 8529 8097",
    "sg:postcode":"E4 6EE",
    "sg:province":"Greater London",
    "sg:tags":[
        "organisation"
    ],
    "wof:name":"Science Of Mind",
    "wof:placetype":"venue"
},
  "geometry": {"coordinates":[0.0104,51.63229],"type":"Point"}
}