{
  "type": "Feature",
  "properties": {
    "iso:country":"GB",
    "sg:address":"22 High St, Cheadle",
    "sg:city":"Stoke-on-trent",
    "sg:classifiers":[
        {
            "category":"Shopping",
            "subcategory":"Clothing, Apparel, & Fashions",
            "type":"Retail Goods"
        }
    ],
    "sg:postcode":"ST10 1AF",
    "sg:province":"Staffordshire",
    "sg:tags":[
        "shop"
    ],
    "wof:name":"Munir,M,",
    "wof:placetype":"venue"
},
  "geometry": {"coordinates":[-1.988613,52.987942],"type":"Point"}
}