{
  "type": "Feature",
  "properties": {
    "iso:country":"GB",
    "sg:address":"66a High Street, Debenham",
    "sg:city":"Stowmarket",
    "sg:classifiers":[
        {
            "category":"Real Estate",
            "subcategory":"Real Estate Agent",
            "type":"Services"
        }
    ],
    "sg:phone":"+44 1728 860860",
    "sg:postcode":"IP14 6QP",
    "sg:province":"Suffolk",
    "wof:name":"Abbotts",
    "wof:placetype":"venue"
},
  "geometry": {"coordinates":[1.182594,52.222996],"type":"Point"}
}