{
  "type": "Feature",
  "properties": {
    "addr:full":"2 Central Parade Cleckheaton West Yorkshire BD19 3RU",
    "addr:housenumber":"2",
    "addr:postcode":"bd19 3ru",
    "addr:street":"Central Parade",
    "iso:country":"GB",
    "sg:address":"2 Central Parade",
    "sg:city":"Cleckheaton",
    "sg:classifiers":[
        {
            "category":"Home & Garden",
            "subcategory":"Home Furnishings",
            "type":"Retail Goods"
        }
    ],
    "sg:phone":"+44 1274 862323",
    "sg:postcode":"BD19 3RU",
    "sg:province":"West Yorkshire",
    "sg:tags":[
        "furnishers",
        "planner",
        "kitchen"
    ],
    "wof:name":"Richmond Kitchens",
    "wof:placetype":"venue"
},
  "geometry": {"coordinates":[-1.7118389606,53.7233200073],"type":"Point"}
}