{
  "type": "Feature",
  "properties": {
    "addr:full":"Wallingford Road Didcot Oxfordshire OX11 9DA",
    "addr:postcode":"ox11 9da",
    "addr:street":"Wallingford Road",
    "iso:country":"GB",
    "sg:address":"Wallingford Road",
    "sg:city":"Didcot",
    "sg:classifiers":[
        {
            "category":"Home & Garden",
            "subcategory":"Hardware",
            "type":"Retail Goods"
        }
    ],
    "sg:phone":"+44 1235 811366",
    "sg:postcode":"OX11 9DA",
    "sg:province":"Oxfordshire",
    "sg:tags":[
        "retailer",
        "diy"
    ],
    "wof:name":"Focus Do It All",
    "wof:placetype":"venue"
},
  "geometry": {"coordinates":[-1.1888200045,51.6035385132],"type":"Point"}
}