{
  "type": "Feature",
  "properties": {
    "iso:country":"GB",
    "sg:address":"Worrall Street",
    "sg:city":"Congleton",
    "sg:classifiers":[
        {
            "category":"Community Center",
            "type":"Public Place"
        },
        {
            "category":"Government",
            "subcategory":"Office",
            "type":"Public Place"
        }
    ],
    "sg:phone":"+44 1260 271552",
    "sg:postcode":"CW12 1DT",
    "sg:province":"Cheshire",
    "sg:tags":[
        "recreation",
        "local",
        "leisure",
        "centre"
    ],
    "wof:name":"Congleton Leisure Centre",
    "wof:placetype":"venue"
},
  "geometry": {"coordinates":[-2.208969,53.164703],"type":"Point"}
}