{
  "type": "Feature",
  "properties": {
    "addr:full":"24 Charnock Crescent, Gleadless Sheffield Derbyshire S12 3HB",
    "addr:housenumber":"24",
    "addr:postcode":"s12 3hb",
    "addr:street":"Charnock Crescent",
    "iso:country":"GB",
    "sg:address":"24 Charnock Crescent, Gleadless",
    "sg:city":"Sheffield",
    "sg:classifiers":[
        {
            "category":"Retail",
            "subcategory":"Auto Repair",
            "type":"Services"
        }
    ],
    "sg:postcode":"S12 3HB",
    "sg:province":"Derbyshire",
    "sg:tags":[
        "modification",
        "garage"
    ],
    "wof:name":"D W Autos",
    "wof:placetype":"venue"
},
  "geometry": {"coordinates":[-1.4249490499,53.343421936],"type":"Point"}
}