{
  "type": "Feature",
  "properties": {
    "addr:full":"Werndriw Lodge, 23 High Street Lampeter Carmarthenshire SA48 7BH",
    "addr:housenumber":"23",
    "addr:postcode":"sa48 7bh",
    "addr:street":"High Street",
    "iso:country":"GB",
    "sg:address":"Werndriw Lodge, 23 High Street",
    "sg:city":"Lampeter",
    "sg:classifiers":[
        {
            "category":"Organizations",
            "subcategory":"Non-profit Organization",
            "type":"Services"
        }
    ],
    "sg:phone":"+44 1570 423916",
    "sg:postcode":"SA48 7BH",
    "sg:province":"Carmarthenshire",
    "sg:tags":[
        "organisation",
        "voluntary",
        "charity"
    ],
    "wof:name":"Standing Conference of Voluntary Organisations for People With A",
    "wof:placetype":"venue"
},
  "geometry": {"coordinates":[-4.0774650574,52.1142616272],"type":"Point"}
}