{
  "type": "Feature",
  "properties": {
    "iso:country":"GB",
    "sg:address":"11 Dukes Rd, Eaton Socon",
    "sg:city":"Huntingdon",
    "sg:classifiers":[
        {
            "category":"Building & Trades",
            "subcategory":"Construction",
            "type":"Services"
        }
    ],
    "sg:phone":"+44 1480 476465",
    "sg:postcode":"PE19 3DD",
    "sg:province":"Bedfordshire",
    "sg:tags":[
        "dry",
        "lining",
        "plasterers",
        "screeders"
    ],
    "wof:name":"Valmark",
    "wof:placetype":"venue"
},
  "geometry": {"coordinates":[-0.2893700004,52.2174682617],"type":"Point"}
}