{
  "type": "Feature",
  "properties": {
    "addr:full":"26 Windsor Road Slough Berkshire SL1 3EJ",
    "addr:housenumber":"26",
    "addr:postcode":"sl1 3ej",
    "addr:street":"Windsor Road",
    "iso:country":"GB",
    "sg:address":"26 Windsor Road",
    "sg:city":"Slough",
    "sg:classifiers":[
        {
            "category":"Community Center",
            "subcategory":"Youth",
            "type":"Public Place"
        }
    ],
    "sg:phone":"+44 1753 694225",
    "sg:postcode":"SL1 3EJ",
    "sg:province":"Berkshire",
    "sg:tags":[
        "organisation",
        "centre"
    ],
    "wof:name":"Project Contact",
    "wof:placetype":"venue"
},
  "geometry": {"coordinates":[-0.5959889889,51.5086975098],"type":"Point"}
}