{
  "type": "Feature",
  "properties": {
    "iso:country":"GB",
    "sg:address":"177 Scawby Road, Scawby Brook",
    "sg:city":"Brigg",
    "sg:classifiers":[
        {
            "category":"Bars & Pubs",
            "type":"Food & Drink"
        },
        {
            "category":"Community Center",
            "subcategory":"Social",
            "type":"Public Place"
        }
    ],
    "sg:phone":"+44 1652 653147",
    "sg:postcode":"DN20 9JX",
    "sg:province":"Lincolnshire",
    "sg:tags":[
        "pubs",
        "house",
        "inn",
        "activity"
    ],
    "wof:name":"King William Iv",
    "wof:placetype":"venue"
},
  "geometry": {"coordinates":[-0.516681,53.546867],"type":"Point"}
}