{
  "type": "Feature",
  "properties": {
    "addr:full":"29 Cardwell Avenue Sheffield South Yorkshire S13 7XB",
    "addr:housenumber":"29",
    "addr:postcode":"s13 7xb",
    "addr:street":"Cardwell Avenue",
    "iso:country":"GB",
    "sg:address":"29 Cardwell Avenue",
    "sg:city":"Sheffield",
    "sg:classifiers":[
        {
            "category":"Home & Garden",
            "subcategory":"Carpets & Floor Coverings",
            "type":"Retail Goods"
        }
    ],
    "sg:phone":"+44 114 269 0004",
    "sg:postcode":"S13 7XB",
    "sg:province":"South Yorkshire",
    "sg:tags":[
        "cleaner",
        "upholstery"
    ],
    "wof:name":"Fresh'n'clean",
    "wof:placetype":"venue"
},
  "geometry": {"coordinates":[-1.3849580288,53.361114502],"type":"Point"}
}