{
  "type": "Feature",
  "properties": {
    "addr:full":"3rd Floor Aldershot Hampshire GU11 1TY",
    "addr:housenumber":"3rd floor aldershot",
    "addr:postcode":"gu11 1ty",
    "iso:country":"GB",
    "sg:address":"3rd Floor",
    "sg:city":"Aldershot",
    "sg:classifiers":[
        {
            "category":"Professional",
            "subcategory":"Management & Consulting",
            "type":"Services"
        }
    ],
    "sg:phone":"+44 1252 337500",
    "sg:postcode":"GU11 1TY",
    "sg:province":"Hampshire",
    "sg:tags":[
        "consultant",
        "training"
    ],
    "wof:name":"Guildford Educational Services Ltd.",
    "wof:placetype":"venue"
},
  "geometry": {"coordinates":[-0.7682589889,51.2509498596],"type":"Point"}
}