{
  "type": "Feature",
  "properties": {
    "addr:full":"Cherry Tree House, Prospect Row Chatham Kent ME4 5QY",
    "addr:postcode":"me4 5qy",
    "addr:street":"Prospect Row",
    "iso:country":"GB",
    "sg:address":"Cherry Tree House, Prospect Row",
    "sg:city":"Chatham",
    "sg:classifiers":[
        {
            "category":"Organizations",
            "subcategory":"Community Association",
            "type":"Services"
        }
    ],
    "sg:phone":"+44 1634 845647",
    "sg:postcode":"ME4 5QY",
    "sg:province":"Kent",
    "sg:tags":[
        "society",
        "housing"
    ],
    "wof:name":"Mhs Homes Ltd.",
    "wof:placetype":"venue"
},
  "geometry": {"coordinates":[0.5287659764,51.3781661987],"type":"Point"}
}