{
  "type": "Feature",
  "properties": {
    "addr:full":"Hall Street, Failsworth Manchester Lancashire M35 0JH",
    "addr:postcode":"m35 0jh",
    "addr:street":"Hall Street",
    "iso:country":"GB",
    "sg:address":"Hall Street, Failsworth",
    "sg:city":"Manchester",
    "sg:classifiers":[
        {
            "category":"Retail",
            "subcategory":"Auto Repair",
            "type":"Services"
        }
    ],
    "sg:phone":"+44 161 684 8975",
    "sg:postcode":"M35 0JH",
    "sg:province":"Lancashire",
    "sg:tags":[
        "modification",
        "garage"
    ],
    "wof:name":"R & G van Spares",
    "wof:placetype":"venue"
},
  "geometry": {"coordinates":[-2.173129,53.504333],"type":"Point"}
}