{
  "type": "Feature",
  "properties": {
    "addr:full":"8 Westbourne Grove Darlington Durham DL3 8LS",
    "addr:housenumber":"8",
    "addr:postcode":"dl3 8ls",
    "addr:street":"Westbourne Grove",
    "iso:country":"GB",
    "sg:address":"8 Westbourne Grove",
    "sg:city":"Darlington",
    "sg:classifiers":[
        {
            "category":"Building & Trades",
            "subcategory":"Landscaping Services",
            "type":"Services"
        }
    ],
    "sg:phone":"+44 1325 467644",
    "sg:postcode":"DL3 8LS",
    "sg:province":"Durham",
    "sg:tags":[
        "forestry",
        "surgeon",
        "tree"
    ],
    "wof:name":"Andrew Jackson",
    "wof:placetype":"venue"
},
  "geometry": {"coordinates":[-1.5720499754,54.5246543884],"type":"Point"}
}