{
  "type": "Feature",
  "properties": {
    "addr:full":"Unit 10 Hampers Green Petworth West Sussex GU28 9NR",
    "addr:housenumber":"unit 10",
    "addr:postcode":"gu28 9nr",
    "addr:street":"Hampers Green",
    "iso:country":"GB",
    "sg:address":"Unit 10 Hampers Green",
    "sg:city":"Petworth",
    "sg:classifiers":[
        {
            "category":"Professional",
            "subcategory":"Testing Lab",
            "type":"Services"
        },
        {
            "category":"Retail",
            "subcategory":"Auto Repair",
            "type":"Services"
        }
    ],
    "sg:phone":"+44 1798 344431",
    "sg:postcode":"GU28 9NR",
    "sg:province":"West Sussex",
    "sg:tags":[
        "modification",
        "garage",
        "mot"
    ],
    "wof:name":"Petworth M O T Centre",
    "wof:placetype":"venue"
},
  "geometry": {"coordinates":[-0.607854,50.986107],"type":"Point"}
}