{
  "type": "Feature",
  "properties": {
    "addr:full":"32 Tretawn Gardens, Mayhill London Greater London NW7 4NR",
    "addr:housenumber":"32",
    "addr:postcode":"nw7 4nr",
    "addr:street":"Tretawn Gardens",
    "iso:country":"GB",
    "sg:address":"32 Tretawn Gardens, Mayhill",
    "sg:city":"London",
    "sg:classifiers":[
        {
            "category":"Banks & Credit Unions",
            "subcategory":"Bank",
            "type":"Services"
        }
    ],
    "sg:phone":"+44 20 8906 4480",
    "sg:postcode":"NW7 4NR",
    "sg:province":"Greater London",
    "sg:tags":[
        "stocktaking",
        "inventory"
    ],
    "wof:name":"Harewood Inventories",
    "wof:placetype":"venue"
},
  "geometry": {"coordinates":[-0.245768,51.623486],"type":"Point"}
}