{
  "type": "Feature",
  "properties": {
    "addr:full":"Tudor Lodge, Raunds Road, Chelveston Wellingborough Northamptonshire NN9 6AA",
    "addr:postcode":"nn9 6aa",
    "addr:street":"Raunds Road",
    "iso:country":"GB",
    "sg:address":"Tudor Lodge, Raunds Road, Chelveston",
    "sg:city":"Wellingborough",
    "sg:classifiers":[
        {
            "category":"Building & Trades",
            "subcategory":"Construction",
            "type":"Services"
        }
    ],
    "sg:phone":"+44 1933 625060",
    "sg:postcode":"NN9 6AA",
    "sg:province":"Northamptonshire",
    "sg:tags":[
        "builder"
    ],
    "wof:name":"Mike Daly Developments",
    "wof:placetype":"venue"
},
  "geometry": {"coordinates":[-0.5477589965,52.315776825],"type":"Point"}
}