{
  "type": "Feature",
  "properties": {
    "addr:full":"235 Skipton Road Harrogate North Yorkshire HG1 3EY",
    "addr:housenumber":"235",
    "addr:postcode":"hg1 3ey",
    "addr:street":"Skipton Road",
    "iso:country":"GB",
    "sg:address":"235 Skipton Road",
    "sg:city":"Harrogate",
    "sg:classifiers":[
        {
            "category":"Fast Food",
            "type":"Food & Drink"
        }
    ],
    "sg:phone":"+44 1423 529295",
    "sg:postcode":"HG1 3EY",
    "sg:province":"North Yorkshire",
    "sg:tags":[
        "away",
        "take"
    ],
    "wof:name":"Raj Rana Indian Take Away",
    "wof:placetype":"venue"
},
  "geometry": {"coordinates":[-1.5423099995,54.0054321289],"type":"Point"}
}