{
  "type": "Feature",
  "properties": {
    "addr:full":"Soothouse Spring Valley Industri St Albans Hertfordshire AL1 3UL",
    "addr:postcode":"al1 3ul",
    "addr:street":"Soothouse Spring Valley Industri",
    "iso:country":"GB",
    "sg:address":"Soothouse Spring Valley Industri",
    "sg:city":"St Albans",
    "sg:classifiers":[
        {
            "category":"Home & Garden",
            "subcategory":"Hardware",
            "type":"Retail Goods"
        }
    ],
    "sg:phone":"+44 1727 861361",
    "sg:postcode":"AL1 3UL",
    "sg:province":"Hertfordshire",
    "sg:tags":[
        "device",
        "fixing",
        "fastener"
    ],
    "wof:name":"Andrews Fasteners Ltd.",
    "wof:placetype":"venue"
},
  "geometry": {"coordinates":[-0.337752,51.753189],"type":"Point"}
}