{
  "type": "Feature",
  "properties": {
    "iso:country":"GB",
    "sg:address":"390 Sydenham Road",
    "sg:city":"Croydon",
    "sg:classifiers":[
        {
            "category":"Building & Trades",
            "subcategory":"Construction",
            "type":"Services"
        },
        {
            "category":"Manufacturing",
            "subcategory":"Lumber",
            "type":"Manufacturing & Wholesale Goods"
        }
    ],
    "sg:phone":"+44 20 8683 0292",
    "sg:postcode":"CR0 2EA",
    "sg:province":"Surrey",
    "sg:tags":[
        "joinery",
        "merchants",
        "importer",
        "agent",
        "timber"
    ],
    "wof:name":"J S M Joinery Ltd.",
    "wof:placetype":"venue"
},
  "geometry": {"coordinates":[-0.0913290009,51.3874664307],"type":"Point"}
}