{
  "type": "Feature",
  "properties": {
    "addr:full":"364 The Cliff, Lower Broughton Rd Salford Greater Manchester M7 2HW",
    "addr:housenumber":"364",
    "addr:postcode":"m7 2hw",
    "addr:street":"The Cliff Lower Broughton Rd",
    "iso:country":"GB",
    "sg:address":"364 The Cliff, Lower Broughton Rd",
    "sg:city":"Salford",
    "sg:classifiers":[
        {
            "category":"Building & Trades",
            "subcategory":"Plumbing",
            "type":"Services"
        }
    ],
    "sg:phone":"+44 161 792 2314",
    "sg:postcode":"M7 2HW",
    "sg:province":"Greater Manchester",
    "sg:tags":[
        "heating"
    ],
    "wof:name":"J Buckley",
    "wof:placetype":"venue"
},
  "geometry": {"coordinates":[-2.2685248852,53.5023612976],"type":"Point"}
}