{
  "type": "Feature",
  "properties": {
    "addr:full":"19 Winter Gro St Helens Cheshire WA9 2JT",
    "addr:housenumber":"19",
    "addr:postcode":"wa9 2jt",
    "addr:street":"Winter Gro",
    "iso:country":"GB",
    "sg:address":"19 Winter Gro",
    "sg:city":"St Helens",
    "sg:classifiers":[
        {
            "category":"Manufacturing",
            "subcategory":"Metals",
            "type":"Manufacturing & Wholesale Goods"
        }
    ],
    "sg:phone":"+44 1744 613383",
    "sg:postcode":"WA9 2JT",
    "sg:province":"Cheshire",
    "sg:tags":[
        "steel",
        "fabricator",
        "erectors"
    ],
    "wof:name":"Derbyshire Fabrications",
    "wof:placetype":"venue"
},
  "geometry": {"coordinates":[-2.682031,53.451614],"type":"Point"}
}