{
  "type": "Feature",
  "properties": {
    "addr:full":"Unit 19 Workshops Hinckley Leicestershire LE10 3ES",
    "addr:housenumber":"unit 19",
    "addr:postcode":"le10 3es",
    "addr:street":"Workshops",
    "iso:country":"GB",
    "sg:address":"Unit 19 Workshops",
    "sg:city":"Hinckley",
    "sg:classifiers":[
        {
            "category":"Professional",
            "subcategory":"Engineering",
            "type":"Services"
        }
    ],
    "sg:phone":"+44 1455 250066",
    "sg:postcode":"LE10 3ES",
    "sg:province":"Leicestershire",
    "sg:tags":[
        "precision",
        "engineer"
    ],
    "wof:name":"Bosworth Tools (Cutters) Ltd.",
    "wof:placetype":"venue"
},
  "geometry": {"coordinates":[-1.319384,52.530357],"type":"Point"}
}