{
  "type": "Feature",
  "properties": {
    "addr:full":"Bridge Ho, Bridge St Witney Oxfordshire OX8 6HY",
    "addr:postcode":"ox8 6hy",
    "addr:street":"Ho Bridge St",
    "iso:country":"GB",
    "sg:address":"Bridge Ho, Bridge St",
    "sg:city":"Witney",
    "sg:classifiers":[
        {
            "category":"Professional",
            "subcategory":"Lawyer & Legal Services",
            "type":"Services"
        }
    ],
    "sg:phone":"+44 1865 202435",
    "sg:postcode":"OX8 6HY",
    "sg:province":"Oxfordshire",
    "sg:tags":[
        "advice",
        "counselling"
    ],
    "wof:name":"Oxford Life Group",
    "wof:placetype":"venue"
},
  "geometry": {"coordinates":[-1.4961700439,51.7826309204],"type":"Point"}
}