{
  "type": "Feature",
  "properties": {
    "addr:full":"Unit 12a Chapel Terr Hayle Cornwall TR27 4AB",
    "addr:housenumber":"unit 12a",
    "addr:postcode":"tr27 4ab",
    "addr:street":"Chapel Terr",
    "iso:country":"GB",
    "sg:address":"Unit 12a Chapel Terr",
    "sg:city":"Hayle",
    "sg:classifiers":[
        {
            "category":"Communications",
            "subcategory":"Film & Video Production",
            "type":"Services"
        }
    ],
    "sg:phone":"+44 1736 756756",
    "sg:postcode":"TR27 4AB",
    "sg:province":"Cornwall",
    "sg:tags":[
        "illustrator",
        "artist"
    ],
    "wof:name":"Bajjer Arts Ltd",
    "wof:placetype":"venue"
},
  "geometry": {"coordinates":[-5.420374,50.183678],"type":"Point"}
}