{
  "type": "Feature",
  "properties": {
    "addr:full":"Colville Road, South Acton Trading Estate London Greater London W3 8BL",
    "addr:postcode":"w3 8bl",
    "addr:street":"Colville Road;Trading",
    "iso:country":"GB",
    "sg:address":"Colville Road, South Acton Trading Estate",
    "sg:city":"London",
    "sg:classifiers":[
        {
            "category":"Professional",
            "subcategory":"Printing & Photocopies",
            "type":"Services"
        }
    ],
    "sg:phone":"+44 20 8992 0014",
    "sg:postcode":"W3 8BL",
    "sg:province":"Greater London",
    "sg:tags":[
        "printer"
    ],
    "wof:name":"Image Litho Ltd.",
    "wof:placetype":"venue"
},
  "geometry": {"coordinates":[-0.273014009,51.5003433228],"type":"Point"}
}