{
  "type": "Feature",
  "properties": {
    "addr:full":"141 Sandygate Road Sheffield South Yorkshire S10 5SA",
    "addr:housenumber":"141",
    "addr:postcode":"s10 5sa",
    "addr:street":"Sandygate Road",
    "iso:country":"GB",
    "sg:address":"141 Sandygate Road",
    "sg:city":"Sheffield",
    "sg:classifiers":[
        {
            "category":"Professional",
            "subcategory":"Engineering",
            "type":"Services"
        }
    ],
    "sg:phone":"+44 114 230 1788",
    "sg:postcode":"S10 5SA",
    "sg:province":"South Yorkshire",
    "wof:name":"Hallamshire Electronics & Engineering",
    "wof:placetype":"venue"
},
  "geometry": {"coordinates":[-1.526473999,53.3777999878],"type":"Point"}
}