{
  "type": "Feature",
  "properties": {
    "iso:country":"GB",
    "sg:address":"162-164 Chapeltown Rd",
    "sg:city":"Leeds",
    "sg:classifiers":[
        {
            "category":"Real Estate",
            "subcategory":"Real Estate Agent",
            "type":"Services"
        }
    ],
    "sg:phone":"+44 113 262 4444",
    "sg:postcode":"LS7 4EE",
    "sg:province":"West Yorkshire",
    "wof:name":"Property Leads",
    "wof:placetype":"venue"
},
  "geometry": {"coordinates":[-1.533723,53.813011],"type":"Point"}
}