{
  "type": "Feature",
  "properties": {
    "iso:country":"GB",
    "sg:address":"Flat 6, 24 Emperors Gate",
    "sg:city":"London",
    "sg:classifiers":[
        {
            "category":"Professional",
            "subcategory":"Management & Consulting",
            "type":"Services"
        }
    ],
    "sg:phone":"+44 20 7370 0014",
    "sg:postcode":"SW7 4HS",
    "sg:province":"Greater London",
    "sg:tags":[
        "consultant",
        "business"
    ],
    "wof:name":"Ruben Strategic Marketing Ltd.",
    "wof:placetype":"venue"
},
  "geometry": {"coordinates":[-0.18629,51.495789],"type":"Point"}
}