{
  "type": "Feature",
  "properties": {
    "iso:country":"GB",
    "sg:address":"21 Lisburn Lane, Tuebrook",
    "sg:city":"Liverpool",
    "sg:classifiers":[
        {
            "category":"Government",
            "subcategory":"Post Office",
            "type":"Public Place"
        }
    ],
    "sg:phone":"+44 151 259 6838",
    "sg:postcode":"L13 9AE",
    "sg:province":"Merseyside",
    "wof:name":"Tuebrook Post Office",
    "wof:placetype":"venue"
},
  "geometry": {"coordinates":[-2.9296910763,53.4266242981],"type":"Point"}
}