{
  "type": "Feature",
  "properties": {
    "addr:full":"67 Bargates Christchurch Dorset BH23 1QE",
    "addr:housenumber":"67",
    "addr:postcode":"bh23 1qe",
    "addr:street":"Bargates",
    "iso:country":"GB",
    "sg:address":"67 Bargates",
    "sg:city":"Christchurch",
    "sg:classifiers":[
        {
            "category":"Deli",
            "type":"Food & Drink"
        },
        {
            "category":"Food & Beverages",
            "subcategory":"Specialty",
            "type":"Retail Goods"
        }
    ],
    "sg:phone":"+44 1202 476461",
    "sg:postcode":"BH23 1QE",
    "sg:province":"Dorset",
    "sg:tags":[
        "delivery",
        "snack",
        "sandwich"
    ],
    "wof:name":"Little Venice",
    "wof:placetype":"venue"
},
  "geometry": {"coordinates":[-1.780542,50.737419],"type":"Point"}
}