{
  "type": "Feature",
  "properties": {
    "addr:full":"Jacksons Landings, The Highlight Hartlepool Durham TS24 0XN",
    "addr:postcode":"ts24 0xn",
    "iso:country":"GB",
    "sg:address":"Jacksons Landings, The Highlight",
    "sg:city":"Hartlepool",
    "sg:classifiers":[
        {
            "category":"Shopping",
            "subcategory":"Clothing, Apparel, & Fashions",
            "type":"Retail Goods"
        }
    ],
    "sg:phone":"+44 1429 866103",
    "sg:postcode":"TS24 0XN",
    "sg:province":"Durham",
    "sg:tags":[
        "workwear",
        "protective"
    ],
    "wof:name":"Tog 24 Factory Outlet Store",
    "wof:placetype":"venue"
},
  "geometry": {"coordinates":[-1.2141189575,54.6854057312],"type":"Point"}
}