{
  "type": "Feature",
  "properties": {
    "iso:country":"GB",
    "sg:address":"30 Blenheim Rd",
    "sg:city":"Kidlington",
    "sg:classifiers":[
        {
            "category":"Building & Trades",
            "subcategory":"Construction",
            "type":"Services"
        }
    ],
    "sg:phone":"+44 1865 375006",
    "sg:postcode":"OX5 2HP",
    "sg:province":"Buckinghamshire",
    "sg:tags":[
        "decorator",
        "painter"
    ],
    "wof:name":"A M McKay",
    "wof:placetype":"venue"
},
  "geometry": {"coordinates":[-1.2809640169,51.8184127808],"type":"Point"}
}