{
  "type": "Feature",
  "properties": {
    "addr:full":"33 Otterham Quay Lane, Rainham Gillingham Kent ME8 8ND",
    "addr:housenumber":"33",
    "addr:postcode":"me8 8nd",
    "addr:street":"Otterham Quay Lane",
    "iso:country":"GB",
    "sg:address":"33 Otterham Quay Lane, Rainham",
    "sg:city":"Gillingham",
    "sg:classifiers":[
        {
            "category":"Retail",
            "subcategory":"Repair Shop",
            "type":"Services"
        }
    ],
    "sg:postcode":"ME8 8ND",
    "sg:province":"Kent",
    "sg:tags":[
        "radio",
        "television",
        "video"
    ],
    "wof:name":"J P A Audio Visual",
    "wof:placetype":"venue"
},
  "geometry": {"coordinates":[0.6225,51.363026],"type":"Point"}
}