{
  "type": "Feature",
  "properties": {
    "addr:full":"Ipswich Railway Station Ipswich Suffolk IP2 8AL",
    "addr:postcode":"ip2 8al",
    "iso:country":"GB",
    "sg:address":"Ipswich Railway Station",
    "sg:city":"Ipswich",
    "sg:classifiers":[
        {
            "category":"Cafe",
            "type":"Food & Drink"
        }
    ],
    "sg:phone":"+44 1473 690717",
    "sg:postcode":"IP2 8AL",
    "sg:province":"Suffolk",
    "sg:tags":[
        "tea",
        "room"
    ],
    "wof:name":"Select Service Partner",
    "wof:placetype":"venue"
},
  "geometry": {"coordinates":[1.1445499659,52.05052948],"type":"Point"}
}