{
  "type": "Feature",
  "properties": {
    "addr:full":"Brookmead, Round Chimneys Farm, Glanvilles Wootton Sherborne Dorset DT9 5QQ",
    "addr:postcode":"dt9 5qq",
    "iso:country":"GB",
    "sg:address":"Brookmead, Round Chimneys Farm, Glanvilles Wootton",
    "sg:city":"Sherborne",
    "sg:classifiers":[
        {
            "category":"Farming",
            "subcategory":"Livestock Farm",
            "type":"Manufacturing & Wholesale Goods"
        }
    ],
    "sg:phone":"+44 1963 210209",
    "sg:postcode":"DT9 5QQ",
    "sg:province":"Dorset",
    "sg:tags":[
        "others"
    ],
    "wof:name":"B E J & J Rich & Son",
    "wof:placetype":"venue"
},
  "geometry": {"coordinates":[-2.459634,50.872204],"type":"Point"}
}