{
  "type": "Feature",
  "properties": {
    "addr:full":"16-17 Holborn Viaduct London Greater London EC1A 2AT",
    "addr:housenumber":"16-17",
    "addr:postcode":"ec1a 2at",
    "addr:street":"Holborn Viaduct",
    "iso:country":"GB",
    "sg:address":"16-17 Holborn Viaduct",
    "sg:city":"London",
    "sg:classifiers":[
        {
            "category":"Fast Food",
            "type":"Food & Drink"
        }
    ],
    "sg:phone":"+44 20 7236 7749",
    "sg:postcode":"EC1A 2AT",
    "sg:province":"Greater London",
    "sg:tags":[
        "away",
        "take"
    ],
    "wof:name":"Mendes Takeaway",
    "wof:placetype":"venue"
},
  "geometry": {"coordinates":[-0.10419,51.516804],"type":"Point"}
}