{
  "type": "Feature",
  "properties": {
    "iso:country":"GB",
    "sg:address":"1 Willesley Road",
    "sg:city":"Ashby-de-la-zouch",
    "sg:classifiers":[
        {
            "category":"Building & Trades",
            "subcategory":"Plumbing",
            "type":"Services"
        }
    ],
    "sg:phone":"+44 1530 416580",
    "sg:postcode":"LE65 2QA",
    "sg:province":"Derbyshire",
    "sg:tags":[
        "repair",
        "heating",
        "servicing",
        "boiler"
    ],
    "wof:name":"Trent Heating & Maintenance",
    "wof:placetype":"venue"
},
  "geometry": {"coordinates":[-1.4864690304,52.7385902405],"type":"Point"}
}