{
  "type": "Feature",
  "properties": {
    "addr:full":"The Yews Farm, Pinchbeck Road Spalding Lincolnshire PE11 3PB",
    "addr:postcode":"pe11 3pb",
    "addr:street":"Pinchbeck Road",
    "iso:country":"GB",
    "sg:address":"The Yews Farm, Pinchbeck Road",
    "sg:city":"Spalding",
    "sg:classifiers":[
        {
            "category":"Wholesale",
            "subcategory":"Machinery & Supplies",
            "type":"Manufacturing & Wholesale Goods"
        }
    ],
    "sg:postcode":"PE11 3PB",
    "sg:province":"Lincolnshire",
    "wof:name":"Freir Farm Machinery",
    "wof:placetype":"venue"
},
  "geometry": {"coordinates":[-0.180834,52.761017],"type":"Point"}
}