{
  "type": "Feature",
  "properties": {
    "addr:full":"Springs Blandford Forum Dorset DT11 8DN",
    "addr:postcode":"dt11 8dn",
    "iso:country":"GB",
    "sg:address":"Springs",
    "sg:city":"Blandford Forum",
    "sg:classifiers":[
        {
            "category":"Farming",
            "subcategory":"Dairy Farm",
            "type":"Manufacturing & Wholesale Goods"
        },
        {
            "category":"Farming",
            "subcategory":"Livestock Farm",
            "type":"Manufacturing & Wholesale Goods"
        }
    ],
    "sg:phone":"+44 1725 552257",
    "sg:postcode":"DT11 8DN",
    "sg:province":"Dorset",
    "sg:tags":[
        "others"
    ],
    "wof:name":"W F Meaden & Son Ltd.",
    "wof:placetype":"venue"
},
  "geometry": {"coordinates":[-2.1194889545,50.8693885803],"type":"Point"}
}