{
  "type": "Feature",
  "properties": {
    "iso:country":"GB",
    "sg:address":"12 Britannia Rd",
    "sg:city":"Sale",
    "sg:classifiers":[
        {
            "category":"Building & Trades",
            "subcategory":"Construction",
            "type":"Services"
        }
    ],
    "sg:phone":"+44 161 969 3711",
    "sg:postcode":"M33 2AA",
    "sg:province":"Cheshire",
    "sg:tags":[
        "roofing"
    ],
    "wof:name":"M.A.C Roofing & Cladding Ltd",
    "wof:placetype":"venue"
},
  "geometry": {"coordinates":[-2.3168709278,53.4266166687],"type":"Point"}
}