{
  "type": "Feature",
  "properties": {
    "addr:full":"Parsloe Road, Epping Green Epping Essex CM16 6QB",
    "addr:postcode":"cm16 6qb",
    "addr:street":"Parsloe Road",
    "iso:country":"GB",
    "sg:address":"Parsloe Road, Epping Green",
    "sg:city":"Epping",
    "sg:classifiers":[
        {
            "category":"Building & Trades",
            "subcategory":"Construction",
            "type":"Services"
        }
    ],
    "sg:phone":"+44 1992 890733",
    "sg:postcode":"CM16 6QB",
    "sg:province":"Essex",
    "sg:tags":[
        "concrete"
    ],
    "wof:name":"Fibercon U K Ltd.",
    "wof:placetype":"venue"
},
  "geometry": {"coordinates":[0.0764430016,51.741268158],"type":"Point"}
}