{
  "type": "Feature",
  "properties": {
    "addr:full":"Station Rd Annan Dumfries and Galloway DG12 6AS",
    "addr:postcode":"dg12 6as",
    "addr:street":"Station Rd",
    "iso:country":"GB",
    "sg:address":"Station Rd",
    "sg:city":"Annan",
    "sg:classifiers":[
        {
            "category":"Shopping",
            "subcategory":"Crafts & Fabrics",
            "type":"Retail Goods"
        }
    ],
    "sg:phone":"+44 1461 202812",
    "sg:postcode":"DG12 6AS",
    "sg:province":"Dumfries and Galloway",
    "sg:tags":[
        "knitwear",
        "yarn"
    ],
    "wof:name":"Barry Knitwear Ltd",
    "wof:placetype":"venue"
},
  "geometry": {"coordinates":[-3.2568190098,54.987033844],"type":"Point"}
}