{
  "type": "Feature",
  "properties": {
    "addr:full":"5 Mill Row, Bexley High Street Bexley Kent DA5 1LA",
    "addr:housenumber":"5",
    "addr:postcode":"da5 1la",
    "addr:street":"Mill Row;High Street",
    "iso:country":"GB",
    "sg:address":"5 Mill Row, Bexley High Street",
    "sg:city":"Bexley",
    "sg:classifiers":[
        {
            "category":"Shopping",
            "subcategory":"Musical Instruments",
            "type":"Retail Goods"
        },
        {
            "category":"Shopping",
            "subcategory":"Computers & Home Electronics",
            "type":"Retail Goods"
        }
    ],
    "sg:postcode":"DA5 1LA",
    "sg:province":"Kent",
    "sg:tags":[
        "sound",
        "equipment",
        "sheet",
        "music"
    ],
    "wof:name":"The Guitar Factory",
    "wof:placetype":"venue"
},
  "geometry": {"coordinates":[0.1481769979,51.4413871765],"type":"Point"}
}