{
  "type": "Feature",
  "properties": {
    "iso:country":"GB",
    "sg:address":"264 Stoney Stanton Road",
    "sg:city":"Coventry",
    "sg:classifiers":[
        {
            "category":"Professional",
            "subcategory":"Accounting & Tax Preparation",
            "type":"Services"
        }
    ],
    "sg:phone":"+44 24 7652 5369",
    "sg:postcode":"CV1 4FP",
    "sg:province":"West Midlands",
    "sg:tags":[
        "accountant",
        "activity"
    ],
    "wof:name":"Dedat & Co",
    "wof:placetype":"venue"
},
  "geometry": {"coordinates":[-1.498427,52.419483],"type":"Point"}
}