{
  "type": "Feature",
  "properties": {
    "addr:full":"17 Kingston Park Centre Newcastle-upon-tyne Tyne and Wear NE3 2FP",
    "addr:housenumber":"17",
    "addr:postcode":"ne3 2fp",
    "addr:street":"Kingston Park Centre",
    "iso:country":"GB",
    "sg:address":"17 Kingston Park Centre",
    "sg:city":"Newcastle-upon-tyne",
    "sg:classifiers":[
        {
            "category":"Personal",
            "subcategory":"Beauty Salon",
            "type":"Services"
        }
    ],
    "sg:phone":"+44 191 286 8900",
    "sg:postcode":"NE3 2FP",
    "sg:province":"Tyne and Wear",
    "sg:tags":[
        "unisex",
        "hairdresser"
    ],
    "wof:name":"Piaf Hair Design",
    "wof:placetype":"venue"
},
  "geometry": {"coordinates":[-1.6688300371,55.013168335],"type":"Point"}
}