{
  "type": "Feature",
  "properties": {
    "addr:full":"18 Welches Close, Northfield Birmingham West Midlands B31 2XT",
    "addr:housenumber":"18",
    "addr:postcode":"2xt",
    "addr:street":"Welches Close",
    "iso:country":"GB",
    "sg:address":"18 Welches Close, Northfield",
    "sg:city":"Birmingham",
    "sg:classifiers":[
        {
            "category":"Professional",
            "subcategory":"Engineering",
            "type":"Services"
        }
    ],
    "sg:postcode":"B31 2XT",
    "sg:province":"West Midlands",
    "sg:tags":[
        "contractor",
        "electrical",
        "engineer"
    ],
    "wof:name":"G Hudson & Son",
    "wof:placetype":"venue"
},
  "geometry": {"coordinates":[-1.959665,52.418926],"type":"Point"}
}