{
  "type": "Feature",
  "properties": {
    "addr:full":"102 Whitchurch Rd Cardiff Cardiff CF14 3LY",
    "addr:housenumber":"102",
    "addr:postcode":"cf14 3ly",
    "addr:street":"Whitchurch Rd",
    "iso:country":"GB",
    "sg:address":"102 Whitchurch Rd",
    "sg:city":"Cardiff",
    "sg:classifiers":[
        {
            "category":"Shopping",
            "subcategory":"News",
            "type":"Retail Goods"
        }
    ],
    "sg:postcode":"CF14 3LY",
    "sg:province":"Cardiff",
    "sg:tags":[
        "newsagent"
    ],
    "wof:name":"Patel,M,",
    "wof:placetype":"venue"
},
  "geometry": {"coordinates":[-3.187575,51.500923],"type":"Point"}
}