{
  "type": "Feature",
  "properties": {
    "addr:full":", Wherwell Andover Hampshire SP11 7JP",
    "addr:postcode":"sp11 7jp",
    "iso:country":"GB",
    "sg:address":", Wherwell",
    "sg:city":"Andover",
    "sg:classifiers":[
        {
            "category":"Education",
            "subcategory":"School",
            "type":"Public Place"
        }
    ],
    "sg:phone":"+44 1264 860384",
    "sg:postcode":"SP11 7JP",
    "sg:province":"Hampshire",
    "sg:tags":[
        "local",
        "authority"
    ],
    "wof:name":"Wherwell Primary School",
    "wof:placetype":"venue"
},
  "geometry": {"coordinates":[-1.4447779655,51.1662864685],"type":"Point"}
}