{
  "type": "Feature",
  "properties": {
    "addr:full":"39 Chester Rd, Castle Northwich Cheshire CW8 1HA",
    "addr:housenumber":"39",
    "addr:postcode":"cw8 1ha",
    "addr:street":"Chester Rd",
    "iso:country":"GB",
    "sg:address":"39 Chester Rd, Castle",
    "sg:city":"Northwich",
    "sg:classifiers":[
        {
            "category":"Shopping",
            "subcategory":"Used Merchandise",
            "type":"Retail Goods"
        }
    ],
    "sg:postcode":"CW8 1HA",
    "sg:province":"Cheshire",
    "sg:tags":[
        "shop",
        "second-hand"
    ],
    "wof:name":"Webb,G P,",
    "wof:placetype":"venue"
},
  "geometry": {"coordinates":[-2.5231089592,53.2564849854],"type":"Point"}
}