{
  "type": "Feature",
  "properties": {
    "iso:country":"GB",
    "sg:address":"Tivoli Rd",
    "sg:city":"Margate",
    "sg:classifiers":[
        {
            "category":"Home & Garden",
            "subcategory":"Kitchen Supply",
            "type":"Retail Goods"
        }
    ],
    "sg:phone":"+44 1843 290577",
    "sg:postcode":"CT9 5TA",
    "sg:province":"Kent",
    "sg:tags":[
        "equipment",
        "catering"
    ],
    "wof:name":"Barretts Catering Supplies Ltd",
    "wof:placetype":"venue"
},
  "geometry": {"coordinates":[1.380284,51.379757],"type":"Point"}
}