{
  "type": "Feature",
  "properties": {
    "iso:country":"GB",
    "sg:address":"Whitford Rd, Kilmington",
    "sg:city":"Axminster",
    "sg:classifiers":[
        {
            "category":"Shopping",
            "subcategory":"Department Store",
            "type":"Retail Goods"
        },
        {
            "category":"Food & Beverages",
            "subcategory":"Groceries & Convenience Stores",
            "type":"Retail Goods"
        }
    ],
    "sg:phone":"+44 1297 33203",
    "sg:postcode":"EX13 7RG",
    "sg:province":"Devon",
    "wof:name":"Hurfords Stores",
    "wof:placetype":"venue"
},
  "geometry": {"coordinates":[-3.03303,50.771095],"type":"Point"}
}