{
  "type": "Feature",
  "properties": {
    "iso:country":"GB",
    "sg:address":"5 Kingston Drive, Royton",
    "sg:city":"Oldham",
    "sg:classifiers":[
        {
            "category":"Food & Beverages",
            "subcategory":"Meat & Fish",
            "type":"Retail Goods"
        }
    ],
    "sg:phone":"+44 161 628 0197",
    "sg:postcode":"OL2 5XU",
    "sg:province":"Lancashire",
    "sg:tags":[
        "chip"
    ],
    "wof:name":"Sizzlers",
    "wof:placetype":"venue"
},
  "geometry": {"coordinates":[-2.133256,53.573246],"type":"Point"}
}