{
  "type": "Feature",
  "properties": {
    "addr:full":"177 Fernhill Rd Bootle Merseyside L20 9DU",
    "addr:housenumber":"177",
    "addr:postcode":"l20 9du",
    "addr:street":"Fernhill Rd",
    "iso:country":"GB",
    "sg:address":"177 Fernhill Rd",
    "sg:city":"Bootle",
    "sg:classifiers":[
        {
            "category":"Home & Garden",
            "subcategory":"Building Materials",
            "type":"Retail Goods"
        }
    ],
    "sg:phone":"+44 151 933 3550",
    "sg:postcode":"L20 9DU",
    "sg:province":"Merseyside",
    "sg:tags":[
        "fencing"
    ],
    "wof:name":"Aintree Fencing & Landscapes Co",
    "wof:placetype":"venue"
},
  "geometry": {"coordinates":[-2.979759,53.457699],"type":"Point"}
}