{
  "type": "Feature",
  "properties": {
    "addr:full":"Coat Walls Farm, Acre Lane, Preesall Poulton-le-fylde Lancashire FY6 0HS",
    "addr:postcode":"fy6 0hs",
    "addr:street":"Acre Lane;Poulton-Le-Fylde",
    "iso:country":"GB",
    "sg:address":"Coat Walls Farm, Acre Lane, Preesall",
    "sg:city":"Poulton-le-fylde",
    "sg:classifiers":[
        {
            "category":"Home & Garden",
            "subcategory":"Garden Supply",
            "type":"Retail Goods"
        },
        {
            "category":"Farming",
            "subcategory":"Livestock Farm",
            "type":"Manufacturing & Wholesale Goods"
        }
    ],
    "sg:postcode":"FY6 0HS",
    "sg:province":"Lancashire",
    "sg:tags":[
        "bulb",
        "grower",
        "others"
    ],
    "wof:name":"P G & J E Taylor",
    "wof:placetype":"venue"
},
  "geometry": {"coordinates":[-2.9680089951,53.9234886169],"type":"Point"}
}