{
  "type": "Feature",
  "properties": {
    "iso:country":"GB",
    "sg:address":"Morris House",
    "sg:city":"Stourport-on-severn",
    "sg:classifiers":[
        {
            "category":"Professional",
            "subcategory":"Detective & Security Services",
            "type":"Services"
        }
    ],
    "sg:phone":"+44 1299 877245",
    "sg:postcode":"DY13 8EQ",
    "sg:province":"Worcestershire",
    "sg:tags":[
        "alarm",
        "burglar",
        "system"
    ],
    "wof:name":"Alarm Associates Britannic",
    "wof:placetype":"venue"
},
  "geometry": {"coordinates":[-2.281167,52.338997],"type":"Point"}
}