{
  "type": "Feature",
  "properties": {
    "addr:full":"150 Robin Hood Lane Chatham Kent ME5 9LB",
    "addr:housenumber":"150",
    "addr:postcode":"me5 9lb",
    "addr:street":"Robin Hood Lane",
    "iso:country":"GB",
    "sg:address":"150 Robin Hood Lane",
    "sg:city":"Chatham",
    "sg:classifiers":[
        {
            "category":"Freight",
            "type":"Transportation"
        }
    ],
    "sg:postcode":"ME5 9LB",
    "sg:province":"Kent",
    "sg:tags":[
        "haulage",
        "road"
    ],
    "wof:name":"J R Innes",
    "wof:placetype":"venue"
},
  "geometry": {"coordinates":[0.5270929933,51.3386917114],"type":"Point"}
}