{
  "type": "Feature",
  "properties": {
    "iso:country":"GB",
    "sg:address":"Energy House, Chasewater Heath Business Park, Atwood Road",
    "sg:city":"Burntwood",
    "sg:classifiers":[
        {
            "category":"Professional",
            "subcategory":"Engineering",
            "type":"Services"
        }
    ],
    "sg:phone":"+44 800 136250",
    "sg:postcode":"WS7 8GJ",
    "sg:province":"Staffordshire",
    "sg:tags":[
        "contractor",
        "electrical",
        "engineer"
    ],
    "wof:name":"Electrosafe Ltd.",
    "wof:placetype":"venue"
},
  "geometry": {"coordinates":[-1.920019,52.67976],"type":"Point"}
}