{
  "type": "Feature",
  "properties": {
    "addr:full":"12-13 Salisbury Pavement, Dawes Road, Fulham London Greater London SW6 7HT",
    "addr:housenumber":"12-13",
    "addr:postcode":"sw6 7ht",
    "addr:street":"Salisbury Pavement Dawes Road",
    "iso:country":"GB",
    "sg:address":"12-13 Salisbury Pavement, Dawes Road, Fulham",
    "sg:city":"London",
    "sg:classifiers":[
        {
            "category":"Wholesale",
            "subcategory":"Meat",
            "type":"Manufacturing & Wholesale Goods"
        }
    ],
    "sg:phone":"+44 20 7385 6260",
    "sg:postcode":"SW6 7HT",
    "sg:province":"Greater London",
    "sg:tags":[
        "-"
    ],
    "wof:name":"The West London Catering Butchers Ltd.",
    "wof:placetype":"venue"
},
  "geometry": {"coordinates":[-0.2073599994,51.4809684753],"type":"Point"}
}