{
  "type": "Feature",
  "properties": {
    "iso:country":"GB",
    "sg:address":"28 Mallard Rd, Mountsorrel",
    "sg:city":"Loughborough",
    "sg:classifiers":[
        {
            "category":"Freight",
            "type":"Transportation"
        }
    ],
    "sg:phone":"+44 116 230 1831",
    "sg:postcode":"LE12 7FR",
    "sg:province":"Leicestershire",
    "sg:tags":[
        "haulage",
        "road"
    ],
    "wof:name":"Parrott's Transport",
    "wof:placetype":"venue"
},
  "geometry": {"coordinates":[-1.132199,52.726311],"type":"Point"}
}