{
  "type": "Feature",
  "properties": {
    "addr:full":"6th Street National Agricultural Centre Kenilworth Warwickshire CV8 2RL",
    "addr:postcode":"cv8 2rl",
    "addr:street":"6Th Street",
    "iso:country":"GB",
    "sg:address":"6th Street National Agricultural Centre",
    "sg:city":"Kenilworth",
    "sg:classifiers":[
        {
            "category":"Wholesale",
            "subcategory":"Machinery & Supplies",
            "type":"Manufacturing & Wholesale Goods"
        }
    ],
    "sg:phone":"+44 24 7669 8270",
    "sg:postcode":"CV8 2RL",
    "sg:province":"Warwickshire",
    "wof:name":"Keenan Feedline",
    "wof:placetype":"venue"
},
  "geometry": {"coordinates":[-1.52452,52.339859],"type":"Point"}
}