{
  "type": "Feature",
  "properties": {
    "addr:full":"234 Oakbank Road Perth Perth and Kinross PH1 1DS",
    "addr:housenumber":"234",
    "addr:postcode":"ph1 1ds",
    "addr:street":"Oakbank Road",
    "iso:country":"GB",
    "sg:address":"234 Oakbank Road",
    "sg:city":"Perth",
    "sg:classifiers":[
        {
            "category":"Travel",
            "subcategory":"Travel Agent",
            "type":"Entertainment"
        }
    ],
    "sg:postcode":"PH1 1DS",
    "sg:province":"Perth and Kinross",
    "wof:name":"Schiehallion Walking Holidays",
    "wof:placetype":"venue"
},
  "geometry": {"coordinates":[-3.4791779518,56.3941459656],"type":"Point"}
}