{
  "type": "Feature",
  "properties": {
    "addr:full":"675 Finchley Road London Greater London NW2 2JP",
    "addr:housenumber":"675",
    "addr:postcode":"nw2 2jp",
    "addr:street":"Finchley Road",
    "iso:country":"GB",
    "sg:address":"675 Finchley Road",
    "sg:city":"London",
    "sg:classifiers":[
        {
            "category":"Fast Food",
            "type":"Food & Drink"
        },
        {
            "category":"Restaurant",
            "type":"Food & Drink"
        }
    ],
    "sg:phone":"+44 20 7794 8499",
    "sg:postcode":"NW2 2JP",
    "sg:province":"Greater London",
    "sg:tags":[
        "away",
        "take"
    ],
    "wof:name":"Quincys",
    "wof:placetype":"venue"
},
  "geometry": {"coordinates":[-0.197385,51.56139],"type":"Point"}
}