{
  "type": "Feature",
  "properties": {
    "addr:full":"Marsh Lane Farm, Tintinhull Yeovil Dorset BA22 8QJ",
    "addr:postcode":"ba22 8qj",
    "addr:street":"Marsh Lane",
    "iso:country":"GB",
    "sg:address":"Marsh Lane Farm, Tintinhull",
    "sg:city":"Yeovil",
    "sg:classifiers":[
        {
            "category":"Personal",
            "subcategory":"Adult",
            "type":"Services"
        }
    ],
    "sg:phone":"+44 1935 825480",
    "sg:postcode":"BA22 8QJ",
    "sg:province":"Dorset",
    "sg:tags":[
        "equestrian"
    ],
    "wof:name":"P Clements",
    "wof:placetype":"venue"
},
  "geometry": {"coordinates":[-2.720667,50.971909],"type":"Point"}
}