{
  "type": "Feature",
  "properties": {
    "addr:full":"West Hall Farm, Whittington Carnforth Cumbria LA6 2PD",
    "addr:postcode":"la6 2pd",
    "addr:street":"Farm",
    "iso:country":"GB",
    "sg:address":"West Hall Farm, Whittington",
    "sg:city":"Carnforth",
    "sg:classifiers":[
        {
            "category":"Farming",
            "subcategory":"Livestock Farm",
            "type":"Manufacturing & Wholesale Goods"
        }
    ],
    "sg:phone":"+44 15242 71463",
    "sg:postcode":"LA6 2PD",
    "sg:province":"Cumbria",
    "sg:tags":[
        "others"
    ],
    "wof:name":"W & S Airey",
    "wof:placetype":"venue"
},
  "geometry": {"coordinates":[-2.611882925,54.1807327271],"type":"Point"}
}