{
  "type": "Feature",
  "properties": {
    "iso:country":"GB",
    "sg:address":"Canal Villa, Canal Road",
    "sg:city":"Congleton",
    "sg:classifiers":[
        {
            "category":"Real Estate",
            "subcategory":"Real Estate Services",
            "type":"Services"
        },
        {
            "category":"Building & Trades",
            "subcategory":"Equipment Rental",
            "type":"Services"
        }
    ],
    "sg:phone":"+44 1260 275052",
    "sg:postcode":"CW12 3AT",
    "sg:province":"Cheshire",
    "sg:tags":[
        "hire",
        "leasing",
        "plant",
        "machinery"
    ],
    "wof:name":"Peter Hibbert",
    "wof:placetype":"venue"
},
  "geometry": {"coordinates":[-2.212205,53.163635],"type":"Point"}
}