{
  "type": "Feature",
  "properties": {
    "addr:full":"7 St Stephens Road Kettering Northamptonshire NN15 5DS",
    "addr:housenumber":"7",
    "addr:postcode":"nn15 5ds",
    "addr:street":"St Stephens Road",
    "iso:country":"GB",
    "sg:address":"7 St Stephens Road",
    "sg:city":"Kettering",
    "sg:classifiers":[
        {
            "category":"Personal",
            "subcategory":"Beauty Salon",
            "type":"Services"
        },
        {
            "category":"Personal",
            "subcategory":"Barber",
            "type":"Services"
        }
    ],
    "sg:phone":"+44 1536 524188",
    "sg:postcode":"NN15 5DS",
    "sg:province":"Northamptonshire",
    "sg:tags":[
        "unisex",
        "hairdresser"
    ],
    "wof:name":"GEORGES HAIR STUDIO",
    "wof:placetype":"venue"
},
  "geometry": {"coordinates":[-0.6899390221,52.3940467834],"type":"Point"}
}