{
  "type": "Feature",
  "properties": {
    "iso:country":"GB",
    "sg:address":"The Annex Burton House, 83 Burton Rd",
    "sg:city":"Derby",
    "sg:classifiers":[
        {
            "category":"Professional",
            "subcategory":"Management & Consulting",
            "type":"Services"
        }
    ],
    "sg:phone":"+44 1332 721021",
    "sg:postcode":"DE1 1TJ",
    "sg:province":"Derbyshire",
    "sg:tags":[
        "consultant",
        "business"
    ],
    "wof:name":"TPG Training Services",
    "wof:placetype":"venue"
},
  "geometry": {"coordinates":[-1.481356,52.914997],"type":"Point"}
}