{
  "type": "Feature",
  "properties": {
    "iso:country":"GB",
    "sg:address":"25 Bridge Street, Framlingham",
    "sg:city":"Woodbridge",
    "sg:classifiers":[
        {
            "category":"Shopping",
            "subcategory":"Pets & Pet Supplies",
            "type":"Retail Goods"
        }
    ],
    "sg:phone":"+44 1728 724571",
    "sg:postcode":"IP13 9AJ",
    "sg:province":"Suffolk",
    "sg:tags":[
        "shop"
    ],
    "wof:name":"Bridge Street Pet Shop",
    "wof:placetype":"venue"
},
  "geometry": {"coordinates":[1.3433320522,52.22108078],"type":"Point"}
}