{
  "type": "Feature",
  "properties": {
    "addr:full":"47 Coinagehall St Helston Cornwall TR13 8EU",
    "addr:housenumber":"47",
    "addr:postcode":"tr13 8eu",
    "addr:street":"Coinagehall St",
    "iso:country":"GB",
    "sg:address":"47 Coinagehall St",
    "sg:city":"Helston",
    "sg:classifiers":[
        {
            "category":"Personal",
            "subcategory":"Beauty Salon",
            "type":"Services"
        }
    ],
    "sg:postcode":"TR13 8EU",
    "sg:province":"Cornwall",
    "sg:tags":[
        "unisex",
        "hairdresser"
    ],
    "wof:name":"Thomas,Keith,",
    "wof:placetype":"venue"
},
  "geometry": {"coordinates":[-5.2772011757,50.1006164551],"type":"Point"}
}