{
  "type": "Feature",
  "properties": {
    "addr:full":"Fulbourn Road, Teversham Cambridge Cambridgeshire CB1 5AN",
    "addr:postcode":"cb1 5an",
    "addr:street":"Fulbourn Road",
    "iso:country":"GB",
    "sg:address":"Fulbourn Road, Teversham",
    "sg:city":"Cambridge",
    "sg:classifiers":[
        {
            "category":"Wholesale",
            "subcategory":"Machinery & Supplies",
            "type":"Manufacturing & Wholesale Goods"
        },
        {
            "category":"Farming",
            "subcategory":"Farm",
            "type":"Manufacturing & Wholesale Goods"
        }
    ],
    "sg:postcode":"CB1 5AN",
    "sg:province":"Cambridgeshire",
    "sg:tags":[
        "agricultural"
    ],
    "wof:name":"Gaze Tractors",
    "wof:placetype":"venue"
},
  "geometry": {"coordinates":[0.2230339944,52.182434082],"type":"Point"}
}