{
  "type": "Feature",
  "properties": {
    "iso:country":"GB",
    "sg:address":"28 Old Brompton Rd",
    "sg:city":"South Kensington",
    "sg:classifiers":[
        {
            "category":"Taxi",
            "type":"Transportation"
        }
    ],
    "sg:phone":"+44 20 7349 8765",
    "sg:postcode":"SW7 3DL",
    "sg:province":"Greater London",
    "sg:tags":[
        "mini",
        "cab"
    ],
    "wof:name":"Airport Taxis & Beaufort Cars",
    "wof:placetype":"venue"
},
  "geometry": {"coordinates":[-0.17522,51.493603],"type":"Point"}
}