{
  "type": "Feature",
  "properties": {
    "addr:full":"19 Fairground Way, Riverside Business Park Northampton Northamptonshire NN3 9HU",
    "addr:housenumber":"19",
    "addr:postcode":"nn3 9hu",
    "addr:street":"Fairground Way",
    "iso:country":"GB",
    "sg:address":"19 Fairground Way, Riverside Business Park",
    "sg:city":"Northampton",
    "sg:classifiers":[
        {
            "category":"Home & Garden",
            "subcategory":"Furniture",
            "type":"Retail Goods"
        }
    ],
    "sg:phone":"+44 1604 409309",
    "sg:postcode":"NN3 9HU",
    "sg:province":"Northamptonshire",
    "wof:name":"Harveys Furnishing Group Ltd.",
    "wof:placetype":"venue"
},
  "geometry": {"coordinates":[-0.835219,52.242889],"type":"Point"}
}