{
  "type": "Feature",
  "properties": {
    "addr:full":"Oban Times Buildings, Corran Esplanade Oban Argyll and Bute PA34 5PX",
    "addr:postcode":"pa34 5px",
    "addr:street":"Corran Esplanade",
    "iso:country":"GB",
    "sg:address":"Oban Times Buildings, Corran Esplanade",
    "sg:city":"Oban",
    "sg:classifiers":[
        {
            "category":"Professional",
            "subcategory":"Lawyer & Legal Services",
            "type":"Services"
        }
    ],
    "sg:phone":"+44 1631 563297",
    "sg:postcode":"PA34 5PX",
    "sg:province":"Argyll and Bute",
    "sg:tags":[
        "advice",
        "counselling"
    ],
    "wof:name":"Marriage Counselling",
    "wof:placetype":"venue"
},
  "geometry": {"coordinates":[-5.47367,56.415932],"type":"Point"}
}