{
  "type": "Feature",
  "properties": {
    "iso:country":"GB",
    "sg:address":"John Barker Place",
    "sg:city":"Hitchin",
    "sg:classifiers":[
        {
            "category":"Community Center",
            "type":"Public Place"
        }
    ],
    "sg:phone":"+44 1462 452098",
    "sg:postcode":"SG5 2PG",
    "sg:province":"Bedfordshire",
    "sg:tags":[
        "centre"
    ],
    "wof:name":"Westmill Centre Bar Ltd.",
    "wof:placetype":"venue"
},
  "geometry": {"coordinates":[-0.291374,51.959106],"type":"Point"}
}