{
  "type": "Feature",
  "properties": {
    "iso:country":"GB",
    "sg:address":"20 The Broadway",
    "sg:city":"London",
    "sg:classifiers":[
        {
            "category":"Restaurant",
            "type":"Food & Drink"
        }
    ],
    "sg:phone":"+44 20 8959 2428",
    "sg:postcode":"NW7 3LL",
    "sg:province":"Greater London",
    "wof:name":"Jenny's Restaurant",
    "wof:placetype":"venue"
},
  "geometry": {"coordinates":[-0.248121,51.614178],"type":"Point"}
}