{
  "type": "Feature",
  "properties": {
    "addr:full":"The Oast, Forge Farm, Tonbridge Rd, Mereworth Maidstone Kent ME18 5JF",
    "addr:postcode":"me18 5jf",
    "addr:street":"Tonbridge Rd",
    "iso:country":"GB",
    "sg:address":"The Oast, Forge Farm, Tonbridge Rd, Mereworth",
    "sg:city":"Maidstone",
    "sg:classifiers":[
        {
            "category":"Utilities",
            "subcategory":"Natural Gas",
            "type":"Services"
        }
    ],
    "sg:phone":"+44 1622 813466",
    "sg:postcode":"ME18 5JF",
    "sg:province":"Kent",
    "sg:tags":[
        "control",
        "energy",
        "management",
        "system"
    ],
    "wof:name":"W Emery",
    "wof:placetype":"venue"
},
  "geometry": {"coordinates":[0.378152,51.259106],"type":"Point"}
}