{
  "type": "Feature",
  "properties": {
    "addr:full":"110 Newton Road Newcastle-upon-tyne Tyne and Wear NE7 7HN",
    "addr:housenumber":"110",
    "addr:postcode":"ne7 7hn",
    "addr:street":"Newton Road",
    "iso:country":"GB",
    "sg:address":"110 Newton Road",
    "sg:city":"Newcastle-upon-tyne",
    "sg:classifiers":[
        {
            "category":"Food & Beverages",
            "subcategory":"Candy",
            "type":"Retail Goods"
        }
    ],
    "sg:phone":"+44 191 281 7953",
    "sg:postcode":"NE7 7HN",
    "sg:province":"Tyne and Wear",
    "sg:tags":[
        "confectioner"
    ],
    "wof:name":"Doreens",
    "wof:placetype":"venue"
},
  "geometry": {"coordinates":[-1.587065,54.995895],"type":"Point"}
}