{
  "type": "Feature",
  "properties": {
    "iso:country":"GB",
    "sg:address":"Waldeck House, 2 Waldeck Road",
    "sg:city":"Luton",
    "sg:classifiers":[
        {
            "category":"Retail",
            "subcategory":"Storage",
            "type":"Services"
        }
    ],
    "sg:postcode":"LU1 1HG",
    "sg:province":"Bedfordshire",
    "sg:tags":[
        "household",
        "removal"
    ],
    "wof:name":"R D Freeman (Warehousing) Ltd.",
    "wof:placetype":"venue"
},
  "geometry": {"coordinates":[-0.426134,51.885464],"type":"Point"}
}