{
  "type": "Feature",
  "properties": {
    "addr:full":"6th Floor 3 Minster Court, Mincing Lane London Greater London EC3R 7DD",
    "addr:housenumber":"6th floor 3",
    "addr:postcode":"ec3r 7dd",
    "addr:street":"Minster Court Mincing Lane",
    "iso:country":"GB",
    "sg:address":"6th Floor 3 Minster Court, Mincing Lane",
    "sg:city":"London",
    "sg:classifiers":[
        {
            "category":"Professional",
            "subcategory":"Detective & Security Services",
            "type":"Services"
        }
    ],
    "sg:phone":"+44 20 7626 0486",
    "sg:postcode":"EC3R 7DD",
    "sg:province":"Greater London",
    "sg:tags":[
        "underwriter"
    ],
    "wof:name":"Catlin Underwriting Agencies Ltd.",
    "wof:placetype":"venue"
},
  "geometry": {"coordinates":[-0.081619,51.510464],"type":"Point"}
}