{
  "type": "Feature",
  "properties": {
    "iso:country":"GB",
    "sg:address":"9 Christopher Street",
    "sg:city":"London",
    "sg:classifiers":[
        {
            "category":"Restaurant",
            "type":"Food & Drink"
        }
    ],
    "sg:phone":"+44 20 7247 8288",
    "sg:postcode":"EC2A 2BS",
    "sg:province":"Greater London",
    "wof:name":"Alexander's",
    "wof:placetype":"venue"
},
  "geometry": {"coordinates":[-0.0846140012,51.521396637],"type":"Point"}
}