{
  "type": "Feature",
  "properties": {
    "iso:country":"GB",
    "sg:address":"Wolverhampton Road",
    "sg:city":"Birmingham",
    "sg:classifiers":[
        {
            "category":"Arena",
            "subcategory":"Sports Club",
            "type":"Entertainment"
        }
    ],
    "sg:phone":"+44 121 429 2808",
    "sg:postcode":"B32 2AY",
    "sg:province":"West Midlands",
    "wof:name":"Midland Red (Bearwood) Social Club Ltd.",
    "wof:placetype":"venue"
},
  "geometry": {"coordinates":[-1.9843189716,52.4658737183],"type":"Point"}
}