{
  "type": "Feature",
  "properties": {
    "iso:country":"GB",
    "sg:address":"98 Britannia Rd",
    "sg:city":"Leeds",
    "sg:classifiers":[
        {
            "category":"Autos & Motor Vehicles",
            "subcategory":"Automobile Sales",
            "type":"Retail Goods"
        }
    ],
    "sg:phone":"+44 113 253 5666",
    "sg:postcode":"LS27 0DT",
    "sg:province":"West Yorkshire",
    "sg:tags":[
        "car"
    ],
    "wof:name":"Howley Park Motor Co",
    "wof:placetype":"venue"
},
  "geometry": {"coordinates":[-1.607969,53.737091],"type":"Point"}
}