{
  "type": "Feature",
  "properties": {
    "iso:country":"GB",
    "sg:address":"13 Warrington Market, Bank Street",
    "sg:city":"Warrington",
    "sg:classifiers":[
        {
            "category":"Home & Garden",
            "subcategory":"Home Furnishings",
            "type":"Retail Goods"
        }
    ],
    "sg:phone":"+44 1925 631056",
    "sg:postcode":"WA1 2EN",
    "sg:province":"Cheshire",
    "sg:tags":[
        "decorative",
        "glass",
        "mirror"
    ],
    "wof:name":"Superframe",
    "wof:placetype":"venue"
},
  "geometry": {"coordinates":[-2.59178,53.38802],"type":"Point"}
}