{
  "type": "Feature",
  "properties": {
    "addr:full":"Unit 8 Bath Road, Business Centre Bath Road Devizes Wiltshire SN10 1XA",
    "addr:housenumber":"unit 8",
    "addr:postcode":"sn10 1xa",
    "addr:street":"Bath Road;Bath Road",
    "iso:country":"GB",
    "sg:address":"Unit 8 Bath Road, Business Centre Bath Road",
    "sg:city":"Devizes",
    "sg:classifiers":[
        {
            "category":"Utilities",
            "subcategory":"Natural Gas",
            "type":"Services"
        }
    ],
    "sg:postcode":"SN10 1XA",
    "sg:province":"Wiltshire",
    "sg:tags":[
        "control",
        "energy",
        "management",
        "system"
    ],
    "wof:name":"Swift 1188 Ltd.",
    "wof:placetype":"venue"
},
  "geometry": {"coordinates":[-2.0119290352,51.3523597717],"type":"Point"}
}