{
  "type": "Feature",
  "properties": {
    "addr:full":"42 Theobalds Road London Greater London WC1X 8NW",
    "addr:housenumber":"42",
    "addr:postcode":"wc1x 8nw",
    "addr:street":"Theobalds Road",
    "iso:country":"GB",
    "sg:address":"42 Theobalds Road",
    "sg:city":"London",
    "sg:classifiers":[
        {
            "category":"Building & Trades",
            "subcategory":"Construction",
            "type":"Services"
        }
    ],
    "sg:phone":"+44 20 7404 3996",
    "sg:postcode":"WC1X 8NW",
    "sg:province":"Greater London",
    "sg:tags":[
        "builder"
    ],
    "wof:name":"A H Diamond & Son Ltd.",
    "wof:placetype":"venue"
},
  "geometry": {"coordinates":[-0.116006,51.520943],"type":"Point"}
}