{
  "type": "Feature",
  "properties": {
    "addr:full":"35 Appleton Gate Newark Nottinghamshire NG24 1JR",
    "addr:housenumber":"35",
    "addr:postcode":"ng24 1jr",
    "addr:street":"Appleton Gate",
    "iso:country":"GB",
    "sg:address":"35 Appleton Gate",
    "sg:city":"Newark",
    "sg:classifiers":[
        {
            "category":"Food & Beverages",
            "subcategory":"Liquor & Beverages",
            "type":"Retail Goods"
        }
    ],
    "sg:postcode":"NG24 1JR",
    "sg:province":"Nottinghamshire",
    "sg:tags":[
        "beer",
        "spirit",
        "wines"
    ],
    "wof:name":"Ian G & Sylvia Howe",
    "wof:placetype":"venue"
},
  "geometry": {"coordinates":[-0.806255,53.07724],"type":"Point"}
}