{
  "type": "Feature",
  "properties": {
    "iso:country":"GB",
    "sg:address":"Redhills Road, Arnside",
    "sg:city":"Carnforth",
    "sg:classifiers":[
        {
            "category":"Organizations",
            "subcategory":"Community Association",
            "type":"Services"
        }
    ],
    "sg:phone":"+44 1524 762165",
    "sg:postcode":"LA5 0AT",
    "sg:province":"Cumbria",
    "sg:tags":[
        "society",
        "housing"
    ],
    "wof:name":"Crossfield House",
    "wof:placetype":"venue"
},
  "geometry": {"coordinates":[-2.832406,54.198524],"type":"Point"}
}