{
  "type": "Feature",
  "properties": {
    "addr:full":"1 Kingsway, Kingswood Bristol City of Bristol BS15 8BF",
    "addr:housenumber":"1",
    "addr:postcode":"bs15 8bf",
    "addr:street":"Kingsway",
    "iso:country":"GB",
    "sg:address":"1 Kingsway, Kingswood",
    "sg:city":"Bristol",
    "sg:classifiers":[
        {
            "category":"Home & Garden",
            "subcategory":"Carpets & Floor Coverings",
            "type":"Retail Goods"
        }
    ],
    "sg:phone":"+44 117 967 4847",
    "sg:postcode":"BS15 8BF",
    "sg:province":"City of Bristol",
    "sg:tags":[
        "carpets",
        "rug",
        "matting"
    ],
    "wof:name":"Kingsway Carpets",
    "wof:placetype":"venue"
},
  "geometry": {"coordinates":[-2.5914289951,51.453666687],"type":"Point"}
}