{
  "type": "Feature",
  "properties": {
    "addr:full":"St. Davids New Rd Newtown Powys SY16 1AS",
    "addr:postcode":"sy16 1as",
    "addr:street":"St. Davids New Rd",
    "iso:country":"GB",
    "sg:address":"St. Davids New Rd",
    "sg:city":"Newtown",
    "sg:classifiers":[
        {
            "category":"Utilities",
            "subcategory":"Fuel Oil & Lpg",
            "type":"Services"
        }
    ],
    "sg:phone":"+44 1686 625521",
    "sg:postcode":"SY16 1AS",
    "sg:province":"Powys",
    "wof:name":"F.W Rodway & Son",
    "wof:placetype":"venue"
},
  "geometry": {"coordinates":[-3.3146119118,52.5127754211],"type":"Point"}
}