{
  "type": "Feature",
  "properties": {
    "addr:full":"Red House Farm, Redding Pit Lane, Winford Bristol Somerset BS40 8DL",
    "addr:postcode":"bs40 8dl",
    "addr:street":"Pit Lane",
    "iso:country":"GB",
    "sg:address":"Red House Farm, Redding Pit Lane, Winford",
    "sg:city":"Bristol",
    "sg:classifiers":[
        {
            "category":"Farming",
            "subcategory":"Farm",
            "type":"Manufacturing & Wholesale Goods"
        }
    ],
    "sg:postcode":"BS40 8DL",
    "sg:province":"Somerset",
    "sg:tags":[
        "mixed",
        "crop"
    ],
    "wof:name":"M J Patch & Sons",
    "wof:placetype":"venue"
},
  "geometry": {"coordinates":[-2.6620140076,51.3826217651],"type":"Point"}
}