{
  "type": "Feature",
  "properties": {
    "addr:full":"7 Hollydale Dr Bromley Kent BR2 8QL",
    "addr:housenumber":"7",
    "addr:postcode":"br2 8ql",
    "addr:street":"Hollydale Dr",
    "iso:country":"GB",
    "sg:address":"7 Hollydale Dr",
    "sg:city":"Bromley",
    "sg:classifiers":[
        {
            "category":"Professional",
            "subcategory":"Accounting & Tax Preparation",
            "type":"Services"
        }
    ],
    "sg:postcode":"BR2 8QL",
    "sg:province":"Kent",
    "sg:tags":[
        "consultant"
    ],
    "wof:name":"Simpson Froud",
    "wof:placetype":"venue"
},
  "geometry": {"coordinates":[0.048208,51.368587],"type":"Point"}
}