{
  "type": "Feature",
  "properties": {
    "addr:full":"51 Northumberland Pl Teignmouth Devon TQ14 8DE",
    "addr:housenumber":"51",
    "addr:postcode":"tq14 8de",
    "addr:street":"Northumberland Pl",
    "iso:country":"GB",
    "sg:address":"51 Northumberland Pl",
    "sg:city":"Teignmouth",
    "sg:classifiers":[
        {
            "category":"Communications",
            "type":"Services"
        }
    ],
    "sg:phone":"+44 1626 772077",
    "sg:postcode":"TQ14 8DE",
    "sg:province":"Devon",
    "sg:tags":[
        "tv",
        "video",
        "radio"
    ],
    "wof:name":"TV Plus",
    "wof:placetype":"venue"
},
  "geometry": {"coordinates":[-3.4978859425,50.5456504822],"type":"Point"}
}