{
  "type": "Feature",
  "properties": {
    "addr:full":"Old Edinburgh Road, Uddingston Glasgow Glasgow City G71 6PQ",
    "addr:postcode":"g71 6pq",
    "addr:street":"Old Edinburgh Road",
    "iso:country":"GB",
    "sg:address":"Old Edinburgh Road, Uddingston",
    "sg:city":"Glasgow",
    "sg:classifiers":[
        {
            "category":"Shopping",
            "subcategory":"Stationery & Office Supplies",
            "type":"Retail Goods"
        },
        {
            "category":"Manufacturing",
            "subcategory":"Wood Products",
            "type":"Manufacturing & Wholesale Goods"
        }
    ],
    "sg:phone":"+44 1698 812901",
    "sg:postcode":"G71 6PQ",
    "sg:province":"Glasgow City",
    "sg:tags":[
        "box",
        "packaging",
        "carton",
        "crate",
        "pallets"
    ],
    "wof:name":"Smurfit Corrugated U K",
    "wof:placetype":"venue"
},
  "geometry": {"coordinates":[-4.070824,55.829144],"type":"Point"}
}