{
  "type": "Feature",
  "properties": {
    "iso:country":"GB",
    "sg:address":"The Holkham Estate",
    "sg:city":"Wells-next-the-sea",
    "sg:classifiers":[
        {
            "category":"Museum",
            "subcategory":"Art Museum",
            "type":"Entertainment"
        }
    ],
    "sg:phone":"+44 1328 710806",
    "sg:postcode":"NR23 1AB",
    "sg:province":"Norfolk",
    "sg:tags":[
        "gallery"
    ],
    "wof:name":"Coke Estates Ltd.",
    "wof:placetype":"venue"
},
  "geometry": {"coordinates":[0.85581,52.952644],"type":"Point"}
}