{
  "type": "Feature",
  "properties": {
    "iso:country":"GB",
    "sg:address":"141 Cape Road",
    "sg:city":"Warwick",
    "sg:classifiers":[
        {
            "category":"Professional",
            "subcategory":"Engineering",
            "type":"Services"
        },
        {
            "category":"Building & Trades",
            "subcategory":"Electrical",
            "type":"Services"
        }
    ],
    "sg:phone":"+44 1926 498837",
    "sg:postcode":"CV34 5DJ",
    "sg:province":"Warwickshire",
    "sg:tags":[
        "engineer",
        "electrician",
        "contractor"
    ],
    "wof:name":"R B Electrical Engineers",
    "wof:placetype":"venue"
},
  "geometry": {"coordinates":[-1.5956720114,52.289981842],"type":"Point"}
}