{
  "type": "Feature",
  "properties": {
    "iso:country":"GB",
    "sg:address":"110 High Street",
    "sg:city":"Deal",
    "sg:classifiers":[
        {
            "category":"Personal",
            "subcategory":"Barber",
            "type":"Services"
        }
    ],
    "sg:postcode":"CT14 6HJ",
    "sg:province":"Kent",
    "sg:tags":[
        "men's",
        "hairdresser"
    ],
    "wof:name":"The Clipper Cabin",
    "wof:placetype":"venue"
},
  "geometry": {"coordinates":[1.402792,51.225594],"type":"Point"}
}