{
  "type": "Feature",
  "properties": {
    "addr:full":"21 High Street Innerleithen Scottish Borders EH44 6HA",
    "addr:housenumber":"21",
    "addr:postcode":"eh44 6ha",
    "addr:street":"High Street",
    "iso:country":"GB",
    "sg:address":"21 High Street",
    "sg:city":"Innerleithen",
    "sg:classifiers":[
        {
            "category":"Fast Food",
            "type":"Food & Drink"
        }
    ],
    "sg:phone":"+44 1896 831036",
    "sg:postcode":"EH44 6HA",
    "sg:province":"Scottish Borders",
    "sg:tags":[
        "away",
        "meal",
        "outlet",
        "take"
    ],
    "wof:name":"Happy Days",
    "wof:placetype":"venue"
},
  "geometry": {"coordinates":[-3.062216,55.619465],"type":"Point"}
}