{
  "type": "Feature",
  "properties": {
    "addr:full":"Hillview, Greenway, Rock Kidderminster Shropshire DY14 9SH",
    "addr:postcode":"dy14 9sh",
    "addr:street":"Greenway",
    "iso:country":"GB",
    "sg:address":"Hillview, Greenway, Rock",
    "sg:city":"Kidderminster",
    "sg:classifiers":[
        {
            "category":"Building & Trades",
            "subcategory":"Construction",
            "type":"Services"
        }
    ],
    "sg:phone":"+44 1299 832990",
    "sg:postcode":"DY14 9SH",
    "sg:province":"Shropshire",
    "sg:tags":[
        "builder"
    ],
    "wof:name":"J S Builders",
    "wof:placetype":"venue"
},
  "geometry": {"coordinates":[-2.3899700642,52.3388175964],"type":"Point"}
}