{
  "type": "Feature",
  "properties": {
    "addr:full":"254 Upper Tooting Road London Greater London SW17 0DN",
    "addr:housenumber":"254",
    "addr:postcode":"sw17 0dn",
    "addr:street":"Upper Tooting Road",
    "iso:country":"GB",
    "sg:address":"254 Upper Tooting Road",
    "sg:city":"London",
    "sg:classifiers":[
        {
            "category":"Restaurant",
            "type":"Food & Drink"
        }
    ],
    "sg:postcode":"SW17 0DN",
    "sg:province":"Greater London",
    "sg:tags":[
        "indian"
    ],
    "wof:name":"Cafe Tandoor",
    "wof:placetype":"venue"
},
  "geometry": {"coordinates":[-0.166117996,51.4299850464],"type":"Point"}
}