{
  "type": "Feature",
  "properties": {
    "iso:country":"GB",
    "sg:address":"5 Field Place",
    "sg:city":"Newport",
    "sg:classifiers":[
        {
            "category":"Building & Trades",
            "subcategory":"Construction",
            "type":"Services"
        }
    ],
    "sg:phone":"+44 1983 521008",
    "sg:postcode":"PO30 5DY",
    "sg:province":"Isle of Wight",
    "sg:tags":[
        "builder"
    ],
    "wof:name":"Steve Evans Plant Hire & Building",
    "wof:placetype":"venue"
},
  "geometry": {"coordinates":[-1.302628994,50.6976623535],"type":"Point"}
}