{
  "type": "Feature",
  "properties": {
    "addr:full":"55 Woodrow Lane, Catshill Bromsgrove Worcestershire B61 0PP",
    "addr:housenumber":"55",
    "addr:postcode":"b61 0pp",
    "addr:street":"Woodrow Lane Catshill",
    "iso:country":"GB",
    "sg:address":"55 Woodrow Lane, Catshill",
    "sg:city":"Bromsgrove",
    "sg:classifiers":[
        {
            "category":"Shopping",
            "subcategory":"News",
            "type":"Retail Goods"
        }
    ],
    "sg:phone":"+44 1527 872449",
    "sg:postcode":"B61 0PP",
    "sg:province":"Worcestershire",
    "sg:tags":[
        "newsagent"
    ],
    "wof:name":"Dillons One-Stop",
    "wof:placetype":"venue"
},
  "geometry": {"coordinates":[-2.0559809208,52.3660697937],"type":"Point"}
}