{
  "type": "Feature",
  "properties": {
    "addr:full":"121 Main Road, Danbury Chelmsford Essex CM3 4DL",
    "addr:housenumber":"121",
    "addr:postcode":"cm3 4dl",
    "addr:street":"Main Road",
    "iso:country":"GB",
    "sg:address":"121 Main Road, Danbury",
    "sg:city":"Chelmsford",
    "sg:classifiers":[
        {
            "category":"Personal",
            "subcategory":"Beauty Salon",
            "type":"Services"
        }
    ],
    "sg:postcode":"CM3 4DL",
    "sg:province":"Essex",
    "wof:name":"Anne Gay & Lesley Reynolds",
    "wof:placetype":"venue"
},
  "geometry": {"coordinates":[0.570373,51.718849],"type":"Point"}
}