{
  "type": "Feature",
  "properties": {
    "addr:full":"7 Great Western Road London Greater London W9 3NW",
    "addr:housenumber":"7",
    "addr:postcode":"w9 3nw",
    "addr:street":"Great Western Road",
    "iso:country":"GB",
    "sg:address":"7 Great Western Road",
    "sg:city":"London",
    "sg:classifiers":[
        {
            "category":"Professional",
            "subcategory":"Art Services",
            "type":"Services"
        }
    ],
    "sg:postcode":"W9 3NW",
    "sg:province":"Greater London",
    "sg:tags":[
        "graphic",
        "designer"
    ],
    "wof:name":"What Next Media Services",
    "wof:placetype":"venue"
},
  "geometry": {"coordinates":[-0.2015420049,51.5235099792],"type":"Point"}
}