{
  "type": "Feature",
  "properties": {
    "addr:full":"28 Andrew Allan Rd, Rockwell Grn Wellington Devon TA21 9DY",
    "addr:housenumber":"28",
    "addr:postcode":"ta21 9dy",
    "addr:street":"Andrew Allan Rd;Grn",
    "iso:country":"GB",
    "sg:address":"28 Andrew Allan Rd, Rockwell Grn",
    "sg:city":"Wellington",
    "sg:classifiers":[
        {
            "category":"Shopping",
            "subcategory":"Stationery & Office Supplies",
            "type":"Retail Goods"
        }
    ],
    "sg:postcode":"TA21 9DY",
    "sg:province":"Devon",
    "sg:tags":[
        "item",
        "promotional"
    ],
    "wof:name":"Masters,Richard J,",
    "wof:placetype":"venue"
},
  "geometry": {"coordinates":[-3.242765,50.971252],"type":"Point"}
}