{
  "type": "Feature",
  "properties": {
    "addr:full":"3 Hylands Parade, Wood Street Chelmsford Essex CM2 8BW",
    "addr:postcode":"cm2 8bw",
    "addr:street":"Parade Wood Street",
    "iso:country":"GB",
    "sg:address":"3 Hylands Parade, Wood Street",
    "sg:city":"Chelmsford",
    "sg:classifiers":[
        {
            "category":"Shopping",
            "subcategory":"Florist",
            "type":"Retail Goods"
        }
    ],
    "sg:phone":"+44 1245 257510",
    "sg:postcode":"CM2 8BW",
    "sg:province":"Essex",
    "wof:name":"G & E Addy",
    "wof:placetype":"venue"
},
  "geometry": {"coordinates":[0.4778909981,51.731918335],"type":"Point"}
}