{
  "type": "Feature",
  "properties": {
    "addr:full":"20 Dewar St Dunfermline Fife KY12 8AD",
    "addr:housenumber":"20",
    "addr:postcode":"ky12 8ad",
    "addr:street":"Dewar St",
    "iso:country":"GB",
    "sg:address":"20 Dewar St",
    "sg:city":"Dunfermline",
    "sg:classifiers":[
        {
            "category":"Building & Trades",
            "subcategory":"Construction",
            "type":"Services"
        }
    ],
    "sg:phone":"+44 1383 732009",
    "sg:postcode":"KY12 8AD",
    "sg:province":"Fife",
    "sg:tags":[
        "joiner",
        "carpenter"
    ],
    "wof:name":"J D Tod",
    "wof:placetype":"venue"
},
  "geometry": {"coordinates":[-3.468833,56.073277],"type":"Point"}
}