{
  "type": "Feature",
  "properties": {
    "addr:full":"The Lawn, The Strand Dawlish Devon EX7 9PW",
    "addr:postcode":"ex7 9pw",
    "addr:street":"The Strand",
    "iso:country":"GB",
    "sg:address":"The Lawn, The Strand",
    "sg:city":"Dawlish",
    "sg:classifiers":[
        {
            "category":"Arena",
            "subcategory":"Sports Club",
            "type":"Entertainment"
        }
    ],
    "sg:phone":"+44 1626 865367",
    "sg:postcode":"EX7 9PW",
    "sg:province":"Devon",
    "wof:name":"Dawlish Bowling Club",
    "wof:placetype":"venue"
},
  "geometry": {"coordinates":[-3.468126,50.581173],"type":"Point"}
}