{
  "type": "Feature",
  "properties": {
    "addr:full":"93 Walgrave Peterborough Cambridgeshire PE2 5NS",
    "addr:housenumber":"93",
    "addr:postcode":"pe2 5ns",
    "addr:street":"Walgrave Peterborough",
    "iso:country":"GB",
    "sg:address":"93 Walgrave",
    "sg:city":"Peterborough",
    "sg:classifiers":[
        {
            "category":"Building & Trades",
            "subcategory":"Construction",
            "type":"Services"
        }
    ],
    "sg:phone":"+44 1733 236006",
    "sg:postcode":"PE2 5NS",
    "sg:province":"Cambridgeshire",
    "sg:tags":[
        "builder"
    ],
    "wof:name":"S D R Builders Ltd",
    "wof:placetype":"venue"
},
  "geometry": {"coordinates":[-0.27845,52.544521],"type":"Point"}
}