{
  "type": "Feature",
  "properties": {
    "addr:full":"98 Calderwood Sq Glasgow South Lanarkshire G74 3BQ",
    "addr:housenumber":"98",
    "addr:postcode":"g74 3bq",
    "addr:street":"Calderwood Sq",
    "iso:country":"GB",
    "sg:address":"98 Calderwood Sq",
    "sg:city":"Glasgow",
    "sg:classifiers":[
        {
            "category":"Shopping",
            "type":"Retail Goods"
        }
    ],
    "sg:phone":"+44 1355 248079",
    "sg:postcode":"G74 3BQ",
    "sg:province":"South Lanarkshire",
    "sg:tags":[
        "part",
        "accessory"
    ],
    "wof:name":"Autoparts Superstores",
    "wof:placetype":"venue"
},
  "geometry": {"coordinates":[-4.162066,55.775345],"type":"Point"}
}