{
  "type": "Feature",
  "properties": {
    "iso:country":"GB",
    "sg:address":"Unit 6, Forum Centre",
    "sg:city":"Dundee",
    "sg:classifiers":[
        {
            "category":"Food & Beverages",
            "subcategory":"Fruits & Vegetables",
            "type":"Retail Goods"
        }
    ],
    "sg:postcode":"DD1 1DQ",
    "sg:province":"Dundee City",
    "sg:tags":[
        "greengrocer"
    ],
    "wof:name":"Betty Thomson",
    "wof:placetype":"venue"
},
  "geometry": {"coordinates":[-2.967609,56.461376],"type":"Point"}
}