{
  "type": "Feature",
  "properties": {
    "addr:full":"65 Linskill Terrace North Shields Tyne and Wear NE30 2EP",
    "addr:housenumber":"65",
    "addr:postcode":"ne30 2ep",
    "addr:street":"Linskill Terrace",
    "iso:country":"GB",
    "sg:address":"65 Linskill Terrace",
    "sg:city":"North Shields",
    "sg:classifiers":[
        {
            "category":"Building & Trades",
            "subcategory":"Construction",
            "type":"Services"
        }
    ],
    "sg:postcode":"NE30 2EP",
    "sg:province":"Tyne and Wear",
    "sg:tags":[
        "builder"
    ],
    "wof:name":"Technicard Ltd.",
    "wof:placetype":"venue"
},
  "geometry": {"coordinates":[-1.4397829771,55.0163040161],"type":"Point"}
}