{
  "type": "Feature",
  "properties": {
    "addr:full":"36 Manse Street Galashiels Scottish Borders TD1 1NE",
    "addr:housenumber":"36",
    "addr:postcode":"td1 1ne",
    "addr:street":"Manse Street",
    "iso:country":"GB",
    "sg:address":"36 Manse Street",
    "sg:city":"Galashiels",
    "sg:classifiers":[
        {
            "category":"Professional",
            "subcategory":"Engineering",
            "type":"Services"
        },
        {
            "category":"Building & Trades",
            "subcategory":"Construction",
            "type":"Services"
        }
    ],
    "sg:phone":"+44 1896 753913",
    "sg:postcode":"TD1 1NE",
    "sg:province":"Scottish Borders",
    "sg:tags":[
        "installers",
        "gas",
        "engineer"
    ],
    "wof:name":"D & S Gas Services",
    "wof:placetype":"venue"
},
  "geometry": {"coordinates":[-2.823949,55.619869],"type":"Point"}
}