{
  "type": "Feature",
  "properties": {
    "iso:country":"GB",
    "sg:address":"34 Leyland Road",
    "sg:city":"Castleford",
    "sg:classifiers":[
        {
            "category":"Food & Beverages",
            "subcategory":"Groceries & Convenience Stores",
            "type":"Retail Goods"
        }
    ],
    "sg:postcode":"WF10 3SG",
    "sg:province":"West Yorkshire",
    "wof:name":"Jill & Andy's",
    "wof:placetype":"venue"
},
  "geometry": {"coordinates":[-1.310102,53.7267],"type":"Point"}
}