{
  "type": "Feature",
  "properties": {
    "addr:full":"134 Kennel La, Great Burstead Billericay Essex CM11 2SU",
    "addr:housenumber":"134",
    "addr:postcode":"cm11 2su",
    "addr:street":"Kennel La Great",
    "iso:country":"GB",
    "sg:address":"134 Kennel La, Great Burstead",
    "sg:city":"Billericay",
    "sg:classifiers":[
        {
            "category":"Professional",
            "subcategory":"Management & Consulting",
            "type":"Services"
        }
    ],
    "sg:postcode":"CM11 2SU",
    "sg:province":"Essex",
    "sg:tags":[
        "consultant"
    ],
    "wof:name":"Business Solutions Telecom Iib Ltd",
    "wof:placetype":"venue"
},
  "geometry": {"coordinates":[0.427705,51.607037],"type":"Point"}
}