{
  "type": "Feature",
  "properties": {
    "iso:country":"GB",
    "sg:address":"36 Hesketh Drive",
    "sg:city":"Southport",
    "sg:classifiers":[
        {
            "category":"Food & Beverages",
            "subcategory":"Candy",
            "type":"Retail Goods"
        }
    ],
    "sg:phone":"+44 1704 213942",
    "sg:postcode":"PR9 7JG",
    "sg:province":"Lancashire",
    "sg:tags":[
        "confectioner"
    ],
    "wof:name":"Craigs Bakery",
    "wof:placetype":"venue"
},
  "geometry": {"coordinates":[-2.974598,53.654854],"type":"Point"}
}