{
  "type": "Feature",
  "properties": {
    "iso:country":"GB",
    "sg:address":"Northcote Hill",
    "sg:city":"Honiton",
    "sg:classifiers":[
        {
            "category":"Building & Trades",
            "subcategory":"Landscaping Services",
            "type":"Services"
        },
        {
            "category":"Home & Garden",
            "subcategory":"Garden Supply",
            "type":"Retail Goods"
        }
    ],
    "sg:phone":"+44 1404 43344",
    "sg:postcode":"EX14 9TH",
    "sg:province":"Devon",
    "sg:tags":[
        "planting",
        "nurseryman",
        "tree",
        "shrub"
    ],
    "sg:website":"http://www.perriehale.com",
    "wof:name":"Perrie Hale Forest Nursery",
    "wof:placetype":"venue"
},
  "geometry": {"coordinates":[-3.155229,50.806755],"type":"Point"}
}