{
  "type": "Feature",
  "properties": {
    "iso:country":"GB",
    "sg:address":"45 Aberdeen Walk",
    "sg:city":"Scarborough",
    "sg:classifiers":[
        {
            "category":"Food & Beverages",
            "subcategory":"Meat & Fish",
            "type":"Retail Goods"
        }
    ],
    "sg:phone":"+44 1723 373302",
    "sg:postcode":"YO11 1BD",
    "sg:province":"North Yorkshire",
    "sg:tags":[
        "chip"
    ],
    "wof:name":"Happy Haddock",
    "wof:placetype":"venue"
},
  "geometry": {"coordinates":[-0.4034970105,54.2831726074],"type":"Point"}
}