{
  "type": "Feature",
  "properties": {
    "addr:full":"954 Johns Street Porthcawl Bridgend CF36 3DT",
    "addr:housenumber":"954",
    "addr:postcode":"cf36 3dt",
    "addr:street":"Johns Street",
    "iso:country":"GB",
    "sg:address":"954 Johns Street",
    "sg:city":"Porthcawl",
    "sg:classifiers":[
        {
            "category":"Social Services",
            "type":"Services"
        },
        {
            "category":"Manufacturing",
            "subcategory":"Tobacco Products",
            "type":"Manufacturing & Wholesale Goods"
        }
    ],
    "sg:phone":"+44 1656 788198",
    "sg:postcode":"CF36 3DT",
    "sg:province":"Bridgend",
    "sg:tags":[
        "equipment",
        "suppliers",
        "disability",
        "manufacturers"
    ],
    "wof:name":"Mobility Care Centre",
    "wof:placetype":"venue"
},
  "geometry": {"coordinates":[-3.7029089928,51.4799804688],"type":"Point"}
}