{
  "type": "Feature",
  "properties": {
    "addr:full":"254 Plumstead High Street, Plumstead London Greater London SE18 1JN",
    "addr:housenumber":"254",
    "addr:postcode":"se18 1jn",
    "addr:street":"High Street",
    "iso:country":"GB",
    "sg:address":"254 Plumstead High Street, Plumstead",
    "sg:city":"London",
    "sg:classifiers":[
        {
            "category":"Retail",
            "subcategory":"Repair Shop",
            "type":"Services"
        }
    ],
    "sg:phone":"+44 20 8855 0397",
    "sg:postcode":"SE18 1JN",
    "sg:province":"Greater London",
    "sg:tags":[
        "radio",
        "television",
        "video"
    ],
    "wof:name":"M A Electronics Tv Video & Hi-Fi Services",
    "wof:placetype":"venue"
},
  "geometry": {"coordinates":[0.098023,51.486061],"type":"Point"}
}