{
  "type": "Feature",
  "properties": {
    "addr:full":"71 West End Lane Barnet Hertfordshire EN5 2SB",
    "addr:housenumber":"71",
    "addr:postcode":"en5 2sb",
    "addr:street":"West End Lane",
    "iso:country":"GB",
    "sg:address":"71 West End Lane",
    "sg:city":"Barnet",
    "sg:classifiers":[
        {
            "category":"Shopping",
            "subcategory":"Computers & Home Electronics",
            "type":"Retail Goods"
        }
    ],
    "sg:postcode":"EN5 2SB",
    "sg:province":"Hertfordshire",
    "wof:name":"Tigermoth Ltd.",
    "wof:placetype":"venue"
},
  "geometry": {"coordinates":[-0.211984,51.651798],"type":"Point"}
}