{
  "type": "Feature",
  "properties": {
    "addr:full":"85 High Street Biggar Dumfries and Galloway ML12 6DL",
    "addr:housenumber":"85",
    "addr:postcode":"ml12 6dl",
    "addr:street":"High Street",
    "iso:country":"GB",
    "sg:address":"85 High Street",
    "sg:city":"Biggar",
    "sg:classifiers":[
        {
            "category":"Professional",
            "subcategory":"Accounting & Tax Preparation",
            "type":"Services"
        }
    ],
    "sg:phone":"+44 1899 220966",
    "sg:postcode":"ML12 6DL",
    "sg:province":"Dumfries and Galloway",
    "sg:tags":[
        "accountant"
    ],
    "wof:name":"George O Thompson & Co.",
    "wof:placetype":"venue"
},
  "geometry": {"coordinates":[-3.5237390995,55.6243476868],"type":"Point"}
}