{
  "type": "Feature",
  "properties": {
    "addr:full":"Villa Farm Boston Lincolnshire PE20 2BN",
    "addr:postcode":"pe20 2bn",
    "iso:country":"GB",
    "sg:address":"Villa Farm",
    "sg:city":"Boston",
    "sg:classifiers":[
        {
            "category":"Farming",
            "subcategory":"Livestock Farm",
            "type":"Manufacturing & Wholesale Goods"
        }
    ],
    "sg:phone":"+44 1205 260283",
    "sg:postcode":"PE20 2BN",
    "sg:province":"Lincolnshire",
    "sg:tags":[
        "others"
    ],
    "wof:name":"E R Harrison",
    "wof:placetype":"venue"
},
  "geometry": {"coordinates":[-0.04773,52.889759],"type":"Point"}
}