{
  "type": "Feature",
  "properties": {
    "addr:full":"Headland Road, Welford On Avon Stratford-upon-avon Warwickshire CV37 8ER",
    "addr:postcode":"cv37 8er",
    "addr:street":"Headland Road",
    "iso:country":"GB",
    "sg:address":"Headland Road, Welford On Avon",
    "sg:city":"Stratford-upon-avon",
    "sg:classifiers":[
        {
            "category":"Education",
            "subcategory":"School",
            "type":"Public Place"
        }
    ],
    "sg:phone":"+44 1789 750214",
    "sg:postcode":"CV37 8ER",
    "sg:province":"Warwickshire",
    "sg:tags":[
        "local",
        "authority"
    ],
    "wof:name":"Welford on Avon Primary School",
    "wof:placetype":"venue"
},
  "geometry": {"coordinates":[-1.7836610079,52.1668243408],"type":"Point"}
}