{
  "type": "Feature",
  "properties": {
    "iso:country":"GB",
    "sg:address":"Potton Road",
    "sg:city":"Biggleswade",
    "sg:classifiers":[
        {
            "category":"Communications",
            "type":"Services"
        }
    ],
    "sg:phone":"+44 1767 600696",
    "sg:postcode":"SG18 0EP",
    "sg:province":"Bedfordshire",
    "sg:tags":[
        "audio-visual"
    ],
    "wof:name":"Busy Bodies (Duplication) Ltd.",
    "wof:placetype":"venue"
},
  "geometry": {"coordinates":[-0.251599,52.095551],"type":"Point"}
}