{
  "type": "Feature",
  "properties": {
    "addr:full":"7 Park Av Birmingham West Midlands B18 5ND",
    "addr:housenumber":"7",
    "addr:postcode":"b18 5nd",
    "addr:street":"Park Av",
    "iso:country":"GB",
    "sg:address":"7 Park Av",
    "sg:city":"Birmingham",
    "sg:classifiers":[
        {
            "category":"Organizations",
            "subcategory":"Membership Organization",
            "type":"Services"
        }
    ],
    "sg:phone":"+44 121 554 6717",
    "sg:postcode":"B18 5ND",
    "sg:province":"West Midlands",
    "sg:tags":[
        "club"
    ],
    "wof:name":"All Muslim Welfare Society",
    "wof:placetype":"venue"
},
  "geometry": {"coordinates":[-1.9214040041,52.4987869263],"type":"Point"}
}