{
  "type": "Feature",
  "properties": {
    "addr:full":"117a Putney High Street London Greater London SW15 1SS",
    "addr:housenumber":"117a",
    "addr:postcode":"sw15 1ss",
    "addr:street":"Putney High Street",
    "iso:country":"GB",
    "sg:address":"117a Putney High Street",
    "sg:city":"London",
    "sg:classifiers":[
        {
            "category":"Education",
            "subcategory":"School",
            "type":"Public Place"
        }
    ],
    "sg:postcode":"SW15 1SS",
    "sg:province":"Greater London",
    "sg:tags":[
        "private",
        "tuition"
    ],
    "wof:name":"The Elizabethan School of English",
    "wof:placetype":"venue"
},
  "geometry": {"coordinates":[-0.2160169929,51.4626350403],"type":"Point"}
}