{
  "type": "Feature",
  "properties": {
    "iso:country":"GB",
    "sg:address":"Dale Road North",
    "sg:city":"Matlock",
    "sg:classifiers":[
        {
            "category":"Autos & Motor Vehicles",
            "subcategory":"Fuel & Gas Station",
            "type":"Retail Goods"
        }
    ],
    "sg:phone":"+44 1629 734778",
    "sg:postcode":"DE4 2HX",
    "sg:province":"Derbyshire",
    "sg:tags":[
        "petrol",
        "filling"
    ],
    "wof:name":"Dale Road Filling Station",
    "wof:placetype":"venue"
},
  "geometry": {"coordinates":[-1.599496,53.166992],"type":"Point"}
}