{
  "type": "Feature",
  "properties": {
    "iso:country":"GB",
    "sg:address":"11th Floor,edgbaston House, 3 Duchess Place,hagley Road, Edgbaston",
    "sg:city":"Birmingham",
    "sg:classifiers":[
        {
            "category":"Professional",
            "subcategory":"Employment Agencies",
            "type":"Services"
        }
    ],
    "sg:phone":"+44 121 454 9922",
    "sg:postcode":"B16 8NH",
    "sg:province":"West Midlands",
    "sg:tags":[
        "consultant"
    ],
    "wof:name":"Corporate Solutions",
    "wof:placetype":"venue"
},
  "geometry": {"coordinates":[-1.923569,52.473419],"type":"Point"}
}