{
  "type": "Feature",
  "properties": {
    "addr:full":"1 Trem Eryri Menai Bridge Isle of Anglesey LL59 5LB",
    "addr:housenumber":"1",
    "addr:postcode":"ll59 5lb",
    "addr:street":"Trem Eryri",
    "iso:country":"GB",
    "sg:address":"1 Trem Eryri",
    "sg:city":"Menai Bridge",
    "sg:classifiers":[
        {
            "category":"Building & Trades",
            "subcategory":"Plumbing",
            "type":"Services"
        }
    ],
    "sg:phone":"+44 1248 713795",
    "sg:postcode":"LL59 5LB",
    "sg:province":"Isle of Anglesey",
    "sg:tags":[
        "heating"
    ],
    "wof:name":"R R Jones Plumbing Heating Ltd",
    "wof:placetype":"venue"
},
  "geometry": {"coordinates":[-4.171688,53.22942],"type":"Point"}
}