{
  "type": "Feature",
  "properties": {
    "addr:full":"10 Links Pl, Port Seton Prestonpans East Lothian EH32 0TP",
    "addr:housenumber":"10",
    "addr:postcode":"eh32 0tp",
    "addr:street":"Links Pl",
    "iso:country":"GB",
    "sg:address":"10 Links Pl, Port Seton",
    "sg:city":"Prestonpans",
    "sg:classifiers":[
        {
            "category":"Recreation",
            "subcategory":"Gun Range",
            "type":"Entertainment"
        }
    ],
    "sg:phone":"+44 1875 812612",
    "sg:postcode":"EH32 0TP",
    "sg:province":"East Lothian",
    "sg:tags":[
        "operator",
        "tour"
    ],
    "wof:name":"Connoisseur Art Tours Ltd",
    "wof:placetype":"venue"
},
  "geometry": {"coordinates":[-2.9431929588,55.9711303711],"type":"Point"}
}