{
  "type": "Feature",
  "properties": {
    "addr:full":"Cainscross Roas Stroud Gloucestershire GL5 4HE",
    "addr:postcode":"gl5 4he",
    "addr:street":"Roas",
    "iso:country":"GB",
    "sg:address":"Cainscross Roas",
    "sg:city":"Stroud",
    "sg:classifiers":[
        {
            "category":"Education",
            "subcategory":"School",
            "type":"Public Place"
        }
    ],
    "sg:phone":"+44 1453 762251",
    "sg:postcode":"GL5 4HE",
    "sg:province":"Gloucestershire",
    "sg:tags":[
        "foundation",
        "college"
    ],
    "wof:name":"Marling School",
    "wof:placetype":"venue"
},
  "geometry": {"coordinates":[-2.2324409485,51.744934082],"type":"Point"}
}