{
  "type": "Feature",
  "properties": {
    "addr:full":"Buildings C & D, Tower Bridge Business Complex, 100 Clements Road London Greater London SE16 4DG",
    "addr:housenumber":"100",
    "addr:postcode":"se16 4dg",
    "addr:street":"Clements Road",
    "iso:country":"GB",
    "sg:address":"Buildings C & D, Tower Bridge Business Complex, 100 Clements Road",
    "sg:city":"London",
    "sg:classifiers":[
        {
            "category":"Shopping",
            "subcategory":"Musical Instruments",
            "type":"Retail Goods"
        }
    ],
    "sg:phone":"+44 20 7252 0001",
    "sg:postcode":"SE16 4DG",
    "sg:province":"Greater London",
    "sg:tags":[
        "music",
        "sheet"
    ],
    "wof:name":"Music Bank (Hire) Ltd.",
    "wof:placetype":"venue"
},
  "geometry": {"coordinates":[-0.0634400025,51.495098114],"type":"Point"}
}