{
  "type": "Feature",
  "properties": {
    "iso:country":"GB",
    "sg:address":"42 London Road, Blackwater",
    "sg:city":"Camberley",
    "sg:classifiers":[
        {
            "category":"Health Services",
            "subcategory":"Optometrist",
            "type":"Services"
        }
    ],
    "sg:phone":"+44 1276 34053",
    "sg:postcode":"GU17 9AA",
    "sg:province":"Hampshire",
    "sg:tags":[
        "optician"
    ],
    "wof:name":"Forsight",
    "wof:placetype":"venue"
},
  "geometry": {"coordinates":[-0.786969,51.329739],"type":"Point"}
}