{
  "type": "Feature",
  "properties": {
    "iso:country":"GB",
    "sg:address":"74 Crayford Rd, Crayford",
    "sg:city":"Dartford",
    "sg:classifiers":[
        {
            "category":"Home & Garden",
            "subcategory":"Home Furnishings",
            "type":"Retail Goods"
        }
    ],
    "sg:phone":"+44 1322 555996",
    "sg:postcode":"DA1 4AT",
    "sg:province":"Kent",
    "sg:tags":[
        "blind",
        "curtain",
        "fitting"
    ],
    "wof:name":"Ribbons Interiors",
    "wof:placetype":"venue"
},
  "geometry": {"coordinates":[0.1836439967,51.4497489929],"type":"Point"}
}