{
  "type": "Feature",
  "properties": {
    "addr:full":"Thrift Road, Heath And Reach Leighton Buzzard Bedfordshire LU7 0AX",
    "addr:postcode":"lu7 0ax",
    "addr:street":"Thrift Road",
    "iso:country":"GB",
    "sg:address":"Thrift Road, Heath And Reach",
    "sg:city":"Leighton Buzzard",
    "sg:classifiers":[
        {
            "category":"Education",
            "subcategory":"School",
            "type":"Public Place"
        }
    ],
    "sg:phone":"+44 1525 237253",
    "sg:postcode":"LU7 0AX",
    "sg:province":"Bedfordshire",
    "sg:tags":[
        "local",
        "authority"
    ],
    "wof:name":"St Leonards Heath & Reach V A Lower School",
    "wof:placetype":"venue"
},
  "geometry": {"coordinates":[-0.656974,51.945251],"type":"Point"}
}