{
  "type": "Feature",
  "properties": {
    "addr:full":"33 Western Road Tring Buckinghamshire HP23 4BQ",
    "addr:housenumber":"33",
    "addr:postcode":"hp23 4bq",
    "addr:street":"Western Road",
    "iso:country":"GB",
    "sg:address":"33 Western Road",
    "sg:city":"Tring",
    "sg:classifiers":[
        {
            "category":"Shopping",
            "subcategory":"Bicycles & Sporting Goods",
            "type":"Retail Goods"
        },
        {
            "category":"Recreation",
            "subcategory":"Fishing",
            "type":"Entertainment"
        }
    ],
    "sg:phone":"+44 1442 825257",
    "sg:postcode":"HP23 4BQ",
    "sg:province":"Buckinghamshire",
    "sg:tags":[
        "equipment",
        "angling"
    ],
    "wof:name":"Chiltern Tackle",
    "wof:placetype":"venue"
},
  "geometry": {"coordinates":[-0.6671599746,51.7918930054],"type":"Point"}
}