{
  "type": "Feature",
  "properties": {
    "addr:full":"17 Ashdown Walk, Isle Of Dogs Poplar Greater London E14 9WH",
    "addr:housenumber":"17",
    "addr:postcode":"e14 9wh",
    "addr:street":"Ashdown Walk",
    "iso:country":"GB",
    "sg:address":"17 Ashdown Walk, Isle Of Dogs",
    "sg:city":"Poplar",
    "sg:classifiers":[
        {
            "category":"Professional",
            "subcategory":"Detective & Security Services",
            "type":"Services"
        }
    ],
    "sg:phone":"+44 20 7987 1625",
    "sg:postcode":"E14 9WH",
    "sg:province":"Greater London",
    "sg:tags":[
        "agency"
    ],
    "wof:name":"City International",
    "wof:placetype":"venue"
},
  "geometry": {"coordinates":[-0.022125,51.492371],"type":"Point"}
}