{
  "type": "Feature",
  "properties": {
    "addr:full":"Balham Health Centre, 120-124 Bedford Hill London Greater London SW12 9HS",
    "addr:housenumber":"120-124",
    "addr:postcode":"sw12 9hs",
    "addr:street":"Bedford Hill",
    "iso:country":"GB",
    "sg:address":"Balham Health Centre, 120-124 Bedford Hill",
    "sg:city":"London",
    "sg:classifiers":[
        {
            "category":"Health Services",
            "subcategory":"Doctor",
            "type":"Services"
        }
    ],
    "sg:phone":"+44 20 8673 8268",
    "sg:postcode":"SW12 9HS",
    "sg:province":"Greater London",
    "sg:tags":[
        "practitioners"
    ],
    "wof:name":"N Akbar",
    "wof:placetype":"venue"
},
  "geometry": {"coordinates":[-0.14908,51.440651],"type":"Point"}
}