{
  "type": "Feature",
  "properties": {
    "iso:country":"GB",
    "sg:address":"Hints Road, Mile Oak",
    "sg:city":"Tamworth",
    "sg:classifiers":[
        {
            "category":"Professional",
            "subcategory":"Management & Consulting",
            "type":"Services"
        }
    ],
    "sg:postcode":"B78 3PQ",
    "sg:province":"Staffordshire",
    "sg:tags":[
        "consultant",
        "business"
    ],
    "wof:name":"Advanced Consultancy",
    "wof:placetype":"venue"
},
  "geometry": {"coordinates":[-1.735798,52.641033],"type":"Point"}
}