{
  "type": "Feature",
  "properties": {
    "addr:full":"69 South Parade Ossett West Yorkshire WF5 0EB",
    "addr:housenumber":"69",
    "addr:postcode":"wf5 0eb",
    "addr:street":"South Parade",
    "iso:country":"GB",
    "sg:address":"69 South Parade",
    "sg:city":"Ossett",
    "sg:classifiers":[
        {
            "category":"Government",
            "subcategory":"Post Office",
            "type":"Public Place"
        }
    ],
    "sg:phone":"+44 1924 280982",
    "sg:postcode":"WF5 0EB",
    "sg:province":"West Yorkshire",
    "wof:name":"Queens Drive Post Office",
    "wof:placetype":"venue"
},
  "geometry": {"coordinates":[-1.5618619919,53.6751747131],"type":"Point"}
}