{
  "type": "Feature",
  "properties": {
    "addr:full":"40 Lady Gro Welwyn Garden City Hertfordshire AL7 4DU",
    "addr:housenumber":"40",
    "addr:postcode":"al7 4du",
    "addr:street":"Lady Gro;Garden",
    "iso:country":"GB",
    "sg:address":"40 Lady Gro",
    "sg:city":"Welwyn Garden City",
    "sg:classifiers":[
        {
            "category":"Professional",
            "subcategory":"Management & Consulting",
            "type":"Services"
        }
    ],
    "sg:phone":"+44 1707 372727",
    "sg:postcode":"AL7 4DU",
    "sg:province":"Hertfordshire",
    "sg:tags":[
        "consultant",
        "business"
    ],
    "wof:name":"Majorissue Ltd.",
    "wof:placetype":"venue"
},
  "geometry": {"coordinates":[-0.1996500045,51.7839622498],"type":"Point"}
}