{
  "type": "Feature",
  "properties": {
    "addr:full":"363 Fore Street London Greater London N9 0NR",
    "addr:housenumber":"363",
    "addr:postcode":"n9 0nr",
    "addr:street":"Fore Street",
    "iso:country":"GB",
    "sg:address":"363 Fore Street",
    "sg:city":"London",
    "sg:classifiers":[
        {
            "category":"Food & Beverages",
            "subcategory":"Supermarket",
            "type":"Retail Goods"
        }
    ],
    "sg:phone":"+44 20 8807 6766",
    "sg:postcode":"N9 0NR",
    "sg:province":"Greater London",
    "wof:name":"Turkish Food Centre",
    "wof:placetype":"venue"
},
  "geometry": {"coordinates":[-0.0617009997,51.6217498779],"type":"Point"}
}