{
  "type": "Feature",
  "properties": {
    "iso:country":"GB",
    "sg:address":"204a Lower Blandford Road",
    "sg:city":"Broadstone",
    "sg:classifiers":[
        {
            "category":"Professional",
            "subcategory":"Accounting & Tax Preparation",
            "type":"Services"
        }
    ],
    "sg:postcode":"BH18 8DP",
    "sg:province":"Dorset",
    "sg:tags":[
        "accountant"
    ],
    "wof:name":"Birkett & Co. Ltd.",
    "wof:placetype":"venue"
},
  "geometry": {"coordinates":[-1.9946850538,50.7607269287],"type":"Point"}
}