{
  "type": "Feature",
  "properties": {
    "iso:country":"GB",
    "sg:address":"1 Forndon Close, Lower Earley",
    "sg:city":"Reading",
    "sg:classifiers":[
        {
            "category":"Building & Trades",
            "subcategory":"Construction",
            "type":"Services"
        }
    ],
    "sg:postcode":"RG6 3XR",
    "sg:province":"Berkshire",
    "sg:tags":[
        "joiner",
        "carpenter"
    ],
    "wof:name":"Woodlink",
    "wof:placetype":"venue"
},
  "geometry": {"coordinates":[-0.9045670033,51.4293708801],"type":"Point"}
}