{
  "type": "Feature",
  "properties": {
    "addr:full":"58 Chapel Road Worthing West Sussex BN11 1BN",
    "addr:housenumber":"58",
    "addr:postcode":"bn11 1bn",
    "addr:street":"Chapel Road",
    "iso:country":"GB",
    "sg:address":"58 Chapel Road",
    "sg:city":"Worthing",
    "sg:classifiers":[
        {
            "category":"Home & Garden",
            "subcategory":"Furniture",
            "type":"Retail Goods"
        }
    ],
    "sg:phone":"+44 1903 202040",
    "sg:postcode":"BN11 1BN",
    "sg:province":"West Sussex",
    "wof:name":"Worthing Suite Centre",
    "wof:placetype":"venue"
},
  "geometry": {"coordinates":[-0.371096,50.814476],"type":"Point"}
}