{
  "type": "Feature",
  "properties": {
    "addr:full":"Unit A Walsden Indstl Est, Rochdale Rd Todmorden Lancashire OL14 5AA",
    "addr:housenumber":"unit",
    "addr:postcode":"ol14 5aa",
    "addr:street":"Indstl;Rochdale Rd",
    "iso:country":"GB",
    "sg:address":"Unit A Walsden Indstl Est, Rochdale Rd",
    "sg:city":"Todmorden",
    "sg:classifiers":[
        {
            "category":"Home & Garden",
            "subcategory":"Kitchen Supply",
            "type":"Retail Goods"
        }
    ],
    "sg:phone":"+44 1706 818281",
    "sg:postcode":"OL14 5AA",
    "sg:province":"Lancashire",
    "sg:tags":[
        "catering"
    ],
    "wof:name":"Ravella (U K) Ltd",
    "wof:placetype":"venue"
},
  "geometry": {"coordinates":[-2.097308,53.71431],"type":"Point"}
}