{
  "type": "Feature",
  "properties": {
    "addr:full":"8 Clifton Moor Business Village, James Nicolson Link York North Yorkshire YO30 4XG",
    "addr:housenumber":"8",
    "addr:postcode":"yo30 4xg",
    "addr:street":"Clifton Moor Business Village;Nicolson Link",
    "iso:country":"GB",
    "sg:address":"8 Clifton Moor Business Village, James Nicolson Link",
    "sg:city":"York",
    "sg:classifiers":[
        {
            "category":"Professional",
            "subcategory":"Accounting & Tax Preparation",
            "type":"Services"
        }
    ],
    "sg:postcode":"YO30 4XG",
    "sg:province":"North Yorkshire",
    "sg:tags":[
        "accountant"
    ],
    "wof:name":"Botting & Co. Ltd.",
    "wof:placetype":"venue"
},
  "geometry": {"coordinates":[-1.100244,53.986423],"type":"Point"}
}