{
  "type": "Feature",
  "properties": {
    "addr:full":"121 Addington Road West Wickham Kent BR4 9BG",
    "addr:housenumber":"121",
    "addr:postcode":"br4 9bg",
    "addr:street":"Addington Road",
    "iso:country":"GB",
    "sg:address":"121 Addington Road",
    "sg:city":"West Wickham",
    "sg:classifiers":[
        {
            "category":"Health Services",
            "subcategory":"Dentist",
            "type":"Services"
        }
    ],
    "sg:phone":"+44 20 8462 5768",
    "sg:postcode":"BR4 9BG",
    "sg:province":"Kent",
    "wof:name":"Parkside Dental Practice",
    "wof:placetype":"venue"
},
  "geometry": {"coordinates":[-0.004607,51.368744],"type":"Point"}
}