{
  "type": "Feature",
  "properties": {
    "addr:full":"75 Boothferry Road Goole East Riding of Yorkshire DN14 6BB",
    "addr:housenumber":"75",
    "addr:postcode":"dn14 6bb",
    "addr:street":"Boothferry Road",
    "iso:country":"GB",
    "sg:address":"75 Boothferry Road",
    "sg:city":"Goole",
    "sg:classifiers":[
        {
            "category":"Personal",
            "subcategory":"Beauty Salon",
            "type":"Services"
        },
        {
            "category":"Personal",
            "subcategory":"Barber",
            "type":"Services"
        }
    ],
    "sg:phone":"+44 1405 768155",
    "sg:postcode":"DN14 6BB",
    "sg:province":"East Riding of Yorkshire",
    "sg:tags":[
        "unisex",
        "hairdresser"
    ],
    "wof:name":"Equinox",
    "wof:placetype":"venue"
},
  "geometry": {"coordinates":[-0.876235,53.705162],"type":"Point"}
}