{
  "type": "Feature",
  "properties": {
    "iso:country":"GB",
    "sg:address":"Bank Street Methodist Church, Bank Street",
    "sg:city":"Mexborough",
    "sg:classifiers":[
        {
            "category":"Shopping",
            "type":"Retail Goods"
        }
    ],
    "sg:phone":"+44 1709 584468",
    "sg:postcode":"S64 9LL",
    "sg:province":"South Yorkshire",
    "sg:tags":[
        "part",
        "accessory"
    ],
    "wof:name":"Bullseye Motorist Centre",
    "wof:placetype":"venue"
},
  "geometry": {"coordinates":[-1.286919,53.493095],"type":"Point"}
}