{
  "type": "Feature",
  "properties": {
    "addr:full":"Owls Court, Five Fields Lane, Four Elms Edenbridge East Sussex TN8 6NB",
    "addr:postcode":"tn8 6nb",
    "addr:street":"Owls Court Five Fields Lane",
    "iso:country":"GB",
    "sg:address":"Owls Court, Five Fields Lane, Four Elms",
    "sg:city":"Edenbridge",
    "sg:classifiers":[
        {
            "category":"Professional",
            "subcategory":"Business Services",
            "type":"Services"
        }
    ],
    "sg:phone":"+44 1732 700011",
    "sg:postcode":"TN8 6NB",
    "sg:province":"East Sussex",
    "sg:tags":[
        "broker",
        "commodity"
    ],
    "wof:name":"Nightserve General Trading Ltd.",
    "wof:placetype":"venue"
},
  "geometry": {"coordinates":[0.0935619995,51.211894989],"type":"Point"}
}