{
  "type": "Feature",
  "properties": {
    "addr:full":"Unit 23 John Hillhouse Industria, L Estate 211 Camb Glasgow South Lanarkshire G72 7TS",
    "addr:housenumber":"unit 23;211",
    "addr:postcode":"g72 7ts",
    "addr:street":"John Hillhouse Industria L;Camb Glasgow",
    "iso:country":"GB",
    "sg:address":"Unit 23 John Hillhouse Industria, L Estate 211 Camb",
    "sg:city":"Glasgow",
    "sg:classifiers":[
        {
            "category":"Autos & Motor Vehicles",
            "subcategory":"Auto Supplies",
            "type":"Retail Goods"
        },
        {
            "category":"Transit Center",
            "subcategory":"Freight",
            "type":"Transportation"
        }
    ],
    "sg:phone":"+44 141 613 1588",
    "sg:postcode":"G72 7TS",
    "sg:province":"South Lanarkshire",
    "sg:tags":[
        "exhaust",
        "tyre",
        "centre"
    ],
    "wof:name":"First Stop",
    "wof:placetype":"venue"
},
  "geometry": {"coordinates":[-4.19499,55.82785],"type":"Point"}
}