{
  "type": "Feature",
  "properties": {
    "iso:country":"GB",
    "sg:address":"4 High Street",
    "sg:city":"Ross-on-wye",
    "sg:classifiers":[
        {
            "category":"Shopping",
            "subcategory":"Antiques",
            "type":"Retail Goods"
        }
    ],
    "sg:postcode":"HR9 5HL",
    "sg:province":"Gloucestershire",
    "wof:name":"Elder Antiques",
    "wof:placetype":"venue"
},
  "geometry": {"coordinates":[-2.585568,51.914577],"type":"Point"}
}