{
  "type": "Feature",
  "properties": {
    "addr:full":"7 Pierrepoint Row, Camden Passage London Greater London N1 8EE",
    "addr:housenumber":"7",
    "addr:postcode":"n1 8ee",
    "addr:street":"Pierrepoint Row Camden Passage",
    "iso:country":"GB",
    "sg:address":"7 Pierrepoint Row, Camden Passage",
    "sg:city":"London",
    "sg:classifiers":[
        {
            "category":"Shopping",
            "subcategory":"Antiques",
            "type":"Retail Goods"
        }
    ],
    "sg:phone":"+44 20 7226 8211",
    "sg:postcode":"N1 8EE",
    "sg:province":"Greater London",
    "wof:name":"Antique Arcades",
    "wof:placetype":"venue"
},
  "geometry": {"coordinates":[-0.1041330025,51.5348320007],"type":"Point"}
}