{
  "type": "Feature",
  "properties": {
    "addr:full":"Empire Ho, Kempshott Industrial Park Est Basingstoke Hampshire RG23 7LP",
    "addr:postcode":"rg23 7lp",
    "addr:street":"Industrial Park Est",
    "iso:country":"GB",
    "sg:address":"Empire Ho, Kempshott Industrial Park Est",
    "sg:city":"Basingstoke",
    "sg:classifiers":[
        {
            "category":"Manufacturing",
            "subcategory":"Paper Products",
            "type":"Manufacturing & Wholesale Goods"
        }
    ],
    "sg:phone":"+44 1256 767777",
    "sg:postcode":"RG23 7LP",
    "sg:province":"Hampshire",
    "sg:tags":[
        "cardboard"
    ],
    "wof:name":"Centurian Services Ltd",
    "wof:placetype":"venue"
},
  "geometry": {"coordinates":[-1.14636,51.222649],"type":"Point"}
}