{
  "type": "Feature",
  "properties": {
    "iso:country":"GB",
    "sg:address":"17 Market Street",
    "sg:city":"Galashiels",
    "sg:classifiers":[
        {
            "category":"Bus Charters",
            "type":"Transportation"
        },
        {
            "category":"Travel",
            "subcategory":"Travel Agent",
            "type":"Entertainment"
        }
    ],
    "sg:postcode":"TD1 3AD",
    "sg:province":"Scottish Borders",
    "sg:tags":[
        "coach"
    ],
    "wof:name":"Premier Coach Tours Ltd.",
    "wof:placetype":"venue"
},
  "geometry": {"coordinates":[-2.8061420918,55.6150016785],"type":"Point"}
}