{
  "type": "Feature",
  "properties": {
    "addr:full":"23 Seneca Way Cheltenham Gloucestershire GL50 4SG",
    "addr:housenumber":"23",
    "addr:postcode":"gl50 4sg",
    "addr:street":"Seneca Way",
    "iso:country":"GB",
    "sg:address":"23 Seneca Way",
    "sg:city":"Cheltenham",
    "sg:classifiers":[
        {
            "category":"Building & Trades",
            "subcategory":"Construction",
            "type":"Services"
        }
    ],
    "sg:phone":"+44 1242 701151",
    "sg:postcode":"GL50 4SG",
    "sg:province":"Gloucestershire",
    "sg:tags":[
        "roofing",
        "builder",
        "contracting"
    ],
    "wof:name":"Seneca Builders",
    "wof:placetype":"venue"
},
  "geometry": {"coordinates":[-2.089125,51.917133],"type":"Point"}
}