{
  "type": "Feature",
  "properties": {
    "iso:country":"GB",
    "sg:address":"60-62 Cannock Rd",
    "sg:city":"Wolverhampton",
    "sg:classifiers":[
        {
            "category":"Health Services",
            "subcategory":"Doctor",
            "type":"Services"
        }
    ],
    "sg:phone":"+44 1902 739973",
    "sg:postcode":"WV10 8PJ",
    "sg:province":"Staffordshire",
    "sg:tags":[
        "practitioners"
    ],
    "wof:name":"Redman, K J",
    "wof:placetype":"venue"
},
  "geometry": {"coordinates":[-2.1007540226,52.6105880737],"type":"Point"}
}