{
  "type": "Feature",
  "properties": {
    "iso:country":"GB",
    "sg:address":"Wide Lane",
    "sg:city":"Southampton",
    "sg:classifiers":[
        {
            "category":"Freight",
            "type":"Transportation"
        }
    ],
    "sg:phone":"+44 23 8062 7217",
    "sg:postcode":"SO18 2NL",
    "sg:province":"Hampshire",
    "sg:tags":[
        "airfreight"
    ],
    "wof:name":"Southampton Airport Cargo Services",
    "wof:placetype":"venue"
},
  "geometry": {"coordinates":[-1.370639,50.943829],"type":"Point"}
}