{
  "type": "Feature",
  "properties": {
    "addr:full":"1 Cross Green App, Cross Grn Leeds West Yorkshire LS9 0SG",
    "addr:housenumber":"1",
    "addr:postcode":"ls9 0sg",
    "addr:street":"Cross Green;Cross",
    "iso:country":"GB",
    "sg:address":"1 Cross Green App, Cross Grn",
    "sg:city":"Leeds",
    "sg:classifiers":[
        {
            "category":"Home & Garden",
            "subcategory":"Hardware",
            "type":"Retail Goods"
        }
    ],
    "sg:phone":"+44 113 391 8200",
    "sg:postcode":"LS9 0SG",
    "sg:province":"West Yorkshire",
    "sg:tags":[
        "device",
        "fixing",
        "fastener"
    ],
    "wof:name":"A C S Stainless Steel Fixings Ltd.",
    "wof:placetype":"venue"
},
  "geometry": {"coordinates":[-1.520701,53.788288],"type":"Point"}
}