{
  "type": "Feature",
  "properties": {
    "addr:full":"Holly Tree Farm, Old Fen Lane, Scrub Hill Lincoln Lincolnshire LN4 4XE",
    "addr:postcode":"ln4 4xe",
    "addr:street":"Holly;Old Fen Lane",
    "iso:country":"GB",
    "sg:address":"Holly Tree Farm, Old Fen Lane, Scrub Hill",
    "sg:city":"Lincoln",
    "sg:classifiers":[
        {
            "category":"Farming",
            "subcategory":"Livestock Farm",
            "type":"Manufacturing & Wholesale Goods"
        }
    ],
    "sg:postcode":"LN4 4XE",
    "sg:province":"Lincolnshire",
    "sg:tags":[
        "others"
    ],
    "wof:name":"J G Marriott",
    "wof:placetype":"venue"
},
  "geometry": {"coordinates":[-0.161769,53.079601],"type":"Point"}
}