{
  "type": "Feature",
  "properties": {
    "addr:full":"Northside House, Mount Pleasent Barnet Hertfordshire EN4 9EB",
    "addr:postcode":"en4 9eb",
    "addr:street":"Mount Pleasent",
    "iso:country":"GB",
    "sg:address":"Northside House, Mount Pleasent",
    "sg:city":"Barnet",
    "sg:classifiers":[
        {
            "category":"Professional",
            "subcategory":"Accounting & Tax Preparation",
            "type":"Services"
        }
    ],
    "sg:phone":"+44 20 8216 2121",
    "sg:postcode":"EN4 9EB",
    "sg:province":"Hertfordshire",
    "sg:tags":[
        "payroll"
    ],
    "wof:name":"Payroll Plus",
    "wof:placetype":"venue"
},
  "geometry": {"coordinates":[-0.1613840014,51.6523094177],"type":"Point"}
}