{
  "type": "Feature",
  "properties": {
    "addr:full":"188 Reservoir Road Gloucester Gloucestershire GL4 6SB",
    "addr:housenumber":"188",
    "addr:postcode":"gl4 6sb",
    "addr:street":"Reservoir Road",
    "iso:country":"GB",
    "sg:address":"188 Reservoir Road",
    "sg:city":"Gloucester",
    "sg:classifiers":[
        {
            "category":"Professional",
            "subcategory":"Accounting & Tax Preparation",
            "type":"Services"
        }
    ],
    "sg:postcode":"GL4 6SB",
    "sg:province":"Gloucestershire",
    "sg:tags":[
        "accountant"
    ],
    "wof:name":"Anthony J Potts",
    "wof:placetype":"venue"
},
  "geometry": {"coordinates":[-2.240094,51.840919],"type":"Point"}
}