{
  "type": "Feature",
  "properties": {
    "addr:full":"96 Long Row, Horsforth Leeds West Yorkshire LS18 5AT",
    "addr:housenumber":"96",
    "addr:postcode":"ls18 5at",
    "addr:street":"Long Row",
    "iso:country":"GB",
    "sg:address":"96 Long Row, Horsforth",
    "sg:city":"Leeds",
    "sg:classifiers":[
        {
            "category":"Professional",
            "subcategory":"Management & Consulting",
            "type":"Services"
        }
    ],
    "sg:phone":"+44 113 293 9000",
    "sg:postcode":"LS18 5AT",
    "sg:province":"West Yorkshire",
    "sg:tags":[
        "marketing",
        "consultant"
    ],
    "wof:name":"Mcintosh & Sewards",
    "wof:placetype":"venue"
},
  "geometry": {"coordinates":[-1.6335860491,53.8445472717],"type":"Point"}
}