{
  "type": "Feature",
  "properties": {
    "addr:full":"Barras Lane, Dalston Carlisle Cumbria CA5 7LX",
    "addr:postcode":"ca5 7lx",
    "addr:street":"Barras Lane",
    "iso:country":"GB",
    "sg:address":"Barras Lane, Dalston",
    "sg:city":"Carlisle",
    "sg:classifiers":[
        {
            "category":"Utilities",
            "subcategory":"Fuel Oil & Lpg",
            "type":"Services"
        }
    ],
    "sg:phone":"+44 1228 711967",
    "sg:postcode":"CA5 7LX",
    "sg:province":"Cumbria",
    "wof:name":"Scottish Oils",
    "wof:placetype":"venue"
},
  "geometry": {"coordinates":[-2.983801,54.842525],"type":"Point"}
}