{
  "type": "Feature",
  "properties": {
    "iso:country":"GB",
    "sg:address":"Fibbersley",
    "sg:city":"Willenhall",
    "sg:classifiers":[
        {
            "category":"Bars & Pubs",
            "type":"Food & Drink"
        }
    ],
    "sg:postcode":"WV11 3SU",
    "sg:province":"Staffordshire",
    "sg:tags":[
        "pubs",
        "inn"
    ],
    "wof:name":"The Navigation Inn",
    "wof:placetype":"venue"
},
  "geometry": {"coordinates":[-2.0626161098,52.5948486328],"type":"Point"}
}