{
  "type": "Feature",
  "properties": {
    "addr:full":"294 Bolton Road, Worsley Manchester Greater Manchester M28 3FJ",
    "addr:housenumber":"294",
    "addr:postcode":"m28 3fj",
    "addr:street":"Bolton Road",
    "iso:country":"GB",
    "sg:address":"294 Bolton Road, Worsley",
    "sg:city":"Manchester",
    "sg:classifiers":[
        {
            "category":"Retail",
            "subcategory":"Funeral Services",
            "type":"Services"
        }
    ],
    "sg:phone":"+44 161 790 2924",
    "sg:postcode":"M28 3FJ",
    "sg:province":"Greater Manchester",
    "sg:tags":[
        "director"
    ],
    "wof:name":"Cheetham Funeral Services",
    "wof:placetype":"venue"
},
  "geometry": {"coordinates":[-2.4005420208,53.5307655334],"type":"Point"}
}