{
  "type": "Feature",
  "properties": {
    "addr:full":"Laurance Court, Dean Street Marlow Berkshire SL7 3BW",
    "addr:postcode":"sl7 3bw",
    "addr:street":"Court Dean Street",
    "iso:country":"GB",
    "sg:address":"Laurance Court, Dean Street",
    "sg:city":"Marlow",
    "sg:classifiers":[
        {
            "category":"Communications",
            "type":"Services"
        }
    ],
    "sg:phone":"+44 1494 614582",
    "sg:postcode":"SL7 3BW",
    "sg:province":"Berkshire",
    "sg:tags":[
        "telecommunication"
    ],
    "wof:name":"Alchemy Communications Ltd.",
    "wof:placetype":"venue"
},
  "geometry": {"coordinates":[-0.778915,51.575001],"type":"Point"}
}