{
  "type": "Feature",
  "properties": {
    "addr:full":"Rock Ferry Primary School, Ionic St Birkenhead Merseyside L42 2BL",
    "addr:postcode":"l42 2bl",
    "addr:street":"Rock;Ionic St",
    "iso:country":"GB",
    "sg:address":"Rock Ferry Primary School, Ionic St",
    "sg:city":"Birkenhead",
    "sg:classifiers":[
        {
            "category":"Government",
            "subcategory":"Office",
            "type":"Public Place"
        }
    ],
    "sg:phone":"+44 151 645 4925",
    "sg:postcode":"L42 2BL",
    "sg:province":"Merseyside",
    "sg:tags":[
        "local"
    ],
    "wof:name":"Metropolitan Borough of Wirral",
    "wof:placetype":"venue"
},
  "geometry": {"coordinates":[-3.0254900455,53.3925590515],"type":"Point"}
}