{
  "type": "Feature",
  "properties": {
    "addr:full":"89 Ridge La Watford Hertfordshire WD1 3SX",
    "addr:housenumber":"89",
    "addr:postcode":"wd1 3sx",
    "addr:street":"Ridge La",
    "iso:country":"GB",
    "sg:address":"89 Ridge La",
    "sg:city":"Watford",
    "sg:classifiers":[
        {
            "category":"Professional",
            "subcategory":"Accounting & Tax Preparation",
            "type":"Services"
        }
    ],
    "sg:phone":"+44 1923 220612",
    "sg:postcode":"WD1 3SX",
    "sg:province":"Hertfordshire",
    "sg:tags":[
        "accountant"
    ],
    "wof:name":"Rolfe & Co",
    "wof:placetype":"venue"
},
  "geometry": {"coordinates":[-0.4176160097,51.6777458191],"type":"Point"}
}