{
  "type": "Feature",
  "properties": {
    "iso:country":"GB",
    "sg:address":"110 Wash La",
    "sg:city":"Bury",
    "sg:classifiers":[
        {
            "category":"Shopping",
            "subcategory":"Bicycles & Sporting Goods",
            "type":"Retail Goods"
        }
    ],
    "sg:phone":"+44 161 797 5625",
    "sg:postcode":"BL9 7DJ",
    "sg:province":"Lancashire",
    "sg:tags":[
        "cycle",
        "accessory"
    ],
    "wof:name":"Leisure Lakes Mountain Bikes",
    "wof:placetype":"venue"
},
  "geometry": {"coordinates":[-2.2794060707,53.5936698914],"type":"Point"}
}