{
  "type": "Feature",
  "properties": {
    "addr:full":"The Oaks, Magdalen Way, Gorleston Great Yarmouth Norfolk NR31 7BP",
    "addr:postcode":"nr31 7bp",
    "addr:street":"Magdalen Way",
    "iso:country":"GB",
    "sg:address":"The Oaks, Magdalen Way, Gorleston",
    "sg:city":"Great Yarmouth",
    "sg:classifiers":[
        {
            "category":"Building & Trades",
            "subcategory":"Construction",
            "type":"Services"
        }
    ],
    "sg:postcode":"NR31 7BP",
    "sg:province":"Norfolk",
    "sg:tags":[
        "builder"
    ],
    "wof:name":"Kevin Marsden Building Contractor",
    "wof:placetype":"venue"
},
  "geometry": {"coordinates":[1.7168550491,52.577331543],"type":"Point"}
}