{
  "type": "Feature",
  "properties": {
    "addr:full":"41 Station Road, Harold Wood Romford Essex RM3 0BS",
    "addr:housenumber":"41",
    "addr:postcode":"rm3 0bs",
    "addr:street":"Station Road",
    "iso:country":"GB",
    "sg:address":"41 Station Road, Harold Wood",
    "sg:city":"Romford",
    "sg:classifiers":[
        {
            "category":"Food & Beverages",
            "subcategory":"Meat & Fish",
            "type":"Retail Goods"
        }
    ],
    "sg:postcode":"RM3 0BS",
    "sg:province":"Essex",
    "sg:tags":[
        "chip"
    ],
    "wof:name":"The Chippy",
    "wof:placetype":"venue"
},
  "geometry": {"coordinates":[0.2350939959,51.5940475464],"type":"Point"}
}