{
  "type": "Feature",
  "properties": {
    "addr:full":"60 Vandyke Rd Leighton Buzzard Bedfordshire LU7 3HH",
    "addr:housenumber":"60",
    "addr:postcode":"lu7 3hh",
    "addr:street":"Vandyke Rd",
    "iso:country":"GB",
    "sg:address":"60 Vandyke Rd",
    "sg:city":"Leighton Buzzard",
    "sg:classifiers":[
        {
            "category":"Professional",
            "subcategory":"Management & Consulting",
            "type":"Services"
        }
    ],
    "sg:postcode":"LU7 3HH",
    "sg:province":"Bedfordshire",
    "sg:tags":[
        "consultant"
    ],
    "wof:name":"P I Telecom Ltd",
    "wof:placetype":"venue"
},
  "geometry": {"coordinates":[-0.6545280218,51.9197120667],"type":"Point"}
}