{
  "type": "Feature",
  "properties": {
    "iso:country":"GB",
    "sg:address":"60 Croydon Rd",
    "sg:city":"Caterham",
    "sg:classifiers":[
        {
            "category":"Sports & Exercise",
            "subcategory":"Gym",
            "type":"Entertainment"
        }
    ],
    "sg:postcode":"CR3 6QB",
    "sg:province":"Surrey",
    "sg:tags":[
        "fitness",
        "health",
        "centre"
    ],
    "wof:name":"Clift-Simpson,Donna,",
    "wof:placetype":"venue"
},
  "geometry": {"coordinates":[-0.078578,51.284107],"type":"Point"}
}