{
  "type": "Feature",
  "properties": {
    "addr:full":"22 Vine Place Sunderland Tyne and Wear SR1 3NA",
    "addr:housenumber":"22",
    "addr:postcode":"sr1 3na",
    "addr:street":"Vine Place",
    "iso:country":"GB",
    "sg:address":"22 Vine Place",
    "sg:city":"Sunderland",
    "sg:classifiers":[
        {
            "category":"Health Services",
            "subcategory":"Dentist",
            "type":"Services"
        }
    ],
    "sg:phone":"+44 191 567 1034",
    "sg:postcode":"SR1 3NA",
    "sg:province":"Tyne and Wear",
    "sg:tags":[
        "technician",
        "dental"
    ],
    "wof:name":"Sunderland Denture Laboratory",
    "wof:placetype":"venue"
},
  "geometry": {"coordinates":[-1.386738,54.90416],"type":"Point"}
}