{
  "type": "Feature",
  "properties": {
    "addr:full":"Langley Works, Langley Macclesfield Cheshire SK11 0DF",
    "addr:postcode":"sk11 0df",
    "iso:country":"GB",
    "sg:address":"Langley Works, Langley",
    "sg:city":"Macclesfield",
    "sg:classifiers":[
        {
            "category":"Wholesale",
            "subcategory":"Machinery & Supplies",
            "type":"Manufacturing & Wholesale Goods"
        }
    ],
    "sg:phone":"+44 1625 506300",
    "sg:postcode":"SK11 0DF",
    "sg:province":"Cheshire",
    "sg:tags":[
        "industrial",
        "commercial"
    ],
    "wof:name":"Rieter-Scragg Ltd.",
    "wof:placetype":"venue"
},
  "geometry": {"coordinates":[-2.09136796,53.2413063049],"type":"Point"}
}