{
  "type": "Feature",
  "properties": {
    "iso:country":"GB",
    "sg:address":"32 Crakehall Road, Ecclesfield",
    "sg:city":"Sheffield",
    "sg:classifiers":[
        {
            "category":"Building & Trades",
            "subcategory":"Construction",
            "type":"Services"
        }
    ],
    "sg:phone":"+44 114 245 1526",
    "sg:postcode":"S35 9WQ",
    "sg:province":"South Yorkshire",
    "sg:tags":[
        "roofing",
        "contracting"
    ],
    "wof:name":"Anglo Roofing Specialists",
    "wof:placetype":"venue"
},
  "geometry": {"coordinates":[-1.4666310549,53.4521598816],"type":"Point"}
}