{
  "type": "Feature",
  "properties": {
    "addr:full":"1 Beaconsfield Road, Portslade Brighton East Sussex BN41 1XA",
    "addr:housenumber":"1",
    "addr:postcode":"bn41 1xa",
    "addr:street":"Beaconsfield Road",
    "iso:country":"GB",
    "sg:address":"1 Beaconsfield Road, Portslade",
    "sg:city":"Brighton",
    "sg:classifiers":[
        {
            "category":"Home & Garden",
            "subcategory":"Building Materials",
            "type":"Retail Goods"
        }
    ],
    "sg:phone":"+44 1273 418878",
    "sg:postcode":"BN41 1XA",
    "sg:province":"East Sussex",
    "sg:tags":[
        "gate",
        "door",
        "barrier"
    ],
    "wof:name":"Sussex Fencing & Construction Co.",
    "wof:placetype":"venue"
},
  "geometry": {"coordinates":[-0.215921,50.836849],"type":"Point"}
}