{
  "type": "Feature",
  "properties": {
    "addr:full":"21 Botchergate Carlisle Cumbria CA1 1RP",
    "addr:housenumber":"21",
    "addr:postcode":"ca1 1rp",
    "addr:street":"Botchergate",
    "iso:country":"GB",
    "sg:address":"21 Botchergate",
    "sg:city":"Carlisle",
    "sg:classifiers":[
        {
            "category":"Home & Garden",
            "subcategory":"Furniture",
            "type":"Retail Goods"
        }
    ],
    "sg:postcode":"CA1 1RP",
    "sg:province":"Cumbria",
    "wof:name":"Guest,George,",
    "wof:placetype":"venue"
},
  "geometry": {"coordinates":[-2.9316899776,54.8911132812],"type":"Point"}
}