{
  "type": "Feature",
  "properties": {
    "addr:full":"27-29 Bridge Street Worksop Nottinghamshire S80 1DA",
    "addr:housenumber":"27-29",
    "addr:postcode":"s80 1da",
    "addr:street":"Bridge Street",
    "iso:country":"GB",
    "sg:address":"27-29 Bridge Street",
    "sg:city":"Worksop",
    "sg:classifiers":[
        {
            "category":"Wholesale",
            "subcategory":"Construction Materials",
            "type":"Manufacturing & Wholesale Goods"
        },
        {
            "category":"Travel",
            "subcategory":"Travel Agent",
            "type":"Entertainment"
        }
    ],
    "sg:postcode":"S80 1DA",
    "sg:province":"Nottinghamshire",
    "sg:tags":[
        "refractory"
    ],
    "wof:name":"Kilton Industries Ltd.",
    "wof:placetype":"venue"
},
  "geometry": {"coordinates":[-1.1242630482,53.3039245605],"type":"Point"}
}