{
  "type": "Feature",
  "properties": {
    "addr:full":"13 Lindisfarne Clo Newcastle Upon Tyne Tyne and Wear NE5 2BU",
    "addr:housenumber":"13",
    "addr:postcode":"ne5 2bu",
    "addr:street":"Lindisfarne Clo",
    "iso:country":"GB",
    "sg:address":"13 Lindisfarne Clo",
    "sg:city":"Newcastle Upon Tyne",
    "sg:classifiers":[
        {
            "category":"Building & Trades",
            "subcategory":"Plumbing",
            "type":"Services"
        }
    ],
    "sg:phone":"+44 191 243 2744",
    "sg:postcode":"NE5 2BU",
    "sg:province":"Tyne and Wear",
    "sg:tags":[
        "heating"
    ],
    "wof:name":"C T Plumbing & Heating",
    "wof:placetype":"venue"
},
  "geometry": {"coordinates":[-1.696293,54.988655],"type":"Point"}
}