{
  "type": "Feature",
  "properties": {
    "iso:country":"GB",
    "sg:address":"2 Glen Park Avenue",
    "sg:city":"Plymouth",
    "sg:classifiers":[
        {
            "category":"Building & Trades",
            "subcategory":"Construction",
            "type":"Services"
        }
    ],
    "sg:phone":"+44 1752 223545",
    "sg:postcode":"PL4 6BA",
    "sg:province":"Devon",
    "sg:tags":[
        "joiner",
        "carpenter"
    ],
    "wof:name":"Alan Holwill",
    "wof:placetype":"venue"
},
  "geometry": {"coordinates":[-4.140063,50.379013],"type":"Point"}
}