{
  "type": "Feature",
  "properties": {
    "addr:full":"5 Princes Avenue Hull East Riding of Yorkshire HU5 3RN",
    "addr:housenumber":"5",
    "addr:postcode":"hu5 3rn",
    "addr:street":"Princes Avenue",
    "iso:country":"GB",
    "sg:address":"5 Princes Avenue",
    "sg:city":"Hull",
    "sg:classifiers":[
        {
            "category":"Personal",
            "subcategory":"Beauty Salon",
            "type":"Services"
        }
    ],
    "sg:postcode":"HU5 3RN",
    "sg:province":"East Riding of Yorkshire",
    "sg:tags":[
        "unisex",
        "hairdresser"
    ],
    "wof:name":"Imij Hair Studio",
    "wof:placetype":"venue"
},
  "geometry": {"coordinates":[-0.361194998,53.7520561218],"type":"Point"}
}