{
  "type": "Feature",
  "properties": {
    "addr:full":"197 Broadway Didcot Oxfordshire OX11 8RU",
    "addr:housenumber":"197",
    "addr:postcode":"ox11 8ru",
    "addr:street":"Broadway",
    "iso:country":"GB",
    "sg:address":"197 Broadway",
    "sg:city":"Didcot",
    "sg:classifiers":[
        {
            "category":"Education",
            "subcategory":"Library",
            "type":"Public Place"
        }
    ],
    "sg:phone":"+44 1235 813103",
    "sg:postcode":"OX11 8RU",
    "sg:province":"Oxfordshire",
    "sg:tags":[
        "book"
    ],
    "wof:name":"Didcot Library",
    "wof:placetype":"venue"
},
  "geometry": {"coordinates":[-1.2474199533,51.6062011719],"type":"Point"}
}