{
  "type": "Feature",
  "properties": {
    "addr:full":"1a Hardwick Mount, Buxton Derby Derbyshire SK17 6PP",
    "addr:housenumber":"1a",
    "addr:postcode":"sk17 6pp",
    "addr:street":"Hardwick Mount",
    "iso:country":"GB",
    "sg:address":"1a Hardwick Mount, Buxton",
    "sg:city":"Derby",
    "sg:classifiers":[
        {
            "category":"Manufacturing",
            "subcategory":"Tools & Machinery",
            "type":"Manufacturing & Wholesale Goods"
        }
    ],
    "sg:phone":"+44 1298 78944",
    "sg:postcode":"SK17 6PP",
    "sg:province":"Derbyshire",
    "sg:tags":[
        "society",
        "friendly"
    ],
    "wof:name":"Spa Insurance Services",
    "wof:placetype":"venue"
},
  "geometry": {"coordinates":[-1.910568,53.25819],"type":"Point"}
}