{
  "type": "Feature",
  "properties": {
    "iso:country":"GB",
    "sg:address":"27 Robinson Road, Scole",
    "sg:city":"Diss",
    "sg:classifiers":[
        {
            "category":"Shopping",
            "subcategory":"Musical Instruments",
            "type":"Retail Goods"
        }
    ],
    "sg:phone":"+44 1379 740929",
    "sg:postcode":"IP21 4EF",
    "sg:province":"Norfolk",
    "wof:name":"John Garlinge",
    "wof:placetype":"venue"
},
  "geometry": {"coordinates":[1.155888,52.364529],"type":"Point"}
}