{
  "type": "Feature",
  "properties": {
    "iso:country":"GB",
    "sg:address":"117 Market Street, Farnworth",
    "sg:city":"Bolton",
    "sg:classifiers":[
        {
            "category":"Shopping",
            "subcategory":"Florist",
            "type":"Retail Goods"
        }
    ],
    "sg:phone":"+44 1204 577939",
    "sg:postcode":"BL4 8EX",
    "sg:province":"Lancashire",
    "wof:name":"David Underwood Florists",
    "wof:placetype":"venue"
},
  "geometry": {"coordinates":[-2.3935489655,53.5488052368],"type":"Point"}
}