{
  "type": "Feature",
  "properties": {
    "addr:full":"1 Drewstead Road London Greater London SW16 1LY",
    "addr:housenumber":"1",
    "addr:postcode":"sw16 1ly",
    "addr:street":"Drewstead Road",
    "iso:country":"GB",
    "sg:address":"1 Drewstead Road",
    "sg:city":"London",
    "sg:classifiers":[
        {
            "category":"Personal",
            "subcategory":"Beauty Salon",
            "type":"Services"
        }
    ],
    "sg:postcode":"SW16 1LY",
    "sg:province":"Greater London",
    "sg:tags":[
        "unisex",
        "hairdresser"
    ],
    "wof:name":"Shades",
    "wof:placetype":"venue"
},
  "geometry": {"coordinates":[-0.1272509992,51.4379386902],"type":"Point"}
}