{
  "type": "Feature",
  "properties": {
    "addr:full":"2 Norwood Court Ibrox Business Park Glasgow Glasgow City G51 2JR",
    "addr:housenumber":"2",
    "addr:postcode":"g51 2jr",
    "addr:street":"Norwood Court Ibrox Business Park",
    "iso:country":"GB",
    "sg:address":"2 Norwood Court Ibrox Business Park",
    "sg:city":"Glasgow",
    "sg:classifiers":[
        {
            "category":"Home & Garden",
            "subcategory":"Carpets & Floor Coverings",
            "type":"Retail Goods"
        }
    ],
    "sg:phone":"+44 141 445 6548",
    "sg:postcode":"G51 2JR",
    "sg:province":"Glasgow City",
    "sg:tags":[
        "rubber",
        "plastic"
    ],
    "wof:name":"Bottcher Airedale Ltd.",
    "wof:placetype":"venue"
},
  "geometry": {"coordinates":[-4.3097,55.854912],"type":"Point"}
}