{
  "type": "Feature",
  "properties": {
    "iso:country":"GB",
    "sg:address":"Unit 6, Pipers Industrial Estate, Pipers Lane",
    "sg:city":"Thatcham",
    "sg:classifiers":[
        {
            "category":"Manufacturing",
            "subcategory":"Metals",
            "type":"Manufacturing & Wholesale Goods"
        },
        {
            "category":"Wholesale",
            "subcategory":"Metals & Minerals",
            "type":"Manufacturing & Wholesale Goods"
        }
    ],
    "sg:phone":"+44 1635 873737",
    "sg:postcode":"RG19 4NA",
    "sg:province":"Berkshire",
    "sg:tags":[
        "fabricator",
        "work",
        "sheet"
    ],
    "wof:name":"Taylor Made Fabrication Ltd.",
    "wof:placetype":"venue"
},
  "geometry": {"coordinates":[-1.24073,51.39521],"type":"Point"}
}