{
  "type": "Feature",
  "properties": {
    "addr:full":"133 Oldham Road, Royton Oldham Lancashire OL2 6BU",
    "addr:housenumber":"133",
    "addr:postcode":"ol2 6bu",
    "addr:street":"Oldham Road",
    "iso:country":"GB",
    "sg:address":"133 Oldham Road, Royton",
    "sg:city":"Oldham",
    "sg:classifiers":[
        {
            "category":"Bars & Pubs",
            "type":"Food & Drink"
        }
    ],
    "sg:phone":"+44 161 624 7292",
    "sg:postcode":"OL2 6BU",
    "sg:province":"Lancashire",
    "sg:tags":[
        "pubs",
        "inn"
    ],
    "wof:name":"Greenalls Management Ltd.",
    "wof:placetype":"venue"
},
  "geometry": {"coordinates":[-2.1198720932,53.5618019104],"type":"Point"}
}