{
  "type": "Feature",
  "properties": {
    "iso:country":"GB",
    "sg:address":"The Red Ho, Brentwood Rd, Orsett",
    "sg:city":"Grays",
    "sg:classifiers":[
        {
            "category":"Professional",
            "subcategory":"Computer Services",
            "type":"Services"
        }
    ],
    "sg:phone":"+44 1375 892885",
    "sg:postcode":"RM16 3BP",
    "sg:province":"Essex",
    "sg:tags":[
        "system",
        "software"
    ],
    "wof:name":"Red House Trading (Orsett) Ltd (The)",
    "wof:placetype":"venue"
},
  "geometry": {"coordinates":[0.366775,51.512321],"type":"Point"}
}