{
  "type": "Feature",
  "properties": {
    "iso:country":"GB",
    "sg:address":"25 Parsons Street",
    "sg:city":"Banbury",
    "sg:classifiers":[
        {
            "category":"Shopping",
            "subcategory":"Clothing, Apparel, & Fashions",
            "type":"Retail Goods"
        }
    ],
    "sg:phone":"+44 1295 269653",
    "sg:postcode":"OX16 5LY",
    "sg:province":"Oxfordshire",
    "sg:tags":[
        "lady",
        "fashionwear",
        "ladieswear"
    ],
    "wof:name":"Gemini",
    "wof:placetype":"venue"
},
  "geometry": {"coordinates":[-1.3361029625,52.0621109009],"type":"Point"}
}