{
  "type": "Feature",
  "properties": {
    "addr:full":"11a South St Torrington Devon EX38 8AA",
    "addr:housenumber":"11a",
    "addr:postcode":"ex38 8aa",
    "addr:street":"South St",
    "iso:country":"GB",
    "sg:address":"11a South St",
    "sg:city":"Torrington",
    "sg:classifiers":[
        {
            "category":"Shopping",
            "subcategory":"Used Merchandise",
            "type":"Retail Goods"
        }
    ],
    "sg:postcode":"EX38 8AA",
    "sg:province":"Devon",
    "sg:tags":[
        "shop",
        "second-hand"
    ],
    "wof:name":"Kimber,J & T,",
    "wof:placetype":"venue"
},
  "geometry": {"coordinates":[-4.1438798904,50.9515762329],"type":"Point"}
}