{
  "type": "Feature",
  "properties": {
    "addr:full":"105 Bolingbroke Gro Battersea Greater London SW11 1DA",
    "addr:housenumber":"105",
    "addr:postcode":"sw11 1da",
    "addr:street":"Bolingbroke Gro",
    "iso:country":"GB",
    "sg:address":"105 Bolingbroke Gro",
    "sg:city":"Battersea",
    "sg:classifiers":[
        {
            "category":"Building & Trades",
            "subcategory":"Construction",
            "type":"Services"
        }
    ],
    "sg:phone":"+44 20 7228 0484",
    "sg:postcode":"SW11 1DA",
    "sg:province":"Greater London",
    "sg:tags":[
        "builder"
    ],
    "wof:name":"H B Pratt",
    "wof:placetype":"venue"
},
  "geometry": {"coordinates":[-0.1705989987,51.4580383301],"type":"Point"}
}