{
  "type": "Feature",
  "properties": {
    "iso:country":"GB",
    "sg:address":"80-82 Church Rd, Litherland",
    "sg:city":"Liverpool",
    "sg:classifiers":[
        {
            "category":"Shopping",
            "subcategory":"Department Store",
            "type":"Retail Goods"
        }
    ],
    "sg:phone":"+44 151 949 0895",
    "sg:postcode":"L21 8NY",
    "sg:province":"Merseyside",
    "wof:name":"Church Rd Stores",
    "wof:placetype":"venue"
},
  "geometry": {"coordinates":[-2.9968519211,53.4702453613],"type":"Point"}
}