{
  "type": "Feature",
  "properties": {
    "iso:country":"GB",
    "sg:address":"21 Raby Road",
    "sg:city":"Stockton-on-tees",
    "sg:classifiers":[
        {
            "category":"Building & Trades",
            "subcategory":"Plumbing",
            "type":"Services"
        }
    ],
    "sg:phone":"+44 1642 604677",
    "sg:postcode":"TS18 4HZ",
    "sg:province":"Durham",
    "sg:tags":[
        "heating"
    ],
    "wof:name":"Hartburn Plumbing & Heating",
    "wof:placetype":"venue"
},
  "geometry": {"coordinates":[-1.340955019,54.5632133484],"type":"Point"}
}