{
  "type": "Feature",
  "properties": {
    "addr:full":"Mortimer Market Bloomsbury Greater London WC1E 6JD",
    "addr:postcode":"wc1e 6jd",
    "iso:country":"GB",
    "sg:address":"Mortimer Market",
    "sg:city":"Bloomsbury",
    "sg:classifiers":[
        {
            "category":"Health Services",
            "subcategory":"Clinic",
            "type":"Services"
        }
    ],
    "sg:phone":"+44 20 7530 5000",
    "sg:postcode":"WC1E 6JD",
    "sg:province":"Greater London",
    "sg:tags":[
        "nh"
    ],
    "wof:name":"The Mortimer Market Centre",
    "wof:placetype":"venue"
},
  "geometry": {"coordinates":[-0.135677,51.522694],"type":"Point"}
}