{
  "type": "Feature",
  "properties": {
    "iso:country":"GB",
    "sg:address":"20 Island Farm Avenue, Molesey Trading Estate",
    "sg:city":"West Molesey",
    "sg:classifiers":[
        {
            "category":"Shopping",
            "subcategory":"Beauty & Cosmetics",
            "type":"Retail Goods"
        }
    ],
    "sg:phone":"+44 20 8979 7261",
    "sg:postcode":"KT8 2UZ",
    "sg:province":"Greater London",
    "sg:tags":[
        "product"
    ],
    "sg:website":"http://www.jica.com",
    "wof:name":"Jica Beauty Products Ltd",
    "wof:placetype":"venue"
},
  "geometry": {"coordinates":[-0.369918,51.396629],"type":"Point"}
}