{
  "type": "Feature",
  "properties": {
    "iso:country":"GB",
    "sg:address":"The Arcade, King St",
    "sg:city":"Stirling",
    "sg:classifiers":[
        {
            "category":"Education",
            "subcategory":"Special Training",
            "type":"Public Place"
        }
    ],
    "sg:postcode":"FK8 1DN",
    "sg:province":"Stirling",
    "sg:tags":[
        "product",
        "centre"
    ],
    "wof:name":"Stirling Women's Technology Centre Ltd",
    "wof:placetype":"venue"
},
  "geometry": {"coordinates":[-3.9395198822,56.1173591614],"type":"Point"}
}