{
  "type": "Feature",
  "properties": {
    "addr:full":"Bangor, Harmans Cross, Corfe Castle Wareham Dorset BH20 5HX",
    "addr:postcode":"bh20 5hx",
    "addr:street":"Cross",
    "iso:country":"GB",
    "sg:address":"Bangor, Harmans Cross, Corfe Castle",
    "sg:city":"Wareham",
    "sg:classifiers":[
        {
            "category":"Building & Trades",
            "subcategory":"Construction",
            "type":"Services"
        }
    ],
    "sg:phone":"+44 1929 480642",
    "sg:postcode":"BH20 5HX",
    "sg:province":"Dorset",
    "sg:tags":[
        "builder"
    ],
    "wof:name":"John Varney",
    "wof:placetype":"venue"
},
  "geometry": {"coordinates":[-2.1126070023,50.6898880005],"type":"Point"}
}