{
  "type": "Feature",
  "properties": {
    "addr:full":"168 Kiln Lane St Helens Merseyside WA10 4RB",
    "addr:housenumber":"168",
    "addr:postcode":"wa10 4rb",
    "addr:street":"Kiln Lane",
    "iso:country":"GB",
    "sg:address":"168 Kiln Lane",
    "sg:city":"St Helens",
    "sg:classifiers":[
        {
            "category":"Deli",
            "type":"Food & Drink"
        }
    ],
    "sg:phone":"+44 1744 22912",
    "sg:postcode":"WA10 4RB",
    "sg:province":"Merseyside",
    "sg:tags":[
        "delicatessen"
    ],
    "wof:name":"Christies Delicatessen",
    "wof:placetype":"venue"
},
  "geometry": {"coordinates":[-2.7710609436,53.4604568481],"type":"Point"}
}