{
  "type": "Feature",
  "properties": {
    "addr:full":"6 Derby Road Burton-on-trent Derbyshire DE14 1RU",
    "addr:housenumber":"6",
    "addr:postcode":"de14 1ru",
    "addr:street":"Derby Road",
    "iso:country":"GB",
    "sg:address":"6 Derby Road",
    "sg:city":"Burton-on-trent",
    "sg:classifiers":[
        {
            "category":"Farming",
            "subcategory":"Nursery",
            "type":"Manufacturing & Wholesale Goods"
        }
    ],
    "sg:phone":"+44 1283 539200",
    "sg:postcode":"DE14 1RU",
    "sg:province":"Derbyshire",
    "sg:tags":[
        "creche"
    ],
    "wof:name":"Honey Pots Day Nursery",
    "wof:placetype":"venue"
},
  "geometry": {"coordinates":[-1.63489,52.814346],"type":"Point"}
}