{
  "type": "Feature",
  "properties": {
    "iso:country":"GB",
    "sg:address":"22 Glebe Road",
    "sg:city":"Bedlington",
    "sg:classifiers":[
        {
            "category":"Personal",
            "subcategory":"Barber",
            "type":"Services"
        }
    ],
    "sg:phone":"+44 1670 822092",
    "sg:postcode":"NE22 6JT",
    "sg:province":"Northumberland",
    "sg:tags":[
        "men's",
        "hairdresser"
    ],
    "wof:name":"John H A & Alan Wailes",
    "wof:placetype":"venue"
},
  "geometry": {"coordinates":[-1.600225,55.13282],"type":"Point"}
}