{
  "type": "Feature",
  "properties": {
    "addr:full":"Warnford Southampton Hampshire SO32 3LG",
    "addr:postcode":"so32 3lg",
    "iso:country":"GB",
    "sg:address":"Warnford",
    "sg:city":"Southampton",
    "sg:classifiers":[
        {
            "category":"Home & Garden",
            "subcategory":"Building Materials",
            "type":"Retail Goods"
        }
    ],
    "sg:phone":"+44 1730 829064",
    "sg:postcode":"SO32 3LG",
    "sg:province":"Hampshire",
    "sg:tags":[
        "gate",
        "door",
        "barrier"
    ],
    "wof:name":"Wheely Down Wood Products",
    "wof:placetype":"venue"
},
  "geometry": {"coordinates":[-1.121739,50.986816],"type":"Point"}
}