{
  "type": "Feature",
  "properties": {
    "addr:full":"Westwey Road Weymouth Dorset DT4 8SU",
    "addr:postcode":"dt4 8su",
    "addr:street":"Westwey Road",
    "iso:country":"GB",
    "sg:address":"Westwey Road",
    "sg:city":"Weymouth",
    "sg:classifiers":[
        {
            "category":"Autos & Motor Vehicles",
            "subcategory":"Auto Supplies",
            "type":"Retail Goods"
        }
    ],
    "sg:phone":"+44 1305 779984",
    "sg:postcode":"DT4 8SU",
    "sg:province":"Dorset",
    "sg:tags":[
        "tyre"
    ],
    "wof:name":"Tyre & Exhaust World Ltd.",
    "wof:placetype":"venue"
},
  "geometry": {"coordinates":[-2.4592061043,50.6099014282],"type":"Point"}
}