{
  "type": "Feature",
  "properties": {
    "iso:country":"GB",
    "sg:address":"27 Princes Drive",
    "sg:city":"Colwyn Bay",
    "sg:classifiers":[
        {
            "category":"Real Estate",
            "subcategory":"Architect",
            "type":"Services"
        }
    ],
    "sg:phone":"+44 1492 533818",
    "sg:postcode":"LL29 8HT",
    "sg:province":"Conwy",
    "wof:name":"David Williams Partnership",
    "wof:placetype":"venue"
},
  "geometry": {"coordinates":[-3.730299,53.297695],"type":"Point"}
}