{
  "type": "Feature",
  "properties": {
    "addr:full":"Unit 1 Swinden Court Milton Keynes Buckinghamshire MK13 7PN",
    "addr:housenumber":"unit 1",
    "addr:postcode":"mk13 7pn",
    "addr:street":"Swinden Court",
    "iso:country":"GB",
    "sg:address":"Unit 1 Swinden Court",
    "sg:city":"Milton Keynes",
    "sg:classifiers":[
        {
            "category":"Fast Food",
            "type":"Food & Drink"
        }
    ],
    "sg:phone":"+44 1908 320898",
    "sg:postcode":"MK13 7PN",
    "sg:province":"Buckinghamshire",
    "sg:tags":[
        "away",
        "take"
    ],
    "wof:name":"Raphael's Barbeque & Pizza Bar",
    "wof:placetype":"venue"
},
  "geometry": {"coordinates":[-0.7794489861,52.051235199],"type":"Point"}
}