{
  "type": "Feature",
  "properties": {
    "iso:country":"GB",
    "sg:address":"2 Beaumond Green",
    "sg:city":"Winchester",
    "sg:classifiers":[
        {
            "category":"Professional",
            "subcategory":"Management & Consulting",
            "type":"Services"
        }
    ],
    "sg:postcode":"SO23 8GF",
    "sg:province":"Hampshire",
    "sg:tags":[
        "consultant",
        "business"
    ],
    "wof:name":"Cna Executive Search (Pro) Ltd",
    "wof:placetype":"venue"
},
  "geometry": {"coordinates":[-1.319688,51.061157],"type":"Point"}
}