{
  "type": "Feature",
  "properties": {
    "addr:full":"Dental Surgery, 16-17 St. James Sq Monmouth Monmouthshire NP5 3DN",
    "addr:housenumber":"16-17",
    "addr:postcode":"np5 3dn",
    "addr:street":"St. James Sq",
    "iso:country":"GB",
    "sg:address":"Dental Surgery, 16-17 St. James Sq",
    "sg:city":"Monmouth",
    "sg:classifiers":[
        {
            "category":"Health Services",
            "subcategory":"Dentist",
            "type":"Services"
        }
    ],
    "sg:phone":"+44 1600 712042",
    "sg:postcode":"NP5 3DN",
    "sg:province":"Monmouthshire",
    "wof:name":"R D B Issac",
    "wof:placetype":"venue"
},
  "geometry": {"coordinates":[-2.7110080719,51.8126525879],"type":"Point"}
}