{
  "type": "Feature",
  "properties": {
    "addr:full":"45a Saville St Macclesfield Cheshire SK11 7LQ",
    "addr:housenumber":"45a",
    "addr:postcode":"sk11 7lq",
    "addr:street":"Saville St",
    "iso:country":"GB",
    "sg:address":"45a Saville St",
    "sg:city":"Macclesfield",
    "sg:classifiers":[
        {
            "category":"Shopping",
            "subcategory":"Discount & Variety Stores",
            "type":"Retail Goods"
        }
    ],
    "sg:phone":"+44 1625 433938",
    "sg:postcode":"SK11 7LQ",
    "sg:province":"Cheshire",
    "sg:tags":[
        "shop",
        "model"
    ],
    "wof:name":"Macclesfield Model Engineering Supplies",
    "wof:placetype":"venue"
},
  "geometry": {"coordinates":[-2.115838,53.25404],"type":"Point"}
}