{
  "type": "Feature",
  "properties": {
    "addr:full":"46 Buchanan Street Glasgow Glasgow City G1 3JX",
    "addr:housenumber":"46",
    "addr:postcode":"g1 3jx",
    "addr:street":"Buchanan Street",
    "iso:country":"GB",
    "sg:address":"46 Buchanan Street",
    "sg:city":"Glasgow",
    "sg:classifiers":[
        {
            "category":"Shopping",
            "subcategory":"Clothing, Apparel, & Fashions",
            "type":"Retail Goods"
        }
    ],
    "sg:phone":"+44 141 226 5113",
    "sg:postcode":"G1 3JX",
    "sg:province":"Glasgow City",
    "sg:tags":[
        "ladieswear"
    ],
    "wof:name":"Karen Millen",
    "wof:placetype":"venue"
},
  "geometry": {"coordinates":[-4.254311,55.85931],"type":"Point"}
}