{
  "type": "Feature",
  "properties": {
    "addr:full":"Unit 5 Glebe Close Farm, Cublington Road, Wing Leighton Buzzard Bedfordshire LU7 0LB",
    "addr:housenumber":"unit 5",
    "addr:postcode":"lu7 0lb",
    "addr:street":"Glebe Close;Cublington Road",
    "iso:country":"GB",
    "sg:address":"Unit 5 Glebe Close Farm, Cublington Road, Wing",
    "sg:city":"Leighton Buzzard",
    "sg:classifiers":[
        {
            "category":"Organizations",
            "subcategory":"Labor Organization",
            "type":"Services"
        },
        {
            "category":"Government",
            "subcategory":"Post Office",
            "type":"Public Place"
        }
    ],
    "sg:phone":"+44 1296 682552",
    "sg:postcode":"LU7 0LB",
    "sg:province":"Bedfordshire",
    "sg:tags":[
        "supplier",
        "equipment",
        "paging",
        "system"
    ],
    "sg:website":"http://www.datanet.org.uk",
    "wof:name":"Datanet Radio Communications",
    "wof:placetype":"venue"
},
  "geometry": {"coordinates":[-0.780385,51.892303],"type":"Point"}
}