{
  "type": "Feature",
  "properties": {
    "addr:full":"91 The Avenue Sale Cheshire M33 4GA",
    "addr:housenumber":"91",
    "addr:postcode":"m33 4ga",
    "addr:street":"The Avenue",
    "iso:country":"GB",
    "sg:address":"91 The Avenue",
    "sg:city":"Sale",
    "sg:classifiers":[
        {
            "category":"Building & Trades",
            "subcategory":"Equipment Rental",
            "type":"Services"
        }
    ],
    "sg:phone":"+44 161 764 2580",
    "sg:postcode":"M33 4GA",
    "sg:province":"Cheshire",
    "sg:tags":[
        "plant",
        "machinery"
    ],
    "wof:name":"Didsbury Plant Hire Ltd.",
    "wof:placetype":"venue"
},
  "geometry": {"coordinates":[-2.347175,53.417038],"type":"Point"}
}