{
  "type": "Feature",
  "properties": {
    "iso:country":"GB",
    "sg:address":"46 Berkeley St",
    "sg:city":"West End",
    "sg:classifiers":[
        {
            "category":"Banks & Credit Unions",
            "subcategory":"Bank",
            "type":"Services"
        }
    ],
    "sg:phone":"+44 20 7499 1234",
    "sg:postcode":"W1X 6AA",
    "sg:province":"Hampshire",
    "wof:name":"Bank of New York",
    "wof:placetype":"venue"
},
  "geometry": {"coordinates":[-0.1431940049,51.5079154968],"type":"Point"}
}