{
  "type": "Feature",
  "properties": {
    "iso:country":"GB",
    "sg:address":"239 Whalley New Road",
    "sg:city":"Blackburn",
    "sg:classifiers":[
        {
            "category":"Food & Beverages",
            "subcategory":"Bakery",
            "type":"Retail Goods"
        },
        {
            "category":"Bakery",
            "type":"Food & Drink"
        }
    ],
    "sg:phone":"+44 1254 680445",
    "sg:postcode":"BB1 9TJ",
    "sg:province":"Lancashire",
    "sg:tags":[
        "cake",
        "shop",
        "baker",
        "maker"
    ],
    "wof:name":"Caroline's Celebration Cakes",
    "wof:placetype":"venue"
},
  "geometry": {"coordinates":[-2.472503,53.762165],"type":"Point"}
}