{
  "type": "Feature",
  "properties": {
    "addr:full":"Poppies, Sutherland Dr, Weylea Farm, Burpham Guildford Surrey GU4 7YJ",
    "addr:housenumber":"burpham",
    "addr:postcode":"gu4 7yj",
    "addr:street":"Sutherland Dr",
    "iso:country":"GB",
    "sg:address":"Poppies, Sutherland Dr, Weylea Farm, Burpham",
    "sg:city":"Guildford",
    "sg:classifiers":[
        {
            "category":"Building & Trades",
            "subcategory":"Construction",
            "type":"Services"
        }
    ],
    "sg:postcode":"GU4 7YJ",
    "sg:province":"Surrey",
    "sg:tags":[
        "glazier"
    ],
    "wof:name":"Durant,Michael,",
    "wof:placetype":"venue"
},
  "geometry": {"coordinates":[-0.5454589725,51.2584838867],"type":"Point"}
}