{
  "type": "Feature",
  "properties": {
    "addr:full":"11 London Road Twickenham Greater London TW1 3SX",
    "addr:housenumber":"11",
    "addr:postcode":"tw1 3sx",
    "addr:street":"London Road",
    "iso:country":"GB",
    "sg:address":"11 London Road",
    "sg:city":"Twickenham",
    "sg:classifiers":[
        {
            "category":"Bars & Pubs",
            "type":"Food & Drink"
        }
    ],
    "sg:phone":"+44 20 8891 2505",
    "sg:postcode":"TW1 3SX",
    "sg:province":"Greater London",
    "sg:tags":[
        "pubs",
        "inn"
    ],
    "wof:name":"The Hobgoblin",
    "wof:placetype":"venue"
},
  "geometry": {"coordinates":[-0.3284380138,51.4469108582],"type":"Point"}
}