{
  "type": "Feature",
  "properties": {
    "addr:full":"Unit 141 Brooker Rd Waltham Abbey Essex EN9 1JH",
    "addr:housenumber":"141",
    "addr:postcode":"en9 1jh",
    "addr:street":"Brooker Rd;Abbey",
    "iso:country":"GB",
    "sg:address":"Unit 141 Brooker Rd",
    "sg:city":"Waltham Abbey",
    "sg:classifiers":[
        {
            "category":"Retail",
            "subcategory":"Auto Repair",
            "type":"Services"
        }
    ],
    "sg:postcode":"EN9 1JH",
    "sg:province":"Essex",
    "sg:tags":[
        "modification",
        "garage"
    ],
    "wof:name":"Danton,Paul,",
    "wof:placetype":"venue"
},
  "geometry": {"coordinates":[-0.0021319999,51.6841583252],"type":"Point"}
}