{
  "type": "Feature",
  "properties": {
    "addr:full":"83 Rye Lane London Greater London SE15 5EX",
    "addr:housenumber":"83",
    "addr:postcode":"se15 5ex",
    "addr:street":"Rye Lane",
    "iso:country":"GB",
    "sg:address":"83 Rye Lane",
    "sg:city":"London",
    "sg:classifiers":[
        {
            "category":"Shopping",
            "subcategory":"Clothing, Apparel, & Fashions",
            "type":"Retail Goods"
        }
    ],
    "sg:phone":"+44 20 7732 4553",
    "sg:postcode":"SE15 5EX",
    "sg:province":"Greater London",
    "sg:tags":[
        "menswear"
    ],
    "wof:name":"Stone (Colours)",
    "wof:placetype":"venue"
},
  "geometry": {"coordinates":[-0.069187,51.471127],"type":"Point"}
}