{
  "type": "Feature",
  "properties": {
    "iso:country":"GB",
    "sg:address":"33 Greenville Gardens",
    "sg:city":"Leeds",
    "sg:classifiers":[
        {
            "category":"Professional",
            "subcategory":"Engineering",
            "type":"Services"
        }
    ],
    "sg:phone":"+44 113 279 3534",
    "sg:postcode":"LS12 4TB",
    "sg:province":"West Yorkshire",
    "sg:tags":[
        "contractor",
        "electrical",
        "engineer"
    ],
    "wof:name":"Mason Electrical",
    "wof:placetype":"venue"
},
  "geometry": {"coordinates":[-1.594013,53.787151],"type":"Point"}
}