{
  "type": "Feature",
  "properties": {
    "iso:country":"GB",
    "sg:address":"23 Hainton Ave",
    "sg:city":"Grimsby",
    "sg:classifiers":[
        {
            "category":"Shopping",
            "subcategory":"Thrift Store",
            "type":"Retail Goods"
        }
    ],
    "sg:postcode":"DN32 9AS",
    "sg:province":"Lincolnshire",
    "sg:tags":[
        "shop",
        "charity"
    ],
    "wof:name":"British Epilepsy Association",
    "wof:placetype":"venue"
},
  "geometry": {"coordinates":[-0.074814,53.566196],"type":"Point"}
}