{
  "type": "Feature",
  "properties": {
    "iso:country":"GB",
    "sg:address":"10 Sandisplatt",
    "sg:city":"Fareham",
    "sg:classifiers":[
        {
            "category":"Building & Trades",
            "subcategory":"Construction",
            "type":"Services"
        }
    ],
    "sg:postcode":"PO14 3AG",
    "sg:province":"Hampshire",
    "sg:tags":[
        "joinery",
        "joiner",
        "carpenter",
        "carpentry"
    ],
    "wof:name":"Terrence D & Prescilla Palmer",
    "wof:placetype":"venue"
},
  "geometry": {"coordinates":[-1.216099,50.846542],"type":"Point"}
}