{
  "type": "Feature",
  "properties": {
    "addr:full":"The Vicarage, Vicarage Lane Kirkby Stephen Cumbria CA17 4QX",
    "addr:postcode":"ca17 4qx",
    "addr:street":"Vicarage Lane",
    "iso:country":"GB",
    "sg:address":"The Vicarage, Vicarage Lane",
    "sg:city":"Kirkby Stephen",
    "sg:classifiers":[
        {
            "category":"Place Of Worship",
            "type":"Public Place"
        }
    ],
    "sg:phone":"+44 17683 71204",
    "sg:postcode":"CA17 4QX",
    "sg:province":"Cumbria",
    "wof:name":"Kirkby Stephen Parish Church",
    "wof:placetype":"venue"
},
  "geometry": {"coordinates":[-2.320475,54.519615],"type":"Point"}
}