{
  "type": "Feature",
  "properties": {
    "iso:country":"GB",
    "sg:address":"Frizlands Lane",
    "sg:city":"Dagenham",
    "sg:classifiers":[
        {
            "category":"Education",
            "subcategory":"School",
            "type":"Public Place"
        }
    ],
    "sg:phone":"+44 20 8270 6506",
    "sg:postcode":"RM10 7HX",
    "sg:province":"Essex",
    "sg:tags":[
        "local",
        "authority"
    ],
    "wof:name":"William Bellamy Junior School",
    "wof:placetype":"venue"
},
  "geometry": {"coordinates":[0.1554850042,51.5588150024],"type":"Point"}
}