{
  "type": "Feature",
  "properties": {
    "addr:full":"11 Crombie Road Aberdeen Aberdeen City AB11 9QQ",
    "addr:housenumber":"11",
    "addr:postcode":"ab11 9qq",
    "addr:street":"Crombie Road",
    "iso:country":"GB",
    "sg:address":"11 Crombie Road",
    "sg:city":"Aberdeen",
    "sg:classifiers":[
        {
            "category":"Retail",
            "subcategory":"Storage",
            "type":"Services"
        }
    ],
    "sg:phone":"+44 1779 477446",
    "sg:postcode":"AB11 9QQ",
    "sg:province":"Aberdeen City",
    "sg:tags":[
        "cold",
        "activity",
        "domestic",
        "removal"
    ],
    "wof:name":"LUNAR FREEZING & COLD STORAGE COMPANY LTD",
    "wof:placetype":"venue"
},
  "geometry": {"coordinates":[-2.0863549709,57.1375732422],"type":"Point"}
}