{
  "type": "Feature",
  "properties": {
    "iso:country":"GB",
    "sg:address":"5 Main St, East Kilbride",
    "sg:city":"Glasgow",
    "sg:classifiers":[
        {
            "category":"Professional",
            "subcategory":"Accounting & Tax Preparation",
            "type":"Services"
        }
    ],
    "sg:postcode":"G74 4JH",
    "sg:province":"South Lanarkshire",
    "sg:tags":[
        "accountant"
    ],
    "wof:name":"Atkinson & Co",
    "wof:placetype":"venue"
},
  "geometry": {"coordinates":[-4.175078,55.76569],"type":"Point"}
}