{
  "type": "Feature",
  "properties": {
    "addr:full":"1 Manor Cottage, Hussell La Alton Hampshire GU34 5PF",
    "addr:housenumber":"1",
    "addr:postcode":"gu34 5pf",
    "addr:street":"Manor;Hussell La Alton",
    "iso:country":"GB",
    "sg:address":"1 Manor Cottage, Hussell La",
    "sg:city":"Alton",
    "sg:classifiers":[
        {
            "category":"Building & Trades",
            "subcategory":"Construction",
            "type":"Services"
        }
    ],
    "sg:phone":"+44 1420 562123",
    "sg:postcode":"GU34 5PF",
    "sg:province":"Hampshire",
    "sg:tags":[
        "builder"
    ],
    "wof:name":"Stan E Whitcher",
    "wof:placetype":"venue"
},
  "geometry": {"coordinates":[-0.9743289948,51.1475601196],"type":"Point"}
}