{
  "type": "Feature",
  "properties": {
    "iso:country":"GB",
    "sg:address":"25 Sardis, Burton",
    "sg:city":"Milford Haven",
    "sg:classifiers":[
        {
            "category":"Autos & Motor Vehicles",
            "subcategory":"Automobile Sales",
            "type":"Retail Goods"
        }
    ],
    "sg:phone":"+44 1646 600457",
    "sg:postcode":"SA73 1LY",
    "sg:province":"Pembrokeshire",
    "sg:tags":[
        "car"
    ],
    "wof:name":"Gareth J Hughes (Motors) Ltd.",
    "wof:placetype":"venue"
},
  "geometry": {"coordinates":[-4.93801,51.739311],"type":"Point"}
}