{
  "type": "Feature",
  "properties": {
    "addr:full":"Communications Ho, 5 Dolphin Sq, Edensor Rd Chiswick Greater London W4 2RG",
    "addr:housenumber":"5",
    "addr:postcode":"w4 2rg",
    "addr:street":"Dolphin Sq Edensor Rd",
    "iso:country":"GB",
    "sg:address":"Communications Ho, 5 Dolphin Sq, Edensor Rd",
    "sg:city":"Chiswick",
    "sg:classifiers":[
        {
            "category":"Organizations",
            "subcategory":"Labor Organization",
            "type":"Services"
        }
    ],
    "sg:phone":"+44 20 8742 3717",
    "sg:postcode":"W4 2RG",
    "sg:province":"Greater London",
    "sg:tags":[
        "equipment",
        "paging",
        "system"
    ],
    "wof:name":"Pagers Direct",
    "wof:placetype":"venue"
},
  "geometry": {"coordinates":[-0.25565,51.48222],"type":"Point"}
}