{
  "type": "Feature",
  "properties": {
    "iso:country":"GB",
    "sg:address":"25 Rankeillor St",
    "sg:city":"Edinburgh",
    "sg:classifiers":[
        {
            "category":"Building & Trades",
            "subcategory":"Plumbing",
            "type":"Services"
        }
    ],
    "sg:phone":"+44 131 657 2765",
    "sg:postcode":"EH8 9JA",
    "sg:province":"City of Edinburgh",
    "sg:tags":[
        "heating"
    ],
    "wof:name":"Holyrood Plumbers",
    "wof:placetype":"venue"
},
  "geometry": {"coordinates":[-3.1804740429,55.9425506592],"type":"Point"}
}