{
  "type": "Feature",
  "properties": {
    "iso:country":"GB",
    "sg:address":"1 Forest View, Barrowford",
    "sg:city":"Nelson",
    "sg:classifiers":[
        {
            "category":"Personal",
            "subcategory":"Beauty Salon",
            "type":"Services"
        },
        {
            "category":"Personal",
            "subcategory":"Barber",
            "type":"Services"
        }
    ],
    "sg:phone":"+44 1282 690416",
    "sg:postcode":"BB9 8PR",
    "sg:province":"Lancashire",
    "sg:tags":[
        "unisex",
        "hairdresser"
    ],
    "wof:name":"Angles Team for Hair",
    "wof:placetype":"venue"
},
  "geometry": {"coordinates":[-2.213340044,53.8359680176],"type":"Point"}
}