{
  "type": "Feature",
  "properties": {
    "iso:country":"GB",
    "sg:address":"23-26 Great Hollands Square",
    "sg:city":"Bracknell",
    "sg:classifiers":[
        {
            "category":"Professional",
            "subcategory":"Printing & Photocopies",
            "type":"Services"
        }
    ],
    "sg:phone":"+44 1344 422959",
    "sg:postcode":"RG12 9UR",
    "sg:province":"Berkshire",
    "sg:tags":[
        "print",
        "finisher"
    ],
    "wof:name":"Karran Products",
    "wof:placetype":"venue"
},
  "geometry": {"coordinates":[-0.771459,51.39864],"type":"Point"}
}