{
  "type": "Feature",
  "properties": {
    "addr:full":"Bridge Works Uxbridge Buckinghamshire UB8 2JG",
    "addr:postcode":"ub8 2jg",
    "iso:country":"GB",
    "sg:address":"Bridge Works",
    "sg:city":"Uxbridge",
    "sg:classifiers":[
        {
            "category":"Manufacturing",
            "subcategory":"Metals",
            "type":"Manufacturing & Wholesale Goods"
        }
    ],
    "sg:phone":"+44 1895 231880",
    "sg:postcode":"UB8 2JG",
    "sg:province":"Buckinghamshire",
    "sg:tags":[
        "work",
        "sheet"
    ],
    "wof:name":"L D J Sheet Metal Engineering",
    "wof:placetype":"venue"
},
  "geometry": {"coordinates":[-0.483157,51.53849],"type":"Point"}
}