{
  "type": "Feature",
  "properties": {
    "iso:country":"GB",
    "sg:address":"Greenside, 54 Old Bank Road",
    "sg:city":"Mirfield",
    "sg:classifiers":[
        {
            "category":"Food & Beverages",
            "subcategory":"Supermarket",
            "type":"Retail Goods"
        }
    ],
    "sg:phone":"+44 1924 493765",
    "sg:postcode":"WF14 0JA",
    "sg:province":"West Yorkshire",
    "wof:name":"Food Fair",
    "wof:placetype":"venue"
},
  "geometry": {"coordinates":[-1.6967099905,53.6749382019],"type":"Point"}
}