{
  "type": "Feature",
  "properties": {
    "addr:full":"1 Birmingham Road Cowes Isle of Wight PO31 7BH",
    "addr:housenumber":"1",
    "addr:postcode":"po31 7bh",
    "addr:street":"Birmingham Road",
    "iso:country":"GB",
    "sg:address":"1 Birmingham Road",
    "sg:city":"Cowes",
    "sg:classifiers":[
        {
            "category":"Shopping",
            "subcategory":"Pets & Pet Supplies",
            "type":"Retail Goods"
        }
    ],
    "sg:phone":"+44 1983 299971",
    "sg:postcode":"PO31 7BH",
    "sg:province":"Isle of Wight",
    "sg:tags":[
        "shop"
    ],
    "wof:name":"Diamond Pet Supplies",
    "wof:placetype":"venue"
},
  "geometry": {"coordinates":[-1.297286,50.760559],"type":"Point"}
}