{
  "type": "Feature",
  "properties": {
    "iso:country":"GB",
    "sg:address":"Columbia House, 88 Llandaff Road",
    "sg:city":"Cardiff",
    "sg:classifiers":[
        {
            "category":"Organizations",
            "subcategory":"Community Association",
            "type":"Services"
        },
        {
            "category":"Organizations",
            "subcategory":"Membership Organization",
            "type":"Services"
        }
    ],
    "sg:phone":"+44 29 2023 1207",
    "sg:postcode":"CF11 9NN",
    "sg:province":"Cardiff",
    "sg:tags":[
        "club",
        "social"
    ],
    "wof:name":"Columba Club",
    "wof:placetype":"venue"
},
  "geometry": {"coordinates":[-3.203786,51.484867],"type":"Point"}
}