{
  "type": "Feature",
  "properties": {
    "addr:full":"Jubilee Terrace, Findochty Buckie Moray AB56 4QA",
    "addr:postcode":"ab56 4qa",
    "addr:street":"Jubilee",
    "iso:country":"GB",
    "sg:address":"Jubilee Terrace, Findochty",
    "sg:city":"Buckie",
    "sg:classifiers":[
        {
            "category":"Government",
            "subcategory":"Office",
            "type":"Public Place"
        },
        {
            "category":"Recreation",
            "subcategory":"Campground",
            "type":"Entertainment"
        }
    ],
    "sg:phone":"+44 1542 835303",
    "sg:postcode":"AB56 4QA",
    "sg:province":"Moray",
    "sg:tags":[
        "park",
        "caravan",
        "local"
    ],
    "wof:name":"The Harbour Caravan Site",
    "wof:placetype":"venue"
},
  "geometry": {"coordinates":[-2.9002590179,57.6971931458],"type":"Point"}
}