{
  "type": "Feature",
  "properties": {
    "addr:full":"95 Station Road Ashington Northumberland NE63 8RS",
    "addr:housenumber":"95",
    "addr:postcode":"ne63 8rs",
    "addr:street":"Station Road;Northumberland",
    "iso:country":"GB",
    "sg:address":"95 Station Road",
    "sg:city":"Ashington",
    "sg:classifiers":[
        {
            "category":"Real Estate",
            "subcategory":"Real Estate Agent",
            "type":"Services"
        }
    ],
    "sg:phone":"+44 1670 852018",
    "sg:postcode":"NE63 8RS",
    "sg:province":"Northumberland",
    "wof:name":"Keith Pattinson Ltd.",
    "wof:placetype":"venue"
},
  "geometry": {"coordinates":[-1.576246,55.18351],"type":"Point"}
}