{
  "type": "Feature",
  "properties": {
    "iso:country":"GB",
    "sg:address":"631 London Rd",
    "sg:city":"Westcliff On Sea",
    "sg:classifiers":[
        {
            "category":"Military Area",
            "subcategory":"Air Force Base",
            "type":"Public Place"
        }
    ],
    "sg:phone":"+44 1702 392828",
    "sg:postcode":"SS0 9PE",
    "sg:province":"Essex",
    "sg:tags":[
        "water",
        "treatment"
    ],
    "wof:name":"Crouch Water Softener Services",
    "wof:placetype":"venue"
},
  "geometry": {"coordinates":[0.6843690276,51.5456542969],"type":"Point"}
}