{
  "type": "Feature",
  "properties": {
    "addr:full":"5 The Mound London Greater London SE9 3BA",
    "addr:housenumber":"5",
    "addr:postcode":"se9 3ba",
    "addr:street":"The Mound",
    "iso:country":"GB",
    "sg:address":"5 The Mound",
    "sg:city":"London",
    "sg:classifiers":[
        {
            "category":"Personal",
            "subcategory":"Beauty Salon",
            "type":"Services"
        },
        {
            "category":"Personal",
            "subcategory":"Barber",
            "type":"Services"
        }
    ],
    "sg:phone":"+44 20 8857 3155",
    "sg:postcode":"SE9 3BA",
    "sg:province":"Greater London",
    "sg:tags":[
        "unisex",
        "hairdresser"
    ],
    "wof:name":"Elegance Hair Stylist",
    "wof:placetype":"venue"
},
  "geometry": {"coordinates":[0.05653,51.429741],"type":"Point"}
}