{
  "type": "Feature",
  "properties": {
    "addr:full":"17d Featherstone Industrial Esta, Te Dominion Road Southall Greater London UB2 5DP",
    "addr:housenumber":"17d",
    "addr:postcode":"ub2 5dp",
    "addr:street":"Featherstone Industrial Esta Te Dominion Road",
    "iso:country":"GB",
    "sg:address":"17d Featherstone Industrial Esta, Te Dominion Road",
    "sg:city":"Southall",
    "sg:classifiers":[
        {
            "category":"Home & Garden",
            "subcategory":"Kitchen Supply",
            "type":"Retail Goods"
        }
    ],
    "sg:phone":"+44 20 8571 1878",
    "sg:postcode":"UB2 5DP",
    "sg:province":"Greater London",
    "sg:tags":[
        "measuring",
        "scale"
    ],
    "wof:name":"P J D Instruments Ltd.",
    "wof:placetype":"venue"
},
  "geometry": {"coordinates":[-0.3839699924,51.5030097961],"type":"Point"}
}