{
  "type": "Feature",
  "properties": {
    "addr:full":"Wellar Eggar Ho, High St Hook Berkshire RG27 8NY",
    "addr:postcode":"rg27 8ny",
    "addr:street":"High St",
    "iso:country":"GB",
    "sg:address":"Wellar Eggar Ho, High St",
    "sg:city":"Hook",
    "sg:classifiers":[
        {
            "category":"Professional",
            "subcategory":"Computer Services",
            "type":"Services"
        }
    ],
    "sg:phone":"+44 1252 844866",
    "sg:postcode":"RG27 8NY",
    "sg:province":"Berkshire",
    "sg:tags":[
        "consultant"
    ],
    "wof:name":"Application Systems",
    "wof:placetype":"venue"
},
  "geometry": {"coordinates":[-0.965719,51.281361],"type":"Point"}
}