{
  "type": "Feature",
  "properties": {
    "addr:full":"47 Cricklewood Broadway London Greater London NW2 3JX",
    "addr:housenumber":"47",
    "addr:postcode":"nw2 3jx",
    "addr:street":"Cricklewood Broadway",
    "iso:country":"GB",
    "sg:address":"47 Cricklewood Broadway",
    "sg:city":"London",
    "sg:classifiers":[
        {
            "category":"Restaurant",
            "type":"Food & Drink"
        }
    ],
    "sg:phone":"+44 20 8450 1116",
    "sg:postcode":"NW2 3JX",
    "sg:province":"Greater London",
    "sg:tags":[
        "indian",
        "-"
    ],
    "wof:name":"Crescent Tandoori Restaurant",
    "wof:placetype":"venue"
},
  "geometry": {"coordinates":[-0.211795,51.553387],"type":"Point"}
}