{
  "type": "Feature",
  "properties": {
    "iso:country":"GB",
    "sg:address":"89 London Rd, Oadby",
    "sg:city":"Leicester",
    "sg:classifiers":[
        {
            "category":"Shopping",
            "subcategory":"Department Store",
            "type":"Retail Goods"
        }
    ],
    "sg:postcode":"LE2 5DN",
    "sg:province":"Leicestershire",
    "wof:name":"Bates,Freddy,",
    "wof:placetype":"venue"
},
  "geometry": {"coordinates":[-1.0762879848,52.5969352722],"type":"Point"}
}