{
  "type": "Feature",
  "properties": {
    "iso:country":"GB",
    "sg:address":"Haydock Lane, Haydock Industrial Estate",
    "sg:city":"St Helens",
    "sg:classifiers":[
        {
            "category":"Manufacturing",
            "subcategory":"Wood Products",
            "type":"Manufacturing & Wholesale Goods"
        }
    ],
    "sg:phone":"+44 1942 295517",
    "sg:postcode":"WA11 9TY",
    "sg:province":"Lancashire",
    "sg:tags":[
        "encapsulation",
        "lamination"
    ],
    "wof:name":"Thermal Laminates Ltd.",
    "wof:placetype":"venue"
},
  "geometry": {"coordinates":[-2.670074,53.473404],"type":"Point"}
}