{
  "type": "Feature",
  "properties": {
    "addr:full":"25 Woodspring Avenue, Worlebury Weston-super-mare Somerset BS22 9RU",
    "addr:housenumber":"25",
    "addr:postcode":"bs22 9ru",
    "addr:street":"Woodspring Avenue Worlebury",
    "iso:country":"GB",
    "sg:address":"25 Woodspring Avenue, Worlebury",
    "sg:city":"Weston-super-mare",
    "sg:classifiers":[
        {
            "category":"Building & Trades",
            "subcategory":"Plumbing",
            "type":"Services"
        }
    ],
    "sg:postcode":"BS22 9RU",
    "sg:province":"Somerset",
    "sg:tags":[
        "drain",
        "clearance",
        "sewer"
    ],
    "wof:name":"Aqua Jet",
    "wof:placetype":"venue"
},
  "geometry": {"coordinates":[-2.956894,51.362976],"type":"Point"}
}