{
  "type": "Feature",
  "properties": {
    "iso:country":"GB",
    "sg:address":"122c Nelson Rd, Whitton",
    "sg:city":"Twickenham",
    "sg:classifiers":[
        {
            "category":"Professional",
            "subcategory":"Lawyer & Legal Services",
            "type":"Services"
        }
    ],
    "sg:phone":"+44 20 8893 4266",
    "sg:postcode":"TW2 7AY",
    "sg:province":"Greater London",
    "sg:tags":[
        "conveyancing"
    ],
    "wof:name":"Raven-Hill,Paul Ingram,",
    "wof:placetype":"venue"
},
  "geometry": {"coordinates":[-0.356633,51.453583],"type":"Point"}
}