{
  "type": "Feature",
  "properties": {
    "addr:full":"Torrs Park Ilfracombe Devon EX34 8AZ",
    "addr:postcode":"ex34 8az",
    "iso:country":"GB",
    "sg:address":"Torrs Park",
    "sg:city":"Ilfracombe",
    "sg:classifiers":[
        {
            "category":"Social Services",
            "subcategory":"Retirement Home",
            "type":"Services"
        }
    ],
    "sg:phone":"+44 1271 863012",
    "sg:postcode":"EX34 8AZ",
    "sg:province":"Devon",
    "sg:tags":[
        "residential",
        "care"
    ],
    "wof:name":"Torrsvale Private Home for the Elderly",
    "wof:placetype":"venue"
},
  "geometry": {"coordinates":[-4.1280422211,51.2085876465],"type":"Point"}
}