{
  "type": "Feature",
  "properties": {
    "addr:full":"Victoria Park Post Office, 408 Cowbridge Road East Cardiff Cardiff CF5 1JJ",
    "addr:housenumber":"408",
    "addr:postcode":"cf5 1jj",
    "addr:street":"Cowbridge Road East",
    "iso:country":"GB",
    "sg:address":"Victoria Park Post Office, 408 Cowbridge Road East",
    "sg:city":"Cardiff",
    "sg:classifiers":[
        {
            "category":"Government",
            "subcategory":"Post Office",
            "type":"Public Place"
        }
    ],
    "sg:phone":"+44 29 2022 6986",
    "sg:postcode":"CF5 1JJ",
    "sg:province":"Cardiff",
    "wof:name":"Victoria Park Post Office",
    "wof:placetype":"venue"
},
  "geometry": {"coordinates":[-3.2153570652,51.4827575684],"type":"Point"}
}