{
  "type": "Feature",
  "properties": {
    "iso:country":"GB",
    "sg:address":"272 Huddersfield Road",
    "sg:city":"Liversedge",
    "sg:classifiers":[
        {
            "category":"Sports & Exercise",
            "subcategory":"Playing Field",
            "type":"Entertainment"
        }
    ],
    "sg:phone":"+44 1924 404333",
    "sg:postcode":"WF15 7QQ",
    "sg:province":"West Yorkshire",
    "sg:tags":[
        "sanitary",
        "hygiene",
        "appliance"
    ],
    "wof:name":"Splashin' Out",
    "wof:placetype":"venue"
},
  "geometry": {"coordinates":[-1.698902,53.696903],"type":"Point"}
}