{
  "type": "Feature",
  "properties": {
    "addr:full":"Chapel Farm, Chapel Lane Cranbrook Kent TN17 2JN",
    "addr:postcode":"tn17 2jn",
    "addr:street":"Chapel Lane",
    "iso:country":"GB",
    "sg:address":"Chapel Farm, Chapel Lane",
    "sg:city":"Cranbrook",
    "sg:classifiers":[
        {
            "category":"Home & Garden",
            "subcategory":"Garden Supply",
            "type":"Retail Goods"
        }
    ],
    "sg:phone":"+44 1580 714377",
    "sg:postcode":"TN17 2JN",
    "sg:province":"Kent",
    "sg:tags":[
        "turfing"
    ],
    "wof:name":"Wrights (Cranbrook)",
    "wof:placetype":"venue"
},
  "geometry": {"coordinates":[0.5654029846,51.1067237854],"type":"Point"}
}