{
  "type": "Feature",
  "properties": {
    "iso:country":"GB",
    "sg:address":"104 High Street",
    "sg:city":"Crediton",
    "sg:classifiers":[
        {
            "category":"Food & Beverages",
            "subcategory":"Meat & Fish",
            "type":"Retail Goods"
        },
        {
            "category":"Food & Beverages",
            "subcategory":"Groceries & Convenience Stores",
            "type":"Retail Goods"
        }
    ],
    "sg:phone":"+44 1363 772898",
    "sg:postcode":"EX17 3LF",
    "sg:province":"Devon",
    "sg:tags":[
        "shop",
        "chip"
    ],
    "wof:name":"Chefs Choice",
    "wof:placetype":"venue"
},
  "geometry": {"coordinates":[-3.661376,50.79097],"type":"Point"}
}