{
  "type": "Feature",
  "properties": {
    "iso:country":"GB",
    "sg:address":"Parsonage Farm, Hatham Green Lane, Stansted",
    "sg:city":"Sevenoaks",
    "sg:classifiers":[
        {
            "category":"Wholesale",
            "subcategory":"Construction Materials",
            "type":"Manufacturing & Wholesale Goods"
        }
    ],
    "sg:phone":"+44 1474 853669",
    "sg:postcode":"TN15 7PL",
    "sg:province":"Kent",
    "sg:tags":[
        "merchant",
        "stone"
    ],
    "wof:name":"Traditional Stone & Brick Co.",
    "wof:placetype":"venue"
},
  "geometry": {"coordinates":[0.3061470091,51.3359107971],"type":"Point"}
}