{
  "type": "Feature",
  "properties": {
    "iso:country":"GB",
    "sg:address":"Halfpenny Grn Airport",
    "sg:city":"Stourbridge",
    "sg:classifiers":[
        {
            "category":"Retail",
            "subcategory":"Auto Repair",
            "type":"Services"
        }
    ],
    "sg:postcode":"DY7 5DY",
    "sg:province":"Shropshire",
    "sg:tags":[
        "modification",
        "garage"
    ],
    "wof:name":"D J Motors",
    "wof:placetype":"venue"
},
  "geometry": {"coordinates":[-2.26312,52.51429],"type":"Point"}
}