{
  "type": "Feature",
  "properties": {
    "addr:full":"200 High Street, Worle Weston Super Mare Somerset BS22 6JD",
    "addr:housenumber":"200",
    "addr:postcode":"bs22 6jd",
    "addr:street":"High Street",
    "iso:country":"GB",
    "sg:address":"200 High Street, Worle",
    "sg:city":"Weston Super Mare",
    "sg:classifiers":[
        {
            "category":"Real Estate",
            "subcategory":"Real Estate Agent",
            "type":"Services"
        }
    ],
    "sg:phone":"+44 1934 521111",
    "sg:postcode":"BS22 6JD",
    "sg:province":"Somerset",
    "wof:name":"Garner Lamb",
    "wof:placetype":"venue"
},
  "geometry": {"coordinates":[-2.926634,51.360378],"type":"Point"}
}