{
  "type": "Feature",
  "properties": {
    "addr:full":"98 Renfrew Rd Ipswich Suffolk IP4 3HJ",
    "addr:housenumber":"98",
    "addr:postcode":"ip4 3hj",
    "addr:street":"Renfrew Rd",
    "iso:country":"GB",
    "sg:address":"98 Renfrew Rd",
    "sg:city":"Ipswich",
    "sg:classifiers":[
        {
            "category":"Wholesale",
            "subcategory":"Meat",
            "type":"Manufacturing & Wholesale Goods"
        }
    ],
    "sg:postcode":"IP4 3HJ",
    "sg:province":"Suffolk",
    "sg:tags":[
        "-"
    ],
    "wof:name":"Dellabella,Salvartore,",
    "wof:placetype":"venue"
},
  "geometry": {"coordinates":[1.190477,52.071011],"type":"Point"}
}