{
  "type": "Feature",
  "properties": {
    "iso:country":"GB",
    "sg:address":"Cavendish Lodge",
    "sg:city":"Mansfield",
    "sg:classifiers":[
        {
            "category":"Farming",
            "subcategory":"Livestock Farm",
            "type":"Manufacturing & Wholesale Goods"
        }
    ],
    "sg:phone":"+44 7767 690214",
    "sg:postcode":"NG21 9BS",
    "sg:province":"Nottinghamshire",
    "sg:tags":[
        "others"
    ],
    "wof:name":"Clipston Park Farms",
    "wof:placetype":"venue"
},
  "geometry": {"coordinates":[-1.113173008,53.1703300476],"type":"Point"}
}