{
  "type": "Feature",
  "properties": {
    "iso:country":"GB",
    "sg:address":"Aci House, Torrington Park",
    "sg:city":"London",
    "sg:classifiers":[
        {
            "category":"Personal",
            "subcategory":"Beauty Salon",
            "type":"Services"
        }
    ],
    "sg:postcode":"N12 9SZ",
    "sg:province":"Greater London",
    "sg:tags":[
        "unisex",
        "hairdresser"
    ],
    "wof:name":"Wisematch Ltd.",
    "wof:placetype":"venue"
},
  "geometry": {"coordinates":[-0.1649290025,51.617401123],"type":"Point"}
}