{
  "type": "Feature",
  "properties": {
    "iso:country":"GB",
    "sg:address":"The Street, Holt Road, Upper Sheringham",
    "sg:city":"Sheringham",
    "sg:classifiers":[
        {
            "category":"Government",
            "subcategory":"Post Office",
            "type":"Public Place"
        }
    ],
    "sg:postcode":"NR26 8AD",
    "sg:province":"Norfolk",
    "wof:name":"Upper Sheringham Post Office",
    "wof:placetype":"venue"
},
  "geometry": {"coordinates":[1.1901350021,52.9315643311],"type":"Point"}
}