{
  "type": "Feature",
  "properties": {
    "iso:country":"GB",
    "sg:address":"Link House, 8 Batholemews Walk",
    "sg:city":"Ely",
    "sg:classifiers":[
        {
            "category":"Professional",
            "subcategory":"Advertising",
            "type":"Services"
        }
    ],
    "sg:phone":"+44 1353 665544",
    "sg:postcode":"CB7 4ZD",
    "sg:province":"Cambridgeshire",
    "sg:tags":[
        "mail",
        "direct"
    ],
    "wof:name":"Wyvern Business Library",
    "wof:placetype":"venue"
},
  "geometry": {"coordinates":[0.26231,52.389927],"type":"Point"}
}