{
  "type": "Feature",
  "properties": {
    "addr:full":"14 College Walk Rotherham South Yorkshire S60 1QB",
    "addr:housenumber":"14",
    "addr:postcode":"s60 1qb",
    "addr:street":"College Walk",
    "iso:country":"GB",
    "sg:address":"14 College Walk",
    "sg:city":"Rotherham",
    "sg:classifiers":[
        {
            "category":"Shopping",
            "subcategory":"Clothing, Apparel, & Fashions",
            "type":"Retail Goods"
        }
    ],
    "sg:phone":"+44 1709 720982",
    "sg:postcode":"S60 1QB",
    "sg:province":"South Yorkshire",
    "sg:tags":[
        "accessory"
    ],
    "wof:name":"Claire's Accessories (Uk)",
    "wof:placetype":"venue"
},
  "geometry": {"coordinates":[-1.3665390015,53.4315910339],"type":"Point"}
}