{
  "type": "Feature",
  "properties": {
    "addr:full":"Lanark Grammer School, Albany Drive Lanark South Lanarkshire ML11 9AQ",
    "addr:postcode":"ml11 9aq",
    "addr:street":"Albany Drive",
    "iso:country":"GB",
    "sg:address":"Lanark Grammer School, Albany Drive",
    "sg:city":"Lanark",
    "sg:classifiers":[
        {
            "category":"Government",
            "subcategory":"Office",
            "type":"Public Place"
        }
    ],
    "sg:phone":"+44 1555 662248",
    "sg:postcode":"ML11 9AQ",
    "sg:province":"South Lanarkshire",
    "sg:tags":[
        "local"
    ],
    "wof:name":"County Careers Office",
    "wof:placetype":"venue"
},
  "geometry": {"coordinates":[-3.7813839912,55.673866272],"type":"Point"}
}