{
  "type": "Feature",
  "properties": {
    "addr:full":"Unit 5, Zone C, Chelmsford Road Indstl Est Dunmow Essex CM6 1HD",
    "addr:housenumber":"unit 5",
    "addr:postcode":"cm6 1hd",
    "addr:street":"Zone C Chelmsford Road Indstl Est",
    "iso:country":"GB",
    "sg:address":"Unit 5, Zone C, Chelmsford Road Indstl Est",
    "sg:city":"Dunmow",
    "sg:classifiers":[
        {
            "category":"Home & Garden",
            "subcategory":"Hardware",
            "type":"Retail Goods"
        }
    ],
    "sg:postcode":"CM6 1HD",
    "sg:province":"Essex",
    "sg:tags":[
        "paint",
        "coating"
    ],
    "wof:name":"R & A Coating Ltd",
    "wof:placetype":"venue"
},
  "geometry": {"coordinates":[0.3649770021,51.8706130981],"type":"Point"}
}