{
  "type": "Feature",
  "properties": {
    "addr:full":"85 Lowther Road Bournemouth Dorset BH8 8NP",
    "addr:housenumber":"85",
    "addr:postcode":"bh8 8np",
    "addr:street":"Lowther Road",
    "iso:country":"GB",
    "sg:address":"85 Lowther Road",
    "sg:city":"Bournemouth",
    "sg:classifiers":[
        {
            "category":"Communications",
            "type":"Services"
        }
    ],
    "sg:phone":"+44 1202 298642",
    "sg:postcode":"BH8 8NP",
    "sg:province":"Dorset",
    "sg:tags":[
        "audio-visual"
    ],
    "wof:name":"Enterprise Video Services",
    "wof:placetype":"venue"
},
  "geometry": {"coordinates":[-1.8639370203,50.7325363159],"type":"Point"}
}