{
  "type": "Feature",
  "properties": {
    "addr:full":"Sheffield Road, Hoyland Common Barnsley South Yorkshire S74 0DP",
    "addr:postcode":"s74 0dp",
    "addr:street":"Sheffield Road;Yorkshire",
    "iso:country":"GB",
    "sg:address":"Sheffield Road, Hoyland Common",
    "sg:city":"Barnsley",
    "sg:classifiers":[
        {
            "category":"Autos & Motor Vehicles",
            "subcategory":"Auto Supplies",
            "type":"Retail Goods"
        }
    ],
    "sg:phone":"+44 1226 360000",
    "sg:postcode":"S74 0DP",
    "sg:province":"South Yorkshire",
    "sg:tags":[
        "exhaust",
        "absorber",
        "shock",
        "tyre"
    ],
    "wof:name":"Challenger Tyres & Exhausts (Sf) Co",
    "wof:placetype":"venue"
},
  "geometry": {"coordinates":[-1.4686390162,53.4985618591],"type":"Point"}
}