{
  "type": "Feature",
  "properties": {
    "addr:full":"37 Chequer Street St Albans Hertfordshire AL1 3YJ",
    "addr:housenumber":"37",
    "addr:postcode":"al1 3yj",
    "addr:street":"Chequer Street",
    "iso:country":"GB",
    "sg:address":"37 Chequer Street",
    "sg:city":"St Albans",
    "sg:classifiers":[
        {
            "category":"Professional",
            "subcategory":"Employment Agencies",
            "type":"Services"
        }
    ],
    "sg:phone":"+44 1727 847722",
    "sg:postcode":"AL1 3YJ",
    "sg:province":"Hertfordshire",
    "sg:tags":[
        "consultant"
    ],
    "wof:name":"Adecco Alfred Marks",
    "wof:placetype":"venue"
},
  "geometry": {"coordinates":[-0.3389579952,51.7519760132],"type":"Point"}
}