{
  "type": "Feature",
  "properties": {
    "addr:full":"Green Hedges Bungalow, Pontadawe Road Neath Neath Port Talbot SA10 7YL",
    "addr:postcode":"sa10 7yl",
    "addr:street":"Pontadawe Road",
    "iso:country":"GB",
    "sg:address":"Green Hedges Bungalow, Pontadawe Road",
    "sg:city":"Neath",
    "sg:classifiers":[
        {
            "category":"Professional",
            "subcategory":"Computer Services",
            "type":"Services"
        }
    ],
    "sg:phone":"+44 1639 633072",
    "sg:postcode":"SA10 7YL",
    "sg:province":"Neath Port Talbot",
    "sg:tags":[
        "system",
        "software"
    ],
    "wof:name":"Trantor Ltd.",
    "wof:placetype":"venue"
},
  "geometry": {"coordinates":[-3.8277549744,51.6670799255],"type":"Point"}
}