{
  "type": "Feature",
  "properties": {
    "iso:country":"GB",
    "sg:address":"Horne Road",
    "sg:city":"Ilfracombe",
    "sg:classifiers":[
        {
            "category":"Real Estate",
            "subcategory":"Real Estate Agent",
            "type":"Services"
        },
        {
            "category":"Social Services",
            "subcategory":"Adult Care",
            "type":"Services"
        },
        {
            "category":"Government",
            "subcategory":"Office",
            "type":"Public Place"
        }
    ],
    "sg:phone":"+44 1271 865370",
    "sg:postcode":"EX34 8HH",
    "sg:province":"Devon",
    "sg:tags":[
        "housing",
        "local",
        "sheltered"
    ],
    "wof:name":"Wilder Park",
    "wof:placetype":"venue"
},
  "geometry": {"coordinates":[-4.124352,51.204311],"type":"Point"}
}