{
  "type": "Feature",
  "properties": {
    "addr:full":"3 Clarence Road East Cowes Isle of Wight PO32 6EP",
    "addr:housenumber":"3",
    "addr:postcode":"po32 6ep",
    "addr:street":"Clarence Road",
    "iso:country":"GB",
    "sg:address":"3 Clarence Road",
    "sg:city":"East Cowes",
    "sg:classifiers":[
        {
            "category":"Home & Garden",
            "subcategory":"Household Appliances",
            "type":"Retail Goods"
        },
        {
            "category":"Retail",
            "subcategory":"Event Space",
            "type":"Services"
        }
    ],
    "sg:phone":"+44 1983 293291",
    "sg:postcode":"PO32 6EP",
    "sg:province":"Isle of Wight",
    "sg:tags":[
        "electrical",
        "product",
        "domestic",
        "sales"
    ],
    "wof:name":"Bruce's",
    "wof:placetype":"venue"
},
  "geometry": {"coordinates":[-1.288057,50.757439],"type":"Point"}
}