{
  "type": "Feature",
  "properties": {
    "addr:full":"206-214 Promenade Blackpool Lancashire FY1 1RU",
    "addr:housenumber":"206-214",
    "addr:postcode":"fy1 1ru",
    "addr:street":"Promenade",
    "iso:country":"GB",
    "sg:address":"206-214 Promenade",
    "sg:city":"Blackpool",
    "sg:classifiers":[
        {
            "category":"Travel",
            "subcategory":"Hotels & Motels",
            "type":"Entertainment"
        }
    ],
    "sg:phone":"+44 1253 625688",
    "sg:postcode":"FY1 1RU",
    "sg:province":"Lancashire",
    "wof:name":"Stretton Hotel",
    "wof:placetype":"venue"
},
  "geometry": {"coordinates":[-3.054892,53.821541],"type":"Point"}
}