{
  "type": "Feature",
  "properties": {
    "addr:full":"29 Elm Street Ipswich Suffolk IP1 2AB",
    "addr:housenumber":"29",
    "addr:postcode":"ip1 2ab",
    "addr:street":"Elm Street",
    "iso:country":"GB",
    "sg:address":"29 Elm Street",
    "sg:city":"Ipswich",
    "sg:classifiers":[
        {
            "category":"Real Estate",
            "subcategory":"Surveying",
            "type":"Services"
        }
    ],
    "sg:phone":"+44 1473 216176",
    "sg:postcode":"IP1 2AB",
    "sg:province":"Suffolk",
    "sg:tags":[
        "building",
        "surveyor",
        "valuer"
    ],
    "wof:name":"Allied Surveyors plc",
    "wof:placetype":"venue"
},
  "geometry": {"coordinates":[1.150241971,52.05676651],"type":"Point"}
}