{
  "type": "Feature",
  "properties": {
    "iso:country":"GB",
    "sg:address":"84-88 High Street",
    "sg:city":"Winsford",
    "sg:classifiers":[
        {
            "category":"Shopping",
            "subcategory":"Used Merchandise",
            "type":"Retail Goods"
        }
    ],
    "sg:postcode":"CW7 2AP",
    "sg:province":"Cheshire",
    "sg:tags":[
        "shop",
        "second-hand"
    ],
    "wof:name":"Pat's Winsford Secondhand Centre",
    "wof:placetype":"venue"
},
  "geometry": {"coordinates":[-2.522268,53.192726],"type":"Point"}
}