{
  "type": "Feature",
  "properties": {
    "addr:full":"16 Smith St Dalry North Ayrshire KA24 5BZ",
    "addr:housenumber":"16",
    "addr:postcode":"ka24 5bz",
    "addr:street":"Smith St",
    "iso:country":"GB",
    "sg:address":"16 Smith St",
    "sg:city":"Dalry",
    "sg:classifiers":[
        {
            "category":"Building & Trades",
            "subcategory":"Construction",
            "type":"Services"
        }
    ],
    "sg:postcode":"KA24 5BZ",
    "sg:province":"North Ayrshire",
    "sg:tags":[
        "joiner",
        "carpenter"
    ],
    "wof:name":"Smith,Thomas,(Remedial) Ltd",
    "wof:placetype":"venue"
},
  "geometry": {"coordinates":[-4.717294,55.708691],"type":"Point"}
}