{
  "type": "Feature",
  "properties": {
    "addr:full":"Chesterfield Road Chesterfield Derbyshire S44 5HT",
    "addr:postcode":"s44 5ht",
    "addr:street":"Chesterfield Road",
    "iso:country":"GB",
    "sg:address":"Chesterfield Road",
    "sg:city":"Chesterfield",
    "sg:classifiers":[
        {
            "category":"Farming",
            "subcategory":"Livestock Farm",
            "type":"Manufacturing & Wholesale Goods"
        }
    ],
    "sg:postcode":"S44 5HT",
    "sg:province":"Derbyshire",
    "sg:tags":[
        "others"
    ],
    "wof:name":"Frank Elliott",
    "wof:placetype":"venue"
},
  "geometry": {"coordinates":[-1.3587440252,53.2332344055],"type":"Point"}
}