{
  "type": "Feature",
  "properties": {
    "iso:country":"GB",
    "sg:address":"21 Dean Lane, Sixpenny Handley",
    "sg:city":"Salisbury",
    "sg:classifiers":[
        {
            "category":"Shopping",
            "subcategory":"Computers & Home Electronics",
            "type":"Retail Goods"
        }
    ],
    "sg:phone":"+44 1722 322862",
    "sg:postcode":"SP5 5PA",
    "sg:province":"Dorset",
    "sg:tags":[
        "aerial",
        "television",
        "radio"
    ],
    "wof:name":"Airwaves",
    "wof:placetype":"venue"
},
  "geometry": {"coordinates":[-1.9991250038,50.9562263489],"type":"Point"}
}