{
  "type": "Feature",
  "properties": {
    "addr:full":"39 Church Street, Farnworth Bolton Lancashire BL4 8AQ",
    "addr:housenumber":"39",
    "addr:postcode":"bl4 8aq",
    "addr:street":"Church Street",
    "iso:country":"GB",
    "sg:address":"39 Church Street, Farnworth",
    "sg:city":"Bolton",
    "sg:classifiers":[
        {
            "category":"Shopping",
            "subcategory":"Clothing, Apparel, & Fashions",
            "type":"Retail Goods"
        }
    ],
    "sg:phone":"+44 1204 576444",
    "sg:postcode":"BL4 8AQ",
    "sg:province":"Lancashire",
    "sg:tags":[
        "sportswear"
    ],
    "wof:name":"D & W Sports",
    "wof:placetype":"venue"
},
  "geometry": {"coordinates":[-2.3899950981,53.5488471985],"type":"Point"}
}