{
  "type": "Feature",
  "properties": {
    "addr:full":"4 White Lodge St Albans Hertfordshire AL1 1JQ",
    "addr:housenumber":"4",
    "addr:postcode":"al1 1jq",
    "addr:street":"White Lodge",
    "iso:country":"GB",
    "sg:address":"4 White Lodge",
    "sg:city":"St Albans",
    "sg:classifiers":[
        {
            "category":"Professional",
            "subcategory":"Lawyer & Legal Services",
            "type":"Services"
        }
    ],
    "sg:phone":"+44 20 8950 0791",
    "sg:postcode":"AL1 1JQ",
    "sg:province":"Hertfordshire",
    "sg:tags":[
        "conveyancing"
    ],
    "wof:name":"Property Package Deal Services Ltd.",
    "wof:placetype":"venue"
},
  "geometry": {"coordinates":[-0.3226099908,51.7426795959],"type":"Point"}
}