{
  "type": "Feature",
  "properties": {
    "iso:country":"GB",
    "sg:address":"167 Liverpool Road, Hutton",
    "sg:city":"Preston",
    "sg:classifiers":[
        {
            "category":"Shopping",
            "subcategory":"Department Store",
            "type":"Retail Goods"
        },
        {
            "category":"Food & Beverages",
            "subcategory":"Supermarket",
            "type":"Retail Goods"
        }
    ],
    "sg:phone":"+44 1772 613701",
    "sg:postcode":"PR4 5FE",
    "sg:province":"Lancashire",
    "wof:name":"Village Store",
    "wof:placetype":"venue"
},
  "geometry": {"coordinates":[-2.768295,53.732021],"type":"Point"}
}