{
  "type": "Feature",
  "properties": {
    "addr:full":"East Rainton Primary School Kitc Houghton-le-spring Durham DH5 9RA",
    "addr:postcode":"dh5 9ra",
    "addr:street":"East;Kitc",
    "iso:country":"GB",
    "sg:address":"East Rainton Primary School Kitc",
    "sg:city":"Houghton-le-spring",
    "sg:classifiers":[
        {
            "category":"Education",
            "subcategory":"School",
            "type":"Public Place"
        }
    ],
    "sg:phone":"+44 191 553 6570",
    "sg:postcode":"DH5 9RA",
    "sg:province":"Durham",
    "sg:tags":[
        "catering"
    ],
    "wof:name":"Sunderland City Council",
    "wof:placetype":"venue"
},
  "geometry": {"coordinates":[-1.4821610451,54.8244476318],"type":"Point"}
}