{
  "type": "Feature",
  "properties": {
    "addr:full":"16a Duke Street St Austell Cornwall PL25 5PQ",
    "addr:housenumber":"16a",
    "addr:postcode":"pl25 5pq",
    "addr:street":"Duke Street",
    "iso:country":"GB",
    "sg:address":"16a Duke Street",
    "sg:city":"St Austell",
    "sg:classifiers":[
        {
            "category":"Organizations",
            "subcategory":"Membership Organization",
            "type":"Services"
        }
    ],
    "sg:postcode":"PL25 5PQ",
    "sg:province":"Cornwall",
    "sg:tags":[
        "club"
    ],
    "wof:name":"Royal British Legion St. Austell Club Ltd.",
    "wof:placetype":"venue"
},
  "geometry": {"coordinates":[-4.792645,50.337845],"type":"Point"}
}