{
  "type": "Feature",
  "properties": {
    "addr:full":"Eastwood Street Bradford West Yorkshire BD4 7DE",
    "addr:postcode":"bd4 7de",
    "addr:street":"Eastwood Street",
    "iso:country":"GB",
    "sg:address":"Eastwood Street",
    "sg:city":"Bradford",
    "sg:classifiers":[
        {
            "category":"Professional",
            "subcategory":"Printing & Photocopies",
            "type":"Services"
        }
    ],
    "sg:phone":"+44 1274 722466",
    "sg:postcode":"BD4 7DE",
    "sg:province":"West Yorkshire",
    "sg:tags":[
        "process",
        "screen",
        "printer"
    ],
    "wof:name":"Grenard Silkscreen",
    "wof:placetype":"venue"
},
  "geometry": {"coordinates":[-1.7437640429,53.786113739],"type":"Point"}
}