{
  "type": "Feature",
  "properties": {
    "addr:full":"Canterbury Road Birchington Kent CT7 9BL",
    "addr:postcode":"ct7 9bl",
    "addr:street":"Canterbury Road",
    "iso:country":"GB",
    "sg:address":"Canterbury Road",
    "sg:city":"Birchington",
    "sg:classifiers":[
        {
            "category":"Education",
            "subcategory":"School",
            "type":"Public Place"
        }
    ],
    "sg:phone":"+44 1843 831999",
    "sg:postcode":"CT7 9BL",
    "sg:province":"Kent",
    "sg:tags":[
        "local",
        "authority"
    ],
    "wof:name":"King Ethelbert School",
    "wof:placetype":"venue"
},
  "geometry": {"coordinates":[1.3089419603,51.3740158081],"type":"Point"}
}