{
  "type": "Feature",
  "properties": {
    "iso:country":"GB",
    "sg:address":"Manor Farm Court, Lower Sundon",
    "sg:city":"Luton",
    "sg:classifiers":[
        {
            "category":"Building & Trades",
            "subcategory":"Construction",
            "type":"Services"
        }
    ],
    "sg:phone":"+44 1525 872014",
    "sg:postcode":"LU3 3PA",
    "sg:province":"Bedfordshire",
    "sg:tags":[
        "builder"
    ],
    "wof:name":"Connolly Homes Plc",
    "wof:placetype":"venue"
},
  "geometry": {"coordinates":[-0.4745849967,51.9314918518],"type":"Point"}
}