{
  "type": "Feature",
  "properties": {
    "addr:full":"381 Manchester Road, Paddington Warrington Cheshire WA1 3LS",
    "addr:housenumber":"381",
    "addr:postcode":"wa1 3ls",
    "addr:street":"Manchester Road",
    "iso:country":"GB",
    "sg:address":"381 Manchester Road, Paddington",
    "sg:city":"Warrington",
    "sg:classifiers":[
        {
            "category":"Building & Trades",
            "subcategory":"Construction",
            "type":"Services"
        }
    ],
    "sg:phone":"+44 1925 815721",
    "sg:postcode":"WA1 3LS",
    "sg:province":"Cheshire",
    "sg:tags":[
        "builder"
    ],
    "wof:name":"S D Holbrook Building Services",
    "wof:placetype":"venue"
},
  "geometry": {"coordinates":[-2.560533,53.397633],"type":"Point"}
}