{
  "type": "Feature",
  "properties": {
    "iso:country":"GB",
    "sg:address":"6 Sunningdale Gardens",
    "sg:city":"Carlisle",
    "sg:classifiers":[
        {
            "category":"Manufacturing",
            "subcategory":"Signs",
            "type":"Manufacturing & Wholesale Goods"
        }
    ],
    "sg:postcode":"CA3 9QN",
    "sg:province":"Cumbria",
    "sg:tags":[
        "writer"
    ],
    "wof:name":"Halliday Davina G Traditional Sign Writer",
    "wof:placetype":"venue"
},
  "geometry": {"coordinates":[-2.9551548958,54.907283783],"type":"Point"}
}