{
  "type": "Feature",
  "properties": {
    "addr:full":"38 Temple Crescent Inverness Highland IV2 4TW",
    "addr:housenumber":"38",
    "addr:postcode":"iv2 4tw",
    "addr:street":"Temple Crescent",
    "iso:country":"GB",
    "sg:address":"38 Temple Crescent",
    "sg:city":"Inverness",
    "sg:classifiers":[
        {
            "category":"Building & Trades",
            "subcategory":"Construction",
            "type":"Services"
        }
    ],
    "sg:phone":"+44 1463 240676",
    "sg:postcode":"IV2 4TW",
    "sg:province":"Highland",
    "sg:tags":[
        "roofing",
        "contracting"
    ],
    "wof:name":"W J & M E Cowan",
    "wof:placetype":"venue"
},
  "geometry": {"coordinates":[-4.2119112015,57.4644241333],"type":"Point"}
}