{
  "type": "Feature",
  "properties": {
    "addr:full":"49 Dulverton Drive, Furzton Milton Keynes Buckinghamshire MK4 1EN",
    "addr:housenumber":"49",
    "addr:postcode":"mk4 1en",
    "addr:street":"Dulverton Drive",
    "iso:country":"GB",
    "sg:address":"49 Dulverton Drive, Furzton",
    "sg:city":"Milton Keynes",
    "sg:classifiers":[
        {
            "category":"Personal",
            "subcategory":"Beauty Salon",
            "type":"Services"
        }
    ],
    "sg:phone":"+44 1908 501712",
    "sg:postcode":"MK4 1EN",
    "sg:province":"Buckinghamshire",
    "sg:tags":[
        "unisex",
        "hairdresser"
    ],
    "wof:name":"Barringtons",
    "wof:placetype":"venue"
},
  "geometry": {"coordinates":[-0.771753,52.008751],"type":"Point"}
}