{
  "type": "Feature",
  "properties": {
    "addr:full":"46 Boundary Road Newark Nottinghamshire NG24 4AL",
    "addr:housenumber":"46",
    "addr:postcode":"ng24 4al",
    "addr:street":"Boundary Road",
    "iso:country":"GB",
    "sg:address":"46 Boundary Road",
    "sg:city":"Newark",
    "sg:classifiers":[
        {
            "category":"Professional",
            "subcategory":"Engineering",
            "type":"Services"
        }
    ],
    "sg:phone":"+44 1636 701731",
    "sg:postcode":"NG24 4AL",
    "sg:province":"Nottinghamshire",
    "sg:tags":[
        "contractor",
        "electrical",
        "engineer"
    ],
    "wof:name":"Trent Electrical Services",
    "wof:placetype":"venue"
},
  "geometry": {"coordinates":[-0.8112099767,53.0690956116],"type":"Point"}
}