{
  "type": "Feature",
  "properties": {
    "iso:country":"GB",
    "sg:address":"Hamilton St",
    "sg:city":"Fishguard",
    "sg:classifiers":[
        {
            "category":"Bars & Pubs",
            "type":"Food & Drink"
        }
    ],
    "sg:phone":"+44 1348 873848",
    "sg:postcode":"SA65 9HL",
    "sg:province":"Pembrokeshire",
    "sg:tags":[
        "pubs",
        "inn"
    ],
    "wof:name":"Cambrian Inn",
    "wof:placetype":"venue"
},
  "geometry": {"coordinates":[-4.9747290611,51.9936752319],"type":"Point"}
}