{
  "type": "Feature",
  "properties": {
    "iso:country":"GB",
    "sg:address":"97 Acton Lane",
    "sg:city":"London",
    "sg:classifiers":[
        {
            "category":"Communications",
            "subcategory":"Newspaper",
            "type":"Services"
        }
    ],
    "sg:postcode":"NW10 8UT",
    "sg:province":"Greater London",
    "sg:tags":[
        "magazine"
    ],
    "wof:name":"Sheps Enterprise Ltd",
    "wof:placetype":"venue"
},
  "geometry": {"coordinates":[-0.254423,51.537136],"type":"Point"}
}