{
  "type": "Feature",
  "properties": {
    "iso:country":"GB",
    "sg:address":"94a Wakefield Road, Clayton West",
    "sg:city":"Huddersfield",
    "sg:classifiers":[
        {
            "category":"Freight",
            "type":"Transportation"
        }
    ],
    "sg:phone":"+44 1484 863244",
    "sg:postcode":"HD8 9NN",
    "sg:province":"South Yorkshire",
    "sg:tags":[
        "haulage",
        "road"
    ],
    "wof:name":"J D Flack (Haulage) Ltd.",
    "wof:placetype":"venue"
},
  "geometry": {"coordinates":[-1.616628,53.595993],"type":"Point"}
}