{
  "type": "Feature",
  "properties": {
    "addr:full":"427 Beechdale Road, Aspley Nottingham Nottinghamshire NG8 3LF",
    "addr:housenumber":"427",
    "addr:postcode":"ng8 3lf",
    "addr:street":"Beechdale Road",
    "iso:country":"GB",
    "sg:address":"427 Beechdale Road, Aspley",
    "sg:city":"Nottingham",
    "sg:classifiers":[
        {
            "category":"Food & Beverages",
            "subcategory":"Bakery",
            "type":"Retail Goods"
        }
    ],
    "sg:phone":"+44 115 929 9093",
    "sg:postcode":"NG8 3LF",
    "sg:province":"Nottinghamshire",
    "sg:tags":[
        "baker"
    ],
    "wof:name":"Bakers",
    "wof:placetype":"venue"
},
  "geometry": {"coordinates":[-1.200204,52.961555],"type":"Point"}
}