{
  "type": "Feature",
  "properties": {
    "addr:full":"Weoley Park Road Birmingham West Midlands B29 6QT",
    "addr:postcode":"b29 6qt",
    "addr:street":"Weoley Park Road",
    "iso:country":"GB",
    "sg:address":"Weoley Park Road",
    "sg:city":"Birmingham",
    "sg:classifiers":[
        {
            "category":"Education",
            "subcategory":"Special Training",
            "type":"Public Place"
        }
    ],
    "sg:phone":"+44 121 472 4228",
    "sg:postcode":"B29 6QT",
    "sg:province":"West Midlands",
    "sg:tags":[
        "product",
        "centre"
    ],
    "wof:name":"Crowther Hall C M S Training College",
    "wof:placetype":"venue"
},
  "geometry": {"coordinates":[-1.9519890547,52.4378089905],"type":"Point"}
}