{
  "type": "Feature",
  "properties": {
    "addr:full":"43 Springfield Clo, Lavant Chichester West Sussex PO18 0AZ",
    "addr:housenumber":"43",
    "addr:postcode":"po18 0az",
    "addr:street":"Springfield Clo Lavant",
    "iso:country":"GB",
    "sg:address":"43 Springfield Clo, Lavant",
    "sg:city":"Chichester",
    "sg:classifiers":[
        {
            "category":"Personal",
            "subcategory":"Beauty Salon",
            "type":"Services"
        }
    ],
    "sg:postcode":"PO18 0AZ",
    "sg:province":"West Sussex",
    "sg:tags":[
        "unisex",
        "hairdresser"
    ],
    "wof:name":"Simpson,Penelope,",
    "wof:placetype":"venue"
},
  "geometry": {"coordinates":[-0.7865080237,50.8745498657],"type":"Point"}
}