{
  "type": "Feature",
  "properties": {
    "iso:country":"GB",
    "sg:address":"6 Caldmore Grn",
    "sg:city":"Walsall",
    "sg:classifiers":[
        {
            "category":"Professional",
            "type":"Services"
        }
    ],
    "sg:phone":"+44 1922 647272",
    "sg:postcode":"WS1 3RL",
    "sg:province":"West Midlands",
    "sg:tags":[
        "caterer"
    ],
    "wof:name":"Mollones",
    "wof:placetype":"venue"
},
  "geometry": {"coordinates":[-1.9823100567,52.5766868591],"type":"Point"}
}