{
  "type": "Feature",
  "properties": {
    "addr:full":"12a Beulah Road Cardiff Cardiff CF14 6LX",
    "addr:housenumber":"12a",
    "addr:postcode":"cf14 6lx",
    "addr:street":"Beulah Road",
    "iso:country":"GB",
    "sg:address":"12a Beulah Road",
    "sg:city":"Cardiff",
    "sg:classifiers":[
        {
            "category":"Personal",
            "subcategory":"Beauty Salon",
            "type":"Services"
        }
    ],
    "sg:postcode":"CF14 6LX",
    "sg:province":"Cardiff",
    "sg:tags":[
        "lady",
        "hairdresser"
    ],
    "wof:name":"Andrews Salon",
    "wof:placetype":"venue"
},
  "geometry": {"coordinates":[-3.210885,51.522327],"type":"Point"}
}