{
  "type": "Feature",
  "properties": {
    "iso:country":"GB",
    "sg:address":"97 Squires Gate Lane",
    "sg:city":"Blackpool",
    "sg:classifiers":[
        {
            "category":"Cafe",
            "type":"Food & Drink"
        }
    ],
    "sg:phone":"+44 1253 312125",
    "sg:postcode":"FY4 1QW",
    "sg:province":"Lancashire",
    "sg:tags":[
        "tea",
        "snack",
        "bar",
        "room"
    ],
    "wof:name":"Squires Cafe",
    "wof:placetype":"venue"
},
  "geometry": {"coordinates":[-3.047159,53.778477],"type":"Point"}
}