{
  "type": "Feature",
  "properties": {
    "iso:country":"GB",
    "sg:address":"Leithen Rd",
    "sg:city":"Innerleithen",
    "sg:classifiers":[
        {
            "category":"Manufacturing",
            "subcategory":"Rubber & Plastics",
            "type":"Manufacturing & Wholesale Goods"
        }
    ],
    "sg:phone":"+44 1896 830345",
    "sg:postcode":"EH44 6HX",
    "sg:province":"Scottish Borders",
    "sg:tags":[
        "product"
    ],
    "wof:name":"Leithen Valley Plastics Ltd",
    "wof:placetype":"venue"
},
  "geometry": {"coordinates":[-3.05783,55.628307],"type":"Point"}
}