{
  "type": "Feature",
  "properties": {
    "addr:full":"Star Ho, Star Hill Rochester Kent ME1 1UX",
    "addr:postcode":"me1 1ux",
    "addr:street":"Star Hill Rochester",
    "iso:country":"GB",
    "sg:address":"Star Ho, Star Hill",
    "sg:city":"Rochester",
    "sg:classifiers":[
        {
            "category":"Building & Trades",
            "subcategory":"Construction",
            "type":"Services"
        }
    ],
    "sg:phone":"+44 1634 582163",
    "sg:postcode":"ME1 1UX",
    "sg:province":"Kent",
    "sg:tags":[
        "flooring"
    ],
    "wof:name":"Hi-Spec",
    "wof:placetype":"venue"
},
  "geometry": {"coordinates":[0.507529974,51.385471344],"type":"Point"}
}