{
  "type": "Feature",
  "properties": {
    "addr:full":"164 High Rd Leytonstone Stratford Greater London E15 1UA",
    "addr:housenumber":"164",
    "addr:postcode":"e15 1ua",
    "addr:street":"High Rd",
    "iso:country":"GB",
    "sg:address":"164 High Rd Leytonstone",
    "sg:city":"Stratford",
    "sg:classifiers":[
        {
            "category":"Manufacturing",
            "subcategory":"Building Materials",
            "type":"Manufacturing & Wholesale Goods"
        }
    ],
    "sg:phone":"+44 20 8534 3439",
    "sg:postcode":"E15 1UA",
    "sg:province":"Greater London",
    "sg:tags":[
        "tile",
        "mnfrs"
    ],
    "wof:name":"Impex Ceramics",
    "wof:placetype":"venue"
},
  "geometry": {"coordinates":[0.0056810002,51.5524940491],"type":"Point"}
}