{
  "type": "Feature",
  "properties": {
    "addr:full":"39 Bath Road Cheltenham Gloucestershire GL53 7HG",
    "addr:housenumber":"39",
    "addr:postcode":"gl53 7hg",
    "addr:street":"Bath Road",
    "iso:country":"GB",
    "sg:address":"39 Bath Road",
    "sg:city":"Cheltenham",
    "sg:classifiers":[
        {
            "category":"Place Of Worship",
            "type":"Public Place"
        },
        {
            "category":"Organizations",
            "subcategory":"Non-profit Organization",
            "type":"Services"
        }
    ],
    "sg:phone":"+44 1242 523412",
    "sg:postcode":"GL53 7HG",
    "sg:province":"Gloucestershire",
    "sg:tags":[
        "organisation",
        "voluntary",
        "charity"
    ],
    "wof:name":"The Salvation Army",
    "wof:placetype":"venue"
},
  "geometry": {"coordinates":[-2.073527,51.897163],"type":"Point"}
}