{
  "type": "Feature",
  "properties": {
    "iso:country":"GB",
    "sg:address":"Wendover Rd, Rackheath Indust Est",
    "sg:city":"Norwich",
    "sg:classifiers":[
        {
            "category":"Manufacturing",
            "subcategory":"Metals",
            "type":"Manufacturing & Wholesale Goods"
        }
    ],
    "sg:phone":"+44 1603 721220",
    "sg:postcode":"NR13 6LH",
    "sg:province":"Norfolk",
    "sg:tags":[
        "steel",
        "fabricator",
        "erectors"
    ],
    "wof:name":"Northcote Services",
    "wof:placetype":"venue"
},
  "geometry": {"coordinates":[1.370659,52.675293],"type":"Point"}
}