{
  "type": "Feature",
  "properties": {
    "addr:full":"28 Clarendon Road London Greater London SW19 2DU",
    "addr:housenumber":"28",
    "addr:postcode":"sw19 2du",
    "addr:street":"Clarendon Road",
    "iso:country":"GB",
    "sg:address":"28 Clarendon Road",
    "sg:city":"London",
    "sg:classifiers":[
        {
            "category":"Professional",
            "subcategory":"Research",
            "type":"Services"
        }
    ],
    "sg:postcode":"SW19 2DU",
    "sg:province":"Greater London",
    "sg:tags":[
        "market"
    ],
    "wof:name":"Market Answers Ltd",
    "wof:placetype":"venue"
},
  "geometry": {"coordinates":[-0.1725520045,51.417301178],"type":"Point"}
}