{
  "type": "Feature",
  "properties": {
    "addr:full":"Roslin Road London Greater London W3 8DH",
    "addr:postcode":"w3 8dh",
    "addr:street":"Roslin Road",
    "iso:country":"GB",
    "sg:address":"Roslin Road",
    "sg:city":"London",
    "sg:classifiers":[
        {
            "category":"Manufacturing",
            "subcategory":"Printing",
            "type":"Manufacturing & Wholesale Goods"
        }
    ],
    "sg:phone":"+44 20 8992 3965",
    "sg:postcode":"W3 8DH",
    "sg:province":"Greater London",
    "sg:tags":[
        "bookbinder"
    ],
    "wof:name":"F J Blissett & Co. Ltd.",
    "wof:placetype":"venue"
},
  "geometry": {"coordinates":[-0.2748889923,51.5005302429],"type":"Point"}
}