{
  "type": "Feature",
  "properties": {
    "iso:country":"GB",
    "sg:address":"3 East Street",
    "sg:city":"Wareham",
    "sg:classifiers":[
        {
            "category":"Museum",
            "subcategory":"Art Museum",
            "type":"Entertainment"
        }
    ],
    "sg:phone":"+44 1929 553448",
    "sg:postcode":"BH20 4NN",
    "sg:province":"Dorset",
    "sg:tags":[
        "gallery"
    ],
    "wof:name":"Wareham Town Museum",
    "wof:placetype":"venue"
},
  "geometry": {"coordinates":[-2.109672,50.68615],"type":"Point"}
}