{
  "type": "Feature",
  "properties": {
    "addr:full":"6 King George Avenue, Dunston Gateshead Tyne and Wear NE11 9UP",
    "addr:housenumber":"6",
    "addr:postcode":"ne11 9up",
    "addr:street":"King George Avenue",
    "iso:country":"GB",
    "sg:address":"6 King George Avenue, Dunston",
    "sg:city":"Gateshead",
    "sg:classifiers":[
        {
            "category":"Shopping",
            "subcategory":"Florist",
            "type":"Retail Goods"
        }
    ],
    "sg:postcode":"NE11 9UP",
    "sg:province":"Tyne and Wear",
    "wof:name":"Evergreen Florists",
    "wof:placetype":"venue"
},
  "geometry": {"coordinates":[-1.646911025,54.9486236572],"type":"Point"}
}