{
  "type": "Feature",
  "properties": {
    "addr:full":"Ty Gwyn Newbury Berkshire RG14 6JB",
    "addr:postcode":"rg14 6jb",
    "addr:street":"Newbury",
    "iso:country":"GB",
    "sg:address":"Ty Gwyn",
    "sg:city":"Newbury",
    "sg:classifiers":[
        {
            "category":"Taxi",
            "type":"Transportation"
        }
    ],
    "sg:phone":"+44 1635 481215",
    "sg:postcode":"RG14 6JB",
    "sg:province":"Berkshire",
    "sg:tags":[
        "mini",
        "cab"
    ],
    "wof:name":"A D C Executive Cars",
    "wof:placetype":"venue"
},
  "geometry": {"coordinates":[-1.3333740234,51.3881835938],"type":"Point"}
}