{
  "type": "Feature",
  "properties": {
    "addr:full":"Airport Cargo, Birmingham International Airport Birmingham West Midlands B26 3QN",
    "addr:postcode":"b26 3qn",
    "iso:country":"GB",
    "sg:address":"Airport Cargo, Birmingham International Airport",
    "sg:city":"Birmingham",
    "sg:classifiers":[
        {
            "category":"Government",
            "subcategory":"Customs House",
            "type":"Public Place"
        }
    ],
    "sg:phone":"+44 121 781 7850",
    "sg:postcode":"B26 3QN",
    "sg:province":"West Midlands",
    "sg:tags":[
        "excise"
    ],
    "wof:name":"H M Customs & Excise",
    "wof:placetype":"venue"
},
  "geometry": {"coordinates":[-1.7505539656,52.4495239258],"type":"Point"}
}