{
  "type": "Feature",
  "properties": {
    "addr:full":"Unit 12 Garth Works, Taffs Well Cardiff Caerphilly CF15 7RN",
    "addr:housenumber":"unit 12",
    "addr:postcode":"cf15 7rn",
    "addr:street":"Garth Works;Well",
    "iso:country":"GB",
    "sg:address":"Unit 12 Garth Works, Taffs Well",
    "sg:city":"Cardiff",
    "sg:classifiers":[
        {
            "category":"Manufacturing",
            "subcategory":"Petroleum Products",
            "type":"Manufacturing & Wholesale Goods"
        }
    ],
    "sg:phone":"+44 29 2081 3066",
    "sg:postcode":"CF15 7RN",
    "sg:province":"Caerphilly",
    "sg:tags":[
        "double",
        "glazing"
    ],
    "wof:name":"Window World (Wales) Ltd.",
    "wof:placetype":"venue"
},
  "geometry": {"coordinates":[-3.26715,51.543541],"type":"Point"}
}