{
  "type": "Feature",
  "properties": {
    "iso:country":"GB",
    "sg:address":"15 Ashfield Parade",
    "sg:city":"Southgate",
    "sg:classifiers":[
        {
            "category":"Communications",
            "type":"Services"
        }
    ],
    "sg:phone":"+44 20 8447 8888",
    "sg:postcode":"N14 5EH",
    "sg:province":"Greater London",
    "sg:tags":[
        "telecommunication"
    ],
    "wof:name":"Phonelink Business Centre",
    "wof:placetype":"venue"
},
  "geometry": {"coordinates":[-0.128234,51.631245],"type":"Point"}
}