{
  "type": "Feature",
  "properties": {
    "addr:full":"Argoedllwyd, Libanus Brecon Powys LD3 8EN",
    "addr:postcode":"ld3 8en",
    "iso:country":"GB",
    "sg:address":"Argoedllwyd, Libanus",
    "sg:city":"Brecon",
    "sg:classifiers":[
        {
            "category":"Recreation",
            "type":"Entertainment"
        }
    ],
    "sg:phone":"+44 1874 611947",
    "sg:postcode":"LD3 8EN",
    "sg:province":"Powys",
    "sg:tags":[
        "outdoor",
        "pursuit"
    ],
    "wof:name":"Hampshire Outdoor Centres",
    "wof:placetype":"venue"
},
  "geometry": {"coordinates":[-3.4636158943,51.9239425659],"type":"Point"}
}