{
  "type": "Feature",
  "properties": {
    "addr:full":"108c High Street Billericay Essex CM12 9BY",
    "addr:housenumber":"108c",
    "addr:postcode":"cm12 9by",
    "addr:street":"High Street",
    "iso:country":"GB",
    "sg:address":"108c High Street",
    "sg:city":"Billericay",
    "sg:classifiers":[
        {
            "category":"Professional",
            "subcategory":"Lawyer & Legal Services",
            "type":"Services"
        }
    ],
    "sg:postcode":"CM12 9BY",
    "sg:province":"Essex",
    "sg:tags":[
        "solicitor"
    ],
    "wof:name":"John Bacon & Co.",
    "wof:placetype":"venue"
},
  "geometry": {"coordinates":[0.416442,51.623684],"type":"Point"}
}