{
  "type": "Feature",
  "properties": {
    "iso:country":"GB",
    "sg:address":"10 Abbott Ford Road, Cotham",
    "sg:city":"Bristol",
    "sg:classifiers":[
        {
            "category":"Wholesale",
            "subcategory":"Construction Materials",
            "type":"Manufacturing & Wholesale Goods"
        }
    ],
    "sg:phone":"+44 117 973 4666",
    "sg:postcode":"BS6 6HP",
    "sg:province":"City of Bristol",
    "sg:tags":[
        "merchant",
        "glass"
    ],
    "wof:name":"Modern Glass (Bristol) Ltd.",
    "wof:placetype":"venue"
},
  "geometry": {"coordinates":[-2.606924,51.463882],"type":"Point"}
}