{
  "type": "Feature",
  "properties": {
    "addr:full":"Entrance 2 Undrewood Farm, Townfield Botley Rd, Bishops Waltham Southampton Hampshire SO32 1DR",
    "addr:housenumber":"entrance 2 undrewood farm townfield",
    "addr:postcode":"so32 1dr",
    "addr:street":"Botley Rd",
    "iso:country":"GB",
    "sg:address":"Entrance 2 Undrewood Farm, Townfield Botley Rd, Bishops Waltham",
    "sg:city":"Southampton",
    "sg:classifiers":[
        {
            "category":"Manufacturing",
            "subcategory":"Furniture",
            "type":"Manufacturing & Wholesale Goods"
        }
    ],
    "sg:phone":"+44 1489 890222",
    "sg:postcode":"SO32 1DR",
    "sg:province":"Hampshire",
    "sg:tags":[
        "mnfr",
        "upholsterer"
    ],
    "wof:name":"M P A Furnishings Ltd",
    "wof:placetype":"venue"
},
  "geometry": {"coordinates":[-1.2120419741,50.9547996521],"type":"Point"}
}