{
  "type": "Feature",
  "properties": {
    "addr:full":"Unit 3f Parkview Industrial Estate, Brenda Road Hartlepool Durham TS25 1PE",
    "addr:housenumber":"unit 3f;estate",
    "addr:postcode":"ts25 1pe",
    "addr:street":"Industrial;Brenda Road",
    "iso:country":"GB",
    "sg:address":"Unit 3f Parkview Industrial Estate, Brenda Road",
    "sg:city":"Hartlepool",
    "sg:classifiers":[
        {
            "category":"Retail",
            "subcategory":"Auto Repair",
            "type":"Services"
        }
    ],
    "sg:phone":"+44 1429 236300",
    "sg:postcode":"TS25 1PE",
    "sg:province":"Durham",
    "sg:tags":[
        "car",
        "servicing",
        "radiator"
    ],
    "wof:name":"The Hartlepool Radiator Co. Ltd.",
    "wof:placetype":"venue"
},
  "geometry": {"coordinates":[-1.2108490467,54.6627044678],"type":"Point"}
}