{
  "type": "Feature",
  "properties": {
    "addr:full":"37 Promenade, Arnside Carnforth Cumbria LA5 0HA",
    "addr:housenumber":"37",
    "addr:postcode":"la5 0ha",
    "addr:street":"Promenade",
    "iso:country":"GB",
    "sg:address":"37 Promenade, Arnside",
    "sg:city":"Carnforth",
    "sg:classifiers":[
        {
            "category":"Shopping",
            "subcategory":"Clothing, Apparel, & Fashions",
            "type":"Retail Goods"
        }
    ],
    "sg:phone":"+44 1524 761334",
    "sg:postcode":"LA5 0HA",
    "sg:province":"Cumbria",
    "sg:tags":[
        "shop"
    ],
    "wof:name":"The Country Shop",
    "wof:placetype":"venue"
},
  "geometry": {"coordinates":[-2.8323690891,54.1741600037],"type":"Point"}
}