{
  "type": "Feature",
  "properties": {
    "iso:country":"GB",
    "sg:address":"322 Old Heath Road",
    "sg:city":"Colchester",
    "sg:classifiers":[
        {
            "category":"Home & Garden",
            "subcategory":"Household Appliances",
            "type":"Retail Goods"
        }
    ],
    "sg:phone":"+44 1206 571050",
    "sg:postcode":"CO2 8BW",
    "sg:province":"Essex",
    "sg:tags":[
        "electrical"
    ],
    "wof:name":"S M Domestics",
    "wof:placetype":"venue"
},
  "geometry": {"coordinates":[0.926216,51.871368],"type":"Point"}
}