{
  "type": "Feature",
  "properties": {
    "addr:full":"65 Thorpe Road Walsall West Midlands WS1 4BT",
    "addr:housenumber":"65",
    "addr:postcode":"ws1 4bt",
    "addr:street":"Thorpe Road",
    "iso:country":"GB",
    "sg:address":"65 Thorpe Road",
    "sg:city":"Walsall",
    "sg:classifiers":[
        {
            "category":"Government",
            "subcategory":"Post Office",
            "type":"Public Place"
        },
        {
            "category":"Military Area",
            "subcategory":"Air Force Base",
            "type":"Public Place"
        }
    ],
    "sg:phone":"+44 1922 638686",
    "sg:postcode":"WS1 4BT",
    "sg:province":"West Midlands",
    "sg:tags":[
        "taxi",
        "hire",
        "messenger",
        "private",
        "courier"
    ],
    "wof:name":"Central Taxis",
    "wof:placetype":"venue"
},
  "geometry": {"coordinates":[-1.982578,52.574081],"type":"Point"}
}