{
  "type": "Feature",
  "properties": {
    "addr:full":"Unit 31, Branbridges Industrial Estate, Branbridges Road Tonbridge Kent TN12 5HF",
    "addr:housenumber":"unit 31",
    "addr:postcode":"tn12 5hf",
    "addr:street":"Branbridges Industrial Estate Branbridges Road",
    "iso:country":"GB",
    "sg:address":"Unit 31, Branbridges Industrial Estate, Branbridges Road",
    "sg:city":"Tonbridge",
    "sg:classifiers":[
        {
            "category":"Manufacturing",
            "subcategory":"Tools & Machinery",
            "type":"Manufacturing & Wholesale Goods"
        }
    ],
    "sg:phone":"+44 1622 872723",
    "sg:postcode":"TN12 5HF",
    "sg:province":"Kent",
    "sg:tags":[
        "design",
        "maker"
    ],
    "wof:name":"Wealden Tool Co.",
    "wof:placetype":"venue"
},
  "geometry": {"coordinates":[0.3956199884,51.2092514038],"type":"Point"}
}