{
  "type": "Feature",
  "properties": {
    "addr:full":"29 Netheravon Rd Chiswick Greater London W4 2NA",
    "addr:housenumber":"29",
    "addr:postcode":"w4 2na",
    "addr:street":"Netheravon Rd",
    "iso:country":"GB",
    "sg:address":"29 Netheravon Rd",
    "sg:city":"Chiswick",
    "sg:classifiers":[
        {
            "category":"Health Services",
            "subcategory":"Doctor",
            "type":"Services"
        }
    ],
    "sg:phone":"+44 20 8994 2506",
    "sg:postcode":"W4 2NA",
    "sg:province":"Greater London",
    "sg:tags":[
        "practitioners"
    ],
    "wof:name":"Paszkowska Dr K",
    "wof:placetype":"venue"
},
  "geometry": {"coordinates":[-0.2465759963,51.4921684265],"type":"Point"}
}