{
  "type": "Feature",
  "properties": {
    "iso:country":"GB",
    "sg:address":"716 Romford Road",
    "sg:city":"London",
    "sg:classifiers":[
        {
            "category":"Cafe",
            "type":"Food & Drink"
        }
    ],
    "sg:phone":"+44 20 8553 4691",
    "sg:postcode":"E12 6BT",
    "sg:province":"Greater London",
    "sg:tags":[
        "tea",
        "snack",
        "bar",
        "room"
    ],
    "wof:name":"Pine Cafe",
    "wof:placetype":"venue"
},
  "geometry": {"coordinates":[0.052752,51.552315],"type":"Point"}
}