{
  "type": "Feature",
  "properties": {
    "addr:full":"Peddimore Hall Farm, Minworth Sutton Coldfield Warwickshire B76 9AA",
    "addr:postcode":"b76 9aa",
    "addr:street":"Minworth",
    "iso:country":"GB",
    "sg:address":"Peddimore Hall Farm, Minworth",
    "sg:city":"Sutton Coldfield",
    "sg:classifiers":[
        {
            "category":"Farming",
            "subcategory":"Livestock Farm",
            "type":"Manufacturing & Wholesale Goods"
        }
    ],
    "sg:phone":"+44 121 351 1441",
    "sg:postcode":"B76 9AA",
    "sg:province":"Warwickshire",
    "sg:tags":[
        "others"
    ],
    "wof:name":"Wallis Bros",
    "wof:placetype":"venue"
},
  "geometry": {"coordinates":[-1.7678519487,52.5275726318],"type":"Point"}
}