{
  "type": "Feature",
  "properties": {
    "iso:country":"GB",
    "sg:address":"25 Back York Street",
    "sg:city":"Leeds",
    "sg:classifiers":[
        {
            "category":"Manufacturing",
            "subcategory":"Printing",
            "type":"Manufacturing & Wholesale Goods"
        }
    ],
    "sg:phone":"+44 113 245 5555",
    "sg:postcode":"LS2 7ED",
    "sg:province":"West Yorkshire",
    "sg:tags":[
        "bookbinder"
    ],
    "wof:name":"J E Ingle & Son Ltd.",
    "wof:placetype":"venue"
},
  "geometry": {"coordinates":[-1.5367799997,53.7959861755],"type":"Point"}
}