{
  "type": "Feature",
  "properties": {
    "iso:country":"GB",
    "sg:address":"319 Gidlow Lane",
    "sg:city":"Wigan",
    "sg:classifiers":[
        {
            "category":"Food & Beverages",
            "subcategory":"Liquor & Beverages",
            "type":"Retail Goods"
        }
    ],
    "sg:postcode":"WN6 7PH",
    "sg:province":"Lancashire",
    "sg:tags":[
        "beer",
        "spirit",
        "wines"
    ],
    "wof:name":"K & J Scarisbrick",
    "wof:placetype":"venue"
},
  "geometry": {"coordinates":[-2.6441090107,53.5564804077],"type":"Point"}
}