{
  "type": "Feature",
  "properties": {
    "iso:country":"GB",
    "sg:address":"443 Tile Hill Lane",
    "sg:city":"Coventry",
    "sg:classifiers":[
        {
            "category":"Professional",
            "subcategory":"Art Services",
            "type":"Services"
        }
    ],
    "sg:phone":"+44 24 7646 4501",
    "sg:postcode":"CV4 9DP",
    "sg:province":"Warwickshire",
    "sg:tags":[
        "photographer"
    ],
    "wof:name":"Martin Bowyn",
    "wof:placetype":"venue"
},
  "geometry": {"coordinates":[-1.568261,52.402618],"type":"Point"}
}