{
  "type": "Feature",
  "properties": {
    "addr:full":"Market Street Ilkeston Derbyshire DE7 5RB",
    "addr:postcode":"de7 5rb",
    "addr:street":"Market Street",
    "iso:country":"GB",
    "sg:address":"Market Street",
    "sg:city":"Ilkeston",
    "sg:classifiers":[
        {
            "category":"Bars & Pubs",
            "type":"Food & Drink"
        }
    ],
    "sg:phone":"+44 115 944 4385",
    "sg:postcode":"DE7 5RB",
    "sg:province":"Derbyshire",
    "sg:tags":[
        "pubs",
        "inn"
    ],
    "wof:name":"The Anchor Inn",
    "wof:placetype":"venue"
},
  "geometry": {"coordinates":[-1.30834198,52.9701423645],"type":"Point"}
}