{
  "type": "Feature",
  "properties": {
    "iso:country":"GB",
    "sg:address":"Unit 3 Greenhill Rd, Kingsteignton",
    "sg:city":"Newton Abbot",
    "sg:classifiers":[
        {
            "category":"Building & Trades",
            "subcategory":"Construction",
            "type":"Services"
        }
    ],
    "sg:phone":"+44 1626 330700",
    "sg:postcode":"TQ12 3BD",
    "sg:province":"Devon",
    "sg:tags":[
        "builder"
    ],
    "wof:name":"Churchill Building & Preservation Servic",
    "wof:placetype":"venue"
},
  "geometry": {"coordinates":[-3.591841,50.54565],"type":"Point"}
}