{
  "type": "Feature",
  "properties": {
    "iso:country":"GB",
    "sg:address":"153/155 High St, Wolstanton",
    "sg:city":"Newcastle",
    "sg:classifiers":[
        {
            "category":"Military Area",
            "subcategory":"Air Force Base",
            "type":"Public Place"
        }
    ],
    "sg:postcode":"ST5 0EJ",
    "sg:province":"Staffordshire",
    "sg:tags":[
        "supplier",
        "mnfrs",
        "plaster"
    ],
    "wof:name":"Auberge Mouldings Ltd.",
    "wof:placetype":"venue"
},
  "geometry": {"coordinates":[-2.2162160873,53.0302429199],"type":"Point"}
}