{
  "type": "Feature",
  "properties": {
    "addr:full":"25 Market Street, Clay Cross Chesterfield Derbyshire S45 9JE",
    "addr:housenumber":"25",
    "addr:postcode":"s45 9je",
    "addr:street":"Market Street",
    "iso:country":"GB",
    "sg:address":"25 Market Street, Clay Cross",
    "sg:city":"Chesterfield",
    "sg:classifiers":[
        {
            "category":"Bars & Pubs",
            "type":"Food & Drink"
        }
    ],
    "sg:phone":"+44 1246 860336",
    "sg:postcode":"S45 9JE",
    "sg:province":"Derbyshire",
    "sg:tags":[
        "pubs",
        "inn"
    ],
    "wof:name":"The New Inn",
    "wof:placetype":"venue"
},
  "geometry": {"coordinates":[-1.4138829708,53.166557312],"type":"Point"}
}