{
  "type": "Feature",
  "properties": {
    "iso:country":"GB",
    "sg:address":"31 Clachnaharry Road",
    "sg:city":"Inverness",
    "sg:classifiers":[
        {
            "category":"Home & Garden",
            "subcategory":"Carpets & Floor Coverings",
            "type":"Retail Goods"
        }
    ],
    "sg:postcode":"IV3 8RA",
    "sg:province":"Highland",
    "sg:tags":[
        "carpets",
        "rug",
        "matting"
    ],
    "wof:name":"Caldon Contracts",
    "wof:placetype":"venue"
},
  "geometry": {"coordinates":[-4.254012,57.486938],"type":"Point"}
}