{
  "type": "Feature",
  "properties": {
    "addr:full":"Riverside Cottage, Clyst St.mary Exeter Devon EX5 1BR",
    "addr:housenumber":"cottage",
    "addr:postcode":"ex5 1br",
    "addr:street":"Clyst St.Mary",
    "iso:country":"GB",
    "sg:address":"Riverside Cottage, Clyst St.mary",
    "sg:city":"Exeter",
    "sg:classifiers":[
        {
            "category":"Home & Garden",
            "subcategory":"Building Materials",
            "type":"Retail Goods"
        }
    ],
    "sg:phone":"+44 1392 874525",
    "sg:postcode":"EX5 1BR",
    "sg:province":"Devon",
    "sg:tags":[
        "stairlifts"
    ],
    "wof:name":"R W Pryse Stairlifts",
    "wof:placetype":"venue"
},
  "geometry": {"coordinates":[-3.4561600685,50.7099189758],"type":"Point"}
}