{
  "type": "Feature",
  "properties": {
    "iso:country":"GB",
    "sg:address":"1 Stella Street",
    "sg:city":"Mansfield",
    "sg:classifiers":[
        {
            "category":"Fast Food",
            "type":"Food & Drink"
        }
    ],
    "sg:postcode":"NG18 4AN",
    "sg:province":"Nottinghamshire",
    "sg:tags":[
        "away",
        "meal",
        "outlet",
        "take"
    ],
    "wof:name":"The Bakery",
    "wof:placetype":"venue"
},
  "geometry": {"coordinates":[-1.196567,53.135971],"type":"Point"}
}