{
  "type": "Feature",
  "properties": {
    "addr:full":"Ground & 1st Floor, Coopers House, Horsefair Court Romsey Hampshire SO51 8JZ",
    "addr:housenumber":"1st floor coopers house",
    "addr:postcode":"so51 8jz",
    "addr:street":"Horsefair Court",
    "iso:country":"GB",
    "sg:address":"Ground & 1st Floor, Coopers House, Horsefair Court",
    "sg:city":"Romsey",
    "sg:classifiers":[
        {
            "category":"Communications",
            "subcategory":"Newspaper",
            "type":"Services"
        }
    ],
    "sg:phone":"+44 1794 835005",
    "sg:postcode":"SO51 8JZ",
    "sg:province":"Hampshire",
    "sg:tags":[
        "magazine"
    ],
    "wof:name":"Dorset & New Forest Freeads",
    "wof:placetype":"venue"
},
  "geometry": {"coordinates":[-1.49925,50.990829],"type":"Point"}
}