{
  "type": "Feature",
  "properties": {
    "iso:country":"GB",
    "sg:address":"Lightash, School La",
    "sg:city":"Preston",
    "sg:classifiers":[
        {
            "category":"Farming",
            "subcategory":"Farm",
            "type":"Manufacturing & Wholesale Goods"
        }
    ],
    "sg:phone":"+44 1524 791981",
    "sg:postcode":"PR3 0JY",
    "sg:province":"Lancashire",
    "sg:tags":[
        "mixed",
        "crop"
    ],
    "wof:name":"T Tomlinson",
    "wof:placetype":"venue"
},
  "geometry": {"coordinates":[-2.79927,53.930771],"type":"Point"}
}