{
  "type": "Feature",
  "properties": {
    "addr:full":"40 Regent Street, Kingswood Bristol City of Bristol BS15 8JS",
    "addr:housenumber":"40",
    "addr:postcode":"bs15 8js",
    "addr:street":"Regent Street",
    "iso:country":"GB",
    "sg:address":"40 Regent Street, Kingswood",
    "sg:city":"Bristol",
    "sg:classifiers":[
        {
            "category":"Travel",
            "subcategory":"Travel Agent",
            "type":"Entertainment"
        }
    ],
    "sg:phone":"+44 117 960 1126",
    "sg:postcode":"BS15 8JS",
    "sg:province":"City of Bristol",
    "wof:name":"Going Places Leisure Travel",
    "wof:placetype":"venue"
},
  "geometry": {"coordinates":[-2.509524107,51.4626045227],"type":"Point"}
}