{
  "type": "Feature",
  "properties": {
    "addr:full":"Unit 1 The Old Stables, Back Grange Av Harrogate North Yorkshire HG1 2AN",
    "addr:housenumber":"unit 1",
    "addr:postcode":"hg1 2an",
    "addr:street":"The;Back Grange Av",
    "iso:country":"GB",
    "sg:address":"Unit 1 The Old Stables, Back Grange Av",
    "sg:city":"Harrogate",
    "sg:classifiers":[
        {
            "category":"Health Services",
            "subcategory":"Medical Lab",
            "type":"Services"
        }
    ],
    "sg:phone":"+44 1423 567409",
    "sg:postcode":"HG1 2AN",
    "sg:province":"North Yorkshire",
    "sg:tags":[
        "dental"
    ],
    "wof:name":"Replicant Ceramics",
    "wof:placetype":"venue"
},
  "geometry": {"coordinates":[-1.536256,54.003941],"type":"Point"}
}