{
  "type": "Feature",
  "properties": {
    "addr:full":"Sir Ivors Road Blackwood Caerphilly NP12 2JH",
    "addr:postcode":"np12 2jh",
    "addr:street":"Sir Ivors Road",
    "iso:country":"GB",
    "sg:address":"Sir Ivors Road",
    "sg:city":"Blackwood",
    "sg:classifiers":[
        {
            "category":"Autos & Motor Vehicles",
            "subcategory":"Auto Supplies",
            "type":"Retail Goods"
        }
    ],
    "sg:phone":"+44 1495 225553",
    "sg:postcode":"NP12 2JH",
    "sg:province":"Caerphilly",
    "sg:tags":[
        "tyre"
    ],
    "wof:name":"David King Tyres",
    "wof:placetype":"venue"
},
  "geometry": {"coordinates":[-3.188094,51.653614],"type":"Point"}
}