{
  "type": "Feature",
  "properties": {
    "addr:full":"4 Dykes Place Stangate Road, Birling West Malling Kent ME19 5JJ",
    "addr:housenumber":"4",
    "addr:postcode":"me19 5jj",
    "addr:street":"Dykes Place Stangate Road",
    "iso:country":"GB",
    "sg:address":"4 Dykes Place Stangate Road, Birling",
    "sg:city":"West Malling",
    "sg:classifiers":[
        {
            "category":"Building & Trades",
            "subcategory":"Construction",
            "type":"Services"
        }
    ],
    "sg:phone":"+44 1634 241813",
    "sg:postcode":"ME19 5JJ",
    "sg:province":"Kent",
    "sg:tags":[
        "roofing"
    ],
    "wof:name":"A J Lucas",
    "wof:placetype":"venue"
},
  "geometry": {"coordinates":[0.4096310139,51.3193435669],"type":"Point"}
}