{
  "type": "Feature",
  "properties": {
    "addr:full":"154 Buxton Road, High Lane Stockport Cheshire SK6 8EA",
    "addr:housenumber":"154",
    "addr:postcode":"sk6 8ea",
    "addr:street":"Buxton Road High Lane",
    "iso:country":"GB",
    "sg:address":"154 Buxton Road, High Lane",
    "sg:city":"Stockport",
    "sg:classifiers":[
        {
            "category":"Communications",
            "subcategory":"Film & Video Production",
            "type":"Services"
        }
    ],
    "sg:phone":"+44 1663 762389",
    "sg:postcode":"SK6 8EA",
    "sg:province":"Cheshire",
    "sg:tags":[
        "illustrator",
        "artist"
    ],
    "wof:name":"Lyme Studio China",
    "wof:placetype":"venue"
},
  "geometry": {"coordinates":[-2.063551,53.363495],"type":"Point"}
}