{
  "type": "Feature",
  "properties": {
    "addr:full":"The Old Raf Building Milton Keynes Bedfordshire MK17 0EA",
    "addr:postcode":"mk17 0ea",
    "iso:country":"GB",
    "sg:address":"The Old Raf Building",
    "sg:city":"Milton Keynes",
    "sg:classifiers":[
        {
            "category":"Autos & Motor Vehicles",
            "subcategory":"Automobile Sales",
            "type":"Retail Goods"
        }
    ],
    "sg:phone":"+44 1525 270174",
    "sg:postcode":"MK17 0EA",
    "sg:province":"Bedfordshire",
    "sg:tags":[
        "commercial"
    ],
    "wof:name":"A K Management Services Ltd.",
    "wof:placetype":"venue"
},
  "geometry": {"coordinates":[-0.7277489901,52.0058555603],"type":"Point"}
}