{
  "type": "Feature",
  "properties": {
    "iso:country":"GB",
    "sg:address":"Cottis House, Locks Hill, Bradley Way",
    "sg:city":"Rochford",
    "sg:classifiers":[
        {
            "category":"Manufacturing",
            "subcategory":"Electronics",
            "type":"Manufacturing & Wholesale Goods"
        }
    ],
    "sg:phone":"+44 1702 542301",
    "sg:postcode":"SS4 1BB",
    "sg:province":"Essex",
    "sg:tags":[
        "mnfr",
        "component",
        "electronic"
    ],
    "wof:name":"Focus Electronic Distribution Ltd.",
    "wof:placetype":"venue"
},
  "geometry": {"coordinates":[0.706535,51.58073],"type":"Point"}
}