{
  "type": "Feature",
  "properties": {
    "addr:full":"Kings Street Mold Denbighshire CH7 1LA",
    "addr:postcode":"ch7 1la",
    "addr:street":"Kings Street",
    "iso:country":"GB",
    "sg:address":"Kings Street",
    "sg:city":"Mold",
    "sg:classifiers":[
        {
            "category":"Bars & Pubs",
            "subcategory":"Wine Bar",
            "type":"Food & Drink"
        }
    ],
    "sg:phone":"+44 1352 759642",
    "sg:postcode":"CH7 1LA",
    "sg:province":"Denbighshire",
    "wof:name":"Y Delyn Wine Bar",
    "wof:placetype":"venue"
},
  "geometry": {"coordinates":[-3.1399838924,53.1638679504],"type":"Point"}
}