{
  "type": "Feature",
  "properties": {
    "addr:full":"Howegarden Turriff Aberdeenshire AB53 7EN",
    "addr:postcode":"ab53 7en",
    "iso:country":"GB",
    "sg:address":"Howegarden",
    "sg:city":"Turriff",
    "sg:classifiers":[
        {
            "category":"Freight",
            "type":"Transportation"
        }
    ],
    "sg:phone":"+44 1888 511800",
    "sg:postcode":"AB53 7EN",
    "sg:province":"Aberdeenshire",
    "sg:tags":[
        "haulage",
        "road"
    ],
    "wof:name":"Trux + Ltd.",
    "wof:placetype":"venue"
},
  "geometry": {"coordinates":[-2.455229044,57.5399017334],"type":"Point"}
}