{
  "type": "Feature",
  "properties": {
    "iso:country":"GB",
    "sg:address":"4 King Street, Inververbie",
    "sg:city":"Montrose",
    "sg:classifiers":[
        {
            "category":"Food & Beverages",
            "subcategory":"Bakery",
            "type":"Retail Goods"
        }
    ],
    "sg:phone":"+44 1561 361221",
    "sg:postcode":"DD10 0RG",
    "sg:province":"Aberdeenshire",
    "sg:tags":[
        "shop",
        "baker"
    ],
    "wof:name":"Kondit Bakery",
    "wof:placetype":"venue"
},
  "geometry": {"coordinates":[-2.278412,56.845303],"type":"Point"}
}