{
  "type": "Feature",
  "properties": {
    "iso:country":"GB",
    "sg:address":"Hungate",
    "sg:city":"Pickering",
    "sg:classifiers":[
        {
            "category":"Travel",
            "subcategory":"Hotels & Motels",
            "type":"Entertainment"
        }
    ],
    "sg:phone":"+44 1751 472722",
    "sg:postcode":"YO18 7DL",
    "sg:province":"North Yorkshire",
    "wof:name":"Forest & Vale Hotel",
    "wof:placetype":"venue"
},
  "geometry": {"coordinates":[-0.7756440043,54.2443733215],"type":"Point"}
}