{
  "type": "Feature",
  "properties": {
    "addr:full":"111-113 High Street Aberdeen Aberdeen City AB24 3EN",
    "addr:housenumber":"111-113",
    "addr:postcode":"ab24 3en",
    "addr:street":"High Street",
    "iso:country":"GB",
    "sg:address":"111-113 High Street",
    "sg:city":"Aberdeen",
    "sg:classifiers":[
        {
            "category":"Professional",
            "type":"Services"
        }
    ],
    "sg:postcode":"AB24 3EN",
    "sg:province":"Aberdeen City",
    "sg:tags":[
        "interior",
        "furnishers",
        "designer"
    ],
    "wof:name":"Cairns Interiors",
    "wof:placetype":"venue"
},
  "geometry": {"coordinates":[-2.102289,57.16687],"type":"Point"}
}