{
  "type": "Feature",
  "properties": {
    "iso:country":"GB",
    "sg:address":"5 Chandos",
    "sg:city":"Sunderland",
    "sg:classifiers":[
        {
            "category":"Building & Trades",
            "subcategory":"Construction",
            "type":"Services"
        }
    ],
    "sg:phone":"+44 191 528 6146",
    "sg:postcode":"SR3 2TU",
    "sg:province":"Tyne and Wear",
    "sg:tags":[
        "contractor",
        "paving",
        "driveway"
    ],
    "wof:name":"City Paving",
    "wof:placetype":"venue"
},
  "geometry": {"coordinates":[-1.404725,54.860023],"type":"Point"}
}