{
  "type": "Feature",
  "properties": {
    "iso:country":"GB",
    "sg:address":"26 Queens Crescent, Putnoe",
    "sg:city":"Bedford",
    "sg:classifiers":[
        {
            "category":"Professional",
            "subcategory":"Engineering",
            "type":"Services"
        }
    ],
    "sg:phone":"+44 1234 261142",
    "sg:postcode":"MK41 9BN",
    "sg:province":"Bedfordshire",
    "sg:tags":[
        "contractor",
        "electrical",
        "engineer"
    ],
    "wof:name":"M W Electrical Contractors",
    "wof:placetype":"venue"
},
  "geometry": {"coordinates":[-0.442066,52.150566],"type":"Point"}
}