{
  "type": "Feature",
  "properties": {
    "addr:full":"23 Knutsford Road Wilmslow Cheshire SK9 6JB",
    "addr:housenumber":"23",
    "addr:postcode":"sk9 6jb",
    "addr:street":"Knutsford Road",
    "iso:country":"GB",
    "sg:address":"23 Knutsford Road",
    "sg:city":"Wilmslow",
    "sg:classifiers":[
        {
            "category":"Retail",
            "subcategory":"Auto Repair",
            "type":"Services"
        }
    ],
    "sg:phone":"+44 1625 523669",
    "sg:postcode":"SK9 6JB",
    "sg:province":"Cheshire",
    "sg:tags":[
        "modification",
        "garage"
    ],
    "wof:name":"H Marsh & Son (Wilmslow) Ltd.",
    "wof:placetype":"venue"
},
  "geometry": {"coordinates":[-2.2416520119,53.3185348511],"type":"Point"}
}