{
  "type": "Feature",
  "properties": {
    "addr:full":"181 Queensway London Greater London W2 5HL",
    "addr:housenumber":"181",
    "addr:postcode":"w2 5hl",
    "addr:street":"Queensway",
    "iso:country":"GB",
    "sg:address":"181 Queensway",
    "sg:city":"London",
    "sg:classifiers":[
        {
            "category":"Retail",
            "subcategory":"Laundry & Dry Cleaning",
            "type":"Services"
        }
    ],
    "sg:phone":"+44 20 7792 1479",
    "sg:postcode":"W2 5HL",
    "sg:province":"Greater London",
    "sg:tags":[
        "alteration"
    ],
    "wof:name":"Deep Clean",
    "wof:placetype":"venue"
},
  "geometry": {"coordinates":[-0.188724,51.515972],"type":"Point"}
}