{
  "type": "Feature",
  "properties": {
    "addr:full":"57 High St Slough Berkshire SL3 8NF",
    "addr:housenumber":"57",
    "addr:postcode":"sl3 8nf",
    "addr:street":"High St",
    "iso:country":"GB",
    "sg:address":"57 High St",
    "sg:city":"Slough",
    "sg:classifiers":[
        {
            "category":"Retail",
            "subcategory":"Storage",
            "type":"Services"
        }
    ],
    "sg:phone":"+44 1753 540099",
    "sg:postcode":"SL3 8NF",
    "sg:province":"Berkshire",
    "sg:tags":[
        "household",
        "removal"
    ],
    "wof:name":"Mayday Removals",
    "wof:placetype":"venue"
},
  "geometry": {"coordinates":[-0.5471159816,51.4954071045],"type":"Point"}
}