{
  "type": "Feature",
  "properties": {
    "iso:country":"GB",
    "sg:address":"The Clock Tower, 1a Rye Lane",
    "sg:city":"London",
    "sg:classifiers":[
        {
            "category":"Bars & Pubs",
            "subcategory":"Nightclub",
            "type":"Food & Drink"
        }
    ],
    "sg:phone":"+44 20 7732 9000",
    "sg:postcode":"SE15 5EW",
    "sg:province":"Greater London",
    "sg:tags":[
        "club",
        "night"
    ],
    "wof:name":"Ezekiel",
    "wof:placetype":"venue"
},
  "geometry": {"coordinates":[-0.070015,51.47303],"type":"Point"}
}