{
  "type": "Feature",
  "properties": {
    "addr:full":"14 Carmyle Avenue Glasgow Glasgow City G32 8HJ",
    "addr:housenumber":"14",
    "addr:postcode":"g32 8hj",
    "addr:street":"Carmyle Avenue",
    "iso:country":"GB",
    "sg:address":"14 Carmyle Avenue",
    "sg:city":"Glasgow",
    "sg:classifiers":[
        {
            "category":"Building & Trades",
            "subcategory":"Construction",
            "type":"Services"
        }
    ],
    "sg:phone":"+44 141 764 0300",
    "sg:postcode":"G32 8HJ",
    "sg:province":"Glasgow City",
    "sg:tags":[
        "builder"
    ],
    "wof:name":"David H Allan (Joiners & Building Contractors) Ltd.",
    "wof:placetype":"venue"
},
  "geometry": {"coordinates":[-4.1617560387,55.8407821655],"type":"Point"}
}