{
  "type": "Feature",
  "properties": {
    "iso:country":"GB",
    "sg:address":"Huxley Street",
    "sg:city":"Altrincham",
    "sg:classifiers":[
        {
            "category":"Home & Garden",
            "subcategory":"Household Appliances",
            "type":"Retail Goods"
        }
    ],
    "sg:phone":"+44 161 926 8150",
    "sg:postcode":"WA14 5EL",
    "sg:province":"Cheshire",
    "sg:tags":[
        "electrical"
    ],
    "wof:name":"Ace Engineering",
    "wof:placetype":"venue"
},
  "geometry": {"coordinates":[-2.354334,53.400768],"type":"Point"}
}