{
  "type": "Feature",
  "properties": {
    "addr:full":"Rood End Road, Warley Birmingham West Midlands B69 4HN",
    "addr:postcode":"b69 4hn",
    "addr:street":"Rood End Road",
    "iso:country":"GB",
    "sg:address":"Rood End Road, Warley",
    "sg:city":"Birmingham",
    "sg:classifiers":[
        {
            "category":"Manufacturing",
            "subcategory":"Signs",
            "type":"Manufacturing & Wholesale Goods"
        }
    ],
    "sg:postcode":"B69 4HN",
    "sg:province":"West Midlands",
    "sg:tags":[
        "maker"
    ],
    "wof:name":"P J Wilkes Signs",
    "wof:placetype":"venue"
},
  "geometry": {"coordinates":[-2.0001,52.494461],"type":"Point"}
}