{
  "type": "Feature",
  "properties": {
    "addr:full":"Unit 6 6 Fieldings Rd Waltham Cross Essex EN8 9TL",
    "addr:housenumber":"unit;6",
    "addr:postcode":"en8 9tl",
    "addr:street":"Fieldings Rd;Cross",
    "iso:country":"GB",
    "sg:address":"Unit 6 6 Fieldings Rd",
    "sg:city":"Waltham Cross",
    "sg:classifiers":[
        {
            "category":"Retail",
            "subcategory":"Auto Repair",
            "type":"Services"
        }
    ],
    "sg:postcode":"EN8 9TL",
    "sg:province":"Essex",
    "sg:tags":[
        "modification",
        "garage"
    ],
    "wof:name":"Tilley,Geoff,",
    "wof:placetype":"venue"
},
  "geometry": {"coordinates":[-0.02432,51.708744],"type":"Point"}
}