{
  "type": "Feature",
  "properties": {
    "iso:country":"GB",
    "sg:address":"14 Overmead",
    "sg:city":"Shoreham-by-sea",
    "sg:classifiers":[
        {
            "category":"Education",
            "subcategory":"Special Training",
            "type":"Public Place"
        }
    ],
    "sg:postcode":"BN43 5NS",
    "sg:province":"West Sussex",
    "sg:tags":[
        "product",
        "centre"
    ],
    "wof:name":"D T P Computer Training",
    "wof:placetype":"venue"
},
  "geometry": {"coordinates":[-0.27712,50.837353],"type":"Point"}
}