{
  "type": "Feature",
  "properties": {
    "iso:country":"GB",
    "sg:address":"132 Hayocks Road",
    "sg:city":"Stevenston",
    "sg:classifiers":[
        {
            "category":"Food & Beverages",
            "subcategory":"Fruits & Vegetables",
            "type":"Retail Goods"
        },
        {
            "category":"Food & Beverages",
            "subcategory":"Groceries & Convenience Stores",
            "type":"Retail Goods"
        }
    ],
    "sg:phone":"+44 1294 603528",
    "sg:postcode":"KA20 4DR",
    "sg:province":"North Ayrshire",
    "sg:tags":[
        "grocer",
        "greengrocer"
    ],
    "wof:name":"Hoyocks Stores",
    "wof:placetype":"venue"
},
  "geometry": {"coordinates":[-4.744965,55.648544],"type":"Point"}
}