{
  "type": "Feature",
  "properties": {
    "addr:full":"The Hall, Thorpe St, Raunds Wellingborough Northamptonshire NN9 6LS",
    "addr:postcode":"nn9 6ls",
    "addr:street":"Thorpe St",
    "iso:country":"GB",
    "sg:address":"The Hall, Thorpe St, Raunds",
    "sg:city":"Wellingborough",
    "sg:classifiers":[
        {
            "category":"Government",
            "subcategory":"Office",
            "type":"Public Place"
        }
    ],
    "sg:phone":"+44 1933 622087",
    "sg:postcode":"NN9 6LS",
    "sg:province":"Northamptonshire",
    "sg:tags":[
        "local"
    ],
    "wof:name":"Raunds Town Council",
    "wof:placetype":"venue"
},
  "geometry": {"coordinates":[-0.5468440056,52.3433532715],"type":"Point"}
}