{
  "type": "Feature",
  "properties": {
    "iso:country":"GB",
    "sg:address":"43 St Stephens Road",
    "sg:city":"West Bromwich",
    "sg:classifiers":[
        {
            "category":"Organizations",
            "subcategory":"Community Association",
            "type":"Services"
        }
    ],
    "sg:postcode":"B71 4LR",
    "sg:province":"West Midlands",
    "sg:tags":[
        "associations",
        "housing",
        "co-operatives",
        "society",
        "trust",
        "societies"
    ],
    "wof:name":"North Smethwick Housing Development Trust",
    "wof:placetype":"venue"
},
  "geometry": {"coordinates":[-1.9625869989,52.5074462891],"type":"Point"}
}