{
  "type": "Feature",
  "properties": {
    "iso:country":"GB",
    "sg:address":"Unit 5 Raans Road",
    "sg:city":"Amersham",
    "sg:classifiers":[
        {
            "category":"Manufacturing",
            "subcategory":"Food",
            "type":"Manufacturing & Wholesale Goods"
        },
        {
            "category":"Food & Beverages",
            "subcategory":"Supermarket",
            "type":"Retail Goods"
        }
    ],
    "sg:phone":"+44 1494 721552",
    "sg:postcode":"HP6 6HU",
    "sg:province":"Buckinghamshire",
    "sg:tags":[
        "frozen",
        "product",
        "manufacturer"
    ],
    "sg:website":"http://www.kerryfoods.co.uk",
    "wof:name":"Kerry Foods Ltd",
    "wof:placetype":"venue"
},
  "geometry": {"coordinates":[-0.588944,51.673737],"type":"Point"}
}