{
  "type": "Feature",
  "properties": {
    "addr:full":"Unit 3 Phase 3, Buntsford Park Road Bromsgrove Worcestershire B60 3DX",
    "addr:housenumber":"unit 3 phase 3",
    "addr:postcode":"b60 3dx",
    "addr:street":"Buntsford Park Road",
    "iso:country":"GB",
    "sg:address":"Unit 3 Phase 3, Buntsford Park Road",
    "sg:city":"Bromsgrove",
    "sg:classifiers":[
        {
            "category":"Autos & Motor Vehicles",
            "subcategory":"Auto Supplies",
            "type":"Retail Goods"
        },
        {
            "category":"Professional",
            "subcategory":"Detective & Security Services",
            "type":"Services"
        }
    ],
    "sg:phone":"+44 1527 575729",
    "sg:postcode":"B60 3DX",
    "sg:province":"Worcestershire",
    "sg:tags":[
        "car",
        "windscreen"
    ],
    "wof:name":"Fastfit Nationwide Ltd.",
    "wof:placetype":"venue"
},
  "geometry": {"coordinates":[-2.06407,52.315281],"type":"Point"}
}