{
  "type": "Feature",
  "properties": {
    "addr:full":"9 Market Square, Toddington Dunstable Bedfordshire LU5 6BP",
    "addr:housenumber":"9",
    "addr:postcode":"lu5 6bp",
    "addr:street":"Market Square",
    "iso:country":"GB",
    "sg:address":"9 Market Square, Toddington",
    "sg:city":"Dunstable",
    "sg:classifiers":[
        {
            "category":"Education",
            "subcategory":"Library",
            "type":"Public Place"
        },
        {
            "category":"Government",
            "subcategory":"Office",
            "type":"Public Place"
        }
    ],
    "sg:phone":"+44 1525 873626",
    "sg:postcode":"LU5 6BP",
    "sg:province":"Bedfordshire",
    "sg:tags":[
        "book",
        "local"
    ],
    "wof:name":"Toddington Library",
    "wof:placetype":"venue"
},
  "geometry": {"coordinates":[-0.531539,51.949108],"type":"Point"}
}