{
  "type": "Feature",
  "properties": {
    "iso:country":"GB",
    "sg:address":"218 Witan St",
    "sg:city":"London",
    "sg:classifiers":[
        {
            "category":"Manufacturing",
            "subcategory":"Wood Products",
            "type":"Manufacturing & Wholesale Goods"
        }
    ],
    "sg:postcode":"E2 6JX",
    "sg:province":"Greater London",
    "sg:tags":[
        "maker",
        "cabinet"
    ],
    "wof:name":"S & A Reproductions",
    "wof:placetype":"venue"
},
  "geometry": {"coordinates":[-0.05654,51.52544],"type":"Point"}
}