{
  "type": "Feature",
  "properties": {
    "addr:full":"218 Witan St London Greater London E2 6JX",
    "addr:housenumber":"218",
    "addr:postcode":"e2 6jx",
    "addr:street":"Witan St",
    "iso:country":"GB",
    "sg:address":"218 Witan St",
    "sg:city":"London",
    "sg:classifiers":[
        {
            "category":"Manufacturing",
            "subcategory":"Wood Products",
            "type":"Manufacturing & Wholesale Goods"
        }
    ],
    "sg:postcode":"E2 6JX",
    "sg:province":"Greater London",
    "sg:tags":[
        "maker",
        "cabinet"
    ],
    "wof:name":"S & A Reproductions",
    "wof:placetype":"venue"
},
  "geometry": {"coordinates":[-0.05654,51.52544],"type":"Point"}
}