{
  "type": "Feature",
  "properties": {
    "iso:country":"GB",
    "sg:address":"47 Vaughan Road",
    "sg:city":"Manchester",
    "sg:classifiers":[
        {
            "category":"Building & Trades",
            "subcategory":"Construction",
            "type":"Services"
        }
    ],
    "sg:postcode":"M21 0ZL",
    "sg:province":"Cheshire",
    "sg:tags":[
        "decorator",
        "painter"
    ],
    "wof:name":"J & B Decorating Contractors",
    "wof:placetype":"venue"
},
  "geometry": {"coordinates":[-2.262879,53.439987],"type":"Point"}
}