{
  "type": "Feature",
  "properties": {
    "addr:full":"Unit 39 Ketley Business Park Telford Shropshire TF1 4JD",
    "addr:housenumber":"unit 39 ketley business park",
    "addr:postcode":"tf1 4jd",
    "iso:country":"GB",
    "sg:address":"Unit 39 Ketley Business Park",
    "sg:city":"Telford",
    "sg:classifiers":[
        {
            "category":"Home & Garden",
            "subcategory":"Building Materials",
            "type":"Retail Goods"
        }
    ],
    "sg:phone":"+44 1952 250000",
    "sg:postcode":"TF1 4JD",
    "sg:province":"Shropshire",
    "sg:tags":[
        "window",
        "frame"
    ],
    "wof:name":"Gemini Windows",
    "wof:placetype":"venue"
},
  "geometry": {"coordinates":[-2.482132,52.693996],"type":"Point"}
}