{
  "type": "Feature",
  "properties": {
    "iso:country":"GB",
    "sg:address":"7 Kootenay Avenue, Thornhill Park",
    "sg:city":"Southampton",
    "sg:classifiers":[
        {
            "category":"Personal",
            "type":"Services"
        }
    ],
    "sg:phone":"+44 23 8046 3545",
    "sg:postcode":"SO18 5RF",
    "sg:province":"Hampshire",
    "sg:tags":[
        "wedding"
    ],
    "wof:name":"Wedding Favours by Forget-Me-Knot",
    "wof:placetype":"venue"
},
  "geometry": {"coordinates":[-1.331124,50.915894],"type":"Point"}
}