{
  "type": "Feature",
  "properties": {
    "iso:country":"GB",
    "sg:address":"335 Watford Road",
    "sg:city":"St Albans",
    "sg:classifiers":[
        {
            "category":"Utilities",
            "subcategory":"Refuse",
            "type":"Services"
        }
    ],
    "sg:postcode":"AL2 3DA",
    "sg:province":"Hertfordshire",
    "sg:tags":[
        "disposal",
        "waste"
    ],
    "wof:name":"Enstone Environmental Management Ltd.",
    "wof:placetype":"venue"
},
  "geometry": {"coordinates":[-0.3595220149,51.7275047302],"type":"Point"}
}