{
  "type": "Feature",
  "properties": {
    "iso:country":"GB",
    "sg:address":"78 Chapel Lane",
    "sg:city":"Wilmslow",
    "sg:classifiers":[
        {
            "category":"Home & Garden",
            "subcategory":"Household Appliances",
            "type":"Retail Goods"
        }
    ],
    "sg:postcode":"SK9 5JH",
    "sg:province":"Cheshire",
    "sg:tags":[
        "electrical"
    ],
    "wof:name":"Wilmslow Electrical Services",
    "wof:placetype":"venue"
},
  "geometry": {"coordinates":[-2.243647,53.32235],"type":"Point"}
}