{
  "type": "Feature",
  "properties": {
    "addr:full":"Cartref, Trefgarn Owen Haverfordwest Pembrokeshire SA62 6NE",
    "addr:postcode":"sa62 6ne",
    "addr:street":"Trefgarn Owen",
    "iso:country":"GB",
    "sg:address":"Cartref, Trefgarn Owen",
    "sg:city":"Haverfordwest",
    "sg:classifiers":[
        {
            "category":"Home & Garden",
            "subcategory":"Hardware",
            "type":"Retail Goods"
        }
    ],
    "sg:postcode":"SA62 6NE",
    "sg:province":"Pembrokeshire",
    "sg:tags":[
        "lawnmowers",
        "machinery"
    ],
    "wof:name":"M M Carter",
    "wof:placetype":"venue"
},
  "geometry": {"coordinates":[-5.1002540588,51.8871307373],"type":"Point"}
}