{
  "type": "Feature",
  "properties": {
    "addr:full":"19 Samford Street London Greater London NW8 8ER",
    "addr:housenumber":"19",
    "addr:postcode":"nw8 8er",
    "addr:street":"Samford Street",
    "iso:country":"GB",
    "sg:address":"19 Samford Street",
    "sg:city":"London",
    "sg:classifiers":[
        {
            "category":"Organizations",
            "subcategory":"Non-profit Organization",
            "type":"Services"
        }
    ],
    "sg:phone":"+44 20 7724 9746",
    "sg:postcode":"NW8 8ER",
    "sg:province":"Greater London",
    "sg:tags":[
        "organisation",
        "voluntary",
        "charity"
    ],
    "wof:name":"Marylebone Bangladesh Society",
    "wof:placetype":"venue"
},
  "geometry": {"coordinates":[-0.1705629975,51.5240440369],"type":"Point"}
}