{
  "type": "Feature",
  "properties": {
    "addr:full":"24 The Hill Avenue Worcester Worcestershire WR5 2AW",
    "addr:housenumber":"24",
    "addr:postcode":"wr5 2aw",
    "addr:street":"The Hill Avenue",
    "iso:country":"GB",
    "sg:address":"24 The Hill Avenue",
    "sg:city":"Worcester",
    "sg:classifiers":[
        {
            "category":"Retail",
            "subcategory":"Storage",
            "type":"Services"
        }
    ],
    "sg:postcode":"WR5 2AW",
    "sg:province":"Worcestershire",
    "sg:tags":[
        "household",
        "removal"
    ],
    "wof:name":"Me & My Van Services",
    "wof:placetype":"venue"
},
  "geometry": {"coordinates":[-2.2162330151,52.1826210022],"type":"Point"}
}