{
  "type": "Feature",
  "properties": {
    "addr:full":"14 Granville Clo Belper Derbyshire DE56 4FY",
    "addr:housenumber":"14",
    "addr:postcode":"de56 4fy",
    "addr:street":"Granville Clo Belper",
    "iso:country":"GB",
    "sg:address":"14 Granville Clo",
    "sg:city":"Belper",
    "sg:classifiers":[
        {
            "category":"Professional",
            "subcategory":"Testing Lab",
            "type":"Services"
        }
    ],
    "sg:phone":"+44 1332 840569",
    "sg:postcode":"DE56 4FY",
    "sg:province":"Derbyshire",
    "sg:tags":[
        "inspection",
        "calibration"
    ],
    "wof:name":"Squires Metalurgical Engineering Consultancy",
    "wof:placetype":"venue"
},
  "geometry": {"coordinates":[-1.4921870232,52.9836807251],"type":"Point"}
}