{
  "type": "Feature",
  "properties": {
    "addr:full":"12a Bondgate Darlington Durham DL3 7JE",
    "addr:housenumber":"12a",
    "addr:postcode":"dl3 7je",
    "addr:street":"Bondgate Darlington",
    "iso:country":"GB",
    "sg:address":"12a Bondgate",
    "sg:city":"Darlington",
    "sg:classifiers":[
        {
            "category":"Organizations",
            "subcategory":"Non-profit Organization",
            "type":"Services"
        }
    ],
    "sg:postcode":"DL3 7JE",
    "sg:province":"Durham",
    "sg:tags":[
        "organisation",
        "voluntary",
        "charity"
    ],
    "wof:name":"Barnardo's",
    "wof:placetype":"venue"
},
  "geometry": {"coordinates":[-1.5561130047,54.5262107849],"type":"Point"}
}