{
  "type": "Feature",
  "properties": {
    "iso:country":"GB",
    "sg:address":"59 Kingston Rd",
    "sg:city":"Poole",
    "sg:classifiers":[
        {
            "category":"Farming",
            "subcategory":"Fish & Marine Products",
            "type":"Manufacturing & Wholesale Goods"
        }
    ],
    "sg:postcode":"BH15 2LR",
    "sg:province":"Dorset",
    "sg:tags":[
        "fishmonger"
    ],
    "wof:name":"Linham,Richard J,",
    "wof:placetype":"venue"
},
  "geometry": {"coordinates":[-1.9751540422,50.7238121033],"type":"Point"}
}