{
  "type": "Feature",
  "properties": {
    "iso:country":"GB",
    "sg:address":"Baskervilles, Roman Road, Margaretting",
    "sg:city":"Ingatestone",
    "sg:classifiers":[
        {
            "category":"Transit Center",
            "subcategory":"Passenger",
            "type":"Transportation"
        },
        {
            "category":"Retail",
            "subcategory":"Pet Boarding",
            "type":"Services"
        }
    ],
    "sg:phone":"+44 1277 354715",
    "sg:postcode":"CM4 0EF",
    "sg:province":"Essex",
    "sg:tags":[
        "kennel",
        "catteries"
    ],
    "wof:name":"BASKERVILLES LTD",
    "wof:placetype":"venue"
},
  "geometry": {"coordinates":[0.383585,51.669922],"type":"Point"}
}