{
  "type": "Feature",
  "properties": {
    "iso:country":"GB",
    "sg:address":"81 Fernwood Drive",
    "sg:city":"Rugeley",
    "sg:classifiers":[
        {
            "category":"Shopping",
            "subcategory":"News",
            "type":"Retail Goods"
        }
    ],
    "sg:phone":"+44 1889 578522",
    "sg:postcode":"WS15 2PY",
    "sg:province":"Staffordshire",
    "sg:tags":[
        "newsagent"
    ],
    "wof:name":"Martin the Newsagent",
    "wof:placetype":"venue"
},
  "geometry": {"coordinates":[-1.9474639893,52.7658081055],"type":"Point"}
}