{
  "type": "Feature",
  "properties": {
    "addr:full":"40-42 Carmichael Street, Govan Glasgow Glasgow City G51 2QT",
    "addr:housenumber":"40-42",
    "addr:postcode":"g51 2qt",
    "addr:street":"Carmichael Street",
    "iso:country":"GB",
    "sg:address":"40-42 Carmichael Street, Govan",
    "sg:city":"Glasgow",
    "sg:classifiers":[
        {
            "category":"Freight",
            "type":"Transportation"
        }
    ],
    "sg:phone":"+44 141 445 2574",
    "sg:postcode":"G51 2QT",
    "sg:province":"Glasgow City",
    "sg:tags":[
        "haulage",
        "road"
    ],
    "wof:name":"John Smillie Ltd.",
    "wof:placetype":"venue"
},
  "geometry": {"coordinates":[-4.3016319275,55.8564071655],"type":"Point"}
}