{
  "type": "Feature",
  "properties": {
    "addr:full":"St Oswalds Hebburn Tyne and Wear NE31 1HT",
    "addr:postcode":"ne31 1ht",
    "addr:street":"St",
    "iso:country":"GB",
    "sg:address":"St Oswalds",
    "sg:city":"Hebburn",
    "sg:classifiers":[
        {
            "category":"Place Of Worship",
            "type":"Public Place"
        },
        {
            "category":"Education",
            "subcategory":"School",
            "type":"Public Place"
        },
        {
            "category":"Government",
            "subcategory":"Office",
            "type":"Public Place"
        }
    ],
    "sg:phone":"+44 191 483 2844",
    "sg:postcode":"NE31 1HT",
    "sg:province":"Tyne and Wear",
    "sg:tags":[
        "local",
        "authority"
    ],
    "wof:name":"St Oswald's C of E Junior Mixed & Infant School",
    "wof:placetype":"venue"
},
  "geometry": {"coordinates":[-1.5116980076,54.9738502502],"type":"Point"}
}