{
  "type": "Feature",
  "properties": {
    "iso:country":"GB",
    "sg:address":"West Side, North Littleton",
    "sg:city":"Evesham",
    "sg:classifiers":[
        {
            "category":"Government",
            "subcategory":"Post Office",
            "type":"Public Place"
        }
    ],
    "sg:phone":"+44 1386 830690",
    "sg:postcode":"WR11 5QP",
    "sg:province":"Gloucestershire",
    "wof:name":"North Littleton PO",
    "wof:placetype":"venue"
},
  "geometry": {"coordinates":[-1.943969,52.106392],"type":"Point"}
}