{
  "type": "Feature",
  "properties": {
    "addr:full":"120 Elmore Green Road Walsall Staffordshire WS3 2HS",
    "addr:housenumber":"120",
    "addr:postcode":"ws3 2hs",
    "addr:street":"Elmore Green Road",
    "iso:country":"GB",
    "sg:address":"120 Elmore Green Road",
    "sg:city":"Walsall",
    "sg:classifiers":[
        {
            "category":"Organizations",
            "subcategory":"Membership Organization",
            "type":"Services"
        }
    ],
    "sg:phone":"+44 1922 405859",
    "sg:postcode":"WS3 2HS",
    "sg:province":"Staffordshire",
    "sg:tags":[
        "club"
    ],
    "wof:name":"The Royal Naval Association Club",
    "wof:placetype":"venue"
},
  "geometry": {"coordinates":[-2.0092020035,52.6172103882],"type":"Point"}
}