{
  "type": "Feature",
  "properties": {
    "iso:country":"GB",
    "sg:address":"St Michaels Hospital, Cawston Road, Aylsham",
    "sg:city":"Norwich",
    "sg:classifiers":[
        {
            "category":"Health Services",
            "subcategory":"Hospital",
            "type":"Services"
        }
    ],
    "sg:phone":"+44 1263 733096",
    "sg:postcode":"NR11 6NA",
    "sg:province":"Norfolk",
    "wof:name":"Norfolk Arthritis Register",
    "wof:placetype":"venue"
},
  "geometry": {"coordinates":[1.2503540516,52.7950668335],"type":"Point"}
}