{
  "type": "Feature",
  "properties": {
    "addr:full":"23a Brightside Avenue Staines Berkshire TW18 1NE",
    "addr:housenumber":"23a",
    "addr:postcode":"tw18 1ne",
    "addr:street":"Brightside Avenue",
    "iso:country":"GB",
    "sg:address":"23a Brightside Avenue",
    "sg:city":"Staines",
    "sg:classifiers":[
        {
            "category":"Building & Trades",
            "subcategory":"Construction",
            "type":"Services"
        }
    ],
    "sg:phone":"+44 1784 459519",
    "sg:postcode":"TW18 1NE",
    "sg:province":"Berkshire",
    "sg:tags":[
        "decorator",
        "painter"
    ],
    "wof:name":"F L Decorating Services",
    "wof:placetype":"venue"
},
  "geometry": {"coordinates":[-0.488409996,51.4215888977],"type":"Point"}
}