{
  "type": "Feature",
  "properties": {
    "iso:country":"GB",
    "sg:address":"7 Warren Place",
    "sg:city":"Hertford",
    "sg:classifiers":[
        {
            "category":"Professional",
            "subcategory":"Art Services",
            "type":"Services"
        }
    ],
    "sg:postcode":"SG14 1BB",
    "sg:province":"Hertfordshire",
    "sg:tags":[
        "photographer"
    ],
    "wof:name":"D Createur Photographie",
    "wof:placetype":"venue"
},
  "geometry": {"coordinates":[-0.076427,51.805511],"type":"Point"}
}