{
  "type": "Feature",
  "properties": {
    "addr:full":"1 Bridge Street Brigg Lincolnshire DN20 8LN",
    "addr:housenumber":"1",
    "addr:postcode":"dn20 8ln",
    "addr:street":"Bridge Street",
    "iso:country":"GB",
    "sg:address":"1 Bridge Street",
    "sg:city":"Brigg",
    "sg:classifiers":[
        {
            "category":"Bars & Pubs",
            "type":"Food & Drink"
        }
    ],
    "sg:postcode":"DN20 8LN",
    "sg:province":"Lincolnshire",
    "sg:tags":[
        "pubs",
        "inn"
    ],
    "wof:name":"Nelthorpe Arms",
    "wof:placetype":"venue"
},
  "geometry": {"coordinates":[-0.495866,53.55143],"type":"Point"}
}