{
  "type": "Feature",
  "properties": {
    "iso:country":"GB",
    "sg:address":"141 High Street",
    "sg:city":"Edenbridge",
    "sg:classifiers":[
        {
            "category":"Insurance",
            "subcategory":"Insurance Agent",
            "type":"Services"
        }
    ],
    "sg:phone":"+44 1732 867727",
    "sg:postcode":"TN8 5AX",
    "sg:province":"East Sussex",
    "wof:name":"National Farmers Union",
    "wof:placetype":"venue"
},
  "geometry": {"coordinates":[0.066288,51.193378],"type":"Point"}
}