{
  "type": "Feature",
  "properties": {
    "addr:full":"239 Sandycombe Road, Kew Gardens Richmond Greater London TW9 2EW",
    "addr:housenumber":"239",
    "addr:postcode":"tw9 2ew",
    "addr:street":"Sandycombe Road",
    "iso:country":"GB",
    "sg:address":"239 Sandycombe Road, Kew Gardens",
    "sg:city":"Richmond",
    "sg:classifiers":[
        {
            "category":"Home & Garden",
            "subcategory":"Home Furnishings",
            "type":"Retail Goods"
        }
    ],
    "sg:postcode":"TW9 2EW",
    "sg:province":"Greater London",
    "sg:tags":[
        "blind",
        "curtain",
        "fitting"
    ],
    "wof:name":"Attitudes Interior Design",
    "wof:placetype":"venue"
},
  "geometry": {"coordinates":[-0.286482,51.473179],"type":"Point"}
}