{
  "type": "Feature",
  "properties": {
    "addr:full":"179 Hylton Road Sunderland Tyne and Wear SR4 7YE",
    "addr:housenumber":"179",
    "addr:postcode":"sr4 7ye",
    "addr:street":"Hylton Road",
    "iso:country":"GB",
    "sg:address":"179 Hylton Road",
    "sg:city":"Sunderland",
    "sg:classifiers":[
        {
            "category":"Fast Food",
            "type":"Food & Drink"
        }
    ],
    "sg:phone":"+44 191 567 2223",
    "sg:postcode":"SR4 7YE",
    "sg:province":"Tyne and Wear",
    "sg:tags":[
        "away",
        "take"
    ],
    "wof:name":"Curry Express",
    "wof:placetype":"venue"
},
  "geometry": {"coordinates":[-1.406003,54.905651],"type":"Point"}
}