{
  "type": "Feature",
  "properties": {
    "iso:country":"GB",
    "sg:address":"Kirklands, Barnsley Road, South Kirkby",
    "sg:city":"Pontefract",
    "sg:classifiers":[
        {
            "category":"Bus Charters",
            "type":"Transportation"
        }
    ],
    "sg:phone":"+44 1977 647454",
    "sg:postcode":"WF9 3LA",
    "sg:province":"West Yorkshire",
    "sg:tags":[
        "coach"
    ],
    "wof:name":"E & J M Brown",
    "wof:placetype":"venue"
},
  "geometry": {"coordinates":[-1.312568,53.594608],"type":"Point"}
}