{
  "type": "Feature",
  "properties": {
    "addr:full":"Hillside Cott, Gambles La Cheltenham Gloucestershire GL52 9PU",
    "addr:postcode":"gl52 9pu",
    "addr:street":"Gambles La Cheltenham",
    "iso:country":"GB",
    "sg:address":"Hillside Cott, Gambles La",
    "sg:city":"Cheltenham",
    "sg:classifiers":[
        {
            "category":"Building & Trades",
            "subcategory":"Construction",
            "type":"Services"
        }
    ],
    "sg:postcode":"GL52 9PU",
    "sg:province":"Gloucestershire",
    "sg:tags":[
        "builder"
    ],
    "wof:name":"Clapham,L J,",
    "wof:placetype":"venue"
},
  "geometry": {"coordinates":[-2.0395059586,51.943447113],"type":"Point"}
}