{
  "type": "Feature",
  "properties": {
    "addr:full":"13a Hanger Lane London Greater London W5 3HH",
    "addr:housenumber":"13a",
    "addr:postcode":"w5 3hh",
    "addr:street":"Hanger Lane",
    "iso:country":"GB",
    "sg:address":"13a Hanger Lane",
    "sg:city":"London",
    "sg:classifiers":[
        {
            "category":"Travel",
            "subcategory":"Hotels & Motels",
            "type":"Entertainment"
        }
    ],
    "sg:phone":"+44 20 8993 3947",
    "sg:postcode":"W5 3HH",
    "sg:province":"Greater London",
    "sg:tags":[
        "house",
        "guest"
    ],
    "wof:name":"Hotspur Lodge",
    "wof:placetype":"venue"
},
  "geometry": {"coordinates":[-0.291700989,51.5125999451],"type":"Point"}
}