{
  "type": "Feature",
  "properties": {
    "iso:country":"GB",
    "sg:address":"40 Regent Place",
    "sg:city":"Rugby",
    "sg:classifiers":[
        {
            "category":"Health Services",
            "subcategory":"Podiatrist",
            "type":"Services"
        }
    ],
    "sg:phone":"+44 1788 574870",
    "sg:postcode":"CV21 2PN",
    "sg:province":"Warwickshire",
    "sg:tags":[
        "podiatrists",
        "chiropodist"
    ],
    "wof:name":"Anne Hindmarch M.S.S.Ch M.B.Ch.A",
    "wof:placetype":"venue"
},
  "geometry": {"coordinates":[-1.2610019445,52.3753242493],"type":"Point"}
}