{
  "type": "Feature",
  "properties": {
    "addr:full":"Hall Road Maldon Essex CM9 4LA",
    "addr:postcode":"cm9 4la",
    "addr:street":"Hall Road",
    "iso:country":"GB",
    "sg:address":"Hall Road",
    "sg:city":"Maldon",
    "sg:classifiers":[
        {
            "category":"Shopping",
            "subcategory":"Computers & Home Electronics",
            "type":"Retail Goods"
        }
    ],
    "sg:phone":"+44 1621 879900",
    "sg:postcode":"CM9 4LA",
    "sg:province":"Essex",
    "wof:name":"Armagard Ltd.",
    "wof:placetype":"venue"
},
  "geometry": {"coordinates":[0.6899279952,51.7381134033],"type":"Point"}
}