{
  "type": "Feature",
  "properties": {
    "iso:country":"GB",
    "sg:address":"Unit 15 Halesworth Business Park, Norwich Road",
    "sg:city":"Halesworth",
    "sg:classifiers":[
        {
            "category":"Manufacturing",
            "subcategory":"Signs",
            "type":"Manufacturing & Wholesale Goods"
        }
    ],
    "sg:postcode":"IP19 8QJ",
    "sg:province":"Suffolk",
    "sg:tags":[
        "commercial",
        "maker"
    ],
    "wof:name":"E P S Transfers",
    "wof:placetype":"venue"
},
  "geometry": {"coordinates":[1.503773,52.344131],"type":"Point"}
}