{
  "type": "Feature",
  "properties": {
    "addr:full":"The Cedars, North Rd Horncastle Lincolnshire LN9 6QH",
    "addr:postcode":"ln9 6qh",
    "addr:street":"North Rd",
    "iso:country":"GB",
    "sg:address":"The Cedars, North Rd",
    "sg:city":"Horncastle",
    "sg:classifiers":[
        {
            "category":"Farming",
            "subcategory":"Farm",
            "type":"Manufacturing & Wholesale Goods"
        }
    ],
    "sg:phone":"+44 1507 533661",
    "sg:postcode":"LN9 6QH",
    "sg:province":"Lincolnshire",
    "sg:tags":[
        "mixed",
        "crop"
    ],
    "wof:name":"A C & K N Simons",
    "wof:placetype":"venue"
},
  "geometry": {"coordinates":[-0.114765,53.208523],"type":"Point"}
}