{
  "type": "Feature",
  "properties": {
    "addr:full":"Fordbridge Road Birmingham West Midlands B37 6LW",
    "addr:postcode":"b37 6lw",
    "addr:street":"Fordbridge Road",
    "iso:country":"GB",
    "sg:address":"Fordbridge Road",
    "sg:city":"Birmingham",
    "sg:classifiers":[
        {
            "category":"Education",
            "subcategory":"School",
            "type":"Public Place"
        },
        {
            "category":"Government",
            "subcategory":"Office",
            "type":"Public Place"
        }
    ],
    "sg:phone":"+44 121 770 3168",
    "sg:postcode":"B37 6LW",
    "sg:province":"West Midlands",
    "sg:tags":[
        "local",
        "authority"
    ],
    "wof:name":"St Anthony's R C Primary School",
    "wof:placetype":"venue"
},
  "geometry": {"coordinates":[-1.747014,52.490891],"type":"Point"}
}