{
  "type": "Feature",
  "properties": {
    "iso:country":"GB",
    "sg:address":"The Voluntary Action Centre, 7 Mansfield Road",
    "sg:city":"Nottingham",
    "sg:classifiers":[
        {
            "category":"Organizations",
            "subcategory":"Non-profit Organization",
            "type":"Services"
        }
    ],
    "sg:phone":"+44 115 934 8400",
    "sg:postcode":"NG1 3FB",
    "sg:province":"Nottinghamshire",
    "sg:tags":[
        "organisation",
        "voluntary",
        "charity"
    ],
    "wof:name":"Nottingham Council for Voluntary Service",
    "wof:placetype":"venue"
},
  "geometry": {"coordinates":[-1.143924,52.949226],"type":"Point"}
}