{
  "type": "Feature",
  "properties": {
    "addr:full":"Leagate Road, Gipsey Bridge Boston Lincolnshire PE22 7DA",
    "addr:postcode":"pe22 7da",
    "addr:street":"Leagate Road Gipsey Bridge",
    "iso:country":"GB",
    "sg:address":"Leagate Road, Gipsey Bridge",
    "sg:city":"Boston",
    "sg:classifiers":[
        {
            "category":"Professional",
            "subcategory":"Engineering",
            "type":"Services"
        }
    ],
    "sg:phone":"+44 1205 280788",
    "sg:postcode":"PE22 7DA",
    "sg:province":"Lincolnshire",
    "sg:tags":[
        "agricultural",
        "engineer"
    ],
    "wof:name":"B D Engineering",
    "wof:placetype":"venue"
},
  "geometry": {"coordinates":[-0.071408,53.013897],"type":"Point"}
}