{
  "type": "Feature",
  "properties": {
    "addr:full":"105-107 Commercial Road Poole Dorset BH14 0JD",
    "addr:housenumber":"105-107",
    "addr:postcode":"bh14 0jd",
    "addr:street":"Commercial Road",
    "iso:country":"GB",
    "sg:address":"105-107 Commercial Road",
    "sg:city":"Poole",
    "sg:classifiers":[
        {
            "category":"Professional",
            "subcategory":"Printing & Photocopies",
            "type":"Services"
        }
    ],
    "sg:phone":"+44 1202 740321",
    "sg:postcode":"BH14 0JD",
    "sg:province":"Dorset",
    "sg:tags":[
        "printer"
    ],
    "wof:name":"Poole Instant Print",
    "wof:placetype":"venue"
},
  "geometry": {"coordinates":[-1.952647,50.72324],"type":"Point"}
}