{
  "type": "Feature",
  "properties": {
    "iso:country":"GB",
    "sg:address":"Mill Of Chon House, Kinlochard",
    "sg:city":"Stirling",
    "sg:classifiers":[
        {
            "category":"Building & Trades",
            "subcategory":"Plumbing",
            "type":"Services"
        }
    ],
    "sg:postcode":"FK8 3TL",
    "sg:province":"Stirling",
    "sg:tags":[
        "heating"
    ],
    "wof:name":"John Boyd Plumbing & Heating Contractors",
    "wof:placetype":"venue"
},
  "geometry": {"coordinates":[-4.4926338196,56.1886444092],"type":"Point"}
}