{
  "type": "Feature",
  "properties": {
    "addr:full":"36 Dern Gate Northampton Northamptonshire NN1 1UH",
    "addr:housenumber":"36",
    "addr:postcode":"nn1 1uh",
    "addr:street":"Dern Gate",
    "iso:country":"GB",
    "sg:address":"36 Dern Gate",
    "sg:city":"Northampton",
    "sg:classifiers":[
        {
            "category":"Real Estate",
            "subcategory":"Surveying",
            "type":"Services"
        }
    ],
    "sg:phone":"+44 1604 621004",
    "sg:postcode":"NN1 1UH",
    "sg:province":"Northamptonshire",
    "sg:tags":[
        "surveyor",
        "quantity"
    ],
    "wof:name":"F Maitland Partnership",
    "wof:placetype":"venue"
},
  "geometry": {"coordinates":[-0.891776979,52.2360115051],"type":"Point"}
}