{
  "type": "Feature",
  "properties": {
    "addr:full":"1 Upland Court Road Romford Essex RM3 0TT",
    "addr:housenumber":"1",
    "addr:postcode":"rm3 0tt",
    "addr:street":"Upland Court Road",
    "iso:country":"GB",
    "sg:address":"1 Upland Court Road",
    "sg:city":"Romford",
    "sg:classifiers":[
        {
            "category":"Manufacturing",
            "subcategory":"Building Materials",
            "type":"Manufacturing & Wholesale Goods"
        }
    ],
    "sg:phone":"+44 1708 342680",
    "sg:postcode":"RM3 0TT",
    "sg:province":"Essex",
    "sg:tags":[
        "mnfr",
        "marble",
        "specialist"
    ],
    "wof:name":"Millheights",
    "wof:placetype":"venue"
},
  "geometry": {"coordinates":[0.230798,51.587921],"type":"Point"}
}