{
  "type": "Feature",
  "properties": {
    "addr:full":"221 Ferry Road Edinburgh City of Edinburgh EH6 4NN",
    "addr:housenumber":"221",
    "addr:postcode":"eh6 4nn",
    "addr:street":"Ferry Road",
    "iso:country":"GB",
    "sg:address":"221 Ferry Road",
    "sg:city":"Edinburgh",
    "sg:classifiers":[
        {
            "category":"Travel",
            "subcategory":"Hotels & Motels",
            "type":"Entertainment"
        }
    ],
    "sg:phone":"+44 131 477 7033",
    "sg:postcode":"EH6 4NN",
    "sg:province":"City of Edinburgh",
    "wof:name":"The Victoria Park Hotel",
    "wof:placetype":"venue"
},
  "geometry": {"coordinates":[-3.1923589706,55.9733695984],"type":"Point"}
}