{
  "type": "Feature",
  "properties": {
    "addr:full":"24 Lindale Garth Wakefield West Yorkshire WF2 0RW",
    "addr:housenumber":"24",
    "addr:postcode":"wf2 0rw",
    "addr:street":"Lindale Garth",
    "iso:country":"GB",
    "sg:address":"24 Lindale Garth",
    "sg:city":"Wakefield",
    "sg:classifiers":[
        {
            "category":"Bus Charters",
            "type":"Transportation"
        }
    ],
    "sg:phone":"+44 1924 375140",
    "sg:postcode":"WF2 0RW",
    "sg:province":"West Yorkshire",
    "sg:tags":[
        "hire",
        "coach"
    ],
    "wof:name":"Lunns Travel",
    "wof:placetype":"venue"
},
  "geometry": {"coordinates":[-1.5450149775,53.702293396],"type":"Point"}
}