{
  "type": "Feature",
  "properties": {
    "iso:country":"GB",
    "sg:address":"22-26 Worthing Road",
    "sg:city":"Horsham",
    "sg:classifiers":[
        {
            "category":"Manufacturing",
            "subcategory":"Rubber & Plastics",
            "type":"Manufacturing & Wholesale Goods"
        }
    ],
    "sg:phone":"+44 1403 264158",
    "sg:postcode":"RH12 1SL",
    "sg:province":"West Sussex",
    "sg:tags":[
        "supplier",
        "stockist"
    ],
    "wof:name":"Polymers International (U K) Ltd.",
    "wof:placetype":"venue"
},
  "geometry": {"coordinates":[-0.33404,51.062077],"type":"Point"}
}