{
  "type": "Feature",
  "properties": {
    "addr:full":"A23 Jobs Lane, Hickstead Haywards Heath East Sussex RH17 5NZ",
    "addr:postcode":"rh17 5nz",
    "addr:street":"Jobs Lane",
    "iso:country":"GB",
    "sg:address":"A23 Jobs Lane, Hickstead",
    "sg:city":"Haywards Heath",
    "sg:classifiers":[
        {
            "category":"Restaurant",
            "type":"Food & Drink"
        }
    ],
    "sg:phone":"+44 1444 881194",
    "sg:postcode":"RH17 5NZ",
    "sg:province":"East Sussex",
    "wof:name":"Little Chef",
    "wof:placetype":"venue"
},
  "geometry": {"coordinates":[-0.1985349953,50.9815216064],"type":"Point"}
}