{
  "type": "Feature",
  "properties": {
    "addr:full":"Unit B5 Elms Farm, Ullesthorpe Rd Lutterworth Leicestershire LE17 4LR",
    "addr:housenumber":"elms farm",
    "addr:postcode":"le17 4lr",
    "addr:street":"Ullesthorpe Rd",
    "iso:country":"GB",
    "sg:address":"Unit B5 Elms Farm, Ullesthorpe Rd",
    "sg:city":"Lutterworth",
    "sg:classifiers":[
        {
            "category":"Professional",
            "type":"Services"
        }
    ],
    "sg:phone":"+44 1455 553888",
    "sg:postcode":"LE17 4LR",
    "sg:province":"Leicestershire",
    "sg:tags":[
        "exhibition"
    ],
    "wof:name":"Elms Farm",
    "wof:placetype":"venue"
},
  "geometry": {"coordinates":[-1.224148035,52.4735221863],"type":"Point"}
}