{
  "type": "Feature",
  "properties": {
    "addr:full":"22a Old Road Bromyard Herefordshire HR7 4BQ",
    "addr:housenumber":"22a",
    "addr:postcode":"hr7 4bq",
    "addr:street":"Old Road",
    "iso:country":"GB",
    "sg:address":"22a Old Road",
    "sg:city":"Bromyard",
    "sg:classifiers":[
        {
            "category":"Organizations",
            "subcategory":"Non-profit Organization",
            "type":"Services"
        }
    ],
    "sg:phone":"+44 1885 488452",
    "sg:postcode":"HR7 4BQ",
    "sg:province":"Herefordshire",
    "sg:tags":[
        "charitable",
        "organisation",
        "voluntary",
        "charity"
    ],
    "wof:name":"Bromyard Community Transport",
    "wof:placetype":"venue"
},
  "geometry": {"coordinates":[-2.5100069046,52.1893806458],"type":"Point"}
}