{
  "type": "Feature",
  "properties": {
    "addr:full":"The Manor House, 12-14 Chapel Street, Devonport Plymouth Devon PL1 4DS",
    "addr:housenumber":"12-14",
    "addr:postcode":"pl1 4ds",
    "addr:street":"Chapel Street",
    "iso:country":"GB",
    "sg:address":"The Manor House, 12-14 Chapel Street, Devonport",
    "sg:city":"Plymouth",
    "sg:classifiers":[
        {
            "category":"Professional",
            "subcategory":"Computer Services",
            "type":"Services"
        }
    ],
    "sg:postcode":"PL1 4DS",
    "sg:province":"Devon",
    "sg:tags":[
        "consultant",
        "system",
        "software"
    ],
    "wof:name":"Paj Computing Ltd",
    "wof:placetype":"venue"
},
  "geometry": {"coordinates":[-4.174747,50.371777],"type":"Point"}
}