{
  "type": "Feature",
  "properties": {
    "iso:country":"GB",
    "sg:address":"210 Mill Road",
    "sg:city":"Cambridge",
    "sg:classifiers":[
        {
            "category":"Fast Food",
            "type":"Food & Drink"
        },
        {
            "category":"Cafe",
            "type":"Food & Drink"
        }
    ],
    "sg:phone":"+44 1223 576875",
    "sg:postcode":"CB1 3NF",
    "sg:province":"Cambridgeshire",
    "sg:tags":[
        "away",
        "snack",
        "bar",
        "take"
    ],
    "wof:name":"TOPKAPI",
    "wof:placetype":"venue"
},
  "geometry": {"coordinates":[0.144585,52.197502],"type":"Point"}
}