{
  "type": "Feature",
  "properties": {
    "addr:full":"Chelmer Road London Greater London E9 6AY",
    "addr:postcode":"e9 6ay",
    "addr:street":"Chelmer Road",
    "iso:country":"GB",
    "sg:address":"Chelmer Road",
    "sg:city":"London",
    "sg:classifiers":[
        {
            "category":"Retail",
            "subcategory":"Auto Repair",
            "type":"Services"
        }
    ],
    "sg:phone":"+44 20 8533 0829",
    "sg:postcode":"E9 6AY",
    "sg:province":"Greater London",
    "sg:tags":[
        "modification",
        "garage",
        "related"
    ],
    "wof:name":"M & D Motors",
    "wof:placetype":"venue"
},
  "geometry": {"coordinates":[-0.0410889983,51.550819397],"type":"Point"}
}