{
  "type": "Feature",
  "properties": {
    "addr:full":"6 Claremont Park Edinburgh City of Edinburgh EH6 7PH",
    "addr:housenumber":"6",
    "addr:postcode":"eh6 7ph",
    "addr:street":"Claremont Park Edinburgh",
    "iso:country":"GB",
    "sg:address":"6 Claremont Park",
    "sg:city":"Edinburgh",
    "sg:classifiers":[
        {
            "category":"Health Services",
            "subcategory":"Clinic",
            "type":"Services"
        },
        {
            "category":"Health Services",
            "subcategory":"Nursing And Care Facility",
            "type":"Services"
        }
    ],
    "sg:phone":"+44 131 554 6868",
    "sg:postcode":"EH6 7PH",
    "sg:province":"City of Edinburgh",
    "sg:tags":[
        "home",
        "private"
    ],
    "wof:name":"Claremont Park Ltd",
    "wof:placetype":"venue"
},
  "geometry": {"coordinates":[-3.156416,55.970005],"type":"Point"}
}