{
  "type": "Feature",
  "properties": {
    "addr:full":"96 Southview Road, Southwick Brighton West Sussex BN42 4TT",
    "addr:housenumber":"96",
    "addr:postcode":"bn42 4tt",
    "addr:street":"Southview Road",
    "iso:country":"GB",
    "sg:address":"96 Southview Road, Southwick",
    "sg:city":"Brighton",
    "sg:classifiers":[
        {
            "category":"Professional",
            "subcategory":"Business Services",
            "type":"Services"
        }
    ],
    "sg:phone":"+44 1273 870777",
    "sg:postcode":"BN42 4TT",
    "sg:province":"West Sussex",
    "sg:tags":[
        "accomodation"
    ],
    "wof:name":"Nicholson Cooper Ltd.",
    "wof:placetype":"venue"
},
  "geometry": {"coordinates":[-0.2370209992,50.8400154114],"type":"Point"}
}