{
  "type": "Feature",
  "properties": {
    "addr:full":"60 Queensway Stevenage Hertfordshire SG1 1EE",
    "addr:housenumber":"60",
    "addr:postcode":"sg1 1ee",
    "addr:street":"Queensway",
    "iso:country":"GB",
    "sg:address":"60 Queensway",
    "sg:city":"Stevenage",
    "sg:classifiers":[
        {
            "category":"Retail",
            "subcategory":"Photofinishing",
            "type":"Services"
        }
    ],
    "sg:phone":"+44 1438 352766",
    "sg:postcode":"SG1 1EE",
    "sg:province":"Hertfordshire",
    "sg:tags":[
        "photographic",
        "processor"
    ],
    "wof:name":"Foto Processing",
    "wof:placetype":"venue"
},
  "geometry": {"coordinates":[-0.198279,51.899319],"type":"Point"}
}