{
  "type": "Feature",
  "properties": {
    "iso:country":"GB",
    "sg:address":"35 Sefton St",
    "sg:city":"Liverpool",
    "sg:classifiers":[
        {
            "category":"Retail",
            "subcategory":"Storage",
            "type":"Services"
        }
    ],
    "sg:phone":"+44 151 709 4162",
    "sg:postcode":"L8 5SN",
    "sg:province":"Merseyside",
    "sg:tags":[
        "vault",
        "safe"
    ],
    "wof:name":"Withy Grove Safes Ltd",
    "wof:placetype":"venue"
},
  "geometry": {"coordinates":[-2.9825029373,53.3932228088],"type":"Point"}
}