{
  "type": "Feature",
  "properties": {
    "iso:country":"GB",
    "sg:address":"61 Warwick Square",
    "sg:city":"London",
    "sg:classifiers":[
        {
            "category":"Professional",
            "subcategory":"Computer Services",
            "type":"Services"
        }
    ],
    "sg:phone":"+44 20 7834 0371",
    "sg:postcode":"SW1V 2AL",
    "sg:province":"Greater London",
    "sg:tags":[
        "system",
        "software"
    ],
    "wof:name":"Minitel Computer Services",
    "wof:placetype":"venue"
},
  "geometry": {"coordinates":[-0.1404,51.490749],"type":"Point"}
}