{
  "type": "Feature",
  "properties": {
    "addr:full":"14 North Street, Sandwick, Isle Of Lewis Isle Of Lewis Eilean Siar HS2 0AD",
    "addr:housenumber":"14",
    "addr:postcode":"hs2 0ad",
    "addr:street":"North Street",
    "iso:country":"GB",
    "sg:address":"14 North Street, Sandwick, Isle Of Lewis",
    "sg:city":"Isle Of Lewis",
    "sg:classifiers":[
        {
            "category":"Home & Garden",
            "subcategory":"Garden Supply",
            "type":"Retail Goods"
        }
    ],
    "sg:phone":"+44 1851 705798",
    "sg:postcode":"HS2 0AD",
    "sg:province":"Eilean Siar",
    "sg:tags":[
        "nursery",
        "centre"
    ],
    "wof:name":"Maybury Gardens",
    "wof:placetype":"venue"
},
  "geometry": {"coordinates":[-6.351284,58.209244],"type":"Point"}
}