{
  "type": "Feature",
  "properties": {
    "addr:full":"Paddington House, New Rd Kidderminster Staffordshire DY10 1AL",
    "addr:postcode":"dy10 1al",
    "addr:street":"New Rd",
    "iso:country":"GB",
    "sg:address":"Paddington House, New Rd",
    "sg:city":"Kidderminster",
    "sg:classifiers":[
        {
            "category":"Sports & Exercise",
            "subcategory":"Playing Field",
            "type":"Entertainment"
        }
    ],
    "sg:phone":"+44 1562 865195",
    "sg:postcode":"DY10 1AL",
    "sg:province":"Staffordshire",
    "sg:tags":[
        "martial art"
    ],
    "wof:name":"Winsper School of Black Belts",
    "wof:placetype":"venue"
},
  "geometry": {"coordinates":[-2.2474389076,52.3854598999],"type":"Point"}
}