{
  "type": "Feature",
  "properties": {
    "iso:country":"GB",
    "sg:address":"Unit 5 Mountbatten Road",
    "sg:city":"Tiverton",
    "sg:classifiers":[
        {
            "category":"Sports & Exercise",
            "subcategory":"Race Track",
            "type":"Entertainment"
        }
    ],
    "sg:phone":"+44 1884 242412",
    "sg:postcode":"EX16 6SW",
    "sg:province":"Devon",
    "sg:tags":[
        "motor"
    ],
    "wof:name":"M E Motor Sports International",
    "wof:placetype":"venue"
},
  "geometry": {"coordinates":[-3.492081,50.907288],"type":"Point"}
}