{
  "type": "Feature",
  "properties": {
    "addr:full":"Unit 15 66 Fife Street Nuneaton Leicestershire CV11 5LR",
    "addr:housenumber":"unit;66",
    "addr:postcode":"cv11 5lr",
    "addr:street":"Fife Street",
    "iso:country":"GB",
    "sg:address":"Unit 15 66 Fife Street",
    "sg:city":"Nuneaton",
    "sg:classifiers":[
        {
            "category":"Building & Trades",
            "subcategory":"Construction",
            "type":"Services"
        }
    ],
    "sg:postcode":"CV11 5LR",
    "sg:province":"Leicestershire",
    "sg:tags":[
        "joiner",
        "carpenter"
    ],
    "wof:name":"Steve Rice Joinery",
    "wof:placetype":"venue"
},
  "geometry": {"coordinates":[-1.478615,52.523037],"type":"Point"}
}