{
  "type": "Feature",
  "properties": {
    "addr:full":"206 Ocean Road South Shields Tyne and Wear NE33 2JQ",
    "addr:housenumber":"206",
    "addr:postcode":"ne33 2jq",
    "addr:street":"Ocean Road",
    "iso:country":"GB",
    "sg:address":"206 Ocean Road",
    "sg:city":"South Shields",
    "sg:classifiers":[
        {
            "category":"Recreation",
            "subcategory":"Fishing",
            "type":"Entertainment"
        }
    ],
    "sg:phone":"+44 191 456 3953",
    "sg:postcode":"NE33 2JQ",
    "sg:province":"Tyne and Wear",
    "sg:tags":[
        "angling"
    ],
    "wof:name":"I D Fishing",
    "wof:placetype":"venue"
},
  "geometry": {"coordinates":[-1.4247080088,55.0002975464],"type":"Point"}
}