{
  "type": "Feature",
  "properties": {
    "addr:full":"2 Ord Drive, Tweedmouth Berwick-upon-tweed Northumberland TD15 2HZ",
    "addr:housenumber":"2",
    "addr:postcode":"td15 2hz",
    "addr:street":"Ord Drive",
    "iso:country":"GB",
    "sg:address":"2 Ord Drive, Tweedmouth",
    "sg:city":"Berwick-upon-tweed",
    "sg:classifiers":[
        {
            "category":"Personal",
            "subcategory":"Beauty Salon",
            "type":"Services"
        },
        {
            "category":"Personal",
            "subcategory":"Barber",
            "type":"Services"
        }
    ],
    "sg:phone":"+44 1289 305238",
    "sg:postcode":"TD15 2HZ",
    "sg:province":"Northumberland",
    "sg:tags":[
        "unisex",
        "hairdresser"
    ],
    "wof:name":"Hairworks",
    "wof:placetype":"venue"
},
  "geometry": {"coordinates":[-2.0126109123,55.7672958374],"type":"Point"}
}