{
  "type": "Feature",
  "properties": {
    "addr:full":"7 Carrick Street Glasgow Glasgow City G2 8PJ",
    "addr:housenumber":"7",
    "addr:postcode":"g2 8pj",
    "addr:street":"Carrick Street",
    "iso:country":"GB",
    "sg:address":"7 Carrick Street",
    "sg:city":"Glasgow",
    "sg:classifiers":[
        {
            "category":"Bars & Pubs",
            "type":"Food & Drink"
        }
    ],
    "sg:phone":"+44 141 572 0003",
    "sg:postcode":"G2 8PJ",
    "sg:province":"Glasgow City",
    "sg:tags":[
        "pubs",
        "inn"
    ],
    "wof:name":"The Montrose Bar & Diner",
    "wof:placetype":"venue"
},
  "geometry": {"coordinates":[-4.2664232254,55.8571014404],"type":"Point"}
}