{
  "type": "Feature",
  "properties": {
    "addr:full":"2 Burdett Road Wisbech Cambridgeshire PE13 2PR",
    "addr:housenumber":"2",
    "addr:postcode":"pe13 2pr",
    "addr:street":"Burdett Road",
    "iso:country":"GB",
    "sg:address":"2 Burdett Road",
    "sg:city":"Wisbech",
    "sg:classifiers":[
        {
            "category":"Manufacturing",
            "subcategory":"Wood Products",
            "type":"Manufacturing & Wholesale Goods"
        }
    ],
    "sg:phone":"+44 1945 583512",
    "sg:postcode":"PE13 2PR",
    "sg:province":"Cambridgeshire",
    "sg:tags":[
        "maker",
        "cabinet"
    ],
    "wof:name":"Roy E Smith",
    "wof:placetype":"venue"
},
  "geometry": {"coordinates":[0.1578589976,52.6602706909],"type":"Point"}
}