{
  "type": "Feature",
  "properties": {
    "addr:full":"64 Brandon Parade East Motherwell North Lanarkshire ML1 1LY",
    "addr:housenumber":"64",
    "addr:postcode":"ml1 1ly",
    "addr:street":"Brandon Parade East",
    "iso:country":"GB",
    "sg:address":"64 Brandon Parade East",
    "sg:city":"Motherwell",
    "sg:classifiers":[
        {
            "category":"Communications",
            "subcategory":"Film & Video Production",
            "type":"Services"
        }
    ],
    "sg:phone":"+44 1698 264004",
    "sg:postcode":"ML1 1LY",
    "sg:province":"North Lanarkshire",
    "sg:tags":[
        "tv"
    ],
    "wof:name":"Granada Home Technology",
    "wof:placetype":"venue"
},
  "geometry": {"coordinates":[-3.9876608849,55.7878799438],"type":"Point"}
}