{
  "type": "Feature",
  "properties": {
    "iso:country":"GB",
    "sg:address":"62 Ridgeway, Plympton",
    "sg:city":"Plymouth",
    "sg:classifiers":[
        {
            "category":"Health Services",
            "subcategory":"Optometrist",
            "type":"Services"
        },
        {
            "category":"Shopping",
            "subcategory":"Optician",
            "type":"Retail Goods"
        }
    ],
    "sg:phone":"+44 1752 345269",
    "sg:postcode":"PL7 2AL",
    "sg:province":"Devon",
    "sg:tags":[
        "ophthalmic"
    ],
    "sg:website":"http://www.noakes-habermehl.co.uk",
    "wof:name":"Noakes & Habermehl",
    "wof:placetype":"venue"
},
  "geometry": {"coordinates":[-4.05317,50.387939],"type":"Point"}
}