{
  "type": "Feature",
  "properties": {
    "addr:full":"Royal Victoria Patriotic Building, Fitzhugh Gro London Greater London SW18 3SX",
    "addr:postcode":"sw18 3sx",
    "addr:street":"Fitzhugh Gro",
    "iso:country":"GB",
    "sg:address":"Royal Victoria Patriotic Building, Fitzhugh Gro",
    "sg:city":"London",
    "sg:classifiers":[
        {
            "category":"Shopping",
            "subcategory":"Musical Instruments",
            "type":"Retail Goods"
        }
    ],
    "sg:phone":"+44 20 8739 0101",
    "sg:postcode":"SW18 3SX",
    "sg:province":"Greater London",
    "wof:name":"Piano Renaissance",
    "wof:placetype":"venue"
},
  "geometry": {"coordinates":[-0.1745499969,51.453250885],"type":"Point"}
}