{
  "type": "Feature",
  "properties": {
    "iso:country":"GB",
    "sg:address":"Roskrow Barton Farm, Roskrow",
    "sg:city":"Penryn",
    "sg:classifiers":[
        {
            "category":"Wholesale",
            "subcategory":"Meat",
            "type":"Manufacturing & Wholesale Goods"
        }
    ],
    "sg:postcode":"TR10 9AP",
    "sg:province":"Cornwall",
    "sg:tags":[
        "abattoir"
    ],
    "wof:name":"Ian Lentern",
    "wof:placetype":"venue"
},
  "geometry": {"coordinates":[-5.128414,50.180542],"type":"Point"}
}