{
  "type": "Feature",
  "properties": {
    "addr:full":"Woodshot, Alrewas Road, Kings Bromley Burton-on-trent Derbyshire DE13 7HY",
    "addr:postcode":"de13 7hy",
    "addr:street":"Alrewas Road",
    "iso:country":"GB",
    "sg:address":"Woodshot, Alrewas Road, Kings Bromley",
    "sg:city":"Burton-on-trent",
    "sg:classifiers":[
        {
            "category":"Home & Garden",
            "subcategory":"Garden Supply",
            "type":"Retail Goods"
        }
    ],
    "sg:phone":"+44 1543 472233",
    "sg:postcode":"DE13 7HY",
    "sg:province":"Derbyshire",
    "sg:tags":[
        "tree",
        "shrub"
    ],
    "wof:name":"Woodshoot Nurseries Ltd.",
    "wof:placetype":"venue"
},
  "geometry": {"coordinates":[-1.821126,52.749306],"type":"Point"}
}