{
  "type": "Feature",
  "properties": {
    "addr:full":"Building 84 Teeside Airport Darlington Durham DL2 1LU",
    "addr:postcode":"dl2 1lu",
    "addr:street":"Teeside",
    "iso:country":"GB",
    "sg:address":"Building 84 Teeside Airport",
    "sg:city":"Darlington",
    "sg:classifiers":[
        {
            "category":"Manufacturing",
            "subcategory":"Metals",
            "type":"Manufacturing & Wholesale Goods"
        },
        {
            "category":"Building & Trades",
            "subcategory":"Construction",
            "type":"Services"
        }
    ],
    "sg:phone":"+44 1325 332374",
    "sg:postcode":"DL2 1LU",
    "sg:province":"Durham",
    "sg:tags":[
        "steel",
        "fabricator",
        "builder",
        "erectors"
    ],
    "wof:name":"Robert Thompson Welding & Fabrication",
    "wof:placetype":"venue"
},
  "geometry": {"coordinates":[-1.4708009958,54.5202255249],"type":"Point"}
}