{
  "type": "Feature",
  "properties": {
    "addr:full":"Western Rd Southall Greater London UB2 5HE",
    "addr:postcode":"ub2 5he",
    "addr:street":"Western Rd",
    "iso:country":"GB",
    "sg:address":"Western Rd",
    "sg:city":"Southall",
    "sg:classifiers":[
        {
            "category":"Place Of Worship",
            "type":"Public Place"
        }
    ],
    "sg:phone":"+44 20 8813 8005",
    "sg:postcode":"UB2 5HE",
    "sg:province":"Greater London",
    "wof:name":"Church Of God (Pentecostal)",
    "wof:placetype":"venue"
},
  "geometry": {"coordinates":[-0.3850840032,51.500705719],"type":"Point"}
}