{
  "type": "Feature",
  "properties": {
    "iso:country":"GB",
    "sg:address":"8 Jenkin Avenue",
    "sg:city":"Sheffield",
    "sg:classifiers":[
        {
            "category":"Professional",
            "subcategory":"Accounting & Tax Preparation",
            "type":"Services"
        }
    ],
    "sg:phone":"+44 114 231 5400",
    "sg:postcode":"S9 1AP",
    "sg:province":"South Yorkshire",
    "sg:tags":[
        "accountant"
    ],
    "wof:name":"Enigma Building Co. Ltd.",
    "wof:placetype":"venue"
},
  "geometry": {"coordinates":[-1.425206,53.415756],"type":"Point"}
}