{
  "type": "Feature",
  "properties": {
    "iso:country":"GB",
    "sg:address":"Unit 3c Venture Industrial Park, Fareham Road",
    "sg:city":"Gosport",
    "sg:classifiers":[
        {
            "category":"Shopping",
            "subcategory":"Clothing, Apparel, & Fashions",
            "type":"Retail Goods"
        }
    ],
    "sg:postcode":"PO13 0BA",
    "sg:province":"Hampshire",
    "sg:tags":[
        "clothing",
        "fabric"
    ],
    "wof:name":"Eagle Sportswear",
    "wof:placetype":"venue"
},
  "geometry": {"coordinates":[-1.1641099453,50.8251113892],"type":"Point"}
}