{
  "type": "Feature",
  "properties": {
    "addr:full":"17 Ling Drive, Atherton Manchester Greater Manchester M46 9BH",
    "addr:housenumber":"17",
    "addr:postcode":"m46 9bh",
    "addr:street":"Ling Drive",
    "iso:country":"GB",
    "sg:address":"17 Ling Drive, Atherton",
    "sg:city":"Manchester",
    "sg:classifiers":[
        {
            "category":"Shopping",
            "subcategory":"Crafts & Fabrics",
            "type":"Retail Goods"
        }
    ],
    "sg:phone":"+44 1942 887565",
    "sg:postcode":"M46 9BH",
    "sg:province":"Greater Manchester",
    "sg:tags":[
        "boiler"
    ],
    "wof:name":"J Peers",
    "wof:placetype":"venue"
},
  "geometry": {"coordinates":[-2.4856390953,53.5206413269],"type":"Point"}
}