{
  "type": "Feature",
  "properties": {
    "iso:country":"GB",
    "sg:address":"Ditch Farm, Tullibody",
    "sg:city":"Alloa",
    "sg:classifiers":[
        {
            "category":"Farming",
            "subcategory":"Farm",
            "type":"Manufacturing & Wholesale Goods"
        }
    ],
    "sg:postcode":"FK10 2PL",
    "sg:province":"Clackmannanshire",
    "sg:tags":[
        "mixed",
        "crop"
    ],
    "wof:name":"Stuart F Stephen",
    "wof:placetype":"venue"
},
  "geometry": {"coordinates":[-3.836669,56.135399],"type":"Point"}
}