{
  "type": "Feature",
  "properties": {
    "addr:full":"19 High Street Epsom Surrey KT19 8DD",
    "addr:housenumber":"19",
    "addr:postcode":"kt19 8dd",
    "addr:street":"High Street",
    "iso:country":"GB",
    "sg:address":"19 High Street",
    "sg:city":"Epsom",
    "sg:classifiers":[
        {
            "category":"Shopping",
            "subcategory":"Used Merchandise",
            "type":"Retail Goods"
        }
    ],
    "sg:phone":"+44 1372 745155",
    "sg:postcode":"KT19 8DD",
    "sg:province":"Surrey",
    "sg:tags":[
        "shop",
        "second-hand"
    ],
    "wof:name":"Pricebusters",
    "wof:placetype":"venue"
},
  "geometry": {"coordinates":[-0.2650859952,51.3338088989],"type":"Point"}
}