{
  "type": "Feature",
  "properties": {
    "addr:full":"23 Mildenhall Road Slough Berkshire SL1 3JA",
    "addr:housenumber":"23",
    "addr:postcode":"sl1 3ja",
    "addr:street":"Mildenhall Road",
    "iso:country":"GB",
    "sg:address":"23 Mildenhall Road",
    "sg:city":"Slough",
    "sg:classifiers":[
        {
            "category":"Building & Trades",
            "subcategory":"Plumbing",
            "type":"Services"
        }
    ],
    "sg:postcode":"SL1 3JA",
    "sg:province":"Berkshire",
    "sg:tags":[
        "plumber",
        "heating"
    ],
    "wof:name":"D W Warner",
    "wof:placetype":"venue"
},
  "geometry": {"coordinates":[-0.6006519794,51.5219573975],"type":"Point"}
}