{
  "type": "Feature",
  "properties": {
    "iso:country":"GB",
    "sg:address":"Medway Farm, Chedzoy La",
    "sg:city":"Bridgwater",
    "sg:classifiers":[
        {
            "category":"Farming",
            "subcategory":"Livestock Farm",
            "type":"Manufacturing & Wholesale Goods"
        }
    ],
    "sg:phone":"+44 1278 422002",
    "sg:postcode":"TA7 8QW",
    "sg:province":"Somerset",
    "sg:tags":[
        "others"
    ],
    "wof:name":"G A Fry",
    "wof:placetype":"venue"
},
  "geometry": {"coordinates":[-2.96921,51.141449],"type":"Point"}
}