{
  "type": "Feature",
  "properties": {
    "addr:full":"52 Haymarket London Greater London SW1Y 4RP",
    "addr:housenumber":"52",
    "addr:postcode":"sw1y 4rp",
    "addr:street":"Haymarket",
    "iso:country":"GB",
    "sg:address":"52 Haymarket",
    "sg:city":"London",
    "sg:classifiers":[
        {
            "category":"Communications",
            "type":"Services"
        }
    ],
    "sg:phone":"+44 20 7930 8926",
    "sg:postcode":"SW1Y 4RP",
    "sg:province":"Greater London",
    "sg:tags":[
        "broadcasting"
    ],
    "wof:name":"Setanta Sport Ltd.",
    "wof:placetype":"venue"
},
  "geometry": {"coordinates":[-0.1327220052,51.5094413757],"type":"Point"}
}