{
  "type": "Feature",
  "properties": {
    "addr:full":"207 Willesden Lane, Kilburn London Greater London NW6 7YR",
    "addr:housenumber":"207",
    "addr:postcode":"nw6 7yr",
    "addr:street":"Willesden Lane",
    "iso:country":"GB",
    "sg:address":"207 Willesden Lane, Kilburn",
    "sg:city":"London",
    "sg:classifiers":[
        {
            "category":"Professional",
            "subcategory":"Computer Services",
            "type":"Services"
        }
    ],
    "sg:phone":"+44 20 8451 1542",
    "sg:postcode":"NW6 7YR",
    "sg:province":"Greater London",
    "sg:tags":[
        "consultant"
    ],
    "wof:name":"Sukhisoft Ltd.",
    "wof:placetype":"venue"
},
  "geometry": {"coordinates":[-0.2146459967,51.5453071594],"type":"Point"}
}