{
  "type": "Feature",
  "properties": {
    "addr:full":"65 Meath Green Lane Horley Surrey RH6 8HN",
    "addr:housenumber":"65",
    "addr:postcode":"rh6 8hn",
    "addr:street":"Meath Green Lane",
    "iso:country":"GB",
    "sg:address":"65 Meath Green Lane",
    "sg:city":"Horley",
    "sg:classifiers":[
        {
            "category":"Banks & Credit Unions",
            "subcategory":"Financial Services",
            "type":"Services"
        }
    ],
    "sg:phone":"+44 1293 822366",
    "sg:postcode":"RH6 8HN",
    "sg:province":"Surrey",
    "sg:tags":[
        "consultant"
    ],
    "wof:name":"Compeer Ltd.",
    "wof:placetype":"venue"
},
  "geometry": {"coordinates":[-0.1776770055,51.1821289062],"type":"Point"}
}