{
  "type": "Feature",
  "properties": {
    "addr:full":"90 Crownfield Road London Greater London E15 2AJ",
    "addr:housenumber":"90",
    "addr:postcode":"e15 2aj",
    "addr:street":"Crownfield Road",
    "iso:country":"GB",
    "sg:address":"90 Crownfield Road",
    "sg:city":"London",
    "sg:classifiers":[
        {
            "category":"Social Services",
            "subcategory":"Child Care",
            "type":"Services"
        },
        {
            "category":"Social Services",
            "subcategory":"Adult Care",
            "type":"Services"
        }
    ],
    "sg:phone":"+44 20 8519 4742",
    "sg:postcode":"E15 2AJ",
    "sg:province":"Greater London",
    "sg:tags":[
        "day",
        "centre"
    ],
    "wof:name":"CROWNFIELD DAY CENTRE",
    "wof:placetype":"venue"
},
  "geometry": {"coordinates":[0.000598,51.5519523621],"type":"Point"}
}