{
  "type": "Feature",
  "properties": {
    "addr:full":"Butetown Health Centre, 40 Loudoun Sq Cardiff Cardiff CF1 5UZ",
    "addr:housenumber":"40",
    "addr:postcode":"cf1 5uz",
    "addr:street":"Loudoun Sq",
    "iso:country":"GB",
    "sg:address":"Butetown Health Centre, 40 Loudoun Sq",
    "sg:city":"Cardiff",
    "sg:classifiers":[
        {
            "category":"Health Services",
            "subcategory":"Doctor",
            "type":"Services"
        }
    ],
    "sg:phone":"+44 29 2048 3126",
    "sg:postcode":"CF1 5UZ",
    "sg:province":"Cardiff",
    "sg:tags":[
        "practitioners"
    ],
    "wof:name":"Kay Saunders",
    "wof:placetype":"venue"
},
  "geometry": {"coordinates":[-3.18067,51.481258],"type":"Point"}
}