{
  "type": "Feature",
  "properties": {
    "addr:full":"45 Fairfax Avenue Basildon Essex SS13 1AY",
    "addr:housenumber":"45",
    "addr:postcode":"ss13 1ay",
    "addr:street":"Fairfax Avenue",
    "iso:country":"GB",
    "sg:address":"45 Fairfax Avenue",
    "sg:city":"Basildon",
    "sg:classifiers":[
        {
            "category":"Home & Garden",
            "subcategory":"Household Appliances",
            "type":"Retail Goods"
        }
    ],
    "sg:phone":"+44 1268 755230",
    "sg:postcode":"SS13 1AY",
    "sg:province":"Essex",
    "sg:tags":[
        "electrical"
    ],
    "wof:name":"Astec Domestic Services",
    "wof:placetype":"venue"
},
  "geometry": {"coordinates":[0.514051,51.581474],"type":"Point"}
}