{
  "type": "Feature",
  "properties": {
    "iso:country":"GB",
    "sg:address":"Mayfield Lodge, 4 Kingswood Road",
    "sg:city":"Bromley",
    "sg:classifiers":[
        {
            "category":"Professional",
            "subcategory":"Computer Services",
            "type":"Services"
        }
    ],
    "sg:postcode":"BR2 0HQ",
    "sg:province":"Kent",
    "sg:tags":[
        "system",
        "software"
    ],
    "wof:name":"Adam Ramli",
    "wof:placetype":"venue"
},
  "geometry": {"coordinates":[0.00041,51.402069],"type":"Point"}
}