{
  "type": "Feature",
  "properties": {
    "addr:full":"187 London Rd Southend On Sea Essex SS1 1PN",
    "addr:housenumber":"187",
    "addr:postcode":"ss1 1pn",
    "addr:street":"London Rd",
    "iso:country":"GB",
    "sg:address":"187 London Rd",
    "sg:city":"Southend On Sea",
    "sg:classifiers":[
        {
            "category":"Cinema",
            "subcategory":"Movie Rental",
            "type":"Entertainment"
        }
    ],
    "sg:phone":"+44 1702 433413",
    "sg:postcode":"SS1 1PN",
    "sg:province":"Essex",
    "sg:tags":[
        "video",
        "library"
    ],
    "wof:name":"Prestige Video",
    "wof:placetype":"venue"
},
  "geometry": {"coordinates":[0.7013030052,51.5400276184],"type":"Point"}
}