{
  "type": "Feature",
  "properties": {
    "iso:country":"GB",
    "sg:address":"278 Evesham Rd",
    "sg:city":"Redditch",
    "sg:classifiers":[
        {
            "category":"Building & Trades",
            "subcategory":"Plumbing",
            "type":"Services"
        }
    ],
    "sg:phone":"+44 1527 545366",
    "sg:postcode":"B97 5EP",
    "sg:province":"Warwickshire",
    "sg:tags":[
        "central",
        "heating"
    ],
    "wof:name":"Bird,John,",
    "wof:placetype":"venue"
},
  "geometry": {"coordinates":[-1.9443989992,52.2865943909],"type":"Point"}
}