{
  "type": "Feature",
  "properties": {
    "iso:country":"GB",
    "sg:address":"Unit 3 Laurel Business Centre, 15 Laurel Road",
    "sg:city":"Liverpool",
    "sg:classifiers":[
        {
            "category":"Building & Trades",
            "subcategory":"Cleaning & Sanitation",
            "type":"Services"
        },
        {
            "category":"Building & Trades",
            "subcategory":"Construction",
            "type":"Services"
        }
    ],
    "sg:phone":"+44 151 228 7511",
    "sg:postcode":"L7 0LJ",
    "sg:province":"Merseyside",
    "sg:tags":[
        "dry",
        "control",
        "damp",
        "rot",
        "builder"
    ],
    "wof:name":"Vortex Damp Proofing Co. Ltd.",
    "wof:placetype":"venue"
},
  "geometry": {"coordinates":[-2.9360399246,53.4096412659],"type":"Point"}
}