{
  "type": "Feature",
  "properties": {
    "iso:country":"GB",
    "sg:address":"Holme Farm, Wettenhall",
    "sg:city":"Winsford",
    "sg:classifiers":[
        {
            "category":"Farming",
            "subcategory":"Dairy Farm",
            "type":"Manufacturing & Wholesale Goods"
        }
    ],
    "sg:phone":"+44 1270 528234",
    "sg:postcode":"CW7 4HJ",
    "sg:province":"Cheshire",
    "wof:name":"R D & D R Rutter",
    "wof:placetype":"venue"
},
  "geometry": {"coordinates":[-2.5616691113,53.1469535828],"type":"Point"}
}