{
  "type": "Feature",
  "properties": {
    "addr:full":"4 Granby Avenue, Garretts Green Birmingham West Midlands B33 0SJ",
    "addr:housenumber":"4",
    "addr:postcode":"b33 0sj",
    "addr:street":"Granby Avenue Garretts Green",
    "iso:country":"GB",
    "sg:address":"4 Granby Avenue, Garretts Green",
    "sg:city":"Birmingham",
    "sg:classifiers":[
        {
            "category":"Building & Trades",
            "subcategory":"Construction",
            "type":"Services"
        }
    ],
    "sg:phone":"+44 121 771 3005",
    "sg:postcode":"B33 0SJ",
    "sg:province":"West Midlands",
    "sg:tags":[
        "builder"
    ],
    "wof:name":"M W C Building Co. Ltd.",
    "wof:placetype":"venue"
},
  "geometry": {"coordinates":[-1.775604,52.473976],"type":"Point"}
}