{
  "type": "Feature",
  "properties": {
    "addr:full":"Dunterton Farm, Teignharvey Newton Abbot Devon TQ12 4RS",
    "addr:housenumber":"dunterton;teignharvey",
    "addr:postcode":"tq12 4rs",
    "iso:country":"GB",
    "sg:address":"Dunterton Farm, Teignharvey",
    "sg:city":"Newton Abbot",
    "sg:classifiers":[
        {
            "category":"Farming",
            "subcategory":"Livestock Farm",
            "type":"Manufacturing & Wholesale Goods"
        },
        {
            "category":"Farming",
            "subcategory":"Farm",
            "type":"Manufacturing & Wholesale Goods"
        }
    ],
    "sg:phone":"+44 1626 873603",
    "sg:postcode":"TQ12 4RS",
    "sg:province":"Devon",
    "sg:tags":[
        "mixed",
        "crop",
        "others"
    ],
    "wof:name":"Michael H J Perry",
    "wof:placetype":"venue"
},
  "geometry": {"coordinates":[-3.6076591015,50.5288696289],"type":"Point"}
}