{
  "type": "Feature",
  "properties": {
    "iso:country":"GB",
    "sg:address":"Springfield Avenue",
    "sg:city":"Bridlington",
    "sg:classifiers":[
        {
            "category":"Autos & Motor Vehicles",
            "subcategory":"Automobile Sales",
            "type":"Retail Goods"
        },
        {
            "category":"Retail",
            "subcategory":"Auto Repair",
            "type":"Services"
        }
    ],
    "sg:phone":"+44 1262 603600",
    "sg:postcode":"YO15 3AA",
    "sg:province":"East Riding of Yorkshire",
    "sg:tags":[
        "modification",
        "garage",
        "car"
    ],
    "wof:name":"Springfield Toyota",
    "wof:placetype":"venue"
},
  "geometry": {"coordinates":[-0.195161,54.08408],"type":"Point"}
}