{
  "type": "Feature",
  "properties": {
    "addr:full":"7 Heyrod Street Manchester Greater Manchester M1 2WW",
    "addr:housenumber":"7",
    "addr:postcode":"m1 2ww",
    "addr:street":"Heyrod Street",
    "iso:country":"GB",
    "sg:address":"7 Heyrod Street",
    "sg:city":"Manchester",
    "sg:classifiers":[
        {
            "category":"Retail",
            "subcategory":"Auto Repair",
            "type":"Services"
        }
    ],
    "sg:phone":"+44 161 273 6914",
    "sg:postcode":"M1 2WW",
    "sg:province":"Greater Manchester",
    "sg:tags":[
        "modification",
        "garage"
    ],
    "wof:name":"Dalkeith Autos",
    "wof:placetype":"venue"
},
  "geometry": {"coordinates":[-2.2242801189,53.4781684875],"type":"Point"}
}