{
  "type": "Feature",
  "properties": {
    "iso:country":"GB",
    "sg:address":"Dyson Street, Sunbridge Road",
    "sg:city":"Bradford",
    "sg:classifiers":[
        {
            "category":"Manufacturing",
            "subcategory":"Signs",
            "type":"Manufacturing & Wholesale Goods"
        }
    ],
    "sg:phone":"+44 1274 725577",
    "sg:postcode":"BD1 2RS",
    "sg:province":"West Yorkshire",
    "sg:tags":[
        "nameplate"
    ],
    "wof:name":"W Dytiche & Son",
    "wof:placetype":"venue"
},
  "geometry": {"coordinates":[-1.763138,53.796574],"type":"Point"}
}