{
  "type": "Feature",
  "properties": {
    "addr:full":"7 Dublin Street Edinburgh City of Edinburgh EH1 3PG",
    "addr:housenumber":"7",
    "addr:postcode":"eh1 3pg",
    "addr:street":"Dublin Street",
    "iso:country":"GB",
    "sg:address":"7 Dublin Street",
    "sg:city":"Edinburgh",
    "sg:classifiers":[
        {
            "category":"Fast Food",
            "type":"Food & Drink"
        }
    ],
    "sg:phone":"+44 131 557 2689",
    "sg:postcode":"EH1 3PG",
    "sg:province":"City of Edinburgh",
    "sg:tags":[
        "away",
        "meal",
        "outlet",
        "take"
    ],
    "wof:name":"Something Tastier",
    "wof:placetype":"venue"
},
  "geometry": {"coordinates":[-3.192902,55.956127],"type":"Point"}
}