{
  "type": "Feature",
  "properties": {
    "iso:country":"GB",
    "sg:address":"109 Old Dover Rd",
    "sg:city":"Blackheath",
    "sg:classifiers":[
        {
            "category":"Bars & Pubs",
            "type":"Food & Drink"
        }
    ],
    "sg:phone":"+44 20 8858 1082",
    "sg:postcode":"SE3 8SU",
    "sg:province":"Greater London",
    "sg:tags":[
        "pubs",
        "inn"
    ],
    "wof:name":"British Oak",
    "wof:placetype":"venue"
},
  "geometry": {"coordinates":[0.026044,51.476074],"type":"Point"}
}