{
  "type": "Feature",
  "properties": {
    "iso:country":"GB",
    "sg:address":"21a Horseshoes Way, Brampton",
    "sg:city":"Huntingdon",
    "sg:classifiers":[
        {
            "category":"Personal",
            "type":"Services"
        },
        {
            "category":"Autos & Motor Vehicles",
            "subcategory":"Motorcycle Sales",
            "type":"Retail Goods"
        }
    ],
    "sg:phone":"+44 1480 456630",
    "sg:postcode":"PE28 4TN",
    "sg:province":"Bedfordshire",
    "sg:tags":[
        "chauffeur",
        "driven",
        "car",
        "wedding"
    ],
    "wof:name":"Calibre Chauffeur Services",
    "wof:placetype":"venue"
},
  "geometry": {"coordinates":[-0.225756,52.320847],"type":"Point"}
}