{
  "type": "Feature",
  "properties": {
    "addr:full":"Unit 5 Alexandra Road Enfield Greater London EN3 7EH",
    "addr:housenumber":"unit 5",
    "addr:postcode":"en3 7eh",
    "addr:street":"Alexandra Road",
    "iso:country":"GB",
    "sg:address":"Unit 5 Alexandra Road",
    "sg:city":"Enfield",
    "sg:classifiers":[
        {
            "category":"Wholesale",
            "subcategory":"Machinery & Supplies",
            "type":"Manufacturing & Wholesale Goods"
        },
        {
            "category":"Retail",
            "subcategory":"Auto Repair",
            "type":"Services"
        }
    ],
    "sg:phone":"+44 20 8805 9744",
    "sg:postcode":"EN3 7EH",
    "sg:province":"Greater London",
    "sg:tags":[
        "garage",
        "-",
        "sale",
        "related",
        "accessory",
        "equipment",
        "hydraulic"
    ],
    "wof:name":"HEL HYDRAULIC ENGINEERING LTD",
    "wof:placetype":"venue"
},
  "geometry": {"coordinates":[-0.037675,51.648933],"type":"Point"}
}