{
  "type": "Feature",
  "properties": {
    "addr:full":"91 Clayton Rd Newcastle Staffordshire ST5 3NE",
    "addr:housenumber":"91",
    "addr:postcode":"st5 3ne",
    "addr:street":"Clayton Rd",
    "iso:country":"GB",
    "sg:address":"91 Clayton Rd",
    "sg:city":"Newcastle",
    "sg:classifiers":[
        {
            "category":"Food & Beverages",
            "subcategory":"Meat & Fish",
            "type":"Retail Goods"
        }
    ],
    "sg:postcode":"ST5 3NE",
    "sg:province":"Staffordshire",
    "sg:tags":[
        "butcher"
    ],
    "wof:name":"Edge,Neil J,",
    "wof:placetype":"venue"
},
  "geometry": {"coordinates":[-2.2222859859,52.9996871948],"type":"Point"}
}