{
  "type": "Feature",
  "properties": {
    "addr:full":"9 Howe Ln Loughborough Leicestershire LE7 7LB",
    "addr:housenumber":"9",
    "addr:postcode":"le7 7lb",
    "addr:street":"Howe Ln",
    "iso:country":"GB",
    "sg:address":"9 Howe Ln",
    "sg:city":"Loughborough",
    "sg:classifiers":[
        {
            "category":"Building & Trades",
            "subcategory":"Plumbing",
            "type":"Services"
        }
    ],
    "sg:postcode":"LE7 7LB",
    "sg:province":"Leicestershire",
    "sg:tags":[
        "heating"
    ],
    "wof:name":"County Gas Service",
    "wof:placetype":"venue"
},
  "geometry": {"coordinates":[-1.1388360262,52.7086105347],"type":"Point"}
}