{
  "type": "Feature",
  "properties": {
    "addr:full":"Townfield Road Altrincham Cheshire WA14 4DS",
    "addr:postcode":"wa14 4ds",
    "addr:street":"Townfield Road",
    "iso:country":"GB",
    "sg:address":"Townfield Road",
    "sg:city":"Altrincham",
    "sg:classifiers":[
        {
            "category":"Education",
            "subcategory":"School",
            "type":"Public Place"
        }
    ],
    "sg:phone":"+44 161 928 7288",
    "sg:postcode":"WA14 4DS",
    "sg:province":"Cheshire",
    "sg:tags":[
        "local",
        "authority"
    ],
    "wof:name":"Altrincham C of E Primary School",
    "wof:placetype":"venue"
},
  "geometry": {"coordinates":[-2.3513588905,53.3910217285],"type":"Point"}
}