{
  "type": "Feature",
  "properties": {
    "addr:full":"22 Seagate Peterhead Aberdeenshire AB42 1JP",
    "addr:housenumber":"22",
    "addr:postcode":"ab42 1jp",
    "addr:street":"Seagate",
    "iso:country":"GB",
    "sg:address":"22 Seagate",
    "sg:city":"Peterhead",
    "sg:classifiers":[
        {
            "category":"Manufacturing",
            "subcategory":"Watercraft",
            "type":"Manufacturing & Wholesale Goods"
        }
    ],
    "sg:phone":"+44 1779 471471",
    "sg:postcode":"AB42 1JP",
    "sg:province":"Aberdeenshire",
    "sg:tags":[
        "repair",
        "ship",
        "builder"
    ],
    "wof:name":"Arthur Buchan",
    "wof:placetype":"venue"
},
  "geometry": {"coordinates":[-1.787432,57.51519],"type":"Point"}
}