{
  "type": "Feature",
  "properties": {
    "addr:full":"Institution Road Elgin Moray IV30 1QX",
    "addr:postcode":"iv30 1qx",
    "addr:street":"Institution Road",
    "iso:country":"GB",
    "sg:address":"Institution Road",
    "sg:city":"Elgin",
    "sg:classifiers":[
        {
            "category":"Health Services",
            "subcategory":"Nursing And Care Facility",
            "type":"Services"
        }
    ],
    "sg:phone":"+44 1343 549468",
    "sg:postcode":"IV30 1QX",
    "sg:province":"Moray",
    "sg:tags":[
        "home"
    ],
    "wof:name":"Abbeyside Nursing Home Ltd.",
    "wof:placetype":"venue"
},
  "geometry": {"coordinates":[-3.306251,57.647884],"type":"Point"}
}