{
  "type": "Feature",
  "properties": {
    "iso:country":"GB",
    "sg:address":"Windy Ridge Bracknell Road",
    "sg:city":"Crowthorne",
    "sg:classifiers":[
        {
            "category":"Professional",
            "subcategory":"Management & Consulting",
            "type":"Services"
        }
    ],
    "sg:phone":"+44 1344 780600",
    "sg:postcode":"RG11 6AR",
    "sg:province":"Berkshire",
    "sg:tags":[
        "consultant",
        "business"
    ],
    "wof:name":"The Salamander Organisation",
    "wof:placetype":"venue"
},
  "geometry": {"coordinates":[-0.8019899726,51.3699493408],"type":"Point"}
}