{
  "type": "Feature",
  "properties": {
    "iso:country":"GB",
    "sg:address":"96 The Avenue, Nunthorpe",
    "sg:city":"Middlesbrough",
    "sg:classifiers":[
        {
            "category":"Personal",
            "subcategory":"Beauty Salon",
            "type":"Services"
        }
    ],
    "sg:phone":"+44 1642 314136",
    "sg:postcode":"TS7 0AP",
    "sg:province":"North Yorkshire",
    "sg:tags":[
        "lady",
        "hairdresser"
    ],
    "wof:name":"Avernue Harcare",
    "wof:placetype":"venue"
},
  "geometry": {"coordinates":[-1.178908,54.529694],"type":"Point"}
}