{
  "type": "Feature",
  "properties": {
    "iso:country":"GB",
    "sg:address":"556 Leeds Road, Outwood",
    "sg:city":"Wakefield",
    "sg:classifiers":[
        {
            "category":"Insurance",
            "subcategory":"Insurance Agent",
            "type":"Services"
        }
    ],
    "sg:phone":"+44 1924 871111",
    "sg:postcode":"WF1 2DX",
    "sg:province":"West Yorkshire",
    "sg:tags":[
        "broker"
    ],
    "wof:name":"Woodhead Taylor James (Management) Ltd.",
    "wof:placetype":"venue"
},
  "geometry": {"coordinates":[-1.500756979,53.7109603882],"type":"Point"}
}