{
  "type": "Feature",
  "properties": {
    "addr:full":"37 Kingsthorne Road, Hunts Cross Liverpool Merseyside L25 0PJ",
    "addr:housenumber":"37",
    "addr:postcode":"l25 0pj",
    "addr:street":"Kingsthorne Road",
    "iso:country":"GB",
    "sg:address":"37 Kingsthorne Road, Hunts Cross",
    "sg:city":"Liverpool",
    "sg:classifiers":[
        {
            "category":"Building & Trades",
            "subcategory":"Construction",
            "type":"Services"
        }
    ],
    "sg:postcode":"L25 0PJ",
    "sg:province":"Merseyside",
    "sg:tags":[
        "contractor",
        "paving",
        "driveway"
    ],
    "wof:name":"Marshall Driveways",
    "wof:placetype":"venue"
},
  "geometry": {"coordinates":[-2.8527131081,53.3586845398],"type":"Point"}
}