{
  "type": "Feature",
  "properties": {
    "addr:full":"29 Saville Row London Greater London W1S 2EY",
    "addr:housenumber":"29",
    "addr:postcode":"w1s 2ey",
    "addr:street":"Saville Row",
    "iso:country":"GB",
    "sg:address":"29 Saville Row",
    "sg:city":"London",
    "sg:classifiers":[
        {
            "category":"Personal",
            "type":"Services"
        }
    ],
    "sg:phone":"+44 20 7434 0605",
    "sg:postcode":"W1S 2EY",
    "sg:province":"Greater London",
    "sg:tags":[
        "tailor"
    ],
    "wof:name":"Flag Clothing Ltd.",
    "wof:placetype":"venue"
},
  "geometry": {"coordinates":[-0.1415430009,51.5118217468],"type":"Point"}
}