{
  "type": "Feature",
  "properties": {
    "iso:country":"GB",
    "sg:address":"356 Chorley Old Road",
    "sg:city":"Bolton",
    "sg:classifiers":[
        {
            "category":"Real Estate",
            "subcategory":"Surveying",
            "type":"Services"
        },
        {
            "category":"Real Estate",
            "subcategory":"Architect",
            "type":"Services"
        }
    ],
    "sg:phone":"+44 1204 845382",
    "sg:postcode":"BL1 6AG",
    "sg:province":"Lancashire",
    "sg:tags":[
        "surveyor",
        "valuer"
    ],
    "wof:name":"Greenhalgh & Co Structural Surveyors & Valuers",
    "wof:placetype":"venue"
},
  "geometry": {"coordinates":[-2.4549689293,53.5876998901],"type":"Point"}
}