{
  "type": "Feature",
  "properties": {
    "addr:full":"Sutton Dept, Albert St Carlisle Cumbria CA6 5SF",
    "addr:postcode":"ca6 5sf",
    "addr:street":"Albert St",
    "iso:country":"GB",
    "sg:address":"Sutton Dept, Albert St",
    "sg:city":"Carlisle",
    "sg:classifiers":[
        {
            "category":"Freight",
            "type":"Transportation"
        }
    ],
    "sg:phone":"+44 1228 792058",
    "sg:postcode":"CA6 5SF",
    "sg:province":"Cumbria",
    "sg:tags":[
        "haulage",
        "road"
    ],
    "wof:name":"R & M Charnley Transport",
    "wof:placetype":"venue"
},
  "geometry": {"coordinates":[-2.9698600769,55.0071296692],"type":"Point"}
}