{
  "type": "Feature",
  "properties": {
    "iso:country":"GB",
    "sg:address":"Dirr Sawmill, Dores",
    "sg:city":"Inverness",
    "sg:classifiers":[
        {
            "category":"Freight",
            "type":"Transportation"
        }
    ],
    "sg:postcode":"IV2 6TR",
    "sg:province":"Highland",
    "sg:tags":[
        "haulage",
        "road"
    ],
    "wof:name":"D Mackintosh",
    "wof:placetype":"venue"
},
  "geometry": {"coordinates":[-4.332264,57.38232],"type":"Point"}
}