{
  "type": "Feature",
  "properties": {
    "addr:full":"Jet Filling Station, Sutton Rd Hull East Riding of Yorkshire HU6 7DR",
    "addr:postcode":"hu6 7dr",
    "addr:street":"Sutton Rd",
    "iso:country":"GB",
    "sg:address":"Jet Filling Station, Sutton Rd",
    "sg:city":"Hull",
    "sg:classifiers":[
        {
            "category":"Military Area",
            "subcategory":"Air Force Base",
            "type":"Public Place"
        }
    ],
    "sg:postcode":"HU6 7DR",
    "sg:province":"East Riding of Yorkshire",
    "sg:tags":[
        "taxi",
        "hire",
        "private"
    ],
    "wof:name":"McGowan's",
    "wof:placetype":"venue"
},
  "geometry": {"coordinates":[-0.35636,53.78167],"type":"Point"}
}