{
  "type": "Feature",
  "properties": {
    "addr:full":"Village Centre, Sway Lymington Hampshire SO41 6BA",
    "addr:postcode":"so41 6ba",
    "iso:country":"GB",
    "sg:address":"Village Centre, Sway",
    "sg:city":"Lymington",
    "sg:classifiers":[
        {
            "category":"Restaurant",
            "type":"Food & Drink"
        }
    ],
    "sg:phone":"+44 1590 682754",
    "sg:postcode":"SO41 6BA",
    "sg:province":"Hampshire",
    "wof:name":"Sway Manor Hotel",
    "wof:placetype":"venue"
},
  "geometry": {"coordinates":[-1.6010320187,50.785068512],"type":"Point"}
}