{
  "type": "Feature",
  "properties": {
    "iso:country":"GB",
    "sg:address":"28 Ashbourne Road",
    "sg:city":"Leek",
    "sg:classifiers":[
        {
            "category":"Food & Beverages",
            "subcategory":"Candy",
            "type":"Retail Goods"
        }
    ],
    "sg:phone":"+44 1538 383107",
    "sg:postcode":"ST13 5AS",
    "sg:province":"Staffordshire",
    "sg:tags":[
        "confectioner"
    ],
    "wof:name":"Candy Cabin",
    "wof:placetype":"venue"
},
  "geometry": {"coordinates":[-2.0185079575,53.1047439575],"type":"Point"}
}