{
  "type": "Feature",
  "properties": {
    "iso:country":"GB",
    "sg:address":"18 Wind Street",
    "sg:city":"Ammanford",
    "sg:classifiers":[
        {
            "category":"Home & Garden",
            "subcategory":"Home Furnishings",
            "type":"Retail Goods"
        }
    ],
    "sg:phone":"+44 1269 591784",
    "sg:postcode":"SA18 3DN",
    "sg:province":"Carmarthenshire",
    "sg:tags":[
        "beds",
        "bedding",
        "blanket"
    ],
    "wof:name":"Try-Angles",
    "wof:placetype":"venue"
},
  "geometry": {"coordinates":[-3.988945,51.792397],"type":"Point"}
}