{
  "type": "Feature",
  "properties": {
    "addr:full":"35 Collingwood Street, Coundon Bishop Auckland Durham DL14 8LG",
    "addr:housenumber":"35",
    "addr:postcode":"dl14 8lg",
    "addr:street":"Collingwood Street;Auckland",
    "iso:country":"GB",
    "sg:address":"35 Collingwood Street, Coundon",
    "sg:city":"Bishop Auckland",
    "sg:classifiers":[
        {
            "category":"Bars & Pubs",
            "type":"Food & Drink"
        }
    ],
    "sg:phone":"+44 1388 661533",
    "sg:postcode":"DL14 8LG",
    "sg:province":"Durham",
    "sg:tags":[
        "pubs",
        "inn"
    ],
    "wof:name":"The Foresters Arms",
    "wof:placetype":"venue"
},
  "geometry": {"coordinates":[-1.630663,54.661793],"type":"Point"}
}