{
  "type": "Feature",
  "properties": {
    "iso:country":"GB",
    "sg:address":"21 Heol-y-nant, Rhos",
    "sg:city":"Swansea",
    "sg:classifiers":[
        {
            "category":"Building & Trades",
            "subcategory":"Construction",
            "type":"Services"
        }
    ],
    "sg:phone":"+44 1792 869532",
    "sg:postcode":"SA8 3EQ",
    "sg:province":"Neath Port Talbot",
    "sg:tags":[
        "builder"
    ],
    "wof:name":"C M Rogers",
    "wof:placetype":"venue"
},
  "geometry": {"coordinates":[-3.842904,51.713459],"type":"Point"}
}