{
  "type": "Feature",
  "properties": {
    "iso:country":"GB",
    "sg:address":"Pullman Gardens",
    "sg:city":"London",
    "sg:classifiers":[
        {
            "category":"Education",
            "subcategory":"School",
            "type":"Public Place"
        }
    ],
    "sg:phone":"+44 20 8788 3421",
    "sg:postcode":"SW15 3DG",
    "sg:province":"Greater London",
    "sg:tags":[
        "college"
    ],
    "wof:name":"Elliott School",
    "wof:placetype":"venue"
},
  "geometry": {"coordinates":[-0.226735,51.454777],"type":"Point"}
}