{
  "type": "Feature",
  "properties": {
    "iso:country":"GB",
    "sg:address":"91-95 St Margarets Road",
    "sg:city":"Twickenham",
    "sg:classifiers":[
        {
            "category":"Retail",
            "subcategory":"Auto Repair",
            "type":"Services"
        }
    ],
    "sg:postcode":"TW1 2LJ",
    "sg:province":"Greater London",
    "sg:tags":[
        "modification",
        "garage"
    ],
    "wof:name":"Everest Motor Servicing",
    "wof:placetype":"venue"
},
  "geometry": {"coordinates":[-0.3182039857,51.4543151855],"type":"Point"}
}