{
  "type": "Feature",
  "properties": {
    "iso:country":"GB",
    "sg:address":"Fernleigh Road",
    "sg:city":"Wadebridge",
    "sg:classifiers":[
        {
            "category":"Social Services",
            "subcategory":"Retirement Home",
            "type":"Services"
        }
    ],
    "sg:phone":"+44 1208 812005",
    "sg:postcode":"PL27 7BB",
    "sg:province":"Cornwall",
    "sg:tags":[
        "residential",
        "care"
    ],
    "wof:name":"Pendennis House",
    "wof:placetype":"venue"
},
  "geometry": {"coordinates":[-4.833703,50.513638],"type":"Point"}
}