{
  "type": "Feature",
  "properties": {
    "addr:full":"6a Glendale Avenue, Wood Green London Greater London N22 5AH",
    "addr:housenumber":"6a",
    "addr:postcode":"n22 5ah",
    "addr:street":"Glendale Avenue",
    "iso:country":"GB",
    "sg:address":"6a Glendale Avenue, Wood Green",
    "sg:city":"London",
    "sg:classifiers":[
        {
            "category":"Communications",
            "type":"Services"
        }
    ],
    "sg:postcode":"N22 5AH",
    "sg:province":"Greater London",
    "sg:tags":[
        "data",
        "network"
    ],
    "wof:name":"Smart Data Ltd",
    "wof:placetype":"venue"
},
  "geometry": {"coordinates":[-0.1091630012,51.606842041],"type":"Point"}
}