{
  "type": "Feature",
  "properties": {
    "addr:full":"2 Moor Lane Upminster Essex RM14 1EB",
    "addr:housenumber":"2",
    "addr:postcode":"rm14 1eb",
    "addr:street":"Moor Lane",
    "iso:country":"GB",
    "sg:address":"2 Moor Lane",
    "sg:city":"Upminster",
    "sg:classifiers":[
        {
            "category":"Personal",
            "subcategory":"Beauty Salon",
            "type":"Services"
        }
    ],
    "sg:phone":"+44 1708 221356",
    "sg:postcode":"RM14 1EB",
    "sg:province":"Essex",
    "sg:tags":[
        "unisex",
        "hairdresser"
    ],
    "wof:name":"Nigel Hair Fashions",
    "wof:placetype":"venue"
},
  "geometry": {"coordinates":[0.268294,51.561901],"type":"Point"}
}