{
  "type": "Feature",
  "properties": {
    "iso:country":"GB",
    "sg:address":"Long Park, Houghton",
    "sg:city":"Carlisle",
    "sg:classifiers":[
        {
            "category":"Farming",
            "subcategory":"Farm",
            "type":"Manufacturing & Wholesale Goods"
        }
    ],
    "sg:postcode":"CA6 4JP",
    "sg:province":"Cumbria",
    "sg:tags":[
        "mixed",
        "crop"
    ],
    "wof:name":"Joseph Thomlinson",
    "wof:placetype":"venue"
},
  "geometry": {"coordinates":[-2.892469,54.949921],"type":"Point"}
}