{
  "type": "Feature",
  "properties": {
    "addr:full":"330-332 Uxbridge Street Burton-on-trent Derbyshire DE14 3JS",
    "addr:housenumber":"330-332",
    "addr:postcode":"de14 3js",
    "addr:street":"Uxbridge Street",
    "iso:country":"GB",
    "sg:address":"330-332 Uxbridge Street",
    "sg:city":"Burton-on-trent",
    "sg:classifiers":[
        {
            "category":"Home & Garden",
            "subcategory":"Carpets & Floor Coverings",
            "type":"Retail Goods"
        }
    ],
    "sg:phone":"+44 1283 546466",
    "sg:postcode":"DE14 3JS",
    "sg:province":"Derbyshire",
    "sg:tags":[
        "carpets",
        "rug",
        "matting"
    ],
    "wof:name":"Carpet & Bedding Co",
    "wof:placetype":"venue"
},
  "geometry": {"coordinates":[-1.639605999,52.8008651733],"type":"Point"}
}