{
  "type": "Feature",
  "properties": {
    "addr:full":"92 Maple Way Gillingham Dorset SP8 4RR",
    "addr:housenumber":"92",
    "addr:postcode":"sp8 4rr",
    "addr:street":"Maple Way",
    "iso:country":"GB",
    "sg:address":"92 Maple Way",
    "sg:city":"Gillingham",
    "sg:classifiers":[
        {
            "category":"Banks & Credit Unions",
            "subcategory":"Bank",
            "type":"Services"
        }
    ],
    "sg:phone":"+44 1747 824593",
    "sg:postcode":"SP8 4RR",
    "sg:province":"Dorset",
    "sg:tags":[
        "broker",
        "mortgage"
    ],
    "wof:name":"Anderson & Co",
    "wof:placetype":"venue"
},
  "geometry": {"coordinates":[-2.2872419357,51.0355186462],"type":"Point"}
}