{
  "type": "Feature",
  "properties": {
    "addr:full":"Po Box 64 Chislehurst Kent BR7 6XA",
    "addr:housenumber":"po box 64",
    "addr:postcode":"br7 6xa",
    "iso:country":"GB",
    "sg:address":"Po Box 64",
    "sg:city":"Chislehurst",
    "sg:classifiers":[
        {
            "category":"Home & Garden",
            "subcategory":"Furniture",
            "type":"Retail Goods"
        }
    ],
    "sg:phone":"+44 20 8295 0222",
    "sg:postcode":"BR7 6XA",
    "sg:province":"Kent",
    "wof:name":"Paul Grant Furniture Ltd.",
    "wof:placetype":"venue"
},
  "geometry": {"coordinates":[0.0663900003,51.4192848206],"type":"Point"}
}