{
  "type": "Feature",
  "properties": {
    "addr:full":"10 South Bridge Edinburgh City of Edinburgh EH1 1LL",
    "addr:housenumber":"10",
    "addr:postcode":"eh1 1ll",
    "addr:street":"South Bridge Edinburgh",
    "iso:country":"GB",
    "sg:address":"10 South Bridge",
    "sg:city":"Edinburgh",
    "sg:classifiers":[
        {
            "category":"Food & Beverages",
            "subcategory":"Bakery",
            "type":"Retail Goods"
        }
    ],
    "sg:phone":"+44 131 556 4119",
    "sg:postcode":"EH1 1LL",
    "sg:province":"City of Edinburgh",
    "sg:tags":[
        "baker"
    ],
    "wof:name":"Greggs",
    "wof:placetype":"venue"
},
  "geometry": {"coordinates":[-3.187211,55.949947],"type":"Point"}
}