{
  "type": "Feature",
  "properties": {
    "iso:country":"GB",
    "sg:address":"Unit H1, Coedcae Lane Industrial Estate, Coedcae Lane",
    "sg:city":"Pontyclun",
    "sg:classifiers":[
        {
            "category":"Professional",
            "subcategory":"Printing & Photocopies",
            "type":"Services"
        }
    ],
    "sg:phone":"+44 1443 238950",
    "sg:postcode":"CF72 9HG",
    "sg:province":"Bridgend",
    "sg:tags":[
        "process",
        "screen",
        "printer"
    ],
    "wof:name":"Complete Jet Cutting Ltd.",
    "wof:placetype":"venue"
},
  "geometry": {"coordinates":[-3.3979790211,51.5317382812],"type":"Point"}
}