{
  "type": "Feature",
  "properties": {
    "addr:full":"419b Manchester Road, Baxenden Accrington Lancashire BB5 2QJ",
    "addr:housenumber":"419b",
    "addr:postcode":"bb5 2qj",
    "addr:street":"Manchester Road;Accrington",
    "iso:country":"GB",
    "sg:address":"419b Manchester Road, Baxenden",
    "sg:city":"Accrington",
    "sg:classifiers":[
        {
            "category":"Food & Beverages",
            "subcategory":"Meat & Fish",
            "type":"Retail Goods"
        }
    ],
    "sg:phone":"+44 1254 398116",
    "sg:postcode":"BB5 2QJ",
    "sg:province":"Lancashire",
    "sg:tags":[
        "butcher"
    ],
    "wof:name":"Sandersons",
    "wof:placetype":"venue"
},
  "geometry": {"coordinates":[-2.3496029377,53.7373504639],"type":"Point"}
}