{
  "type": "Feature",
  "properties": {
    "addr:full":"156 Foryd Road, Kinmel Bay Rhyl Conwy LL18 5LS",
    "addr:housenumber":"156",
    "addr:postcode":"ll18 5ls",
    "addr:street":"Foryd Road",
    "iso:country":"GB",
    "sg:address":"156 Foryd Road, Kinmel Bay",
    "sg:city":"Rhyl",
    "sg:classifiers":[
        {
            "category":"Restaurant",
            "type":"Food & Drink"
        }
    ],
    "sg:phone":"+44 1745 337755",
    "sg:postcode":"LL18 5LS",
    "sg:province":"Conwy",
    "sg:tags":[
        "indian"
    ],
    "wof:name":"Shapla Tandoori Restaurant",
    "wof:placetype":"venue"
},
  "geometry": {"coordinates":[-3.525908,53.308506],"type":"Point"}
}