{
  "type": "Feature",
  "properties": {
    "iso:country":"GB",
    "sg:address":"6 St Johns Road",
    "sg:city":"Woking",
    "sg:classifiers":[
        {
            "category":"Personal",
            "subcategory":"Beauty Salon",
            "type":"Services"
        }
    ],
    "sg:phone":"+44 1483 715127",
    "sg:postcode":"GU21 7SA",
    "sg:province":"Surrey",
    "sg:tags":[
        "unisex",
        "hairdresser"
    ],
    "wof:name":"David Peters",
    "wof:placetype":"venue"
},
  "geometry": {"coordinates":[-0.5950829983,51.3120918274],"type":"Point"}
}