{
  "type": "Feature",
  "properties": {
    "addr:full":"253 Burlington Rd New Malden Surrey KT3 4NE",
    "addr:housenumber":"253",
    "addr:postcode":"kt3 4ne",
    "addr:street":"Burlington Rd",
    "iso:country":"GB",
    "sg:address":"253 Burlington Rd",
    "sg:city":"New Malden",
    "sg:classifiers":[
        {
            "category":"Utilities",
            "subcategory":"Telephone",
            "type":"Services"
        }
    ],
    "sg:phone":"+44 20 8942 0788",
    "sg:postcode":"KT3 4NE",
    "sg:province":"Surrey",
    "sg:tags":[
        "telecommunication"
    ],
    "wof:name":"Melita Europe Ltd",
    "wof:placetype":"venue"
},
  "geometry": {"coordinates":[-0.239132,51.400303],"type":"Point"}
}