{
  "type": "Feature",
  "properties": {
    "addr:full":"34 Fulham High Street, Fulham London Greater London SW6 3LQ",
    "addr:housenumber":"34",
    "addr:postcode":"sw6 3lq",
    "addr:street":"Fulham High Street",
    "iso:country":"GB",
    "sg:address":"34 Fulham High Street, Fulham",
    "sg:city":"London",
    "sg:classifiers":[
        {
            "category":"Health Services",
            "subcategory":"Dentist",
            "type":"Services"
        }
    ],
    "sg:phone":"+44 20 7731 1162",
    "sg:postcode":"SW6 3LQ",
    "sg:province":"Greater London",
    "wof:name":"P Haworth",
    "wof:placetype":"venue"
},
  "geometry": {"coordinates":[-0.2112189978,51.4709815979],"type":"Point"}
}