{
  "type": "Feature",
  "properties": {
    "addr:full":"14a Argyle Street St Andrews Fife KY16 9BP",
    "addr:housenumber":"14a",
    "addr:postcode":"ky16 9bp",
    "addr:street":"Argyle Street",
    "iso:country":"GB",
    "sg:address":"14a Argyle Street",
    "sg:city":"St Andrews",
    "sg:classifiers":[
        {
            "category":"Professional",
            "subcategory":"Printing & Photocopies",
            "type":"Services"
        }
    ],
    "sg:phone":"+44 1334 477135",
    "sg:postcode":"KY16 9BP",
    "sg:province":"Fife",
    "sg:tags":[
        "printer"
    ],
    "wof:name":"West Port Print & Design",
    "wof:placetype":"venue"
},
  "geometry": {"coordinates":[-2.8018510342,56.3385658264],"type":"Point"}
}