{
  "type": "Feature",
  "properties": {
    "iso:country":"GB",
    "sg:address":"17 Lochlibo Ct",
    "sg:city":"Irvine",
    "sg:classifiers":[
        {
            "category":"Home & Garden",
            "subcategory":"Furniture",
            "type":"Retail Goods"
        }
    ],
    "sg:postcode":"KA11 1RE",
    "sg:province":"East Ayrshire",
    "wof:name":"Sheerin,Mary,",
    "wof:placetype":"venue"
},
  "geometry": {"coordinates":[-4.635281086,55.6302528381],"type":"Point"}
}