{
  "type": "Feature",
  "properties": {
    "addr:full":"91 High St Bruton Somerset BA10 0AR",
    "addr:housenumber":"91",
    "addr:postcode":"ba10 0ar",
    "addr:street":"High St",
    "iso:country":"GB",
    "sg:address":"91 High St",
    "sg:city":"Bruton",
    "sg:classifiers":[
        {
            "category":"Education",
            "subcategory":"Library",
            "type":"Public Place"
        }
    ],
    "sg:phone":"+44 1749 813385",
    "sg:postcode":"BA10 0AR",
    "sg:province":"Somerset",
    "sg:tags":[
        "book"
    ],
    "wof:name":"Library & Information Co-operation Council",
    "wof:placetype":"venue"
},
  "geometry": {"coordinates":[-2.458547,51.110481],"type":"Point"}
}