{
  "type": "Feature",
  "properties": {
    "addr:full":"Group Practise Centre, Howard St Glossop Derbyshire SK13 9DD",
    "addr:postcode":"sk13 9dd",
    "addr:street":"Howard St",
    "iso:country":"GB",
    "sg:address":"Group Practise Centre, Howard St",
    "sg:city":"Glossop",
    "sg:classifiers":[
        {
            "category":"Health Services",
            "subcategory":"Doctor",
            "type":"Services"
        }
    ],
    "sg:phone":"+44 1457 854321",
    "sg:postcode":"SK13 9DD",
    "sg:province":"Derbyshire",
    "sg:tags":[
        "practitioners"
    ],
    "wof:name":"Banerjee, B",
    "wof:placetype":"venue"
},
  "geometry": {"coordinates":[-1.94657,53.443336],"type":"Point"}
}