{
  "type": "Feature",
  "properties": {
    "iso:country":"GB",
    "sg:address":"72 Pasture Road",
    "sg:city":"Barton-upon-humber",
    "sg:classifiers":[
        {
            "category":"Farming",
            "subcategory":"Nursery",
            "type":"Manufacturing & Wholesale Goods"
        }
    ],
    "sg:postcode":"DN18 5HZ",
    "sg:province":"Lincolnshire",
    "sg:tags":[
        "creche"
    ],
    "wof:name":"Field View Day Nursery",
    "wof:placetype":"venue"
},
  "geometry": {"coordinates":[-0.432983,53.687489],"type":"Point"}
}