{
  "type": "Feature",
  "properties": {
    "addr:full":"Holly Farm, Harley Road, Harley Rotherham South Yorkshire S62 7UD",
    "addr:postcode":"s62 7ud",
    "addr:street":"Harley Road",
    "iso:country":"GB",
    "sg:address":"Holly Farm, Harley Road, Harley",
    "sg:city":"Rotherham",
    "sg:classifiers":[
        {
            "category":"Shopping",
            "subcategory":"Antiques",
            "type":"Retail Goods"
        }
    ],
    "sg:postcode":"S62 7UD",
    "sg:province":"South Yorkshire",
    "wof:name":"Holly Farm Antiques",
    "wof:placetype":"venue"
},
  "geometry": {"coordinates":[-1.445849,53.481155],"type":"Point"}
}