{
  "type": "Feature",
  "properties": {
    "addr:full":"19 Bridgeman Pl Bolton Lancashire BL2 1DE",
    "addr:housenumber":"19",
    "addr:postcode":"bl2 1de",
    "addr:street":"Bridgeman Pl",
    "iso:country":"GB",
    "sg:address":"19 Bridgeman Pl",
    "sg:city":"Bolton",
    "sg:classifiers":[
        {
            "category":"Autos & Motor Vehicles",
            "subcategory":"Fuel & Gas Station",
            "type":"Retail Goods"
        }
    ],
    "sg:phone":"+44 1204 533310",
    "sg:postcode":"BL2 1DE",
    "sg:province":"Lancashire",
    "sg:tags":[
        "hr",
        "petrol"
    ],
    "wof:name":"Bridgeman Place Services Ltd",
    "wof:placetype":"venue"
},
  "geometry": {"coordinates":[-2.4224889278,53.5751914978],"type":"Point"}
}