{
  "type": "Feature",
  "properties": {
    "addr:full":"Croft Farm, Fylingthorpe Whitby North Yorkshire YO22 4PW",
    "addr:postcode":"yo22 4pw",
    "addr:street":"Fylingthorpe",
    "iso:country":"GB",
    "sg:address":"Croft Farm, Fylingthorpe",
    "sg:city":"Whitby",
    "sg:classifiers":[
        {
            "category":"Farming",
            "subcategory":"Livestock Farm",
            "type":"Manufacturing & Wholesale Goods"
        },
        {
            "category":"Farming",
            "subcategory":"Farm",
            "type":"Manufacturing & Wholesale Goods"
        }
    ],
    "sg:postcode":"YO22 4PW",
    "sg:province":"North Yorkshire",
    "sg:tags":[
        "mixed",
        "crop",
        "others"
    ],
    "wof:name":"J A & P M Featherstone",
    "wof:placetype":"venue"
},
  "geometry": {"coordinates":[-0.54853,54.431358],"type":"Point"}
}