{
  "type": "Feature",
  "properties": {
    "iso:country":"GB",
    "sg:address":"Park Rd",
    "sg:city":"St Austell",
    "sg:classifiers":[
        {
            "category":"Government",
            "subcategory":"Post Office",
            "type":"Public Place"
        }
    ],
    "sg:phone":"+44 1726 822239",
    "sg:postcode":"PL26 7XQ",
    "sg:province":"Cornwall",
    "wof:name":"Whitemoor Post Office",
    "wof:placetype":"venue"
},
  "geometry": {"coordinates":[-4.856744,50.379559],"type":"Point"}
}