{
  "type": "Feature",
  "properties": {
    "addr:full":"Dalgety Business Centre, Thorpe Way Banbury Oxfordshire OX16 4SA",
    "addr:postcode":"ox16 4sa",
    "addr:street":"Thorpe Way",
    "iso:country":"GB",
    "sg:address":"Dalgety Business Centre, Thorpe Way",
    "sg:city":"Banbury",
    "sg:classifiers":[
        {
            "category":"Autos & Motor Vehicles",
            "subcategory":"Auto Supplies",
            "type":"Retail Goods"
        }
    ],
    "sg:postcode":"OX16 4SA",
    "sg:province":"Oxfordshire",
    "sg:tags":[
        "rubber",
        "tyre"
    ],
    "wof:name":"M Reidmore",
    "wof:placetype":"venue"
},
  "geometry": {"coordinates":[-1.340028,52.061111],"type":"Point"}
}