{
  "type": "Feature",
  "properties": {
    "iso:country":"GB",
    "sg:address":"Over Haddon, Hungate La",
    "sg:city":"Harrogate",
    "sg:classifiers":[
        {
            "category":"Building & Trades",
            "subcategory":"Construction",
            "type":"Services"
        }
    ],
    "sg:phone":"+44 1629 812209",
    "sg:postcode":"HG3 3QL",
    "sg:province":"North Yorkshire",
    "sg:tags":[
        "decorator",
        "painter"
    ],
    "wof:name":"G R Pendleton & Son",
    "wof:placetype":"venue"
},
  "geometry": {"coordinates":[-1.50056,54.091888],"type":"Point"}
}