{
  "type": "Feature",
  "properties": {
    "iso:country":"GB",
    "sg:address":"1 Bower Terrace, Tunbridge Road",
    "sg:city":"Maidstone",
    "sg:classifiers":[
        {
            "category":"Professional",
            "subcategory":"Management & Consulting",
            "type":"Services"
        }
    ],
    "sg:phone":"+44 1622 675547",
    "sg:postcode":"ME16 8RY",
    "sg:province":"Kent",
    "sg:tags":[
        "consultant",
        "business"
    ],
    "wof:name":"Maidstone Enterprise Agency Ltd.",
    "wof:placetype":"venue"
},
  "geometry": {"coordinates":[0.5128470063,51.2702674866],"type":"Point"}
}