{
  "type": "Feature",
  "properties": {
    "iso:country":"GB",
    "sg:address":"1 Recreation Road",
    "sg:city":"Norwich",
    "sg:classifiers":[
        {
            "category":"Health Services",
            "subcategory":"Dentist",
            "type":"Services"
        }
    ],
    "sg:phone":"+44 1603 458206",
    "sg:postcode":"NR2 3PA",
    "sg:province":"Norfolk",
    "wof:name":"Recreation Road Dental Surgery",
    "wof:placetype":"venue"
},
  "geometry": {"coordinates":[1.2697880268,52.629283905],"type":"Point"}
}