{
  "type": "Feature",
  "properties": {
    "addr:full":"393 High Road, Harrow Weald Harrow Greater London HA3 6EN",
    "addr:housenumber":"393",
    "addr:postcode":"ha3 6en",
    "addr:street":"High Road",
    "iso:country":"GB",
    "sg:address":"393 High Road, Harrow Weald",
    "sg:city":"Harrow",
    "sg:classifiers":[
        {
            "category":"Shopping",
            "subcategory":"Gifts & Souvenirs",
            "type":"Retail Goods"
        }
    ],
    "sg:phone":"+44 20 8427 1631",
    "sg:postcode":"HA3 6EN",
    "sg:province":"Greater London",
    "sg:tags":[
        "poster",
        "card"
    ],
    "wof:name":"Love & Best Wishes",
    "wof:placetype":"venue"
},
  "geometry": {"coordinates":[-0.3402610123,51.6048316956],"type":"Point"}
}