{
  "type": "Feature",
  "properties": {
    "addr:full":"Campbell Way, Fair Oak Eastleigh Hampshire SO50 7AX",
    "addr:postcode":"so50 7ax",
    "addr:street":"Campbell Way",
    "iso:country":"GB",
    "sg:address":"Campbell Way, Fair Oak",
    "sg:city":"Eastleigh",
    "sg:classifiers":[
        {
            "category":"Arena",
            "subcategory":"Sports Club",
            "type":"Entertainment"
        }
    ],
    "sg:phone":"+44 23 8069 5107",
    "sg:postcode":"SO50 7AX",
    "sg:province":"Hampshire",
    "wof:name":"Fair Oak Squash Club",
    "wof:placetype":"venue"
},
  "geometry": {"coordinates":[-1.290794,50.965431],"type":"Point"}
}