{
  "type": "Feature",
  "properties": {
    "addr:full":"3 Mill Rd Cambridge Cambridgeshire CB4 5ST",
    "addr:housenumber":"3",
    "addr:postcode":"cb4 5st",
    "addr:street":"Mill Rd",
    "iso:country":"GB",
    "sg:address":"3 Mill Rd",
    "sg:city":"Cambridge",
    "sg:classifiers":[
        {
            "category":"Building & Trades",
            "subcategory":"Landscaping Services",
            "type":"Services"
        }
    ],
    "sg:phone":"+44 1954 230579",
    "sg:postcode":"CB4 5ST",
    "sg:province":"Cambridgeshire",
    "sg:tags":[
        "landscape",
        "contractor"
    ],
    "wof:name":"K.J. Willis Landscapes",
    "wof:placetype":"venue"
},
  "geometry": {"coordinates":[-0.054333,52.294521],"type":"Point"}
}