{
  "type": "Feature",
  "properties": {
    "addr:full":"22 St Johns Road Faversham Kent ME13 8EL",
    "addr:housenumber":"22",
    "addr:postcode":"me13 8el",
    "addr:street":"St Johns Road",
    "iso:country":"GB",
    "sg:address":"22 St Johns Road",
    "sg:city":"Faversham",
    "sg:classifiers":[
        {
            "category":"Building & Trades",
            "subcategory":"Plumbing",
            "type":"Services"
        },
        {
            "category":"Building & Trades",
            "subcategory":"Construction",
            "type":"Services"
        }
    ],
    "sg:phone":"+44 1795 591096",
    "sg:postcode":"ME13 8EL",
    "sg:province":"Kent",
    "sg:tags":[
        "excavation",
        "groundwork",
        "plumber",
        "contractor"
    ],
    "wof:name":"M A Brice Mole Services",
    "wof:placetype":"venue"
},
  "geometry": {"coordinates":[0.894903,51.313499],"type":"Point"}
}