{
  "type": "Feature",
  "properties": {
    "iso:country":"GB",
    "sg:address":"The Barn, Becks Green Lane, Ilketshall St Andrew",
    "sg:city":"Beccles",
    "sg:classifiers":[
        {
            "category":"Wholesale",
            "subcategory":"Music Publishers",
            "type":"Manufacturing & Wholesale Goods"
        }
    ],
    "sg:phone":"+44 1986 781682",
    "sg:postcode":"NR34 8NB",
    "sg:province":"Norfolk",
    "sg:tags":[
        "record"
    ],
    "wof:name":"New World Music Ltd.",
    "wof:placetype":"venue"
},
  "geometry": {"coordinates":[1.507875,52.402939],"type":"Point"}
}