{
  "type": "Feature",
  "properties": {
    "iso:country":"GB",
    "sg:address":"36 Park Terrace",
    "sg:city":"Stirling",
    "sg:classifiers":[
        {
            "category":"Organizations",
            "subcategory":"Non-profit Organization",
            "type":"Services"
        }
    ],
    "sg:phone":"+44 1786 450335",
    "sg:postcode":"FK8 2JR",
    "sg:province":"Stirling",
    "sg:tags":[
        "charitable",
        "organisation",
        "voluntary",
        "charity"
    ],
    "wof:name":"Aberlour Childcare Trust",
    "wof:placetype":"venue"
},
  "geometry": {"coordinates":[-3.948666,56.111614],"type":"Point"}
}