{
  "type": "Feature",
  "properties": {
    "addr:full":"Weoley Park Road, Selly Oak Birmingham West Midlands B29 6QY",
    "addr:postcode":"b29 6qy",
    "addr:street":"Weoley Park Road",
    "iso:country":"GB",
    "sg:address":"Weoley Park Road, Selly Oak",
    "sg:city":"Birmingham",
    "sg:classifiers":[
        {
            "category":"Education",
            "subcategory":"University",
            "type":"Public Place"
        }
    ],
    "sg:phone":"+44 121 472 7245",
    "sg:postcode":"B29 6QY",
    "sg:province":"West Midlands",
    "sg:tags":[
        "higher"
    ],
    "wof:name":"Westhill College",
    "wof:placetype":"venue"
},
  "geometry": {"coordinates":[-1.9449779987,52.4418945312],"type":"Point"}
}