{
  "type": "Feature",
  "properties": {
    "addr:full":"Station Yard, Stanwell Rd Ashford Greater London TW15 3DT",
    "addr:postcode":"tw15 3dt",
    "addr:street":"Stanwell Rd",
    "iso:country":"GB",
    "sg:address":"Station Yard, Stanwell Rd",
    "sg:city":"Ashford",
    "sg:classifiers":[
        {
            "category":"Manufacturing",
            "subcategory":"Building Materials",
            "type":"Manufacturing & Wholesale Goods"
        }
    ],
    "sg:phone":"+44 1784 256111",
    "sg:postcode":"TW15 3DT",
    "sg:province":"Greater London",
    "sg:tags":[
        "merchant",
        "builder"
    ],
    "wof:name":"Builder Center",
    "wof:placetype":"venue"
},
  "geometry": {"coordinates":[-0.470974,51.43787],"type":"Point"}
}