{
  "type": "Feature",
  "properties": {
    "iso:country":"GB",
    "sg:address":"Unit 4, Rocky Lane, Eccles",
    "sg:city":"Manchester",
    "sg:classifiers":[
        {
            "category":"Retail",
            "subcategory":"Auto Rental",
            "type":"Services"
        }
    ],
    "sg:postcode":"M30 9LS",
    "sg:province":"Greater Manchester",
    "sg:tags":[
        "car"
    ],
    "wof:name":"J B Mobiles",
    "wof:placetype":"venue"
},
  "geometry": {"coordinates":[-2.350174,53.49641],"type":"Point"}
}