{
  "type": "Feature",
  "properties": {
    "iso:country":"GB",
    "sg:address":"21 Northgate Street",
    "sg:city":"Great Yarmouth",
    "sg:classifiers":[
        {
            "category":"Food & Beverages",
            "subcategory":"Bakery",
            "type":"Retail Goods"
        }
    ],
    "sg:phone":"+44 1493 842592",
    "sg:postcode":"NR30 1BA",
    "sg:province":"Norfolk",
    "sg:tags":[
        "confectionery"
    ],
    "wof:name":"G E Bales & Son",
    "wof:placetype":"venue"
},
  "geometry": {"coordinates":[1.7260899544,52.6123580933],"type":"Point"}
}