{
  "type": "Feature",
  "properties": {
    "addr:full":"7 Mayes Clo, Bowthorpe Norwich Norfolk NR5 9AR",
    "addr:housenumber":"7",
    "addr:postcode":"nr5 9ar",
    "addr:street":"Mayes Clo;Norwich Norfolk",
    "iso:country":"GB",
    "sg:address":"7 Mayes Clo, Bowthorpe",
    "sg:city":"Norwich",
    "sg:classifiers":[
        {
            "category":"Building & Trades",
            "subcategory":"Plumbing",
            "type":"Services"
        }
    ],
    "sg:postcode":"NR5 9AR",
    "sg:province":"Norfolk",
    "sg:tags":[
        "heating"
    ],
    "wof:name":"Staff,K T,",
    "wof:placetype":"venue"
},
  "geometry": {"coordinates":[1.229081,52.639545],"type":"Point"}
}