{
  "type": "Feature",
  "properties": {
    "addr:full":"12 Spring Garden Centre Buxton Derbyshire SK17 6BJ",
    "addr:housenumber":"12",
    "addr:postcode":"sk17 6bj",
    "addr:street":"Spring Garden",
    "iso:country":"GB",
    "sg:address":"12 Spring Garden Centre",
    "sg:city":"Buxton",
    "sg:classifiers":[
        {
            "category":"Shopping",
            "subcategory":"Pharmacy",
            "type":"Retail Goods"
        }
    ],
    "sg:phone":"+44 1298 79315",
    "sg:postcode":"SK17 6BJ",
    "sg:province":"Derbyshire",
    "sg:tags":[
        "store",
        "drug"
    ],
    "wof:name":"Superdrug Stores Plc",
    "wof:placetype":"venue"
},
  "geometry": {"coordinates":[-1.9126629829,53.2588310242],"type":"Point"}
}