{
  "type": "Feature",
  "properties": {
    "addr:full":"9a Bonnyrigg Rd Dalkeith City of Edinburgh EH22 3EY",
    "addr:housenumber":"9a",
    "addr:postcode":"eh22 3ey",
    "addr:street":"Bonnyrigg Rd",
    "iso:country":"GB",
    "sg:address":"9a Bonnyrigg Rd",
    "sg:city":"Dalkeith",
    "sg:classifiers":[
        {
            "category":"Social Services",
            "subcategory":"Retirement Home",
            "type":"Services"
        }
    ],
    "sg:phone":"+44 131 663 3155",
    "sg:postcode":"EH22 3EY",
    "sg:province":"City of Edinburgh",
    "sg:tags":[
        "residential",
        "care"
    ],
    "wof:name":"Highbank Day Centre For The Elderly",
    "wof:placetype":"venue"
},
  "geometry": {"coordinates":[-3.078873,55.872921],"type":"Point"}
}