{
  "type": "Feature",
  "properties": {
    "addr:full":"41 Regent Way Hamilton South Lanarkshire ML3 7EF",
    "addr:housenumber":"41",
    "addr:postcode":"ml3 7ef",
    "addr:street":"Regent Way",
    "iso:country":"GB",
    "sg:address":"41 Regent Way",
    "sg:city":"Hamilton",
    "sg:classifiers":[
        {
            "category":"Shopping",
            "subcategory":"Hobbies, Toys, & Games",
            "type":"Retail Goods"
        },
        {
            "category":"Shopping",
            "subcategory":"News",
            "type":"Retail Goods"
        }
    ],
    "sg:phone":"+44 1698 283568",
    "sg:postcode":"ML3 7EF",
    "sg:province":"South Lanarkshire",
    "sg:tags":[
        "shop",
        "toy",
        "newsagent",
        "sale"
    ],
    "wof:name":"Early Learning Centre Ltd",
    "wof:placetype":"venue"
},
  "geometry": {"coordinates":[-4.052891,55.777321],"type":"Point"}
}