{
  "type": "Feature",
  "properties": {
    "addr:full":"1 Hall Street, Featherstone Pontefract West Yorkshire WF7 5LS",
    "addr:housenumber":"1",
    "addr:postcode":"wf7 5ls",
    "addr:street":"Hall Street;West",
    "iso:country":"GB",
    "sg:address":"1 Hall Street, Featherstone",
    "sg:city":"Pontefract",
    "sg:classifiers":[
        {
            "category":"Manufacturing",
            "subcategory":"Tools & Machinery",
            "type":"Manufacturing & Wholesale Goods"
        }
    ],
    "sg:phone":"+44 1977 794311",
    "sg:postcode":"WF7 5LS",
    "sg:province":"West Yorkshire",
    "sg:tags":[
        "society",
        "friendly"
    ],
    "wof:name":"New Horizon Insurance Services Ltd.",
    "wof:placetype":"venue"
},
  "geometry": {"coordinates":[-1.3501800299,53.6738319397],"type":"Point"}
}