{
  "type": "Feature",
  "properties": {
    "addr:full":"Rosslyn Road Barking Essex IG11 9UH",
    "addr:postcode":"ig11 9uh",
    "addr:street":"Rosslyn Road",
    "iso:country":"GB",
    "sg:address":"Rosslyn Road",
    "sg:city":"Barking",
    "sg:classifiers":[
        {
            "category":"Education",
            "subcategory":"School",
            "type":"Public Place"
        }
    ],
    "sg:phone":"+44 20 8270 4000",
    "sg:postcode":"IG11 9UH",
    "sg:province":"Essex",
    "sg:tags":[
        "local",
        "authority"
    ],
    "wof:name":"Eastbury Lower Comprehensive School",
    "wof:placetype":"venue"
},
  "geometry": {"coordinates":[0.085755,51.538681],"type":"Point"}
}