{
  "type": "Feature",
  "properties": {
    "iso:country":"GB",
    "sg:address":"Lancaster House, Great Austins",
    "sg:city":"Farnham",
    "sg:classifiers":[
        {
            "category":"Real Estate",
            "subcategory":"Developer",
            "type":"Services"
        }
    ],
    "sg:postcode":"GU9 8JQ",
    "sg:province":"Surrey",
    "sg:tags":[
        "property"
    ],
    "wof:name":"Monogram Properties",
    "wof:placetype":"venue"
},
  "geometry": {"coordinates":[-0.787741,51.207943],"type":"Point"}
}