{
  "type": "Feature",
  "properties": {
    "iso:country":"GB",
    "sg:address":"2nd Floor",
    "sg:city":"Amersham",
    "sg:classifiers":[
        {
            "category":"Utilities",
            "subcategory":"Sewage",
            "type":"Services"
        }
    ],
    "sg:phone":"+44 1494 725530",
    "sg:postcode":"HP6 5EL",
    "sg:province":"Buckinghamshire",
    "sg:tags":[
        "acoustic",
        "consultant"
    ],
    "wof:name":"Moir Hands & Associates",
    "wof:placetype":"venue"
},
  "geometry": {"coordinates":[-0.6107590199,51.6845817566],"type":"Point"}
}