{
  "type": "Feature",
  "properties": {
    "iso:country":"GB",
    "sg:address":"Cauldon Avenue",
    "sg:city":"Newcastle",
    "sg:classifiers":[
        {
            "category":"Education",
            "subcategory":"School",
            "type":"Public Place"
        },
        {
            "category":"Government",
            "subcategory":"Office",
            "type":"Public Place"
        }
    ],
    "sg:phone":"+44 1782 297700",
    "sg:postcode":"ST5 8JN",
    "sg:province":"Staffordshire",
    "sg:tags":[
        "local",
        "authority"
    ],
    "wof:name":"Bradwell County Primary School",
    "wof:placetype":"venue"
},
  "geometry": {"coordinates":[-2.2361700535,53.0417060852],"type":"Point"}
}