{
  "type": "Feature",
  "properties": {
    "addr:full":"12 Castle St Truro Cornwall TR1 3AF",
    "addr:housenumber":"12",
    "addr:postcode":"tr1 3af",
    "addr:street":"Castle St",
    "iso:country":"GB",
    "sg:address":"12 Castle St",
    "sg:city":"Truro",
    "sg:classifiers":[
        {
            "category":"Professional",
            "subcategory":"Lawyer & Legal Services",
            "type":"Services"
        }
    ],
    "sg:postcode":"TR1 3AF",
    "sg:province":"Cornwall",
    "sg:tags":[
        "conveyancing"
    ],
    "wof:name":"Morris,Graham,",
    "wof:placetype":"venue"
},
  "geometry": {"coordinates":[-5.055738,50.264225],"type":"Point"}
}