{
  "type": "Feature",
  "properties": {
    "addr:full":"Unit 16 Mowlem Trading Est, Leeside Rd, Tottenham London Greater London N17 0QJ",
    "addr:housenumber":"unit 16",
    "addr:postcode":"n17 0qj",
    "addr:street":"Mowlem Trading Est Leeside Rd",
    "iso:country":"GB",
    "sg:address":"Unit 16 Mowlem Trading Est, Leeside Rd, Tottenham",
    "sg:city":"London",
    "sg:classifiers":[
        {
            "category":"Wholesale",
            "subcategory":"Electrical",
            "type":"Manufacturing & Wholesale Goods"
        },
        {
            "category":"Shopping",
            "subcategory":"Computers & Home Electronics",
            "type":"Retail Goods"
        }
    ],
    "sg:phone":"+44 20 8880 3870",
    "sg:postcode":"N17 0QJ",
    "sg:province":"Greater London",
    "sg:tags":[
        "wholesaler"
    ],
    "wof:name":"Newey & Eyre Ltd",
    "wof:placetype":"venue"
},
  "geometry": {"coordinates":[-0.047694,51.60553],"type":"Point"}
}