{
  "type": "Feature",
  "properties": {
    "iso:country":"GB",
    "sg:address":"8 The Ridgeway",
    "sg:city":"Walton-on-thames",
    "sg:classifiers":[
        {
            "category":"Education",
            "subcategory":"Music School",
            "type":"Public Place"
        }
    ],
    "sg:phone":"+44 1932 223995",
    "sg:postcode":"KT12 1BH",
    "sg:province":"Surrey",
    "sg:tags":[
        "teacher"
    ],
    "wof:name":"Gary Verth",
    "wof:placetype":"venue"
},
  "geometry": {"coordinates":[-0.426929,51.386703],"type":"Point"}
}