{
  "type": "Feature",
  "properties": {
    "addr:full":"3 Elm Gro London Greater London SW19 4HE",
    "addr:housenumber":"3",
    "addr:postcode":"sw19 4he",
    "addr:street":"Elm Gro",
    "iso:country":"GB",
    "sg:address":"3 Elm Gro",
    "sg:city":"London",
    "sg:classifiers":[
        {
            "category":"Organizations",
            "subcategory":"Community Association",
            "type":"Services"
        }
    ],
    "sg:postcode":"SW19 4HE",
    "sg:province":"Greater London",
    "sg:tags":[
        "society",
        "housing"
    ],
    "wof:name":"Louie Black House",
    "wof:placetype":"venue"
},
  "geometry": {"coordinates":[-0.21514,51.4168701172],"type":"Point"}
}