{
  "type": "Feature",
  "properties": {
    "addr:full":"High Street, Sennybridge Brecon Powys LD3 8PH",
    "addr:postcode":"ld3 8ph",
    "addr:street":"High Street",
    "iso:country":"GB",
    "sg:address":"High Street, Sennybridge",
    "sg:city":"Brecon",
    "sg:classifiers":[
        {
            "category":"Bars & Pubs",
            "type":"Food & Drink"
        }
    ],
    "sg:phone":"+44 1874 636346",
    "sg:postcode":"LD3 8PH",
    "sg:province":"Powys",
    "sg:tags":[
        "pubs",
        "inn"
    ],
    "wof:name":"The Red Lion Hotel",
    "wof:placetype":"venue"
},
  "geometry": {"coordinates":[-3.563175,51.937592],"type":"Point"}
}