{
  "type": "Feature",
  "properties": {
    "addr:full":"Alexander House, Staden Business Park Buxton Derbyshire SK17 9RZ",
    "addr:postcode":"sk17 9rz",
    "addr:street":"Staden Business Park",
    "iso:country":"GB",
    "sg:address":"Alexander House, Staden Business Park",
    "sg:city":"Buxton",
    "sg:classifiers":[
        {
            "category":"Professional",
            "subcategory":"Computer Services",
            "type":"Services"
        }
    ],
    "sg:phone":"+44 845 345 2111",
    "sg:postcode":"SK17 9RZ",
    "sg:province":"Derbyshire",
    "sg:tags":[
        "system",
        "software"
    ],
    "wof:name":"Vardells",
    "wof:placetype":"venue"
},
  "geometry": {"coordinates":[-1.9130489826,53.2603874207],"type":"Point"}
}