{
  "type": "Feature",
  "properties": {
    "addr:full":"39 Chertsey Road Woking Surrey GU21 5AJ",
    "addr:housenumber":"39",
    "addr:postcode":"gu21 5aj",
    "addr:street":"Chertsey Road",
    "iso:country":"GB",
    "sg:address":"39 Chertsey Road",
    "sg:city":"Woking",
    "sg:classifiers":[
        {
            "category":"Restaurant",
            "type":"Food & Drink"
        }
    ],
    "sg:phone":"+44 1483 728820",
    "sg:postcode":"GU21 5AJ",
    "sg:province":"Surrey",
    "sg:tags":[
        "indian"
    ],
    "wof:name":"Bombay Nights",
    "wof:placetype":"venue"
},
  "geometry": {"coordinates":[-0.555481,51.320377],"type":"Point"}
}