{
  "type": "Feature",
  "properties": {
    "addr:full":"4 Chabstand Bristol Somerset BS20 7HW",
    "addr:housenumber":"4",
    "addr:postcode":"bs20 7hw",
    "addr:street":"Chabstand",
    "iso:country":"GB",
    "sg:address":"4 Chabstand",
    "sg:city":"Bristol",
    "sg:classifiers":[
        {
            "category":"Personal",
            "subcategory":"Beauty Salon",
            "type":"Services"
        }
    ],
    "sg:phone":"+44 1275 842777",
    "sg:postcode":"BS20 7HW",
    "sg:province":"Somerset",
    "wof:name":"Natural Beauty At Rj's",
    "wof:placetype":"venue"
},
  "geometry": {"coordinates":[-2.756728,51.462864],"type":"Point"}
}