{
  "type": "Feature",
  "properties": {
    "addr:full":"Unit 3 Tregoniggie Industrial Estate Falmouth Cornwall TR11 4SN",
    "addr:housenumber":"unit 3;estate",
    "addr:postcode":"tr11 4sn",
    "addr:street":"Tregoniggie Industrial",
    "iso:country":"GB",
    "sg:address":"Unit 3 Tregoniggie Industrial Estate",
    "sg:city":"Falmouth",
    "sg:classifiers":[
        {
            "category":"Professional",
            "subcategory":"Engineering",
            "type":"Services"
        }
    ],
    "sg:phone":"+44 1326 378242",
    "sg:postcode":"TR11 4SN",
    "sg:province":"Cornwall",
    "sg:tags":[
        "contractor",
        "electrical",
        "engineer"
    ],
    "wof:name":"David & Magdeline Anne Addinall",
    "wof:placetype":"venue"
},
  "geometry": {"coordinates":[-5.0800328255,50.1522064209],"type":"Point"}
}