{
  "type": "Feature",
  "properties": {
    "addr:full":"Albany Mill, Lower Middleton St Ilkeston Derbyshire DE7 5TN",
    "addr:postcode":"de7 5tn",
    "addr:street":"Albany;Lower Middleton St",
    "iso:country":"GB",
    "sg:address":"Albany Mill, Lower Middleton St",
    "sg:city":"Ilkeston",
    "sg:classifiers":[
        {
            "category":"Manufacturing",
            "subcategory":"Textiles",
            "type":"Manufacturing & Wholesale Goods"
        }
    ],
    "sg:phone":"+44 115 930 0001",
    "sg:postcode":"DE7 5TN",
    "sg:province":"Derbyshire",
    "wof:name":"Albany Textiles Ltd",
    "wof:placetype":"venue"
},
  "geometry": {"coordinates":[-1.294960022,52.9767341614],"type":"Point"}
}