{
  "type": "Feature",
  "properties": {
    "addr:full":"106 Taff Street Pontypridd Caerphilly CF37 4UY",
    "addr:housenumber":"106",
    "addr:postcode":"cf37 4uy",
    "addr:street":"Taff Street",
    "iso:country":"GB",
    "sg:address":"106 Taff Street",
    "sg:city":"Pontypridd",
    "sg:classifiers":[
        {
            "category":"Organizations",
            "subcategory":"Non-profit Organization",
            "type":"Services"
        }
    ],
    "sg:phone":"+44 1443 403440",
    "sg:postcode":"CF37 4UY",
    "sg:province":"Caerphilly",
    "sg:tags":[
        "organisation",
        "voluntary",
        "charity"
    ],
    "wof:name":"British Heart Foundation",
    "wof:placetype":"venue"
},
  "geometry": {"coordinates":[-3.3406999111,51.6018943787],"type":"Point"}
}