{
  "type": "Feature",
  "properties": {
    "addr:full":"7 Lomond Drive Dumbarton Argyll and Bute G82 3AT",
    "addr:housenumber":"7",
    "addr:postcode":"g82 3at",
    "addr:street":"Lomond Drive",
    "iso:country":"GB",
    "sg:address":"7 Lomond Drive",
    "sg:city":"Dumbarton",
    "sg:classifiers":[
        {
            "category":"Building & Trades",
            "subcategory":"Landscaping Services",
            "type":"Services"
        }
    ],
    "sg:postcode":"G82 3AT",
    "sg:province":"Argyll and Bute",
    "sg:tags":[
        "landscape",
        "contractor"
    ],
    "wof:name":"J R McPherson Landscapes",
    "wof:placetype":"venue"
},
  "geometry": {"coordinates":[-4.5549502373,55.9566307068],"type":"Point"}
}