{
  "type": "Feature",
  "properties": {
    "iso:country":"GB",
    "sg:address":"Heath Farm, Stanton Road",
    "sg:city":"Burton-on-trent",
    "sg:classifiers":[
        {
            "category":"Farming",
            "subcategory":"Livestock Farm",
            "type":"Manufacturing & Wholesale Goods"
        },
        {
            "category":"Farming",
            "subcategory":"Farm",
            "type":"Manufacturing & Wholesale Goods"
        }
    ],
    "sg:postcode":"DE15 9SQ",
    "sg:province":"Derbyshire",
    "sg:tags":[
        "mixed",
        "crop",
        "others"
    ],
    "wof:name":"Steven John Thirlby",
    "wof:placetype":"venue"
},
  "geometry": {"coordinates":[-1.599828,52.774734],"type":"Point"}
}