{
  "type": "Feature",
  "properties": {
    "iso:country":"GB",
    "sg:address":"1 Savoy Court, Strand",
    "sg:city":"London",
    "sg:classifiers":[
        {
            "category":"Banks & Credit Unions",
            "subcategory":"Bureau De Change",
            "type":"Services"
        }
    ],
    "sg:phone":"+44 20 7240 1521",
    "sg:postcode":"WC2R 0EZ",
    "sg:province":"Greater London",
    "wof:name":"American Express Europe Ltd.",
    "wof:placetype":"venue"
},
  "geometry": {"coordinates":[-0.120887,51.510273],"type":"Point"}
}