{
  "type": "Feature",
  "properties": {
    "iso:country":"GB",
    "sg:address":"Kettering Road",
    "sg:city":"Northampton",
    "sg:classifiers":[
        {
            "category":"Autos & Motor Vehicles",
            "subcategory":"Fuel & Gas Station",
            "type":"Retail Goods"
        }
    ],
    "sg:postcode":"NN2 7HL",
    "sg:province":"Northamptonshire",
    "sg:tags":[
        "hr",
        "petrol"
    ],
    "wof:name":"Kettering Road Service Station",
    "wof:placetype":"venue"
},
  "geometry": {"coordinates":[-0.871694,52.257912],"type":"Point"}
}