{
  "type": "Feature",
  "properties": {
    "addr:full":"Boddam Library, 26 Queens Road, Boddam Peterhead Aberdeenshire AB42 3AX",
    "addr:housenumber":"26",
    "addr:postcode":"ab42 3ax",
    "addr:street":"Queens Road",
    "iso:country":"GB",
    "sg:address":"Boddam Library, 26 Queens Road, Boddam",
    "sg:city":"Peterhead",
    "sg:classifiers":[
        {
            "category":"Education",
            "subcategory":"Library",
            "type":"Public Place"
        },
        {
            "category":"Government",
            "subcategory":"Office",
            "type":"Public Place"
        }
    ],
    "sg:phone":"+44 1779 473479",
    "sg:postcode":"AB42 3AX",
    "sg:province":"Aberdeenshire",
    "sg:tags":[
        "book",
        "local"
    ],
    "wof:name":"Boddam Library",
    "wof:placetype":"venue"
},
  "geometry": {"coordinates":[-1.7789540291,57.4707489014],"type":"Point"}
}