{
  "type": "Feature",
  "properties": {
    "iso:country":"GB",
    "sg:address":"166 Heath End Road",
    "sg:city":"Nuneaton",
    "sg:classifiers":[
        {
            "category":"Autos & Motor Vehicles",
            "subcategory":"Boat Sales",
            "type":"Retail Goods"
        },
        {
            "category":"Retail",
            "subcategory":"Auto Repair",
            "type":"Services"
        }
    ],
    "sg:phone":"+44 24 7637 2033",
    "sg:postcode":"CV10 7JE",
    "sg:province":"Leicestershire",
    "sg:tags":[
        "engine",
        "car",
        "rebuilders",
        "specialist"
    ],
    "wof:name":"Odus Commercial",
    "wof:placetype":"venue"
},
  "geometry": {"coordinates":[-1.4795819521,52.5129356384],"type":"Point"}
}