{
  "type": "Feature",
  "properties": {
    "addr:full":"29-31 Southport Road Chorley Lancashire PR7 1LF",
    "addr:housenumber":"29-31",
    "addr:postcode":"pr7 1lf",
    "addr:street":"Southport Road",
    "iso:country":"GB",
    "sg:address":"29-31 Southport Road",
    "sg:city":"Chorley",
    "sg:classifiers":[
        {
            "category":"Health Services",
            "subcategory":"Nursing And Care Facility",
            "type":"Services"
        },
        {
            "category":"Social Services",
            "subcategory":"Retirement Home",
            "type":"Services"
        }
    ],
    "sg:phone":"+44 1257 264626",
    "sg:postcode":"PR7 1LF",
    "sg:province":"Lancashire",
    "sg:tags":[
        "residential",
        "rest"
    ],
    "wof:name":"Westcliffe Homes Ltd",
    "wof:placetype":"venue"
},
  "geometry": {"coordinates":[-2.640588,53.653748],"type":"Point"}
}