{
  "type": "Feature",
  "properties": {
    "addr:full":"16 Park Gate, Somerhill Road Hove East Sussex BN3 1RL",
    "addr:housenumber":"16",
    "addr:postcode":"bn3 1rl",
    "addr:street":"Park Gate Somerhill Road",
    "iso:country":"GB",
    "sg:address":"16 Park Gate, Somerhill Road",
    "sg:city":"Hove",
    "sg:classifiers":[
        {
            "category":"Recreation",
            "subcategory":"Gun Range",
            "type":"Entertainment"
        }
    ],
    "sg:postcode":"BN3 1RL",
    "sg:province":"East Sussex",
    "sg:tags":[
        "operator",
        "tour"
    ],
    "wof:name":"Connaught Cultural Tours",
    "wof:placetype":"venue"
},
  "geometry": {"coordinates":[-0.158174,50.829823],"type":"Point"}
}