{
  "type": "Feature",
  "properties": {
    "addr:full":"18 Bridge Street Pershore Worcestershire WR10 1AT",
    "addr:housenumber":"18",
    "addr:postcode":"wr10 1at",
    "addr:street":"Bridge Street",
    "iso:country":"GB",
    "sg:address":"18 Bridge Street",
    "sg:city":"Pershore",
    "sg:classifiers":[
        {
            "category":"Shopping",
            "subcategory":"Clothing, Apparel, & Fashions",
            "type":"Retail Goods"
        }
    ],
    "sg:phone":"+44 1386 552121",
    "sg:postcode":"WR10 1AT",
    "sg:province":"Worcestershire",
    "sg:tags":[
        "dresswear"
    ],
    "wof:name":"The House of Beautiful Clothes",
    "wof:placetype":"venue"
},
  "geometry": {"coordinates":[-2.0729420185,52.1070747375],"type":"Point"}
}