{
  "type": "Feature",
  "properties": {
    "iso:country":"GB",
    "sg:address":"Unit 15, Osier Way, Park Street Industrial Estate",
    "sg:city":"Aylesbury",
    "sg:classifiers":[
        {
            "category":"Manufacturing",
            "subcategory":"Rubber & Plastics",
            "type":"Manufacturing & Wholesale Goods"
        }
    ],
    "sg:phone":"+44 1296 425689",
    "sg:postcode":"HP20 1EB",
    "sg:province":"Buckinghamshire",
    "sg:tags":[
        "mould"
    ],
    "wof:name":"Mall Moulds",
    "wof:placetype":"venue"
},
  "geometry": {"coordinates":[-0.7987769842,51.8178215027],"type":"Point"}
}