{
  "type": "Feature",
  "properties": {
    "addr:full":"195 St Fagans Road Cardiff Cardiff CF5 3DW",
    "addr:housenumber":"195",
    "addr:postcode":"cf5 3dw",
    "addr:street":"St Fagans Road",
    "iso:country":"GB",
    "sg:address":"195 St Fagans Road",
    "sg:city":"Cardiff",
    "sg:classifiers":[
        {
            "category":"Building & Trades",
            "subcategory":"Construction",
            "type":"Services"
        }
    ],
    "sg:phone":"+44 29 2056 6922",
    "sg:postcode":"CF5 3DW",
    "sg:province":"Cardiff",
    "sg:tags":[
        "platform",
        "work",
        "scaffolding"
    ],
    "wof:name":"Cardiff Scaffolding",
    "wof:placetype":"venue"
},
  "geometry": {"coordinates":[-3.243792057,51.4896774292],"type":"Point"}
}