{
  "type": "Feature",
  "properties": {
    "addr:full":"117 Hampstead Road London Greater London NW1 3EE",
    "addr:housenumber":"117",
    "addr:postcode":"nw1 3ee",
    "addr:street":"Hampstead Road",
    "iso:country":"GB",
    "sg:address":"117 Hampstead Road",
    "sg:city":"London",
    "sg:classifiers":[
        {
            "category":"Food & Beverages",
            "subcategory":"Fruits & Vegetables",
            "type":"Retail Goods"
        }
    ],
    "sg:phone":"+44 20 7388 8098",
    "sg:postcode":"NW1 3EE",
    "sg:province":"Greater London",
    "sg:tags":[
        "greengrocer"
    ],
    "wof:name":"Polok International Foods",
    "wof:placetype":"venue"
},
  "geometry": {"coordinates":[-0.138695,51.528034],"type":"Point"}
}