{
  "type": "Feature",
  "properties": {
    "iso:country":"GB",
    "sg:address":"5 Buckland Road",
    "sg:city":"Yeovil",
    "sg:classifiers":[
        {
            "category":"Autos & Motor Vehicles",
            "subcategory":"Auto Supplies",
            "type":"Retail Goods"
        }
    ],
    "sg:phone":"+44 1935 474954",
    "sg:postcode":"BA21 5ED",
    "sg:province":"Somerset",
    "sg:tags":[
        "tyre"
    ],
    "wof:name":"Motorway Tyres & Accessories Ltd.",
    "wof:placetype":"venue"
},
  "geometry": {"coordinates":[-2.6102459431,50.9472961426],"type":"Point"}
}