{
  "type": "Feature",
  "properties": {
    "iso:country":"GB",
    "sg:address":"St. Andrew St",
    "sg:city":"Dumfries",
    "sg:classifiers":[
        {
            "category":"Bars & Pubs",
            "type":"Food & Drink"
        }
    ],
    "sg:postcode":"DG1 1BS",
    "sg:province":"Dumfries and Galloway",
    "sg:tags":[
        "pubs",
        "inn"
    ],
    "wof:name":"Halladay,William,",
    "wof:placetype":"venue"
},
  "geometry": {"coordinates":[-3.600649,55.072525],"type":"Point"}
}