{
  "type": "Feature",
  "properties": {
    "iso:country":"GB",
    "sg:address":"Stream Road, Kingswinford",
    "sg:city":"Brierley Hill",
    "sg:classifiers":[
        {
            "category":"Social Services",
            "subcategory":"Retirement Home",
            "type":"Services"
        },
        {
            "category":"Government",
            "subcategory":"Office",
            "type":"Public Place"
        }
    ],
    "sg:phone":"+44 1384 813515",
    "sg:postcode":"DY6 9NP",
    "sg:province":"Staffordshire",
    "sg:tags":[
        "residential",
        "local",
        "care"
    ],
    "wof:name":"New Bradley Hall Residential Care",
    "wof:placetype":"venue"
},
  "geometry": {"coordinates":[-2.166513,52.492943],"type":"Point"}
}