{
  "type": "Feature",
  "properties": {
    "addr:full":"48 Walton St Chelsea Greater London SW3 1RB",
    "addr:housenumber":"48",
    "addr:postcode":"sw3 1rb",
    "addr:street":"Walton St",
    "iso:country":"GB",
    "sg:address":"48 Walton St",
    "sg:city":"Chelsea",
    "sg:classifiers":[
        {
            "category":"Retail",
            "subcategory":"Laundry & Dry Cleaning",
            "type":"Services"
        }
    ],
    "sg:phone":"+44 20 7584 0784",
    "sg:postcode":"SW3 1RB",
    "sg:province":"Greater London",
    "sg:tags":[
        "alteration"
    ],
    "wof:name":"Concorde Of Knightsbridge",
    "wof:placetype":"venue"
},
  "geometry": {"coordinates":[-0.1641290039,51.4965515137],"type":"Point"}
}