{
  "type": "Feature",
  "properties": {
    "addr:full":"Church Close, New Inn Pontypool Monmouthshire NP4 0PE",
    "addr:postcode":"np4 0pe",
    "addr:street":"Church Close New Inn Pontypool",
    "iso:country":"GB",
    "sg:address":"Church Close, New Inn",
    "sg:city":"Pontypool",
    "sg:classifiers":[
        {
            "category":"Social Services",
            "subcategory":"Adult Care",
            "type":"Services"
        },
        {
            "category":"Government",
            "subcategory":"Office",
            "type":"Public Place"
        }
    ],
    "sg:phone":"+44 1495 764081",
    "sg:postcode":"NP4 0PE",
    "sg:province":"Monmouthshire",
    "sg:tags":[
        "housing",
        "local",
        "sheltered"
    ],
    "wof:name":"Church Close Sheltered Housing",
    "wof:placetype":"venue"
},
  "geometry": {"coordinates":[-3.01343894,51.6936416626],"type":"Point"}
}