{
  "type": "Feature",
  "properties": {
    "iso:country":"GB",
    "sg:address":"Whitehouse Service St, Lynn Rd, Gayton",
    "sg:city":"King's Lynn",
    "sg:classifiers":[
        {
            "category":"Autos & Motor Vehicles",
            "subcategory":"Fuel & Gas Station",
            "type":"Retail Goods"
        }
    ],
    "sg:phone":"+44 1553 636368",
    "sg:postcode":"PE32 1QJ",
    "sg:province":"Norfolk",
    "sg:tags":[
        "petrol",
        "filling"
    ],
    "wof:name":"Prior News",
    "wof:placetype":"venue"
},
  "geometry": {"coordinates":[0.5511199832,52.7449111938],"type":"Point"}
}