{
  "type": "Feature",
  "properties": {
    "iso:country":"GB",
    "sg:address":"155 Acre Lane, Cheadle Hulme",
    "sg:city":"Cheadle",
    "sg:classifiers":[
        {
            "category":"Education",
            "subcategory":"Special Training",
            "type":"Public Place"
        }
    ],
    "sg:postcode":"SK8 7PB",
    "sg:province":"Cheshire",
    "sg:tags":[
        "product",
        "centre"
    ],
    "wof:name":"Data Train",
    "wof:placetype":"venue"
},
  "geometry": {"coordinates":[-2.175754,53.357815],"type":"Point"}
}