{
  "type": "Feature",
  "properties": {
    "addr:full":"17 Heathfield Crescent, Whitchurch Bristol City of Bristol BS14 9RG",
    "addr:housenumber":"17",
    "addr:postcode":"bs14 9rg",
    "addr:street":"Heathfield Crescent",
    "iso:country":"GB",
    "sg:address":"17 Heathfield Crescent, Whitchurch",
    "sg:city":"Bristol",
    "sg:classifiers":[
        {
            "category":"Professional",
            "subcategory":"Engineering",
            "type":"Services"
        }
    ],
    "sg:phone":"+44 1275 838866",
    "sg:postcode":"BS14 9RG",
    "sg:province":"City of Bristol",
    "sg:tags":[
        "design",
        "engineer"
    ],
    "wof:name":"M & E Designs",
    "wof:placetype":"venue"
},
  "geometry": {"coordinates":[-2.5700819492,51.4073944092],"type":"Point"}
}