{
  "type": "Feature",
  "properties": {
    "iso:country":"GB",
    "sg:address":"14 Micheldever Road",
    "sg:city":"Whitchurch",
    "sg:classifiers":[
        {
            "category":"Wholesale",
            "subcategory":"Medical Equipment & Supplies",
            "type":"Manufacturing & Wholesale Goods"
        }
    ],
    "sg:phone":"+44 1256 893356",
    "sg:postcode":"RG28 7JG",
    "sg:province":"Hampshire",
    "sg:tags":[
        "hospital"
    ],
    "wof:name":"Meden Stainless Equipment Ltd.",
    "wof:placetype":"venue"
},
  "geometry": {"coordinates":[-1.333423,51.225117],"type":"Point"}
}