{
  "type": "Feature",
  "properties": {
    "addr:full":"12a Lombard Street Newark Nottinghamshire NG24 1XB",
    "addr:housenumber":"12a",
    "addr:postcode":"ng24 1xb",
    "addr:street":"Lombard Street",
    "iso:country":"GB",
    "sg:address":"12a Lombard Street",
    "sg:city":"Newark",
    "sg:classifiers":[
        {
            "category":"Building & Trades",
            "subcategory":"Construction",
            "type":"Services"
        }
    ],
    "sg:phone":"+44 1636 605344",
    "sg:postcode":"NG24 1XB",
    "sg:province":"Nottinghamshire",
    "sg:tags":[
        "repair",
        "window",
        "replacement"
    ],
    "wof:name":"Anglian Home Improvements Ltd",
    "wof:placetype":"venue"
},
  "geometry": {"coordinates":[-0.8097090125,53.0746879578],"type":"Point"}
}