{
  "type": "Feature",
  "properties": {
    "iso:country":"GB",
    "sg:address":"19 Main Road, Jacksdale",
    "sg:city":"Nottingham",
    "sg:classifiers":[
        {
            "category":"Shopping",
            "subcategory":"News",
            "type":"Retail Goods"
        }
    ],
    "sg:phone":"+44 1773 602953",
    "sg:postcode":"NG16 5JU",
    "sg:province":"Derbyshire",
    "sg:tags":[
        "newsagent"
    ],
    "wof:name":"Jacksdale News",
    "wof:placetype":"venue"
},
  "geometry": {"coordinates":[-1.336207,53.059074],"type":"Point"}
}