{
  "type": "Feature",
  "properties": {
    "addr:full":"The Bungalow, High Street, Horseheath Cambridge Cambridgeshire CB1 6QN",
    "addr:postcode":"cb1 6qn",
    "addr:street":"High Street",
    "iso:country":"GB",
    "sg:address":"The Bungalow, High Street, Horseheath",
    "sg:city":"Cambridge",
    "sg:classifiers":[
        {
            "category":"Building & Trades",
            "subcategory":"Construction",
            "type":"Services"
        }
    ],
    "sg:phone":"+44 1223 891655",
    "sg:postcode":"CB1 6QN",
    "sg:province":"Cambridgeshire",
    "sg:tags":[
        "conservation",
        "builder",
        "craft",
        "thatching"
    ],
    "wof:name":"Paul Ernest Mizon",
    "wof:placetype":"venue"
},
  "geometry": {"coordinates":[0.352946,52.099262],"type":"Point"}
}