{
  "type": "Feature",
  "properties": {
    "iso:country":"GB",
    "sg:address":"137 Evelina Rd",
    "sg:city":"London",
    "sg:classifiers":[
        {
            "category":"Home & Garden",
            "subcategory":"Furniture",
            "type":"Retail Goods"
        }
    ],
    "sg:postcode":"SE15 3HB",
    "sg:province":"Greater London",
    "wof:name":"Ace Furniture",
    "wof:placetype":"venue"
},
  "geometry": {"coordinates":[-0.057174,51.465908],"type":"Point"}
}