{
  "type": "Feature",
  "properties": {
    "addr:full":"1 Acomb Court, Acomb York North Yorkshire YO24 3BJ",
    "addr:housenumber":"1",
    "addr:postcode":"yo24 3bj",
    "addr:street":"Acomb Court",
    "iso:country":"GB",
    "sg:address":"1 Acomb Court, Acomb",
    "sg:city":"York",
    "sg:classifiers":[
        {
            "category":"Food & Beverages",
            "subcategory":"Candy",
            "type":"Retail Goods"
        }
    ],
    "sg:phone":"+44 1904 798493",
    "sg:postcode":"YO24 3BJ",
    "sg:province":"North Yorkshire",
    "sg:tags":[
        "confectioner"
    ],
    "wof:name":"The Cakery",
    "wof:placetype":"venue"
},
  "geometry": {"coordinates":[-1.129234,53.954182],"type":"Point"}
}