{
  "type": "Feature",
  "properties": {
    "iso:country":"GB",
    "sg:address":"53 High Street, Felling",
    "sg:city":"Gateshead",
    "sg:classifiers":[
        {
            "category":"Government",
            "subcategory":"Office",
            "type":"Public Place"
        }
    ],
    "sg:phone":"+44 191 495 0840",
    "sg:postcode":"NE10 9QQ",
    "sg:province":"Tyne and Wear",
    "sg:tags":[
        "local"
    ],
    "wof:name":"Rent Service",
    "wof:placetype":"venue"
},
  "geometry": {"coordinates":[-1.5702040195,54.9516906738],"type":"Point"}
}