{
  "type": "Feature",
  "properties": {
    "addr:full":"4 Shrewsbury Street, Hodnit Market Drayton Shropshire TF9 3NP",
    "addr:housenumber":"4",
    "addr:postcode":"tf9 3np",
    "addr:street":"Shrewsbury Street;Market",
    "iso:country":"GB",
    "sg:address":"4 Shrewsbury Street, Hodnit",
    "sg:city":"Market Drayton",
    "sg:classifiers":[
        {
            "category":"Food & Beverages",
            "subcategory":"Fruits & Vegetables",
            "type":"Retail Goods"
        }
    ],
    "sg:phone":"+44 1630 685213",
    "sg:postcode":"TF9 3NP",
    "sg:province":"Shropshire",
    "sg:tags":[
        "greengrocer"
    ],
    "wof:name":"W G & F M Bennett",
    "wof:placetype":"venue"
},
  "geometry": {"coordinates":[-2.575245,52.853603],"type":"Point"}
}