{
  "type": "Feature",
  "properties": {
    "iso:country":"GB",
    "sg:address":"33 Hadrian Avenue, Southwick",
    "sg:city":"Brighton",
    "sg:classifiers":[
        {
            "category":"Bakery",
            "type":"Food & Drink"
        }
    ],
    "sg:postcode":"BN42 4LJ",
    "sg:province":"West Sussex",
    "sg:tags":[
        "cake",
        "maker"
    ],
    "wof:name":"Design-A-Cake",
    "wof:placetype":"venue"
},
  "geometry": {"coordinates":[-0.225868,50.837379],"type":"Point"}
}