{
  "type": "Feature",
  "properties": {
    "addr:full":"53 Harvard Road Isleworth Greater London TW7 4PA",
    "addr:housenumber":"53",
    "addr:postcode":"tw7 4pa",
    "addr:street":"Harvard Road",
    "iso:country":"GB",
    "sg:address":"53 Harvard Road",
    "sg:city":"Isleworth",
    "sg:classifiers":[
        {
            "category":"Shopping",
            "subcategory":"Clothing, Apparel, & Fashions",
            "type":"Retail Goods"
        }
    ],
    "sg:phone":"+44 20 8560 8855",
    "sg:postcode":"TW7 4PA",
    "sg:province":"Greater London",
    "sg:tags":[
        "dresswear"
    ],
    "wof:name":"Rags to Riches",
    "wof:placetype":"venue"
},
  "geometry": {"coordinates":[-0.3415359855,51.4777183533],"type":"Point"}
}