{
  "type": "Feature",
  "properties": {
    "iso:country":"GB",
    "sg:address":"Woodlands, York Road, Islington",
    "sg:city":"Tadcaster",
    "sg:classifiers":[
        {
            "category":"Freight",
            "type":"Transportation"
        }
    ],
    "sg:phone":"+44 1937 833877",
    "sg:postcode":"LS24 8EB",
    "sg:province":"North Yorkshire",
    "sg:tags":[
        "haulage",
        "transport",
        "road"
    ],
    "wof:name":"Richard Rooke Ltd.",
    "wof:placetype":"venue"
},
  "geometry": {"coordinates":[-1.23849,53.89093],"type":"Point"}
}