{
  "type": "Feature",
  "properties": {
    "addr:full":"17 Tavern Quay, Rote Street London Greater London SE16 7TX",
    "addr:housenumber":"17",
    "addr:postcode":"se16 7tx",
    "addr:street":"Tavern Quay Rote Street",
    "iso:country":"GB",
    "sg:address":"17 Tavern Quay, Rote Street",
    "sg:city":"London",
    "sg:classifiers":[
        {
            "category":"Professional",
            "subcategory":"Detective & Security Services",
            "type":"Services"
        }
    ],
    "sg:phone":"+44 20 8761 9530",
    "sg:postcode":"SE16 7TX",
    "sg:province":"Greater London",
    "sg:tags":[
        "agency"
    ],
    "wof:name":"C B Investigations",
    "wof:placetype":"venue"
},
  "geometry": {"coordinates":[-0.03864,51.49313],"type":"Point"}
}