{
  "type": "Feature",
  "properties": {
    "addr:full":"5 Lordswood Industrial Estate, Revenge Road Chatham Kent ME5 8UD",
    "addr:housenumber":"5",
    "addr:postcode":"me5 8ud",
    "addr:street":"Lordswood Industrial Estate Revenge Road",
    "iso:country":"GB",
    "sg:address":"5 Lordswood Industrial Estate, Revenge Road",
    "sg:city":"Chatham",
    "sg:classifiers":[
        {
            "category":"Shopping",
            "subcategory":"Computers & Home Electronics",
            "type":"Retail Goods"
        }
    ],
    "sg:phone":"+44 1634 200000",
    "sg:postcode":"ME5 8UD",
    "sg:province":"Kent",
    "sg:tags":[
        "equipment",
        "video",
        "cctv"
    ],
    "wof:name":"E S Video",
    "wof:placetype":"venue"
},
  "geometry": {"coordinates":[0.54138,51.33091],"type":"Point"}
}