{
  "type": "Feature",
  "properties": {
    "iso:country":"GB",
    "sg:address":"18 Kirkgate, Silsden",
    "sg:city":"Keighley",
    "sg:classifiers":[
        {
            "category":"Cafe",
            "type":"Food & Drink"
        }
    ],
    "sg:phone":"+44 1535 657173",
    "sg:postcode":"BD20 0AL",
    "sg:province":"North Yorkshire",
    "sg:tags":[
        "tea",
        "room"
    ],
    "wof:name":"Sizzles",
    "wof:placetype":"venue"
},
  "geometry": {"coordinates":[-1.937484,53.912228],"type":"Point"}
}