{
  "type": "Feature",
  "properties": {
    "addr:full":"3-5 West Stewart St Greenock Inverclyde PA15 1SN",
    "addr:housenumber":"3-5",
    "addr:postcode":"pa15 1sn",
    "addr:street":"West Stewart St",
    "iso:country":"GB",
    "sg:address":"3-5 West Stewart St",
    "sg:city":"Greenock",
    "sg:classifiers":[
        {
            "category":"Cafe",
            "type":"Food & Drink"
        }
    ],
    "sg:phone":"+44 1475 727766",
    "sg:postcode":"PA15 1SN",
    "sg:province":"Inverclyde",
    "sg:tags":[
        "tea",
        "room"
    ],
    "wof:name":"Kopper Kettle",
    "wof:placetype":"venue"
},
  "geometry": {"coordinates":[-4.761873,55.948948],"type":"Point"}
}