{
  "type": "Feature",
  "properties": {
    "addr:full":"Unit 5-6a, The Old Malthouse, Springfield Road Grantham Lincolnshire NG31 7BG",
    "addr:housenumber":"unit 5-6a the old",
    "addr:postcode":"ng31 7bg",
    "addr:street":"Springfield Road",
    "iso:country":"GB",
    "sg:address":"Unit 5-6a, The Old Malthouse, Springfield Road",
    "sg:city":"Grantham",
    "sg:classifiers":[
        {
            "category":"Shopping",
            "subcategory":"Bicycles & Sporting Goods",
            "type":"Retail Goods"
        }
    ],
    "sg:phone":"+44 1476 566998",
    "sg:postcode":"NG31 7BG",
    "sg:province":"Lincolnshire",
    "sg:tags":[
        "equipment",
        "leisure"
    ],
    "wof:name":"Aquabeam Ltd.",
    "wof:placetype":"venue"
},
  "geometry": {"coordinates":[-0.6428589821,52.9131965637],"type":"Point"}
}