{
  "type": "Feature",
  "properties": {
    "addr:full":"29 Peckers Hill Road, Sutton Village St Helens Cheshire WA9 3LQ",
    "addr:housenumber":"29",
    "addr:postcode":"wa9 3lq",
    "addr:street":"Peckers Hill Road;Village",
    "iso:country":"GB",
    "sg:address":"29 Peckers Hill Road, Sutton Village",
    "sg:city":"St Helens",
    "sg:classifiers":[
        {
            "category":"Restaurant",
            "type":"Food & Drink"
        }
    ],
    "sg:phone":"+44 1744 811933",
    "sg:postcode":"WA9 3LQ",
    "sg:province":"Cheshire",
    "wof:name":"Di Marco's",
    "wof:placetype":"venue"
},
  "geometry": {"coordinates":[-2.702613,53.43663],"type":"Point"}
}