{
  "type": "Feature",
  "properties": {
    "iso:country":"GB",
    "sg:address":"Stonehouse Farm, Stockwood Lane",
    "sg:city":"Worcester",
    "sg:classifiers":[
        {
            "category":"Farming",
            "subcategory":"Farm",
            "type":"Manufacturing & Wholesale Goods"
        }
    ],
    "sg:postcode":"WR7 4JG",
    "sg:province":"Worcestershire",
    "sg:tags":[
        "mixed",
        "crop"
    ],
    "wof:name":"C W & M E Jordan & Son",
    "wof:placetype":"venue"
},
  "geometry": {"coordinates":[-1.98575,52.217838],"type":"Point"}
}