{
  "type": "Feature",
  "properties": {
    "iso:country":"GB",
    "sg:address":"3 High Street",
    "sg:city":"Church Stretton",
    "sg:classifiers":[
        {
            "category":"Farming",
            "subcategory":"Fish & Marine Products",
            "type":"Manufacturing & Wholesale Goods"
        },
        {
            "category":"Food & Beverages",
            "subcategory":"Meat & Fish",
            "type":"Retail Goods"
        }
    ],
    "sg:phone":"+44 1694 722867",
    "sg:postcode":"SY6 6BU",
    "sg:province":"Shropshire",
    "sg:tags":[
        "fishmonger",
        "butcher"
    ],
    "wof:name":"Bernhard H Richardson",
    "wof:placetype":"venue"
},
  "geometry": {"coordinates":[-2.807571,52.538929],"type":"Point"}
}