{
  "type": "Feature",
  "properties": {
    "addr:full":"43 Hall Gate Doncaster South Yorkshire DN1 3NR",
    "addr:housenumber":"43",
    "addr:postcode":"dn1 3nr",
    "addr:street":"Hall Gate",
    "iso:country":"GB",
    "sg:address":"43 Hall Gate",
    "sg:city":"Doncaster",
    "sg:classifiers":[
        {
            "category":"Professional",
            "subcategory":"Employment Agencies",
            "type":"Services"
        }
    ],
    "sg:phone":"+44 1302 344128",
    "sg:postcode":"DN1 3NR",
    "sg:province":"South Yorkshire",
    "sg:tags":[
        "career",
        "guidance"
    ],
    "wof:name":"Army Careers Office",
    "wof:placetype":"venue"
},
  "geometry": {"coordinates":[-1.1297860146,53.5222015381],"type":"Point"}
}