{
  "type": "Feature",
  "properties": {
    "addr:full":"12-16 Bristol Rd Greenford Greater London UB6 8XT",
    "addr:housenumber":"12-16",
    "addr:postcode":"ub6 8xt",
    "addr:street":"Bristol Rd",
    "iso:country":"GB",
    "sg:address":"12-16 Bristol Rd",
    "sg:city":"Greenford",
    "sg:classifiers":[
        {
            "category":"Shopping",
            "subcategory":"Clothing, Apparel, & Fashions",
            "type":"Retail Goods"
        }
    ],
    "sg:phone":"+44 870 516 8118",
    "sg:postcode":"UB6 8XT",
    "sg:province":"Greater London",
    "sg:tags":[
        "workwear",
        "protective"
    ],
    "wof:name":"3m United Kingdom PLC",
    "wof:placetype":"venue"
},
  "geometry": {"coordinates":[-0.359646,51.540005],"type":"Point"}
}