{
  "type": "Feature",
  "properties": {
    "iso:country":"GB",
    "sg:address":"27 Haining Garden, Mytchett",
    "sg:city":"Camberley",
    "sg:classifiers":[
        {
            "category":"Building & Trades",
            "subcategory":"Construction",
            "type":"Services"
        }
    ],
    "sg:phone":"+44 1252 378406",
    "sg:postcode":"GU16 6BJ",
    "sg:province":"Hampshire",
    "sg:tags":[
        "builder"
    ],
    "wof:name":"Glendair",
    "wof:placetype":"venue"
},
  "geometry": {"coordinates":[-0.72256,51.291176],"type":"Point"}
}