{
  "type": "Feature",
  "properties": {
    "iso:country":"GB",
    "sg:address":"Gawne Lane",
    "sg:city":"Cradley Heath",
    "sg:classifiers":[
        {
            "category":"Manufacturing",
            "subcategory":"Rubber & Plastics",
            "type":"Manufacturing & Wholesale Goods"
        }
    ],
    "sg:phone":"+44 1384 414840",
    "sg:postcode":"B64 5QY",
    "sg:province":"West Midlands",
    "sg:tags":[
        "product",
        "manufacturer"
    ],
    "wof:name":"WESTLEY PLASTICS LTD",
    "wof:placetype":"venue"
},
  "geometry": {"coordinates":[-2.067759037,52.4861068726],"type":"Point"}
}