{
  "type": "Feature",
  "properties": {
    "iso:country":"GB",
    "sg:address":"27-29 Whitfield St",
    "sg:city":"West End",
    "sg:classifiers":[
        {
            "category":"Real Estate",
            "subcategory":"Architect",
            "type":"Services"
        }
    ],
    "sg:phone":"+44 20 7580 2899",
    "sg:postcode":"W1P 5RB",
    "sg:province":"Hampshire",
    "wof:name":"Buschow Henley",
    "wof:placetype":"venue"
},
  "geometry": {"coordinates":[-0.1343539953,51.5197944641],"type":"Point"}
}