{
  "type": "Feature",
  "properties": {
    "addr:full":"78a Chapel Lane Wilmslow Cheshire SK9 5JH",
    "addr:housenumber":"78a",
    "addr:postcode":"sk9 5jh",
    "addr:street":"Chapel Lane",
    "iso:country":"GB",
    "sg:address":"78a Chapel Lane",
    "sg:city":"Wilmslow",
    "sg:classifiers":[
        {
            "category":"Building & Trades",
            "subcategory":"Cleaning & Sanitation",
            "type":"Services"
        },
        {
            "category":"Professional",
            "subcategory":"Business Services",
            "type":"Services"
        }
    ],
    "sg:phone":"+44 1625 521880",
    "sg:postcode":"SK9 5JH",
    "sg:province":"Cheshire",
    "sg:tags":[
        "shop",
        "contracting",
        "commercial"
    ],
    "wof:name":"Office Cleaning Northern Ltd",
    "wof:placetype":"venue"
},
  "geometry": {"coordinates":[-2.243647,53.32235],"type":"Point"}
}