{
  "type": "Feature",
  "properties": {
    "iso:country":"GB",
    "sg:address":"27 Elm Avenue",
    "sg:city":"Upminster",
    "sg:classifiers":[
        {
            "category":"Building & Trades",
            "subcategory":"Construction",
            "type":"Services"
        }
    ],
    "sg:phone":"+44 1708 250554",
    "sg:postcode":"RM14 2AZ",
    "sg:province":"Essex",
    "sg:tags":[
        "dry",
        "roofing",
        "screeders",
        "plasterers",
        "lining"
    ],
    "wof:name":"Michael T Dickson",
    "wof:placetype":"venue"
},
  "geometry": {"coordinates":[0.2455330044,51.5510406494],"type":"Point"}
}