{
  "type": "Feature",
  "properties": {
    "addr:full":"Brae View House, 9 - 11 Brae View Place, Nerston East Instl Estate Glasgow South Lanarkshire G74 3XH",
    "addr:housenumber":"9 11",
    "addr:postcode":"g74 3xh",
    "addr:street":"Brae;Brae View Place Nerston East Instl Estate",
    "iso:country":"GB",
    "sg:address":"Brae View House, 9 - 11 Brae View Place, Nerston East Instl Estate",
    "sg:city":"Glasgow",
    "sg:classifiers":[
        {
            "category":"Professional",
            "subcategory":"Employment Agencies",
            "type":"Services"
        }
    ],
    "sg:phone":"+44 1355 266661",
    "sg:postcode":"G74 3XH",
    "sg:province":"South Lanarkshire",
    "sg:tags":[
        "recr",
        "hire",
        "driver"
    ],
    "wof:name":"Driver Hire East Kilbride",
    "wof:placetype":"venue"
},
  "geometry": {"coordinates":[-4.160025,55.777481],"type":"Point"}
}