{
  "type": "Feature",
  "properties": {
    "addr:full":"26 North Road, Yate Bristol Gloucestershire BS37 7PA",
    "addr:housenumber":"26",
    "addr:postcode":"bs37 7pa",
    "addr:street":"North Road Yate",
    "iso:country":"GB",
    "sg:address":"26 North Road, Yate",
    "sg:city":"Bristol",
    "sg:classifiers":[
        {
            "category":"Shopping",
            "subcategory":"Clothing, Apparel, & Fashions",
            "type":"Retail Goods"
        }
    ],
    "sg:phone":"+44 1454 335000",
    "sg:postcode":"BS37 7PA",
    "sg:province":"Gloucestershire",
    "sg:tags":[
        "workwear",
        "protective"
    ],
    "wof:name":"U K Safety Holdings Ltd.",
    "wof:placetype":"venue"
},
  "geometry": {"coordinates":[-2.4351890087,51.550491333],"type":"Point"}
}