{
  "type": "Feature",
  "properties": {
    "addr:full":"Within Pontyrhyl Service Station, Bryn Cottages, Pontyrhyl Bridgend Bridgend CF32 8PX",
    "addr:postcode":"cf32 8px",
    "addr:street":"Bryn;Pontyrhyl Bridgend",
    "iso:country":"GB",
    "sg:address":"Within Pontyrhyl Service Station, Bryn Cottages, Pontyrhyl",
    "sg:city":"Bridgend",
    "sg:classifiers":[
        {
            "category":"Retail",
            "subcategory":"Auto Repair",
            "type":"Services"
        }
    ],
    "sg:phone":"+44 1656 870246",
    "sg:postcode":"CF32 8PX",
    "sg:province":"Bridgend",
    "sg:tags":[
        "modification",
        "garage"
    ],
    "wof:name":"W Braund",
    "wof:placetype":"venue"
},
  "geometry": {"coordinates":[-3.577804,51.591095],"type":"Point"}
}