{
  "type": "Feature",
  "properties": {
    "iso:country":"GB",
    "sg:address":"8 Clifton Avenue",
    "sg:city":"London",
    "sg:classifiers":[
        {
            "category":"Shopping",
            "subcategory":"News",
            "type":"Retail Goods"
        }
    ],
    "sg:phone":"+44 20 8349 1829",
    "sg:postcode":"N3 1BN",
    "sg:province":"Greater London",
    "sg:tags":[
        "newsagent"
    ],
    "wof:name":"C & B PATEL",
    "wof:placetype":"venue"
},
  "geometry": {"coordinates":[-0.199418,51.601196],"type":"Point"}
}