{
  "type": "Feature",
  "properties": {
    "addr:full":"4 & 5 Felnex Square, Cross Green Industrial Estate Leeds West Yorkshire LS9 0ST",
    "addr:housenumber":"4 & 5",
    "addr:postcode":"ls9 0st",
    "addr:street":"Felnex Square Cross Green Industrial Estate",
    "iso:country":"GB",
    "sg:address":"4 & 5 Felnex Square, Cross Green Industrial Estate",
    "sg:city":"Leeds",
    "sg:classifiers":[
        {
            "category":"Manufacturing",
            "subcategory":"Rubber & Plastics",
            "type":"Manufacturing & Wholesale Goods"
        }
    ],
    "sg:phone":"+44 113 249 1155",
    "sg:postcode":"LS9 0ST",
    "sg:province":"West Yorkshire",
    "sg:tags":[
        "supplier",
        "stockist"
    ],
    "wof:name":"E P C O Ltd.",
    "wof:placetype":"venue"
},
  "geometry": {"coordinates":[-1.5010900497,53.7875289917],"type":"Point"}
}