{
  "type": "Feature",
  "properties": {
    "iso:country":"GB",
    "sg:address":"76 South Lane, Ash",
    "sg:city":"Aldershot",
    "sg:classifiers":[
        {
            "category":"Building & Trades",
            "subcategory":"Construction",
            "type":"Services"
        }
    ],
    "sg:phone":"+44 1252 310241",
    "sg:postcode":"GU12 6NJ",
    "sg:province":"Hampshire",
    "sg:tags":[
        "builder"
    ],
    "wof:name":"Nelson Marney",
    "wof:placetype":"venue"
},
  "geometry": {"coordinates":[-0.717739,51.24297],"type":"Point"}
}