{
  "type": "Feature",
  "properties": {
    "iso:country":"GB",
    "sg:address":"7 Greenhill Rents",
    "sg:city":"London",
    "sg:classifiers":[
        {
            "category":"Bars & Pubs",
            "type":"Food & Drink"
        }
    ],
    "sg:phone":"+44 20 7336 8898",
    "sg:postcode":"EC1M 6BN",
    "sg:province":"Greater London",
    "sg:tags":[
        "pubs",
        "inn"
    ],
    "wof:name":"Fabric London Ltd.",
    "wof:placetype":"venue"
},
  "geometry": {"coordinates":[-0.10246,51.51981],"type":"Point"}
}