{
  "type": "Feature",
  "properties": {
    "addr:full":"Unit 6 Silver Rd, White City Indstl Est London Greater London W12 7SG",
    "addr:housenumber":"unit 6",
    "addr:postcode":"w12 7sg",
    "addr:street":"Silver Rd;Indstl Est",
    "iso:country":"GB",
    "sg:address":"Unit 6 Silver Rd, White City Indstl Est",
    "sg:city":"London",
    "sg:classifiers":[
        {
            "category":"Communications",
            "subcategory":"Film & Video Production",
            "type":"Services"
        }
    ],
    "sg:phone":"+44 20 8749 6911",
    "sg:postcode":"W12 7SG",
    "sg:province":"Greater London",
    "sg:tags":[
        "tv",
        "studio"
    ],
    "wof:name":"Fraser,Mike,Ltd",
    "wof:placetype":"venue"
},
  "geometry": {"coordinates":[-0.2209890038,51.5103263855],"type":"Point"}
}