{
  "type": "Feature",
  "properties": {
    "addr:full":"71 Market Street Stoke-on-trent Staffordshire ST3 1BW",
    "addr:housenumber":"71",
    "addr:postcode":"st3 1bw",
    "addr:street":"Market Street",
    "iso:country":"GB",
    "sg:address":"71 Market Street",
    "sg:city":"Stoke-on-trent",
    "sg:classifiers":[
        {
            "category":"Manufacturing",
            "subcategory":"Tools & Machinery",
            "type":"Manufacturing & Wholesale Goods"
        }
    ],
    "sg:phone":"+44 1782 315597",
    "sg:postcode":"ST3 1BW",
    "sg:province":"Staffordshire",
    "sg:tags":[
        "society",
        "friendly"
    ],
    "wof:name":"Lawson & Fern Ltd.",
    "wof:placetype":"venue"
},
  "geometry": {"coordinates":[-2.132874012,52.9877967834],"type":"Point"}
}