{
  "type": "Feature",
  "properties": {
    "iso:country":"GB",
    "sg:address":"Eye Hill Drove, Barcham",
    "sg:city":"Ely",
    "sg:classifiers":[
        {
            "category":"Home & Garden",
            "subcategory":"Garden Supply",
            "type":"Retail Goods"
        }
    ],
    "sg:phone":"+44 1353 720748",
    "sg:postcode":"CB7 5XF",
    "sg:province":"Cambridgeshire",
    "sg:tags":[
        "planting",
        "tree",
        "shrub"
    ],
    "wof:name":"Barcham Trees Plc",
    "wof:placetype":"venue"
},
  "geometry": {"coordinates":[0.30997,52.363899],"type":"Point"}
}