{
  "type": "Feature",
  "properties": {
    "iso:country":"GB",
    "sg:address":"Cromwell Avenue, Westbrook",
    "sg:city":"Warrington",
    "sg:classifiers":[
        {
            "category":"Education",
            "subcategory":"School",
            "type":"Public Place"
        },
        {
            "category":"Government",
            "subcategory":"Office",
            "type":"Public Place"
        }
    ],
    "sg:phone":"+44 1925 574888",
    "sg:postcode":"WA5 1HG",
    "sg:province":"Cheshire",
    "sg:tags":[
        "local",
        "authority"
    ],
    "wof:name":"St Gregory's R C (Aided) High School",
    "wof:placetype":"venue"
},
  "geometry": {"coordinates":[-2.622369,53.388664],"type":"Point"}
}