{
  "type": "Feature",
  "properties": {
    "iso:country":"GB",
    "sg:address":"8a Ray Park Avenue",
    "sg:city":"Maidenhead",
    "sg:classifiers":[
        {
            "category":"Health Services",
            "subcategory":"Doctor",
            "type":"Services"
        }
    ],
    "sg:phone":"+44 1628 622023",
    "sg:postcode":"SL6 8DS",
    "sg:province":"Berkshire",
    "sg:tags":[
        "practitioners"
    ],
    "wof:name":"C Hutchings & M Johnson",
    "wof:placetype":"venue"
},
  "geometry": {"coordinates":[-0.704725,51.524731],"type":"Point"}
}