{
  "type": "Feature",
  "properties": {
    "iso:country":"GB",
    "sg:address":"Coburg St",
    "sg:city":"Camden",
    "sg:classifiers":[
        {
            "category":"Shopping",
            "subcategory":"Hobbies, Toys, & Games",
            "type":"Retail Goods"
        }
    ],
    "sg:phone":"+44 20 7922 6436",
    "sg:postcode":"NW1 2HP",
    "sg:province":"Greater London",
    "sg:tags":[
        "collectors'",
        "item"
    ],
    "wof:name":"Rail Collectors Corner",
    "wof:placetype":"venue"
},
  "geometry": {"coordinates":[-0.135764,51.527191],"type":"Point"}
}