{
  "type": "Feature",
  "properties": {
    "addr:full":"37 Bell Street Sawbridgeworth Essex CM21 9AR",
    "addr:housenumber":"37",
    "addr:postcode":"cm21 9ar",
    "addr:street":"Bell Street",
    "iso:country":"GB",
    "sg:address":"37 Bell Street",
    "sg:city":"Sawbridgeworth",
    "sg:classifiers":[
        {
            "category":"Banks & Credit Unions",
            "subcategory":"Bank",
            "type":"Services"
        }
    ],
    "sg:phone":"+44 845 072 3333",
    "sg:postcode":"CM21 9AR",
    "sg:province":"Essex",
    "sg:tags":[
        "financial",
        "institution"
    ],
    "sg:website":"http://www.lloydstsb.com",
    "wof:name":"Lloyds T S B Bank Plc",
    "wof:placetype":"venue"
},
  "geometry": {"coordinates":[0.150007993,51.8126907349],"type":"Point"}
}