{
  "type": "Feature",
  "properties": {
    "addr:full":"Beech House, Tower Brae South, Westhill Inverness Highland IV2 5BW",
    "addr:postcode":"iv2 5bw",
    "addr:street":"Brae South;Inverness",
    "iso:country":"GB",
    "sg:address":"Beech House, Tower Brae South, Westhill",
    "sg:city":"Inverness",
    "sg:classifiers":[
        {
            "category":"Autos & Motor Vehicles",
            "subcategory":"Motorcycle Sales",
            "type":"Retail Goods"
        }
    ],
    "sg:phone":"+44 1463 791287",
    "sg:postcode":"IV2 5BW",
    "sg:province":"Highland",
    "sg:tags":[
        "chauffeur",
        "driven",
        "car"
    ],
    "wof:name":"Premier Chauffer Co",
    "wof:placetype":"venue"
},
  "geometry": {"coordinates":[-4.1472940445,57.4703407288],"type":"Point"}
}