{
  "type": "Feature",
  "properties": {
    "addr:full":"Unit 24 Brookside Business Park, Brookside Road Uttoxeter Derbyshire ST14 8AU",
    "addr:housenumber":"unit 24",
    "addr:postcode":"st14 8au",
    "addr:street":"Brookside Business Park Brookside Road",
    "iso:country":"GB",
    "sg:address":"Unit 24 Brookside Business Park, Brookside Road",
    "sg:city":"Uttoxeter",
    "sg:classifiers":[
        {
            "category":"Professional",
            "subcategory":"Engineering",
            "type":"Services"
        }
    ],
    "sg:phone":"+44 1889 564932",
    "sg:postcode":"ST14 8AU",
    "sg:province":"Derbyshire",
    "sg:tags":[
        "precision",
        "engineer"
    ],
    "wof:name":"Valeform Ltd.",
    "wof:placetype":"venue"
},
  "geometry": {"coordinates":[-1.8696440458,52.896522522],"type":"Point"}
}