{
  "type": "Feature",
  "properties": {
    "iso:country":"GB",
    "sg:address":"25 Huddersfield Road",
    "sg:city":"Brighouse",
    "sg:classifiers":[
        {
            "category":"Professional",
            "subcategory":"Art Services",
            "type":"Services"
        }
    ],
    "sg:phone":"+44 1484 717910",
    "sg:postcode":"HD6 3RQ",
    "sg:province":"West Yorkshire",
    "sg:tags":[
        "graphic",
        "designer"
    ],
    "wof:name":"Greenwood Graphics Ltd.",
    "wof:placetype":"venue"
},
  "geometry": {"coordinates":[-1.778537035,53.6974525452],"type":"Point"}
}