{
  "type": "Feature",
  "properties": {
    "iso:country":"GB",
    "sg:address":"2 The Limes, Church Road Yapton",
    "sg:city":"Arundel",
    "sg:classifiers":[
        {
            "category":"Professional",
            "subcategory":"Accounting & Tax Preparation",
            "type":"Services"
        }
    ],
    "sg:postcode":"BN18 0EL",
    "sg:province":"West Sussex",
    "sg:tags":[
        "accountant"
    ],
    "wof:name":"B.J.S. Accountancy Ltd",
    "wof:placetype":"venue"
},
  "geometry": {"coordinates":[-0.6100800037,50.8217849731],"type":"Point"}
}