{
  "type": "Feature",
  "properties": {
    "addr:full":"195 Uppingham Road Leicester Leicestershire LE5 4BQ",
    "addr:housenumber":"195",
    "addr:postcode":"le5 4bq",
    "addr:street":"Uppingham Road",
    "iso:country":"GB",
    "sg:address":"195 Uppingham Road",
    "sg:city":"Leicester",
    "sg:classifiers":[
        {
            "category":"Home & Garden",
            "subcategory":"Household Appliances",
            "type":"Retail Goods"
        }
    ],
    "sg:phone":"+44 116 276 9180",
    "sg:postcode":"LE5 4BQ",
    "sg:province":"Leicestershire",
    "sg:tags":[
        "electrical"
    ],
    "wof:name":"A C Electrical/Refrigeration",
    "wof:placetype":"venue"
},
  "geometry": {"coordinates":[-1.092947,52.642166],"type":"Point"}
}