{
  "type": "Feature",
  "properties": {
    "iso:country":"GB",
    "sg:address":"70 Sheffield Road",
    "sg:city":"Barnsley",
    "sg:classifiers":[
        {
            "category":"Banks & Credit Unions",
            "subcategory":"Financial Services",
            "type":"Services"
        }
    ],
    "sg:phone":"+44 1226 733255",
    "sg:postcode":"S70 1HS",
    "sg:province":"South Yorkshire",
    "sg:tags":[
        "consultant"
    ],
    "wof:name":"Norton Finance (U K) Ltd.",
    "wof:placetype":"venue"
},
  "geometry": {"coordinates":[-1.475342989,53.5491714478],"type":"Point"}
}