{
  "type": "Feature",
  "properties": {
    "iso:country":"GB",
    "sg:address":"2-4 Watford Road",
    "sg:city":"Birmingham",
    "sg:classifiers":[
        {
            "category":"Shopping",
            "subcategory":"News",
            "type":"Retail Goods"
        }
    ],
    "sg:phone":"+44 121 458 3122",
    "sg:postcode":"B30 1JA",
    "sg:province":"West Midlands",
    "sg:tags":[
        "newsagent"
    ],
    "wof:name":"Forbuoys",
    "wof:placetype":"venue"
},
  "geometry": {"coordinates":[-1.930341,52.416271],"type":"Point"}
}