{
  "type": "Feature",
  "properties": {
    "iso:country":"GB",
    "sg:address":"200 Wigston Road, Woodway Park",
    "sg:city":"Coventry",
    "sg:classifiers":[
        {
            "category":"Shopping",
            "subcategory":"Pharmacy",
            "type":"Retail Goods"
        }
    ],
    "sg:phone":"+44 24 7661 8643",
    "sg:postcode":"CV2 2RH",
    "sg:province":"Warwickshire",
    "sg:tags":[
        "pharmacist",
        "dispensing",
        "chemist"
    ],
    "wof:name":"Futurechart Ltd.",
    "wof:placetype":"venue"
},
  "geometry": {"coordinates":[-1.448462,52.43819],"type":"Point"}
}