{
  "type": "Feature",
  "properties": {
    "iso:country":"GB",
    "sg:address":"Tamworth St",
    "sg:city":"Lichfield",
    "sg:classifiers":[
        {
            "category":"Bars & Pubs",
            "type":"Food & Drink"
        }
    ],
    "sg:phone":"+44 1543 262312",
    "sg:postcode":"WS13 6JP",
    "sg:province":"Staffordshire",
    "sg:tags":[
        "pubs",
        "inn"
    ],
    "wof:name":"Punch Retail Ltd",
    "wof:placetype":"venue"
},
  "geometry": {"coordinates":[-1.8242540359,52.6839675903],"type":"Point"}
}