{
  "type": "Feature",
  "properties": {
    "iso:country":"GB",
    "sg:address":"Hazel Way",
    "sg:city":"Telford",
    "sg:classifiers":[
        {
            "category":"Social Services",
            "subcategory":"Adult Care",
            "type":"Services"
        }
    ],
    "sg:phone":"+44 1952 615059",
    "sg:postcode":"TF2 9HH",
    "sg:province":"Shropshire",
    "sg:tags":[
        "housing",
        "sheltered"
    ],
    "wof:name":"Shrubbery Sheltered Housing The",
    "wof:placetype":"venue"
},
  "geometry": {"coordinates":[-2.4405620098,52.688835144],"type":"Point"}
}