{
  "type": "Feature",
  "properties": {
    "iso:country":"GB",
    "sg:address":"23 Corporation Rd",
    "sg:city":"Lincoln",
    "sg:classifiers":[
        {
            "category":"Communications",
            "type":"Services"
        }
    ],
    "sg:phone":"+44 1522 887799",
    "sg:postcode":"LN6 3NH",
    "sg:province":"Lincolnshire",
    "sg:tags":[
        "telecommunication"
    ],
    "wof:name":"Northclough Ltd",
    "wof:placetype":"venue"
},
  "geometry": {"coordinates":[-0.60247,53.210011],"type":"Point"}
}