{
  "type": "Feature",
  "properties": {
    "addr:full":"74-75 St Nicholas Market, St Nicholas St Bristol City of Bristol BS1 1LJ",
    "addr:housenumber":"74-75",
    "addr:postcode":"bs1 1lj",
    "addr:street":"St;Market St Nicholas St",
    "iso:country":"GB",
    "sg:address":"74-75 St Nicholas Market, St Nicholas St",
    "sg:city":"Bristol",
    "sg:classifiers":[
        {
            "category":"Sports & Exercise",
            "subcategory":"Sports Center",
            "type":"Entertainment"
        }
    ],
    "sg:phone":"+44 117 907 7679",
    "sg:postcode":"BS1 1LJ",
    "sg:province":"City of Bristol",
    "sg:tags":[
        "shop",
        "good"
    ],
    "wof:name":"Sportscene",
    "wof:placetype":"venue"
},
  "geometry": {"coordinates":[-2.594340086,51.45362854],"type":"Point"}
}