{
  "type": "Feature",
  "properties": {
    "addr:full":"Unit 4 Oswestry Shropshire SY11 4HS",
    "addr:housenumber":"unit 4",
    "addr:postcode":"sy11 4hs",
    "iso:country":"GB",
    "sg:address":"Unit 4",
    "sg:city":"Oswestry",
    "sg:classifiers":[
        {
            "category":"Manufacturing",
            "subcategory":"Metals",
            "type":"Manufacturing & Wholesale Goods"
        }
    ],
    "sg:phone":"+44 1691 610434",
    "sg:postcode":"SY11 4HS",
    "sg:province":"Shropshire",
    "sg:tags":[
        "steel",
        "fabricator",
        "erectors"
    ],
    "wof:name":"des Evans (Steel Fabrication) Ltd.",
    "wof:placetype":"venue"
},
  "geometry": {"coordinates":[-3.0040090084,52.8481483459],"type":"Point"}
}