{
  "type": "Feature",
  "properties": {
    "iso:country":"GB",
    "sg:address":"127 Broughton Rd",
    "sg:city":"Edinburgh",
    "sg:classifiers":[
        {
            "category":"Professional",
            "subcategory":"Art Services",
            "type":"Services"
        }
    ],
    "sg:phone":"+44 131 558 1416",
    "sg:postcode":"EH7 4JH",
    "sg:province":"City of Edinburgh",
    "sg:tags":[
        "consultant",
        "design"
    ],
    "wof:name":"McKenzie Advertising & Design",
    "wof:placetype":"venue"
},
  "geometry": {"coordinates":[-3.196203,55.968159],"type":"Point"}
}