{
  "type": "Feature",
  "properties": {
    "iso:country":"GB",
    "sg:address":"72 Wellingborough Road",
    "sg:city":"Northampton",
    "sg:classifiers":[
        {
            "category":"Government",
            "subcategory":"Post Office",
            "type":"Public Place"
        }
    ],
    "sg:phone":"+44 1604 231113",
    "sg:postcode":"NN1 4DP",
    "sg:province":"Northamptonshire",
    "sg:tags":[
        "messenger",
        "courier"
    ],
    "wof:name":"J W T (Distribution) Ltd.",
    "wof:placetype":"venue"
},
  "geometry": {"coordinates":[-0.8852339983,52.2406158447],"type":"Point"}
}