{
  "type": "Feature",
  "properties": {
    "iso:country":"GB",
    "sg:address":"117 Dorchester Road",
    "sg:city":"Weymouth",
    "sg:classifiers":[
        {
            "category":"Shopping",
            "subcategory":"Thrift Store",
            "type":"Retail Goods"
        }
    ],
    "sg:phone":"+44 1305 770182",
    "sg:postcode":"DT4 7LA",
    "sg:province":"Dorset",
    "sg:tags":[
        "shop",
        "charity"
    ],
    "wof:name":"Sue Ryder Shop",
    "wof:placetype":"venue"
},
  "geometry": {"coordinates":[-2.4562349319,50.6240463257],"type":"Point"}
}