{
  "type": "Feature",
  "properties": {
    "addr:full":"Pentrich Road, Swanwick Alfreton Derbyshire DE55 1BQ",
    "addr:postcode":"de55 1bq",
    "addr:street":"Pentrich Road",
    "iso:country":"GB",
    "sg:address":"Pentrich Road, Swanwick",
    "sg:city":"Alfreton",
    "sg:classifiers":[
        {
            "category":"Retail",
            "subcategory":"Auto Repair",
            "type":"Services"
        }
    ],
    "sg:phone":"+44 1773 602747",
    "sg:postcode":"DE55 1BQ",
    "sg:province":"Derbyshire",
    "sg:tags":[
        "modification",
        "garage",
        "related"
    ],
    "wof:name":"Pentrich Road Garage",
    "wof:placetype":"venue"
},
  "geometry": {"coordinates":[-1.3915859461,53.0733032227],"type":"Point"}
}