{
  "type": "Feature",
  "properties": {
    "iso:country":"GB",
    "sg:address":"Camilla Court, Nacton",
    "sg:city":"Ipswich",
    "sg:classifiers":[
        {
            "category":"Professional",
            "subcategory":"Printing & Photocopies",
            "type":"Services"
        }
    ],
    "sg:phone":"+44 1473 655141",
    "sg:postcode":"IP10 0EU",
    "sg:province":"Suffolk",
    "sg:tags":[
        "printer"
    ],
    "wof:name":"Print Innovative Technology Ltd.",
    "wof:placetype":"venue"
},
  "geometry": {"coordinates":[1.206199,52.026524],"type":"Point"}
}