{
  "type": "Feature",
  "properties": {
    "iso:country":"GB",
    "sg:address":"2 Chester Rd",
    "sg:city":"Manchester",
    "sg:classifiers":[
        {
            "category":"Health Services",
            "subcategory":"Clinic",
            "type":"Services"
        }
    ],
    "sg:phone":"+44 161 832 3334",
    "sg:postcode":"M15 4WX",
    "sg:province":"Cheshire",
    "sg:tags":[
        "private"
    ],
    "wof:name":"Centre For Laser Surgery",
    "wof:placetype":"venue"
},
  "geometry": {"coordinates":[-2.254973,53.473099],"type":"Point"}
}