{
  "type": "Feature",
  "properties": {
    "iso:country":"GB",
    "sg:address":"60 Cricklade Avenue",
    "sg:city":"Brixton",
    "sg:classifiers":[
        {
            "category":"Health Services",
            "subcategory":"Nursing And Care Facility",
            "type":"Services"
        }
    ],
    "sg:phone":"+44 20 8674 3980",
    "sg:postcode":"SW2 3HG",
    "sg:province":"Greater London",
    "sg:tags":[
        "home"
    ],
    "wof:name":"Nishi's Agencies",
    "wof:placetype":"venue"
},
  "geometry": {"coordinates":[-0.1231629997,51.4391517639],"type":"Point"}
}