{
  "type": "Feature",
  "properties": {
    "addr:full":"55 Farringdon Rd Clerkenwell Greater London EC1M 3JB",
    "addr:housenumber":"55",
    "addr:postcode":"ec1m 3jb",
    "addr:street":"Farringdon Rd",
    "iso:country":"GB",
    "sg:address":"55 Farringdon Rd",
    "sg:city":"Clerkenwell",
    "sg:classifiers":[
        {
            "category":"Professional",
            "subcategory":"Art Services",
            "type":"Services"
        }
    ],
    "sg:phone":"+44 20 7242 9565",
    "sg:postcode":"EC1M 3JB",
    "sg:province":"Greater London",
    "sg:tags":[
        "graphic",
        "designer"
    ],
    "wof:name":"Blast",
    "wof:placetype":"venue"
},
  "geometry": {"coordinates":[-0.106181,51.520542],"type":"Point"}
}