{
  "type": "Feature",
  "properties": {
    "iso:country":"GB",
    "sg:address":"2 Swaine Street",
    "sg:city":"Nelson",
    "sg:classifiers":[
        {
            "category":"Manufacturing",
            "subcategory":"Building Materials",
            "type":"Manufacturing & Wholesale Goods"
        }
    ],
    "sg:phone":"+44 1282 605918",
    "sg:postcode":"BB9 7AW",
    "sg:province":"Lancashire",
    "sg:tags":[
        "tarmac",
        "asphalt"
    ],
    "wof:name":"Richard Nuttall Tarmacadam",
    "wof:placetype":"venue"
},
  "geometry": {"coordinates":[-2.2217979431,53.833694458],"type":"Point"}
}