{
  "type": "Feature",
  "properties": {
    "addr:full":"4 Rocklynes, Dye La Stockport Cheshire SK6 4BD",
    "addr:housenumber":"4",
    "addr:postcode":"sk6 4bd",
    "addr:street":"Rocklynes Dye La Stockport",
    "iso:country":"GB",
    "sg:address":"4 Rocklynes, Dye La",
    "sg:city":"Stockport",
    "sg:classifiers":[
        {
            "category":"Professional",
            "subcategory":"Business Services",
            "type":"Services"
        }
    ],
    "sg:phone":"+44 161 406 6167",
    "sg:postcode":"SK6 4BD",
    "sg:province":"Cheshire",
    "sg:tags":[
        "transfer",
        "agent"
    ],
    "wof:name":"Everett Masson & Furby",
    "wof:placetype":"venue"
},
  "geometry": {"coordinates":[-2.09579,53.414234],"type":"Point"}
}