{
  "type": "Feature",
  "properties": {
    "iso:country":"GB",
    "sg:address":"11 Campfield Square, Broughty Ferry",
    "sg:city":"Dundee",
    "sg:classifiers":[
        {
            "category":"Personal",
            "subcategory":"Beauty Salon",
            "type":"Services"
        }
    ],
    "sg:phone":"+44 1382 731333",
    "sg:postcode":"DD5 2PU",
    "sg:province":"Angus",
    "wof:name":"J L  Hair Design",
    "wof:placetype":"venue"
},
  "geometry": {"coordinates":[-2.861662,56.473694],"type":"Point"}
}