{
  "type": "Feature",
  "properties": {
    "iso:country":"GB",
    "sg:address":"Longford Rd",
    "sg:city":"Coventry",
    "sg:classifiers":[
        {
            "category":"Retail",
            "subcategory":"Auto Repair",
            "type":"Services"
        }
    ],
    "sg:phone":"+44 24 7666 7011",
    "sg:postcode":"CV6 6DY",
    "sg:province":"Warwickshire",
    "sg:tags":[
        "car",
        "specialist",
        "customizing"
    ],
    "wof:name":"Rapid Fit",
    "wof:placetype":"venue"
},
  "geometry": {"coordinates":[-1.485499,52.452492],"type":"Point"}
}