{
  "type": "Feature",
  "properties": {
    "addr:full":"52 Littondale Avenue Knaresborough North Yorkshire HG5 0BQ",
    "addr:housenumber":"52",
    "addr:postcode":"hg5 0bq",
    "addr:street":"Littondale Avenue",
    "iso:country":"GB",
    "sg:address":"52 Littondale Avenue",
    "sg:city":"Knaresborough",
    "sg:classifiers":[
        {
            "category":"Manufacturing",
            "subcategory":"Petroleum Products",
            "type":"Manufacturing & Wholesale Goods"
        }
    ],
    "sg:postcode":"HG5 0BQ",
    "sg:province":"North Yorkshire",
    "sg:tags":[
        "double",
        "glazing"
    ],
    "wof:name":"Sash Solutions",
    "wof:placetype":"venue"
},
  "geometry": {"coordinates":[-1.447434,54.009937],"type":"Point"}
}