{
  "type": "Feature",
  "properties": {
    "iso:country":"GB",
    "sg:address":"21 St Leonards Close",
    "sg:city":"Wymondham",
    "sg:classifiers":[
        {
            "category":"Professional",
            "subcategory":"Engineering",
            "type":"Services"
        },
        {
            "category":"Building & Trades",
            "subcategory":"Plumbing",
            "type":"Services"
        }
    ],
    "sg:postcode":"NR18 0JF",
    "sg:province":"Norfolk",
    "sg:tags":[
        "gas",
        "heating",
        "engineer"
    ],
    "wof:name":"Robert W T Baker",
    "wof:placetype":"venue"
},
  "geometry": {"coordinates":[1.115334,52.581226],"type":"Point"}
}