{
  "type": "Feature",
  "properties": {
    "addr:full":"Harwoods Green Farm, Stopham Pulborough West Sussex RH20 1EF",
    "addr:postcode":"rh20 1ef",
    "iso:country":"GB",
    "sg:address":"Harwoods Green Farm, Stopham",
    "sg:city":"Pulborough",
    "sg:classifiers":[
        {
            "category":"Farming",
            "subcategory":"Livestock Farm",
            "type":"Manufacturing & Wholesale Goods"
        }
    ],
    "sg:postcode":"RH20 1EF",
    "sg:province":"West Sussex",
    "sg:tags":[
        "others"
    ],
    "wof:name":"D Branch Flock & Farm Services",
    "wof:placetype":"venue"
},
  "geometry": {"coordinates":[-0.539089,50.961864],"type":"Point"}
}