{
  "type": "Feature",
  "properties": {
    "iso:country":"GB",
    "sg:address":"63 West Princes St",
    "sg:city":"Helensburgh",
    "sg:classifiers":[
        {
            "category":"Social Services",
            "subcategory":"Adult Care",
            "type":"Services"
        }
    ],
    "sg:phone":"+44 1436 670303",
    "sg:postcode":"G84 8BN",
    "sg:province":"Argyll and Bute",
    "sg:tags":[
        "mnfr",
        "aid",
        "hearing"
    ],
    "wof:name":"Better Hearing",
    "wof:placetype":"venue"
},
  "geometry": {"coordinates":[-4.759756,56.017525],"type":"Point"}
}