{
  "type": "Feature",
  "properties": {
    "iso:country":"GB",
    "sg:address":"79 High Street, Stony Stratford",
    "sg:city":"Milton Keynes",
    "sg:classifiers":[
        {
            "category":"Professional",
            "subcategory":"Lawyer & Legal Services",
            "type":"Services"
        }
    ],
    "sg:phone":"+44 1908 563232",
    "sg:postcode":"MK11 1AU",
    "sg:province":"Buckinghamshire",
    "sg:tags":[
        "solicitor"
    ],
    "wof:name":"Ray Borley & Dunkley",
    "wof:placetype":"venue"
},
  "geometry": {"coordinates":[-0.8548160195,52.0578613281],"type":"Point"}
}