{
  "type": "Feature",
  "properties": {
    "addr:full":"43 Portland Street Troon South Ayrshire KA10 6AA",
    "addr:housenumber":"43",
    "addr:postcode":"ka10 6aa",
    "addr:street":"Portland Street",
    "iso:country":"GB",
    "sg:address":"43 Portland Street",
    "sg:city":"Troon",
    "sg:classifiers":[
        {
            "category":"Restaurant",
            "type":"Food & Drink"
        }
    ],
    "sg:phone":"+44 1292 316754",
    "sg:postcode":"KA10 6AA",
    "sg:province":"South Ayrshire",
    "wof:name":"The Golden City",
    "wof:placetype":"venue"
},
  "geometry": {"coordinates":[-4.662923,55.544617],"type":"Point"}
}