{
  "type": "Feature",
  "properties": {
    "iso:country":"GB",
    "sg:address":"Unit 4, Kilnbridge Wks",
    "sg:city":"Maidstone",
    "sg:classifiers":[
        {
            "category":"Government",
            "subcategory":"Post Office",
            "type":"Public Place"
        }
    ],
    "sg:phone":"+44 1622 720828",
    "sg:postcode":"ME15 0HD",
    "sg:province":"Kent",
    "sg:tags":[
        "print",
        "typesetter"
    ],
    "wof:name":"Orchard,Peter,Graphics Ltd",
    "wof:placetype":"venue"
},
  "geometry": {"coordinates":[0.4801560044,51.2523155212],"type":"Point"}
}