{
  "type": "Feature",
  "properties": {
    "addr:full":"Broomhillock Farm, Keith Hall Inverurie Aberdeenshire AB51 0LQ",
    "addr:postcode":"ab51 0lq",
    "addr:street":"Inverurie",
    "iso:country":"GB",
    "sg:address":"Broomhillock Farm, Keith Hall",
    "sg:city":"Inverurie",
    "sg:classifiers":[
        {
            "category":"Farming",
            "subcategory":"Farm",
            "type":"Manufacturing & Wholesale Goods"
        }
    ],
    "sg:postcode":"AB51 0LQ",
    "sg:province":"Aberdeenshire",
    "sg:tags":[
        "mixed",
        "crop"
    ],
    "wof:name":"D H McGregor",
    "wof:placetype":"venue"
},
  "geometry": {"coordinates":[-2.389794,57.291119],"type":"Point"}
}