{
  "type": "Feature",
  "properties": {
    "iso:country":"GB",
    "sg:address":"6 Central Blvd, Central Park",
    "sg:city":"Larbert",
    "sg:classifiers":[
        {
            "category":"Communications",
            "subcategory":"Television Station",
            "type":"Services"
        }
    ],
    "sg:phone":"+44 1324 550500",
    "sg:postcode":"FK5 4RU",
    "sg:province":"Falkirk",
    "sg:tags":[
        "video"
    ],
    "wof:name":"Mack Technologies Ltd.",
    "wof:placetype":"venue"
},
  "geometry": {"coordinates":[-3.805453,56.028389],"type":"Point"}
}