{
  "type": "Feature",
  "properties": {
    "addr:full":"George House, 18 George Street York North Yorkshire YO1 9QB",
    "addr:housenumber":"18",
    "addr:postcode":"yo1 9qb",
    "addr:street":"George Street",
    "iso:country":"GB",
    "sg:address":"George House, 18 George Street",
    "sg:city":"York",
    "sg:classifiers":[
        {
            "category":"Organizations",
            "subcategory":"Non-profit Organization",
            "type":"Services"
        }
    ],
    "sg:phone":"+44 1904 639056",
    "sg:postcode":"YO1 9QB",
    "sg:province":"North Yorkshire",
    "sg:tags":[
        "organisation",
        "voluntary",
        "charity"
    ],
    "wof:name":"P A C T",
    "wof:placetype":"venue"
},
  "geometry": {"coordinates":[-1.075206,53.955982],"type":"Point"}
}