{
  "type": "Feature",
  "properties": {
    "addr:full":"Twyford House, Exchange Square Beccles Norfolk NR34 9HL",
    "addr:postcode":"nr34 9hl",
    "addr:street":"Exchange Square",
    "iso:country":"GB",
    "sg:address":"Twyford House, Exchange Square",
    "sg:city":"Beccles",
    "sg:classifiers":[
        {
            "category":"Cafe",
            "type":"Food & Drink"
        }
    ],
    "sg:phone":"+44 1502 710614",
    "sg:postcode":"NR34 9HL",
    "sg:province":"Norfolk",
    "sg:tags":[
        "tea",
        "room"
    ],
    "wof:name":"Twyfords",
    "wof:placetype":"venue"
},
  "geometry": {"coordinates":[1.56398,52.45705],"type":"Point"}
}