{
  "type": "Feature",
  "properties": {
    "iso:country":"GB",
    "sg:address":"Units 1, & 2 Stephenson Place",
    "sg:city":"Crawley",
    "sg:classifiers":[
        {
            "category":"Retail",
            "subcategory":"Auto Repair",
            "type":"Services"
        }
    ],
    "sg:phone":"+44 1293 522529",
    "sg:postcode":"RH10 1TL",
    "sg:province":"Surrey",
    "sg:tags":[
        "body",
        "car"
    ],
    "wof:name":"Three Bridges Accident Repairs Centre",
    "wof:placetype":"venue"
},
  "geometry": {"coordinates":[-0.16413,51.113541],"type":"Point"}
}