{
  "type": "Feature",
  "properties": {
    "iso:country":"GB",
    "sg:address":"50 Broad Street, Sidemoor",
    "sg:city":"Bromsgrove",
    "sg:classifiers":[
        {
            "category":"Professional",
            "subcategory":"Business Services",
            "type":"Services"
        }
    ],
    "sg:phone":"+44 1527 875590",
    "sg:postcode":"B61 8LW",
    "sg:province":"Worcestershire",
    "sg:tags":[
        "bookmaker"
    ],
    "wof:name":"Sidemoor Turf Accountants",
    "wof:placetype":"venue"
},
  "geometry": {"coordinates":[-2.0669240952,52.3406410217],"type":"Point"}
}