{
  "type": "Feature",
  "properties": {
    "addr:full":"361 Pensby Road, Heswall Wirral Merseyside CH61 9NF",
    "addr:housenumber":"361",
    "addr:postcode":"ch61 9nf",
    "addr:street":"Pensby Road",
    "iso:country":"GB",
    "sg:address":"361 Pensby Road, Heswall",
    "sg:city":"Wirral",
    "sg:classifiers":[
        {
            "category":"Professional",
            "subcategory":"Accounting & Tax Preparation",
            "type":"Services"
        }
    ],
    "sg:phone":"+44 151 648 0000",
    "sg:postcode":"CH61 9NF",
    "sg:province":"Merseyside",
    "sg:tags":[
        "accountant",
        "bookkeeping",
        "primarily",
        "activity"
    ],
    "wof:name":"Walker Langford & Co",
    "wof:placetype":"venue"
},
  "geometry": {"coordinates":[-3.0946779251,53.3461685181],"type":"Point"}
}