{
  "type": "Feature",
  "properties": {
    "addr:full":"12 Alfred Place London Greater London WC1E 7EB",
    "addr:housenumber":"12",
    "addr:postcode":"wc1e 7eb",
    "addr:street":"Alfred Place",
    "iso:country":"GB",
    "sg:address":"12 Alfred Place",
    "sg:city":"London",
    "sg:classifiers":[
        {
            "category":"Shopping",
            "subcategory":"Stationery & Office Supplies",
            "type":"Retail Goods"
        }
    ],
    "sg:phone":"+44 20 7467 6200",
    "sg:postcode":"WC1E 7EB",
    "sg:province":"Greater London",
    "wof:name":"Paperchase Products Ltd.",
    "wof:placetype":"venue"
},
  "geometry": {"coordinates":[-0.265591,51.507339],"type":"Point"}
}