{
  "type": "Feature",
  "properties": {
    "addr:full":"Isle View, Isle Brewers Taunton Devon TA3 6QW",
    "addr:postcode":"ta3 6qw",
    "addr:street":"Isle View Isle",
    "iso:country":"GB",
    "sg:address":"Isle View, Isle Brewers",
    "sg:city":"Taunton",
    "sg:classifiers":[
        {
            "category":"Freight",
            "type":"Transportation"
        }
    ],
    "sg:phone":"+44 1460 281587",
    "sg:postcode":"TA3 6QW",
    "sg:province":"Devon",
    "sg:tags":[
        "haulage",
        "road"
    ],
    "wof:name":"O J Brownsey",
    "wof:placetype":"venue"
},
  "geometry": {"coordinates":[-2.89397,50.98283],"type":"Point"}
}