{
  "type": "Feature",
  "properties": {
    "addr:full":"10 Church St, Haswell Durham Durham DH6 2DZ",
    "addr:housenumber":"10",
    "addr:postcode":"dh6 2dz",
    "addr:street":"Church St",
    "iso:country":"GB",
    "sg:address":"10 Church St, Haswell",
    "sg:city":"Durham",
    "sg:classifiers":[
        {
            "category":"Food & Beverages",
            "subcategory":"Supermarket",
            "type":"Retail Goods"
        }
    ],
    "sg:phone":"+44 191 526 1642",
    "sg:postcode":"DH6 2DZ",
    "sg:province":"Durham",
    "sg:tags":[
        "frozen"
    ],
    "wof:name":"Hamilton Wholesale Supplies",
    "wof:placetype":"venue"
},
  "geometry": {"coordinates":[-1.4194639921,54.7819519043],"type":"Point"}
}