{
  "type": "Feature",
  "properties": {
    "iso:country":"GB",
    "sg:address":"Kilbane Street, Off Copse Road",
    "sg:city":"Fleetwood",
    "sg:classifiers":[
        {
            "category":"Manufacturing",
            "subcategory":"Metals",
            "type":"Manufacturing & Wholesale Goods"
        }
    ],
    "sg:phone":"+44 1253 778780",
    "sg:postcode":"FY7 7PF",
    "sg:province":"Lancashire",
    "sg:tags":[
        "steel",
        "fabricator",
        "erectors"
    ],
    "wof:name":"Wilko Fabrications Ltd.",
    "wof:placetype":"venue"
},
  "geometry": {"coordinates":[-3.025734,53.906555],"type":"Point"}
}