{
  "type": "Feature",
  "properties": {
    "addr:full":"271-287 Dale Street Chatham Kent ME4 6QR",
    "addr:housenumber":"271-287",
    "addr:postcode":"me4 6qr",
    "addr:street":"Dale Street",
    "iso:country":"GB",
    "sg:address":"271-287 Dale Street",
    "sg:city":"Chatham",
    "sg:classifiers":[
        {
            "category":"Retail",
            "subcategory":"Auto Repair",
            "type":"Services"
        }
    ],
    "sg:phone":"+44 1634 406664",
    "sg:postcode":"ME4 6QR",
    "sg:province":"Kent",
    "sg:tags":[
        "modification",
        "garage"
    ],
    "wof:name":"Hazel Motors (Gillingham) Ltd.",
    "wof:placetype":"venue"
},
  "geometry": {"coordinates":[0.518682003,51.3716011047],"type":"Point"}
}