{
  "type": "Feature",
  "properties": {
    "iso:country":"GB",
    "sg:address":"32 Lewes Way",
    "sg:city":"Rickmansworth",
    "sg:classifiers":[
        {
            "category":"Building & Trades",
            "subcategory":"Plumbing",
            "type":"Services"
        }
    ],
    "sg:postcode":"WD3 3SN",
    "sg:province":"Hertfordshire",
    "sg:tags":[
        "heating"
    ],
    "wof:name":"Martin Walledge",
    "wof:placetype":"venue"
},
  "geometry": {"coordinates":[-0.439177,51.65617],"type":"Point"}
}