{
  "type": "Feature",
  "properties": {
    "iso:country":"GB",
    "sg:address":"19 Park Avenue",
    "sg:city":"Whitley Bay",
    "sg:classifiers":[
        {
            "category":"Taxi",
            "type":"Transportation"
        },
        {
            "category":"Military Area",
            "subcategory":"Air Force Base",
            "type":"Public Place"
        }
    ],
    "sg:phone":"+44 191 251 5151",
    "sg:postcode":"NE26 1DP",
    "sg:province":"Northumberland",
    "sg:tags":[
        "mini",
        "hire",
        "private",
        "cab"
    ],
    "wof:name":"North East Taxis",
    "wof:placetype":"venue"
},
  "geometry": {"coordinates":[-1.447039,55.043526],"type":"Point"}
}