{
  "type": "Feature",
  "properties": {
    "addr:full":"23 Midland Road Gloucester Gloucestershire GL1 4UQ",
    "addr:housenumber":"23",
    "addr:postcode":"gl1 4uq",
    "addr:street":"Midland Road",
    "iso:country":"GB",
    "sg:address":"23 Midland Road",
    "sg:city":"Gloucester",
    "sg:classifiers":[
        {
            "category":"Travel",
            "subcategory":"Hostel",
            "type":"Entertainment"
        }
    ],
    "sg:phone":"+44 1452 307531",
    "sg:postcode":"GL1 4UQ",
    "sg:province":"Gloucestershire",
    "wof:name":"Link Project",
    "wof:placetype":"venue"
},
  "geometry": {"coordinates":[-2.241712,51.858444],"type":"Point"}
}