{
  "type": "Feature",
  "properties": {
    "addr:full":"23 Market Place Boston Lincolnshire PE21 6EH",
    "addr:housenumber":"23",
    "addr:postcode":"pe21 6eh",
    "addr:street":"Market Place",
    "iso:country":"GB",
    "sg:address":"23 Market Place",
    "sg:city":"Boston",
    "sg:classifiers":[
        {
            "category":"Bars & Pubs",
            "type":"Food & Drink"
        },
        {
            "category":"Community Center",
            "subcategory":"Social",
            "type":"Public Place"
        }
    ],
    "sg:phone":"+44 1205 369009",
    "sg:postcode":"PE21 6EH",
    "sg:province":"Lincolnshire",
    "sg:tags":[
        "pubs",
        "house",
        "inn",
        "activity"
    ],
    "wof:name":"GREENALLS MANAGEMENT LTD",
    "wof:placetype":"venue"
},
  "geometry": {"coordinates":[-0.0235450007,52.9774742126],"type":"Point"}
}