{
  "type": "Feature",
  "properties": {
    "addr:full":"Redannick Ho, Redannick La Truro Cornwall TR1 2JR",
    "addr:postcode":"tr1 2jr",
    "addr:street":"La",
    "iso:country":"GB",
    "sg:address":"Redannick Ho, Redannick La",
    "sg:city":"Truro",
    "sg:classifiers":[
        {
            "category":"Social Services",
            "subcategory":"Retirement Home",
            "type":"Services"
        }
    ],
    "sg:phone":"+44 1872 276889",
    "sg:postcode":"TR1 2JR",
    "sg:province":"Cornwall",
    "sg:tags":[
        "residential",
        "care"
    ],
    "wof:name":"Cornwall Care Homes",
    "wof:placetype":"venue"
},
  "geometry": {"coordinates":[-5.0536308289,50.2652397156],"type":"Point"}
}