{
  "type": "Feature",
  "properties": {
    "addr:full":"Gulf Service Station, Mumbles Road Swansea Swansea SA3 5AS",
    "addr:postcode":"sa3 5as",
    "addr:street":"Mumbles Road",
    "iso:country":"GB",
    "sg:address":"Gulf Service Station, Mumbles Road",
    "sg:city":"Swansea",
    "sg:classifiers":[
        {
            "category":"Autos & Motor Vehicles",
            "subcategory":"Fuel & Gas Station",
            "type":"Retail Goods"
        }
    ],
    "sg:postcode":"SA3 5AS",
    "sg:province":"Swansea",
    "sg:tags":[
        "hr",
        "petrol"
    ],
    "wof:name":"Mumbles Service Station",
    "wof:placetype":"venue"
},
  "geometry": {"coordinates":[-4.013214,51.588634],"type":"Point"}
}