{
  "type": "Feature",
  "properties": {
    "addr:full":"Unit 34 Cibyn Industrial Estate Caernarfon Gwynedd LL55 2BD",
    "addr:housenumber":"unit 34",
    "addr:postcode":"ll55 2bd",
    "addr:street":"Cibyn Industrial Estate",
    "iso:country":"GB",
    "sg:address":"Unit 34 Cibyn Industrial Estate",
    "sg:city":"Caernarfon",
    "sg:classifiers":[
        {
            "category":"Home & Garden",
            "subcategory":"Kitchen Supply",
            "type":"Retail Goods"
        }
    ],
    "sg:phone":"+44 1286 676999",
    "sg:postcode":"LL55 2BD",
    "sg:province":"Gwynedd",
    "sg:tags":[
        "measuring",
        "scale"
    ],
    "wof:name":"P P M Technology Ltd.",
    "wof:placetype":"venue"
},
  "geometry": {"coordinates":[-4.2528247833,53.1405830383],"type":"Point"}
}