{
  "type": "Feature",
  "properties": {
    "addr:full":"5 Gold Street Mews, 47 Gold St Northampton Northamptonshire NN1 1RA",
    "addr:housenumber":"5;47",
    "addr:postcode":"nn1 1ra",
    "addr:street":"Gold Street;Gold St",
    "iso:country":"GB",
    "sg:address":"5 Gold Street Mews, 47 Gold St",
    "sg:city":"Northampton",
    "sg:classifiers":[
        {
            "category":"Shopping",
            "subcategory":"Party Supplies",
            "type":"Retail Goods"
        }
    ],
    "sg:phone":"+44 1604 232639",
    "sg:postcode":"NN1 1RA",
    "sg:province":"Northamptonshire",
    "sg:tags":[
        "novelty"
    ],
    "wof:name":"Party In A Box",
    "wof:placetype":"venue"
},
  "geometry": {"coordinates":[-0.895284,52.23394],"type":"Point"}
}