{
  "type": "Feature",
  "properties": {
    "addr:full":"Brynhyfryd, Llanddeusant Llangadog Carmarthenshire SA19 9SP",
    "addr:postcode":"sa19 9sp",
    "iso:country":"GB",
    "sg:address":"Brynhyfryd, Llanddeusant",
    "sg:city":"Llangadog",
    "sg:classifiers":[
        {
            "category":"Building & Trades",
            "subcategory":"Construction",
            "type":"Services"
        }
    ],
    "sg:phone":"+44 1550 740286",
    "sg:postcode":"SA19 9SP",
    "sg:province":"Carmarthenshire",
    "sg:tags":[
        "builder"
    ],
    "wof:name":"Thomas K Williams",
    "wof:placetype":"venue"
},
  "geometry": {"coordinates":[-3.878694,51.938721],"type":"Point"}
}