{
  "type": "Feature",
  "properties": {
    "iso:country":"GB",
    "sg:address":"6 Skerry Hill",
    "sg:city":"Mansfield",
    "sg:classifiers":[
        {
            "category":"Personal",
            "subcategory":"Beauty Salon",
            "type":"Services"
        }
    ],
    "sg:postcode":"NG18 2PR",
    "sg:province":"Nottinghamshire",
    "sg:tags":[
        "unisex",
        "hairdresser"
    ],
    "wof:name":"Coppock,Glynis,",
    "wof:placetype":"venue"
},
  "geometry": {"coordinates":[-1.1798989773,53.1437683105],"type":"Point"}
}