{
  "type": "Feature",
  "properties": {
    "addr:full":"28 Bridge Street Alexandria Argyll and Bute G83 0TA",
    "addr:housenumber":"28",
    "addr:postcode":"g83 0ta",
    "addr:street":"Bridge Street",
    "iso:country":"GB",
    "sg:address":"28 Bridge Street",
    "sg:city":"Alexandria",
    "sg:classifiers":[
        {
            "category":"Travel",
            "subcategory":"Hostel",
            "type":"Entertainment"
        }
    ],
    "sg:phone":"+44 1389 757822",
    "sg:postcode":"G83 0TA",
    "sg:province":"Argyll and Bute",
    "sg:website":"http://www.nch.org.uk",
    "wof:name":"Preparation For Life",
    "wof:placetype":"venue"
},
  "geometry": {"coordinates":[-4.57996,55.984352],"type":"Point"}
}