{
  "type": "Feature",
  "properties": {
    "iso:country":"GB",
    "sg:address":"16 Albert Road",
    "sg:city":"Chatham",
    "sg:classifiers":[
        {
            "category":"Building & Trades",
            "subcategory":"Construction",
            "type":"Services"
        }
    ],
    "sg:phone":"+44 1634 848652",
    "sg:postcode":"ME4 5PZ",
    "sg:province":"Kent",
    "sg:tags":[
        "decorator",
        "painter"
    ],
    "wof:name":"City Artexing",
    "wof:placetype":"venue"
},
  "geometry": {"coordinates":[0.52985,51.374485],"type":"Point"}
}