{
  "type": "Feature",
  "properties": {
    "addr:full":"42 Brooke St Alfreton Derbyshire DE55 5PX",
    "addr:housenumber":"42",
    "addr:postcode":"de55 5px",
    "addr:street":"Brooke St",
    "iso:country":"GB",
    "sg:address":"42 Brooke St",
    "sg:city":"Alfreton",
    "sg:classifiers":[
        {
            "category":"Food & Beverages",
            "subcategory":"Bakery",
            "type":"Retail Goods"
        }
    ],
    "sg:phone":"+44 1773 872251",
    "sg:postcode":"DE55 5PX",
    "sg:province":"Derbyshire",
    "sg:tags":[
        "baker"
    ],
    "wof:name":"F A Smith & Sons",
    "wof:placetype":"venue"
},
  "geometry": {"coordinates":[-1.338611,53.144012],"type":"Point"}
}