{
  "type": "Feature",
  "properties": {
    "addr:full":"24 Sillwood Street Brighton East Sussex BN1 2PS",
    "addr:housenumber":"24",
    "addr:postcode":"bn1 2ps",
    "addr:street":"Sillwood Street",
    "iso:country":"GB",
    "sg:address":"24 Sillwood Street",
    "sg:city":"Brighton",
    "sg:classifiers":[
        {
            "category":"Bars & Pubs",
            "type":"Food & Drink"
        }
    ],
    "sg:phone":"+44 1273 327299",
    "sg:postcode":"BN1 2PS",
    "sg:province":"East Sussex",
    "sg:tags":[
        "pubs",
        "inn"
    ],
    "wof:name":"The Lion & Lobster",
    "wof:placetype":"venue"
},
  "geometry": {"coordinates":[-0.1540450007,50.823764801],"type":"Point"}
}