{
  "type": "Feature",
  "properties": {
    "addr:full":"Gushmere Court Farm, Gushmere, Selling Faversham Kent ME13 9RF",
    "addr:postcode":"me13 9rf",
    "iso:country":"GB",
    "sg:address":"Gushmere Court Farm, Gushmere, Selling",
    "sg:city":"Faversham",
    "sg:classifiers":[
        {
            "category":"Farming",
            "subcategory":"Farm",
            "type":"Manufacturing & Wholesale Goods"
        }
    ],
    "sg:phone":"+44 1227 752205",
    "sg:postcode":"ME13 9RF",
    "sg:province":"Kent",
    "sg:tags":[
        "mixed",
        "crop"
    ],
    "sg:website":"http://www.farmline.com",
    "wof:name":"S C & J H Berry Ltd",
    "wof:placetype":"venue"
},
  "geometry": {"coordinates":[0.88344,51.309605],"type":"Point"}
}