{
  "type": "Feature",
  "properties": {
    "iso:country":"GB",
    "sg:address":"179 Crow Lane",
    "sg:city":"Bristol",
    "sg:classifiers":[
        {
            "category":"Cafe",
            "type":"Food & Drink"
        }
    ],
    "sg:postcode":"BS10 7DR",
    "sg:province":"City of Bristol",
    "sg:tags":[
        "tea",
        "room"
    ],
    "wof:name":"Mrs Miggins Coffee Shop",
    "wof:placetype":"venue"
},
  "geometry": {"coordinates":[-2.619913,51.509502],"type":"Point"}
}