{
  "type": "Feature",
  "properties": {
    "addr:full":"High Bank Farm, Appledore Road Tenterden Kent TN30 7DH",
    "addr:postcode":"tn30 7dh",
    "addr:street":"Appledore Road",
    "iso:country":"GB",
    "sg:address":"High Bank Farm, Appledore Road",
    "sg:city":"Tenterden",
    "sg:classifiers":[
        {
            "category":"Food & Beverages",
            "subcategory":"Fruits & Vegetables",
            "type":"Retail Goods"
        }
    ],
    "sg:postcode":"TN30 7DH",
    "sg:province":"Kent",
    "sg:tags":[
        "greengrocer"
    ],
    "wof:name":"A R & G M Bush",
    "wof:placetype":"venue"
},
  "geometry": {"coordinates":[0.6940600276,51.0754051208],"type":"Point"}
}