{
  "type": "Feature",
  "properties": {
    "iso:country":"GB",
    "sg:address":"2 Lyne House, Rusper Road, Capel",
    "sg:city":"Dorking",
    "sg:classifiers":[
        {
            "category":"Manufacturing",
            "subcategory":"Textiles",
            "type":"Manufacturing & Wholesale Goods"
        },
        {
            "category":"Shopping",
            "subcategory":"Crafts & Fabrics",
            "type":"Retail Goods"
        }
    ],
    "sg:phone":"+44 1293 871670",
    "sg:postcode":"RH5 5HQ",
    "sg:province":"Surrey",
    "sg:tags":[
        "shop",
        "merchant",
        "agent"
    ],
    "wof:name":"Tessuti Ltd.",
    "wof:placetype":"venue"
},
  "geometry": {"coordinates":[-0.323139,51.149815],"type":"Point"}
}