{
  "type": "Feature",
  "properties": {
    "iso:country":"GB",
    "sg:address":"12 Widnes Road",
    "sg:city":"Widnes",
    "sg:classifiers":[
        {
            "category":"Shopping",
            "subcategory":"Stationery & Office Supplies",
            "type":"Retail Goods"
        },
        {
            "category":"Professional",
            "subcategory":"Printing & Photocopies",
            "type":"Services"
        }
    ],
    "sg:phone":"+44 151 495 2359",
    "sg:postcode":"WA8 6AD",
    "sg:province":"Cheshire",
    "sg:tags":[
        "equipment",
        "duplicating",
        "copying"
    ],
    "wof:name":"Commercial Business Equipment (Services) Ltd.",
    "wof:placetype":"venue"
},
  "geometry": {"coordinates":[-2.7310009003,53.3632125854],"type":"Point"}
}