{
  "type": "Feature",
  "properties": {
    "addr:full":"44 Westgate Shipley West Yorkshire BD18 3QX",
    "addr:housenumber":"44",
    "addr:postcode":"bd18 3qx",
    "addr:street":"Westgate Shipley West",
    "iso:country":"GB",
    "sg:address":"44 Westgate",
    "sg:city":"Shipley",
    "sg:classifiers":[
        {
            "category":"Personal",
            "subcategory":"Beauty Salon",
            "type":"Services"
        },
        {
            "category":"Personal",
            "subcategory":"Barber",
            "type":"Services"
        }
    ],
    "sg:phone":"+44 1274 589126",
    "sg:postcode":"BD18 3QX",
    "sg:province":"West Yorkshire",
    "sg:tags":[
        "unisex",
        "hairdresser"
    ],
    "wof:name":"Raymond Norcliffe",
    "wof:placetype":"venue"
},
  "geometry": {"coordinates":[-1.779005,53.834499],"type":"Point"}
}