{
  "type": "Feature",
  "properties": {
    "iso:country":"GB",
    "sg:address":"289 Mackadown Lane",
    "sg:city":"Birmingham",
    "sg:classifiers":[
        {
            "category":"Travel",
            "subcategory":"Hotels & Motels",
            "type":"Entertainment"
        }
    ],
    "sg:phone":"+44 121 785 2145",
    "sg:postcode":"B33 0NH",
    "sg:province":"West Midlands",
    "sg:tags":[
        "house",
        "guest"
    ],
    "wof:name":"CHARD HOUSE",
    "wof:placetype":"venue"
},
  "geometry": {"coordinates":[-1.770547,52.479156],"type":"Point"}
}