{
  "type": "Feature",
  "properties": {
    "addr:full":"Spitalgate Level Grantham Lincolnshire NG31 7UP",
    "addr:postcode":"ng31 7up",
    "addr:street":"Spitalgate",
    "iso:country":"GB",
    "sg:address":"Spitalgate Level",
    "sg:city":"Grantham",
    "sg:classifiers":[
        {
            "category":"Freight",
            "type":"Transportation"
        }
    ],
    "sg:phone":"+44 1476 591485",
    "sg:postcode":"NG31 7UP",
    "sg:province":"Lincolnshire",
    "sg:tags":[
        "haulage",
        "road"
    ],
    "wof:name":"Swain Contracts",
    "wof:placetype":"venue"
},
  "geometry": {"coordinates":[-0.6328889728,52.8882255554],"type":"Point"}
}