{
  "type": "Feature",
  "properties": {
    "iso:country":"GB",
    "sg:address":"Fosseway",
    "sg:city":"Clevedon",
    "sg:classifiers":[
        {
            "category":"Education",
            "subcategory":"School",
            "type":"Public Place"
        },
        {
            "category":"Government",
            "subcategory":"Office",
            "type":"Public Place"
        }
    ],
    "sg:phone":"+44 1275 873417",
    "sg:postcode":"BS21 5EL",
    "sg:province":"Somerset",
    "sg:tags":[
        "local",
        "authority"
    ],
    "wof:name":"St John the Evangelist C of E Primary School",
    "wof:placetype":"venue"
},
  "geometry": {"coordinates":[-2.858147,51.430843],"type":"Point"}
}