{
  "type": "Feature",
  "properties": {
    "iso:country":"GB",
    "sg:address":"First Floor",
    "sg:city":"Dover",
    "sg:classifiers":[
        {
            "category":"Social Services",
            "subcategory":"Job Training",
            "type":"Services"
        }
    ],
    "sg:phone":"+44 1304 242702",
    "sg:postcode":"CT16 1PW",
    "sg:province":"Kent",
    "sg:tags":[
        "draughtsman",
        "drawing"
    ],
    "wof:name":"C A D Solutions",
    "wof:placetype":"venue"
},
  "geometry": {"coordinates":[1.328761,51.126846],"type":"Point"}
}