{
  "type": "Feature",
  "properties": {
    "iso:country":"GB",
    "sg:address":"The Farmhouse, New Salts Farm",
    "sg:city":"Shoreham-by-sea",
    "sg:classifiers":[
        {
            "category":"Farming",
            "subcategory":"Livestock Farm",
            "type":"Manufacturing & Wholesale Goods"
        }
    ],
    "sg:phone":"+44 1273 453303",
    "sg:postcode":"BN43 5FE",
    "sg:province":"West Sussex",
    "sg:tags":[
        "others"
    ],
    "wof:name":"Jack Hoad",
    "wof:placetype":"venue"
},
  "geometry": {"coordinates":[-0.276469,50.831917],"type":"Point"}
}