{
  "type": "Feature",
  "properties": {
    "addr:full":"48 East Crescent, New Southgate London Greater London N11 3AY",
    "addr:housenumber":"48",
    "addr:postcode":"n11 3ay",
    "addr:street":"East Crescent",
    "iso:country":"GB",
    "sg:address":"48 East Crescent, New Southgate",
    "sg:city":"London",
    "sg:classifiers":[
        {
            "category":"Building & Trades",
            "subcategory":"Construction",
            "type":"Services"
        }
    ],
    "sg:phone":"+44 20 8361 4848",
    "sg:postcode":"N11 3AY",
    "sg:province":"Greater London",
    "sg:tags":[
        "builder"
    ],
    "wof:name":"Wood & Waters",
    "wof:placetype":"venue"
},
  "geometry": {"coordinates":[-0.153216,51.620831],"type":"Point"}
}