{
  "type": "Feature",
  "properties": {
    "addr:full":"186 High Street Slough Berkshire SL1 1JS",
    "addr:housenumber":"186",
    "addr:postcode":"sl1 1js",
    "addr:street":"High Street",
    "iso:country":"GB",
    "sg:address":"186 High Street",
    "sg:city":"Slough",
    "sg:classifiers":[
        {
            "category":"Shopping",
            "subcategory":"Clothing, Apparel, & Fashions",
            "type":"Retail Goods"
        }
    ],
    "sg:phone":"+44 1753 529585",
    "sg:postcode":"SL1 1JS",
    "sg:province":"Berkshire",
    "sg:tags":[
        "shop"
    ],
    "wof:name":"River Island Clothing Co",
    "wof:placetype":"venue"
},
  "geometry": {"coordinates":[-0.588939,51.507778],"type":"Point"}
}