{
  "type": "Feature",
  "properties": {
    "addr:full":"5 Dunchurch Clo Redditch Warwickshire B98 0BG",
    "addr:housenumber":"5",
    "addr:postcode":"b98 0bg",
    "addr:street":"Dunchurch Clo",
    "iso:country":"GB",
    "sg:address":"5 Dunchurch Clo",
    "sg:city":"Redditch",
    "sg:classifiers":[
        {
            "category":"Professional",
            "type":"Services"
        }
    ],
    "sg:phone":"+44 1527 527841",
    "sg:postcode":"B98 0BG",
    "sg:province":"Warwickshire",
    "sg:tags":[
        "caterer"
    ],
    "wof:name":"Tomlin Caterers",
    "wof:placetype":"venue"
},
  "geometry": {"coordinates":[-1.8885309696,52.2928848267],"type":"Point"}
}