{
  "type": "Feature",
  "properties": {
    "addr:full":"Woodside Way Glenrothes Fife KY7 4ND",
    "addr:postcode":"ky7 4nd",
    "addr:street":"Woodside Way",
    "iso:country":"GB",
    "sg:address":"Woodside Way",
    "sg:city":"Glenrothes",
    "sg:classifiers":[
        {
            "category":"Home & Garden",
            "subcategory":"Home Furnishings",
            "type":"Retail Goods"
        }
    ],
    "sg:postcode":"KY7 4ND",
    "sg:province":"Fife",
    "sg:tags":[
        "racking",
        "shelving",
        "diy"
    ],
    "wof:name":"Wilma Finnie",
    "wof:placetype":"venue"
},
  "geometry": {"coordinates":[-3.1487190723,56.1876945496],"type":"Point"}
}