{
  "type": "Feature",
  "properties": {
    "iso:country":"GB",
    "sg:address":"Unit 11 Cranfield Innovation Cen, Tre University Wa",
    "sg:city":"Bedford",
    "sg:classifiers":[
        {
            "category":"Professional",
            "subcategory":"Management & Consulting",
            "type":"Services"
        }
    ],
    "sg:phone":"+44 70 7178 1723",
    "sg:postcode":"MK43 0BT",
    "sg:province":"Bedfordshire",
    "sg:tags":[
        "consultant",
        "training"
    ],
    "wof:name":"Strategic Training & Consulting Ltd.",
    "wof:placetype":"venue"
},
  "geometry": {"coordinates":[-0.634594,52.065235],"type":"Point"}
}