{
  "type": "Feature",
  "properties": {
    "addr:full":"54 St Thomas Street Wells Somerset BA5 2UZ",
    "addr:housenumber":"54",
    "addr:postcode":"ba5 2uz",
    "addr:street":"St Thomas Street",
    "iso:country":"GB",
    "sg:address":"54 St Thomas Street",
    "sg:city":"Wells",
    "sg:classifiers":[
        {
            "category":"Farming",
            "subcategory":"Dairy Farm",
            "type":"Manufacturing & Wholesale Goods"
        }
    ],
    "sg:postcode":"BA5 2UZ",
    "sg:province":"Somerset",
    "wof:name":"Pullin Bros",
    "wof:placetype":"venue"
},
  "geometry": {"coordinates":[-2.6384160519,51.2126731873],"type":"Point"}
}