{
  "type": "Feature",
  "properties": {
    "addr:full":"260 Walton Rd, Manor Park Manor Park Greater London E12 5RL",
    "addr:housenumber":"260",
    "addr:postcode":"e12 5rl",
    "addr:street":"Walton Rd;Park Manor Park",
    "iso:country":"GB",
    "sg:address":"260 Walton Rd, Manor Park",
    "sg:city":"Manor Park",
    "sg:classifiers":[
        {
            "category":"Building & Trades",
            "subcategory":"Construction",
            "type":"Services"
        }
    ],
    "sg:phone":"+44 20 8478 0949",
    "sg:postcode":"E12 5RL",
    "sg:province":"Greater London",
    "sg:tags":[
        "decorator",
        "painter"
    ],
    "wof:name":"Icon Interiors",
    "wof:placetype":"venue"
},
  "geometry": {"coordinates":[0.064032,51.549835],"type":"Point"}
}