{
  "type": "Feature",
  "properties": {
    "addr:full":"Barn Cottage, Higher Street Merriott Somerset TA16 5PJ",
    "addr:postcode":"ta16 5pj",
    "addr:street":"Higher Street",
    "iso:country":"GB",
    "sg:address":"Barn Cottage, Higher Street",
    "sg:city":"Merriott",
    "sg:classifiers":[
        {
            "category":"Professional",
            "subcategory":"Engineering",
            "type":"Services"
        },
        {
            "category":"Building & Trades",
            "subcategory":"Electrical",
            "type":"Services"
        }
    ],
    "sg:phone":"+44 1460 73260",
    "sg:postcode":"TA16 5PJ",
    "sg:province":"Somerset",
    "sg:tags":[
        "engineer",
        "electrician",
        "contractor"
    ],
    "wof:name":"Kevin Swain",
    "wof:placetype":"venue"
},
  "geometry": {"coordinates":[-2.794613,50.908924],"type":"Point"}
}