{
  "type": "Feature",
  "properties": {
    "addr:full":"Wedgewood, Sarratt Lane, Loudwater Rickmansworth Hertfordshire WD3 4AS",
    "addr:postcode":"wd3 4as",
    "addr:street":"Sarratt Lane",
    "iso:country":"GB",
    "sg:address":"Wedgewood, Sarratt Lane, Loudwater",
    "sg:city":"Rickmansworth",
    "sg:classifiers":[
        {
            "category":"Professional",
            "subcategory":"Management & Consulting",
            "type":"Services"
        }
    ],
    "sg:phone":"+44 1923 896606",
    "sg:postcode":"WD3 4AS",
    "sg:province":"Hertfordshire",
    "sg:tags":[
        "consultant",
        "business"
    ],
    "wof:name":"Corporate Development Partnership",
    "wof:placetype":"venue"
},
  "geometry": {"coordinates":[-0.4780910015,51.6542930603],"type":"Point"}
}