{
  "type": "Feature",
  "properties": {
    "addr:full":"The Smithy, Four Crosses Llanymynech Shropshire SY22 6PG",
    "addr:postcode":"sy22 6pg",
    "iso:country":"GB",
    "sg:address":"The Smithy, Four Crosses",
    "sg:city":"Llanymynech",
    "sg:classifiers":[
        {
            "category":"Professional",
            "subcategory":"Engineering",
            "type":"Services"
        }
    ],
    "sg:phone":"+44 1691 830440",
    "sg:postcode":"SY22 6PG",
    "sg:province":"Shropshire",
    "wof:name":"Heylin Engineering",
    "wof:placetype":"venue"
},
  "geometry": {"coordinates":[-3.0893540382,52.7808532715],"type":"Point"}
}