{
  "type": "Feature",
  "properties": {
    "addr:full":"484 Green Lanes London Greater London N13 5PA",
    "addr:housenumber":"484",
    "addr:postcode":"n13 5pa",
    "addr:street":"Green Lanes",
    "iso:country":"GB",
    "sg:address":"484 Green Lanes",
    "sg:city":"London",
    "sg:classifiers":[
        {
            "category":"Shopping",
            "subcategory":"Antiques",
            "type":"Retail Goods"
        }
    ],
    "sg:postcode":"N13 5PA",
    "sg:province":"Greater London",
    "wof:name":"Barry Middleton",
    "wof:placetype":"venue"
},
  "geometry": {"coordinates":[-0.103926,51.623322],"type":"Point"}
}