{
  "type": "Feature",
  "properties": {
    "iso:country":"GB",
    "sg:address":"29 Kings St",
    "sg:city":"Leeds",
    "sg:classifiers":[
        {
            "category":"Professional",
            "subcategory":"Employment Agencies",
            "type":"Services"
        }
    ],
    "sg:phone":"+44 113 246 0049",
    "sg:postcode":"LS1 2HL",
    "sg:province":"West Yorkshire",
    "sg:tags":[
        "consultant"
    ],
    "wof:name":"Jarvis - Morgan Recruitment",
    "wof:placetype":"venue"
},
  "geometry": {"coordinates":[-1.550345,53.797272],"type":"Point"}
}