{
  "type": "Feature",
  "properties": {
    "iso:country":"GB",
    "sg:address":"472 St Albans Rd",
    "sg:city":"Watford",
    "sg:classifiers":[
        {
            "category":"Shopping",
            "subcategory":"Mobile Phones",
            "type":"Retail Goods"
        }
    ],
    "sg:phone":"+44 1923 241422",
    "sg:postcode":"WD2 5QU",
    "sg:province":"Hertfordshire",
    "wof:name":"Telecom Warehouse",
    "wof:placetype":"venue"
},
  "geometry": {"coordinates":[-0.396328,51.678715],"type":"Point"}
}