{
  "type": "Feature",
  "properties": {
    "addr:full":"1 Marine Parade Dawlish Devon EX7 9DJ",
    "addr:housenumber":"1",
    "addr:postcode":"ex7 9dj",
    "addr:street":"Marine Parade",
    "iso:country":"GB",
    "sg:address":"1 Marine Parade",
    "sg:city":"Dawlish",
    "sg:classifiers":[
        {
            "category":"Travel",
            "subcategory":"Hotels & Motels",
            "type":"Entertainment"
        },
        {
            "category":"Bars & Pubs",
            "subcategory":"Hookah Bar",
            "type":"Food & Drink"
        }
    ],
    "sg:phone":"+44 1626 862372",
    "sg:postcode":"EX7 9DJ",
    "sg:province":"Devon",
    "sg:tags":[
        "self",
        "holiday",
        "catering"
    ],
    "wof:name":"Blenheim Holiday Flatlets",
    "wof:placetype":"venue"
},
  "geometry": {"coordinates":[-3.4661478996,50.5795402527],"type":"Point"}
}