{
  "type": "Feature",
  "properties": {
    "addr:full":"Unit 1a, The Old Railway Works, Newtown Rd Ind Est Ashford Kent TN24 0PN",
    "addr:housenumber":"unit 1a",
    "addr:postcode":"tn24 0pn",
    "addr:street":"The Old Railway Works Newtown Rd",
    "iso:country":"GB",
    "sg:address":"Unit 1a, The Old Railway Works, Newtown Rd Ind Est",
    "sg:city":"Ashford",
    "sg:classifiers":[
        {
            "category":"Utilities",
            "subcategory":"Recycling",
            "type":"Services"
        }
    ],
    "sg:phone":"+44 1233 642900",
    "sg:postcode":"TN24 0PN",
    "sg:province":"Kent",
    "sg:tags":[
        "centre"
    ],
    "wof:name":"Enviroplus",
    "wof:placetype":"venue"
},
  "geometry": {"coordinates":[0.8840199709,51.1378097534],"type":"Point"}
}