{
  "type": "Feature",
  "properties": {
    "addr:full":"42 Church Road London Greater London N17 8AQ",
    "addr:housenumber":"42",
    "addr:postcode":"n17 8aq",
    "addr:street":"Church Road",
    "iso:country":"GB",
    "sg:address":"42 Church Road",
    "sg:city":"London",
    "sg:classifiers":[
        {
            "category":"Shopping",
            "subcategory":"News",
            "type":"Retail Goods"
        }
    ],
    "sg:phone":"+44 20 8808 6515",
    "sg:postcode":"N17 8AQ",
    "sg:province":"Greater London",
    "sg:tags":[
        "newsagent"
    ],
    "wof:name":"Yogi Newsagents",
    "wof:placetype":"venue"
},
  "geometry": {"coordinates":[-0.071238,51.602249],"type":"Point"}
}