{
  "type": "Feature",
  "properties": {
    "addr:full":"Anchor House, 1-3 The Parade Esher Surrey KT10 0PD",
    "addr:housenumber":"1-3",
    "addr:postcode":"kt10 0pd",
    "addr:street":"The Parade",
    "iso:country":"GB",
    "sg:address":"Anchor House, 1-3 The Parade",
    "sg:city":"Esher",
    "sg:classifiers":[
        {
            "category":"Professional",
            "subcategory":"Accounting & Tax Preparation",
            "type":"Services"
        }
    ],
    "sg:phone":"+44 1372 469966",
    "sg:postcode":"KT10 0PD",
    "sg:province":"Surrey",
    "sg:tags":[
        "accountant",
        "activity"
    ],
    "wof:name":"Li Mitchell & Co",
    "wof:placetype":"venue"
},
  "geometry": {"coordinates":[-0.3462379873,51.361038208],"type":"Point"}
}