{
  "type": "Feature",
  "properties": {
    "iso:country":"GB",
    "sg:address":"7-8 High Street",
    "sg:city":"Crediton",
    "sg:classifiers":[
        {
            "category":"Shopping",
            "subcategory":"Pets & Pet Supplies",
            "type":"Retail Goods"
        }
    ],
    "sg:phone":"+44 1363 773247",
    "sg:postcode":"EX17 3AE",
    "sg:province":"Devon",
    "sg:tags":[
        "shop"
    ],
    "wof:name":"Crediton Pet Shop",
    "wof:placetype":"venue"
},
  "geometry": {"coordinates":[-3.6578450203,50.7903175354],"type":"Point"}
}