{
  "type": "Feature",
  "properties": {
    "iso:country":"GB",
    "sg:address":"6 Skye Road, Shawfarm Industrial Estate",
    "sg:city":"Prestwick",
    "sg:classifiers":[
        {
            "category":"Recreation",
            "subcategory":"Water Park",
            "type":"Entertainment"
        }
    ],
    "sg:postcode":"KA9 2TA",
    "sg:province":"South Ayrshire",
    "sg:tags":[
        "sport"
    ],
    "wof:name":"Teltale",
    "wof:placetype":"venue"
},
  "geometry": {"coordinates":[-4.593694,55.502071],"type":"Point"}
}