{
  "type": "Feature",
  "properties": {
    "iso:country":"GB",
    "sg:address":"Unit 2, Cwmdraw Industrial Estate",
    "sg:city":"Ebbw Vale",
    "sg:classifiers":[
        {
            "category":"Building & Trades",
            "subcategory":"Construction",
            "type":"Services"
        }
    ],
    "sg:phone":"+44 1495 350758",
    "sg:postcode":"NP23 5AE",
    "sg:province":"Blaenau Gwent",
    "sg:tags":[
        "joinery"
    ],
    "wof:name":"Gwent Woodcraft Ltd.",
    "wof:placetype":"venue"
},
  "geometry": {"coordinates":[-3.200026,51.777477],"type":"Point"}
}