{
  "type": "Feature",
  "properties": {
    "addr:full":"74 Bowerdean Road High Wycombe Buckinghamshire HP13 6AZ",
    "addr:housenumber":"74",
    "addr:postcode":"hp13 6az",
    "addr:street":"Bowerdean Road",
    "iso:country":"GB",
    "sg:address":"74 Bowerdean Road",
    "sg:city":"High Wycombe",
    "sg:classifiers":[
        {
            "category":"Retail",
            "subcategory":"Auto Repair",
            "type":"Services"
        }
    ],
    "sg:phone":"+44 1494 452296",
    "sg:postcode":"HP13 6AZ",
    "sg:province":"Buckinghamshire",
    "sg:tags":[
        "modification",
        "garage"
    ],
    "wof:name":"A & B Auto Salvage",
    "wof:placetype":"venue"
},
  "geometry": {"coordinates":[-0.7343930006,51.6289710999],"type":"Point"}
}