{
  "type": "Feature",
  "properties": {
    "addr:full":"469-471 Eglinton Street Glasgow Glasgow City G5 9RU",
    "addr:housenumber":"469-471",
    "addr:postcode":"g5 9ru",
    "addr:street":"Eglinton Street",
    "iso:country":"GB",
    "sg:address":"469-471 Eglinton Street",
    "sg:city":"Glasgow",
    "sg:classifiers":[
        {
            "category":"Food & Beverages",
            "subcategory":"Meat & Fish",
            "type":"Retail Goods"
        }
    ],
    "sg:phone":"+44 141 429 7892",
    "sg:postcode":"G5 9RU",
    "sg:province":"Glasgow City",
    "sg:tags":[
        "butcher"
    ],
    "wof:name":"Kashmir Stores",
    "wof:placetype":"venue"
},
  "geometry": {"coordinates":[-4.2616667747,55.8447418213],"type":"Point"}
}