{
  "type": "Feature",
  "properties": {
    "iso:country":"GB",
    "sg:address":"65 Wrexham St",
    "sg:city":"Mold",
    "sg:classifiers":[
        {
            "category":"Shopping",
            "subcategory":"Clothing, Apparel, & Fashions",
            "type":"Retail Goods"
        }
    ],
    "sg:postcode":"CH7 1HQ",
    "sg:province":"Denbighshire",
    "sg:tags":[
        "dresswear"
    ],
    "wof:name":"Vaughan-Davies Ltd",
    "wof:placetype":"venue"
},
  "geometry": {"coordinates":[-3.141354084,53.1663742065],"type":"Point"}
}