{
  "type": "Feature",
  "properties": {
    "iso:country":"GB",
    "sg:address":"40 Spring Hill, Kingswood",
    "sg:city":"Bristol",
    "sg:classifiers":[
        {
            "category":"Professional",
            "subcategory":"Detective & Security Services",
            "type":"Services"
        }
    ],
    "sg:postcode":"BS15 1XT",
    "sg:province":"City of Bristol",
    "wof:name":"Robert Close",
    "wof:placetype":"venue"
},
  "geometry": {"coordinates":[-2.501747,51.468853],"type":"Point"}
}