{
  "type": "Feature",
  "properties": {
    "addr:full":"71 Trinity Rd Tooting Greater London SW17 7SD",
    "addr:housenumber":"71",
    "addr:postcode":"sw17 7sd",
    "addr:street":"Trinity Rd",
    "iso:country":"GB",
    "sg:address":"71 Trinity Rd",
    "sg:city":"Tooting",
    "sg:classifiers":[
        {
            "category":"Autos & Motor Vehicles",
            "subcategory":"Motorcycle Sales",
            "type":"Retail Goods"
        }
    ],
    "sg:phone":"+44 20 8767 8737",
    "sg:postcode":"SW17 7SD",
    "sg:province":"Greater London",
    "wof:name":"Siamoto Scooters",
    "wof:placetype":"venue"
},
  "geometry": {"coordinates":[-0.161654,51.437035],"type":"Point"}
}