{
  "type": "Feature",
  "properties": {
    "addr:full":"23 Hazel Close, Floral Way Andover Hampshire SP10 3PT",
    "addr:housenumber":"23",
    "addr:postcode":"sp10 3pt",
    "addr:street":"Hazel Close Floral Way",
    "iso:country":"GB",
    "sg:address":"23 Hazel Close, Floral Way",
    "sg:city":"Andover",
    "sg:classifiers":[
        {
            "category":"Building & Trades",
            "subcategory":"Construction",
            "type":"Services"
        }
    ],
    "sg:phone":"+44 1264 359039",
    "sg:postcode":"SP10 3PT",
    "sg:province":"Hampshire",
    "sg:tags":[
        "decorator",
        "painter"
    ],
    "wof:name":"Andrew Kent",
    "wof:placetype":"venue"
},
  "geometry": {"coordinates":[-1.5033860207,51.2008705139],"type":"Point"}
}