{
  "type": "Feature",
  "properties": {
    "addr:full":"15 Maberly Street Aberdeen Aberdeen City AB25 1NA",
    "addr:housenumber":"15",
    "addr:postcode":"ab25 1na",
    "addr:street":"Maberly Street",
    "iso:country":"GB",
    "sg:address":"15 Maberly Street",
    "sg:city":"Aberdeen",
    "sg:classifiers":[
        {
            "category":"Professional",
            "subcategory":"Printing & Photocopies",
            "type":"Services"
        }
    ],
    "sg:phone":"+44 1224 637383",
    "sg:postcode":"AB25 1NA",
    "sg:province":"Aberdeen City",
    "sg:tags":[
        "printer"
    ],
    "wof:name":"Scottaspress Publishers Ltd.",
    "wof:placetype":"venue"
},
  "geometry": {"coordinates":[-2.1046090126,57.152141571],"type":"Point"}
}