{
  "type": "Feature",
  "properties": {
    "addr:full":"221b Shinfield Road Reading Berkshire RG2 8HA",
    "addr:housenumber":"221b",
    "addr:postcode":"rg2 8ha",
    "addr:street":"Shinfield Road",
    "iso:country":"GB",
    "sg:address":"221b Shinfield Road",
    "sg:city":"Reading",
    "sg:classifiers":[
        {
            "category":"Health Services",
            "subcategory":"Dentist",
            "type":"Services"
        }
    ],
    "sg:phone":"+44 118 975 6161",
    "sg:postcode":"RG2 8HA",
    "sg:province":"Berkshire",
    "wof:name":"B S Ranu",
    "wof:placetype":"venue"
},
  "geometry": {"coordinates":[-0.946219027,51.4275016785],"type":"Point"}
}