{
  "type": "Feature",
  "properties": {
    "addr:full":"6 Barton Court, Barton Road Woolacombe Devon EX34 7BA",
    "addr:housenumber":"6",
    "addr:postcode":"ex34 7ba",
    "addr:street":"Barton Court Barton Road",
    "iso:country":"GB",
    "sg:address":"6 Barton Court, Barton Road",
    "sg:city":"Woolacombe",
    "sg:classifiers":[
        {
            "category":"Fast Food",
            "type":"Food & Drink"
        },
        {
            "category":"Cafe",
            "type":"Food & Drink"
        }
    ],
    "sg:phone":"+44 1271 870714",
    "sg:postcode":"EX34 7BA",
    "sg:province":"Devon",
    "sg:tags":[
        "tea",
        "away",
        "room",
        "take"
    ],
    "wof:name":"Lunch Box Sandwich Bar",
    "wof:placetype":"venue"
},
  "geometry": {"coordinates":[-4.2064838409,51.1728668213],"type":"Point"}
}