{
  "type": "Feature",
  "properties": {
    "addr:full":"429 Stapleton Road, Eastville Bristol City of Bristol BS5 6NA",
    "addr:housenumber":"429",
    "addr:postcode":"bs5 6na",
    "addr:street":"Stapleton Road",
    "iso:country":"GB",
    "sg:address":"429 Stapleton Road, Eastville",
    "sg:city":"Bristol",
    "sg:classifiers":[
        {
            "category":"Organizations",
            "subcategory":"Community Association",
            "type":"Services"
        }
    ],
    "sg:phone":"+44 117 939 3911",
    "sg:postcode":"BS5 6NA",
    "sg:province":"City of Bristol",
    "sg:tags":[
        "society",
        "housing"
    ],
    "wof:name":"Aashyana Housing Association Ltd.",
    "wof:placetype":"venue"
},
  "geometry": {"coordinates":[-2.5647230148,51.4697875977],"type":"Point"}
}