{
  "type": "Feature",
  "properties": {
    "addr:full":"16a Bath Rd Walsall West Midlands WS1 3BS",
    "addr:housenumber":"16a",
    "addr:postcode":"ws1 3bs",
    "addr:street":"Bath Rd",
    "iso:country":"GB",
    "sg:address":"16a Bath Rd",
    "sg:city":"Walsall",
    "sg:classifiers":[
        {
            "category":"Retail",
            "subcategory":"Auto Repair",
            "type":"Services"
        }
    ],
    "sg:postcode":"WS1 3BS",
    "sg:province":"West Midlands",
    "sg:tags":[
        "electrician"
    ],
    "wof:name":"Adcock,Bernard,",
    "wof:placetype":"venue"
},
  "geometry": {"coordinates":[-1.980043,52.576595],"type":"Point"}
}