{
  "type": "Feature",
  "properties": {
    "addr:full":"234 Old Road Clacton-on-sea Essex CO15 3LX",
    "addr:housenumber":"234",
    "addr:postcode":"co15 3lx",
    "addr:street":"Old Road",
    "iso:country":"GB",
    "sg:address":"234 Old Road",
    "sg:city":"Clacton-on-sea",
    "sg:classifiers":[
        {
            "category":"Autos & Motor Vehicles",
            "subcategory":"Auto Supplies",
            "type":"Retail Goods"
        },
        {
            "category":"Retail",
            "subcategory":"Auto Repair",
            "type":"Services"
        }
    ],
    "sg:postcode":"CO15 3LX",
    "sg:province":"Essex",
    "sg:tags":[
        "modification",
        "garage",
        "windscreen"
    ],
    "wof:name":"B T B Windscreens",
    "wof:placetype":"venue"
},
  "geometry": {"coordinates":[1.1500589848,51.7972717285],"type":"Point"}
}