{
  "type": "Feature",
  "properties": {
    "iso:country":"GB",
    "sg:address":"Unit 1, The Shires Ind Est, Essington Close",
    "sg:city":"Lichfield",
    "sg:classifiers":[
        {
            "category":"Organizations",
            "subcategory":"Non-profit Organization",
            "type":"Services"
        }
    ],
    "sg:phone":"+44 1543 268661",
    "sg:postcode":"WS14 9AZ",
    "sg:province":"Staffordshire",
    "sg:tags":[
        "organisation",
        "voluntary",
        "charity"
    ],
    "wof:name":"Sense Trading",
    "wof:placetype":"venue"
},
  "geometry": {"coordinates":[-1.832508,52.673374],"type":"Point"}
}