{
  "type": "Feature",
  "properties": {
    "addr:full":"11 Old Queen St Westminster Greater London SW1H 9JA",
    "addr:housenumber":"11",
    "addr:postcode":"sw1h 9ja",
    "addr:street":"Old Queen St",
    "iso:country":"GB",
    "sg:address":"11 Old Queen St",
    "sg:city":"Westminster",
    "sg:classifiers":[
        {
            "category":"Organizations",
            "subcategory":"Non-profit Organization",
            "type":"Services"
        }
    ],
    "sg:phone":"+44 20 7233 0066",
    "sg:postcode":"SW1H 9JA",
    "sg:province":"Greater London",
    "sg:tags":[
        "organisation",
        "voluntary",
        "charity"
    ],
    "wof:name":"A.M.R.E.F",
    "wof:placetype":"venue"
},
  "geometry": {"coordinates":[-0.129865,51.500748],"type":"Point"}
}