{
  "type": "Feature",
  "properties": {
    "iso:country":"GB",
    "sg:address":"53 Hardy Street",
    "sg:city":"Maidstone",
    "sg:classifiers":[
        {
            "category":"Home & Garden",
            "subcategory":"Household Appliances",
            "type":"Retail Goods"
        },
        {
            "category":"Food & Beverages",
            "subcategory":"Liquor & Beverages",
            "type":"Retail Goods"
        }
    ],
    "sg:phone":"+44 1622 677619",
    "sg:postcode":"ME14 2SJ",
    "sg:province":"Kent",
    "sg:tags":[
        "wines",
        "supply",
        "equipment",
        "beer",
        "brew",
        "spirit"
    ],
    "wof:name":"Maidstone Wine Making Centre",
    "wof:placetype":"venue"
},
  "geometry": {"coordinates":[0.524929,51.282108],"type":"Point"}
}