{
  "type": "Feature",
  "properties": {
    "iso:country":"GB",
    "sg:address":"Cross-stone",
    "sg:city":"Ellon",
    "sg:classifiers":[
        {
            "category":"Farming",
            "subcategory":"Farm",
            "type":"Manufacturing & Wholesale Goods"
        }
    ],
    "sg:phone":"+44 1358 720339",
    "sg:postcode":"AB41 8ND",
    "sg:province":"Aberdeenshire",
    "sg:tags":[
        "mixed",
        "crop"
    ],
    "wof:name":"James Youngson",
    "wof:placetype":"venue"
},
  "geometry": {"coordinates":[-2.0447189808,57.4113616943],"type":"Point"}
}