{
  "type": "Feature",
  "properties": {
    "iso:country":"GB",
    "sg:address":"193 Gorgie Rd",
    "sg:city":"Edinburgh",
    "sg:classifiers":[
        {
            "category":"Shopping",
            "subcategory":"Used Merchandise",
            "type":"Retail Goods"
        }
    ],
    "sg:postcode":"EH11 1TT",
    "sg:province":"City of Edinburgh",
    "sg:tags":[
        "shop",
        "second-hand"
    ],
    "wof:name":"Mangniotta,Salvatore,",
    "wof:placetype":"venue"
},
  "geometry": {"coordinates":[-3.233543,55.937637],"type":"Point"}
}