{
  "type": "Feature",
  "properties": {
    "iso:country":"GB",
    "sg:address":"32 Crown Rd",
    "sg:city":"Twickenham",
    "sg:classifiers":[
        {
            "category":"Arts & Performance",
            "subcategory":"Art Gallery",
            "type":"Entertainment"
        }
    ],
    "sg:phone":"+44 20 8891 2345",
    "sg:postcode":"TW1 3EE",
    "sg:province":"Greater London",
    "wof:name":"Ailsa Gallery",
    "wof:placetype":"venue"
},
  "geometry": {"coordinates":[-0.319295,51.454079],"type":"Point"}
}