{
  "type": "Feature",
  "properties": {
    "addr:full":"Glebe Farm, Sturton Road, Hatton Market Rasen Lincolnshire LN8 5QQ",
    "addr:postcode":"ln8 5qq",
    "addr:street":"Sturton Road Hatton;Rasen",
    "iso:country":"GB",
    "sg:address":"Glebe Farm, Sturton Road, Hatton",
    "sg:city":"Market Rasen",
    "sg:classifiers":[
        {
            "category":"Farming",
            "subcategory":"Farm",
            "type":"Manufacturing & Wholesale Goods"
        }
    ],
    "sg:phone":"+44 1507 578225",
    "sg:postcode":"LN8 5QQ",
    "sg:province":"Lincolnshire",
    "sg:tags":[
        "mixed",
        "crop"
    ],
    "wof:name":"R S Catlin &Son",
    "wof:placetype":"venue"
},
  "geometry": {"coordinates":[-0.227506,53.28793],"type":"Point"}
}