{
  "type": "Feature",
  "properties": {
    "iso:country":"GB",
    "sg:address":"21 Brinklow Crescent",
    "sg:city":"London",
    "sg:classifiers":[
        {
            "category":"Real Estate",
            "subcategory":"Architect",
            "type":"Services"
        }
    ],
    "sg:phone":"+44 20 8473 8001",
    "sg:postcode":"SE18 3BS",
    "sg:province":"Greater London",
    "wof:name":"Regalway Engineering Ltd.",
    "wof:placetype":"venue"
},
  "geometry": {"coordinates":[0.070533,51.476238],"type":"Point"}
}