{
  "type": "Feature",
  "properties": {
    "addr:full":"7 Eversley Park Chester Cheshire CH2 2AJ",
    "addr:housenumber":"7",
    "addr:postcode":"ch2 2aj",
    "addr:street":"Eversley Park",
    "iso:country":"GB",
    "sg:address":"7 Eversley Park",
    "sg:city":"Chester",
    "sg:classifiers":[
        {
            "category":"Social Services",
            "subcategory":"Retirement Home",
            "type":"Services"
        }
    ],
    "sg:phone":"+44 1244 380343",
    "sg:postcode":"CH2 2AJ",
    "sg:province":"Cheshire",
    "sg:tags":[
        "residential",
        "care"
    ],
    "wof:name":"Clovelly House",
    "wof:placetype":"venue"
},
  "geometry": {"coordinates":[-2.892699,53.204014],"type":"Point"}
}