{
  "type": "Feature",
  "properties": {
    "iso:country":"GB",
    "sg:address":"Keepers Cottage, Wassand",
    "sg:city":"Hull",
    "sg:classifiers":[
        {
            "category":"Professional",
            "type":"Services"
        }
    ],
    "sg:postcode":"HU11 5RJ",
    "sg:province":"East Riding of Yorkshire",
    "sg:tags":[
        "writer"
    ],
    "wof:name":"Alan Wilkinson",
    "wof:placetype":"venue"
},
  "geometry": {"coordinates":[-0.226378,53.896835],"type":"Point"}
}