{
  "type": "Feature",
  "properties": {
    "iso:country":"GB",
    "sg:address":"23 Friery Feld",
    "sg:city":"Dunstable",
    "sg:classifiers":[
        {
            "category":"Social Services",
            "subcategory":"Job Training",
            "type":"Services"
        }
    ],
    "sg:postcode":"LU6 3ZW",
    "sg:province":"Bedfordshire",
    "sg:tags":[
        "translator",
        "interpreter"
    ],
    "wof:name":"A B Languages",
    "wof:placetype":"venue"
},
  "geometry": {"coordinates":[-0.520663,51.885803],"type":"Point"}
}