{
  "type": "Feature",
  "properties": {
    "addr:full":"3 Downend Park Rd Bristol City of Bristol BS16 5SZ",
    "addr:housenumber":"3",
    "addr:postcode":"bs16 5sz",
    "addr:street":"Downend Park Rd",
    "iso:country":"GB",
    "sg:address":"3 Downend Park Rd",
    "sg:city":"Bristol",
    "sg:classifiers":[
        {
            "category":"Building & Trades",
            "subcategory":"Plumbing",
            "type":"Services"
        }
    ],
    "sg:phone":"+44 117 940 0074",
    "sg:postcode":"BS16 5SZ",
    "sg:province":"City of Bristol",
    "sg:tags":[
        "heating"
    ],
    "wof:name":"D G Lewis",
    "wof:placetype":"venue"
},
  "geometry": {"coordinates":[-2.52377,51.481976],"type":"Point"}
}