{
  "type": "Feature",
  "properties": {
    "iso:country":"GB",
    "sg:address":"5 Woodfield, Kingsley",
    "sg:city":"Bordon",
    "sg:classifiers":[
        {
            "category":"Professional",
            "subcategory":"Detective & Security Services",
            "type":"Services"
        }
    ],
    "sg:phone":"+44 1420 475480",
    "sg:postcode":"GU35 9NB",
    "sg:province":"Hampshire",
    "sg:tags":[
        "locksmith"
    ],
    "wof:name":"Autokeys",
    "wof:placetype":"venue"
},
  "geometry": {"coordinates":[-0.87315,51.112682],"type":"Point"}
}