{
  "type": "Feature",
  "properties": {
    "iso:country":"GB",
    "sg:address":"118 Wandsworth Bridge Road",
    "sg:city":"London",
    "sg:classifiers":[
        {
            "category":"Personal",
            "subcategory":"Beauty Salon",
            "type":"Services"
        }
    ],
    "sg:phone":"+44 20 7731 6543",
    "sg:postcode":"SW6 2TF",
    "sg:province":"Greater London",
    "sg:tags":[
        "unisex",
        "hairdresser"
    ],
    "wof:name":"Francois Michel",
    "wof:placetype":"venue"
},
  "geometry": {"coordinates":[-0.191914,51.473049],"type":"Point"}
}