{
  "type": "Feature",
  "properties": {
    "addr:full":"201 Well Street London Greater London E9 6QU",
    "addr:housenumber":"201",
    "addr:postcode":"e9 6qu",
    "addr:street":"Well Street",
    "iso:country":"GB",
    "sg:address":"201 Well Street",
    "sg:city":"London",
    "sg:classifiers":[
        {
            "category":"Professional",
            "subcategory":"Computer Services",
            "type":"Services"
        }
    ],
    "sg:phone":"+44 20 8985 1242",
    "sg:postcode":"E9 6QU",
    "sg:province":"Greater London",
    "sg:tags":[
        "aided",
        "design"
    ],
    "wof:name":"Showcad",
    "wof:placetype":"venue"
},
  "geometry": {"coordinates":[-0.0475529991,51.5435562134],"type":"Point"}
}