{
  "type": "Feature",
  "properties": {
    "iso:country":"GB",
    "sg:address":"16 Biggin Lane, Ramsey",
    "sg:city":"Huntingdon",
    "sg:classifiers":[
        {
            "category":"Home & Garden",
            "subcategory":"Garden Supply",
            "type":"Retail Goods"
        },
        {
            "category":"Farming",
            "subcategory":"Crops",
            "type":"Manufacturing & Wholesale Goods"
        },
        {
            "category":"Food & Beverages",
            "subcategory":"Groceries & Convenience Stores",
            "type":"Retail Goods"
        }
    ],
    "sg:postcode":"PE26 1NB",
    "sg:province":"Cambridgeshire",
    "sg:tags":[
        "merchant",
        "bulb",
        "arable",
        "grower",
        "potato"
    ],
    "wof:name":"A H Wagstaffe & Sons",
    "wof:placetype":"venue"
},
  "geometry": {"coordinates":[-0.115018,52.444225],"type":"Point"}
}