{
  "type": "Feature",
  "properties": {
    "addr:full":"The Old Mill, Therapy Centre, North Rd Ambleside Cumbria LA22 9DT",
    "addr:postcode":"la22 9dt",
    "addr:street":"North Rd",
    "iso:country":"GB",
    "sg:address":"The Old Mill, Therapy Centre, North Rd",
    "sg:city":"Ambleside",
    "sg:classifiers":[
        {
            "category":"Health Services",
            "subcategory":"Health Practitioner",
            "type":"Services"
        }
    ],
    "sg:phone":"+44 15394 31880",
    "sg:postcode":"LA22 9DT",
    "sg:province":"Cumbria",
    "sg:tags":[
        "homoeopathic"
    ],
    "wof:name":"Sue Williams MLC Hom",
    "wof:placetype":"venue"
},
  "geometry": {"coordinates":[-2.9630889893,54.4326057434],"type":"Point"}
}