{
  "type": "Feature",
  "properties": {
    "addr:full":"13 Church Lane Crawley Surrey RH10 3PT",
    "addr:housenumber":"13",
    "addr:postcode":"rh10 3pt",
    "addr:street":"Church Lane",
    "iso:country":"GB",
    "sg:address":"13 Church Lane",
    "sg:city":"Crawley",
    "sg:classifiers":[
        {
            "category":"Professional",
            "subcategory":"Management & Consulting",
            "type":"Services"
        }
    ],
    "sg:phone":"+44 1342 715256",
    "sg:postcode":"RH10 3PT",
    "sg:province":"Surrey",
    "sg:tags":[
        "consultant",
        "business"
    ],
    "wof:name":"Learning Edge",
    "wof:placetype":"venue"
},
  "geometry": {"coordinates":[-0.123474,51.134979],"type":"Point"}
}