{
  "type": "Feature",
  "properties": {
    "iso:country":"GB",
    "sg:address":"52 Bulford Road, Durrington",
    "sg:city":"Salisbury",
    "sg:classifiers":[
        {
            "category":"Building & Trades",
            "subcategory":"Construction",
            "type":"Services"
        }
    ],
    "sg:phone":"+44 1980 653771",
    "sg:postcode":"SP4 8DJ",
    "sg:province":"Hampshire",
    "sg:tags":[
        "glazier"
    ],
    "wof:name":"J P Todd Glass & Glazing",
    "wof:placetype":"venue"
},
  "geometry": {"coordinates":[-1.770531,51.196754],"type":"Point"}
}