{
  "type": "Feature",
  "properties": {
    "addr:full":"Piccadilly Tamworth Staffordshire B78 2EP",
    "addr:postcode":"b78 2ep",
    "addr:street":"Staffordshire",
    "iso:country":"GB",
    "sg:address":"Piccadilly",
    "sg:city":"Tamworth",
    "sg:classifiers":[
        {
            "category":"Shopping",
            "subcategory":"Department Store",
            "type":"Retail Goods"
        }
    ],
    "sg:postcode":"B78 2EP",
    "sg:province":"Staffordshire",
    "wof:name":"Piccadilly Post Office",
    "wof:placetype":"venue"
},
  "geometry": {"coordinates":[-1.666469,52.579456],"type":"Point"}
}