{
  "type": "Feature",
  "properties": {
    "addr:full":"4 St. Gregory Clo Darlington Durham DL2 3LG",
    "addr:housenumber":"4",
    "addr:postcode":"dl2 3lg",
    "addr:street":"St.;Darlington",
    "iso:country":"GB",
    "sg:address":"4 St. Gregory Clo",
    "sg:city":"Darlington",
    "sg:classifiers":[
        {
            "category":"Freight",
            "type":"Transportation"
        }
    ],
    "sg:phone":"+44 1833 660509",
    "sg:postcode":"DL2 3LG",
    "sg:province":"Durham",
    "sg:tags":[
        "haulage",
        "road"
    ],
    "wof:name":"C Butler",
    "wof:placetype":"venue"
},
  "geometry": {"coordinates":[-1.812845,54.578564],"type":"Point"}
}