{
  "type": "Feature",
  "properties": {
    "iso:country":"GB",
    "sg:address":"39 Castle Street",
    "sg:city":"Kirkcudbright",
    "sg:classifiers":[
        {
            "category":"Professional",
            "subcategory":"Engineering",
            "type":"Services"
        }
    ],
    "sg:postcode":"DG6 4JD",
    "sg:province":"Dumfries and Galloway",
    "sg:tags":[
        "contractor",
        "electrical",
        "engineer"
    ],
    "wof:name":"Thompson & Dunbar Electrical Contractors",
    "wof:placetype":"venue"
},
  "geometry": {"coordinates":[-4.053171,54.835621],"type":"Point"}
}