{
  "type": "Feature",
  "properties": {
    "iso:country":"GB",
    "sg:address":"68 Commercial Road",
    "sg:city":"Bournemouth",
    "sg:classifiers":[
        {
            "category":"Shopping",
            "subcategory":"Music",
            "type":"Retail Goods"
        }
    ],
    "sg:phone":"+44 1202 551177",
    "sg:postcode":"BH2 5RT",
    "sg:province":"Dorset",
    "sg:tags":[
        "record",
        "tape",
        "cd"
    ],
    "wof:name":"Our Price Entertainment Ltd.",
    "wof:placetype":"venue"
},
  "geometry": {"coordinates":[-1.882678,50.72028],"type":"Point"}
}