{
  "type": "Feature",
  "properties": {
    "addr:full":"Pound Street Carshalton Surrey SM5 3PS",
    "addr:postcode":"sm5 3ps",
    "addr:street":"Pound Street",
    "iso:country":"GB",
    "sg:address":"Pound Street",
    "sg:city":"Carshalton",
    "sg:classifiers":[
        {
            "category":"Education",
            "subcategory":"Special Training",
            "type":"Public Place"
        },
        {
            "category":"Education",
            "subcategory":"University",
            "type":"Public Place"
        },
        {
            "category":"Education",
            "subcategory":"School",
            "type":"Public Place"
        }
    ],
    "sg:phone":"+44 20 8642 2025",
    "sg:postcode":"SM5 3PS",
    "sg:province":"Surrey",
    "sg:tags":[
        "local",
        "college",
        "authority"
    ],
    "wof:name":"ST PHILOMENA'S CATHOLIC HIGH SCHOOL FOR GIRLS",
    "wof:placetype":"venue"
},
  "geometry": {"coordinates":[-0.1653030068,51.364780426],"type":"Point"}
}