{
  "type": "Feature",
  "properties": {
    "iso:country":"GB",
    "sg:address":"Kings Dock Mill, Tabley Street",
    "sg:city":"Liverpool",
    "sg:classifiers":[
        {
            "category":"Shopping",
            "subcategory":"News",
            "type":"Retail Goods"
        }
    ],
    "sg:phone":"+44 151 709 6158",
    "sg:postcode":"L1 8JH",
    "sg:province":"Merseyside",
    "sg:tags":[
        "newsagent"
    ],
    "wof:name":"Doreen's News & Cafe",
    "wof:placetype":"venue"
},
  "geometry": {"coordinates":[-2.98424,53.397568],"type":"Point"}
}