{
  "type": "Feature",
  "properties": {
    "addr:full":"22 Chapel St Bridlington East Riding of Yorkshire YO15 2DW",
    "addr:housenumber":"22",
    "addr:postcode":"yo15 2dw",
    "addr:street":"Chapel St",
    "iso:country":"GB",
    "sg:address":"22 Chapel St",
    "sg:city":"Bridlington",
    "sg:classifiers":[
        {
            "category":"Home & Garden",
            "subcategory":"Kitchen Supply",
            "type":"Retail Goods"
        }
    ],
    "sg:phone":"+44 1262 679826",
    "sg:postcode":"YO15 2DW",
    "sg:province":"East Riding of Yorkshire",
    "sg:tags":[
        "ware"
    ],
    "wof:name":"Original Cookstore,The",
    "wof:placetype":"venue"
},
  "geometry": {"coordinates":[-0.187399,54.08749],"type":"Point"}
}