{
  "type": "Feature",
  "properties": {
    "addr:full":"9 Hadfield Street, Cornbrook Manchester Cheshire M16 9FE",
    "addr:housenumber":"9",
    "addr:postcode":"m16 9fe",
    "addr:street":"Hadfield Street",
    "iso:country":"GB",
    "sg:address":"9 Hadfield Street, Cornbrook",
    "sg:city":"Manchester",
    "sg:classifiers":[
        {
            "category":"Professional",
            "type":"Services"
        }
    ],
    "sg:phone":"+44 161 872 2573",
    "sg:postcode":"M16 9FE",
    "sg:province":"Cheshire",
    "sg:tags":[
        "exhibition"
    ],
    "wof:name":"Skylight Ltd.",
    "wof:placetype":"venue"
},
  "geometry": {"coordinates":[-2.268249,53.46666],"type":"Point"}
}