{
  "type": "Feature",
  "properties": {
    "iso:country":"GB",
    "sg:address":"61 Sheffield Road, Penistone",
    "sg:city":"Sheffield",
    "sg:classifiers":[
        {
            "category":"Fast Food",
            "type":"Food & Drink"
        }
    ],
    "sg:postcode":"S36 6HH",
    "sg:province":"South Yorkshire",
    "sg:tags":[
        "away",
        "take"
    ],
    "wof:name":"Canton House",
    "wof:placetype":"venue"
},
  "geometry": {"coordinates":[-1.6170940399,53.5247917175],"type":"Point"}
}