{
  "type": "Feature",
  "properties": {
    "addr:full":"242 Ladypool Road Birmingham West Midlands B12 8JT",
    "addr:housenumber":"242",
    "addr:postcode":"b12 8jt",
    "addr:street":"Ladypool Road",
    "iso:country":"GB",
    "sg:address":"242 Ladypool Road",
    "sg:city":"Birmingham",
    "sg:classifiers":[
        {
            "category":"Shopping",
            "subcategory":"Books",
            "type":"Retail Goods"
        }
    ],
    "sg:phone":"+44 121 693 6053",
    "sg:postcode":"B12 8JT",
    "sg:province":"West Midlands",
    "sg:tags":[
        "bookseller"
    ],
    "wof:name":"Anwar Communication",
    "wof:placetype":"venue"
},
  "geometry": {"coordinates":[-1.876472,52.455906],"type":"Point"}
}