{
  "type": "Feature",
  "properties": {
    "iso:country":"GB",
    "sg:address":"141a Wincheap",
    "sg:city":"Canterbury",
    "sg:classifiers":[
        {
            "category":"Building & Trades",
            "subcategory":"Construction",
            "type":"Services"
        }
    ],
    "sg:phone":"+44 1227 457086",
    "sg:postcode":"CT1 3SE",
    "sg:province":"Kent",
    "sg:tags":[
        "decorator",
        "painter"
    ],
    "wof:name":"Galvin,I T,",
    "wof:placetype":"venue"
},
  "geometry": {"coordinates":[1.067975,51.271671],"type":"Point"}
}