{
  "type": "Feature",
  "properties": {
    "iso:country":"GB",
    "sg:address":"Top Rd, Worlaby",
    "sg:city":"Brigg",
    "sg:classifiers":[
        {
            "category":"Bars & Pubs",
            "type":"Food & Drink"
        }
    ],
    "sg:postcode":"DN20 0NN",
    "sg:province":"Lincolnshire",
    "sg:tags":[
        "pubs",
        "inn"
    ],
    "wof:name":"Tyas,J,",
    "wof:placetype":"venue"
},
  "geometry": {"coordinates":[-0.4683940113,53.6131668091],"type":"Point"}
}