{
  "type": "Feature",
  "properties": {
    "addr:full":"647 Roundhay Road Leeds West Yorkshire LS8 4BA",
    "addr:housenumber":"647",
    "addr:postcode":"ls8 4ba",
    "addr:street":"Roundhay Road",
    "iso:country":"GB",
    "sg:address":"647 Roundhay Road",
    "sg:city":"Leeds",
    "sg:classifiers":[
        {
            "category":"Professional",
            "subcategory":"Management & Consulting",
            "type":"Services"
        },
        {
            "category":"Banks & Credit Unions",
            "subcategory":"Investment Brokerage",
            "type":"Services"
        }
    ],
    "sg:phone":"+44 113 235 0632",
    "sg:postcode":"LS8 4BA",
    "sg:province":"West Yorkshire",
    "sg:tags":[
        "holding",
        "activity"
    ],
    "wof:name":"Caldwell Investments Plc",
    "wof:placetype":"venue"
},
  "geometry": {"coordinates":[-1.506619,53.826359],"type":"Point"}
}