{
  "type": "Feature",
  "properties": {
    "addr:full":"Middridge Mill Farm Shildon Durham DL4 2QE",
    "addr:postcode":"dl4 2qe",
    "addr:street":"Middridge",
    "iso:country":"GB",
    "sg:address":"Middridge Mill Farm",
    "sg:city":"Shildon",
    "sg:classifiers":[
        {
            "category":"Farming",
            "subcategory":"Farm",
            "type":"Manufacturing & Wholesale Goods"
        }
    ],
    "sg:phone":"+44 1388 772095",
    "sg:postcode":"DL4 2QE",
    "sg:province":"Durham",
    "sg:tags":[
        "mixed",
        "crop"
    ],
    "wof:name":"Roy Finlay",
    "wof:placetype":"venue"
},
  "geometry": {"coordinates":[-1.635561,54.634129],"type":"Point"}
}