{
  "type": "Feature",
  "properties": {
    "addr:full":"Vann La Godalming Surrey GU8 4EF",
    "addr:postcode":"gu8 4ef",
    "addr:street":"Vann La Godalming",
    "iso:country":"GB",
    "sg:address":"Vann La",
    "sg:city":"Godalming",
    "sg:classifiers":[
        {
            "category":"Real Estate",
            "subcategory":"Architect",
            "type":"Services"
        }
    ],
    "sg:phone":"+44 1428 683413",
    "sg:postcode":"GU8 4EF",
    "sg:province":"Surrey",
    "wof:name":"Caroe & Partners",
    "wof:placetype":"venue"
},
  "geometry": {"coordinates":[-0.6072999835,51.1162185669],"type":"Point"}
}