{
  "type": "Feature",
  "properties": {
    "addr:full":"1 Warrior Sq St Leonards On Sea East Sussex TN37 6BA",
    "addr:housenumber":"1",
    "addr:postcode":"tn37 6ba",
    "addr:street":"Warrior Sq",
    "iso:country":"GB",
    "sg:address":"1 Warrior Sq",
    "sg:city":"St Leonards On Sea",
    "sg:classifiers":[
        {
            "category":"Health Services",
            "subcategory":"Doctor",
            "type":"Services"
        }
    ],
    "sg:phone":"+44 1424 430123",
    "sg:postcode":"TN37 6BA",
    "sg:province":"East Sussex",
    "sg:tags":[
        "practitioners"
    ],
    "wof:name":"Herbert, P",
    "wof:placetype":"venue"
},
  "geometry": {"coordinates":[0.56239,50.851959],"type":"Point"}
}