{
  "type": "Feature",
  "properties": {
    "addr:full":"Waterworks Rd Worcester Worcestershire WR1 3EZ",
    "addr:postcode":"wr1 3ez",
    "addr:street":"Waterworks Rd",
    "iso:country":"GB",
    "sg:address":"Waterworks Rd",
    "sg:city":"Worcester",
    "sg:classifiers":[
        {
            "category":"Real Estate",
            "subcategory":"Surveying",
            "type":"Services"
        }
    ],
    "sg:phone":"+44 1905 21073",
    "sg:postcode":"WR1 3EZ",
    "sg:province":"Worcestershire",
    "sg:tags":[
        "surveyor",
        "land"
    ],
    "wof:name":"Survey Centre",
    "wof:placetype":"venue"
},
  "geometry": {"coordinates":[-2.231396,52.206745],"type":"Point"}
}