{
  "type": "Feature",
  "properties": {
    "iso:country":"GB",
    "sg:address":"Bowland St",
    "sg:city":"Bradford",
    "sg:classifiers":[
        {
            "category":"Place Of Worship",
            "type":"Public Place"
        }
    ],
    "sg:phone":"+44 1274 728925",
    "sg:postcode":"BD1 3BW",
    "sg:province":"West Yorkshire",
    "wof:name":"Bradford Synagogue",
    "wof:placetype":"venue"
},
  "geometry": {"coordinates":[-1.761887,53.801342],"type":"Point"}
}