{
  "type": "Feature",
  "properties": {
    "addr:full":"Rm Company Services Ltd, 2nd Floor 80 Great Eastern Street London Greater London EC2A 3JL",
    "addr:housenumber":"2nd floor 80",
    "addr:postcode":"ec2a 3jl",
    "addr:street":"Great Eastern Street",
    "iso:country":"GB",
    "sg:address":"Rm Company Services Ltd, 2nd Floor 80 Great Eastern Street",
    "sg:city":"London",
    "sg:classifiers":[
        {
            "category":"Travel",
            "subcategory":"Travel Agent",
            "type":"Entertainment"
        }
    ],
    "sg:postcode":"EC2A 3JL",
    "sg:province":"Greater London",
    "wof:name":"Globe Granite Ltd (The)",
    "wof:placetype":"venue"
},
  "geometry": {"coordinates":[-0.0826200023,51.5257110596],"type":"Point"}
}