{
  "type": "Feature",
  "properties": {
    "addr:full":"24 & 6 Camden Passage Islington London Greater London N1 8ED",
    "addr:housenumber":"24 & 6",
    "addr:postcode":"n1 8ed",
    "addr:street":"Camden Passage",
    "iso:country":"GB",
    "sg:address":"24 & 6 Camden Passage Islington",
    "sg:city":"London",
    "sg:classifiers":[
        {
            "category":"Shopping",
            "subcategory":"Antiques",
            "type":"Retail Goods"
        }
    ],
    "sg:phone":"+44 20 7226 8558",
    "sg:postcode":"N1 8ED",
    "sg:province":"Greater London",
    "wof:name":"Kevin Page Oriental Art",
    "wof:placetype":"venue"
},
  "geometry": {"coordinates":[-0.1034160033,51.5350990295],"type":"Point"}
}