{
  "type": "Feature",
  "properties": {
    "addr:full":"Beckside View, Coperove Harrogate North Yorkshire HG3 3TA",
    "addr:postcode":"hg3 3ta",
    "addr:street":"Beckside;Coperove",
    "iso:country":"GB",
    "sg:address":"Beckside View, Coperove",
    "sg:city":"Harrogate",
    "sg:classifiers":[
        {
            "category":"Farming",
            "subcategory":"Dairy Farm",
            "type":"Manufacturing & Wholesale Goods"
        }
    ],
    "sg:phone":"+44 1423 340446",
    "sg:postcode":"HG3 3TA",
    "sg:province":"North Yorkshire",
    "wof:name":"M Wills",
    "wof:placetype":"venue"
},
  "geometry": {"coordinates":[-1.46501,54.062279],"type":"Point"}
}