{
  "type": "Feature",
  "properties": {
    "addr:full":"Devon Way Chessington Surrey KT9 2RJ",
    "addr:postcode":"kt9 2rj",
    "addr:street":"Devon Way",
    "iso:country":"GB",
    "sg:address":"Devon Way",
    "sg:city":"Chessington",
    "sg:classifiers":[
        {
            "category":"Government",
            "subcategory":"City Hall",
            "type":"Public Place"
        }
    ],
    "sg:phone":"+44 20 8397 2216",
    "sg:postcode":"KT9 2RJ",
    "sg:province":"Surrey",
    "wof:name":"Hook Youth & Activity Centre",
    "wof:placetype":"venue"
},
  "geometry": {"coordinates":[-0.3138439953,51.3678817749],"type":"Point"}
}