{
  "type": "Feature",
  "properties": {
    "addr:full":"94 Brown St Chorley Lancashire PR6 0BA",
    "addr:housenumber":"94",
    "addr:postcode":"pr6 0ba",
    "addr:street":"Brown St",
    "iso:country":"GB",
    "sg:address":"94 Brown St",
    "sg:city":"Chorley",
    "sg:classifiers":[
        {
            "category":"Building & Trades",
            "subcategory":"Construction",
            "type":"Services"
        }
    ],
    "sg:phone":"+44 1257 263003",
    "sg:postcode":"PR6 0BA",
    "sg:province":"Lancashire",
    "sg:tags":[
        "decorator",
        "painter"
    ],
    "wof:name":"Rimmers Decorating",
    "wof:placetype":"venue"
},
  "geometry": {"coordinates":[-2.6214139462,53.6544418335],"type":"Point"}
}