{
  "type": "Feature",
  "properties": {
    "iso:country":"GB",
    "sg:address":"Godson House Sheltered Housing, Lawn Street",
    "sg:city":"Winchester",
    "sg:classifiers":[
        {
            "category":"Government",
            "subcategory":"Office",
            "type":"Public Place"
        }
    ],
    "sg:phone":"+44 1962 864393",
    "sg:postcode":"SO23 8ED",
    "sg:province":"Hampshire",
    "sg:tags":[
        "local"
    ],
    "wof:name":"Winchester City Council",
    "wof:placetype":"venue"
},
  "geometry": {"coordinates":[-1.316809,51.063068],"type":"Point"}
}