{
  "type": "Feature",
  "properties": {
    "iso:country":"GB",
    "sg:address":"White Cliff Surgery, White Cliff Mill St",
    "sg:city":"Blandford Forum",
    "sg:classifiers":[
        {
            "category":"Health Services",
            "subcategory":"Doctor",
            "type":"Services"
        }
    ],
    "sg:phone":"+44 1258 452501",
    "sg:postcode":"DT11 7BH",
    "sg:province":"Dorset",
    "sg:tags":[
        "practitioners"
    ],
    "wof:name":"Kreeger, P",
    "wof:placetype":"venue"
},
  "geometry": {"coordinates":[-2.158819,50.862644],"type":"Point"}
}