{
  "type": "Feature",
  "properties": {
    "addr:full":"6 Culver Court, Malting Lane Much Hadham Hertfordshire SG10 6AN",
    "addr:housenumber":"6",
    "addr:postcode":"sg10 6an",
    "addr:street":"Culver Court Malting Lane",
    "iso:country":"GB",
    "sg:address":"6 Culver Court, Malting Lane",
    "sg:city":"Much Hadham",
    "sg:classifiers":[
        {
            "category":"Building & Trades",
            "subcategory":"Landscaping Services",
            "type":"Services"
        }
    ],
    "sg:phone":"+44 1279 842288",
    "sg:postcode":"SG10 6AN",
    "sg:province":"Hertfordshire",
    "sg:tags":[
        "landscape",
        "contractor"
    ],
    "wof:name":"M C I Timply Ltd.",
    "wof:placetype":"venue"
},
  "geometry": {"coordinates":[0.070275,51.848179],"type":"Point"}
}