{
  "type": "Feature",
  "properties": {
    "iso:country":"GB",
    "sg:address":"The Orchards, Overton Rd",
    "sg:city":"Stoke On Trent",
    "sg:classifiers":[
        {
            "category":"Retail",
            "subcategory":"Driving School",
            "type":"Services"
        }
    ],
    "sg:phone":"+44 1782 516392",
    "sg:postcode":"ST8 7ST",
    "sg:province":"Staffordshire",
    "wof:name":"Biddulph & District School Of Motoring",
    "wof:placetype":"venue"
},
  "geometry": {"coordinates":[-2.15425,53.143471],"type":"Point"}
}