{
  "type": "Feature",
  "properties": {
    "addr:full":"Suite 2a Northbrook Court Park Street Newbury Berkshire RG14 1EA",
    "addr:housenumber":"suite 2a",
    "addr:postcode":"rg14 1ea",
    "addr:street":"Northbrook Court Park Street",
    "iso:country":"GB",
    "sg:address":"Suite 2a Northbrook Court Park Street",
    "sg:city":"Newbury",
    "sg:classifiers":[
        {
            "category":"Real Estate",
            "subcategory":"Developer",
            "type":"Services"
        }
    ],
    "sg:phone":"+44 1635 47700",
    "sg:postcode":"RG14 1EA",
    "sg:province":"Berkshire",
    "sg:tags":[
        "property"
    ],
    "wof:name":"Trencherwood Commercial Ltd.",
    "wof:placetype":"venue"
},
  "geometry": {"coordinates":[-1.323715,51.404922],"type":"Point"}
}