{
  "type": "Feature",
  "properties": {
    "addr:full":"Crown House, The Street, Bunwell Norwich Norfolk NR16 1NA",
    "addr:postcode":"nr16 1na",
    "addr:street":"The Street;Norwich",
    "iso:country":"GB",
    "sg:address":"Crown House, The Street, Bunwell",
    "sg:city":"Norwich",
    "sg:classifiers":[
        {
            "category":"Home & Garden",
            "subcategory":"Home Furnishings",
            "type":"Retail Goods"
        }
    ],
    "sg:phone":"+44 1953 788303",
    "sg:postcode":"NR16 1NA",
    "sg:province":"Norfolk",
    "sg:tags":[
        "homefurnishings"
    ],
    "wof:name":"Oakcraft",
    "wof:placetype":"venue"
},
  "geometry": {"coordinates":[1.15453,52.53447],"type":"Point"}
}