{
  "type": "Feature",
  "properties": {
    "iso:country":"GB",
    "sg:address":"54 Church Street",
    "sg:city":"Doncaster",
    "sg:classifiers":[
        {
            "category":"Food & Beverages",
            "subcategory":"Meat & Fish",
            "type":"Retail Goods"
        }
    ],
    "sg:phone":"+44 1709 862471",
    "sg:postcode":"DN12 3JJ",
    "sg:province":"South Yorkshire",
    "sg:tags":[
        "chip"
    ],
    "wof:name":"Castle Fisheries",
    "wof:placetype":"venue"
},
  "geometry": {"coordinates":[-1.2310960293,53.4824295044],"type":"Point"}
}