{
  "type": "Feature",
  "properties": {
    "addr:full":"Boswells North Tawton Devon EX20 2BY",
    "addr:housenumber":"tawton",
    "addr:postcode":"ex20 2by",
    "addr:street":"Devon",
    "iso:country":"GB",
    "sg:address":"Boswells",
    "sg:city":"North Tawton",
    "sg:classifiers":[
        {
            "category":"Farming",
            "subcategory":"Farm",
            "type":"Manufacturing & Wholesale Goods"
        }
    ],
    "sg:postcode":"EX20 2BY",
    "sg:province":"Devon",
    "sg:tags":[
        "mixed",
        "crop"
    ],
    "wof:name":"Timothy A Folland",
    "wof:placetype":"venue"
},
  "geometry": {"coordinates":[-3.8970689774,50.7989768982],"type":"Point"}
}