{
  "type": "Feature",
  "properties": {
    "addr:full":"16 Kingstonia Gardens Ripon North Yorkshire HG4 1TE",
    "addr:housenumber":"16",
    "addr:postcode":"hg4 1te",
    "addr:street":"Kingstonia Gardens",
    "iso:country":"GB",
    "sg:address":"16 Kingstonia Gardens",
    "sg:city":"Ripon",
    "sg:classifiers":[
        {
            "category":"Professional",
            "subcategory":"Engineering",
            "type":"Services"
        }
    ],
    "sg:postcode":"HG4 1TE",
    "sg:province":"North Yorkshire",
    "sg:tags":[
        "contractor",
        "electrical",
        "engineer"
    ],
    "wof:name":"M & R Tinsley Electrical Contractors",
    "wof:placetype":"venue"
},
  "geometry": {"coordinates":[-1.524684,54.1255],"type":"Point"}
}