{
  "type": "Feature",
  "properties": {
    "addr:full":"289 Church Rd Bristol City of Bristol BS5 9HT",
    "addr:housenumber":"289",
    "addr:postcode":"bs5 9ht",
    "addr:street":"Church Rd",
    "iso:country":"GB",
    "sg:address":"289 Church Rd",
    "sg:city":"Bristol",
    "sg:classifiers":[
        {
            "category":"Professional",
            "subcategory":"Lawyer & Legal Services",
            "type":"Services"
        }
    ],
    "sg:phone":"+44 117 954 1133",
    "sg:postcode":"BS5 9HT",
    "sg:province":"City of Bristol",
    "sg:tags":[
        "solicitor"
    ],
    "wof:name":"David Gist & Co",
    "wof:placetype":"venue"
},
  "geometry": {"coordinates":[-2.5511090755,51.4597396851],"type":"Point"}
}