{
  "type": "Feature",
  "properties": {
    "addr:full":"West Way, Wick Littlehampton West Sussex BN17 7NB",
    "addr:postcode":"bn17 7nb",
    "addr:street":"West Way",
    "iso:country":"GB",
    "sg:address":"West Way, Wick",
    "sg:city":"Littlehampton",
    "sg:classifiers":[
        {
            "category":"Social Services",
            "subcategory":"Retirement Home",
            "type":"Services"
        }
    ],
    "sg:phone":"+44 1903 715348",
    "sg:postcode":"BN17 7NB",
    "sg:province":"West Sussex",
    "sg:tags":[
        "rest"
    ],
    "sg:website":"http://www.shawhealth.co.uk",
    "wof:name":"Hampton House",
    "wof:placetype":"venue"
},
  "geometry": {"coordinates":[-0.5481060147,50.8178215027],"type":"Point"}
}