{
  "type": "Feature",
  "properties": {
    "addr:full":"1 Noke Cottage, Pembridge Leominster Herefordshire HR6 9HW",
    "addr:housenumber":"1",
    "addr:postcode":"hr6 9hw",
    "addr:street":"Pembridge",
    "iso:country":"GB",
    "sg:address":"1 Noke Cottage, Pembridge",
    "sg:city":"Leominster",
    "sg:classifiers":[
        {
            "category":"Communications",
            "subcategory":"Film & Video Production",
            "type":"Services"
        }
    ],
    "sg:postcode":"HR6 9HW",
    "sg:province":"Herefordshire",
    "sg:tags":[
        "illustrator",
        "artist"
    ],
    "wof:name":"Cider Graphics & Illustration Ltd.",
    "wof:placetype":"venue"
},
  "geometry": {"coordinates":[-2.894509,52.217983],"type":"Point"}
}