{
  "type": "Feature",
  "properties": {
    "iso:country":"GB",
    "sg:address":"91 Shevington Lane, Shevington",
    "sg:city":"Wigan",
    "sg:classifiers":[
        {
            "category":"Professional",
            "subcategory":"Computer Services",
            "type":"Services"
        }
    ],
    "sg:phone":"+44 1257 401900",
    "sg:postcode":"WN6 8AE",
    "sg:province":"Lancashire",
    "sg:tags":[
        "system",
        "software"
    ],
    "wof:name":"System 26",
    "wof:placetype":"venue"
},
  "geometry": {"coordinates":[-2.686551,53.576653],"type":"Point"}
}