{
  "type": "Feature",
  "properties": {
    "iso:country":"GB",
    "sg:address":"172 Mill Road",
    "sg:city":"Cambridge",
    "sg:classifiers":[
        {
            "category":"Shopping",
            "subcategory":"Thrift Store",
            "type":"Retail Goods"
        }
    ],
    "sg:phone":"+44 1223 566997",
    "sg:postcode":"CB1 3LP",
    "sg:province":"Cambridgeshire",
    "sg:tags":[
        "shop",
        "charity"
    ],
    "sg:website":"http://www.catchat.org.uk",
    "wof:name":"Cats Protection League",
    "wof:placetype":"venue"
},
  "geometry": {"coordinates":[0.142866,52.198048],"type":"Point"}
}