{
  "type": "Feature",
  "properties": {
    "addr:full":"Dove House, Arcadia Avenue, Finchley London Greater London N3 2JU",
    "addr:postcode":"n3 2ju",
    "addr:street":"Arcadia Avenue",
    "iso:country":"GB",
    "sg:address":"Dove House, Arcadia Avenue, Finchley",
    "sg:city":"London",
    "sg:classifiers":[
        {
            "category":"Education",
            "subcategory":"Special Training",
            "type":"Public Place"
        }
    ],
    "sg:phone":"+44 20 8371 7000",
    "sg:postcode":"N3 2JU",
    "sg:province":"Greater London",
    "sg:tags":[
        "product",
        "centre"
    ],
    "wof:name":"JSB Training and Consulting",
    "wof:placetype":"venue"
},
  "geometry": {"coordinates":[-0.1939599961,51.5993118286],"type":"Point"}
}