{
  "type": "Feature",
  "properties": {
    "addr:full":"9 High Chelmer Chelmsford Essex CM1 1XL",
    "addr:housenumber":"9",
    "addr:postcode":"cm1 1xl",
    "addr:street":"High Chelmer",
    "iso:country":"GB",
    "sg:address":"9 High Chelmer",
    "sg:city":"Chelmsford",
    "sg:classifiers":[
        {
            "category":"Shopping",
            "subcategory":"Clothing, Apparel, & Fashions",
            "type":"Retail Goods"
        }
    ],
    "sg:phone":"+44 1245 350755",
    "sg:postcode":"CM1 1XL",
    "sg:province":"Essex",
    "sg:tags":[
        "shop"
    ],
    "wof:name":"C & A",
    "wof:placetype":"venue"
},
  "geometry": {"coordinates":[0.469733,51.734058],"type":"Point"}
}