{
  "type": "Feature",
  "properties": {
    "addr:full":"Imperial Ho, 64 Willoughby La Tottenham Greater London N17 0SP",
    "addr:housenumber":"64",
    "addr:postcode":"n17 0sp",
    "addr:street":"Willoughby La Tottenham",
    "iso:country":"GB",
    "sg:address":"Imperial Ho, 64 Willoughby La",
    "sg:city":"Tottenham",
    "sg:classifiers":[
        {
            "category":"Professional",
            "subcategory":"Detective & Security Services",
            "type":"Services"
        }
    ],
    "sg:phone":"+44 20 8808 0178",
    "sg:postcode":"N17 0SP",
    "sg:province":"Greater London",
    "wof:name":"Securzone Security Ltd",
    "wof:placetype":"venue"
},
  "geometry": {"coordinates":[-0.0543899983,51.6043815613],"type":"Point"}
}