{
  "type": "Feature",
  "properties": {
    "addr:full":"19 Manor Park Crescent Edgware Greater London HA8 7NH",
    "addr:housenumber":"19",
    "addr:postcode":"ha8 7nh",
    "addr:street":"Manor Park Crescent",
    "iso:country":"GB",
    "sg:address":"19 Manor Park Crescent",
    "sg:city":"Edgware",
    "sg:classifiers":[
        {
            "category":"Education",
            "subcategory":"Music School",
            "type":"Public Place"
        }
    ],
    "sg:phone":"+44 20 8952 3417",
    "sg:postcode":"HA8 7NH",
    "sg:province":"Greater London",
    "sg:tags":[
        "teacher"
    ],
    "wof:name":"Jonathan Land",
    "wof:placetype":"venue"
},
  "geometry": {"coordinates":[-0.279326,51.612484],"type":"Point"}
}