{
  "type": "Feature",
  "properties": {
    "addr:full":"Breydon Road, Cobholm Great Yarmouth Norfolk NR31 0AJ",
    "addr:postcode":"nr31 0aj",
    "addr:street":"Breydon Road Cobholm Great Yarmouth",
    "iso:country":"GB",
    "sg:address":"Breydon Road, Cobholm",
    "sg:city":"Great Yarmouth",
    "sg:classifiers":[
        {
            "category":"Autos & Motor Vehicles",
            "subcategory":"Boat Sales",
            "type":"Retail Goods"
        }
    ],
    "sg:phone":"+44 1493 656996",
    "sg:postcode":"NR31 0AJ",
    "sg:province":"Norfolk",
    "sg:tags":[
        "repair",
        "builder"
    ],
    "wof:name":"Bure Marine",
    "wof:placetype":"venue"
},
  "geometry": {"coordinates":[1.7184400558,52.6077957153],"type":"Point"}
}