{
  "type": "Feature",
  "properties": {
    "iso:country":"GB",
    "sg:address":"Poole Road, Upton",
    "sg:city":"Poole",
    "sg:classifiers":[
        {
            "category":"Retail",
            "subcategory":"Auto Repair",
            "type":"Services"
        }
    ],
    "sg:phone":"+44 1202 622249",
    "sg:postcode":"BH16 5HY",
    "sg:province":"Dorset",
    "sg:tags":[
        "modification",
        "garage",
        "related"
    ],
    "wof:name":"Palmer's Garage",
    "wof:placetype":"venue"
},
  "geometry": {"coordinates":[-2.013959,50.73996],"type":"Point"}
}