{
  "type": "Feature",
  "properties": {
    "addr:full":"20 North Gate Bridgnorth Shropshire WV16 4ET",
    "addr:housenumber":"20",
    "addr:postcode":"wv16 4et",
    "addr:street":"North Gate",
    "iso:country":"GB",
    "sg:address":"20 North Gate",
    "sg:city":"Bridgnorth",
    "sg:classifiers":[
        {
            "category":"Bus Charters",
            "type":"Transportation"
        }
    ],
    "sg:phone":"+44 1746 762676",
    "sg:postcode":"WV16 4ET",
    "sg:province":"Shropshire",
    "sg:tags":[
        "coach"
    ],
    "wof:name":"Elcock Coaches",
    "wof:placetype":"venue"
},
  "geometry": {"coordinates":[-2.421276,52.537724],"type":"Point"}
}