{
  "type": "Feature",
  "properties": {
    "iso:country":"GB",
    "sg:address":"39 Hopetoun Road",
    "sg:city":"South Queensferry",
    "sg:classifiers":[
        {
            "category":"Personal",
            "subcategory":"Beauty Salon",
            "type":"Services"
        },
        {
            "category":"Personal",
            "subcategory":"Barber",
            "type":"Services"
        }
    ],
    "sg:phone":"+44 131 331 4315",
    "sg:postcode":"EH30 9RB",
    "sg:province":"City of Edinburgh",
    "sg:tags":[
        "unisex",
        "hairdresser"
    ],
    "sg:website":"http://www.hairchair.org",
    "wof:name":"Hair Chair",
    "wof:placetype":"venue"
},
  "geometry": {"coordinates":[-3.4003500938,55.9906425476],"type":"Point"}
}