{
  "type": "Feature",
  "properties": {
    "addr:full":"35 Clifton Road Lossiemouth Moray IV31 6DP",
    "addr:housenumber":"35",
    "addr:postcode":"iv31 6dp",
    "addr:street":"Clifton Road",
    "iso:country":"GB",
    "sg:address":"35 Clifton Road",
    "sg:city":"Lossiemouth",
    "sg:classifiers":[
        {
            "category":"Retail",
            "subcategory":"Auto Repair",
            "type":"Services"
        }
    ],
    "sg:phone":"+44 1343 812063",
    "sg:postcode":"IV31 6DP",
    "sg:province":"Moray",
    "sg:tags":[
        "modification",
        "garage",
        "related"
    ],
    "wof:name":"Lossiemouth Garage",
    "wof:placetype":"venue"
},
  "geometry": {"coordinates":[-3.2856040001,57.7177810669],"type":"Point"}
}