{
  "type": "Feature",
  "properties": {
    "iso:country":"GB",
    "sg:address":"Desmond Court, 1c Kings Road",
    "sg:city":"Hitchin",
    "sg:classifiers":[
        {
            "category":"Military Area",
            "subcategory":"Air Force Base",
            "type":"Public Place"
        }
    ],
    "sg:postcode":"SG5 1RD",
    "sg:province":"Bedfordshire",
    "sg:tags":[
        "taxi",
        "hire",
        "private"
    ],
    "wof:name":"A A & Tiny's Taxis",
    "wof:placetype":"venue"
},
  "geometry": {"coordinates":[-0.2694920003,51.9540977478],"type":"Point"}
}