{
  "type": "Feature",
  "properties": {
    "iso:country":"GB",
    "sg:address":"7 Wellington Road",
    "sg:city":"Bilston",
    "sg:classifiers":[
        {
            "category":"Health Services",
            "subcategory":"Dentist",
            "type":"Services"
        }
    ],
    "sg:phone":"+44 1902 491009",
    "sg:postcode":"WV14 6AA",
    "sg:province":"West Midlands",
    "wof:name":"Brown & Turner",
    "wof:placetype":"venue"
},
  "geometry": {"coordinates":[-2.075597,52.567429],"type":"Point"}
}