{
  "type": "Feature",
  "properties": {
    "iso:country":"GB",
    "sg:address":"96 Cairns Road",
    "sg:city":"Bristol",
    "sg:classifiers":[
        {
            "category":"Retail",
            "subcategory":"Auto Repair",
            "type":"Services"
        }
    ],
    "sg:phone":"+44 117 942 0241",
    "sg:postcode":"BS6 7TG",
    "sg:province":"City of Bristol",
    "sg:tags":[
        "modification",
        "garage"
    ],
    "wof:name":"Cairns Rd Garage",
    "wof:placetype":"venue"
},
  "geometry": {"coordinates":[-2.604036,51.477848],"type":"Point"}
}