{
  "type": "Feature",
  "properties": {
    "addr:full":"Newhouse, Newhouse Motherwell North Lanarkshire ML1 5SY",
    "addr:postcode":"ml1 5sy",
    "iso:country":"GB",
    "sg:address":"Newhouse, Newhouse",
    "sg:city":"Motherwell",
    "sg:classifiers":[
        {
            "category":"Bars & Pubs",
            "type":"Food & Drink"
        }
    ],
    "sg:phone":"+44 1698 860277",
    "sg:postcode":"ML1 5SY",
    "sg:province":"North Lanarkshire",
    "sg:tags":[
        "pubs",
        "inn"
    ],
    "wof:name":"Newhouse Travel Inn & Brewers' Fayre",
    "wof:placetype":"venue"
},
  "geometry": {"coordinates":[-3.927571,55.830997],"type":"Point"}
}