{
  "type": "Feature",
  "properties": {
    "addr:full":"25 North St Alexandria Argyll and Bute G83 0EA",
    "addr:housenumber":"25",
    "addr:postcode":"g83 0ea",
    "addr:street":"North St",
    "iso:country":"GB",
    "sg:address":"25 North St",
    "sg:city":"Alexandria",
    "sg:classifiers":[
        {
            "category":"Manufacturing",
            "subcategory":"Building Materials",
            "type":"Manufacturing & Wholesale Goods"
        }
    ],
    "sg:phone":"+44 1389 750834",
    "sg:postcode":"G83 0EA",
    "sg:province":"Argyll and Bute",
    "sg:tags":[
        "merchant",
        "builder"
    ],
    "wof:name":"James Donald Builders Merchants",
    "wof:placetype":"venue"
},
  "geometry": {"coordinates":[-4.585209,55.992142],"type":"Point"}
}