{
  "type": "Feature",
  "properties": {
    "addr:full":"1 Sydenham Rd London Greater London SE26 5ET",
    "addr:housenumber":"1",
    "addr:postcode":"se26 5et",
    "addr:street":"Sydenham Rd",
    "iso:country":"GB",
    "sg:address":"1 Sydenham Rd",
    "sg:city":"London",
    "sg:classifiers":[
        {
            "category":"Shopping",
            "subcategory":"Clothing, Apparel, & Fashions",
            "type":"Retail Goods"
        }
    ],
    "sg:postcode":"SE26 5ET",
    "sg:province":"Greater London",
    "sg:tags":[
        "shop"
    ],
    "wof:name":"Wood,L,",
    "wof:placetype":"venue"
},
  "geometry": {"coordinates":[-0.0542990007,51.4264984131],"type":"Point"}
}