{
  "type": "Feature",
  "properties": {
    "addr:full":"The Barn, Church Street Matlock Derbyshire DE4 5FH",
    "addr:postcode":"de4 5fh",
    "addr:street":"Church Street",
    "iso:country":"GB",
    "sg:address":"The Barn, Church Street",
    "sg:city":"Matlock",
    "sg:classifiers":[
        {
            "category":"Building & Trades",
            "subcategory":"Construction",
            "type":"Services"
        }
    ],
    "sg:phone":"+44 1629 56586",
    "sg:postcode":"DE4 5FH",
    "sg:province":"Derbyshire",
    "sg:tags":[
        "builder"
    ],
    "wof:name":"Stuart Godfrey",
    "wof:placetype":"venue"
},
  "geometry": {"coordinates":[-1.514658,53.10297],"type":"Point"}
}