{
  "type": "Feature",
  "properties": {
    "iso:country":"GB",
    "sg:address":"3 St Fagans Street",
    "sg:city":"Caerphilly",
    "sg:classifiers":[
        {
            "category":"Shopping",
            "subcategory":"Department Store",
            "type":"Retail Goods"
        },
        {
            "category":"Shopping",
            "subcategory":"Clothing, Apparel, & Fashions",
            "type":"Retail Goods"
        }
    ],
    "sg:phone":"+44 29 2088 4019",
    "sg:postcode":"CF83 1FZ",
    "sg:province":"Caerphilly",
    "sg:tags":[
        "shop",
        "departmental"
    ],
    "wof:name":"Peacocks Stores Ltd",
    "wof:placetype":"venue"
},
  "geometry": {"coordinates":[-3.220635,51.574066],"type":"Point"}
}