{
  "type": "Feature",
  "properties": {
    "addr:full":"26 Lexden Road Colchester Essex CO3 3QD",
    "addr:housenumber":"26",
    "addr:postcode":"co3 3qd",
    "addr:street":"Lexden Road Colchester",
    "iso:country":"GB",
    "sg:address":"26 Lexden Road",
    "sg:city":"Colchester",
    "sg:classifiers":[
        {
            "category":"Social Services",
            "subcategory":"Retirement Home",
            "type":"Services"
        }
    ],
    "sg:postcode":"CO3 3QD",
    "sg:province":"Essex",
    "sg:tags":[
        "residential",
        "care"
    ],
    "wof:name":"West Lodge",
    "wof:placetype":"venue"
},
  "geometry": {"coordinates":[0.8816999793,51.8873138428],"type":"Point"}
}