{
  "type": "Feature",
  "properties": {
    "iso:country":"GB",
    "sg:address":"Staneyhill",
    "sg:city":"Lerwick",
    "sg:classifiers":[
        {
            "category":"Education",
            "subcategory":"College",
            "type":"Public Place"
        },
        {
            "category":"Education",
            "subcategory":"Vocational School",
            "type":"Public Place"
        }
    ],
    "sg:phone":"+44 1595 693520",
    "sg:postcode":"ZE1 0NA",
    "sg:province":"Shetland Islands",
    "sg:tags":[
        "technical",
        "agricultural"
    ],
    "wof:name":"The Scottish Agricultural College",
    "wof:placetype":"venue"
},
  "geometry": {"coordinates":[-1.1452239752,60.1518287659],"type":"Point"}
}