{
  "type": "Feature",
  "properties": {
    "iso:country":"GB",
    "sg:address":"177 Stoke Newington Church Street",
    "sg:city":"London",
    "sg:classifiers":[
        {
            "category":"Cinema",
            "subcategory":"Movie Rental",
            "type":"Entertainment"
        }
    ],
    "sg:phone":"+44 20 7249 1762",
    "sg:postcode":"N16 0UL",
    "sg:province":"Greater London",
    "sg:tags":[
        "video",
        "library"
    ],
    "wof:name":"The Film Shop",
    "wof:placetype":"venue"
},
  "geometry": {"coordinates":[-0.082804,51.561111],"type":"Point"}
}