{
  "type": "Feature",
  "properties": {
    "addr:full":"13 Mead Park Harlow Essex CM20 2SE",
    "addr:housenumber":"13",
    "addr:postcode":"cm20 2se",
    "addr:street":"Mead Park",
    "iso:country":"GB",
    "sg:address":"13 Mead Park",
    "sg:city":"Harlow",
    "sg:classifiers":[
        {
            "category":"Manufacturing",
            "subcategory":"Wood Products",
            "type":"Manufacturing & Wholesale Goods"
        }
    ],
    "sg:postcode":"CM20 2SE",
    "sg:province":"Essex",
    "sg:tags":[
        "packaging",
        "crate",
        "pallets"
    ],
    "wof:name":"Murlyn Services",
    "wof:placetype":"venue"
},
  "geometry": {"coordinates":[0.11152,51.788029],"type":"Point"}
}