{
  "type": "Feature",
  "properties": {
    "addr:full":"Morton Acres, Fence Houses Houghton-le-spring Durham DH4 6PY",
    "addr:postcode":"dh4 6py",
    "iso:country":"GB",
    "sg:address":"Morton Acres, Fence Houses",
    "sg:city":"Houghton-le-spring",
    "sg:classifiers":[
        {
            "category":"Home & Garden",
            "subcategory":"Garden Supply",
            "type":"Retail Goods"
        },
        {
            "category":"Banks & Credit Unions",
            "subcategory":"Investment Brokerage",
            "type":"Services"
        }
    ],
    "sg:phone":"+44 191 385 2208",
    "sg:postcode":"DH4 6PY",
    "sg:province":"Durham",
    "sg:tags":[
        "supplier",
        "turf",
        "turfing",
        "contractor"
    ],
    "wof:name":"DURHAM TURF",
    "wof:placetype":"venue"
},
  "geometry": {"coordinates":[-1.50879,54.836819],"type":"Point"}
}