{
  "type": "Feature",
  "properties": {
    "iso:country":"GB",
    "sg:address":"204 Lavender Hill",
    "sg:city":"London",
    "sg:classifiers":[
        {
            "category":"Food & Beverages",
            "subcategory":"Supermarket",
            "type":"Retail Goods"
        }
    ],
    "sg:phone":"+44 20 7223 0101",
    "sg:postcode":"SW11 1JG",
    "sg:province":"Greater London",
    "sg:website":"http://www.asda.com",
    "wof:name":"Asda Stores Ltd.",
    "wof:placetype":"venue"
},
  "geometry": {"coordinates":[-0.1645590067,51.4641189575],"type":"Point"}
}