{
  "type": "Feature",
  "properties": {
    "addr:full":"69 Holmes Avenue Hove East Sussex BN3 7LB",
    "addr:housenumber":"69",
    "addr:postcode":"bn3 7lb",
    "addr:street":"Holmes Avenue",
    "iso:country":"GB",
    "sg:address":"69 Holmes Avenue",
    "sg:city":"Hove",
    "sg:classifiers":[
        {
            "category":"Manufacturing",
            "subcategory":"Petroleum Products",
            "type":"Manufacturing & Wholesale Goods"
        }
    ],
    "sg:postcode":"BN3 7LB",
    "sg:province":"East Sussex",
    "sg:tags":[
        "double",
        "glazing"
    ],
    "wof:name":"Custom Windows Ltd.",
    "wof:placetype":"venue"
},
  "geometry": {"coordinates":[-0.187342,50.842587],"type":"Point"}
}