{
  "type": "Feature",
  "properties": {
    "iso:country":"GB",
    "sg:address":"13 Tenterfield Terr",
    "sg:city":"Halifax",
    "sg:classifiers":[
        {
            "category":"Building & Trades",
            "subcategory":"Plumbing",
            "type":"Services"
        }
    ],
    "sg:postcode":"HX3 7AH",
    "sg:province":"West Yorkshire",
    "sg:tags":[
        "heating"
    ],
    "wof:name":"J S B Heating Services",
    "wof:placetype":"venue"
},
  "geometry": {"coordinates":[-1.830679059,53.7316703796],"type":"Point"}
}