{
  "type": "Feature",
  "properties": {
    "addr:full":"27a Mill Street Brierley Hill West Midlands DY5 2RG",
    "addr:housenumber":"27a",
    "addr:postcode":"dy5 2rg",
    "addr:street":"Mill Street",
    "iso:country":"GB",
    "sg:address":"27a Mill Street",
    "sg:city":"Brierley Hill",
    "sg:classifiers":[
        {
            "category":"Professional",
            "subcategory":"Engineering",
            "type":"Services"
        }
    ],
    "sg:phone":"+44 1384 482190",
    "sg:postcode":"DY5 2RG",
    "sg:province":"West Midlands",
    "sg:tags":[
        "precision",
        "engineer"
    ],
    "wof:name":"Bennett Engineering",
    "wof:placetype":"venue"
},
  "geometry": {"coordinates":[-2.120525,52.480408],"type":"Point"}
}