{
  "type": "Feature",
  "properties": {
    "addr:full":"Tennis Court Farm, Wells Road, Hallatrow Bristol Somerset BS39 6EJ",
    "addr:postcode":"bs39 6ej",
    "addr:street":"Tennis;Wells Road",
    "iso:country":"GB",
    "sg:address":"Tennis Court Farm, Wells Road, Hallatrow",
    "sg:city":"Bristol",
    "sg:classifiers":[
        {
            "category":"Farming",
            "subcategory":"Livestock Farm",
            "type":"Manufacturing & Wholesale Goods"
        }
    ],
    "sg:phone":"+44 1761 452285",
    "sg:postcode":"BS39 6EJ",
    "sg:province":"Somerset",
    "sg:tags":[
        "others"
    ],
    "wof:name":"B J Stock",
    "wof:placetype":"venue"
},
  "geometry": {"coordinates":[-2.521044,51.312405],"type":"Point"}
}