{
  "type": "Feature",
  "properties": {
    "addr:full":"Unit 2 Eagle Estate, Brookers Road Billingshurst West Sussex RH14 9RZ",
    "addr:housenumber":"unit 2",
    "addr:postcode":"rh14 9rz",
    "addr:street":"Eagle Estate Brookers Road",
    "iso:country":"GB",
    "sg:address":"Unit 2 Eagle Estate, Brookers Road",
    "sg:city":"Billingshurst",
    "sg:classifiers":[
        {
            "category":"Professional",
            "subcategory":"Engineering",
            "type":"Services"
        }
    ],
    "sg:phone":"+44 1403 786759",
    "sg:postcode":"RH14 9RZ",
    "sg:province":"West Sussex",
    "wof:name":"Amytech Ltd.",
    "wof:placetype":"venue"
},
  "geometry": {"coordinates":[-0.452428,51.021183],"type":"Point"}
}