{
  "type": "Feature",
  "properties": {
    "addr:full":"6 Greenshield Industrial Estate, Bradfield Road, Silvertown London Greater London E16 2AU",
    "addr:housenumber":"6",
    "addr:postcode":"e16 2au",
    "addr:street":"Greenshield Industrial Estate Bradfield Road",
    "iso:country":"GB",
    "sg:address":"6 Greenshield Industrial Estate, Bradfield Road, Silvertown",
    "sg:city":"London",
    "sg:classifiers":[
        {
            "category":"Building & Trades",
            "subcategory":"Construction",
            "type":"Services"
        }
    ],
    "sg:phone":"+44 20 7511 2090",
    "sg:postcode":"E16 2AU",
    "sg:province":"Greater London",
    "sg:tags":[
        "platform",
        "work",
        "scaffolding"
    ],
    "wof:name":"London Tower Service Ltd.",
    "wof:placetype":"venue"
},
  "geometry": {"coordinates":[0.02337,51.50172],"type":"Point"}
}