{
  "type": "Feature",
  "properties": {
    "addr:full":"F 41 Crown Gate, Shopping Centre Friary Walk Worcester Worcestershire WR1 3LE",
    "addr:housenumber":"41",
    "addr:postcode":"wr1 3le",
    "addr:street":"Crown Gate Shopping;Friary Walk",
    "iso:country":"GB",
    "sg:address":"F 41 Crown Gate, Shopping Centre Friary Walk",
    "sg:city":"Worcester",
    "sg:classifiers":[
        {
            "category":"Food & Beverages",
            "subcategory":"Candy",
            "type":"Retail Goods"
        },
        {
            "category":"Food & Beverages",
            "subcategory":"Specialty",
            "type":"Retail Goods"
        }
    ],
    "sg:phone":"+44 1905 611129",
    "sg:postcode":"WR1 3LE",
    "sg:province":"Worcestershire",
    "sg:tags":[
        "merchant",
        "product",
        "produce",
        "health"
    ],
    "wof:name":"Graves,Julian,Ltd",
    "wof:placetype":"venue"
},
  "geometry": {"coordinates":[-2.222274065,52.1910667419],"type":"Point"}
}