{
  "type": "Feature",
  "properties": {
    "addr:full":"185 Lady Margaret Road Southall Greater London UB1 2PT",
    "addr:housenumber":"185",
    "addr:postcode":"ub1 2pt",
    "addr:street":"Lady Margaret Road",
    "iso:country":"GB",
    "sg:address":"185 Lady Margaret Road",
    "sg:city":"Southall",
    "sg:classifiers":[
        {
            "category":"Shopping",
            "subcategory":"Pharmacy",
            "type":"Retail Goods"
        }
    ],
    "sg:phone":"+44 20 8574 2767",
    "sg:postcode":"UB1 2PT",
    "sg:province":"Greater London",
    "sg:tags":[
        "pharmacist",
        "dispensing",
        "chemist"
    ],
    "wof:name":"H J Dixon",
    "wof:placetype":"venue"
},
  "geometry": {"coordinates":[-0.3756250143,51.5187644958],"type":"Point"}
}