{
  "type": "Feature",
  "properties": {
    "addr:full":"118 Desswood Place, Aberdeen Aberdeen Aberdeen City AB15 4DQ",
    "addr:housenumber":"118",
    "addr:postcode":"ab15 4dq",
    "addr:street":"Desswood Place",
    "iso:country":"GB",
    "sg:address":"118 Desswood Place, Aberdeen",
    "sg:city":"Aberdeen",
    "sg:classifiers":[
        {
            "category":"Utilities",
            "subcategory":"Fuel Oil & Lpg",
            "type":"Services"
        }
    ],
    "sg:phone":"+44 1224 637684",
    "sg:postcode":"AB15 4DQ",
    "sg:province":"Aberdeen City",
    "sg:tags":[
        "gas"
    ],
    "wof:name":"Seraglio Ltd.",
    "wof:placetype":"venue"
},
  "geometry": {"coordinates":[-2.128519,57.14537],"type":"Point"}
}