{
  "type": "Feature",
  "properties": {
    "addr:full":"16 The Plain Bristol Gloucestershire BS35 2BG",
    "addr:housenumber":"16",
    "addr:postcode":"bs35 2bg",
    "addr:street":"The Plain",
    "iso:country":"GB",
    "sg:address":"16 The Plain",
    "sg:city":"Bristol",
    "sg:classifiers":[
        {
            "category":"Banks & Credit Unions",
            "subcategory":"Bank",
            "type":"Services"
        }
    ],
    "sg:phone":"+44 1454 620100",
    "sg:postcode":"BS35 2BG",
    "sg:province":"Gloucestershire",
    "wof:name":"NatWest",
    "wof:placetype":"venue"
},
  "geometry": {"coordinates":[-2.526175,51.609341],"type":"Point"}
}