{
  "type": "Feature",
  "properties": {
    "iso:country":"GB",
    "sg:address":"38 First Gardens",
    "sg:city":"Glasgow",
    "sg:classifiers":[
        {
            "category":"Professional",
            "subcategory":"Engineering",
            "type":"Services"
        }
    ],
    "sg:phone":"+44 141 427 1703",
    "sg:postcode":"G41 5NB",
    "sg:province":"Glasgow City",
    "sg:tags":[
        "contractor",
        "electrical",
        "engineer"
    ],
    "wof:name":"M & M Electrics",
    "wof:placetype":"venue"
},
  "geometry": {"coordinates":[-4.310422,55.843559],"type":"Point"}
}