{
  "type": "Feature",
  "properties": {
    "addr:full":"Corner Building, Solar Rd Liverpool Merseyside L9 9AS",
    "addr:postcode":"l9 9as",
    "addr:street":"Solar Rd",
    "iso:country":"GB",
    "sg:address":"Corner Building, Solar Rd",
    "sg:city":"Liverpool",
    "sg:classifiers":[
        {
            "category":"Farming",
            "subcategory":"Nursery",
            "type":"Manufacturing & Wholesale Goods"
        }
    ],
    "sg:phone":"+44 151 521 4227",
    "sg:postcode":"L9 9AS",
    "sg:province":"Merseyside",
    "sg:tags":[
        "creche"
    ],
    "wof:name":"Rowan Day Nursery",
    "wof:placetype":"venue"
},
  "geometry": {"coordinates":[-2.9545500278,53.4642295837],"type":"Point"}
}