{
  "type": "Feature",
  "properties": {
    "iso:country":"GB",
    "sg:address":"102 Woodchurch Lane",
    "sg:city":"Birkenhead",
    "sg:classifiers":[
        {
            "category":"Fast Food",
            "type":"Food & Drink"
        }
    ],
    "sg:phone":"+44 151 608 0045",
    "sg:postcode":"CH42 9PD",
    "sg:province":"Merseyside",
    "sg:tags":[
        "away",
        "meal",
        "outlet",
        "take"
    ],
    "wof:name":"Phoenix Takeaway",
    "wof:placetype":"venue"
},
  "geometry": {"coordinates":[-3.039893,53.373917],"type":"Point"}
}