{
  "type": "Feature",
  "properties": {
    "iso:country":"GB",
    "sg:address":"Unit 8/9 The Vivars Industrial C, Entre Vivars Way, Canal Road",
    "sg:city":"Selby",
    "sg:classifiers":[
        {
            "category":"Recreation",
            "subcategory":"Fishing",
            "type":"Entertainment"
        }
    ],
    "sg:phone":"+44 1757 210160",
    "sg:postcode":"YO8 8BE",
    "sg:province":"East Riding of Yorkshire",
    "sg:tags":[
        "angling"
    ],
    "wof:name":"Guide Flyfishing Ltd.",
    "wof:placetype":"venue"
},
  "geometry": {"coordinates":[-1.070346,53.783909],"type":"Point"}
}