{
  "type": "Feature",
  "properties": {
    "addr:full":"Central Ho, 32-66 High St, Stratford London Greater London E15 2PD",
    "addr:housenumber":"32-66",
    "addr:postcode":"e15 2pd",
    "addr:street":"High St",
    "iso:country":"GB",
    "sg:address":"Central Ho, 32-66 High St, Stratford",
    "sg:city":"London",
    "sg:classifiers":[
        {
            "category":"Real Estate",
            "subcategory":"Real Estate Operator",
            "type":"Services"
        }
    ],
    "sg:postcode":"E15 2PD",
    "sg:province":"Greater London",
    "sg:tags":[
        "rental"
    ],
    "wof:name":"I Ellison",
    "wof:placetype":"venue"
},
  "geometry": {"coordinates":[-0.009471,51.532536],"type":"Point"}
}