{
  "type": "Feature",
  "properties": {
    "addr:full":"16a Arbour Road Leicester Leicestershire LE4 6QA",
    "addr:housenumber":"16a",
    "addr:postcode":"le4 6qa",
    "addr:street":"Arbour Road",
    "iso:country":"GB",
    "sg:address":"16a Arbour Road",
    "sg:city":"Leicester",
    "sg:classifiers":[
        {
            "category":"Wholesale",
            "subcategory":"Fruits & Vegetables",
            "type":"Manufacturing & Wholesale Goods"
        }
    ],
    "sg:postcode":"LE4 6QA",
    "sg:province":"Leicestershire",
    "wof:name":"Adams Produce",
    "wof:placetype":"venue"
},
  "geometry": {"coordinates":[-1.117203,52.655479],"type":"Point"}
}