{
  "type": "Feature",
  "properties": {
    "addr:full":"Coombe Gro Farm, Ermine Way, Arrington Royston Bedfordshire SG8 0AL",
    "addr:postcode":"sg8 0al",
    "addr:street":"Gro Farm Ermine Way",
    "iso:country":"GB",
    "sg:address":"Coombe Gro Farm, Ermine Way, Arrington",
    "sg:city":"Royston",
    "sg:classifiers":[
        {
            "category":"Manufacturing",
            "subcategory":"Electronics",
            "type":"Manufacturing & Wholesale Goods"
        }
    ],
    "sg:phone":"+44 1223 208877",
    "sg:postcode":"SG8 0AL",
    "sg:province":"Bedfordshire",
    "sg:tags":[
        "control",
        "component",
        "-",
        "electronic"
    ],
    "wof:name":"Yoshino Ltd.",
    "wof:placetype":"venue"
},
  "geometry": {"coordinates":[-0.0643400028,52.1348876953],"type":"Point"}
}