{
  "type": "Feature",
  "properties": {
    "iso:country":"GB",
    "sg:address":"4 Weald Way",
    "sg:city":"Caterham",
    "sg:classifiers":[
        {
            "category":"Education",
            "subcategory":"School",
            "type":"Public Place"
        }
    ],
    "sg:phone":"+44 1883 342002",
    "sg:postcode":"CR3 6EG",
    "sg:province":"Surrey",
    "sg:tags":[
        "private",
        "tuition"
    ],
    "wof:name":"E.B French Tuition",
    "wof:placetype":"venue"
},
  "geometry": {"coordinates":[-0.090347,51.263771],"type":"Point"}
}