{
  "type": "Feature",
  "properties": {
    "iso:country":"GB",
    "sg:address":"50 Albert Rd, Farnworth",
    "sg:city":"Bolton",
    "sg:classifiers":[
        {
            "category":"Shopping",
            "subcategory":"News",
            "type":"Retail Goods"
        }
    ],
    "sg:phone":"+44 1204 572578",
    "sg:postcode":"BL4 7BB",
    "sg:province":"Lancashire",
    "sg:tags":[
        "newsagent"
    ],
    "wof:name":"M Ayub",
    "wof:placetype":"venue"
},
  "geometry": {"coordinates":[-2.401255,53.548615],"type":"Point"}
}