{
  "type": "Feature",
  "properties": {
    "iso:country":"GB",
    "sg:address":"20 Market Street",
    "sg:city":"Highbridge",
    "sg:classifiers":[
        {
            "category":"Fast Food",
            "type":"Food & Drink"
        }
    ],
    "sg:phone":"+44 1278 782427",
    "sg:postcode":"TA9 3BT",
    "sg:province":"Somerset",
    "sg:tags":[
        "away",
        "meal",
        "outlet",
        "take"
    ],
    "wof:name":"Yeung's",
    "wof:placetype":"venue"
},
  "geometry": {"coordinates":[-2.9743,51.219215],"type":"Point"}
}