{
  "type": "Feature",
  "properties": {
    "addr:full":"142 High Street Scunthorpe Lincolnshire DN15 6EN",
    "addr:housenumber":"142",
    "addr:postcode":"dn15 6en",
    "addr:street":"High Street",
    "iso:country":"GB",
    "sg:address":"142 High Street",
    "sg:city":"Scunthorpe",
    "sg:classifiers":[
        {
            "category":"Shopping",
            "subcategory":"Bicycles & Sporting Goods",
            "type":"Retail Goods"
        }
    ],
    "sg:phone":"+44 1724 865429",
    "sg:postcode":"DN15 6EN",
    "sg:province":"Lincolnshire",
    "sg:tags":[
        "cycle",
        "accessory"
    ],
    "wof:name":"Johns (Scunthorpe) Ltd.",
    "wof:placetype":"venue"
},
  "geometry": {"coordinates":[-0.650644,53.591415],"type":"Point"}
}