{
  "type": "Feature",
  "properties": {
    "addr:full":"300 Longbarn Blvd, Birchwood Warrington Cheshire WA2 0XD",
    "addr:housenumber":"300",
    "addr:postcode":"wa2 0xd",
    "addr:street":"Longbarn Blvd",
    "iso:country":"GB",
    "sg:address":"300 Longbarn Blvd, Birchwood",
    "sg:city":"Warrington",
    "sg:classifiers":[
        {
            "category":"Shopping",
            "subcategory":"Computers & Home Electronics",
            "type":"Retail Goods"
        }
    ],
    "sg:phone":"+44 1925 851851",
    "sg:postcode":"WA2 0XD",
    "sg:province":"Cheshire",
    "wof:name":"M D I S",
    "wof:placetype":"venue"
},
  "geometry": {"coordinates":[-2.5384790897,53.4128608704],"type":"Point"}
}