{
  "type": "Feature",
  "properties": {
    "addr:full":"Ling Hall, Coalpit Lane, Lawford Heath Rugby Northamptonshire CV23 9HH",
    "addr:postcode":"cv23 9hh",
    "addr:street":"Coalpit Lane",
    "iso:country":"GB",
    "sg:address":"Ling Hall, Coalpit Lane, Lawford Heath",
    "sg:city":"Rugby",
    "sg:classifiers":[
        {
            "category":"Utilities",
            "subcategory":"Refuse",
            "type":"Services"
        }
    ],
    "sg:phone":"+44 1788 522709",
    "sg:postcode":"CV23 9HH",
    "sg:province":"Northamptonshire",
    "sg:tags":[
        "disposal",
        "waste",
        "retail"
    ],
    "wof:name":"Onyx Total Waste Management",
    "wof:placetype":"venue"
},
  "geometry": {"coordinates":[-1.3337539434,52.3551864624],"type":"Point"}
}