{
  "type": "Feature",
  "properties": {
    "addr:full":"D169-171 Fruit & Vegetable Mark, Et London Greater London SW8 5LL",
    "addr:postcode":"sw8 5ll",
    "iso:country":"GB",
    "sg:address":"D169-171 Fruit & Vegetable Mark, Et",
    "sg:city":"London",
    "sg:classifiers":[
        {
            "category":"Wholesale",
            "subcategory":"Fruits & Vegetables",
            "type":"Manufacturing & Wholesale Goods"
        }
    ],
    "sg:phone":"+44 20 7622 5545",
    "sg:postcode":"SW8 5LL",
    "sg:province":"Greater London",
    "wof:name":"T D A (London) Ltd.",
    "wof:placetype":"venue"
},
  "geometry": {"coordinates":[-0.1348499954,51.4773902893],"type":"Point"}
}