{
  "type": "Feature",
  "properties": {
    "addr:full":"Noel House, 2-4 Noel Street London Greater London W1F 8GA",
    "addr:housenumber":"2-4",
    "addr:postcode":"w1f 8ga",
    "addr:street":"Noel Street",
    "iso:country":"GB",
    "sg:address":"Noel House, 2-4 Noel Street",
    "sg:city":"London",
    "sg:classifiers":[
        {
            "category":"Arts & Performance",
            "subcategory":"Theater",
            "type":"Entertainment"
        }
    ],
    "sg:phone":"+44 20 7287 9000",
    "sg:postcode":"W1F 8GA",
    "sg:province":"Greater London",
    "sg:tags":[
        "theatrical",
        "agency"
    ],
    "wof:name":"London Management & Representation Ltd.",
    "wof:placetype":"venue"
},
  "geometry": {"coordinates":[-0.136973,51.515022],"type":"Point"}
}