{
  "type": "Feature",
  "properties": {
    "addr:full":"18 The Pentagon Chatham Kent ME4 4HP",
    "addr:housenumber":"18",
    "addr:postcode":"me4 4hp",
    "addr:street":"The Pentagon",
    "iso:country":"GB",
    "sg:address":"18 The Pentagon",
    "sg:city":"Chatham",
    "sg:classifiers":[
        {
            "category":"Shopping",
            "subcategory":"Clothing, Apparel, & Fashions",
            "type":"Retail Goods"
        }
    ],
    "sg:phone":"+44 1634 402111",
    "sg:postcode":"ME4 4HP",
    "sg:province":"Kent",
    "sg:tags":[
        "shop"
    ],
    "wof:name":"Etam Plc",
    "wof:placetype":"venue"
},
  "geometry": {"coordinates":[0.5224400163,51.3818893433],"type":"Point"}
}