{
  "type": "Feature",
  "properties": {
    "addr:full":"Unit 1, St Lukes Business Centre Suther Cradley Heath West Midlands B64 6EA",
    "addr:housenumber":"unit 1",
    "addr:postcode":"b64 6ea",
    "addr:street":"St;Suther",
    "iso:country":"GB",
    "sg:address":"Unit 1, St Lukes Business Centre Suther",
    "sg:city":"Cradley Heath",
    "sg:classifiers":[
        {
            "category":"Professional",
            "subcategory":"Engineering",
            "type":"Services"
        }
    ],
    "sg:postcode":"B64 6EA",
    "sg:province":"West Midlands",
    "sg:tags":[
        "ge",
        "engineer",
        "mechanical"
    ],
    "wof:name":"I D A Engineering Services",
    "wof:placetype":"venue"
},
  "geometry": {"coordinates":[-2.0722498894,52.4724807739],"type":"Point"}
}