{
  "type": "Feature",
  "properties": {
    "addr:full":"The Butchery, Bosbury Road Malvern Gloucestershire WR13 5LT",
    "addr:postcode":"wr13 5lt",
    "addr:street":"Bosbury Road",
    "iso:country":"GB",
    "sg:address":"The Butchery, Bosbury Road",
    "sg:city":"Malvern",
    "sg:classifiers":[
        {
            "category":"Food & Beverages",
            "subcategory":"Meat & Fish",
            "type":"Retail Goods"
        }
    ],
    "sg:phone":"+44 1886 880221",
    "sg:postcode":"WR13 5LT",
    "sg:province":"Gloucestershire",
    "sg:tags":[
        "butcher"
    ],
    "wof:name":"Peter W Hodgkiss",
    "wof:placetype":"venue"
},
  "geometry": {"coordinates":[-2.40226,52.118069],"type":"Point"}
}