{
  "type": "Feature",
  "properties": {
    "addr:full":"4 The Ford, Braintree Road Dunmow Essex CM6 1HU",
    "addr:housenumber":"4",
    "addr:postcode":"cm6 1hu",
    "addr:street":"The Ford Braintree Road",
    "iso:country":"GB",
    "sg:address":"4 The Ford, Braintree Road",
    "sg:city":"Dunmow",
    "sg:classifiers":[
        {
            "category":"Wholesale",
            "subcategory":"Medical Equipment & Supplies",
            "type":"Manufacturing & Wholesale Goods"
        }
    ],
    "sg:phone":"+44 1371 875576",
    "sg:postcode":"CM6 1HU",
    "sg:province":"Essex",
    "sg:tags":[
        "hospital"
    ],
    "wof:name":"Raven Equipment Ltd.",
    "wof:placetype":"venue"
},
  "geometry": {"coordinates":[0.3649770021,51.8706130981],"type":"Point"}
}