{
  "type": "Feature",
  "properties": {
    "addr:full":"404 The Spa Melksham Wiltshire SN12 6QL",
    "addr:housenumber":"404",
    "addr:postcode":"sn12 6ql",
    "addr:street":"The",
    "iso:country":"GB",
    "sg:address":"404 The Spa",
    "sg:city":"Melksham",
    "sg:classifiers":[
        {
            "category":"Professional",
            "subcategory":"Management & Consulting",
            "type":"Services"
        },
        {
            "category":"Professional",
            "subcategory":"Computer Services",
            "type":"Services"
        }
    ],
    "sg:phone":"+44 1225 708225",
    "sg:postcode":"SN12 6QL",
    "sg:province":"Wiltshire",
    "sg:tags":[
        "development",
        "consultant",
        "business",
        "database"
    ],
    "wof:name":"WELL HOUSE CONSULTANTS LTD",
    "wof:placetype":"venue"
},
  "geometry": {"coordinates":[-2.1259899139,51.3645820618],"type":"Point"}
}