{
  "type": "Feature",
  "properties": {
    "iso:country":"GB",
    "sg:address":"62 Churchfield Lane, Glasshoughton",
    "sg:city":"Castleford",
    "sg:classifiers":[
        {
            "category":"Retail",
            "subcategory":"Auto Repair",
            "type":"Services"
        }
    ],
    "sg:phone":"+44 1977 552241",
    "sg:postcode":"WF10 4DD",
    "sg:province":"West Yorkshire",
    "sg:tags":[
        "engine",
        "specialist",
        "diagnostic",
        "tuning",
        "car"
    ],
    "wof:name":"Tom Mobile Engine Tuning",
    "wof:placetype":"venue"
},
  "geometry": {"coordinates":[-1.337769,53.719803],"type":"Point"}
}