{
  "type": "Feature",
  "properties": {
    "addr:full":"Mill Lodge, Lower Mills Glasgow East Renfrewshire G76 8BJ",
    "addr:postcode":"g76 8bj",
    "iso:country":"GB",
    "sg:address":"Mill Lodge, Lower Mills",
    "sg:city":"Glasgow",
    "sg:classifiers":[
        {
            "category":"Shopping",
            "subcategory":"Computers & Home Electronics",
            "type":"Retail Goods"
        }
    ],
    "sg:phone":"+44 141 644 4962",
    "sg:postcode":"G76 8BJ",
    "sg:province":"East Renfrewshire",
    "sg:tags":[
        "electrical"
    ],
    "wof:name":"Bill Brown Electrical",
    "wof:placetype":"venue"
},
  "geometry": {"coordinates":[-4.271611,55.785015],"type":"Point"}
}