{
  "type": "Feature",
  "properties": {
    "addr:full":"212 Blackburn Rd, Egerton Bolton Lancashire BL7 9SR",
    "addr:housenumber":"212",
    "addr:postcode":"bl7 9sr",
    "addr:street":"Blackburn Rd",
    "iso:country":"GB",
    "sg:address":"212 Blackburn Rd, Egerton",
    "sg:city":"Bolton",
    "sg:classifiers":[
        {
            "category":"Arena",
            "subcategory":"Sports Club",
            "type":"Entertainment"
        }
    ],
    "sg:postcode":"BL7 9SR",
    "sg:province":"Lancashire",
    "wof:name":"Turton & District Bowling Association",
    "wof:placetype":"venue"
},
  "geometry": {"coordinates":[-2.4404211044,53.6289482117],"type":"Point"}
}