{
  "type": "Feature",
  "properties": {
    "iso:country":"GB",
    "sg:address":"Hill Barn, Lyde",
    "sg:city":"Hereford",
    "sg:classifiers":[
        {
            "category":"Sports & Exercise",
            "subcategory":"Golf",
            "type":"Entertainment"
        }
    ],
    "sg:postcode":"HR4 8AB",
    "sg:province":"Herefordshire",
    "sg:tags":[
        "range",
        "driving"
    ],
    "wof:name":"Hereford Driving Range & Golf Centre",
    "wof:placetype":"venue"
},
  "geometry": {"coordinates":[-2.7317609787,52.0592041016],"type":"Point"}
}