{
  "type": "Feature",
  "properties": {
    "addr:full":"215a North Street Romford Essex RM1 4QA",
    "addr:housenumber":"215a",
    "addr:postcode":"rm1 4qa",
    "addr:street":"North Street",
    "iso:country":"GB",
    "sg:address":"215a North Street",
    "sg:city":"Romford",
    "sg:classifiers":[
        {
            "category":"Building & Trades",
            "subcategory":"Plumbing",
            "type":"Services"
        }
    ],
    "sg:phone":"+44 1708 734155",
    "sg:postcode":"RM1 4QA",
    "sg:province":"Essex",
    "sg:tags":[
        "central",
        "heating"
    ],
    "wof:name":"Squirrels Plumbing & Heating",
    "wof:placetype":"venue"
},
  "geometry": {"coordinates":[0.1734980047,51.5844955444],"type":"Point"}
}