{
  "type": "Feature",
  "properties": {
    "addr:full":"386/388 Palatine Road, Northenden Manchester Greater Manchester M22 4FZ",
    "addr:housenumber":"386 / 388",
    "addr:postcode":"m22 4fz",
    "addr:street":"Palatine Road",
    "iso:country":"GB",
    "sg:address":"386/388 Palatine Road, Northenden",
    "sg:city":"Manchester",
    "sg:classifiers":[
        {
            "category":"Professional",
            "subcategory":"Employment Agencies",
            "type":"Services"
        }
    ],
    "sg:postcode":"M22 4FZ",
    "sg:province":"Greater Manchester",
    "sg:tags":[
        "consultant"
    ],
    "wof:name":"Social Care Ltd",
    "wof:placetype":"venue"
},
  "geometry": {"coordinates":[-2.2584910393,53.4077262878],"type":"Point"}
}