{
  "type": "Feature",
  "properties": {
    "addr:full":"Unit 18 Bromfield Trad Est Mold Denbighshire CH7 1JR",
    "addr:housenumber":"unit 18",
    "addr:postcode":"ch7 1jr",
    "iso:country":"GB",
    "sg:address":"Unit 18 Bromfield Trad Est",
    "sg:city":"Mold",
    "sg:classifiers":[
        {
            "category":"Retail",
            "subcategory":"Auto Repair",
            "type":"Services"
        }
    ],
    "sg:postcode":"CH7 1JR",
    "sg:province":"Denbighshire",
    "sg:tags":[
        "body",
        "car"
    ],
    "wof:name":"Sullivan,Mark,",
    "wof:placetype":"venue"
},
  "geometry": {"coordinates":[-3.1342539787,53.1602363586],"type":"Point"}
}