{
  "type": "Feature",
  "properties": {
    "iso:country":"GB",
    "sg:address":"Heatherleigh Gardens",
    "sg:city":"Blackburn",
    "sg:classifiers":[
        {
            "category":"Manufacturing",
            "subcategory":"Textiles",
            "type":"Manufacturing & Wholesale Goods"
        }
    ],
    "sg:phone":"+44 1254 675025",
    "sg:postcode":"BB2 4SX",
    "sg:province":"Lancashire",
    "sg:tags":[
        "dyer"
    ],
    "wof:name":"Carters of Blackburn",
    "wof:placetype":"venue"
},
  "geometry": {"coordinates":[-2.489689,53.718357],"type":"Point"}
}