{
  "type": "Feature",
  "properties": {
    "iso:country":"GB",
    "sg:address":"Baths Road, Longton",
    "sg:city":"Stoke-on-trent",
    "sg:classifiers":[
        {
            "category":"Home & Garden",
            "subcategory":"Hardware",
            "type":"Retail Goods"
        }
    ],
    "sg:phone":"+44 1782 313488",
    "sg:postcode":"ST3 2JG",
    "sg:province":"Staffordshire",
    "wof:name":"R D Cresswell & Co. Ltd.",
    "wof:placetype":"venue"
},
  "geometry": {"coordinates":[-2.137049,52.988914],"type":"Point"}
}