{
  "type": "Feature",
  "properties": {
    "addr:full":"85 The Broadway, Wimbledon London Greater London SW19 1QE",
    "addr:housenumber":"85",
    "addr:postcode":"sw19 1qe",
    "addr:street":"The Broadway",
    "iso:country":"GB",
    "sg:address":"85 The Broadway, Wimbledon",
    "sg:city":"London",
    "sg:classifiers":[
        {
            "category":"Real Estate",
            "subcategory":"Real Estate Agent",
            "type":"Services"
        }
    ],
    "sg:phone":"+44 20 8543 8336",
    "sg:postcode":"SW19 1QE",
    "sg:province":"Greater London",
    "wof:name":"Cross & Prior",
    "wof:placetype":"venue"
},
  "geometry": {"coordinates":[-0.202384,51.419491],"type":"Point"}
}