{
  "type": "Feature",
  "properties": {
    "addr:full":"Westexe Tiverton Devon EX16 5LL",
    "addr:postcode":"ex16 5ll",
    "addr:street":"Westexe",
    "iso:country":"GB",
    "sg:address":"Westexe",
    "sg:city":"Tiverton",
    "sg:classifiers":[
        {
            "category":"Professional",
            "subcategory":"Management & Consulting",
            "type":"Services"
        }
    ],
    "sg:postcode":"EX16 5LL",
    "sg:province":"Devon",
    "sg:tags":[
        "consultant",
        "business"
    ],
    "wof:name":"Mid Devon Enterprise Agency",
    "wof:placetype":"venue"
},
  "geometry": {"coordinates":[-3.491649,50.903332],"type":"Point"}
}