{
  "type": "Feature",
  "properties": {
    "iso:country":"GB",
    "sg:address":"The Old Corn Store, London Road",
    "sg:city":"Westerham",
    "sg:classifiers":[
        {
            "category":"Shopping",
            "subcategory":"Beauty & Cosmetics",
            "type":"Retail Goods"
        }
    ],
    "sg:postcode":"TN16 1GE",
    "sg:province":"Kent",
    "sg:tags":[
        "equipment",
        "supply",
        "hairdressing"
    ],
    "wof:name":"Alan Roy Nail Products Ltd.",
    "wof:placetype":"venue"
},
  "geometry": {"coordinates":[0.0686400011,51.2713012695],"type":"Point"}
}