{
  "type": "Feature",
  "properties": {
    "addr:full":"Wardens Office, Trewarden Avenue, Iver Heath Iver Berkshire SL0 0SB",
    "addr:postcode":"sl0 0sb",
    "addr:street":"Trewarden Avenue",
    "iso:country":"GB",
    "sg:address":"Wardens Office, Trewarden Avenue, Iver Heath",
    "sg:city":"Iver",
    "sg:classifiers":[
        {
            "category":"Social Services",
            "subcategory":"Adult Care",
            "type":"Services"
        },
        {
            "category":"Social Services",
            "subcategory":"Retirement Home",
            "type":"Services"
        }
    ],
    "sg:phone":"+44 1753 650210",
    "sg:postcode":"SL0 0SB",
    "sg:province":"Berkshire",
    "sg:tags":[
        "housing",
        "sheltered",
        "accommodation"
    ],
    "wof:name":"Bodley House",
    "wof:placetype":"venue"
},
  "geometry": {"coordinates":[-0.5206189752,51.5365447998],"type":"Point"}
}