{
  "type": "Feature",
  "properties": {
    "iso:country":"GB",
    "sg:address":"8 Spur Road",
    "sg:city":"Portsmouth",
    "sg:classifiers":[
        {
            "category":"Professional",
            "subcategory":"Accounting & Tax Preparation",
            "type":"Services"
        }
    ],
    "sg:phone":"+44 23 9237 2235",
    "sg:postcode":"PO6 3EB",
    "sg:province":"Hampshire",
    "sg:tags":[
        "accountant"
    ],
    "wof:name":"K S L Chartered Accountants",
    "wof:placetype":"venue"
},
  "geometry": {"coordinates":[-1.068116,50.846745],"type":"Point"}
}