{
  "type": "Feature",
  "properties": {
    "iso:country":"GB",
    "sg:address":"18 Morpeth Close, Oxclose",
    "sg:city":"Washington",
    "sg:phone":"+44 191 415 1399",
    "sg:postcode":"NE38 0NU",
    "sg:province":"Durham",
    "wof:name":"Indico Technical Services",
    "wof:placetype":"venue"
},
  "geometry": {"coordinates":[-1.549314,54.895283],"type":"Point"}
}