{
  "type": "Feature",
  "properties": {
    "iso:country":"GB",
    "sg:address":"The Wharf, Buxton Road",
    "sg:city":"Macclesfield",
    "sg:classifiers":[
        {
            "category":"Retail",
            "subcategory":"Auto Repair",
            "type":"Services"
        }
    ],
    "sg:phone":"+44 1625 422388",
    "sg:postcode":"SK10 1LZ",
    "sg:province":"Cheshire",
    "sg:tags":[
        "modification",
        "garage"
    ],
    "wof:name":"Central Tyre & Auto Services",
    "wof:placetype":"venue"
},
  "geometry": {"coordinates":[-2.1153399944,53.259021759],"type":"Point"}
}