{
  "type": "Feature",
  "properties": {
    "addr:full":"77 Vardar Avenue, Clarkston Glasgow East Renfrewshire G76 7QW",
    "addr:housenumber":"77",
    "addr:postcode":"g76 7qw",
    "addr:street":"Vardar Avenue",
    "iso:country":"GB",
    "sg:address":"77 Vardar Avenue, Clarkston",
    "sg:city":"Glasgow",
    "sg:classifiers":[
        {
            "category":"Real Estate",
            "subcategory":"Architect",
            "type":"Services"
        }
    ],
    "sg:postcode":"G76 7QW",
    "sg:province":"East Renfrewshire",
    "wof:name":"Thomas Ramsay",
    "wof:placetype":"venue"
},
  "geometry": {"coordinates":[-4.292187,55.790581],"type":"Point"}
}