{
  "type": "Feature",
  "properties": {
    "iso:country":"GB",
    "sg:address":"8-10 The Square",
    "sg:city":"Bromyard",
    "sg:classifiers":[
        {
            "category":"Real Estate",
            "subcategory":"Real Estate Agent",
            "type":"Services"
        }
    ],
    "sg:phone":"+44 1885 482515",
    "sg:postcode":"HR7 4BP",
    "sg:province":"Herefordshire",
    "wof:name":"Mvi",
    "wof:placetype":"venue"
},
  "geometry": {"coordinates":[-2.5103991032,52.1890983582],"type":"Point"}
}