{
  "type": "Feature",
  "properties": {
    "addr:full":"94 Guildford Road Croydon Surrey CR0 2HJ",
    "addr:housenumber":"94",
    "addr:postcode":"cr0 2hj",
    "addr:street":"Guildford Road",
    "iso:country":"GB",
    "sg:address":"94 Guildford Road",
    "sg:city":"Croydon",
    "sg:classifiers":[
        {
            "category":"Professional",
            "subcategory":"Printing & Photocopies",
            "type":"Services"
        }
    ],
    "sg:phone":"+44 20 8683 0546",
    "sg:postcode":"CR0 2HJ",
    "sg:province":"Surrey",
    "sg:tags":[
        "emblem",
        "wholesale",
        "badge"
    ],
    "wof:name":"Alexco",
    "wof:placetype":"venue"
},
  "geometry": {"coordinates":[-0.094075,51.389782],"type":"Point"}
}