{
  "type": "Feature",
  "properties": {
    "iso:country":"GB",
    "sg:address":"Stirling Rd",
    "sg:city":"Dumbarton",
    "sg:classifiers":[
        {
            "category":"Shopping",
            "subcategory":"Florist",
            "type":"Retail Goods"
        }
    ],
    "sg:phone":"+44 1389 767780",
    "sg:postcode":"G82 2PJ",
    "sg:province":"Argyll and Bute",
    "wof:name":"Express Country Blooms",
    "wof:placetype":"venue"
},
  "geometry": {"coordinates":[-4.5427517891,55.9434356689],"type":"Point"}
}