{
  "type": "Feature",
  "properties": {
    "addr:full":"Unit 12 Caldbeck Road, Croft Business Park, Bromborough Wirral Cheshire CH62 3PL",
    "addr:housenumber":"unit 12",
    "addr:postcode":"ch62 3pl",
    "addr:street":"Caldbeck Road Croft Business Park",
    "iso:country":"GB",
    "sg:address":"Unit 12 Caldbeck Road, Croft Business Park, Bromborough",
    "sg:city":"Wirral",
    "sg:classifiers":[
        {
            "category":"Professional",
            "subcategory":"Engineering",
            "type":"Services"
        }
    ],
    "sg:phone":"+44 151 334 5300",
    "sg:postcode":"CH62 3PL",
    "sg:province":"Cheshire",
    "sg:tags":[
        "consulting",
        "engineer"
    ],
    "wof:name":"Huppert Engineering (U K) Ltd.",
    "wof:placetype":"venue"
},
  "geometry": {"coordinates":[-2.978718996,53.3372459412],"type":"Point"}
}