{
  "type": "Feature",
  "properties": {
    "iso:country":"GB",
    "sg:address":"25 High Street, Great Dunmow",
    "sg:city":"Dunmow",
    "sg:classifiers":[
        {
            "category":"Personal",
            "subcategory":"Beauty Salon",
            "type":"Services"
        }
    ],
    "sg:phone":"+44 1371 873079",
    "sg:postcode":"CM6 1AB",
    "sg:province":"Essex",
    "wof:name":"Profiles Beauty Salon",
    "wof:placetype":"venue"
},
  "geometry": {"coordinates":[0.36326,51.872166],"type":"Point"}
}