{
  "type": "Feature",
  "properties": {
    "addr:full":"57 Sandford Mill Rd Chelmsford Essex CM2 6NS",
    "addr:housenumber":"57",
    "addr:postcode":"cm2 6ns",
    "addr:street":"Sandford Mill Rd",
    "iso:country":"GB",
    "sg:address":"57 Sandford Mill Rd",
    "sg:city":"Chelmsford",
    "sg:classifiers":[
        {
            "category":"Building & Trades",
            "subcategory":"Plumbing",
            "type":"Services"
        }
    ],
    "sg:postcode":"CM2 6NS",
    "sg:province":"Essex",
    "sg:tags":[
        "drain",
        "clearance",
        "sewer"
    ],
    "wof:name":"B A Plumbing",
    "wof:placetype":"venue"
},
  "geometry": {"coordinates":[0.50813,51.731899],"type":"Point"}
}