{
  "type": "Feature",
  "properties": {
    "addr:full":"14 West End Llanelli Carmarthenshire SA15 3DN",
    "addr:housenumber":"14",
    "addr:postcode":"sa15 3dn",
    "addr:street":"West End",
    "iso:country":"GB",
    "sg:address":"14 West End",
    "sg:city":"Llanelli",
    "sg:classifiers":[
        {
            "category":"Home & Garden",
            "subcategory":"Home Furnishings",
            "type":"Retail Goods"
        }
    ],
    "sg:phone":"+44 1554 749364",
    "sg:postcode":"SA15 3DN",
    "sg:province":"Carmarthenshire",
    "sg:tags":[
        "mantelpiece",
        "fireplace"
    ],
    "wof:name":"Trade Direct Surrounds Ltd",
    "wof:placetype":"venue"
},
  "geometry": {"coordinates":[-4.1647291183,51.6844329834],"type":"Point"}
}