{
  "type": "Feature",
  "properties": {
    "addr:full":"2 Smithy Walk Ormskirk Lancashire L40 5UU",
    "addr:housenumber":"2",
    "addr:postcode":"l40 5uu",
    "addr:street":"Smithy Walk",
    "iso:country":"GB",
    "sg:address":"2 Smithy Walk",
    "sg:city":"Ormskirk",
    "sg:classifiers":[
        {
            "category":"Shopping",
            "subcategory":"Shoes",
            "type":"Retail Goods"
        }
    ],
    "sg:phone":"+44 1704 892174",
    "sg:postcode":"L40 5UU",
    "sg:province":"Lancashire",
    "sg:tags":[
        "shop"
    ],
    "wof:name":"Eastwoods",
    "wof:placetype":"venue"
},
  "geometry": {"coordinates":[-2.9213979244,53.5965042114],"type":"Point"}
}