{
  "type": "Feature",
  "properties": {
    "iso:country":"GB",
    "sg:address":"Broadford Post Office",
    "sg:city":"Isle Of Skye",
    "sg:classifiers":[
        {
            "category":"Transit Center",
            "subcategory":"Freight",
            "type":"Transportation"
        }
    ],
    "sg:phone":"+44 1471 822754",
    "sg:postcode":"IV49 9AB",
    "sg:province":"Highland",
    "sg:tags":[
        "shop",
        "craft",
        "centre"
    ],
    "wof:name":"Craft Encounters",
    "wof:placetype":"venue"
},
  "geometry": {"coordinates":[-5.91218,57.242214],"type":"Point"}
}