{
  "type": "Feature",
  "properties": {
    "addr:full":"Brook Lane, Chillerton Newport Isle of Wight PO30 3EW",
    "addr:postcode":"po30 3ew",
    "addr:street":"Brook Lane",
    "iso:country":"GB",
    "sg:address":"Brook Lane, Chillerton",
    "sg:city":"Newport",
    "sg:classifiers":[
        {
            "category":"Manufacturing",
            "subcategory":"Furniture",
            "type":"Manufacturing & Wholesale Goods"
        }
    ],
    "sg:phone":"+44 1983 721324",
    "sg:postcode":"PO30 3EW",
    "sg:province":"Isle of Wight",
    "sg:tags":[
        "mnfr",
        "garden",
        "patio"
    ],
    "wof:name":"Village Gates",
    "wof:placetype":"venue"
},
  "geometry": {"coordinates":[-1.306129,50.656586],"type":"Point"}
}