{
  "type": "Feature",
  "properties": {
    "addr:full":"Hamworthy Ho, New Quay Rd Poole Dorset BH15 4AD",
    "addr:postcode":"bh15 4ad",
    "addr:street":"New Quay Rd",
    "iso:country":"GB",
    "sg:address":"Hamworthy Ho, New Quay Rd",
    "sg:city":"Poole",
    "sg:classifiers":[
        {
            "category":"Professional",
            "subcategory":"Computer Services",
            "type":"Services"
        }
    ],
    "sg:phone":"+44 1202 667337",
    "sg:postcode":"BH15 4AD",
    "sg:province":"Dorset",
    "sg:tags":[
        "system",
        "software"
    ],
    "wof:name":"MICRO90 Ltd",
    "wof:placetype":"venue"
},
  "geometry": {"coordinates":[-1.986739,50.714485],"type":"Point"}
}