{
  "type": "Feature",
  "properties": {
    "iso:country":"GB",
    "sg:address":"28 Latch Road",
    "sg:city":"Brechin",
    "sg:classifiers":[
        {
            "category":"Home & Garden",
            "subcategory":"Hardware",
            "type":"Retail Goods"
        }
    ],
    "sg:phone":"+44 1356 623599",
    "sg:postcode":"DD9 6JF",
    "sg:province":"Aberdeenshire",
    "sg:tags":[
        "equipment",
        "welding"
    ],
    "wof:name":"Teg-Tech",
    "wof:placetype":"venue"
},
  "geometry": {"coordinates":[-2.664437,56.735146],"type":"Point"}
}