{
  "type": "Feature",
  "properties": {
    "iso:country":"GB",
    "sg:address":"Unit 2a New Elm Road, Manchester Industrial Estate",
    "sg:city":"Manchester",
    "sg:classifiers":[
        {
            "category":"Autos & Motor Vehicles",
            "subcategory":"Auto Supplies",
            "type":"Retail Goods"
        }
    ],
    "sg:phone":"+44 161 832 8222",
    "sg:postcode":"M3 4JU",
    "sg:province":"Greater Manchester",
    "sg:tags":[
        "car",
        "lacquer",
        "paint"
    ],
    "wof:name":"Spray Shop Supplies Ltd.",
    "wof:placetype":"venue"
},
  "geometry": {"coordinates":[-2.259764,53.476345],"type":"Point"}
}