{
  "type": "Feature",
  "properties": {
    "iso:country":"GB",
    "sg:address":"Broxell Close, Wedgenock Industrial Estate",
    "sg:city":"Warwick",
    "sg:classifiers":[
        {
            "category":"Retail",
            "subcategory":"Auto Repair",
            "type":"Services"
        }
    ],
    "sg:phone":"+44 1926 418800",
    "sg:postcode":"CV34 5QF",
    "sg:province":"Warwickshire",
    "sg:tags":[
        "car",
        "sprayer",
        "painter"
    ],
    "wof:name":"Durr Ltd.",
    "wof:placetype":"venue"
},
  "geometry": {"coordinates":[-1.6009089947,52.2917442322],"type":"Point"}
}