{
  "type": "Feature",
  "properties": {
    "addr:full":"Plantation Lane Newtown Powys SY16 1LH",
    "addr:postcode":"sy16 1lh",
    "addr:street":"Plantation Lane",
    "iso:country":"GB",
    "sg:address":"Plantation Lane",
    "sg:city":"Newtown",
    "sg:classifiers":[
        {
            "category":"Bars & Pubs",
            "type":"Food & Drink"
        }
    ],
    "sg:phone":"+44 1686 625891",
    "sg:postcode":"SY16 1LH",
    "sg:province":"Powys",
    "sg:tags":[
        "pubs",
        "inn"
    ],
    "wof:name":"Red Dragon",
    "wof:placetype":"venue"
},
  "geometry": {"coordinates":[-3.3187439442,52.5075759888],"type":"Point"}
}