{
  "type": "Feature",
  "properties": {
    "iso:country":"GB",
    "sg:address":"3 Beech Court",
    "sg:city":"Dartford",
    "sg:classifiers":[
        {
            "category":"Organizations",
            "subcategory":"Political Organization",
            "type":"Services"
        }
    ],
    "sg:phone":"+44 1322 294176",
    "sg:postcode":"DA1 5PD",
    "sg:province":"Kent",
    "sg:tags":[
        "party"
    ],
    "wof:name":"THE LIBERAL DEMOCRAT PARTY",
    "wof:placetype":"venue"
},
  "geometry": {"coordinates":[0.213378,51.436905],"type":"Point"}
}