{
  "type": "Feature",
  "properties": {
    "addr:full":"Unit 2f Brown Lees Road Industrial Estat, Forge Way, Knypersley Stoke-on-trent Staffordshire ST8 7DN",
    "addr:housenumber":"unit 2f",
    "addr:postcode":"staffordshire st8 7dn",
    "addr:street":"Brown Lees Road Industrial Estat Forge Way",
    "iso:country":"GB",
    "sg:address":"Unit 2f Brown Lees Road Industrial Estat, Forge Way, Knypersley",
    "sg:city":"Stoke-on-trent",
    "sg:classifiers":[
        {
            "category":"Personal",
            "type":"Services"
        }
    ],
    "sg:phone":"+44 1782 523336",
    "sg:postcode":"ST8 7DN",
    "sg:province":"Staffordshire",
    "sg:tags":[
        "delivery"
    ],
    "wof:name":"A N C Congleton",
    "wof:placetype":"venue"
},
  "geometry": {"coordinates":[-2.1809339523,53.0974159241],"type":"Point"}
}