{
  "type": "Feature",
  "properties": {
    "addr:full":"42 Ward Ave Grays Essex RM17 5RE",
    "addr:housenumber":"42",
    "addr:postcode":"rm17 5re",
    "addr:street":"Ward Ave",
    "iso:country":"GB",
    "sg:address":"42 Ward Ave",
    "sg:city":"Grays",
    "sg:classifiers":[
        {
            "category":"Building & Trades",
            "subcategory":"Plumbing",
            "type":"Services"
        }
    ],
    "sg:postcode":"RM17 5RE",
    "sg:province":"Essex",
    "sg:tags":[
        "heating"
    ],
    "wof:name":"Robinson,Phil,",
    "wof:placetype":"venue"
},
  "geometry": {"coordinates":[0.328353,51.486771],"type":"Point"}
}