{
  "type": "Feature",
  "properties": {
    "addr:full":"21 Hyde Road, Denton Manchester Greater Manchester M34 3AF",
    "addr:housenumber":"21",
    "addr:postcode":"m34 3af",
    "addr:street":"Hyde Road",
    "iso:country":"GB",
    "sg:address":"21 Hyde Road, Denton",
    "sg:city":"Manchester",
    "sg:classifiers":[
        {
            "category":"Military Area",
            "subcategory":"Air Force Base",
            "type":"Public Place"
        }
    ],
    "sg:phone":"+44 161 320 7117",
    "sg:postcode":"M34 3AF",
    "sg:province":"Greater Manchester",
    "sg:tags":[
        "taxi",
        "hire",
        "private"
    ],
    "wof:name":"Call A Cab",
    "wof:placetype":"venue"
},
  "geometry": {"coordinates":[-2.1126379967,53.4563751221],"type":"Point"}
}