{
  "type": "Feature",
  "properties": {
    "iso:country":"GB",
    "sg:address":"51 High Street",
    "sg:city":"Honiton",
    "sg:classifiers":[
        {
            "category":"Shopping",
            "subcategory":"Books",
            "type":"Retail Goods"
        }
    ],
    "sg:phone":"+44 1404 47180",
    "sg:postcode":"EX14 1PW",
    "sg:province":"Devon",
    "sg:tags":[
        "second-hand"
    ],
    "wof:name":"Honiton Old Book Shop",
    "wof:placetype":"venue"
},
  "geometry": {"coordinates":[-3.186424017,50.8005943298],"type":"Point"}
}