{
  "type": "Feature",
  "properties": {
    "addr:full":"Amroth Court, Caldy Close Barry The Vale of Glamorgan CF62 9DU",
    "addr:postcode":"cf62 9du",
    "addr:street":"Amroth Court Caldy Close;Vale",
    "iso:country":"GB",
    "sg:address":"Amroth Court, Caldy Close",
    "sg:city":"Barry",
    "sg:classifiers":[
        {
            "category":"Education",
            "subcategory":"School",
            "type":"Public Place"
        },
        {
            "category":"Government",
            "subcategory":"Office",
            "type":"Public Place"
        }
    ],
    "sg:phone":"+44 1446 744606",
    "sg:postcode":"CF62 9DU",
    "sg:province":"The Vale of Glamorgan",
    "sg:tags":[
        "local",
        "authority"
    ],
    "wof:name":"Oak Field Primary & Nursery School",
    "wof:placetype":"venue"
},
  "geometry": {"coordinates":[-3.267224,51.418194],"type":"Point"}
}