{
  "type": "Feature",
  "properties": {
    "iso:country":"GB",
    "sg:address":"Titan House, Station Road, Horsforth",
    "sg:city":"Leeds",
    "sg:classifiers":[
        {
            "category":"Professional",
            "subcategory":"Accounting & Tax Preparation",
            "type":"Services"
        }
    ],
    "sg:phone":"+44 113 239 0039",
    "sg:postcode":"LS18 5PA",
    "sg:province":"West Yorkshire",
    "sg:tags":[
        "accountant"
    ],
    "wof:name":"Goldsborough & Co",
    "wof:placetype":"venue"
},
  "geometry": {"coordinates":[-1.6309540272,53.8470306396],"type":"Point"}
}