{
  "type": "Feature",
  "properties": {
    "addr:full":"10 Balgibbon Drive Callander Stirling FK17 8EU",
    "addr:housenumber":"10",
    "addr:postcode":"fk17 8eu",
    "addr:street":"Balgibbon Drive",
    "iso:country":"GB",
    "sg:address":"10 Balgibbon Drive",
    "sg:city":"Callander",
    "sg:classifiers":[
        {
            "category":"Arena",
            "subcategory":"Sports Club",
            "type":"Entertainment"
        }
    ],
    "sg:phone":"+44 1877 331323",
    "sg:postcode":"FK17 8EU",
    "sg:province":"Stirling",
    "wof:name":"Scottish Clay Target Association",
    "wof:placetype":"venue"
},
  "geometry": {"coordinates":[-4.198073,56.241543],"type":"Point"}
}