{
  "type": "Feature",
  "properties": {
    "iso:country":"GB",
    "sg:address":"101 Bearton Road",
    "sg:city":"Hitchin",
    "sg:classifiers":[
        {
            "category":"Professional",
            "subcategory":"Art Services",
            "type":"Services"
        }
    ],
    "sg:phone":"+44 1462 455568",
    "sg:postcode":"SG5 1UF",
    "sg:province":"Bedfordshire",
    "sg:tags":[
        "graphic",
        "designer"
    ],
    "wof:name":"Michael Orton Designs",
    "wof:placetype":"venue"
},
  "geometry": {"coordinates":[-0.2827630043,51.9573326111],"type":"Point"}
}