{
  "type": "Feature",
  "properties": {
    "iso:country":"GB",
    "sg:address":"Beech Court, 86 Rectory Rd",
    "sg:city":"Deal",
    "sg:classifiers":[
        {
            "category":"Place Of Worship",
            "type":"Public Place"
        }
    ],
    "sg:phone":"+44 1304 374737",
    "sg:postcode":"CT14 9NB",
    "sg:province":"Kent",
    "wof:name":"Convent of our Lady of the Missions",
    "wof:placetype":"venue"
},
  "geometry": {"coordinates":[1.377889,51.215794],"type":"Point"}
}