{
  "type": "Feature",
  "properties": {
    "addr:full":"71 Muswell Hill Broadway London Greater London N10 3HA",
    "addr:housenumber":"71",
    "addr:postcode":"n10 3ha",
    "addr:street":"Muswell Hill Broadway",
    "iso:country":"GB",
    "sg:address":"71 Muswell Hill Broadway",
    "sg:city":"London",
    "sg:classifiers":[
        {
            "category":"Shopping",
            "subcategory":"Shoes",
            "type":"Retail Goods"
        }
    ],
    "sg:phone":"+44 20 8444 1227",
    "sg:postcode":"N10 3HA",
    "sg:province":"Greater London",
    "sg:tags":[
        "shop"
    ],
    "wof:name":"Kate Kuba Ltd.",
    "wof:placetype":"venue"
},
  "geometry": {"coordinates":[-0.140234,51.589924],"type":"Point"}
}