{
  "type": "Feature",
  "properties": {
    "iso:country":"GB",
    "sg:address":"60-62 Galloway La",
    "sg:city":"Pudsey",
    "sg:classifiers":[
        {
            "category":"Food & Beverages",
            "subcategory":"Groceries & Convenience Stores",
            "type":"Retail Goods"
        }
    ],
    "sg:phone":"+44 1274 665514",
    "sg:postcode":"LS28 8LE",
    "sg:province":"West Yorkshire",
    "wof:name":"Dillons",
    "wof:placetype":"venue"
},
  "geometry": {"coordinates":[-1.6895489693,53.8009109497],"type":"Point"}
}