{
  "type": "Feature",
  "properties": {
    "addr:full":"Wellingborough Road, Finedon Wellingborough Northamptonshire NN9 5JS",
    "addr:postcode":"nn9 5js",
    "addr:street":"Wellingborough Road",
    "iso:country":"GB",
    "sg:address":"Wellingborough Road, Finedon",
    "sg:city":"Wellingborough",
    "sg:classifiers":[
        {
            "category":"Parking",
            "type":"Transportation"
        }
    ],
    "sg:phone":"+44 1933 680017",
    "sg:postcode":"NN9 5JS",
    "sg:province":"Northamptonshire",
    "sg:tags":[
        "car",
        "valet"
    ],
    "wof:name":"Ashley Motors",
    "wof:placetype":"venue"
},
  "geometry": {"coordinates":[-0.649276,52.340191],"type":"Point"}
}