{
  "type": "Feature",
  "properties": {
    "iso:country":"GB",
    "sg:address":"R D S Supermarket, Haddon Road",
    "sg:city":"Barnsley",
    "sg:classifiers":[
        {
            "category":"Food & Beverages",
            "subcategory":"Supermarket",
            "type":"Retail Goods"
        },
        {
            "category":"Food & Beverages",
            "subcategory":"Groceries & Convenience Stores",
            "type":"Retail Goods"
        }
    ],
    "sg:phone":"+44 1226 297042",
    "sg:postcode":"S71 3SZ",
    "sg:province":"South Yorkshire",
    "wof:name":"R S D Superstores",
    "wof:placetype":"venue"
},
  "geometry": {"coordinates":[-1.462809,53.576199],"type":"Point"}
}