{
  "type": "Feature",
  "properties": {
    "addr:full":"22 Benedict Street Glastonbury Somerset BA6 9EX",
    "addr:housenumber":"22",
    "addr:postcode":"ba6 9ex",
    "addr:street":"Benedict Street",
    "iso:country":"GB",
    "sg:address":"22 Benedict Street",
    "sg:city":"Glastonbury",
    "sg:classifiers":[
        {
            "category":"Home & Garden",
            "subcategory":"Hardware",
            "type":"Retail Goods"
        }
    ],
    "sg:phone":"+44 1458 832292",
    "sg:postcode":"BA6 9EX",
    "sg:province":"Somerset",
    "wof:name":"G Miller & Son",
    "wof:placetype":"venue"
},
  "geometry": {"coordinates":[-2.718359,51.147232],"type":"Point"}
}