{
  "type": "Feature",
  "properties": {
    "addr:full":"Glenavon House, 39 Common Road, Claygate Esher Surrey KT10 0HG",
    "addr:housenumber":"39",
    "addr:postcode":"kt10 0hg",
    "addr:street":"Common Road",
    "iso:country":"GB",
    "sg:address":"Glenavon House, 39 Common Road, Claygate",
    "sg:city":"Esher",
    "sg:classifiers":[
        {
            "category":"Building & Trades",
            "subcategory":"Construction",
            "type":"Services"
        }
    ],
    "sg:phone":"+44 1372 467644",
    "sg:postcode":"KT10 0HG",
    "sg:province":"Surrey",
    "sg:tags":[
        "builder"
    ],
    "wof:name":"James Homes Ltd.",
    "wof:placetype":"venue"
},
  "geometry": {"coordinates":[-0.340494,51.360138],"type":"Point"}
}