{
  "type": "Feature",
  "properties": {
    "iso:country":"GB",
    "sg:address":"The Cross, West Felton",
    "sg:city":"Oswestry",
    "sg:classifiers":[
        {
            "category":"Government",
            "subcategory":"Post Office",
            "type":"Public Place"
        }
    ],
    "sg:phone":"+44 1691 610220",
    "sg:postcode":"SY11 4EH",
    "sg:province":"Shropshire",
    "wof:name":"West Felton Post Office",
    "wof:placetype":"venue"
},
  "geometry": {"coordinates":[-2.9746611118,52.821182251],"type":"Point"}
}