{
  "type": "Feature",
  "properties": {
    "iso:country":"GB",
    "sg:address":"62 Worcester Road",
    "sg:city":"Bromsgrove",
    "sg:classifiers":[
        {
            "category":"Building & Trades",
            "subcategory":"Construction",
            "type":"Services"
        }
    ],
    "sg:phone":"+44 1527 835044",
    "sg:postcode":"B61 7AG",
    "sg:province":"Worcestershire",
    "sg:tags":[
        "builder"
    ],
    "wof:name":"Password Services Maintenance",
    "wof:placetype":"venue"
},
  "geometry": {"coordinates":[-2.06438,52.332184],"type":"Point"}
}