{
  "type": "Feature",
  "properties": {
    "iso:country":"GB",
    "sg:address":"Longfurlong Farm, Catesby",
    "sg:city":"Daventry",
    "sg:classifiers":[
        {
            "category":"Farming",
            "subcategory":"Livestock Farm",
            "type":"Manufacturing & Wholesale Goods"
        },
        {
            "category":"Manufacturing",
            "subcategory":"Musical Instruments",
            "type":"Manufacturing & Wholesale Goods"
        }
    ],
    "sg:phone":"+44 1327 260278",
    "sg:postcode":"NN11 6LW",
    "sg:province":"Northamptonshire",
    "sg:tags":[
        "mechanical",
        "handling",
        "others"
    ],
    "wof:name":"G A S Haigh",
    "wof:placetype":"venue"
},
  "geometry": {"coordinates":[-1.2275880575,52.2299690247],"type":"Point"}
}