{
  "type": "Feature",
  "properties": {
    "addr:full":"Farmers Road London Greater London SE5 0UB",
    "addr:postcode":"se5 0ub",
    "addr:street":"Farmers Road",
    "iso:country":"GB",
    "sg:address":"Farmers Road",
    "sg:city":"London",
    "sg:classifiers":[
        {
            "category":"Education",
            "subcategory":"School",
            "type":"Public Place"
        },
        {
            "category":"Government",
            "subcategory":"Office",
            "type":"Public Place"
        }
    ],
    "sg:phone":"+44 20 7701 4166",
    "sg:postcode":"SE5 0UB",
    "sg:province":"Greater London",
    "sg:tags":[
        "local",
        "authority"
    ],
    "wof:name":"Archbishop Michael Ramsey School",
    "wof:placetype":"venue"
},
  "geometry": {"coordinates":[-0.102362,51.478924],"type":"Point"}
}