{
  "type": "Feature",
  "properties": {
    "addr:full":"36 Crescent Road Manchester Greater Manchester M8 9DQ",
    "addr:housenumber":"36",
    "addr:postcode":"m8 9dq",
    "addr:street":"Crescent Road",
    "iso:country":"GB",
    "sg:address":"36 Crescent Road",
    "sg:city":"Manchester",
    "sg:classifiers":[
        {
            "category":"Professional",
            "subcategory":"Employment Agencies",
            "type":"Services"
        }
    ],
    "sg:phone":"+44 161 253 8700",
    "sg:postcode":"M8 9DQ",
    "sg:province":"Greater Manchester",
    "sg:tags":[
        "consultant"
    ],
    "wof:name":"Employment Service Jobcentres",
    "wof:placetype":"venue"
},
  "geometry": {"coordinates":[-2.243111,53.512272],"type":"Point"}
}