{
  "type": "Feature",
  "properties": {
    "iso:country":"GB",
    "sg:address":"27 Blakeney Road, Patchway",
    "sg:city":"Bristol",
    "sg:classifiers":[
        {
            "category":"Building & Trades",
            "subcategory":"Cleaning & Sanitation",
            "type":"Services"
        }
    ],
    "sg:phone":"+44 117 969 7889",
    "sg:postcode":"BS34 5LY",
    "sg:province":"Gloucestershire",
    "sg:tags":[
        "commercial"
    ],
    "wof:name":"E Lovell & Son",
    "wof:placetype":"venue"
},
  "geometry": {"coordinates":[-2.58522,51.538101],"type":"Point"}
}