{
  "type": "Feature",
  "properties": {
    "iso:country":"GB",
    "sg:address":"Upperton Road",
    "sg:city":"Leicester",
    "sg:classifiers":[
        {
            "category":"Home & Garden",
            "subcategory":"Home Furnishings",
            "type":"Retail Goods"
        },
        {
            "category":"Wholesale",
            "subcategory":"Construction Materials",
            "type":"Manufacturing & Wholesale Goods"
        }
    ],
    "sg:phone":"+44 116 204 6000",
    "sg:postcode":"LE2 7AY",
    "sg:province":"Leicestershire",
    "sg:tags":[
        "merchant",
        "decorative",
        "mirror",
        "glass"
    ],
    "wof:name":"Mawby & King (Retail) Ltd.",
    "wof:placetype":"venue"
},
  "geometry": {"coordinates":[-1.1439180374,52.625667572],"type":"Point"}
}