{
  "type": "Feature",
  "properties": {
    "addr:full":"126-128 Sale Road Manchester Cheshire M23 0BX",
    "addr:housenumber":"126-128",
    "addr:postcode":"m23 0bx",
    "addr:street":"Sale Road",
    "iso:country":"GB",
    "sg:address":"126-128 Sale Road",
    "sg:city":"Manchester",
    "sg:classifiers":[
        {
            "category":"Food & Beverages",
            "subcategory":"Supermarket",
            "type":"Retail Goods"
        }
    ],
    "sg:phone":"+44 161 998 1769",
    "sg:postcode":"M23 0BX",
    "sg:province":"Cheshire",
    "wof:name":"Target",
    "wof:placetype":"venue"
},
  "geometry": {"coordinates":[-2.277309,53.410919],"type":"Point"}
}