{
  "type": "Feature",
  "properties": {
    "addr:full":"9 Ketton Av Sheffield Derbyshire S8 8PA",
    "addr:housenumber":"9",
    "addr:postcode":"s8 8pa",
    "addr:street":"Ketton Av",
    "iso:country":"GB",
    "sg:address":"9 Ketton Av",
    "sg:city":"Sheffield",
    "sg:classifiers":[
        {
            "category":"Health Services",
            "subcategory":"Podiatrist",
            "type":"Services"
        }
    ],
    "sg:phone":"+44 114 258 5601",
    "sg:postcode":"S8 8PA",
    "sg:province":"Derbyshire",
    "sg:tags":[
        "podiatrists",
        "chiropodist"
    ],
    "wof:name":"Bramall Christina",
    "wof:placetype":"venue"
},
  "geometry": {"coordinates":[-1.4672830105,53.3463554382],"type":"Point"}
}