{
  "type": "Feature",
  "properties": {
    "addr:full":"1 Sutton Road, Eyeworth Sandy Bedfordshire SG19 2TP",
    "addr:housenumber":"1",
    "addr:postcode":"sg19 2tp",
    "addr:street":"Sutton Road",
    "iso:country":"GB",
    "sg:address":"1 Sutton Road, Eyeworth",
    "sg:city":"Sandy",
    "sg:classifiers":[
        {
            "category":"Professional",
            "subcategory":"Management & Consulting",
            "type":"Services"
        }
    ],
    "sg:phone":"+44 1767 631779",
    "sg:postcode":"SG19 2TP",
    "sg:province":"Bedfordshire",
    "sg:tags":[
        "consultant",
        "business"
    ],
    "wof:name":"R T A Partnership",
    "wof:placetype":"venue"
},
  "geometry": {"coordinates":[-0.2041479945,52.128704071],"type":"Point"}
}