{
  "type": "Feature",
  "properties": {
    "addr:full":"The Cross, Berwick St John Shaftesbury Dorset SP7 0HA",
    "addr:postcode":"sp7 0ha",
    "addr:street":"The Cross Berwick;Dorset",
    "iso:country":"GB",
    "sg:address":"The Cross, Berwick St John",
    "sg:city":"Shaftesbury",
    "sg:classifiers":[
        {
            "category":"Bars & Pubs",
            "type":"Food & Drink"
        }
    ],
    "sg:phone":"+44 1747 828222",
    "sg:postcode":"SP7 0HA",
    "sg:province":"Dorset",
    "sg:tags":[
        "pubs",
        "inn"
    ],
    "wof:name":"Talbot Inn",
    "wof:placetype":"venue"
},
  "geometry": {"coordinates":[-2.0762300491,51.0001983643],"type":"Point"}
}