{
  "type": "Feature",
  "properties": {
    "addr:full":"62 High Street, Melbourn Royston Bedfordshire SG8 6AJ",
    "addr:housenumber":"62",
    "addr:postcode":"sg8 6aj",
    "addr:street":"High Street",
    "iso:country":"GB",
    "sg:address":"62 High Street, Melbourn",
    "sg:city":"Royston",
    "sg:classifiers":[
        {
            "category":"Professional",
            "subcategory":"Computer Services",
            "type":"Services"
        }
    ],
    "sg:phone":"+44 1763 261429",
    "sg:postcode":"SG8 6AJ",
    "sg:province":"Bedfordshire",
    "sg:tags":[
        "system",
        "software"
    ],
    "wof:name":"Azion",
    "wof:placetype":"venue"
},
  "geometry": {"coordinates":[0.014806,52.082661],"type":"Point"}
}