{
  "type": "Feature",
  "properties": {
    "addr:full":"84 Watling Avenue Edgware Greater London HA8 0LU",
    "addr:housenumber":"84",
    "addr:postcode":"ha8 0lu",
    "addr:street":"Watling Avenue",
    "iso:country":"GB",
    "sg:address":"84 Watling Avenue",
    "sg:city":"Edgware",
    "sg:classifiers":[
        {
            "category":"Shopping",
            "subcategory":"Baby Store",
            "type":"Retail Goods"
        }
    ],
    "sg:phone":"+44 20 8951 0285",
    "sg:postcode":"HA8 0LU",
    "sg:province":"Greater London",
    "sg:tags":[
        "babywear",
        "childrens"
    ],
    "wof:name":"Potty Kids",
    "wof:placetype":"venue"
},
  "geometry": {"coordinates":[-0.2640300095,51.6023025513],"type":"Point"}
}