{
  "type": "Feature",
  "properties": {
    "addr:full":"36 Datchworth Green, Datchworth Knebworth Hertfordshire SG3 6TL",
    "addr:housenumber":"36",
    "addr:postcode":"sg3 6tl",
    "addr:street":"Datchworth Green",
    "iso:country":"GB",
    "sg:address":"36 Datchworth Green, Datchworth",
    "sg:city":"Knebworth",
    "sg:classifiers":[
        {
            "category":"Real Estate",
            "subcategory":"Architect",
            "type":"Services"
        }
    ],
    "sg:postcode":"SG3 6TL",
    "sg:province":"Hertfordshire",
    "wof:name":"Packman Clarke",
    "wof:placetype":"venue"
},
  "geometry": {"coordinates":[-0.163549006,51.8498687744],"type":"Point"}
}