{
  "type": "Feature",
  "properties": {
    "addr:full":"38 Cambridge Street, Godmanchester Huntingdon Cambridgeshire PE29 2AY",
    "addr:housenumber":"38",
    "addr:postcode":"pe29 2ay",
    "addr:street":"Cambridge Street",
    "iso:country":"GB",
    "sg:address":"38 Cambridge Street, Godmanchester",
    "sg:city":"Huntingdon",
    "sg:classifiers":[
        {
            "category":"Personal",
            "subcategory":"Beauty Salon",
            "type":"Services"
        }
    ],
    "sg:postcode":"PE29 2AY",
    "sg:province":"Cambridgeshire",
    "sg:tags":[
        "lady",
        "hairdresser"
    ],
    "wof:name":"Jackies Hair Stylists",
    "wof:placetype":"venue"
},
  "geometry": {"coordinates":[-0.1707819998,52.3187217712],"type":"Point"}
}