{
  "type": "Feature",
  "properties": {
    "addr:full":"Wassell Gro Farm Wassell Gro Lane, Hagley Stourbridge West Midlands DY9 9JH",
    "addr:postcode":"dy9 9jh",
    "addr:street":"Gro;Wassell Gro Lane",
    "iso:country":"GB",
    "sg:address":"Wassell Gro Farm Wassell Gro Lane, Hagley",
    "sg:city":"Stourbridge",
    "sg:classifiers":[
        {
            "category":"Autos & Motor Vehicles",
            "subcategory":"Automobile Sales",
            "type":"Retail Goods"
        }
    ],
    "sg:phone":"+44 1562 886484",
    "sg:postcode":"DY9 9JH",
    "sg:province":"West Midlands",
    "sg:tags":[
        "commercial"
    ],
    "wof:name":"Davis & Davis",
    "wof:placetype":"venue"
},
  "geometry": {"coordinates":[-2.110117,52.433292],"type":"Point"}
}