{
  "type": "Feature",
  "properties": {
    "addr:full":"2 Whitfield Street London Greater London W1T 2RB",
    "addr:housenumber":"2",
    "addr:postcode":"w1t 2rb",
    "addr:street":"Whitfield Street",
    "iso:country":"GB",
    "sg:address":"2 Whitfield Street",
    "sg:city":"London",
    "sg:classifiers":[
        {
            "category":"Communications",
            "type":"Services"
        }
    ],
    "sg:phone":"+44 20 7692 5262",
    "sg:postcode":"W1T 2RB",
    "sg:province":"Greater London",
    "sg:tags":[
        "audio-visual"
    ],
    "wof:name":"Wildcat Productions Ltd.",
    "wof:placetype":"venue"
},
  "geometry": {"coordinates":[-0.1336359978,51.5190467834],"type":"Point"}
}