{
  "type": "Feature",
  "properties": {
    "addr:full":"15 Hazel Road, Kingswinford Brierley Hill Staffordshire DY6 8EZ",
    "addr:housenumber":"15",
    "addr:postcode":"dy6 8ez",
    "addr:street":"Hazel Road",
    "iso:country":"GB",
    "sg:address":"15 Hazel Road, Kingswinford",
    "sg:city":"Brierley Hill",
    "sg:classifiers":[
        {
            "category":"Retail",
            "subcategory":"Driving School",
            "type":"Services"
        }
    ],
    "sg:phone":"+44 1384 278523",
    "sg:postcode":"DY6 8EZ",
    "sg:province":"Staffordshire",
    "wof:name":"Escort Motoring School",
    "wof:placetype":"venue"
},
  "geometry": {"coordinates":[-2.161847,52.493008],"type":"Point"}
}