{
  "type": "Feature",
  "properties": {
    "iso:country":"GB",
    "sg:address":"Bramford Rd",
    "sg:city":"Ipswich",
    "sg:classifiers":[
        {
            "category":"Community Center",
            "type":"Public Place"
        }
    ],
    "sg:postcode":"IP8 4BA",
    "sg:province":"Suffolk",
    "sg:tags":[
        "nursery",
        "centre"
    ],
    "wof:name":"By-Pass Nurseries Ltd",
    "wof:placetype":"venue"
},
  "geometry": {"coordinates":[1.107389,52.073639],"type":"Point"}
}