{
  "type": "Feature",
  "properties": {
    "addr:full":"1 Strathview, Dingwall Business Park Dingwall Highland IV15 9XD",
    "addr:housenumber":"1",
    "addr:postcode":"iv15 9xd",
    "addr:street":"Strathview Dingwall Business Park Dingwall",
    "iso:country":"GB",
    "sg:address":"1 Strathview, Dingwall Business Park",
    "sg:city":"Dingwall",
    "sg:classifiers":[
        {
            "category":"Food & Beverages",
            "subcategory":"Meat & Fish",
            "type":"Retail Goods"
        }
    ],
    "sg:phone":"+44 1349 860600",
    "sg:postcode":"IV15 9XD",
    "sg:province":"Highland",
    "sg:tags":[
        "merchant"
    ],
    "wof:name":"The Edinburgh Smoked Salmon Co. (1992) Ltd.",
    "wof:placetype":"venue"
},
  "geometry": {"coordinates":[-4.431448,57.59618],"type":"Point"}
}