{
  "type": "Feature",
  "properties": {
    "iso:country":"GB",
    "sg:address":"398 Blackburn Road",
    "sg:city":"Accrington",
    "sg:classifiers":[
        {
            "category":"Shopping",
            "subcategory":"Department Store",
            "type":"Retail Goods"
        },
        {
            "category":"Home & Garden",
            "subcategory":"Carpets & Floor Coverings",
            "type":"Retail Goods"
        }
    ],
    "sg:phone":"+44 1254 383597",
    "sg:postcode":"BB5 1SA",
    "sg:province":"Lancashire",
    "sg:tags":[
        "carpets",
        "retailer",
        "rug",
        "matting"
    ],
    "wof:name":"Accrington Carpet & Bed Centre",
    "wof:placetype":"venue"
},
  "geometry": {"coordinates":[-2.38474,53.752674],"type":"Point"}
}