{
  "type": "Feature",
  "properties": {
    "addr:full":"Fishery Pier Kyle Highland IV40 8AJ",
    "addr:postcode":"iv40 8aj",
    "addr:street":"Kyle",
    "iso:country":"GB",
    "sg:address":"Fishery Pier",
    "sg:city":"Kyle",
    "sg:classifiers":[
        {
            "category":"Farming",
            "subcategory":"Fish & Marine Products",
            "type":"Manufacturing & Wholesale Goods"
        }
    ],
    "sg:phone":"+44 1599 534224",
    "sg:postcode":"IV40 8AJ",
    "sg:province":"Highland",
    "sg:tags":[
        "fishmonger"
    ],
    "wof:name":"Amazon Seafoods (U K) Ltd.",
    "wof:placetype":"venue"
},
  "geometry": {"coordinates":[-5.714052,57.280945],"type":"Point"}
}