{
  "type": "Feature",
  "properties": {
    "iso:country":"GB",
    "sg:address":"26 Bridge St",
    "sg:city":"Berwick-upon-tweed",
    "sg:classifiers":[
        {
            "category":"Restaurant",
            "type":"Food & Drink"
        }
    ],
    "sg:postcode":"TD15 1AQ",
    "sg:province":"Northumberland",
    "sg:tags":[
        "chinese"
    ],
    "wof:name":"Choung,Alan,",
    "wof:placetype":"venue"
},
  "geometry": {"coordinates":[-2.003472,55.768265],"type":"Point"}
}