{
  "type": "Feature",
  "properties": {
    "iso:country":"GB",
    "sg:address":"321 Maesyrhandir",
    "sg:city":"Newtown",
    "sg:classifiers":[
        {
            "category":"Professional",
            "subcategory":"Lawyer & Legal Services",
            "type":"Services"
        }
    ],
    "sg:phone":"+44 1686 629114",
    "sg:postcode":"SY16 2ZZ",
    "sg:province":"Powys",
    "sg:tags":[
        "advice",
        "counselling"
    ],
    "wof:name":"Montgomeryshire Womens Centre",
    "wof:placetype":"venue"
},
  "geometry": {"coordinates":[-3.3132998943,52.5143013],"type":"Point"}
}