{
  "type": "Feature",
  "properties": {
    "addr:full":"Winterleys, Albert Road London Greater London NW6 5DR",
    "addr:postcode":"nw6 5dr",
    "addr:street":"Albert Road",
    "iso:country":"GB",
    "sg:address":"Winterleys, Albert Road",
    "sg:city":"London",
    "sg:classifiers":[
        {
            "category":"Farming",
            "subcategory":"Nursery",
            "type":"Manufacturing & Wholesale Goods"
        }
    ],
    "sg:phone":"+44 20 7372 7335",
    "sg:postcode":"NW6 5DR",
    "sg:province":"Greater London",
    "sg:tags":[
        "creche"
    ],
    "wof:name":"Montessori Nursery School",
    "wof:placetype":"venue"
},
  "geometry": {"coordinates":[-0.2007099986,51.5336799622],"type":"Point"}
}