{
  "type": "Feature",
  "properties": {
    "iso:country":"GB",
    "sg:address":"16 St Cuthberts St",
    "sg:city":"Bedford",
    "sg:classifiers":[
        {
            "category":"Professional",
            "subcategory":"Business Services",
            "type":"Services"
        }
    ],
    "sg:postcode":"MK40 3JG",
    "sg:province":"Bedfordshire",
    "sg:tags":[
        "holding"
    ],
    "wof:name":"Tote-All Holdings Ltd",
    "wof:placetype":"venue"
},
  "geometry": {"coordinates":[-0.463194,52.138023],"type":"Point"}
}