{
  "type": "Feature",
  "properties": {
    "iso:country":"GB",
    "sg:address":"Allhallows Lane, Off Upper Thames Street",
    "sg:city":"London",
    "sg:classifiers":[
        {
            "category":"Sports & Exercise",
            "subcategory":"Golf",
            "type":"Entertainment"
        }
    ],
    "sg:postcode":"EC4R 3UL",
    "sg:province":"Greater London",
    "sg:tags":[
        "club",
        "course"
    ],
    "wof:name":"St. Andrew Golf Club Ltd.",
    "wof:placetype":"venue"
},
  "geometry": {"coordinates":[-0.0904960036,51.5097732544],"type":"Point"}
}