{
  "type": "Feature",
  "properties": {
    "iso:country":"GB",
    "sg:address":"Commercial Road, Rhydyfro",
    "sg:city":"Swansea",
    "sg:classifiers":[
        {
            "category":"Health Services",
            "subcategory":"Nursing And Care Facility",
            "type":"Services"
        }
    ],
    "sg:phone":"+44 1792 862845",
    "sg:postcode":"SA8 4SS",
    "sg:province":"Neath Port Talbot",
    "sg:tags":[
        "home"
    ],
    "wof:name":"Cwmcartref Nursing Home",
    "wof:placetype":"venue"
},
  "geometry": {"coordinates":[-3.864068985,51.7339134216],"type":"Point"}
}