{
  "type": "Feature",
  "properties": {
    "addr:full":"Coronation Road Totnes Devon TQ9 5GH",
    "addr:postcode":"tq9 5gh",
    "addr:street":"Coronation Road",
    "iso:country":"GB",
    "sg:address":"Coronation Road",
    "sg:city":"Totnes",
    "sg:classifiers":[
        {
            "category":"Health Services",
            "subcategory":"Hospital",
            "type":"Services"
        }
    ],
    "sg:phone":"+44 1803 862622",
    "sg:postcode":"TQ9 5GH",
    "sg:province":"Devon",
    "wof:name":"Totnes Community Hospital",
    "wof:placetype":"venue"
},
  "geometry": {"coordinates":[-3.684724,50.433369],"type":"Point"}
}