{
  "type": "Feature",
  "properties": {
    "iso:country":"GB",
    "sg:address":"Calderbank House 155 Muirhead Road, Baillieston",
    "sg:city":"Glasgow",
    "sg:classifiers":[
        {
            "category":"Organizations",
            "subcategory":"Non-profit Organization",
            "type":"Services"
        }
    ],
    "sg:phone":"+44 141 771 1071",
    "sg:postcode":"G69 7UJ",
    "sg:province":"East Dunbartonshire",
    "sg:tags":[
        "organisation",
        "voluntary",
        "charity"
    ],
    "wof:name":"Talbot Associations",
    "wof:placetype":"venue"
},
  "geometry": {"coordinates":[-4.10327,55.842999],"type":"Point"}
}