{
  "type": "Feature",
  "properties": {
    "addr:full":"Office, 48a School Road Manchester Cheshire M33 7XE",
    "addr:housenumber":"48a",
    "addr:postcode":"m33 7xe",
    "addr:street":"School Road",
    "iso:country":"GB",
    "sg:address":"Office, 48a School Road",
    "sg:city":"Manchester",
    "sg:classifiers":[
        {
            "category":"Food & Beverages",
            "subcategory":"Bakery",
            "type":"Retail Goods"
        }
    ],
    "sg:phone":"+44 161 969 6888",
    "sg:postcode":"M33 7XE",
    "sg:province":"Cheshire",
    "sg:tags":[
        "confectionery"
    ],
    "wof:name":"Lyndale Foods Ltd.",
    "wof:placetype":"venue"
},
  "geometry": {"coordinates":[-2.248809,53.479622],"type":"Point"}
}