{
  "type": "Feature",
  "properties": {
    "addr:full":"8 Spring Gro Hampton Greater London TW12 2DP",
    "addr:housenumber":"8",
    "addr:postcode":"tw12 2dp",
    "addr:street":"Spring Gro",
    "iso:country":"GB",
    "sg:address":"8 Spring Gro",
    "sg:city":"Hampton",
    "sg:classifiers":[
        {
            "category":"Social Services",
            "subcategory":"Child Care",
            "type":"Services"
        }
    ],
    "sg:phone":"+44 20 8941 5422",
    "sg:postcode":"TW12 2DP",
    "sg:province":"Greater London",
    "sg:tags":[
        "agency",
        "nanny"
    ],
    "wof:name":"Portland Placements",
    "wof:placetype":"venue"
},
  "geometry": {"coordinates":[-0.3659070134,51.413230896],"type":"Point"}
}