{
  "type": "Feature",
  "properties": {
    "iso:country":"GB",
    "sg:address":"Boundary Industrial Estate, Stafford Road",
    "sg:city":"Wolverhampton",
    "sg:classifiers":[
        {
            "category":"Retail",
            "subcategory":"Auto Repair",
            "type":"Services"
        }
    ],
    "sg:phone":"+44 1902 783442",
    "sg:postcode":"WV10 7EL",
    "sg:province":"Staffordshire",
    "sg:tags":[
        "modification",
        "garage"
    ],
    "wof:name":"Davlyns Auto Repairs",
    "wof:placetype":"venue"
},
  "geometry": {"coordinates":[-2.1260080338,52.6352806091],"type":"Point"}
}