{
  "type": "Feature",
  "properties": {
    "addr:full":"14 Laburnum Road Waterlooville Hampshire PO7 7AX",
    "addr:housenumber":"14",
    "addr:postcode":"po7 7ax",
    "addr:street":"Laburnum Road",
    "iso:country":"GB",
    "sg:address":"14 Laburnum Road",
    "sg:city":"Waterlooville",
    "sg:classifiers":[
        {
            "category":"Home & Garden",
            "subcategory":"Household Appliances",
            "type":"Retail Goods"
        }
    ],
    "sg:postcode":"PO7 7AX",
    "sg:province":"Hampshire",
    "sg:tags":[
        "electrical"
    ],
    "wof:name":"Cold Care",
    "wof:placetype":"venue"
},
  "geometry": {"coordinates":[-1.0358910561,50.874835968],"type":"Point"}
}