{
  "type": "Feature",
  "properties": {
    "addr:full":"Winnall Manor Road Winchester Hampshire SO23 0LF",
    "addr:postcode":"so23 0lf",
    "addr:street":"Manor Road",
    "iso:country":"GB",
    "sg:address":"Winnall Manor Road",
    "sg:city":"Winchester",
    "sg:classifiers":[
        {
            "category":"Home & Garden",
            "subcategory":"Hardware",
            "type":"Retail Goods"
        }
    ],
    "sg:phone":"+44 1962 856655",
    "sg:postcode":"SO23 0LF",
    "sg:province":"Hampshire",
    "sg:tags":[
        "compressor",
        "air"
    ],
    "wof:name":"Martlets Machinery Ltd.",
    "wof:placetype":"venue"
},
  "geometry": {"coordinates":[-1.296709,51.066422],"type":"Point"}
}