{
  "type": "Feature",
  "properties": {
    "iso:country":"GB",
    "sg:address":"31 Skelmersdale Road",
    "sg:city":"Clacton-on-sea",
    "sg:classifiers":[
        {
            "category":"Social Services",
            "subcategory":"Retirement Home",
            "type":"Services"
        }
    ],
    "sg:phone":"+44 1255 420090",
    "sg:postcode":"CO15 6BZ",
    "sg:province":"Essex",
    "sg:tags":[
        "residential",
        "care"
    ],
    "wof:name":"O'Boyle Woodboro",
    "wof:placetype":"venue"
},
  "geometry": {"coordinates":[1.156684,51.793919],"type":"Point"}
}