{
  "type": "Feature",
  "properties": {
    "addr:full":"11 Southampton Road London Greater London NW5 4JS",
    "addr:housenumber":"11",
    "addr:postcode":"nw5 4js",
    "addr:street":"Southampton Road",
    "iso:country":"GB",
    "sg:address":"11 Southampton Road",
    "sg:city":"London",
    "sg:classifiers":[
        {
            "category":"Shopping",
            "subcategory":"Party Supplies",
            "type":"Retail Goods"
        }
    ],
    "sg:phone":"+44 20 7267 9084",
    "sg:postcode":"NW5 4JS",
    "sg:province":"Greater London",
    "sg:tags":[
        "novelty"
    ],
    "wof:name":"Party Party",
    "wof:placetype":"venue"
},
  "geometry": {"coordinates":[-0.157333,51.551483],"type":"Point"}
}