{
  "type": "Feature",
  "properties": {
    "iso:country":"GB",
    "sg:address":"5 Avon Way, Shoeburyness",
    "sg:city":"Southend-on-sea",
    "sg:classifiers":[
        {
            "category":"Personal",
            "subcategory":"Beauty Salon",
            "type":"Services"
        }
    ],
    "sg:postcode":"SS3 9DZ",
    "sg:province":"Essex",
    "sg:tags":[
        "unisex",
        "hairdresser"
    ],
    "wof:name":"Shades",
    "wof:placetype":"venue"
},
  "geometry": {"coordinates":[0.780196,51.530907],"type":"Point"}
}