{
  "type": "Feature",
  "properties": {
    "addr:full":"Forge Parkway Retail Park, Biggar Road Glasgow Glasgow City G31 4BH",
    "addr:postcode":"g31 4bh",
    "addr:street":"Forge Parkway Retail Park Biggar Road",
    "iso:country":"GB",
    "sg:address":"Forge Parkway Retail Park, Biggar Road",
    "sg:city":"Glasgow",
    "sg:classifiers":[
        {
            "category":"Shopping",
            "subcategory":"Bicycles & Sporting Goods",
            "type":"Retail Goods"
        },
        {
            "category":"Sports & Exercise",
            "subcategory":"Sports Center",
            "type":"Entertainment"
        }
    ],
    "sg:phone":"+44 141 550 0250",
    "sg:postcode":"G31 4BH",
    "sg:province":"Glasgow City",
    "sg:tags":[
        "shop",
        "sale"
    ],
    "wof:name":"J J B Sports Plc",
    "wof:placetype":"venue"
},
  "geometry": {"coordinates":[-4.2087101936,55.8542518616],"type":"Point"}
}