{
  "type": "Feature",
  "properties": {
    "addr:full":"10 Meadowhead Sheffield Derbyshire S8 7UD",
    "addr:housenumber":"10",
    "addr:postcode":"s8 7ud",
    "addr:street":"Meadowhead",
    "iso:country":"GB",
    "sg:address":"10 Meadowhead",
    "sg:city":"Sheffield",
    "sg:classifiers":[
        {
            "category":"Recreation",
            "subcategory":"Dog Park",
            "type":"Entertainment"
        }
    ],
    "sg:phone":"+44 114 274 7250",
    "sg:postcode":"S8 7UD",
    "sg:province":"Derbyshire",
    "wof:name":"The Dog House",
    "wof:placetype":"venue"
},
  "geometry": {"coordinates":[-1.482313,53.338547],"type":"Point"}
}