{
  "type": "Feature",
  "properties": {
    "iso:country":"GB",
    "sg:address":"Field Grn Oast, Field Grn",
    "sg:city":"Cranbrook",
    "sg:classifiers":[
        {
            "category":"Building & Trades",
            "subcategory":"Construction",
            "type":"Services"
        }
    ],
    "sg:postcode":"TN18 5NP",
    "sg:province":"East Sussex",
    "sg:tags":[
        "builder"
    ],
    "wof:name":"Kent & Sussex Conversions",
    "wof:placetype":"venue"
},
  "geometry": {"coordinates":[0.54798,51.038239],"type":"Point"}
}