{
  "type": "Feature",
  "properties": {
    "iso:country":"GB",
    "sg:address":"110 Whitchurch Road",
    "sg:city":"Cardiff",
    "sg:classifiers":[
        {
            "category":"Real Estate",
            "subcategory":"Real Estate Agent",
            "type":"Services"
        }
    ],
    "sg:postcode":"CF14 3LY",
    "sg:province":"Cardiff",
    "wof:name":"Driscoll Properties Ltd",
    "wof:placetype":"venue"
},
  "geometry": {"coordinates":[-3.18779,51.50106],"type":"Point"}
}