{
  "type": "Feature",
  "properties": {
    "addr:full":"Coal Park Lane, Swanwick Southampton Hampshire SO31 7GW",
    "addr:postcode":"so31 7gw",
    "addr:street":"Coal Park Lane",
    "iso:country":"GB",
    "sg:address":"Coal Park Lane, Swanwick",
    "sg:city":"Southampton",
    "sg:classifiers":[
        {
            "category":"Autos & Motor Vehicles",
            "subcategory":"Boat Sales",
            "type":"Retail Goods"
        }
    ],
    "sg:postcode":"SO31 7GW",
    "sg:province":"Hampshire",
    "sg:tags":[
        "repair",
        "builder"
    ],
    "wof:name":"Midas Marine & Joinery Co.",
    "wof:placetype":"venue"
},
  "geometry": {"coordinates":[-1.290982,50.887428],"type":"Point"}
}