{
  "type": "Feature",
  "properties": {
    "iso:country":"GB",
    "sg:address":"114 High Street",
    "sg:city":"Swanage",
    "sg:classifiers":[
        {
            "category":"Food & Beverages",
            "subcategory":"Meat & Fish",
            "type":"Retail Goods"
        }
    ],
    "sg:phone":"+44 1929 422042",
    "sg:postcode":"BH19 2NY",
    "sg:province":"Dorset",
    "sg:tags":[
        "butcher"
    ],
    "wof:name":"P E G Stickland",
    "wof:placetype":"venue"
},
  "geometry": {"coordinates":[-1.962466,50.608063],"type":"Point"}
}