{
  "type": "Feature",
  "properties": {
    "iso:country":"GB",
    "sg:address":"Little Catterton Lane, Islington",
    "sg:city":"Tadcaster",
    "sg:classifiers":[
        {
            "category":"Autos & Motor Vehicles",
            "subcategory":"Automobile Sales",
            "type":"Retail Goods"
        },
        {
            "category":"Autos & Motor Vehicles",
            "subcategory":"Recreational Vehicle Sales",
            "type":"Retail Goods"
        }
    ],
    "sg:phone":"+44 1937 833997",
    "sg:postcode":"LS24 8EA",
    "sg:province":"North Yorkshire",
    "sg:tags":[
        "car",
        "used",
        "new"
    ],
    "sg:website":"http://www.lawtonsoftadcaster.co.uk",
    "wof:name":"Lawton'S Of Tadcaster",
    "wof:placetype":"venue"
},
  "geometry": {"coordinates":[-1.239614,53.892036],"type":"Point"}
}