{
  "type": "Feature",
  "properties": {
    "addr:full":"7 Haddo Crescent, Newburgh, Ellon Aberdeenshire AB41 6DU",
    "addr:housenumber":"7",
    "addr:postcode":"ab41 6du",
    "addr:street":"Haddo Crescent",
    "iso:country":"GB",
    "sg:address":"7 Haddo Crescent, Newburgh,",
    "sg:city":"Ellon",
    "sg:classifiers":[
        {
            "category":"Professional",
            "subcategory":"Engineering",
            "type":"Services"
        }
    ],
    "sg:postcode":"AB41 6DU",
    "sg:province":"Aberdeenshire",
    "sg:tags":[
        "design",
        "engineer"
    ],
    "wof:name":"Adams Conceputal Design Co Ltd",
    "wof:placetype":"venue"
},
  "geometry": {"coordinates":[-2.0099010468,57.3160362244],"type":"Point"}
}