{
  "type": "Feature",
  "properties": {
    "addr:full":"Brentor Road, St Judes Plymouth Devon PL4 9PS",
    "addr:postcode":"pl4 9ps",
    "addr:street":"Brentor Road",
    "iso:country":"GB",
    "sg:address":"Brentor Road, St Judes",
    "sg:city":"Plymouth",
    "sg:classifiers":[
        {
            "category":"Retail",
            "subcategory":"Auto Repair",
            "type":"Services"
        }
    ],
    "sg:postcode":"PL4 9PS",
    "sg:province":"Devon",
    "sg:tags":[
        "modification",
        "garage"
    ],
    "wof:name":"Centre Line Garage Services",
    "wof:placetype":"venue"
},
  "geometry": {"coordinates":[-4.1162638664,50.3724632263],"type":"Point"}
}