{
  "type": "Feature",
  "properties": {
    "addr:full":"40 Marine Parade Worthing West Sussex BN11 3QA",
    "addr:housenumber":"40",
    "addr:postcode":"bn11 3qa",
    "addr:street":"Marine Parade",
    "iso:country":"GB",
    "sg:address":"40 Marine Parade",
    "sg:city":"Worthing",
    "sg:classifiers":[
        {
            "category":"Arena",
            "subcategory":"Sports Club",
            "type":"Entertainment"
        }
    ],
    "sg:postcode":"BN11 3QA",
    "sg:province":"West Sussex",
    "wof:name":"Worthing Sailing & Motor Club",
    "wof:placetype":"venue"
},
  "geometry": {"coordinates":[-0.3711709976,50.8094673157],"type":"Point"}
}