{
  "type": "Feature",
  "properties": {
    "iso:country":"GB",
    "sg:address":"Barton Street",
    "sg:city":"Darlington",
    "sg:classifiers":[
        {
            "category":"Home & Garden",
            "subcategory":"Home Furnishings",
            "type":"Retail Goods"
        }
    ],
    "sg:phone":"+44 1325 362879",
    "sg:postcode":"DL1 2LP",
    "sg:province":"Durham",
    "sg:tags":[
        "decorative",
        "glass",
        "mirror"
    ],
    "wof:name":"S & S Marketing Services",
    "wof:placetype":"venue"
},
  "geometry": {"coordinates":[-1.538234,54.532501],"type":"Point"}
}