{
  "type": "Feature",
  "properties": {
    "addr:full":"7 Canary Gro Birmingham West Midlands B19 1HU",
    "addr:housenumber":"7",
    "addr:postcode":"b19 1hu",
    "addr:street":"Canary Gro",
    "iso:country":"GB",
    "sg:address":"7 Canary Gro",
    "sg:city":"Birmingham",
    "sg:classifiers":[
        {
            "category":"Building & Trades",
            "subcategory":"Cleaning & Sanitation",
            "type":"Services"
        },
        {
            "category":"Retail",
            "subcategory":"Laundry & Dry Cleaning",
            "type":"Services"
        }
    ],
    "sg:phone":"+44 121 240 0368",
    "sg:postcode":"B19 1HU",
    "sg:province":"West Midlands",
    "sg:tags":[
        "home",
        "commercial",
        "ironing"
    ],
    "wof:name":"Golden Touch",
    "wof:placetype":"venue"
},
  "geometry": {"coordinates":[-1.910232,52.504593],"type":"Point"}
}