{
  "type": "Feature",
  "properties": {
    "iso:country":"GB",
    "sg:address":"5 New Street, Bridge Of Allan",
    "sg:city":"Stirling",
    "sg:classifiers":[
        {
            "category":"Organizations",
            "subcategory":"Non-profit Organization",
            "type":"Services"
        }
    ],
    "sg:phone":"+44 1786 831171",
    "sg:postcode":"FK9 4NZ",
    "sg:province":"Clackmannanshire",
    "sg:tags":[
        "organisation",
        "voluntary",
        "charity"
    ],
    "wof:name":"Alzheimer Scotland - Action on Dementia",
    "wof:placetype":"venue"
},
  "geometry": {"coordinates":[-3.949792,56.155296],"type":"Point"}
}