{
  "type": "Feature",
  "properties": {
    "addr:full":"211 London Road Mitcham Greater London CR4 2JD",
    "addr:housenumber":"211",
    "addr:postcode":"cr4 2jd",
    "addr:street":"London Road",
    "iso:country":"GB",
    "sg:address":"211 London Road",
    "sg:city":"Mitcham",
    "sg:classifiers":[
        {
            "category":"Home & Garden",
            "subcategory":"Furniture",
            "type":"Retail Goods"
        }
    ],
    "sg:postcode":"CR4 2JD",
    "sg:province":"Greater London",
    "wof:name":"Emmerdale Furnishings",
    "wof:placetype":"venue"
},
  "geometry": {"coordinates":[-0.1636649966,51.4069099426],"type":"Point"}
}