{
  "type": "Feature",
  "properties": {
    "addr:full":"6 Glasgow Road Glasgow East Renfrewshire G76 0JQ",
    "addr:housenumber":"6",
    "addr:postcode":"g76 0jq",
    "addr:street":"Glasgow Road",
    "iso:country":"GB",
    "sg:address":"6 Glasgow Road",
    "sg:city":"Glasgow",
    "sg:classifiers":[
        {
            "category":"Cafe",
            "type":"Food & Drink"
        }
    ],
    "sg:phone":"+44 1355 302094",
    "sg:postcode":"G76 0JQ",
    "sg:province":"East Renfrewshire",
    "sg:tags":[
        "tea",
        "snack",
        "bar",
        "room"
    ],
    "wof:name":"The Hamlet Coffee Shop",
    "wof:placetype":"venue"
},
  "geometry": {"coordinates":[-4.276586,55.743855],"type":"Point"}
}