{
  "type": "Feature",
  "properties": {
    "iso:country":"GB",
    "sg:address":"Unit B6, Hortonwood 10",
    "sg:city":"Telford",
    "sg:classifiers":[
        {
            "category":"Building & Trades",
            "subcategory":"Construction",
            "type":"Services"
        }
    ],
    "sg:phone":"+44 1952 676555",
    "sg:postcode":"TF1 7ES",
    "sg:province":"Shropshire",
    "sg:tags":[
        "roofing",
        "contracting"
    ],
    "sg:website":"http://www.ironbridgeconstruction.co.uk",
    "wof:name":"Ironbridge Construction Ltd",
    "wof:placetype":"venue"
},
  "geometry": {"coordinates":[-2.466704,52.71553],"type":"Point"}
}