{
  "type": "Feature",
  "properties": {
    "iso:country":"GB",
    "sg:address":"22 Warburton Road",
    "sg:city":"Poole",
    "sg:classifiers":[
        {
            "category":"Building & Trades",
            "subcategory":"Construction",
            "type":"Services"
        }
    ],
    "sg:phone":"+44 1202 681366",
    "sg:postcode":"BH17 8SF",
    "sg:province":"Dorset",
    "sg:tags":[
        "builder"
    ],
    "wof:name":"Andrew J Fry",
    "wof:placetype":"venue"
},
  "geometry": {"coordinates":[-1.965610981,50.7436714172],"type":"Point"}
}