{
  "type": "Feature",
  "properties": {
    "addr:full":"Cricketers Way Basildon Essex SS13 1SA",
    "addr:postcode":"ss13 1sa",
    "addr:street":"Cricketers Way",
    "iso:country":"GB",
    "sg:address":"Cricketers Way",
    "sg:city":"Basildon",
    "sg:classifiers":[
        {
            "category":"Home & Garden",
            "subcategory":"Furniture",
            "type":"Retail Goods"
        }
    ],
    "sg:phone":"+44 1268 280290",
    "sg:postcode":"SS13 1SA",
    "sg:province":"Essex",
    "wof:name":"Land of Leather",
    "wof:placetype":"venue"
},
  "geometry": {"coordinates":[0.5027629733,51.5911102295],"type":"Point"}
}