{
  "type": "Feature",
  "properties": {
    "addr:full":"107 Alphington Road Exeter Devon EX2 8JD",
    "addr:housenumber":"107",
    "addr:postcode":"ex2 8jd",
    "addr:street":"Alphington Road",
    "iso:country":"GB",
    "sg:address":"107 Alphington Road",
    "sg:city":"Exeter",
    "sg:classifiers":[
        {
            "category":"Travel",
            "subcategory":"Hotels & Motels",
            "type":"Entertainment"
        }
    ],
    "sg:phone":"+44 1392 272093",
    "sg:postcode":"EX2 8JD",
    "sg:province":"Devon",
    "wof:name":"Crawford Hotel",
    "wof:placetype":"venue"
},
  "geometry": {"coordinates":[-3.5377469063,50.7104911804],"type":"Point"}
}