{
  "type": "Feature",
  "properties": {
    "addr:full":"3 Gilbert Street London Greater London W1K 5HA",
    "addr:housenumber":"3",
    "addr:postcode":"w1k 5ha",
    "addr:street":"Gilbert Street",
    "iso:country":"GB",
    "sg:address":"3 Gilbert Street",
    "sg:city":"London",
    "sg:classifiers":[
        {
            "category":"Shopping",
            "subcategory":"Computers & Home Electronics",
            "type":"Retail Goods"
        }
    ],
    "sg:phone":"+44 20 7495 7005",
    "sg:postcode":"W1K 5HA",
    "sg:province":"Greater London",
    "sg:tags":[
        "tape",
        "video"
    ],
    "wof:name":"C C K Video Services Ltd.",
    "wof:placetype":"venue"
},
  "geometry": {"coordinates":[-0.150169,51.5136222839],"type":"Point"}
}