{
  "type": "Feature",
  "properties": {
    "iso:country":"GB",
    "sg:address":"57 High St, Walkern",
    "sg:city":"Stevenage",
    "sg:classifiers":[
        {
            "category":"Bars & Pubs",
            "type":"Food & Drink"
        }
    ],
    "sg:phone":"+44 1438 861321",
    "sg:postcode":"SG2 7NX",
    "sg:province":"Hertfordshire",
    "sg:tags":[
        "pubs",
        "inn"
    ],
    "wof:name":"The Yew Tree",
    "wof:placetype":"venue"
},
  "geometry": {"coordinates":[-0.126845,51.920025],"type":"Point"}
}