{
  "type": "Feature",
  "properties": {
    "iso:country":"GB",
    "sg:address":"15 Quarry Close, Alcombe",
    "sg:city":"Minehead",
    "sg:classifiers":[
        {
            "category":"Building & Trades",
            "subcategory":"Plumbing",
            "type":"Services"
        }
    ],
    "sg:phone":"+44 1643 705423",
    "sg:postcode":"TA24 6ED",
    "sg:province":"Somerset",
    "sg:tags":[
        "central",
        "heating"
    ],
    "wof:name":"Davis Alan & Son",
    "wof:placetype":"venue"
},
  "geometry": {"coordinates":[-3.46905,51.195564],"type":"Point"}
}