{
  "type": "Feature",
  "properties": {
    "iso:country":"GB",
    "sg:address":"Myrtle Close",
    "sg:city":"Penarth",
    "sg:classifiers":[
        {
            "category":"Health Services",
            "subcategory":"Nursing And Care Facility",
            "type":"Services"
        },
        {
            "category":"Social Services",
            "subcategory":"Retirement Home",
            "type":"Services"
        }
    ],
    "sg:phone":"+44 29 2070 9331",
    "sg:postcode":"CF64 3NQ",
    "sg:province":"The Vale of Glamorgan",
    "sg:tags":[
        "residential"
    ],
    "wof:name":"Ty Dewi Sant",
    "wof:placetype":"venue"
},
  "geometry": {"coordinates":[-3.192381,51.432186],"type":"Point"}
}