{
  "type": "Feature",
  "properties": {
    "addr:full":"13 Station Rd, Keynsham Bristol City of Bristol BS31 2BH",
    "addr:housenumber":"13",
    "addr:postcode":"bs31 2bh",
    "addr:street":"Station Rd",
    "iso:country":"GB",
    "sg:address":"13 Station Rd, Keynsham",
    "sg:city":"Bristol",
    "sg:classifiers":[
        {
            "category":"Personal",
            "type":"Services"
        }
    ],
    "sg:postcode":"BS31 2BH",
    "sg:province":"City of Bristol",
    "sg:tags":[
        "wedding"
    ],
    "wof:name":"Cameo Brides",
    "wof:placetype":"venue"
},
  "geometry": {"coordinates":[-2.4988789558,51.417804718],"type":"Point"}
}