{
  "type": "Feature",
  "properties": {
    "addr:full":"59 New Broadway London Greater London W5 5AH",
    "addr:housenumber":"59",
    "addr:postcode":"w5 5ah",
    "addr:street":"New Broadway",
    "iso:country":"GB",
    "sg:address":"59 New Broadway",
    "sg:city":"London",
    "sg:classifiers":[
        {
            "category":"Professional",
            "subcategory":"Research",
            "type":"Services"
        }
    ],
    "sg:postcode":"W5 5AH",
    "sg:province":"Greater London",
    "sg:tags":[
        "market"
    ],
    "wof:name":"A B M",
    "wof:placetype":"venue"
},
  "geometry": {"coordinates":[-0.307053,51.512714],"type":"Point"}
}