{
  "type": "Feature",
  "properties": {
    "iso:country":"GB",
    "sg:address":"Rainbow Drive, Leadenhall",
    "sg:city":"Milton Keynes",
    "sg:classifiers":[
        {
            "category":"Farming",
            "subcategory":"Nursery",
            "type":"Manufacturing & Wholesale Goods"
        }
    ],
    "sg:phone":"+44 1908 678562",
    "sg:postcode":"MK6 5EH",
    "sg:province":"Buckinghamshire",
    "sg:tags":[
        "creche"
    ],
    "wof:name":"Woughton Day Nursery",
    "wof:placetype":"venue"
},
  "geometry": {"coordinates":[-0.7487840056,52.0297241211],"type":"Point"}
}