{
  "type": "Feature",
  "properties": {
    "addr:full":"Canal Road Gravesend Kent DA12 2RS",
    "addr:postcode":"da12 2rs",
    "addr:street":"Canal Road",
    "iso:country":"GB",
    "sg:address":"Canal Road",
    "sg:city":"Gravesend",
    "sg:classifiers":[
        {
            "category":"Bars & Pubs",
            "type":"Food & Drink"
        },
        {
            "category":"Community Center",
            "subcategory":"Social",
            "type":"Public Place"
        }
    ],
    "sg:phone":"+44 1474 326931",
    "sg:postcode":"DA12 2RS",
    "sg:province":"Kent",
    "sg:tags":[
        "pubs",
        "house",
        "inn",
        "activity"
    ],
    "wof:name":"Canal Tavern",
    "wof:placetype":"venue"
},
  "geometry": {"coordinates":[0.382835,51.442577],"type":"Point"}
}