{
  "type": "Feature",
  "properties": {
    "addr:full":"25 Otterburn Av Newcastle Upon Tyne Tyne and Wear NE3 4RR",
    "addr:housenumber":"25",
    "addr:postcode":"ne3 4rr",
    "addr:street":"Otterburn Av",
    "iso:country":"GB",
    "sg:address":"25 Otterburn Av",
    "sg:city":"Newcastle Upon Tyne",
    "sg:classifiers":[
        {
            "category":"Shopping",
            "subcategory":"Clothing, Apparel, & Fashions",
            "type":"Retail Goods"
        }
    ],
    "sg:phone":"+44 191 285 6455",
    "sg:postcode":"NE3 4RR",
    "sg:province":"Tyne and Wear",
    "sg:tags":[
        "accessory"
    ],
    "wof:name":"Gild The Lily",
    "wof:placetype":"venue"
},
  "geometry": {"coordinates":[-1.6354600191,55.0022392273],"type":"Point"}
}