{
  "type": "Feature",
  "properties": {
    "addr:full":"2 Tilsworth Road Beaconsfield Buckinghamshire HP9 1TR",
    "addr:housenumber":"2",
    "addr:postcode":"hp9 1tr",
    "addr:street":"Tilsworth Road",
    "iso:country":"GB",
    "sg:address":"2 Tilsworth Road",
    "sg:city":"Beaconsfield",
    "sg:classifiers":[
        {
            "category":"Personal",
            "subcategory":"Tanning Parlor",
            "type":"Services"
        }
    ],
    "sg:phone":"+44 1494 678977",
    "sg:postcode":"HP9 1TR",
    "sg:province":"Buckinghamshire",
    "sg:tags":[
        "sunbeds"
    ],
    "wof:name":"Leisuretan Sunbeds",
    "wof:placetype":"venue"
},
  "geometry": {"coordinates":[-0.6513990164,51.6005439758],"type":"Point"}
}