{
  "type": "Feature",
  "properties": {
    "addr:full":"Leckwith Works, 6 Hadfield Rd Cardiff Cardiff CF1 8AQ",
    "addr:housenumber":"6",
    "addr:postcode":"cf1 8aq",
    "addr:street":"Hadfield Rd",
    "iso:country":"GB",
    "sg:address":"Leckwith Works, 6 Hadfield Rd",
    "sg:city":"Cardiff",
    "sg:classifiers":[
        {
            "category":"Personal",
            "type":"Services"
        }
    ],
    "sg:phone":"+44 1525 372957",
    "sg:postcode":"CF1 8AQ",
    "sg:province":"Cardiff",
    "sg:tags":[
        "delivery"
    ],
    "wof:name":"Colne Vehicles Deliveries Ltd",
    "wof:placetype":"venue"
},
  "geometry": {"coordinates":[-3.18067,51.481258],"type":"Point"}
}