{
  "type": "Feature",
  "properties": {
    "iso:country":"GB",
    "sg:address":"24-30 Station Road",
    "sg:city":"London",
    "sg:classifiers":[
        {
            "category":"Professional",
            "subcategory":"Printing & Photocopies",
            "type":"Services"
        }
    ],
    "sg:phone":"+44 20 8659 1221",
    "sg:postcode":"SE20 7BQ",
    "sg:province":"Greater London",
    "sg:tags":[
        "printer"
    ],
    "wof:name":"Copyfax Business Equipment Ltd.",
    "wof:placetype":"venue"
},
  "geometry": {"coordinates":[-0.0556100011,51.4191932678],"type":"Point"}
}