{
  "type": "Feature",
  "properties": {
    "addr:full":"Willoughby Street Nottingham Nottinghamshire NG7 1RQ",
    "addr:postcode":"ng7 1rq",
    "addr:street":"Willoughby Street",
    "iso:country":"GB",
    "sg:address":"Willoughby Street",
    "sg:city":"Nottingham",
    "sg:classifiers":[
        {
            "category":"Community Center",
            "type":"Public Place"
        }
    ],
    "sg:phone":"+44 115 915 0095",
    "sg:postcode":"NG7 1RQ",
    "sg:province":"Nottinghamshire",
    "sg:tags":[
        "recreation",
        "leisure",
        "centre"
    ],
    "wof:name":"Lenton Leisure Centre",
    "wof:placetype":"venue"
},
  "geometry": {"coordinates":[-1.171653986,52.9485054016],"type":"Point"}
}