{
  "type": "Feature",
  "properties": {
    "iso:country":"GB",
    "sg:address":"20 Chamber Road, Shaw",
    "sg:city":"Oldham",
    "sg:classifiers":[
        {
            "category":"Home & Garden",
            "subcategory":"Carpets & Floor Coverings",
            "type":"Retail Goods"
        }
    ],
    "sg:postcode":"OL2 7AR",
    "sg:province":"Lancashire",
    "sg:tags":[
        "carpets",
        "retailer",
        "rug",
        "matting"
    ],
    "wof:name":"D WOLSTENHOLME",
    "wof:placetype":"venue"
},
  "geometry": {"coordinates":[-2.1000859737,53.5785484314],"type":"Point"}
}