{
  "type": "Feature",
  "properties": {
    "iso:country":"GB",
    "sg:address":"Drumacre Lane East, Longton",
    "sg:city":"Preston",
    "sg:classifiers":[
        {
            "category":"Transit Center",
            "subcategory":"Passenger",
            "type":"Transportation"
        },
        {
            "category":"Retail",
            "subcategory":"Pet Boarding",
            "type":"Services"
        }
    ],
    "sg:phone":"+44 1772 614715",
    "sg:postcode":"PR4 4SD",
    "sg:province":"Lancashire",
    "sg:tags":[
        "kennel",
        "catteries"
    ],
    "wof:name":"Morningside Boarding Kennels",
    "wof:placetype":"venue"
},
  "geometry": {"coordinates":[-2.7575290203,53.7176856995],"type":"Point"}
}