{
  "type": "Feature",
  "properties": {
    "addr:full":"2 Carrier Street Halifax West Yorkshire HX1 1DU",
    "addr:housenumber":"2",
    "addr:postcode":"hx1 1du",
    "addr:street":"Carrier Street",
    "iso:country":"GB",
    "sg:address":"2 Carrier Street",
    "sg:city":"Halifax",
    "sg:classifiers":[
        {
            "category":"Home & Garden",
            "subcategory":"Home Furnishings",
            "type":"Retail Goods"
        },
        {
            "category":"Manufacturing",
            "subcategory":"Textiles",
            "type":"Manufacturing & Wholesale Goods"
        }
    ],
    "sg:phone":"+44 1422 330993",
    "sg:postcode":"HX1 1DU",
    "sg:province":"West Yorkshire",
    "sg:tags":[
        "blind",
        "made-up",
        "fitting",
        "curtain"
    ],
    "wof:name":"Legacy Interiors",
    "wof:placetype":"venue"
},
  "geometry": {"coordinates":[-1.8592540026,53.7218055725],"type":"Point"}
}