{
  "type": "Feature",
  "properties": {
    "addr:full":"Continence Advisory Service, Bancroft Rd Whitechapel Greater London E1 4DG",
    "addr:postcode":"e1 4dg",
    "addr:street":"Bancroft Rd",
    "iso:country":"GB",
    "sg:address":"Continence Advisory Service, Bancroft Rd",
    "sg:city":"Whitechapel",
    "sg:classifiers":[
        {
            "category":"Health Services",
            "subcategory":"Clinic",
            "type":"Services"
        }
    ],
    "sg:phone":"+44 20 7377 7887",
    "sg:postcode":"E1 4DG",
    "sg:province":"Greater London",
    "sg:tags":[
        "nh"
    ],
    "wof:name":"Tower Hamlets Healthcare NHS Trust",
    "wof:placetype":"venue"
},
  "geometry": {"coordinates":[-0.0426299982,51.5244483948],"type":"Point"}
}