{
  "type": "Feature",
  "properties": {
    "iso:country":"GB",
    "sg:address":"28 High St, New Bradwell",
    "sg:city":"Milton Keynes",
    "sg:classifiers":[
        {
            "category":"Shopping",
            "subcategory":"Stationery & Office Supplies",
            "type":"Retail Goods"
        }
    ],
    "sg:phone":"+44 1908 318400",
    "sg:postcode":"MK13 0BT",
    "sg:province":"Buckinghamshire",
    "sg:tags":[
        "item",
        "promotional"
    ],
    "wof:name":"Especially For You",
    "wof:placetype":"venue"
},
  "geometry": {"coordinates":[-0.790979,52.065056],"type":"Point"}
}