{
  "type": "Feature",
  "properties": {
    "addr:full":"Marina, Cambrai Avenue Chichester West Sussex PO19 2JY",
    "addr:postcode":"po19 2jy",
    "addr:street":"Avenue",
    "iso:country":"GB",
    "sg:address":"Marina, Cambrai Avenue",
    "sg:city":"Chichester",
    "sg:classifiers":[
        {
            "category":"Health Services",
            "subcategory":"Chiropractor",
            "type":"Services"
        }
    ],
    "sg:phone":"+44 1243 780451",
    "sg:postcode":"PO19 2JY",
    "sg:province":"West Sussex",
    "wof:name":"Holistic Bodytherapy",
    "wof:placetype":"venue"
},
  "geometry": {"coordinates":[-0.7754290104,50.8361663818],"type":"Point"}
}