{
  "type": "Feature",
  "properties": {
    "addr:full":"7 Cumberland Way Leicester Leicestershire LE9 8HX",
    "addr:housenumber":"7",
    "addr:postcode":"le9 8hx",
    "addr:street":"Cumberland Way",
    "iso:country":"GB",
    "sg:address":"7 Cumberland Way",
    "sg:city":"Leicester",
    "sg:classifiers":[
        {
            "category":"Food & Beverages",
            "subcategory":"Liquor & Beverages",
            "type":"Retail Goods"
        }
    ],
    "sg:phone":"+44 1455 851000",
    "sg:postcode":"LE9 8HX",
    "sg:province":"Leicestershire",
    "sg:tags":[
        "beer",
        "spirit",
        "wines"
    ],
    "wof:name":"Barwell Beer",
    "wof:placetype":"venue"
},
  "geometry": {"coordinates":[-1.34998,52.571964],"type":"Point"}
}