{
  "type": "Feature",
  "properties": {
    "addr:full":"140 Kings Road Bury St Edmunds Suffolk IP33 3DP",
    "addr:housenumber":"140",
    "addr:postcode":"ip33 3dp",
    "addr:street":"Kings Road",
    "iso:country":"GB",
    "sg:address":"140 Kings Road",
    "sg:city":"Bury St Edmunds",
    "sg:classifiers":[
        {
            "category":"Building & Trades",
            "subcategory":"Construction",
            "type":"Services"
        }
    ],
    "sg:phone":"+44 1284 754560",
    "sg:postcode":"IP33 3DP",
    "sg:province":"Suffolk",
    "sg:tags":[
        "builder"
    ],
    "wof:name":"Fenner Builders",
    "wof:placetype":"venue"
},
  "geometry": {"coordinates":[0.7070320249,52.2446250916],"type":"Point"}
}