{
  "type": "Feature",
  "properties": {
    "addr:full":"12 Oaklea, Ash Vale Aldershot Hampshire GU12 5HP",
    "addr:housenumber":"12",
    "addr:postcode":"gu12 5hp",
    "addr:street":"Oaklea Ash Vale",
    "iso:country":"GB",
    "sg:address":"12 Oaklea, Ash Vale",
    "sg:city":"Aldershot",
    "sg:classifiers":[
        {
            "category":"Building & Trades",
            "subcategory":"Landscaping Services",
            "type":"Services"
        }
    ],
    "sg:phone":"+44 1252 311877",
    "sg:postcode":"GU12 5HP",
    "sg:province":"Hampshire",
    "sg:tags":[
        "gardening"
    ],
    "wof:name":"Woburn Landscapes",
    "wof:placetype":"venue"
},
  "geometry": {"coordinates":[-0.7233769894,51.2598686218],"type":"Point"}
}