{
  "type": "Feature",
  "properties": {
    "iso:country":"GB",
    "sg:address":"South Bridge Street",
    "sg:city":"Bathgate",
    "sg:classifiers":[
        {
            "category":"Government",
            "subcategory":"Police Station",
            "type":"Public Place"
        }
    ],
    "sg:phone":"+44 1506 633033",
    "sg:postcode":"EH48 1TW",
    "sg:province":"West Lothian",
    "sg:tags":[
        "support"
    ],
    "wof:name":"Lothian and Borders Police Station",
    "wof:placetype":"venue"
},
  "geometry": {"coordinates":[-3.644138,55.901806],"type":"Point"}
}