{
  "type": "Feature",
  "properties": {
    "addr:full":"17 Padgate La Warrington Cheshire WA1 3RS",
    "addr:housenumber":"17",
    "addr:postcode":"wa1 3rs",
    "addr:street":"Padgate La Warrington Cheshire",
    "iso:country":"GB",
    "sg:address":"17 Padgate La",
    "sg:city":"Warrington",
    "sg:classifiers":[
        {
            "category":"Personal",
            "subcategory":"Nail Salon",
            "type":"Services"
        }
    ],
    "sg:postcode":"WA1 3RS",
    "sg:province":"Cheshire",
    "sg:tags":[
        "solarium",
        "tanning"
    ],
    "wof:name":"Anderson,Mike,",
    "wof:placetype":"venue"
},
  "geometry": {"coordinates":[-2.5731430054,53.3975296021],"type":"Point"}
}