{
  "type": "Feature",
  "properties": {
    "iso:country":"GB",
    "sg:address":"Warden, King Rdm",
    "sg:city":"Herne Bay",
    "sg:classifiers":[
        {
            "category":"Social Services",
            "subcategory":"Adult Care",
            "type":"Services"
        }
    ],
    "sg:postcode":"CT6 5RL",
    "sg:province":"Kent",
    "sg:tags":[
        "housing",
        "sheltered"
    ],
    "wof:name":"Countrywide Rentals 1 Ltd.",
    "wof:placetype":"venue"
},
  "geometry": {"coordinates":[1.1251000166,51.3712158203],"type":"Point"}
}