{
  "type": "Feature",
  "properties": {
    "iso:country":"GB",
    "sg:address":"Junction Rd, Wordsley",
    "sg:city":"Stourbridge",
    "sg:classifiers":[
        {
            "category":"Shopping",
            "subcategory":"Bicycles & Sporting Goods",
            "type":"Retail Goods"
        }
    ],
    "sg:phone":"+44 1384 395278",
    "sg:postcode":"DY8 4YJ",
    "sg:province":"Staffordshire",
    "sg:tags":[
        "riding",
        "saddlery",
        "wear"
    ],
    "wof:name":"Wordsley Saddlery Ltd",
    "wof:placetype":"venue"
},
  "geometry": {"coordinates":[-2.156527,52.472591],"type":"Point"}
}