{
  "type": "Feature",
  "properties": {
    "iso:country":"GB",
    "sg:address":"152 Bethnal Green Road",
    "sg:city":"London",
    "sg:classifiers":[
        {
            "category":"Personal",
            "subcategory":"Skin Care",
            "type":"Services"
        }
    ],
    "sg:phone":"+44 20 7749 9930",
    "sg:postcode":"E2 6DG",
    "sg:province":"Greater London",
    "sg:tags":[
        "leather",
        "merchant"
    ],
    "wof:name":"Task 2000 Ltd.",
    "wof:placetype":"venue"
},
  "geometry": {"coordinates":[-0.069631,51.525539],"type":"Point"}
}