{
  "type": "Feature",
  "properties": {
    "addr:full":"33-35 Aberdeen Walk Scarborough North Yorkshire YO11 1BD",
    "addr:housenumber":"33-35",
    "addr:postcode":"yo11 1bd",
    "addr:street":"Aberdeen Walk",
    "iso:country":"GB",
    "sg:address":"33-35 Aberdeen Walk",
    "sg:city":"Scarborough",
    "sg:classifiers":[
        {
            "category":"Shopping",
            "subcategory":"Department Store",
            "type":"Retail Goods"
        }
    ],
    "sg:postcode":"YO11 1BD",
    "sg:province":"North Yorkshire",
    "wof:name":"Price Right",
    "wof:placetype":"venue"
},
  "geometry": {"coordinates":[-0.4030860066,54.2829437256],"type":"Point"}
}