{
  "type": "Feature",
  "properties": {
    "iso:country":"GB",
    "sg:address":"9 Charleston Road",
    "sg:city":"Eastbourne",
    "sg:classifiers":[
        {
            "category":"Health Services",
            "subcategory":"Health Practitioner",
            "type":"Services"
        }
    ],
    "sg:phone":"+44 1323 733194",
    "sg:postcode":"BN21 1SE",
    "sg:province":"East Sussex",
    "sg:tags":[
        "physiotherapist"
    ],
    "wof:name":"Concepts Physiotherapy",
    "wof:placetype":"venue"
},
  "geometry": {"coordinates":[0.2618370056,50.774810791],"type":"Point"}
}