{
  "type": "Feature",
  "properties": {
    "iso:country":"GB",
    "sg:address":"68 High St",
    "sg:city":"Dingwall",
    "sg:classifiers":[
        {
            "category":"Professional",
            "subcategory":"Business Services",
            "type":"Services"
        }
    ],
    "sg:postcode":"IV15 9RY",
    "sg:province":"Highland",
    "sg:tags":[
        "management",
        "holding",
        "pub"
    ],
    "wof:name":"Tobar Mor Ltd",
    "wof:placetype":"venue"
},
  "geometry": {"coordinates":[-4.4271788597,57.5953788757],"type":"Point"}
}