{
  "type": "Feature",
  "properties": {
    "addr:full":"72-74 Dyke Rd, Mews Dyke Rd Brighton East Sussex BN1 3RB",
    "addr:housenumber":"72-74",
    "addr:postcode":"bn1 3rb",
    "addr:street":"Dyke Rd Mews Dyke Rd",
    "iso:country":"GB",
    "sg:address":"72-74 Dyke Rd, Mews Dyke Rd",
    "sg:city":"Brighton",
    "sg:classifiers":[
        {
            "category":"Autos & Motor Vehicles",
            "subcategory":"Automobile Sales",
            "type":"Retail Goods"
        }
    ],
    "sg:phone":"+44 1273 822345",
    "sg:postcode":"BN1 3RB",
    "sg:province":"East Sussex",
    "sg:tags":[
        "car",
        "specialist",
        "sales",
        "classic"
    ],
    "wof:name":"Independently Italian Ltd",
    "wof:placetype":"venue"
},
  "geometry": {"coordinates":[-0.1470669955,50.8294715881],"type":"Point"}
}