{
  "type": "Feature",
  "properties": {
    "addr:full":"108-110 Edgware Road London Greater London W2 2EA",
    "addr:housenumber":"108-110",
    "addr:postcode":"w2 2ea",
    "addr:street":"Edgware Road",
    "iso:country":"GB",
    "sg:address":"108-110 Edgware Road",
    "sg:city":"London",
    "sg:classifiers":[
        {
            "category":"Shopping",
            "subcategory":"Clothing, Apparel, & Fashions",
            "type":"Retail Goods"
        },
        {
            "category":"Shopping",
            "subcategory":"Shoes",
            "type":"Retail Goods"
        }
    ],
    "sg:phone":"+44 20 7402 7776",
    "sg:postcode":"W2 2EA",
    "sg:province":"Greater London",
    "sg:tags":[
        "shop"
    ],
    "wof:name":"Reachmead Ltd.",
    "wof:placetype":"venue"
},
  "geometry": {"coordinates":[-0.167033,51.517883],"type":"Point"}
}