{
  "type": "Feature",
  "properties": {
    "addr:full":"Abbetts La Camberley Berkshire GU15 2PR",
    "addr:postcode":"gu15 2pr",
    "addr:street":"La",
    "iso:country":"GB",
    "sg:address":"Abbetts La",
    "sg:city":"Camberley",
    "sg:classifiers":[
        {
            "category":"Communications",
            "subcategory":"Film & Video Production",
            "type":"Services"
        },
        {
            "category":"Professional",
            "subcategory":"Art Services",
            "type":"Services"
        }
    ],
    "sg:postcode":"GU15 2PR",
    "sg:province":"Berkshire",
    "sg:tags":[
        "photographer",
        "illustrator",
        "artist"
    ],
    "wof:name":"Shepherd,Pia,",
    "wof:placetype":"venue"
},
  "geometry": {"coordinates":[-0.7539740205,51.3271141052],"type":"Point"}
}