{
  "type": "Feature",
  "properties": {
    "addr:full":"Bath Factory Estate, Norwood Rd Herne Hill Greater London SE24 9AJ",
    "addr:postcode":"se24 9aj",
    "addr:street":"Norwood Rd",
    "iso:country":"GB",
    "sg:address":"Bath Factory Estate, Norwood Rd",
    "sg:city":"Herne Hill",
    "sg:classifiers":[
        {
            "category":"Military Area",
            "subcategory":"Air Force Base",
            "type":"Public Place"
        }
    ],
    "sg:phone":"+44 20 8671 1349",
    "sg:postcode":"SE24 9AJ",
    "sg:province":"Greater London",
    "sg:tags":[
        "supplier",
        "mnfrs",
        "plaster"
    ],
    "wof:name":"Miles & Wild Mouldings",
    "wof:placetype":"venue"
},
  "geometry": {"coordinates":[-0.099584,51.455086],"type":"Point"}
}