{
  "type": "Feature",
  "properties": {
    "iso:country":"GB",
    "sg:address":"2 Chapel Street, Mumbles",
    "sg:city":"Swansea",
    "sg:classifiers":[
        {
            "category":"Retail",
            "subcategory":"Repair Shop",
            "type":"Services"
        }
    ],
    "sg:postcode":"SA3 4NH",
    "sg:province":"Swansea",
    "sg:tags":[
        "clocks",
        "watch"
    ],
    "wof:name":"Chimes of Mumbles",
    "wof:placetype":"venue"
},
  "geometry": {"coordinates":[-4.001288,51.574543],"type":"Point"}
}