{
  "type": "Feature",
  "properties": {
    "iso:country":"GB",
    "sg:address":"16 Market Street",
    "sg:city":"Ulverston",
    "sg:classifiers":[
        {
            "category":"Travel",
            "subcategory":"Travel Agent",
            "type":"Entertainment"
        }
    ],
    "sg:phone":"+44 1229 586663",
    "sg:postcode":"LA12 7LR",
    "sg:province":"Cumbria",
    "sg:tags":[
        "agency",
        "activity"
    ],
    "wof:name":"Ulverston Travel",
    "wof:placetype":"venue"
},
  "geometry": {"coordinates":[-3.09532,54.195999],"type":"Point"}
}