{
  "type": "Feature",
  "properties": {
    "addr:full":"8 Cleehill Rd Birkenhead Merseyside L42 8PA",
    "addr:housenumber":"8",
    "addr:postcode":"l42 8pa",
    "addr:street":"Cleehill Rd",
    "iso:country":"GB",
    "sg:address":"8 Cleehill Rd",
    "sg:city":"Birkenhead",
    "sg:classifiers":[
        {
            "category":"Professional",
            "subcategory":"Engineering",
            "type":"Services"
        }
    ],
    "sg:phone":"+44 151 609 0972",
    "sg:postcode":"L42 8PA",
    "sg:province":"Merseyside",
    "sg:tags":[
        "underpinning",
        "foundation",
        "engineer"
    ],
    "wof:name":"C D Groundworks",
    "wof:placetype":"venue"
},
  "geometry": {"coordinates":[-3.0339939594,53.3688430786],"type":"Point"}
}