{
  "type": "Feature",
  "properties": {
    "addr:full":"125 Cannon Workshops, 3 Cannon Drive London Greater London E14 4AS",
    "addr:housenumber":"125;3",
    "addr:postcode":"e14 4as",
    "addr:street":"Workshops;Cannon Drive",
    "iso:country":"GB",
    "sg:address":"125 Cannon Workshops, 3 Cannon Drive",
    "sg:city":"London",
    "sg:classifiers":[
        {
            "category":"Professional",
            "subcategory":"Management & Consulting",
            "type":"Services"
        }
    ],
    "sg:phone":"+44 20 7536 0755",
    "sg:postcode":"E14 4AS",
    "sg:province":"Greater London",
    "sg:tags":[
        "fire",
        "consultant",
        "protection"
    ],
    "wof:name":"How Fire Maintenance",
    "wof:placetype":"venue"
},
  "geometry": {"coordinates":[-0.0257799998,51.5077285767],"type":"Point"}
}