{
  "type": "Feature",
  "properties": {
    "addr:full":"33 Duke Street Brighton East Sussex BN1 1AG",
    "addr:housenumber":"33",
    "addr:postcode":"bn1 1ag",
    "addr:street":"Duke Street",
    "iso:country":"GB",
    "sg:address":"33 Duke Street",
    "sg:city":"Brighton",
    "sg:classifiers":[
        {
            "category":"Shopping",
            "subcategory":"Clothing, Apparel, & Fashions",
            "type":"Retail Goods"
        }
    ],
    "sg:postcode":"BN1 1AG",
    "sg:province":"East Sussex",
    "sg:tags":[
        "menswear"
    ],
    "wof:name":"Lecoste",
    "wof:placetype":"venue"
},
  "geometry": {"coordinates":[-0.142834,50.822922],"type":"Point"}
}