{
  "type": "Feature",
  "properties": {
    "addr:full":"4th Floor Chesham House, 29-30 Warwick St West End Hampshire W1R5RD",
    "addr:housenumber":"4th floor chesham;29-30",
    "addr:postcode":"w1r5rd",
    "addr:street":"Warwick St",
    "iso:country":"GB",
    "sg:address":"4th Floor Chesham House, 29-30 Warwick St",
    "sg:city":"West End",
    "sg:classifiers":[
        {
            "category":"Organizations",
            "subcategory":"Non-profit Organization",
            "type":"Services"
        }
    ],
    "sg:phone":"+44 20 7437 4334",
    "sg:postcode":"W1R5RD",
    "sg:province":"Hampshire",
    "sg:tags":[
        "organisation",
        "voluntary",
        "charity"
    ],
    "wof:name":"Prison Charity Shop Trust",
    "wof:placetype":"venue"
},
  "geometry": {"coordinates":[-0.1380349994,51.5108184814],"type":"Point"}
}