{
  "type": "Feature",
  "properties": {
    "iso:country":"GB",
    "sg:address":"201 Abbey Street",
    "sg:city":"Rugby",
    "sg:classifiers":[
        {
            "category":"Autos & Motor Vehicles",
            "subcategory":"Automobile Sales",
            "type":"Retail Goods"
        }
    ],
    "sg:phone":"+44 1788 337558",
    "sg:postcode":"CV21 3LW",
    "sg:province":"Warwickshire",
    "sg:tags":[
        "car"
    ],
    "wof:name":"Abbey Car Centre",
    "wof:placetype":"venue"
},
  "geometry": {"coordinates":[-1.242751956,52.3765449524],"type":"Point"}
}