{
  "type": "Feature",
  "properties": {
    "addr:full":"Unit 2 Hoddersdon Industrial Centre, Pindar Road Hoddesdon Essex EN11 0DD",
    "addr:housenumber":"unit 2",
    "addr:postcode":"en11 0dd",
    "addr:street":"Hoddersdon;Pindar Road",
    "iso:country":"GB",
    "sg:address":"Unit 2 Hoddersdon Industrial Centre, Pindar Road",
    "sg:city":"Hoddesdon",
    "sg:classifiers":[
        {
            "category":"Professional",
            "type":"Services"
        }
    ],
    "sg:postcode":"EN11 0DD",
    "sg:province":"Essex",
    "sg:tags":[
        "entertainer"
    ],
    "wof:name":"Impeyan Productions",
    "wof:placetype":"venue"
},
  "geometry": {"coordinates":[-0.0132550001,51.7678413391],"type":"Point"}
}