{
  "type": "Feature",
  "properties": {
    "iso:country":"GB",
    "sg:address":"54 Station Approach",
    "sg:city":"West Byfleet",
    "sg:classifiers":[
        {
            "category":"Professional",
            "subcategory":"Management & Consulting",
            "type":"Services"
        }
    ],
    "sg:phone":"+44 1932 353885",
    "sg:postcode":"KT14 6NE",
    "sg:province":"Surrey",
    "sg:tags":[
        "consultant",
        "specialist"
    ],
    "wof:name":"Cloud Nine",
    "wof:placetype":"venue"
},
  "geometry": {"coordinates":[-0.505012,51.339165],"type":"Point"}
}