{
  "type": "Feature",
  "properties": {
    "iso:country":"GB",
    "sg:address":"21 South Crescent, Portpatrick",
    "sg:city":"Stranraer",
    "sg:classifiers":[
        {
            "category":"Travel",
            "subcategory":"Hotels & Motels",
            "type":"Entertainment"
        }
    ],
    "sg:postcode":"DG9 8JR",
    "sg:province":"Dumfries and Galloway",
    "sg:tags":[
        "house",
        "guest"
    ],
    "wof:name":"Carlton Guest House",
    "wof:placetype":"venue"
},
  "geometry": {"coordinates":[-5.116392,54.841526],"type":"Point"}
}