{
  "type": "Feature",
  "properties": {
    "iso:country":"GB",
    "sg:address":"51 Durham Street",
    "sg:city":"Gosport",
    "sg:classifiers":[
        {
            "category":"Retail",
            "subcategory":"Auto Repair",
            "type":"Services"
        }
    ],
    "sg:phone":"+44 23 9258 6374",
    "sg:postcode":"PO12 3JE",
    "sg:province":"Hampshire",
    "sg:tags":[
        "modification",
        "garage"
    ],
    "wof:name":"Motormech",
    "wof:placetype":"venue"
},
  "geometry": {"coordinates":[-1.146903,50.802036],"type":"Point"}
}