{
  "type": "Feature",
  "properties": {
    "iso:country":"GB",
    "sg:address":"2 Arthur Road",
    "sg:city":"Christchurch",
    "sg:classifiers":[
        {
            "category":"Building & Trades",
            "subcategory":"Plumbing",
            "type":"Services"
        }
    ],
    "sg:postcode":"BH23 1PU",
    "sg:province":"Dorset",
    "sg:tags":[
        "heating"
    ],
    "wof:name":"Sean Lawry",
    "wof:placetype":"venue"
},
  "geometry": {"coordinates":[-1.784592,50.737617],"type":"Point"}
}