{
  "type": "Feature",
  "properties": {
    "addr:full":"Wood Street Wallingford Oxfordshire OX10 0BD",
    "addr:postcode":"ox10 0bd",
    "addr:street":"Wood Street",
    "iso:country":"GB",
    "sg:address":"Wood Street",
    "sg:city":"Wallingford",
    "sg:classifiers":[
        {
            "category":"Organizations",
            "subcategory":"Membership Organization",
            "type":"Services"
        }
    ],
    "sg:phone":"+44 1491 835164",
    "sg:postcode":"OX10 0BD",
    "sg:province":"Oxfordshire",
    "sg:tags":[
        "club"
    ],
    "wof:name":"The Comrades Club Ltd.",
    "wof:placetype":"venue"
},
  "geometry": {"coordinates":[-1.12367,51.600719],"type":"Point"}
}