{
  "type": "Feature",
  "properties": {
    "addr:full":"46 Bellevue Road London Greater London N11 3ER",
    "addr:housenumber":"46",
    "addr:postcode":"n11 3er",
    "addr:street":"Bellevue Road",
    "iso:country":"GB",
    "sg:address":"46 Bellevue Road",
    "sg:city":"London",
    "sg:classifiers":[
        {
            "category":"Retail",
            "subcategory":"Portrait Studio",
            "type":"Services"
        },
        {
            "category":"Professional",
            "subcategory":"Art Services",
            "type":"Services"
        }
    ],
    "sg:phone":"+44 20 8361 2213",
    "sg:postcode":"N11 3ER",
    "sg:province":"Greater London",
    "sg:tags":[
        "photographer",
        "commercial"
    ],
    "wof:name":"Pascoe Willis",
    "wof:placetype":"venue"
},
  "geometry": {"coordinates":[-0.1495359987,51.6162948608],"type":"Point"}
}