{
  "type": "Feature",
  "properties": {
    "addr:full":"35 Church Street Romsey Hampshire SO51 8BT",
    "addr:housenumber":"35",
    "addr:postcode":"so51 8bt",
    "addr:street":"Church Street",
    "iso:country":"GB",
    "sg:address":"35 Church Street",
    "sg:city":"Romsey",
    "sg:classifiers":[
        {
            "category":"Professional",
            "type":"Services"
        }
    ],
    "sg:phone":"+44 1794 514257",
    "sg:postcode":"SO51 8BT",
    "sg:province":"Hampshire",
    "sg:tags":[
        "interior",
        "furnishers",
        "designer"
    ],
    "wof:name":"Susan Smith Interiors",
    "wof:placetype":"venue"
},
  "geometry": {"coordinates":[-1.4999690056,50.9903259277],"type":"Point"}
}