{
  "type": "Feature",
  "properties": {
    "addr:full":"6 Johnsons Field Olney Buckinghamshire MK46 5JF",
    "addr:housenumber":"6",
    "addr:postcode":"mk46 5jf",
    "addr:street":"Johnsons Field",
    "iso:country":"GB",
    "sg:address":"6 Johnsons Field",
    "sg:city":"Olney",
    "sg:classifiers":[
        {
            "category":"Building & Trades",
            "subcategory":"Plumbing",
            "type":"Services"
        }
    ],
    "sg:postcode":"MK46 5JF",
    "sg:province":"Buckinghamshire",
    "sg:tags":[
        "central",
        "heating"
    ],
    "wof:name":"K R Heating",
    "wof:placetype":"venue"
},
  "geometry": {"coordinates":[-0.701844,52.153469],"type":"Point"}
}