{
  "type": "Feature",
  "properties": {
    "iso:country":"GB",
    "sg:address":"Old Forge Rushford, Lamerton",
    "sg:city":"Tavistock",
    "sg:classifiers":[
        {
            "category":"Shopping",
            "subcategory":"Music",
            "type":"Retail Goods"
        }
    ],
    "sg:postcode":"PL19 8RY",
    "sg:province":"Devon",
    "sg:tags":[
        "record",
        "tape",
        "cd"
    ],
    "wof:name":"Ruptured Ambitions",
    "wof:placetype":"venue"
},
  "geometry": {"coordinates":[-4.196254,50.569664],"type":"Point"}
}