{
  "type": "Feature",
  "properties": {
    "addr:full":"1 Derrick Road Beckenham Kent BR3 3QG",
    "addr:housenumber":"1",
    "addr:postcode":"br3 3qg",
    "addr:street":"Derrick Road",
    "iso:country":"GB",
    "sg:address":"1 Derrick Road",
    "sg:city":"Beckenham",
    "sg:classifiers":[
        {
            "category":"Autos & Motor Vehicles",
            "subcategory":"Auto Supplies",
            "type":"Retail Goods"
        }
    ],
    "sg:phone":"+44 20 8650 1236",
    "sg:postcode":"BR3 3QG",
    "sg:province":"Kent",
    "sg:tags":[
        "windscreen"
    ],
    "wof:name":"D J Phillips",
    "wof:placetype":"venue"
},
  "geometry": {"coordinates":[-0.0384249985,51.3995704651],"type":"Point"}
}