{
  "type": "Feature",
  "properties": {
    "iso:country":"GB",
    "sg:address":"91 Croydon Road, Erdington",
    "sg:city":"Birmingham",
    "sg:classifiers":[
        {
            "category":"Building & Trades",
            "subcategory":"Construction",
            "type":"Services"
        }
    ],
    "sg:postcode":"B24 8HU",
    "sg:province":"West Midlands",
    "sg:tags":[
        "glazier"
    ],
    "wof:name":"Conway,John,",
    "wof:placetype":"venue"
},
  "geometry": {"coordinates":[-1.838978,52.512093],"type":"Point"}
}