{
  "type": "Feature",
  "properties": {
    "addr:full":"75 Whiteway Rd Bristol City of Bristol BS5 7QS",
    "addr:housenumber":"75",
    "addr:postcode":"bs5 7qs",
    "addr:street":"Whiteway Rd",
    "iso:country":"GB",
    "sg:address":"75 Whiteway Rd",
    "sg:city":"Bristol",
    "sg:classifiers":[
        {
            "category":"Personal",
            "subcategory":"Beauty Salon",
            "type":"Services"
        }
    ],
    "sg:phone":"+44 117 914 0241",
    "sg:postcode":"BS5 7QS",
    "sg:province":"City of Bristol",
    "wof:name":"Focus On Beauty",
    "wof:placetype":"venue"
},
  "geometry": {"coordinates":[-2.532558,51.46312],"type":"Point"}
}