{
  "type": "Feature",
  "properties": {
    "iso:country":"GB",
    "sg:address":"19 Kirkgate",
    "sg:city":"Ripon",
    "sg:classifiers":[
        {
            "category":"Health Services",
            "subcategory":"Optometrist",
            "type":"Services"
        }
    ],
    "sg:phone":"+44 1765 602820",
    "sg:postcode":"HG4 1PA",
    "sg:province":"North Yorkshire",
    "sg:tags":[
        "optician"
    ],
    "wof:name":"Fisher & Ruddy",
    "wof:placetype":"venue"
},
  "geometry": {"coordinates":[-1.5213940144,54.1350784302],"type":"Point"}
}