{
  "type": "Feature",
  "properties": {
    "addr:full":"Girsby Grange, Burgh On Bain Market Rasen Lincolnshire LN8 6LA",
    "addr:postcode":"ln8 6la",
    "iso:country":"GB",
    "sg:address":"Girsby Grange, Burgh On Bain",
    "sg:city":"Market Rasen",
    "sg:classifiers":[
        {
            "category":"Farming",
            "subcategory":"Farm",
            "type":"Manufacturing & Wholesale Goods"
        },
        {
            "category":"Wholesale",
            "subcategory":"Fruits & Vegetables",
            "type":"Manufacturing & Wholesale Goods"
        }
    ],
    "sg:postcode":"LN8 6LA",
    "sg:province":"Lincolnshire",
    "sg:tags":[
        "mixed",
        "crop"
    ],
    "wof:name":"R M & E F Davey",
    "wof:placetype":"venue"
},
  "geometry": {"coordinates":[-0.1753329933,53.3662376404],"type":"Point"}
}