{
  "type": "Feature",
  "properties": {
    "addr:full":"Newsagents168-170 Yarmouth Road Norwich Norfolk NR7 0AD",
    "addr:postcode":"nr7 0ad",
    "addr:street":"Newsagents168-170 Yarmouth Road Norwich Norfolk",
    "iso:country":"GB",
    "sg:address":"Newsagents168-170 Yarmouth Road",
    "sg:city":"Norwich",
    "sg:classifiers":[
        {
            "category":"Shopping",
            "subcategory":"News",
            "type":"Retail Goods"
        }
    ],
    "sg:phone":"+44 1603 437369",
    "sg:postcode":"NR7 0AD",
    "sg:province":"Norfolk",
    "sg:tags":[
        "newsagent"
    ],
    "wof:name":"W & J GALLOP",
    "wof:placetype":"venue"
},
  "geometry": {"coordinates":[1.3584239483,52.6281929016],"type":"Point"}
}