{
  "type": "Feature",
  "properties": {
    "iso:country":"GB",
    "sg:address":"8 Stonehouse St",
    "sg:city":"Plymouth",
    "sg:classifiers":[
        {
            "category":"Retail",
            "subcategory":"Auto Repair",
            "type":"Services"
        }
    ],
    "sg:phone":"+44 1752 669373",
    "sg:postcode":"PL1 3PN",
    "sg:province":"Devon",
    "sg:tags":[
        "car",
        "servicing",
        "radiator"
    ],
    "wof:name":"Serck Marston",
    "wof:placetype":"venue"
},
  "geometry": {"coordinates":[-4.1618599892,50.3683624268],"type":"Point"}
}