{
  "type": "Feature",
  "properties": {
    "addr:full":"Firsland Studios, Henfield Road, Albourne Hassocks East Sussex BN6 9JJ",
    "addr:postcode":"bn6 9jj",
    "addr:street":"Henfield Road",
    "iso:country":"GB",
    "sg:address":"Firsland Studios, Henfield Road, Albourne",
    "sg:city":"Hassocks",
    "sg:classifiers":[
        {
            "category":"Shopping",
            "subcategory":"Stationery & Office Supplies",
            "type":"Retail Goods"
        }
    ],
    "sg:postcode":"BN6 9JJ",
    "sg:province":"East Sussex",
    "sg:tags":[
        "printers'"
    ],
    "wof:name":"Aurora Foil Blocking",
    "wof:placetype":"venue"
},
  "geometry": {"coordinates":[-0.201507,50.933369],"type":"Point"}
}