{
  "type": "Feature",
  "properties": {
    "iso:country":"GB",
    "sg:address":"Flat 3 32 Alderney Street, Pimlico",
    "sg:city":"London",
    "sg:classifiers":[
        {
            "category":"Professional",
            "subcategory":"Management & Consulting",
            "type":"Services"
        }
    ],
    "sg:postcode":"SW1V 4EU",
    "sg:province":"Greater London",
    "sg:tags":[
        "consultant",
        "business"
    ],
    "wof:name":"Levey Consultants Ltd",
    "wof:placetype":"venue"
},
  "geometry": {"coordinates":[-0.14543,51.4902],"type":"Point"}
}