{
  "type": "Feature",
  "properties": {
    "addr:full":"60 Whitehouse Road, Dordon Tamworth Staffordshire B78 1QF",
    "addr:housenumber":"60",
    "addr:postcode":"b78 1qf",
    "addr:street":"Whitehouse Road",
    "iso:country":"GB",
    "sg:address":"60 Whitehouse Road, Dordon",
    "sg:city":"Tamworth",
    "sg:classifiers":[
        {
            "category":"Building & Trades",
            "subcategory":"Cleaning & Sanitation",
            "type":"Services"
        },
        {
            "category":"Home & Garden",
            "subcategory":"Carpets & Floor Coverings",
            "type":"Retail Goods"
        }
    ],
    "sg:phone":"+44 1827 897849",
    "sg:postcode":"B78 1QF",
    "sg:province":"Staffordshire",
    "sg:tags":[
        "cleaner",
        "upholstery"
    ],
    "wof:name":"A V P Cleaning Service",
    "wof:placetype":"venue"
},
  "geometry": {"coordinates":[-1.619194,52.609314],"type":"Point"}
}