{
  "type": "Feature",
  "properties": {
    "iso:country":"GB",
    "sg:address":"21 Albermarle Street",
    "sg:city":"Clitheroe",
    "sg:classifiers":[
        {
            "category":"Organizations",
            "subcategory":"Non-profit Organization",
            "type":"Services"
        }
    ],
    "sg:phone":"+44 1200 424546",
    "sg:postcode":"BB7 2EA",
    "sg:province":"Lancashire",
    "sg:tags":[
        "organisation",
        "voluntary",
        "charity"
    ],
    "wof:name":"Multiple Sclerosis Society of Great Britain & Northern Ireland",
    "wof:placetype":"venue"
},
  "geometry": {"coordinates":[-2.396969,53.87199],"type":"Point"}
}