{
  "type": "Feature",
  "properties": {
    "addr:full":"Ellgreave Street, Dalehall, Burslem Stoke-on-trent Staffordshire ST6 4DQ",
    "addr:postcode":"staffordshire st6 4dq",
    "addr:street":"Ellgreave Street Dalehall",
    "iso:country":"GB",
    "sg:address":"Ellgreave Street, Dalehall, Burslem",
    "sg:city":"Stoke-on-trent",
    "sg:classifiers":[
        {
            "category":"Building & Trades",
            "subcategory":"Construction",
            "type":"Services"
        }
    ],
    "sg:postcode":"ST6 4DQ",
    "sg:province":"Staffordshire",
    "sg:tags":[
        "ceiling",
        "contractor"
    ],
    "wof:name":"Focusbrook Ltd.",
    "wof:placetype":"venue"
},
  "geometry": {"coordinates":[-2.207076,53.044975],"type":"Point"}
}