{
  "type": "Feature",
  "properties": {
    "iso:country":"GB",
    "sg:address":"9 Brightwell Cres",
    "sg:city":"Solihull",
    "sg:classifiers":[
        {
            "category":"Building & Trades",
            "subcategory":"Construction",
            "type":"Services"
        }
    ],
    "sg:phone":"+44 1564 770582",
    "sg:postcode":"B93 8HF",
    "sg:province":"Warwickshire",
    "sg:tags":[
        "builder"
    ],
    "wof:name":"C.J. Builders",
    "wof:placetype":"venue"
},
  "geometry": {"coordinates":[-1.762231946,52.3740921021],"type":"Point"}
}