{
  "type": "Feature",
  "properties": {
    "addr:full":"Drainage, West Riding Ho, 9 Manchester Rd Huddersfield West Yorkshire HD1 3HH",
    "addr:housenumber":"9",
    "addr:postcode":"hd1 3hh",
    "addr:street":"Manchester Rd",
    "iso:country":"GB",
    "sg:address":"Drainage, West Riding Ho, 9 Manchester Rd",
    "sg:city":"Huddersfield",
    "sg:classifiers":[
        {
            "category":"Government",
            "subcategory":"Office",
            "type":"Public Place"
        }
    ],
    "sg:phone":"+44 1484 226894",
    "sg:postcode":"HD1 3HH",
    "sg:province":"West Yorkshire",
    "sg:tags":[
        "local"
    ],
    "wof:name":"Kirklees Environmental Services",
    "wof:placetype":"venue"
},
  "geometry": {"coordinates":[-1.7826839685,53.6469535828],"type":"Point"}
}