{
  "type": "Feature",
  "properties": {
    "iso:country":"GB",
    "sg:address":"24 Old Brompton Road",
    "sg:city":"London",
    "sg:classifiers":[
        {
            "category":"Food & Beverages",
            "subcategory":"Specialty",
            "type":"Retail Goods"
        }
    ],
    "sg:phone":"+44 20 7589 5870",
    "sg:postcode":"SW7 3DL",
    "sg:province":"Greater London",
    "sg:tags":[
        "product",
        "health"
    ],
    "wof:name":"Health Craze",
    "wof:placetype":"venue"
},
  "geometry": {"coordinates":[-0.175109,51.493599],"type":"Point"}
}