{
  "type": "Feature",
  "properties": {
    "addr:full":"Aztec Studios, Clarendon Rd Hornsey Greater London N8 0DD",
    "addr:postcode":"n8 0dd",
    "addr:street":"Clarendon Rd",
    "iso:country":"GB",
    "sg:address":"Aztec Studios, Clarendon Rd",
    "sg:city":"Hornsey",
    "sg:classifiers":[
        {
            "category":"Manufacturing",
            "subcategory":"Apparel",
            "type":"Manufacturing & Wholesale Goods"
        }
    ],
    "sg:phone":"+44 20 8372 6019",
    "sg:postcode":"N8 0DD",
    "sg:province":"Greater London",
    "sg:tags":[
        "garment",
        "designer"
    ],
    "wof:name":"Suzanne French",
    "wof:placetype":"venue"
},
  "geometry": {"coordinates":[-0.11234,51.589569],"type":"Point"}
}