{
  "type": "Feature",
  "properties": {
    "addr:full":"Unit 36, Craster Court, Manor Walk Shopping Centre Cramlington Northumberland NE23 6UT",
    "addr:housenumber":"unit 36",
    "addr:postcode":"ne23 6ut",
    "addr:street":"Craster Court Manor Walk Shopping;Northumberland",
    "iso:country":"GB",
    "sg:address":"Unit 36, Craster Court, Manor Walk Shopping Centre",
    "sg:city":"Cramlington",
    "sg:classifiers":[
        {
            "category":"Travel",
            "subcategory":"Travel Agent",
            "type":"Entertainment"
        }
    ],
    "sg:phone":"+44 1670 732938",
    "sg:postcode":"NE23 6UT",
    "sg:province":"Northumberland",
    "wof:name":"Lunn Poly Ltd.",
    "wof:placetype":"venue"
},
  "geometry": {"coordinates":[-1.5648570061,55.0781173706],"type":"Point"}
}