{
  "type": "Feature",
  "properties": {
    "addr:full":"Albert Road Hayes Greater London UB3 4BL",
    "addr:postcode":"ub3 4bl",
    "addr:street":"Albert Road",
    "iso:country":"GB",
    "sg:address":"Albert Road",
    "sg:city":"Hayes",
    "sg:classifiers":[
        {
            "category":"Organizations",
            "subcategory":"Membership Organization",
            "type":"Services"
        }
    ],
    "sg:phone":"+44 20 8573 5273",
    "sg:postcode":"UB3 4BL",
    "sg:province":"Greater London",
    "sg:tags":[
        "club"
    ],
    "wof:name":"Hayes & Harlington Community Association",
    "wof:placetype":"venue"
},
  "geometry": {"coordinates":[-0.4240610003,51.5019836426],"type":"Point"}
}