{
  "type": "Feature",
  "properties": {
    "addr:full":"68 Victoria Road, Mount Charles St Austell Cornwall PL25 4QD",
    "addr:housenumber":"68",
    "addr:postcode":"charles;pl25 4qd",
    "addr:street":"Victoria Road;St",
    "iso:country":"GB",
    "sg:address":"68 Victoria Road, Mount Charles",
    "sg:city":"St Austell",
    "sg:classifiers":[
        {
            "category":"Autos & Motor Vehicles",
            "subcategory":"Auto Supplies",
            "type":"Retail Goods"
        }
    ],
    "sg:phone":"+44 1726 72542",
    "sg:postcode":"PL25 4QD",
    "sg:province":"Cornwall",
    "sg:tags":[
        "tyre"
    ],
    "wof:name":"National Tyres and Autocare",
    "wof:placetype":"venue"
},
  "geometry": {"coordinates":[-4.775017,50.338219],"type":"Point"}
}