{
  "type": "Feature",
  "properties": {
    "iso:country":"GB",
    "sg:address":"2 Norman Parade, Maylands Drive",
    "sg:city":"Sidcup",
    "sg:classifiers":[
        {
            "category":"Food & Beverages",
            "subcategory":"Liquor & Beverages",
            "type":"Retail Goods"
        }
    ],
    "sg:phone":"+44 20 8300 5471",
    "sg:postcode":"DA14 4RP",
    "sg:province":"Kent",
    "sg:tags":[
        "beer",
        "spirit",
        "wines"
    ],
    "wof:name":"Cheers Off Licence",
    "wof:placetype":"venue"
},
  "geometry": {"coordinates":[0.103945,51.425919],"type":"Point"}
}