{
  "type": "Feature",
  "properties": {
    "iso:country":"GB",
    "sg:address":"Belsyde, Drummond Road",
    "sg:city":"Dingwall",
    "sg:classifiers":[
        {
            "category":"Building & Trades",
            "subcategory":"Construction",
            "type":"Services"
        }
    ],
    "sg:postcode":"IV16 9UT",
    "sg:province":"Highland",
    "sg:tags":[
        "pipework",
        "contractor"
    ],
    "wof:name":"S J Fletcher",
    "wof:placetype":"venue"
},
  "geometry": {"coordinates":[-4.3415870667,57.6595840454],"type":"Point"}
}