{
  "type": "Feature",
  "properties": {
    "iso:country":"GB",
    "sg:address":"5a Hampton Road, Hampton Hill",
    "sg:city":"Hampton",
    "sg:classifiers":[
        {
            "category":"Professional",
            "subcategory":"Management & Consulting",
            "type":"Services"
        }
    ],
    "sg:phone":"+44 20 8977 6944",
    "sg:postcode":"TW12 1JN",
    "sg:province":"Greater London",
    "sg:tags":[
        "consultant",
        "training"
    ],
    "wof:name":"I T C Network Ltd.",
    "wof:placetype":"venue"
},
  "geometry": {"coordinates":[-0.353531,51.429062],"type":"Point"}
}