{
  "type": "Feature",
  "properties": {
    "addr:full":"45 Durand Road, Lower Early Reading Berkshire RG6 5YU",
    "addr:housenumber":"45",
    "addr:postcode":"rg6 5yu",
    "addr:street":"Durand Road Lower",
    "iso:country":"GB",
    "sg:address":"45 Durand Road, Lower Early",
    "sg:city":"Reading",
    "sg:classifiers":[
        {
            "category":"Retail",
            "subcategory":"Auto Repair",
            "type":"Services"
        }
    ],
    "sg:postcode":"RG6 5YU",
    "sg:province":"Berkshire",
    "sg:tags":[
        "modification",
        "garage"
    ],
    "wof:name":"R M Autos",
    "wof:placetype":"venue"
},
  "geometry": {"coordinates":[-0.932445,51.427814],"type":"Point"}
}