{
  "type": "Feature",
  "properties": {
    "addr:full":"210 Station Road, Lower Stondon Henlow Bedfordshire SG16 6JE",
    "addr:housenumber":"210",
    "addr:postcode":"sg16 6je",
    "addr:street":"Station Road Lower Stondon",
    "iso:country":"GB",
    "sg:address":"210 Station Road, Lower Stondon",
    "sg:city":"Henlow",
    "sg:classifiers":[
        {
            "category":"Building & Trades",
            "subcategory":"Construction",
            "type":"Services"
        }
    ],
    "sg:postcode":"SG16 6JE",
    "sg:province":"Bedfordshire",
    "sg:tags":[
        "builder"
    ],
    "wof:name":"A M Services",
    "wof:placetype":"venue"
},
  "geometry": {"coordinates":[-0.306333,52.007149],"type":"Point"}
}