{
  "type": "Feature",
  "properties": {
    "addr:full":"75 Pontypridd Road Porth Bridgend CF39 9PL",
    "addr:housenumber":"75",
    "addr:postcode":"cf39 9pl",
    "addr:street":"Pontypridd Road",
    "iso:country":"GB",
    "sg:address":"75 Pontypridd Road",
    "sg:city":"Porth",
    "sg:classifiers":[
        {
            "category":"Shopping",
            "subcategory":"News",
            "type":"Retail Goods"
        }
    ],
    "sg:phone":"+44 1443 682192",
    "sg:postcode":"CF39 9PL",
    "sg:province":"Bridgend",
    "sg:tags":[
        "newsagent"
    ],
    "wof:name":"United News Shops Ltd.",
    "wof:placetype":"venue"
},
  "geometry": {"coordinates":[-3.408932,51.611622],"type":"Point"}
}