{
  "type": "Feature",
  "properties": {
    "iso:country":"GB",
    "sg:address":"52 Station Road",
    "sg:city":"Blackpool",
    "sg:classifiers":[
        {
            "category":"Travel",
            "subcategory":"Hotels & Motels",
            "type":"Entertainment"
        }
    ],
    "sg:phone":"+44 1253 342390",
    "sg:postcode":"FY4 1EU",
    "sg:province":"Lancashire",
    "sg:tags":[
        "house",
        "self",
        "guest",
        "catering"
    ],
    "wof:name":"Avalon Holiday Flats",
    "wof:placetype":"venue"
},
  "geometry": {"coordinates":[-3.052284956,53.7959976196],"type":"Point"}
}