{
  "type": "Feature",
  "properties": {
    "addr:full":"115a Delamere Street Winsford Cheshire CW7 2LX",
    "addr:housenumber":"115a",
    "addr:postcode":"cw7 2lx",
    "addr:street":"Delamere Street",
    "iso:country":"GB",
    "sg:address":"115a Delamere Street",
    "sg:city":"Winsford",
    "sg:classifiers":[
        {
            "category":"Shopping",
            "type":"Retail Goods"
        }
    ],
    "sg:phone":"+44 1606 592504",
    "sg:postcode":"CW7 2LX",
    "sg:province":"Cheshire",
    "sg:tags":[
        "merchant"
    ],
    "wof:name":"Chelford Farm Supplies Ltd.",
    "wof:placetype":"venue"
},
  "geometry": {"coordinates":[-2.5446209908,53.1916236877],"type":"Point"}
}