{
  "type": "Feature",
  "properties": {
    "iso:country":"GB",
    "sg:address":"3 Nile Street",
    "sg:city":"Brighton",
    "sg:classifiers":[
        {
            "category":"Retail",
            "subcategory":"Photofinishing",
            "type":"Services"
        }
    ],
    "sg:phone":"+44 1273 327344",
    "sg:postcode":"BN1 1HW",
    "sg:province":"East Sussex",
    "sg:tags":[
        "photographic",
        "processor"
    ],
    "wof:name":"First Light",
    "wof:placetype":"venue"
},
  "geometry": {"coordinates":[-0.140877,50.821209],"type":"Point"}
}