{
  "type": "Feature",
  "properties": {
    "addr:full":"44 Nigel Rd Peckham Greater London SE15 4NR",
    "addr:housenumber":"44",
    "addr:postcode":"se15 4nr",
    "addr:street":"Nigel Rd",
    "iso:country":"GB",
    "sg:address":"44 Nigel Rd",
    "sg:city":"Peckham",
    "sg:classifiers":[
        {
            "category":"Retail",
            "subcategory":"Driving School",
            "type":"Services"
        }
    ],
    "sg:phone":"+44 20 7639 5810",
    "sg:postcode":"SE15 4NR",
    "sg:province":"Greater London",
    "wof:name":"Anthony Key School Of Motoring",
    "wof:placetype":"venue"
},
  "geometry": {"coordinates":[-0.067094,51.466064],"type":"Point"}
}