{
  "type": "Feature",
  "properties": {
    "addr:full":"30 St Margarets Grn Ipswich Suffolk IP4 2BS",
    "addr:housenumber":"30",
    "addr:postcode":"ip4 2bs",
    "addr:street":"St Margarets Grn",
    "iso:country":"GB",
    "sg:address":"30 St Margarets Grn",
    "sg:city":"Ipswich",
    "sg:classifiers":[
        {
            "category":"Manufacturing",
            "subcategory":"Tools & Machinery",
            "type":"Manufacturing & Wholesale Goods"
        }
    ],
    "sg:phone":"+44 1473 251692",
    "sg:postcode":"IP4 2BS",
    "sg:province":"Suffolk",
    "sg:tags":[
        "society",
        "friendly"
    ],
    "wof:name":"Ancient Order of Foresters",
    "wof:placetype":"venue"
},
  "geometry": {"coordinates":[1.158843,52.059223],"type":"Point"}
}