{
  "type": "Feature",
  "properties": {
    "addr:full":"1 Lea Way Off Shelford Drive, Wootton Road King's Lynn Norfolk PE30 3AT",
    "addr:housenumber":"1",
    "addr:postcode":"pe30 3at",
    "addr:street":"Lea Way Off Shelford Drive Wootton Road",
    "iso:country":"GB",
    "sg:address":"1 Lea Way Off Shelford Drive, Wootton Road",
    "sg:city":"King's Lynn",
    "sg:classifiers":[
        {
            "category":"Professional",
            "subcategory":"Art Services",
            "type":"Services"
        }
    ],
    "sg:postcode":"PE30 3AT",
    "sg:province":"Norfolk",
    "sg:tags":[
        "photographer"
    ],
    "wof:name":"Tom Pegg Photography",
    "wof:placetype":"venue"
},
  "geometry": {"coordinates":[0.42821,52.769611],"type":"Point"}
}