{
  "type": "Feature",
  "properties": {
    "iso:country":"GB",
    "sg:address":"Maxwell Heugh",
    "sg:city":"Kelso",
    "sg:classifiers":[
        {
            "category":"Autos & Motor Vehicles",
            "subcategory":"Automobile Sales",
            "type":"Retail Goods"
        }
    ],
    "sg:phone":"+44 1573 224016",
    "sg:postcode":"TD5 8DQ",
    "sg:province":"Scottish Borders",
    "sg:tags":[
        "car"
    ],
    "wof:name":"Maxwell Heugh Car Sales",
    "wof:placetype":"venue"
},
  "geometry": {"coordinates":[-2.479497,55.568378],"type":"Point"}
}