{
  "type": "Feature",
  "properties": {
    "addr:full":"6 Mount Park Crescent, Ealing London Greater London W5 2RN",
    "addr:housenumber":"6",
    "addr:postcode":"w5 2rn",
    "addr:street":"Mount Park Crescent",
    "iso:country":"GB",
    "sg:address":"6 Mount Park Crescent, Ealing",
    "sg:city":"London",
    "sg:classifiers":[
        {
            "category":"Building & Trades",
            "subcategory":"Construction",
            "type":"Services"
        }
    ],
    "sg:phone":"+44 20 8998 3439",
    "sg:postcode":"W5 2RN",
    "sg:province":"Greater London",
    "sg:tags":[
        "builder"
    ],
    "wof:name":"Viewsure Ltd.",
    "wof:placetype":"venue"
},
  "geometry": {"coordinates":[-0.303148,51.518826],"type":"Point"}
}