{
  "type": "Feature",
  "properties": {
    "addr:full":"3a Gloddaeth Street Llandudno Conwy LL30 2DD",
    "addr:housenumber":"3a",
    "addr:postcode":"ll30 2dd",
    "addr:street":"Gloddaeth Street",
    "iso:country":"GB",
    "sg:address":"3a Gloddaeth Street",
    "sg:city":"Llandudno",
    "sg:classifiers":[
        {
            "category":"Home & Garden",
            "subcategory":"Home Furnishings",
            "type":"Retail Goods"
        }
    ],
    "sg:phone":"+44 1492 871940",
    "sg:postcode":"LL30 2DD",
    "sg:province":"Conwy",
    "sg:tags":[
        "beds",
        "bedding",
        "blanket"
    ],
    "wof:name":"Lister's Household Textiles",
    "wof:placetype":"venue"
},
  "geometry": {"coordinates":[-3.8320651054,53.3253211975],"type":"Point"}
}