{
  "type": "Feature",
  "properties": {
    "addr:full":"2 Perry Hill Rd, Oldbury Birmingham West Midlands B68 0AZ",
    "addr:housenumber":"2",
    "addr:postcode":"b68 0az",
    "addr:street":"Perry Hill Rd",
    "iso:country":"GB",
    "sg:address":"2 Perry Hill Rd, Oldbury",
    "sg:city":"Birmingham",
    "sg:classifiers":[
        {
            "category":"Personal",
            "subcategory":"Beauty Salon",
            "type":"Services"
        }
    ],
    "sg:postcode":"B68 0AZ",
    "sg:province":"West Midlands",
    "sg:tags":[
        "unisex",
        "hairdresser"
    ],
    "wof:name":"Linford,Joanne,",
    "wof:placetype":"venue"
},
  "geometry": {"coordinates":[-2.0009739399,52.4678192139],"type":"Point"}
}