{
  "type": "Feature",
  "properties": {
    "addr:full":"Trenance Mill, Blowing House Hill St Austell Cornwall PL25 5AH",
    "addr:postcode":"pl25 5ah",
    "addr:street":"Hill",
    "iso:country":"GB",
    "sg:address":"Trenance Mill, Blowing House Hill",
    "sg:city":"St Austell",
    "sg:classifiers":[
        {
            "category":"Professional",
            "subcategory":"Printing & Photocopies",
            "type":"Services"
        }
    ],
    "sg:phone":"+44 1726 61264",
    "sg:postcode":"PL25 5AH",
    "sg:province":"Cornwall",
    "sg:tags":[
        "printer"
    ],
    "wof:name":"Francis Anthony",
    "wof:placetype":"venue"
},
  "geometry": {"coordinates":[-4.792324,50.337421],"type":"Point"}
}