{
  "type": "Feature",
  "properties": {
    "addr:full":"190 Sunbridge Rd Bradford West Yorkshire BD1 2LF",
    "addr:housenumber":"190",
    "addr:postcode":"bd1 2lf",
    "addr:street":"Sunbridge Rd",
    "iso:country":"GB",
    "sg:address":"190 Sunbridge Rd",
    "sg:city":"Bradford",
    "sg:classifiers":[
        {
            "category":"Shopping",
            "subcategory":"Computers & Home Electronics",
            "type":"Retail Goods"
        }
    ],
    "sg:phone":"+44 1274 308656",
    "sg:postcode":"BD1 2LF",
    "sg:province":"West Yorkshire",
    "sg:tags":[
        "electrical"
    ],
    "wof:name":"Windsor",
    "wof:placetype":"venue"
},
  "geometry": {"coordinates":[-1.767096,53.797821],"type":"Point"}
}