{
  "type": "Feature",
  "properties": {
    "addr:full":"Lansdown Road Bath Bath and North East Somerset BA1 5TJ",
    "addr:postcode":"ba1 5tj",
    "addr:street":"Lansdown Road",
    "iso:country":"GB",
    "sg:address":"Lansdown Road",
    "sg:city":"Bath",
    "sg:classifiers":[
        {
            "category":"Bars & Pubs",
            "type":"Food & Drink"
        },
        {
            "category":"Community Center",
            "subcategory":"Social",
            "type":"Public Place"
        }
    ],
    "sg:phone":"+44 1225 482682",
    "sg:postcode":"BA1 5TJ",
    "sg:province":"Bath and North East Somerset",
    "sg:tags":[
        "pubs",
        "house",
        "inn",
        "activity"
    ],
    "wof:name":"Hare & Hounds",
    "wof:placetype":"venue"
},
  "geometry": {"coordinates":[-2.3621790409,51.3889007568],"type":"Point"}
}