{
  "type": "Feature",
  "properties": {
    "addr:full":"2 Princes Way Milton Keynes Buckinghamshire MK2 2UL",
    "addr:housenumber":"2",
    "addr:postcode":"mk2 2ul",
    "addr:street":"Princes Way",
    "iso:country":"GB",
    "sg:address":"2 Princes Way",
    "sg:city":"Milton Keynes",
    "sg:classifiers":[
        {
            "category":"Home & Garden",
            "subcategory":"Carpets & Floor Coverings",
            "type":"Retail Goods"
        }
    ],
    "sg:phone":"+44 1908 365417",
    "sg:postcode":"MK2 2UL",
    "sg:province":"Buckinghamshire",
    "sg:tags":[
        "carpets",
        "rug",
        "matting"
    ],
    "wof:name":"Henry's Carpets",
    "wof:placetype":"venue"
},
  "geometry": {"coordinates":[-0.7303689718,51.9972648621],"type":"Point"}
}