{
  "type": "Feature",
  "properties": {
    "addr:full":"Bilton Lane, Long Lawford Rugby Northamptonshire CV23 9DU",
    "addr:postcode":"cv23 9du",
    "addr:street":"Bilton Lane",
    "iso:country":"GB",
    "sg:address":"Bilton Lane, Long Lawford",
    "sg:city":"Rugby",
    "sg:classifiers":[
        {
            "category":"Bars & Pubs",
            "type":"Food & Drink"
        },
        {
            "category":"Community Center",
            "subcategory":"Social",
            "type":"Public Place"
        }
    ],
    "sg:phone":"+44 1788 522297",
    "sg:postcode":"CV23 9DU",
    "sg:province":"Northamptonshire",
    "sg:tags":[
        "pubs",
        "house",
        "inn",
        "activity"
    ],
    "wof:name":"The Bear",
    "wof:placetype":"venue"
},
  "geometry": {"coordinates":[-1.3016899824,52.3719329834],"type":"Point"}
}