{
  "type": "Feature",
  "properties": {
    "addr:full":"Broad St Denny Falkirk FK6 6DX",
    "addr:postcode":"fk6 6dx",
    "addr:street":"Broad St",
    "iso:country":"GB",
    "sg:address":"Broad St",
    "sg:city":"Denny",
    "sg:classifiers":[
        {
            "category":"Government",
            "subcategory":"Police Station",
            "type":"Public Place"
        }
    ],
    "sg:phone":"+44 1324 823688",
    "sg:postcode":"FK6 6DX",
    "sg:province":"Falkirk",
    "sg:tags":[
        "support"
    ],
    "wof:name":"Denny Police Station",
    "wof:placetype":"venue"
},
  "geometry": {"coordinates":[-3.907094,56.022919],"type":"Point"}
}