{
  "type": "Feature",
  "properties": {
    "addr:full":"2 Victoria Rd Doncaster North Yorkshire DN6 7AZ",
    "addr:housenumber":"2",
    "addr:postcode":"dn6 7az",
    "addr:street":"Victoria Rd",
    "iso:country":"GB",
    "sg:address":"2 Victoria Rd",
    "sg:city":"Doncaster",
    "sg:classifiers":[
        {
            "category":"Shopping",
            "subcategory":"Clothing, Apparel, & Fashions",
            "type":"Retail Goods"
        }
    ],
    "sg:phone":"+44 1302 337824",
    "sg:postcode":"DN6 7AZ",
    "sg:province":"North Yorkshire",
    "sg:tags":[
        "wear",
        "leisure"
    ],
    "wof:name":"Emb-Racing",
    "wof:placetype":"venue"
},
  "geometry": {"coordinates":[-1.1458719969,53.5097312927],"type":"Point"}
}