{
  "type": "Feature",
  "properties": {
    "iso:country":"GB",
    "sg:address":"Main Rd, Parson Drove",
    "sg:city":"Wisbech",
    "sg:classifiers":[
        {
            "category":"Education",
            "subcategory":"School",
            "type":"Public Place"
        }
    ],
    "sg:phone":"+44 1945 700275",
    "sg:postcode":"PE13 4JA",
    "sg:province":"Cambridgeshire",
    "sg:tags":[
        "local",
        "authority"
    ],
    "wof:name":"Payne County Primary School",
    "wof:placetype":"venue"
},
  "geometry": {"coordinates":[0.04011,52.65913],"type":"Point"}
}