{
  "type": "Feature",
  "properties": {
    "addr:full":"Club Mill Road Sheffield South Yorkshire S6 2FH",
    "addr:postcode":"s6 2fh",
    "addr:street":"Mill Road",
    "iso:country":"GB",
    "sg:address":"Club Mill Road",
    "sg:city":"Sheffield",
    "sg:classifiers":[
        {
            "category":"Wholesale",
            "subcategory":"Machinery & Supplies",
            "type":"Manufacturing & Wholesale Goods"
        }
    ],
    "sg:phone":"+44 114 285 6000",
    "sg:postcode":"S6 2FH",
    "sg:province":"South Yorkshire",
    "wof:name":"Chapmans Agricultural Ltd.",
    "wof:placetype":"venue"
},
  "geometry": {"coordinates":[-1.4858180285,53.4035453796],"type":"Point"}
}