{
  "type": "Feature",
  "properties": {
    "iso:country":"GB",
    "sg:address":"Fosseway",
    "sg:city":"Cheltenham",
    "sg:classifiers":[
        {
            "category":"Professional",
            "subcategory":"Business Services",
            "type":"Services"
        }
    ],
    "sg:phone":"+44 1451 822228",
    "sg:postcode":"GL54 2EY",
    "sg:province":"Gloucestershire",
    "sg:tags":[
        "import",
        "export",
        "agent"
    ],
    "wof:name":"Russanglia Ltd",
    "wof:placetype":"venue"
},
  "geometry": {"coordinates":[-1.739619,51.87545],"type":"Point"}
}