{
  "type": "Feature",
  "properties": {
    "addr:full":"Chorley Lichfield Staffordshire WS13 8DD",
    "addr:postcode":"ws13 8dd",
    "iso:country":"GB",
    "sg:address":"Chorley",
    "sg:city":"Lichfield",
    "sg:classifiers":[
        {
            "category":"Bars & Pubs",
            "type":"Food & Drink"
        }
    ],
    "sg:phone":"+44 1543 685277",
    "sg:postcode":"WS13 8DD",
    "sg:province":"Staffordshire",
    "sg:tags":[
        "pubs",
        "inn"
    ],
    "wof:name":"Malt Shovel Inn The",
    "wof:placetype":"venue"
},
  "geometry": {"coordinates":[-1.8975100517,52.6977310181],"type":"Point"}
}