{
  "type": "Feature",
  "properties": {
    "iso:country":"GB",
    "sg:address":"Unit 5 Meadow Farm, Cross, Moor Lane, Haxby",
    "sg:city":"York",
    "sg:classifiers":[
        {
            "category":"Retail",
            "subcategory":"Auto Repair",
            "type":"Services"
        }
    ],
    "sg:phone":"+44 1904 767137",
    "sg:postcode":"YO32 2QR",
    "sg:province":"North Yorkshire",
    "sg:tags":[
        "modification",
        "garage"
    ],
    "wof:name":"Andy Wood Motor Engineer",
    "wof:placetype":"venue"
},
  "geometry": {"coordinates":[-1.0697499514,54.031539917],"type":"Point"}
}