{
  "type": "Feature",
  "properties": {
    "iso:country":"GB",
    "sg:address":"10-14 East Trinity Road",
    "sg:city":"Edinburgh",
    "sg:classifiers":[
        {
            "category":"Real Estate",
            "subcategory":"Architect",
            "type":"Services"
        }
    ],
    "sg:phone":"+44 131 551 5663",
    "sg:postcode":"EH5 3DY",
    "sg:province":"City of Edinburgh",
    "wof:name":"Margaret Lynn & Associates",
    "wof:placetype":"venue"
},
  "geometry": {"coordinates":[-3.1978349686,55.9778633118],"type":"Point"}
}