{
  "type": "Feature",
  "properties": {
    "addr:full":"708 Huddersfield Rd, Wyke Bradford West Yorkshire BD12 8JY",
    "addr:housenumber":"708",
    "addr:postcode":"bd12 8jy",
    "addr:street":"Huddersfield Rd",
    "iso:country":"GB",
    "sg:address":"708 Huddersfield Rd, Wyke",
    "sg:city":"Bradford",
    "sg:classifiers":[
        {
            "category":"Coffee & Tea",
            "type":"Food & Drink"
        }
    ],
    "sg:phone":"+44 1274 605211",
    "sg:postcode":"BD12 8JY",
    "sg:province":"West Yorkshire",
    "wof:name":"Bewley's Coffeeman",
    "wof:placetype":"venue"
},
  "geometry": {"coordinates":[-1.774691,53.737331],"type":"Point"}
}