{
  "type": "Feature",
  "properties": {
    "addr:full":"70 High St, Aberdour Burntisland Fife KY3 0SW",
    "addr:housenumber":"70",
    "addr:postcode":"ky3 0sw",
    "addr:street":"High St",
    "iso:country":"GB",
    "sg:address":"70 High St, Aberdour",
    "sg:city":"Burntisland",
    "sg:classifiers":[
        {
            "category":"Professional",
            "subcategory":"Art Services",
            "type":"Services"
        }
    ],
    "sg:postcode":"KY3 0SW",
    "sg:province":"Fife",
    "sg:tags":[
        "photographer",
        "graphic",
        "designer"
    ],
    "wof:name":"Thomson,Douglas,",
    "wof:placetype":"venue"
},
  "geometry": {"coordinates":[-3.3032469749,56.0534820557],"type":"Point"}
}