{
  "type": "Feature",
  "properties": {
    "iso:country":"GB",
    "sg:address":"Fernbrook, Semley",
    "sg:city":"Shaftesbury",
    "sg:classifiers":[
        {
            "category":"Building & Trades",
            "subcategory":"Construction",
            "type":"Services"
        }
    ],
    "sg:phone":"+44 1747 830687",
    "sg:postcode":"SP7 9AU",
    "sg:province":"Dorset",
    "sg:tags":[
        "builder"
    ],
    "wof:name":"J Pike & Sons",
    "wof:placetype":"venue"
},
  "geometry": {"coordinates":[-2.155759,51.041698],"type":"Point"}
}