{
  "type": "Feature",
  "properties": {
    "addr:full":"2 Ditchling Road Brighton East Sussex BN1 4SF",
    "addr:housenumber":"2",
    "addr:postcode":"bn1 4sf",
    "addr:street":"Ditchling Road",
    "iso:country":"GB",
    "sg:address":"2 Ditchling Road",
    "sg:city":"Brighton",
    "sg:classifiers":[
        {
            "category":"Shopping",
            "subcategory":"Shoes",
            "type":"Retail Goods"
        }
    ],
    "sg:phone":"+44 1273 684242",
    "sg:postcode":"BN1 4SF",
    "sg:province":"East Sussex",
    "sg:tags":[
        "shop"
    ],
    "wof:name":"Neat Feet Total Footcare Centre",
    "wof:placetype":"venue"
},
  "geometry": {"coordinates":[-0.134133,50.831936],"type":"Point"}
}