{
  "type": "Feature",
  "properties": {
    "addr:full":"Barnwell Manor, Barnwell Peterborough Cambridgeshire PE8 5PJ",
    "addr:postcode":"pe8 5pj",
    "addr:street":"Barnwell Peterborough",
    "iso:country":"GB",
    "sg:address":"Barnwell Manor, Barnwell",
    "sg:city":"Peterborough",
    "sg:classifiers":[
        {
            "category":"Shopping",
            "subcategory":"Antiques",
            "type":"Retail Goods"
        }
    ],
    "sg:phone":"+44 1832 274070",
    "sg:postcode":"PE8 5PJ",
    "sg:province":"Cambridgeshire",
    "wof:name":"Berengar Antiques Ltd.",
    "wof:placetype":"venue"
},
  "geometry": {"coordinates":[-0.4598770142,52.4525375366],"type":"Point"}
}