{
  "type": "Feature",
  "properties": {
    "addr:full":"Llanrwst Road, Llansanffraid Glan Conwy Colwyn Bay Conwy LL28 5LF",
    "addr:postcode":"ll28 5lf",
    "addr:street":"Llanrwst Road",
    "iso:country":"GB",
    "sg:address":"Llanrwst Road, Llansanffraid Glan Conwy",
    "sg:city":"Colwyn Bay",
    "sg:classifiers":[
        {
            "category":"Restaurant",
            "type":"Food & Drink"
        }
    ],
    "sg:postcode":"LL28 5LF",
    "sg:province":"Conwy",
    "wof:name":"The Old Rectory",
    "wof:placetype":"venue"
},
  "geometry": {"coordinates":[-3.7431828976,53.2893829346],"type":"Point"}
}