{
  "type": "Feature",
  "properties": {
    "iso:country":"GB",
    "sg:address":"11 Rushycroft, Mottram",
    "sg:city":"Hyde",
    "sg:classifiers":[
        {
            "category":"Building & Trades",
            "subcategory":"Construction",
            "type":"Services"
        }
    ],
    "sg:postcode":"SK14 6TD",
    "sg:province":"Cheshire",
    "sg:tags":[
        "builder"
    ],
    "wof:name":"Eckersley,C,",
    "wof:placetype":"venue"
},
  "geometry": {"coordinates":[-2.080884,53.454311],"type":"Point"}
}