{
  "type": "Feature",
  "properties": {
    "addr:full":"East Gartmillan Farm Airdrie North Lanarkshire ML6 0PW",
    "addr:postcode":"ml6 0pw",
    "addr:street":"East",
    "iso:country":"GB",
    "sg:address":"East Gartmillan Farm",
    "sg:city":"Airdrie",
    "sg:classifiers":[
        {
            "category":"Farming",
            "subcategory":"Dairy Farm",
            "type":"Manufacturing & Wholesale Goods"
        }
    ],
    "sg:phone":"+44 1236 760806",
    "sg:postcode":"ML6 0PW",
    "sg:province":"North Lanarkshire",
    "wof:name":"John Brown & Son",
    "wof:placetype":"venue"
},
  "geometry": {"coordinates":[-3.982489109,55.8689537048],"type":"Point"}
}