{
  "type": "Feature",
  "properties": {
    "addr:full":"23 Goodacre, Orton Goldhay Peterborough Cambridgeshire PE2 5NZ",
    "addr:housenumber":"23",
    "addr:postcode":"pe2 5nz",
    "addr:street":"Goodacre",
    "iso:country":"GB",
    "sg:address":"23 Goodacre, Orton Goldhay",
    "sg:city":"Peterborough",
    "sg:classifiers":[
        {
            "category":"Professional",
            "subcategory":"Detective & Security Services",
            "type":"Services"
        }
    ],
    "sg:phone":"+44 1733 233933",
    "sg:postcode":"PE2 5NZ",
    "sg:province":"Cambridgeshire",
    "sg:tags":[
        "alarm",
        "burglar",
        "system"
    ],
    "wof:name":"G C Techsecurity",
    "wof:placetype":"venue"
},
  "geometry": {"coordinates":[-0.287696,52.547977],"type":"Point"}
}