{
  "type": "Feature",
  "properties": {
    "addr:full":"1 Dole Lane Chorley Lancashire PR7 2RL",
    "addr:housenumber":"1",
    "addr:postcode":"pr7 2rl",
    "addr:street":"Dole Lane",
    "iso:country":"GB",
    "sg:address":"1 Dole Lane",
    "sg:city":"Chorley",
    "sg:classifiers":[
        {
            "category":"Restaurant",
            "type":"Food & Drink"
        }
    ],
    "sg:phone":"+44 1257 231975",
    "sg:postcode":"PR7 2RL",
    "sg:province":"Lancashire",
    "sg:tags":[
        "indian"
    ],
    "wof:name":"Hyatt Indian Cuisine The",
    "wof:placetype":"venue"
},
  "geometry": {"coordinates":[-2.6321339607,53.6520881653],"type":"Point"}
}