{
  "type": "Feature",
  "properties": {
    "addr:full":"12 Merton Park Pde Wimbledon Greater London SW19 3NT",
    "addr:housenumber":"12",
    "addr:postcode":"sw19 3nt",
    "addr:street":"Merton Park",
    "iso:country":"GB",
    "sg:address":"12 Merton Park Pde",
    "sg:city":"Wimbledon",
    "sg:classifiers":[
        {
            "category":"Building & Trades",
            "subcategory":"Cleaning & Sanitation",
            "type":"Services"
        }
    ],
    "sg:phone":"+44 20 8543 4727",
    "sg:postcode":"SW19 3NT",
    "sg:province":"Greater London",
    "sg:tags":[
        "dry",
        "control",
        "damp",
        "rot"
    ],
    "wof:name":"Pro-Tech Ltd",
    "wof:placetype":"venue"
},
  "geometry": {"coordinates":[-0.2134979963,51.4153938293],"type":"Point"}
}