{
  "type": "Feature",
  "properties": {
    "iso:country":"GB",
    "sg:address":"5 Centurion Business Centre, Bulwell",
    "sg:city":"Nottingham",
    "sg:classifiers":[
        {
            "category":"Professional",
            "subcategory":"Engineering",
            "type":"Services"
        }
    ],
    "sg:phone":"+44 115 973 9220",
    "sg:postcode":"NG6 8WA",
    "sg:province":"Nottinghamshire",
    "wof:name":"W S P Environmental Ltd.",
    "wof:placetype":"venue"
},
  "geometry": {"coordinates":[-1.1981639862,53.0011940002],"type":"Point"}
}