{
  "type": "Feature",
  "properties": {
    "iso:country":"GB",
    "sg:address":"64 High Street, Ecclesfield",
    "sg:city":"Sheffield",
    "sg:classifiers":[
        {
            "category":"Manufacturing",
            "subcategory":"Tools & Machinery",
            "type":"Manufacturing & Wholesale Goods"
        }
    ],
    "sg:phone":"+44 114 257 1113",
    "sg:postcode":"S35 9XD",
    "sg:province":"South Yorkshire",
    "sg:tags":[
        "society",
        "friendly"
    ],
    "wof:name":"B H Shield & Co.",
    "wof:placetype":"venue"
},
  "geometry": {"coordinates":[-1.464778,53.43927],"type":"Point"}
}