{
  "type": "Feature",
  "properties": {
    "iso:country":"GB",
    "sg:address":"150 Armley Road",
    "sg:city":"Leeds",
    "sg:classifiers":[
        {
            "category":"Manufacturing",
            "subcategory":"Electronics",
            "type":"Manufacturing & Wholesale Goods"
        }
    ],
    "sg:postcode":"LS12 2QQ",
    "sg:province":"West Yorkshire",
    "sg:tags":[
        "control",
        "component",
        "-",
        "electronic"
    ],
    "wof:name":"Premier Farnell Plc",
    "wof:placetype":"venue"
},
  "geometry": {"coordinates":[-1.578739,53.798752],"type":"Point"}
}