{
  "type": "Feature",
  "properties": {
    "addr:full":"Rowlandson House, 289-293 Ballards Lane North Finchley Greater London N12 8NP",
    "addr:housenumber":"289-293",
    "addr:postcode":"n12 8np",
    "addr:street":"Ballards Lane",
    "iso:country":"GB",
    "sg:address":"Rowlandson House, 289-293 Ballards Lane",
    "sg:city":"North Finchley",
    "sg:classifiers":[
        {
            "category":"Professional",
            "subcategory":"Business Services",
            "type":"Services"
        }
    ],
    "sg:phone":"+44 20 8492 0272",
    "sg:postcode":"N12 8NP",
    "sg:province":"Greater London",
    "sg:tags":[
        "information"
    ],
    "wof:name":"Ices England",
    "wof:placetype":"venue"
},
  "geometry": {"coordinates":[-0.1767240018,51.6149787903],"type":"Point"}
}