{
  "type": "Feature",
  "properties": {
    "addr:full":"12 The Woolmead Farnham Surrey GU9 7TX",
    "addr:housenumber":"12",
    "addr:postcode":"gu9 7tx",
    "addr:street":"The Woolmead Farnham",
    "iso:country":"GB",
    "sg:address":"12 The Woolmead",
    "sg:city":"Farnham",
    "sg:classifiers":[
        {
            "category":"Health Services",
            "subcategory":"Health Practitioner",
            "type":"Services"
        }
    ],
    "sg:phone":"+44 1252 718888",
    "sg:postcode":"GU9 7TX",
    "sg:province":"Surrey",
    "sg:tags":[
        "acupuncture"
    ],
    "wof:name":"Oriental Medical International Ltd.",
    "wof:placetype":"venue"
},
  "geometry": {"coordinates":[-0.7983689904,51.2118492126],"type":"Point"}
}