{
  "type": "Feature",
  "properties": {
    "addr:full":"Turnpike House, Tollgate, Chandlers Ford Eastleigh Hampshire SO53 3TG",
    "addr:postcode":"so53 3tg",
    "addr:street":"Turnpike;Tollgate Chandlers",
    "iso:country":"GB",
    "sg:address":"Turnpike House, Tollgate, Chandlers Ford",
    "sg:city":"Eastleigh",
    "sg:classifiers":[
        {
            "category":"Professional",
            "subcategory":"Detective & Security Services",
            "type":"Services"
        }
    ],
    "sg:postcode":"SO53 3TG",
    "sg:province":"Hampshire",
    "wof:name":"Risk Audit & Security Consultant Ltd",
    "wof:placetype":"venue"
},
  "geometry": {"coordinates":[-1.383811,50.966919],"type":"Point"}
}