{
  "type": "Feature",
  "properties": {
    "addr:full":"The Workshop, Furze Lane, Booton Norwich Norfolk NR10 4NU",
    "addr:postcode":"nr10 4nu",
    "addr:street":"Furze Lane",
    "iso:country":"GB",
    "sg:address":"The Workshop, Furze Lane, Booton",
    "sg:city":"Norwich",
    "sg:classifiers":[
        {
            "category":"Manufacturing",
            "subcategory":"Wood Products",
            "type":"Manufacturing & Wholesale Goods"
        }
    ],
    "sg:phone":"+44 1603 458033",
    "sg:postcode":"NR10 4NU",
    "sg:province":"Norfolk",
    "sg:tags":[
        "maker",
        "cabinet"
    ],
    "wof:name":"Darren Tubby Cabinet Makers",
    "wof:placetype":"venue"
},
  "geometry": {"coordinates":[1.125757,52.760761],"type":"Point"}
}