{
  "type": "Feature",
  "properties": {
    "iso:country":"GB",
    "sg:address":"16 West Way",
    "sg:city":"Oxford",
    "sg:classifiers":[
        {
            "category":"Communications",
            "type":"Services"
        }
    ],
    "sg:postcode":"OX2 0JH",
    "sg:province":"Oxfordshire",
    "sg:tags":[
        "telecommunication"
    ],
    "wof:name":"Knight Media Communications Ltd",
    "wof:placetype":"venue"
},
  "geometry": {"coordinates":[-1.292873,51.753513],"type":"Point"}
}