{
  "type": "Feature",
  "properties": {
    "addr:full":"9 Whitehall Terrace Sunderland Tyne and Wear SR4 7SW",
    "addr:housenumber":"9",
    "addr:postcode":"sr4 7sw",
    "addr:street":"Whitehall Terrace",
    "iso:country":"GB",
    "sg:address":"9 Whitehall Terrace",
    "sg:city":"Sunderland",
    "sg:classifiers":[
        {
            "category":"Food & Beverages",
            "subcategory":"Bakery",
            "type":"Retail Goods"
        }
    ],
    "sg:postcode":"SR4 7SW",
    "sg:province":"Tyne and Wear",
    "sg:tags":[
        "baker"
    ],
    "wof:name":"Whitehall Bakers",
    "wof:placetype":"venue"
},
  "geometry": {"coordinates":[-1.4137099981,54.9035491943],"type":"Point"}
}