{
  "type": "Feature",
  "properties": {
    "iso:country":"GB",
    "sg:address":"Higher Port View",
    "sg:city":"Saltash",
    "sg:classifiers":[
        {
            "category":"Health Services",
            "subcategory":"Hospital",
            "type":"Services"
        }
    ],
    "sg:phone":"+44 1752 857400",
    "sg:postcode":"PL12 4BU",
    "sg:province":"Cornwall",
    "wof:name":"St Barnabas Hospital",
    "wof:placetype":"venue"
},
  "geometry": {"coordinates":[-4.217719,50.407623],"type":"Point"}
}