{
  "type": "Feature",
  "properties": {
    "addr:full":"14 Harcourt Way, Selsey Chichester West Sussex PO20 0PF",
    "addr:housenumber":"14",
    "addr:postcode":"po20 0pf",
    "addr:street":"Harcourt Way",
    "iso:country":"GB",
    "sg:address":"14 Harcourt Way, Selsey",
    "sg:city":"Chichester",
    "sg:classifiers":[
        {
            "category":"Taxi",
            "type":"Transportation"
        },
        {
            "category":"Military Area",
            "subcategory":"Air Force Base",
            "type":"Public Place"
        }
    ],
    "sg:phone":"+44 1243 606854",
    "sg:postcode":"PO20 0PF",
    "sg:province":"West Sussex",
    "sg:tags":[
        "hire",
        "private",
        "vehicle"
    ],
    "wof:name":"Cannon Cars",
    "wof:placetype":"venue"
},
  "geometry": {"coordinates":[-0.7770419717,50.7368240356],"type":"Point"}
}