{
  "type": "Feature",
  "properties": {
    "addr:full":"Three Meadows, Rowney Green Lane, Rowney Grn Birmingham Worcestershire B48 7QF",
    "addr:postcode":"b48 7qf",
    "addr:street":"Green Lane Rowney Grn",
    "iso:country":"GB",
    "sg:address":"Three Meadows, Rowney Green Lane, Rowney Grn",
    "sg:city":"Birmingham",
    "sg:classifiers":[
        {
            "category":"Professional",
            "subcategory":"Engineering",
            "type":"Services"
        }
    ],
    "sg:phone":"+44 1527 62103",
    "sg:postcode":"B48 7QF",
    "sg:province":"Worcestershire",
    "wof:name":"Border Alldrive Tractors Ltd.",
    "wof:placetype":"venue"
},
  "geometry": {"coordinates":[-1.936547,52.343586],"type":"Point"}
}