{
  "type": "Feature",
  "properties": {
    "addr:full":"1 Lyndale Road Weymouth Dorset DT4 9AY",
    "addr:housenumber":"1",
    "addr:postcode":"dt4 9ay",
    "addr:street":"Lyndale Road",
    "iso:country":"GB",
    "sg:address":"1 Lyndale Road",
    "sg:city":"Weymouth",
    "sg:classifiers":[
        {
            "category":"Building & Trades",
            "subcategory":"Construction",
            "type":"Services"
        }
    ],
    "sg:phone":"+44 1305 777634",
    "sg:postcode":"DT4 9AY",
    "sg:province":"Dorset",
    "sg:tags":[
        "glazier",
        "decorator",
        "painter"
    ],
    "wof:name":"Wyke Services",
    "wof:placetype":"venue"
},
  "geometry": {"coordinates":[-2.4725780487,50.5883598328],"type":"Point"}
}