{
  "type": "Feature",
  "properties": {
    "addr:full":"Cock Street Norwich Norfolk NR9 4BD",
    "addr:postcode":"nr9 4bd",
    "addr:street":"Cock Street",
    "iso:country":"GB",
    "sg:address":"Cock Street",
    "sg:city":"Norwich",
    "sg:classifiers":[
        {
            "category":"Utilities",
            "subcategory":"Telephone",
            "type":"Services"
        }
    ],
    "sg:postcode":"NR9 4BD",
    "sg:province":"Norfolk",
    "sg:tags":[
        "telecommunication"
    ],
    "wof:name":"A P R Telecommunications",
    "wof:placetype":"venue"
},
  "geometry": {"coordinates":[1.1195189953,52.6247940063],"type":"Point"}
}