{
  "type": "Feature",
  "properties": {
    "iso:country":"GB",
    "sg:address":"194 Lockhurst La",
    "sg:city":"Coventry",
    "sg:classifiers":[
        {
            "category":"Personal",
            "subcategory":"Psychics & Astrologers",
            "type":"Services"
        }
    ],
    "sg:phone":"+44 24 7666 4962",
    "sg:postcode":"CV6 5NJ",
    "sg:province":"Warwickshire",
    "sg:tags":[
        "clairvoyant",
        "palmist"
    ],
    "wof:name":"The Fortune Tellers",
    "wof:placetype":"venue"
},
  "geometry": {"coordinates":[-1.503546,52.430786],"type":"Point"}
}