{
  "type": "Feature",
  "properties": {
    "iso:country":"GB",
    "sg:address":"22 Blake Road",
    "sg:city":"Great Yarmouth",
    "sg:classifiers":[
        {
            "category":"Building & Trades",
            "subcategory":"Plumbing",
            "type":"Services"
        }
    ],
    "sg:phone":"+44 1493 852056",
    "sg:postcode":"NR30 4LT",
    "sg:province":"Norfolk",
    "sg:tags":[
        "heating"
    ],
    "wof:name":"B R Newson Plumbers",
    "wof:placetype":"venue"
},
  "geometry": {"coordinates":[1.7357180119,52.6209106445],"type":"Point"}
}