{
  "type": "Feature",
  "properties": {
    "addr:full":"William Knox House, Britannic Way Neath Neath Port Talbot SA10 6EL",
    "addr:postcode":"sa10 6el",
    "addr:street":"William;Britannic Way",
    "iso:country":"GB",
    "sg:address":"William Knox House, Britannic Way",
    "sg:city":"Neath",
    "sg:classifiers":[
        {
            "category":"Professional",
            "subcategory":"Engineering",
            "type":"Services"
        }
    ],
    "sg:postcode":"SA10 6EL",
    "sg:province":"Neath Port Talbot",
    "sg:tags":[
        "contractor",
        "electrical",
        "engineer"
    ],
    "wof:name":"Switchgear & Instrumentation Ltd.",
    "wof:placetype":"venue"
},
  "geometry": {"coordinates":[-3.852478,51.646343],"type":"Point"}
}