{
  "type": "Feature",
  "properties": {
    "addr:full":"2 Harbour Street Ramsgate Kent CT11 8HA",
    "addr:housenumber":"2",
    "addr:postcode":"ct11 8ha",
    "addr:street":"Harbour Street Ramsgate",
    "iso:country":"GB",
    "sg:address":"2 Harbour Street",
    "sg:city":"Ramsgate",
    "sg:classifiers":[
        {
            "category":"Shopping",
            "subcategory":"Shoes",
            "type":"Retail Goods"
        }
    ],
    "sg:phone":"+44 1843 583643",
    "sg:postcode":"CT11 8HA",
    "sg:province":"Kent",
    "wof:name":"Timpson Shoe Repairs",
    "wof:placetype":"venue"
},
  "geometry": {"coordinates":[1.4200290442,51.3334960938],"type":"Point"}
}