{
  "type": "Feature",
  "properties": {
    "iso:country":"GB",
    "sg:address":"30a Green Lane",
    "sg:city":"Northwood",
    "sg:classifiers":[
        {
            "category":"Professional",
            "subcategory":"Accounting & Tax Preparation",
            "type":"Services"
        }
    ],
    "sg:phone":"+44 1923 825188",
    "sg:postcode":"HA6 2QB",
    "sg:province":"Greater London",
    "sg:tags":[
        "accountant",
        "chartered"
    ],
    "wof:name":"Ames & Co",
    "wof:placetype":"venue"
},
  "geometry": {"coordinates":[-0.427424,51.6119],"type":"Point"}
}