{
  "type": "Feature",
  "properties": {
    "iso:country":"GB",
    "sg:address":"New Market Hall, Ainsworth Street",
    "sg:city":"Blackburn",
    "sg:classifiers":[
        {
            "category":"Shopping",
            "subcategory":"Bicycles & Sporting Goods",
            "type":"Retail Goods"
        }
    ],
    "sg:phone":"+44 1254 59917",
    "sg:postcode":"BB1 6AS",
    "sg:province":"Lancashire",
    "sg:tags":[
        "dance",
        "balletwear"
    ],
    "wof:name":"The Ballet Shop",
    "wof:placetype":"venue"
},
  "geometry": {"coordinates":[-2.480399,53.748516],"type":"Point"}
}