{
  "type": "Feature",
  "properties": {
    "addr:full":"191 Ordnance Road Enfield Greater London EN3 6AB",
    "addr:housenumber":"191",
    "addr:postcode":"en3 6ab",
    "addr:street":"Ordnance Road",
    "iso:country":"GB",
    "sg:address":"191 Ordnance Road",
    "sg:city":"Enfield",
    "sg:classifiers":[
        {
            "category":"Fast Food",
            "type":"Food & Drink"
        },
        {
            "category":"Wholesale",
            "subcategory":"Groceries",
            "type":"Manufacturing & Wholesale Goods"
        }
    ],
    "sg:phone":"+44 1992 767741",
    "sg:postcode":"EN3 6AB",
    "sg:province":"Greater London",
    "sg:tags":[
        "away",
        "take",
        "supplier",
        "meal",
        "outlet",
        "pizza"
    ],
    "wof:name":"Pizza Parlour",
    "wof:placetype":"venue"
},
  "geometry": {"coordinates":[-0.0306509994,51.671131134],"type":"Point"}
}