{
  "type": "Feature",
  "properties": {
    "iso:country":"GB",
    "sg:address":"1 Calderhurst Lane, Astley",
    "sg:city":"Manchester",
    "sg:classifiers":[
        {
            "category":"Manufacturing",
            "subcategory":"Food",
            "type":"Manufacturing & Wholesale Goods"
        }
    ],
    "sg:phone":"+44 1942 874980",
    "sg:postcode":"M29 7BS",
    "sg:province":"Greater Manchester",
    "sg:tags":[
        "processing"
    ],
    "wof:name":"C B J Service Ltd.",
    "wof:placetype":"venue"
},
  "geometry": {"coordinates":[-2.455664,53.500778],"type":"Point"}
}