{
  "type": "Feature",
  "properties": {
    "iso:country":"GB",
    "sg:address":"City Wells House, Sidbury",
    "sg:city":"Worcester",
    "sg:classifiers":[
        {
            "category":"Real Estate",
            "subcategory":"Real Estate Agent",
            "type":"Services"
        }
    ],
    "sg:phone":"+44 1905 723438",
    "sg:postcode":"WR1 2HZ",
    "sg:province":"Worcestershire",
    "wof:name":"Knight Frank",
    "wof:placetype":"venue"
},
  "geometry": {"coordinates":[-2.2182190418,52.1881141663],"type":"Point"}
}