{
  "type": "Feature",
  "properties": {
    "iso:country":"GB",
    "sg:address":"4 Hinchwell Close, Marsdon Industrial Estate, Handsworth",
    "sg:city":"Sheffield",
    "sg:classifiers":[
        {
            "category":"Building & Trades",
            "subcategory":"Cleaning & Sanitation",
            "type":"Services"
        }
    ],
    "sg:phone":"+44 114 256 1411",
    "sg:postcode":"S13 9DF",
    "sg:province":"South Yorkshire",
    "sg:tags":[
        "dry",
        "control",
        "damp",
        "rot"
    ],
    "wof:name":"Timberwise",
    "wof:placetype":"venue"
},
  "geometry": {"coordinates":[-1.379039,53.37291],"type":"Point"}
}