{
  "type": "Feature",
  "properties": {
    "addr:full":"460 Wandsworth Road London Greater London SW8 3LX",
    "addr:housenumber":"460",
    "addr:postcode":"sw8 3lx",
    "addr:street":"Wandsworth Road",
    "iso:country":"GB",
    "sg:address":"460 Wandsworth Road",
    "sg:city":"London",
    "sg:classifiers":[
        {
            "category":"Organizations",
            "subcategory":"Non-profit Organization",
            "type":"Services"
        }
    ],
    "sg:phone":"+44 20 7622 9455",
    "sg:postcode":"SW8 3LX",
    "sg:province":"Greater London",
    "sg:tags":[
        "organisation",
        "voluntary",
        "charity"
    ],
    "wof:name":"The Lady Margaret Hall Settlement (Incorporated)",
    "wof:placetype":"venue"
},
  "geometry": {"coordinates":[-0.1421660036,51.4691238403],"type":"Point"}
}