{
  "type": "Feature",
  "properties": {
    "addr:full":"3 Station Street Lewes East Sussex BN7 2DA",
    "addr:housenumber":"3",
    "addr:postcode":"bn7 2da",
    "addr:street":"Station Street",
    "iso:country":"GB",
    "sg:address":"3 Station Street",
    "sg:city":"Lewes",
    "sg:classifiers":[
        {
            "category":"Bars & Pubs",
            "type":"Food & Drink"
        }
    ],
    "sg:phone":"+44 1273 474803",
    "sg:postcode":"BN7 2DA",
    "sg:province":"East Sussex",
    "sg:tags":[
        "pubs",
        "inn"
    ],
    "wof:name":"The Royal Oak",
    "wof:placetype":"venue"
},
  "geometry": {"coordinates":[0.0108439997,50.8728790283],"type":"Point"}
}