{
  "type": "Feature",
  "properties": {
    "addr:full":"Unit 5, Maling St, Ouseburn Newcastle Upon Tyne Tyne and Wear NE6 1LP",
    "addr:housenumber":"unit 5",
    "addr:postcode":"ne6 1lp",
    "addr:street":"St",
    "iso:country":"GB",
    "sg:address":"Unit 5, Maling St, Ouseburn",
    "sg:city":"Newcastle Upon Tyne",
    "sg:classifiers":[
        {
            "category":"Professional",
            "subcategory":"Printing & Photocopies",
            "type":"Services"
        }
    ],
    "sg:phone":"+44 191 276 7474",
    "sg:postcode":"NE6 1LP",
    "sg:province":"Tyne and Wear",
    "sg:tags":[
        "plate",
        "lithographic",
        "maker"
    ],
    "wof:name":"Comma Print",
    "wof:placetype":"venue"
},
  "geometry": {"coordinates":[-1.5881299973,54.9715995789],"type":"Point"}
}