{
  "type": "Feature",
  "properties": {
    "iso:country":"GB",
    "sg:address":"11 Littlemoor Road",
    "sg:city":"Pudsey",
    "sg:classifiers":[
        {
            "category":"Professional",
            "subcategory":"Art Services",
            "type":"Services"
        }
    ],
    "sg:phone":"+44 113 257 0002",
    "sg:postcode":"LS28 8AF",
    "sg:province":"West Yorkshire",
    "sg:tags":[
        "picture",
        "restoration",
        "framing"
    ],
    "wof:name":"Beaver Products",
    "wof:placetype":"venue"
},
  "geometry": {"coordinates":[-1.661123,53.791142],"type":"Point"}
}