{
  "type": "Feature",
  "properties": {
    "addr:full":"1 Urquhart Street Dundee Dundee City DD1 5NL",
    "addr:housenumber":"1",
    "addr:postcode":"dd1 5nl",
    "addr:street":"Urquhart Street",
    "iso:country":"GB",
    "sg:address":"1 Urquhart Street",
    "sg:city":"Dundee",
    "sg:classifiers":[
        {
            "category":"Wholesale",
            "subcategory":"Electrical",
            "type":"Manufacturing & Wholesale Goods"
        },
        {
            "category":"Shopping",
            "subcategory":"Computers & Home Electronics",
            "type":"Retail Goods"
        }
    ],
    "sg:phone":"+44 1382 224667",
    "sg:postcode":"DD1 5NL",
    "sg:province":"Dundee City",
    "sg:tags":[
        "wholesaler"
    ],
    "wof:name":"Holland House Electrical Co Ltd",
    "wof:placetype":"venue"
},
  "geometry": {"coordinates":[-2.9857358932,56.4602813721],"type":"Point"}
}