{
  "type": "Feature",
  "properties": {
    "iso:country":"GB",
    "sg:address":"Orchard House, 175 Doncaster Road, Thrybergh",
    "sg:city":"Rotherham",
    "sg:classifiers":[
        {
            "category":"Autos & Motor Vehicles",
            "subcategory":"Auto Supplies",
            "type":"Retail Goods"
        }
    ],
    "sg:phone":"+44 1709 850273",
    "sg:postcode":"S65 4NS",
    "sg:province":"South Yorkshire",
    "sg:tags":[
        "tyre"
    ],
    "wof:name":"A N A Tyre Co",
    "wof:placetype":"venue"
},
  "geometry": {"coordinates":[-1.293914,53.458698],"type":"Point"}
}