{
  "type": "Feature",
  "properties": {
    "addr:full":"Westbury Clo, Townsend Indust Est Dunstable Bedfordshire LU5 5BA",
    "addr:postcode":"lu5 5ba",
    "addr:street":"Townsend Indust Est",
    "iso:country":"GB",
    "sg:address":"Westbury Clo, Townsend Indust Est",
    "sg:city":"Dunstable",
    "sg:classifiers":[
        {
            "category":"Professional",
            "subcategory":"Engineering",
            "type":"Services"
        }
    ],
    "sg:phone":"+44 1582 666208",
    "sg:postcode":"LU5 5BA",
    "sg:province":"Bedfordshire",
    "sg:tags":[
        "precision",
        "engineer"
    ],
    "wof:name":"S C Engineering",
    "wof:placetype":"venue"
},
  "geometry": {"coordinates":[-0.5231710076,51.8997573853],"type":"Point"}
}