{
  "type": "Feature",
  "properties": {
    "iso:country":"GB",
    "sg:address":"4 East Grange, Fulwell",
    "sg:city":"Sunderland",
    "sg:classifiers":[
        {
            "category":"Building & Trades",
            "subcategory":"Construction",
            "type":"Services"
        }
    ],
    "sg:phone":"+44 191 548 5569",
    "sg:postcode":"SR5 1NX",
    "sg:province":"Tyne and Wear",
    "sg:tags":[
        "dry",
        "lining",
        "plasterers",
        "screeders"
    ],
    "wof:name":"A R P Professional Plasterers",
    "wof:placetype":"venue"
},
  "geometry": {"coordinates":[-1.388767004,54.9249916077],"type":"Point"}
}