{
  "type": "Feature",
  "properties": {
    "iso:country":"GB",
    "sg:address":"Station Street, South Wigston",
    "sg:city":"Wigston",
    "sg:classifiers":[
        {
            "category":"Retail",
            "subcategory":"Auto Repair",
            "type":"Services"
        }
    ],
    "sg:phone":"+44 116 277 8431",
    "sg:postcode":"LE18 4TH",
    "sg:province":"Leicestershire",
    "sg:tags":[
        "modification",
        "garage"
    ],
    "wof:name":"Station Street Garage",
    "wof:placetype":"venue"
},
  "geometry": {"coordinates":[-1.130579,52.580986],"type":"Point"}
}