{
  "type": "Feature",
  "properties": {
    "iso:country":"GB",
    "sg:address":"8 Pilmuir Holding, Newton Mearns",
    "sg:city":"Glasgow",
    "sg:classifiers":[
        {
            "category":"Food & Beverages",
            "subcategory":"Fruits & Vegetables",
            "type":"Retail Goods"
        }
    ],
    "sg:phone":"+44 141 639 1604",
    "sg:postcode":"G77 6PS",
    "sg:province":"East Ayrshire",
    "sg:tags":[
        "greengrocer"
    ],
    "wof:name":"Imrie Fruit",
    "wof:placetype":"venue"
},
  "geometry": {"coordinates":[-4.357861,55.762321],"type":"Point"}
}