{
  "type": "Feature",
  "properties": {
    "addr:full":"James Square Crieff Perth and Kinross PH7 3EY",
    "addr:postcode":"ph7 3ey",
    "addr:street":"James Square",
    "iso:country":"GB",
    "sg:address":"James Square",
    "sg:city":"Crieff",
    "sg:classifiers":[
        {
            "category":"Shopping",
            "subcategory":"Clothing, Apparel, & Fashions",
            "type":"Retail Goods"
        }
    ],
    "sg:phone":"+44 1764 655200",
    "sg:postcode":"PH7 3EY",
    "sg:province":"Perth and Kinross",
    "sg:tags":[
        "shop"
    ],
    "wof:name":"Edinburgh Woollen Mill",
    "wof:placetype":"venue"
},
  "geometry": {"coordinates":[-3.841555,56.372944],"type":"Point"}
}