{
  "type": "Feature",
  "properties": {
    "iso:country":"GB",
    "sg:address":"1 County Arc, Meliden Rd",
    "sg:city":"Prestatyn",
    "sg:classifiers":[
        {
            "category":"Personal",
            "subcategory":"Beauty Salon",
            "type":"Services"
        }
    ],
    "sg:phone":"+44 1745 852712",
    "sg:postcode":"LL19 9SB",
    "sg:province":"Denbighshire",
    "sg:tags":[
        "unisex",
        "hairdresser"
    ],
    "wof:name":"Ladyfayre",
    "wof:placetype":"venue"
},
  "geometry": {"coordinates":[-3.416739,53.336128],"type":"Point"}
}