{
  "type": "Feature",
  "properties": {
    "iso:country":"GB",
    "sg:address":"2 Birch Lane, Aldridge",
    "sg:city":"Walsall",
    "sg:classifiers":[
        {
            "category":"Wholesale",
            "subcategory":"Electrical",
            "type":"Manufacturing & Wholesale Goods"
        }
    ],
    "sg:phone":"+44 1922 453500",
    "sg:postcode":"WS9 0NF",
    "sg:province":"Staffordshire",
    "sg:tags":[
        "equipment",
        "refrigeration"
    ],
    "wof:name":"Coolgas Ltd",
    "wof:placetype":"venue"
},
  "geometry": {"coordinates":[-1.9002989531,52.616859436],"type":"Point"}
}