{
  "type": "Feature",
  "properties": {
    "addr:full":"5 North Quay Padstow Cornwall PL28 8AF",
    "addr:housenumber":"5",
    "addr:postcode":"pl28 8af",
    "addr:street":"North Quay",
    "iso:country":"GB",
    "sg:address":"5 North Quay",
    "sg:city":"Padstow",
    "sg:classifiers":[
        {
            "category":"Personal",
            "subcategory":"Beauty Salon",
            "type":"Services"
        }
    ],
    "sg:phone":"+44 1841 532474",
    "sg:postcode":"PL28 8AF",
    "sg:province":"Cornwall",
    "sg:tags":[
        "unisex",
        "hairdresser"
    ],
    "wof:name":"Guys & Dolls",
    "wof:placetype":"venue"
},
  "geometry": {"coordinates":[-4.938075,50.542122],"type":"Point"}
}