{
  "type": "Feature",
  "properties": {
    "addr:full":"86 Front Street Chester-le-street Durham DH3 3BB",
    "addr:housenumber":"86",
    "addr:postcode":"dh3 3bb",
    "addr:street":"Front Street",
    "iso:country":"GB",
    "sg:address":"86 Front Street",
    "sg:city":"Chester-le-street",
    "sg:classifiers":[
        {
            "category":"Home & Garden",
            "subcategory":"Hardware",
            "type":"Retail Goods"
        }
    ],
    "sg:phone":"+44 191 387 1567",
    "sg:postcode":"DH3 3BB",
    "sg:province":"Durham",
    "sg:tags":[
        "retailer",
        "diy"
    ],
    "wof:name":"Chester Diy",
    "wof:placetype":"venue"
},
  "geometry": {"coordinates":[-1.5736080408,54.8562965393],"type":"Point"}
}