{
  "type": "Feature",
  "properties": {
    "addr:full":"317/325 Corn Exchange Building, Fenwick Street Liverpool Merseyside L2 7QZ",
    "addr:housenumber":"317 / 325",
    "addr:postcode":"l2 7qz",
    "addr:street":"Fenwick Street",
    "iso:country":"GB",
    "sg:address":"317/325 Corn Exchange Building, Fenwick Street",
    "sg:city":"Liverpool",
    "sg:classifiers":[
        {
            "category":"Freight",
            "type":"Transportation"
        }
    ],
    "sg:phone":"+44 151 227 4506",
    "sg:postcode":"L2 7QZ",
    "sg:province":"Merseyside",
    "sg:tags":[
        "forwarders"
    ],
    "wof:name":"Mersey Forwarding Co. (North West) Ltd.",
    "wof:placetype":"venue"
},
  "geometry": {"coordinates":[-2.9918398857,53.4056015015],"type":"Point"}
}