{
  "type": "Feature",
  "properties": {
    "addr:full":"62a Chatsworth Road London Greater London E5 0LS",
    "addr:housenumber":"62a",
    "addr:postcode":"e5 0ls",
    "addr:street":"Chatsworth Road",
    "iso:country":"GB",
    "sg:address":"62a Chatsworth Road",
    "sg:city":"London",
    "sg:classifiers":[
        {
            "category":"Professional",
            "subcategory":"Engineering",
            "type":"Services"
        },
        {
            "category":"Utilities",
            "subcategory":"Electric",
            "type":"Services"
        },
        {
            "category":"Building & Trades",
            "subcategory":"Electrical",
            "type":"Services"
        }
    ],
    "sg:phone":"+44 20 8533 7234",
    "sg:postcode":"E5 0LS",
    "sg:province":"Greater London",
    "sg:tags":[
        "engineer",
        "electrician",
        "contractor"
    ],
    "wof:name":"Tjaden Ltd",
    "wof:placetype":"venue"
},
  "geometry": {"coordinates":[-0.0446159989,51.5535697937],"type":"Point"}
}