{
  "type": "Feature",
  "properties": {
    "addr:full":"4-8 Tulketh St Southport Lancashire PR8 1AQ",
    "addr:housenumber":"4-8",
    "addr:postcode":"pr8 1aq",
    "addr:street":"Tulketh St",
    "iso:country":"GB",
    "sg:address":"4-8 Tulketh St",
    "sg:city":"Southport",
    "sg:classifiers":[
        {
            "category":"Shopping",
            "subcategory":"Bicycles & Sporting Goods",
            "type":"Retail Goods"
        }
    ],
    "sg:phone":"+44 1704 534017",
    "sg:postcode":"PR8 1AQ",
    "sg:province":"Lancashire",
    "sg:tags":[
        "equipment",
        "camping"
    ],
    "wof:name":"Famous Army Stores Ltd",
    "wof:placetype":"venue"
},
  "geometry": {"coordinates":[-3.004608,53.64682],"type":"Point"}
}