{
  "type": "Feature",
  "properties": {
    "addr:full":"The Old Granary, Pinkney Park Malmesbury Wiltshire SN16 0NX",
    "addr:postcode":"sn16 0nx",
    "addr:street":"Pinkney Park",
    "iso:country":"GB",
    "sg:address":"The Old Granary, Pinkney Park",
    "sg:city":"Malmesbury",
    "sg:classifiers":[
        {
            "category":"Professional",
            "subcategory":"Computer Services",
            "type":"Services"
        }
    ],
    "sg:postcode":"SN16 0NX",
    "sg:province":"Wiltshire",
    "sg:tags":[
        "system",
        "software"
    ],
    "wof:name":"Lenticular Designs Ltd.",
    "wof:placetype":"venue"
},
  "geometry": {"coordinates":[-2.196278,51.580215],"type":"Point"}
}