{
  "type": "Feature",
  "properties": {
    "addr:full":"3 Royden Cres, Billinge Wigan Lancashire WN5 7LL",
    "addr:housenumber":"3",
    "addr:postcode":"wn5 7ll",
    "addr:street":"Royden Cres",
    "iso:country":"GB",
    "sg:address":"3 Royden Cres, Billinge",
    "sg:city":"Wigan",
    "sg:classifiers":[
        {
            "category":"Professional",
            "subcategory":"Engineering",
            "type":"Services"
        }
    ],
    "sg:phone":"+44 1744 895076",
    "sg:postcode":"WN5 7LL",
    "sg:province":"Lancashire",
    "sg:tags":[
        "contractor",
        "electrical",
        "engineer"
    ],
    "wof:name":"H & H Electrical Services Ltd",
    "wof:placetype":"venue"
},
  "geometry": {"coordinates":[-2.702862,53.498722],"type":"Point"}
}