{
  "type": "Feature",
  "properties": {
    "addr:full":"67 Low Street Keighley West Yorkshire BD21 3QP",
    "addr:housenumber":"67",
    "addr:postcode":"bd21 3qp",
    "addr:street":"Low Street",
    "iso:country":"GB",
    "sg:address":"67 Low Street",
    "sg:city":"Keighley",
    "sg:classifiers":[
        {
            "category":"Fast Food",
            "type":"Food & Drink"
        },
        {
            "category":"Cafe",
            "type":"Food & Drink"
        }
    ],
    "sg:postcode":"BD21 3QP",
    "sg:province":"West Yorkshire",
    "sg:tags":[
        "tea",
        "away",
        "room",
        "take"
    ],
    "wof:name":"Thomson,Margaret,",
    "wof:placetype":"venue"
},
  "geometry": {"coordinates":[-1.9082189798,53.8658599854],"type":"Point"}
}