{
  "type": "Feature",
  "properties": {
    "iso:country":"GB",
    "sg:address":"1 Hertford House, Farm Close",
    "sg:city":"Radlett",
    "sg:classifiers":[
        {
            "category":"Communications",
            "subcategory":"Newspaper",
            "type":"Services"
        }
    ],
    "sg:phone":"+44 1923 851701",
    "sg:postcode":"WD7 9AB",
    "sg:province":"Hertfordshire",
    "sg:tags":[
        "magazine"
    ],
    "wof:name":"Finlayson Media Communications Ltd.",
    "wof:placetype":"venue"
},
  "geometry": {"coordinates":[-0.3172090054,51.6835746765],"type":"Point"}
}