{
  "type": "Feature",
  "properties": {
    "addr:full":"Pegasus Wa, Bowerhill Trading Estate Melksham Wiltshire SN12 6TR",
    "addr:postcode":"sn12 6tr",
    "addr:street":"Pegasus Wa;Melksham",
    "iso:country":"GB",
    "sg:address":"Pegasus Wa, Bowerhill Trading Estate",
    "sg:city":"Melksham",
    "sg:classifiers":[
        {
            "category":"Professional",
            "subcategory":"Engineering",
            "type":"Services"
        }
    ],
    "sg:phone":"+44 1225 707646",
    "sg:postcode":"SN12 6TR",
    "sg:province":"Wiltshire",
    "sg:tags":[
        "precision",
        "engineer"
    ],
    "wof:name":"Kristek Precision Ltd.",
    "wof:placetype":"venue"
},
  "geometry": {"coordinates":[-2.13560009,51.3740653992],"type":"Point"}
}