{
  "type": "Feature",
  "properties": {
    "addr:full":"28 Park Street Luton Bedfordshire LU1 3ET",
    "addr:housenumber":"28",
    "addr:postcode":"lu1 3et",
    "addr:street":"Park Street",
    "iso:country":"GB",
    "sg:address":"28 Park Street",
    "sg:city":"Luton",
    "sg:classifiers":[
        {
            "category":"Shopping",
            "subcategory":"Clothing, Apparel, & Fashions",
            "type":"Retail Goods"
        }
    ],
    "sg:phone":"+44 1582 483440",
    "sg:postcode":"LU1 3ET",
    "sg:province":"Bedfordshire",
    "sg:tags":[
        "shop"
    ],
    "wof:name":"Earley's Female Clothing",
    "wof:placetype":"venue"
},
  "geometry": {"coordinates":[-0.4119929969,51.8774909973],"type":"Point"}
}