{
  "type": "Feature",
  "properties": {
    "iso:country":"GB",
    "sg:address":"42 Fitzgerald Avenue",
    "sg:city":"Herne Bay",
    "sg:classifiers":[
        {
            "category":"Arts & Performance",
            "subcategory":"Music",
            "type":"Entertainment"
        }
    ],
    "sg:phone":"+44 1227 370851",
    "sg:postcode":"CT6 8NA",
    "sg:province":"Kent",
    "sg:tags":[
        "mobile",
        "disco"
    ],
    "wof:name":"Skyline Discos",
    "wof:placetype":"venue"
},
  "geometry": {"coordinates":[1.105502,51.365204],"type":"Point"}
}