{
  "type": "Feature",
  "properties": {
    "iso:country":"GB",
    "sg:address":"Empire House, Mount Stuart Square Docks",
    "sg:city":"Cardiff",
    "sg:classifiers":[
        {
            "category":"Government",
            "subcategory":"Embassy",
            "type":"Public Place"
        }
    ],
    "sg:postcode":"CF10 5QZ",
    "sg:province":"Cardiff",
    "sg:tags":[
        "consulate"
    ],
    "wof:name":"Turkish Consulate",
    "wof:placetype":"venue"
},
  "geometry": {"coordinates":[-3.166886,51.464985],"type":"Point"}
}