{
  "type": "Feature",
  "properties": {
    "addr:full":"Chelmsford College, Moulsham St Chelmsford Essex CM2 0JQ",
    "addr:postcode":"cm2 0jq",
    "addr:street":"Moulsham St",
    "iso:country":"GB",
    "sg:address":"Chelmsford College, Moulsham St",
    "sg:city":"Chelmsford",
    "sg:classifiers":[
        {
            "category":"Professional",
            "subcategory":"Lawyer & Legal Services",
            "type":"Services"
        }
    ],
    "sg:phone":"+44 1245 256272",
    "sg:postcode":"CM2 0JQ",
    "sg:province":"Essex",
    "sg:tags":[
        "advice",
        "counselling"
    ],
    "wof:name":"Essex Returners Unit",
    "wof:placetype":"venue"
},
  "geometry": {"coordinates":[0.477891,51.731918],"type":"Point"}
}