{
  "type": "Feature",
  "properties": {
    "addr:full":"301 Cirencester Business Park, Love Lane Cirencester Gloucestershire GL7 1XD",
    "addr:housenumber":"301",
    "addr:postcode":"gl7 1xd",
    "addr:street":"Cirencester Business Park Love Lane",
    "iso:country":"GB",
    "sg:address":"301 Cirencester Business Park, Love Lane",
    "sg:city":"Cirencester",
    "sg:classifiers":[
        {
            "category":"Utilities",
            "type":"Services"
        }
    ],
    "sg:phone":"+44 1285 653782",
    "sg:postcode":"GL7 1XD",
    "sg:province":"Gloucestershire",
    "sg:tags":[
        "internet"
    ],
    "wof:name":"Weblinks Advertising Ltd.",
    "wof:placetype":"venue"
},
  "geometry": {"coordinates":[-1.953541,51.718548],"type":"Point"}
}