{
  "type": "Feature",
  "properties": {
    "iso:country":"GB",
    "sg:address":"11 Buttermarket Street",
    "sg:city":"Warrington",
    "sg:classifiers":[
        {
            "category":"Shopping",
            "subcategory":"Clothing, Apparel, & Fashions",
            "type":"Retail Goods"
        },
        {
            "category":"Shopping",
            "subcategory":"Baby Store",
            "type":"Retail Goods"
        }
    ],
    "sg:phone":"+44 1925 415134",
    "sg:postcode":"WA1 2LY",
    "sg:province":"Cheshire",
    "sg:tags":[
        "child",
        "childrens",
        "babywear"
    ],
    "wof:name":"Ethel Austin Ltd.",
    "wof:placetype":"venue"
},
  "geometry": {"coordinates":[-2.592654,53.389465],"type":"Point"}
}