{
  "type": "Feature",
  "properties": {
    "iso:country":"GB",
    "sg:address":"Unit 4 Techno Trading Estate",
    "sg:city":"Swindon",
    "sg:classifiers":[
        {
            "category":"Manufacturing",
            "subcategory":"Glass & Minerals",
            "type":"Manufacturing & Wholesale Goods"
        }
    ],
    "sg:postcode":"SN2 8HB",
    "sg:province":"Wiltshire",
    "sg:tags":[
        "mould"
    ],
    "wof:name":"Retrac Composites Ltd.",
    "wof:placetype":"venue"
},
  "geometry": {"coordinates":[-1.76266,51.576626],"type":"Point"}
}