{
  "type": "Feature",
  "properties": {
    "addr:full":"5a Brunel Precinct, Off West Street Somerton Somerset TA11 7PY",
    "addr:housenumber":"5a",
    "addr:postcode":"ta11 7py",
    "addr:street":"West Street",
    "iso:country":"GB",
    "sg:address":"5a Brunel Precinct, Off West Street",
    "sg:city":"Somerton",
    "sg:classifiers":[
        {
            "category":"Food & Beverages",
            "subcategory":"Specialty",
            "type":"Retail Goods"
        },
        {
            "category":"Food & Beverages",
            "subcategory":"Bakery",
            "type":"Retail Goods"
        },
        {
            "category":"Deli",
            "type":"Food & Drink"
        }
    ],
    "sg:phone":"+44 1458 274066",
    "sg:postcode":"TA11 7PY",
    "sg:province":"Somerset",
    "sg:tags":[
        "product",
        "health",
        "baker",
        "delicatessen"
    ],
    "wof:name":"Cobbs Delicatessen",
    "wof:placetype":"venue"
},
  "geometry": {"coordinates":[-2.734899044,51.0541648865],"type":"Point"}
}