{
  "type": "Feature",
  "properties": {
    "iso:country":"GB",
    "sg:address":"St Johns Road",
    "sg:city":"Boston",
    "sg:classifiers":[
        {
            "category":"Building & Trades",
            "subcategory":"Equipment Rental",
            "type":"Services"
        }
    ],
    "sg:phone":"+44 1205 355450",
    "sg:postcode":"PE21 6BE",
    "sg:province":"Lincolnshire",
    "sg:tags":[
        "plant",
        "machinery"
    ],
    "wof:name":"A-Plant Hire",
    "wof:placetype":"venue"
},
  "geometry": {"coordinates":[-0.020477,52.971912],"type":"Point"}
}