{
  "type": "Feature",
  "properties": {
    "addr:full":"46 St Pauls Terrace Swansea Carmarthenshire SA4 4EZ",
    "addr:housenumber":"46",
    "addr:postcode":"sa4 4ez",
    "addr:street":"St Pauls Terrace",
    "iso:country":"GB",
    "sg:address":"46 St Pauls Terrace",
    "sg:city":"Swansea",
    "sg:classifiers":[
        {
            "category":"Building & Trades",
            "subcategory":"Construction",
            "type":"Services"
        }
    ],
    "sg:phone":"+44 1792 895753",
    "sg:postcode":"SA4 4EZ",
    "sg:province":"Carmarthenshire",
    "sg:tags":[
        "builder"
    ],
    "wof:name":"D B M Building & Maintenance",
    "wof:placetype":"venue"
},
  "geometry": {"coordinates":[-4.0295782089,51.6597862244],"type":"Point"}
}