{
  "type": "Feature",
  "properties": {
    "iso:country":"GB",
    "sg:address":"11 West St",
    "sg:city":"Alford",
    "sg:classifiers":[
        {
            "category":"Shopping",
            "type":"Retail Goods"
        }
    ],
    "sg:postcode":"LN13 9DG",
    "sg:province":"Lincolnshire",
    "sg:tags":[
        "part",
        "accessory"
    ],
    "wof:name":"Rixon,Peter D R,",
    "wof:placetype":"venue"
},
  "geometry": {"coordinates":[0.1764560044,53.26039505],"type":"Point"}
}