{
  "type": "Feature",
  "properties": {
    "addr:full":"C A Site, Longshot La Bracknell Berkshire RG12 1RL",
    "addr:postcode":"rg12 1rl",
    "addr:street":"La",
    "iso:country":"GB",
    "sg:address":"C A Site, Longshot La",
    "sg:city":"Bracknell",
    "sg:classifiers":[
        {
            "category":"Utilities",
            "subcategory":"Refuse",
            "type":"Services"
        }
    ],
    "sg:phone":"+44 1344 424915",
    "sg:postcode":"RG12 1RL",
    "sg:province":"Berkshire",
    "sg:tags":[
        "disposal",
        "waste"
    ],
    "wof:name":"Park Environmental Services Ltd",
    "wof:placetype":"venue"
},
  "geometry": {"coordinates":[-0.7710379958,51.4166908264],"type":"Point"}
}