{
  "type": "Feature",
  "properties": {
    "addr:full":"52 New House Park St Albans Hertfordshire AL1 1UJ",
    "addr:housenumber":"52",
    "addr:postcode":"al1 1uj",
    "addr:street":"Park",
    "iso:country":"GB",
    "sg:address":"52 New House Park",
    "sg:city":"St Albans",
    "sg:classifiers":[
        {
            "category":"Home & Garden",
            "subcategory":"Home Furnishings",
            "type":"Retail Goods"
        }
    ],
    "sg:phone":"+44 1727 835678",
    "sg:postcode":"AL1 1UJ",
    "sg:province":"Hertfordshire",
    "sg:tags":[
        "merchant",
        "diy",
        "decorators'"
    ],
    "wof:name":"Abbey Decorating Supplies",
    "wof:placetype":"venue"
},
  "geometry": {"coordinates":[-0.3131439984,51.7355995178],"type":"Point"}
}