{
  "type": "Feature",
  "properties": {
    "addr:full":"448 Stafford Road Wolverhampton Staffordshire WV10 6AN",
    "addr:housenumber":"448",
    "addr:postcode":"wv10 6an",
    "addr:street":"Stafford Road",
    "iso:country":"GB",
    "sg:address":"448 Stafford Road",
    "sg:city":"Wolverhampton",
    "sg:classifiers":[
        {
            "category":"Food & Beverages",
            "subcategory":"Meat & Fish",
            "type":"Retail Goods"
        }
    ],
    "sg:phone":"+44 1902 782229",
    "sg:postcode":"WV10 6AN",
    "sg:province":"Staffordshire",
    "sg:tags":[
        "butcher"
    ],
    "wof:name":"H C Kay",
    "wof:placetype":"venue"
},
  "geometry": {"coordinates":[-2.1305708885,52.6176452637],"type":"Point"}
}