{
  "type": "Feature",
  "properties": {
    "iso:country":"GB",
    "sg:address":"7 Garth Way",
    "sg:city":"Northallerton",
    "sg:classifiers":[
        {
            "category":"Shopping",
            "subcategory":"Baby Store",
            "type":"Retail Goods"
        }
    ],
    "sg:postcode":"DL7 8NS",
    "sg:province":"North Yorkshire",
    "sg:tags":[
        "nursery",
        "accessory"
    ],
    "wof:name":"The Mulberry Bush",
    "wof:placetype":"venue"
},
  "geometry": {"coordinates":[-1.444912,54.332104],"type":"Point"}
}