{
  "type": "Feature",
  "properties": {
    "addr:full":"5 Salters Way Dunstable Bedfordshire LU6 1BT",
    "addr:housenumber":"5",
    "addr:postcode":"lu6 1bt",
    "addr:street":"Salters Way",
    "iso:country":"GB",
    "sg:address":"5 Salters Way",
    "sg:city":"Dunstable",
    "sg:classifiers":[
        {
            "category":"Freight",
            "type":"Transportation"
        },
        {
            "category":"Government",
            "subcategory":"Post Office",
            "type":"Public Place"
        }
    ],
    "sg:postcode":"LU6 1BT",
    "sg:province":"Bedfordshire",
    "sg:tags":[
        "haulage",
        "messenger",
        "courier",
        "road"
    ],
    "wof:name":"Bluebird Express",
    "wof:placetype":"venue"
},
  "geometry": {"coordinates":[-0.538964,51.896034],"type":"Point"}
}