{
  "type": "Feature",
  "properties": {
    "iso:country":"GB",
    "sg:address":"6 Brook House, Northbrook Street",
    "sg:city":"Newbury",
    "sg:classifiers":[
        {
            "category":"Personal",
            "subcategory":"Beauty Salon",
            "type":"Services"
        }
    ],
    "sg:phone":"+44 1635 40402",
    "sg:postcode":"RG14 1AN",
    "sg:province":"Berkshire",
    "sg:tags":[
        "unisex",
        "hairdresser"
    ],
    "wof:name":"Debretts Hair Studio",
    "wof:placetype":"venue"
},
  "geometry": {"coordinates":[-1.3245220184,51.4021072388],"type":"Point"}
}