{
  "type": "Feature",
  "properties": {
    "addr:full":"Cut Lane, Sandy Brow Liverpool Lancashire L33 3AE",
    "addr:postcode":"l33 3ae",
    "addr:street":"Cut Lane;Brow",
    "iso:country":"GB",
    "sg:address":"Cut Lane, Sandy Brow",
    "sg:city":"Liverpool",
    "sg:classifiers":[
        {
            "category":"Transit Center",
            "subcategory":"Passenger",
            "type":"Transportation"
        }
    ],
    "sg:phone":"+44 151 546 0308",
    "sg:postcode":"L33 3AE",
    "sg:province":"Lancashire",
    "sg:tags":[
        "boarding",
        "kennel",
        "catteries"
    ],
    "wof:name":"Aristocats Boarding Cattery",
    "wof:placetype":"venue"
},
  "geometry": {"coordinates":[-2.8258800507,53.4706039429],"type":"Point"}
}