{
  "type": "Feature",
  "properties": {
    "iso:country":"GB",
    "sg:address":"Unit 1 Grove Court, Station Road, Langford",
    "sg:city":"Biggleswade",
    "sg:classifiers":[
        {
            "category":"Professional",
            "subcategory":"Engineering",
            "type":"Services"
        }
    ],
    "sg:phone":"+44 1462 700910",
    "sg:postcode":"SG18 9PD",
    "sg:province":"Bedfordshire",
    "sg:tags":[
        "contractor",
        "electrical",
        "engineer"
    ],
    "wof:name":"Danbury Maintenance Services",
    "wof:placetype":"venue"
},
  "geometry": {"coordinates":[-0.2701739967,52.0532455444],"type":"Point"}
}