{
  "type": "Feature",
  "properties": {
    "iso:country":"GB",
    "sg:address":"47 Mersey Sq",
    "sg:city":"Stockport",
    "sg:classifiers":[
        {
            "category":"Shopping",
            "subcategory":"Clothing, Apparel, & Fashions",
            "type":"Retail Goods"
        }
    ],
    "sg:postcode":"SK1 1NU",
    "sg:province":"Cheshire",
    "sg:tags":[
        "ladieswear"
    ],
    "wof:name":"Hornby,Rebecca,",
    "wof:placetype":"venue"
},
  "geometry": {"coordinates":[-2.1621389389,53.4096183777],"type":"Point"}
}