{
  "type": "Feature",
  "properties": {
    "addr:full":"140 Woodside Street Coatbridge North Lanarkshire ML5 5NS",
    "addr:housenumber":"140",
    "addr:postcode":"ml5 5ns",
    "addr:street":"Woodside Street",
    "iso:country":"GB",
    "sg:address":"140 Woodside Street",
    "sg:city":"Coatbridge",
    "sg:classifiers":[
        {
            "category":"Manufacturing",
            "subcategory":"Petroleum Products",
            "type":"Manufacturing & Wholesale Goods"
        }
    ],
    "sg:phone":"+44 1236 422822",
    "sg:postcode":"ML5 5NS",
    "sg:province":"North Lanarkshire",
    "sg:tags":[
        "double",
        "glazing"
    ],
    "wof:name":"Aluclad Ltd.",
    "wof:placetype":"venue"
},
  "geometry": {"coordinates":[-4.0492258072,55.8483390808],"type":"Point"}
}