{
  "type": "Feature",
  "properties": {
    "addr:full":"3 Mason La Solihull Warwickshire B94 5JJ",
    "addr:housenumber":"3",
    "addr:postcode":"b94 5jj",
    "addr:street":"Mason La",
    "iso:country":"GB",
    "sg:address":"3 Mason La",
    "sg:city":"Solihull",
    "sg:classifiers":[
        {
            "category":"Building & Trades",
            "subcategory":"Construction",
            "type":"Services"
        }
    ],
    "sg:phone":"+44 1564 702873",
    "sg:postcode":"B94 5JJ",
    "sg:province":"Warwickshire",
    "sg:tags":[
        "joiner",
        "carpenter"
    ],
    "wof:name":"Fitted Interiors",
    "wof:placetype":"venue"
},
  "geometry": {"coordinates":[-1.840939045,52.3666343689],"type":"Point"}
}