{
  "type": "Feature",
  "properties": {
    "iso:country":"GB",
    "sg:address":"26 Rectory Lane, Houghton Conquest",
    "sg:city":"Bedford",
    "sg:classifiers":[
        {
            "category":"Food & Beverages",
            "subcategory":"Meat & Fish",
            "type":"Retail Goods"
        }
    ],
    "sg:phone":"+44 1234 740332",
    "sg:postcode":"MK45 3LD",
    "sg:province":"Bedfordshire",
    "sg:tags":[
        "butcher"
    ],
    "wof:name":"M & C West & Son",
    "wof:placetype":"venue"
},
  "geometry": {"coordinates":[-0.477384001,52.0610466003],"type":"Point"}
}