{
  "type": "Feature",
  "properties": {
    "addr:full":"Unit 2, 2 London Road Sevenoaks Kent TN15 6ET",
    "addr:housenumber":"unit;2",
    "addr:postcode":"tn15 6et",
    "addr:street":"London Road",
    "iso:country":"GB",
    "sg:address":"Unit 2, 2 London Road",
    "sg:city":"Sevenoaks",
    "sg:classifiers":[
        {
            "category":"Manufacturing",
            "subcategory":"Petroleum Products",
            "type":"Manufacturing & Wholesale Goods"
        }
    ],
    "sg:postcode":"TN15 6ET",
    "sg:province":"Kent",
    "sg:tags":[
        "double",
        "glazing"
    ],
    "wof:name":"Longfield Windows",
    "wof:placetype":"venue"
},
  "geometry": {"coordinates":[0.2795459926,51.3325767517],"type":"Point"}
}