{
  "type": "Feature",
  "properties": {
    "addr:full":"608 Tollcross Rd Glasgow Glasgow City G32 8TE",
    "addr:housenumber":"608",
    "addr:postcode":"g32 8te",
    "addr:street":"Tollcross Rd",
    "iso:country":"GB",
    "sg:address":"608 Tollcross Rd",
    "sg:city":"Glasgow",
    "sg:classifiers":[
        {
            "category":"Home & Garden",
            "subcategory":"Home Furnishings",
            "type":"Retail Goods"
        }
    ],
    "sg:phone":"+44 141 556 2030",
    "sg:postcode":"G32 8TE",
    "sg:province":"Glasgow City",
    "sg:tags":[
        "blind",
        "curtain",
        "fitting"
    ],
    "wof:name":"Park View Furnishings",
    "wof:placetype":"venue"
},
  "geometry": {"coordinates":[-4.1805157661,55.8443565369],"type":"Point"}
}