{
  "type": "Feature",
  "properties": {
    "iso:country":"GB",
    "sg:address":"542 Wimborne Road",
    "sg:city":"Bournemouth",
    "sg:classifiers":[
        {
            "category":"Home & Garden",
            "subcategory":"Household Appliances",
            "type":"Retail Goods"
        }
    ],
    "sg:postcode":"BH9 2EX",
    "sg:province":"Dorset",
    "sg:tags":[
        "domestic",
        "centre"
    ],
    "wof:name":"Graham's Electrical",
    "wof:placetype":"venue"
},
  "geometry": {"coordinates":[-1.878429,50.745018],"type":"Point"}
}