{
  "type": "Feature",
  "properties": {
    "addr:full":"Lexton Lodge Ind Est, Crowborough Hill Crowborough East Sussex TN6 2NQ",
    "addr:postcode":"tn6 2nq",
    "iso:country":"GB",
    "sg:address":"Lexton Lodge Ind Est, Crowborough Hill",
    "sg:city":"Crowborough",
    "sg:classifiers":[
        {
            "category":"Utilities",
            "subcategory":"Natural Gas",
            "type":"Services"
        }
    ],
    "sg:phone":"+44 1892 668333",
    "sg:postcode":"TN6 2NQ",
    "sg:province":"East Sussex",
    "sg:tags":[
        "control",
        "energy",
        "management",
        "system"
    ],
    "wof:name":"Ridley-buck Security Ltd",
    "wof:placetype":"venue"
},
  "geometry": {"coordinates":[0.171893,51.053196],"type":"Point"}
}