{
  "type": "Feature",
  "properties": {
    "iso:country":"GB",
    "sg:address":"37 London Road",
    "sg:city":"Coventry",
    "sg:classifiers":[
        {
            "category":"Manufacturing",
            "subcategory":"Signs",
            "type":"Manufacturing & Wholesale Goods"
        }
    ],
    "sg:phone":"+44 24 7625 6471",
    "sg:postcode":"CV1 2JP",
    "sg:province":"West Midlands",
    "sg:tags":[
        "writer"
    ],
    "wof:name":"Signhere",
    "wof:placetype":"venue"
},
  "geometry": {"coordinates":[-1.500351,52.403416],"type":"Point"}
}