{
  "type": "Feature",
  "properties": {
    "addr:full":"Rear Of 28-30 Victoria Road, Aston Birmingham West Midlands B6 5HA",
    "addr:housenumber":"rear of 28-30",
    "addr:postcode":"b6 5ha",
    "addr:street":"Victoria Road",
    "iso:country":"GB",
    "sg:address":"Rear Of 28-30 Victoria Road, Aston",
    "sg:city":"Birmingham",
    "sg:classifiers":[
        {
            "category":"Retail",
            "subcategory":"Auto Repair",
            "type":"Services"
        }
    ],
    "sg:phone":"+44 121 507 1610",
    "sg:postcode":"B6 5HA",
    "sg:province":"West Midlands",
    "sg:tags":[
        "modification",
        "garage",
        "related"
    ],
    "wof:name":"C R C Motors",
    "wof:placetype":"venue"
},
  "geometry": {"coordinates":[-1.8911989927,52.5023040771],"type":"Point"}
}