{
  "type": "Feature",
  "properties": {
    "iso:country":"GB",
    "sg:address":"64 Moffats Lane, Brookmans Park",
    "sg:city":"Hatfield",
    "sg:classifiers":[
        {
            "category":"Real Estate",
            "subcategory":"Developer",
            "type":"Services"
        },
        {
            "category":"Organizations",
            "subcategory":"Membership Organization",
            "type":"Services"
        }
    ],
    "sg:phone":"+44 1707 658320",
    "sg:postcode":"AL9 7RU",
    "sg:province":"Hertfordshire",
    "sg:tags":[
        "property"
    ],
    "wof:name":"Moffats Park Ltd.",
    "wof:placetype":"venue"
},
  "geometry": {"coordinates":[-0.194713,51.72187],"type":"Point"}
}