{
  "type": "Feature",
  "properties": {
    "iso:country":"GB",
    "sg:address":"30 Chapel Street, Tingley",
    "sg:city":"Wakefield",
    "sg:classifiers":[
        {
            "category":"Retail",
            "subcategory":"Auto Repair",
            "type":"Services"
        }
    ],
    "sg:phone":"+44 113 252 5129",
    "sg:postcode":"WF3 1RD",
    "sg:province":"West Yorkshire",
    "sg:tags":[
        "electrician"
    ],
    "wof:name":"G Barugh Mobile Auto Electrics",
    "wof:placetype":"venue"
},
  "geometry": {"coordinates":[-1.5682610273,53.7315254211],"type":"Point"}
}