{
  "type": "Feature",
  "properties": {
    "addr:full":"292 Bolton Road North Bury Lancashire BL0 0NG",
    "addr:housenumber":"292",
    "addr:postcode":"bl0 0ng",
    "addr:street":"Bolton Road North",
    "iso:country":"GB",
    "sg:address":"292 Bolton Road North",
    "sg:city":"Bury",
    "sg:classifiers":[
        {
            "category":"Food & Beverages",
            "subcategory":"Supermarket",
            "type":"Retail Goods"
        }
    ],
    "sg:postcode":"BL0 0NG",
    "sg:province":"Lancashire",
    "wof:name":"P Emmott",
    "wof:placetype":"venue"
},
  "geometry": {"coordinates":[-2.316278,53.657772],"type":"Point"}
}