{
  "type": "Feature",
  "properties": {
    "iso:country":"GB",
    "sg:address":"10 Lake Road",
    "sg:city":"Ambleside",
    "sg:classifiers":[
        {
            "category":"Cafe",
            "type":"Food & Drink"
        }
    ],
    "sg:phone":"+44 15394 31338",
    "sg:postcode":"LA22 0AD",
    "sg:province":"Cumbria",
    "sg:tags":[
        "tea",
        "snack",
        "bar",
        "room"
    ],
    "wof:name":"Pippins Cafe",
    "wof:placetype":"venue"
},
  "geometry": {"coordinates":[-2.962596,54.429119],"type":"Point"}
}