{
  "type": "Feature",
  "properties": {
    "addr:full":"16 Gallows Hill Lane Abbots Langley Hertfordshire WD5 0DA",
    "addr:housenumber":"16",
    "addr:postcode":"wd5 0da",
    "addr:street":"Gallows Hill Lane",
    "iso:country":"GB",
    "sg:address":"16 Gallows Hill Lane",
    "sg:city":"Abbots Langley",
    "sg:classifiers":[
        {
            "category":"Autos & Motor Vehicles",
            "subcategory":"Motorcycle Sales",
            "type":"Retail Goods"
        }
    ],
    "sg:postcode":"WD5 0DA",
    "sg:province":"Hertfordshire",
    "sg:tags":[
        "chauffeur",
        "driven",
        "car"
    ],
    "wof:name":"Dorfgar Chauffeur Drive",
    "wof:placetype":"venue"
},
  "geometry": {"coordinates":[-0.4331809878,51.7012557983],"type":"Point"}
}