{
  "type": "Feature",
  "properties": {
    "addr:full":"Keele Road Newcastle Staffordshire ST5 5AB",
    "addr:postcode":"st5 5ab",
    "addr:street":"Keele Road",
    "iso:country":"GB",
    "sg:address":"Keele Road",
    "sg:city":"Newcastle",
    "sg:classifiers":[
        {
            "category":"Sports & Exercise",
            "subcategory":"Golf",
            "type":"Entertainment"
        }
    ],
    "sg:phone":"+44 1782 717417",
    "sg:postcode":"ST5 5AB",
    "sg:province":"Staffordshire",
    "sg:tags":[
        "range",
        "driving"
    ],
    "wof:name":"Keele Driving Range & Golf Shop",
    "wof:placetype":"venue"
},
  "geometry": {"coordinates":[-2.2501349449,53.0072021484],"type":"Point"}
}