{
  "type": "Feature",
  "properties": {
    "addr:full":"134 Percival Rd Enfield Greater London EN1 1QU",
    "addr:housenumber":"134",
    "addr:postcode":"en1 1qu",
    "addr:street":"Percival Rd",
    "iso:country":"GB",
    "sg:address":"134 Percival Rd",
    "sg:city":"Enfield",
    "sg:classifiers":[
        {
            "category":"Professional",
            "subcategory":"Printing & Photocopies",
            "type":"Services"
        }
    ],
    "sg:postcode":"EN1 1QU",
    "sg:province":"Greater London",
    "sg:tags":[
        "plate",
        "lithographic",
        "maker"
    ],
    "wof:name":"Classic Repro Limited",
    "wof:placetype":"venue"
},
  "geometry": {"coordinates":[-0.064998,51.64727],"type":"Point"}
}