{
  "type": "Feature",
  "properties": {
    "iso:country":"GB",
    "sg:address":"446 Bath Rd",
    "sg:city":"Slough",
    "sg:classifiers":[
        {
            "category":"Wholesale",
            "subcategory":"Construction Materials",
            "type":"Manufacturing & Wholesale Goods"
        }
    ],
    "sg:phone":"+44 1628 663737",
    "sg:postcode":"SL1 6BB",
    "sg:province":"Berkshire",
    "sg:tags":[
        "merchant",
        "glass"
    ],
    "wof:name":"Glass & Glazing Company",
    "wof:placetype":"venue"
},
  "geometry": {"coordinates":[-0.646953,51.520344],"type":"Point"}
}