{
  "type": "Feature",
  "properties": {
    "addr:full":"Naughton Road, Wormit Newport-on-tay Fife DD6 8NE",
    "addr:postcode":"dd6 8ne",
    "addr:street":"Naughton Road;Newport-On-Tay",
    "iso:country":"GB",
    "sg:address":"Naughton Road, Wormit",
    "sg:city":"Newport-on-tay",
    "sg:classifiers":[
        {
            "category":"Bars & Pubs",
            "type":"Food & Drink"
        }
    ],
    "sg:phone":"+44 1382 542579",
    "sg:postcode":"DD6 8NE",
    "sg:province":"Fife",
    "sg:tags":[
        "pubs",
        "inn"
    ],
    "wof:name":"A & M Robertson",
    "wof:placetype":"venue"
},
  "geometry": {"coordinates":[-2.941731,56.439812],"type":"Point"}
}