{
  "type": "Feature",
  "properties": {
    "iso:country":"GB",
    "sg:address":"192 Wigan Road, Aspull",
    "sg:city":"Wigan",
    "sg:classifiers":[
        {
            "category":"Bars & Pubs",
            "type":"Food & Drink"
        }
    ],
    "sg:postcode":"WN2 1DU",
    "sg:province":"Lancashire",
    "sg:tags":[
        "pubs",
        "inn"
    ],
    "wof:name":"Colliers Arms",
    "wof:placetype":"venue"
},
  "geometry": {"coordinates":[-2.598685,53.561333],"type":"Point"}
}