{
  "type": "Feature",
  "properties": {
    "addr:full":"147 Main Street, Wilsden Bradford West Yorkshire BD15 0AQ",
    "addr:housenumber":"147",
    "addr:postcode":"bd15 0aq",
    "addr:street":"Main Street",
    "iso:country":"GB",
    "sg:address":"147 Main Street, Wilsden",
    "sg:city":"Bradford",
    "sg:classifiers":[
        {
            "category":"Food & Beverages",
            "subcategory":"Bakery",
            "type":"Retail Goods"
        }
    ],
    "sg:phone":"+44 1535 272368",
    "sg:postcode":"BD15 0AQ",
    "sg:province":"West Yorkshire",
    "sg:tags":[
        "shop",
        "baker"
    ],
    "wof:name":"Wilsden Bakery",
    "wof:placetype":"venue"
},
  "geometry": {"coordinates":[-1.859364,53.82214],"type":"Point"}
}