{
  "type": "Feature",
  "properties": {
    "iso:country":"GB",
    "sg:address":"The Gate House, Alban Park, Hatfield Road",
    "sg:city":"St Albans",
    "sg:classifiers":[
        {
            "category":"Professional",
            "subcategory":"Employment Agencies",
            "type":"Services"
        },
        {
            "category":"Real Estate",
            "subcategory":"Real Estate Agent",
            "type":"Services"
        }
    ],
    "sg:phone":"+44 20 7930 5100",
    "sg:postcode":"AL4 0JJ",
    "sg:province":"Hertfordshire",
    "sg:tags":[
        "consultant"
    ],
    "wof:name":"High Profile Properties Ltd.",
    "wof:placetype":"venue"
},
  "geometry": {"coordinates":[-0.249449,51.737598],"type":"Point"}
}