{
  "type": "Feature",
  "properties": {
    "addr:full":"31-33 Midland Road Scunthorpe Lincolnshire DN16 1DQ",
    "addr:housenumber":"31-33",
    "addr:postcode":"dn16 1dq",
    "addr:street":"Midland Road",
    "iso:country":"GB",
    "sg:address":"31-33 Midland Road",
    "sg:city":"Scunthorpe",
    "sg:classifiers":[
        {
            "category":"Real Estate",
            "subcategory":"Developer",
            "type":"Services"
        }
    ],
    "sg:phone":"+44 1724 271130",
    "sg:postcode":"DN16 1DQ",
    "sg:province":"Lincolnshire",
    "sg:tags":[
        "property"
    ],
    "wof:name":"Maltgrade Ltd.",
    "wof:placetype":"venue"
},
  "geometry": {"coordinates":[-0.6313989758,53.5821113586],"type":"Point"}
}