{
  "type": "Feature",
  "properties": {
    "addr:full":"Bristow Farm, Gregory Lane, Halsall Ormskirk Lancashire L39 8SP",
    "addr:postcode":"l39 8sp",
    "addr:street":"Gregory Lane",
    "iso:country":"GB",
    "sg:address":"Bristow Farm, Gregory Lane, Halsall",
    "sg:city":"Ormskirk",
    "sg:classifiers":[
        {
            "category":"Food & Beverages",
            "subcategory":"Groceries & Convenience Stores",
            "type":"Retail Goods"
        }
    ],
    "sg:postcode":"L39 8SP",
    "sg:province":"Lancashire",
    "sg:tags":[
        "merchant",
        "potato"
    ],
    "wof:name":"A & K J Georgeson",
    "wof:placetype":"venue"
},
  "geometry": {"coordinates":[-2.9546189308,53.5842704773],"type":"Point"}
}