{
  "type": "Feature",
  "properties": {
    "iso:country":"GB",
    "sg:address":"1 Bridge Industrial Estate, Thornhill Road",
    "sg:city":"Solihull",
    "sg:classifiers":[
        {
            "category":"Home & Garden",
            "subcategory":"Home Furnishings",
            "type":"Retail Goods"
        }
    ],
    "sg:phone":"+44 121 711 4115",
    "sg:postcode":"B91 2HB",
    "sg:province":"West Midlands",
    "sg:tags":[
        "furnishers",
        "planner",
        "kitchen"
    ],
    "wof:name":"Cupboard Love (U K) Ltd.",
    "wof:placetype":"venue"
},
  "geometry": {"coordinates":[-1.777849,52.415066],"type":"Point"}
}