{
  "type": "Feature",
  "properties": {
    "iso:country":"GB",
    "sg:address":"Polton Road",
    "sg:city":"Lasswade",
    "sg:classifiers":[
        {
            "category":"Bars & Pubs",
            "type":"Food & Drink"
        },
        {
            "category":"Community Center",
            "subcategory":"Social",
            "type":"Public Place"
        }
    ],
    "sg:phone":"+44 131 663 7014",
    "sg:postcode":"EH18 1BS",
    "sg:province":"City of Edinburgh",
    "sg:tags":[
        "pubs",
        "house",
        "inn",
        "activity"
    ],
    "wof:name":"Polton Inn",
    "wof:placetype":"venue"
},
  "geometry": {"coordinates":[-3.145045042,55.8723678589],"type":"Point"}
}