{
  "type": "Feature",
  "properties": {
    "iso:country":"GB",
    "sg:address":"38 Church Down Close",
    "sg:city":"Redditch",
    "sg:classifiers":[
        {
            "category":"Banks & Credit Unions",
            "subcategory":"Financial Services",
            "type":"Services"
        }
    ],
    "sg:postcode":"B97 5ND",
    "sg:province":"Warwickshire",
    "sg:tags":[
        "adviser"
    ],
    "wof:name":"Neil Spalding",
    "wof:placetype":"venue"
},
  "geometry": {"coordinates":[-1.945165,52.281216],"type":"Point"}
}