{
  "type": "Feature",
  "properties": {
    "iso:country":"GB",
    "sg:address":"6 Bath Rd",
    "sg:city":"Melksham",
    "sg:classifiers":[
        {
            "category":"Food & Beverages",
            "subcategory":"Bakery",
            "type":"Retail Goods"
        }
    ],
    "sg:phone":"+44 1225 707542",
    "sg:postcode":"SN12 6LP",
    "sg:province":"Wiltshire",
    "sg:tags":[
        "baker"
    ],
    "wof:name":"Little Brook Bakery The",
    "wof:placetype":"venue"
},
  "geometry": {"coordinates":[-2.1383109093,51.3749694824],"type":"Point"}
}