{
  "type": "Feature",
  "properties": {
    "iso:country":"GB",
    "sg:address":"367 Boldmere Road",
    "sg:city":"Sutton Coldfield",
    "sg:classifiers":[
        {
            "category":"Fast Food",
            "type":"Food & Drink"
        }
    ],
    "sg:phone":"+44 121 382 4977",
    "sg:postcode":"B73 5EX",
    "sg:province":"West Midlands",
    "sg:tags":[
        "away",
        "meal",
        "outlet",
        "take"
    ],
    "wof:name":"Good Harvest Cantonese Cuisine",
    "wof:placetype":"venue"
},
  "geometry": {"coordinates":[-1.835999,52.537727],"type":"Point"}
}