{
  "type": "Feature",
  "properties": {
    "addr:full":"South Rd, Chapel-st-leonards Skegness Lincolnshire PE24 5TH",
    "addr:postcode":"pe24 5th",
    "addr:street":"South Rd",
    "iso:country":"GB",
    "sg:address":"South Rd, Chapel-st-leonards",
    "sg:city":"Skegness",
    "sg:classifiers":[
        {
            "category":"Cafe",
            "type":"Food & Drink"
        }
    ],
    "sg:postcode":"PE24 5TH",
    "sg:province":"Lincolnshire",
    "sg:tags":[
        "tea",
        "room"
    ],
    "wof:name":"Whitehead,Neil,",
    "wof:placetype":"venue"
},
  "geometry": {"coordinates":[0.336813,53.223297],"type":"Point"}
}