{
  "type": "Feature",
  "properties": {
    "addr:full":"123 Newland Street Witham Essex CM8 1BE",
    "addr:housenumber":"123",
    "addr:postcode":"cm8 1be",
    "addr:street":"Newland Street",
    "iso:country":"GB",
    "sg:address":"123 Newland Street",
    "sg:city":"Witham",
    "sg:classifiers":[
        {
            "category":"Professional",
            "subcategory":"Art Services",
            "type":"Services"
        }
    ],
    "sg:phone":"+44 1376 513777",
    "sg:postcode":"CM8 1BE",
    "sg:province":"Essex",
    "sg:tags":[
        "graphic",
        "designer"
    ],
    "wof:name":"Premier Design",
    "wof:placetype":"venue"
},
  "geometry": {"coordinates":[0.6375420094,51.7976531982],"type":"Point"}
}