{
  "type": "Feature",
  "properties": {
    "addr:full":"Hazel Farm, Strode Common Bristol Gloucestershire BS35 3PS",
    "addr:postcode":"bs35 3ps",
    "addr:street":"Strode Common",
    "iso:country":"GB",
    "sg:address":"Hazel Farm, Strode Common",
    "sg:city":"Bristol",
    "sg:classifiers":[
        {
            "category":"Home & Garden",
            "subcategory":"Garden Supply",
            "type":"Retail Goods"
        },
        {
            "category":"Farming",
            "subcategory":"Farm",
            "type":"Manufacturing & Wholesale Goods"
        }
    ],
    "sg:phone":"+44 1454 413247",
    "sg:postcode":"BS35 3PS",
    "sg:province":"Gloucestershire",
    "sg:tags":[
        "mixed",
        "bulb",
        "crop",
        "grower"
    ],
    "wof:name":"Michael G Spratt & Son",
    "wof:placetype":"venue"
},
  "geometry": {"coordinates":[-2.535575,51.586853],"type":"Point"}
}