{
  "type": "Feature",
  "properties": {
    "addr:full":"Hill House, Rodbourne Malmesbury Wiltshire SN16 0ES",
    "addr:postcode":"sn16 0es",
    "iso:country":"GB",
    "sg:address":"Hill House, Rodbourne",
    "sg:city":"Malmesbury",
    "sg:classifiers":[
        {
            "category":"Professional",
            "subcategory":"Management & Consulting",
            "type":"Services"
        },
        {
            "category":"Education",
            "subcategory":"Special Training",
            "type":"Public Place"
        }
    ],
    "sg:phone":"+44 1666 823456",
    "sg:postcode":"SN16 0ES",
    "sg:province":"Wiltshire",
    "sg:tags":[
        "consultant",
        "product",
        "centre"
    ],
    "wof:name":"Jeff Monk Training",
    "wof:placetype":"venue"
},
  "geometry": {"coordinates":[-2.098792,51.548321],"type":"Point"}
}