{
  "type": "Feature",
  "properties": {
    "iso:country":"GB",
    "sg:address":"318 Abbeyhills Road",
    "sg:city":"Oldham",
    "sg:classifiers":[
        {
            "category":"Government",
            "subcategory":"Post Office",
            "type":"Public Place"
        }
    ],
    "sg:phone":"+44 161 624 4926",
    "sg:postcode":"OL8 2DH",
    "sg:province":"Lancashire",
    "wof:name":"Abbeyhills Post Office",
    "wof:placetype":"venue"
},
  "geometry": {"coordinates":[-2.096889,53.534157],"type":"Point"}
}