{
  "type": "Feature",
  "properties": {
    "addr:full":"Place Farm, Firle Lewes East Sussex BN8 6LP",
    "addr:postcode":"bn8 6lp",
    "addr:street":"Place",
    "iso:country":"GB",
    "sg:address":"Place Farm, Firle",
    "sg:city":"Lewes",
    "sg:classifiers":[
        {
            "category":"Home & Garden",
            "subcategory":"Garden Supply",
            "type":"Retail Goods"
        },
        {
            "category":"Farming",
            "subcategory":"Farm",
            "type":"Manufacturing & Wholesale Goods"
        }
    ],
    "sg:phone":"+44 1273 858275",
    "sg:postcode":"BN8 6LP",
    "sg:province":"East Sussex",
    "sg:tags":[
        "mixed",
        "bulb",
        "crop",
        "grower"
    ],
    "wof:name":"D J J Rowsell",
    "wof:placetype":"venue"
},
  "geometry": {"coordinates":[0.0869690031,50.8452568054],"type":"Point"}
}