{
  "type": "Feature",
  "properties": {
    "addr:full":"134 Rose Street Edinburgh City of Edinburgh EH2 3JD",
    "addr:housenumber":"134",
    "addr:postcode":"eh2 3jd",
    "addr:street":"Rose Street",
    "iso:country":"GB",
    "sg:address":"134 Rose Street",
    "sg:city":"Edinburgh",
    "sg:classifiers":[
        {
            "category":"Shopping",
            "subcategory":"Clothing, Apparel, & Fashions",
            "type":"Retail Goods"
        },
        {
            "category":"Manufacturing",
            "subcategory":"Apparel",
            "type":"Manufacturing & Wholesale Goods"
        }
    ],
    "sg:phone":"+44 131 220 4628",
    "sg:postcode":"EH2 3JD",
    "sg:province":"City of Edinburgh",
    "sg:tags":[
        "supplier",
        "shirt",
        "maker",
        "uniform"
    ],
    "sg:website":"http://www.getshirty.com",
    "wof:name":"Get Shirty Ltd",
    "wof:placetype":"venue"
},
  "geometry": {"coordinates":[-3.2015500069,55.951877594],"type":"Point"}
}