{
  "type": "Feature",
  "properties": {
    "iso:country":"GB",
    "sg:address":"The Wandsworth Centre, 1c Yukon Rd",
    "sg:city":"Balham",
    "sg:classifiers":[
        {
            "category":"Organizations",
            "subcategory":"Non-profit Organization",
            "type":"Services"
        }
    ],
    "sg:phone":"+44 20 8675 4246",
    "sg:postcode":"SW12 9PZ",
    "sg:province":"Greater London",
    "sg:tags":[
        "organisation",
        "voluntary",
        "charity"
    ],
    "wof:name":"Action for Blind People",
    "wof:placetype":"venue"
},
  "geometry": {"coordinates":[-0.148549,51.447979],"type":"Point"}
}