{
  "type": "Feature",
  "properties": {
    "iso:country":"GB",
    "sg:address":"Barry's Lane",
    "sg:city":"Scarborough",
    "sg:classifiers":[
        {
            "category":"Education",
            "subcategory":"Special Training",
            "type":"Public Place"
        },
        {
            "category":"Government",
            "subcategory":"Office",
            "type":"Public Place"
        }
    ],
    "sg:phone":"+44 1723 367829",
    "sg:postcode":"YO12 4HA",
    "sg:province":"North Yorkshire",
    "sg:tags":[
        "school",
        "local"
    ],
    "wof:name":"Springhead School",
    "wof:placetype":"venue"
},
  "geometry": {"coordinates":[-0.417,54.267151],"type":"Point"}
}