{
  "type": "Feature",
  "properties": {
    "iso:country":"GB",
    "sg:address":"6 Ledsgrove, Ipplepen",
    "sg:city":"Newton Abbot",
    "sg:classifiers":[
        {
            "category":"Professional",
            "subcategory":"Accounting & Tax Preparation",
            "type":"Services"
        }
    ],
    "sg:phone":"+44 1803 812582",
    "sg:postcode":"TQ12 5QY",
    "sg:province":"Devon",
    "sg:tags":[
        "accountant"
    ],
    "wof:name":"William N Tolfree",
    "wof:placetype":"venue"
},
  "geometry": {"coordinates":[-3.6028840542,50.496761322],"type":"Point"}
}