{
  "type": "Feature",
  "properties": {
    "iso:country":"GB",
    "sg:address":"Brooklyn Farm, North Hill",
    "sg:city":"Stanford Le Hope",
    "sg:classifiers":[
        {
            "category":"Building & Trades",
            "subcategory":"Cleaning & Sanitation",
            "type":"Services"
        }
    ],
    "sg:phone":"+44 1375 361408",
    "sg:postcode":"SS17 8QA",
    "sg:province":"Essex",
    "sg:tags":[
        "blast"
    ],
    "wof:name":"Halls Specialised Services",
    "wof:placetype":"venue"
},
  "geometry": {"coordinates":[0.41475,51.513645],"type":"Point"}
}