{
  "type": "Feature",
  "properties": {
    "addr:full":"Marpool Yard, Green Close Exmouth Devon EX8 3QD",
    "addr:postcode":"ex8 3qd",
    "addr:street":"Green Close",
    "iso:country":"GB",
    "sg:address":"Marpool Yard, Green Close",
    "sg:city":"Exmouth",
    "sg:classifiers":[
        {
            "category":"Retail",
            "subcategory":"Auto Repair",
            "type":"Services"
        }
    ],
    "sg:phone":"+44 1395 279811",
    "sg:postcode":"EX8 3QD",
    "sg:province":"Devon",
    "sg:tags":[
        "modification",
        "garage"
    ],
    "wof:name":"The Old Barn Garage",
    "wof:placetype":"venue"
},
  "geometry": {"coordinates":[-3.3982410431,50.6267051697],"type":"Point"}
}