{
  "type": "Feature",
  "properties": {
    "iso:country":"GB",
    "sg:address":"Pickup Street, Clayton Le Moors",
    "sg:city":"Accrington",
    "sg:classifiers":[
        {
            "category":"Social Services",
            "subcategory":"Child Care",
            "type":"Services"
        },
        {
            "category":"Social Services",
            "subcategory":"Adult Care",
            "type":"Services"
        }
    ],
    "sg:phone":"+44 1254 384395",
    "sg:postcode":"BB5 5NS",
    "sg:province":"Lancashire",
    "sg:tags":[
        "day",
        "centre"
    ],
    "wof:name":"Arthur Wilson Centre",
    "wof:placetype":"venue"
},
  "geometry": {"coordinates":[-2.385204,53.774944],"type":"Point"}
}