{
  "type": "Feature",
  "properties": {
    "addr:full":"382 Ivydale Rd London Greater London SE15 3DG",
    "addr:housenumber":"382",
    "addr:postcode":"se15 3dg",
    "addr:street":"Ivydale Rd",
    "iso:country":"GB",
    "sg:address":"382 Ivydale Rd",
    "sg:city":"London",
    "sg:classifiers":[
        {
            "category":"Food & Beverages",
            "subcategory":"Supermarket",
            "type":"Retail Goods"
        }
    ],
    "sg:postcode":"SE15 3DG",
    "sg:province":"Greater London",
    "wof:name":"Gok,Kazim,",
    "wof:placetype":"venue"
},
  "geometry": {"coordinates":[-0.0503249988,51.4562988281],"type":"Point"}
}