{
  "type": "Feature",
  "properties": {
    "addr:full":"Rutherglen, Wycombe Rd, Saunderton Princes Risborough Buckinghamshire HP27 9NP",
    "addr:postcode":"hp27 9np",
    "addr:street":"Wycombe Rd",
    "iso:country":"GB",
    "sg:address":"Rutherglen, Wycombe Rd, Saunderton",
    "sg:city":"Princes Risborough",
    "sg:classifiers":[
        {
            "category":"Retail",
            "subcategory":"Auto Repair",
            "type":"Services"
        }
    ],
    "sg:phone":"+44 1844 273373",
    "sg:postcode":"HP27 9NP",
    "sg:province":"Buckinghamshire",
    "sg:tags":[
        "car",
        "specialist",
        "customizing"
    ],
    "wof:name":"Tyre Team",
    "wof:placetype":"venue"
},
  "geometry": {"coordinates":[-0.8505380154,51.711265564],"type":"Point"}
}