{
  "type": "Feature",
  "properties": {
    "addr:full":"45 Churchfield Rd Acton Greater London W3 6AY",
    "addr:housenumber":"45",
    "addr:postcode":"w3 6ay",
    "addr:street":"Churchfield Rd",
    "iso:country":"GB",
    "sg:address":"45 Churchfield Rd",
    "sg:city":"Acton",
    "sg:classifiers":[
        {
            "category":"Food & Beverages",
            "subcategory":"Bakery",
            "type":"Retail Goods"
        }
    ],
    "sg:phone":"+44 20 8993 4830",
    "sg:postcode":"W3 6AY",
    "sg:province":"Greater London",
    "wof:name":"Arabic Sweet Centre",
    "wof:placetype":"venue"
},
  "geometry": {"coordinates":[-0.265685,51.508583],"type":"Point"}
}