{
  "type": "Feature",
  "properties": {
    "addr:full":"90 Islington High Street London Greater London N1 8EQ",
    "addr:housenumber":"90",
    "addr:postcode":"n1 8eq",
    "addr:street":"Islington High Street",
    "iso:country":"GB",
    "sg:address":"90 Islington High Street",
    "sg:city":"London",
    "sg:classifiers":[
        {
            "category":"Professional",
            "subcategory":"Lawyer & Legal Services",
            "type":"Services"
        }
    ],
    "sg:phone":"+44 20 7704 7500",
    "sg:postcode":"N1 8EQ",
    "sg:province":"Greater London",
    "sg:tags":[
        "solicitor"
    ],
    "wof:name":"Trott & Gentry",
    "wof:placetype":"venue"
},
  "geometry": {"coordinates":[-0.1046639979,51.5340080261],"type":"Point"}
}