{
  "type": "Feature",
  "properties": {
    "addr:full":"39-41 High Street Stourbridge Staffordshire DY8 1DA",
    "addr:housenumber":"39-41",
    "addr:postcode":"dy8 1da",
    "addr:street":"High Street",
    "iso:country":"GB",
    "sg:address":"39-41 High Street",
    "sg:city":"Stourbridge",
    "sg:classifiers":[
        {
            "category":"Shopping",
            "subcategory":"Clothing, Apparel, & Fashions",
            "type":"Retail Goods"
        }
    ],
    "sg:phone":"+44 1384 394115",
    "sg:postcode":"DY8 1DA",
    "sg:province":"Staffordshire",
    "sg:tags":[
        "shop",
        "lady",
        "fashionwear"
    ],
    "wof:name":"Christian Marcus Direct",
    "wof:placetype":"venue"
},
  "geometry": {"coordinates":[-2.14678,52.457424],"type":"Point"}
}