{
  "type": "Feature",
  "properties": {
    "iso:country":"GB",
    "sg:address":"126 Queen Street",
    "sg:city":"Hitchin",
    "sg:classifiers":[
        {
            "category":"Retail",
            "subcategory":"Laundry & Dry Cleaning",
            "type":"Services"
        }
    ],
    "sg:phone":"+44 1462 451697",
    "sg:postcode":"SG4 9TH",
    "sg:province":"Hertfordshire",
    "sg:tags":[
        "alteration"
    ],
    "wof:name":"Daromley Ltd.",
    "wof:placetype":"venue"
},
  "geometry": {"coordinates":[-0.2746689916,51.9488601685],"type":"Point"}
}