{
  "type": "Feature",
  "properties": {
    "addr:full":"24 Town End Close Pickering North Yorkshire YO18 8JB",
    "addr:housenumber":"24",
    "addr:postcode":"yo18 8jb",
    "addr:street":"Town End Close",
    "iso:country":"GB",
    "sg:address":"24 Town End Close",
    "sg:city":"Pickering",
    "sg:classifiers":[
        {
            "category":"Manufacturing",
            "subcategory":"Lumber",
            "type":"Manufacturing & Wholesale Goods"
        }
    ],
    "sg:phone":"+44 1751 475144",
    "sg:postcode":"YO18 8JB",
    "sg:province":"North Yorkshire",
    "sg:tags":[
        "importer",
        "merchants",
        "agent",
        "timber"
    ],
    "wof:name":"Hallam Haulage",
    "wof:placetype":"venue"
},
  "geometry": {"coordinates":[-0.7636479735,54.2416725159],"type":"Point"}
}