{
  "type": "Feature",
  "properties": {
    "addr:full":"17 Old Cross Hertford Hertfordshire SG14 1RE",
    "addr:housenumber":"17",
    "addr:postcode":"sg14 1re",
    "addr:street":"Old Cross",
    "iso:country":"GB",
    "sg:address":"17 Old Cross",
    "sg:city":"Hertford",
    "sg:classifiers":[
        {
            "category":"Professional",
            "type":"Services"
        }
    ],
    "sg:phone":"+44 1992 550505",
    "sg:postcode":"SG14 1RE",
    "sg:province":"Hertfordshire",
    "sg:tags":[
        "interior",
        "furnishers",
        "designer"
    ],
    "wof:name":"Hertford Interiors",
    "wof:placetype":"venue"
},
  "geometry": {"coordinates":[-0.080843,51.797352],"type":"Point"}
}