{
  "type": "Feature",
  "properties": {
    "addr:full":"21 Overton Drive, Chadwell Heath Romford Essex RM6 4EN",
    "addr:housenumber":"21",
    "addr:postcode":"rm6 4en",
    "addr:street":"Overton Drive",
    "iso:country":"GB",
    "sg:address":"21 Overton Drive, Chadwell Heath",
    "sg:city":"Romford",
    "sg:classifiers":[
        {
            "category":"Professional",
            "subcategory":"Art Services",
            "type":"Services"
        }
    ],
    "sg:phone":"+44 20 8597 1377",
    "sg:postcode":"RM6 4EN",
    "sg:province":"Essex",
    "sg:tags":[
        "photographer"
    ],
    "wof:name":"Ro3 Photographique",
    "wof:placetype":"venue"
},
  "geometry": {"coordinates":[0.124389,51.56778],"type":"Point"}
}