{
  "type": "Feature",
  "properties": {
    "addr:full":"45 The Concourse Skelmersdale Lancashire WN8 6LJ",
    "addr:housenumber":"45",
    "addr:postcode":"wn8 6lj",
    "addr:street":"The Concourse",
    "iso:country":"GB",
    "sg:address":"45 The Concourse",
    "sg:city":"Skelmersdale",
    "sg:classifiers":[
        {
            "category":"Food & Beverages",
            "subcategory":"Bakery",
            "type":"Retail Goods"
        }
    ],
    "sg:phone":"+44 1695 556010",
    "sg:postcode":"WN8 6LJ",
    "sg:province":"Lancashire",
    "sg:tags":[
        "baker"
    ],
    "wof:name":"Tricia & Vera's Cake Shop",
    "wof:placetype":"venue"
},
  "geometry": {"coordinates":[-2.7701659203,53.5566558838],"type":"Point"}
}