{
  "type": "Feature",
  "properties": {
    "addr:full":"80 Widnes Road Widnes Cheshire WA8 6AT",
    "addr:housenumber":"80",
    "addr:postcode":"wa8 6at",
    "addr:street":"Widnes Road",
    "iso:country":"GB",
    "sg:address":"80 Widnes Road",
    "sg:city":"Widnes",
    "sg:classifiers":[
        {
            "category":"Fast Food",
            "type":"Food & Drink"
        }
    ],
    "sg:phone":"+44 151 423 2757",
    "sg:postcode":"WA8 6AT",
    "sg:province":"Cheshire",
    "sg:tags":[
        "away",
        "take"
    ],
    "wof:name":"Deedar Balti House",
    "wof:placetype":"venue"
},
  "geometry": {"coordinates":[-2.7276620865,53.3669281006],"type":"Point"}
}