{
  "type": "Feature",
  "properties": {
    "iso:country":"GB",
    "sg:address":"28a Church Street",
    "sg:city":"Crawley",
    "sg:classifiers":[
        {
            "category":"Personal",
            "subcategory":"Beauty Salon",
            "type":"Services"
        }
    ],
    "sg:phone":"+44 1293 528419",
    "sg:postcode":"RH11 7BG",
    "sg:province":"West Sussex",
    "sg:tags":[
        "unisex",
        "hairdresser"
    ],
    "wof:name":"Ciao",
    "wof:placetype":"venue"
},
  "geometry": {"coordinates":[-0.196619004,51.1152420044],"type":"Point"}
}