{
  "type": "Feature",
  "properties": {
    "addr:full":"Westfield Lane, Idle Bradford West Yorkshire BD10 8PY",
    "addr:postcode":"bd10 8py",
    "addr:street":"Westfield Lane",
    "iso:country":"GB",
    "sg:address":"Westfield Lane, Idle",
    "sg:city":"Bradford",
    "sg:classifiers":[
        {
            "category":"Organizations",
            "subcategory":"Community Association",
            "type":"Services"
        },
        {
            "category":"Organizations",
            "subcategory":"Membership Organization",
            "type":"Services"
        }
    ],
    "sg:phone":"+44 1274 411080",
    "sg:postcode":"BD10 8PY",
    "sg:province":"West Yorkshire",
    "sg:tags":[
        "club",
        "social"
    ],
    "wof:name":"Idle & Thackley Operatic & Dramatic Society",
    "wof:placetype":"venue"
},
  "geometry": {"coordinates":[-1.733769,53.83736],"type":"Point"}
}