{
  "type": "Feature",
  "properties": {
    "addr:full":"The Oasis, Meadowhall Centre Sheffield South Yorkshire S9 1EP",
    "addr:postcode":"s9 1ep",
    "iso:country":"GB",
    "sg:address":"The Oasis, Meadowhall Centre",
    "sg:city":"Sheffield",
    "sg:classifiers":[
        {
            "category":"Fast Food",
            "type":"Food & Drink"
        }
    ],
    "sg:phone":"+44 114 256 8068",
    "sg:postcode":"S9 1EP",
    "sg:province":"South Yorkshire",
    "sg:tags":[
        "away",
        "meal",
        "outlet",
        "take"
    ],
    "wof:name":"The 3 Amigo'S",
    "wof:placetype":"venue"
},
  "geometry": {"coordinates":[-1.406079,53.41412],"type":"Point"}
}