{
  "type": "Feature",
  "properties": {
    "addr:full":"1 Mckinnell Crescent Rugby Warwickshire CV21 4AZ",
    "addr:housenumber":"1",
    "addr:postcode":"cv21 4az",
    "addr:street":"Mckinnell Crescent",
    "iso:country":"GB",
    "sg:address":"1 Mckinnell Crescent",
    "sg:city":"Rugby",
    "sg:classifiers":[
        {
            "category":"Building & Trades",
            "subcategory":"Construction",
            "type":"Services"
        }
    ],
    "sg:postcode":"CV21 4AZ",
    "sg:province":"Warwickshire",
    "sg:tags":[
        "glazier",
        "decorator",
        "painter"
    ],
    "wof:name":"Sharp Decorating",
    "wof:placetype":"venue"
},
  "geometry": {"coordinates":[-1.233307004,52.3700561523],"type":"Point"}
}