{
  "type": "Feature",
  "properties": {
    "addr:full":"Research Avenue South, Heriott, Watt University Currie City of Edinburgh EH14 4AP",
    "addr:postcode":"eh14 4ap",
    "addr:street":"Research Avenue South Heriott Watt",
    "iso:country":"GB",
    "sg:address":"Research Avenue South, Heriott, Watt University",
    "sg:city":"Currie",
    "sg:classifiers":[
        {
            "category":"Military Area",
            "subcategory":"Air Force Base",
            "type":"Public Place"
        }
    ],
    "sg:phone":"+44 131 449 5086",
    "sg:postcode":"EH14 4AP",
    "sg:province":"City of Edinburgh",
    "sg:tags":[
        "water",
        "treatment"
    ],
    "wof:name":"Mykrolis (U K) Ltd.",
    "wof:placetype":"venue"
},
  "geometry": {"coordinates":[-3.315524,55.916676],"type":"Point"}
}