{
  "type": "Feature",
  "properties": {
    "addr:full":"Hall Farm, Neenton Bridgnorth Shropshire WV16 6RL",
    "addr:housenumber":"bridgnorth",
    "addr:postcode":"wv16 6rl",
    "addr:street":"Hall",
    "iso:country":"GB",
    "sg:address":"Hall Farm, Neenton",
    "sg:city":"Bridgnorth",
    "sg:classifiers":[
        {
            "category":"Farming",
            "subcategory":"Farm",
            "type":"Manufacturing & Wholesale Goods"
        }
    ],
    "sg:postcode":"WV16 6RL",
    "sg:province":"Shropshire",
    "sg:tags":[
        "mixed",
        "crop"
    ],
    "wof:name":"J & E Moreton",
    "wof:placetype":"venue"
},
  "geometry": {"coordinates":[-2.5359480381,52.486125946],"type":"Point"}
}