{
  "type": "Feature",
  "properties": {
    "addr:full":"London Rd Haywards Heath East Sussex RH17 5RL",
    "addr:postcode":"rh17 5rl",
    "addr:street":"London Rd",
    "iso:country":"GB",
    "sg:address":"London Rd",
    "sg:city":"Haywards Heath",
    "sg:classifiers":[
        {
            "category":"Shopping",
            "subcategory":"Clothing, Apparel, & Fashions",
            "type":"Retail Goods"
        }
    ],
    "sg:phone":"+44 1444 881511",
    "sg:postcode":"RH17 5RL",
    "sg:province":"East Sussex",
    "sg:tags":[
        "shop"
    ],
    "wof:name":"M G Designer Fashions Clearing House",
    "wof:placetype":"venue"
},
  "geometry": {"coordinates":[-0.141044,51.012241],"type":"Point"}
}