{
  "type": "Feature",
  "properties": {
    "iso:country":"GB",
    "sg:address":"Custom House Quay",
    "sg:city":"Falmouth",
    "sg:classifiers":[
        {
            "category":"Bars & Pubs",
            "subcategory":"Wine Bar",
            "type":"Food & Drink"
        }
    ],
    "sg:phone":"+44 1326 212168",
    "sg:postcode":"TR11 3JT",
    "sg:province":"Cornwall",
    "wof:name":"The Water Front Wine Bar",
    "wof:placetype":"venue"
},
  "geometry": {"coordinates":[-5.066734,50.152336],"type":"Point"}
}