{
  "type": "Feature",
  "properties": {
    "addr:full":"Woodcroft, Sand Lane, Nether Alderley Macclesfield Cheshire SK10 4TS",
    "addr:postcode":"sk10 4ts",
    "addr:street":"Sand Lane",
    "iso:country":"GB",
    "sg:address":"Woodcroft, Sand Lane, Nether Alderley",
    "sg:city":"Macclesfield",
    "sg:classifiers":[
        {
            "category":"Professional",
            "subcategory":"Computer Services",
            "type":"Services"
        }
    ],
    "sg:phone":"+44 1625 586330",
    "sg:postcode":"SK10 4TS",
    "sg:province":"Cheshire",
    "sg:tags":[
        "consultant"
    ],
    "wof:name":"I T Business Services Ltd.",
    "wof:placetype":"venue"
},
  "geometry": {"coordinates":[-2.2372140884,53.2833137512],"type":"Point"}
}