{
  "type": "Feature",
  "properties": {
    "iso:country":"GB",
    "sg:address":"27 Queens Road",
    "sg:city":"Broadstairs",
    "sg:classifiers":[
        {
            "category":"Organizations",
            "subcategory":"Non-profit Organization",
            "type":"Services"
        }
    ],
    "sg:phone":"+44 1843 865758",
    "sg:postcode":"CT10 1NU",
    "sg:province":"Kent",
    "sg:tags":[
        "organisation",
        "voluntary",
        "charity"
    ],
    "wof:name":"Barts Renal Patients Association",
    "wof:placetype":"venue"
},
  "geometry": {"coordinates":[1.438593,51.357391],"type":"Point"}
}