{
  "type": "Feature",
  "properties": {
    "addr:full":"Unit 2, Woburn Sands Road, Bow Brickhill Milton Keynes Bedfordshire MK17 9JL",
    "addr:housenumber":"unit 2",
    "addr:postcode":"mk17 9jl",
    "addr:street":"Woburn Sands Road",
    "iso:country":"GB",
    "sg:address":"Unit 2, Woburn Sands Road, Bow Brickhill",
    "sg:city":"Milton Keynes",
    "sg:classifiers":[
        {
            "category":"Shopping",
            "subcategory":"Party Supplies",
            "type":"Retail Goods"
        }
    ],
    "sg:phone":"+44 1908 270350",
    "sg:postcode":"MK17 9JL",
    "sg:province":"Bedfordshire",
    "sg:tags":[
        "marquees",
        "floor",
        "tent"
    ],
    "wof:name":"M & B Marquees",
    "wof:placetype":"venue"
},
  "geometry": {"coordinates":[-0.679324,52.003475],"type":"Point"}
}