{
  "type": "Feature",
  "properties": {
    "addr:full":"Holm Court, Wainwright Way Ipswich Suffolk IP5 2XG",
    "addr:postcode":"ip5 2xg",
    "addr:street":"Holm Court Wainwright Way",
    "iso:country":"GB",
    "sg:address":"Holm Court, Wainwright Way",
    "sg:city":"Ipswich",
    "sg:classifiers":[
        {
            "category":"Health Services",
            "subcategory":"Nursing And Care Facility",
            "type":"Services"
        }
    ],
    "sg:phone":"+44 1473 631606",
    "sg:postcode":"IP5 2XG",
    "sg:province":"Suffolk",
    "sg:tags":[
        "home"
    ],
    "wof:name":"Housing 21",
    "wof:placetype":"venue"
},
  "geometry": {"coordinates":[1.24915,52.065388],"type":"Point"}
}