{
  "type": "Feature",
  "properties": {
    "addr:full":"13 Appletree Gro Ferndown Dorset BH22 9LA",
    "addr:housenumber":"13",
    "addr:postcode":"bh22 9la",
    "addr:street":"Appletree Gro",
    "iso:country":"GB",
    "sg:address":"13 Appletree Gro",
    "sg:city":"Ferndown",
    "sg:classifiers":[
        {
            "category":"Building & Trades",
            "subcategory":"Construction",
            "type":"Services"
        }
    ],
    "sg:postcode":"BH22 9LA",
    "sg:province":"Dorset",
    "sg:tags":[
        "builder"
    ],
    "wof:name":"F S Arnold",
    "wof:placetype":"venue"
},
  "geometry": {"coordinates":[-1.8834569454,50.8050956726],"type":"Point"}
}