{
  "type": "Feature",
  "properties": {
    "addr:full":"125 Ellison Road Gateshead Tyne and Wear NE11 9SS",
    "addr:housenumber":"125",
    "addr:postcode":"ne11 9ss",
    "addr:street":"Ellison Road",
    "iso:country":"GB",
    "sg:address":"125 Ellison Road",
    "sg:city":"Gateshead",
    "sg:classifiers":[
        {
            "category":"Food & Beverages",
            "subcategory":"Groceries & Convenience Stores",
            "type":"Retail Goods"
        }
    ],
    "sg:phone":"+44 191 493 2064",
    "sg:postcode":"NE11 9SS",
    "sg:province":"Tyne and Wear",
    "wof:name":"Dunston Value Stores",
    "wof:placetype":"venue"
},
  "geometry": {"coordinates":[-1.6387640238,54.9512481689],"type":"Point"}
}