{
  "type": "Feature",
  "properties": {
    "addr:full":"63 Archery Road London Greater London SE9 1HF",
    "addr:housenumber":"63",
    "addr:postcode":"se9 1hf",
    "addr:street":"Archery Road",
    "iso:country":"GB",
    "sg:address":"63 Archery Road",
    "sg:city":"London",
    "sg:classifiers":[
        {
            "category":"Professional",
            "type":"Services"
        }
    ],
    "sg:phone":"+44 20 8850 3965",
    "sg:postcode":"SE9 1HF",
    "sg:province":"Greater London",
    "sg:tags":[
        "shopfitters"
    ],
    "wof:name":"Bromley Shopfitters",
    "wof:placetype":"venue"
},
  "geometry": {"coordinates":[0.054912,51.454369],"type":"Point"}
}