{
  "type": "Feature",
  "properties": {
    "iso:country":"GB",
    "sg:address":"Andil House, Court Street",
    "sg:city":"Trowbridge",
    "sg:classifiers":[
        {
            "category":"Wholesale",
            "subcategory":"Apparel",
            "type":"Manufacturing & Wholesale Goods"
        },
        {
            "category":"Shopping",
            "subcategory":"Shoes",
            "type":"Retail Goods"
        }
    ],
    "sg:phone":"+44 1225 767700",
    "sg:postcode":"BA14 8BR",
    "sg:province":"Wiltshire",
    "sg:tags":[
        "wholesaler",
        "footwear"
    ],
    "wof:name":"Cordel International",
    "wof:placetype":"venue"
},
  "geometry": {"coordinates":[-2.208769083,51.319229126],"type":"Point"}
}