{
  "type": "Feature",
  "properties": {
    "addr:full":"47 St James's Parade Bath Bath and North East Somerset BA1 1UQ",
    "addr:housenumber":"47",
    "addr:postcode":"ba1 1uq",
    "addr:street":"St James'S Parade",
    "iso:country":"GB",
    "sg:address":"47 St James's Parade",
    "sg:city":"Bath",
    "sg:classifiers":[
        {
            "category":"Bars & Pubs",
            "type":"Food & Drink"
        },
        {
            "category":"Community Center",
            "subcategory":"Social",
            "type":"Public Place"
        }
    ],
    "sg:phone":"+44 1225 460785",
    "sg:postcode":"BA1 1UQ",
    "sg:province":"Bath and North East Somerset",
    "sg:tags":[
        "pubs",
        "house",
        "inn",
        "activity"
    ],
    "wof:name":"The Hobgoblin",
    "wof:placetype":"venue"
},
  "geometry": {"coordinates":[-2.3612499237,51.3797416687],"type":"Point"}
}