{
  "type": "Feature",
  "properties": {
    "addr:full":"Rosehill, High St Lydney Gloucestershire GL15 6EQ",
    "addr:postcode":"gl15 6eq",
    "addr:street":"High St",
    "iso:country":"GB",
    "sg:address":"Rosehill, High St",
    "sg:city":"Lydney",
    "sg:classifiers":[
        {
            "category":"Farming",
            "subcategory":"Dairy Farm",
            "type":"Manufacturing & Wholesale Goods"
        }
    ],
    "sg:phone":"+44 1594 563407",
    "sg:postcode":"GL15 6EQ",
    "sg:province":"Gloucestershire",
    "wof:name":"A J Kear",
    "wof:placetype":"venue"
},
  "geometry": {"coordinates":[-2.535819,51.724491],"type":"Point"}
}