{
  "type": "Feature",
  "properties": {
    "iso:country":"GB",
    "sg:address":"34 Horsham Road",
    "sg:city":"Crawley",
    "sg:classifiers":[
        {
            "category":"Personal",
            "subcategory":"Tattoo Parlor",
            "type":"Services"
        }
    ],
    "sg:postcode":"RH11 7AX",
    "sg:province":"West Sussex",
    "sg:tags":[
        "tattooing",
        "piercing"
    ],
    "wof:name":"Dave How Tattoo's & Body Piercing",
    "wof:placetype":"venue"
},
  "geometry": {"coordinates":[-0.1962610036,51.1140098572],"type":"Point"}
}