{
  "type": "Feature",
  "properties": {
    "iso:country":"GB",
    "sg:address":"147 Church Road, Frampton Cotterell",
    "sg:city":"Bristol",
    "sg:classifiers":[
        {
            "category":"Food & Beverages",
            "subcategory":"Meat & Fish",
            "type":"Retail Goods"
        }
    ],
    "sg:postcode":"BS36 2JX",
    "sg:province":"Gloucestershire",
    "sg:tags":[
        "butcher"
    ],
    "wof:name":"Alan E Gardiner",
    "wof:placetype":"venue"
},
  "geometry": {"coordinates":[-2.464069,51.53093],"type":"Point"}
}