{
  "type": "Feature",
  "properties": {
    "addr:full":"211 Woodhouse Lane East, Timperley Altrincham Cheshire WA15 6AS",
    "addr:housenumber":"211",
    "addr:postcode":"wa15 6as",
    "addr:street":"Woodhouse Lane East",
    "iso:country":"GB",
    "sg:address":"211 Woodhouse Lane East, Timperley",
    "sg:city":"Altrincham",
    "sg:classifiers":[
        {
            "category":"Home & Garden",
            "subcategory":"Building Materials",
            "type":"Retail Goods"
        }
    ],
    "sg:postcode":"WA15 6AS",
    "sg:province":"Cheshire",
    "sg:tags":[
        "furnishers",
        "bathroom",
        "planner"
    ],
    "wof:name":"Regal Sage Bathrooms",
    "wof:placetype":"venue"
},
  "geometry": {"coordinates":[-2.3226020336,53.4072990417],"type":"Point"}
}