{
  "type": "Feature",
  "properties": {
    "iso:country":"GB",
    "sg:address":"Sweethedges Farm, Stockerston Road, Allexton",
    "sg:city":"Oakham",
    "sg:classifiers":[
        {
            "category":"Cafe",
            "type":"Food & Drink"
        },
        {
            "category":"Recreation",
            "subcategory":"Fishing",
            "type":"Entertainment"
        }
    ],
    "sg:postcode":"LE15 9AD",
    "sg:province":"Leicestershire",
    "sg:tags":[
        "tea",
        "angling",
        "room"
    ],
    "wof:name":"E B & A J Bray",
    "wof:placetype":"venue"
},
  "geometry": {"coordinates":[-0.7921460271,52.5966072083],"type":"Point"}
}