{
  "type": "Feature",
  "properties": {
    "iso:country":"GB",
    "sg:address":"Princes Drive, Coventry Road",
    "sg:city":"Kenilworth",
    "sg:classifiers":[
        {
            "category":"Autos & Motor Vehicles",
            "subcategory":"Automobile Sales",
            "type":"Retail Goods"
        }
    ],
    "sg:phone":"+44 1926 864404",
    "sg:postcode":"CV8 2SD",
    "sg:province":"Warwickshire",
    "sg:tags":[
        "car"
    ],
    "wof:name":"Warwick 4 X 4 Ltd.",
    "wof:placetype":"venue"
},
  "geometry": {"coordinates":[-1.567931,52.357346],"type":"Point"}
}