{
  "type": "Feature",
  "properties": {
    "addr:full":"Portmand Square 6 Floor 35 38 Guildford Greater London W1H 6LR",
    "addr:housenumber":"6 floor 35 38",
    "addr:postcode":"w1h 6lr",
    "iso:country":"GB",
    "sg:address":"Portmand Square 6 Floor 35 38",
    "sg:city":"Guildford",
    "sg:classifiers":[
        {
            "category":"Utilities",
            "subcategory":"Fuel Oil & Lpg",
            "type":"Services"
        }
    ],
    "sg:phone":"+44 1483 406000",
    "sg:postcode":"W1H 6LR",
    "sg:province":"Greater London",
    "sg:tags":[
        "gas"
    ],
    "wof:name":"Petrobras Uk Ltd",
    "wof:placetype":"venue"
},
  "geometry": {"coordinates":[-0.15605,51.51479],"type":"Point"}
}