{
  "type": "Feature",
  "properties": {
    "addr:full":"Hillgarden Clo, Lower Gunstone Bideford Devon EX39 2DE",
    "addr:postcode":"ex39 2de",
    "addr:street":"Lower Gunstone",
    "iso:country":"GB",
    "sg:address":"Hillgarden Clo, Lower Gunstone",
    "sg:city":"Bideford",
    "sg:classifiers":[
        {
            "category":"Organizations",
            "subcategory":"Community Association",
            "type":"Services"
        }
    ],
    "sg:phone":"+44 1237 470483",
    "sg:postcode":"EX39 2DE",
    "sg:province":"Devon",
    "sg:tags":[
        "society",
        "housing"
    ],
    "wof:name":"English Churches Housing Group",
    "wof:placetype":"venue"
},
  "geometry": {"coordinates":[-4.2042589188,51.0192489624],"type":"Point"}
}