{
  "type": "Feature",
  "properties": {
    "iso:country":"GB",
    "sg:address":"Unit 2 Southwall Industrial Estate, Southwall Road",
    "sg:city":"Deal",
    "sg:classifiers":[
        {
            "category":"Building & Trades",
            "subcategory":"Construction",
            "type":"Services"
        }
    ],
    "sg:postcode":"CT14 9QB",
    "sg:province":"Kent",
    "sg:tags":[
        "joiner",
        "decorator",
        "carpenter",
        "painter"
    ],
    "wof:name":"Kingswood Property Developments",
    "wof:placetype":"venue"
},
  "geometry": {"coordinates":[1.403235,51.223129],"type":"Point"}
}