{
  "type": "Feature",
  "properties": {
    "iso:country":"GB",
    "sg:address":"Radcliffe Infirmary, Woodstock Rd",
    "sg:city":"Oxford",
    "sg:classifiers":[
        {
            "category":"Food & Beverages",
            "subcategory":"Groceries & Convenience Stores",
            "type":"Retail Goods"
        }
    ],
    "sg:phone":"+44 1865 310429",
    "sg:postcode":"OX2 6HE",
    "sg:province":"Oxfordshire",
    "wof:name":"Piccadilly Pantry",
    "wof:placetype":"venue"
},
  "geometry": {"coordinates":[-1.2622300386,51.7606391907],"type":"Point"}
}