{
  "type": "Feature",
  "properties": {
    "addr:full":"70 Woodbridge Road Guildford Surrey GU1 4RD",
    "addr:housenumber":"70",
    "addr:postcode":"gu1 4rd",
    "addr:street":"Woodbridge Road",
    "iso:country":"GB",
    "sg:address":"70 Woodbridge Road",
    "sg:city":"Guildford",
    "sg:classifiers":[
        {
            "category":"Professional",
            "subcategory":"Accounting & Tax Preparation",
            "type":"Services"
        }
    ],
    "sg:phone":"+44 1483 566007",
    "sg:postcode":"GU1 4RD",
    "sg:province":"Surrey",
    "sg:tags":[
        "accountant"
    ],
    "wof:name":"Enticknap Peak",
    "wof:placetype":"venue"
},
  "geometry": {"coordinates":[-0.5758820176,51.2404251099],"type":"Point"}
}