{
  "type": "Feature",
  "properties": {
    "addr:full":"247 Sutton Rd Southend On Sea Essex SS2 5PE",
    "addr:housenumber":"247",
    "addr:postcode":"ss2 5pe",
    "addr:street":"Sutton Rd",
    "iso:country":"GB",
    "sg:address":"247 Sutton Rd",
    "sg:city":"Southend On Sea",
    "sg:classifiers":[
        {
            "category":"Professional",
            "subcategory":"Testing Lab",
            "type":"Services"
        }
    ],
    "sg:phone":"+44 1702 615071",
    "sg:postcode":"SS2 5PE",
    "sg:province":"Essex",
    "sg:tags":[
        "mot"
    ],
    "wof:name":"Autotech Motor Engineers",
    "wof:placetype":"venue"
},
  "geometry": {"coordinates":[0.718148,51.545864],"type":"Point"}
}