{
  "type": "Feature",
  "properties": {
    "iso:country":"GB",
    "sg:address":"24 High Street",
    "sg:city":"Mold",
    "sg:classifiers":[
        {
            "category":"Professional",
            "subcategory":"Lawyer & Legal Services",
            "type":"Services"
        }
    ],
    "sg:postcode":"CH7 1DY",
    "sg:province":"Denbighshire",
    "sg:tags":[
        "solicitor"
    ],
    "wof:name":"Jeffery Morris & Aston",
    "wof:placetype":"venue"
},
  "geometry": {"coordinates":[-3.144479,53.169449],"type":"Point"}
}