{
  "type": "Feature",
  "properties": {
    "addr:full":"Unit 2, Pilot Close, Fulmar Way Wickford Essex SS11 8YP",
    "addr:housenumber":"unit 2",
    "addr:postcode":"ss11 8yp",
    "addr:street":"Pilot Close Fulmar Way",
    "iso:country":"GB",
    "sg:address":"Unit 2, Pilot Close, Fulmar Way",
    "sg:city":"Wickford",
    "sg:classifiers":[
        {
            "category":"Shopping",
            "subcategory":"Gifts & Souvenirs",
            "type":"Retail Goods"
        }
    ],
    "sg:phone":"+44 1268 764467",
    "sg:postcode":"SS11 8YP",
    "sg:province":"Essex",
    "sg:tags":[
        "ducting"
    ],
    "wof:name":"Chadstone Engineering Ltd.",
    "wof:placetype":"venue"
},
  "geometry": {"coordinates":[0.5469099879,51.6014709473],"type":"Point"}
}