{
  "type": "Feature",
  "properties": {
    "iso:country":"GB",
    "sg:address":"Arrowe Park Road, Upton",
    "sg:city":"Wirral",
    "sg:classifiers":[
        {
            "category":"Professional",
            "type":"Services"
        },
        {
            "category":"Personal",
            "type":"Services"
        }
    ],
    "sg:phone":"+44 151 677 4007",
    "sg:postcode":"CH49 9AA",
    "sg:province":"Merseyside",
    "sg:tags":[
        "delivery",
        "good"
    ],
    "wof:name":"Upton Royal Mail Letter Delivery Office",
    "wof:placetype":"venue"
},
  "geometry": {"coordinates":[-3.113029,53.381016],"type":"Point"}
}