{
  "type": "Feature",
  "properties": {
    "addr:full":"Kirkgate Street Wisbech Cambridgeshire PE13 3QR",
    "addr:postcode":"pe13 3qr",
    "addr:street":"Kirkgate Street",
    "iso:country":"GB",
    "sg:address":"Kirkgate Street",
    "sg:city":"Wisbech",
    "sg:classifiers":[
        {
            "category":"Shopping",
            "subcategory":"Department Store",
            "type":"Retail Goods"
        },
        {
            "category":"Food & Beverages",
            "subcategory":"Groceries & Convenience Stores",
            "type":"Retail Goods"
        }
    ],
    "sg:phone":"+44 1945 583389",
    "sg:postcode":"PE13 3QR",
    "sg:province":"Cambridgeshire",
    "wof:name":"Old Walsoken Post Office",
    "wof:placetype":"venue"
},
  "geometry": {"coordinates":[0.1785250008,52.6745681763],"type":"Point"}
}