{
  "type": "Feature",
  "properties": {
    "addr:full":"Priory Cres, Penwortham Preston Lancashire PR1 0AL",
    "addr:postcode":"pr1 0al",
    "addr:street":"Priory Cres",
    "iso:country":"GB",
    "sg:address":"Priory Cres, Penwortham",
    "sg:city":"Preston",
    "sg:classifiers":[
        {
            "category":"Health Services",
            "subcategory":"Nursing And Care Facility",
            "type":"Services"
        }
    ],
    "sg:postcode":"PR1 0AL",
    "sg:province":"Lancashire",
    "sg:tags":[
        "home"
    ],
    "wof:name":"McArthur,Lorna,",
    "wof:placetype":"venue"
},
  "geometry": {"coordinates":[-2.727389,53.754532],"type":"Point"}
}