{
  "type": "Feature",
  "properties": {
    "addr:full":"31 Hazelmere Road, Petts Wood Orpington Kent BR5 1PA",
    "addr:housenumber":"31",
    "addr:postcode":"br5 1pa",
    "addr:street":"Hazelmere Road",
    "iso:country":"GB",
    "sg:address":"31 Hazelmere Road, Petts Wood",
    "sg:city":"Orpington",
    "sg:classifiers":[
        {
            "category":"Building & Trades",
            "subcategory":"Landscaping Services",
            "type":"Services"
        }
    ],
    "sg:phone":"+44 1689 820524",
    "sg:postcode":"BR5 1PA",
    "sg:province":"Kent",
    "sg:tags":[
        "designer",
        "architect",
        "landscape"
    ],
    "wof:name":"Complete Garden Services",
    "wof:placetype":"venue"
},
  "geometry": {"coordinates":[0.0755399987,51.3952598572],"type":"Point"}
}