{
  "type": "Feature",
  "properties": {
    "iso:country":"GB",
    "sg:address":"37 West View Rd",
    "sg:city":"Bristol",
    "sg:classifiers":[
        {
            "category":"Health Services",
            "subcategory":"Doctor",
            "type":"Services"
        }
    ],
    "sg:phone":"+44 117 986 3063",
    "sg:postcode":"BS18 1BH",
    "sg:province":"City of Bristol",
    "sg:tags":[
        "practitioners"
    ],
    "wof:name":"Nutt, N R",
    "wof:placetype":"venue"
},
  "geometry": {"coordinates":[-2.610581,51.436768],"type":"Point"}
}