{
  "type": "Feature",
  "properties": {
    "addr:full":"37 St Marys Crescent Basildon Essex SS13 2AR",
    "addr:housenumber":"37",
    "addr:postcode":"ss13 2ar",
    "addr:street":"St Marys Crescent",
    "iso:country":"GB",
    "sg:address":"37 St Marys Crescent",
    "sg:city":"Basildon",
    "sg:classifiers":[
        {
            "category":"Bus Charters",
            "type":"Transportation"
        }
    ],
    "sg:phone":"+44 1268 451166",
    "sg:postcode":"SS13 2AR",
    "sg:province":"Essex",
    "sg:tags":[
        "mini",
        "hire",
        "leasing"
    ],
    "wof:name":"Abacus Travel",
    "wof:placetype":"venue"
},
  "geometry": {"coordinates":[0.5112050176,51.5726318359],"type":"Point"}
}