{
  "type": "Feature",
  "properties": {
    "addr:full":"Grove Barn, Droitwich Road Redditch Warwickshire B96 6JA",
    "addr:postcode":"b96 6ja",
    "addr:street":"Droitwich Road",
    "iso:country":"GB",
    "sg:address":"Grove Barn, Droitwich Road",
    "sg:city":"Redditch",
    "sg:classifiers":[
        {
            "category":"Building & Trades",
            "subcategory":"Construction",
            "type":"Services"
        }
    ],
    "sg:phone":"+44 1527 892281",
    "sg:postcode":"B96 6JA",
    "sg:province":"Warwickshire",
    "sg:tags":[
        "builder"
    ],
    "wof:name":"Oak Timber Frame Construction",
    "wof:placetype":"venue"
},
  "geometry": {"coordinates":[-1.9878100157,52.2498512268],"type":"Point"}
}