{
  "type": "Feature",
  "properties": {
    "addr:full":"4 Katherine Place, College Road Abbots Langley Hertfordshire WD5 0BT",
    "addr:housenumber":"4",
    "addr:postcode":"wd5 0bt",
    "addr:street":"Katherine Place College Road",
    "iso:country":"GB",
    "sg:address":"4 Katherine Place, College Road",
    "sg:city":"Abbots Langley",
    "sg:classifiers":[
        {
            "category":"Food & Beverages",
            "subcategory":"Meat & Fish",
            "type":"Retail Goods"
        }
    ],
    "sg:phone":"+44 1923 681841",
    "sg:postcode":"WD5 0BT",
    "sg:province":"Hertfordshire",
    "sg:tags":[
        "chip"
    ],
    "wof:name":"Barkers Fish & Chip Shop",
    "wof:placetype":"venue"
},
  "geometry": {"coordinates":[-0.4187319875,51.704990387],"type":"Point"}
}