{
  "type": "Feature",
  "properties": {
    "iso:country":"GB",
    "sg:address":"39 High St",
    "sg:city":"Great Yarmouth",
    "sg:classifiers":[
        {
            "category":"Food & Beverages",
            "subcategory":"Bakery",
            "type":"Retail Goods"
        }
    ],
    "sg:phone":"+44 1493 720558",
    "sg:postcode":"NR30 5EL",
    "sg:province":"Norfolk",
    "sg:tags":[
        "baker"
    ],
    "wof:name":"Home Made Cake Shop",
    "wof:placetype":"venue"
},
  "geometry": {"coordinates":[1.727711,52.647568],"type":"Point"}
}