{
  "type": "Feature",
  "properties": {
    "addr:full":"Compactor House, Richardson Street High Wycombe Buckinghamshire HP11 2SB",
    "addr:postcode":"hp11 2sb",
    "addr:street":"Richardson Street",
    "iso:country":"GB",
    "sg:address":"Compactor House, Richardson Street",
    "sg:city":"High Wycombe",
    "sg:classifiers":[
        {
            "category":"Shopping",
            "subcategory":"Computers & Home Electronics",
            "type":"Retail Goods"
        }
    ],
    "sg:phone":"+44 1494 441133",
    "sg:postcode":"HP11 2SB",
    "sg:province":"Buckinghamshire",
    "sg:tags":[
        "refuse",
        "compactors"
    ],
    "wof:name":"Pakmaster Ltd.",
    "wof:placetype":"venue"
},
  "geometry": {"coordinates":[-0.763024,51.6325],"type":"Point"}
}