{
  "type": "Feature",
  "properties": {
    "iso:country":"GB",
    "sg:address":"49 Livingstone Road",
    "sg:city":"Hove",
    "sg:classifiers":[
        {
            "category":"Food & Beverages",
            "subcategory":"Groceries & Convenience Stores",
            "type":"Retail Goods"
        }
    ],
    "sg:phone":"+44 1273 775004",
    "sg:postcode":"BN3 3WN",
    "sg:province":"East Sussex",
    "wof:name":"First Stop Minimarket",
    "wof:placetype":"venue"
},
  "geometry": {"coordinates":[-0.1741860062,50.8336715698],"type":"Point"}
}