{
  "type": "Feature",
  "properties": {
    "addr:full":"25 Ferndale Rd New Milton Hampshire BH25 5EX",
    "addr:housenumber":"25",
    "addr:postcode":"bh25 5ex",
    "addr:street":"Ferndale Rd",
    "iso:country":"GB",
    "sg:address":"25 Ferndale Rd",
    "sg:city":"New Milton",
    "sg:classifiers":[
        {
            "category":"Education",
            "subcategory":"Special Training",
            "type":"Public Place"
        }
    ],
    "sg:phone":"+44 1425 616163",
    "sg:postcode":"BH25 5EX",
    "sg:province":"Hampshire",
    "sg:tags":[
        "product",
        "centre"
    ],
    "wof:name":"Education Direct",
    "wof:placetype":"venue"
},
  "geometry": {"coordinates":[-1.648523,50.762527],"type":"Point"}
}