{
  "type": "Feature",
  "properties": {
    "addr:full":"17 King Street Maryport Cumbria CA15 6AJ",
    "addr:housenumber":"17",
    "addr:postcode":"ca15 6aj",
    "addr:street":"King Street",
    "iso:country":"GB",
    "sg:address":"17 King Street",
    "sg:city":"Maryport",
    "sg:classifiers":[
        {
            "category":"Bars & Pubs",
            "type":"Food & Drink"
        }
    ],
    "sg:phone":"+44 1900 813124",
    "sg:postcode":"CA15 6AJ",
    "sg:province":"Cumbria",
    "sg:tags":[
        "pubs",
        "inn"
    ],
    "wof:name":"The Sailors Return",
    "wof:placetype":"venue"
},
  "geometry": {"coordinates":[-3.500739,54.714939],"type":"Point"}
}