{
  "type": "Feature",
  "properties": {
    "addr:full":"Unit 8 Shawlands Court, Newchapel Road Lingfield Surrey RH7 6BL",
    "addr:housenumber":"unit 8",
    "addr:postcode":"rh7 6bl",
    "addr:street":"Shawlands Court Newchapel Road",
    "iso:country":"GB",
    "sg:address":"Unit 8 Shawlands Court, Newchapel Road",
    "sg:city":"Lingfield",
    "sg:classifiers":[
        {
            "category":"Building & Trades",
            "subcategory":"Construction",
            "type":"Services"
        }
    ],
    "sg:phone":"+44 1342 832740",
    "sg:postcode":"RH7 6BL",
    "sg:province":"Surrey",
    "sg:tags":[
        "builder"
    ],
    "wof:name":"Wealden Services",
    "wof:placetype":"venue"
},
  "geometry": {"coordinates":[-0.0219190009,51.1746559143],"type":"Point"}
}