{
  "type": "Feature",
  "properties": {
    "iso:country":"GB",
    "sg:address":"81 Mill Lane, Chinnor",
    "sg:city":"Thame",
    "sg:classifiers":[
        {
            "category":"Professional",
            "subcategory":"Management & Consulting",
            "type":"Services"
        },
        {
            "category":"Retail",
            "subcategory":"Driving School",
            "type":"Services"
        }
    ],
    "sg:phone":"+44 1844 352180",
    "sg:postcode":"OX39 4QU",
    "sg:province":"Buckinghamshire",
    "sg:tags":[
        "consultant",
        "business"
    ],
    "wof:name":"Street-Wise School of Motoring",
    "wof:placetype":"venue"
},
  "geometry": {"coordinates":[-0.920204,51.701935],"type":"Point"}
}