{
  "type": "Feature",
  "properties": {
    "iso:country":"GB",
    "sg:address":"Axsia House, Davy Way, Waterwells Business Park",
    "sg:city":"Gloucester",
    "sg:classifiers":[
        {
            "category":"Military Area",
            "subcategory":"Air Force Base",
            "type":"Public Place"
        }
    ],
    "sg:phone":"+44 1452 833800",
    "sg:postcode":"GL2 4AS",
    "sg:province":"Gloucestershire",
    "sg:tags":[
        "water",
        "treatment"
    ],
    "wof:name":"Axsia Serck Baker Ltd.",
    "wof:placetype":"venue"
},
  "geometry": {"coordinates":[-2.2772591114,51.8139381409],"type":"Point"}
}