{
  "type": "Feature",
  "properties": {
    "iso:country":"GB",
    "sg:address":"Churchill Road",
    "sg:city":"Wisbech",
    "sg:classifiers":[
        {
            "category":"Shopping",
            "subcategory":"Catalog Store",
            "type":"Retail Goods"
        }
    ],
    "sg:phone":"+44 1945 466482",
    "sg:postcode":"PE13 1AR",
    "sg:province":"Cambridgeshire",
    "sg:tags":[
        "catalogue",
        "showroom"
    ],
    "wof:name":"Argos Distributors",
    "wof:placetype":"venue"
},
  "geometry": {"coordinates":[0.163319,52.665127],"type":"Point"}
}