{
  "type": "Feature",
  "properties": {
    "iso:country":"GB",
    "sg:address":"12 Carlton Street",
    "sg:city":"Weston-super-mare",
    "sg:classifiers":[
        {
            "category":"Bars & Pubs",
            "type":"Food & Drink"
        }
    ],
    "sg:phone":"+44 1934 413412",
    "sg:postcode":"BS23 1UA",
    "sg:province":"Somerset",
    "sg:tags":[
        "pubs",
        "inn"
    ],
    "wof:name":"D Coupe",
    "wof:placetype":"venue"
},
  "geometry": {"coordinates":[-2.979170084,51.3449935913],"type":"Point"}
}