{
  "type": "Feature",
  "properties": {
    "addr:full":"20 East Fen Road, Isleham Ely Cambridgeshire CB7 5SW",
    "addr:housenumber":"20",
    "addr:postcode":"cb7 5sw",
    "addr:street":"East Fen Road",
    "iso:country":"GB",
    "sg:address":"20 East Fen Road, Isleham",
    "sg:city":"Ely",
    "sg:classifiers":[
        {
            "category":"Home & Garden",
            "subcategory":"Carpets & Floor Coverings",
            "type":"Retail Goods"
        }
    ],
    "sg:postcode":"CB7 5SW",
    "sg:province":"Cambridgeshire",
    "sg:tags":[
        "cleaner",
        "upholstery"
    ],
    "wof:name":"Rainbow International",
    "wof:placetype":"venue"
},
  "geometry": {"coordinates":[0.42366,52.345963],"type":"Point"}
}