{
  "type": "Feature",
  "properties": {
    "addr:full":"Bucklesbury House, 3 Queen Victoria Street London Greater London EC4N 4TQ",
    "addr:housenumber":"3",
    "addr:postcode":"ec4n 4tq",
    "addr:street":"Queen Victoria Street",
    "iso:country":"GB",
    "sg:address":"Bucklesbury House, 3 Queen Victoria Street",
    "sg:city":"London",
    "sg:classifiers":[
        {
            "category":"Restaurant",
            "type":"Food & Drink"
        }
    ],
    "sg:phone":"+44 20 7827 0202",
    "sg:postcode":"EC4N 4TQ",
    "sg:province":"Greater London",
    "sg:tags":[
        "thai"
    ],
    "wof:name":"Sri Thai Restaurant",
    "wof:placetype":"venue"
},
  "geometry": {"coordinates":[-0.090086,51.513088],"type":"Point"}
}