{
  "type": "Feature",
  "properties": {
    "addr:full":"7 Cumberland House, Cumberland Street York North Yorkshire YO1 1NX",
    "addr:housenumber":"7",
    "addr:postcode":"yo1 1nx",
    "addr:street":"Cumberland House Cumberland Street",
    "iso:country":"GB",
    "sg:address":"7 Cumberland House, Cumberland Street",
    "sg:city":"York",
    "sg:classifiers":[
        {
            "category":"Military Area",
            "subcategory":"Air Force Base",
            "type":"Public Place"
        }
    ],
    "sg:phone":"+44 1904 638833",
    "sg:postcode":"YO1 1NX",
    "sg:province":"North Yorkshire",
    "sg:tags":[
        "taxi",
        "hire",
        "private"
    ],
    "wof:name":"Streamline Taxis (York) Ltd.",
    "wof:placetype":"venue"
},
  "geometry": {"coordinates":[-1.0813499689,53.958770752],"type":"Point"}
}