{
  "type": "Feature",
  "properties": {
    "addr:full":"20-24 Pierce Lane, Fulbourn Cambridge Cambridgeshire CB1 5DL",
    "addr:housenumber":"20-24",
    "addr:postcode":"cb1 5dl",
    "addr:street":"Pierce Lane",
    "iso:country":"GB",
    "sg:address":"20-24 Pierce Lane, Fulbourn",
    "sg:city":"Cambridge",
    "sg:classifiers":[
        {
            "category":"Transit Center",
            "subcategory":"Freight",
            "type":"Transportation"
        },
        {
            "category":"Retail",
            "subcategory":"Repair Shop",
            "type":"Services"
        }
    ],
    "sg:phone":"+44 1223 881691",
    "sg:postcode":"CB1 5DL",
    "sg:province":"Cambridgeshire",
    "sg:tags":[
        "instrument",
        "piano",
        "restoration",
        "musical",
        "accessory"
    ],
    "wof:name":"1066 PIANOS",
    "wof:placetype":"venue"
},
  "geometry": {"coordinates":[0.2195229977,52.1837806702],"type":"Point"}
}