{
  "type": "Feature",
  "properties": {
    "addr:full":"76 Baldry Gardens London Greater London SW16 3DP",
    "addr:housenumber":"76",
    "addr:postcode":"sw16 3dp",
    "addr:street":"Baldry Gardens",
    "iso:country":"GB",
    "sg:address":"76 Baldry Gardens",
    "sg:city":"London",
    "sg:classifiers":[
        {
            "category":"Building & Trades",
            "subcategory":"Construction",
            "type":"Services"
        }
    ],
    "sg:postcode":"SW16 3DP",
    "sg:province":"Greater London",
    "sg:tags":[
        "builder"
    ],
    "wof:name":"John A Fraser",
    "wof:placetype":"venue"
},
  "geometry": {"coordinates":[-0.120408,51.420998],"type":"Point"}
}