{
  "type": "Feature",
  "properties": {
    "iso:country":"GB",
    "sg:address":"74 Lower Galdeford",
    "sg:city":"Ludlow",
    "sg:classifiers":[
        {
            "category":"Building & Trades",
            "subcategory":"Construction",
            "type":"Services"
        }
    ],
    "sg:phone":"+44 1584 873146",
    "sg:postcode":"SY8 1RU",
    "sg:province":"Herefordshire",
    "sg:tags":[
        "glazier",
        "decorator",
        "painter"
    ],
    "wof:name":"Tony R Flowers",
    "wof:placetype":"venue"
},
  "geometry": {"coordinates":[-2.713936,52.367912],"type":"Point"}
}