{
  "type": "Feature",
  "properties": {
    "iso:country":"GB",
    "sg:address":"Fairfield Farm, Upper North Wraxall",
    "sg:city":"Chippenham",
    "sg:classifiers":[
        {
            "category":"Farming",
            "subcategory":"Livestock Farm",
            "type":"Manufacturing & Wholesale Goods"
        }
    ],
    "sg:postcode":"SN14 7AG",
    "sg:province":"Gloucestershire",
    "sg:tags":[
        "others"
    ],
    "wof:name":"Macattack Partners",
    "wof:placetype":"venue"
},
  "geometry": {"coordinates":[-2.263205,51.473179],"type":"Point"}
}