{
  "type": "Feature",
  "properties": {
    "iso:country":"GB",
    "sg:address":"5a Eaglesham Rd",
    "sg:city":"Glasgow",
    "sg:classifiers":[
        {
            "category":"Health Services",
            "subcategory":"Doctor",
            "type":"Services"
        }
    ],
    "sg:phone":"+44 141 644 2356",
    "sg:postcode":"G76 7BU",
    "sg:province":"East Renfrewshire",
    "sg:tags":[
        "practitioners"
    ],
    "wof:name":"Irene Colquhoun",
    "wof:placetype":"venue"
},
  "geometry": {"coordinates":[-4.274733,55.785595],"type":"Point"}
}