{
  "type": "Feature",
  "properties": {
    "addr:full":"Commercial Road, Redcliffe Bristol City of Bristol BS1 6TH",
    "addr:postcode":"bs1 6th",
    "addr:street":"Commercial Road",
    "iso:country":"GB",
    "sg:address":"Commercial Road, Redcliffe",
    "sg:city":"Bristol",
    "sg:classifiers":[
        {
            "category":"Bars & Pubs",
            "type":"Food & Drink"
        }
    ],
    "sg:phone":"+44 117 926 2812",
    "sg:postcode":"BS1 6TH",
    "sg:province":"City of Bristol",
    "sg:tags":[
        "pubs",
        "inn"
    ],
    "wof:name":"The Velindra",
    "wof:placetype":"venue"
},
  "geometry": {"coordinates":[-2.5954759121,51.4462814331],"type":"Point"}
}