{
  "type": "Feature",
  "properties": {
    "addr:full":"Gerrard Busns Centre Littlehampton West Sussex BN16 1AW",
    "addr:postcode":"bn16 1aw",
    "iso:country":"GB",
    "sg:address":"Gerrard Busns Centre",
    "sg:city":"Littlehampton",
    "sg:classifiers":[
        {
            "category":"Professional",
            "subcategory":"Computer Services",
            "type":"Services"
        }
    ],
    "sg:phone":"+44 1903 859019",
    "sg:postcode":"BN16 1AW",
    "sg:province":"West Sussex",
    "sg:tags":[
        "consultant"
    ],
    "wof:name":"Admin Com Ltd.",
    "wof:placetype":"venue"
},
  "geometry": {"coordinates":[-0.4886299968,50.8153991699],"type":"Point"}
}