{
  "type": "Feature",
  "properties": {
    "addr:full":"Avenue Road Freshwater Isle of Wight PO40 9UT",
    "addr:postcode":"po40 9ut",
    "addr:street":"Avenue Road",
    "iso:country":"GB",
    "sg:address":"Avenue Road",
    "sg:city":"Freshwater",
    "sg:classifiers":[
        {
            "category":"Food & Beverages",
            "subcategory":"Fruits & Vegetables",
            "type":"Retail Goods"
        }
    ],
    "sg:phone":"+44 1983 755256",
    "sg:postcode":"PO40 9UT",
    "sg:province":"Isle of Wight",
    "sg:tags":[
        "greengrocer"
    ],
    "wof:name":"Avenue Road Greengrocers",
    "wof:placetype":"venue"
},
  "geometry": {"coordinates":[-1.529724,50.684238],"type":"Point"}
}