{
  "type": "Feature",
  "properties": {
    "addr:full":"Unit 13 Poppletons Mill, Engine La Wakefield West Yorkshire WF4 5NH",
    "addr:housenumber":"unit 13",
    "addr:postcode":"wf4 5nh",
    "addr:street":"Poppletons;West",
    "iso:country":"GB",
    "sg:address":"Unit 13 Poppletons Mill, Engine La",
    "sg:city":"Wakefield",
    "sg:classifiers":[
        {
            "category":"Personal",
            "subcategory":"Skin Care",
            "type":"Services"
        }
    ],
    "sg:phone":"+44 1924 272236",
    "sg:postcode":"WF4 5NH",
    "sg:province":"West Yorkshire",
    "sg:tags":[
        "leather",
        "merchant"
    ],
    "wof:name":"B B M",
    "wof:placetype":"venue"
},
  "geometry": {"coordinates":[-1.56685,53.657791],"type":"Point"}
}