{
  "type": "Feature",
  "properties": {
    "addr:full":"5 Daleham Gardens London Greater London NW3 5BY",
    "addr:housenumber":"5",
    "addr:postcode":"nw3 5by",
    "addr:street":"Daleham Gardens",
    "iso:country":"GB",
    "sg:address":"5 Daleham Gardens",
    "sg:city":"London",
    "sg:classifiers":[
        {
            "category":"Health Services",
            "subcategory":"Clinic",
            "type":"Services"
        }
    ],
    "sg:phone":"+44 20 7530 2500",
    "sg:postcode":"NW3 5BY",
    "sg:province":"Greater London",
    "sg:tags":[
        "nh"
    ],
    "wof:name":"Daleham Garden Nhs Health Clinic",
    "wof:placetype":"venue"
},
  "geometry": {"coordinates":[-0.17315,51.548798],"type":"Point"}
}