{
  "type": "Feature",
  "properties": {
    "addr:full":"Holt Ct, Heneage St, Aston Science Pk, Love La Birmingham West Midlands B7 4AX",
    "addr:postcode":"b7 4ax",
    "addr:street":"Holt Ct Heneage St;Science Pk Love La Birmingham",
    "iso:country":"GB",
    "sg:address":"Holt Ct, Heneage St, Aston Science Pk, Love La",
    "sg:city":"Birmingham",
    "sg:classifiers":[
        {
            "category":"Wholesale",
            "subcategory":"Machinery & Supplies",
            "type":"Manufacturing & Wholesale Goods"
        }
    ],
    "sg:postcode":"B7 4AX",
    "sg:province":"West Midlands",
    "sg:tags":[
        "equipment",
        "handling",
        "lifting"
    ],
    "wof:name":"Stocklin Translogistics Ltd",
    "wof:placetype":"venue"
},
  "geometry": {"coordinates":[-1.884165,52.485771],"type":"Point"}
}