{
  "type": "Feature",
  "properties": {
    "iso:country":"GB",
    "sg:address":"53 Clandon Close, Stoneleigh",
    "sg:city":"Epsom",
    "sg:classifiers":[
        {
            "category":"Real Estate",
            "subcategory":"Architect",
            "type":"Services"
        }
    ],
    "sg:postcode":"KT17 2NH",
    "sg:province":"Surrey",
    "wof:name":"James Parsons",
    "wof:placetype":"venue"
},
  "geometry": {"coordinates":[-0.248602,51.361725],"type":"Point"}
}