{
  "type": "Feature",
  "properties": {
    "iso:country":"GB",
    "sg:address":"8 Birchwood Place",
    "sg:city":"Aboyne",
    "sg:classifiers":[
        {
            "category":"Taxi",
            "type":"Transportation"
        },
        {
            "category":"Military Area",
            "subcategory":"Air Force Base",
            "type":"Public Place"
        }
    ],
    "sg:phone":"+44 1339 886715",
    "sg:postcode":"AB34 5FA",
    "sg:province":"Aberdeenshire",
    "sg:tags":[
        "hire",
        "private"
    ],
    "wof:name":"Aboyne Taxis",
    "wof:placetype":"venue"
},
  "geometry": {"coordinates":[-2.793668,57.073402],"type":"Point"}
}