{
  "type": "Feature",
  "properties": {
    "addr:full":"2 Lyndhurst Cres Gateshead Tyne and Wear NE9 6BA",
    "addr:housenumber":"2",
    "addr:postcode":"ne9 6ba",
    "addr:street":"Lyndhurst Cres",
    "iso:country":"GB",
    "sg:address":"2 Lyndhurst Cres",
    "sg:city":"Gateshead",
    "sg:classifiers":[
        {
            "category":"Banks & Credit Unions",
            "subcategory":"Financial Services",
            "type":"Services"
        }
    ],
    "sg:phone":"+44 191 420 5111",
    "sg:postcode":"NE9 6BA",
    "sg:province":"Tyne and Wear",
    "sg:tags":[
        "consultant"
    ],
    "wof:name":"Cornhill Financial Services",
    "wof:placetype":"venue"
},
  "geometry": {"coordinates":[-1.595187,54.930107],"type":"Point"}
}