{
  "type": "Feature",
  "properties": {
    "iso:country":"GB",
    "sg:address":"36 Burnley Road, Brierfield",
    "sg:city":"Burnley",
    "sg:classifiers":[
        {
            "category":"Autos & Motor Vehicles",
            "subcategory":"Automobile Sales",
            "type":"Retail Goods"
        }
    ],
    "sg:phone":"+44 1282 722606",
    "sg:postcode":"BB9 5HY",
    "sg:province":"Lancashire",
    "sg:tags":[
        "commercial"
    ],
    "wof:name":"Independent Vehicle Sourcing",
    "wof:placetype":"venue"
},
  "geometry": {"coordinates":[-2.234284,53.823605],"type":"Point"}
}