{
  "type": "Feature",
  "properties": {
    "iso:country":"GB",
    "sg:address":"510 Darwen Road, Bromley Cross",
    "sg:city":"Bolton",
    "sg:classifiers":[
        {
            "category":"Building & Trades",
            "subcategory":"Construction",
            "type":"Services"
        }
    ],
    "sg:phone":"+44 1204 592227",
    "sg:postcode":"BL7 9DX",
    "sg:province":"Lancashire",
    "sg:tags":[
        "contractor"
    ],
    "wof:name":"M J D Construction Ltd.",
    "wof:placetype":"venue"
},
  "geometry": {"coordinates":[-2.43115,53.620327],"type":"Point"}
}