{
  "type": "Feature",
  "properties": {
    "addr:full":"Dickens Place Chelmsford Essex CM1 4UU",
    "addr:postcode":"cm1 4uu",
    "addr:street":"Dickens Place",
    "iso:country":"GB",
    "sg:address":"Dickens Place",
    "sg:city":"Chelmsford",
    "sg:classifiers":[
        {
            "category":"Education",
            "subcategory":"Preschool",
            "type":"Public Place"
        },
        {
            "category":"Education",
            "subcategory":"School",
            "type":"Public Place"
        }
    ],
    "sg:phone":"+44 1245 442505",
    "sg:postcode":"CM1 4UU",
    "sg:province":"Essex",
    "sg:tags":[
        "pre",
        "playgroups",
        "pre-school",
        "college"
    ],
    "wof:name":"Newlands Spring Pre-School",
    "wof:placetype":"venue"
},
  "geometry": {"coordinates":[0.445795,51.754887],"type":"Point"}
}