{
  "type": "Feature",
  "properties": {
    "iso:country":"GB",
    "sg:address":"31 Rodney Street",
    "sg:city":"Liverpool",
    "sg:classifiers":[
        {
            "category":"Health Services",
            "subcategory":"Doctor",
            "type":"Services"
        }
    ],
    "sg:phone":"+44 151 703 2915",
    "sg:postcode":"L1 9EH",
    "sg:province":"Merseyside",
    "sg:tags":[
        "surgeon"
    ],
    "wof:name":"J Ansari",
    "wof:placetype":"venue"
},
  "geometry": {"coordinates":[-2.973218,53.401337],"type":"Point"}
}