{
  "type": "Feature",
  "properties": {
    "addr:full":"1 East Barnet Road Barnet Hertfordshire EN4 8RR",
    "addr:housenumber":"1",
    "addr:postcode":"en4 8rr",
    "addr:street":"East Barnet Road",
    "iso:country":"GB",
    "sg:address":"1 East Barnet Road",
    "sg:city":"Barnet",
    "sg:classifiers":[
        {
            "category":"Professional",
            "subcategory":"Accounting & Tax Preparation",
            "type":"Services"
        }
    ],
    "sg:phone":"+44 20 8449 8297",
    "sg:postcode":"EN4 8RR",
    "sg:province":"Hertfordshire",
    "sg:tags":[
        "accountant"
    ],
    "wof:name":"Taylors",
    "wof:placetype":"venue"
},
  "geometry": {"coordinates":[-0.1747429967,51.6500663757],"type":"Point"}
}