{
  "type": "Feature",
  "properties": {
    "iso:country":"GB",
    "sg:address":"Units 1m-1n, Bechers Drive, Racecourse Retail & Business Park",
    "sg:city":"Liverpool",
    "sg:classifiers":[
        {
            "category":"Building & Trades",
            "subcategory":"Plumbing",
            "type":"Services"
        }
    ],
    "sg:phone":"+44 151 521 1000",
    "sg:postcode":"L9 5AY",
    "sg:province":"Merseyside",
    "sg:tags":[
        "merchant",
        "plumbers'"
    ],
    "wof:name":"P T S Plumbing Trade Supplies Ltd.",
    "wof:placetype":"venue"
},
  "geometry": {"coordinates":[-2.94715,53.480141],"type":"Point"}
}