{
  "type": "Feature",
  "properties": {
    "addr:full":"84 Upney Lane Barking Essex IG11 9LR",
    "addr:housenumber":"84",
    "addr:postcode":"ig11 9lr",
    "addr:street":"Upney Lane",
    "iso:country":"GB",
    "sg:address":"84 Upney Lane",
    "sg:city":"Barking",
    "sg:classifiers":[
        {
            "category":"Organizations",
            "subcategory":"Non-profit Organization",
            "type":"Services"
        }
    ],
    "sg:postcode":"IG11 9LR",
    "sg:province":"Essex",
    "sg:tags":[
        "organisation",
        "voluntary",
        "charity"
    ],
    "wof:name":"Royal London Society",
    "wof:placetype":"venue"
},
  "geometry": {"coordinates":[0.09562,51.542934],"type":"Point"}
}