{
  "type": "Feature",
  "properties": {
    "addr:full":"2a & 3a Warbreck Moor Liverpool Merseyside L9 4RN",
    "addr:housenumber":"2a & 3a",
    "addr:postcode":"l9 4rn",
    "addr:street":"Warbreck Moor",
    "iso:country":"GB",
    "sg:address":"2a & 3a Warbreck Moor",
    "sg:city":"Liverpool",
    "sg:classifiers":[
        {
            "category":"Shopping",
            "subcategory":"Discount & Variety Stores",
            "type":"Retail Goods"
        }
    ],
    "sg:phone":"+44 151 525 2334",
    "sg:postcode":"L9 4RN",
    "sg:province":"Merseyside",
    "sg:tags":[
        "centre"
    ],
    "wof:name":"Money Saver",
    "wof:placetype":"venue"
},
  "geometry": {"coordinates":[-2.957883,53.465],"type":"Point"}
}