{
  "type": "Feature",
  "properties": {
    "addr:full":"Merthyr Mawr Road Bridgend Bridgend CF31 3NN",
    "addr:postcode":"cf31 3nn",
    "addr:street":"Merthyr Mawr Road",
    "iso:country":"GB",
    "sg:address":"Merthyr Mawr Road",
    "sg:city":"Bridgend",
    "sg:classifiers":[
        {
            "category":"Farming",
            "subcategory":"Farm",
            "type":"Manufacturing & Wholesale Goods"
        },
        {
            "category":"Health Services",
            "subcategory":"Dentist",
            "type":"Services"
        }
    ],
    "sg:phone":"+44 1656 652212",
    "sg:postcode":"CF31 3NN",
    "sg:province":"Bridgend",
    "sg:tags":[
        "mixed"
    ],
    "wof:name":"JONES BIRKS & JOHN",
    "wof:placetype":"venue"
},
  "geometry": {"coordinates":[-3.5798239708,51.5019454956],"type":"Point"}
}