{
  "type": "Feature",
  "properties": {
    "iso:country":"GB",
    "sg:address":"Rookery House, Abbeygate Street",
    "sg:city":"Colchester",
    "sg:classifiers":[
        {
            "category":"Professional",
            "subcategory":"Engineering",
            "type":"Services"
        }
    ],
    "sg:phone":"+44 1206 768556",
    "sg:postcode":"CO2 7HB",
    "sg:province":"Essex",
    "sg:tags":[
        "consultant",
        "structural",
        "engineer"
    ],
    "sg:website":"http://www.eapcc.co.uk",
    "wof:name":"E A P Property Services Ltd",
    "wof:placetype":"venue"
},
  "geometry": {"coordinates":[0.903514,51.8853],"type":"Point"}
}