{
  "type": "Feature",
  "properties": {
    "addr:full":"Buckland Rd Chessington Surrey KT9 1JE",
    "addr:postcode":"kt9 1je",
    "addr:street":"Buckland Rd",
    "iso:country":"GB",
    "sg:address":"Buckland Rd",
    "sg:city":"Chessington",
    "sg:classifiers":[
        {
            "category":"Education",
            "subcategory":"School",
            "type":"Public Place"
        }
    ],
    "sg:phone":"+44 20 8397 3951",
    "sg:postcode":"KT9 1JE",
    "sg:province":"Surrey",
    "sg:tags":[
        "local",
        "authority"
    ],
    "wof:name":"Buckland Infants School",
    "wof:placetype":"venue"
},
  "geometry": {"coordinates":[-0.2971740067,51.3659858704],"type":"Point"}
}