{
  "type": "Feature",
  "properties": {
    "iso:country":"GB",
    "sg:address":"27 Woodburn Rd",
    "sg:city":"Manchester",
    "sg:classifiers":[
        {
            "category":"Building & Trades",
            "subcategory":"Plumbing",
            "type":"Services"
        }
    ],
    "sg:phone":"+44 161 998 4141",
    "sg:postcode":"M22 4BZ",
    "sg:province":"Greater Manchester",
    "sg:tags":[
        "heating"
    ],
    "wof:name":"M.J. Scott",
    "wof:placetype":"venue"
},
  "geometry": {"coordinates":[-2.262781,53.404713],"type":"Point"}
}