{
  "type": "Feature",
  "properties": {
    "iso:country":"GB",
    "sg:address":"16 Gradwell St",
    "sg:city":"Liverpool",
    "sg:classifiers":[
        {
            "category":"Parking",
            "type":"Transportation"
        }
    ],
    "sg:phone":"+44 151 707 1708",
    "sg:postcode":"L1 4JH",
    "sg:province":"Merseyside",
    "sg:tags":[
        "car",
        "park"
    ],
    "wof:name":"R.C.P Car Park",
    "wof:placetype":"venue"
},
  "geometry": {"coordinates":[-2.983347,53.402554],"type":"Point"}
}