{
  "type": "Feature",
  "properties": {
    "addr:full":"Brazilia House, Victoria Way, Studlands Park Avenue Newmarket Cambridgeshire CB8 7SH",
    "addr:housenumber":"brazilia",
    "addr:postcode":"cb8 7sh",
    "addr:street":"Victoria Way Studlands Park Avenue Newmarket",
    "iso:country":"GB",
    "sg:address":"Brazilia House, Victoria Way, Studlands Park Avenue",
    "sg:city":"Newmarket",
    "sg:classifiers":[
        {
            "category":"Coffee & Tea",
            "type":"Food & Drink"
        },
        {
            "category":"Food & Beverages",
            "subcategory":"Groceries & Convenience Stores",
            "type":"Retail Goods"
        }
    ],
    "sg:phone":"+44 1638 666733",
    "sg:postcode":"CB8 7SH",
    "sg:province":"Cambridgeshire",
    "sg:tags":[
        "machine",
        "supplier"
    ],
    "wof:name":"Coffee Express",
    "wof:placetype":"venue"
},
  "geometry": {"coordinates":[0.3883799911,52.2603797913],"type":"Point"}
}