{
  "type": "Feature",
  "properties": {
    "addr:full":"Victoria Road, Southwick Brighton West Sussex BN42 4DH",
    "addr:postcode":"bn42 4dh",
    "addr:street":"Victoria Road",
    "iso:country":"GB",
    "sg:address":"Victoria Road, Southwick",
    "sg:city":"Brighton",
    "sg:classifiers":[
        {
            "category":"Retail",
            "subcategory":"Auto Repair",
            "type":"Services"
        }
    ],
    "sg:phone":"+44 1273 592318",
    "sg:postcode":"BN42 4DH",
    "sg:province":"West Sussex",
    "sg:tags":[
        "modification",
        "garage"
    ],
    "wof:name":"Amber Garage",
    "wof:placetype":"venue"
},
  "geometry": {"coordinates":[-0.23742,50.836205],"type":"Point"}
}