{
  "type": "Feature",
  "properties": {
    "iso:country":"GB",
    "sg:address":"14 High Street",
    "sg:city":"Barnstaple",
    "sg:classifiers":[
        {
            "category":"Personal",
            "subcategory":"Beauty Salon",
            "type":"Services"
        }
    ],
    "sg:phone":"+44 1271 379985",
    "sg:postcode":"EX31 1BG",
    "sg:province":"Devon",
    "sg:tags":[
        "unisex",
        "hairdresser"
    ],
    "wof:name":"Evon's",
    "wof:placetype":"venue"
},
  "geometry": {"coordinates":[-4.059076,51.079231],"type":"Point"}
}