{
  "type": "Feature",
  "properties": {
    "addr:full":"42b Eastern Avenue Reading Berkshire RG1 5RY",
    "addr:housenumber":"42b",
    "addr:postcode":"rg1 5ry",
    "addr:street":"Eastern Avenue",
    "iso:country":"GB",
    "sg:address":"42b Eastern Avenue",
    "sg:city":"Reading",
    "sg:classifiers":[
        {
            "category":"Shopping",
            "subcategory":"Florist",
            "type":"Retail Goods"
        }
    ],
    "sg:postcode":"RG1 5RY",
    "sg:province":"Berkshire",
    "wof:name":"Pinks Plant Shops Ltd.",
    "wof:placetype":"venue"
},
  "geometry": {"coordinates":[-0.94696,51.450516],"type":"Point"}
}