{
  "type": "Feature",
  "properties": {
    "addr:full":"62 Bullpond Lane Dunstable Bedfordshire LU6 3BJ",
    "addr:housenumber":"62",
    "addr:postcode":"lu6 3bj",
    "addr:street":"Bullpond Lane",
    "iso:country":"GB",
    "sg:address":"62 Bullpond Lane",
    "sg:city":"Dunstable",
    "sg:classifiers":[
        {
            "category":"Retail",
            "subcategory":"Driving School",
            "type":"Services"
        }
    ],
    "sg:phone":"+44 1582 660865",
    "sg:postcode":"LU6 3BJ",
    "sg:province":"Bedfordshire",
    "wof:name":"D F B School Of Motoring",
    "wof:placetype":"venue"
},
  "geometry": {"coordinates":[-0.5222989917,51.8828086853],"type":"Point"}
}