{
  "type": "Feature",
  "properties": {
    "addr:full":"Tregonan, Tregony Truro Cornwall TR2 5SN",
    "addr:postcode":"tr2 5sn",
    "iso:country":"GB",
    "sg:address":"Tregonan, Tregony",
    "sg:city":"Truro",
    "sg:classifiers":[
        {
            "category":"Farming",
            "subcategory":"Livestock Farm",
            "type":"Manufacturing & Wholesale Goods"
        }
    ],
    "sg:phone":"+44 1872 530249",
    "sg:postcode":"TR2 5SN",
    "sg:province":"Cornwall",
    "sg:tags":[
        "others"
    ],
    "wof:name":"J C Collins",
    "wof:placetype":"venue"
},
  "geometry": {"coordinates":[-4.9126501083,50.2677154541],"type":"Point"}
}