{
  "type": "Feature",
  "properties": {
    "addr:full":"Jaguar House, Scotswood Road Newcastle-upon-tyne Tyne and Wear NE4 7DF",
    "addr:postcode":"ne4 7df",
    "addr:street":"Scotswood Road",
    "iso:country":"GB",
    "sg:address":"Jaguar House, Scotswood Road",
    "sg:city":"Newcastle-upon-tyne",
    "sg:classifiers":[
        {
            "category":"Autos & Motor Vehicles",
            "subcategory":"Automobile Sales",
            "type":"Retail Goods"
        }
    ],
    "sg:phone":"+44 191 226 7171",
    "sg:postcode":"NE4 7DF",
    "sg:province":"Tyne and Wear",
    "sg:tags":[
        "car"
    ],
    "wof:name":"The Dutton-Forshaw Motor Co Ltd",
    "wof:placetype":"venue"
},
  "geometry": {"coordinates":[-1.621894,54.967205],"type":"Point"}
}