{
  "type": "Feature",
  "properties": {
    "iso:country":"GB",
    "sg:address":"8-9 Victoria Rd",
    "sg:city":"Swindon",
    "sg:classifiers":[
        {
            "category":"Recreation",
            "subcategory":"Amusement Park",
            "type":"Entertainment"
        }
    ],
    "sg:phone":"+44 1793 535218",
    "sg:postcode":"SN1 3AJ",
    "sg:province":"Wiltshire",
    "sg:tags":[
        "arcade"
    ],
    "wof:name":"Amusement Caterers (Swindon) Ltd",
    "wof:placetype":"venue"
},
  "geometry": {"coordinates":[-1.778908968,51.5567703247],"type":"Point"}
}