{
  "type": "Feature",
  "properties": {
    "addr:full":"Rosehill Terr, 591 Ormskirk Rd Wigan Lancashire WN5 8AG",
    "addr:housenumber":"591",
    "addr:postcode":"wn5 8ag",
    "addr:street":"Rosehill Terr;Ormskirk Rd",
    "iso:country":"GB",
    "sg:address":"Rosehill Terr, 591 Ormskirk Rd",
    "sg:city":"Wigan",
    "sg:classifiers":[
        {
            "category":"Home & Garden",
            "subcategory":"Household Appliances",
            "type":"Retail Goods"
        }
    ],
    "sg:phone":"+44 1942 701845",
    "sg:postcode":"WN5 8AG",
    "sg:province":"Lancashire",
    "sg:tags":[
        "electrical"
    ],
    "wof:name":"Electro-Check UK",
    "wof:placetype":"venue"
},
  "geometry": {"coordinates":[-2.6776599884,53.5356292725],"type":"Point"}
}