{
  "type": "Feature",
  "properties": {
    "iso:country":"GB",
    "sg:address":"11-13 Winchester Street",
    "sg:city":"Basingstoke",
    "sg:classifiers":[
        {
            "category":"Professional",
            "subcategory":"Employment Agencies",
            "type":"Services"
        }
    ],
    "sg:phone":"+44 1256 466725",
    "sg:postcode":"RG21 1ED",
    "sg:province":"Hampshire",
    "sg:tags":[
        "consultant"
    ],
    "wof:name":"Adecco Alfred Marks",
    "wof:placetype":"venue"
},
  "geometry": {"coordinates":[-1.0876400471,51.2622909546],"type":"Point"}
}