{
  "type": "Feature",
  "properties": {
    "iso:country":"GB",
    "sg:address":"Organford Farm House",
    "sg:city":"Poole",
    "sg:classifiers":[
        {
            "category":"Farming",
            "subcategory":"Livestock Farm",
            "type":"Manufacturing & Wholesale Goods"
        }
    ],
    "sg:phone":"+44 1202 622233",
    "sg:postcode":"BH16 6EU",
    "sg:province":"Dorset",
    "sg:tags":[
        "others"
    ],
    "wof:name":"W F B Palmer & Son (Organ Ford) Ltd.",
    "wof:placetype":"venue"
},
  "geometry": {"coordinates":[-2.072369,50.73354],"type":"Point"}
}