{
  "type": "Feature",
  "properties": {
    "iso:country":"GB",
    "sg:address":"Oxford St",
    "sg:city":"Keighley",
    "sg:classifiers":[
        {
            "category":"Organizations",
            "subcategory":"Non-profit Organization",
            "type":"Services"
        }
    ],
    "sg:phone":"+44 1535 602204",
    "sg:postcode":"BD21 1RA",
    "sg:province":"West Yorkshire",
    "sg:tags":[
        "organisation",
        "voluntary",
        "charity"
    ],
    "wof:name":"Keighley Resource Centre",
    "wof:placetype":"venue"
},
  "geometry": {"coordinates":[-1.9186140299,53.862613678],"type":"Point"}
}