{
  "type": "Feature",
  "properties": {
    "addr:full":"Grove Road Cowes Isle of Wight PO31 7JP",
    "addr:postcode":"po31 7jp",
    "addr:street":"Grove Road",
    "iso:country":"GB",
    "sg:address":"Grove Road",
    "sg:city":"Cowes",
    "sg:classifiers":[
        {
            "category":"Travel",
            "subcategory":"Hotels & Motels",
            "type":"Entertainment"
        }
    ],
    "sg:phone":"+44 1983 291334",
    "sg:postcode":"PO31 7JP",
    "sg:province":"Isle of Wight",
    "sg:tags":[
        "house",
        "guest"
    ],
    "wof:name":"Halcyone Villa",
    "wof:placetype":"venue"
},
  "geometry": {"coordinates":[-1.301794,50.756893],"type":"Point"}
}