{
  "type": "Feature",
  "properties": {
    "addr:full":"43 Sandgate High Street Folkestone Kent CT20 3AH",
    "addr:housenumber":"43",
    "addr:postcode":"ct20 3ah",
    "addr:street":"Sandgate High Street",
    "iso:country":"GB",
    "sg:address":"43 Sandgate High Street",
    "sg:city":"Folkestone",
    "sg:classifiers":[
        {
            "category":"Shopping",
            "subcategory":"Antiques",
            "type":"Retail Goods"
        }
    ],
    "sg:postcode":"CT20 3AH",
    "sg:province":"Kent",
    "wof:name":"Norden's",
    "wof:placetype":"venue"
},
  "geometry": {"coordinates":[1.1483900547,51.0740203857],"type":"Point"}
}