{
  "type": "Feature",
  "properties": {
    "addr:full":"5 Alexander Park Broxburn City of Edinburgh EH52 5RT",
    "addr:housenumber":"5",
    "addr:postcode":"eh52 5rt",
    "addr:street":"Alexander Park",
    "iso:country":"GB",
    "sg:address":"5 Alexander Park",
    "sg:city":"Broxburn",
    "sg:classifiers":[
        {
            "category":"Professional",
            "subcategory":"Art Services",
            "type":"Services"
        }
    ],
    "sg:phone":"+44 1506 854613",
    "sg:postcode":"EH52 5RT",
    "sg:province":"City of Edinburgh",
    "sg:tags":[
        "photographer"
    ],
    "wof:name":"Different Class Wedding Services",
    "wof:placetype":"venue"
},
  "geometry": {"coordinates":[-3.4690730572,55.9321937561],"type":"Point"}
}