{
  "type": "Feature",
  "properties": {
    "addr:full":"16 Meon Road, Oakley Basingstoke Hampshire RG23 7AL",
    "addr:housenumber":"16",
    "addr:postcode":"rg23 7al",
    "addr:street":"Meon Road",
    "iso:country":"GB",
    "sg:address":"16 Meon Road, Oakley",
    "sg:city":"Basingstoke",
    "sg:classifiers":[
        {
            "category":"Personal",
            "subcategory":"Beauty Salon",
            "type":"Services"
        }
    ],
    "sg:postcode":"RG23 7AL",
    "sg:province":"Hampshire",
    "sg:tags":[
        "unisex",
        "hairdresser"
    ],
    "wof:name":"Hair Beauty",
    "wof:placetype":"venue"
},
  "geometry": {"coordinates":[-1.1742810011,51.2492408752],"type":"Point"}
}