{
  "type": "Feature",
  "properties": {
    "addr:full":"49 Welbeck Street London Greater London W1G 9XN",
    "addr:housenumber":"49",
    "addr:postcode":"w1g 9xn",
    "addr:street":"Welbeck Street",
    "iso:country":"GB",
    "sg:address":"49 Welbeck Street",
    "sg:city":"London",
    "sg:classifiers":[
        {
            "category":"Real Estate",
            "subcategory":"Real Estate Operator",
            "type":"Services"
        }
    ],
    "sg:phone":"+44 20 7935 5573",
    "sg:postcode":"W1G 9XN",
    "sg:province":"Greater London",
    "sg:tags":[
        "letting",
        "agent"
    ],
    "wof:name":"Peterman Properties Ltd.",
    "wof:placetype":"venue"
},
  "geometry": {"coordinates":[-0.149553,51.517715],"type":"Point"}
}