{
  "type": "Feature",
  "properties": {
    "addr:full":"Main Road, Parson Drove Wisbech Cambridgeshire PE13 4LA",
    "addr:postcode":"pe13 4la",
    "addr:street":"Main Road",
    "iso:country":"GB",
    "sg:address":"Main Road, Parson Drove",
    "sg:city":"Wisbech",
    "sg:classifiers":[
        {
            "category":"Wholesale",
            "subcategory":"Vending Machines",
            "type":"Manufacturing & Wholesale Goods"
        }
    ],
    "sg:phone":"+44 1945 701545",
    "sg:postcode":"PE13 4LA",
    "sg:province":"Cambridgeshire",
    "sg:tags":[
        "sale"
    ],
    "wof:name":"Vendacup",
    "wof:placetype":"venue"
},
  "geometry": {"coordinates":[-0.0189270005,52.6167526245],"type":"Point"}
}