{
  "type": "Feature",
  "properties": {
    "iso:country":"GB",
    "sg:address":"192 Church Road, Astley",
    "sg:city":"Manchester",
    "sg:classifiers":[
        {
            "category":"Building & Trades",
            "subcategory":"Construction",
            "type":"Services"
        }
    ],
    "sg:postcode":"M29 7FS",
    "sg:province":"Greater Manchester",
    "sg:tags":[
        "builder"
    ],
    "wof:name":"Geoffrey Pennington",
    "wof:placetype":"venue"
},
  "geometry": {"coordinates":[-2.450964,53.504524],"type":"Point"}
}