{
  "type": "Feature",
  "properties": {
    "iso:country":"GB",
    "sg:address":"134a Virginia Street",
    "sg:city":"Southport",
    "sg:classifiers":[
        {
            "category":"Professional",
            "subcategory":"Engineering",
            "type":"Services"
        }
    ],
    "sg:phone":"+44 1704 534668",
    "sg:postcode":"PR8 6SP",
    "sg:province":"Lancashire",
    "sg:tags":[
        "precision",
        "engineer"
    ],
    "wof:name":"Hargood Engineers Ltd.",
    "wof:placetype":"venue"
},
  "geometry": {"coordinates":[-2.993285,53.643246],"type":"Point"}
}