{
  "type": "Feature",
  "properties": {
    "addr:full":"11 Mocha Parade Salford Greater Manchester M7 1QE",
    "addr:housenumber":"11",
    "addr:postcode":"m7 1qe",
    "addr:street":"Mocha Parade",
    "iso:country":"GB",
    "sg:address":"11 Mocha Parade",
    "sg:city":"Salford",
    "sg:classifiers":[
        {
            "category":"Food & Beverages",
            "subcategory":"Liquor & Beverages",
            "type":"Retail Goods"
        }
    ],
    "sg:phone":"+44 161 834 5894",
    "sg:postcode":"M7 1QE",
    "sg:province":"Greater Manchester",
    "sg:tags":[
        "beer",
        "spirit",
        "wines"
    ],
    "wof:name":"Whitbread Group Plc",
    "wof:placetype":"venue"
},
  "geometry": {"coordinates":[-2.261246,53.491318],"type":"Point"}
}