{
  "type": "Feature",
  "properties": {
    "addr:full":"20 The Grove Ilkley North Yorkshire LS29 9EG",
    "addr:housenumber":"20",
    "addr:postcode":"ls29 9eg",
    "addr:street":"The Grove",
    "iso:country":"GB",
    "sg:address":"20 The Grove",
    "sg:city":"Ilkley",
    "sg:classifiers":[
        {
            "category":"Professional",
            "subcategory":"Lawyer & Legal Services",
            "type":"Services"
        }
    ],
    "sg:phone":"+44 1943 603545",
    "sg:postcode":"LS29 9EG",
    "sg:province":"North Yorkshire",
    "sg:tags":[
        "solicitor"
    ],
    "wof:name":"Barret Chamberlain",
    "wof:placetype":"venue"
},
  "geometry": {"coordinates":[-1.8247230053,53.9246635437],"type":"Point"}
}