{
  "type": "Feature",
  "properties": {
    "addr:full":"67 Conway Road, Carlton Nottingham Nottinghamshire NG4 2PW",
    "addr:housenumber":"67",
    "addr:postcode":"ng4 2pw",
    "addr:street":"Conway Road",
    "iso:country":"GB",
    "sg:address":"67 Conway Road, Carlton",
    "sg:city":"Nottingham",
    "sg:classifiers":[
        {
            "category":"Building & Trades",
            "subcategory":"Cleaning & Sanitation",
            "type":"Services"
        }
    ],
    "sg:postcode":"NG4 2PW",
    "sg:province":"Nottinghamshire",
    "sg:tags":[
        "cleaner",
        "window"
    ],
    "wof:name":"Kirk Contracts",
    "wof:placetype":"venue"
},
  "geometry": {"coordinates":[-1.074967,52.97007],"type":"Point"}
}