{
  "type": "Feature",
  "properties": {
    "addr:full":"45-53 Union St Glasgow East Dunbartonshire G66 1DN",
    "addr:housenumber":"45-53",
    "addr:postcode":"g66 1dn",
    "addr:street":"Union St",
    "iso:country":"GB",
    "sg:address":"45-53 Union St",
    "sg:city":"Glasgow",
    "sg:classifiers":[
        {
            "category":"Health Services",
            "subcategory":"Doctor",
            "type":"Services"
        }
    ],
    "sg:phone":"+44 141 211 8270",
    "sg:postcode":"G66 1DN",
    "sg:province":"East Dunbartonshire",
    "sg:tags":[
        "practitioners"
    ],
    "wof:name":"Sutherland, M",
    "wof:placetype":"venue"
},
  "geometry": {"coordinates":[-4.1596179008,55.9393882751],"type":"Point"}
}