{
  "type": "Feature",
  "properties": {
    "iso:country":"GB",
    "sg:address":"24 Petworth Road",
    "sg:city":"Haslemere",
    "sg:classifiers":[
        {
            "category":"Professional",
            "subcategory":"Management & Consulting",
            "type":"Services"
        }
    ],
    "sg:postcode":"GU27 2HR",
    "sg:province":"Hampshire",
    "sg:tags":[
        "consultant",
        "business"
    ],
    "wof:name":"Acn Ltd",
    "wof:placetype":"venue"
},
  "geometry": {"coordinates":[-0.7081180215,51.0868377686],"type":"Point"}
}