{
  "type": "Feature",
  "properties": {
    "addr:full":"99 Lumley Road Skegness Lincolnshire PE25 3LZ",
    "addr:housenumber":"99",
    "addr:postcode":"pe25 3lz",
    "addr:street":"Lumley Road",
    "iso:country":"GB",
    "sg:address":"99 Lumley Road",
    "sg:city":"Skegness",
    "sg:classifiers":[
        {
            "category":"Shopping",
            "subcategory":"Clothing, Apparel, & Fashions",
            "type":"Retail Goods"
        },
        {
            "category":"Shopping",
            "subcategory":"Baby Store",
            "type":"Retail Goods"
        }
    ],
    "sg:phone":"+44 1754 763278",
    "sg:postcode":"PE25 3LZ",
    "sg:province":"Lincolnshire",
    "sg:tags":[
        "child",
        "childrens",
        "babywear"
    ],
    "wof:name":"R Lowndes",
    "wof:placetype":"venue"
},
  "geometry": {"coordinates":[0.3419960141,53.1424713135],"type":"Point"}
}