{
  "type": "Feature",
  "properties": {
    "iso:country":"GB",
    "sg:address":"College Road",
    "sg:city":"Eastbourne",
    "sg:classifiers":[
        {
            "category":"Community Center",
            "type":"Public Place"
        }
    ],
    "sg:postcode":"BN21 4JJ",
    "sg:province":"East Sussex",
    "sg:tags":[
        "recreation",
        "leisure",
        "centre"
    ],
    "wof:name":"Devonshire Park Fitness Centre",
    "wof:placetype":"venue"
},
  "geometry": {"coordinates":[0.281142,50.76569],"type":"Point"}
}