{
  "type": "Feature",
  "properties": {
    "addr:full":"11 Lodge Court, Staining Blackpool Lancashire FY3 0EH",
    "addr:housenumber":"11",
    "addr:postcode":"fy3 0eh",
    "addr:street":"Lodge Court",
    "iso:country":"GB",
    "sg:address":"11 Lodge Court, Staining",
    "sg:city":"Blackpool",
    "sg:classifiers":[
        {
            "category":"Building & Trades",
            "subcategory":"Construction",
            "type":"Services"
        }
    ],
    "sg:phone":"+44 1253 896744",
    "sg:postcode":"FY3 0EH",
    "sg:province":"Lancashire",
    "sg:tags":[
        "builder"
    ],
    "wof:name":"Wainhomes Ltd",
    "wof:placetype":"venue"
},
  "geometry": {"coordinates":[-2.993684,53.816376],"type":"Point"}
}