{
  "type": "Feature",
  "properties": {
    "iso:country":"GB",
    "sg:address":"Marwood Grange, Marwood",
    "sg:city":"Barnard Castle",
    "sg:classifiers":[
        {
            "category":"Farming",
            "subcategory":"Livestock Farm",
            "type":"Manufacturing & Wholesale Goods"
        }
    ],
    "sg:postcode":"DL12 8SA",
    "sg:province":"Cumbria",
    "sg:tags":[
        "others"
    ],
    "wof:name":"David A & A M Gill",
    "wof:placetype":"venue"
},
  "geometry": {"coordinates":[-1.9238090515,54.5431518555],"type":"Point"}
}