{
  "type": "Feature",
  "properties": {
    "addr:full":"Crown Works, Staincliffe Road Dewsbury West Yorkshire WF13 4SB",
    "addr:postcode":"wf13 4sb",
    "addr:street":"Staincliffe Road",
    "iso:country":"GB",
    "sg:address":"Crown Works, Staincliffe Road",
    "sg:city":"Dewsbury",
    "sg:classifiers":[
        {
            "category":"Professional",
            "type":"Services"
        },
        {
            "category":"Organizations",
            "subcategory":"Non-profit Organization",
            "type":"Services"
        }
    ],
    "sg:phone":"+44 1924 468191",
    "sg:postcode":"WF13 4SB",
    "sg:province":"West Yorkshire",
    "sg:tags":[
        "services",
        "belt",
        "system",
        "conveyor"
    ],
    "sg:website":"http://www.diepress-richardson.co.uk",
    "wof:name":"R S Richardson Belting Co. Ltd.",
    "wof:placetype":"venue"
},
  "geometry": {"coordinates":[-1.653799,53.7066],"type":"Point"}
}