{
  "type": "Feature",
  "properties": {
    "iso:country":"GB",
    "sg:address":"5-9 Fairfield Road",
    "sg:city":"Dundee",
    "sg:classifiers":[
        {
            "category":"Building & Trades",
            "subcategory":"Construction",
            "type":"Services"
        }
    ],
    "sg:phone":"+44 1382 815415",
    "sg:postcode":"DD3 8HR",
    "sg:province":"Dundee City",
    "sg:tags":[
        "builder"
    ],
    "wof:name":"George Martin (Builders) Ltd.",
    "wof:placetype":"venue"
},
  "geometry": {"coordinates":[-2.979644,56.478535],"type":"Point"}
}