{
  "type": "Feature",
  "properties": {
    "addr:full":"Windmill Garage, Pembroke Road Ruislip Greater London HA4 8NN",
    "addr:postcode":"ha4 8nn",
    "addr:street":"Pembroke Road",
    "iso:country":"GB",
    "sg:address":"Windmill Garage, Pembroke Road",
    "sg:city":"Ruislip",
    "sg:classifiers":[
        {
            "category":"Autos & Motor Vehicles",
            "subcategory":"Auto Supplies",
            "type":"Retail Goods"
        }
    ],
    "sg:phone":"+44 1895 623443",
    "sg:postcode":"HA4 8NN",
    "sg:province":"Greater London",
    "sg:tags":[
        "exhaust",
        "absorber",
        "shock"
    ],
    "wof:name":"Kwik-Fit (G B) Ltd.",
    "wof:placetype":"venue"
},
  "geometry": {"coordinates":[-0.4140639901,51.5747032166],"type":"Point"}
}