{
  "type": "Feature",
  "properties": {
    "addr:full":"360 Nottingham Road Ilkeston Derbyshire DE7 5BN",
    "addr:housenumber":"360",
    "addr:postcode":"de7 5bn",
    "addr:street":"Nottingham Road",
    "iso:country":"GB",
    "sg:address":"360 Nottingham Road",
    "sg:city":"Ilkeston",
    "sg:classifiers":[
        {
            "category":"Retail",
            "subcategory":"Repair Shop",
            "type":"Services"
        }
    ],
    "sg:phone":"+44 115 930 7017",
    "sg:postcode":"DE7 5BN",
    "sg:province":"Derbyshire",
    "sg:tags":[
        "upholsterer"
    ],
    "wof:name":"S C Webb Upholstery",
    "wof:placetype":"venue"
},
  "geometry": {"coordinates":[-1.29345,52.960587],"type":"Point"}
}