{
  "type": "Feature",
  "properties": {
    "addr:full":"11 Dawley Ride, Colnbrook Slough Berkshire SL3 0QE",
    "addr:housenumber":"11",
    "addr:postcode":"sl3 0qe",
    "addr:street":"Dawley Ride",
    "iso:country":"GB",
    "sg:address":"11 Dawley Ride, Colnbrook",
    "sg:city":"Slough",
    "sg:classifiers":[
        {
            "category":"Professional",
            "subcategory":"Accounting & Tax Preparation",
            "type":"Services"
        }
    ],
    "sg:phone":"+44 1753 684195",
    "sg:postcode":"SL3 0QE",
    "sg:province":"Berkshire",
    "sg:tags":[
        "accountant"
    ],
    "wof:name":"John Callow Book-Keeper",
    "wof:placetype":"venue"
},
  "geometry": {"coordinates":[-0.514894,51.481197],"type":"Point"}
}