{
  "type": "Feature",
  "properties": {
    "addr:full":"10 Sherbrook Avenue, Daybrook Nottingham Nottinghamshire NG5 6AN",
    "addr:housenumber":"10",
    "addr:postcode":"ng5 6an",
    "addr:street":"Sherbrook Avenue",
    "iso:country":"GB",
    "sg:address":"10 Sherbrook Avenue, Daybrook",
    "sg:city":"Nottingham",
    "sg:classifiers":[
        {
            "category":"Shopping",
            "subcategory":"Computers & Home Electronics",
            "type":"Retail Goods"
        }
    ],
    "sg:postcode":"NG5 6AN",
    "sg:province":"Nottinghamshire",
    "sg:tags":[
        "equipment",
        "radio"
    ],
    "wof:name":"In Touch Electronics",
    "wof:placetype":"venue"
},
  "geometry": {"coordinates":[-1.141362,52.996922],"type":"Point"}
}