{
  "type": "Feature",
  "properties": {
    "iso:country":"GB",
    "sg:address":"North Holme, Main St",
    "sg:city":"Brigg",
    "sg:classifiers":[
        {
            "category":"Wholesale",
            "subcategory":"Machinery & Supplies",
            "type":"Manufacturing & Wholesale Goods"
        }
    ],
    "sg:phone":"+44 1652 618887",
    "sg:postcode":"DN20 0PY",
    "sg:province":"Lincolnshire",
    "wof:name":"Nick Young",
    "wof:placetype":"venue"
},
  "geometry": {"coordinates":[-0.484879,53.552986],"type":"Point"}
}