{
  "type": "Feature",
  "properties": {
    "iso:country":"GB",
    "sg:address":"115 Muirend Rd",
    "sg:city":"Glasgow",
    "sg:classifiers":[
        {
            "category":"Health Services",
            "subcategory":"Doctor",
            "type":"Services"
        }
    ],
    "sg:phone":"+44 141 637 4877",
    "sg:postcode":"G44 3EX",
    "sg:province":"East Renfrewshire",
    "sg:tags":[
        "practitioners"
    ],
    "wof:name":"Kelly, J L",
    "wof:placetype":"venue"
},
  "geometry": {"coordinates":[-4.2774977684,55.8109130859],"type":"Point"}
}