{
  "type": "Feature",
  "properties": {
    "addr:full":"Buckenham House, 81 High Street Southwold Suffolk IP18 6DS",
    "addr:housenumber":"81",
    "addr:postcode":"ip18 6ds",
    "addr:street":"High Street",
    "iso:country":"GB",
    "sg:address":"Buckenham House, 81 High Street",
    "sg:city":"Southwold",
    "sg:classifiers":[
        {
            "category":"Arts & Performance",
            "subcategory":"Art Gallery",
            "type":"Entertainment"
        },
        {
            "category":"Cafe",
            "type":"Food & Drink"
        }
    ],
    "sg:phone":"+44 1502 723273",
    "sg:postcode":"IP18 6DS",
    "sg:province":"Suffolk",
    "sg:tags":[
        "tea",
        "snack",
        "bar",
        "room"
    ],
    "wof:name":"Buckenham Coffee House",
    "wof:placetype":"venue"
},
  "geometry": {"coordinates":[1.678804,52.326275],"type":"Point"}
}