{
  "type": "Feature",
  "properties": {
    "iso:country":"GB",
    "sg:address":"14 All Saints Grn",
    "sg:city":"Norwich",
    "sg:classifiers":[
        {
            "category":"Personal",
            "subcategory":"Beauty Salon",
            "type":"Services"
        }
    ],
    "sg:postcode":"NR1 3NA",
    "sg:province":"Norfolk",
    "sg:tags":[
        "unisex",
        "hairdresser"
    ],
    "wof:name":"Clever Dicks Hair Saloon",
    "wof:placetype":"venue"
},
  "geometry": {"coordinates":[1.29532,52.625286],"type":"Point"}
}