{
  "type": "Feature",
  "properties": {
    "iso:country":"GB",
    "sg:address":"Prep Dept, Sandford Ho, 55-57 Liverpool Rd",
    "sg:city":"Chester",
    "sg:classifiers":[
        {
            "category":"Education",
            "subcategory":"School",
            "type":"Public Place"
        }
    ],
    "sg:phone":"+44 1244 373793",
    "sg:postcode":"CH2 1AW",
    "sg:province":"Cheshire",
    "sg:tags":[
        "independent",
        "preparatory"
    ],
    "wof:name":"Queen's School The",
    "wof:placetype":"venue"
},
  "geometry": {"coordinates":[-2.89446,53.206982],"type":"Point"}
}