{
  "type": "Feature",
  "properties": {
    "addr:full":"5 Lowfield La Hoddesdon Essex EN11 8PD",
    "addr:housenumber":"5",
    "addr:postcode":"en11 8pd",
    "addr:street":"Lowfield La Hoddesdon",
    "iso:country":"GB",
    "sg:address":"5 Lowfield La",
    "sg:city":"Hoddesdon",
    "sg:classifiers":[
        {
            "category":"Professional",
            "subcategory":"Accounting & Tax Preparation",
            "type":"Services"
        },
        {
            "category":"Banks & Credit Unions",
            "subcategory":"Financial Services",
            "type":"Services"
        }
    ],
    "sg:postcode":"EN11 8PD",
    "sg:province":"Essex",
    "sg:tags":[
        "consultant",
        "accountant"
    ],
    "wof:name":"Cutler,Michael,",
    "wof:placetype":"venue"
},
  "geometry": {"coordinates":[-0.013237,51.758957],"type":"Point"}
}