{
  "type": "Feature",
  "properties": {
    "addr:full":"The Offas Dyke Centre, West Street Knighton Shropshire LD7 1EN",
    "addr:postcode":"ld7 1en",
    "addr:street":"West Street",
    "iso:country":"GB",
    "sg:address":"The Offas Dyke Centre, West Street",
    "sg:city":"Knighton",
    "sg:classifiers":[
        {
            "category":"Government",
            "subcategory":"Office",
            "type":"Public Place"
        },
        {
            "category":"Landmark",
            "subcategory":"Tourist Information",
            "type":"Public Place"
        }
    ],
    "sg:phone":"+44 1547 528753",
    "sg:postcode":"LD7 1EN",
    "sg:province":"Shropshire",
    "sg:tags":[
        "local"
    ],
    "wof:name":"Tourist Information Centre",
    "wof:placetype":"venue"
},
  "geometry": {"coordinates":[-3.04771,52.343067],"type":"Point"}
}