{
  "type": "Feature",
  "properties": {
    "addr:full":"Oldmedow Road King's Lynn Norfolk PE30 4JJ",
    "addr:postcode":"pe30 4jj",
    "addr:street":"Oldmedow Road",
    "iso:country":"GB",
    "sg:address":"Oldmedow Road",
    "sg:city":"King's Lynn",
    "sg:classifiers":[
        {
            "category":"Manufacturing",
            "subcategory":"Paper Products",
            "type":"Manufacturing & Wholesale Goods"
        }
    ],
    "sg:phone":"+44 1553 776607",
    "sg:postcode":"PE30 4JJ",
    "sg:province":"Norfolk",
    "sg:tags":[
        "material",
        "drawing",
        "writing"
    ],
    "wof:name":"Prodir Ltd.",
    "wof:placetype":"venue"
},
  "geometry": {"coordinates":[0.4126699865,52.7423210144],"type":"Point"}
}