{
  "type": "Feature",
  "properties": {
    "addr:full":"90 Empingham Rd Stamford Cambridgeshire PE9 2RJ",
    "addr:housenumber":"90",
    "addr:postcode":"pe9 2rj",
    "addr:street":"Empingham Rd",
    "iso:country":"GB",
    "sg:address":"90 Empingham Rd",
    "sg:city":"Stamford",
    "sg:classifiers":[
        {
            "category":"Retail",
            "subcategory":"Storage",
            "type":"Services"
        }
    ],
    "sg:phone":"+44 1780 766051",
    "sg:postcode":"PE9 2RJ",
    "sg:province":"Cambridgeshire",
    "sg:tags":[
        "household",
        "removal"
    ],
    "wof:name":"Pegasus Removals",
    "wof:placetype":"venue"
},
  "geometry": {"coordinates":[-0.492864,52.653206],"type":"Point"}
}