{
  "type": "Feature",
  "properties": {
    "iso:country":"GB",
    "sg:address":"Nr Thirsk",
    "sg:city":"York",
    "sg:classifiers":[
        {
            "category":"Bars & Pubs",
            "type":"Food & Drink"
        }
    ],
    "sg:phone":"+44 1845 597271",
    "sg:postcode":"YO7 2PR",
    "sg:province":"North Yorkshire",
    "sg:tags":[
        "pubs",
        "inn"
    ],
    "wof:name":"The Whitestonecliffe Inn",
    "wof:placetype":"venue"
},
  "geometry": {"coordinates":[-1.2556600571,54.2363815308],"type":"Point"}
}