{
  "type": "Feature",
  "properties": {
    "iso:country":"GB",
    "sg:address":"14 East Street",
    "sg:city":"Havant",
    "sg:classifiers":[
        {
            "category":"Retail",
            "subcategory":"Portrait Studio",
            "type":"Services"
        }
    ],
    "sg:phone":"+44 23 9245 5255",
    "sg:postcode":"PO9 1AQ",
    "sg:province":"Hampshire",
    "sg:tags":[
        "photographic"
    ],
    "wof:name":"Olan Mills Inc",
    "wof:placetype":"venue"
},
  "geometry": {"coordinates":[-0.980845,50.851032],"type":"Point"}
}