{
  "type": "Feature",
  "properties": {
    "iso:country":"GB",
    "sg:address":"15 Oakfield House",
    "sg:city":"Altrincham",
    "sg:classifiers":[
        {
            "category":"Real Estate",
            "subcategory":"Surveying",
            "type":"Services"
        }
    ],
    "sg:postcode":"WA15 8EW",
    "sg:province":"Cheshire",
    "sg:tags":[
        "surveyor",
        "valuer"
    ],
    "wof:name":"Berkeley Brown Residential Ltd.",
    "wof:placetype":"venue"
},
  "geometry": {"coordinates":[-2.345147,53.389874],"type":"Point"}
}