{
  "type": "Feature",
  "properties": {
    "addr:full":"Unit 1-4 Acrow Site, Road 2 Hoobrook Industrial Estate, Off Worcester Road Kidderminster Staffordshire DY10 1HY",
    "addr:housenumber":"unit 1-4;estate",
    "addr:postcode":"dy10 1hy",
    "addr:street":"Site Road 2 Hoobrook Industrial;Off Worcester Road",
    "iso:country":"GB",
    "sg:address":"Unit 1-4 Acrow Site, Road 2 Hoobrook Industrial Estate, Off Worcester Road",
    "sg:city":"Kidderminster",
    "sg:classifiers":[
        {
            "category":"Utilities",
            "subcategory":"Refuse",
            "type":"Services"
        }
    ],
    "sg:phone":"+44 1562 752771",
    "sg:postcode":"DY10 1HY",
    "sg:province":"Staffordshire",
    "sg:tags":[
        "skip",
        "hire"
    ],
    "wof:name":"Lawrence Skip Hire",
    "wof:placetype":"venue"
},
  "geometry": {"coordinates":[-2.249084,52.388111],"type":"Point"}
}