{
  "type": "Feature",
  "properties": {
    "addr:full":"123 Station Rd Leicester Leicestershire LE3 8GS",
    "addr:housenumber":"123",
    "addr:postcode":"le3 8gs",
    "addr:street":"Station Rd",
    "iso:country":"GB",
    "sg:address":"123 Station Rd",
    "sg:city":"Leicester",
    "sg:classifiers":[
        {
            "category":"Health Services",
            "subcategory":"Health Practitioner",
            "type":"Services"
        }
    ],
    "sg:phone":"+44 116 287 1992",
    "sg:postcode":"LE3 8GS",
    "sg:province":"Leicestershire",
    "sg:tags":[
        "acupuncture"
    ],
    "wof:name":"Josephine Smith",
    "wof:placetype":"venue"
},
  "geometry": {"coordinates":[-1.195177,52.656658],"type":"Point"}
}