{
  "type": "Feature",
  "properties": {
    "addr:full":"Care Of Black & Decker, Green La Spennymoor Durham DL16 6JG",
    "addr:postcode":"dl16 6jg",
    "addr:street":"Green",
    "iso:country":"GB",
    "sg:address":"Care Of Black & Decker, Green La",
    "sg:city":"Spennymoor",
    "sg:classifiers":[
        {
            "category":"Professional",
            "subcategory":"Business Services",
            "type":"Services"
        }
    ],
    "sg:phone":"+44 1388 815002",
    "sg:postcode":"DL16 6JG",
    "sg:province":"Durham",
    "sg:tags":[
        "distribution"
    ],
    "wof:name":"Tibbett & Britten Consumer Products Group",
    "wof:placetype":"venue"
},
  "geometry": {"coordinates":[-1.5708899498,54.7061386108],"type":"Point"}
}