{
  "type": "Feature",
  "properties": {
    "iso:country":"GB",
    "sg:address":"Woodcote Gro, Ashley Rd",
    "sg:city":"Epsom",
    "sg:classifiers":[
        {
            "category":"Building & Trades",
            "subcategory":"Cleaning & Sanitation",
            "type":"Services"
        }
    ],
    "sg:phone":"+44 1372 741536",
    "sg:postcode":"KT18 5BW",
    "sg:province":"Surrey",
    "sg:tags":[
        "commercial"
    ],
    "wof:name":"Pall Mall Group Services Ltd",
    "wof:placetype":"venue"
},
  "geometry": {"coordinates":[-0.24252,51.31488],"type":"Point"}
}