{
  "type": "Feature",
  "properties": {
    "addr:full":"202 Moseley Road Birmingham West Midlands B12 0DJ",
    "addr:housenumber":"202",
    "addr:postcode":"b12 0dj",
    "addr:street":"Moseley Road",
    "iso:country":"GB",
    "sg:address":"202 Moseley Road",
    "sg:city":"Birmingham",
    "sg:classifiers":[
        {
            "category":"Autos & Motor Vehicles",
            "subcategory":"Auto Supplies",
            "type":"Retail Goods"
        }
    ],
    "sg:phone":"+44 121 440 1360",
    "sg:postcode":"B12 0DJ",
    "sg:province":"West Midlands",
    "sg:tags":[
        "exhaust",
        "absorber",
        "shock"
    ],
    "wof:name":"Mr Gollys",
    "wof:placetype":"venue"
},
  "geometry": {"coordinates":[-1.882555,52.466152],"type":"Point"}
}