{
  "type": "Feature",
  "properties": {
    "iso:country":"GB",
    "sg:address":"2 Richmond Hill",
    "sg:city":"Wigan",
    "sg:classifiers":[
        {
            "category":"Professional",
            "subcategory":"Engineering",
            "type":"Services"
        }
    ],
    "sg:phone":"+44 1942 213084",
    "sg:postcode":"WN5 8AD",
    "sg:province":"Lancashire",
    "wof:name":"Grimes Engineering",
    "wof:placetype":"venue"
},
  "geometry": {"coordinates":[-2.680634,53.536228],"type":"Point"}
}