{
  "type": "Feature",
  "properties": {
    "addr:full":"6 St. Pauls St Walsall West Midlands WS1 1NR",
    "addr:housenumber":"6",
    "addr:postcode":"ws1 1nr",
    "addr:street":"St. Pauls St",
    "iso:country":"GB",
    "sg:address":"6 St. Pauls St",
    "sg:city":"Walsall",
    "sg:classifiers":[
        {
            "category":"Professional",
            "subcategory":"Computer Services",
            "type":"Services"
        }
    ],
    "sg:phone":"+44 1922 633970",
    "sg:postcode":"WS1 1NR",
    "sg:province":"West Midlands",
    "sg:tags":[
        "information"
    ],
    "wof:name":"Community Health Council",
    "wof:placetype":"venue"
},
  "geometry": {"coordinates":[-1.9822330475,52.5852584839],"type":"Point"}
}