{
  "type": "Feature",
  "properties": {
    "addr:full":"53 Bynes Rd South Croydon Surrey CR2 0PZ",
    "addr:housenumber":"53",
    "addr:postcode":"cr2 0pz",
    "addr:street":"Bynes Rd",
    "iso:country":"GB",
    "sg:address":"53 Bynes Rd",
    "sg:city":"South Croydon",
    "sg:classifiers":[
        {
            "category":"Building & Trades",
            "subcategory":"Construction",
            "type":"Services"
        }
    ],
    "sg:phone":"+44 20 8680 2444",
    "sg:postcode":"CR2 0PZ",
    "sg:province":"Surrey",
    "sg:tags":[
        "builder"
    ],
    "wof:name":"J Simmons",
    "wof:placetype":"venue"
},
  "geometry": {"coordinates":[-0.0952230021,51.3537139893],"type":"Point"}
}