{
  "type": "Feature",
  "properties": {
    "iso:country":"GB",
    "sg:address":"91 Hill Road",
    "sg:city":"Clevedon",
    "sg:classifiers":[
        {
            "category":"Fast Food",
            "type":"Food & Drink"
        }
    ],
    "sg:postcode":"BS21 7PN",
    "sg:province":"Somerset",
    "sg:tags":[
        "delivery"
    ],
    "wof:name":"Olive Garden Pizzas",
    "wof:placetype":"venue"
},
  "geometry": {"coordinates":[-2.8581769466,51.4436073303],"type":"Point"}
}