{
  "type": "Feature",
  "properties": {
    "addr:full":"Upstairs, Sayers Sq Tenterden Kent TN30 6BW",
    "addr:postcode":"tn30 6bw",
    "addr:street":"Sq",
    "iso:country":"GB",
    "sg:address":"Upstairs, Sayers Sq",
    "sg:city":"Tenterden",
    "sg:classifiers":[
        {
            "category":"Shopping",
            "subcategory":"Clothing, Apparel, & Fashions",
            "type":"Retail Goods"
        }
    ],
    "sg:postcode":"TN30 6BW",
    "sg:province":"Kent",
    "sg:tags":[
        "dresswear"
    ],
    "wof:name":"Top Room (The)",
    "wof:placetype":"venue"
},
  "geometry": {"coordinates":[0.69406,51.075405],"type":"Point"}
}