{
  "type": "Feature",
  "properties": {
    "iso:country":"GB",
    "sg:address":"51/53 High Street",
    "sg:city":"Burnham-on-crouch",
    "sg:classifiers":[
        {
            "category":"Shopping",
            "subcategory":"Clothing, Apparel, & Fashions",
            "type":"Retail Goods"
        }
    ],
    "sg:phone":"+44 1621 782462",
    "sg:postcode":"CM0 8AG",
    "sg:province":"Essex",
    "sg:tags":[
        "menswear"
    ],
    "wof:name":"Harold H  Clarke",
    "wof:placetype":"venue"
},
  "geometry": {"coordinates":[0.818523,51.625175],"type":"Point"}
}