{
  "type": "Feature",
  "properties": {
    "addr:full":"3 Blair Pde, Moredon Rd Swindon Wiltshire SN25 3DE",
    "addr:housenumber":"3",
    "addr:postcode":"sn25 3de",
    "addr:street":"Blair Pde Moredon Rd",
    "iso:country":"GB",
    "sg:address":"3 Blair Pde, Moredon Rd",
    "sg:city":"Swindon",
    "sg:classifiers":[
        {
            "category":"Professional",
            "subcategory":"Business Services",
            "type":"Services"
        }
    ],
    "sg:phone":"+44 1793 521624",
    "sg:postcode":"SN25 3DE",
    "sg:province":"Wiltshire",
    "sg:tags":[
        "bookmaker"
    ],
    "wof:name":"Graham,Chris,Racing",
    "wof:placetype":"venue"
},
  "geometry": {"coordinates":[-1.7995890379,51.5830917358],"type":"Point"}
}