{
  "type": "Feature",
  "properties": {
    "addr:full":"High Street, Cilgerran Cardigan Ceredigion SA43 2SQ",
    "addr:postcode":"sa43 2sq",
    "addr:street":"High Street",
    "iso:country":"GB",
    "sg:address":"High Street, Cilgerran",
    "sg:city":"Cardigan",
    "sg:classifiers":[
        {
            "category":"Bars & Pubs",
            "type":"Food & Drink"
        }
    ],
    "sg:phone":"+44 1239 614600",
    "sg:postcode":"SA43 2SQ",
    "sg:province":"Ceredigion",
    "sg:tags":[
        "pubs",
        "inn"
    ],
    "wof:name":"Cardiff Arms",
    "wof:placetype":"venue"
},
  "geometry": {"coordinates":[-4.6339640617,52.0555763245],"type":"Point"}
}