{
  "type": "Feature",
  "properties": {
    "addr:full":"312-314 Green Lane Road Leicester Leicestershire LE5 4PB",
    "addr:housenumber":"312-314",
    "addr:postcode":"le5 4pb",
    "addr:street":"Green Lane Road",
    "iso:country":"GB",
    "sg:address":"312-314 Green Lane Road",
    "sg:city":"Leicester",
    "sg:classifiers":[
        {
            "category":"Retail",
            "subcategory":"Auto Repair",
            "type":"Services"
        }
    ],
    "sg:postcode":"LE5 4PB",
    "sg:province":"Leicestershire",
    "sg:tags":[
        "engine",
        "car",
        "specialist"
    ],
    "wof:name":"Shree Autos",
    "wof:placetype":"venue"
},
  "geometry": {"coordinates":[-1.0913610458,52.6378097534],"type":"Point"}
}