{
  "type": "Feature",
  "properties": {
    "iso:country":"GB",
    "sg:address":"3a Walpole Mews, Walpole Road",
    "sg:city":"London",
    "sg:classifiers":[
        {
            "category":"Professional",
            "subcategory":"Printing & Photocopies",
            "type":"Services"
        }
    ],
    "sg:postcode":"SW19 2DL",
    "sg:province":"Greater London",
    "sg:tags":[
        "plate",
        "lithographic",
        "maker"
    ],
    "wof:name":"Richard Harden (Printing)",
    "wof:placetype":"venue"
},
  "geometry": {"coordinates":[-0.1757380068,51.4210090637],"type":"Point"}
}