{
  "type": "Feature",
  "properties": {
    "addr:full":"The Music Centre, Borough Road Darlington Durham DL1 1SG",
    "addr:postcode":"dl1 1sg",
    "addr:street":"Borough Road",
    "iso:country":"GB",
    "sg:address":"The Music Centre, Borough Road",
    "sg:city":"Darlington",
    "sg:classifiers":[
        {
            "category":"Education",
            "subcategory":"School",
            "type":"Public Place"
        },
        {
            "category":"Government",
            "subcategory":"Office",
            "type":"Public Place"
        }
    ],
    "sg:phone":"+44 1325 380757",
    "sg:postcode":"DL1 1SG",
    "sg:province":"Durham",
    "sg:tags":[
        "local",
        "authority"
    ],
    "wof:name":"Durham County Council",
    "wof:placetype":"venue"
},
  "geometry": {"coordinates":[-1.5488940477,54.5245018005],"type":"Point"}
}