{
  "type": "Feature",
  "properties": {
    "iso:country":"GB",
    "sg:address":"Wilmington",
    "sg:city":"Polegate",
    "sg:classifiers":[
        {
            "category":"Autos & Motor Vehicles",
            "subcategory":"Automobile Sales",
            "type":"Retail Goods"
        }
    ],
    "sg:phone":"+44 1323 483869",
    "sg:postcode":"BN26 6RL",
    "sg:province":"East Sussex",
    "sg:tags":[
        "commercial"
    ],
    "wof:name":"Southern Commercial Sales",
    "wof:placetype":"venue"
},
  "geometry": {"coordinates":[0.2441229969,50.8213386536],"type":"Point"}
}