{
  "type": "Feature",
  "properties": {
    "iso:country":"GB",
    "sg:address":"Unit C 4 Hayland Street",
    "sg:city":"Sheffield",
    "sg:classifiers":[
        {
            "category":"Insurance",
            "subcategory":"Insurance Agent",
            "type":"Services"
        }
    ],
    "sg:phone":"+44 114 263 7700",
    "sg:postcode":"S9 1BY",
    "sg:province":"South Yorkshire",
    "wof:name":"Britannic Assurance Plc",
    "wof:placetype":"venue"
},
  "geometry": {"coordinates":[-1.419080019,53.4120101929],"type":"Point"}
}