{
  "type": "Feature",
  "properties": {
    "addr:full":"3 Market Place, Bolsover Chesterfield Derbyshire S44 6PN",
    "addr:housenumber":"3",
    "addr:postcode":"s44 6pn",
    "addr:street":"Market Place",
    "iso:country":"GB",
    "sg:address":"3 Market Place, Bolsover",
    "sg:city":"Chesterfield",
    "sg:classifiers":[
        {
            "category":"Shopping",
            "subcategory":"Baby Store",
            "type":"Retail Goods"
        }
    ],
    "sg:postcode":"S44 6PN",
    "sg:province":"Derbyshire",
    "sg:tags":[
        "babywear",
        "childrens"
    ],
    "wof:name":"Yvonne Clarke",
    "wof:placetype":"venue"
},
  "geometry": {"coordinates":[-1.292269,53.229477],"type":"Point"}
}