{
  "type": "Feature",
  "properties": {
    "addr:full":"Daventry Nature Works Daventry Northamptonshire NN11 4HU",
    "addr:postcode":"nn11 4hu",
    "iso:country":"GB",
    "sg:address":"Daventry Nature Works",
    "sg:city":"Daventry",
    "sg:classifiers":[
        {
            "category":"Health Services",
            "subcategory":"Health Practitioner",
            "type":"Services"
        }
    ],
    "sg:phone":"+44 1327 311507",
    "sg:postcode":"NN11 4HU",
    "sg:province":"Northamptonshire",
    "sg:tags":[
        "acupuncture"
    ],
    "wof:name":"J E Bellingham",
    "wof:placetype":"venue"
},
  "geometry": {"coordinates":[-1.1622389555,52.260433197],"type":"Point"}
}