{
  "type": "Feature",
  "properties": {
    "addr:full":"Treroosel Road, St Teath Bodmin Cornwall PL30 3LA",
    "addr:postcode":"pl30 3la",
    "addr:street":"Treroosel Road St Teath",
    "iso:country":"GB",
    "sg:address":"Treroosel Road, St Teath",
    "sg:city":"Bodmin",
    "sg:classifiers":[
        {
            "category":"Recreation",
            "subcategory":"Campground",
            "type":"Entertainment"
        }
    ],
    "sg:phone":"+44 1208 850495",
    "sg:postcode":"PL30 3LA",
    "sg:province":"Cornwall",
    "sg:tags":[
        "caravan",
        "park"
    ],
    "wof:name":"Rosewater Caravan Park",
    "wof:placetype":"venue"
},
  "geometry": {"coordinates":[-4.761604,50.59486],"type":"Point"}
}