{
  "type": "Feature",
  "properties": {
    "iso:country":"GB",
    "sg:address":"Treroosel Road, St Teath",
    "sg:city":"Bodmin",
    "sg:classifiers":[
        {
            "category":"Recreation",
            "subcategory":"Campground",
            "type":"Entertainment"
        }
    ],
    "sg:phone":"+44 1208 850495",
    "sg:postcode":"PL30 3LA",
    "sg:province":"Cornwall",
    "sg:tags":[
        "caravan",
        "park"
    ],
    "wof:name":"Rosewater Caravan Park",
    "wof:placetype":"venue"
},
  "geometry": {"coordinates":[-4.761604,50.59486],"type":"Point"}
}