{
  "type": "Feature",
  "properties": {
    "iso:country":"GB",
    "sg:address":"Alexander Ho, 50 Station Rd",
    "sg:city":"Aldershot",
    "sg:classifiers":[
        {
            "category":"Shopping",
            "subcategory":"Computers & Home Electronics",
            "type":"Retail Goods"
        }
    ],
    "sg:phone":"+44 1252 344454",
    "sg:postcode":"GU11 1BG",
    "sg:province":"Hampshire",
    "sg:tags":[
        "equipment",
        "radio"
    ],
    "wof:name":"Cordless L A N Modems Unlimited",
    "wof:placetype":"venue"
},
  "geometry": {"coordinates":[-0.759346,51.249603],"type":"Point"}
}