{
  "type": "Feature",
  "properties": {
    "addr:full":"41 Norbury Drive Mansfield Nottinghamshire NG18 4HT",
    "addr:housenumber":"41",
    "addr:postcode":"ng18 4ht",
    "addr:street":"Norbury Drive",
    "iso:country":"GB",
    "sg:address":"41 Norbury Drive",
    "sg:city":"Mansfield",
    "sg:classifiers":[
        {
            "category":"Professional",
            "subcategory":"Engineering",
            "type":"Services"
        },
        {
            "category":"Building & Trades",
            "subcategory":"Electrical",
            "type":"Services"
        }
    ],
    "sg:phone":"+44 1623 643811",
    "sg:postcode":"NG18 4HT",
    "sg:province":"Nottinghamshire",
    "sg:tags":[
        "engineer",
        "electrician",
        "contractor"
    ],
    "wof:name":"K Drake Electrical Ltd.",
    "wof:placetype":"venue"
},
  "geometry": {"coordinates":[-1.1729520559,53.1333961487],"type":"Point"}
}