{
  "type": "Feature",
  "properties": {
    "addr:full":"Unit 134 Ellesmere Chambers, Ellesmere Centre, Worsley Manchester Greater Manchester M28 3ZH",
    "addr:housenumber":"134;chambers",
    "addr:postcode":"m28 3zh",
    "addr:street":"Ellesmere",
    "iso:country":"GB",
    "sg:address":"Unit 134 Ellesmere Chambers, Ellesmere Centre, Worsley",
    "sg:city":"Manchester",
    "sg:classifiers":[
        {
            "category":"Manufacturing",
            "subcategory":"Tools & Machinery",
            "type":"Manufacturing & Wholesale Goods"
        },
        {
            "category":"Insurance",
            "subcategory":"Insurance Agent",
            "type":"Services"
        }
    ],
    "sg:phone":"+44 161 799 6093",
    "sg:postcode":"M28 3ZH",
    "sg:province":"Greater Manchester",
    "sg:tags":[
        "society",
        "friendly"
    ],
    "wof:name":"Richardson Investment Services Ltd.",
    "wof:placetype":"venue"
},
  "geometry": {"coordinates":[-2.39917,53.526649],"type":"Point"}
}