{
  "type": "Feature",
  "properties": {
    "addr:full":"9 Brunton Place Edinburgh City of Edinburgh EH7 5EG",
    "addr:housenumber":"9",
    "addr:postcode":"eh7 5eg",
    "addr:street":"Brunton Place Edinburgh",
    "iso:country":"GB",
    "sg:address":"9 Brunton Place",
    "sg:city":"Edinburgh",
    "sg:classifiers":[
        {
            "category":"Health Services",
            "subcategory":"Doctor",
            "type":"Services"
        }
    ],
    "sg:phone":"+44 131 557 5545",
    "sg:postcode":"EH7 5EG",
    "sg:province":"City of Edinburgh",
    "sg:tags":[
        "practitioners"
    ],
    "wof:name":"Drs Drever Dobbin Henderson Waterer & McLean",
    "wof:placetype":"venue"
},
  "geometry": {"coordinates":[-3.1737949848,55.9574584961],"type":"Point"}
}