{
  "type": "Feature",
  "properties": {
    "addr:full":"Unit 49 Van Alloys Industrial Estate, Busgrove Lane, Stoke Row Henley-on-thames Berkshire RG9 5QW",
    "addr:housenumber":"unit 49",
    "addr:postcode":"rg9 5qw",
    "addr:street":"Van Alloys Industrial Estate Busgrove Lane",
    "iso:country":"GB",
    "sg:address":"Unit 49 Van Alloys Industrial Estate, Busgrove Lane, Stoke Row",
    "sg:city":"Henley-on-thames",
    "sg:classifiers":[
        {
            "category":"Professional",
            "subcategory":"Business Services",
            "type":"Services"
        }
    ],
    "sg:phone":"+44 1491 681661",
    "sg:postcode":"RG9 5QW",
    "sg:province":"Berkshire",
    "sg:tags":[
        "import",
        "export",
        "agent"
    ],
    "wof:name":"Carter Winkler International",
    "wof:placetype":"venue"
},
  "geometry": {"coordinates":[-1.015119,51.55069],"type":"Point"}
}