{
  "type": "Feature",
  "properties": {
    "iso:country":"GB",
    "sg:address":"175 Whitehorse La, South Norwood",
    "sg:city":"London",
    "sg:classifiers":[
        {
            "category":"Home & Garden",
            "subcategory":"Home Furnishings",
            "type":"Retail Goods"
        }
    ],
    "sg:postcode":"SE25 6RB",
    "sg:province":"Greater London",
    "sg:tags":[
        "awning",
        "canopy",
        "blinds"
    ],
    "wof:name":"Mullinder,David,",
    "wof:placetype":"venue"
},
  "geometry": {"coordinates":[-0.0868249983,51.3992843628],"type":"Point"}
}