{
  "type": "Feature",
  "properties": {
    "addr:full":"Forest House, 3-5 Horndean Road Bracknell Berkshire RG12 0XQ",
    "addr:housenumber":"3-5",
    "addr:postcode":"rg12 0xq",
    "addr:street":"Horndean Road",
    "iso:country":"GB",
    "sg:address":"Forest House, 3-5 Horndean Road",
    "sg:city":"Bracknell",
    "sg:classifiers":[
        {
            "category":"Professional",
            "subcategory":"Accounting & Tax Preparation",
            "type":"Services"
        }
    ],
    "sg:href":"http://api.simplegeo.com/1.0/features/SG_62S3GaaUcshZjjMTkfDCNy_51.398167_-0.729072@1300740015.json",
    "sg:phone":"+44 1344 305244",
    "sg:postcode":"RG12 0XQ",
    "sg:province":"Berkshire",
    "sg:tags":[
        "accountant"
    ],
    "wof:name":"Kevin Beare & Co",
    "wof:placetype":"venue"
},
  "geometry": {"coordinates":[-0.729072,51.398167],"type":"Point"}
}