{"geometry":{"type":"Point","coordinates":[-0.729072,51.398167]},"type":"Feature","id":102560385,"bbox":[-0.729072,51.398167,-0.729072,51.398167],"properties":{"sg:province":"Berkshire","sg:tags":["accountant"],"geom:longitude":-0.729072,"wof:breaches":[],"sg:href":"http://api.simplegeo.com/1.0/features/SG_62S3GaaUcshZjjMTkfDCNy_51.398167_-0.729072@1300740015.json","sg:owner":"simplegeo","sg:postcode":"RG12 0XQ","geom:latitude":51.398167,"sg:classifiers":[{"category":"Professional","type":"Services","subcategory":"Accounting & Tax Preparation"}],"sg:address":"Forest House, 3-5 Horndean Road","sg:phone":"+44 1344 305244","wof:hierarchy":[{"locality_id":101750375,"venue_id":102560385,"country_id":85633159,"neighbourhood_id":85860901,"region_id":85684497}],"geom:area":0.000000,"sg:city":"Bracknell","wof:lastmodified":1438093238,"iso:country":"GB","wof:geomhash":"a94a0c0dea4471b995e5c2b51a1d662f","wof:name":"Kevin Beare & Co","wof:belongsto":[101750375,85633159,85860901,85684497],"src:geom":"simplegeo","wof:placetype":"venue","wof:supersedes":[],"wof:id":102560385,"wof:superseded_by":[],"wof:concordances":{"sg:id":"SG_62S3GaaUcshZjjMTkfDCNy_51.398167_-0.729072@1300740015"},"wof:parent_id":85860901}}