{
  "type": "Feature",
  "properties": {
    "addr:full":"Crew Lane Southwell Nottinghamshire NG25 0TX",
    "addr:postcode":"ng25 0tx",
    "addr:street":"Crew Lane",
    "iso:country":"GB",
    "sg:address":"Crew Lane",
    "sg:city":"Southwell",
    "sg:classifiers":[
        {
            "category":"Sports & Exercise",
            "subcategory":"Skate Park",
            "type":"Entertainment"
        }
    ],
    "sg:phone":"+44 1636 816464",
    "sg:postcode":"NG25 0TX",
    "sg:province":"Nottinghamshire",
    "sg:tags":[
        "mushroom"
    ],
    "wof:name":"Southwell Mushrooms Ltd.",
    "wof:placetype":"venue"
},
  "geometry": {"coordinates":[-0.9417729974,53.0772743225],"type":"Point"}
}