{
  "type": "Feature",
  "properties": {
    "addr:full":"211213 Merton Road London Greater London SW18 5EE",
    "addr:housenumber":"211213",
    "addr:postcode":"sw18 5ee",
    "addr:street":"Merton Road",
    "iso:country":"GB",
    "sg:address":"211213 Merton Road",
    "sg:city":"London",
    "sg:classifiers":[
        {
            "category":"Building & Trades",
            "subcategory":"Construction",
            "type":"Services"
        }
    ],
    "sg:phone":"+44 20 8874 3949",
    "sg:postcode":"SW18 5EE",
    "sg:province":"Greater London",
    "sg:tags":[
        "builder"
    ],
    "wof:name":"Ashe Construction (London) Ltd.",
    "wof:placetype":"venue"
},
  "geometry": {"coordinates":[-0.1981890053,51.4513282776],"type":"Point"}
}