{
  "type": "Feature",
  "properties": {
    "addr:full":"41 Kildrummy Road Aberdeen Aberdeen City AB15 8HT",
    "addr:housenumber":"41",
    "addr:postcode":"ab15 8ht",
    "addr:street":"Kildrummy Road",
    "iso:country":"GB",
    "sg:address":"41 Kildrummy Road",
    "sg:city":"Aberdeen",
    "sg:classifiers":[
        {
            "category":"Building & Trades",
            "subcategory":"Construction",
            "type":"Services"
        }
    ],
    "sg:phone":"+44 1224 317342",
    "sg:postcode":"AB15 8HT",
    "sg:province":"Aberdeen City",
    "sg:tags":[
        "builder"
    ],
    "wof:name":"W G Building Contractor",
    "wof:placetype":"venue"
},
  "geometry": {"coordinates":[-2.16237,57.137482],"type":"Point"}
}