{
  "type": "Feature",
  "properties": {
    "iso:country":"GB",
    "sg:address":"25 Walton Crescent",
    "sg:city":"Oxford",
    "sg:classifiers":[
        {
            "category":"Restaurant",
            "type":"Food & Drink"
        }
    ],
    "sg:phone":"+44 1865 311777",
    "sg:postcode":"OX1 2JG",
    "sg:province":"Oxfordshire",
    "wof:name":"Al-Shami",
    "wof:placetype":"venue"
},
  "geometry": {"coordinates":[-1.266129,51.756996],"type":"Point"}
}