{
  "type": "Feature",
  "properties": {
    "iso:country":"GB",
    "sg:address":"56 Sheridan Rd",
    "sg:city":"Richmond",
    "sg:classifiers":[
        {
            "category":"Professional",
            "type":"Services"
        }
    ],
    "sg:phone":"+44 20 8948 6112",
    "sg:postcode":"TW10 7NH",
    "sg:province":"Greater London",
    "sg:tags":[
        "caterer"
    ],
    "wof:name":"Banqueting By Thameside",
    "wof:placetype":"venue"
},
  "geometry": {"coordinates":[-0.315409,51.435638],"type":"Point"}
}