{
  "type": "Feature",
  "properties": {
    "addr:full":"Houlston Manor, Houlston La Shrewsbury Shropshire SY4 3RD",
    "addr:postcode":"sy4 3rd",
    "addr:street":"La Shrewsbury",
    "iso:country":"GB",
    "sg:address":"Houlston Manor, Houlston La",
    "sg:city":"Shrewsbury",
    "sg:classifiers":[
        {
            "category":"Professional",
            "subcategory":"Computer Services",
            "type":"Services"
        }
    ],
    "sg:phone":"+44 1939 291221",
    "sg:postcode":"SY4 3RD",
    "sg:province":"Shropshire",
    "sg:tags":[
        "consultant"
    ],
    "wof:name":"P G Computer Systems",
    "wof:placetype":"venue"
},
  "geometry": {"coordinates":[-2.7747299671,52.8181114197],"type":"Point"}
}