{
  "type": "Feature",
  "properties": {
    "addr:full":"75-77 London Road Peterborough Cambridgeshire PE2 9BS",
    "addr:housenumber":"75-77",
    "addr:postcode":"pe2 9bs",
    "addr:street":"London Road",
    "iso:country":"GB",
    "sg:address":"75-77 London Road",
    "sg:city":"Peterborough",
    "sg:classifiers":[
        {
            "category":"Travel",
            "subcategory":"Hotels & Motels",
            "type":"Entertainment"
        }
    ],
    "sg:phone":"+44 1733 563718",
    "sg:postcode":"PE2 9BS",
    "sg:province":"Cambridgeshire",
    "sg:tags":[
        "house",
        "guest"
    ],
    "wof:name":"Aragon House",
    "wof:placetype":"venue"
},
  "geometry": {"coordinates":[-0.2450090051,52.5612258911],"type":"Point"}
}