{
  "type": "Feature",
  "properties": {
    "addr:full":"15 Warmdene Clo, Patcham Brighton East Sussex BN1 8LB",
    "addr:housenumber":"15",
    "addr:postcode":"bn1 8lb",
    "addr:street":"Warmdene Clo",
    "iso:country":"GB",
    "sg:address":"15 Warmdene Clo, Patcham",
    "sg:city":"Brighton",
    "sg:classifiers":[
        {
            "category":"Building & Trades",
            "subcategory":"Construction",
            "type":"Services"
        }
    ],
    "sg:postcode":"BN1 8LB",
    "sg:province":"East Sussex",
    "sg:tags":[
        "builder"
    ],
    "wof:name":"Hayward,R V,",
    "wof:placetype":"venue"
},
  "geometry": {"coordinates":[-0.141258,50.860939],"type":"Point"}
}