{
  "type": "Feature",
  "properties": {
    "addr:full":"Rosskeen Invergordon Highland IV18 0PL",
    "addr:postcode":"iv18 0pl",
    "iso:country":"GB",
    "sg:address":"Rosskeen",
    "sg:city":"Invergordon",
    "sg:classifiers":[
        {
            "category":"Professional",
            "subcategory":"Engineering",
            "type":"Services"
        },
        {
            "category":"Manufacturing",
            "subcategory":"Motor Vehicles & Parts",
            "type":"Manufacturing & Wholesale Goods"
        }
    ],
    "sg:phone":"+44 1349 853900",
    "sg:postcode":"IV18 0PL",
    "sg:province":"Highland",
    "sg:tags":[
        "merchant",
        "bearing",
        "engineer"
    ],
    "wof:name":"Rosskeen Supply Co",
    "wof:placetype":"venue"
},
  "geometry": {"coordinates":[-4.166444,57.687851],"type":"Point"}
}