{
  "type": "Feature",
  "properties": {
    "addr:full":"29 Balmoral Dr Crewe Cheshire CW4 7JQ",
    "addr:housenumber":"29",
    "addr:postcode":"cw4 7jq",
    "addr:street":"Balmoral Dr",
    "iso:country":"GB",
    "sg:address":"29 Balmoral Dr",
    "sg:city":"Crewe",
    "sg:classifiers":[
        {
            "category":"Building & Trades",
            "subcategory":"Electrical",
            "type":"Services"
        }
    ],
    "sg:phone":"+44 1477 535997",
    "sg:postcode":"CW4 7JQ",
    "sg:province":"Cheshire",
    "sg:tags":[
        "heating"
    ],
    "wof:name":"Thermon UK Ltd",
    "wof:placetype":"venue"
},
  "geometry": {"coordinates":[-2.3643429279,53.1980247498],"type":"Point"}
}