{
  "type": "Feature",
  "properties": {
    "addr:full":"Block D, Imperial Works, Perren Street London Greater London NW5 3ED",
    "addr:housenumber":"d",
    "addr:postcode":"nw5 3ed",
    "addr:street":"Imperial Works Perren Street",
    "iso:country":"GB",
    "sg:address":"Block D, Imperial Works, Perren Street",
    "sg:city":"London",
    "sg:classifiers":[
        {
            "category":"Manufacturing",
            "subcategory":"Jewelry",
            "type":"Manufacturing & Wholesale Goods"
        },
        {
            "category":"Building & Trades",
            "subcategory":"Construction",
            "type":"Services"
        }
    ],
    "sg:phone":"+44 20 7482 9000",
    "sg:postcode":"NW5 3ED",
    "sg:province":"Greater London",
    "sg:tags":[
        "joinery",
        "jewellery",
        "repair"
    ],
    "wof:name":"Marinetime Ltd.",
    "wof:placetype":"venue"
},
  "geometry": {"coordinates":[-0.1460999995,51.5472984314],"type":"Point"}
}