{
  "type": "Feature",
  "properties": {
    "addr:full":"3 Merchiston Place Edinburgh City of Edinburgh EH10 4NP",
    "addr:housenumber":"3",
    "addr:postcode":"eh10 4np",
    "addr:street":"Merchiston Place Edinburgh",
    "iso:country":"GB",
    "sg:address":"3 Merchiston Place",
    "sg:city":"Edinburgh",
    "sg:classifiers":[
        {
            "category":"Building & Trades",
            "subcategory":"Plumbing",
            "type":"Services"
        }
    ],
    "sg:phone":"+44 131 229 1918",
    "sg:postcode":"EH10 4NP",
    "sg:province":"City of Edinburgh",
    "sg:tags":[
        "heating"
    ],
    "wof:name":"W F Wightman",
    "wof:placetype":"venue"
},
  "geometry": {"coordinates":[-3.2105269432,55.9358825684],"type":"Point"}
}