{
  "type": "Feature",
  "properties": {
    "iso:country":"GB",
    "sg:address":"Unit 2 The Mews, 16 Holly Bush Lane",
    "sg:city":"Sevenoaks",
    "sg:classifiers":[
        {
            "category":"Professional",
            "subcategory":"Business Services",
            "type":"Services"
        }
    ],
    "sg:phone":"+44 1732 742752",
    "sg:postcode":"TN13 3TH",
    "sg:province":"Kent",
    "sg:tags":[
        "import",
        "export",
        "agent"
    ],
    "wof:name":"Invicta Foods Ltd.",
    "wof:placetype":"venue"
},
  "geometry": {"coordinates":[0.1929389983,51.270198822],"type":"Point"}
}