{
  "type": "Feature",
  "properties": {
    "iso:country":"GB",
    "sg:address":"Newsome Mills, Hart Street",
    "sg:city":"Huddersfield",
    "sg:classifiers":[
        {
            "category":"Autos & Motor Vehicles",
            "subcategory":"Recreational Vehicle Sales",
            "type":"Retail Goods"
        }
    ],
    "sg:postcode":"HD4 6LS",
    "sg:province":"West Yorkshire",
    "sg:tags":[
        "caravan"
    ],
    "wof:name":"Tourmaster Motorhomes",
    "wof:placetype":"venue"
},
  "geometry": {"coordinates":[-1.7854729891,53.6267967224],"type":"Point"}
}