{
  "type": "Feature",
  "properties": {
    "iso:country":"GB",
    "sg:address":"Sherbourne House, 23-25 Northolt Road",
    "sg:city":"Harrow",
    "sg:classifiers":[
        {
            "category":"Wholesale",
            "subcategory":"Groceries",
            "type":"Manufacturing & Wholesale Goods"
        }
    ],
    "sg:phone":"+44 20 8426 4777",
    "sg:postcode":"HA2 0LH",
    "sg:province":"Greater London",
    "sg:tags":[
        "food",
        "supplier",
        "drink"
    ],
    "wof:name":"McM Select Foods Ltd.",
    "wof:placetype":"venue"
},
  "geometry": {"coordinates":[-0.347561,51.568733],"type":"Point"}
}