{
  "type": "Feature",
  "properties": {
    "addr:full":"43 Stonegate York North Yorkshire YO1 8AW",
    "addr:housenumber":"43",
    "addr:postcode":"yo1 8aw",
    "addr:street":"Stonegate",
    "iso:country":"GB",
    "sg:address":"43 Stonegate",
    "sg:city":"York",
    "sg:classifiers":[
        {
            "category":"Arts & Performance",
            "subcategory":"Art Gallery",
            "type":"Entertainment"
        }
    ],
    "sg:phone":"+44 1904 641187",
    "sg:postcode":"YO1 8AW",
    "sg:province":"North Yorkshire",
    "wof:name":"Pyramid Gallery",
    "wof:placetype":"venue"
},
  "geometry": {"coordinates":[-1.082975,53.960987],"type":"Point"}
}