{
  "type": "Feature",
  "properties": {
    "iso:country":"GB",
    "sg:address":"27 Halifax Road, Hipperholme",
    "sg:city":"Halifax",
    "sg:classifiers":[
        {
            "category":"Shopping",
            "subcategory":"Clothing, Apparel, & Fashions",
            "type":"Retail Goods"
        }
    ],
    "sg:phone":"+44 1422 205080",
    "sg:postcode":"HX3 8HQ",
    "sg:province":"West Yorkshire",
    "sg:tags":[
        "dresswear"
    ],
    "wof:name":"The Cream Dress Agency",
    "wof:placetype":"venue"
},
  "geometry": {"coordinates":[-1.819483,53.726334],"type":"Point"}
}