{
  "type": "Feature",
  "properties": {
    "addr:full":"40 High Street, Market Place, Highworth Swindon Gloucestershire SN6 7AQ",
    "addr:housenumber":"40",
    "addr:postcode":"sn6 7aq",
    "addr:street":"High Street Market Place",
    "iso:country":"GB",
    "sg:address":"40 High Street, Market Place, Highworth",
    "sg:city":"Swindon",
    "sg:classifiers":[
        {
            "category":"Professional",
            "subcategory":"Accounting & Tax Preparation",
            "type":"Services"
        }
    ],
    "sg:postcode":"SN6 7AQ",
    "sg:province":"Gloucestershire",
    "sg:tags":[
        "accountant"
    ],
    "wof:name":"Hobson Hughes",
    "wof:placetype":"venue"
},
  "geometry": {"coordinates":[-1.7107360363,51.6307106018],"type":"Point"}
}