{
  "type": "Feature",
  "properties": {
    "iso:country":"GB",
    "sg:address":"Unit 17 Hanley Workshop",
    "sg:city":"Worcester",
    "sg:classifiers":[
        {
            "category":"Professional",
            "subcategory":"Printing & Photocopies",
            "type":"Services"
        }
    ],
    "sg:phone":"+44 1684 311071",
    "sg:postcode":"WR8 0DX",
    "sg:province":"Gloucestershire",
    "sg:tags":[
        "engraving"
    ],
    "wof:name":"Aldis Engraving",
    "wof:placetype":"venue"
},
  "geometry": {"coordinates":[-2.218449,52.064701],"type":"Point"}
}