{
  "type": "Feature",
  "properties": {
    "addr:full":"Tettenham College Wolverhampton Shropshire WV6 8QX",
    "addr:postcode":"wv6 8qx",
    "iso:country":"GB",
    "sg:address":"Tettenham College",
    "sg:city":"Wolverhampton",
    "sg:classifiers":[
        {
            "category":"Education",
            "subcategory":"Music School",
            "type":"Public Place"
        }
    ],
    "sg:postcode":"WV6 8QX",
    "sg:province":"Shropshire",
    "wof:name":"Stagecoach Drama School",
    "wof:placetype":"venue"
},
  "geometry": {"coordinates":[-2.1658000946,52.5990257263],"type":"Point"}
}