{
  "type": "Feature",
  "properties": {
    "addr:full":"The Ploughmans Cottage, Temple Guiting Cheltenham Gloucestershire GL54 5RW",
    "addr:postcode":"gl54 5rw",
    "iso:country":"GB",
    "sg:address":"The Ploughmans Cottage, Temple Guiting",
    "sg:city":"Cheltenham",
    "sg:classifiers":[
        {
            "category":"Professional",
            "subcategory":"Engineering",
            "type":"Services"
        }
    ],
    "sg:phone":"+44 1451 850733",
    "sg:postcode":"GL54 5RW",
    "sg:province":"Gloucestershire",
    "sg:tags":[
        "contractor",
        "electrical",
        "engineer"
    ],
    "wof:name":"Stephen P Hughes",
    "wof:placetype":"venue"
},
  "geometry": {"coordinates":[-1.867414,51.951569],"type":"Point"}
}