{
  "type": "Feature",
  "properties": {
    "addr:full":"Rivington Lane, Horwich Bolton Lancashire BL6 7SB",
    "addr:postcode":"bl6 7sb",
    "addr:street":"Rivington Lane",
    "iso:country":"GB",
    "sg:address":"Rivington Lane, Horwich",
    "sg:city":"Bolton",
    "sg:classifiers":[
        {
            "category":"Transit Center",
            "subcategory":"Freight",
            "type":"Transportation"
        }
    ],
    "sg:phone":"+44 1204 690056",
    "sg:postcode":"BL6 7SB",
    "sg:province":"Lancashire",
    "sg:tags":[
        "shop",
        "craft",
        "centre"
    ],
    "wof:name":"Great House Gallery",
    "wof:placetype":"venue"
},
  "geometry": {"coordinates":[-2.551749,53.609741],"type":"Point"}
}