{
  "type": "Feature",
  "properties": {
    "addr:full":"24 Leigh Close Westbury Wiltshire BA13 3SX",
    "addr:housenumber":"24",
    "addr:postcode":"ba13 3sx",
    "addr:street":"Leigh Close",
    "iso:country":"GB",
    "sg:address":"24 Leigh Close",
    "sg:city":"Westbury",
    "sg:classifiers":[
        {
            "category":"Real Estate",
            "subcategory":"Real Estate Services",
            "type":"Services"
        },
        {
            "category":"Retail",
            "subcategory":"Auto Rental",
            "type":"Services"
        },
        {
            "category":"Military Area",
            "subcategory":"Air Force Base",
            "type":"Public Place"
        }
    ],
    "sg:phone":"+44 1373 823589",
    "sg:postcode":"BA13 3SX",
    "sg:province":"Wiltshire",
    "sg:tags":[
        "taxi",
        "hire",
        "van",
        "plant",
        "private",
        "truck",
        "leasing"
    ],
    "wof:name":"David J Rose",
    "wof:placetype":"venue"
},
  "geometry": {"coordinates":[-2.188911,51.256203],"type":"Point"}
}