{
  "type": "Feature",
  "properties": {
    "addr:full":"2 New Close Cotts, London Road Hassocks East Sussex BN6 9NF",
    "addr:housenumber":"2",
    "addr:postcode":"bn6 9nf",
    "addr:street":"New Close;London Road",
    "iso:country":"GB",
    "sg:address":"2 New Close Cotts, London Road",
    "sg:city":"Hassocks",
    "sg:classifiers":[
        {
            "category":"Building & Trades",
            "subcategory":"Plumbing",
            "type":"Services"
        }
    ],
    "sg:phone":"+44 1273 844456",
    "sg:postcode":"BN6 9NF",
    "sg:province":"East Sussex",
    "sg:tags":[
        "central",
        "heating"
    ],
    "wof:name":"Kingscott Associates",
    "wof:placetype":"venue"
},
  "geometry": {"coordinates":[-0.14544,50.938881],"type":"Point"}
}