{
  "type": "Feature",
  "properties": {
    "iso:country":"GB",
    "sg:address":"542 Bolton Road",
    "sg:city":"Darwen",
    "sg:classifiers":[
        {
            "category":"Bars & Pubs",
            "type":"Food & Drink"
        },
        {
            "category":"Community Center",
            "subcategory":"Social",
            "type":"Public Place"
        }
    ],
    "sg:phone":"+44 1254 703829",
    "sg:postcode":"BB3 2JR",
    "sg:province":"Lancashire",
    "sg:tags":[
        "pubs",
        "house",
        "inn",
        "activity"
    ],
    "wof:name":"Swan Hotel",
    "wof:placetype":"venue"
},
  "geometry": {"coordinates":[-2.460006,53.681293],"type":"Point"}
}