{
  "type": "Feature",
  "properties": {
    "addr:full":"2 Arandale Avenue, East Ewell Epsom Surrey KT17 2RG",
    "addr:housenumber":"2",
    "addr:postcode":"kt17 2rg",
    "addr:street":"Arandale Avenue East",
    "iso:country":"GB",
    "sg:address":"2 Arandale Avenue, East Ewell",
    "sg:city":"Epsom",
    "sg:classifiers":[
        {
            "category":"Building & Trades",
            "subcategory":"Construction",
            "type":"Services"
        }
    ],
    "sg:postcode":"KT17 2RG",
    "sg:province":"Surrey",
    "sg:tags":[
        "builder"
    ],
    "wof:name":"J Gallagher",
    "wof:placetype":"venue"
},
  "geometry": {"coordinates":[-0.248943001,51.3582763672],"type":"Point"}
}