{
  "type": "Feature",
  "properties": {
    "addr:full":"Unit D, Abeles Way, Holly Lane Industrial Estate Atherstone Leicestershire CV9 2QZ",
    "addr:housenumber":"unit d",
    "addr:postcode":"cv9 2qz",
    "addr:street":"Abeles Way Holly Lane Industrial Estate",
    "iso:country":"GB",
    "sg:address":"Unit D, Abeles Way, Holly Lane Industrial Estate",
    "sg:city":"Atherstone",
    "sg:classifiers":[
        {
            "category":"Manufacturing",
            "subcategory":"Wood Products",
            "type":"Manufacturing & Wholesale Goods"
        },
        {
            "category":"Building & Trades",
            "subcategory":"Construction",
            "type":"Services"
        }
    ],
    "sg:phone":"+44 1827 717003",
    "sg:postcode":"CV9 2QZ",
    "sg:province":"Leicestershire",
    "sg:tags":[
        "joinery",
        "manufacturer"
    ],
    "sg:website":"http://www.seyerjoinery.co.uk",
    "wof:name":"Seyer Joinery",
    "wof:placetype":"venue"
},
  "geometry": {"coordinates":[-1.554386,52.583954],"type":"Point"}
}