{
  "type": "Feature",
  "properties": {
    "iso:country":"GB",
    "sg:address":"18 Calder Park",
    "sg:city":"Edinburgh",
    "sg:classifiers":[
        {
            "category":"Shopping",
            "subcategory":"Pharmacy",
            "type":"Retail Goods"
        }
    ],
    "sg:phone":"+44 131 453 2674",
    "sg:postcode":"EH11 4JN",
    "sg:province":"City of Edinburgh",
    "sg:tags":[
        "pharmacist",
        "dispensing",
        "chemist"
    ],
    "wof:name":"Calder Pharmacy",
    "wof:placetype":"venue"
},
  "geometry": {"coordinates":[-3.294489,55.919872],"type":"Point"}
}