{
  "type": "Feature",
  "properties": {
    "iso:country":"GB",
    "sg:address":"Eden Golf Course, Crosby On Eden",
    "sg:city":"Carlisle",
    "sg:classifiers":[
        {
            "category":"Sports & Exercise",
            "subcategory":"Golf",
            "type":"Entertainment"
        }
    ],
    "sg:phone":"+44 1228 573003",
    "sg:postcode":"CA6 4RA",
    "sg:province":"Cumbria",
    "sg:tags":[
        "club",
        "course"
    ],
    "wof:name":"Eden Golf Centre Ltd.",
    "wof:placetype":"venue"
},
  "geometry": {"coordinates":[-2.8415338993,54.930809021],"type":"Point"}
}