{
  "type": "Feature",
  "properties": {
    "addr:full":"Barringers Court, Neats Acre Ruislip Greater London HA4 7JP",
    "addr:postcode":"ha4 7jp",
    "iso:country":"GB",
    "sg:address":"Barringers Court, Neats Acre",
    "sg:city":"Ruislip",
    "sg:classifiers":[
        {
            "category":"Organizations",
            "subcategory":"Community Association",
            "type":"Services"
        }
    ],
    "sg:phone":"+44 1895 638193",
    "sg:postcode":"HA4 7JP",
    "sg:province":"Greater London",
    "sg:tags":[
        "co-operatives",
        "society",
        "housing",
        "trust"
    ],
    "sg:website":"http://www.anchor.org.uk",
    "wof:name":"Anchor Trust",
    "wof:placetype":"venue"
},
  "geometry": {"coordinates":[-0.4318619967,51.5770759583],"type":"Point"}
}