{
  "type": "Feature",
  "properties": {
    "iso:country":"GB",
    "sg:address":"Kings Highway",
    "sg:city":"London",
    "sg:classifiers":[
        {
            "category":"Retail",
            "subcategory":"Funeral Services",
            "type":"Services"
        }
    ],
    "sg:phone":"+44 20 8854 0740",
    "sg:postcode":"SE18 2BJ",
    "sg:province":"Greater London",
    "sg:tags":[
        "cemetery",
        "crematorium"
    ],
    "wof:name":"Woolwich Cemetery",
    "wof:placetype":"venue"
},
  "geometry": {"coordinates":[0.0996799991,51.4787712097],"type":"Point"}
}