{
  "type": "Feature",
  "properties": {
    "addr:full":"1 Quebec Rd Norwich Norfolk NR1 4AX",
    "addr:housenumber":"1",
    "addr:postcode":"nr1 4ax",
    "addr:street":"Quebec Rd",
    "iso:country":"GB",
    "sg:address":"1 Quebec Rd",
    "sg:city":"Norwich",
    "sg:classifiers":[
        {
            "category":"Food & Beverages",
            "subcategory":"Meat & Fish",
            "type":"Retail Goods"
        }
    ],
    "sg:postcode":"NR1 4AX",
    "sg:province":"Norfolk",
    "sg:tags":[
        "butcher"
    ],
    "wof:name":"Lane,D S,",
    "wof:placetype":"venue"
},
  "geometry": {"coordinates":[1.312615,52.629848],"type":"Point"}
}