{
  "type": "Feature",
  "properties": {
    "addr:full":"Tidwell Farm Dairies, 92 Granary Lane Budleigh Salterton Devon EX9 6ER",
    "addr:housenumber":"92",
    "addr:postcode":"ex9 6er",
    "addr:street":"Dairies;Granary Lane",
    "iso:country":"GB",
    "sg:address":"Tidwell Farm Dairies, 92 Granary Lane",
    "sg:city":"Budleigh Salterton",
    "sg:classifiers":[
        {
            "category":"Farming",
            "subcategory":"Dairy Farm",
            "type":"Manufacturing & Wholesale Goods"
        }
    ],
    "sg:phone":"+44 1395 442067",
    "sg:postcode":"EX9 6ER",
    "sg:province":"Devon",
    "wof:name":"Tidwell Farm Dairies",
    "wof:placetype":"venue"
},
  "geometry": {"coordinates":[-3.315598011,50.6351013184],"type":"Point"}
}