{
  "type": "Feature",
  "properties": {
    "addr:full":"Pitt House, East Buckland Barnstaple Devon EX32 0TD",
    "addr:postcode":"ex32 0td",
    "addr:street":"East Buckland",
    "iso:country":"GB",
    "sg:address":"Pitt House, East Buckland",
    "sg:city":"Barnstaple",
    "sg:classifiers":[
        {
            "category":"Building & Trades",
            "subcategory":"Construction",
            "type":"Services"
        }
    ],
    "sg:phone":"+44 1598 760448",
    "sg:postcode":"EX32 0TD",
    "sg:province":"Devon",
    "sg:tags":[
        "joinery"
    ],
    "wof:name":"D B Marks",
    "wof:placetype":"venue"
},
  "geometry": {"coordinates":[-3.987807,51.057533],"type":"Point"}
}