{
  "type": "Feature",
  "properties": {
    "addr:full":"106a High Street, Carrville Durham Durham DH1 1BQ",
    "addr:housenumber":"106a",
    "addr:postcode":"dh1 1bq",
    "addr:street":"High Street",
    "iso:country":"GB",
    "sg:address":"106a High Street, Carrville",
    "sg:city":"Durham",
    "sg:classifiers":[
        {
            "category":"Home & Garden",
            "subcategory":"Household Appliances",
            "type":"Retail Goods"
        }
    ],
    "sg:phone":"+44 191 383 2074",
    "sg:postcode":"DH1 1BQ",
    "sg:province":"Durham",
    "sg:tags":[
        "electrical"
    ],
    "wof:name":"R Graham",
    "wof:placetype":"venue"
},
  "geometry": {"coordinates":[-1.526292,54.790031],"type":"Point"}
}