{
  "type": "Feature",
  "properties": {
    "addr:full":"Croft Foot Seascale Cumbria CA20 1AH",
    "addr:postcode":"ca20 1ah",
    "addr:street":"Croft",
    "iso:country":"GB",
    "sg:address":"Croft Foot",
    "sg:city":"Seascale",
    "sg:classifiers":[
        {
            "category":"Cafe",
            "type":"Food & Drink"
        }
    ],
    "sg:postcode":"CA20 1AH",
    "sg:province":"Cumbria",
    "sg:tags":[
        "tea",
        "room"
    ],
    "wof:name":"Naylor,Helen,",
    "wof:placetype":"venue"
},
  "geometry": {"coordinates":[-3.4846200943,54.394821167],"type":"Point"}
}