{
  "type": "Feature",
  "properties": {
    "addr:full":"Woodway Farm, Bicester Road Aylesbury Buckinghamshire HP18 9EP",
    "addr:postcode":"hp18 9ep",
    "addr:street":"Bicester Road",
    "iso:country":"GB",
    "sg:address":"Woodway Farm, Bicester Road",
    "sg:city":"Aylesbury",
    "sg:classifiers":[
        {
            "category":"Retail",
            "subcategory":"Auto Repair",
            "type":"Services"
        }
    ],
    "sg:postcode":"HP18 9EP",
    "sg:province":"Buckinghamshire",
    "sg:tags":[
        "modification",
        "garage"
    ],
    "wof:name":"Major Motor Sports",
    "wof:placetype":"venue"
},
  "geometry": {"coordinates":[-1.073442,51.770947],"type":"Point"}
}