{
  "type": "Feature",
  "properties": {
    "addr:full":"93 Acacia Avenue Spalding Lincolnshire PE11 2LR",
    "addr:housenumber":"93",
    "addr:postcode":"pe11 2lr",
    "addr:street":"Acacia Avenue Spalding",
    "iso:country":"GB",
    "sg:address":"93 Acacia Avenue",
    "sg:city":"Spalding",
    "sg:classifiers":[
        {
            "category":"Building & Trades",
            "subcategory":"Construction",
            "type":"Services"
        }
    ],
    "sg:postcode":"PE11 2LR",
    "sg:province":"Lincolnshire",
    "sg:tags":[
        "bricklaying"
    ],
    "wof:name":"David Wilkinson",
    "wof:placetype":"venue"
},
  "geometry": {"coordinates":[-0.137804,52.793549],"type":"Point"}
}