{
  "type": "Feature",
  "properties": {
    "addr:full":"1 Newark Ho, Hempsted La Gloucester Gloucestershire GL2 5JR",
    "addr:housenumber":"1",
    "addr:postcode":"gl2 5jr",
    "addr:street":"Newark Ho Hempsted La Gloucester",
    "iso:country":"GB",
    "sg:address":"1 Newark Ho, Hempsted La",
    "sg:city":"Gloucester",
    "sg:classifiers":[
        {
            "category":"Organizations",
            "subcategory":"Non-profit Organization",
            "type":"Services"
        }
    ],
    "sg:phone":"+44 1452 526904",
    "sg:postcode":"GL2 5JR",
    "sg:province":"Gloucestershire",
    "sg:tags":[
        "organisation",
        "voluntary",
        "charity"
    ],
    "wof:name":"National Childbirth Trust",
    "wof:placetype":"venue"
},
  "geometry": {"coordinates":[-2.2674601078,51.8552284241],"type":"Point"}
}