{
  "type": "Feature",
  "properties": {
    "iso:country":"GB",
    "sg:address":"35 Naylor Street",
    "sg:city":"Liverpool",
    "sg:classifiers":[
        {
            "category":"Autos & Motor Vehicles",
            "subcategory":"Motorcycle Sales",
            "type":"Retail Goods"
        }
    ],
    "sg:phone":"+44 151 236 4300",
    "sg:postcode":"L3 6DR",
    "sg:province":"Merseyside",
    "wof:name":"C C C",
    "wof:placetype":"venue"
},
  "geometry": {"coordinates":[-2.987116,53.41412],"type":"Point"}
}