{
  "type": "Feature",
  "properties": {
    "iso:country":"GB",
    "sg:address":"Unit 2 Prescott Road, Colnbrook",
    "sg:city":"Slough",
    "sg:classifiers":[
        {
            "category":"Government",
            "subcategory":"Post Office",
            "type":"Public Place"
        }
    ],
    "sg:phone":"+44 1753 680033",
    "sg:postcode":"SL3 0AE",
    "sg:province":"Berkshire",
    "sg:tags":[
        "messenger",
        "courier"
    ],
    "wof:name":"Initial City Link Slough",
    "wof:placetype":"venue"
},
  "geometry": {"coordinates":[-0.516274,51.473602],"type":"Point"}
}