{
  "type": "Feature",
  "properties": {
    "addr:full":"139 Clarence Avenue Northampton Northamptonshire NN2 6NY",
    "addr:housenumber":"139",
    "addr:postcode":"nn2 6ny",
    "addr:street":"Clarence Avenue",
    "iso:country":"GB",
    "sg:address":"139 Clarence Avenue",
    "sg:city":"Northampton",
    "sg:classifiers":[
        {
            "category":"Building & Trades",
            "subcategory":"Construction",
            "type":"Services"
        }
    ],
    "sg:phone":"+44 1604 711597",
    "sg:postcode":"NN2 6NY",
    "sg:province":"Northamptonshire",
    "sg:tags":[
        "joinery",
        "joiner",
        "carpenter",
        "carpentry"
    ],
    "wof:name":"B D TEW",
    "wof:placetype":"venue"
},
  "geometry": {"coordinates":[-0.8987450004,52.2574386597],"type":"Point"}
}