{
  "type": "Feature",
  "properties": {
    "addr:full":"Neville Avenue Spalding Lincolnshire PE11 2EH",
    "addr:postcode":"pe11 2eh",
    "addr:street":"Neville Avenue",
    "iso:country":"GB",
    "sg:address":"Neville Avenue",
    "sg:city":"Spalding",
    "sg:classifiers":[
        {
            "category":"Education",
            "subcategory":"Music School",
            "type":"Public Place"
        }
    ],
    "sg:phone":"+44 1775 725527",
    "sg:postcode":"PE11 2EH",
    "sg:province":"Lincolnshire",
    "wof:name":"Spalding Music Centre",
    "wof:placetype":"venue"
},
  "geometry": {"coordinates":[-0.137966,52.787842],"type":"Point"}
}