{
  "type": "Feature",
  "properties": {
    "iso:country":"GB",
    "sg:address":"31 Clifton Road",
    "sg:city":"Cambridge",
    "sg:classifiers":[
        {
            "category":"Retail",
            "subcategory":"Photofinishing",
            "type":"Services"
        },
        {
            "category":"Retail",
            "subcategory":"Portrait Studio",
            "type":"Services"
        }
    ],
    "sg:phone":"+44 1223 519555",
    "sg:postcode":"CB1 7EB",
    "sg:province":"Cambridgeshire",
    "sg:tags":[
        "photographic",
        "photographer",
        "commercial",
        "processor"
    ],
    "wof:name":"A M PHOTOGRAPHIC",
    "wof:placetype":"venue"
},
  "geometry": {"coordinates":[0.1382180005,52.1920509338],"type":"Point"}
}