{
  "type": "Feature",
  "properties": {
    "addr:full":"Beechcroft Nurseries, Meadow La Burton-on-trent Derbyshire DE13 8NJ",
    "addr:postcode":"de13 8nj",
    "addr:street":"Meadow",
    "iso:country":"GB",
    "sg:address":"Beechcroft Nurseries, Meadow La",
    "sg:city":"Burton-on-trent",
    "sg:classifiers":[
        {
            "category":"Home & Garden",
            "subcategory":"Garden Supply",
            "type":"Retail Goods"
        }
    ],
    "sg:postcode":"DE13 8NJ",
    "sg:province":"Derbyshire",
    "sg:tags":[
        "fertiliser"
    ],
    "wof:name":"Webb,Thomas,",
    "wof:placetype":"venue"
},
  "geometry": {"coordinates":[-1.7974,52.759911],"type":"Point"}
}