{
  "type": "Feature",
  "properties": {
    "iso:country":"GB",
    "sg:address":"Welyndale, Verwood Road, Three Legged Cross",
    "sg:city":"Wimborne",
    "sg:classifiers":[
        {
            "category":"Manufacturing",
            "subcategory":"Metals",
            "type":"Manufacturing & Wholesale Goods"
        },
        {
            "category":"Utilities",
            "subcategory":"Natural Gas",
            "type":"Services"
        }
    ],
    "sg:postcode":"BH21 6RR",
    "sg:province":"Dorset",
    "sg:tags":[
        "blacksmith",
        "forgemasters"
    ],
    "wof:name":"Christopher J Jeneson",
    "wof:placetype":"venue"
},
  "geometry": {"coordinates":[-1.8842710257,50.8503456116],"type":"Point"}
}