{
  "type": "Feature",
  "properties": {
    "addr:full":"71 Taunton Drive Liverpool Merseyside L10 8JN",
    "addr:housenumber":"71",
    "addr:postcode":"l10 8jn",
    "addr:street":"Taunton Drive",
    "iso:country":"GB",
    "sg:address":"71 Taunton Drive",
    "sg:city":"Liverpool",
    "sg:classifiers":[
        {
            "category":"Professional",
            "subcategory":"Engineering",
            "type":"Services"
        },
        {
            "category":"Building & Trades",
            "subcategory":"Electrical",
            "type":"Services"
        }
    ],
    "sg:phone":"+44 151 520 0044",
    "sg:postcode":"L10 8JN",
    "sg:province":"Merseyside",
    "sg:tags":[
        "engineer",
        "electrician",
        "contractor"
    ],
    "wof:name":"Fortress Electrics",
    "wof:placetype":"venue"
},
  "geometry": {"coordinates":[-2.926793,53.48035],"type":"Point"}
}