{
  "type": "Feature",
  "properties": {
    "iso:country":"GB",
    "sg:address":"Unit 3, Keathpark Ind Est, Balmoral Rd, Rattray",
    "sg:city":"Blairgowrie",
    "sg:classifiers":[
        {
            "category":"Bus Charters",
            "type":"Transportation"
        }
    ],
    "sg:phone":"+44 1250 873474",
    "sg:postcode":"PH10 7HU",
    "sg:province":"Perth and Kinross",
    "sg:tags":[
        "coach"
    ],
    "wof:name":"SUN N FUN HOLIDAYS",
    "wof:placetype":"venue"
},
  "geometry": {"coordinates":[-3.333313942,56.5941734314],"type":"Point"}
}