{
  "type": "Feature",
  "properties": {
    "iso:country":"GB",
    "sg:address":"32 Harveys Nurseries, Peppard Road",
    "sg:city":"Reading",
    "sg:classifiers":[
        {
            "category":"Retail",
            "subcategory":"Driving School",
            "type":"Services"
        }
    ],
    "sg:phone":"+44 118 947 6504",
    "sg:postcode":"RG4 8TN",
    "sg:province":"Berkshire",
    "wof:name":"Terry Renn",
    "wof:placetype":"venue"
},
  "geometry": {"coordinates":[-0.9621790051,51.4779815674],"type":"Point"}
}