{
  "type": "Feature",
  "properties": {
    "addr:full":"12 Harwood St Hartlepool Durham TS24 8QB",
    "addr:housenumber":"12",
    "addr:postcode":"ts24 8qb",
    "addr:street":"Harwood St",
    "iso:country":"GB",
    "sg:address":"12 Harwood St",
    "sg:city":"Hartlepool",
    "sg:classifiers":[
        {
            "category":"Sports & Exercise",
            "subcategory":"Tennis Court",
            "type":"Entertainment"
        }
    ],
    "sg:phone":"+44 1429 268715",
    "sg:postcode":"TS24 8QB",
    "sg:province":"Durham",
    "sg:tags":[
        "breakdown",
        "recovery"
    ],
    "wof:name":"Elite Mobile Vehicle Repairs",
    "wof:placetype":"venue"
},
  "geometry": {"coordinates":[-1.2219699621,54.6937675476],"type":"Point"}
}