{
  "type": "Feature",
  "properties": {
    "addr:full":"The Workshop, The Harbour Wall Margate Kent CT9 1JD",
    "addr:postcode":"ct9 1jd",
    "addr:street":"The Harbour Wall Margate",
    "iso:country":"GB",
    "sg:address":"The Workshop, The Harbour Wall",
    "sg:city":"Margate",
    "sg:classifiers":[
        {
            "category":"Home & Garden",
            "subcategory":"Building Materials",
            "type":"Retail Goods"
        }
    ],
    "sg:postcode":"CT9 1JD",
    "sg:province":"Kent",
    "sg:tags":[
        "ironwork",
        "diy",
        "wrought"
    ],
    "wof:name":"Jon Hone",
    "wof:placetype":"venue"
},
  "geometry": {"coordinates":[1.379247,51.386662],"type":"Point"}
}