{
  "type": "Feature",
  "properties": {
    "iso:country":"GB",
    "sg:address":"1a Langley High St",
    "sg:city":"Oldbury",
    "sg:classifiers":[
        {
            "category":"Food & Beverages",
            "subcategory":"Bakery",
            "type":"Retail Goods"
        }
    ],
    "sg:phone":"+44 121 544 5001",
    "sg:postcode":"B69 4SN",
    "sg:province":"West Midlands",
    "sg:tags":[
        "baker"
    ],
    "wof:name":"J S Conway",
    "wof:placetype":"venue"
},
  "geometry": {"coordinates":[-2.012685,52.491825],"type":"Point"}
}