{
  "type": "Feature",
  "properties": {
    "iso:country":"GB",
    "sg:address":"Butt Rd",
    "sg:city":"Colchester",
    "sg:classifiers":[
        {
            "category":"Sports & Exercise",
            "subcategory":"Stables",
            "type":"Entertainment"
        }
    ],
    "sg:phone":"+44 1206 540578",
    "sg:postcode":"CO2 7TE",
    "sg:province":"Essex",
    "sg:tags":[
        "education",
        "equestrian"
    ],
    "wof:name":"Colchester Garrison Saddle Club",
    "wof:placetype":"venue"
},
  "geometry": {"coordinates":[0.8946,51.885803],"type":"Point"}
}