{
  "type": "Feature",
  "properties": {
    "iso:country":"GB",
    "sg:address":"18 Cross Street",
    "sg:city":"Fraserburgh",
    "sg:classifiers":[
        {
            "category":"Food & Beverages",
            "subcategory":"Bakery",
            "type":"Retail Goods"
        }
    ],
    "sg:phone":"+44 1771 637241",
    "sg:postcode":"AB43 9EQ",
    "sg:province":"Aberdeenshire",
    "sg:tags":[
        "confectionery"
    ],
    "wof:name":"Murdoch Allan & Sons",
    "wof:placetype":"venue"
},
  "geometry": {"coordinates":[-2.00689,57.693283],"type":"Point"}
}