{
  "type": "Feature",
  "properties": {
    "addr:full":"Haydown Farm, East Cholderton Andover Hampshire SP11 8LR",
    "addr:postcode":"sp11 8lr",
    "addr:street":"East",
    "iso:country":"GB",
    "sg:address":"Haydown Farm, East Cholderton",
    "sg:city":"Andover",
    "sg:classifiers":[
        {
            "category":"Farming",
            "subcategory":"Dairy Farm",
            "type":"Manufacturing & Wholesale Goods"
        }
    ],
    "sg:phone":"+44 1264 772572",
    "sg:postcode":"SP11 8LR",
    "sg:province":"Hampshire",
    "wof:name":"Simon P Chesshire",
    "wof:placetype":"venue"
},
  "geometry": {"coordinates":[-1.5735759735,51.2036094666],"type":"Point"}
}