{
  "type": "Feature",
  "properties": {
    "addr:full":"2-3 Main Road, Gilwern Abergavenny Herefordshire NP7 0AU",
    "addr:housenumber":"2-3",
    "addr:postcode":"np7 0au",
    "addr:street":"Main Road",
    "iso:country":"GB",
    "sg:address":"2-3 Main Road, Gilwern",
    "sg:city":"Abergavenny",
    "sg:classifiers":[
        {
            "category":"Shopping",
            "subcategory":"Clothing, Apparel, & Fashions",
            "type":"Retail Goods"
        }
    ],
    "sg:postcode":"NP7 0AU",
    "sg:province":"Herefordshire",
    "sg:tags":[
        "ladieswear"
    ],
    "wof:name":"Jenallens",
    "wof:placetype":"venue"
},
  "geometry": {"coordinates":[-3.093924,51.824921],"type":"Point"}
}