{
  "type": "Feature",
  "properties": {
    "addr:full":"Amberley, Rodborough Common Stroud Gloucestershire GL5 5DB",
    "addr:postcode":"gl5 5db",
    "addr:street":"Common",
    "iso:country":"GB",
    "sg:address":"Amberley, Rodborough Common",
    "sg:city":"Stroud",
    "sg:classifiers":[
        {
            "category":"Education",
            "subcategory":"Special Training",
            "type":"Public Place"
        },
        {
            "category":"Education",
            "subcategory":"School",
            "type":"Public Place"
        }
    ],
    "sg:phone":"+44 1453 872536",
    "sg:postcode":"GL5 5DB",
    "sg:province":"Gloucestershire",
    "wof:name":"Amberley Ridge School",
    "wof:placetype":"venue"
},
  "geometry": {"coordinates":[-2.226962,51.710972],"type":"Point"}
}