{
  "type": "Feature",
  "properties": {
    "iso:country":"GB",
    "sg:address":"158 High Street",
    "sg:city":"Irvine",
    "sg:classifiers":[
        {
            "category":"Shopping",
            "subcategory":"Clothing, Apparel, & Fashions",
            "type":"Retail Goods"
        },
        {
            "category":"Manufacturing",
            "subcategory":"Paper Products",
            "type":"Manufacturing & Wholesale Goods"
        }
    ],
    "sg:phone":"+44 1294 271225",
    "sg:postcode":"KA12 8AN",
    "sg:province":"North Ayrshire",
    "sg:tags":[
        "t-shirt",
        "shirt",
        "manufacturer"
    ],
    "wof:name":"R J Paxton",
    "wof:placetype":"venue"
},
  "geometry": {"coordinates":[-4.6678209305,55.6158828735],"type":"Point"}
}