{
  "type": "Feature",
  "properties": {
    "addr:full":"Lovat Hall, Silver St Newport Pagnell Buckinghamshire MK16 0EJ",
    "addr:postcode":"mk16 0ej",
    "addr:street":"Silver St",
    "iso:country":"GB",
    "sg:address":"Lovat Hall, Silver St",
    "sg:city":"Newport Pagnell",
    "sg:classifiers":[
        {
            "category":"Place Of Worship",
            "type":"Public Place"
        }
    ],
    "sg:phone":"+44 1908 618898",
    "sg:postcode":"MK16 0EJ",
    "sg:province":"Buckinghamshire",
    "wof:name":"Newport Pagnell Baptist Church",
    "wof:placetype":"venue"
},
  "geometry": {"coordinates":[-0.7230190039,52.0866966248],"type":"Point"}
}