{
  "type": "Feature",
  "properties": {
    "iso:country":"GB",
    "sg:address":"Yew Cottage, Cherry Garden Lane",
    "sg:city":"Maidenhead",
    "sg:classifiers":[
        {
            "category":"Farming",
            "subcategory":"Nursery",
            "type":"Manufacturing & Wholesale Goods"
        },
        {
            "category":"Real Estate",
            "subcategory":"Real Estate Operator",
            "type":"Services"
        }
    ],
    "sg:phone":"+44 1628 823047",
    "sg:postcode":"SL6 3QD",
    "sg:province":"Berkshire",
    "sg:tags":[
        "leasing",
        "property",
        "creche"
    ],
    "wof:name":"CHANDOS ROAD RESIDENTS LTD",
    "wof:placetype":"venue"
},
  "geometry": {"coordinates":[-0.7761089802,51.5161933899],"type":"Point"}
}