{
  "type": "Feature",
  "properties": {
    "iso:country":"GB",
    "sg:address":"27 Pickard Street",
    "sg:city":"Warwick",
    "sg:classifiers":[
        {
            "category":"Bars & Pubs",
            "type":"Food & Drink"
        }
    ],
    "sg:postcode":"CV34 4PT",
    "sg:province":"Warwickshire",
    "sg:tags":[
        "pubs",
        "house",
        "inn",
        "public",
        "activity"
    ],
    "wof:name":"Avon Tavern",
    "wof:placetype":"venue"
},
  "geometry": {"coordinates":[-1.572077,52.284531],"type":"Point"}
}