{
  "type": "Feature",
  "properties": {
    "addr:full":"12 Wharfedale Rd Ipswich Suffolk IP1 4JP",
    "addr:housenumber":"12",
    "addr:postcode":"ip1 4jp",
    "addr:street":"Wharfedale Rd",
    "iso:country":"GB",
    "sg:address":"12 Wharfedale Rd",
    "sg:city":"Ipswich",
    "sg:classifiers":[
        {
            "category":"Food & Beverages",
            "subcategory":"Bakery",
            "type":"Retail Goods"
        }
    ],
    "sg:postcode":"IP1 4JP",
    "sg:province":"Suffolk",
    "sg:tags":[
        "confectionery"
    ],
    "wof:name":"Bloom 'N' Peck Bread Distribution",
    "wof:placetype":"venue"
},
  "geometry": {"coordinates":[1.142531991,52.0740585327],"type":"Point"}
}