{
  "type": "Feature",
  "properties": {
    "addr:full":"61a Gertrude Road Belvedere Kent DA17 5AS",
    "addr:housenumber":"61a",
    "addr:postcode":"da17 5as",
    "addr:street":"Gertrude Road",
    "iso:country":"GB",
    "sg:address":"61a Gertrude Road",
    "sg:city":"Belvedere",
    "sg:classifiers":[
        {
            "category":"Autos & Motor Vehicles",
            "subcategory":"Motorcycle Sales",
            "type":"Retail Goods"
        }
    ],
    "sg:phone":"+44 1322 430728",
    "sg:postcode":"DA17 5AS",
    "sg:province":"Kent",
    "sg:tags":[
        "chauffeur",
        "driven",
        "car"
    ],
    "wof:name":"Tim Holloway",
    "wof:placetype":"venue"
},
  "geometry": {"coordinates":[0.1487679929,51.4897613525],"type":"Point"}
}