{
  "type": "Feature",
  "properties": {
    "iso:country":"GB",
    "sg:address":"75 North Rd",
    "sg:city":"Brighton",
    "sg:classifiers":[
        {
            "category":"Bars & Pubs",
            "type":"Food & Drink"
        }
    ],
    "sg:phone":"+44 1273 624799",
    "sg:postcode":"BN1 1YD",
    "sg:province":"East Sussex",
    "sg:tags":[
        "pubs",
        "inn"
    ],
    "wof:name":"The Heart & Hand",
    "wof:placetype":"venue"
},
  "geometry": {"coordinates":[-0.139806,50.825798],"type":"Point"}
}