{
  "type": "Feature",
  "properties": {
    "addr:full":"12 Navigation Road Altrincham Cheshire WA14 1NF",
    "addr:housenumber":"12",
    "addr:postcode":"wa14 1nf",
    "addr:street":"Navigation Road",
    "iso:country":"GB",
    "sg:address":"12 Navigation Road",
    "sg:city":"Altrincham",
    "sg:classifiers":[
        {
            "category":"Personal",
            "subcategory":"Beauty Salon",
            "type":"Services"
        }
    ],
    "sg:postcode":"WA14 1NF",
    "sg:province":"Cheshire",
    "sg:tags":[
        "unisex",
        "hairdresser"
    ],
    "wof:name":"Classic Cutz",
    "wof:placetype":"venue"
},
  "geometry": {"coordinates":[-2.350183,53.397251],"type":"Point"}
}