{
  "type": "Feature",
  "properties": {
    "iso:country":"GB",
    "sg:address":", Lelant Downs",
    "sg:city":"Hayle",
    "sg:classifiers":[
        {
            "category":"Travel",
            "subcategory":"Hotels & Motels",
            "type":"Entertainment"
        }
    ],
    "sg:phone":"+44 1736 752243",
    "sg:postcode":"TR27 6LL",
    "sg:province":"Cornwall",
    "sg:tags":[
        "self",
        "catering"
    ],
    "wof:name":"Sunny Meadows Holiday Park",
    "wof:placetype":"venue"
},
  "geometry": {"coordinates":[-5.4633789062,50.1726760864],"type":"Point"}
}