{
  "type": "Feature",
  "properties": {
    "iso:country":"GB",
    "sg:address":"Unit 3, Redwood Business Park, Oldbury Road",
    "sg:city":"Smethwick",
    "sg:classifiers":[
        {
            "category":"Manufacturing",
            "subcategory":"Petroleum Products",
            "type":"Manufacturing & Wholesale Goods"
        }
    ],
    "sg:phone":"+44 121 555 6664",
    "sg:postcode":"B66 1NJ",
    "sg:province":"West Midlands",
    "sg:tags":[
        "double",
        "glazing"
    ],
    "wof:name":"Quay Plastics Distributors",
    "wof:placetype":"venue"
},
  "geometry": {"coordinates":[-1.9685640335,52.5032577515],"type":"Point"}
}