{
  "type": "Feature",
  "properties": {
    "addr:full":"64 Thanington Road Canterbury Kent CT1 3XE",
    "addr:housenumber":"64",
    "addr:postcode":"ct1 3xe",
    "addr:street":"Thanington Road",
    "iso:country":"GB",
    "sg:address":"64 Thanington Road",
    "sg:city":"Canterbury",
    "sg:classifiers":[
        {
            "category":"Professional",
            "subcategory":"Accounting & Tax Preparation",
            "type":"Services"
        }
    ],
    "sg:phone":"+44 1227 762750",
    "sg:postcode":"CT1 3XE",
    "sg:province":"Kent",
    "sg:tags":[
        "accountant",
        "activity"
    ],
    "wof:name":"Henry Reeves & Son",
    "wof:placetype":"venue"
},
  "geometry": {"coordinates":[1.056586,51.270042],"type":"Point"}
}