{
  "type": "Feature",
  "properties": {
    "addr:full":"30 Burnbank Road, Burnbank Hamilton South Lanarkshire ML3 9AA",
    "addr:housenumber":"30",
    "addr:postcode":"ml3 9aa",
    "addr:street":"Burnbank Road",
    "iso:country":"GB",
    "sg:address":"30 Burnbank Road, Burnbank",
    "sg:city":"Hamilton",
    "sg:classifiers":[
        {
            "category":"Farming",
            "subcategory":"Nursery",
            "type":"Manufacturing & Wholesale Goods"
        },
        {
            "category":"Education",
            "subcategory":"Preschool",
            "type":"Public Place"
        }
    ],
    "sg:phone":"+44 1698 424321",
    "sg:postcode":"ML3 9AA",
    "sg:province":"South Lanarkshire",
    "sg:tags":[
        "school",
        "creche"
    ],
    "wof:name":"A & B Education Ltd.",
    "wof:placetype":"venue"
},
  "geometry": {"coordinates":[-4.0560159683,55.7785987854],"type":"Point"}
}