{
  "type": "Feature",
  "properties": {
    "addr:full":"Old Brewery Building, 63 Union Street Stockport Cheshire SK1 3NP",
    "addr:housenumber":"63",
    "addr:postcode":"sk1 3np",
    "addr:street":"Old;Union Street",
    "iso:country":"GB",
    "sg:address":"Old Brewery Building, 63 Union Street",
    "sg:city":"Stockport",
    "sg:classifiers":[
        {
            "category":"Insurance",
            "subcategory":"Insurance Agent",
            "type":"Services"
        }
    ],
    "sg:phone":"+44 161 477 3944",
    "sg:postcode":"SK1 3NP",
    "sg:province":"Cheshire",
    "sg:tags":[
        "broker"
    ],
    "wof:name":"Chambers & Newman (Manchester) Ltd.",
    "wof:placetype":"venue"
},
  "geometry": {"coordinates":[-2.15693,53.403839],"type":"Point"}
}