{
  "type": "Feature",
  "properties": {
    "iso:country":"GB",
    "sg:address":"10 Lound Rd",
    "sg:city":"Kendal",
    "sg:classifiers":[
        {
            "category":"Manufacturing",
            "subcategory":"Signs",
            "type":"Manufacturing & Wholesale Goods"
        }
    ],
    "sg:phone":"+44 1539 737800",
    "sg:postcode":"LA9 7DT",
    "sg:province":"Cumbria",
    "sg:tags":[
        "maker"
    ],
    "wof:name":"Aztec Systems Uk",
    "wof:placetype":"venue"
},
  "geometry": {"coordinates":[-2.743389,54.320377],"type":"Point"}
}