{
  "type": "Feature",
  "properties": {
    "addr:full":"Edward Close Houndstone, Business Park, Houndstone Yeovil Dorset BA22 8RU",
    "addr:postcode":"ba22 8ru",
    "addr:street":"Edward Close Houndstone Business Park Houndstone",
    "iso:country":"GB",
    "sg:address":"Edward Close Houndstone, Business Park, Houndstone",
    "sg:city":"Yeovil",
    "sg:classifiers":[
        {
            "category":"Personal",
            "type":"Services"
        }
    ],
    "sg:phone":"+44 1935 432429",
    "sg:postcode":"BA22 8RU",
    "sg:province":"Dorset",
    "sg:tags":[
        "delivery"
    ],
    "wof:name":"White Arrow Parcels",
    "wof:placetype":"venue"
},
  "geometry": {"coordinates":[-2.6698150635,50.9451408386],"type":"Point"}
}