{
  "type": "Feature",
  "properties": {
    "iso:country":"GB",
    "sg:address":"22 Rathen Avenue, Ince",
    "sg:city":"Wigan",
    "sg:classifiers":[
        {
            "category":"Retail",
            "subcategory":"Driving School",
            "type":"Services"
        }
    ],
    "sg:phone":"+44 1942 239771",
    "sg:postcode":"WN2 2JR",
    "sg:province":"Lancashire",
    "wof:name":"Arnold Trimble Driving Institution",
    "wof:placetype":"venue"
},
  "geometry": {"coordinates":[-2.6020491123,53.5491523743],"type":"Point"}
}