{
  "type": "Feature",
  "properties": {
    "addr:full":"Marshall Road, Luncarty Perth Perth and Kinross PH1 3UT",
    "addr:postcode":"ph1 3ut",
    "addr:street":"Marshall Road",
    "iso:country":"GB",
    "sg:address":"Marshall Road, Luncarty",
    "sg:city":"Perth",
    "sg:classifiers":[
        {
            "category":"Education",
            "subcategory":"School",
            "type":"Public Place"
        }
    ],
    "sg:postcode":"PH1 3UT",
    "sg:province":"Perth and Kinross",
    "sg:tags":[
        "local",
        "authority"
    ],
    "wof:name":"Luncarty Primary School",
    "wof:placetype":"venue"
},
  "geometry": {"coordinates":[-3.470336,56.453316],"type":"Point"}
}