{
  "type": "Feature",
  "properties": {
    "addr:full":"43 Kirkby Rd Sutton In Ashfield Nottinghamshire NG17 1GG",
    "addr:housenumber":"43",
    "addr:postcode":"ng17 1gg",
    "addr:street":"Kirkby Rd",
    "iso:country":"GB",
    "sg:address":"43 Kirkby Rd",
    "sg:city":"Sutton In Ashfield",
    "sg:classifiers":[
        {
            "category":"Shopping",
            "subcategory":"Clothing, Apparel, & Fashions",
            "type":"Retail Goods"
        }
    ],
    "sg:phone":"+44 1623 550810",
    "sg:postcode":"NG17 1GG",
    "sg:province":"Nottinghamshire",
    "sg:tags":[
        "lingerie"
    ],
    "wof:name":"P & M Hardstaff",
    "wof:placetype":"venue"
},
  "geometry": {"coordinates":[-1.2667410374,53.1206474304],"type":"Point"}
}