{
  "type": "Feature",
  "properties": {
    "iso:country":"GB",
    "sg:address":"Unit 8 Tanners Brook Way, Millbrook",
    "sg:city":"Southampton",
    "sg:classifiers":[
        {
            "category":"Shopping",
            "subcategory":"Discount & Variety Stores",
            "type":"Retail Goods"
        }
    ],
    "sg:phone":"+44 23 8077 4646",
    "sg:postcode":"SO15 0JY",
    "sg:province":"Hampshire",
    "sg:tags":[
        "cleaning",
        "supply"
    ],
    "wof:name":"Nu Link Supplies",
    "wof:placetype":"venue"
},
  "geometry": {"coordinates":[-1.4518740177,50.9136810303],"type":"Point"}
}