{
  "type": "Feature",
  "properties": {
    "addr:full":"28 Old Brompton Rd South Kensington Greater London SW7 3DQ",
    "addr:housenumber":"28",
    "addr:postcode":"sw7 3dq",
    "addr:street":"Old Brompton Rd",
    "iso:country":"GB",
    "sg:address":"28 Old Brompton Rd",
    "sg:city":"South Kensington",
    "sg:classifiers":[
        {
            "category":"Personal",
            "type":"Services"
        }
    ],
    "sg:phone":"+44 20 7384 3779",
    "sg:postcode":"SW7 3DQ",
    "sg:province":"Greater London",
    "sg:tags":[
        "party",
        "organiser"
    ],
    "wof:name":"Bose Hewitt Management",
    "wof:placetype":"venue"
},
  "geometry": {"coordinates":[-0.17522,51.493603],"type":"Point"}
}