{
  "type": "Feature",
  "properties": {
    "iso:country":"GB",
    "sg:address":"Rooks Acre, Scaynes Hill Road, Walstead",
    "sg:city":"Haywards Heath",
    "sg:classifiers":[
        {
            "category":"Professional",
            "subcategory":"Engineering",
            "type":"Services"
        }
    ],
    "sg:phone":"+44 1444 483854",
    "sg:postcode":"RH16 2QQ",
    "sg:province":"East Sussex",
    "sg:tags":[
        "contractor",
        "electrical",
        "engineer"
    ],
    "wof:name":"Cassam Electrical Services",
    "wof:placetype":"venue"
},
  "geometry": {"coordinates":[-0.07099,51.004959],"type":"Point"}
}