{
  "type": "Feature",
  "properties": {
    "addr:full":"15 Cairniehill Gardens Arbroath Angus DD11 4EP",
    "addr:housenumber":"15",
    "addr:postcode":"dd11 4ep",
    "addr:street":"Cairniehill Gardens",
    "iso:country":"GB",
    "sg:address":"15 Cairniehill Gardens",
    "sg:city":"Arbroath",
    "sg:classifiers":[
        {
            "category":"Professional",
            "subcategory":"Art Services",
            "type":"Services"
        }
    ],
    "sg:phone":"+44 1241 872844",
    "sg:postcode":"DD11 4EP",
    "sg:province":"Angus",
    "sg:tags":[
        "framing",
        "artist"
    ],
    "wof:name":"Frank McDiarmid",
    "wof:placetype":"venue"
},
  "geometry": {"coordinates":[-2.5959749222,56.5649604797],"type":"Point"}
}