{
  "type": "Feature",
  "properties": {
    "addr:full":"27 Willow Grn Knutsford Cheshire WA16 6AX",
    "addr:housenumber":"27",
    "addr:postcode":"willow;wa16 6ax",
    "iso:country":"GB",
    "sg:address":"27 Willow Grn",
    "sg:city":"Knutsford",
    "sg:classifiers":[
        {
            "category":"Shopping",
            "subcategory":"Catalog Store",
            "type":"Retail Goods"
        }
    ],
    "sg:postcode":"WA16 6AX",
    "sg:province":"Cheshire",
    "sg:tags":[
        "mail",
        "order"
    ],
    "wof:name":"Heebee Designs",
    "wof:placetype":"venue"
},
  "geometry": {"coordinates":[-2.3808429241,53.3099327087],"type":"Point"}
}