{
  "type": "Feature",
  "properties": {
    "iso:country":"GB",
    "sg:address":"School House, London Road",
    "sg:city":"Hook",
    "sg:classifiers":[
        {
            "category":"Taxi",
            "type":"Transportation"
        }
    ],
    "sg:phone":"+44 1256 702345",
    "sg:postcode":"RG29 1AJ",
    "sg:province":"Hampshire",
    "sg:tags":[
        "mini",
        "cab"
    ],
    "wof:name":"Nairn's Cars",
    "wof:placetype":"venue"
},
  "geometry": {"coordinates":[-0.9287779927,51.2629203796],"type":"Point"}
}