{
  "type": "Feature",
  "properties": {
    "addr:full":"4 Churchgate Street, Soham Ely Cambridgeshire CB7 5DR",
    "addr:housenumber":"4",
    "addr:postcode":"cb7 5dr",
    "addr:street":"Churchgate Street",
    "iso:country":"GB",
    "sg:address":"4 Churchgate Street, Soham",
    "sg:city":"Ely",
    "sg:classifiers":[
        {
            "category":"Food & Beverages",
            "subcategory":"Fruits & Vegetables",
            "type":"Retail Goods"
        }
    ],
    "sg:phone":"+44 1353 723161",
    "sg:postcode":"CB7 5DR",
    "sg:province":"Cambridgeshire",
    "sg:tags":[
        "greengrocer"
    ],
    "wof:name":"Palmers Fruit Shop",
    "wof:placetype":"venue"
},
  "geometry": {"coordinates":[0.3374800086,52.3339881897],"type":"Point"}
}