{
  "type": "Feature",
  "properties": {
    "iso:country":"GB",
    "sg:address":"Heartsease Post Office 3-5",
    "sg:city":"Norwich",
    "sg:classifiers":[
        {
            "category":"Government",
            "subcategory":"Post Office",
            "type":"Public Place"
        }
    ],
    "sg:phone":"+44 1603 434656",
    "sg:postcode":"NR7 9AA",
    "sg:province":"Norfolk",
    "wof:name":"Heartsease Post Office",
    "wof:placetype":"venue"
},
  "geometry": {"coordinates":[1.3320399523,52.6451911926],"type":"Point"}
}