{
  "type": "Feature",
  "properties": {
    "addr:full":"Riverside Road, Tean Stoke-on-trent Staffordshire ST10 4JW",
    "addr:postcode":"st10 4jw",
    "addr:street":"Riverside Road",
    "iso:country":"GB",
    "sg:address":"Riverside Road, Tean",
    "sg:city":"Stoke-on-trent",
    "sg:classifiers":[
        {
            "category":"Farming",
            "subcategory":"Farm",
            "type":"Manufacturing & Wholesale Goods"
        }
    ],
    "sg:phone":"+44 1538 722328",
    "sg:postcode":"ST10 4JW",
    "sg:province":"Staffordshire",
    "sg:tags":[
        "mixed",
        "crop"
    ],
    "wof:name":"A J Minshall",
    "wof:placetype":"venue"
},
  "geometry": {"coordinates":[-1.9897090197,52.9536857605],"type":"Point"}
}