{
  "type": "Feature",
  "properties": {
    "addr:full":"14 Bedford Way North Shields Tyne and Wear NE29 6RX",
    "addr:housenumber":"14",
    "addr:postcode":"ne29 6rx",
    "addr:street":"Bedford Way",
    "iso:country":"GB",
    "sg:address":"14 Bedford Way",
    "sg:city":"North Shields",
    "sg:classifiers":[
        {
            "category":"Travel",
            "subcategory":"Travel Agent",
            "type":"Entertainment"
        }
    ],
    "sg:phone":"+44 191 258 3690",
    "sg:postcode":"NE29 6RX",
    "sg:province":"Tyne and Wear",
    "sg:tags":[
        "agency",
        "activity"
    ],
    "wof:name":"Dawson & Sanderson Ltd",
    "wof:placetype":"venue"
},
  "geometry": {"coordinates":[-1.446489,55.008369],"type":"Point"}
}