{
  "type": "Feature",
  "properties": {
    "addr:full":"156 Goldhawk Road London Greater London W12 8HJ",
    "addr:housenumber":"156",
    "addr:postcode":"w12 8hj",
    "addr:street":"Goldhawk Road",
    "iso:country":"GB",
    "sg:address":"156 Goldhawk Road",
    "sg:city":"London",
    "sg:classifiers":[
        {
            "category":"Home & Garden",
            "subcategory":"Carpets & Floor Coverings",
            "type":"Retail Goods"
        }
    ],
    "sg:phone":"+44 20 8749 9340",
    "sg:postcode":"W12 8HJ",
    "sg:province":"Greater London",
    "sg:tags":[
        "carpets",
        "retailer",
        "rug",
        "matting"
    ],
    "wof:name":"The Carpet Store",
    "wof:placetype":"venue"
},
  "geometry": {"coordinates":[-0.232189998,51.5014381409],"type":"Point"}
}