{
  "type": "Feature",
  "properties": {
    "iso:country":"GB",
    "sg:address":"Castlemartin",
    "sg:city":"Pembroke",
    "sg:classifiers":[
        {
            "category":"Place Of Worship",
            "type":"Public Place"
        }
    ],
    "sg:phone":"+44 1646 641368",
    "sg:postcode":"SA71 5AN",
    "sg:province":"Pembrokeshire",
    "wof:name":"St Michaels & All Angels",
    "wof:placetype":"venue"
},
  "geometry": {"coordinates":[-5.0174088478,51.645816803],"type":"Point"}
}