{
  "type": "Feature",
  "properties": {
    "addr:full":"68 Wavell Road Maidenhead Berkshire SL6 5AD",
    "addr:housenumber":"68",
    "addr:postcode":"sl6 5ad",
    "addr:street":"Wavell Road",
    "iso:country":"GB",
    "sg:address":"68 Wavell Road",
    "sg:city":"Maidenhead",
    "sg:classifiers":[
        {
            "category":"Building & Trades",
            "subcategory":"Construction",
            "type":"Services"
        }
    ],
    "sg:phone":"+44 1628 628851",
    "sg:postcode":"SL6 5AD",
    "sg:province":"Berkshire",
    "sg:tags":[
        "builder"
    ],
    "wof:name":"Brian F Maidment",
    "wof:placetype":"venue"
},
  "geometry": {"coordinates":[-0.750809,51.519779],"type":"Point"}
}