{
  "type": "Feature",
  "properties": {
    "addr:full":"673 Leeds Road Dewsbury West Yorkshire WF12 7HP",
    "addr:housenumber":"673",
    "addr:postcode":"wf12 7hp",
    "addr:street":"Leeds Road",
    "iso:country":"GB",
    "sg:address":"673 Leeds Road",
    "sg:city":"Dewsbury",
    "sg:classifiers":[
        {
            "category":"Personal",
            "subcategory":"Beauty Salon",
            "type":"Services"
        }
    ],
    "sg:postcode":"WF12 7HP",
    "sg:province":"West Yorkshire",
    "sg:tags":[
        "unisex",
        "hairdresser"
    ],
    "wof:name":"Scruples Hair Studio",
    "wof:placetype":"venue"
},
  "geometry": {"coordinates":[-1.603866,53.703907],"type":"Point"}
}