{
  "type": "Feature",
  "properties": {
    "addr:full":"19 Sambridge Rd Dagenham Essex RM8 1NS",
    "addr:housenumber":"19",
    "addr:postcode":"rm8 1ns",
    "addr:street":"Sambridge Rd",
    "iso:country":"GB",
    "sg:address":"19 Sambridge Rd",
    "sg:city":"Dagenham",
    "sg:classifiers":[
        {
            "category":"Building & Trades",
            "subcategory":"Construction",
            "type":"Services"
        }
    ],
    "sg:postcode":"RM8 1NS",
    "sg:province":"Essex",
    "sg:tags":[
        "glass",
        "replacement"
    ],
    "wof:name":"Gladden,John,",
    "wof:placetype":"venue"
},
  "geometry": {"coordinates":[0.1504500061,51.5660018921],"type":"Point"}
}