{
  "type": "Feature",
  "properties": {
    "iso:country":"GB",
    "sg:address":"65 Heanor Road, Codnor",
    "sg:city":"Ripley",
    "sg:classifiers":[
        {
            "category":"Personal",
            "subcategory":"Beauty Salon",
            "type":"Services"
        }
    ],
    "sg:phone":"+44 1773 742636",
    "sg:postcode":"DE5 9SF",
    "sg:province":"Derbyshire",
    "sg:tags":[
        "unisex",
        "hairdresser"
    ],
    "wof:name":"Shirleys",
    "wof:placetype":"venue"
},
  "geometry": {"coordinates":[-1.37508,53.040977],"type":"Point"}
}