{
  "type": "Feature",
  "properties": {
    "addr:full":"6-7 St Georges Terrace, St James Square Cheltenham Gloucestershire GL50 3PR",
    "addr:housenumber":"6-7",
    "addr:postcode":"gl50 3pr",
    "addr:street":"St Georges Terrace St James Square",
    "iso:country":"GB",
    "sg:address":"6-7 St Georges Terrace, St James Square",
    "sg:city":"Cheltenham",
    "sg:classifiers":[
        {
            "category":"Real Estate",
            "subcategory":"Surveying",
            "type":"Services"
        }
    ],
    "sg:phone":"+44 1242 522822",
    "sg:postcode":"GL50 3PR",
    "sg:province":"Gloucestershire",
    "sg:tags":[
        "surveyor",
        "valuer"
    ],
    "wof:name":"Evans Jones & Partners",
    "wof:placetype":"venue"
},
  "geometry": {"coordinates":[-2.0778670311,51.9019050598],"type":"Point"}
}