{
  "type": "Feature",
  "properties": {
    "addr:full":"10 Cross Keys Mews, Market Square St Neots Bedfordshire PE19 2AR",
    "addr:housenumber":"10",
    "addr:postcode":"pe19 2ar",
    "addr:street":"Cross Keys Mews Market Square",
    "iso:country":"GB",
    "sg:address":"10 Cross Keys Mews, Market Square",
    "sg:city":"St Neots",
    "sg:classifiers":[
        {
            "category":"Shopping",
            "subcategory":"Hobbies, Toys, & Games",
            "type":"Retail Goods"
        }
    ],
    "sg:phone":"+44 1480 403580",
    "sg:postcode":"PE19 2AR",
    "sg:province":"Bedfordshire",
    "sg:tags":[
        "collectors'",
        "item"
    ],
    "wof:name":"Peggies Pandora",
    "wof:placetype":"venue"
},
  "geometry": {"coordinates":[-0.2716200054,52.2277297974],"type":"Point"}
}