{
  "type": "Feature",
  "properties": {
    "iso:country":"GB",
    "sg:address":"Fircroft Way",
    "sg:city":"Edenbridge",
    "sg:classifiers":[
        {
            "category":"Professional",
            "type":"Services"
        }
    ],
    "sg:phone":"+44 1732 863666",
    "sg:postcode":"TN8 6ET",
    "sg:province":"East Sussex",
    "sg:tags":[
        "display",
        "maker"
    ],
    "wof:name":"Standeasy Modular Display Systems Ltd.",
    "wof:placetype":"venue"
},
  "geometry": {"coordinates":[0.064218,51.20673],"type":"Point"}
}