{
  "type": "Feature",
  "properties": {
    "iso:country":"GB",
    "sg:address":"10 Berrington Street",
    "sg:city":"Hereford",
    "sg:classifiers":[
        {
            "category":"Professional",
            "subcategory":"Art Services",
            "type":"Services"
        }
    ],
    "sg:postcode":"HR4 0BJ",
    "sg:province":"Herefordshire",
    "sg:tags":[
        "photographer"
    ],
    "wof:name":"Graham Wilson Photography",
    "wof:placetype":"venue"
},
  "geometry": {"coordinates":[-2.719095,52.055866],"type":"Point"}
}