{
  "type": "Feature",
  "properties": {
    "addr:full":"29 Finlayson Dr Airdrie North Lanarkshire ML6 8LU",
    "addr:housenumber":"29",
    "addr:postcode":"ml6 8lu",
    "addr:street":"Finlayson Dr",
    "iso:country":"GB",
    "sg:address":"29 Finlayson Dr",
    "sg:city":"Airdrie",
    "sg:classifiers":[
        {
            "category":"Professional",
            "subcategory":"Printing & Photocopies",
            "type":"Services"
        }
    ],
    "sg:phone":"+44 1236 755562",
    "sg:postcode":"ML6 8LU",
    "sg:province":"North Lanarkshire",
    "sg:tags":[
        "printer"
    ],
    "wof:name":"Monklands Instant Print",
    "wof:placetype":"venue"
},
  "geometry": {"coordinates":[-3.9456090927,55.8664283752],"type":"Point"}
}