{
  "type": "Feature",
  "properties": {
    "iso:country":"GB",
    "sg:address":"1 Crown Ct, The Square",
    "sg:city":"Wimborne",
    "sg:classifiers":[
        {
            "category":"Shopping",
            "subcategory":"Department Store",
            "type":"Retail Goods"
        }
    ],
    "sg:postcode":"BH21 1LP",
    "sg:province":"Dorset",
    "wof:name":"Fayfield Ltd",
    "wof:placetype":"venue"
},
  "geometry": {"coordinates":[-1.987334,50.800652],"type":"Point"}
}