{
  "type": "Feature",
  "properties": {
    "iso:country":"GB",
    "sg:address":"Milton Farm, Balmullo",
    "sg:city":"St Andrews",
    "sg:classifiers":[
        {
            "category":"Farming",
            "subcategory":"Livestock Farm",
            "type":"Manufacturing & Wholesale Goods"
        }
    ],
    "sg:phone":"+44 1334 839281",
    "sg:postcode":"KY16 0AB",
    "sg:province":"Fife",
    "sg:tags":[
        "others"
    ],
    "wof:name":"Alexander Black",
    "wof:placetype":"venue"
},
  "geometry": {"coordinates":[-2.8997499943,56.3740386963],"type":"Point"}
}