{
  "type": "Feature",
  "properties": {
    "addr:full":"Fennant Road, Ponciau Wrexham Wrexham LL14 1HL",
    "addr:postcode":"ll14 1hl",
    "addr:street":"Fennant Road Ponciau",
    "iso:country":"GB",
    "sg:address":"Fennant Road, Ponciau",
    "sg:city":"Wrexham",
    "sg:classifiers":[
        {
            "category":"Bars & Pubs",
            "type":"Food & Drink"
        }
    ],
    "sg:phone":"+44 1978 840122",
    "sg:postcode":"LL14 1HL",
    "sg:province":"Wrexham",
    "sg:tags":[
        "pubs",
        "inn"
    ],
    "wof:name":"The Royal Oak",
    "wof:placetype":"venue"
},
  "geometry": {"coordinates":[-3.0522589684,53.0142211914],"type":"Point"}
}