{
  "type": "Feature",
  "properties": {
    "iso:country":"GB",
    "sg:address":"Westmill Farm, Westmill Lane, Ickleford",
    "sg:city":"Hitchin",
    "sg:classifiers":[
        {
            "category":"Home & Garden",
            "subcategory":"Garden Supply",
            "type":"Retail Goods"
        },
        {
            "category":"Farming",
            "subcategory":"Livestock Farm",
            "type":"Manufacturing & Wholesale Goods"
        }
    ],
    "sg:phone":"+44 1462 459596",
    "sg:postcode":"SG5 3RP",
    "sg:province":"Bedfordshire",
    "sg:tags":[
        "bulb",
        "grower",
        "others"
    ],
    "wof:name":"Roland A Peach",
    "wof:placetype":"venue"
},
  "geometry": {"coordinates":[-0.2872090042,51.9678039551],"type":"Point"}
}