{
  "type": "Feature",
  "properties": {
    "addr:full":"5th Floor, Silver City House London Greater London SW3 1BW",
    "addr:housenumber":"5th floor silver",
    "addr:postcode":"sw3 1bw",
    "iso:country":"GB",
    "sg:address":"5th Floor, Silver City House",
    "sg:city":"London",
    "sg:classifiers":[
        {
            "category":"Professional",
            "subcategory":"Management & Consulting",
            "type":"Services"
        }
    ],
    "sg:postcode":"SW3 1BW",
    "sg:province":"Greater London",
    "sg:tags":[
        "consultant",
        "business"
    ],
    "wof:name":"Central Europe Trust Co. Ltd.",
    "wof:placetype":"venue"
},
  "geometry": {"coordinates":[-0.1624599993,51.500579834],"type":"Point"}
}