{
  "type": "Feature",
  "properties": {
    "iso:country":"GB",
    "sg:address":"4 Risedale Road",
    "sg:city":"Barrow-in-furness",
    "sg:classifiers":[
        {
            "category":"Shopping",
            "subcategory":"Baby Store",
            "type":"Retail Goods"
        }
    ],
    "sg:postcode":"LA13 9RD",
    "sg:province":"Cumbria",
    "sg:tags":[
        "babywear",
        "childrens"
    ],
    "wof:name":"Jacquelines",
    "wof:placetype":"venue"
},
  "geometry": {"coordinates":[-3.2079610825,54.1112060547],"type":"Point"}
}