{
  "type": "Feature",
  "properties": {
    "addr:full":"Unit 9, Baileygate Industrial Estate Pontefract North Yorkshire WF8 2LN",
    "addr:housenumber":"unit 9",
    "addr:postcode":"wf8 2ln",
    "addr:street":"Baileygate Industrial Estate",
    "iso:country":"GB",
    "sg:address":"Unit 9, Baileygate Industrial Estate",
    "sg:city":"Pontefract",
    "sg:classifiers":[
        {
            "category":"Recreation",
            "subcategory":"Amusement Park",
            "type":"Entertainment"
        }
    ],
    "sg:phone":"+44 1977 704241",
    "sg:postcode":"WF8 2LN",
    "sg:province":"North Yorkshire",
    "sg:tags":[
        "arcade"
    ],
    "wof:name":"Aristomatics (Pontefract) Ltd.",
    "wof:placetype":"venue"
},
  "geometry": {"coordinates":[-1.3014039993,53.6962928772],"type":"Point"}
}