{
  "type": "Feature",
  "properties": {
    "iso:country":"GB",
    "sg:address":"97 Ivy Rd",
    "sg:city":"Northampton",
    "sg:classifiers":[
        {
            "category":"Organizations",
            "subcategory":"Membership Organization",
            "type":"Services"
        }
    ],
    "sg:postcode":"NN1 4QS",
    "sg:province":"Northamptonshire",
    "sg:tags":[
        "club"
    ],
    "wof:name":"Northampton Scout Shop",
    "wof:placetype":"venue"
},
  "geometry": {"coordinates":[-0.878025,52.249268],"type":"Point"}
}