{
  "type": "Feature",
  "properties": {
    "iso:country":"GB",
    "sg:address":"28 Lanark Road",
    "sg:city":"Edinburgh",
    "sg:classifiers":[
        {
            "category":"Arena",
            "subcategory":"Sports Club",
            "type":"Entertainment"
        }
    ],
    "sg:phone":"+44 131 443 7663",
    "sg:postcode":"EH14 1TH",
    "sg:province":"City of Edinburgh",
    "wof:name":"Slateford Bowling Club",
    "wof:placetype":"venue"
},
  "geometry": {"coordinates":[-3.248973,55.923103],"type":"Point"}
}