{
  "type": "Feature",
  "properties": {
    "addr:full":"Enquiries, 235 East Barnet Rd Barnet Hertfordshire EN4 8SS",
    "addr:housenumber":"235",
    "addr:postcode":"en4 8ss",
    "addr:street":"East Barnet Rd",
    "iso:country":"GB",
    "sg:address":"Enquiries, 235 East Barnet Rd",
    "sg:city":"Barnet",
    "sg:classifiers":[
        {
            "category":"Manufacturing",
            "subcategory":"Tools & Machinery",
            "type":"Manufacturing & Wholesale Goods"
        }
    ],
    "sg:phone":"+44 20 8275 0990",
    "sg:postcode":"EN4 8SS",
    "sg:province":"Hertfordshire",
    "sg:tags":[
        "society",
        "friendly"
    ],
    "wof:name":"Scott & Casey",
    "wof:placetype":"venue"
},
  "geometry": {"coordinates":[-0.161705,51.644211],"type":"Point"}
}