{
  "type": "Feature",
  "properties": {
    "addr:full":"Unit 12 Rangemoor Industrial Area, Rangemoor Road London Greater London N15 4LX",
    "addr:housenumber":"unit 12",
    "addr:postcode":"n15 4lx",
    "addr:street":"Rangemoor Industrial Area Rangemoor Road",
    "iso:country":"GB",
    "sg:address":"Unit 12 Rangemoor Industrial Area, Rangemoor Road",
    "sg:city":"London",
    "sg:classifiers":[
        {
            "category":"Home & Garden",
            "subcategory":"Household Appliances",
            "type":"Retail Goods"
        }
    ],
    "sg:phone":"+44 20 8801 6235",
    "sg:postcode":"N15 4LX",
    "sg:province":"Greater London",
    "sg:tags":[
        "equipment",
        "electrical",
        "air conditioning"
    ],
    "wof:name":"Control Center",
    "wof:placetype":"venue"
},
  "geometry": {"coordinates":[-0.0690800026,51.5817718506],"type":"Point"}
}