{
  "type": "Feature",
  "properties": {
    "iso:country":"GB",
    "sg:address":"Broadcasting Ho, Newport Rd",
    "sg:city":"Middlesbrough",
    "sg:classifiers":[
        {
            "category":"Wholesale",
            "subcategory":"Books, Periodicals, & Newspapers",
            "type":"Manufacturing & Wholesale Goods"
        }
    ],
    "sg:postcode":"TS1 5JA",
    "sg:province":"North Yorkshire",
    "sg:tags":[
        "publishing"
    ],
    "wof:name":"Arete Publishing & Design",
    "wof:placetype":"venue"
},
  "geometry": {"coordinates":[-1.236569,54.572971],"type":"Point"}
}