{
  "type": "Feature",
  "properties": {
    "addr:full":"98 Edgewood Road, Rednal Birmingham West Midlands B45 8SG",
    "addr:housenumber":"98",
    "addr:postcode":"b45 8sg",
    "addr:street":"Edgewood Road",
    "iso:country":"GB",
    "sg:address":"98 Edgewood Road, Rednal",
    "sg:city":"Birmingham",
    "sg:classifiers":[
        {
            "category":"Shopping",
            "subcategory":"Gifts & Souvenirs",
            "type":"Retail Goods"
        }
    ],
    "sg:phone":"+44 121 453 2606",
    "sg:postcode":"B45 8SG",
    "sg:province":"West Midlands",
    "sg:tags":[
        "poster",
        "card"
    ],
    "wof:name":"Edgewood Road Sub Post Office",
    "wof:placetype":"venue"
},
  "geometry": {"coordinates":[-2.003237009,52.3906135559],"type":"Point"}
}