{
  "type": "Feature",
  "properties": {
    "iso:country":"GB",
    "sg:address":"28 Coronation St",
    "sg:city":"Barnstaple",
    "sg:classifiers":[
        {
            "category":"Manufacturing",
            "subcategory":"Metals",
            "type":"Manufacturing & Wholesale Goods"
        },
        {
            "category":"Utilities",
            "subcategory":"Natural Gas",
            "type":"Services"
        }
    ],
    "sg:postcode":"EX32 7AY",
    "sg:province":"Devon",
    "sg:tags":[
        "supplier",
        "steel",
        "stockholder"
    ],
    "wof:name":"Storey,Chris,",
    "wof:placetype":"venue"
},
  "geometry": {"coordinates":[-4.057667,51.083965],"type":"Point"}
}