{
  "type": "Feature",
  "properties": {
    "iso:country":"GB",
    "sg:address":"20 Bytham Heights, Castle Bytham",
    "sg:city":"Grantham",
    "sg:classifiers":[
        {
            "category":"Professional",
            "subcategory":"Computer Services",
            "type":"Services"
        }
    ],
    "sg:phone":"+44 1780 410847",
    "sg:postcode":"NG33 4ST",
    "sg:province":"Leicestershire",
    "sg:tags":[
        "system",
        "software"
    ],
    "wof:name":"Firstworld Systems Ltd.",
    "wof:placetype":"venue"
},
  "geometry": {"coordinates":[-0.5371159911,52.7545433044],"type":"Point"}
}