{
  "type": "Feature",
  "properties": {
    "addr:full":"Unit 44 Barns Court, Turners Hill Rd Crawley Surrey RH10 4HQ",
    "addr:housenumber":"unit 44",
    "addr:postcode":"rh10 4hq",
    "addr:street":"Barns Court Turners Hill Rd",
    "iso:country":"GB",
    "sg:address":"Unit 44 Barns Court, Turners Hill Rd",
    "sg:city":"Crawley",
    "sg:classifiers":[
        {
            "category":"Professional",
            "subcategory":"Printing & Photocopies",
            "type":"Services"
        }
    ],
    "sg:phone":"+44 1342 715717",
    "sg:postcode":"RH10 4HQ",
    "sg:province":"Surrey",
    "sg:tags":[
        "printer"
    ],
    "wof:name":"Inspired Printing",
    "wof:placetype":"venue"
},
  "geometry": {"coordinates":[-0.0923480019,51.1326560974],"type":"Point"}
}