{
  "type": "Feature",
  "properties": {
    "addr:full":"Westward House, Cross Lane, Marple Stockport Cheshire SK6 7QD",
    "addr:postcode":"sk6 7qd",
    "addr:street":"Cross Lane",
    "iso:country":"GB",
    "sg:address":"Westward House, Cross Lane, Marple",
    "sg:city":"Stockport",
    "sg:classifiers":[
        {
            "category":"Autos & Motor Vehicles",
            "subcategory":"Automobile Sales",
            "type":"Retail Goods"
        },
        {
            "category":"Insurance",
            "subcategory":"Insurance Agent",
            "type":"Services"
        }
    ],
    "sg:phone":"+44 161 449 7000",
    "sg:postcode":"SK6 7QD",
    "sg:province":"Cheshire",
    "sg:tags":[
        "car"
    ],
    "wof:name":"Motor & Legal Group Ltd.",
    "wof:placetype":"venue"
},
  "geometry": {"coordinates":[-2.0736479759,53.3931999207],"type":"Point"}
}