{
  "type": "Feature",
  "properties": {
    "addr:full":"32a Vicar Street Falkirk Falkirk FK1 1JB",
    "addr:housenumber":"32a",
    "addr:postcode":"fk1 1jb",
    "addr:street":"Vicar Street",
    "iso:country":"GB",
    "sg:address":"32a Vicar Street",
    "sg:city":"Falkirk",
    "sg:classifiers":[
        {
            "category":"Sports & Exercise",
            "subcategory":"Gym",
            "type":"Entertainment"
        }
    ],
    "sg:phone":"+44 1324 610022",
    "sg:postcode":"FK1 1JB",
    "sg:province":"Falkirk",
    "sg:tags":[
        "fitness",
        "health",
        "centre"
    ],
    "wof:name":"Callanetics Studio Central Ltd.",
    "wof:placetype":"venue"
},
  "geometry": {"coordinates":[-3.7846360207,56.001121521],"type":"Point"}
}