{
  "type": "Feature",
  "properties": {
    "iso:country":"GB",
    "sg:address":"5 Hamilton St",
    "sg:city":"Birkenhead",
    "sg:classifiers":[
        {
            "category":"Personal",
            "subcategory":"Beauty Salon",
            "type":"Services"
        }
    ],
    "sg:phone":"+44 151 650 1196",
    "sg:postcode":"L41 6DL",
    "sg:province":"Merseyside",
    "sg:tags":[
        "unisex",
        "hairdresser"
    ],
    "wof:name":"Hair Society",
    "wof:placetype":"venue"
},
  "geometry": {"coordinates":[-3.015036,53.394146],"type":"Point"}
}