{
  "type": "Feature",
  "properties": {
    "addr:full":"Strait La Darlington Durham DL2 1QJ",
    "addr:postcode":"dl2 1qj",
    "iso:country":"GB",
    "sg:address":"Strait La",
    "sg:city":"Darlington",
    "sg:classifiers":[
        {
            "category":"Transit Center",
            "subcategory":"Passenger",
            "type":"Transportation"
        }
    ],
    "sg:phone":"+44 1325 720672",
    "sg:postcode":"DL2 1QJ",
    "sg:province":"Durham",
    "sg:tags":[
        "boarding",
        "kennel",
        "catteries"
    ],
    "wof:name":"Four Winds Boarding Kennels",
    "wof:placetype":"venue"
},
  "geometry": {"coordinates":[-1.520923,54.494865],"type":"Point"}
}