{
  "type": "Feature",
  "properties": {
    "addr:full":"Station Road, Drigg Holmrook Cumbria CA19 1XQ",
    "addr:postcode":"ca19 1xq",
    "addr:street":"Station Road",
    "iso:country":"GB",
    "sg:address":"Station Road, Drigg",
    "sg:city":"Holmrook",
    "sg:classifiers":[
        {
            "category":"Travel",
            "subcategory":"Hotels & Motels",
            "type":"Entertainment"
        }
    ],
    "sg:phone":"+44 19467 24231",
    "sg:postcode":"CA19 1XQ",
    "sg:province":"Cumbria",
    "wof:name":"YICTORIA HOTEL",
    "wof:placetype":"venue"
},
  "geometry": {"coordinates":[-3.41979599,54.3854026794],"type":"Point"}
}