{
  "type": "Feature",
  "properties": {
    "iso:country":"GB",
    "sg:address":"Montgomery Way, Stratton Business Park",
    "sg:city":"Biggleswade",
    "sg:classifiers":[
        {
            "category":"Wholesale",
            "subcategory":"Machinery & Supplies",
            "type":"Manufacturing & Wholesale Goods"
        }
    ],
    "sg:phone":"+44 1767 312125",
    "sg:postcode":"SG18 8QB",
    "sg:province":"Bedfordshire",
    "sg:tags":[
        "equipment",
        "handling",
        "lifting"
    ],
    "wof:name":"Anglia Handling Services Ltd.",
    "wof:placetype":"venue"
},
  "geometry": {"coordinates":[-0.240353,52.074581],"type":"Point"}
}