{
  "type": "Feature",
  "properties": {
    "addr:full":"20 Eastcastle Street London Greater London W1W 8DB",
    "addr:housenumber":"20",
    "addr:postcode":"w1w 8db",
    "addr:street":"Eastcastle Street",
    "iso:country":"GB",
    "sg:address":"20 Eastcastle Street",
    "sg:city":"London",
    "sg:classifiers":[
        {
            "category":"Organizations",
            "subcategory":"Community Association",
            "type":"Services"
        }
    ],
    "sg:phone":"+44 20 7323 5656",
    "sg:postcode":"W1W 8DB",
    "sg:province":"Greater London",
    "sg:tags":[
        "relation",
        "public"
    ],
    "wof:name":"Saffron Public Relations",
    "wof:placetype":"venue"
},
  "geometry": {"coordinates":[-0.137967,51.516712],"type":"Point"}
}