{
  "type": "Feature",
  "properties": {
    "addr:full":"15 Fairhaven Court, Victoria Esplanade West Mersea Colchester Essex CO5 8DE",
    "addr:housenumber":"15",
    "addr:postcode":"co5 8de",
    "addr:street":"Fairhaven Court;Esplanade West;Colchester",
    "iso:country":"GB",
    "sg:address":"15 Fairhaven Court, Victoria Esplanade West Mersea",
    "sg:city":"Colchester",
    "sg:classifiers":[
        {
            "category":"Professional",
            "subcategory":"Computer Services",
            "type":"Services"
        }
    ],
    "sg:phone":"+44 1206 386770",
    "sg:postcode":"CO5 8DE",
    "sg:province":"Essex",
    "sg:tags":[
        "system",
        "software"
    ],
    "wof:name":"Entity Development Ltd.",
    "wof:placetype":"venue"
},
  "geometry": {"coordinates":[0.9285100102,51.7801742554],"type":"Point"}
}