{
  "type": "Feature",
  "properties": {
    "iso:country":"GB",
    "sg:address":"1 The Hallards, Eaton Socon",
    "sg:city":"Huntingdon",
    "sg:classifiers":[
        {
            "category":"Professional",
            "type":"Services"
        }
    ],
    "sg:phone":"+44 1480 216372",
    "sg:postcode":"PE19 3QW",
    "sg:province":"Bedfordshire",
    "sg:tags":[
        "exhibition"
    ],
    "wof:name":"East Midland Doll Fairs",
    "wof:placetype":"venue"
},
  "geometry": {"coordinates":[-0.28937,52.217468],"type":"Point"}
}