{
  "type": "Feature",
  "properties": {
    "iso:country":"GB",
    "sg:address":"2 Gatewick La",
    "sg:city":"Milton Keynes",
    "sg:classifiers":[
        {
            "category":"Building & Trades",
            "subcategory":"Plumbing",
            "type":"Services"
        }
    ],
    "sg:phone":"+44 1908 645291",
    "sg:postcode":"MK7 8LJ",
    "sg:province":"Buckinghamshire",
    "sg:tags":[
        "heating"
    ],
    "wof:name":"New City Plumbers",
    "wof:placetype":"venue"
},
  "geometry": {"coordinates":[-0.697117,52.00766],"type":"Point"}
}