{
  "type": "Feature",
  "properties": {
    "addr:full":"47 Chapel Street, Blakenell Walsall Staffordshire WS3 1LJ",
    "addr:housenumber":"47",
    "addr:postcode":"ws3 1lj",
    "addr:street":"Chapel Street",
    "iso:country":"GB",
    "sg:address":"47 Chapel Street, Blakenell",
    "sg:city":"Walsall",
    "sg:classifiers":[
        {
            "category":"Personal",
            "type":"Services"
        }
    ],
    "sg:postcode":"WS3 1LJ",
    "sg:province":"Staffordshire",
    "sg:tags":[
        "tailor"
    ],
    "wof:name":"Claire Cope Machining",
    "wof:placetype":"venue"
},
  "geometry": {"coordinates":[-1.9887750149,52.6124534607],"type":"Point"}
}