{
  "type": "Feature",
  "properties": {
    "addr:full":"42 Cheam Road Sutton Surrey SM1 2SS",
    "addr:housenumber":"42",
    "addr:postcode":"sm1 2ss",
    "addr:street":"Cheam Road",
    "iso:country":"GB",
    "sg:address":"42 Cheam Road",
    "sg:city":"Sutton",
    "sg:classifiers":[
        {
            "category":"Place Of Worship",
            "type":"Public Place"
        }
    ],
    "sg:phone":"+44 20 8642 2784",
    "sg:postcode":"SM1 2SS",
    "sg:province":"Surrey",
    "wof:name":"First Church of Christ Scientist",
    "wof:placetype":"venue"
},
  "geometry": {"coordinates":[-0.197615996,51.3613166809],"type":"Point"}
}