{
  "type": "Feature",
  "properties": {
    "iso:country":"GB",
    "sg:address":"345-349 Ladypool Road",
    "sg:city":"Birmingham",
    "sg:classifiers":[
        {
            "category":"Food & Beverages",
            "subcategory":"Liquor & Beverages",
            "type":"Retail Goods"
        }
    ],
    "sg:postcode":"B12 8LA",
    "sg:province":"West Midlands",
    "sg:tags":[
        "beer",
        "spirit",
        "wines"
    ],
    "wof:name":"Amex Wines Ltd.",
    "wof:placetype":"venue"
},
  "geometry": {"coordinates":[-1.878453,52.452866],"type":"Point"}
}