{
  "type": "Feature",
  "properties": {
    "addr:full":"100 North Street, Portslade Brighton East Sussex BN41 1DG",
    "addr:housenumber":"100",
    "addr:postcode":"bn41 1dg",
    "addr:street":"North Street",
    "iso:country":"GB",
    "sg:address":"100 North Street, Portslade",
    "sg:city":"Brighton",
    "sg:classifiers":[
        {
            "category":"Professional",
            "subcategory":"Printing & Photocopies",
            "type":"Services"
        }
    ],
    "sg:phone":"+44 1273 415746",
    "sg:postcode":"BN41 1DG",
    "sg:province":"East Sussex",
    "sg:tags":[
        "engraving"
    ],
    "wof:name":"Patrick Homewood",
    "wof:placetype":"venue"
},
  "geometry": {"coordinates":[-0.2131969929,50.8312149048],"type":"Point"}
}