{
  "type": "Feature",
  "properties": {
    "addr:full":"Dyce Airport, Dyce Aberdeen Aberdeen City AB21 7DU",
    "addr:postcode":"ab21 7du",
    "iso:country":"GB",
    "sg:address":"Dyce Airport, Dyce",
    "sg:city":"Aberdeen",
    "sg:classifiers":[
        {
            "category":"Freight",
            "type":"Transportation"
        }
    ],
    "sg:phone":"+44 1224 723014",
    "sg:postcode":"AB21 7DU",
    "sg:province":"Aberdeen City",
    "sg:tags":[
        "airfreight"
    ],
    "wof:name":"Ogden Cargo Ltd.",
    "wof:placetype":"venue"
},
  "geometry": {"coordinates":[-2.2034199238,57.2005615234],"type":"Point"}
}