{
  "type": "Feature",
  "properties": {
    "iso:country":"GB",
    "sg:address":"Unit 6 Logan Square, Northern Court",
    "sg:city":"Nottingham",
    "sg:classifiers":[
        {
            "category":"Retail",
            "subcategory":"Auto Repair",
            "type":"Services"
        }
    ],
    "sg:postcode":"NG6 0BJ",
    "sg:province":"Nottinghamshire",
    "sg:tags":[
        "modification",
        "garage"
    ],
    "wof:name":"Notts Premier Service Centre Ltd.",
    "wof:placetype":"venue"
},
  "geometry": {"coordinates":[-1.175409,52.981087],"type":"Point"}
}