{
  "type": "Feature",
  "properties": {
    "addr:full":"Whitehurst Park Community Centre, West Doura Rd Kilwinning East Ayrshire KA13 6NR",
    "addr:postcode":"ka13 6nr",
    "addr:street":"West Doura Rd",
    "iso:country":"GB",
    "sg:address":"Whitehurst Park Community Centre, West Doura Rd",
    "sg:city":"Kilwinning",
    "sg:classifiers":[
        {
            "category":"Education",
            "subcategory":"Dance Studio",
            "type":"Public Place"
        }
    ],
    "sg:phone":"+44 1505 349752",
    "sg:postcode":"KA13 6NR",
    "sg:province":"East Ayrshire",
    "sg:tags":[
        "school",
        "dancing"
    ],
    "wof:name":"Susan Fraser School Of Dancing",
    "wof:placetype":"venue"
},
  "geometry": {"coordinates":[-4.7046089172,55.6543884277],"type":"Point"}
}