{
  "type": "Feature",
  "properties": {
    "addr:full":"Vartry Road, Tottenham London Greater London N15 6PU",
    "addr:postcode":"n15 6pu",
    "addr:street":"Vartry Road",
    "iso:country":"GB",
    "sg:address":"Vartry Road, Tottenham",
    "sg:city":"London",
    "sg:classifiers":[
        {
            "category":"Place Of Worship",
            "type":"Public Place"
        }
    ],
    "sg:phone":"+44 20 8802 2846",
    "sg:postcode":"N15 6PU",
    "sg:province":"Greater London",
    "wof:name":"Woodberry Down baptist Church",
    "wof:placetype":"venue"
},
  "geometry": {"coordinates":[-0.080357,51.57592],"type":"Point"}
}