{
  "type": "Feature",
  "properties": {
    "iso:country":"GB",
    "sg:address":"11 Nelson Place, East Dereham",
    "sg:city":"Dereham",
    "sg:classifiers":[
        {
            "category":"Shopping",
            "subcategory":"Department Store",
            "type":"Retail Goods"
        },
        {
            "category":"Sports & Exercise",
            "subcategory":"Sports Center",
            "type":"Entertainment"
        }
    ],
    "sg:postcode":"NR19 1EA",
    "sg:province":"Norfolk",
    "sg:tags":[
        "shop"
    ],
    "wof:name":"Track & Field",
    "wof:placetype":"venue"
},
  "geometry": {"coordinates":[0.941305,52.680695],"type":"Point"}
}