{
  "type": "Feature",
  "properties": {
    "iso:country":"GB",
    "sg:address":"1a Longman Drive",
    "sg:city":"Inverness",
    "sg:classifiers":[
        {
            "category":"Freight",
            "type":"Transportation"
        }
    ],
    "sg:postcode":"IV1 1SU",
    "sg:province":"Highland",
    "sg:tags":[
        "haulage",
        "road"
    ],
    "wof:name":"James Paterson Haulage Contractors",
    "wof:placetype":"venue"
},
  "geometry": {"coordinates":[-4.221487,57.491207],"type":"Point"}
}