{
  "type": "Feature",
  "properties": {
    "iso:country":"GB",
    "sg:address":"186 Chester Road, Streetly",
    "sg:city":"Sutton Coldfield",
    "sg:classifiers":[
        {
            "category":"Personal",
            "subcategory":"Beauty Salon",
            "type":"Services"
        },
        {
            "category":"Personal",
            "subcategory":"Barber",
            "type":"Services"
        }
    ],
    "sg:phone":"+44 121 353 7677",
    "sg:postcode":"B74 3NA",
    "sg:province":"Staffordshire",
    "sg:tags":[
        "unisex",
        "hairdresser"
    ],
    "wof:name":"Carl Hair Studio",
    "wof:placetype":"venue"
},
  "geometry": {"coordinates":[-1.884689,52.577831],"type":"Point"}
}