{
  "type": "Feature",
  "properties": {
    "iso:country":"GB",
    "sg:address":"27 Osborne Avenue, Jesmond",
    "sg:city":"Newcastle-upon-tyne",
    "sg:classifiers":[
        {
            "category":"Travel",
            "subcategory":"Hotels & Motels",
            "type":"Entertainment"
        }
    ],
    "sg:postcode":"NE2 1JR",
    "sg:province":"Tyne and Wear",
    "wof:name":"Westland Hotel",
    "wof:placetype":"venue"
},
  "geometry": {"coordinates":[-1.600317,54.98785],"type":"Point"}
}