{
  "type": "Feature",
  "properties": {
    "addr:full":"Ogibly Estate Office, Greenways Court, Butts Green Road Hornchurch Essex RM11 2JL",
    "addr:postcode":"rm11 2jl",
    "addr:street":"Greenways Court Butts Green Road",
    "iso:country":"GB",
    "sg:address":"Ogibly Estate Office, Greenways Court, Butts Green Road",
    "sg:city":"Hornchurch",
    "sg:classifiers":[
        {
            "category":"Organizations",
            "subcategory":"Community Association",
            "type":"Services"
        }
    ],
    "sg:phone":"+44 1708 475115",
    "sg:postcode":"RM11 2JL",
    "sg:province":"Essex",
    "sg:tags":[
        "society",
        "housing"
    ],
    "wof:name":"Ogilby Housing Society Ltd.",
    "wof:placetype":"venue"
},
  "geometry": {"coordinates":[0.2183050066,51.5728912354],"type":"Point"}
}