{
  "type": "Feature",
  "properties": {
    "iso:country":"GB",
    "sg:address":"30 Denson Close, Waterbeach",
    "sg:city":"Cambridge",
    "sg:classifiers":[
        {
            "category":"Retail",
            "subcategory":"Driving School",
            "type":"Services"
        }
    ],
    "sg:phone":"+44 1223 861466",
    "sg:postcode":"CB5 9RN",
    "sg:province":"Cambridgeshire",
    "wof:name":"Roger Nutcombe",
    "wof:placetype":"venue"
},
  "geometry": {"coordinates":[0.1872189939,52.2677841187],"type":"Point"}
}