{
  "type": "Feature",
  "properties": {
    "iso:country":"GB",
    "sg:address":"56 Station Road",
    "sg:city":"Woodbridge",
    "sg:classifiers":[
        {
            "category":"Shopping",
            "subcategory":"Pets & Pet Supplies",
            "type":"Retail Goods"
        }
    ],
    "sg:phone":"+44 1728 723374",
    "sg:postcode":"IP13 9EE",
    "sg:province":"Suffolk",
    "sg:tags":[
        "food"
    ],
    "wof:name":"A B N A Ltd.",
    "wof:placetype":"venue"
},
  "geometry": {"coordinates":[1.343286,52.216755],"type":"Point"}
}