{
  "type": "Feature",
  "properties": {
    "addr:full":"195 Uttoxeter Road, Blythe Bridge Stoke-on-trent Staffordshire ST11 9HQ",
    "addr:housenumber":"195",
    "addr:postcode":"st11 9hq",
    "addr:street":"Uttoxeter Road",
    "iso:country":"GB",
    "sg:address":"195 Uttoxeter Road, Blythe Bridge",
    "sg:city":"Stoke-on-trent",
    "sg:classifiers":[
        {
            "category":"Farming",
            "subcategory":"Nursery",
            "type":"Manufacturing & Wholesale Goods"
        }
    ],
    "sg:phone":"+44 1782 399324",
    "sg:postcode":"ST11 9HQ",
    "sg:province":"Staffordshire",
    "sg:tags":[
        "creche"
    ],
    "wof:name":"Little Treasures Day Nursery",
    "wof:placetype":"venue"
},
  "geometry": {"coordinates":[-2.0711700916,52.9691085815],"type":"Point"}
}