{
  "type": "Feature",
  "properties": {
    "addr:full":"13 Edith Road Ramsgate Kent CT11 0EN",
    "addr:housenumber":"13",
    "addr:postcode":"ct11 0en",
    "addr:street":"Edith Road Ramsgate",
    "iso:country":"GB",
    "sg:address":"13 Edith Road",
    "sg:city":"Ramsgate",
    "sg:classifiers":[
        {
            "category":"Building & Trades",
            "subcategory":"Construction",
            "type":"Services"
        }
    ],
    "sg:phone":"+44 1843 851500",
    "sg:postcode":"CT11 0EN",
    "sg:province":"Kent",
    "sg:tags":[
        "roofing"
    ],
    "wof:name":"Albany Roofing",
    "wof:placetype":"venue"
},
  "geometry": {"coordinates":[1.405604,51.332054],"type":"Point"}
}