{
  "type": "Feature",
  "properties": {
    "addr:full":"The Old Temperance House, Kent Road, Congresbury Bristol Somerset BS49 5BD",
    "addr:postcode":"bs49 5bd",
    "addr:street":"Kent Road",
    "iso:country":"GB",
    "sg:address":"The Old Temperance House, Kent Road, Congresbury",
    "sg:city":"Bristol",
    "sg:classifiers":[
        {
            "category":"Shopping",
            "subcategory":"Crafts & Fabrics",
            "type":"Retail Goods"
        }
    ],
    "sg:postcode":"BS49 5BD",
    "sg:province":"Somerset",
    "sg:tags":[
        "material",
        "art"
    ],
    "wof:name":"Congresbury Fine Arts",
    "wof:placetype":"venue"
},
  "geometry": {"coordinates":[-2.8034191132,51.3749046326],"type":"Point"}
}