{
  "type": "Feature",
  "properties": {
    "addr:full":"7 Chalford Rd Manchester Cheshire M23 2SG",
    "addr:housenumber":"7",
    "addr:postcode":"m23 2sg",
    "addr:street":"Chalford Rd",
    "iso:country":"GB",
    "sg:address":"7 Chalford Rd",
    "sg:city":"Manchester",
    "sg:classifiers":[
        {
            "category":"Fast Food",
            "type":"Food & Drink"
        }
    ],
    "sg:phone":"+44 161 493 9948",
    "sg:postcode":"M23 2SG",
    "sg:province":"Cheshire",
    "sg:tags":[
        "away",
        "take"
    ],
    "wof:name":"Lunch Box The",
    "wof:placetype":"venue"
},
  "geometry": {"coordinates":[-2.283715,53.38451],"type":"Point"}
}