{
  "type": "Feature",
  "properties": {
    "addr:full":"169 Widemarsh Street Hereford Herefordshire HR4 9HE",
    "addr:housenumber":"169",
    "addr:postcode":"hr4 9he",
    "addr:street":"Widemarsh Street",
    "iso:country":"GB",
    "sg:address":"169 Widemarsh Street",
    "sg:city":"Hereford",
    "sg:classifiers":[
        {
            "category":"Fast Food",
            "type":"Food & Drink"
        },
        {
            "category":"Food & Beverages",
            "subcategory":"Meat & Fish",
            "type":"Retail Goods"
        }
    ],
    "sg:phone":"+44 1432 352332",
    "sg:postcode":"HR4 9HE",
    "sg:province":"Herefordshire",
    "sg:tags":[
        "shop",
        "away",
        "take",
        "chip"
    ],
    "wof:name":"The Welcome Fish Bar",
    "wof:placetype":"venue"
},
  "geometry": {"coordinates":[-2.7150669098,52.0627441406],"type":"Point"}
}