{
  "type": "Feature",
  "properties": {
    "iso:country":"GB",
    "sg:address":"Unit D9 The Falcon Enterprise Centre, Victoria St",
    "sg:city":"Oldham",
    "sg:classifiers":[
        {
            "category":"Personal",
            "type":"Services"
        }
    ],
    "sg:phone":"+44 161 345 3899",
    "sg:postcode":"OL9 0HB",
    "sg:province":"Lancashire",
    "sg:tags":[
        "delivery"
    ],
    "wof:name":"Goldstar Transport",
    "wof:placetype":"venue"
},
  "geometry": {"coordinates":[-2.1355099678,53.5478210449],"type":"Point"}
}