{
  "type": "Feature",
  "properties": {
    "iso:country":"GB",
    "sg:address":"Fordwich Rise",
    "sg:city":"Hertford",
    "sg:classifiers":[
        {
            "category":"Education",
            "subcategory":"Preschool",
            "type":"Public Place"
        }
    ],
    "sg:phone":"+44 1992 509906",
    "sg:postcode":"SG14 2DF",
    "sg:province":"Hertfordshire",
    "sg:tags":[
        "pre",
        "school",
        "playgroups",
        "pre-school"
    ],
    "wof:name":"Hollybush under Fives Preschool Group",
    "wof:placetype":"venue"
},
  "geometry": {"coordinates":[-0.095939,51.798512],"type":"Point"}
}