{
  "type": "Feature",
  "properties": {
    "iso:country":"GB",
    "sg:address":"30 George Street",
    "sg:city":"Brandon",
    "sg:classifiers":[
        {
            "category":"Retail",
            "subcategory":"Veterinary Services",
            "type":"Services"
        }
    ],
    "sg:phone":"+44 1842 810480",
    "sg:postcode":"IP27 0BX",
    "sg:province":"Norfolk",
    "sg:tags":[
        "surgeon",
        "activity"
    ],
    "wof:name":"Aquarius Veterinary Centre",
    "wof:placetype":"venue"
},
  "geometry": {"coordinates":[0.6255509853,52.4472808838],"type":"Point"}
}