{
  "type": "Feature",
  "properties": {
    "iso:country":"GB",
    "sg:address":"80 High Street",
    "sg:city":"Thornton Heath",
    "sg:classifiers":[
        {
            "category":"Personal",
            "subcategory":"Beauty Salon",
            "type":"Services"
        }
    ],
    "sg:phone":"+44 20 8684 8187",
    "sg:postcode":"CR7 8LF",
    "sg:province":"Surrey",
    "sg:tags":[
        "unisex",
        "hairdresser"
    ],
    "wof:name":"Lynns Hairdressing Salon",
    "wof:placetype":"venue"
},
  "geometry": {"coordinates":[-0.09611,51.398823],"type":"Point"}
}