{
  "type": "Feature",
  "properties": {
    "addr:full":"3 Middlesex St Whitechapel Greater London E1 7EX",
    "addr:housenumber":"3",
    "addr:postcode":"e1 7ex",
    "addr:street":"Middlesex St",
    "iso:country":"GB",
    "sg:address":"3 Middlesex St",
    "sg:city":"Whitechapel",
    "sg:classifiers":[
        {
            "category":"Food & Beverages",
            "subcategory":"Liquor & Beverages",
            "type":"Retail Goods"
        }
    ],
    "sg:phone":"+44 20 7247 7065",
    "sg:postcode":"E1 7EX",
    "sg:province":"Greater London",
    "sg:tags":[
        "beer",
        "spirit",
        "wines"
    ],
    "wof:name":"Asta 3",
    "wof:placetype":"venue"
},
  "geometry": {"coordinates":[-0.0759190023,51.5158882141],"type":"Point"}
}