{
  "type": "Feature",
  "properties": {
    "addr:full":"4 Greville Court, High Street, Knowle Solihull Warwickshire B93 0LY",
    "addr:housenumber":"4",
    "addr:postcode":"b93 0ly",
    "addr:street":"Greville Court High Street",
    "iso:country":"GB",
    "sg:address":"4 Greville Court, High Street, Knowle",
    "sg:city":"Solihull",
    "sg:classifiers":[
        {
            "category":"Retail",
            "subcategory":"Laundry & Dry Cleaning",
            "type":"Services"
        }
    ],
    "sg:postcode":"B93 0LY",
    "sg:province":"Warwickshire",
    "sg:tags":[
        "alteration"
    ],
    "wof:name":"Ideal Dry Cleaners",
    "wof:placetype":"venue"
},
  "geometry": {"coordinates":[-1.7346160412,52.3884429932],"type":"Point"}
}