{
  "type": "Feature",
  "properties": {
    "addr:full":"907-909 Fulham Road London Greater London SW6 5HU",
    "addr:housenumber":"907-909",
    "addr:postcode":"sw6 5hu",
    "addr:street":"Fulham Road",
    "iso:country":"GB",
    "sg:address":"907-909 Fulham Road",
    "sg:city":"London",
    "sg:classifiers":[
        {
            "category":"Sports & Exercise",
            "subcategory":"Winter Sports",
            "type":"Entertainment"
        }
    ],
    "sg:phone":"+44 20 7731 5415",
    "sg:postcode":"SW6 5HU",
    "sg:province":"Greater London",
    "sg:tags":[
        "skiing"
    ],
    "wof:name":"Ski 47 Degrees",
    "wof:placetype":"venue"
},
  "geometry": {"coordinates":[-0.2083790004,51.4730148315],"type":"Point"}
}