{
  "type": "Feature",
  "properties": {
    "iso:country":"GB",
    "sg:address":"146 Constitution Hill",
    "sg:city":"Norwich",
    "sg:classifiers":[
        {
            "category":"Food & Beverages",
            "subcategory":"Groceries & Convenience Stores",
            "type":"Retail Goods"
        }
    ],
    "sg:phone":"+44 1603 788894",
    "sg:postcode":"NR3 4BB",
    "sg:province":"Norfolk",
    "wof:name":"M & W Local Store",
    "wof:placetype":"venue"
},
  "geometry": {"coordinates":[1.300541,52.649513],"type":"Point"}
}