{
  "type": "Feature",
  "properties": {
    "addr:full":"Murdoch House Cambridge Cambridgeshire CB5 8HW",
    "addr:postcode":"cb5 8hw",
    "iso:country":"GB",
    "sg:address":"Murdoch House",
    "sg:city":"Cambridge",
    "sg:classifiers":[
        {
            "category":"Building & Trades",
            "subcategory":"Construction",
            "type":"Services"
        }
    ],
    "sg:phone":"+44 1223 702100",
    "sg:postcode":"CB5 8HW",
    "sg:province":"Cambridgeshire",
    "sg:tags":[
        "heating",
        "contractor"
    ],
    "wof:name":"Munro Building Services Ltd.",
    "wof:placetype":"venue"
},
  "geometry": {"coordinates":[0.1628299952,52.2122497559],"type":"Point"}
}