{
  "type": "Feature",
  "properties": {
    "iso:country":"GB",
    "sg:address":"43 Harrington Gardens",
    "sg:city":"London",
    "sg:classifiers":[
        {
            "category":"Government",
            "subcategory":"Office",
            "type":"Public Place"
        }
    ],
    "sg:phone":"+44 20 7244 6258",
    "sg:postcode":"SW7 4JU",
    "sg:province":"Greater London",
    "sg:tags":[
        "education",
        "agency",
        "authority"
    ],
    "wof:name":"The London Internship Program",
    "wof:placetype":"venue"
},
  "geometry": {"coordinates":[-0.184965,51.49271],"type":"Point"}
}