{
  "type": "Feature",
  "properties": {
    "iso:country":"GB",
    "sg:address":"20 Melville Street",
    "sg:city":"Perth",
    "sg:classifiers":[
        {
            "category":"Place Of Worship",
            "type":"Public Place"
        }
    ],
    "sg:phone":"+44 1738 622241",
    "sg:postcode":"PH1 5PY",
    "sg:province":"Perth and Kinross",
    "wof:name":"St.John's Catholic Church",
    "wof:placetype":"venue"
},
  "geometry": {"coordinates":[-3.43545,56.400166],"type":"Point"}
}