{
  "type": "Feature",
  "properties": {
    "addr:full":"26 Park Row Leeds West Yorkshire LS1 5QB",
    "addr:housenumber":"26",
    "addr:postcode":"ls1 5qb",
    "addr:street":"Park Row",
    "iso:country":"GB",
    "sg:address":"26 Park Row",
    "sg:city":"Leeds",
    "sg:classifiers":[
        {
            "category":"Education",
            "subcategory":"Special Training",
            "type":"Public Place"
        }
    ],
    "sg:phone":"+44 113 243 1516",
    "sg:postcode":"LS1 5QB",
    "sg:province":"West Yorkshire",
    "sg:tags":[
        "product",
        "centre"
    ],
    "wof:name":"Central Council For Education & Training In Social Work",
    "wof:placetype":"venue"
},
  "geometry": {"coordinates":[-1.547167,53.798958],"type":"Point"}
}