{
  "type": "Feature",
  "properties": {
    "addr:full":"Unit H Venture Business Park, Witty Street Hull East Riding of Yorkshire HU3 4TT",
    "addr:postcode":"hu3 4tt",
    "addr:street":"Witty Street",
    "iso:country":"GB",
    "sg:address":"Unit H Venture Business Park, Witty Street",
    "sg:city":"Hull",
    "sg:classifiers":[
        {
            "category":"Shopping",
            "subcategory":"Computers & Home Electronics",
            "type":"Retail Goods"
        }
    ],
    "sg:phone":"+44 1482 589015",
    "sg:postcode":"HU3 4TT",
    "sg:province":"East Riding of Yorkshire",
    "sg:tags":[
        "electrical"
    ],
    "wof:name":"Jones Electrical Supply Co",
    "wof:placetype":"venue"
},
  "geometry": {"coordinates":[-0.3693499863,53.7328186035],"type":"Point"}
}