{
  "type": "Feature",
  "properties": {
    "iso:country":"GB",
    "sg:address":"37 Middle Street",
    "sg:city":"Yeovil",
    "sg:classifiers":[
        {
            "category":"Shopping",
            "subcategory":"Pharmacy",
            "type":"Retail Goods"
        }
    ],
    "sg:phone":"+44 1935 426673",
    "sg:postcode":"BA20 1LG",
    "sg:province":"Somerset",
    "sg:tags":[
        "pharmacist",
        "chemist"
    ],
    "wof:name":"Boots the Chemists",
    "wof:placetype":"venue"
},
  "geometry": {"coordinates":[-2.6295809746,50.9413070679],"type":"Point"}
}