{
  "type": "Feature",
  "properties": {
    "iso:country":"GB",
    "sg:address":"Lakewall Farm, Lakewall",
    "sg:city":"Bridgwater",
    "sg:classifiers":[
        {
            "category":"Building & Trades",
            "subcategory":"Construction",
            "type":"Services"
        }
    ],
    "sg:phone":"+44 1278 691161",
    "sg:postcode":"TA7 0LR",
    "sg:province":"Somerset",
    "sg:tags":[
        "welder",
        "welding"
    ],
    "wof:name":"Ron Williams",
    "wof:placetype":"venue"
},
  "geometry": {"coordinates":[-2.94392,51.093868],"type":"Point"}
}