{
  "type": "Feature",
  "properties": {
    "addr:full":"41 Roman Road, Birstall Leicester Leicestershire LE4 4BB",
    "addr:housenumber":"41",
    "addr:postcode":"le4 4bb",
    "addr:street":"Roman Road",
    "iso:country":"GB",
    "sg:address":"41 Roman Road, Birstall",
    "sg:city":"Leicester",
    "sg:classifiers":[
        {
            "category":"Real Estate",
            "subcategory":"Architect",
            "type":"Services"
        }
    ],
    "sg:phone":"+44 116 267 2727",
    "sg:postcode":"LE4 4BB",
    "sg:province":"Leicestershire",
    "wof:name":"Andrew Shephard",
    "wof:placetype":"venue"
},
  "geometry": {"coordinates":[-1.127630949,52.6690826416],"type":"Point"}
}