{
  "type": "Feature",
  "properties": {
    "iso:country":"GB",
    "sg:address":"38 St Andrew Street",
    "sg:city":"Hertford",
    "sg:classifiers":[
        {
            "category":"Home & Garden",
            "subcategory":"Home Furnishings",
            "type":"Retail Goods"
        }
    ],
    "sg:phone":"+44 1992 589880",
    "sg:postcode":"SG14 1JA",
    "sg:province":"Hertfordshire",
    "sg:tags":[
        "blind",
        "curtain",
        "fitting"
    ],
    "wof:name":"Peter & Susan Brown Ltd.",
    "wof:placetype":"venue"
},
  "geometry": {"coordinates":[-0.082487,51.796505],"type":"Point"}
}