{
  "type": "Feature",
  "properties": {
    "iso:country":"GB",
    "sg:address":"92b Audley Street",
    "sg:city":"Reading",
    "sg:classifiers":[
        {
            "category":"Professional",
            "subcategory":"Printing & Photocopies",
            "type":"Services"
        }
    ],
    "sg:phone":"+44 118 958 8957",
    "sg:postcode":"RG30 1BS",
    "sg:province":"Berkshire",
    "sg:tags":[
        "printer"
    ],
    "wof:name":"Armour Print & Design",
    "wof:placetype":"venue"
},
  "geometry": {"coordinates":[-0.99454,51.458374],"type":"Point"}
}