{
  "type": "Feature",
  "properties": {
    "addr:full":"St Augustine's Road Wisbech Cambridgeshire PE13 3AJ",
    "addr:postcode":"pe13 3aj",
    "addr:street":"Augustine'S Road",
    "iso:country":"GB",
    "sg:address":"St Augustine's Road",
    "sg:city":"Wisbech",
    "sg:classifiers":[
        {
            "category":"Manufacturing",
            "subcategory":"Building Materials",
            "type":"Manufacturing & Wholesale Goods"
        }
    ],
    "sg:phone":"+44 1945 582848",
    "sg:postcode":"PE13 3AJ",
    "sg:province":"Cambridgeshire",
    "sg:tags":[
        "merchant",
        "builder"
    ],
    "wof:name":"Isaac Collett & Sons (1964) Ltd.",
    "wof:placetype":"venue"
},
  "geometry": {"coordinates":[0.162846,52.668125],"type":"Point"}
}