{
  "type": "Feature",
  "properties": {
    "iso:country":"GB",
    "sg:address":"26 Abington Grove",
    "sg:city":"Northampton",
    "sg:classifiers":[
        {
            "category":"Home & Garden",
            "subcategory":"Household Appliances",
            "type":"Retail Goods"
        }
    ],
    "sg:phone":"+44 1604 713232",
    "sg:postcode":"NN1 4QX",
    "sg:province":"Northamptonshire",
    "sg:tags":[
        "repairs",
        "electrical",
        "domestic",
        "servicing"
    ],
    "wof:name":"Moulton Electrical Distributors Ltd.",
    "wof:placetype":"venue"
},
  "geometry": {"coordinates":[-0.880948,52.246841],"type":"Point"}
}