{
  "type": "Feature",
  "properties": {
    "addr:full":"12 Bridge Road Edinburgh City of Edinburgh EH13 0LQ",
    "addr:housenumber":"12",
    "addr:postcode":"eh13 0lq",
    "addr:street":"Bridge Road",
    "iso:country":"GB",
    "sg:address":"12 Bridge Road",
    "sg:city":"Edinburgh",
    "sg:classifiers":[
        {
            "category":"Bars & Pubs",
            "type":"Food & Drink"
        }
    ],
    "sg:phone":"+44 131 441 3218",
    "sg:postcode":"EH13 0LQ",
    "sg:province":"City of Edinburgh",
    "sg:tags":[
        "pubs",
        "inn"
    ],
    "wof:name":"Coninton Inn & Dell Lounge",
    "wof:placetype":"venue"
},
  "geometry": {"coordinates":[-3.2561819553,55.9076080322],"type":"Point"}
}