{
  "type": "Feature",
  "properties": {
    "addr:full":"1 Oak Court, Bethel Rd Sevenoaks Kent TN13 3UE",
    "addr:housenumber":"1",
    "addr:postcode":"tn13 3ue",
    "addr:street":"Oak Court Bethel Rd",
    "iso:country":"GB",
    "sg:address":"1 Oak Court, Bethel Rd",
    "sg:city":"Sevenoaks",
    "sg:classifiers":[
        {
            "category":"Communications",
            "type":"Services"
        }
    ],
    "sg:phone":"+44 1732 455955",
    "sg:postcode":"TN13 3UE",
    "sg:province":"Kent",
    "sg:tags":[
        "audio-visual"
    ],
    "wof:name":"The Slide Studio",
    "wof:placetype":"venue"
},
  "geometry": {"coordinates":[0.1845239997,51.2856941223],"type":"Point"}
}