{
  "type": "Feature",
  "properties": {
    "addr:full":"Fellgate, White Lund Industrial Estate Morecambe Lancashire LA3 3PE",
    "addr:postcode":"la3 3pe",
    "addr:street":"Fellgate White Lund Industrial Estate",
    "iso:country":"GB",
    "sg:address":"Fellgate, White Lund Industrial Estate",
    "sg:city":"Morecambe",
    "sg:classifiers":[
        {
            "category":"Manufacturing",
            "subcategory":"Wood Products",
            "type":"Manufacturing & Wholesale Goods"
        }
    ],
    "sg:phone":"+44 1524 64444",
    "sg:postcode":"LA3 3PE",
    "sg:province":"Lancashire",
    "sg:tags":[
        "packaging",
        "crate",
        "pallets"
    ],
    "wof:name":"Castle Industrial Supplies",
    "wof:placetype":"venue"
},
  "geometry": {"coordinates":[-2.8349239826,54.059135437],"type":"Point"}
}