{
  "type": "Feature",
  "properties": {
    "addr:full":"56 Pioneer Avenue, Burton Latimer Kettering Northamptonshire NN15 5LH",
    "addr:housenumber":"56",
    "addr:postcode":"nn15 5lh",
    "addr:street":"Pioneer Avenue",
    "iso:country":"GB",
    "sg:address":"56 Pioneer Avenue, Burton Latimer",
    "sg:city":"Kettering",
    "sg:classifiers":[
        {
            "category":"Home & Garden",
            "subcategory":"Household Appliances",
            "type":"Retail Goods"
        },
        {
            "category":"Shopping",
            "subcategory":"Computers & Home Electronics",
            "type":"Retail Goods"
        }
    ],
    "sg:phone":"+44 1536 726640",
    "sg:postcode":"NN15 5LH",
    "sg:province":"Northamptonshire",
    "sg:tags":[
        "hi-fi",
        "equipment",
        "electrical",
        "mnfr"
    ],
    "wof:name":"Fadquest Ltd.",
    "wof:placetype":"venue"
},
  "geometry": {"coordinates":[-0.6822590232,52.3649978638],"type":"Point"}
}