{
  "type": "Feature",
  "properties": {
    "iso:country":"GB",
    "sg:address":"Hill Head",
    "sg:city":"Fareham",
    "sg:classifiers":[
        {
            "category":"Building & Trades",
            "subcategory":"Construction",
            "type":"Services"
        }
    ],
    "sg:phone":"+44 1329 662755",
    "sg:postcode":"PO14 3PG",
    "sg:province":"Hampshire",
    "sg:tags":[
        "builder"
    ],
    "wof:name":"Titchfield Builders",
    "wof:placetype":"venue"
},
  "geometry": {"coordinates":[-1.2228300571,50.8220596313],"type":"Point"}
}