{
  "type": "Feature",
  "properties": {
    "addr:full":"Evelyn Ho, Coker Clo Winchester Hampshire SO22 5AF",
    "addr:postcode":"so22 5af",
    "iso:country":"GB",
    "sg:address":"Evelyn Ho, Coker Clo",
    "sg:city":"Winchester",
    "sg:classifiers":[
        {
            "category":"Building & Trades",
            "subcategory":"Construction",
            "type":"Services"
        }
    ],
    "sg:phone":"+44 1962 844488",
    "sg:postcode":"SO22 5AF",
    "sg:province":"Hampshire",
    "sg:tags":[
        "builder"
    ],
    "wof:name":"Churches Building Services",
    "wof:placetype":"venue"
},
  "geometry": {"coordinates":[-1.3236299753,51.0665016174],"type":"Point"}
}