{
  "type": "Feature",
  "properties": {
    "addr:full":"10 Tonbridge Drive, Alvaston Derby Derbyshire DE24 0DH",
    "addr:housenumber":"10",
    "addr:postcode":"de24 0dh",
    "addr:street":"Tonbridge Drive",
    "iso:country":"GB",
    "sg:address":"10 Tonbridge Drive, Alvaston",
    "sg:city":"Derby",
    "sg:classifiers":[
        {
            "category":"Home & Garden",
            "subcategory":"Household Appliances",
            "type":"Retail Goods"
        }
    ],
    "sg:postcode":"DE24 0DH",
    "sg:province":"Derbyshire",
    "sg:tags":[
        "electrical"
    ],
    "wof:name":"Trust Electrical Services",
    "wof:placetype":"venue"
},
  "geometry": {"coordinates":[-1.4331539869,52.8884429932],"type":"Point"}
}