{
  "type": "Feature",
  "properties": {
    "addr:full":"294 Blackburn Rd Bolton Lancashire BL1 8DU",
    "addr:housenumber":"294",
    "addr:postcode":"bl1 8du",
    "addr:street":"Blackburn Rd",
    "iso:country":"GB",
    "sg:address":"294 Blackburn Rd",
    "sg:city":"Bolton",
    "sg:classifiers":[
        {
            "category":"Home & Garden",
            "subcategory":"Furniture",
            "type":"Retail Goods"
        },
        {
            "category":"Shopping",
            "subcategory":"Used Merchandise",
            "type":"Retail Goods"
        }
    ],
    "sg:postcode":"BL1 8DU",
    "sg:province":"Lancashire",
    "sg:tags":[
        "shop",
        "second-hand"
    ],
    "wof:name":"F F First Choice",
    "wof:placetype":"venue"
},
  "geometry": {"coordinates":[-2.431386,53.594578],"type":"Point"}
}