{
  "type": "Feature",
  "properties": {
    "iso:country":"GB",
    "sg:address":"Unit 20, Shipyard Estate, Brightlingsea",
    "sg:city":"Colchester",
    "sg:classifiers":[
        {
            "category":"Professional",
            "subcategory":"Engineering",
            "type":"Services"
        }
    ],
    "sg:phone":"+44 1206 304063",
    "sg:postcode":"CO7 0AR",
    "sg:province":"Essex",
    "sg:tags":[
        "engineer"
    ],
    "wof:name":"Eurotex International Ltd",
    "wof:placetype":"venue"
},
  "geometry": {"coordinates":[1.02868,51.810421],"type":"Point"}
}