{
  "type": "Feature",
  "properties": {
    "addr:full":"35 Colston Ave Bristol City of Bristol BS1 4TT",
    "addr:housenumber":"35",
    "addr:postcode":"bs1 4tt",
    "addr:street":"Colston Ave",
    "iso:country":"GB",
    "sg:address":"35 Colston Ave",
    "sg:city":"Bristol",
    "sg:classifiers":[
        {
            "category":"Professional",
            "subcategory":"Lawyer & Legal Services",
            "type":"Services"
        }
    ],
    "sg:postcode":"BS1 4TT",
    "sg:province":"City of Bristol",
    "sg:tags":[
        "solicitor"
    ],
    "wof:name":"Bevan Ashford Services Incorporated Ltd",
    "wof:placetype":"venue"
},
  "geometry": {"coordinates":[-2.59612,51.455151],"type":"Point"}
}