{
  "type": "Feature",
  "properties": {
    "iso:country":"GB",
    "sg:address":"6 Livingstone Circus",
    "sg:city":"Gillingham",
    "sg:classifiers":[
        {
            "category":"Professional",
            "subcategory":"Business Services",
            "type":"Services"
        }
    ],
    "sg:postcode":"ME7 4HA",
    "sg:province":"Kent",
    "sg:tags":[
        "assessment",
        "quality"
    ],
    "wof:name":"Gow-Mac Instrument Co (U K) Ltd",
    "wof:placetype":"venue"
},
  "geometry": {"coordinates":[0.55571,51.384701],"type":"Point"}
}