{
  "type": "Feature",
  "properties": {
    "addr:full":"181 Shortlands Road Sittingbourne Kent ME10 3JU",
    "addr:housenumber":"181",
    "addr:postcode":"me10 3ju",
    "addr:street":"Shortlands Road",
    "iso:country":"GB",
    "sg:address":"181 Shortlands Road",
    "sg:city":"Sittingbourne",
    "sg:classifiers":[
        {
            "category":"Retail",
            "subcategory":"Emissions Testing",
            "type":"Services"
        },
        {
            "category":"Professional",
            "subcategory":"Testing Lab",
            "type":"Services"
        }
    ],
    "sg:phone":"+44 1795 425781",
    "sg:postcode":"ME10 3JU",
    "sg:province":"Kent",
    "sg:tags":[
        "mot"
    ],
    "wof:name":"C R Stevenson & Son",
    "wof:placetype":"venue"
},
  "geometry": {"coordinates":[0.7513719797,51.3400154114],"type":"Point"}
}