{
  "type": "Feature",
  "properties": {
    "iso:country":"GB",
    "sg:address":"10 The Drey",
    "sg:city":"Newcastle-upon-tyne",
    "sg:classifiers":[
        {
            "category":"Professional",
            "subcategory":"Accounting & Tax Preparation",
            "type":"Services"
        }
    ],
    "sg:phone":"+44 191 285 1500",
    "sg:postcode":"NE20 9NS",
    "sg:province":"Northumberland",
    "sg:tags":[
        "accountant"
    ],
    "wof:name":"Drey Developments Ltd.",
    "wof:placetype":"venue"
},
  "geometry": {"coordinates":[-1.767582,55.037331],"type":"Point"}
}