{
  "type": "Feature",
  "properties": {
    "addr:full":"15 Talbot Terrace, Birtley Chester-le-street Durham DH3 2PQ",
    "addr:housenumber":"15",
    "addr:postcode":"dh3 2pq",
    "addr:street":"Talbot Terrace",
    "iso:country":"GB",
    "sg:address":"15 Talbot Terrace, Birtley",
    "sg:city":"Chester-le-street",
    "sg:classifiers":[
        {
            "category":"Personal",
            "subcategory":"Tattoo Parlor",
            "type":"Services"
        },
        {
            "category":"Shopping",
            "subcategory":"News",
            "type":"Retail Goods"
        }
    ],
    "sg:phone":"+44 191 410 2655",
    "sg:postcode":"DH3 2PQ",
    "sg:province":"Durham",
    "sg:tags":[
        "newsagent",
        "artist"
    ],
    "wof:name":"Californi Ann",
    "wof:placetype":"venue"
},
  "geometry": {"coordinates":[-1.577639,54.895672],"type":"Point"}
}