{
  "type": "Feature",
  "properties": {
    "addr:full":"1 Rosevale Street Langholm Dumfries and Galloway DG13 0DS",
    "addr:housenumber":"1",
    "addr:postcode":"dg13 0ds",
    "addr:street":"Rosevale Street",
    "iso:country":"GB",
    "sg:address":"1 Rosevale Street",
    "sg:city":"Langholm",
    "sg:classifiers":[
        {
            "category":"Professional",
            "subcategory":"Engineering",
            "type":"Services"
        },
        {
            "category":"Building & Trades",
            "subcategory":"Electrical",
            "type":"Services"
        }
    ],
    "sg:phone":"+44 13873 81300",
    "sg:postcode":"DG13 0DS",
    "sg:province":"Dumfries and Galloway",
    "sg:tags":[
        "engineer",
        "electrician",
        "contractor"
    ],
    "wof:name":"Michael Haining",
    "wof:placetype":"venue"
},
  "geometry": {"coordinates":[-2.999984,55.149796],"type":"Point"}
}