{
  "type": "Feature",
  "properties": {
    "addr:full":"Burnham Laboratory, Rembrance Avenue Burnham-on-crouch Essex CM0 8HA",
    "addr:postcode":"cm0 8ha",
    "addr:street":"Rembrance Avenue",
    "iso:country":"GB",
    "sg:address":"Burnham Laboratory, Rembrance Avenue",
    "sg:city":"Burnham-on-crouch",
    "sg:classifiers":[
        {
            "category":"Government",
            "subcategory":"Office",
            "type":"Public Place"
        }
    ],
    "sg:postcode":"CM0 8HA",
    "sg:province":"Essex",
    "sg:tags":[
        "central"
    ],
    "wof:name":"Centre for Environment Fisheries & Aquaculture Sci",
    "wof:placetype":"venue"
},
  "geometry": {"coordinates":[0.8154270053,51.6318397522],"type":"Point"}
}