{
  "type": "Feature",
  "properties": {
    "addr:full":"Stone End Farm, Church Lane, Hartpury Gloucester Gloucestershire GL19 3BX",
    "addr:postcode":"gl19 3bx",
    "addr:street":"Stone;Church Lane",
    "iso:country":"GB",
    "sg:address":"Stone End Farm, Church Lane, Hartpury",
    "sg:city":"Gloucester",
    "sg:classifiers":[
        {
            "category":"Farming",
            "subcategory":"Livestock Farm",
            "type":"Manufacturing & Wholesale Goods"
        }
    ],
    "sg:phone":"+44 1452 700254",
    "sg:postcode":"GL19 3BX",
    "sg:province":"Gloucestershire",
    "sg:tags":[
        "others"
    ],
    "wof:name":"Roy G Spry",
    "wof:placetype":"venue"
},
  "geometry": {"coordinates":[-2.312167,51.957561],"type":"Point"}
}