{
  "type": "Feature",
  "properties": {
    "addr:full":"171 Halesowen Road Cradley Heath West Midlands B64 6HX",
    "addr:housenumber":"171",
    "addr:postcode":"b64 6hx",
    "addr:street":"Halesowen Road",
    "iso:country":"GB",
    "sg:address":"171 Halesowen Road",
    "sg:city":"Cradley Heath",
    "sg:classifiers":[
        {
            "category":"Food & Beverages",
            "subcategory":"Liquor & Beverages",
            "type":"Retail Goods"
        }
    ],
    "sg:phone":"+44 1384 410988",
    "sg:postcode":"B64 6HX",
    "sg:province":"West Midlands",
    "sg:tags":[
        "beer",
        "spirit",
        "wines"
    ],
    "wof:name":"General Stores & Off Licence",
    "wof:placetype":"venue"
},
  "geometry": {"coordinates":[-2.0677089691,52.4766769409],"type":"Point"}
}