{
  "type": "Feature",
  "properties": {
    "addr:full":"43 New Street, Baddesley Ensor Atherstone Leicestershire CV9 2DN",
    "addr:housenumber":"43",
    "addr:postcode":"cv9 2dn",
    "addr:street":"New Street",
    "iso:country":"GB",
    "sg:address":"43 New Street, Baddesley Ensor",
    "sg:city":"Atherstone",
    "sg:classifiers":[
        {
            "category":"Building & Trades",
            "subcategory":"Construction",
            "type":"Services"
        }
    ],
    "sg:postcode":"CV9 2DN",
    "sg:province":"Leicestershire",
    "sg:tags":[
        "contractor",
        "paving",
        "driveway"
    ],
    "wof:name":"Premier Blockpaving",
    "wof:placetype":"venue"
},
  "geometry": {"coordinates":[-1.601238966,52.5798149109],"type":"Point"}
}