{
  "type": "Feature",
  "properties": {
    "iso:country":"GB",
    "sg:address":"80 Mariners Way, Strand Shopping Centre",
    "sg:city":"Bootle",
    "sg:classifiers":[
        {
            "category":"Travel",
            "subcategory":"Travel Agent",
            "type":"Entertainment"
        }
    ],
    "sg:phone":"+44 151 933 9272",
    "sg:postcode":"L20 4ST",
    "sg:province":"Merseyside",
    "wof:name":"Travelcare",
    "wof:placetype":"venue"
},
  "geometry": {"coordinates":[-2.9967598915,53.4510498047],"type":"Point"}
}