{
  "type": "Feature",
  "properties": {
    "addr:full":"37 Bidston Avenue St Helens Lancashire WA11 9BJ",
    "addr:housenumber":"37",
    "addr:postcode":"wa11 9bj",
    "addr:street":"Bidston Avenue",
    "iso:country":"GB",
    "sg:address":"37 Bidston Avenue",
    "sg:city":"St Helens",
    "sg:classifiers":[
        {
            "category":"Building & Trades",
            "subcategory":"Construction",
            "type":"Services"
        }
    ],
    "sg:phone":"+44 1744 754556",
    "sg:postcode":"WA11 9BJ",
    "sg:province":"Lancashire",
    "sg:tags":[
        "dry",
        "lining",
        "plasterers",
        "screeders"
    ],
    "wof:name":"Cliff Waring Artexing",
    "wof:placetype":"venue"
},
  "geometry": {"coordinates":[-2.7107219696,53.4598846436],"type":"Point"}
}