{
  "type": "Feature",
  "properties": {
    "iso:country":"GB",
    "sg:address":"17 High Street",
    "sg:city":"Boston",
    "sg:classifiers":[
        {
            "category":"Restaurant",
            "type":"Food & Drink"
        }
    ],
    "sg:phone":"+44 1205 311677",
    "sg:postcode":"PE21 8SH",
    "sg:province":"Lincolnshire",
    "wof:name":"Mediteranean D'Or",
    "wof:placetype":"venue"
},
  "geometry": {"coordinates":[-0.0241979994,52.9763298035],"type":"Point"}
}