{
  "type": "Feature",
  "properties": {
    "addr:full":"20 Reynolds Close, Keynsham Bristol City of Bristol BS31 1LX",
    "addr:housenumber":"20",
    "addr:postcode":"bs31 1lx",
    "addr:street":"Reynolds Close",
    "iso:country":"GB",
    "sg:address":"20 Reynolds Close, Keynsham",
    "sg:city":"Bristol",
    "sg:classifiers":[
        {
            "category":"Banks & Credit Unions",
            "subcategory":"Financial Services",
            "type":"Services"
        },
        {
            "category":"Insurance",
            "subcategory":"Health Insurance",
            "type":"Services"
        }
    ],
    "sg:phone":"+44 117 986 7535",
    "sg:postcode":"BS31 1LX",
    "sg:province":"City of Bristol",
    "sg:tags":[
        "claim",
        "assessor"
    ],
    "wof:name":"Stevens & Co",
    "wof:placetype":"venue"
},
  "geometry": {"coordinates":[-2.4901320934,51.4131965637],"type":"Point"}
}