{
  "type": "Feature",
  "properties": {
    "addr:full":"23-27 George Street London Greater London W1U 3QA",
    "addr:housenumber":"23-27",
    "addr:postcode":"w1u 3qa",
    "addr:street":"George Street",
    "iso:country":"GB",
    "sg:address":"23-27 George Street",
    "sg:city":"London",
    "sg:classifiers":[
        {
            "category":"Manufacturing",
            "subcategory":"Textiles",
            "type":"Manufacturing & Wholesale Goods"
        }
    ],
    "sg:postcode":"W1U 3QA",
    "sg:province":"Greater London",
    "sg:tags":[
        "knitwear"
    ],
    "wof:name":"London Chic Shopping Centre",
    "wof:placetype":"venue"
},
  "geometry": {"coordinates":[-0.153954,51.517551],"type":"Point"}
}