{
  "type": "Feature",
  "properties": {
    "addr:full":"Unit 6, Montague Street Birmingham West Midlands B9 4BA",
    "addr:housenumber":"unit 6",
    "addr:postcode":"b9 4ba",
    "addr:street":"Montague Street",
    "iso:country":"GB",
    "sg:address":"Unit 6, Montague Street",
    "sg:city":"Birmingham",
    "sg:classifiers":[
        {
            "category":"Freight",
            "type":"Transportation"
        }
    ],
    "sg:phone":"+44 121 773 9138",
    "sg:postcode":"B9 4BA",
    "sg:province":"West Midlands",
    "sg:tags":[
        "haulage",
        "road"
    ],
    "wof:name":"Taylor Transport (U K) Ltd.",
    "wof:placetype":"venue"
},
  "geometry": {"coordinates":[-1.879164,52.480083],"type":"Point"}
}