{
  "type": "Feature",
  "properties": {
    "addr:full":"22-26 Worthing Rd Horsham West Sussex RH12 1SL",
    "addr:housenumber":"22-26",
    "addr:postcode":"rh12 1sl",
    "addr:street":"Worthing Rd",
    "iso:country":"GB",
    "sg:address":"22-26 Worthing Rd",
    "sg:city":"Horsham",
    "sg:postcode":"RH12 1SL",
    "sg:province":"West Sussex",
    "wof:name":"Polymers International (U K) Ltd",
    "wof:placetype":"venue"
},
  "geometry": {"coordinates":[-0.33404,51.062077],"type":"Point"}
}