{
  "type": "Feature",
  "properties": {
    "iso:country":"GB",
    "sg:address":"6 Matilda Street",
    "sg:city":"Sheffield",
    "sg:classifiers":[
        {
            "category":"Shopping",
            "subcategory":"Thrift Store",
            "type":"Retail Goods"
        }
    ],
    "sg:postcode":"S1 4QD",
    "sg:province":"South Yorkshire",
    "sg:tags":[
        "shop",
        "charity"
    ],
    "wof:name":"Oxfam",
    "wof:placetype":"venue"
},
  "geometry": {"coordinates":[-1.472355,53.376907],"type":"Point"}
}