{
  "type": "Feature",
  "properties": {
    "addr:full":"2 Arden Road, Rubery Birmingham West Midlands B45 0JA",
    "addr:housenumber":"2",
    "addr:postcode":"b45 0ja",
    "addr:street":"Arden Road",
    "iso:country":"GB",
    "sg:address":"2 Arden Road, Rubery",
    "sg:city":"Birmingham",
    "sg:classifiers":[
        {
            "category":"Food & Beverages",
            "subcategory":"Meat & Fish",
            "type":"Retail Goods"
        }
    ],
    "sg:postcode":"B45 0JA",
    "sg:province":"West Midlands",
    "sg:tags":[
        "chip"
    ],
    "wof:name":"Golden Plaice Fish Bar",
    "wof:placetype":"venue"
},
  "geometry": {"coordinates":[-2.015414,52.403168],"type":"Point"}
}