{
  "type": "Feature",
  "properties": {
    "addr:full":"Signal House, Lyon Road Harrow Greater London HA1 2AG",
    "addr:postcode":"ha1 2ag",
    "addr:street":"Lyon Road",
    "iso:country":"GB",
    "sg:address":"Signal House, Lyon Road",
    "sg:city":"Harrow",
    "sg:classifiers":[
        {
            "category":"Shopping",
            "subcategory":"Computers & Home Electronics",
            "type":"Retail Goods"
        },
        {
            "category":"Professional",
            "subcategory":"Computer Services",
            "type":"Services"
        }
    ],
    "sg:postcode":"HA1 2AG",
    "sg:province":"Greater London",
    "sg:tags":[
        "software",
        "sales",
        "system"
    ],
    "wof:name":"Silicon Vision Ltd.",
    "wof:placetype":"venue"
},
  "geometry": {"coordinates":[-0.332569,51.58041],"type":"Point"}
}