{
  "type": "Feature",
  "properties": {
    "addr:full":"Llay Hall Industrial Estate, Mold Road, Cefn-y-bedd Wrexham Wrexham LL12 9YG",
    "addr:postcode":"ll12 9yg",
    "addr:street":"Industrial Estate Mold Road",
    "iso:country":"GB",
    "sg:address":"Llay Hall Industrial Estate, Mold Road, Cefn-y-bedd",
    "sg:city":"Wrexham",
    "sg:classifiers":[
        {
            "category":"Manufacturing",
            "subcategory":"Metals",
            "type":"Manufacturing & Wholesale Goods"
        }
    ],
    "sg:phone":"+44 1978 762224",
    "sg:postcode":"LL12 9YG",
    "sg:province":"Wrexham",
    "sg:tags":[
        "steel",
        "stockholder"
    ],
    "wof:name":"North Wales Profiling Ltd.",
    "wof:placetype":"venue"
},
  "geometry": {"coordinates":[-3.0310690403,53.0979194641],"type":"Point"}
}