{
  "type": "Feature",
  "properties": {
    "addr:full":"125 High Street Southampton Hampshire SO14 3TA",
    "addr:housenumber":"125",
    "addr:postcode":"so14 3ta",
    "addr:street":"High Street",
    "iso:country":"GB",
    "sg:address":"125 High Street",
    "sg:city":"Southampton",
    "sg:classifiers":[
        {
            "category":"Banks & Credit Unions",
            "subcategory":"Financial Services",
            "type":"Services"
        }
    ],
    "sg:phone":"+44 23 8063 8022",
    "sg:postcode":"SO14 3TA",
    "sg:province":"Hampshire",
    "sg:tags":[
        "consultant"
    ],
    "wof:name":"Citifinancial Europe Plc",
    "wof:placetype":"venue"
},
  "geometry": {"coordinates":[-1.40403,50.899269],"type":"Point"}
}