{
  "type": "Feature",
  "properties": {
    "iso:country":"GB",
    "sg:address":"14 Holywell Road",
    "sg:city":"Flint",
    "sg:classifiers":[
        {
            "category":"Military Area",
            "subcategory":"Air Force Base",
            "type":"Public Place"
        }
    ],
    "sg:postcode":"CH6 5ES",
    "sg:province":"Flintshire",
    "sg:tags":[
        "taxi",
        "hire",
        "private"
    ],
    "wof:name":"Classic Cars",
    "wof:placetype":"venue"
},
  "geometry": {"coordinates":[-3.135088,53.250877],"type":"Point"}
}