{
  "type": "Feature",
  "properties": {
    "iso:country":"GB",
    "sg:address":"441 Hagley Road",
    "sg:city":"Birmingham",
    "sg:classifiers":[
        {
            "category":"Health Services",
            "subcategory":"Nursing And Care Facility",
            "type":"Services"
        },
        {
            "category":"Social Services",
            "subcategory":"Retirement Home",
            "type":"Services"
        }
    ],
    "sg:phone":"+44 121 420 4580",
    "sg:postcode":"B17 8BL",
    "sg:province":"West Midlands",
    "sg:tags":[
        "residential"
    ],
    "wof:name":"Bournedale House",
    "wof:placetype":"venue"
},
  "geometry": {"coordinates":[-1.964079,52.473511],"type":"Point"}
}