{
  "type": "Feature",
  "properties": {
    "iso:country":"GB",
    "sg:address":"43 Portland Place",
    "sg:city":"London",
    "sg:classifiers":[
        {
            "category":"Professional",
            "subcategory":"Lawyer & Legal Services",
            "type":"Services"
        }
    ],
    "sg:phone":"+44 20 7637 2900",
    "sg:postcode":"W1B 1QH",
    "sg:province":"Greater London",
    "sg:tags":[
        "solicitor"
    ],
    "wof:name":"Beller & Co",
    "wof:placetype":"venue"
},
  "geometry": {"coordinates":[-0.145465,51.52058],"type":"Point"}
}