{
  "type": "Feature",
  "properties": {
    "addr:full":"36 Chatterton Road Bromley Kent BR2 9QN",
    "addr:housenumber":"36",
    "addr:postcode":"br2 9qn",
    "addr:street":"Chatterton Road",
    "iso:country":"GB",
    "sg:address":"36 Chatterton Road",
    "sg:city":"Bromley",
    "sg:classifiers":[
        {
            "category":"Food & Beverages",
            "subcategory":"Meat & Fish",
            "type":"Retail Goods"
        }
    ],
    "sg:phone":"+44 20 8460 1381",
    "sg:postcode":"BR2 9QN",
    "sg:province":"Kent",
    "sg:tags":[
        "butcher"
    ],
    "wof:name":"Master Butcher",
    "wof:placetype":"venue"
},
  "geometry": {"coordinates":[0.0353970006,51.3922958374],"type":"Point"}
}