{
  "type": "Feature",
  "properties": {
    "addr:full":"93 Rudston Rd, Childwall Liverpool Merseyside L16 4PQ",
    "addr:housenumber":"93",
    "addr:postcode":"l16 4pq",
    "addr:street":"Rudston Rd",
    "iso:country":"GB",
    "sg:address":"93 Rudston Rd, Childwall",
    "sg:city":"Liverpool",
    "sg:classifiers":[
        {
            "category":"Building & Trades",
            "subcategory":"Construction",
            "type":"Services"
        }
    ],
    "sg:postcode":"L16 4PQ",
    "sg:province":"Merseyside",
    "sg:tags":[
        "decorator",
        "painter"
    ],
    "wof:name":"Hilton,Colin,",
    "wof:placetype":"venue"
},
  "geometry": {"coordinates":[-2.8921871185,53.399017334],"type":"Point"}
}