{
  "type": "Feature",
  "properties": {
    "addr:full":"96-98 High Street Beckenham Kent BR3 1ED",
    "addr:housenumber":"96-98",
    "addr:postcode":"br3 1ed",
    "addr:street":"High Street",
    "iso:country":"GB",
    "sg:address":"96-98 High Street",
    "sg:city":"Beckenham",
    "sg:classifiers":[
        {
            "category":"Shopping",
            "subcategory":"Stationery & Office Supplies",
            "type":"Retail Goods"
        }
    ],
    "sg:phone":"+44 20 8658 2980",
    "sg:postcode":"BR3 1ED",
    "sg:province":"Kent",
    "wof:name":"Thornton Stationers",
    "wof:placetype":"venue"
},
  "geometry": {"coordinates":[-0.0256900005,51.4078941345],"type":"Point"}
}