{
  "type": "Feature",
  "properties": {
    "iso:country":"GB",
    "sg:address":"52 Dyke Rd",
    "sg:city":"Brighton",
    "sg:classifiers":[
        {
            "category":"Farming",
            "subcategory":"Nursery",
            "type":"Manufacturing & Wholesale Goods"
        }
    ],
    "sg:phone":"+44 1273 724038",
    "sg:postcode":"BN1 3JB",
    "sg:province":"East Sussex",
    "sg:tags":[
        "creche"
    ],
    "wof:name":"Regent House Day Nursery",
    "wof:placetype":"venue"
},
  "geometry": {"coordinates":[-0.146521,50.828815],"type":"Point"}
}