{
  "type": "Feature",
  "properties": {
    "addr:full":"Unit 3 Hermitage Works, 7 Vale Gro London Greater London N4 1PY",
    "addr:housenumber":"unit 3;7",
    "addr:postcode":"n4 1py",
    "addr:street":"Hermitage Works",
    "iso:country":"GB",
    "sg:address":"Unit 3 Hermitage Works, 7 Vale Gro",
    "sg:city":"London",
    "sg:classifiers":[
        {
            "category":"Communications",
            "subcategory":"Film & Video Production",
            "type":"Services"
        }
    ],
    "sg:phone":"+44 20 8802 8979",
    "sg:postcode":"N4 1PY",
    "sg:province":"Greater London",
    "sg:tags":[
        "recording",
        "studio"
    ],
    "wof:name":"Groove Works Studios Ltd.",
    "wof:placetype":"venue"
},
  "geometry": {"coordinates":[-0.0936200023,51.5753707886],"type":"Point"}
}