{
  "type": "Feature",
  "properties": {
    "addr:full":"243 Oldham Road, Royton Oldham Lancashire OL2 6BB",
    "addr:housenumber":"243",
    "addr:postcode":"ol2 6bb",
    "addr:street":"Oldham Road",
    "iso:country":"GB",
    "sg:address":"243 Oldham Road, Royton",
    "sg:city":"Oldham",
    "sg:classifiers":[
        {
            "category":"Shopping",
            "subcategory":"News",
            "type":"Retail Goods"
        }
    ],
    "sg:phone":"+44 161 652 6050",
    "sg:postcode":"OL2 6BB",
    "sg:province":"Lancashire",
    "sg:tags":[
        "newsagent"
    ],
    "wof:name":"Gary Samuel",
    "wof:placetype":"venue"
},
  "geometry": {"coordinates":[-2.120456934,53.558631897],"type":"Point"}
}