{
  "type": "Feature",
  "properties": {
    "addr:full":"13 Mostyn Crescent Llandudno Conwy LL30 1AR",
    "addr:housenumber":"13",
    "addr:postcode":"ll30 1ar",
    "addr:street":"Mostyn Crescent",
    "iso:country":"GB",
    "sg:address":"13 Mostyn Crescent",
    "sg:city":"Llandudno",
    "sg:classifiers":[
        {
            "category":"Travel",
            "subcategory":"Hotels & Motels",
            "type":"Entertainment"
        }
    ],
    "sg:phone":"+44 1492 879660",
    "sg:postcode":"LL30 1AR",
    "sg:province":"Conwy",
    "wof:name":"Shelbourne Hotel",
    "wof:placetype":"venue"
},
  "geometry": {"coordinates":[-3.8125710487,53.3206520081],"type":"Point"}
}