{
  "type": "Feature",
  "properties": {
    "iso:country":"GB",
    "sg:address":"18 Bramley Avenue",
    "sg:city":"Canterbury",
    "sg:classifiers":[
        {
            "category":"Fast Food",
            "type":"Food & Drink"
        }
    ],
    "sg:postcode":"CT1 3XW",
    "sg:province":"Kent",
    "sg:tags":[
        "away",
        "take"
    ],
    "wof:name":"Rosecroft Catering Supplies",
    "wof:placetype":"venue"
},
  "geometry": {"coordinates":[1.052857995,51.2685432434],"type":"Point"}
}