{
  "type": "Feature",
  "properties": {
    "addr:full":"Church Road Worcester Park Surrey KT4 7RD",
    "addr:postcode":"kt4 7rd",
    "addr:street":"Church Road",
    "iso:country":"GB",
    "sg:address":"Church Road",
    "sg:city":"Worcester Park",
    "sg:classifiers":[
        {
            "category":"Education",
            "subcategory":"Library",
            "type":"Public Place"
        },
        {
            "category":"Government",
            "subcategory":"Office",
            "type":"Public Place"
        }
    ],
    "sg:phone":"+44 20 8337 6344",
    "sg:postcode":"KT4 7RD",
    "sg:province":"Surrey",
    "sg:tags":[
        "book",
        "local"
    ],
    "wof:name":"Old Malden Library",
    "wof:placetype":"venue"
},
  "geometry": {"coordinates":[-0.2547580004,51.3841934204],"type":"Point"}
}