{
  "type": "Feature",
  "properties": {
    "addr:full":"45 Croft Road Blyth Northumberland NE24 2EL",
    "addr:housenumber":"45",
    "addr:postcode":"ne24 2el",
    "addr:street":"Croft Road;Northumberland",
    "iso:country":"GB",
    "sg:address":"45 Croft Road",
    "sg:city":"Blyth",
    "sg:classifiers":[
        {
            "category":"Building & Trades",
            "subcategory":"Construction",
            "type":"Services"
        }
    ],
    "sg:phone":"+44 1670 368268",
    "sg:postcode":"NE24 2EL",
    "sg:province":"Northumberland",
    "sg:tags":[
        "builder"
    ],
    "wof:name":"David Wilkinson Building Contractors Ltd.",
    "wof:placetype":"venue"
},
  "geometry": {"coordinates":[-1.508064,55.125198],"type":"Point"}
}