{
  "type": "Feature",
  "properties": {
    "iso:country":"GB",
    "sg:address":"Unit 17",
    "sg:city":"Birmingham",
    "sg:classifiers":[
        {
            "category":"Professional",
            "subcategory":"Printing & Photocopies",
            "type":"Services"
        }
    ],
    "sg:postcode":"B44 8NH",
    "sg:province":"West Midlands",
    "sg:tags":[
        "engraving"
    ],
    "wof:name":"Hamilton Rand",
    "wof:placetype":"venue"
},
  "geometry": {"coordinates":[-1.882329,52.539639],"type":"Point"}
}