{
  "type": "Feature",
  "properties": {
    "addr:full":"15 Brickfield Hatfield Hertfordshire AL10 8TN",
    "addr:housenumber":"15",
    "addr:postcode":"al10 8tn",
    "addr:street":"Brickfield",
    "iso:country":"GB",
    "sg:address":"15 Brickfield",
    "sg:city":"Hatfield",
    "sg:classifiers":[
        {
            "category":"Wholesale",
            "subcategory":"Office Equipment",
            "type":"Manufacturing & Wholesale Goods"
        },
        {
            "category":"Building & Trades",
            "subcategory":"Construction",
            "type":"Services"
        }
    ],
    "sg:phone":"+44 1707 895447",
    "sg:postcode":"AL10 8TN",
    "sg:province":"Hertfordshire",
    "sg:tags":[
        "cubicle",
        "partition",
        "installation"
    ],
    "wof:name":"Floorspace",
    "wof:placetype":"venue"
},
  "geometry": {"coordinates":[-0.2270919979,51.7450485229],"type":"Point"}
}