{
  "type": "Feature",
  "properties": {
    "addr:full":"The Maltings Cardiff Cardiff CF24 5EA",
    "addr:postcode":"cf24 5ea",
    "addr:street":"The Maltings",
    "iso:country":"GB",
    "sg:address":"The Maltings",
    "sg:city":"Cardiff",
    "sg:classifiers":[
        {
            "category":"Home & Garden",
            "subcategory":"Home Furnishings",
            "type":"Retail Goods"
        }
    ],
    "sg:postcode":"CF24 5EA",
    "sg:province":"Cardiff",
    "sg:tags":[
        "racking",
        "shelving",
        "diy"
    ],
    "wof:name":"G J Winterbottom",
    "wof:placetype":"venue"
},
  "geometry": {"coordinates":[-3.1540760994,51.4792442322],"type":"Point"}
}