{
  "type": "Feature",
  "properties": {
    "addr:full":"119 Mill Road Cambridge Cambridgeshire CB1 2AZ",
    "addr:housenumber":"119",
    "addr:postcode":"cb1 2az",
    "addr:street":"Mill Road",
    "iso:country":"GB",
    "sg:address":"119 Mill Road",
    "sg:city":"Cambridge",
    "sg:classifiers":[
        {
            "category":"Education",
            "subcategory":"Special Training",
            "type":"Public Place"
        }
    ],
    "sg:postcode":"CB1 2AZ",
    "sg:province":"Cambridgeshire",
    "sg:tags":[
        "school",
        "language"
    ],
    "wof:name":"Cambridge Tutors",
    "wof:placetype":"venue"
},
  "geometry": {"coordinates":[0.1396670043,52.199131012],"type":"Point"}
}