{
  "type": "Feature",
  "properties": {
    "iso:country":"GB",
    "sg:address":"Suite 2b 101 Park St",
    "sg:city":"Luton",
    "sg:classifiers":[
        {
            "category":"Professional",
            "subcategory":"Art Services",
            "type":"Services"
        }
    ],
    "sg:phone":"+44 1582 733234",
    "sg:postcode":"LU1 3HG",
    "sg:province":"Bedfordshire",
    "sg:tags":[
        "graphic",
        "designer"
    ],
    "wof:name":"A & D Creative Marketing Ltd",
    "wof:placetype":"venue"
},
  "geometry": {"coordinates":[-0.408773005,51.8758239746],"type":"Point"}
}