{
  "type": "Feature",
  "properties": {
    "iso:country":"GB",
    "sg:address":"Runnymede Malthouse, Hummer Rd",
    "sg:city":"Egham",
    "sg:classifiers":[
        {
            "category":"Landmark",
            "subcategory":"Tourist Information",
            "type":"Public Place"
        }
    ],
    "sg:phone":"+44 1784 497086",
    "sg:postcode":"TW20 9BD",
    "sg:province":"Surrey",
    "wof:name":"Illinois Bureau Of Tourism",
    "wof:placetype":"venue"
},
  "geometry": {"coordinates":[-0.5474889874,51.430896759],"type":"Point"}
}