{
  "type": "Feature",
  "properties": {
    "iso:country":"GB",
    "sg:address":"38 Bromley Common",
    "sg:city":"Bromley",
    "sg:classifiers":[
        {
            "category":"Wholesale",
            "subcategory":"Construction Materials",
            "type":"Manufacturing & Wholesale Goods"
        }
    ],
    "sg:phone":"+44 20 8464 5321",
    "sg:postcode":"BR2 9PD",
    "sg:province":"Kent",
    "sg:tags":[
        "lift"
    ],
    "wof:name":"I Maszlik (Lift Engineers) Ltd.",
    "wof:placetype":"venue"
},
  "geometry": {"coordinates":[0.0295850001,51.3931732178],"type":"Point"}
}