{
  "type": "Feature",
  "properties": {
    "iso:country":"GB",
    "sg:address":"Clifton Moor Centre",
    "sg:city":"York",
    "sg:classifiers":[
        {
            "category":"Commercial Area",
            "type":"Public Place"
        }
    ],
    "sg:phone":"+44 1904 690206",
    "sg:postcode":"YO30 4XZ",
    "sg:province":"North Yorkshire",
    "sg:tags":[
        "shop",
        "centre"
    ],
    "wof:name":"Clifton Moor Shopping Centre",
    "wof:placetype":"venue"
},
  "geometry": {"coordinates":[-1.103076,53.98703],"type":"Point"}
}