{
  "type": "Feature",
  "properties": {
    "addr:full":"Northlands Industrial Estate, Cop Heap Lane Warminster Somerset BA12 0BG",
    "addr:postcode":"ba12 0bg",
    "addr:street":"Heap Lane",
    "iso:country":"GB",
    "sg:address":"Northlands Industrial Estate, Cop Heap Lane",
    "sg:city":"Warminster",
    "sg:classifiers":[
        {
            "category":"Shopping",
            "subcategory":"Crafts & Fabrics",
            "type":"Retail Goods"
        }
    ],
    "sg:phone":"+44 1985 846400",
    "sg:postcode":"BA12 0BG",
    "sg:province":"Somerset",
    "sg:tags":[
        "material",
        "art"
    ],
    "wof:name":"Fabric Flair Ltd.",
    "wof:placetype":"venue"
},
  "geometry": {"coordinates":[-2.183125,51.205364],"type":"Point"}
}