{
  "type": "Feature",
  "properties": {
    "iso:country":"GB",
    "sg:address":"6 Godwin Close, Kemsley",
    "sg:city":"Sittingbourne",
    "sg:classifiers":[
        {
            "category":"Professional",
            "subcategory":"Engineering",
            "type":"Services"
        }
    ],
    "sg:phone":"+44 1795 424045",
    "sg:postcode":"ME10 2SW",
    "sg:province":"Kent",
    "sg:tags":[
        "contractor",
        "electrical",
        "engineer"
    ],
    "wof:name":"Alan T Double Electrical Ltd.",
    "wof:placetype":"venue"
},
  "geometry": {"coordinates":[0.7365589738,51.3648796082],"type":"Point"}
}