{
  "type": "Feature",
  "properties": {
    "addr:full":"2 Market Place Faversham Kent ME13 7AG",
    "addr:housenumber":"2",
    "addr:postcode":"me13 7ag",
    "addr:street":"Market Place",
    "iso:country":"GB",
    "sg:address":"2 Market Place",
    "sg:city":"Faversham",
    "sg:classifiers":[
        {
            "category":"Retail",
            "subcategory":"Laundry & Dry Cleaning",
            "type":"Services"
        }
    ],
    "sg:phone":"+44 1795 532665",
    "sg:postcode":"ME13 7AG",
    "sg:province":"Kent",
    "sg:tags":[
        "alteration"
    ],
    "wof:name":"Kengate Cleaners",
    "wof:placetype":"venue"
},
  "geometry": {"coordinates":[0.89107,51.315739],"type":"Point"}
}