{
  "type": "Feature",
  "properties": {
    "iso:country":"GB",
    "sg:address":"Units 13-15, Wilburn, Wooburn Industrial Park",
    "sg:city":"High Wycombe",
    "sg:classifiers":[
        {
            "category":"Professional",
            "subcategory":"Printing & Photocopies",
            "type":"Services"
        }
    ],
    "sg:phone":"+44 1628 810888",
    "sg:postcode":"HP10 0PG",
    "sg:province":"Buckinghamshire",
    "sg:tags":[
        "printer"
    ],
    "wof:name":"Capital Print & Design Ltd.",
    "wof:placetype":"venue"
},
  "geometry": {"coordinates":[-0.69372,51.581772],"type":"Point"}
}