{
  "type": "Feature",
  "properties": {
    "addr:full":"2 Exchange Rd Nottingham Nottinghamshire NG2 6BZ",
    "addr:housenumber":"2",
    "addr:postcode":"ng2 6bz",
    "addr:street":"Exchange Rd",
    "iso:country":"GB",
    "sg:address":"2 Exchange Rd",
    "sg:city":"Nottingham",
    "sg:classifiers":[
        {
            "category":"Building & Trades",
            "subcategory":"Construction",
            "type":"Services"
        }
    ],
    "sg:postcode":"NG2 6BZ",
    "sg:province":"Nottinghamshire",
    "sg:tags":[
        "window",
        "door"
    ],
    "wof:name":"Forman,Andrew,",
    "wof:placetype":"venue"
},
  "geometry": {"coordinates":[-1.12642,52.929695],"type":"Point"}
}