{
  "type": "Feature",
  "properties": {
    "addr:full":"94 Leonard Street London Greater London EC2A 4RH",
    "addr:housenumber":"94",
    "addr:postcode":"ec2a 4rh",
    "addr:street":"Leonard Street",
    "iso:country":"GB",
    "sg:address":"94 Leonard Street",
    "sg:city":"London",
    "sg:classifiers":[
        {
            "category":"Professional",
            "subcategory":"Art Services",
            "type":"Services"
        }
    ],
    "sg:postcode":"EC2A 4RH",
    "sg:province":"Greater London",
    "sg:tags":[
        "consultant",
        "design"
    ],
    "wof:name":"The Corporate Village Ltd.",
    "wof:placetype":"venue"
},
  "geometry": {"coordinates":[-0.0818430036,51.5245399475],"type":"Point"}
}