{
  "type": "Feature",
  "properties": {
    "addr:full":"6 Heath Field, Stacey Bushes Milton Keynes Buckinghamshire MK12 6HP",
    "addr:housenumber":"6",
    "addr:postcode":"mk12 6hp",
    "addr:street":"Heath Field",
    "iso:country":"GB",
    "sg:address":"6 Heath Field, Stacey Bushes",
    "sg:city":"Milton Keynes",
    "sg:classifiers":[
        {
            "category":"Shopping",
            "subcategory":"Stationery & Office Supplies",
            "type":"Retail Goods"
        }
    ],
    "sg:postcode":"MK12 6HP",
    "sg:province":"Buckinghamshire",
    "sg:tags":[
        "printers'"
    ],
    "wof:name":"Ribbon Revival",
    "wof:placetype":"venue"
},
  "geometry": {"coordinates":[-0.727749,52.005856],"type":"Point"}
}