{
  "type": "Feature",
  "properties": {
    "addr:full":"1 Filey Road Scarborough North Yorkshire YO11 2SG",
    "addr:housenumber":"1",
    "addr:postcode":"yo11 2sg",
    "addr:street":"Filey Road",
    "iso:country":"GB",
    "sg:address":"1 Filey Road",
    "sg:city":"Scarborough",
    "sg:classifiers":[
        {
            "category":"Government",
            "subcategory":"Post Office",
            "type":"Public Place"
        }
    ],
    "sg:phone":"+44 1723 365138",
    "sg:postcode":"YO11 2SG",
    "sg:province":"North Yorkshire",
    "wof:name":"South Cliff Post Office",
    "wof:placetype":"venue"
},
  "geometry": {"coordinates":[-0.403031,54.272648],"type":"Point"}
}