{
  "type": "Feature",
  "properties": {
    "iso:country":"GB",
    "sg:address":"17 High Street",
    "sg:city":"Bridlington",
    "sg:classifiers":[
        {
            "category":"Retail",
            "subcategory":"Repair Shop",
            "type":"Services"
        },
        {
            "category":"Shopping",
            "subcategory":"Computers & Home Electronics",
            "type":"Retail Goods"
        }
    ],
    "sg:postcode":"YO16 4PR",
    "sg:province":"East Riding of Yorkshire",
    "sg:tags":[
        "video",
        "television",
        "aerial",
        "radio"
    ],
    "wof:name":"Burlington T V and Video",
    "wof:placetype":"venue"
},
  "geometry": {"coordinates":[-0.2054809928,54.0930747986],"type":"Point"}
}