{
  "type": "Feature",
  "properties": {
    "addr:full":"Diomed House, 2000 Cambridge Research Park, Ely Road Cambridge Cambridgeshire CB5 9TE",
    "addr:housenumber":"2000",
    "addr:postcode":"cb5 9te",
    "addr:street":"Cambridge Research Park Ely Road",
    "iso:country":"GB",
    "sg:address":"Diomed House, 2000 Cambridge Research Park, Ely Road",
    "sg:city":"Cambridge",
    "sg:classifiers":[
        {
            "category":"Health Services",
            "subcategory":"Clinic",
            "type":"Services"
        }
    ],
    "sg:phone":"+44 1223 729300",
    "sg:postcode":"CB5 9TE",
    "sg:province":"Cambridgeshire",
    "sg:tags":[
        "medical"
    ],
    "wof:name":"Diomed Ltd.",
    "wof:placetype":"venue"
},
  "geometry": {"coordinates":[0.1733299941,52.2892990112],"type":"Point"}
}