{
  "type": "Feature",
  "properties": {
    "addr:full":"386-388 Brixton Road London Greater London SW9 7AW",
    "addr:housenumber":"386-388",
    "addr:postcode":"sw9 7aw",
    "addr:street":"Brixton Road",
    "iso:country":"GB",
    "sg:address":"386-388 Brixton Road",
    "sg:city":"London",
    "sg:classifiers":[
        {
            "category":"Shopping",
            "subcategory":"Clothing, Apparel, & Fashions",
            "type":"Retail Goods"
        }
    ],
    "sg:phone":"+44 20 7326 4182",
    "sg:postcode":"SW9 7AW",
    "sg:province":"Greater London",
    "sg:tags":[
        "shop",
        "clothing"
    ],
    "wof:name":"Fabco Ltd.",
    "wof:placetype":"venue"
},
  "geometry": {"coordinates":[-0.113981,51.465576],"type":"Point"}
}