{
  "type": "Feature",
  "properties": {
    "iso:country":"GB",
    "sg:address":"182 Hasland Rd",
    "sg:city":"Chesterfield",
    "sg:classifiers":[
        {
            "category":"Health Services",
            "subcategory":"Dentist",
            "type":"Services"
        }
    ],
    "sg:phone":"+44 1246 232039",
    "sg:postcode":"S41 0AG",
    "sg:province":"Derbyshire",
    "wof:name":"S Thompson",
    "wof:placetype":"venue"
},
  "geometry": {"coordinates":[-1.411427,53.222591],"type":"Point"}
}