{
  "type": "Feature",
  "properties": {
    "addr:full":"Bridgend, 1 Fore Street Looe Cornwall PL13 1HH",
    "addr:housenumber":"1",
    "addr:postcode":"pl13 1hh",
    "addr:street":"Bridgend;Fore Street",
    "iso:country":"GB",
    "sg:address":"Bridgend, 1 Fore Street",
    "sg:city":"Looe",
    "sg:classifiers":[
        {
            "category":"Fast Food",
            "type":"Food & Drink"
        },
        {
            "category":"Restaurant",
            "type":"Food & Drink"
        }
    ],
    "sg:phone":"+44 1503 262038",
    "sg:postcode":"PL13 1HH",
    "sg:province":"Cornwall",
    "sg:tags":[
        "away",
        "-",
        "take",
        "pizza"
    ],
    "wof:name":"Pizza Palace",
    "wof:placetype":"venue"
},
  "geometry": {"coordinates":[-4.4551510811,50.3570518494],"type":"Point"}
}