{
  "type": "Feature",
  "properties": {
    "iso:country":"GB",
    "sg:address":"20-22 Hagley Road",
    "sg:city":"Stourbridge",
    "sg:classifiers":[
        {
            "category":"Real Estate",
            "subcategory":"Real Estate Operator",
            "type":"Services"
        },
        {
            "category":"Real Estate",
            "subcategory":"Real Estate Agent",
            "type":"Services"
        }
    ],
    "sg:phone":"+44 1384 440884",
    "sg:postcode":"DY8 1QQ",
    "sg:province":"Staffordshire",
    "sg:tags":[
        "letting"
    ],
    "wof:name":"Letting Services Ltd.",
    "wof:placetype":"venue"
},
  "geometry": {"coordinates":[-2.1435580254,52.4536018372],"type":"Point"}
}