{
  "type": "Feature",
  "properties": {
    "iso:country":"GB",
    "sg:address":"Murco Service Station, South Pde",
    "sg:city":"Chiswick",
    "sg:classifiers":[
        {
            "category":"Retail",
            "subcategory":"Auto Repair",
            "type":"Services"
        }
    ],
    "sg:phone":"+44 20 8994 3817",
    "sg:postcode":"W4 1JU",
    "sg:province":"Greater London",
    "sg:tags":[
        "modification",
        "garage"
    ],
    "wof:name":"Chiswick Car Care",
    "wof:placetype":"venue"
},
  "geometry": {"coordinates":[-0.25697,51.495998],"type":"Point"}
}