{
  "type": "Feature",
  "properties": {
    "addr:full":"48 Chestnut Avenue Chatham Kent ME5 9AJ",
    "addr:housenumber":"48",
    "addr:postcode":"me5 9aj",
    "addr:street":"Chestnut Avenue",
    "iso:country":"GB",
    "sg:address":"48 Chestnut Avenue",
    "sg:city":"Chatham",
    "sg:classifiers":[
        {
            "category":"Travel",
            "subcategory":"Travel Agent",
            "type":"Entertainment"
        }
    ],
    "sg:phone":"+44 1634 201646",
    "sg:postcode":"ME5 9AJ",
    "sg:province":"Kent",
    "wof:name":"Maida Holidays",
    "wof:placetype":"venue"
},
  "geometry": {"coordinates":[0.521357,51.343716],"type":"Point"}
}