{
  "type": "Feature",
  "properties": {
    "addr:full":"77 Listerhills Road Bradford West Yorkshire BD7 1HZ",
    "addr:housenumber":"77",
    "addr:postcode":"bd7 1hz",
    "addr:street":"Listerhills Road",
    "iso:country":"GB",
    "sg:address":"77 Listerhills Road",
    "sg:city":"Bradford",
    "sg:classifiers":[
        {
            "category":"Bars & Pubs",
            "type":"Food & Drink"
        }
    ],
    "sg:postcode":"BD7 1HZ",
    "sg:province":"West Yorkshire",
    "sg:tags":[
        "pubs",
        "inn"
    ],
    "wof:name":"Dunnachir,Julie,",
    "wof:placetype":"venue"
},
  "geometry": {"coordinates":[-1.768179,53.79414],"type":"Point"}
}