{
  "type": "Feature",
  "properties": {
    "iso:country":"GB",
    "sg:address":"20 North Malvern Road",
    "sg:city":"Malvern",
    "sg:classifiers":[
        {
            "category":"Autos & Motor Vehicles",
            "subcategory":"Motorcycle Sales",
            "type":"Retail Goods"
        }
    ],
    "sg:phone":"+44 1684 575802",
    "sg:postcode":"WR14 4LT",
    "sg:province":"Herefordshire",
    "sg:tags":[
        "chauffeur",
        "driven",
        "car"
    ],
    "wof:name":"Bayleys",
    "wof:placetype":"venue"
},
  "geometry": {"coordinates":[-2.334041,52.120541],"type":"Point"}
}