{
  "type": "Feature",
  "properties": {
    "addr:full":"8 North Street, Ashburton Newton Abbot Devon TQ13 7QD",
    "addr:housenumber":"8",
    "addr:postcode":"tq13 7qd",
    "addr:street":"North Street",
    "iso:country":"GB",
    "sg:address":"8 North Street, Ashburton",
    "sg:city":"Newton Abbot",
    "sg:classifiers":[
        {
            "category":"Shopping",
            "subcategory":"Pharmacy",
            "type":"Retail Goods"
        }
    ],
    "sg:phone":"+44 1364 652222",
    "sg:postcode":"TQ13 7QD",
    "sg:province":"Devon",
    "sg:tags":[
        "pharmacist",
        "chemist"
    ],
    "wof:name":"Lloyds Chemist",
    "wof:placetype":"venue"
},
  "geometry": {"coordinates":[-3.7562470436,50.5157203674],"type":"Point"}
}