{
  "type": "Feature",
  "properties": {
    "iso:country":"GB",
    "sg:address":"5 Red Lion Parade, Bridge St",
    "sg:city":"Pinner",
    "sg:classifiers":[
        {
            "category":"Real Estate",
            "subcategory":"Real Estate Agent",
            "type":"Services"
        }
    ],
    "sg:phone":"+44 20 8866 2131",
    "sg:postcode":"HA5 3JD",
    "sg:province":"Greater London",
    "wof:name":"Corbett Altman",
    "wof:placetype":"venue"
},
  "geometry": {"coordinates":[-0.38253,51.594528],"type":"Point"}
}