{
  "type": "Feature",
  "properties": {
    "iso:country":"GB",
    "sg:address":"Bonnyton Croft, Bonnyton, Old Rayne",
    "sg:city":"Insch",
    "sg:classifiers":[
        {
            "category":"Health Services",
            "subcategory":"Health Practitioner",
            "type":"Services"
        }
    ],
    "sg:phone":"+44 1464 851444",
    "sg:postcode":"AB52 6TD",
    "sg:province":"Aberdeenshire",
    "sg:tags":[
        "acupuncture"
    ],
    "wof:name":"S P May",
    "wof:placetype":"venue"
},
  "geometry": {"coordinates":[-2.613011,57.342918],"type":"Point"}
}