{
  "type": "Feature",
  "properties": {
    "addr:full":"483 Hornsey Road London Greater London N19 3QL",
    "addr:housenumber":"483",
    "addr:postcode":"n19 3ql",
    "addr:street":"Hornsey Road",
    "iso:country":"GB",
    "sg:address":"483 Hornsey Road",
    "sg:city":"London",
    "sg:classifiers":[
        {
            "category":"Retail",
            "subcategory":"Laundry & Dry Cleaning",
            "type":"Services"
        }
    ],
    "sg:phone":"+44 20 7272 5171",
    "sg:postcode":"N19 3QL",
    "sg:province":"Greater London",
    "sg:tags":[
        "launderette"
    ],
    "wof:name":"Bendix Self Service Launderettes",
    "wof:placetype":"venue"
},
  "geometry": {"coordinates":[-0.123883,51.568829],"type":"Point"}
}