{
  "type": "Feature",
  "properties": {
    "addr:full":"Centenary Business Park Henley-on-thames Berkshire RG9 1DS",
    "addr:postcode":"rg9 1ds",
    "addr:street":"Park",
    "iso:country":"GB",
    "sg:address":"Centenary Business Park",
    "sg:city":"Henley-on-thames",
    "sg:classifiers":[
        {
            "category":"Food & Beverages",
            "subcategory":"Specialty",
            "type":"Retail Goods"
        }
    ],
    "sg:phone":"+44 1491 411767",
    "sg:postcode":"RG9 1DS",
    "sg:province":"Berkshire",
    "sg:tags":[
        "product",
        "health"
    ],
    "wof:name":"Lifestyle Healthcare Ltd.",
    "wof:placetype":"venue"
},
  "geometry": {"coordinates":[-0.903189,51.535297],"type":"Point"}
}