{
  "type": "Feature",
  "properties": {
    "iso:country":"GB",
    "sg:address":"1 Northcroft Lane",
    "sg:city":"Newbury",
    "sg:classifiers":[
        {
            "category":"Personal",
            "subcategory":"Beauty Salon",
            "type":"Services"
        }
    ],
    "sg:postcode":"RG14 1BT",
    "sg:province":"Berkshire",
    "sg:tags":[
        "lady",
        "hairdresser"
    ],
    "wof:name":"Valda",
    "wof:placetype":"venue"
},
  "geometry": {"coordinates":[-1.3260550499,51.4018478394],"type":"Point"}
}