{
  "type": "Feature",
  "properties": {
    "iso:country":"GB",
    "sg:address":"9 Bath Road, Peasedown St John",
    "sg:city":"Bath",
    "sg:classifiers":[
        {
            "category":"Food & Beverages",
            "subcategory":"Meat & Fish",
            "type":"Retail Goods"
        }
    ],
    "sg:phone":"+44 1761 436849",
    "sg:postcode":"BA2 8DX",
    "sg:province":"Somerset",
    "sg:tags":[
        "butcher"
    ],
    "wof:name":"Brian Jesse Millard",
    "wof:placetype":"venue"
},
  "geometry": {"coordinates":[-2.426022,51.315746],"type":"Point"}
}