{
  "type": "Feature",
  "properties": {
    "iso:country":"GB",
    "sg:address":"11 Bingham Road, Radcliffe-on-trent",
    "sg:city":"Nottingham",
    "sg:classifiers":[
        {
            "category":"Home & Garden",
            "subcategory":"Furniture",
            "type":"Retail Goods"
        }
    ],
    "sg:phone":"+44 115 933 2532",
    "sg:postcode":"NG12 2FY",
    "sg:province":"Nottinghamshire",
    "wof:name":"J H Supplies (Furniture) Ltd.",
    "wof:placetype":"venue"
},
  "geometry": {"coordinates":[-1.0355249643,52.9471549988],"type":"Point"}
}