{
  "type": "Feature",
  "properties": {
    "addr:full":"6 Ashworth Lane Bolton Lancashire BL1 8RA",
    "addr:housenumber":"6",
    "addr:postcode":"bl1 8ra",
    "addr:street":"Ashworth Lane",
    "iso:country":"GB",
    "sg:address":"6 Ashworth Lane",
    "sg:city":"Bolton",
    "sg:classifiers":[
        {
            "category":"Building & Trades",
            "subcategory":"Construction",
            "type":"Services"
        }
    ],
    "sg:postcode":"BL1 8RA",
    "sg:province":"Lancashire",
    "sg:tags":[
        "joiner",
        "carpenter"
    ],
    "wof:name":"Ian Smith",
    "wof:placetype":"venue"
},
  "geometry": {"coordinates":[-2.4317638874,53.6039848328],"type":"Point"}
}