{
  "type": "Feature",
  "properties": {
    "iso:country":"GB",
    "sg:address":"Lynton, Waterside, Burwell",
    "sg:city":"Cambridge",
    "sg:classifiers":[
        {
            "category":"Professional",
            "subcategory":"Business Services",
            "type":"Services"
        }
    ],
    "sg:phone":"+44 1223 890558",
    "sg:postcode":"CB5 0BJ",
    "sg:province":"Cambridgeshire",
    "sg:tags":[
        "shop",
        "cleaning"
    ],
    "wof:name":"C M S Contract Cleaning Services",
    "wof:placetype":"venue"
},
  "geometry": {"coordinates":[0.3289549947,52.2775611877],"type":"Point"}
}