{
  "type": "Feature",
  "properties": {
    "iso:country":"GB",
    "sg:address":"12 Cherry Drive",
    "sg:city":"Canterbury",
    "sg:classifiers":[
        {
            "category":"Shopping",
            "subcategory":"Antiques",
            "type":"Retail Goods"
        }
    ],
    "sg:phone":"+44 1227 459939",
    "sg:postcode":"CT2 8HF",
    "sg:province":"Kent",
    "wof:name":"Borough Antiques",
    "wof:placetype":"venue"
},
  "geometry": {"coordinates":[1.0633590221,51.2872047424],"type":"Point"}
}