{
  "type": "Feature",
  "properties": {
    "addr:full":"Lugar St Cumnock East Ayrshire KA18 1AD",
    "addr:postcode":"ka18 1ad",
    "addr:street":"Lugar St",
    "iso:country":"GB",
    "sg:address":"Lugar St",
    "sg:city":"Cumnock",
    "sg:classifiers":[
        {
            "category":"Retail",
            "subcategory":"Funeral Services",
            "type":"Services"
        }
    ],
    "sg:phone":"+44 1290 425900",
    "sg:postcode":"KA18 1AD",
    "sg:province":"East Ayrshire",
    "wof:name":"Brian Allan Whyte & Sons",
    "wof:placetype":"venue"
},
  "geometry": {"coordinates":[-4.264099,55.453255],"type":"Point"}
}