{
  "type": "Feature",
  "properties": {
    "iso:country":"GB",
    "sg:address":"90 Ings La",
    "sg:city":"Rochdale",
    "sg:classifiers":[
        {
            "category":"Professional",
            "subcategory":"Detective & Security Services",
            "type":"Services"
        }
    ],
    "sg:postcode":"OL12 7DX",
    "sg:province":"Lancashire",
    "sg:tags":[
        "alarm",
        "burglar",
        "system"
    ],
    "wof:name":"Holden,Michael,",
    "wof:placetype":"venue"
},
  "geometry": {"coordinates":[-2.181686,53.62571],"type":"Point"}
}