{
  "type": "Feature",
  "properties": {
    "iso:country":"GB",
    "sg:address":"33 St Marys Road, Garston",
    "sg:city":"Liverpool",
    "sg:classifiers":[
        {
            "category":"Bars & Pubs",
            "type":"Food & Drink"
        },
        {
            "category":"Community Center",
            "subcategory":"Social",
            "type":"Public Place"
        }
    ],
    "sg:phone":"+44 151 281 5533",
    "sg:postcode":"L19 2NJ",
    "sg:province":"Merseyside",
    "sg:tags":[
        "pubs",
        "house",
        "inn",
        "activity"
    ],
    "wof:name":"Mariners",
    "wof:placetype":"venue"
},
  "geometry": {"coordinates":[-2.8988978863,53.3540382385],"type":"Point"}
}