{
  "type": "Feature",
  "properties": {
    "addr:full":"Shepherds Hill, London Road Reading Berkshire RG6 1BB",
    "addr:postcode":"rg6 1bb",
    "addr:street":"Shepherds Hill London Road",
    "iso:country":"GB",
    "sg:address":"Shepherds Hill, London Road",
    "sg:city":"Reading",
    "sg:classifiers":[
        {
            "category":"Organizations",
            "subcategory":"Community Association",
            "type":"Services"
        },
        {
            "category":"Organizations",
            "subcategory":"Membership Organization",
            "type":"Services"
        }
    ],
    "sg:phone":"+44 118 926 8413",
    "sg:postcode":"RG6 1BB",
    "sg:province":"Berkshire",
    "sg:tags":[
        "club",
        "social"
    ],
    "wof:name":"Brunel Club",
    "wof:placetype":"venue"
},
  "geometry": {"coordinates":[-0.919943,51.459961],"type":"Point"}
}