{
  "type": "Feature",
  "properties": {
    "addr:full":"Leicester Lane, Desford Leicester Leicestershire LE9 9JL",
    "addr:postcode":"le9 9jl",
    "addr:street":"Leicester Lane",
    "iso:country":"GB",
    "sg:address":"Leicester Lane, Desford",
    "sg:city":"Leicester",
    "sg:classifiers":[
        {
            "category":"Education",
            "subcategory":"School",
            "type":"Public Place"
        }
    ],
    "sg:phone":"+44 1455 822841",
    "sg:postcode":"LE9 9JL",
    "sg:province":"Leicestershire",
    "sg:tags":[
        "local",
        "authority"
    ],
    "wof:name":"Bosworth Community College",
    "wof:placetype":"venue"
},
  "geometry": {"coordinates":[-1.268914,52.618011],"type":"Point"}
}