{
  "type": "Feature",
  "properties": {
    "addr:full":"Glebe House, Vicarage Drive Barking Essex IG11 7NS",
    "addr:postcode":"ig11 7ns",
    "addr:street":"Vicarage Drive",
    "iso:country":"GB",
    "sg:address":"Glebe House, Vicarage Drive",
    "sg:city":"Barking",
    "sg:classifiers":[
        {
            "category":"Professional",
            "subcategory":"Business Services",
            "type":"Services"
        }
    ],
    "sg:phone":"+44 20 8591 5151",
    "sg:postcode":"IG11 7NS",
    "sg:province":"Essex",
    "sg:tags":[
        "bookmaker"
    ],
    "wof:name":"Coral Racing Ltd.",
    "wof:placetype":"venue"
},
  "geometry": {"coordinates":[0.081602,51.537037],"type":"Point"}
}