{
  "type": "Feature",
  "properties": {
    "iso:country":"GB",
    "sg:address":"The Town House, 63 High Street, Chobham",
    "sg:city":"Woking",
    "sg:classifiers":[
        {
            "category":"Professional",
            "subcategory":"Management & Consulting",
            "type":"Services"
        },
        {
            "category":"Landmark",
            "subcategory":"Tourist Information",
            "type":"Public Place"
        }
    ],
    "sg:phone":"+44 1276 858930",
    "sg:postcode":"GU24 8AF",
    "sg:province":"Surrey",
    "sg:tags":[
        "sport"
    ],
    "wof:name":"Professional Sports Events Ltd",
    "wof:placetype":"venue"
},
  "geometry": {"coordinates":[-0.603856,51.346939],"type":"Point"}
}