{
  "type": "Feature",
  "properties": {
    "iso:country":"GB",
    "sg:address":"206 Wellingborough Road",
    "sg:city":"Rushden",
    "sg:classifiers":[
        {
            "category":"Manufacturing",
            "subcategory":"Leather Goods",
            "type":"Manufacturing & Wholesale Goods"
        },
        {
            "category":"Personal",
            "subcategory":"Skin Care",
            "type":"Services"
        }
    ],
    "sg:phone":"+44 1933 312231",
    "sg:postcode":"NN10 9SY",
    "sg:province":"Bedfordshire",
    "sg:tags":[
        "merchant",
        "manufacture",
        "product",
        "hide",
        "supply"
    ],
    "wof:name":"Wildman & Bugby Ltd",
    "wof:placetype":"venue"
},
  "geometry": {"coordinates":[-0.608239,52.292824],"type":"Point"}
}