{
  "type": "Feature",
  "properties": {
    "iso:country":"GB",
    "sg:address":"Kwik Save Store, Stars La",
    "sg:city":"Yeovil",
    "sg:classifiers":[
        {
            "category":"Food & Beverages",
            "subcategory":"Fruits & Vegetables",
            "type":"Retail Goods"
        }
    ],
    "sg:postcode":"BA20 1NR",
    "sg:province":"Somerset",
    "sg:tags":[
        "greengrocer"
    ],
    "wof:name":"Hurst Parnell & Co Ltd",
    "wof:placetype":"venue"
},
  "geometry": {"coordinates":[-2.6277899742,50.9405593872],"type":"Point"}
}