{
  "type": "Feature",
  "properties": {
    "iso:country":"GB",
    "sg:address":"Corporation Street",
    "sg:city":"Sowerby Bridge",
    "sg:classifiers":[
        {
            "category":"Wholesale",
            "subcategory":"Machinery & Supplies",
            "type":"Manufacturing & Wholesale Goods"
        }
    ],
    "sg:phone":"+44 1422 839651",
    "sg:postcode":"HX6 2QQ",
    "sg:province":"West Yorkshire",
    "sg:tags":[
        "theatrical"
    ],
    "wof:name":"White Light North Ltd.",
    "wof:placetype":"venue"
},
  "geometry": {"coordinates":[-1.911699,53.70887],"type":"Point"}
}