{
  "type": "Feature",
  "properties": {
    "iso:country":"GB",
    "sg:address":"Devon Farm, Kennoway",
    "sg:city":"Leven",
    "sg:classifiers":[
        {
            "category":"Home & Garden",
            "subcategory":"Garden Supply",
            "type":"Retail Goods"
        },
        {
            "category":"Farming",
            "subcategory":"Livestock Farm",
            "type":"Manufacturing & Wholesale Goods"
        }
    ],
    "sg:phone":"+44 1333 350262",
    "sg:postcode":"KY8 5SH",
    "sg:province":"Fife",
    "sg:tags":[
        "bulb",
        "grower",
        "others"
    ],
    "wof:name":"The Firm of Dawson Robert",
    "wof:placetype":"venue"
},
  "geometry": {"coordinates":[-3.048894,56.211174],"type":"Point"}
}