{
  "type": "Feature",
  "properties": {
    "addr:full":"Stag Hill, Chilton Foliat Hungerford Berkshire RG17 0TF",
    "addr:postcode":"rg17 0tf",
    "addr:street":"Stag Hill",
    "iso:country":"GB",
    "sg:address":"Stag Hill, Chilton Foliat",
    "sg:city":"Hungerford",
    "sg:classifiers":[
        {
            "category":"Education",
            "subcategory":"School",
            "type":"Public Place"
        },
        {
            "category":"Government",
            "subcategory":"Office",
            "type":"Public Place"
        }
    ],
    "sg:phone":"+44 1488 682630",
    "sg:postcode":"RG17 0TF",
    "sg:province":"Berkshire",
    "sg:tags":[
        "local",
        "authority"
    ],
    "wof:name":"Chilton Foliat C of E Primary School",
    "wof:placetype":"venue"
},
  "geometry": {"coordinates":[-1.5161559582,51.4131965637],"type":"Point"}
}