{
  "type": "Feature",
  "properties": {
    "addr:full":"69 Fonnereau Road Ipswich Suffolk IP1 3JN",
    "addr:housenumber":"69",
    "addr:postcode":"ip1 3jn",
    "addr:street":"Fonnereau Road",
    "iso:country":"GB",
    "sg:address":"69 Fonnereau Road",
    "sg:city":"Ipswich",
    "sg:classifiers":[
        {
            "category":"Health Services",
            "subcategory":"Dentist",
            "type":"Services"
        }
    ],
    "sg:phone":"+44 1473 250977",
    "sg:postcode":"IP1 3JN",
    "sg:province":"Suffolk",
    "wof:name":"Ringrose & Wright",
    "wof:placetype":"venue"
},
  "geometry": {"coordinates":[1.1514550447,52.0619316101],"type":"Point"}
}