{
  "type": "Feature",
  "properties": {
    "addr:full":"12 Perth Road St Leonards-on-sea East Sussex TN37 7EB",
    "addr:housenumber":"12",
    "addr:postcode":"leonards-on-sea;tn37 7eb",
    "addr:street":"Perth Road St",
    "iso:country":"GB",
    "sg:address":"12 Perth Road",
    "sg:city":"St Leonards-on-sea",
    "sg:classifiers":[
        {
            "category":"Building & Trades",
            "subcategory":"Construction",
            "type":"Services"
        }
    ],
    "sg:postcode":"TN37 7EB",
    "sg:province":"East Sussex",
    "sg:tags":[
        "builder"
    ],
    "wof:name":"Chris Burt Builder",
    "wof:placetype":"venue"
},
  "geometry": {"coordinates":[0.5547779799,50.8721542358],"type":"Point"}
}