{
  "type": "Feature",
  "properties": {
    "iso:country":"GB",
    "sg:address":"138 Bottesford Lane",
    "sg:city":"Scunthorpe",
    "sg:classifiers":[
        {
            "category":"Building & Trades",
            "subcategory":"Construction",
            "type":"Services"
        }
    ],
    "sg:phone":"+44 1724 271275",
    "sg:postcode":"DN16 3QH",
    "sg:province":"Lincolnshire",
    "sg:tags":[
        "joiner",
        "carpenter"
    ],
    "wof:name":"Rosewood Joinery",
    "wof:placetype":"venue"
},
  "geometry": {"coordinates":[-0.6469550133,53.5587387085],"type":"Point"}
}