{
  "type": "Feature",
  "properties": {
    "addr:full":"Bailie Court, 197a North Lane Aldershot Hampshire GU12 4SY",
    "addr:housenumber":"197a",
    "addr:postcode":"gu12 4sy",
    "addr:street":"Bailie Court;North Lane",
    "iso:country":"GB",
    "sg:address":"Bailie Court, 197a North Lane",
    "sg:city":"Aldershot",
    "sg:classifiers":[
        {
            "category":"Cafe",
            "type":"Food & Drink"
        }
    ],
    "sg:phone":"+44 1252 315268",
    "sg:postcode":"GU12 4SY",
    "sg:province":"Hampshire",
    "sg:tags":[
        "tea",
        "snack",
        "bar",
        "room"
    ],
    "wof:name":"Sue's Cafe",
    "wof:placetype":"venue"
},
  "geometry": {"coordinates":[-0.7431179881,51.2505531311],"type":"Point"}
}