{
  "type": "Feature",
  "properties": {
    "iso:country":"GB",
    "sg:address":"11 Devon Avenue",
    "sg:city":"Twickenham",
    "sg:classifiers":[
        {
            "category":"Professional",
            "subcategory":"Management & Consulting",
            "type":"Services"
        }
    ],
    "sg:phone":"+44 1253 782551",
    "sg:postcode":"TW2 6PN",
    "sg:province":"Greater London",
    "sg:tags":[
        "consultant",
        "promotion",
        "direct",
        "sale"
    ],
    "wof:name":"Pauline Paul (Uk) Ltd.",
    "wof:placetype":"venue"
},
  "geometry": {"coordinates":[-0.353618,51.44735],"type":"Point"}
}