{
  "type": "Feature",
  "properties": {
    "addr:full":"1a Wheeler House, Newbottle St Houghton Le Spring Durham DH4 4AL",
    "addr:housenumber":"1a",
    "addr:postcode":"dh4 4al",
    "addr:street":"Wheeler;Newbottle St",
    "iso:country":"GB",
    "sg:address":"1a Wheeler House, Newbottle St",
    "sg:city":"Houghton Le Spring",
    "sg:classifiers":[
        {
            "category":"Food & Beverages",
            "subcategory":"Fruits & Vegetables",
            "type":"Retail Goods"
        }
    ],
    "sg:phone":"+44 191 584 4607",
    "sg:postcode":"DH4 4AL",
    "sg:province":"Durham",
    "sg:tags":[
        "greengrocer"
    ],
    "wof:name":"Foodweigh",
    "wof:placetype":"venue"
},
  "geometry": {"coordinates":[-1.47041,54.84314],"type":"Point"}
}