{
  "type": "Feature",
  "properties": {
    "iso:country":"GB",
    "sg:address":"18 Albion St, Clifford",
    "sg:city":"Wetherby",
    "sg:classifiers":[
        {
            "category":"Building & Trades",
            "subcategory":"Construction",
            "type":"Services"
        }
    ],
    "sg:postcode":"LS23 6HY",
    "sg:province":"West Yorkshire",
    "sg:tags":[
        "concrete",
        "contractor"
    ],
    "wof:name":"Melton Concrete Products Ltd",
    "wof:placetype":"venue"
},
  "geometry": {"coordinates":[-1.3505430222,53.8934059143],"type":"Point"}
}