{
  "type": "Feature",
  "properties": {
    "iso:country":"GB",
    "sg:address":"17 Brown Lees Road, Brown Lees, Biddulph",
    "sg:city":"Stoke-on-trent",
    "sg:classifiers":[
        {
            "category":"Shopping",
            "subcategory":"News",
            "type":"Retail Goods"
        }
    ],
    "sg:postcode":"ST8 6PJ",
    "sg:province":"Staffordshire",
    "sg:tags":[
        "newsagent"
    ],
    "wof:name":"B T & L Knight",
    "wof:placetype":"venue"
},
  "geometry": {"coordinates":[-2.1870748997,53.1023750305],"type":"Point"}
}