{
  "type": "Feature",
  "properties": {
    "iso:country":"GB",
    "sg:address":"Unit 15 Champagne Whinn, Springs Lane, Walton",
    "sg:city":"Wetherby",
    "sg:classifiers":[
        {
            "category":"Home & Garden",
            "subcategory":"Building Materials",
            "type":"Retail Goods"
        },
        {
            "category":"Building & Trades",
            "subcategory":"Construction",
            "type":"Services"
        }
    ],
    "sg:phone":"+44 1937 844413",
    "sg:postcode":"LS23 7DN",
    "sg:province":"West Yorkshire",
    "sg:tags":[
        "ironwork",
        "product",
        "builder",
        "production",
        "design",
        "diy",
        "iron",
        "wrought"
    ],
    "wof:name":"Brammer Engineering",
    "wof:placetype":"venue"
},
  "geometry": {"coordinates":[-1.327797,53.924114],"type":"Point"}
}