{
  "type": "Feature",
  "properties": {
    "addr:full":"Hundayfield Farm, Marton Cum Grafton York North Yorkshire YO51 9QT",
    "addr:postcode":"yo51 9qt",
    "addr:street":"Cum Grafton",
    "iso:country":"GB",
    "sg:address":"Hundayfield Farm, Marton Cum Grafton",
    "sg:city":"York",
    "sg:classifiers":[
        {
            "category":"Farming",
            "subcategory":"Livestock Farm",
            "type":"Manufacturing & Wholesale Goods"
        }
    ],
    "sg:phone":"+44 1423 322414",
    "sg:postcode":"YO51 9QT",
    "sg:province":"North Yorkshire",
    "sg:tags":[
        "others"
    ],
    "wof:name":"G T Barton & Sons",
    "wof:placetype":"venue"
},
  "geometry": {"coordinates":[-1.3632760048,54.0609092712],"type":"Point"}
}