{
  "type": "Feature",
  "properties": {
    "iso:country":"GB",
    "sg:address":"204 High Street",
    "sg:city":"Hornchurch",
    "sg:classifiers":[
        {
            "category":"Shopping",
            "subcategory":"Pharmacy",
            "type":"Retail Goods"
        }
    ],
    "sg:postcode":"RM12 6QP",
    "sg:province":"Essex",
    "sg:tags":[
        "medicine",
        "therapy"
    ],
    "wof:name":"Reflexology Clinic",
    "wof:placetype":"venue"
},
  "geometry": {"coordinates":[0.223059997,51.5612831116],"type":"Point"}
}