{
  "type": "Feature",
  "properties": {
    "iso:country":"GB",
    "sg:address":"5 Rossett Holt View",
    "sg:city":"Harrogate",
    "sg:classifiers":[
        {
            "category":"Professional",
            "type":"Services"
        }
    ],
    "sg:postcode":"HG2 9AF",
    "sg:province":"North Yorkshire",
    "sg:tags":[
        "entertainer"
    ],
    "wof:name":"Harrogate Concert Party",
    "wof:placetype":"venue"
},
  "geometry": {"coordinates":[-1.550679,53.981304],"type":"Point"}
}