{
  "type": "Feature",
  "properties": {
    "addr:full":"Police Station, High St Fort William Highland PH33 6EE",
    "addr:postcode":"ph33 6ee",
    "addr:street":"High St",
    "iso:country":"GB",
    "sg:address":"Police Station, High St",
    "sg:city":"Fort William",
    "sg:classifiers":[
        {
            "category":"Government",
            "subcategory":"Police Station",
            "type":"Public Place"
        }
    ],
    "sg:phone":"+44 1397 702000",
    "sg:postcode":"PH33 6EE",
    "sg:province":"Highland",
    "sg:tags":[
        "support"
    ],
    "wof:name":"Nothern Constabulary",
    "wof:placetype":"venue"
},
  "geometry": {"coordinates":[-5.1084589958,56.8184318542],"type":"Point"}
}