{
  "type": "Feature",
  "properties": {
    "addr:full":"71 High Street Coldstream Northumberland TD12 4AH",
    "addr:housenumber":"71",
    "addr:postcode":"td12 4ah",
    "addr:street":"High Street",
    "iso:country":"GB",
    "sg:address":"71 High Street",
    "sg:city":"Coldstream",
    "sg:classifiers":[
        {
            "category":"Social Services",
            "subcategory":"Retirement Home",
            "type":"Services"
        }
    ],
    "sg:phone":"+44 1890 882112",
    "sg:postcode":"TD12 4AH",
    "sg:province":"Northumberland",
    "sg:tags":[
        "residential",
        "care"
    ],
    "wof:name":"Victoria Lodge Residential Home for the Elderly",
    "wof:placetype":"venue"
},
  "geometry": {"coordinates":[-2.251176,55.651901],"type":"Point"}
}