{
  "type": "Feature",
  "properties": {
    "iso:country":"GB",
    "sg:address":"Britvic House, Broomfield Road",
    "sg:city":"Chelmsford",
    "sg:classifiers":[
        {
            "category":"Personal",
            "subcategory":"Barber",
            "type":"Services"
        },
        {
            "category":"Manufacturing",
            "subcategory":"Food",
            "type":"Manufacturing & Wholesale Goods"
        }
    ],
    "sg:phone":"+44 1245 261871",
    "sg:postcode":"CM1 1TU",
    "sg:province":"Essex",
    "sg:tags":[
        "unisex",
        "mnfr",
        "drink",
        "soft",
        "hairdresser"
    ],
    "sg:website":"http://www.britvic.co.uk",
    "wof:name":"Britannia Soft Drinks Ltd.",
    "wof:placetype":"venue"
},
  "geometry": {"coordinates":[0.46699,51.746738],"type":"Point"}
}