{
  "type": "Feature",
  "properties": {
    "iso:country":"GB",
    "sg:address":"5th Floor, Clarendon House, Stamford New Road",
    "sg:city":"Altrincham",
    "sg:classifiers":[
        {
            "category":"Freight",
            "type":"Transportation"
        }
    ],
    "sg:postcode":"WA14 1BT",
    "sg:province":"Cheshire",
    "sg:tags":[
        "haulage",
        "road"
    ],
    "wof:name":"Jacob's Haulage & Removals",
    "wof:placetype":"venue"
},
  "geometry": {"coordinates":[-2.348254,53.387589],"type":"Point"}
}