{
  "type": "Feature",
  "properties": {
    "iso:country":"GB",
    "sg:address":"234 Oldbury Road",
    "sg:city":"Oldbury",
    "sg:classifiers":[
        {
            "category":"Manufacturing",
            "subcategory":"Buildings",
            "type":"Manufacturing & Wholesale Goods"
        },
        {
            "category":"Home & Garden",
            "subcategory":"Garden Supply",
            "type":"Retail Goods"
        }
    ],
    "sg:phone":"+44 121 559 9488",
    "sg:postcode":"B65 0QG",
    "sg:province":"West Midlands",
    "sg:tags":[
        "shed",
        "greenhouse"
    ],
    "wof:name":"WILLETTS FENCING WAREHOUSE",
    "wof:placetype":"venue"
},
  "geometry": {"coordinates":[-2.029983,52.483852],"type":"Point"}
}