{
  "type": "Feature",
  "properties": {
    "addr:full":"Unit 20, Central Ind Est, Cable St Wolverhampton West Midlands WV2 2RJ",
    "addr:housenumber":"unit 20",
    "addr:postcode":"wv2 2rj",
    "addr:street":"Central Ind Est Cable St",
    "iso:country":"GB",
    "sg:address":"Unit 20, Central Ind Est, Cable St",
    "sg:city":"Wolverhampton",
    "sg:classifiers":[
        {
            "category":"Manufacturing",
            "subcategory":"Apparel",
            "type":"Manufacturing & Wholesale Goods"
        }
    ],
    "sg:phone":"+44 1902 456161",
    "sg:postcode":"WV2 2RJ",
    "sg:province":"West Midlands",
    "sg:tags":[
        "shirt",
        "maker"
    ],
    "wof:name":"ID Ltd",
    "wof:placetype":"venue"
},
  "geometry": {"coordinates":[-2.1110200882,52.5754585266],"type":"Point"}
}