{
  "type": "Feature",
  "properties": {
    "iso:country":"GB",
    "sg:address":"46 Abbott Lea",
    "sg:city":"Mansfield",
    "sg:classifiers":[
        {
            "category":"Organizations",
            "subcategory":"Non-profit Organization",
            "type":"Services"
        }
    ],
    "sg:phone":"+44 1623 489900",
    "sg:postcode":"NG19 6NF",
    "sg:province":"Derbyshire",
    "sg:tags":[
        "organisation",
        "voluntary",
        "charity"
    ],
    "wof:name":"Arthritis Care Volunteer",
    "wof:placetype":"venue"
},
  "geometry": {"coordinates":[-1.221033,53.156597],"type":"Point"}
}