{
  "type": "Feature",
  "properties": {
    "addr:full":"296 High St Sutton Surrey SM1 1PQ",
    "addr:housenumber":"296",
    "addr:postcode":"sm1 1pq",
    "addr:street":"High St",
    "iso:country":"GB",
    "sg:address":"296 High St",
    "sg:city":"Sutton",
    "sg:classifiers":[
        {
            "category":"Professional",
            "subcategory":"Business Services",
            "type":"Services"
        }
    ],
    "sg:phone":"+44 20 8661 2555",
    "sg:postcode":"SM1 1PQ",
    "sg:province":"Surrey",
    "sg:tags":[
        "fashion",
        "agent"
    ],
    "wof:name":"Natural Looks",
    "wof:placetype":"venue"
},
  "geometry": {"coordinates":[-0.1949149966,51.3688316345],"type":"Point"}
}