{
  "type": "Feature",
  "properties": {
    "iso:country":"GB",
    "sg:address":"Tan Lane",
    "sg:city":"Exeter",
    "sg:classifiers":[
        {
            "category":"Freight",
            "type":"Transportation"
        }
    ],
    "sg:phone":"+44 1392 841316",
    "sg:postcode":"EX2 8EG",
    "sg:province":"Devon",
    "sg:tags":[
        "haulage",
        "road"
    ],
    "wof:name":"Wally Balsdon Ltd.",
    "wof:placetype":"venue"
},
  "geometry": {"coordinates":[-3.5317099094,50.7129936218],"type":"Point"}
}