{
  "type": "Feature",
  "properties": {
    "iso:country":"GB",
    "sg:address":"Westlands Farm, Osmotherley",
    "sg:city":"Northallerton",
    "sg:classifiers":[
        {
            "category":"Farming",
            "subcategory":"Dairy Farm",
            "type":"Manufacturing & Wholesale Goods"
        }
    ],
    "sg:phone":"+44 1609 883384",
    "sg:postcode":"DL6 3AR",
    "sg:province":"North Yorkshire",
    "wof:name":"D Stockdale",
    "wof:placetype":"venue"
},
  "geometry": {"coordinates":[-1.302098,54.368725],"type":"Point"}
}