{
  "type": "Feature",
  "properties": {
    "iso:country":"GB",
    "sg:address":"P O Box 166, Ashley Road",
    "sg:city":"St Albans",
    "sg:classifiers":[
        {
            "category":"Building & Trades",
            "subcategory":"Plumbing",
            "type":"Services"
        }
    ],
    "sg:phone":"+44 1727 860315",
    "sg:postcode":"AL4 9JE",
    "sg:province":"Hertfordshire",
    "sg:tags":[
        "drain",
        "clearance",
        "sewer"
    ],
    "wof:name":"Dial-A-Rod",
    "wof:placetype":"venue"
},
  "geometry": {"coordinates":[-0.29342,51.76329],"type":"Point"}
}