{
  "type": "Feature",
  "properties": {
    "iso:country":"GB",
    "sg:address":"Clocken Syke Farm, Dacre",
    "sg:city":"Harrogate",
    "sg:classifiers":[
        {
            "category":"Farming",
            "subcategory":"Dairy Farm",
            "type":"Manufacturing & Wholesale Goods"
        },
        {
            "category":"Farming",
            "subcategory":"Livestock Farm",
            "type":"Manufacturing & Wholesale Goods"
        }
    ],
    "sg:postcode":"HG3 4AE",
    "sg:province":"North Yorkshire",
    "sg:tags":[
        "others"
    ],
    "wof:name":"J Bradley & Son",
    "wof:placetype":"venue"
},
  "geometry": {"coordinates":[-1.707774,54.043049],"type":"Point"}
}