{
  "type": "Feature",
  "properties": {
    "iso:country":"GB",
    "sg:address":"South Holland Enterprise Park, Stephenson St",
    "sg:city":"Spalding",
    "sg:classifiers":[
        {
            "category":"Freight",
            "type":"Transportation"
        }
    ],
    "sg:phone":"+44 1775 710616",
    "sg:postcode":"PE11 3SW",
    "sg:province":"Lincolnshire",
    "sg:tags":[
        "forwarders"
    ],
    "wof:name":"Silvergrid International",
    "wof:placetype":"venue"
},
  "geometry": {"coordinates":[-0.180834,52.761017],"type":"Point"}
}