{
  "type": "Feature",
  "properties": {
    "iso:country":"GB",
    "sg:address":"20 Valletort Road, Millbridge",
    "sg:city":"Plymouth",
    "sg:classifiers":[
        {
            "category":"Building & Trades",
            "subcategory":"Construction",
            "type":"Services"
        }
    ],
    "sg:phone":"+44 1752 562004",
    "sg:postcode":"PL1 5PH",
    "sg:province":"Devon",
    "sg:tags":[
        "decorator",
        "painter"
    ],
    "wof:name":"Hilton Decorations",
    "wof:placetype":"venue"
},
  "geometry": {"coordinates":[-4.160533905,50.3758811951],"type":"Point"}
}