{
  "type": "Feature",
  "properties": {
    "iso:country":"GB",
    "sg:address":"Church Lane, Ipstones",
    "sg:city":"Stoke-on-trent",
    "sg:classifiers":[
        {
            "category":"Building & Trades",
            "subcategory":"Plumbing",
            "type":"Services"
        }
    ],
    "sg:phone":"+44 1538 266465",
    "sg:postcode":"ST10 2LF",
    "sg:province":"Staffordshire",
    "sg:tags":[
        "heating"
    ],
    "wof:name":"D R Glover Plumbing & Heating",
    "wof:placetype":"venue"
},
  "geometry": {"coordinates":[-1.976644,53.050755],"type":"Point"}
}