{
  "type": "Feature",
  "properties": {
    "addr:full":"Dumayne Ho, 1 Fox La Palmers Green Greater London N13 4XD",
    "addr:housenumber":"1",
    "addr:postcode":"n13 4xd",
    "addr:street":"Fox La Palmers",
    "iso:country":"GB",
    "sg:address":"Dumayne Ho, 1 Fox La",
    "sg:city":"Palmers Green",
    "sg:classifiers":[
        {
            "category":"Real Estate",
            "subcategory":"Architect",
            "type":"Services"
        }
    ],
    "sg:phone":"+44 20 8882 5822",
    "sg:postcode":"N13 4XD",
    "sg:province":"Greater London",
    "wof:name":"Wilde & Neil",
    "wof:placetype":"venue"
},
  "geometry": {"coordinates":[-0.11035,51.615429],"type":"Point"}
}