{
  "type": "Feature",
  "properties": {
    "addr:full":"The Haskins Complex, Townsend Road Shepton Mallet Somerset BA4 5SB",
    "addr:postcode":"ba4 5sb",
    "addr:street":"Townsend Road",
    "iso:country":"GB",
    "sg:address":"The Haskins Complex, Townsend Road",
    "sg:city":"Shepton Mallet",
    "sg:classifiers":[
        {
            "category":"Autos & Motor Vehicles",
            "subcategory":"Auto Supplies",
            "type":"Retail Goods"
        }
    ],
    "sg:phone":"+44 1749 343343",
    "sg:postcode":"BA4 5SB",
    "sg:province":"Somerset",
    "sg:tags":[
        "tyre"
    ],
    "wof:name":"Speed-Fit Shepton Mallet",
    "wof:placetype":"venue"
},
  "geometry": {"coordinates":[-2.5467779636,51.1897315979],"type":"Point"}
}