{
  "type": "Feature",
  "properties": {
    "addr:full":"174 Brabazon Road Hounslow Greater London TW5 9LP",
    "addr:housenumber":"174",
    "addr:postcode":"tw5 9lp",
    "addr:street":"Brabazon Road",
    "iso:country":"GB",
    "sg:address":"174 Brabazon Road",
    "sg:city":"Hounslow",
    "sg:classifiers":[
        {
            "category":"Food & Beverages",
            "subcategory":"Fruits & Vegetables",
            "type":"Retail Goods"
        }
    ],
    "sg:phone":"+44 20 8897 0918",
    "sg:postcode":"TW5 9LP",
    "sg:province":"Greater London",
    "sg:tags":[
        "greengrocer"
    ],
    "wof:name":"Hairflex",
    "wof:placetype":"venue"
},
  "geometry": {"coordinates":[-0.396624,51.48476],"type":"Point"}
}