{
  "type": "Feature",
  "properties": {
    "iso:country":"GB",
    "sg:address":"2-4 Knights Rd",
    "sg:city":"Canning Town",
    "sg:classifiers":[
        {
            "category":"Building & Trades",
            "subcategory":"Construction",
            "type":"Services"
        }
    ],
    "sg:phone":"+44 1708 866066",
    "sg:postcode":"E16 2AT",
    "sg:province":"Greater London",
    "sg:tags":[
        "platform",
        "work",
        "scaffolding"
    ],
    "wof:name":"Century Scaffolding Services",
    "wof:placetype":"venue"
},
  "geometry": {"coordinates":[0.021925,51.501484],"type":"Point"}
}