{
  "type": "Feature",
  "properties": {
    "iso:country":"GB",
    "sg:address":"P.s.a. Sub Office, Rnaw Almond Bank",
    "sg:city":"Perth",
    "sg:classifiers":[
        {
            "category":"Building & Trades",
            "subcategory":"Construction",
            "type":"Services"
        }
    ],
    "sg:phone":"+44 1738 583588",
    "sg:postcode":"PH1 3JY",
    "sg:province":"Perth and Kinross",
    "sg:tags":[
        "heating",
        "contractor"
    ],
    "wof:name":"Heden Maintenance Ltd",
    "wof:placetype":"venue"
},
  "geometry": {"coordinates":[-3.5126390457,56.4157905579],"type":"Point"}
}