{
  "type": "Feature",
  "properties": {
    "iso:country":"GB",
    "sg:address":"22 Chiltern Avenue, Cosby",
    "sg:city":"Leicester",
    "sg:classifiers":[
        {
            "category":"Coffee & Tea",
            "type":"Food & Drink"
        }
    ],
    "sg:phone":"+44 116 286 2532",
    "sg:postcode":"LE9 1UF",
    "sg:province":"Leicestershire",
    "wof:name":"Cosby Coffee",
    "wof:placetype":"venue"
},
  "geometry": {"coordinates":[-1.188917,52.55109],"type":"Point"}
}