{
  "type": "Feature",
  "properties": {
    "addr:full":"15 Bude Close, Bramhall Stockport Cheshire SK7 2QP",
    "addr:housenumber":"15",
    "addr:postcode":"sk7 2qp",
    "addr:street":"Bude Close",
    "iso:country":"GB",
    "sg:address":"15 Bude Close, Bramhall",
    "sg:city":"Stockport",
    "sg:classifiers":[
        {
            "category":"Professional",
            "subcategory":"Employment Agencies",
            "type":"Services"
        }
    ],
    "sg:postcode":"SK7 2QP",
    "sg:province":"Cheshire",
    "sg:tags":[
        "consultant"
    ],
    "wof:name":"M & A Marketing",
    "wof:placetype":"venue"
},
  "geometry": {"coordinates":[-2.1544919014,53.364780426],"type":"Point"}
}