{
  "type": "Feature",
  "properties": {
    "iso:country":"GB",
    "sg:address":"110 Queens Rd",
    "sg:city":"Brighton",
    "sg:classifiers":[
        {
            "category":"Professional",
            "subcategory":"Computer Services",
            "type":"Services"
        }
    ],
    "sg:phone":"+44 1273 748083",
    "sg:postcode":"BN1 3XF",
    "sg:province":"East Sussex",
    "sg:tags":[
        "system",
        "software"
    ],
    "wof:name":"Network Professional",
    "wof:placetype":"venue"
},
  "geometry": {"coordinates":[-0.142023,50.826252],"type":"Point"}
}