{
  "type": "Feature",
  "properties": {
    "iso:country":"GB",
    "sg:address":"559 Bexhill Rd",
    "sg:city":"St Leonards On Sea",
    "sg:classifiers":[
        {
            "category":"Social Services",
            "subcategory":"Adult Care",
            "type":"Services"
        }
    ],
    "sg:phone":"+44 1424 460336",
    "sg:postcode":"TN38 8AX",
    "sg:province":"East Sussex",
    "sg:tags":[
        "domestic",
        "cleaning"
    ],
    "wof:name":"A S Cleaners",
    "wof:placetype":"venue"
},
  "geometry": {"coordinates":[0.510699,50.845997],"type":"Point"}
}