{
  "type": "Feature",
  "properties": {
    "iso:country":"GB",
    "sg:address":"Rushmere Park, Old Linslade Road, Heath & Reach",
    "sg:city":"Leighton Buzzard",
    "sg:classifiers":[
        {
            "category":"Sports & Exercise",
            "subcategory":"Sports Center",
            "type":"Entertainment"
        }
    ],
    "sg:phone":"+44 1234 266266",
    "sg:postcode":"LU7 0DU",
    "sg:province":"Bedfordshire",
    "sg:tags":[
        "game",
        "combat"
    ],
    "wof:name":"Great Adventure Game",
    "wof:placetype":"venue"
},
  "geometry": {"coordinates":[-0.65844,51.945641],"type":"Point"}
}