{
  "type": "Feature",
  "properties": {
    "iso:country":"GB",
    "sg:address":"40 Joppa Road",
    "sg:city":"Edinburgh",
    "sg:classifiers":[
        {
            "category":"Food & Beverages",
            "subcategory":"Supermarket",
            "type":"Retail Goods"
        },
        {
            "category":"Food & Beverages",
            "subcategory":"Groceries & Convenience Stores",
            "type":"Retail Goods"
        }
    ],
    "sg:phone":"+44 131 669 9069",
    "sg:postcode":"EH15 2ET",
    "sg:province":"City of Edinburgh",
    "wof:name":"Ben Store",
    "wof:placetype":"venue"
},
  "geometry": {"coordinates":[-3.098625,55.949257],"type":"Point"}
}