{
  "type": "Feature",
  "properties": {
    "iso:country":"GB",
    "sg:address":"8 Woodlands",
    "sg:city":"Chatham",
    "sg:classifiers":[
        {
            "category":"Utilities",
            "subcategory":"Fuel Oil & Lpg",
            "type":"Services"
        }
    ],
    "sg:phone":"+44 1634 862758",
    "sg:postcode":"ME5 9JX",
    "sg:province":"Kent",
    "sg:tags":[
        "coal",
        "smokeless"
    ],
    "wof:name":"H Barty & Son",
    "wof:placetype":"venue"
},
  "geometry": {"coordinates":[0.528607,51.335453],"type":"Point"}
}