{
  "type": "Feature",
  "properties": {
    "addr:full":"Sparta Works, 487 Blackfen Road Sidcup Kent DA15 9NP",
    "addr:housenumber":"487",
    "addr:postcode":"da15 9np",
    "addr:street":"Blackfen Road",
    "iso:country":"GB",
    "sg:address":"Sparta Works, 487 Blackfen Road",
    "sg:city":"Sidcup",
    "sg:classifiers":[
        {
            "category":"Professional",
            "subcategory":"Printing & Photocopies",
            "type":"Services"
        }
    ],
    "sg:postcode":"DA15 9NP",
    "sg:province":"Kent",
    "sg:tags":[
        "printer"
    ],
    "wof:name":"Sparta Press (Blackfen) Ltd.",
    "wof:placetype":"venue"
},
  "geometry": {"coordinates":[0.1180299968,51.4480705261],"type":"Point"}
}