{
  "type": "Feature",
  "properties": {
    "iso:country":"GB",
    "sg:address":"Doughty Farm, Back Lane, Southfield",
    "sg:city":"Burnley",
    "sg:classifiers":[
        {
            "category":"Farming",
            "subcategory":"Livestock Farm",
            "type":"Manufacturing & Wholesale Goods"
        }
    ],
    "sg:phone":"+44 1282 613530",
    "sg:postcode":"BB10 3RG",
    "sg:province":"Lancashire",
    "sg:tags":[
        "others"
    ],
    "wof:name":"A P Townsend",
    "wof:placetype":"venue"
},
  "geometry": {"coordinates":[-2.199694,53.818531],"type":"Point"}
}