{
  "type": "Feature",
  "properties": {
    "addr:full":"Sunrays, Stratton Rd Bude Cornwall EX23 8AQ",
    "addr:postcode":"ex23 8aq",
    "addr:street":"Sunrays Stratton Rd",
    "iso:country":"GB",
    "sg:address":"Sunrays, Stratton Rd",
    "sg:city":"Bude",
    "sg:classifiers":[
        {
            "category":"Taxi",
            "type":"Transportation"
        }
    ],
    "sg:phone":"+44 7866 886145",
    "sg:postcode":"EX23 8AQ",
    "sg:province":"Cornwall",
    "sg:tags":[
        "mini",
        "cab"
    ],
    "wof:name":"Flexitaxi",
    "wof:placetype":"venue"
},
  "geometry": {"coordinates":[-4.544478,50.828362],"type":"Point"}
}