{
  "type": "Feature",
  "properties": {
    "iso:country":"GB",
    "sg:address":"251 Two Mile Hill Road",
    "sg:city":"Bristol",
    "sg:classifiers":[
        {
            "category":"Fast Food",
            "type":"Food & Drink"
        }
    ],
    "sg:phone":"+44 117 967 3379",
    "sg:postcode":"BS15 1AY",
    "sg:province":"City of Bristol",
    "sg:tags":[
        "away",
        "take"
    ],
    "wof:name":"The Canton Dish",
    "wof:placetype":"venue"
},
  "geometry": {"coordinates":[-2.514919,51.463234],"type":"Point"}
}