{
  "type": "Feature",
  "properties": {
    "addr:full":"2 Moores Farm, Two Gate Lane, Overton Basingstoke Hampshire RG25 3NF",
    "addr:housenumber":"2",
    "addr:postcode":"rg25 3nf",
    "addr:street":"Moores Farm Two Gate Lane",
    "iso:country":"GB",
    "sg:address":"2 Moores Farm, Two Gate Lane, Overton",
    "sg:city":"Basingstoke",
    "sg:classifiers":[
        {
            "category":"Professional",
            "subcategory":"Business Services",
            "type":"Services"
        }
    ],
    "sg:postcode":"RG25 3NF",
    "sg:province":"Hampshire",
    "sg:tags":[
        "transfer",
        "agent"
    ],
    "wof:name":"Anderson Moore Consultants",
    "wof:placetype":"venue"
},
  "geometry": {"coordinates":[-1.2567759752,51.2429542542],"type":"Point"}
}