{
  "type": "Feature",
  "properties": {
    "addr:full":"Unit 6 Dollar Industrial Estate Falkirk Falkirk FK2 7YS",
    "addr:housenumber":"unit 6",
    "addr:postcode":"fk2 7ys",
    "addr:street":"Dollar Industrial Estate",
    "iso:country":"GB",
    "sg:address":"Unit 6 Dollar Industrial Estate",
    "sg:city":"Falkirk",
    "sg:classifiers":[
        {
            "category":"Manufacturing",
            "subcategory":"Metals",
            "type":"Manufacturing & Wholesale Goods"
        }
    ],
    "sg:phone":"+44 1324 631528",
    "sg:postcode":"FK2 7YS",
    "sg:province":"Falkirk",
    "sg:tags":[
        "steel",
        "fabricator",
        "erectors"
    ],
    "wof:name":"B C S Steel Fabricators (Falkirk) Ltd.",
    "wof:placetype":"venue"
},
  "geometry": {"coordinates":[-3.79847,56.00444],"type":"Point"}
}