{
  "type": "Feature",
  "properties": {
    "iso:country":"GB",
    "sg:address":"620 Stockport Road",
    "sg:city":"Manchester",
    "sg:classifiers":[
        {
            "category":"Shopping",
            "subcategory":"Computers & Home Electronics",
            "type":"Retail Goods"
        }
    ],
    "sg:postcode":"M13 0SH",
    "sg:province":"Greater Manchester",
    "sg:tags":[
        "electrical"
    ],
    "wof:name":"North West Electrical Ltd.",
    "wof:placetype":"venue"
},
  "geometry": {"coordinates":[-2.198681,53.455379],"type":"Point"}
}