{
  "type": "Feature",
  "properties": {
    "iso:country":"GB",
    "sg:address":"203 London Road",
    "sg:city":"Benfleet",
    "sg:classifiers":[
        {
            "category":"Bars & Pubs",
            "type":"Food & Drink"
        }
    ],
    "sg:phone":"+44 1268 755756",
    "sg:postcode":"SS7 5UN",
    "sg:province":"Essex",
    "sg:tags":[
        "pubs",
        "inn"
    ],
    "wof:name":"The Lighthouse",
    "wof:placetype":"venue"
},
  "geometry": {"coordinates":[0.556156,51.567101],"type":"Point"}
}