{
  "type": "Feature",
  "properties": {
    "addr:full":"60 High Street, Needham Market Ipswich Suffolk IP6 8AW",
    "addr:housenumber":"60",
    "addr:postcode":"ip6 8aw",
    "addr:street":"High Street",
    "iso:country":"GB",
    "sg:address":"60 High Street, Needham Market",
    "sg:city":"Ipswich",
    "sg:classifiers":[
        {
            "category":"Food & Beverages",
            "subcategory":"Bakery",
            "type":"Retail Goods"
        }
    ],
    "sg:phone":"+44 1449 720261",
    "sg:postcode":"IP6 8AW",
    "sg:province":"Suffolk",
    "sg:tags":[
        "shop",
        "baker"
    ],
    "wof:name":"R J & B M Brett",
    "wof:placetype":"venue"
},
  "geometry": {"coordinates":[1.051707983,52.1541137695],"type":"Point"}
}