{
  "type": "Feature",
  "properties": {
    "iso:country":"GB",
    "sg:address":"14a Goodwins Court",
    "sg:city":"London",
    "sg:classifiers":[
        {
            "category":"Professional",
            "subcategory":"Lawyer & Legal Services",
            "type":"Services"
        }
    ],
    "sg:phone":"+44 20 7227 7929",
    "sg:postcode":"WC2N 4LL",
    "sg:province":"Greater London",
    "sg:tags":[
        "solicitor"
    ],
    "wof:name":"Beer Solicitors",
    "wof:placetype":"venue"
},
  "geometry": {"coordinates":[-0.126682,51.510834],"type":"Point"}
}