{
  "type": "Feature",
  "properties": {
    "addr:full":"Wishing Well House, 38 Forest Road Melksham Wiltshire SN12 7AB",
    "addr:housenumber":"38",
    "addr:postcode":"sn12 7ab",
    "addr:street":"Forest Road",
    "iso:country":"GB",
    "sg:address":"Wishing Well House, 38 Forest Road",
    "sg:city":"Melksham",
    "sg:classifiers":[
        {
            "category":"Health Services",
            "subcategory":"Nursing And Care Facility",
            "type":"Services"
        }
    ],
    "sg:phone":"+44 1225 791625",
    "sg:postcode":"SN12 7AB",
    "sg:province":"Wiltshire",
    "sg:tags":[
        "agency"
    ],
    "wof:name":"Castell Care Services Ltd.",
    "wof:placetype":"venue"
},
  "geometry": {"coordinates":[-2.1308050156,51.3788871765],"type":"Point"}
}