{
  "type": "Feature",
  "properties": {
    "addr:full":"153-155 Kensington High St Kensington Greater London W8 6SU",
    "addr:housenumber":"153-155",
    "addr:postcode":"w8 6su",
    "addr:street":"Kensington High St",
    "iso:country":"GB",
    "sg:address":"153-155 Kensington High St",
    "sg:city":"Kensington",
    "sg:classifiers":[
        {
            "category":"Shopping",
            "subcategory":"Shoes",
            "type":"Retail Goods"
        }
    ],
    "sg:phone":"+44 20 7376 2300",
    "sg:postcode":"W8 6SU",
    "sg:province":"Greater London",
    "sg:tags":[
        "shop"
    ],
    "wof:name":"Nine West",
    "wof:placetype":"venue"
},
  "geometry": {"coordinates":[-0.1951369941,51.5004310608],"type":"Point"}
}