{
  "type": "Feature",
  "properties": {
    "addr:full":"Unit 13 Blencathra Business Cent, Re, Threlkeld Keswick Cumbria CA12 4TR",
    "addr:housenumber":"unit 13",
    "addr:postcode":"ca12 4tr",
    "addr:street":"Blencathra Business Cent Re",
    "iso:country":"GB",
    "sg:address":"Unit 13 Blencathra Business Cent, Re, Threlkeld",
    "sg:city":"Keswick",
    "sg:classifiers":[
        {
            "category":"Utilities",
            "subcategory":"Natural Gas",
            "type":"Services"
        }
    ],
    "sg:phone":"+44 17687 79945",
    "sg:postcode":"CA12 4TR",
    "sg:province":"Cumbria",
    "sg:tags":[
        "control",
        "energy",
        "management",
        "system"
    ],
    "wof:name":"Building Management Technology",
    "wof:placetype":"venue"
},
  "geometry": {"coordinates":[-3.0480539799,54.6129112244],"type":"Point"}
}