{
  "type": "Feature",
  "properties": {
    "iso:country":"GB",
    "sg:address":"14-16 Barrasgate Road",
    "sg:city":"Fraserburgh",
    "sg:classifiers":[
        {
            "category":"Wholesale",
            "subcategory":"Construction Materials",
            "type":"Manufacturing & Wholesale Goods"
        },
        {
            "category":"Building & Trades",
            "subcategory":"Construction",
            "type":"Services"
        }
    ],
    "sg:phone":"+44 1346 513297",
    "sg:postcode":"AB43 9DQ",
    "sg:province":"Aberdeenshire",
    "sg:tags":[
        "sawdust",
        "joinery",
        "sawmills",
        "shaving"
    ],
    "wof:name":"A Gordon & Co. Ltd.",
    "wof:placetype":"venue"
},
  "geometry": {"coordinates":[-2.007936,57.695206],"type":"Point"}
}