{
  "type": "Feature",
  "properties": {
    "iso:country":"GB",
    "sg:address":"9 Wallington Square",
    "sg:city":"Wallington",
    "sg:classifiers":[
        {
            "category":"Travel",
            "subcategory":"Travel Agent",
            "type":"Entertainment"
        }
    ],
    "sg:phone":"+44 20 8918 1900",
    "sg:postcode":"SM6 8RG",
    "sg:province":"Surrey",
    "wof:name":"Thomas Cook",
    "wof:placetype":"venue"
},
  "geometry": {"coordinates":[-0.148569,51.35799],"type":"Point"}
}