{
  "type": "Feature",
  "properties": {
    "iso:country":"GB",
    "sg:address":"Nam House, 22-26 Spencer Street",
    "sg:city":"Birmingham",
    "sg:classifiers":[
        {
            "category":"Manufacturing",
            "subcategory":"Jewelry",
            "type":"Manufacturing & Wholesale Goods"
        }
    ],
    "sg:phone":"+44 121 233 9999",
    "sg:postcode":"B18 6DS",
    "sg:province":"West Midlands",
    "sg:tags":[
        "repair",
        "jewellery"
    ],
    "wof:name":"Renatex Ltd.",
    "wof:placetype":"venue"
},
  "geometry": {"coordinates":[-1.9094309807,52.4878082275],"type":"Point"}
}