{
  "type": "Feature",
  "properties": {
    "iso:country":"GB",
    "sg:address":"Unit 14",
    "sg:city":"London",
    "sg:classifiers":[
        {
            "category":"Banks & Credit Unions",
            "subcategory":"Financial Services",
            "type":"Services"
        }
    ],
    "sg:phone":"+44 20 8947 9900",
    "sg:postcode":"SW20 0JH",
    "sg:province":"Greater London",
    "sg:tags":[
        "adviser"
    ],
    "wof:name":"Minerva Financial Management Ltd.",
    "wof:placetype":"venue"
},
  "geometry": {"coordinates":[-0.1243010014,51.4130630493],"type":"Point"}
}