{
  "type": "Feature",
  "properties": {
    "addr:full":"Church Street Clitheroe Lancashire BB7 2DG",
    "addr:postcode":"bb7 2dg",
    "addr:street":"Church Street",
    "iso:country":"GB",
    "sg:address":"Church Street",
    "sg:city":"Clitheroe",
    "sg:classifiers":[
        {
            "category":"Education",
            "subcategory":"Library",
            "type":"Public Place"
        }
    ],
    "sg:phone":"+44 1200 428788",
    "sg:postcode":"BB7 2DG",
    "sg:province":"Lancashire",
    "sg:tags":[
        "book"
    ],
    "wof:name":"Clitheroe Library",
    "wof:placetype":"venue"
},
  "geometry": {"coordinates":[-2.390543,53.873386],"type":"Point"}
}