{
  "type": "Feature",
  "properties": {
    "addr:full":"115 Bitterne Road West Southampton Hampshire SO18 1AR",
    "addr:housenumber":"115",
    "addr:postcode":"so18 1ar",
    "addr:street":"Bitterne Road West",
    "iso:country":"GB",
    "sg:address":"115 Bitterne Road West",
    "sg:city":"Southampton",
    "sg:classifiers":[
        {
            "category":"Health Services",
            "subcategory":"Dentist",
            "type":"Services"
        }
    ],
    "sg:phone":"+44 23 8022 8363",
    "sg:postcode":"SO18 1AR",
    "sg:province":"Hampshire",
    "wof:name":"Miss H N Owers",
    "wof:placetype":"venue"
},
  "geometry": {"coordinates":[-1.3791810274,50.9180488586],"type":"Point"}
}