{
  "type": "Feature",
  "properties": {
    "addr:full":"21 Far Croft, Breaston Derby Derbyshire DE72 3HL",
    "addr:housenumber":"21",
    "addr:postcode":"de72 3hl",
    "addr:street":"Far Croft",
    "iso:country":"GB",
    "sg:address":"21 Far Croft, Breaston",
    "sg:city":"Derby",
    "sg:classifiers":[
        {
            "category":"Building & Trades",
            "subcategory":"Plumbing",
            "type":"Services"
        }
    ],
    "sg:postcode":"DE72 3HL",
    "sg:province":"Derbyshire",
    "sg:tags":[
        "heating"
    ],
    "wof:name":"Keith Alliott & Associates",
    "wof:placetype":"venue"
},
  "geometry": {"coordinates":[-1.323004961,52.8977012634],"type":"Point"}
}