{
  "type": "Feature",
  "properties": {
    "iso:country":"GB",
    "sg:address":"688 Aldridge Road",
    "sg:city":"Birmingham",
    "sg:classifiers":[
        {
            "category":"Professional",
            "subcategory":"Printing & Photocopies",
            "type":"Services"
        }
    ],
    "sg:phone":"+44 121 360 5656",
    "sg:postcode":"B44 8NJ",
    "sg:province":"West Midlands",
    "sg:tags":[
        "printer"
    ],
    "wof:name":"B G Marketing",
    "wof:placetype":"venue"
},
  "geometry": {"coordinates":[-1.8963110447,52.5395698547],"type":"Point"}
}