{
  "type": "Feature",
  "properties": {
    "iso:country":"GB",
    "sg:address":"Gibbs Grn, Beaumont Crescent",
    "sg:city":"London",
    "sg:classifiers":[
        {
            "category":"Social Services",
            "subcategory":"Adult Care",
            "type":"Services"
        },
        {
            "category":"Government",
            "subcategory":"Office",
            "type":"Public Place"
        }
    ],
    "sg:phone":"+44 20 7385 4757",
    "sg:postcode":"W14 9ND",
    "sg:province":"Greater London",
    "sg:tags":[
        "housing",
        "local",
        "sheltered"
    ],
    "wof:name":"Gibbs Green Sheltered Housing",
    "wof:placetype":"venue"
},
  "geometry": {"coordinates":[-0.204124,51.489586],"type":"Point"}
}