{
  "type": "Feature",
  "properties": {
    "addr:full":"85 Marlpool La Kidderminster Staffordshire DY11 5HP",
    "addr:housenumber":"85",
    "addr:postcode":"dy11 5hp",
    "addr:street":"Marlpool La Kidderminster",
    "iso:country":"GB",
    "sg:address":"85 Marlpool La",
    "sg:city":"Kidderminster",
    "sg:classifiers":[
        {
            "category":"Retail",
            "subcategory":"Repair Shop",
            "type":"Services"
        }
    ],
    "sg:postcode":"DY11 5HP",
    "sg:province":"Staffordshire",
    "sg:tags":[
        "maintenance"
    ],
    "wof:name":"Morbey,Jonathon,",
    "wof:placetype":"venue"
},
  "geometry": {"coordinates":[-2.263093,52.397907],"type":"Point"}
}