{
  "type": "Feature",
  "properties": {
    "addr:full":"35 Edgar Street Hereford Herefordshire HR4 9JP",
    "addr:housenumber":"35",
    "addr:postcode":"hr4 9jp",
    "addr:street":"Edgar Street",
    "iso:country":"GB",
    "sg:address":"35 Edgar Street",
    "sg:city":"Hereford",
    "sg:classifiers":[
        {
            "category":"Health Services",
            "subcategory":"Doctor",
            "type":"Services"
        },
        {
            "category":"Health Services",
            "subcategory":"Clinic",
            "type":"Services"
        }
    ],
    "sg:phone":"+44 1432 272175",
    "sg:postcode":"HR4 9JP",
    "sg:province":"Herefordshire",
    "sg:tags":[
        "nh",
        "practitioners"
    ],
    "wof:name":"Moorfield House Surgery",
    "wof:placetype":"venue"
},
  "geometry": {"coordinates":[-2.7201681137,52.0581130981],"type":"Point"}
}