{
  "type": "Feature",
  "properties": {
    "addr:full":"Bull Lane, Long Melford Sudbury Essex CO10 9DZ",
    "addr:postcode":"co10 9dz",
    "addr:street":"Bull Lane",
    "iso:country":"GB",
    "sg:address":"Bull Lane, Long Melford",
    "sg:city":"Sudbury",
    "sg:classifiers":[
        {
            "category":"Shopping",
            "subcategory":"Musical Instruments",
            "type":"Retail Goods"
        }
    ],
    "sg:postcode":"CO10 9DZ",
    "sg:province":"Essex",
    "wof:name":"Barry Andrew Caradine",
    "wof:placetype":"venue"
},
  "geometry": {"coordinates":[0.7164800167,52.0752639771],"type":"Point"}
}