{
  "type": "Feature",
  "properties": {
    "addr:full":"Bay Quarry Works, Barton Mill Bury St Edmunds Cambridgeshire IP28 6BS",
    "addr:postcode":"ip28 6bs",
    "addr:street":"Bay;Barton Mill;St",
    "iso:country":"GB",
    "sg:address":"Bay Quarry Works, Barton Mill",
    "sg:city":"Bury St Edmunds",
    "sg:classifiers":[
        {
            "category":"Professional",
            "subcategory":"Engineering",
            "type":"Services"
        }
    ],
    "sg:phone":"+44 1638 712102",
    "sg:postcode":"IP28 6BS",
    "sg:province":"Cambridgeshire",
    "wof:name":"Reed & Upton Ltd.",
    "wof:placetype":"venue"
},
  "geometry": {"coordinates":[0.4959,52.31815],"type":"Point"}
}