{
  "type": "Feature",
  "properties": {
    "iso:country":"GB",
    "sg:address":"1 Swindon Street",
    "sg:city":"Cheltenham",
    "sg:classifiers":[
        {
            "category":"Autos & Motor Vehicles",
            "subcategory":"Auto Supplies",
            "type":"Retail Goods"
        }
    ],
    "sg:phone":"+44 1242 584886",
    "sg:postcode":"GL51 9ES",
    "sg:province":"Gloucestershire",
    "sg:tags":[
        "tyre"
    ],
    "wof:name":"Thrupp Tyre Co. Ltd.",
    "wof:placetype":"venue"
},
  "geometry": {"coordinates":[-2.0862009525,51.9085121155],"type":"Point"}
}