{
  "type": "Feature",
  "properties": {
    "addr:full":"23 High St Elgin Moray IV30 1EE",
    "addr:housenumber":"23",
    "addr:postcode":"iv30 1ee",
    "addr:street":"High St",
    "iso:country":"GB",
    "sg:address":"23 High St",
    "sg:city":"Elgin",
    "sg:classifiers":[
        {
            "category":"Health Services",
            "subcategory":"Dentist",
            "type":"Services"
        }
    ],
    "sg:phone":"+44 1343 547559",
    "sg:postcode":"IV30 1EE",
    "sg:province":"Moray",
    "wof:name":"R M Sandison Orthodontists",
    "wof:placetype":"venue"
},
  "geometry": {"coordinates":[-3.3112800121,57.6489486694],"type":"Point"}
}