{
  "type": "Feature",
  "properties": {
    "addr:full":"33 The Esplanade Weymouth Dorset DT4 8DJ",
    "addr:housenumber":"33",
    "addr:postcode":"dt4 8dj",
    "addr:street":"The Esplanade",
    "iso:country":"GB",
    "sg:address":"33 The Esplanade",
    "sg:city":"Weymouth",
    "sg:classifiers":[
        {
            "category":"Health Services",
            "subcategory":"Dentist",
            "type":"Services"
        }
    ],
    "sg:phone":"+44 1305 782077",
    "sg:postcode":"DT4 8DJ",
    "sg:province":"Dorset",
    "wof:name":"P Runeckles",
    "wof:placetype":"venue"
},
  "geometry": {"coordinates":[-2.4523849487,50.6089630127],"type":"Point"}
}