{
  "type": "Feature",
  "properties": {
    "addr:full":"Nth Walsham Rd, Crostwick Norwich Norfolk NR12 7BD",
    "addr:postcode":"nr12 7bd",
    "addr:street":"Nth Walsham Rd;Norwich",
    "iso:country":"GB",
    "sg:address":"Nth Walsham Rd, Crostwick",
    "sg:city":"Norwich",
    "sg:classifiers":[
        {
            "category":"Bars & Pubs",
            "type":"Food & Drink"
        }
    ],
    "sg:phone":"+44 1603 737560",
    "sg:postcode":"NR12 7BD",
    "sg:province":"Norfolk",
    "sg:tags":[
        "pubs",
        "inn"
    ],
    "wof:name":"The White Horse",
    "wof:placetype":"venue"
},
  "geometry": {"coordinates":[1.327829957,52.6747741699],"type":"Point"}
}