{
  "type": "Feature",
  "properties": {
    "iso:country":"GB",
    "sg:address":"14 High St South, Langley Moor",
    "sg:city":"Durham",
    "sg:classifiers":[
        {
            "category":"Health Services",
            "subcategory":"Clinic",
            "type":"Services"
        }
    ],
    "sg:phone":"+44 191 378 4848",
    "sg:postcode":"DH7 8JN",
    "sg:province":"Durham",
    "sg:tags":[
        "private"
    ],
    "wof:name":"Goldens Health",
    "wof:placetype":"venue"
},
  "geometry": {"coordinates":[-1.610124,54.758076],"type":"Point"}
}