{
  "type": "Feature",
  "properties": {
    "addr:full":"Poplar Ho, 12 Manchester Rd Wilmslow Cheshire SK9 1BG",
    "addr:housenumber":"12",
    "addr:postcode":"sk9 1bg",
    "addr:street":"Poplar;Manchester Rd",
    "iso:country":"GB",
    "sg:address":"Poplar Ho, 12 Manchester Rd",
    "sg:city":"Wilmslow",
    "sg:classifiers":[
        {
            "category":"Professional",
            "subcategory":"Lawyer & Legal Services",
            "type":"Services"
        }
    ],
    "sg:phone":"+44 1625 536330",
    "sg:postcode":"SK9 1BG",
    "sg:province":"Cheshire",
    "sg:tags":[
        "solicitor"
    ],
    "wof:name":"Richard Dawson & Co",
    "wof:placetype":"venue"
},
  "geometry": {"coordinates":[-2.227897,53.326797],"type":"Point"}
}