{
  "type": "Feature",
  "properties": {
    "addr:full":"Abbey House, 20 East Street Faversham Kent ME13 8AS",
    "addr:housenumber":"20",
    "addr:postcode":"me13 8as",
    "addr:street":"East Street",
    "iso:country":"GB",
    "sg:address":"Abbey House, 20 East Street",
    "sg:city":"Faversham",
    "sg:classifiers":[
        {
            "category":"Professional",
            "subcategory":"Computer Services",
            "type":"Services"
        }
    ],
    "sg:phone":"+44 1795 531532",
    "sg:postcode":"ME13 8AS",
    "sg:province":"Kent",
    "sg:tags":[
        "development",
        "system",
        "software"
    ],
    "wof:name":"FINANCIAL & MANAGEMENT INFORMATION SYSTEMS LTD",
    "wof:placetype":"venue"
},
  "geometry": {"coordinates":[0.894597,51.314934],"type":"Point"}
}