{
  "type": "Feature",
  "properties": {
    "addr:full":"Millow, Dunton Biggleswade Bedfordshire SG18 8RH",
    "addr:postcode":"sg18 8rh",
    "addr:street":"Millow",
    "iso:country":"GB",
    "sg:address":"Millow, Dunton",
    "sg:city":"Biggleswade",
    "sg:classifiers":[
        {
            "category":"Farming",
            "subcategory":"Dairy Farm",
            "type":"Manufacturing & Wholesale Goods"
        }
    ],
    "sg:phone":"+44 1767 312906",
    "sg:postcode":"SG18 8RH",
    "sg:province":"Bedfordshire",
    "wof:name":"F D Maynard & Son",
    "wof:placetype":"venue"
},
  "geometry": {"coordinates":[-0.1962690055,52.0827560425],"type":"Point"}
}