{
  "type": "Feature",
  "properties": {
    "addr:full":"5 Hanging Chadder Farm, Hanging Chadder, Royton Oldham Lancashire OL2 6XR",
    "addr:housenumber":"5",
    "addr:postcode":"ol2 6xr",
    "addr:street":"Hanging Chadder;Hanging Chadder",
    "iso:country":"GB",
    "sg:address":"5 Hanging Chadder Farm, Hanging Chadder, Royton",
    "sg:city":"Oldham",
    "sg:classifiers":[
        {
            "category":"Farming",
            "subcategory":"Dairy Farm",
            "type":"Manufacturing & Wholesale Goods"
        }
    ],
    "sg:phone":"+44 161 624 4937",
    "sg:postcode":"OL2 6XR",
    "sg:province":"Lancashire",
    "sg:tags":[
        "farmer"
    ],
    "wof:name":"Days Of Royton",
    "wof:placetype":"venue"
},
  "geometry": {"coordinates":[-2.131298,53.580582],"type":"Point"}
}