{
  "type": "Feature",
  "properties": {
    "addr:full":"67 Sunbrow Haslemere Hampshire GU27 2QL",
    "addr:housenumber":"67",
    "addr:postcode":"gu27 2ql",
    "addr:street":"Sunbrow Haslemere",
    "iso:country":"GB",
    "sg:address":"67 Sunbrow",
    "sg:city":"Haslemere",
    "sg:classifiers":[
        {
            "category":"Taxi",
            "type":"Transportation"
        }
    ],
    "sg:phone":"+44 1428 641400",
    "sg:postcode":"GU27 2QL",
    "sg:province":"Hampshire",
    "sg:tags":[
        "mini",
        "cab"
    ],
    "wof:name":"Airtime Taxis & Private Hire",
    "wof:placetype":"venue"
},
  "geometry": {"coordinates":[-0.7279919982,51.0855712891],"type":"Point"}
}