{
  "type": "Feature",
  "properties": {
    "iso:country":"GB",
    "sg:address":"20 Bramble Chase, Bishops Cleeve",
    "sg:city":"Cheltenham",
    "sg:classifiers":[
        {
            "category":"Professional",
            "subcategory":"Computer Services",
            "type":"Services"
        }
    ],
    "sg:postcode":"GL52 8WN",
    "sg:province":"Gloucestershire",
    "sg:tags":[
        "system",
        "software"
    ],
    "wof:name":"Megascene Ltd.",
    "wof:placetype":"venue"
},
  "geometry": {"coordinates":[-2.067051,51.949345],"type":"Point"}
}