{
  "type": "Feature",
  "properties": {
    "addr:full":"6 Overton Grove Kilmacolm Inverclyde PA13 4DR",
    "addr:housenumber":"6",
    "addr:postcode":"pa13 4dr",
    "addr:street":"Overton Grove",
    "iso:country":"GB",
    "sg:address":"6 Overton Grove",
    "sg:city":"Kilmacolm",
    "sg:classifiers":[
        {
            "category":"Professional",
            "subcategory":"Management & Consulting",
            "type":"Services"
        }
    ],
    "sg:phone":"+44 1505 874666",
    "sg:postcode":"PA13 4DR",
    "sg:province":"Inverclyde",
    "sg:tags":[
        "marketing",
        "consultant"
    ],
    "wof:name":"Jan Torrance Consultant in Marketing Services",
    "wof:placetype":"venue"
},
  "geometry": {"coordinates":[-4.618264,55.896965],"type":"Point"}
}