{
  "type": "Feature",
  "properties": {
    "iso:country":"GB",
    "sg:address":"15 Arnhall Dr",
    "sg:city":"Westhill",
    "sg:classifiers":[
        {
            "category":"Building & Trades",
            "subcategory":"Construction",
            "type":"Services"
        }
    ],
    "sg:phone":"+44 1224 742573",
    "sg:postcode":"AB32 6TZ",
    "sg:province":"Aberdeen City",
    "sg:tags":[
        "joiner",
        "carpenter"
    ],
    "wof:name":"C W Wood Design",
    "wof:placetype":"venue"
},
  "geometry": {"coordinates":[-2.3024129868,57.1511535645],"type":"Point"}
}