{
  "type": "Feature",
  "properties": {
    "addr:full":"57 Pitfield Street London Greater London N1 6BU",
    "addr:housenumber":"57",
    "addr:postcode":"n1 6bu",
    "addr:street":"Pitfield Street",
    "iso:country":"GB",
    "sg:address":"57 Pitfield Street",
    "sg:city":"London",
    "sg:classifiers":[
        {
            "category":"Food & Beverages",
            "subcategory":"Fruits & Vegetables",
            "type":"Retail Goods"
        },
        {
            "category":"Food & Beverages",
            "subcategory":"Groceries & Convenience Stores",
            "type":"Retail Goods"
        }
    ],
    "sg:phone":"+44 20 7253 9457",
    "sg:postcode":"N1 6BU",
    "sg:province":"Greater London",
    "sg:tags":[
        "grocer",
        "greengrocer"
    ],
    "wof:name":"Jay Ambe",
    "wof:placetype":"venue"
},
  "geometry": {"coordinates":[-0.0838000029,51.5289916992],"type":"Point"}
}