{
  "type": "Feature",
  "properties": {
    "addr:full":"Reeds Holme Works, Burnley Road Rossendale Lancashire BB4 8LN",
    "addr:postcode":"bb4 8ln",
    "addr:street":"Burnley Road",
    "iso:country":"GB",
    "sg:address":"Reeds Holme Works, Burnley Road",
    "sg:city":"Rossendale",
    "sg:classifiers":[
        {
            "category":"Manufacturing",
            "subcategory":"Textiles",
            "type":"Manufacturing & Wholesale Goods"
        }
    ],
    "sg:phone":"+44 1254 771221",
    "sg:postcode":"BB4 8LN",
    "sg:province":"Lancashire",
    "sg:tags":[
        "production"
    ],
    "wof:name":"J B Broadley Inc Gordon & Fairclough",
    "wof:placetype":"venue"
},
  "geometry": {"coordinates":[-2.274824,53.708961],"type":"Point"}
}