{
  "type": "Feature",
  "properties": {
    "iso:country":"GB",
    "sg:address":"56 Mullein Road",
    "sg:city":"Bicester",
    "sg:classifiers":[
        {
            "category":"Shopping",
            "subcategory":"Bicycles & Sporting Goods",
            "type":"Retail Goods"
        }
    ],
    "sg:postcode":"OX26 3WX",
    "sg:province":"Oxfordshire",
    "sg:tags":[
        "water",
        "cooler"
    ],
    "wof:name":"Drinkwell",
    "wof:placetype":"venue"
},
  "geometry": {"coordinates":[-1.158314,51.913494],"type":"Point"}
}