{
  "type": "Feature",
  "properties": {
    "addr:full":"1a Wedmore Street London Greater London N19 4RU",
    "addr:housenumber":"1a",
    "addr:postcode":"n19 4ru",
    "addr:street":"Wedmore Street",
    "iso:country":"GB",
    "sg:address":"1a Wedmore Street",
    "sg:city":"London",
    "sg:classifiers":[
        {
            "category":"Real Estate",
            "subcategory":"Architect",
            "type":"Services"
        }
    ],
    "sg:phone":"+44 20 7263 3902",
    "sg:postcode":"N19 4RU",
    "sg:province":"Greater London",
    "wof:name":"Chapman Designs",
    "wof:placetype":"venue"
},
  "geometry": {"coordinates":[-0.1300369948,51.5624694824],"type":"Point"}
}