{
  "type": "Feature",
  "properties": {
    "iso:country":"GB",
    "sg:address":"Hale Oak Road, Weald",
    "sg:city":"Sevenoaks",
    "sg:classifiers":[
        {
            "category":"Travel",
            "subcategory":"Hotels & Motels",
            "type":"Entertainment"
        },
        {
            "category":"Organizations",
            "subcategory":"Non-profit Organization",
            "type":"Services"
        }
    ],
    "sg:phone":"+44 1732 463212",
    "sg:postcode":"TN14 6NQ",
    "sg:province":"Kent",
    "sg:tags":[
        "voluntary",
        "house",
        "self",
        "catering",
        "charity",
        "organisation",
        "guest"
    ],
    "wof:name":"Hall Green Adventure Centre",
    "wof:placetype":"venue"
},
  "geometry": {"coordinates":[0.18773,51.237644],"type":"Point"}
}