{
  "type": "Feature",
  "properties": {
    "iso:country":"GB",
    "sg:address":"Curtis House 34 Third Avenue",
    "sg:city":"Hove",
    "sg:classifiers":[
        {
            "category":"Professional",
            "subcategory":"Employment Agencies",
            "type":"Services"
        }
    ],
    "sg:postcode":"BN3 2PD",
    "sg:province":"East Sussex",
    "sg:tags":[
        "consultant"
    ],
    "wof:name":"Accountancy Connections",
    "wof:placetype":"venue"
},
  "geometry": {"coordinates":[-0.170321,50.827499],"type":"Point"}
}