{
  "type": "Feature",
  "properties": {
    "addr:full":"Pheasant Meadow, Birdwood Gloucester Gloucestershire GL19 3EH",
    "addr:postcode":"gl19 3eh",
    "addr:street":"Pheasant Meadow",
    "iso:country":"GB",
    "sg:address":"Pheasant Meadow, Birdwood",
    "sg:city":"Gloucester",
    "sg:classifiers":[
        {
            "category":"Retail",
            "subcategory":"Veterinary Services",
            "type":"Services"
        }
    ],
    "sg:phone":"+44 1452 750170",
    "sg:postcode":"GL19 3EH",
    "sg:province":"Gloucestershire",
    "sg:tags":[
        "surgeon",
        "activity"
    ],
    "wof:name":"B W Paterson",
    "wof:placetype":"venue"
},
  "geometry": {"coordinates":[-2.376622,51.86692],"type":"Point"}
}