{
  "type": "Feature",
  "properties": {
    "iso:country":"GB",
    "sg:address":"Harrington Mill, Leopold Street, Long Eaton",
    "sg:city":"Nottingham",
    "sg:classifiers":[
        {
            "category":"Shopping",
            "subcategory":"Stationery & Office Supplies",
            "type":"Retail Goods"
        }
    ],
    "sg:postcode":"NG10 4QD",
    "sg:province":"Derbyshire",
    "sg:tags":[
        "printers'"
    ],
    "wof:name":"International Data Services",
    "wof:placetype":"venue"
},
  "geometry": {"coordinates":[-1.282627,52.901863],"type":"Point"}
}