{
  "type": "Feature",
  "properties": {
    "addr:full":"4 Boston Road, Gorse Hill Industrial Estate, Beaumont Leys Leicester Leicestershire LE4 1AQ",
    "addr:housenumber":"4",
    "addr:postcode":"leys;le4 1aq",
    "addr:street":"Boston Road;Estate",
    "iso:country":"GB",
    "sg:address":"4 Boston Road, Gorse Hill Industrial Estate, Beaumont Leys",
    "sg:city":"Leicester",
    "sg:classifiers":[
        {
            "category":"Professional",
            "subcategory":"Printing & Photocopies",
            "type":"Services"
        }
    ],
    "sg:phone":"+44 116 235 5221",
    "sg:postcode":"LE4 1AQ",
    "sg:province":"Leicestershire",
    "sg:tags":[
        "printer"
    ],
    "wof:name":"The Artisan Press Ltd.",
    "wof:placetype":"venue"
},
  "geometry": {"coordinates":[-1.1708420515,52.6634788513],"type":"Point"}
}