{
  "type": "Feature",
  "properties": {
    "addr:full":"41 Hahnemann Rd, Walton Liverpool Merseyside L4 3RZ",
    "addr:housenumber":"41",
    "addr:postcode":"l4 3rz",
    "addr:street":"Hahnemann Rd",
    "iso:country":"GB",
    "sg:address":"41 Hahnemann Rd, Walton",
    "sg:city":"Liverpool",
    "sg:classifiers":[
        {
            "category":"Building & Trades",
            "subcategory":"Construction",
            "type":"Services"
        }
    ],
    "sg:postcode":"L4 3RZ",
    "sg:province":"Merseyside",
    "sg:tags":[
        "joiner",
        "carpenter"
    ],
    "wof:name":"Enterprise Joinery Ltd",
    "wof:placetype":"venue"
},
  "geometry": {"coordinates":[-2.973322,53.444157],"type":"Point"}
}