{
  "type": "Feature",
  "properties": {
    "addr:full":"562 Whitmore Way Basildon Essex SS14 2ER",
    "addr:housenumber":"562",
    "addr:postcode":"ss14 2er",
    "addr:street":"Whitmore Way",
    "iso:country":"GB",
    "sg:address":"562 Whitmore Way",
    "sg:city":"Basildon",
    "sg:classifiers":[
        {
            "category":"Shopping",
            "subcategory":"Pharmacy",
            "type":"Retail Goods"
        }
    ],
    "sg:phone":"+44 1268 520753",
    "sg:postcode":"SS14 2ER",
    "sg:province":"Essex",
    "sg:tags":[
        "pharmacist",
        "chemist"
    ],
    "wof:name":"All Cures",
    "wof:placetype":"venue"
},
  "geometry": {"coordinates":[0.467941,51.575577],"type":"Point"}
}