{
  "type": "Feature",
  "properties": {
    "addr:full":"297 Knowsley Road Bootle Merseyside L20 5DF",
    "addr:housenumber":"297",
    "addr:postcode":"l20 5df",
    "addr:street":"Knowsley Road",
    "iso:country":"GB",
    "sg:address":"297 Knowsley Road",
    "sg:city":"Bootle",
    "sg:classifiers":[
        {
            "category":"Personal",
            "type":"Services"
        },
        {
            "category":"Professional",
            "subcategory":"Lawyer & Legal Services",
            "type":"Services"
        }
    ],
    "sg:phone":"+44 151 922 3760",
    "sg:postcode":"L20 5DF",
    "sg:province":"Merseyside",
    "sg:tags":[
        "advice",
        "counselling"
    ],
    "wof:name":"Sefton Choices",
    "wof:placetype":"venue"
},
  "geometry": {"coordinates":[-2.9932470322,53.4585494995],"type":"Point"}
}