{
  "type": "Feature",
  "properties": {
    "iso:country":"GB",
    "sg:address":"5 The Parade, Cherry Willingham",
    "sg:city":"Lincoln",
    "sg:classifiers":[
        {
            "category":"Shopping",
            "subcategory":"News",
            "type":"Retail Goods"
        }
    ],
    "sg:postcode":"LN3 4JL",
    "sg:province":"Lincolnshire",
    "sg:tags":[
        "newsagent"
    ],
    "wof:name":"Phillips Newsagents",
    "wof:placetype":"venue"
},
  "geometry": {"coordinates":[-0.455512,53.24192],"type":"Point"}
}