{
  "type": "Feature",
  "properties": {
    "iso:country":"GB",
    "sg:address":"New House Farm, Chester Road",
    "sg:city":"Newport",
    "sg:classifiers":[
        {
            "category":"Farming",
            "subcategory":"Livestock Farm",
            "type":"Manufacturing & Wholesale Goods"
        }
    ],
    "sg:postcode":"TF10 8BN",
    "sg:province":"Shropshire",
    "sg:tags":[
        "others"
    ],
    "wof:name":"P & G Furniss",
    "wof:placetype":"venue"
},
  "geometry": {"coordinates":[-2.393749,52.789913],"type":"Point"}
}