{
  "type": "Feature",
  "properties": {
    "iso:country":"GB",
    "sg:address":"Care Of Savacentre, 1 Merton High Street, Merton",
    "sg:city":"London",
    "sg:classifiers":[
        {
            "category":"Health Services",
            "subcategory":"Optometrist",
            "type":"Services"
        }
    ],
    "sg:phone":"+44 20 8543 8026",
    "sg:postcode":"SW19 2LT",
    "sg:province":"Greater London",
    "sg:tags":[
        "optician"
    ],
    "wof:name":"Optical Express",
    "wof:placetype":"venue"
},
  "geometry": {"coordinates":[-0.1914590001,51.4156303406],"type":"Point"}
}