{
  "type": "Feature",
  "properties": {
    "iso:country":"GB",
    "sg:address":"166 Wolsey Way, Syston",
    "sg:city":"Leicester",
    "sg:classifiers":[
        {
            "category":"Organizations",
            "subcategory":"Community Association",
            "type":"Services"
        }
    ],
    "sg:postcode":"LE7 1NZ",
    "sg:province":"Leicestershire",
    "sg:tags":[
        "relation",
        "public"
    ],
    "wof:name":"S J B Tobin & Co.",
    "wof:placetype":"venue"
},
  "geometry": {"coordinates":[-1.083811,52.694176],"type":"Point"}
}