{
  "type": "Feature",
  "properties": {
    "iso:country":"GB",
    "sg:address":"Lumley House, Cheadle Road, Blithe Bridge",
    "sg:city":"Stoke-on-trent",
    "sg:classifiers":[
        {
            "category":"Professional",
            "subcategory":"Engineering",
            "type":"Services"
        }
    ],
    "sg:phone":"+44 1782 395521",
    "sg:postcode":"ST11 9PW",
    "sg:province":"Staffordshire",
    "sg:tags":[
        "contractor",
        "electrical",
        "engineer"
    ],
    "wof:name":"Stuvalectrix Ltd.",
    "wof:placetype":"venue"
},
  "geometry": {"coordinates":[-2.021656,52.966675],"type":"Point"}
}