{
  "type": "Feature",
  "properties": {
    "iso:country":"GB",
    "sg:address":"P O Box 16",
    "sg:city":"Shipley",
    "sg:classifiers":[
        {
            "category":"Professional",
            "subcategory":"Lawyer & Legal Services",
            "type":"Services"
        }
    ],
    "sg:postcode":"BD18 4YW",
    "sg:province":"West Yorkshire",
    "sg:tags":[
        "conveyancing"
    ],
    "wof:name":"Homemoves (Uk) Ltd",
    "wof:placetype":"venue"
},
  "geometry": {"coordinates":[-1.7981899977,53.8339004517],"type":"Point"}
}