{
  "type": "Feature",
  "properties": {
    "addr:full":"Phoenix Works, Dudley Road West Oldbury West Midlands B69 2PJ",
    "addr:postcode":"b69 2pj",
    "addr:street":"Dudley Road West Oldbury",
    "iso:country":"GB",
    "sg:address":"Phoenix Works, Dudley Road West",
    "sg:city":"Oldbury",
    "sg:classifiers":[
        {
            "category":"Freight",
            "type":"Transportation"
        }
    ],
    "sg:phone":"+44 121 557 0011",
    "sg:postcode":"B69 2PJ",
    "sg:province":"West Midlands",
    "sg:tags":[
        "haulage",
        "road"
    ],
    "wof:name":"Freelance Transport & Hire Ltd",
    "wof:placetype":"venue"
},
  "geometry": {"coordinates":[-2.053039,52.514786],"type":"Point"}
}