{
  "type": "Feature",
  "properties": {
    "addr:full":"2 Tanner Street Thetford Norfolk IP24 2BQ",
    "addr:housenumber":"2",
    "addr:postcode":"ip24 2bq",
    "addr:street":"Tanner Street",
    "iso:country":"GB",
    "sg:address":"2 Tanner Street",
    "sg:city":"Thetford",
    "sg:classifiers":[
        {
            "category":"Shopping",
            "subcategory":"Musical Instruments",
            "type":"Retail Goods"
        }
    ],
    "sg:phone":"+44 1842 766325",
    "sg:postcode":"IP24 2BQ",
    "sg:province":"Norfolk",
    "sg:tags":[
        "retailer",
        "sheet",
        "music"
    ],
    "wof:name":"Thetford Music",
    "wof:placetype":"venue"
},
  "geometry": {"coordinates":[0.748239994,52.4138946533],"type":"Point"}
}