{
  "type": "Feature",
  "properties": {
    "iso:country":"GB",
    "sg:address":"118 The Brent",
    "sg:city":"Dartford",
    "sg:classifiers":[
        {
            "category":"Retail",
            "subcategory":"Funeral Services",
            "type":"Services"
        }
    ],
    "sg:phone":"+44 1322 284420",
    "sg:postcode":"DA2 6DE",
    "sg:province":"Kent",
    "wof:name":"Bournes Funeral Services",
    "wof:placetype":"venue"
},
  "geometry": {"coordinates":[0.2386559993,51.4426460266],"type":"Point"}
}