{
  "type": "Feature",
  "properties": {
    "addr:full":"57 Mount Pleasant Drive, Queens Park Bournemouth Dorset BH8 9JN",
    "addr:housenumber":"57",
    "addr:postcode":"bh8 9jn",
    "addr:street":"Mount Pleasant Drive Queens Park",
    "iso:country":"GB",
    "sg:address":"57 Mount Pleasant Drive, Queens Park",
    "sg:city":"Bournemouth",
    "sg:classifiers":[
        {
            "category":"Manufacturing",
            "subcategory":"Tools & Machinery",
            "type":"Manufacturing & Wholesale Goods"
        }
    ],
    "sg:phone":"+44 1202 397770",
    "sg:postcode":"BH8 9JN",
    "sg:province":"Dorset",
    "sg:tags":[
        "society",
        "friendly"
    ],
    "wof:name":"R T Phipp",
    "wof:placetype":"venue"
},
  "geometry": {"coordinates":[-1.8347170353,50.7462043762],"type":"Point"}
}