{
  "type": "Feature",
  "properties": {
    "addr:full":"Unit 4 Hammer La Hemel Hempstead Hertfordshire HP2 4EU",
    "addr:housenumber":"unit 4",
    "addr:postcode":"hp2 4eu",
    "addr:street":"La Hemel Hempstead",
    "iso:country":"GB",
    "sg:address":"Unit 4 Hammer La",
    "sg:city":"Hemel Hempstead",
    "sg:classifiers":[
        {
            "category":"Home & Garden",
            "subcategory":"Home Furnishings",
            "type":"Retail Goods"
        }
    ],
    "sg:phone":"+44 1442 235911",
    "sg:postcode":"HP2 4EU",
    "sg:province":"Hertfordshire",
    "sg:tags":[
        "furnishers",
        "planner",
        "kitchen"
    ],
    "wof:name":"Meridian Carpentry & Joinery",
    "wof:placetype":"venue"
},
  "geometry": {"coordinates":[-0.452333,51.756207],"type":"Point"}
}