{
  "type": "Feature",
  "properties": {
    "iso:country":"GB",
    "sg:address":"87 School Lane",
    "sg:city":"Herne Bay",
    "sg:classifiers":[
        {
            "category":"Building & Trades",
            "subcategory":"Construction",
            "type":"Services"
        }
    ],
    "sg:phone":"+44 1227 369482",
    "sg:postcode":"CT6 7AR",
    "sg:province":"Kent",
    "sg:tags":[
        "builder"
    ],
    "wof:name":"K & S BUILDERS",
    "wof:placetype":"venue"
},
  "geometry": {"coordinates":[1.138014,51.352779],"type":"Point"}
}