{
  "type": "Feature",
  "properties": {
    "iso:country":"GB",
    "sg:address":"Broadway",
    "sg:city":"Sidmouth",
    "sg:classifiers":[
        {
            "category":"Education",
            "subcategory":"School",
            "type":"Public Place"
        }
    ],
    "sg:phone":"+44 1395 513984",
    "sg:postcode":"EX10 8RG",
    "sg:province":"Devon",
    "sg:tags":[
        "independent",
        "preparatory",
        "local",
        "authority"
    ],
    "wof:name":"St. Johns Preparatory School",
    "wof:placetype":"venue"
},
  "geometry": {"coordinates":[-3.246444,50.686279],"type":"Point"}
}