{
  "type": "Feature",
  "properties": {
    "addr:full":"4 Union Street Filey North Yorkshire YO14 9DZ",
    "addr:housenumber":"4",
    "addr:postcode":"yo14 9dz",
    "addr:street":"Union Street",
    "iso:country":"GB",
    "sg:address":"4 Union Street",
    "sg:city":"Filey",
    "sg:classifiers":[
        {
            "category":"Shopping",
            "subcategory":"Pets & Pet Supplies",
            "type":"Retail Goods"
        }
    ],
    "sg:phone":"+44 1723 512752",
    "sg:postcode":"YO14 9DZ",
    "sg:province":"North Yorkshire",
    "sg:tags":[
        "shop"
    ],
    "wof:name":"Filey Pets & Gardens & Grooming",
    "wof:placetype":"venue"
},
  "geometry": {"coordinates":[-0.288194,54.21043],"type":"Point"}
}