{
  "type": "Feature",
  "properties": {
    "addr:full":"61a Surrenden Road Brighton East Sussex BN1 6PQ",
    "addr:housenumber":"61a",
    "addr:postcode":"bn1 6pq",
    "addr:street":"Surrenden Road",
    "iso:country":"GB",
    "sg:address":"61a Surrenden Road",
    "sg:city":"Brighton",
    "sg:classifiers":[
        {
            "category":"Organizations",
            "subcategory":"Membership Organization",
            "type":"Services"
        }
    ],
    "sg:postcode":"BN1 6PQ",
    "sg:province":"East Sussex",
    "sg:tags":[
        "club"
    ],
    "wof:name":"39 Langdale Road Hove Management Ltd.",
    "wof:placetype":"venue"
},
  "geometry": {"coordinates":[-0.1467989981,50.8477897644],"type":"Point"}
}