{
  "type": "Feature",
  "properties": {
    "addr:full":"Unit 5 Chapel St, Long Eaton Nottingham Derbyshire NG10 1EQ",
    "addr:housenumber":"unit 5",
    "addr:postcode":"ng10 1eq",
    "addr:street":"Chapel St",
    "iso:country":"GB",
    "sg:address":"Unit 5 Chapel St, Long Eaton",
    "sg:city":"Nottingham",
    "sg:classifiers":[
        {
            "category":"Professional",
            "subcategory":"Engineering",
            "type":"Services"
        }
    ],
    "sg:postcode":"NG10 1EQ",
    "sg:province":"Derbyshire",
    "wof:name":"Lindley,Gordon,",
    "wof:placetype":"venue"
},
  "geometry": {"coordinates":[-1.268584013,52.8951148987],"type":"Point"}
}