{
  "type": "Feature",
  "properties": {
    "addr:full":"Skeltons La London Greater London E10 5BT",
    "addr:postcode":"e10 5bt",
    "addr:street":"La",
    "iso:country":"GB",
    "sg:address":"Skeltons La",
    "sg:city":"London",
    "sg:classifiers":[
        {
            "category":"Manufacturing",
            "subcategory":"Metals",
            "type":"Manufacturing & Wholesale Goods"
        }
    ],
    "sg:postcode":"E10 5BT",
    "sg:province":"Greater London",
    "sg:tags":[
        "steel",
        "fabricator",
        "erectors"
    ],
    "wof:name":"Metal Work Direct Ltd.",
    "wof:placetype":"venue"
},
  "geometry": {"coordinates":[-0.012934,51.569912],"type":"Point"}
}