{
  "type": "Feature",
  "properties": {
    "addr:full":"347 Edinburgh Avenue Slough Berkshire SL1 4TU",
    "addr:housenumber":"347",
    "addr:postcode":"sl1 4tu",
    "addr:street":"Edinburgh Avenue",
    "iso:country":"GB",
    "sg:address":"347 Edinburgh Avenue",
    "sg:city":"Slough",
    "sg:classifiers":[
        {
            "category":"Professional",
            "subcategory":"Art Services",
            "type":"Services"
        }
    ],
    "sg:phone":"+44 1753 828828",
    "sg:postcode":"SL1 4TU",
    "sg:province":"Berkshire",
    "sg:tags":[
        "consultant",
        "design"
    ],
    "wof:name":"Martin Dawe Design plc",
    "wof:placetype":"venue"
},
  "geometry": {"coordinates":[-0.6234419942,51.5236549377],"type":"Point"}
}