{
  "type": "Feature",
  "properties": {
    "iso:country":"GB",
    "sg:address":"Unit 7b Britannia Estate, Leagrave Road",
    "sg:city":"Luton",
    "sg:classifiers":[
        {
            "category":"Manufacturing",
            "subcategory":"Apparel",
            "type":"Manufacturing & Wholesale Goods"
        }
    ],
    "sg:postcode":"LU3 1RJ",
    "sg:province":"Bedfordshire",
    "sg:tags":[
        "shirt",
        "maker"
    ],
    "wof:name":"Virtual Style Ltd",
    "wof:placetype":"venue"
},
  "geometry": {"coordinates":[-0.436417,51.904079],"type":"Point"}
}