{
  "type": "Feature",
  "properties": {
    "iso:country":"GB",
    "sg:address":"Unit 1, Bridgegate Business Pk, Gatehouse Way",
    "sg:city":"Aylesbury",
    "sg:classifiers":[
        {
            "category":"Communications",
            "subcategory":"Television Station",
            "type":"Services"
        },
        {
            "category":"Military Area",
            "subcategory":"Air Force Base",
            "type":"Public Place"
        }
    ],
    "sg:phone":"+44 1296 436161",
    "sg:postcode":"HP19 8XN",
    "sg:province":"Buckinghamshire",
    "sg:tags":[
        "manufacture",
        "equipment",
        "video",
        "component",
        "electronic"
    ],
    "sg:website":"http://www.micha.co.uk",
    "wof:name":"Micha Design Co Ltd (The)",
    "wof:placetype":"venue"
},
  "geometry": {"coordinates":[-0.83133,51.819901],"type":"Point"}
}