{
  "type": "Feature",
  "properties": {
    "iso:country":"GB",
    "sg:address":"3 Blenheim Court, Lustleigh Close",
    "sg:city":"Exeter",
    "sg:classifiers":[
        {
            "category":"Professional",
            "subcategory":"Computer Services",
            "type":"Services"
        }
    ],
    "sg:phone":"+44 1392 203522",
    "sg:postcode":"EX2 8PW",
    "sg:province":"Devon",
    "sg:tags":[
        "system",
        "software"
    ],
    "wof:name":"Ambridge Medical Systems Ltd.",
    "wof:placetype":"venue"
},
  "geometry": {"coordinates":[-3.536255,50.704269],"type":"Point"}
}