{
  "type": "Feature",
  "properties": {
    "addr:full":"34 St Georges Way Salford Greater Manchester M6 6SU",
    "addr:housenumber":"34",
    "addr:postcode":"m6 6su",
    "addr:street":"St Georges Way",
    "iso:country":"GB",
    "sg:address":"34 St Georges Way",
    "sg:city":"Salford",
    "sg:classifiers":[
        {
            "category":"Real Estate",
            "subcategory":"Real Estate Operator",
            "type":"Services"
        },
        {
            "category":"Social Services",
            "subcategory":"Retirement Home",
            "type":"Services"
        }
    ],
    "sg:phone":"+44 161 737 5511",
    "sg:postcode":"M6 6SU",
    "sg:province":"Greater Manchester",
    "sg:tags":[
        "letting",
        "residential",
        "agent",
        "care"
    ],
    "wof:name":"Kings Property Letting",
    "wof:placetype":"venue"
},
  "geometry": {"coordinates":[-2.281126,53.495232],"type":"Point"}
}