{
  "type": "Feature",
  "properties": {
    "addr:full":"4 Sharpitts Portland Dorset DT5 2HL",
    "addr:housenumber":"4",
    "addr:postcode":"dt5 2hl",
    "addr:street":"Sharpitts Portland",
    "iso:country":"GB",
    "sg:address":"4 Sharpitts",
    "sg:city":"Portland",
    "sg:classifiers":[
        {
            "category":"Building & Trades",
            "subcategory":"Construction",
            "type":"Services"
        }
    ],
    "sg:phone":"+44 1305 820719",
    "sg:postcode":"DT5 2HL",
    "sg:province":"Dorset",
    "sg:tags":[
        "monumental",
        "mason"
    ],
    "wof:name":"John Broddle",
    "wof:placetype":"venue"
},
  "geometry": {"coordinates":[-2.448194,50.542755],"type":"Point"}
}