{
  "type": "Feature",
  "properties": {
    "addr:full":"Meadow View, Pockford Road, Chiddingfold Godalming Surrey GU8 4TP",
    "addr:postcode":"gu8 4tp",
    "addr:street":"Pockford Road",
    "iso:country":"GB",
    "sg:address":"Meadow View, Pockford Road, Chiddingfold",
    "sg:city":"Godalming",
    "sg:classifiers":[
        {
            "category":"Building & Trades",
            "subcategory":"Construction",
            "type":"Services"
        }
    ],
    "sg:phone":"+44 1428 683964",
    "sg:postcode":"GU8 4TP",
    "sg:province":"Surrey",
    "sg:tags":[
        "builder"
    ],
    "wof:name":"Carter & Street",
    "wof:placetype":"venue"
},
  "geometry": {"coordinates":[-0.6277520061,51.1137619019],"type":"Point"}
}