{
  "type": "Feature",
  "properties": {
    "iso:country":"GB",
    "sg:address":"Eccleshall",
    "sg:city":"Stafford",
    "sg:classifiers":[
        {
            "category":"Place Of Worship",
            "type":"Public Place"
        }
    ],
    "sg:phone":"+44 1785 850351",
    "sg:postcode":"ST21 6BY",
    "sg:province":"Staffordshire",
    "wof:name":"Holy Trinity C of E",
    "wof:placetype":"venue"
},
  "geometry": {"coordinates":[-2.25772,52.859138],"type":"Point"}
}