{
  "type": "Feature",
  "properties": {
    "addr:full":"Second Floor London Greater London WC2E 7BN",
    "addr:housenumber":"second",
    "addr:postcode":"wc2e 7bn",
    "iso:country":"GB",
    "sg:address":"Second Floor",
    "sg:city":"London",
    "sg:classifiers":[
        {
            "category":"Communications",
            "type":"Services"
        }
    ],
    "sg:postcode":"WC2E 7BN",
    "sg:province":"Greater London",
    "sg:tags":[
        "broadcasting"
    ],
    "wof:name":"Compulsive Viewing",
    "wof:placetype":"venue"
},
  "geometry": {"coordinates":[-0.1209900007,51.5123100281],"type":"Point"}
}