{
  "type": "Feature",
  "properties": {
    "iso:country":"GB",
    "sg:address":"10 Wynnstay Road",
    "sg:city":"Colwyn Bay",
    "sg:classifiers":[
        {
            "category":"Professional",
            "subcategory":"Detective & Security Services",
            "type":"Services"
        }
    ],
    "sg:phone":"+44 1492 532748",
    "sg:postcode":"LL29 8NB",
    "sg:province":"Conwy",
    "sg:tags":[
        "agency"
    ],
    "wof:name":"North West Investigation Bureau",
    "wof:placetype":"venue"
},
  "geometry": {"coordinates":[-3.729859,53.296474],"type":"Point"}
}