{
  "type": "Feature",
  "properties": {
    "addr:full":"Unit 17 Marland Mill, Nixon Street Rochdale Lancashire OL11 3JD",
    "addr:housenumber":"unit 17",
    "addr:postcode":"ol11 3jd",
    "addr:street":"Nixon Street",
    "iso:country":"GB",
    "sg:address":"Unit 17 Marland Mill, Nixon Street",
    "sg:city":"Rochdale",
    "sg:classifiers":[
        {
            "category":"Utilities",
            "subcategory":"Natural Gas",
            "type":"Services"
        }
    ],
    "sg:phone":"+44 1706 719567",
    "sg:postcode":"OL11 3JD",
    "sg:province":"Lancashire",
    "sg:tags":[
        "supplier"
    ],
    "wof:name":"Cellar Gas",
    "wof:placetype":"venue"
},
  "geometry": {"coordinates":[-2.18524,53.596401],"type":"Point"}
}