{
  "type": "Feature",
  "properties": {
    "addr:full":"73 Bridge Street Newport Newport NP20 4AQ",
    "addr:housenumber":"73",
    "addr:postcode":"np20 4aq",
    "addr:street":"Bridge Street",
    "iso:country":"GB",
    "sg:address":"73 Bridge Street",
    "sg:city":"Newport",
    "sg:classifiers":[
        {
            "category":"Banks & Credit Unions",
            "subcategory":"Bank",
            "type":"Services"
        },
        {
            "category":"Banks & Credit Unions",
            "subcategory":"Financial Services",
            "type":"Services"
        }
    ],
    "sg:phone":"+44 1633 672000",
    "sg:postcode":"NP20 4AQ",
    "sg:province":"Newport",
    "sg:tags":[
        "adviser",
        "broker",
        "mortgage"
    ],
    "wof:name":"David Stock & Co. Ltd.",
    "wof:placetype":"venue"
},
  "geometry": {"coordinates":[-2.9984269142,51.5877799988],"type":"Point"}
}