{
  "type": "Feature",
  "properties": {
    "iso:country":"GB",
    "sg:address":"68 Wimmerfield Av",
    "sg:city":"Swansea",
    "sg:classifiers":[
        {
            "category":"Place Of Worship",
            "type":"Public Place"
        }
    ],
    "sg:phone":"+44 1792 203833",
    "sg:postcode":"SA2 7DA",
    "sg:province":"Swansea",
    "wof:name":"Upper Killay Congregational Church",
    "wof:placetype":"venue"
},
  "geometry": {"coordinates":[-4.020446,51.619045],"type":"Point"}
}