{
  "type": "Feature",
  "properties": {
    "iso:country":"GB",
    "sg:address":"393 Halesowen Road",
    "sg:city":"Cradley Heath",
    "sg:classifiers":[
        {
            "category":"Health Services",
            "subcategory":"Dentist",
            "type":"Services"
        }
    ],
    "sg:phone":"+44 1384 637835",
    "sg:postcode":"B64 7HH",
    "sg:province":"West Midlands",
    "wof:name":"P J Thomas",
    "wof:placetype":"venue"
},
  "geometry": {"coordinates":[-2.061169,52.470261],"type":"Point"}
}