{
  "type": "Feature",
  "properties": {
    "iso:country":"GB",
    "sg:address":"Emergency No, Frampton House, Winterborne Stickland",
    "sg:city":"Blandford Forum",
    "sg:classifiers":[
        {
            "category":"Health Services",
            "subcategory":"Doctor",
            "type":"Services"
        }
    ],
    "sg:phone":"+44 1258 880279",
    "sg:postcode":"DT11 0NN",
    "sg:province":"Dorset",
    "sg:tags":[
        "practitioners"
    ],
    "wof:name":"Lang, J R",
    "wof:placetype":"venue"
},
  "geometry": {"coordinates":[-2.158819,50.862644],"type":"Point"}
}