{
  "type": "Feature",
  "properties": {
    "iso:country":"GB",
    "sg:address":"212 Radford Road",
    "sg:city":"Coventry",
    "sg:classifiers":[
        {
            "category":"Fast Food",
            "type":"Food & Drink"
        },
        {
            "category":"Food & Beverages",
            "subcategory":"Meat & Fish",
            "type":"Retail Goods"
        }
    ],
    "sg:phone":"+44 24 7659 1414",
    "sg:postcode":"CV6 3BQ",
    "sg:province":"Warwickshire",
    "sg:tags":[
        "shop",
        "chip"
    ],
    "wof:name":"Raja Abbas Khan",
    "wof:placetype":"venue"
},
  "geometry": {"coordinates":[-1.518806,52.420441],"type":"Point"}
}