{
  "type": "Feature",
  "properties": {
    "addr:full":"Porchestall Drove Glastonbury Somerset BA6 9NW",
    "addr:postcode":"ba6 9nw",
    "addr:street":"Porchestall Drove",
    "iso:country":"GB",
    "sg:address":"Porchestall Drove",
    "sg:city":"Glastonbury",
    "sg:classifiers":[
        {
            "category":"Manufacturing",
            "subcategory":"Lumber",
            "type":"Manufacturing & Wholesale Goods"
        }
    ],
    "sg:postcode":"BA6 9NW",
    "sg:province":"Somerset",
    "sg:tags":[
        "importer",
        "merchants",
        "agent",
        "timber"
    ],
    "wof:name":"Bradfords Timber Supplies Ltd.",
    "wof:placetype":"venue"
},
  "geometry": {"coordinates":[-2.7295570374,51.1466598511],"type":"Point"}
}