{
  "type": "Feature",
  "properties": {
    "addr:full":"Elizabethan House Lincoln Lincolnshire LN4 4RF",
    "addr:postcode":"ln4 4rf",
    "iso:country":"GB",
    "sg:address":"Elizabethan House",
    "sg:city":"Lincoln",
    "sg:classifiers":[
        {
            "category":"Autos & Motor Vehicles",
            "subcategory":"Automobile Sales",
            "type":"Retail Goods"
        }
    ],
    "sg:postcode":"LN4 4RF",
    "sg:province":"Lincolnshire",
    "sg:tags":[
        "car"
    ],
    "wof:name":"Coningsby Cars",
    "wof:placetype":"venue"
},
  "geometry": {"coordinates":[-0.214713,53.089836],"type":"Point"}
}