{
  "type": "Feature",
  "properties": {
    "addr:full":"Eldon Road Rotherham South Yorkshire S65 1RD",
    "addr:postcode":"s65 1rd",
    "addr:street":"Eldon Road",
    "iso:country":"GB",
    "sg:address":"Eldon Road",
    "sg:city":"Rotherham",
    "sg:classifiers":[
        {
            "category":"Professional",
            "subcategory":"Detective & Security Services",
            "type":"Services"
        }
    ],
    "sg:phone":"+44 1709 373551",
    "sg:postcode":"S65 1RD",
    "sg:province":"South Yorkshire",
    "wof:name":"Securicor",
    "wof:placetype":"venue"
},
  "geometry": {"coordinates":[-1.3441890478,53.4393005371],"type":"Point"}
}