{
  "type": "Feature",
  "properties": {
    "addr:full":"2 Duchess St Whitley Bay Northumberland NE26 3PW",
    "addr:housenumber":"2",
    "addr:postcode":"ne26 3pw",
    "addr:street":"Duchess St",
    "iso:country":"GB",
    "sg:address":"2 Duchess St",
    "sg:city":"Whitley Bay",
    "sg:classifiers":[
        {
            "category":"Professional",
            "subcategory":"Detective & Security Services",
            "type":"Services"
        }
    ],
    "sg:phone":"+44 191 251 9999",
    "sg:postcode":"NE26 3PW",
    "sg:province":"Northumberland",
    "wof:name":"Building Security Services",
    "wof:placetype":"venue"
},
  "geometry": {"coordinates":[-1.4516680241,55.0442504883],"type":"Point"}
}