{
  "type": "Feature",
  "properties": {
    "iso:country":"GB",
    "sg:address":"Suite 7, Hitching Court, Blacklands Way",
    "sg:city":"Abingdon",
    "sg:classifiers":[
        {
            "category":"Professional",
            "subcategory":"Engineering",
            "type":"Services"
        }
    ],
    "sg:phone":"+44 1235 538616",
    "sg:postcode":"OX14 1RG",
    "sg:province":"Oxfordshire",
    "sg:tags":[
        "consulting",
        "engineer"
    ],
    "wof:name":"O'Brien & Gere International",
    "wof:placetype":"venue"
},
  "geometry": {"coordinates":[-1.303447,51.672333],"type":"Point"}
}