{
  "type": "Feature",
  "properties": {
    "iso:country":"GB",
    "sg:address":"62 Edenhall Rd, Quinton",
    "sg:city":"Birmingham",
    "sg:classifiers":[
        {
            "category":"Building & Trades",
            "subcategory":"Construction",
            "type":"Services"
        }
    ],
    "sg:phone":"+44 121 423 2681",
    "sg:postcode":"B32 1DD",
    "sg:province":"West Midlands",
    "sg:tags":[
        "ceiling",
        "contractor"
    ],
    "wof:name":"P.J Poston",
    "wof:placetype":"venue"
},
  "geometry": {"coordinates":[-2.0011301041,52.4601974487],"type":"Point"}
}