{
  "type": "Feature",
  "properties": {
    "iso:country":"GB",
    "sg:address":"Fairholme, 1a Dunbar Avenue",
    "sg:city":"London",
    "sg:classifiers":[
        {
            "category":"Farming",
            "subcategory":"Nursery",
            "type":"Manufacturing & Wholesale Goods"
        }
    ],
    "sg:phone":"+44 20 8764 2564",
    "sg:postcode":"SW16 4SB",
    "sg:province":"Greater London",
    "sg:tags":[
        "creche"
    ],
    "wof:name":"Norbury Day Nursery & School",
    "wof:placetype":"venue"
},
  "geometry": {"coordinates":[-0.11591,51.407082],"type":"Point"}
}