{
  "type": "Feature",
  "properties": {
    "iso:country":"GB",
    "sg:address":"304 Kennington Road",
    "sg:city":"London",
    "sg:classifiers":[
        {
            "category":"Health Services",
            "subcategory":"Podiatrist",
            "type":"Services"
        }
    ],
    "sg:phone":"+44 20 7735 4303",
    "sg:postcode":"SE11 4LD",
    "sg:province":"Greater London",
    "sg:tags":[
        "podiatrists",
        "chiropodist"
    ],
    "wof:name":"The Kennington Chiropody Surgery",
    "wof:placetype":"venue"
},
  "geometry": {"coordinates":[-0.111511,51.485645],"type":"Point"}
}