{
  "type": "Feature",
  "properties": {
    "addr:full":"Oakland Avenue Droitwich Worcestershire WR9 7BT",
    "addr:postcode":"wr9 7bt",
    "addr:street":"Oakland Avenue",
    "iso:country":"GB",
    "sg:address":"Oakland Avenue",
    "sg:city":"Droitwich",
    "sg:classifiers":[
        {
            "category":"Food & Beverages",
            "subcategory":"Groceries & Convenience Stores",
            "type":"Retail Goods"
        }
    ],
    "sg:phone":"+44 1905 773242",
    "sg:postcode":"WR9 7BT",
    "sg:province":"Worcestershire",
    "wof:name":"Spar Oakland Stores",
    "wof:placetype":"venue"
},
  "geometry": {"coordinates":[-2.1527090073,52.2574653625],"type":"Point"}
}