{
  "type": "Feature",
  "properties": {
    "addr:full":"155 The Maples Harlow Essex CM19 4RD",
    "addr:housenumber":"155",
    "addr:postcode":"cm19 4rd",
    "addr:street":"The Maples",
    "iso:country":"GB",
    "sg:address":"155 The Maples",
    "sg:city":"Harlow",
    "sg:classifiers":[
        {
            "category":"Professional",
            "type":"Services"
        },
        {
            "category":"Professional",
            "subcategory":"Employment Agencies",
            "type":"Services"
        }
    ],
    "sg:phone":"+44 1279 415837",
    "sg:postcode":"CM19 4RD",
    "sg:province":"Essex",
    "sg:tags":[
        "entertainer",
        "entertainment"
    ],
    "wof:name":"Mike Jordan Entertainments",
    "wof:placetype":"venue"
},
  "geometry": {"coordinates":[0.082265,51.746845],"type":"Point"}
}