{
  "type": "Feature",
  "properties": {
    "iso:country":"GB",
    "sg:address":"12 York Street",
    "sg:city":"Cheltenham",
    "sg:classifiers":[
        {
            "category":"Retail",
            "subcategory":"Repair Shop",
            "type":"Services"
        },
        {
            "category":"Building & Trades",
            "subcategory":"Construction",
            "type":"Services"
        }
    ],
    "sg:phone":"+44 1242 517447",
    "sg:postcode":"GL52 2JT",
    "sg:province":"Gloucestershire",
    "sg:tags":[
        "joinery",
        "maintenance",
        "carpentry"
    ],
    "wof:name":"Colin Hay",
    "wof:placetype":"venue"
},
  "geometry": {"coordinates":[-2.068138,51.903019],"type":"Point"}
}