{
  "type": "Feature",
  "properties": {
    "iso:country":"GB",
    "sg:address":"9 Bantree Court",
    "sg:city":"Bradford",
    "sg:classifiers":[
        {
            "category":"Professional",
            "subcategory":"Lawyer & Legal Services",
            "type":"Services"
        }
    ],
    "sg:phone":"+44 1274 638267",
    "sg:postcode":"BD10 0SG",
    "sg:province":"West Yorkshire",
    "wof:name":"West Riding Law Agency",
    "wof:placetype":"venue"
},
  "geometry": {"coordinates":[-1.7417969704,53.8421669006],"type":"Point"}
}