{
  "type": "Feature",
  "properties": {
    "iso:country":"GB",
    "sg:address":"Moor Farm, Black Dog",
    "sg:city":"Crediton",
    "sg:classifiers":[
        {
            "category":"Farming",
            "subcategory":"Livestock Farm",
            "type":"Manufacturing & Wholesale Goods"
        }
    ],
    "sg:phone":"+44 1363 866297",
    "sg:postcode":"EX17 4RW",
    "sg:province":"Devon",
    "sg:tags":[
        "others"
    ],
    "wof:name":"N W & S M Gosling",
    "wof:placetype":"venue"
},
  "geometry": {"coordinates":[-3.698794,50.87484],"type":"Point"}
}