{
  "type": "Feature",
  "properties": {
    "addr:full":"77 Norwich Road, Watton Thetford Norfolk IP25 6DH",
    "addr:housenumber":"77",
    "addr:postcode":"ip25 6dh",
    "addr:street":"Norwich Road",
    "iso:country":"GB",
    "sg:address":"77 Norwich Road, Watton",
    "sg:city":"Thetford",
    "sg:classifiers":[
        {
            "category":"Autos & Motor Vehicles",
            "subcategory":"Automobile Sales",
            "type":"Retail Goods"
        }
    ],
    "sg:phone":"+44 1953 889090",
    "sg:postcode":"IP25 6DH",
    "sg:province":"Norfolk",
    "sg:tags":[
        "car"
    ],
    "wof:name":"Dyes of Watton Ltd.",
    "wof:placetype":"venue"
},
  "geometry": {"coordinates":[0.8342000246,52.5704994202],"type":"Point"}
}