{
  "type": "Feature",
  "properties": {
    "addr:full":"Unit 2 Woods Way, Goring-by-sea Worthing West Sussex BN12 4QY",
    "addr:housenumber":"unit 2",
    "addr:postcode":"bn12 4qy",
    "addr:street":"Woods Way",
    "iso:country":"GB",
    "sg:address":"Unit 2 Woods Way, Goring-by-sea",
    "sg:city":"Worthing",
    "sg:classifiers":[
        {
            "category":"Shopping",
            "subcategory":"Stationery & Office Supplies",
            "type":"Retail Goods"
        }
    ],
    "sg:phone":"+44 1903 501040",
    "sg:postcode":"BN12 4QY",
    "sg:province":"West Sussex",
    "sg:tags":[
        "printers'"
    ],
    "wof:name":"College Hill Press Ltd.",
    "wof:placetype":"venue"
},
  "geometry": {"coordinates":[-0.4231590033,50.8170661926],"type":"Point"}
}