{
  "type": "Feature",
  "properties": {
    "iso:country":"GB",
    "sg:address":"4 Church Street",
    "sg:city":"Oakham",
    "sg:classifiers":[
        {
            "category":"Food & Beverages",
            "subcategory":"Bakery",
            "type":"Retail Goods"
        }
    ],
    "sg:phone":"+44 1572 722114",
    "sg:postcode":"LE15 6AA",
    "sg:province":"Leicestershire",
    "sg:tags":[
        "confectionery"
    ],
    "wof:name":"A B Strickland & Son",
    "wof:placetype":"venue"
},
  "geometry": {"coordinates":[-0.730006,52.669991],"type":"Point"}
}