{
  "type": "Feature",
  "properties": {
    "iso:country":"GB",
    "sg:address":"4 Hurst Lane North, Castle Bromwich",
    "sg:city":"Birmingham",
    "sg:classifiers":[
        {
            "category":"Personal",
            "subcategory":"Beauty Salon",
            "type":"Services"
        }
    ],
    "sg:phone":"+44 121 747 2129",
    "sg:postcode":"B36 0EU",
    "sg:province":"West Midlands",
    "sg:tags":[
        "unisex",
        "hairdresser"
    ],
    "wof:name":"Snowdons",
    "wof:placetype":"venue"
},
  "geometry": {"coordinates":[-1.764193,52.50169],"type":"Point"}
}