{
  "type": "Feature",
  "properties": {
    "iso:country":"GB",
    "sg:address":"79 The Fairway",
    "sg:city":"Abbots Langley",
    "sg:classifiers":[
        {
            "category":"Home & Garden",
            "subcategory":"Building Materials",
            "type":"Retail Goods"
        }
    ],
    "sg:postcode":"WD5 0JY",
    "sg:province":"Hertfordshire",
    "sg:tags":[
        "fencing"
    ],
    "wof:name":"Raymond J French",
    "wof:placetype":"venue"
},
  "geometry": {"coordinates":[-0.423372,51.697273],"type":"Point"}
}