{
  "type": "Feature",
  "properties": {
    "iso:country":"GB",
    "sg:address":"105 Hanover Street",
    "sg:city":"Edinburgh",
    "sg:classifiers":[
        {
            "category":"Organizations",
            "subcategory":"Professional Association",
            "type":"Services"
        }
    ],
    "sg:phone":"+44 131 226 1414",
    "sg:postcode":"EH2 1DR",
    "sg:province":"City of Edinburgh",
    "sg:tags":[
        "union",
        "trade"
    ],
    "wof:name":"G P M U",
    "wof:placetype":"venue"
},
  "geometry": {"coordinates":[-3.197591,55.954613],"type":"Point"}
}