{
  "type": "Feature",
  "properties": {
    "addr:full":"Gorseinon Road, Penllergaer Swansea Carmarthenshire SA4 9GG",
    "addr:postcode":"sa4 9gg",
    "addr:street":"Gorseinon Road",
    "iso:country":"GB",
    "sg:address":"Gorseinon Road, Penllergaer",
    "sg:city":"Swansea",
    "sg:classifiers":[
        {
            "category":"Building & Trades",
            "subcategory":"Construction",
            "type":"Services"
        }
    ],
    "sg:postcode":"SA4 9GG",
    "sg:province":"Carmarthenshire",
    "sg:tags":[
        "flooring"
    ],
    "wof:name":"Paul Combes Decorative Interiors",
    "wof:placetype":"venue"
},
  "geometry": {"coordinates":[-4.0086832047,51.6707420349],"type":"Point"}
}