{
  "type": "Feature",
  "properties": {
    "addr:full":"Lyndon House, Heeley Road, Selly Oak Birmingham West Midlands B29 6EN",
    "addr:postcode":"b29 6en",
    "addr:street":"Heeley Road",
    "iso:country":"GB",
    "sg:address":"Lyndon House, Heeley Road, Selly Oak",
    "sg:city":"Birmingham",
    "sg:classifiers":[
        {
            "category":"Wholesale",
            "subcategory":"Medical Equipment & Supplies",
            "type":"Manufacturing & Wholesale Goods"
        }
    ],
    "sg:phone":"+44 121 472 7353",
    "sg:postcode":"B29 6EN",
    "sg:province":"West Midlands",
    "sg:tags":[
        "hospital"
    ],
    "wof:name":"Appleton Woods Ltd.",
    "wof:placetype":"venue"
},
  "geometry": {"coordinates":[-1.935939,52.442749],"type":"Point"}
}