{
  "type": "Feature",
  "properties": {
    "addr:full":"5 Main St Perth Perth and Kinross PH1 3NJ",
    "addr:housenumber":"5",
    "addr:postcode":"ph1 3nj",
    "addr:street":"Main St",
    "iso:country":"GB",
    "sg:address":"5 Main St",
    "sg:city":"Perth",
    "sg:classifiers":[
        {
            "category":"Professional",
            "subcategory":"Accounting & Tax Preparation",
            "type":"Services"
        }
    ],
    "sg:phone":"+44 1738 583990",
    "sg:postcode":"PH1 3NJ",
    "sg:province":"Perth and Kinross",
    "sg:tags":[
        "accountant"
    ],
    "wof:name":"Tax Team The",
    "wof:placetype":"venue"
},
  "geometry": {"coordinates":[-3.5164220333,56.4161262512],"type":"Point"}
}