{
  "type": "Feature",
  "properties": {
    "addr:full":"116 Collier Row Road, Collier Road Romford Essex RM5 2BB",
    "addr:housenumber":"116",
    "addr:postcode":"rm5 2bb",
    "addr:street":"Collier Row Road Collier Road",
    "iso:country":"GB",
    "sg:address":"116 Collier Row Road, Collier Road",
    "sg:city":"Romford",
    "sg:classifiers":[
        {
            "category":"Shopping",
            "subcategory":"Photographic Equipment",
            "type":"Retail Goods"
        }
    ],
    "sg:postcode":"RM5 2BB",
    "sg:province":"Essex",
    "wof:name":"Concord U K Ltd.",
    "wof:placetype":"venue"
},
  "geometry": {"coordinates":[0.156991,51.59811],"type":"Point"}
}