{
  "type": "Feature",
  "properties": {
    "iso:country":"GB",
    "sg:address":"1 The Arcade, Fore Street",
    "sg:city":"Okehampton",
    "sg:classifiers":[
        {
            "category":"Home & Garden",
            "subcategory":"Household Appliances",
            "type":"Retail Goods"
        }
    ],
    "sg:phone":"+44 1837 55070",
    "sg:postcode":"EX20 1EX",
    "sg:province":"Devon",
    "sg:tags":[
        "domestic",
        "centre"
    ],
    "wof:name":"P K Domestic Appliances",
    "wof:placetype":"venue"
},
  "geometry": {"coordinates":[-4.001889,50.738876],"type":"Point"}
}