{
  "type": "Feature",
  "properties": {
    "addr:full":"Fore Street, Bovey Tracey Newton Abbot Devon TQ13 9AF",
    "addr:postcode":"tq13 9af",
    "addr:street":"Fore Street",
    "iso:country":"GB",
    "sg:address":"Fore Street, Bovey Tracey",
    "sg:city":"Newton Abbot",
    "sg:classifiers":[
        {
            "category":"Travel",
            "subcategory":"Hotels & Motels",
            "type":"Entertainment"
        }
    ],
    "sg:phone":"+44 1626 832293",
    "sg:postcode":"TQ13 9AF",
    "sg:province":"Devon",
    "wof:name":"The Riverside Inn",
    "wof:placetype":"venue"
},
  "geometry": {"coordinates":[-3.673219,50.594585],"type":"Point"}
}