{
  "type": "Feature",
  "properties": {
    "iso:country":"GB",
    "sg:address":"The Old Bakehouse, Tintern",
    "sg:city":"Chepstow",
    "sg:classifiers":[
        {
            "category":"Shopping",
            "subcategory":"Antiques",
            "type":"Retail Goods"
        }
    ],
    "sg:postcode":"NP16 6SE",
    "sg:province":"Gloucestershire",
    "wof:name":"Tintern Antiques",
    "wof:placetype":"venue"
},
  "geometry": {"coordinates":[-2.683521986,51.7062301636],"type":"Point"}
}