{
  "type": "Feature",
  "properties": {
    "addr:full":"1/69 Sinclair Road, Kensington London Greater London W14 0NR",
    "addr:housenumber":"1 / 69",
    "addr:postcode":"w14 0nr",
    "addr:street":"Sinclair Road",
    "iso:country":"GB",
    "sg:address":"1/69 Sinclair Road, Kensington",
    "sg:city":"London",
    "sg:classifiers":[
        {
            "category":"Professional",
            "subcategory":"Computer Services",
            "type":"Services"
        }
    ],
    "sg:postcode":"W14 0NR",
    "sg:province":"Greater London",
    "sg:tags":[
        "system",
        "software"
    ],
    "wof:name":"Minoan Enterprises Ltd",
    "wof:placetype":"venue"
},
  "geometry": {"coordinates":[-0.211401,51.497738],"type":"Point"}
}