{
  "type": "Feature",
  "properties": {
    "addr:full":"4 Minden Pde Bury Lancashire BL9 0QG",
    "addr:housenumber":"4",
    "addr:postcode":"bl9 0qg",
    "iso:country":"GB",
    "sg:address":"4 Minden Pde",
    "sg:city":"Bury",
    "sg:classifiers":[
        {
            "category":"Shopping",
            "subcategory":"Department Store",
            "type":"Retail Goods"
        }
    ],
    "sg:postcode":"BL9 0QG",
    "sg:province":"Lancashire",
    "wof:name":"Morris,Edward,",
    "wof:placetype":"venue"
},
  "geometry": {"coordinates":[-2.325309,53.591099],"type":"Point"}
}