{
  "type": "Feature",
  "properties": {
    "addr:full":"Spencer Road, Lidget Grn Bradford West Yorkshire BD7 2HD",
    "addr:postcode":"bd7 2hd",
    "addr:street":"Spencer Road Lidget Grn Bradford West",
    "iso:country":"GB",
    "sg:address":"Spencer Road, Lidget Grn",
    "sg:city":"Bradford",
    "sg:classifiers":[
        {
            "category":"Government",
            "subcategory":"Fire Station",
            "type":"Public Place"
        }
    ],
    "sg:phone":"+44 1274 571578",
    "sg:postcode":"BD7 2HD",
    "sg:province":"West Yorkshire",
    "sg:tags":[
        "equipment",
        "escape",
        "evacuation"
    ],
    "wof:name":"E Greenwood",
    "wof:placetype":"venue"
},
  "geometry": {"coordinates":[-1.779384017,53.7882881165],"type":"Point"}
}