{
  "type": "Feature",
  "properties": {
    "iso:country":"GB",
    "sg:address":"10 Holst Way",
    "sg:city":"Waterlooville",
    "sg:classifiers":[
        {
            "category":"Building & Trades",
            "subcategory":"Landscaping Services",
            "type":"Services"
        }
    ],
    "sg:postcode":"PO7 5SJ",
    "sg:province":"Hampshire",
    "sg:tags":[
        "forestry",
        "tree"
    ],
    "wof:name":"Arbro Tree Surgeons",
    "wof:placetype":"venue"
},
  "geometry": {"coordinates":[-1.027538,50.868961],"type":"Point"}
}