{
  "type": "Feature",
  "properties": {
    "addr:full":"86 Mayfield Crescent London Greater London N9 7NJ",
    "addr:housenumber":"86",
    "addr:postcode":"n9 7nj",
    "addr:street":"Mayfield Crescent",
    "iso:country":"GB",
    "sg:address":"86 Mayfield Crescent",
    "sg:city":"London",
    "sg:classifiers":[
        {
            "category":"Building & Trades",
            "subcategory":"Construction",
            "type":"Services"
        }
    ],
    "sg:postcode":"N9 7NJ",
    "sg:province":"Greater London",
    "sg:tags":[
        "concrete"
    ],
    "wof:name":"A C Pumps Ltd.",
    "wof:placetype":"venue"
},
  "geometry": {"coordinates":[-0.054949,51.642254],"type":"Point"}
}