{
  "type": "Feature",
  "properties": {
    "iso:country":"GB",
    "sg:address":"212 Winsford Avenue",
    "sg:city":"Coventry",
    "sg:classifiers":[
        {
            "category":"Personal",
            "subcategory":"Barber",
            "type":"Services"
        }
    ],
    "sg:phone":"+44 24 7669 1693",
    "sg:postcode":"CV5 9NB",
    "sg:province":"West Midlands",
    "sg:tags":[
        "men's",
        "hairdresser"
    ],
    "wof:name":"Sean's",
    "wof:placetype":"venue"
},
  "geometry": {"coordinates":[-1.5635420084,52.4158668518],"type":"Point"}
}