{
  "type": "Feature",
  "properties": {
    "addr:full":"Stubden House, Denholme Bradford West Yorkshire BD13 4DX",
    "addr:postcode":"bd13 4dx",
    "addr:street":"West",
    "iso:country":"GB",
    "sg:address":"Stubden House, Denholme",
    "sg:city":"Bradford",
    "sg:classifiers":[
        {
            "category":"Real Estate",
            "subcategory":"Real Estate Services",
            "type":"Services"
        },
        {
            "category":"Building & Trades",
            "subcategory":"Construction",
            "type":"Services"
        }
    ],
    "sg:phone":"+44 1274 832987",
    "sg:postcode":"BD13 4DX",
    "sg:province":"West Yorkshire",
    "sg:tags":[
        "builder"
    ],
    "wof:name":"Headworks Maintenance Services Ltd",
    "wof:placetype":"venue"
},
  "geometry": {"coordinates":[-1.896679,53.800529],"type":"Point"}
}