{
  "type": "Feature",
  "properties": {
    "addr:full":"Graphics House, Arundel Road Uxbridge Buckinghamshire UB8 2JX",
    "addr:postcode":"ub8 2jx",
    "addr:street":"Arundel Road",
    "iso:country":"GB",
    "sg:address":"Graphics House, Arundel Road",
    "sg:city":"Uxbridge",
    "sg:classifiers":[
        {
            "category":"Professional",
            "subcategory":"Printing & Photocopies",
            "type":"Services"
        }
    ],
    "sg:phone":"+44 1895 812525",
    "sg:postcode":"UB8 2JX",
    "sg:province":"Buckinghamshire",
    "sg:tags":[
        "printer"
    ],
    "wof:name":"Maygray Graphics Ltd.",
    "wof:placetype":"venue"
},
  "geometry": {"coordinates":[-0.490101,51.535194],"type":"Point"}
}