{
  "type": "Feature",
  "properties": {
    "iso:country":"GB",
    "sg:address":"45 Mill Farm Road, Harborne",
    "sg:city":"Birmingham",
    "sg:classifiers":[
        {
            "category":"Building & Trades",
            "subcategory":"Construction",
            "type":"Services"
        }
    ],
    "sg:phone":"+44 121 472 0718",
    "sg:postcode":"B17 0QX",
    "sg:province":"West Midlands",
    "sg:tags":[
        "builder"
    ],
    "wof:name":"J J Ryan & Sons",
    "wof:placetype":"venue"
},
  "geometry": {"coordinates":[-1.9535449743,52.4492073059],"type":"Point"}
}