{
  "type": "Feature",
  "properties": {
    "addr:full":"8 Endwell Road Bexhill-on-sea East Sussex TN40 1EA",
    "addr:housenumber":"8",
    "addr:postcode":"tn40 1ea",
    "addr:street":"Endwell Road",
    "iso:country":"GB",
    "sg:address":"8 Endwell Road",
    "sg:city":"Bexhill-on-sea",
    "sg:classifiers":[
        {
            "category":"Real Estate",
            "subcategory":"Surveying",
            "type":"Services"
        },
        {
            "category":"Real Estate",
            "subcategory":"Architect",
            "type":"Services"
        }
    ],
    "sg:phone":"+44 1424 218510",
    "sg:postcode":"TN40 1EA",
    "sg:province":"East Sussex",
    "sg:tags":[
        "surveyor",
        "valuer"
    ],
    "wof:name":"Stephen L Cawthorne",
    "wof:placetype":"venue"
},
  "geometry": {"coordinates":[0.4747979939,50.8405761719],"type":"Point"}
}