{
  "type": "Feature",
  "properties": {
    "addr:full":"27 Winton Place Tranent East Lothian EH33 1AE",
    "addr:housenumber":"27",
    "addr:postcode":"eh33 1ae",
    "addr:street":"Winton",
    "iso:country":"GB",
    "sg:address":"27 Winton Place",
    "sg:city":"Tranent",
    "sg:classifiers":[
        {
            "category":"Building & Trades",
            "subcategory":"Construction",
            "type":"Services"
        }
    ],
    "sg:phone":"+44 1875 611441",
    "sg:postcode":"EH33 1AE",
    "sg:province":"East Lothian",
    "sg:tags":[
        "joinery",
        "joiner",
        "carpenter",
        "carpentry"
    ],
    "wof:name":"Brian S Blackie",
    "wof:placetype":"venue"
},
  "geometry": {"coordinates":[-2.953473,55.945221],"type":"Point"}
}