{
  "type": "Feature",
  "properties": {
    "addr:full":"Meathop Road Grange-over-sands Cumbria LA11 6QX",
    "addr:postcode":"la11 6qx",
    "addr:street":"Meathop Road",
    "iso:country":"GB",
    "sg:address":"Meathop Road",
    "sg:city":"Grange-over-sands",
    "sg:classifiers":[
        {
            "category":"Sports & Exercise",
            "subcategory":"Golf",
            "type":"Entertainment"
        }
    ],
    "sg:phone":"+44 15395 33180",
    "sg:postcode":"LA11 6QX",
    "sg:province":"Cumbria",
    "sg:tags":[
        "club",
        "course"
    ],
    "wof:name":"Grange-over-Sands Golf Club",
    "wof:placetype":"venue"
},
  "geometry": {"coordinates":[-2.8769791126,54.2029647827],"type":"Point"}
}