{
  "type": "Feature",
  "properties": {
    "addr:full":"The Grange, Wolverton Stratford Upon Avon Warwickshire CV37 0HD",
    "addr:postcode":"cv37 0hd",
    "iso:country":"GB",
    "sg:address":"The Grange, Wolverton",
    "sg:city":"Stratford Upon Avon",
    "sg:classifiers":[
        {
            "category":"Autos & Motor Vehicles",
            "subcategory":"Auto Supplies",
            "type":"Retail Goods"
        }
    ],
    "sg:phone":"+44 1789 730095",
    "sg:postcode":"CV37 0HD",
    "sg:province":"Warwickshire",
    "sg:tags":[
        "component"
    ],
    "wof:name":"Relco",
    "wof:placetype":"venue"
},
  "geometry": {"coordinates":[-1.6968870163,52.2574615479],"type":"Point"}
}