{
  "type": "Feature",
  "properties": {
    "addr:full":"21a St Leonards Road London Greater London SW14 7LY",
    "addr:housenumber":"21a",
    "addr:postcode":"sw14 7ly",
    "addr:street":"St Leonards Road",
    "iso:country":"GB",
    "sg:address":"21a St Leonards Road",
    "sg:city":"London",
    "sg:classifiers":[
        {
            "category":"Retail",
            "subcategory":"Event Space",
            "type":"Services"
        }
    ],
    "sg:phone":"+44 20 8487 2200",
    "sg:postcode":"SW14 7LY",
    "sg:province":"Greater London",
    "sg:tags":[
        "exhibition",
        "organiser"
    ],
    "wof:name":"Richmond Events Ltd.",
    "wof:placetype":"venue"
},
  "geometry": {"coordinates":[-0.2680810094,51.4665412903],"type":"Point"}
}