{
  "type": "Feature",
  "properties": {
    "addr:full":"Gem Mill, Fields New Road, Chadderton Oldham Lancashire OL9 8NP",
    "addr:postcode":"ol9 8np",
    "addr:street":"Gem Mill Fields New Road",
    "iso:country":"GB",
    "sg:address":"Gem Mill, Fields New Road, Chadderton",
    "sg:city":"Oldham",
    "sg:classifiers":[
        {
            "category":"Professional",
            "type":"Services"
        }
    ],
    "sg:phone":"+44 161 628 9599",
    "sg:postcode":"OL9 8NP",
    "sg:province":"Lancashire",
    "sg:tags":[
        "control",
        "system"
    ],
    "wof:name":"Hollas Electronic Assembly Services",
    "wof:placetype":"venue"
},
  "geometry": {"coordinates":[-2.143439,53.53672],"type":"Point"}
}