{
  "type": "Feature",
  "properties": {
    "iso:country":"GB",
    "sg:address":"A3 Bowling Mill, Dean Clough Office Park",
    "sg:city":"Halifax",
    "sg:classifiers":[
        {
            "category":"Professional",
            "type":"Services"
        }
    ],
    "sg:phone":"+44 1422 330950",
    "sg:postcode":"HX3 5AX",
    "sg:province":"West Yorkshire",
    "sg:tags":[
        "specialist",
        "coating"
    ],
    "wof:name":"Coating & Converting Services",
    "wof:placetype":"venue"
},
  "geometry": {"coordinates":[-1.86319,53.728081],"type":"Point"}
}