{
  "type": "Feature",
  "properties": {
    "iso:country":"GB",
    "sg:address":"11 Salop Road, Oswestry Street",
    "sg:city":"Oswestry",
    "sg:classifiers":[
        {
            "category":"Wholesale",
            "subcategory":"Office Equipment",
            "type":"Manufacturing & Wholesale Goods"
        }
    ],
    "sg:phone":"+44 1691 655244",
    "sg:postcode":"SY11 2NR",
    "sg:province":"Shropshire",
    "wof:name":"The Hollis Office Supply Co. Ltd.",
    "wof:placetype":"venue"
},
  "geometry": {"coordinates":[-3.053042,52.858757],"type":"Point"}
}