{
  "type": "Feature",
  "properties": {
    "iso:country":"GB",
    "sg:address":"West Park Road",
    "sg:city":"Blackburn",
    "sg:classifiers":[
        {
            "category":"Education",
            "subcategory":"School",
            "type":"Public Place"
        }
    ],
    "sg:phone":"+44 1254 686300",
    "sg:postcode":"BB2 6DF",
    "sg:province":"Lancashire",
    "sg:tags":[
        "independent",
        "preparatory"
    ],
    "wof:name":"Queen Elizabeth's Grammar School Blackburn Ltd.",
    "wof:placetype":"venue"
},
  "geometry": {"coordinates":[-2.499449,53.753948],"type":"Point"}
}