{
  "type": "Feature",
  "properties": {
    "addr:full":"Huntingdon St Nottingham Nottinghamshire NG1 3LH",
    "addr:postcode":"ng1 3lh",
    "addr:street":"Huntingdon St",
    "iso:country":"GB",
    "sg:address":"Huntingdon St",
    "sg:city":"Nottingham",
    "sg:classifiers":[
        {
            "category":"Government",
            "subcategory":"Post Office",
            "type":"Public Place"
        }
    ],
    "sg:phone":"+44 115 915 3800",
    "sg:postcode":"NG1 3LH",
    "sg:province":"Nottinghamshire",
    "sg:tags":[
        "organisation",
        "soc",
        "research"
    ],
    "wof:name":"Nottingham Fashion Centre",
    "wof:placetype":"venue"
},
  "geometry": {"coordinates":[-1.1509280205,52.9626922607],"type":"Point"}
}