{
  "type": "Feature",
  "properties": {
    "iso:country":"GB",
    "sg:address":"61 Sandwell Centre",
    "sg:city":"West Bromwich",
    "sg:classifiers":[
        {
            "category":"Professional",
            "subcategory":"Computer Services",
            "type":"Services"
        }
    ],
    "sg:phone":"+44 121 525 5708",
    "sg:postcode":"B70 7NJ",
    "sg:province":"West Midlands",
    "sg:tags":[
        "system",
        "software"
    ],
    "wof:name":"Game Retail (U K) Ltd.",
    "wof:placetype":"venue"
},
  "geometry": {"coordinates":[-1.9902240038,52.5186233521],"type":"Point"}
}