{
  "type": "Feature",
  "properties": {
    "iso:country":"GB",
    "sg:address":"5 The Square, Keyworth",
    "sg:city":"Nottingham",
    "sg:classifiers":[
        {
            "category":"Shopping",
            "subcategory":"Clothing, Apparel, & Fashions",
            "type":"Retail Goods"
        }
    ],
    "sg:postcode":"NG12 5JT",
    "sg:province":"Nottinghamshire",
    "sg:tags":[
        "menswear"
    ],
    "wof:name":"Wise Guise",
    "wof:placetype":"venue"
},
  "geometry": {"coordinates":[-1.090158,52.871143],"type":"Point"}
}