{
  "type": "Feature",
  "properties": {
    "addr:full":"14 Haven Grn, Ealing Broadway London Greater London W5 2UU",
    "addr:housenumber":"14",
    "addr:postcode":"w5 2uu",
    "addr:street":"Haven Grn",
    "iso:country":"GB",
    "sg:address":"14 Haven Grn, Ealing Broadway",
    "sg:city":"London",
    "sg:classifiers":[
        {
            "category":"Organizations",
            "subcategory":"Non-profit Organization",
            "type":"Services"
        }
    ],
    "sg:phone":"+44 20 8997 2489",
    "sg:postcode":"W5 2UU",
    "sg:province":"Greater London",
    "sg:tags":[
        "organisation",
        "voluntary",
        "charity"
    ],
    "wof:name":"Nousha Creations",
    "wof:placetype":"venue"
},
  "geometry": {"coordinates":[-0.3049300015,51.5158729553],"type":"Point"}
}