{
  "type": "Feature",
  "properties": {
    "addr:full":"Zetland Street Northallerton North Yorkshire DL6 1NA",
    "addr:postcode":"dl6 1na",
    "addr:street":"Zetland Street",
    "iso:country":"GB",
    "sg:address":"Zetland Street",
    "sg:city":"Northallerton",
    "sg:classifiers":[
        {
            "category":"Communications",
            "type":"Services"
        }
    ],
    "sg:postcode":"DL6 1NA",
    "sg:province":"North Yorkshire",
    "sg:tags":[
        "tv",
        "video",
        "radio"
    ],
    "wof:name":"4 A Electricas Services",
    "wof:placetype":"venue"
},
  "geometry": {"coordinates":[-1.432814,54.338902],"type":"Point"}
}