{
  "type": "Feature",
  "properties": {
    "addr:full":"13-15 Cavendish Square Swindon Wiltshire SN3 2LP",
    "addr:housenumber":"13-15",
    "addr:postcode":"sn3 2lp",
    "addr:street":"Cavendish Square",
    "iso:country":"GB",
    "sg:address":"13-15 Cavendish Square",
    "sg:city":"Swindon",
    "sg:classifiers":[
        {
            "category":"Autos & Motor Vehicles",
            "subcategory":"Auto Supplies",
            "type":"Retail Goods"
        },
        {
            "category":"Shopping",
            "type":"Retail Goods"
        }
    ],
    "sg:phone":"+44 1793 526344",
    "sg:postcode":"SN3 2LP",
    "sg:province":"Wiltshire",
    "sg:tags":[
        "car",
        "part",
        "accessory"
    ],
    "wof:name":"Motorcare",
    "wof:placetype":"venue"
},
  "geometry": {"coordinates":[-1.751204,51.552654],"type":"Point"}
}