{
  "type": "Feature",
  "properties": {
    "addr:full":"48 Holme Terrace, Ashton In Makerfield Wigan Lancashire WN1 2HG",
    "addr:housenumber":"48",
    "addr:postcode":"wn1 2hg",
    "addr:street":"Holme Terrace",
    "iso:country":"GB",
    "sg:address":"48 Holme Terrace, Ashton In Makerfield",
    "sg:city":"Wigan",
    "sg:classifiers":[
        {
            "category":"Shopping",
            "subcategory":"Books",
            "type":"Retail Goods"
        }
    ],
    "sg:phone":"+44 1942 748494",
    "sg:postcode":"WN1 2HG",
    "sg:province":"Lancashire",
    "wof:name":"Impact Education",
    "wof:placetype":"venue"
},
  "geometry": {"coordinates":[-2.635875,53.558449],"type":"Point"}
}