{
  "type": "Feature",
  "properties": {
    "iso:country":"GB",
    "sg:address":"8 Botley Rd, North Baddesley",
    "sg:city":"Southampton",
    "sg:phone":"+44 23 8041 2555",
    "sg:postcode":"SO52 9DP",
    "sg:province":"Hampshire",
    "wof:name":"Prototyp UK",
    "wof:placetype":"venue"
},
  "geometry": {"coordinates":[-1.4545500278,50.9833641052],"type":"Point"}
}