{
  "type": "Feature",
  "properties": {
    "addr:full":"High Street, Guidepost Choppington Northumberland NE62 5QY",
    "addr:postcode":"ne62 5qy",
    "addr:street":"High Street;Northumberland",
    "iso:country":"GB",
    "sg:address":"High Street, Guidepost",
    "sg:city":"Choppington",
    "sg:classifiers":[
        {
            "category":"Retail",
            "subcategory":"Auto Repair",
            "type":"Services"
        }
    ],
    "sg:postcode":"NE62 5QY",
    "sg:province":"Northumberland",
    "sg:tags":[
        "modification",
        "garage"
    ],
    "wof:name":"Carl Carey",
    "wof:placetype":"venue"
},
  "geometry": {"coordinates":[-1.6000850201,55.1461753845],"type":"Point"}
}