{
  "type": "Feature",
  "properties": {
    "iso:country":"GB",
    "sg:address":"65 School Road, Himley",
    "sg:city":"Dudley",
    "sg:classifiers":[
        {
            "category":"Retail",
            "subcategory":"Auto Repair",
            "type":"Services"
        }
    ],
    "sg:phone":"+44 1902 897447",
    "sg:postcode":"DY3 4LG",
    "sg:province":"Staffordshire",
    "sg:tags":[
        "modification",
        "garage",
        "related"
    ],
    "wof:name":"David & Tony Hewitt Hewitt",
    "wof:placetype":"venue"
},
  "geometry": {"coordinates":[-2.177725,52.519062],"type":"Point"}
}