{
  "type": "Feature",
  "properties": {
    "addr:full":"Stall 37 Market Hall, Admill Market Nelson Lancashire BB9 9SL",
    "addr:housenumber":"37",
    "addr:postcode":"bb9 9sl",
    "addr:street":"Stall;Market Hall Admill;Nelson",
    "iso:country":"GB",
    "sg:address":"Stall 37 Market Hall, Admill Market",
    "sg:city":"Nelson",
    "sg:classifiers":[
        {
            "category":"Shopping",
            "subcategory":"Clothing, Apparel, & Fashions",
            "type":"Retail Goods"
        }
    ],
    "sg:phone":"+44 1282 614331",
    "sg:postcode":"BB9 9SL",
    "sg:province":"Lancashire",
    "sg:tags":[
        "haberdasher"
    ],
    "wof:name":"The Sewing Box",
    "wof:placetype":"venue"
},
  "geometry": {"coordinates":[-2.21334,53.835968],"type":"Point"}
}