{
  "type": "Feature",
  "properties": {
    "iso:country":"GB",
    "sg:address":"14 Emlyn Square",
    "sg:city":"Swindon",
    "sg:classifiers":[
        {
            "category":"Bars & Pubs",
            "type":"Food & Drink"
        }
    ],
    "sg:phone":"+44 1793 523780",
    "sg:postcode":"SN1 5BN",
    "sg:province":"Wiltshire",
    "sg:tags":[
        "pubs",
        "inn"
    ],
    "wof:name":"The Cricketers Arms",
    "wof:placetype":"venue"
},
  "geometry": {"coordinates":[-1.79129,51.561428],"type":"Point"}
}