{
  "type": "Feature",
  "properties": {
    "iso:country":"GB",
    "sg:address":"Romford Road, Astonfields Estate",
    "sg:city":"Stafford",
    "sg:classifiers":[
        {
            "category":"Manufacturing",
            "subcategory":"Chemicals & Compounds",
            "type":"Manufacturing & Wholesale Goods"
        }
    ],
    "sg:phone":"+44 1785 222313",
    "sg:postcode":"ST16 3DZ",
    "sg:province":"Staffordshire",
    "sg:tags":[
        "abrasive",
        "product",
        "cleaning"
    ],
    "wof:name":"Abrapower Ltd.",
    "wof:placetype":"venue"
},
  "geometry": {"coordinates":[-2.1145870686,52.8201713562],"type":"Point"}
}