{
  "type": "Feature",
  "properties": {
    "addr:full":"3 Blackpool Old Rd Poulton-le-fylde Lancashire FY6 7DU",
    "addr:housenumber":"3",
    "addr:postcode":"fy6 7du",
    "addr:street":"Blackpool Old Rd Poulton-Le-Fylde",
    "iso:country":"GB",
    "sg:address":"3 Blackpool Old Rd",
    "sg:city":"Poulton-le-fylde",
    "sg:classifiers":[
        {
            "category":"Insurance",
            "subcategory":"Insurance Agent",
            "type":"Services"
        }
    ],
    "sg:postcode":"FY6 7DU",
    "sg:province":"Lancashire",
    "sg:tags":[
        "broker"
    ],
    "wof:name":"Mackie,David,",
    "wof:placetype":"venue"
},
  "geometry": {"coordinates":[-2.992214,53.846489],"type":"Point"}
}