{
  "type": "Feature",
  "properties": {
    "iso:country":"GB",
    "sg:address":"Swallow Mead Farm, 26 Worlington Road",
    "sg:city":"Bury St Edmunds",
    "sg:classifiers":[
        {
            "category":"Professional",
            "subcategory":"Engineering",
            "type":"Services"
        }
    ],
    "sg:phone":"+44 1638 714296",
    "sg:postcode":"IP28 7DY",
    "sg:province":"Cambridgeshire",
    "sg:tags":[
        "contractor",
        "electrical",
        "engineer"
    ],
    "wof:name":"Robert J King",
    "wof:placetype":"venue"
},
  "geometry": {"coordinates":[0.50496,52.33931],"type":"Point"}
}