{
  "type": "Feature",
  "properties": {
    "addr:full":"193 Ashley Road, Hale Altrincham Cheshire WA15 9SQ",
    "addr:housenumber":"193",
    "addr:postcode":"wa15 9sq",
    "addr:street":"Ashley Road",
    "iso:country":"GB",
    "sg:address":"193 Ashley Road, Hale",
    "sg:city":"Altrincham",
    "sg:classifiers":[
        {
            "category":"Shopping",
            "subcategory":"Books",
            "type":"Retail Goods"
        }
    ],
    "sg:phone":"+44 161 928 1494",
    "sg:postcode":"WA15 9SQ",
    "sg:province":"Cheshire",
    "sg:tags":[
        "bookseller"
    ],
    "wof:name":"Hale Bookshop",
    "wof:placetype":"venue"
},
  "geometry": {"coordinates":[-2.344829,53.376614],"type":"Point"}
}