{
  "type": "Feature",
  "properties": {
    "iso:country":"GB",
    "sg:address":"46 Green La",
    "sg:city":"Amersham",
    "sg:classifiers":[
        {
            "category":"Professional",
            "subcategory":"Printing & Photocopies",
            "type":"Services"
        }
    ],
    "sg:phone":"+44 1494 723355",
    "sg:postcode":"HP6 6AR",
    "sg:province":"Buckinghamshire",
    "sg:tags":[
        "printer"
    ],
    "wof:name":"Alexander Print Management",
    "wof:placetype":"venue"
},
  "geometry": {"coordinates":[-0.5972880125,51.676776886],"type":"Point"}
}