{
  "type": "Feature",
  "properties": {
    "addr:full":"48 Morland Estate, Richmond Road London Greater London E8 3EJ",
    "addr:housenumber":"48",
    "addr:postcode":"e8 3ej",
    "addr:street":"Morland Estate Richmond Road",
    "iso:country":"GB",
    "sg:address":"48 Morland Estate, Richmond Road",
    "sg:city":"London",
    "sg:classifiers":[
        {
            "category":"Professional",
            "type":"Services"
        }
    ],
    "sg:postcode":"E8 3EJ",
    "sg:province":"Greater London",
    "sg:tags":[
        "entertainer"
    ],
    "wof:name":"Len Belmont Productions",
    "wof:placetype":"venue"
},
  "geometry": {"coordinates":[-0.0640259981,51.5425949097],"type":"Point"}
}