{
  "type": "Feature",
  "properties": {
    "iso:country":"GB",
    "sg:address":"Catherine House, 9-11 St Catherine Street",
    "sg:city":"Gloucester",
    "sg:classifiers":[
        {
            "category":"Home & Garden",
            "subcategory":"Hardware",
            "type":"Retail Goods"
        },
        {
            "category":"Home & Garden",
            "subcategory":"Building Materials",
            "type":"Retail Goods"
        }
    ],
    "sg:phone":"+44 1452 505555",
    "sg:postcode":"GL1 2BS",
    "sg:province":"Gloucestershire",
    "sg:tags":[
        "manufacture",
        "adhesive",
        "adhesives",
        "sealant",
        "distribution",
        "glue"
    ],
    "wof:name":"RAYMOND PONSFORD",
    "wof:placetype":"venue"
},
  "geometry": {"coordinates":[-2.2441289425,51.869682312],"type":"Point"}
}