{
  "type": "Feature",
  "properties": {
    "addr:full":"5 Gloucester Rd Ross On Wye Gloucestershire HR9 5BU",
    "addr:housenumber":"5",
    "addr:postcode":"hr9 5bu",
    "addr:street":"Gloucester Rd",
    "iso:country":"GB",
    "sg:address":"5 Gloucester Rd",
    "sg:city":"Ross On Wye",
    "sg:classifiers":[
        {
            "category":"Shopping",
            "subcategory":"Clothing, Apparel, & Fashions",
            "type":"Retail Goods"
        }
    ],
    "sg:phone":"+44 1989 562711",
    "sg:postcode":"HR9 5BU",
    "sg:province":"Gloucestershire",
    "sg:tags":[
        "menswear"
    ],
    "wof:name":"Dunn & Co",
    "wof:placetype":"venue"
},
  "geometry": {"coordinates":[-2.5832369328,51.9141082764],"type":"Point"}
}