{
  "type": "Feature",
  "properties": {
    "iso:country":"GB",
    "sg:address":"Enterprise House, Haddenham Business Park, Thame Road",
    "sg:city":"Aylesbury",
    "sg:classifiers":[
        {
            "category":"Professional",
            "type":"Services"
        }
    ],
    "sg:phone":"+44 1844 293000",
    "sg:postcode":"HP17 8LJ",
    "sg:province":"Buckinghamshire",
    "sg:tags":[
        "repair",
        "tech",
        "maintenance"
    ],
    "wof:name":"Information Technology Solutions (Maintenance) Ltd.",
    "wof:placetype":"venue"
},
  "geometry": {"coordinates":[-0.92491,51.755402],"type":"Point"}
}