{
  "type": "Feature",
  "properties": {
    "addr:full":"31 Brownlow Road Bolton Lancashire BL6 7DW",
    "addr:housenumber":"31",
    "addr:postcode":"bl6 7dw",
    "addr:street":"Brownlow Road",
    "iso:country":"GB",
    "sg:address":"31 Brownlow Road",
    "sg:city":"Bolton",
    "sg:classifiers":[
        {
            "category":"Professional",
            "subcategory":"Engineering",
            "type":"Services"
        }
    ],
    "sg:postcode":"BL6 7DW",
    "sg:province":"Lancashire",
    "sg:tags":[
        "gas",
        "engineer"
    ],
    "wof:name":"M & R Plumbing & Heating",
    "wof:placetype":"venue"
},
  "geometry": {"coordinates":[-2.5458130836,53.6010131836],"type":"Point"}
}