{
  "type": "Feature",
  "properties": {
    "addr:full":"111 Erdington Road, Aldridge Walsall Staffordshire WS9 0RT",
    "addr:housenumber":"111",
    "addr:postcode":"ws9 0rt",
    "addr:street":"Erdington Road",
    "iso:country":"GB",
    "sg:address":"111 Erdington Road, Aldridge",
    "sg:city":"Walsall",
    "sg:classifiers":[
        {
            "category":"Shopping",
            "subcategory":"Clothing, Apparel, & Fashions",
            "type":"Retail Goods"
        }
    ],
    "sg:phone":"+44 1922 453891",
    "sg:postcode":"WS9 0RT",
    "sg:province":"Staffordshire",
    "sg:tags":[
        "menswear"
    ],
    "wof:name":"Chelsea International",
    "wof:placetype":"venue"
},
  "geometry": {"coordinates":[-1.9134659767,52.5971450806],"type":"Point"}
}