{
  "type": "Feature",
  "properties": {
    "addr:full":"Needham Rd Stowmarket Suffolk IP14 2AD",
    "addr:postcode":"ip14 2ad",
    "addr:street":"Needham Rd",
    "iso:country":"GB",
    "sg:address":"Needham Rd",
    "sg:city":"Stowmarket",
    "sg:classifiers":[
        {
            "category":"Professional",
            "subcategory":"Art Services",
            "type":"Services"
        }
    ],
    "sg:phone":"+44 1449 613161",
    "sg:postcode":"IP14 2AD",
    "sg:province":"Suffolk",
    "sg:tags":[
        "decorating",
        "painting"
    ],
    "wof:name":"Ppg Industries Uk",
    "wof:placetype":"venue"
},
  "geometry": {"coordinates":[1.003082,52.179821],"type":"Point"}
}