{
  "type": "Feature",
  "properties": {
    "addr:full":"19 Repton Court, Repton Close Basildon Essex SS13 1LN",
    "addr:housenumber":"19",
    "addr:postcode":"ss13 1ln",
    "addr:street":"Repton Court Repton Close",
    "iso:country":"GB",
    "sg:address":"19 Repton Court, Repton Close",
    "sg:city":"Basildon",
    "sg:classifiers":[
        {
            "category":"Home & Garden",
            "subcategory":"Building Materials",
            "type":"Retail Goods"
        }
    ],
    "sg:phone":"+44 1268 293030",
    "sg:postcode":"SS13 1LN",
    "sg:province":"Essex",
    "sg:tags":[
        "ventilator",
        "ventilation",
        "system"
    ],
    "wof:name":"S K (Sales) Ltd.",
    "wof:placetype":"venue"
},
  "geometry": {"coordinates":[0.50187,51.584339],"type":"Point"}
}