{
  "type": "Feature",
  "properties": {
    "iso:country":"GB",
    "sg:address":"Hampton Avenue",
    "sg:city":"Torquay",
    "sg:classifiers":[
        {
            "category":"Landmark",
            "subcategory":"Tourist Attraction",
            "type":"Public Place"
        }
    ],
    "sg:phone":"+44 1803 315315",
    "sg:postcode":"TQ1 3LA",
    "sg:province":"Devon",
    "sg:tags":[
        "interest"
    ],
    "wof:name":"Merrivale (Torquay) Ltd.",
    "wof:placetype":"venue"
},
  "geometry": {"coordinates":[-3.519719,50.48267],"type":"Point"}
}