{
  "type": "Feature",
  "properties": {
    "iso:country":"GB",
    "sg:address":"1 New Market Walk, Tydfil Square Centre",
    "sg:city":"Merthyr Tydfil",
    "sg:classifiers":[
        {
            "category":"Food & Beverages",
            "subcategory":"Supermarket",
            "type":"Retail Goods"
        }
    ],
    "sg:phone":"+44 845 677 9460",
    "sg:postcode":"CF47 8EL",
    "sg:province":"Merthyr Tydfil",
    "wof:name":"Tesco Stores Ltd.",
    "wof:placetype":"venue"
},
  "geometry": {"coordinates":[-3.376464,51.750439],"type":"Point"}
}