{
  "type": "Feature",
  "properties": {
    "addr:full":"Bridge House, Clyst St Mary Exeter Devon EX5 1BR",
    "addr:housenumber":"bridge",
    "addr:postcode":"ex5 1br",
    "addr:street":"Clyst St Mary",
    "iso:country":"GB",
    "sg:address":"Bridge House, Clyst St Mary",
    "sg:city":"Exeter",
    "sg:classifiers":[
        {
            "category":"Building & Trades",
            "subcategory":"Construction",
            "type":"Services"
        }
    ],
    "sg:phone":"+44 1392 875755",
    "sg:postcode":"EX5 1BR",
    "sg:province":"Devon",
    "sg:tags":[
        "dry",
        "plastering",
        "plasterers",
        "lining",
        "related",
        "screeders"
    ],
    "wof:name":"Andrews Bros Plastering Ltd",
    "wof:placetype":"venue"
},
  "geometry": {"coordinates":[-3.4482440948,50.7080192566],"type":"Point"}
}