{
  "type": "Feature",
  "properties": {
    "addr:full":"Bescot Stadium, Bescot Crescent Walsall West Midlands WS1 4SA",
    "addr:postcode":"ws1 4sa",
    "addr:street":"Bescot Crescent",
    "iso:country":"GB",
    "sg:address":"Bescot Stadium, Bescot Crescent",
    "sg:city":"Walsall",
    "sg:classifiers":[
        {
            "category":"Sports & Exercise",
            "subcategory":"Sports Center",
            "type":"Entertainment"
        }
    ],
    "sg:phone":"+44 1922 643331",
    "sg:postcode":"WS1 4SA",
    "sg:province":"West Midlands",
    "sg:tags":[
        "shop",
        "good"
    ],
    "wof:name":"Walsall Club Shop",
    "wof:placetype":"venue"
},
  "geometry": {"coordinates":[-1.976104,52.585289],"type":"Point"}
}