{
  "type": "Feature",
  "properties": {
    "addr:full":"Hind Court, 147 Fleet Street London Greater London EC4A 2BU",
    "addr:housenumber":"147",
    "addr:postcode":"ec4a 2bu",
    "addr:street":"Hind;Fleet Street",
    "iso:country":"GB",
    "sg:address":"Hind Court, 147 Fleet Street",
    "sg:city":"London",
    "sg:classifiers":[
        {
            "category":"Professional",
            "subcategory":"Lawyer & Legal Services",
            "type":"Services"
        }
    ],
    "sg:postcode":"EC4A 2BU",
    "sg:province":"Greater London",
    "sg:tags":[
        "solicitor"
    ],
    "wof:name":"Thomas Woodforde Solicitors",
    "wof:placetype":"venue"
},
  "geometry": {"coordinates":[-0.107427001,51.5142250061],"type":"Point"}
}