{
  "type": "Feature",
  "properties": {
    "addr:full":"Pintail, Main Road, Friday Bridge Wisbech Cambridgeshire PE14 0HL",
    "addr:postcode":"pe14 0hl",
    "addr:street":"Pintail Main Road Friday Bridge",
    "iso:country":"GB",
    "sg:address":"Pintail, Main Road, Friday Bridge",
    "sg:city":"Wisbech",
    "sg:classifiers":[
        {
            "category":"Retail",
            "subcategory":"Storage",
            "type":"Services"
        }
    ],
    "sg:postcode":"PE14 0HL",
    "sg:province":"Cambridgeshire",
    "sg:tags":[
        "household",
        "removal"
    ],
    "wof:name":"R & J Wardle Removals",
    "wof:placetype":"venue"
},
  "geometry": {"coordinates":[0.1640899926,52.6210594177],"type":"Point"}
}