{
  "type": "Feature",
  "properties": {
    "addr:full":"Beazer House, Kirk Sandall Industrial Estate Doncaster South Yorkshire DN3 1QP",
    "addr:housenumber":"estate",
    "addr:postcode":"dn3 1qp",
    "addr:street":"Kirk Sandall Industrial",
    "iso:country":"GB",
    "sg:address":"Beazer House, Kirk Sandall Industrial Estate",
    "sg:city":"Doncaster",
    "sg:classifiers":[
        {
            "category":"Building & Trades",
            "subcategory":"Construction",
            "type":"Services"
        }
    ],
    "sg:phone":"+44 1225 428401",
    "sg:postcode":"DN3 1QP",
    "sg:province":"South Yorkshire",
    "sg:tags":[
        "builder"
    ],
    "wof:name":"Beazer Homes (yorkshire) Ltd",
    "wof:placetype":"venue"
},
  "geometry": {"coordinates":[-1.0765000582,53.557800293],"type":"Point"}
}