{
  "type": "Feature",
  "properties": {
    "iso:country":"GB",
    "sg:address":"8 Conegra Road",
    "sg:city":"High Wycombe",
    "sg:classifiers":[
        {
            "category":"Professional",
            "subcategory":"Management & Consulting",
            "type":"Services"
        },
        {
            "category":"Professional",
            "subcategory":"Business Services",
            "type":"Services"
        }
    ],
    "sg:postcode":"HP13 6DY",
    "sg:province":"Buckinghamshire",
    "sg:tags":[
        "consultant",
        "planning",
        "supervisor"
    ],
    "wof:name":"Crowthers",
    "wof:placetype":"venue"
},
  "geometry": {"coordinates":[-0.7431110144,51.6305274963],"type":"Point"}
}