{
  "type": "Feature",
  "properties": {
    "iso:country":"GB",
    "sg:address":"34 St Thomas Road",
    "sg:city":"Brentwood",
    "sg:classifiers":[
        {
            "category":"Health Services",
            "subcategory":"Dentist",
            "type":"Services"
        }
    ],
    "sg:phone":"+44 1277 210691",
    "sg:postcode":"CM14 4DF",
    "sg:province":"Essex",
    "wof:name":"James Tobin",
    "wof:placetype":"venue"
},
  "geometry": {"coordinates":[0.305369,51.619686],"type":"Point"}
}