{
  "type": "Feature",
  "properties": {
    "addr:full":"39 High Street Hounslow Greater London TW3 1RH",
    "addr:housenumber":"39",
    "addr:postcode":"tw3 1rh",
    "addr:street":"High Street",
    "iso:country":"GB",
    "sg:address":"39 High Street",
    "sg:city":"Hounslow",
    "sg:classifiers":[
        {
            "category":"Shopping",
            "subcategory":"Pharmacy",
            "type":"Retail Goods"
        }
    ],
    "sg:phone":"+44 20 8570 7254",
    "sg:postcode":"TW3 1RH",
    "sg:province":"Greater London",
    "sg:tags":[
        "pharmacist",
        "dispensing",
        "chemist"
    ],
    "wof:name":"Crystal Pharmacy",
    "wof:placetype":"venue"
},
  "geometry": {"coordinates":[-0.3545329869,51.470451355],"type":"Point"}
}