{
  "type": "Feature",
  "properties": {
    "iso:country":"GB",
    "sg:address":"70b Reddal Hill Rd",
    "sg:city":"Cradley Heath",
    "sg:classifiers":[
        {
            "category":"Retail",
            "subcategory":"Repair Shop",
            "type":"Services"
        }
    ],
    "sg:postcode":"B64 5JT",
    "sg:province":"West Midlands",
    "sg:tags":[
        "upholsterer"
    ],
    "wof:name":"Select Upholstery",
    "wof:placetype":"venue"
},
  "geometry": {"coordinates":[-2.075602,52.475117],"type":"Point"}
}