{
  "type": "Feature",
  "properties": {
    "addr:full":"High Street, Henham Bishops Stortford Essex CM22 6AS",
    "addr:postcode":"cm22 6as",
    "addr:street":"High Street;Stortford",
    "iso:country":"GB",
    "sg:address":"High Street, Henham",
    "sg:city":"Bishops Stortford",
    "sg:classifiers":[
        {
            "category":"Shopping",
            "subcategory":"Department Store",
            "type":"Retail Goods"
        },
        {
            "category":"Government",
            "subcategory":"Post Office",
            "type":"Public Place"
        }
    ],
    "sg:phone":"+44 1279 850044",
    "sg:postcode":"CM22 6AS",
    "sg:province":"Essex",
    "wof:name":"HENHAM STORES",
    "wof:placetype":"venue"
},
  "geometry": {"coordinates":[0.2292200029,51.914226532],"type":"Point"}
}