{
  "type": "Feature",
  "properties": {
    "iso:country":"GB",
    "sg:address":", Thorington",
    "sg:city":"Saxmundham",
    "sg:classifiers":[
        {
            "category":"Restaurant",
            "type":"Food & Drink"
        }
    ],
    "sg:phone":"+44 1502 478220",
    "sg:postcode":"IP17 3RE",
    "sg:province":"Suffolk",
    "wof:name":"The Round House Restaurant",
    "wof:placetype":"venue"
},
  "geometry": {"coordinates":[1.56914,52.269508],"type":"Point"}
}