{
  "type": "Feature",
  "properties": {
    "iso:country":"GB",
    "sg:address":"Unit 2a, Cottingham Way, Thrapston",
    "sg:city":"Kettering",
    "sg:classifiers":[
        {
            "category":"Building & Trades",
            "subcategory":"Construction",
            "type":"Services"
        }
    ],
    "sg:phone":"+44 1832 734570",
    "sg:postcode":"NN14 4PL",
    "sg:province":"Northamptonshire",
    "sg:tags":[
        "glazier"
    ],
    "wof:name":"Thrapston Glazing",
    "wof:placetype":"venue"
},
  "geometry": {"coordinates":[-0.539789021,52.3974647522],"type":"Point"}
}