{
  "type": "Feature",
  "properties": {
    "addr:full":"340 Central Markets Clerkenwell Greater London EC1A 9NB",
    "addr:housenumber":"340",
    "addr:postcode":"ec1a 9nb",
    "addr:street":"Central Markets",
    "iso:country":"GB",
    "sg:address":"340 Central Markets",
    "sg:city":"Clerkenwell",
    "sg:classifiers":[
        {
            "category":"Bars & Pubs",
            "type":"Food & Drink"
        }
    ],
    "sg:phone":"+44 20 7248 5311",
    "sg:postcode":"EC1A 9NB",
    "sg:province":"Greater London",
    "sg:tags":[
        "pubs",
        "inn"
    ],
    "wof:name":"Smithfield Freehouse",
    "wof:placetype":"venue"
},
  "geometry": {"coordinates":[-0.10442,51.518299],"type":"Point"}
}