{
  "type": "Feature",
  "properties": {
    "addr:full":"Erw Las, Salem Road, St Clears Carmarthen Carmarthenshire SA33 4DH",
    "addr:postcode":"sa33 4dh",
    "addr:street":"Las Salem Road St Clears",
    "iso:country":"GB",
    "sg:address":"Erw Las, Salem Road, St Clears",
    "sg:city":"Carmarthen",
    "sg:classifiers":[
        {
            "category":"Building & Trades",
            "subcategory":"Construction",
            "type":"Services"
        }
    ],
    "sg:phone":"+44 1994 230596",
    "sg:postcode":"SA33 4DH",
    "sg:province":"Carmarthenshire",
    "sg:tags":[
        "builder"
    ],
    "wof:name":"D Lloyd Davies",
    "wof:placetype":"venue"
},
  "geometry": {"coordinates":[-4.495470047,51.8350906372],"type":"Point"}
}