{
  "type": "Feature",
  "properties": {
    "addr:full":"71 Hersham Close, Putney Putney Greater London SW15 4JQ",
    "addr:housenumber":"71",
    "addr:postcode":"sw15 4jq",
    "addr:street":"Hersham Close",
    "iso:country":"GB",
    "sg:address":"71 Hersham Close, Putney",
    "sg:city":"Putney",
    "sg:classifiers":[
        {
            "category":"Building & Trades",
            "subcategory":"Construction",
            "type":"Services"
        }
    ],
    "sg:phone":"+44 20 8785 9656",
    "sg:postcode":"SW15 4JQ",
    "sg:province":"Greater London",
    "sg:tags":[
        "decorator",
        "painter"
    ],
    "wof:name":"D.L Hanlon Building & Decorating Contractors",
    "wof:placetype":"venue"
},
  "geometry": {"coordinates":[-0.24019,51.448433],"type":"Point"}
}