{
  "type": "Feature",
  "properties": {
    "iso:country":"GB",
    "sg:address":"100 Field Way",
    "sg:city":"Dagenham",
    "sg:classifiers":[
        {
            "category":"Retail",
            "subcategory":"Auto Repair",
            "type":"Services"
        }
    ],
    "sg:phone":"+44 20 8598 9430",
    "sg:postcode":"RM8 2BB",
    "sg:province":"Essex",
    "sg:tags":[
        "modification",
        "garage"
    ],
    "wof:name":"R T Auto Electrical",
    "wof:placetype":"venue"
},
  "geometry": {"coordinates":[0.12039,51.55442],"type":"Point"}
}