{
  "type": "Feature",
  "properties": {
    "addr:full":"10 Glovers Lane, Middleton Cheney Banbury Northamptonshire OX17 2NU",
    "addr:housenumber":"10",
    "addr:postcode":"ox17 2nu",
    "addr:street":"Glovers Lane",
    "iso:country":"GB",
    "sg:address":"10 Glovers Lane, Middleton Cheney",
    "sg:city":"Banbury",
    "sg:classifiers":[
        {
            "category":"Building & Trades",
            "subcategory":"Construction",
            "type":"Services"
        }
    ],
    "sg:postcode":"OX17 2NU",
    "sg:province":"Northamptonshire",
    "sg:tags":[
        "conservation",
        "craft",
        "thatching"
    ],
    "wof:name":"John Henry Pinfold",
    "wof:placetype":"venue"
},
  "geometry": {"coordinates":[-1.2732850313,52.0758247375],"type":"Point"}
}