{
  "type": "Feature",
  "properties": {
    "addr:full":"9b King Street Penrith Cumbria CA11 7AJ",
    "addr:housenumber":"9b",
    "addr:postcode":"ca11 7aj",
    "addr:street":"King Street",
    "iso:country":"GB",
    "sg:address":"9b King Street",
    "sg:city":"Penrith",
    "sg:classifiers":[
        {
            "category":"Real Estate",
            "subcategory":"Real Estate Agent",
            "type":"Services"
        }
    ],
    "sg:phone":"+44 1768 866992",
    "sg:postcode":"CA11 7AJ",
    "sg:province":"Cumbria",
    "wof:name":"Reeds Rains",
    "wof:placetype":"venue"
},
  "geometry": {"coordinates":[-2.7510919571,54.6635818481],"type":"Point"}
}