{
  "type": "Feature",
  "properties": {
    "addr:full":"3 Parsonage Lane, Winford Bristol Somerset BS40 8DG",
    "addr:housenumber":"3",
    "addr:postcode":"bs40 8dg",
    "addr:street":"Parsonage Lane",
    "iso:country":"GB",
    "sg:address":"3 Parsonage Lane, Winford",
    "sg:city":"Bristol",
    "sg:classifiers":[
        {
            "category":"Professional",
            "subcategory":"Accounting & Tax Preparation",
            "type":"Services"
        }
    ],
    "sg:phone":"+44 1275 472046",
    "sg:postcode":"BS40 8DG",
    "sg:province":"Somerset",
    "sg:tags":[
        "accountant"
    ],
    "wof:name":"Brian L O'Connor & Co. Accountant & Tax Practitioner",
    "wof:placetype":"venue"
},
  "geometry": {"coordinates":[-2.6630001068,51.382724762],"type":"Point"}
}