{
  "type": "Feature",
  "properties": {
    "addr:full":"Milthorp Business Centre, Monckton Rd Wakefield West Yorkshire WF2 7AS",
    "addr:postcode":"wf2 7as",
    "addr:street":"Monckton Rd",
    "iso:country":"GB",
    "sg:address":"Milthorp Business Centre, Monckton Rd",
    "sg:city":"Wakefield",
    "sg:classifiers":[
        {
            "category":"Social Services",
            "subcategory":"Job Training",
            "type":"Services"
        }
    ],
    "sg:phone":"+44 1924 888140",
    "sg:postcode":"WF2 7AS",
    "sg:province":"West Yorkshire",
    "sg:tags":[
        "translator",
        "interpreter"
    ],
    "wof:name":"Pro Translation UK Ltd",
    "wof:placetype":"venue"
},
  "geometry": {"coordinates":[-1.5102740526,53.6799697876],"type":"Point"}
}