{
  "type": "Feature",
  "properties": {
    "addr:full":"34 Main Street, Wentworth Rotherham South Yorkshire S62 7TN",
    "addr:housenumber":"34",
    "addr:postcode":"s62 7tn",
    "addr:street":"Main Street",
    "iso:country":"GB",
    "sg:address":"34 Main Street, Wentworth",
    "sg:city":"Rotherham",
    "sg:classifiers":[
        {
            "category":"Food & Beverages",
            "subcategory":"Meat & Fish",
            "type":"Retail Goods"
        }
    ],
    "sg:phone":"+44 1709 370536",
    "sg:postcode":"S62 7TN",
    "sg:province":"South Yorkshire",
    "sg:tags":[
        "butcher"
    ],
    "wof:name":"J T Hill & Son",
    "wof:placetype":"venue"
},
  "geometry": {"coordinates":[-1.4195350409,53.4793586731],"type":"Point"}
}