{
  "type": "Feature",
  "properties": {
    "addr:full":"Crichton Ho Pathhead East Lothian EH37 5UX",
    "addr:postcode":"eh37 5ux",
    "addr:street":"Crichton",
    "iso:country":"GB",
    "sg:address":"Crichton Ho",
    "sg:city":"Pathhead",
    "sg:classifiers":[
        {
            "category":"Shopping",
            "subcategory":"Clothing, Apparel, & Fashions",
            "type":"Retail Goods"
        }
    ],
    "sg:postcode":"EH37 5UX",
    "sg:province":"East Lothian",
    "sg:tags":[
        "clothing",
        "fabric"
    ],
    "wof:name":"Calpin,C,",
    "wof:placetype":"venue"
},
  "geometry": {"coordinates":[-2.97027,55.868595],"type":"Point"}
}