{
  "type": "Feature",
  "properties": {
    "addr:full":"St. Mary's Square Swansea Neath Port Talbot SA1 3LP",
    "addr:postcode":"sa1 3lp",
    "addr:street":"Square",
    "iso:country":"GB",
    "sg:address":"St. Mary's Square",
    "sg:city":"Swansea",
    "sg:classifiers":[
        {
            "category":"Place Of Worship",
            "type":"Public Place"
        }
    ],
    "sg:phone":"+44 1792 298616",
    "sg:postcode":"SA1 3LP",
    "sg:province":"Neath Port Talbot",
    "wof:name":"St. Mary's Church",
    "wof:placetype":"venue"
},
  "geometry": {"coordinates":[-3.9423799515,51.6187095642],"type":"Point"}
}