{
  "type": "Feature",
  "properties": {
    "iso:country":"GB",
    "sg:address":"Phoenix House, Kingmoor Ind Est",
    "sg:city":"Carlisle",
    "sg:classifiers":[
        {
            "category":"Professional",
            "subcategory":"Management & Consulting",
            "type":"Services"
        }
    ],
    "sg:phone":"+44 1228 514267",
    "sg:postcode":"CA3 9QJ",
    "sg:province":"Cumbria",
    "sg:tags":[
        "consultant",
        "business"
    ],
    "wof:name":"Quantec Kingfisher Consultants",
    "wof:placetype":"venue"
},
  "geometry": {"coordinates":[-2.9643220901,54.9163703918],"type":"Point"}
}