{
  "type": "Feature",
  "properties": {
    "addr:full":"12 High Street, Bovingdon Hemel Hempstead Hertfordshire HP3 0HG",
    "addr:housenumber":"12",
    "addr:postcode":"hp3 0hg",
    "addr:street":"High Street;Hempstead",
    "iso:country":"GB",
    "sg:address":"12 High Street, Bovingdon",
    "sg:city":"Hemel Hempstead",
    "sg:classifiers":[
        {
            "category":"Manufacturing",
            "subcategory":"Signs",
            "type":"Manufacturing & Wholesale Goods"
        }
    ],
    "sg:postcode":"HP3 0HG",
    "sg:province":"Hertfordshire",
    "sg:tags":[
        "marquee"
    ],
    "wof:name":"Croft Interior",
    "wof:placetype":"venue"
},
  "geometry": {"coordinates":[-0.5346059799,51.7242546082],"type":"Point"}
}