{
  "type": "Feature",
  "properties": {
    "iso:country":"GB",
    "sg:address":"100 Nursery Rd",
    "sg:city":"Pinner",
    "sg:classifiers":[
        {
            "category":"Communications",
            "type":"Services"
        }
    ],
    "sg:phone":"+44 20 8868 1729",
    "sg:postcode":"HA5 2AS",
    "sg:province":"Greater London",
    "sg:tags":[
        "audio-visual"
    ],
    "wof:name":"ARC Television Productions",
    "wof:placetype":"venue"
},
  "geometry": {"coordinates":[-0.396076,51.595654],"type":"Point"}
}