{
  "type": "Feature",
  "properties": {
    "iso:country":"GB",
    "sg:address":"Church Rd",
    "sg:city":"Port Talbot",
    "sg:classifiers":[
        {
            "category":"Place Of Worship",
            "type":"Public Place"
        }
    ],
    "sg:phone":"+44 1639 812199",
    "sg:postcode":"SA12 8ST",
    "sg:province":"Neath Port Talbot",
    "wof:name":"St Catharines Church In Wales",
    "wof:placetype":"venue"
},
  "geometry": {"coordinates":[-3.8074638844,51.6184082031],"type":"Point"}
}