{
  "type": "Feature",
  "properties": {
    "addr:full":"Rooksgrove Farm, Warnford Southampton Hampshire SO32 3LJ",
    "addr:postcode":"so32 3lj",
    "iso:country":"GB",
    "sg:address":"Rooksgrove Farm, Warnford",
    "sg:city":"Southampton",
    "sg:classifiers":[
        {
            "category":"Building & Trades",
            "subcategory":"Construction",
            "type":"Services"
        }
    ],
    "sg:postcode":"SO32 3LJ",
    "sg:province":"Hampshire",
    "sg:tags":[
        "welder"
    ],
    "wof:name":"C & W Engineering",
    "wof:placetype":"venue"
},
  "geometry": {"coordinates":[-1.115908,51.003586],"type":"Point"}
}