{
  "type": "Feature",
  "properties": {
    "addr:full":"47 High Street Steyning West Sussex BN44 3RE",
    "addr:housenumber":"47",
    "addr:postcode":"bn44 3re",
    "addr:street":"High Street",
    "iso:country":"GB",
    "sg:address":"47 High Street",
    "sg:city":"Steyning",
    "sg:classifiers":[
        {
            "category":"Personal",
            "subcategory":"Beauty Salon",
            "type":"Services"
        }
    ],
    "sg:postcode":"BN44 3RE",
    "sg:province":"West Sussex",
    "sg:tags":[
        "unisex",
        "hairdresser"
    ],
    "wof:name":"Cameo Hairdressers",
    "wof:placetype":"venue"
},
  "geometry": {"coordinates":[-0.3296900094,50.8885231018],"type":"Point"}
}