{
  "type": "Feature",
  "properties": {
    "iso:country":"GB",
    "sg:address":"The Park Foundry",
    "sg:city":"Belper",
    "sg:classifiers":[
        {
            "category":"Manufacturing",
            "subcategory":"Metals",
            "type":"Manufacturing & Wholesale Goods"
        }
    ],
    "sg:postcode":"DE56 1JJ",
    "sg:province":"Derbyshire",
    "sg:tags":[
        "fabricator",
        "aluminium"
    ],
    "wof:name":"Hepworth Extrusions Ltd.",
    "wof:placetype":"venue"
},
  "geometry": {"coordinates":[-1.4759819508,53.0286102295],"type":"Point"}
}