{
  "type": "Feature",
  "properties": {
    "iso:country":"GB",
    "sg:address":"Tara, Spenwood Close",
    "sg:city":"Reading",
    "sg:classifiers":[
        {
            "category":"Recreation",
            "type":"Entertainment"
        }
    ],
    "sg:postcode":"RG7 1DE",
    "sg:province":"Berkshire",
    "sg:tags":[
        "snooker",
        "billiards",
        "pool"
    ],
    "wof:name":"Pot Black 8 Ball",
    "wof:placetype":"venue"
},
  "geometry": {"coordinates":[-0.972014,51.394135],"type":"Point"}
}