{
  "type": "Feature",
  "properties": {
    "iso:country":"GB",
    "sg:address":"17 St Martins Close, Broadmayne",
    "sg:city":"Dorchester",
    "sg:classifiers":[
        {
            "category":"Home & Garden",
            "subcategory":"Building Materials",
            "type":"Retail Goods"
        }
    ],
    "sg:postcode":"DT2 8DG",
    "sg:province":"Dorset",
    "sg:tags":[
        "fencing"
    ],
    "wof:name":"Steve Brown Hurdle Maker",
    "wof:placetype":"venue"
},
  "geometry": {"coordinates":[-2.385514,50.677811],"type":"Point"}
}