{
  "type": "Feature",
  "properties": {
    "iso:country":"GB",
    "sg:address":"California Drive",
    "sg:city":"Castleford",
    "sg:classifiers":[
        {
            "category":"Cafe",
            "type":"Food & Drink"
        }
    ],
    "sg:phone":"+44 1977 517690",
    "sg:postcode":"WF10 5QH",
    "sg:province":"West Yorkshire",
    "sg:tags":[
        "tea",
        "room"
    ],
    "wof:name":"Whitwood Truck Stop Ltd.",
    "wof:placetype":"venue"
},
  "geometry": {"coordinates":[-1.399124,53.712784],"type":"Point"}
}