{
  "type": "Feature",
  "properties": {
    "addr:full":"6 New St, Slaidhwaide Huddersfield West Yorkshire HD7 5AB",
    "addr:housenumber":"6",
    "addr:postcode":"hd7 5ab",
    "addr:street":"New St Slaidhwaide",
    "iso:country":"GB",
    "sg:address":"6 New St, Slaidhwaide",
    "sg:city":"Huddersfield",
    "sg:classifiers":[
        {
            "category":"Shopping",
            "type":"Retail Goods"
        }
    ],
    "sg:phone":"+44 1484 420283",
    "sg:postcode":"HD7 5AB",
    "sg:province":"West Yorkshire",
    "sg:tags":[
        "merchant"
    ],
    "wof:name":"Carters Ltd",
    "wof:placetype":"venue"
},
  "geometry": {"coordinates":[-1.8784979582,53.6238746643],"type":"Point"}
}