{
  "type": "Feature",
  "properties": {
    "iso:country":"GB",
    "sg:address":"Town Ho, Millrow",
    "sg:city":"Dunblane",
    "sg:classifiers":[
        {
            "category":"Professional",
            "subcategory":"Management & Consulting",
            "type":"Services"
        }
    ],
    "sg:phone":"+44 1786 823647",
    "sg:postcode":"FK15 0EL",
    "sg:province":"Perth and Kinross",
    "sg:tags":[
        "marketing",
        "consultant"
    ],
    "wof:name":"Philip Gregory Associates Ltd",
    "wof:placetype":"venue"
},
  "geometry": {"coordinates":[-3.952979,56.19886],"type":"Point"}
}