{
  "type": "Feature",
  "properties": {
    "addr:full":"Little Haven, The Village, Ashleworth Gloucester Gloucestershire GL19 4JG",
    "addr:postcode":"gl19 4jg",
    "iso:country":"GB",
    "sg:address":"Little Haven, The Village, Ashleworth",
    "sg:city":"Gloucester",
    "sg:classifiers":[
        {
            "category":"Retail",
            "subcategory":"Repair Shop",
            "type":"Services"
        }
    ],
    "sg:phone":"+44 1452 700265",
    "sg:postcode":"GL19 4JG",
    "sg:province":"Gloucestershire",
    "sg:tags":[
        "maintenance"
    ],
    "wof:name":"William Ennis",
    "wof:placetype":"venue"
},
  "geometry": {"coordinates":[-2.274441,51.929852],"type":"Point"}
}