{
  "type": "Feature",
  "properties": {
    "addr:full":"42 St. Bernards Rd Solihull West Midlands B92 7BB",
    "addr:housenumber":"42",
    "addr:postcode":"b92 7bb",
    "addr:street":"St. Bernards Rd",
    "iso:country":"GB",
    "sg:address":"42 St. Bernards Rd",
    "sg:city":"Solihull",
    "sg:classifiers":[
        {
            "category":"Health Services",
            "subcategory":"Nursing And Care Facility",
            "type":"Services"
        }
    ],
    "sg:phone":"+44 121 707 6760",
    "sg:postcode":"B92 7BB",
    "sg:province":"West Midlands",
    "sg:tags":[
        "home"
    ],
    "wof:name":"Mereside Home For People With A Severe Learning Di",
    "wof:placetype":"venue"
},
  "geometry": {"coordinates":[-1.807149,52.435459],"type":"Point"}
}