{
  "type": "Feature",
  "properties": {
    "addr:full":"Warden Only, Admiral Ct, Blake Clo Carshalton Surrey SM5 1LJ",
    "addr:postcode":"sm5 1lj",
    "addr:street":"Admiral Ct Blake Clo",
    "iso:country":"GB",
    "sg:address":"Warden Only, Admiral Ct, Blake Clo",
    "sg:city":"Carshalton",
    "sg:classifiers":[
        {
            "category":"Social Services",
            "subcategory":"Retirement Home",
            "type":"Services"
        },
        {
            "category":"Organizations",
            "subcategory":"Community Association",
            "type":"Services"
        }
    ],
    "sg:phone":"+44 20 8687 1171",
    "sg:postcode":"SM5 1LJ",
    "sg:province":"Surrey",
    "sg:tags":[
        "society",
        "housing",
        "sheltered",
        "accommodation"
    ],
    "sg:website":"http://www.anchor.org.uk",
    "wof:name":"Anchor Trust",
    "wof:placetype":"venue"
},
  "geometry": {"coordinates":[-0.161094,51.365288],"type":"Point"}
}