{
  "type": "Feature",
  "properties": {
    "iso:country":"GB",
    "sg:address":"11 Church Rd",
    "sg:city":"Wolverhampton",
    "sg:classifiers":[
        {
            "category":"Parking",
            "type":"Transportation"
        }
    ],
    "sg:phone":"+44 1902 336127",
    "sg:postcode":"WV3 7ET",
    "sg:province":"Staffordshire",
    "sg:tags":[
        "car",
        "valet"
    ],
    "wof:name":"Motor Proud Mobile Valeting",
    "wof:placetype":"venue"
},
  "geometry": {"coordinates":[-2.157181,52.574673],"type":"Point"}
}