{
  "type": "Feature",
  "properties": {
    "addr:full":"Brae Smithy Garage, Cushinie Alford Aberdeenshire AB33 8LH",
    "addr:postcode":"ab33 8lh",
    "iso:country":"GB",
    "sg:address":"Brae Smithy Garage, Cushinie",
    "sg:city":"Alford",
    "sg:classifiers":[
        {
            "category":"Retail",
            "subcategory":"Auto Repair",
            "type":"Services"
        }
    ],
    "sg:phone":"+44 1975 581252",
    "sg:postcode":"AB33 8LH",
    "sg:province":"Aberdeenshire",
    "sg:tags":[
        "modification",
        "garage",
        "related"
    ],
    "wof:name":"John C Robertson",
    "wof:placetype":"venue"
},
  "geometry": {"coordinates":[-2.7054889202,57.2341384888],"type":"Point"}
}