{
  "type": "Feature",
  "properties": {
    "addr:full":"63 High Street, Wolstanton Newcastle Staffordshire ST5 0ES",
    "addr:housenumber":"63",
    "addr:postcode":"st5 0es",
    "addr:street":"High Street",
    "iso:country":"GB",
    "sg:address":"63 High Street, Wolstanton",
    "sg:city":"Newcastle",
    "sg:classifiers":[
        {
            "category":"Manufacturing",
            "subcategory":"Petroleum Products",
            "type":"Manufacturing & Wholesale Goods"
        }
    ],
    "sg:postcode":"ST5 0ES",
    "sg:province":"Staffordshire",
    "sg:tags":[
        "double",
        "glazing"
    ],
    "wof:name":"Summit Windows",
    "wof:placetype":"venue"
},
  "geometry": {"coordinates":[-2.2196030617,53.0331611633],"type":"Point"}
}