{
  "type": "Feature",
  "properties": {
    "iso:country":"GB",
    "sg:address":"Barnes Hotel, Durham Rd",
    "sg:city":"Sunderland",
    "sg:classifiers":[
        {
            "category":"Restaurant",
            "type":"Food & Drink"
        }
    ],
    "sg:phone":"+44 191 528 5644",
    "sg:postcode":"SR2 7RB",
    "sg:province":"Tyne and Wear",
    "wof:name":"Toby Restaurants",
    "wof:placetype":"venue"
},
  "geometry": {"coordinates":[-1.40087,54.893372],"type":"Point"}
}