{
  "type": "Feature",
  "properties": {
    "addr:full":"Coombe Farm, Oaks Road Croydon Surrey CR0 5HL",
    "addr:postcode":"cr0 5hl",
    "addr:street":"Oaks Road",
    "iso:country":"GB",
    "sg:address":"Coombe Farm, Oaks Road",
    "sg:city":"Croydon",
    "sg:classifiers":[
        {
            "category":"Government",
            "subcategory":"City Hall",
            "type":"Public Place"
        }
    ],
    "sg:postcode":"CR0 5HL",
    "sg:province":"Surrey",
    "wof:name":"Coombe Farm Hall",
    "wof:placetype":"venue"
},
  "geometry": {"coordinates":[-0.0593499988,51.3655204773],"type":"Point"}
}