{
  "type": "Feature",
  "properties": {
    "addr:full":"Swiss Cottage, 28 Willows Road Walsall West Midlands WS1 2DR",
    "addr:housenumber":"28",
    "addr:postcode":"ws1 2dr",
    "addr:street":"Willows Road",
    "iso:country":"GB",
    "sg:address":"Swiss Cottage, 28 Willows Road",
    "sg:city":"Walsall",
    "sg:classifiers":[
        {
            "category":"Building & Trades",
            "subcategory":"Construction",
            "type":"Services"
        }
    ],
    "sg:phone":"+44 1922 721380",
    "sg:postcode":"WS1 2DR",
    "sg:province":"West Midlands",
    "sg:tags":[
        "roofing"
    ],
    "wof:name":"Classic Roofing Ltd.",
    "wof:placetype":"venue"
},
  "geometry": {"coordinates":[-1.9761040211,52.5852890015],"type":"Point"}
}