{
  "type": "Feature",
  "properties": {
    "addr:full":"9 Walton Pl, Weston Turville Aylesbury Buckinghamshire HP22 5RB",
    "addr:housenumber":"9;turville",
    "addr:postcode":"hp22 5rb",
    "addr:street":"Walton Pl",
    "iso:country":"GB",
    "sg:address":"9 Walton Pl, Weston Turville",
    "sg:city":"Aylesbury",
    "sg:classifiers":[
        {
            "category":"Building & Trades",
            "subcategory":"Landscaping Services",
            "type":"Services"
        }
    ],
    "sg:postcode":"HP22 5RB",
    "sg:province":"Buckinghamshire",
    "sg:tags":[
        "gardening"
    ],
    "wof:name":"Arnott,Andrew J,",
    "wof:placetype":"venue"
},
  "geometry": {"coordinates":[-0.759953,51.792168],"type":"Point"}
}