{
  "type": "Feature",
  "properties": {
    "addr:full":"67 New Cheltenham Road, Kingswood Bristol City of Bristol BS15 1UL",
    "addr:housenumber":"67",
    "addr:postcode":"bs15 1ul",
    "addr:street":"New Cheltenham Road",
    "iso:country":"GB",
    "sg:address":"67 New Cheltenham Road, Kingswood",
    "sg:city":"Bristol",
    "sg:classifiers":[
        {
            "category":"Building & Trades",
            "subcategory":"Construction",
            "type":"Services"
        }
    ],
    "sg:phone":"+44 117 961 6791",
    "sg:postcode":"BS15 1UL",
    "sg:province":"City of Bristol",
    "sg:tags":[
        "decorator",
        "painter"
    ],
    "wof:name":"Clive Houlden",
    "wof:placetype":"venue"
},
  "geometry": {"coordinates":[-2.5042469501,51.4676704407],"type":"Point"}
}