{
  "type": "Feature",
  "properties": {
    "addr:full":"73 Rodney Road Cheltenham Gloucestershire GL50 1HT",
    "addr:housenumber":"73",
    "addr:postcode":"gl50 1ht",
    "addr:street":"Rodney Road",
    "iso:country":"GB",
    "sg:address":"73 Rodney Road",
    "sg:city":"Cheltenham",
    "sg:classifiers":[
        {
            "category":"Communications",
            "subcategory":"Newspaper",
            "type":"Services"
        }
    ],
    "sg:phone":"+44 1242 537900",
    "sg:postcode":"GL50 1HT",
    "sg:province":"Gloucestershire",
    "sg:tags":[
        "magazine"
    ],
    "wof:name":"This England Ltd.",
    "wof:placetype":"venue"
},
  "geometry": {"coordinates":[-2.0757009983,51.8978347778],"type":"Point"}
}