{
  "type": "Feature",
  "properties": {
    "iso:country":"GB",
    "sg:address":"23 Ynys Terrace, Rhydyfelin",
    "sg:city":"Pontypridd",
    "sg:classifiers":[
        {
            "category":"Taxi",
            "type":"Transportation"
        },
        {
            "category":"Military Area",
            "subcategory":"Air Force Base",
            "type":"Public Place"
        }
    ],
    "sg:postcode":"CF37 5NY",
    "sg:province":"Caerphilly",
    "sg:tags":[
        "mini",
        "hire",
        "private",
        "cab"
    ],
    "wof:name":"Steve's Taxis",
    "wof:placetype":"venue"
},
  "geometry": {"coordinates":[-3.316421,51.586842],"type":"Point"}
}