{
  "type": "Feature",
  "properties": {
    "addr:full":"44 Drumcross Rd Bathgate West Lothian EH48 1AR",
    "addr:housenumber":"44",
    "addr:postcode":"eh48 1ar",
    "addr:street":"Drumcross Rd Bathgate",
    "iso:country":"GB",
    "sg:address":"44 Drumcross Rd",
    "sg:city":"Bathgate",
    "sg:classifiers":[
        {
            "category":"Education",
            "subcategory":"Special Training",
            "type":"Public Place"
        }
    ],
    "sg:phone":"+44 1506 632086",
    "sg:postcode":"EH48 1AR",
    "sg:province":"West Lothian",
    "sg:tags":[
        "aid",
        "first"
    ],
    "wof:name":"Albercare",
    "wof:placetype":"venue"
},
  "geometry": {"coordinates":[-3.635382,55.903774],"type":"Point"}
}