{
  "type": "Feature",
  "properties": {
    "addr:full":"30 St Marys Street Edinburgh City of Edinburgh EH1 1SU",
    "addr:housenumber":"30",
    "addr:postcode":"eh1 1su",
    "addr:street":"St Marys Street",
    "iso:country":"GB",
    "sg:address":"30 St Marys Street",
    "sg:city":"Edinburgh",
    "sg:classifiers":[
        {
            "category":"Arts & Performance",
            "subcategory":"Art Gallery",
            "type":"Entertainment"
        }
    ],
    "sg:phone":"+44 131 558 7880",
    "sg:postcode":"EH1 1SU",
    "sg:province":"City of Edinburgh",
    "wof:name":"Dom",
    "wof:placetype":"venue"
},
  "geometry": {"coordinates":[-3.183287,55.949699],"type":"Point"}
}