{
  "type": "Feature",
  "properties": {
    "addr:full":"26 South Road Weston-super-mare Somerset BS23 2HF",
    "addr:housenumber":"26",
    "addr:postcode":"bs23 2hf",
    "addr:street":"South Road",
    "iso:country":"GB",
    "sg:address":"26 South Road",
    "sg:city":"Weston-super-mare",
    "sg:classifiers":[
        {
            "category":"Travel",
            "subcategory":"Hostel",
            "type":"Entertainment"
        }
    ],
    "sg:postcode":"BS23 2HF",
    "sg:province":"Somerset",
    "wof:name":"The Anchorage Residential Hostel",
    "wof:placetype":"venue"
},
  "geometry": {"coordinates":[-2.9903690815,51.3554267883],"type":"Point"}
}