{
  "type": "Feature",
  "properties": {
    "addr:full":"Ash Tree Farm, Boyton Cross Chelmsford Essex CM1 4LP",
    "addr:postcode":"cm1 4lp",
    "addr:street":"Ash;Boyton Cross",
    "iso:country":"GB",
    "sg:address":"Ash Tree Farm, Boyton Cross",
    "sg:city":"Chelmsford",
    "sg:classifiers":[
        {
            "category":"Building & Trades",
            "subcategory":"Construction",
            "type":"Services"
        }
    ],
    "sg:phone":"+44 1245 248970",
    "sg:postcode":"CM1 4LP",
    "sg:province":"Essex",
    "sg:tags":[
        "contractor"
    ],
    "wof:name":"John Mullin",
    "wof:placetype":"venue"
},
  "geometry": {"coordinates":[0.3878400028,51.7575035095],"type":"Point"}
}