{
  "type": "Feature",
  "properties": {
    "addr:full":"51 Bedford Street London Greater London WC2R 0PZ",
    "addr:housenumber":"51",
    "addr:postcode":"wc2r 0pz",
    "addr:street":"Bedford Street",
    "iso:country":"GB",
    "sg:address":"51 Bedford Street",
    "sg:city":"London",
    "sg:classifiers":[
        {
            "category":"Shopping",
            "subcategory":"News",
            "type":"Retail Goods"
        }
    ],
    "sg:phone":"+44 20 7379 0755",
    "sg:postcode":"WC2R 0PZ",
    "sg:province":"Greater London",
    "sg:tags":[
        "newsagent"
    ],
    "wof:name":"Bedford News",
    "wof:placetype":"venue"
},
  "geometry": {"coordinates":[-0.123344,51.509796],"type":"Point"}
}