{
  "type": "Feature",
  "properties": {
    "addr:full":"11 Fanton Chase Wickford Essex SS11 8QX",
    "addr:housenumber":"11",
    "addr:postcode":"ss11 8qx",
    "addr:street":"Fanton Chase",
    "iso:country":"GB",
    "sg:address":"11 Fanton Chase",
    "sg:city":"Wickford",
    "sg:classifiers":[
        {
            "category":"Manufacturing",
            "subcategory":"Petroleum Products",
            "type":"Manufacturing & Wholesale Goods"
        }
    ],
    "sg:phone":"+44 1268 560495",
    "sg:postcode":"SS11 8QX",
    "sg:province":"Essex",
    "sg:tags":[
        "double",
        "glazing"
    ],
    "wof:name":"C.Mead",
    "wof:placetype":"venue"
},
  "geometry": {"coordinates":[0.5476419926,51.6062049866],"type":"Point"}
}