{
  "type": "Feature",
  "properties": {
    "iso:country":"GB",
    "sg:address":"Hillside, Lodes Lane, Kingston St Mary",
    "sg:city":"Taunton",
    "sg:classifiers":[
        {
            "category":"Professional",
            "subcategory":"Employment Agencies",
            "type":"Services"
        }
    ],
    "sg:postcode":"TA2 8HU",
    "sg:province":"Somerset",
    "sg:tags":[
        "agricultural",
        "advice"
    ],
    "wof:name":"Peter Day & Associates Agricultural Consultants",
    "wof:placetype":"venue"
},
  "geometry": {"coordinates":[-3.11296,51.062222],"type":"Point"}
}