{
  "type": "Feature",
  "properties": {
    "addr:full":"Lwr Langdon Farm, North Bovey Newton Abbot Devon TQ13 8RR",
    "addr:housenumber":"lwr;north bovey newton",
    "addr:postcode":"tq13 8rr",
    "iso:country":"GB",
    "sg:address":"Lwr Langdon Farm, North Bovey",
    "sg:city":"Newton Abbot",
    "sg:classifiers":[
        {
            "category":"Farming",
            "subcategory":"Livestock Farm",
            "type":"Manufacturing & Wholesale Goods"
        },
        {
            "category":"Farming",
            "subcategory":"Farm",
            "type":"Manufacturing & Wholesale Goods"
        }
    ],
    "sg:postcode":"TQ13 8RR",
    "sg:province":"Devon",
    "sg:tags":[
        "mixed",
        "crop",
        "others"
    ],
    "wof:name":"Rae,Linea J,",
    "wof:placetype":"venue"
},
  "geometry": {"coordinates":[-3.783277,50.641479],"type":"Point"}
}