{
  "type": "Feature",
  "properties": {
    "iso:country":"GB",
    "sg:address":"Moorgate Business Centre, South Grn",
    "sg:city":"Dereham",
    "sg:classifiers":[
        {
            "category":"Home & Garden",
            "subcategory":"Home Furnishings",
            "type":"Retail Goods"
        }
    ],
    "sg:phone":"+44 1362 691112",
    "sg:postcode":"NR19 1PT",
    "sg:province":"Norfolk",
    "sg:tags":[
        "decorative",
        "glass",
        "mirror"
    ],
    "wof:name":"Westead Ltd.",
    "wof:placetype":"venue"
},
  "geometry": {"coordinates":[0.9455890059,52.6801681519],"type":"Point"}
}