{
  "type": "Feature",
  "properties": {
    "iso:country":"GB",
    "sg:address":"Gossops Green La",
    "sg:city":"Crawley",
    "sg:classifiers":[
        {
            "category":"Place Of Worship",
            "type":"Public Place"
        }
    ],
    "sg:phone":"+44 1293 523918",
    "sg:postcode":"RH11 8BJ",
    "sg:province":"West Sussex",
    "wof:name":"St Theodore R C Church",
    "wof:placetype":"venue"
},
  "geometry": {"coordinates":[-0.21295,51.11351],"type":"Point"}
}