{
  "type": "Feature",
  "properties": {
    "iso:country":"GB",
    "sg:address":"12 High Street, Stalham",
    "sg:city":"Norwich",
    "sg:classifiers":[
        {
            "category":"Travel",
            "subcategory":"Hotels & Motels",
            "type":"Entertainment"
        }
    ],
    "sg:phone":"+44 1692 581974",
    "sg:postcode":"NR12 9AN",
    "sg:province":"Norfolk",
    "wof:name":"Kingfisher Hotel",
    "wof:placetype":"venue"
},
  "geometry": {"coordinates":[1.511376,52.772495],"type":"Point"}
}