{
  "type": "Feature",
  "properties": {
    "iso:country":"GB",
    "sg:address":"Tinmis Road",
    "sg:city":"Stourbridge",
    "sg:classifiers":[
        {
            "category":"Wholesale",
            "subcategory":"Machinery & Supplies",
            "type":"Manufacturing & Wholesale Goods"
        }
    ],
    "sg:phone":"+44 1384 892378",
    "sg:postcode":"DY9 7BQ",
    "sg:province":"West Midlands",
    "sg:tags":[
        "industrial",
        "commercial"
    ],
    "wof:name":"Jke Supplies Ltd.",
    "wof:placetype":"venue"
},
  "geometry": {"coordinates":[-2.124401,52.460068],"type":"Point"}
}