{
  "type": "Feature",
  "properties": {
    "addr:full":"35 Moorfield Walk Manchester Cheshire M41 0TT",
    "addr:housenumber":"35",
    "addr:postcode":"m41 0tt",
    "addr:street":"Moorfield Walk",
    "iso:country":"GB",
    "sg:address":"35 Moorfield Walk",
    "sg:city":"Manchester",
    "sg:classifiers":[
        {
            "category":"Food & Beverages",
            "subcategory":"Bakery",
            "type":"Retail Goods"
        }
    ],
    "sg:postcode":"M41 0TT",
    "sg:province":"Cheshire",
    "sg:tags":[
        "baker"
    ],
    "wof:name":"Parker Bradburn Ltd",
    "wof:placetype":"venue"
},
  "geometry": {"coordinates":[-2.35448,53.449261],"type":"Point"}
}