{
  "type": "Feature",
  "properties": {
    "addr:full":"Henfaes Lane Welshpool Shropshire SY21 9DJ",
    "addr:postcode":"sy21 9dj",
    "addr:street":"Henfaes Lane",
    "iso:country":"GB",
    "sg:address":"Henfaes Lane",
    "sg:city":"Welshpool",
    "sg:classifiers":[
        {
            "category":"Banks & Credit Unions",
            "subcategory":"Investment Brokerage",
            "type":"Services"
        }
    ],
    "sg:postcode":"SY21 9DJ",
    "sg:province":"Shropshire",
    "sg:tags":[
        "contractor"
    ],
    "wof:name":"John Davies Agricultural Contractors",
    "wof:placetype":"venue"
},
  "geometry": {"coordinates":[-3.135224,52.659054],"type":"Point"}
}