{
  "type": "Feature",
  "properties": {
    "iso:country":"GB",
    "sg:address":"Hollingbury Park Golf Course Dit, Ching Road",
    "sg:city":"Brighton",
    "sg:classifiers":[
        {
            "category":"Shopping",
            "subcategory":"Department Store",
            "type":"Retail Goods"
        }
    ],
    "sg:phone":"+44 1273 500086",
    "sg:postcode":"BN1 7HS",
    "sg:province":"East Sussex",
    "wof:name":"Peter Brown",
    "wof:placetype":"venue"
},
  "geometry": {"coordinates":[-0.130879,50.84391],"type":"Point"}
}