{
  "type": "Feature",
  "properties": {
    "addr:full":"14 Deptford High Street London Greater London SE8 4AF",
    "addr:housenumber":"14",
    "addr:postcode":"se8 4af",
    "addr:street":"Deptford High Street",
    "iso:country":"GB",
    "sg:address":"14 Deptford High Street",
    "sg:city":"London",
    "sg:classifiers":[
        {
            "category":"Shopping",
            "subcategory":"Baby Store",
            "type":"Retail Goods"
        }
    ],
    "sg:phone":"+44 20 8691 7344",
    "sg:postcode":"SE8 4AF",
    "sg:province":"Greater London",
    "sg:tags":[
        "nursery",
        "accessory"
    ],
    "wof:name":"Nirmal & Subhash Katyal",
    "wof:placetype":"venue"
},
  "geometry": {"coordinates":[-0.023553,51.474373],"type":"Point"}
}