{
  "type": "Feature",
  "properties": {
    "addr:full":"Bayton Rd, Exhall Coventry Warwickshire CV7 9EL",
    "addr:postcode":"cv7 9el",
    "addr:street":"Bayton Rd",
    "iso:country":"GB",
    "sg:address":"Bayton Rd, Exhall",
    "sg:city":"Coventry",
    "sg:classifiers":[
        {
            "category":"Manufacturing",
            "subcategory":"Rubber & Plastics",
            "type":"Manufacturing & Wholesale Goods"
        }
    ],
    "sg:phone":"+44 24 7636 1411",
    "sg:postcode":"CV7 9EL",
    "sg:province":"Warwickshire",
    "sg:tags":[
        "product"
    ],
    "wof:name":"Varicol Ltd",
    "wof:placetype":"venue"
},
  "geometry": {"coordinates":[-1.482574,52.465111],"type":"Point"}
}