{
  "type": "Feature",
  "properties": {
    "addr:full":"239 Broad Street Bromsgrove Worcestershire B61 8NL",
    "addr:housenumber":"239",
    "addr:postcode":"b61 8nl",
    "addr:street":"Broad Street",
    "iso:country":"GB",
    "sg:address":"239 Broad Street",
    "sg:city":"Bromsgrove",
    "sg:classifiers":[
        {
            "category":"Building & Trades",
            "subcategory":"Construction",
            "type":"Services"
        }
    ],
    "sg:postcode":"B61 8NL",
    "sg:province":"Worcestershire",
    "sg:tags":[
        "joiner",
        "carpenter"
    ],
    "wof:name":"Paul White Carpentry Services",
    "wof:placetype":"venue"
},
  "geometry": {"coordinates":[-2.0606880188,52.3469543457],"type":"Point"}
}