{
  "type": "Feature",
  "properties": {
    "iso:country":"GB",
    "sg:address":"116 Wickham Street",
    "sg:city":"Welling",
    "sg:classifiers":[
        {
            "category":"Shopping",
            "subcategory":"Department Store",
            "type":"Retail Goods"
        }
    ],
    "sg:phone":"+44 20 8854 4258",
    "sg:postcode":"DA16 3LU",
    "sg:province":"Kent",
    "wof:name":"Wickham Food & Wine",
    "wof:placetype":"venue"
},
  "geometry": {"coordinates":[0.0967160016,51.4689559937],"type":"Point"}
}