{
  "type": "Feature",
  "properties": {
    "addr:full":"99 Snydale Rd Barnsley South Yorkshire S72 8LH",
    "addr:housenumber":"99",
    "addr:postcode":"s72 8lh",
    "addr:street":"Snydale Rd;Yorkshire",
    "iso:country":"GB",
    "sg:address":"99 Snydale Rd",
    "sg:city":"Barnsley",
    "sg:classifiers":[
        {
            "category":"Shopping",
            "subcategory":"Department Store",
            "type":"Retail Goods"
        }
    ],
    "sg:phone":"+44 1226 710517",
    "sg:postcode":"S72 8LH",
    "sg:province":"South Yorkshire",
    "wof:name":"B Senior",
    "wof:placetype":"venue"
},
  "geometry": {"coordinates":[-1.413269043,53.5747184753],"type":"Point"}
}