{
  "type": "Feature",
  "properties": {
    "iso:country":"GB",
    "sg:address":"2 Belmont",
    "sg:city":"Shrewsbury",
    "sg:classifiers":[
        {
            "category":"Professional",
            "subcategory":"Lawyer & Legal Services",
            "type":"Services"
        }
    ],
    "sg:postcode":"SY1 1TD",
    "sg:province":"Shropshire",
    "sg:tags":[
        "solicitor"
    ],
    "wof:name":"Wace Morgan",
    "wof:placetype":"venue"
},
  "geometry": {"coordinates":[-2.752811,52.706402],"type":"Point"}
}