{
  "type": "Feature",
  "properties": {
    "addr:full":"24 Preston Old Road, Freckleton Preston Lancashire PR4 1PD",
    "addr:housenumber":"24",
    "addr:postcode":"pr4 1pd",
    "addr:street":"Preston Old Road",
    "iso:country":"GB",
    "sg:address":"24 Preston Old Road, Freckleton",
    "sg:city":"Preston",
    "sg:classifiers":[
        {
            "category":"Retail",
            "subcategory":"Veterinary Services",
            "type":"Services"
        }
    ],
    "sg:phone":"+44 1772 632317",
    "sg:postcode":"PR4 1PD",
    "sg:province":"Lancashire",
    "sg:tags":[
        "surgeon"
    ],
    "wof:name":"M G Cowgill",
    "wof:placetype":"venue"
},
  "geometry": {"coordinates":[-2.864626,53.754391],"type":"Point"}
}