{
  "type": "Feature",
  "properties": {
    "addr:full":"Chapel Street, Willington Crook Durham DL15 0EQ",
    "addr:postcode":"dl15 0eq",
    "addr:street":"Chapel Street",
    "iso:country":"GB",
    "sg:address":"Chapel Street, Willington",
    "sg:city":"Crook",
    "sg:classifiers":[
        {
            "category":"Health Services",
            "subcategory":"Clinic",
            "type":"Services"
        },
        {
            "category":"Education",
            "subcategory":"School",
            "type":"Public Place"
        },
        {
            "category":"Government",
            "subcategory":"Office",
            "type":"Public Place"
        }
    ],
    "sg:phone":"+44 1388 746414",
    "sg:postcode":"DL15 0EQ",
    "sg:province":"Durham",
    "sg:tags":[
        "nh",
        "local",
        "authority"
    ],
    "wof:name":"Willington Primary School",
    "wof:placetype":"venue"
},
  "geometry": {"coordinates":[-1.6967890263,54.712310791],"type":"Point"}
}