{
  "type": "Feature",
  "properties": {
    "addr:full":"32-34 Mill St Witney Oxfordshire OX29 4JS",
    "addr:housenumber":"32-34",
    "addr:postcode":"ox29 4js",
    "addr:street":"Mill St",
    "iso:country":"GB",
    "sg:address":"32-34 Mill St",
    "sg:city":"Witney",
    "sg:classifiers":[
        {
            "category":"Taxi",
            "type":"Transportation"
        }
    ],
    "sg:postcode":"OX29 4JS",
    "sg:province":"Oxfordshire",
    "sg:tags":[
        "mini",
        "cab"
    ],
    "wof:name":"Kabs Taxis",
    "wof:placetype":"venue"
},
  "geometry": {"coordinates":[-1.373923,51.782387],"type":"Point"}
}