{
  "type": "Feature",
  "properties": {
    "iso:country":"GB",
    "sg:address":"16 Streatham High Road",
    "sg:city":"London",
    "sg:classifiers":[
        {
            "category":"Food & Beverages",
            "subcategory":"Fruits & Vegetables",
            "type":"Retail Goods"
        }
    ],
    "sg:phone":"+44 20 8769 0584",
    "sg:postcode":"SW16 1PN",
    "sg:province":"Greater London",
    "sg:tags":[
        "greengrocer"
    ],
    "wof:name":"Streatham Fruiterers",
    "wof:placetype":"venue"
},
  "geometry": {"coordinates":[-0.1275119931,51.4375648499],"type":"Point"}
}