{
  "type": "Feature",
  "properties": {
    "addr:full":"29 Cardigan Av Accrington Lancashire BB5 4QL",
    "addr:housenumber":"29",
    "addr:postcode":"bb5 4ql",
    "addr:street":"Cardigan Av Accrington",
    "iso:country":"GB",
    "sg:address":"29 Cardigan Av",
    "sg:city":"Accrington",
    "sg:classifiers":[
        {
            "category":"Arts & Performance",
            "subcategory":"Music",
            "type":"Entertainment"
        }
    ],
    "sg:phone":"+44 1254 385476",
    "sg:postcode":"BB5 4QL",
    "sg:province":"Lancashire",
    "sg:tags":[
        "mobile",
        "disco"
    ],
    "wof:name":"Disco-Mobile",
    "wof:placetype":"venue"
},
  "geometry": {"coordinates":[-2.4086070061,53.7455368042],"type":"Point"}
}