{
  "type": "Feature",
  "properties": {
    "addr:full":"40 Chippenham Mews London Greater London W9 2AW",
    "addr:housenumber":"40",
    "addr:postcode":"w9 2aw",
    "addr:street":"Chippenham Mews",
    "iso:country":"GB",
    "sg:address":"40 Chippenham Mews",
    "sg:city":"London",
    "sg:classifiers":[
        {
            "category":"Professional",
            "subcategory":"Printing & Photocopies",
            "type":"Services"
        }
    ],
    "sg:phone":"+44 20 7286 7993",
    "sg:postcode":"W9 2AW",
    "sg:province":"Greater London",
    "sg:tags":[
        "printer"
    ],
    "wof:name":"Posters Unlimited",
    "wof:placetype":"venue"
},
  "geometry": {"coordinates":[-0.1972849965,51.5236701965],"type":"Point"}
}