{
  "type": "Feature",
  "properties": {
    "iso:country":"GB",
    "sg:address":"High St, Catterick",
    "sg:city":"Richmond",
    "sg:classifiers":[
        {
            "category":"Health Services",
            "subcategory":"Clinic",
            "type":"Services"
        }
    ],
    "sg:phone":"+44 1748 811100",
    "sg:postcode":"DL10 7LD",
    "sg:province":"North Yorkshire",
    "sg:tags":[
        "private"
    ],
    "wof:name":"Catterick Village Health Centre",
    "wof:placetype":"venue"
},
  "geometry": {"coordinates":[-1.630638957,54.3771018982],"type":"Point"}
}