{
  "type": "Feature",
  "properties": {
    "iso:country":"GB",
    "sg:address":"1 Crowhurst",
    "sg:city":"Peterborough",
    "sg:classifiers":[
        {
            "category":"Retail",
            "subcategory":"Storage",
            "type":"Services"
        }
    ],
    "sg:phone":"+44 1733 320331",
    "sg:postcode":"PE4 6JY",
    "sg:province":"Cambridgeshire",
    "sg:tags":[
        "household",
        "removal"
    ],
    "wof:name":"ABS Removals",
    "wof:placetype":"venue"
},
  "geometry": {"coordinates":[-0.269453,52.622677],"type":"Point"}
}