{
  "type": "Feature",
  "properties": {
    "addr:full":"89 Abingdon Road Wallingford Oxfordshire OX10 7LB",
    "addr:housenumber":"89",
    "addr:postcode":"ox10 7lb",
    "addr:street":"Abingdon Road",
    "iso:country":"GB",
    "sg:address":"89 Abingdon Road",
    "sg:city":"Wallingford",
    "sg:classifiers":[
        {
            "category":"Professional",
            "type":"Services"
        }
    ],
    "sg:postcode":"OX10 7LB",
    "sg:province":"Oxfordshire",
    "sg:tags":[
        "caterer"
    ],
    "wof:name":"Val Stones Catering",
    "wof:placetype":"venue"
},
  "geometry": {"coordinates":[-1.178086,51.654827],"type":"Point"}
}