{
  "type": "Feature",
  "properties": {
    "addr:full":"Fole Farm, Fole Uttoxeter Derbyshire ST14 5EF",
    "addr:postcode":"st14 5ef",
    "addr:street":"Uttoxeter",
    "iso:country":"GB",
    "sg:address":"Fole Farm, Fole",
    "sg:city":"Uttoxeter",
    "sg:classifiers":[
        {
            "category":"Farming",
            "subcategory":"Livestock Farm",
            "type":"Manufacturing & Wholesale Goods"
        }
    ],
    "sg:postcode":"ST14 5EF",
    "sg:province":"Derbyshire",
    "sg:tags":[
        "others"
    ],
    "wof:name":"J H & R H Ede",
    "wof:placetype":"venue"
},
  "geometry": {"coordinates":[-1.933769,52.933727],"type":"Point"}
}