{
  "type": "Feature",
  "properties": {
    "addr:full":"26 Charlton Road Shepton Mallet Somerset BA4 5NZ",
    "addr:housenumber":"26",
    "addr:postcode":"ba4 5nz",
    "addr:street":"Charlton Road",
    "iso:country":"GB",
    "sg:address":"26 Charlton Road",
    "sg:city":"Shepton Mallet",
    "sg:classifiers":[
        {
            "category":"Health Services",
            "subcategory":"Hospital",
            "type":"Services"
        }
    ],
    "sg:phone":"+44 1749 343911",
    "sg:postcode":"BA4 5NZ",
    "sg:province":"Somerset",
    "wof:name":"Windsor Day Hospital",
    "wof:placetype":"venue"
},
  "geometry": {"coordinates":[-2.539633,51.188454],"type":"Point"}
}