{
  "type": "Feature",
  "properties": {
    "addr:full":"1st Floor 26 Victoria St Cambridge Cambridgeshire CB1 1JP",
    "addr:housenumber":"26",
    "addr:postcode":"cb1 1jp",
    "addr:street":"Victoria St",
    "iso:country":"GB",
    "sg:address":"1st Floor 26 Victoria St",
    "sg:city":"Cambridge",
    "sg:classifiers":[
        {
            "category":"Personal",
            "subcategory":"Beauty Salon",
            "type":"Services"
        }
    ],
    "sg:phone":"+44 1223 355568",
    "sg:postcode":"CB1 1JP",
    "sg:province":"Cambridgeshire",
    "sg:tags":[
        "unisex",
        "hairdresser"
    ],
    "wof:name":"Clouds",
    "wof:placetype":"venue"
},
  "geometry": {"coordinates":[0.126162,52.205029],"type":"Point"}
}