{
  "type": "Feature",
  "properties": {
    "addr:full":"Warbraham Mains Farm, Heath Road, Burwell Cambridge Cambridgeshire CB5 0AP",
    "addr:postcode":"cb5 0ap",
    "addr:street":"Heath Road",
    "iso:country":"GB",
    "sg:address":"Warbraham Mains Farm, Heath Road, Burwell",
    "sg:city":"Cambridge",
    "sg:classifiers":[
        {
            "category":"Professional",
            "type":"Services"
        },
        {
            "category":"Banks & Credit Unions",
            "subcategory":"Investment Brokerage",
            "type":"Services"
        }
    ],
    "sg:phone":"+44 1638 741415",
    "sg:postcode":"CB5 0AP",
    "sg:province":"Cambridgeshire",
    "sg:tags":[
        "farm",
        "agricultural",
        "contractor"
    ],
    "wof:name":"P G KING & SON",
    "wof:placetype":"venue"
},
  "geometry": {"coordinates":[0.3289549947,52.2775611877],"type":"Point"}
}