{
  "type": "Feature",
  "properties": {
    "addr:full":"51 Merafield Road, Plympton Plymouth Devon PL7 1TL",
    "addr:housenumber":"51",
    "addr:postcode":"pl7 1tl",
    "addr:street":"Merafield Road",
    "iso:country":"GB",
    "sg:address":"51 Merafield Road, Plympton",
    "sg:city":"Plymouth",
    "sg:classifiers":[
        {
            "category":"Building & Trades",
            "subcategory":"Construction",
            "type":"Services"
        }
    ],
    "sg:phone":"+44 1752 336450",
    "sg:postcode":"PL7 1TL",
    "sg:province":"Devon",
    "sg:tags":[
        "welder"
    ],
    "wof:name":"Steve Gorten Welding Service",
    "wof:placetype":"venue"
},
  "geometry": {"coordinates":[-4.0647230148,50.3851127625],"type":"Point"}
}