{
  "type": "Feature",
  "properties": {
    "addr:full":"Diesel Centre, The Wards Elgin Moray IV30 6AA",
    "addr:postcode":"iv30 6aa",
    "addr:street":"The",
    "iso:country":"GB",
    "sg:address":"Diesel Centre, The Wards",
    "sg:city":"Elgin",
    "sg:classifiers":[
        {
            "category":"Autos & Motor Vehicles",
            "subcategory":"Auto Supplies",
            "type":"Retail Goods"
        }
    ],
    "sg:phone":"+44 1343 540794",
    "sg:postcode":"IV30 6AA",
    "sg:province":"Moray",
    "sg:tags":[
        "windscreen"
    ],
    "wof:name":"Autoglass",
    "wof:placetype":"venue"
},
  "geometry": {"coordinates":[-3.3046429157,57.6364860535],"type":"Point"}
}