{
  "type": "Feature",
  "properties": {
    "iso:country":"GB",
    "sg:address":"20 Malvern Crescent, Little Dawley",
    "sg:city":"Telford",
    "sg:classifiers":[
        {
            "category":"Freight",
            "type":"Transportation"
        }
    ],
    "sg:postcode":"TF4 3HE",
    "sg:province":"Shropshire",
    "sg:tags":[
        "haulage",
        "road"
    ],
    "wof:name":"Telford Tachograph Services",
    "wof:placetype":"venue"
},
  "geometry": {"coordinates":[-2.4675269127,52.6535758972],"type":"Point"}
}