{
  "type": "Feature",
  "properties": {
    "iso:country":"GB",
    "sg:address":"107 High Street",
    "sg:city":"Crawley",
    "sg:classifiers":[
        {
            "category":"Professional",
            "subcategory":"Lawyer & Legal Services",
            "type":"Services"
        }
    ],
    "sg:phone":"+44 1293 529889",
    "sg:postcode":"RH10 1DD",
    "sg:province":"Surrey",
    "sg:tags":[
        "solicitor"
    ],
    "wof:name":"Alistair Harper & Co.",
    "wof:placetype":"venue"
},
  "geometry": {"coordinates":[-0.189409,51.117409],"type":"Point"}
}