{
  "type": "Feature",
  "properties": {
    "iso:country":"GB",
    "sg:address":"29 Marylebone Lane",
    "sg:city":"London",
    "sg:classifiers":[
        {
            "category":"Transit Center",
            "subcategory":"Freight",
            "type":"Transportation"
        }
    ],
    "sg:phone":"+44 20 7486 0025",
    "sg:postcode":"W1U 2NQ",
    "sg:province":"Greater London",
    "sg:tags":[
        "piano",
        "accessory"
    ],
    "wof:name":"The Music Studios Ltd.",
    "wof:placetype":"venue"
},
  "geometry": {"coordinates":[-0.150702,51.516708],"type":"Point"}
}