{
  "type": "Feature",
  "properties": {
    "addr:full":"Brymbol Steel Site Works Wrexham Wrexham LL11 5BT",
    "addr:postcode":"ll11 5bt",
    "addr:street":"Works",
    "iso:country":"GB",
    "sg:address":"Brymbol Steel Site Works",
    "sg:city":"Wrexham",
    "sg:classifiers":[
        {
            "category":"Real Estate",
            "subcategory":"Developer",
            "type":"Services"
        }
    ],
    "sg:phone":"+44 1978 756333",
    "sg:postcode":"LL11 5BT",
    "sg:province":"Wrexham",
    "sg:tags":[
        "property"
    ],
    "wof:name":"Brymbol Developments Ltd",
    "wof:placetype":"venue"
},
  "geometry": {"coordinates":[-3.051609993,53.0783615112],"type":"Point"}
}