{
  "type": "Feature",
  "properties": {
    "iso:country":"GB",
    "sg:address":"170 Bridge Road, Sutton Bridge",
    "sg:city":"Spalding",
    "sg:classifiers":[
        {
            "category":"Personal",
            "subcategory":"Barber",
            "type":"Services"
        }
    ],
    "sg:phone":"+44 1406 351152",
    "sg:postcode":"PE12 9SF",
    "sg:province":"Cambridgeshire",
    "sg:tags":[
        "men's",
        "hairdresser"
    ],
    "wof:name":"Nick's Gentlemen's Hairdressers",
    "wof:placetype":"venue"
},
  "geometry": {"coordinates":[0.184935,52.770222],"type":"Point"}
}