{
  "type": "Feature",
  "properties": {
    "iso:country":"GB",
    "sg:address":"Unit 19 Imex Spaces Business Centre, Planetary Road",
    "sg:city":"Willenhall",
    "sg:classifiers":[
        {
            "category":"Manufacturing",
            "subcategory":"Tools & Machinery",
            "type":"Manufacturing & Wholesale Goods"
        }
    ],
    "sg:phone":"+44 1902 864305",
    "sg:postcode":"WV13 3SW",
    "sg:province":"West Midlands",
    "sg:tags":[
        "bearing",
        "stockist"
    ],
    "wof:name":"Campion Engineering Services Ltd.",
    "wof:placetype":"venue"
},
  "geometry": {"coordinates":[-2.0571041107,52.5842704773],"type":"Point"}
}