{
  "type": "Feature",
  "properties": {
    "iso:country":"GB",
    "sg:address":"Scott Polar Research Institute, Lensfield Road",
    "sg:city":"Cambridge",
    "sg:classifiers":[
        {
            "category":"Government",
            "subcategory":"Post Office",
            "type":"Public Place"
        }
    ],
    "sg:phone":"+44 1223 362061",
    "sg:postcode":"CB2 1ER",
    "sg:province":"Cambridgeshire",
    "sg:tags":[
        "organisation",
        "soc",
        "research"
    ],
    "wof:name":"Scientific Committee on Antarctic Research",
    "wof:placetype":"venue"
},
  "geometry": {"coordinates":[0.12633,52.198181],"type":"Point"}
}