{
  "type": "Feature",
  "properties": {
    "addr:full":"25 Allan Park Stirling Stirling FK8 2LT",
    "addr:housenumber":"25",
    "addr:postcode":"fk8 2lt",
    "addr:street":"Allan Park",
    "iso:country":"GB",
    "sg:address":"25 Allan Park",
    "sg:city":"Stirling",
    "sg:classifiers":[
        {
            "category":"Professional",
            "subcategory":"Management & Consulting",
            "type":"Services"
        }
    ],
    "sg:phone":"+44 1786 475095",
    "sg:postcode":"FK8 2LT",
    "sg:province":"Stirling",
    "sg:tags":[
        "consultant",
        "specialist"
    ],
    "wof:name":"Helen's Hair & Beauty Salon",
    "wof:placetype":"venue"
},
  "geometry": {"coordinates":[-3.939656,56.115959],"type":"Point"}
}