{
  "type": "Feature",
  "properties": {
    "addr:full":"24 East St Wareham Dorset BH20 4NP",
    "addr:housenumber":"24",
    "addr:postcode":"bh20 4np",
    "addr:street":"East St",
    "iso:country":"GB",
    "sg:address":"24 East St",
    "sg:city":"Wareham",
    "sg:classifiers":[
        {
            "category":"Social Services",
            "type":"Services"
        }
    ],
    "sg:phone":"+44 1929 552005",
    "sg:postcode":"BH20 4NP",
    "sg:province":"Dorset",
    "sg:tags":[
        "disability"
    ],
    "wof:name":"Ezi-Line Ltd",
    "wof:placetype":"venue"
},
  "geometry": {"coordinates":[-2.108406,50.686142],"type":"Point"}
}