{
  "type": "Feature",
  "properties": {
    "addr:full":"32 High Street, Pelsall Walsall Staffordshire WS3 4LX",
    "addr:housenumber":"32",
    "addr:postcode":"ws3 4lx",
    "addr:street":"High Street",
    "iso:country":"GB",
    "sg:address":"32 High Street, Pelsall",
    "sg:city":"Walsall",
    "sg:classifiers":[
        {
            "category":"Retail",
            "subcategory":"Repair Shop",
            "type":"Services"
        }
    ],
    "sg:phone":"+44 1922 692627",
    "sg:postcode":"WS3 4LX",
    "sg:province":"Staffordshire",
    "sg:tags":[
        "radio",
        "television",
        "video"
    ],
    "wof:name":"A & P Tv Video Services",
    "wof:placetype":"venue"
},
  "geometry": {"coordinates":[-1.967674,52.629162],"type":"Point"}
}