{
  "type": "Feature",
  "properties": {
    "iso:country":"GB",
    "sg:address":"43 Kirkgate",
    "sg:city":"Tadcaster",
    "sg:classifiers":[
        {
            "category":"Health Services",
            "subcategory":"Dentist",
            "type":"Services"
        }
    ],
    "sg:postcode":"LS24 9AQ",
    "sg:province":"North Yorkshire",
    "wof:name":"Andrew R Waterfield",
    "wof:placetype":"venue"
},
  "geometry": {"coordinates":[-1.262101,53.884277],"type":"Point"}
}