{
  "type": "Feature",
  "properties": {
    "addr:full":"31 Stoke Road Walton-on-thames Surrey KT12 3DD",
    "addr:housenumber":"31",
    "addr:postcode":"kt12 3dd",
    "addr:street":"Stoke Road",
    "iso:country":"GB",
    "sg:address":"31 Stoke Road",
    "sg:city":"Walton-on-thames",
    "sg:classifiers":[
        {
            "category":"Building & Trades",
            "subcategory":"Construction",
            "type":"Services"
        }
    ],
    "sg:postcode":"KT12 3DD",
    "sg:province":"Surrey",
    "sg:tags":[
        "builder"
    ],
    "wof:name":"Bricks & Mortar (Weybridge)",
    "wof:placetype":"venue"
},
  "geometry": {"coordinates":[-0.402245,51.375282],"type":"Point"}
}