{
  "type": "Feature",
  "properties": {
    "addr:full":"Unit 8, Blackhorse Road Letchworth Hertfordshire SG6 1HB",
    "addr:housenumber":"unit 8",
    "addr:postcode":"sg6 1hb",
    "addr:street":"Blackhorse Road",
    "iso:country":"GB",
    "sg:address":"Unit 8, Blackhorse Road",
    "sg:city":"Letchworth",
    "sg:classifiers":[
        {
            "category":"Manufacturing",
            "subcategory":"Electronics",
            "type":"Manufacturing & Wholesale Goods"
        }
    ],
    "sg:phone":"+44 1462 483858",
    "sg:postcode":"SG6 1HB",
    "sg:province":"Hertfordshire",
    "sg:tags":[
        "printed",
        "circuit"
    ],
    "wof:name":"Acadamies Ltd.",
    "wof:placetype":"venue"
},
  "geometry": {"coordinates":[-0.208429,51.987061],"type":"Point"}
}