{
  "type": "Feature",
  "properties": {
    "iso:country":"GB",
    "sg:address":"160 Shorrock Lane",
    "sg:city":"Blackburn",
    "sg:classifiers":[
        {
            "category":"Retail",
            "subcategory":"Driving School",
            "type":"Services"
        }
    ],
    "sg:phone":"+44 1254 202478",
    "sg:postcode":"BB2 4TT",
    "sg:province":"Lancashire",
    "wof:name":"Michael English",
    "wof:placetype":"venue"
},
  "geometry": {"coordinates":[-2.508948,53.729168],"type":"Point"}
}