{
  "type": "Feature",
  "properties": {
    "iso:country":"GB",
    "sg:address":"26 St Georges Shopping & Leisur, E Centre",
    "sg:city":"Harrow",
    "sg:classifiers":[
        {
            "category":"Restaurant",
            "type":"Food & Drink"
        }
    ],
    "sg:phone":"+44 20 8861 0007",
    "sg:postcode":"HA1 1HS",
    "sg:province":"Greater London",
    "sg:tags":[
        "american"
    ],
    "wof:name":"Fatty Arbuckles American Diner",
    "wof:placetype":"venue"
},
  "geometry": {"coordinates":[-0.383253,51.626461],"type":"Point"}
}