{
  "type": "Feature",
  "properties": {
    "addr:full":"Damar, Tregoney Hill, Mevagissey St Austell Cornwall PL26 6RF",
    "addr:postcode":"pl26 6rf",
    "addr:street":"Tregoney Hill",
    "iso:country":"GB",
    "sg:address":"Damar, Tregoney Hill, Mevagissey",
    "sg:city":"St Austell",
    "sg:classifiers":[
        {
            "category":"Building & Trades",
            "subcategory":"Construction",
            "type":"Services"
        }
    ],
    "sg:phone":"+44 1726 843477",
    "sg:postcode":"PL26 6RF",
    "sg:province":"Cornwall",
    "sg:tags":[
        "builder"
    ],
    "wof:name":"David Churms",
    "wof:placetype":"venue"
},
  "geometry": {"coordinates":[-4.789794,50.271118],"type":"Point"}
}