{
  "type": "Feature",
  "properties": {
    "addr:full":"Unit 17, Creekmouth Industrial Estate, River Road Barking Essex IG11 0DA",
    "addr:housenumber":"unit 17",
    "addr:postcode":"ig11 0da",
    "addr:street":"Industrial Estate River Road",
    "iso:country":"GB",
    "sg:address":"Unit 17, Creekmouth Industrial Estate, River Road",
    "sg:city":"Barking",
    "sg:classifiers":[
        {
            "category":"Building & Trades",
            "subcategory":"Construction",
            "type":"Services"
        }
    ],
    "sg:phone":"+44 20 8507 8480",
    "sg:postcode":"IG11 0DA",
    "sg:province":"Essex",
    "sg:tags":[
        "glazier"
    ],
    "wof:name":"Glass & General Maintenance",
    "wof:placetype":"venue"
},
  "geometry": {"coordinates":[0.104205,51.516819],"type":"Point"}
}