{
  "type": "Feature",
  "properties": {
    "addr:full":"High St Bolton Lancashire BL3 1NB",
    "addr:postcode":"bl3 1nb",
    "addr:street":"High St",
    "iso:country":"GB",
    "sg:address":"High St",
    "sg:city":"Bolton",
    "sg:classifiers":[
        {
            "category":"Retail",
            "subcategory":"Auto Repair",
            "type":"Services"
        }
    ],
    "sg:postcode":"BL3 1NB",
    "sg:province":"Lancashire",
    "sg:tags":[
        "modification",
        "garage"
    ],
    "wof:name":"Gregory,Ernie",
    "wof:placetype":"venue"
},
  "geometry": {"coordinates":[-2.369114,53.561291],"type":"Point"}
}