{
  "type": "Feature",
  "properties": {
    "addr:full":"Sea Rd, Milford On Sea Lymington Hampshire SO41 0PG",
    "addr:postcode":"so41 0pg",
    "addr:street":"Sea Rd",
    "iso:country":"GB",
    "sg:address":"Sea Rd, Milford On Sea",
    "sg:city":"Lymington",
    "sg:classifiers":[
        {
            "category":"Health Services",
            "subcategory":"Hospital",
            "type":"Services"
        }
    ],
    "sg:phone":"+44 1590 648100",
    "sg:postcode":"SO41 0PG",
    "sg:province":"Hampshire",
    "wof:name":"Milford War Memorial Hospital",
    "wof:placetype":"venue"
},
  "geometry": {"coordinates":[-1.5922290087,50.725063324],"type":"Point"}
}