{
  "type": "Feature",
  "properties": {
    "addr:full":"Primrose Quay, Ferry Road Renfrew Renfrewshire PA4 8SH",
    "addr:postcode":"pa4 8sh",
    "addr:street":"Primrose Quay Ferry Road",
    "iso:country":"GB",
    "sg:address":"Primrose Quay, Ferry Road",
    "sg:city":"Renfrew",
    "sg:classifiers":[
        {
            "category":"Recreation",
            "subcategory":"Boat Charter",
            "type":"Entertainment"
        },
        {
            "category":"Recreation",
            "subcategory":"Sailing Club",
            "type":"Entertainment"
        }
    ],
    "sg:phone":"+44 141 886 1212",
    "sg:postcode":"PA4 8SH",
    "sg:province":"Renfrewshire",
    "sg:tags":[
        "excursion"
    ],
    "wof:name":"Clambay",
    "wof:placetype":"venue"
},
  "geometry": {"coordinates":[-4.3836,55.885311],"type":"Point"}
}