{
  "type": "Feature",
  "properties": {
    "addr:full":"324 Hackney Road London Greater London E2 7AX",
    "addr:housenumber":"324",
    "addr:postcode":"e2 7ax",
    "addr:street":"Hackney Road",
    "iso:country":"GB",
    "sg:address":"324 Hackney Road",
    "sg:city":"London",
    "sg:classifiers":[
        {
            "category":"Shopping",
            "subcategory":"Luggage & Leather Goods",
            "type":"Retail Goods"
        }
    ],
    "sg:phone":"+44 20 7613 0719",
    "sg:postcode":"E2 7AX",
    "sg:province":"Greater London",
    "sg:tags":[
        "shop",
        "leathergoods"
    ],
    "wof:name":"Monarch Leather Goods Ltd.",
    "wof:placetype":"venue"
},
  "geometry": {"coordinates":[-0.067101,51.531063],"type":"Point"}
}