{
  "type": "Feature",
  "properties": {
    "addr:full":"Unit 10e The Grip Indust Est, Hadstock Rd Cambridge Cambridgeshire CB1 6NR",
    "addr:housenumber":"unit 10e",
    "addr:postcode":"cb1 6nr",
    "addr:street":"The;Indust;Hadstock Rd",
    "iso:country":"GB",
    "sg:address":"Unit 10e The Grip Indust Est, Hadstock Rd",
    "sg:city":"Cambridge",
    "sg:classifiers":[
        {
            "category":"Building & Trades",
            "subcategory":"Construction",
            "type":"Services"
        }
    ],
    "sg:phone":"+44 1223 891423",
    "sg:postcode":"CB1 6NR",
    "sg:province":"Cambridgeshire",
    "sg:tags":[
        "builder"
    ],
    "wof:name":"G Impey & Co Development Ltd",
    "wof:placetype":"venue"
},
  "geometry": {"coordinates":[0.2733150125,52.0809059143],"type":"Point"}
}