{
  "type": "Feature",
  "properties": {
    "iso:country":"GB",
    "sg:address":"The Health Centre, Church La",
    "sg:city":"Chester",
    "sg:classifiers":[
        {
            "category":"Health Services",
            "subcategory":"Doctor",
            "type":"Services"
        }
    ],
    "sg:phone":"+44 1829 270206",
    "sg:postcode":"CH3 6QD",
    "sg:province":"Cheshire",
    "sg:tags":[
        "practitioners"
    ],
    "wof:name":"Duffin, L B",
    "wof:placetype":"venue"
},
  "geometry": {"coordinates":[-2.87805,53.083961],"type":"Point"}
}