{
  "type": "Feature",
  "properties": {
    "iso:country":"GB",
    "sg:address":"6 Church Street",
    "sg:city":"Glenrothes",
    "sg:classifiers":[
        {
            "category":"Retail",
            "subcategory":"Funeral Services",
            "type":"Services"
        }
    ],
    "sg:phone":"+44 1592 751997",
    "sg:postcode":"KY7 5ND",
    "sg:province":"Fife",
    "sg:tags":[
        "director"
    ],
    "wof:name":"Crosbie Matthew Funeral Directors Ltd.",
    "wof:placetype":"venue"
},
  "geometry": {"coordinates":[-3.165789,56.196991],"type":"Point"}
}