{
  "type": "Feature",
  "properties": {
    "addr:full":"Worthy Street Chorley Lancashire PR6 0NH",
    "addr:postcode":"pr6 0nh",
    "addr:street":"Worthy Street",
    "iso:country":"GB",
    "sg:address":"Worthy Street",
    "sg:city":"Chorley",
    "sg:classifiers":[
        {
            "category":"Organizations",
            "subcategory":"Membership Organization",
            "type":"Services"
        }
    ],
    "sg:phone":"+44 1257 270092",
    "sg:postcode":"PR6 0NH",
    "sg:province":"Lancashire",
    "sg:tags":[
        "club",
        "social"
    ],
    "wof:name":"Sacred Heart",
    "wof:placetype":"venue"
},
  "geometry": {"coordinates":[-2.621019,53.651428],"type":"Point"}
}