{
  "type": "Feature",
  "properties": {
    "addr:full":"18 The Crescent Leatherhead Surrey KT22 8EE",
    "addr:housenumber":"18",
    "addr:postcode":"kt22 8ee",
    "addr:street":"The Crescent",
    "iso:country":"GB",
    "sg:address":"18 The Crescent",
    "sg:city":"Leatherhead",
    "sg:classifiers":[
        {
            "category":"Professional",
            "subcategory":"Lawyer & Legal Services",
            "type":"Services"
        }
    ],
    "sg:phone":"+44 1372 376493",
    "sg:postcode":"KT22 8EE",
    "sg:province":"Surrey",
    "sg:tags":[
        "barrister"
    ],
    "wof:name":"Peter John & Tanya White",
    "wof:placetype":"venue"
},
  "geometry": {"coordinates":[-0.3268299997,51.2947158813],"type":"Point"}
}