{
  "type": "Feature",
  "properties": {
    "addr:full":"1 Rock Terrace Leeds Road, Lightcliffe Halifax West Yorkshire HX3 8DY",
    "addr:housenumber":"1",
    "addr:postcode":"hx3 8dy",
    "addr:street":"Rock Terrace Leeds Road",
    "iso:country":"GB",
    "sg:address":"1 Rock Terrace Leeds Road, Lightcliffe",
    "sg:city":"Halifax",
    "sg:classifiers":[
        {
            "category":"Professional",
            "subcategory":"Employment Agencies",
            "type":"Services"
        }
    ],
    "sg:postcode":"HX3 8DY",
    "sg:province":"West Yorkshire",
    "sg:tags":[
        "consultant"
    ],
    "wof:name":"Halifax Resources Ltd.",
    "wof:placetype":"venue"
},
  "geometry": {"coordinates":[-1.784537,53.723907],"type":"Point"}
}