{
  "type": "Feature",
  "properties": {
    "addr:full":"Kingsley Clinic Coventry Road, Kingsbury Tamworth Staffordshire B78 2LN",
    "addr:postcode":"b78 2ln",
    "addr:street":"Coventry Road",
    "iso:country":"GB",
    "sg:address":"Kingsley Clinic Coventry Road, Kingsbury",
    "sg:city":"Tamworth",
    "sg:classifiers":[
        {
            "category":"Health Services",
            "subcategory":"Clinic",
            "type":"Services"
        }
    ],
    "sg:phone":"+44 1827 874883",
    "sg:postcode":"B78 2LN",
    "sg:province":"Staffordshire",
    "sg:tags":[
        "private"
    ],
    "wof:name":"Peripatetic Day Hospital",
    "wof:placetype":"venue"
},
  "geometry": {"coordinates":[-1.683309,52.568787],"type":"Point"}
}