{
  "type": "Feature",
  "properties": {
    "addr:full":"Harton Depot, Stanwell Rd Slough Berkshire SL3 9PE",
    "addr:postcode":"sl3 9pe",
    "addr:street":"Stanwell Rd",
    "iso:country":"GB",
    "sg:address":"Harton Depot, Stanwell Rd",
    "sg:city":"Slough",
    "sg:classifiers":[
        {
            "category":"Retail",
            "subcategory":"Auto Repair",
            "type":"Services"
        }
    ],
    "sg:phone":"+44 1753 680441",
    "sg:postcode":"SL3 9PE",
    "sg:province":"Berkshire",
    "sg:tags":[
        "car",
        "upholsterer"
    ],
    "wof:name":"M P C",
    "wof:placetype":"venue"
},
  "geometry": {"coordinates":[-0.53196,51.470219],"type":"Point"}
}