{
  "type": "Feature",
  "properties": {
    "addr:full":"Care Of Kwik Save St Andrews Fife KY16 8NH",
    "addr:postcode":"ky16 8nh",
    "addr:street":"St Andrews",
    "iso:country":"GB",
    "sg:address":"Care Of Kwik Save",
    "sg:city":"St Andrews",
    "sg:classifiers":[
        {
            "category":"Wholesale",
            "subcategory":"Meat",
            "type":"Manufacturing & Wholesale Goods"
        }
    ],
    "sg:postcode":"KY16 8NH",
    "sg:province":"Fife",
    "sg:tags":[
        "-"
    ],
    "wof:name":"Thompson Young",
    "wof:placetype":"venue"
},
  "geometry": {"coordinates":[-2.80328,56.333179],"type":"Point"}
}