{
  "type": "Feature",
  "properties": {
    "iso:country":"GB",
    "sg:address":"4 Love La",
    "sg:city":"Grantham",
    "sg:classifiers":[
        {
            "category":"Farming",
            "subcategory":"Farm",
            "type":"Manufacturing & Wholesale Goods"
        }
    ],
    "sg:phone":"+44 1400 272203",
    "sg:postcode":"NG32 3DE",
    "sg:province":"Leicestershire",
    "sg:tags":[
        "mixed",
        "crop"
    ],
    "wof:name":"C W Rossington",
    "wof:placetype":"venue"
},
  "geometry": {"coordinates":[-0.598444,53.022205],"type":"Point"}
}