{
  "type": "Feature",
  "properties": {
    "addr:full":"141-149 Wigan Lane Wigan Lancashire WN1 2NB",
    "addr:postcode":"141-149;wn1 2nb",
    "addr:street":"Wigan Lane",
    "iso:country":"GB",
    "sg:address":"141-149 Wigan Lane",
    "sg:city":"Wigan",
    "sg:classifiers":[
        {
            "category":"Travel",
            "subcategory":"Hotels & Motels",
            "type":"Entertainment"
        }
    ],
    "sg:phone":"+44 1942 243893",
    "sg:postcode":"WN1 2NB",
    "sg:province":"Lancashire",
    "wof:name":"Macdonald Hotels (Management) Ltd.",
    "wof:placetype":"venue"
},
  "geometry": {"coordinates":[-2.628371954,53.5566596985],"type":"Point"}
}