{
  "type": "Feature",
  "properties": {
    "addr:full":"126 Chester Street Wolverhampton Shropshire WV6 0BZ",
    "addr:housenumber":"126",
    "addr:postcode":"wv6 0bz",
    "addr:street":"Chester Street",
    "iso:country":"GB",
    "sg:address":"126 Chester Street",
    "sg:city":"Wolverhampton",
    "sg:classifiers":[
        {
            "category":"Organizations",
            "subcategory":"Community Association",
            "type":"Services"
        }
    ],
    "sg:phone":"+44 1902 427330",
    "sg:postcode":"WV6 0BZ",
    "sg:province":"Shropshire",
    "sg:tags":[
        "society",
        "housing"
    ],
    "wof:name":"Asra Midlands Housing Association",
    "wof:placetype":"venue"
},
  "geometry": {"coordinates":[-2.138983,52.594406],"type":"Point"}
}