{
  "type": "Feature",
  "properties": {
    "addr:full":"Unit 2 Manor Park, Turpin Lane Erith Kent DA8 2AT",
    "addr:housenumber":"unit 2",
    "addr:postcode":"da8 2at",
    "addr:street":"Manor Park Turpin Lane",
    "iso:country":"GB",
    "sg:address":"Unit 2 Manor Park, Turpin Lane",
    "sg:city":"Erith",
    "sg:classifiers":[
        {
            "category":"Building & Trades",
            "subcategory":"Plumbing",
            "type":"Services"
        }
    ],
    "sg:phone":"+44 1322 553544",
    "sg:postcode":"DA8 2AT",
    "sg:province":"Kent",
    "sg:tags":[
        "central",
        "heating"
    ],
    "wof:name":"S C Mechanical Services Ltd.",
    "wof:placetype":"venue"
},
  "geometry": {"coordinates":[0.183935,51.478371],"type":"Point"}
}