{
  "type": "Feature",
  "properties": {
    "iso:country":"GB",
    "sg:address":"Suite 235 St Neots Road, Eaton Ford",
    "sg:city":"St Neots",
    "sg:classifiers":[
        {
            "category":"Professional",
            "subcategory":"Computer Services",
            "type":"Services"
        }
    ],
    "sg:phone":"+44 1480 403111",
    "sg:postcode":"PE19 7BD",
    "sg:province":"Bedfordshire",
    "sg:tags":[
        "system",
        "software"
    ],
    "wof:name":"Greenfield Software Ltd.",
    "wof:placetype":"venue"
},
  "geometry": {"coordinates":[-0.2785969973,52.225944519],"type":"Point"}
}