{
  "type": "Feature",
  "properties": {
    "addr:full":"1 Purley Road Purley Surrey CR8 2HA",
    "addr:housenumber":"1",
    "addr:postcode":"cr8 2ha",
    "addr:street":"Purley Road",
    "iso:country":"GB",
    "sg:address":"1 Purley Road",
    "sg:city":"Purley",
    "sg:classifiers":[
        {
            "category":"Professional",
            "subcategory":"Accounting & Tax Preparation",
            "type":"Services"
        }
    ],
    "sg:phone":"+44 20 8763 1948",
    "sg:postcode":"CR8 2HA",
    "sg:province":"Surrey",
    "sg:tags":[
        "accountant",
        "activity"
    ],
    "wof:name":"Lees",
    "wof:placetype":"venue"
},
  "geometry": {"coordinates":[-0.116685003,51.338470459],"type":"Point"}
}