{
  "type": "Feature",
  "properties": {
    "addr:full":"44 Acacia Road Leamington Spa Warwickshire CV32 6EQ",
    "addr:housenumber":"44",
    "addr:postcode":"cv32 6eq",
    "addr:street":"Acacia Road",
    "iso:country":"GB",
    "sg:address":"44 Acacia Road",
    "sg:city":"Leamington Spa",
    "sg:classifiers":[
        {
            "category":"Government",
            "subcategory":"Post Office",
            "type":"Public Place"
        }
    ],
    "sg:phone":"+44 1926 881515",
    "sg:postcode":"CV32 6EQ",
    "sg:province":"Warwickshire",
    "sg:tags":[
        "messenger",
        "courier"
    ],
    "wof:name":"Action Express",
    "wof:placetype":"venue"
},
  "geometry": {"coordinates":[-1.5534110069,52.2929267883],"type":"Point"}
}