{
  "type": "Feature",
  "properties": {
    "iso:country":"GB",
    "sg:address":"Fron Haul",
    "sg:city":"Llansantffraid",
    "sg:classifiers":[
        {
            "category":"Retail",
            "subcategory":"Auto Repair",
            "type":"Services"
        }
    ],
    "sg:postcode":"SY22 6TA",
    "sg:province":"Shropshire",
    "sg:tags":[
        "body",
        "garage",
        "modification",
        "car"
    ],
    "wof:name":"D Roy Evans",
    "wof:placetype":"venue"
},
  "geometry": {"coordinates":[-3.1549890041,52.7744903564],"type":"Point"}
}