{
  "type": "Feature",
  "properties": {
    "addr:full":"15 Canfield Gardens Kilburn Greater London NW6 3JT",
    "addr:housenumber":"15",
    "addr:postcode":"nw6 3jt",
    "addr:street":"Canfield Gardens",
    "iso:country":"GB",
    "sg:address":"15 Canfield Gardens",
    "sg:city":"Kilburn",
    "sg:classifiers":[
        {
            "category":"Health Services",
            "subcategory":"Health Practitioner",
            "type":"Services"
        }
    ],
    "sg:phone":"+44 20 7328 1430",
    "sg:postcode":"NW6 3JT",
    "sg:province":"Greater London",
    "sg:tags":[
        "acupuncture"
    ],
    "wof:name":"Alnoor Mohamed",
    "wof:placetype":"venue"
},
  "geometry": {"coordinates":[-0.1817879975,51.5456581116],"type":"Point"}
}