{
  "type": "Feature",
  "properties": {
    "iso:country":"GB",
    "sg:address":"32 Brocks Drive",
    "sg:city":"Guildford",
    "sg:classifiers":[
        {
            "category":"Autos & Motor Vehicles",
            "subcategory":"Motorcycle Sales",
            "type":"Retail Goods"
        }
    ],
    "sg:postcode":"GU3 3NQ",
    "sg:province":"Surrey",
    "sg:tags":[
        "chauffeur",
        "driven",
        "car"
    ],
    "wof:name":"Roger Frogley",
    "wof:placetype":"venue"
},
  "geometry": {"coordinates":[-0.6219,51.259666],"type":"Point"}
}