{
  "type": "Feature",
  "properties": {
    "addr:full":"80 Cartledge Lane, Holmesfield Dronfield Derbyshire S18 7SB",
    "addr:housenumber":"80",
    "addr:postcode":"s18 7sb",
    "addr:street":"Cartledge Lane",
    "iso:country":"GB",
    "sg:address":"80 Cartledge Lane, Holmesfield",
    "sg:city":"Dronfield",
    "sg:classifiers":[
        {
            "category":"Sports & Exercise",
            "subcategory":"Stables",
            "type":"Entertainment"
        },
        {
            "category":"Personal",
            "subcategory":"Adult",
            "type":"Services"
        }
    ],
    "sg:postcode":"S18 7SB",
    "sg:province":"Derbyshire",
    "sg:tags":[
        "education",
        "equestrian"
    ],
    "wof:name":"David Adlington",
    "wof:placetype":"venue"
},
  "geometry": {"coordinates":[-1.515465,53.29073],"type":"Point"}
}