{
  "type": "Feature",
  "properties": {
    "addr:full":"10 Harrison Gro Harrogate North Yorkshire HG1 4QJ",
    "addr:housenumber":"10",
    "addr:postcode":"hg1 4qj",
    "addr:street":"Harrison Gro",
    "iso:country":"GB",
    "sg:address":"10 Harrison Gro",
    "sg:city":"Harrogate",
    "sg:classifiers":[
        {
            "category":"Building & Trades",
            "subcategory":"Construction",
            "type":"Services"
        }
    ],
    "sg:postcode":"HG1 4QJ",
    "sg:province":"North Yorkshire",
    "sg:tags":[
        "decorator",
        "painter"
    ],
    "wof:name":"M E Harvey",
    "wof:placetype":"venue"
},
  "geometry": {"coordinates":[-1.5022939444,54.0023193359],"type":"Point"}
}