{
  "type": "Feature",
  "properties": {
    "addr:full":"Victoria Road Kington Herefordshire HR5 3BY",
    "addr:postcode":"hr5 3by",
    "addr:street":"Victoria Road",
    "iso:country":"GB",
    "sg:address":"Victoria Road",
    "sg:city":"Kington",
    "sg:classifiers":[
        {
            "category":"Building & Trades",
            "subcategory":"Construction",
            "type":"Services"
        }
    ],
    "sg:phone":"+44 1544 230403",
    "sg:postcode":"HR5 3BY",
    "sg:province":"Herefordshire",
    "sg:tags":[
        "builder"
    ],
    "wof:name":"Ernest Deacon Ltd",
    "wof:placetype":"venue"
},
  "geometry": {"coordinates":[-3.026444,52.204571],"type":"Point"}
}