{
  "type": "Feature",
  "properties": {
    "addr:full":"1 Ryecroft Way Wooler Northumberland NE71 6BW",
    "addr:housenumber":"1",
    "addr:postcode":"ne71 6bw",
    "addr:street":"Ryecroft Way",
    "iso:country":"GB",
    "sg:address":"1 Ryecroft Way",
    "sg:city":"Wooler",
    "sg:classifiers":[
        {
            "category":"Travel",
            "subcategory":"Hotels & Motels",
            "type":"Entertainment"
        }
    ],
    "sg:postcode":"NE71 6BW",
    "sg:province":"Northumberland",
    "sg:tags":[
        "house",
        "guest"
    ],
    "wof:name":"LORETO GUEST HOUSE",
    "wof:placetype":"venue"
},
  "geometry": {"coordinates":[-2.0181128979,55.5478019714],"type":"Point"}
}