{
  "type": "Feature",
  "properties": {
    "addr:full":"24-34 Crawley Road Luton Bedfordshire LU1 1HZ",
    "addr:housenumber":"24-34",
    "addr:postcode":"lu1 1hz",
    "addr:street":"Crawley Road",
    "iso:country":"GB",
    "sg:address":"24-34 Crawley Road",
    "sg:city":"Luton",
    "sg:classifiers":[
        {
            "category":"Retail",
            "subcategory":"Auto Rental",
            "type":"Services"
        }
    ],
    "sg:phone":"+44 1582 455333",
    "sg:postcode":"LU1 1HZ",
    "sg:province":"Bedfordshire",
    "sg:tags":[
        "car"
    ],
    "wof:name":"Kenning Car & Van Rental",
    "wof:placetype":"venue"
},
  "geometry": {"coordinates":[-0.422313,51.883862],"type":"Point"}
}