{
  "type": "Feature",
  "properties": {
    "addr:full":"188-190 Torquay Rd Paignton Devon TQ3 2AL",
    "addr:housenumber":"188-190",
    "addr:postcode":"tq3 2al",
    "addr:street":"Torquay Rd",
    "iso:country":"GB",
    "sg:address":"188-190 Torquay Rd",
    "sg:city":"Paignton",
    "sg:classifiers":[
        {
            "category":"Bars & Pubs",
            "type":"Food & Drink"
        }
    ],
    "sg:phone":"+44 1803 551385",
    "sg:postcode":"TQ3 2AL",
    "sg:province":"Devon",
    "sg:tags":[
        "pubs",
        "inn"
    ],
    "wof:name":"The Half Moon Inn",
    "wof:placetype":"venue"
},
  "geometry": {"coordinates":[-3.563879,50.443504],"type":"Point"}
}