{
  "type": "Feature",
  "properties": {
    "addr:full":"77 Springfield Rd, Wickersley Rotherham South Yorkshire S66 2DQ",
    "addr:housenumber":"77",
    "addr:postcode":"s66 2dq",
    "addr:street":"Springfield Rd",
    "iso:country":"GB",
    "sg:address":"77 Springfield Rd, Wickersley",
    "sg:city":"Rotherham",
    "sg:classifiers":[
        {
            "category":"Building & Trades",
            "subcategory":"Plumbing",
            "type":"Services"
        }
    ],
    "sg:postcode":"S66 2DQ",
    "sg:province":"South Yorkshire",
    "sg:tags":[
        "heating"
    ],
    "wof:name":"D L Plumbing",
    "wof:placetype":"venue"
},
  "geometry": {"coordinates":[-1.291206,53.423347],"type":"Point"}
}