{
  "type": "Feature",
  "properties": {
    "iso:country":"GB",
    "sg:address":"Barr Street",
    "sg:city":"Ardrossan",
    "sg:classifiers":[
        {
            "category":"Social Services",
            "subcategory":"Adult Care",
            "type":"Services"
        }
    ],
    "sg:phone":"+44 1294 602538",
    "sg:postcode":"KA22 8HJ",
    "sg:province":"North Ayrshire",
    "sg:tags":[
        "housing",
        "sheltered"
    ],
    "wof:name":"Currie Court Sheltered Housing",
    "wof:placetype":"venue"
},
  "geometry": {"coordinates":[-4.8133039474,55.6438064575],"type":"Point"}
}