{
  "type": "Feature",
  "properties": {
    "iso:country":"GB",
    "sg:address":"Plot 7a, Clwydfro Business Centre, Lon Parcwr Ind Est",
    "sg:city":"Ruthin",
    "sg:classifiers":[
        {
            "category":"Professional",
            "subcategory":"Business Services",
            "type":"Services"
        }
    ],
    "sg:phone":"+44 1824 705782",
    "sg:postcode":"LL15 1NJ",
    "sg:province":"Denbighshire",
    "sg:tags":[
        "accomodation"
    ],
    "wof:name":"Clwydfro Enterprise Agency",
    "wof:placetype":"venue"
},
  "geometry": {"coordinates":[-3.304522,53.114017],"type":"Point"}
}