{
  "type": "Feature",
  "properties": {
    "iso:country":"GB",
    "sg:address":"Unit 11, Hooe Farm",
    "sg:city":"Arundel",
    "sg:classifiers":[
        {
            "category":"Professional",
            "subcategory":"Art Services",
            "type":"Services"
        }
    ],
    "sg:postcode":"BN18 0LU",
    "sg:province":"West Sussex",
    "sg:tags":[
        "framing"
    ],
    "wof:name":"S J Paige Frames",
    "wof:placetype":"venue"
},
  "geometry": {"coordinates":[-0.554589,50.854836],"type":"Point"}
}