{
  "type": "Feature",
  "properties": {
    "addr:full":"Barn Farm, Heath Road Billericay Essex CM11 1LZ",
    "addr:postcode":"cm11 1lz",
    "addr:street":"Heath Road",
    "iso:country":"GB",
    "sg:address":"Barn Farm, Heath Road",
    "sg:city":"Billericay",
    "sg:classifiers":[
        {
            "category":"Building & Trades",
            "subcategory":"Construction",
            "type":"Services"
        }
    ],
    "sg:phone":"+44 1268 711446",
    "sg:postcode":"CM11 1LZ",
    "sg:province":"Essex",
    "sg:tags":[
        "builder"
    ],
    "wof:name":"John M Kleider",
    "wof:placetype":"venue"
},
  "geometry": {"coordinates":[0.46951,51.63567],"type":"Point"}
}