{
  "type": "Feature",
  "properties": {
    "iso:country":"GB",
    "sg:address":"10 The Gallop",
    "sg:city":"South Croydon",
    "sg:classifiers":[
        {
            "category":"Professional",
            "subcategory":"Engineering",
            "type":"Services"
        }
    ],
    "sg:phone":"+44 20 8651 4555",
    "sg:postcode":"CR2 7LP",
    "sg:province":"Surrey",
    "sg:tags":[
        "engineer",
        "mechanical"
    ],
    "wof:name":"Alpha Building Services Ltd.",
    "wof:placetype":"venue"
},
  "geometry": {"coordinates":[-0.0641499981,51.3529396057],"type":"Point"}
}