{
  "type": "Feature",
  "properties": {
    "iso:country":"GB",
    "sg:address":"6-7 The Lanes Shopping Centre, Birmingham Road",
    "sg:city":"Sutton Coldfield",
    "sg:classifiers":[
        {
            "category":"Sports & Exercise",
            "subcategory":"Sports Center",
            "type":"Entertainment"
        }
    ],
    "sg:postcode":"B72 1YG",
    "sg:province":"West Midlands",
    "sg:tags":[
        "shop",
        "good"
    ],
    "wof:name":"Sports & Leisure World Ltd.",
    "wof:placetype":"venue"
},
  "geometry": {"coordinates":[-1.825695,52.543568],"type":"Point"}
}