{
  "type": "Feature",
  "properties": {
    "iso:country":"GB",
    "sg:address":"Ashdale, Blacksmiths Lane, Reed",
    "sg:city":"Royston",
    "sg:classifiers":[
        {
            "category":"Professional",
            "subcategory":"Computer Services",
            "type":"Services"
        }
    ],
    "sg:phone":"+44 1763 848437",
    "sg:postcode":"SG8 8AY",
    "sg:province":"Bedfordshire",
    "sg:tags":[
        "system",
        "software"
    ],
    "wof:name":"Voicebrand Ltd.",
    "wof:placetype":"venue"
},
  "geometry": {"coordinates":[-0.024611,52.0071144104],"type":"Point"}
}