{
  "type": "Feature",
  "properties": {
    "iso:country":"GB",
    "sg:address":"647 South Promenade",
    "sg:city":"Blackpool",
    "sg:classifiers":[
        {
            "category":"Social Services",
            "subcategory":"Retirement Home",
            "type":"Services"
        }
    ],
    "sg:phone":"+44 1253 349589",
    "sg:postcode":"FY4 1RN",
    "sg:province":"Lancashire",
    "sg:tags":[
        "rest"
    ],
    "wof:name":"Whittingham Property Ltd.",
    "wof:placetype":"venue"
},
  "geometry": {"coordinates":[-3.05713,53.781872],"type":"Point"}
}