{
  "type": "Feature",
  "properties": {
    "addr:full":"Unit 1a Thackley Court, Thackley Old Road Shipley West Yorkshire BD18 1BW",
    "addr:housenumber":"unit 1a",
    "addr:postcode":"bd18 1bw",
    "addr:street":"Thackley Court;Old Road",
    "iso:country":"GB",
    "sg:address":"Unit 1a Thackley Court, Thackley Old Road",
    "sg:city":"Shipley",
    "sg:classifiers":[
        {
            "category":"Wholesale",
            "subcategory":"Electrical",
            "type":"Manufacturing & Wholesale Goods"
        },
        {
            "category":"Shopping",
            "subcategory":"Computers & Home Electronics",
            "type":"Retail Goods"
        }
    ],
    "sg:phone":"+44 1274 531289",
    "sg:postcode":"BD18 1BW",
    "sg:province":"West Yorkshire",
    "sg:tags":[
        "wholesaler"
    ],
    "wof:name":"City Electrical Factors Ltd",
    "wof:placetype":"venue"
},
  "geometry": {"coordinates":[-1.7532680035,53.8400764465],"type":"Point"}
}