{
  "type": "Feature",
  "properties": {
    "addr:full":"Greenleighton, Longwitton Morpeth Northumberland NE61 4JZ",
    "addr:postcode":"ne61 4jz",
    "addr:street":"Northumberland",
    "iso:country":"GB",
    "sg:address":"Greenleighton, Longwitton",
    "sg:city":"Morpeth",
    "sg:classifiers":[
        {
            "category":"Farming",
            "subcategory":"Livestock Farm",
            "type":"Manufacturing & Wholesale Goods"
        }
    ],
    "sg:phone":"+44 1670 774663",
    "sg:postcode":"NE61 4JZ",
    "sg:province":"Northumberland",
    "sg:tags":[
        "others"
    ],
    "wof:name":"G & S Paxton",
    "wof:placetype":"venue"
},
  "geometry": {"coordinates":[-1.8753709793,55.1936988831],"type":"Point"}
}