{
  "type": "Feature",
  "properties": {
    "iso:country":"GB",
    "sg:address":"163 College Road",
    "sg:city":"Rotherham",
    "sg:classifiers":[
        {
            "category":"Travel",
            "subcategory":"Hotels & Motels",
            "type":"Entertainment"
        }
    ],
    "sg:phone":"+44 1709 561611",
    "sg:postcode":"S60 1JA",
    "sg:province":"South Yorkshire",
    "wof:name":"Corona Hotel",
    "wof:placetype":"venue"
},
  "geometry": {"coordinates":[-1.3698259592,53.4316291809],"type":"Point"}
}