{
  "type": "Feature",
  "properties": {
    "addr:full":"172 Holton Road Barry The Vale of Glamorgan CF63 4HN",
    "addr:housenumber":"172",
    "addr:postcode":"cf63 4hn",
    "addr:street":"Holton Road;Vale",
    "iso:country":"GB",
    "sg:address":"172 Holton Road",
    "sg:city":"Barry",
    "sg:classifiers":[
        {
            "category":"Shopping",
            "subcategory":"Florist",
            "type":"Retail Goods"
        }
    ],
    "sg:phone":"+44 1446 733685",
    "sg:postcode":"CF63 4HN",
    "sg:province":"The Vale of Glamorgan",
    "wof:name":"F C Ball",
    "wof:placetype":"venue"
},
  "geometry": {"coordinates":[-3.2653839588,51.4063072205],"type":"Point"}
}