{
  "type": "Feature",
  "properties": {
    "iso:country":"GB",
    "sg:address":"27 Hillside Avenue",
    "sg:city":"Blackburn",
    "sg:classifiers":[
        {
            "category":"Bus Charters",
            "type":"Transportation"
        }
    ],
    "sg:phone":"+44 1254 399019",
    "sg:postcode":"BB1 2BB",
    "sg:province":"Lancashire",
    "sg:tags":[
        "hire",
        "coach"
    ],
    "wof:name":"Red Rose Travel",
    "wof:placetype":"venue"
},
  "geometry": {"coordinates":[-2.448594,53.745705],"type":"Point"}
}