{
  "type": "Feature",
  "properties": {
    "addr:full":"Warren Parc, Penegoes Machynlleth Ceredigion SY20 8NN",
    "addr:postcode":"sy20 8nn",
    "iso:country":"GB",
    "sg:address":"Warren Parc, Penegoes",
    "sg:city":"Machynlleth",
    "sg:classifiers":[
        {
            "category":"Train Station",
            "subcategory":"Rail",
            "type":"Transportation"
        }
    ],
    "sg:phone":"+44 1654 702054",
    "sg:postcode":"SY20 8NN",
    "sg:province":"Ceredigion",
    "sg:tags":[
        "caravan"
    ],
    "wof:name":"Warren Parc Leisure Ltd.",
    "wof:placetype":"venue"
},
  "geometry": {"coordinates":[-3.8467230797,52.5909614563],"type":"Point"}
}