{
  "type": "Feature",
  "properties": {
    "iso:country":"GB",
    "sg:address":"20b Seabrook Rd",
    "sg:city":"Tonbridge",
    "sg:classifiers":[
        {
            "category":"Shopping",
            "subcategory":"Party Supplies",
            "type":"Retail Goods"
        }
    ],
    "sg:postcode":"TN10 3AS",
    "sg:province":"Kent",
    "sg:tags":[
        "inflatables",
        "bouncy",
        "castle"
    ],
    "wof:name":"Boogie Bouncers",
    "wof:placetype":"venue"
},
  "geometry": {"coordinates":[0.265049994,51.2041320801],"type":"Point"}
}