{
  "type": "Feature",
  "properties": {
    "addr:full":"Lingard Lane, Bredbury Park Industrial Estate, Bredbury Stockport Cheshire SK6 2RN",
    "addr:postcode":"sk6 2rn",
    "addr:street":"Lingard Lane Bredbury Park Industrial;Bredbury",
    "iso:country":"GB",
    "sg:address":"Lingard Lane, Bredbury Park Industrial Estate, Bredbury",
    "sg:city":"Stockport",
    "sg:classifiers":[
        {
            "category":"Utilities",
            "subcategory":"Refuse",
            "type":"Services"
        }
    ],
    "sg:phone":"+44 161 430 5650",
    "sg:postcode":"SK6 2RN",
    "sg:province":"Cheshire",
    "sg:tags":[
        "skip",
        "hire"
    ],
    "wof:name":"Owen Skip Hire Ltd.",
    "wof:placetype":"venue"
},
  "geometry": {"coordinates":[-2.1251590252,53.4287605286],"type":"Point"}
}