{
  "type": "Feature",
  "properties": {
    "iso:country":"GB",
    "sg:address":"Essex County Cricket Club, County Ground, New Writtle St",
    "sg:city":"Chelmsford",
    "sg:classifiers":[
        {
            "category":"Sports & Exercise",
            "subcategory":"Sports Center",
            "type":"Entertainment"
        }
    ],
    "sg:phone":"+44 1245 252420",
    "sg:postcode":"CM2 0PG",
    "sg:province":"Essex",
    "sg:tags":[
        "shop",
        "good"
    ],
    "wof:name":"Essex Shop The",
    "wof:placetype":"venue"
},
  "geometry": {"coordinates":[0.477891,51.731918],"type":"Point"}
}