{
  "type": "Feature",
  "properties": {
    "addr:full":"23 Roundmoor Dr Waltham Cross Essex EN8 9HZ",
    "addr:housenumber":"23",
    "addr:postcode":"en8 9hz",
    "addr:street":"Roundmoor Dr",
    "iso:country":"GB",
    "sg:address":"23 Roundmoor Dr",
    "sg:city":"Waltham Cross",
    "sg:classifiers":[
        {
            "category":"Retail",
            "subcategory":"Storage",
            "type":"Services"
        }
    ],
    "sg:phone":"+44 20 8804 4143",
    "sg:postcode":"EN8 9HZ",
    "sg:province":"Essex",
    "sg:tags":[
        "household",
        "removal"
    ],
    "wof:name":"Marsh & Sons",
    "wof:placetype":"venue"
},
  "geometry": {"coordinates":[-0.028801,51.704105],"type":"Point"}
}