{
  "type": "Feature",
  "properties": {
    "addr:full":"114 Mutton Lane Potters Bar Greater London EN6 2HE",
    "addr:housenumber":"114",
    "addr:postcode":"en6 2he",
    "addr:street":"Mutton Lane",
    "iso:country":"GB",
    "sg:address":"114 Mutton Lane",
    "sg:city":"Potters Bar",
    "sg:classifiers":[
        {
            "category":"Organizations",
            "subcategory":"Non-profit Organization",
            "type":"Services"
        }
    ],
    "sg:phone":"+44 1707 655493",
    "sg:postcode":"EN6 2HE",
    "sg:province":"Greater London",
    "sg:tags":[
        "organisation",
        "voluntary",
        "charity"
    ],
    "wof:name":"British Red Cross",
    "wof:placetype":"venue"
},
  "geometry": {"coordinates":[-0.185139,51.693188],"type":"Point"}
}