{
  "type": "Feature",
  "properties": {
    "addr:full":"White Lodge, The Drive Banstead Surrey SM7 1DA",
    "addr:postcode":"sm7 1da",
    "addr:street":"The Drive",
    "iso:country":"GB",
    "sg:address":"White Lodge, The Drive",
    "sg:city":"Banstead",
    "sg:classifiers":[
        {
            "category":"Organizations",
            "subcategory":"Non-profit Organization",
            "type":"Services"
        }
    ],
    "sg:phone":"+44 1737 356077",
    "sg:postcode":"SM7 1DA",
    "sg:province":"Surrey",
    "sg:tags":[
        "organisation",
        "voluntary",
        "charity"
    ],
    "wof:name":"British Red Cross Society",
    "wof:placetype":"venue"
},
  "geometry": {"coordinates":[-0.200601995,51.3228225708],"type":"Point"}
}