{
  "type": "Feature",
  "properties": {
    "addr:full":"Glan-yr-afon Industrial Estate Aberystwyth Ceredigion SY23 3JQ",
    "addr:postcode":"sy23 3jq",
    "addr:street":"Estate",
    "iso:country":"GB",
    "sg:address":"Glan-yr-afon Industrial Estate",
    "sg:city":"Aberystwyth",
    "sg:classifiers":[
        {
            "category":"Home & Garden",
            "subcategory":"Building Materials",
            "type":"Retail Goods"
        },
        {
            "category":"Shopping",
            "type":"Retail Goods"
        }
    ],
    "sg:phone":"+44 1970 611919",
    "sg:postcode":"SY23 3JQ",
    "sg:province":"Ceredigion",
    "sg:tags":[
        "merchant",
        "gate",
        "door",
        "barrier"
    ],
    "wof:name":"Mount Trading Co. Ltd.",
    "wof:placetype":"venue"
},
  "geometry": {"coordinates":[-4.059997,52.406124],"type":"Point"}
}