{
  "type": "Feature",
  "properties": {
    "addr:full":"France House, Digbeth St, Stow On The Wold Cheltenham Gloucestershire GL54 1BN",
    "addr:postcode":"gl54 1bn",
    "addr:street":"Digbeth St",
    "iso:country":"GB",
    "sg:address":"France House, Digbeth St, Stow On The Wold",
    "sg:city":"Cheltenham",
    "sg:classifiers":[
        {
            "category":"Manufacturing",
            "subcategory":"Furniture",
            "type":"Manufacturing & Wholesale Goods"
        }
    ],
    "sg:phone":"+44 1451 830308",
    "sg:postcode":"GL54 1BN",
    "sg:province":"Gloucestershire",
    "sg:tags":[
        "mnfr",
        "garden",
        "patio"
    ],
    "wof:name":"The Wadham Trading Co",
    "wof:placetype":"venue"
},
  "geometry": {"coordinates":[-1.721868,51.929626],"type":"Point"}
}