{
  "type": "Feature",
  "properties": {
    "iso:country":"GB",
    "sg:address":"213 Long Lane",
    "sg:city":"Bexleyheath",
    "sg:classifiers":[
        {
            "category":"Professional",
            "subcategory":"Computer Services",
            "type":"Services"
        }
    ],
    "sg:phone":"+44 20 8306 1515",
    "sg:postcode":"DA7 5JB",
    "sg:province":"Kent",
    "sg:tags":[
        "system",
        "software"
    ],
    "wof:name":"J R B S Ltd.",
    "wof:placetype":"venue"
},
  "geometry": {"coordinates":[0.141687,51.468075],"type":"Point"}
}