{
  "type": "Feature",
  "properties": {
    "addr:full":"33 Queens Avenue Widnes Cheshire WA8 8HR",
    "addr:housenumber":"33",
    "addr:postcode":"wa8 8hr",
    "addr:street":"Queens Avenue",
    "iso:country":"GB",
    "sg:address":"33 Queens Avenue",
    "sg:city":"Widnes",
    "sg:classifiers":[
        {
            "category":"Food & Beverages",
            "subcategory":"Meat & Fish",
            "type":"Retail Goods"
        }
    ],
    "sg:phone":"+44 151 424 4534",
    "sg:postcode":"WA8 8HR",
    "sg:province":"Cheshire",
    "sg:tags":[
        "butcher"
    ],
    "wof:name":"S Fogarty",
    "wof:placetype":"venue"
},
  "geometry": {"coordinates":[-2.7695169449,53.3679695129],"type":"Point"}
}