{
  "type": "Feature",
  "properties": {
    "addr:full":"Highlands Farm, Gravenhurst Road, Campton Shefford Bedfordshire SG17 5NZ",
    "addr:postcode":"sg17 5nz",
    "addr:street":"Gravenhurst Road",
    "iso:country":"GB",
    "sg:address":"Highlands Farm, Gravenhurst Road, Campton",
    "sg:city":"Shefford",
    "sg:classifiers":[
        {
            "category":"Building & Trades",
            "subcategory":"Landscaping Services",
            "type":"Services"
        }
    ],
    "sg:phone":"+44 1462 813301",
    "sg:postcode":"SG17 5NZ",
    "sg:province":"Bedfordshire",
    "sg:tags":[
        "horticultural",
        "consultant"
    ],
    "wof:name":"J J & B Engineering",
    "wof:placetype":"venue"
},
  "geometry": {"coordinates":[-0.334879,52.04134],"type":"Point"}
}