{
  "type": "Feature",
  "properties": {
    "iso:country":"GB",
    "sg:address":"19 George St",
    "sg:city":"Perth",
    "sg:classifiers":[
        {
            "category":"Sports & Exercise",
            "subcategory":"Gym",
            "type":"Entertainment"
        }
    ],
    "sg:phone":"+44 1738 447744",
    "sg:postcode":"PH1 5JY",
    "sg:province":"Perth and Kinross",
    "sg:tags":[
        "fitness",
        "health",
        "centre"
    ],
    "wof:name":"Ivy Court Leisure Club",
    "wof:placetype":"venue"
},
  "geometry": {"coordinates":[-3.4271531105,56.3973846436],"type":"Point"}
}