{
  "type": "Feature",
  "properties": {
    "addr:full":"30a Melton Rd Leicester Leicestershire LE4 5EA",
    "addr:housenumber":"30a",
    "addr:postcode":"le4 5ea",
    "addr:street":"Melton Rd",
    "iso:country":"GB",
    "sg:address":"30a Melton Rd",
    "sg:city":"Leicester",
    "sg:classifiers":[
        {
            "category":"Retail",
            "subcategory":"Auto Repair",
            "type":"Services"
        }
    ],
    "sg:postcode":"LE4 5EA",
    "sg:province":"Leicestershire",
    "sg:tags":[
        "modification",
        "garage"
    ],
    "wof:name":"Bishop,Glenn,",
    "wof:placetype":"venue"
},
  "geometry": {"coordinates":[-1.120862,52.652195],"type":"Point"}
}