{
  "type": "Feature",
  "properties": {
    "addr:full":"16-17 Cornmarket Thame Buckinghamshire OX9 2BW",
    "addr:housenumber":"16-17",
    "addr:postcode":"ox9 2bw",
    "addr:street":"Cornmarket Thame",
    "iso:country":"GB",
    "sg:address":"16-17 Cornmarket",
    "sg:city":"Thame",
    "sg:classifiers":[
        {
            "category":"Travel",
            "subcategory":"Hotels & Motels",
            "type":"Entertainment"
        }
    ],
    "sg:phone":"+44 1844 213661",
    "sg:postcode":"OX9 2BW",
    "sg:province":"Buckinghamshire",
    "wof:name":"The Spread Eagle Hotel (Thame) Ltd.",
    "wof:placetype":"venue"
},
  "geometry": {"coordinates":[-0.977787,51.746941],"type":"Point"}
}