{
  "type": "Feature",
  "properties": {
    "addr:full":"2 Endgain Drive, Shenley Church End Milton Keynes Buckinghamshire MK5 6JY",
    "addr:housenumber":"2",
    "addr:postcode":"mk5 6jy",
    "addr:street":"Endgain Drive",
    "iso:country":"GB",
    "sg:address":"2 Endgain Drive, Shenley Church End",
    "sg:city":"Milton Keynes",
    "sg:classifiers":[
        {
            "category":"Community Center",
            "type":"Public Place"
        }
    ],
    "sg:phone":"+44 1908 503344",
    "sg:postcode":"MK5 6JY",
    "sg:province":"Buckinghamshire",
    "sg:tags":[
        "recreation",
        "leisure",
        "centre"
    ],
    "wof:name":"Splashdown Milton Keynes Ltd.",
    "wof:placetype":"venue"
},
  "geometry": {"coordinates":[-0.797313,52.021435],"type":"Point"}
}