{
  "type": "Feature",
  "properties": {
    "iso:country":"GB",
    "sg:address":"Salthouse Road",
    "sg:city":"Millom",
    "sg:classifiers":[
        {
            "category":"Education",
            "subcategory":"School",
            "type":"Public Place"
        }
    ],
    "sg:phone":"+44 1229 772300",
    "sg:postcode":"LA18 5AB",
    "sg:province":"Cumbria",
    "sg:tags":[
        "local",
        "authority"
    ],
    "wof:name":"Millom School",
    "wof:placetype":"venue"
},
  "geometry": {"coordinates":[-3.268289,54.215618],"type":"Point"}
}