{
  "type": "Feature",
  "properties": {
    "addr:full":"Unit 3 Greens Court, Manners Avenue, Manners Industrial Estate Ilkeston Derbyshire DE7 8EF",
    "addr:housenumber":"unit 3",
    "addr:postcode":"de7 8ef",
    "addr:street":"Greens Court Manners Avenue Manners Industrial Estate",
    "iso:country":"GB",
    "sg:address":"Unit 3 Greens Court, Manners Avenue, Manners Industrial Estate",
    "sg:city":"Ilkeston",
    "sg:classifiers":[
        {
            "category":"Manufacturing",
            "subcategory":"Wood Products",
            "type":"Manufacturing & Wholesale Goods"
        },
        {
            "category":"Building & Trades",
            "subcategory":"Construction",
            "type":"Services"
        }
    ],
    "sg:phone":"+44 115 944 4650",
    "sg:postcode":"DE7 8EF",
    "sg:province":"Derbyshire",
    "sg:tags":[
        "joinery",
        "manufacturer"
    ],
    "wof:name":"Ilkeston Joinery Ltd",
    "wof:placetype":"venue"
},
  "geometry": {"coordinates":[-1.309729,52.977039],"type":"Point"}
}