{
  "type": "Feature",
  "properties": {
    "iso:country":"GB",
    "sg:address":"Sherwood Drive, Bletchley",
    "sg:city":"Milton Keynes",
    "sg:classifiers":[
        {
            "category":"Education",
            "subcategory":"University",
            "type":"Public Place"
        }
    ],
    "sg:phone":"+44 1908 684444",
    "sg:postcode":"MK3 6DR",
    "sg:province":"Buckinghamshire",
    "sg:tags":[
        "higher"
    ],
    "wof:name":"Milton Keynes College",
    "wof:placetype":"venue"
},
  "geometry": {"coordinates":[-0.7381759882,51.9985198975],"type":"Point"}
}