{
  "type": "Feature",
  "properties": {
    "addr:full":"12a Beaverhall Rd Edinburgh City of Edinburgh EH7 4JE",
    "addr:housenumber":"12a",
    "addr:postcode":"eh7 4je",
    "addr:street":"Beaverhall Rd",
    "iso:country":"GB",
    "sg:address":"12a Beaverhall Rd",
    "sg:city":"Edinburgh",
    "sg:classifiers":[
        {
            "category":"Professional",
            "subcategory":"Advertising",
            "type":"Services"
        }
    ],
    "sg:phone":"+44 131 558 3558",
    "sg:postcode":"EH7 4JE",
    "sg:province":"City of Edinburgh",
    "wof:name":"Nationwide Discount Vouchers Edinburgh",
    "wof:placetype":"venue"
},
  "geometry": {"coordinates":[-3.196203,55.968159],"type":"Point"}
}