{
  "type": "Feature",
  "properties": {
    "addr:full":"2 Railway Road, Urmston Manchester Cheshire M41 0XL",
    "addr:housenumber":"2",
    "addr:postcode":"m41 0xl",
    "addr:street":"Railway Road",
    "iso:country":"GB",
    "sg:address":"2 Railway Road, Urmston",
    "sg:city":"Manchester",
    "sg:classifiers":[
        {
            "category":"Personal",
            "subcategory":"Beauty Salon",
            "type":"Services"
        }
    ],
    "sg:phone":"+44 161 755 3282",
    "sg:postcode":"M41 0XL",
    "sg:province":"Cheshire",
    "sg:tags":[
        "unisex",
        "hairdresser"
    ],
    "wof:name":"Clipinn",
    "wof:placetype":"venue"
},
  "geometry": {"coordinates":[-2.352694,53.448822],"type":"Point"}
}