{
  "type": "Feature",
  "properties": {
    "iso:country":"GB",
    "sg:address":"33 Railway Road",
    "sg:city":"Darwen",
    "sg:classifiers":[
        {
            "category":"Professional",
            "subcategory":"Lawyer & Legal Services",
            "type":"Services"
        }
    ],
    "sg:phone":"+44 1254 774914",
    "sg:postcode":"BB3 2RL",
    "sg:province":"Lancashire",
    "sg:tags":[
        "solicitor"
    ],
    "wof:name":"John Fish & Co.",
    "wof:placetype":"venue"
},
  "geometry": {"coordinates":[-2.465379,53.696831],"type":"Point"}
}