{
  "type": "Feature",
  "properties": {
    "iso:country":"GB",
    "sg:address":"40 London Road, Shenley",
    "sg:city":"Radlett",
    "sg:classifiers":[
        {
            "category":"Shopping",
            "subcategory":"Department Store",
            "type":"Retail Goods"
        },
        {
            "category":"Government",
            "subcategory":"Post Office",
            "type":"Public Place"
        }
    ],
    "sg:phone":"+44 1923 856152",
    "sg:postcode":"WD7 9EN",
    "sg:province":"Hertfordshire",
    "wof:name":"Shelley Stores and Post Office",
    "wof:placetype":"venue"
},
  "geometry": {"coordinates":[-0.282001,51.692879],"type":"Point"}
}