{
  "type": "Feature",
  "properties": {
    "addr:full":"Adamson House, Green Lane, Hotham York East Riding of Yorkshire YO43 4UJ",
    "addr:postcode":"yo43 4uj",
    "addr:street":"Green Lane",
    "iso:country":"GB",
    "sg:address":"Adamson House, Green Lane, Hotham",
    "sg:city":"York",
    "sg:classifiers":[
        {
            "category":"Professional",
            "subcategory":"Lawyer & Legal Services",
            "type":"Services"
        }
    ],
    "sg:phone":"+44 1430 421080",
    "sg:postcode":"YO43 4UJ",
    "sg:province":"East Riding of Yorkshire",
    "sg:tags":[
        "solicitor"
    ],
    "wof:name":"Phillip Conyers",
    "wof:placetype":"venue"
},
  "geometry": {"coordinates":[-0.643799,53.798977],"type":"Point"}
}