{
  "type": "Feature",
  "properties": {
    "addr:full":"71 Selworthy Drive Crewe Cheshire CW1 3RS",
    "addr:housenumber":"71",
    "addr:postcode":"cw1 3rs",
    "addr:street":"Selworthy Drive",
    "iso:country":"GB",
    "sg:address":"71 Selworthy Drive",
    "sg:city":"Crewe",
    "sg:classifiers":[
        {
            "category":"Arts & Performance",
            "subcategory":"Music",
            "type":"Entertainment"
        }
    ],
    "sg:phone":"+44 1270 582207",
    "sg:postcode":"CW1 3RS",
    "sg:province":"Cheshire",
    "sg:tags":[
        "mobile",
        "disco"
    ],
    "wof:name":"R J's Discos Karaoke",
    "wof:placetype":"venue"
},
  "geometry": {"coordinates":[-2.456483,53.112701],"type":"Point"}
}