{
  "type": "Feature",
  "properties": {
    "addr:full":"Higher Clenston Farm Blandford Forum Dorset DT11 0NX",
    "addr:housenumber":"blandford forum",
    "addr:postcode":"dt11 0nx",
    "iso:country":"GB",
    "sg:address":"Higher Clenston Farm",
    "sg:city":"Blandford Forum",
    "sg:classifiers":[
        {
            "category":"Autos & Motor Vehicles",
            "subcategory":"Auto Supplies",
            "type":"Retail Goods"
        }
    ],
    "sg:phone":"+44 1258 880440",
    "sg:postcode":"DT11 0NX",
    "sg:province":"Dorset",
    "sg:tags":[
        "gearbox"
    ],
    "wof:name":"Major Units",
    "wof:placetype":"venue"
},
  "geometry": {"coordinates":[-2.158819,50.862644],"type":"Point"}
}