{
  "type": "Feature",
  "properties": {
    "iso:country":"GB",
    "sg:address":"Galston Road, Hurlford",
    "sg:city":"Kilmarnock",
    "sg:classifiers":[
        {
            "category":"Building & Trades",
            "subcategory":"Construction",
            "type":"Services"
        }
    ],
    "sg:postcode":"KA1 5JD",
    "sg:province":"East Ayrshire",
    "sg:tags":[
        "equipment"
    ],
    "wof:name":"James Hamilton",
    "wof:placetype":"venue"
},
  "geometry": {"coordinates":[-4.4569540024,55.6008491516],"type":"Point"}
}