{
  "type": "Feature",
  "properties": {
    "iso:country":"GB",
    "sg:address":"12 Sauchiebank",
    "sg:city":"Edinburgh",
    "sg:classifiers":[
        {
            "category":"Banks & Credit Unions",
            "subcategory":"Bureau De Change",
            "type":"Services"
        },
        {
            "category":"Building & Trades",
            "subcategory":"Construction",
            "type":"Services"
        }
    ],
    "sg:phone":"+44 131 337 0555",
    "sg:postcode":"EH11 2NN",
    "sg:province":"City of Edinburgh",
    "sg:tags":[
        "paint",
        "varnish",
        "decorator",
        "remover",
        "painter"
    ],
    "wof:name":"Dip 'N' Strip",
    "wof:placetype":"venue"
},
  "geometry": {"coordinates":[-3.2269179821,55.9431114197],"type":"Point"}
}