{
  "type": "Feature",
  "properties": {
    "addr:full":"Cameo House London Greater London WC2H 7AS",
    "addr:postcode":"wc2h 7as",
    "iso:country":"GB",
    "sg:address":"Cameo House",
    "sg:city":"London",
    "sg:classifiers":[
        {
            "category":"Shopping",
            "subcategory":"Books",
            "type":"Retail Goods"
        }
    ],
    "sg:postcode":"WC2H 7AS",
    "sg:province":"Greater London",
    "wof:name":"Graham Hodges",
    "wof:placetype":"venue"
},
  "geometry": {"coordinates":[-0.1288940012,51.5117263794],"type":"Point"}
}