{
  "type": "Feature",
  "properties": {
    "addr:full":"Care Of Sciamed, Woodburn Road, Blackburn Industrial Estate Aberdeen Aberdeen City AB21 0RX",
    "addr:postcode":"ab21 0rx",
    "addr:street":"Woodburn Road;Industrial Estate",
    "iso:country":"GB",
    "sg:address":"Care Of Sciamed, Woodburn Road, Blackburn Industrial Estate",
    "sg:city":"Aberdeen",
    "sg:classifiers":[
        {
            "category":"Wholesale",
            "subcategory":"Medical Equipment & Supplies",
            "type":"Manufacturing & Wholesale Goods"
        }
    ],
    "sg:phone":"+44 1224 791179",
    "sg:postcode":"AB21 0RX",
    "sg:province":"Aberdeen City",
    "sg:tags":[
        "dental"
    ],
    "wof:name":"C E I Castellini Enterprises (North)",
    "wof:placetype":"venue"
},
  "geometry": {"coordinates":[-2.288230896,57.2036743164],"type":"Point"}
}