{
  "type": "Feature",
  "properties": {
    "addr:full":"1 Station Avenue Filey North Yorkshire YO14 9AH",
    "addr:housenumber":"1",
    "addr:postcode":"yo14 9ah",
    "addr:street":"Station Avenue",
    "iso:country":"GB",
    "sg:address":"1 Station Avenue",
    "sg:city":"Filey",
    "sg:classifiers":[
        {
            "category":"Retail",
            "subcategory":"Veterinary Services",
            "type":"Services"
        }
    ],
    "sg:phone":"+44 1723 513119",
    "sg:postcode":"YO14 9AH",
    "sg:province":"North Yorkshire",
    "sg:tags":[
        "surgeon",
        "activity"
    ],
    "wof:name":"The Veterinary Centre",
    "wof:placetype":"venue"
},
  "geometry": {"coordinates":[-0.2937569916,54.2108612061],"type":"Point"}
}