{
  "type": "Feature",
  "properties": {
    "iso:country":"GB",
    "sg:address":"368 High Street, Harborne",
    "sg:city":"Birmingham",
    "sg:classifiers":[
        {
            "category":"Shopping",
            "subcategory":"Pharmacy",
            "type":"Retail Goods"
        }
    ],
    "sg:phone":"+44 121 427 8565",
    "sg:postcode":"B17 9PY",
    "sg:province":"West Midlands",
    "sg:tags":[
        "pharmacist",
        "dispensing",
        "chemist"
    ],
    "wof:name":"R E Walker",
    "wof:placetype":"venue"
},
  "geometry": {"coordinates":[-1.9573669434,52.4578552246],"type":"Point"}
}