{
  "type": "Feature",
  "properties": {
    "iso:country":"GB",
    "sg:address":"5 Whitegate Drive",
    "sg:city":"Blackpool",
    "sg:classifiers":[
        {
            "category":"Personal",
            "subcategory":"Beauty Salon",
            "type":"Services"
        }
    ],
    "sg:postcode":"FY3 9AE",
    "sg:province":"Lancashire",
    "wof:name":"Ethos Beauty",
    "wof:placetype":"venue"
},
  "geometry": {"coordinates":[-3.038038,53.817928],"type":"Point"}
}