{
  "type": "Feature",
  "properties": {
    "addr:full":"19 Montpelier Ave Bexley Kent DA5 3AP",
    "addr:housenumber":"19",
    "addr:postcode":"da5 3ap",
    "addr:street":"Montpelier Ave",
    "iso:country":"GB",
    "sg:address":"19 Montpelier Ave",
    "sg:city":"Bexley",
    "sg:classifiers":[
        {
            "category":"Retail",
            "subcategory":"Repair Shop",
            "type":"Services"
        }
    ],
    "sg:postcode":"DA5 3AP",
    "sg:province":"Kent",
    "sg:tags":[
        "plant",
        "machinery"
    ],
    "wof:name":"Abra Plant Services",
    "wof:placetype":"venue"
},
  "geometry": {"coordinates":[0.1255519986,51.4422035217],"type":"Point"}
}