{
  "type": "Feature",
  "properties": {
    "addr:full":"Abercrai, Trecastle Cardiff Caerphilly CF3 8RB",
    "addr:postcode":"cf3 8rb",
    "iso:country":"GB",
    "sg:address":"Abercrai, Trecastle",
    "sg:city":"Cardiff",
    "sg:classifiers":[
        {
            "category":"Banks & Credit Unions",
            "subcategory":"Investment Brokerage",
            "type":"Services"
        }
    ],
    "sg:phone":"+44 1874 636866",
    "sg:postcode":"CF3 8RB",
    "sg:province":"Caerphilly",
    "sg:tags":[
        "contractor"
    ],
    "wof:name":"Tymms Contracting",
    "wof:placetype":"venue"
},
  "geometry": {"coordinates":[-3.0919098854,51.5330505371],"type":"Point"}
}