{
  "type": "Feature",
  "properties": {
    "addr:full":"The Drive, Warley Brentwood Essex CM13 3BE",
    "addr:postcode":"cm13 3be",
    "addr:street":"The Drive",
    "iso:country":"GB",
    "sg:address":"The Drive, Warley",
    "sg:city":"Brentwood",
    "sg:classifiers":[
        {
            "category":"Utilities",
            "subcategory":"Refuse",
            "type":"Services"
        }
    ],
    "sg:phone":"+44 1277 234567",
    "sg:postcode":"CM13 3BE",
    "sg:province":"Essex",
    "sg:tags":[
        "disposal",
        "waste"
    ],
    "wof:name":"Clean World Ltd.",
    "wof:placetype":"venue"
},
  "geometry": {"coordinates":[0.2997210026,51.6007957458],"type":"Point"}
}