{
  "type": "Feature",
  "properties": {
    "iso:country":"GB",
    "sg:address":"54 Norman Road",
    "sg:city":"Whitstable",
    "sg:classifiers":[
        {
            "category":"Building & Trades",
            "subcategory":"Construction",
            "type":"Services"
        }
    ],
    "sg:postcode":"CT5 4QL",
    "sg:province":"Kent",
    "sg:tags":[
        "builder"
    ],
    "wof:name":"A D Rigden",
    "wof:placetype":"venue"
},
  "geometry": {"coordinates":[1.0282,51.349419],"type":"Point"}
}