{
  "type": "Feature",
  "properties": {
    "iso:country":"GB",
    "sg:address":"M K A House 4-6 St Andrews Road",
    "sg:city":"Droitwich",
    "sg:classifiers":[
        {
            "category":"Professional",
            "subcategory":"Management & Consulting",
            "type":"Services"
        }
    ],
    "sg:phone":"+44 1905 790600",
    "sg:postcode":"WR9 8DN",
    "sg:province":"Worcestershire",
    "sg:tags":[
        "consultant",
        "business"
    ],
    "wof:name":"M K A Management Consulting Ltd.",
    "wof:placetype":"venue"
},
  "geometry": {"coordinates":[-2.152228,52.266323],"type":"Point"}
}