{
  "type": "Feature",
  "properties": {
    "iso:country":"GB",
    "sg:address":"12 Reid St",
    "sg:city":"Hamilton",
    "sg:classifiers":[
        {
            "category":"Building & Trades",
            "subcategory":"Construction",
            "type":"Services"
        }
    ],
    "sg:phone":"+44 1698 711119",
    "sg:postcode":"ML3 0RQ",
    "sg:province":"South Lanarkshire",
    "sg:tags":[
        "decorator",
        "painter"
    ],
    "wof:name":"Graham McKain",
    "wof:placetype":"venue"
},
  "geometry": {"coordinates":[-4.073632,55.781925],"type":"Point"}
}