{
  "type": "Feature",
  "properties": {
    "iso:country":"GB",
    "sg:address":"Prospect Close, Lowmoor Industrial Estate, Kirkby-in-ashfield",
    "sg:city":"Nottingham",
    "sg:classifiers":[
        {
            "category":"Home & Garden",
            "subcategory":"Hardware",
            "type":"Retail Goods"
        },
        {
            "category":"Retail",
            "subcategory":"Auto Repair",
            "type":"Services"
        }
    ],
    "sg:phone":"+44 1623 751558",
    "sg:postcode":"NG17 7LF",
    "sg:province":"Nottinghamshire",
    "sg:tags":[
        "fixing",
        "nuts",
        "bolt",
        "manufacturer"
    ],
    "wof:name":"Bapp Industrial Supplies (Mansfield) Ltd.",
    "wof:placetype":"venue"
},
  "geometry": {"coordinates":[-1.240459,53.112041],"type":"Point"}
}