{
  "type": "Feature",
  "properties": {
    "addr:full":"The Hutments Llwynegryn, County Hall Mold Denbighshire CH7 6NB",
    "addr:postcode":"ch7 6nb",
    "iso:country":"GB",
    "sg:address":"The Hutments Llwynegryn, County Hall",
    "sg:city":"Mold",
    "sg:classifiers":[
        {
            "category":"Organizations",
            "subcategory":"Non-profit Organization",
            "type":"Services"
        }
    ],
    "sg:postcode":"CH7 6NB",
    "sg:province":"Denbighshire",
    "sg:tags":[
        "organisation",
        "voluntary",
        "charity"
    ],
    "wof:name":"Pre-School Playgroup Association",
    "wof:placetype":"venue"
},
  "geometry": {"coordinates":[-3.139984,53.163868],"type":"Point"}
}