{
  "type": "Feature",
  "properties": {
    "iso:country":"GB",
    "sg:address":"Chapel House, Calcotts Green",
    "sg:city":"Gloucester",
    "sg:classifiers":[
        {
            "category":"Building & Trades",
            "subcategory":"Construction",
            "type":"Services"
        }
    ],
    "sg:phone":"+44 1452 750584",
    "sg:postcode":"GL2 8JN",
    "sg:province":"Gloucestershire",
    "sg:tags":[
        "builder"
    ],
    "wof:name":"Anthony W Laken",
    "wof:placetype":"venue"
},
  "geometry": {"coordinates":[-2.32007,51.851219],"type":"Point"}
}