{
  "type": "Feature",
  "properties": {
    "addr:full":"Southwell Gardens South Kensington Greater London SW7 4RL",
    "addr:postcode":"sw7 4rl",
    "addr:street":"Southwell Gardens",
    "iso:country":"GB",
    "sg:address":"Southwell Gardens",
    "sg:city":"South Kensington",
    "sg:classifiers":[
        {
            "category":"Government",
            "subcategory":"City Hall",
            "type":"Public Place"
        }
    ],
    "sg:phone":"+44 20 7370 3418",
    "sg:postcode":"SW7 4RL",
    "sg:province":"Greater London",
    "wof:name":"St Stephens Church Hall",
    "wof:placetype":"venue"
},
  "geometry": {"coordinates":[-0.184094,51.495869],"type":"Point"}
}