{
  "type": "Feature",
  "properties": {
    "addr:full":"6a Station Street, Cheslyn Hay Walsall Staffordshire WS6 7ED",
    "addr:housenumber":"6a",
    "addr:postcode":"ws6 7ed",
    "addr:street":"Station Street",
    "iso:country":"GB",
    "sg:address":"6a Station Street, Cheslyn Hay",
    "sg:city":"Walsall",
    "sg:classifiers":[
        {
            "category":"Personal",
            "subcategory":"Beauty Salon",
            "type":"Services"
        }
    ],
    "sg:postcode":"WS6 7ED",
    "sg:province":"Staffordshire",
    "sg:tags":[
        "unisex",
        "hairdresser"
    ],
    "wof:name":"Twist Hair Co",
    "wof:placetype":"venue"
},
  "geometry": {"coordinates":[-2.0311529636,52.6620788574],"type":"Point"}
}