{
  "type": "Feature",
  "properties": {
    "iso:country":"GB",
    "sg:address":"73 Lower Richmond Road",
    "sg:city":"London",
    "sg:classifiers":[
        {
            "category":"Shopping",
            "subcategory":"Florist",
            "type":"Retail Goods"
        }
    ],
    "sg:postcode":"SW14 7HJ",
    "sg:province":"Greater London",
    "wof:name":"The Flower Shop",
    "wof:placetype":"venue"
},
  "geometry": {"coordinates":[-0.272728,51.468636],"type":"Point"}
}