{
  "type": "Feature",
  "properties": {
    "iso:country":"GB",
    "sg:address":"The Elms, Winteringham Lane, West Halton",
    "sg:city":"Scunthorpe",
    "sg:classifiers":[
        {
            "category":"Farming",
            "subcategory":"Farm",
            "type":"Manufacturing & Wholesale Goods"
        }
    ],
    "sg:phone":"+44 1724 734757",
    "sg:postcode":"DN15 9AU",
    "sg:province":"Lincolnshire",
    "sg:tags":[
        "mixed",
        "crop"
    ],
    "wof:name":"Nethermoor Ltd.",
    "wof:placetype":"venue"
},
  "geometry": {"coordinates":[-0.6323239803,53.6779441833],"type":"Point"}
}