{
  "type": "Feature",
  "properties": {
    "iso:country":"GB",
    "sg:address":"5 The Bdwy, Portswood Road",
    "sg:city":"Southampton",
    "sg:classifiers":[
        {
            "category":"Shopping",
            "subcategory":"Thrift Store",
            "type":"Retail Goods"
        }
    ],
    "sg:postcode":"SO17 2WE",
    "sg:province":"Hampshire",
    "sg:tags":[
        "shop",
        "charity"
    ],
    "wof:name":"Oxfam",
    "wof:placetype":"venue"
},
  "geometry": {"coordinates":[-1.394013,50.923428],"type":"Point"}
}