{
  "type": "Feature",
  "properties": {
    "iso:country":"GB",
    "sg:address":"Southern Area Depot, Robert Way, Wickford Business Park",
    "sg:city":"Wickford",
    "sg:classifiers":[
        {
            "category":"Building & Trades",
            "subcategory":"Plumbing",
            "type":"Services"
        }
    ],
    "sg:phone":"+44 1268 560165",
    "sg:postcode":"SS11 8BH",
    "sg:province":"Essex",
    "sg:tags":[
        "heating"
    ],
    "wof:name":"Dial-A-Rod",
    "wof:placetype":"venue"
},
  "geometry": {"coordinates":[0.53507,51.60841],"type":"Point"}
}