{
  "type": "Feature",
  "properties": {
    "iso:country":"GB",
    "sg:address":"105 Westbourne Gro",
    "sg:city":"London",
    "sg:classifiers":[
        {
            "category":"Home & Garden",
            "subcategory":"Hardware",
            "type":"Retail Goods"
        }
    ],
    "sg:phone":"+44 20 7243 1100",
    "sg:postcode":"W2 4UW",
    "sg:province":"Greater London",
    "sg:tags":[
        "part",
        "accessory"
    ],
    "wof:name":"Fielding & Graham Ltd.",
    "wof:placetype":"venue"
},
  "geometry": {"coordinates":[-0.179967,51.516518],"type":"Point"}
}