{
  "type": "Feature",
  "properties": {
    "addr:full":"Suprema Industrial Estate, Eddington Bridgwater Somerset TA7 8AU",
    "addr:housenumber":"estate",
    "addr:postcode":"ta7 8au",
    "addr:street":"Eddington",
    "iso:country":"GB",
    "sg:address":"Suprema Industrial Estate, Eddington",
    "sg:city":"Bridgwater",
    "sg:classifiers":[
        {
            "category":"Home & Garden",
            "subcategory":"Building Materials",
            "type":"Retail Goods"
        }
    ],
    "sg:phone":"+44 1278 685308",
    "sg:postcode":"TA7 8AU",
    "sg:province":"Somerset",
    "sg:tags":[
        "ironwork",
        "product",
        "production",
        "design",
        "diy",
        "iron",
        "wrought"
    ],
    "wof:name":"Classic Iron",
    "wof:placetype":"venue"
},
  "geometry": {"coordinates":[-2.96948,51.170361],"type":"Point"}
}