{
  "type": "Feature",
  "properties": {
    "addr:full":"76-90 High Street Solihull West Midlands B91 3TA",
    "addr:housenumber":"76-90",
    "addr:postcode":"b91 3ta",
    "addr:street":"High Street",
    "iso:country":"GB",
    "sg:address":"76-90 High Street",
    "sg:city":"Solihull",
    "sg:classifiers":[
        {
            "category":"Personal",
            "subcategory":"Beauty Salon",
            "type":"Services"
        }
    ],
    "sg:phone":"+44 121 458 1323",
    "sg:postcode":"B91 3TA",
    "sg:province":"West Midlands",
    "sg:tags":[
        "unisex",
        "hairdresser"
    ],
    "wof:name":"James Hair Team & Beauty Salon",
    "wof:placetype":"venue"
},
  "geometry": {"coordinates":[-1.778287,52.412991],"type":"Point"}
}