{
  "type": "Feature",
  "properties": {
    "addr:full":"36a Bedford Rd, Stagsden Bedford Bedfordshire MK43 8TP",
    "addr:housenumber":"36a",
    "addr:postcode":"mk43 8tp",
    "addr:street":"Bedford Rd",
    "iso:country":"GB",
    "sg:address":"36a Bedford Rd, Stagsden",
    "sg:city":"Bedford",
    "sg:classifiers":[
        {
            "category":"Organizations",
            "subcategory":"Non-profit Organization",
            "type":"Services"
        }
    ],
    "sg:phone":"+44 1234 824281",
    "sg:postcode":"MK43 8TP",
    "sg:province":"Bedfordshire",
    "sg:tags":[
        "organisation",
        "voluntary",
        "charity"
    ],
    "wof:name":"Simply Forward Support Group",
    "wof:placetype":"venue"
},
  "geometry": {"coordinates":[-0.5618370175,52.1329421997],"type":"Point"}
}