{
  "type": "Feature",
  "properties": {
    "addr:full":"8 Park Lane Newmarket Cambridgeshire CB8 8AX",
    "addr:housenumber":"8",
    "addr:postcode":"cb8 8ax",
    "addr:street":"Park Lane",
    "iso:country":"GB",
    "sg:address":"8 Park Lane",
    "sg:city":"Newmarket",
    "sg:classifiers":[
        {
            "category":"Retail",
            "subcategory":"Auto Repair",
            "type":"Services"
        }
    ],
    "sg:postcode":"CB8 8AX",
    "sg:province":"Cambridgeshire",
    "sg:tags":[
        "modification",
        "garage"
    ],
    "wof:name":"Goldings Garage",
    "wof:placetype":"venue"
},
  "geometry": {"coordinates":[0.4070079923,52.2424621582],"type":"Point"}
}