{
  "type": "Feature",
  "properties": {
    "addr:full":"9 The Links, Queens Square Corby Northamptonshire NN17 1PZ",
    "addr:housenumber":"9",
    "addr:postcode":"nn17 1pz",
    "addr:street":"The;Queens Square",
    "iso:country":"GB",
    "sg:address":"9 The Links, Queens Square",
    "sg:city":"Corby",
    "sg:classifiers":[
        {
            "category":"Education",
            "subcategory":"Library",
            "type":"Public Place"
        }
    ],
    "sg:phone":"+44 1536 203304",
    "sg:postcode":"NN17 1PZ",
    "sg:province":"Northamptonshire",
    "sg:tags":[
        "book"
    ],
    "wof:name":"Corby Library",
    "wof:placetype":"venue"
},
  "geometry": {"coordinates":[-0.7026000023,52.4859771729],"type":"Point"}
}