{
  "type": "Feature",
  "properties": {
    "iso:country":"GB",
    "sg:address":"32 Bedford Road, Clophill",
    "sg:city":"Bedford",
    "sg:classifiers":[
        {
            "category":"Travel",
            "subcategory":"Hotels & Motels",
            "type":"Entertainment"
        }
    ],
    "sg:phone":"+44 1525 861565",
    "sg:postcode":"MK45 4AE",
    "sg:province":"Bedfordshire",
    "sg:tags":[
        "house",
        "guest"
    ],
    "wof:name":"Shallmarose",
    "wof:placetype":"venue"
},
  "geometry": {"coordinates":[-0.4237079918,52.0102539062],"type":"Point"}
}