{
  "type": "Feature",
  "properties": {
    "addr:full":"28 Priestpopple Hexham Northumberland NE46 1PQ",
    "addr:housenumber":"28",
    "addr:postcode":"ne46 1pq",
    "addr:street":"Priestpopple",
    "iso:country":"GB",
    "sg:address":"28 Priestpopple",
    "sg:city":"Hexham",
    "sg:classifiers":[
        {
            "category":"Restaurant",
            "type":"Food & Drink"
        }
    ],
    "sg:phone":"+44 1434 603509",
    "sg:postcode":"NE46 1PQ",
    "sg:province":"Northumberland",
    "sg:tags":[
        "indian"
    ],
    "wof:name":"Abbey Tandoori Restaurant Ltd.",
    "wof:placetype":"venue"
},
  "geometry": {"coordinates":[-2.099198,54.970387],"type":"Point"}
}