{
  "type": "Feature",
  "properties": {
    "iso:country":"GB",
    "sg:address":"1a Moorside Walk",
    "sg:city":"Bradford",
    "sg:classifiers":[
        {
            "category":"Building & Trades",
            "subcategory":"Construction",
            "type":"Services"
        },
        {
            "category":"Manufacturing",
            "subcategory":"Paper Products",
            "type":"Manufacturing & Wholesale Goods"
        }
    ],
    "sg:phone":"+44 113 285 4794",
    "sg:postcode":"BD11 1HL",
    "sg:province":"West Yorkshire",
    "sg:tags":[
        "cardboard",
        "decorator",
        "painter"
    ],
    "wof:name":"H & B Decorators",
    "wof:placetype":"venue"
},
  "geometry": {"coordinates":[-1.655833,53.752766],"type":"Point"}
}