{
  "type": "Feature",
  "properties": {
    "addr:full":"83 Redcar Rd, Thornaby Stockton On Tees Durham TS17 8LW",
    "addr:housenumber":"83",
    "addr:postcode":"ts17 8lw",
    "addr:street":"Redcar Rd;On",
    "iso:country":"GB",
    "sg:address":"83 Redcar Rd, Thornaby",
    "sg:city":"Stockton On Tees",
    "sg:classifiers":[
        {
            "category":"Building & Trades",
            "subcategory":"Construction",
            "type":"Services"
        }
    ],
    "sg:phone":"+44 1642 801999",
    "sg:postcode":"TS17 8LW",
    "sg:province":"Durham",
    "sg:tags":[
        "builder"
    ],
    "wof:name":"D M B Building Services",
    "wof:placetype":"venue"
},
  "geometry": {"coordinates":[-1.295282,54.546822],"type":"Point"}
}