{
  "type": "Feature",
  "properties": {
    "addr:full":"Ashes Farm, Sparkbridges Ulverston Cumbria LA12 7SU",
    "addr:postcode":"la12 7su",
    "addr:street":"Sparkbridges",
    "iso:country":"GB",
    "sg:address":"Ashes Farm, Sparkbridges",
    "sg:city":"Ulverston",
    "sg:classifiers":[
        {
            "category":"Freight",
            "type":"Transportation"
        }
    ],
    "sg:phone":"+44 1229 861260",
    "sg:postcode":"LA12 7SU",
    "sg:province":"Cumbria",
    "sg:tags":[
        "haulage",
        "road"
    ],
    "wof:name":"M E S Transport Ltd.",
    "wof:placetype":"venue"
},
  "geometry": {"coordinates":[-3.0923540592,54.1967315674],"type":"Point"}
}