{
  "type": "Feature",
  "properties": {
    "addr:full":"63 Crawther Avenue Leeds West Yorkshire LS28 5SA",
    "addr:housenumber":"63",
    "addr:postcode":"ls28 5sa",
    "addr:street":"Crawther Avenue",
    "iso:country":"GB",
    "sg:address":"63 Crawther Avenue",
    "sg:city":"Leeds",
    "sg:classifiers":[
        {
            "category":"Building & Trades",
            "subcategory":"Construction",
            "type":"Services"
        }
    ],
    "sg:postcode":"LS28 5SA",
    "sg:province":"West Yorkshire",
    "sg:tags":[
        "builder"
    ],
    "wof:name":"Geoffrey Ward",
    "wof:placetype":"venue"
},
  "geometry": {"coordinates":[-1.70192,53.828289],"type":"Point"}
}