{
  "type": "Feature",
  "properties": {
    "iso:country":"GB",
    "sg:address":"51 Fortis Green Road",
    "sg:city":"London",
    "sg:classifiers":[
        {
            "category":"Travel",
            "subcategory":"Travel Agent",
            "type":"Entertainment"
        }
    ],
    "sg:phone":"+44 20 8444 4444",
    "sg:postcode":"N10 3HP",
    "sg:province":"Greater London",
    "wof:name":"Travelwise Ltd.",
    "wof:placetype":"venue"
},
  "geometry": {"coordinates":[-0.146516,51.590004],"type":"Point"}
}