{
  "type": "Feature",
  "properties": {
    "iso:country":"GB",
    "sg:address":"6 Curley Hill Road",
    "sg:city":"Lightwater",
    "sg:classifiers":[
        {
            "category":"Communications",
            "subcategory":"Film & Video Production",
            "type":"Services"
        }
    ],
    "sg:phone":"+44 1276 472179",
    "sg:postcode":"GU18 5YG",
    "sg:province":"Surrey",
    "sg:tags":[
        "tv",
        "studio"
    ],
    "wof:name":"Animal Tracks Productions Ltd.",
    "wof:placetype":"venue"
},
  "geometry": {"coordinates":[-0.683868,51.346104],"type":"Point"}
}