{
  "type": "Feature",
  "properties": {
    "iso:country":"GB",
    "sg:address":"55 Sefton Street",
    "sg:city":"Southport",
    "sg:classifiers":[
        {
            "category":"Building & Trades",
            "subcategory":"Plumbing",
            "type":"Services"
        }
    ],
    "sg:phone":"+44 1704 500365",
    "sg:postcode":"PR8 6SH",
    "sg:province":"Lancashire",
    "sg:tags":[
        "plumber",
        "heating"
    ],
    "wof:name":"Northern Plumbing & Heating Contractors Ltd.",
    "wof:placetype":"venue"
},
  "geometry": {"coordinates":[-2.998364,53.639702],"type":"Point"}
}