{
  "type": "Feature",
  "properties": {
    "addr:full":"13 Crown St Aberdeen Aberdeen City AB11 6HA",
    "addr:housenumber":"13",
    "addr:postcode":"ab11 6ha",
    "addr:street":"Crown St",
    "iso:country":"GB",
    "sg:address":"13 Crown St",
    "sg:city":"Aberdeen",
    "sg:classifiers":[
        {
            "category":"Restaurant",
            "type":"Food & Drink"
        }
    ],
    "sg:phone":"+44 1224 259961",
    "sg:postcode":"AB11 6HA",
    "sg:province":"Aberdeen City",
    "wof:name":"Lauras",
    "wof:placetype":"venue"
},
  "geometry": {"coordinates":[-2.103224,57.144554],"type":"Point"}
}