{
  "type": "Feature",
  "properties": {
    "addr:full":"17 Gullane St Glasgow Glasgow City G11 6AH",
    "addr:housenumber":"17",
    "addr:postcode":"g11 6ah",
    "addr:street":"Gullane St",
    "iso:country":"GB",
    "sg:address":"17 Gullane St",
    "sg:city":"Glasgow",
    "sg:classifiers":[
        {
            "category":"Government",
            "subcategory":"Office",
            "type":"Public Place"
        }
    ],
    "sg:phone":"+44 141 334 5530",
    "sg:postcode":"G11 6AH",
    "sg:province":"Glasgow City",
    "sg:tags":[
        "local"
    ],
    "wof:name":"Centre For Sensory Impaired People",
    "wof:placetype":"venue"
},
  "geometry": {"coordinates":[-4.305279,55.869999],"type":"Point"}
}