{
  "type": "Feature",
  "properties": {
    "iso:country":"GB",
    "sg:address":"10 Whaddon Chase",
    "sg:city":"Fareham",
    "sg:classifiers":[
        {
            "category":"Taxi",
            "type":"Transportation"
        }
    ],
    "sg:phone":"+44 1329 517387",
    "sg:postcode":"PO14 3SG",
    "sg:province":"Hampshire",
    "sg:tags":[
        "mini",
        "cab"
    ],
    "wof:name":"Crofton Cars",
    "wof:placetype":"venue"
},
  "geometry": {"coordinates":[-1.226214,50.821777],"type":"Point"}
}