{
  "type": "Feature",
  "properties": {
    "addr:full":"48 Stephyns Chambers Hemel Hempstead Hertfordshire HP1 1DD",
    "addr:housenumber":"48",
    "addr:postcode":"hp1 1dd",
    "addr:street":"Hemel Hempstead",
    "iso:country":"GB",
    "sg:address":"48 Stephyns Chambers",
    "sg:city":"Hemel Hempstead",
    "sg:classifiers":[
        {
            "category":"Professional",
            "subcategory":"Employment Agencies",
            "type":"Services"
        }
    ],
    "sg:phone":"+44 1442 235555",
    "sg:postcode":"HP1 1DD",
    "sg:province":"Hertfordshire",
    "sg:tags":[
        "consultant"
    ],
    "wof:name":"Boxmoor Bureau Ltd.",
    "wof:placetype":"venue"
},
  "geometry": {"coordinates":[-0.4862389863,51.7516593933],"type":"Point"}
}