{
  "type": "Feature",
  "properties": {
    "iso:country":"GB",
    "sg:address":"6 Admirals Walk",
    "sg:city":"Chatham",
    "sg:classifiers":[
        {
            "category":"Fast Food",
            "type":"Food & Drink"
        }
    ],
    "sg:phone":"+44 1634 685820",
    "sg:postcode":"ME5 8NL",
    "sg:province":"Kent",
    "sg:tags":[
        "away",
        "take"
    ],
    "wof:name":"Mr Wu",
    "wof:placetype":"venue"
},
  "geometry": {"coordinates":[0.5359,51.341438],"type":"Point"}
}