{
  "type": "Feature",
  "properties": {
    "addr:full":"Dairy House Encombe, Corfe Castle Wareham Dorset BH20 5LW",
    "addr:postcode":"bh20 5lw",
    "addr:street":"Encombe",
    "iso:country":"GB",
    "sg:address":"Dairy House Encombe, Corfe Castle",
    "sg:city":"Wareham",
    "sg:classifiers":[
        {
            "category":"Professional",
            "type":"Services"
        },
        {
            "category":"Professional",
            "subcategory":"Management & Consulting",
            "type":"Services"
        }
    ],
    "sg:phone":"+44 1929 480189",
    "sg:postcode":"BH20 5LW",
    "sg:province":"Dorset",
    "sg:tags":[
        "interior",
        "consultant",
        "designer",
        "business",
        "furnishers"
    ],
    "wof:name":"Sue Best Interiors",
    "wof:placetype":"venue"
},
  "geometry": {"coordinates":[-2.0535941124,50.6338386536],"type":"Point"}
}