{
  "type": "Feature",
  "properties": {
    "iso:country":"GB",
    "sg:address":"85 High Street",
    "sg:city":"Saltburn-by-the-sea",
    "sg:classifiers":[
        {
            "category":"Bars & Pubs",
            "type":"Food & Drink"
        }
    ],
    "sg:phone":"+44 1287 640087",
    "sg:postcode":"TS13 4HG",
    "sg:province":"North Yorkshire",
    "sg:tags":[
        "pubs",
        "inn"
    ],
    "wof:name":"Golden Lion Hotel",
    "wof:placetype":"venue"
},
  "geometry": {"coordinates":[-0.885191977,54.5536308289],"type":"Point"}
}