{
  "type": "Feature",
  "properties": {
    "addr:full":"Coedmor, Caswell Avenue, Caswell Swansea Swansea SA3 4RU",
    "addr:postcode":"sa3 4ru",
    "addr:street":"Coedmor Caswell Avenue",
    "iso:country":"GB",
    "sg:address":"Coedmor, Caswell Avenue, Caswell",
    "sg:city":"Swansea",
    "sg:classifiers":[
        {
            "category":"Real Estate",
            "subcategory":"Architect",
            "type":"Services"
        }
    ],
    "sg:phone":"+44 1792 360508",
    "sg:postcode":"SA3 4RU",
    "sg:province":"Swansea",
    "wof:name":"Alan Seager",
    "wof:placetype":"venue"
},
  "geometry": {"coordinates":[-4.0403909683,51.5700416565],"type":"Point"}
}