{
  "type": "Feature",
  "properties": {
    "addr:full":"Squirrels Leap, Beech Waye Gerrards Cross Buckinghamshire SL9 8BL",
    "addr:postcode":"sl9 8bl",
    "addr:street":"Beech",
    "iso:country":"GB",
    "sg:address":"Squirrels Leap, Beech Waye",
    "sg:city":"Gerrards Cross",
    "sg:classifiers":[
        {
            "category":"Shopping",
            "subcategory":"Mobile Phones",
            "type":"Retail Goods"
        }
    ],
    "sg:phone":"+44 1753 886075",
    "sg:postcode":"SL9 8BL",
    "sg:province":"Buckinghamshire",
    "wof:name":"Telepaz",
    "wof:placetype":"venue"
},
  "geometry": {"coordinates":[-0.5625789762,51.5789756775],"type":"Point"}
}