{
  "type": "Feature",
  "properties": {
    "iso:country":"GB",
    "sg:address":"Unit 1-4 Holloway Drive, Wardley Industrial Estate, Worsley",
    "sg:city":"Manchester",
    "sg:classifiers":[
        {
            "category":"Wholesale",
            "subcategory":"Non-durable Goods",
            "type":"Manufacturing & Wholesale Goods"
        }
    ],
    "sg:phone":"+44 161 728 8000",
    "sg:postcode":"M28 2LA",
    "sg:province":"Greater Manchester",
    "sg:tags":[
        "carry",
        "wholesaler",
        "cash"
    ],
    "wof:name":"Stax Trade Centres Ltd",
    "wof:placetype":"venue"
},
  "geometry": {"coordinates":[-2.3617429733,53.5158233643],"type":"Point"}
}