{
  "type": "Feature",
  "properties": {
    "addr:full":"19 Heatherdale Road Camberley Berkshire GU15 2LT",
    "addr:housenumber":"19",
    "addr:postcode":"gu15 2lt",
    "addr:street":"Heatherdale Road",
    "iso:country":"GB",
    "sg:address":"19 Heatherdale Road",
    "sg:city":"Camberley",
    "sg:classifiers":[
        {
            "category":"Shopping",
            "subcategory":"Stationery & Office Supplies",
            "type":"Retail Goods"
        }
    ],
    "sg:postcode":"GU15 2LT",
    "sg:province":"Berkshire",
    "sg:tags":[
        "equipment"
    ],
    "wof:name":"Instant Business Supplies Ltd.",
    "wof:placetype":"venue"
},
  "geometry": {"coordinates":[-0.7445350289,51.3302574158],"type":"Point"}
}