{
  "type": "Feature",
  "properties": {
    "iso:country":"GB",
    "sg:address":"65-67 High Road, Chilwell",
    "sg:city":"Nottingham",
    "sg:classifiers":[
        {
            "category":"Shopping",
            "subcategory":"Crafts & Fabrics",
            "type":"Retail Goods"
        }
    ],
    "sg:phone":"+44 115 925 4080",
    "sg:postcode":"NG9 4AJ",
    "sg:province":"Nottinghamshire",
    "sg:tags":[
        "knitwear",
        "yarn"
    ],
    "wof:name":"G H Hurt & Son Ltd.",
    "wof:placetype":"venue"
},
  "geometry": {"coordinates":[-1.223036,52.921085],"type":"Point"}
}