{
  "type": "Feature",
  "properties": {
    "iso:country":"GB",
    "sg:address":"33 Church Street",
    "sg:city":"Basingstoke",
    "sg:classifiers":[
        {
            "category":"Shopping",
            "subcategory":"Florist",
            "type":"Retail Goods"
        }
    ],
    "sg:phone":"+44 1256 470631",
    "sg:postcode":"RG21 7QQ",
    "sg:province":"Hampshire",
    "wof:name":"Nicola",
    "wof:placetype":"venue"
},
  "geometry": {"coordinates":[-1.087979,51.263493],"type":"Point"}
}