{
  "type": "Feature",
  "properties": {
    "addr:full":"Matrix House, 5 Wick Lane Christchurch Dorset BH23 1HT",
    "addr:housenumber":"5",
    "addr:postcode":"bh23 1ht",
    "addr:street":"Wick Lane",
    "iso:country":"GB",
    "sg:address":"Matrix House, 5 Wick Lane",
    "sg:city":"Christchurch",
    "sg:classifiers":[
        {
            "category":"Real Estate",
            "subcategory":"Developer",
            "type":"Services"
        }
    ],
    "sg:phone":"+44 1202 488366",
    "sg:postcode":"BH23 1HT",
    "sg:province":"Dorset",
    "sg:tags":[
        "property"
    ],
    "wof:name":"Parkcrest Ltd.",
    "wof:placetype":"venue"
},
  "geometry": {"coordinates":[-1.7781939507,50.7327232361],"type":"Point"}
}