{
  "type": "Feature",
  "properties": {
    "addr:full":"135 Deightonby Street Rotherham South Yorkshire S63 0HZ",
    "addr:housenumber":"135",
    "addr:postcode":"s63 0hz",
    "addr:street":"Deightonby Street",
    "iso:country":"GB",
    "sg:address":"135 Deightonby Street",
    "sg:city":"Rotherham",
    "sg:classifiers":[
        {
            "category":"Building & Trades",
            "subcategory":"Construction",
            "type":"Services"
        }
    ],
    "sg:phone":"+44 1709 896524",
    "sg:postcode":"S63 0HZ",
    "sg:province":"South Yorkshire",
    "sg:tags":[
        "builder"
    ],
    "wof:name":"N Stones",
    "wof:placetype":"venue"
},
  "geometry": {"coordinates":[-1.303552,53.551895],"type":"Point"}
}