{
  "type": "Feature",
  "properties": {
    "addr:full":"208 Mosslands Drive, Wallasey Wirral Merseyside CH44 2EG",
    "addr:housenumber":"208",
    "addr:postcode":"ch44 2eg",
    "addr:street":"Mosslands Drive",
    "iso:country":"GB",
    "sg:address":"208 Mosslands Drive, Wallasey",
    "sg:city":"Wirral",
    "sg:classifiers":[
        {
            "category":"Building & Trades",
            "subcategory":"Construction",
            "type":"Services"
        }
    ],
    "sg:postcode":"CH44 2EG",
    "sg:province":"Merseyside",
    "sg:tags":[
        "builder"
    ],
    "wof:name":"M & K Building",
    "wof:placetype":"venue"
},
  "geometry": {"coordinates":[-3.0606229305,53.4160308838],"type":"Point"}
}