{
  "type": "Feature",
  "properties": {
    "iso:country":"GB",
    "sg:address":"43 George Street",
    "sg:city":"Hastings",
    "sg:classifiers":[
        {
            "category":"Restaurant",
            "type":"Food & Drink"
        }
    ],
    "sg:phone":"+44 1424 429685",
    "sg:postcode":"TN34 3EA",
    "sg:province":"East Sussex",
    "sg:tags":[
        "indian"
    ],
    "wof:name":"Castle Tandoori Restaurant",
    "wof:placetype":"venue"
},
  "geometry": {"coordinates":[0.589198,50.856087],"type":"Point"}
}