{
  "type": "Feature",
  "properties": {
    "iso:country":"GB",
    "sg:address":"Front St West",
    "sg:city":"Wingate",
    "sg:classifiers":[
        {
            "category":"Organizations",
            "subcategory":"Membership Organization",
            "type":"Services"
        }
    ],
    "sg:phone":"+44 1429 838384",
    "sg:postcode":"TS28 5AG",
    "sg:province":"Durham",
    "sg:tags":[
        "club"
    ],
    "wof:name":"Wingate Catholic Club",
    "wof:placetype":"venue"
},
  "geometry": {"coordinates":[-1.380794,54.727718],"type":"Point"}
}