{
  "type": "Feature",
  "properties": {
    "iso:country":"GB",
    "sg:address":"Brineton St",
    "sg:city":"Walsall",
    "sg:classifiers":[
        {
            "category":"Professional",
            "subcategory":"Engineering",
            "type":"Services"
        }
    ],
    "sg:phone":"+44 1922 640509",
    "sg:postcode":"WS2 9EP",
    "sg:province":"West Midlands",
    "sg:tags":[
        "precision",
        "engineer"
    ],
    "wof:name":"Mercia Precision Die & Tool",
    "wof:placetype":"venue"
},
  "geometry": {"coordinates":[-1.997497,52.579742],"type":"Point"}
}