{
  "type": "Feature",
  "properties": {
    "iso:country":"GB",
    "sg:address":"105 Main Street",
    "sg:city":"Pembroke",
    "sg:classifiers":[
        {
            "category":"Food & Beverages",
            "subcategory":"Liquor & Beverages",
            "type":"Retail Goods"
        }
    ],
    "sg:postcode":"SA71 4DB",
    "sg:province":"Pembrokeshire",
    "sg:tags":[
        "beer",
        "spirit",
        "wines"
    ],
    "wof:name":"Lyndale Wine",
    "wof:placetype":"venue"
},
  "geometry": {"coordinates":[-4.912825,51.674641],"type":"Point"}
}