{
  "type": "Feature",
  "properties": {
    "iso:country":"GB",
    "sg:address":"Four Elms Service Station,, Main Rd, Chattenden,",
    "sg:city":"Rochester",
    "sg:classifiers":[
        {
            "category":"Autos & Motor Vehicles",
            "subcategory":"Automobile Sales",
            "type":"Retail Goods"
        }
    ],
    "sg:postcode":"ME3 8LL",
    "sg:province":"Kent",
    "sg:tags":[
        "car"
    ],
    "wof:name":"Stickings,Ashley R,",
    "wof:placetype":"venue"
},
  "geometry": {"coordinates":[0.517162,51.413795],"type":"Point"}
}