{
  "type": "Feature",
  "properties": {
    "addr:full":"41 Landor Street, Bordesley Birmingham West Midlands B8 1AE",
    "addr:housenumber":"41",
    "addr:postcode":"b8 1ae",
    "addr:street":"Landor Street",
    "iso:country":"GB",
    "sg:address":"41 Landor Street, Bordesley",
    "sg:city":"Birmingham",
    "sg:classifiers":[
        {
            "category":"Building & Trades",
            "subcategory":"Equipment Rental",
            "type":"Services"
        }
    ],
    "sg:phone":"+44 121 328 1151",
    "sg:postcode":"B8 1AE",
    "sg:province":"West Midlands",
    "sg:tags":[
        "plant",
        "machinery"
    ],
    "wof:name":"Epl Plant & Access Hire",
    "wof:placetype":"venue"
},
  "geometry": {"coordinates":[-1.867141,52.482586],"type":"Point"}
}