{
  "type": "Feature",
  "properties": {
    "addr:full":"65 Scale Hall Lane Lancaster Lancashire LA1 2RP",
    "addr:housenumber":"65",
    "addr:postcode":"la1 2rp",
    "addr:street":"Scale Hall Lane",
    "iso:country":"GB",
    "sg:address":"65 Scale Hall Lane",
    "sg:city":"Lancaster",
    "sg:classifiers":[
        {
            "category":"Building & Trades",
            "subcategory":"Cleaning & Sanitation",
            "type":"Services"
        }
    ],
    "sg:postcode":"LA1 2RP",
    "sg:province":"Lancashire",
    "sg:tags":[
        "dry",
        "control",
        "damp",
        "rot"
    ],
    "wof:name":"Sovereign Damp Proofing",
    "wof:placetype":"venue"
},
  "geometry": {"coordinates":[-2.81735,54.059307],"type":"Point"}
}