{
  "type": "Feature",
  "properties": {
    "addr:full":"15 Palace Street Caernarfon Gwynedd LL55 1RR",
    "addr:housenumber":"15",
    "addr:postcode":"ll55 1rr",
    "addr:street":"Palace Street",
    "iso:country":"GB",
    "sg:address":"15 Palace Street",
    "sg:city":"Caernarfon",
    "sg:classifiers":[
        {
            "category":"Retail",
            "subcategory":"Photofinishing",
            "type":"Services"
        },
        {
            "category":"Shopping",
            "subcategory":"Photographic Equipment",
            "type":"Retail Goods"
        }
    ],
    "sg:phone":"+44 1286 672606",
    "sg:postcode":"LL55 1RR",
    "sg:province":"Gwynedd",
    "sg:tags":[
        "processor",
        "supply"
    ],
    "wof:name":"George Thomas & Co",
    "wof:placetype":"venue"
},
  "geometry": {"coordinates":[-4.276049,53.140266],"type":"Point"}
}