{
  "type": "Feature",
  "properties": {
    "addr:full":"Largs Yacht Haven, Irvine Rd Largs North Ayrshire KA30 8EZ",
    "addr:postcode":"ka30 8ez",
    "addr:street":"Yacht Haven Irvine Rd",
    "iso:country":"GB",
    "sg:address":"Largs Yacht Haven, Irvine Rd",
    "sg:city":"Largs",
    "sg:classifiers":[
        {
            "category":"Building & Trades",
            "subcategory":"Electrical",
            "type":"Services"
        }
    ],
    "sg:phone":"+44 1475 672281",
    "sg:postcode":"KA30 8EZ",
    "sg:province":"North Ayrshire",
    "sg:tags":[
        "consultant",
        "lighting"
    ],
    "wof:name":"Nationwide Maintenance Services Ltd",
    "wof:placetype":"venue"
},
  "geometry": {"coordinates":[-4.8600149155,55.788734436],"type":"Point"}
}