{
  "type": "Feature",
  "properties": {
    "addr:full":"Unit 5 Beachnut Industrial Estate, Off Beachnut Rd Aldershot Hampshire GU12 4SA",
    "addr:housenumber":"unit 5;estate",
    "addr:postcode":"gu12 4sa",
    "addr:street":"Beachnut Industrial;Off Beachnut Rd",
    "iso:country":"GB",
    "sg:address":"Unit 5 Beachnut Industrial Estate, Off Beachnut Rd",
    "sg:city":"Aldershot",
    "sg:classifiers":[
        {
            "category":"Retail",
            "subcategory":"Auto Repair",
            "type":"Services"
        }
    ],
    "sg:phone":"+44 1252 329970",
    "sg:postcode":"GU12 4SA",
    "sg:province":"Hampshire",
    "sg:tags":[
        "modification",
        "garage"
    ],
    "wof:name":"Hiscock's Mobile",
    "wof:placetype":"venue"
},
  "geometry": {"coordinates":[-0.7437599897,51.2481498718],"type":"Point"}
}