{
  "type": "Feature",
  "properties": {
    "iso:country":"GB",
    "sg:address":"64 Church Road",
    "sg:city":"Ashford",
    "sg:classifiers":[
        {
            "category":"Sports & Exercise",
            "subcategory":"Gym",
            "type":"Entertainment"
        }
    ],
    "sg:postcode":"TW15 2TS",
    "sg:province":"Greater London",
    "sg:tags":[
        "fitness",
        "health",
        "centre"
    ],
    "wof:name":"Shapers Health Studio",
    "wof:placetype":"venue"
},
  "geometry": {"coordinates":[-0.461793,51.432823],"type":"Point"}
}