{
  "type": "Feature",
  "properties": {
    "addr:full":"30 The Street, Rayne Braintree Essex CM77 6RS",
    "addr:housenumber":"30",
    "addr:postcode":"cm77 6rs",
    "addr:street":"The Street",
    "iso:country":"GB",
    "sg:address":"30 The Street, Rayne",
    "sg:city":"Braintree",
    "sg:classifiers":[
        {
            "category":"Building & Trades",
            "subcategory":"Construction",
            "type":"Services"
        }
    ],
    "sg:phone":"+44 1376 551258",
    "sg:postcode":"CM77 6RS",
    "sg:province":"Essex",
    "sg:tags":[
        "conservation",
        "roofing",
        "craft",
        "thatching",
        "contracting"
    ],
    "wof:name":"ANTHONY WILLIAM LAUDRUM",
    "wof:placetype":"venue"
},
  "geometry": {"coordinates":[0.506538,51.875103],"type":"Point"}
}