{
  "type": "Feature",
  "properties": {
    "iso:country":"GB",
    "sg:address":"12-14 Benedict Street",
    "sg:city":"Glastonbury",
    "sg:classifiers":[
        {
            "category":"Home & Garden",
            "subcategory":"Carpets & Floor Coverings",
            "type":"Retail Goods"
        }
    ],
    "sg:phone":"+44 1458 832494",
    "sg:postcode":"BA6 9EX",
    "sg:province":"Somerset",
    "sg:tags":[
        "carpets",
        "rug",
        "matting"
    ],
    "wof:name":"Bancroft Carpets",
    "wof:placetype":"venue"
},
  "geometry": {"coordinates":[-2.718848,51.147095],"type":"Point"}
}