{
  "type": "Feature",
  "properties": {
    "iso:country":"GB",
    "sg:address":"Unit A12 Northbridge House, Elm Street",
    "sg:city":"Burnley",
    "sg:classifiers":[
        {
            "category":"Shopping",
            "subcategory":"Stationery & Office Supplies",
            "type":"Retail Goods"
        }
    ],
    "sg:phone":"+44 1282 427709",
    "sg:postcode":"BB10 1PD",
    "sg:province":"Lancashire",
    "sg:tags":[
        "equipment"
    ],
    "wof:name":"Maid For You Cleaning Services",
    "wof:placetype":"venue"
},
  "geometry": {"coordinates":[-2.243463,53.802872],"type":"Point"}
}