{
  "type": "Feature",
  "properties": {
    "addr:full":"2nd Floor, Standbrook House, 2-5 Old Bond St West End Hampshire W1X 3TB",
    "addr:housenumber":"2nd floor standbrook house 2-5",
    "addr:postcode":"w1x 3tb",
    "addr:street":"Old Bond St",
    "iso:country":"GB",
    "sg:address":"2nd Floor, Standbrook House, 2-5 Old Bond St",
    "sg:city":"West End",
    "sg:classifiers":[
        {
            "category":"Building & Trades",
            "subcategory":"Construction",
            "type":"Services"
        }
    ],
    "sg:phone":"+44 20 8788 0119",
    "sg:postcode":"W1X 3TB",
    "sg:province":"Hampshire",
    "sg:tags":[
        "builder"
    ],
    "wof:name":"Quantum Design Associates",
    "wof:placetype":"venue"
},
  "geometry": {"coordinates":[-0.1401250064,51.508441925],"type":"Point"}
}