{
  "type": "Feature",
  "properties": {
    "addr:full":"9 Kabin Road Norwich Norfolk NR5 0LW",
    "addr:housenumber":"9",
    "addr:postcode":"nr5 0lw",
    "addr:street":"Kabin Road Norwich Norfolk",
    "iso:country":"GB",
    "sg:address":"9 Kabin Road",
    "sg:city":"Norwich",
    "sg:classifiers":[
        {
            "category":"Manufacturing",
            "subcategory":"Wood Products",
            "type":"Manufacturing & Wholesale Goods"
        },
        {
            "category":"Building & Trades",
            "subcategory":"Construction",
            "type":"Services"
        }
    ],
    "sg:phone":"+44 1603 742068",
    "sg:postcode":"NR5 0LW",
    "sg:province":"Norfolk",
    "sg:tags":[
        "joinery",
        "manufacturer"
    ],
    "wof:name":"Glen & Paul Fox",
    "wof:placetype":"venue"
},
  "geometry": {"coordinates":[1.231222,52.649822],"type":"Point"}
}