{
  "type": "Feature",
  "properties": {
    "iso:country":"GB",
    "sg:address":"Gore House Farm, Acres Lane",
    "sg:city":"Liverpool",
    "sg:classifiers":[
        {
            "category":"Farming",
            "subcategory":"Livestock Farm",
            "type":"Manufacturing & Wholesale Goods"
        }
    ],
    "sg:postcode":"L31 4EX",
    "sg:province":"Lancashire",
    "sg:tags":[
        "others"
    ],
    "wof:name":"Bruce Edwards & Sons",
    "wof:placetype":"venue"
},
  "geometry": {"coordinates":[-2.969989,53.532688],"type":"Point"}
}