{
  "type": "Feature",
  "properties": {
    "iso:country":"GB",
    "sg:address":"19 Mead Row",
    "sg:city":"Godalming",
    "sg:classifiers":[
        {
            "category":"Manufacturing",
            "subcategory":"Tools & Machinery",
            "type":"Manufacturing & Wholesale Goods"
        }
    ],
    "sg:phone":"+44 1483 411800",
    "sg:postcode":"GU7 3HJ",
    "sg:province":"Surrey",
    "sg:tags":[
        "society",
        "friendly"
    ],
    "wof:name":"Iptc Ltd.",
    "wof:placetype":"venue"
},
  "geometry": {"coordinates":[-0.605276,51.190632],"type":"Point"}
}