{
  "type": "Feature",
  "properties": {
    "addr:full":"20 Gowing Road Norwich Norfolk NR6 6UN",
    "addr:housenumber":"20",
    "addr:postcode":"nr6 6un",
    "addr:street":"Gowing Road Norwich Norfolk",
    "iso:country":"GB",
    "sg:address":"20 Gowing Road",
    "sg:city":"Norwich",
    "sg:classifiers":[
        {
            "category":"Home & Garden",
            "subcategory":"Home Furnishings",
            "type":"Retail Goods"
        },
        {
            "category":"Home & Garden",
            "subcategory":"Building Materials",
            "type":"Retail Goods"
        }
    ],
    "sg:phone":"+44 1603 486885",
    "sg:postcode":"NR6 6UN",
    "sg:province":"Norfolk",
    "sg:tags":[
        "installers",
        "planner",
        "kitchen",
        "furnishers"
    ],
    "wof:name":"Anthony Arthur Gray",
    "wof:placetype":"venue"
},
  "geometry": {"coordinates":[1.261795,52.667309],"type":"Point"}
}