{
  "type": "Feature",
  "properties": {
    "addr:full":"12 Bruton Street London Greater London W1J 6PZ",
    "addr:housenumber":"12",
    "addr:postcode":"w1j 6pz",
    "addr:street":"Bruton Street",
    "iso:country":"GB",
    "sg:address":"12 Bruton Street",
    "sg:city":"London",
    "sg:classifiers":[
        {
            "category":"Professional",
            "subcategory":"Employment Agencies",
            "type":"Services"
        }
    ],
    "sg:phone":"+44 20 7333 9444",
    "sg:postcode":"W1J 6PZ",
    "sg:province":"Greater London",
    "sg:tags":[
        "consultant"
    ],
    "wof:name":"Vertis Consulting Ltd.",
    "wof:placetype":"venue"
},
  "geometry": {"coordinates":[-0.1442719996,51.5105514526],"type":"Point"}
}