{
  "type": "Feature",
  "properties": {
    "iso:country":"GB",
    "sg:address":"60 West Green Rd",
    "sg:city":"Seven Sisters",
    "sg:classifiers":[
        {
            "category":"Shopping",
            "subcategory":"Music",
            "type":"Retail Goods"
        }
    ],
    "sg:phone":"+44 20 8800 6779",
    "sg:postcode":"N15 5NR",
    "sg:province":"Greater London",
    "sg:tags":[
        "record",
        "tape",
        "cd"
    ],
    "wof:name":"Koy & Son",
    "wof:placetype":"venue"
},
  "geometry": {"coordinates":[-0.0753230006,51.5843582153],"type":"Point"}
}