{
  "type": "Feature",
  "properties": {
    "iso:country":"GB",
    "sg:address":"206 Marlowes",
    "sg:city":"Hemel Hempstead",
    "sg:classifiers":[
        {
            "category":"Shopping",
            "subcategory":"Hobbies, Toys, & Games",
            "type":"Retail Goods"
        }
    ],
    "sg:phone":"+44 1442 216461",
    "sg:postcode":"HP1 1BH",
    "sg:province":"Hertfordshire",
    "sg:tags":[
        "shop",
        "toy",
        "sale"
    ],
    "sg:website":"http://www.elc.co.uk",
    "wof:name":"Early Learning Centre Ltd",
    "wof:placetype":"venue"
},
  "geometry": {"coordinates":[-0.4724490047,51.7511405945],"type":"Point"}
}