{
  "type": "Feature",
  "properties": {
    "iso:country":"GB",
    "sg:address":"44 Westgate",
    "sg:city":"Skelmersdale",
    "sg:classifiers":[
        {
            "category":"Professional",
            "subcategory":"Art Services",
            "type":"Services"
        }
    ],
    "sg:postcode":"WN8 8AZ",
    "sg:province":"Lancashire",
    "sg:tags":[
        "graphic",
        "designer"
    ],
    "wof:name":"Bad Design",
    "wof:placetype":"venue"
},
  "geometry": {"coordinates":[-2.7990789413,53.5510787964],"type":"Point"}
}