{
  "type": "Feature",
  "properties": {
    "iso:country":"GB",
    "sg:address":"143 Old Woking Road, Pyrford",
    "sg:city":"Woking",
    "sg:classifiers":[
        {
            "category":"Education",
            "subcategory":"School",
            "type":"Public Place"
        }
    ],
    "sg:phone":"+44 1932 342565",
    "sg:postcode":"GU22 8PD",
    "sg:province":"Surrey",
    "sg:tags":[
        "independent",
        "preparatory"
    ],
    "wof:name":"Highfield Nursery School",
    "wof:placetype":"venue"
},
  "geometry": {"coordinates":[-0.5325080156,51.3189430237],"type":"Point"}
}