{
  "type": "Feature",
  "properties": {
    "addr:full":"37 Twickenham Road Newton Abbot Devon TQ12 4JF",
    "addr:housenumber":"37",
    "addr:postcode":"tq12 4jf",
    "addr:street":"Twickenham Road",
    "iso:country":"GB",
    "sg:address":"37 Twickenham Road",
    "sg:city":"Newton Abbot",
    "sg:classifiers":[
        {
            "category":"Social Services",
            "subcategory":"Child Care",
            "type":"Services"
        }
    ],
    "sg:postcode":"TQ12 4JF",
    "sg:province":"Devon",
    "sg:tags":[
        "childminders"
    ],
    "wof:name":"Jenny Rogers",
    "wof:placetype":"venue"
},
  "geometry": {"coordinates":[-3.5786280632,50.5244178772],"type":"Point"}
}