{
  "type": "Feature",
  "properties": {
    "addr:full":"624c Fulham Road, Parsons Grn London Greater London SW6 5RS",
    "addr:housenumber":"624c",
    "addr:postcode":"sw6 5rs",
    "addr:street":"Fulham Road;Grn",
    "iso:country":"GB",
    "sg:address":"624c Fulham Road, Parsons Grn",
    "sg:city":"London",
    "sg:classifiers":[
        {
            "category":"Shopping",
            "subcategory":"Gifts & Souvenirs",
            "type":"Retail Goods"
        }
    ],
    "sg:phone":"+44 20 7351 7674",
    "sg:postcode":"SW6 5RS",
    "sg:province":"Greater London",
    "sg:tags":[
        "shop"
    ],
    "wof:name":"Brats Ltd.",
    "wof:placetype":"venue"
},
  "geometry": {"coordinates":[-0.2042450011,51.4766235352],"type":"Point"}
}