{
  "type": "Feature",
  "properties": {
    "iso:country":"GB",
    "sg:address":"96 Ock Street",
    "sg:city":"Abingdon",
    "sg:classifiers":[
        {
            "category":"Professional",
            "subcategory":"Accounting & Tax Preparation",
            "type":"Services"
        }
    ],
    "sg:phone":"+44 1235 520131",
    "sg:postcode":"OX14 5DH",
    "sg:province":"Oxfordshire",
    "sg:tags":[
        "accountant"
    ],
    "wof:name":"Mercer Hammond",
    "wof:placetype":"venue"
},
  "geometry": {"coordinates":[-1.288302,51.669567],"type":"Point"}
}