{
  "type": "Feature",
  "properties": {
    "addr:full":"139 Manse Road Motherwell North Lanarkshire ML1 2PS",
    "addr:housenumber":"139",
    "addr:postcode":"ml1 2ps",
    "addr:street":"Manse Road",
    "iso:country":"GB",
    "sg:address":"139 Manse Road",
    "sg:city":"Motherwell",
    "sg:classifiers":[
        {
            "category":"Professional",
            "subcategory":"Management & Consulting",
            "type":"Services"
        }
    ],
    "sg:phone":"+44 1698 275467",
    "sg:postcode":"ML1 2PS",
    "sg:province":"North Lanarkshire",
    "sg:tags":[
        "consultant",
        "investigation",
        "site"
    ],
    "wof:name":"Geotechnical Services Ltd.",
    "wof:placetype":"venue"
},
  "geometry": {"coordinates":[-3.98315,55.780125],"type":"Point"}
}