{
  "type": "Feature",
  "properties": {
    "addr:full":"10 Alexandra Road Lytham St Annes Lancashire FY8 1YE",
    "addr:housenumber":"10",
    "addr:postcode":"fy8 1ye",
    "addr:street":"Alexandra Road",
    "iso:country":"GB",
    "sg:address":"10 Alexandra Road",
    "sg:city":"Lytham St Annes",
    "sg:classifiers":[
        {
            "category":"Wholesale",
            "subcategory":"Electrical",
            "type":"Manufacturing & Wholesale Goods"
        }
    ],
    "sg:phone":"+44 1253 721598",
    "sg:postcode":"FY8 1YE",
    "sg:province":"Lancashire",
    "sg:tags":[
        "equipment",
        "refrigeration"
    ],
    "wof:name":"Wood H & T Refrigeration Air Conditioning",
    "wof:placetype":"venue"
},
  "geometry": {"coordinates":[-3.0189230442,53.7543640137],"type":"Point"}
}