{
  "type": "Feature",
  "properties": {
    "iso:country":"GB",
    "sg:address":"398a Ripple Road",
    "sg:city":"Barking",
    "sg:classifiers":[
        {
            "category":"Retail",
            "subcategory":"Auto Repair",
            "type":"Services"
        }
    ],
    "sg:phone":"+44 20 8594 7177",
    "sg:postcode":"IG11 9RS",
    "sg:province":"Essex",
    "sg:tags":[
        "modification",
        "garage"
    ],
    "wof:name":"Blake Autopoint",
    "wof:placetype":"venue"
},
  "geometry": {"coordinates":[0.094895,51.535511],"type":"Point"}
}