{
  "type": "Feature",
  "properties": {
    "iso:country":"GB",
    "sg:address":"Cressex Road",
    "sg:city":"High Wycombe",
    "sg:classifiers":[
        {
            "category":"Health Services",
            "subcategory":"Hospital",
            "type":"Services"
        }
    ],
    "sg:phone":"+44 1494 526161",
    "sg:postcode":"HP12 4QG",
    "sg:province":"Buckinghamshire",
    "wof:name":"Booker Hospital",
    "wof:placetype":"venue"
},
  "geometry": {"coordinates":[-0.770949,51.615799],"type":"Point"}
}