{
  "type": "Feature",
  "properties": {
    "addr:full":"35 Bagshot St Elephant And Castle Greater London SE17 2QW",
    "addr:housenumber":"35",
    "addr:postcode":"se17 2qw",
    "addr:street":"Bagshot St",
    "iso:country":"GB",
    "sg:address":"35 Bagshot St",
    "sg:city":"Elephant And Castle",
    "sg:classifiers":[
        {
            "category":"Food & Beverages",
            "subcategory":"Meat & Fish",
            "type":"Retail Goods"
        }
    ],
    "sg:phone":"+44 20 7703 9161",
    "sg:postcode":"SE17 2QW",
    "sg:province":"Greater London",
    "sg:tags":[
        "chip"
    ],
    "wof:name":"Mus's Chip Shop",
    "wof:placetype":"venue"
},
  "geometry": {"coordinates":[-0.084839,51.487061],"type":"Point"}
}