{
  "type": "Feature",
  "properties": {
    "addr:full":"Staynor House, Chapel Street, Epworth Doncaster Lincolnshire DN9 1HH",
    "addr:postcode":"dn9 1hh",
    "addr:street":"Chapel Street",
    "iso:country":"GB",
    "sg:address":"Staynor House, Chapel Street, Epworth",
    "sg:city":"Doncaster",
    "sg:classifiers":[
        {
            "category":"Professional",
            "subcategory":"Engineering",
            "type":"Services"
        }
    ],
    "sg:postcode":"DN9 1HH",
    "sg:province":"Lincolnshire",
    "sg:tags":[
        "civil",
        "engineer"
    ],
    "wof:name":"Stevenson Associates",
    "wof:placetype":"venue"
},
  "geometry": {"coordinates":[-0.82413,53.525673],"type":"Point"}
}