{
  "type": "Feature",
  "properties": {
    "iso:country":"GB",
    "sg:address":"Suite A Concept 2000, Sunderland Road",
    "sg:city":"Gateshead",
    "sg:classifiers":[
        {
            "category":"Professional",
            "subcategory":"Advertising",
            "type":"Services"
        }
    ],
    "sg:phone":"+44 191 469 7070",
    "sg:postcode":"NE10 9LQ",
    "sg:province":"Tyne and Wear",
    "wof:name":"North East Auto Freeway",
    "wof:placetype":"venue"
},
  "geometry": {"coordinates":[-1.5762900114,54.9540481567],"type":"Point"}
}