{
  "type": "Feature",
  "properties": {
    "iso:country":"GB",
    "sg:address":"Hurst Park Medical Practice, 2a Hurst Park Av",
    "sg:city":"Cambridge",
    "sg:classifiers":[
        {
            "category":"Health Services",
            "subcategory":"Dentist",
            "type":"Services"
        }
    ],
    "sg:phone":"+44 1223 356765",
    "sg:postcode":"CB4 2AE",
    "sg:province":"Cambridgeshire",
    "wof:name":"J H Nicoll",
    "wof:placetype":"venue"
},
  "geometry": {"coordinates":[0.1287699938,52.219871521],"type":"Point"}
}