{
  "type": "Feature",
  "properties": {
    "addr:full":"Unit 15 Miry Lane Wigan Lancashire WN6 7TG",
    "addr:housenumber":"unit 15",
    "addr:postcode":"wn6 7tg",
    "addr:street":"Miry Lane",
    "iso:country":"GB",
    "sg:address":"Unit 15 Miry Lane",
    "sg:city":"Wigan",
    "sg:classifiers":[
        {
            "category":"Bus Charters",
            "type":"Transportation"
        }
    ],
    "sg:phone":"+44 1942 820343",
    "sg:postcode":"WN6 7TG",
    "sg:province":"Lancashire",
    "sg:tags":[
        "hire",
        "coach"
    ],
    "wof:name":"Springfield Coachways",
    "wof:placetype":"venue"
},
  "geometry": {"coordinates":[-2.647279,53.547356],"type":"Point"}
}