{
  "type": "Feature",
  "properties": {
    "addr:full":"13 Falsgrave Road Scarborough North Yorkshire YO12 5EA",
    "addr:housenumber":"13",
    "addr:postcode":"yo12 5ea",
    "addr:street":"Falsgrave Road",
    "iso:country":"GB",
    "sg:address":"13 Falsgrave Road",
    "sg:city":"Scarborough",
    "sg:classifiers":[
        {
            "category":"Home & Garden",
            "subcategory":"Home Furnishings",
            "type":"Retail Goods"
        }
    ],
    "sg:phone":"+44 1723 360449",
    "sg:postcode":"YO12 5EA",
    "sg:province":"North Yorkshire",
    "sg:tags":[
        "blind",
        "manufacture",
        "fitting",
        "curtain"
    ],
    "wof:name":"The Sewing Service",
    "wof:placetype":"venue"
},
  "geometry": {"coordinates":[-0.4102790058,54.2781524658],"type":"Point"}
}