{
  "type": "Feature",
  "properties": {
    "addr:full":"6b The Square Guildford Surrey GU1 4YD",
    "addr:housenumber":"6b",
    "addr:postcode":"gu1 4yd",
    "addr:street":"The Square",
    "iso:country":"GB",
    "sg:address":"6b The Square",
    "sg:city":"Guildford",
    "sg:classifiers":[
        {
            "category":"Professional",
            "subcategory":"Business Services",
            "type":"Services"
        }
    ],
    "sg:phone":"+44 1428 713713",
    "sg:postcode":"GU1 4YD",
    "sg:province":"Surrey",
    "sg:tags":[
        "holding"
    ],
    "wof:name":"United Business Group Plc",
    "wof:placetype":"venue"
},
  "geometry": {"coordinates":[-0.570516,51.237087],"type":"Point"}
}