{
  "type": "Feature",
  "properties": {
    "addr:full":"Little Hall Farm, Cottage Lane Ormskirk Lancashire L39 3NQ",
    "addr:postcode":"l39 3nq",
    "addr:street":"Lane",
    "iso:country":"GB",
    "sg:address":"Little Hall Farm, Cottage Lane",
    "sg:city":"Ormskirk",
    "sg:classifiers":[
        {
            "category":"Wholesale",
            "subcategory":"Fruits & Vegetables",
            "type":"Manufacturing & Wholesale Goods"
        },
        {
            "category":"Sports & Exercise",
            "subcategory":"Skate Park",
            "type":"Entertainment"
        }
    ],
    "sg:phone":"+44 1695 572059",
    "sg:postcode":"L39 3NQ",
    "sg:province":"Lancashire",
    "sg:tags":[
        "grower",
        "mushroom"
    ],
    "wof:name":"J Rothwell & Son Ltd.",
    "wof:placetype":"venue"
},
  "geometry": {"coordinates":[-2.8863,53.566277],"type":"Point"}
}