{
  "type": "Feature",
  "properties": {
    "addr:full":"Breakspear House, Bury Street Ruislip Greater London HA4 7SY",
    "addr:postcode":"ha4 7sy",
    "addr:street":"Bury Street",
    "iso:country":"GB",
    "sg:address":"Breakspear House, Bury Street",
    "sg:city":"Ruislip",
    "sg:classifiers":[
        {
            "category":"Professional",
            "type":"Services"
        }
    ],
    "sg:phone":"+44 1895 633655",
    "sg:postcode":"HA4 7SY",
    "sg:province":"Greater London",
    "sg:tags":[
        "directory",
        "pub"
    ],
    "wof:name":"Andsome Prints",
    "wof:placetype":"venue"
},
  "geometry": {"coordinates":[-0.435131,51.586277],"type":"Point"}
}