{
  "type": "Feature",
  "properties": {
    "addr:full":"7a Truro Walk Chippenham Gloucestershire SN14 0QY",
    "addr:housenumber":"7a",
    "addr:postcode":"sn14 0qy",
    "addr:street":"Truro Walk",
    "iso:country":"GB",
    "sg:address":"7a Truro Walk",
    "sg:city":"Chippenham",
    "sg:classifiers":[
        {
            "category":"Home & Garden",
            "subcategory":"Home Furnishings",
            "type":"Retail Goods"
        }
    ],
    "sg:postcode":"SN14 0QY",
    "sg:province":"Gloucestershire",
    "sg:tags":[
        "blind",
        "curtain",
        "fitting"
    ],
    "wof:name":"All Sewn Up",
    "wof:placetype":"venue"
},
  "geometry": {"coordinates":[-2.1469271183,51.4545516968],"type":"Point"}
}