{
  "type": "Feature",
  "properties": {
    "iso:country":"GB",
    "sg:address":"116 Brockenhurst Avenue",
    "sg:city":"Worcester Park",
    "sg:classifiers":[
        {
            "category":"Professional",
            "subcategory":"Business Services",
            "type":"Services"
        }
    ],
    "sg:postcode":"KT4 7RE",
    "sg:province":"Surrey",
    "wof:name":"Russett Services Ltd.",
    "wof:placetype":"venue"
},
  "geometry": {"coordinates":[-0.259165,51.383568],"type":"Point"}
}