{
  "type": "Feature",
  "properties": {
    "addr:full":"Eglin Ave, Maida Vale London Greater London W9 3QP",
    "addr:postcode":"w9 3qp",
    "addr:street":"Eglin Ave",
    "iso:country":"GB",
    "sg:address":"Eglin Ave, Maida Vale",
    "sg:city":"London",
    "sg:classifiers":[
        {
            "category":"Bars & Pubs",
            "type":"Food & Drink"
        }
    ],
    "sg:postcode":"W9 3QP",
    "sg:province":"Greater London",
    "sg:tags":[
        "pubs",
        "inn"
    ],
    "wof:name":"Barry,G,",
    "wof:placetype":"venue"
},
  "geometry": {"coordinates":[-0.1952590048,51.5258712769],"type":"Point"}
}