{
  "type": "Feature",
  "properties": {
    "iso:country":"GB",
    "sg:address":"Unit 1, Larkfield Centre, Stonefield Road",
    "sg:city":"Glasgow",
    "sg:classifiers":[
        {
            "category":"Home & Garden",
            "subcategory":"Home Furnishings",
            "type":"Retail Goods"
        }
    ],
    "sg:phone":"+44 1698 829836",
    "sg:postcode":"G72 0HD",
    "sg:province":"South Lanarkshire",
    "sg:tags":[
        "awning",
        "canopy",
        "blinds"
    ],
    "wof:name":"J D S (Window Blinds)",
    "wof:placetype":"venue"
},
  "geometry": {"coordinates":[-4.0989608765,55.7855186462],"type":"Point"}
}