{
  "type": "Feature",
  "properties": {
    "addr:full":"6 Ruthrie Road Aberdeen Aberdeen City AB10 7HN",
    "addr:housenumber":"6",
    "addr:postcode":"ab10 7hn",
    "addr:street":"Ruthrie Road",
    "iso:country":"GB",
    "sg:address":"6 Ruthrie Road",
    "sg:city":"Aberdeen",
    "sg:classifiers":[
        {
            "category":"Building & Trades",
            "subcategory":"Construction",
            "type":"Services"
        }
    ],
    "sg:postcode":"AB10 7HN",
    "sg:province":"Aberdeen City",
    "sg:tags":[
        "dry",
        "lining",
        "plasterers",
        "screeders"
    ],
    "wof:name":"Ace",
    "wof:placetype":"venue"
},
  "geometry": {"coordinates":[-2.125532,57.127216],"type":"Point"}
}