{
  "type": "Feature",
  "properties": {
    "addr:full":"1 Oakridge Rd Bromley Kent BR1 5QW",
    "addr:housenumber":"1",
    "addr:postcode":"br1 5qw",
    "addr:street":"Oakridge Rd",
    "iso:country":"GB",
    "sg:address":"1 Oakridge Rd",
    "sg:city":"Bromley",
    "sg:classifiers":[
        {
            "category":"Communications",
            "type":"Services"
        }
    ],
    "sg:phone":"+44 20 8461 4614",
    "sg:postcode":"BR1 5QW",
    "sg:province":"Kent",
    "sg:tags":[
        "broadcasting"
    ],
    "wof:name":"Fairfield Advertising Department",
    "wof:placetype":"venue"
},
  "geometry": {"coordinates":[-0.004679,51.4257011414],"type":"Point"}
}