{
  "type": "Feature",
  "properties": {
    "iso:country":"GB",
    "sg:address":"46 Seaway Avenue, Friarscliff",
    "sg:city":"Christchurch",
    "sg:classifiers":[
        {
            "category":"Real Estate",
            "subcategory":"Architect",
            "type":"Services"
        }
    ],
    "sg:phone":"+44 1425 271701",
    "sg:postcode":"BH23 4EX",
    "sg:province":"Dorset",
    "wof:name":"Richard Green Associates",
    "wof:placetype":"venue"
},
  "geometry": {"coordinates":[-1.726408,50.734978],"type":"Point"}
}