{
  "type": "Feature",
  "properties": {
    "addr:full":"98-100 Chichester Road Bognor Regis West Sussex PO21 5AA",
    "addr:housenumber":"98-100",
    "addr:postcode":"po21 5aa",
    "addr:street":"Chichester Road",
    "iso:country":"GB",
    "sg:address":"98-100 Chichester Road",
    "sg:city":"Bognor Regis",
    "sg:classifiers":[
        {
            "category":"Banks & Credit Unions",
            "subcategory":"Financial Services",
            "type":"Services"
        }
    ],
    "sg:phone":"+44 1243 866522",
    "sg:postcode":"PO21 5AA",
    "sg:province":"West Sussex",
    "sg:tags":[
        "adviser"
    ],
    "wof:name":"Allfield Ltd.",
    "wof:placetype":"venue"
},
  "geometry": {"coordinates":[-0.6810230017,50.7946815491],"type":"Point"}
}