{
  "type": "Feature",
  "properties": {
    "addr:full":"42 Horsemarket Barnard Castle Cumbria DL12 8NA",
    "addr:housenumber":"42",
    "addr:postcode":"dl12 8na",
    "addr:street":"Horsemarket",
    "iso:country":"GB",
    "sg:address":"42 Horsemarket",
    "sg:city":"Barnard Castle",
    "sg:classifiers":[
        {
            "category":"Bars & Pubs",
            "type":"Food & Drink"
        }
    ],
    "sg:phone":"+44 1833 637232",
    "sg:postcode":"DL12 8NA",
    "sg:province":"Cumbria",
    "sg:tags":[
        "pubs",
        "inn"
    ],
    "wof:name":"Teesdale Traditional Taverns",
    "wof:placetype":"venue"
},
  "geometry": {"coordinates":[-1.9233590364,54.5434265137],"type":"Point"}
}