{
  "type": "Feature",
  "properties": {
    "iso:country":"GB",
    "sg:address":"21 Halifax Road",
    "sg:city":"Brighouse",
    "sg:classifiers":[
        {
            "category":"Building & Trades",
            "subcategory":"Plumbing",
            "type":"Services"
        }
    ],
    "sg:phone":"+44 1484 718357",
    "sg:postcode":"HD6 2AA",
    "sg:province":"West Yorkshire",
    "sg:tags":[
        "central",
        "heating"
    ],
    "wof:name":"Fuelsave Gas Central Heating",
    "wof:placetype":"venue"
},
  "geometry": {"coordinates":[-1.786542058,53.7031440735],"type":"Point"}
}