{
  "type": "Feature",
  "properties": {
    "iso:country":"GB",
    "sg:address":"20 Lostwithiel Street",
    "sg:city":"Fowey",
    "sg:classifiers":[
        {
            "category":"Communications",
            "subcategory":"Newspaper",
            "type":"Services"
        }
    ],
    "sg:phone":"+44 1726 833666",
    "sg:postcode":"PL23 1BE",
    "sg:province":"Cornwall",
    "sg:tags":[
        "magazine"
    ],
    "wof:name":"Fowey News Publishing Co",
    "wof:placetype":"venue"
},
  "geometry": {"coordinates":[-4.6361880302,50.3350791931],"type":"Point"}
}