{
  "type": "Feature",
  "properties": {
    "iso:country":"GB",
    "sg:address":"104 Thorpe Road",
    "sg:city":"Norwich",
    "sg:classifiers":[
        {
            "category":"Organizations",
            "subcategory":"Membership Organization",
            "type":"Services"
        }
    ],
    "sg:phone":"+44 1603 627342",
    "sg:postcode":"NR1 1RT",
    "sg:province":"Norfolk",
    "sg:tags":[
        "club"
    ],
    "wof:name":"The Canary Social Club",
    "wof:placetype":"venue"
},
  "geometry": {"coordinates":[1.3122739792,52.6264457703],"type":"Point"}
}