{
  "type": "Feature",
  "properties": {
    "iso:country":"GB",
    "sg:address":"209 Ynysddu",
    "sg:city":"Pontyclun",
    "sg:classifiers":[
        {
            "category":"Retail",
            "subcategory":"Repair Shop",
            "type":"Services"
        }
    ],
    "sg:phone":"+44 1443 227918",
    "sg:postcode":"CF72 9UE",
    "sg:province":"Bridgend",
    "sg:tags":[
        "maintenance"
    ],
    "wof:name":"Help In Hand",
    "wof:placetype":"venue"
},
  "geometry": {"coordinates":[-3.435084,51.529934],"type":"Point"}
}