{
  "type": "Feature",
  "properties": {
    "addr:full":"18 Gillibrand Street Chorley Lancashire PR7 2EJ",
    "addr:housenumber":"18",
    "addr:postcode":"pr7 2ej",
    "addr:street":"Gillibrand Street",
    "iso:country":"GB",
    "sg:address":"18 Gillibrand Street",
    "sg:city":"Chorley",
    "sg:classifiers":[
        {
            "category":"Professional",
            "subcategory":"Business Services",
            "type":"Services"
        }
    ],
    "sg:phone":"+44 1257 416024",
    "sg:postcode":"PR7 2EJ",
    "sg:province":"Lancashire",
    "sg:tags":[
        "house",
        "mailing"
    ],
    "wof:name":"E M S",
    "wof:placetype":"venue"
},
  "geometry": {"coordinates":[-2.632535,53.651443],"type":"Point"}
}