{
  "type": "Feature",
  "properties": {
    "addr:full":"Walton Street Liverpool Merseyside L17 3BH",
    "addr:postcode":"l17 3bh",
    "addr:street":"Walton Street",
    "iso:country":"GB",
    "sg:address":"Walton Street",
    "sg:city":"Liverpool",
    "sg:classifiers":[
        {
            "category":"Retail",
            "subcategory":"Auto Repair",
            "type":"Services"
        }
    ],
    "sg:phone":"+44 151 207 2553",
    "sg:postcode":"L17 3BH",
    "sg:province":"Merseyside",
    "sg:tags":[
        "modification",
        "garage"
    ],
    "wof:name":"W & M Motors",
    "wof:placetype":"venue"
},
  "geometry": {"coordinates":[-2.9676148891,53.4369888306],"type":"Point"}
}