{
  "type": "Feature",
  "properties": {
    "addr:full":"2 Crummock Ct Wallsend Tyne and Wear NE28 0NL",
    "addr:housenumber":"2",
    "addr:postcode":"ne28 0nl",
    "addr:street":"Crummock Ct",
    "iso:country":"GB",
    "sg:address":"2 Crummock Ct",
    "sg:city":"Wallsend",
    "sg:classifiers":[
        {
            "category":"Social Services",
            "subcategory":"Adult Care",
            "type":"Services"
        }
    ],
    "sg:phone":"+44 191 263 1847",
    "sg:postcode":"NE28 0NL",
    "sg:province":"Tyne and Wear",
    "sg:tags":[
        "housing",
        "sheltered"
    ],
    "wof:name":"Crummock Court",
    "wof:placetype":"venue"
},
  "geometry": {"coordinates":[-1.49905,55.003422],"type":"Point"}
}