{
  "type": "Feature",
  "properties": {
    "iso:country":"GB",
    "sg:address":"25 Street La",
    "sg:city":"Leeds",
    "sg:classifiers":[
        {
            "category":"Health Services",
            "subcategory":"Dentist",
            "type":"Services"
        }
    ],
    "sg:phone":"+44 113 266 3659",
    "sg:postcode":"LS8 1BW",
    "sg:province":"West Yorkshire",
    "wof:name":"N R Shafi",
    "wof:placetype":"venue"
},
  "geometry": {"coordinates":[-1.506283,53.843208],"type":"Point"}
}