{
  "type": "Feature",
  "properties": {
    "addr:full":"132 Dawpool Road, Neasden London Greater London NW2 7JY",
    "addr:housenumber":"132",
    "addr:postcode":"nw2 7jy",
    "addr:street":"Dawpool Road",
    "iso:country":"GB",
    "sg:address":"132 Dawpool Road, Neasden",
    "sg:city":"London",
    "sg:classifiers":[
        {
            "category":"Building & Trades",
            "subcategory":"Construction",
            "type":"Services"
        }
    ],
    "sg:postcode":"NW2 7JY",
    "sg:province":"Greater London",
    "sg:tags":[
        "contractor"
    ],
    "wof:name":"Aldridge Construction Ltd.",
    "wof:placetype":"venue"
},
  "geometry": {"coordinates":[-0.2421160042,51.5667381287],"type":"Point"}
}