{
  "type": "Feature",
  "properties": {
    "addr:full":"26 Chapel Lane Wilmslow Cheshire SK9 5HZ",
    "addr:housenumber":"26",
    "addr:postcode":"sk9 5hz",
    "addr:street":"Chapel Lane",
    "iso:country":"GB",
    "sg:address":"26 Chapel Lane",
    "sg:city":"Wilmslow",
    "sg:classifiers":[
        {
            "category":"Personal",
            "subcategory":"Beauty Salon",
            "type":"Services"
        }
    ],
    "sg:phone":"+44 1625 536073",
    "sg:postcode":"SK9 5HZ",
    "sg:province":"Cheshire",
    "wof:name":"Leah Beauty Therapy Clinic",
    "wof:placetype":"venue"
},
  "geometry": {"coordinates":[-2.239099,53.322735],"type":"Point"}
}