{
  "type": "Feature",
  "properties": {
    "iso:country":"GB",
    "sg:address":"17 West Street, St Philips",
    "sg:city":"Bristol",
    "sg:classifiers":[
        {
            "category":"Wholesale",
            "subcategory":"Photographic Equipment",
            "type":"Manufacturing & Wholesale Goods"
        }
    ],
    "sg:postcode":"BS2 0DF",
    "sg:province":"City of Bristol",
    "sg:tags":[
        "repair"
    ],
    "wof:name":"Luton Camera Repairs (Bristol)",
    "wof:placetype":"venue"
},
  "geometry": {"coordinates":[-2.579365,51.456776],"type":"Point"}
}