{
  "type": "Feature",
  "properties": {
    "addr:full":"71 Harrington Gardens London Greater London SW7 4JZ",
    "addr:housenumber":"71",
    "addr:postcode":"sw7 4jz",
    "addr:street":"Harrington Gardens",
    "iso:country":"GB",
    "sg:address":"71 Harrington Gardens",
    "sg:city":"London",
    "sg:classifiers":[
        {
            "category":"Banks & Credit Unions",
            "subcategory":"Investment Brokerage",
            "type":"Services"
        }
    ],
    "sg:phone":"+44 20 7245 6237",
    "sg:postcode":"SW7 4JZ",
    "sg:province":"Greater London",
    "wof:name":"Kayton Estates Ltd.",
    "wof:placetype":"venue"
},
  "geometry": {"coordinates":[-0.186831,51.492241],"type":"Point"}
}