{
  "type": "Feature",
  "properties": {
    "addr:full":"10 George Street Newcastle Staffordshire ST5 1DH",
    "addr:housenumber":"10",
    "addr:postcode":"st5 1dh",
    "addr:street":"George Street",
    "iso:country":"GB",
    "sg:address":"10 George Street",
    "sg:city":"Newcastle",
    "sg:classifiers":[
        {
            "category":"Shopping",
            "subcategory":"Clothing, Apparel, & Fashions",
            "type":"Retail Goods"
        }
    ],
    "sg:postcode":"ST5 1DH",
    "sg:province":"Staffordshire",
    "sg:tags":[
        "menswear"
    ],
    "wof:name":"Paul La Gambina International",
    "wof:placetype":"venue"
},
  "geometry": {"coordinates":[-2.218584,53.012318],"type":"Point"}
}