{
  "type": "Feature",
  "properties": {
    "addr:full":"12-14 Low Street, South Millford Leeds North Yorkshire LS25 5AR",
    "addr:housenumber":"12-14",
    "addr:postcode":"ls25 5ar",
    "addr:street":"Low Street South",
    "iso:country":"GB",
    "sg:address":"12-14 Low Street, South Millford",
    "sg:city":"Leeds",
    "sg:classifiers":[
        {
            "category":"Building & Trades",
            "subcategory":"Construction",
            "type":"Services"
        }
    ],
    "sg:postcode":"LS25 5AR",
    "sg:province":"North Yorkshire",
    "sg:tags":[
        "joiner",
        "carpenter"
    ],
    "wof:name":"David P Sample",
    "wof:placetype":"venue"
},
  "geometry": {"coordinates":[-1.2479239702,53.7788887024],"type":"Point"}
}