{
  "type": "Feature",
  "properties": {
    "addr:full":"151 Church St Blackpool Lancashire FY1 3NX",
    "addr:housenumber":"151",
    "addr:postcode":"fy1 3nx",
    "addr:street":"Church St",
    "iso:country":"GB",
    "sg:address":"151 Church St",
    "sg:city":"Blackpool",
    "sg:classifiers":[
        {
            "category":"Shopping",
            "subcategory":"Bicycles & Sporting Goods",
            "type":"Retail Goods"
        }
    ],
    "sg:postcode":"FY1 3NX",
    "sg:province":"Lancashire",
    "sg:tags":[
        "dance",
        "balletwear"
    ],
    "wof:name":"Chinta Danceworld",
    "wof:placetype":"venue"
},
  "geometry": {"coordinates":[-3.047388,53.817833],"type":"Point"}
}