{
  "type": "Feature",
  "properties": {
    "addr:full":"Northumberland House Building 863, Beacon Rd Hounslow Greater London TW6 3JG",
    "addr:housenumber":"863",
    "addr:postcode":"tw6 3jg",
    "addr:street":"Beacon Rd",
    "iso:country":"GB",
    "sg:address":"Northumberland House Building 863, Beacon Rd",
    "sg:city":"Hounslow",
    "sg:classifiers":[
        {
            "category":"Building & Trades",
            "subcategory":"Equipment Rental",
            "type":"Services"
        }
    ],
    "sg:phone":"+44 20 8897 2209",
    "sg:postcode":"TW6 3JG",
    "sg:province":"Greater London",
    "sg:tags":[
        "hire",
        "centre"
    ],
    "wof:name":"Hewden Hire Centres",
    "wof:placetype":"venue"
},
  "geometry": {"coordinates":[-0.4547390044,51.4560127258],"type":"Point"}
}