{
  "type": "Feature",
  "properties": {
    "iso:country":"GB",
    "sg:address":"Rose Cottage, The Square, Nether Wallop",
    "sg:city":"Stockbridge",
    "sg:classifiers":[
        {
            "category":"Real Estate",
            "subcategory":"Architect",
            "type":"Services"
        }
    ],
    "sg:postcode":"SO20 8EX",
    "sg:province":"Hampshire",
    "wof:name":"Paul Robinson Chartered Architect",
    "wof:placetype":"venue"
},
  "geometry": {"coordinates":[-1.573193,51.127632],"type":"Point"}
}