{
  "type": "Feature",
  "properties": {
    "addr:full":"Community Centre, Micklefield Road High Wycombe Buckinghamshire HP13 7AQ",
    "addr:postcode":"hp13 7aq",
    "addr:street":"Micklefield Road",
    "iso:country":"GB",
    "sg:address":"Community Centre, Micklefield Road",
    "sg:city":"High Wycombe",
    "sg:classifiers":[
        {
            "category":"Education",
            "subcategory":"School",
            "type":"Public Place"
        },
        {
            "category":"Community Center",
            "type":"Public Place"
        }
    ],
    "sg:phone":"+44 1494 462912",
    "sg:postcode":"HP13 7AQ",
    "sg:province":"Buckinghamshire",
    "sg:tags":[
        "local",
        "authority",
        "centre"
    ],
    "wof:name":"Micklefield Community Association",
    "wof:placetype":"venue"
},
  "geometry": {"coordinates":[-0.747789,51.628944],"type":"Point"}
}