{
  "type": "Feature",
  "properties": {
    "iso:country":"GB",
    "sg:address":"Red Hill House, Hope Street",
    "sg:city":"Chester",
    "sg:classifiers":[
        {
            "category":"Professional",
            "subcategory":"Engineering",
            "type":"Services"
        }
    ],
    "sg:postcode":"CH4 8BU",
    "sg:province":"Cheshire",
    "sg:tags":[
        "design",
        "engineer"
    ],
    "wof:name":"Brady Engineering Consultants Limited",
    "wof:placetype":"venue"
},
  "geometry": {"coordinates":[-2.916774,53.179329],"type":"Point"}
}