{
  "type": "Feature",
  "properties": {
    "addr:full":"34 Avenue Parade Accrington Lancashire BB5 6PP",
    "addr:housenumber":"34",
    "addr:postcode":"bb5 6pp",
    "addr:street":"Avenue Parade",
    "iso:country":"GB",
    "sg:address":"34 Avenue Parade",
    "sg:city":"Accrington",
    "sg:classifiers":[
        {
            "category":"Professional",
            "subcategory":"Computer Services",
            "type":"Services"
        }
    ],
    "sg:postcode":"BB5 6PP",
    "sg:province":"Lancashire",
    "sg:tags":[
        "system",
        "software"
    ],
    "wof:name":"Pierlink Ltd",
    "wof:placetype":"venue"
},
  "geometry": {"coordinates":[-2.3606519699,53.7544326782],"type":"Point"}
}