{
  "type": "Feature",
  "properties": {
    "addr:full":"Woodlands Rd Barry The Vale of Glamorgan CF63 4EF",
    "addr:postcode":"cf63 4ef",
    "addr:street":"Woodlands Rd;Vale",
    "iso:country":"GB",
    "sg:address":"Woodlands Rd",
    "sg:city":"Barry",
    "sg:classifiers":[
        {
            "category":"Social Services",
            "subcategory":"Child Care",
            "type":"Services"
        },
        {
            "category":"Social Services",
            "subcategory":"Adult Care",
            "type":"Services"
        }
    ],
    "sg:phone":"+44 1446 732158",
    "sg:postcode":"CF63 4EF",
    "sg:province":"The Vale of Glamorgan",
    "sg:tags":[
        "day",
        "centre"
    ],
    "wof:name":"Woodlands Day Centre",
    "wof:placetype":"venue"
},
  "geometry": {"coordinates":[-3.2643129826,51.4093170166],"type":"Point"}
}