{
  "type": "Feature",
  "properties": {
    "addr:full":"7a Station Terrace East Boldon Tyne and Wear NE36 0LJ",
    "addr:housenumber":"7a",
    "addr:postcode":"ne36 0lj",
    "addr:street":"Station Terrace",
    "iso:country":"GB",
    "sg:address":"7a Station Terrace",
    "sg:city":"East Boldon",
    "sg:classifiers":[
        {
            "category":"Professional",
            "subcategory":"Lawyer & Legal Services",
            "type":"Services"
        }
    ],
    "sg:phone":"+44 191 536 6579",
    "sg:postcode":"NE36 0LJ",
    "sg:province":"Tyne and Wear",
    "sg:tags":[
        "solicitor"
    ],
    "wof:name":"George Sainthouse",
    "wof:placetype":"venue"
},
  "geometry": {"coordinates":[-1.420576,54.947445],"type":"Point"}
}