{
  "type": "Feature",
  "properties": {
    "iso:country":"GB",
    "sg:address":"3 Charterhouse Mews",
    "sg:city":"London",
    "sg:classifiers":[
        {
            "category":"Professional",
            "subcategory":"Management & Consulting",
            "type":"Services"
        }
    ],
    "sg:phone":"+44 20 7253 8244",
    "sg:postcode":"EC1M 6BB",
    "sg:province":"Greater London",
    "sg:tags":[
        "consultant",
        "business"
    ],
    "wof:name":"Singer & Co",
    "wof:placetype":"venue"
},
  "geometry": {"coordinates":[-0.100849,51.521233],"type":"Point"}
}