{
  "type": "Feature",
  "properties": {
    "iso:country":"GB",
    "sg:address":"120 Hartley Road, Radford",
    "sg:city":"Nottingham",
    "sg:classifiers":[
        {
            "category":"Government",
            "subcategory":"Customs House",
            "type":"Public Place"
        }
    ],
    "sg:postcode":"NG7 3AJ",
    "sg:province":"Nottinghamshire",
    "sg:tags":[
        "clearance"
    ],
    "wof:name":"Pats Tat",
    "wof:placetype":"venue"
},
  "geometry": {"coordinates":[-1.176211,52.960526],"type":"Point"}
}