{
  "type": "Feature",
  "properties": {
    "iso:country":"GB",
    "sg:address":"Station Rd, Buck Haven",
    "sg:city":"Leven",
    "sg:classifiers":[
        {
            "category":"Wholesale",
            "subcategory":"Vending Machines",
            "type":"Manufacturing & Wholesale Goods"
        }
    ],
    "sg:phone":"+44 1333 426793",
    "sg:postcode":"KY8 1JH",
    "sg:province":"Fife",
    "sg:tags":[
        "sale"
    ],
    "wof:name":"Allson Ltd",
    "wof:placetype":"venue"
},
  "geometry": {"coordinates":[-3.040604,56.174019],"type":"Point"}
}