{
  "type": "Feature",
  "properties": {
    "iso:country":"GB",
    "sg:address":"4 Crinan Street, Kingscross",
    "sg:city":"London",
    "sg:classifiers":[
        {
            "category":"Professional",
            "type":"Services"
        },
        {
            "category":"Professional",
            "subcategory":"Research",
            "type":"Services"
        }
    ],
    "sg:phone":"+44 20 7837 4872",
    "sg:postcode":"N1 9SQ",
    "sg:province":"Greater London",
    "sg:tags":[
        "directory",
        "pub",
        "market"
    ],
    "wof:name":"Market Assessment Publications Ltd.",
    "wof:placetype":"venue"
},
  "geometry": {"coordinates":[-0.1214630008,51.533870697],"type":"Point"}
}