{
  "type": "Feature",
  "properties": {
    "addr:full":"35-43 High St Harrow Greater London HA3 7AE",
    "addr:housenumber":"35-43",
    "addr:postcode":"ha3 7ae",
    "addr:street":"High St",
    "iso:country":"GB",
    "sg:address":"35-43 High St",
    "sg:city":"Harrow",
    "sg:classifiers":[
        {
            "category":"Food & Beverages",
            "subcategory":"Supermarket",
            "type":"Retail Goods"
        }
    ],
    "sg:phone":"+44 20 8424 2527",
    "sg:postcode":"HA3 7AE",
    "sg:province":"Greater London",
    "wof:name":"Joblot",
    "wof:placetype":"venue"
},
  "geometry": {"coordinates":[-0.337049,51.597912],"type":"Point"}
}