{
  "type": "Feature",
  "properties": {
    "addr:full":"Unit 15/17, Dryden Vale Loanhead Midlothian EH20 9HN",
    "addr:housenumber":"unit 15 / 17",
    "addr:postcode":"eh20 9hn",
    "addr:street":"Dryden Vale",
    "iso:country":"GB",
    "sg:address":"Unit 15/17, Dryden Vale",
    "sg:city":"Loanhead",
    "sg:classifiers":[
        {
            "category":"Professional",
            "type":"Services"
        },
        {
            "category":"Professional",
            "subcategory":"Printing & Photocopies",
            "type":"Services"
        }
    ],
    "sg:phone":"+44 131 440 9727",
    "sg:postcode":"EH20 9HN",
    "sg:province":"Midlothian",
    "sg:tags":[
        "printer",
        "publishing"
    ],
    "wof:name":"Capital Scanning Studios Ltd.",
    "wof:placetype":"venue"
},
  "geometry": {"coordinates":[-3.164621,55.876205],"type":"Point"}
}