{
  "type": "Feature",
  "properties": {
    "addr:full":"5 Queens Ride London Greater London SW13 0JB",
    "addr:housenumber":"5",
    "addr:postcode":"sw13 0jb",
    "addr:street":"Queens Ride",
    "iso:country":"GB",
    "sg:address":"5 Queens Ride",
    "sg:city":"London",
    "sg:classifiers":[
        {
            "category":"Shopping",
            "subcategory":"Gifts & Souvenirs",
            "type":"Retail Goods"
        }
    ],
    "sg:phone":"+44 20 8789 9393",
    "sg:postcode":"SW13 0JB",
    "sg:province":"Greater London",
    "sg:tags":[
        "greeting",
        "card"
    ],
    "wof:name":"Caroline Gardner Design Company",
    "wof:placetype":"venue"
},
  "geometry": {"coordinates":[-0.239589,51.46579],"type":"Point"}
}