{
  "type": "Feature",
  "properties": {
    "addr:full":"Hallsford Bridge Industrial Esta, Te Stondon Road Ongar Essex CM5 9RB",
    "addr:postcode":"cm5 9rb",
    "addr:street":"Stondon Road",
    "iso:country":"GB",
    "sg:address":"Hallsford Bridge Industrial Esta, Te Stondon Road",
    "sg:city":"Ongar",
    "sg:classifiers":[
        {
            "category":"Shopping",
            "type":"Retail Goods"
        }
    ],
    "sg:postcode":"CM5 9RB",
    "sg:province":"Essex",
    "sg:tags":[
        "med",
        "scientific",
        "apparatus"
    ],
    "wof:name":"Optical Technology Ltd.",
    "wof:placetype":"venue"
},
  "geometry": {"coordinates":[0.259174,51.694519],"type":"Point"}
}