{
  "type": "Feature",
  "properties": {
    "iso:country":"GB",
    "sg:address":"Gwyddon Road, Abercarn",
    "sg:city":"Newport",
    "sg:classifiers":[
        {
            "category":"Education",
            "subcategory":"School",
            "type":"Public Place"
        }
    ],
    "sg:phone":"+44 1495 244267",
    "sg:postcode":"NP11 5GX",
    "sg:province":"Blaenau Gwent",
    "sg:tags":[
        "local",
        "authority"
    ],
    "wof:name":"Ysgol Gymraeg Cwm Gwyddon",
    "wof:placetype":"venue"
},
  "geometry": {"coordinates":[-3.131206,51.647949],"type":"Point"}
}