{
  "type": "Feature",
  "properties": {
    "iso:country":"GB",
    "sg:address":"Wilson Centre, Wilson Road",
    "sg:city":"Reading",
    "sg:classifiers":[
        {
            "category":"Education",
            "subcategory":"University",
            "type":"Public Place"
        }
    ],
    "sg:phone":"+44 118 958 1754",
    "sg:postcode":"RG30 2RW",
    "sg:province":"Berkshire",
    "sg:tags":[
        "adult"
    ],
    "wof:name":"Reading Educational Guidance Service For Adults",
    "wof:placetype":"venue"
},
  "geometry": {"coordinates":[-0.96301,51.453522],"type":"Point"}
}