{
  "type": "Feature",
  "properties": {
    "iso:country":"GB",
    "sg:address":"172 Bolton Road West, Ramsbottom",
    "sg:city":"Bury",
    "sg:classifiers":[
        {
            "category":"Building & Trades",
            "subcategory":"Plumbing",
            "type":"Services"
        }
    ],
    "sg:phone":"+44 1204 888912",
    "sg:postcode":"BL0 9PE",
    "sg:province":"Lancashire",
    "sg:tags":[
        "heating"
    ],
    "wof:name":"T Schofield Plumbing & Heating",
    "wof:placetype":"venue"
},
  "geometry": {"coordinates":[-2.3269040585,53.6394805908],"type":"Point"}
}