{
  "type": "Feature",
  "properties": {
    "addr:full":"30 Orgarswick Avenue, Dymchurch Romney Marsh Kent TN29 0NX",
    "addr:housenumber":"30",
    "addr:postcode":"tn29 0nx",
    "addr:street":"Orgarswick Avenue",
    "iso:country":"GB",
    "sg:address":"30 Orgarswick Avenue, Dymchurch",
    "sg:city":"Romney Marsh",
    "sg:classifiers":[
        {
            "category":"Recreation",
            "subcategory":"Boat Charter",
            "type":"Entertainment"
        }
    ],
    "sg:phone":"+44 1303 872329",
    "sg:postcode":"TN29 0NX",
    "sg:province":"Kent",
    "sg:tags":[
        "excursion"
    ],
    "wof:name":"J C & M J Coker",
    "wof:placetype":"venue"
},
  "geometry": {"coordinates":[0.992833972,51.0252761841],"type":"Point"}
}