{
  "type": "Feature",
  "properties": {
    "addr:full":"120 Camberwell Road, Camberwell London Greater London SE5 0EE",
    "addr:housenumber":"120",
    "addr:postcode":"se5 0ee",
    "addr:street":"Camberwell Road",
    "iso:country":"GB",
    "sg:address":"120 Camberwell Road, Camberwell",
    "sg:city":"London",
    "sg:classifiers":[
        {
            "category":"Professional",
            "subcategory":"Computer Services",
            "type":"Services"
        }
    ],
    "sg:phone":"+44 20 7701 1069",
    "sg:postcode":"SE5 0EE",
    "sg:province":"Greater London",
    "sg:tags":[
        "system",
        "software"
    ],
    "wof:name":"P C Stop",
    "wof:placetype":"venue"
},
  "geometry": {"coordinates":[-0.0944840014,51.4802589417],"type":"Point"}
}