{
  "type": "Feature",
  "properties": {
    "iso:country":"GB",
    "sg:address":"Abbey Mills, Abbey Road",
    "sg:city":"Leeds",
    "sg:classifiers":[
        {
            "category":"Manufacturing",
            "subcategory":"Building Materials",
            "type":"Manufacturing & Wholesale Goods"
        }
    ],
    "sg:postcode":"LS5 3HP",
    "sg:province":"West Yorkshire",
    "sg:tags":[
        "mnfr",
        "maker",
        "cabinet"
    ],
    "wof:name":"L Brunavs & Son",
    "wof:placetype":"venue"
},
  "geometry": {"coordinates":[-1.6028540134,53.8206481934],"type":"Point"}
}