{
  "type": "Feature",
  "properties": {
    "addr:full":"Burnfield House Glasgow East Renfrewshire G46 7TP",
    "addr:postcode":"g46 7tp",
    "iso:country":"GB",
    "sg:address":"Burnfield House",
    "sg:city":"Glasgow",
    "sg:classifiers":[
        {
            "category":"Building & Trades",
            "subcategory":"Landscaping Services",
            "type":"Services"
        },
        {
            "category":"Building & Trades",
            "subcategory":"Cleaning & Sanitation",
            "type":"Services"
        }
    ],
    "sg:postcode":"G46 7TP",
    "sg:province":"East Renfrewshire",
    "sg:tags":[
        "dry",
        "control",
        "damp",
        "preservation",
        "rot",
        "timber"
    ],
    "wof:name":"Healthy Homes Ltd.",
    "wof:placetype":"venue"
},
  "geometry": {"coordinates":[-4.3068590164,55.8012809753],"type":"Point"}
}