{
  "type": "Feature",
  "properties": {
    "addr:full":"Manor Rd, Kempston Hardwick Bedford Bedfordshire MK43 9NT",
    "addr:postcode":"mk43 9nt",
    "addr:street":"Manor Rd",
    "iso:country":"GB",
    "sg:address":"Manor Rd, Kempston Hardwick",
    "sg:city":"Bedford",
    "sg:classifiers":[
        {
            "category":"Home & Garden",
            "subcategory":"Building Materials",
            "type":"Retail Goods"
        }
    ],
    "sg:phone":"+44 1234 841546",
    "sg:postcode":"MK43 9NT",
    "sg:province":"Bedfordshire",
    "sg:tags":[
        "ready",
        "mixed",
        "concrete"
    ],
    "wof:name":"Redland Readymix Holdings Ltd",
    "wof:placetype":"venue"
},
  "geometry": {"coordinates":[-0.49159,52.086632],"type":"Point"}
}