{
  "type": "Feature",
  "properties": {
    "iso:country":"GB",
    "sg:address":"18 Melbourne Street",
    "sg:city":"Stalybridge",
    "sg:classifiers":[
        {
            "category":"Banks & Credit Unions",
            "subcategory":"Bank",
            "type":"Services"
        }
    ],
    "sg:phone":"+44 161 338 2119",
    "sg:postcode":"SK15 2JE",
    "sg:province":"Greater Manchester",
    "wof:name":"Yorkshire Bank Plc",
    "wof:placetype":"venue"
},
  "geometry": {"coordinates":[-2.057346,53.483143],"type":"Point"}
}