{
  "type": "Feature",
  "properties": {
    "addr:full":"High Road, Whaplode Spalding Cambridgeshire PE12 6TG",
    "addr:postcode":"pe12 6tg",
    "addr:street":"High Road;Spalding",
    "iso:country":"GB",
    "sg:address":"High Road, Whaplode",
    "sg:city":"Spalding",
    "sg:classifiers":[
        {
            "category":"Building & Trades",
            "subcategory":"Construction",
            "type":"Services"
        }
    ],
    "sg:phone":"+44 1406 370483",
    "sg:postcode":"PE12 6TG",
    "sg:province":"Cambridgeshire",
    "sg:tags":[
        "builder"
    ],
    "wof:name":"P L Ely (Contractors) Ltd.",
    "wof:placetype":"venue"
},
  "geometry": {"coordinates":[-0.070671998,52.8063964844],"type":"Point"}
}