{
  "type": "Feature",
  "properties": {
    "addr:full":"12-14 Hall Place Spalding Lincolnshire PE11 1SA",
    "addr:housenumber":"12-14",
    "addr:postcode":"pe11 1sa",
    "addr:street":"Hall Place",
    "iso:country":"GB",
    "sg:address":"12-14 Hall Place",
    "sg:city":"Spalding",
    "sg:classifiers":[
        {
            "category":"Shopping",
            "subcategory":"Pharmacy",
            "type":"Retail Goods"
        }
    ],
    "sg:phone":"+44 1775 722803",
    "sg:postcode":"PE11 1SA",
    "sg:province":"Lincolnshire",
    "sg:tags":[
        "pharmacist",
        "chemist"
    ],
    "wof:name":"Boots the Chemist",
    "wof:placetype":"venue"
},
  "geometry": {"coordinates":[-0.152438,52.787403],"type":"Point"}
}