{
  "type": "Feature",
  "properties": {
    "addr:full":"38 Sutherland Ave Sunbury-on-thames Surrey TW16 6LJ",
    "addr:housenumber":"38",
    "addr:postcode":"tw16 6lj",
    "addr:street":"Sutherland Ave",
    "iso:country":"GB",
    "sg:address":"38 Sutherland Ave",
    "sg:city":"Sunbury-on-thames",
    "sg:classifiers":[
        {
            "category":"Freight",
            "type":"Transportation"
        }
    ],
    "sg:postcode":"TW16 6LJ",
    "sg:province":"Surrey",
    "sg:tags":[
        "haulage",
        "road"
    ],
    "wof:name":"Miles Ahead Transport",
    "wof:placetype":"venue"
},
  "geometry": {"coordinates":[-0.4196330011,51.4125976562],"type":"Point"}
}