{
  "type": "Feature",
  "properties": {
    "addr:full":"Sevendale House, 7 Dale Street Manchester Greater Manchester M1 1JB",
    "addr:housenumber":"7",
    "addr:postcode":"m1 1jb",
    "addr:street":"Dale Street",
    "iso:country":"GB",
    "sg:address":"Sevendale House, 7 Dale Street",
    "sg:city":"Manchester",
    "sg:classifiers":[
        {
            "category":"Education",
            "subcategory":"Junior College",
            "type":"Public Place"
        },
        {
            "category":"Professional",
            "subcategory":"Business Services",
            "type":"Services"
        }
    ],
    "sg:phone":"+44 161 228 6733",
    "sg:postcode":"M1 1JB",
    "sg:province":"Greater Manchester",
    "sg:tags":[
        "distance",
        "secretarial",
        "learning"
    ],
    "wof:name":"National School Of Salesmanship Concessionaires Ltd",
    "wof:placetype":"venue"
},
  "geometry": {"coordinates":[-2.235539,53.482544],"type":"Point"}
}