{
  "type": "Feature",
  "properties": {
    "addr:full":"25 John Street Penicuik Midlothian EH26 8HN",
    "addr:housenumber":"25",
    "addr:postcode":"eh26 8hn",
    "addr:street":"John Street",
    "iso:country":"GB",
    "sg:address":"25 John Street",
    "sg:city":"Penicuik",
    "sg:classifiers":[
        {
            "category":"Professional",
            "subcategory":"Employment Agencies",
            "type":"Services"
        }
    ],
    "sg:phone":"+44 1968 623200",
    "sg:postcode":"EH26 8HN",
    "sg:province":"Midlothian",
    "sg:tags":[
        "consultant"
    ],
    "wof:name":"Department of Education & Skills",
    "wof:placetype":"venue"
},
  "geometry": {"coordinates":[-3.223769,55.83012],"type":"Point"}
}