{
  "type": "Feature",
  "properties": {
    "iso:country":"GB",
    "sg:address":"42 Loanda Ho, Linden Gro",
    "sg:city":"London",
    "sg:classifiers":[
        {
            "category":"Food & Beverages",
            "subcategory":"Bakery",
            "type":"Retail Goods"
        }
    ],
    "sg:postcode":"SE15 3QA",
    "sg:province":"Greater London",
    "sg:tags":[
        "baker"
    ],
    "wof:name":"Remmy Ventures Ltd",
    "wof:placetype":"venue"
},
  "geometry": {"coordinates":[-0.101282,51.495991],"type":"Point"}
}