{
  "type": "Feature",
  "properties": {
    "iso:country":"GB",
    "sg:address":"26 Green St, Ston Easton",
    "sg:city":"Bath",
    "sg:classifiers":[
        {
            "category":"Home & Garden",
            "subcategory":"Home Furnishings",
            "type":"Retail Goods"
        }
    ],
    "sg:postcode":"BA3 4DA",
    "sg:province":"Somerset",
    "sg:tags":[
        "furnishers",
        "planner",
        "kitchen"
    ],
    "wof:name":"Avonview Interiors",
    "wof:placetype":"venue"
},
  "geometry": {"coordinates":[-2.544617,51.28141],"type":"Point"}
}