{
  "type": "Feature",
  "properties": {
    "iso:country":"GB",
    "sg:address":"Help Out Mill, Shackerston",
    "sg:city":"Nuneaton",
    "sg:classifiers":[
        {
            "category":"Restaurant",
            "type":"Food & Drink"
        }
    ],
    "sg:postcode":"CV13 0BT",
    "sg:province":"Leicestershire",
    "wof:name":"Benney,Anthony,",
    "wof:placetype":"venue"
},
  "geometry": {"coordinates":[-1.44097,52.66671],"type":"Point"}
}