{
  "type": "Feature",
  "properties": {
    "iso:country":"GB",
    "sg:address":"Lyndale Thornford Road, Headley",
    "sg:city":"Thatcham",
    "sg:classifiers":[
        {
            "category":"Food & Beverages",
            "subcategory":"Candy",
            "type":"Retail Goods"
        }
    ],
    "sg:postcode":"RG19 8AD",
    "sg:province":"Berkshire",
    "sg:tags":[
        "confectionery"
    ],
    "wof:name":"Gerrys Catering",
    "wof:placetype":"venue"
},
  "geometry": {"coordinates":[-1.2579909563,51.3581237793],"type":"Point"}
}