{
  "type": "Feature",
  "properties": {
    "iso:country":"GB",
    "sg:address":"367 Southport Road",
    "sg:city":"Preston",
    "sg:classifiers":[
        {
            "category":"Manufacturing",
            "subcategory":"Signs",
            "type":"Manufacturing & Wholesale Goods"
        }
    ],
    "sg:phone":"+44 1772 601287",
    "sg:postcode":"PR26 8LQ",
    "sg:province":"Lancashire",
    "sg:tags":[
        "nameplate"
    ],
    "wof:name":"B Goldsmith Signs & Graphics",
    "wof:placetype":"venue"
},
  "geometry": {"coordinates":[-2.74849,53.663631],"type":"Point"}
}