{
  "type": "Feature",
  "properties": {
    "iso:country":"GB",
    "sg:address":"57 Middlewood St",
    "sg:city":"Salford",
    "sg:classifiers":[
        {
            "category":"Retail",
            "subcategory":"Auto Repair",
            "type":"Services"
        }
    ],
    "sg:postcode":"M5 4RF",
    "sg:province":"Greater Manchester",
    "sg:tags":[
        "electrician"
    ],
    "wof:name":"Clifton Auto Electrical Service",
    "wof:placetype":"venue"
},
  "geometry": {"coordinates":[-2.2652070522,53.4791793823],"type":"Point"}
}