{
  "type": "Feature",
  "properties": {
    "iso:country":"GB",
    "sg:address":"Units 4-6, Brindley Road South, Exall",
    "sg:city":"Coventry",
    "sg:classifiers":[
        {
            "category":"Manufacturing",
            "subcategory":"Chemicals & Compounds",
            "type":"Manufacturing & Wholesale Goods"
        }
    ],
    "sg:phone":"+44 24 7637 4999",
    "sg:postcode":"CV7 9EP",
    "sg:province":"Warwickshire",
    "wof:name":"Exhall Chemicals Ltd.",
    "wof:placetype":"venue"
},
  "geometry": {"coordinates":[-1.47381,52.46648],"type":"Point"}
}