{
  "type": "Feature",
  "properties": {
    "addr:full":"31 High Brooms Huddersfield West Yorkshire HD2 2FP",
    "addr:housenumber":"31",
    "addr:postcode":"hd2 2fp",
    "addr:street":"High Brooms",
    "iso:country":"GB",
    "sg:address":"31 High Brooms",
    "sg:city":"Huddersfield",
    "sg:classifiers":[
        {
            "category":"Professional",
            "subcategory":"Computer Services",
            "type":"Services"
        }
    ],
    "sg:phone":"+44 1484 453334",
    "sg:postcode":"HD2 2FP",
    "sg:province":"West Yorkshire",
    "sg:tags":[
        "consultant"
    ],
    "wof:name":"Broadacre Enterprises",
    "wof:placetype":"venue"
},
  "geometry": {"coordinates":[-1.8026280403,53.6617851257],"type":"Point"}
}