{
  "type": "Feature",
  "properties": {
    "addr:full":"300 Huddersfield Road Halifax West Yorkshire HX3 0PF",
    "addr:housenumber":"300",
    "addr:postcode":"hx3 0pf",
    "addr:street":"Huddersfield Road",
    "iso:country":"GB",
    "sg:address":"300 Huddersfield Road",
    "sg:city":"Halifax",
    "sg:classifiers":[
        {
            "category":"Personal",
            "subcategory":"Beauty Salon",
            "type":"Services"
        }
    ],
    "sg:phone":"+44 1422 365380",
    "sg:postcode":"HX3 0PF",
    "sg:province":"West Yorkshire",
    "sg:tags":[
        "unisex",
        "hairdresser"
    ],
    "wof:name":"Patricia Ann's Hair Stylist",
    "wof:placetype":"venue"
},
  "geometry": {"coordinates":[-1.8569920063,53.7066764832],"type":"Point"}
}