{
  "type": "Feature",
  "properties": {
    "addr:full":"601 North Road Industrial Estate Bridgend Bridgend CF31 3RG",
    "addr:housenumber":"601",
    "addr:postcode":"cf31 3rg",
    "addr:street":"North Road Industrial Estate",
    "iso:country":"GB",
    "sg:address":"601 North Road Industrial Estate",
    "sg:city":"Bridgend",
    "sg:classifiers":[
        {
            "category":"Retail",
            "subcategory":"Auto Repair",
            "type":"Services"
        }
    ],
    "sg:phone":"+44 1656 767800",
    "sg:postcode":"CF31 3RG",
    "sg:province":"Bridgend",
    "sg:tags":[
        "modification",
        "garage"
    ],
    "wof:name":"Groom & Llewellyn Ltd.",
    "wof:placetype":"venue"
},
  "geometry": {"coordinates":[-3.541609,51.503674],"type":"Point"}
}