{
  "type": "Feature",
  "properties": {
    "addr:full":"Concourse House, Suite 2, 432 Dewesbury Road Leeds West Yorkshire LS11 7DF",
    "addr:housenumber":"suite 2",
    "addr:postcode":"432;ls11 7df",
    "addr:street":"Dewesbury Road",
    "iso:country":"GB",
    "sg:address":"Concourse House, Suite 2, 432 Dewesbury Road",
    "sg:city":"Leeds",
    "sg:classifiers":[
        {
            "category":"Professional",
            "subcategory":"Engineering",
            "type":"Services"
        }
    ],
    "sg:phone":"+44 113 270 1199",
    "sg:postcode":"LS11 7DF",
    "sg:province":"West Yorkshire",
    "sg:tags":[
        "civil",
        "engineer"
    ],
    "wof:name":"J S M Designs Ltd.",
    "wof:placetype":"venue"
},
  "geometry": {"coordinates":[-1.561124,53.764896],"type":"Point"}
}