{
  "type": "Feature",
  "properties": {
    "iso:country":"GB",
    "sg:address":"Unit 8, Howgate Shopping Centre, Howgate",
    "sg:city":"Falkirk",
    "sg:classifiers":[
        {
            "category":"Shopping",
            "subcategory":"Clothing, Apparel, & Fashions",
            "type":"Retail Goods"
        }
    ],
    "sg:phone":"+44 1324 613423",
    "sg:postcode":"FK1 1DN",
    "sg:province":"Falkirk",
    "sg:tags":[
        "shop"
    ],
    "wof:name":"International",
    "wof:placetype":"venue"
},
  "geometry": {"coordinates":[-3.7873339653,55.9990386963],"type":"Point"}
}