{
  "type": "Feature",
  "properties": {
    "addr:full":"3 Cranleigh Drive, Whitfield Dover Kent CT16 3NN",
    "addr:housenumber":"3",
    "addr:postcode":"ct16 3nn",
    "addr:street":"Cranleigh Drive;Dover",
    "iso:country":"GB",
    "sg:address":"3 Cranleigh Drive, Whitfield",
    "sg:city":"Dover",
    "sg:classifiers":[
        {
            "category":"Retail",
            "subcategory":"Driving School",
            "type":"Services"
        }
    ],
    "sg:phone":"+44 1304 821782",
    "sg:postcode":"CT16 3NN",
    "sg:province":"Kent",
    "wof:name":"Keith Davies Driving Tuition",
    "wof:placetype":"venue"
},
  "geometry": {"coordinates":[1.2980999947,51.1595306396],"type":"Point"}
}