{
  "type": "Feature",
  "properties": {
    "addr:full":"130 Hereson Road Ramsgate Kent CT11 7EG",
    "addr:housenumber":"130",
    "addr:postcode":"ct11 7eg",
    "addr:street":"Hereson Road Ramsgate",
    "iso:country":"GB",
    "sg:address":"130 Hereson Road",
    "sg:city":"Ramsgate",
    "sg:classifiers":[
        {
            "category":"Personal",
            "subcategory":"Beauty Salon",
            "type":"Services"
        }
    ],
    "sg:phone":"+44 1843 590814",
    "sg:postcode":"CT11 7EG",
    "sg:province":"Kent",
    "sg:tags":[
        "lady",
        "hairdresser"
    ],
    "wof:name":"Shamillers",
    "wof:placetype":"venue"
},
  "geometry": {"coordinates":[1.426641,51.341248],"type":"Point"}
}