{
  "type": "Feature",
  "properties": {
    "iso:country":"GB",
    "sg:address":"50 Thames Street",
    "sg:city":"Windsor",
    "sg:classifiers":[
        {
            "category":"Bars & Pubs",
            "subcategory":"Wine Bar",
            "type":"Food & Drink"
        }
    ],
    "sg:phone":"+44 1753 865565",
    "sg:postcode":"SL4 1PU",
    "sg:province":"Berkshire",
    "wof:name":"The Punter Wine Bar",
    "wof:placetype":"venue"
},
  "geometry": {"coordinates":[-0.607786,51.485188],"type":"Point"}
}