{
  "type": "Feature",
  "properties": {
    "addr:full":"Denholm Bridge Yard Minto Road, Denholm Hawick Cumbria TD9 8ND",
    "addr:postcode":"td9 8nd",
    "addr:street":"Minto Road",
    "iso:country":"GB",
    "sg:address":"Denholm Bridge Yard Minto Road, Denholm",
    "sg:city":"Hawick",
    "sg:classifiers":[
        {
            "category":"Building & Trades",
            "subcategory":"Construction",
            "type":"Services"
        }
    ],
    "sg:phone":"+44 1835 862125",
    "sg:postcode":"TD9 8ND",
    "sg:province":"Cumbria",
    "sg:tags":[
        "equipment"
    ],
    "wof:name":"James Thomson",
    "wof:placetype":"venue"
},
  "geometry": {"coordinates":[-2.6823561192,55.458152771],"type":"Point"}
}