{
  "type": "Feature",
  "properties": {
    "addr:full":"72 High Street, Meadowhall Centre Sheffield South Yorkshire S9 1EN",
    "addr:housenumber":"72",
    "addr:postcode":"s9 1en",
    "addr:street":"High Street",
    "iso:country":"GB",
    "sg:address":"72 High Street, Meadowhall Centre",
    "sg:city":"Sheffield",
    "sg:classifiers":[
        {
            "category":"Shopping",
            "subcategory":"Comic Books",
            "type":"Retail Goods"
        }
    ],
    "sg:phone":"+44 114 256 8075",
    "sg:postcode":"S9 1EN",
    "sg:province":"South Yorkshire",
    "sg:tags":[
        "jeweller"
    ],
    "wof:name":"Goldsmiths Plc",
    "wof:placetype":"venue"
},
  "geometry": {"coordinates":[-1.41245,53.413029],"type":"Point"}
}