{
  "type": "Feature",
  "properties": {
    "addr:full":"Fore Street, Grampound Truro Cornwall TR2 4QT",
    "addr:postcode":"tr2 4qt",
    "addr:street":"Fore Street",
    "iso:country":"GB",
    "sg:address":"Fore Street, Grampound",
    "sg:city":"Truro",
    "sg:classifiers":[
        {
            "category":"Shopping",
            "subcategory":"Antiques",
            "type":"Retail Goods"
        }
    ],
    "sg:postcode":"TR2 4QT",
    "sg:province":"Cornwall",
    "wof:name":"Radnor House",
    "wof:placetype":"venue"
},
  "geometry": {"coordinates":[-4.8990340233,50.2982139587],"type":"Point"}
}