{
  "type": "Feature",
  "properties": {
    "addr:full":"Whitehall Rd East Bradford West Yorkshire BD11 2EJ",
    "addr:postcode":"bd11 2ej",
    "addr:street":"Whitehall Rd",
    "iso:country":"GB",
    "sg:address":"Whitehall Rd East",
    "sg:city":"Bradford",
    "sg:classifiers":[
        {
            "category":"Retail",
            "subcategory":"Auto Repair",
            "type":"Services"
        }
    ],
    "sg:postcode":"BD11 2EJ",
    "sg:province":"West Yorkshire",
    "sg:tags":[
        "modification",
        "garage"
    ],
    "wof:name":"Pratt,D,",
    "wof:placetype":"venue"
},
  "geometry": {"coordinates":[-1.682124,53.750397],"type":"Point"}
}