{
  "type": "Feature",
  "properties": {
    "iso:country":"GB",
    "sg:address":"9-11 High Street, Earls Colne",
    "sg:city":"Colchester",
    "sg:classifiers":[
        {
            "category":"Bars & Pubs",
            "type":"Food & Drink"
        }
    ],
    "sg:phone":"+44 1787 224120",
    "sg:postcode":"CO6 2PA",
    "sg:province":"Essex",
    "sg:tags":[
        "pubs",
        "inn"
    ],
    "wof:name":"The Lion",
    "wof:placetype":"venue"
},
  "geometry": {"coordinates":[0.698466,51.928158],"type":"Point"}
}