{
  "type": "Feature",
  "properties": {
    "addr:full":"Estuary Road King's Lynn Norfolk PE30 2HH",
    "addr:postcode":"pe30 2hh",
    "addr:street":"Estuary Road",
    "iso:country":"GB",
    "sg:address":"Estuary Road",
    "sg:city":"King's Lynn",
    "sg:classifiers":[
        {
            "category":"Retail",
            "subcategory":"Auto Repair",
            "type":"Services"
        }
    ],
    "sg:phone":"+44 1553 772480",
    "sg:postcode":"PE30 2HH",
    "sg:province":"Norfolk",
    "sg:tags":[
        "modification",
        "garage"
    ],
    "wof:name":"Hugh Smith (Estuary Rd) Ltd.",
    "wof:placetype":"venue"
},
  "geometry": {"coordinates":[0.3992500007,52.7642707825],"type":"Point"}
}