{
  "type": "Feature",
  "properties": {
    "iso:country":"GB",
    "sg:address":"188 Old Rd",
    "sg:city":"Clacton-on-sea",
    "sg:classifiers":[
        {
            "category":"Shopping",
            "subcategory":"Pets & Pet Supplies",
            "type":"Retail Goods"
        },
        {
            "category":"Shopping",
            "type":"Retail Goods"
        }
    ],
    "sg:postcode":"CO15 3LR",
    "sg:province":"Essex",
    "sg:tags":[
        "food",
        "merchant"
    ],
    "wof:name":"Lonsdale,M,",
    "wof:placetype":"venue"
},
  "geometry": {"coordinates":[1.149362,51.796062],"type":"Point"}
}