{
  "type": "Feature",
  "properties": {
    "iso:country":"GB",
    "sg:address":"135 South Street",
    "sg:city":"Perth",
    "sg:classifiers":[
        {
            "category":"Shopping",
            "subcategory":"Department Store",
            "type":"Retail Goods"
        }
    ],
    "sg:phone":"+44 1738 442272",
    "sg:postcode":"PH2 8PA",
    "sg:province":"Perth and Kinross",
    "wof:name":"Scoop & Save",
    "wof:placetype":"venue"
},
  "geometry": {"coordinates":[-3.432062,56.395458],"type":"Point"}
}