{
  "type": "Feature",
  "properties": {
    "addr:full":"191 Canley Road Coventry West Midlands CV5 6AS",
    "addr:housenumber":"191",
    "addr:postcode":"cv5 6as",
    "addr:street":"Canley Road",
    "iso:country":"GB",
    "sg:address":"191 Canley Road",
    "sg:city":"Coventry",
    "sg:classifiers":[
        {
            "category":"Shopping",
            "subcategory":"Hobbies, Toys, & Games",
            "type":"Retail Goods"
        }
    ],
    "sg:phone":"+44 24 7667 6077",
    "sg:postcode":"CV5 6AS",
    "sg:province":"West Midlands",
    "sg:tags":[
        "gunsmith"
    ],
    "wof:name":"Godiva Guns (Coventry)",
    "wof:placetype":"venue"
},
  "geometry": {"coordinates":[-1.54741,52.392384],"type":"Point"}
}