{
  "type": "Feature",
  "properties": {
    "addr:full":"104 London Road, Shenley Radlett Hertfordshire WD7 9BS",
    "addr:housenumber":"104",
    "addr:postcode":"wd7 9bs",
    "addr:street":"London Road",
    "iso:country":"GB",
    "sg:address":"104 London Road, Shenley",
    "sg:city":"Radlett",
    "sg:classifiers":[
        {
            "category":"Real Estate",
            "subcategory":"Real Estate Agent",
            "type":"Services"
        }
    ],
    "sg:phone":"+44 1923 855266",
    "sg:postcode":"WD7 9BS",
    "sg:province":"Hertfordshire",
    "wof:name":"Barkers Estate & Letting Agents",
    "wof:placetype":"venue"
},
  "geometry": {"coordinates":[-0.2806439996,51.6911201477],"type":"Point"}
}