{
  "type": "Feature",
  "properties": {
    "iso:country":"GB",
    "sg:address":"Bridge St Industrial Estate, Bridge Street, Clay Cross",
    "sg:city":"Chesterfield",
    "sg:classifiers":[
        {
            "category":"Freight",
            "type":"Transportation"
        }
    ],
    "sg:postcode":"S45 9NU",
    "sg:province":"Derbyshire",
    "sg:tags":[
        "haulage",
        "road"
    ],
    "wof:name":"Kelway Transport",
    "wof:placetype":"venue"
},
  "geometry": {"coordinates":[-1.407894,53.172211],"type":"Point"}
}