{
  "type": "Feature",
  "properties": {
    "iso:country":"GB",
    "sg:address":"132 Leatfield Drive",
    "sg:city":"Plymouth",
    "sg:classifiers":[
        {
            "category":"Retail",
            "subcategory":"Repair Shop",
            "type":"Services"
        }
    ],
    "sg:phone":"+44 1752 786838",
    "sg:postcode":"PL6 5EY",
    "sg:province":"Devon",
    "sg:tags":[
        "maintenance"
    ],
    "wof:name":"Mend-A-Bath International",
    "wof:placetype":"venue"
},
  "geometry": {"coordinates":[-4.136322,50.421009],"type":"Point"}
}