{
  "type": "Feature",
  "properties": {
    "addr:full":"Unit 3a Townfoot Industrial Estate Brampton Cumbria CA8 1SW",
    "addr:housenumber":"unit 3a",
    "addr:postcode":"ca8 1sw",
    "addr:street":"Townfoot Industrial Estate",
    "iso:country":"GB",
    "sg:address":"Unit 3a Townfoot Industrial Estate",
    "sg:city":"Brampton",
    "sg:classifiers":[
        {
            "category":"Professional",
            "subcategory":"Computer Services",
            "type":"Services"
        }
    ],
    "sg:postcode":"CA8 1SW",
    "sg:province":"Cumbria",
    "sg:tags":[
        "system",
        "software"
    ],
    "wof:name":"Cumbria Software Systems Ltd.",
    "wof:placetype":"venue"
},
  "geometry": {"coordinates":[-2.7372810841,54.9422798157],"type":"Point"}
}