{
  "type": "Feature",
  "properties": {
    "iso:country":"GB",
    "sg:address":"Glyn Cynwal Uchaf Farm, Lower Cwmtwrch",
    "sg:city":"Swansea",
    "sg:classifiers":[
        {
            "category":"Home & Garden",
            "subcategory":"Garden Supply",
            "type":"Retail Goods"
        },
        {
            "category":"Farming",
            "subcategory":"Farm",
            "type":"Manufacturing & Wholesale Goods"
        }
    ],
    "sg:phone":"+44 1639 842385",
    "sg:postcode":"SA9 2QQ",
    "sg:province":"Carmarthenshire",
    "sg:tags":[
        "mixed",
        "bulb",
        "crop",
        "grower"
    ],
    "wof:name":"Palleg Refuse & Re-Cycling Co. Ltd.",
    "wof:placetype":"venue"
},
  "geometry": {"coordinates":[-3.803108,51.786301],"type":"Point"}
}