{
  "type": "Feature",
  "properties": {
    "iso:country":"GB",
    "sg:address":"32 Carrington Road, Moulton Marsh",
    "sg:city":"Spalding",
    "sg:classifiers":[
        {
            "category":"Professional",
            "type":"Services"
        },
        {
            "category":"Farming",
            "subcategory":"Livestock Farm",
            "type":"Manufacturing & Wholesale Goods"
        }
    ],
    "sg:phone":"+44 1406 370627",
    "sg:postcode":"PE12 6LS",
    "sg:province":"Cambridgeshire",
    "sg:tags":[
        "agricultural",
        "others",
        "contractor"
    ],
    "wof:name":"A & J Goodale",
    "wof:placetype":"venue"
},
  "geometry": {"coordinates":[-0.056764,52.831402],"type":"Point"}
}