{
  "type": "Feature",
  "properties": {
    "addr:full":"324 Main Street Bellshill North Lanarkshire ML4 1BA",
    "addr:housenumber":"324",
    "addr:postcode":"ml4 1ba",
    "addr:street":"Main Street",
    "iso:country":"GB",
    "sg:address":"324 Main Street",
    "sg:city":"Bellshill",
    "sg:classifiers":[
        {
            "category":"Organizations",
            "subcategory":"Community Association",
            "type":"Services"
        },
        {
            "category":"Organizations",
            "subcategory":"Membership Organization",
            "type":"Services"
        }
    ],
    "sg:phone":"+44 1698 745064",
    "sg:postcode":"ML4 1BA",
    "sg:province":"North Lanarkshire",
    "sg:tags":[
        "club",
        "social"
    ],
    "wof:name":"The Imperial Social Club",
    "wof:placetype":"venue"
},
  "geometry": {"coordinates":[-4.018152,55.81913],"type":"Point"}
}