{
  "type": "Feature",
  "properties": {
    "iso:country":"GB",
    "sg:address":"20 Commercial Rd",
    "sg:city":"Hereford",
    "sg:classifiers":[
        {
            "category":"Shopping",
            "subcategory":"News",
            "type":"Retail Goods"
        }
    ],
    "sg:postcode":"HR1 2BB",
    "sg:province":"Herefordshire",
    "sg:tags":[
        "newsagent"
    ],
    "wof:name":"Kalleen,Michael,",
    "wof:placetype":"venue"
},
  "geometry": {"coordinates":[-2.711039,52.058414],"type":"Point"}
}