{
  "type": "Feature",
  "properties": {
    "addr:full":"21 Western Avenue Ellon Aberdeenshire AB41 9EX",
    "addr:housenumber":"21",
    "addr:postcode":"ab41 9ex",
    "addr:street":"Western Avenue",
    "iso:country":"GB",
    "sg:address":"21 Western Avenue",
    "sg:city":"Ellon",
    "sg:classifiers":[
        {
            "category":"Professional",
            "subcategory":"Employment Agencies",
            "type":"Services"
        }
    ],
    "sg:phone":"+44 1358 720217",
    "sg:postcode":"AB41 9EX",
    "sg:province":"Aberdeenshire",
    "sg:tags":[
        "modelling"
    ],
    "wof:name":"Portfolio Images Photography",
    "wof:placetype":"venue"
},
  "geometry": {"coordinates":[-2.092555,57.359402],"type":"Point"}
}