{
  "type": "Feature",
  "properties": {
    "iso:country":"GB",
    "sg:address":"3 Tannery House, Ground Floor, Tannery Lane",
    "sg:city":"Woking",
    "sg:classifiers":[
        {
            "category":"Real Estate",
            "subcategory":"Real Estate Agent",
            "type":"Services"
        }
    ],
    "sg:postcode":"GU23 7ES",
    "sg:province":"Surrey",
    "wof:name":"Wey Estates Ltd.",
    "wof:placetype":"venue"
},
  "geometry": {"coordinates":[-0.5165500045,51.297870636],"type":"Point"}
}