{
  "type": "Feature",
  "properties": {
    "addr:full":"The Millennium Centre, Sandall La, Kirk Sandall Indstl Est Doncaster South Yorkshire DN3 1RA",
    "addr:postcode":"dn3 1ra",
    "addr:street":"Sandall La Kirk;Indstl Est",
    "iso:country":"GB",
    "sg:address":"The Millennium Centre, Sandall La, Kirk Sandall Indstl Est",
    "sg:city":"Doncaster",
    "sg:classifiers":[
        {
            "category":"Professional",
            "subcategory":"Detective & Security Services",
            "type":"Services"
        }
    ],
    "sg:phone":"+44 1302 882255",
    "sg:postcode":"DN3 1RA",
    "sg:province":"South Yorkshire",
    "wof:name":"Millennium Security Northern Ltd",
    "wof:placetype":"venue"
},
  "geometry": {"coordinates":[-1.072788,53.562778],"type":"Point"}
}