{
  "type": "Feature",
  "properties": {
    "addr:full":"Unit B6 Poplar Business Pk, Prestons Rd London Greater London E14 9RL",
    "addr:postcode":"e14 9rl",
    "addr:street":"Poplar Business Pk Prestons Rd",
    "iso:country":"GB",
    "sg:address":"Unit B6 Poplar Business Pk, Prestons Rd",
    "sg:city":"London",
    "sg:classifiers":[
        {
            "category":"Professional",
            "subcategory":"Printing & Photocopies",
            "type":"Services"
        }
    ],
    "sg:postcode":"E14 9RL",
    "sg:province":"Greater London",
    "sg:tags":[
        "printer"
    ],
    "wof:name":"Alpha Colour",
    "wof:placetype":"venue"
},
  "geometry": {"coordinates":[-0.011166,51.501862],"type":"Point"}
}