{
  "type": "Feature",
  "properties": {
    "addr:full":"4 Broadbent Close, Highgate Highgate Greater London N6 5JW",
    "addr:housenumber":"4",
    "addr:postcode":"n6 5jw",
    "addr:street":"Broadbent Close Highgate Highgate",
    "iso:country":"GB",
    "sg:address":"4 Broadbent Close, Highgate",
    "sg:city":"Highgate",
    "sg:classifiers":[
        {
            "category":"Professional",
            "subcategory":"Art Services",
            "type":"Services"
        }
    ],
    "sg:phone":"+44 20 8341 9119",
    "sg:postcode":"N6 5JW",
    "sg:province":"Greater London",
    "sg:tags":[
        "consultant",
        "design"
    ],
    "wof:name":"Grant Walker",
    "wof:placetype":"venue"
},
  "geometry": {"coordinates":[-0.145218,51.571056],"type":"Point"}
}