{
  "type": "Feature",
  "properties": {
    "addr:full":"36 Sylvania Way Clydebank East Dunbartonshire G81 2TL",
    "addr:housenumber":"36",
    "addr:postcode":"g81 2tl",
    "addr:street":"Sylvania Way",
    "iso:country":"GB",
    "sg:address":"36 Sylvania Way",
    "sg:city":"Clydebank",
    "sg:classifiers":[
        {
            "category":"Personal",
            "subcategory":"Beauty Salon",
            "type":"Services"
        },
        {
            "category":"Personal",
            "subcategory":"Barber",
            "type":"Services"
        }
    ],
    "sg:phone":"+44 141 951 1561",
    "sg:postcode":"G81 2TL",
    "sg:province":"East Dunbartonshire",
    "sg:tags":[
        "unisex",
        "hairdresser"
    ],
    "wof:name":"Shortcuts",
    "wof:placetype":"venue"
},
  "geometry": {"coordinates":[-4.4036488533,55.9108581543],"type":"Point"}
}