{
  "type": "Feature",
  "properties": {
    "iso:country":"GB",
    "sg:address":"Factory Premises, New Rd",
    "sg:city":"Atherstone",
    "sg:classifiers":[
        {
            "category":"Retail",
            "subcategory":"Repair Shop",
            "type":"Services"
        }
    ],
    "sg:phone":"+44 1827 715917",
    "sg:postcode":"CV9 2BA",
    "sg:province":"Leicestershire",
    "sg:tags":[
        "upholsterer"
    ],
    "wof:name":"Whetstone Bros Upholstery",
    "wof:placetype":"venue"
},
  "geometry": {"coordinates":[-1.541959,52.575935],"type":"Point"}
}