{
  "type": "Feature",
  "properties": {
    "iso:country":"GB",
    "sg:address":"Po Box 45",
    "sg:city":"Liverpool",
    "sg:classifiers":[
        {
            "category":"Real Estate",
            "subcategory":"Real Estate Operator",
            "type":"Services"
        }
    ],
    "sg:phone":"+44 151 494 1500",
    "sg:postcode":"L19 0NA",
    "sg:province":"Merseyside",
    "sg:tags":[
        "letting",
        "agent"
    ],
    "wof:name":"Queensdale Estates Ltd.",
    "wof:placetype":"venue"
},
  "geometry": {"coordinates":[-2.915759,53.35936],"type":"Point"}
}