{
  "type": "Feature",
  "properties": {
    "addr:full":"42 Towersey Drive Thame Buckinghamshire OX9 3NS",
    "addr:housenumber":"42",
    "addr:postcode":"ox9 3ns",
    "addr:street":"Towersey Drive",
    "iso:country":"GB",
    "sg:address":"42 Towersey Drive",
    "sg:city":"Thame",
    "sg:classifiers":[
        {
            "category":"Building & Trades",
            "subcategory":"Construction",
            "type":"Services"
        }
    ],
    "sg:postcode":"OX9 3NS",
    "sg:province":"Buckinghamshire",
    "sg:tags":[
        "builder"
    ],
    "wof:name":"Horwood & Fenemore",
    "wof:placetype":"venue"
},
  "geometry": {"coordinates":[-0.961526,51.74268],"type":"Point"}
}