{
  "type": "Feature",
  "properties": {
    "iso:country":"GB",
    "sg:address":"1 Westminster Road, Westminster Trading Estate",
    "sg:city":"Wareham",
    "sg:classifiers":[
        {
            "category":"Manufacturing",
            "subcategory":"Food",
            "type":"Manufacturing & Wholesale Goods"
        },
        {
            "category":"Communications",
            "type":"Services"
        }
    ],
    "sg:phone":"+44 1929 554884",
    "sg:postcode":"BH20 4SR",
    "sg:province":"Dorset",
    "sg:tags":[
        "mech",
        "telecommunication",
        "processing"
    ],
    "wof:name":"Arcall Plc",
    "wof:placetype":"venue"
},
  "geometry": {"coordinates":[-2.122175,50.695049],"type":"Point"}
}