{
  "type": "Feature",
  "properties": {
    "iso:country":"GB",
    "sg:address":"394 Middleton Rd",
    "sg:city":"Carshalton",
    "sg:classifiers":[
        {
            "category":"Shopping",
            "subcategory":"News",
            "type":"Retail Goods"
        }
    ],
    "sg:phone":"+44 20 8715 1067",
    "sg:postcode":"SM5 1HP",
    "sg:province":"Surrey",
    "sg:tags":[
        "newsagent"
    ],
    "wof:name":"J Golding Group",
    "wof:placetype":"venue"
},
  "geometry": {"coordinates":[-0.1736849993,51.3848342896],"type":"Point"}
}