{
  "type": "Feature",
  "properties": {
    "addr:full":"1 Flamsteed Rd Charlton Greater London SE7 8HT",
    "addr:housenumber":"1",
    "addr:postcode":"se7 8ht",
    "addr:street":"Flamsteed Rd",
    "iso:country":"GB",
    "sg:address":"1 Flamsteed Rd",
    "sg:city":"Charlton",
    "sg:classifiers":[
        {
            "category":"Professional",
            "subcategory":"Management & Consulting",
            "type":"Services"
        }
    ],
    "sg:phone":"+44 20 8316 1708",
    "sg:postcode":"SE7 8HT",
    "sg:province":"Greater London",
    "sg:tags":[
        "consultant",
        "specialist"
    ],
    "wof:name":"Nails By Sharon",
    "wof:placetype":"venue"
},
  "geometry": {"coordinates":[0.045837,51.4851531982],"type":"Point"}
}