{
  "type": "Feature",
  "properties": {
    "addr:full":"170 Sussex Gardens London Greater London W2 1TP",
    "addr:housenumber":"170",
    "addr:postcode":"w2 1tp",
    "addr:street":"Sussex Gardens",
    "iso:country":"GB",
    "sg:address":"170 Sussex Gardens",
    "sg:city":"London",
    "sg:classifiers":[
        {
            "category":"Travel",
            "subcategory":"Hotels & Motels",
            "type":"Entertainment"
        }
    ],
    "sg:phone":"+44 20 7402 0281",
    "sg:postcode":"W2 1TP",
    "sg:province":"Greater London",
    "wof:name":"Westpoint Hotel (Hyde Park) Ltd.",
    "wof:placetype":"venue"
},
  "geometry": {"coordinates":[-0.1735820025,51.5148162842],"type":"Point"}
}