{
  "type": "Feature",
  "properties": {
    "iso:country":"GB",
    "sg:address":"83 Hanham Rd, Kingswood",
    "sg:city":"Bristol",
    "sg:classifiers":[
        {
            "category":"Education",
            "subcategory":"Dance Studio",
            "type":"Public Place"
        }
    ],
    "sg:phone":"+44 117 960 7998",
    "sg:postcode":"BS15 8PY",
    "sg:province":"City of Bristol",
    "sg:tags":[
        "school",
        "dancing"
    ],
    "wof:name":"The Elite Dance Co",
    "wof:placetype":"venue"
},
  "geometry": {"coordinates":[-2.5068969727,51.4579162598],"type":"Point"}
}