{
  "type": "Feature",
  "properties": {
    "addr:full":"141 Hornby Road Blackpool Lancashire FY1 4JG",
    "addr:housenumber":"141",
    "addr:postcode":"fy1 4jg",
    "addr:street":"Hornby Road",
    "iso:country":"GB",
    "sg:address":"141 Hornby Road",
    "sg:city":"Blackpool",
    "sg:classifiers":[
        {
            "category":"Travel",
            "subcategory":"Hostel",
            "type":"Entertainment"
        }
    ],
    "sg:postcode":"FY1 4JG",
    "sg:province":"Lancashire",
    "wof:name":"The Fylde House of Help",
    "wof:placetype":"venue"
},
  "geometry": {"coordinates":[-3.042791,53.815403],"type":"Point"}
}