{
  "type": "Feature",
  "properties": {
    "addr:full":"138 High St Sevenoaks Kent TN13 1XE",
    "addr:housenumber":"138",
    "addr:postcode":"tn13 1xe",
    "addr:street":"High St",
    "iso:country":"GB",
    "sg:address":"138 High St",
    "sg:city":"Sevenoaks",
    "sg:classifiers":[
        {
            "category":"Real Estate",
            "subcategory":"Real Estate Agent",
            "type":"Services"
        }
    ],
    "sg:phone":"+44 1732 460440",
    "sg:postcode":"TN13 1XE",
    "sg:province":"Kent",
    "wof:name":"GA Town & Country",
    "wof:placetype":"venue"
},
  "geometry": {"coordinates":[0.192811,51.272305],"type":"Point"}
}