{
  "type": "Feature",
  "properties": {
    "iso:country":"GB",
    "sg:address":"140 Peascod Street",
    "sg:city":"Windsor",
    "sg:classifiers":[
        {
            "category":"Professional",
            "subcategory":"Employment Agencies",
            "type":"Services"
        }
    ],
    "sg:phone":"+44 1753 831212",
    "sg:postcode":"SL4 1DS",
    "sg:province":"Berkshire",
    "sg:tags":[
        "consultant"
    ],
    "wof:name":"Business Back-Up",
    "wof:placetype":"venue"
},
  "geometry": {"coordinates":[-0.607912,51.482567],"type":"Point"}
}