{
  "type": "Feature",
  "properties": {
    "iso:country":"GB",
    "sg:address":"Nutfield Rd (a25)",
    "sg:city":"Redhill",
    "sg:classifiers":[
        {
            "category":"Travel",
            "subcategory":"Hotels & Motels",
            "type":"Entertainment"
        }
    ],
    "sg:postcode":"RH1 4ED",
    "sg:province":"Surrey",
    "wof:name":"T F L Car Hire",
    "wof:placetype":"venue"
},
  "geometry": {"coordinates":[-0.158363,51.23624],"type":"Point"}
}