{
  "type": "Feature",
  "properties": {
    "iso:country":"GB",
    "sg:address":"Watchet Lane, Holmer Grn",
    "sg:city":"High Wycombe",
    "sg:classifiers":[
        {
            "category":"Education",
            "subcategory":"Preschool",
            "type":"Public Place"
        }
    ],
    "sg:postcode":"HP15 6UG",
    "sg:province":"Buckinghamshire",
    "sg:tags":[
        "pre-school",
        "playgroups"
    ],
    "wof:name":"Playmates Day Nursery",
    "wof:placetype":"venue"
},
  "geometry": {"coordinates":[-0.705764,51.661594],"type":"Point"}
}