{
  "type": "Feature",
  "properties": {
    "iso:country":"GB",
    "sg:address":"24 Heads Of Valley Industrial Estate, Rhymney",
    "sg:city":"Tredegar",
    "sg:classifiers":[
        {
            "category":"Banks & Credit Unions",
            "subcategory":"Investment Brokerage",
            "type":"Services"
        },
        {
            "category":"Building & Trades",
            "subcategory":"Electrical",
            "type":"Services"
        }
    ],
    "sg:phone":"+44 1685 844678",
    "sg:postcode":"NP22 5RL",
    "sg:province":"Blaenau Gwent",
    "sg:tags":[
        "lighting",
        "contractor"
    ],
    "sg:website":"http://www.parkersell.com",
    "wof:name":"Parkersell (Lighting & Electrical) Services Ltd.",
    "wof:placetype":"venue"
},
  "geometry": {"coordinates":[-3.2876889706,51.7635231018],"type":"Point"}
}