{
  "type": "Feature",
  "properties": {
    "iso:country":"GB",
    "sg:address":"1 Lazy Hill Road, Aldridge",
    "sg:city":"Walsall",
    "sg:classifiers":[
        {
            "category":"Personal",
            "subcategory":"Beauty Salon",
            "type":"Services"
        }
    ],
    "sg:phone":"+44 1922 458212",
    "sg:postcode":"WS9 8RW",
    "sg:province":"Staffordshire",
    "sg:tags":[
        "unisex",
        "hairdresser"
    ],
    "wof:name":"Sarullos",
    "wof:placetype":"venue"
},
  "geometry": {"coordinates":[-1.914231,52.615223],"type":"Point"}
}