{
  "type": "Feature",
  "properties": {
    "addr:full":"20 Surtees Gro, Fenton Stoke-on-trent Staffordshire ST4 3HH",
    "addr:housenumber":"20",
    "addr:postcode":"st4 3hh",
    "addr:street":"Surtees Gro Fenton",
    "iso:country":"GB",
    "sg:address":"20 Surtees Gro, Fenton",
    "sg:city":"Stoke-on-trent",
    "sg:classifiers":[
        {
            "category":"Freight",
            "type":"Transportation"
        }
    ],
    "sg:postcode":"ST4 3HH",
    "sg:province":"Staffordshire",
    "sg:tags":[
        "haulage",
        "road"
    ],
    "wof:name":"Parkhall Vehicle Services",
    "wof:placetype":"venue"
},
  "geometry": {"coordinates":[-2.141919,52.996204],"type":"Point"}
}