{
  "type": "Feature",
  "properties": {
    "iso:country":"GB",
    "sg:address":"Warden, 10 Redwood Ho, Broomcroft Rd",
    "sg:city":"Birmingham",
    "sg:classifiers":[
        {
            "category":"Social Services",
            "subcategory":"Adult Care",
            "type":"Services"
        },
        {
            "category":"Government",
            "subcategory":"Office",
            "type":"Public Place"
        }
    ],
    "sg:phone":"+44 121 770 8505",
    "sg:postcode":"B37 6HB",
    "sg:province":"West Midlands",
    "sg:tags":[
        "housing",
        "local",
        "sheltered"
    ],
    "wof:name":"Solihull Metropolitan Borough Council",
    "wof:placetype":"venue"
},
  "geometry": {"coordinates":[-1.75146,52.492981],"type":"Point"}
}