{
  "type": "Feature",
  "properties": {
    "iso:country":"GB",
    "sg:address":"106 Birch Lane",
    "sg:city":"Bradford",
    "sg:classifiers":[
        {
            "category":"Organizations",
            "subcategory":"Community Association",
            "type":"Services"
        },
        {
            "category":"Organizations",
            "subcategory":"Membership Organization",
            "type":"Services"
        }
    ],
    "sg:phone":"+44 1274 776433",
    "sg:postcode":"BD5 8BL",
    "sg:province":"West Yorkshire",
    "sg:tags":[
        "club",
        "social"
    ],
    "wof:name":"West Bowling Social Club",
    "wof:placetype":"venue"
},
  "geometry": {"coordinates":[-1.7524540424,53.7766494751],"type":"Point"}
}