{
  "type": "Feature",
  "properties": {
    "iso:country":"GB",
    "sg:address":"69-71 Tavistock Street",
    "sg:city":"Bedford",
    "sg:classifiers":[
        {
            "category":"Restaurant",
            "type":"Food & Drink"
        }
    ],
    "sg:phone":"+44 1234 355544",
    "sg:postcode":"MK40 2RR",
    "sg:province":"Bedfordshire",
    "sg:tags":[
        "indian"
    ],
    "wof:name":"Gulshan",
    "wof:placetype":"venue"
},
  "geometry": {"coordinates":[-0.471085012,52.1409721375],"type":"Point"}
}