{
  "type": "Feature",
  "properties": {
    "iso:country":"GB",
    "sg:address":"43 High Street",
    "sg:city":"Burton-on-trent",
    "sg:classifiers":[
        {
            "category":"Professional",
            "subcategory":"Employment Agencies",
            "type":"Services"
        }
    ],
    "sg:phone":"+44 1283 515253",
    "sg:postcode":"DE14 1JS",
    "sg:province":"Derbyshire",
    "sg:tags":[
        "consultant"
    ],
    "wof:name":"Personnel Plus Ltd.",
    "wof:placetype":"venue"
},
  "geometry": {"coordinates":[-1.629587,52.803337],"type":"Point"}
}