{
  "type": "Feature",
  "properties": {
    "iso:country":"GB",
    "sg:address":"41 Newmarket Rd, Moulton",
    "sg:city":"Newmarket",
    "sg:classifiers":[
        {
            "category":"Wholesale",
            "subcategory":"Machinery & Supplies",
            "type":"Manufacturing & Wholesale Goods"
        }
    ],
    "sg:phone":"+44 1638 552023",
    "sg:postcode":"CB8 8QP",
    "sg:province":"Cambridgeshire",
    "sg:tags":[
        "pump"
    ],
    "wof:name":"C Graney",
    "wof:placetype":"venue"
},
  "geometry": {"coordinates":[0.47584,52.250477],"type":"Point"}
}