{
  "type": "Feature",
  "properties": {
    "iso:country":"GB",
    "sg:address":"264 Milton Rd",
    "sg:city":"Weston-super-mare",
    "sg:classifiers":[
        {
            "category":"Home & Garden",
            "subcategory":"Household Appliances",
            "type":"Retail Goods"
        }
    ],
    "sg:postcode":"BS22 8EN",
    "sg:province":"Somerset",
    "sg:tags":[
        "domestic",
        "centre"
    ],
    "wof:name":"Brown,Benjamin,",
    "wof:placetype":"venue"
},
  "geometry": {"coordinates":[-2.944067955,51.3538894653],"type":"Point"}
}