{
  "type": "Feature",
  "properties": {
    "addr:full":"11 Tenby Mansions, Nottingham Street London Greater London W1U 5ER",
    "addr:housenumber":"11",
    "addr:postcode":"w1u 5er",
    "addr:street":"Nottingham Street",
    "iso:country":"GB",
    "sg:address":"11 Tenby Mansions, Nottingham Street",
    "sg:city":"London",
    "sg:classifiers":[
        {
            "category":"Professional",
            "subcategory":"Engineering",
            "type":"Services"
        }
    ],
    "sg:phone":"+44 20 7935 7462",
    "sg:postcode":"W1U 5ER",
    "sg:province":"Greater London",
    "sg:tags":[
        "consulting",
        "engineer"
    ],
    "wof:name":"Jules Blatt",
    "wof:placetype":"venue"
},
  "geometry": {"coordinates":[-0.153961,51.522411],"type":"Point"}
}