{
  "type": "Feature",
  "properties": {
    "iso:country":"GB",
    "sg:address":"Ocot Lane, Scammonden",
    "sg:city":"Huddersfield",
    "sg:classifiers":[
        {
            "category":"Transit Center",
            "subcategory":"Passenger",
            "type":"Transportation"
        }
    ],
    "sg:phone":"+44 1484 842584",
    "sg:postcode":"HD3 3FR",
    "sg:province":"West Yorkshire",
    "sg:tags":[
        "boarding",
        "kennel",
        "catteries"
    ],
    "wof:name":"Scammonden Kennels & Cattery",
    "wof:placetype":"venue"
},
  "geometry": {"coordinates":[-1.9323940277,53.6345710754],"type":"Point"}
}