{
  "type": "Feature",
  "properties": {
    "addr:full":"87a Falcon Road London Greater London SW11 2PF",
    "addr:housenumber":"87a",
    "addr:postcode":"sw11 2pf",
    "addr:street":"Falcon Road",
    "iso:country":"GB",
    "sg:address":"87a Falcon Road",
    "sg:city":"London",
    "sg:classifiers":[
        {
            "category":"Taxi",
            "type":"Transportation"
        }
    ],
    "sg:phone":"+44 20 7924 1799",
    "sg:postcode":"SW11 2PF",
    "sg:province":"Greater London",
    "sg:tags":[
        "mini",
        "cab"
    ],
    "wof:name":"Keens Couriers",
    "wof:placetype":"venue"
},
  "geometry": {"coordinates":[-0.1702120006,51.4671897888],"type":"Point"}
}