{
  "type": "Feature",
  "properties": {
    "addr:full":"Lucy Avenue Folkestone Kent CT19 5TX",
    "addr:postcode":"ct19 5tx",
    "addr:street":"Lucy Avenue",
    "iso:country":"GB",
    "sg:address":"Lucy Avenue",
    "sg:city":"Folkestone",
    "sg:classifiers":[
        {
            "category":"Social Services",
            "subcategory":"Adult Care",
            "type":"Services"
        }
    ],
    "sg:phone":"+44 1303 244894",
    "sg:postcode":"CT19 5TX",
    "sg:province":"Kent",
    "sg:tags":[
        "day",
        "centre"
    ],
    "wof:name":"Broadmeadow Day Centre",
    "wof:placetype":"venue"
},
  "geometry": {"coordinates":[1.1633110046,51.0928077698],"type":"Point"}
}