{
  "type": "Feature",
  "properties": {
    "iso:country":"GB",
    "sg:address":"The Crossroads Yard, Pengam",
    "sg:city":"Blackwood",
    "sg:classifiers":[
        {
            "category":"Building & Trades",
            "subcategory":"Construction",
            "type":"Services"
        }
    ],
    "sg:phone":"+44 1443 832132",
    "sg:postcode":"NP12 3XR",
    "sg:province":"Caerphilly",
    "sg:tags":[
        "builder"
    ],
    "wof:name":"Hawker Builders (Bargoed) Ltd.",
    "wof:placetype":"venue"
},
  "geometry": {"coordinates":[-3.2234940529,51.66431427],"type":"Point"}
}