{
  "type": "Feature",
  "properties": {
    "iso:country":"GB",
    "sg:address":"36 Baker Street",
    "sg:city":"Brighton",
    "sg:classifiers":[
        {
            "category":"Personal",
            "subcategory":"Beauty Salon",
            "type":"Services"
        }
    ],
    "sg:postcode":"BN1 4JN",
    "sg:province":"East Sussex",
    "sg:tags":[
        "lady",
        "hairdresser"
    ],
    "wof:name":"Melinda",
    "wof:placetype":"venue"
},
  "geometry": {"coordinates":[-0.134893,50.831715],"type":"Point"}
}