{
  "type": "Feature",
  "properties": {
    "addr:full":"17 Beancroft Road Castleford West Yorkshire WF10 5BN",
    "addr:housenumber":"17",
    "addr:postcode":"wf10 5bn",
    "addr:street":"Beancroft Road",
    "iso:country":"GB",
    "sg:address":"17 Beancroft Road",
    "sg:city":"Castleford",
    "sg:classifiers":[
        {
            "category":"Home & Garden",
            "subcategory":"Household Appliances",
            "type":"Retail Goods"
        }
    ],
    "sg:phone":"+44 1977 512801",
    "sg:postcode":"WF10 5BN",
    "sg:province":"West Yorkshire",
    "sg:tags":[
        "electrical"
    ],
    "wof:name":"Castleford Domestic Refrigeration Centre",
    "wof:placetype":"venue"
},
  "geometry": {"coordinates":[-1.3554500341,53.7231712341],"type":"Point"}
}