{
  "type": "Feature",
  "properties": {
    "iso:country":"GB",
    "sg:address":"Prospect House, Newbiggin",
    "sg:city":"Penrith",
    "sg:classifiers":[
        {
            "category":"Travel",
            "subcategory":"Hotels & Motels",
            "type":"Entertainment"
        }
    ],
    "sg:phone":"+44 17684 83249",
    "sg:postcode":"CA11 0HT",
    "sg:province":"Cumbria",
    "sg:tags":[
        "self",
        "catering"
    ],
    "wof:name":"K D Whitehead",
    "wof:placetype":"venue"
},
  "geometry": {"coordinates":[-2.823274,54.656013],"type":"Point"}
}