{
  "type": "Feature",
  "properties": {
    "iso:country":"GB",
    "sg:address":"Marston Rd, Greatworth",
    "sg:city":"Banbury",
    "sg:classifiers":[
        {
            "category":"Government",
            "subcategory":"Post Office",
            "type":"Public Place"
        }
    ],
    "sg:phone":"+44 1295 711410",
    "sg:postcode":"OX17 2EA",
    "sg:province":"Northamptonshire",
    "wof:name":"Greatworth P.O",
    "wof:placetype":"venue"
},
  "geometry": {"coordinates":[-1.196889,52.078125],"type":"Point"}
}