{
  "type": "Feature",
  "properties": {
    "addr:full":"St Peters Square London Greater London E2 7AF",
    "addr:postcode":"e2 7af",
    "addr:street":"Square",
    "iso:country":"GB",
    "sg:address":"St Peters Square",
    "sg:city":"London",
    "sg:classifiers":[
        {
            "category":"Shopping",
            "subcategory":"Musical Instruments",
            "type":"Retail Goods"
        }
    ],
    "sg:phone":"+44 20 7739 4747",
    "sg:postcode":"E2 7AF",
    "sg:province":"Greater London",
    "sg:tags":[
        "organ",
        "accessory"
    ],
    "wof:name":"N P Mander Ltd.",
    "wof:placetype":"venue"
},
  "geometry": {"coordinates":[-0.06438,51.530521],"type":"Point"}
}