{
  "type": "Feature",
  "properties": {
    "addr:full":"P O Box 208 Stourbridge West Midlands DY9 0WZ",
    "addr:housenumber":"208",
    "addr:postcode":"dy9 0wz",
    "addr:street":"P O Box",
    "iso:country":"GB",
    "sg:address":"P O Box 208",
    "sg:city":"Stourbridge",
    "sg:classifiers":[
        {
            "category":"Building & Trades",
            "subcategory":"Construction",
            "type":"Services"
        }
    ],
    "sg:phone":"+44 1562 882204",
    "sg:postcode":"DY9 0WZ",
    "sg:province":"West Midlands",
    "sg:tags":[
        "dry",
        "lining",
        "plasterers",
        "screeders"
    ],
    "wof:name":"Morris Plasterers",
    "wof:placetype":"venue"
},
  "geometry": {"coordinates":[-2.1325690746,52.4230117798],"type":"Point"}
}