{
  "type": "Feature",
  "properties": {
    "iso:country":"GB",
    "sg:address":"Walshes Meadow",
    "sg:city":"Stourport-on-severn",
    "sg:classifiers":[
        {
            "category":"Bars & Pubs",
            "type":"Food & Drink"
        }
    ],
    "sg:postcode":"DY13 0AA",
    "sg:province":"Worcestershire",
    "sg:tags":[
        "pubs",
        "inn"
    ],
    "wof:name":"The Old Beams",
    "wof:placetype":"venue"
},
  "geometry": {"coordinates":[-2.281167,52.338997],"type":"Point"}
}