{
  "type": "Feature",
  "properties": {
    "addr:full":"2 Springfield Avenue Stockport Cheshire SK5 7BD",
    "addr:housenumber":"2",
    "addr:postcode":"sk5 7bd",
    "addr:street":"Springfield Avenue",
    "iso:country":"GB",
    "sg:address":"2 Springfield Avenue",
    "sg:city":"Stockport",
    "sg:classifiers":[
        {
            "category":"Building & Trades",
            "subcategory":"Construction",
            "type":"Services"
        }
    ],
    "sg:phone":"+44 161 428 0275",
    "sg:postcode":"SK5 7BD",
    "sg:province":"Cheshire",
    "sg:tags":[
        "builder"
    ],
    "wof:name":"Downes & Entwistle Ltd.",
    "wof:placetype":"venue"
},
  "geometry": {"coordinates":[-2.163765,53.434727],"type":"Point"}
}