{
  "type": "Feature",
  "properties": {
    "iso:country":"GB",
    "sg:address":"Constituency Of Winchester, 45 Southgate St",
    "sg:city":"Winchester",
    "sg:classifiers":[
        {
            "category":"Government",
            "subcategory":"Office",
            "type":"Public Place"
        }
    ],
    "sg:phone":"+44 1962 868800",
    "sg:postcode":"SO23 9EH",
    "sg:province":"Hampshire",
    "sg:tags":[
        "mp",
        "meps"
    ],
    "wof:name":"Mark Oaten MP (LDem)",
    "wof:placetype":"venue"
},
  "geometry": {"coordinates":[-1.316809,51.063068],"type":"Point"}
}