{
  "type": "Feature",
  "properties": {
    "addr:full":"36 Broadway Parade London Greater London N8 9DB",
    "addr:housenumber":"36",
    "addr:postcode":"n8 9db",
    "addr:street":"Broadway Parade",
    "iso:country":"GB",
    "sg:address":"36 Broadway Parade",
    "sg:city":"London",
    "sg:classifiers":[
        {
            "category":"Personal",
            "subcategory":"Beauty Salon",
            "type":"Services"
        }
    ],
    "sg:phone":"+44 20 8348 4008",
    "sg:postcode":"N8 9DB",
    "sg:province":"Greater London",
    "wof:name":"Graces Bodycare",
    "wof:placetype":"venue"
},
  "geometry": {"coordinates":[-0.12137,51.581299],"type":"Point"}
}