{
  "type": "Feature",
  "properties": {
    "addr:full":"91a Billett Road, Walthamstow London Greater London E17 5DB",
    "addr:housenumber":"91a",
    "addr:postcode":"e17 5db",
    "addr:street":"Billett Road",
    "iso:country":"GB",
    "sg:address":"91a Billett Road, Walthamstow",
    "sg:city":"London",
    "sg:classifiers":[
        {
            "category":"Building & Trades",
            "subcategory":"Construction",
            "type":"Services"
        }
    ],
    "sg:phone":"+44 20 8531 9899",
    "sg:postcode":"E17 5DB",
    "sg:province":"Greater London",
    "sg:tags":[
        "roofing"
    ],
    "wof:name":"A. Billett Roofing",
    "wof:placetype":"venue"
},
  "geometry": {"coordinates":[-0.0248450004,51.5994987488],"type":"Point"}
}