{
  "type": "Feature",
  "properties": {
    "addr:full":"7 North Ormesby Rd Middlesbrough North Yorkshire TS4 2AA",
    "addr:housenumber":"7",
    "addr:postcode":"ts4 2aa",
    "addr:street":"North Ormesby Rd",
    "iso:country":"GB",
    "sg:address":"7 North Ormesby Rd",
    "sg:city":"Middlesbrough",
    "sg:classifiers":[
        {
            "category":"Retail",
            "subcategory":"Auto Repair",
            "type":"Services"
        }
    ],
    "sg:postcode":"TS4 2AA",
    "sg:province":"North Yorkshire",
    "sg:tags":[
        "body",
        "car"
    ],
    "wof:name":"Stadium Motors",
    "wof:placetype":"venue"
},
  "geometry": {"coordinates":[-1.22596,54.574986],"type":"Point"}
}