{
  "type": "Feature",
  "properties": {
    "addr:full":"Bridge House, Delamere Terrace Bayswater Greater London W2 6ND",
    "addr:postcode":"w2 6nd",
    "addr:street":"Delamere Terrace",
    "iso:country":"GB",
    "sg:address":"Bridge House, Delamere Terrace",
    "sg:city":"Bayswater",
    "sg:classifiers":[
        {
            "category":"Arts & Performance",
            "subcategory":"Theater",
            "type":"Entertainment"
        }
    ],
    "sg:phone":"+44 20 7266 1717",
    "sg:postcode":"W2 6ND",
    "sg:province":"Greater London",
    "sg:tags":[
        "hall",
        "theatre",
        "concert"
    ],
    "wof:name":"Bish Bash Bosh Club",
    "wof:placetype":"venue"
},
  "geometry": {"coordinates":[-0.1864739954,51.5218887329],"type":"Point"}
}