{
  "type": "Feature",
  "properties": {
    "addr:full":"8a Rugby Road Hinckley Leicestershire LE10 0QD",
    "addr:housenumber":"8a",
    "addr:postcode":"le10 0qd",
    "addr:street":"Rugby Road",
    "iso:country":"GB",
    "sg:address":"8a Rugby Road",
    "sg:city":"Hinckley",
    "sg:classifiers":[
        {
            "category":"Health Services",
            "subcategory":"Nursing And Care Facility",
            "type":"Services"
        }
    ],
    "sg:postcode":"LE10 0QD",
    "sg:province":"Leicestershire",
    "sg:tags":[
        "home"
    ],
    "wof:name":"United Care Group Ltd.",
    "wof:placetype":"venue"
},
  "geometry": {"coordinates":[-1.376176,52.539059],"type":"Point"}
}