{
  "type": "Feature",
  "properties": {
    "iso:country":"GB",
    "sg:address":"Rose Grove Surgery, Albert Rd",
    "sg:city":"Grange Over Sands",
    "sg:classifiers":[
        {
            "category":"Health Services",
            "subcategory":"Doctor",
            "type":"Services"
        }
    ],
    "sg:phone":"+44 15395 33018",
    "sg:postcode":"LA11 7EZ",
    "sg:province":"Cumbria",
    "sg:tags":[
        "practitioners"
    ],
    "wof:name":"Phizacklea, S",
    "wof:placetype":"venue"
},
  "geometry": {"coordinates":[-2.92164,54.184158],"type":"Point"}
}