{
  "type": "Feature",
  "properties": {
    "iso:country":"GB",
    "sg:address":"8 High Rd",
    "sg:city":"West Byfleet",
    "sg:classifiers":[
        {
            "category":"Building & Trades",
            "subcategory":"Landscaping Services",
            "type":"Services"
        }
    ],
    "sg:phone":"+44 1932 353162",
    "sg:postcode":"KT14 7QG",
    "sg:province":"Surrey",
    "sg:tags":[
        "forestry",
        "tree"
    ],
    "wof:name":"Treecare",
    "wof:placetype":"venue"
},
  "geometry": {"coordinates":[-0.4807960093,51.3396835327],"type":"Point"}
}