{
  "type": "Feature",
  "properties": {
    "iso:country":"GB",
    "sg:address":"189 Queens Road",
    "sg:city":"Hastings",
    "sg:classifiers":[
        {
            "category":"Professional",
            "type":"Services"
        }
    ],
    "sg:postcode":"TN34 1RG",
    "sg:province":"East Sussex",
    "sg:tags":[
        "repair",
        "tech",
        "maintenance"
    ],
    "wof:name":"Fast Track Computer Systems Ltd",
    "wof:placetype":"venue"
},
  "geometry": {"coordinates":[0.582855,50.858574],"type":"Point"}
}