{
  "type": "Feature",
  "properties": {
    "addr:full":"1 Lemington Gro Bracknell Berkshire RG12 7JE",
    "addr:housenumber":"1",
    "addr:postcode":"rg12 7je",
    "addr:street":"Lemington Gro",
    "iso:country":"GB",
    "sg:address":"1 Lemington Gro",
    "sg:city":"Bracknell",
    "sg:classifiers":[
        {
            "category":"Autos & Motor Vehicles",
            "subcategory":"Motorcycle Sales",
            "type":"Retail Goods"
        }
    ],
    "sg:phone":"+44 1344 640796",
    "sg:postcode":"RG12 7JE",
    "sg:province":"Berkshire",
    "sg:tags":[
        "chauffeur",
        "driven",
        "car"
    ],
    "wof:name":"Donald Brecknock",
    "wof:placetype":"venue"
},
  "geometry": {"coordinates":[-0.7521070242,51.3994407654],"type":"Point"}
}