{
  "type": "Feature",
  "properties": {
    "addr:full":"Midsummer House, 439 Midsummer Boulevard, Central Milton Keynes Milton Keynes Buckinghamshire MK9 3BN",
    "addr:housenumber":"439",
    "addr:postcode":"mk9 3bn",
    "addr:street":"Midsummer Boulevard",
    "iso:country":"GB",
    "sg:address":"Midsummer House, 439 Midsummer Boulevard, Central Milton Keynes",
    "sg:city":"Milton Keynes",
    "sg:classifiers":[
        {
            "category":"Banks & Credit Unions",
            "subcategory":"Financial Services",
            "type":"Services"
        }
    ],
    "sg:phone":"+44 1908 696196",
    "sg:postcode":"MK9 3BN",
    "sg:province":"Buckinghamshire",
    "sg:tags":[
        "consultant"
    ],
    "wof:name":"United Friendly",
    "wof:placetype":"venue"
},
  "geometry": {"coordinates":[-0.7568190098,52.0418510437],"type":"Point"}
}