{
  "type": "Feature",
  "properties": {
    "iso:country":"GB",
    "sg:address":"146 Grainger Street",
    "sg:city":"Newcastle-upon-tyne",
    "sg:classifiers":[
        {
            "category":"Shopping",
            "subcategory":"Shoes",
            "type":"Retail Goods"
        }
    ],
    "sg:phone":"+44 191 261 7724",
    "sg:postcode":"NE1 5AF",
    "sg:province":"Tyne and Wear",
    "sg:tags":[
        "shop"
    ],
    "wof:name":"Aspecto Clothing Co. Ltd.",
    "wof:placetype":"venue"
},
  "geometry": {"coordinates":[-1.613677,54.97282],"type":"Point"}
}