{
  "type": "Feature",
  "properties": {
    "addr:full":"Hall Farm, Northwold Thetford Norfolk IP26 5LG",
    "addr:housenumber":"northwold",
    "addr:postcode":"ip26 5lg",
    "addr:street":"Hall",
    "iso:country":"GB",
    "sg:address":"Hall Farm, Northwold",
    "sg:city":"Thetford",
    "sg:classifiers":[
        {
            "category":"Farming",
            "subcategory":"Livestock Farm",
            "type":"Manufacturing & Wholesale Goods"
        }
    ],
    "sg:postcode":"IP26 5LG",
    "sg:province":"Norfolk",
    "sg:tags":[
        "others"
    ],
    "wof:name":"B A Eyles",
    "wof:placetype":"venue"
},
  "geometry": {"coordinates":[0.5818939805,52.5389213562],"type":"Point"}
}