{
  "type": "Feature",
  "properties": {
    "addr:full":"Backfield Farm, Wotton Road Bristol Gloucestershire BS37 9XD",
    "addr:postcode":"bs37 9xd",
    "addr:street":"Wotton Road",
    "iso:country":"GB",
    "sg:address":"Backfield Farm, Wotton Road",
    "sg:city":"Bristol",
    "sg:classifiers":[
        {
            "category":"Professional",
            "subcategory":"Engineering",
            "type":"Services"
        }
    ],
    "sg:postcode":"BS37 9XD",
    "sg:province":"Gloucestershire",
    "sg:tags":[
        "precision",
        "engineer"
    ],
    "wof:name":"D & H Engineering",
    "wof:placetype":"venue"
},
  "geometry": {"coordinates":[-2.45275,51.558201],"type":"Point"}
}