{
  "type": "Feature",
  "properties": {
    "iso:country":"GB",
    "sg:address":"Power House, 69a The Street, Old Basing",
    "sg:city":"Basingstoke",
    "sg:classifiers":[
        {
            "category":"Manufacturing",
            "subcategory":"Tools & Machinery",
            "type":"Manufacturing & Wholesale Goods"
        }
    ],
    "sg:phone":"+44 1256 814717",
    "sg:postcode":"RG24 7BY",
    "sg:province":"Hampshire",
    "sg:tags":[
        "society",
        "friendly"
    ],
    "wof:name":"Came & Co",
    "wof:placetype":"venue"
},
  "geometry": {"coordinates":[-1.046833,51.273666],"type":"Point"}
}