{
  "type": "Feature",
  "properties": {
    "addr:full":"12 Bergholt Crescent London Greater London N16 5JE",
    "addr:housenumber":"12",
    "addr:postcode":"n16 5je",
    "addr:street":"Bergholt Crescent",
    "iso:country":"GB",
    "sg:address":"12 Bergholt Crescent",
    "sg:city":"London",
    "sg:classifiers":[
        {
            "category":"Personal",
            "type":"Services"
        }
    ],
    "sg:phone":"+44 20 8880 2693",
    "sg:postcode":"N16 5JE",
    "sg:province":"Greater London",
    "sg:tags":[
        "wedding"
    ],
    "wof:name":"Ernest Gelbard Ltd.",
    "wof:placetype":"venue"
},
  "geometry": {"coordinates":[-0.079792,51.574043],"type":"Point"}
}