{
  "type": "Feature",
  "properties": {
    "addr:full":"Durdar Road Carlisle Cumbria CA2 4TS",
    "addr:postcode":"ca2 4ts",
    "addr:street":"Durdar Road",
    "iso:country":"GB",
    "sg:address":"Durdar Road",
    "sg:city":"Carlisle",
    "sg:classifiers":[
        {
            "category":"Sports & Exercise",
            "subcategory":"Race Track",
            "type":"Entertainment"
        }
    ],
    "sg:phone":"+44 1228 522973",
    "sg:postcode":"CA2 4TS",
    "sg:province":"Cumbria",
    "sg:tags":[
        "racecourse"
    ],
    "wof:name":"The Carlisle Racecourse Co. Ltd.",
    "wof:placetype":"venue"
},
  "geometry": {"coordinates":[-2.927279,54.850128],"type":"Point"}
}