{
  "type": "Feature",
  "properties": {
    "addr:full":"Main Street Pembroke Pembrokeshire SA71 4DB",
    "addr:postcode":"sa71 4db",
    "addr:street":"Main Street",
    "iso:country":"GB",
    "sg:address":"Main Street",
    "sg:city":"Pembroke",
    "sg:classifiers":[
        {
            "category":"Autos & Motor Vehicles",
            "subcategory":"Fuel & Gas Station",
            "type":"Retail Goods"
        }
    ],
    "sg:phone":"+44 1646 684770",
    "sg:postcode":"SA71 4DB",
    "sg:province":"Pembrokeshire",
    "sg:tags":[
        "petrol",
        "filling"
    ],
    "wof:name":"C J & P M Rickard",
    "wof:placetype":"venue"
},
  "geometry": {"coordinates":[-4.916795,51.675861],"type":"Point"}
}