{
  "type": "Feature",
  "properties": {
    "addr:full":"73 Newtown Thetford Norfolk IP24 3AU",
    "addr:housenumber":"73",
    "addr:postcode":"ip24 3au",
    "addr:street":"Newtown",
    "iso:country":"GB",
    "sg:address":"73 Newtown",
    "sg:city":"Thetford",
    "sg:classifiers":[
        {
            "category":"Place Of Worship",
            "type":"Public Place"
        }
    ],
    "sg:phone":"+44 1842 752266",
    "sg:postcode":"IP24 3AU",
    "sg:province":"Norfolk",
    "wof:name":"St Marys Catholic Church",
    "wof:placetype":"venue"
},
  "geometry": {"coordinates":[0.743483,52.412022],"type":"Point"}
}