{
  "type": "Feature",
  "properties": {
    "iso:country":"GB",
    "sg:address":"Lewes Rd",
    "sg:city":"Uckfield",
    "sg:classifiers":[
        {
            "category":"Shopping",
            "subcategory":"Stationery & Office Supplies",
            "type":"Retail Goods"
        }
    ],
    "sg:phone":"+44 1825 890959",
    "sg:postcode":"TN22 5LF",
    "sg:province":"East Sussex",
    "wof:name":"Sterling Envelopes",
    "wof:placetype":"venue"
},
  "geometry": {"coordinates":[0.099212,50.961349],"type":"Point"}
}