{
  "type": "Feature",
  "properties": {
    "addr:full":"Suite F5, Bates Business Ctr Romford Essex RM3 0JF",
    "addr:housenumber":"f5",
    "addr:postcode":"rm3 0jf",
    "iso:country":"GB",
    "sg:address":"Suite F5, Bates Business Ctr",
    "sg:city":"Romford",
    "sg:classifiers":[
        {
            "category":"Home & Garden",
            "subcategory":"Hardware",
            "type":"Retail Goods"
        }
    ],
    "sg:phone":"+44 1708 378666",
    "sg:postcode":"RM3 0JF",
    "sg:province":"Essex",
    "sg:tags":[
        "paint"
    ],
    "wof:name":"H C C Protective Coatings Ltd.",
    "wof:placetype":"venue"
},
  "geometry": {"coordinates":[0.243852,51.598431],"type":"Point"}
}