{
  "type": "Feature",
  "properties": {
    "addr:full":"Ystard Gwernaffield Road Mold Denbighshire CH7 1RE",
    "addr:postcode":"ch7 1re",
    "addr:street":"Gwernaffield Road",
    "iso:country":"GB",
    "sg:address":"Ystard Gwernaffield Road",
    "sg:city":"Mold",
    "sg:classifiers":[
        {
            "category":"Building & Trades",
            "subcategory":"Construction",
            "type":"Services"
        }
    ],
    "sg:phone":"+44 1352 755658",
    "sg:postcode":"CH7 1RE",
    "sg:province":"Denbighshire",
    "sg:tags":[
        "decorator",
        "painter"
    ],
    "wof:name":"Michael Hammersley",
    "wof:placetype":"venue"
},
  "geometry": {"coordinates":[-3.139984,53.163868],"type":"Point"}
}