{
  "type": "Feature",
  "properties": {
    "iso:country":"GB",
    "sg:address":"P O Box 12875",
    "sg:city":"London",
    "sg:classifiers":[
        {
            "category":"Manufacturing",
            "subcategory":"Tools & Machinery",
            "type":"Manufacturing & Wholesale Goods"
        },
        {
            "category":"Bus Stop",
            "subcategory":"None",
            "type":"Transportation"
        }
    ],
    "sg:phone":"+44 20 8991 2078",
    "sg:postcode":"W13 8WW",
    "sg:province":"Greater London",
    "sg:tags":[
        "equipment",
        "builder",
        "walling",
        "curtain"
    ],
    "wof:name":"S N Murdoch Ltd.",
    "wof:placetype":"venue"
},
  "geometry": {"coordinates":[-0.316209,51.52182],"type":"Point"}
}