{
  "type": "Feature",
  "properties": {
    "addr:full":"Unit 1 Delph La Prescot Cheshire L35 7JQ",
    "addr:housenumber":"unit 1",
    "addr:postcode":"l35 7jq",
    "addr:street":"La Prescot",
    "iso:country":"GB",
    "sg:address":"Unit 1 Delph La",
    "sg:city":"Prescot",
    "sg:classifiers":[
        {
            "category":"Utilities",
            "subcategory":"Natural Gas",
            "type":"Services"
        }
    ],
    "sg:phone":"+44 151 480 7917",
    "sg:postcode":"L35 7JQ",
    "sg:province":"Cheshire",
    "sg:tags":[
        "supplier"
    ],
    "wof:name":"Dengas ( Within Rainhill Tyres)",
    "wof:placetype":"venue"
},
  "geometry": {"coordinates":[-2.784764,53.424259],"type":"Point"}
}