{
  "type": "Feature",
  "properties": {
    "iso:country":"GB",
    "sg:address":"Unit 3 Central Business Pk, Masbrough St",
    "sg:city":"Rotherham",
    "sg:classifiers":[
        {
            "category":"Professional",
            "subcategory":"Engineering",
            "type":"Services"
        }
    ],
    "sg:phone":"+44 1709 551555",
    "sg:postcode":"S60 1EX",
    "sg:province":"South Yorkshire",
    "sg:tags":[
        "precision",
        "engineer"
    ],
    "wof:name":"Retroplas Ltd",
    "wof:placetype":"venue"
},
  "geometry": {"coordinates":[-1.3634040356,53.4306907654],"type":"Point"}
}