{
  "type": "Feature",
  "properties": {
    "addr:full":"Aultmore Cottage, Bayhall Rd Tunbridge Wells East Sussex TN2 4UB",
    "addr:postcode":"tn2 4ub",
    "addr:street":"Bayhall Rd",
    "iso:country":"GB",
    "sg:address":"Aultmore Cottage, Bayhall Rd",
    "sg:city":"Tunbridge Wells",
    "sg:classifiers":[
        {
            "category":"Professional",
            "subcategory":"Accounting & Tax Preparation",
            "type":"Services"
        }
    ],
    "sg:phone":"+44 1892 514295",
    "sg:postcode":"TN2 4UB",
    "sg:province":"East Sussex",
    "sg:tags":[
        "consultant"
    ],
    "wof:name":"Davis,Anthony Phillip,",
    "wof:placetype":"venue"
},
  "geometry": {"coordinates":[0.27795,51.12915],"type":"Point"}
}