{
  "type": "Feature",
  "properties": {
    "addr:full":"The Old Station, Broome Craven Arms Herefordshire SY7 0NT",
    "addr:postcode":"sy7 0nt",
    "addr:street":"Herefordshire",
    "iso:country":"GB",
    "sg:address":"The Old Station, Broome",
    "sg:city":"Craven Arms",
    "sg:classifiers":[
        {
            "category":"Autos & Motor Vehicles",
            "subcategory":"Auto Supplies",
            "type":"Retail Goods"
        }
    ],
    "sg:phone":"+44 1588 660400",
    "sg:postcode":"SY7 0NT",
    "sg:province":"Herefordshire",
    "sg:tags":[
        "component"
    ],
    "wof:name":"Jeeparts U K",
    "wof:placetype":"venue"
},
  "geometry": {"coordinates":[-2.88316,52.423981],"type":"Point"}
}