{
  "type": "Feature",
  "properties": {
    "iso:country":"GB",
    "sg:address":"2 London Road",
    "sg:city":"Tunbridge Wells",
    "sg:classifiers":[
        {
            "category":"Manufacturing",
            "subcategory":"Furniture",
            "type":"Manufacturing & Wholesale Goods"
        }
    ],
    "sg:phone":"+44 1892 519949",
    "sg:postcode":"TN1 1DQ",
    "sg:province":"Kent",
    "sg:tags":[
        "mnfr",
        "upholsterer"
    ],
    "wof:name":"The Ballard Upholstery Studio",
    "wof:placetype":"venue"
},
  "geometry": {"coordinates":[0.2593460083,51.1270027161],"type":"Point"}
}