{
  "type": "Feature",
  "properties": {
    "iso:country":"GB",
    "sg:address":"Unit 3 Pittman Court, Pittman Way, Fulwood",
    "sg:city":"Preston",
    "sg:classifiers":[
        {
            "category":"Shopping",
            "subcategory":"Computers & Home Electronics",
            "type":"Retail Goods"
        }
    ],
    "sg:phone":"+44 1772 651951",
    "sg:postcode":"PR2 9ZG",
    "sg:province":"Lancashire",
    "sg:tags":[
        "electrical"
    ],
    "wof:name":"Tom Whalley (Electrical) Ltd.",
    "wof:placetype":"venue"
},
  "geometry": {"coordinates":[-2.6880090237,53.7965011597],"type":"Point"}
}