{
  "type": "Feature",
  "properties": {
    "iso:country":"GB",
    "sg:address":"Cutler House, Wakefield Road",
    "sg:city":"Bradford",
    "sg:classifiers":[
        {
            "category":"Professional",
            "subcategory":"Engineering",
            "type":"Services"
        }
    ],
    "sg:phone":"+44 1274 771100",
    "sg:postcode":"BD4 7LU",
    "sg:province":"West Yorkshire",
    "sg:tags":[
        "contractor",
        "electrical",
        "engineer"
    ],
    "wof:name":"Pitts Electrical Ltd.",
    "wof:placetype":"venue"
},
  "geometry": {"coordinates":[-1.747389,53.790245],"type":"Point"}
}