{
  "type": "Feature",
  "properties": {
    "addr:full":"Whitworth Avenue Coventry Warwickshire CV3 1EP",
    "addr:postcode":"cv3 1ep",
    "addr:street":"Whitworth Avenue",
    "iso:country":"GB",
    "sg:address":"Whitworth Avenue",
    "sg:city":"Coventry",
    "sg:classifiers":[
        {
            "category":"Social Services",
            "type":"Services"
        },
        {
            "category":"Government",
            "subcategory":"Office",
            "type":"Public Place"
        }
    ],
    "sg:phone":"+44 24 7645 8336",
    "sg:postcode":"CV3 1EP",
    "sg:province":"Warwickshire",
    "sg:tags":[
        "local"
    ],
    "wof:name":"Stoke Aldermoor Social Services",
    "wof:placetype":"venue"
},
  "geometry": {"coordinates":[-1.4668140411,52.3991966248],"type":"Point"}
}