{
  "type": "Feature",
  "properties": {
    "addr:full":"Boverton Llantwit Major The Vale of Glamorgan CF61 1UE",
    "addr:postcode":"cf61 1ue",
    "addr:street":"Vale",
    "iso:country":"GB",
    "sg:address":"Boverton",
    "sg:city":"Llantwit Major",
    "sg:classifiers":[
        {
            "category":"Community Center",
            "type":"Public Place"
        }
    ],
    "sg:phone":"+44 1446 796675",
    "sg:postcode":"CF61 1UE",
    "sg:province":"The Vale of Glamorgan",
    "sg:tags":[
        "conference",
        "room",
        "centre"
    ],
    "wof:name":"Summerhouse Bay Christian Conference Centre",
    "wof:placetype":"venue"
},
  "geometry": {"coordinates":[-3.46643,51.405392],"type":"Point"}
}