{
  "type": "Feature",
  "properties": {
    "addr:full":"Royal Works, Goulbourne Street Keighley West Yorkshire BD21 1PL",
    "addr:postcode":"bd21 1pl",
    "addr:street":"Goulbourne Street",
    "iso:country":"GB",
    "sg:address":"Royal Works, Goulbourne Street",
    "sg:city":"Keighley",
    "sg:classifiers":[
        {
            "category":"Home & Garden",
            "subcategory":"Furniture",
            "type":"Retail Goods"
        }
    ],
    "sg:postcode":"BD21 1PL",
    "sg:province":"West Yorkshire",
    "wof:name":"The Woodworks",
    "wof:placetype":"venue"
},
  "geometry": {"coordinates":[-1.915759,53.861954],"type":"Point"}
}