{
  "type": "Feature",
  "properties": {
    "addr:full":"1 Saddler Street, Landore Swansea Neath Port Talbot SA1 2PP",
    "addr:housenumber":"1",
    "addr:postcode":"sa1 2pp",
    "addr:street":"Saddler Street",
    "iso:country":"GB",
    "sg:address":"1 Saddler Street, Landore",
    "sg:city":"Swansea",
    "sg:classifiers":[
        {
            "category":"Building & Trades",
            "subcategory":"Construction",
            "type":"Services"
        }
    ],
    "sg:phone":"+44 1792 520239",
    "sg:postcode":"SA1 2PP",
    "sg:province":"Neath Port Talbot",
    "sg:tags":[
        "door",
        "replacement"
    ],
    "wof:name":"Ace Maintenance",
    "wof:placetype":"venue"
},
  "geometry": {"coordinates":[-3.943155,51.642387],"type":"Point"}
}