{
  "type": "Feature",
  "properties": {
    "addr:full":"6 Pier Walk, Gorleston Great Yarmouth Norfolk NR31 6DA",
    "addr:housenumber":"6",
    "addr:postcode":"nr31 6da",
    "addr:street":"Pier Walk;Great Yarmouth",
    "iso:country":"GB",
    "sg:address":"6 Pier Walk, Gorleston",
    "sg:city":"Great Yarmouth",
    "sg:classifiers":[
        {
            "category":"Wholesale",
            "subcategory":"Scrap",
            "type":"Manufacturing & Wholesale Goods"
        }
    ],
    "sg:postcode":"NR31 6DA",
    "sg:province":"Norfolk",
    "sg:tags":[
        "waste",
        "metal"
    ],
    "wof:name":"Bell,V,",
    "wof:placetype":"venue"
},
  "geometry": {"coordinates":[1.7306710482,52.5743370056],"type":"Point"}
}