{
  "type": "Feature",
  "properties": {
    "iso:country":"GB",
    "sg:address":"Quee Lane, Willslock",
    "sg:city":"Uttoxeter",
    "sg:classifiers":[
        {
            "category":"Bars & Pubs",
            "type":"Food & Drink"
        }
    ],
    "sg:phone":"+44 1889 563405",
    "sg:postcode":"ST14 8RB",
    "sg:province":"Derbyshire",
    "sg:tags":[
        "pubs",
        "inn"
    ],
    "wof:name":"Red Cow Inn",
    "wof:placetype":"venue"
},
  "geometry": {"coordinates":[-1.889499,52.871361],"type":"Point"}
}