{
  "type": "Feature",
  "properties": {
    "iso:country":"GB",
    "sg:address":"Primrose Hill",
    "sg:city":"King's Langley",
    "sg:classifiers":[
        {
            "category":"Professional",
            "subcategory":"Detective & Security Services",
            "type":"Services"
        }
    ],
    "sg:phone":"+44 1923 269544",
    "sg:postcode":"WD4 8HR",
    "sg:province":"Hertfordshire",
    "sg:tags":[
        "alarm",
        "burglar",
        "system"
    ],
    "wof:name":"Euro Alarms Ltd.",
    "wof:placetype":"venue"
},
  "geometry": {"coordinates":[-0.44151,51.714531],"type":"Point"}
}