{
  "type": "Feature",
  "properties": {
    "iso:country":"GB",
    "sg:address":"2 Umberston Street",
    "sg:city":"London",
    "sg:classifiers":[
        {
            "category":"Fast Food",
            "type":"Food & Drink"
        }
    ],
    "sg:postcode":"E1 1PY",
    "sg:province":"Greater London",
    "sg:tags":[
        "away",
        "take"
    ],
    "wof:name":"Lahore Kebab House",
    "wof:placetype":"venue"
},
  "geometry": {"coordinates":[-0.0630249977,51.5146980286],"type":"Point"}
}