{
  "type": "Feature",
  "properties": {
    "addr:full":"Mardyke, Water La Purfleet Essex RM19 1GS",
    "addr:postcode":"rm19 1gs",
    "iso:country":"GB",
    "sg:address":"Mardyke, Water La",
    "sg:city":"Purfleet",
    "sg:classifiers":[
        {
            "category":"Health Services",
            "subcategory":"Doctor",
            "type":"Services"
        }
    ],
    "sg:phone":"+44 1708 861207",
    "sg:postcode":"RM19 1GS",
    "sg:province":"Essex",
    "sg:tags":[
        "practitioners"
    ],
    "wof:name":"Dey, K R",
    "wof:placetype":"venue"
},
  "geometry": {"coordinates":[0.2374799997,51.4805755615],"type":"Point"}
}