{
  "type": "Feature",
  "properties": {
    "addr:full":"97 Cambridge Road Hitchin Hertfordshire SG4 0JH",
    "addr:housenumber":"97",
    "addr:postcode":"sg4 0jh",
    "addr:street":"Cambridge Road",
    "iso:country":"GB",
    "sg:address":"97 Cambridge Road",
    "sg:city":"Hitchin",
    "sg:classifiers":[
        {
            "category":"Bars & Pubs",
            "type":"Food & Drink"
        }
    ],
    "sg:phone":"+44 1462 434227",
    "sg:postcode":"SG4 0JH",
    "sg:province":"Hertfordshire",
    "sg:tags":[
        "pubs",
        "inn"
    ],
    "wof:name":"The Millstream",
    "wof:placetype":"venue"
},
  "geometry": {"coordinates":[-0.2577080131,51.9557418823],"type":"Point"}
}