{
  "type": "Feature",
  "properties": {
    "addr:full":"63 St.mary Axe Monument Greater London EC3A 8NB",
    "addr:housenumber":"63",
    "addr:postcode":"ec3a 8nb",
    "addr:street":"St.Mary Axe",
    "iso:country":"GB",
    "sg:address":"63 St.mary Axe",
    "sg:city":"Monument",
    "sg:classifiers":[
        {
            "category":"Government",
            "subcategory":"Office",
            "type":"Public Place"
        }
    ],
    "sg:phone":"+44 20 7621 1061",
    "sg:postcode":"EC3A 8NB",
    "sg:province":"Greater London",
    "sg:tags":[
        "central"
    ],
    "wof:name":"Insurance Brokers Registration Council",
    "wof:placetype":"venue"
},
  "geometry": {"coordinates":[-0.080401,51.515301],"type":"Point"}
}