{
  "type": "Feature",
  "properties": {
    "iso:country":"GB",
    "sg:address":"946 Uxbridge Road",
    "sg:city":"Hayes",
    "sg:classifiers":[
        {
            "category":"Home & Garden",
            "subcategory":"Home Furnishings",
            "type":"Retail Goods"
        }
    ],
    "sg:postcode":"UB4 0RL",
    "sg:province":"Greater London",
    "sg:tags":[
        "blind",
        "curtain",
        "fitting"
    ],
    "wof:name":"Needles & Pins",
    "wof:placetype":"venue"
},
  "geometry": {"coordinates":[-0.421099,51.52264],"type":"Point"}
}