{
  "type": "Feature",
  "properties": {
    "iso:country":"GB",
    "sg:address":"The Hire Centre, Oldbury Road",
    "sg:city":"Cwmbran",
    "sg:classifiers":[
        {
            "category":"Home & Garden",
            "subcategory":"Hardware",
            "type":"Retail Goods"
        }
    ],
    "sg:phone":"+44 1633 866263",
    "sg:postcode":"NP44 3JU",
    "sg:province":"Monmouthshire",
    "sg:tags":[
        "lawnmowers",
        "machinery"
    ],
    "wof:name":"Virgo Plant Hire Ltd.",
    "wof:placetype":"venue"
},
  "geometry": {"coordinates":[-3.025864,51.657467],"type":"Point"}
}