{
  "type": "Feature",
  "properties": {
    "addr:full":"27 Victoria Terrace Barnsley South Yorkshire S70 4NT",
    "addr:housenumber":"27",
    "addr:postcode":"s70 4nt",
    "addr:street":"Victoria Terrace;Yorkshire",
    "iso:country":"GB",
    "sg:address":"27 Victoria Terrace",
    "sg:city":"Barnsley",
    "sg:classifiers":[
        {
            "category":"Building & Trades",
            "subcategory":"Construction",
            "type":"Services"
        }
    ],
    "sg:phone":"+44 1226 245260",
    "sg:postcode":"S70 4NT",
    "sg:province":"South Yorkshire",
    "sg:tags":[
        "joiner",
        "carpenter"
    ],
    "wof:name":"M Harris",
    "wof:placetype":"venue"
},
  "geometry": {"coordinates":[-1.4716880322,53.5460472107],"type":"Point"}
}