{
  "type": "Feature",
  "properties": {
    "iso:country":"GB",
    "sg:address":"Knaves Beech Business Centre, Davies Way, Loudwater",
    "sg:city":"High Wycombe",
    "sg:classifiers":[
        {
            "category":"Home & Garden",
            "subcategory":"Hardware",
            "type":"Retail Goods"
        }
    ],
    "sg:phone":"+44 1628 810333",
    "sg:postcode":"HP10 9QR",
    "sg:province":"Buckinghamshire",
    "sg:tags":[
        "shop",
        "retailer",
        "diy"
    ],
    "sg:website":"http://www.homebase.co.uk",
    "wof:name":"Homebase Ltd",
    "wof:placetype":"venue"
},
  "geometry": {"coordinates":[-0.692513,51.606087],"type":"Point"}
}