{
  "type": "Feature",
  "properties": {
    "iso:country":"GB",
    "sg:address":"77 Mitcham Road",
    "sg:city":"Croydon",
    "sg:classifiers":[
        {
            "category":"Social Services",
            "subcategory":"Child Care",
            "type":"Services"
        }
    ],
    "sg:postcode":"CR0 3RR",
    "sg:province":"Surrey",
    "sg:tags":[
        "childminders"
    ],
    "wof:name":"Michelle Sopp",
    "wof:placetype":"venue"
},
  "geometry": {"coordinates":[-0.1128529981,51.3805961609],"type":"Point"}
}