{
  "type": "Feature",
  "properties": {
    "addr:full":"More Wrks, More Bishops Castle Shropshire SY9 5HH",
    "addr:postcode":"sy9 5hh",
    "iso:country":"GB",
    "sg:address":"More Wrks, More",
    "sg:city":"Bishops Castle",
    "sg:classifiers":[
        {
            "category":"Professional",
            "subcategory":"Accounting & Tax Preparation",
            "type":"Services"
        }
    ],
    "sg:phone":"+44 1588 650123",
    "sg:postcode":"SY9 5HH",
    "sg:province":"Shropshire",
    "sg:tags":[
        "stove",
        "woodburning"
    ],
    "wof:name":"Clearview Stoves Ltd.",
    "wof:placetype":"venue"
},
  "geometry": {"coordinates":[-2.996149,52.493301],"type":"Point"}
}