{
  "type": "Feature",
  "properties": {
    "addr:full":"137 Woolacombe Way Hayes Greater London UB3 4EY",
    "addr:housenumber":"137",
    "addr:postcode":"ub3 4ey",
    "addr:street":"Woolacombe Way",
    "iso:country":"GB",
    "sg:address":"137 Woolacombe Way",
    "sg:city":"Hayes",
    "sg:classifiers":[
        {
            "category":"Social Services",
            "subcategory":"Adult Care",
            "type":"Services"
        }
    ],
    "sg:postcode":"UB3 4EY",
    "sg:province":"Greater London",
    "sg:tags":[
        "domestic",
        "cleaning"
    ],
    "wof:name":"Celclene",
    "wof:placetype":"venue"
},
  "geometry": {"coordinates":[-0.424741,51.496807],"type":"Point"}
}