{
  "type": "Feature",
  "properties": {
    "iso:country":"GB",
    "sg:address":"137 Woolacombe Way",
    "sg:city":"Hayes",
    "sg:classifiers":[
        {
            "category":"Social Services",
            "subcategory":"Adult Care",
            "type":"Services"
        }
    ],
    "sg:postcode":"UB3 4EY",
    "sg:province":"Greater London",
    "sg:tags":[
        "domestic",
        "cleaning"
    ],
    "wof:name":"Celclene",
    "wof:placetype":"venue"
},
  "geometry": {"coordinates":[-0.424741,51.496807],"type":"Point"}
}