{
  "type": "Feature",
  "properties": {
    "addr:full":"Paddock Hill Cottage, Paddock Hill, Mobberley Knutsford Cheshire WA16 7DA",
    "addr:postcode":"wa16 7da",
    "addr:street":"Paddock;Paddock Hill",
    "iso:country":"GB",
    "sg:address":"Paddock Hill Cottage, Paddock Hill, Mobberley",
    "sg:city":"Knutsford",
    "sg:classifiers":[
        {
            "category":"Building & Trades",
            "subcategory":"Construction",
            "type":"Services"
        }
    ],
    "sg:phone":"+44 1565 872397",
    "sg:postcode":"WA16 7DA",
    "sg:province":"Cheshire",
    "sg:tags":[
        "builder"
    ],
    "wof:name":"Keith Whitehead",
    "wof:placetype":"venue"
},
  "geometry": {"coordinates":[-2.331651926,53.3145523071],"type":"Point"}
}