{
  "type": "Feature",
  "properties": {
    "addr:full":"Unit 56 Joseph Wilson Industrial Estate, Millstrood Road Whitstable Kent CT5 3PS",
    "addr:housenumber":"unit 56",
    "addr:postcode":"ct5 3ps",
    "addr:street":"Joseph Wilson Industrial Estate Millstrood Road",
    "iso:country":"GB",
    "sg:address":"Unit 56 Joseph Wilson Industrial Estate, Millstrood Road",
    "sg:city":"Whitstable",
    "sg:classifiers":[
        {
            "category":"Utilities",
            "subcategory":"Natural Gas",
            "type":"Services"
        }
    ],
    "sg:phone":"+44 1304 813852",
    "sg:postcode":"CT5 3PS",
    "sg:province":"Kent",
    "sg:tags":[
        "welding"
    ],
    "wof:name":"Kema U K Ltd.",
    "wof:placetype":"venue"
},
  "geometry": {"coordinates":[1.0264060497,51.362247467],"type":"Point"}
}