{
  "type": "Feature",
  "properties": {
    "iso:country":"GB",
    "sg:address":"Unit M Linsford Industrial Park, Linsford Lane, Mytchett",
    "sg:city":"Camberley",
    "sg:classifiers":[
        {
            "category":"Manufacturing",
            "subcategory":"Wood Products",
            "type":"Manufacturing & Wholesale Goods"
        }
    ],
    "sg:phone":"+44 1252 372373",
    "sg:postcode":"GU16 6DJ",
    "sg:province":"Hampshire",
    "sg:tags":[
        "packaging",
        "crate",
        "pallets"
    ],
    "wof:name":"Engineering Services (Crondall) Ltd.",
    "wof:placetype":"venue"
},
  "geometry": {"coordinates":[-0.72549,51.287422],"type":"Point"}
}