{
  "type": "Feature",
  "properties": {
    "iso:country":"GB",
    "sg:address":"10 Great Stuart St",
    "sg:city":"Edinburgh",
    "sg:classifiers":[
        {
            "category":"Organizations",
            "subcategory":"Membership Organization",
            "type":"Services"
        }
    ],
    "sg:phone":"+44 131 225 2417",
    "sg:postcode":"EH3 7TN",
    "sg:province":"City of Edinburgh",
    "sg:tags":[
        "club"
    ],
    "wof:name":"Salmon & Trout Association The",
    "wof:placetype":"venue"
},
  "geometry": {"coordinates":[-3.214981,55.952438],"type":"Point"}
}