{
  "type": "Feature",
  "properties": {
    "addr:full":"75 Burgh Road Carlisle Cumbria CA2 7NB",
    "addr:housenumber":"75",
    "addr:postcode":"ca2 7nb",
    "addr:street":"Burgh Road",
    "iso:country":"GB",
    "sg:address":"75 Burgh Road",
    "sg:city":"Carlisle",
    "sg:classifiers":[
        {
            "category":"Travel",
            "subcategory":"Hotels & Motels",
            "type":"Entertainment"
        }
    ],
    "sg:phone":"+44 1228 521860",
    "sg:postcode":"CA2 7NB",
    "sg:province":"Cumbria",
    "wof:name":"Vallum House Hotel",
    "wof:placetype":"venue"
},
  "geometry": {"coordinates":[-2.9780890942,54.8978042603],"type":"Point"}
}