{
  "type": "Feature",
  "properties": {
    "iso:country":"GB",
    "sg:address":"130 Lancaster Rd, New Barnet",
    "sg:city":"Barnet",
    "sg:classifiers":[
        {
            "category":"Building & Trades",
            "subcategory":"Cleaning & Sanitation",
            "type":"Services"
        }
    ],
    "sg:phone":"+44 20 8449 8030",
    "sg:postcode":"EN4 8AL",
    "sg:province":"Hertfordshire",
    "sg:tags":[
        "commercial"
    ],
    "wof:name":"Lloyd Cleaning Company",
    "wof:placetype":"venue"
},
  "geometry": {"coordinates":[-0.1696400046,51.6440391541],"type":"Point"}
}