{
  "type": "Feature",
  "properties": {
    "addr:full":"21 Dunster Cres Hornchurch Essex RM11 3QD",
    "addr:housenumber":"21",
    "addr:postcode":"rm11 3qd",
    "addr:street":"Dunster Cres",
    "iso:country":"GB",
    "sg:address":"21 Dunster Cres",
    "sg:city":"Hornchurch",
    "sg:classifiers":[
        {
            "category":"Real Estate",
            "subcategory":"Architect",
            "type":"Services"
        }
    ],
    "sg:phone":"+44 1708 477940",
    "sg:postcode":"RM11 3QD",
    "sg:province":"Essex",
    "wof:name":"Wicek Sosna Architects",
    "wof:placetype":"venue"
},
  "geometry": {"coordinates":[0.24098,51.560226],"type":"Point"}
}