{
  "type": "Feature",
  "properties": {
    "iso:country":"GB",
    "sg:address":"A18 A46 Barton St",
    "sg:city":"Grimsby",
    "sg:classifiers":[
        {
            "category":"Restaurant",
            "type":"Food & Drink"
        }
    ],
    "sg:phone":"+44 1472 750779",
    "sg:postcode":"DN37 7LG",
    "sg:province":"Lincolnshire",
    "wof:name":"Little Chef",
    "wof:placetype":"venue"
},
  "geometry": {"coordinates":[-0.1977490038,53.5514373779],"type":"Point"}
}