{
  "type": "Feature",
  "properties": {
    "addr:full":"P O Box 1427 Sherborne Dorset DT9 4YF",
    "addr:housenumber":"p o;1427",
    "addr:postcode":"dt9 4yf",
    "iso:country":"GB",
    "sg:address":"P O Box 1427",
    "sg:city":"Sherborne",
    "sg:classifiers":[
        {
            "category":"Wholesale",
            "subcategory":"Books, Periodicals, & Newspapers",
            "type":"Manufacturing & Wholesale Goods"
        }
    ],
    "sg:phone":"+44 1935 817686",
    "sg:postcode":"DT9 4YF",
    "sg:province":"Dorset",
    "sg:tags":[
        "surplus"
    ],
    "wof:name":"Centasales Ltd.",
    "wof:placetype":"venue"
},
  "geometry": {"coordinates":[-2.514138937,50.971698761],"type":"Point"}
}