{
  "type": "Feature",
  "properties": {
    "addr:full":"4 Lansdowne Rd Bournemouth Dorset BH1 1SD",
    "addr:housenumber":"4",
    "addr:postcode":"bh1 1sd",
    "addr:street":"Lansdowne Rd",
    "iso:country":"GB",
    "sg:address":"4 Lansdowne Rd",
    "sg:city":"Bournemouth",
    "sg:classifiers":[
        {
            "category":"Professional",
            "subcategory":"Detective & Security Services",
            "type":"Services"
        }
    ],
    "sg:phone":"+44 1202 291007",
    "sg:postcode":"BH1 1SD",
    "sg:province":"Dorset",
    "sg:tags":[
        "locksmith"
    ],
    "wof:name":"Dorset Locksmith",
    "wof:placetype":"venue"
},
  "geometry": {"coordinates":[-1.867022,50.722458],"type":"Point"}
}