{
  "type": "Feature",
  "properties": {
    "iso:country":"GB",
    "sg:address":"7 Hawthorn Rd",
    "sg:city":"Bourne",
    "sg:classifiers":[
        {
            "category":"Government",
            "subcategory":"Post Office",
            "type":"Public Place"
        }
    ],
    "sg:phone":"+44 1778 393327",
    "sg:postcode":"PE10 9SN",
    "sg:province":"Lincolnshire",
    "sg:tags":[
        "messenger",
        "courier"
    ],
    "wof:name":"Fast Forward Direct",
    "wof:placetype":"venue"
},
  "geometry": {"coordinates":[-0.382502,52.775642],"type":"Point"}
}