{
  "type": "Feature",
  "properties": {
    "addr:full":"21 Grant St Cleethorpes Lincolnshire DN35 8AT",
    "addr:housenumber":"21",
    "addr:postcode":"dn35 8at",
    "addr:street":"Grant St",
    "iso:country":"GB",
    "sg:address":"21 Grant St",
    "sg:city":"Cleethorpes",
    "sg:classifiers":[
        {
            "category":"Arts & Performance",
            "subcategory":"Music",
            "type":"Entertainment"
        }
    ],
    "sg:postcode":"DN35 8AT",
    "sg:province":"Lincolnshire",
    "sg:tags":[
        "mobile",
        "disco"
    ],
    "wof:name":"Weaver,Tony,",
    "wof:placetype":"venue"
},
  "geometry": {"coordinates":[-0.0311789997,53.5619888306],"type":"Point"}
}