{
  "type": "Feature",
  "properties": {
    "iso:country":"GB",
    "sg:address":"58 Park Road",
    "sg:city":"Hampton",
    "sg:classifiers":[
        {
            "category":"Real Estate",
            "subcategory":"Architect",
            "type":"Services"
        }
    ],
    "sg:postcode":"TW12 1HP",
    "sg:province":"Greater London",
    "wof:name":"Alcor Ltd.",
    "wof:placetype":"venue"
},
  "geometry": {"coordinates":[-0.360691011,51.430519104],"type":"Point"}
}