{
  "type": "Feature",
  "properties": {
    "iso:country":"GB",
    "sg:address":"43 Woodcote Road",
    "sg:city":"Wallington",
    "sg:classifiers":[
        {
            "category":"Real Estate",
            "subcategory":"Real Estate Agent",
            "type":"Services"
        }
    ],
    "sg:phone":"+44 20 8669 9169",
    "sg:postcode":"SM6 0LR",
    "sg:province":"Surrey",
    "wof:name":"Frost Brothers Ltd.",
    "wof:placetype":"venue"
},
  "geometry": {"coordinates":[-0.1492920071,51.3581466675],"type":"Point"}
}