{
  "type": "Feature",
  "properties": {
    "addr:full":"Showell Rd Wolverhampton Staffordshire WV10 9LU",
    "addr:postcode":"wv10 9lu",
    "addr:street":"Showell Rd",
    "iso:country":"GB",
    "sg:address":"Showell Rd",
    "sg:city":"Wolverhampton",
    "sg:classifiers":[
        {
            "category":"Retail",
            "subcategory":"Auto Repair",
            "type":"Services"
        }
    ],
    "sg:phone":"+44 1902 714473",
    "sg:postcode":"WV10 9LU",
    "sg:province":"Staffordshire",
    "sg:tags":[
        "modification",
        "garage"
    ],
    "wof:name":"C.J Autos",
    "wof:placetype":"venue"
},
  "geometry": {"coordinates":[-2.122609,52.609043],"type":"Point"}
}