{
  "type": "Feature",
  "properties": {
    "addr:full":"Unit 15, Dinnington Business Centre Sheffield South Yorkshire S25 3QX",
    "addr:housenumber":"unit 15",
    "addr:postcode":"s25 3qx",
    "addr:street":"Dinnington Business Centre",
    "iso:country":"GB",
    "sg:address":"Unit 15, Dinnington Business Centre",
    "sg:city":"Sheffield",
    "sg:classifiers":[
        {
            "category":"Building & Trades",
            "subcategory":"Construction",
            "type":"Services"
        }
    ],
    "sg:phone":"+44 1909 551107",
    "sg:postcode":"S25 3QX",
    "sg:province":"South Yorkshire",
    "sg:tags":[
        "heat",
        "exchanger"
    ],
    "wof:name":"G E A Ecoflex Uk Ltd.",
    "wof:placetype":"venue"
},
  "geometry": {"coordinates":[-1.21774,53.375195],"type":"Point"}
}