{
  "type": "Feature",
  "properties": {
    "iso:country":"GB",
    "sg:address":"Harper Lodge Farm, Harper Lane",
    "sg:city":"Radlett",
    "sg:classifiers":[
        {
            "category":"Personal",
            "subcategory":"Adult",
            "type":"Services"
        }
    ],
    "sg:phone":"+44 1923 856081",
    "sg:postcode":"WD7 7HU",
    "sg:province":"Hertfordshire",
    "sg:tags":[
        "equestrian"
    ],
    "wof:name":"K T Ivory Plc",
    "wof:placetype":"venue"
},
  "geometry": {"coordinates":[-0.3172090054,51.6835746765],"type":"Point"}
}