{
  "type": "Feature",
  "properties": {
    "addr:full":"Unit 404, Building J Tower Bridge Business London Greater London SE16 4DG",
    "addr:housenumber":"404",
    "addr:postcode":"se16 4dg",
    "addr:street":"J Tower Bridge",
    "iso:country":"GB",
    "sg:address":"Unit 404, Building J Tower Bridge Business",
    "sg:city":"London",
    "sg:classifiers":[
        {
            "category":"Communications",
            "subcategory":"Film & Video Production",
            "type":"Services"
        }
    ],
    "sg:phone":"+44 20 7231 4441",
    "sg:postcode":"SE16 4DG",
    "sg:province":"Greater London",
    "sg:tags":[
        "illustrator",
        "artist"
    ],
    "wof:name":"Arts Desire",
    "wof:placetype":"venue"
},
  "geometry": {"coordinates":[-0.0634400025,51.495098114],"type":"Point"}
}