{
  "type": "Feature",
  "properties": {
    "addr:full":"52 Shirley Rd Southampton Hampshire SO15 3EU",
    "addr:housenumber":"52",
    "addr:postcode":"so15 3eu",
    "addr:street":"Shirley Rd",
    "iso:country":"GB",
    "sg:address":"52 Shirley Rd",
    "sg:city":"Southampton",
    "sg:classifiers":[
        {
            "category":"Travel",
            "subcategory":"Travel Agent",
            "type":"Entertainment"
        }
    ],
    "sg:postcode":"SO15 3EU",
    "sg:province":"Hampshire",
    "wof:name":"Crocombe,J,",
    "wof:placetype":"venue"
},
  "geometry": {"coordinates":[-1.418418,50.909676],"type":"Point"}
}