{
  "type": "Feature",
  "properties": {
    "addr:full":"Unit 12 Lwr Basset Down Workshops, Bassett Down Swindon Wiltshire SN4 9QP",
    "addr:housenumber":"unit 12;basset",
    "addr:postcode":"sn4 9qp",
    "iso:country":"GB",
    "sg:address":"Unit 12 Lwr Basset Down Workshops, Bassett Down",
    "sg:city":"Swindon",
    "sg:classifiers":[
        {
            "category":"Professional",
            "subcategory":"Engineering",
            "type":"Services"
        }
    ],
    "sg:postcode":"SN4 9QP",
    "sg:province":"Wiltshire",
    "wof:name":"Morris,Keith,",
    "wof:placetype":"venue"
},
  "geometry": {"coordinates":[-1.8388999701,51.5207595825],"type":"Point"}
}