{
  "type": "Feature",
  "properties": {
    "addr:full":"Dunkeswell Airfield, Dunkeswell Honiton Devon EX14 4RA",
    "addr:housenumber":"dunkeswell;dunkeswell",
    "addr:postcode":"ex14 4ra",
    "iso:country":"GB",
    "sg:address":"Dunkeswell Airfield, Dunkeswell",
    "sg:city":"Honiton",
    "sg:classifiers":[
        {
            "category":"Freight",
            "type":"Transportation"
        }
    ],
    "sg:postcode":"EX14 4RA",
    "sg:province":"Devon",
    "sg:tags":[
        "haulage",
        "road"
    ],
    "wof:name":"T J Coles",
    "wof:placetype":"venue"
},
  "geometry": {"coordinates":[-3.2225089073,50.8633232117],"type":"Point"}
}