{
  "type": "Feature",
  "properties": {
    "iso:country":"GB",
    "sg:address":"1 Kirby Road",
    "sg:city":"Blackpool",
    "sg:classifiers":[
        {
            "category":"Travel",
            "subcategory":"Hotels & Motels",
            "type":"Entertainment"
        }
    ],
    "sg:phone":"+44 1253 621972",
    "sg:postcode":"FY1 6EB",
    "sg:province":"Lancashire",
    "wof:name":"Fourways",
    "wof:placetype":"venue"
},
  "geometry": {"coordinates":[-3.0533208847,53.8057441711],"type":"Point"}
}