{
  "type": "Feature",
  "properties": {
    "addr:full":"15 Ceiriog Drive Caerphilly Caerphilly CF83 3FW",
    "addr:housenumber":"15",
    "addr:postcode":"cf83 3fw",
    "addr:street":"Ceiriog Drive",
    "iso:country":"GB",
    "sg:address":"15 Ceiriog Drive",
    "sg:city":"Caerphilly",
    "sg:classifiers":[
        {
            "category":"Building & Trades",
            "subcategory":"Construction",
            "type":"Services"
        }
    ],
    "sg:postcode":"CF83 3FW",
    "sg:province":"Caerphilly",
    "sg:tags":[
        "glazier",
        "decorator",
        "painter"
    ],
    "wof:name":"T W H Evans",
    "wof:placetype":"venue"
},
  "geometry": {"coordinates":[-3.227562,51.583847],"type":"Point"}
}