{
  "type": "Feature",
  "properties": {
    "iso:country":"GB",
    "sg:address":"805 New Hey Road, Outlane",
    "sg:city":"Huddersfield",
    "sg:classifiers":[
        {
            "category":"Bars & Pubs",
            "type":"Food & Drink"
        },
        {
            "category":"Community Center",
            "subcategory":"Social",
            "type":"Public Place"
        }
    ],
    "sg:phone":"+44 1422 374764",
    "sg:postcode":"HD3 3YP",
    "sg:province":"West Yorkshire",
    "sg:tags":[
        "pubs",
        "house",
        "inn",
        "activity"
    ],
    "wof:name":"Wagon & Horses Inn",
    "wof:placetype":"venue"
},
  "geometry": {"coordinates":[-1.871125,53.65794],"type":"Point"}
}