{
  "type": "Feature",
  "properties": {
    "addr:full":"1st Contact, Piccadilly Ho, 33 Regent St London Greater London SW1Y 4ND",
    "addr:housenumber":"33",
    "addr:postcode":"sw1y 4nd",
    "addr:street":"Piccadilly Ho;Regent St",
    "iso:country":"GB",
    "sg:address":"1st Contact, Piccadilly Ho, 33 Regent St",
    "sg:city":"London",
    "sg:classifiers":[
        {
            "category":"Professional",
            "subcategory":"Management & Consulting",
            "type":"Services"
        }
    ],
    "sg:postcode":"SW1Y 4ND",
    "sg:province":"Greater London",
    "sg:tags":[
        "consultant",
        "business"
    ],
    "wof:name":"Ten Man Consultants Ltd",
    "wof:placetype":"venue"
},
  "geometry": {"coordinates":[-0.13466,51.50943],"type":"Point"}
}