{
  "type": "Feature",
  "properties": {
    "addr:full":"May House Dental Practice, 4 Cadewell La Torquay Devon TQ2 7AG",
    "addr:housenumber":"4",
    "addr:postcode":"tq2 7ag",
    "addr:street":"Cadewell La Torquay",
    "iso:country":"GB",
    "sg:address":"May House Dental Practice, 4 Cadewell La",
    "sg:city":"Torquay",
    "sg:classifiers":[
        {
            "category":"Health Services",
            "subcategory":"Dentist",
            "type":"Services"
        }
    ],
    "sg:phone":"+44 1803 612525",
    "sg:postcode":"TQ2 7AG",
    "sg:province":"Devon",
    "wof:name":"J Lewis",
    "wof:placetype":"venue"
},
  "geometry": {"coordinates":[-3.543464,50.467194],"type":"Point"}
}