{
  "type": "Feature",
  "properties": {
    "iso:country":"GB",
    "sg:address":"22-24 Hill Avenue",
    "sg:city":"Amersham",
    "sg:classifiers":[
        {
            "category":"Real Estate",
            "subcategory":"Real Estate Agent",
            "type":"Services"
        }
    ],
    "sg:phone":"+44 1494 724999",
    "sg:postcode":"HP6 5BW",
    "sg:province":"Buckinghamshire",
    "wof:name":"Peter Robson & Co.",
    "wof:placetype":"venue"
},
  "geometry": {"coordinates":[-0.607826,51.675949],"type":"Point"}
}