{
  "type": "Feature",
  "properties": {
    "addr:full":"5 Legion Lane Wirral Cheshire CH62 7JQ",
    "addr:housenumber":"5",
    "addr:postcode":"ch62 7jq",
    "addr:street":"Legion Lane",
    "iso:country":"GB",
    "sg:address":"5 Legion Lane",
    "sg:city":"Wirral",
    "sg:classifiers":[
        {
            "category":"Taxi",
            "type":"Transportation"
        },
        {
            "category":"Military Area",
            "subcategory":"Air Force Base",
            "type":"Public Place"
        }
    ],
    "sg:phone":"+44 151 334 7878",
    "sg:postcode":"CH62 7JQ",
    "sg:province":"Cheshire",
    "sg:tags":[
        "hire",
        "private"
    ],
    "wof:name":"Borough Taxis",
    "wof:placetype":"venue"
},
  "geometry": {"coordinates":[-2.978873,53.331329],"type":"Point"}
}