{
  "type": "Feature",
  "properties": {
    "addr:full":"The Gatehouse, Weekin Works, 112- Park Hill Road Birmingham West Midlands B17 9HD",
    "addr:housenumber":"112",
    "addr:postcode":"b17 9hd",
    "addr:street":"Park Hill Road",
    "iso:country":"GB",
    "sg:address":"The Gatehouse, Weekin Works, 112- Park Hill Road",
    "sg:city":"Birmingham",
    "sg:classifiers":[
        {
            "category":"Wholesale",
            "subcategory":"Books, Periodicals, & Newspapers",
            "type":"Manufacturing & Wholesale Goods"
        }
    ],
    "sg:phone":"+44 121 428 4474",
    "sg:postcode":"B17 9HD",
    "sg:province":"West Midlands",
    "sg:tags":[
        "publishing"
    ],
    "wof:name":"Pepar Publications Ltd.",
    "wof:placetype":"venue"
},
  "geometry": {"coordinates":[-1.9086040258,52.4785957336],"type":"Point"}
}