{
  "type": "Feature",
  "properties": {
    "addr:full":"2 Airfield Way Christchurch Dorset BH23 3TA",
    "addr:housenumber":"2",
    "addr:postcode":"bh23 3ta",
    "addr:street":"Airfield Way",
    "iso:country":"GB",
    "sg:address":"2 Airfield Way",
    "sg:city":"Christchurch",
    "sg:classifiers":[
        {
            "category":"Home & Garden",
            "subcategory":"Kitchen Supply",
            "type":"Retail Goods"
        }
    ],
    "sg:phone":"+44 1202 471699",
    "sg:postcode":"BH23 3TA",
    "sg:province":"Dorset",
    "sg:tags":[
        "equipment",
        "catering"
    ],
    "wof:name":"Truedale Ltd",
    "wof:placetype":"venue"
},
  "geometry": {"coordinates":[-1.7503039837,50.738155365],"type":"Point"}
}