{
  "type": "Feature",
  "properties": {
    "addr:full":"127 Queen Street, Morley Leeds West Yorkshire LS27 8HE",
    "addr:housenumber":"127",
    "addr:postcode":"ls27 8he",
    "addr:street":"Queen Street",
    "iso:country":"GB",
    "sg:address":"127 Queen Street, Morley",
    "sg:city":"Leeds",
    "sg:classifiers":[
        {
            "category":"Communications",
            "type":"Services"
        }
    ],
    "sg:postcode":"LS27 8HE",
    "sg:province":"West Yorkshire",
    "sg:tags":[
        "tv",
        "video",
        "radio"
    ],
    "wof:name":"H Sutcliffe & Son",
    "wof:placetype":"venue"
},
  "geometry": {"coordinates":[-1.5996140242,53.7437057495],"type":"Point"}
}