{
  "type": "Feature",
  "properties": {
    "addr:full":"43 Red House Rd Banbury Oxfordshire OX15 4AZ",
    "addr:housenumber":"43",
    "addr:postcode":"ox15 4az",
    "addr:street":"Red House Rd",
    "iso:country":"GB",
    "sg:address":"43 Red House Rd",
    "sg:city":"Banbury",
    "sg:classifiers":[
        {
            "category":"Professional",
            "subcategory":"Art Services",
            "type":"Services"
        }
    ],
    "sg:phone":"+44 1295 262529",
    "sg:postcode":"OX15 4AZ",
    "sg:province":"Oxfordshire",
    "sg:tags":[
        "photographer"
    ],
    "wof:name":"Gee's Photorium",
    "wof:placetype":"venue"
},
  "geometry": {"coordinates":[-1.325792,52.034714],"type":"Point"}
}