{
  "type": "Feature",
  "properties": {
    "iso:country":"GB",
    "sg:address":"2a Station Road, Radyr",
    "sg:city":"Cardiff",
    "sg:classifiers":[
        {
            "category":"Professional",
            "subcategory":"Accounting & Tax Preparation",
            "type":"Services"
        }
    ],
    "sg:postcode":"CF15 8AA",
    "sg:province":"Caerphilly",
    "sg:tags":[
        "consultant"
    ],
    "wof:name":"Tax-Link",
    "wof:placetype":"venue"
},
  "geometry": {"coordinates":[-3.251489,51.515392],"type":"Point"}
}