{
  "type": "Feature",
  "properties": {
    "iso:country":"GB",
    "sg:address":"Unit 19, Hallmark Trading Estate, Fourth Way",
    "sg:city":"Wembley",
    "sg:classifiers":[
        {
            "category":"Shopping",
            "subcategory":"Clothing, Apparel, & Fashions",
            "type":"Retail Goods"
        }
    ],
    "sg:phone":"+44 20 8795 5007",
    "sg:postcode":"HA9 0LB",
    "sg:province":"Greater London",
    "sg:tags":[
        "accessory"
    ],
    "wof:name":"Poldy Ltd",
    "wof:placetype":"venue"
},
  "geometry": {"coordinates":[-0.295539,51.552963],"type":"Point"}
}