{
  "type": "Feature",
  "properties": {
    "addr:full":"11 Mardol Head Shrewsbury Shropshire SY1 1HD",
    "addr:housenumber":"11",
    "addr:postcode":"sy1 1hd",
    "addr:street":"Mardol Head",
    "iso:country":"GB",
    "sg:address":"11 Mardol Head",
    "sg:city":"Shrewsbury",
    "sg:classifiers":[
        {
            "category":"Shopping",
            "subcategory":"Shoes",
            "type":"Retail Goods"
        }
    ],
    "sg:phone":"+44 1743 343286",
    "sg:postcode":"SY1 1HD",
    "sg:province":"Shropshire",
    "sg:tags":[
        "shop"
    ],
    "wof:name":"The Oliver Group",
    "wof:placetype":"venue"
},
  "geometry": {"coordinates":[-2.7547039986,52.7081794739],"type":"Point"}
}