{
  "type": "Feature",
  "properties": {
    "addr:full":"13 Princes Street, Monifieth Dundee Angus DD5 4AW",
    "addr:housenumber":"13",
    "addr:postcode":"dd5 4aw",
    "addr:street":"Princes Street",
    "iso:country":"GB",
    "sg:address":"13 Princes Street, Monifieth",
    "sg:city":"Dundee",
    "sg:classifiers":[
        {
            "category":"Building & Trades",
            "subcategory":"Plumbing",
            "type":"Services"
        }
    ],
    "sg:phone":"+44 1382 532172",
    "sg:postcode":"DD5 4AW",
    "sg:province":"Angus",
    "sg:tags":[
        "heating"
    ],
    "wof:name":"G S Whyte & Co.",
    "wof:placetype":"venue"
},
  "geometry": {"coordinates":[-2.808084,56.484241],"type":"Point"}
}