{
  "type": "Feature",
  "properties": {
    "addr:full":"1 South Bar Street Banbury Oxfordshire OX16 9AA",
    "addr:housenumber":"1",
    "addr:postcode":"ox16 9aa",
    "addr:street":"South Bar Street",
    "iso:country":"GB",
    "sg:address":"1 South Bar Street",
    "sg:city":"Banbury",
    "sg:classifiers":[
        {
            "category":"Real Estate",
            "subcategory":"Real Estate Agent",
            "type":"Services"
        }
    ],
    "sg:phone":"+44 1295 267567",
    "sg:postcode":"OX16 9AA",
    "sg:province":"Oxfordshire",
    "wof:name":"Chancellors Estate Agents",
    "wof:placetype":"venue"
},
  "geometry": {"coordinates":[-1.340248,52.059975],"type":"Point"}
}