{
  "type": "Feature",
  "properties": {
    "addr:full":"Williams Close, Riddings Alfreton Derbyshire DE55 4DF",
    "addr:postcode":"de55 4df",
    "addr:street":"Williams Close",
    "iso:country":"GB",
    "sg:address":"Williams Close, Riddings",
    "sg:city":"Alfreton",
    "sg:classifiers":[
        {
            "category":"Building & Trades",
            "subcategory":"Landscaping Services",
            "type":"Services"
        }
    ],
    "sg:postcode":"DE55 4DF",
    "sg:province":"Derbyshire",
    "sg:tags":[
        "landscape",
        "contractor"
    ],
    "wof:name":"Croftdale Landscape & Nursery",
    "wof:placetype":"venue"
},
  "geometry": {"coordinates":[-1.362472,53.06749],"type":"Point"}
}