{
  "type": "Feature",
  "properties": {
    "addr:full":"Fore Street Castle Cary Somerset BA7 7BG",
    "addr:postcode":"ba7 7bg",
    "addr:street":"Fore Street",
    "iso:country":"GB",
    "sg:address":"Fore Street",
    "sg:city":"Castle Cary",
    "sg:classifiers":[
        {
            "category":"Real Estate",
            "subcategory":"Surveying",
            "type":"Services"
        },
        {
            "category":"Food & Beverages",
            "subcategory":"Supermarket",
            "type":"Retail Goods"
        }
    ],
    "sg:phone":"+44 1963 350482",
    "sg:postcode":"BA7 7BG",
    "sg:province":"Somerset",
    "sg:tags":[
        "surveyor",
        "valuer"
    ],
    "wof:name":"Cooper & Tanner Chartered Surveyors",
    "wof:placetype":"venue"
},
  "geometry": {"coordinates":[-2.5148239136,51.0883216858],"type":"Point"}
}