{
  "type": "Feature",
  "properties": {
    "addr:full":"100 Daneby Rd London Greater London SE6 2QG",
    "addr:housenumber":"100",
    "addr:postcode":"se6 2qg",
    "addr:street":"Daneby Rd",
    "iso:country":"GB",
    "sg:address":"100 Daneby Rd",
    "sg:city":"London",
    "sg:classifiers":[
        {
            "category":"Arts & Performance",
            "subcategory":"Music",
            "type":"Entertainment"
        }
    ],
    "sg:postcode":"SE6 2QG",
    "sg:province":"Greater London",
    "sg:tags":[
        "mobile",
        "disco"
    ],
    "wof:name":"Right Stuff Disco",
    "wof:placetype":"venue"
},
  "geometry": {"coordinates":[-0.011228,51.435375],"type":"Point"}
}