{
  "type": "Feature",
  "properties": {
    "addr:full":"16 Waterloo Terrace London Greater London N1 1TQ",
    "addr:housenumber":"16",
    "addr:postcode":"n1 1tq",
    "addr:street":"Waterloo Terrace",
    "iso:country":"GB",
    "sg:address":"16 Waterloo Terrace",
    "sg:city":"London",
    "sg:classifiers":[
        {
            "category":"Real Estate",
            "subcategory":"Architect",
            "type":"Services"
        }
    ],
    "sg:phone":"+44 20 7704 8890",
    "sg:postcode":"N1 1TQ",
    "sg:province":"Greater London",
    "wof:name":"Enthoven Architects",
    "wof:placetype":"venue"
},
  "geometry": {"coordinates":[-0.1042699963,51.5404472351],"type":"Point"}
}