{
  "type": "Feature",
  "properties": {
    "addr:full":"394 Lees Road Oldham Lancashire OL4 5EP",
    "addr:housenumber":"394",
    "addr:postcode":"ol4 5ep",
    "addr:street":"Lees Road",
    "iso:country":"GB",
    "sg:address":"394 Lees Road",
    "sg:city":"Oldham",
    "sg:classifiers":[
        {
            "category":"Bars & Pubs",
            "type":"Food & Drink"
        }
    ],
    "sg:postcode":"OL4 5EP",
    "sg:province":"Lancashire",
    "sg:tags":[
        "pubs",
        "inn"
    ],
    "wof:name":"The Royal Hotel",
    "wof:placetype":"venue"
},
  "geometry": {"coordinates":[-2.0857820511,53.5384902954],"type":"Point"}
}