{
  "type": "Feature",
  "properties": {
    "addr:full":"204a High Street Dunstable Bedfordshire LU6 3HS",
    "addr:housenumber":"204a",
    "addr:postcode":"lu6 3hs",
    "addr:street":"High Street",
    "iso:country":"GB",
    "sg:address":"204a High Street",
    "sg:city":"Dunstable",
    "sg:classifiers":[
        {
            "category":"Building & Trades",
            "subcategory":"Electrical",
            "type":"Services"
        }
    ],
    "sg:phone":"+44 1582 664627",
    "sg:postcode":"LU6 3HS",
    "sg:province":"Bedfordshire",
    "sg:tags":[
        "equipment",
        "purification",
        "air"
    ],
    "wof:name":"Environmental Air Care Ltd.",
    "wof:placetype":"venue"
},
  "geometry": {"coordinates":[-0.513775,51.881107],"type":"Point"}
}