{
  "type": "Feature",
  "properties": {
    "addr:full":"501 Slade Road Birmingham West Midlands B23 7JG",
    "addr:housenumber":"501",
    "addr:postcode":"b23 7jg",
    "addr:street":"Slade Road",
    "iso:country":"GB",
    "sg:address":"501 Slade Road",
    "sg:city":"Birmingham",
    "sg:classifiers":[
        {
            "category":"Organizations",
            "subcategory":"Non-profit Organization",
            "type":"Services"
        }
    ],
    "sg:phone":"+44 121 693 7407",
    "sg:postcode":"B23 7JG",
    "sg:province":"West Midlands",
    "sg:tags":[
        "organisation",
        "voluntary",
        "charity"
    ],
    "wof:name":"Mind in Birmingham",
    "wof:placetype":"venue"
},
  "geometry": {"coordinates":[-1.8592350483,52.5240402222],"type":"Point"}
}