{
  "type": "Feature",
  "properties": {
    "iso:country":"GB",
    "sg:address":"The Square, Aston",
    "sg:city":"Bampton",
    "sg:classifiers":[
        {
            "category":"Shopping",
            "subcategory":"Department Store",
            "type":"Retail Goods"
        },
        {
            "category":"Food & Beverages",
            "subcategory":"Groceries & Convenience Stores",
            "type":"Retail Goods"
        }
    ],
    "sg:phone":"+44 1993 850820",
    "sg:postcode":"OX18 2DL",
    "sg:province":"Gloucestershire",
    "wof:name":"Aston Stores",
    "wof:placetype":"venue"
},
  "geometry": {"coordinates":[-1.546758,51.727924],"type":"Point"}
}