{
  "type": "Feature",
  "properties": {
    "iso:country":"GB",
    "sg:address":"109 Sylvania Way",
    "sg:city":"Clydebank",
    "sg:classifiers":[
        {
            "category":"Community Center",
            "subcategory":"Social",
            "type":"Public Place"
        },
        {
            "category":"Food & Beverages",
            "subcategory":"Groceries & Convenience Stores",
            "type":"Retail Goods"
        }
    ],
    "sg:phone":"+44 141 952 7082",
    "sg:postcode":"G81 2RR",
    "sg:province":"East Dunbartonshire",
    "sg:tags":[
        "frozen",
        "retailer",
        "freezer",
        "centre"
    ],
    "wof:name":"Farmfoods Ltd.",
    "wof:placetype":"venue"
},
  "geometry": {"coordinates":[-4.403649,55.910858],"type":"Point"}
}