{
  "type": "Feature",
  "properties": {
    "addr:full":"3 Plant Street, Dadsford Bridge Estate, Wordsley Stourbridge Staffordshire DY8 5SY",
    "addr:housenumber":"3",
    "addr:postcode":"dy8 5sy",
    "addr:street":"Plant Street Dadsford Bridge Estate",
    "iso:country":"GB",
    "sg:address":"3 Plant Street, Dadsford Bridge Estate, Wordsley",
    "sg:city":"Stourbridge",
    "sg:classifiers":[
        {
            "category":"Building & Trades",
            "subcategory":"Construction",
            "type":"Services"
        }
    ],
    "sg:phone":"+44 1384 76278",
    "sg:postcode":"DY8 5SY",
    "sg:province":"Staffordshire",
    "sg:tags":[
        "heating",
        "contractor"
    ],
    "wof:name":"G T Windridge & Co. 1993 Ltd.",
    "wof:placetype":"venue"
},
  "geometry": {"coordinates":[-2.1580789089,52.4767799377],"type":"Point"}
}