{
  "type": "Feature",
  "properties": {
    "iso:country":"GB",
    "sg:address":"The Old Forge, The Street",
    "sg:city":"Chippenham",
    "sg:classifiers":[
        {
            "category":"Building & Trades",
            "subcategory":"Construction",
            "type":"Services"
        }
    ],
    "sg:postcode":"SN14 7BA",
    "sg:province":"Gloucestershire",
    "sg:tags":[
        "builder"
    ],
    "wof:name":"R C Penny (Contruction Hire)",
    "wof:placetype":"venue"
},
  "geometry": {"coordinates":[-2.19352,51.486259],"type":"Point"}
}