{
  "type": "Feature",
  "properties": {
    "addr:full":"West St Axminster Devon EX13 5PA",
    "addr:postcode":"ex13 5pa",
    "addr:street":"West St",
    "iso:country":"GB",
    "sg:address":"West St",
    "sg:city":"Axminster",
    "sg:classifiers":[
        {
            "category":"Food & Beverages",
            "subcategory":"Supermarket",
            "type":"Retail Goods"
        }
    ],
    "sg:phone":"+44 1297 35225",
    "sg:postcode":"EX13 5PA",
    "sg:province":"Devon",
    "wof:name":"CRS Ltd",
    "wof:placetype":"venue"
},
  "geometry": {"coordinates":[-2.9998230934,50.7818183899],"type":"Point"}
}