{
  "type": "Feature",
  "properties": {
    "addr:full":"22e Dragonville Durham Durham DH1 2DX",
    "addr:housenumber":"22e",
    "addr:postcode":"dh1 2dx",
    "addr:street":"Dragonville Durham",
    "iso:country":"GB",
    "sg:address":"22e Dragonville",
    "sg:city":"Durham",
    "sg:classifiers":[
        {
            "category":"Shopping",
            "subcategory":"Clothing, Apparel, & Fashions",
            "type":"Retail Goods"
        }
    ],
    "sg:postcode":"DH1 2DX",
    "sg:province":"Durham",
    "sg:tags":[
        "ladieswear"
    ],
    "wof:name":"Ours Fashions",
    "wof:placetype":"venue"
},
  "geometry": {"coordinates":[-1.534234,54.77494],"type":"Point"}
}