{
  "type": "Feature",
  "properties": {
    "iso:country":"GB",
    "sg:address":"52 The Broadway",
    "sg:city":"Leigh On Sea",
    "sg:classifiers":[
        {
            "category":"Professional",
            "subcategory":"Art Services",
            "type":"Services"
        }
    ],
    "sg:phone":"+44 1702 472771",
    "sg:postcode":"SS9 1AG",
    "sg:province":"Essex",
    "sg:tags":[
        "photographer"
    ],
    "wof:name":"John Alexander",
    "wof:placetype":"venue"
},
  "geometry": {"coordinates":[0.6580659747,51.5414085388],"type":"Point"}
}