{
  "type": "Feature",
  "properties": {
    "iso:country":"GB",
    "sg:address":"315 Kilmarnock Road",
    "sg:city":"Glasgow",
    "sg:classifiers":[
        {
            "category":"Autos & Motor Vehicles",
            "subcategory":"Fuel & Gas Station",
            "type":"Retail Goods"
        }
    ],
    "sg:phone":"+44 141 636 1640",
    "sg:postcode":"G43 2XF",
    "sg:province":"Glasgow City",
    "sg:tags":[
        "hr",
        "petrol"
    ],
    "wof:name":"Whitecart Service Station",
    "wof:placetype":"venue"
},
  "geometry": {"coordinates":[-4.286028,55.824474],"type":"Point"}
}