{
  "type": "Feature",
  "properties": {
    "iso:country":"GB",
    "sg:address":"13a New Street, Erdington",
    "sg:city":"Birmingham",
    "sg:classifiers":[
        {
            "category":"Real Estate",
            "subcategory":"Real Estate Operator",
            "type":"Services"
        }
    ],
    "sg:phone":"+44 121 384 5566",
    "sg:postcode":"B23 6SD",
    "sg:province":"West Midlands",
    "sg:tags":[
        "letting",
        "agent"
    ],
    "wof:name":"Collins Son & Harvey",
    "wof:placetype":"venue"
},
  "geometry": {"coordinates":[-1.838839,52.525303],"type":"Point"}
}