{
  "type": "Feature",
  "properties": {
    "iso:country":"GB",
    "sg:address":"Angel Drove",
    "sg:city":"Ely",
    "sg:classifiers":[
        {
            "category":"Manufacturing",
            "subcategory":"Building Materials",
            "type":"Manufacturing & Wholesale Goods"
        }
    ],
    "sg:phone":"+44 1353 662867",
    "sg:postcode":"CB7 4GA",
    "sg:province":"Cambridgeshire",
    "sg:tags":[
        "merchant",
        "builder"
    ],
    "wof:name":"Jewson Ltd.",
    "wof:placetype":"venue"
},
  "geometry": {"coordinates":[0.264832,52.392307],"type":"Point"}
}