{
  "type": "Feature",
  "properties": {
    "addr:full":"5 The Pavement, Clapham London Greater London SW4 0HY",
    "addr:housenumber":"5",
    "addr:postcode":"sw4 0hy",
    "addr:street":"The Pavement",
    "iso:country":"GB",
    "sg:address":"5 The Pavement, Clapham",
    "sg:city":"London",
    "sg:classifiers":[
        {
            "category":"Shopping",
            "subcategory":"Clothing, Apparel, & Fashions",
            "type":"Retail Goods"
        }
    ],
    "sg:phone":"+44 20 7622 2588",
    "sg:postcode":"SW4 0HY",
    "sg:province":"Greater London",
    "sg:tags":[
        "shop"
    ],
    "wof:name":"Evans",
    "wof:placetype":"venue"
},
  "geometry": {"coordinates":[-0.1387220025,51.4619216919],"type":"Point"}
}