{
  "type": "Feature",
  "properties": {
    "addr:full":"3 Woods Terrace, Murton Seaham Durham SR7 9AD",
    "addr:housenumber":"3",
    "addr:postcode":"sr7 9ad",
    "addr:street":"Woods Terrace",
    "iso:country":"GB",
    "sg:address":"3 Woods Terrace, Murton",
    "sg:city":"Seaham",
    "sg:classifiers":[
        {
            "category":"Shopping",
            "subcategory":"Pets & Pet Supplies",
            "type":"Retail Goods"
        }
    ],
    "sg:postcode":"SR7 9AD",
    "sg:province":"Durham",
    "wof:name":"Rory's Pet & Garden Centre",
    "wof:placetype":"venue"
},
  "geometry": {"coordinates":[-1.3835439682,54.8162956238],"type":"Point"}
}