{
  "type": "Feature",
  "properties": {
    "addr:full":"9 Bridge St Peterborough Cambridgeshire PE1 1HJ",
    "addr:housenumber":"9",
    "addr:postcode":"pe1 1hj",
    "addr:street":"Bridge St",
    "iso:country":"GB",
    "sg:address":"9 Bridge St",
    "sg:city":"Peterborough",
    "sg:classifiers":[
        {
            "category":"Shopping",
            "subcategory":"Hobbies, Toys, & Games",
            "type":"Retail Goods"
        }
    ],
    "sg:phone":"+44 1733 310395",
    "sg:postcode":"PE1 1HJ",
    "sg:province":"Cambridgeshire",
    "sg:tags":[
        "computer"
    ],
    "wof:name":"Software Plus",
    "wof:placetype":"venue"
},
  "geometry": {"coordinates":[-0.242198,52.572529],"type":"Point"}
}