{
  "type": "Feature",
  "properties": {
    "addr:full":"2a Green La Waterlooville Hampshire PO8 0JU",
    "addr:housenumber":"2a",
    "addr:postcode":"po8 0ju",
    "addr:street":"Green La Waterlooville",
    "iso:country":"GB",
    "sg:address":"2a Green La",
    "sg:city":"Waterlooville",
    "sg:classifiers":[
        {
            "category":"Organizations",
            "subcategory":"Membership Organization",
            "type":"Services"
        }
    ],
    "sg:phone":"+44 23 9259 2432",
    "sg:postcode":"PO8 0JU",
    "sg:province":"Hampshire",
    "sg:tags":[
        "club"
    ],
    "wof:name":"Portsdown Archery Club",
    "wof:placetype":"venue"
},
  "geometry": {"coordinates":[-0.999649,50.935726],"type":"Point"}
}