{
  "type": "Feature",
  "properties": {
    "iso:country":"GB",
    "sg:address":"Brookside Cottage, Church Road, Swallowfield",
    "sg:city":"Reading",
    "sg:classifiers":[
        {
            "category":"Building & Trades",
            "subcategory":"Construction",
            "type":"Services"
        }
    ],
    "sg:postcode":"RG7 1TH",
    "sg:province":"Berkshire",
    "sg:tags":[
        "flooring"
    ],
    "wof:name":"Boston Floors",
    "wof:placetype":"venue"
},
  "geometry": {"coordinates":[-0.966979,51.375095],"type":"Point"}
}