{
  "type": "Feature",
  "properties": {
    "iso:country":"GB",
    "sg:address":"17 Victoria Road",
    "sg:city":"Consett",
    "sg:classifiers":[
        {
            "category":"Insurance",
            "subcategory":"Insurance Agent",
            "type":"Services"
        }
    ],
    "sg:phone":"+44 1207 592222",
    "sg:postcode":"DH8 5BQ",
    "sg:province":"Durham",
    "wof:name":"Swinton",
    "wof:placetype":"venue"
},
  "geometry": {"coordinates":[-1.831844,54.852299],"type":"Point"}
}