{
  "type": "Feature",
  "properties": {
    "iso:country":"GB",
    "sg:address":"61a Kershaw Street",
    "sg:city":"Bury",
    "sg:classifiers":[
        {
            "category":"Communications",
            "type":"Services"
        }
    ],
    "sg:postcode":"BL9 7HH",
    "sg:province":"Lancashire",
    "sg:tags":[
        "telecommunication"
    ],
    "wof:name":"Ethernet Communications Ltd.",
    "wof:placetype":"venue"
},
  "geometry": {"coordinates":[-2.284949,53.592537],"type":"Point"}
}