{
  "type": "Feature",
  "properties": {
    "addr:full":"Telford Way Kettering Northamptonshire NN16 8UN",
    "addr:postcode":"nn16 8un",
    "addr:street":"Telford Way",
    "iso:country":"GB",
    "sg:address":"Telford Way",
    "sg:city":"Kettering",
    "sg:classifiers":[
        {
            "category":"Shopping",
            "subcategory":"Bicycles & Sporting Goods",
            "type":"Retail Goods"
        }
    ],
    "sg:phone":"+44 1536 484481",
    "sg:postcode":"NN16 8UN",
    "sg:province":"Northamptonshire",
    "sg:tags":[
        "equipment",
        "marine",
        "supply"
    ],
    "wof:name":"Cooney Marine International Ltd.",
    "wof:placetype":"venue"
},
  "geometry": {"coordinates":[-0.737827003,52.4126434326],"type":"Point"}
}