{
  "type": "Feature",
  "properties": {
    "iso:country":"GB",
    "sg:address":"33 Wharfside, Fenny Stratford",
    "sg:city":"Milton Keynes",
    "sg:classifiers":[
        {
            "category":"Building & Trades",
            "subcategory":"Construction",
            "type":"Services"
        }
    ],
    "sg:phone":"+44 1908 270027",
    "sg:postcode":"MK2 2AZ",
    "sg:province":"Buckinghamshire",
    "sg:tags":[
        "builder"
    ],
    "wof:name":"Central Services",
    "wof:placetype":"venue"
},
  "geometry": {"coordinates":[-0.715573,51.997162],"type":"Point"}
}