{
  "type": "Feature",
  "properties": {
    "addr:full":"Cuminestown Industrial Estate, Cuminestown Turriff Aberdeenshire AB53 5ZA",
    "addr:postcode":"ab53 5za",
    "addr:street":"Estate",
    "iso:country":"GB",
    "sg:address":"Cuminestown Industrial Estate, Cuminestown",
    "sg:city":"Turriff",
    "sg:classifiers":[
        {
            "category":"Manufacturing",
            "subcategory":"Glass & Minerals",
            "type":"Manufacturing & Wholesale Goods"
        }
    ],
    "sg:postcode":"AB53 5ZA",
    "sg:province":"Aberdeenshire",
    "sg:tags":[
        "mnfrs",
        "fibre"
    ],
    "wof:name":"Grampian Glass Fibre",
    "wof:placetype":"venue"
},
  "geometry": {"coordinates":[-2.321464,57.545254],"type":"Point"}
}