{
  "type": "Feature",
  "properties": {
    "addr:full":"7 Manor Court Common Lane Radlett Hertfordshire WD7 8PU",
    "addr:housenumber":"7",
    "addr:postcode":"wd7 8pu",
    "addr:street":"Manor Court Common Lane",
    "iso:country":"GB",
    "sg:address":"7 Manor Court Common Lane",
    "sg:city":"Radlett",
    "sg:classifiers":[
        {
            "category":"Professional",
            "subcategory":"Art Services",
            "type":"Services"
        }
    ],
    "sg:postcode":"WD7 8PU",
    "sg:province":"Hertfordshire",
    "sg:tags":[
        "photographer"
    ],
    "wof:name":"John Wender",
    "wof:placetype":"venue"
},
  "geometry": {"coordinates":[-0.33079,51.673218],"type":"Point"}
}