{
  "type": "Feature",
  "properties": {
    "addr:full":"18 High Street Dingwall Highland IV15 9RU",
    "addr:housenumber":"18",
    "addr:postcode":"iv15 9ru",
    "addr:street":"High Street",
    "iso:country":"GB",
    "sg:address":"18 High Street",
    "sg:city":"Dingwall",
    "sg:classifiers":[
        {
            "category":"Shopping",
            "subcategory":"Department Store",
            "type":"Retail Goods"
        }
    ],
    "sg:postcode":"IV15 9RU",
    "sg:province":"Highland",
    "wof:name":"Envy for Fine Things",
    "wof:placetype":"venue"
},
  "geometry": {"coordinates":[-4.4259161949,57.5951766968],"type":"Point"}
}