{
  "type": "Feature",
  "properties": {
    "addr:full":"20 Frog Lane, Upper Boddington Daventry Northamptonshire NN11 6DJ",
    "addr:housenumber":"20",
    "addr:postcode":"nn11 6dj",
    "addr:street":"Frog Lane",
    "iso:country":"GB",
    "sg:address":"20 Frog Lane, Upper Boddington",
    "sg:city":"Daventry",
    "sg:classifiers":[
        {
            "category":"Utilities",
            "subcategory":"Fuel Oil & Lpg",
            "type":"Services"
        }
    ],
    "sg:phone":"+44 1327 260224",
    "sg:postcode":"NN11 6DJ",
    "sg:province":"Northamptonshire",
    "sg:tags":[
        "coal",
        "smokeless"
    ],
    "wof:name":"W.G Cowper",
    "wof:placetype":"venue"
},
  "geometry": {"coordinates":[-1.2990750074,52.1776885986],"type":"Point"}
}