{
  "type": "Feature",
  "properties": {
    "iso:country":"GB",
    "sg:address":"Queensbridge Road",
    "sg:city":"Birmingham",
    "sg:classifiers":[
        {
            "category":"Education",
            "subcategory":"Special Training",
            "type":"Public Place"
        },
        {
            "category":"Education",
            "subcategory":"School",
            "type":"Public Place"
        },
        {
            "category":"Government",
            "subcategory":"Office",
            "type":"Public Place"
        }
    ],
    "sg:phone":"+44 121 449 1081",
    "sg:postcode":"B13 8QB",
    "sg:province":"West Midlands",
    "sg:tags":[
        "local"
    ],
    "wof:name":"Uffculme Special School",
    "wof:placetype":"venue"
},
  "geometry": {"coordinates":[-1.893231988,52.4400024414],"type":"Point"}
}