{
  "type": "Feature",
  "properties": {
    "iso:country":"GB",
    "sg:address":"Eld Road",
    "sg:city":"Coventry",
    "sg:classifiers":[
        {
            "category":"Place Of Worship",
            "type":"Public Place"
        }
    ],
    "sg:phone":"+44 24 7668 8536",
    "sg:postcode":"CV6 5DD",
    "sg:province":"Warwickshire",
    "wof:name":"St Elizabeth R C Church",
    "wof:placetype":"venue"
},
  "geometry": {"coordinates":[-1.493819,52.430084],"type":"Point"}
}