{
  "type": "Feature",
  "properties": {
    "addr:full":"63 Blackfriars Rd Salford Greater Manchester M3 7DB",
    "addr:housenumber":"63",
    "addr:postcode":"m3 7db",
    "addr:street":"Blackfriars Rd",
    "iso:country":"GB",
    "sg:address":"63 Blackfriars Rd",
    "sg:city":"Salford",
    "sg:classifiers":[
        {
            "category":"Military Area",
            "subcategory":"Air Force Base",
            "type":"Public Place"
        }
    ],
    "sg:postcode":"M3 7DB",
    "sg:province":"Greater Manchester",
    "sg:tags":[
        "taxi",
        "hire",
        "private"
    ],
    "wof:name":"Trinity Private Hire",
    "wof:placetype":"venue"
},
  "geometry": {"coordinates":[-2.255066,53.48745],"type":"Point"}
}