{
  "type": "Feature",
  "properties": {
    "addr:full":"142 London Rd Bexhill-on-sea East Sussex TN39 4AA",
    "addr:housenumber":"142",
    "addr:postcode":"tn39 4aa",
    "addr:street":"London Rd",
    "iso:country":"GB",
    "sg:address":"142 London Rd",
    "sg:city":"Bexhill-on-sea",
    "sg:classifiers":[
        {
            "category":"Building & Trades",
            "subcategory":"Construction",
            "type":"Services"
        }
    ],
    "sg:postcode":"TN39 4AA",
    "sg:province":"East Sussex",
    "sg:tags":[
        "roofing"
    ],
    "wof:name":"Usher,Heath,",
    "wof:placetype":"venue"
},
  "geometry": {"coordinates":[0.469381,50.847206],"type":"Point"}
}