{
  "type": "Feature",
  "properties": {
    "iso:country":"GB",
    "sg:address":"Aneurin Bevan House, 81 Commercial Road",
    "sg:city":"London",
    "sg:classifiers":[
        {
            "category":"Social Services",
            "type":"Services"
        }
    ],
    "sg:phone":"+44 20 7655 6709",
    "sg:postcode":"E1 1RD",
    "sg:province":"Greater London",
    "sg:tags":[
        "health",
        "authority"
    ],
    "wof:name":"East London & the City Health Authority",
    "wof:placetype":"venue"
},
  "geometry": {"coordinates":[-0.064637,51.514915],"type":"Point"}
}