{
  "type": "Feature",
  "properties": {
    "addr:full":"428 Coldharbour Lane London Greater London SW9 8LF",
    "addr:housenumber":"428",
    "addr:postcode":"sw9 8lf",
    "addr:street":"Coldharbour Lane",
    "iso:country":"GB",
    "sg:address":"428 Coldharbour Lane",
    "sg:city":"London",
    "sg:classifiers":[
        {
            "category":"Health Services",
            "subcategory":"Optometrist",
            "type":"Services"
        }
    ],
    "sg:phone":"+44 20 7737 3660",
    "sg:postcode":"SW9 8LF",
    "sg:province":"Greater London",
    "sg:tags":[
        "optician"
    ],
    "wof:name":"Clearvision Opticians",
    "wof:placetype":"venue"
},
  "geometry": {"coordinates":[-0.11409,51.461605],"type":"Point"}
}