{
  "type": "Feature",
  "properties": {
    "addr:full":"5 Lampington Row, Langton Grn Tunbridge Wells East Sussex TN3 0JG",
    "addr:housenumber":"5",
    "addr:postcode":"tn3 0jg",
    "addr:street":"Lampington Row Langton Grn;Wells",
    "iso:country":"GB",
    "sg:address":"5 Lampington Row, Langton Grn",
    "sg:city":"Tunbridge Wells",
    "sg:classifiers":[
        {
            "category":"Building & Trades",
            "subcategory":"Pest Control",
            "type":"Services"
        }
    ],
    "sg:phone":"+44 1892 863207",
    "sg:postcode":"TN3 0JG",
    "sg:province":"East Sussex",
    "sg:tags":[
        "vermin"
    ],
    "wof:name":"L. P. Apiaries",
    "wof:placetype":"venue"
},
  "geometry": {"coordinates":[0.204269,51.133865],"type":"Point"}
}