{
  "type": "Feature",
  "properties": {
    "addr:full":"96a High Street, Frimley Yateley Hampshire GU16 7JE",
    "addr:housenumber":"96a",
    "addr:postcode":"gu16 7je",
    "addr:street":"High Street",
    "iso:country":"GB",
    "sg:address":"96a High Street, Frimley",
    "sg:city":"Yateley",
    "sg:classifiers":[
        {
            "category":"Banks & Credit Unions",
            "subcategory":"Financial Services",
            "type":"Services"
        }
    ],
    "sg:phone":"+44 1276 671550",
    "sg:postcode":"GU16 7JE",
    "sg:province":"Hampshire",
    "sg:tags":[
        "adviser",
        "independent"
    ],
    "wof:name":"Enterprise Consulting",
    "wof:placetype":"venue"
},
  "geometry": {"coordinates":[-0.7452790141,51.3132591248],"type":"Point"}
}