{
  "type": "Feature",
  "properties": {
    "addr:full":"33 Seaborn Rd Morecambe Lancashire LA4 6BA",
    "addr:housenumber":"33",
    "addr:postcode":"la4 6ba",
    "addr:street":"Seaborn Rd",
    "iso:country":"GB",
    "sg:address":"33 Seaborn Rd",
    "sg:city":"Morecambe",
    "sg:classifiers":[
        {
            "category":"Food & Beverages",
            "subcategory":"Supermarket",
            "type":"Retail Goods"
        }
    ],
    "sg:postcode":"LA4 6BA",
    "sg:province":"Lancashire",
    "wof:name":"Asten,K E,",
    "wof:placetype":"venue"
},
  "geometry": {"coordinates":[-2.842228,54.076355],"type":"Point"}
}