{
  "type": "Feature",
  "properties": {
    "iso:country":"GB",
    "sg:address":"67 Hanover Street",
    "sg:city":"Stranraer",
    "sg:classifiers":[
        {
            "category":"Professional",
            "subcategory":"Art Services",
            "type":"Services"
        },
        {
            "category":"Building & Trades",
            "subcategory":"Construction",
            "type":"Services"
        }
    ],
    "sg:phone":"+44 1776 702197",
    "sg:postcode":"DG9 7RX",
    "sg:province":"Dumfries and Galloway",
    "sg:tags":[
        "decorating",
        "painting",
        "decorator",
        "painter"
    ],
    "wof:name":"Brush Strokes",
    "wof:placetype":"venue"
},
  "geometry": {"coordinates":[-5.024924,54.903435],"type":"Point"}
}