{
  "type": "Feature",
  "properties": {
    "addr:full":"57-59 Houldsworth Street Manchester Greater Manchester M1 2ES",
    "addr:housenumber":"57-59",
    "addr:postcode":"m1 2es",
    "addr:street":"Houldsworth Street",
    "iso:country":"GB",
    "sg:address":"57-59 Houldsworth Street",
    "sg:city":"Manchester",
    "sg:classifiers":[
        {
            "category":"Retail",
            "subcategory":"Event Space",
            "type":"Services"
        }
    ],
    "sg:phone":"+44 161 236 4165",
    "sg:postcode":"M1 2ES",
    "sg:province":"Greater Manchester",
    "sg:tags":[
        "exhibition",
        "organiser"
    ],
    "wof:name":"Compass Display Systems Ltd.",
    "wof:placetype":"venue"
},
  "geometry": {"coordinates":[-2.230349,53.482975],"type":"Point"}
}