{
  "type": "Feature",
  "properties": {
    "addr:full":"Oundle Road, Woodston Peterborough Cambridgeshire PE2 9PA",
    "addr:postcode":"pe2 9pa",
    "addr:street":"Oundle Road",
    "iso:country":"GB",
    "sg:address":"Oundle Road, Woodston",
    "sg:city":"Peterborough",
    "sg:classifiers":[
        {
            "category":"Government",
            "subcategory":"Post Office",
            "type":"Public Place"
        }
    ],
    "sg:phone":"+44 1733 310643",
    "sg:postcode":"PE2 9PA",
    "sg:province":"Cambridgeshire",
    "wof:name":"Woodston Post Office",
    "wof:placetype":"venue"
},
  "geometry": {"coordinates":[-0.2515639961,52.5606040955],"type":"Point"}
}