{
  "type": "Feature",
  "properties": {
    "addr:full":"Cowbridge Road East, Canton Cardiff Cardiff CF5 1GW",
    "addr:postcode":"cf5 1gw",
    "addr:street":"Cowbridge Road East",
    "iso:country":"GB",
    "sg:address":"Cowbridge Road East, Canton",
    "sg:city":"Cardiff",
    "sg:classifiers":[
        {
            "category":"Professional",
            "subcategory":"Art Services",
            "type":"Services"
        }
    ],
    "sg:phone":"+44 29 2025 1555",
    "sg:postcode":"CF5 1GW",
    "sg:province":"Cardiff",
    "sg:tags":[
        "photographer"
    ],
    "wof:name":"Olan Mills Portrait Studios",
    "wof:placetype":"venue"
},
  "geometry": {"coordinates":[-3.227634,51.484783],"type":"Point"}
}