{
  "type": "Feature",
  "properties": {
    "addr:full":"1 Allerton Road London Greater London N16 5UJ",
    "addr:housenumber":"1",
    "addr:postcode":"n16 5uj",
    "addr:street":"Allerton Road",
    "iso:country":"GB",
    "sg:address":"1 Allerton Road",
    "sg:city":"London",
    "sg:classifiers":[
        {
            "category":"Professional",
            "type":"Services"
        }
    ],
    "sg:phone":"+44 20 8809 0056",
    "sg:postcode":"N16 5UJ",
    "sg:province":"Greater London",
    "sg:tags":[
        "entertainer"
    ],
    "wof:name":"Redflame Ltd.",
    "wof:placetype":"venue"
},
  "geometry": {"coordinates":[-0.091393,51.564625],"type":"Point"}
}