{
  "type": "Feature",
  "properties": {
    "iso:country":"GB",
    "sg:address":"Canal Works, Harbour Rd",
    "sg:city":"Lydney",
    "sg:classifiers":[
        {
            "category":"Wholesale",
            "subcategory":"Scrap",
            "type":"Manufacturing & Wholesale Goods"
        }
    ],
    "sg:phone":"+44 1594 844243",
    "sg:postcode":"GL15 4EW",
    "sg:province":"Gloucestershire",
    "sg:tags":[
        "waste",
        "metal"
    ],
    "wof:name":"H.G Bendall",
    "wof:placetype":"venue"
},
  "geometry": {"coordinates":[-2.535819,51.724491],"type":"Point"}
}