{
  "type": "Feature",
  "properties": {
    "addr:full":"The Innovation Centre, Warwick Technology Park Warwick Warwickshire CV34 6UW",
    "addr:postcode":"cv34 6uw",
    "iso:country":"GB",
    "sg:address":"The Innovation Centre, Warwick Technology Park",
    "sg:city":"Warwick",
    "sg:classifiers":[
        {
            "category":"Professional",
            "subcategory":"Engineering",
            "type":"Services"
        }
    ],
    "sg:phone":"+44 1926 623200",
    "sg:postcode":"CV34 6UW",
    "sg:province":"Warwickshire",
    "sg:tags":[
        "consulting",
        "engineer"
    ],
    "wof:name":"Randle Engineering Solutions",
    "wof:placetype":"venue"
},
  "geometry": {"coordinates":[-1.591034,52.281754],"type":"Point"}
}