{
  "type": "Feature",
  "properties": {
    "addr:full":"Timbrell Street Trowbridge Wiltshire BA14 8PL",
    "addr:postcode":"ba14 8pl",
    "addr:street":"Timbrell Street",
    "iso:country":"GB",
    "sg:address":"Timbrell Street",
    "sg:city":"Trowbridge",
    "sg:classifiers":[
        {
            "category":"Health Services",
            "subcategory":"Dentist",
            "type":"Services"
        }
    ],
    "sg:phone":"+44 1225 753198",
    "sg:postcode":"BA14 8PL",
    "sg:province":"Wiltshire",
    "wof:name":"Dental Surgery",
    "wof:placetype":"venue"
},
  "geometry": {"coordinates":[-2.206112,51.323414],"type":"Point"}
}