{
  "type": "Feature",
  "properties": {
    "addr:full":"5 Silver Court, Fullerton Place Gateshead Tyne and Wear NE9 5LZ",
    "addr:housenumber":"5",
    "addr:postcode":"ne9 5lz",
    "addr:street":"Silver Court Fullerton Place",
    "iso:country":"GB",
    "sg:address":"5 Silver Court, Fullerton Place",
    "sg:city":"Gateshead",
    "sg:classifiers":[
        {
            "category":"Organizations",
            "subcategory":"Community Association",
            "type":"Services"
        }
    ],
    "sg:phone":"+44 191 478 3157",
    "sg:postcode":"NE9 5LZ",
    "sg:province":"Tyne and Wear",
    "sg:tags":[
        "associations",
        "housing",
        "co-operatives",
        "society",
        "trust",
        "societies"
    ],
    "wof:name":"Anchor Trust",
    "wof:placetype":"venue"
},
  "geometry": {"coordinates":[-1.59295,54.94928],"type":"Point"}
}