{
  "type": "Feature",
  "properties": {
    "iso:country":"GB",
    "sg:address":"Prospect Road, Denby",
    "sg:city":"Ripley",
    "sg:classifiers":[
        {
            "category":"Freight",
            "type":"Transportation"
        }
    ],
    "sg:phone":"+44 1332 880379",
    "sg:postcode":"DE5 8RE",
    "sg:province":"Derbyshire",
    "sg:tags":[
        "haulage",
        "road"
    ],
    "wof:name":"Ronald Leslie Butler",
    "wof:placetype":"venue"
},
  "geometry": {"coordinates":[-1.412279,53.012726],"type":"Point"}
}