{
  "type": "Feature",
  "properties": {
    "addr:full":"Honor Oak Park, Forest Hill Road London Greater London SE23 3LE",
    "addr:postcode":"se23 3le",
    "addr:street":"Honor;Park Forest Hill Road",
    "iso:country":"GB",
    "sg:address":"Honor Oak Park, Forest Hill Road",
    "sg:city":"London",
    "sg:classifiers":[
        {
            "category":"Education",
            "subcategory":"School",
            "type":"Public Place"
        }
    ],
    "sg:phone":"+44 20 8699 8862",
    "sg:postcode":"SE23 3LE",
    "sg:province":"Greater London",
    "sg:tags":[
        "college"
    ],
    "wof:name":"St Francesca Cabrina Primary School",
    "wof:placetype":"venue"
},
  "geometry": {"coordinates":[-0.05346,51.4496],"type":"Point"}
}