{
  "type": "Feature",
  "properties": {
    "iso:country":"GB",
    "sg:address":"Sprouston Road, Newtown St Boswells",
    "sg:city":"Kelso",
    "sg:classifiers":[
        {
            "category":"Arena",
            "subcategory":"Sports Club",
            "type":"Entertainment"
        }
    ],
    "sg:phone":"+44 1835 822917",
    "sg:postcode":"TD5 8EU",
    "sg:province":"Scottish Borders",
    "wof:name":"Newtown St.Boswells Bowling Club",
    "wof:placetype":"venue"
},
  "geometry": {"coordinates":[-2.43062,55.593037],"type":"Point"}
}