{
  "type": "Feature",
  "properties": {
    "iso:country":"GB",
    "sg:address":"40 Poole Road, Westborne",
    "sg:city":"Wimborne",
    "sg:classifiers":[
        {
            "category":"Organizations",
            "subcategory":"Membership Organization",
            "type":"Services"
        }
    ],
    "sg:phone":"+44 1202 763118",
    "sg:postcode":"BH4 9DW",
    "sg:province":"Dorset",
    "sg:tags":[
        "club"
    ],
    "wof:name":"The Grand Bingo & Social Club",
    "wof:placetype":"venue"
},
  "geometry": {"coordinates":[-1.89954,50.722389],"type":"Point"}
}