{
  "type": "Feature",
  "properties": {
    "iso:country":"GB",
    "sg:address":"146-148 Central Drive",
    "sg:city":"Blackpool",
    "sg:classifiers":[
        {
            "category":"Food & Beverages",
            "subcategory":"Liquor & Beverages",
            "type":"Retail Goods"
        }
    ],
    "sg:phone":"+44 1253 625931",
    "sg:postcode":"FY1 5EA",
    "sg:province":"Lancashire",
    "sg:tags":[
        "beer",
        "spirit",
        "wines"
    ],
    "wof:name":"Boozebuster",
    "wof:placetype":"venue"
},
  "geometry": {"coordinates":[-3.049374,53.811729],"type":"Point"}
}