{
  "type": "Feature",
  "properties": {
    "iso:country":"GB",
    "sg:address":"High Street, Cross Keys",
    "sg:city":"Newport",
    "sg:classifiers":[
        {
            "category":"Bars & Pubs",
            "type":"Food & Drink"
        }
    ],
    "sg:phone":"+44 1495 272964",
    "sg:postcode":"NP11 7FN",
    "sg:province":"Blaenau Gwent",
    "sg:tags":[
        "pubs",
        "inn"
    ],
    "wof:name":"Eagle Inn",
    "wof:placetype":"venue"
},
  "geometry": {"coordinates":[-3.1241590977,51.6195983887],"type":"Point"}
}