{
  "type": "Feature",
  "properties": {
    "iso:country":"GB",
    "sg:address":"21 Murdock Road, Brickhill, Manton Industrial Estate",
    "sg:city":"Bedford",
    "sg:classifiers":[
        {
            "category":"Home & Garden",
            "subcategory":"Building Materials",
            "type":"Retail Goods"
        }
    ],
    "sg:phone":"+44 1234 355255",
    "sg:postcode":"MK41 7PE",
    "sg:province":"Bedfordshire",
    "sg:tags":[
        "brick"
    ],
    "wof:name":"Apex Block Cutters Ltd.",
    "wof:placetype":"venue"
},
  "geometry": {"coordinates":[-0.473836,52.154182],"type":"Point"}
}