{
  "type": "Feature",
  "properties": {
    "iso:country":"GB",
    "sg:address":"80 Longbrooke, Houghton Regis",
    "sg:city":"Dunstable",
    "sg:classifiers":[
        {
            "category":"Professional",
            "subcategory":"Engineering",
            "type":"Services"
        },
        {
            "category":"Building & Trades",
            "subcategory":"Electrical",
            "type":"Services"
        }
    ],
    "sg:phone":"+44 1582 863369",
    "sg:postcode":"LU5 5QY",
    "sg:province":"Bedfordshire",
    "sg:tags":[
        "engineer",
        "electrician",
        "contractor"
    ],
    "wof:name":"Trevor Hyde",
    "wof:placetype":"venue"
},
  "geometry": {"coordinates":[-0.513807,51.906487],"type":"Point"}
}