{
  "type": "Feature",
  "properties": {
    "addr:full":"19 Hasted Close Greenhithe Kent DA9 9HS",
    "addr:housenumber":"19",
    "addr:postcode":"da9 9hs",
    "addr:street":"Hasted Close",
    "iso:country":"GB",
    "sg:address":"19 Hasted Close",
    "sg:city":"Greenhithe",
    "sg:classifiers":[
        {
            "category":"Professional",
            "subcategory":"Computer Services",
            "type":"Services"
        }
    ],
    "sg:postcode":"DA9 9HS",
    "sg:province":"Kent",
    "sg:tags":[
        "system",
        "software"
    ],
    "wof:name":"Information Essential Ltd.",
    "wof:placetype":"venue"
},
  "geometry": {"coordinates":[0.289173,51.444771],"type":"Point"}
}