{
  "type": "Feature",
  "properties": {
    "iso:country":"GB",
    "sg:address":"Belle Vue Street",
    "sg:city":"Milford Haven",
    "sg:classifiers":[
        {
            "category":"Government",
            "subcategory":"Office",
            "type":"Public Place"
        }
    ],
    "sg:postcode":"SA73 1TN",
    "sg:province":"Pembrokeshire",
    "sg:tags":[
        "local"
    ],
    "wof:name":"Pembrokeshire County Council",
    "wof:placetype":"venue"
},
  "geometry": {"coordinates":[-4.9520192146,51.7104797363],"type":"Point"}
}