{
  "type": "Feature",
  "properties": {
    "iso:country":"GB",
    "sg:address":"27 Cowgate, Kirkintilloch",
    "sg:city":"Glasgow",
    "sg:classifiers":[
        {
            "category":"Shopping",
            "subcategory":"Thrift Store",
            "type":"Retail Goods"
        }
    ],
    "sg:phone":"+44 141 776 4847",
    "sg:postcode":"G66 1HW",
    "sg:province":"East Dunbartonshire",
    "sg:tags":[
        "shop",
        "charity"
    ],
    "wof:name":"Barnardo's Shops",
    "wof:placetype":"venue"
},
  "geometry": {"coordinates":[-4.1584348679,55.9408874512],"type":"Point"}
}