{
  "type": "Feature",
  "properties": {
    "iso:country":"GB",
    "sg:address":"Station Yard Green Lane, Cherry Tree",
    "sg:city":"Blackburn",
    "sg:classifiers":[
        {
            "category":"Wholesale",
            "subcategory":"Machinery & Supplies",
            "type":"Manufacturing & Wholesale Goods"
        }
    ],
    "sg:phone":"+44 1254 209149",
    "sg:postcode":"BB2 4SH",
    "sg:province":"Lancashire",
    "sg:tags":[
        "pump"
    ],
    "wof:name":"Hydro-Recons",
    "wof:placetype":"venue"
},
  "geometry": {"coordinates":[-2.51873,53.733471],"type":"Point"}
}