{
  "type": "Feature",
  "properties": {
    "addr:full":"3-4 Sycamore Mews, Sycamore St Leicester Leicestershire LE8 4FL",
    "addr:housenumber":"3-4",
    "addr:postcode":"le8 4fl",
    "addr:street":"Sycamore Mews Sycamore St",
    "iso:country":"GB",
    "sg:address":"3-4 Sycamore Mews, Sycamore St",
    "sg:city":"Leicester",
    "sg:classifiers":[
        {
            "category":"Retail",
            "subcategory":"Repair Shop",
            "type":"Services"
        }
    ],
    "sg:phone":"+44 116 277 9705",
    "sg:postcode":"LE8 4FL",
    "sg:province":"Leicestershire",
    "sg:tags":[
        "upholsterer"
    ],
    "wof:name":"Shaun Bott Upholstery & Interiors",
    "wof:placetype":"venue"
},
  "geometry": {"coordinates":[-1.1630769968,52.5767021179],"type":"Point"}
}