{
  "type": "Feature",
  "properties": {
    "addr:full":"72 Boness Road Grangemouth Falkirk FK3 9BL",
    "addr:housenumber":"72",
    "addr:postcode":"fk3 9bl",
    "addr:street":"Boness Road",
    "iso:country":"GB",
    "sg:address":"72 Boness Road",
    "sg:city":"Grangemouth",
    "sg:classifiers":[
        {
            "category":"Health Services",
            "subcategory":"Dentist",
            "type":"Services"
        }
    ],
    "sg:phone":"+44 1324 482292",
    "sg:postcode":"FK3 9BL",
    "sg:province":"Falkirk",
    "wof:name":"The Dental Practice",
    "wof:placetype":"venue"
},
  "geometry": {"coordinates":[-3.7178039551,56.0186729431],"type":"Point"}
}