{
  "type": "Feature",
  "properties": {
    "addr:full":"Maypole Health Centre, 10 Sladepool Farm Rd Birmingham West Midlands B14 5DJ",
    "addr:housenumber":"10",
    "addr:postcode":"b14 5dj",
    "addr:street":"Sladepool Farm Rd",
    "iso:country":"GB",
    "sg:address":"Maypole Health Centre, 10 Sladepool Farm Rd",
    "sg:city":"Birmingham",
    "sg:classifiers":[
        {
            "category":"Health Services",
            "subcategory":"Doctor",
            "type":"Services"
        }
    ],
    "sg:phone":"+44 121 430 5551",
    "sg:postcode":"B14 5DJ",
    "sg:province":"West Midlands",
    "sg:tags":[
        "practitioners"
    ],
    "wof:name":"Acharya, M P",
    "wof:placetype":"venue"
},
  "geometry": {"coordinates":[-1.908604,52.478596],"type":"Point"}
}