{
  "type": "Feature",
  "properties": {
    "iso:country":"GB",
    "sg:address":"Glen House, 200-208 Totenham Court Rd",
    "sg:city":"West End",
    "sg:classifiers":[
        {
            "category":"Professional",
            "subcategory":"Employment Agencies",
            "type":"Services"
        }
    ],
    "sg:phone":"+44 20 7580 6500",
    "sg:postcode":"W1P 9LA",
    "sg:province":"Hampshire",
    "sg:tags":[
        "consultant"
    ],
    "wof:name":"Baker Associates",
    "wof:placetype":"venue"
},
  "geometry": {"coordinates":[-0.13899,51.50758],"type":"Point"}
}