{
  "type": "Feature",
  "properties": {
    "iso:country":"GB",
    "sg:address":"Linley Road, Rushall",
    "sg:city":"Walsall",
    "sg:classifiers":[
        {
            "category":"Social Services",
            "subcategory":"Retirement Home",
            "type":"Services"
        },
        {
            "category":"Government",
            "subcategory":"Office",
            "type":"Public Place"
        }
    ],
    "sg:phone":"+44 1922 720739",
    "sg:postcode":"WS4 1HL",
    "sg:province":"West Midlands",
    "sg:tags":[
        "residential",
        "local",
        "care"
    ],
    "wof:name":"Limes Home Residential Care",
    "wof:placetype":"venue"
},
  "geometry": {"coordinates":[-1.959899,52.608299],"type":"Point"}
}