{
  "type": "Feature",
  "properties": {
    "addr:full":"37 Osborne Clo Kidlington Buckinghamshire OX5 1TU",
    "addr:housenumber":"37",
    "addr:postcode":"ox5 1tu",
    "addr:street":"Osborne Clo Kidlington",
    "iso:country":"GB",
    "sg:address":"37 Osborne Clo",
    "sg:city":"Kidlington",
    "sg:classifiers":[
        {
            "category":"Building & Trades",
            "subcategory":"Construction",
            "type":"Services"
        }
    ],
    "sg:phone":"+44 1865 377819",
    "sg:postcode":"OX5 1TU",
    "sg:province":"Buckinghamshire",
    "sg:tags":[
        "decorator",
        "painter"
    ],
    "wof:name":"Class Painters",
    "wof:placetype":"venue"
},
  "geometry": {"coordinates":[-1.293751955,51.817943573],"type":"Point"}
}