{
  "type": "Feature",
  "properties": {
    "iso:country":"GB",
    "sg:address":"Cherry Tree, School Lane, Onneley",
    "sg:city":"Crewe",
    "sg:classifiers":[
        {
            "category":"Freight",
            "type":"Transportation"
        }
    ],
    "sg:postcode":"CW3 9QN",
    "sg:province":"Cheshire",
    "sg:tags":[
        "haulage",
        "road"
    ],
    "wof:name":"E Barrett & Son",
    "wof:placetype":"venue"
},
  "geometry": {"coordinates":[-2.373396,52.98394],"type":"Point"}
}