{
  "type": "Feature",
  "properties": {
    "addr:full":"5 Ladywell Rd Edinburgh City of Edinburgh EH12 7TA",
    "addr:housenumber":"5",
    "addr:postcode":"eh12 7ta",
    "addr:street":"Ladywell Rd",
    "iso:country":"GB",
    "sg:address":"5 Ladywell Rd",
    "sg:city":"Edinburgh",
    "sg:classifiers":[
        {
            "category":"Personal",
            "subcategory":"Beauty Salon",
            "type":"Services"
        }
    ],
    "sg:postcode":"EH12 7TA",
    "sg:province":"City of Edinburgh",
    "sg:tags":[
        "unisex",
        "hairdresser"
    ],
    "wof:name":"Evin,Kathrine,",
    "wof:placetype":"venue"
},
  "geometry": {"coordinates":[-3.2884418964,55.9399642944],"type":"Point"}
}