{
  "type": "Feature",
  "properties": {
    "iso:country":"GB",
    "sg:address":"5a Rock Terrace, Mossley",
    "sg:city":"Ashton-under-lyne",
    "sg:classifiers":[
        {
            "category":"Bus Charters",
            "type":"Transportation"
        }
    ],
    "sg:phone":"+44 1457 837478",
    "sg:postcode":"OL5 0RG",
    "sg:province":"Greater Manchester",
    "sg:tags":[
        "hire",
        "coach"
    ],
    "wof:name":"Hartshead Luxury Travel",
    "wof:placetype":"venue"
},
  "geometry": {"coordinates":[-2.037224,53.524364],"type":"Point"}
}