{
  "type": "Feature",
  "properties": {
    "addr:full":"7 St Helens Place London Greater London EC3A 6AU",
    "addr:housenumber":"7",
    "addr:postcode":"ec3a 6au",
    "addr:street":"St Helens Place",
    "iso:country":"GB",
    "sg:address":"7 St Helens Place",
    "sg:city":"London",
    "sg:classifiers":[
        {
            "category":"Professional",
            "subcategory":"Employment Agencies",
            "type":"Services"
        }
    ],
    "sg:phone":"+44 20 7256 9000",
    "sg:postcode":"EC3A 6AU",
    "sg:province":"Greater London",
    "sg:tags":[
        "consultant"
    ],
    "wof:name":"Rochester Partnership Ltd.",
    "wof:placetype":"venue"
},
  "geometry": {"coordinates":[-0.082016997,51.5150947571],"type":"Point"}
}