{
  "type": "Feature",
  "properties": {
    "iso:country":"GB",
    "sg:address":"West Side, Tyne Dock",
    "sg:city":"South Shields",
    "sg:classifiers":[
        {
            "category":"Manufacturing",
            "subcategory":"Building Materials",
            "type":"Manufacturing & Wholesale Goods"
        }
    ],
    "sg:phone":"+44 191 489 4481",
    "sg:postcode":"NE34 9PL",
    "sg:province":"Tyne and Wear",
    "sg:tags":[
        "merchant",
        "builder"
    ],
    "wof:name":"J T Dove",
    "wof:placetype":"venue"
},
  "geometry": {"coordinates":[-1.4546999931,54.9766082764],"type":"Point"}
}