{
  "type": "Feature",
  "properties": {
    "iso:country":"GB",
    "sg:address":"Lantsbery Drive, Liverton",
    "sg:city":"Saltburn By The Sea",
    "sg:classifiers":[
        {
            "category":"Home & Garden",
            "subcategory":"Kitchen Supply",
            "type":"Retail Goods"
        }
    ],
    "sg:phone":"+44 1287 643232",
    "sg:postcode":"TS13 4QZ",
    "sg:province":"North Yorkshire",
    "sg:tags":[
        "equipment",
        "bakery"
    ],
    "wof:name":"Stonehouse Bakery",
    "wof:placetype":"venue"
},
  "geometry": {"coordinates":[-0.900459,54.548759],"type":"Point"}
}