{
  "type": "Feature",
  "properties": {
    "iso:country":"GB",
    "sg:address":"10a Market Street",
    "sg:city":"Cinderford",
    "sg:classifiers":[
        {
            "category":"Shopping",
            "subcategory":"Gifts & Souvenirs",
            "type":"Retail Goods"
        }
    ],
    "sg:phone":"+44 1594 826005",
    "sg:postcode":"GL14 2RX",
    "sg:province":"Gloucestershire",
    "sg:tags":[
        "poster",
        "card"
    ],
    "wof:name":"Skoops",
    "wof:placetype":"venue"
},
  "geometry": {"coordinates":[-2.4996809959,51.8240776062],"type":"Point"}
}