{
  "type": "Feature",
  "properties": {
    "iso:country":"GB",
    "sg:address":"33 Bramston Clo",
    "sg:city":"Ilford",
    "sg:classifiers":[
        {
            "category":"Social Services",
            "type":"Services"
        }
    ],
    "sg:phone":"+44 20 8502 6566",
    "sg:postcode":"IG6 3DU",
    "sg:province":"Essex",
    "sg:tags":[
        "need",
        "disability",
        "special"
    ],
    "wof:name":"Redbridge Living Options In Progress",
    "wof:placetype":"venue"
},
  "geometry": {"coordinates":[0.10659,51.606548],"type":"Point"}
}