{
  "type": "Feature",
  "properties": {
    "iso:country":"GB",
    "sg:address":"The British Works, Talywain",
    "sg:city":"Pontypool",
    "sg:classifiers":[
        {
            "category":"Manufacturing",
            "subcategory":"Metals",
            "type":"Manufacturing & Wholesale Goods"
        }
    ],
    "sg:phone":"+44 1495 773730",
    "sg:postcode":"NP4 7UH",
    "sg:province":"Monmouthshire",
    "sg:tags":[
        "work",
        "sheet"
    ],
    "wof:name":"South Wales Profilers Ltd.",
    "wof:placetype":"venue"
},
  "geometry": {"coordinates":[-3.080142,51.727947],"type":"Point"}
}