{
  "type": "Feature",
  "properties": {
    "iso:country":"GB",
    "sg:address":"37 Holmethorpe Avenue",
    "sg:city":"Redhill",
    "sg:classifiers":[
        {
            "category":"Professional",
            "subcategory":"Engineering",
            "type":"Services"
        }
    ],
    "sg:phone":"+44 1737 765686",
    "sg:postcode":"RH1 2NG",
    "sg:province":"Surrey",
    "sg:tags":[
        "precision",
        "engineer"
    ],
    "wof:name":"Automatics Tooling Co. Ltd.",
    "wof:placetype":"venue"
},
  "geometry": {"coordinates":[-0.15809,51.250378],"type":"Point"}
}