{
  "type": "Feature",
  "properties": {
    "iso:country":"GB",
    "sg:address":"2 Mercian Close",
    "sg:city":"Cirencester",
    "sg:classifiers":[
        {
            "category":"Home & Garden",
            "subcategory":"Furniture",
            "type":"Retail Goods"
        }
    ],
    "sg:phone":"+44 1285 659279",
    "sg:postcode":"GL7 1LD",
    "sg:province":"Gloucestershire",
    "wof:name":"The Pine Shop",
    "wof:placetype":"venue"
},
  "geometry": {"coordinates":[-1.959117,51.709126],"type":"Point"}
}