{
  "type": "Feature",
  "properties": {
    "iso:country":"GB",
    "sg:address":"500 London Road",
    "sg:city":"Westcliff-on-sea",
    "sg:classifiers":[
        {
            "category":"Food & Beverages",
            "subcategory":"Liquor & Beverages",
            "type":"Retail Goods"
        }
    ],
    "sg:phone":"+44 1702 345474",
    "sg:postcode":"SS0 9LD",
    "sg:province":"Essex",
    "sg:tags":[
        "beer",
        "spirit",
        "wines"
    ],
    "wof:name":"Beers Unlimited",
    "wof:placetype":"venue"
},
  "geometry": {"coordinates":[0.689187,51.544487],"type":"Point"}
}