{
  "type": "Feature",
  "properties": {
    "addr:full":"58 Salusbury Road London Greater London NW6 6NP",
    "addr:housenumber":"58",
    "addr:postcode":"nw6 6np",
    "addr:street":"Salusbury Road",
    "iso:country":"GB",
    "sg:address":"58 Salusbury Road",
    "sg:city":"London",
    "sg:classifiers":[
        {
            "category":"Food & Beverages",
            "subcategory":"Liquor & Beverages",
            "type":"Retail Goods"
        }
    ],
    "sg:phone":"+44 20 7624 7639",
    "sg:postcode":"NW6 6NP",
    "sg:province":"Greater London",
    "sg:tags":[
        "beer",
        "spirit",
        "wines"
    ],
    "wof:name":"Thresher Wine Shop",
    "wof:placetype":"venue"
},
  "geometry": {"coordinates":[-0.204632,51.534889],"type":"Point"}
}