{
  "type": "Feature",
  "properties": {
    "addr:full":"2 Bridge Ct, Ermington Rd Ivybridge Devon PL21 9EY",
    "addr:housenumber":"2",
    "addr:postcode":"pl21 9ey",
    "addr:street":"Bridge Ct Ermington Rd",
    "iso:country":"GB",
    "sg:address":"2 Bridge Ct, Ermington Rd",
    "sg:city":"Ivybridge",
    "sg:classifiers":[
        {
            "category":"Home & Garden",
            "subcategory":"Building Materials",
            "type":"Retail Goods"
        }
    ],
    "sg:phone":"+44 1752 698866",
    "sg:postcode":"PL21 9EY",
    "sg:province":"Devon",
    "sg:tags":[
        "plaster",
        "ware"
    ],
    "wof:name":"Classic Mouldings",
    "wof:placetype":"venue"
},
  "geometry": {"coordinates":[-3.9290390015,50.3872642517],"type":"Point"}
}