{
  "type": "Feature",
  "properties": {
    "addr:full":"Lowlaithes Golf House Ossett West Yorkshire WF5 9AP",
    "addr:postcode":"wf5 9ap",
    "addr:street":"Ossett West",
    "iso:country":"GB",
    "sg:address":"Lowlaithes Golf House",
    "sg:city":"Ossett",
    "sg:classifiers":[
        {
            "category":"Sports & Exercise",
            "subcategory":"Golf",
            "type":"Entertainment"
        }
    ],
    "sg:phone":"+44 1924 273275",
    "sg:postcode":"WF5 9AP",
    "sg:province":"West Yorkshire",
    "sg:tags":[
        "club",
        "course"
    ],
    "wof:name":"The Low Laithes Golf Club Ltd.",
    "wof:placetype":"venue"
},
  "geometry": {"coordinates":[-1.587806,53.684235],"type":"Point"}
}