{
  "type": "Feature",
  "properties": {
    "addr:full":"34-35 Jordan Well Coventry West Midlands CV1 5RW",
    "addr:housenumber":"34-35",
    "addr:postcode":"cv1 5rw",
    "addr:street":"Jordan Well",
    "iso:country":"GB",
    "sg:address":"34-35 Jordan Well",
    "sg:city":"Coventry",
    "sg:classifiers":[
        {
            "category":"Shopping",
            "subcategory":"Clothing, Apparel, & Fashions",
            "type":"Retail Goods"
        }
    ],
    "sg:phone":"+44 24 7622 6099",
    "sg:postcode":"CV1 5RW",
    "sg:province":"West Midlands",
    "sg:tags":[
        "menswear"
    ],
    "wof:name":"First for Men",
    "wof:placetype":"venue"
},
  "geometry": {"coordinates":[-1.5044540167,52.4066581726],"type":"Point"}
}