{
  "type": "Feature",
  "properties": {
    "iso:country":"GB",
    "sg:address":"50 Albert Road",
    "sg:city":"Colne",
    "sg:classifiers":[
        {
            "category":"Professional",
            "subcategory":"Lawyer & Legal Services",
            "type":"Services"
        }
    ],
    "sg:phone":"+44 1282 864081",
    "sg:postcode":"BB8 0AW",
    "sg:province":"Lancashire",
    "sg:tags":[
        "solicitor"
    ],
    "wof:name":"Farnworth & Watson",
    "wof:placetype":"venue"
},
  "geometry": {"coordinates":[-2.1741518974,53.8561820984],"type":"Point"}
}