{
  "type": "Feature",
  "properties": {
    "addr:full":"Ifield Court Farm, Charlwood Road, Ifield Crawley West Sussex RH11 0JY",
    "addr:postcode":"rh11 0jy",
    "addr:street":"Ifield Court;Charlwood Road",
    "iso:country":"GB",
    "sg:address":"Ifield Court Farm, Charlwood Road, Ifield",
    "sg:city":"Crawley",
    "sg:classifiers":[
        {
            "category":"Farming",
            "subcategory":"Livestock Farm",
            "type":"Manufacturing & Wholesale Goods"
        }
    ],
    "sg:postcode":"RH11 0JY",
    "sg:province":"West Sussex",
    "sg:tags":[
        "others"
    ],
    "wof:name":"E A Ellis",
    "wof:placetype":"venue"
},
  "geometry": {"coordinates":[-0.2177940011,51.1240310669],"type":"Point"}
}