{
  "type": "Feature",
  "properties": {
    "addr:full":"212 Sandycombe Road, Corner Of Windsor Road Richmond Greater London TW9 2EW",
    "addr:housenumber":"212",
    "addr:postcode":"tw9 2ew",
    "addr:street":"Sandycombe Road Corner Of Windsor Road",
    "iso:country":"GB",
    "sg:address":"212 Sandycombe Road, Corner Of Windsor Road",
    "sg:city":"Richmond",
    "sg:classifiers":[
        {
            "category":"Shopping",
            "subcategory":"Antiques",
            "type":"Retail Goods"
        }
    ],
    "sg:postcode":"TW9 2EW",
    "sg:province":"Greater London",
    "wof:name":"Jims Things",
    "wof:placetype":"venue"
},
  "geometry": {"coordinates":[-0.287358,51.471775],"type":"Point"}
}