{
  "type": "Feature",
  "properties": {
    "addr:full":"68 St Mary Road London Greater London E17 9RE",
    "addr:housenumber":"68",
    "addr:postcode":"e17 9re",
    "addr:street":"St Mary Road",
    "iso:country":"GB",
    "sg:address":"68 St Mary Road",
    "sg:city":"London",
    "sg:classifiers":[
        {
            "category":"Food & Beverages",
            "subcategory":"Supermarket",
            "type":"Retail Goods"
        },
        {
            "category":"Food & Beverages",
            "subcategory":"Groceries & Convenience Stores",
            "type":"Retail Goods"
        }
    ],
    "sg:postcode":"E17 9RE",
    "sg:province":"Greater London",
    "wof:name":"P C RATFORD",
    "wof:placetype":"venue"
},
  "geometry": {"coordinates":[-0.0169479996,51.5837745667],"type":"Point"}
}