{
  "type": "Feature",
  "properties": {
    "iso:country":"GB",
    "sg:address":"Unit 6 Riverbank Business Centre, Old Shoreham Road",
    "sg:city":"Shoreham-by-sea",
    "sg:classifiers":[
        {
            "category":"Manufacturing",
            "subcategory":"Furniture",
            "type":"Manufacturing & Wholesale Goods"
        }
    ],
    "sg:phone":"+44 1273 441606",
    "sg:postcode":"BN43 5FL",
    "sg:province":"West Sussex",
    "sg:tags":[
        "polishing",
        "french"
    ],
    "wof:name":"Rodney Arthur Classics",
    "wof:placetype":"venue"
},
  "geometry": {"coordinates":[-0.2764689922,50.8319168091],"type":"Point"}
}