{
  "type": "Feature",
  "properties": {
    "addr:full":"Old Road, Darley Dale Matlock Derbyshire DE4 2ER",
    "addr:postcode":"de4 2er",
    "addr:street":"Old Road;Dale",
    "iso:country":"GB",
    "sg:address":"Old Road, Darley Dale",
    "sg:city":"Matlock",
    "sg:classifiers":[
        {
            "category":"Travel",
            "subcategory":"Hotels & Motels",
            "type":"Entertainment"
        }
    ],
    "sg:phone":"+44 1629 733775",
    "sg:postcode":"DE4 2ER",
    "sg:province":"Derbyshire",
    "wof:name":"G Banks",
    "wof:placetype":"venue"
},
  "geometry": {"coordinates":[-1.6016340256,53.1641044617],"type":"Point"}
}