{
  "type": "Feature",
  "properties": {
    "addr:full":"8 The Plain, Thornbury Bristol Gloucestershire BS35 2AG",
    "addr:housenumber":"8",
    "addr:postcode":"bs35 2ag",
    "addr:street":"The Plain",
    "iso:country":"GB",
    "sg:address":"8 The Plain, Thornbury",
    "sg:city":"Bristol",
    "sg:classifiers":[
        {
            "category":"Health Services",
            "subcategory":"Health Practitioner",
            "type":"Services"
        }
    ],
    "sg:phone":"+44 1454 281243",
    "sg:postcode":"BS35 2AG",
    "sg:province":"Gloucestershire",
    "sg:tags":[
        "osteopath"
    ],
    "wof:name":"Jones Cheryl",
    "wof:placetype":"venue"
},
  "geometry": {"coordinates":[-2.5252609253,51.6092567444],"type":"Point"}
}