{
  "type": "Feature",
  "properties": {
    "iso:country":"GB",
    "sg:address":"Unit 11 White Hart Arcade",
    "sg:city":"Launceston",
    "sg:classifiers":[
        {
            "category":"Utilities",
            "subcategory":"Fuel Oil & Lpg",
            "type":"Services"
        }
    ],
    "sg:phone":"+44 1566 773621",
    "sg:postcode":"PL15 8AA",
    "sg:province":"Cornwall",
    "wof:name":"David Viggers Ltd.",
    "wof:placetype":"venue"
},
  "geometry": {"coordinates":[-4.363344,50.636707],"type":"Point"}
}