{
  "type": "Feature",
  "properties": {
    "iso:country":"GB",
    "sg:address":"108-110 Burghley Road",
    "sg:city":"Peterborough",
    "sg:classifiers":[
        {
            "category":"Manufacturing",
            "subcategory":"Tools & Machinery",
            "type":"Manufacturing & Wholesale Goods"
        }
    ],
    "sg:phone":"+44 1733 564252",
    "sg:postcode":"PE1 2QE",
    "sg:province":"Cambridgeshire",
    "sg:tags":[
        "manufacture",
        "powertools",
        "power",
        "supply"
    ],
    "wof:name":"Williams Distributors",
    "wof:placetype":"venue"
},
  "geometry": {"coordinates":[-0.2433719933,52.5812492371],"type":"Point"}
}