{
  "type": "Feature",
  "properties": {
    "addr:full":"3 Elmwood Parade, Elmwood Way Basingstoke Hampshire RG23 8LL",
    "addr:housenumber":"3",
    "addr:postcode":"rg23 8ll",
    "addr:street":"Elmwood Parade Elmwood Way",
    "iso:country":"GB",
    "sg:address":"3 Elmwood Parade, Elmwood Way",
    "sg:city":"Basingstoke",
    "sg:classifiers":[
        {
            "category":"Personal",
            "subcategory":"Beauty Salon",
            "type":"Services"
        }
    ],
    "sg:postcode":"RG23 8LL",
    "sg:province":"Hampshire",
    "wof:name":"Duette",
    "wof:placetype":"venue"
},
  "geometry": {"coordinates":[-1.1223640442,51.2736854553],"type":"Point"}
}