{
  "type": "Feature",
  "properties": {
    "addr:full":"19 Stone Breck, Costessey Norwich Norfolk NR5 0PP",
    "addr:housenumber":"19",
    "addr:postcode":"nr5 0pp",
    "addr:street":"Stone Breck;Norwich Norfolk",
    "iso:country":"GB",
    "sg:address":"19 Stone Breck, Costessey",
    "sg:city":"Norwich",
    "sg:classifiers":[
        {
            "category":"Shopping",
            "subcategory":"Department Store",
            "type":"Retail Goods"
        }
    ],
    "sg:postcode":"NR5 0PP",
    "sg:province":"Norfolk",
    "wof:name":"C D R (Lighting) Ltd",
    "wof:placetype":"venue"
},
  "geometry": {"coordinates":[1.212917,52.648773],"type":"Point"}
}