{
  "type": "Feature",
  "properties": {
    "addr:full":"Salford Court, Clifton-on-teme Worcester Herefordshire WR6 6EW",
    "addr:postcode":"wr6 6ew",
    "addr:street":"Salford",
    "iso:country":"GB",
    "sg:address":"Salford Court, Clifton-on-teme",
    "sg:city":"Worcester",
    "sg:classifiers":[
        {
            "category":"Farming",
            "subcategory":"Livestock Farm",
            "type":"Manufacturing & Wholesale Goods"
        }
    ],
    "sg:phone":"+44 1886 853238",
    "sg:postcode":"WR6 6EW",
    "sg:province":"Herefordshire",
    "sg:tags":[
        "others"
    ],
    "wof:name":"J E Yeomans & Son",
    "wof:placetype":"venue"
},
  "geometry": {"coordinates":[-2.4316399097,52.2651901245],"type":"Point"}
}