{
  "type": "Feature",
  "properties": {
    "iso:country":"GB",
    "sg:address":"1b Pickford Lane",
    "sg:city":"Bexleyheath",
    "sg:classifiers":[
        {
            "category":"Retail",
            "subcategory":"Auto Repair",
            "type":"Services"
        }
    ],
    "sg:postcode":"DA7 4RD",
    "sg:province":"Kent",
    "sg:tags":[
        "modification",
        "garage"
    ],
    "wof:name":"Roger Moore",
    "wof:placetype":"venue"
},
  "geometry": {"coordinates":[0.132441,51.463699],"type":"Point"}
}