{
  "type": "Feature",
  "properties": {
    "iso:country":"GB",
    "sg:address":"2420 London Road",
    "sg:city":"Glasgow",
    "sg:classifiers":[
        {
            "category":"Shopping",
            "type":"Retail Goods"
        }
    ],
    "sg:postcode":"G32 8XZ",
    "sg:province":"Glasgow City",
    "sg:tags":[
        "part",
        "accessory"
    ],
    "wof:name":"Autosafe",
    "wof:placetype":"venue"
},
  "geometry": {"coordinates":[-4.14633,55.838196],"type":"Point"}
}