{
  "type": "Feature",
  "properties": {
    "addr:full":"Wherwel Priory, Wherwell Andover Hampshire SP11 7JH",
    "addr:postcode":"sp11 7jh",
    "iso:country":"GB",
    "sg:address":"Wherwel Priory, Wherwell",
    "sg:city":"Andover",
    "sg:classifiers":[
        {
            "category":"Shopping",
            "subcategory":"Bicycles & Sporting Goods",
            "type":"Retail Goods"
        },
        {
            "category":"Food & Beverages",
            "subcategory":"Bakery",
            "type":"Retail Goods"
        }
    ],
    "sg:phone":"+44 1264 860186",
    "sg:postcode":"SP11 7JH",
    "sg:province":"Hampshire",
    "sg:tags":[
        "equipment",
        "baker",
        "marine",
        "supply"
    ],
    "wof:name":"Simplex-Turbulo Co. Ltd.",
    "wof:placetype":"venue"
},
  "geometry": {"coordinates":[-1.4447779655,51.1662864685],"type":"Point"}
}