{
  "type": "Feature",
  "properties": {
    "addr:full":"31 Redenhall Road Harleston Norfolk IP20 9HE",
    "addr:housenumber":"31",
    "addr:postcode":"ip20 9he",
    "addr:street":"Redenhall Road",
    "iso:country":"GB",
    "sg:address":"31 Redenhall Road",
    "sg:city":"Harleston",
    "sg:classifiers":[
        {
            "category":"Personal",
            "type":"Services"
        }
    ],
    "sg:postcode":"IP20 9HE",
    "sg:province":"Norfolk",
    "sg:tags":[
        "dressmaker"
    ],
    "wof:name":"Ivy Fashions",
    "wof:placetype":"venue"
},
  "geometry": {"coordinates":[1.3050940037,52.4066352844],"type":"Point"}
}