{
  "type": "Feature",
  "properties": {
    "addr:full":"Sadle Safari, Crown Lane Marlow Berkshire SL7 3HL",
    "addr:postcode":"sl7 3hl",
    "addr:street":"Crown Lane",
    "iso:country":"GB",
    "sg:address":"Sadle Safari, Crown Lane",
    "sg:city":"Marlow",
    "sg:classifiers":[
        {
            "category":"Shopping",
            "subcategory":"Bicycles & Sporting Goods",
            "type":"Retail Goods"
        }
    ],
    "sg:postcode":"SL7 3HL",
    "sg:province":"Berkshire",
    "sg:tags":[
        "cycle",
        "accessory"
    ],
    "wof:name":"Saddle Safari",
    "wof:placetype":"venue"
},
  "geometry": {"coordinates":[-0.741308,51.584927],"type":"Point"}
}