{
  "type": "Feature",
  "properties": {
    "iso:country":"GB",
    "sg:address":"Shire View The Leeds Centre, 72 Headingley Lane",
    "sg:city":"Leeds",
    "sg:classifiers":[
        {
            "category":"Professional",
            "subcategory":"Printing & Photocopies",
            "type":"Services"
        }
    ],
    "sg:phone":"+44 113 214 4540",
    "sg:postcode":"LS6 2DJ",
    "sg:province":"West Yorkshire",
    "sg:tags":[
        "printer"
    ],
    "wof:name":"Brail & Large Print Services",
    "wof:placetype":"venue"
},
  "geometry": {"coordinates":[-1.574360013,53.8187789917],"type":"Point"}
}