{
  "type": "Feature",
  "properties": {
    "iso:country":"GB",
    "sg:address":"176 Stockport Road",
    "sg:city":"Stockport",
    "sg:classifiers":[
        {
            "category":"Building & Trades",
            "subcategory":"Plumbing",
            "type":"Services"
        }
    ],
    "sg:postcode":"SK3 0NW",
    "sg:province":"Cheshire",
    "sg:tags":[
        "drain",
        "clearance",
        "sewer"
    ],
    "wof:name":"A1 Superkleen Ltd.",
    "wof:placetype":"venue"
},
  "geometry": {"coordinates":[-2.1895999908,53.4025611877],"type":"Point"}
}