{
  "type": "Feature",
  "properties": {
    "addr:full":"Peterdale, Moorhouse Carlisle Cumbria CA5 6EY",
    "addr:postcode":"ca5 6ey",
    "iso:country":"GB",
    "sg:address":"Peterdale, Moorhouse",
    "sg:city":"Carlisle",
    "sg:classifiers":[
        {
            "category":"Building & Trades",
            "subcategory":"Construction",
            "type":"Services"
        }
    ],
    "sg:phone":"+44 1228 576891",
    "sg:postcode":"CA5 6EY",
    "sg:province":"Cumbria",
    "sg:tags":[
        "builder"
    ],
    "wof:name":"R & F Richardson",
    "wof:placetype":"venue"
},
  "geometry": {"coordinates":[-3.0402669907,54.901134491],"type":"Point"}
}