{
  "type": "Feature",
  "properties": {
    "addr:full":"Lamberts Garage, Town Street, Farsley Pudsey West Yorkshire LS28 5HX",
    "addr:postcode":"ls28 5hx",
    "addr:street":"Town Street;West",
    "iso:country":"GB",
    "sg:address":"Lamberts Garage, Town Street, Farsley",
    "sg:city":"Pudsey",
    "sg:classifiers":[
        {
            "category":"Autos & Motor Vehicles",
            "subcategory":"Automobile Sales",
            "type":"Retail Goods"
        }
    ],
    "sg:phone":"+44 113 239 3023",
    "sg:postcode":"LS28 5HX",
    "sg:province":"West Yorkshire",
    "sg:tags":[
        "car",
        "used",
        "commercial"
    ],
    "sg:website":"http://www.doylesoffarsley.co.uk",
    "wof:name":"Doyles Of Farsley",
    "wof:placetype":"venue"
},
  "geometry": {"coordinates":[-1.67147,53.812592],"type":"Point"}
}