{
  "type": "Feature",
  "properties": {
    "iso:country":"GB",
    "sg:address":"10 Charlotte Street",
    "sg:city":"Manchester",
    "sg:classifiers":[
        {
            "category":"Professional",
            "subcategory":"Accounting & Tax Preparation",
            "type":"Services"
        }
    ],
    "sg:phone":"+44 161 236 9354",
    "sg:postcode":"M1 4EX",
    "sg:province":"Greater Manchester",
    "sg:tags":[
        "consultant",
        "consultancy"
    ],
    "wof:name":"Brody Lee Cershaw & Co.",
    "wof:placetype":"venue"
},
  "geometry": {"coordinates":[-2.240218,53.479309],"type":"Point"}
}