{
  "type": "Feature",
  "properties": {
    "addr:full":"69 Kilmarnock Road Glasgow Glasgow City G41 3YR",
    "addr:housenumber":"69",
    "addr:postcode":"g41 3yr",
    "addr:street":"Kilmarnock Road",
    "iso:country":"GB",
    "sg:address":"69 Kilmarnock Road",
    "sg:city":"Glasgow",
    "sg:classifiers":[
        {
            "category":"Home & Garden",
            "subcategory":"Home Furnishings",
            "type":"Retail Goods"
        }
    ],
    "sg:phone":"+44 141 636 6021",
    "sg:postcode":"G41 3YR",
    "sg:province":"Glasgow City",
    "sg:tags":[
        "furnishers",
        "planner",
        "kitchen"
    ],
    "wof:name":"Moben Kitchens",
    "wof:placetype":"venue"
},
  "geometry": {"coordinates":[-4.2830338478,55.8287010193],"type":"Point"}
}