{
  "type": "Feature",
  "properties": {
    "addr:full":"79 High Street Wallingford Oxfordshire OX10 0BX",
    "addr:housenumber":"79",
    "addr:postcode":"ox10 0bx",
    "addr:street":"High Street",
    "iso:country":"GB",
    "sg:address":"79 High Street",
    "sg:city":"Wallingford",
    "sg:classifiers":[
        {
            "category":"Cafe",
            "type":"Food & Drink"
        }
    ],
    "sg:phone":"+44 1491 836308",
    "sg:postcode":"OX10 0BX",
    "sg:province":"Oxfordshire",
    "sg:tags":[
        "tea",
        "room"
    ],
    "wof:name":"Annie's Tea Rooms",
    "wof:placetype":"venue"
},
  "geometry": {"coordinates":[-1.125036,51.601078],"type":"Point"}
}