{
  "type": "Feature",
  "properties": {
    "iso:country":"GB",
    "sg:address":"Drayton Lane, Drayton",
    "sg:city":"Portsmouth",
    "sg:classifiers":[
        {
            "category":"Education",
            "subcategory":"Special Training",
            "type":"Public Place"
        },
        {
            "category":"Government",
            "subcategory":"Office",
            "type":"Public Place"
        }
    ],
    "sg:phone":"+44 23 9237 5318",
    "sg:postcode":"PO6 1HG",
    "sg:province":"Hampshire",
    "sg:tags":[
        "school",
        "local"
    ],
    "wof:name":"The Futcher School",
    "wof:placetype":"venue"
},
  "geometry": {"coordinates":[-1.040704,50.846596],"type":"Point"}
}