{
  "type": "Feature",
  "properties": {
    "addr:full":"176 Belasis Av Billingham Durham TS23 1EY",
    "addr:housenumber":"176",
    "addr:postcode":"ts23 1ey",
    "addr:street":"Av Billingham",
    "iso:country":"GB",
    "sg:address":"176 Belasis Av",
    "sg:city":"Billingham",
    "sg:classifiers":[
        {
            "category":"Professional",
            "subcategory":"Detective & Security Services",
            "type":"Services"
        }
    ],
    "sg:phone":"+44 1642 559711",
    "sg:postcode":"TS23 1EY",
    "sg:province":"Durham",
    "wof:name":"Securicor Guarding",
    "wof:placetype":"venue"
},
  "geometry": {"coordinates":[-1.2774790525,54.5983963013],"type":"Point"}
}