{
  "type": "Feature",
  "properties": {
    "iso:country":"GB",
    "sg:address":"35 Curzon St",
    "sg:city":"West End",
    "sg:classifiers":[
        {
            "category":"Professional",
            "subcategory":"Employment Agencies",
            "type":"Services"
        }
    ],
    "sg:phone":"+44 20 7495 1234",
    "sg:postcode":"W1Y 7AE",
    "sg:province":"Hampshire",
    "sg:tags":[
        "consultant"
    ],
    "wof:name":"Howgate Sable & Partners",
    "wof:placetype":"venue"
},
  "geometry": {"coordinates":[-0.148617,51.506481],"type":"Point"}
}