{
  "type": "Feature",
  "properties": {
    "iso:country":"GB",
    "sg:address":"Unit 4 James Cameron House, 12 Castlehaven Road",
    "sg:city":"London",
    "sg:classifiers":[
        {
            "category":"Manufacturing",
            "subcategory":"Apparel",
            "type":"Manufacturing & Wholesale Goods"
        }
    ],
    "sg:phone":"+44 20 7485 1425",
    "sg:postcode":"NW1 8QW",
    "sg:province":"Greater London",
    "sg:tags":[
        "garment",
        "designer"
    ],
    "wof:name":"Charles Gray London Ltd.",
    "wof:placetype":"venue"
},
  "geometry": {"coordinates":[-0.144798,51.542255],"type":"Point"}
}