{
  "type": "Feature",
  "properties": {
    "addr:full":"7 Memorial Road, Worsley Manchester Greater Manchester M28 3AQ",
    "addr:housenumber":"7",
    "addr:postcode":"m28 3aq",
    "addr:street":"Memorial Road",
    "iso:country":"GB",
    "sg:address":"7 Memorial Road, Worsley",
    "sg:city":"Manchester",
    "sg:classifiers":[
        {
            "category":"Real Estate",
            "subcategory":"Surveying",
            "type":"Services"
        }
    ],
    "sg:postcode":"M28 3AQ",
    "sg:province":"Greater Manchester",
    "sg:tags":[
        "surveyor",
        "valuer"
    ],
    "wof:name":"Carr & Hume",
    "wof:placetype":"venue"
},
  "geometry": {"coordinates":[-2.398485,53.522724],"type":"Point"}
}