{
  "type": "Feature",
  "properties": {
    "addr:full":"19 Newcastle Rd Chester-le-street Durham DH3 3TX",
    "addr:housenumber":"19",
    "addr:postcode":"dh3 3tx",
    "addr:street":"Newcastle Rd",
    "iso:country":"GB",
    "sg:address":"19 Newcastle Rd",
    "sg:city":"Chester-le-street",
    "sg:classifiers":[
        {
            "category":"Industrial Area",
            "type":"Public Place"
        }
    ],
    "sg:postcode":"DH3 3TX",
    "sg:province":"Durham",
    "sg:tags":[
        "sharpening",
        "saw",
        "repair"
    ],
    "wof:name":"Durham Lock & Key Co",
    "wof:placetype":"venue"
},
  "geometry": {"coordinates":[-1.574277997,54.8617286682],"type":"Point"}
}