{
  "type": "Feature",
  "properties": {
    "addr:full":"Brick Kiln Street, Off Canal Street Brierley Hill West Midlands DY5 1JJ",
    "addr:postcode":"dy5 1jj",
    "addr:street":"Brick Kiln Street Off Canal Street",
    "iso:country":"GB",
    "sg:address":"Brick Kiln Street, Off Canal Street",
    "sg:city":"Brierley Hill",
    "sg:classifiers":[
        {
            "category":"Autos & Motor Vehicles",
            "subcategory":"Auto Supplies",
            "type":"Retail Goods"
        }
    ],
    "sg:phone":"+44 1384 263676",
    "sg:postcode":"DY5 1JJ",
    "sg:province":"West Midlands",
    "sg:tags":[
        "car",
        "component"
    ],
    "wof:name":"E & S Accessories",
    "wof:placetype":"venue"
},
  "geometry": {"coordinates":[-2.113164,52.493027],"type":"Point"}
}