{
  "type": "Feature",
  "properties": {
    "iso:country":"GB",
    "sg:address":"Crown Ho, 80 Crown Rd",
    "sg:city":"Twickenham",
    "sg:classifiers":[
        {
            "category":"Manufacturing",
            "subcategory":"Signs",
            "type":"Manufacturing & Wholesale Goods"
        }
    ],
    "sg:phone":"+44 20 8892 7008",
    "sg:postcode":"TW1 3ER",
    "sg:province":"Greater London",
    "sg:tags":[
        "writer"
    ],
    "wof:name":"Allsigns",
    "wof:placetype":"venue"
},
  "geometry": {"coordinates":[-0.328229,51.446636],"type":"Point"}
}