{
  "type": "Feature",
  "properties": {
    "addr:full":"Unit 6, Pontnewynydd Industrial Estate Pontypool Monmouthshire NP4 6YW",
    "addr:housenumber":"unit 6",
    "addr:postcode":"np4 6yw",
    "addr:street":"Pontnewynydd Industrial Estate",
    "iso:country":"GB",
    "sg:address":"Unit 6, Pontnewynydd Industrial Estate",
    "sg:city":"Pontypool",
    "sg:classifiers":[
        {
            "category":"Autos & Motor Vehicles",
            "subcategory":"Auto Supplies",
            "type":"Retail Goods"
        }
    ],
    "sg:phone":"+44 1495 753667",
    "sg:postcode":"NP4 6YW",
    "sg:province":"Monmouthshire",
    "sg:tags":[
        "electric",
        "servicing",
        "sales"
    ],
    "wof:name":"Pontypool Rewinds Ltd.",
    "wof:placetype":"venue"
},
  "geometry": {"coordinates":[-3.0600659847,51.7087516785],"type":"Point"}
}