{
  "type": "Feature",
  "properties": {
    "addr:full":"363 Bearwood Rd Smethwick West Midlands B66 4DB",
    "addr:housenumber":"363",
    "addr:postcode":"b66 4db",
    "addr:street":"Bearwood Rd",
    "iso:country":"GB",
    "sg:address":"363 Bearwood Rd",
    "sg:city":"Smethwick",
    "sg:classifiers":[
        {
            "category":"Farming",
            "subcategory":"Fish & Marine Products",
            "type":"Manufacturing & Wholesale Goods"
        }
    ],
    "sg:postcode":"B66 4DB",
    "sg:province":"West Midlands",
    "sg:tags":[
        "fishmonger"
    ],
    "wof:name":"Blewitt",
    "wof:placetype":"venue"
},
  "geometry": {"coordinates":[-1.969547,52.480213],"type":"Point"}
}