{
  "type": "Feature",
  "properties": {
    "iso:country":"GB",
    "sg:address":"786 Chesterfield Rd, Woodseats",
    "sg:city":"Sheffield",
    "sg:classifiers":[
        {
            "category":"Real Estate",
            "subcategory":"Real Estate Agent",
            "type":"Services"
        }
    ],
    "sg:postcode":"S8 0SF",
    "sg:province":"Derbyshire",
    "wof:name":"Haybrook Ltd",
    "wof:placetype":"venue"
},
  "geometry": {"coordinates":[-1.478208,53.34203],"type":"Point"}
}