{
  "type": "Feature",
  "properties": {
    "iso:country":"GB",
    "sg:address":"70 Bridgen Road",
    "sg:city":"Bexley",
    "sg:classifiers":[
        {
            "category":"Real Estate",
            "subcategory":"Architect",
            "type":"Services"
        }
    ],
    "sg:postcode":"DA5 1JG",
    "sg:province":"Kent",
    "wof:name":"Phoenixset Ltd.",
    "wof:placetype":"venue"
},
  "geometry": {"coordinates":[0.133806,51.444885],"type":"Point"}
}