{
  "type": "Feature",
  "properties": {
    "addr:full":"Arterial Road Basildon Essex SS14 3JH",
    "addr:postcode":"ss14 3jh",
    "addr:street":"Arterial Road",
    "iso:country":"GB",
    "sg:address":"Arterial Road",
    "sg:city":"Basildon",
    "sg:classifiers":[
        {
            "category":"Home & Garden",
            "subcategory":"Garden Supply",
            "type":"Retail Goods"
        }
    ],
    "sg:phone":"+44 1268 285145",
    "sg:postcode":"SS14 3JH",
    "sg:province":"Essex",
    "sg:tags":[
        "planting",
        "tree",
        "shrub"
    ],
    "wof:name":"Stevensons Farm",
    "wof:placetype":"venue"
},
  "geometry": {"coordinates":[0.4820710123,51.5919303894],"type":"Point"}
}