{
  "type": "Feature",
  "properties": {
    "addr:full":"109 Ditchling Road Brighton East Sussex BN1 4SE",
    "addr:housenumber":"109",
    "addr:postcode":"bn1 4se",
    "addr:street":"Ditchling Road",
    "iso:country":"GB",
    "sg:address":"109 Ditchling Road",
    "sg:city":"Brighton",
    "sg:classifiers":[
        {
            "category":"Health Services",
            "subcategory":"Nursing And Care Facility",
            "type":"Services"
        }
    ],
    "sg:postcode":"BN1 4SE",
    "sg:province":"East Sussex",
    "sg:tags":[
        "home"
    ],
    "wof:name":"B M Bellingham",
    "wof:placetype":"venue"
},
  "geometry": {"coordinates":[-0.1339730024,50.8347511292],"type":"Point"}
}