{
  "type": "Feature",
  "properties": {
    "addr:full":"Annex, Thompson Close Ilford Essex IG1 1TY",
    "addr:postcode":"ig1 1ty",
    "addr:street":"Thompson Close",
    "iso:country":"GB",
    "sg:address":"Annex, Thompson Close",
    "sg:city":"Ilford",
    "sg:classifiers":[
        {
            "category":"Education",
            "subcategory":"School",
            "type":"Public Place"
        }
    ],
    "sg:phone":"+44 20 8501 3951",
    "sg:postcode":"IG1 1TY",
    "sg:province":"Essex",
    "sg:tags":[
        "local",
        "authority"
    ],
    "wof:name":"New Rush Hall Secondary School",
    "wof:placetype":"venue"
},
  "geometry": {"coordinates":[0.081234999,51.5609588623],"type":"Point"}
}