{
  "type": "Feature",
  "properties": {
    "iso:country":"GB",
    "sg:address":"Amotherby",
    "sg:city":"Malton",
    "sg:classifiers":[
        {
            "category":"Retail",
            "subcategory":"Auto Repair",
            "type":"Services"
        }
    ],
    "sg:phone":"+44 1653 693616",
    "sg:postcode":"YO17 6TG",
    "sg:province":"North Yorkshire",
    "sg:tags":[
        "modification",
        "garage",
        "related"
    ],
    "wof:name":"BENTLEY'S GARAGE",
    "wof:placetype":"venue"
},
  "geometry": {"coordinates":[-0.8538380265,54.1506462097],"type":"Point"}
}