{
  "type": "Feature",
  "properties": {
    "iso:country":"GB",
    "sg:address":"Great North Road, Great Ponton",
    "sg:city":"Grantham",
    "sg:classifiers":[
        {
            "category":"Retail",
            "subcategory":"Auto Repair",
            "type":"Services"
        }
    ],
    "sg:phone":"+44 1476 530261",
    "sg:postcode":"NG33 5DW",
    "sg:province":"Leicestershire",
    "sg:tags":[
        "modification",
        "garage"
    ],
    "wof:name":"Ponton Main Service Station",
    "wof:placetype":"venue"
},
  "geometry": {"coordinates":[-0.621134,52.814964],"type":"Point"}
}