{
  "type": "Feature",
  "properties": {
    "iso:country":"GB",
    "sg:address":"Killington Farm, Martinhoe, Parracombe",
    "sg:city":"Barnstaple",
    "sg:classifiers":[
        {
            "category":"Farming",
            "subcategory":"Livestock Farm",
            "type":"Manufacturing & Wholesale Goods"
        }
    ],
    "sg:phone":"+44 1598 763234",
    "sg:postcode":"EX31 4QW",
    "sg:province":"Devon",
    "sg:tags":[
        "others"
    ],
    "wof:name":"B C Dallyn",
    "wof:placetype":"venue"
},
  "geometry": {"coordinates":[-3.9059948921,51.1877632141],"type":"Point"}
}