{
  "type": "Feature",
  "properties": {
    "addr:full":"5 Torriano Mews London Greater London NW5 2RZ",
    "addr:housenumber":"5",
    "addr:postcode":"nw5 2rz",
    "addr:street":"Torriano Mews",
    "iso:country":"GB",
    "sg:address":"5 Torriano Mews",
    "sg:city":"London",
    "sg:classifiers":[
        {
            "category":"Professional",
            "subcategory":"Lawyer & Legal Services",
            "type":"Services"
        }
    ],
    "sg:phone":"+44 20 7284 0555",
    "sg:postcode":"NW5 2RZ",
    "sg:province":"Greater London",
    "sg:tags":[
        "advice",
        "counselling"
    ],
    "wof:name":"Post Adoption Centre",
    "wof:placetype":"venue"
},
  "geometry": {"coordinates":[-0.1336369962,51.5511207581],"type":"Point"}
}