{
  "type": "Feature",
  "properties": {
    "addr:full":"27 Hawbank Road, East Kilbride Glasgow South Lanarkshire G74 5EG",
    "addr:housenumber":"27",
    "addr:postcode":"g74 5eg",
    "addr:street":"Hawbank Road",
    "iso:country":"GB",
    "sg:address":"27 Hawbank Road, East Kilbride",
    "sg:city":"Glasgow",
    "sg:classifiers":[
        {
            "category":"Food & Beverages",
            "subcategory":"Supermarket",
            "type":"Retail Goods"
        }
    ],
    "sg:postcode":"G74 5EG",
    "sg:province":"South Lanarkshire",
    "sg:tags":[
        "frozen"
    ],
    "wof:name":"Wellhall Bakery",
    "wof:placetype":"venue"
},
  "geometry": {"coordinates":[-4.212195,55.772545],"type":"Point"}
}