{
  "type": "Feature",
  "properties": {
    "addr:full":"Pentre Morgan Farm, St Martins Oswestry Shropshire SY11 3HG",
    "addr:postcode":"sy11 3hg",
    "addr:street":"Farm St Martins",
    "iso:country":"GB",
    "sg:address":"Pentre Morgan Farm, St Martins",
    "sg:city":"Oswestry",
    "sg:classifiers":[
        {
            "category":"Farming",
            "subcategory":"Livestock Farm",
            "type":"Manufacturing & Wholesale Goods"
        }
    ],
    "sg:postcode":"SY11 3HG",
    "sg:province":"Shropshire",
    "sg:tags":[
        "others"
    ],
    "wof:name":"G L  Arthan",
    "wof:placetype":"venue"
},
  "geometry": {"coordinates":[-3.048089,52.863602],"type":"Point"}
}