{
  "type": "Feature",
  "properties": {
    "addr:full":"252 Londonderry Lane Smethwick West Midlands B67 7EN",
    "addr:housenumber":"252",
    "addr:postcode":"b67 7en",
    "addr:street":"Londonderry Lane",
    "iso:country":"GB",
    "sg:address":"252 Londonderry Lane",
    "sg:city":"Smethwick",
    "sg:classifiers":[
        {
            "category":"Food & Beverages",
            "subcategory":"Supermarket",
            "type":"Retail Goods"
        }
    ],
    "sg:phone":"+44 121 565 1360",
    "sg:postcode":"B67 7EN",
    "sg:province":"West Midlands",
    "wof:name":"Costcutter",
    "wof:placetype":"venue"
},
  "geometry": {"coordinates":[-1.9865779877,52.4887008667],"type":"Point"}
}