{
  "type": "Feature",
  "properties": {
    "addr:full":"42 St Catherines Road Bournemouth Dorset BH6 4AD",
    "addr:housenumber":"42",
    "addr:postcode":"bh6 4ad",
    "addr:street":"St Catherines Road",
    "iso:country":"GB",
    "sg:address":"42 St Catherines Road",
    "sg:city":"Bournemouth",
    "sg:classifiers":[
        {
            "category":"Social Services",
            "subcategory":"Retirement Home",
            "type":"Services"
        }
    ],
    "sg:phone":"+44 1202 429514",
    "sg:postcode":"BH6 4AD",
    "sg:province":"Dorset",
    "sg:tags":[
        "rest"
    ],
    "wof:name":"Primrose Lodge Rest Home",
    "wof:placetype":"venue"
},
  "geometry": {"coordinates":[-1.7935860157,50.7229766846],"type":"Point"}
}