{
  "type": "Feature",
  "properties": {
    "addr:full":"103 Mortlake Road, Kew Richmond Greater London TW9 4AA",
    "addr:housenumber":"103",
    "addr:postcode":"tw9 4aa",
    "addr:street":"Mortlake Road",
    "iso:country":"GB",
    "sg:address":"103 Mortlake Road, Kew",
    "sg:city":"Richmond",
    "sg:classifiers":[
        {
            "category":"Health Services",
            "subcategory":"Dentist",
            "type":"Services"
        }
    ],
    "sg:phone":"+44 20 8876 4542",
    "sg:postcode":"TW9 4AA",
    "sg:province":"Greater London",
    "wof:name":"Aesthetic Dentistry",
    "wof:placetype":"venue"
},
  "geometry": {"coordinates":[-0.281325,51.478397],"type":"Point"}
}