{
  "type": "Feature",
  "properties": {
    "iso:country":"GB",
    "sg:address":"Unit 1, 58 High Street",
    "sg:city":"Rushden",
    "sg:classifiers":[
        {
            "category":"Travel",
            "subcategory":"Travel Agent",
            "type":"Entertainment"
        }
    ],
    "sg:phone":"+44 1933 411752",
    "sg:postcode":"NN10 0PJ",
    "sg:province":"Bedfordshire",
    "sg:tags":[
        "agency",
        "activity"
    ],
    "wof:name":"LUNN POLY LTD",
    "wof:placetype":"venue"
},
  "geometry": {"coordinates":[-0.596151,52.286102],"type":"Point"}
}