{
  "type": "Feature",
  "properties": {
    "addr:full":"3 The Precinct, London Road Waterlooville Hampshire PO7 7DT",
    "addr:housenumber":"3",
    "addr:postcode":"po7 7dt",
    "addr:street":"The Precinct London Road",
    "iso:country":"GB",
    "sg:address":"3 The Precinct, London Road",
    "sg:city":"Waterlooville",
    "sg:classifiers":[
        {
            "category":"Shopping",
            "subcategory":"News",
            "type":"Retail Goods"
        }
    ],
    "sg:phone":"+44 23 9226 4234",
    "sg:postcode":"PO7 7DT",
    "sg:province":"Hampshire",
    "sg:tags":[
        "newsagent"
    ],
    "wof:name":"Forbuoys",
    "wof:placetype":"venue"
},
  "geometry": {"coordinates":[-1.03561,50.877151],"type":"Point"}
}