{
  "type": "Feature",
  "properties": {
    "addr:full":"Bishops Lane Robertsbridge East Sussex TN32 5EB",
    "addr:postcode":"tn32 5eb",
    "addr:street":"Bishops Lane",
    "iso:country":"GB",
    "sg:address":"Bishops Lane",
    "sg:city":"Robertsbridge",
    "sg:classifiers":[
        {
            "category":"Health Services",
            "subcategory":"Nursing And Care Facility",
            "type":"Services"
        }
    ],
    "sg:phone":"+44 1580 880212",
    "sg:postcode":"TN32 5EB",
    "sg:province":"East Sussex",
    "sg:tags":[
        "home"
    ],
    "wof:name":"Glottenham Manor",
    "wof:placetype":"venue"
},
  "geometry": {"coordinates":[0.4726719856,50.9821166992],"type":"Point"}
}