{
  "type": "Feature",
  "properties": {
    "iso:country":"GB",
    "sg:address":"5 Lugley Street",
    "sg:city":"Newport",
    "sg:classifiers":[
        {
            "category":"Shopping",
            "subcategory":"Crafts & Fabrics",
            "type":"Retail Goods"
        }
    ],
    "sg:phone":"+44 1983 526104",
    "sg:postcode":"PO30 5HG",
    "sg:province":"Isle of Wight",
    "sg:tags":[
        "shop"
    ],
    "wof:name":"Hellerslea",
    "wof:placetype":"venue"
},
  "geometry": {"coordinates":[-1.2943120003,50.7007446289],"type":"Point"}
}