{
  "type": "Feature",
  "properties": {
    "iso:country":"GB",
    "sg:address":"180d Cheltenham Road",
    "sg:city":"Bristol",
    "sg:classifiers":[
        {
            "category":"Building & Trades",
            "subcategory":"Construction",
            "type":"Services"
        }
    ],
    "sg:phone":"+44 117 914 4385",
    "sg:postcode":"BS6 5RB",
    "sg:province":"City of Bristol",
    "sg:tags":[
        "decorator",
        "painter"
    ],
    "wof:name":"P J P Decorations",
    "wof:placetype":"venue"
},
  "geometry": {"coordinates":[-2.591303,51.467598],"type":"Point"}
}