{
  "type": "Feature",
  "properties": {
    "addr:full":"255 Old Marylebone Road London Greater London NW1 5QT",
    "addr:housenumber":"255",
    "addr:postcode":"nw1 5qt",
    "addr:street":"Old Marylebone Road",
    "iso:country":"GB",
    "sg:address":"255 Old Marylebone Road",
    "sg:city":"London",
    "sg:classifiers":[
        {
            "category":"Organizations",
            "subcategory":"Non-profit Organization",
            "type":"Services"
        }
    ],
    "sg:phone":"+44 20 7723 7544",
    "sg:postcode":"NW1 5QT",
    "sg:province":"Greater London",
    "sg:tags":[
        "organisation",
        "voluntary",
        "charity"
    ],
    "wof:name":"New to London Project",
    "wof:placetype":"venue"
},
  "geometry": {"coordinates":[-0.166699,51.518517],"type":"Point"}
}