{
  "type": "Feature",
  "properties": {
    "addr:full":"Leonard Fairclough House Chorley Lancashire PR7 4LB",
    "addr:postcode":"pr7 4lb",
    "addr:street":"Leonard",
    "iso:country":"GB",
    "sg:address":"Leonard Fairclough House",
    "sg:city":"Chorley",
    "sg:classifiers":[
        {
            "category":"Building & Trades",
            "subcategory":"Construction",
            "type":"Services"
        }
    ],
    "sg:phone":"+44 1257 484400",
    "sg:postcode":"PR7 4LB",
    "sg:province":"Lancashire",
    "sg:tags":[
        "contractor"
    ],
    "wof:name":"Amec Capital Projects Ltd.",
    "wof:placetype":"venue"
},
  "geometry": {"coordinates":[-2.623258,53.625481],"type":"Point"}
}