{
  "type": "Feature",
  "properties": {
    "addr:full":"19 Bargate Drive Wolverhampton Shropshire WV6 0QW",
    "addr:housenumber":"19",
    "addr:postcode":"wv6 0qw",
    "addr:street":"Bargate Drive",
    "iso:country":"GB",
    "sg:address":"19 Bargate Drive",
    "sg:city":"Wolverhampton",
    "sg:classifiers":[
        {
            "category":"Shopping",
            "subcategory":"Discount & Variety Stores",
            "type":"Retail Goods"
        }
    ],
    "sg:phone":"+44 1902 714534",
    "sg:postcode":"WV6 0QW",
    "sg:province":"Shropshire",
    "sg:tags":[
        "centre"
    ],
    "wof:name":"Steve's Discount",
    "wof:placetype":"venue"
},
  "geometry": {"coordinates":[-2.142331,52.594124],"type":"Point"}
}