{
  "type": "Feature",
  "properties": {
    "iso:country":"GB",
    "sg:address":"Tanners Bank, Fish Quay",
    "sg:city":"North Shields",
    "sg:classifiers":[
        {
            "category":"Food & Beverages",
            "subcategory":"Meat & Fish",
            "type":"Retail Goods"
        }
    ],
    "sg:phone":"+44 191 257 1838",
    "sg:postcode":"NE30 1JH",
    "sg:province":"Tyne and Wear",
    "sg:tags":[
        "merchant"
    ],
    "wof:name":"Wright & Eddie (Exporters & Importers) Ltd.",
    "wof:placetype":"venue"
},
  "geometry": {"coordinates":[-1.433444,55.011154],"type":"Point"}
}