{
  "type": "Feature",
  "properties": {
    "addr:full":"17 Delph Road Industrial Estate, Delph Road Brierley Hill West Midlands DY5 2UA",
    "addr:housenumber":"17",
    "addr:postcode":"estate;dy5 2ua",
    "addr:street":"Delph Road Industrial;Delph Road",
    "iso:country":"GB",
    "sg:address":"17 Delph Road Industrial Estate, Delph Road",
    "sg:city":"Brierley Hill",
    "sg:classifiers":[
        {
            "category":"Home & Garden",
            "subcategory":"Building Materials",
            "type":"Retail Goods"
        }
    ],
    "sg:postcode":"DY5 2UA",
    "sg:province":"West Midlands",
    "sg:tags":[
        "garage",
        "door"
    ],
    "wof:name":"Central Garage Doors Ltd.",
    "wof:placetype":"venue"
},
  "geometry": {"coordinates":[-2.1209731102,52.470954895],"type":"Point"}
}