{
  "type": "Feature",
  "properties": {
    "addr:full":"13 Lewisham Way London Greater London SE14 6PP",
    "addr:housenumber":"13",
    "addr:postcode":"se14 6pp",
    "addr:street":"Lewisham Way",
    "iso:country":"GB",
    "sg:address":"13 Lewisham Way",
    "sg:city":"London",
    "sg:classifiers":[
        {
            "category":"Fast Food",
            "type":"Food & Drink"
        }
    ],
    "sg:postcode":"SE14 6PP",
    "sg:province":"Greater London",
    "sg:tags":[
        "away",
        "take"
    ],
    "wof:name":"Chinese Healthy Take Away",
    "wof:placetype":"venue"
},
  "geometry": {"coordinates":[-0.035574,51.475391],"type":"Point"}
}