{
  "type": "Feature",
  "properties": {
    "addr:full":"White Lodge, Tadworth Street Tadworth Surrey KT20 5RE",
    "addr:postcode":"kt20 5re",
    "addr:street":"Tadworth Street",
    "iso:country":"GB",
    "sg:address":"White Lodge, Tadworth Street",
    "sg:city":"Tadworth",
    "sg:classifiers":[
        {
            "category":"Banks & Credit Unions",
            "subcategory":"Investment Brokerage",
            "type":"Services"
        },
        {
            "category":"Building & Trades",
            "subcategory":"Equipment Rental",
            "type":"Services"
        }
    ],
    "sg:phone":"+44 1737 812218",
    "sg:postcode":"KT20 5RE",
    "sg:province":"Surrey",
    "sg:tags":[
        "engraving",
        "marking",
        "identification",
        "id"
    ],
    "sg:website":"http://www.ketchums.co.uk",
    "wof:name":"Ketchum Manufacturing Co",
    "wof:placetype":"venue"
},
  "geometry": {"coordinates":[-0.2351489961,51.2915382385],"type":"Point"}
}