{
  "type": "Feature",
  "properties": {
    "iso:country":"GB",
    "sg:address":"Archway Tavern, Archway Close, Archway Road",
    "sg:city":"London",
    "sg:classifiers":[
        {
            "category":"Bars & Pubs",
            "type":"Food & Drink"
        },
        {
            "category":"Community Center",
            "subcategory":"Social",
            "type":"Public Place"
        }
    ],
    "sg:phone":"+44 20 7272 2840",
    "sg:postcode":"N19 3TD",
    "sg:province":"Greater London",
    "sg:tags":[
        "pubs",
        "house",
        "inn",
        "activity"
    ],
    "wof:name":"The Archway Tavern",
    "wof:placetype":"venue"
},
  "geometry": {"coordinates":[-0.1345700026,51.5660514832],"type":"Point"}
}