{
  "type": "Feature",
  "properties": {
    "iso:country":"GB",
    "sg:address":"Frome Road",
    "sg:city":"Trowbridge",
    "sg:classifiers":[
        {
            "category":"Autos & Motor Vehicles",
            "subcategory":"Automobile Sales",
            "type":"Retail Goods"
        },
        {
            "category":"Shopping",
            "subcategory":"Pharmacy",
            "type":"Retail Goods"
        },
        {
            "category":"Retail",
            "subcategory":"Auto Repair",
            "type":"Services"
        }
    ],
    "sg:phone":"+44 1225 752019",
    "sg:postcode":"BA14 0DH",
    "sg:province":"Wiltshire",
    "sg:tags":[
        "modification",
        "car",
        "pharmacist",
        "chemist",
        "garage"
    ],
    "wof:name":"F Sleightholme & Sons Ltd.",
    "wof:placetype":"venue"
},
  "geometry": {"coordinates":[-2.2137289047,51.3141212463],"type":"Point"}
}