{
  "type": "Feature",
  "properties": {
    "addr:full":"899 Old Kent Road London Greater London SE15 1NL",
    "addr:housenumber":"899",
    "addr:postcode":"se15 1nl",
    "addr:street":"Old Kent Road",
    "iso:country":"GB",
    "sg:address":"899 Old Kent Road",
    "sg:city":"London",
    "sg:classifiers":[
        {
            "category":"Cafe",
            "type":"Food & Drink"
        }
    ],
    "sg:phone":"+44 20 7358 0605",
    "sg:postcode":"SE15 1NL",
    "sg:province":"Greater London",
    "sg:tags":[
        "tea",
        "room"
    ],
    "wof:name":"Dave's Cafe",
    "wof:placetype":"venue"
},
  "geometry": {"coordinates":[-0.054454,51.478855],"type":"Point"}
}