{
  "type": "Feature",
  "properties": {
    "addr:full":"Bellais Street Stafford Staffordshire ST16 3DD",
    "addr:postcode":"st16 3dd",
    "addr:street":"Bellais Street",
    "iso:country":"GB",
    "sg:address":"Bellais Street",
    "sg:city":"Stafford",
    "sg:classifiers":[
        {
            "category":"Manufacturing",
            "subcategory":"Building Materials",
            "type":"Manufacturing & Wholesale Goods"
        }
    ],
    "sg:phone":"+44 1785 228081",
    "sg:postcode":"ST16 3DD",
    "sg:province":"Staffordshire",
    "sg:tags":[
        "shutter",
        "supp",
        "door"
    ],
    "wof:name":"Briton Shutters & Grilles",
    "wof:placetype":"venue"
},
  "geometry": {"coordinates":[-2.1089351177,52.8151168823],"type":"Point"}
}