{
  "type": "Feature",
  "properties": {
    "iso:country":"GB",
    "sg:address":"4 Middleton Gate, Guildford Business Park",
    "sg:city":"Guildford",
    "sg:classifiers":[
        {
            "category":"Utilities",
            "subcategory":"Telephone",
            "type":"Services"
        }
    ],
    "sg:phone":"+44 1483 303666",
    "sg:postcode":"GU2 8SG",
    "sg:province":"Surrey",
    "sg:tags":[
        "telecommunication"
    ],
    "wof:name":"Ericsson Ltd.",
    "wof:placetype":"venue"
},
  "geometry": {"coordinates":[-0.587156,51.246056],"type":"Point"}
}