{
  "type": "Feature",
  "properties": {
    "iso:country":"GB",
    "sg:address":"Queen St",
    "sg:city":"Bury",
    "sg:classifiers":[
        {
            "category":"Professional",
            "subcategory":"Engineering",
            "type":"Services"
        }
    ],
    "sg:postcode":"BL9 7BG",
    "sg:province":"Lancashire",
    "sg:tags":[
        "precision",
        "engineer"
    ],
    "wof:name":"Hussain,Gohar,",
    "wof:placetype":"venue"
},
  "geometry": {"coordinates":[-2.2856600285,53.5935554504],"type":"Point"}
}