{
  "type": "Feature",
  "properties": {
    "iso:country":"GB",
    "sg:address":"Eagle La",
    "sg:city":"Tipton",
    "sg:classifiers":[
        {
            "category":"Wholesale",
            "subcategory":"Scrap",
            "type":"Manufacturing & Wholesale Goods"
        }
    ],
    "sg:phone":"+44 121 557 4983",
    "sg:postcode":"DY4 0JE",
    "sg:province":"West Midlands",
    "sg:tags":[
        "breaker",
        "dismantlers"
    ],
    "wof:name":"Mainline Vehicle Dismantlers Ltd",
    "wof:placetype":"venue"
},
  "geometry": {"coordinates":[-2.034899,52.534115],"type":"Point"}
}