{
  "type": "Feature",
  "properties": {
    "addr:full":"Chwaen Wen Isaf, Llantrisant Holyhead Isle of Anglesey LL65 4TF",
    "addr:postcode":"ll65 4tf",
    "addr:street":"Chwaen Wen Isaf",
    "iso:country":"GB",
    "sg:address":"Chwaen Wen Isaf, Llantrisant",
    "sg:city":"Holyhead",
    "sg:classifiers":[
        {
            "category":"Farming",
            "subcategory":"Crops",
            "type":"Manufacturing & Wholesale Goods"
        },
        {
            "category":"Farming",
            "subcategory":"Livestock Farm",
            "type":"Manufacturing & Wholesale Goods"
        },
        {
            "category":"Farming",
            "subcategory":"Farm",
            "type":"Manufacturing & Wholesale Goods"
        }
    ],
    "sg:phone":"+44 1248 470332",
    "sg:postcode":"LL65 4TF",
    "sg:province":"Isle of Anglesey",
    "sg:tags":[
        "mixed",
        "arable",
        "others"
    ],
    "wof:name":"Emir Richard Thomas",
    "wof:placetype":"venue"
},
  "geometry": {"coordinates":[-4.487339,53.272137],"type":"Point"}
}