{
  "type": "Feature",
  "properties": {
    "iso:country":"GB",
    "sg:address":"Unit 7, Westland Court",
    "sg:city":"Leeds",
    "sg:classifiers":[
        {
            "category":"Taxi",
            "type":"Transportation"
        }
    ],
    "sg:phone":"+44 113 277 2244",
    "sg:postcode":"LS11 5ST",
    "sg:province":"West Yorkshire",
    "sg:tags":[
        "mini",
        "cab"
    ],
    "wof:name":"Direct Cars",
    "wof:placetype":"venue"
},
  "geometry": {"coordinates":[-1.550754,53.764977],"type":"Point"}
}