{
  "type": "Feature",
  "properties": {
    "iso:country":"GB",
    "sg:address":"143 Broad Lane",
    "sg:city":"London",
    "sg:classifiers":[
        {
            "category":"Shopping",
            "subcategory":"Clothing, Apparel, & Fashions",
            "type":"Retail Goods"
        }
    ],
    "sg:phone":"+44 20 8365 1080",
    "sg:postcode":"N15 4QX",
    "sg:province":"Greater London",
    "sg:tags":[
        "clothing",
        "fabric"
    ],
    "wof:name":"Vural Ltd.",
    "wof:placetype":"venue"
},
  "geometry": {"coordinates":[-0.0640840009,51.5860099792],"type":"Point"}
}