{
  "type": "Feature",
  "properties": {
    "addr:full":"176 Sutcliffe Avenue Grimsby Lincolnshire DN33 1HA",
    "addr:housenumber":"176",
    "addr:postcode":"dn33 1ha",
    "addr:street":"Sutcliffe Avenue",
    "iso:country":"GB",
    "sg:address":"176 Sutcliffe Avenue",
    "sg:city":"Grimsby",
    "sg:classifiers":[
        {
            "category":"Personal",
            "subcategory":"Beauty Salon",
            "type":"Services"
        }
    ],
    "sg:phone":"+44 1472 877732",
    "sg:postcode":"DN33 1HA",
    "sg:province":"Lincolnshire",
    "sg:tags":[
        "unisex",
        "hairdresser"
    ],
    "wof:name":"Jean Johnson Hairdressers",
    "wof:placetype":"venue"
},
  "geometry": {"coordinates":[-0.1079559997,53.548412323],"type":"Point"}
}