{
  "type": "Feature",
  "properties": {
    "addr:full":"74 Leigh Road Leigh Lancashire WN7 1SL",
    "addr:housenumber":"74",
    "addr:postcode":"wn7 1sl",
    "addr:street":"Leigh Road Leigh",
    "iso:country":"GB",
    "sg:address":"74 Leigh Road",
    "sg:city":"Leigh",
    "sg:classifiers":[
        {
            "category":"Shopping",
            "type":"Retail Goods"
        }
    ],
    "sg:phone":"+44 1942 262698",
    "sg:postcode":"WN7 1SL",
    "sg:province":"Lancashire",
    "sg:tags":[
        "part",
        "accessory"
    ],
    "wof:name":"Master Auto Parts Ltd.",
    "wof:placetype":"venue"
},
  "geometry": {"coordinates":[-2.51801,53.502151],"type":"Point"}
}