{
  "type": "Feature",
  "properties": {
    "iso:country":"GB",
    "sg:address":"Serendib House, 67a Boston Manor Road",
    "sg:city":"Brentford",
    "sg:classifiers":[
        {
            "category":"Professional",
            "subcategory":"Management & Consulting",
            "type":"Services"
        }
    ],
    "sg:phone":"+44 20 8232 8866",
    "sg:postcode":"TW8 9JQ",
    "sg:province":"Greater London",
    "sg:tags":[
        "fire",
        "consultant",
        "protection"
    ],
    "wof:name":"Atlas Fire Engineering Ltd.",
    "wof:placetype":"venue"
},
  "geometry": {"coordinates":[-0.3148790002,51.4894256592],"type":"Point"}
}