{
  "type": "Feature",
  "properties": {
    "addr:full":"7 Gordonbrock Rd, Brockley Brockley Greater London SE4 1JA",
    "addr:housenumber":"7",
    "addr:postcode":"se4 1ja",
    "addr:street":"Gordonbrock Rd",
    "iso:country":"GB",
    "sg:address":"7 Gordonbrock Rd, Brockley",
    "sg:city":"Brockley",
    "sg:classifiers":[
        {
            "category":"Professional",
            "subcategory":"Detective & Security Services",
            "type":"Services"
        }
    ],
    "sg:phone":"+44 20 8690 0258",
    "sg:postcode":"SE4 1JA",
    "sg:province":"Greater London",
    "sg:tags":[
        "alarm",
        "burglar",
        "system"
    ],
    "wof:name":"Adassa Security",
    "wof:placetype":"venue"
},
  "geometry": {"coordinates":[-0.0270709991,51.4559173584],"type":"Point"}
}