{
  "type": "Feature",
  "properties": {
    "addr:full":"Warrington Road, Lower Ince Wigan Lancashire WN3 4TA",
    "addr:postcode":"wn3 4ta",
    "addr:street":"Warrington Road Lower",
    "iso:country":"GB",
    "sg:address":"Warrington Road, Lower Ince",
    "sg:city":"Wigan",
    "sg:classifiers":[
        {
            "category":"Autos & Motor Vehicles",
            "subcategory":"Automobile Sales",
            "type":"Retail Goods"
        }
    ],
    "sg:phone":"+44 1942 745745",
    "sg:postcode":"WN3 4TA",
    "sg:province":"Lancashire",
    "sg:tags":[
        "car"
    ],
    "wof:name":"Ron Hodgson Specialist Cars",
    "wof:placetype":"venue"
},
  "geometry": {"coordinates":[-2.620994,53.538635],"type":"Point"}
}