{
  "type": "Feature",
  "properties": {
    "iso:country":"GB",
    "sg:address":"Unit 19 Evans Street",
    "sg:city":"Ashton-under-lyne",
    "sg:classifiers":[
        {
            "category":"Retail",
            "subcategory":"Repair Shop",
            "type":"Services"
        }
    ],
    "sg:phone":"+44 161 339 1806",
    "sg:postcode":"OL6 9QD",
    "sg:province":"Greater Manchester",
    "sg:tags":[
        "upholstering",
        "upholsterer"
    ],
    "wof:name":"New Image",
    "wof:placetype":"venue"
},
  "geometry": {"coordinates":[-2.081714,53.494934],"type":"Point"}
}