{
  "type": "Feature",
  "properties": {
    "addr:full":"2-4 Fitzilian Avenue, Harold Wood Romford Essex RM3 0QS",
    "addr:housenumber":"2-4",
    "addr:postcode":"rm3 0qs",
    "addr:street":"Fitzilian Avenue",
    "iso:country":"GB",
    "sg:address":"2-4 Fitzilian Avenue, Harold Wood",
    "sg:city":"Romford",
    "sg:classifiers":[
        {
            "category":"Professional",
            "subcategory":"Testing Lab",
            "type":"Services"
        }
    ],
    "sg:phone":"+44 1708 342810",
    "sg:postcode":"RM3 0QS",
    "sg:province":"Essex",
    "sg:tags":[
        "mot"
    ],
    "wof:name":"Mercury Service Station (Harold Wood) Ltd.",
    "wof:placetype":"venue"
},
  "geometry": {"coordinates":[0.2346740067,51.5927391052],"type":"Point"}
}