{
  "type": "Feature",
  "properties": {
    "addr:full":"42 Edinburgh Road, Wingerworth Chesterfield Derbyshire S42 6SQ",
    "addr:housenumber":"42",
    "addr:postcode":"s42 6sq",
    "addr:street":"Edinburgh Road",
    "iso:country":"GB",
    "sg:address":"42 Edinburgh Road, Wingerworth",
    "sg:city":"Chesterfield",
    "sg:classifiers":[
        {
            "category":"Professional",
            "subcategory":"Accounting & Tax Preparation",
            "type":"Services"
        }
    ],
    "sg:phone":"+44 1246 279059",
    "sg:postcode":"S42 6SQ",
    "sg:province":"Derbyshire",
    "sg:tags":[
        "accountant"
    ],
    "wof:name":"P J Taylor & Co",
    "wof:placetype":"venue"
},
  "geometry": {"coordinates":[-1.443708,53.207764],"type":"Point"}
}