{
  "type": "Feature",
  "properties": {
    "iso:country":"GB",
    "sg:address":"Shafers Tarpots Corner, 316 London Road",
    "sg:city":"Benfleet",
    "sg:classifiers":[
        {
            "category":"Personal",
            "subcategory":"Tattoo Parlor",
            "type":"Services"
        }
    ],
    "sg:phone":"+44 1268 416324",
    "sg:postcode":"SS7 5XR",
    "sg:province":"Essex",
    "sg:tags":[
        "tattooing",
        "piercing"
    ],
    "wof:name":"Tattooing by Mark Pettigrew",
    "wof:placetype":"venue"
},
  "geometry": {"coordinates":[0.55067,51.561779],"type":"Point"}
}