{
  "type": "Feature",
  "properties": {
    "addr:full":"136 Norwich Road Wymondham Norfolk NR18 0SX",
    "addr:housenumber":"136",
    "addr:postcode":"nr18 0sx",
    "addr:street":"Norwich Road",
    "iso:country":"GB",
    "sg:address":"136 Norwich Road",
    "sg:city":"Wymondham",
    "sg:classifiers":[
        {
            "category":"Health Services",
            "subcategory":"Nursing And Care Facility",
            "type":"Services"
        }
    ],
    "sg:phone":"+44 1953 600900",
    "sg:postcode":"NR18 0SX",
    "sg:province":"Norfolk",
    "sg:tags":[
        "home"
    ],
    "sg:website":"http://www.eachltd.co.uk",
    "wof:name":"Sutherlands",
    "wof:placetype":"venue"
},
  "geometry": {"coordinates":[1.154219985,52.587020874],"type":"Point"}
}