{
  "type": "Feature",
  "properties": {
    "iso:country":"GB",
    "sg:address":"St Marys Gate",
    "sg:city":"Chesterfield",
    "sg:classifiers":[
        {
            "category":"Place Of Worship",
            "type":"Public Place"
        }
    ],
    "sg:phone":"+44 1246 206506",
    "sg:postcode":"S41 7TJ",
    "sg:province":"Derbyshire",
    "wof:name":"St Mary & All Saints Parish Church",
    "wof:placetype":"venue"
},
  "geometry": {"coordinates":[-1.424349,53.235062],"type":"Point"}
}