{
  "type": "Feature",
  "properties": {
    "addr:full":"Nottingham Road, Codnor Ripley Derbyshire DE5 9RH",
    "addr:postcode":"de5 9rh",
    "addr:street":"Nottingham Road",
    "iso:country":"GB",
    "sg:address":"Nottingham Road, Codnor",
    "sg:city":"Ripley",
    "sg:classifiers":[
        {
            "category":"Bars & Pubs",
            "type":"Food & Drink"
        }
    ],
    "sg:phone":"+44 1773 742776",
    "sg:postcode":"DE5 9RH",
    "sg:province":"Derbyshire",
    "sg:tags":[
        "pubs",
        "inn"
    ],
    "wof:name":"The French Horn",
    "wof:placetype":"venue"
},
  "geometry": {"coordinates":[-1.373074,53.040424],"type":"Point"}
}