{
  "type": "Feature",
  "properties": {
    "addr:full":"2 Seldown Lane Poole Dorset BH15 1UF",
    "addr:housenumber":"2",
    "addr:postcode":"bh15 1uf",
    "addr:street":"Seldown Lane",
    "iso:country":"GB",
    "sg:address":"2 Seldown Lane",
    "sg:city":"Poole",
    "sg:classifiers":[
        {
            "category":"Arts & Performance",
            "subcategory":"Music",
            "type":"Entertainment"
        },
        {
            "category":"Arts & Performance",
            "subcategory":"Theater",
            "type":"Entertainment"
        }
    ],
    "sg:phone":"+44 1202 670611",
    "sg:postcode":"BH15 1UF",
    "sg:province":"Dorset",
    "sg:tags":[
        "musician",
        "orchestra",
        "composer"
    ],
    "wof:name":"Bournemouth Symphony Orchestra Ltd",
    "wof:placetype":"venue"
},
  "geometry": {"coordinates":[-1.977633,50.718807],"type":"Point"}
}