{
  "type": "Feature",
  "properties": {
    "addr:full":"16 Delenty Drive, Birchwood Warrington Cheshire WA3 6AP",
    "addr:housenumber":"16",
    "addr:postcode":"wa3 6ap",
    "addr:street":"Delenty Drive",
    "iso:country":"GB",
    "sg:address":"16 Delenty Drive, Birchwood",
    "sg:city":"Warrington",
    "sg:classifiers":[
        {
            "category":"Retail",
            "subcategory":"Repair Shop",
            "type":"Services"
        }
    ],
    "sg:postcode":"WA3 6AP",
    "sg:province":"Cheshire",
    "sg:tags":[
        "maintenance"
    ],
    "wof:name":"Heathfield Construction",
    "wof:placetype":"venue"
},
  "geometry": {"coordinates":[-2.527463,53.423679],"type":"Point"}
}