{
  "type": "Feature",
  "properties": {
    "iso:country":"GB",
    "sg:address":"Padden Brook, Romiley",
    "sg:city":"Stockport",
    "sg:classifiers":[
        {
            "category":"Wholesale",
            "subcategory":"Sporting Goods",
            "type":"Manufacturing & Wholesale Goods"
        }
    ],
    "sg:phone":"+44 161 430 6788",
    "sg:postcode":"SK6 3AW",
    "sg:province":"Cheshire",
    "sg:tags":[
        "mnfr",
        "sport",
        "equipment"
    ],
    "wof:name":"Zsig Sports Ltd.",
    "wof:placetype":"venue"
},
  "geometry": {"coordinates":[-2.091184,53.413841],"type":"Point"}
}