{
  "type": "Feature",
  "properties": {
    "addr:full":"72 New Bond St West End Hampshire W1Y 9DD",
    "addr:housenumber":"72",
    "addr:postcode":"w1y 9dd",
    "addr:street":"New Bond St",
    "iso:country":"GB",
    "sg:address":"72 New Bond St",
    "sg:city":"West End",
    "sg:classifiers":[
        {
            "category":"Bus Charters",
            "type":"Transportation"
        }
    ],
    "sg:phone":"+44 870 902 0908",
    "sg:postcode":"W1Y 9DD",
    "sg:province":"Hampshire",
    "sg:tags":[
        "hire",
        "coach"
    ],
    "wof:name":"Astral Travels",
    "wof:placetype":"venue"
},
  "geometry": {"coordinates":[-0.145802,51.513821],"type":"Point"}
}