{
  "type": "Feature",
  "properties": {
    "addr:full":"19-28 Wilton Rd Westminster Greater London SW1V 1LW",
    "addr:housenumber":"19-28",
    "addr:postcode":"sw1v 1lw",
    "addr:street":"Wilton Rd",
    "iso:country":"GB",
    "sg:address":"19-28 Wilton Rd",
    "sg:city":"Westminster",
    "sg:classifiers":[
        {
            "category":"Organizations",
            "subcategory":"Membership Organization",
            "type":"Services"
        }
    ],
    "sg:phone":"+44 20 7233 7268",
    "sg:postcode":"SW1V 1LW",
    "sg:province":"Greater London",
    "sg:tags":[
        "club"
    ],
    "wof:name":"A R P London Desk",
    "wof:placetype":"venue"
},
  "geometry": {"coordinates":[-0.1426589936,51.4950408936],"type":"Point"}
}