{
  "type": "Feature",
  "properties": {
    "addr:full":"Booth House Farm, Northlands Road, Winterton Scunthorpe Lincolnshire DN15 9UP",
    "addr:postcode":"dn15 9up",
    "addr:street":"Northlands Road",
    "iso:country":"GB",
    "sg:address":"Booth House Farm, Northlands Road, Winterton",
    "sg:city":"Scunthorpe",
    "sg:classifiers":[
        {
            "category":"Food & Beverages",
            "subcategory":"Fruits & Vegetables",
            "type":"Retail Goods"
        }
    ],
    "sg:postcode":"DN15 9UP",
    "sg:province":"Lincolnshire",
    "sg:tags":[
        "greengrocer"
    ],
    "wof:name":"D E & J Robinson",
    "wof:placetype":"venue"
},
  "geometry": {"coordinates":[-0.6013829708,53.6555633545],"type":"Point"}
}