{
  "type": "Feature",
  "properties": {
    "iso:country":"GB",
    "sg:address":"17 Woddville Road",
    "sg:city":"Exmouth",
    "sg:classifiers":[
        {
            "category":"Autos & Motor Vehicles",
            "subcategory":"Auto Supplies",
            "type":"Retail Goods"
        }
    ],
    "sg:phone":"+44 1395 223596",
    "sg:postcode":"EX8 1SE",
    "sg:province":"Devon",
    "sg:tags":[
        "towing",
        "eqpt",
        "trailer"
    ],
    "wof:name":"D Price",
    "wof:placetype":"venue"
},
  "geometry": {"coordinates":[-3.414205,50.62067],"type":"Point"}
}