{
  "type": "Feature",
  "properties": {
    "iso:country":"GB",
    "sg:address":"5a Lincoln Road, Welton",
    "sg:city":"Lincoln",
    "sg:classifiers":[
        {
            "category":"Shopping",
            "subcategory":"News",
            "type":"Retail Goods"
        }
    ],
    "sg:phone":"+44 1673 860963",
    "sg:postcode":"LN2 3HZ",
    "sg:province":"Lincolnshire",
    "sg:tags":[
        "newsagent"
    ],
    "wof:name":"The Welton Paper Shop",
    "wof:placetype":"venue"
},
  "geometry": {"coordinates":[-0.4670009911,53.3002510071],"type":"Point"}
}