{
  "type": "Feature",
  "properties": {
    "iso:country":"GB",
    "sg:address":"37 Lonsdale Street",
    "sg:city":"Carlisle",
    "sg:classifiers":[
        {
            "category":"Organizations",
            "subcategory":"Professional Association",
            "type":"Services"
        }
    ],
    "sg:phone":"+44 1228 607421",
    "sg:postcode":"CA1 1BJ",
    "sg:province":"Cumbria",
    "sg:tags":[
        "union",
        "trade"
    ],
    "wof:name":"Unison",
    "wof:placetype":"venue"
},
  "geometry": {"coordinates":[-2.930643,54.894321],"type":"Point"}
}