{
  "type": "Feature",
  "properties": {
    "addr:full":"2-3 Northbrook Street Newbury Berkshire RG14 1DJ",
    "addr:housenumber":"2-3",
    "addr:postcode":"rg14 1dj",
    "addr:street":"Northbrook Street",
    "iso:country":"GB",
    "sg:address":"2-3 Northbrook Street",
    "sg:city":"Newbury",
    "sg:classifiers":[
        {
            "category":"Shopping",
            "subcategory":"Clothing, Apparel, & Fashions",
            "type":"Retail Goods"
        }
    ],
    "sg:phone":"+44 1635 36469",
    "sg:postcode":"RG14 1DJ",
    "sg:province":"Berkshire",
    "sg:tags":[
        "lady",
        "fashionwear",
        "ladieswear"
    ],
    "wof:name":"Dorothy Perkins",
    "wof:placetype":"venue"
},
  "geometry": {"coordinates":[-1.324097991,51.4021606445],"type":"Point"}
}