{
  "type": "Feature",
  "properties": {
    "iso:country":"GB",
    "sg:address":"1e Links Way, Off Links Road",
    "sg:city":"London",
    "sg:classifiers":[
        {
            "category":"Professional",
            "subcategory":"Engineering",
            "type":"Services"
        }
    ],
    "sg:phone":"+44 20 8672 9091",
    "sg:postcode":"SW17 9ED",
    "sg:province":"Greater London",
    "wof:name":"Kaz Engineering",
    "wof:placetype":"venue"
},
  "geometry": {"coordinates":[-0.161359,51.420319],"type":"Point"}
}