{
  "type": "Feature",
  "properties": {
    "addr:full":"8 Grove Farm, Crookham Fleet Hampshire GU51 5SD",
    "addr:housenumber":"8",
    "addr:postcode":"gu51 5sd",
    "addr:street":"Grove Farm Crookham",
    "iso:country":"GB",
    "sg:address":"8 Grove Farm, Crookham",
    "sg:city":"Fleet",
    "sg:classifiers":[
        {
            "category":"Home & Garden",
            "subcategory":"Hardware",
            "type":"Retail Goods"
        }
    ],
    "sg:phone":"+44 1252 621701",
    "sg:postcode":"GU51 5SD",
    "sg:province":"Hampshire",
    "sg:tags":[
        "paint",
        "coating"
    ],
    "wof:name":"Spray Art Ltd.",
    "wof:placetype":"venue"
},
  "geometry": {"coordinates":[-0.86458,51.26606],"type":"Point"}
}