{
  "type": "Feature",
  "properties": {
    "iso:country":"GB",
    "sg:address":"65 Edmunds Road",
    "sg:city":"Banbury",
    "sg:classifiers":[
        {
            "category":"Manufacturing",
            "subcategory":"Metals",
            "type":"Manufacturing & Wholesale Goods"
        },
        {
            "category":"Wholesale",
            "subcategory":"Metals & Minerals",
            "type":"Manufacturing & Wholesale Goods"
        }
    ],
    "sg:phone":"+44 1295 712939",
    "sg:postcode":"OX16 0QJ",
    "sg:province":"Oxfordshire",
    "sg:tags":[
        "fabricator",
        "work",
        "sheet"
    ],
    "wof:name":"Alan Newman",
    "wof:placetype":"venue"
},
  "geometry": {"coordinates":[-1.360372,52.059425],"type":"Point"}
}