{
  "type": "Feature",
  "properties": {
    "addr:full":"Cardinal Ho, 7 Wolsey Rd, Hampton Ct East Molesey Greater London KT8 9HF",
    "addr:housenumber":"7",
    "addr:postcode":"kt8 9hf",
    "addr:street":"Wolsey Rd;Ct",
    "iso:country":"GB",
    "sg:address":"Cardinal Ho, 7 Wolsey Rd, Hampton Ct",
    "sg:city":"East Molesey",
    "sg:classifiers":[
        {
            "category":"Freight",
            "type":"Transportation"
        }
    ],
    "sg:postcode":"KT8 9HF",
    "sg:province":"Greater London",
    "sg:tags":[
        "haulage",
        "road"
    ],
    "wof:name":"Kent European Transport Ltd",
    "wof:placetype":"venue"
},
  "geometry": {"coordinates":[-0.344541,51.401962],"type":"Point"}
}