{
  "type": "Feature",
  "properties": {
    "iso:country":"GB",
    "sg:address":"Bow Street",
    "sg:city":"Guisborough",
    "sg:classifiers":[
        {
            "category":"Real Estate",
            "subcategory":"Real Estate Operator",
            "type":"Services"
        }
    ],
    "sg:phone":"+44 1287 610600",
    "sg:postcode":"TS14 6PR",
    "sg:province":"North Yorkshire",
    "sg:tags":[
        "letting",
        "agent"
    ],
    "wof:name":"Bow Street Centre",
    "wof:placetype":"venue"
},
  "geometry": {"coordinates":[-1.0508129597,54.535446167],"type":"Point"}
}