{
  "type": "Feature",
  "properties": {
    "iso:country":"GB",
    "sg:address":"20 Lower Parliament Street",
    "sg:city":"Nottingham",
    "sg:classifiers":[
        {
            "category":"Home & Garden",
            "subcategory":"Hardware",
            "type":"Retail Goods"
        }
    ],
    "sg:phone":"+44 115 950 3923",
    "sg:postcode":"NG1 3DA",
    "sg:province":"Nottinghamshire",
    "sg:tags":[
        "retailer",
        "diy"
    ],
    "wof:name":"Wilkinson Hardware Stores Ltd.",
    "wof:placetype":"venue"
},
  "geometry": {"coordinates":[-1.146386,52.95517],"type":"Point"}
}