{
  "type": "Feature",
  "properties": {
    "addr:full":"169 High Street, Kings Heath Birmingham West Midlands B14 7DJ",
    "addr:housenumber":"169",
    "addr:postcode":"b14 7dj",
    "addr:street":"High Street",
    "iso:country":"GB",
    "sg:address":"169 High Street, Kings Heath",
    "sg:city":"Birmingham",
    "sg:classifiers":[
        {
            "category":"Home & Garden",
            "subcategory":"Home Furnishings",
            "type":"Retail Goods"
        },
        {
            "category":"Manufacturing",
            "subcategory":"Textiles",
            "type":"Manufacturing & Wholesale Goods"
        }
    ],
    "sg:phone":"+44 121 441 3795",
    "sg:postcode":"B14 7DJ",
    "sg:province":"West Midlands",
    "sg:tags":[
        "manufacture",
        "made-up",
        "curtain"
    ],
    "wof:name":"Samrex Textiles Ltd.",
    "wof:placetype":"venue"
},
  "geometry": {"coordinates":[-1.892959,52.432861],"type":"Point"}
}