{
  "type": "Feature",
  "properties": {
    "iso:country":"GB",
    "sg:address":"33 London Road, Thatcham",
    "sg:city":"Newbury",
    "sg:classifiers":[
        {
            "category":"Manufacturing",
            "subcategory":"Lumber",
            "type":"Manufacturing & Wholesale Goods"
        }
    ],
    "sg:postcode":"RG18 4GE",
    "sg:province":"Berkshire",
    "sg:tags":[
        "importer",
        "merchants",
        "agent",
        "timber"
    ],
    "wof:name":"Keith Willis Top Soil",
    "wof:placetype":"venue"
},
  "geometry": {"coordinates":[-1.245218,51.403465],"type":"Point"}
}