{
  "type": "Feature",
  "properties": {
    "iso:country":"GB",
    "sg:address":"91-92 Charles Henry St, Highgate",
    "sg:city":"Birmingham",
    "sg:classifiers":[
        {
            "category":"Autos & Motor Vehicles",
            "subcategory":"Automobile Sales",
            "type":"Retail Goods"
        }
    ],
    "sg:postcode":"B12 0SJ",
    "sg:province":"West Midlands",
    "sg:tags":[
        "car"
    ],
    "wof:name":"Carstock U K",
    "wof:placetype":"venue"
},
  "geometry": {"coordinates":[-1.8908940554,52.4691123962],"type":"Point"}
}