{
  "type": "Feature",
  "properties": {
    "addr:full":"14 High Street Saffron Walden Cambridgeshire CB10 1AY",
    "addr:housenumber":"14",
    "addr:postcode":"cb10 1ay",
    "addr:street":"High Street",
    "iso:country":"GB",
    "sg:address":"14 High Street",
    "sg:city":"Saffron Walden",
    "sg:classifiers":[
        {
            "category":"Home & Garden",
            "subcategory":"Furniture",
            "type":"Retail Goods"
        }
    ],
    "sg:phone":"+44 1799 528777",
    "sg:postcode":"CB10 1AY",
    "sg:province":"Cambridgeshire",
    "wof:name":"An Angel At My Table Ltd.",
    "wof:placetype":"venue"
},
  "geometry": {"coordinates":[0.238788,52.023533],"type":"Point"}
}