{
  "type": "Feature",
  "properties": {
    "addr:full":"Unit 7 Rainbow Industrial Park, Station Approach, Raynes Park London Greater London SW20 0JY",
    "addr:housenumber":"unit 7",
    "addr:postcode":"sw20 0jy",
    "addr:street":"Rainbow Industrial Park Station Approach",
    "iso:country":"GB",
    "sg:address":"Unit 7 Rainbow Industrial Park, Station Approach, Raynes Park",
    "sg:city":"London",
    "sg:classifiers":[
        {
            "category":"Autos & Motor Vehicles",
            "subcategory":"Automobile Sales",
            "type":"Retail Goods"
        },
        {
            "category":"Retail",
            "subcategory":"Auto Rental",
            "type":"Services"
        }
    ],
    "sg:phone":"+44 20 8944 9513",
    "sg:postcode":"SW20 0JY",
    "sg:province":"Greater London",
    "sg:tags":[
        "commercial",
        "hire",
        "van",
        "truck"
    ],
    "wof:name":"Central van & Truck Centre Ltd.",
    "wof:placetype":"venue"
},
  "geometry": {"coordinates":[-0.2383600026,51.404510498],"type":"Point"}
}