{
  "type": "Feature",
  "properties": {
    "addr:full":"Devonshire Square, Cartmel Grange-over-sands Cumbria LA11 6QD",
    "addr:postcode":"la11 6qd",
    "addr:street":"Devonshire Square",
    "iso:country":"GB",
    "sg:address":"Devonshire Square, Cartmel",
    "sg:city":"Grange-over-sands",
    "sg:classifiers":[
        {
            "category":"Personal",
            "subcategory":"Beauty Salon",
            "type":"Services"
        }
    ],
    "sg:phone":"+44 15395 36531",
    "sg:postcode":"LA11 6QD",
    "sg:province":"Cumbria",
    "sg:tags":[
        "ladies",
        "lady",
        "hairdresser"
    ],
    "wof:name":"Priory Salon",
    "wof:placetype":"venue"
},
  "geometry": {"coordinates":[-2.9497990608,54.1995735168],"type":"Point"}
}