{
  "type": "Feature",
  "properties": {
    "iso:country":"GB",
    "sg:address":"Oakroom House",
    "sg:city":"Harlow",
    "sg:classifiers":[
        {
            "category":"Manufacturing",
            "subcategory":"Petroleum Products",
            "type":"Manufacturing & Wholesale Goods"
        }
    ],
    "sg:phone":"+44 1279 433275",
    "sg:postcode":"CM20 2BY",
    "sg:province":"Essex",
    "sg:tags":[
        "double",
        "glazing"
    ],
    "wof:name":"Temple Windows Ltd.",
    "wof:placetype":"venue"
},
  "geometry": {"coordinates":[0.0784649998,51.7864265442],"type":"Point"}
}