{
  "type": "Feature",
  "properties": {
    "addr:full":"Building 9 Soho Mills, Soho Mills Industrial Estate, Wooburn Grn High Wycombe Buckinghamshire HP10 0PF",
    "addr:postcode":"hp10 0pf",
    "addr:street":"Soho;Soho Mills Industrial;Wooburn Grn",
    "iso:country":"GB",
    "sg:address":"Building 9 Soho Mills, Soho Mills Industrial Estate, Wooburn Grn",
    "sg:city":"High Wycombe",
    "sg:classifiers":[
        {
            "category":"Professional",
            "subcategory":"Engineering",
            "type":"Services"
        }
    ],
    "sg:phone":"+44 1628 530116",
    "sg:postcode":"HP10 0PF",
    "sg:province":"Buckinghamshire",
    "wof:name":"D D & G Engineering",
    "wof:placetype":"venue"
},
  "geometry": {"coordinates":[-0.6933100224,51.5819129944],"type":"Point"}
}