{
  "type": "Feature",
  "properties": {
    "addr:full":"Marsden House, 74a King William Street Blackburn Lancashire BB2 7DT",
    "addr:housenumber":"74a",
    "addr:postcode":"bb2 7dt",
    "addr:street":"King William Street",
    "iso:country":"GB",
    "sg:address":"Marsden House, 74a King William Street",
    "sg:city":"Blackburn",
    "sg:classifiers":[
        {
            "category":"Personal",
            "subcategory":"Beauty Salon",
            "type":"Services"
        }
    ],
    "sg:phone":"+44 1254 681143",
    "sg:postcode":"BB2 7DT",
    "sg:province":"Lancashire",
    "wof:name":"Visage Beauty Studio",
    "wof:placetype":"venue"
},
  "geometry": {"coordinates":[-2.4853570461,53.7503967285],"type":"Point"}
}