{
  "type": "Feature",
  "properties": {
    "addr:full":"Cross Keys, Withington Hereford Herefordshire HR1 3NX",
    "addr:postcode":"hr1 3nx",
    "iso:country":"GB",
    "sg:address":"Cross Keys, Withington",
    "sg:city":"Hereford",
    "sg:classifiers":[
        {
            "category":"Autos & Motor Vehicles",
            "subcategory":"Fuel & Gas Station",
            "type":"Retail Goods"
        }
    ],
    "sg:phone":"+44 1432 820683",
    "sg:postcode":"HR1 3NX",
    "sg:province":"Herefordshire",
    "sg:tags":[
        "petrol",
        "filling"
    ],
    "wof:name":"D Griffiths",
    "wof:placetype":"venue"
},
  "geometry": {"coordinates":[-2.637644,52.085419],"type":"Point"}
}