{
  "type": "Feature",
  "properties": {
    "addr:full":"Station Yard Caersws Powys SY17 5HH",
    "addr:postcode":"sy17 5hh",
    "iso:country":"GB",
    "sg:address":"Station Yard",
    "sg:city":"Caersws",
    "sg:classifiers":[
        {
            "category":"Social Services",
            "subcategory":"Job Training",
            "type":"Services"
        }
    ],
    "sg:phone":"+44 1686 688505",
    "sg:postcode":"SY17 5HH",
    "sg:province":"Powys",
    "sg:tags":[
        "engineering",
        "marine"
    ],
    "wof:name":"Divemex Ltd.",
    "wof:placetype":"venue"
},
  "geometry": {"coordinates":[-3.430329,52.516735],"type":"Point"}
}