{
  "type": "Feature",
  "properties": {
    "addr:full":"41 Effingham Street Ramsgate Kent CT11 9AT",
    "addr:housenumber":"41",
    "addr:postcode":"ct11 9at",
    "addr:street":"Effingham Street Ramsgate",
    "iso:country":"GB",
    "sg:address":"41 Effingham Street",
    "sg:city":"Ramsgate",
    "sg:classifiers":[
        {
            "category":"Personal",
            "subcategory":"Beauty Salon",
            "type":"Services"
        }
    ],
    "sg:phone":"+44 1843 587805",
    "sg:postcode":"CT11 9AT",
    "sg:province":"Kent",
    "sg:tags":[
        "unisex",
        "hairdresser"
    ],
    "wof:name":"Fringe Benefits",
    "wof:placetype":"venue"
},
  "geometry": {"coordinates":[1.416533947,51.3341064453],"type":"Point"}
}