{
  "type": "Feature",
  "properties": {
    "addr:full":"Denham Court Nursery, Denham Court Drive, Denham Uxbridge Buckinghamshire UB9 5PG",
    "addr:postcode":"ub9 5pg",
    "addr:street":"Denham;Denham Court Drive",
    "iso:country":"GB",
    "sg:address":"Denham Court Nursery, Denham Court Drive, Denham",
    "sg:city":"Uxbridge",
    "sg:classifiers":[
        {
            "category":"Home & Garden",
            "subcategory":"Garden Supply",
            "type":"Retail Goods"
        }
    ],
    "sg:postcode":"UB9 5PG",
    "sg:province":"Buckinghamshire",
    "sg:tags":[
        "planting",
        "tree",
        "shrub"
    ],
    "wof:name":"A J Palmer & Son",
    "wof:placetype":"venue"
},
  "geometry": {"coordinates":[-0.503404,51.575932],"type":"Point"}
}