{
  "type": "Feature",
  "properties": {
    "addr:full":"4th Floor Tor Hill House, Union Street Torquay Devon TQ2 5QJ",
    "addr:housenumber":"4th floor",
    "addr:postcode":"tq2 5qj",
    "addr:street":"Tor Hill;Union Street",
    "iso:country":"GB",
    "sg:address":"4th Floor Tor Hill House, Union Street",
    "sg:city":"Torquay",
    "sg:classifiers":[
        {
            "category":"Government",
            "subcategory":"Office",
            "type":"Public Place"
        }
    ],
    "sg:phone":"+44 1803 210300",
    "sg:postcode":"TQ2 5QJ",
    "sg:province":"Devon",
    "sg:tags":[
        "inland",
        "revenue"
    ],
    "wof:name":"Board of Inland Revenue",
    "wof:placetype":"venue"
},
  "geometry": {"coordinates":[-3.53904,50.47094],"type":"Point"}
}