{
  "type": "Feature",
  "properties": {
    "iso:country":"GB",
    "sg:address":"10 Vicarage Hill, Kingsteignton",
    "sg:city":"Newton Abbot",
    "sg:classifiers":[
        {
            "category":"Social Services",
            "subcategory":"Retirement Home",
            "type":"Services"
        }
    ],
    "sg:phone":"+44 1626 360274",
    "sg:postcode":"TQ12 3BA",
    "sg:province":"Devon",
    "sg:tags":[
        "rest"
    ],
    "wof:name":"Penns Mount",
    "wof:placetype":"venue"
},
  "geometry": {"coordinates":[-3.587527,50.54697],"type":"Point"}
}