{
  "type": "Feature",
  "properties": {
    "addr:full":"Manor Farm, Hambleton Selby East Riding of Yorkshire YO8 9JG",
    "addr:postcode":"yo8 9jg",
    "addr:street":"Manor",
    "iso:country":"GB",
    "sg:address":"Manor Farm, Hambleton",
    "sg:city":"Selby",
    "sg:classifiers":[
        {
            "category":"Home & Garden",
            "subcategory":"Garden Supply",
            "type":"Retail Goods"
        }
    ],
    "sg:phone":"+44 1757 228021",
    "sg:postcode":"YO8 9JG",
    "sg:province":"East Riding of Yorkshire",
    "sg:tags":[
        "bulb",
        "grower"
    ],
    "wof:name":"H Hey & Sons",
    "wof:placetype":"venue"
},
  "geometry": {"coordinates":[-1.1657140255,53.7704963684],"type":"Point"}
}