{
  "type": "Feature",
  "properties": {
    "iso:country":"GB",
    "sg:address":"Oaklands House",
    "sg:city":"Hockley",
    "sg:classifiers":[
        {
            "category":"Building & Trades",
            "subcategory":"Construction",
            "type":"Services"
        }
    ],
    "sg:postcode":"SS5 4SF",
    "sg:province":"Essex",
    "sg:tags":[
        "builder"
    ],
    "wof:name":"Page Builders",
    "wof:placetype":"venue"
},
  "geometry": {"coordinates":[0.6557229757,51.6007041931],"type":"Point"}
}