{
  "type": "Feature",
  "properties": {
    "addr:full":"307 Abergele Road, Old Colwyn Colwyn Bay Conwy LL29 9YF",
    "addr:housenumber":"307",
    "addr:postcode":"ll29 9yf",
    "addr:street":"Abergele Road",
    "iso:country":"GB",
    "sg:address":"307 Abergele Road, Old Colwyn",
    "sg:city":"Colwyn Bay",
    "sg:classifiers":[
        {
            "category":"Building & Trades",
            "subcategory":"Plumbing",
            "type":"Services"
        },
        {
            "category":"Home & Garden",
            "subcategory":"Hardware",
            "type":"Retail Goods"
        }
    ],
    "sg:phone":"+44 1492 515281",
    "sg:postcode":"LL29 9YF",
    "sg:province":"Conwy",
    "sg:tags":[
        "merchant",
        "plumber",
        "plumbers'"
    ],
    "wof:name":"Plumb Center Ltd",
    "wof:placetype":"venue"
},
  "geometry": {"coordinates":[-3.705452,53.290188],"type":"Point"}
}