{
  "type": "Feature",
  "properties": {
    "addr:full":"3b Stormore, Dilton Marsh Westbury Wiltshire BA13 4BH",
    "addr:housenumber":"3b",
    "addr:postcode":"ba13 4bh",
    "addr:street":"Stormore Dilton Marsh Westbury",
    "iso:country":"GB",
    "sg:address":"3b Stormore, Dilton Marsh",
    "sg:city":"Westbury",
    "sg:classifiers":[
        {
            "category":"Building & Trades",
            "subcategory":"Construction",
            "type":"Services"
        }
    ],
    "sg:phone":"+44 1373 823347",
    "sg:postcode":"BA13 4BH",
    "sg:province":"Wiltshire",
    "sg:tags":[
        "joinery",
        "joiner",
        "carpenter",
        "carpentry"
    ],
    "wof:name":"John R Nagle",
    "wof:placetype":"venue"
},
  "geometry": {"coordinates":[-2.2279210091,51.2462806702],"type":"Point"}
}