{
  "type": "Feature",
  "properties": {
    "iso:country":"GB",
    "sg:address":"Wern Street, Clydach Vale",
    "sg:city":"Tonypandy",
    "sg:classifiers":[
        {
            "category":"Education",
            "subcategory":"School",
            "type":"Public Place"
        }
    ],
    "sg:phone":"+44 1443 434370",
    "sg:postcode":"CF40 2BQ",
    "sg:province":"Rhondda, Cynon, Taff",
    "sg:tags":[
        "local",
        "authority"
    ],
    "wof:name":"Rhondda Borough Council",
    "wof:placetype":"venue"
},
  "geometry": {"coordinates":[-3.475302,51.627052],"type":"Point"}
}