{
  "type": "Feature",
  "properties": {
    "addr:full":"Unit 5, Merryhills Industrial Estate, Showell Road Wolverhampton Staffordshire WV10 9LN",
    "addr:housenumber":"unit 5",
    "addr:postcode":"wv10 9ln",
    "addr:street":"Merryhills Industrial Estate Showell Road",
    "iso:country":"GB",
    "sg:address":"Unit 5, Merryhills Industrial Estate, Showell Road",
    "sg:city":"Wolverhampton",
    "sg:classifiers":[
        {
            "category":"Professional",
            "subcategory":"Business Services",
            "type":"Services"
        }
    ],
    "sg:phone":"+44 1902 306670",
    "sg:postcode":"WV10 9LN",
    "sg:province":"Staffordshire",
    "sg:tags":[
        "distribution"
    ],
    "wof:name":"Microfleet Ltd.",
    "wof:placetype":"venue"
},
  "geometry": {"coordinates":[-2.121669,52.58865],"type":"Point"}
}