{
  "type": "Feature",
  "properties": {
    "addr:full":"Cromwell Road St Neots Bedfordshire PE19 1QW",
    "addr:postcode":"pe19 1qw",
    "addr:street":"Cromwell Road",
    "iso:country":"GB",
    "sg:address":"Cromwell Road",
    "sg:city":"St Neots",
    "sg:classifiers":[
        {
            "category":"Manufacturing",
            "subcategory":"Paper Products",
            "type":"Manufacturing & Wholesale Goods"
        }
    ],
    "sg:postcode":"PE19 1QW",
    "sg:province":"Bedfordshire",
    "sg:tags":[
        "cardboard"
    ],
    "wof:name":"Dufaylite Holdings Ltd.",
    "wof:placetype":"venue"
},
  "geometry": {"coordinates":[-0.253862,52.224602],"type":"Point"}
}