{
  "type": "Feature",
  "properties": {
    "addr:full":"16 Cheraton Clo Swindon Wiltshire SN3 3NR",
    "addr:housenumber":"16",
    "addr:postcode":"sn3 3nr",
    "addr:street":"Cheraton Clo Swindon",
    "iso:country":"GB",
    "sg:address":"16 Cheraton Clo",
    "sg:city":"Swindon",
    "sg:classifiers":[
        {
            "category":"Professional",
            "subcategory":"Engineering",
            "type":"Services"
        }
    ],
    "sg:phone":"+44 1793 526737",
    "sg:postcode":"SN3 3NR",
    "sg:province":"Wiltshire",
    "sg:tags":[
        "contractor",
        "electrical",
        "engineer"
    ],
    "wof:name":"Steve Jervis",
    "wof:placetype":"venue"
},
  "geometry": {"coordinates":[-1.743572,51.564823],"type":"Point"}
}