{
  "type": "Feature",
  "properties": {
    "addr:full":"Lloyd Street Ammanford Carmarthenshire SA18 3BY",
    "addr:postcode":"sa18 3by",
    "addr:street":"Lloyd Street",
    "iso:country":"GB",
    "sg:address":"Lloyd Street",
    "sg:city":"Ammanford",
    "sg:classifiers":[
        {
            "category":"Professional",
            "subcategory":"Lawyer & Legal Services",
            "type":"Services"
        }
    ],
    "sg:phone":"+44 1269 593463",
    "sg:postcode":"SA18 3BY",
    "sg:province":"Carmarthenshire",
    "sg:tags":[
        "solicitor"
    ],
    "wof:name":"David L L R Davies & Co",
    "wof:placetype":"venue"
},
  "geometry": {"coordinates":[-3.988229,51.791889],"type":"Point"}
}