{
  "type": "Feature",
  "properties": {
    "iso:country":"GB",
    "sg:address":"4 Prince Consort Drive",
    "sg:city":"Ascot",
    "sg:classifiers":[
        {
            "category":"Professional",
            "subcategory":"Business Services",
            "type":"Services"
        }
    ],
    "sg:phone":"+44 1344 872522",
    "sg:postcode":"SL5 8AW",
    "sg:province":"Berkshire",
    "sg:tags":[
        "import",
        "export",
        "agent"
    ],
    "wof:name":"Y & W Export Ltd.",
    "wof:placetype":"venue"
},
  "geometry": {"coordinates":[-0.699407,51.404812],"type":"Point"}
}