{
  "type": "Feature",
  "properties": {
    "iso:country":"GB",
    "sg:address":"140-142 St James St",
    "sg:city":"Burnley",
    "sg:classifiers":[
        {
            "category":"Social Services",
            "type":"Services"
        },
        {
            "category":"Utilities",
            "subcategory":"Mobile Phone",
            "type":"Services"
        },
        {
            "category":"Retail",
            "subcategory":"Auto Repair",
            "type":"Services"
        }
    ],
    "sg:phone":"+44 1282 450684",
    "sg:postcode":"BB11 1NR",
    "sg:province":"Lancashire",
    "sg:tags":[
        "equipment",
        "garage",
        "disability",
        "related",
        "mobility"
    ],
    "wof:name":"Shop Mobility",
    "wof:placetype":"venue"
},
  "geometry": {"coordinates":[-2.246434,53.789768],"type":"Point"}
}