{
  "type": "Feature",
  "properties": {
    "addr:full":"3 Parkfield Crewe Cheshire CW1 4TT",
    "addr:housenumber":"3",
    "addr:postcode":"cw1 4tt",
    "addr:street":"Parkfield",
    "iso:country":"GB",
    "sg:address":"3 Parkfield",
    "sg:city":"Crewe",
    "sg:classifiers":[
        {
            "category":"Education",
            "subcategory":"Special Training",
            "type":"Public Place"
        }
    ],
    "sg:phone":"+44 1270 584947",
    "sg:postcode":"CW1 4TT",
    "sg:province":"Cheshire",
    "sg:tags":[
        "product",
        "centre"
    ],
    "wof:name":"S L H Consultants",
    "wof:placetype":"venue"
},
  "geometry": {"coordinates":[-2.459265,53.118317],"type":"Point"}
}