{
  "type": "Feature",
  "properties": {
    "addr:full":"Grange Farm, Chapel Lane, Addlethorpe Skegness Lincolnshire PE24 4TG",
    "addr:postcode":"pe24 4tg",
    "addr:street":"Chapel Lane",
    "iso:country":"GB",
    "sg:address":"Grange Farm, Chapel Lane, Addlethorpe",
    "sg:city":"Skegness",
    "sg:classifiers":[
        {
            "category":"Farming",
            "subcategory":"Crops",
            "type":"Manufacturing & Wholesale Goods"
        },
        {
            "category":"Farming",
            "subcategory":"Livestock Farm",
            "type":"Manufacturing & Wholesale Goods"
        }
    ],
    "sg:phone":"+44 1754 873497",
    "sg:postcode":"PE24 4TG",
    "sg:province":"Lincolnshire",
    "sg:tags":[
        "arable",
        "others"
    ],
    "wof:name":"Hand Bros",
    "wof:placetype":"venue"
},
  "geometry": {"coordinates":[0.3181799948,53.1951942444],"type":"Point"}
}