{
  "type": "Feature",
  "properties": {
    "iso:country":"GB",
    "sg:address":"Windy Nook, Lower Queen Street",
    "sg:city":"Sutton Coldfield",
    "sg:classifiers":[
        {
            "category":"Building & Trades",
            "subcategory":"Plumbing",
            "type":"Services"
        }
    ],
    "sg:postcode":"B72 1RT",
    "sg:province":"West Midlands",
    "sg:tags":[
        "heating"
    ],
    "wof:name":"Steve Dressler",
    "wof:placetype":"venue"
},
  "geometry": {"coordinates":[-1.8225170374,52.560344696],"type":"Point"}
}