{
  "type": "Feature",
  "properties": {
    "addr:full":"Sundon Road, Harlington Dunstable Bedfordshire LU5 6LS",
    "addr:postcode":"lu5 6ls",
    "addr:street":"Sundon Road",
    "iso:country":"GB",
    "sg:address":"Sundon Road, Harlington",
    "sg:city":"Dunstable",
    "sg:classifiers":[
        {
            "category":"Bars & Pubs",
            "type":"Food & Drink"
        }
    ],
    "sg:phone":"+44 1525 872384",
    "sg:postcode":"LU5 6LS",
    "sg:province":"Bedfordshire",
    "sg:tags":[
        "pubs",
        "inn"
    ],
    "wof:name":"The Carpenters Arms",
    "wof:placetype":"venue"
},
  "geometry": {"coordinates":[-0.492363,51.961987],"type":"Point"}
}