{
  "type": "Feature",
  "properties": {
    "iso:country":"GB",
    "sg:address":"Orchard House, Station Road, Lanham",
    "sg:city":"Gillingham",
    "sg:classifiers":[
        {
            "category":"Banks & Credit Unions",
            "subcategory":"Financial Services",
            "type":"Services"
        }
    ],
    "sg:phone":"+44 1634 239943",
    "sg:postcode":"ME8 7RS",
    "sg:province":"Kent",
    "sg:tags":[
        "adviser"
    ],
    "wof:name":"Owl Insurance Services",
    "wof:placetype":"venue"
},
  "geometry": {"coordinates":[0.619948,51.372734],"type":"Point"}
}