{
  "type": "Feature",
  "properties": {
    "iso:country":"GB",
    "sg:address":"23 Housley Park, Chapeltown",
    "sg:city":"Sheffield",
    "sg:classifiers":[
        {
            "category":"Place Of Worship",
            "type":"Public Place"
        }
    ],
    "sg:phone":"+44 114 257 0966",
    "sg:postcode":"S35 2UE",
    "sg:province":"South Yorkshire",
    "wof:name":"St Johns Vicarage",
    "wof:placetype":"venue"
},
  "geometry": {"coordinates":[-1.470885,53.4646],"type":"Point"}
}