{
  "type": "Feature",
  "properties": {
    "addr:full":"35a Dundas Street Edinburgh City of Edinburgh EH3 6QQ",
    "addr:housenumber":"35a",
    "addr:postcode":"eh3 6qq",
    "addr:street":"Dundas Street",
    "iso:country":"GB",
    "sg:address":"35a Dundas Street",
    "sg:city":"Edinburgh",
    "sg:classifiers":[
        {
            "category":"Wholesale",
            "subcategory":"Toys & Hobbies",
            "type":"Manufacturing & Wholesale Goods"
        }
    ],
    "sg:postcode":"EH3 6QQ",
    "sg:province":"City of Edinburgh",
    "sg:tags":[
        "hospital",
        "doll"
    ],
    "wof:name":"Geraldine's of Edinburgh",
    "wof:placetype":"venue"
},
  "geometry": {"coordinates":[-3.1991329193,55.9574584961],"type":"Point"}
}