{
  "type": "Feature",
  "properties": {
    "iso:country":"GB",
    "sg:address":"Ashwellthorpe Road, Wreningham",
    "sg:city":"Norwich",
    "sg:classifiers":[
        {
            "category":"Education",
            "subcategory":"School",
            "type":"Public Place"
        }
    ],
    "sg:phone":"+44 1508 489355",
    "sg:postcode":"NR16 1AW",
    "sg:province":"Norfolk",
    "sg:tags":[
        "local",
        "authority"
    ],
    "wof:name":"Norfolk County Council",
    "wof:placetype":"venue"
},
  "geometry": {"coordinates":[1.1584310532,52.5344276428],"type":"Point"}
}