{
  "type": "Feature",
  "properties": {
    "addr:full":"62 Bellegrove Road Welling Kent DA16 3PY",
    "addr:housenumber":"62",
    "addr:postcode":"da16 3py",
    "addr:street":"Bellegrove Road",
    "iso:country":"GB",
    "sg:address":"62 Bellegrove Road",
    "sg:city":"Welling",
    "sg:classifiers":[
        {
            "category":"Retail",
            "subcategory":"Laundry & Dry Cleaning",
            "type":"Services"
        }
    ],
    "sg:phone":"+44 20 8303 1200",
    "sg:postcode":"DA16 3PY",
    "sg:province":"Kent",
    "sg:tags":[
        "alteration"
    ],
    "wof:name":"Bellegrove Dry Cleaners",
    "wof:placetype":"venue"
},
  "geometry": {"coordinates":[0.1039090008,51.4632072449],"type":"Point"}
}