{
  "type": "Feature",
  "properties": {
    "addr:full":"Waunlluest Farm, Gorrig Llandysul Carmarthenshire SA44 4LL",
    "addr:postcode":"sa44 4ll",
    "iso:country":"GB",
    "sg:address":"Waunlluest Farm, Gorrig",
    "sg:city":"Llandysul",
    "sg:classifiers":[
        {
            "category":"Farming",
            "subcategory":"Livestock Farm",
            "type":"Manufacturing & Wholesale Goods"
        }
    ],
    "sg:phone":"+44 1559 363257",
    "sg:postcode":"SA44 4LL",
    "sg:province":"Carmarthenshire",
    "sg:tags":[
        "others"
    ],
    "wof:name":"D D & M I Jones",
    "wof:placetype":"venue"
},
  "geometry": {"coordinates":[-4.3078169823,52.0444793701],"type":"Point"}
}