{
  "type": "Feature",
  "properties": {
    "addr:full":"323 Brockley Road, Brockley London Greater London SE4 2QZ",
    "addr:housenumber":"323",
    "addr:postcode":"se4 2qz",
    "addr:street":"Brockley Road",
    "iso:country":"GB",
    "sg:address":"323 Brockley Road, Brockley",
    "sg:city":"London",
    "sg:classifiers":[
        {
            "category":"Shopping",
            "subcategory":"Used Merchandise",
            "type":"Retail Goods"
        }
    ],
    "sg:phone":"+44 20 8691 8000",
    "sg:postcode":"SE4 2QZ",
    "sg:province":"Greater London",
    "sg:tags":[
        "shop",
        "second-hand"
    ],
    "wof:name":"Goodies",
    "wof:placetype":"venue"
},
  "geometry": {"coordinates":[-0.0338019989,51.45936203],"type":"Point"}
}