{
  "type": "Feature",
  "properties": {
    "addr:full":"Vernon Drive Whitley Bay Northumberland NE25 8JN",
    "addr:postcode":"ne25 8jn",
    "addr:street":"Vernon Drive",
    "iso:country":"GB",
    "sg:address":"Vernon Drive",
    "sg:city":"Whitley Bay",
    "sg:classifiers":[
        {
            "category":"Education",
            "subcategory":"School",
            "type":"Public Place"
        }
    ],
    "sg:phone":"+44 191 200 8715",
    "sg:postcode":"NE25 8JN",
    "sg:province":"Northumberland",
    "sg:tags":[
        "local",
        "authority"
    ],
    "wof:name":"Monkseaton Middle School",
    "wof:placetype":"venue"
},
  "geometry": {"coordinates":[-1.463307,55.039101],"type":"Point"}
}