{
  "type": "Feature",
  "properties": {
    "iso:country":"GB",
    "sg:address":"122-128 Guildhall Street",
    "sg:city":"Folkestone",
    "sg:classifiers":[
        {
            "category":"Retail",
            "subcategory":"Auto Repair",
            "type":"Services"
        }
    ],
    "sg:postcode":"CT20 1ES",
    "sg:province":"Kent",
    "sg:tags":[
        "modification",
        "garage"
    ],
    "wof:name":"The Mini Man",
    "wof:placetype":"venue"
},
  "geometry": {"coordinates":[1.17604,51.083721],"type":"Point"}
}