{
  "type": "Feature",
  "properties": {
    "addr:full":"14 Reswythen Walk, Tolvaddon Camborne Cornwall TR14 0EX",
    "addr:housenumber":"14",
    "addr:postcode":"tr14 0ex",
    "addr:street":"Reswythen Walk Tolvaddon",
    "iso:country":"GB",
    "sg:address":"14 Reswythen Walk, Tolvaddon",
    "sg:city":"Camborne",
    "sg:classifiers":[
        {
            "category":"Building & Trades",
            "subcategory":"Construction",
            "type":"Services"
        }
    ],
    "sg:postcode":"TR14 0EX",
    "sg:province":"Cornwall",
    "sg:tags":[
        "roofing"
    ],
    "wof:name":"Hooper & Smith",
    "wof:placetype":"venue"
},
  "geometry": {"coordinates":[-5.2844948769,50.2314872742],"type":"Point"}
}