{
  "type": "Feature",
  "properties": {
    "iso:country":"GB",
    "sg:address":"14 Reswythen Walk, Tolvaddon",
    "sg:city":"Camborne",
    "sg:classifiers":[
        {
            "category":"Building & Trades",
            "subcategory":"Construction",
            "type":"Services"
        }
    ],
    "sg:postcode":"TR14 0EX",
    "sg:province":"Cornwall",
    "sg:tags":[
        "roofing"
    ],
    "wof:name":"Hooper & Smith",
    "wof:placetype":"venue"
},
  "geometry": {"coordinates":[-5.2844948769,50.2314872742],"type":"Point"}
}