{
  "type": "Feature",
  "properties": {
    "iso:country":"GB",
    "sg:address":"Manor Farm, Scoreby, Gate Helmsley",
    "sg:city":"York",
    "sg:classifiers":[
        {
            "category":"Farming",
            "subcategory":"Livestock Farm",
            "type":"Manufacturing & Wholesale Goods"
        }
    ],
    "sg:phone":"+44 1904 489344",
    "sg:postcode":"YO41 1NR",
    "sg:province":"East Riding of Yorkshire",
    "sg:tags":[
        "others"
    ],
    "wof:name":"C P Wilkinson",
    "wof:placetype":"venue"
},
  "geometry": {"coordinates":[-0.944454,53.989609],"type":"Point"}
}