{
  "type": "Feature",
  "properties": {
    "iso:country":"GB",
    "sg:address":"Tillietudlum, Lesmahagow",
    "sg:city":"Lanark",
    "sg:classifiers":[
        {
            "category":"Home & Garden",
            "subcategory":"Garden Supply",
            "type":"Retail Goods"
        }
    ],
    "sg:phone":"+44 1555 860370",
    "sg:postcode":"ML11 9PN",
    "sg:province":"South Lanarkshire",
    "sg:tags":[
        "tree",
        "shrub"
    ],
    "wof:name":"Frames Plants Direct",
    "wof:placetype":"venue"
},
  "geometry": {"coordinates":[-3.781384,55.673866],"type":"Point"}
}