{
  "type": "Feature",
  "properties": {
    "addr:full":"44 Sandhurst Dr Ilford Essex IG3 9DD",
    "addr:housenumber":"44",
    "addr:postcode":"ig3 9dd",
    "addr:street":"Sandhurst Dr",
    "iso:country":"GB",
    "sg:address":"44 Sandhurst Dr",
    "sg:city":"Ilford",
    "sg:classifiers":[
        {
            "category":"Manufacturing",
            "subcategory":"Paper Products",
            "type":"Manufacturing & Wholesale Goods"
        }
    ],
    "sg:phone":"+44 20 8983 8998",
    "sg:postcode":"IG3 9DD",
    "sg:province":"Essex",
    "sg:tags":[
        "board"
    ],
    "wof:name":"D C Board Sales",
    "wof:placetype":"venue"
},
  "geometry": {"coordinates":[0.103139,51.551426],"type":"Point"}
}