{
  "type": "Feature",
  "properties": {
    "addr:full":"36a Burghley Rd Kentish Town Greater London NW5 1UE",
    "addr:housenumber":"36a",
    "addr:postcode":"nw5 1ue",
    "addr:street":"Burghley Rd",
    "iso:country":"GB",
    "sg:address":"36a Burghley Rd",
    "sg:city":"Kentish Town",
    "sg:classifiers":[
        {
            "category":"Professional",
            "subcategory":"Art Services",
            "type":"Services"
        }
    ],
    "sg:phone":"+44 20 7209 4047",
    "sg:postcode":"NW5 1UE",
    "sg:province":"Greater London",
    "sg:tags":[
        "photographer"
    ],
    "wof:name":"Adam Parker-Fagin",
    "wof:placetype":"venue"
},
  "geometry": {"coordinates":[-0.1415269971,51.5544776917],"type":"Point"}
}