{
  "type": "Feature",
  "properties": {
    "addr:full":"27 Stall Street Bath Bath and North East Somerset BA1 1QF",
    "addr:housenumber":"27",
    "addr:postcode":"ba1 1qf",
    "addr:street":"Stall Street",
    "iso:country":"GB",
    "sg:address":"27 Stall Street",
    "sg:city":"Bath",
    "sg:classifiers":[
        {
            "category":"Shopping",
            "subcategory":"Clothing, Apparel, & Fashions",
            "type":"Retail Goods"
        }
    ],
    "sg:phone":"+44 1225 444909",
    "sg:postcode":"BA1 1QF",
    "sg:province":"Bath and North East Somerset",
    "sg:tags":[
        "shop",
        "lady",
        "fashionwear"
    ],
    "wof:name":"Pilot Clothing Ltd.",
    "wof:placetype":"venue"
},
  "geometry": {"coordinates":[-2.360061,51.380188],"type":"Point"}
}