{
  "type": "Feature",
  "properties": {
    "iso:country":"GB",
    "sg:address":"Unit 6, Crystal Drive, Sandwell Business Park",
    "sg:city":"Smethwick",
    "sg:classifiers":[
        {
            "category":"Home & Garden",
            "subcategory":"Home Furnishings",
            "type":"Retail Goods"
        }
    ],
    "sg:phone":"+44 121 543 2828",
    "sg:postcode":"B66 1QG",
    "sg:province":"West Midlands",
    "sg:tags":[
        "pipe",
        "fitting"
    ],
    "wof:name":"Rokker & Stanton-midlands",
    "wof:placetype":"venue"
},
  "geometry": {"coordinates":[-1.994658947,52.5047340393],"type":"Point"}
}