{
  "type": "Feature",
  "properties": {
    "iso:country":"GB",
    "sg:address":"Jubilee Buildings, 99 Holloway Bank",
    "sg:city":"Wednesbury",
    "sg:classifiers":[
        {
            "category":"Wholesale",
            "subcategory":"Construction Materials",
            "type":"Manufacturing & Wholesale Goods"
        }
    ],
    "sg:postcode":"WS10 0PA",
    "sg:province":"West Midlands",
    "sg:tags":[
        "coating",
        "powder"
    ],
    "wof:name":"Elite Powder Coatings",
    "wof:placetype":"venue"
},
  "geometry": {"coordinates":[-2.019254,52.552731],"type":"Point"}
}