{
  "type": "Feature",
  "properties": {
    "iso:country":"GB",
    "sg:address":"95 Treseifion Estate",
    "sg:city":"Holyhead",
    "sg:classifiers":[
        {
            "category":"Professional",
            "subcategory":"Art Services",
            "type":"Services"
        }
    ],
    "sg:phone":"+44 1407 760471",
    "sg:postcode":"LL65 2YN",
    "sg:province":"Isle of Anglesey",
    "sg:tags":[
        "photographer"
    ],
    "wof:name":"Arthur A Lloyd",
    "wof:placetype":"venue"
},
  "geometry": {"coordinates":[-4.635305,53.302277],"type":"Point"}
}