{
  "type": "Feature",
  "properties": {
    "addr:full":"23 West Street Bridport Dorset DT6 3QN",
    "addr:housenumber":"23",
    "addr:postcode":"dt6 3qn",
    "addr:street":"West Street",
    "iso:country":"GB",
    "sg:address":"23 West Street",
    "sg:city":"Bridport",
    "sg:classifiers":[
        {
            "category":"Food & Beverages",
            "subcategory":"Meat & Fish",
            "type":"Retail Goods"
        }
    ],
    "sg:phone":"+44 1308 423041",
    "sg:postcode":"DT6 3QN",
    "sg:province":"Dorset",
    "sg:tags":[
        "chip"
    ],
    "wof:name":"Longs (Davies)",
    "wof:placetype":"venue"
},
  "geometry": {"coordinates":[-2.759469986,50.7339248657],"type":"Point"}
}