{
  "type": "Feature",
  "properties": {
    "addr:full":"High Street, Oldland Common Bristol Gloucestershire BS30 9TL",
    "addr:postcode":"bs30 9tl",
    "addr:street":"High Street",
    "iso:country":"GB",
    "sg:address":"High Street, Oldland Common",
    "sg:city":"Bristol",
    "sg:classifiers":[
        {
            "category":"Education",
            "subcategory":"School",
            "type":"Public Place"
        }
    ],
    "sg:phone":"+44 1454 867165",
    "sg:postcode":"BS30 9TL",
    "sg:province":"Gloucestershire",
    "sg:tags":[
        "local",
        "authority"
    ],
    "wof:name":"Redfield Edge Primary School",
    "wof:placetype":"venue"
},
  "geometry": {"coordinates":[-2.4634740353,51.4447288513],"type":"Point"}
}