{
  "type": "Feature",
  "properties": {
    "addr:full":"67 George Street Oldham Lancashire OL1 1LX",
    "addr:housenumber":"67",
    "addr:postcode":"ol1 1lx",
    "addr:street":"George Street",
    "iso:country":"GB",
    "sg:address":"67 George Street",
    "sg:city":"Oldham",
    "sg:classifiers":[
        {
            "category":"Food & Beverages",
            "subcategory":"Bakery",
            "type":"Retail Goods"
        },
        {
            "category":"Bakery",
            "type":"Food & Drink"
        }
    ],
    "sg:phone":"+44 161 624 4639",
    "sg:postcode":"OL1 1LX",
    "sg:province":"Lancashire",
    "sg:tags":[
        "cake",
        "confectionery",
        "maker"
    ],
    "wof:name":"Sugar Flair Cakes",
    "wof:placetype":"venue"
},
  "geometry": {"coordinates":[-2.116038,53.539803],"type":"Point"}
}