{
  "type": "Feature",
  "properties": {
    "addr:full":"4 Neckley Street Farnborough Hampshire GU14 6AQ",
    "addr:housenumber":"4",
    "addr:postcode":"gu14 6aq",
    "addr:street":"Neckley Street",
    "iso:country":"GB",
    "sg:address":"4 Neckley Street",
    "sg:city":"Farnborough",
    "sg:classifiers":[
        {
            "category":"Retail",
            "subcategory":"Auto Repair",
            "type":"Services"
        }
    ],
    "sg:phone":"+44 1252 511822",
    "sg:postcode":"GU14 6AQ",
    "sg:province":"Hampshire",
    "sg:tags":[
        "modification",
        "garage"
    ],
    "wof:name":"Woodford Motors (Farnborough) Ltd.",
    "wof:placetype":"venue"
},
  "geometry": {"coordinates":[-0.755569,51.293724],"type":"Point"}
}