{
  "type": "Feature",
  "properties": {
    "addr:full":"Unit 1b Castle Retail Park, Radford Blvd Nottingham Nottinghamshire NG7 5QJ",
    "addr:housenumber":"unit 1b",
    "addr:postcode":"ng7 5qj",
    "addr:street":"Castle Retail Park Radford Blvd",
    "iso:country":"GB",
    "sg:address":"Unit 1b Castle Retail Park, Radford Blvd",
    "sg:city":"Nottingham",
    "sg:classifiers":[
        {
            "category":"Recreation",
            "subcategory":"Dance Hall",
            "type":"Entertainment"
        }
    ],
    "sg:phone":"+44 115 970 4323",
    "sg:postcode":"NG7 5QJ",
    "sg:province":"Nottinghamshire",
    "sg:tags":[
        "bingo"
    ],
    "wof:name":"Ritz Bingo",
    "wof:placetype":"venue"
},
  "geometry": {"coordinates":[-1.176614,52.960789],"type":"Point"}
}