{
  "type": "Feature",
  "properties": {
    "addr:full":"Bryn-awel, Tufton Clarbeston Road Pembrokeshire SA63 4TU",
    "addr:postcode":"sa63 4tu",
    "addr:street":"Road",
    "iso:country":"GB",
    "sg:address":"Bryn-awel, Tufton",
    "sg:city":"Clarbeston Road",
    "sg:classifiers":[
        {
            "category":"Farming",
            "subcategory":"Farm",
            "type":"Manufacturing & Wholesale Goods"
        }
    ],
    "sg:postcode":"SA63 4TU",
    "sg:province":"Pembrokeshire",
    "sg:tags":[
        "mixed",
        "crop"
    ],
    "wof:name":"W K Davies",
    "wof:placetype":"venue"
},
  "geometry": {"coordinates":[-4.8799791336,51.8500785828],"type":"Point"}
}