{
  "type": "Feature",
  "properties": {
    "iso:country":"GB",
    "sg:address":"West Pier, Peterhead Harbour",
    "sg:city":"Peterhead",
    "sg:classifiers":[
        {
            "category":"Harbor",
            "type":"Transportation"
        }
    ],
    "sg:phone":"+44 1779 476075",
    "sg:postcode":"AB42 6DZ",
    "sg:province":"Aberdeenshire",
    "sg:tags":[
        "dock",
        "ports",
        "harbour"
    ],
    "wof:name":"Peterhead Pilots",
    "wof:placetype":"venue"
},
  "geometry": {"coordinates":[-1.7973099947,57.5065307617],"type":"Point"}
}