{
  "type": "Feature",
  "properties": {
    "addr:full":"80 Station Road, Cuffley Potters Bar Greater London EN6 4EU",
    "addr:housenumber":"80",
    "addr:postcode":"en6 4eu",
    "addr:street":"Station Road",
    "iso:country":"GB",
    "sg:address":"80 Station Road, Cuffley",
    "sg:city":"Potters Bar",
    "sg:classifiers":[
        {
            "category":"Autos & Motor Vehicles",
            "subcategory":"Fuel & Gas Station",
            "type":"Retail Goods"
        }
    ],
    "sg:phone":"+44 1707 875887",
    "sg:postcode":"EN6 4EU",
    "sg:province":"Greater London",
    "sg:tags":[
        "petrol",
        "filling"
    ],
    "wof:name":"Save Service Station",
    "wof:placetype":"venue"
},
  "geometry": {"coordinates":[-0.1096670032,51.7082328796],"type":"Point"}
}