{
  "type": "Feature",
  "properties": {
    "addr:full":"Unit 14, Wilford Business Park, Nottingham South Nottingham Nottinghamshire NG11 7EP",
    "addr:housenumber":"unit 14",
    "addr:postcode":"ng11 7ep",
    "addr:street":"Wilford Business Park",
    "iso:country":"GB",
    "sg:address":"Unit 14, Wilford Business Park, Nottingham South",
    "sg:city":"Nottingham",
    "sg:classifiers":[
        {
            "category":"Building & Trades",
            "subcategory":"Construction",
            "type":"Services"
        }
    ],
    "sg:phone":"+44 115 982 7744",
    "sg:postcode":"NG11 7EP",
    "sg:province":"Nottinghamshire",
    "sg:tags":[
        "window",
        "door"
    ],
    "wof:name":"Systems Hardware Ltd.",
    "wof:placetype":"venue"
},
  "geometry": {"coordinates":[-1.157379,52.914173],"type":"Point"}
}