{
  "type": "Feature",
  "properties": {
    "addr:full":"14 Belgic Square Peterborough Cambridgeshire PE1 5XF",
    "addr:housenumber":"14",
    "addr:postcode":"pe1 5xf",
    "addr:street":"Belgic Square",
    "iso:country":"GB",
    "sg:address":"14 Belgic Square",
    "sg:city":"Peterborough",
    "sg:classifiers":[
        {
            "category":"Professional",
            "subcategory":"Engineering",
            "type":"Services"
        },
        {
            "category":"Building & Trades",
            "subcategory":"Electrical",
            "type":"Services"
        }
    ],
    "sg:phone":"+44 1733 897700",
    "sg:postcode":"PE1 5XF",
    "sg:province":"Cambridgeshire",
    "sg:tags":[
        "engineer",
        "electrician",
        "contractor"
    ],
    "wof:name":"R & T MORLEY",
    "wof:placetype":"venue"
},
  "geometry": {"coordinates":[-0.2115239948,52.576915741],"type":"Point"}
}