{
  "type": "Feature",
  "properties": {
    "iso:country":"GB",
    "sg:address":"21 Queens Road",
    "sg:city":"Richmond",
    "sg:classifiers":[
        {
            "category":"Retail",
            "subcategory":"Funeral Services",
            "type":"Services"
        }
    ],
    "sg:phone":"+44 1748 850033",
    "sg:postcode":"DL10 4AJ",
    "sg:province":"North Yorkshire",
    "wof:name":"John Blenkiron",
    "wof:placetype":"venue"
},
  "geometry": {"coordinates":[-1.7364120483,54.4060325623],"type":"Point"}
}