{
  "type": "Feature",
  "properties": {
    "iso:country":"GB",
    "sg:address":"25 Cambridge Yard, Cambridge Road",
    "sg:city":"Hanwell",
    "sg:classifiers":[
        {
            "category":"Manufacturing",
            "subcategory":"Building Materials",
            "type":"Manufacturing & Wholesale Goods"
        }
    ],
    "sg:phone":"+44 20 8840 8292",
    "sg:postcode":"W7 3UP",
    "sg:province":"Greater London",
    "sg:tags":[
        "mnfr",
        "maker",
        "cabinet"
    ],
    "wof:name":"D & S Joinery",
    "wof:placetype":"venue"
},
  "geometry": {"coordinates":[-0.33412,51.505219],"type":"Point"}
}