{
  "type": "Feature",
  "properties": {
    "iso:country":"GB",
    "sg:address":"41-42 The Old Woodyard, Hagley Hall",
    "sg:city":"Stourbridge",
    "sg:classifiers":[
        {
            "category":"Shopping",
            "subcategory":"Musical Instruments",
            "type":"Retail Goods"
        },
        {
            "category":"Professional",
            "subcategory":"Art Services",
            "type":"Services"
        }
    ],
    "sg:postcode":"DY9 9LG",
    "sg:province":"West Midlands",
    "sg:tags":[
        "framing"
    ],
    "wof:name":"Grove,Alan & Nina,",
    "wof:placetype":"venue"
},
  "geometry": {"coordinates":[-2.12055,52.424191],"type":"Point"}
}