{
  "type": "Feature",
  "properties": {
    "iso:country":"GB",
    "sg:address":"16-22 King Street",
    "sg:city":"Watford",
    "sg:classifiers":[
        {
            "category":"Manufacturing",
            "subcategory":"Tools & Machinery",
            "type":"Manufacturing & Wholesale Goods"
        }
    ],
    "sg:phone":"+44 1923 219457",
    "sg:postcode":"WD18 0BP",
    "sg:province":"Hertfordshire",
    "sg:tags":[
        "society",
        "friendly"
    ],
    "wof:name":"Applied Technology Adjusting Ltd.",
    "wof:placetype":"venue"
},
  "geometry": {"coordinates":[-0.3962790072,51.6530685425],"type":"Point"}
}