{
  "type": "Feature",
  "properties": {
    "addr:full":"Unit 21 Richmond Ho, George St, Mondale Indust Est Stockton On Tees Durham TS17 6DE",
    "addr:housenumber":"unit 21",
    "addr:postcode":"ts17 6de",
    "addr:street":"George St;Indust",
    "iso:country":"GB",
    "sg:address":"Unit 21 Richmond Ho, George St, Mondale Indust Est",
    "sg:city":"Stockton On Tees",
    "sg:classifiers":[
        {
            "category":"Utilities",
            "type":"Services"
        }
    ],
    "sg:phone":"+44 1642 603133",
    "sg:postcode":"TS17 6DE",
    "sg:province":"Durham",
    "sg:tags":[
        "internet"
    ],
    "wof:name":"Northern Creations",
    "wof:placetype":"venue"
},
  "geometry": {"coordinates":[-1.3043899536,54.5562400818],"type":"Point"}
}