{
  "type": "Feature",
  "properties": {
    "addr:full":"Oldwick Farm, West Stoke Road, Lavant Chichester West Sussex PO18 9AA",
    "addr:postcode":"po18 9aa",
    "addr:street":"West Stoke Road",
    "iso:country":"GB",
    "sg:address":"Oldwick Farm, West Stoke Road, Lavant",
    "sg:city":"Chichester",
    "sg:classifiers":[
        {
            "category":"Retail",
            "subcategory":"Veterinary Services",
            "type":"Services"
        }
    ],
    "sg:phone":"+44 1243 528899",
    "sg:postcode":"PO18 9AA",
    "sg:province":"West Sussex",
    "sg:tags":[
        "surgeon"
    ],
    "wof:name":"Kingley Veterinary Centre",
    "wof:placetype":"venue"
},
  "geometry": {"coordinates":[-0.822344,50.870602],"type":"Point"}
}