{
  "type": "Feature",
  "properties": {
    "addr:full":"Kirk Sandall Industrial Estate Doncaster South Yorkshire DN3 1QP",
    "addr:housenumber":"estate",
    "addr:postcode":"dn3 1qp",
    "addr:street":"Industrial",
    "iso:country":"GB",
    "sg:address":"Kirk Sandall Industrial Estate",
    "sg:city":"Doncaster",
    "sg:classifiers":[
        {
            "category":"Real Estate",
            "subcategory":"Developer",
            "type":"Services"
        }
    ],
    "sg:phone":"+44 1302 883141",
    "sg:postcode":"DN3 1QP",
    "sg:province":"South Yorkshire",
    "sg:tags":[
        "property"
    ],
    "wof:name":"Persimmon Homes (Doncaster) Ltd.",
    "wof:placetype":"venue"
},
  "geometry": {"coordinates":[-1.0727880001,53.5627784729],"type":"Point"}
}