{
  "type": "Feature",
  "properties": {
    "addr:full":"21-22 Enterprise Way London Greater London NW10 6UG",
    "addr:housenumber":"21-22",
    "addr:postcode":"nw10 6ug",
    "addr:street":"Enterprise Way",
    "iso:country":"GB",
    "sg:address":"21-22 Enterprise Way",
    "sg:city":"London",
    "sg:classifiers":[
        {
            "category":"Professional",
            "subcategory":"Art Services",
            "type":"Services"
        },
        {
            "category":"Professional",
            "subcategory":"Printing & Photocopies",
            "type":"Services"
        }
    ],
    "sg:phone":"+44 20 8965 1502",
    "sg:postcode":"NW10 6UG",
    "sg:province":"Greater London",
    "sg:tags":[
        "designer",
        "graphic",
        "printer"
    ],
    "wof:name":"The Kingfisher Press",
    "wof:placetype":"venue"
},
  "geometry": {"coordinates":[-0.241976,51.52895],"type":"Point"}
}