{
  "type": "Feature",
  "properties": {
    "addr:full":"Hillhouse Lane Bottom, Cartworth Moor Huddersfield South Yorkshire HD9 2RL",
    "addr:postcode":"hd9 2rl",
    "addr:street":"Hillhouse Lane;Moor",
    "iso:country":"GB",
    "sg:address":"Hillhouse Lane Bottom, Cartworth Moor",
    "sg:city":"Huddersfield",
    "sg:classifiers":[
        {
            "category":"Manufacturing",
            "subcategory":"Glass & Minerals",
            "type":"Manufacturing & Wholesale Goods"
        }
    ],
    "sg:phone":"+44 1484 683239",
    "sg:postcode":"HD9 2RL",
    "sg:province":"South Yorkshire",
    "sg:tags":[
        "chalk",
        "stone",
        "slate"
    ],
    "wof:name":"Saxonmoor Ltd.",
    "wof:placetype":"venue"
},
  "geometry": {"coordinates":[-1.80232,53.556629],"type":"Point"}
}