{
  "type": "Feature",
  "properties": {
    "iso:country":"GB",
    "sg:address":"1 Strickland Street, Hessle Road",
    "sg:city":"Hull",
    "sg:classifiers":[
        {
            "category":"Retail",
            "subcategory":"Auto Repair",
            "type":"Services"
        }
    ],
    "sg:phone":"+44 1482 320816",
    "sg:postcode":"HU3 4AQ",
    "sg:province":"East Riding of Yorkshire",
    "sg:tags":[
        "modification",
        "garage"
    ],
    "wof:name":"Castle Motors",
    "wof:placetype":"venue"
},
  "geometry": {"coordinates":[-0.358925,53.736187],"type":"Point"}
}