{
  "type": "Feature",
  "properties": {
    "iso:country":"GB",
    "sg:address":"293 Hoylake Rd",
    "sg:city":"Wirral",
    "sg:classifiers":[
        {
            "category":"Professional",
            "subcategory":"Accounting & Tax Preparation",
            "type":"Services"
        }
    ],
    "sg:phone":"+44 151 677 7729",
    "sg:postcode":"L46 0RL",
    "sg:province":"Cheshire",
    "sg:tags":[
        "accountant"
    ],
    "wof:name":"Hailwood & Co",
    "wof:placetype":"venue"
},
  "geometry": {"coordinates":[-3.115122,53.399715],"type":"Point"}
}