{
  "type": "Feature",
  "properties": {
    "iso:country":"GB",
    "sg:address":"403 Limpsfield Road",
    "sg:city":"Warlingham",
    "sg:classifiers":[
        {
            "category":"Food & Beverages",
            "subcategory":"Liquor & Beverages",
            "type":"Retail Goods"
        }
    ],
    "sg:phone":"+44 1883 622377",
    "sg:postcode":"CR6 9HA",
    "sg:province":"Kent",
    "sg:tags":[
        "beer",
        "wine",
        "spirit",
        "wines"
    ],
    "wof:name":"Bottoms Up",
    "wof:placetype":"venue"
},
  "geometry": {"coordinates":[-0.055094,51.309776],"type":"Point"}
}