{
  "type": "Feature",
  "properties": {
    "iso:country":"GB",
    "sg:address":"10 Stone Street",
    "sg:city":"Tunbridge Wells",
    "sg:classifiers":[
        {
            "category":"Government",
            "subcategory":"Post Office",
            "type":"Public Place"
        }
    ],
    "sg:phone":"+44 1892 547571",
    "sg:postcode":"TN1 2QT",
    "sg:province":"Kent",
    "sg:tags":[
        "messenger",
        "courier"
    ],
    "wof:name":"A L C",
    "wof:placetype":"venue"
},
  "geometry": {"coordinates":[0.270135,51.136395],"type":"Point"}
}