{
  "type": "Feature",
  "properties": {
    "addr:full":"8-15 The Arches, Archway Close, Endeavour Way London Greater London SW19 8UL",
    "addr:housenumber":"8-15;arches",
    "addr:postcode":"sw19 8ul",
    "addr:street":"The;Archway Close Endeavour Way",
    "iso:country":"GB",
    "sg:address":"8-15 The Arches, Archway Close, Endeavour Way",
    "sg:city":"London",
    "sg:classifiers":[
        {
            "category":"Manufacturing",
            "subcategory":"Building Materials",
            "type":"Manufacturing & Wholesale Goods"
        }
    ],
    "sg:phone":"+44 20 8947 6909",
    "sg:postcode":"SW19 8UL",
    "sg:province":"Greater London",
    "sg:tags":[
        "merchant",
        "builder"
    ],
    "wof:name":"Builders Center",
    "wof:placetype":"venue"
},
  "geometry": {"coordinates":[-0.1945700049,51.4326210022],"type":"Point"}
}