{
  "type": "Feature",
  "properties": {
    "iso:country":"GB",
    "sg:address":"Unit A3 Claire Road Industrial Estate, Kirby Cross",
    "sg:city":"Frinton-on-sea",
    "sg:classifiers":[
        {
            "category":"Manufacturing",
            "subcategory":"Petroleum Products",
            "type":"Manufacturing & Wholesale Goods"
        }
    ],
    "sg:phone":"+44 1255 850255",
    "sg:postcode":"CO13 0LY",
    "sg:province":"Essex",
    "sg:tags":[
        "double",
        "glazing"
    ],
    "wof:name":"A & P Carrington",
    "wof:placetype":"venue"
},
  "geometry": {"coordinates":[1.217081,51.841431],"type":"Point"}
}