{
  "type": "Feature",
  "properties": {
    "iso:country":"GB",
    "sg:address":"Heathfield House, 91 Heathfield",
    "sg:city":"Swansea",
    "sg:classifiers":[
        {
            "category":"Professional",
            "type":"Services"
        }
    ],
    "sg:phone":"+44 1792 655208",
    "sg:postcode":"SA1 6EL",
    "sg:province":"Neath Port Talbot",
    "sg:tags":[
        "archaeologist"
    ],
    "wof:name":"The Glamorgan-Gwent Archaeological Trust Ltd.",
    "wof:placetype":"venue"
},
  "geometry": {"coordinates":[-3.952489,51.621731],"type":"Point"}
}