{
  "type": "Feature",
  "properties": {
    "iso:country":"GB",
    "sg:address":"14 Follyhall Road, Wibsey",
    "sg:city":"Bradford",
    "sg:classifiers":[
        {
            "category":"Professional",
            "subcategory":"Engineering",
            "type":"Services"
        }
    ],
    "sg:postcode":"BD6 1UN",
    "sg:province":"West Yorkshire",
    "sg:tags":[
        "contractor",
        "electrical",
        "engineer"
    ],
    "wof:name":"D B M Electrical",
    "wof:placetype":"venue"
},
  "geometry": {"coordinates":[-1.7757220268,53.7664489746],"type":"Point"}
}