{
  "type": "Feature",
  "properties": {
    "iso:country":"GB",
    "sg:address":"27 Firs Hill Ave",
    "sg:city":"Sheffield",
    "sg:classifiers":[
        {
            "category":"Personal",
            "subcategory":"Tanning Parlor",
            "type":"Services"
        }
    ],
    "sg:postcode":"S4 7AA",
    "sg:province":"South Yorkshire",
    "sg:tags":[
        "sunbeds"
    ],
    "wof:name":"C N C Sunbeds",
    "wof:placetype":"venue"
},
  "geometry": {"coordinates":[-1.462671,53.403889],"type":"Point"}
}