{
  "type": "Feature",
  "properties": {
    "addr:full":"Uit 3 The Old Quarry, Cemetery Rd, Abercarn Newport Blaenau Gwent NP11 5AQ",
    "addr:housenumber":"3",
    "addr:postcode":"np11 5aq",
    "addr:street":"Uit;The Old Quarry Cemetery Rd",
    "iso:country":"GB",
    "sg:address":"Uit 3 The Old Quarry, Cemetery Rd, Abercarn",
    "sg:city":"Newport",
    "sg:classifiers":[
        {
            "category":"Home & Garden",
            "subcategory":"Hardware",
            "type":"Retail Goods"
        }
    ],
    "sg:postcode":"NP11 5AQ",
    "sg:province":"Blaenau Gwent",
    "sg:tags":[
        "paint",
        "coating"
    ],
    "wof:name":"Willcocks Coatings",
    "wof:placetype":"venue"
},
  "geometry": {"coordinates":[-3.134824,51.647129],"type":"Point"}
}