{
  "type": "Feature",
  "properties": {
    "iso:country":"GB",
    "sg:address":"77 Westgate",
    "sg:city":"Wakefield",
    "sg:classifiers":[
        {
            "category":"Health Services",
            "subcategory":"Optometrist",
            "type":"Services"
        }
    ],
    "sg:phone":"+44 1924 374282",
    "sg:postcode":"WF1 1EP",
    "sg:province":"West Yorkshire",
    "sg:tags":[
        "optician"
    ],
    "wof:name":"Patterson Opticians",
    "wof:placetype":"venue"
},
  "geometry": {"coordinates":[-1.502149,53.681927],"type":"Point"}
}