{
  "type": "Feature",
  "properties": {
    "iso:country":"GB",
    "sg:address":"55 Queen St",
    "sg:city":"Glasgow",
    "sg:classifiers":[
        {
            "category":"Shopping",
            "subcategory":"Clothing, Apparel, & Fashions",
            "type":"Retail Goods"
        }
    ],
    "sg:phone":"+44 141 572 0142",
    "sg:postcode":"G1 3EN",
    "sg:province":"Glasgow City",
    "sg:tags":[
        "shop"
    ],
    "wof:name":"Penelope's Pitstop",
    "wof:placetype":"venue"
},
  "geometry": {"coordinates":[-4.252525,55.859013],"type":"Point"}
}