{
  "type": "Feature",
  "properties": {
    "addr:full":"21 Albert Drive, Victoria Estate Burgess Hill East Sussex RH15 9YZ",
    "addr:housenumber":"21",
    "addr:postcode":"rh15 9yz",
    "addr:street":"Albert Drive;Hill",
    "iso:country":"GB",
    "sg:address":"21 Albert Drive, Victoria Estate",
    "sg:city":"Burgess Hill",
    "sg:classifiers":[
        {
            "category":"Professional",
            "subcategory":"Printing & Photocopies",
            "type":"Services"
        }
    ],
    "sg:phone":"+44 1444 247581",
    "sg:postcode":"RH15 9YZ",
    "sg:province":"East Sussex",
    "sg:tags":[
        "process",
        "screen",
        "printer"
    ],
    "wof:name":"Danielson Ltd.",
    "wof:placetype":"venue"
},
  "geometry": {"coordinates":[-0.145536,50.951942],"type":"Point"}
}