{
  "type": "Feature",
  "properties": {
    "addr:full":"21b Milford Street Salisbury Wiltshire SP1 2AP",
    "addr:housenumber":"21b",
    "addr:postcode":"sp1 2ap",
    "addr:street":"Milford Street",
    "iso:country":"GB",
    "sg:address":"21b Milford Street",
    "sg:city":"Salisbury",
    "sg:classifiers":[
        {
            "category":"Shopping",
            "subcategory":"Clothing, Apparel, & Fashions",
            "type":"Retail Goods"
        }
    ],
    "sg:phone":"+44 1722 410522",
    "sg:postcode":"SP1 2AP",
    "sg:province":"Wiltshire",
    "sg:tags":[
        "shop"
    ],
    "wof:name":"Twenty One B",
    "wof:placetype":"venue"
},
  "geometry": {"coordinates":[-1.7923289537,51.0687637329],"type":"Point"}
}