{
  "type": "Feature",
  "properties": {
    "addr:full":"Roseleigh, Lime Kiln Road, Gayton King's Lynn Norfolk PE32 1QT",
    "addr:postcode":"pe32 1qt",
    "addr:street":"Lime Kiln Road;Lynn",
    "iso:country":"GB",
    "sg:address":"Roseleigh, Lime Kiln Road, Gayton",
    "sg:city":"King's Lynn",
    "sg:classifiers":[
        {
            "category":"Building & Trades",
            "subcategory":"Construction",
            "type":"Services"
        },
        {
            "category":"Local Transit",
            "type":"Transportation"
        }
    ],
    "sg:phone":"+44 1553 636231",
    "sg:postcode":"PE32 1QT",
    "sg:province":"Norfolk",
    "sg:tags":[
        "surfacers",
        "surfacing",
        "road"
    ],
    "wof:name":"Howard Hire Roadsweepers",
    "wof:placetype":"venue"
},
  "geometry": {"coordinates":[0.5586599708,52.7456512451],"type":"Point"}
}