{
  "type": "Feature",
  "properties": {
    "iso:country":"GB",
    "sg:address":"47-48 Priory Centre",
    "sg:city":"Worksop",
    "sg:classifiers":[
        {
            "category":"Recreation",
            "subcategory":"Amusement Park",
            "type":"Entertainment"
        }
    ],
    "sg:postcode":"S80 1JR",
    "sg:province":"Nottinghamshire",
    "sg:tags":[
        "arcade"
    ],
    "wof:name":"Twin Leisure Ltd.",
    "wof:placetype":"venue"
},
  "geometry": {"coordinates":[-1.126649,53.305229],"type":"Point"}
}