{
  "type": "Feature",
  "properties": {
    "addr:full":"32 Grotto Rd, Cliftonville Margate Kent CT9 2BT",
    "addr:housenumber":"32",
    "addr:postcode":"ct9 2bt",
    "addr:street":"Grotto Rd;Margate",
    "iso:country":"GB",
    "sg:address":"32 Grotto Rd, Cliftonville",
    "sg:city":"Margate",
    "sg:classifiers":[
        {
            "category":"Communications",
            "type":"Services"
        }
    ],
    "sg:phone":"+44 1843 299095",
    "sg:postcode":"CT9 2BT",
    "sg:province":"Kent",
    "sg:tags":[
        "tv",
        "video",
        "radio"
    ],
    "wof:name":"Alpine Aerials",
    "wof:placetype":"venue"
},
  "geometry": {"coordinates":[1.390755,51.387962],"type":"Point"}
}