{
  "type": "Feature",
  "properties": {
    "addr:full":"43-61 Brighton Road Shoreham-by-sea West Sussex BN43 6RE",
    "addr:housenumber":"43-61",
    "addr:postcode":"bn43 6re",
    "addr:street":"Brighton Road",
    "iso:country":"GB",
    "sg:address":"43-61 Brighton Road",
    "sg:city":"Shoreham-by-sea",
    "sg:classifiers":[
        {
            "category":"Home & Garden",
            "subcategory":"Hardware",
            "type":"Retail Goods"
        }
    ],
    "sg:phone":"+44 1273 463423",
    "sg:postcode":"BN43 6RE",
    "sg:province":"West Sussex",
    "sg:tags":[
        "retailer",
        "diy"
    ],
    "wof:name":"B & Q Diy Supercentre",
    "wof:placetype":"venue"
},
  "geometry": {"coordinates":[-0.2478210032,50.8311920166],"type":"Point"}
}