{
  "type": "Feature",
  "properties": {
    "iso:country":"GB",
    "sg:address":"Po Box 15",
    "sg:city":"Hatfield",
    "sg:classifiers":[
        {
            "category":"Professional",
            "subcategory":"Employment Agencies",
            "type":"Services"
        }
    ],
    "sg:phone":"+44 1582 834848",
    "sg:postcode":"AL10 0SF",
    "sg:province":"Hertfordshire",
    "sg:tags":[
        "consultant"
    ],
    "wof:name":"Red Sky Ltd.",
    "wof:placetype":"venue"
},
  "geometry": {"coordinates":[-0.2261089981,51.764831543],"type":"Point"}
}