{
  "type": "Feature",
  "properties": {
    "addr:full":"2 Holbeth Road Dunfermline Fife KY12 7QX",
    "addr:housenumber":"2",
    "addr:postcode":"ky12 7qx",
    "addr:street":"Holbeth Road",
    "iso:country":"GB",
    "sg:address":"2 Holbeth Road",
    "sg:city":"Dunfermline",
    "sg:classifiers":[
        {
            "category":"Organizations",
            "subcategory":"Non-profit Organization",
            "type":"Services"
        }
    ],
    "sg:phone":"+44 1383 624382",
    "sg:postcode":"KY12 7QX",
    "sg:province":"Fife",
    "sg:tags":[
        "organisation",
        "voluntary",
        "charity"
    ],
    "wof:name":"Dunfernline Advocacy Initiative",
    "wof:placetype":"venue"
},
  "geometry": {"coordinates":[-3.444206,56.074631],"type":"Point"}
}