{
  "type": "Feature",
  "properties": {
    "addr:full":"18 Ownsted Hill Croydon Surrey CR0 0JQ",
    "addr:housenumber":"18",
    "addr:postcode":"cr0 0jq",
    "addr:street":"Ownsted Hill",
    "iso:country":"GB",
    "sg:address":"18 Ownsted Hill",
    "sg:city":"Croydon",
    "sg:classifiers":[
        {
            "category":"Building & Trades",
            "subcategory":"Construction",
            "type":"Services"
        }
    ],
    "sg:phone":"+44 1689 848172",
    "sg:postcode":"CR0 0JQ",
    "sg:province":"Surrey",
    "sg:tags":[
        "tiling",
        "contractor"
    ],
    "wof:name":"Terry Townsend",
    "wof:placetype":"venue"
},
  "geometry": {"coordinates":[-0.0127520002,51.3425216675],"type":"Point"}
}