{
  "type": "Feature",
  "properties": {
    "addr:full":"42 Portman Rd Reading Berkshire RG30 1EA",
    "addr:housenumber":"42",
    "addr:postcode":"rg30 1ea",
    "addr:street":"Portman Rd",
    "iso:country":"GB",
    "sg:address":"42 Portman Rd",
    "sg:city":"Reading",
    "sg:classifiers":[
        {
            "category":"Real Estate",
            "subcategory":"Architect",
            "type":"Services"
        }
    ],
    "sg:phone":"+44 118 957 3200",
    "sg:postcode":"RG30 1EA",
    "sg:province":"Berkshire",
    "sg:tags":[
        "architectural"
    ],
    "wof:name":"Hunt Ian",
    "wof:placetype":"venue"
},
  "geometry": {"coordinates":[-1.0043159723,51.4615440369],"type":"Point"}
}