{
  "type": "Feature",
  "properties": {
    "iso:country":"GB",
    "sg:address":"118 Harrington Road",
    "sg:city":"Bristol",
    "sg:classifiers":[
        {
            "category":"Retail",
            "subcategory":"Repair Shop",
            "type":"Services"
        }
    ],
    "sg:phone":"+44 1275 834628",
    "sg:postcode":"BS14 8JR",
    "sg:province":"City of Bristol",
    "sg:tags":[
        "maintenance"
    ],
    "wof:name":"David Veal & Sons Building Maintenance",
    "wof:placetype":"venue"
},
  "geometry": {"coordinates":[-2.542987,51.417038],"type":"Point"}
}