{
  "type": "Feature",
  "properties": {
    "iso:country":"GB",
    "sg:address":"12 Commercial Road, Bulwell",
    "sg:city":"Nottingham",
    "sg:classifiers":[
        {
            "category":"Real Estate",
            "subcategory":"Real Estate Agent",
            "type":"Services"
        }
    ],
    "sg:phone":"+44 115 975 2220",
    "sg:postcode":"NG6 8HA",
    "sg:province":"Nottinghamshire",
    "wof:name":"Halifax Property Services",
    "wof:placetype":"venue"
},
  "geometry": {"coordinates":[-1.19996,53.002388],"type":"Point"}
}