{
  "type": "Feature",
  "properties": {
    "iso:country":"GB",
    "sg:address":"Cross Inn Farm",
    "sg:city":"Llanfyrnach",
    "sg:classifiers":[
        {
            "category":"Banks & Credit Unions",
            "subcategory":"Investment Brokerage",
            "type":"Services"
        }
    ],
    "sg:phone":"+44 1239 698224",
    "sg:postcode":"SA35 0AH",
    "sg:province":"Carmarthenshire",
    "sg:tags":[
        "contractor"
    ],
    "wof:name":"Gethin Thomas",
    "wof:placetype":"venue"
},
  "geometry": {"coordinates":[-4.589888,51.951145],"type":"Point"}
}