{
  "type": "Feature",
  "properties": {
    "addr:full":"Stirchley Road, Stirchley Telford Shropshire TF3 1DY",
    "addr:postcode":"tf3 1dy",
    "addr:street":"Stirchley Road",
    "iso:country":"GB",
    "sg:address":"Stirchley Road, Stirchley",
    "sg:city":"Telford",
    "sg:classifiers":[
        {
            "category":"Bars & Pubs",
            "type":"Food & Drink"
        }
    ],
    "sg:phone":"+44 1952 590453",
    "sg:postcode":"TF3 1DY",
    "sg:province":"Shropshire",
    "sg:tags":[
        "pubs",
        "inn"
    ],
    "wof:name":"Rose & Crown",
    "wof:placetype":"venue"
},
  "geometry": {"coordinates":[-2.444429,52.658443],"type":"Point"}
}