{
  "type": "Feature",
  "properties": {
    "iso:country":"GB",
    "sg:address":"Whalley Road",
    "sg:city":"Manchester",
    "sg:classifiers":[
        {
            "category":"Education",
            "subcategory":"School",
            "type":"Public Place"
        }
    ],
    "sg:phone":"+44 161 226 2767",
    "sg:postcode":"M16 8AW",
    "sg:province":"Cheshire",
    "sg:tags":[
        "local",
        "authority"
    ],
    "wof:name":"Our Lady's R C Primary School",
    "wof:placetype":"venue"
},
  "geometry": {"coordinates":[-2.252719,53.450321],"type":"Point"}
}