{
  "type": "Feature",
  "properties": {
    "iso:country":"GB",
    "sg:address":"99 Queen St, Morley",
    "sg:city":"Leeds",
    "sg:classifiers":[
        {
            "category":"Shopping",
            "subcategory":"Clothing, Apparel, & Fashions",
            "type":"Retail Goods"
        }
    ],
    "sg:phone":"+44 113 252 5826",
    "sg:postcode":"LS27 8DW",
    "sg:province":"West Yorkshire",
    "sg:tags":[
        "shop"
    ],
    "wof:name":"Faded Glory",
    "wof:placetype":"venue"
},
  "geometry": {"coordinates":[-1.600522,53.744904],"type":"Point"}
}