{
  "type": "Feature",
  "properties": {
    "addr:full":"Birthwaithe Business Park Barnsley South Yorkshire S75 5JS",
    "addr:postcode":"s75 5js",
    "addr:street":"Business Park;Yorkshire",
    "iso:country":"GB",
    "sg:address":"Birthwaithe Business Park",
    "sg:city":"Barnsley",
    "sg:classifiers":[
        {
            "category":"Building & Trades",
            "subcategory":"Construction",
            "type":"Services"
        }
    ],
    "sg:phone":"+44 1226 383434",
    "sg:postcode":"S75 5JS",
    "sg:province":"South Yorkshire",
    "sg:tags":[
        "window",
        "sale"
    ],
    "wof:name":"Premdor U K Holdings Ltd.",
    "wof:placetype":"venue"
},
  "geometry": {"coordinates":[-1.54698,53.590019],"type":"Point"}
}