{
  "type": "Feature",
  "properties": {
    "addr:full":"Churchill Street Wallsend Tyne and Wear NE28 7TN",
    "addr:postcode":"ne28 7tn",
    "addr:street":"Churchill Street",
    "iso:country":"GB",
    "sg:address":"Churchill Street",
    "sg:city":"Wallsend",
    "sg:classifiers":[
        {
            "category":"Education",
            "subcategory":"School",
            "type":"Public Place"
        }
    ],
    "sg:phone":"+44 191 200 7260",
    "sg:postcode":"NE28 7TN",
    "sg:province":"Tyne and Wear",
    "sg:tags":[
        "local",
        "authority"
    ],
    "wof:name":"Willington Community High School",
    "wof:placetype":"venue"
},
  "geometry": {"coordinates":[-1.506564,55.006618],"type":"Point"}
}