{
  "type": "Feature",
  "properties": {
    "addr:full":"Preston Park House, South Road Brighton East Sussex BN1 6SB",
    "addr:postcode":"bn1 6sb",
    "addr:street":"South Road",
    "iso:country":"GB",
    "sg:address":"Preston Park House, South Road",
    "sg:city":"Brighton",
    "sg:classifiers":[
        {
            "category":"Restaurant",
            "type":"Food & Drink"
        }
    ],
    "sg:phone":"+44 1323 416808",
    "sg:postcode":"BN1 6SB",
    "sg:province":"East Sussex",
    "wof:name":"Sports Track Ltd.",
    "wof:placetype":"venue"
},
  "geometry": {"coordinates":[-0.1523389965,50.8423538208],"type":"Point"}
}