{
  "type": "Feature",
  "properties": {
    "addr:full":"2 Greenwich Crescent London Greater London E6 4TU",
    "addr:housenumber":"2",
    "addr:postcode":"e6 4tu",
    "addr:street":"Greenwich Crescent",
    "iso:country":"GB",
    "sg:address":"2 Greenwich Crescent",
    "sg:city":"London",
    "sg:classifiers":[
        {
            "category":"Professional",
            "subcategory":"Computer Services",
            "type":"Services"
        }
    ],
    "sg:phone":"+44 20 7473 4455",
    "sg:postcode":"E6 4TU",
    "sg:province":"Greater London",
    "sg:tags":[
        "system",
        "software"
    ],
    "wof:name":"Active Data Solutions",
    "wof:placetype":"venue"
},
  "geometry": {"coordinates":[-0.057289999,51.515296936],"type":"Point"}
}