{
  "type": "Feature",
  "properties": {
    "addr:full":"7b Avenue Square, Stewarton Kilmarnock East Ayrshire KA3 5AB",
    "addr:housenumber":"7b",
    "addr:postcode":"ka3 5ab",
    "addr:street":"Avenue Square Stewarton",
    "iso:country":"GB",
    "sg:address":"7b Avenue Square, Stewarton",
    "sg:city":"Kilmarnock",
    "sg:classifiers":[
        {
            "category":"Personal",
            "subcategory":"Beauty Salon",
            "type":"Services"
        },
        {
            "category":"Personal",
            "subcategory":"Barber",
            "type":"Services"
        }
    ],
    "sg:phone":"+44 1560 485365",
    "sg:postcode":"KA3 5AB",
    "sg:province":"East Ayrshire",
    "sg:tags":[
        "unisex",
        "hairdresser"
    ],
    "wof:name":"Hairstop",
    "wof:placetype":"venue"
},
  "geometry": {"coordinates":[-4.5148820877,55.6810379028],"type":"Point"}
}