{
  "type": "Feature",
  "properties": {
    "addr:full":"Unit A2, Wyther Lane Indstl Est Leeds West Yorkshire LS5 3BT",
    "addr:postcode":"ls5 3bt",
    "addr:street":"Wyther Lane Indstl Est",
    "iso:country":"GB",
    "sg:address":"Unit A2, Wyther Lane Indstl Est",
    "sg:city":"Leeds",
    "sg:classifiers":[
        {
            "category":"Professional",
            "subcategory":"Printing & Photocopies",
            "type":"Services"
        }
    ],
    "sg:phone":"+44 113 274 6767",
    "sg:postcode":"LS5 3BT",
    "sg:province":"West Yorkshire",
    "sg:tags":[
        "printer"
    ],
    "wof:name":"Colortone Repro Services Ltd",
    "wof:placetype":"venue"
},
  "geometry": {"coordinates":[-1.6071909666,53.8131752014],"type":"Point"}
}