{
  "type": "Feature",
  "properties": {
    "iso:country":"GB",
    "sg:address":"24 Church Street",
    "sg:city":"Monmouth",
    "sg:classifiers":[
        {
            "category":"Manufacturing",
            "subcategory":"Lumber",
            "type":"Manufacturing & Wholesale Goods"
        }
    ],
    "sg:phone":"+44 1600 712688",
    "sg:postcode":"NP25 3BU",
    "sg:province":"Gloucestershire",
    "sg:tags":[
        "importer",
        "merchants",
        "agent",
        "timber"
    ],
    "wof:name":"Intertimber Ltd.",
    "wof:placetype":"venue"
},
  "geometry": {"coordinates":[-2.7144289017,51.8128967285],"type":"Point"}
}