{
  "type": "Feature",
  "properties": {
    "iso:country":"GB",
    "sg:address":"102 Watergate Street",
    "sg:city":"Chester",
    "sg:classifiers":[
        {
            "category":"Travel",
            "subcategory":"Hostel",
            "type":"Entertainment"
        },
        {
            "category":"Organizations",
            "subcategory":"Community Association",
            "type":"Services"
        }
    ],
    "sg:phone":"+44 1244 347122",
    "sg:postcode":"CH1 2LF",
    "sg:province":"Cheshire",
    "sg:tags":[
        "co-operatives",
        "society",
        "housing",
        "trust"
    ],
    "wof:name":"Stonham Housing Association Ltd",
    "wof:placetype":"venue"
},
  "geometry": {"coordinates":[-2.8944690228,53.1898117065],"type":"Point"}
}