{
  "type": "Feature",
  "properties": {
    "addr:full":"1106 London Rd London Greater London SW16 4DT",
    "addr:housenumber":"1106",
    "addr:postcode":"sw16 4dt",
    "addr:street":"London Rd",
    "iso:country":"GB",
    "sg:address":"1106 London Rd",
    "sg:city":"London",
    "sg:classifiers":[
        {
            "category":"Shopping",
            "subcategory":"Department Store",
            "type":"Retail Goods"
        }
    ],
    "sg:postcode":"SW16 4DT",
    "sg:province":"Greater London",
    "wof:name":"137 (Norbury) Grocers",
    "wof:placetype":"venue"
},
  "geometry": {"coordinates":[-0.11863,51.402321],"type":"Point"}
}