{
  "type": "Feature",
  "properties": {
    "iso:country":"GB",
    "sg:address":"34 Lower Addiscombe Road",
    "sg:city":"Croydon",
    "sg:classifiers":[
        {
            "category":"Social Services",
            "subcategory":"Job Training",
            "type":"Services"
        }
    ],
    "sg:phone":"+44 20 8686 6844",
    "sg:postcode":"CR0 6AA",
    "sg:province":"Surrey",
    "sg:tags":[
        "draughtsman",
        "drawing"
    ],
    "wof:name":"Project Co-Ordination Ltd.",
    "wof:placetype":"venue"
},
  "geometry": {"coordinates":[-0.088227,51.380505],"type":"Point"}
}