{
  "type": "Feature",
  "properties": {
    "iso:country":"GB",
    "sg:address":"343 Weston Coyney Road, Weston Coyney",
    "sg:city":"Stoke-on-trent",
    "sg:classifiers":[
        {
            "category":"Health Services",
            "subcategory":"Dentist",
            "type":"Services"
        }
    ],
    "sg:phone":"+44 1782 313232",
    "sg:postcode":"ST3 6ES",
    "sg:province":"Staffordshire",
    "wof:name":"Charles M Toh",
    "wof:placetype":"venue"
},
  "geometry": {"coordinates":[-2.1057078838,52.9894981384],"type":"Point"}
}