{
  "type": "Feature",
  "properties": {
    "addr:full":"1 Western Rd St Leonards On Sea East Sussex TN37 6DG",
    "addr:housenumber":"1",
    "addr:postcode":"tn37 6dg",
    "addr:street":"Western Rd St",
    "iso:country":"GB",
    "sg:address":"1 Western Rd",
    "sg:city":"St Leonards On Sea",
    "sg:classifiers":[
        {
            "category":"Cafe",
            "type":"Food & Drink"
        }
    ],
    "sg:phone":"+44 1424 437411",
    "sg:postcode":"TN37 6DG",
    "sg:province":"East Sussex",
    "sg:tags":[
        "tea",
        "room"
    ],
    "wof:name":"Slap Ups",
    "wof:placetype":"venue"
},
  "geometry": {"coordinates":[0.561522,50.852501],"type":"Point"}
}