{
  "type": "Feature",
  "properties": {
    "iso:country":"GB",
    "sg:address":"Office 4, Holland Park Indstl Est, Cyttir Rd",
    "sg:city":"Holyhead",
    "sg:classifiers":[
        {
            "category":"Manufacturing",
            "subcategory":"Rubber & Plastics",
            "type":"Manufacturing & Wholesale Goods"
        }
    ],
    "sg:phone":"+44 1407 762345",
    "sg:postcode":"LL65 2PU",
    "sg:province":"Isle of Anglesey",
    "sg:tags":[
        "injection",
        "moulding"
    ],
    "wof:name":"Adtag Marketing Ltd",
    "wof:placetype":"venue"
},
  "geometry": {"coordinates":[-4.630714,53.30637],"type":"Point"}
}