{
  "type": "Feature",
  "properties": {
    "addr:full":"The Old Bakehouse, Caberston Road Walkerburn Scottish Borders EH43 6AU",
    "addr:postcode":"eh43 6au",
    "addr:street":"Caberston Road",
    "iso:country":"GB",
    "sg:address":"The Old Bakehouse, Caberston Road",
    "sg:city":"Walkerburn",
    "sg:classifiers":[
        {
            "category":"Building & Trades",
            "subcategory":"Construction",
            "type":"Services"
        }
    ],
    "sg:postcode":"EH43 6AU",
    "sg:province":"Scottish Borders",
    "sg:tags":[
        "joiner",
        "carpenter"
    ],
    "wof:name":"E Fraser Joiners",
    "wof:placetype":"venue"
},
  "geometry": {"coordinates":[-3.018695,55.623707],"type":"Point"}
}