{
  "type": "Feature",
  "properties": {
    "addr:full":"7 Wood Acre Clo, Long Ashes Park Skipton Lancashire BD23 5PF",
    "addr:housenumber":"7",
    "addr:postcode":"bd23 5pf",
    "addr:street":"Wood Acre Clo Long Ashes Park",
    "iso:country":"GB",
    "sg:address":"7 Wood Acre Clo, Long Ashes Park",
    "sg:city":"Skipton",
    "sg:classifiers":[
        {
            "category":"Education",
            "subcategory":"Dance Studio",
            "type":"Public Place"
        }
    ],
    "sg:phone":"+44 1756 753247",
    "sg:postcode":"BD23 5PF",
    "sg:province":"Lancashire",
    "sg:tags":[
        "school",
        "dancing"
    ],
    "wof:name":"Northern Dance Centre",
    "wof:placetype":"venue"
},
  "geometry": {"coordinates":[-2.0297350883,54.0790863037],"type":"Point"}
}