{
  "type": "Feature",
  "properties": {
    "addr:full":"Po Box 8755 Biggar Dumfries and Galloway ML12 6YJ",
    "addr:housenumber":"po;8755",
    "addr:postcode":"ml12 6yj",
    "addr:street":"Box",
    "iso:country":"GB",
    "sg:address":"Po Box 8755",
    "sg:city":"Biggar",
    "sg:classifiers":[
        {
            "category":"Banks & Credit Unions",
            "subcategory":"Financial Services",
            "type":"Services"
        }
    ],
    "sg:phone":"+44 1899 220666",
    "sg:postcode":"ML12 6YJ",
    "sg:province":"Dumfries and Galloway",
    "sg:tags":[
        "claim",
        "assessor"
    ],
    "wof:name":"David McIlvenna",
    "wof:placetype":"venue"
},
  "geometry": {"coordinates":[-3.613829,55.56908],"type":"Point"}
}