{
  "type": "Feature",
  "properties": {
    "iso:country":"GB",
    "sg:address":"46 The Village, Haxby",
    "sg:city":"York",
    "sg:classifiers":[
        {
            "category":"Banks & Credit Unions",
            "subcategory":"Bank",
            "type":"Services"
        }
    ],
    "sg:phone":"+44 1904 882200",
    "sg:postcode":"YO32 2HX",
    "sg:province":"North Yorkshire",
    "sg:tags":[
        "financial",
        "institution"
    ],
    "sg:website":"http://www.barclays.co.uk",
    "wof:name":"Barclays Bank Plc",
    "wof:placetype":"venue"
},
  "geometry": {"coordinates":[-1.086753,54.01931],"type":"Point"}
}