{
  "type": "Feature",
  "properties": {
    "addr:full":"35 West Park London Greater London SE9 4RZ",
    "addr:housenumber":"35",
    "addr:postcode":"se9 4rz",
    "addr:street":"West Park",
    "iso:country":"GB",
    "sg:address":"35 West Park",
    "sg:city":"London",
    "sg:classifiers":[
        {
            "category":"Building & Trades",
            "subcategory":"Plumbing",
            "type":"Services"
        }
    ],
    "sg:postcode":"SE9 4RZ",
    "sg:province":"Greater London",
    "sg:tags":[
        "plumber",
        "heating"
    ],
    "wof:name":"Anthony L & Mark Edward Harris",
    "wof:placetype":"venue"
},
  "geometry": {"coordinates":[0.046108,51.4385299683],"type":"Point"}
}