{
  "type": "Feature",
  "properties": {
    "iso:country":"GB",
    "sg:address":"Carr Farm, Carr Lane, Wilberfoss",
    "sg:city":"York",
    "sg:classifiers":[
        {
            "category":"Farming",
            "subcategory":"Livestock Farm",
            "type":"Manufacturing & Wholesale Goods"
        }
    ],
    "sg:phone":"+44 1759 380243",
    "sg:postcode":"YO41 5PG",
    "sg:province":"East Riding of Yorkshire",
    "sg:tags":[
        "others"
    ],
    "wof:name":"B R Barker",
    "wof:placetype":"venue"
},
  "geometry": {"coordinates":[-0.8852710128,53.9464912415],"type":"Point"}
}