{
  "type": "Feature",
  "properties": {
    "addr:full":"Orchard Hill Farm, Upper Clatford Andover Hampshire SP11 7HA",
    "addr:housenumber":"clatford",
    "addr:postcode":"sp11 7ha",
    "addr:street":"Orchard Hill",
    "iso:country":"GB",
    "sg:address":"Orchard Hill Farm, Upper Clatford",
    "sg:city":"Andover",
    "sg:classifiers":[
        {
            "category":"Shopping",
            "subcategory":"Stationery & Office Supplies",
            "type":"Retail Goods"
        }
    ],
    "sg:phone":"+44 1264 332234",
    "sg:postcode":"SP11 7HA",
    "sg:province":"Hampshire",
    "wof:name":"South Western Litho",
    "wof:placetype":"venue"
},
  "geometry": {"coordinates":[-1.49565804,51.1931266785],"type":"Point"}
}