{
  "type": "Feature",
  "properties": {
    "iso:country":"GB",
    "sg:address":"9 Elder Mount",
    "sg:city":"Leeds",
    "sg:classifiers":[
        {
            "category":"Health Services",
            "subcategory":"Dentist",
            "type":"Services"
        }
    ],
    "sg:phone":"+44 113 236 1442",
    "sg:postcode":"LS13 4BQ",
    "sg:province":"West Yorkshire",
    "sg:tags":[
        "technician",
        "dental"
    ],
    "wof:name":"Bramley Dental Ceramics",
    "wof:placetype":"venue"
},
  "geometry": {"coordinates":[-1.631994009,53.8057746887],"type":"Point"}
}