{
  "type": "Feature",
  "properties": {
    "addr:full":"92 Arnside Av Oldham Lancashire OL9 9DJ",
    "addr:housenumber":"92",
    "addr:postcode":"ol9 9dj",
    "addr:street":"Arnside Av Oldham",
    "iso:country":"GB",
    "sg:address":"92 Arnside Av",
    "sg:city":"Oldham",
    "sg:classifiers":[
        {
            "category":"Building & Trades",
            "subcategory":"Plumbing",
            "type":"Services"
        }
    ],
    "sg:phone":"+44 161 652 1783",
    "sg:postcode":"OL9 9DJ",
    "sg:province":"Lancashire",
    "sg:tags":[
        "central",
        "heating"
    ],
    "wof:name":"M Howarth",
    "wof:placetype":"venue"
},
  "geometry": {"coordinates":[-2.1481289864,53.5383911133],"type":"Point"}
}