{
  "type": "Feature",
  "properties": {
    "addr:full":"12 Ridgeway, Holywell Whitley Bay Northumberland NE25 0PH",
    "addr:housenumber":"12",
    "addr:postcode":"ne25 0ph",
    "addr:street":"Ridgeway",
    "iso:country":"GB",
    "sg:address":"12 Ridgeway, Holywell",
    "sg:city":"Whitley Bay",
    "sg:classifiers":[
        {
            "category":"Building & Trades",
            "subcategory":"Construction",
            "type":"Services"
        }
    ],
    "sg:phone":"+44 191 237 3017",
    "sg:postcode":"NE25 0PH",
    "sg:province":"Northumberland",
    "sg:tags":[
        "builder"
    ],
    "wof:name":"Joseph Gardner Dixon",
    "wof:placetype":"venue"
},
  "geometry": {"coordinates":[-1.5204859972,55.0725631714],"type":"Point"}
}