{
  "type": "Feature",
  "properties": {
    "addr:full":"53 Durleston Park Drive, Bookham Leatherhead Surrey KT23 4AJ",
    "addr:housenumber":"53",
    "addr:postcode":"kt23 4aj",
    "addr:street":"Durleston Park Drive",
    "iso:country":"GB",
    "sg:address":"53 Durleston Park Drive, Bookham",
    "sg:city":"Leatherhead",
    "sg:classifiers":[
        {
            "category":"Communications",
            "subcategory":"Film & Video Production",
            "type":"Services"
        },
        {
            "category":"Communications",
            "type":"Services"
        }
    ],
    "sg:phone":"+44 1372 451679",
    "sg:postcode":"KT23 4AJ",
    "sg:province":"Surrey",
    "sg:tags":[
        "equipment",
        "audio-visual"
    ],
    "wof:name":"P D Video Services",
    "wof:placetype":"venue"
},
  "geometry": {"coordinates":[-0.362405,51.283836],"type":"Point"}
}