{
  "type": "Feature",
  "properties": {
    "iso:country":"GB",
    "sg:address":"Masters House, Guildford Road, Westcott",
    "sg:city":"Dorking",
    "sg:classifiers":[
        {
            "category":"Home & Garden",
            "subcategory":"Household Appliances",
            "type":"Retail Goods"
        }
    ],
    "sg:postcode":"RH4 3NG",
    "sg:province":"Surrey",
    "sg:tags":[
        "refrigeration",
        "air conditioning"
    ],
    "wof:name":"Industrial Air Systems (London) Ltd.",
    "wof:placetype":"venue"
},
  "geometry": {"coordinates":[-0.3570789993,51.2265510559],"type":"Point"}
}