{
  "type": "Feature",
  "properties": {
    "iso:country":"GB",
    "sg:address":"Windsor Court, Thurnscoe",
    "sg:city":"Rotherham",
    "sg:classifiers":[
        {
            "category":"Social Services",
            "subcategory":"Adult Care",
            "type":"Services"
        }
    ],
    "sg:phone":"+44 1709 892035",
    "sg:postcode":"S63 0JE",
    "sg:province":"South Yorkshire",
    "sg:tags":[
        "housing",
        "sheltered"
    ],
    "wof:name":"Windsor Court Flats",
    "wof:placetype":"venue"
},
  "geometry": {"coordinates":[-1.304799,53.548046],"type":"Point"}
}