{
  "type": "Feature",
  "properties": {
    "addr:full":"79 Wych La, Bridgemary Gosport Hampshire PO13 0TA",
    "addr:housenumber":"79",
    "addr:postcode":"po13 0ta",
    "addr:street":"Wych La Bridgemary",
    "iso:country":"GB",
    "sg:address":"79 Wych La, Bridgemary",
    "sg:city":"Gosport",
    "sg:classifiers":[
        {
            "category":"Building & Trades",
            "subcategory":"Construction",
            "type":"Services"
        }
    ],
    "sg:phone":"+44 1329 318178",
    "sg:postcode":"PO13 0TA",
    "sg:province":"Hampshire",
    "sg:tags":[
        "builder"
    ],
    "wof:name":"Trenchline (Fareham) Ltd",
    "wof:placetype":"venue"
},
  "geometry": {"coordinates":[-1.179407,50.830349],"type":"Point"}
}