{
  "type": "Feature",
  "properties": {
    "iso:country":"GB",
    "sg:address":"45 Nunnery Lane",
    "sg:city":"York",
    "sg:classifiers":[
        {
            "category":"Personal",
            "subcategory":"Beauty Salon",
            "type":"Services"
        }
    ],
    "sg:postcode":"YO23 1AB",
    "sg:province":"North Yorkshire",
    "sg:tags":[
        "lady",
        "hairdresser"
    ],
    "wof:name":"Mistrals Ladies Hair Salon",
    "wof:placetype":"venue"
},
  "geometry": {"coordinates":[-1.087282,53.953899],"type":"Point"}
}