{
  "type": "Feature",
  "properties": {
    "addr:full":"Clitheroe Rd, Brierfield Nelson Lancashire BB9 5PT",
    "addr:postcode":"bb9 5pt",
    "addr:street":"Clitheroe Rd",
    "iso:country":"GB",
    "sg:address":"Clitheroe Rd, Brierfield",
    "sg:city":"Nelson",
    "sg:classifiers":[
        {
            "category":"Manufacturing",
            "subcategory":"Glass & Minerals",
            "type":"Manufacturing & Wholesale Goods"
        }
    ],
    "sg:phone":"+44 1282 616221",
    "sg:postcode":"BB9 5PT",
    "sg:province":"Lancashire",
    "sg:tags":[
        "fibre",
        "material"
    ],
    "wof:name":"Trojan Products Ltd",
    "wof:placetype":"venue"
},
  "geometry": {"coordinates":[-2.241589,53.824547],"type":"Point"}
}