{
  "type": "Feature",
  "properties": {
    "addr:full":"Nashlea Farm, Poors Lane North Benfleet Essex SS7 2XF",
    "addr:postcode":"ss7 2xf",
    "addr:street":"Poors Lane North Benfleet",
    "iso:country":"GB",
    "sg:address":"Nashlea Farm, Poors Lane North",
    "sg:city":"Benfleet",
    "sg:classifiers":[
        {
            "category":"Professional",
            "subcategory":"Secretarial Services",
            "type":"Services"
        }
    ],
    "sg:postcode":"SS7 2XF",
    "sg:province":"Essex",
    "wof:name":"Office Overload",
    "wof:placetype":"venue"
},
  "geometry": {"coordinates":[0.56264,51.543316],"type":"Point"}
}