{
  "type": "Feature",
  "properties": {
    "iso:country":"GB",
    "sg:address":"Trevena, New Zealand Farm, New Zealand",
    "sg:city":"Calne",
    "sg:classifiers":[
        {
            "category":"Farming",
            "subcategory":"Farm",
            "type":"Manufacturing & Wholesale Goods"
        },
        {
            "category":"Food & Beverages",
            "subcategory":"Groceries & Convenience Stores",
            "type":"Retail Goods"
        }
    ],
    "sg:phone":"+44 1249 760673",
    "sg:postcode":"SN11 9JL",
    "sg:province":"Wiltshire",
    "sg:tags":[
        "merchant",
        "egg",
        "producer"
    ],
    "wof:name":"B D Taylor",
    "wof:placetype":"venue"
},
  "geometry": {"coordinates":[-1.9846739769,51.4936714172],"type":"Point"}
}