{
  "type": "Feature",
  "properties": {
    "iso:country":"GB",
    "sg:address":"5 Clydeview, Shopping Centre",
    "sg:city":"Glasgow",
    "sg:classifiers":[
        {
            "category":"Health Services",
            "subcategory":"Optometrist",
            "type":"Services"
        }
    ],
    "sg:phone":"+44 1698 824788",
    "sg:postcode":"G72 0QD",
    "sg:province":"South Lanarkshire",
    "sg:tags":[
        "optician"
    ],
    "wof:name":"E Coyle",
    "wof:placetype":"venue"
},
  "geometry": {"coordinates":[-4.0883698463,55.7924690247],"type":"Point"}
}