{
  "type": "Feature",
  "properties": {
    "iso:country":"GB",
    "sg:address":"Unit 3 Station Road, Woodchester",
    "sg:city":"Stroud",
    "sg:classifiers":[
        {
            "category":"Wholesale",
            "subcategory":"Machinery & Supplies",
            "type":"Manufacturing & Wholesale Goods"
        }
    ],
    "sg:postcode":"GL5 5EQ",
    "sg:province":"Gloucestershire",
    "sg:tags":[
        "pump"
    ],
    "wof:name":"Britannia Seals & Packings",
    "wof:placetype":"venue"
},
  "geometry": {"coordinates":[-2.231226,51.718784],"type":"Point"}
}