{
  "type": "Feature",
  "properties": {
    "iso:country":"GB",
    "sg:address":"Unit F3 Aven Industrial Park, Tickhill Road, Maltby",
    "sg:city":"Rotherham",
    "sg:classifiers":[
        {
            "category":"Building & Trades",
            "subcategory":"Construction",
            "type":"Services"
        }
    ],
    "sg:phone":"+44 1709 812201",
    "sg:postcode":"S66 7QR",
    "sg:province":"South Yorkshire",
    "sg:tags":[
        "decorator",
        "painter"
    ],
    "wof:name":"K & G Challinor",
    "wof:placetype":"venue"
},
  "geometry": {"coordinates":[-1.16536,53.423504],"type":"Point"}
}