{
  "type": "Feature",
  "properties": {
    "iso:country":"GB",
    "sg:address":"Dulwich Delivery Off, 76 Alleyn Park",
    "sg:city":"London",
    "sg:classifiers":[
        {
            "category":"Personal",
            "type":"Services"
        }
    ],
    "sg:phone":"+44 20 8670 1223",
    "sg:postcode":"SE21 8SG",
    "sg:province":"Greater London",
    "sg:tags":[
        "delivery"
    ],
    "wof:name":"Royal Mail",
    "wof:placetype":"venue"
},
  "geometry": {"coordinates":[-0.08714,51.436359],"type":"Point"}
}