{
  "type": "Feature",
  "properties": {
    "iso:country":"GB",
    "sg:address":"48 Clockhouse Avenue",
    "sg:city":"Burnley",
    "sg:classifiers":[
        {
            "category":"Arts & Performance",
            "subcategory":"Music",
            "type":"Entertainment"
        }
    ],
    "sg:postcode":"BB10 2SU",
    "sg:province":"Lancashire",
    "sg:tags":[
        "mobile",
        "disco"
    ],
    "wof:name":"After Dark Discos",
    "wof:placetype":"venue"
},
  "geometry": {"coordinates":[-2.215773,53.814106],"type":"Point"}
}