{
  "type": "Feature",
  "properties": {
    "addr:full":"21 Perinville Road Torquay Devon TQ1 3NZ",
    "addr:housenumber":"21",
    "addr:postcode":"tq1 3nz",
    "addr:street":"Perinville Road",
    "iso:country":"GB",
    "sg:address":"21 Perinville Road",
    "sg:city":"Torquay",
    "sg:classifiers":[
        {
            "category":"Manufacturing",
            "subcategory":"Petroleum Products",
            "type":"Manufacturing & Wholesale Goods"
        },
        {
            "category":"Building & Trades",
            "subcategory":"Construction",
            "type":"Services"
        }
    ],
    "sg:phone":"+44 1803 311388",
    "sg:postcode":"TQ1 3NZ",
    "sg:province":"Devon",
    "sg:tags":[
        "double",
        "glazing",
        "installers"
    ],
    "wof:name":"Universal Windows South West",
    "wof:placetype":"venue"
},
  "geometry": {"coordinates":[-3.5148489475,50.4769477844],"type":"Point"}
}