{
  "type": "Feature",
  "properties": {
    "addr:full":"83 Inglis Green Road Edinburgh City of Edinburgh EH14 2EZ",
    "addr:housenumber":"83",
    "addr:postcode":"eh14 2ez",
    "addr:street":"Inglis Green Road",
    "iso:country":"GB",
    "sg:address":"83 Inglis Green Road",
    "sg:city":"Edinburgh",
    "sg:classifiers":[
        {
            "category":"Real Estate",
            "subcategory":"Surveying",
            "type":"Services"
        }
    ],
    "sg:phone":"+44 131 443 6966",
    "sg:postcode":"EH14 2EZ",
    "sg:province":"City of Edinburgh",
    "sg:tags":[
        "instrument"
    ],
    "wof:name":"Leica Microsystems (U K Holdings) Ltd.",
    "wof:placetype":"venue"
},
  "geometry": {"coordinates":[-3.2556869984,55.924949646],"type":"Point"}
}