{
  "type": "Feature",
  "properties": {
    "iso:country":"GB",
    "sg:address":"19 Carthagena Avenue",
    "sg:city":"Dumfries",
    "sg:classifiers":[
        {
            "category":"Communications",
            "type":"Services"
        }
    ],
    "sg:phone":"+44 1387 248444",
    "sg:postcode":"DG1 4XN",
    "sg:province":"Dumfries and Galloway",
    "sg:tags":[
        "telecommunication"
    ],
    "wof:name":"Nicom Phone Systems",
    "wof:placetype":"venue"
},
  "geometry": {"coordinates":[-3.570725,55.06271],"type":"Point"}
}