{
  "type": "Feature",
  "properties": {
    "addr:full":"Olivier House, 18 Marine Parade Brighton East Sussex BN2 1TL",
    "addr:housenumber":"18",
    "addr:postcode":"bn2 1tl",
    "addr:street":"Marine Parade",
    "iso:country":"GB",
    "sg:address":"Olivier House, 18 Marine Parade",
    "sg:city":"Brighton",
    "sg:classifiers":[
        {
            "category":"Professional",
            "subcategory":"Computer Services",
            "type":"Services"
        }
    ],
    "sg:phone":"+44 1273 624814",
    "sg:postcode":"BN2 1TL",
    "sg:province":"East Sussex",
    "sg:tags":[
        "system",
        "software"
    ],
    "wof:name":"Rational Software Ltd.",
    "wof:placetype":"venue"
},
  "geometry": {"coordinates":[-0.1340110004,50.8198471069],"type":"Point"}
}