{
  "type": "Feature",
  "properties": {
    "addr:full":"21 Beckford Street Hamilton South Lanarkshire ML3 0BT",
    "addr:housenumber":"21",
    "addr:postcode":"ml3 0bt",
    "addr:street":"Beckford Street",
    "iso:country":"GB",
    "sg:address":"21 Beckford Street",
    "sg:city":"Hamilton",
    "sg:classifiers":[
        {
            "category":"Government",
            "subcategory":"Office",
            "type":"Public Place"
        }
    ],
    "sg:phone":"+44 1698 454211",
    "sg:postcode":"ML3 0BT",
    "sg:province":"South Lanarkshire",
    "sg:tags":[
        "marriage",
        "death",
        "births",
        "local"
    ],
    "wof:name":"Registration of Births Deaths & Marriages",
    "wof:placetype":"venue"
},
  "geometry": {"coordinates":[-4.0495939255,55.7793998718],"type":"Point"}
}