{
  "type": "Feature",
  "properties": {
    "addr:full":"Cheriton, Milton On Stour Gillingham Dorset SP8 5PX",
    "addr:postcode":"sp8 5px",
    "addr:street":"Stour",
    "iso:country":"GB",
    "sg:address":"Cheriton, Milton On Stour",
    "sg:city":"Gillingham",
    "sg:classifiers":[
        {
            "category":"Real Estate",
            "subcategory":"Surveying",
            "type":"Services"
        }
    ],
    "sg:postcode":"SP8 5PX",
    "sg:province":"Dorset",
    "sg:tags":[
        "building",
        "surveyor"
    ],
    "wof:name":"Christopher J Greenwood",
    "wof:placetype":"venue"
},
  "geometry": {"coordinates":[-2.2862870693,51.0560379028],"type":"Point"}
}