{
  "type": "Feature",
  "properties": {
    "addr:full":"145 Lupus Street London Greater London SW1V 3HG",
    "addr:housenumber":"145",
    "addr:postcode":"sw1v 3hg",
    "addr:street":"Lupus Street",
    "iso:country":"GB",
    "sg:address":"145 Lupus Street",
    "sg:city":"London",
    "sg:classifiers":[
        {
            "category":"Health Services",
            "subcategory":"Dentist",
            "type":"Services"
        }
    ],
    "sg:phone":"+44 20 7834 8081",
    "sg:postcode":"SW1V 3HG",
    "sg:province":"Greater London",
    "wof:name":"H M Patel",
    "wof:placetype":"venue"
},
  "geometry": {"coordinates":[-0.1445969939,51.4872550964],"type":"Point"}
}