{
  "type": "Feature",
  "properties": {
    "iso:country":"GB",
    "sg:address":"Hanscombe End Farm, Handscombe End Road, Shillington",
    "sg:city":"Hitchin",
    "sg:classifiers":[
        {
            "category":"Farming",
            "subcategory":"Farm",
            "type":"Manufacturing & Wholesale Goods"
        }
    ],
    "sg:postcode":"SG5 3HL",
    "sg:province":"Bedfordshire",
    "sg:tags":[
        "mixed",
        "crop"
    ],
    "wof:name":"Anthony D Papworth",
    "wof:placetype":"venue"
},
  "geometry": {"coordinates":[-0.371589005,51.9869804382],"type":"Point"}
}