{
  "type": "Feature",
  "properties": {
    "iso:country":"GB",
    "sg:address":"Main Road, Hawkwell",
    "sg:city":"Hockley",
    "sg:classifiers":[
        {
            "category":"Government",
            "subcategory":"City Hall",
            "type":"Public Place"
        }
    ],
    "sg:postcode":"SS5 4EH",
    "sg:province":"Essex",
    "wof:name":"Hawkwell Village Hall",
    "wof:placetype":"venue"
},
  "geometry": {"coordinates":[0.655723,51.600704],"type":"Point"}
}