{
  "type": "Feature",
  "properties": {
    "addr:full":"Unit 6 Phoenix Court, Cleator Moor Business Centre, Cragg Road Cleator Moor Cumbria CA25 5PT",
    "addr:housenumber":"unit 6",
    "addr:postcode":"ca25 5pt",
    "addr:street":"Phoenix Court;Moor;Cragg Road",
    "iso:country":"GB",
    "sg:address":"Unit 6 Phoenix Court, Cleator Moor Business Centre, Cragg Road",
    "sg:city":"Cleator Moor",
    "sg:classifiers":[
        {
            "category":"Home & Garden",
            "subcategory":"Home Furnishings",
            "type":"Retail Goods"
        },
        {
            "category":"Manufacturing",
            "subcategory":"Textiles",
            "type":"Manufacturing & Wholesale Goods"
        }
    ],
    "sg:postcode":"CA25 5PT",
    "sg:province":"Cumbria",
    "sg:tags":[
        "made-up",
        "soft"
    ],
    "wof:name":"Margaret Winter Designs",
    "wof:placetype":"venue"
},
  "geometry": {"coordinates":[-3.515809,54.52137],"type":"Point"}
}