{
  "type": "Feature",
  "properties": {
    "addr:full":"33 Ringway Neston Cheshire CH64 3RS",
    "addr:housenumber":"33",
    "addr:postcode":"ch64 3rs",
    "addr:street":"Ringway Neston",
    "iso:country":"GB",
    "sg:address":"33 Ringway",
    "sg:city":"Neston",
    "sg:classifiers":[
        {
            "category":"Arts & Performance",
            "subcategory":"Music",
            "type":"Entertainment"
        }
    ],
    "sg:phone":"+44 151 336 8614",
    "sg:postcode":"CH64 3RS",
    "sg:province":"Cheshire",
    "sg:tags":[
        "mobile",
        "disco"
    ],
    "wof:name":"Global Discos",
    "wof:placetype":"venue"
},
  "geometry": {"coordinates":[-3.060721,53.298244],"type":"Point"}
}