{
  "type": "Feature",
  "properties": {
    "iso:country":"GB",
    "sg:address":"Unit A6b Barton Industrial Estate, Faldo Road, Barton Le Cley",
    "sg:city":"Bedford",
    "sg:classifiers":[
        {
            "category":"Building & Trades",
            "subcategory":"Construction",
            "type":"Services"
        }
    ],
    "sg:phone":"+44 1582 883339",
    "sg:postcode":"MK45 4RP",
    "sg:province":"Bedfordshire",
    "sg:tags":[
        "decorator",
        "painter"
    ],
    "wof:name":"Andersons Painting Contractors",
    "wof:placetype":"venue"
},
  "geometry": {"coordinates":[-0.4390330017,51.9727401733],"type":"Point"}
}