{
  "type": "Feature",
  "properties": {
    "iso:country":"GB",
    "sg:address":"1 Ives Street, Chelsea",
    "sg:city":"London",
    "sg:classifiers":[
        {
            "category":"Cafe",
            "type":"Food & Drink"
        },
        {
            "category":"Food & Beverages",
            "subcategory":"Bakery",
            "type":"Retail Goods"
        }
    ],
    "sg:phone":"+44 20 7591 0333",
    "sg:postcode":"SW3 2ND",
    "sg:province":"Greater London",
    "sg:tags":[
        "tea",
        "confectionery",
        "room"
    ],
    "wof:name":"D D (U K) Ltd.",
    "wof:placetype":"venue"
},
  "geometry": {"coordinates":[-0.167128,51.493565],"type":"Point"}
}