{
  "type": "Feature",
  "properties": {
    "iso:country":"GB",
    "sg:address":"36 Pickhurst Mead",
    "sg:city":"Bromley",
    "sg:classifiers":[
        {
            "category":"Professional",
            "subcategory":"Business Services",
            "type":"Services"
        }
    ],
    "sg:phone":"+44 20 8462 8721",
    "sg:postcode":"BR2 7QR",
    "sg:province":"Kent",
    "sg:tags":[
        "agent",
        "manufacturers'"
    ],
    "wof:name":"S L Sales & Promotions",
    "wof:placetype":"venue"
},
  "geometry": {"coordinates":[0.006322,51.383095],"type":"Point"}
}