{
  "type": "Feature",
  "properties": {
    "addr:full":"14-16 Sheep Street Skipton Lancashire BD23 1JH",
    "addr:housenumber":"14-16",
    "addr:postcode":"bd23 1jh",
    "addr:street":"Sheep Street",
    "iso:country":"GB",
    "sg:address":"14-16 Sheep Street",
    "sg:city":"Skipton",
    "sg:classifiers":[
        {
            "category":"Shopping",
            "subcategory":"Clothing, Apparel, & Fashions",
            "type":"Retail Goods"
        }
    ],
    "sg:phone":"+44 1756 794315",
    "sg:postcode":"BD23 1JH",
    "sg:province":"Lancashire",
    "sg:tags":[
        "menswear"
    ],
    "wof:name":"Gmw1 Ltd.",
    "wof:placetype":"venue"
},
  "geometry": {"coordinates":[-2.017314,53.961273],"type":"Point"}
}