{
  "type": "Feature",
  "properties": {
    "iso:country":"GB",
    "sg:address":"Bretton Street Industrial Estate, Savile Town",
    "sg:city":"Dewsbury",
    "sg:classifiers":[
        {
            "category":"Shopping",
            "subcategory":"Bicycles & Sporting Goods",
            "type":"Retail Goods"
        }
    ],
    "sg:phone":"+44 1924 466633",
    "sg:postcode":"WF12 9BB",
    "sg:province":"West Yorkshire",
    "sg:tags":[
        "cycle",
        "accessory"
    ],
    "wof:name":"Hartley Dawson J Ltd.",
    "wof:placetype":"venue"
},
  "geometry": {"coordinates":[-1.624734,53.677593],"type":"Point"}
}