{
  "type": "Feature",
  "properties": {
    "addr:full":"253 Evering Road, Hackney London Greater London E5 8AL",
    "addr:housenumber":"253",
    "addr:postcode":"e5 8al",
    "addr:street":"Evering Road",
    "iso:country":"GB",
    "sg:address":"253 Evering Road, Hackney",
    "sg:city":"London",
    "sg:classifiers":[
        {
            "category":"Professional",
            "subcategory":"Art Services",
            "type":"Services"
        }
    ],
    "sg:postcode":"E5 8AL",
    "sg:province":"Greater London",
    "sg:tags":[
        "picture",
        "restoration",
        "cleaning"
    ],
    "wof:name":"Alfred T Poole",
    "wof:placetype":"venue"
},
  "geometry": {"coordinates":[-0.058843,51.56218],"type":"Point"}
}