{
  "type": "Feature",
  "properties": {
    "iso:country":"GB",
    "sg:address":"Ravensdene Dental Surgery, 150 Park Rd",
    "sg:city":"Peterborough",
    "sg:classifiers":[
        {
            "category":"Health Services",
            "subcategory":"Dentist",
            "type":"Services"
        }
    ],
    "sg:phone":"+44 1733 551534",
    "sg:postcode":"PE1 2UB",
    "sg:province":"Cambridgeshire",
    "wof:name":"B Hollingdale",
    "wof:placetype":"venue"
},
  "geometry": {"coordinates":[-0.23938,52.58009],"type":"Point"}
}