{
  "type": "Feature",
  "properties": {
    "addr:full":"27 Bank Street Ashford Kent TN23 1DG",
    "addr:housenumber":"27",
    "addr:postcode":"tn23 1dg",
    "addr:street":"Bank Street",
    "iso:country":"GB",
    "sg:address":"27 Bank Street",
    "sg:city":"Ashford",
    "sg:classifiers":[
        {
            "category":"Shopping",
            "subcategory":"Mobile Phones",
            "type":"Retail Goods"
        }
    ],
    "sg:postcode":"TN23 1DG",
    "sg:province":"Kent",
    "wof:name":"Road Radio",
    "wof:placetype":"venue"
},
  "geometry": {"coordinates":[0.870811,51.147919],"type":"Point"}
}