{
  "type": "Feature",
  "properties": {
    "addr:full":"147 Lumb Lane, Audenshaw Manchester Greater Manchester M34 5RU",
    "addr:housenumber":"147",
    "addr:postcode":"m34 5ru",
    "addr:street":"Lumb Lane",
    "iso:country":"GB",
    "sg:address":"147 Lumb Lane, Audenshaw",
    "sg:city":"Manchester",
    "sg:classifiers":[
        {
            "category":"Professional",
            "subcategory":"Engineering",
            "type":"Services"
        },
        {
            "category":"Building & Trades",
            "subcategory":"Electrical",
            "type":"Services"
        }
    ],
    "sg:phone":"+44 161 301 1952",
    "sg:postcode":"M34 5RU",
    "sg:province":"Greater Manchester",
    "sg:tags":[
        "engineer",
        "electrician",
        "contractor"
    ],
    "wof:name":"Iain Whittaker",
    "wof:placetype":"venue"
},
  "geometry": {"coordinates":[-2.1334619522,53.4799423218],"type":"Point"}
}