{
  "type": "Feature",
  "properties": {
    "iso:country":"GB",
    "sg:address":"112 South Street",
    "sg:city":"Eastbourne",
    "sg:classifiers":[
        {
            "category":"Sports & Exercise",
            "subcategory":"Golf",
            "type":"Entertainment"
        }
    ],
    "sg:phone":"+44 1323 639553",
    "sg:postcode":"BN21 4LZ",
    "sg:province":"East Sussex",
    "sg:tags":[
        "equipment"
    ],
    "wof:name":"Image Tech",
    "wof:placetype":"venue"
},
  "geometry": {"coordinates":[0.284293,50.76635],"type":"Point"}
}