{
  "type": "Feature",
  "properties": {
    "addr:full":"116 Sandy Lane, Middleton Manchester Greater Manchester M24 2FU",
    "addr:housenumber":"116",
    "addr:postcode":"m24 2fu",
    "addr:street":"Sandy Lane",
    "iso:country":"GB",
    "sg:address":"116 Sandy Lane, Middleton",
    "sg:city":"Manchester",
    "sg:classifiers":[
        {
            "category":"Health Services",
            "subcategory":"Nursing And Care Facility",
            "type":"Services"
        },
        {
            "category":"Social Services",
            "subcategory":"Retirement Home",
            "type":"Services"
        }
    ],
    "sg:phone":"+44 161 653 2454",
    "sg:postcode":"M24 2FU",
    "sg:province":"Greater Manchester",
    "sg:tags":[
        "residential"
    ],
    "wof:name":"Archmoor Residential Care Homes",
    "wof:placetype":"venue"
},
  "geometry": {"coordinates":[-2.1807188988,53.5469512939],"type":"Point"}
}