{
  "type": "Feature",
  "properties": {
    "addr:full":"3 Church Street Ilkley North Yorkshire LS29 9DR",
    "addr:housenumber":"3",
    "addr:postcode":"ls29 9dr",
    "addr:street":"Church Street",
    "iso:country":"GB",
    "sg:address":"3 Church Street",
    "sg:city":"Ilkley",
    "sg:classifiers":[
        {
            "category":"Shopping",
            "subcategory":"Clothing, Apparel, & Fashions",
            "type":"Retail Goods"
        }
    ],
    "sg:phone":"+44 1943 601850",
    "sg:postcode":"LS29 9DR",
    "sg:province":"North Yorkshire",
    "sg:tags":[
        "haberdasher"
    ],
    "sg:website":"http://www.duttonsforbuttons.co.uk",
    "wof:name":"Duttons for Buttons",
    "wof:placetype":"venue"
},
  "geometry": {"coordinates":[-1.823595047,53.9261322021],"type":"Point"}
}