{
  "type": "Feature",
  "properties": {
    "addr:full":"45 Haggs Road Glasgow Glasgow City G41 4AP",
    "addr:housenumber":"45",
    "addr:postcode":"g41 4ap",
    "addr:street":"Haggs Road",
    "iso:country":"GB",
    "sg:address":"45 Haggs Road",
    "sg:city":"Glasgow",
    "sg:classifiers":[
        {
            "category":"Building & Trades",
            "subcategory":"Construction",
            "type":"Services"
        }
    ],
    "sg:phone":"+44 141 632 6266",
    "sg:postcode":"G41 4AP",
    "sg:province":"Glasgow City",
    "sg:tags":[
        "builder"
    ],
    "wof:name":"Robert Loudon Builders Ltd.",
    "wof:placetype":"venue"
},
  "geometry": {"coordinates":[-4.2960939407,55.8300552368],"type":"Point"}
}