{
  "type": "Feature",
  "properties": {
    "iso:country":"GB",
    "sg:address":"63 Highfield Park Road, Bredbury",
    "sg:city":"Stockport",
    "sg:classifiers":[
        {
            "category":"Government",
            "subcategory":"Post Office",
            "type":"Public Place"
        }
    ],
    "sg:phone":"+44 161 494 6294",
    "sg:postcode":"SK6 2PG",
    "sg:province":"Cheshire",
    "sg:tags":[
        "messenger",
        "courier"
    ],
    "wof:name":"Door 2 Door",
    "wof:placetype":"venue"
},
  "geometry": {"coordinates":[-2.114724,53.420807],"type":"Point"}
}