{
  "type": "Feature",
  "properties": {
    "iso:country":"GB",
    "sg:address":"339 Haydn Rd",
    "sg:city":"Nottingham",
    "sg:classifiers":[
        {
            "category":"Fast Food",
            "type":"Food & Drink"
        }
    ],
    "sg:phone":"+44 115 962 1118",
    "sg:postcode":"NG5 1DZ",
    "sg:province":"Nottinghamshire",
    "sg:tags":[
        "away",
        "take"
    ],
    "wof:name":"Timothy Roy's Snack Bar & Takeaway",
    "wof:placetype":"venue"
},
  "geometry": {"coordinates":[-1.16181,52.979065],"type":"Point"}
}