{
  "type": "Feature",
  "properties": {
    "iso:country":"GB",
    "sg:address":"Hogfair Lane, Burnham",
    "sg:city":"Slough",
    "sg:classifiers":[
        {
            "category":"Education",
            "subcategory":"School",
            "type":"Public Place"
        },
        {
            "category":"Government",
            "subcategory":"Office",
            "type":"Public Place"
        }
    ],
    "sg:phone":"+44 1628 604812",
    "sg:postcode":"SL1 7HG",
    "sg:province":"Berkshire",
    "sg:tags":[
        "local",
        "authority"
    ],
    "wof:name":"Burnham Grammar School",
    "wof:placetype":"venue"
},
  "geometry": {"coordinates":[-0.6535540223,51.5314598083],"type":"Point"}
}