{
  "type": "Feature",
  "properties": {
    "addr:full":"Foss House Garage, Foss Islands Road York North Yorkshire YO31 7UR",
    "addr:postcode":"yo31 7ur",
    "addr:street":"Foss Islands Road",
    "iso:country":"GB",
    "sg:address":"Foss House Garage, Foss Islands Road",
    "sg:city":"York",
    "sg:classifiers":[
        {
            "category":"Professional",
            "subcategory":"Secretarial Services",
            "type":"Services"
        }
    ],
    "sg:postcode":"YO31 7UR",
    "sg:province":"North Yorkshire",
    "wof:name":"J J Office Services",
    "wof:placetype":"venue"
},
  "geometry": {"coordinates":[-1.0735989809,53.9612312317],"type":"Point"}
}