{
  "type": "Feature",
  "properties": {
    "addr:full":"11 Leopold St Nairn Highland IV12 4BE",
    "addr:housenumber":"11",
    "addr:postcode":"iv12 4be",
    "addr:street":"Leopold St",
    "iso:country":"GB",
    "sg:address":"11 Leopold St",
    "sg:city":"Nairn",
    "sg:classifiers":[
        {
            "category":"Shopping",
            "subcategory":"Clothing, Apparel, & Fashions",
            "type":"Retail Goods"
        }
    ],
    "sg:phone":"+44 1667 451593",
    "sg:postcode":"IV12 4BE",
    "sg:province":"Highland",
    "sg:tags":[
        "shop"
    ],
    "wof:name":"Katie Millar",
    "wof:placetype":"venue"
},
  "geometry": {"coordinates":[-3.871018,57.58437],"type":"Point"}
}