{
  "type": "Feature",
  "properties": {
    "addr:full":"64 Midland Rd, Bramhall Stockport Cheshire SK7 3DT",
    "addr:housenumber":"64",
    "addr:postcode":"sk7 3dt",
    "addr:street":"Midland Rd",
    "iso:country":"GB",
    "sg:address":"64 Midland Rd, Bramhall",
    "sg:city":"Stockport",
    "sg:classifiers":[
        {
            "category":"Retail",
            "subcategory":"Event Space",
            "type":"Services"
        },
        {
            "category":"Organizations",
            "subcategory":"Membership Organization",
            "type":"Services"
        }
    ],
    "sg:phone":"+44 161 439 4270",
    "sg:postcode":"SK7 3DT",
    "sg:province":"Cheshire",
    "sg:tags":[
        "function",
        "club",
        "hire",
        "room"
    ],
    "wof:name":"Parkside Social Club Ltd",
    "wof:placetype":"venue"
},
  "geometry": {"coordinates":[-2.162234,53.383568],"type":"Point"}
}