{
  "type": "Feature",
  "properties": {
    "iso:country":"GB",
    "sg:address":"Movie Time, 15 London Road",
    "sg:city":"Newcastle",
    "sg:classifiers":[
        {
            "category":"Fast Food",
            "type":"Food & Drink"
        }
    ],
    "sg:postcode":"ST5 7EA",
    "sg:province":"Staffordshire",
    "sg:tags":[
        "away",
        "take"
    ],
    "wof:name":"Kashmir Delight",
    "wof:placetype":"venue"
},
  "geometry": {"coordinates":[-2.228601,53.008801],"type":"Point"}
}