{
  "type": "Feature",
  "properties": {
    "iso:country":"GB",
    "sg:address":"105-113 Longbridge Road",
    "sg:city":"Barking",
    "sg:classifiers":[
        {
            "category":"Autos & Motor Vehicles",
            "subcategory":"Automobile Sales",
            "type":"Retail Goods"
        }
    ],
    "sg:phone":"+44 20 8594 5461",
    "sg:postcode":"IG11 8SZ",
    "sg:province":"Essex",
    "sg:tags":[
        "car"
    ],
    "wof:name":"Premier Motors (Romford)",
    "wof:placetype":"venue"
},
  "geometry": {"coordinates":[0.085048,51.542019],"type":"Point"}
}