{
  "type": "Feature",
  "properties": {
    "addr:full":"24 Mark Road Hemel Hempstead Hertfordshire HP2 7DN",
    "addr:housenumber":"24",
    "addr:postcode":"hp2 7dn",
    "addr:street":"Mark Road",
    "iso:country":"GB",
    "sg:address":"24 Mark Road",
    "sg:city":"Hemel Hempstead",
    "sg:classifiers":[
        {
            "category":"Retail",
            "subcategory":"Auto Repair",
            "type":"Services"
        }
    ],
    "sg:phone":"+44 1442 232522",
    "sg:postcode":"HP2 7DN",
    "sg:province":"Hertfordshire",
    "sg:tags":[
        "body",
        "garage",
        "modification",
        "car"
    ],
    "wof:name":"Abbey Motors (Hemel Hempstead) Ltd.",
    "wof:placetype":"venue"
},
  "geometry": {"coordinates":[-0.4413279891,51.7614555359],"type":"Point"}
}