{
  "type": "Feature",
  "properties": {
    "addr:full":"Greyhound House, 23-24 George St Richmond Greater London TW9 1HY",
    "addr:housenumber":"23-24",
    "addr:postcode":"tw9 1hy",
    "addr:street":"George St",
    "iso:country":"GB",
    "sg:address":"Greyhound House, 23-24 George St",
    "sg:city":"Richmond",
    "sg:classifiers":[
        {
            "category":"Professional",
            "subcategory":"Computer Services",
            "type":"Services"
        }
    ],
    "sg:phone":"+44 20 8948 3244",
    "sg:postcode":"TW9 1HY",
    "sg:province":"Greater London",
    "sg:tags":[
        "system",
        "software"
    ],
    "wof:name":"Investment Software Solutions",
    "wof:placetype":"venue"
},
  "geometry": {"coordinates":[-0.304622,51.460545],"type":"Point"}
}