{
  "type": "Feature",
  "properties": {
    "addr:full":"93 Forburg Road London Greater London N16 6HR",
    "addr:housenumber":"93",
    "addr:postcode":"n16 6hr",
    "addr:street":"Forburg Road",
    "iso:country":"GB",
    "sg:address":"93 Forburg Road",
    "sg:city":"London",
    "sg:classifiers":[
        {
            "category":"Building & Trades",
            "subcategory":"Equipment Rental",
            "type":"Services"
        }
    ],
    "sg:phone":"+44 20 8880 0888",
    "sg:postcode":"N16 6HR",
    "sg:province":"Greater London",
    "sg:tags":[
        "hire",
        "centre"
    ],
    "wof:name":"The Floor Store Direct Ltd.",
    "wof:placetype":"venue"
},
  "geometry": {"coordinates":[-0.063268,51.568657],"type":"Point"}
}