{
  "type": "Feature",
  "properties": {
    "addr:full":"Heaton Court, Meynell Close Chesterfield Derbyshire S40 3BN",
    "addr:postcode":"s40 3bn",
    "addr:street":"Heaton Court Meynell Close",
    "iso:country":"GB",
    "sg:address":"Heaton Court, Meynell Close",
    "sg:city":"Chesterfield",
    "sg:classifiers":[
        {
            "category":"Social Services",
            "subcategory":"Adult Care",
            "type":"Services"
        },
        {
            "category":"Government",
            "subcategory":"Office",
            "type":"Public Place"
        }
    ],
    "sg:phone":"+44 1246 235506",
    "sg:postcode":"S40 3BN",
    "sg:province":"Derbyshire",
    "sg:tags":[
        "housing",
        "local",
        "sheltered"
    ],
    "wof:name":"Heaton Court Sheltered Housing",
    "wof:placetype":"venue"
},
  "geometry": {"coordinates":[-1.457179,53.23307],"type":"Point"}
}