{
  "type": "Feature",
  "properties": {
    "iso:country":"GB",
    "sg:address":"Burlton Cottage, The Cross, Shillingstone",
    "sg:city":"Blandford Forum",
    "sg:classifiers":[
        {
            "category":"Communications",
            "subcategory":"Film & Video Production",
            "type":"Services"
        },
        {
            "category":"Professional",
            "subcategory":"Art Services",
            "type":"Services"
        }
    ],
    "sg:phone":"+44 1258 860641",
    "sg:postcode":"DT11 0SP",
    "sg:province":"Dorset",
    "sg:tags":[
        "illustrator",
        "artist"
    ],
    "wof:name":"C C G Edwards",
    "wof:placetype":"venue"
},
  "geometry": {"coordinates":[-2.244481,50.896336],"type":"Point"}
}