{
  "type": "Feature",
  "properties": {
    "addr:full":"1 Jubilee Court, Montrose Avenue, Hillington Industrial Estate Glasgow Glasgow City G52 4LB",
    "addr:housenumber":"1",
    "addr:postcode":"g52 4lb",
    "addr:street":"Jubilee Court Montrose Avenue;Industrial Estate",
    "iso:country":"GB",
    "sg:address":"1 Jubilee Court, Montrose Avenue, Hillington Industrial Estate",
    "sg:city":"Glasgow",
    "sg:classifiers":[
        {
            "category":"Sports & Exercise",
            "subcategory":"Sports Center",
            "type":"Entertainment"
        }
    ],
    "sg:postcode":"G52 4LB",
    "sg:province":"Glasgow City",
    "sg:tags":[
        "shop",
        "good"
    ],
    "wof:name":"Florence Clothiers (Scotland) Ltd.",
    "wof:placetype":"venue"
},
  "geometry": {"coordinates":[-4.377349,55.862068],"type":"Point"}
}