{
  "type": "Feature",
  "properties": {
    "addr:full":"37 Churchill Avenue, Cheddleton Leek Staffordshire ST13 7EJ",
    "addr:housenumber":"37",
    "addr:postcode":"st13 7ej",
    "addr:street":"Churchill Avenue",
    "iso:country":"GB",
    "sg:address":"37 Churchill Avenue, Cheddleton",
    "sg:city":"Leek",
    "sg:classifiers":[
        {
            "category":"Retail",
            "subcategory":"Driving School",
            "type":"Services"
        }
    ],
    "sg:postcode":"ST13 7EJ",
    "sg:province":"Staffordshire",
    "wof:name":"Cheddleton Driving School",
    "wof:placetype":"venue"
},
  "geometry": {"coordinates":[-2.03383708,53.065032959],"type":"Point"}
}