{
  "type": "Feature",
  "properties": {
    "addr:full":"The Video Casting Facility, 5 Argyle St London Greater London W1F 7TA",
    "addr:housenumber":"5",
    "addr:postcode":"w1f 7ta",
    "addr:street":"Argyle St",
    "iso:country":"GB",
    "sg:address":"The Video Casting Facility, 5 Argyle St",
    "sg:city":"London",
    "sg:classifiers":[
        {
            "category":"Communications",
            "type":"Services"
        }
    ],
    "sg:phone":"+44 20 7437 3547",
    "sg:postcode":"W1F 7TA",
    "sg:province":"Greater London",
    "sg:tags":[
        "audio-visual"
    ],
    "wof:name":"Green Room Casting Ltd (The)",
    "wof:placetype":"venue"
},
  "geometry": {"coordinates":[-0.14015,51.51424],"type":"Point"}
}