{
  "type": "Feature",
  "properties": {
    "addr:full":"The Fairway, Becton Lane New Milton Hampshire BH25 7AE",
    "addr:postcode":"bh25 7ae",
    "addr:street":"Fairway Becton Lane",
    "iso:country":"GB",
    "sg:address":"The Fairway, Becton Lane",
    "sg:city":"New Milton",
    "sg:classifiers":[
        {
            "category":"Health Services",
            "subcategory":"Nursing And Care Facility",
            "type":"Services"
        }
    ],
    "sg:postcode":"BH25 7AE",
    "sg:province":"Hampshire",
    "sg:tags":[
        "home"
    ],
    "wof:name":"Glancestyle Care Homes Ltd.",
    "wof:placetype":"venue"
},
  "geometry": {"coordinates":[-1.651409,50.739525],"type":"Point"}
}