{
  "type": "Feature",
  "properties": {
    "iso:country":"GB",
    "sg:address":"Manor Farm, Tytherington",
    "sg:city":"Warminster",
    "sg:classifiers":[
        {
            "category":"Farming",
            "subcategory":"Farm",
            "type":"Manufacturing & Wholesale Goods"
        }
    ],
    "sg:phone":"+44 1985 841052",
    "sg:postcode":"BA12 7AD",
    "sg:province":"Somerset",
    "sg:tags":[
        "mixed",
        "crop"
    ],
    "wof:name":"G H Osborne & Son",
    "wof:placetype":"venue"
},
  "geometry": {"coordinates":[-2.119339,51.171097],"type":"Point"}
}