{
  "type": "Feature",
  "properties": {
    "addr:full":"107 High Street, Brownhill Walsall Staffordshire WS8 6HL",
    "addr:housenumber":"107",
    "addr:postcode":"ws8 6hl",
    "addr:street":"High Street",
    "iso:country":"GB",
    "sg:address":"107 High Street, Brownhill",
    "sg:city":"Walsall",
    "sg:classifiers":[
        {
            "category":"Professional",
            "subcategory":"Employment Agencies",
            "type":"Services"
        }
    ],
    "sg:phone":"+44 1543 515000",
    "sg:postcode":"WS8 6HL",
    "sg:province":"Staffordshire",
    "sg:tags":[
        "consultant"
    ],
    "wof:name":"Employment Service Jobcentre",
    "wof:placetype":"venue"
},
  "geometry": {"coordinates":[-1.9318890572,52.646522522],"type":"Point"}
}