{
  "type": "Feature",
  "properties": {
    "iso:country":"GB",
    "sg:address":"Jingle Joys, Cleeve Road, North Littleton",
    "sg:city":"Evesham",
    "sg:classifiers":[
        {
            "category":"Communications",
            "subcategory":"Film & Video Production",
            "type":"Services"
        }
    ],
    "sg:postcode":"WR11 8JU",
    "sg:province":"Gloucestershire",
    "sg:tags":[
        "illustrator",
        "artist"
    ],
    "wof:name":"Animal Portraits",
    "wof:placetype":"venue"
},
  "geometry": {"coordinates":[-1.881574,52.123886],"type":"Point"}
}