{
  "type": "Feature",
  "properties": {
    "addr:full":"Station Stop, Eastbourne Station Eastbourne East Sussex BN21 3QJ",
    "addr:postcode":"bn21 3qj",
    "iso:country":"GB",
    "sg:address":"Station Stop, Eastbourne Station",
    "sg:city":"Eastbourne",
    "sg:classifiers":[
        {
            "category":"Shopping",
            "subcategory":"Books",
            "type":"Retail Goods"
        }
    ],
    "sg:phone":"+44 1323 724787",
    "sg:postcode":"BN21 3QJ",
    "sg:province":"East Sussex",
    "sg:tags":[
        "bookseller"
    ],
    "wof:name":"W H Smith Trading Ltd.",
    "wof:placetype":"venue"
},
  "geometry": {"coordinates":[0.28535,50.766911],"type":"Point"}
}