{
  "type": "Feature",
  "properties": {
    "iso:country":"GB",
    "sg:address":"38 Hatch Pond Rd",
    "sg:city":"Poole",
    "sg:classifiers":[
        {
            "category":"Building & Trades",
            "subcategory":"Construction",
            "type":"Services"
        }
    ],
    "sg:phone":"+44 1202 642400",
    "sg:postcode":"BH17 0LH",
    "sg:province":"Dorset",
    "sg:tags":[
        "block"
    ],
    "wof:name":"Tarmac Toppave",
    "wof:placetype":"venue"
},
  "geometry": {"coordinates":[-1.9803689718,50.7436904907],"type":"Point"}
}