{
  "type": "Feature",
  "properties": {
    "addr:full":"Wellbury Northallerton North Yorkshire DL6 2SE",
    "addr:postcode":"dl6 2se",
    "iso:country":"GB",
    "sg:address":"Wellbury",
    "sg:city":"Northallerton",
    "sg:classifiers":[
        {
            "category":"Bars & Pubs",
            "type":"Food & Drink"
        }
    ],
    "sg:phone":"+44 1609 882464",
    "sg:postcode":"DL6 2SE",
    "sg:province":"North Yorkshire",
    "sg:tags":[
        "pubs",
        "inn"
    ],
    "wof:name":"The Duke of Wellington",
    "wof:placetype":"venue"
},
  "geometry": {"coordinates":[-1.4315240383,54.3383674622],"type":"Point"}
}