{
  "type": "Feature",
  "properties": {
    "iso:country":"GB",
    "sg:address":"26 South Acre, South Harting",
    "sg:city":"Petersfield",
    "sg:classifiers":[
        {
            "category":"Taxi",
            "type":"Transportation"
        }
    ],
    "sg:phone":"+44 1730 825225",
    "sg:postcode":"GU31 5LJ",
    "sg:province":"Hampshire",
    "sg:tags":[
        "mini",
        "cab"
    ],
    "wof:name":"Harting Carriage Co",
    "wof:placetype":"venue"
},
  "geometry": {"coordinates":[-0.950503,50.973438],"type":"Point"}
}