{
  "type": "Feature",
  "properties": {
    "addr:full":"101 Wattleton Road Beaconsfield Buckinghamshire HP9 1RW",
    "addr:housenumber":"101",
    "addr:postcode":"hp9 1rw",
    "addr:street":"Wattleton Road",
    "iso:country":"GB",
    "sg:address":"101 Wattleton Road",
    "sg:city":"Beaconsfield",
    "sg:classifiers":[
        {
            "category":"Professional",
            "subcategory":"Engineering",
            "type":"Services"
        }
    ],
    "sg:phone":"+44 1923 897903",
    "sg:postcode":"HP9 1RW",
    "sg:province":"Buckinghamshire",
    "sg:tags":[
        "consulting",
        "engineer"
    ],
    "wof:name":"Startech Engineering Consultancy Ltd.",
    "wof:placetype":"venue"
},
  "geometry": {"coordinates":[-0.641569972,51.6043968201],"type":"Point"}
}