{
  "type": "Feature",
  "properties": {
    "iso:country":"GB",
    "sg:address":"Bushey Row, High Street",
    "sg:city":"Bampton",
    "sg:classifiers":[
        {
            "category":"Home & Garden",
            "subcategory":"Home Furnishings",
            "type":"Retail Goods"
        }
    ],
    "sg:phone":"+44 1993 853900",
    "sg:postcode":"OX18 2JU",
    "sg:province":"Gloucestershire",
    "sg:tags":[
        "patio",
        "furniture"
    ],
    "wof:name":"The Garden Trading Co. Ltd.",
    "wof:placetype":"venue"
},
  "geometry": {"coordinates":[-1.543809,51.729195],"type":"Point"}
}