{
  "type": "Feature",
  "properties": {
    "addr:full":"28-30 Cheltenham Parade Harrogate North Yorkshire HG1 5AN",
    "addr:housenumber":"28-30",
    "addr:postcode":"hg1 5an",
    "addr:street":"Cheltenham Parade",
    "iso:country":"GB",
    "sg:address":"28-30 Cheltenham Parade",
    "sg:city":"Harrogate",
    "sg:classifiers":[
        {
            "category":"Travel",
            "subcategory":"Hotels & Motels",
            "type":"Entertainment"
        }
    ],
    "sg:phone":"+44 1423 505041",
    "sg:postcode":"HG1 5AN",
    "sg:province":"North Yorkshire",
    "wof:name":"Harrogate Brasserie Ltd.",
    "wof:placetype":"venue"
},
  "geometry": {"coordinates":[-1.5411499739,53.9948310852],"type":"Point"}
}