{
  "type": "Feature",
  "properties": {
    "addr:full":"Eskdale Road, Telford Estate Shrewsbury Shropshire SY2 5UD",
    "addr:postcode":"sy2 5ud",
    "addr:street":"Eskdale Road",
    "iso:country":"GB",
    "sg:address":"Eskdale Road, Telford Estate",
    "sg:city":"Shrewsbury",
    "sg:classifiers":[
        {
            "category":"Social Services",
            "type":"Services"
        }
    ],
    "sg:phone":"+44 1743 231303",
    "sg:postcode":"SY2 5UD",
    "sg:province":"Shropshire",
    "wof:name":"Eskdale House",
    "wof:placetype":"venue"
},
  "geometry": {"coordinates":[-2.721204,52.716927],"type":"Point"}
}