{
  "type": "Feature",
  "properties": {
    "addr:full":"5 Leiston Close, Irby Wirral Merseyside CH61 4YR",
    "addr:housenumber":"5",
    "addr:postcode":"ch61 4yr",
    "addr:street":"Leiston Close",
    "iso:country":"GB",
    "sg:address":"5 Leiston Close, Irby",
    "sg:city":"Wirral",
    "sg:classifiers":[
        {
            "category":"Professional",
            "subcategory":"Art Services",
            "type":"Services"
        }
    ],
    "sg:postcode":"CH61 4YR",
    "sg:province":"Merseyside",
    "sg:tags":[
        "photographer"
    ],
    "wof:name":"Wedding Bells Photography",
    "wof:placetype":"venue"
},
  "geometry": {"coordinates":[-3.112614,53.359821],"type":"Point"}
}