{
  "type": "Feature",
  "properties": {
    "addr:full":"10a West St, Abbotsbury Weymouth Dorset DT3 4JT",
    "addr:housenumber":"10a",
    "addr:postcode":"dt3 4jt",
    "addr:street":"West St",
    "iso:country":"GB",
    "sg:address":"10a West St, Abbotsbury",
    "sg:city":"Weymouth",
    "sg:classifiers":[
        {
            "category":"Shopping",
            "subcategory":"Computers & Home Electronics",
            "type":"Retail Goods"
        }
    ],
    "sg:postcode":"DT3 4JT",
    "sg:province":"Dorset",
    "wof:name":"Dansel",
    "wof:placetype":"venue"
},
  "geometry": {"coordinates":[-2.60584,50.666092],"type":"Point"}
}