{
  "type": "Feature",
  "properties": {
    "iso:country":"GB",
    "sg:address":"31 Chantry La",
    "sg:city":"Grimsby",
    "sg:classifiers":[
        {
            "category":"Health Services",
            "subcategory":"Doctor",
            "type":"Services"
        }
    ],
    "sg:phone":"+44 1472 342325",
    "sg:postcode":"DN31 2LP",
    "sg:province":"Lincolnshire",
    "sg:tags":[
        "practitioners"
    ],
    "wof:name":"Clow, E",
    "wof:placetype":"venue"
},
  "geometry": {"coordinates":[-0.0924549997,53.5646820068],"type":"Point"}
}