{
  "type": "Feature",
  "properties": {
    "addr:full":"60-62 London Rd Kingston-upon-thames Greater London KT2 6QZ",
    "addr:housenumber":"60-62",
    "addr:postcode":"kt2 6qz",
    "addr:street":"London Rd",
    "iso:country":"GB",
    "sg:address":"60-62 London Rd",
    "sg:city":"Kingston-upon-thames",
    "sg:classifiers":[
        {
            "category":"Building & Trades",
            "subcategory":"Plumbing",
            "type":"Services"
        }
    ],
    "sg:postcode":"KT2 6QZ",
    "sg:province":"Greater London",
    "sg:tags":[
        "central",
        "heating"
    ],
    "wof:name":"Betta Heat",
    "wof:placetype":"venue"
},
  "geometry": {"coordinates":[-0.2979510128,51.4105529785],"type":"Point"}
}