{
  "type": "Feature",
  "properties": {
    "iso:country":"GB",
    "sg:address":"Unit 12 14 Newlands Dr",
    "sg:city":"Slough",
    "sg:classifiers":[
        {
            "category":"Professional",
            "subcategory":"Computer Services",
            "type":"Services"
        }
    ],
    "sg:postcode":"SL3 0DX",
    "sg:province":"Berkshire",
    "sg:tags":[
        "system",
        "software"
    ],
    "wof:name":"Metrologie Ltd",
    "wof:placetype":"venue"
},
  "geometry": {"coordinates":[-0.5133590102,51.4702796936],"type":"Point"}
}