{
  "type": "Feature",
  "properties": {
    "addr:full":"Ruthin Craft Centre, Lon Parcwr Ruthin Denbighshire LL15 1BB",
    "addr:postcode":"ll15 1bb",
    "addr:street":"Lon Parcwr",
    "iso:country":"GB",
    "sg:address":"Ruthin Craft Centre, Lon Parcwr",
    "sg:city":"Ruthin",
    "sg:classifiers":[
        {
            "category":"Travel",
            "subcategory":"Travel Agent",
            "type":"Entertainment"
        },
        {
            "category":"Landmark",
            "subcategory":"Tourist Information",
            "type":"Public Place"
        }
    ],
    "sg:phone":"+44 1824 703992",
    "sg:postcode":"LL15 1BB",
    "sg:province":"Denbighshire",
    "sg:tags":[
        "agency",
        "activity"
    ],
    "wof:name":"TOURIST INFORMATION CENTRE",
    "wof:placetype":"venue"
},
  "geometry": {"coordinates":[-3.3045220375,53.1140174866],"type":"Point"}
}