{
  "type": "Feature",
  "properties": {
    "iso:country":"GB",
    "sg:address":"25 College Road",
    "sg:city":"Bromley",
    "sg:classifiers":[
        {
            "category":"Autos & Motor Vehicles",
            "subcategory":"Automobile Sales",
            "type":"Retail Goods"
        }
    ],
    "sg:phone":"+44 20 8290 8600",
    "sg:postcode":"BR1 3PU",
    "sg:province":"Kent",
    "sg:tags":[
        "car"
    ],
    "wof:name":"Whitehouse B M W",
    "wof:placetype":"venue"
},
  "geometry": {"coordinates":[0.014157,51.4109916687],"type":"Point"}
}