{
  "type": "Feature",
  "properties": {
    "addr:full":"34-35a Shepherds Bush Market London Greater London W12 8DQ",
    "addr:housenumber":"34-35a",
    "addr:postcode":"w12 8dq",
    "addr:street":"Shepherds Bush Market",
    "iso:country":"GB",
    "sg:address":"34-35a Shepherds Bush Market",
    "sg:city":"London",
    "sg:classifiers":[
        {
            "category":"Shopping",
            "subcategory":"Clothing, Apparel, & Fashions",
            "type":"Retail Goods"
        }
    ],
    "sg:phone":"+44 20 8749 6077",
    "sg:postcode":"W12 8DQ",
    "sg:province":"Greater London",
    "sg:tags":[
        "lingerie",
        "hosiery"
    ],
    "wof:name":"British Lingerie",
    "wof:placetype":"venue"
},
  "geometry": {"coordinates":[-0.218723,51.504841],"type":"Point"}
}