{
  "type": "Feature",
  "properties": {
    "addr:full":"50 Denmark Road Northampton Northamptonshire NN1 5QS",
    "addr:housenumber":"50",
    "addr:postcode":"nn1 5qs",
    "addr:street":"Denmark Road",
    "iso:country":"GB",
    "sg:address":"50 Denmark Road",
    "sg:city":"Northampton",
    "sg:classifiers":[
        {
            "category":"Health Services",
            "subcategory":"Podiatrist",
            "type":"Services"
        }
    ],
    "sg:phone":"+44 1604 635012",
    "sg:postcode":"NN1 5QS",
    "sg:province":"Northamptonshire",
    "sg:tags":[
        "podiatrists",
        "chiropodist"
    ],
    "wof:name":"Donna M Williamson",
    "wof:placetype":"venue"
},
  "geometry": {"coordinates":[-0.886874,52.239109],"type":"Point"}
}