{
  "type": "Feature",
  "properties": {
    "addr:full":"141 High Street, Chalfont St Peter Gerrards Cross Buckinghamshire SL9 9QL",
    "addr:housenumber":"141",
    "addr:postcode":"sl9 9ql",
    "addr:street":"High Street",
    "iso:country":"GB",
    "sg:address":"141 High Street, Chalfont St Peter",
    "sg:city":"Gerrards Cross",
    "sg:classifiers":[
        {
            "category":"Real Estate",
            "subcategory":"Real Estate Agent",
            "type":"Services"
        }
    ],
    "sg:phone":"+44 1753 892100",
    "sg:postcode":"SL9 9QL",
    "sg:province":"Buckinghamshire",
    "wof:name":"The Barrington Partnership",
    "wof:placetype":"venue"
},
  "geometry": {"coordinates":[-0.555539,51.608089],"type":"Point"}
}