{
  "type": "Feature",
  "properties": {
    "addr:full":"65 Castellan Avenue, Gidea Park Romford Essex RM2 6EB",
    "addr:housenumber":"65",
    "addr:postcode":"rm2 6eb",
    "addr:street":"Castellan Avenue",
    "iso:country":"GB",
    "sg:address":"65 Castellan Avenue, Gidea Park",
    "sg:city":"Romford",
    "sg:classifiers":[
        {
            "category":"Professional",
            "subcategory":"Accounting & Tax Preparation",
            "type":"Services"
        }
    ],
    "sg:phone":"+44 1708 748274",
    "sg:postcode":"RM2 6EB",
    "sg:province":"Essex",
    "sg:tags":[
        "accountant"
    ],
    "wof:name":"Conrich & Co",
    "wof:placetype":"venue"
},
  "geometry": {"coordinates":[0.208872,51.588482],"type":"Point"}
}