{
  "type": "Feature",
  "properties": {
    "addr:full":"232 High St Barnet Hertfordshire EN5 5TD",
    "addr:housenumber":"232",
    "addr:postcode":"en5 5td",
    "addr:street":"High St",
    "iso:country":"GB",
    "sg:address":"232 High St",
    "sg:city":"Barnet",
    "sg:classifiers":[
        {
            "category":"Personal",
            "type":"Services"
        }
    ],
    "sg:phone":"+44 20 8440 1650",
    "sg:postcode":"EN5 5TD",
    "sg:province":"Hertfordshire",
    "sg:tags":[
        "wedding"
    ],
    "wof:name":"Bridal Suite",
    "wof:placetype":"venue"
},
  "geometry": {"coordinates":[-0.198699,51.65247],"type":"Point"}
}