{
  "type": "Feature",
  "properties": {
    "iso:country":"GB",
    "sg:address":"17 Saxby Gro",
    "sg:city":"Blackpool",
    "sg:classifiers":[
        {
            "category":"Professional",
            "subcategory":"Engineering",
            "type":"Services"
        }
    ],
    "sg:postcode":"FY4 4LA",
    "sg:province":"Lancashire",
    "sg:tags":[
        "contractor",
        "electrical",
        "engineer"
    ],
    "wof:name":"Silk,Thomas,",
    "wof:placetype":"venue"
},
  "geometry": {"coordinates":[-3.019625,53.800018],"type":"Point"}
}