{
  "type": "Feature",
  "properties": {
    "iso:country":"GB",
    "sg:address":"36 Barnes High St, Barnes",
    "sg:city":"London",
    "sg:classifiers":[
        {
            "category":"Professional",
            "subcategory":"Art Services",
            "type":"Services"
        }
    ],
    "sg:phone":"+44 20 8878 0040",
    "sg:postcode":"SW13 9LP",
    "sg:province":"Greater London",
    "sg:tags":[
        "framing"
    ],
    "wof:name":"Riverside Framing Ltd",
    "wof:placetype":"venue"
},
  "geometry": {"coordinates":[-0.251168,51.4734],"type":"Point"}
}