{
  "type": "Feature",
  "properties": {
    "addr:full":"5 Mansfield Close, Parkstone Poole Dorset BH14 0DH",
    "addr:housenumber":"5",
    "addr:postcode":"bh14 0dh",
    "addr:street":"Mansfield Close",
    "iso:country":"GB",
    "sg:address":"5 Mansfield Close, Parkstone",
    "sg:city":"Poole",
    "sg:classifiers":[
        {
            "category":"Building & Trades",
            "subcategory":"Construction",
            "type":"Services"
        }
    ],
    "sg:postcode":"BH14 0DH",
    "sg:province":"Dorset",
    "sg:tags":[
        "builder",
        "joiner",
        "carpenter"
    ],
    "wof:name":"Tony Harlow Carpentry",
    "wof:placetype":"venue"
},
  "geometry": {"coordinates":[-1.941888,50.726986],"type":"Point"}
}