{
  "type": "Feature",
  "properties": {
    "addr:full":"10-10a Market Place, Mildenhall Bury St Edmunds Cambridgeshire IP28 7EF",
    "addr:housenumber":"10-10a",
    "addr:postcode":"ip28 7ef",
    "addr:street":"Market Place;St",
    "iso:country":"GB",
    "sg:address":"10-10a Market Place, Mildenhall",
    "sg:city":"Bury St Edmunds",
    "sg:classifiers":[
        {
            "category":"Health Services",
            "subcategory":"Doctor",
            "type":"Services"
        }
    ],
    "sg:phone":"+44 1638 718177",
    "sg:postcode":"IP28 7EF",
    "sg:province":"Cambridgeshire",
    "sg:tags":[
        "practitioners"
    ],
    "wof:name":"The Whitehouse Surgery",
    "wof:placetype":"venue"
},
  "geometry": {"coordinates":[0.509929,52.343449],"type":"Point"}
}