{
  "type": "Feature",
  "properties": {
    "addr:full":"28 Cemetery Road Belper Derbyshire DE56 1EJ",
    "addr:housenumber":"28",
    "addr:postcode":"de56 1ej",
    "addr:street":"Cemetery Road",
    "iso:country":"GB",
    "sg:address":"28 Cemetery Road",
    "sg:city":"Belper",
    "sg:classifiers":[
        {
            "category":"Building & Trades",
            "subcategory":"Construction",
            "type":"Services"
        }
    ],
    "sg:phone":"+44 1773 824869",
    "sg:postcode":"DE56 1EJ",
    "sg:province":"Derbyshire",
    "sg:tags":[
        "builder"
    ],
    "wof:name":"Modern Builders",
    "wof:placetype":"venue"
},
  "geometry": {"coordinates":[-1.4788110256,53.0354614258],"type":"Point"}
}