{
  "type": "Feature",
  "properties": {
    "iso:country":"GB",
    "sg:address":"4 Queen St",
    "sg:city":"Derby",
    "sg:classifiers":[
        {
            "category":"Insurance",
            "subcategory":"Insurance Agent",
            "type":"Services"
        }
    ],
    "sg:phone":"+44 1332 348844",
    "sg:postcode":"DE1 3DL",
    "sg:province":"Derbyshire",
    "wof:name":"Hill House Hammond Ltd",
    "wof:placetype":"venue"
},
  "geometry": {"coordinates":[-1.4782379866,52.9254875183],"type":"Point"}
}