{
  "type": "Feature",
  "properties": {
    "addr:full":"58 High Street East Grinstead East Sussex RH19 3DE",
    "addr:housenumber":"58",
    "addr:postcode":"rh19 3de",
    "addr:street":"High Street",
    "iso:country":"GB",
    "sg:address":"58 High Street",
    "sg:city":"East Grinstead",
    "sg:classifiers":[
        {
            "category":"Bars & Pubs",
            "type":"Food & Drink"
        }
    ],
    "sg:phone":"+44 1342 316363",
    "sg:postcode":"RH19 3DE",
    "sg:province":"East Sussex",
    "sg:tags":[
        "pubs",
        "inn"
    ],
    "wof:name":"The Dorset Arms",
    "wof:placetype":"venue"
},
  "geometry": {"coordinates":[-0.0054410002,51.1238822937],"type":"Point"}
}