{
  "type": "Feature",
  "properties": {
    "iso:country":"GB",
    "sg:address":"52 Park Street",
    "sg:city":"Camberley",
    "sg:classifiers":[
        {
            "category":"Professional",
            "subcategory":"Computer Services",
            "type":"Services"
        }
    ],
    "sg:phone":"+44 1276 681261",
    "sg:postcode":"GU15 3PT",
    "sg:province":"Berkshire",
    "sg:tags":[
        "consultant"
    ],
    "wof:name":"Coveford Data Systems Ltd.",
    "wof:placetype":"venue"
},
  "geometry": {"coordinates":[-0.7476069927,51.3363380432],"type":"Point"}
}