{
  "type": "Feature",
  "properties": {
    "addr:full":"42b Windmill Road Croydon Surrey CR0 2XP",
    "addr:housenumber":"42b",
    "addr:postcode":"cr0 2xp",
    "addr:street":"Windmill Road",
    "iso:country":"GB",
    "sg:address":"42b Windmill Road",
    "sg:city":"Croydon",
    "sg:classifiers":[
        {
            "category":"Retail",
            "subcategory":"Auto Repair",
            "type":"Services"
        }
    ],
    "sg:phone":"+44 20 8665 1190",
    "sg:postcode":"CR0 2XP",
    "sg:province":"Surrey",
    "sg:tags":[
        "modification",
        "garage"
    ],
    "wof:name":"R J Autos",
    "wof:placetype":"venue"
},
  "geometry": {"coordinates":[-0.101426,51.385014],"type":"Point"}
}