{
  "type": "Feature",
  "properties": {
    "addr:full":"Units 2-4, Kinsley Industrial Estate Pontefract West Yorkshire WF9 5JB",
    "addr:housenumber":"units 2-4",
    "addr:postcode":"wf9 5jb",
    "addr:street":"Kinsley Industrial Estate Pontefract West",
    "iso:country":"GB",
    "sg:address":"Units 2-4, Kinsley Industrial Estate",
    "sg:city":"Pontefract",
    "sg:classifiers":[
        {
            "category":"Wholesale",
            "subcategory":"Meat",
            "type":"Manufacturing & Wholesale Goods"
        }
    ],
    "sg:phone":"+44 1977 613053",
    "sg:postcode":"WF9 5JB",
    "sg:province":"West Yorkshire",
    "sg:tags":[
        "product"
    ],
    "wof:name":"Premier Quality Foods Ltd.",
    "wof:placetype":"venue"
},
  "geometry": {"coordinates":[-1.360730052,53.6252212524],"type":"Point"}
}