{
  "type": "Feature",
  "properties": {
    "iso:country":"GB",
    "sg:address":"Bank Chambers, 2 High Street",
    "sg:city":"New Malden",
    "sg:classifiers":[
        {
            "category":"Professional",
            "subcategory":"Lawyer & Legal Services",
            "type":"Services"
        }
    ],
    "sg:postcode":"KT3 4HF",
    "sg:province":"Surrey",
    "sg:tags":[
        "solicitor"
    ],
    "wof:name":"A C S Hards & Co.",
    "wof:placetype":"venue"
},
  "geometry": {"coordinates":[-0.256194,51.401772],"type":"Point"}
}