{
  "type": "Feature",
  "properties": {
    "iso:country":"GB",
    "sg:address":"102 Western Road",
    "sg:city":"Brighton",
    "sg:classifiers":[
        {
            "category":"Shopping",
            "subcategory":"Shoes",
            "type":"Retail Goods"
        }
    ],
    "sg:phone":"+44 1273 770966",
    "sg:postcode":"BN1 2AA",
    "sg:province":"East Sussex",
    "sg:tags":[
        "shop"
    ],
    "wof:name":"Valentine Shoes",
    "wof:placetype":"venue"
},
  "geometry": {"coordinates":[-0.153115,50.824791],"type":"Point"}
}