{
  "type": "Feature",
  "properties": {
    "addr:full":"7 Buchan Close Newport Newport NP20 3HF",
    "addr:housenumber":"7",
    "addr:postcode":"np20 3hf",
    "addr:street":"Buchan Close",
    "iso:country":"GB",
    "sg:address":"7 Buchan Close",
    "sg:city":"Newport",
    "sg:classifiers":[
        {
            "category":"Building & Trades",
            "subcategory":"Construction",
            "type":"Services"
        }
    ],
    "sg:postcode":"NP20 3HF",
    "sg:province":"Newport",
    "sg:tags":[
        "roofing"
    ],
    "wof:name":"John H Hawkins",
    "wof:placetype":"venue"
},
  "geometry": {"coordinates":[-3.014554,51.576378],"type":"Point"}
}