{
  "type": "Feature",
  "properties": {
    "addr:full":"Millbay Docks Plymouth Devon PL1 3EF",
    "addr:postcode":"pl1 3ef",
    "addr:street":"Millbay",
    "iso:country":"GB",
    "sg:address":"Millbay Docks",
    "sg:city":"Plymouth",
    "sg:classifiers":[
        {
            "category":"Harbor",
            "type":"Transportation"
        }
    ],
    "sg:phone":"+44 1752 662191",
    "sg:postcode":"PL1 3EF",
    "sg:province":"Devon",
    "sg:tags":[
        "dock",
        "ports",
        "harbour"
    ],
    "wof:name":"Associated British Ports",
    "wof:placetype":"venue"
},
  "geometry": {"coordinates":[-4.1557879448,50.3673629761],"type":"Point"}
}