{
  "type": "Feature",
  "properties": {
    "addr:full":"10 Edward Avenue Morden Surrey SM4 6EP",
    "addr:housenumber":"10",
    "addr:postcode":"sm4 6ep",
    "addr:street":"Edward Avenue",
    "iso:country":"GB",
    "sg:address":"10 Edward Avenue",
    "sg:city":"Morden",
    "sg:classifiers":[
        {
            "category":"Home & Garden",
            "subcategory":"Home Furnishings",
            "type":"Retail Goods"
        }
    ],
    "sg:postcode":"SM4 6EP",
    "sg:province":"Surrey",
    "sg:tags":[
        "furnishers",
        "planner",
        "kitchen"
    ],
    "wof:name":"Victoria Kitchens",
    "wof:placetype":"venue"
},
  "geometry": {"coordinates":[-0.1813679934,51.3954467773],"type":"Point"}
}