{
  "type": "Feature",
  "properties": {
    "addr:full":"49 Street La Leeds West Yorkshire LS8 1AP",
    "addr:postcode":"ls8 1ap",
    "addr:street":"49 Street",
    "iso:country":"GB",
    "sg:address":"49 Street La",
    "sg:city":"Leeds",
    "sg:classifiers":[
        {
            "category":"Shopping",
            "type":"Retail Goods"
        }
    ],
    "sg:phone":"+44 113 288 8585",
    "sg:postcode":"LS8 1AP",
    "sg:province":"West Yorkshire",
    "sg:tags":[
        "part",
        "accessory"
    ],
    "wof:name":"Vital Signs",
    "wof:placetype":"venue"
},
  "geometry": {"coordinates":[-1.5087510347,53.8441162109],"type":"Point"}
}