{
  "type": "Feature",
  "properties": {
    "iso:country":"GB",
    "sg:address":"45 Eagle Way",
    "sg:city":"Southend On Sea",
    "sg:classifiers":[
        {
            "category":"Real Estate",
            "subcategory":"Real Estate Agent",
            "type":"Services"
        }
    ],
    "sg:phone":"+44 1702 292526",
    "sg:postcode":"SS3 9XZ",
    "sg:province":"Essex",
    "wof:name":"Old Shoebury Combined Services",
    "wof:placetype":"venue"
},
  "geometry": {"coordinates":[0.7908089757,51.5375518799],"type":"Point"}
}