{
  "type": "Feature",
  "properties": {
    "iso:country":"GB",
    "sg:address":"82 Maxwell Ave, Bearsden",
    "sg:city":"Glasgow",
    "sg:classifiers":[
        {
            "category":"Government",
            "subcategory":"City Hall",
            "type":"Public Place"
        },
        {
            "category":"Retail",
            "subcategory":"Event Space",
            "type":"Services"
        },
        {
            "category":"Government",
            "subcategory":"Office",
            "type":"Public Place"
        }
    ],
    "sg:phone":"+44 141 942 2679",
    "sg:postcode":"G61 1NZ",
    "sg:province":"East Dunbartonshire",
    "sg:tags":[
        "function",
        "hire",
        "local",
        "room"
    ],
    "wof:name":"EAST DUNBARTONSHIRE COUNCIL",
    "wof:placetype":"venue"
},
  "geometry": {"coordinates":[-4.336825,55.906746],"type":"Point"}
}