{
  "type": "Feature",
  "properties": {
    "iso:country":"GB",
    "sg:address":"Parliament St",
    "sg:city":"Stroud",
    "sg:classifiers":[
        {
            "category":"Arts & Performance",
            "subcategory":"Theater",
            "type":"Entertainment"
        }
    ],
    "sg:phone":"+44 1453 833184",
    "sg:postcode":"GL5 1LW",
    "sg:province":"Gloucestershire",
    "sg:tags":[
        "hall",
        "theatre",
        "concert"
    ],
    "wof:name":"Cotswold Players (The)",
    "wof:placetype":"venue"
},
  "geometry": {"coordinates":[-2.2115290165,51.7453231812],"type":"Point"}
}