{
  "type": "Feature",
  "properties": {
    "iso:country":"GB",
    "sg:address":"Rectory Gardens, Worthen",
    "sg:city":"Shrewsbury",
    "sg:classifiers":[
        {
            "category":"Social Services",
            "subcategory":"Adult Care",
            "type":"Services"
        }
    ],
    "sg:phone":"+44 1743 891591",
    "sg:postcode":"SY5 9JU",
    "sg:province":"Shropshire",
    "sg:tags":[
        "housing",
        "sheltered"
    ],
    "wof:name":"South Shropshire Housing Association",
    "wof:placetype":"venue"
},
  "geometry": {"coordinates":[-2.994581,52.634846],"type":"Point"}
}