{
  "type": "Feature",
  "properties": {
    "addr:full":"Bailey Flat Farm Buxton Derbyshire SK17 7JG",
    "addr:postcode":"sk17 7jg",
    "iso:country":"GB",
    "sg:address":"Bailey Flat Farm",
    "sg:city":"Buxton",
    "sg:classifiers":[
        {
            "category":"Building & Trades",
            "subcategory":"Construction",
            "type":"Services"
        }
    ],
    "sg:phone":"+44 1298 73224",
    "sg:postcode":"SK17 7JG",
    "sg:province":"Derbyshire",
    "sg:tags":[
        "joiner",
        "carpenter"
    ],
    "wof:name":"S J Cocker",
    "wof:placetype":"venue"
},
  "geometry": {"coordinates":[-1.9130489826,53.2603874207],"type":"Point"}
}