{
  "type": "Feature",
  "properties": {
    "addr:full":"14 Clifton Road Exeter Devon EX1 2BR",
    "addr:housenumber":"14",
    "addr:postcode":"ex1 2br",
    "addr:street":"Clifton Road",
    "iso:country":"GB",
    "sg:address":"14 Clifton Road",
    "sg:city":"Exeter",
    "sg:classifiers":[
        {
            "category":"Personal",
            "subcategory":"Beauty Salon",
            "type":"Services"
        }
    ],
    "sg:postcode":"EX1 2BR",
    "sg:province":"Devon",
    "sg:tags":[
        "unisex",
        "hairdresser"
    ],
    "wof:name":"Jennys",
    "wof:placetype":"venue"
},
  "geometry": {"coordinates":[-3.519588,50.726086],"type":"Point"}
}