{
  "type": "Feature",
  "properties": {
    "addr:full":"High St Clapham Greater London SW4 7UH",
    "addr:postcode":"sw4 7uh",
    "addr:street":"High St",
    "iso:country":"GB",
    "sg:address":"High St",
    "sg:city":"Clapham",
    "sg:classifiers":[
        {
            "category":"Food & Beverages",
            "subcategory":"Supermarket",
            "type":"Retail Goods"
        }
    ],
    "sg:phone":"+44 20 7498 9396",
    "sg:postcode":"SW4 7UH",
    "sg:province":"Greater London",
    "wof:name":"J Sainsbury PLC",
    "wof:placetype":"venue"
},
  "geometry": {"coordinates":[-0.1392340064,51.4609794617],"type":"Point"}
}