{
  "type": "Feature",
  "properties": {
    "iso:country":"GB",
    "sg:address":"46 Heol Y Coed",
    "sg:city":"Pontyclun",
    "sg:classifiers":[
        {
            "category":"Military Area",
            "subcategory":"Air Force Base",
            "type":"Public Place"
        }
    ],
    "sg:postcode":"CF72 9AT",
    "sg:province":"Bridgend",
    "sg:tags":[
        "taxi",
        "hire",
        "private"
    ],
    "wof:name":"Regal Taxis",
    "wof:placetype":"venue"
},
  "geometry": {"coordinates":[-3.3825199604,51.5244560242],"type":"Point"}
}