{
  "type": "Feature",
  "properties": {
    "addr:full":"Unit 15 Tait Road Industrial Estate Croydon Surrey CR0 2DP",
    "addr:housenumber":"unit 15",
    "addr:postcode":"cr0 2dp",
    "addr:street":"Tait Road Industrial Estate",
    "iso:country":"GB",
    "sg:address":"Unit 15 Tait Road Industrial Estate",
    "sg:city":"Croydon",
    "sg:classifiers":[
        {
            "category":"Professional",
            "subcategory":"Printing & Photocopies",
            "type":"Services"
        }
    ],
    "sg:postcode":"CR0 2DP",
    "sg:province":"Surrey",
    "sg:tags":[
        "printer"
    ],
    "wof:name":"Lundie Brothers Ltd.",
    "wof:placetype":"venue"
},
  "geometry": {"coordinates":[-0.087977998,51.3850021362],"type":"Point"}
}