{
  "type": "Feature",
  "properties": {
    "addr:full":"Weavers Cottage Museum, 23-27 Wellwynd Airdrie North Lanarkshire ML6 0BN",
    "addr:housenumber":"23-27",
    "addr:postcode":"ml6 0bn",
    "addr:street":"Wellwynd Airdrie",
    "iso:country":"GB",
    "sg:address":"Weavers Cottage Museum, 23-27 Wellwynd",
    "sg:city":"Airdrie",
    "sg:classifiers":[
        {
            "category":"Government",
            "subcategory":"Office",
            "type":"Public Place"
        }
    ],
    "sg:phone":"+44 1236 747712",
    "sg:postcode":"ML6 0BN",
    "sg:province":"North Lanarkshire",
    "sg:tags":[
        "local"
    ],
    "wof:name":"North Lanarkshire Council",
    "wof:placetype":"venue"
},
  "geometry": {"coordinates":[-3.9942009449,55.8868026733],"type":"Point"}
}