{
  "type": "Feature",
  "properties": {
    "addr:full":"122 North End Croydon Surrey CR0 1UD",
    "addr:housenumber":"122",
    "addr:postcode":"cr0 1ud",
    "addr:street":"North End",
    "iso:country":"GB",
    "sg:address":"122 North End",
    "sg:city":"Croydon",
    "sg:classifiers":[
        {
            "category":"Bars & Pubs",
            "subcategory":"Wine Bar",
            "type":"Food & Drink"
        }
    ],
    "sg:phone":"+44 20 8680 2419",
    "sg:postcode":"CR0 1UD",
    "sg:province":"Surrey",
    "sg:website":"http://www.davy.co.uk",
    "wof:name":"Davys Wine Vaults",
    "wof:placetype":"venue"
},
  "geometry": {"coordinates":[-0.1019489989,51.3773269653],"type":"Point"}
}