{
  "type": "Feature",
  "properties": {
    "addr:full":"54 Liverpool Road, Eccles Manchester Greater Manchester M30 0WA",
    "addr:housenumber":"54",
    "addr:postcode":"m30 0wa",
    "addr:street":"Liverpool Road",
    "iso:country":"GB",
    "sg:address":"54 Liverpool Road, Eccles",
    "sg:city":"Manchester",
    "sg:classifiers":[
        {
            "category":"Personal",
            "subcategory":"Beauty Salon",
            "type":"Services"
        },
        {
            "category":"Personal",
            "subcategory":"Barber",
            "type":"Services"
        }
    ],
    "sg:phone":"+44 161 787 9394",
    "sg:postcode":"M30 0WA",
    "sg:province":"Greater Manchester",
    "sg:tags":[
        "unisex",
        "hairdresser"
    ],
    "wof:name":"Images",
    "wof:placetype":"venue"
},
  "geometry": {"coordinates":[-2.3470990658,53.483417511],"type":"Point"}
}