{
  "type": "Feature",
  "properties": {
    "iso:country":"GB",
    "sg:address":"Coach Lane",
    "sg:city":"Redruth",
    "sg:classifiers":[
        {
            "category":"Shopping",
            "type":"Retail Goods"
        }
    ],
    "sg:postcode":"TR15 2TP",
    "sg:province":"Cornwall",
    "sg:tags":[
        "merchant"
    ],
    "wof:name":"Coach Lane Feed Stores",
    "wof:placetype":"venue"
},
  "geometry": {"coordinates":[-5.234394,50.23032],"type":"Point"}
}