{
  "type": "Feature",
  "properties": {
    "addr:full":"Wharf Street, Chadderton Oldham Lancashire OL9 7PF",
    "addr:postcode":"ol9 7pf",
    "addr:street":"Wharf Street",
    "iso:country":"GB",
    "sg:address":"Wharf Street, Chadderton",
    "sg:city":"Oldham",
    "sg:classifiers":[
        {
            "category":"Professional",
            "subcategory":"Engineering",
            "type":"Services"
        }
    ],
    "sg:phone":"+44 161 633 1633",
    "sg:postcode":"OL9 7PF",
    "sg:province":"Lancashire",
    "sg:tags":[
        "engineer"
    ],
    "wof:name":"QUALICUT ENGINEERING LTD",
    "wof:placetype":"venue"
},
  "geometry": {"coordinates":[-2.141151,53.526588],"type":"Point"}
}