{
  "type": "Feature",
  "properties": {
    "addr:full":"22 Finchley Rd London Greater London NW8 6EB",
    "addr:housenumber":"22",
    "addr:postcode":"nw8 6eb",
    "addr:street":"Finchley Rd",
    "iso:country":"GB",
    "sg:address":"22 Finchley Rd",
    "sg:city":"London",
    "sg:classifiers":[
        {
            "category":"Shopping",
            "subcategory":"Mobile Phones",
            "type":"Retail Goods"
        }
    ],
    "sg:postcode":"NW8 6EB",
    "sg:province":"Greater London",
    "wof:name":"Prestige Technical",
    "wof:placetype":"venue"
},
  "geometry": {"coordinates":[-0.1759160012,51.5359992981],"type":"Point"}
}