{
  "type": "Feature",
  "properties": {
    "iso:country":"GB",
    "sg:address":"22 Finchley Rd",
    "sg:city":"London",
    "sg:classifiers":[
        {
            "category":"Shopping",
            "subcategory":"Mobile Phones",
            "type":"Retail Goods"
        }
    ],
    "sg:postcode":"NW8 6EB",
    "sg:province":"Greater London",
    "wof:name":"Prestige Technical",
    "wof:placetype":"venue"
},
  "geometry": {"coordinates":[-0.1759160012,51.5359992981],"type":"Point"}
}