{
  "type": "Feature",
  "properties": {
    "addr:full":"33 Ffordd Gwenllian, Llay Wrexham Wrexham LL12 0UW",
    "addr:housenumber":"33",
    "addr:postcode":"ll12 0uw",
    "addr:street":"Ffordd Gwenllian",
    "iso:country":"GB",
    "sg:address":"33 Ffordd Gwenllian, Llay",
    "sg:city":"Wrexham",
    "sg:classifiers":[
        {
            "category":"Professional",
            "subcategory":"Lawyer & Legal Services",
            "type":"Services"
        }
    ],
    "sg:phone":"+44 1978 856192",
    "sg:postcode":"LL12 0UW",
    "sg:province":"Wrexham",
    "wof:name":"Injury Claims Bureau",
    "wof:placetype":"venue"
},
  "geometry": {"coordinates":[-2.986172,53.09486],"type":"Point"}
}