{
  "type": "Feature",
  "properties": {
    "addr:full":"101 Ampthill Road, Flitwick Bedford Bedfordshire MK45 1BE",
    "addr:housenumber":"101",
    "addr:postcode":"mk45 1be",
    "addr:street":"Ampthill Road",
    "iso:country":"GB",
    "sg:address":"101 Ampthill Road, Flitwick",
    "sg:city":"Bedford",
    "sg:classifiers":[
        {
            "category":"Autos & Motor Vehicles",
            "subcategory":"Automobile Sales",
            "type":"Retail Goods"
        }
    ],
    "sg:phone":"+44 1525 633003",
    "sg:postcode":"MK45 1BE",
    "sg:province":"Bedfordshire",
    "sg:tags":[
        "commercial"
    ],
    "wof:name":"Mid-Beds van Centre",
    "wof:placetype":"venue"
},
  "geometry": {"coordinates":[-0.501149,52.014099],"type":"Point"}
}