{
  "type": "Feature",
  "properties": {
    "addr:full":"Rectors Way Weston-super-mare Somerset BS23 3NP",
    "addr:postcode":"bs23 3np",
    "addr:street":"Rectors Way",
    "iso:country":"GB",
    "sg:address":"Rectors Way",
    "sg:city":"Weston-super-mare",
    "sg:classifiers":[
        {
            "category":"Professional",
            "subcategory":"Testing Lab",
            "type":"Services"
        },
        {
            "category":"Retail",
            "subcategory":"Auto Rental",
            "type":"Services"
        },
        {
            "category":"Retail",
            "subcategory":"Auto Repair",
            "type":"Services"
        }
    ],
    "sg:phone":"+44 1934 618292",
    "sg:postcode":"BS23 3NP",
    "sg:province":"Somerset",
    "sg:tags":[
        "hire",
        "van",
        "mot",
        "garage",
        "truck",
        "modification"
    ],
    "wof:name":"Hutton Coach Hire",
    "wof:placetype":"venue"
},
  "geometry": {"coordinates":[-2.9678890705,51.3402862549],"type":"Point"}
}