{
  "type": "Feature",
  "properties": {
    "iso:country":"GB",
    "sg:address":"Oaktree Cottage, Bushy Common, Gressenhall",
    "sg:city":"Dereham",
    "sg:classifiers":[
        {
            "category":"Building & Trades",
            "subcategory":"Construction",
            "type":"Services"
        }
    ],
    "sg:postcode":"NR19 2NZ",
    "sg:province":"Norfolk",
    "sg:tags":[
        "decorator",
        "painter"
    ],
    "wof:name":"T E B Services",
    "wof:placetype":"venue"
},
  "geometry": {"coordinates":[0.88534,52.684109],"type":"Point"}
}