{
  "type": "Feature",
  "properties": {
    "addr:full":"193a Shirland Road London Greater London W9 2EU",
    "addr:housenumber":"193a",
    "addr:postcode":"w9 2eu",
    "addr:street":"Shirland Road",
    "iso:country":"GB",
    "sg:address":"193a Shirland Road",
    "sg:city":"London",
    "sg:classifiers":[
        {
            "category":"Taxi",
            "type":"Transportation"
        }
    ],
    "sg:phone":"+44 20 7266 1919",
    "sg:postcode":"W9 2EU",
    "sg:province":"Greater London",
    "sg:tags":[
        "mini",
        "cab"
    ],
    "wof:name":"Carlton Cars",
    "wof:placetype":"venue"
},
  "geometry": {"coordinates":[-0.1961739957,51.5276107788],"type":"Point"}
}