{
  "type": "Feature",
  "properties": {
    "iso:country":"GB",
    "sg:address":"11 Waterloo Place, Elphinstone",
    "sg:city":"Tranent",
    "sg:classifiers":[
        {
            "category":"Home & Garden",
            "subcategory":"Household Appliances",
            "type":"Retail Goods"
        },
        {
            "category":"Retail",
            "subcategory":"Repair Shop",
            "type":"Services"
        }
    ],
    "sg:phone":"+44 1875 611510",
    "sg:postcode":"EH33 2NW",
    "sg:province":"East Lothian",
    "sg:tags":[
        "machine",
        "electrical",
        "washing"
    ],
    "wof:name":"Washing Machine Doctor",
    "wof:placetype":"venue"
},
  "geometry": {"coordinates":[-2.96704,55.92466],"type":"Point"}
}