{
  "type": "Feature",
  "properties": {
    "addr:full":"The Birches, Wolverley Kidderminster Staffordshire DY11 5XE",
    "addr:postcode":"dy11 5xe",
    "addr:street":"Wolverley",
    "iso:country":"GB",
    "sg:address":"The Birches, Wolverley",
    "sg:city":"Kidderminster",
    "sg:classifiers":[
        {
            "category":"Building & Trades",
            "subcategory":"Construction",
            "type":"Services"
        }
    ],
    "sg:postcode":"DY11 5XE",
    "sg:province":"Staffordshire",
    "sg:tags":[
        "window",
        "replacement"
    ],
    "wof:name":"Embassy Windows",
    "wof:placetype":"venue"
},
  "geometry": {"coordinates":[-2.2552659512,52.4104957581],"type":"Point"}
}