{
  "type": "Feature",
  "properties": {
    "addr:full":"20 Teal Close, Quedgeley Gloucester Gloucestershire GL2 4GR",
    "addr:housenumber":"20",
    "addr:postcode":"gl2 4gr",
    "addr:street":"Teal Close",
    "iso:country":"GB",
    "sg:address":"20 Teal Close, Quedgeley",
    "sg:city":"Gloucester",
    "sg:classifiers":[
        {
            "category":"Building & Trades",
            "subcategory":"Cleaning & Sanitation",
            "type":"Services"
        },
        {
            "category":"Home & Garden",
            "subcategory":"Carpets & Floor Coverings",
            "type":"Retail Goods"
        }
    ],
    "sg:phone":"+44 1452 883334",
    "sg:postcode":"GL2 4GR",
    "sg:province":"Gloucestershire",
    "sg:tags":[
        "cleaner",
        "upholstery",
        "commercial"
    ],
    "wof:name":"Hayward Cleaning Services",
    "wof:placetype":"venue"
},
  "geometry": {"coordinates":[-2.2937939167,51.8285217285],"type":"Point"}
}