{
  "type": "Feature",
  "properties": {
    "addr:full":"Beaconsfield House, Fieldhouse Lane Marlow Berkshire SL7 1LW",
    "addr:postcode":"sl7 1lw",
    "addr:street":"Fieldhouse Lane",
    "iso:country":"GB",
    "sg:address":"Beaconsfield House, Fieldhouse Lane",
    "sg:city":"Marlow",
    "sg:classifiers":[
        {
            "category":"Building & Trades",
            "subcategory":"Plumbing",
            "type":"Services"
        }
    ],
    "sg:phone":"+44 1628 484995",
    "sg:postcode":"SL7 1LW",
    "sg:province":"Berkshire",
    "sg:tags":[
        "drain",
        "clearance",
        "sewer"
    ],
    "wof:name":"Clear Drains (U K) Ltd.",
    "wof:placetype":"venue"
},
  "geometry": {"coordinates":[-0.762194,51.57375],"type":"Point"}
}