{
  "type": "Feature",
  "properties": {
    "iso:country":"GB",
    "sg:address":"Wayside Farm, Mill Lane, Ashley",
    "sg:city":"Altrincham",
    "sg:classifiers":[
        {
            "category":"Farming",
            "subcategory":"Farm",
            "type":"Manufacturing & Wholesale Goods"
        }
    ],
    "sg:phone":"+44 161 929 6920",
    "sg:postcode":"WA15 0RE",
    "sg:province":"Cheshire",
    "sg:tags":[
        "mixed",
        "crop"
    ],
    "wof:name":"Christopher Edward Blockley",
    "wof:placetype":"venue"
},
  "geometry": {"coordinates":[-2.3395750523,53.3545188904],"type":"Point"}
}