{
  "type": "Feature",
  "properties": {
    "iso:country":"GB",
    "sg:address":"9 10 Oaklands Ct, Martock Business Pk",
    "sg:city":"Martock",
    "sg:classifiers":[
        {
            "category":"Professional",
            "subcategory":"Engineering",
            "type":"Services"
        }
    ],
    "sg:phone":"+44 1935 823383",
    "sg:postcode":"TA12 6HB",
    "sg:province":"Somerset",
    "sg:tags":[
        "precision",
        "engineer"
    ],
    "wof:name":"Kemek (P M S) Ltd",
    "wof:placetype":"venue"
},
  "geometry": {"coordinates":[-2.770669,50.967247],"type":"Point"}
}