{
  "type": "Feature",
  "properties": {
    "addr:full":"7 Aylmer Road Leicester Leicestershire LE3 1NA",
    "addr:housenumber":"7",
    "addr:postcode":"le3 1na",
    "addr:street":"Aylmer Road",
    "iso:country":"GB",
    "sg:address":"7 Aylmer Road",
    "sg:city":"Leicester",
    "sg:classifiers":[
        {
            "category":"Government",
            "subcategory":"Post Office",
            "type":"Public Place"
        }
    ],
    "sg:phone":"+44 116 285 8515",
    "sg:postcode":"LE3 1NA",
    "sg:province":"Leicestershire",
    "wof:name":"Aylmer Post Office",
    "wof:placetype":"venue"
},
  "geometry": {"coordinates":[-1.1754720211,52.6277351379],"type":"Point"}
}