{
  "type": "Feature",
  "properties": {
    "addr:full":"Unit 101, Glan Yr Afon Industrial Estate Aberystwyth Ceredigion SY23 3JQ",
    "addr:housenumber":"101",
    "addr:postcode":"sy23 3jq",
    "addr:street":"Glan Yr Afon Industrial Estate",
    "iso:country":"GB",
    "sg:address":"Unit 101, Glan Yr Afon Industrial Estate",
    "sg:city":"Aberystwyth",
    "sg:classifiers":[
        {
            "category":"Home & Garden",
            "subcategory":"Kitchen Supply",
            "type":"Retail Goods"
        }
    ],
    "sg:phone":"+44 1437 890990",
    "sg:postcode":"SY23 3JQ",
    "sg:province":"Ceredigion",
    "sg:tags":[
        "equipment",
        "catering"
    ],
    "wof:name":"Aberystwyth Catering Centre",
    "wof:placetype":"venue"
},
  "geometry": {"coordinates":[-4.059997,52.406124],"type":"Point"}
}