{
  "type": "Feature",
  "properties": {
    "iso:country":"GB",
    "sg:address":"Top Floor, 45 Sartoris Road",
    "sg:city":"Rushden",
    "sg:classifiers":[
        {
            "category":"Professional",
            "subcategory":"Printing & Photocopies",
            "type":"Services"
        }
    ],
    "sg:phone":"+44 1933 315930",
    "sg:postcode":"NN10 9TL",
    "sg:province":"Bedfordshire",
    "sg:tags":[
        "process",
        "screen",
        "printer"
    ],
    "wof:name":"Elite Screen Printers & Embroiderers Ltd.",
    "wof:placetype":"venue"
},
  "geometry": {"coordinates":[-0.598024,52.287624],"type":"Point"}
}