{
  "type": "Feature",
  "properties": {
    "iso:country":"GB",
    "sg:address":"White Lodge, Wood Lane",
    "sg:city":"Iver",
    "sg:classifiers":[
        {
            "category":"Sports & Exercise",
            "subcategory":"Stables",
            "type":"Entertainment"
        },
        {
            "category":"Personal",
            "subcategory":"Adult",
            "type":"Services"
        }
    ],
    "sg:phone":"+44 1753 653000",
    "sg:postcode":"SL0 0LE",
    "sg:province":"Berkshire",
    "sg:tags":[
        "education",
        "equestrian"
    ],
    "wof:name":"White Lodge Stables",
    "wof:placetype":"venue"
},
  "geometry": {"coordinates":[-0.5206189752,51.5365447998],"type":"Point"}
}