{
  "type": "Feature",
  "properties": {
    "iso:country":"GB",
    "sg:address":"18 Melsonby Close, Moorside",
    "sg:city":"Sunderland",
    "sg:classifiers":[
        {
            "category":"Building & Trades",
            "subcategory":"Construction",
            "type":"Services"
        }
    ],
    "sg:postcode":"SR3 2QL",
    "sg:province":"Tyne and Wear",
    "sg:tags":[
        "glazier"
    ],
    "wof:name":"Priory Glazing",
    "wof:placetype":"venue"
},
  "geometry": {"coordinates":[-1.4291859865,54.8669052124],"type":"Point"}
}