{
  "type": "Feature",
  "properties": {
    "iso:country":"GB",
    "sg:address":"61 Bardolph St",
    "sg:city":"Leicester",
    "sg:classifiers":[
        {
            "category":"Manufacturing",
            "subcategory":"Apparel",
            "type":"Manufacturing & Wholesale Goods"
        }
    ],
    "sg:phone":"+44 116 266 1566",
    "sg:postcode":"LE4 6EH",
    "sg:province":"Leicestershire",
    "sg:tags":[
        "shirt",
        "maker"
    ],
    "wof:name":"The Exxtra Look",
    "wof:placetype":"venue"
},
  "geometry": {"coordinates":[-1.1168320179,52.6475143433],"type":"Point"}
}