{
  "type": "Feature",
  "properties": {
    "iso:country":"GB",
    "sg:address":"13 Mid Kent Shopping Centre, Castle Rd",
    "sg:city":"Maidstone",
    "sg:classifiers":[
        {
            "category":"Shopping",
            "subcategory":"Pharmacy",
            "type":"Retail Goods"
        }
    ],
    "sg:phone":"+44 1622 756477",
    "sg:postcode":"ME16 0PU",
    "sg:province":"Kent",
    "sg:tags":[
        "pharmacist",
        "chemist"
    ],
    "wof:name":"Hills Pharmacy",
    "wof:placetype":"venue"
},
  "geometry": {"coordinates":[0.4971100092,51.2860603333],"type":"Point"}
}