{
  "type": "Feature",
  "properties": {
    "addr:full":"23 Nideggen Close Thatcham Berkshire RG19 4HS",
    "addr:housenumber":"23",
    "addr:postcode":"rg19 4hs",
    "addr:street":"Nideggen Close",
    "iso:country":"GB",
    "sg:address":"23 Nideggen Close",
    "sg:city":"Thatcham",
    "sg:classifiers":[
        {
            "category":"Retail",
            "subcategory":"Repair Shop",
            "type":"Services"
        },
        {
            "category":"Professional",
            "subcategory":"Art Services",
            "type":"Services"
        }
    ],
    "sg:phone":"+44 1635 202995",
    "sg:postcode":"RG19 4HS",
    "sg:province":"Berkshire",
    "sg:tags":[
        "decorator",
        "maintenance",
        "painter"
    ],
    "wof:name":"D J HAYES",
    "wof:placetype":"venue"
},
  "geometry": {"coordinates":[-1.2572610378,51.4012832642],"type":"Point"}
}