{
  "type": "Feature",
  "properties": {
    "addr:full":"Appleton House, 33 Sayce Street Widnes Cheshire WA8 6EE",
    "addr:housenumber":"33",
    "addr:postcode":"wa8 6ee",
    "addr:street":"Sayce Street",
    "iso:country":"GB",
    "sg:address":"Appleton House, 33 Sayce Street",
    "sg:city":"Widnes",
    "sg:classifiers":[
        {
            "category":"Professional",
            "subcategory":"Accounting & Tax Preparation",
            "type":"Services"
        }
    ],
    "sg:phone":"+44 151 495 3487",
    "sg:postcode":"WA8 6EE",
    "sg:province":"Cheshire",
    "sg:tags":[
        "accountant"
    ],
    "wof:name":"Capital Accounts",
    "wof:placetype":"venue"
},
  "geometry": {"coordinates":[-2.7275130749,53.3711776733],"type":"Point"}
}