{
  "type": "Feature",
  "properties": {
    "addr:full":"Research Dept, 58 College Rd Maidstone Kent ME15 6SJ",
    "addr:housenumber":"58",
    "addr:postcode":"me15 6sj",
    "addr:street":"College Rd",
    "iso:country":"GB",
    "sg:address":"Research Dept, 58 College Rd",
    "sg:city":"Maidstone",
    "sg:classifiers":[
        {
            "category":"Government",
            "subcategory":"Office",
            "type":"Public Place"
        }
    ],
    "sg:phone":"+44 1622 757888",
    "sg:postcode":"ME15 6SJ",
    "sg:province":"Kent",
    "sg:tags":[
        "central"
    ],
    "wof:name":"Probation Service",
    "wof:placetype":"venue"
},
  "geometry": {"coordinates":[0.52126,51.26759],"type":"Point"}
}