{
  "type": "Feature",
  "properties": {
    "addr:full":"46 Chorley Road, Swinton Manchester Greater Manchester M27 5AF",
    "addr:housenumber":"46",
    "addr:postcode":"m27 5af",
    "addr:street":"Chorley Road",
    "iso:country":"GB",
    "sg:address":"46 Chorley Road, Swinton",
    "sg:city":"Manchester",
    "sg:classifiers":[
        {
            "category":"Building & Trades",
            "subcategory":"Construction",
            "type":"Services"
        }
    ],
    "sg:phone":"+44 161 728 4625",
    "sg:postcode":"M27 5AF",
    "sg:province":"Greater Manchester",
    "sg:tags":[
        "flooring"
    ],
    "wof:name":"T P Flooring",
    "wof:placetype":"venue"
},
  "geometry": {"coordinates":[-2.3344531059,53.5092773438],"type":"Point"}
}