{
  "type": "Feature",
  "properties": {
    "addr:full":"Old Dairy Yard, Hall St, Long Melford Sudbury Essex CO10 9JA",
    "addr:postcode":"co10 9ja",
    "addr:street":"Old;St",
    "iso:country":"GB",
    "sg:address":"Old Dairy Yard, Hall St, Long Melford",
    "sg:city":"Sudbury",
    "sg:classifiers":[
        {
            "category":"Building & Trades",
            "subcategory":"Construction",
            "type":"Services"
        }
    ],
    "sg:phone":"+44 1787 313077",
    "sg:postcode":"CO10 9JA",
    "sg:province":"Essex",
    "sg:tags":[
        "builder"
    ],
    "wof:name":"I & J Murphy",
    "wof:placetype":"venue"
},
  "geometry": {"coordinates":[0.71648,52.075264],"type":"Point"}
}