{
  "type": "Feature",
  "properties": {
    "iso:country":"GB",
    "sg:address":"Warwick Rd",
    "sg:city":"Kenilworth",
    "sg:classifiers":[
        {
            "category":"Bars & Pubs",
            "type":"Food & Drink"
        }
    ],
    "sg:phone":"+44 1926 863061",
    "sg:postcode":"CV8 1HS",
    "sg:province":"Warwickshire",
    "sg:tags":[
        "pubs",
        "inn"
    ],
    "wof:name":"Green Man",
    "wof:placetype":"venue"
},
  "geometry": {"coordinates":[-1.576479,52.340084],"type":"Point"}
}