{
  "type": "Feature",
  "properties": {
    "addr:full":"7 Park View Stockton-on-tees Durham TS18 3PT",
    "addr:housenumber":"7",
    "addr:postcode":"ts18 3pt",
    "addr:street":"Park View",
    "iso:country":"GB",
    "sg:address":"7 Park View",
    "sg:city":"Stockton-on-tees",
    "sg:classifiers":[
        {
            "category":"Autos & Motor Vehicles",
            "subcategory":"Auto Supplies",
            "type":"Retail Goods"
        }
    ],
    "sg:postcode":"TS18 3PT",
    "sg:province":"Durham",
    "sg:tags":[
        "exhaust",
        "absorber",
        "shock"
    ],
    "wof:name":"M A L Mobile Exhausts",
    "wof:placetype":"venue"
},
  "geometry": {"coordinates":[-1.322003,54.558933],"type":"Point"}
}