{
  "type": "Feature",
  "properties": {
    "addr:full":"90 Yeldham Road, Hammersmith London Greater London W6 8JG",
    "addr:housenumber":"90",
    "addr:postcode":"w6 8jg",
    "addr:street":"Yeldham Road",
    "iso:country":"GB",
    "sg:address":"90 Yeldham Road, Hammersmith",
    "sg:city":"London",
    "sg:classifiers":[
        {
            "category":"Professional",
            "subcategory":"Accounting & Tax Preparation",
            "type":"Services"
        }
    ],
    "sg:postcode":"W6 8JG",
    "sg:province":"Greater London",
    "sg:tags":[
        "accountant"
    ],
    "wof:name":"Watercress Accounting Ltd",
    "wof:placetype":"venue"
},
  "geometry": {"coordinates":[-0.219720006,51.4898300171],"type":"Point"}
}