{
  "type": "Feature",
  "properties": {
    "addr:full":"72-74 Drury Lane Solihull West Midlands B91 3BH",
    "addr:housenumber":"72-74",
    "addr:postcode":"b91 3bh",
    "addr:street":"Drury Lane",
    "iso:country":"GB",
    "sg:address":"72-74 Drury Lane",
    "sg:city":"Solihull",
    "sg:classifiers":[
        {
            "category":"Shopping",
            "subcategory":"Bicycles & Sporting Goods",
            "type":"Retail Goods"
        }
    ],
    "sg:postcode":"B91 3BH",
    "sg:province":"West Midlands",
    "sg:tags":[
        "cycle",
        "accessory"
    ],
    "wof:name":"Freewheel (Solihull)",
    "wof:placetype":"venue"
},
  "geometry": {"coordinates":[-1.775199,52.41423],"type":"Point"}
}