{
  "type": "Feature",
  "properties": {
    "iso:country":"GB",
    "sg:address":"28 Bedale Road",
    "sg:city":"Nottingham",
    "sg:classifiers":[
        {
            "category":"Bus Charters",
            "type":"Transportation"
        }
    ],
    "sg:postcode":"NG5 3GH",
    "sg:province":"Nottinghamshire",
    "sg:tags":[
        "hire",
        "coach"
    ],
    "wof:name":"Boulevard Executive Travel",
    "wof:placetype":"venue"
},
  "geometry": {"coordinates":[-1.140544,52.994598],"type":"Point"}
}