{
  "type": "Feature",
  "properties": {
    "iso:country":"GB",
    "sg:address":"96 Clarendon Rd",
    "sg:city":"Luton",
    "sg:classifiers":[
        {
            "category":"Building & Trades",
            "subcategory":"Construction",
            "type":"Services"
        }
    ],
    "sg:phone":"+44 1582 737880",
    "sg:postcode":"LU2 7PJ",
    "sg:province":"Bedfordshire",
    "sg:tags":[
        "ventilation",
        "contractor"
    ],
    "wof:name":"Building Tech",
    "wof:placetype":"venue"
},
  "geometry": {"coordinates":[-0.414621,51.888245],"type":"Point"}
}