{
  "type": "Feature",
  "properties": {
    "addr:full":"44 Frys Hill Bristol City of Bristol BS15 4QJ",
    "addr:housenumber":"44",
    "addr:postcode":"bs15 4qj",
    "addr:street":"Frys Hill",
    "iso:country":"GB",
    "sg:address":"44 Frys Hill",
    "sg:city":"Bristol",
    "sg:classifiers":[
        {
            "category":"Building & Trades",
            "subcategory":"Cleaning & Sanitation",
            "type":"Services"
        }
    ],
    "sg:phone":"+44 117 987 7907",
    "sg:postcode":"BS15 4QJ",
    "sg:province":"City of Bristol",
    "sg:tags":[
        "steam"
    ],
    "wof:name":"Hydro-Tech",
    "wof:placetype":"venue"
},
  "geometry": {"coordinates":[-2.4895439148,51.4675445557],"type":"Point"}
}