{
  "type": "Feature",
  "properties": {
    "iso:country":"GB",
    "sg:address":"Jesters Court",
    "sg:city":"Windermere",
    "sg:classifiers":[
        {
            "category":"Fast Food",
            "type":"Food & Drink"
        },
        {
            "category":"Restaurant",
            "type":"Food & Drink"
        }
    ],
    "sg:phone":"+44 15394 42522",
    "sg:postcode":"LA23 1EG",
    "sg:province":"Cumbria",
    "sg:tags":[
        "away",
        "take"
    ],
    "wof:name":"M & J's Fish Restaurant",
    "wof:placetype":"venue"
},
  "geometry": {"coordinates":[-2.906404,54.379665],"type":"Point"}
}