{
  "type": "Feature",
  "properties": {
    "addr:full":"1001 Warwick Rd, Acocks Grn Birmingham West Midlands B27 6QJ",
    "addr:housenumber":"1001",
    "addr:postcode":"b27 6qj",
    "addr:street":"Warwick Rd Acocks Grn",
    "iso:country":"GB",
    "sg:address":"1001 Warwick Rd, Acocks Grn",
    "sg:city":"Birmingham",
    "sg:classifiers":[
        {
            "category":"Autos & Motor Vehicles",
            "subcategory":"Motorcycle Sales",
            "type":"Retail Goods"
        }
    ],
    "sg:postcode":"B27 6QJ",
    "sg:province":"West Midlands",
    "sg:tags":[
        "chauffeur",
        "driven",
        "car"
    ],
    "wof:name":"1001 Wedding Cars",
    "wof:placetype":"venue"
},
  "geometry": {"coordinates":[-1.8245840073,52.4468574524],"type":"Point"}
}