{
  "type": "Feature",
  "properties": {
    "iso:country":"GB",
    "sg:address":"Napier Road, Wardpark North, Cumbernauld",
    "sg:city":"Glasgow",
    "sg:classifiers":[
        {
            "category":"Professional",
            "subcategory":"Printing & Photocopies",
            "type":"Services"
        }
    ],
    "sg:phone":"+44 1236 725611",
    "sg:postcode":"G68 0EF",
    "sg:province":"East Dunbartonshire",
    "sg:tags":[
        "computer",
        "tag",
        "label"
    ],
    "wof:name":"Merroc Ltd.",
    "wof:placetype":"venue"
},
  "geometry": {"coordinates":[-3.967697,55.975136],"type":"Point"}
}