{
  "type": "Feature",
  "properties": {
    "iso:country":"GB",
    "sg:address":"35 George Street",
    "sg:city":"Newcastle",
    "sg:classifiers":[
        {
            "category":"Building & Trades",
            "subcategory":"Construction",
            "type":"Services"
        }
    ],
    "sg:phone":"+44 1782 711809",
    "sg:postcode":"ST5 1JU",
    "sg:province":"Staffordshire",
    "sg:tags":[
        "dry",
        "lining",
        "plasterers",
        "screeders"
    ],
    "wof:name":"G W McCarthy & Co. Ltd.",
    "wof:placetype":"venue"
},
  "geometry": {"coordinates":[-2.217026,53.012455],"type":"Point"}
}