{
  "type": "Feature",
  "properties": {
    "addr:full":"25 Denmark Street Fraserburgh Aberdeenshire AB43 9EY",
    "addr:housenumber":"25",
    "addr:postcode":"ab43 9ey",
    "addr:street":"Denmark Street",
    "iso:country":"GB",
    "sg:address":"25 Denmark Street",
    "sg:city":"Fraserburgh",
    "sg:classifiers":[
        {
            "category":"Wholesale",
            "subcategory":"Seafood",
            "type":"Manufacturing & Wholesale Goods"
        },
        {
            "category":"Food & Beverages",
            "subcategory":"Meat & Fish",
            "type":"Retail Goods"
        }
    ],
    "sg:phone":"+44 1346 513221",
    "sg:postcode":"AB43 9EY",
    "sg:province":"Aberdeenshire",
    "sg:tags":[
        "merchant"
    ],
    "wof:name":"Duthie & Summers",
    "wof:placetype":"venue"
},
  "geometry": {"coordinates":[-2.009774,57.6954],"type":"Point"}
}