{
  "type": "Feature",
  "properties": {
    "addr:full":"18 Old Dover Road London Greater London SE3 7BT",
    "addr:housenumber":"18",
    "addr:postcode":"se3 7bt",
    "addr:street":"Old Dover Road",
    "iso:country":"GB",
    "sg:address":"18 Old Dover Road",
    "sg:city":"London",
    "sg:classifiers":[
        {
            "category":"Shopping",
            "subcategory":"Shoes",
            "type":"Retail Goods"
        }
    ],
    "sg:postcode":"SE3 7BT",
    "sg:province":"Greater London",
    "wof:name":"P Amato",
    "wof:placetype":"venue"
},
  "geometry": {"coordinates":[0.021053,51.476704],"type":"Point"}
}