{
  "type": "Feature",
  "properties": {
    "addr:full":"32 Manor Drive London Greater London N20 0DX",
    "addr:housenumber":"32",
    "addr:postcode":"n20 0dx",
    "addr:street":"Manor Drive",
    "iso:country":"GB",
    "sg:address":"32 Manor Drive",
    "sg:city":"London",
    "sg:classifiers":[
        {
            "category":"Shopping",
            "subcategory":"Clothing, Apparel, & Fashions",
            "type":"Retail Goods"
        },
        {
            "category":"Wholesale",
            "subcategory":"Apparel",
            "type":"Manufacturing & Wholesale Goods"
        }
    ],
    "sg:phone":"+44 20 8361 8107",
    "sg:postcode":"N20 0DX",
    "sg:province":"Greater London",
    "sg:tags":[
        "supplier",
        "clothing"
    ],
    "wof:name":"Marcline Ltd.",
    "wof:placetype":"venue"
},
  "geometry": {"coordinates":[-0.160111,51.62402],"type":"Point"}
}