{
  "type": "Feature",
  "properties": {
    "iso:country":"GB",
    "sg:address":"16 Watergate",
    "sg:city":"Grantham",
    "sg:classifiers":[
        {
            "category":"Fast Food",
            "type":"Food & Drink"
        }
    ],
    "sg:phone":"+44 1476 577331",
    "sg:postcode":"NG31 6PR",
    "sg:province":"Lincolnshire",
    "sg:tags":[
        "away",
        "take"
    ],
    "wof:name":"Grantham Charcoal Grills",
    "wof:placetype":"venue"
},
  "geometry": {"coordinates":[-0.643816,52.911598],"type":"Point"}
}