{
  "type": "Feature",
  "properties": {
    "addr:full":"16 Holbrook St Heanor Derbyshire DE75 7AY",
    "addr:housenumber":"16",
    "addr:postcode":"de75 7ay",
    "addr:street":"Holbrook St",
    "iso:country":"GB",
    "sg:address":"16 Holbrook St",
    "sg:city":"Heanor",
    "sg:classifiers":[
        {
            "category":"Retail",
            "subcategory":"Auto Repair",
            "type":"Services"
        }
    ],
    "sg:phone":"+44 1773 533450",
    "sg:postcode":"DE75 7AY",
    "sg:province":"Derbyshire",
    "sg:tags":[
        "modification",
        "garage"
    ],
    "wof:name":"Langley Mill Auto Centre",
    "wof:placetype":"venue"
},
  "geometry": {"coordinates":[-1.342639,53.01593],"type":"Point"}
}