{
  "type": "Feature",
  "properties": {
    "iso:country":"GB",
    "sg:address":"Gordon Road",
    "sg:city":"London",
    "sg:classifiers":[
        {
            "category":"Education",
            "subcategory":"Library",
            "type":"Public Place"
        },
        {
            "category":"Government",
            "subcategory":"Office",
            "type":"Public Place"
        }
    ],
    "sg:phone":"+44 20 7639 0264",
    "sg:postcode":"SE15 3RW",
    "sg:province":"Greater London",
    "sg:tags":[
        "book",
        "local"
    ],
    "wof:name":"Nunhead Library",
    "wof:placetype":"venue"
},
  "geometry": {"coordinates":[-0.060339,51.467682],"type":"Point"}
}