{
  "type": "Feature",
  "properties": {
    "addr:full":"21-24 Grosvenor Place London Greater London SW1X 7HU",
    "addr:housenumber":"21-24",
    "addr:postcode":"sw1x 7hu",
    "addr:street":"Grosvenor Place",
    "iso:country":"GB",
    "sg:address":"21-24 Grosvenor Place",
    "sg:city":"London",
    "sg:classifiers":[
        {
            "category":"Government",
            "subcategory":"Embassy",
            "type":"Public Place"
        },
        {
            "category":"Banks & Credit Unions",
            "subcategory":"Investment Brokerage",
            "type":"Services"
        }
    ],
    "sg:phone":"+44 20 7823 1895",
    "sg:postcode":"SW1X 7HU",
    "sg:province":"Greater London",
    "sg:tags":[
        "consulate"
    ],
    "wof:name":"Invest in France Agency",
    "wof:placetype":"venue"
},
  "geometry": {"coordinates":[-0.149335,51.500202],"type":"Point"}
}