{
  "type": "Feature",
  "properties": {
    "iso:country":"GB",
    "sg:address":"The Old Bakery",
    "sg:city":"Taunton",
    "sg:classifiers":[
        {
            "category":"Building & Trades",
            "subcategory":"Construction",
            "type":"Services"
        }
    ],
    "sg:phone":"+44 1460 281977",
    "sg:postcode":"TA3 6PA",
    "sg:province":"Devon",
    "sg:tags":[
        "excavation",
        "groundwork",
        "contractor"
    ],
    "wof:name":"R W Westworth",
    "wof:placetype":"venue"
},
  "geometry": {"coordinates":[-2.9696729183,51.024230957],"type":"Point"}
}