{
  "type": "Feature",
  "properties": {
    "addr:full":"Unit 4 Kents Avenue Hemel Hempstead Hertfordshire HP3 9XH",
    "addr:housenumber":"unit 4",
    "addr:postcode":"hp3 9xh",
    "addr:street":"Kents Avenue Hemel",
    "iso:country":"GB",
    "sg:address":"Unit 4 Kents Avenue",
    "sg:city":"Hemel Hempstead",
    "sg:classifiers":[
        {
            "category":"Wholesale",
            "subcategory":"Construction Materials",
            "type":"Manufacturing & Wholesale Goods"
        }
    ],
    "sg:phone":"+44 1442 244343",
    "sg:postcode":"HP3 9XH",
    "sg:province":"Hertfordshire",
    "sg:tags":[
        "coating",
        "powder"
    ],
    "wof:name":"R B Industrial Finishers",
    "wof:placetype":"venue"
},
  "geometry": {"coordinates":[-0.4689339995,51.7361793518],"type":"Point"}
}