{
  "type": "Feature",
  "properties": {
    "addr:full":"Old Edinburgh Rd Bellshill North Lanarkshire ML4 3HN",
    "addr:postcode":"ml4 3hn",
    "addr:street":"Old Edinburgh Rd",
    "iso:country":"GB",
    "sg:address":"Old Edinburgh Rd",
    "sg:city":"Bellshill",
    "sg:classifiers":[
        {
            "category":"Autos & Motor Vehicles",
            "subcategory":"Fuel & Gas Station",
            "type":"Retail Goods"
        }
    ],
    "sg:postcode":"ML4 3HN",
    "sg:province":"North Lanarkshire",
    "sg:tags":[
        "hr",
        "petrol"
    ],
    "wof:name":"Hazlett,A J,",
    "wof:placetype":"venue"
},
  "geometry": {"coordinates":[-4.0517039299,55.8208274841],"type":"Point"}
}