{
  "type": "Feature",
  "properties": {
    "addr:full":"Watlington Rd, Cowley Oxford Oxfordshire OX4 6SS",
    "addr:postcode":"ox4 6ss",
    "addr:street":"Watlington Rd",
    "iso:country":"GB",
    "sg:address":"Watlington Rd, Cowley",
    "sg:city":"Oxford",
    "sg:classifiers":[
        {
            "category":"Bars & Pubs",
            "type":"Food & Drink"
        }
    ],
    "sg:phone":"+44 1865 771430",
    "sg:postcode":"OX4 6SS",
    "sg:province":"Oxfordshire",
    "sg:tags":[
        "pubs",
        "inn"
    ],
    "wof:name":"Punch Retail Ltd",
    "wof:placetype":"venue"
},
  "geometry": {"coordinates":[-1.1940490007,51.7259483337],"type":"Point"}
}