{
  "type": "Feature",
  "properties": {
    "iso:country":"GB",
    "sg:address":"Plumpton Ho, Unit 2c Plumpton Rd, Rye Pk",
    "sg:city":"Hoddesdon",
    "sg:classifiers":[
        {
            "category":"Manufacturing",
            "subcategory":"Rubber & Plastics",
            "type":"Manufacturing & Wholesale Goods"
        }
    ],
    "sg:phone":"+44 1992 466600",
    "sg:postcode":"EN11 0EB",
    "sg:province":"Essex",
    "sg:tags":[
        "injection",
        "moulding"
    ],
    "wof:name":"Berison Tools Ltd",
    "wof:placetype":"venue"
},
  "geometry": {"coordinates":[0.0040000002,51.7702789307],"type":"Point"}
}