{
  "type": "Feature",
  "properties": {
    "addr:full":"22 Crowndale Road London Greater London NW1 1TT",
    "addr:housenumber":"22",
    "addr:postcode":"nw1 1tt",
    "addr:street":"Crowndale Road",
    "iso:country":"GB",
    "sg:address":"22 Crowndale Road",
    "sg:city":"London",
    "sg:classifiers":[
        {
            "category":"Shopping",
            "subcategory":"News",
            "type":"Retail Goods"
        }
    ],
    "sg:postcode":"NW1 1TT",
    "sg:province":"Greater London",
    "sg:tags":[
        "newsagent"
    ],
    "wof:name":"Vinst Newagents",
    "wof:placetype":"venue"
},
  "geometry": {"coordinates":[-0.134867996,51.5354614258],"type":"Point"}
}