{
  "type": "Feature",
  "properties": {
    "iso:country":"GB",
    "sg:address":"39 High St",
    "sg:city":"Colchester",
    "sg:classifiers":[
        {
            "category":"Retail",
            "subcategory":"Auto Repair",
            "type":"Services"
        }
    ],
    "sg:postcode":"CO5 7ET",
    "sg:province":"Essex",
    "sg:tags":[
        "modification",
        "garage"
    ],
    "wof:name":"Rowhedge Engine Centre",
    "wof:placetype":"venue"
},
  "geometry": {"coordinates":[0.94931,51.854984],"type":"Point"}
}