{
  "type": "Feature",
  "properties": {
    "addr:full":"45-49 Coventry Rd Leicester Leicestershire LE9 5GE",
    "addr:housenumber":"45-49",
    "addr:postcode":"le9 5ge",
    "addr:street":"Coventry Rd",
    "iso:country":"GB",
    "sg:address":"45-49 Coventry Rd",
    "sg:city":"Leicester",
    "sg:classifiers":[
        {
            "category":"Retail",
            "subcategory":"Auto Repair",
            "type":"Services"
        }
    ],
    "sg:phone":"+44 116 275 2800",
    "sg:postcode":"LE9 5GE",
    "sg:province":"Leicestershire",
    "sg:tags":[
        "modification",
        "garage"
    ],
    "wof:name":"Francis Honda",
    "wof:placetype":"venue"
},
  "geometry": {"coordinates":[-1.237197,52.536926],"type":"Point"}
}