{
  "type": "Feature",
  "properties": {
    "iso:country":"GB",
    "sg:address":"70 Haddon Cres",
    "sg:city":"Nottingham",
    "sg:classifiers":[
        {
            "category":"Building & Trades",
            "subcategory":"Construction",
            "type":"Services"
        }
    ],
    "sg:phone":"+44 115 925 6992",
    "sg:postcode":"NG9 5JR",
    "sg:province":"Nottinghamshire",
    "sg:tags":[
        "flooring"
    ],
    "wof:name":"J R Wortley",
    "wof:placetype":"venue"
},
  "geometry": {"coordinates":[-1.2383830547,52.9103050232],"type":"Point"}
}