{
  "type": "Feature",
  "properties": {
    "addr:full":"Bridge St, Garstang Preston Lancashire PR3 1YB",
    "addr:postcode":"pr3 1yb",
    "addr:street":"Bridge",
    "iso:country":"GB",
    "sg:address":"Bridge St, Garstang",
    "sg:city":"Preston",
    "sg:classifiers":[
        {
            "category":"Restaurant",
            "type":"Food & Drink"
        }
    ],
    "sg:postcode":"PR3 1YB",
    "sg:province":"Lancashire",
    "wof:name":"Blagden,Valerie,",
    "wof:placetype":"venue"
},
  "geometry": {"coordinates":[-2.774332,53.899529],"type":"Point"}
}