{
  "type": "Feature",
  "properties": {
    "addr:full":"72 Ash Bank Road Stoke-on-trent Staffordshire ST2 9DU",
    "addr:housenumber":"72",
    "addr:postcode":"st2 9du",
    "addr:street":"Ash Bank Road",
    "iso:country":"GB",
    "sg:address":"72 Ash Bank Road",
    "sg:city":"Stoke-on-trent",
    "sg:classifiers":[
        {
            "category":"Professional",
            "type":"Services"
        }
    ],
    "sg:phone":"+44 1952 820485",
    "sg:postcode":"ST2 9DU",
    "sg:province":"Staffordshire",
    "sg:tags":[
        "entertainer"
    ],
    "wof:name":"Marjo's Punch & Judy",
    "wof:placetype":"venue"
},
  "geometry": {"coordinates":[-2.119859,53.021191],"type":"Point"}
}