{
  "type": "Feature",
  "properties": {
    "addr:full":"28 Maybrook Rd, Brownhills Walsall Staffordshire WS8 7DG",
    "addr:housenumber":"28",
    "addr:postcode":"ws8 7dg",
    "addr:street":"Maybrook Rd",
    "iso:country":"GB",
    "sg:address":"28 Maybrook Rd, Brownhills",
    "sg:city":"Walsall",
    "sg:classifiers":[
        {
            "category":"Building & Trades",
            "subcategory":"Construction",
            "type":"Services"
        }
    ],
    "sg:postcode":"WS8 7DG",
    "sg:province":"Staffordshire",
    "sg:tags":[
        "builder"
    ],
    "wof:name":"Meller,David G,",
    "wof:placetype":"venue"
},
  "geometry": {"coordinates":[-1.932145,52.634689],"type":"Point"}
}