{
  "type": "Feature",
  "properties": {
    "iso:country":"GB",
    "sg:address":"18 Forest Road, Kingswood",
    "sg:city":"Bristol",
    "sg:classifiers":[
        {
            "category":"Home & Garden",
            "subcategory":"Building Materials",
            "type":"Retail Goods"
        }
    ],
    "sg:phone":"+44 117 935 2454",
    "sg:postcode":"BS15 8EG",
    "sg:province":"City of Bristol",
    "sg:tags":[
        "insulation",
        "installers"
    ],
    "wof:name":"Westward Insulation Ltd.",
    "wof:placetype":"venue"
},
  "geometry": {"coordinates":[-2.512053,51.459007],"type":"Point"}
}