{
  "type": "Feature",
  "properties": {
    "addr:full":"Birmingham Road West Bromwich West Midlands B71 4JJ",
    "addr:postcode":"b71 4jj",
    "addr:street":"Birmingham Road",
    "iso:country":"GB",
    "sg:address":"Birmingham Road",
    "sg:city":"West Bromwich",
    "sg:classifiers":[
        {
            "category":"Sports & Exercise",
            "subcategory":"Golf",
            "type":"Entertainment"
        }
    ],
    "sg:phone":"+44 121 553 4637",
    "sg:postcode":"B71 4JJ",
    "sg:province":"West Midlands",
    "sg:tags":[
        "club",
        "course"
    ],
    "wof:name":"Sandwell Park Golf Club Ltd.",
    "wof:placetype":"venue"
},
  "geometry": {"coordinates":[-1.973446,52.511364],"type":"Point"}
}