{
  "type": "Feature",
  "properties": {
    "addr:full":"4 Trenance Lane Newquay Cornwall TR7 2HX",
    "addr:housenumber":"4",
    "addr:postcode":"tr7 2hx",
    "addr:street":"Trenance Lane",
    "iso:country":"GB",
    "sg:address":"4 Trenance Lane",
    "sg:city":"Newquay",
    "sg:classifiers":[
        {
            "category":"Building & Trades",
            "subcategory":"Construction",
            "type":"Services"
        }
    ],
    "sg:phone":"+44 1637 873734",
    "sg:postcode":"TR7 2HX",
    "sg:province":"Cornwall",
    "sg:tags":[
        "builder"
    ],
    "wof:name":"G T Tetsill & Son Ltd.",
    "wof:placetype":"venue"
},
  "geometry": {"coordinates":[-5.0762982368,50.4081611633],"type":"Point"}
}