{
  "type": "Feature",
  "properties": {
    "addr:full":"Dromana, Brock Hill Wickford Essex SS11 7PB",
    "addr:postcode":"ss11 7pb",
    "iso:country":"GB",
    "sg:address":"Dromana, Brock Hill",
    "sg:city":"Wickford",
    "sg:classifiers":[
        {
            "category":"Professional",
            "type":"Services"
        }
    ],
    "sg:phone":"+44 1268 711003",
    "sg:postcode":"SS11 7PB",
    "sg:province":"Essex",
    "sg:tags":[
        "interior",
        "furnishers",
        "designer"
    ],
    "wof:name":"Tina Curnick",
    "wof:placetype":"venue"
},
  "geometry": {"coordinates":[0.5167,51.630161],"type":"Point"}
}