{
  "type": "Feature",
  "properties": {
    "iso:country":"GB",
    "sg:address":"208 Linthorpe Road",
    "sg:city":"Middlesbrough",
    "sg:classifiers":[
        {
            "category":"Restaurant",
            "type":"Food & Drink"
        }
    ],
    "sg:phone":"+44 1642 219199",
    "sg:postcode":"TS1 3QW",
    "sg:province":"North Yorkshire",
    "wof:name":"The Townhouse Cafe",
    "wof:placetype":"venue"
},
  "geometry": {"coordinates":[-1.239829,54.567612],"type":"Point"}
}