{
  "type": "Feature",
  "properties": {
    "iso:country":"GB",
    "sg:address":"156 Ashley Road, Hale",
    "sg:city":"Altrincham",
    "sg:classifiers":[
        {
            "category":"Sports & Exercise",
            "subcategory":"Athletic Track",
            "type":"Entertainment"
        }
    ],
    "sg:postcode":"WA15 9SA",
    "sg:province":"Cheshire",
    "sg:tags":[
        "bags",
        "accessory",
        "belt"
    ],
    "wof:name":"Monica Barbour",
    "wof:placetype":"venue"
},
  "geometry": {"coordinates":[-2.346985,53.377769],"type":"Point"}
}