{
  "type": "Feature",
  "properties": {
    "iso:country":"GB",
    "sg:address":"21 Waterside",
    "sg:city":"Ely",
    "sg:classifiers":[
        {
            "category":"Retail",
            "subcategory":"Repair Shop",
            "type":"Services"
        },
        {
            "category":"Manufacturing",
            "subcategory":"Retail Goods",
            "type":"Manufacturing & Wholesale Goods"
        }
    ],
    "sg:phone":"+44 1353 663095",
    "sg:postcode":"CB7 4AU",
    "sg:province":"Cambridgeshire",
    "sg:tags":[
        "ship",
        "chandler"
    ],
    "wof:name":"Ely Boat Chandlers",
    "wof:placetype":"venue"
},
  "geometry": {"coordinates":[0.269737,52.397526],"type":"Point"}
}