{
  "type": "Feature",
  "properties": {
    "addr:full":"Langton Manor, Langton Horncastle Lincolnshire LN9 5JR",
    "addr:postcode":"ln9 5jr",
    "iso:country":"GB",
    "sg:address":"Langton Manor, Langton",
    "sg:city":"Horncastle",
    "sg:classifiers":[
        {
            "category":"Farming",
            "subcategory":"Farm",
            "type":"Manufacturing & Wholesale Goods"
        }
    ],
    "sg:phone":"+44 1507 522253",
    "sg:postcode":"LN9 5JR",
    "sg:province":"Lincolnshire",
    "sg:tags":[
        "mixed",
        "crop"
    ],
    "wof:name":"John Read",
    "wof:placetype":"venue"
},
  "geometry": {"coordinates":[-0.114765,53.208523],"type":"Point"}
}