{
  "type": "Feature",
  "properties": {
    "addr:full":"61 Park Lane, Poynton Stockport Cheshire SK12 1RD",
    "addr:housenumber":"61",
    "addr:postcode":"sk12 1rd",
    "addr:street":"Park Lane",
    "iso:country":"GB",
    "sg:address":"61 Park Lane, Poynton",
    "sg:city":"Stockport",
    "sg:classifiers":[
        {
            "category":"Personal",
            "subcategory":"Beauty Salon",
            "type":"Services"
        }
    ],
    "sg:phone":"+44 1625 850336",
    "sg:postcode":"SK12 1RD",
    "sg:province":"Cheshire",
    "sg:tags":[
        "unisex",
        "hairdresser"
    ],
    "wof:name":"Natura Hairdressing",
    "wof:placetype":"venue"
},
  "geometry": {"coordinates":[-2.118807,53.348785],"type":"Point"}
}