{
  "type": "Feature",
  "properties": {
    "addr:full":"6 Ravenscourt Pl London Greater London W6 0UN",
    "addr:housenumber":"6",
    "addr:postcode":"w6 0un",
    "addr:street":"Ravenscourt Pl",
    "iso:country":"GB",
    "sg:address":"6 Ravenscourt Pl",
    "sg:city":"London",
    "sg:classifiers":[
        {
            "category":"Organizations",
            "subcategory":"Community Association",
            "type":"Services"
        }
    ],
    "sg:postcode":"W6 0UN",
    "sg:province":"Greater London",
    "sg:tags":[
        "relation",
        "public"
    ],
    "wof:name":"Payne & Dagworthy",
    "wof:placetype":"venue"
},
  "geometry": {"coordinates":[-0.23982,51.494156],"type":"Point"}
}