{
  "type": "Feature",
  "properties": {
    "addr:full":"Langham Ho, Regent St West End Hampshire W1R 5AL",
    "addr:postcode":"w1r 5al",
    "addr:street":"Regent St",
    "iso:country":"GB",
    "sg:address":"Langham Ho, Regent St",
    "sg:city":"West End",
    "sg:classifiers":[
        {
            "category":"Manufacturing",
            "subcategory":"Textiles",
            "type":"Manufacturing & Wholesale Goods"
        }
    ],
    "sg:phone":"+44 20 7636 6660",
    "sg:postcode":"W1R 5AL",
    "sg:province":"Hampshire",
    "sg:tags":[
        "merchant",
        "agent"
    ],
    "wof:name":"Brookman Gorney Textile Agencies",
    "wof:placetype":"venue"
},
  "geometry": {"coordinates":[-0.13741,51.509995],"type":"Point"}
}