{
  "type": "Feature",
  "properties": {
    "addr:full":"Coppergate Close, Nafferton Driffield East Riding of Yorkshire YO25 0LX",
    "addr:postcode":"yo25 0lx",
    "addr:street":"Coppergate Close Nafferton",
    "iso:country":"GB",
    "sg:address":"Coppergate Close, Nafferton",
    "sg:city":"Driffield",
    "sg:classifiers":[
        {
            "category":"Building & Trades",
            "subcategory":"Construction",
            "type":"Services"
        }
    ],
    "sg:phone":"+44 1377 241384",
    "sg:postcode":"YO25 0LX",
    "sg:province":"East Riding of Yorkshire",
    "sg:tags":[
        "builder"
    ],
    "wof:name":"S Raines",
    "wof:placetype":"venue"
},
  "geometry": {"coordinates":[-0.436299,54.008968],"type":"Point"}
}