{
  "type": "Feature",
  "properties": {
    "addr:full":"Riverside Barn Bridport Dorset DT6 4PG",
    "addr:postcode":"dt6 4pg",
    "iso:country":"GB",
    "sg:address":"Riverside Barn",
    "sg:city":"Bridport",
    "sg:classifiers":[
        {
            "category":"Real Estate",
            "subcategory":"Architect",
            "type":"Services"
        }
    ],
    "sg:phone":"+44 1308 485010",
    "sg:postcode":"DT6 4PG",
    "sg:province":"Dorset",
    "wof:name":"G Saunders & J R Wheelwright",
    "wof:placetype":"venue"
},
  "geometry": {"coordinates":[-2.758019,50.733566],"type":"Point"}
}