{
  "type": "Feature",
  "properties": {
    "addr:full":"Arclid Hall Farm, Arclid Grn Sandbach Cheshire CW11 0SY",
    "addr:postcode":"cw11 0sy",
    "addr:street":"Arclid Grn",
    "iso:country":"GB",
    "sg:address":"Arclid Hall Farm, Arclid Grn",
    "sg:city":"Sandbach",
    "sg:classifiers":[
        {
            "category":"Farming",
            "subcategory":"Livestock Farm",
            "type":"Manufacturing & Wholesale Goods"
        },
        {
            "category":"Retail",
            "subcategory":"Auto Repair",
            "type":"Services"
        }
    ],
    "sg:phone":"+44 1270 759234",
    "sg:postcode":"CW11 0SY",
    "sg:province":"Cheshire",
    "sg:tags":[
        "modification",
        "garage",
        "others"
    ],
    "wof:name":"Arclid Motors",
    "wof:placetype":"venue"
},
  "geometry": {"coordinates":[-2.3636479378,53.1422080994],"type":"Point"}
}