{
  "type": "Feature",
  "properties": {
    "addr:full":"25 Tunsgate Guildford Surrey GU1 3QS",
    "addr:housenumber":"25",
    "addr:postcode":"gu1 3qs",
    "addr:street":"Tunsgate",
    "iso:country":"GB",
    "sg:address":"25 Tunsgate",
    "sg:city":"Guildford",
    "sg:classifiers":[
        {
            "category":"Home & Garden",
            "subcategory":"Home Furnishings",
            "type":"Retail Goods"
        },
        {
            "category":"Home & Garden",
            "subcategory":"Building Materials",
            "type":"Retail Goods"
        }
    ],
    "sg:phone":"+44 1483 502901",
    "sg:postcode":"GU1 3QS",
    "sg:province":"Surrey",
    "sg:tags":[
        "installers",
        "planner",
        "kitchen",
        "furnishers"
    ],
    "wof:name":"County Kitchens",
    "wof:placetype":"venue"
},
  "geometry": {"coordinates":[-0.5717909932,51.234828949],"type":"Point"}
}