{
  "type": "Feature",
  "properties": {
    "addr:full":"Unit 5 Flitch Industrial Estate, Chelmsford Road Dunmow Essex CM6 1XJ",
    "addr:housenumber":"unit 5",
    "addr:postcode":"cm6 1xj",
    "addr:street":"Flitch Industrial Estate Chelmsford Road",
    "iso:country":"GB",
    "sg:address":"Unit 5 Flitch Industrial Estate, Chelmsford Road",
    "sg:city":"Dunmow",
    "sg:classifiers":[
        {
            "category":"Wholesale",
            "subcategory":"Chemicals & Plastics",
            "type":"Manufacturing & Wholesale Goods"
        },
        {
            "category":"Food & Beverages",
            "subcategory":"Ethnic Foods",
            "type":"Retail Goods"
        }
    ],
    "sg:phone":"+44 1371 874116",
    "sg:postcode":"CM6 1XJ",
    "sg:province":"Essex",
    "sg:tags":[
        "merchant",
        "w'sale",
        "oil",
        "perfume",
        "supplier",
        "essential"
    ],
    "wof:name":"Fleuroma Ltd.",
    "wof:placetype":"venue"
},
  "geometry": {"coordinates":[0.365555,51.86731],"type":"Point"}
}