{
  "type": "Feature",
  "properties": {
    "addr:full":"27 Upper Terrace, Letterston Haverfordwest Pembrokeshire SA62 5UG",
    "addr:housenumber":"27",
    "addr:postcode":"sa62 5ug",
    "addr:street":"Upper Terrace",
    "iso:country":"GB",
    "sg:address":"27 Upper Terrace, Letterston",
    "sg:city":"Haverfordwest",
    "sg:classifiers":[
        {
            "category":"Retail",
            "subcategory":"Auto Repair",
            "type":"Services"
        }
    ],
    "sg:phone":"+44 1348 840788",
    "sg:postcode":"SA62 5UG",
    "sg:province":"Pembrokeshire",
    "sg:tags":[
        "modification",
        "garage"
    ],
    "wof:name":"Penbryn Motors",
    "wof:placetype":"venue"
},
  "geometry": {"coordinates":[-4.9918189049,51.928730011],"type":"Point"}
}