{
  "type": "Feature",
  "properties": {
    "addr:full":"172 Hope Street Glasgow Glasgow City G2 2TX",
    "addr:housenumber":"172",
    "addr:postcode":"g2 2tx",
    "addr:street":"Hope Street",
    "iso:country":"GB",
    "sg:address":"172 Hope Street",
    "sg:city":"Glasgow",
    "sg:classifiers":[
        {
            "category":"Shopping",
            "subcategory":"Stationery & Office Supplies",
            "type":"Retail Goods"
        }
    ],
    "sg:phone":"+44 141 332 4105",
    "sg:postcode":"G2 2TX",
    "sg:province":"Glasgow City",
    "sg:tags":[
        "commercial"
    ],
    "wof:name":"G A H Douglas & Co. Ltd.",
    "wof:placetype":"venue"
},
  "geometry": {"coordinates":[-4.257493,55.863476],"type":"Point"}
}