{
  "type": "Feature",
  "properties": {
    "addr:full":"Flat 9 Woodbridge House, 145 Mornington Road Wanstead Greater London E11 3DZ",
    "addr:housenumber":"145",
    "addr:postcode":"e11 3dz",
    "addr:street":"Mornington Road",
    "iso:country":"GB",
    "sg:address":"Flat 9 Woodbridge House, 145 Mornington Road",
    "sg:city":"Wanstead",
    "sg:classifiers":[
        {
            "category":"Education",
            "subcategory":"University",
            "type":"Public Place"
        }
    ],
    "sg:phone":"+44 20 8556 7382",
    "sg:postcode":"E11 3DZ",
    "sg:province":"Greater London",
    "sg:tags":[
        "higher"
    ],
    "wof:name":"J Barker",
    "wof:placetype":"venue"
},
  "geometry": {"coordinates":[0.0136299999,51.5659484863],"type":"Point"}
}