{
  "type": "Feature",
  "properties": {
    "addr:full":"Greenwood House, 5 London Rd Bracknell Berkshire RG12 2UB",
    "addr:housenumber":"5",
    "addr:postcode":"rg12 2ub",
    "addr:street":"London Rd",
    "iso:country":"GB",
    "sg:address":"Greenwood House, 5 London Rd",
    "sg:city":"Bracknell",
    "sg:classifiers":[
        {
            "category":"Professional",
            "subcategory":"Computer Services",
            "type":"Services"
        }
    ],
    "sg:phone":"+44 1344 866600",
    "sg:postcode":"RG12 2UB",
    "sg:province":"Berkshire",
    "sg:tags":[
        "system",
        "software"
    ],
    "wof:name":"Remedy Corporation",
    "wof:placetype":"venue"
},
  "geometry": {"coordinates":[-0.744269,51.416462],"type":"Point"}
}