{
  "type": "Feature",
  "properties": {
    "addr:full":"8 Barford Close, Spaxton Bridgwater Somerset TA5 1AE",
    "addr:housenumber":"8",
    "addr:postcode":"ta5 1ae",
    "addr:street":"Barford Close Spaxton",
    "iso:country":"GB",
    "sg:address":"8 Barford Close, Spaxton",
    "sg:city":"Bridgwater",
    "sg:classifiers":[
        {
            "category":"Building & Trades",
            "subcategory":"Construction",
            "type":"Services"
        }
    ],
    "sg:postcode":"TA5 1AE",
    "sg:province":"Somerset",
    "sg:tags":[
        "tiling",
        "contractor"
    ],
    "wof:name":"R J Bradley Contracts",
    "wof:placetype":"venue"
},
  "geometry": {"coordinates":[-3.0989699364,51.1263580322],"type":"Point"}
}