{
  "type": "Feature",
  "properties": {
    "iso:country":"GB",
    "sg:address":"86 Spring Gardens",
    "sg:city":"Doncaster",
    "sg:classifiers":[
        {
            "category":"Utilities",
            "subcategory":"Natural Gas",
            "type":"Services"
        }
    ],
    "sg:phone":"+44 1302 329020",
    "sg:postcode":"DN1 3DJ",
    "sg:province":"South Yorkshire",
    "sg:tags":[
        "supplier"
    ],
    "wof:name":"Eco Systems Northern Ltd.",
    "wof:placetype":"venue"
},
  "geometry": {"coordinates":[-1.136332,53.521072],"type":"Point"}
}