{
  "type": "Feature",
  "properties": {
    "iso:country":"GB",
    "sg:address":"50 Oreston Road",
    "sg:city":"Plymouth",
    "sg:classifiers":[
        {
            "category":"Retail",
            "subcategory":"Auto Repair",
            "type":"Services"
        }
    ],
    "sg:phone":"+44 1752 403225",
    "sg:postcode":"PL9 7JU",
    "sg:province":"Devon",
    "sg:tags":[
        "modification",
        "garage"
    ],
    "wof:name":"Oreston Motor Centre",
    "wof:placetype":"venue"
},
  "geometry": {"coordinates":[-4.103237,50.363914],"type":"Point"}
}