{
  "type": "Feature",
  "properties": {
    "addr:full":"Hollin Ho, Holehouse La Stoke On Trent Staffordshire ST9 9AE",
    "addr:postcode":"st9 9ae",
    "addr:street":"La Stoke",
    "iso:country":"GB",
    "sg:address":"Hollin Ho, Holehouse La",
    "sg:city":"Stoke On Trent",
    "sg:classifiers":[
        {
            "category":"Farming",
            "subcategory":"Livestock Farm",
            "type":"Manufacturing & Wholesale Goods"
        }
    ],
    "sg:phone":"+44 1782 502444",
    "sg:postcode":"ST9 9AE",
    "sg:province":"Staffordshire",
    "sg:tags":[
        "others"
    ],
    "wof:name":"R Brassington",
    "wof:placetype":"venue"
},
  "geometry": {"coordinates":[-2.12,53.090343],"type":"Point"}
}