{
  "type": "Feature",
  "properties": {
    "addr:full":"C/o Boyle & Co Property London Greater London SW6 7LP",
    "addr:housenumber":"/ o",
    "addr:postcode":"sw6 7lp",
    "addr:street":"C",
    "iso:country":"GB",
    "sg:address":"C/o Boyle & Co Property",
    "sg:city":"London",
    "sg:classifiers":[
        {
            "category":"Organizations",
            "subcategory":"Community Association",
            "type":"Services"
        }
    ],
    "sg:phone":"+44 20 7823 7735",
    "sg:postcode":"SW6 7LP",
    "sg:province":"Greater London",
    "sg:tags":[
        "relation",
        "public"
    ],
    "wof:name":"Sydney Place Property Management Co. Ltd.",
    "wof:placetype":"venue"
},
  "geometry": {"coordinates":[-0.2082999945,51.4834709167],"type":"Point"}
}