{
  "type": "Feature",
  "properties": {
    "addr:full":"2 Carterhatch Road Enfield Greater London EN3 5LS",
    "addr:housenumber":"2",
    "addr:postcode":"en3 5ls",
    "addr:street":"Carterhatch Road",
    "iso:country":"GB",
    "sg:address":"2 Carterhatch Road",
    "sg:city":"Enfield",
    "sg:classifiers":[
        {
            "category":"Health Services",
            "subcategory":"Medical Lab",
            "type":"Services"
        },
        {
            "category":"Health Services",
            "subcategory":"Dentist",
            "type":"Services"
        }
    ],
    "sg:phone":"+44 20 8443 0887",
    "sg:postcode":"EN3 5LS",
    "sg:province":"Greater London",
    "sg:tags":[
        "technician",
        "dental"
    ],
    "wof:name":"Carterhouse Dental",
    "wof:placetype":"venue"
},
  "geometry": {"coordinates":[-0.045969,51.660286],"type":"Point"}
}