{
  "type": "Feature",
  "properties": {
    "addr:full":"The Firs Valencia Road Stanmore Greater London HA7 4JL",
    "addr:postcode":"ha7 4jl",
    "addr:street":"Valencia Road",
    "iso:country":"GB",
    "sg:address":"The Firs Valencia Road",
    "sg:city":"Stanmore",
    "sg:classifiers":[
        {
            "category":"Professional",
            "subcategory":"Computer Services",
            "type":"Services"
        }
    ],
    "sg:postcode":"HA7 4JL",
    "sg:province":"Greater London",
    "sg:tags":[
        "consultant"
    ],
    "wof:name":"Oriforce Ltd.",
    "wof:placetype":"venue"
},
  "geometry": {"coordinates":[-0.3104090095,51.6175460815],"type":"Point"}
}