{
  "type": "Feature",
  "properties": {
    "addr:full":"Jordan Lane, Horrabridge Yelverton Devon PL20 7QY",
    "addr:postcode":"pl20 7qy",
    "addr:street":"Jordan Lane",
    "iso:country":"GB",
    "sg:address":"Jordan Lane, Horrabridge",
    "sg:city":"Yelverton",
    "sg:classifiers":[
        {
            "category":"Community Center",
            "type":"Public Place"
        }
    ],
    "sg:phone":"+44 1822 854358",
    "sg:postcode":"PL20 7QY",
    "sg:province":"Devon",
    "sg:tags":[
        "conference",
        "room",
        "centre"
    ],
    "wof:name":"Grimstone Manor",
    "wof:placetype":"venue"
},
  "geometry": {"coordinates":[-4.101278,50.507496],"type":"Point"}
}