{
  "type": "Feature",
  "properties": {
    "addr:full":"40 Ashlands Road Ilkley North Yorkshire LS29 8JT",
    "addr:housenumber":"40",
    "addr:postcode":"ls29 8jt",
    "addr:street":"Ashlands Road",
    "iso:country":"GB",
    "sg:address":"40 Ashlands Road",
    "sg:city":"Ilkley",
    "sg:classifiers":[
        {
            "category":"Shopping",
            "subcategory":"Stationery & Office Supplies",
            "type":"Retail Goods"
        }
    ],
    "sg:phone":"+44 1943 601360",
    "sg:postcode":"LS29 8JT",
    "sg:province":"North Yorkshire",
    "sg:tags":[
        "printers'"
    ],
    "wof:name":"Talismann Printing Services",
    "wof:placetype":"venue"
},
  "geometry": {"coordinates":[-1.813009,53.9305],"type":"Point"}
}