{
  "type": "Feature",
  "properties": {
    "addr:full":"72 Regent Road Bootle Merseyside L20 8DB",
    "addr:housenumber":"72",
    "addr:postcode":"l20 8db",
    "addr:street":"Regent Road",
    "iso:country":"GB",
    "sg:address":"72 Regent Road",
    "sg:city":"Bootle",
    "sg:classifiers":[
        {
            "category":"Cafe",
            "type":"Food & Drink"
        }
    ],
    "sg:phone":"+44 151 922 7635",
    "sg:postcode":"L20 8DB",
    "sg:province":"Merseyside",
    "sg:tags":[
        "tea",
        "snack",
        "bar",
        "room"
    ],
    "wof:name":"Blanches Cafe",
    "wof:placetype":"venue"
},
  "geometry": {"coordinates":[-3.0013709068,53.4429168701],"type":"Point"}
}