{
  "type": "Feature",
  "properties": {
    "iso:country":"GB",
    "sg:address":"41 Waterloo Road",
    "sg:city":"London",
    "sg:classifiers":[
        {
            "category":"Retail",
            "subcategory":"Auto Repair",
            "type":"Services"
        }
    ],
    "sg:phone":"+44 20 7435 8435",
    "sg:postcode":"NW2 7TS",
    "sg:province":"Greater London",
    "sg:tags":[
        "modification",
        "garage"
    ],
    "wof:name":"Wingmead Ltd.",
    "wof:placetype":"venue"
},
  "geometry": {"coordinates":[-0.2363850027,51.5674133301],"type":"Point"}
}