{
  "type": "Feature",
  "properties": {
    "addr:full":"After Sales Broadleys Industrial Park Stirling Falkirk FK7 7RX",
    "addr:postcode":"fk7 7rx",
    "addr:street":"Industrial Park",
    "iso:country":"GB",
    "sg:address":"After Sales Broadleys Industrial Park",
    "sg:city":"Stirling",
    "sg:classifiers":[
        {
            "category":"Autos & Motor Vehicles",
            "subcategory":"Automobile Sales",
            "type":"Retail Goods"
        }
    ],
    "sg:postcode":"FK7 7RX",
    "sg:province":"Falkirk",
    "sg:tags":[
        "car"
    ],
    "wof:name":"Fraser Anderson Ltd.",
    "wof:placetype":"venue"
},
  "geometry": {"coordinates":[-3.9151699543,56.1117286682],"type":"Point"}
}