{
  "type": "Feature",
  "properties": {
    "iso:country":"GB",
    "sg:address":"Concourse",
    "sg:city":"Northampton",
    "sg:classifiers":[
        {
            "category":"Bus Charters",
            "type":"Transportation"
        }
    ],
    "sg:postcode":"NN1 3BZ",
    "sg:province":"Northamptonshire",
    "sg:tags":[
        "coach"
    ],
    "wof:name":"Northampton Borough Council",
    "wof:placetype":"venue"
},
  "geometry": {"coordinates":[-0.895284,52.23394],"type":"Point"}
}