{
  "type": "Feature",
  "properties": {
    "iso:country":"GB",
    "sg:address":"101 St Marys Road",
    "sg:city":"Market Harborough",
    "sg:classifiers":[
        {
            "category":"Bars & Pubs",
            "type":"Food & Drink"
        }
    ],
    "sg:phone":"+44 1858 463680",
    "sg:postcode":"LE16 7DT",
    "sg:province":"Leicestershire",
    "sg:tags":[
        "pubs",
        "inn"
    ],
    "wof:name":"The Village Inn",
    "wof:placetype":"venue"
},
  "geometry": {"coordinates":[-0.9155920148,52.4782295227],"type":"Point"}
}