{
  "type": "Feature",
  "properties": {
    "iso:country":"GB",
    "sg:address":"Sunny Downs, Out Elmstead Lane, Barham",
    "sg:city":"Canterbury",
    "sg:classifiers":[
        {
            "category":"Home & Garden",
            "subcategory":"Garden Supply",
            "type":"Retail Goods"
        }
    ],
    "sg:postcode":"CT4 6HL",
    "sg:province":"Kent",
    "sg:tags":[
        "turfing"
    ],
    "wof:name":"Garden Care-Turfing Contractors",
    "wof:placetype":"venue"
},
  "geometry": {"coordinates":[1.157095,51.202278],"type":"Point"}
}