{
  "type": "Feature",
  "properties": {
    "addr:full":"53 Greenleaze, Knowle Bristol City of Bristol BS4 2TL",
    "addr:housenumber":"53",
    "addr:postcode":"bs4 2tl",
    "addr:street":"Greenleaze Knowle",
    "iso:country":"GB",
    "sg:address":"53 Greenleaze, Knowle",
    "sg:city":"Bristol",
    "sg:classifiers":[
        {
            "category":"Shopping",
            "subcategory":"Bicycles & Sporting Goods",
            "type":"Retail Goods"
        }
    ],
    "sg:phone":"+44 117 977 6205",
    "sg:postcode":"BS4 2TL",
    "sg:province":"City of Bristol",
    "sg:tags":[
        "cycle",
        "accessory"
    ],
    "wof:name":"Mikes Bikes",
    "wof:placetype":"venue"
},
  "geometry": {"coordinates":[-2.569779,51.434929],"type":"Point"}
}