{
  "type": "Feature",
  "properties": {
    "addr:full":"24 Fore Street Saltash Cornwall PL12 6JN",
    "addr:housenumber":"24",
    "addr:postcode":"pl12 6jn",
    "addr:street":"Fore Street",
    "iso:country":"GB",
    "sg:address":"24 Fore Street",
    "sg:city":"Saltash",
    "sg:classifiers":[
        {
            "category":"Banks & Credit Unions",
            "subcategory":"Bank",
            "type":"Services"
        }
    ],
    "sg:phone":"+44 1579 335753",
    "sg:postcode":"PL12 6JN",
    "sg:province":"Cornwall",
    "wof:name":"Barclays Bank Plc",
    "wof:placetype":"venue"
},
  "geometry": {"coordinates":[-4.2111821175,50.4087562561],"type":"Point"}
}