{
  "type": "Feature",
  "properties": {
    "addr:full":"Unit 3 Flanshaw Way, Flanshaw Industrial Estate Wakefield West Yorkshire WF2 9LP",
    "addr:housenumber":"unit 3",
    "addr:postcode":"wf2 9lp",
    "addr:street":"Flanshaw Way;Industrial Estate",
    "iso:country":"GB",
    "sg:address":"Unit 3 Flanshaw Way, Flanshaw Industrial Estate",
    "sg:city":"Wakefield",
    "sg:classifiers":[
        {
            "category":"Manufacturing",
            "subcategory":"Paper Products",
            "type":"Manufacturing & Wholesale Goods"
        }
    ],
    "sg:phone":"+44 1924 201620",
    "sg:postcode":"WF2 9LP",
    "sg:province":"West Yorkshire",
    "sg:tags":[
        "board"
    ],
    "wof:name":"Pinnacle Film & Board Sales Ltd.",
    "wof:placetype":"venue"
},
  "geometry": {"coordinates":[-1.537644,53.684872],"type":"Point"}
}