{
  "type": "Feature",
  "properties": {
    "addr:full":"14 Goodmayes Road Ilford Essex IG3 9UN",
    "addr:housenumber":"14",
    "addr:postcode":"ig3 9un",
    "addr:street":"Goodmayes Road",
    "iso:country":"GB",
    "sg:address":"14 Goodmayes Road",
    "sg:city":"Ilford",
    "sg:classifiers":[
        {
            "category":"Health Services",
            "subcategory":"Medical Lab",
            "type":"Services"
        },
        {
            "category":"Shopping",
            "subcategory":"Pharmacy",
            "type":"Retail Goods"
        }
    ],
    "sg:phone":"+44 20 8598 8880",
    "sg:postcode":"IG3 9UN",
    "sg:province":"Essex",
    "sg:tags":[
        "medicine",
        "alternative",
        "therapy",
        "treatment"
    ],
    "wof:name":"Yin Yang Chinese Medical Centre",
    "wof:placetype":"venue"
},
  "geometry": {"coordinates":[0.110312,51.566452],"type":"Point"}
}