{
  "type": "Feature",
  "properties": {
    "iso:country":"GB",
    "sg:address":"8 Duke Street",
    "sg:city":"London",
    "sg:classifiers":[
        {
            "category":"Museum",
            "subcategory":"Art Museum",
            "type":"Entertainment"
        }
    ],
    "sg:phone":"+44 20 7839 3100",
    "sg:postcode":"SW1Y 6BN",
    "sg:province":"Greater London",
    "sg:tags":[
        "gallery"
    ],
    "wof:name":"Robert Bowman Ltd.",
    "wof:placetype":"venue"
},
  "geometry": {"coordinates":[-0.152434,51.515892],"type":"Point"}
}