{
  "type": "Feature",
  "properties": {
    "addr:full":"47 East Road, West Mersea Colchester Essex CO5 8EP",
    "addr:housenumber":"47",
    "addr:postcode":"co5 8ep",
    "addr:street":"East Road West;Colchester",
    "iso:country":"GB",
    "sg:address":"47 East Road, West Mersea",
    "sg:city":"Colchester",
    "sg:classifiers":[
        {
            "category":"Building & Trades",
            "subcategory":"Construction",
            "type":"Services"
        }
    ],
    "sg:postcode":"CO5 8EP",
    "sg:province":"Essex",
    "sg:tags":[
        "builder"
    ],
    "wof:name":"Parnell,H J,",
    "wof:placetype":"venue"
},
  "geometry": {"coordinates":[0.9255200028,51.7816047668],"type":"Point"}
}