{
  "type": "Feature",
  "properties": {
    "iso:country":"GB",
    "sg:address":"Unit 4 Beaumont Ct, Prince William Rd",
    "sg:city":"Loughborough",
    "sg:classifiers":[
        {
            "category":"Professional",
            "subcategory":"Printing & Photocopies",
            "type":"Services"
        }
    ],
    "sg:phone":"+44 1509 211212",
    "sg:postcode":"LE11 5DA",
    "sg:province":"Leicestershire",
    "sg:tags":[
        "printer"
    ],
    "wof:name":"Print Factory The",
    "wof:placetype":"venue"
},
  "geometry": {"coordinates":[-1.2121440172,52.7821846008],"type":"Point"}
}