{
  "type": "Feature",
  "properties": {
    "iso:country":"GB",
    "sg:address":"Croft Wlk, Nr Pitchcroft",
    "sg:city":"Worcester",
    "sg:classifiers":[
        {
            "category":"Shopping",
            "subcategory":"Stationery & Office Supplies",
            "type":"Retail Goods"
        }
    ],
    "sg:phone":"+44 1905 25168",
    "sg:postcode":"WR1 3NZ",
    "sg:province":"Worcestershire",
    "sg:tags":[
        "equipment",
        "school"
    ],
    "wof:name":"Coomber Electronic Equipment Ltd.",
    "wof:placetype":"venue"
},
  "geometry": {"coordinates":[-2.2272861004,52.1946754456],"type":"Point"}
}