{
  "type": "Feature",
  "properties": {
    "iso:country":"GB",
    "sg:address":"Harris Industrial Estate, Hanbury Road, Stoke Prior",
    "sg:city":"Bromsgrove",
    "sg:classifiers":[
        {
            "category":"Manufacturing",
            "subcategory":"Tools & Machinery",
            "type":"Manufacturing & Wholesale Goods"
        },
        {
            "category":"Real Estate",
            "subcategory":"Architect",
            "type":"Services"
        }
    ],
    "sg:phone":"+44 1527 881993",
    "sg:postcode":"B60 4AA",
    "sg:province":"Worcestershire",
    "sg:tags":[
        "design",
        "maker"
    ],
    "wof:name":"Reddiroll Ltd.",
    "wof:placetype":"venue"
},
  "geometry": {"coordinates":[-2.055703,52.2729],"type":"Point"}
}