{
  "type": "Feature",
  "properties": {
    "iso:country":"GB",
    "sg:address":"35 John Street, Knutton",
    "sg:city":"Newcastle",
    "sg:classifiers":[
        {
            "category":"Building & Trades",
            "subcategory":"Construction",
            "type":"Services"
        }
    ],
    "sg:postcode":"ST5 6DT",
    "sg:province":"Staffordshire",
    "sg:tags":[
        "roofing"
    ],
    "wof:name":"Superior Roofing",
    "wof:placetype":"venue"
},
  "geometry": {"coordinates":[-2.247305,53.020187],"type":"Point"}
}