{
  "type": "Feature",
  "properties": {
    "iso:country":"GB",
    "sg:address":"74 Gosport Road",
    "sg:city":"Lee-on-the-solent",
    "sg:classifiers":[
        {
            "category":"Fast Food",
            "type":"Food & Drink"
        }
    ],
    "sg:phone":"+44 23 9255 1238",
    "sg:postcode":"PO13 9EN",
    "sg:province":"Hampshire",
    "sg:tags":[
        "away",
        "meal",
        "outlet",
        "take"
    ],
    "wof:name":"Tangs",
    "wof:placetype":"venue"
},
  "geometry": {"coordinates":[-1.1960639954,50.7972259521],"type":"Point"}
}