{
  "type": "Feature",
  "properties": {
    "iso:country":"GB",
    "sg:address":"56a Swan Street",
    "sg:city":"Loughborough",
    "sg:classifiers":[
        {
            "category":"Fast Food",
            "type":"Food & Drink"
        }
    ],
    "sg:phone":"+44 1509 231321",
    "sg:postcode":"LE11 5BL",
    "sg:province":"Leicestershire",
    "sg:tags":[
        "away",
        "take"
    ],
    "wof:name":"T J Burgers",
    "wof:placetype":"venue"
},
  "geometry": {"coordinates":[-1.2063310146,52.7723274231],"type":"Point"}
}