{
  "type": "Feature",
  "properties": {
    "addr:full":"Knock Hundred Ho, Knockhundred Row Midhurst West Sussex GU29 9DQ",
    "addr:postcode":"gu29 9dq",
    "addr:street":"Row",
    "iso:country":"GB",
    "sg:address":"Knock Hundred Ho, Knockhundred Row",
    "sg:city":"Midhurst",
    "sg:classifiers":[
        {
            "category":"Real Estate",
            "subcategory":"Architect",
            "type":"Services"
        }
    ],
    "sg:phone":"+44 1730 816850",
    "sg:postcode":"GU29 9DQ",
    "sg:province":"West Sussex",
    "wof:name":"Conservation Practice The",
    "wof:placetype":"venue"
},
  "geometry": {"coordinates":[-0.7405800223,50.9849128723],"type":"Point"}
}