{
  "type": "Feature",
  "properties": {
    "iso:country":"GB",
    "sg:address":"14a Park Avenue South",
    "sg:city":"Northampton",
    "sg:classifiers":[
        {
            "category":"Building & Trades",
            "subcategory":"Construction",
            "type":"Services"
        }
    ],
    "sg:phone":"+44 1604 631534",
    "sg:postcode":"NN3 3AA",
    "sg:province":"Northamptonshire",
    "sg:tags":[
        "builder"
    ],
    "wof:name":"Lifestyle Builders",
    "wof:placetype":"venue"
},
  "geometry": {"coordinates":[-0.8632810116,52.2426986694],"type":"Point"}
}