{
  "type": "Feature",
  "properties": {
    "addr:full":"129 Bridge Street Macclesfield Cheshire SK11 6QE",
    "addr:housenumber":"129",
    "addr:postcode":"sk11 6qe",
    "addr:street":"Bridge Street",
    "iso:country":"GB",
    "sg:address":"129 Bridge Street",
    "sg:city":"Macclesfield",
    "sg:classifiers":[
        {
            "category":"Professional",
            "subcategory":"Accounting & Tax Preparation",
            "type":"Services"
        }
    ],
    "sg:phone":"+44 1625 431160",
    "sg:postcode":"SK11 6QE",
    "sg:province":"Cheshire",
    "sg:tags":[
        "accountant"
    ],
    "wof:name":"Bookminders",
    "wof:placetype":"venue"
},
  "geometry": {"coordinates":[-2.1304960251,53.2561836243],"type":"Point"}
}