{
  "type": "Feature",
  "properties": {
    "addr:full":"71 Bramley Road London Greater London N14 4EY",
    "addr:housenumber":"71",
    "addr:postcode":"n14 4ey",
    "addr:street":"Bramley Road",
    "iso:country":"GB",
    "sg:address":"71 Bramley Road",
    "sg:city":"London",
    "sg:classifiers":[
        {
            "category":"Shopping",
            "subcategory":"News",
            "type":"Retail Goods"
        }
    ],
    "sg:phone":"+44 20 8886 3391",
    "sg:postcode":"N14 4EY",
    "sg:province":"Greater London",
    "sg:tags":[
        "newsagent"
    ],
    "wof:name":"Harrison",
    "wof:placetype":"venue"
},
  "geometry": {"coordinates":[-0.134872,51.646744],"type":"Point"}
}