{
  "type": "Feature",
  "properties": {
    "iso:country":"GB",
    "sg:address":"178 Chesterfield Road",
    "sg:city":"Ashford",
    "sg:classifiers":[
        {
            "category":"Retail",
            "subcategory":"Repair Shop",
            "type":"Services"
        }
    ],
    "sg:postcode":"TW15 3PU",
    "sg:province":"Greater London",
    "sg:tags":[
        "maintenance"
    ],
    "wof:name":"M & S Construction",
    "wof:placetype":"venue"
},
  "geometry": {"coordinates":[-0.4757449925,51.4332008362],"type":"Point"}
}