{
  "type": "Feature",
  "properties": {
    "addr:full":"183 Mill Rd Cambridge Cambridgeshire CB1 3AN",
    "addr:housenumber":"183",
    "addr:postcode":"cb1 3an",
    "addr:street":"Mill Rd",
    "iso:country":"GB",
    "sg:address":"183 Mill Rd",
    "sg:city":"Cambridge",
    "sg:classifiers":[
        {
            "category":"Shopping",
            "subcategory":"Pharmacy",
            "type":"Retail Goods"
        }
    ],
    "sg:phone":"+44 1223 210662",
    "sg:postcode":"CB1 3AN",
    "sg:province":"Cambridgeshire",
    "sg:tags":[
        "pharmacist",
        "chemist"
    ],
    "wof:name":"Co-op Pharmacy",
    "wof:placetype":"venue"
},
  "geometry": {"coordinates":[0.1457590014,52.1975021362],"type":"Point"}
}