{
  "type": "Feature",
  "properties": {
    "iso:country":"GB",
    "sg:address":"408-410 Radford Road",
    "sg:city":"Coventry",
    "sg:classifiers":[
        {
            "category":"Building & Trades",
            "subcategory":"Construction",
            "type":"Services"
        }
    ],
    "sg:phone":"+44 24 7660 1183",
    "sg:postcode":"CV6 3AB",
    "sg:province":"Warwickshire",
    "sg:tags":[
        "joiner",
        "carpenter"
    ],
    "wof:name":"Ron Congrave Contractors",
    "wof:placetype":"venue"
},
  "geometry": {"coordinates":[-1.5252410173,52.4252929688],"type":"Point"}
}