{
  "type": "Feature",
  "properties": {
    "addr:full":"Windsor, 24 New Road, Waltham Grimsby Lincolnshire DN37 0EN",
    "addr:housenumber":"24",
    "addr:postcode":"dn37 0en",
    "addr:street":"Windsor;New Road",
    "iso:country":"GB",
    "sg:address":"Windsor, 24 New Road, Waltham",
    "sg:city":"Grimsby",
    "sg:classifiers":[
        {
            "category":"Health Services",
            "subcategory":"Health Practitioner",
            "type":"Services"
        }
    ],
    "sg:phone":"+44 1472 823589",
    "sg:postcode":"DN37 0EN",
    "sg:province":"Lincolnshire",
    "sg:tags":[
        "physiotherapist"
    ],
    "wof:name":"Raymonde D Adams",
    "wof:placetype":"venue"
},
  "geometry": {"coordinates":[-0.102155,53.5164451599],"type":"Point"}
}