{
  "type": "Feature",
  "properties": {
    "iso:country":"GB",
    "sg:address":"Studio 110, 28 St. Leonards Rd",
    "sg:city":"Windsor",
    "sg:classifiers":[
        {
            "category":"Sports & Exercise",
            "subcategory":"Sports Center",
            "type":"Entertainment"
        }
    ],
    "sg:phone":"+44 1753 851660",
    "sg:postcode":"SL4 3BB",
    "sg:province":"Berkshire",
    "sg:tags":[
        "coaching"
    ],
    "wof:name":"Foundation Personal Training",
    "wof:placetype":"venue"
},
  "geometry": {"coordinates":[-0.624664,51.478806],"type":"Point"}
}