{
  "type": "Feature",
  "properties": {
    "iso:country":"GB",
    "sg:address":"Atlas Ho, 265 Stratford Rd",
    "sg:city":"Solihull",
    "sg:classifiers":[
        {
            "category":"Professional",
            "subcategory":"Business Services",
            "type":"Services"
        }
    ],
    "sg:phone":"+44 121 746 3999",
    "sg:postcode":"B90 3AL",
    "sg:province":"West Midlands",
    "sg:tags":[
        "answering"
    ],
    "wof:name":"Professional & Trade Support Services",
    "wof:placetype":"venue"
},
  "geometry": {"coordinates":[-1.82546,52.41011],"type":"Point"}
}