{
  "type": "Feature",
  "properties": {
    "addr:full":"121 Sandgate Road Folkestone Kent CT20 2BL",
    "addr:housenumber":"121",
    "addr:postcode":"ct20 2bl",
    "addr:street":"Sandgate Road",
    "iso:country":"GB",
    "sg:address":"121 Sandgate Road",
    "sg:city":"Folkestone",
    "sg:classifiers":[
        {
            "category":"Cafe",
            "type":"Food & Drink"
        }
    ],
    "sg:phone":"+44 1303 255710",
    "sg:postcode":"CT20 2BL",
    "sg:province":"Kent",
    "sg:tags":[
        "tea",
        "snack",
        "bar",
        "room"
    ],
    "wof:name":"Le Cafe Ganmac",
    "wof:placetype":"venue"
},
  "geometry": {"coordinates":[1.175776,51.077686],"type":"Point"}
}