{
  "type": "Feature",
  "properties": {
    "addr:full":"Penkhull New Rd Stoke On Trent Staffordshire ST4 5DG",
    "addr:postcode":"st4 5dg",
    "addr:street":"New Rd",
    "iso:country":"GB",
    "sg:address":"Penkhull New Rd",
    "sg:city":"Stoke On Trent",
    "sg:classifiers":[
        {
            "category":"Bars & Pubs",
            "type":"Food & Drink"
        }
    ],
    "sg:phone":"+44 1782 418941",
    "sg:postcode":"ST4 5DG",
    "sg:province":"Staffordshire",
    "sg:tags":[
        "pubs",
        "inn"
    ],
    "wof:name":"Terrace Inn The",
    "wof:placetype":"venue"
},
  "geometry": {"coordinates":[-2.194239,53.001244],"type":"Point"}
}