{
  "type": "Feature",
  "properties": {
    "addr:full":"Hill Top Farm, Pepper Hill Halifax West Yorkshire HX3 7TH",
    "addr:postcode":"hx3 7th",
    "iso:country":"GB",
    "sg:address":"Hill Top Farm, Pepper Hill",
    "sg:city":"Halifax",
    "sg:classifiers":[
        {
            "category":"Food & Beverages",
            "subcategory":"Groceries & Convenience Stores",
            "type":"Retail Goods"
        }
    ],
    "sg:postcode":"HX3 7TH",
    "sg:province":"West Yorkshire",
    "sg:tags":[
        "merchant",
        "potato"
    ],
    "wof:name":"S M R Prepacked Potatoes",
    "wof:placetype":"venue"
},
  "geometry": {"coordinates":[-1.82934,53.756191],"type":"Point"}
}