{
  "type": "Feature",
  "properties": {
    "addr:full":"12 Charlton Dr Cradley Heath West Midlands B64 7BJ",
    "addr:housenumber":"12",
    "addr:postcode":"b64 7bj",
    "addr:street":"Charlton Dr",
    "iso:country":"GB",
    "sg:address":"12 Charlton Dr",
    "sg:city":"Cradley Heath",
    "sg:classifiers":[
        {
            "category":"Home & Garden",
            "subcategory":"Hardware",
            "type":"Retail Goods"
        }
    ],
    "sg:postcode":"B64 7BJ",
    "sg:province":"West Midlands",
    "sg:tags":[
        "device",
        "fixing",
        "fastener"
    ],
    "wof:name":"Rivex Ltd",
    "wof:placetype":"venue"
},
  "geometry": {"coordinates":[-2.081997,52.46553],"type":"Point"}
}