{
  "type": "Feature",
  "properties": {
    "addr:full":"Unit 5, Buckwins Square, Burnt Mills Industrial Basildon Essex SS13 1BJ",
    "addr:housenumber":"unit 5",
    "addr:postcode":"ss13 1bj",
    "addr:street":"Buckwins Square",
    "iso:country":"GB",
    "sg:address":"Unit 5, Buckwins Square, Burnt Mills Industrial",
    "sg:city":"Basildon",
    "sg:classifiers":[
        {
            "category":"Home & Garden",
            "subcategory":"Building Materials",
            "type":"Retail Goods"
        }
    ],
    "sg:phone":"+44 1268 726633",
    "sg:postcode":"SS13 1BJ",
    "sg:province":"Essex",
    "sg:tags":[
        "insulation",
        "installers"
    ],
    "wof:name":"D R Matthews Insulations Ltd.",
    "wof:placetype":"venue"
},
  "geometry": {"coordinates":[0.519958,51.584824],"type":"Point"}
}