{
  "type": "Feature",
  "properties": {
    "iso:country":"GB",
    "sg:address":"Unit F Liver Industrial Estate, Long Lane, Aintree",
    "sg:city":"Liverpool",
    "sg:classifiers":[
        {
            "category":"Building & Trades",
            "subcategory":"Plumbing",
            "type":"Services"
        },
        {
            "category":"Home & Garden",
            "subcategory":"Hardware",
            "type":"Retail Goods"
        }
    ],
    "sg:phone":"+44 151 525 3344",
    "sg:postcode":"L9 7ES",
    "sg:province":"Merseyside",
    "sg:tags":[
        "merchant",
        "plumber",
        "plumbers'"
    ],
    "wof:name":"William Wilson Ltd.",
    "wof:placetype":"venue"
},
  "geometry": {"coordinates":[-2.946449995,53.4522285461],"type":"Point"}
}