{
  "type": "Feature",
  "properties": {
    "addr:full":"Fewster Bldgs, Hexham Rd, Swallwell Newcastle-upon-tyne Durham NE16 3AE",
    "addr:postcode":"ne16 3ae",
    "addr:street":"Hexham Rd",
    "iso:country":"GB",
    "sg:address":"Fewster Bldgs, Hexham Rd, Swallwell",
    "sg:city":"Newcastle-upon-tyne",
    "sg:classifiers":[
        {
            "category":"Communications",
            "type":"Services"
        }
    ],
    "sg:postcode":"NE16 3AE",
    "sg:province":"Durham",
    "sg:tags":[
        "telecommunication"
    ],
    "wof:name":"Telecom Eirean U K",
    "wof:placetype":"venue"
},
  "geometry": {"coordinates":[-1.685023,54.954487],"type":"Point"}
}