{
  "type": "Feature",
  "properties": {
    "addr:full":"Beaulieu Farm, 740 The Ridge St Leonards-on-sea East Sussex TN37 7PS",
    "addr:housenumber":"740",
    "addr:postcode":"tn37 7ps",
    "addr:street":"The Ridge St",
    "iso:country":"GB",
    "sg:address":"Beaulieu Farm, 740 The Ridge",
    "sg:city":"St Leonards-on-sea",
    "sg:classifiers":[
        {
            "category":"Retail",
            "subcategory":"Repair Shop",
            "type":"Services"
        },
        {
            "category":"Shopping",
            "subcategory":"Pets & Pet Supplies",
            "type":"Retail Goods"
        }
    ],
    "sg:phone":"+44 1424 755300",
    "sg:postcode":"TN37 7PS",
    "sg:province":"East Sussex",
    "sg:tags":[
        "feed",
        "food",
        "plant",
        "machinery",
        "animal"
    ],
    "wof:name":"Eldridge Bros",
    "wof:placetype":"venue"
},
  "geometry": {"coordinates":[0.5581700206,50.8892211914],"type":"Point"}
}