{
  "type": "Feature",
  "properties": {
    "iso:country":"GB",
    "sg:address":"33-35 Manor Road",
    "sg:city":"Colchester",
    "sg:classifiers":[
        {
            "category":"Professional",
            "subcategory":"Computer Services",
            "type":"Services"
        }
    ],
    "sg:phone":"+44 1206 711400",
    "sg:postcode":"CO3 3LX",
    "sg:province":"Essex",
    "sg:tags":[
        "repair",
        "system",
        "maintenance",
        "software"
    ],
    "sg:website":"http://www.cwise.co.uk",
    "wof:name":"Computerwise Ltd",
    "wof:placetype":"venue"
},
  "geometry": {"coordinates":[0.891461,51.888081],"type":"Point"}
}