{
  "type": "Feature",
  "properties": {
    "iso:country":"GB",
    "sg:address":"The Bungalow, Ashlands Farm, Southwick",
    "sg:city":"Fareham",
    "sg:classifiers":[
        {
            "category":"Farming",
            "subcategory":"Dairy Farm",
            "type":"Manufacturing & Wholesale Goods"
        }
    ],
    "sg:postcode":"PO17 6BJ",
    "sg:province":"Hampshire",
    "wof:name":"J & J E Lillywhite",
    "wof:placetype":"venue"
},
  "geometry": {"coordinates":[-1.107613,50.869907],"type":"Point"}
}