{
  "type": "Feature",
  "properties": {
    "iso:country":"GB",
    "sg:address":"Allinson Street, Off Station Lane, Featherstone",
    "sg:city":"Pontefract",
    "sg:classifiers":[
        {
            "category":"Bus Charters",
            "type":"Transportation"
        }
    ],
    "sg:phone":"+44 1977 791738",
    "sg:postcode":"WF7 5BL",
    "sg:province":"West Yorkshire",
    "sg:tags":[
        "hire",
        "coach"
    ],
    "wof:name":"Mary Ross",
    "wof:placetype":"venue"
},
  "geometry": {"coordinates":[-1.35983,53.677212],"type":"Point"}
}