{
  "type": "Feature",
  "properties": {
    "iso:country":"GB",
    "sg:address":"45 Bournemouth Road, Chandlers Ford, Eastleigh",
    "sg:city":"Southampton",
    "sg:classifiers":[
        {
            "category":"Shopping",
            "subcategory":"Computers & Home Electronics",
            "type":"Retail Goods"
        }
    ],
    "sg:phone":"+44 23 8026 0311",
    "sg:postcode":"SO53 3DJ",
    "sg:province":"Hampshire",
    "sg:tags":[
        "electrical"
    ],
    "wof:name":"Rex Electrical Wholesale",
    "wof:placetype":"venue"
},
  "geometry": {"coordinates":[-1.385202,50.979298],"type":"Point"}
}