{
  "type": "Feature",
  "properties": {
    "addr:full":"60 Wolverhampton Street Willenhall West Midlands WV13 2NF",
    "addr:housenumber":"60",
    "addr:postcode":"wv13 2nf",
    "addr:street":"Wolverhampton Street",
    "iso:country":"GB",
    "sg:address":"60 Wolverhampton Street",
    "sg:city":"Willenhall",
    "sg:classifiers":[
        {
            "category":"Personal",
            "subcategory":"Sauna",
            "type":"Services"
        }
    ],
    "sg:phone":"+44 1902 632413",
    "sg:postcode":"WV13 2NF",
    "sg:province":"West Midlands",
    "wof:name":"Annabel's Sauna",
    "wof:placetype":"venue"
},
  "geometry": {"coordinates":[-2.0562419891,52.5843467712],"type":"Point"}
}