{
  "type": "Feature",
  "properties": {
    "iso:country":"GB",
    "sg:address":"54 Kingsway South",
    "sg:city":"Warrington",
    "sg:classifiers":[
        {
            "category":"Autos & Motor Vehicles",
            "subcategory":"Automobile Sales",
            "type":"Retail Goods"
        }
    ],
    "sg:postcode":"WA4 1LR",
    "sg:province":"Cheshire",
    "sg:tags":[
        "car"
    ],
    "wof:name":"Lakeside Motors Warrington",
    "wof:placetype":"venue"
},
  "geometry": {"coordinates":[-2.579264,53.383705],"type":"Point"}
}