{
  "type": "Feature",
  "properties": {
    "iso:country":"GB",
    "sg:address":"25 Wellington Street, St Johns",
    "sg:city":"Blackburn",
    "sg:classifiers":[
        {
            "category":"Personal",
            "type":"Services"
        },
        {
            "category":"Professional",
            "subcategory":"Computer Services",
            "type":"Services"
        }
    ],
    "sg:phone":"+44 1254 583032",
    "sg:postcode":"BB1 8AF",
    "sg:province":"Lancashire",
    "sg:tags":[
        "information",
        "advice",
        "counselling"
    ],
    "wof:name":"The Women's Centre",
    "wof:placetype":"venue"
},
  "geometry": {"coordinates":[-2.48803,53.752361],"type":"Point"}
}