{
  "type": "Feature",
  "properties": {
    "addr:full":"Unit 4 Osmaston Road Business Park, Osmaston Road Derby Derbyshire DE23 8LD",
    "addr:housenumber":"unit 4",
    "addr:postcode":"de23 8ld",
    "addr:street":"Osmaston Road Business Park Osmaston Road",
    "iso:country":"GB",
    "sg:address":"Unit 4 Osmaston Road Business Park, Osmaston Road",
    "sg:city":"Derby",
    "sg:classifiers":[
        {
            "category":"Education",
            "subcategory":"Music School",
            "type":"Public Place"
        }
    ],
    "sg:phone":"+44 1332 207507",
    "sg:postcode":"DE23 8LD",
    "sg:province":"Derbyshire",
    "sg:tags":[
        "conservatory"
    ],
    "wof:name":"Choice Conservatories (Derby) Ltd.",
    "wof:placetype":"venue"
},
  "geometry": {"coordinates":[-1.4706740379,52.9135284424],"type":"Point"}
}