{
  "type": "Feature",
  "properties": {
    "addr:full":"382 Windy Bank Lane, Hartshead Liversedge West Yorkshire WF15 8AG",
    "addr:housenumber":"382",
    "addr:postcode":"wf15 8ag",
    "addr:street":"Windy Bank Lane Hartshead Liversedge West",
    "iso:country":"GB",
    "sg:address":"382 Windy Bank Lane, Hartshead",
    "sg:city":"Liversedge",
    "sg:classifiers":[
        {
            "category":"Education",
            "subcategory":"Special Training",
            "type":"Public Place"
        }
    ],
    "sg:postcode":"WF15 8AG",
    "sg:province":"West Yorkshire",
    "sg:tags":[
        "product",
        "centre"
    ],
    "wof:name":"Fork Truck Training",
    "wof:placetype":"venue"
},
  "geometry": {"coordinates":[-1.7187819481,53.7026786804],"type":"Point"}
}