{
  "type": "Feature",
  "properties": {
    "addr:full":"Main Street, North Kessock Inverness Highland IV1 3XN",
    "addr:postcode":"iv1 3xn",
    "addr:street":"Main Street",
    "iso:country":"GB",
    "sg:address":"Main Street, North Kessock",
    "sg:city":"Inverness",
    "sg:classifiers":[
        {
            "category":"Personal",
            "subcategory":"Beauty Salon",
            "type":"Services"
        }
    ],
    "sg:postcode":"IV1 3XN",
    "sg:province":"Highland",
    "sg:tags":[
        "unisex",
        "hairdresser"
    ],
    "wof:name":"Adam & Eve",
    "wof:placetype":"venue"
},
  "geometry": {"coordinates":[-4.2468008995,57.5013427734],"type":"Point"}
}