{
  "type": "Feature",
  "properties": {
    "addr:full":"119 Stoke Road Guildford Surrey GU1 1ET",
    "addr:housenumber":"119",
    "addr:postcode":"gu1 1et",
    "addr:street":"Stoke Road",
    "iso:country":"GB",
    "sg:address":"119 Stoke Road",
    "sg:city":"Guildford",
    "sg:classifiers":[
        {
            "category":"Travel",
            "subcategory":"Hotels & Motels",
            "type":"Entertainment"
        }
    ],
    "sg:phone":"+44 1483 532200",
    "sg:postcode":"GU1 1ET",
    "sg:province":"Surrey",
    "sg:tags":[
        "house",
        "guest"
    ],
    "wof:name":"Abeille House",
    "wof:placetype":"venue"
},
  "geometry": {"coordinates":[-0.571927,51.243942],"type":"Point"}
}