{
  "type": "Feature",
  "properties": {
    "iso:country":"GB",
    "sg:address":"Unit 1 Palace Industrial Estate, Bircholt Road, Parkwood",
    "sg:city":"Maidstone",
    "sg:classifiers":[
        {
            "category":"Professional",
            "subcategory":"Printing & Photocopies",
            "type":"Services"
        }
    ],
    "sg:phone":"+44 1622 763040",
    "sg:postcode":"ME15 9XU",
    "sg:province":"Kent",
    "sg:tags":[
        "printer"
    ],
    "wof:name":"Langleyprint",
    "wof:placetype":"venue"
},
  "geometry": {"coordinates":[0.5584700108,51.2346687317],"type":"Point"}
}