{
  "type": "Feature",
  "properties": {
    "iso:country":"GB",
    "sg:address":"15 Hollman Drive",
    "sg:city":"Romsey",
    "sg:classifiers":[
        {
            "category":"Building & Trades",
            "subcategory":"Construction",
            "type":"Services"
        }
    ],
    "sg:phone":"+44 1794 513730",
    "sg:postcode":"SO51 8ES",
    "sg:province":"Hampshire",
    "sg:tags":[
        "dry",
        "lining",
        "plasterers",
        "screeders"
    ],
    "wof:name":"N C Norris",
    "wof:placetype":"venue"
},
  "geometry": {"coordinates":[-1.503839016,50.9920272827],"type":"Point"}
}