{
  "type": "Feature",
  "properties": {
    "addr:full":"Broadmead La, Keynsham Bristol City of Bristol BS31 1ST",
    "addr:postcode":"bs31 1st",
    "iso:country":"GB",
    "sg:address":"Broadmead La, Keynsham",
    "sg:city":"Bristol",
    "sg:classifiers":[
        {
            "category":"Professional",
            "subcategory":"Printing & Photocopies",
            "type":"Services"
        }
    ],
    "sg:phone":"+44 117 986 0702",
    "sg:postcode":"BS31 1ST",
    "sg:province":"City of Bristol",
    "sg:tags":[
        "embroiderer"
    ],
    "wof:name":"Cutting Edge (Bristol) Ltd",
    "wof:placetype":"venue"
},
  "geometry": {"coordinates":[-2.4838340282,51.4178733826],"type":"Point"}
}