{
  "type": "Feature",
  "properties": {
    "iso:country":"GB",
    "sg:address":"London Road",
    "sg:city":"Attleborough",
    "sg:classifiers":[
        {
            "category":"Home & Garden",
            "subcategory":"Garden Supply",
            "type":"Retail Goods"
        }
    ],
    "sg:phone":"+44 1953 454707",
    "sg:postcode":"NR17 1AY",
    "sg:province":"Norfolk",
    "sg:tags":[
        "planting",
        "tree",
        "shrub"
    ],
    "wof:name":"Peter Beales Roses Ltd.",
    "wof:placetype":"venue"
},
  "geometry": {"coordinates":[1.000969,52.509281],"type":"Point"}
}