{
  "type": "Feature",
  "properties": {
    "addr:full":"77 Brynau Road, Castle Park Caerphilly Caerphilly CF83 1PF",
    "addr:housenumber":"77",
    "addr:postcode":"cf83 1pf",
    "addr:street":"Brynau Road Castle",
    "iso:country":"GB",
    "sg:address":"77 Brynau Road, Castle Park",
    "sg:city":"Caerphilly",
    "sg:classifiers":[
        {
            "category":"Building & Trades",
            "subcategory":"Plumbing",
            "type":"Services"
        }
    ],
    "sg:postcode":"CF83 1PF",
    "sg:province":"Caerphilly",
    "sg:tags":[
        "heating"
    ],
    "wof:name":"Richard S Ferris Plumbing & Heating",
    "wof:placetype":"venue"
},
  "geometry": {"coordinates":[-3.2108969688,51.5768966675],"type":"Point"}
}