{
  "type": "Feature",
  "properties": {
    "addr:full":"155 Newgate La Mansfield Nottinghamshire NG18 2QD",
    "addr:housenumber":"155",
    "addr:postcode":"ng18 2qd",
    "addr:street":"Newgate La Mansfield",
    "iso:country":"GB",
    "sg:address":"155 Newgate La",
    "sg:city":"Mansfield",
    "sg:classifiers":[
        {
            "category":"Shopping",
            "subcategory":"Used Merchandise",
            "type":"Retail Goods"
        }
    ],
    "sg:phone":"+44 1623 464419",
    "sg:postcode":"NG18 2QD",
    "sg:province":"Nottinghamshire",
    "sg:tags":[
        "shop",
        "second-hand"
    ],
    "wof:name":"Classic Junk",
    "wof:placetype":"venue"
},
  "geometry": {"coordinates":[-1.182825,53.144127],"type":"Point"}
}