{
  "type": "Feature",
  "properties": {
    "iso:country":"GB",
    "sg:address":"Unit 19 Marples Ridgeway Est, Station Approach",
    "sg:city":"Watford",
    "sg:classifiers":[
        {
            "category":"Utilities",
            "subcategory":"Refuse",
            "type":"Services"
        }
    ],
    "sg:phone":"+44 1923 233603",
    "sg:postcode":"WD1 7LR",
    "sg:province":"Hertfordshire",
    "sg:tags":[
        "skip",
        "hire"
    ],
    "wof:name":"R J & H Skip Hire",
    "wof:placetype":"venue"
},
  "geometry": {"coordinates":[-0.390719,51.652119],"type":"Point"}
}