{
  "type": "Feature",
  "properties": {
    "addr:full":"319 High Street Slough Berkshire SL1 1BH",
    "addr:housenumber":"319",
    "addr:postcode":"sl1 1bh",
    "addr:street":"High Street",
    "iso:country":"GB",
    "sg:address":"319 High Street",
    "sg:city":"Slough",
    "sg:classifiers":[
        {
            "category":"Insurance",
            "subcategory":"Insurance Agent",
            "type":"Services"
        }
    ],
    "sg:phone":"+44 1753 521216",
    "sg:postcode":"SL1 1BH",
    "sg:province":"Berkshire",
    "wof:name":"Berkshire Insurance Centre",
    "wof:placetype":"venue"
},
  "geometry": {"coordinates":[-0.5854139924,51.5073852539],"type":"Point"}
}