{
  "type": "Feature",
  "properties": {
    "iso:country":"GB",
    "sg:address":"10a Whin Common Rd",
    "sg:city":"Downham Market",
    "sg:classifiers":[
        {
            "category":"Farming",
            "subcategory":"Livestock Farm",
            "type":"Manufacturing & Wholesale Goods"
        }
    ],
    "sg:phone":"+44 1366 382106",
    "sg:postcode":"PE38 0DX",
    "sg:province":"Cambridgeshire",
    "sg:tags":[
        "others"
    ],
    "wof:name":"R E Weeds",
    "wof:placetype":"venue"
},
  "geometry": {"coordinates":[0.380845,52.586777],"type":"Point"}
}