{
  "type": "Feature",
  "properties": {
    "iso:country":"GB",
    "sg:address":"Lee Mills, Parkside, Scholes",
    "sg:city":"Huddersfield",
    "sg:classifiers":[
        {
            "category":"Farming",
            "subcategory":"Dairy Farm",
            "type":"Manufacturing & Wholesale Goods"
        }
    ],
    "sg:phone":"+44 1484 681227",
    "sg:postcode":"HD9 1UF",
    "sg:province":"South Yorkshire",
    "wof:name":"D & C Tinker",
    "wof:placetype":"venue"
},
  "geometry": {"coordinates":[-1.763534,53.563446],"type":"Point"}
}