{
  "type": "Feature",
  "properties": {
    "iso:country":"GB",
    "sg:address":"8b Newbegin",
    "sg:city":"Hornsea",
    "sg:classifiers":[
        {
            "category":"Personal",
            "subcategory":"Beauty Salon",
            "type":"Services"
        }
    ],
    "sg:postcode":"HU18 1AG",
    "sg:province":"East Riding of Yorkshire",
    "sg:tags":[
        "unisex",
        "hairdresser"
    ],
    "wof:name":"Young Ones",
    "wof:placetype":"venue"
},
  "geometry": {"coordinates":[-0.173125,53.910591],"type":"Point"}
}