{
  "type": "Feature",
  "properties": {
    "addr:full":"32 Danbury Street, Islington London Greater London N1 8JU",
    "addr:housenumber":"32",
    "addr:postcode":"n1 8ju",
    "addr:street":"Danbury Street",
    "iso:country":"GB",
    "sg:address":"32 Danbury Street, Islington",
    "sg:city":"London",
    "sg:classifiers":[
        {
            "category":"Professional",
            "subcategory":"Research",
            "type":"Services"
        }
    ],
    "sg:phone":"+44 20 7553 6717",
    "sg:postcode":"N1 8JU",
    "sg:province":"Greater London",
    "sg:tags":[
        "market"
    ],
    "wof:name":"Field Management Ltd.",
    "wof:placetype":"venue"
},
  "geometry": {"coordinates":[-0.0988710001,51.5343322754],"type":"Point"}
}