{
  "type": "Feature",
  "properties": {
    "iso:country":"GB",
    "sg:address":"119 Edmund St",
    "sg:city":"Birmingham",
    "sg:classifiers":[
        {
            "category":"Bars & Pubs",
            "type":"Food & Drink"
        }
    ],
    "sg:phone":"+44 121 200 3821",
    "sg:postcode":"B3 2HJ",
    "sg:province":"West Midlands",
    "sg:tags":[
        "pubs",
        "inn"
    ],
    "wof:name":"White Swan The",
    "wof:placetype":"venue"
},
  "geometry": {"coordinates":[-1.900957942,52.4819068909],"type":"Point"}
}