{
  "type": "Feature",
  "properties": {
    "addr:full":"Park View, Croftamie Glasgow Argyll and Bute G63 0EU",
    "addr:postcode":"g63 0eu",
    "iso:country":"GB",
    "sg:address":"Park View, Croftamie",
    "sg:city":"Glasgow",
    "sg:classifiers":[
        {
            "category":"Utilities",
            "subcategory":"Fuel Oil & Lpg",
            "type":"Services"
        }
    ],
    "sg:phone":"+44 1360 660264",
    "sg:postcode":"G63 0EU",
    "sg:province":"Argyll and Bute",
    "sg:tags":[
        "distributor"
    ],
    "wof:name":"James D Bilsland Ltd.",
    "wof:placetype":"venue"
},
  "geometry": {"coordinates":[-4.446002,56.042091],"type":"Point"}
}