{
  "type": "Feature",
  "properties": {
    "iso:country":"GB",
    "sg:address":"Rock Lodge Road, Roker",
    "sg:city":"Sunderland",
    "sg:classifiers":[
        {
            "category":"Health Services",
            "subcategory":"Nursing And Care Facility",
            "type":"Services"
        }
    ],
    "sg:phone":"+44 191 549 6441",
    "sg:postcode":"SR6 9NH",
    "sg:province":"Tyne and Wear",
    "sg:tags":[
        "home"
    ],
    "wof:name":"Wearcourt Nursing Home",
    "wof:placetype":"venue"
},
  "geometry": {"coordinates":[-1.3676990271,54.9275093079],"type":"Point"}
}