{
  "type": "Feature",
  "properties": {
    "addr:full":"Richmond Osteopathic & Sports Close, Inic Richmond Greater London TW9 2SS",
    "addr:postcode":"tw9 2ss",
    "addr:street":"Close",
    "iso:country":"GB",
    "sg:address":"Richmond Osteopathic & Sports Close, Inic",
    "sg:city":"Richmond",
    "sg:classifiers":[
        {
            "category":"Health Services",
            "subcategory":"Health Practitioner",
            "type":"Services"
        }
    ],
    "sg:phone":"+44 20 8940 2336",
    "sg:postcode":"TW9 2SS",
    "sg:province":"Greater London",
    "sg:tags":[
        "osteopath"
    ],
    "wof:name":"Richmond Osteopathic & Sports Clinic",
    "wof:placetype":"venue"
},
  "geometry": {"coordinates":[-0.30226,51.46545],"type":"Point"}
}