{
  "type": "Feature",
  "properties": {
    "addr:full":"The Courtyard, 4 Evelyn Rd Chiswick Greater London W4 5JL",
    "addr:housenumber":"4",
    "addr:postcode":"w4 5jl",
    "addr:street":"Evelyn Rd",
    "iso:country":"GB",
    "sg:address":"The Courtyard, 4 Evelyn Rd",
    "sg:city":"Chiswick",
    "sg:classifiers":[
        {
            "category":"Professional",
            "subcategory":"Management & Consulting",
            "type":"Services"
        }
    ],
    "sg:phone":"+44 20 8742 7827",
    "sg:postcode":"W4 5JL",
    "sg:province":"Greater London",
    "sg:tags":[
        "marketing",
        "consultant"
    ],
    "wof:name":"Writing For Business",
    "wof:placetype":"venue"
},
  "geometry": {"coordinates":[-0.2632600069,51.4986114502],"type":"Point"}
}