{
  "type": "Feature",
  "properties": {
    "iso:country":"GB",
    "sg:address":"North Skene",
    "sg:city":"Turriff",
    "sg:classifiers":[
        {
            "category":"Organizations",
            "subcategory":"Non-profit Organization",
            "type":"Services"
        }
    ],
    "sg:phone":"+44 1888 551328",
    "sg:postcode":"AB53 5RD",
    "sg:province":"Aberdeenshire",
    "sg:tags":[
        "organisation",
        "animal",
        "welfare"
    ],
    "wof:name":"Banff & Aberdeenshire Rescue & Rehoming Kennels Office",
    "wof:placetype":"venue"
},
  "geometry": {"coordinates":[-2.322259,57.57436],"type":"Point"}
}