{
  "type": "Feature",
  "properties": {
    "addr:full":"Leven Valley Enterprise Centre, Castlehill Rd Dumbarton Argyll and Bute G82 5BN",
    "addr:postcode":"g82 5bn",
    "addr:street":"Leven;Castlehill Rd",
    "iso:country":"GB",
    "sg:address":"Leven Valley Enterprise Centre, Castlehill Rd",
    "sg:city":"Dumbarton",
    "sg:classifiers":[
        {
            "category":"Organizations",
            "subcategory":"Non-profit Organization",
            "type":"Services"
        }
    ],
    "sg:phone":"+44 1389 726800",
    "sg:postcode":"G82 5BN",
    "sg:province":"Argyll and Bute",
    "sg:tags":[
        "charitable",
        "organisation",
        "voluntary",
        "charity"
    ],
    "sg:website":"http://www.samh.org.uk",
    "wof:name":"Scottish Association For Mental Health",
    "wof:placetype":"venue"
},
  "geometry": {"coordinates":[-4.636309,55.959103],"type":"Point"}
}