{
  "type": "Feature",
  "properties": {
    "iso:country":"GB",
    "sg:address":"Endwood Cottage, East Road, Tetford",
    "sg:city":"Horncastle",
    "sg:classifiers":[
        {
            "category":"Manufacturing",
            "subcategory":"Wood Products",
            "type":"Manufacturing & Wholesale Goods"
        }
    ],
    "sg:postcode":"LN9 6QQ",
    "sg:province":"Lincolnshire",
    "sg:tags":[
        "maker",
        "cabinet"
    ],
    "wof:name":"Peter Davis",
    "wof:placetype":"venue"
},
  "geometry": {"coordinates":[-0.009216,53.252239],"type":"Point"}
}