{
  "type": "Feature",
  "properties": {
    "addr:full":"Glebe Farm, Creake Road Sculthorpe Fakenham Norfolk NR21 9NF",
    "addr:postcode":"nr21 9nf",
    "addr:street":"Creake Road",
    "iso:country":"GB",
    "sg:address":"Glebe Farm, Creake Road Sculthorpe",
    "sg:city":"Fakenham",
    "sg:classifiers":[
        {
            "category":"Communications",
            "subcategory":"Film & Video Production",
            "type":"Services"
        }
    ],
    "sg:phone":"+44 1328 862383",
    "sg:postcode":"NR21 9NF",
    "sg:province":"Norfolk",
    "sg:tags":[
        "hot",
        "stamping",
        "foil"
    ],
    "wof:name":"Spun Components",
    "wof:placetype":"venue"
},
  "geometry": {"coordinates":[0.809607,52.842388],"type":"Point"}
}