{
  "type": "Feature",
  "properties": {
    "iso:country":"GB",
    "sg:address":"Chistlehurst, Ceciliford, Trelleck",
    "sg:city":"Monmouth",
    "sg:classifiers":[
        {
            "category":"Building & Trades",
            "subcategory":"Construction",
            "type":"Services"
        }
    ],
    "sg:phone":"+44 1600 860806",
    "sg:postcode":"NP25 4PT",
    "sg:province":"Gloucestershire",
    "sg:tags":[
        "roofing"
    ],
    "wof:name":"A B S Elbrow Ltd.",
    "wof:placetype":"venue"
},
  "geometry": {"coordinates":[-2.724471,51.745747],"type":"Point"}
}