{
  "type": "Feature",
  "properties": {
    "iso:country":"GB",
    "sg:address":"14 Baylis Road",
    "sg:city":"London",
    "sg:classifiers":[
        {
            "category":"Organizations",
            "subcategory":"Non-profit Organization",
            "type":"Services"
        }
    ],
    "sg:phone":"+44 20 7633 9291",
    "sg:postcode":"SE1 7AA",
    "sg:province":"Greater London",
    "sg:tags":[
        "organisation",
        "voluntary",
        "charity"
    ],
    "wof:name":"Waterloo Community Development Group",
    "wof:placetype":"venue"
},
  "geometry": {"coordinates":[-0.1104559973,51.501865387],"type":"Point"}
}