{
  "type": "Feature",
  "properties": {
    "addr:full":"Heather House, 11-14 Gibbon Lane Plymouth Devon PL4 8BR",
    "addr:housenumber":"11-14",
    "addr:postcode":"pl4 8br",
    "addr:street":"Gibbon Lane",
    "iso:country":"GB",
    "sg:address":"Heather House, 11-14 Gibbon Lane",
    "sg:city":"Plymouth",
    "sg:classifiers":[
        {
            "category":"Organizations",
            "subcategory":"Non-profit Organization",
            "type":"Services"
        }
    ],
    "sg:phone":"+44 1752 673626",
    "sg:postcode":"PL4 8BR",
    "sg:province":"Devon",
    "sg:tags":[
        "organisation",
        "voluntary",
        "charity"
    ],
    "wof:name":"Youth Justice Team",
    "wof:placetype":"venue"
},
  "geometry": {"coordinates":[-4.136019,50.375],"type":"Point"}
}