{
  "type": "Feature",
  "properties": {
    "iso:country":"GB",
    "sg:address":"3 Pynchon Hall, Wrights Green, Little Hallingbury",
    "sg:city":"Bishops Stortford",
    "sg:classifiers":[
        {
            "category":"Professional",
            "subcategory":"Management & Consulting",
            "type":"Services"
        }
    ],
    "sg:phone":"+44 1279 721589",
    "sg:postcode":"CM22 7RH",
    "sg:province":"Essex",
    "sg:tags":[
        "consultant",
        "business"
    ],
    "wof:name":"Elmbridge Consultants Ltd",
    "wof:placetype":"venue"
},
  "geometry": {"coordinates":[0.1884600073,51.8338317871],"type":"Point"}
}