{
  "type": "Feature",
  "properties": {
    "iso:country":"GB",
    "sg:address":"59 Glenshee Street, Parkhead",
    "sg:city":"Glasgow",
    "sg:classifiers":[
        {
            "category":"Building & Trades",
            "subcategory":"Cleaning & Sanitation",
            "type":"Services"
        }
    ],
    "sg:phone":"+44 141 556 5427",
    "sg:postcode":"G31 4RT",
    "sg:province":"Glasgow City",
    "sg:tags":[
        "cleaner",
        "window"
    ],
    "wof:name":"John Henderson",
    "wof:placetype":"venue"
},
  "geometry": {"coordinates":[-4.1908450127,55.8456726074],"type":"Point"}
}