{
  "type": "Feature",
  "properties": {
    "iso:country":"GB",
    "sg:address":"77 King Edward Road",
    "sg:city":"Northampton",
    "sg:classifiers":[
        {
            "category":"Shopping",
            "subcategory":"Clothing, Apparel, & Fashions",
            "type":"Retail Goods"
        }
    ],
    "sg:phone":"+44 1604 635237",
    "sg:postcode":"NN1 5LY",
    "sg:province":"Northamptonshire",
    "sg:tags":[
        "shop"
    ],
    "wof:name":"Coppers",
    "wof:placetype":"venue"
},
  "geometry": {"coordinates":[-0.868229,52.242298],"type":"Point"}
}