{
  "type": "Feature",
  "properties": {
    "iso:country":"GB",
    "sg:address":"229 Ammanford Rd, Llandybie",
    "sg:city":"Ammanford",
    "sg:classifiers":[
        {
            "category":"Building & Trades",
            "subcategory":"Construction",
            "type":"Services"
        }
    ],
    "sg:phone":"+44 1269 850167",
    "sg:postcode":"SA18 2SU",
    "sg:province":"Carmarthenshire",
    "sg:tags":[
        "builder"
    ],
    "wof:name":"Reg Evans & Son",
    "wof:placetype":"venue"
},
  "geometry": {"coordinates":[-3.999304,51.810669],"type":"Point"}
}