{
  "type": "Feature",
  "properties": {
    "iso:country":"GB",
    "sg:address":"27 Roundway Down, Freshbrook",
    "sg:city":"Swindon",
    "sg:classifiers":[
        {
            "category":"Professional",
            "subcategory":"Engineering",
            "type":"Services"
        }
    ],
    "sg:phone":"+44 1793 480701",
    "sg:postcode":"SN5 8NT",
    "sg:province":"Wiltshire",
    "sg:tags":[
        "civil",
        "engineer"
    ],
    "wof:name":"Will, & Nicky Pitt",
    "wof:placetype":"venue"
},
  "geometry": {"coordinates":[-1.845259,51.545357],"type":"Point"}
}