{
  "type": "Feature",
  "properties": {
    "addr:full":"8 Thorniewood Road, Uddingston Glasgow Glasgow City G71 5QQ",
    "addr:housenumber":"8",
    "addr:postcode":"g71 5qq",
    "addr:street":"Thorniewood Road",
    "iso:country":"GB",
    "sg:address":"8 Thorniewood Road, Uddingston",
    "sg:city":"Glasgow",
    "sg:classifiers":[
        {
            "category":"Personal",
            "subcategory":"Beauty Salon",
            "type":"Services"
        }
    ],
    "sg:phone":"+44 1698 813786",
    "sg:postcode":"G71 5QQ",
    "sg:province":"Glasgow City",
    "sg:tags":[
        "unisex",
        "hairdresser"
    ],
    "wof:name":"The Hair People",
    "wof:placetype":"venue"
},
  "geometry": {"coordinates":[-4.078547,55.831638],"type":"Point"}
}