{
  "type": "Feature",
  "properties": {
    "addr:full":"5 Nappers Court, Charles Street Dorchester Dorset DT1 1EE",
    "addr:housenumber":"5",
    "addr:postcode":"dt1 1ee",
    "addr:street":"Nappers Court Charles Street",
    "iso:country":"GB",
    "sg:address":"5 Nappers Court, Charles Street",
    "sg:city":"Dorchester",
    "sg:classifiers":[
        {
            "category":"Professional",
            "subcategory":"Engineering",
            "type":"Services"
        }
    ],
    "sg:postcode":"DT1 1EE",
    "sg:province":"Dorset",
    "sg:tags":[
        "consultant",
        "structural"
    ],
    "wof:name":"Aspley Associates",
    "wof:placetype":"venue"
},
  "geometry": {"coordinates":[-2.441564,50.711906],"type":"Point"}
}