{
  "type": "Feature",
  "properties": {
    "iso:country":"GB",
    "sg:address":"4 Church Street",
    "sg:city":"Newent",
    "sg:classifiers":[
        {
            "category":"Professional",
            "subcategory":"Computer Services",
            "type":"Services"
        }
    ],
    "sg:phone":"+44 1531 822622",
    "sg:postcode":"GL18 1PP",
    "sg:province":"Gloucestershire",
    "sg:tags":[
        "development",
        "system",
        "software"
    ],
    "wof:name":"Pillar Software Ltd",
    "wof:placetype":"venue"
},
  "geometry": {"coordinates":[-2.4045,51.930698],"type":"Point"}
}