{
  "type": "Feature",
  "properties": {
    "addr:full":"The Old Post House, 81 High Street Esher Surrey KT10 9QA",
    "addr:housenumber":"81",
    "addr:postcode":"kt10 9qa",
    "addr:street":"High Street",
    "iso:country":"GB",
    "sg:address":"The Old Post House, 81 High Street",
    "sg:city":"Esher",
    "sg:classifiers":[
        {
            "category":"Real Estate",
            "subcategory":"Real Estate Agent",
            "type":"Services"
        }
    ],
    "sg:phone":"+44 1372 464496",
    "sg:postcode":"KT10 9QA",
    "sg:province":"Surrey",
    "wof:name":"Knight Frank",
    "wof:placetype":"venue"
},
  "geometry": {"coordinates":[-0.365855,51.368801],"type":"Point"}
}