{
  "type": "Feature",
  "properties": {
    "addr:full":"81 Melton Rd, West Bridgford Nottingham Nottinghamshire NG2 6EN",
    "addr:housenumber":"81",
    "addr:postcode":"ng2 6en",
    "addr:street":"Melton Rd",
    "iso:country":"GB",
    "sg:address":"81 Melton Rd, West Bridgford",
    "sg:city":"Nottingham",
    "sg:classifiers":[
        {
            "category":"Professional",
            "subcategory":"Management & Consulting",
            "type":"Services"
        }
    ],
    "sg:postcode":"NG2 6EN",
    "sg:province":"Nottinghamshire",
    "sg:tags":[
        "consultant",
        "business"
    ],
    "wof:name":"Britech Management Ltd",
    "wof:placetype":"venue"
},
  "geometry": {"coordinates":[-1.129656,52.927429],"type":"Point"}
}