{
  "type": "Feature",
  "properties": {
    "iso:country":"GB",
    "sg:address":"3 Arnbog Cottages, Meigle",
    "sg:city":"Blairgowrie",
    "sg:classifiers":[
        {
            "category":"Freight",
            "type":"Transportation"
        }
    ],
    "sg:phone":"+44 1307 840298",
    "sg:postcode":"PH12 8QT",
    "sg:province":"Angus",
    "sg:tags":[
        "haulage",
        "road"
    ],
    "wof:name":"Miller Services",
    "wof:placetype":"venue"
},
  "geometry": {"coordinates":[-3.1617720127,56.5883178711],"type":"Point"}
}