{
  "type": "Feature",
  "properties": {
    "iso:country":"GB",
    "sg:address":"31 Morgan Arcade",
    "sg:city":"Cardiff",
    "sg:classifiers":[
        {
            "category":"Shopping",
            "subcategory":"Baby Store",
            "type":"Retail Goods"
        }
    ],
    "sg:postcode":"CF10 1AF",
    "sg:province":"Cardiff",
    "sg:tags":[
        "babywear",
        "childrens"
    ],
    "wof:name":"Donald,E,",
    "wof:placetype":"venue"
},
  "geometry": {"coordinates":[-3.177089,51.47879],"type":"Point"}
}