{
  "type": "Feature",
  "properties": {
    "iso:country":"GB",
    "sg:address":"13 Norfolk Place",
    "sg:city":"London",
    "sg:classifiers":[
        {
            "category":"Manufacturing",
            "subcategory":"Tools & Machinery",
            "type":"Manufacturing & Wholesale Goods"
        }
    ],
    "sg:phone":"+44 20 7723 2295",
    "sg:postcode":"W2 1QJ",
    "sg:province":"Greater London",
    "sg:tags":[
        "power"
    ],
    "wof:name":"Langham Tools Ltd.",
    "wof:placetype":"venue"
},
  "geometry": {"coordinates":[-0.1724960059,51.5168876648],"type":"Point"}
}