{
  "type": "Feature",
  "properties": {
    "iso:country":"GB",
    "sg:address":"19a Cambridge Road, Granby Industrial Estate",
    "sg:city":"Weymouth",
    "sg:classifiers":[
        {
            "category":"Wholesale",
            "subcategory":"Non-durable Goods",
            "type":"Manufacturing & Wholesale Goods"
        },
        {
            "category":"Wholesale",
            "subcategory":"Seafood",
            "type":"Manufacturing & Wholesale Goods"
        }
    ],
    "sg:phone":"+44 1305 761162",
    "sg:postcode":"DT4 9TJ",
    "sg:province":"Dorset",
    "sg:tags":[
        "merchant",
        "carry",
        "fish",
        "cash"
    ],
    "wof:name":"Southern Food Service Ltd.",
    "wof:placetype":"venue"
},
  "geometry": {"coordinates":[-2.490671,50.613609],"type":"Point"}
}