{
  "type": "Feature",
  "properties": {
    "addr:full":"Unit 9 Glenthorne Mews, 115a Glenthorne Road London Greater London W6 0LJ",
    "addr:housenumber":"unit 9;115a",
    "addr:postcode":"w6 0lj",
    "addr:street":"Glenthorne Mews;Glenthorne Road",
    "iso:country":"GB",
    "sg:address":"Unit 9 Glenthorne Mews, 115a Glenthorne Road",
    "sg:city":"London",
    "sg:classifiers":[
        {
            "category":"Wholesale",
            "subcategory":"Construction Materials",
            "type":"Manufacturing & Wholesale Goods"
        }
    ],
    "sg:postcode":"W6 0LJ",
    "sg:province":"Greater London",
    "sg:tags":[
        "cladding"
    ],
    "wof:name":"Gig Fassadenbau Uk Ltd.",
    "wof:placetype":"venue"
},
  "geometry": {"coordinates":[-0.23159,51.494431],"type":"Point"}
}