{
  "type": "Feature",
  "properties": {
    "addr:full":"22 Barnsbury Park London Greater London N1 1HQ",
    "addr:housenumber":"22",
    "addr:postcode":"n1 1hq",
    "addr:street":"Barnsbury Park",
    "iso:country":"GB",
    "sg:address":"22 Barnsbury Park",
    "sg:city":"London",
    "sg:classifiers":[
        {
            "category":"Bars & Pubs",
            "subcategory":"Nightclub",
            "type":"Food & Drink"
        },
        {
            "category":"Banks & Credit Unions",
            "subcategory":"Financial Services",
            "type":"Services"
        }
    ],
    "sg:phone":"+44 20 7700 2939",
    "sg:postcode":"N1 1HQ",
    "sg:province":"Greater London",
    "sg:tags":[
        "club",
        "adviser",
        "night"
    ],
    "wof:name":"Home Buyers Corporation",
    "wof:placetype":"venue"
},
  "geometry": {"coordinates":[-0.10801,51.543011],"type":"Point"}
}