{
  "type": "Feature",
  "properties": {
    "addr:full":"55 Back Bridge St Manchester Greater Manchester M3 2PB",
    "addr:housenumber":"55",
    "addr:postcode":"m3 2pb",
    "addr:street":"Back Bridge St",
    "iso:country":"GB",
    "sg:address":"55 Back Bridge St",
    "sg:city":"Manchester",
    "sg:classifiers":[
        {
            "category":"Restaurant",
            "type":"Food & Drink"
        }
    ],
    "sg:postcode":"M3 2PB",
    "sg:province":"Greater Manchester",
    "wof:name":"Onour,Sacit,",
    "wof:placetype":"venue"
},
  "geometry": {"coordinates":[-2.2488598824,53.4814109802],"type":"Point"}
}