{
  "type": "Feature",
  "properties": {
    "addr:full":"43 Belvoir Street Leicester Leicestershire LE1 6SL",
    "addr:housenumber":"43",
    "addr:postcode":"le1 6sl",
    "addr:street":"Belvoir Street",
    "iso:country":"GB",
    "sg:address":"43 Belvoir Street",
    "sg:city":"Leicester",
    "sg:classifiers":[
        {
            "category":"Shopping",
            "subcategory":"Books",
            "type":"Retail Goods"
        }
    ],
    "sg:phone":"+44 116 255 8481",
    "sg:postcode":"LE1 6SL",
    "sg:province":"Leicestershire",
    "sg:tags":[
        "bookseller"
    ],
    "wof:name":"Paul Crisp",
    "wof:placetype":"venue"
},
  "geometry": {"coordinates":[-1.1317820549,52.6326980591],"type":"Point"}
}