{
  "type": "Feature",
  "properties": {
    "iso:country":"GB",
    "sg:address":"43 Montreal Road",
    "sg:city":"Brighton",
    "sg:classifiers":[
        {
            "category":"Retail",
            "subcategory":"Laundry & Dry Cleaning",
            "type":"Services"
        }
    ],
    "sg:phone":"+44 1273 691297",
    "sg:postcode":"BN2 9UY",
    "sg:province":"East Sussex",
    "sg:tags":[
        "launderette",
        "alteration"
    ],
    "wof:name":"Bates Launderette",
    "wof:placetype":"venue"
},
  "geometry": {"coordinates":[-0.127658993,50.8275489807],"type":"Point"}
}