{
  "type": "Feature",
  "properties": {
    "addr:full":"9 Walden Avenue, Arborfield Reading Berkshire RG2 9HR",
    "addr:housenumber":"9",
    "addr:postcode":"rg2 9hr",
    "addr:street":"Walden Avenue",
    "iso:country":"GB",
    "sg:address":"9 Walden Avenue, Arborfield",
    "sg:city":"Reading",
    "sg:classifiers":[
        {
            "category":"Social Services",
            "subcategory":"Child Care",
            "type":"Services"
        }
    ],
    "sg:postcode":"RG2 9HR",
    "sg:province":"Berkshire",
    "sg:tags":[
        "agency",
        "nanny"
    ],
    "wof:name":"Countrywide Nannylink",
    "wof:placetype":"venue"
},
  "geometry": {"coordinates":[-0.916121,51.399723],"type":"Point"}
}