{
  "type": "Feature",
  "properties": {
    "addr:full":"22 Lloyds Avenue Ipswich Suffolk IP1 3HD",
    "addr:housenumber":"22",
    "addr:postcode":"ip1 3hd",
    "addr:street":"Lloyds Avenue",
    "iso:country":"GB",
    "sg:address":"22 Lloyds Avenue",
    "sg:city":"Ipswich",
    "sg:classifiers":[
        {
            "category":"Bars & Pubs",
            "type":"Food & Drink"
        }
    ],
    "sg:phone":"+44 1473 250036",
    "sg:postcode":"IP1 3HD",
    "sg:province":"Suffolk",
    "sg:tags":[
        "pubs",
        "inn"
    ],
    "wof:name":"Hogs Head",
    "wof:placetype":"venue"
},
  "geometry": {"coordinates":[1.1530549526,52.058216095],"type":"Point"}
}