{
  "type": "Feature",
  "properties": {
    "addr:full":"100b Henshaw Lane, Yeadon Leeds West Yorkshire LS19 7RZ",
    "addr:housenumber":"100b",
    "addr:postcode":"ls19 7rz",
    "addr:street":"Henshaw Lane",
    "iso:country":"GB",
    "sg:address":"100b Henshaw Lane, Yeadon",
    "sg:city":"Leeds",
    "sg:classifiers":[
        {
            "category":"Professional",
            "subcategory":"Business Services",
            "type":"Services"
        }
    ],
    "sg:phone":"+44 113 250 5301",
    "sg:postcode":"LS19 7RZ",
    "sg:province":"West Yorkshire",
    "sg:tags":[
        "tile",
        "stockist"
    ],
    "wof:name":"Fine Ceramics",
    "wof:placetype":"venue"
},
  "geometry": {"coordinates":[-1.690285,53.860252],"type":"Point"}
}