{
  "type": "Feature",
  "properties": {
    "addr:full":"Devon Road Bordon Hampshire GU35 0BB",
    "addr:postcode":"gu35 0bb",
    "addr:street":"Devon Road",
    "iso:country":"GB",
    "sg:address":"Devon Road",
    "sg:city":"Bordon",
    "sg:classifiers":[
        {
            "category":"Professional",
            "subcategory":"Engineering",
            "type":"Services"
        }
    ],
    "sg:phone":"+44 1420 473953",
    "sg:postcode":"GU35 0BB",
    "sg:province":"Hampshire",
    "sg:tags":[
        "precision",
        "engineer"
    ],
    "wof:name":"Baker Engineering",
    "wof:placetype":"venue"
},
  "geometry": {"coordinates":[-0.862529,51.110153],"type":"Point"}
}