{
  "type": "Feature",
  "properties": {
    "addr:full":"30 Holywell Hill St Albans Hertfordshire AL1 1BZ",
    "addr:housenumber":"30",
    "addr:postcode":"al1 1bz",
    "addr:street":"Holywell Hill",
    "iso:country":"GB",
    "sg:address":"30 Holywell Hill",
    "sg:city":"St Albans",
    "sg:classifiers":[
        {
            "category":"Restaurant",
            "type":"Food & Drink"
        }
    ],
    "sg:phone":"+44 1727 832841",
    "sg:postcode":"AL1 1BZ",
    "sg:province":"Hertfordshire",
    "sg:tags":[
        "greek",
        "-"
    ],
    "wof:name":"KYRIAKOS GREEK TAVERNA",
    "wof:placetype":"venue"
},
  "geometry": {"coordinates":[-0.340458,51.750118],"type":"Point"}
}