{
  "type": "Feature",
  "properties": {
    "addr:full":"32 Hyndford Road Lanark South Lanarkshire ML11 9AE",
    "addr:housenumber":"32",
    "addr:postcode":"ml11 9ae",
    "addr:street":"Hyndford Road",
    "iso:country":"GB",
    "sg:address":"32 Hyndford Road",
    "sg:city":"Lanark",
    "sg:classifiers":[
        {
            "category":"Building & Trades",
            "subcategory":"Construction",
            "type":"Services"
        }
    ],
    "sg:phone":"+44 1555 664889",
    "sg:postcode":"ML11 9AE",
    "sg:province":"South Lanarkshire",
    "sg:tags":[
        "builder"
    ],
    "wof:name":"Dickie & Jack",
    "wof:placetype":"venue"
},
  "geometry": {"coordinates":[-3.771531105,55.6708641052],"type":"Point"}
}