{
  "type": "Feature",
  "properties": {
    "addr:full":"67 Bolton Road, Aspull Wigan Lancashire WN2 1QT",
    "addr:housenumber":"67",
    "addr:postcode":"wn2 1qt",
    "addr:street":"Bolton Road Aspull",
    "iso:country":"GB",
    "sg:address":"67 Bolton Road, Aspull",
    "sg:city":"Wigan",
    "sg:classifiers":[
        {
            "category":"Professional",
            "subcategory":"Management & Consulting",
            "type":"Services"
        }
    ],
    "sg:phone":"+44 1942 831803",
    "sg:postcode":"WN2 1QT",
    "sg:province":"Lancashire",
    "sg:tags":[
        "consultant",
        "business"
    ],
    "wof:name":"B M Management",
    "wof:placetype":"venue"
},
  "geometry": {"coordinates":[-2.5819730759,53.5663948059],"type":"Point"}
}