{
  "type": "Feature",
  "properties": {
    "addr:full":"20 Blenheim Gardens Bath Bath and North East Somerset BA1 6NL",
    "addr:housenumber":"20",
    "addr:postcode":"ba1 6nl",
    "addr:street":"Blenheim Gardens",
    "iso:country":"GB",
    "sg:address":"20 Blenheim Gardens",
    "sg:city":"Bath",
    "sg:classifiers":[
        {
            "category":"Professional",
            "subcategory":"Computer Services",
            "type":"Services"
        }
    ],
    "sg:postcode":"BA1 6NL",
    "sg:province":"Bath and North East Somerset",
    "sg:tags":[
        "system",
        "software"
    ],
    "wof:name":"Big Sky Technology Ltd.",
    "wof:placetype":"venue"
},
  "geometry": {"coordinates":[-2.359213,51.399731],"type":"Point"}
}