{
  "type": "Feature",
  "properties": {
    "iso:country":"GB",
    "sg:address":"20 Blenheim Gardens",
    "sg:city":"Bath",
    "sg:classifiers":[
        {
            "category":"Professional",
            "subcategory":"Computer Services",
            "type":"Services"
        }
    ],
    "sg:postcode":"BA1 6NL",
    "sg:province":"Bath and North East Somerset",
    "sg:tags":[
        "system",
        "software"
    ],
    "wof:name":"Big Sky Technology Ltd.",
    "wof:placetype":"venue"
},
  "geometry": {"coordinates":[-2.359213,51.399731],"type":"Point"}
}