{
  "type": "Feature",
  "properties": {
    "addr:full":"228 High Street London Greater London NW10 4TD",
    "addr:housenumber":"228",
    "addr:postcode":"nw10 4td",
    "addr:street":"High Street",
    "iso:country":"GB",
    "sg:address":"228 High Street",
    "sg:city":"London",
    "sg:classifiers":[
        {
            "category":"Bars & Pubs",
            "type":"Food & Drink"
        }
    ],
    "sg:postcode":"NW10 4TD",
    "sg:province":"Greater London",
    "sg:tags":[
        "pubs",
        "house",
        "inn",
        "public",
        "activity"
    ],
    "wof:name":"The Bar",
    "wof:placetype":"venue"
},
  "geometry": {"coordinates":[-0.241184,51.533432],"type":"Point"}
}