{
  "type": "Feature",
  "properties": {
    "addr:full":"Crook Road Kendal Cumbria LA8 8LY",
    "addr:postcode":"la8 8ly",
    "addr:street":"Crook Road",
    "iso:country":"GB",
    "sg:address":"Crook Road",
    "sg:city":"Kendal",
    "sg:classifiers":[
        {
            "category":"Manufacturing",
            "subcategory":"Wood Products",
            "type":"Manufacturing & Wholesale Goods"
        }
    ],
    "sg:postcode":"LA8 8LY",
    "sg:province":"Cumbria",
    "sg:tags":[
        "woodturning"
    ],
    "wof:name":"P & J Walling",
    "wof:placetype":"venue"
},
  "geometry": {"coordinates":[-2.7756490707,54.3446731567],"type":"Point"}
}