{
  "type": "Feature",
  "properties": {
    "addr:full":"Sportsman Lane, Nounsley, Hatfield Peverel Chelmsford Essex CM3 2NW",
    "addr:postcode":"cm3 2nw",
    "addr:street":"Sportsman Lane Nounsley",
    "iso:country":"GB",
    "sg:address":"Sportsman Lane, Nounsley, Hatfield Peverel",
    "sg:city":"Chelmsford",
    "sg:classifiers":[
        {
            "category":"Restaurant",
            "type":"Food & Drink"
        }
    ],
    "sg:phone":"+44 1245 380410",
    "sg:postcode":"CM3 2NW",
    "sg:province":"Essex",
    "wof:name":"Sportsman Arms",
    "wof:placetype":"venue"
},
  "geometry": {"coordinates":[0.5986580253,51.7770957947],"type":"Point"}
}