{
  "type": "Feature",
  "properties": {
    "iso:country":"GB",
    "sg:address":"120 Eastgate St",
    "sg:city":"Gloucester",
    "sg:classifiers":[
        {
            "category":"Farming",
            "subcategory":"Fish & Marine Products",
            "type":"Manufacturing & Wholesale Goods"
        }
    ],
    "sg:postcode":"GL1 1QT",
    "sg:province":"Gloucestershire",
    "sg:tags":[
        "fishmonger"
    ],
    "wof:name":"Longley,M R,",
    "wof:placetype":"venue"
},
  "geometry": {"coordinates":[-2.2401769161,51.8621711731],"type":"Point"}
}