{
  "type": "Feature",
  "properties": {
    "addr:full":"Rear Of 18 Barnet Road Potters Bar Greater London EN6 2QS",
    "addr:housenumber":"rear of 18",
    "addr:postcode":"en6 2qs",
    "addr:street":"Barnet Road",
    "iso:country":"GB",
    "sg:address":"Rear Of 18 Barnet Road",
    "sg:city":"Potters Bar",
    "sg:classifiers":[
        {
            "category":"Retail",
            "subcategory":"Auto Repair",
            "type":"Services"
        }
    ],
    "sg:phone":"+44 1707 650284",
    "sg:postcode":"EN6 2QS",
    "sg:province":"Greater London",
    "sg:tags":[
        "engine",
        "specialist",
        "garage",
        "modification",
        "car"
    ],
    "wof:name":"Moordale Motors",
    "wof:placetype":"venue"
},
  "geometry": {"coordinates":[-0.1784240007,51.6930122375],"type":"Point"}
}