{
  "type": "Feature",
  "properties": {
    "addr:full":"Fourth Floor, Gostins Building, Hanover Street Liverpool Merseyside L1 4LN",
    "addr:postcode":"l1 4ln",
    "addr:street":"Hanover Street",
    "iso:country":"GB",
    "sg:address":"Fourth Floor, Gostins Building, Hanover Street",
    "sg:city":"Liverpool",
    "sg:classifiers":[
        {
            "category":"Organizations",
            "subcategory":"Non-profit Organization",
            "type":"Services"
        }
    ],
    "sg:phone":"+44 151 709 3334",
    "sg:postcode":"L1 4LN",
    "sg:province":"Merseyside",
    "sg:tags":[
        "charitable",
        "organisation",
        "voluntary",
        "charity"
    ],
    "wof:name":"Brouhaha International",
    "wof:placetype":"venue"
},
  "geometry": {"coordinates":[-2.978481,53.409775],"type":"Point"}
}