{
  "type": "Feature",
  "properties": {
    "iso:country":"GB",
    "sg:address":"4 Epsom Clo",
    "sg:city":"Bristol",
    "sg:classifiers":[
        {
            "category":"Building & Trades",
            "subcategory":"Construction",
            "type":"Services"
        }
    ],
    "sg:phone":"+44 117 970 1076",
    "sg:postcode":"BS16 6ST",
    "sg:province":"City of Bristol",
    "sg:tags":[
        "dry",
        "lining",
        "plasterers",
        "screeders"
    ],
    "wof:name":"P Gregory",
    "wof:placetype":"venue"
},
  "geometry": {"coordinates":[-2.498129,51.497051],"type":"Point"}
}