{
  "type": "Feature",
  "properties": {
    "addr:full":"Within Crowmoor C.p School, Crowmere Rd Shrewsbury Shropshire SY2 5JJ",
    "addr:postcode":"sy2 5jj",
    "addr:street":"Crowmere Rd",
    "iso:country":"GB",
    "sg:address":"Within Crowmoor C.p School, Crowmere Rd",
    "sg:city":"Shrewsbury",
    "sg:classifiers":[
        {
            "category":"Communications",
            "subcategory":"Film & Video Production",
            "type":"Services"
        }
    ],
    "sg:phone":"+44 1743 233274",
    "sg:postcode":"SY2 5JJ",
    "sg:province":"Shropshire",
    "sg:tags":[
        "illustrator",
        "artist"
    ],
    "wof:name":"Art Studio",
    "wof:placetype":"venue"
},
  "geometry": {"coordinates":[-2.7297,52.710529],"type":"Point"}
}