{
  "type": "Feature",
  "properties": {
    "addr:full":"Bayshill Lodge, Barnet Lane, Elstree Borehamwood Hertfordshire WD6 3QU",
    "addr:postcode":"wd6 3qu",
    "addr:street":"Barnet Lane",
    "iso:country":"GB",
    "sg:address":"Bayshill Lodge, Barnet Lane, Elstree",
    "sg:city":"Borehamwood",
    "sg:classifiers":[
        {
            "category":"Communications",
            "subcategory":"News Services",
            "type":"Services"
        }
    ],
    "sg:phone":"+44 20 8953 3000",
    "sg:postcode":"WD6 3QU",
    "sg:province":"Hertfordshire",
    "sg:tags":[
        "journalist"
    ],
    "wof:name":"Michael Freedland",
    "wof:placetype":"venue"
},
  "geometry": {"coordinates":[-0.2986789942,51.6441116333],"type":"Point"}
}