{
  "type": "Feature",
  "properties": {
    "iso:country":"GB",
    "sg:address":"Tewkesbury Rd",
    "sg:city":"Cheltenham",
    "sg:classifiers":[
        {
            "category":"Travel",
            "subcategory":"Hotels & Motels",
            "type":"Entertainment"
        }
    ],
    "sg:phone":"+44 1242 233847",
    "sg:postcode":"GL51 9SL",
    "sg:province":"Gloucestershire",
    "wof:name":"Travel Inn",
    "wof:placetype":"venue"
},
  "geometry": {"coordinates":[-2.092699,51.910004],"type":"Point"}
}