{
  "type": "Feature",
  "properties": {
    "iso:country":"GB",
    "sg:address":"Shibden Head Farm, Ambler Thorn",
    "sg:city":"Bradford",
    "sg:classifiers":[
        {
            "category":"Farming",
            "subcategory":"Dairy Farm",
            "type":"Manufacturing & Wholesale Goods"
        }
    ],
    "sg:phone":"+44 1274 814184",
    "sg:postcode":"BD13 2NH",
    "sg:province":"West Yorkshire",
    "wof:name":"R A Carruthers",
    "wof:placetype":"venue"
},
  "geometry": {"coordinates":[-1.8594939709,53.7597732544],"type":"Point"}
}