{
  "type": "Feature",
  "properties": {
    "addr:full":"22-24 Thackeray Mall Fareham Hampshire PO16 0PQ",
    "addr:housenumber":"22-24",
    "addr:postcode":"po16 0pq",
    "addr:street":"Thackeray Mall",
    "iso:country":"GB",
    "sg:address":"22-24 Thackeray Mall",
    "sg:city":"Fareham",
    "sg:classifiers":[
        {
            "category":"Shopping",
            "subcategory":"Books",
            "type":"Retail Goods"
        }
    ],
    "sg:phone":"+44 1329 825693",
    "sg:postcode":"PO16 0PQ",
    "sg:province":"Hampshire",
    "sg:tags":[
        "bookseller"
    ],
    "wof:name":"Ottakars",
    "wof:placetype":"venue"
},
  "geometry": {"coordinates":[-1.174099,50.852734],"type":"Point"}
}