{
  "type": "Feature",
  "properties": {
    "addr:full":"3 Pentland Road Glasgow Glasgow City G43 2AR",
    "addr:housenumber":"3",
    "addr:postcode":"g43 2ar",
    "addr:street":"Pentland Road",
    "iso:country":"GB",
    "sg:address":"3 Pentland Road",
    "sg:city":"Glasgow",
    "sg:classifiers":[
        {
            "category":"Building & Trades",
            "subcategory":"Plumbing",
            "type":"Services"
        }
    ],
    "sg:phone":"+44 141 637 1796",
    "sg:postcode":"G43 2AR",
    "sg:province":"Glasgow City",
    "sg:tags":[
        "heating"
    ],
    "wof:name":"Munro Plumbing & Heating",
    "wof:placetype":"venue"
},
  "geometry": {"coordinates":[-4.293191,55.815899],"type":"Point"}
}