{
  "type": "Feature",
  "properties": {
    "iso:country":"GB",
    "sg:address":"119 Coles Lane",
    "sg:city":"Sutton Coldfield",
    "sg:classifiers":[
        {
            "category":"Shopping",
            "subcategory":"Department Store",
            "type":"Retail Goods"
        },
        {
            "category":"Food & Beverages",
            "subcategory":"Groceries & Convenience Stores",
            "type":"Retail Goods"
        }
    ],
    "sg:phone":"+44 121 355 4304",
    "sg:postcode":"B72 1NL",
    "sg:province":"West Midlands",
    "wof:name":"Taylors",
    "wof:placetype":"venue"
},
  "geometry": {"coordinates":[-1.819648,52.556126],"type":"Point"}
}