{
  "type": "Feature",
  "properties": {
    "iso:country":"GB",
    "sg:address":"The Fairways Hotel",
    "sg:city":"Porthcawl",
    "sg:classifiers":[
        {
            "category":"Building & Trades",
            "subcategory":"Construction",
            "type":"Services"
        }
    ],
    "sg:phone":"+44 1656 772071",
    "sg:postcode":"CF36 3LS",
    "sg:province":"Bridgend",
    "sg:tags":[
        "builder"
    ],
    "wof:name":"Godbeer Associates (U K) Ltd",
    "wof:placetype":"venue"
},
  "geometry": {"coordinates":[-3.709124,51.478554],"type":"Point"}
}