{
  "type": "Feature",
  "properties": {
    "iso:country":"GB",
    "sg:address":"3 Market Pl",
    "sg:city":"Shipston-on-stour",
    "sg:classifiers":[
        {
            "category":"Fast Food",
            "type":"Food & Drink"
        }
    ],
    "sg:postcode":"CV36 4AG",
    "sg:province":"Warwickshire",
    "sg:tags":[
        "away",
        "take"
    ],
    "wof:name":"Harvey,J,",
    "wof:placetype":"venue"
},
  "geometry": {"coordinates":[-1.624594,52.063488],"type":"Point"}
}