{
  "type": "Feature",
  "properties": {
    "iso:country":"GB",
    "sg:address":"Albert House",
    "sg:city":"Glasgow",
    "sg:classifiers":[
        {
            "category":"Professional",
            "subcategory":"Accounting & Tax Preparation",
            "type":"Services"
        }
    ],
    "sg:phone":"+44 141 429 1700",
    "sg:postcode":"G41 5RS",
    "sg:province":"Glasgow City",
    "sg:tags":[
        "accountant",
        "activity"
    ],
    "sg:website":"http://www.tbdunn.co.uk",
    "wof:name":"T B Dunn & Co",
    "wof:placetype":"venue"
},
  "geometry": {"coordinates":[-4.27848,55.84325],"type":"Point"}
}