{
  "type": "Feature",
  "properties": {
    "addr:full":"68 Bridgnorth Road, Wollaston Stourbridge Staffordshire DY8 3PA",
    "addr:housenumber":"68",
    "addr:postcode":"dy8 3pa",
    "addr:street":"Bridgnorth Road",
    "iso:country":"GB",
    "sg:address":"68 Bridgnorth Road, Wollaston",
    "sg:city":"Stourbridge",
    "sg:classifiers":[
        {
            "category":"Real Estate",
            "subcategory":"Architect",
            "type":"Services"
        }
    ],
    "sg:phone":"+44 1384 442044",
    "sg:postcode":"DY8 3PA",
    "sg:province":"Staffordshire",
    "sg:tags":[
        "technician",
        "architectural"
    ],
    "wof:name":"Capital Design Partnership",
    "wof:placetype":"venue"
},
  "geometry": {"coordinates":[-2.1642680168,52.460395813],"type":"Point"}
}