{
  "type": "Feature",
  "properties": {
    "addr:full":"29 Barry Drive Leicester Leicestershire LE3 3HH",
    "addr:housenumber":"29",
    "addr:postcode":"le3 3hh",
    "addr:street":"Barry Drive",
    "iso:country":"GB",
    "sg:address":"29 Barry Drive",
    "sg:city":"Leicester",
    "sg:classifiers":[
        {
            "category":"Autos & Motor Vehicles",
            "subcategory":"Automobile Sales",
            "type":"Retail Goods"
        }
    ],
    "sg:postcode":"LE3 3HH",
    "sg:province":"Leicestershire",
    "sg:tags":[
        "car"
    ],
    "wof:name":"Field Cars",
    "wof:placetype":"venue"
},
  "geometry": {"coordinates":[-1.228529,52.625912],"type":"Point"}
}