{
  "type": "Feature",
  "properties": {
    "iso:country":"GB",
    "sg:address":"16 High St",
    "sg:city":"Cinderford",
    "sg:classifiers":[
        {
            "category":"Shopping",
            "subcategory":"Pharmacy",
            "type":"Retail Goods"
        }
    ],
    "sg:postcode":"GL14 2SH",
    "sg:province":"Gloucestershire",
    "sg:tags":[
        "store",
        "drug"
    ],
    "wof:name":"Pennywise Drug Store",
    "wof:placetype":"venue"
},
  "geometry": {"coordinates":[-2.499054,51.824257],"type":"Point"}
}