{
  "type": "Feature",
  "properties": {
    "addr:full":"Unit 15 Bristol Vale Trading Estate, Hartcliffe Way Bristol City of Bristol BS3 5RJ",
    "addr:housenumber":"unit 15 bristol",
    "addr:postcode":"bs3 5rj",
    "addr:street":"Vale Trading Estate Hartcliffe Way",
    "iso:country":"GB",
    "sg:address":"Unit 15 Bristol Vale Trading Estate, Hartcliffe Way",
    "sg:city":"Bristol",
    "sg:classifiers":[
        {
            "category":"Home & Garden",
            "subcategory":"Home Furnishings",
            "type":"Retail Goods"
        },
        {
            "category":"Manufacturing",
            "subcategory":"Building Materials",
            "type":"Manufacturing & Wholesale Goods"
        }
    ],
    "sg:phone":"+44 117 966 4045",
    "sg:postcode":"BS3 5RJ",
    "sg:province":"City of Bristol",
    "sg:tags":[
        "merchant",
        "furnishers",
        "builder",
        "planner",
        "kitchen"
    ],
    "wof:name":"Chrissons for Corian Tops",
    "wof:placetype":"venue"
},
  "geometry": {"coordinates":[-2.6048340797,51.4300346375],"type":"Point"}
}