{
  "type": "Feature",
  "properties": {
    "iso:country":"GB",
    "sg:address":"Units 15-18 Flemington Indust Est, Hamilton Rd",
    "sg:city":"Glasgow",
    "sg:classifiers":[
        {
            "category":"Retail",
            "subcategory":"Auto Repair",
            "type":"Services"
        }
    ],
    "sg:phone":"+44 141 641 2122",
    "sg:postcode":"G72 7TN",
    "sg:province":"South Lanarkshire",
    "sg:tags":[
        "body",
        "car"
    ],
    "wof:name":"H Macartney",
    "wof:placetype":"venue"
},
  "geometry": {"coordinates":[-4.1365,55.810741],"type":"Point"}
}