{
  "type": "Feature",
  "properties": {
    "iso:country":"GB",
    "sg:address":"Old Court House, Clark Street",
    "sg:city":"Morecambe",
    "sg:classifiers":[
        {
            "category":"Real Estate",
            "subcategory":"Real Estate Agent",
            "type":"Services"
        }
    ],
    "sg:phone":"+44 1524 410727",
    "sg:postcode":"LA4 5HR",
    "sg:province":"Lancashire",
    "wof:name":"Crescent Arcade Properties (Morecambe) Ltd.",
    "wof:placetype":"venue"
},
  "geometry": {"coordinates":[-2.8607189655,54.0750198364],"type":"Point"}
}