{
  "type": "Feature",
  "properties": {
    "iso:country":"GB",
    "sg:address":"42 The Warren, Chartridge",
    "sg:city":"Chesham",
    "sg:classifiers":[
        {
            "category":"Home & Garden",
            "subcategory":"Carpets & Floor Coverings",
            "type":"Retail Goods"
        }
    ],
    "sg:phone":"+44 1494 774737",
    "sg:postcode":"HP5 2RY",
    "sg:province":"Buckinghamshire",
    "sg:tags":[
        "cleaner",
        "upholstery"
    ],
    "wof:name":"Cyvic Carpet & Upholstery Cleaners",
    "wof:placetype":"venue"
},
  "geometry": {"coordinates":[-0.635685,51.71838],"type":"Point"}
}