{
  "type": "Feature",
  "properties": {
    "addr:full":"Sussex Lodge, Station Road Taunton Somerset TA1 1NS",
    "addr:postcode":"ta1 1ns",
    "addr:street":"Station Road",
    "iso:country":"GB",
    "sg:address":"Sussex Lodge, Station Road",
    "sg:city":"Taunton",
    "sg:classifiers":[
        {
            "category":"Professional",
            "subcategory":"Lawyer & Legal Services",
            "type":"Services"
        }
    ],
    "sg:phone":"+44 1823 282235",
    "sg:postcode":"TA1 1NS",
    "sg:province":"Somerset",
    "sg:tags":[
        "advice",
        "counselling"
    ],
    "wof:name":"Taunton & District Citizens Advice Bureau",
    "wof:placetype":"venue"
},
  "geometry": {"coordinates":[-3.110699,51.01049],"type":"Point"}
}