{
  "type": "Feature",
  "properties": {
    "addr:full":"10 Fraser Street Grimsby Lincolnshire DN32 8AQ",
    "addr:housenumber":"10",
    "addr:postcode":"dn32 8aq",
    "addr:street":"Fraser Street",
    "iso:country":"GB",
    "sg:address":"10 Fraser Street",
    "sg:city":"Grimsby",
    "sg:classifiers":[
        {
            "category":"Retail",
            "subcategory":"Auto Repair",
            "type":"Services"
        }
    ],
    "sg:phone":"+44 1472 358470",
    "sg:postcode":"DN32 8AQ",
    "sg:province":"Lincolnshire",
    "sg:tags":[
        "modification",
        "garage"
    ],
    "wof:name":"T K Garnett Engineering Ltd.",
    "wof:placetype":"venue"
},
  "geometry": {"coordinates":[-0.069095999,53.566192627],"type":"Point"}
}