{
  "type": "Feature",
  "properties": {
    "iso:country":"GB",
    "sg:address":"47 Central St",
    "sg:city":"Clerkenwell",
    "sg:classifiers":[
        {
            "category":"Communications",
            "type":"Services"
        }
    ],
    "sg:phone":"+44 20 7250 0904",
    "sg:postcode":"EC1V 8AB",
    "sg:province":"Greater London",
    "sg:tags":[
        "broadcasting"
    ],
    "wof:name":"Janus Scerek",
    "wof:placetype":"venue"
},
  "geometry": {"coordinates":[-0.096769,51.527081],"type":"Point"}
}