{
  "type": "Feature",
  "properties": {
    "addr:full":"5 Richmond Street Manchester Greater Manchester M1 3HF",
    "addr:housenumber":"5",
    "addr:postcode":"m1 3hf",
    "addr:street":"Richmond Street",
    "iso:country":"GB",
    "sg:address":"5 Richmond Street",
    "sg:city":"Manchester",
    "sg:classifiers":[
        {
            "category":"Communications",
            "subcategory":"Film & Video Production",
            "type":"Services"
        }
    ],
    "sg:postcode":"M1 3HF",
    "sg:province":"Greater Manchester",
    "sg:tags":[
        "illustrator",
        "artist"
    ],
    "wof:name":"Profile Studios",
    "wof:placetype":"venue"
},
  "geometry": {"coordinates":[-2.23533,53.478184],"type":"Point"}
}