{
  "type": "Feature",
  "properties": {
    "addr:full":"25 Wood End Gardens Northolt Greater London UB5 4QJ",
    "addr:housenumber":"25",
    "addr:postcode":"ub5 4qj",
    "addr:street":"Wood End Gardens",
    "iso:country":"GB",
    "sg:address":"25 Wood End Gardens",
    "sg:city":"Northolt",
    "sg:classifiers":[
        {
            "category":"Professional",
            "subcategory":"Printing & Photocopies",
            "type":"Services"
        }
    ],
    "sg:phone":"+44 20 8422 8749",
    "sg:postcode":"UB5 4QJ",
    "sg:province":"Greater London",
    "sg:tags":[
        "printer"
    ],
    "wof:name":"Mister Print",
    "wof:placetype":"venue"
},
  "geometry": {"coordinates":[-0.3476350009,51.5573654175],"type":"Point"}
}