{
  "type": "Feature",
  "properties": {
    "addr:full":"2 Moorfield Road Orpington Kent BR6 0HQ",
    "addr:housenumber":"2",
    "addr:postcode":"br6 0hq",
    "addr:street":"Moorfield Road",
    "iso:country":"GB",
    "sg:address":"2 Moorfield Road",
    "sg:city":"Orpington",
    "sg:classifiers":[
        {
            "category":"Professional",
            "subcategory":"Detective & Security Services",
            "type":"Services"
        }
    ],
    "sg:postcode":"BR6 0HQ",
    "sg:province":"Kent",
    "wof:name":"Coseam",
    "wof:placetype":"venue"
},
  "geometry": {"coordinates":[0.1029200032,51.3798370361],"type":"Point"}
}