{
  "type": "Feature",
  "properties": {
    "addr:full":"Faringdon Road, Frilford Heath Abingdon Oxfordshire OX13 6QJ",
    "addr:postcode":"ox13 6qj",
    "addr:street":"Faringdon Road",
    "iso:country":"GB",
    "sg:address":"Faringdon Road, Frilford Heath",
    "sg:city":"Abingdon",
    "sg:classifiers":[
        {
            "category":"Travel",
            "subcategory":"Hotels & Motels",
            "type":"Entertainment"
        }
    ],
    "sg:phone":"+44 1865 390830",
    "sg:postcode":"OX13 6QJ",
    "sg:province":"Oxfordshire",
    "wof:name":"The Dog House Hotel",
    "wof:placetype":"venue"
},
  "geometry": {"coordinates":[-1.3213939667,51.6834411621],"type":"Point"}
}