{
  "type": "Feature",
  "properties": {
    "addr:full":"3b The Triangle, Langdon Hills Basildon Essex SS16 6HF",
    "addr:housenumber":"3b",
    "addr:postcode":"ss16 6hf",
    "addr:street":"The Triangle",
    "iso:country":"GB",
    "sg:address":"3b The Triangle, Langdon Hills",
    "sg:city":"Basildon",
    "sg:classifiers":[
        {
            "category":"Food & Beverages",
            "subcategory":"Liquor & Beverages",
            "type":"Retail Goods"
        }
    ],
    "sg:postcode":"SS16 6HF",
    "sg:province":"Essex",
    "sg:tags":[
        "beer",
        "spirit",
        "wines"
    ],
    "wof:name":"Pints & Litres",
    "wof:placetype":"venue"
},
  "geometry": {"coordinates":[0.4219810069,51.561882019],"type":"Point"}
}