{
  "type": "Feature",
  "properties": {
    "iso:country":"GB",
    "sg:address":"45 Anchor Road, Kingswood",
    "sg:city":"Bristol",
    "sg:classifiers":[
        {
            "category":"Home & Garden",
            "subcategory":"Carpets & Floor Coverings",
            "type":"Retail Goods"
        }
    ],
    "sg:postcode":"BS15 4RE",
    "sg:province":"City of Bristol",
    "sg:tags":[
        "carpets",
        "rug",
        "matting"
    ],
    "wof:name":"R J Hopewell",
    "wof:placetype":"venue"
},
  "geometry": {"coordinates":[-2.488223,51.469597],"type":"Point"}
}