{
  "type": "Feature",
  "properties": {
    "addr:full":"68 Union St Oldham Lancashire OL1 1DJ",
    "addr:housenumber":"68",
    "addr:postcode":"ol1 1dj",
    "addr:street":"Union St",
    "iso:country":"GB",
    "sg:address":"68 Union St",
    "sg:city":"Oldham",
    "sg:classifiers":[
        {
            "category":"Organizations",
            "subcategory":"Non-profit Organization",
            "type":"Services"
        }
    ],
    "sg:phone":"+44 161 620 6288",
    "sg:postcode":"OL1 1DJ",
    "sg:province":"Lancashire",
    "sg:tags":[
        "organisation",
        "voluntary",
        "charity"
    ],
    "wof:name":"Afro Carribean Project",
    "wof:placetype":"venue"
},
  "geometry": {"coordinates":[-2.1117789745,53.5402641296],"type":"Point"}
}