{
  "type": "Feature",
  "properties": {
    "addr:full":"36 A Market Jew Street Penzance Cornwall TR18 2HP",
    "addr:housenumber":"36 a",
    "addr:postcode":"tr18 2hp",
    "addr:street":"Market Jew Street",
    "iso:country":"GB",
    "sg:address":"36 A Market Jew Street",
    "sg:city":"Penzance",
    "sg:classifiers":[
        {
            "category":"Professional",
            "subcategory":"Art Services",
            "type":"Services"
        }
    ],
    "sg:phone":"+44 1736 330887",
    "sg:postcode":"TR18 2HP",
    "sg:province":"Cornwall",
    "sg:tags":[
        "framing"
    ],
    "wof:name":"Moonshine Studios",
    "wof:placetype":"venue"
},
  "geometry": {"coordinates":[-5.5342850685,50.1207542419],"type":"Point"}
}