{
  "type": "Feature",
  "properties": {
    "addr:full":"The Anchorage Bruichladdich Argyll and Bute PA49 7UN",
    "addr:postcode":"pa49 7un",
    "iso:country":"GB",
    "sg:address":"The Anchorage",
    "sg:city":"Bruichladdich",
    "sg:classifiers":[
        {
            "category":"Health Services",
            "subcategory":"Doctor",
            "type":"Services"
        }
    ],
    "sg:postcode":"PA49 7UN",
    "sg:province":"Argyll and Bute",
    "sg:tags":[
        "practitioners"
    ],
    "wof:name":"Argyll & Clyde Health Board",
    "wof:placetype":"venue"
},
  "geometry": {"coordinates":[-6.361869,55.76601],"type":"Point"}
}