{
  "type": "Feature",
  "properties": {
    "addr:full":"Premier House, 3a High St Harpenden Hertfordshire AL5 2RT",
    "addr:housenumber":"3a",
    "addr:postcode":"al5 2rt",
    "addr:street":"High St",
    "iso:country":"GB",
    "sg:address":"Premier House, 3a High St",
    "sg:city":"Harpenden",
    "sg:classifiers":[
        {
            "category":"Shopping",
            "subcategory":"Computers & Home Electronics",
            "type":"Retail Goods"
        }
    ],
    "sg:phone":"+44 1582 623666",
    "sg:postcode":"AL5 2RT",
    "sg:province":"Hertfordshire",
    "wof:name":"Direct Source",
    "wof:placetype":"venue"
},
  "geometry": {"coordinates":[-0.354896,51.814632],"type":"Point"}
}