{
  "type": "Feature",
  "properties": {
    "iso:country":"GB",
    "sg:address":"Unit 3 Station Way Industrial Estate, Tolleshunt Darcy",
    "sg:city":"Maldon",
    "sg:classifiers":[
        {
            "category":"Professional",
            "subcategory":"Engineering",
            "type":"Services"
        }
    ],
    "sg:phone":"+44 1621 868848",
    "sg:postcode":"CM9 8TY",
    "sg:province":"Essex",
    "sg:tags":[
        "precision",
        "engineer"
    ],
    "wof:name":"Wickham Engineering",
    "wof:placetype":"venue"
},
  "geometry": {"coordinates":[0.83357,51.761219],"type":"Point"}
}