{
  "type": "Feature",
  "properties": {
    "addr:full":"Orchardside, Frognall, Deeping St James Peterborough Cambridgeshire PE6 8RP",
    "addr:postcode":"pe6 8rp",
    "addr:street":"St James Peterborough",
    "iso:country":"GB",
    "sg:address":"Orchardside, Frognall, Deeping St James",
    "sg:city":"Peterborough",
    "sg:classifiers":[
        {
            "category":"Building & Trades",
            "subcategory":"Construction",
            "type":"Services"
        },
        {
            "category":"Government",
            "subcategory":"Customs House",
            "type":"Public Place"
        }
    ],
    "sg:phone":"+44 1778 342601",
    "sg:postcode":"PE6 8RP",
    "sg:province":"Cambridgeshire",
    "sg:tags":[
        "fork",
        "plant",
        "lift",
        "truck",
        "crushing"
    ],
    "wof:name":"Anglo Fork Lifts",
    "wof:placetype":"venue"
},
  "geometry": {"coordinates":[-0.299614,52.671082],"type":"Point"}
}