{
  "type": "Feature",
  "properties": {
    "iso:country":"GB",
    "sg:address":"50-52 Valley Forge, Washington Village",
    "sg:city":"Washington",
    "sg:classifiers":[
        {
            "category":"Cinema",
            "subcategory":"Movie Rental",
            "type":"Entertainment"
        }
    ],
    "sg:phone":"+44 191 417 7166",
    "sg:postcode":"NE38 7JL",
    "sg:province":"Durham",
    "sg:tags":[
        "video",
        "library"
    ],
    "wof:name":"Zodiac Video",
    "wof:placetype":"venue"
},
  "geometry": {"coordinates":[-1.519891,54.904289],"type":"Point"}
}