{
  "type": "Feature",
  "properties": {
    "iso:country":"GB",
    "sg:address":"39 Bath Street",
    "sg:city":"Southport",
    "sg:classifiers":[
        {
            "category":"Travel",
            "subcategory":"Hotels & Motels",
            "type":"Entertainment"
        }
    ],
    "sg:phone":"+44 1704 530707",
    "sg:postcode":"PR9 0DP",
    "sg:province":"Lancashire",
    "sg:website":"http://www.thewarwicksouthport.co.uk",
    "wof:name":"Warwick Hotel",
    "wof:placetype":"venue"
},
  "geometry": {"coordinates":[-3.004431,53.650803],"type":"Point"}
}