{
  "type": "Feature",
  "properties": {
    "addr:full":"Vivienda, Northgate Lane, Gate Helmsley York East Riding of Yorkshire YO41 1NN",
    "addr:postcode":"yo41 1nn",
    "addr:street":"Northgate Lane",
    "iso:country":"GB",
    "sg:address":"Vivienda, Northgate Lane, Gate Helmsley",
    "sg:city":"York",
    "sg:classifiers":[
        {
            "category":"Farming",
            "subcategory":"Livestock Farm",
            "type":"Manufacturing & Wholesale Goods"
        }
    ],
    "sg:phone":"+44 1759 372197",
    "sg:postcode":"YO41 1NN",
    "sg:province":"East Riding of Yorkshire",
    "sg:tags":[
        "others"
    ],
    "wof:name":"Michael Musson",
    "wof:placetype":"venue"
},
  "geometry": {"coordinates":[-0.9444540143,53.9896087646],"type":"Point"}
}