{
  "type": "Feature",
  "properties": {
    "iso:country":"GB",
    "sg:address":"17 Parson Lane",
    "sg:city":"Bury",
    "sg:classifiers":[
        {
            "category":"Professional",
            "subcategory":"Computer Services",
            "type":"Services"
        }
    ],
    "sg:phone":"+44 161 761 2136",
    "sg:postcode":"BL9 0LY",
    "sg:province":"Lancashire",
    "sg:tags":[
        "information"
    ],
    "wof:name":"Young Persons Advisory Service",
    "wof:placetype":"venue"
},
  "geometry": {"coordinates":[-2.295142889,53.5951538086],"type":"Point"}
}