{
  "type": "Feature",
  "properties": {
    "addr:full":"111 Boroughbridge Rd York East Riding of Yorkshire YO2 6AA",
    "addr:housenumber":"111",
    "addr:postcode":"yo2 6aa",
    "addr:street":"Boroughbridge Rd",
    "iso:country":"GB",
    "sg:address":"111 Boroughbridge Rd",
    "sg:city":"York",
    "sg:classifiers":[
        {
            "category":"Retail",
            "subcategory":"Driving School",
            "type":"Services"
        }
    ],
    "sg:phone":"+44 1904 781211",
    "sg:postcode":"YO2 6AA",
    "sg:province":"East Riding of Yorkshire",
    "wof:name":"Bailey's Motoring School",
    "wof:placetype":"venue"
},
  "geometry": {"coordinates":[-1.1251130104,53.9657707214],"type":"Point"}
}