{
  "type": "Feature",
  "properties": {
    "iso:country":"GB",
    "sg:address":"13 Cinnamon Row, Plantation Wharf",
    "sg:city":"Battersea",
    "sg:classifiers":[
        {
            "category":"Professional",
            "subcategory":"Art Services",
            "type":"Services"
        }
    ],
    "sg:phone":"+44 20 7924 4447",
    "sg:postcode":"SW11 3TW",
    "sg:province":"Greater London",
    "sg:tags":[
        "photographer"
    ],
    "wof:name":"Michael Joseph Pictures Ltd",
    "wof:placetype":"venue"
},
  "geometry": {"coordinates":[-0.180774,51.467091],"type":"Point"}
}