{
  "type": "Feature",
  "properties": {
    "addr:full":"50 Tullis Street Glasgow Glasgow City G40 1HW",
    "addr:housenumber":"50",
    "addr:postcode":"g40 1hw",
    "addr:street":"Tullis Street",
    "iso:country":"GB",
    "sg:address":"50 Tullis Street",
    "sg:city":"Glasgow",
    "sg:classifiers":[
        {
            "category":"Organizations",
            "subcategory":"Community Association",
            "type":"Services"
        },
        {
            "category":"Organizations",
            "subcategory":"Membership Organization",
            "type":"Services"
        }
    ],
    "sg:phone":"+44 141 554 4248",
    "sg:postcode":"G40 1HW",
    "sg:province":"Glasgow City",
    "sg:tags":[
        "club",
        "social"
    ],
    "wof:name":"LOYAL ORANGE LODGE",
    "wof:placetype":"venue"
},
  "geometry": {"coordinates":[-4.229065,55.846947],"type":"Point"}
}