{
  "type": "Feature",
  "properties": {
    "iso:country":"GB",
    "sg:address":"2 Sherwins Cotts, Abbots Wick Lane, Great Wigborough",
    "sg:city":"Colchester",
    "sg:classifiers":[
        {
            "category":"Professional",
            "type":"Services"
        }
    ],
    "sg:postcode":"CO5 7RT",
    "sg:province":"Essex",
    "sg:tags":[
        "entertainer"
    ],
    "wof:name":"Sunset Entertainments Agency",
    "wof:placetype":"venue"
},
  "geometry": {"coordinates":[0.8532969952,51.7990722656],"type":"Point"}
}