{
  "type": "Feature",
  "properties": {
    "iso:country":"GB",
    "sg:address":"92 Heathfield Rd",
    "sg:city":"Redditch",
    "sg:classifiers":[
        {
            "category":"Professional",
            "subcategory":"Employment Agencies",
            "type":"Services"
        }
    ],
    "sg:postcode":"B97 5RD",
    "sg:province":"Warwickshire",
    "sg:tags":[
        "recr",
        "consultant",
        "hire",
        "driver"
    ],
    "wof:name":"Hogg,Douglas,",
    "wof:placetype":"venue"
},
  "geometry": {"coordinates":[-1.970511,52.295891],"type":"Point"}
}