{
  "type": "Feature",
  "properties": {
    "addr:full":"60 Bridge Street, Garstang Preston Lancashire PR3 1YB",
    "addr:housenumber":"60",
    "addr:postcode":"pr3 1yb",
    "addr:street":"Bridge Street",
    "iso:country":"GB",
    "sg:address":"60 Bridge Street, Garstang",
    "sg:city":"Preston",
    "sg:classifiers":[
        {
            "category":"Manufacturing",
            "subcategory":"Pet Food",
            "type":"Manufacturing & Wholesale Goods"
        },
        {
            "category":"Shopping",
            "subcategory":"Pets & Pet Supplies",
            "type":"Retail Goods"
        }
    ],
    "sg:phone":"+44 1995 601355",
    "sg:postcode":"PR3 1YB",
    "sg:province":"Lancashire",
    "sg:tags":[
        "feed",
        "animal"
    ],
    "wof:name":"Dawngreen Ltd",
    "wof:placetype":"venue"
},
  "geometry": {"coordinates":[-2.772421,53.898026],"type":"Point"}
}