{
  "type": "Feature",
  "properties": {
    "addr:full":"Westbank Road, Macmerry Tranent East Lothian EH33 1PJ",
    "addr:postcode":"eh33 1pj",
    "addr:street":"Westbank Road",
    "iso:country":"GB",
    "sg:address":"Westbank Road, Macmerry",
    "sg:city":"Tranent",
    "sg:classifiers":[
        {
            "category":"Wholesale",
            "subcategory":"Fruits & Vegetables",
            "type":"Manufacturing & Wholesale Goods"
        }
    ],
    "sg:postcode":"EH33 1PJ",
    "sg:province":"East Lothian",
    "wof:name":"R B G Fruits",
    "wof:placetype":"venue"
},
  "geometry": {"coordinates":[-2.953758955,55.9445152283],"type":"Point"}
}