{
  "type": "Feature",
  "properties": {
    "iso:country":"GB",
    "sg:address":"Bayton Rd, Exhall",
    "sg:city":"Coventry",
    "sg:classifiers":[
        {
            "category":"Home & Garden",
            "subcategory":"Building Materials",
            "type":"Retail Goods"
        }
    ],
    "sg:phone":"+44 24 7636 0808",
    "sg:postcode":"CV7 9EJ",
    "sg:province":"Warwickshire",
    "sg:tags":[
        "ready",
        "mixed",
        "concrete"
    ],
    "wof:name":"Warwickshire Mini-mix",
    "wof:placetype":"venue"
},
  "geometry": {"coordinates":[-1.471339,52.467522],"type":"Point"}
}