{
  "type": "Feature",
  "properties": {
    "iso:country":"GB",
    "sg:address":"3 Ye Corner",
    "sg:city":"Watford",
    "sg:classifiers":[
        {
            "category":"Personal",
            "subcategory":"Tattoo Parlor",
            "type":"Services"
        }
    ],
    "sg:phone":"+44 1923 248090",
    "sg:postcode":"WD19 4BS",
    "sg:province":"Hertfordshire",
    "sg:tags":[
        "tattooing",
        "piercing"
    ],
    "wof:name":"Little Daves Tattoo Studio",
    "wof:placetype":"venue"
},
  "geometry": {"coordinates":[-0.382340014,51.6466217041],"type":"Point"}
}