{
  "type": "Feature",
  "properties": {
    "addr:full":"24 Cheyne Row London Greater London SW3 5HL",
    "addr:housenumber":"24",
    "addr:postcode":"sw3 5hl",
    "addr:street":"Cheyne Row",
    "iso:country":"GB",
    "sg:address":"24 Cheyne Row",
    "sg:city":"London",
    "sg:classifiers":[
        {
            "category":"Museum",
            "subcategory":"Art Museum",
            "type":"Entertainment"
        }
    ],
    "sg:phone":"+44 20 7352 7087",
    "sg:postcode":"SW3 5HL",
    "sg:province":"Greater London",
    "sg:tags":[
        "gallery"
    ],
    "wof:name":"The National Trust",
    "wof:placetype":"venue"
},
  "geometry": {"coordinates":[-0.1698060036,51.4842033386],"type":"Point"}
}