{
  "type": "Feature",
  "properties": {
    "addr:full":"5 Station Buildings, Birmingham Road, Water Orton Birmingham Warwickshire B46 1SR",
    "addr:housenumber":"5",
    "addr:postcode":"b46 1sr",
    "addr:street":"Station Buildings Birmingham Road",
    "iso:country":"GB",
    "sg:address":"5 Station Buildings, Birmingham Road, Water Orton",
    "sg:city":"Birmingham",
    "sg:classifiers":[
        {
            "category":"Health Services",
            "subcategory":"Dentist",
            "type":"Services"
        }
    ],
    "sg:phone":"+44 121 749 4980",
    "sg:postcode":"B46 1SR",
    "sg:province":"Warwickshire",
    "wof:name":"Griffin & Griffin",
    "wof:placetype":"venue"
},
  "geometry": {"coordinates":[-1.737806,52.517654],"type":"Point"}
}