{
  "type": "Feature",
  "properties": {
    "iso:country":"GB",
    "sg:address":"143 Grimsby Road",
    "sg:city":"Cleethorpes",
    "sg:classifiers":[
        {
            "category":"Shopping",
            "subcategory":"News",
            "type":"Retail Goods"
        }
    ],
    "sg:phone":"+44 1472 691281",
    "sg:postcode":"DN35 7DG",
    "sg:province":"Lincolnshire",
    "sg:tags":[
        "newsagent"
    ],
    "wof:name":"Doddy's Newsagents",
    "wof:placetype":"venue"
},
  "geometry": {"coordinates":[-0.049585,53.569614],"type":"Point"}
}