{
  "type": "Feature",
  "properties": {
    "addr:full":"74 Cavendish Street Barrow-in-furness Cumbria LA14 1PZ",
    "addr:housenumber":"74",
    "addr:postcode":"la14 1pz",
    "addr:street":"Cavendish Street",
    "iso:country":"GB",
    "sg:address":"74 Cavendish Street",
    "sg:city":"Barrow-in-furness",
    "sg:classifiers":[
        {
            "category":"Professional",
            "subcategory":"Printing & Photocopies",
            "type":"Services"
        }
    ],
    "sg:phone":"+44 1229 834011",
    "sg:postcode":"LA14 1PZ",
    "sg:province":"Cumbria",
    "sg:tags":[
        "rubber",
        "stamp"
    ],
    "wof:name":"The Stamp Store",
    "wof:placetype":"venue"
},
  "geometry": {"coordinates":[-3.2271559238,54.1135292053],"type":"Point"}
}