{
  "type": "Feature",
  "properties": {
    "addr:full":"Unit 11 The Workshops, Crawford Street Newport Newport NP19 7AY",
    "addr:housenumber":"unit 11",
    "addr:postcode":"np19 7ay",
    "addr:street":"The Workshops Crawford Street",
    "iso:country":"GB",
    "sg:address":"Unit 11 The Workshops, Crawford Street",
    "sg:city":"Newport",
    "sg:classifiers":[
        {
            "category":"Home & Garden",
            "subcategory":"Building Materials",
            "type":"Retail Goods"
        }
    ],
    "sg:phone":"+44 1633 213045",
    "sg:postcode":"NP19 7AY",
    "sg:province":"Newport",
    "sg:tags":[
        "ironwork",
        "wrought",
        "diy"
    ],
    "wof:name":"T & S Wrought Iron",
    "wof:placetype":"venue"
},
  "geometry": {"coordinates":[-2.9882569313,51.5910491943],"type":"Point"}
}