{
  "type": "Feature",
  "properties": {
    "iso:country":"GB",
    "sg:address":"Fursdon Farm, Frithelstock Stone",
    "sg:city":"Torrington",
    "sg:classifiers":[
        {
            "category":"Transit Center",
            "subcategory":"Passenger",
            "type":"Transportation"
        },
        {
            "category":"Retail",
            "subcategory":"Pet Boarding",
            "type":"Services"
        }
    ],
    "sg:phone":"+44 1805 623501",
    "sg:postcode":"EX38 8LA",
    "sg:province":"Devon",
    "sg:tags":[
        "kennel",
        "catteries"
    ],
    "wof:name":"Fursdon Farm Kennel & Cattery",
    "wof:placetype":"venue"
},
  "geometry": {"coordinates":[-4.142255,50.953152],"type":"Point"}
}