{
  "type": "Feature",
  "properties": {
    "addr:full":"9 Sybron Way Crowborough East Sussex TN6 3DZ",
    "addr:housenumber":"9",
    "addr:postcode":"tn6 3dz",
    "addr:street":"Sybron Way",
    "iso:country":"GB",
    "sg:address":"9 Sybron Way",
    "sg:city":"Crowborough",
    "sg:classifiers":[
        {
            "category":"Manufacturing",
            "subcategory":"Glass & Minerals",
            "type":"Manufacturing & Wholesale Goods"
        }
    ],
    "sg:postcode":"TN6 3DZ",
    "sg:province":"East Sussex",
    "sg:tags":[
        "mnfrs",
        "fibre"
    ],
    "wof:name":"Carroll McManus Ltd.",
    "wof:placetype":"venue"
},
  "geometry": {"coordinates":[0.1910089999,51.0463981628],"type":"Point"}
}