{
  "type": "Feature",
  "properties": {
    "iso:country":"GB",
    "sg:address":"13 Henderson Road",
    "sg:city":"Inverness",
    "sg:classifiers":[
        {
            "category":"Communications",
            "subcategory":"Newspaper",
            "type":"Services"
        }
    ],
    "sg:phone":"+44 1463 246575",
    "sg:postcode":"IV1 1SP",
    "sg:province":"Highland",
    "sg:tags":[
        "magazine"
    ],
    "wof:name":"The Moray & Nairn Newspaper Co. Ltd.",
    "wof:placetype":"venue"
},
  "geometry": {"coordinates":[-4.223999,57.488132],"type":"Point"}
}