{
  "type": "Feature",
  "properties": {
    "addr:full":"Lower East End, Harlington Dunstable Bedfordshire LU5 6LJ",
    "addr:postcode":"lu5 6lj",
    "addr:street":"Lower",
    "iso:country":"GB",
    "sg:address":"Lower East End, Harlington",
    "sg:city":"Dunstable",
    "sg:classifiers":[
        {
            "category":"Transit Center",
            "subcategory":"Passenger",
            "type":"Transportation"
        }
    ],
    "sg:phone":"+44 1525 872951",
    "sg:postcode":"LU5 6LJ",
    "sg:province":"Bedfordshire",
    "sg:tags":[
        "boarding",
        "kennel",
        "catteries"
    ],
    "wof:name":"The Hound Hotel",
    "wof:placetype":"venue"
},
  "geometry": {"coordinates":[-0.4947850108,51.9624176025],"type":"Point"}
}