{
  "type": "Feature",
  "properties": {
    "iso:country":"GB",
    "sg:address":"Copperworks Road",
    "sg:city":"Llanelli",
    "sg:classifiers":[
        {
            "category":"Shopping",
            "subcategory":"Baby Store",
            "type":"Retail Goods"
        }
    ],
    "sg:phone":"+44 1554 753434",
    "sg:postcode":"SA15 2NH",
    "sg:province":"Carmarthenshire",
    "sg:tags":[
        "babywear",
        "childrens"
    ],
    "wof:name":"Crazy Maisies",
    "wof:placetype":"venue"
},
  "geometry": {"coordinates":[-4.159504,51.67297],"type":"Point"}
}