{
  "type": "Feature",
  "properties": {
    "iso:country":"GB",
    "sg:address":"Unit A, Hoyle St",
    "sg:city":"Warrington",
    "sg:classifiers":[
        {
            "category":"Professional",
            "subcategory":"Testing Lab",
            "type":"Services"
        }
    ],
    "sg:postcode":"WA5 0LW",
    "sg:province":"Cheshire",
    "sg:tags":[
        "mot"
    ],
    "wof:name":"One Stop Auto Centre",
    "wof:placetype":"venue"
},
  "geometry": {"coordinates":[-2.60046,53.398491],"type":"Point"}
}