{
  "type": "Feature",
  "properties": {
    "addr:full":"Head Office, 99 Waverley Rd St Albans Hertfordshire AL3 5TL",
    "addr:housenumber":"99",
    "addr:postcode":"al3 5tl",
    "addr:street":"Waverley Rd",
    "iso:country":"GB",
    "sg:address":"Head Office, 99 Waverley Rd",
    "sg:city":"St Albans",
    "sg:classifiers":[
        {
            "category":"Government",
            "subcategory":"Office",
            "type":"Public Place"
        }
    ],
    "sg:postcode":"AL3 5TL",
    "sg:province":"Hertfordshire",
    "sg:tags":[
        "project",
        "gov",
        "community"
    ],
    "wof:name":"West Herts Community Health N H S Trust",
    "wof:placetype":"venue"
},
  "geometry": {"coordinates":[-0.3452799916,51.7627487183],"type":"Point"}
}