{
  "type": "Feature",
  "properties": {
    "iso:country":"GB",
    "sg:address":"125/127 Whitehill Road",
    "sg:city":"Gravesend",
    "sg:classifiers":[
        {
            "category":"Retail",
            "subcategory":"Laundry & Dry Cleaning",
            "type":"Services"
        }
    ],
    "sg:postcode":"DA12 5PN",
    "sg:province":"Kent",
    "sg:tags":[
        "alteration"
    ],
    "wof:name":"Shaws Laundries (Holdings) Ltd.",
    "wof:placetype":"venue"
},
  "geometry": {"coordinates":[0.377951,51.42651],"type":"Point"}
}