{
  "type": "Feature",
  "properties": {
    "iso:country":"GB",
    "sg:address":"100 Ashey Road",
    "sg:city":"Ryde",
    "sg:classifiers":[
        {
            "category":"Utilities",
            "subcategory":"Fuel Oil & Lpg",
            "type":"Services"
        }
    ],
    "sg:postcode":"PO33 2UZ",
    "sg:province":"Isle of Wight",
    "sg:tags":[
        "coal",
        "smokeless"
    ],
    "wof:name":"W Wright",
    "wof:placetype":"venue"
},
  "geometry": {"coordinates":[-1.166421,50.716518],"type":"Point"}
}