{
  "type": "Feature",
  "properties": {
    "addr:full":"Sundrum Place Kilwinning East Ayrshire KA13 6SE",
    "addr:postcode":"ka13 6se",
    "addr:street":"Place Kilwinning East",
    "iso:country":"GB",
    "sg:address":"Sundrum Place",
    "sg:city":"Kilwinning",
    "sg:classifiers":[
        {
            "category":"Education",
            "subcategory":"School",
            "type":"Public Place"
        }
    ],
    "sg:phone":"+44 1294 552807",
    "sg:postcode":"KA13 6SE",
    "sg:province":"East Ayrshire",
    "sg:tags":[
        "local",
        "authority"
    ],
    "wof:name":"Pennyburn Primary School",
    "wof:placetype":"venue"
},
  "geometry": {"coordinates":[-4.712604,55.650459],"type":"Point"}
}