{
  "type": "Feature",
  "properties": {
    "addr:full":"24 Middleton Road, Royton Oldham Lancashire OL2 5PA",
    "addr:housenumber":"24",
    "addr:postcode":"ol2 5pa",
    "addr:street":"Middleton Road",
    "iso:country":"GB",
    "sg:address":"24 Middleton Road, Royton",
    "sg:city":"Oldham",
    "sg:classifiers":[
        {
            "category":"Food & Beverages",
            "subcategory":"Liquor & Beverages",
            "type":"Retail Goods"
        }
    ],
    "sg:phone":"+44 161 633 5178",
    "sg:postcode":"OL2 5PA",
    "sg:province":"Lancashire",
    "sg:tags":[
        "beer",
        "spirit",
        "wines"
    ],
    "wof:name":"Carol's",
    "wof:placetype":"venue"
},
  "geometry": {"coordinates":[-2.123097,53.564938],"type":"Point"}
}