{
  "type": "Feature",
  "properties": {
    "iso:country":"GB",
    "sg:address":"26 Eastwood Avenue, Giffnock",
    "sg:city":"Glasgow",
    "sg:classifiers":[
        {
            "category":"Professional",
            "type":"Services"
        }
    ],
    "sg:phone":"+44 141 638 3129",
    "sg:postcode":"G46 6LR",
    "sg:province":"East Renfrewshire",
    "sg:tags":[
        "caterer"
    ],
    "wof:name":"Gill Hastie",
    "wof:placetype":"venue"
},
  "geometry": {"coordinates":[-4.2905788422,55.8025588989],"type":"Point"}
}