{
  "type": "Feature",
  "properties": {
    "addr:full":"Tudor Road Broadstone Dorset BH18 8AA",
    "addr:postcode":"bh18 8aa",
    "addr:street":"Tudor Road",
    "iso:country":"GB",
    "sg:address":"Tudor Road",
    "sg:city":"Broadstone",
    "sg:classifiers":[
        {
            "category":"Education",
            "subcategory":"School",
            "type":"Public Place"
        }
    ],
    "sg:phone":"+44 1202 694376",
    "sg:postcode":"BH18 8AA",
    "sg:province":"Dorset",
    "sg:tags":[
        "local",
        "authority"
    ],
    "wof:name":"Broadstone First School",
    "wof:placetype":"venue"
},
  "geometry": {"coordinates":[-1.99357903,50.7630691528],"type":"Point"}
}