{
  "type": "Feature",
  "properties": {
    "addr:full":"10 Dyer Street Cirencester Gloucestershire GL7 2PF",
    "addr:housenumber":"10",
    "addr:postcode":"gl7 2pf",
    "addr:street":"Dyer Street",
    "iso:country":"GB",
    "sg:address":"10 Dyer Street",
    "sg:city":"Cirencester",
    "sg:classifiers":[
        {
            "category":"Shopping",
            "subcategory":"Jewelry",
            "type":"Retail Goods"
        },
        {
            "category":"Shopping",
            "subcategory":"Comic Books",
            "type":"Retail Goods"
        }
    ],
    "sg:phone":"+44 1285 653875",
    "sg:postcode":"GL7 2PF",
    "sg:province":"Gloucestershire",
    "sg:tags":[
        "jeweller",
        "sale",
        "jewellery"
    ],
    "wof:name":"Walter Bull & Son Cirencester Ltd",
    "wof:placetype":"venue"
},
  "geometry": {"coordinates":[-1.965172,51.716427],"type":"Point"}
}