{
  "type": "Feature",
  "properties": {
    "iso:country":"GB",
    "sg:address":"1-3 Ashfield Parade",
    "sg:city":"London",
    "sg:classifiers":[
        {
            "category":"Travel",
            "subcategory":"Travel Agent",
            "type":"Entertainment"
        }
    ],
    "sg:phone":"+44 20 8882 1777",
    "sg:postcode":"N14 5EH",
    "sg:province":"Greater London",
    "wof:name":"Libra Travel",
    "wof:placetype":"venue"
},
  "geometry": {"coordinates":[-0.128009,51.631454],"type":"Point"}
}