{
  "type": "Feature",
  "properties": {
    "addr:full":"2 Florence Wright Avenue Louth Lincolnshire LN11 8EJ",
    "addr:housenumber":"2",
    "addr:postcode":"ln11 8ej",
    "addr:street":"Florence Wright Avenue Louth",
    "iso:country":"GB",
    "sg:address":"2 Florence Wright Avenue",
    "sg:city":"Louth",
    "sg:classifiers":[
        {
            "category":"Retail",
            "subcategory":"Driving School",
            "type":"Services"
        }
    ],
    "sg:phone":"+44 1507 604159",
    "sg:postcode":"LN11 8EJ",
    "sg:province":"Lincolnshire",
    "wof:name":"Jeanette Wilkinson",
    "wof:placetype":"venue"
},
  "geometry": {"coordinates":[0.0082909996,53.3581466675],"type":"Point"}
}