{
  "type": "Feature",
  "properties": {
    "addr:full":"King Alfred Kingsway Hove East Sussex BN3 2WW",
    "addr:postcode":"bn3 2ww",
    "addr:street":"King;Kingsway",
    "iso:country":"GB",
    "sg:address":"King Alfred Kingsway",
    "sg:city":"Hove",
    "sg:classifiers":[
        {
            "category":"Sports & Exercise",
            "subcategory":"Gym",
            "type":"Entertainment"
        }
    ],
    "sg:phone":"+44 1273 206644",
    "sg:postcode":"BN3 2WW",
    "sg:province":"East Sussex",
    "sg:tags":[
        "fitness",
        "health",
        "centre"
    ],
    "wof:name":"Cheetah's Gym",
    "wof:placetype":"venue"
},
  "geometry": {"coordinates":[-0.171554,50.824715],"type":"Point"}
}