{
  "type": "Feature",
  "properties": {
    "addr:full":"7 Holmleigh, Haydon Wick Swindon Wiltshire SN25 1RH",
    "addr:housenumber":"7",
    "addr:postcode":"sn25 1rh",
    "addr:street":"Holmleigh",
    "iso:country":"GB",
    "sg:address":"7 Holmleigh, Haydon Wick",
    "sg:city":"Swindon",
    "sg:classifiers":[
        {
            "category":"Professional",
            "subcategory":"Management & Consulting",
            "type":"Services"
        },
        {
            "category":"Professional",
            "subcategory":"Employment Agencies",
            "type":"Services"
        }
    ],
    "sg:phone":"+44 1793 701038",
    "sg:postcode":"SN25 1RH",
    "sg:province":"Wiltshire",
    "sg:tags":[
        "consultant",
        "business"
    ],
    "wof:name":"William John Ponag",
    "wof:placetype":"venue"
},
  "geometry": {"coordinates":[-1.8140200377,51.5887184143],"type":"Point"}
}