{
  "type": "Feature",
  "properties": {
    "iso:country":"GB",
    "sg:address":"Suite 23, The Colliseum Centre, Watchmoor Pk",
    "sg:city":"Camberley",
    "sg:classifiers":[
        {
            "category":"Airport",
            "subcategory":"General Aviation",
            "type":"Transportation"
        }
    ],
    "sg:postcode":"GU15 3YL",
    "sg:province":"Berkshire",
    "wof:name":"Aeronautical Resources Ltd",
    "wof:placetype":"venue"
},
  "geometry": {"coordinates":[-0.73423,51.336216],"type":"Point"}
}