{
  "type": "Feature",
  "properties": {
    "addr:full":"Copper Beech House, The Grn, Little Addington Kettering Northamptonshire NN14 4BB",
    "addr:postcode":"nn14 4bb",
    "addr:street":"The Grn",
    "iso:country":"GB",
    "sg:address":"Copper Beech House, The Grn, Little Addington",
    "sg:city":"Kettering",
    "sg:classifiers":[
        {
            "category":"Building & Trades",
            "subcategory":"Construction",
            "type":"Services"
        }
    ],
    "sg:postcode":"NN14 4BB",
    "sg:province":"Northamptonshire",
    "sg:tags":[
        "builder"
    ],
    "wof:name":"Windsor Builders",
    "wof:placetype":"venue"
},
  "geometry": {"coordinates":[-0.5897089839,52.3546485901],"type":"Point"}
}