{
  "type": "Feature",
  "properties": {
    "iso:country":"GB",
    "sg:address":"348 Harrow Road",
    "sg:city":"London",
    "sg:classifiers":[
        {
            "category":"Personal",
            "subcategory":"Beauty Salon",
            "type":"Services"
        }
    ],
    "sg:phone":"+44 20 7289 4053",
    "sg:postcode":"W9 2HP",
    "sg:province":"Greater London",
    "sg:tags":[
        "unisex",
        "hairdresser"
    ],
    "wof:name":"Illusions",
    "wof:placetype":"venue"
},
  "geometry": {"coordinates":[-0.194609,51.522949],"type":"Point"}
}