{
  "type": "Feature",
  "properties": {
    "iso:country":"GB",
    "sg:address":"High Street, Wroot",
    "sg:city":"Doncaster",
    "sg:classifiers":[
        {
            "category":"Government",
            "subcategory":"Post Office",
            "type":"Public Place"
        }
    ],
    "sg:phone":"+44 1302 770383",
    "sg:postcode":"DN9 2BU",
    "sg:province":"Lincolnshire",
    "wof:name":"Wroot Post Office",
    "wof:placetype":"venue"
},
  "geometry": {"coordinates":[-0.8426349759,53.4899101257],"type":"Point"}
}