{
  "type": "Feature",
  "properties": {
    "iso:country":"GB",
    "sg:address":"Burrfields Road",
    "sg:city":"Portsmouth",
    "sg:classifiers":[
        {
            "category":"Travel",
            "subcategory":"Hotels & Motels",
            "type":"Entertainment"
        }
    ],
    "sg:phone":"+44 23 9265 0510",
    "sg:postcode":"PO3 5HH",
    "sg:province":"Hampshire",
    "sg:website":"http://www.innlodge.com",
    "wof:name":"Inn Lodge Portsmouth",
    "wof:placetype":"venue"
},
  "geometry": {"coordinates":[-1.064135,50.81702],"type":"Point"}
}