{
  "type": "Feature",
  "properties": {
    "iso:country":"GB",
    "sg:address":"Bryn Clwydgellifor",
    "sg:city":"Ruthin",
    "sg:classifiers":[
        {
            "category":"Freight",
            "type":"Transportation"
        }
    ],
    "sg:phone":"+44 1824 790365",
    "sg:postcode":"LL15 1SF",
    "sg:province":"Denbighshire",
    "sg:tags":[
        "haulage",
        "road"
    ],
    "wof:name":"Haulage Contractor",
    "wof:placetype":"venue"
},
  "geometry": {"coordinates":[-3.3045220375,53.1140174866],"type":"Point"}
}