{
  "type": "Feature",
  "properties": {
    "addr:full":"Ribbleton Av Preston Lancashire PR2 6RD",
    "addr:postcode":"pr2 6rd",
    "addr:street":"Ribbleton Av",
    "iso:country":"GB",
    "sg:address":"Ribbleton Av",
    "sg:city":"Preston",
    "sg:classifiers":[
        {
            "category":"Place Of Worship",
            "type":"Public Place"
        }
    ],
    "sg:phone":"+44 1772 792592",
    "sg:postcode":"PR2 6RD",
    "sg:province":"Lancashire",
    "wof:name":"Church of Jesus Christ of Latter Day Saints",
    "wof:placetype":"venue"
},
  "geometry": {"coordinates":[-2.6687889099,53.7689781189],"type":"Point"}
}