{
  "type": "Feature",
  "properties": {
    "addr:full":"104 College Rd Sandhurst Berkshire GU47 0RD",
    "addr:housenumber":"104",
    "addr:postcode":"gu47 0rd",
    "addr:street":"College Rd",
    "iso:country":"GB",
    "sg:address":"104 College Rd",
    "sg:city":"Sandhurst",
    "sg:classifiers":[
        {
            "category":"Building & Trades",
            "subcategory":"Construction",
            "type":"Services"
        }
    ],
    "sg:phone":"+44 1276 33418",
    "sg:postcode":"GU47 0RD",
    "sg:province":"Berkshire",
    "sg:tags":[
        "decorator",
        "painter"
    ],
    "wof:name":"B Sinden",
    "wof:placetype":"venue"
},
  "geometry": {"coordinates":[-0.7760999799,51.3457374573],"type":"Point"}
}