{
  "type": "Feature",
  "properties": {
    "iso:country":"GB",
    "sg:address":"Windsor House, Windsor Road",
    "sg:city":"Shipley",
    "sg:classifiers":[
        {
            "category":"Shopping",
            "subcategory":"Pharmacy",
            "type":"Retail Goods"
        }
    ],
    "sg:phone":"+44 1274 584422",
    "sg:postcode":"BD18 3EQ",
    "sg:province":"West Yorkshire",
    "sg:tags":[
        "pharmacist",
        "dispensing",
        "chemist"
    ],
    "wof:name":"Mindwise Ltd.",
    "wof:placetype":"venue"
},
  "geometry": {"coordinates":[-1.779944,53.833134],"type":"Point"}
}