{
  "type": "Feature",
  "properties": {
    "addr:full":"Old Market Avenue Chichester West Sussex PO19 1SW",
    "addr:postcode":"po19 1sw",
    "addr:street":"Old Market Avenue",
    "iso:country":"GB",
    "sg:address":"Old Market Avenue",
    "sg:city":"Chichester",
    "sg:classifiers":[
        {
            "category":"Place Of Worship",
            "type":"Public Place"
        }
    ],
    "sg:phone":"+44 1243 531594",
    "sg:postcode":"PO19 1SW",
    "sg:province":"West Sussex",
    "wof:name":"Christ Church Methodist & U.R.C",
    "wof:placetype":"venue"
},
  "geometry": {"coordinates":[-0.779295,50.833836],"type":"Point"}
}