{
  "type": "Feature",
  "properties": {
    "iso:country":"GB",
    "sg:address":"Neap House Works",
    "sg:city":"Scunthorpe",
    "sg:classifiers":[
        {
            "category":"Retail",
            "subcategory":"Auto Repair",
            "type":"Services"
        }
    ],
    "sg:phone":"+44 1724 783991",
    "sg:postcode":"DN15 8UE",
    "sg:province":"Lincolnshire",
    "sg:tags":[
        "modification",
        "garage"
    ],
    "wof:name":"V J Smith",
    "wof:placetype":"venue"
},
  "geometry": {"coordinates":[-0.726188,53.59716],"type":"Point"}
}