{
  "type": "Feature",
  "properties": {
    "addr:full":"Lorne Ho, Rotten Row Lichfield Staffordshire WS13 6JB",
    "addr:postcode":"ws13 6jb",
    "addr:street":"Lorne;Rotten Row",
    "iso:country":"GB",
    "sg:address":"Lorne Ho, Rotten Row",
    "sg:city":"Lichfield",
    "sg:classifiers":[
        {
            "category":"Sports & Exercise",
            "subcategory":"Gym",
            "type":"Entertainment"
        }
    ],
    "sg:postcode":"WS13 6JB",
    "sg:province":"Staffordshire",
    "sg:tags":[
        "fitness",
        "health",
        "centre"
    ],
    "wof:name":"Health Lines",
    "wof:placetype":"venue"
},
  "geometry": {"coordinates":[-1.8196599483,52.6840286255],"type":"Point"}
}