{
  "type": "Feature",
  "properties": {
    "addr:full":"58 Dudley Street Wolverhampton West Midlands WV1 3EN",
    "addr:housenumber":"58",
    "addr:postcode":"wv1 3en",
    "addr:street":"Dudley Street",
    "iso:country":"GB",
    "sg:address":"58 Dudley Street",
    "sg:city":"Wolverhampton",
    "sg:classifiers":[
        {
            "category":"Shopping",
            "subcategory":"Clothing, Apparel, & Fashions",
            "type":"Retail Goods"
        }
    ],
    "sg:phone":"+44 1902 713106",
    "sg:postcode":"WV1 3EN",
    "sg:province":"West Midlands",
    "sg:tags":[
        "accessory"
    ],
    "wof:name":"Bags by Anne Marie",
    "wof:placetype":"venue"
},
  "geometry": {"coordinates":[-2.127772,52.585606],"type":"Point"}
}