{
  "type": "Feature",
  "properties": {
    "addr:full":"43 Bramble Walk Epsom Surrey KT18 7TB",
    "addr:housenumber":"43",
    "addr:postcode":"kt18 7tb",
    "addr:street":"Bramble Walk",
    "iso:country":"GB",
    "sg:address":"43 Bramble Walk",
    "sg:city":"Epsom",
    "sg:classifiers":[
        {
            "category":"Building & Trades",
            "subcategory":"Construction",
            "type":"Services"
        }
    ],
    "sg:postcode":"KT18 7TB",
    "sg:province":"Surrey",
    "sg:tags":[
        "roofing"
    ],
    "wof:name":"J Macdonald",
    "wof:placetype":"venue"
},
  "geometry": {"coordinates":[-0.2847270072,51.3306159973],"type":"Point"}
}