{
  "type": "Feature",
  "properties": {
    "addr:full":"12 Brunswick Street Stoke-on-trent Staffordshire ST1 1DR",
    "addr:housenumber":"12",
    "addr:postcode":"st1 1dr",
    "addr:street":"Brunswick Street",
    "iso:country":"GB",
    "sg:address":"12 Brunswick Street",
    "sg:city":"Stoke-on-trent",
    "sg:classifiers":[
        {
            "category":"Shopping",
            "subcategory":"Shoes",
            "type":"Retail Goods"
        }
    ],
    "sg:phone":"+44 1782 271553",
    "sg:postcode":"ST1 1DR",
    "sg:province":"Staffordshire",
    "sg:tags":[
        "shop"
    ],
    "wof:name":"Grimm Bros",
    "wof:placetype":"venue"
},
  "geometry": {"coordinates":[-2.1769909859,53.025390625],"type":"Point"}
}