{
  "type": "Feature",
  "properties": {
    "iso:country":"GB",
    "sg:address":"Cribbs Farm, Cribbs Causeway",
    "sg:city":"Bristol",
    "sg:classifiers":[
        {
            "category":"Transit Center",
            "subcategory":"Passenger",
            "type":"Transportation"
        }
    ],
    "sg:postcode":"BS10 7TU",
    "sg:province":"City of Bristol",
    "sg:tags":[
        "boarding",
        "kennel",
        "catteries"
    ],
    "wof:name":"Cribbs Farm Boarding Kennels",
    "wof:placetype":"venue"
},
  "geometry": {"coordinates":[-2.601149,51.529171],"type":"Point"}
}