{
  "type": "Feature",
  "properties": {
    "addr:full":"79 Penkville Street, West End Stoke-on-trent Staffordshire ST4 5AL",
    "addr:housenumber":"79",
    "addr:postcode":"staffordshire st4 5al",
    "addr:street":"Penkville Street",
    "iso:country":"GB",
    "sg:address":"79 Penkville Street, West End",
    "sg:city":"Stoke-on-trent",
    "sg:classifiers":[
        {
            "category":"Retail",
            "subcategory":"Repair Shop",
            "type":"Services"
        }
    ],
    "sg:postcode":"ST4 5AL",
    "sg:province":"Staffordshire",
    "sg:tags":[
        "maintenance"
    ],
    "wof:name":"Maurice Haslegrave",
    "wof:placetype":"venue"
},
  "geometry": {"coordinates":[-2.1913700104,52.9961090088],"type":"Point"}
}