{
  "type": "Feature",
  "properties": {
    "iso:country":"GB",
    "sg:address":"Highwood House, Highwood Lane",
    "sg:city":"Romsey",
    "sg:classifiers":[
        {
            "category":"Education",
            "subcategory":"School",
            "type":"Public Place"
        }
    ],
    "sg:phone":"+44 1794 513231",
    "sg:postcode":"SO51 9ZH",
    "sg:province":"Hampshire",
    "sg:tags":[
        "independent",
        "preparatory"
    ],
    "wof:name":"Stroud School Ltd.",
    "wof:placetype":"venue"
},
  "geometry": {"coordinates":[-1.464632988,50.9940032959],"type":"Point"}
}