{
  "type": "Feature",
  "properties": {
    "iso:country":"GB",
    "sg:address":"Clubhouse, Rectory Road, Rowhedge",
    "sg:city":"Colchester",
    "sg:classifiers":[
        {
            "category":"Arena",
            "subcategory":"Sports Club",
            "type":"Entertainment"
        }
    ],
    "sg:phone":"+44 1206 728022",
    "sg:postcode":"CO5 7HP",
    "sg:province":"Essex",
    "wof:name":"Rowhedge Football Club",
    "wof:placetype":"venue"
},
  "geometry": {"coordinates":[0.9468,51.857784],"type":"Point"}
}