{
  "type": "Feature",
  "properties": {
    "addr:full":"Chasty Holsworthy Cornwall EX22 6NA",
    "addr:postcode":"ex22 6na",
    "iso:country":"GB",
    "sg:address":"Chasty",
    "sg:city":"Holsworthy",
    "sg:classifiers":[
        {
            "category":"Farming",
            "subcategory":"Livestock Farm",
            "type":"Manufacturing & Wholesale Goods"
        }
    ],
    "sg:postcode":"EX22 6NA",
    "sg:province":"Cornwall",
    "sg:tags":[
        "others"
    ],
    "wof:name":"P L May",
    "wof:placetype":"venue"
},
  "geometry": {"coordinates":[-4.35627985,50.7999000549],"type":"Point"}
}