{
  "type": "Feature",
  "properties": {
    "addr:full":"105 Main Road, Quadring Spalding Lincolnshire PE11 4PW",
    "addr:housenumber":"105",
    "addr:postcode":"pe11 4pw",
    "addr:street":"Main Road;Spalding",
    "iso:country":"GB",
    "sg:address":"105 Main Road, Quadring",
    "sg:city":"Spalding",
    "sg:classifiers":[
        {
            "category":"Government",
            "subcategory":"Post Office",
            "type":"Public Place"
        }
    ],
    "sg:postcode":"PE11 4PW",
    "sg:province":"Lincolnshire",
    "wof:name":"Quadring Po",
    "wof:placetype":"venue"
},
  "geometry": {"coordinates":[-0.182942,52.882748],"type":"Point"}
}