{
  "type": "Feature",
  "properties": {
    "addr:full":"792 Chesterfield Road Sheffield Derbyshire S8 0SF",
    "addr:housenumber":"792",
    "addr:postcode":"s8 0sf",
    "addr:street":"Chesterfield Road",
    "iso:country":"GB",
    "sg:address":"792 Chesterfield Road",
    "sg:city":"Sheffield",
    "sg:classifiers":[
        {
            "category":"Real Estate",
            "subcategory":"Real Estate Agent",
            "type":"Services"
        }
    ],
    "sg:phone":"+44 114 255 5651",
    "sg:postcode":"S8 0SF",
    "sg:province":"Derbyshire",
    "wof:name":"Blundells",
    "wof:placetype":"venue"
},
  "geometry": {"coordinates":[-1.478348,53.341839],"type":"Point"}
}