{
  "type": "Feature",
  "properties": {
    "addr:full":"6 Abinger Mews London Greater London W9 3SP",
    "addr:housenumber":"6",
    "addr:postcode":"w9 3sp",
    "addr:street":"Abinger Mews",
    "iso:country":"GB",
    "sg:address":"6 Abinger Mews",
    "sg:city":"London",
    "sg:classifiers":[
        {
            "category":"Manufacturing",
            "subcategory":"Apparel",
            "type":"Manufacturing & Wholesale Goods"
        }
    ],
    "sg:postcode":"W9 3SP",
    "sg:province":"Greater London",
    "sg:tags":[
        "shirt",
        "maker"
    ],
    "wof:name":"Bernard & Bernard",
    "wof:placetype":"venue"
},
  "geometry": {"coordinates":[-0.1984200031,51.5266609192],"type":"Point"}
}