{
  "type": "Feature",
  "properties": {
    "iso:country":"GB",
    "sg:address":"13 Lyndhurst Road",
    "sg:city":"Liverpool",
    "sg:classifiers":[
        {
            "category":"Building & Trades",
            "subcategory":"Construction",
            "type":"Services"
        }
    ],
    "sg:phone":"+44 151 924 2351",
    "sg:postcode":"L23 9TN",
    "sg:province":"Merseyside",
    "sg:tags":[
        "builder"
    ],
    "wof:name":"M Tyms",
    "wof:placetype":"venue"
},
  "geometry": {"coordinates":[-3.008924,53.4902],"type":"Point"}
}