{
  "type": "Feature",
  "properties": {
    "addr:full":"132 Feering Hill, Feering Colchester Essex CO5 9PY",
    "addr:housenumber":"132",
    "addr:postcode":"co5 9py",
    "addr:street":"Feering Hill",
    "iso:country":"GB",
    "sg:address":"132 Feering Hill, Feering",
    "sg:city":"Colchester",
    "sg:classifiers":[
        {
            "category":"Bars & Pubs",
            "type":"Food & Drink"
        }
    ],
    "sg:postcode":"CO5 9PY",
    "sg:province":"Essex",
    "sg:tags":[
        "pubs",
        "inn"
    ],
    "wof:name":"The Old Anchor",
    "wof:placetype":"venue"
},
  "geometry": {"coordinates":[0.7154219747,51.8437423706],"type":"Point"}
}