{
  "type": "Feature",
  "properties": {
    "iso:country":"GB",
    "sg:address":"3 Mill Hill Crescent",
    "sg:city":"Northallerton",
    "sg:classifiers":[
        {
            "category":"Banks & Credit Unions",
            "subcategory":"Financial Services",
            "type":"Services"
        }
    ],
    "sg:postcode":"DL6 1RU",
    "sg:province":"North Yorkshire",
    "sg:tags":[
        "consultant"
    ],
    "wof:name":"Northallerton Finance Services",
    "wof:placetype":"venue"
},
  "geometry": {"coordinates":[-1.425081,54.331264],"type":"Point"}
}