{
  "type": "Feature",
  "properties": {
    "addr:full":"130-132 Tooley St Southwark Greater London SE1 2TU",
    "addr:housenumber":"130-132",
    "addr:postcode":"se1 2tu",
    "addr:street":"Tooley St",
    "iso:country":"GB",
    "sg:address":"130-132 Tooley St",
    "sg:city":"Southwark",
    "sg:classifiers":[
        {
            "category":"Professional",
            "subcategory":"Detective & Security Services",
            "type":"Services"
        }
    ],
    "sg:phone":"+44 20 7403 5444",
    "sg:postcode":"SE1 2TU",
    "sg:province":"Greater London",
    "sg:tags":[
        "equipment"
    ],
    "wof:name":"Camera City Television",
    "wof:placetype":"venue"
},
  "geometry": {"coordinates":[-0.0816539973,51.5039787292],"type":"Point"}
}