{
  "type": "Feature",
  "properties": {
    "iso:country":"GB",
    "sg:address":"Orchard Farm, Pecking Mill, Evercreech",
    "sg:city":"Shepton Mallet",
    "sg:classifiers":[
        {
            "category":"Farming",
            "subcategory":"Dairy Farm",
            "type":"Manufacturing & Wholesale Goods"
        },
        {
            "category":"Farming",
            "subcategory":"Livestock Farm",
            "type":"Manufacturing & Wholesale Goods"
        }
    ],
    "sg:postcode":"BA4 6PQ",
    "sg:province":"Somerset",
    "sg:tags":[
        "others"
    ],
    "wof:name":"Norris,Clifford F",
    "wof:placetype":"venue"
},
  "geometry": {"coordinates":[-2.505549,51.148304],"type":"Point"}
}