{
  "type": "Feature",
  "properties": {
    "iso:country":"GB",
    "sg:address":"61 Nightingale Crescent, New Invention",
    "sg:city":"Willenhall",
    "sg:classifiers":[
        {
            "category":"Home & Garden",
            "subcategory":"Household Appliances",
            "type":"Retail Goods"
        }
    ],
    "sg:postcode":"WV12 5HE",
    "sg:province":"West Midlands",
    "sg:tags":[
        "electrical"
    ],
    "wof:name":"Robert & Colleen Ludwig",
    "wof:placetype":"venue"
},
  "geometry": {"coordinates":[-2.046557,52.612148],"type":"Point"}
}