{
  "type": "Feature",
  "properties": {
    "iso:country":"GB",
    "sg:address":"213-227 Lancaster Road",
    "sg:city":"Preston",
    "sg:classifiers":[
        {
            "category":"Building & Trades",
            "subcategory":"Construction",
            "type":"Services"
        }
    ],
    "sg:phone":"+44 1772 883775",
    "sg:postcode":"PR1 2QL",
    "sg:province":"Lancashire",
    "sg:tags":[
        "builder"
    ],
    "wof:name":"Specialist Heating Components Ltd.",
    "wof:placetype":"venue"
},
  "geometry": {"coordinates":[-2.7004699707,53.7633781433],"type":"Point"}
}