{
  "type": "Feature",
  "properties": {
    "addr:full":"11 Adlington Court, Birchwood Warrington Cheshire WA3 6PL",
    "addr:housenumber":"11",
    "addr:postcode":"wa3 6pl",
    "addr:street":"Adlington Court",
    "iso:country":"GB",
    "sg:address":"11 Adlington Court, Birchwood",
    "sg:city":"Warrington",
    "sg:classifiers":[
        {
            "category":"Professional",
            "subcategory":"Engineering",
            "type":"Services"
        }
    ],
    "sg:phone":"+44 1925 818223",
    "sg:postcode":"WA3 6PL",
    "sg:province":"Cheshire",
    "sg:tags":[
        "civil",
        "engineer"
    ],
    "wof:name":"Rachelfield Ltd.",
    "wof:placetype":"venue"
},
  "geometry": {"coordinates":[-2.5152750015,53.4287605286],"type":"Point"}
}