{
  "type": "Feature",
  "properties": {
    "iso:country":"GB",
    "sg:address":"Warren Farm, Panton",
    "sg:city":"Market Rasen",
    "sg:classifiers":[
        {
            "category":"Farming",
            "subcategory":"Livestock Farm",
            "type":"Manufacturing & Wholesale Goods"
        }
    ],
    "sg:phone":"+44 1673 858152",
    "sg:postcode":"LN8 5LQ",
    "sg:province":"Lincolnshire",
    "sg:tags":[
        "others"
    ],
    "wof:name":"A Parsonson",
    "wof:placetype":"venue"
},
  "geometry": {"coordinates":[-0.238789,53.29435],"type":"Point"}
}