{
  "type": "Feature",
  "properties": {
    "iso:country":"GB",
    "sg:address":"2 Lavender Ct, Molesham Way",
    "sg:city":"East Molesey",
    "sg:classifiers":[
        {
            "category":"Home & Garden",
            "subcategory":"Carpets & Floor Coverings",
            "type":"Retail Goods"
        }
    ],
    "sg:phone":"+44 20 8979 5772",
    "sg:postcode":"KT8 9NY",
    "sg:province":"Greater London",
    "sg:tags":[
        "carpets",
        "rug",
        "matting"
    ],
    "wof:name":"Fred A Flack",
    "wof:placetype":"venue"
},
  "geometry": {"coordinates":[-0.344541,51.401962],"type":"Point"}
}