{
  "type": "Feature",
  "properties": {
    "iso:country":"GB",
    "sg:address":"New Chapel Surgery, High St",
    "sg:city":"Aylesbury",
    "sg:classifiers":[
        {
            "category":"Health Services",
            "subcategory":"Doctor",
            "type":"Services"
        }
    ],
    "sg:phone":"+44 1844 208228",
    "sg:postcode":"HP18 9AF",
    "sg:province":"Buckinghamshire",
    "sg:tags":[
        "practitioners"
    ],
    "wof:name":"Whittington, J M",
    "wof:placetype":"venue"
},
  "geometry": {"coordinates":[-1.000757,51.796688],"type":"Point"}
}