{
  "type": "Feature",
  "properties": {
    "addr:full":"41 Rectory La Loughton Essex IG10 1NZ",
    "addr:housenumber":"41",
    "addr:postcode":"ig10 1nz",
    "addr:street":"Rectory La Loughton",
    "iso:country":"GB",
    "sg:address":"41 Rectory La",
    "sg:city":"Loughton",
    "sg:classifiers":[
        {
            "category":"Health Services",
            "subcategory":"Health Practitioner",
            "type":"Services"
        }
    ],
    "sg:phone":"+44 20 8502 0029",
    "sg:postcode":"IG10 1NZ",
    "sg:province":"Essex",
    "sg:tags":[
        "acupuncture"
    ],
    "wof:name":"Physiotherapy (Manipulation Clinic)",
    "wof:placetype":"venue"
},
  "geometry": {"coordinates":[0.071703,51.654026],"type":"Point"}
}