{
  "type": "Feature",
  "properties": {
    "addr:full":"8 Nelson Avenue Tonbridge Kent TN9 1XA",
    "addr:housenumber":"8",
    "addr:postcode":"tn9 1xa",
    "addr:street":"Nelson Avenue",
    "iso:country":"GB",
    "sg:address":"8 Nelson Avenue",
    "sg:city":"Tonbridge",
    "sg:classifiers":[
        {
            "category":"Building & Trades",
            "subcategory":"Construction",
            "type":"Services"
        }
    ],
    "sg:postcode":"TN9 1XA",
    "sg:province":"Kent",
    "sg:tags":[
        "decorator",
        "painter"
    ],
    "wof:name":"T J Decorators & Building Contractors",
    "wof:placetype":"venue"
},
  "geometry": {"coordinates":[0.264187,51.192699],"type":"Point"}
}