{
  "type": "Feature",
  "properties": {
    "iso:country":"GB",
    "sg:address":"Llanddowror",
    "sg:city":"Carmarthen",
    "sg:classifiers":[
        {
            "category":"Travel",
            "subcategory":"Hotels & Motels",
            "type":"Entertainment"
        }
    ],
    "sg:phone":"+44 1994 230383",
    "sg:postcode":"SA33 4HJ",
    "sg:province":"Carmarthenshire",
    "wof:name":"Picton House Country Club",
    "wof:placetype":"venue"
},
  "geometry": {"coordinates":[-4.50891,51.794559],"type":"Point"}
}