{
  "type": "Feature",
  "properties": {
    "iso:country":"GB",
    "sg:address":"New Road, Offord Cluny",
    "sg:city":"Huntingdon",
    "sg:classifiers":[
        {
            "category":"Sports & Exercise",
            "subcategory":"Stables",
            "type":"Entertainment"
        }
    ],
    "sg:phone":"+44 1480 812654",
    "sg:postcode":"PE19 5RP",
    "sg:province":"Bedfordshire",
    "sg:tags":[
        "equestrian",
        "centre",
        "livery",
        "schools",
        "riding",
        "education"
    ],
    "wof:name":"Northbrook Equestrian Centre",
    "wof:placetype":"venue"
},
  "geometry": {"coordinates":[-0.1159629971,52.318523407],"type":"Point"}
}