{
  "type": "Feature",
  "properties": {
    "addr:full":"434 Ormskirk Road, Pemberton Wigan Lancashire WN5 9DF",
    "addr:housenumber":"434",
    "addr:postcode":"wn5 9df",
    "addr:street":"Ormskirk Road",
    "iso:country":"GB",
    "sg:address":"434 Ormskirk Road, Pemberton",
    "sg:city":"Wigan",
    "sg:classifiers":[
        {
            "category":"Building & Trades",
            "subcategory":"Plumbing",
            "type":"Services"
        }
    ],
    "sg:postcode":"WN5 9DF",
    "sg:province":"Lancashire",
    "sg:tags":[
        "central",
        "heating"
    ],
    "wof:name":"Premier Gas Care Ltd.",
    "wof:placetype":"venue"
},
  "geometry": {"coordinates":[-2.667366,53.535397],"type":"Point"}
}