{
  "type": "Feature",
  "properties": {
    "addr:full":"1 Brunton Terrace Edinburgh City of Edinburgh EH7 5EH",
    "addr:housenumber":"1",
    "addr:postcode":"eh7 5eh",
    "addr:street":"Brunton Terrace",
    "iso:country":"GB",
    "sg:address":"1 Brunton Terrace",
    "sg:city":"Edinburgh",
    "sg:classifiers":[
        {
            "category":"Home & Garden",
            "subcategory":"Household Appliances",
            "type":"Retail Goods"
        },
        {
            "category":"Manufacturing",
            "subcategory":"Food",
            "type":"Manufacturing & Wholesale Goods"
        }
    ],
    "sg:phone":"+44 131 652 2576",
    "sg:postcode":"EH7 5EH",
    "sg:province":"City of Edinburgh",
    "sg:tags":[
        "supplier",
        "electrical",
        "oven",
        "microwave",
        "manufacturer"
    ],
    "wof:name":"Lothian Appliances",
    "wof:placetype":"venue"
},
  "geometry": {"coordinates":[-3.1737709045,55.9577789307],"type":"Point"}
}