{
  "type": "Feature",
  "properties": {
    "iso:country":"GB",
    "sg:address":"46 West Street",
    "sg:city":"Alresford",
    "sg:classifiers":[
        {
            "category":"Deli",
            "type":"Food & Drink"
        }
    ],
    "sg:postcode":"SO24 9AU",
    "sg:province":"Hampshire",
    "sg:tags":[
        "delicatessen"
    ],
    "wof:name":"Harvest Deli",
    "wof:placetype":"venue"
},
  "geometry": {"coordinates":[-1.1637380123,51.0901832581],"type":"Point"}
}