{
  "type": "Feature",
  "properties": {
    "addr:full":"Unit 4 Hollyhill Park, Hollyhill Road, Forest Vale Industrial Estate Cinderford Gloucestershire GL14 2YB",
    "addr:housenumber":"unit 4",
    "addr:postcode":"gl14 2yb",
    "addr:street":"Hollyhill Park Hollyhill Road;Industrial Estate",
    "iso:country":"GB",
    "sg:address":"Unit 4 Hollyhill Park, Hollyhill Road, Forest Vale Industrial Estate",
    "sg:city":"Cinderford",
    "sg:classifiers":[
        {
            "category":"Manufacturing",
            "subcategory":"Signs",
            "type":"Manufacturing & Wholesale Goods"
        }
    ],
    "sg:postcode":"GL14 2YB",
    "sg:province":"Gloucestershire",
    "sg:tags":[
        "writer"
    ],
    "wof:name":"Designer Signs",
    "wof:placetype":"venue"
},
  "geometry": {"coordinates":[-2.511299,51.825871],"type":"Point"}
}