{
  "type": "Feature",
  "properties": {
    "addr:full":"Bestwood Road Nottingham Nottinghamshire NG6 8SS",
    "addr:postcode":"ng6 8ss",
    "addr:street":"Bestwood Road",
    "iso:country":"GB",
    "sg:address":"Bestwood Road",
    "sg:city":"Nottingham",
    "sg:classifiers":[
        {
            "category":"Shopping",
            "subcategory":"Stationery & Office Supplies",
            "type":"Retail Goods"
        }
    ],
    "sg:postcode":"NG6 8SS",
    "sg:province":"Nottinghamshire",
    "sg:tags":[
        "equipment"
    ],
    "wof:name":"Crail Office Supplies",
    "wof:placetype":"venue"
},
  "geometry": {"coordinates":[-1.1833699942,53.0164527893],"type":"Point"}
}