{
  "type": "Feature",
  "properties": {
    "addr:full":"Lysways Ho, 45 Brittania Way, Brittania Enterprise Pk Lichfield Staffordshire WS14 9UY",
    "addr:housenumber":"45",
    "addr:postcode":"ws14 9uy",
    "addr:street":"Brittania Way;Enterprise Pk",
    "iso:country":"GB",
    "sg:address":"Lysways Ho, 45 Brittania Way, Brittania Enterprise Pk",
    "sg:city":"Lichfield",
    "sg:classifiers":[
        {
            "category":"Professional",
            "subcategory":"Business Services",
            "type":"Services"
        }
    ],
    "sg:phone":"+44 1543 418855",
    "sg:postcode":"WS14 9UY",
    "sg:province":"Staffordshire",
    "sg:tags":[
        "shop",
        "cleaning"
    ],
    "wof:name":"W G (Cleaning Services) Ltd",
    "wof:placetype":"venue"
},
  "geometry": {"coordinates":[-1.8018100262,52.6846618652],"type":"Point"}
}