{
  "type": "Feature",
  "properties": {
    "addr:full":"46 Park Mall, Saddlers Centre Walsall West Midlands WS1 1YS",
    "addr:housenumber":"46",
    "addr:postcode":"ws1 1ys",
    "addr:street":"Park Mall Saddlers Centre",
    "iso:country":"GB",
    "sg:address":"46 Park Mall, Saddlers Centre",
    "sg:city":"Walsall",
    "sg:classifiers":[
        {
            "category":"Shopping",
            "subcategory":"Shoes",
            "type":"Retail Goods"
        }
    ],
    "sg:phone":"+44 1922 624075",
    "sg:postcode":"WS1 1YS",
    "sg:province":"West Midlands",
    "sg:tags":[
        "shop"
    ],
    "wof:name":"The Clarks Shop",
    "wof:placetype":"venue"
},
  "geometry": {"coordinates":[-1.9837189913,52.5852584839],"type":"Point"}
}