{
  "type": "Feature",
  "properties": {
    "addr:full":"88 Main Street Mexborough South Yorkshire S64 9EB",
    "addr:housenumber":"88",
    "addr:postcode":"s64 9eb",
    "addr:street":"Main Street",
    "iso:country":"GB",
    "sg:address":"88 Main Street",
    "sg:city":"Mexborough",
    "sg:classifiers":[
        {
            "category":"Health Services",
            "subcategory":"Clinic",
            "type":"Services"
        },
        {
            "category":"Health Services",
            "subcategory":"Dentist",
            "type":"Services"
        }
    ],
    "sg:phone":"+44 1709 571323",
    "sg:postcode":"S64 9EB",
    "sg:province":"South Yorkshire",
    "sg:tags":[
        "nh"
    ],
    "wof:name":"Mexborough Dental Surgery",
    "wof:placetype":"venue"
},
  "geometry": {"coordinates":[-1.2975690365,53.4949913025],"type":"Point"}
}