{
  "type": "Feature",
  "properties": {
    "addr:full":"50 Johnstone Ave Stirling Clackmannanshire FK9 5DJ",
    "addr:housenumber":"50",
    "addr:postcode":"fk9 5dj",
    "addr:street":"Johnstone Ave",
    "iso:country":"GB",
    "sg:address":"50 Johnstone Ave",
    "sg:city":"Stirling",
    "sg:classifiers":[
        {
            "category":"Food & Beverages",
            "subcategory":"Meat & Fish",
            "type":"Retail Goods"
        }
    ],
    "sg:postcode":"FK9 5DJ",
    "sg:province":"Clackmannanshire",
    "sg:tags":[
        "butcher"
    ],
    "wof:name":"Hunter,J P,",
    "wof:placetype":"venue"
},
  "geometry": {"coordinates":[-3.9393010139,56.1357536316],"type":"Point"}
}