{
  "type": "Feature",
  "properties": {
    "iso:country":"GB",
    "sg:address":"160 Vernon Road",
    "sg:city":"Nottingham",
    "sg:classifiers":[
        {
            "category":"Home & Garden",
            "subcategory":"Home Furnishings",
            "type":"Retail Goods"
        },
        {
            "category":"Building & Trades",
            "subcategory":"Landfill",
            "type":"Services"
        }
    ],
    "sg:phone":"+44 115 942 0898",
    "sg:postcode":"NG6 0AD",
    "sg:province":"Nottinghamshire",
    "sg:tags":[
        "blind",
        "curtain",
        "fitting",
        "canopy"
    ],
    "wof:name":"Elite Blinds",
    "wof:placetype":"venue"
},
  "geometry": {"coordinates":[-1.1780200005,52.9819831848],"type":"Point"}
}