{
  "type": "Feature",
  "properties": {
    "iso:country":"GB",
    "sg:address":"Sussex Avenue",
    "sg:city":"Leeds",
    "sg:classifiers":[
        {
            "category":"Real Estate",
            "subcategory":"Real Estate Services",
            "type":"Services"
        },
        {
            "category":"Manufacturing",
            "subcategory":"Building Materials",
            "type":"Manufacturing & Wholesale Goods"
        }
    ],
    "sg:phone":"+44 113 385 7700",
    "sg:postcode":"LS10 2LF",
    "sg:province":"West Yorkshire",
    "sg:tags":[
        "insulation",
        "cladding"
    ],
    "wof:name":"Sheffield Insulations Ltd",
    "wof:placetype":"venue"
},
  "geometry": {"coordinates":[-1.51815,53.775719],"type":"Point"}
}