{
  "type": "Feature",
  "properties": {
    "addr:full":"Paradise Road Downham Market Cambridgeshire PE38 9HS",
    "addr:postcode":"pe38 9hs",
    "addr:street":"Paradise Road",
    "iso:country":"GB",
    "sg:address":"Paradise Road",
    "sg:city":"Downham Market",
    "sg:classifiers":[
        {
            "category":"Personal",
            "subcategory":"Beauty Salon",
            "type":"Services"
        }
    ],
    "sg:phone":"+44 1366 385917",
    "sg:postcode":"PE38 9HS",
    "sg:province":"Cambridgeshire",
    "wof:name":"Beauty Profile",
    "wof:placetype":"venue"
},
  "geometry": {"coordinates":[0.3766979873,52.6042785645],"type":"Point"}
}