{
  "type": "Feature",
  "properties": {
    "addr:full":"Bullen Street, Thorverton Exeter Devon EX5 5NG",
    "addr:postcode":"ex5 5ng",
    "addr:street":"Bullen Street",
    "iso:country":"GB",
    "sg:address":"Bullen Street, Thorverton",
    "sg:city":"Exeter",
    "sg:classifiers":[
        {
            "category":"Personal",
            "subcategory":"Beauty Salon",
            "type":"Services"
        }
    ],
    "sg:postcode":"EX5 5NG",
    "sg:province":"Devon",
    "sg:tags":[
        "unisex",
        "hairdresser"
    ],
    "wof:name":"Barnets Hairdressing & Beauty Salon",
    "wof:placetype":"venue"
},
  "geometry": {"coordinates":[-3.5277628899,50.8082275391],"type":"Point"}
}