{
  "type": "Feature",
  "properties": {
    "addr:full":"7 Broad Grn Wellingborough Northamptonshire NN8 4LE",
    "addr:housenumber":"7",
    "addr:postcode":"nn8 4le",
    "addr:street":"Broad Grn",
    "iso:country":"GB",
    "sg:address":"7 Broad Grn",
    "sg:city":"Wellingborough",
    "sg:classifiers":[
        {
            "category":"Organizations",
            "subcategory":"Membership Organization",
            "type":"Services"
        }
    ],
    "sg:postcode":"NN8 4LE",
    "sg:province":"Northamptonshire",
    "sg:tags":[
        "club"
    ],
    "wof:name":"Northamptonshire Province R A O B Club",
    "wof:placetype":"venue"
},
  "geometry": {"coordinates":[-0.6993889809,52.3050308228],"type":"Point"}
}