{
  "type": "Feature",
  "properties": {
    "iso:country":"GB",
    "sg:address":"5 Post Office Rd",
    "sg:city":"Bournemouth",
    "sg:classifiers":[
        {
            "category":"Shopping",
            "subcategory":"Beauty & Cosmetics",
            "type":"Retail Goods"
        }
    ],
    "sg:phone":"+44 1202 291887",
    "sg:postcode":"BH1 1BB",
    "sg:province":"Dorset",
    "sg:tags":[
        "wig",
        "hairpiece"
    ],
    "wof:name":"Dorset Hairdressing Services",
    "wof:placetype":"venue"
},
  "geometry": {"coordinates":[-1.878089,50.720455],"type":"Point"}
}