{
  "type": "Feature",
  "properties": {
    "addr:full":"27 Old Street London Greater London EC1V 9HL",
    "addr:housenumber":"27",
    "addr:postcode":"ec1v 9hl",
    "addr:street":"Old Street",
    "iso:country":"GB",
    "sg:address":"27 Old Street",
    "sg:city":"London",
    "sg:classifiers":[
        {
            "category":"Professional",
            "subcategory":"Management & Consulting",
            "type":"Services"
        }
    ],
    "sg:phone":"+44 20 7253 5064",
    "sg:postcode":"EC1V 9HL",
    "sg:province":"Greater London",
    "sg:tags":[
        "consultant",
        "business"
    ],
    "wof:name":"Institute for Health Sector Development",
    "wof:placetype":"venue"
},
  "geometry": {"coordinates":[-0.0976559967,51.5237503052],"type":"Point"}
}