{
  "type": "Feature",
  "properties": {
    "iso:country":"GB",
    "sg:address":"5 Queensway",
    "sg:city":"Manchester",
    "sg:classifiers":[
        {
            "category":"Banks & Credit Unions",
            "subcategory":"Financial Services",
            "type":"Services"
        }
    ],
    "sg:phone":"+44 161 703 8898",
    "sg:postcode":"M28 7TZ",
    "sg:province":"Greater Manchester",
    "sg:tags":[
        "consultant"
    ],
    "wof:name":"Gregory Matthew",
    "wof:placetype":"venue"
},
  "geometry": {"coordinates":[-2.4094429016,53.5135726929],"type":"Point"}
}