{
  "type": "Feature",
  "properties": {
    "addr:full":"50 High Street, Sawston Cambridge Cambridgeshire CB2 4BG",
    "addr:housenumber":"50",
    "addr:postcode":"cb2 4bg",
    "addr:street":"High Street",
    "iso:country":"GB",
    "sg:address":"50 High Street, Sawston",
    "sg:city":"Cambridge",
    "sg:classifiers":[
        {
            "category":"Government",
            "subcategory":"Post Office",
            "type":"Public Place"
        }
    ],
    "sg:phone":"+44 1223 833101",
    "sg:postcode":"CB2 4BG",
    "sg:province":"Cambridgeshire",
    "wof:name":"Sawston Post Office",
    "wof:placetype":"venue"
},
  "geometry": {"coordinates":[0.169436,52.123169],"type":"Point"}
}