{
  "type": "Feature",
  "properties": {
    "addr:full":"66 Windsor Road, Ealing London Greater London W5 5PH",
    "addr:housenumber":"66",
    "addr:postcode":"w5 5ph",
    "addr:street":"Windsor Road",
    "iso:country":"GB",
    "sg:address":"66 Windsor Road, Ealing",
    "sg:city":"London",
    "sg:classifiers":[
        {
            "category":"Health Services",
            "subcategory":"Health Practitioner",
            "type":"Services"
        }
    ],
    "sg:phone":"+44 20 8840 9961",
    "sg:postcode":"W5 5PH",
    "sg:province":"Greater London",
    "sg:tags":[
        "hypnotherapists"
    ],
    "wof:name":"Robert Matthews",
    "wof:placetype":"venue"
},
  "geometry": {"coordinates":[-0.300284,51.51022],"type":"Point"}
}