{
  "type": "Feature",
  "properties": {
    "iso:country":"GB",
    "sg:address":"Turrett House, 77 Portsmouth Road",
    "sg:city":"Guildford",
    "sg:classifiers":[
        {
            "category":"Shopping",
            "subcategory":"Books",
            "type":"Retail Goods"
        }
    ],
    "sg:postcode":"GU2 4BS",
    "sg:province":"Surrey",
    "wof:name":"Amberwood Publishing Ltd.",
    "wof:placetype":"venue"
},
  "geometry": {"coordinates":[-0.578869,51.231823],"type":"Point"}
}