{
  "type": "Feature",
  "properties": {
    "addr:full":"Wallis Road Kettering Northamptonshire NN15 6NX",
    "addr:postcode":"nn15 6nx",
    "addr:street":"Wallis Road",
    "iso:country":"GB",
    "sg:address":"Wallis Road",
    "sg:city":"Kettering",
    "sg:classifiers":[
        {
            "category":"Retail",
            "subcategory":"Funeral Services",
            "type":"Services"
        }
    ],
    "sg:postcode":"NN15 6NX",
    "sg:province":"Northamptonshire",
    "wof:name":"Jack Warwick",
    "wof:placetype":"venue"
},
  "geometry": {"coordinates":[-0.715873003,52.3919334412],"type":"Point"}
}