{
  "type": "Feature",
  "properties": {
    "iso:country":"GB",
    "sg:address":"52 Ingleston Avenue",
    "sg:city":"Denny",
    "sg:classifiers":[
        {
            "category":"Professional",
            "type":"Services"
        }
    ],
    "sg:postcode":"FK6 6QP",
    "sg:province":"Falkirk",
    "sg:tags":[
        "caterer"
    ],
    "wof:name":"Crown Catering",
    "wof:placetype":"venue"
},
  "geometry": {"coordinates":[-3.9172160625,56.034034729],"type":"Point"}
}