{
  "type": "Feature",
  "properties": {
    "addr:full":"Victoria Road Barnstaple Devon EX32 8NP",
    "addr:postcode":"ex32 8np",
    "addr:street":"Victoria Road",
    "iso:country":"GB",
    "sg:address":"Victoria Road",
    "sg:city":"Barnstaple",
    "sg:classifiers":[
        {
            "category":"Government",
            "subcategory":"Office",
            "type":"Public Place"
        },
        {
            "category":"Organizations",
            "subcategory":"Non-profit Organization",
            "type":"Services"
        }
    ],
    "sg:phone":"+44 1271 321411",
    "sg:postcode":"EX32 8NP",
    "sg:province":"Devon",
    "sg:tags":[
        "charitable",
        "organisation",
        "central",
        "voluntary",
        "charity"
    ],
    "wof:name":"Victoria House Family Centre",
    "wof:placetype":"venue"
},
  "geometry": {"coordinates":[-4.045783,51.077225],"type":"Point"}
}