{
  "type": "Feature",
  "properties": {
    "iso:country":"GB",
    "sg:address":"198 Tower Gardens Road",
    "sg:city":"London",
    "sg:classifiers":[
        {
            "category":"Building & Trades",
            "subcategory":"Construction",
            "type":"Services"
        }
    ],
    "sg:phone":"+44 20 8808 4116",
    "sg:postcode":"N17 7QB",
    "sg:province":"Greater London",
    "sg:tags":[
        "roofing",
        "builder",
        "contracting"
    ],
    "wof:name":"I T T Roofing",
    "wof:placetype":"venue"
},
  "geometry": {"coordinates":[-0.083239,51.598297],"type":"Point"}
}