{
  "type": "Feature",
  "properties": {
    "addr:full":"Station Lane, Lapworth Solihull Warwickshire B94 6LT",
    "addr:postcode":"b94 6lt",
    "addr:street":"Station Lane",
    "iso:country":"GB",
    "sg:address":"Station Lane, Lapworth",
    "sg:city":"Solihull",
    "sg:classifiers":[
        {
            "category":"Education",
            "subcategory":"School",
            "type":"Public Place"
        }
    ],
    "sg:phone":"+44 1564 783225",
    "sg:postcode":"B94 6LT",
    "sg:province":"Warwickshire",
    "sg:tags":[
        "local",
        "authority"
    ],
    "wof:name":"Lapworth C Of E Primary School",
    "wof:placetype":"venue"
},
  "geometry": {"coordinates":[-1.72492,52.337944],"type":"Point"}
}