{
  "type": "Feature",
  "properties": {
    "addr:full":"Unit 3 Rivergate Mall Irvine North Ayrshire KA12 8HY",
    "addr:housenumber":"unit 3",
    "addr:postcode":"ka12 8hy",
    "addr:street":"Rivergate Mall",
    "iso:country":"GB",
    "sg:address":"Unit 3 Rivergate Mall",
    "sg:city":"Irvine",
    "sg:classifiers":[
        {
            "category":"Shopping",
            "subcategory":"Comic Books",
            "type":"Retail Goods"
        }
    ],
    "sg:phone":"+44 1294 275008",
    "sg:postcode":"KA12 8HY",
    "sg:province":"North Ayrshire",
    "sg:tags":[
        "jeweller"
    ],
    "wof:name":"Chesters the Jewellers",
    "wof:placetype":"venue"
},
  "geometry": {"coordinates":[-4.6732587814,55.6019744873],"type":"Point"}
}