{
  "type": "Feature",
  "properties": {
    "addr:full":"Weekends Only, 6 Haven St, Camden Town Camden Greater London NW1 8QX",
    "addr:housenumber":"6",
    "addr:postcode":"nw1 8qx",
    "addr:street":"Haven St",
    "iso:country":"GB",
    "sg:address":"Weekends Only, 6 Haven St, Camden Town",
    "sg:city":"Camden",
    "sg:classifiers":[
        {
            "category":"Professional",
            "subcategory":"Business Services",
            "type":"Services"
        }
    ],
    "sg:phone":"+44 20 7485 8355",
    "sg:postcode":"NW1 8QX",
    "sg:province":"Greater London",
    "sg:tags":[
        "operator",
        "market"
    ],
    "wof:name":"Camden Canal Market",
    "wof:placetype":"venue"
},
  "geometry": {"coordinates":[-0.1449,51.542198],"type":"Point"}
}