{
  "type": "Feature",
  "properties": {
    "iso:country":"GB",
    "sg:address":"Fourth Floor, St James Yarn Mill, Whitefriars",
    "sg:city":"Norwich",
    "sg:classifiers":[
        {
            "category":"Government",
            "subcategory":"Office",
            "type":"Public Place"
        }
    ],
    "sg:phone":"+44 1603 220105",
    "sg:postcode":"NR3 1SU",
    "sg:province":"Norfolk",
    "sg:tags":[
        "central"
    ],
    "wof:name":"Norfolk Probation Service",
    "wof:placetype":"venue"
},
  "geometry": {"coordinates":[1.3066,52.636936],"type":"Point"}
}