{
  "type": "Feature",
  "properties": {
    "iso:country":"GB",
    "sg:address":"29 Spittal Terrace",
    "sg:city":"Gainsborough",
    "sg:classifiers":[
        {
            "category":"Landmark",
            "subcategory":"Tourist Information",
            "type":"Public Place"
        }
    ],
    "sg:phone":"+44 1427 615411",
    "sg:postcode":"DN21 2HG",
    "sg:province":"Lincolnshire",
    "wof:name":"Tourist Information Centre",
    "wof:placetype":"venue"
},
  "geometry": {"coordinates":[-0.771832,53.401398],"type":"Point"}
}