{
  "type": "Feature",
  "properties": {
    "addr:full":"58 Bohemia Road St Leonards-on-sea East Sussex TN37 6RQ",
    "addr:housenumber":"58",
    "addr:postcode":"leonards-on-sea;tn37 6rq",
    "addr:street":"Bohemia Road St",
    "iso:country":"GB",
    "sg:address":"58 Bohemia Road",
    "sg:city":"St Leonards-on-sea",
    "sg:classifiers":[
        {
            "category":"Recreation",
            "subcategory":"Fishing",
            "type":"Entertainment"
        }
    ],
    "sg:phone":"+44 1424 431583",
    "sg:postcode":"TN37 6RQ",
    "sg:province":"East Sussex",
    "sg:tags":[
        "angling"
    ],
    "wof:name":"S H Tackle",
    "wof:placetype":"venue"
},
  "geometry": {"coordinates":[0.5587260127,50.8632507324],"type":"Point"}
}