{
  "type": "Feature",
  "properties": {
    "addr:full":"Units 14-15 Station Lane, Old Whittington Chesterfield Derbyshire S41 9QX",
    "addr:housenumber":"units 14-15",
    "addr:postcode":"s41 9qx",
    "addr:street":"Station Lane",
    "iso:country":"GB",
    "sg:address":"Units 14-15 Station Lane, Old Whittington",
    "sg:city":"Chesterfield",
    "sg:classifiers":[
        {
            "category":"Home & Garden",
            "subcategory":"Household Appliances",
            "type":"Retail Goods"
        }
    ],
    "sg:phone":"+44 1246 261900",
    "sg:postcode":"S41 9QX",
    "sg:province":"Derbyshire",
    "sg:tags":[
        "refrigeration",
        "air conditioning"
    ],
    "wof:name":"Strawford C S  Trading As Strawford Mechanical Se",
    "wof:placetype":"venue"
},
  "geometry": {"coordinates":[-1.4269989729,53.2666664124],"type":"Point"}
}