{
  "type": "Feature",
  "properties": {
    "iso:country":"GB",
    "sg:address":"Unit 3 9 Union Mills Dewsbury Rd",
    "sg:city":"Leeds",
    "sg:classifiers":[
        {
            "category":"Building & Trades",
            "subcategory":"Construction",
            "type":"Services"
        }
    ],
    "sg:postcode":"LS11 5DD",
    "sg:province":"West Yorkshire",
    "sg:tags":[
        "flooring"
    ],
    "wof:name":"Florplan (N E) Ltd",
    "wof:placetype":"venue"
},
  "geometry": {"coordinates":[-1.5465869904,53.7944946289],"type":"Point"}
}