{
  "type": "Feature",
  "properties": {
    "addr:full":"35 Old Queen Street London Greater London SW1H 9JD",
    "addr:housenumber":"35",
    "addr:postcode":"sw1h 9jd",
    "addr:street":"Old Queen Street",
    "iso:country":"GB",
    "sg:address":"35 Old Queen Street",
    "sg:city":"London",
    "sg:classifiers":[
        {
            "category":"Professional",
            "subcategory":"Accounting & Tax Preparation",
            "type":"Services"
        }
    ],
    "sg:phone":"+44 20 7835 1171",
    "sg:postcode":"SW1H 9JD",
    "sg:province":"Greater London",
    "sg:tags":[
        "accountant"
    ],
    "wof:name":"H A International Associates Ltd.",
    "wof:placetype":"venue"
},
  "geometry": {"coordinates":[-0.131058,51.500668],"type":"Point"}
}