{
  "type": "Feature",
  "properties": {
    "addr:full":"31 Orwell Road Felixstowe Suffolk IP11 7DD",
    "addr:housenumber":"31",
    "addr:postcode":"ip11 7dd",
    "addr:street":"Orwell Road",
    "iso:country":"GB",
    "sg:address":"31 Orwell Road",
    "sg:city":"Felixstowe",
    "sg:classifiers":[
        {
            "category":"Health Services",
            "subcategory":"Doctor",
            "type":"Services"
        }
    ],
    "sg:phone":"+44 1394 282706",
    "sg:postcode":"IP11 7DD",
    "sg:province":"Suffolk",
    "sg:tags":[
        "practitioners"
    ],
    "wof:name":"Howard House Surgery",
    "wof:placetype":"venue"
},
  "geometry": {"coordinates":[1.349646,51.961418],"type":"Point"}
}