{
  "type": "Feature",
  "properties": {
    "iso:country":"GB",
    "sg:address":"84 High Street",
    "sg:city":"Ramsgate",
    "sg:classifiers":[
        {
            "category":"Shopping",
            "subcategory":"Crafts & Fabrics",
            "type":"Retail Goods"
        }
    ],
    "sg:phone":"+44 1843 595768",
    "sg:postcode":"CT11 9RX",
    "sg:province":"Kent",
    "sg:tags":[
        "shop",
        "needlecraft",
        "wool"
    ],
    "wof:name":"Keans",
    "wof:placetype":"venue"
},
  "geometry": {"coordinates":[1.416849,51.335312],"type":"Point"}
}