{
  "type": "Feature",
  "properties": {
    "addr:full":"15 St. Athan Close, Bowerhill Melksham Wiltshire SN12 6XP",
    "addr:housenumber":"15",
    "addr:postcode":"sn12 6xp",
    "addr:street":"St. Athan Close",
    "iso:country":"GB",
    "sg:address":"15 St. Athan Close, Bowerhill",
    "sg:city":"Melksham",
    "sg:classifiers":[
        {
            "category":"Manufacturing",
            "subcategory":"Building Materials",
            "type":"Manufacturing & Wholesale Goods"
        }
    ],
    "sg:phone":"+44 1225 707704",
    "sg:postcode":"SN12 6XP",
    "sg:province":"Wiltshire",
    "sg:tags":[
        "tile",
        "mnfrs"
    ],
    "wof:name":"Interfix Tile Fixing",
    "wof:placetype":"venue"
},
  "geometry": {"coordinates":[-2.122976,51.35331],"type":"Point"}
}