{
  "type": "Feature",
  "properties": {
    "addr:full":"60 Union Street, Harthill Sheffield South Yorkshire S26 7YH",
    "addr:housenumber":"60",
    "addr:postcode":"s26 7yh",
    "addr:street":"Union Street",
    "iso:country":"GB",
    "sg:address":"60 Union Street, Harthill",
    "sg:city":"Sheffield",
    "sg:classifiers":[
        {
            "category":"Food & Beverages",
            "subcategory":"Bakery",
            "type":"Retail Goods"
        }
    ],
    "sg:phone":"+44 1909 770128",
    "sg:postcode":"S26 7YH",
    "sg:province":"South Yorkshire",
    "sg:tags":[
        "shop",
        "baker"
    ],
    "wof:name":"Harthill Bakery",
    "wof:placetype":"venue"
},
  "geometry": {"coordinates":[-1.260262,53.321285],"type":"Point"}
}