{
  "type": "Feature",
  "properties": {
    "iso:country":"GB",
    "sg:address":"Unit 12, Heaton Mill",
    "sg:city":"Manchester",
    "sg:classifiers":[
        {
            "category":"Home & Garden",
            "subcategory":"Home Furnishings",
            "type":"Retail Goods"
        }
    ],
    "sg:phone":"+44 161 320 5020",
    "sg:postcode":"M34 3RG",
    "sg:province":"Greater Manchester",
    "sg:tags":[
        "furnishers",
        "planner",
        "bedroom"
    ],
    "wof:name":"Mystique Bedrooms",
    "wof:placetype":"venue"
},
  "geometry": {"coordinates":[-2.126661,53.456104],"type":"Point"}
}