{
  "type": "Feature",
  "properties": {
    "addr:full":"Springvale Works, Elland Road Brighouse West Yorkshire HD6 2RN",
    "addr:postcode":"hd6 2rn",
    "addr:street":"Elland Road",
    "iso:country":"GB",
    "sg:address":"Springvale Works, Elland Road",
    "sg:city":"Brighouse",
    "sg:classifiers":[
        {
            "category":"Retail",
            "subcategory":"Auto Repair",
            "type":"Services"
        }
    ],
    "sg:phone":"+44 1484 400404",
    "sg:postcode":"HD6 2RN",
    "sg:province":"West Yorkshire",
    "sg:tags":[
        "modification",
        "garage"
    ],
    "wof:name":"Grey Shed Motors",
    "wof:placetype":"venue"
},
  "geometry": {"coordinates":[-1.7737369537,53.7021942139],"type":"Point"}
}