{
  "type": "Feature",
  "properties": {
    "addr:full":"Dock Side, Junction Cut, Avonmouth Docks Bristol City of Bristol BS11 9BU",
    "addr:postcode":"bs11 9bu",
    "iso:country":"GB",
    "sg:address":"Dock Side, Junction Cut, Avonmouth Docks",
    "sg:city":"Bristol",
    "sg:classifiers":[
        {
            "category":"Freight",
            "type":"Transportation"
        }
    ],
    "sg:phone":"+44 117 982 2704",
    "sg:postcode":"BS11 9BU",
    "sg:province":"City of Bristol",
    "sg:tags":[
        "overseas",
        "shipping",
        "removal"
    ],
    "wof:name":"B S I Inspecorate Ltd.",
    "wof:placetype":"venue"
},
  "geometry": {"coordinates":[-2.694124,51.498917],"type":"Point"}
}