{
  "type": "Feature",
  "properties": {
    "iso:country":"GB",
    "sg:address":"65-67 St Clair St",
    "sg:city":"Kirkcaldy",
    "sg:classifiers":[
        {
            "category":"Shopping",
            "subcategory":"News",
            "type":"Retail Goods"
        }
    ],
    "sg:phone":"+44 1592 651920",
    "sg:postcode":"KY1 2NW",
    "sg:province":"Fife",
    "sg:tags":[
        "newsagent"
    ],
    "wof:name":"News World",
    "wof:placetype":"venue"
},
  "geometry": {"coordinates":[-3.142099,56.124031],"type":"Point"}
}