{
  "type": "Feature",
  "properties": {
    "addr:full":"3-5 Elephant Lane London Greater London SE16 4JD",
    "addr:housenumber":"3-5",
    "addr:postcode":"se16 4jd",
    "addr:street":"Elephant Lane",
    "iso:country":"GB",
    "sg:address":"3-5 Elephant Lane",
    "sg:city":"London",
    "sg:classifiers":[
        {
            "category":"Arts & Performance",
            "subcategory":"Theater",
            "type":"Entertainment"
        }
    ],
    "sg:phone":"+44 20 7237 4434",
    "sg:postcode":"SE16 4JD",
    "sg:province":"Greater London",
    "sg:tags":[
        "theatre"
    ],
    "wof:name":"The Bubble Theatre Co. Ltd.",
    "wof:placetype":"venue"
},
  "geometry": {"coordinates":[-0.055146,51.50037],"type":"Point"}
}