{
  "type": "Feature",
  "properties": {
    "addr:full":"5 Church Lane, Madingley Cambridge Cambridgeshire CB3 8AF",
    "addr:housenumber":"5",
    "addr:postcode":"cb3 8af",
    "addr:street":"Church Lane",
    "iso:country":"GB",
    "sg:address":"5 Church Lane, Madingley",
    "sg:city":"Cambridge",
    "sg:classifiers":[
        {
            "category":"Professional",
            "subcategory":"Management & Consulting",
            "type":"Services"
        }
    ],
    "sg:phone":"+44 1954 212121",
    "sg:postcode":"CB3 8AF",
    "sg:province":"Cambridgeshire",
    "sg:tags":[
        "marketing",
        "consultant"
    ],
    "wof:name":"The Cambridge Strategy Centre Ltd.",
    "wof:placetype":"venue"
},
  "geometry": {"coordinates":[-0.0696099997,52.2538070679],"type":"Point"}
}