{
  "type": "Feature",
  "properties": {
    "addr:full":"Canal Road, Timperley Altrincham Cheshire WA14 1TD",
    "addr:postcode":"wa14 1td",
    "addr:street":"Canal Road",
    "iso:country":"GB",
    "sg:address":"Canal Road, Timperley",
    "sg:city":"Altrincham",
    "sg:classifiers":[
        {
            "category":"Manufacturing",
            "subcategory":"Textiles",
            "type":"Manufacturing & Wholesale Goods"
        }
    ],
    "sg:phone":"+44 161 969 1909",
    "sg:postcode":"WA14 1TD",
    "sg:province":"Cheshire",
    "sg:tags":[
        "designer"
    ],
    "wof:name":"Rhino Frames Ltd.",
    "wof:placetype":"venue"
},
  "geometry": {"coordinates":[-2.344394,53.400681],"type":"Point"}
}