{
  "type": "Feature",
  "properties": {
    "iso:country":"GB",
    "sg:address":"Unit 4, Stamford Business Park",
    "sg:city":"Stamford",
    "sg:classifiers":[
        {
            "category":"Professional",
            "subcategory":"Management & Consulting",
            "type":"Services"
        }
    ],
    "sg:phone":"+44 1780 766966",
    "sg:postcode":"PE9 1XT",
    "sg:province":"Cambridgeshire",
    "sg:tags":[
        "marketing",
        "consultant"
    ],
    "wof:name":"Nomis Marketing Ltd.",
    "wof:placetype":"venue"
},
  "geometry": {"coordinates":[-0.48029,52.652084],"type":"Point"}
}