{
  "type": "Feature",
  "properties": {
    "iso:country":"GB",
    "sg:address":"102 High Street",
    "sg:city":"Berkhamsted",
    "sg:classifiers":[
        {
            "category":"Farming",
            "subcategory":"Livestock Farm",
            "type":"Manufacturing & Wholesale Goods"
        }
    ],
    "sg:phone":"+44 1442 864836",
    "sg:postcode":"HP4 2BL",
    "sg:province":"Bedfordshire",
    "sg:tags":[
        "breeder"
    ],
    "wof:name":"Sarah Stewart (Flowers)",
    "wof:placetype":"venue"
},
  "geometry": {"coordinates":[-0.5602869987,51.759098053],"type":"Point"}
}