{
  "type": "Feature",
  "properties": {
    "iso:country":"GB",
    "sg:address":"6 Little Wade",
    "sg:city":"Welwyn Garden City",
    "sg:classifiers":[
        {
            "category":"Shopping",
            "subcategory":"Party Supplies",
            "type":"Retail Goods"
        },
        {
            "category":"Arts & Performance",
            "subcategory":"Music",
            "type":"Entertainment"
        }
    ],
    "sg:phone":"+44 1707 891617",
    "sg:postcode":"AL7 4LE",
    "sg:province":"Hertfordshire",
    "sg:tags":[
        "mobile",
        "operator",
        "disco"
    ],
    "wof:name":"Geoffrey Chambers",
    "wof:placetype":"venue"
},
  "geometry": {"coordinates":[-0.189757,51.784267],"type":"Point"}
}