{
  "type": "Feature",
  "properties": {
    "addr:full":"71 Narrow La Leicester Leicestershire LE2 8NA",
    "addr:housenumber":"71",
    "addr:postcode":"le2 8na",
    "addr:street":"Narrow La Leicester",
    "iso:country":"GB",
    "sg:address":"71 Narrow La",
    "sg:city":"Leicester",
    "sg:classifiers":[
        {
            "category":"Manufacturing",
            "subcategory":"Motor Vehicles & Parts",
            "type":"Manufacturing & Wholesale Goods"
        }
    ],
    "sg:phone":"+44 116 244 0288",
    "sg:postcode":"LE2 8NA",
    "sg:province":"Leicestershire",
    "sg:tags":[
        "bearing"
    ],
    "wof:name":"Rexnord Corporation",
    "wof:placetype":"venue"
},
  "geometry": {"coordinates":[-1.1597440243,52.6029891968],"type":"Point"}
}