{
  "type": "Feature",
  "properties": {
    "iso:country":"GB",
    "sg:address":"Unit 6,, Bardon 22 Industrial Estate, Bardon Hill",
    "sg:city":"Coalville",
    "sg:classifiers":[
        {
            "category":"Home & Garden",
            "subcategory":"Hardware",
            "type":"Retail Goods"
        }
    ],
    "sg:phone":"+44 1530 518900",
    "sg:postcode":"LE67 1TE",
    "sg:province":"Leicestershire",
    "sg:tags":[
        "device",
        "fixing",
        "fastener"
    ],
    "wof:name":"Fairchild Fasteners UK Ltd",
    "wof:placetype":"venue"
},
  "geometry": {"coordinates":[-1.340121,52.703991],"type":"Point"}
}