{
  "type": "Feature",
  "properties": {
    "iso:country":"GB",
    "sg:address":"127 Commercial Road, Lower Parkstone",
    "sg:city":"Poole",
    "sg:classifiers":[
        {
            "category":"Home & Garden",
            "subcategory":"Home Furnishings",
            "type":"Retail Goods"
        }
    ],
    "sg:phone":"+44 1202 740779",
    "sg:postcode":"BH14 0JD",
    "sg:province":"Dorset",
    "sg:tags":[
        "blind",
        "manufacture",
        "fitting",
        "curtain"
    ],
    "wof:name":"Poppy Designs",
    "wof:placetype":"venue"
},
  "geometry": {"coordinates":[-1.951474,50.723824],"type":"Point"}
}