{
  "type": "Feature",
  "properties": {
    "iso:country":"GB",
    "sg:address":"1 Bivelham Cottages, Witherenden Rd",
    "sg:city":"Mayfield",
    "sg:classifiers":[
        {
            "category":"Manufacturing",
            "subcategory":"Printing",
            "type":"Manufacturing & Wholesale Goods"
        }
    ],
    "sg:phone":"+44 1435 883738",
    "sg:postcode":"TN20 6RS",
    "sg:province":"East Sussex",
    "sg:tags":[
        "bookbinder"
    ],
    "wof:name":"Bookbinding Equipment",
    "wof:placetype":"venue"
},
  "geometry": {"coordinates":[0.2587350011,51.0200042725],"type":"Point"}
}