{
  "type": "Feature",
  "properties": {
    "iso:country":"GB",
    "sg:address":"Whitelees Road",
    "sg:city":"Lanark",
    "sg:classifiers":[
        {
            "category":"Farming",
            "subcategory":"Poultry Farm",
            "type":"Manufacturing & Wholesale Goods"
        }
    ],
    "sg:phone":"+44 1555 664432",
    "sg:postcode":"ML11 7LD",
    "sg:province":"South Lanarkshire",
    "sg:tags":[
        "related"
    ],
    "wof:name":"Ian Crawford Farm Supplies",
    "wof:placetype":"venue"
},
  "geometry": {"coordinates":[-3.736699,55.704376],"type":"Point"}
}