{
  "type": "Feature",
  "properties": {
    "addr:full":"Princess Of Wales Hospital, Stourbridge Road Bromsgrove Worcestershire B61 0BB",
    "addr:postcode":"b61 0bb",
    "addr:street":"Stourbridge Road",
    "iso:country":"GB",
    "sg:address":"Princess Of Wales Hospital, Stourbridge Road",
    "sg:city":"Bromsgrove",
    "sg:classifiers":[
        {
            "category":"Health Services",
            "subcategory":"Hospital",
            "type":"Services"
        }
    ],
    "sg:phone":"+44 1527 488000",
    "sg:postcode":"B61 0BB",
    "sg:province":"Worcestershire",
    "wof:name":"Princess of Wales Community Hospital",
    "wof:placetype":"venue"
},
  "geometry": {"coordinates":[-2.0618290901,52.3483581543],"type":"Point"}
}