{
  "type": "Feature",
  "properties": {
    "addr:full":"772-774 Romford Road London Greater London E12 6BU",
    "addr:housenumber":"772-774",
    "addr:postcode":"e12 6bu",
    "addr:street":"Romford Road",
    "iso:country":"GB",
    "sg:address":"772-774 Romford Road",
    "sg:city":"London",
    "sg:classifiers":[
        {
            "category":"Food & Beverages",
            "subcategory":"Chocolate",
            "type":"Retail Goods"
        }
    ],
    "sg:phone":"+44 20 8514 8099",
    "sg:postcode":"E12 6BU",
    "sg:province":"Greater London",
    "sg:tags":[
        "packer"
    ],
    "wof:name":"Mina Stores",
    "wof:placetype":"venue"
},
  "geometry": {"coordinates":[0.05471,51.553211],"type":"Point"}
}