{
  "type": "Feature",
  "properties": {
    "iso:country":"GB",
    "sg:address":"Tredegar Rd",
    "sg:city":"New Tredegar",
    "sg:classifiers":[
        {
            "category":"Organizations",
            "subcategory":"Membership Organization",
            "type":"Services"
        }
    ],
    "sg:phone":"+44 1443 834655",
    "sg:postcode":"NP2 6AL",
    "sg:province":"Caerphilly",
    "sg:tags":[
        "club"
    ],
    "wof:name":"New Empire Club",
    "wof:placetype":"venue"
},
  "geometry": {"coordinates":[-3.242734,51.722122],"type":"Point"}
}