{
  "type": "Feature",
  "properties": {
    "iso:country":"GB",
    "sg:address":"13 St Andrew Street",
    "sg:city":"Dumfries",
    "sg:classifiers":[
        {
            "category":"Personal",
            "subcategory":"Beauty Salon",
            "type":"Services"
        }
    ],
    "sg:postcode":"DG1 1BS",
    "sg:province":"Dumfries and Galloway",
    "sg:tags":[
        "unisex",
        "hairdresser"
    ],
    "wof:name":"Shylocks Hairdresser",
    "wof:placetype":"venue"
},
  "geometry": {"coordinates":[-3.604989,55.070751],"type":"Point"}
}