{
  "type": "Feature",
  "properties": {
    "addr:full":"60 Boston Road London Greater London W7 3TR",
    "addr:housenumber":"60",
    "addr:postcode":"w7 3tr",
    "addr:street":"Boston Road",
    "iso:country":"GB",
    "sg:address":"60 Boston Road",
    "sg:city":"London",
    "sg:classifiers":[
        {
            "category":"Home & Garden",
            "subcategory":"Furniture",
            "type":"Retail Goods"
        }
    ],
    "sg:phone":"+44 20 8579 3552",
    "sg:postcode":"W7 3TR",
    "sg:province":"Greater London",
    "wof:name":"Boston Pine",
    "wof:placetype":"venue"
},
  "geometry": {"coordinates":[-0.337482,51.50639],"type":"Point"}
}