{
  "type": "Feature",
  "properties": {
    "addr:full":"St Peters Park, Wells Road Bath Somerset BA2 3AN",
    "addr:postcode":"ba2 3an",
    "addr:street":"Wells Road",
    "iso:country":"GB",
    "sg:address":"St Peters Park, Wells Road",
    "sg:city":"Bath",
    "sg:classifiers":[
        {
            "category":"Professional",
            "subcategory":"Computer Services",
            "type":"Services"
        }
    ],
    "sg:phone":"+44 1761 410285",
    "sg:postcode":"BA2 3AN",
    "sg:province":"Somerset",
    "sg:tags":[
        "system",
        "software"
    ],
    "wof:name":"Proform Ltd.",
    "wof:placetype":"venue"
},
  "geometry": {"coordinates":[-2.3672099113,51.3766899109],"type":"Point"}
}