{
  "type": "Feature",
  "properties": {
    "iso:country":"GB",
    "sg:address":"46 Cambridge Street",
    "sg:city":"Rugby",
    "sg:classifiers":[
        {
            "category":"Place Of Worship",
            "type":"Public Place"
        },
        {
            "category":"Organizations",
            "subcategory":"Non-profit Organization",
            "type":"Services"
        }
    ],
    "sg:phone":"+44 1788 544608",
    "sg:postcode":"CV21 3NQ",
    "sg:province":"Warwickshire",
    "sg:tags":[
        "charitable",
        "organisation",
        "charity"
    ],
    "wof:name":"RUGBY CHRISTIAN FELLOWSHIP",
    "wof:placetype":"venue"
},
  "geometry": {"coordinates":[-1.2478259802,52.3739585876],"type":"Point"}
}