{
  "type": "Feature",
  "properties": {
    "iso:country":"GB",
    "sg:address":"101 Ripon Rd",
    "sg:city":"Bournemouth",
    "sg:classifiers":[
        {
            "category":"Insurance",
            "subcategory":"Hazard Insurance",
            "type":"Services"
        }
    ],
    "sg:phone":"+44 1202 776000",
    "sg:postcode":"BH9 1RA",
    "sg:province":"Dorset",
    "sg:tags":[
        "fire",
        "water",
        "damage"
    ],
    "wof:name":"Merlin Fire Flood Damage Specialist",
    "wof:placetype":"venue"
},
  "geometry": {"coordinates":[-1.8689090014,50.7481079102],"type":"Point"}
}