{
  "type": "Feature",
  "properties": {
    "addr:full":"Thrum Hall, Thrum Hall Lane Rochdale Lancashire OL12 6DE",
    "addr:postcode":"ol12 6de",
    "addr:street":"Hall Lane",
    "iso:country":"GB",
    "sg:address":"Thrum Hall, Thrum Hall Lane",
    "sg:city":"Rochdale",
    "sg:classifiers":[
        {
            "category":"Manufacturing",
            "subcategory":"Textiles",
            "type":"Manufacturing & Wholesale Goods"
        }
    ],
    "sg:phone":"+44 1706 646292",
    "sg:postcode":"OL12 6DE",
    "sg:province":"Lancashire",
    "sg:tags":[
        "made-up"
    ],
    "wof:name":"Fibrescan",
    "wof:placetype":"venue"
},
  "geometry": {"coordinates":[-2.1627659798,53.6190071106],"type":"Point"}
}