{
  "type": "Feature",
  "properties": {
    "addr:full":"28 Gerrard Road Willenhall West Midlands WV13 3LB",
    "addr:housenumber":"28",
    "addr:postcode":"wv13 3lb",
    "addr:street":"Gerrard Road",
    "iso:country":"GB",
    "sg:address":"28 Gerrard Road",
    "sg:city":"Willenhall",
    "sg:classifiers":[
        {
            "category":"Building & Trades",
            "subcategory":"Plumbing",
            "type":"Services"
        },
        {
            "category":"Building & Trades",
            "subcategory":"Construction",
            "type":"Services"
        }
    ],
    "sg:phone":"+44 1902 609968",
    "sg:postcode":"WV13 3LB",
    "sg:province":"West Midlands",
    "sg:tags":[
        "heating",
        "contractor"
    ],
    "wof:name":"Cooper Bros Heating & Plumbing Ltd.",
    "wof:placetype":"venue"
},
  "geometry": {"coordinates":[-2.0707809925,52.5801467896],"type":"Point"}
}