{
  "type": "Feature",
  "properties": {
    "addr:full":"58-60 Freeman Street Grimsby Lincolnshire DN32 7AG",
    "addr:housenumber":"58-60",
    "addr:postcode":"dn32 7ag",
    "addr:street":"Freeman Street",
    "iso:country":"GB",
    "sg:address":"58-60 Freeman Street",
    "sg:city":"Grimsby",
    "sg:classifiers":[
        {
            "category":"Home & Garden",
            "subcategory":"Home Furnishings",
            "type":"Retail Goods"
        },
        {
            "category":"Home & Garden",
            "subcategory":"Furniture",
            "type":"Retail Goods"
        }
    ],
    "sg:phone":"+44 1472 362942",
    "sg:postcode":"DN32 7AG",
    "sg:province":"Lincolnshire",
    "sg:tags":[
        "blind",
        "manufacture",
        "fitting",
        "curtain"
    ],
    "wof:name":"A & D Curtains",
    "wof:placetype":"venue"
},
  "geometry": {"coordinates":[-0.073486,53.572987],"type":"Point"}
}