{
  "type": "Feature",
  "properties": {
    "iso:country":"GB",
    "sg:address":"Unit 1, The Red House, Shieldhill Road",
    "sg:city":"Falkirk",
    "sg:classifiers":[
        {
            "category":"Retail",
            "subcategory":"Auto Repair",
            "type":"Services"
        }
    ],
    "sg:phone":"+44 1324 714113",
    "sg:postcode":"FK2 0DT",
    "sg:province":"Falkirk",
    "sg:tags":[
        "modification",
        "garage"
    ],
    "wof:name":"James Kelly Motor Engineers",
    "wof:placetype":"venue"
},
  "geometry": {"coordinates":[-3.740679,55.980728],"type":"Point"}
}