{
  "type": "Feature",
  "properties": {
    "addr:full":"4 The Square Cumnock East Ayrshire KA18 1BG",
    "addr:housenumber":"4",
    "addr:postcode":"ka18 1bg",
    "addr:street":"The Square Cumnock East",
    "iso:country":"GB",
    "sg:address":"4 The Square",
    "sg:city":"Cumnock",
    "sg:classifiers":[
        {
            "category":"Professional",
            "subcategory":"Lawyer & Legal Services",
            "type":"Services"
        }
    ],
    "sg:phone":"+44 1290 421602",
    "sg:postcode":"KA18 1BG",
    "sg:province":"East Ayrshire",
    "sg:tags":[
        "advice",
        "counselling"
    ],
    "wof:name":"Bridge Project The",
    "wof:placetype":"venue"
},
  "geometry": {"coordinates":[-4.2640991211,55.4532546997],"type":"Point"}
}