{
  "type": "Feature",
  "properties": {
    "iso:country":"GB",
    "sg:address":"2 Weald Road",
    "sg:city":"Brentwood",
    "sg:classifiers":[
        {
            "category":"Home & Garden",
            "subcategory":"Carpets & Floor Coverings",
            "type":"Retail Goods"
        }
    ],
    "sg:phone":"+44 1277 219213",
    "sg:postcode":"CM14 4SX",
    "sg:province":"Essex",
    "sg:tags":[
        "carpets",
        "retailer",
        "rug",
        "matting"
    ],
    "wof:name":"Clements Hall Ltd.",
    "wof:placetype":"venue"
},
  "geometry": {"coordinates":[0.2974289954,51.6194725037],"type":"Point"}
}