{
  "type": "Feature",
  "properties": {
    "iso:country":"GB",
    "sg:address":"19 Clayport Street",
    "sg:city":"Alnwick",
    "sg:classifiers":[
        {
            "category":"Shopping",
            "subcategory":"Clothing, Apparel, & Fashions",
            "type":"Retail Goods"
        }
    ],
    "sg:postcode":"NE66 1LA",
    "sg:province":"Northumberland",
    "sg:tags":[
        "clothing"
    ],
    "wof:name":"U K Golf Discount",
    "wof:placetype":"venue"
},
  "geometry": {"coordinates":[-1.709276,55.412327],"type":"Point"}
}