{
  "type": "Feature",
  "properties": {
    "iso:country":"GB",
    "sg:address":"Tamar Valley",
    "sg:city":"Saltash",
    "sg:classifiers":[
        {
            "category":"Place Of Worship",
            "type":"Public Place"
        }
    ],
    "sg:phone":"+44 1579 383274",
    "sg:postcode":"PL12 6TQ",
    "sg:province":"Cornwall",
    "wof:name":"Tamar Valley Methodist Church",
    "wof:placetype":"venue"
},
  "geometry": {"coordinates":[-4.212884,50.408749],"type":"Point"}
}