{
  "type": "Feature",
  "properties": {
    "iso:country":"GB",
    "sg:address":"1aa Units, Cogegoes Farm",
    "sg:city":"Camborne",
    "sg:classifiers":[
        {
            "category":"Manufacturing",
            "subcategory":"Petroleum Products",
            "type":"Manufacturing & Wholesale Goods"
        }
    ],
    "sg:phone":"+44 1209 716960",
    "sg:postcode":"TR14 0BQ",
    "sg:province":"Cornwall",
    "sg:tags":[
        "double",
        "glazing"
    ],
    "wof:name":"Locost Windows",
    "wof:placetype":"venue"
},
  "geometry": {"coordinates":[-5.301258,50.213654],"type":"Point"}
}