{
  "type": "Feature",
  "properties": {
    "iso:country":"GB",
    "sg:address":"1 Constable Cres",
    "sg:city":"Seven Sisters",
    "sg:classifiers":[
        {
            "category":"Personal",
            "type":"Services"
        }
    ],
    "sg:phone":"+44 20 8365 1654",
    "sg:postcode":"N15 4QZ",
    "sg:province":"Greater London",
    "sg:tags":[
        "dressmaker"
    ],
    "wof:name":"Elmastyle Ltd",
    "wof:placetype":"venue"
},
  "geometry": {"coordinates":[-0.0650629997,51.5827484131],"type":"Point"}
}