{
  "type": "Feature",
  "properties": {
    "iso:country":"GB",
    "sg:address":"Churchill House, Churchill Rd",
    "sg:city":"Blackburn",
    "sg:classifiers":[
        {
            "category":"Farming",
            "subcategory":"Nursery",
            "type":"Manufacturing & Wholesale Goods"
        }
    ],
    "sg:phone":"+44 1254 52816",
    "sg:postcode":"BB1 5NX",
    "sg:province":"Lancashire",
    "sg:tags":[
        "creche"
    ],
    "wof:name":"Churchill House Nursery",
    "wof:placetype":"venue"
},
  "geometry": {"coordinates":[-2.464854,53.757351],"type":"Point"}
}