{
  "type": "Feature",
  "properties": {
    "addr:full":"Unit 1 38 Wilbury Way Hitchin Hertfordshire SG4 0AP",
    "addr:housenumber":"unit;38",
    "addr:postcode":"sg4 0ap",
    "addr:street":"Wilbury Way",
    "iso:country":"GB",
    "sg:address":"Unit 1 38 Wilbury Way",
    "sg:city":"Hitchin",
    "sg:classifiers":[
        {
            "category":"Manufacturing",
            "subcategory":"Signs",
            "type":"Manufacturing & Wholesale Goods"
        }
    ],
    "sg:phone":"+44 1462 452060",
    "sg:postcode":"SG4 0AP",
    "sg:province":"Hertfordshire",
    "sg:tags":[
        "writer"
    ],
    "wof:name":"Caledonian Solutions Ltd.",
    "wof:placetype":"venue"
},
  "geometry": {"coordinates":[-0.265014,51.96104],"type":"Point"}
}