{
  "type": "Feature",
  "properties": {
    "addr:full":"41 Rectory Ct, 189 High Rd South Woodford Greater London E18 2PE",
    "addr:housenumber":"41;189",
    "addr:postcode":"e18 2pe",
    "addr:street":"Rectory Ct;High Rd",
    "iso:country":"GB",
    "sg:address":"41 Rectory Ct, 189 High Rd",
    "sg:city":"South Woodford",
    "sg:classifiers":[
        {
            "category":"Professional",
            "subcategory":"Accounting & Tax Preparation",
            "type":"Services"
        }
    ],
    "sg:phone":"+44 20 8504 3585",
    "sg:postcode":"E18 2PE",
    "sg:province":"Greater London",
    "sg:tags":[
        "accountant"
    ],
    "wof:name":"El-Jai Consulting",
    "wof:placetype":"venue"
},
  "geometry": {"coordinates":[0.0208199993,51.5980300903],"type":"Point"}
}