{
  "type": "Feature",
  "properties": {
    "iso:country":"GB",
    "sg:address":"1st Floor Rear Of 23 Bargate",
    "sg:city":"Grimsby",
    "sg:classifiers":[
        {
            "category":"Organizations",
            "subcategory":"Non-profit Organization",
            "type":"Services"
        }
    ],
    "sg:phone":"+44 1472 347914",
    "sg:postcode":"DN34 4SS",
    "sg:province":"Lincolnshire",
    "sg:tags":[
        "charitable",
        "organisation",
        "voluntary",
        "charity"
    ],
    "wof:name":"Grimsby Fishermans Dependents Fund",
    "wof:placetype":"venue"
},
  "geometry": {"coordinates":[-0.1100390032,53.5625495911],"type":"Point"}
}