{
  "type": "Feature",
  "properties": {
    "iso:country":"GB",
    "sg:address":"Suite 1 Anders Sq, Perton",
    "sg:city":"Wolverhampton",
    "sg:classifiers":[
        {
            "category":"Shopping",
            "subcategory":"Mobile Phones",
            "type":"Retail Goods"
        }
    ],
    "sg:phone":"+44 1902 844211",
    "sg:postcode":"WV6 7QH",
    "sg:province":"Shropshire",
    "wof:name":"K Phones Ltd",
    "wof:placetype":"venue"
},
  "geometry": {"coordinates":[-2.202073,52.598049],"type":"Point"}
}