{
  "type": "Feature",
  "properties": {
    "addr:full":"2a Ramford St St. Helens Cheshire WA9 1QG",
    "addr:housenumber":"2a",
    "addr:postcode":"wa9 1qg",
    "addr:street":"Ramford St",
    "iso:country":"GB",
    "sg:address":"2a Ramford St",
    "sg:city":"St. Helens",
    "sg:classifiers":[
        {
            "category":"Social Services",
            "subcategory":"Retirement Home",
            "type":"Services"
        }
    ],
    "sg:phone":"+44 1744 750740",
    "sg:postcode":"WA9 1QG",
    "sg:province":"Cheshire",
    "sg:tags":[
        "care"
    ],
    "wof:name":"Care Support",
    "wof:placetype":"venue"
},
  "geometry": {"coordinates":[-2.7136380672,53.4507293701],"type":"Point"}
}