{
  "type": "Feature",
  "properties": {
    "iso:country":"GB",
    "sg:address":"65 Mount Ephraim",
    "sg:city":"Tunbridge Wells",
    "sg:classifiers":[
        {
            "category":"Health Services",
            "subcategory":"Dentist",
            "type":"Services"
        }
    ],
    "sg:phone":"+44 1892 542141",
    "sg:postcode":"TN4 8BH",
    "sg:province":"Kent",
    "wof:name":"L Winchester",
    "wof:placetype":"venue"
},
  "geometry": {"coordinates":[0.2580110133,51.1337547302],"type":"Point"}
}