{
  "type": "Feature",
  "properties": {
    "iso:country":"GB",
    "sg:address":"Bells La",
    "sg:city":"Birmingham",
    "sg:classifiers":[
        {
            "category":"Autos & Motor Vehicles",
            "subcategory":"Fuel & Gas Station",
            "type":"Retail Goods"
        }
    ],
    "sg:phone":"+44 121 433 2990",
    "sg:postcode":"B14 5QH",
    "sg:province":"West Midlands",
    "sg:tags":[
        "hr",
        "petrol"
    ],
    "wof:name":"Shell UK Ltd",
    "wof:placetype":"venue"
},
  "geometry": {"coordinates":[-1.909265995,52.4062004089],"type":"Point"}
}