{
  "type": "Feature",
  "properties": {
    "addr:full":"The Roos Saffron Walden Essex CB11 3JS",
    "addr:postcode":"cb11 3js",
    "iso:country":"GB",
    "sg:address":"The Roos",
    "sg:city":"Saffron Walden",
    "sg:classifiers":[
        {
            "category":"Farming",
            "subcategory":"Livestock Farm",
            "type":"Manufacturing & Wholesale Goods"
        }
    ],
    "sg:phone":"+44 1799 522250",
    "sg:postcode":"CB11 3JS",
    "sg:province":"Essex",
    "sg:tags":[
        "others"
    ],
    "wof:name":"Roosfarmers",
    "wof:placetype":"venue"
},
  "geometry": {"coordinates":[0.267275,51.977089],"type":"Point"}
}