{
  "type": "Feature",
  "properties": {
    "iso:country":"GB",
    "sg:address":"227 Three Bridges Road",
    "sg:city":"Crawley",
    "sg:classifiers":[
        {
            "category":"Shopping",
            "subcategory":"Department Store",
            "type":"Retail Goods"
        }
    ],
    "sg:phone":"+44 1293 520015",
    "sg:postcode":"RH10 1LG",
    "sg:province":"Surrey",
    "wof:name":"The Corner Stores",
    "wof:placetype":"venue"
},
  "geometry": {"coordinates":[-0.1643379927,51.1177902222],"type":"Point"}
}