{
  "type": "Feature",
  "properties": {
    "addr:full":"9 Bridgewater Road, Hertburn Industrial Estate Washington Tyne and Wear NE37 2SG",
    "addr:housenumber":"9",
    "addr:postcode":"ne37 2sg",
    "addr:street":"Bridgewater Road Hertburn Industrial Estate",
    "iso:country":"GB",
    "sg:address":"9 Bridgewater Road, Hertburn Industrial Estate",
    "sg:city":"Washington",
    "sg:classifiers":[
        {
            "category":"Home & Garden",
            "subcategory":"Household Appliances",
            "type":"Retail Goods"
        },
        {
            "category":"Professional",
            "subcategory":"Testing Lab",
            "type":"Services"
        },
        {
            "category":"Home & Garden",
            "subcategory":"Kitchen Supply",
            "type":"Retail Goods"
        }
    ],
    "sg:phone":"+44 191 417 9888",
    "sg:postcode":"NE37 2SG",
    "sg:province":"Tyne and Wear",
    "sg:tags":[
        "measuring",
        "instrument",
        "scale",
        "inspection",
        "calibration"
    ],
    "wof:name":"D M G Control Systems Ltd.",
    "wof:placetype":"venue"
},
  "geometry": {"coordinates":[-1.514236,54.908142],"type":"Point"}
}