{
  "type": "Feature",
  "properties": {
    "iso:country":"GB",
    "sg:address":"35-37 Jane Street",
    "sg:city":"Workington",
    "sg:classifiers":[
        {
            "category":"Travel",
            "subcategory":"Travel Agent",
            "type":"Entertainment"
        }
    ],
    "sg:phone":"+44 1900 62222",
    "sg:postcode":"CA14 3BQ",
    "sg:province":"Cumbria",
    "wof:name":"Grahams Travel Service",
    "wof:placetype":"venue"
},
  "geometry": {"coordinates":[-3.544882,54.642513],"type":"Point"}
}