{
  "type": "Feature",
  "properties": {
    "iso:country":"GB",
    "sg:address":"Charles St",
    "sg:city":"Rotherham",
    "sg:classifiers":[
        {
            "category":"Communications",
            "subcategory":"Television Station",
            "type":"Services"
        }
    ],
    "sg:phone":"+44 1709 580633",
    "sg:postcode":"S62 5TG",
    "sg:province":"South Yorkshire",
    "sg:tags":[
        "equipment",
        "telephone"
    ],
    "wof:name":"Red Telephone Box Co Ltd",
    "wof:placetype":"venue"
},
  "geometry": {"coordinates":[-1.329337,53.46909],"type":"Point"}
}