{
  "type": "Feature",
  "properties": {
    "addr:full":"36 Hamlet Court Road Westcliff-on-sea Essex SS0 7LX",
    "addr:housenumber":"36",
    "addr:postcode":"ss0 7lx",
    "addr:street":"Hamlet Court Road",
    "iso:country":"GB",
    "sg:address":"36 Hamlet Court Road",
    "sg:city":"Westcliff-on-sea",
    "sg:classifiers":[
        {
            "category":"Personal",
            "subcategory":"Beauty Salon",
            "type":"Services"
        }
    ],
    "sg:postcode":"SS0 7LX",
    "sg:province":"Essex",
    "sg:tags":[
        "unisex",
        "hairdresser"
    ],
    "wof:name":"M A",
    "wof:placetype":"venue"
},
  "geometry": {"coordinates":[0.693035,51.538086],"type":"Point"}
}