{
  "type": "Feature",
  "properties": {
    "iso:country":"GB",
    "sg:address":"Bagley Lane, Farsley",
    "sg:city":"Pudsey",
    "sg:classifiers":[
        {
            "category":"Communications",
            "type":"Services"
        }
    ],
    "sg:phone":"+44 113 257 5502",
    "sg:postcode":"LS28 5LY",
    "sg:province":"West Yorkshire",
    "sg:tags":[
        "data",
        "network"
    ],
    "wof:name":"Hi-Tech Group Ltd.",
    "wof:placetype":"venue"
},
  "geometry": {"coordinates":[-1.663828,53.817299],"type":"Point"}
}