{
  "type": "Feature",
  "properties": {
    "iso:country":"GB",
    "sg:address":"Fredrick House, Beam Heath Way",
    "sg:city":"Nantwich",
    "sg:classifiers":[
        {
            "category":"Real Estate",
            "subcategory":"Surveying",
            "type":"Services"
        }
    ],
    "sg:postcode":"CW5 6PQ",
    "sg:province":"Cheshire",
    "sg:tags":[
        "surveyor",
        "quantity"
    ],
    "wof:name":"Specialists Quantity Surveyors",
    "wof:placetype":"venue"
},
  "geometry": {"coordinates":[-2.5158519745,53.0771636963],"type":"Point"}
}