{
  "type": "Feature",
  "properties": {
    "addr:full":"First Floor Abergavenny Herefordshire NP7 5AH",
    "addr:postcode":"np7 5ah",
    "iso:country":"GB",
    "sg:address":"First Floor",
    "sg:city":"Abergavenny",
    "sg:classifiers":[
        {
            "category":"Home & Garden",
            "subcategory":"Home Furnishings",
            "type":"Retail Goods"
        }
    ],
    "sg:phone":"+44 1873 856360",
    "sg:postcode":"NP7 5AH",
    "sg:province":"Herefordshire",
    "sg:tags":[
        "blind",
        "curtain",
        "fitting"
    ],
    "wof:name":"Georgina's",
    "wof:placetype":"venue"
},
  "geometry": {"coordinates":[-3.013649,51.82201],"type":"Point"}
}