{
  "type": "Feature",
  "properties": {
    "addr:full":"102 Notting Hill Gate London Greater London W11 3QA",
    "addr:housenumber":"102",
    "addr:postcode":"w11 3qa",
    "addr:street":"Notting Hill Gate",
    "iso:country":"GB",
    "sg:address":"102 Notting Hill Gate",
    "sg:city":"London",
    "sg:classifiers":[
        {
            "category":"Shopping",
            "subcategory":"Music",
            "type":"Retail Goods"
        }
    ],
    "sg:phone":"+44 20 7229 6796",
    "sg:postcode":"W11 3QA",
    "sg:province":"Greater London",
    "sg:tags":[
        "record",
        "tape",
        "cd"
    ],
    "wof:name":"Our Price",
    "wof:placetype":"venue"
},
  "geometry": {"coordinates":[-0.1972759962,51.5090103149],"type":"Point"}
}