{
  "type": "Feature",
  "properties": {
    "iso:country":"GB",
    "sg:address":"Y Llwyn, Llandrillo",
    "sg:city":"Corwen",
    "sg:classifiers":[
        {
            "category":"Retail",
            "subcategory":"Repair Shop",
            "type":"Services"
        }
    ],
    "sg:postcode":"LL21 0ST",
    "sg:province":"Conwy",
    "sg:tags":[
        "upholsterer"
    ],
    "wof:name":"Eirlys Roberts-Jones",
    "wof:placetype":"venue"
},
  "geometry": {"coordinates":[-3.373668,52.980648],"type":"Point"}
}