{
  "type": "Feature",
  "properties": {
    "iso:country":"GB",
    "sg:address":"55 Stanhope Street",
    "sg:city":"Birmingham",
    "sg:classifiers":[
        {
            "category":"Professional",
            "subcategory":"Engineering",
            "type":"Services"
        }
    ],
    "sg:phone":"+44 121 446 5223",
    "sg:postcode":"B12 0UX",
    "sg:province":"West Midlands",
    "sg:tags":[
        "precision",
        "engineer"
    ],
    "wof:name":"B B W Engineering Co. (Aston) Ltd.",
    "wof:placetype":"venue"
},
  "geometry": {"coordinates":[-1.8874989748,52.4670982361],"type":"Point"}
}