{
  "type": "Feature",
  "properties": {
    "addr:full":"P O Box 24117 London Greater London SW18 5WU",
    "addr:housenumber":"box 24117",
    "addr:postcode":"sw18 5wu",
    "iso:country":"GB",
    "sg:address":"P O Box 24117",
    "sg:city":"London",
    "sg:classifiers":[
        {
            "category":"Real Estate",
            "subcategory":"Real Estate Agent",
            "type":"Services"
        }
    ],
    "sg:phone":"+44 20 8870 2444",
    "sg:postcode":"SW18 5WU",
    "sg:province":"Greater London",
    "wof:name":"Real Estate Direct Ltd.",
    "wof:placetype":"venue"
},
  "geometry": {"coordinates":[-0.20311,51.446201],"type":"Point"}
}