{
  "type": "Feature",
  "properties": {
    "iso:country":"GB",
    "sg:address":"20 Bracken Drive",
    "sg:city":"Chigwell",
    "sg:classifiers":[
        {
            "category":"Military Area",
            "subcategory":"Air Force Base",
            "type":"Public Place"
        }
    ],
    "sg:phone":"+44 20 8500 1960",
    "sg:postcode":"IG7 5RF",
    "sg:province":"Essex",
    "sg:tags":[
        "sanitary"
    ],
    "wof:name":"Essex Vending Hygiene Services",
    "wof:placetype":"venue"
},
  "geometry": {"coordinates":[0.079853,51.608906],"type":"Point"}
}