{
  "type": "Feature",
  "properties": {
    "addr:full":"Unit 15, Shaw Road Liverpool Merseyside L24 9JT",
    "addr:housenumber":"unit 15",
    "addr:postcode":"l24 9jt",
    "addr:street":"Shaw Road",
    "iso:country":"GB",
    "sg:address":"Unit 15, Shaw Road",
    "sg:city":"Liverpool",
    "sg:classifiers":[
        {
            "category":"Shopping",
            "type":"Retail Goods"
        }
    ],
    "sg:phone":"+44 151 448 0900",
    "sg:postcode":"L24 9JT",
    "sg:province":"Merseyside",
    "sg:tags":[
        "part",
        "accessory"
    ],
    "wof:name":"Woodend Car Spares",
    "wof:placetype":"venue"
},
  "geometry": {"coordinates":[-2.8464169502,53.3507919312],"type":"Point"}
}