{
  "type": "Feature",
  "properties": {
    "addr:full":"7 Clarke Close, Irthlingborough Wellingborough Northamptonshire NN9 5XD",
    "addr:housenumber":"7",
    "addr:postcode":"nn9 5xd",
    "addr:street":"Clarke Close",
    "iso:country":"GB",
    "sg:address":"7 Clarke Close, Irthlingborough",
    "sg:city":"Wellingborough",
    "sg:classifiers":[
        {
            "category":"Building & Trades",
            "subcategory":"Construction",
            "type":"Services"
        }
    ],
    "sg:phone":"+44 1933 651205",
    "sg:postcode":"NN9 5XD",
    "sg:province":"Northamptonshire",
    "sg:tags":[
        "contractor",
        "paving",
        "driveway"
    ],
    "wof:name":"Paul Parsons Builders",
    "wof:placetype":"venue"
},
  "geometry": {"coordinates":[-0.598219,52.337109],"type":"Point"}
}