{
  "type": "Feature",
  "properties": {
    "addr:full":"2 Holland Drive, Belgrano Abergele Conwy LL22 9AF",
    "addr:housenumber":"2",
    "addr:postcode":"ll22 9af",
    "addr:street":"Holland Drive",
    "iso:country":"GB",
    "sg:address":"2 Holland Drive, Belgrano",
    "sg:city":"Abergele",
    "sg:classifiers":[
        {
            "category":"Building & Trades",
            "subcategory":"Construction",
            "type":"Services"
        }
    ],
    "sg:phone":"+44 1745 832219",
    "sg:postcode":"LL22 9AF",
    "sg:province":"Conwy",
    "sg:tags":[
        "dry",
        "lining",
        "plasterers",
        "screeders"
    ],
    "wof:name":"Emyr Jones Plastering Contractor",
    "wof:placetype":"venue"
},
  "geometry": {"coordinates":[-3.563314,53.297878],"type":"Point"}
}