{
  "type": "Feature",
  "properties": {
    "iso:country":"GB",
    "sg:address":"64 Northgate",
    "sg:city":"Walsall",
    "sg:classifiers":[
        {
            "category":"Building & Trades",
            "subcategory":"Plumbing",
            "type":"Services"
        }
    ],
    "sg:postcode":"WS9 8BD",
    "sg:province":"Staffordshire",
    "sg:tags":[
        "heating"
    ],
    "wof:name":"Robathan,T,",
    "wof:placetype":"venue"
},
  "geometry": {"coordinates":[-1.92059,52.609776],"type":"Point"}
}