{
  "type": "Feature",
  "properties": {
    "addr:full":"167 Wapping High St, Wapping London Greater London E1 9NQ",
    "addr:housenumber":"167",
    "addr:postcode":"e1 9nq",
    "addr:street":"Wapping High St",
    "iso:country":"GB",
    "sg:address":"167 Wapping High St, Wapping",
    "sg:city":"London",
    "sg:classifiers":[
        {
            "category":"Health Services",
            "subcategory":"Hospital",
            "type":"Services"
        }
    ],
    "sg:postcode":"E1 9NQ",
    "sg:province":"Greater London",
    "wof:name":"Painter,Ivan,",
    "wof:placetype":"venue"
},
  "geometry": {"coordinates":[-0.054594,51.505657],"type":"Point"}
}