{
  "type": "Feature",
  "properties": {
    "iso:country":"GB",
    "sg:address":"19b Kassasin St",
    "sg:city":"Southsea",
    "sg:classifiers":[
        {
            "category":"Retail",
            "subcategory":"Auto Repair",
            "type":"Services"
        }
    ],
    "sg:postcode":"PO4 9PS",
    "sg:province":"Hampshire",
    "sg:tags":[
        "modification",
        "garage"
    ],
    "wof:name":"Walsh,Michael,",
    "wof:placetype":"venue"
},
  "geometry": {"coordinates":[-1.058377,50.785488],"type":"Point"}
}