{
  "type": "Feature",
  "properties": {
    "addr:full":"96-97 Murray Gro London Greater London N1 7QP",
    "addr:housenumber":"96-97",
    "addr:postcode":"n1 7qp",
    "addr:street":"Murray Gro",
    "iso:country":"GB",
    "sg:address":"96-97 Murray Gro",
    "sg:city":"London",
    "sg:classifiers":[
        {
            "category":"Government",
            "subcategory":"Post Office",
            "type":"Public Place"
        }
    ],
    "sg:phone":"+44 20 7253 6909",
    "sg:postcode":"N1 7QP",
    "sg:province":"Greater London",
    "wof:name":"Murray Grove Post Office",
    "wof:placetype":"venue"
},
  "geometry": {"coordinates":[-0.0889659971,51.531036377],"type":"Point"}
}