{
  "type": "Feature",
  "properties": {
    "iso:country":"GB",
    "sg:address":"Beechfield Rd, Fremington",
    "sg:city":"Barnstaple",
    "sg:classifiers":[
        {
            "category":"Food & Beverages",
            "subcategory":"Meat & Fish",
            "type":"Retail Goods"
        }
    ],
    "sg:postcode":"EX31 3DD",
    "sg:province":"Devon",
    "sg:tags":[
        "chip"
    ],
    "wof:name":"Fremington Friar (The)",
    "wof:placetype":"venue"
},
  "geometry": {"coordinates":[-4.124613,51.072178],"type":"Point"}
}