{
  "type": "Feature",
  "properties": {
    "iso:country":"GB",
    "sg:address":"M C L Ho, Adams Clo, Heanor Gate Indstl Est",
    "sg:city":"Heanor",
    "sg:classifiers":[
        {
            "category":"Professional",
            "subcategory":"Engineering",
            "type":"Services"
        }
    ],
    "sg:phone":"+44 1773 710878",
    "sg:postcode":"DE75 7SW",
    "sg:province":"Derbyshire",
    "sg:tags":[
        "civil",
        "engineer"
    ],
    "wof:name":"Titan Building & Civil Engineering Ltd",
    "wof:placetype":"venue"
},
  "geometry": {"coordinates":[-1.353434,53.013737],"type":"Point"}
}