{
  "type": "Feature",
  "properties": {
    "addr:full":"3-5 Alexandra Road Farnborough Hampshire GU14 6BU",
    "addr:housenumber":"3-5",
    "addr:postcode":"gu14 6bu",
    "addr:street":"Alexandra Road",
    "iso:country":"GB",
    "sg:address":"3-5 Alexandra Road",
    "sg:city":"Farnborough",
    "sg:classifiers":[
        {
            "category":"Professional",
            "subcategory":"Employment Agencies",
            "type":"Services"
        }
    ],
    "sg:phone":"+44 1252 517778",
    "sg:postcode":"GU14 6BU",
    "sg:province":"Hampshire",
    "sg:tags":[
        "consultant"
    ],
    "wof:name":"The Accounts Department",
    "wof:placetype":"venue"
},
  "geometry": {"coordinates":[-0.7494350076,51.2746963501],"type":"Point"}
}