{
  "type": "Feature",
  "properties": {
    "iso:country":"GB",
    "sg:address":"Ashton Farm, Stapleford Abbotts",
    "sg:city":"Romford",
    "sg:classifiers":[
        {
            "category":"Manufacturing",
            "subcategory":"Petroleum Products",
            "type":"Manufacturing & Wholesale Goods"
        }
    ],
    "sg:phone":"+44 1708 474805",
    "sg:postcode":"RM4 1JU",
    "sg:province":"Essex",
    "sg:tags":[
        "double",
        "glazing"
    ],
    "wof:name":"Thistle Windows & Conservatories",
    "wof:placetype":"venue"
},
  "geometry": {"coordinates":[0.16912,51.63644],"type":"Point"}
}