{
  "type": "Feature",
  "properties": {
    "iso:country":"GB",
    "sg:address":"Oast House",
    "sg:city":"Cambridge",
    "sg:classifiers":[
        {
            "category":"Real Estate",
            "subcategory":"Architect",
            "type":"Services"
        }
    ],
    "sg:phone":"+44 1223 364777",
    "sg:postcode":"CB3 9HF",
    "sg:province":"Cambridgeshire",
    "wof:name":"David Owers Associates",
    "wof:placetype":"venue"
},
  "geometry": {"coordinates":[0.1115650013,52.2098693848],"type":"Point"}
}