{
  "type": "Feature",
  "properties": {
    "addr:full":"London Road, Rockbeare Exeter Devon EX5 2EP",
    "addr:postcode":"ex5 2ep",
    "addr:street":"London Road",
    "iso:country":"GB",
    "sg:address":"London Road, Rockbeare",
    "sg:city":"Exeter",
    "sg:classifiers":[
        {
            "category":"Train Station",
            "subcategory":"Rail",
            "type":"Transportation"
        }
    ],
    "sg:phone":"+44 1404 823999",
    "sg:postcode":"EX5 2EP",
    "sg:province":"Devon",
    "sg:tags":[
        "caravan"
    ],
    "wof:name":"Devon Caravans Ltd.",
    "wof:placetype":"venue"
},
  "geometry": {"coordinates":[-3.391084,50.746044],"type":"Point"}
}