{
  "type": "Feature",
  "properties": {
    "addr:full":"180 Glendale Gardens Leigh-on-sea Essex SS9 2BA",
    "addr:housenumber":"180",
    "addr:postcode":"ss9 2ba",
    "addr:street":"Glendale Gardens",
    "iso:country":"GB",
    "sg:address":"180 Glendale Gardens",
    "sg:city":"Leigh-on-sea",
    "sg:classifiers":[
        {
            "category":"Building & Trades",
            "subcategory":"Construction",
            "type":"Services"
        }
    ],
    "sg:phone":"+44 1702 712227",
    "sg:postcode":"SS9 2BA",
    "sg:province":"Essex",
    "sg:tags":[
        "roofing"
    ],
    "wof:name":"Delta G B R",
    "wof:placetype":"venue"
},
  "geometry": {"coordinates":[0.646055,51.544704],"type":"Point"}
}