{
  "type": "Feature",
  "properties": {
    "iso:country":"GB",
    "sg:address":"70 Hollyhurst Rd",
    "sg:city":"Sutton Coldfield",
    "sg:classifiers":[
        {
            "category":"Shopping",
            "subcategory":"Clothing, Apparel, & Fashions",
            "type":"Retail Goods"
        }
    ],
    "sg:phone":"+44 121 354 6725",
    "sg:postcode":"B73 6SZ",
    "sg:province":"West Midlands",
    "sg:tags":[
        "shop",
        "hat"
    ],
    "wof:name":"Lady Style",
    "wof:placetype":"venue"
},
  "geometry": {"coordinates":[-1.871868,52.554848],"type":"Point"}
}