{
  "type": "Feature",
  "properties": {
    "addr:full":"16 English Street, Longtown Carlisle Cumbria CA6 5SD",
    "addr:housenumber":"16",
    "addr:postcode":"ca6 5sd",
    "addr:street":"English Street",
    "iso:country":"GB",
    "sg:address":"16 English Street, Longtown",
    "sg:city":"Carlisle",
    "sg:classifiers":[
        {
            "category":"Bars & Pubs",
            "type":"Food & Drink"
        }
    ],
    "sg:postcode":"CA6 5SD",
    "sg:province":"Cumbria",
    "sg:tags":[
        "pubs",
        "inn"
    ],
    "wof:name":"Harold Jobson & Partners Ltd.",
    "wof:placetype":"venue"
},
  "geometry": {"coordinates":[-2.9718511105,55.0082015991],"type":"Point"}
}