{
  "type": "Feature",
  "properties": {
    "addr:full":"Unit M1 Hilton Business Park Chichester West Sussex PO20 8RL",
    "addr:postcode":"po20 8rl",
    "iso:country":"GB",
    "sg:address":"Unit M1 Hilton Business Park",
    "sg:city":"Chichester",
    "sg:classifiers":[
        {
            "category":"Manufacturing",
            "subcategory":"Wood Products",
            "type":"Manufacturing & Wholesale Goods"
        }
    ],
    "sg:phone":"+44 1243 671177",
    "sg:postcode":"PO20 8RL",
    "sg:province":"West Sussex",
    "wof:name":"ITW Chronomatic",
    "wof:placetype":"venue"
},
  "geometry": {"coordinates":[-0.8645920157,50.7737617493],"type":"Point"}
}