{
  "type": "Feature",
  "properties": {
    "iso:country":"GB",
    "sg:address":"241 Church St",
    "sg:city":"Blackpool",
    "sg:classifiers":[
        {
            "category":"Government",
            "subcategory":"Office",
            "type":"Public Place"
        }
    ],
    "sg:phone":"+44 1253 294780",
    "sg:postcode":"FY1 3PB",
    "sg:province":"Lancashire",
    "sg:tags":[
        "central"
    ],
    "wof:name":"Probation Service",
    "wof:placetype":"venue"
},
  "geometry": {"coordinates":[-3.042139,53.818607],"type":"Point"}
}