{
  "type": "Feature",
  "properties": {
    "addr:full":"101-103 Beaver Lane Ashford Kent TN23 5NU",
    "addr:housenumber":"101-103",
    "addr:postcode":"tn23 5nu",
    "addr:street":"Beaver Lane",
    "iso:country":"GB",
    "sg:address":"101-103 Beaver Lane",
    "sg:city":"Ashford",
    "sg:classifiers":[
        {
            "category":"Food & Beverages",
            "subcategory":"Supermarket",
            "type":"Retail Goods"
        }
    ],
    "sg:phone":"+44 1233 628262",
    "sg:postcode":"TN23 5NU",
    "sg:province":"Kent",
    "wof:name":"Costcutter",
    "wof:placetype":"venue"
},
  "geometry": {"coordinates":[0.85441,51.135799],"type":"Point"}
}