{
  "type": "Feature",
  "properties": {
    "addr:full":"30 The Centre Margate Kent CT9 1JG",
    "addr:housenumber":"30",
    "addr:postcode":"ct9 1jg",
    "addr:street":"The Centre Margate",
    "iso:country":"GB",
    "sg:address":"30 The Centre",
    "sg:city":"Margate",
    "sg:classifiers":[
        {
            "category":"Shopping",
            "subcategory":"Gifts & Souvenirs",
            "type":"Retail Goods"
        }
    ],
    "sg:phone":"+44 1843 290233",
    "sg:postcode":"CT9 1JG",
    "sg:province":"Kent",
    "sg:tags":[
        "shop",
        "poster",
        "card"
    ],
    "wof:name":"Celebrations",
    "wof:placetype":"venue"
},
  "geometry": {"coordinates":[1.38351,51.387371],"type":"Point"}
}