{
  "type": "Feature",
  "properties": {
    "iso:country":"GB",
    "sg:address":"South Pier Offices, The Enade Promenade",
    "sg:city":"Blackpool",
    "sg:classifiers":[
        {
            "category":"Community Center",
            "type":"Public Place"
        }
    ],
    "sg:phone":"+44 1253 343097",
    "sg:postcode":"FY4 1BB",
    "sg:province":"Lancashire",
    "sg:tags":[
        "centre",
        "entertainment"
    ],
    "wof:name":"South Pier",
    "wof:placetype":"venue"
},
  "geometry": {"coordinates":[-3.05725,53.79541],"type":"Point"}
}