{
  "type": "Feature",
  "properties": {
    "addr:full":", Pontmorlais Merthyr Tydfil Merthyr Tydfil CF47 8UN",
    "addr:postcode":"cf47 8un",
    "addr:street":"Pontmorlais Merthyr Tydfil",
    "iso:country":"GB",
    "sg:address":", Pontmorlais",
    "sg:city":"Merthyr Tydfil",
    "sg:classifiers":[
        {
            "category":"Bars & Pubs",
            "type":"Food & Drink"
        }
    ],
    "sg:phone":"+44 1685 722530",
    "sg:postcode":"CF47 8UN",
    "sg:province":"Merthyr Tydfil",
    "sg:tags":[
        "pubs",
        "inn"
    ],
    "wof:name":"Penydarren End Inn",
    "wof:placetype":"venue"
},
  "geometry": {"coordinates":[-3.376464,51.750439],"type":"Point"}
}