{
  "type": "Feature",
  "properties": {
    "iso:country":"GB",
    "sg:address":"34 Chertsey Road, Chobham",
    "sg:city":"Woking",
    "sg:classifiers":[
        {
            "category":"Fast Food",
            "type":"Food & Drink"
        },
        {
            "category":"Food & Beverages",
            "subcategory":"Meat & Fish",
            "type":"Retail Goods"
        },
        {
            "category":"Food & Beverages",
            "subcategory":"Groceries & Convenience Stores",
            "type":"Retail Goods"
        }
    ],
    "sg:phone":"+44 1276 858086",
    "sg:postcode":"GU24 8PQ",
    "sg:province":"Surrey",
    "sg:tags":[
        "shop",
        "away",
        "take",
        "chip"
    ],
    "wof:name":"Derelis Fish Bar",
    "wof:placetype":"venue"
},
  "geometry": {"coordinates":[-0.5982310176,51.3499259949],"type":"Point"}
}