{
  "type": "Feature",
  "properties": {
    "addr:full":"Stonehurst, Long Clo Salisbury Dorset SP5 3HG",
    "addr:postcode":"sp5 3hg",
    "addr:street":"Dorset",
    "iso:country":"GB",
    "sg:address":"Stonehurst, Long Clo",
    "sg:city":"Salisbury",
    "sg:classifiers":[
        {
            "category":"Health Services",
            "subcategory":"Dentist",
            "type":"Services"
        }
    ],
    "sg:phone":"+44 1725 510554",
    "sg:postcode":"SP5 3HG",
    "sg:province":"Dorset",
    "wof:name":"C J Sprawson",
    "wof:placetype":"venue"
},
  "geometry": {"coordinates":[-1.75581,50.993439],"type":"Point"}
}