{
  "type": "Feature",
  "properties": {
    "addr:full":"8a Church St, Blantyre Glasgow South Lanarkshire G72 0NY",
    "addr:housenumber":"8a",
    "addr:postcode":"g72 0ny",
    "addr:street":"Church St",
    "iso:country":"GB",
    "sg:address":"8a Church St, Blantyre",
    "sg:city":"Glasgow",
    "sg:classifiers":[
        {
            "category":"Health Services",
            "subcategory":"Health Practitioner",
            "type":"Services"
        }
    ],
    "sg:phone":"+44 1698 829742",
    "sg:postcode":"G72 0NY",
    "sg:province":"South Lanarkshire",
    "sg:tags":[
        "therapist",
        "speech"
    ],
    "wof:name":"Anne Penman Laser Therapy Centre",
    "wof:placetype":"venue"
},
  "geometry": {"coordinates":[-4.0857830048,55.7920150757],"type":"Point"}
}