{
  "type": "Feature",
  "properties": {
    "iso:country":"GB",
    "sg:address":"Runcorn Road, Balsall Heath",
    "sg:city":"Birmingham",
    "sg:classifiers":[
        {
            "category":"Professional",
            "subcategory":"Art Services",
            "type":"Services"
        }
    ],
    "sg:phone":"+44 121 442 2073",
    "sg:postcode":"B12 8QP",
    "sg:province":"West Midlands",
    "sg:tags":[
        "glass",
        "engraver"
    ],
    "wof:name":"The Glassworks Limited",
    "wof:placetype":"venue"
},
  "geometry": {"coordinates":[-1.884656,52.455498],"type":"Point"}
}