{
  "type": "Feature",
  "properties": {
    "addr:full":"22 Chapel High Brentwood Essex CM14 4BX",
    "addr:housenumber":"22",
    "addr:postcode":"cm14 4bx",
    "addr:street":"Chapel High",
    "iso:country":"GB",
    "sg:address":"22 Chapel High",
    "sg:city":"Brentwood",
    "sg:classifiers":[
        {
            "category":"Communications",
            "type":"Services"
        }
    ],
    "sg:phone":"+44 1277 218227",
    "sg:postcode":"CM14 4BX",
    "sg:province":"Essex",
    "sg:tags":[
        "telecommunication"
    ],
    "wof:name":"WirelessWorld",
    "wof:placetype":"venue"
},
  "geometry": {"coordinates":[0.3028340042,51.6204452515],"type":"Point"}
}