{
  "type": "Feature",
  "properties": {
    "addr:full":"76 Summerwood Lane, Clifton Nottingham Nottinghamshire NG11 9FY",
    "addr:housenumber":"76",
    "addr:postcode":"ng11 9fy",
    "addr:street":"Summerwood Lane",
    "iso:country":"GB",
    "sg:address":"76 Summerwood Lane, Clifton",
    "sg:city":"Nottingham",
    "sg:classifiers":[
        {
            "category":"Building & Trades",
            "subcategory":"Plumbing",
            "type":"Services"
        }
    ],
    "sg:phone":"+44 115 984 1297",
    "sg:postcode":"NG11 9FY",
    "sg:province":"Nottinghamshire",
    "sg:tags":[
        "shower",
        "accessory"
    ],
    "wof:name":"R.B Shower Services",
    "wof:placetype":"venue"
},
  "geometry": {"coordinates":[-1.1879550219,52.8943634033],"type":"Point"}
}