{
  "type": "Feature",
  "properties": {
    "iso:country":"GB",
    "sg:address":"56-62 High St",
    "sg:city":"Clacton On Sea",
    "sg:classifiers":[
        {
            "category":"Autos & Motor Vehicles",
            "subcategory":"Automobile Sales",
            "type":"Retail Goods"
        }
    ],
    "sg:phone":"+44 1255 222322",
    "sg:postcode":"CO15 6PW",
    "sg:province":"Essex",
    "sg:tags":[
        "commercial"
    ],
    "wof:name":"Primacars Ltd",
    "wof:placetype":"venue"
},
  "geometry": {"coordinates":[1.156818,51.790985],"type":"Point"}
}