{
  "type": "Feature",
  "properties": {
    "iso:country":"GB",
    "sg:address":"90 High St",
    "sg:city":"Brierley Hill",
    "sg:classifiers":[
        {
            "category":"Retail",
            "subcategory":"Repair Shop",
            "type":"Services"
        }
    ],
    "sg:phone":"+44 1384 634362",
    "sg:postcode":"DY5 2AD",
    "sg:province":"West Midlands",
    "sg:tags":[
        "upholsterer"
    ],
    "wof:name":"J & B",
    "wof:placetype":"venue"
},
  "geometry": {"coordinates":[-2.1029100418,52.4720573425],"type":"Point"}
}