{
  "type": "Feature",
  "properties": {
    "iso:country":"GB",
    "sg:address":"Brown Lane, Coal Aston",
    "sg:city":"Dronfield",
    "sg:classifiers":[
        {
            "category":"Bars & Pubs",
            "type":"Food & Drink"
        }
    ],
    "sg:phone":"+44 1246 412728",
    "sg:postcode":"S18 3AJ",
    "sg:province":"Derbyshire",
    "sg:tags":[
        "pubs",
        "inn"
    ],
    "wof:name":"The Cross Daggers",
    "wof:placetype":"venue"
},
  "geometry": {"coordinates":[-1.4601789713,53.3110923767],"type":"Point"}
}