{
  "type": "Feature",
  "properties": {
    "iso:country":"GB",
    "sg:address":"Kendall Yard, Ash Church Road",
    "sg:city":"Aldershot",
    "sg:classifiers":[
        {
            "category":"Taxi",
            "type":"Transportation"
        },
        {
            "category":"Military Area",
            "subcategory":"Air Force Base",
            "type":"Public Place"
        }
    ],
    "sg:postcode":"GU12 6LX",
    "sg:province":"Hampshire",
    "sg:tags":[
        "mini",
        "hire",
        "private",
        "cab"
    ],
    "wof:name":"Barry Hill",
    "wof:placetype":"venue"
},
  "geometry": {"coordinates":[-0.75934,51.249599],"type":"Point"}
}