{
  "type": "Feature",
  "properties": {
    "iso:country":"GB",
    "sg:address":"The Parade",
    "sg:city":"Chester",
    "sg:classifiers":[
        {
            "category":"Shopping",
            "subcategory":"Department Store",
            "type":"Retail Goods"
        }
    ],
    "sg:phone":"+44 1244 390479",
    "sg:postcode":"CH1 5HW",
    "sg:province":"Cheshire",
    "wof:name":"The Spar",
    "wof:placetype":"venue"
},
  "geometry": {"coordinates":[-2.926848,53.208355],"type":"Point"}
}