{
  "type": "Feature",
  "properties": {
    "addr:full":"Unit 2-4, Limes Court, Conduit Lane Hoddesdon Essex EN11 8EP",
    "addr:housenumber":"unit 2-4",
    "addr:postcode":"en11 8ep",
    "addr:street":"Limes Court Conduit Lane",
    "iso:country":"GB",
    "sg:address":"Unit 2-4, Limes Court, Conduit Lane",
    "sg:city":"Hoddesdon",
    "sg:classifiers":[
        {
            "category":"Professional",
            "subcategory":"Art Services",
            "type":"Services"
        }
    ],
    "sg:phone":"+44 1992 442285",
    "sg:postcode":"EN11 8EP",
    "sg:province":"Essex",
    "sg:tags":[
        "graphic",
        "designer"
    ],
    "wof:name":"Renown Marketing Solutions",
    "wof:placetype":"venue"
},
  "geometry": {"coordinates":[-0.010295,51.759048],"type":"Point"}
}