{
  "type": "Feature",
  "properties": {
    "iso:country":"GB",
    "sg:address":"81 Haverstock Hill",
    "sg:city":"London",
    "sg:classifiers":[
        {
            "category":"Shopping",
            "subcategory":"Antiques",
            "type":"Retail Goods"
        }
    ],
    "sg:phone":"+44 20 7835 2202",
    "sg:postcode":"NW3 4SL",
    "sg:province":"Greater London",
    "wof:name":"Nine Schools",
    "wof:placetype":"venue"
},
  "geometry": {"coordinates":[-0.157916,51.546501],"type":"Point"}
}