{
  "type": "Feature",
  "properties": {
    "addr:full":"Hemscott Hill, Widdrington Morpeth Northumberland NE61 5EQ",
    "addr:postcode":"ne61 5eq",
    "addr:street":"Hemscott;Northumberland",
    "iso:country":"GB",
    "sg:address":"Hemscott Hill, Widdrington",
    "sg:city":"Morpeth",
    "sg:classifiers":[
        {
            "category":"Farming",
            "subcategory":"Farm",
            "type":"Manufacturing & Wholesale Goods"
        }
    ],
    "sg:phone":"+44 1670 860254",
    "sg:postcode":"NE61 5EQ",
    "sg:province":"Northumberland",
    "sg:tags":[
        "mixed",
        "crop"
    ],
    "wof:name":"William Bell",
    "wof:placetype":"venue"
},
  "geometry": {"coordinates":[-1.6169990301,55.2415008545],"type":"Point"}
}