{
  "type": "Feature",
  "properties": {
    "iso:country":"GB",
    "sg:address":"271 Pickersleigh Road",
    "sg:city":"Malvern",
    "sg:classifiers":[
        {
            "category":"Food & Beverages",
            "subcategory":"Meat & Fish",
            "type":"Retail Goods"
        }
    ],
    "sg:phone":"+44 1684 573778",
    "sg:postcode":"WR14 2QS",
    "sg:province":"Herefordshire",
    "sg:tags":[
        "chip"
    ],
    "wof:name":"The Golden Fry",
    "wof:placetype":"venue"
},
  "geometry": {"coordinates":[-2.309876,52.114822],"type":"Point"}
}