{
  "type": "Feature",
  "properties": {
    "addr:full":"1 Abacus House Corsham Wiltshire SN13 0BH",
    "addr:housenumber":"1",
    "addr:postcode":"sn13 0bh",
    "addr:street":"Corsham",
    "iso:country":"GB",
    "sg:address":"1 Abacus House",
    "sg:city":"Corsham",
    "sg:classifiers":[
        {
            "category":"Professional",
            "subcategory":"Accounting & Tax Preparation",
            "type":"Services"
        }
    ],
    "sg:phone":"+44 1249 712074",
    "sg:postcode":"SN13 0BH",
    "sg:province":"Wiltshire",
    "sg:tags":[
        "accountant"
    ],
    "wof:name":"Robson Taylor",
    "wof:placetype":"venue"
},
  "geometry": {"coordinates":[-2.1872389317,51.4314842224],"type":"Point"}
}