{
  "type": "Feature",
  "properties": {
    "addr:full":"49 Witney Road, Eynsham Witney Oxfordshire OX29 4PL",
    "addr:housenumber":"49",
    "addr:postcode":"ox29 4pl",
    "addr:street":"Witney Road",
    "iso:country":"GB",
    "sg:address":"49 Witney Road, Eynsham",
    "sg:city":"Witney",
    "sg:classifiers":[
        {
            "category":"Travel",
            "subcategory":"Hotels & Motels",
            "type":"Entertainment"
        }
    ],
    "sg:postcode":"OX29 4PL",
    "sg:province":"Oxfordshire",
    "sg:tags":[
        "house",
        "guest"
    ],
    "wof:name":"Parkview",
    "wof:placetype":"venue"
},
  "geometry": {"coordinates":[-1.3824050426,51.7843055725],"type":"Point"}
}