{
  "type": "Feature",
  "properties": {
    "iso:country":"GB",
    "sg:address":"37 Gautrey Road",
    "sg:city":"London",
    "sg:classifiers":[
        {
            "category":"Ice Cream",
            "type":"Food & Drink"
        }
    ],
    "sg:phone":"+44 20 7639 9906",
    "sg:postcode":"SE15 2JE",
    "sg:province":"Greater London",
    "sg:tags":[
        "mnfr"
    ],
    "wof:name":"C & U",
    "wof:placetype":"venue"
},
  "geometry": {"coordinates":[-0.052256,51.469421],"type":"Point"}
}