{
  "type": "Feature",
  "properties": {
    "addr:full":"42 Arwenack St Falmouth Cornwall TR11 3JH",
    "addr:housenumber":"42",
    "addr:postcode":"tr11 3jh",
    "addr:street":"Arwenack St",
    "iso:country":"GB",
    "sg:address":"42 Arwenack St",
    "sg:city":"Falmouth",
    "sg:classifiers":[
        {
            "category":"Real Estate",
            "subcategory":"Real Estate Agent",
            "type":"Services"
        }
    ],
    "sg:phone":"+44 1326 313141",
    "sg:postcode":"TR11 3JH",
    "sg:province":"Cornwall",
    "wof:name":"Holmes & Jardin",
    "wof:placetype":"venue"
},
  "geometry": {"coordinates":[-5.066115,50.152229],"type":"Point"}
}