{
  "type": "Feature",
  "properties": {
    "addr:full":"14 Capon Hill Brampton Cumbria CA8 1QJ",
    "addr:housenumber":"14",
    "addr:postcode":"ca8 1qj",
    "addr:street":"Capon Hill",
    "iso:country":"GB",
    "sg:address":"14 Capon Hill",
    "sg:city":"Brampton",
    "sg:classifiers":[
        {
            "category":"Sports & Exercise",
            "subcategory":"Bicycle Rental",
            "type":"Entertainment"
        }
    ],
    "sg:phone":"+44 16977 2458",
    "sg:postcode":"CA8 1QJ",
    "sg:province":"Cumbria",
    "sg:tags":[
        "renting",
        "cycle"
    ],
    "wof:name":"Bentleys Border Bikes",
    "wof:placetype":"venue"
},
  "geometry": {"coordinates":[-2.730909,54.933899],"type":"Point"}
}