{
  "type": "Feature",
  "properties": {
    "addr:full":"Firstlings, Heybridge Vicarage Maldon Essex CM9 4NB",
    "addr:postcode":"cm9 4nb",
    "iso:country":"GB",
    "sg:address":"Firstlings, Heybridge Vicarage",
    "sg:city":"Maldon",
    "sg:classifiers":[
        {
            "category":"Social Services",
            "subcategory":"Retirement Home",
            "type":"Services"
        }
    ],
    "sg:phone":"+44 1621 853747",
    "sg:postcode":"CM9 4NB",
    "sg:province":"Essex",
    "sg:tags":[
        "rest"
    ],
    "wof:name":"Firstlings Ltd.",
    "wof:placetype":"venue"
},
  "geometry": {"coordinates":[0.692628026,51.7405929565],"type":"Point"}
}