{
  "type": "Feature",
  "properties": {
    "iso:country":"GB",
    "sg:address":"Unit B, Great Blakenham Trading Estate",
    "sg:city":"Ipswich",
    "sg:classifiers":[
        {
            "category":"Building & Trades",
            "subcategory":"Cleaning & Sanitation",
            "type":"Services"
        }
    ],
    "sg:phone":"+44 1473 831360",
    "sg:postcode":"IP4 4PS",
    "sg:province":"Suffolk",
    "sg:tags":[
        "hygiene",
        "cleansing"
    ],
    "wof:name":"Industrial Supplies (Peterborough) Ltd.",
    "wof:placetype":"venue"
},
  "geometry": {"coordinates":[1.18465,52.061378],"type":"Point"}
}