{
  "type": "Feature",
  "properties": {
    "iso:country":"GB",
    "sg:address":"36a Stenson Rd",
    "sg:city":"Derby",
    "sg:classifiers":[
        {
            "category":"Cafe",
            "type":"Food & Drink"
        }
    ],
    "sg:postcode":"DE23 7JB",
    "sg:province":"Derbyshire",
    "sg:tags":[
        "tea",
        "room"
    ],
    "wof:name":"Parkinson,Andrew,",
    "wof:placetype":"venue"
},
  "geometry": {"coordinates":[-1.486382,52.902218],"type":"Point"}
}