{
  "type": "Feature",
  "properties": {
    "iso:country":"GB",
    "sg:address":"Friston Business Centre, Aldeburgh Road, Friston",
    "sg:city":"Saxmundham",
    "sg:classifiers":[
        {
            "category":"Professional",
            "subcategory":"Management & Consulting",
            "type":"Services"
        },
        {
            "category":"Professional",
            "subcategory":"Employment Agencies",
            "type":"Services"
        }
    ],
    "sg:phone":"+44 1728 688770",
    "sg:postcode":"IP17 1NP",
    "sg:province":"Suffolk",
    "sg:tags":[
        "consultant",
        "business"
    ],
    "wof:name":"Project Assignment Ltd.",
    "wof:placetype":"venue"
},
  "geometry": {"coordinates":[1.4895329475,52.2167129517],"type":"Point"}
}