{
  "type": "Feature",
  "properties": {
    "iso:country":"GB",
    "sg:address":"Carriden Industrial Estate",
    "sg:city":"Bo'ness",
    "sg:classifiers":[
        {
            "category":"Professional",
            "type":"Services"
        }
    ],
    "sg:phone":"+44 1506 827693",
    "sg:postcode":"EH51 9SF",
    "sg:province":"Falkirk",
    "sg:tags":[
        "valuer",
        "auctioneer"
    ],
    "wof:name":"D J MANNING",
    "wof:placetype":"venue"
},
  "geometry": {"coordinates":[-3.5720000267,56.0149612427],"type":"Point"}
}