{
  "type": "Feature",
  "properties": {
    "iso:country":"GB",
    "sg:address":"Prospect House, 32 Sovereign Street",
    "sg:city":"Leeds",
    "sg:classifiers":[
        {
            "category":"Professional",
            "subcategory":"Employment Agencies",
            "type":"Services"
        }
    ],
    "sg:phone":"+44 113 245 4448",
    "sg:postcode":"LS1 4BJ",
    "sg:province":"West Yorkshire",
    "sg:tags":[
        "consultant"
    ],
    "wof:name":"Professional Preselection Services",
    "wof:placetype":"venue"
},
  "geometry": {"coordinates":[-1.543122,53.793972],"type":"Point"}
}