{
  "type": "Feature",
  "properties": {
    "addr:full":"Wick Lane Christchurch Dorset BH23 1HX",
    "addr:postcode":"bh23 1hx",
    "addr:street":"Wick Lane",
    "iso:country":"GB",
    "sg:address":"Wick Lane",
    "sg:city":"Christchurch",
    "sg:classifiers":[
        {
            "category":"Education",
            "subcategory":"School",
            "type":"Public Place"
        }
    ],
    "sg:phone":"+44 1202 484105",
    "sg:postcode":"BH23 1HX",
    "sg:province":"Dorset",
    "sg:tags":[
        "local",
        "authority"
    ],
    "wof:name":"The Priory C of E Primary School",
    "wof:placetype":"venue"
},
  "geometry": {"coordinates":[-1.7778069973,50.7327461243],"type":"Point"}
}