{
  "type": "Feature",
  "properties": {
    "iso:country":"GB",
    "sg:address":"Sheephouse Farm, Reading Road",
    "sg:city":"Henley-on-thames",
    "sg:classifiers":[
        {
            "category":"Farming",
            "subcategory":"Livestock Farm",
            "type":"Manufacturing & Wholesale Goods"
        }
    ],
    "sg:postcode":"RG9 4HF",
    "sg:province":"Berkshire",
    "sg:tags":[
        "others"
    ],
    "wof:name":"Robert E Hopper",
    "wof:placetype":"venue"
},
  "geometry": {"coordinates":[-0.903189,51.535297],"type":"Point"}
}