{
  "type": "Feature",
  "properties": {
    "iso:country":"GB",
    "sg:address":"Blandford Square",
    "sg:city":"Newcastle Upon Tyne",
    "sg:classifiers":[
        {
            "category":"Home & Garden",
            "subcategory":"Household Appliances",
            "type":"Retail Goods"
        }
    ],
    "sg:phone":"+44 191 232 0200",
    "sg:postcode":"NE99 1UY",
    "sg:province":"Tyne and Wear",
    "sg:tags":[
        "electrical"
    ],
    "wof:name":"C W S Engineers",
    "wof:placetype":"venue"
},
  "geometry": {"coordinates":[-1.6157699823,54.9677009583],"type":"Point"}
}