{
  "type": "Feature",
  "properties": {
    "addr:full":"13 Harvey Crescent, Warsash Southampton Hampshire SO31 9TA",
    "addr:housenumber":"13",
    "addr:postcode":"so31 9ta",
    "addr:street":"Harvey Crescent",
    "iso:country":"GB",
    "sg:address":"13 Harvey Crescent, Warsash",
    "sg:city":"Southampton",
    "sg:classifiers":[
        {
            "category":"Autos & Motor Vehicles",
            "subcategory":"Boat Sales",
            "type":"Retail Goods"
        }
    ],
    "sg:phone":"+44 1489 580580",
    "sg:postcode":"SO31 9TA",
    "sg:province":"Hampshire",
    "sg:tags":[
        "repair",
        "builder"
    ],
    "wof:name":"B L T Ltd.",
    "wof:placetype":"venue"
},
  "geometry": {"coordinates":[-1.2790449858,50.8563117981],"type":"Point"}
}