{
  "type": "Feature",
  "properties": {
    "iso:country":"GB",
    "sg:address":"83 Kimberley Rd",
    "sg:city":"Bournemouth",
    "sg:classifiers":[
        {
            "category":"Shopping",
            "subcategory":"Department Store",
            "type":"Retail Goods"
        }
    ],
    "sg:postcode":"BH6 5DE",
    "sg:province":"Dorset",
    "wof:name":"Buck,David,",
    "wof:placetype":"venue"
},
  "geometry": {"coordinates":[-1.809942,50.730015],"type":"Point"}
}