{
  "type": "Feature",
  "properties": {
    "iso:country":"GB",
    "sg:address":"33 Fortis Green Road, Muswell Hill",
    "sg:city":"London",
    "sg:classifiers":[
        {
            "category":"Shopping",
            "subcategory":"Luggage & Leather Goods",
            "type":"Retail Goods"
        }
    ],
    "sg:phone":"+44 20 8883 7990",
    "sg:postcode":"N10 3HP",
    "sg:province":"Greater London",
    "sg:tags":[
        "shop",
        "leathergoods"
    ],
    "wof:name":"Shimco",
    "wof:placetype":"venue"
},
  "geometry": {"coordinates":[-0.146366,51.589939],"type":"Point"}
}