{
  "type": "Feature",
  "properties": {
    "iso:country":"GB",
    "sg:address":"First Floor, Chancellor Ct, 21 The Calls",
    "sg:city":"Leeds",
    "sg:classifiers":[
        {
            "category":"Shopping",
            "subcategory":"Mobile Phones",
            "type":"Retail Goods"
        }
    ],
    "sg:phone":"+44 113 236 6800",
    "sg:postcode":"LS2 7EH",
    "sg:province":"West Yorkshire",
    "wof:name":"Cellnet Ltd",
    "wof:placetype":"venue"
},
  "geometry": {"coordinates":[-1.5400600433,53.7951698303],"type":"Point"}
}