{
  "type": "Feature",
  "properties": {
    "addr:full":"95 Hatfield Road St Albans Hertfordshire AL1 4JL",
    "addr:housenumber":"95",
    "addr:postcode":"al1 4jl",
    "addr:street":"Hatfield Road",
    "iso:country":"GB",
    "sg:address":"95 Hatfield Road",
    "sg:city":"St Albans",
    "sg:classifiers":[
        {
            "category":"Food & Beverages",
            "subcategory":"Groceries & Convenience Stores",
            "type":"Retail Goods"
        }
    ],
    "sg:phone":"+44 1727 847607",
    "sg:postcode":"AL1 4JL",
    "sg:province":"Hertfordshire",
    "wof:name":"Madina General Store",
    "wof:placetype":"venue"
},
  "geometry": {"coordinates":[-0.320451,51.752308],"type":"Point"}
}