{
  "type": "Feature",
  "properties": {
    "addr:full":"15 School Wynd Kirriemuir Angus DD8 4BQ",
    "addr:housenumber":"15",
    "addr:postcode":"dd8 4bq",
    "addr:street":"School Wynd",
    "iso:country":"GB",
    "sg:address":"15 School Wynd",
    "sg:city":"Kirriemuir",
    "sg:classifiers":[
        {
            "category":"Taxi",
            "type":"Transportation"
        }
    ],
    "sg:phone":"+44 1575 573744",
    "sg:postcode":"DD8 4BQ",
    "sg:province":"Angus",
    "sg:tags":[
        "mini",
        "cab"
    ],
    "wof:name":"K Cabs",
    "wof:placetype":"venue"
},
  "geometry": {"coordinates":[-3.011468,56.691925],"type":"Point"}
}