{
  "type": "Feature",
  "properties": {
    "addr:full":"202 The Broadway London Greater London NW9 7EE",
    "addr:housenumber":"202",
    "addr:postcode":"nw9 7ee",
    "addr:street":"The Broadway",
    "iso:country":"GB",
    "sg:address":"202 The Broadway",
    "sg:city":"London",
    "sg:classifiers":[
        {
            "category":"Recreation",
            "subcategory":"Fishing",
            "type":"Entertainment"
        }
    ],
    "sg:phone":"+44 20 8202 0264",
    "sg:postcode":"NW9 7EE",
    "sg:province":"Greater London",
    "sg:tags":[
        "angling"
    ],
    "wof:name":"Frames",
    "wof:placetype":"venue"
},
  "geometry": {"coordinates":[-0.2389400005,51.577091217],"type":"Point"}
}