{
  "type": "Feature",
  "properties": {
    "iso:country":"GB",
    "sg:address":"Marshlands Road",
    "sg:city":"Portsmouth",
    "sg:classifiers":[
        {
            "category":"Manufacturing",
            "subcategory":"Metals",
            "type":"Manufacturing & Wholesale Goods"
        }
    ],
    "sg:phone":"+44 23 9221 9260",
    "sg:postcode":"PO6 1ST",
    "sg:province":"Hampshire",
    "sg:tags":[
        "work",
        "sheet"
    ],
    "wof:name":"Production & Development Services Ltd.",
    "wof:placetype":"venue"
},
  "geometry": {"coordinates":[-1.03563,50.841789],"type":"Point"}
}