{
  "type": "Feature",
  "properties": {
    "iso:country":"GB",
    "sg:address":"12 Hall Gro",
    "sg:city":"Welwyn Garden City",
    "sg:classifiers":[
        {
            "category":"Shopping",
            "subcategory":"Department Store",
            "type":"Retail Goods"
        }
    ],
    "sg:phone":"+44 1707 334462",
    "sg:postcode":"AL7 4PH",
    "sg:province":"Hertfordshire",
    "wof:name":"Gerald Esmund",
    "wof:placetype":"venue"
},
  "geometry": {"coordinates":[-0.180328995,51.7892456055],"type":"Point"}
}