{
  "type": "Feature",
  "properties": {
    "iso:country":"GB",
    "sg:address":"109 South Rd",
    "sg:city":"South Ockendon",
    "sg:classifiers":[
        {
            "category":"Food & Beverages",
            "subcategory":"Liquor & Beverages",
            "type":"Retail Goods"
        }
    ],
    "sg:postcode":"RM15 6NP",
    "sg:province":"Essex",
    "sg:tags":[
        "beer",
        "spirit",
        "wines"
    ],
    "wof:name":"Singh,Amrik,",
    "wof:placetype":"venue"
},
  "geometry": {"coordinates":[0.2941659987,51.5178642273],"type":"Point"}
}