{
  "type": "Feature",
  "properties": {
    "iso:country":"GB",
    "sg:address":"Crewe Hall Industrial Estate, Weston Road",
    "sg:city":"Crewe",
    "sg:classifiers":[
        {
            "category":"Wholesale",
            "subcategory":"Scrap",
            "type":"Manufacturing & Wholesale Goods"
        }
    ],
    "sg:postcode":"CW1 6UB",
    "sg:province":"Cheshire",
    "sg:tags":[
        "waste",
        "metal"
    ],
    "wof:name":"J W Plastic Services",
    "wof:placetype":"venue"
},
  "geometry": {"coordinates":[-2.429444,53.08802],"type":"Point"}
}