{
  "type": "Feature",
  "properties": {
    "addr:full":"296 Broadway Bexleyheath Kent DA6 8AJ",
    "addr:housenumber":"296",
    "addr:postcode":"da6 8aj",
    "addr:street":"Broadway",
    "iso:country":"GB",
    "sg:address":"296 Broadway",
    "sg:city":"Bexleyheath",
    "sg:classifiers":[
        {
            "category":"Professional",
            "subcategory":"Detective & Security Services",
            "type":"Services"
        }
    ],
    "sg:postcode":"DA6 8AJ",
    "sg:province":"Kent",
    "sg:tags":[
        "car"
    ],
    "wof:name":"Diamond Security Ltd.",
    "wof:placetype":"venue"
},
  "geometry": {"coordinates":[0.134072,51.458164],"type":"Point"}
}