{
  "type": "Feature",
  "properties": {
    "iso:country":"GB",
    "sg:address":"Marlborough Court, 14-18 Holborn",
    "sg:city":"London",
    "sg:classifiers":[
        {
            "category":"Manufacturing",
            "subcategory":"Metals",
            "type":"Manufacturing & Wholesale Goods"
        },
        {
            "category":"Government",
            "subcategory":"Post Office",
            "type":"Public Place"
        }
    ],
    "sg:phone":"+44 20 7404 2401",
    "sg:postcode":"EC1N 2LE",
    "sg:province":"Greater London",
    "sg:tags":[
        "steel",
        "mnfrs",
        "organisation",
        "soc",
        "research"
    ],
    "wof:name":"Kobe Steel Europe Ltd.",
    "wof:placetype":"venue"
},
  "geometry": {"coordinates":[-0.199049,51.494888],"type":"Point"}
}