{
  "type": "Feature",
  "properties": {
    "addr:full":"87a Wellesley Rd, Chiswick London Greater London W4 3AT",
    "addr:housenumber":"87a",
    "addr:postcode":"w4 3at",
    "addr:street":"Wellesley Rd",
    "iso:country":"GB",
    "sg:address":"87a Wellesley Rd, Chiswick",
    "sg:city":"London",
    "sg:classifiers":[
        {
            "category":"Autos & Motor Vehicles",
            "subcategory":"Auto Supplies",
            "type":"Retail Goods"
        },
        {
            "category":"Professional",
            "subcategory":"Detective & Security Services",
            "type":"Services"
        }
    ],
    "sg:postcode":"W4 3AT",
    "sg:province":"Greater London",
    "sg:tags":[
        "car",
        "audio"
    ],
    "wof:name":"Wiffen,Lee,",
    "wof:placetype":"venue"
},
  "geometry": {"coordinates":[-0.2841399908,51.4901428223],"type":"Point"}
}