{
  "type": "Feature",
  "properties": {
    "iso:country":"GB",
    "sg:address":"159 Heywood Road, Castleton",
    "sg:city":"Rochdale",
    "sg:classifiers":[
        {
            "category":"Professional",
            "subcategory":"Engineering",
            "type":"Services"
        }
    ],
    "sg:postcode":"OL11 3BS",
    "sg:province":"Lancashire",
    "sg:tags":[
        "engineer",
        "structural"
    ],
    "wof:name":"David W Hill & Associates Ltd.",
    "wof:placetype":"venue"
},
  "geometry": {"coordinates":[-2.1864910126,53.591003418],"type":"Point"}
}