{
  "type": "Feature",
  "properties": {
    "iso:country":"GB",
    "sg:address":"22 Station Road",
    "sg:city":"Hinckley",
    "sg:classifiers":[
        {
            "category":"Government",
            "subcategory":"Post Office",
            "type":"Public Place"
        }
    ],
    "sg:phone":"+44 845 722 3344",
    "sg:postcode":"LE10 1BA",
    "sg:province":"Leicestershire",
    "wof:name":"Post Office Ltd.",
    "wof:placetype":"venue"
},
  "geometry": {"coordinates":[-1.372973,52.539703],"type":"Point"}
}