{
  "type": "Feature",
  "properties": {
    "addr:full":"5 Spendlove Centre, Enstone Road, Charlbury Chipping Norton Gloucestershire OX7 3PQ",
    "addr:housenumber":"5;norton",
    "addr:postcode":"ox7 3pq",
    "addr:street":"Spendlove Centre Enstone Road",
    "iso:country":"GB",
    "sg:address":"5 Spendlove Centre, Enstone Road, Charlbury",
    "sg:city":"Chipping Norton",
    "sg:classifiers":[
        {
            "category":"Shopping",
            "subcategory":"Pharmacy",
            "type":"Retail Goods"
        }
    ],
    "sg:phone":"+44 1608 810019",
    "sg:postcode":"OX7 3PQ",
    "sg:province":"Gloucestershire",
    "sg:tags":[
        "medicine",
        "therapy"
    ],
    "wof:name":"Charlbury Natural Health Clinic",
    "wof:placetype":"venue"
},
  "geometry": {"coordinates":[-1.4756430387,51.8729782104],"type":"Point"}
}