{
  "type": "Feature",
  "properties": {
    "iso:country":"GB",
    "sg:address":"21-23 High St",
    "sg:city":"Ramsgate",
    "sg:classifiers":[
        {
            "category":"Shopping",
            "subcategory":"Clothing, Apparel, & Fashions",
            "type":"Retail Goods"
        }
    ],
    "sg:phone":"+44 1843 585205",
    "sg:postcode":"CT11 9AG",
    "sg:province":"Kent",
    "sg:tags":[
        "shop"
    ],
    "wof:name":"Tammy Girl",
    "wof:placetype":"venue"
},
  "geometry": {"coordinates":[1.4191730022,51.3341941833],"type":"Point"}
}