{
  "type": "Feature",
  "properties": {
    "addr:full":"45 Comberton Road Kidderminster Staffordshire DY10 3DT",
    "addr:housenumber":"45",
    "addr:postcode":"dy10 3dt",
    "addr:street":"Comberton Road",
    "iso:country":"GB",
    "sg:address":"45 Comberton Road",
    "sg:city":"Kidderminster",
    "sg:classifiers":[
        {
            "category":"Banks & Credit Unions",
            "subcategory":"Financial Services",
            "type":"Services"
        }
    ],
    "sg:postcode":"DY10 3DT",
    "sg:province":"Staffordshire",
    "sg:tags":[
        "adviser"
    ],
    "wof:name":"David Hughes",
    "wof:placetype":"venue"
},
  "geometry": {"coordinates":[-2.228808,52.381618],"type":"Point"}
}