{
  "type": "Feature",
  "properties": {
    "addr:full":"316a Priory Road Southampton Hampshire SO17 2LS",
    "addr:housenumber":"316a",
    "addr:postcode":"so17 2ls",
    "addr:street":"Priory Road",
    "iso:country":"GB",
    "sg:address":"316a Priory Road",
    "sg:city":"Southampton",
    "sg:classifiers":[
        {
            "category":"Professional",
            "subcategory":"Printing & Photocopies",
            "type":"Services"
        }
    ],
    "sg:phone":"+44 23 8055 0299",
    "sg:postcode":"SO17 2LS",
    "sg:province":"Hampshire",
    "sg:tags":[
        "printer"
    ],
    "wof:name":"Hamble Valley Press Ltd.",
    "wof:placetype":"venue"
},
  "geometry": {"coordinates":[-1.3818600178,50.9265327454],"type":"Point"}
}