{
  "type": "Feature",
  "properties": {
    "addr:full":"Greyfriars Place Stafford Staffordshire ST16 2PQ",
    "addr:postcode":"st16 2pq",
    "addr:street":"Greyfriars Place",
    "iso:country":"GB",
    "sg:address":"Greyfriars Place",
    "sg:city":"Stafford",
    "sg:classifiers":[
        {
            "category":"Home & Garden",
            "subcategory":"Hardware",
            "type":"Retail Goods"
        },
        {
            "category":"Building & Trades",
            "subcategory":"Electrical",
            "type":"Services"
        }
    ],
    "sg:phone":"+44 1785 211711",
    "sg:postcode":"ST16 2PQ",
    "sg:province":"Staffordshire",
    "sg:tags":[
        "retailer",
        "lighting",
        "consultant"
    ],
    "wof:name":"Triumph Lighting",
    "wof:placetype":"venue"
},
  "geometry": {"coordinates":[-2.1217679977,52.8039588928],"type":"Point"}
}