{
  "type": "Feature",
  "properties": {
    "addr:full":"5 Railway Street Glossop Derbyshire SK13 7AG",
    "addr:housenumber":"5",
    "addr:postcode":"sk13 7ag",
    "addr:street":"Railway Street",
    "iso:country":"GB",
    "sg:address":"5 Railway Street",
    "sg:city":"Glossop",
    "sg:classifiers":[
        {
            "category":"Personal",
            "subcategory":"Barber",
            "type":"Services"
        }
    ],
    "sg:phone":"+44 1457 853421",
    "sg:postcode":"SK13 7AG",
    "sg:province":"Derbyshire",
    "sg:tags":[
        "men's",
        "hairdresser"
    ],
    "wof:name":"Barnetts",
    "wof:placetype":"venue"
},
  "geometry": {"coordinates":[-1.950828,53.443966],"type":"Point"}
}