{
  "type": "Feature",
  "properties": {
    "addr:full":"15 Coombe Road New Malden Surrey KT3 4PX",
    "addr:housenumber":"15",
    "addr:postcode":"kt3 4px",
    "addr:street":"Coombe Road",
    "iso:country":"GB",
    "sg:address":"15 Coombe Road",
    "sg:city":"New Malden",
    "sg:classifiers":[
        {
            "category":"Restaurant",
            "type":"Food & Drink"
        }
    ],
    "sg:phone":"+44 20 8949 2710",
    "sg:postcode":"KT3 4PX",
    "sg:province":"Surrey",
    "sg:tags":[
        "italian"
    ],
    "wof:name":"H Hoi",
    "wof:placetype":"venue"
},
  "geometry": {"coordinates":[-0.2568230033,51.4043464661],"type":"Point"}
}