{
  "type": "Feature",
  "properties": {
    "iso:country":"GB",
    "sg:address":"7a St Thomas Road, Crabtree Manorway",
    "sg:city":"Belvedere",
    "sg:classifiers":[
        {
            "category":"Retail",
            "subcategory":"Auto Repair",
            "type":"Services"
        }
    ],
    "sg:phone":"+44 20 8311 7721",
    "sg:postcode":"DA17 6AG",
    "sg:province":"Kent",
    "sg:tags":[
        "body",
        "car"
    ],
    "wof:name":"G B Motors",
    "wof:placetype":"venue"
},
  "geometry": {"coordinates":[0.160422,51.49659],"type":"Point"}
}