{
  "type": "Feature",
  "properties": {
    "iso:country":"GB",
    "sg:address":"10 Station Parade, Station Road, Rustington",
    "sg:city":"Littlehampton",
    "sg:classifiers":[
        {
            "category":"Home & Garden",
            "subcategory":"Household Appliances",
            "type":"Retail Goods"
        }
    ],
    "sg:postcode":"BN16 3AE",
    "sg:province":"West Sussex",
    "sg:tags":[
        "electrical"
    ],
    "wof:name":"A M Services",
    "wof:placetype":"venue"
},
  "geometry": {"coordinates":[-0.4893670082,50.8169631958],"type":"Point"}
}