{
  "type": "Feature",
  "properties": {
    "iso:country":"GB",
    "sg:address":"116 Raffles Rd",
    "sg:city":"Birkenhead",
    "sg:classifiers":[
        {
            "category":"Professional",
            "subcategory":"Engineering",
            "type":"Services"
        }
    ],
    "sg:phone":"+44 151 651 1943",
    "sg:postcode":"L42 0HW",
    "sg:province":"Merseyside",
    "sg:tags":[
        "contractor",
        "electrical",
        "engineer"
    ],
    "wof:name":"M D Electrics",
    "wof:placetype":"venue"
},
  "geometry": {"coordinates":[-3.027602,53.385017],"type":"Point"}
}