{
  "type": "Feature",
  "properties": {
    "addr:full":"18 Hillview Crescent Ilford Essex IG1 3QD",
    "addr:housenumber":"18",
    "addr:postcode":"ig1 3qd",
    "addr:street":"Hillview Crescent",
    "iso:country":"GB",
    "sg:address":"18 Hillview Crescent",
    "sg:city":"Ilford",
    "sg:classifiers":[
        {
            "category":"Professional",
            "subcategory":"Computer Services",
            "type":"Services"
        }
    ],
    "sg:postcode":"IG1 3QD",
    "sg:province":"Essex",
    "sg:tags":[
        "system",
        "software"
    ],
    "wof:name":"Grosvenor I.T. Ltd",
    "wof:placetype":"venue"
},
  "geometry": {"coordinates":[0.05757,51.574379],"type":"Point"}
}