{
  "type": "Feature",
  "properties": {
    "addr:full":"Unit 8 Radius Park, Faggs Road Feltham Greater London TW14 0NG",
    "addr:housenumber":"unit 8",
    "addr:postcode":"tw14 0ng",
    "addr:street":"Radius Park Faggs Road",
    "iso:country":"GB",
    "sg:address":"Unit 8 Radius Park, Faggs Road",
    "sg:city":"Feltham",
    "sg:classifiers":[
        {
            "category":"Freight",
            "type":"Transportation"
        }
    ],
    "sg:phone":"+44 20 8751 5000",
    "sg:postcode":"TW14 0NG",
    "sg:province":"Greater London",
    "sg:tags":[
        "forwarders"
    ],
    "wof:name":"Air New Zealand Cargo",
    "wof:placetype":"venue"
},
  "geometry": {"coordinates":[-0.41907,51.464272],"type":"Point"}
}