{
  "type": "Feature",
  "properties": {
    "addr:full":"163 Bardon Rd Coalville Leicestershire LE674BG",
    "addr:housenumber":"163",
    "addr:postcode":"le674bg",
    "addr:street":"Bardon Rd",
    "iso:country":"GB",
    "sg:address":"163 Bardon Rd",
    "sg:city":"Coalville",
    "sg:classifiers":[
        {
            "category":"Organizations",
            "subcategory":"Membership Organization",
            "type":"Services"
        }
    ],
    "sg:postcode":"LE674BG",
    "sg:province":"Leicestershire",
    "sg:tags":[
        "club"
    ],
    "wof:name":"Bardon Road Working Men's Club & Institu",
    "wof:placetype":"venue"
},
  "geometry": {"coordinates":[-1.3573720455,52.7197341919],"type":"Point"}
}