{
  "type": "Feature",
  "properties": {
    "iso:country":"GB",
    "sg:address":"29 Ennerdale Drive, Lakeside",
    "sg:city":"Congleton",
    "sg:classifiers":[
        {
            "category":"Professional",
            "subcategory":"Accounting & Tax Preparation",
            "type":"Services"
        }
    ],
    "sg:phone":"+44 1625 423433",
    "sg:postcode":"CW12 4FR",
    "sg:province":"Cheshire",
    "sg:tags":[
        "accountant"
    ],
    "wof:name":"Afa Accountancy Ltd.",
    "wof:placetype":"venue"
},
  "geometry": {"coordinates":[-2.230071,53.162086],"type":"Point"}
}