{
  "type": "Feature",
  "properties": {
    "addr:full":"Unit 130, Lydney Industrial Estate, Harbour Road Lydney Gloucestershire GL15 4EJ",
    "addr:housenumber":"130",
    "addr:postcode":"gl15 4ej",
    "addr:street":"Lydney Industrial Estate Harbour Road",
    "iso:country":"GB",
    "sg:address":"Unit 130, Lydney Industrial Estate, Harbour Road",
    "sg:city":"Lydney",
    "sg:classifiers":[
        {
            "category":"Professional",
            "subcategory":"Engineering",
            "type":"Services"
        }
    ],
    "sg:postcode":"GL15 4EJ",
    "sg:province":"Gloucestershire",
    "wof:name":"F & E Engineering",
    "wof:placetype":"venue"
},
  "geometry": {"coordinates":[-2.517624,51.710091],"type":"Point"}
}