{
  "type": "Feature",
  "properties": {
    "addr:full":"64 Water Lane Leeds West Yorkshire LS12 5LX",
    "addr:housenumber":"64",
    "addr:postcode":"ls12 5lx",
    "addr:street":"Water Lane",
    "iso:country":"GB",
    "sg:address":"64 Water Lane",
    "sg:city":"Leeds",
    "sg:classifiers":[
        {
            "category":"Building & Trades",
            "subcategory":"Construction",
            "type":"Services"
        }
    ],
    "sg:postcode":"LS12 5LX",
    "sg:province":"West Yorkshire",
    "sg:tags":[
        "roofing"
    ],
    "wof:name":"Apex Roofing",
    "wof:placetype":"venue"
},
  "geometry": {"coordinates":[-1.626124,53.794998],"type":"Point"}
}