{
  "type": "Feature",
  "properties": {
    "iso:country":"GB",
    "sg:address":"The Buckland Medical Centre, Brookfield Pl, Buckland Av",
    "sg:city":"Dover",
    "sg:classifiers":[
        {
            "category":"Health Services",
            "subcategory":"Doctor",
            "type":"Services"
        }
    ],
    "sg:phone":"+44 1304 206353",
    "sg:postcode":"CT16 2AE",
    "sg:province":"Kent",
    "sg:tags":[
        "practitioners"
    ],
    "wof:name":"Bahadur, T",
    "wof:placetype":"venue"
},
  "geometry": {"coordinates":[1.328761,51.126846],"type":"Point"}
}