{
  "type": "Feature",
  "properties": {
    "addr:full":"240 Block Shop, Kirkgate Market Leeds West Yorkshire LS2 7HN",
    "addr:housenumber":"240",
    "addr:postcode":"ls2 7hn",
    "addr:street":"Kirkgate Market Leeds West",
    "iso:country":"GB",
    "sg:address":"240 Block Shop, Kirkgate Market",
    "sg:city":"Leeds",
    "sg:classifiers":[
        {
            "category":"Food & Beverages",
            "subcategory":"Bakery",
            "type":"Retail Goods"
        }
    ],
    "sg:postcode":"LS2 7HN",
    "sg:province":"West Yorkshire",
    "sg:tags":[
        "baker"
    ],
    "wof:name":"Christian Ross Confectionery",
    "wof:placetype":"venue"
},
  "geometry": {"coordinates":[-1.5391099453,53.7972183228],"type":"Point"}
}