{
  "type": "Feature",
  "properties": {
    "iso:country":"GB",
    "sg:address":"Stoodleigh Club, Stoodleigh",
    "sg:city":"Tiverton",
    "sg:classifiers":[
        {
            "category":"Organizations",
            "subcategory":"Community Association",
            "type":"Services"
        },
        {
            "category":"Organizations",
            "subcategory":"Membership Organization",
            "type":"Services"
        }
    ],
    "sg:phone":"+44 1398 351357",
    "sg:postcode":"EX16 9PR",
    "sg:province":"Devon",
    "sg:tags":[
        "club",
        "social"
    ],
    "wof:name":"Stoodleigh Village Club",
    "wof:placetype":"venue"
},
  "geometry": {"coordinates":[-3.516079,50.990231],"type":"Point"}
}