{
  "type": "Feature",
  "properties": {
    "addr:full":"44 Raeburn Pl Edinburgh City of Edinburgh EH4 1HL",
    "addr:housenumber":"44",
    "addr:postcode":"eh4 1hl",
    "addr:street":"Raeburn Pl",
    "iso:country":"GB",
    "sg:address":"44 Raeburn Pl",
    "sg:city":"Edinburgh",
    "sg:classifiers":[
        {
            "category":"Shopping",
            "subcategory":"Gifts & Souvenirs",
            "type":"Retail Goods"
        }
    ],
    "sg:phone":"+44 131 332 5078",
    "sg:postcode":"EH4 1HL",
    "sg:province":"City of Edinburgh",
    "sg:tags":[
        "poster",
        "card"
    ],
    "wof:name":"Pickwicks",
    "wof:placetype":"venue"
},
  "geometry": {"coordinates":[-3.212444067,55.9590682983],"type":"Point"}
}