{
  "type": "Feature",
  "properties": {
    "iso:country":"GB",
    "sg:address":"28 Greenside Court, Eccles",
    "sg:city":"Manchester",
    "sg:classifiers":[
        {
            "category":"Building & Trades",
            "subcategory":"Plumbing",
            "type":"Services"
        }
    ],
    "sg:phone":"+44 161 707 3842",
    "sg:postcode":"M30 9QH",
    "sg:province":"Greater Manchester",
    "sg:tags":[
        "central",
        "installation",
        "heating",
        "servicing",
        "system"
    ],
    "wof:name":"Action Plumbing",
    "wof:placetype":"venue"
},
  "geometry": {"coordinates":[-2.3505940437,53.4887695312],"type":"Point"}
}