{
  "type": "Feature",
  "properties": {
    "addr:full":"172 Wragby Road Lincoln Lincolnshire LN2 4PT",
    "addr:housenumber":"172",
    "addr:postcode":"ln2 4pt",
    "addr:street":"Wragby Road",
    "iso:country":"GB",
    "sg:address":"172 Wragby Road",
    "sg:city":"Lincoln",
    "sg:classifiers":[
        {
            "category":"Military Area",
            "subcategory":"Air Force Base",
            "type":"Public Place"
        }
    ],
    "sg:phone":"+44 1522 797484",
    "sg:postcode":"LN2 4PT",
    "sg:province":"Lincolnshire",
    "sg:tags":[
        "taxi",
        "hire",
        "private"
    ],
    "wof:name":"Central Cruiser",
    "wof:placetype":"venue"
},
  "geometry": {"coordinates":[-0.518457,53.239834],"type":"Point"}
}