{
  "type": "Feature",
  "properties": {
    "addr:full":"Unit 3c Moorfields Indust Est, Moor Park Av Blackpool Lancashire FY2 0JY",
    "addr:housenumber":"unit 3c",
    "addr:postcode":"fy2 0jy",
    "addr:street":"Indust Est Moor Park Av",
    "iso:country":"GB",
    "sg:address":"Unit 3c Moorfields Indust Est, Moor Park Av",
    "sg:city":"Blackpool",
    "sg:classifiers":[
        {
            "category":"Home & Garden",
            "subcategory":"Hardware",
            "type":"Retail Goods"
        }
    ],
    "sg:phone":"+44 1253 592983",
    "sg:postcode":"FY2 0JY",
    "sg:province":"Lancashire",
    "sg:tags":[
        "equipment",
        "heating"
    ],
    "wof:name":"Lancashire Stoves & Fires Ltd",
    "wof:placetype":"venue"
},
  "geometry": {"coordinates":[-3.0227689743,53.8503837585],"type":"Point"}
}