{
  "type": "Feature",
  "properties": {
    "iso:country":"GB",
    "sg:address":"Court Road",
    "sg:city":"Orpington",
    "sg:classifiers":[
        {
            "category":"Food & Beverages",
            "subcategory":"Fruits & Vegetables",
            "type":"Retail Goods"
        },
        {
            "category":"Wholesale",
            "subcategory":"Fruits & Vegetables",
            "type":"Manufacturing & Wholesale Goods"
        }
    ],
    "sg:postcode":"BR6 0PW",
    "sg:province":"Kent",
    "sg:tags":[
        "greengrocer"
    ],
    "wof:name":"Hewitts Farm Market",
    "wof:placetype":"venue"
},
  "geometry": {"coordinates":[0.124005,51.357243],"type":"Point"}
}