{
  "type": "Feature",
  "properties": {
    "iso:country":"GB",
    "sg:address":"Trotterbank House, Overtown",
    "sg:city":"Wishaw",
    "sg:classifiers":[
        {
            "category":"Parking",
            "type":"Transportation"
        }
    ],
    "sg:phone":"+44 1698 359230",
    "sg:postcode":"ML2 0RW",
    "sg:province":"North Lanarkshire",
    "sg:tags":[
        "car",
        "valet"
    ],
    "wof:name":"Strathclyde Autoclean",
    "wof:placetype":"venue"
},
  "geometry": {"coordinates":[-3.904667,55.759212],"type":"Point"}
}