{
  "type": "Feature",
  "properties": {
    "iso:country":"GB",
    "sg:address":"69 The Links",
    "sg:city":"Pontypool",
    "sg:classifiers":[
        {
            "category":"Building & Trades",
            "subcategory":"Plumbing",
            "type":"Services"
        }
    ],
    "sg:phone":"+44 1495 753389",
    "sg:postcode":"NP4 8DQ",
    "sg:province":"Monmouthshire",
    "sg:tags":[
        "central",
        "heating"
    ],
    "wof:name":"B & R Services",
    "wof:placetype":"venue"
},
  "geometry": {"coordinates":[-3.04047,51.716171],"type":"Point"}
}