{
  "type": "Feature",
  "properties": {
    "addr:full":"Vicars Bridge Road, Blairingone Dollar Clackmannanshire FK14 7LR",
    "addr:postcode":"fk14 7lr",
    "addr:street":"Vicars Bridge Road Blairingone",
    "iso:country":"GB",
    "sg:address":"Vicars Bridge Road, Blairingone",
    "sg:city":"Dollar",
    "sg:classifiers":[
        {
            "category":"Government",
            "subcategory":"Post Office",
            "type":"Public Place"
        }
    ],
    "sg:postcode":"FK14 7LR",
    "sg:province":"Clackmannanshire",
    "wof:name":"Blairingone Post Office",
    "wof:placetype":"venue"
},
  "geometry": {"coordinates":[-3.6740090847,56.1627616882],"type":"Point"}
}