{
  "type": "Feature",
  "properties": {
    "iso:country":"GB",
    "sg:address":"427 Dunstable Road",
    "sg:city":"Luton",
    "sg:classifiers":[
        {
            "category":"Autos & Motor Vehicles",
            "subcategory":"Auto Supplies",
            "type":"Retail Goods"
        }
    ],
    "sg:phone":"+44 1582 592006",
    "sg:postcode":"LU4 8DA",
    "sg:province":"Bedfordshire",
    "sg:tags":[
        "rubber",
        "tyre"
    ],
    "wof:name":"S&j Tyres",
    "wof:placetype":"venue"
},
  "geometry": {"coordinates":[-0.447847,51.891354],"type":"Point"}
}