{
  "type": "Feature",
  "properties": {
    "iso:country":"GB",
    "sg:address":"1 Tudor Buildings, Bath Road",
    "sg:city":"Cowes",
    "sg:classifiers":[
        {
            "category":"Arts & Performance",
            "subcategory":"Art Gallery",
            "type":"Entertainment"
        }
    ],
    "sg:phone":"+44 1983 200124",
    "sg:postcode":"PO31 7RH",
    "sg:province":"Isle of Wight",
    "wof:name":"The Marine Gallery",
    "wof:placetype":"venue"
},
  "geometry": {"coordinates":[-1.297866,50.758121],"type":"Point"}
}