{
  "type": "Feature",
  "properties": {
    "addr:full":"Brockholme, Bellingdon Chesham Buckinghamshire HP5 2XL",
    "addr:postcode":"hp5 2xl",
    "iso:country":"GB",
    "sg:address":"Brockholme, Bellingdon",
    "sg:city":"Chesham",
    "sg:classifiers":[
        {
            "category":"Building & Trades",
            "subcategory":"Construction",
            "type":"Services"
        },
        {
            "category":"Manufacturing",
            "subcategory":"Paper Products",
            "type":"Manufacturing & Wholesale Goods"
        }
    ],
    "sg:phone":"+44 1494 771932",
    "sg:postcode":"HP5 2XL",
    "sg:province":"Buckinghamshire",
    "sg:tags":[
        "cardboard",
        "decorator",
        "painter"
    ],
    "wof:name":"B Hearn & Sons",
    "wof:placetype":"venue"
},
  "geometry": {"coordinates":[-0.636425,51.7384],"type":"Point"}
}