{
  "type": "Feature",
  "properties": {
    "iso:country":"GB",
    "sg:address":"26 Junction Road",
    "sg:city":"Kirkwall",
    "sg:classifiers":[
        {
            "category":"Bars & Pubs",
            "type":"Food & Drink"
        }
    ],
    "sg:phone":"+44 1856 871422",
    "sg:postcode":"KW15 1AB",
    "sg:province":"Orkney Islands",
    "sg:tags":[
        "pubs",
        "inn"
    ],
    "wof:name":"Auld Motor House",
    "wof:placetype":"venue"
},
  "geometry": {"coordinates":[-2.96168,58.982986],"type":"Point"}
}