{
  "type": "Feature",
  "properties": {
    "addr:full":"The Orchard, Chivers Way Cambridge Cambridgeshire CB4 9NR",
    "addr:postcode":"cb4 9nr",
    "addr:street":"Chivers Way",
    "iso:country":"GB",
    "sg:address":"The Orchard, Chivers Way",
    "sg:city":"Cambridge",
    "sg:classifiers":[
        {
            "category":"Professional",
            "subcategory":"Business Services",
            "type":"Services"
        },
        {
            "category":"Food & Beverages",
            "subcategory":"Supermarket",
            "type":"Retail Goods"
        }
    ],
    "sg:phone":"+44 1223 233333",
    "sg:postcode":"CB4 9NR",
    "sg:province":"Cambridgeshire",
    "sg:tags":[
        "frozen",
        "distribution"
    ],
    "wof:name":"H L Foods Ltd.",
    "wof:placetype":"venue"
},
  "geometry": {"coordinates":[0.110885,52.255871],"type":"Point"}
}