{
  "type": "Feature",
  "properties": {
    "iso:country":"GB",
    "sg:address":"Longley Grn, Suckley",
    "sg:city":"Worcester",
    "sg:classifiers":[
        {
            "category":"Bars & Pubs",
            "type":"Food & Drink"
        }
    ],
    "sg:phone":"+44 1886 884530",
    "sg:postcode":"WR6 5DU",
    "sg:province":"Herefordshire",
    "sg:tags":[
        "pubs",
        "inn"
    ],
    "wof:name":"Nelson Inn",
    "wof:placetype":"venue"
},
  "geometry": {"coordinates":[-2.4050760269,52.1568260193],"type":"Point"}
}