{
  "type": "Feature",
  "properties": {
    "iso:country":"GB",
    "sg:address":"Horsehoe Cottage, Brown Bread Street, Ashburnham",
    "sg:city":"Battle",
    "sg:classifiers":[
        {
            "category":"Banks & Credit Unions",
            "subcategory":"Financial Services",
            "type":"Services"
        }
    ],
    "sg:postcode":"TN33 9NX",
    "sg:province":"East Sussex",
    "sg:tags":[
        "adviser"
    ],
    "wof:name":"David Walters Financial Services",
    "wof:placetype":"venue"
},
  "geometry": {"coordinates":[0.38305,50.90992],"type":"Point"}
}