{
  "type": "Feature",
  "properties": {
    "iso:country":"GB",
    "sg:address":"152 Faversham Road",
    "sg:city":"Ashford",
    "sg:classifiers":[
        {
            "category":"Retail",
            "subcategory":"Funeral Services",
            "type":"Services"
        }
    ],
    "sg:phone":"+44 1233 621518",
    "sg:postcode":"TN24 9AE",
    "sg:province":"Kent",
    "wof:name":"Kent Co-Operative Funeral Service",
    "wof:placetype":"venue"
},
  "geometry": {"coordinates":[0.886686,51.166824],"type":"Point"}
}