{
  "type": "Feature",
  "properties": {
    "addr:full":"27 Hartfield Road London Greater London SW19 3SG",
    "addr:housenumber":"27",
    "addr:postcode":"sw19 3sg",
    "addr:street":"Hartfield Road",
    "iso:country":"GB",
    "sg:address":"27 Hartfield Road",
    "sg:city":"London",
    "sg:classifiers":[
        {
            "category":"Bars & Pubs",
            "subcategory":"Wine Bar",
            "type":"Food & Drink"
        }
    ],
    "sg:phone":"+44 20 8543 9788",
    "sg:postcode":"SW19 3SG",
    "sg:province":"Greater London",
    "wof:name":"Christopher Dean",
    "wof:placetype":"venue"
},
  "geometry": {"coordinates":[-0.2057079971,51.4196434021],"type":"Point"}
}