{
  "type": "Feature",
  "properties": {
    "addr:full":"Queens Drive, Walton Liverpool Merseyside L4 8SW",
    "addr:postcode":"l4 8sw",
    "addr:street":"Queens Drive",
    "iso:country":"GB",
    "sg:address":"Queens Drive, Walton",
    "sg:city":"Liverpool",
    "sg:classifiers":[
        {
            "category":"Sports & Exercise",
            "subcategory":"Swimming Pool",
            "type":"Entertainment"
        }
    ],
    "sg:phone":"+44 151 525 3563",
    "sg:postcode":"L4 8SW",
    "sg:province":"Merseyside",
    "wof:name":"Queens Drive Baths",
    "wof:placetype":"venue"
},
  "geometry": {"coordinates":[-2.9410140514,53.4398498535],"type":"Point"}
}