{
  "type": "Feature",
  "properties": {
    "iso:country":"GB",
    "sg:address":"31 Queens Pine, Crown Wood",
    "sg:city":"Bracknell",
    "sg:classifiers":[
        {
            "category":"Professional",
            "subcategory":"Detective & Security Services",
            "type":"Services"
        }
    ],
    "sg:phone":"+44 1344 412245",
    "sg:postcode":"RG12 0TL",
    "sg:province":"Berkshire",
    "sg:tags":[
        "car"
    ],
    "wof:name":"Pro-Fit Car Electrics",
    "wof:placetype":"venue"
},
  "geometry": {"coordinates":[-0.73511,51.398556],"type":"Point"}
}