{
  "type": "Feature",
  "properties": {
    "addr:full":"11 Hamberts Road, Blackall Industrial Estate Chelmsford Essex CM3 5UW",
    "addr:housenumber":"11",
    "addr:postcode":"cm3 5uw",
    "addr:street":"Hamberts Road Blackall Industrial Estate",
    "iso:country":"GB",
    "sg:address":"11 Hamberts Road, Blackall Industrial Estate",
    "sg:city":"Chelmsford",
    "sg:classifiers":[
        {
            "category":"Wholesale",
            "subcategory":"Machinery & Supplies",
            "type":"Manufacturing & Wholesale Goods"
        }
    ],
    "sg:postcode":"CM3 5UW",
    "sg:province":"Essex",
    "sg:tags":[
        "control",
        "instrument",
        "industrial",
        "-"
    ],
    "wof:name":"Dold Industries Ltd.",
    "wof:placetype":"venue"
},
  "geometry": {"coordinates":[0.6215299964,51.6516227722],"type":"Point"}
}