{
  "type": "Feature",
  "properties": {
    "iso:country":"GB",
    "sg:address":"Play House 2 2 Newtown Street, Shaw",
    "sg:city":"Oldham",
    "sg:classifiers":[
        {
            "category":"Arts & Performance",
            "subcategory":"Theater",
            "type":"Entertainment"
        }
    ],
    "sg:phone":"+44 1706 847281",
    "sg:postcode":"OL2 8NX",
    "sg:province":"Lancashire",
    "sg:tags":[
        "hall",
        "theatre",
        "concert"
    ],
    "wof:name":"Crompton Stage Society",
    "wof:placetype":"venue"
},
  "geometry": {"coordinates":[-2.09351,53.579559],"type":"Point"}
}