{
  "type": "Feature",
  "properties": {
    "addr:full":"93 Frankby Road, West Kirby Wirral Merseyside CH48 6EQ",
    "addr:housenumber":"93",
    "addr:postcode":"ch48 6eq",
    "addr:street":"Frankby Road",
    "iso:country":"GB",
    "sg:address":"93 Frankby Road, West Kirby",
    "sg:city":"Wirral",
    "sg:classifiers":[
        {
            "category":"Building & Trades",
            "subcategory":"Plumbing",
            "type":"Services"
        }
    ],
    "sg:postcode":"CH48 6EQ",
    "sg:province":"Merseyside",
    "sg:tags":[
        "heating"
    ],
    "wof:name":"A Cooper",
    "wof:placetype":"venue"
},
  "geometry": {"coordinates":[-3.157359,53.37458],"type":"Point"}
}