{
  "type": "Feature",
  "properties": {
    "addr:full":"9 Fort End, Haddenham Aylesbury Buckinghamshire HP17 8EJ",
    "addr:housenumber":"9;haddenham",
    "addr:postcode":"hp17 8ej",
    "addr:street":"Fort End",
    "iso:country":"GB",
    "sg:address":"9 Fort End, Haddenham",
    "sg:city":"Aylesbury",
    "sg:classifiers":[
        {
            "category":"Banks & Credit Unions",
            "subcategory":"Atm",
            "type":"Services"
        },
        {
            "category":"Manufacturing",
            "subcategory":"Electronics",
            "type":"Manufacturing & Wholesale Goods"
        }
    ],
    "sg:phone":"+44 1844 291803",
    "sg:postcode":"HP17 8EJ",
    "sg:province":"Buckinghamshire",
    "sg:tags":[
        "printed",
        "circuit",
        "integrated"
    ],
    "wof:name":"Good Thinking",
    "wof:placetype":"venue"
},
  "geometry": {"coordinates":[-0.928559,51.773071],"type":"Point"}
}