{
  "type": "Feature",
  "properties": {
    "iso:country":"GB",
    "sg:address":"51a William St, Totterdown",
    "sg:city":"Bristol",
    "sg:classifiers":[
        {
            "category":"Professional",
            "type":"Services"
        }
    ],
    "sg:phone":"+44 117 904 6441",
    "sg:postcode":"BS3 4TY",
    "sg:province":"City of Bristol",
    "sg:tags":[
        "interior",
        "furnishers",
        "designer"
    ],
    "wof:name":"Handprints",
    "wof:placetype":"venue"
},
  "geometry": {"coordinates":[-2.581595,51.442715],"type":"Point"}
}