{
  "type": "Feature",
  "properties": {
    "iso:country":"GB",
    "sg:address":"42 Kitchener Road, Amesbury",
    "sg:city":"Salisbury",
    "sg:classifiers":[
        {
            "category":"Professional",
            "subcategory":"Art Services",
            "type":"Services"
        }
    ],
    "sg:postcode":"SP4 7AD",
    "sg:province":"Hampshire",
    "sg:tags":[
        "photographer"
    ],
    "wof:name":"T L Fuller & Sons",
    "wof:placetype":"venue"
},
  "geometry": {"coordinates":[-1.77412,51.175117],"type":"Point"}
}