{
  "type": "Feature",
  "properties": {
    "addr:full":"Hawke Road Ipswich Suffolk IP3 0JF",
    "addr:postcode":"ip3 0jf",
    "addr:street":"Hawke Road",
    "iso:country":"GB",
    "sg:address":"Hawke Road",
    "sg:city":"Ipswich",
    "sg:classifiers":[
        {
            "category":"Retail",
            "subcategory":"Auto Repair",
            "type":"Services"
        }
    ],
    "sg:phone":"+44 1473 251800",
    "sg:postcode":"IP3 0JF",
    "sg:province":"Suffolk",
    "sg:tags":[
        "electrician"
    ],
    "wof:name":"Fuel Electrics",
    "wof:placetype":"venue"
},
  "geometry": {"coordinates":[1.167566,52.037952],"type":"Point"}
}