{
  "type": "Feature",
  "properties": {
    "addr:full":"10 Benedict Close Romsey Hampshire SO51 8PN",
    "addr:housenumber":"10",
    "addr:postcode":"so51 8pn",
    "addr:street":"Benedict Close",
    "iso:country":"GB",
    "sg:address":"10 Benedict Close",
    "sg:city":"Romsey",
    "sg:classifiers":[
        {
            "category":"Building & Trades",
            "subcategory":"Landscaping Services",
            "type":"Services"
        }
    ],
    "sg:postcode":"SO51 8PN",
    "sg:province":"Hampshire",
    "sg:tags":[
        "designer",
        "architect",
        "landscape"
    ],
    "wof:name":"Rowallan Montrose",
    "wof:placetype":"venue"
},
  "geometry": {"coordinates":[-1.471132,50.989426],"type":"Point"}
}