{
  "type": "Feature",
  "properties": {
    "addr:full":"25 Finsbury Circus Moorgate Lancashire W1X 1AH",
    "addr:housenumber":"25",
    "addr:postcode":"w1x 1ah",
    "addr:street":"Finsbury Circus Moorgate",
    "iso:country":"GB",
    "sg:address":"25 Finsbury Circus",
    "sg:city":"Moorgate",
    "sg:classifiers":[
        {
            "category":"Real Estate",
            "subcategory":"Developer",
            "type":"Services"
        }
    ],
    "sg:phone":"+44 20 7494 9401",
    "sg:postcode":"W1X 1AH",
    "sg:province":"Lancashire",
    "sg:tags":[
        "property"
    ],
    "wof:name":"Highbridge Properties",
    "wof:placetype":"venue"
},
  "geometry": {"coordinates":[-0.0905200019,51.5189704895],"type":"Point"}
}