{
  "type": "Feature",
  "properties": {
    "addr:full":"3 Bridge Street Llanfyllin Shropshire SY22 5AU",
    "addr:housenumber":"3",
    "addr:postcode":"sy22 5au",
    "addr:street":"Bridge Street",
    "iso:country":"GB",
    "sg:address":"3 Bridge Street",
    "sg:city":"Llanfyllin",
    "sg:classifiers":[
        {
            "category":"Professional",
            "subcategory":"Accounting & Tax Preparation",
            "type":"Services"
        }
    ],
    "sg:phone":"+44 1691 648414",
    "sg:postcode":"SY22 5AU",
    "sg:province":"Shropshire",
    "sg:tags":[
        "accountant"
    ],
    "wof:name":"Geraint Humphreys & Co",
    "wof:placetype":"venue"
},
  "geometry": {"coordinates":[-3.272367,52.766186],"type":"Point"}
}