{
  "type": "Feature",
  "properties": {
    "iso:country":"GB",
    "sg:address":"11 Charlton Road",
    "sg:city":"Shepton Mallet",
    "sg:classifiers":[
        {
            "category":"Government",
            "subcategory":"Office",
            "type":"Public Place"
        }
    ],
    "sg:phone":"+44 1749 343127",
    "sg:postcode":"BA4 5PG",
    "sg:province":"Somerset",
    "sg:tags":[
        "education",
        "agency",
        "authority"
    ],
    "wof:name":"Community Education Department",
    "wof:placetype":"venue"
},
  "geometry": {"coordinates":[-2.5388009548,51.1885795593],"type":"Point"}
}