{
  "type": "Feature",
  "properties": {
    "addr:full":"35 Nork Way Banstead Surrey SM7 1PB",
    "addr:housenumber":"35",
    "addr:postcode":"sm7 1pb",
    "addr:street":"Nork Way",
    "iso:country":"GB",
    "sg:address":"35 Nork Way",
    "sg:city":"Banstead",
    "sg:classifiers":[
        {
            "category":"Professional",
            "subcategory":"Art Services",
            "type":"Services"
        }
    ],
    "sg:phone":"+44 1737 361011",
    "sg:postcode":"SM7 1PB",
    "sg:province":"Surrey",
    "sg:tags":[
        "framing"
    ],
    "wof:name":"Mackie (Uk) Ltd.",
    "wof:placetype":"venue"
},
  "geometry": {"coordinates":[-0.2151349932,51.3273239136],"type":"Point"}
}