{
  "type": "Feature",
  "properties": {
    "addr:full":"35 Stockwell Street Glasgow Glasgow City G1 4RZ",
    "addr:housenumber":"35",
    "addr:postcode":"g1 4rz",
    "addr:street":"Stockwell Street",
    "iso:country":"GB",
    "sg:address":"35 Stockwell Street",
    "sg:city":"Glasgow",
    "sg:classifiers":[
        {
            "category":"Professional",
            "subcategory":"Management & Consulting",
            "type":"Services"
        }
    ],
    "sg:phone":"+44 141 552 2152",
    "sg:postcode":"G1 4RZ",
    "sg:province":"Glasgow City",
    "sg:tags":[
        "consultant",
        "specialist"
    ],
    "wof:name":"Sensation Nails",
    "wof:placetype":"venue"
},
  "geometry": {"coordinates":[-4.2493047714,55.8568305969],"type":"Point"}
}