{
  "type": "Feature",
  "properties": {
    "iso:country":"GB",
    "sg:address":", Milwich",
    "sg:city":"Stafford",
    "sg:classifiers":[
        {
            "category":"Bars & Pubs",
            "type":"Food & Drink"
        }
    ],
    "sg:phone":"+44 1889 505310",
    "sg:postcode":"ST18 0EG",
    "sg:province":"Staffordshire",
    "sg:tags":[
        "pubs",
        "inn"
    ],
    "wof:name":"GREEN MAN",
    "wof:placetype":"venue"
},
  "geometry": {"coordinates":[-2.0416789055,52.8883857727],"type":"Point"}
}