{
  "type": "Feature",
  "properties": {
    "addr:full":"Golden Valley Service Station, Enbrook Valley Folkestone Kent CT20 3NE",
    "addr:postcode":"ct20 3ne",
    "addr:street":"Enbrook Valley",
    "iso:country":"GB",
    "sg:address":"Golden Valley Service Station, Enbrook Valley",
    "sg:city":"Folkestone",
    "sg:classifiers":[
        {
            "category":"Retail",
            "subcategory":"Auto Repair",
            "type":"Services"
        }
    ],
    "sg:postcode":"CT20 3NE",
    "sg:province":"Kent",
    "sg:tags":[
        "modification",
        "garage"
    ],
    "wof:name":"Enbrook Garage",
    "wof:placetype":"venue"
},
  "geometry": {"coordinates":[1.177945,51.084431],"type":"Point"}
}