{
  "type": "Feature",
  "properties": {
    "addr:full":"22 Dorchester Rd Weybridge Surrey KT13 8PG",
    "addr:housenumber":"22",
    "addr:postcode":"kt13 8pg",
    "addr:street":"Dorchester Rd",
    "iso:country":"GB",
    "sg:address":"22 Dorchester Rd",
    "sg:city":"Weybridge",
    "sg:classifiers":[
        {
            "category":"Real Estate",
            "subcategory":"Developer",
            "type":"Services"
        }
    ],
    "sg:postcode":"KT13 8PG",
    "sg:province":"Surrey",
    "sg:tags":[
        "property"
    ],
    "wof:name":"Ebdon,John,Homes Ltd",
    "wof:placetype":"venue"
},
  "geometry": {"coordinates":[-0.4557209909,51.3751716614],"type":"Point"}
}