{
  "type": "Feature",
  "properties": {
    "iso:country":"GB",
    "sg:address":"Emerson District 5",
    "sg:city":"Washington",
    "sg:classifiers":[
        {
            "category":"Travel",
            "subcategory":"Hotels & Motels",
            "type":"Entertainment"
        }
    ],
    "sg:phone":"+44 191 416 2264",
    "sg:postcode":"NE37 1LB",
    "sg:province":"Tyne and Wear",
    "wof:name":"Forte Posthouse",
    "wof:placetype":"venue"
},
  "geometry": {"coordinates":[-1.5573400259,54.8867683411],"type":"Point"}
}