{
  "type": "Feature",
  "properties": {
    "addr:full":"85 Millgate Newark Nottinghamshire NG24 4UA",
    "addr:housenumber":"85",
    "addr:postcode":"ng24 4ua",
    "addr:street":"Millgate",
    "iso:country":"GB",
    "sg:address":"85 Millgate",
    "sg:city":"Newark",
    "sg:classifiers":[
        {
            "category":"Organizations",
            "subcategory":"Non-profit Organization",
            "type":"Services"
        }
    ],
    "sg:phone":"+44 1636 679539",
    "sg:postcode":"NG24 4UA",
    "sg:province":"Nottinghamshire",
    "sg:tags":[
        "organisation",
        "voluntary",
        "charity"
    ],
    "wof:name":"Newark & Sherwood Community & Voluntary Service",
    "wof:placetype":"venue"
},
  "geometry": {"coordinates":[-0.8093469739,53.0738945007],"type":"Point"}
}