{
  "type": "Feature",
  "properties": {
    "addr:full":"6 Swine Market Nantwich Cheshire CW5 5LN",
    "addr:housenumber":"6",
    "addr:postcode":"cw5 5ln",
    "addr:street":"Swine Market",
    "iso:country":"GB",
    "sg:address":"6 Swine Market",
    "sg:city":"Nantwich",
    "sg:classifiers":[
        {
            "category":"Shopping",
            "subcategory":"Crafts & Fabrics",
            "type":"Retail Goods"
        }
    ],
    "sg:phone":"+44 1270 626344",
    "sg:postcode":"CW5 5LN",
    "sg:province":"Cheshire",
    "sg:tags":[
        "shop",
        "needlecraft",
        "wool"
    ],
    "wof:name":"Stitchability",
    "wof:placetype":"venue"
},
  "geometry": {"coordinates":[-2.5231881142,53.0678977966],"type":"Point"}
}