{
  "type": "Feature",
  "properties": {
    "addr:full":"Alexanders, Weston Favell Centre Northampton Northamptonshire NN3 8JL",
    "addr:postcode":"nn3 8jl",
    "iso:country":"GB",
    "sg:address":"Alexanders, Weston Favell Centre",
    "sg:city":"Northampton",
    "sg:classifiers":[
        {
            "category":"Retail",
            "subcategory":"Auto Repair",
            "type":"Services"
        }
    ],
    "sg:phone":"+44 1604 786675",
    "sg:postcode":"NN3 8JL",
    "sg:province":"Northamptonshire",
    "sg:tags":[
        "car",
        "specialist",
        "customizing"
    ],
    "wof:name":"Rapid Fit",
    "wof:placetype":"venue"
},
  "geometry": {"coordinates":[-0.837329,52.258251],"type":"Point"}
}