{
  "type": "Feature",
  "properties": {
    "iso:country":"GB",
    "sg:address":"Adelaide Medical Centre, Adelaide Terr",
    "sg:city":"Newcastle Upon Tyne",
    "sg:classifiers":[
        {
            "category":"Health Services",
            "subcategory":"Doctor",
            "type":"Services"
        }
    ],
    "sg:phone":"+44 191 273 6686",
    "sg:postcode":"NE4 8BE",
    "sg:province":"Tyne and Wear",
    "sg:tags":[
        "practitioners"
    ],
    "wof:name":"Kai, J P",
    "wof:placetype":"venue"
},
  "geometry": {"coordinates":[-1.65574,54.970268],"type":"Point"}
}