{
  "type": "Feature",
  "properties": {
    "iso:country":"GB",
    "sg:address":"63-67 Lowestoft Road, Gorleston",
    "sg:city":"Great Yarmouth",
    "sg:classifiers":[
        {
            "category":"Shopping",
            "subcategory":"Bicycles & Sporting Goods",
            "type":"Retail Goods"
        }
    ],
    "sg:postcode":"NR31 6SH",
    "sg:province":"Norfolk",
    "sg:tags":[
        "cycle",
        "accessory"
    ],
    "wof:name":"B & D Cycles",
    "wof:placetype":"venue"
},
  "geometry": {"coordinates":[1.7256720066,52.5740737915],"type":"Point"}
}