{
  "type": "Feature",
  "properties": {
    "iso:country":"GB",
    "sg:address":"47 Halsey Dr",
    "sg:city":"Hitchin",
    "sg:classifiers":[
        {
            "category":"Real Estate",
            "subcategory":"Architect",
            "type":"Services"
        }
    ],
    "sg:phone":"+44 1462 454837",
    "sg:postcode":"SG4 9QS",
    "sg:province":"Hertfordshire",
    "sg:tags":[
        "architectural"
    ],
    "wof:name":"Architectural Surveying Services",
    "wof:placetype":"venue"
},
  "geometry": {"coordinates":[-0.256932,51.94698],"type":"Point"}
}