{
  "type": "Feature",
  "properties": {
    "iso:country":"GB",
    "sg:address":"Unit 8, Sadlers Hall Farm",
    "sg:city":"Basildon",
    "sg:classifiers":[
        {
            "category":"Home & Garden",
            "subcategory":"Building Materials",
            "type":"Retail Goods"
        }
    ],
    "sg:phone":"+44 1268 566618",
    "sg:postcode":"SS13 2HB",
    "sg:province":"Essex",
    "sg:tags":[
        "insulation",
        "installers"
    ],
    "wof:name":"A T I Ltd",
    "wof:placetype":"venue"
},
  "geometry": {"coordinates":[0.5413410068,51.5673179626],"type":"Point"}
}