{
  "type": "Feature",
  "properties": {
    "iso:country":"GB",
    "sg:address":"30 Staplegrove Cres",
    "sg:city":"Bristol",
    "sg:classifiers":[
        {
            "category":"Professional",
            "subcategory":"Engineering",
            "type":"Services"
        }
    ],
    "sg:phone":"+44 117 935 3049",
    "sg:postcode":"BS5 8QW",
    "sg:province":"City of Bristol",
    "sg:tags":[
        "contractor",
        "electrical",
        "engineer"
    ],
    "wof:name":"All Power Ltd",
    "wof:placetype":"venue"
},
  "geometry": {"coordinates":[-2.526605,51.455204],"type":"Point"}
}