{
  "type": "Feature",
  "properties": {
    "addr:full":"George House, 48a George Street Manchester Greater Manchester M1 4HF",
    "addr:housenumber":"48a",
    "addr:postcode":"m1 4hf",
    "addr:street":"George Street",
    "iso:country":"GB",
    "sg:address":"George House, 48a George Street",
    "sg:city":"Manchester",
    "sg:classifiers":[
        {
            "category":"Professional",
            "subcategory":"Accounting & Tax Preparation",
            "type":"Services"
        }
    ],
    "sg:phone":"+44 161 237 1400",
    "sg:postcode":"M1 4HF",
    "sg:province":"Greater Manchester",
    "sg:tags":[
        "accountant"
    ],
    "wof:name":"D F A",
    "wof:placetype":"venue"
},
  "geometry": {"coordinates":[-2.240309,53.47921],"type":"Point"}
}