{
  "type": "Feature",
  "properties": {
    "addr:full":"Nether Leask Farm, Slains Ellon Aberdeenshire AB41 8JT",
    "addr:postcode":"ab41 8jt",
    "addr:street":"Ellon",
    "iso:country":"GB",
    "sg:address":"Nether Leask Farm, Slains",
    "sg:city":"Ellon",
    "sg:classifiers":[
        {
            "category":"Farming",
            "subcategory":"Farm",
            "type":"Manufacturing & Wholesale Goods"
        }
    ],
    "sg:phone":"+44 1358 711235",
    "sg:postcode":"AB41 8JT",
    "sg:province":"Aberdeenshire",
    "sg:tags":[
        "mixed",
        "crop"
    ],
    "wof:name":"Edward Irvine & Son",
    "wof:placetype":"venue"
},
  "geometry": {"coordinates":[-2.0728139877,57.3641357422],"type":"Point"}
}