{
  "type": "Feature",
  "properties": {
    "iso:country":"GB",
    "sg:address":"Bridge End Cottage, Sandyhills",
    "sg:city":"Dalbeattie",
    "sg:classifiers":[
        {
            "category":"Building & Trades",
            "subcategory":"Construction",
            "type":"Services"
        }
    ],
    "sg:phone":"+44 1387 780220",
    "sg:postcode":"DG5 4NY",
    "sg:province":"Dumfries and Galloway",
    "sg:tags":[
        "builder"
    ],
    "wof:name":"BRIDGE END BUILDERS",
    "wof:placetype":"venue"
},
  "geometry": {"coordinates":[-3.823039,54.933456],"type":"Point"}
}