{
  "type": "Feature",
  "properties": {
    "addr:full":"Chapel House, Chapel Yard, Potton Sandy Bedfordshire SG19 2YP",
    "addr:postcode":"sg19 2yp",
    "iso:country":"GB",
    "sg:address":"Chapel House, Chapel Yard, Potton",
    "sg:city":"Sandy",
    "sg:classifiers":[
        {
            "category":"Freight",
            "type":"Transportation"
        }
    ],
    "sg:phone":"+44 1767 260206",
    "sg:postcode":"SG19 2YP",
    "sg:province":"Bedfordshire",
    "sg:tags":[
        "haulage",
        "road"
    ],
    "wof:name":"T B Kitchener & Co. Ltd.",
    "wof:placetype":"venue"
},
  "geometry": {"coordinates":[-0.2161410004,52.1265907288],"type":"Point"}
}