{
  "type": "Feature",
  "properties": {
    "iso:country":"GB",
    "sg:address":"Grange Medical Group, 1 Beaufort Rd",
    "sg:city":"Edinburgh",
    "sg:classifiers":[
        {
            "category":"Health Services",
            "subcategory":"Doctor",
            "type":"Services"
        }
    ],
    "sg:phone":"+44 131 447 1646",
    "sg:postcode":"EH9 1AG",
    "sg:province":"City of Edinburgh",
    "sg:tags":[
        "practitioners"
    ],
    "wof:name":"Susan Buck",
    "wof:placetype":"venue"
},
  "geometry": {"coordinates":[-3.188699007,55.9380493164],"type":"Point"}
}