{
  "type": "Feature",
  "properties": {
    "addr:full":"120 High Street, Portishead Bristol Somerset BS20 6PT",
    "addr:housenumber":"120",
    "addr:postcode":"bs20 6pt",
    "addr:street":"High Street",
    "iso:country":"GB",
    "sg:address":"120 High Street, Portishead",
    "sg:city":"Bristol",
    "sg:classifiers":[
        {
            "category":"Autos & Motor Vehicles",
            "subcategory":"Automobile Sales",
            "type":"Retail Goods"
        },
        {
            "category":"Retail",
            "subcategory":"Auto Rental",
            "type":"Services"
        }
    ],
    "sg:phone":"+44 1275 843444",
    "sg:postcode":"BS20 6PT",
    "sg:province":"Somerset",
    "sg:tags":[
        "car",
        "hire",
        "van",
        "truck"
    ],
    "wof:name":"Practical Car & Van Rental",
    "wof:placetype":"venue"
},
  "geometry": {"coordinates":[-2.768585,51.481628],"type":"Point"}
}