{
  "type": "Feature",
  "properties": {
    "addr:full":"17a Stour St Canterbury Kent CT1 2NR",
    "addr:housenumber":"17a",
    "addr:postcode":"ct1 2nr",
    "addr:street":"Stour St",
    "iso:country":"GB",
    "sg:address":"17a Stour St",
    "sg:city":"Canterbury",
    "sg:classifiers":[
        {
            "category":"Real Estate",
            "subcategory":"Architect",
            "type":"Services"
        }
    ],
    "sg:phone":"+44 1227 765958",
    "sg:postcode":"CT1 2NR",
    "sg:province":"Kent",
    "wof:name":"Roger Mason Angus Architects",
    "wof:placetype":"venue"
},
  "geometry": {"coordinates":[1.077915,51.278812],"type":"Point"}
}