{
  "type": "Feature",
  "properties": {
    "addr:full":"Humberdale Way, Warboys Huntingdon Bedfordshire PE28 2RX",
    "addr:postcode":"pe28 2rx",
    "addr:street":"Humberdale Way",
    "iso:country":"GB",
    "sg:address":"Humberdale Way, Warboys",
    "sg:city":"Huntingdon",
    "sg:classifiers":[
        {
            "category":"Education",
            "subcategory":"School",
            "type":"Public Place"
        }
    ],
    "sg:phone":"+44 1487 822317",
    "sg:postcode":"PE28 2RX",
    "sg:province":"Bedfordshire",
    "sg:tags":[
        "local",
        "authority"
    ],
    "wof:name":"Warboys Community Primary School",
    "wof:placetype":"venue"
},
  "geometry": {"coordinates":[-0.078339003,52.4035797119],"type":"Point"}
}