{
  "type": "Feature",
  "properties": {
    "addr:full":"156 Ralston Rd Campbeltown Argyll and Bute PA28 6LQ",
    "addr:housenumber":"156",
    "addr:postcode":"pa28 6lq",
    "addr:street":"Ralston Rd",
    "iso:country":"GB",
    "sg:address":"156 Ralston Rd",
    "sg:city":"Campbeltown",
    "sg:classifiers":[
        {
            "category":"Military Area",
            "subcategory":"Air Force Base",
            "type":"Public Place"
        }
    ],
    "sg:phone":"+44 1586 554959",
    "sg:postcode":"PA28 6LQ",
    "sg:province":"Argyll and Bute",
    "sg:tags":[
        "taxi",
        "hire",
        "private"
    ],
    "wof:name":"Davaar Taxis",
    "wof:placetype":"venue"
},
  "geometry": {"coordinates":[-5.610239,55.431419],"type":"Point"}
}