{
  "type": "Feature",
  "properties": {
    "iso:country":"GB",
    "sg:address":"1 Sheep Mkt",
    "sg:city":"Spalding",
    "sg:classifiers":[
        {
            "category":"Food & Beverages",
            "subcategory":"Bakery",
            "type":"Retail Goods"
        }
    ],
    "sg:postcode":"PE11 1BH",
    "sg:province":"Lincolnshire",
    "sg:tags":[
        "baker"
    ],
    "wof:name":"Atkins,S R B,",
    "wof:placetype":"venue"
},
  "geometry": {"coordinates":[-0.1532160044,52.787525177],"type":"Point"}
}