{
  "type": "Feature",
  "properties": {
    "iso:country":"GB",
    "sg:address":"6 Blackwood Cres",
    "sg:city":"Milton Keynes",
    "sg:classifiers":[
        {
            "category":"Utilities",
            "subcategory":"Sewage",
            "type":"Services"
        }
    ],
    "sg:phone":"+44 1908 220845",
    "sg:postcode":"MK13 0LP",
    "sg:province":"Buckinghamshire",
    "sg:tags":[
        "acoustic",
        "consultant"
    ],
    "wof:name":"Beatty Simon",
    "wof:placetype":"venue"
},
  "geometry": {"coordinates":[-0.799156,52.058891],"type":"Point"}
}