{
  "type": "Feature",
  "properties": {
    "addr:full":"2 Silverdale Road Burgess Hill East Sussex RH15 0EF",
    "addr:housenumber":"2",
    "addr:postcode":"rh15 0ef",
    "addr:street":"Silverdale Road",
    "iso:country":"GB",
    "sg:address":"2 Silverdale Road",
    "sg:city":"Burgess Hill",
    "sg:classifiers":[
        {
            "category":"Health Services",
            "subcategory":"Nursing And Care Facility",
            "type":"Services"
        }
    ],
    "sg:postcode":"RH15 0EF",
    "sg:province":"East Sussex",
    "sg:tags":[
        "home"
    ],
    "wof:name":"Oak Lodge Nursing Home",
    "wof:placetype":"venue"
},
  "geometry": {"coordinates":[-0.1253809929,50.9527511597],"type":"Point"}
}