{
  "type": "Feature",
  "properties": {
    "iso:country":"GB",
    "sg:address":"Refuge House, 5 Bedford Street",
    "sg:city":"Leeds",
    "sg:classifiers":[
        {
            "category":"Real Estate",
            "subcategory":"Real Estate Agent",
            "type":"Services"
        }
    ],
    "sg:phone":"+44 113 243 3434",
    "sg:postcode":"LS1 5PZ",
    "sg:province":"West Yorkshire",
    "wof:name":"David Price",
    "wof:placetype":"venue"
},
  "geometry": {"coordinates":[-1.54814,53.79858],"type":"Point"}
}