{
  "type": "Feature",
  "properties": {
    "addr:full":"Woodstock, Pett Bottom Canterbury Kent CT4 5PB",
    "addr:postcode":"ct4 5pb",
    "addr:street":"Pett Bottom",
    "iso:country":"GB",
    "sg:address":"Woodstock, Pett Bottom",
    "sg:city":"Canterbury",
    "sg:classifiers":[
        {
            "category":"Professional",
            "subcategory":"Engineering",
            "type":"Services"
        }
    ],
    "sg:postcode":"CT4 5PB",
    "sg:province":"Kent",
    "sg:tags":[
        "contractor",
        "electrical",
        "engineer"
    ],
    "wof:name":"J C Swain",
    "wof:placetype":"venue"
},
  "geometry": {"coordinates":[1.093781,51.226608],"type":"Point"}
}