{
  "type": "Feature",
  "properties": {
    "iso:country":"GB",
    "sg:address":"14 Hobill Close, Leicester Forest East",
    "sg:city":"Leicester",
    "sg:classifiers":[
        {
            "category":"Building & Trades",
            "subcategory":"Construction",
            "type":"Services"
        }
    ],
    "sg:postcode":"LE3 3PS",
    "sg:province":"Leicestershire",
    "sg:tags":[
        "roofing"
    ],
    "wof:name":"P J & J B Glennon & Sons Ltd.",
    "wof:placetype":"venue"
},
  "geometry": {"coordinates":[-1.210348,52.621319],"type":"Point"}
}