{
  "type": "Feature",
  "properties": {
    "addr:full":"Old Station Road Carmarthen Carmarthenshire SA31 1LP",
    "addr:postcode":"sa31 1lp",
    "addr:street":"Old Station Road",
    "iso:country":"GB",
    "sg:address":"Old Station Road",
    "sg:city":"Carmarthen",
    "sg:classifiers":[
        {
            "category":"Retail",
            "subcategory":"Auto Repair",
            "type":"Services"
        }
    ],
    "sg:phone":"+44 1267 234925",
    "sg:postcode":"SA31 1LP",
    "sg:province":"Carmarthenshire",
    "sg:tags":[
        "modification",
        "garage"
    ],
    "wof:name":"Peter Jones Motor Body Repairs",
    "wof:placetype":"venue"
},
  "geometry": {"coordinates":[-4.3022751808,51.856010437],"type":"Point"}
}