{
  "type": "Feature",
  "properties": {
    "iso:country":"GB",
    "sg:address":"139 Allaway Avenue",
    "sg:city":"Portsmouth",
    "sg:classifiers":[
        {
            "category":"Food & Beverages",
            "subcategory":"Meat & Fish",
            "type":"Retail Goods"
        }
    ],
    "sg:phone":"+44 23 9237 6288",
    "sg:postcode":"PO6 4HE",
    "sg:province":"Hampshire",
    "sg:tags":[
        "butcher"
    ],
    "wof:name":"Greenfields Butchers",
    "wof:placetype":"venue"
},
  "geometry": {"coordinates":[-1.092694,50.849648],"type":"Point"}
}