{
  "type": "Feature",
  "properties": {
    "addr:full":"Old Manse Whitehills, New Deer Turriff Aberdeenshire AB53 6UH",
    "addr:postcode":"ab53 6uh",
    "addr:street":"Whitehills",
    "iso:country":"GB",
    "sg:address":"Old Manse Whitehills, New Deer",
    "sg:city":"Turriff",
    "sg:classifiers":[
        {
            "category":"Retail",
            "subcategory":"Storage",
            "type":"Services"
        }
    ],
    "sg:phone":"+44 1771 653737",
    "sg:postcode":"AB53 6UH",
    "sg:province":"Aberdeenshire",
    "sg:tags":[
        "household",
        "removal",
        "operation",
        "facility"
    ],
    "wof:name":"Whitehills Storage Co",
    "wof:placetype":"venue"
},
  "geometry": {"coordinates":[-2.1930038929,57.5111465454],"type":"Point"}
}