{
  "type": "Feature",
  "properties": {
    "iso:country":"GB",
    "sg:address":"21 Atholl Road",
    "sg:city":"Pitlochry",
    "sg:classifiers":[
        {
            "category":"Professional",
            "subcategory":"Lawyer & Legal Services",
            "type":"Services"
        }
    ],
    "sg:phone":"+44 1796 472409",
    "sg:postcode":"PH16 5BX",
    "sg:province":"Perth and Kinross",
    "sg:tags":[
        "solicitor"
    ],
    "wof:name":"Macnab Gordon & Douglas",
    "wof:placetype":"venue"
},
  "geometry": {"coordinates":[-3.729562,56.701462],"type":"Point"}
}