{
  "type": "Feature",
  "properties": {
    "iso:country":"GB",
    "sg:address":"Corfe Mullen Library, 54 Wareham Road, Corfe Mullen",
    "sg:city":"Wimborne",
    "sg:classifiers":[
        {
            "category":"Education",
            "subcategory":"Library",
            "type":"Public Place"
        }
    ],
    "sg:phone":"+44 1202 659755",
    "sg:postcode":"BH21 3LE",
    "sg:province":"Dorset",
    "sg:tags":[
        "book"
    ],
    "wof:name":"Corfe Mullen Library",
    "wof:placetype":"venue"
},
  "geometry": {"coordinates":[-2.0157399178,50.7767601013],"type":"Point"}
}