{
  "type": "Feature",
  "properties": {
    "iso:country":"GB",
    "sg:address":"42 Union Street",
    "sg:city":"Melksham",
    "sg:classifiers":[
        {
            "category":"Professional",
            "subcategory":"Engineering",
            "type":"Services"
        }
    ],
    "sg:postcode":"SN12 7PR",
    "sg:province":"Wiltshire",
    "sg:tags":[
        "gas",
        "engineer"
    ],
    "wof:name":"B K L Gas Services",
    "wof:placetype":"venue"
},
  "geometry": {"coordinates":[-2.1370360851,51.3749809265],"type":"Point"}
}