{
  "type": "Feature",
  "properties": {
    "addr:full":"Leisure Centre, High Street Spennymoor Durham DL16 6DB",
    "addr:postcode":"dl16 6db",
    "addr:street":"High Street",
    "iso:country":"GB",
    "sg:address":"Leisure Centre, High Street",
    "sg:city":"Spennymoor",
    "sg:classifiers":[
        {
            "category":"Community Center",
            "type":"Public Place"
        }
    ],
    "sg:phone":"+44 1388 811877",
    "sg:postcode":"DL16 6DB",
    "sg:province":"Durham",
    "sg:tags":[
        "recreation",
        "leisure",
        "centre"
    ],
    "wof:name":"South Durham Gym Club",
    "wof:placetype":"venue"
},
  "geometry": {"coordinates":[-1.5822139978,54.7020606995],"type":"Point"}
}