{
  "type": "Feature",
  "properties": {
    "addr:full":"Carew Quarries, Carew Cheriton Tenby Pembrokeshire SA70 8SR",
    "addr:postcode":"sa70 8sr",
    "addr:street":"Cheriton;Pembrokeshire",
    "iso:country":"GB",
    "sg:address":"Carew Quarries, Carew Cheriton",
    "sg:city":"Tenby",
    "sg:classifiers":[
        {
            "category":"Manufacturing",
            "subcategory":"Glass & Minerals",
            "type":"Manufacturing & Wholesale Goods"
        }
    ],
    "sg:phone":"+44 1646 651326",
    "sg:postcode":"SA70 8SR",
    "sg:province":"Pembrokeshire",
    "sg:tags":[
        "chalk",
        "stone",
        "slate"
    ],
    "wof:name":"Thomas Scourfield & Sons",
    "wof:placetype":"venue"
},
  "geometry": {"coordinates":[-4.71205616,51.6767997742],"type":"Point"}
}