{
  "type": "Feature",
  "properties": {
    "addr:full":"209 Reede Road Dagenham Essex RM10 8EH",
    "addr:housenumber":"209",
    "addr:postcode":"rm10 8eh",
    "addr:street":"Reede Road",
    "iso:country":"GB",
    "sg:address":"209 Reede Road",
    "sg:city":"Dagenham",
    "sg:classifiers":[
        {
            "category":"Fast Food",
            "type":"Food & Drink"
        }
    ],
    "sg:postcode":"RM10 8EH",
    "sg:province":"Essex",
    "sg:tags":[
        "away",
        "take"
    ],
    "wof:name":"Yong's Chinese Take-Away",
    "wof:placetype":"venue"
},
  "geometry": {"coordinates":[0.160644,51.545174],"type":"Point"}
}