{
  "type": "Feature",
  "properties": {
    "addr:full":"141 Coxtie Green Rd Brentwood Essex CM14 5PT",
    "addr:housenumber":"141",
    "addr:postcode":"cm14 5pt",
    "addr:street":"Coxtie Green Rd",
    "iso:country":"GB",
    "sg:address":"141 Coxtie Green Rd",
    "sg:city":"Brentwood",
    "sg:classifiers":[
        {
            "category":"Wholesale",
            "subcategory":"Scrap",
            "type":"Manufacturing & Wholesale Goods"
        }
    ],
    "sg:phone":"+44 1277 372637",
    "sg:postcode":"CM14 5PT",
    "sg:province":"Essex",
    "sg:tags":[
        "waste",
        "metal"
    ],
    "wof:name":"E H S & G Recycling",
    "wof:placetype":"venue"
},
  "geometry": {"coordinates":[0.2596949935,51.6398506165],"type":"Point"}
}