{
  "type": "Feature",
  "properties": {
    "iso:country":"GB",
    "sg:address":"1b Queen Street",
    "sg:city":"Edinburgh",
    "sg:classifiers":[
        {
            "category":"Professional",
            "subcategory":"Printing & Photocopies",
            "type":"Services"
        }
    ],
    "sg:phone":"+44 131 440 0246",
    "sg:postcode":"EH2 1JB",
    "sg:province":"City of Edinburgh",
    "sg:tags":[
        "plate",
        "lithographic",
        "maker"
    ],
    "wof:name":"Macdonald Lindsay Pindar Plc",
    "wof:placetype":"venue"
},
  "geometry": {"coordinates":[-3.193578,55.955563],"type":"Point"}
}