{
  "type": "Feature",
  "properties": {
    "addr:full":"32 Church Street Cromer Norfolk NR27 9ES",
    "addr:housenumber":"32",
    "addr:postcode":"nr27 9es",
    "addr:street":"Church Street",
    "iso:country":"GB",
    "sg:address":"32 Church Street",
    "sg:city":"Cromer",
    "sg:classifiers":[
        {
            "category":"Bars & Pubs",
            "type":"Food & Drink"
        },
        {
            "category":"Community Center",
            "subcategory":"Social",
            "type":"Public Place"
        }
    ],
    "sg:phone":"+44 1263 513135",
    "sg:postcode":"NR27 9ES",
    "sg:province":"Norfolk",
    "sg:tags":[
        "pubs",
        "house",
        "inn",
        "activity"
    ],
    "wof:name":"The Albion",
    "wof:placetype":"venue"
},
  "geometry": {"coordinates":[1.302334,52.930767],"type":"Point"}
}