{
  "type": "Feature",
  "properties": {
    "iso:country":"GB",
    "sg:address":"35-37 Leg St",
    "sg:city":"Oswestry",
    "sg:classifiers":[
        {
            "category":"Professional",
            "subcategory":"Business Services",
            "type":"Services"
        }
    ],
    "sg:phone":"+44 1691 671256",
    "sg:postcode":"SY11 2HG",
    "sg:province":"Shropshire",
    "sg:tags":[
        "food",
        "import",
        "export",
        "agent"
    ],
    "wof:name":"Orchard Foods (Oswestry) Ltd",
    "wof:placetype":"venue"
},
  "geometry": {"coordinates":[-3.053222,52.859455],"type":"Point"}
}