{
  "type": "Feature",
  "properties": {
    "addr:full":"Wales La Burton On Trent Derbyshire DE13 8JF",
    "addr:postcode":"de13 8jf",
    "addr:street":"On",
    "iso:country":"GB",
    "sg:address":"Wales La",
    "sg:city":"Burton On Trent",
    "sg:classifiers":[
        {
            "category":"Place Of Worship",
            "type":"Public Place"
        }
    ],
    "sg:phone":"+44 1283 713104",
    "sg:postcode":"DE13 8JF",
    "sg:province":"Derbyshire",
    "wof:name":"Our Lady's Church",
    "wof:placetype":"venue"
},
  "geometry": {"coordinates":[-1.7262289524,52.7645187378],"type":"Point"}
}