{
  "type": "Feature",
  "properties": {
    "iso:country":"GB",
    "sg:address":"49 Collingwood Road",
    "sg:city":"Chorley",
    "sg:classifiers":[
        {
            "category":"Building & Trades",
            "subcategory":"Construction",
            "type":"Services"
        }
    ],
    "sg:phone":"+44 1257 261294",
    "sg:postcode":"PR7 2PN",
    "sg:province":"Lancashire",
    "sg:tags":[
        "builder"
    ],
    "wof:name":"Building & Property Repairs",
    "wof:placetype":"venue"
},
  "geometry": {"coordinates":[-2.6418960094,53.6469192505],"type":"Point"}
}