{
  "type": "Feature",
  "properties": {
    "addr:full":"230 Long Lane Southwark Greater London SE1 4QE",
    "addr:housenumber":"230",
    "addr:postcode":"se1 4qe",
    "addr:street":"Long Lane",
    "iso:country":"GB",
    "sg:address":"230 Long Lane",
    "sg:city":"Southwark",
    "sg:classifiers":[
        {
            "category":"Professional",
            "type":"Services"
        }
    ],
    "sg:phone":"+44 20 7357 6012",
    "sg:postcode":"SE1 4QE",
    "sg:province":"Greater London",
    "sg:tags":[
        "interior",
        "furnishers",
        "designer"
    ],
    "wof:name":"Mackenzies",
    "wof:placetype":"venue"
},
  "geometry": {"coordinates":[-0.0834060013,51.4982376099],"type":"Point"}
}