{
  "type": "Feature",
  "properties": {
    "addr:full":"16 Morningside Gdns Edinburgh City of Edinburgh EH10 5LE",
    "addr:housenumber":"16",
    "addr:postcode":"eh10 5le",
    "addr:street":"Morningside Gdns Edinburgh",
    "iso:country":"GB",
    "sg:address":"16 Morningside Gdns",
    "sg:city":"Edinburgh",
    "sg:classifiers":[
        {
            "category":"Personal",
            "subcategory":"Beauty Salon",
            "type":"Services"
        }
    ],
    "sg:postcode":"EH10 5LE",
    "sg:province":"City of Edinburgh",
    "sg:tags":[
        "unisex",
        "hairdresser"
    ],
    "wof:name":"Macintosh,Ian,",
    "wof:placetype":"venue"
},
  "geometry": {"coordinates":[-3.2225179672,55.922794342],"type":"Point"}
}