{
  "type": "Feature",
  "properties": {
    "addr:full":"85 South Parade Northallerton North Yorkshire DL7 8SJ",
    "addr:housenumber":"85",
    "addr:postcode":"dl7 8sj",
    "addr:street":"South Parade",
    "iso:country":"GB",
    "sg:address":"85 South Parade",
    "sg:city":"Northallerton",
    "sg:classifiers":[
        {
            "category":"Professional",
            "subcategory":"Lawyer & Legal Services",
            "type":"Services"
        }
    ],
    "sg:phone":"+44 1609 780486",
    "sg:postcode":"DL7 8SJ",
    "sg:province":"North Yorkshire",
    "sg:tags":[
        "advice",
        "counselling"
    ],
    "wof:name":"Alcohol & Drug Services",
    "wof:placetype":"venue"
},
  "geometry": {"coordinates":[-1.434526,54.336327],"type":"Point"}
}