{
  "type": "Feature",
  "properties": {
    "addr:full":"1st Floor Component Ho, Thomas St Manchester Cheshire M32 0LB",
    "addr:postcode":"m32 0lb",
    "addr:street":"Thomas St",
    "iso:country":"GB",
    "sg:address":"1st Floor Component Ho, Thomas St",
    "sg:city":"Manchester",
    "sg:classifiers":[
        {
            "category":"Government",
            "subcategory":"Fire Station",
            "type":"Public Place"
        }
    ],
    "sg:phone":"+44 161 865 6474",
    "sg:postcode":"M32 0LB",
    "sg:province":"Cheshire",
    "sg:tags":[
        "w'sale",
        "lighting"
    ],
    "wof:name":"Lighting Design Services",
    "wof:placetype":"venue"
},
  "geometry": {"coordinates":[-2.248809,53.479622],"type":"Point"}
}