{
  "type": "Feature",
  "properties": {
    "iso:country":"GB",
    "sg:address":"5 Ethelbert Road, Hawley",
    "sg:city":"Dartford",
    "sg:classifiers":[
        {
            "category":"Building & Trades",
            "subcategory":"Construction",
            "type":"Services"
        }
    ],
    "sg:postcode":"DA2 7SJ",
    "sg:province":"Kent",
    "sg:tags":[
        "roofing"
    ],
    "wof:name":"T Miller Roofing",
    "wof:placetype":"venue"
},
  "geometry": {"coordinates":[0.2206349969,51.4211997986],"type":"Point"}
}