{
  "type": "Feature",
  "properties": {
    "addr:full":"Mount Pleasant Farm, Forest Road, Hale Fordingbridge Dorset SP6 2NR",
    "addr:postcode":"sp6 2nr",
    "addr:street":"Forest Road",
    "iso:country":"GB",
    "sg:address":"Mount Pleasant Farm, Forest Road, Hale",
    "sg:city":"Fordingbridge",
    "sg:classifiers":[
        {
            "category":"Farming",
            "subcategory":"Livestock Farm",
            "type":"Manufacturing & Wholesale Goods"
        }
    ],
    "sg:postcode":"SP6 2NR",
    "sg:province":"Dorset",
    "sg:tags":[
        "others"
    ],
    "wof:name":"D E & P M Eyres",
    "wof:placetype":"venue"
},
  "geometry": {"coordinates":[-1.724047,50.969585],"type":"Point"}
}