{
  "type": "Feature",
  "properties": {
    "iso:country":"GB",
    "sg:address":"15 King Street",
    "sg:city":"Thetford",
    "sg:classifiers":[
        {
            "category":"Food & Beverages",
            "subcategory":"Bakery",
            "type":"Retail Goods"
        }
    ],
    "sg:phone":"+44 1842 752333",
    "sg:postcode":"IP24 2AN",
    "sg:province":"Norfolk",
    "sg:tags":[
        "baker"
    ],
    "wof:name":"The Bakers Oven",
    "wof:placetype":"venue"
},
  "geometry": {"coordinates":[0.7494760156,52.4137268066],"type":"Point"}
}