{
  "type": "Feature",
  "properties": {
    "addr:full":"Church Terrace, Rosehearty Fraserburgh Aberdeenshire AB43 7NP",
    "addr:postcode":"ab43 7np",
    "addr:street":"Church Terrace",
    "iso:country":"GB",
    "sg:address":"Church Terrace, Rosehearty",
    "sg:city":"Fraserburgh",
    "sg:classifiers":[
        {
            "category":"Education",
            "subcategory":"Library",
            "type":"Public Place"
        }
    ],
    "sg:phone":"+44 1346 571219",
    "sg:postcode":"AB43 7NP",
    "sg:province":"Aberdeenshire",
    "sg:tags":[
        "book"
    ],
    "wof:name":"Rosehearty Library",
    "wof:placetype":"venue"
},
  "geometry": {"coordinates":[-2.1159439087,57.6976394653],"type":"Point"}
}