{
  "type": "Feature",
  "properties": {
    "addr:full":"90 Wakefield Road, Rothwell Leeds West Yorkshire LS26 0SF",
    "addr:housenumber":"90",
    "addr:postcode":"ls26 0sf",
    "addr:street":"Wakefield Road",
    "iso:country":"GB",
    "sg:address":"90 Wakefield Road, Rothwell",
    "sg:city":"Leeds",
    "sg:classifiers":[
        {
            "category":"Professional",
            "subcategory":"Engineering",
            "type":"Services"
        }
    ],
    "sg:phone":"+44 113 282 9297",
    "sg:postcode":"LS26 0SF",
    "sg:province":"West Yorkshire",
    "sg:tags":[
        "contractor",
        "electrical",
        "engineer"
    ],
    "wof:name":"Rothwell Electrical Contractors",
    "wof:placetype":"venue"
},
  "geometry": {"coordinates":[-1.5071359873,53.7491722107],"type":"Point"}
}