{
  "type": "Feature",
  "properties": {
    "iso:country":"GB",
    "sg:address":"25 Montrose Avenue",
    "sg:city":"Luton",
    "sg:classifiers":[
        {
            "category":"Building & Trades",
            "subcategory":"Construction",
            "type":"Services"
        }
    ],
    "sg:phone":"+44 7976 521127",
    "sg:postcode":"LU3 1HW",
    "sg:province":"Bedfordshire",
    "sg:tags":[
        "tiling",
        "flooring",
        "contractor"
    ],
    "wof:name":"Montrose Interior Contracts",
    "wof:placetype":"venue"
},
  "geometry": {"coordinates":[-0.423664,51.896431],"type":"Point"}
}