{
  "type": "Feature",
  "properties": {
    "iso:country":"GB",
    "sg:address":"47 Berwick Street",
    "sg:city":"London",
    "sg:classifiers":[
        {
            "category":"Personal",
            "type":"Services"
        }
    ],
    "sg:phone":"+44 20 7439 1078",
    "sg:postcode":"W1F 8SQ",
    "sg:province":"Greater London",
    "sg:tags":[
        "tailor"
    ],
    "wof:name":"Nicos Demetriou",
    "wof:placetype":"venue"
},
  "geometry": {"coordinates":[-0.1362050027,51.5153923035],"type":"Point"}
}