{
  "type": "Feature",
  "properties": {
    "addr:full":"414a Edgware Rd Bayswater Greater London W2 1ED",
    "addr:housenumber":"414a",
    "addr:postcode":"w2 1ed",
    "addr:street":"Edgware Rd",
    "iso:country":"GB",
    "sg:address":"414a Edgware Rd",
    "sg:city":"Bayswater",
    "sg:classifiers":[
        {
            "category":"Home & Garden",
            "subcategory":"Hardware",
            "type":"Retail Goods"
        }
    ],
    "sg:phone":"+44 20 7723 2429",
    "sg:postcode":"W2 1ED",
    "sg:province":"Greater London",
    "sg:tags":[
        "product",
        "wire",
        "electrical"
    ],
    "wof:name":"A E Pierson & Co",
    "wof:placetype":"venue"
},
  "geometry": {"coordinates":[-0.1748089939,51.523311615],"type":"Point"}
}