{
  "type": "Feature",
  "properties": {
    "iso:country":"GB",
    "sg:address":"32 Castlefields",
    "sg:city":"Hartfield",
    "sg:classifiers":[
        {
            "category":"Building & Trades",
            "subcategory":"Construction",
            "type":"Services"
        }
    ],
    "sg:phone":"+44 1892 770738",
    "sg:postcode":"TN7 4JA",
    "sg:province":"East Sussex",
    "sg:tags":[
        "contractor",
        "paving",
        "driveway"
    ],
    "wof:name":"Mick Rush",
    "wof:placetype":"venue"
},
  "geometry": {"coordinates":[0.113856,51.103142],"type":"Point"}
}