{
  "type": "Feature",
  "properties": {
    "addr:full":"Folly Cottage, Barlavington Petworth West Sussex GU28 0LG",
    "addr:postcode":"gu28 0lg",
    "iso:country":"GB",
    "sg:address":"Folly Cottage, Barlavington",
    "sg:city":"Petworth",
    "sg:classifiers":[
        {
            "category":"Shopping",
            "subcategory":"Party Supplies",
            "type":"Retail Goods"
        }
    ],
    "sg:phone":"+44 1798 869231",
    "sg:postcode":"GU28 0LG",
    "sg:province":"West Sussex",
    "sg:tags":[
        "marquees",
        "floor",
        "tent"
    ],
    "wof:name":"CHARLESWORTH MARQUEES",
    "wof:placetype":"venue"
},
  "geometry": {"coordinates":[-0.6078540087,50.9861068726],"type":"Point"}
}