{
  "type": "Feature",
  "properties": {
    "addr:full":"10 Harbour St Whitstable Kent CT5 1AQ",
    "addr:housenumber":"10",
    "addr:postcode":"ct5 1aq",
    "addr:street":"Harbour St",
    "iso:country":"GB",
    "sg:address":"10 Harbour St",
    "sg:city":"Whitstable",
    "sg:classifiers":[
        {
            "category":"Education",
            "subcategory":"Preschool",
            "type":"Public Place"
        }
    ],
    "sg:phone":"+44 1227 276360",
    "sg:postcode":"CT5 1AQ",
    "sg:province":"Kent",
    "sg:tags":[
        "pre-school",
        "playgroups"
    ],
    "wof:name":"Harbour Street Playgroup",
    "wof:placetype":"venue"
},
  "geometry": {"coordinates":[1.025227,51.361599],"type":"Point"}
}