{
  "type": "Feature",
  "properties": {
    "iso:country":"GB",
    "sg:address":"Unit 1 Grange Rd Business Centre, Grange",
    "sg:city":"Christchurch",
    "sg:classifiers":[
        {
            "category":"Professional",
            "subcategory":"Engineering",
            "type":"Services"
        }
    ],
    "sg:postcode":"BH23 4JD",
    "sg:province":"Dorset",
    "sg:tags":[
        "contractor",
        "electrical",
        "engineer"
    ],
    "wof:name":"Phasor Electrical Contractors",
    "wof:placetype":"venue"
},
  "geometry": {"coordinates":[-1.737603,50.74041],"type":"Point"}
}