{
  "type": "Feature",
  "properties": {
    "addr:full":"Bohemia House, 78 Bohemia Road St Leonards-on-sea East Sussex TN37 6RN",
    "addr:housenumber":"78",
    "addr:postcode":"leonards-on-sea;tn37 6rn",
    "addr:street":"Bohemia Road St",
    "iso:country":"GB",
    "sg:address":"Bohemia House, 78 Bohemia Road",
    "sg:city":"St Leonards-on-sea",
    "sg:classifiers":[
        {
            "category":"Manufacturing",
            "subcategory":"Tools & Machinery",
            "type":"Manufacturing & Wholesale Goods"
        },
        {
            "category":"Insurance",
            "subcategory":"Insurance Agent",
            "type":"Services"
        }
    ],
    "sg:phone":"+44 1424 434675",
    "sg:postcode":"TN37 6RN",
    "sg:province":"East Sussex",
    "sg:tags":[
        "society",
        "friendly"
    ],
    "wof:name":"Ware Barton Mann Ltd.",
    "wof:placetype":"venue"
},
  "geometry": {"coordinates":[0.5592960119,50.862701416],"type":"Point"}
}