{
  "type": "Feature",
  "properties": {
    "iso:country":"GB",
    "sg:address":"Victoria House",
    "sg:city":"Bathgate",
    "sg:classifiers":[
        {
            "category":"Home & Garden",
            "subcategory":"Hardware",
            "type":"Retail Goods"
        }
    ],
    "sg:phone":"+44 1501 771632",
    "sg:postcode":"EH47 9LR",
    "sg:province":"North Lanarkshire",
    "sg:tags":[
        "retailer",
        "diy"
    ],
    "wof:name":"Victoria Wood Mill",
    "wof:placetype":"venue"
},
  "geometry": {"coordinates":[-3.698244,55.831444],"type":"Point"}
}