{
  "type": "Feature",
  "properties": {
    "iso:country":"GB",
    "sg:address":"154 Burnley Road East, Waterfoot",
    "sg:city":"Rossendale",
    "sg:classifiers":[
        {
            "category":"Home & Garden",
            "subcategory":"Hardware",
            "type":"Retail Goods"
        }
    ],
    "sg:phone":"+44 1706 223792",
    "sg:postcode":"BB4 9DF",
    "sg:province":"Lancashire",
    "sg:tags":[
        "sealant",
        "glue",
        "adhesives"
    ],
    "wof:name":"K M V Adhesives",
    "wof:placetype":"venue"
},
  "geometry": {"coordinates":[-2.2493910789,53.6965637207],"type":"Point"}
}