{
  "type": "Feature",
  "properties": {
    "iso:country":"GB",
    "sg:address":"18 Leopold Avenue, Handsworth Wood",
    "sg:city":"Birmingham",
    "sg:classifiers":[
        {
            "category":"Professional",
            "subcategory":"Engineering",
            "type":"Services"
        }
    ],
    "sg:phone":"+44 121 551 0518",
    "sg:postcode":"B20 1ER",
    "sg:province":"West Midlands",
    "wof:name":"J & B Engineering",
    "wof:placetype":"venue"
},
  "geometry": {"coordinates":[-1.9332159758,52.5253829956],"type":"Point"}
}