{
  "type": "Feature",
  "properties": {
    "addr:full":"5 Copley Road, Market Gate Doncaster South Yorkshire DN1 2PE",
    "addr:housenumber":"5",
    "addr:postcode":"dn1 2pe",
    "addr:street":"Copley Road Market Gate",
    "iso:country":"GB",
    "sg:address":"5 Copley Road, Market Gate",
    "sg:city":"Doncaster",
    "sg:classifiers":[
        {
            "category":"Professional",
            "subcategory":"Lawyer & Legal Services",
            "type":"Services"
        }
    ],
    "sg:phone":"+44 1302 819000",
    "sg:postcode":"DN1 2PE",
    "sg:province":"South Yorkshire",
    "sg:tags":[
        "solicitor"
    ],
    "wof:name":"Paul Bullen & Co Solicitors",
    "wof:placetype":"venue"
},
  "geometry": {"coordinates":[-1.1307560205,53.5258293152],"type":"Point"}
}