{
  "type": "Feature",
  "properties": {
    "addr:full":"Crisis & Support Helpline, Petherton Resource Centre, Hengrove Bristol City of Bristol BS14 9BP",
    "addr:postcode":"bs14 9bp",
    "iso:country":"GB",
    "sg:address":"Crisis & Support Helpline, Petherton Resource Centre, Hengrove",
    "sg:city":"Bristol",
    "sg:classifiers":[
        {
            "category":"Professional",
            "subcategory":"Lawyer & Legal Services",
            "type":"Services"
        }
    ],
    "sg:phone":"+44 117 983 0330",
    "sg:postcode":"BS14 9BP",
    "sg:province":"City of Bristol",
    "sg:tags":[
        "advice",
        "counselling"
    ],
    "wof:name":"Mind",
    "wof:placetype":"venue"
},
  "geometry": {"coordinates":[-2.56319,51.421661],"type":"Point"}
}