{
  "type": "Feature",
  "properties": {
    "addr:full":"Blackpool Road, Little Eccleston Preston Lancashire PR3 0ZQ",
    "addr:postcode":"pr3 0zq",
    "addr:street":"Blackpool Road",
    "iso:country":"GB",
    "sg:address":"Blackpool Road, Little Eccleston",
    "sg:city":"Preston",
    "sg:classifiers":[
        {
            "category":"Real Estate",
            "subcategory":"Real Estate Agent",
            "type":"Services"
        }
    ],
    "sg:phone":"+44 1995 670266",
    "sg:postcode":"PR3 0ZQ",
    "sg:province":"Lancashire",
    "wof:name":"Meadow Croft Caravan Park",
    "wof:placetype":"venue"
},
  "geometry": {"coordinates":[-2.8821790218,53.8582954407],"type":"Point"}
}