{
  "type": "Feature",
  "properties": {
    "addr:full":"50 Cereleton Park, Charlton Marshall Blandford Forum Dorset DT11 9PL",
    "addr:housenumber":"50",
    "addr:postcode":"dt11 9pl",
    "addr:street":"Cereleton Park",
    "iso:country":"GB",
    "sg:address":"50 Cereleton Park, Charlton Marshall",
    "sg:city":"Blandford Forum",
    "sg:classifiers":[
        {
            "category":"Personal",
            "type":"Services"
        }
    ],
    "sg:postcode":"DT11 9PL",
    "sg:province":"Dorset",
    "sg:tags":[
        "consultant",
        "fitness"
    ],
    "wof:name":"Caroline Barr Aerobics",
    "wof:placetype":"venue"
},
  "geometry": {"coordinates":[-2.146609,50.835884],"type":"Point"}
}