{
  "type": "Feature",
  "properties": {
    "iso:country":"GB",
    "sg:address":"3 Mill Road, Alconbury",
    "sg:city":"Huntingdon",
    "sg:classifiers":[
        {
            "category":"Bars & Pubs",
            "type":"Food & Drink"
        }
    ],
    "sg:postcode":"PE17 5EN",
    "sg:province":"Cambridgeshire",
    "sg:tags":[
        "pubs",
        "inn"
    ],
    "wof:name":"Alconbury Mill",
    "wof:placetype":"venue"
},
  "geometry": {"coordinates":[-0.25798,52.367081],"type":"Point"}
}