{
  "type": "Feature",
  "properties": {
    "addr:full":"7 Washington Buildings, Stanwell Road Penarth The Vale of Glamorgan CF64 2AD",
    "addr:housenumber":"7",
    "addr:postcode":"cf64 2ad",
    "addr:street":"Washington Buildings Stanwell Road;Vale",
    "iso:country":"GB",
    "sg:address":"7 Washington Buildings, Stanwell Road",
    "sg:city":"Penarth",
    "sg:classifiers":[
        {
            "category":"Shopping",
            "subcategory":"Pets & Pet Supplies",
            "type":"Retail Goods"
        }
    ],
    "sg:postcode":"CF64 2AD",
    "sg:province":"The Vale of Glamorgan",
    "wof:name":"Washington Pet Stores",
    "wof:placetype":"venue"
},
  "geometry": {"coordinates":[-3.1744139194,51.4389190674],"type":"Point"}
}