{
  "type": "Feature",
  "properties": {
    "addr:full":"67 East Parade, Heworth York North Yorkshire YO31 7YB",
    "addr:housenumber":"67",
    "addr:postcode":"yo31 7yb",
    "addr:street":"East Parade",
    "iso:country":"GB",
    "sg:address":"67 East Parade, Heworth",
    "sg:city":"York",
    "sg:classifiers":[
        {
            "category":"Shopping",
            "subcategory":"Pets & Pet Supplies",
            "type":"Retail Goods"
        }
    ],
    "sg:postcode":"YO31 7YB",
    "sg:province":"North Yorkshire",
    "wof:name":"Pets 'N' Stuff",
    "wof:placetype":"venue"
},
  "geometry": {"coordinates":[-1.0644990206,53.9655609131],"type":"Point"}
}