{
  "type": "Feature",
  "properties": {
    "addr:full":"271 Bury New Road, Whitefield Manchester Lancashire M45 8QP",
    "addr:housenumber":"271",
    "addr:postcode":"m45 8qp",
    "addr:street":"Bury New Road",
    "iso:country":"GB",
    "sg:address":"271 Bury New Road, Whitefield",
    "sg:city":"Manchester",
    "sg:classifiers":[
        {
            "category":"Bars & Pubs",
            "type":"Food & Drink"
        },
        {
            "category":"Community Center",
            "subcategory":"Social",
            "type":"Public Place"
        }
    ],
    "sg:phone":"+44 161 766 5968",
    "sg:postcode":"M45 8QP",
    "sg:province":"Lancashire",
    "sg:tags":[
        "pubs",
        "house",
        "inn",
        "activity"
    ],
    "wof:name":"Bulls Head Hotel",
    "wof:placetype":"venue"
},
  "geometry": {"coordinates":[-2.296875,53.5524673462],"type":"Point"}
}