{
  "type": "Feature",
  "properties": {
    "addr:full":"102 Beach Road, Scratby Great Yarmouth Norfolk NR29 3PG",
    "addr:housenumber":"102",
    "addr:postcode":"nr29 3pg",
    "addr:street":"Beach Road Scratby Great Yarmouth",
    "iso:country":"GB",
    "sg:address":"102 Beach Road, Scratby",
    "sg:city":"Great Yarmouth",
    "sg:classifiers":[
        {
            "category":"Personal",
            "subcategory":"Beauty Salon",
            "type":"Services"
        }
    ],
    "sg:phone":"+44 1493 731141",
    "sg:postcode":"NR29 3PG",
    "sg:province":"Norfolk",
    "sg:tags":[
        "unisex",
        "hairdresser"
    ],
    "wof:name":"Hairlines Hair Stylists",
    "wof:placetype":"venue"
},
  "geometry": {"coordinates":[1.7157889605,52.677947998],"type":"Point"}
}