{
  "type": "Feature",
  "properties": {
    "iso:country":"GB",
    "sg:address":"50 Ashley Road",
    "sg:city":"Newmarket",
    "sg:classifiers":[
        {
            "category":"Home & Garden",
            "subcategory":"Household Appliances",
            "type":"Retail Goods"
        }
    ],
    "sg:postcode":"CB8 8DA",
    "sg:province":"Cambridgeshire",
    "sg:tags":[
        "electrical"
    ],
    "wof:name":"Terry Moody Domestic Appliances",
    "wof:placetype":"venue"
},
  "geometry": {"coordinates":[0.4276,52.238914],"type":"Point"}
}