{
  "type": "Feature",
  "properties": {
    "addr:full":"22 Park View, Acton London Greater London W3 0PT",
    "addr:housenumber":"22",
    "addr:postcode":"w3 0pt",
    "addr:street":"Park View",
    "iso:country":"GB",
    "sg:address":"22 Park View, Acton",
    "sg:city":"London",
    "sg:classifiers":[
        {
            "category":"Social Services",
            "subcategory":"Job Training",
            "type":"Services"
        }
    ],
    "sg:postcode":"W3 0PT",
    "sg:province":"Greater London",
    "sg:tags":[
        "translator",
        "interpreter"
    ],
    "wof:name":"German Translations by Dehmel J G",
    "wof:placetype":"venue"
},
  "geometry": {"coordinates":[-0.2678959966,51.5216827393],"type":"Point"}
}