{
  "type": "Feature",
  "properties": {
    "iso:country":"GB",
    "sg:address":"8a Quantock Gardens",
    "sg:city":"Hastings",
    "sg:classifiers":[
        {
            "category":"Professional",
            "type":"Services"
        }
    ],
    "sg:phone":"+44 1424 434367",
    "sg:postcode":"TN34 3QB",
    "sg:province":"East Sussex",
    "sg:tags":[
        "repair",
        "tech",
        "maintenance"
    ],
    "wof:name":"Computer Repairs Services",
    "wof:placetype":"venue"
},
  "geometry": {"coordinates":[0.5985569954,50.8730278015],"type":"Point"}
}