{
  "type": "Feature",
  "properties": {
    "addr:full":"7 Barton Clo Shaftesbury Dorset SP7 8DJ",
    "addr:housenumber":"7;clo",
    "addr:postcode":"sp7 8dj",
    "addr:street":"Barton",
    "iso:country":"GB",
    "sg:address":"7 Barton Clo",
    "sg:city":"Shaftesbury",
    "sg:classifiers":[
        {
            "category":"Building & Trades",
            "subcategory":"Construction",
            "type":"Services"
        }
    ],
    "sg:phone":"+44 1747 850058",
    "sg:postcode":"SP7 8DJ",
    "sg:province":"Dorset",
    "sg:tags":[
        "decorator",
        "painter"
    ],
    "wof:name":"Silverstone Decorators",
    "wof:placetype":"venue"
},
  "geometry": {"coordinates":[-2.194287,51.007626],"type":"Point"}
}