{
  "type": "Feature",
  "properties": {
    "addr:full":"Unit 8 Swallow Mill, Swallow Street Stockport Cheshire SK1 3HJ",
    "addr:housenumber":"unit 8",
    "addr:postcode":"sk1 3hj",
    "addr:street":"Swallow Mill Swallow Street",
    "iso:country":"GB",
    "sg:address":"Unit 8 Swallow Mill, Swallow Street",
    "sg:city":"Stockport",
    "sg:classifiers":[
        {
            "category":"Manufacturing",
            "subcategory":"Printing",
            "type":"Manufacturing & Wholesale Goods"
        }
    ],
    "sg:phone":"+44 161 477 2799",
    "sg:postcode":"SK1 3HJ",
    "sg:province":"Cheshire",
    "sg:tags":[
        "bookbinder"
    ],
    "wof:name":"Stockport Bindery",
    "wof:placetype":"venue"
},
  "geometry": {"coordinates":[-2.1528949738,53.4021186829],"type":"Point"}
}