{
  "type": "Feature",
  "properties": {
    "addr:full":"Pontiago Moor, Pontiago Goodwick Pembrokeshire SA64 0JD",
    "addr:postcode":"sa64 0jd",
    "addr:street":"Pontiago;Pontiago;Pembrokeshire",
    "iso:country":"GB",
    "sg:address":"Pontiago Moor, Pontiago",
    "sg:city":"Goodwick",
    "sg:classifiers":[
        {
            "category":"Building & Trades",
            "subcategory":"Construction",
            "type":"Services"
        }
    ],
    "sg:phone":"+44 1348 891691",
    "sg:postcode":"SA64 0JD",
    "sg:province":"Pembrokeshire",
    "sg:tags":[
        "roofing"
    ],
    "wof:name":"Burn & Whitby",
    "wof:placetype":"venue"
},
  "geometry": {"coordinates":[-4.997849,52.000923],"type":"Point"}
}