{
  "type": "Feature",
  "properties": {
    "iso:country":"GB",
    "sg:address":"115 Boldon Lane",
    "sg:city":"South Shields",
    "sg:classifiers":[
        {
            "category":"Cinema",
            "subcategory":"Movie Rental",
            "type":"Entertainment"
        }
    ],
    "sg:postcode":"NE34 0AS",
    "sg:province":"Tyne and Wear",
    "sg:tags":[
        "video",
        "library"
    ],
    "wof:name":"Vision Videos",
    "wof:placetype":"venue"
},
  "geometry": {"coordinates":[-1.439515,54.972366],"type":"Point"}
}