{
  "type": "Feature",
  "properties": {
    "addr:full":"33 Central Ave, West Bridgford Nottingham Nottinghamshire NG2 5GQ",
    "addr:housenumber":"33",
    "addr:postcode":"ng2 5gq",
    "addr:street":"Central Ave",
    "iso:country":"GB",
    "sg:address":"33 Central Ave, West Bridgford",
    "sg:city":"Nottingham",
    "sg:classifiers":[
        {
            "category":"Shopping",
            "subcategory":"Gifts & Souvenirs",
            "type":"Retail Goods"
        }
    ],
    "sg:postcode":"NG2 5GQ",
    "sg:province":"Nottinghamshire",
    "sg:tags":[
        "poster",
        "card"
    ],
    "wof:name":"Central News & Cards",
    "wof:placetype":"venue"
},
  "geometry": {"coordinates":[-1.1261329651,52.9316635132],"type":"Point"}
}