{
  "type": "Feature",
  "properties": {
    "addr:full":"5-9 West Street Leominster Herefordshire HR6 8EP",
    "addr:housenumber":"5-9",
    "addr:postcode":"hr6 8ep",
    "addr:street":"West Street",
    "iso:country":"GB",
    "sg:address":"5-9 West Street",
    "sg:city":"Leominster",
    "sg:classifiers":[
        {
            "category":"Travel",
            "subcategory":"Hotels & Motels",
            "type":"Entertainment"
        }
    ],
    "sg:phone":"+44 1568 616347",
    "sg:postcode":"HR6 8EP",
    "sg:province":"Herefordshire",
    "wof:name":"The Chalet (Lickey Hills) Ltd.",
    "wof:placetype":"venue"
},
  "geometry": {"coordinates":[-2.739477,52.22665],"type":"Point"}
}