{
  "type": "Feature",
  "properties": {
    "addr:full":"1069 Maryhill Road Glasgow Glasgow City G20 9AX",
    "addr:housenumber":"1069",
    "addr:postcode":"g20 9ax",
    "addr:street":"Maryhill Road",
    "iso:country":"GB",
    "sg:address":"1069 Maryhill Road",
    "sg:city":"Glasgow",
    "sg:classifiers":[
        {
            "category":"Health Services",
            "subcategory":"Optometrist",
            "type":"Services"
        }
    ],
    "sg:phone":"+44 141 946 1954",
    "sg:postcode":"G20 9AX",
    "sg:province":"Glasgow City",
    "sg:tags":[
        "optician"
    ],
    "wof:name":"Errol Hornstein",
    "wof:placetype":"venue"
},
  "geometry": {"coordinates":[-4.2860221863,55.8875083923],"type":"Point"}
}