{
  "type": "Feature",
  "properties": {
    "addr:full":"42a Beckenham Lane Bromley Kent BR2 0DQ",
    "addr:housenumber":"42a",
    "addr:postcode":"br2 0dq",
    "addr:street":"Beckenham Lane",
    "iso:country":"GB",
    "sg:address":"42a Beckenham Lane",
    "sg:city":"Bromley",
    "sg:classifiers":[
        {
            "category":"Manufacturing",
            "subcategory":"Tools & Machinery",
            "type":"Manufacturing & Wholesale Goods"
        }
    ],
    "sg:phone":"+44 20 8402 7702",
    "sg:postcode":"BR2 0DQ",
    "sg:province":"Kent",
    "sg:tags":[
        "design",
        "maker"
    ],
    "wof:name":"R Winter & Co.",
    "wof:placetype":"venue"
},
  "geometry": {"coordinates":[0.005444,51.407269],"type":"Point"}
}