{
  "type": "Feature",
  "properties": {
    "addr:full":"Halewood Avenue, Kenton Newcastle-upon-tyne Tyne and Wear NE3 3RA",
    "addr:postcode":"ne3 3ra",
    "addr:street":"Halewood Avenue",
    "iso:country":"GB",
    "sg:address":"Halewood Avenue, Kenton",
    "sg:city":"Newcastle-upon-tyne",
    "sg:classifiers":[
        {
            "category":"Food & Beverages",
            "subcategory":"Bakery",
            "type":"Retail Goods"
        }
    ],
    "sg:phone":"+44 191 286 0025",
    "sg:postcode":"NE3 3RA",
    "sg:province":"Tyne and Wear",
    "sg:tags":[
        "baker"
    ],
    "wof:name":"Greggs",
    "wof:placetype":"venue"
},
  "geometry": {"coordinates":[-1.6522289515,55.0063552856],"type":"Point"}
}