{
  "type": "Feature",
  "properties": {
    "iso:country":"GB",
    "sg:address":"2-4 West Street",
    "sg:city":"Congleton",
    "sg:classifiers":[
        {
            "category":"Real Estate",
            "subcategory":"Real Estate Agent",
            "type":"Services"
        }
    ],
    "sg:phone":"+44 1260 271255",
    "sg:postcode":"CW12 1JR",
    "sg:province":"Cheshire",
    "wof:name":"Timothy A Brown",
    "wof:placetype":"venue"
},
  "geometry": {"coordinates":[-2.2151749134,53.1631736755],"type":"Point"}
}