{
  "type": "Feature",
  "properties": {
    "iso:country":"GB",
    "sg:address":"Countess Street",
    "sg:city":"Saltcoats",
    "sg:classifiers":[
        {
            "category":"Government",
            "subcategory":"City Hall",
            "type":"Public Place"
        }
    ],
    "sg:phone":"+44 1294 465121",
    "sg:postcode":"KA21 5HP",
    "sg:province":"North Ayrshire",
    "wof:name":"Saltcoats Town Hall",
    "wof:placetype":"venue"
},
  "geometry": {"coordinates":[-4.785041,55.633286],"type":"Point"}
}