{
  "type": "Feature",
  "properties": {
    "iso:country":"GB",
    "sg:address":"3 South Street",
    "sg:city":"Fochabers",
    "sg:classifiers":[
        {
            "category":"Social Services",
            "subcategory":"Retirement Home",
            "type":"Services"
        },
        {
            "category":"Organizations",
            "subcategory":"Non-profit Organization",
            "type":"Services"
        }
    ],
    "sg:phone":"+44 1343 821626",
    "sg:postcode":"IV32 7ED",
    "sg:province":"Moray",
    "sg:tags":[
        "voluntary",
        "residential",
        "organisation",
        "charitable",
        "care",
        "charity"
    ],
    "wof:name":"Cornerstone Community Care",
    "wof:placetype":"venue"
},
  "geometry": {"coordinates":[-3.115087,57.662163],"type":"Point"}
}