{
  "type": "Feature",
  "properties": {
    "addr:full":"37 Hornby Road Blackpool Lancashire FY1 4QJ",
    "addr:housenumber":"37",
    "addr:postcode":"fy1 4qj",
    "addr:street":"Hornby Road",
    "iso:country":"GB",
    "sg:address":"37 Hornby Road",
    "sg:city":"Blackpool",
    "sg:classifiers":[
        {
            "category":"Food & Beverages",
            "subcategory":"Liquor & Beverages",
            "type":"Retail Goods"
        }
    ],
    "sg:phone":"+44 1253 625420",
    "sg:postcode":"FY1 4QJ",
    "sg:province":"Lancashire",
    "sg:tags":[
        "beer",
        "wine",
        "spirit",
        "wines"
    ],
    "wof:name":"Booze Buster",
    "wof:placetype":"venue"
},
  "geometry": {"coordinates":[-3.050022,53.813877],"type":"Point"}
}