{
  "type": "Feature",
  "properties": {
    "iso:country":"GB",
    "sg:address":"Northop Road",
    "sg:city":"Flint",
    "sg:classifiers":[
        {
            "category":"Retail",
            "subcategory":"Auto Repair",
            "type":"Services"
        }
    ],
    "sg:phone":"+44 1352 733153",
    "sg:postcode":"CH6 5QG",
    "sg:province":"Flintshire",
    "sg:tags":[
        "modification",
        "garage"
    ],
    "wof:name":"Flint Filling Station",
    "wof:placetype":"venue"
},
  "geometry": {"coordinates":[-3.131417,53.212559],"type":"Point"}
}