{
  "type": "Feature",
  "properties": {
    "iso:country":"GB",
    "sg:address":"Little Acre, St Neots Road, Bolnhurst",
    "sg:city":"Bedford",
    "sg:classifiers":[
        {
            "category":"Farming",
            "subcategory":"Livestock Farm",
            "type":"Manufacturing & Wholesale Goods"
        }
    ],
    "sg:postcode":"MK44 2EP",
    "sg:province":"Bedfordshire",
    "sg:tags":[
        "others"
    ],
    "wof:name":"Daniel Hartop",
    "wof:placetype":"venue"
},
  "geometry": {"coordinates":[-0.4102239907,52.2257537842],"type":"Point"}
}