{
  "type": "Feature",
  "properties": {
    "iso:country":"GB",
    "sg:address":"241 Whitechapel Road",
    "sg:city":"London",
    "sg:classifiers":[
        {
            "category":"Restaurant",
            "type":"Food & Drink"
        }
    ],
    "sg:phone":"+44 20 7247 0982",
    "sg:postcode":"E1 1DB",
    "sg:province":"Greater London",
    "wof:name":"Wimpy Bar",
    "wof:placetype":"venue"
},
  "geometry": {"coordinates":[-0.061008,51.518951],"type":"Point"}
}