{
  "type": "Feature",
  "properties": {
    "addr:full":"117a New Road, Croxley Grn Rickmansworth Hertfordshire WD3 3EN",
    "addr:housenumber":"117a",
    "addr:postcode":"wd3 3en",
    "addr:street":"New Road Croxley Grn",
    "iso:country":"GB",
    "sg:address":"117a New Road, Croxley Grn",
    "sg:city":"Rickmansworth",
    "sg:classifiers":[
        {
            "category":"Professional",
            "subcategory":"Employment Agencies",
            "type":"Services"
        }
    ],
    "sg:postcode":"WD3 3EN",
    "sg:province":"Hertfordshire",
    "sg:tags":[
        "consultant"
    ],
    "wof:name":"Cedar Services",
    "wof:placetype":"venue"
},
  "geometry": {"coordinates":[-0.449146986,51.6484909058],"type":"Point"}
}