{
  "type": "Feature",
  "properties": {
    "iso:country":"GB",
    "sg:address":"18 Osborne Rd, Netheredge",
    "sg:city":"Sheffield",
    "sg:classifiers":[
        {
            "category":"Building & Trades",
            "subcategory":"Construction",
            "type":"Services"
        }
    ],
    "sg:postcode":"S11 9AY",
    "sg:province":"Derbyshire",
    "sg:tags":[
        "decorator",
        "painter"
    ],
    "wof:name":"Wright,Matthew,",
    "wof:placetype":"venue"
},
  "geometry": {"coordinates":[-1.4921950102,53.3606872559],"type":"Point"}
}