{
  "type": "Feature",
  "properties": {
    "addr:full":"38 Bladen Drive, Rushmere St Andrew Ipswich Suffolk IP4 5UG",
    "addr:housenumber":"38",
    "addr:postcode":"ip4 5ug",
    "addr:street":"Bladen Drive Rushmere St",
    "iso:country":"GB",
    "sg:address":"38 Bladen Drive, Rushmere St Andrew",
    "sg:city":"Ipswich",
    "sg:classifiers":[
        {
            "category":"Banks & Credit Unions",
            "subcategory":"Bank",
            "type":"Services"
        },
        {
            "category":"Professional",
            "subcategory":"Business Services",
            "type":"Services"
        }
    ],
    "sg:phone":"+44 1473 270573",
    "sg:postcode":"IP4 5UG",
    "sg:province":"Suffolk",
    "sg:tags":[
        "stocktaking",
        "inventory"
    ],
    "wof:name":"D S Spashett",
    "wof:placetype":"venue"
},
  "geometry": {"coordinates":[1.215221,52.051323],"type":"Point"}
}