{
  "type": "Feature",
  "properties": {
    "addr:full":"Stanedykehead Edinburgh City of Edinburgh EH16 6YE",
    "addr:postcode":"eh16 6ye",
    "iso:country":"GB",
    "sg:address":"Stanedykehead",
    "sg:city":"Edinburgh",
    "sg:classifiers":[
        {
            "category":"Building & Trades",
            "subcategory":"Landscaping Services",
            "type":"Services"
        },
        {
            "category":"Sports & Exercise",
            "subcategory":"Athletic Track",
            "type":"Entertainment"
        }
    ],
    "sg:phone":"+44 131 666 2264",
    "sg:postcode":"EH16 6YE",
    "sg:province":"City of Edinburgh",
    "sg:tags":[
        "racecourse",
        "ground",
        "racetrack",
        "contractor"
    ],
    "wof:name":"Liberton Greyhound Kennels",
    "wof:placetype":"venue"
},
  "geometry": {"coordinates":[-3.1777589321,55.9080505371],"type":"Point"}
}