{
  "type": "Feature",
  "properties": {
    "addr:full":"Church Street Harwich Essex CO12 3DR",
    "addr:postcode":"co12 3dr",
    "addr:street":"Church Street",
    "iso:country":"GB",
    "sg:address":"Church Street",
    "sg:city":"Harwich",
    "sg:classifiers":[
        {
            "category":"Bars & Pubs",
            "type":"Food & Drink"
        }
    ],
    "sg:phone":"+44 1255 502927",
    "sg:postcode":"CO12 3DR",
    "sg:province":"Essex",
    "sg:tags":[
        "pubs",
        "inn"
    ],
    "wof:name":"Hanover Inn",
    "wof:placetype":"venue"
},
  "geometry": {"coordinates":[1.2863069773,51.9469642639],"type":"Point"}
}