{
  "type": "Feature",
  "properties": {
    "addr:full":"201 Market St Manchester Greater Manchester M43 7AY",
    "addr:housenumber":"201",
    "addr:postcode":"m43 7ay",
    "addr:street":"Market St",
    "iso:country":"GB",
    "sg:address":"201 Market St",
    "sg:city":"Manchester",
    "sg:classifiers":[
        {
            "category":"Bars & Pubs",
            "type":"Food & Drink"
        }
    ],
    "sg:phone":"+44 161 371 6921",
    "sg:postcode":"M43 7AY",
    "sg:province":"Greater Manchester",
    "sg:tags":[
        "pubs",
        "inn"
    ],
    "wof:name":"Butchers Arms The",
    "wof:placetype":"venue"
},
  "geometry": {"coordinates":[-2.1434988976,53.4822998047],"type":"Point"}
}