{
  "type": "Feature",
  "properties": {
    "iso:country":"GB",
    "sg:address":"Hereford Road",
    "sg:city":"Bromyard",
    "sg:classifiers":[
        {
            "category":"Retail",
            "subcategory":"Auto Repair",
            "type":"Services"
        }
    ],
    "sg:phone":"+44 1885 483342",
    "sg:postcode":"HR7 4QU",
    "sg:province":"Herefordshire",
    "sg:tags":[
        "modification",
        "garage"
    ],
    "wof:name":"Top Garage (Bromyard 2000)",
    "wof:placetype":"venue"
},
  "geometry": {"coordinates":[-2.510399,52.189098],"type":"Point"}
}