{
  "type": "Feature",
  "properties": {
    "addr:full":"Kenmar, Beeswing Dumfries Dumfries and Galloway DG2 8JH",
    "addr:postcode":"dg2 8jh",
    "iso:country":"GB",
    "sg:address":"Kenmar, Beeswing",
    "sg:city":"Dumfries",
    "sg:classifiers":[
        {
            "category":"Retail",
            "subcategory":"Auto Repair",
            "type":"Services"
        }
    ],
    "sg:phone":"+44 1387 760662",
    "sg:postcode":"DG2 8JH",
    "sg:province":"Dumfries and Galloway",
    "sg:tags":[
        "body",
        "car",
        "repairer",
        "modification",
        "garage"
    ],
    "wof:name":"K Niven",
    "wof:placetype":"venue"
},
  "geometry": {"coordinates":[-3.7305688858,55.0051651001],"type":"Point"}
}