{
  "type": "Feature",
  "properties": {
    "addr:full":"Sterling Ct, Eastworth Rd Chertsey Surrey KT16 8DF",
    "addr:postcode":"kt16 8df",
    "addr:street":"Sterling Ct Eastworth Rd",
    "iso:country":"GB",
    "sg:address":"Sterling Ct, Eastworth Rd",
    "sg:city":"Chertsey",
    "sg:classifiers":[
        {
            "category":"Professional",
            "subcategory":"Computer Services",
            "type":"Services"
        }
    ],
    "sg:postcode":"KT16 8DF",
    "sg:province":"Surrey",
    "sg:tags":[
        "system",
        "software"
    ],
    "wof:name":"Synon Europe Ltd",
    "wof:placetype":"venue"
},
  "geometry": {"coordinates":[-0.5082539916,51.3881988525],"type":"Point"}
}