{
  "type": "Feature",
  "properties": {
    "addr:full":"1 Helford Walk Woking Surrey GU21 3PL",
    "addr:housenumber":"1",
    "addr:postcode":"gu21 3pl",
    "addr:street":"Helford Walk",
    "iso:country":"GB",
    "sg:address":"1 Helford Walk",
    "sg:city":"Woking",
    "sg:classifiers":[
        {
            "category":"Taxi",
            "type":"Transportation"
        },
        {
            "category":"Military Area",
            "subcategory":"Air Force Base",
            "type":"Public Place"
        }
    ],
    "sg:phone":"+44 1483 763815",
    "sg:postcode":"GU21 3PL",
    "sg:province":"Surrey",
    "sg:tags":[
        "hire",
        "private",
        "vehicle"
    ],
    "wof:name":"Elliotts Private Hire",
    "wof:placetype":"venue"
},
  "geometry": {"coordinates":[-0.594045,51.315495],"type":"Point"}
}