{
  "type": "Feature",
  "properties": {
    "addr:full":"East Marsh Rd Barrow Upon Humber Lincolnshire DN19 7NQ",
    "addr:postcode":"dn19 7nq",
    "addr:street":"East Marsh Rd",
    "iso:country":"GB",
    "sg:address":"East Marsh Rd",
    "sg:city":"Barrow Upon Humber",
    "sg:classifiers":[
        {
            "category":"Shopping",
            "subcategory":"Pets & Pet Supplies",
            "type":"Retail Goods"
        }
    ],
    "sg:phone":"+44 1469 532810",
    "sg:postcode":"DN19 7NQ",
    "sg:province":"Lincolnshire",
    "wof:name":"Five Seasons Pet Supplies",
    "wof:placetype":"venue"
},
  "geometry": {"coordinates":[-0.30568,53.711449],"type":"Point"}
}