{
  "type": "Feature",
  "properties": {
    "addr:full":"Hawkins Lane Burton-on-trent Derbyshire DE14 1PY",
    "addr:postcode":"de14 1py",
    "addr:street":"Hawkins Lane",
    "iso:country":"GB",
    "sg:address":"Hawkins Lane",
    "sg:city":"Burton-on-trent",
    "sg:classifiers":[
        {
            "category":"Building & Trades",
            "subcategory":"Equipment Rental",
            "type":"Services"
        }
    ],
    "sg:phone":"+44 1283 537333",
    "sg:postcode":"DE14 1PY",
    "sg:province":"Derbyshire",
    "sg:tags":[
        "hire",
        "centre"
    ],
    "wof:name":"Speedy Hire",
    "wof:placetype":"venue"
},
  "geometry": {"coordinates":[-1.632988,52.809162],"type":"Point"}
}