{
  "type": "Feature",
  "properties": {
    "iso:country":"GB",
    "sg:address":"Garth Pwt, Clatter",
    "sg:city":"Caersws",
    "sg:classifiers":[
        {
            "category":"Farming",
            "subcategory":"Livestock Farm",
            "type":"Manufacturing & Wholesale Goods"
        }
    ],
    "sg:phone":"+44 1686 420564",
    "sg:postcode":"SY17 5NR",
    "sg:province":"Powys",
    "sg:tags":[
        "others"
    ],
    "wof:name":"Nigel Pugh",
    "wof:placetype":"venue"
},
  "geometry": {"coordinates":[-3.4303290844,52.5167350769],"type":"Point"}
}