{
  "type": "Feature",
  "properties": {
    "addr:full":"6d Church St Woodbridge Suffolk IP12 1DH",
    "addr:housenumber":"6d",
    "addr:postcode":"ip12 1dh",
    "addr:street":"Church St",
    "iso:country":"GB",
    "sg:address":"6d Church St",
    "sg:city":"Woodbridge",
    "sg:classifiers":[
        {
            "category":"Real Estate",
            "subcategory":"Real Estate Agent",
            "type":"Services"
        }
    ],
    "sg:postcode":"IP12 1DH",
    "sg:province":"Suffolk",
    "wof:name":"Dyson,John,",
    "wof:placetype":"venue"
},
  "geometry": {"coordinates":[1.3161059618,52.0928497314],"type":"Point"}
}