{
  "type": "Feature",
  "properties": {
    "iso:country":"GB",
    "sg:address":"Lyme Valley Rd",
    "sg:city":"Newcastle",
    "sg:classifiers":[
        {
            "category":"Building & Trades",
            "subcategory":"Construction",
            "type":"Services"
        }
    ],
    "sg:phone":"+44 1782 715023",
    "sg:postcode":"ST5 3TF",
    "sg:province":"Staffordshire",
    "sg:tags":[
        "roofing"
    ],
    "wof:name":"Newcastle Roofing Supplies",
    "wof:placetype":"venue"
},
  "geometry": {"coordinates":[-2.224587,53.006416],"type":"Point"}
}