{
  "type": "Feature",
  "properties": {
    "iso:country":"GB",
    "sg:address":"Hunters Quay, Ridgeway Close",
    "sg:city":"Heathfield",
    "sg:classifiers":[
        {
            "category":"Shopping",
            "subcategory":"Photographic Equipment",
            "type":"Retail Goods"
        }
    ],
    "sg:postcode":"TN21 8NS",
    "sg:province":"East Sussex",
    "sg:tags":[
        "supply"
    ],
    "wof:name":"K J P",
    "wof:placetype":"venue"
},
  "geometry": {"coordinates":[0.252349,50.971859],"type":"Point"}
}