{
  "type": "Feature",
  "properties": {
    "iso:country":"GB",
    "sg:address":"Glass Street, Hanley",
    "sg:city":"Stoke-on-trent",
    "sg:classifiers":[
        {
            "category":"Parking",
            "type":"Transportation"
        }
    ],
    "sg:phone":"+44 20 7499 7050",
    "sg:postcode":"ST1 2ET",
    "sg:province":"Staffordshire",
    "sg:tags":[
        "car",
        "park"
    ],
    "wof:name":"Ncp",
    "wof:placetype":"venue"
},
  "geometry": {"coordinates":[-2.1736540794,53.0273704529],"type":"Point"}
}