{
  "type": "Feature",
  "properties": {
    "iso:country":"GB",
    "sg:address":"99 Great Russell Street",
    "sg:city":"London",
    "sg:classifiers":[
        {
            "category":"Professional",
            "subcategory":"Engineering",
            "type":"Services"
        }
    ],
    "sg:phone":"+44 20 7580 2412",
    "sg:postcode":"WC1B 3LA",
    "sg:province":"Greater London",
    "sg:tags":[
        "civil",
        "consulting",
        "engineer"
    ],
    "wof:name":"Charles Haswell & Partners Ltd.",
    "wof:placetype":"venue"
},
  "geometry": {"coordinates":[-0.128288,51.517773],"type":"Point"}
}