{
  "type": "Feature",
  "properties": {
    "addr:full":"5 Liverpool Rd Stoke On Trent Staffordshire ST4 1AR",
    "addr:housenumber":"5",
    "addr:postcode":"st4 1ar",
    "addr:street":"Liverpool Rd",
    "iso:country":"GB",
    "sg:address":"5 Liverpool Rd",
    "sg:city":"Stoke On Trent",
    "sg:classifiers":[
        {
            "category":"Professional",
            "subcategory":"Printing & Photocopies",
            "type":"Services"
        }
    ],
    "sg:phone":"+44 1782 849090",
    "sg:postcode":"ST4 1AR",
    "sg:province":"Staffordshire",
    "sg:tags":[
        "embroiderer"
    ],
    "wof:name":"J & J Creative Embroidery",
    "wof:placetype":"venue"
},
  "geometry": {"coordinates":[-2.1862609386,53.0050468445],"type":"Point"}
}