{
  "type": "Feature",
  "properties": {
    "addr:full":"20 Daniel Owen Precinct Mold Denbighshire CH7 1AP",
    "addr:housenumber":"20",
    "addr:postcode":"ch7 1ap",
    "addr:street":"Daniel Owen",
    "iso:country":"GB",
    "sg:address":"20 Daniel Owen Precinct",
    "sg:city":"Mold",
    "sg:classifiers":[
        {
            "category":"Shopping",
            "subcategory":"Shoes",
            "type":"Retail Goods"
        }
    ],
    "sg:postcode":"CH7 1AP",
    "sg:province":"Denbighshire",
    "sg:tags":[
        "shop"
    ],
    "wof:name":"Stead & Simpson Ltd",
    "wof:placetype":"venue"
},
  "geometry": {"coordinates":[-3.142594099,53.1665267944],"type":"Point"}
}