{
  "type": "Feature",
  "properties": {
    "addr:full":"23 Lochburn Road Glasgow Glasgow City G20 9AE",
    "addr:housenumber":"23",
    "addr:postcode":"g20 9ae",
    "addr:street":"Lochburn Road",
    "iso:country":"GB",
    "sg:address":"23 Lochburn Road",
    "sg:city":"Glasgow",
    "sg:classifiers":[
        {
            "category":"Military Area",
            "subcategory":"Air Force Base",
            "type":"Public Place"
        }
    ],
    "sg:phone":"+44 141 945 4445",
    "sg:postcode":"G20 9AE",
    "sg:province":"Glasgow City",
    "sg:tags":[
        "taxi",
        "hire",
        "private"
    ],
    "wof:name":"Executive Radio Cars",
    "wof:placetype":"venue"
},
  "geometry": {"coordinates":[-4.2896180153,55.8917121887],"type":"Point"}
}