{
  "type": "Feature",
  "properties": {
    "iso:country":"GB",
    "sg:address":"92 The Street, Rustington",
    "sg:city":"Littlehampton",
    "sg:classifiers":[
        {
            "category":"Building & Trades",
            "subcategory":"Construction",
            "type":"Services"
        }
    ],
    "sg:phone":"+44 1903 850444",
    "sg:postcode":"BN16 3NJ",
    "sg:province":"West Sussex",
    "sg:tags":[
        "excavation",
        "groundwork",
        "builder",
        "contractor"
    ],
    "wof:name":"M Merridue Contractors Ltd.",
    "wof:placetype":"venue"
},
  "geometry": {"coordinates":[-0.508946,50.810699],"type":"Point"}
}