{
  "type": "Feature",
  "properties": {
    "addr:full":"132 Commonside, Pensnett Brierley Hill West Midlands DY5 4AE",
    "addr:housenumber":"132",
    "addr:postcode":"dy5 4ae",
    "addr:street":"Commonside Pensnett Brierley Hill",
    "iso:country":"GB",
    "sg:address":"132 Commonside, Pensnett",
    "sg:city":"Brierley Hill",
    "sg:classifiers":[
        {
            "category":"Professional",
            "subcategory":"Business Services",
            "type":"Services"
        },
        {
            "category":"Casinos & Gambling",
            "type":"Entertainment"
        }
    ],
    "sg:phone":"+44 1384 79297",
    "sg:postcode":"DY5 4AE",
    "sg:province":"West Midlands",
    "sg:tags":[
        "turf",
        "accountant",
        "bookmaker"
    ],
    "wof:name":"Longville Racing Ltd.",
    "wof:placetype":"venue"
},
  "geometry": {"coordinates":[-2.133269,52.495358],"type":"Point"}
}