{
  "type": "Feature",
  "properties": {
    "iso:country":"GB",
    "sg:address":"Blanche Ho, Turkdean",
    "sg:city":"Cheltenham",
    "sg:classifiers":[
        {
            "category":"Banks & Credit Unions",
            "subcategory":"Investment Brokerage",
            "type":"Services"
        }
    ],
    "sg:postcode":"GL54 3NX",
    "sg:province":"Gloucestershire",
    "wof:name":"Lawrence-Scrivener Ltd",
    "wof:placetype":"venue"
},
  "geometry": {"coordinates":[-1.8464750051,51.8551750183],"type":"Point"}
}