{
  "type": "Feature",
  "properties": {
    "addr:full":"17 Horace Av Romford Essex RM7 0XA",
    "addr:housenumber":"17",
    "addr:postcode":"rm7 0xa",
    "addr:street":"Horace Av",
    "iso:country":"GB",
    "sg:address":"17 Horace Av",
    "sg:city":"Romford",
    "sg:classifiers":[
        {
            "category":"Building & Trades",
            "subcategory":"Construction",
            "type":"Services"
        }
    ],
    "sg:phone":"+44 1708 766585",
    "sg:postcode":"RM7 0XA",
    "sg:province":"Essex",
    "sg:tags":[
        "roofing"
    ],
    "wof:name":"B Lewis & Sons",
    "wof:placetype":"venue"
},
  "geometry": {"coordinates":[0.172977,51.564308],"type":"Point"}
}