{
  "type": "Feature",
  "properties": {
    "addr:full":"7 Victoria Street, Narborough Leicester Leicestershire LE19 2DQ",
    "addr:housenumber":"7",
    "addr:postcode":"le19 2dq",
    "addr:street":"Victoria Street",
    "iso:country":"GB",
    "sg:address":"7 Victoria Street, Narborough",
    "sg:city":"Leicester",
    "sg:classifiers":[
        {
            "category":"Building & Trades",
            "subcategory":"Construction",
            "type":"Services"
        }
    ],
    "sg:phone":"+44 116 262 7800",
    "sg:postcode":"LE19 2DQ",
    "sg:province":"Leicestershire",
    "sg:tags":[
        "monumental",
        "mason"
    ],
    "wof:name":"Dobsons Memorials",
    "wof:placetype":"venue"
},
  "geometry": {"coordinates":[-1.2014349699,52.5725669861],"type":"Point"}
}