{
  "type": "Feature",
  "properties": {
    "addr:full":"Barkers Farm, Larling Norwich Norfolk NR16 2RA",
    "addr:postcode":"nr16 2ra",
    "addr:street":"Larling Norwich",
    "iso:country":"GB",
    "sg:address":"Barkers Farm, Larling",
    "sg:city":"Norwich",
    "sg:classifiers":[
        {
            "category":"Farming",
            "subcategory":"Livestock Farm",
            "type":"Manufacturing & Wholesale Goods"
        }
    ],
    "sg:phone":"+44 1953 498242",
    "sg:postcode":"NR16 2RA",
    "sg:province":"Norfolk",
    "sg:tags":[
        "others"
    ],
    "wof:name":"E H Lewin & Sons",
    "wof:placetype":"venue"
},
  "geometry": {"coordinates":[0.90828,52.462986],"type":"Point"}
}