{
  "type": "Feature",
  "properties": {
    "addr:full":"101 Talbot Road London Greater London W11 2AT",
    "addr:housenumber":"101",
    "addr:postcode":"w11 2at",
    "addr:street":"Talbot Road",
    "iso:country":"GB",
    "sg:address":"101 Talbot Road",
    "sg:city":"London",
    "sg:classifiers":[
        {
            "category":"Communications",
            "subcategory":"News Services",
            "type":"Services"
        }
    ],
    "sg:phone":"+44 20 7792 3500",
    "sg:postcode":"W11 2AT",
    "sg:province":"Greater London",
    "sg:tags":[
        "photo",
        "agency"
    ],
    "wof:name":"Terrie Tanaka Management Ltd.",
    "wof:placetype":"venue"
},
  "geometry": {"coordinates":[-0.2002560049,51.5167236328],"type":"Point"}
}