{
  "type": "Feature",
  "properties": {
    "iso:country":"GB",
    "sg:address":"3 Berrylands Road",
    "sg:city":"Surbiton",
    "sg:classifiers":[
        {
            "category":"Social Services",
            "subcategory":"Child Care",
            "type":"Services"
        },
        {
            "category":"Social Services",
            "subcategory":"Adult Care",
            "type":"Services"
        }
    ],
    "sg:phone":"+44 20 8399 4289",
    "sg:postcode":"KT5 8RB",
    "sg:province":"Surrey",
    "sg:tags":[
        "day",
        "centre"
    ],
    "wof:name":"Alfristons Day Centre",
    "wof:placetype":"venue"
},
  "geometry": {"coordinates":[-0.293578,51.391975],"type":"Point"}
}