{
  "type": "Feature",
  "properties": {
    "addr:full":"3 Barracks Square Newcastle Staffordshire ST5 1LG",
    "addr:housenumber":"3",
    "addr:postcode":"st5 1lg",
    "addr:street":"Barracks Square",
    "iso:country":"GB",
    "sg:address":"3 Barracks Square",
    "sg:city":"Newcastle",
    "sg:classifiers":[
        {
            "category":"Manufacturing",
            "subcategory":"Pottery",
            "type":"Manufacturing & Wholesale Goods"
        }
    ],
    "sg:phone":"+44 1782 637484",
    "sg:postcode":"ST5 1LG",
    "sg:province":"Staffordshire",
    "wof:name":"July Ceramic Products",
    "wof:placetype":"venue"
},
  "geometry": {"coordinates":[-2.223744,53.011303],"type":"Point"}
}