{
  "type": "Feature",
  "properties": {
    "iso:country":"GB",
    "sg:address":"18 High Street",
    "sg:city":"Baldock",
    "sg:classifiers":[
        {
            "category":"Autos & Motor Vehicles",
            "subcategory":"Automobile Sales",
            "type":"Retail Goods"
        }
    ],
    "sg:phone":"+44 1462 490049",
    "sg:postcode":"SG7 6AS",
    "sg:province":"Bedfordshire",
    "sg:tags":[
        "car",
        "specialist",
        "sales",
        "classic"
    ],
    "wof:name":"Brown & Gammons Ltd.",
    "wof:placetype":"venue"
},
  "geometry": {"coordinates":[-0.18808,51.988789],"type":"Point"}
}