{
  "type": "Feature",
  "properties": {
    "iso:country":"GB",
    "sg:address":"4 Cromwell Hill",
    "sg:city":"Luton",
    "sg:classifiers":[
        {
            "category":"Organizations",
            "subcategory":"Membership Organization",
            "type":"Services"
        }
    ],
    "sg:postcode":"LU2 7PY",
    "sg:province":"Bedfordshire",
    "sg:tags":[
        "club"
    ],
    "wof:name":"Street Systems Ltd",
    "wof:placetype":"venue"
},
  "geometry": {"coordinates":[-0.420692,51.887306],"type":"Point"}
}