{
  "type": "Feature",
  "properties": {
    "addr:full":"238 Elgar Ave Malvern Herefordshire WR14 2YA",
    "addr:housenumber":"238",
    "addr:postcode":"wr14 2ya",
    "addr:street":"Elgar Ave;Herefordshire",
    "iso:country":"GB",
    "sg:address":"238 Elgar Ave",
    "sg:city":"Malvern",
    "sg:classifiers":[
        {
            "category":"Communications",
            "type":"Services"
        }
    ],
    "sg:postcode":"WR14 2YA",
    "sg:province":"Herefordshire",
    "sg:tags":[
        "tv",
        "video",
        "radio"
    ],
    "wof:name":"Day,Martin,",
    "wof:placetype":"venue"
},
  "geometry": {"coordinates":[-2.3054959774,52.1193771362],"type":"Point"}
}