{
  "type": "Feature",
  "properties": {
    "iso:country":"GB",
    "sg:address":"40 Highfield Avenue",
    "sg:city":"Banchory",
    "sg:classifiers":[
        {
            "category":"Freight",
            "type":"Transportation"
        }
    ],
    "sg:phone":"+44 1330 824225",
    "sg:postcode":"AB31 4FB",
    "sg:province":"Aberdeen City",
    "sg:tags":[
        "haulage",
        "road"
    ],
    "wof:name":"Michael P Gilbert Transport",
    "wof:placetype":"venue"
},
  "geometry": {"coordinates":[-2.498197,57.057652],"type":"Point"}
}