{
  "type": "Feature",
  "properties": {
    "iso:country":"GB",
    "sg:address":"3 Pytchley Court",
    "sg:city":"Corby",
    "sg:classifiers":[
        {
            "category":"Shopping",
            "subcategory":"Pharmacy",
            "type":"Retail Goods"
        }
    ],
    "sg:phone":"+44 1536 204834",
    "sg:postcode":"NN17 2QD",
    "sg:province":"Northamptonshire",
    "sg:tags":[
        "pharmacist",
        "chemist"
    ],
    "wof:name":"Galen Butlin Ltd.",
    "wof:placetype":"venue"
},
  "geometry": {"coordinates":[-0.7220039964,52.4979362488],"type":"Point"}
}