{
  "type": "Feature",
  "properties": {
    "addr:full":"Mcclaren Building, 35 Dale End Birmingham West Midlands B4 7NP",
    "addr:housenumber":"35",
    "addr:postcode":"b4 7np",
    "addr:street":"Dale End",
    "iso:country":"GB",
    "sg:address":"Mcclaren Building, 35 Dale End",
    "sg:city":"Birmingham",
    "sg:classifiers":[
        {
            "category":"Government",
            "subcategory":"Office",
            "type":"Public Place"
        }
    ],
    "sg:phone":"+44 121 607 6200",
    "sg:postcode":"B4 7NP",
    "sg:province":"West Midlands",
    "sg:tags":[
        "central"
    ],
    "wof:name":"Health & Safety Executive",
    "wof:placetype":"venue"
},
  "geometry": {"coordinates":[-1.8923300505,52.4819984436],"type":"Point"}
}