{
  "type": "Feature",
  "properties": {
    "iso:country":"GB",
    "sg:address":"Stainsacre Lane Industrial Estat, E",
    "sg:city":"Whitby",
    "sg:classifiers":[
        {
            "category":"Utilities",
            "subcategory":"Fuel Oil & Lpg",
            "type":"Services"
        }
    ],
    "sg:phone":"+44 1947 602255",
    "sg:postcode":"YO22 4PU",
    "sg:province":"North Yorkshire",
    "sg:tags":[
        "distributor"
    ],
    "wof:name":"W Eves & Co. (Petrol) Ltd.",
    "wof:placetype":"venue"
},
  "geometry": {"coordinates":[-0.604286,54.473671],"type":"Point"}
}