{
  "type": "Feature",
  "properties": {
    "addr:full":"18 Spring Gardens Centre Buxton Derbyshire SK17 6DF",
    "addr:housenumber":"18",
    "addr:postcode":"sk17 6df",
    "addr:street":"Spring Gardens",
    "iso:country":"GB",
    "sg:address":"18 Spring Gardens Centre",
    "sg:city":"Buxton",
    "sg:classifiers":[
        {
            "category":"Shopping",
            "subcategory":"Comic Books",
            "type":"Retail Goods"
        }
    ],
    "sg:phone":"+44 1298 72292",
    "sg:postcode":"SK17 6DF",
    "sg:province":"Derbyshire",
    "sg:tags":[
        "jeweller"
    ],
    "wof:name":"H Samuel",
    "wof:placetype":"venue"
},
  "geometry": {"coordinates":[-1.9124740362,53.2588539124],"type":"Point"}
}