{
  "type": "Feature",
  "properties": {
    "iso:country":"GB",
    "sg:address":"6 Edwyn Close",
    "sg:city":"Barnet",
    "sg:classifiers":[
        {
            "category":"Building & Trades",
            "subcategory":"Construction",
            "type":"Services"
        }
    ],
    "sg:phone":"+44 20 8441 2709",
    "sg:postcode":"EN5 2QR",
    "sg:province":"Hertfordshire",
    "sg:tags":[
        "builder"
    ],
    "wof:name":"Mansfield Construction",
    "wof:placetype":"venue"
},
  "geometry": {"coordinates":[-0.216172,51.644279],"type":"Point"}
}