{
  "type": "Feature",
  "properties": {
    "iso:country":"GB",
    "sg:address":"Double Row, Seaton Delaval",
    "sg:city":"Whitley Bay",
    "sg:classifiers":[
        {
            "category":"Education",
            "subcategory":"School",
            "type":"Public Place"
        }
    ],
    "sg:phone":"+44 191 237 1239",
    "sg:postcode":"NE25 0PS",
    "sg:province":"Northumberland",
    "sg:tags":[
        "local",
        "authority"
    ],
    "wof:name":"Seaton Delaval County First School",
    "wof:placetype":"venue"
},
  "geometry": {"coordinates":[-1.5348379612,55.0779266357],"type":"Point"}
}