{
  "type": "Feature",
  "properties": {
    "addr:full":"10 Broad Drove Wisbech Cambridgeshire PE14 0RW",
    "addr:housenumber":"10",
    "addr:postcode":"pe14 0rw",
    "addr:street":"Broad Drove",
    "iso:country":"GB",
    "sg:address":"10 Broad Drove",
    "sg:city":"Wisbech",
    "sg:classifiers":[
        {
            "category":"Personal",
            "subcategory":"Beauty Salon",
            "type":"Services"
        }
    ],
    "sg:phone":"+44 1945 474337",
    "sg:postcode":"PE14 0RW",
    "sg:province":"Cambridgeshire",
    "wof:name":"Body & Soul Beauty Salon",
    "wof:placetype":"venue"
},
  "geometry": {"coordinates":[0.141989,52.639744],"type":"Point"}
}