{
  "type": "Feature",
  "properties": {
    "addr:full":"Greencroft Court, Greencroft Close Darlington Durham DL3 8HW",
    "addr:postcode":"dl3 8hw",
    "addr:street":"Greencroft Court Greencroft Close",
    "iso:country":"GB",
    "sg:address":"Greencroft Court, Greencroft Close",
    "sg:city":"Darlington",
    "sg:classifiers":[
        {
            "category":"Organizations",
            "subcategory":"Community Association",
            "type":"Services"
        }
    ],
    "sg:phone":"+44 1325 484155",
    "sg:postcode":"DL3 8HW",
    "sg:province":"Durham",
    "sg:tags":[
        "co-operatives",
        "society",
        "housing",
        "trust"
    ],
    "wof:name":"Anchor Trust",
    "wof:placetype":"venue"
},
  "geometry": {"coordinates":[-1.568999,54.52166],"type":"Point"}
}