{
  "type": "Feature",
  "properties": {
    "iso:country":"GB",
    "sg:address":"Burton House, North Road, Kirkburton",
    "sg:city":"Huddersfield",
    "sg:classifiers":[
        {
            "category":"Communications",
            "subcategory":"Film & Video Production",
            "type":"Services"
        },
        {
            "category":"Professional",
            "subcategory":"Detective & Security Services",
            "type":"Services"
        }
    ],
    "sg:phone":"+44 1484 607999",
    "sg:postcode":"HD8 0RL",
    "sg:province":"South Yorkshire",
    "sg:tags":[
        "cctv",
        "alarm",
        "burglar",
        "system",
        "equipment"
    ],
    "wof:name":"N T Systems",
    "wof:placetype":"venue"
},
  "geometry": {"coordinates":[-1.701374,53.607441],"type":"Point"}
}