{
  "type": "Feature",
  "properties": {
    "addr:full":"89 Brookdale Road Nuneaton Leicestershire CV10 0BL",
    "addr:housenumber":"89",
    "addr:postcode":"cv10 0bl",
    "addr:street":"Brookdale Road",
    "iso:country":"GB",
    "sg:address":"89 Brookdale Road",
    "sg:city":"Nuneaton",
    "sg:classifiers":[
        {
            "category":"Building & Trades",
            "subcategory":"Plumbing",
            "type":"Services"
        }
    ],
    "sg:phone":"+44 24 7632 9171",
    "sg:postcode":"CV10 0BL",
    "sg:province":"Leicestershire",
    "sg:tags":[
        "heating"
    ],
    "wof:name":"Plumber Patrol",
    "wof:placetype":"venue"
},
  "geometry": {"coordinates":[-1.4565800428,52.5342712402],"type":"Point"}
}