{
  "type": "Feature",
  "properties": {
    "iso:country":"GB",
    "sg:address":"56 Stourbridge Rd",
    "sg:city":"Halesowen",
    "sg:classifiers":[
        {
            "category":"Shopping",
            "subcategory":"News",
            "type":"Retail Goods"
        }
    ],
    "sg:postcode":"B63 3US",
    "sg:province":"West Midlands",
    "sg:tags":[
        "newsagent"
    ],
    "wof:name":"Singh,S,",
    "wof:placetype":"venue"
},
  "geometry": {"coordinates":[-2.055415,52.452206],"type":"Point"}
}