{
  "type": "Feature",
  "properties": {
    "addr:full":"18 Elm Bank Drive, Mapperley Park Nottingham Nottinghamshire NG3 5AL",
    "addr:housenumber":"18",
    "addr:postcode":"ng3 5al",
    "addr:street":"Elm Bank Drive",
    "iso:country":"GB",
    "sg:address":"18 Elm Bank Drive, Mapperley Park",
    "sg:city":"Nottingham",
    "sg:classifiers":[
        {
            "category":"Freight",
            "type":"Transportation"
        }
    ],
    "sg:phone":"+44 115 960 2771",
    "sg:postcode":"NG3 5AL",
    "sg:province":"Nottinghamshire",
    "sg:tags":[
        "haulage",
        "transport",
        "road"
    ],
    "wof:name":"Peter John Garnett",
    "wof:placetype":"venue"
},
  "geometry": {"coordinates":[-1.1498390436,52.9696388245],"type":"Point"}
}