{
  "type": "Feature",
  "properties": {
    "addr:full":"Rear Of 5 Regent St Hinckley Leicestershire LE10 0AZ",
    "addr:housenumber":"rear of 5",
    "addr:postcode":"le10 0az",
    "addr:street":"Regent St",
    "iso:country":"GB",
    "sg:address":"Rear Of 5 Regent St",
    "sg:city":"Hinckley",
    "sg:classifiers":[
        {
            "category":"Building & Trades",
            "subcategory":"Construction",
            "type":"Services"
        }
    ],
    "sg:postcode":"LE10 0AZ",
    "sg:province":"Leicestershire",
    "sg:tags":[
        "builder"
    ],
    "wof:name":"Ashton,Rod,",
    "wof:placetype":"venue"
},
  "geometry": {"coordinates":[-1.372754,52.542439],"type":"Point"}
}