{
  "type": "Feature",
  "properties": {
    "addr:full":"19 The Broadway Bedford Bedfordshire MK40 2TL",
    "addr:housenumber":"19",
    "addr:postcode":"mk40 2tl",
    "addr:street":"The Broadway",
    "iso:country":"GB",
    "sg:address":"19 The Broadway",
    "sg:city":"Bedford",
    "sg:classifiers":[
        {
            "category":"Home & Garden",
            "subcategory":"Household Appliances",
            "type":"Retail Goods"
        }
    ],
    "sg:phone":"+44 1234 352107",
    "sg:postcode":"MK40 2TL",
    "sg:province":"Bedfordshire",
    "sg:tags":[
        "domestic",
        "centre"
    ],
    "wof:name":"Michael R Peters",
    "wof:placetype":"venue"
},
  "geometry": {"coordinates":[-0.4680570066,52.1400756836],"type":"Point"}
}