{
  "type": "Feature",
  "properties": {
    "addr:full":"17 Fetteresso Terrace Stonehaven Aberdeenshire AB39 2DS",
    "addr:housenumber":"17",
    "addr:postcode":"ab39 2ds",
    "addr:street":"Fetteresso Terrace",
    "iso:country":"GB",
    "sg:address":"17 Fetteresso Terrace",
    "sg:city":"Stonehaven",
    "sg:classifiers":[
        {
            "category":"Building & Trades",
            "subcategory":"Construction",
            "type":"Services"
        }
    ],
    "sg:phone":"+44 1569 762529",
    "sg:postcode":"AB39 2DS",
    "sg:province":"Aberdeenshire",
    "sg:tags":[
        "glazier"
    ],
    "wof:name":"Stuart Mason",
    "wof:placetype":"venue"
},
  "geometry": {"coordinates":[-2.2242391109,56.959980011],"type":"Point"}
}