{
  "type": "Feature",
  "properties": {
    "addr:full":"22 Dering Street London Greater London W1S 1AN",
    "addr:housenumber":"22",
    "addr:postcode":"w1s 1an",
    "addr:street":"Dering Street",
    "iso:country":"GB",
    "sg:address":"22 Dering Street",
    "sg:city":"London",
    "sg:classifiers":[
        {
            "category":"Professional",
            "subcategory":"Printing & Photocopies",
            "type":"Services"
        }
    ],
    "sg:phone":"+44 20 7408 1150",
    "sg:postcode":"W1S 1AN",
    "sg:province":"Greater London",
    "sg:tags":[
        "printer"
    ],
    "wof:name":"Prorepro",
    "wof:placetype":"venue"
},
  "geometry": {"coordinates":[-0.1456349939,51.514175415],"type":"Point"}
}