{
  "type": "Feature",
  "properties": {
    "iso:country":"GB",
    "sg:address":"Unit 11 Riverside Park, Sheaf Gardens",
    "sg:city":"Sheffield",
    "sg:classifiers":[
        {
            "category":"Professional",
            "subcategory":"Printing & Photocopies",
            "type":"Services"
        }
    ],
    "sg:phone":"+44 114 275 7222",
    "sg:postcode":"S2 4BB",
    "sg:province":"South Yorkshire",
    "sg:tags":[
        "printer"
    ],
    "wof:name":"For Colour Mix Ltd.",
    "wof:placetype":"venue"
},
  "geometry": {"coordinates":[-1.4649,53.372719],"type":"Point"}
}