{
  "type": "Feature",
  "properties": {
    "iso:country":"GB",
    "sg:address":"8 Standish Drive, Rainford",
    "sg:city":"St Helens",
    "sg:classifiers":[
        {
            "category":"Building & Trades",
            "subcategory":"Construction",
            "type":"Services"
        }
    ],
    "sg:phone":"+44 1744 883846",
    "sg:postcode":"WA11 8JY",
    "sg:province":"Lancashire",
    "sg:tags":[
        "builder"
    ],
    "wof:name":"Edward Christopher Hamilton",
    "wof:placetype":"venue"
},
  "geometry": {"coordinates":[-2.784749,53.50565],"type":"Point"}
}