{
  "type": "Feature",
  "properties": {
    "addr:full":"Unit 23 Wainwright Street Birmingham West Midlands B6 5TH",
    "addr:housenumber":"unit 23;b6",
    "addr:postcode":"5th",
    "addr:street":"Wainwright Street",
    "iso:country":"GB",
    "sg:address":"Unit 23 Wainwright Street",
    "sg:city":"Birmingham",
    "sg:classifiers":[
        {
            "category":"Wholesale",
            "subcategory":"Photographic Equipment",
            "type":"Manufacturing & Wholesale Goods"
        }
    ],
    "sg:phone":"+44 121 326 7636",
    "sg:postcode":"B6 5TH",
    "sg:province":"West Midlands",
    "sg:tags":[
        "w'sale"
    ],
    "wof:name":"Keith Johnson & Pelling",
    "wof:placetype":"venue"
},
  "geometry": {"coordinates":[-1.8746030331,52.5004806519],"type":"Point"}
}