{
  "type": "Feature",
  "properties": {
    "iso:country":"GB",
    "sg:address":"Stockwith Close",
    "sg:city":"Middlesbrough",
    "sg:classifiers":[
        {
            "category":"Education",
            "subcategory":"School",
            "type":"Public Place"
        },
        {
            "category":"Government",
            "subcategory":"Office",
            "type":"Public Place"
        }
    ],
    "sg:phone":"+44 1642 452191",
    "sg:postcode":"TS3 0RG",
    "sg:province":"North Yorkshire",
    "sg:tags":[
        "local",
        "authority"
    ],
    "wof:name":"Ormesby Comprehensive School",
    "wof:placetype":"venue"
},
  "geometry": {"coordinates":[-1.1750439405,54.5532836914],"type":"Point"}
}