{
  "type": "Feature",
  "properties": {
    "addr:full":"42 Salisbury Rd Reading Berkshire RG30 1BJ",
    "addr:housenumber":"42",
    "addr:postcode":"rg30 1bj",
    "addr:street":"Salisbury Rd",
    "iso:country":"GB",
    "sg:address":"42 Salisbury Rd",
    "sg:city":"Reading",
    "sg:classifiers":[
        {
            "category":"Personal",
            "subcategory":"Hair Removal",
            "type":"Services"
        }
    ],
    "sg:phone":"+44 118 958 9241",
    "sg:postcode":"RG30 1BJ",
    "sg:province":"Berkshire",
    "sg:tags":[
        "electrolysis"
    ],
    "wof:name":"Depille",
    "wof:placetype":"venue"
},
  "geometry": {"coordinates":[-0.9898999929,51.4571342468],"type":"Point"}
}