{
  "type": "Feature",
  "properties": {
    "addr:full":"56 Wellington Road Bridlington East Riding of Yorkshire YO15 2AZ",
    "addr:housenumber":"56",
    "addr:postcode":"yo15 2az",
    "addr:street":"Wellington Road",
    "iso:country":"GB",
    "sg:address":"56 Wellington Road",
    "sg:city":"Bridlington",
    "sg:classifiers":[
        {
            "category":"Travel",
            "subcategory":"Hotels & Motels",
            "type":"Entertainment"
        }
    ],
    "sg:phone":"+44 1262 672370",
    "sg:postcode":"YO15 2AZ",
    "sg:province":"East Riding of Yorkshire",
    "wof:name":"Sheringham Hotel",
    "wof:placetype":"venue"
},
  "geometry": {"coordinates":[-0.191759,54.086044],"type":"Point"}
}