{
  "type": "Feature",
  "properties": {
    "addr:full":"Norway Road, Hilsea Industrial Estate Portsmouth Hampshire PO3 5HT",
    "addr:postcode":"hampshire po3 5ht",
    "addr:street":"Norway Road;Industrial Estate",
    "iso:country":"GB",
    "sg:address":"Norway Road, Hilsea Industrial Estate",
    "sg:city":"Portsmouth",
    "sg:classifiers":[
        {
            "category":"Home & Garden",
            "subcategory":"Hardware",
            "type":"Retail Goods"
        }
    ],
    "sg:phone":"+44 870 243 5246",
    "sg:postcode":"PO3 5HT",
    "sg:province":"Hampshire",
    "sg:tags":[
        "retailer",
        "diy"
    ],
    "wof:name":"B & Q Diy Supercentre",
    "wof:placetype":"venue"
},
  "geometry": {"coordinates":[-1.0585440397,50.8284263611],"type":"Point"}
}