{
  "type": "Feature",
  "properties": {
    "iso:country":"GB",
    "sg:address":"165-167 Bolton Road",
    "sg:city":"Bury",
    "sg:classifiers":[
        {
            "category":"Communications",
            "type":"Services"
        }
    ],
    "sg:phone":"+44 161 797 7682",
    "sg:postcode":"BL8 2NW",
    "sg:province":"Lancashire",
    "sg:tags":[
        "tv",
        "video",
        "radio"
    ],
    "wof:name":"Lords T V & Video",
    "wof:placetype":"venue"
},
  "geometry": {"coordinates":[-2.313858,53.59129],"type":"Point"}
}