{
  "type": "Feature",
  "properties": {
    "iso:country":"GB",
    "sg:address":"P O Box 50",
    "sg:city":"Otley",
    "sg:classifiers":[
        {
            "category":"Professional",
            "subcategory":"Testing Lab",
            "type":"Services"
        }
    ],
    "sg:postcode":"LS21 3XD",
    "sg:province":"North Yorkshire",
    "sg:tags":[
        "inspection",
        "calibration"
    ],
    "wof:name":"Textile Laboratory Services Ltd.",
    "wof:placetype":"venue"
},
  "geometry": {"coordinates":[-1.704679,53.901081],"type":"Point"}
}