{
  "type": "Feature",
  "properties": {
    "iso:country":"GB",
    "sg:address":"6 Barr Street, Whittlesey",
    "sg:city":"Peterborough",
    "sg:classifiers":[
        {
            "category":"Organizations",
            "subcategory":"Non-profit Organization",
            "type":"Services"
        }
    ],
    "sg:phone":"+44 1733 208090",
    "sg:postcode":"PE7 1DA",
    "sg:province":"Cambridgeshire",
    "sg:tags":[
        "organisation",
        "animal",
        "welfare"
    ],
    "wof:name":"Lyon Bennett & Associates",
    "wof:placetype":"venue"
},
  "geometry": {"coordinates":[-0.130787,52.556541],"type":"Point"}
}