{
  "type": "Feature",
  "properties": {
    "addr:full":"Old School House, Rhewl Ruthin Denbighshire LL15 2TU",
    "addr:postcode":"ll15 2tu",
    "addr:street":"Rhewl",
    "iso:country":"GB",
    "sg:address":"Old School House, Rhewl",
    "sg:city":"Ruthin",
    "sg:classifiers":[
        {
            "category":"Professional",
            "subcategory":"Management & Consulting",
            "type":"Services"
        },
        {
            "category":"Professional",
            "subcategory":"Computer Services",
            "type":"Services"
        }
    ],
    "sg:phone":"+44 1824 705551",
    "sg:postcode":"LL15 2TU",
    "sg:province":"Denbighshire",
    "sg:tags":[
        "consultant",
        "system",
        "business",
        "software"
    ],
    "wof:name":"Soltech",
    "wof:placetype":"venue"
},
  "geometry": {"coordinates":[-3.334002,53.081635],"type":"Point"}
}