{
  "type": "Feature",
  "properties": {
    "addr:full":"357 Brandlesholme Road Bury Lancashire BL8 1HS",
    "addr:housenumber":"357",
    "addr:postcode":"bl8 1hs",
    "addr:street":"Brandlesholme Road",
    "iso:country":"GB",
    "sg:address":"357 Brandlesholme Road",
    "sg:city":"Bury",
    "sg:classifiers":[
        {
            "category":"Personal",
            "subcategory":"Beauty Salon",
            "type":"Services"
        }
    ],
    "sg:phone":"+44 161 797 7540",
    "sg:postcode":"BL8 1HS",
    "sg:province":"Lancashire",
    "sg:tags":[
        "unisex",
        "hairdresser"
    ],
    "wof:name":"Zig Zag Hair Design",
    "wof:placetype":"venue"
},
  "geometry": {"coordinates":[-2.31386,53.608932],"type":"Point"}
}