{
  "type": "Feature",
  "properties": {
    "iso:country":"GB",
    "sg:address":"Greencroft Ho, 42-46 Salt La",
    "sg:city":"Salisbury",
    "sg:classifiers":[
        {
            "category":"Professional",
            "subcategory":"Lawyer & Legal Services",
            "type":"Services"
        }
    ],
    "sg:phone":"+44 1722 421951",
    "sg:postcode":"SP1 1EG",
    "sg:province":"Wiltshire",
    "sg:tags":[
        "advice",
        "counselling"
    ],
    "wof:name":"Gay Mens Health For Wiltshire & Swindon",
    "wof:placetype":"venue"
},
  "geometry": {"coordinates":[-1.79165,51.071011],"type":"Point"}
}