{
  "type": "Feature",
  "properties": {
    "addr:full":"162-164 Ravenscroft Road Beckenham Kent BR3 4TW",
    "addr:housenumber":"162-164",
    "addr:postcode":"br3 4tw",
    "addr:street":"Ravenscroft Road",
    "iso:country":"GB",
    "sg:address":"162-164 Ravenscroft Road",
    "sg:city":"Beckenham",
    "sg:classifiers":[
        {
            "category":"Wholesale",
            "subcategory":"Machinery & Supplies",
            "type":"Manufacturing & Wholesale Goods"
        }
    ],
    "sg:phone":"+44 20 8659 6977",
    "sg:postcode":"BR3 4TW",
    "sg:province":"Kent",
    "sg:tags":[
        "industrial",
        "commercial"
    ],
    "wof:name":"Recoil Ltd.",
    "wof:placetype":"venue"
},
  "geometry": {"coordinates":[-0.0535669997,51.4074058533],"type":"Point"}
}