{
  "type": "Feature",
  "properties": {
    "iso:country":"GB",
    "sg:address":"21 Beach Road",
    "sg:city":"Littlehampton",
    "sg:classifiers":[
        {
            "category":"Home & Garden",
            "subcategory":"Furniture",
            "type":"Retail Goods"
        }
    ],
    "sg:phone":"+44 1903 716784",
    "sg:postcode":"BN17 5JA",
    "sg:province":"West Sussex",
    "sg:tags":[
        "outlet"
    ],
    "sg:website":"http://www.arunfurnishers.co.uk",
    "wof:name":"Arun Furnishers",
    "wof:placetype":"venue"
},
  "geometry": {"coordinates":[-0.539839,50.808575],"type":"Point"}
}