{
  "type": "Feature",
  "properties": {
    "iso:country":"GB",
    "sg:address":"3 Panmure Pl",
    "sg:city":"Edinburgh",
    "sg:classifiers":[
        {
            "category":"Manufacturing",
            "subcategory":"Apparel",
            "type":"Manufacturing & Wholesale Goods"
        }
    ],
    "sg:postcode":"EH3 9HP",
    "sg:province":"City of Edinburgh",
    "sg:tags":[
        "garment",
        "designer"
    ],
    "wof:name":"Genuine Labels",
    "wof:placetype":"venue"
},
  "geometry": {"coordinates":[-3.2012290955,55.9428672791],"type":"Point"}
}