{
  "type": "Feature",
  "properties": {
    "addr:full":"Taw Vale Barnstaple Devon EX32 8NJ",
    "addr:postcode":"ex32 8nj",
    "iso:country":"GB",
    "sg:address":"Taw Vale",
    "sg:city":"Barnstaple",
    "sg:classifiers":[
        {
            "category":"Travel",
            "subcategory":"Hotels & Motels",
            "type":"Entertainment"
        }
    ],
    "sg:postcode":"EX32 8NJ",
    "sg:province":"Devon",
    "wof:name":"Brend Hotels",
    "wof:placetype":"venue"
},
  "geometry": {"coordinates":[-4.058293,51.07766],"type":"Point"}
}