{
  "type": "Feature",
  "properties": {
    "iso:country":"GB",
    "sg:address":"Unit 8 High Street, Ecclesfield",
    "sg:city":"Sheffield",
    "sg:classifiers":[
        {
            "category":"Food & Beverages",
            "subcategory":"Liquor & Beverages",
            "type":"Retail Goods"
        }
    ],
    "sg:phone":"+44 114 246 3855",
    "sg:postcode":"S30 3XA",
    "sg:province":"Derbyshire",
    "sg:tags":[
        "beer",
        "spirit",
        "wines"
    ],
    "wof:name":"The Drinks Cabin",
    "wof:placetype":"venue"
},
  "geometry": {"coordinates":[-1.47022,53.441818],"type":"Point"}
}