{
  "type": "Feature",
  "properties": {
    "addr:full":"Manor House Nursing Home, Church Lane, Lelant St Ives Cornwall TR26 3DZ",
    "addr:postcode":"tr26 3dz",
    "addr:street":"Manor;Church Lane",
    "iso:country":"GB",
    "sg:address":"Manor House Nursing Home, Church Lane, Lelant",
    "sg:city":"St Ives",
    "sg:classifiers":[
        {
            "category":"Health Services",
            "subcategory":"Nursing And Care Facility",
            "type":"Services"
        }
    ],
    "sg:phone":"+44 1736 753029",
    "sg:postcode":"TR26 3DZ",
    "sg:province":"Cornwall",
    "sg:tags":[
        "home"
    ],
    "wof:name":"Inch Bros Ltd.",
    "wof:placetype":"venue"
},
  "geometry": {"coordinates":[-5.440329,50.183201],"type":"Point"}
}