{
  "type": "Feature",
  "properties": {
    "addr:full":"10 The Rise Weymouth Dorset DT4 0TD",
    "addr:housenumber":"10",
    "addr:postcode":"dt4 0td",
    "addr:street":"The Rise",
    "iso:country":"GB",
    "sg:address":"10 The Rise",
    "sg:city":"Weymouth",
    "sg:classifiers":[
        {
            "category":"Shopping",
            "subcategory":"Computers & Home Electronics",
            "type":"Retail Goods"
        }
    ],
    "sg:phone":"+44 1305 761127",
    "sg:postcode":"DT4 0TD",
    "sg:province":"Dorset",
    "sg:tags":[
        "aerial",
        "television",
        "radio"
    ],
    "wof:name":"Weymouth Aerials & Satellites",
    "wof:placetype":"venue"
},
  "geometry": {"coordinates":[-2.4778959751,50.6221122742],"type":"Point"}
}