{
  "type": "Feature",
  "properties": {
    "iso:country":"GB",
    "sg:address":"123 Dalry Road",
    "sg:city":"Edinburgh",
    "sg:classifiers":[
        {
            "category":"Shopping",
            "subcategory":"News",
            "type":"Retail Goods"
        }
    ],
    "sg:phone":"+44 131 337 2661",
    "sg:postcode":"EH11 2DR",
    "sg:province":"City of Edinburgh",
    "sg:tags":[
        "newsagent"
    ],
    "wof:name":"Scotts Newsagents",
    "wof:placetype":"venue"
},
  "geometry": {"coordinates":[-3.2205,55.943226],"type":"Point"}
}