{
  "type": "Feature",
  "properties": {
    "iso:country":"GB",
    "sg:address":"49 Mount Pleasant, Quarry Bank",
    "sg:city":"Brierley Hill",
    "sg:classifiers":[
        {
            "category":"Bus Station",
            "type":"Transportation"
        },
        {
            "category":"Bus Charters",
            "type":"Transportation"
        }
    ],
    "sg:phone":"+44 1384 77672",
    "sg:postcode":"DY5 2YY",
    "sg:province":"West Midlands",
    "sg:tags":[
        "operator",
        "coach"
    ],
    "wof:name":"Parkes Coach Travel",
    "wof:placetype":"venue"
},
  "geometry": {"coordinates":[-2.111279,52.47366],"type":"Point"}
}