{
  "type": "Feature",
  "properties": {
    "addr:full":"16 High Street Normanton West Yorkshire WF6 2AB",
    "addr:housenumber":"16",
    "addr:postcode":"wf6 2ab",
    "addr:street":"High Street",
    "iso:country":"GB",
    "sg:address":"16 High Street",
    "sg:city":"Normanton",
    "sg:classifiers":[
        {
            "category":"Home & Garden",
            "subcategory":"Home Furnishings",
            "type":"Retail Goods"
        }
    ],
    "sg:phone":"+44 1924 892087",
    "sg:postcode":"WF6 2AB",
    "sg:province":"West Yorkshire",
    "sg:tags":[
        "wall",
        "wallpaper",
        "covering"
    ],
    "wof:name":"Bedford Wallcoverings",
    "wof:placetype":"venue"
},
  "geometry": {"coordinates":[-1.416509,53.700489],"type":"Point"}
}