{
  "type": "Feature",
  "properties": {
    "iso:country":"GB",
    "sg:address":"30 Tower Road, Branksome Park",
    "sg:city":"Poole",
    "sg:classifiers":[
        {
            "category":"Social Services",
            "subcategory":"Retirement Home",
            "type":"Services"
        }
    ],
    "sg:phone":"+44 1202 762855",
    "sg:postcode":"BH13 6HZ",
    "sg:province":"Dorset",
    "sg:tags":[
        "rest"
    ],
    "wof:name":"Pine Tower",
    "wof:placetype":"venue"
},
  "geometry": {"coordinates":[-1.9082039595,50.7155075073],"type":"Point"}
}