{
  "type": "Feature",
  "properties": {
    "addr:full":"5 Hogarth Road, Earls Court London Greater London SW5 0QH",
    "addr:housenumber":"5",
    "addr:postcode":"sw5 0qh",
    "addr:street":"Hogarth Road",
    "iso:country":"GB",
    "sg:address":"5 Hogarth Road, Earls Court",
    "sg:city":"London",
    "sg:classifiers":[
        {
            "category":"Organizations",
            "subcategory":"Non-profit Organization",
            "type":"Services"
        }
    ],
    "sg:phone":"+44 20 7835 1817",
    "sg:postcode":"SW5 0QH",
    "sg:province":"Greater London",
    "sg:tags":[
        "organisation",
        "voluntary",
        "charity"
    ],
    "wof:name":"Punch & Judy Family Centre",
    "wof:placetype":"venue"
},
  "geometry": {"coordinates":[-0.192568,51.493248],"type":"Point"}
}