{
  "type": "Feature",
  "properties": {
    "iso:country":"GB",
    "sg:address":"Colchester Industrial Estate, Colchester Avenue",
    "sg:city":"Cardiff",
    "sg:classifiers":[
        {
            "category":"Retail",
            "subcategory":"Storage",
            "type":"Services"
        }
    ],
    "sg:phone":"+44 29 2049 2063",
    "sg:postcode":"CF23 9AP",
    "sg:province":"Cardiff",
    "sg:tags":[
        "household",
        "removal"
    ],
    "wof:name":"Henry Chapman & Son (Removals) Ltd.",
    "wof:placetype":"venue"
},
  "geometry": {"coordinates":[-3.1608200073,51.4996109009],"type":"Point"}
}