{
  "type": "Feature",
  "properties": {
    "addr:full":"173 Merry Hill Road Watford Hertfordshire WD23 1DH",
    "addr:housenumber":"173",
    "addr:postcode":"wd23 1dh",
    "addr:street":"Merry Hill Road",
    "iso:country":"GB",
    "sg:address":"173 Merry Hill Road",
    "sg:city":"Watford",
    "sg:classifiers":[
        {
            "category":"Building & Trades",
            "subcategory":"Construction",
            "type":"Services"
        }
    ],
    "sg:phone":"+44 20 8950 1800",
    "sg:postcode":"WD23 1DH",
    "sg:province":"Hertfordshire",
    "sg:tags":[
        "joiner",
        "carpenter"
    ],
    "wof:name":"Jeffrey Charles Batten",
    "wof:placetype":"venue"
},
  "geometry": {"coordinates":[-0.3543600142,51.6357002258],"type":"Point"}
}