{
  "type": "Feature",
  "properties": {
    "addr:full":"Rear Of 17-19 Bower Road Harrogate North Yorkshire HG1 1BE",
    "addr:housenumber":"rear of 17-19",
    "addr:postcode":"hg1 1be",
    "addr:street":"Bower Road",
    "iso:country":"GB",
    "sg:address":"Rear Of 17-19 Bower Road",
    "sg:city":"Harrogate",
    "sg:classifiers":[
        {
            "category":"Retail",
            "subcategory":"Auto Repair",
            "type":"Services"
        }
    ],
    "sg:phone":"+44 1423 568555",
    "sg:postcode":"HG1 1BE",
    "sg:province":"North Yorkshire",
    "sg:tags":[
        "modification",
        "garage"
    ],
    "wof:name":"Central Garage",
    "wof:placetype":"venue"
},
  "geometry": {"coordinates":[-1.5445239544,53.9946899414],"type":"Point"}
}