{
  "type": "Feature",
  "properties": {
    "iso:country":"GB",
    "sg:address":"44 Lychgate Avenue, Pedmore",
    "sg:city":"Stourbridge",
    "sg:classifiers":[
        {
            "category":"Building & Trades",
            "subcategory":"Construction",
            "type":"Services"
        }
    ],
    "sg:phone":"+44 1562 884976",
    "sg:postcode":"DY9 0TS",
    "sg:province":"West Midlands",
    "sg:tags":[
        "heating",
        "contractor"
    ],
    "wof:name":"B H P",
    "wof:placetype":"venue"
},
  "geometry": {"coordinates":[-2.1278479099,52.4383201599],"type":"Point"}
}