{
  "type": "Feature",
  "properties": {
    "addr:full":"9 Cotswold Green Aylesbury Buckinghamshire HP20 2HB",
    "addr:housenumber":"9",
    "addr:postcode":"hp20 2hb",
    "addr:street":"Cotswold Green",
    "iso:country":"GB",
    "sg:address":"9 Cotswold Green",
    "sg:city":"Aylesbury",
    "sg:classifiers":[
        {
            "category":"Home & Garden",
            "subcategory":"Home Furnishings",
            "type":"Retail Goods"
        }
    ],
    "sg:phone":"+44 1296 481417",
    "sg:postcode":"HP20 2HB",
    "sg:province":"Buckinghamshire",
    "sg:tags":[
        "awning",
        "canopy",
        "blinds"
    ],
    "wof:name":"CHILTERN BLIND COMPANY",
    "wof:placetype":"venue"
},
  "geometry": {"coordinates":[-0.804449,51.825459],"type":"Point"}
}