{
  "type": "Feature",
  "properties": {
    "addr:full":"Unit 10 Murray Place, Righead Industrial Estate Bellshill North Lanarkshire ML4 3LP",
    "addr:housenumber":"unit 10",
    "addr:postcode":"ml4 3lp",
    "addr:street":"Murray Place Righead Industrial Estate",
    "iso:country":"GB",
    "sg:address":"Unit 10 Murray Place, Righead Industrial Estate",
    "sg:city":"Bellshill",
    "sg:classifiers":[
        {
            "category":"Manufacturing",
            "subcategory":"Printing",
            "type":"Manufacturing & Wholesale Goods"
        },
        {
            "category":"Building & Trades",
            "subcategory":"Plumbing",
            "type":"Services"
        }
    ],
    "sg:phone":"+44 1698 749666",
    "sg:postcode":"ML4 3LP",
    "sg:province":"North Lanarkshire",
    "sg:tags":[
        "joint",
        "seal",
        "manufacturer"
    ],
    "sg:website":"http://www.barnwell.co.uk",
    "wof:name":"Barnwell Services Ltd",
    "wof:placetype":"venue"
},
  "geometry": {"coordinates":[-4.0358009338,55.8203048706],"type":"Point"}
}