{
  "type": "Feature",
  "properties": {
    "addr:full":"Legion Way, East Wittering Chichester West Sussex PO20 8PA",
    "addr:postcode":"po20 8pa",
    "addr:street":"Legion Way",
    "iso:country":"GB",
    "sg:address":"Legion Way, East Wittering",
    "sg:city":"Chichester",
    "sg:classifiers":[
        {
            "category":"Organizations",
            "subcategory":"Membership Organization",
            "type":"Services"
        }
    ],
    "sg:phone":"+44 1243 670305",
    "sg:postcode":"PO20 8PA",
    "sg:province":"West Sussex",
    "sg:tags":[
        "club",
        "social"
    ],
    "wof:name":"The Royal British Legion",
    "wof:placetype":"venue"
},
  "geometry": {"coordinates":[-0.871509,50.769089],"type":"Point"}
}