{
  "type": "Feature",
  "properties": {
    "iso:country":"GB",
    "sg:address":"47 Princes St",
    "sg:city":"Yeovil",
    "sg:classifiers":[
        {
            "category":"Professional",
            "subcategory":"Business Services",
            "type":"Services"
        },
        {
            "category":"Shopping",
            "subcategory":"Pets & Pet Supplies",
            "type":"Retail Goods"
        }
    ],
    "sg:postcode":"BA20 1EG",
    "sg:province":"Somerset",
    "sg:tags":[
        "import",
        "export",
        "agent"
    ],
    "wof:name":"Bloor,Mark,",
    "wof:placetype":"venue"
},
  "geometry": {"coordinates":[-2.63398,50.942745],"type":"Point"}
}