{
  "type": "Feature",
  "properties": {
    "addr:full":"Henstridge Trading Estate, Lanshire Lane, Henstridge Templecombe Somerset BA8 0SD",
    "addr:postcode":"ba8 0sd",
    "addr:street":"Lanshire Lane",
    "iso:country":"GB",
    "sg:address":"Henstridge Trading Estate, Lanshire Lane, Henstridge",
    "sg:city":"Templecombe",
    "sg:classifiers":[
        {
            "category":"Autos & Motor Vehicles",
            "subcategory":"Boat Sales",
            "type":"Retail Goods"
        },
        {
            "category":"Retail",
            "subcategory":"Auto Repair",
            "type":"Services"
        }
    ],
    "sg:phone":"+44 1963 362603",
    "sg:postcode":"BA8 0SD",
    "sg:province":"Somerset",
    "sg:tags":[
        "engine",
        "car",
        "rebuilders",
        "specialist"
    ],
    "wof:name":"Perrett Engineering",
    "wof:placetype":"venue"
},
  "geometry": {"coordinates":[-2.4152870178,51.0013809204],"type":"Point"}
}