{
  "type": "Feature",
  "properties": {
    "iso:country":"GB",
    "sg:address":"Unit 5, The Enterprise Centre, Bowerhill Ind Est, Bowerhill",
    "sg:city":"Melksham",
    "sg:classifiers":[
        {
            "category":"Retail",
            "subcategory":"Auto Repair",
            "type":"Services"
        }
    ],
    "sg:phone":"+44 1225 793678",
    "sg:postcode":"SN12 6SP",
    "sg:province":"Wiltshire",
    "sg:tags":[
        "modification",
        "car",
        "classic"
    ],
    "wof:name":"Britannic Automotive Engineering",
    "wof:placetype":"venue"
},
  "geometry": {"coordinates":[-2.1221280098,51.3611679077],"type":"Point"}
}