{
  "type": "Feature",
  "properties": {
    "addr:full":"37 Groat Market Newcastle-upon-tyne Tyne and Wear NE1 1UQ",
    "addr:housenumber":"37",
    "addr:postcode":"ne1 1uq",
    "iso:country":"GB",
    "sg:address":"37 Groat Market",
    "sg:city":"Newcastle-upon-tyne",
    "sg:classifiers":[
        {
            "category":"Fast Food",
            "type":"Food & Drink"
        }
    ],
    "sg:phone":"+44 191 233 1818",
    "sg:postcode":"NE1 1UQ",
    "sg:province":"Tyne and Wear",
    "sg:tags":[
        "away",
        "take"
    ],
    "wof:name":"Uncle Wong (U K)",
    "wof:placetype":"venue"
},
  "geometry": {"coordinates":[-1.6126079559,54.9703941345],"type":"Point"}
}