{
  "type": "Feature",
  "properties": {
    "addr:full":"Briggate, Windhill Shipley West Yorkshire BD18 2BT",
    "addr:postcode":"bd18 2bt",
    "addr:street":"Briggate Windhill",
    "iso:country":"GB",
    "sg:address":"Briggate, Windhill",
    "sg:city":"Shipley",
    "sg:classifiers":[
        {
            "category":"Manufacturing",
            "subcategory":"Textiles",
            "type":"Manufacturing & Wholesale Goods"
        },
        {
            "category":"Home & Garden",
            "subcategory":"Carpets & Floor Coverings",
            "type":"Retail Goods"
        }
    ],
    "sg:phone":"+44 1274 599476",
    "sg:postcode":"BD18 2BT",
    "sg:province":"West Yorkshire",
    "sg:tags":[
        "merchant",
        "agent"
    ],
    "wof:name":"Jones Wool Blenders",
    "wof:placetype":"venue"
},
  "geometry": {"coordinates":[-1.765135,53.830803],"type":"Point"}
}