{
  "type": "Feature",
  "properties": {
    "addr:full":"46 Belhaven Road Wishaw North Lanarkshire ML2 7NX",
    "addr:housenumber":"46",
    "addr:postcode":"ml2 7nx",
    "addr:street":"Belhaven Road",
    "iso:country":"GB",
    "sg:address":"46 Belhaven Road",
    "sg:city":"Wishaw",
    "sg:classifiers":[
        {
            "category":"Home & Garden",
            "subcategory":"Household Appliances",
            "type":"Retail Goods"
        }
    ],
    "sg:phone":"+44 1698 357505",
    "sg:postcode":"ML2 7NX",
    "sg:province":"North Lanarkshire",
    "sg:tags":[
        "electrical"
    ],
    "wof:name":"Calder Refrigeration (Sales & Services) Ltd.",
    "wof:placetype":"venue"
},
  "geometry": {"coordinates":[-3.928499,55.775105],"type":"Point"}
}