{
  "type": "Feature",
  "properties": {
    "addr:full":"The Cottages, Morton Grange Farm, Fencehouses Houghton-le-spring Durham DH4 6QB",
    "addr:postcode":"dh4 6qb",
    "addr:street":"Morton;Fencehouses",
    "iso:country":"GB",
    "sg:address":"The Cottages, Morton Grange Farm, Fencehouses",
    "sg:city":"Houghton-le-spring",
    "sg:classifiers":[
        {
            "category":"Food & Beverages",
            "subcategory":"Specialty",
            "type":"Retail Goods"
        }
    ],
    "sg:postcode":"DH4 6QB",
    "sg:province":"Durham",
    "sg:tags":[
        "product",
        "health"
    ],
    "wof:name":"Herbalife",
    "wof:placetype":"venue"
},
  "geometry": {"coordinates":[-1.500067,54.837326],"type":"Point"}
}