{
  "type": "Feature",
  "properties": {
    "iso:country":"GB",
    "sg:address":"15 Bancroft Road",
    "sg:city":"Luton",
    "sg:classifiers":[
        {
            "category":"Building & Trades",
            "subcategory":"Cleaning & Sanitation",
            "type":"Services"
        }
    ],
    "sg:phone":"+44 1582 706108",
    "sg:postcode":"LU3 2NB",
    "sg:province":"Bedfordshire",
    "sg:tags":[
        "dry",
        "control",
        "damp",
        "rot"
    ],
    "wof:name":"Anglia Preservation",
    "wof:placetype":"venue"
},
  "geometry": {"coordinates":[-0.4378910065,51.9044837952],"type":"Point"}
}