{
  "type": "Feature",
  "properties": {
    "addr:full":"130 St Marys Rd Tonbridge Kent TN9 2NN",
    "addr:housenumber":"130",
    "addr:postcode":"tn9 2nn",
    "addr:street":"St Marys Rd",
    "iso:country":"GB",
    "sg:address":"130 St Marys Rd",
    "sg:city":"Tonbridge",
    "sg:classifiers":[
        {
            "category":"Building & Trades",
            "subcategory":"Construction",
            "type":"Services"
        }
    ],
    "sg:phone":"+44 7860 385466",
    "sg:postcode":"TN9 2NN",
    "sg:province":"Kent",
    "sg:tags":[
        "roofing"
    ],
    "wof:name":"Abmar Roofing",
    "wof:placetype":"venue"
},
  "geometry": {"coordinates":[0.268464,51.18478],"type":"Point"}
}