{
  "type": "Feature",
  "properties": {
    "addr:full":"Y Bryn, Ffordd Gyffylog, Eglwysbach Colwyn Bay Conwy LL28 5TU",
    "addr:postcode":"ll28 5tu",
    "addr:street":"Ffordd Gyffylog",
    "iso:country":"GB",
    "sg:address":"Y Bryn, Ffordd Gyffylog, Eglwysbach",
    "sg:city":"Colwyn Bay",
    "sg:classifiers":[
        {
            "category":"Real Estate",
            "subcategory":"Architect",
            "type":"Services"
        }
    ],
    "sg:phone":"+44 1492 650465",
    "sg:postcode":"LL28 5TU",
    "sg:province":"Conwy",
    "wof:name":"Realtime Engineering Services Ltd.",
    "wof:placetype":"venue"
},
  "geometry": {"coordinates":[-3.792649,53.217411],"type":"Point"}
}