{
  "type": "Feature",
  "properties": {
    "addr:full":"2nd Floor Care Of House Of Fraser, High St Sheffield South Yorkshire S1 1QH",
    "addr:housenumber":"2nd",
    "addr:postcode":"s1 1qh",
    "addr:street":"High St",
    "iso:country":"GB",
    "sg:address":"2nd Floor Care Of House Of Fraser, High St",
    "sg:city":"Sheffield",
    "sg:classifiers":[
        {
            "category":"Personal",
            "subcategory":"Beauty Salon",
            "type":"Services"
        }
    ],
    "sg:phone":"+44 114 276 9797",
    "sg:postcode":"S1 1QH",
    "sg:province":"South Yorkshire",
    "sg:tags":[
        "unisex",
        "hairdresser"
    ],
    "wof:name":"Essanelle Hair & Beauty Salon",
    "wof:placetype":"venue"
},
  "geometry": {"coordinates":[-1.4645440578,53.3831100464],"type":"Point"}
}