{
  "type": "Feature",
  "properties": {
    "iso:country":"GB",
    "sg:address":"39 Woodfield Road",
    "sg:city":"Blackpool",
    "sg:classifiers":[
        {
            "category":"Travel",
            "subcategory":"Hotels & Motels",
            "type":"Entertainment"
        }
    ],
    "sg:phone":"+44 1253 346143",
    "sg:postcode":"FY1 6AX",
    "sg:province":"Lancashire",
    "wof:name":"The Wildlife Vegetarian & Vegan Hotel",
    "wof:placetype":"venue"
},
  "geometry": {"coordinates":[-3.052837,53.803455],"type":"Point"}
}