{
  "type": "Feature",
  "properties": {
    "addr:full":"Unit 8 Skyways Business Park, Fair Oak Close, Exeter Airport Exeter Devon EX5 2UL",
    "addr:housenumber":"unit 8",
    "addr:postcode":"ex5 2ul",
    "addr:street":"Skyways Business Park Fair Oak Close",
    "iso:country":"GB",
    "sg:address":"Unit 8 Skyways Business Park, Fair Oak Close, Exeter Airport",
    "sg:city":"Exeter",
    "sg:classifiers":[
        {
            "category":"Shopping",
            "subcategory":"Gifts & Souvenirs",
            "type":"Retail Goods"
        }
    ],
    "sg:postcode":"EX5 2UL",
    "sg:province":"Devon",
    "sg:tags":[
        "greeting",
        "card"
    ],
    "wof:name":"Card Express",
    "wof:placetype":"venue"
},
  "geometry": {"coordinates":[-3.40881,50.729599],"type":"Point"}
}