{
  "type": "Feature",
  "properties": {
    "addr:full":"High Street, New Galloway Castle Douglas Dumfries and Galloway DG7 3RN",
    "addr:postcode":"dg7 3rn",
    "addr:street":"High Street",
    "iso:country":"GB",
    "sg:address":"High Street, New Galloway",
    "sg:city":"Castle Douglas",
    "sg:classifiers":[
        {
            "category":"Travel",
            "subcategory":"Hotels & Motels",
            "type":"Entertainment"
        },
        {
            "category":"Cafe",
            "type":"Food & Drink"
        }
    ],
    "sg:phone":"+44 1644 420246",
    "sg:postcode":"DG7 3RN",
    "sg:province":"Dumfries and Galloway",
    "sg:tags":[
        "snack",
        "bar",
        "room",
        "house",
        "tea",
        "guest"
    ],
    "wof:name":"KITT'S TEAROOMS",
    "wof:placetype":"venue"
},
  "geometry": {"coordinates":[-4.140919,55.072273],"type":"Point"}
}