{
  "type": "Feature",
  "properties": {
    "iso:country":"GB",
    "sg:address":"231 Woodhouse Road, Fiern Barnet",
    "sg:city":"London",
    "sg:classifiers":[
        {
            "category":"Real Estate",
            "subcategory":"Surveying",
            "type":"Services"
        }
    ],
    "sg:phone":"+44 20 8361 0033",
    "sg:postcode":"N12 9BD",
    "sg:province":"Greater London",
    "sg:tags":[
        "surveyor",
        "valuer"
    ],
    "wof:name":"F Ferrier Tomlin",
    "wof:placetype":"venue"
},
  "geometry": {"coordinates":[-0.158969,51.612709],"type":"Point"}
}