{
  "type": "Feature",
  "properties": {
    "addr:full":"Lander Building, Daniell Road Truro Cornwall TR1 2DA",
    "addr:postcode":"tr1 2da",
    "addr:street":"Daniell Road",
    "iso:country":"GB",
    "sg:address":"Lander Building, Daniell Road",
    "sg:city":"Truro",
    "sg:classifiers":[
        {
            "category":"Professional",
            "subcategory":"Management & Consulting",
            "type":"Services"
        }
    ],
    "sg:phone":"+44 1872 322660",
    "sg:postcode":"TR1 2DA",
    "sg:province":"Cornwall",
    "sg:tags":[
        "conservation"
    ],
    "wof:name":"St. Agnes to Newquay Countryside Service",
    "wof:placetype":"venue"
},
  "geometry": {"coordinates":[-5.0536308289,50.2652397156],"type":"Point"}
}