{
  "type": "Feature",
  "properties": {
    "addr:full":"The Red House Sea Road, Pevensey Bay Pevensey East Sussex BN24 6EH",
    "addr:postcode":"bn24 6eh",
    "addr:street":"Sea Road",
    "iso:country":"GB",
    "sg:address":"The Red House Sea Road, Pevensey Bay",
    "sg:city":"Pevensey",
    "sg:classifiers":[
        {
            "category":"Building & Trades",
            "subcategory":"Cleaning & Sanitation",
            "type":"Services"
        }
    ],
    "sg:phone":"+44 1323 762570",
    "sg:postcode":"BN24 6EH",
    "sg:province":"East Sussex",
    "sg:tags":[
        "commercial"
    ],
    "wof:name":"Allcleaning Ltd.",
    "wof:placetype":"venue"
},
  "geometry": {"coordinates":[0.3517749906,50.8128395081],"type":"Point"}
}