{
  "type": "Feature",
  "properties": {
    "addr:full":"2 Mansfield Road Sutton In Ashfield Nottinghamshire NG17 4GR",
    "addr:housenumber":"2",
    "addr:postcode":"ng17 4gr",
    "addr:street":"Mansfield Road",
    "iso:country":"GB",
    "sg:address":"2 Mansfield Road",
    "sg:city":"Sutton In Ashfield",
    "sg:classifiers":[
        {
            "category":"Building & Trades",
            "subcategory":"Construction",
            "type":"Services"
        }
    ],
    "sg:phone":"+44 1623 440804",
    "sg:postcode":"NG17 4GR",
    "sg:province":"Nottinghamshire",
    "sg:tags":[
        "builder"
    ],
    "wof:name":"Elizabeth Grant",
    "wof:placetype":"venue"
},
  "geometry": {"coordinates":[-1.2535640001,53.131023407],"type":"Point"}
}