{
  "type": "Feature",
  "properties": {
    "addr:full":"Unit 158 Watford Hertfordshire WD17 2TH",
    "addr:housenumber":"158",
    "addr:postcode":"wd17 2th",
    "iso:country":"GB",
    "sg:address":"Unit 158",
    "sg:city":"Watford",
    "sg:classifiers":[
        {
            "category":"Shopping",
            "subcategory":"Shoes",
            "type":"Retail Goods"
        }
    ],
    "sg:phone":"+44 1923 212236",
    "sg:postcode":"WD17 2TH",
    "sg:province":"Hertfordshire",
    "sg:tags":[
        "shop"
    ],
    "wof:name":"Dolcis",
    "wof:placetype":"venue"
},
  "geometry": {"coordinates":[-0.3891789913,51.6544799805],"type":"Point"}
}