{
  "type": "Feature",
  "properties": {
    "addr:full":"43 Mariscaal Street Aberdeen Aberdeen City AB115AB",
    "addr:housenumber":"43",
    "addr:postcode":"ab115ab",
    "addr:street":"Mariscaal Street",
    "iso:country":"GB",
    "sg:address":"43 Mariscaal Street",
    "sg:city":"Aberdeen",
    "sg:classifiers":[
        {
            "category":"Home & Garden",
            "subcategory":"Household Appliances",
            "type":"Retail Goods"
        }
    ],
    "sg:phone":"+44 141 427 7737",
    "sg:postcode":"AB115AB",
    "sg:province":"Aberdeen City",
    "sg:tags":[
        "refrigeration",
        "air conditioning"
    ],
    "wof:name":"Sutton Services International Ltd.",
    "wof:placetype":"venue"
},
  "geometry": {"coordinates":[-2.0921270847,57.1470451355],"type":"Point"}
}