{
  "type": "Feature",
  "properties": {
    "iso:country":"GB",
    "sg:address":"68 Pelham Road",
    "sg:city":"Immingham",
    "sg:classifiers":[
        {
            "category":"Autos & Motor Vehicles",
            "subcategory":"Auto Supplies",
            "type":"Retail Goods"
        }
    ],
    "sg:postcode":"DN40 1AB",
    "sg:province":"Lincolnshire",
    "sg:tags":[
        "component"
    ],
    "wof:name":"Immingham Auto Parts",
    "wof:placetype":"venue"
},
  "geometry": {"coordinates":[-0.202614,53.619816],"type":"Point"}
}