{
  "type": "Feature",
  "properties": {
    "iso:country":"GB",
    "sg:address":"4 York Lodge, Kingston",
    "sg:city":"Yeovil",
    "sg:classifiers":[
        {
            "category":"Real Estate",
            "subcategory":"Developer",
            "type":"Services"
        }
    ],
    "sg:phone":"+44 1935 432199",
    "sg:postcode":"BA20 2QL",
    "sg:province":"Somerset",
    "sg:tags":[
        "property"
    ],
    "wof:name":"Whiteway Developments Ltd.",
    "wof:placetype":"venue"
},
  "geometry": {"coordinates":[-2.635729,50.94429],"type":"Point"}
}