{
  "type": "Feature",
  "properties": {
    "addr:full":"42-44 St Benedicts Street Norwich Norfolk NR2 4AQ",
    "addr:housenumber":"42-44",
    "addr:postcode":"nr2 4aq",
    "addr:street":"St Benedicts Street",
    "iso:country":"GB",
    "sg:address":"42-44 St Benedicts Street",
    "sg:city":"Norwich",
    "sg:classifiers":[
        {
            "category":"Shopping",
            "subcategory":"Used Merchandise",
            "type":"Retail Goods"
        }
    ],
    "sg:phone":"+44 1603 622611",
    "sg:postcode":"NR2 4AQ",
    "sg:province":"Norfolk",
    "sg:tags":[
        "shop",
        "second-hand"
    ],
    "wof:name":"Cash Converters",
    "wof:placetype":"venue"
},
  "geometry": {"coordinates":[1.2890369892,52.6309242249],"type":"Point"}
}