{
  "type": "Feature",
  "properties": {
    "addr:full":"29 Belgrave Road, Newtake Newton Abbot Devon TQ12 4JR",
    "addr:housenumber":"29",
    "addr:postcode":"tq12 4jr",
    "addr:street":"Belgrave Road Newtake",
    "iso:country":"GB",
    "sg:address":"29 Belgrave Road, Newtake",
    "sg:city":"Newton Abbot",
    "sg:classifiers":[
        {
            "category":"Building & Trades",
            "subcategory":"Construction",
            "type":"Services"
        }
    ],
    "sg:phone":"+44 1626 365414",
    "sg:postcode":"TQ12 4JR",
    "sg:province":"Devon",
    "sg:tags":[
        "contractor",
        "paving",
        "driveway"
    ],
    "wof:name":"Premier Paving",
    "wof:placetype":"venue"
},
  "geometry": {"coordinates":[-3.5809049606,50.5218772888],"type":"Point"}
}