{
  "type": "Feature",
  "properties": {
    "addr:full":"Hill House, Flag Hill, Colchester Rd, Great Bentley Colchester Essex CO7 8RE",
    "addr:postcode":"co7 8re",
    "addr:street":"Flag Hill Colchester Rd",
    "iso:country":"GB",
    "sg:address":"Hill House, Flag Hill, Colchester Rd, Great Bentley",
    "sg:city":"Colchester",
    "sg:classifiers":[
        {
            "category":"Recreation",
            "subcategory":"Arcade",
            "type":"Entertainment"
        }
    ],
    "sg:phone":"+44 1255 821201",
    "sg:postcode":"CO7 8RE",
    "sg:province":"Essex",
    "sg:tags":[
        "machine",
        "amusement"
    ],
    "wof:name":"Spencer Servicing",
    "wof:placetype":"venue"
},
  "geometry": {"coordinates":[1.0704610348,51.8204879761],"type":"Point"}
}