{
  "type": "Feature",
  "properties": {
    "iso:country":"GB",
    "sg:address":"Garth House, 303 Bristol Road, Quedgeley",
    "sg:city":"Gloucester",
    "sg:classifiers":[
        {
            "category":"Farming",
            "subcategory":"Nursery",
            "type":"Manufacturing & Wholesale Goods"
        }
    ],
    "sg:phone":"+44 1452 724303",
    "sg:postcode":"GL2 4QP",
    "sg:province":"Gloucestershire",
    "sg:tags":[
        "creche"
    ],
    "wof:name":"Scallywags Day Nursery",
    "wof:placetype":"venue"
},
  "geometry": {"coordinates":[-2.279115,51.818336],"type":"Point"}
}