{
  "type": "Feature",
  "properties": {
    "addr:full":"Unit 3, Rushey Lane Birmingham West Midlands B11 2BL",
    "addr:housenumber":"unit 3",
    "addr:postcode":"b11 2bl",
    "addr:street":"Rushey Lane",
    "iso:country":"GB",
    "sg:address":"Unit 3, Rushey Lane",
    "sg:city":"Birmingham",
    "sg:classifiers":[
        {
            "category":"Shopping",
            "type":"Retail Goods"
        }
    ],
    "sg:phone":"+44 121 708 0172",
    "sg:postcode":"B11 2BL",
    "sg:province":"West Midlands",
    "sg:tags":[
        "part",
        "accessory"
    ],
    "wof:name":"Revolve",
    "wof:placetype":"venue"
},
  "geometry": {"coordinates":[-1.833814,52.4543],"type":"Point"}
}