{
  "type": "Feature",
  "properties": {
    "iso:country":"GB",
    "sg:address":"59 South Park Rd",
    "sg:city":"Macclesfield",
    "sg:classifiers":[
        {
            "category":"Food & Beverages",
            "subcategory":"Supermarket",
            "type":"Retail Goods"
        }
    ],
    "sg:postcode":"SK11 6RS",
    "sg:province":"Cheshire",
    "wof:name":"Newton,H,",
    "wof:placetype":"venue"
},
  "geometry": {"coordinates":[-2.1312060356,53.2545776367],"type":"Point"}
}