{
  "type": "Feature",
  "properties": {
    "addr:full":"59 South Park Rd Macclesfield Cheshire SK11 6RS",
    "addr:housenumber":"59",
    "addr:postcode":"sk11 6rs",
    "addr:street":"South Park Rd",
    "iso:country":"GB",
    "sg:address":"59 South Park Rd",
    "sg:city":"Macclesfield",
    "sg:classifiers":[
        {
            "category":"Food & Beverages",
            "subcategory":"Supermarket",
            "type":"Retail Goods"
        }
    ],
    "sg:postcode":"SK11 6RS",
    "sg:province":"Cheshire",
    "wof:name":"Newton,H,",
    "wof:placetype":"venue"
},
  "geometry": {"coordinates":[-2.1312060356,53.2545776367],"type":"Point"}
}