{
  "type": "Feature",
  "properties": {
    "iso:country":"GB",
    "sg:address":"118 Summerhill Road",
    "sg:city":"Glasgow",
    "sg:classifiers":[
        {
            "category":"Professional",
            "subcategory":"Lawyer & Legal Services",
            "type":"Services"
        }
    ],
    "sg:phone":"+44 141 944 2255",
    "sg:postcode":"G15 7JY",
    "sg:province":"Glasgow City",
    "sg:tags":[
        "solicitor"
    ],
    "wof:name":"SINCLAIR MCCORMICK & GIUSTI MARTIN",
    "wof:placetype":"venue"
},
  "geometry": {"coordinates":[-4.3562760353,55.9161911011],"type":"Point"}
}