{
  "type": "Feature",
  "properties": {
    "iso:country":"GB",
    "sg:address":"13 Eskside West",
    "sg:city":"Musselburgh",
    "sg:classifiers":[
        {
            "category":"Professional",
            "subcategory":"Management & Consulting",
            "type":"Services"
        }
    ],
    "sg:phone":"+44 131 665 5669",
    "sg:postcode":"EH21 6PL",
    "sg:province":"City of Edinburgh",
    "sg:tags":[
        "consultant",
        "business"
    ],
    "wof:name":"Corona Consulting Ltd.",
    "wof:placetype":"venue"
},
  "geometry": {"coordinates":[-3.053836,55.943459],"type":"Point"}
}