{
  "type": "Feature",
  "properties": {
    "addr:full":"118 Station Rd Wallsend Tyne and Wear NE28 8QS",
    "addr:housenumber":"118",
    "addr:postcode":"ne28 8qs",
    "addr:street":"Station Rd",
    "iso:country":"GB",
    "sg:address":"118 Station Rd",
    "sg:city":"Wallsend",
    "sg:classifiers":[
        {
            "category":"Personal",
            "subcategory":"Beauty Salon",
            "type":"Services"
        }
    ],
    "sg:phone":"+44 191 262 0912",
    "sg:postcode":"NE28 8QS",
    "sg:province":"Tyne and Wear",
    "wof:name":"Images Of Fern Park",
    "wof:placetype":"venue"
},
  "geometry": {"coordinates":[-1.5336649418,54.9915275574],"type":"Point"}
}