{
  "type": "Feature",
  "properties": {
    "iso:country":"GB",
    "sg:address":"109 Waterside Road, Carmunnock, Clarkston",
    "sg:city":"Glasgow",
    "sg:classifiers":[
        {
            "category":"Community Center",
            "type":"Public Place"
        }
    ],
    "sg:phone":"+44 141 644 1340",
    "sg:postcode":"G76 9DU",
    "sg:province":"East Renfrewshire",
    "sg:tags":[
        "recreation",
        "leisure",
        "centre"
    ],
    "wof:name":"Carmunnock Village Recreation Club",
    "wof:placetype":"venue"
},
  "geometry": {"coordinates":[-4.235111,55.791359],"type":"Point"}
}