{
  "type": "Feature",
  "properties": {
    "iso:country":"GB",
    "sg:address":"405 High Street",
    "sg:city":"Perth",
    "sg:classifiers":[
        {
            "category":"Retail",
            "subcategory":"Auto Rental",
            "type":"Services"
        }
    ],
    "sg:phone":"+44 1738 623097",
    "sg:postcode":"PH1 1PL",
    "sg:province":"Perth and Kinross",
    "sg:tags":[
        "truck",
        "hire",
        "van"
    ],
    "wof:name":"Autorent Van Hire",
    "wof:placetype":"venue"
},
  "geometry": {"coordinates":[-3.439609,56.397652],"type":"Point"}
}