{
  "type": "Feature",
  "properties": {
    "iso:country":"GB",
    "sg:address":"6 Merland Rise",
    "sg:city":"Epsom",
    "sg:classifiers":[
        {
            "category":"Health Services",
            "subcategory":"Podiatrist",
            "type":"Services"
        }
    ],
    "sg:phone":"+44 1737 371134",
    "sg:postcode":"KT18 5RZ",
    "sg:province":"Surrey",
    "sg:tags":[
        "podiatrists",
        "chiropodist"
    ],
    "wof:name":"Terry D Noble",
    "wof:placetype":"venue"
},
  "geometry": {"coordinates":[-0.2361090034,51.3077964783],"type":"Point"}
}