{
  "type": "Feature",
  "properties": {
    "iso:country":"GB",
    "sg:address":"The Elms, Upper Tockington Road, Tockington",
    "sg:city":"Bristol",
    "sg:classifiers":[
        {
            "category":"Farming",
            "subcategory":"Poultry Farm",
            "type":"Manufacturing & Wholesale Goods"
        }
    ],
    "sg:phone":"+44 1454 613252",
    "sg:postcode":"BS32 4LQ",
    "sg:province":"Gloucestershire",
    "sg:tags":[
        "game"
    ],
    "wof:name":"Tockington Poultry Centre",
    "wof:placetype":"venue"
},
  "geometry": {"coordinates":[-2.5650498867,51.5766410828],"type":"Point"}
}