{
  "type": "Feature",
  "properties": {
    "iso:country":"GB",
    "sg:address":"6 Kings Road",
    "sg:city":"Alton",
    "sg:classifiers":[
        {
            "category":"Shopping",
            "subcategory":"Catalog Store",
            "type":"Retail Goods"
        }
    ],
    "sg:phone":"+44 1420 543366",
    "sg:postcode":"GU34 1PZ",
    "sg:province":"Hampshire",
    "sg:tags":[
        "mail",
        "order"
    ],
    "wof:name":"David Johnson",
    "wof:placetype":"venue"
},
  "geometry": {"coordinates":[-0.985525,51.147045],"type":"Point"}
}