{
  "type": "Feature",
  "properties": {
    "addr:full":"29 Moriconium Quay, Lake Avenue Poole Dorset BH15 4QP",
    "addr:housenumber":"29",
    "addr:postcode":"bh15 4qp",
    "addr:street":"Moriconium Quay Lake Avenue",
    "iso:country":"GB",
    "sg:address":"29 Moriconium Quay, Lake Avenue",
    "sg:city":"Poole",
    "sg:classifiers":[
        {
            "category":"Real Estate",
            "subcategory":"Developer",
            "type":"Services"
        }
    ],
    "sg:phone":"+44 1202 678086",
    "sg:postcode":"BH15 4QP",
    "sg:province":"Dorset",
    "sg:tags":[
        "property"
    ],
    "wof:name":"Gemsa Ltd.",
    "wof:placetype":"venue"
},
  "geometry": {"coordinates":[-1.9867390394,50.7144851685],"type":"Point"}
}