{
  "type": "Feature",
  "properties": {
    "addr:full":"14-18 Gibraltar Row, King Edward Industrial Estate Liverpool Merseyside L3 7HJ",
    "addr:housenumber":"14-18",
    "addr:postcode":"l3 7hj",
    "addr:street":"Gibraltar Row;Industrial Estate",
    "iso:country":"GB",
    "sg:address":"14-18 Gibraltar Row, King Edward Industrial Estate",
    "sg:city":"Liverpool",
    "sg:classifiers":[
        {
            "category":"Professional",
            "subcategory":"Printing & Photocopies",
            "type":"Services"
        }
    ],
    "sg:postcode":"L3 7HJ",
    "sg:province":"Merseyside",
    "sg:tags":[
        "printer"
    ],
    "wof:name":"Printfine Ltd.",
    "wof:placetype":"venue"
},
  "geometry": {"coordinates":[-2.998337,53.411263],"type":"Point"}
}