{
  "type": "Feature",
  "properties": {
    "addr:full":"North View, Main Road, Flax Bourton Bristol Somerset BS48 3QJ",
    "addr:postcode":"bs48 3qj",
    "addr:street":"North;Main Road",
    "iso:country":"GB",
    "sg:address":"North View, Main Road, Flax Bourton",
    "sg:city":"Bristol",
    "sg:classifiers":[
        {
            "category":"Building & Trades",
            "subcategory":"Construction",
            "type":"Services"
        }
    ],
    "sg:phone":"+44 1225 463344",
    "sg:postcode":"BS48 3QJ",
    "sg:province":"Somerset",
    "sg:tags":[
        "roofing"
    ],
    "wof:name":"Paul O'Brien Roofing Ltd.",
    "wof:placetype":"venue"
},
  "geometry": {"coordinates":[-2.706053,51.386551],"type":"Point"}
}