{
  "type": "Feature",
  "properties": {
    "iso:country":"GB",
    "sg:address":"Unit 3 77 Glassbrook Rd",
    "sg:city":"Rushden",
    "sg:classifiers":[
        {
            "category":"Shopping",
            "subcategory":"Bicycles & Sporting Goods",
            "type":"Retail Goods"
        }
    ],
    "sg:phone":"+44 1933 777123",
    "sg:postcode":"NN10 9TH",
    "sg:province":"Bedfordshire",
    "sg:tags":[
        "equipment",
        "leisure"
    ],
    "wof:name":"Club Sub (North Hants)",
    "wof:placetype":"venue"
},
  "geometry": {"coordinates":[-0.608062,52.291183],"type":"Point"}
}