{
  "type": "Feature",
  "properties": {
    "addr:full":"64 Lyndon Av, Shevington Wigan Lancashire WN6 8BU",
    "addr:housenumber":"64",
    "addr:postcode":"wn6 8bu",
    "addr:street":"Lyndon Av",
    "iso:country":"GB",
    "sg:address":"64 Lyndon Av, Shevington",
    "sg:city":"Wigan",
    "sg:classifiers":[
        {
            "category":"Building & Trades",
            "subcategory":"Construction",
            "type":"Services"
        }
    ],
    "sg:phone":"+44 1257 421799",
    "sg:postcode":"WN6 8BU",
    "sg:province":"Lancashire",
    "sg:tags":[
        "decorator",
        "painter"
    ],
    "wof:name":"A Hewitt Artexing",
    "wof:placetype":"venue"
},
  "geometry": {"coordinates":[-2.688644886,53.5764122009],"type":"Point"}
}