{
  "type": "Feature",
  "properties": {
    "addr:full":"Briercliffe Road Burnley Lancashire BB10 1UR",
    "addr:postcode":"bb10 1ur",
    "addr:street":"Briercliffe Road",
    "iso:country":"GB",
    "sg:address":"Briercliffe Road",
    "sg:city":"Burnley",
    "sg:classifiers":[
        {
            "category":"Banks & Credit Unions",
            "subcategory":"Bank",
            "type":"Services"
        }
    ],
    "sg:phone":"+44 845 765 4321",
    "sg:postcode":"BB10 1UR",
    "sg:province":"Lancashire",
    "wof:name":"Abbey National Plc",
    "wof:placetype":"venue"
},
  "geometry": {"coordinates":[-2.224034071,53.8084793091],"type":"Point"}
}