{
  "type": "Feature",
  "properties": {
    "addr:full":"4 Parklands Road Chichester West Sussex PO19 3DT",
    "addr:housenumber":"4",
    "addr:postcode":"po19 3dt",
    "addr:street":"Parklands Road",
    "iso:country":"GB",
    "sg:address":"4 Parklands Road",
    "sg:city":"Chichester",
    "sg:classifiers":[
        {
            "category":"Health Services",
            "subcategory":"Doctor",
            "type":"Services"
        },
        {
            "category":"Health Services",
            "subcategory":"Clinic",
            "type":"Services"
        }
    ],
    "sg:phone":"+44 1243 782819",
    "sg:postcode":"PO19 3DT",
    "sg:province":"West Sussex",
    "sg:tags":[
        "nh",
        "practitioners"
    ],
    "wof:name":"Dr Copsey & Partners",
    "wof:placetype":"venue"
},
  "geometry": {"coordinates":[-0.7886660099,50.8368263245],"type":"Point"}
}