{
  "type": "Feature",
  "properties": {
    "iso:country":"GB",
    "sg:address":"Unit 12-13 Baxter Square, Freshney Place",
    "sg:city":"Grimsby",
    "sg:classifiers":[
        {
            "category":"Shopping",
            "subcategory":"Clothing, Apparel, & Fashions",
            "type":"Retail Goods"
        }
    ],
    "sg:phone":"+44 1472 348560",
    "sg:postcode":"DN31 1QQ",
    "sg:province":"Lincolnshire",
    "sg:tags":[
        "shop"
    ],
    "wof:name":"River Island Clothing Co",
    "wof:placetype":"venue"
},
  "geometry": {"coordinates":[-0.08646,53.566151],"type":"Point"}
}