{
  "type": "Feature",
  "properties": {
    "addr:full":"38 West Street, Storrington Pulborough West Sussex RH20 4EE",
    "addr:housenumber":"38",
    "addr:postcode":"rh20 4ee",
    "addr:street":"West Street",
    "iso:country":"GB",
    "sg:address":"38 West Street, Storrington",
    "sg:city":"Pulborough",
    "sg:classifiers":[
        {
            "category":"Shopping",
            "subcategory":"Bicycles & Sporting Goods",
            "type":"Retail Goods"
        }
    ],
    "sg:phone":"+44 1903 745534",
    "sg:postcode":"RH20 4EE",
    "sg:province":"West Sussex",
    "sg:tags":[
        "cycle",
        "accessory"
    ],
    "wof:name":"The Storrington Cyclist",
    "wof:placetype":"venue"
},
  "geometry": {"coordinates":[-0.456679,50.918289],"type":"Point"}
}