{
  "type": "Feature",
  "properties": {
    "addr:full":"56 Stowupland Road, Charles Industrial Estate Stowmarket Suffolk IP14 5AL",
    "addr:housenumber":"56",
    "addr:postcode":"ip14 5al",
    "addr:street":"Stowupland Road Charles Industrial Estate",
    "iso:country":"GB",
    "sg:address":"56 Stowupland Road, Charles Industrial Estate",
    "sg:city":"Stowmarket",
    "sg:classifiers":[
        {
            "category":"Professional",
            "subcategory":"Computer Services",
            "type":"Services"
        }
    ],
    "sg:postcode":"IP14 5AL",
    "sg:province":"Suffolk",
    "sg:tags":[
        "system",
        "software"
    ],
    "wof:name":"Raycom Systems",
    "wof:placetype":"venue"
},
  "geometry": {"coordinates":[1.0015300512,52.1922531128],"type":"Point"}
}