{
  "type": "Feature",
  "properties": {
    "iso:country":"GB",
    "sg:address":"21 Church Walk",
    "sg:city":"Thames Ditton",
    "sg:classifiers":[
        {
            "category":"Communications",
            "subcategory":"Newspaper",
            "type":"Services"
        }
    ],
    "sg:phone":"+44 20 8398 2000",
    "sg:postcode":"KT7 0NP",
    "sg:province":"Surrey",
    "sg:tags":[
        "magazine"
    ],
    "wof:name":"Drumport Ltd.",
    "wof:placetype":"venue"
},
  "geometry": {"coordinates":[-0.33498,51.391773],"type":"Point"}
}