{
  "type": "Feature",
  "properties": {
    "addr:full":"103 Durham Road Consett Durham DH8 8RP",
    "addr:housenumber":"103",
    "addr:postcode":"dh8 8rp",
    "addr:street":"Durham Road",
    "iso:country":"GB",
    "sg:address":"103 Durham Road",
    "sg:city":"Consett",
    "sg:classifiers":[
        {
            "category":"Personal",
            "subcategory":"Beauty Salon",
            "type":"Services"
        }
    ],
    "sg:phone":"+44 1207 500312",
    "sg:postcode":"DH8 8RP",
    "sg:province":"Durham",
    "sg:tags":[
        "unisex",
        "hairdresser"
    ],
    "wof:name":"I & S Hair Design",
    "wof:placetype":"venue"
},
  "geometry": {"coordinates":[-1.848567009,54.861125946],"type":"Point"}
}