{
  "type": "Feature",
  "properties": {
    "addr:full":"22 Petitor Road, St Marychurch Torquay Devon TQ1 4QD",
    "addr:housenumber":"22",
    "addr:postcode":"tq1 4qd",
    "addr:street":"Petitor Road St Marychurch",
    "iso:country":"GB",
    "sg:address":"22 Petitor Road, St Marychurch",
    "sg:city":"Torquay",
    "sg:classifiers":[
        {
            "category":"Health Services",
            "subcategory":"Nursing And Care Facility",
            "type":"Services"
        }
    ],
    "sg:postcode":"TQ1 4QD",
    "sg:province":"Devon",
    "sg:tags":[
        "home"
    ],
    "wof:name":"Kaemar House Residential Home",
    "wof:placetype":"venue"
},
  "geometry": {"coordinates":[-3.5227530003,50.4848747253],"type":"Point"}
}