{
  "type": "Feature",
  "properties": {
    "addr:full":"72 Banners La Halesowen West Midlands B63 2SD",
    "addr:housenumber":"72",
    "addr:postcode":"b63 2sd",
    "addr:street":"Banners La Halesowen",
    "iso:country":"GB",
    "sg:address":"72 Banners La",
    "sg:city":"Halesowen",
    "sg:classifiers":[
        {
            "category":"Organizations",
            "subcategory":"Non-profit Organization",
            "type":"Services"
        }
    ],
    "sg:postcode":"B63 2SD",
    "sg:province":"West Midlands",
    "sg:tags":[
        "organisation",
        "voluntary",
        "charity"
    ],
    "wof:name":"Christian Consciousness",
    "wof:placetype":"venue"
},
  "geometry": {"coordinates":[-2.0761239529,52.4617576599],"type":"Point"}
}