{
  "type": "Feature",
  "properties": {
    "addr:full":"115 Union Street Torquay Devon TQ1 3DW",
    "addr:housenumber":"115",
    "addr:postcode":"tq1 3dw",
    "addr:street":"Union Street",
    "iso:country":"GB",
    "sg:address":"115 Union Street",
    "sg:city":"Torquay",
    "sg:classifiers":[
        {
            "category":"Real Estate",
            "subcategory":"Real Estate Agent",
            "type":"Services"
        }
    ],
    "sg:phone":"+44 1803 213641",
    "sg:postcode":"TQ1 3DW",
    "sg:province":"Devon",
    "sg:website":"http://www.connells.co.uk",
    "wof:name":"Connell Estate Agents",
    "wof:placetype":"venue"
},
  "geometry": {"coordinates":[-3.531914,50.468227],"type":"Point"}
}