{
  "type": "Feature",
  "properties": {
    "iso:country":"GB",
    "sg:address":"3a Hailes Street, Winchcombe",
    "sg:city":"Cheltenham",
    "sg:classifiers":[
        {
            "category":"Professional",
            "subcategory":"Advertising",
            "type":"Services"
        }
    ],
    "sg:phone":"+44 1242 603333",
    "sg:postcode":"GL54 5HU",
    "sg:province":"Gloucestershire",
    "sg:tags":[
        "agency"
    ],
    "wof:name":"Mike Weaver Advertising",
    "wof:placetype":"venue"
},
  "geometry": {"coordinates":[-1.963271,51.954006],"type":"Point"}
}