{
  "type": "Feature",
  "properties": {
    "addr:full":"Randalls Road Leatherhead Surrey KT22 0AG",
    "addr:postcode":"kt22 0ag",
    "addr:street":"Randalls Road",
    "iso:country":"GB",
    "sg:address":"Randalls Road",
    "sg:city":"Leatherhead",
    "sg:classifiers":[
        {
            "category":"Retail",
            "subcategory":"Funeral Services",
            "type":"Services"
        }
    ],
    "sg:phone":"+44 1372 373813",
    "sg:postcode":"KT22 0AG",
    "sg:province":"Surrey",
    "sg:tags":[
        "cemetery",
        "crematorium"
    ],
    "wof:name":"Randalls Park Crematorium",
    "wof:placetype":"venue"
},
  "geometry": {"coordinates":[-0.3493449986,51.3072357178],"type":"Point"}
}