{
  "type": "Feature",
  "properties": {
    "iso:country":"GB",
    "sg:address":"Unit 9 Amber Clo",
    "sg:city":"Tamworth",
    "sg:classifiers":[
        {
            "category":"Professional",
            "subcategory":"Art Services",
            "type":"Services"
        }
    ],
    "sg:postcode":"B77 4RP",
    "sg:province":"Staffordshire",
    "sg:tags":[
        "model",
        "maker"
    ],
    "wof:name":"Needwood Precision Products",
    "wof:placetype":"venue"
},
  "geometry": {"coordinates":[-1.650389,52.62648],"type":"Point"}
}