{
  "type": "Feature",
  "properties": {
    "addr:full":"35c Bear Street Barnstaple Devon EX32 7BZ",
    "addr:housenumber":"35c",
    "addr:postcode":"ex32 7bz",
    "addr:street":"Bear Street",
    "iso:country":"GB",
    "sg:address":"35c Bear Street",
    "sg:city":"Barnstaple",
    "sg:classifiers":[
        {
            "category":"Shopping",
            "subcategory":"Pharmacy",
            "type":"Retail Goods"
        }
    ],
    "sg:postcode":"EX32 7BZ",
    "sg:province":"Devon",
    "sg:tags":[
        "medicine",
        "therapy"
    ],
    "wof:name":"The Natural Health Clinic",
    "wof:placetype":"venue"
},
  "geometry": {"coordinates":[-4.055744,51.081135],"type":"Point"}
}