{
  "type": "Feature",
  "properties": {
    "iso:country":"GB",
    "sg:address":"17 St Marys Place",
    "sg:city":"Chippenham",
    "sg:classifiers":[
        {
            "category":"Professional",
            "subcategory":"Printing & Photocopies",
            "type":"Services"
        }
    ],
    "sg:postcode":"SN15 1EN",
    "sg:province":"Wiltshire",
    "sg:tags":[
        "duplicating",
        "copying"
    ],
    "wof:name":"B M Windram",
    "wof:placetype":"venue"
},
  "geometry": {"coordinates":[-2.116324,51.461136],"type":"Point"}
}