{
  "type": "Feature",
  "properties": {
    "addr:full":"34 Guildford Road Brighton East Sussex BN1 3LW",
    "addr:housenumber":"34",
    "addr:postcode":"bn1 3lw",
    "addr:street":"Guildford Road",
    "iso:country":"GB",
    "sg:address":"34 Guildford Road",
    "sg:city":"Brighton",
    "sg:classifiers":[
        {
            "category":"Bars & Pubs",
            "type":"Food & Drink"
        }
    ],
    "sg:phone":"+44 1273 327997",
    "sg:postcode":"BN1 3LW",
    "sg:province":"East Sussex",
    "sg:tags":[
        "pubs",
        "inn"
    ],
    "wof:name":"The Battle of Trafalgar",
    "wof:placetype":"venue"
},
  "geometry": {"coordinates":[-0.142559,50.828274],"type":"Point"}
}