{
  "type": "Feature",
  "properties": {
    "addr:full":"16 Arcadia Gardens, Oakington Cambridge Cambridgeshire CB4 5AJ",
    "addr:housenumber":"16",
    "addr:postcode":"cb4 5aj",
    "addr:street":"Arcadia Gardens",
    "iso:country":"GB",
    "sg:address":"16 Arcadia Gardens, Oakington",
    "sg:city":"Cambridge",
    "sg:classifiers":[
        {
            "category":"Home & Garden",
            "subcategory":"Building Materials",
            "type":"Retail Goods"
        }
    ],
    "sg:phone":"+44 1223 234266",
    "sg:postcode":"CB4 5AJ",
    "sg:province":"Cambridgeshire",
    "sg:tags":[
        "fencing"
    ],
    "wof:name":"Paul Barry Wilson",
    "wof:placetype":"venue"
},
  "geometry": {"coordinates":[0.068225,52.258999],"type":"Point"}
}