{
  "type": "Feature",
  "properties": {
    "addr:full":"26 Alexandra Road Mold Denbighshire CH7 1HJ",
    "addr:housenumber":"26",
    "addr:postcode":"ch7 1hj",
    "addr:street":"Alexandra Road",
    "iso:country":"GB",
    "sg:address":"26 Alexandra Road",
    "sg:city":"Mold",
    "sg:classifiers":[
        {
            "category":"Wholesale",
            "subcategory":"Fruits & Vegetables",
            "type":"Manufacturing & Wholesale Goods"
        }
    ],
    "sg:postcode":"CH7 1HJ",
    "sg:province":"Denbighshire",
    "wof:name":"D R Parry & Son",
    "wof:placetype":"venue"
},
  "geometry": {"coordinates":[-3.1366040707,53.165058136],"type":"Point"}
}