{
  "type": "Feature",
  "properties": {
    "addr:full":"468 Gower Road Swansea Swansea SA2 7DZ",
    "addr:housenumber":"468",
    "addr:postcode":"sa2 7dz",
    "addr:street":"Gower Road",
    "iso:country":"GB",
    "sg:address":"468 Gower Road",
    "sg:city":"Swansea",
    "sg:classifiers":[
        {
            "category":"Home & Garden",
            "subcategory":"Hardware",
            "type":"Retail Goods"
        }
    ],
    "sg:postcode":"SA2 7DZ",
    "sg:province":"Swansea",
    "sg:tags":[
        "retailer",
        "diy"
    ],
    "wof:name":"C H Hardware",
    "wof:placetype":"venue"
},
  "geometry": {"coordinates":[-4.022174,51.616642],"type":"Point"}
}