{
  "type": "Feature",
  "properties": {
    "addr:full":"2 Elmtree Drive, Burbage Hinckley Leicestershire LE10 2TX",
    "addr:housenumber":"2",
    "addr:postcode":"le10 2tx",
    "addr:street":"Elmtree Drive",
    "iso:country":"GB",
    "sg:address":"2 Elmtree Drive, Burbage",
    "sg:city":"Hinckley",
    "sg:classifiers":[
        {
            "category":"Building & Trades",
            "subcategory":"Equipment Rental",
            "type":"Services"
        }
    ],
    "sg:phone":"+44 1455 230680",
    "sg:postcode":"LE10 2TX",
    "sg:province":"Leicestershire",
    "sg:tags":[
        "plant",
        "machinery"
    ],
    "wof:name":"A E Hopewell Ltd.",
    "wof:placetype":"venue"
},
  "geometry": {"coordinates":[-1.354293,52.540413],"type":"Point"}
}