{
  "type": "Feature",
  "properties": {
    "iso:country":"GB",
    "sg:address":"Unit 23, Parsonage Indstl Est, Forest Ha",
    "sg:city":"Stansted",
    "sg:classifiers":[
        {
            "category":"Building & Trades",
            "subcategory":"Plumbing",
            "type":"Services"
        }
    ],
    "sg:phone":"+44 1279 647764",
    "sg:postcode":"CM24 8TY",
    "sg:province":"Essex",
    "sg:tags":[
        "heating"
    ],
    "wof:name":"A & T Services",
    "wof:placetype":"venue"
},
  "geometry": {"coordinates":[0.2034,51.886841],"type":"Point"}
}