{
  "type": "Feature",
  "properties": {
    "addr:full":"Unit 16 Falcon Close Burton On Trent Derbyshire DE14 1SG",
    "addr:housenumber":"unit 16",
    "addr:postcode":"de14 1sg",
    "addr:street":"Falcon Close",
    "iso:country":"GB",
    "sg:address":"Unit 16 Falcon Close",
    "sg:city":"Burton On Trent",
    "sg:classifiers":[
        {
            "category":"Taxi",
            "type":"Transportation"
        }
    ],
    "sg:phone":"+44 1283 540000",
    "sg:postcode":"DE14 1SG",
    "sg:province":"Derbyshire",
    "sg:tags":[
        "mini",
        "cab"
    ],
    "wof:name":"Umar Hayad",
    "wof:placetype":"venue"
},
  "geometry": {"coordinates":[-1.627839,52.816147],"type":"Point"}
}