{
  "type": "Feature",
  "properties": {
    "addr:full":"1 Stangate Mansions, Tower Road Twickenham Greater London TW1 4PW",
    "addr:housenumber":"1",
    "addr:postcode":"tw1 4pw",
    "addr:street":"Stangate;Tower Road",
    "iso:country":"GB",
    "sg:address":"1 Stangate Mansions, Tower Road",
    "sg:city":"Twickenham",
    "sg:classifiers":[
        {
            "category":"Professional",
            "subcategory":"Engineering",
            "type":"Services"
        }
    ],
    "sg:postcode":"TW1 4PW",
    "sg:province":"Greater London",
    "sg:tags":[
        "consulting",
        "engineer"
    ],
    "wof:name":"Steve Elphick Associates",
    "wof:placetype":"venue"
},
  "geometry": {"coordinates":[-0.328229,51.446636],"type":"Point"}
}