{
  "type": "Feature",
  "properties": {
    "addr:full":"51 Clifton Street Lytham St Annes Lancashire FY8 5ER",
    "addr:housenumber":"51",
    "addr:postcode":"fy8 5er",
    "addr:street":"Clifton Street",
    "iso:country":"GB",
    "sg:address":"51 Clifton Street",
    "sg:city":"Lytham St Annes",
    "sg:classifiers":[
        {
            "category":"Shopping",
            "subcategory":"Shoes",
            "type":"Retail Goods"
        }
    ],
    "sg:phone":"+44 1253 731094",
    "sg:postcode":"FY8 5ER",
    "sg:province":"Lancashire",
    "sg:tags":[
        "shop"
    ],
    "wof:name":"Stampede Childrens Shoe Co",
    "wof:placetype":"venue"
},
  "geometry": {"coordinates":[-2.9600811005,53.7374420166],"type":"Point"}
}