{
  "type": "Feature",
  "properties": {
    "iso:country":"GB",
    "sg:address":"Unit 1 Adderley Trading Estate, Adderley Road, Saltley",
    "sg:city":"Birmingham",
    "sg:classifiers":[
        {
            "category":"Manufacturing",
            "subcategory":"Furniture",
            "type":"Manufacturing & Wholesale Goods"
        }
    ],
    "sg:postcode":"B8 1AN",
    "sg:province":"West Midlands",
    "sg:tags":[
        "mnfr",
        "upholsterer"
    ],
    "wof:name":"Apollo Furniture Frames",
    "wof:placetype":"venue"
},
  "geometry": {"coordinates":[-1.862094,52.48716],"type":"Point"}
}