{
  "type": "Feature",
  "properties": {
    "iso:country":"GB",
    "sg:address":"687 Warrington Rd",
    "sg:city":"Warrington",
    "sg:classifiers":[
        {
            "category":"Restaurant",
            "type":"Food & Drink"
        }
    ],
    "sg:phone":"+44 1925 812022",
    "sg:postcode":"WA3 6AY",
    "sg:province":"Cheshire",
    "wof:name":"Noggin Inn",
    "wof:placetype":"venue"
},
  "geometry": {"coordinates":[-2.526149,53.43351],"type":"Point"}
}