{
  "type": "Feature",
  "properties": {
    "iso:country":"GB",
    "sg:address":"45 Watercall Avenue",
    "sg:city":"Coventry",
    "sg:classifiers":[
        {
            "category":"Shopping",
            "subcategory":"Stationery & Office Supplies",
            "type":"Retail Goods"
        },
        {
            "category":"Retail",
            "subcategory":"Repair Shop",
            "type":"Services"
        }
    ],
    "sg:phone":"+44 24 7641 1895",
    "sg:postcode":"CV3 5AW",
    "sg:province":"Warwickshire",
    "sg:tags":[
        "machine",
        "clock",
        "watch",
        "sale",
        "recording",
        "time"
    ],
    "wof:name":"J S Clock Repairs",
    "wof:placetype":"venue"
},
  "geometry": {"coordinates":[-1.509995,52.385654],"type":"Point"}
}