{
  "type": "Feature",
  "properties": {
    "addr:full":"Cannon Mills Bradford West Yorkshire BD7 3HW",
    "addr:postcode":"bd7 3hw",
    "addr:street":"Cannon;Bradford West",
    "iso:country":"GB",
    "sg:address":"Cannon Mills",
    "sg:city":"Bradford",
    "sg:classifiers":[
        {
            "category":"Shopping",
            "subcategory":"Books",
            "type":"Retail Goods"
        }
    ],
    "sg:phone":"+44 1274 521191",
    "sg:postcode":"BD7 3HW",
    "sg:province":"West Yorkshire",
    "sg:tags":[
        "bookseller"
    ],
    "wof:name":"Bookworld",
    "wof:placetype":"venue"
},
  "geometry": {"coordinates":[-1.7834320068,53.7836227417],"type":"Point"}
}