{
  "type": "Feature",
  "properties": {
    "addr:full":"274 Low Lane, Horsforth Leeds West Yorkshire LS18 5DN",
    "addr:housenumber":"274",
    "addr:postcode":"ls18 5dn",
    "addr:street":"Low Lane",
    "iso:country":"GB",
    "sg:address":"274 Low Lane, Horsforth",
    "sg:city":"Leeds",
    "sg:classifiers":[
        {
            "category":"Fast Food",
            "type":"Food & Drink"
        },
        {
            "category":"Food & Beverages",
            "subcategory":"Meat & Fish",
            "type":"Retail Goods"
        }
    ],
    "sg:phone":"+44 113 258 2371",
    "sg:postcode":"LS18 5DN",
    "sg:province":"West Yorkshire",
    "sg:tags":[
        "shop",
        "chip"
    ],
    "wof:name":"David & Natalie Orange",
    "wof:placetype":"venue"
},
  "geometry": {"coordinates":[-1.622003,53.839474],"type":"Point"}
}