{
  "type": "Feature",
  "properties": {
    "addr:full":"22 Berrycroft Lane, Romiley Stockport Cheshire SK6 3AU",
    "addr:housenumber":"22",
    "addr:postcode":"sk6 3au",
    "addr:street":"Berrycroft Lane",
    "iso:country":"GB",
    "sg:address":"22 Berrycroft Lane, Romiley",
    "sg:city":"Stockport",
    "sg:classifiers":[
        {
            "category":"Fast Food",
            "type":"Food & Drink"
        }
    ],
    "sg:phone":"+44 161 406 6446",
    "sg:postcode":"SK6 3AU",
    "sg:province":"Cheshire",
    "sg:tags":[
        "away",
        "take"
    ],
    "wof:name":"The Slow Boat",
    "wof:placetype":"venue"
},
  "geometry": {"coordinates":[-2.104082,53.415726],"type":"Point"}
}