{
  "type": "Feature",
  "properties": {
    "addr:full":"Slade Green, Maintenance Depot, Moat Lane Erith Kent DA8 2NJ",
    "addr:postcode":"da8 2nj",
    "addr:street":"Slade;Moat Lane",
    "iso:country":"GB",
    "sg:address":"Slade Green, Maintenance Depot, Moat Lane",
    "sg:city":"Erith",
    "sg:classifiers":[
        {
            "category":"Wholesale",
            "subcategory":"Machinery & Supplies",
            "type":"Manufacturing & Wholesale Goods"
        }
    ],
    "sg:phone":"+44 1322 348300",
    "sg:postcode":"DA8 2NJ",
    "sg:province":"Kent",
    "sg:tags":[
        "equipment",
        "railway"
    ],
    "wof:name":"BREL Ltd",
    "wof:placetype":"venue"
},
  "geometry": {"coordinates":[0.1867360026,51.4708328247],"type":"Point"}
}