{
  "type": "Feature",
  "properties": {
    "addr:full":"Main Road, Renishaw Sheffield Derbyshire S21 3UX",
    "addr:postcode":"s21 3ux",
    "addr:street":"Main Road",
    "iso:country":"GB",
    "sg:address":"Main Road, Renishaw",
    "sg:city":"Sheffield",
    "sg:classifiers":[
        {
            "category":"Manufacturing",
            "subcategory":"Building Materials",
            "type":"Manufacturing & Wholesale Goods"
        }
    ],
    "sg:phone":"+44 1246 432251",
    "sg:postcode":"S21 3UX",
    "sg:province":"Derbyshire",
    "sg:tags":[
        "tarmac",
        "asphalt"
    ],
    "wof:name":"Tarmac Quarry Products",
    "wof:placetype":"venue"
},
  "geometry": {"coordinates":[-1.3318510056,53.2968597412],"type":"Point"}
}