{
  "type": "Feature",
  "properties": {
    "addr:full":"539 Green Lanes London Greater London N8 0RL",
    "addr:housenumber":"539",
    "addr:postcode":"n8 0rl",
    "addr:street":"Green Lanes",
    "iso:country":"GB",
    "sg:address":"539 Green Lanes",
    "sg:city":"London",
    "sg:classifiers":[
        {
            "category":"Communications",
            "type":"Services"
        }
    ],
    "sg:phone":"+44 20 8348 7656",
    "sg:postcode":"N8 0RL",
    "sg:province":"Greater London",
    "sg:tags":[
        "telecommunication"
    ],
    "wof:name":"Global Calling Centre",
    "wof:placetype":"venue"
},
  "geometry": {"coordinates":[-0.0999749973,51.582572937],"type":"Point"}
}