{
  "type": "Feature",
  "properties": {
    "iso:country":"GB",
    "sg:address":"34 Chapel Street",
    "sg:city":"Thatcham",
    "sg:classifiers":[
        {
            "category":"Professional",
            "subcategory":"Accounting & Tax Preparation",
            "type":"Services"
        }
    ],
    "sg:phone":"+44 1635 867222",
    "sg:postcode":"RG18 4QL",
    "sg:province":"Berkshire",
    "sg:tags":[
        "accountant",
        "activity"
    ],
    "wof:name":"Paul D Welch",
    "wof:placetype":"venue"
},
  "geometry": {"coordinates":[-1.2549090385,51.4037017822],"type":"Point"}
}