{
  "type": "Feature",
  "properties": {
    "iso:country":"GB",
    "sg:address":"Ravenscraig, 6 Barton Avenue",
    "sg:city":"Blackpool",
    "sg:classifiers":[
        {
            "category":"Travel",
            "subcategory":"Hotels & Motels",
            "type":"Entertainment"
        },
        {
            "category":"Bars & Pubs",
            "subcategory":"Hookah Bar",
            "type":"Food & Drink"
        }
    ],
    "sg:phone":"+44 1253 349096",
    "sg:postcode":"FY1 6AP",
    "sg:province":"Lancashire",
    "sg:tags":[
        "self",
        "holiday",
        "catering"
    ],
    "wof:name":"Ravenscraig Holiday Flats",
    "wof:placetype":"venue"
},
  "geometry": {"coordinates":[-3.054213,53.80492],"type":"Point"}
}