{
  "type": "Feature",
  "properties": {
    "addr:full":"1 Cedar Trade Park, Fern Down Industrial Estate Wimborne Dorset BH21 7SD",
    "addr:housenumber":"1",
    "addr:postcode":"bh21 7sd",
    "addr:street":"Cedar Trade Park Fern Down Industrial",
    "iso:country":"GB",
    "sg:address":"1 Cedar Trade Park, Fern Down Industrial Estate",
    "sg:city":"Wimborne",
    "sg:classifiers":[
        {
            "category":"Shopping",
            "subcategory":"Department Store",
            "type":"Retail Goods"
        },
        {
            "category":"Wholesale",
            "subcategory":"Sporting Goods",
            "type":"Manufacturing & Wholesale Goods"
        },
        {
            "category":"Shopping",
            "subcategory":"Computers & Home Electronics",
            "type":"Retail Goods"
        }
    ],
    "sg:phone":"+44 1202 894555",
    "sg:postcode":"BH21 7SD",
    "sg:province":"Dorset",
    "sg:tags":[
        "mnfr",
        "sport",
        "equipment"
    ],
    "wof:name":"T & S International",
    "wof:placetype":"venue"
},
  "geometry": {"coordinates":[-1.988709,50.802235],"type":"Point"}
}