{
  "type": "Feature",
  "properties": {
    "addr:full":"6 Abbey Terrace, Scone Perth Perth and Kinross PH2 6JR",
    "addr:housenumber":"6",
    "addr:postcode":"ph2 6jr",
    "addr:street":"Abbey Terrace",
    "iso:country":"GB",
    "sg:address":"6 Abbey Terrace, Scone",
    "sg:city":"Perth",
    "sg:classifiers":[
        {
            "category":"Retail",
            "subcategory":"Driving School",
            "type":"Services"
        }
    ],
    "sg:postcode":"PH2 6JR",
    "sg:province":"Perth and Kinross",
    "wof:name":"Newscone Driving School",
    "wof:placetype":"venue"
},
  "geometry": {"coordinates":[-3.404346,56.419434],"type":"Point"}
}