{
  "type": "Feature",
  "properties": {
    "addr:full":"27 Cardiff Road, Llandaff Cardiff Cardiff CF5 2DP",
    "addr:housenumber":"27",
    "addr:postcode":"cf5 2dp",
    "addr:street":"Cardiff Road",
    "iso:country":"GB",
    "sg:address":"27 Cardiff Road, Llandaff",
    "sg:city":"Cardiff",
    "sg:classifiers":[
        {
            "category":"Professional",
            "subcategory":"Lawyer & Legal Services",
            "type":"Services"
        }
    ],
    "sg:phone":"+44 29 2056 9108",
    "sg:postcode":"CF5 2DP",
    "sg:province":"Cardiff",
    "sg:tags":[
        "solicitor"
    ],
    "wof:name":"Alun Rees",
    "wof:placetype":"venue"
},
  "geometry": {"coordinates":[-3.221045,51.494846],"type":"Point"}
}