{
  "type": "Feature",
  "properties": {
    "addr:full":"Newfield Farm Stranraer Dumfries and Galloway DG9 8HX",
    "addr:postcode":"dg9 8hx",
    "addr:street":"Stranraer",
    "iso:country":"GB",
    "sg:address":"Newfield Farm",
    "sg:city":"Stranraer",
    "sg:classifiers":[
        {
            "category":"Home & Garden",
            "subcategory":"Garden Supply",
            "type":"Retail Goods"
        },
        {
            "category":"Farming",
            "subcategory":"Farm",
            "type":"Manufacturing & Wholesale Goods"
        }
    ],
    "sg:postcode":"DG9 8HX",
    "sg:province":"Dumfries and Galloway",
    "sg:tags":[
        "mixed",
        "bulb",
        "crop",
        "grower"
    ],
    "wof:name":"R & M Downie",
    "wof:placetype":"venue"
},
  "geometry": {"coordinates":[-5.0164442062,54.9056358337],"type":"Point"}
}