{
  "type": "Feature",
  "properties": {
    "addr:full":"1a Court Street Faversham Kent ME13 7AN",
    "addr:housenumber":"1a",
    "addr:postcode":"me13 7an",
    "addr:street":"Court Street",
    "iso:country":"GB",
    "sg:address":"1a Court Street",
    "sg:city":"Faversham",
    "sg:classifiers":[
        {
            "category":"Communications",
            "type":"Services"
        }
    ],
    "sg:phone":"+44 1795 536624",
    "sg:postcode":"ME13 7AN",
    "sg:province":"Kent",
    "sg:tags":[
        "tv",
        "video",
        "radio"
    ],
    "wof:name":"Legend",
    "wof:placetype":"venue"
},
  "geometry": {"coordinates":[0.891301,51.316063],"type":"Point"}
}