{
  "type": "Feature",
  "properties": {
    "addr:full":"23 Boxhill Road Abingdon Oxfordshire OX14 2ET",
    "addr:housenumber":"23",
    "addr:postcode":"ox14 2et",
    "addr:street":"Boxhill Road",
    "iso:country":"GB",
    "sg:address":"23 Boxhill Road",
    "sg:city":"Abingdon",
    "sg:classifiers":[
        {
            "category":"Building & Trades",
            "subcategory":"Landscaping Services",
            "type":"Services"
        }
    ],
    "sg:postcode":"OX14 2ET",
    "sg:province":"Oxfordshire",
    "sg:tags":[
        "gardening"
    ],
    "wof:name":"Fairacres",
    "wof:placetype":"venue"
},
  "geometry": {"coordinates":[-1.2783039808,51.6771888733],"type":"Point"}
}