{
  "type": "Feature",
  "properties": {
    "addr:full":"35/37 Station Road London Greater London E12 5BP",
    "addr:housenumber":"35 / 37",
    "addr:postcode":"e12 5bp",
    "addr:street":"Station Road",
    "iso:country":"GB",
    "sg:address":"35/37 Station Road",
    "sg:city":"London",
    "sg:classifiers":[
        {
            "category":"Manufacturing",
            "subcategory":"Tools & Machinery",
            "type":"Manufacturing & Wholesale Goods"
        }
    ],
    "sg:postcode":"E12 5BP",
    "sg:province":"Greater London",
    "sg:tags":[
        "society",
        "friendly"
    ],
    "wof:name":"Archer Insurance Services Ltd.",
    "wof:placetype":"venue"
},
  "geometry": {"coordinates":[0.046736,51.551857],"type":"Point"}
}