{
  "type": "Feature",
  "properties": {
    "addr:full":"13 Bar End Road Winchester Hampshire SO23 9NT",
    "addr:housenumber":"13",
    "addr:postcode":"so23 9nt",
    "addr:street":"Bar End Road",
    "iso:country":"GB",
    "sg:address":"13 Bar End Road",
    "sg:city":"Winchester",
    "sg:classifiers":[
        {
            "category":"Organizations",
            "subcategory":"Non-profit Organization",
            "type":"Services"
        }
    ],
    "sg:phone":"+44 1962 869471",
    "sg:postcode":"SO23 9NT",
    "sg:province":"Hampshire",
    "sg:tags":[
        "organisation",
        "voluntary",
        "charity"
    ],
    "wof:name":"United Nations Association",
    "wof:placetype":"venue"
},
  "geometry": {"coordinates":[-1.3066879511,51.056968689],"type":"Point"}
}