{
  "type": "Feature",
  "properties": {
    "iso:country":"GB",
    "sg:address":"1 Hazel Parade, Penrose Road",
    "sg:city":"Leatherhead",
    "sg:classifiers":[
        {
            "category":"Wholesale",
            "subcategory":"Construction Materials",
            "type":"Manufacturing & Wholesale Goods"
        }
    ],
    "sg:phone":"+44 1372 451777",
    "sg:postcode":"KT22 9PY",
    "sg:province":"Surrey",
    "sg:tags":[
        "merchant",
        "glass"
    ],
    "wof:name":"D B Designs Glass Merchants",
    "wof:placetype":"venue"
},
  "geometry": {"coordinates":[-0.329418987,51.2963600159],"type":"Point"}
}