{
  "type": "Feature",
  "properties": {
    "addr:full":"494 Leeds Road, Thackley Bradford West Yorkshire BD10 8JH",
    "addr:housenumber":"494",
    "addr:postcode":"bd10 8jh",
    "addr:street":"Leeds Road",
    "iso:country":"GB",
    "sg:address":"494 Leeds Road, Thackley",
    "sg:city":"Bradford",
    "sg:classifiers":[
        {
            "category":"Manufacturing",
            "subcategory":"Petroleum Products",
            "type":"Manufacturing & Wholesale Goods"
        }
    ],
    "sg:postcode":"BD10 8JH",
    "sg:province":"West Yorkshire",
    "sg:tags":[
        "double",
        "glazing"
    ],
    "wof:name":"Willow Windows",
    "wof:placetype":"venue"
},
  "geometry": {"coordinates":[-1.7339780331,53.8429260254],"type":"Point"}
}