{
  "type": "Feature",
  "properties": {
    "addr:full":"1 Lombard Dr, North Lodge, Chester-le-street Durham DH3 4BE",
    "addr:housenumber":"1",
    "addr:postcode":"dh3 4be",
    "addr:street":"Lombard Dr North Lodge",
    "iso:country":"GB",
    "sg:address":"1 Lombard Dr, North Lodge,",
    "sg:city":"Chester-le-street",
    "sg:classifiers":[
        {
            "category":"Freight",
            "type":"Transportation"
        }
    ],
    "sg:postcode":"DH3 4BE",
    "sg:province":"Durham",
    "sg:tags":[
        "haulage",
        "road"
    ],
    "wof:name":"Cordon,William,",
    "wof:placetype":"venue"
},
  "geometry": {"coordinates":[-1.5734889507,54.8741645813],"type":"Point"}
}