{
  "type": "Feature",
  "properties": {
    "iso:country":"GB",
    "sg:address":"81 Green Lanes",
    "sg:city":"London",
    "sg:classifiers":[
        {
            "category":"Retail",
            "subcategory":"Funeral Services",
            "type":"Services"
        }
    ],
    "sg:phone":"+44 20 7226 1956",
    "sg:postcode":"N16 9BX",
    "sg:province":"Greater London",
    "sg:tags":[
        "director"
    ],
    "wof:name":"Recknell & Foster",
    "wof:placetype":"venue"
},
  "geometry": {"coordinates":[-0.0888080001,51.5539665222],"type":"Point"}
}