{
  "type": "Feature",
  "properties": {
    "addr:full":"109 Ladywell Road, Tunstall Stoke-on-trent Staffordshire ST6 5BP",
    "addr:housenumber":"109",
    "addr:postcode":"staffordshire st6 5bp",
    "addr:street":"Ladywell Road",
    "iso:country":"GB",
    "sg:address":"109 Ladywell Road, Tunstall",
    "sg:city":"Stoke-on-trent",
    "sg:classifiers":[
        {
            "category":"Retail",
            "subcategory":"Auto Repair",
            "type":"Services"
        }
    ],
    "sg:postcode":"ST6 5BP",
    "sg:province":"Staffordshire",
    "sg:tags":[
        "body",
        "car"
    ],
    "wof:name":"Scalise & Sons",
    "wof:placetype":"venue"
},
  "geometry": {"coordinates":[-2.214775,53.058994],"type":"Point"}
}