{
  "type": "Feature",
  "properties": {
    "iso:country":"GB",
    "sg:address":"23 Memorial Road, Worsley",
    "sg:city":"Manchester",
    "sg:classifiers":[
        {
            "category":"Shopping",
            "subcategory":"News",
            "type":"Retail Goods"
        }
    ],
    "sg:phone":"+44 161 790 2964",
    "sg:postcode":"M28 3AG",
    "sg:province":"Greater Manchester",
    "sg:tags":[
        "newsagent"
    ],
    "wof:name":"C K News",
    "wof:placetype":"venue"
},
  "geometry": {"coordinates":[-2.3981039524,53.5220069885],"type":"Point"}
}