{
  "type": "Feature",
  "properties": {
    "addr:full":"Solmere House, Dovecot Hill, South Church Enterprise Park Bishop Auckland Durham DL14 6XR",
    "addr:postcode":"dl14 6xr",
    "addr:street":"Dovecot Hill South;Enterprise Park",
    "iso:country":"GB",
    "sg:address":"Solmere House, Dovecot Hill, South Church Enterprise Park",
    "sg:city":"Bishop Auckland",
    "sg:classifiers":[
        {
            "category":"Wholesale",
            "subcategory":"Home Furnishings",
            "type":"Manufacturing & Wholesale Goods"
        }
    ],
    "sg:phone":"+44 1388 774550",
    "sg:postcode":"DL14 6XR",
    "sg:province":"Durham",
    "sg:tags":[
        "wsale",
        "rug",
        "carpet"
    ],
    "wof:name":"Solmere Ltd.",
    "wof:placetype":"venue"
},
  "geometry": {"coordinates":[-1.673958,54.646873],"type":"Point"}
}