{
  "type": "Feature",
  "properties": {
    "iso:country":"GB",
    "sg:address":"Unit 2, 20 Old Mill Road, Hunton Bridge",
    "sg:city":"King's Langley",
    "sg:classifiers":[
        {
            "category":"Building & Trades",
            "subcategory":"Construction",
            "type":"Services"
        }
    ],
    "sg:phone":"+44 1442 878822",
    "sg:postcode":"WD4 8QT",
    "sg:province":"Hertfordshire",
    "sg:tags":[
        "welder"
    ],
    "wof:name":"Mobiweld (Watford)",
    "wof:placetype":"venue"
},
  "geometry": {"coordinates":[-0.433392,51.689045],"type":"Point"}
}