{
  "type": "Feature",
  "properties": {
    "addr:full":"51 Princes Road, Tividale Smethwick West Midlands B69 2LS",
    "addr:housenumber":"51",
    "addr:postcode":"b69 2ls",
    "addr:street":"Princes Road Tividale Smethwick",
    "iso:country":"GB",
    "sg:address":"51 Princes Road, Tividale",
    "sg:city":"Smethwick",
    "sg:classifiers":[
        {
            "category":"Shopping",
            "subcategory":"Clothing, Apparel, & Fashions",
            "type":"Retail Goods"
        }
    ],
    "sg:phone":"+44 121 520 4855",
    "sg:postcode":"B69 2LS",
    "sg:province":"West Midlands",
    "sg:tags":[
        "dresswear"
    ],
    "wof:name":"Barbara Ann Bridal Hire",
    "wof:placetype":"venue"
},
  "geometry": {"coordinates":[-2.0530591011,52.5133132935],"type":"Point"}
}