{
  "type": "Feature",
  "properties": {
    "addr:full":"6 Front Street, Lanchester Durham Durham DH7 0ER",
    "addr:housenumber":"6",
    "addr:postcode":"dh7 0er",
    "addr:street":"Front Street",
    "iso:country":"GB",
    "sg:address":"6 Front Street, Lanchester",
    "sg:city":"Durham",
    "sg:classifiers":[
        {
            "category":"Food & Beverages",
            "subcategory":"Fruits & Vegetables",
            "type":"Retail Goods"
        }
    ],
    "sg:phone":"+44 1207 521150",
    "sg:postcode":"DH7 0ER",
    "sg:province":"Durham",
    "sg:tags":[
        "greengrocer"
    ],
    "wof:name":"Ray Emmerton",
    "wof:placetype":"venue"
},
  "geometry": {"coordinates":[-1.742922,54.821693],"type":"Point"}
}