{
  "type": "Feature",
  "properties": {
    "addr:full":"5 Brig Square, Freeman Street Wells-next-the-sea Norfolk NR23 1BH",
    "addr:housenumber":"5",
    "addr:postcode":"nr23 1bh",
    "addr:street":"Brig Square Freeman Street",
    "iso:country":"GB",
    "sg:address":"5 Brig Square, Freeman Street",
    "sg:city":"Wells-next-the-sea",
    "sg:classifiers":[
        {
            "category":"Travel",
            "subcategory":"Hotels & Motels",
            "type":"Entertainment"
        }
    ],
    "sg:phone":"+44 1328 710440",
    "sg:postcode":"NR23 1BH",
    "sg:province":"Norfolk",
    "sg:tags":[
        "self",
        "catering"
    ],
    "wof:name":"Brig Square Holiday Cottages",
    "wof:placetype":"venue"
},
  "geometry": {"coordinates":[0.8558099866,52.9526443481],"type":"Point"}
}