{
  "type": "Feature",
  "properties": {
    "iso:country":"GB",
    "sg:address":"Fleet Community Centre, Fleet Way",
    "sg:city":"Peterborough",
    "sg:classifiers":[
        {
            "category":"Social Services",
            "subcategory":"Child Care",
            "type":"Services"
        },
        {
            "category":"Social Services",
            "subcategory":"Adult Care",
            "type":"Services"
        }
    ],
    "sg:phone":"+44 1733 558181",
    "sg:postcode":"PE2 8DL",
    "sg:province":"Cambridgeshire",
    "sg:tags":[
        "childcare",
        "day",
        "centre"
    ],
    "wof:name":"FLETTON DAY CENTRE",
    "wof:placetype":"venue"
},
  "geometry": {"coordinates":[-0.23592,52.556332],"type":"Point"}
}