{
  "type": "Feature",
  "properties": {
    "addr:full":"49 Lower Forster Street Walsall West Midlands WS1 1XB",
    "addr:housenumber":"49",
    "addr:postcode":"ws1 1xb",
    "addr:street":"Lower Forster Street",
    "iso:country":"GB",
    "sg:address":"49 Lower Forster Street",
    "sg:city":"Walsall",
    "sg:classifiers":[
        {
            "category":"Bars & Pubs",
            "type":"Food & Drink"
        }
    ],
    "sg:phone":"+44 1922 629741",
    "sg:postcode":"WS1 1XB",
    "sg:province":"West Midlands",
    "sg:tags":[
        "pubs",
        "inn"
    ],
    "wof:name":"The Fountain Inn",
    "wof:placetype":"venue"
},
  "geometry": {"coordinates":[-1.9773800373,52.5886077881],"type":"Point"}
}