{
  "type": "Feature",
  "properties": {
    "addr:full":"18 Bury St Stowmarket Suffolk IP14 1HH",
    "addr:housenumber":"18",
    "addr:postcode":"ip14 1hh",
    "addr:street":"Bury St",
    "iso:country":"GB",
    "sg:address":"18 Bury St",
    "sg:city":"Stowmarket",
    "sg:classifiers":[
        {
            "category":"Social Services",
            "subcategory":"Retirement Home",
            "type":"Services"
        }
    ],
    "sg:phone":"+44 1449 774041",
    "sg:postcode":"IP14 1HH",
    "sg:province":"Suffolk",
    "sg:tags":[
        "care"
    ],
    "wof:name":"Haven Care",
    "wof:placetype":"venue"
},
  "geometry": {"coordinates":[0.995685,52.188805],"type":"Point"}
}