{
  "type": "Feature",
  "properties": {
    "iso:country":"GB",
    "sg:address":"185 Old Kent Road",
    "sg:city":"London",
    "sg:classifiers":[
        {
            "category":"Travel",
            "subcategory":"Travel Agent",
            "type":"Entertainment"
        }
    ],
    "sg:postcode":"SE1 5NA",
    "sg:province":"Greater London",
    "wof:name":"Distinctive Travel Ltd.",
    "wof:placetype":"venue"
},
  "geometry": {"coordinates":[-0.081454,51.491253],"type":"Point"}
}