{
  "type": "Feature",
  "properties": {
    "addr:full":"5 St Georges Crt Dairyhouse Lane, Broadheath Altrincham Cheshire WA14 5UA",
    "addr:housenumber":"5",
    "addr:postcode":"wa14 5ua",
    "addr:street":"St;Crt Dairyhouse Lane",
    "iso:country":"GB",
    "sg:address":"5 St Georges Crt Dairyhouse Lane, Broadheath",
    "sg:city":"Altrincham",
    "sg:classifiers":[
        {
            "category":"Wholesale",
            "subcategory":"Farm Supplies",
            "type":"Manufacturing & Wholesale Goods"
        }
    ],
    "sg:phone":"+44 161 942 4444",
    "sg:postcode":"WA14 5UA",
    "sg:province":"Cheshire",
    "sg:tags":[
        "merchant",
        "grain"
    ],
    "wof:name":"Matrix Europe Ltd.",
    "wof:placetype":"venue"
},
  "geometry": {"coordinates":[-2.3525509834,53.400390625],"type":"Point"}
}