{
  "type": "Feature",
  "properties": {
    "addr:full":"Baydon Road, Wickham Newbury Berkshire RG20 8HH",
    "addr:postcode":"rg20 8hh",
    "addr:street":"Baydon Road",
    "iso:country":"GB",
    "sg:address":"Baydon Road, Wickham",
    "sg:city":"Newbury",
    "sg:classifiers":[
        {
            "category":"Bars & Pubs",
            "type":"Food & Drink"
        }
    ],
    "sg:postcode":"RG20 8HH",
    "sg:province":"Berkshire",
    "sg:tags":[
        "pubs",
        "inn"
    ],
    "wof:name":"The Five Bells At Wickham",
    "wof:placetype":"venue"
},
  "geometry": {"coordinates":[-1.429163,51.442619],"type":"Point"}
}