{
  "type": "Feature",
  "properties": {
    "addr:full":"932 Ecclesall Rd Sheffield Derbyshire S11 8TR",
    "addr:housenumber":"932",
    "addr:postcode":"s11 8tr",
    "addr:street":"Ecclesall Rd",
    "iso:country":"GB",
    "sg:address":"932 Ecclesall Rd",
    "sg:city":"Sheffield",
    "sg:classifiers":[
        {
            "category":"Deli",
            "type":"Food & Drink"
        }
    ],
    "sg:phone":"+44 114 266 0601",
    "sg:postcode":"S11 8TR",
    "sg:province":"Derbyshire",
    "sg:tags":[
        "delicatessen"
    ],
    "wof:name":"M Stringer & Son",
    "wof:placetype":"venue"
},
  "geometry": {"coordinates":[-1.5085029602,53.3616828918],"type":"Point"}
}