{
  "type": "Feature",
  "properties": {
    "iso:country":"GB",
    "sg:address":"Unit 6",
    "sg:city":"Woking",
    "sg:classifiers":[
        {
            "category":"Wholesale",
            "subcategory":"Machinery & Supplies",
            "type":"Manufacturing & Wholesale Goods"
        }
    ],
    "sg:postcode":"GU21 5EN",
    "sg:province":"Surrey",
    "sg:tags":[
        "theatrical"
    ],
    "wof:name":"Storm Lighting Ltd.",
    "wof:placetype":"venue"
},
  "geometry": {"coordinates":[-0.535919,51.32811],"type":"Point"}
}