{
  "type": "Feature",
  "properties": {
    "addr:full":"Chapman House, 10 The Village, Blackheath London Greater London SE3 9LE",
    "addr:housenumber":"10",
    "addr:postcode":"se3 9le",
    "addr:street":"The Village",
    "iso:country":"GB",
    "sg:address":"Chapman House, 10 The Village, Blackheath",
    "sg:city":"London",
    "sg:classifiers":[
        {
            "category":"Real Estate",
            "subcategory":"Real Estate Agent",
            "type":"Services"
        }
    ],
    "sg:phone":"+44 20 8297 1210",
    "sg:postcode":"SE3 9LE",
    "sg:province":"Greater London",
    "wof:name":"Blackheath Cator Estate Residents Ltd.",
    "wof:placetype":"venue"
},
  "geometry": {"coordinates":[0.0365419984,51.4816207886],"type":"Point"}
}