{
  "type": "Feature",
  "properties": {
    "addr:full":"Goods Farm, Dover Street, Stour Row Shaftesbury Dorset SP7 0QH",
    "addr:postcode":"sp7 0qh",
    "addr:street":"Dover Street",
    "iso:country":"GB",
    "sg:address":"Goods Farm, Dover Street, Stour Row",
    "sg:city":"Shaftesbury",
    "sg:classifiers":[
        {
            "category":"Farming",
            "subcategory":"Livestock Farm",
            "type":"Manufacturing & Wholesale Goods"
        }
    ],
    "sg:phone":"+44 1747 838565",
    "sg:postcode":"SP7 0QH",
    "sg:province":"Dorset",
    "sg:tags":[
        "others"
    ],
    "wof:name":"G I & S Ralph & Son",
    "wof:placetype":"venue"
},
  "geometry": {"coordinates":[-2.2544538975,50.9891738892],"type":"Point"}
}