{
  "type": "Feature",
  "properties": {
    "addr:full":"Meridian House, 41 Eastgate Louth Lincolnshire LN11 9NH",
    "addr:housenumber":"41",
    "addr:postcode":"ln11 9nh",
    "addr:street":"Eastgate Louth",
    "iso:country":"GB",
    "sg:address":"Meridian House, 41 Eastgate",
    "sg:city":"Louth",
    "sg:classifiers":[
        {
            "category":"Utilities",
            "type":"Services"
        }
    ],
    "sg:phone":"+44 1507 607607",
    "sg:postcode":"LN11 9NH",
    "sg:province":"Lincolnshire",
    "sg:tags":[
        "internet"
    ],
    "wof:name":"Lincolnshire Regional Access Centres",
    "wof:placetype":"venue"
},
  "geometry": {"coordinates":[-0.005176,53.367107],"type":"Point"}
}