{
  "type": "Feature",
  "properties": {
    "addr:full":"8 West Precinct Billingham Durham TS23 2NH",
    "addr:housenumber":"8",
    "addr:postcode":"ts23 2nh",
    "addr:street":"Billingham",
    "iso:country":"GB",
    "sg:address":"8 West Precinct",
    "sg:city":"Billingham",
    "sg:classifiers":[
        {
            "category":"Organizations",
            "subcategory":"Non-profit Organization",
            "type":"Services"
        }
    ],
    "sg:phone":"+44 1642 365400",
    "sg:postcode":"TS23 2NH",
    "sg:province":"Durham",
    "sg:tags":[
        "organisation",
        "voluntary",
        "charity"
    ],
    "wof:name":"British Red Cross",
    "wof:placetype":"venue"
},
  "geometry": {"coordinates":[-1.2938640118,54.6080284119],"type":"Point"}
}