{
  "type": "Feature",
  "properties": {
    "addr:full":"Cold Harbour Works, Gryers Hill High Wycombe Buckinghamshire HP15 6LU",
    "addr:postcode":"hp15 6lu",
    "addr:street":"Cold Harbour;Gryers Hill",
    "iso:country":"GB",
    "sg:address":"Cold Harbour Works, Gryers Hill",
    "sg:city":"High Wycombe",
    "sg:classifiers":[
        {
            "category":"Real Estate",
            "subcategory":"Architect",
            "type":"Services"
        }
    ],
    "sg:phone":"+44 1494 716345",
    "sg:postcode":"HP15 6LU",
    "sg:province":"Buckinghamshire",
    "sg:tags":[
        "architectural"
    ],
    "wof:name":"M J Joiner Enterprises Ltd.",
    "wof:placetype":"venue"
},
  "geometry": {"coordinates":[-0.74052,51.667671],"type":"Point"}
}