{
  "type": "Feature",
  "properties": {
    "iso:country":"GB",
    "sg:address":"Skipton Road, Foulridge",
    "sg:city":"Colne",
    "sg:classifiers":[
        {
            "category":"Food & Beverages",
            "subcategory":"Fruits & Vegetables",
            "type":"Retail Goods"
        }
    ],
    "sg:postcode":"BB8 7PQ",
    "sg:province":"Lancashire",
    "sg:tags":[
        "greengrocer"
    ],
    "wof:name":"Anne Poole",
    "wof:placetype":"venue"
},
  "geometry": {"coordinates":[-2.168396,53.877003],"type":"Point"}
}