{
  "type": "Feature",
  "properties": {
    "iso:country":"GB",
    "sg:address":"Queensmead, High Street",
    "sg:city":"Brockenhurst",
    "sg:classifiers":[
        {
            "category":"Restaurant",
            "type":"Food & Drink"
        }
    ],
    "sg:phone":"+44 1590 612777",
    "sg:postcode":"SO42 7YA",
    "sg:province":"Hampshire",
    "wof:name":"The Old Bake House",
    "wof:placetype":"venue"
},
  "geometry": {"coordinates":[-1.5720039606,50.8186416626],"type":"Point"}
}