{
  "type": "Feature",
  "properties": {
    "iso:country":"GB",
    "sg:address":"18 Brook Farm Road",
    "sg:city":"Cobham",
    "sg:classifiers":[
        {
            "category":"Professional",
            "subcategory":"Accounting & Tax Preparation",
            "type":"Services"
        }
    ],
    "sg:phone":"+44 1932 866359",
    "sg:postcode":"KT11 3AX",
    "sg:province":"Surrey",
    "sg:tags":[
        "accountant"
    ],
    "wof:name":"Scholey Consultancy",
    "wof:placetype":"venue"
},
  "geometry": {"coordinates":[-0.395684,51.325619],"type":"Point"}
}