{
  "type": "Feature",
  "properties": {
    "addr:full":"13 Crown St Ayr South Ayrshire KA8 8AG",
    "addr:housenumber":"13",
    "addr:postcode":"ka8 8ag",
    "addr:street":"Crown St",
    "iso:country":"GB",
    "sg:address":"13 Crown St",
    "sg:city":"Ayr",
    "sg:classifiers":[
        {
            "category":"Building & Trades",
            "subcategory":"Construction",
            "type":"Services"
        }
    ],
    "sg:postcode":"KA8 8AG",
    "sg:province":"South Ayrshire",
    "sg:tags":[
        "builder"
    ],
    "wof:name":"Smith,Robin,",
    "wof:placetype":"venue"
},
  "geometry": {"coordinates":[-4.633518219,55.4682846069],"type":"Point"}
}