{
  "type": "Feature",
  "properties": {
    "iso:country":"GB",
    "sg:address":"Bedgrove County Junior School, Ingram Avenue",
    "sg:city":"Aylesbury",
    "sg:classifiers":[
        {
            "category":"Farming",
            "subcategory":"Nursery",
            "type":"Manufacturing & Wholesale Goods"
        }
    ],
    "sg:phone":"+44 1296 399661",
    "sg:postcode":"HP21 9DN",
    "sg:province":"Buckinghamshire",
    "sg:tags":[
        "creche"
    ],
    "wof:name":"Bright Start Day Nursery",
    "wof:placetype":"venue"
},
  "geometry": {"coordinates":[-0.7785000205,51.8052787781],"type":"Point"}
}