{
  "type": "Feature",
  "properties": {
    "addr:full":"4 Northcroft Drive Hull East Riding of Yorkshire HU8 9UL",
    "addr:housenumber":"4",
    "addr:postcode":"hu8 9ul",
    "addr:street":"Northcroft Drive",
    "iso:country":"GB",
    "sg:address":"4 Northcroft Drive",
    "sg:city":"Hull",
    "sg:classifiers":[
        {
            "category":"Home & Garden",
            "subcategory":"Household Appliances",
            "type":"Retail Goods"
        }
    ],
    "sg:phone":"+44 1482 711785",
    "sg:postcode":"HU8 9UL",
    "sg:province":"East Riding of Yorkshire",
    "sg:tags":[
        "gas"
    ],
    "wof:name":"Warm Air Replacements & Services",
    "wof:placetype":"venue"
},
  "geometry": {"coordinates":[-0.298591,53.782928],"type":"Point"}
}