{
  "type": "Feature",
  "properties": {
    "addr:full":"437 High St North London Greater London E12 6TJ",
    "addr:housenumber":"437",
    "addr:postcode":"e12 6tj",
    "addr:street":"High St North",
    "iso:country":"GB",
    "sg:address":"437 High St North",
    "sg:city":"London",
    "sg:classifiers":[
        {
            "category":"Shopping",
            "subcategory":"News",
            "type":"Retail Goods"
        }
    ],
    "sg:phone":"+44 20 8472 2768",
    "sg:postcode":"E12 6TJ",
    "sg:province":"Greater London",
    "sg:tags":[
        "newsagent"
    ],
    "wof:name":"J & R News",
    "wof:placetype":"venue"
},
  "geometry": {"coordinates":[0.0485059991,51.5469360352],"type":"Point"}
}