{
  "type": "Feature",
  "properties": {
    "addr:full":"Vickers House, Priestley Road Basingstoke Hampshire RG24 9RA",
    "addr:postcode":"rg24 9ra",
    "addr:street":"Priestley Road",
    "iso:country":"GB",
    "sg:address":"Vickers House, Priestley Road",
    "sg:city":"Basingstoke",
    "sg:classifiers":[
        {
            "category":"Communications",
            "type":"Services"
        }
    ],
    "sg:phone":"+44 1635 291890",
    "sg:postcode":"RG24 9RA",
    "sg:province":"Hampshire",
    "sg:tags":[
        "audio-visual"
    ],
    "wof:name":"Harrison Ford",
    "wof:placetype":"venue"
},
  "geometry": {"coordinates":[-1.1055459976,51.2773551941],"type":"Point"}
}