{
  "type": "Feature",
  "properties": {
    "addr:full":"54 West Cliff Preston Lancashire PR1 8HU",
    "addr:housenumber":"54",
    "addr:postcode":"pr1 8hu",
    "addr:street":"West Cliff",
    "iso:country":"GB",
    "sg:address":"54 West Cliff",
    "sg:city":"Preston",
    "sg:classifiers":[
        {
            "category":"Real Estate",
            "subcategory":"Architect",
            "type":"Services"
        }
    ],
    "sg:phone":"+44 1772 881992",
    "sg:postcode":"PR1 8HU",
    "sg:province":"Lancashire",
    "wof:name":"Wilson Mason & Partners",
    "wof:placetype":"venue"
},
  "geometry": {"coordinates":[-2.709127,53.753273],"type":"Point"}
}