{
  "type": "Feature",
  "properties": {
    "iso:country":"GB",
    "sg:address":"Cressey Holme Farm, Bullpit Lane",
    "sg:city":"Newark",
    "sg:classifiers":[
        {
            "category":"Manufacturing",
            "subcategory":"Wood Products",
            "type":"Manufacturing & Wholesale Goods"
        },
        {
            "category":"Home & Garden",
            "subcategory":"Furniture",
            "type":"Retail Goods"
        }
    ],
    "sg:phone":"+44 1636 702284",
    "sg:postcode":"NG24 3LZ",
    "sg:province":"Nottinghamshire",
    "sg:tags":[
        "maker",
        "cabinet"
    ],
    "wof:name":"Cressey Holme Pine Furniture",
    "wof:placetype":"venue"
},
  "geometry": {"coordinates":[-0.809347,53.073895],"type":"Point"}
}