{
  "type": "Feature",
  "properties": {
    "addr:full":"West Ash Farm, Bradworthy Holsworthy Cornwall EX22 7SN",
    "addr:postcode":"ex22 7sn",
    "addr:street":"West Ash",
    "iso:country":"GB",
    "sg:address":"West Ash Farm, Bradworthy",
    "sg:city":"Holsworthy",
    "sg:classifiers":[
        {
            "category":"Farming",
            "subcategory":"Farm",
            "type":"Manufacturing & Wholesale Goods"
        }
    ],
    "sg:phone":"+44 1409 241242",
    "sg:postcode":"EX22 7SN",
    "sg:province":"Cornwall",
    "sg:tags":[
        "mixed",
        "crop"
    ],
    "wof:name":"H M BOND",
    "wof:placetype":"venue"
},
  "geometry": {"coordinates":[-4.386544,50.898212],"type":"Point"}
}