{
  "type": "Feature",
  "properties": {
    "addr:full":"17 Compton Terrace Islington Greater London N1 2UN",
    "addr:housenumber":"17",
    "addr:postcode":"n1 2un",
    "addr:street":"Compton Terrace",
    "iso:country":"GB",
    "sg:address":"17 Compton Terrace",
    "sg:city":"Islington",
    "sg:classifiers":[
        {
            "category":"Professional",
            "subcategory":"Accounting & Tax Preparation",
            "type":"Services"
        }
    ],
    "sg:phone":"+44 20 7359 6363",
    "sg:postcode":"N1 2UN",
    "sg:province":"Greater London",
    "sg:tags":[
        "accountant"
    ],
    "wof:name":"C A S Hewlett",
    "wof:placetype":"venue"
},
  "geometry": {"coordinates":[-0.1026690006,51.5444984436],"type":"Point"}
}