{
  "type": "Feature",
  "properties": {
    "iso:country":"GB",
    "sg:address":"37 Ranelagh Street",
    "sg:city":"Liverpool",
    "sg:classifiers":[
        {
            "category":"Shopping",
            "subcategory":"Discount & Variety Stores",
            "type":"Retail Goods"
        }
    ],
    "sg:postcode":"L1 1JP",
    "sg:province":"Merseyside",
    "sg:tags":[
        "rental",
        "menswear"
    ],
    "wof:name":"Youngs Retail Hire",
    "wof:placetype":"venue"
},
  "geometry": {"coordinates":[-2.9796910286,53.4051475525],"type":"Point"}
}