{
  "type": "Feature",
  "properties": {
    "addr:full":"Hartley Av Mill Hill Greater London NW7 2HX",
    "addr:postcode":"nw7 2hx",
    "addr:street":"Av Mill Hill",
    "iso:country":"GB",
    "sg:address":"Hartley Av",
    "sg:city":"Mill Hill",
    "sg:classifiers":[
        {
            "category":"Health Services",
            "subcategory":"Doctor",
            "type":"Services"
        }
    ],
    "sg:phone":"+44 20 8959 0888",
    "sg:postcode":"NW7 2HX",
    "sg:province":"Greater London",
    "sg:tags":[
        "practitioners"
    ],
    "wof:name":"Figa, S A",
    "wof:placetype":"venue"
},
  "geometry": {"coordinates":[-0.243983,51.615322],"type":"Point"}
}