{
  "type": "Feature",
  "properties": {
    "addr:full":"131 Masons Hill Bromley Kent BR2 9HT",
    "addr:housenumber":"131",
    "addr:postcode":"br2 9ht",
    "addr:street":"Masons Hill",
    "iso:country":"GB",
    "sg:address":"131 Masons Hill",
    "sg:city":"Bromley",
    "sg:classifiers":[
        {
            "category":"Retail",
            "subcategory":"Auto Rental",
            "type":"Services"
        }
    ],
    "sg:postcode":"BR2 9HT",
    "sg:province":"Kent",
    "sg:tags":[
        "car"
    ],
    "wof:name":"U-Rent",
    "wof:placetype":"venue"
},
  "geometry": {"coordinates":[0.023861,51.396763],"type":"Point"}
}