{
  "type": "Feature",
  "properties": {
    "addr:full":"20 Horbury Road Ossett West Yorkshire WF5 0BN",
    "addr:housenumber":"20",
    "addr:postcode":"wf5 0bn",
    "addr:street":"Horbury Road",
    "iso:country":"GB",
    "sg:address":"20 Horbury Road",
    "sg:city":"Ossett",
    "sg:classifiers":[
        {
            "category":"Travel",
            "subcategory":"Hotels & Motels",
            "type":"Entertainment"
        }
    ],
    "sg:phone":"+44 1924 272495",
    "sg:postcode":"WF5 0BN",
    "sg:province":"West Yorkshire",
    "wof:name":"The Crown Hotel",
    "wof:placetype":"venue"
},
  "geometry": {"coordinates":[-1.573743,53.670406],"type":"Point"}
}