{
  "type": "Feature",
  "properties": {
    "iso:country":"GB",
    "sg:address":"Mathesons Gardens",
    "sg:city":"Morpeth",
    "sg:classifiers":[
        {
            "category":"Health Services",
            "subcategory":"Nursing And Care Facility",
            "type":"Services"
        }
    ],
    "sg:phone":"+44 1670 517722",
    "sg:postcode":"NE61 1ET",
    "sg:province":"Northumberland",
    "sg:tags":[
        "home"
    ],
    "wof:name":"Anchor Trust",
    "wof:placetype":"venue"
},
  "geometry": {"coordinates":[-1.692609,55.165489],"type":"Point"}
}