{
  "type": "Feature",
  "properties": {
    "addr:full":"22 High Street, St Peters Broadstairs Kent CT10 2TQ",
    "addr:housenumber":"22",
    "addr:postcode":"ct10 2tq",
    "addr:street":"High Street",
    "iso:country":"GB",
    "sg:address":"22 High Street, St Peters",
    "sg:city":"Broadstairs",
    "sg:classifiers":[
        {
            "category":"Building & Trades",
            "subcategory":"Construction",
            "type":"Services"
        }
    ],
    "sg:postcode":"CT10 2TQ",
    "sg:province":"Kent",
    "sg:tags":[
        "builder"
    ],
    "wof:name":"B R Turrell",
    "wof:placetype":"venue"
},
  "geometry": {"coordinates":[1.420075,51.364674],"type":"Point"}
}