{
  "type": "Feature",
  "properties": {
    "addr:full":"Wilthorpe Road Barnsley South Yorkshire S75 1JF",
    "addr:postcode":"s75 1jf",
    "addr:street":"Wilthorpe Road;Yorkshire",
    "iso:country":"GB",
    "sg:address":"Wilthorpe Road",
    "sg:city":"Barnsley",
    "sg:classifiers":[
        {
            "category":"Professional",
            "subcategory":"Printing & Photocopies",
            "type":"Services"
        }
    ],
    "sg:postcode":"S75 1JF",
    "sg:province":"South Yorkshire",
    "sg:tags":[
        "process",
        "screen",
        "printer"
    ],
    "wof:name":"Anglo Norse",
    "wof:placetype":"venue"
},
  "geometry": {"coordinates":[-1.5046030283,53.5661621094],"type":"Point"}
}