{
  "type": "Feature",
  "properties": {
    "iso:country":"GB",
    "sg:address":"Edisford Road, Waddington",
    "sg:city":"Clitheroe",
    "sg:classifiers":[
        {
            "category":"Bars & Pubs",
            "type":"Food & Drink"
        }
    ],
    "sg:phone":"+44 1200 428705",
    "sg:postcode":"BB7 3HU",
    "sg:province":"Lancashire",
    "sg:tags":[
        "pubs",
        "inn"
    ],
    "wof:name":"J Brown",
    "wof:placetype":"venue"
},
  "geometry": {"coordinates":[-2.413391,53.889187],"type":"Point"}
}