{
  "type": "Feature",
  "properties": {
    "addr:full":"155 Thornbury Road, Osterley Isleworth Greater London TW7 4QG",
    "addr:housenumber":"155",
    "addr:postcode":"tw7 4qg",
    "addr:street":"Thornbury Road",
    "iso:country":"GB",
    "sg:address":"155 Thornbury Road, Osterley",
    "sg:city":"Isleworth",
    "sg:classifiers":[
        {
            "category":"Food & Beverages",
            "subcategory":"Liquor & Beverages",
            "type":"Retail Goods"
        }
    ],
    "sg:phone":"+44 20 8560 3344",
    "sg:postcode":"TW7 4QG",
    "sg:province":"Greater London",
    "sg:tags":[
        "beer",
        "spirit",
        "wines"
    ],
    "wof:name":"Unwins Wine Merchants",
    "wof:placetype":"venue"
},
  "geometry": {"coordinates":[-0.348038,51.483471],"type":"Point"}
}