{
  "type": "Feature",
  "properties": {
    "addr:full":"Emergencies After Hours, 9 Haywards Close New Romney Kent TN28 8LA",
    "addr:housenumber":"9",
    "addr:postcode":"tn28 8la",
    "addr:street":"Haywards Close",
    "iso:country":"GB",
    "sg:address":"Emergencies After Hours, 9 Haywards Close",
    "sg:city":"New Romney",
    "sg:classifiers":[
        {
            "category":"Organizations",
            "subcategory":"Non-profit Organization",
            "type":"Services"
        }
    ],
    "sg:phone":"+44 1797 366360",
    "sg:postcode":"TN28 8LA",
    "sg:province":"Kent",
    "sg:tags":[
        "organisation",
        "voluntary",
        "charity"
    ],
    "wof:name":"British Red Cross",
    "wof:placetype":"venue"
},
  "geometry": {"coordinates":[0.94648,50.986767],"type":"Point"}
}