{
  "type": "Feature",
  "properties": {
    "iso:country":"GB",
    "sg:address":"Drapers House, 71 Connaught Avenue",
    "sg:city":"Frinton-on-sea",
    "sg:classifiers":[
        {
            "category":"Shopping",
            "subcategory":"Crafts & Fabrics",
            "type":"Retail Goods"
        }
    ],
    "sg:phone":"+44 1255 674456",
    "sg:postcode":"CO13 9PP",
    "sg:province":"Essex",
    "sg:tags":[
        "shop"
    ],
    "wof:name":"Branch",
    "wof:placetype":"venue"
},
  "geometry": {"coordinates":[1.2452470064,51.8317565918],"type":"Point"}
}