{
  "type": "Feature",
  "properties": {
    "iso:country":"GB",
    "sg:address":"Samson Close, Killingworth",
    "sg:city":"Newcastle-upon-tyne",
    "sg:classifiers":[
        {
            "category":"Manufacturing",
            "subcategory":"Petroleum Products",
            "type":"Manufacturing & Wholesale Goods"
        },
        {
            "category":"Wholesale",
            "subcategory":"Petroleum",
            "type":"Manufacturing & Wholesale Goods"
        }
    ],
    "sg:phone":"+44 191 268 4555",
    "sg:postcode":"NE12 6DZ",
    "sg:province":"Tyne and Wear",
    "sg:tags":[
        "fuel",
        "lubricant",
        "distributor",
        "oil"
    ],
    "wof:name":"Revol Ltd",
    "wof:placetype":"venue"
},
  "geometry": {"coordinates":[-1.569304,55.036621],"type":"Point"}
}