{
  "type": "Feature",
  "properties": {
    "iso:country":"GB",
    "sg:address":"Woodlands, 31 Preston Road, Copphull",
    "sg:city":"Chorley",
    "sg:classifiers":[
        {
            "category":"Freight",
            "type":"Transportation"
        }
    ],
    "sg:phone":"+44 1257 792536",
    "sg:postcode":"PR7 5HS",
    "sg:province":"Lancashire",
    "sg:tags":[
        "haulage",
        "road"
    ],
    "wof:name":"M C & M A Stewart (Haulage) Ltd.",
    "wof:placetype":"venue"
},
  "geometry": {"coordinates":[-2.632134,53.652088],"type":"Point"}
}