{
  "type": "Feature",
  "properties": {
    "iso:country":"GB",
    "sg:address":"Marchwood Ho, 934-974 St Albans Rd",
    "sg:city":"Watford",
    "sg:classifiers":[
        {
            "category":"Bus Charters",
            "type":"Transportation"
        }
    ],
    "sg:phone":"+44 1923 673121",
    "sg:postcode":"WD2 6NN",
    "sg:province":"Hertfordshire",
    "sg:tags":[
        "coach"
    ],
    "wof:name":"Shires Network The",
    "wof:placetype":"venue"
},
  "geometry": {"coordinates":[-0.39072,51.652119],"type":"Point"}
}