{
  "type": "Feature",
  "properties": {
    "addr:full":"41c Holland Rd London Greater London W14 8HJ",
    "addr:housenumber":"41c",
    "addr:postcode":"w14 8hj",
    "addr:street":"Holland Rd",
    "iso:country":"GB",
    "sg:address":"41c Holland Rd",
    "sg:city":"London",
    "sg:classifiers":[
        {
            "category":"Farming",
            "subcategory":"Nursery",
            "type":"Manufacturing & Wholesale Goods"
        }
    ],
    "sg:postcode":"W14 8HJ",
    "sg:province":"Greater London",
    "sg:tags":[
        "creche"
    ],
    "wof:name":"Clancy,Bernadette,",
    "wof:placetype":"venue"
},
  "geometry": {"coordinates":[-0.207769,51.497803],"type":"Point"}
}