{
  "type": "Feature",
  "properties": {
    "iso:country":"GB",
    "sg:address":"Hallworthy Stockyard, Hallworthy",
    "sg:city":"Camelford",
    "sg:classifiers":[
        {
            "category":"Food & Beverages",
            "subcategory":"Farmers Market",
            "type":"Retail Goods"
        }
    ],
    "sg:postcode":"PL32 9SH",
    "sg:province":"Cornwall",
    "sg:tags":[
        "livestock"
    ],
    "wof:name":"K V N Stockdale Ltd.",
    "wof:placetype":"venue"
},
  "geometry": {"coordinates":[-4.678636,50.623116],"type":"Point"}
}