{
  "type": "Feature",
  "properties": {
    "iso:country":"GB",
    "sg:address":"29 Downs Road",
    "sg:city":"Luton",
    "sg:classifiers":[
        {
            "category":"Professional",
            "type":"Services"
        }
    ],
    "sg:phone":"+44 1582 458042",
    "sg:postcode":"LU1 1QP",
    "sg:province":"Bedfordshire",
    "sg:tags":[
        "entertainer"
    ],
    "wof:name":"'Appy Clowns",
    "wof:placetype":"venue"
},
  "geometry": {"coordinates":[-0.4285430014,51.8784751892],"type":"Point"}
}