{
  "type": "Feature",
  "properties": {
    "iso:country":"GB",
    "sg:address":"Unit 12 Saxon Way Trading Estate, Saxon Way, Harmondsworth",
    "sg:city":"West Drayton",
    "sg:classifiers":[
        {
            "category":"Freight",
            "type":"Transportation"
        }
    ],
    "sg:phone":"+44 20 8564 7635",
    "sg:postcode":"UB7 0LW",
    "sg:province":"Greater London",
    "sg:tags":[
        "haulage",
        "road"
    ],
    "wof:name":"Electronic Handling Ltd.",
    "wof:placetype":"venue"
},
  "geometry": {"coordinates":[-0.485009,51.49054],"type":"Point"}
}