{
  "type": "Feature",
  "properties": {
    "addr:full":"Batley High School, Field Hill Batley West Yorkshire WF17 0BJ",
    "addr:postcode":"wf17 0bj",
    "addr:street":"Field Hill",
    "iso:country":"GB",
    "sg:address":"Batley High School, Field Hill",
    "sg:city":"Batley",
    "sg:classifiers":[
        {
            "category":"Government",
            "subcategory":"Office",
            "type":"Public Place"
        }
    ],
    "sg:phone":"+44 1924 326328",
    "sg:postcode":"WF17 0BJ",
    "sg:province":"West Yorkshire",
    "sg:tags":[
        "education",
        "agency",
        "authority"
    ],
    "wof:name":"Compact Education Business Services",
    "wof:placetype":"venue"
},
  "geometry": {"coordinates":[-1.631819,53.719818],"type":"Point"}
}