{
  "type": "Feature",
  "properties": {
    "addr:full":"38 Gloucester Road, Wheatley Doncaster South Yorkshire DN2 4JQ",
    "addr:housenumber":"38",
    "addr:postcode":"dn2 4jq",
    "addr:street":"Gloucester Road",
    "iso:country":"GB",
    "sg:address":"38 Gloucester Road, Wheatley",
    "sg:city":"Doncaster",
    "sg:classifiers":[
        {
            "category":"Building & Trades",
            "subcategory":"Construction",
            "type":"Services"
        }
    ],
    "sg:phone":"+44 1302 817416",
    "sg:postcode":"DN2 4JQ",
    "sg:province":"South Yorkshire",
    "sg:tags":[
        "joiner",
        "carpenter"
    ],
    "wof:name":"S C Joinery",
    "wof:placetype":"venue"
},
  "geometry": {"coordinates":[-1.1095739603,53.5340156555],"type":"Point"}
}