{
  "type": "Feature",
  "properties": {
    "addr:full":"Lynden Way, The Square Beaminster Dorset DT8 3AS",
    "addr:postcode":"dt8 3as",
    "addr:street":"Lynden Way The Square",
    "iso:country":"GB",
    "sg:address":"Lynden Way, The Square",
    "sg:city":"Beaminster",
    "sg:classifiers":[
        {
            "category":"Professional",
            "type":"Services"
        }
    ],
    "sg:phone":"+44 1308 863437",
    "sg:postcode":"DT8 3AS",
    "sg:province":"Dorset",
    "sg:tags":[
        "interior",
        "furnishers",
        "designer"
    ],
    "wof:name":"Minster Joinery",
    "wof:placetype":"venue"
},
  "geometry": {"coordinates":[-2.7388939857,50.8090057373],"type":"Point"}
}