{
  "type": "Feature",
  "properties": {
    "addr:full":"Cleave Farm Bideford Devon EX39 4QX",
    "addr:housenumber":"bideford",
    "addr:postcode":"ex39 4qx",
    "addr:street":"Devon",
    "iso:country":"GB",
    "sg:address":"Cleave Farm",
    "sg:city":"Bideford",
    "sg:classifiers":[
        {
            "category":"Farming",
            "subcategory":"Dairy Farm",
            "type":"Manufacturing & Wholesale Goods"
        }
    ],
    "sg:phone":"+44 1805 623671",
    "sg:postcode":"EX39 4QX",
    "sg:province":"Devon",
    "wof:name":"David & Elizabeth Moore",
    "wof:placetype":"venue"
},
  "geometry": {"coordinates":[-4.181339,51.033211],"type":"Point"}
}