{
  "type": "Feature",
  "properties": {
    "addr:full":"129 Airport Road Bristol City of Bristol BS14 9TD",
    "addr:housenumber":"129",
    "addr:postcode":"bs14 9td",
    "addr:street":"Airport Road",
    "iso:country":"GB",
    "sg:address":"129 Airport Road",
    "sg:city":"Bristol",
    "sg:classifiers":[
        {
            "category":"Building & Trades",
            "subcategory":"Construction",
            "type":"Services"
        }
    ],
    "sg:postcode":"BS14 9TD",
    "sg:province":"City of Bristol",
    "sg:tags":[
        "builder"
    ],
    "wof:name":"J R Builders",
    "wof:placetype":"venue"
},
  "geometry": {"coordinates":[-2.5703299046,51.4262313843],"type":"Point"}
}