{
  "type": "Feature",
  "properties": {
    "addr:full":"42 Bridlesmith Gate Nottingham Nottinghamshire NG1 2GQ",
    "addr:housenumber":"42",
    "addr:postcode":"ng1 2gq",
    "addr:street":"Bridlesmith Gate",
    "iso:country":"GB",
    "sg:address":"42 Bridlesmith Gate",
    "sg:city":"Nottingham",
    "sg:classifiers":[
        {
            "category":"Professional",
            "subcategory":"Art Services",
            "type":"Services"
        }
    ],
    "sg:phone":"+44 115 948 1615",
    "sg:postcode":"NG1 2GQ",
    "sg:province":"Nottinghamshire",
    "sg:tags":[
        "picture",
        "restoration"
    ],
    "wof:name":"Elliotts",
    "wof:placetype":"venue"
},
  "geometry": {"coordinates":[-1.147323966,52.9529266357],"type":"Point"}
}