{
  "type": "Feature",
  "properties": {
    "iso:country":"GB",
    "sg:address":"Unit 2 Station Approach",
    "sg:city":"Bicester",
    "sg:classifiers":[
        {
            "category":"Professional",
            "subcategory":"Computer Services",
            "type":"Services"
        }
    ],
    "sg:phone":"+44 1869 253555",
    "sg:postcode":"OX6 7BZ",
    "sg:province":"Oxfordshire",
    "sg:tags":[
        "system",
        "software"
    ],
    "wof:name":"Cyberdesk",
    "wof:placetype":"venue"
},
  "geometry": {"coordinates":[-1.1491910219,51.8930702209],"type":"Point"}
}