{
  "type": "Feature",
  "properties": {
    "addr:full":"8 Prospect Business Centre, Dundee Technology Park Dundee Dundee City DD2 1TY",
    "addr:housenumber":"8",
    "addr:postcode":"dd2 1ty",
    "addr:street":"Prospect Business Centre;Technology Park",
    "iso:country":"GB",
    "sg:address":"8 Prospect Business Centre, Dundee Technology Park",
    "sg:city":"Dundee",
    "sg:classifiers":[
        {
            "category":"Organizations",
            "subcategory":"Community Association",
            "type":"Services"
        }
    ],
    "sg:phone":"+44 1382 598408",
    "sg:postcode":"DD2 1TY",
    "sg:province":"Dundee City",
    "sg:tags":[
        "relation",
        "public"
    ],
    "wof:name":"Beattie Media",
    "wof:placetype":"venue"
},
  "geometry": {"coordinates":[-3.0514359474,56.4621315002],"type":"Point"}
}