{
  "type": "Feature",
  "properties": {
    "addr:full":"10 Cheetham Street Rochdale Lancashire OL16 1DL",
    "addr:housenumber":"10",
    "addr:postcode":"ol16 1dl",
    "addr:street":"Cheetham Street",
    "iso:country":"GB",
    "sg:address":"10 Cheetham Street",
    "sg:city":"Rochdale",
    "sg:classifiers":[
        {
            "category":"Travel",
            "subcategory":"Hotels & Motels",
            "type":"Entertainment"
        },
        {
            "category":"Community Center",
            "subcategory":"Social",
            "type":"Public Place"
        }
    ],
    "sg:phone":"+44 1706 648958",
    "sg:postcode":"OL16 1DL",
    "sg:province":"Lancashire",
    "sg:tags":[
        "house",
        "guest",
        "activity"
    ],
    "wof:name":"Spread Eagle",
    "wof:placetype":"venue"
},
  "geometry": {"coordinates":[-2.1567089558,53.6196289062],"type":"Point"}
}