{
  "type": "Feature",
  "properties": {
    "addr:full":"1 High Level Drive London Greater London SE26 6XT",
    "addr:housenumber":"1",
    "addr:postcode":"se26 6xt",
    "addr:street":"High Level Drive",
    "iso:country":"GB",
    "sg:address":"1 High Level Drive",
    "sg:city":"London",
    "sg:classifiers":[
        {
            "category":"Shopping",
            "subcategory":"News",
            "type":"Retail Goods"
        }
    ],
    "sg:phone":"+44 20 8778 0197",
    "sg:postcode":"SE26 6XT",
    "sg:province":"Greater London",
    "sg:tags":[
        "newsagent"
    ],
    "wof:name":"Hill Crest General Stores",
    "wof:placetype":"venue"
},
  "geometry": {"coordinates":[-0.069628,51.427071],"type":"Point"}
}