{
  "type": "Feature",
  "properties": {
    "addr:full":"122 Railway Road, Adlington Chorley Lancashire PR6 9QT",
    "addr:housenumber":"122",
    "addr:postcode":"pr6 9qt",
    "addr:street":"Railway Road",
    "iso:country":"GB",
    "sg:address":"122 Railway Road, Adlington",
    "sg:city":"Chorley",
    "sg:classifiers":[
        {
            "category":"Cinema",
            "subcategory":"Movie Rental",
            "type":"Entertainment"
        }
    ],
    "sg:phone":"+44 1257 474987",
    "sg:postcode":"PR6 9QT",
    "sg:province":"Lancashire",
    "sg:tags":[
        "video",
        "library"
    ],
    "wof:name":"Apollo Home Entertainment",
    "wof:placetype":"venue"
},
  "geometry": {"coordinates":[-2.597466,53.617168],"type":"Point"}
}