{
  "type": "Feature",
  "properties": {
    "addr:full":"537 Pinner Road, North Harrow Harrow Greater London HA2 6EH",
    "addr:housenumber":"537",
    "addr:postcode":"ha2 6eh",
    "addr:street":"Pinner Road North",
    "iso:country":"GB",
    "sg:address":"537 Pinner Road, North Harrow",
    "sg:city":"Harrow",
    "sg:classifiers":[
        {
            "category":"Autos & Motor Vehicles",
            "subcategory":"Auto Supplies",
            "type":"Retail Goods"
        }
    ],
    "sg:phone":"+44 20 8427 1111",
    "sg:postcode":"HA2 6EH",
    "sg:province":"Greater London",
    "sg:tags":[
        "car",
        "audio"
    ],
    "wof:name":"New Image Car Hi-Fi Ltd.",
    "wof:placetype":"venue"
},
  "geometry": {"coordinates":[-0.363167,51.588665],"type":"Point"}
}