{
  "type": "Feature",
  "properties": {
    "iso:country":"GB",
    "sg:address":"East Walls",
    "sg:city":"Chichester",
    "sg:classifiers":[
        {
            "category":"Food & Beverages",
            "subcategory":"Supermarket",
            "type":"Retail Goods"
        }
    ],
    "sg:phone":"+44 1243 788373",
    "sg:postcode":"PO19 1PQ",
    "sg:province":"West Sussex",
    "sg:tags":[
        "frozen"
    ],
    "wof:name":"C Shippam Ltd.",
    "wof:placetype":"venue"
},
  "geometry": {"coordinates":[-0.774301,50.836781],"type":"Point"}
}