{
  "type": "Feature",
  "properties": {
    "addr:full":"18 Ashley Road Runcorn Cheshire WA7 5NP",
    "addr:housenumber":"18",
    "addr:postcode":"wa7 5np",
    "addr:street":"Ashley Road",
    "iso:country":"GB",
    "sg:address":"18 Ashley Road",
    "sg:city":"Runcorn",
    "sg:classifiers":[
        {
            "category":"Building & Trades",
            "subcategory":"Construction",
            "type":"Services"
        }
    ],
    "sg:postcode":"WA7 5NP",
    "sg:province":"Cheshire",
    "sg:tags":[
        "contractor",
        "paving",
        "driveway"
    ],
    "wof:name":"Runcorn Paving Services",
    "wof:placetype":"venue"
},
  "geometry": {"coordinates":[-2.7109270096,53.3398246765],"type":"Point"}
}