{
  "type": "Feature",
  "properties": {
    "addr:full":"5a The Parade Exmouth Devon EX8 1RS",
    "addr:housenumber":"5a",
    "addr:postcode":"ex8 1rs",
    "addr:street":"The Parade",
    "iso:country":"GB",
    "sg:address":"5a The Parade",
    "sg:city":"Exmouth",
    "sg:classifiers":[
        {
            "category":"Sports & Exercise",
            "subcategory":"Gym",
            "type":"Entertainment"
        }
    ],
    "sg:postcode":"EX8 1RS",
    "sg:province":"Devon",
    "sg:tags":[
        "fitness",
        "health",
        "centre"
    ],
    "wof:name":"Foster,Michael,",
    "wof:placetype":"venue"
},
  "geometry": {"coordinates":[-3.413735,50.620621],"type":"Point"}
}