{
  "type": "Feature",
  "properties": {
    "iso:country":"GB",
    "sg:address":"5 Bunyan Close, Gamlingay",
    "sg:city":"Sandy",
    "sg:classifiers":[
        {
            "category":"Home & Garden",
            "subcategory":"Building Materials",
            "type":"Retail Goods"
        }
    ],
    "sg:phone":"+44 1767 651175",
    "sg:postcode":"SG19 3JD",
    "sg:province":"Bedfordshire",
    "sg:tags":[
        "insulation",
        "installers"
    ],
    "wof:name":"Cole & Ashcroft",
    "wof:placetype":"venue"
},
  "geometry": {"coordinates":[-0.191535,52.152164],"type":"Point"}
}