{
  "type": "Feature",
  "properties": {
    "iso:country":"GB",
    "sg:address":"Newton Road, Kingsteignton",
    "sg:city":"Newton Abbot",
    "sg:classifiers":[
        {
            "category":"Manufacturing",
            "subcategory":"Building Materials",
            "type":"Manufacturing & Wholesale Goods"
        }
    ],
    "sg:phone":"+44 1626 331444",
    "sg:postcode":"TQ12 3AF",
    "sg:province":"Devon",
    "sg:tags":[
        "merchant",
        "builder"
    ],
    "wof:name":"Jewson Ltd.",
    "wof:placetype":"venue"
},
  "geometry": {"coordinates":[-3.5881938934,50.5465736389],"type":"Point"}
}