{
  "type": "Feature",
  "properties": {
    "addr:full":"160 Reading Road Wokingham Berkshire RG41 1LH",
    "addr:housenumber":"160",
    "addr:postcode":"rg41 1lh",
    "addr:street":"Reading Road",
    "iso:country":"GB",
    "sg:address":"160 Reading Road",
    "sg:city":"Wokingham",
    "sg:classifiers":[
        {
            "category":"Building & Trades",
            "subcategory":"Construction",
            "type":"Services"
        }
    ],
    "sg:phone":"+44 118 978 7781",
    "sg:postcode":"RG41 1LH",
    "sg:province":"Berkshire",
    "sg:tags":[
        "joiner",
        "carpenter"
    ],
    "wof:name":"Michael J Cowlard",
    "wof:placetype":"venue"
},
  "geometry": {"coordinates":[-0.856176,51.419559],"type":"Point"}
}