{
  "type": "Feature",
  "properties": {
    "addr:full":"Hartsdown Rd Margate Kent CT9 5QP",
    "addr:postcode":"ct9 5qp",
    "addr:street":"Hartsdown Rd Margate",
    "iso:country":"GB",
    "sg:address":"Hartsdown Rd",
    "sg:city":"Margate",
    "sg:classifiers":[
        {
            "category":"Place Of Worship",
            "type":"Public Place"
        }
    ],
    "sg:phone":"+44 1843 227046",
    "sg:postcode":"CT9 5QP",
    "sg:province":"Kent",
    "wof:name":"All Saints Parish Office",
    "wof:placetype":"venue"
},
  "geometry": {"coordinates":[1.3758679628,51.3786048889],"type":"Point"}
}