{
  "type": "Feature",
  "properties": {
    "addr:full":"357 Stockport Road, Timperley Altrincham Cheshire WA15 7UG",
    "addr:housenumber":"357",
    "addr:postcode":"wa15 7ug",
    "addr:street":"Stockport Road",
    "iso:country":"GB",
    "sg:address":"357 Stockport Road, Timperley",
    "sg:city":"Altrincham",
    "sg:classifiers":[
        {
            "category":"Fast Food",
            "type":"Food & Drink"
        }
    ],
    "sg:phone":"+44 161 903 8088",
    "sg:postcode":"WA15 7UG",
    "sg:province":"Cheshire",
    "sg:tags":[
        "away",
        "take"
    ],
    "wof:name":"Pinocchio's",
    "wof:placetype":"venue"
},
  "geometry": {"coordinates":[-2.3188641071,53.3973922729],"type":"Point"}
}