{
  "type": "Feature",
  "properties": {
    "addr:full":"54 Oaklands Road, Rodley Leeds West Yorkshire LS13 1LQ",
    "addr:housenumber":"54",
    "addr:postcode":"ls13 1lq",
    "addr:street":"Oaklands Road",
    "iso:country":"GB",
    "sg:address":"54 Oaklands Road, Rodley",
    "sg:city":"Leeds",
    "sg:classifiers":[
        {
            "category":"Shopping",
            "subcategory":"Bicycles & Sporting Goods",
            "type":"Retail Goods"
        },
        {
            "category":"Wholesale",
            "subcategory":"Sporting Goods",
            "type":"Manufacturing & Wholesale Goods"
        }
    ],
    "sg:phone":"+44 113 236 1577",
    "sg:postcode":"LS13 1LQ",
    "sg:province":"West Yorkshire",
    "sg:tags":[
        "supplier",
        "equipment",
        "camping"
    ],
    "wof:name":"European Services Ltd.",
    "wof:placetype":"venue"
},
  "geometry": {"coordinates":[-1.665479,53.822659],"type":"Point"}
}