{
  "type": "Feature",
  "properties": {
    "iso:country":"GB",
    "sg:address":"Barton Vale Farm, Barton Vale",
    "sg:city":"Barton-upon-humber",
    "sg:classifiers":[
        {
            "category":"Farming",
            "subcategory":"Crops",
            "type":"Manufacturing & Wholesale Goods"
        },
        {
            "category":"Farming",
            "subcategory":"Farm",
            "type":"Manufacturing & Wholesale Goods"
        }
    ],
    "sg:phone":"+44 1652 632115",
    "sg:postcode":"DN18 6DY",
    "sg:province":"Lincolnshire",
    "sg:tags":[
        "mixed",
        "arable"
    ],
    "wof:name":"E J Judge & Co",
    "wof:placetype":"venue"
},
  "geometry": {"coordinates":[-0.407277,53.667534],"type":"Point"}
}