{
  "type": "Feature",
  "properties": {
    "addr:full":"223 Fir Tree Road Epsom Surrey KT17 3LB",
    "addr:housenumber":"223",
    "addr:postcode":"kt17 3lb",
    "addr:street":"Fir Tree Road",
    "iso:country":"GB",
    "sg:address":"223 Fir Tree Road",
    "sg:city":"Epsom",
    "sg:classifiers":[
        {
            "category":"Shopping",
            "subcategory":"Department Store",
            "type":"Retail Goods"
        },
        {
            "category":"Shopping",
            "subcategory":"Bicycles & Sporting Goods",
            "type":"Retail Goods"
        }
    ],
    "sg:phone":"+44 1737 371137",
    "sg:postcode":"KT17 3LB",
    "sg:province":"Surrey",
    "sg:tags":[
        "riding",
        "saddlery",
        "wear"
    ],
    "wof:name":"Annabelle Brown",
    "wof:placetype":"venue"
},
  "geometry": {"coordinates":[-0.2335480005,51.3248100281],"type":"Point"}
}