{
  "type": "Feature",
  "properties": {
    "iso:country":"GB",
    "sg:address":"Units 13 & 14, Factory Units",
    "sg:city":"Grantham",
    "sg:classifiers":[
        {
            "category":"Personal",
            "type":"Services"
        }
    ],
    "sg:phone":"+44 1476 577428",
    "sg:postcode":"NG31 9HN",
    "sg:province":"Lincolnshire",
    "sg:tags":[
        "delivery"
    ],
    "wof:name":"R D M Couriers Ltd.",
    "wof:placetype":"venue"
},
  "geometry": {"coordinates":[-0.63571,52.919209],"type":"Point"}
}