{
  "type": "Feature",
  "properties": {
    "addr:full":"Unit 7 Beggarlee Park, Engine Lane, Newthorpe Nottingham Derbyshire NG16 3RN",
    "addr:housenumber":"unit 7",
    "addr:postcode":"ng16 3rn",
    "addr:street":"Beggarlee Park Engine Lane",
    "iso:country":"GB",
    "sg:address":"Unit 7 Beggarlee Park, Engine Lane, Newthorpe",
    "sg:city":"Nottingham",
    "sg:classifiers":[
        {
            "category":"Government",
            "subcategory":"Fire Station",
            "type":"Public Place"
        }
    ],
    "sg:postcode":"NG16 3RN",
    "sg:province":"Derbyshire",
    "sg:tags":[
        "security"
    ],
    "wof:name":"B W Fire Engineering",
    "wof:placetype":"venue"
},
  "geometry": {"coordinates":[-1.28923,53.0261],"type":"Point"}
}