{
  "type": "Feature",
  "properties": {
    "addr:full":"85 East Barnet Road Barnet Hertfordshire EN4 8RF",
    "addr:housenumber":"85",
    "addr:postcode":"en4 8rf",
    "addr:street":"East Barnet Road",
    "iso:country":"GB",
    "sg:address":"85 East Barnet Road",
    "sg:city":"Barnet",
    "sg:classifiers":[
        {
            "category":"Home & Garden",
            "subcategory":"Garden Supply",
            "type":"Retail Goods"
        }
    ],
    "sg:postcode":"EN4 8RF",
    "sg:province":"Hertfordshire",
    "sg:tags":[
        "nursery",
        "centre"
    ],
    "wof:name":"East Barnet Pets & Garden Centre",
    "wof:placetype":"venue"
},
  "geometry": {"coordinates":[-0.169022,51.648754],"type":"Point"}
}