{
  "type": "Feature",
  "properties": {
    "iso:country":"GB",
    "sg:address":"Hardy Street, Eccles",
    "sg:city":"Manchester",
    "sg:classifiers":[
        {
            "category":"Professional",
            "subcategory":"Business Services",
            "type":"Services"
        }
    ],
    "sg:phone":"+44 161 787 8343",
    "sg:postcode":"M30 7NB",
    "sg:province":"Greater Manchester",
    "sg:tags":[
        "accomodation"
    ],
    "wof:name":"Barton Hall Business Centre",
    "wof:placetype":"venue"
},
  "geometry": {"coordinates":[-2.366534,53.480656],"type":"Point"}
}