{
  "type": "Feature",
  "properties": {
    "iso:country":"GB",
    "sg:address":"12 Canfield Pl",
    "sg:city":"London",
    "sg:classifiers":[
        {
            "category":"Retail",
            "subcategory":"Auto Repair",
            "type":"Services"
        }
    ],
    "sg:postcode":"NW6 3BT",
    "sg:province":"Greater London",
    "sg:tags":[
        "body",
        "car"
    ],
    "wof:name":"Hampstead Coachworks",
    "wof:placetype":"venue"
},
  "geometry": {"coordinates":[-0.1813009977,51.5463294983],"type":"Point"}
}