{
  "type": "Feature",
  "properties": {
    "iso:country":"GB",
    "sg:address":"Distribution Only, Maritime Indust Est",
    "sg:city":"Pontypridd",
    "sg:classifiers":[
        {
            "category":"Wholesale",
            "subcategory":"Meat",
            "type":"Manufacturing & Wholesale Goods"
        }
    ],
    "sg:phone":"+44 1443 402557",
    "sg:postcode":"CF37 1NY",
    "sg:province":"Caerphilly",
    "sg:tags":[
        "product"
    ],
    "wof:name":"Pork Farms Bowyers",
    "wof:placetype":"venue"
},
  "geometry": {"coordinates":[-3.330959,51.597549],"type":"Point"}
}