{
  "type": "Feature",
  "properties": {
    "addr:full":"21 Mill Street Luton Bedfordshire LU1 2NA",
    "addr:housenumber":"21",
    "addr:postcode":"lu1 2na",
    "addr:street":"Mill Street",
    "iso:country":"GB",
    "sg:address":"21 Mill Street",
    "sg:city":"Luton",
    "sg:classifiers":[
        {
            "category":"Fast Food",
            "type":"Food & Drink"
        }
    ],
    "sg:phone":"+44 1582 401873",
    "sg:postcode":"LU1 2NA",
    "sg:province":"Bedfordshire",
    "sg:tags":[
        "away",
        "take"
    ],
    "wof:name":"Southern Fried Chicken",
    "wof:placetype":"venue"
},
  "geometry": {"coordinates":[-0.4177069962,51.8827667236],"type":"Point"}
}