{
  "type": "Feature",
  "properties": {
    "addr:full":"167 Greenford Road Harrow Greater London HA1 3RA",
    "addr:housenumber":"167",
    "addr:postcode":"ha1 3ra",
    "addr:street":"Greenford Road",
    "iso:country":"GB",
    "sg:address":"167 Greenford Road",
    "sg:city":"Harrow",
    "sg:classifiers":[
        {
            "category":"Shopping",
            "subcategory":"Gifts & Souvenirs",
            "type":"Retail Goods"
        }
    ],
    "sg:postcode":"HA1 3RA",
    "sg:province":"Greater London",
    "sg:tags":[
        "poster",
        "card"
    ],
    "wof:name":"Martinns",
    "wof:placetype":"venue"
},
  "geometry": {"coordinates":[-0.336058,51.55703],"type":"Point"}
}