{
  "type": "Feature",
  "properties": {
    "addr:full":"18 Kirkgate Wakefield West Yorkshire WF1 1SS",
    "addr:housenumber":"18",
    "addr:postcode":"wf1 1ss",
    "addr:street":"Kirkgate Wakefield West",
    "iso:country":"GB",
    "sg:address":"18 Kirkgate",
    "sg:city":"Wakefield",
    "sg:classifiers":[
        {
            "category":"Shopping",
            "subcategory":"Department Store",
            "type":"Retail Goods"
        }
    ],
    "sg:phone":"+44 1924 373164",
    "sg:postcode":"WF1 1SS",
    "sg:province":"West Yorkshire",
    "sg:tags":[
        "departmental"
    ],
    "wof:name":"Marks & Spencer Plc",
    "wof:placetype":"venue"
},
  "geometry": {"coordinates":[-1.4943909645,53.6824645996],"type":"Point"}
}