{
  "type": "Feature",
  "properties": {
    "iso:country":"GB",
    "sg:address":"2 Chilmark Ct, Riverside Clo",
    "sg:city":"Liss",
    "sg:classifiers":[
        {
            "category":"Military Area",
            "subcategory":"Air Force Base",
            "type":"Public Place"
        }
    ],
    "sg:postcode":"GU33 7SA",
    "sg:province":"Hampshire",
    "sg:tags":[
        "taxi",
        "hire",
        "private"
    ],
    "wof:name":"Atkins,M W,",
    "wof:placetype":"venue"
},
  "geometry": {"coordinates":[-0.89265,51.043026],"type":"Point"}
}