{
  "type": "Feature",
  "properties": {
    "iso:country":"GB",
    "sg:address":"91 Stocks Bank Road",
    "sg:city":"Mirfield",
    "sg:classifiers":[
        {
            "category":"Organizations",
            "subcategory":"Membership Organization",
            "type":"Services"
        }
    ],
    "sg:phone":"+44 1924 492528",
    "sg:postcode":"WF14 9QB",
    "sg:province":"West Yorkshire",
    "sg:tags":[
        "club"
    ],
    "wof:name":"Mirfield W M Social Club",
    "wof:placetype":"venue"
},
  "geometry": {"coordinates":[-1.7115199566,53.6807479858],"type":"Point"}
}