{
  "type": "Feature",
  "properties": {
    "addr:full":"Beacon Industrial Estate Withernsea East Riding of Yorkshire HU19 2DL",
    "addr:housenumber":"estate",
    "addr:postcode":"hu19 2dl",
    "addr:street":"Beacon Industrial",
    "iso:country":"GB",
    "sg:address":"Beacon Industrial Estate",
    "sg:city":"Withernsea",
    "sg:classifiers":[
        {
            "category":"Depot",
            "subcategory":"Train",
            "type":"Transportation"
        },
        {
            "category":"Autos & Motor Vehicles",
            "subcategory":"Auto Supplies",
            "type":"Retail Goods"
        }
    ],
    "sg:phone":"+44 1964 612225",
    "sg:postcode":"HU19 2DL",
    "sg:province":"East Riding of Yorkshire",
    "sg:tags":[
        "mnfrs",
        "caravan",
        "accessory"
    ],
    "wof:name":"Withernsea Caravan Services Ltd.",
    "wof:placetype":"venue"
},
  "geometry": {"coordinates":[0.0330349989,53.7302818298],"type":"Point"}
}