{
  "type": "Feature",
  "properties": {
    "iso:country":"GB",
    "sg:address":"47 Devizes Road, Wroughton",
    "sg:city":"Swindon",
    "sg:classifiers":[
        {
            "category":"Travel",
            "subcategory":"Hotels & Motels",
            "type":"Entertainment"
        },
        {
            "category":"Community Center",
            "subcategory":"Social",
            "type":"Public Place"
        }
    ],
    "sg:phone":"+44 1793 812210",
    "sg:postcode":"SN4 0SA",
    "sg:province":"Wiltshire",
    "sg:tags":[
        "house",
        "activity"
    ],
    "wof:name":"Three Tuns",
    "wof:placetype":"venue"
},
  "geometry": {"coordinates":[-1.789553,51.524345],"type":"Point"}
}