{
  "type": "Feature",
  "properties": {
    "addr:full":"Church Rd, Baschurch Shrewsbury Shropshire SY4 2EF",
    "addr:postcode":"sy4 2ef",
    "addr:street":"Church Rd",
    "iso:country":"GB",
    "sg:address":"Church Rd, Baschurch",
    "sg:city":"Shrewsbury",
    "sg:classifiers":[
        {
            "category":"Bars & Pubs",
            "type":"Food & Drink"
        }
    ],
    "sg:phone":"+44 1939 260335",
    "sg:postcode":"SY4 2EF",
    "sg:province":"Shropshire",
    "sg:tags":[
        "pubs",
        "inn"
    ],
    "wof:name":"The New Inn",
    "wof:placetype":"venue"
},
  "geometry": {"coordinates":[-2.8526599407,52.7872276306],"type":"Point"}
}