{
  "type": "Feature",
  "properties": {
    "addr:full":"Mill Cottage, Maunsel Road, North Newton Bridgwater Somerset TA7 0BU",
    "addr:postcode":"ta7 0bu",
    "addr:street":"Maunsel Road North Newton",
    "iso:country":"GB",
    "sg:address":"Mill Cottage, Maunsel Road, North Newton",
    "sg:city":"Bridgwater",
    "sg:classifiers":[
        {
            "category":"Professional",
            "subcategory":"Engineering",
            "type":"Services"
        },
        {
            "category":"Military Area",
            "subcategory":"Air Force Base",
            "type":"Public Place"
        }
    ],
    "sg:postcode":"TA7 0BU",
    "sg:province":"Somerset",
    "sg:tags":[
        "groundwork",
        "civil",
        "engineer",
        "contractor"
    ],
    "wof:name":"John F Durbin",
    "wof:placetype":"venue"
},
  "geometry": {"coordinates":[-3.0004739761,51.074546814],"type":"Point"}
}