{
  "type": "Feature",
  "properties": {
    "addr:full":"4 North Quay Hayle Cornwall TR27 4BL",
    "addr:housenumber":"4",
    "addr:postcode":"tr27 4bl",
    "addr:street":"North Quay",
    "iso:country":"GB",
    "sg:address":"4 North Quay",
    "sg:city":"Hayle",
    "sg:classifiers":[
        {
            "category":"Wholesale",
            "subcategory":"Fruits & Vegetables",
            "type":"Manufacturing & Wholesale Goods"
        }
    ],
    "sg:phone":"+44 1736 757992",
    "sg:postcode":"TR27 4BL",
    "sg:province":"Cornwall",
    "wof:name":"Ready Fresh Prepared Vegetables",
    "wof:placetype":"venue"
},
  "geometry": {"coordinates":[-5.423913002,50.1893157959],"type":"Point"}
}