{
  "type": "Feature",
  "properties": {
    "iso:country":"GB",
    "sg:address":"28 Bedminster Road, Bedminster",
    "sg:city":"Bristol",
    "sg:classifiers":[
        {
            "category":"Shopping",
            "subcategory":"Hobbies, Toys, & Games",
            "type":"Retail Goods"
        }
    ],
    "sg:phone":"+44 117 963 3645",
    "sg:postcode":"BS3 5PD",
    "sg:province":"City of Bristol",
    "sg:tags":[
        "gunsmith"
    ],
    "wof:name":"Newavon Arms",
    "wof:placetype":"venue"
},
  "geometry": {"coordinates":[-2.6001970768,51.4354553223],"type":"Point"}
}