{
  "type": "Feature",
  "properties": {
    "iso:country":"GB",
    "sg:address":"16 Coniston Crescent",
    "sg:city":"Loughborough",
    "sg:classifiers":[
        {
            "category":"Shopping",
            "subcategory":"Stationery & Office Supplies",
            "type":"Retail Goods"
        }
    ],
    "sg:phone":"+44 1509 235550",
    "sg:postcode":"LE11 3RH",
    "sg:province":"Leicestershire",
    "sg:tags":[
        "item",
        "product",
        "corporate",
        "promotional"
    ],
    "wof:name":"C N Promotions",
    "wof:placetype":"venue"
},
  "geometry": {"coordinates":[-1.238274,52.760948],"type":"Point"}
}