{
  "type": "Feature",
  "properties": {
    "addr:full":"Aldermary House London Greater London EC4N 1TX",
    "addr:postcode":"ec4n 1tx",
    "iso:country":"GB",
    "sg:address":"Aldermary House",
    "sg:city":"London",
    "sg:classifiers":[
        {
            "category":"Organizations",
            "subcategory":"Community Association",
            "type":"Services"
        }
    ],
    "sg:phone":"+44 20 7329 6009",
    "sg:postcode":"EC4N 1TX",
    "sg:province":"Greater London",
    "sg:tags":[
        "relation",
        "public"
    ],
    "wof:name":"Square Mile Communications Ltd.",
    "wof:placetype":"venue"
},
  "geometry": {"coordinates":[-0.087574,51.508404],"type":"Point"}
}