{
  "type": "Feature",
  "properties": {
    "iso:country":"GB",
    "sg:address":"Barrwick Road",
    "sg:city":"Leeds",
    "sg:classifiers":[
        {
            "category":"Education",
            "subcategory":"School",
            "type":"Public Place"
        }
    ],
    "sg:phone":"+44 113 293 0240",
    "sg:postcode":"LS15 8RQ",
    "sg:province":"West Yorkshire",
    "sg:tags":[
        "independent",
        "preparatory"
    ],
    "wof:name":"St Theresas R C Primary School",
    "wof:placetype":"venue"
},
  "geometry": {"coordinates":[-1.436499,53.81657],"type":"Point"}
}