{
  "type": "Feature",
  "properties": {
    "iso:country":"GB",
    "sg:address":"Spring Close Cottage, Lyburn Road, No Man's Land",
    "sg:city":"Salisbury",
    "sg:classifiers":[
        {
            "category":"Freight",
            "type":"Transportation"
        }
    ],
    "sg:phone":"+44 1794 390461",
    "sg:postcode":"SP5 2DF",
    "sg:province":"Dorset",
    "sg:tags":[
        "haulage",
        "road"
    ],
    "wof:name":"M & S Freight",
    "wof:placetype":"venue"
},
  "geometry": {"coordinates":[-1.64949,50.957069],"type":"Point"}
}