{
  "type": "Feature",
  "properties": {
    "addr:full":"Tramways Bldg, Frederick Rd Salford Greater Manchester M6 6BY",
    "addr:postcode":"m6 6by",
    "addr:street":"Frederick Rd",
    "iso:country":"GB",
    "sg:address":"Tramways Bldg, Frederick Rd",
    "sg:city":"Salford",
    "sg:classifiers":[
        {
            "category":"Education",
            "subcategory":"School",
            "type":"Public Place"
        }
    ],
    "sg:postcode":"M6 6BY",
    "sg:province":"Greater Manchester",
    "sg:tags":[
        "local",
        "authority"
    ],
    "wof:name":"Shinedetail Ltd",
    "wof:placetype":"venue"
},
  "geometry": {"coordinates":[-2.284299,53.489731],"type":"Point"}
}