{
  "type": "Feature",
  "properties": {
    "iso:country":"GB",
    "sg:address":"110-112 Barnards Green Road",
    "sg:city":"Malvern",
    "sg:classifiers":[
        {
            "category":"Food & Beverages",
            "subcategory":"Liquor & Beverages",
            "type":"Retail Goods"
        }
    ],
    "sg:phone":"+44 1684 565706",
    "sg:postcode":"WR14 3ND",
    "sg:province":"Herefordshire",
    "sg:tags":[
        "beer",
        "spirit",
        "wines"
    ],
    "wof:name":"Wine Rack",
    "wof:placetype":"venue"
},
  "geometry": {"coordinates":[-2.309983,52.108276],"type":"Point"}
}