{
  "type": "Feature",
  "properties": {
    "addr:full":"82 St Helens Street Ipswich Suffolk IP4 2LB",
    "addr:housenumber":"82",
    "addr:postcode":"ip4 2lb",
    "addr:street":"St Helens Street",
    "iso:country":"GB",
    "sg:address":"82 St Helens Street",
    "sg:city":"Ipswich",
    "sg:classifiers":[
        {
            "category":"Professional",
            "subcategory":"Engineering",
            "type":"Services"
        },
        {
            "category":"Building & Trades",
            "subcategory":"Electrical",
            "type":"Services"
        }
    ],
    "sg:phone":"+44 1473 213086",
    "sg:postcode":"IP4 2LB",
    "sg:province":"Suffolk",
    "sg:tags":[
        "engineer",
        "electrician",
        "contractor"
    ],
    "wof:name":"PITT & ABBOTT",
    "wof:placetype":"venue"
},
  "geometry": {"coordinates":[1.164398,52.056438],"type":"Point"}
}