{
  "type": "Feature",
  "properties": {
    "addr:full":"35 High Street Burnham-on-sea Somerset TA8 1PA",
    "addr:housenumber":"35",
    "addr:postcode":"ta8 1pa",
    "addr:street":"High Street",
    "iso:country":"GB",
    "sg:address":"35 High Street",
    "sg:city":"Burnham-on-sea",
    "sg:classifiers":[
        {
            "category":"Professional",
            "subcategory":"Art Services",
            "type":"Services"
        }
    ],
    "sg:phone":"+44 1278 781633",
    "sg:postcode":"TA8 1PA",
    "sg:province":"Somerset",
    "sg:tags":[
        "photographer"
    ],
    "wof:name":"The Photo Co. (Bristol) Ltd.",
    "wof:placetype":"venue"
},
  "geometry": {"coordinates":[-2.9974091053,51.2355575562],"type":"Point"}
}