{
  "type": "Feature",
  "properties": {
    "iso:country":"GB",
    "sg:address":"Doctors Surgery Glebe Ho, Church Rd",
    "sg:city":"Lincoln",
    "sg:classifiers":[
        {
            "category":"Health Services",
            "subcategory":"Doctor",
            "type":"Services"
        }
    ],
    "sg:phone":"+44 1522 702236",
    "sg:postcode":"LN1 2HJ",
    "sg:province":"Lincolnshire",
    "sg:tags":[
        "practitioners"
    ],
    "wof:name":"Abbas, E M",
    "wof:placetype":"venue"
},
  "geometry": {"coordinates":[-0.661650002,53.2729110718],"type":"Point"}
}