{
  "type": "Feature",
  "properties": {
    "iso:country":"GB",
    "sg:address":"25 Parsonage Lane, North Cray",
    "sg:city":"Sidcup",
    "sg:classifiers":[
        {
            "category":"Sports & Exercise",
            "subcategory":"Stables",
            "type":"Entertainment"
        }
    ],
    "sg:phone":"+44 20 8300 1378",
    "sg:postcode":"DA14 5EZ",
    "sg:province":"Kent",
    "sg:tags":[
        "education",
        "equestrian"
    ],
    "wof:name":"North Cray & Sidcup Riding School",
    "wof:placetype":"venue"
},
  "geometry": {"coordinates":[0.139167,51.423946],"type":"Point"}
}