{
  "type": "Feature",
  "properties": {
    "iso:country":"GB",
    "sg:address":"7 Effingham Crescent",
    "sg:city":"Dover",
    "sg:classifiers":[
        {
            "category":"Professional",
            "subcategory":"Detective & Security Services",
            "type":"Services"
        }
    ],
    "sg:phone":"+44 1304 211220",
    "sg:postcode":"CT17 9RH",
    "sg:province":"Kent",
    "sg:tags":[
        "locksmith"
    ],
    "wof:name":"Safe & Secure",
    "wof:placetype":"venue"
},
  "geometry": {"coordinates":[1.30896,51.12772],"type":"Point"}
}