{
  "type": "Feature",
  "properties": {
    "iso:country":"GB",
    "sg:address":"Hawksworth Road, Screveton",
    "sg:city":"Nottingham",
    "sg:classifiers":[
        {
            "category":"Bars & Pubs",
            "type":"Food & Drink"
        }
    ],
    "sg:phone":"+44 1949 20383",
    "sg:postcode":"NG13 8JP",
    "sg:province":"Leicestershire",
    "sg:tags":[
        "pubs",
        "inn"
    ],
    "wof:name":"The Royal Oak",
    "wof:placetype":"venue"
},
  "geometry": {"coordinates":[-0.912119,52.98526],"type":"Point"}
}