{
  "type": "Feature",
  "properties": {
    "iso:country":"GB",
    "sg:address":"224 Terminus Road",
    "sg:city":"Eastbourne",
    "sg:classifiers":[
        {
            "category":"Shopping",
            "subcategory":"Comic Books",
            "type":"Retail Goods"
        }
    ],
    "sg:phone":"+44 1323 411200",
    "sg:postcode":"BN21 3DF",
    "sg:province":"East Sussex",
    "sg:tags":[
        "jeweller"
    ],
    "wof:name":"Chalcraft Jewellers",
    "wof:placetype":"venue"
},
  "geometry": {"coordinates":[0.289507,50.766979],"type":"Point"}
}