{
  "type": "Feature",
  "properties": {
    "addr:full":"Abbeygreen, Lesmahagow Lanark South Lanarkshire ML11 0DB",
    "addr:postcode":"ml11 0db",
    "addr:street":"Abbeygreen",
    "iso:country":"GB",
    "sg:address":"Abbeygreen, Lesmahagow",
    "sg:city":"Lanark",
    "sg:classifiers":[
        {
            "category":"Health Services",
            "subcategory":"Doctor",
            "type":"Services"
        }
    ],
    "sg:phone":"+44 1555 892328",
    "sg:postcode":"ML11 0DB",
    "sg:province":"South Lanarkshire",
    "sg:tags":[
        "practitioners"
    ],
    "wof:name":"Glebe Medical Centre",
    "wof:placetype":"venue"
},
  "geometry": {"coordinates":[-3.886588,55.637596],"type":"Point"}
}