{
  "type": "Feature",
  "properties": {
    "addr:full":"Thornton Industrial Estate Milford Haven Pembrokeshire SA73 2RR",
    "addr:postcode":"sa73 2rr",
    "addr:street":"Estate;Haven",
    "iso:country":"GB",
    "sg:address":"Thornton Industrial Estate",
    "sg:city":"Milford Haven",
    "sg:classifiers":[
        {
            "category":"Wholesale",
            "subcategory":"Groceries",
            "type":"Manufacturing & Wholesale Goods"
        }
    ],
    "sg:phone":"+44 1646 695527",
    "sg:postcode":"SA73 2RR",
    "sg:province":"Pembrokeshire",
    "sg:tags":[
        "food",
        "supplier",
        "drink"
    ],
    "wof:name":"M & M Snacks & Drinks",
    "wof:placetype":"venue"
},
  "geometry": {"coordinates":[-5.027044,51.716808],"type":"Point"}
}