{
  "type": "Feature",
  "properties": {
    "iso:country":"GB",
    "sg:address":"Hibbert Street, Whitehill Industrial Estate",
    "sg:city":"Stockport",
    "sg:classifiers":[
        {
            "category":"Home & Garden",
            "subcategory":"Hardware",
            "type":"Retail Goods"
        }
    ],
    "sg:phone":"+44 161 429 6066",
    "sg:postcode":"SK4 1NS",
    "sg:province":"Cheshire",
    "sg:tags":[
        "device",
        "fixing",
        "fastener"
    ],
    "wof:name":"Roy Hopwood (Fasteners) Ltd.",
    "wof:placetype":"venue"
},
  "geometry": {"coordinates":[-2.162114,53.426216],"type":"Point"}
}