{
  "type": "Feature",
  "properties": {
    "addr:full":"Caplan Ho, Derby St Manchester Greater Manchester M8 8HE",
    "addr:postcode":"m8 8he",
    "addr:street":"Derby St",
    "iso:country":"GB",
    "sg:address":"Caplan Ho, Derby St",
    "sg:city":"Manchester",
    "sg:classifiers":[
        {
            "category":"Wholesale",
            "subcategory":"Non-durable Goods",
            "type":"Manufacturing & Wholesale Goods"
        }
    ],
    "sg:phone":"+44 161 832 5614",
    "sg:postcode":"M8 8HE",
    "sg:province":"Greater Manchester",
    "sg:tags":[
        "carry",
        "cash"
    ],
    "wof:name":"Nield Manchester Ltd",
    "wof:placetype":"venue"
},
  "geometry": {"coordinates":[-2.2486999035,53.4961395264],"type":"Point"}
}