{
  "type": "Feature",
  "properties": {
    "iso:country":"GB",
    "sg:address":"Brompton Road, Scorton",
    "sg:city":"Richmond",
    "sg:classifiers":[
        {
            "category":"Farming",
            "subcategory":"Farm",
            "type":"Manufacturing & Wholesale Goods"
        }
    ],
    "sg:phone":"+44 1748 811371",
    "sg:postcode":"DL10 6AB",
    "sg:province":"North Yorkshire",
    "sg:tags":[
        "mixed",
        "crop"
    ],
    "wof:name":"W L Barker & Sons",
    "wof:placetype":"venue"
},
  "geometry": {"coordinates":[-1.6166540384,54.396938324],"type":"Point"}
}