{
  "type": "Feature",
  "properties": {
    "addr:full":"Sandy Lane Watford Hertfordshire WD25 8HE",
    "addr:postcode":"wd25 8he",
    "addr:street":"Sandy Lane",
    "iso:country":"GB",
    "sg:address":"Sandy Lane",
    "sg:city":"Watford",
    "sg:classifiers":[
        {
            "category":"Transit Center",
            "subcategory":"Passenger",
            "type":"Transportation"
        }
    ],
    "sg:postcode":"WD25 8HE",
    "sg:province":"Hertfordshire",
    "sg:tags":[
        "boarding",
        "kennel",
        "catteries"
    ],
    "wof:name":"Roundcroft Kennels",
    "wof:placetype":"venue"
},
  "geometry": {"coordinates":[-0.348711,51.659416],"type":"Point"}
}