{
  "type": "Feature",
  "properties": {
    "iso:country":"GB",
    "sg:address":"77 Eastdale Close, Kempston",
    "sg:city":"Bedford",
    "sg:classifiers":[
        {
            "category":"Building & Trades",
            "subcategory":"Landscaping Services",
            "type":"Services"
        }
    ],
    "sg:phone":"+44 1234 219261",
    "sg:postcode":"MK42 8LY",
    "sg:province":"Bedfordshire",
    "sg:tags":[
        "gardening"
    ],
    "wof:name":"Garden Care Services",
    "wof:placetype":"venue"
},
  "geometry": {"coordinates":[-0.4792479873,52.1193618774],"type":"Point"}
}