{
  "type": "Feature",
  "properties": {
    "addr:full":"Po Box 4 Motherwell North Lanarkshire ML1 3NP",
    "addr:housenumber":"po;4",
    "addr:postcode":"ml1 3np",
    "addr:street":"Box",
    "iso:country":"GB",
    "sg:address":"Po Box 4",
    "sg:city":"Motherwell",
    "sg:classifiers":[
        {
            "category":"Professional",
            "subcategory":"Engineering",
            "type":"Services"
        }
    ],
    "sg:phone":"+44 1698 262277",
    "sg:postcode":"ML1 3NP",
    "sg:province":"North Lanarkshire",
    "sg:tags":[
        "engineer",
        "mechanical"
    ],
    "wof:name":"Torch Technical Services Ltd.",
    "wof:placetype":"venue"
},
  "geometry": {"coordinates":[-3.991519,55.788765],"type":"Point"}
}