{
  "type": "Feature",
  "properties": {
    "addr:full":"29a Bonnygate Cupar Fife KY15 4BU",
    "addr:housenumber":"29a",
    "addr:postcode":"ky15 4bu",
    "addr:street":"Bonnygate Cupar",
    "iso:country":"GB",
    "sg:address":"29a Bonnygate",
    "sg:city":"Cupar",
    "sg:classifiers":[
        {
            "category":"Shopping",
            "subcategory":"Books",
            "type":"Retail Goods"
        }
    ],
    "sg:phone":"+44 1334 657890",
    "sg:postcode":"KY15 4BU",
    "sg:province":"Fife",
    "sg:tags":[
        "bookseller",
        "retailer"
    ],
    "wof:name":"Courtyard Books",
    "wof:placetype":"venue"
},
  "geometry": {"coordinates":[-3.0127871037,56.3196487427],"type":"Point"}
}