{
  "type": "Feature",
  "properties": {
    "iso:country":"GB",
    "sg:address":"9 Beachfield Avenue",
    "sg:city":"Newquay",
    "sg:classifiers":[
        {
            "category":"Wholesale",
            "subcategory":"Sporting Goods",
            "type":"Manufacturing & Wholesale Goods"
        }
    ],
    "sg:phone":"+44 1637 877277",
    "sg:postcode":"TR7 1DP",
    "sg:province":"Cornwall",
    "sg:tags":[
        "mnfr",
        "sport",
        "equipment"
    ],
    "wof:name":"David Farrow",
    "wof:placetype":"venue"
},
  "geometry": {"coordinates":[-5.085172,50.41423],"type":"Point"}
}