{
  "type": "Feature",
  "properties": {
    "iso:country":"GB",
    "sg:address":"M B L Buildings, Whitelea Grove Trading Estate",
    "sg:city":"Mexborough",
    "sg:classifiers":[
        {
            "category":"Home & Garden",
            "subcategory":"Home Furnishings",
            "type":"Retail Goods"
        }
    ],
    "sg:phone":"+44 1709 578286",
    "sg:postcode":"S64 9QP",
    "sg:province":"South Yorkshire",
    "sg:tags":[
        "mantelpiece",
        "fireplace"
    ],
    "wof:name":"The Ashley Design Co.",
    "wof:placetype":"venue"
},
  "geometry": {"coordinates":[-1.299809,53.495354],"type":"Point"}
}