{
  "type": "Feature",
  "properties": {
    "addr:full":"Kestrel House, Mill St Trowbridge Wiltshire BA14 8BE",
    "addr:postcode":"ba14 8be",
    "addr:street":"Mill St",
    "iso:country":"GB",
    "sg:address":"Kestrel House, Mill St",
    "sg:city":"Trowbridge",
    "sg:classifiers":[
        {
            "category":"Building & Trades",
            "subcategory":"Construction",
            "type":"Services"
        }
    ],
    "sg:phone":"+44 1225 752907",
    "sg:postcode":"BA14 8BE",
    "sg:province":"Wiltshire",
    "sg:tags":[
        "window",
        "replacement"
    ],
    "wof:name":"Europlas Ltd",
    "wof:placetype":"venue"
},
  "geometry": {"coordinates":[-2.208034,51.318748],"type":"Point"}
}