{
  "type": "Feature",
  "properties": {
    "addr:full":"13-17 Clarence Street Gloucester Gloucestershire GL1 1EA",
    "addr:housenumber":"13-17",
    "addr:postcode":"gl1 1ea",
    "addr:street":"Clarence Street",
    "iso:country":"GB",
    "sg:address":"13-17 Clarence Street",
    "sg:city":"Gloucester",
    "sg:classifiers":[
        {
            "category":"Home & Garden",
            "subcategory":"Household Appliances",
            "type":"Retail Goods"
        }
    ],
    "sg:phone":"+44 1452 301323",
    "sg:postcode":"GL1 1EA",
    "sg:province":"Gloucestershire",
    "sg:tags":[
        "electrical",
        "domestic"
    ],
    "wof:name":"Tandy",
    "wof:placetype":"venue"
},
  "geometry": {"coordinates":[-2.242361,51.864819],"type":"Point"}
}