{
  "type": "Feature",
  "properties": {
    "addr:full":"71 Lower Street Merriott Somerset TA16 5NP",
    "addr:housenumber":"71",
    "addr:postcode":"ta16 5np",
    "addr:street":"Lower Street",
    "iso:country":"GB",
    "sg:address":"71 Lower Street",
    "sg:city":"Merriott",
    "sg:classifiers":[
        {
            "category":"Organizations",
            "subcategory":"Community Association",
            "type":"Services"
        },
        {
            "category":"Organizations",
            "subcategory":"Membership Organization",
            "type":"Services"
        }
    ],
    "sg:phone":"+44 1460 74376",
    "sg:postcode":"TA16 5NP",
    "sg:province":"Somerset",
    "sg:tags":[
        "club",
        "social"
    ],
    "wof:name":"Merriott Social Club",
    "wof:placetype":"venue"
},
  "geometry": {"coordinates":[-2.789470911,50.9087677002],"type":"Point"}
}