{
  "type": "Feature",
  "properties": {
    "addr:full":"51 Tunstall Road Canterbury Kent CT2 7BX",
    "addr:housenumber":"51",
    "addr:postcode":"ct2 7bx",
    "addr:street":"Tunstall Road",
    "iso:country":"GB",
    "sg:address":"51 Tunstall Road",
    "sg:city":"Canterbury",
    "sg:classifiers":[
        {
            "category":"Home & Garden",
            "subcategory":"Building Materials",
            "type":"Retail Goods"
        }
    ],
    "sg:phone":"+44 1227 768812",
    "sg:postcode":"CT2 7BX",
    "sg:province":"Kent",
    "sg:tags":[
        "insulation",
        "installers"
    ],
    "wof:name":"Ian Clark",
    "wof:placetype":"venue"
},
  "geometry": {"coordinates":[1.084951,51.295437],"type":"Point"}
}