{
  "type": "Feature",
  "properties": {
    "addr:full":"Bernard Way Newport Isle of Wight PO30 5YL",
    "addr:postcode":"po30 5yl",
    "addr:street":"Bernard Way",
    "iso:country":"GB",
    "sg:address":"Bernard Way",
    "sg:city":"Newport",
    "sg:classifiers":[
        {
            "category":"Wholesale",
            "subcategory":"Machinery & Supplies",
            "type":"Manufacturing & Wholesale Goods"
        },
        {
            "category":"Recreation",
            "subcategory":"Fishing",
            "type":"Entertainment"
        }
    ],
    "sg:phone":"+44 1983 528088",
    "sg:postcode":"PO30 5YL",
    "sg:province":"Isle of Wight",
    "sg:tags":[
        "control",
        "industrial",
        "equipment",
        "-",
        "instrument",
        "angling"
    ],
    "wof:name":"I D M L (Dotcom)",
    "wof:placetype":"venue"
},
  "geometry": {"coordinates":[-1.294176,50.706566],"type":"Point"}
}