{
  "type": "Feature",
  "properties": {
    "addr:full":"Battle Hill Hexham Northumberland NE46 1BA",
    "addr:postcode":"ne46 1ba",
    "addr:street":"Battle Hill",
    "iso:country":"GB",
    "sg:address":"Battle Hill",
    "sg:city":"Hexham",
    "sg:classifiers":[
        {
            "category":"Bars & Pubs",
            "type":"Food & Drink"
        },
        {
            "category":"Community Center",
            "subcategory":"Social",
            "type":"Public Place"
        }
    ],
    "sg:phone":"+44 1434 602039",
    "sg:postcode":"NE46 1BA",
    "sg:province":"Northumberland",
    "sg:tags":[
        "pubs",
        "house",
        "inn",
        "activity"
    ],
    "wof:name":"Tap & Spile",
    "wof:placetype":"venue"
},
  "geometry": {"coordinates":[-2.1012940407,54.970035553],"type":"Point"}
}