{
  "type": "Feature",
  "properties": {
    "addr:full":"Park House, 15-19 Greenhill Crescent Watford Hertfordshire WD18 8PH",
    "addr:housenumber":"15-19",
    "addr:postcode":"wd18 8ph",
    "addr:street":"Greenhill Crescent",
    "iso:country":"GB",
    "sg:address":"Park House, 15-19 Greenhill Crescent",
    "sg:city":"Watford",
    "sg:classifiers":[
        {
            "category":"Professional",
            "subcategory":"Printing & Photocopies",
            "type":"Services"
        }
    ],
    "sg:phone":"+44 1923 818906",
    "sg:postcode":"WD18 8PH",
    "sg:province":"Hertfordshire",
    "sg:tags":[
        "printer"
    ],
    "wof:name":"Tiger Press",
    "wof:placetype":"venue"
},
  "geometry": {"coordinates":[-0.425391,51.645702],"type":"Point"}
}