{
  "type": "Feature",
  "properties": {
    "iso:country":"GB",
    "sg:address":"285 Cambuslang Road, Cambuslang",
    "sg:city":"Glasgow",
    "sg:classifiers":[
        {
            "category":"Government",
            "subcategory":"Office",
            "type":"Public Place"
        }
    ],
    "sg:phone":"+44 141 641 1565",
    "sg:postcode":"G72 7DB",
    "sg:province":"South Lanarkshire",
    "sg:tags":[
        "local",
        "agency",
        "education",
        "authority"
    ],
    "wof:name":"Eastfield Resource Centre",
    "wof:placetype":"venue"
},
  "geometry": {"coordinates":[-4.186863,55.825703],"type":"Point"}
}