{
  "type": "Feature",
  "properties": {
    "addr:full":"9 South Street Dorking Surrey RH4 2DY",
    "addr:housenumber":"9",
    "addr:postcode":"rh4 2dy",
    "addr:street":"South Street",
    "iso:country":"GB",
    "sg:address":"9 South Street",
    "sg:city":"Dorking",
    "sg:classifiers":[
        {
            "category":"Food & Beverages",
            "subcategory":"Meat & Fish",
            "type":"Retail Goods"
        }
    ],
    "sg:phone":"+44 1306 883053",
    "sg:postcode":"RH4 2DY",
    "sg:province":"Surrey",
    "sg:tags":[
        "butcher"
    ],
    "wof:name":"Stuart Pearce Family Butcher",
    "wof:placetype":"venue"
},
  "geometry": {"coordinates":[-0.333258,51.231247],"type":"Point"}
}