{
  "type": "Feature",
  "properties": {
    "addr:full":"1 Burnside Road, Monkton Prestwick South Ayrshire KA9 2RL",
    "addr:housenumber":"1",
    "addr:postcode":"ka9 2rl",
    "addr:street":"Burnside Road;Prestwick",
    "iso:country":"GB",
    "sg:address":"1 Burnside Road, Monkton",
    "sg:city":"Prestwick",
    "sg:classifiers":[
        {
            "category":"Building & Trades",
            "subcategory":"Landscaping Services",
            "type":"Services"
        }
    ],
    "sg:postcode":"KA9 2RL",
    "sg:province":"South Ayrshire",
    "sg:tags":[
        "landscape",
        "contractor"
    ],
    "wof:name":"Elm Landscape",
    "wof:placetype":"venue"
},
  "geometry": {"coordinates":[-4.6024851799,55.5165405273],"type":"Point"}
}