{
  "type": "Feature",
  "properties": {
    "addr:full":"The Rookery, Grateley Andover Hampshire SP11 8JR",
    "addr:postcode":"sp11 8jr",
    "iso:country":"GB",
    "sg:address":"The Rookery, Grateley",
    "sg:city":"Andover",
    "sg:classifiers":[
        {
            "category":"Health Services",
            "subcategory":"Dentist",
            "type":"Services"
        }
    ],
    "sg:postcode":"SP11 8JR",
    "sg:province":"Hampshire",
    "wof:name":"E Medley",
    "wof:placetype":"venue"
},
  "geometry": {"coordinates":[-1.6045160294,51.1755065918],"type":"Point"}
}