{
  "type": "Feature",
  "properties": {
    "iso:country":"GB",
    "sg:address":"Kelston Park, Kelston",
    "sg:city":"Bath",
    "sg:classifiers":[
        {
            "category":"Sports & Exercise",
            "subcategory":"Golf",
            "type":"Entertainment"
        }
    ],
    "sg:phone":"+44 1225 444544",
    "sg:postcode":"BA1 9AE",
    "sg:province":"Bath and North East Somerset",
    "sg:tags":[
        "greeting",
        "card"
    ],
    "wof:name":"The Andrew Brownsword Collection",
    "wof:placetype":"venue"
},
  "geometry": {"coordinates":[-2.4320130348,51.4024467468],"type":"Point"}
}