{
  "type": "Feature",
  "properties": {
    "addr:full":"Nine Oaks Park, Exchange Road Lincoln Lincolnshire LN6 3JZ",
    "addr:postcode":"ln6 3jz",
    "addr:street":"Exchange Road",
    "iso:country":"GB",
    "sg:address":"Nine Oaks Park, Exchange Road",
    "sg:city":"Lincoln",
    "sg:classifiers":[
        {
            "category":"Professional",
            "subcategory":"Printing & Photocopies",
            "type":"Services"
        }
    ],
    "sg:phone":"+44 1522 695200",
    "sg:postcode":"LN6 3JZ",
    "sg:province":"Lincolnshire",
    "sg:tags":[
        "printer"
    ],
    "wof:name":"Rayprint & Design",
    "wof:placetype":"venue"
},
  "geometry": {"coordinates":[-0.5915799737,53.2008705139],"type":"Point"}
}