{
  "type": "Feature",
  "properties": {
    "iso:country":"GB",
    "sg:address":"101 Bispham Road",
    "sg:city":"Blackpool",
    "sg:classifiers":[
        {
            "category":"Personal",
            "subcategory":"Beauty Salon",
            "type":"Services"
        },
        {
            "category":"Personal",
            "subcategory":"Barber",
            "type":"Services"
        }
    ],
    "sg:phone":"+44 1253 354630",
    "sg:postcode":"FY2 0NR",
    "sg:province":"Lancashire",
    "sg:tags":[
        "unisex",
        "hairdresser"
    ],
    "wof:name":"Imagination",
    "wof:placetype":"venue"
},
  "geometry": {"coordinates":[-3.031047,53.837585],"type":"Point"}
}