{
  "type": "Feature",
  "properties": {
    "addr:full":"Unit 16 Lodge Forge Trading Estate, Cradley Road Cradley Heath West Midlands B64 7RW",
    "addr:housenumber":"unit 16",
    "addr:postcode":"b64 7rw",
    "addr:street":"Lodge Forge Trading Estate Cradley Road",
    "iso:country":"GB",
    "sg:address":"Unit 16 Lodge Forge Trading Estate, Cradley Road",
    "sg:city":"Cradley Heath",
    "sg:classifiers":[
        {
            "category":"Home & Garden",
            "subcategory":"Garden Supply",
            "type":"Retail Goods"
        }
    ],
    "sg:phone":"+44 1384 413088",
    "sg:postcode":"B64 7RW",
    "sg:province":"West Midlands",
    "sg:tags":[
        "equipment",
        "playground"
    ],
    "wof:name":"B & S Chains (Midlands) Ltd.",
    "wof:placetype":"venue"
},
  "geometry": {"coordinates":[-2.081574,52.472416],"type":"Point"}
}