{
  "type": "Feature",
  "properties": {
    "addr:full":"67a High Street Stone Staffordshire ST15 8AD",
    "addr:housenumber":"67a",
    "addr:postcode":"st15 8ad",
    "addr:street":"High Street",
    "iso:country":"GB",
    "sg:address":"67a High Street",
    "sg:city":"Stone",
    "sg:classifiers":[
        {
            "category":"Real Estate",
            "subcategory":"Architect",
            "type":"Services"
        }
    ],
    "sg:phone":"+44 1785 816859",
    "sg:postcode":"ST15 8AD",
    "sg:province":"Staffordshire",
    "wof:name":"Edward G Anderson",
    "wof:placetype":"venue"
},
  "geometry": {"coordinates":[-2.1479949951,52.9031181335],"type":"Point"}
}