{
  "type": "Feature",
  "properties": {
    "addr:full":"20 Wood Street Bolton Lancashire BL1 1DY",
    "addr:housenumber":"20",
    "addr:postcode":"bl1 1dy",
    "addr:street":"Wood Street",
    "iso:country":"GB",
    "sg:address":"20 Wood Street",
    "sg:city":"Bolton",
    "sg:classifiers":[
        {
            "category":"Professional",
            "subcategory":"Lawyer & Legal Services",
            "type":"Services"
        }
    ],
    "sg:phone":"+44 1204 535147",
    "sg:postcode":"BL1 1DY",
    "sg:province":"Lancashire",
    "wof:name":"Bolton Incorporated Law Society",
    "wof:placetype":"venue"
},
  "geometry": {"coordinates":[-2.425485,53.578644],"type":"Point"}
}