{
  "type": "Feature",
  "properties": {
    "addr:full":"88 West Street Fareham Hampshire PO16 0EP",
    "addr:housenumber":"88",
    "addr:postcode":"po16 0ep",
    "addr:street":"West Street",
    "iso:country":"GB",
    "sg:address":"88 West Street",
    "sg:city":"Fareham",
    "sg:classifiers":[
        {
            "category":"Communications",
            "subcategory":"Newspaper",
            "type":"Services"
        },
        {
            "category":"Wholesale",
            "subcategory":"Books, Periodicals, & Newspapers",
            "type":"Manufacturing & Wholesale Goods"
        }
    ],
    "sg:phone":"+44 1329 822555",
    "sg:postcode":"PO16 0EP",
    "sg:province":"Hampshire",
    "sg:tags":[
        "magazine",
        "publishing"
    ],
    "wof:name":"Portsmouth Publishing & Printing Ltd",
    "wof:placetype":"venue"
},
  "geometry": {"coordinates":[-1.180797,50.85247],"type":"Point"}
}