{
  "type": "Feature",
  "properties": {
    "iso:country":"GB",
    "sg:address":"Wellbank, Main Street, Howwood",
    "sg:city":"Johnstone",
    "sg:classifiers":[
        {
            "category":"Shopping",
            "subcategory":"Musical Instruments",
            "type":"Retail Goods"
        }
    ],
    "sg:phone":"+44 1505 702623",
    "sg:postcode":"PA9 1AW",
    "sg:province":"Renfrewshire",
    "sg:tags":[
        "piano",
        "tuning",
        "maintenance"
    ],
    "wof:name":"Graham Brown",
    "wof:placetype":"venue"
},
  "geometry": {"coordinates":[-4.561974,55.808956],"type":"Point"}
}