{
  "type": "Feature",
  "properties": {
    "iso:country":"GB",
    "sg:address":"5 Pier Street",
    "sg:city":"Ventnor",
    "sg:classifiers":[
        {
            "category":"Shopping",
            "subcategory":"Gifts & Souvenirs",
            "type":"Retail Goods"
        }
    ],
    "sg:phone":"+44 1983 856189",
    "sg:postcode":"PO38 1ST",
    "sg:province":"Isle of Wight",
    "sg:tags":[
        "shop"
    ],
    "wof:name":"Reed'S Hobbys",
    "wof:placetype":"venue"
},
  "geometry": {"coordinates":[-1.2055130005,50.5949249268],"type":"Point"}
}