{
  "type": "Feature",
  "properties": {
    "iso:country":"GB",
    "sg:address":"81 Brecon Road",
    "sg:city":"Abergavenny",
    "sg:classifiers":[
        {
            "category":"Professional",
            "subcategory":"Accounting & Tax Preparation",
            "type":"Services"
        }
    ],
    "sg:postcode":"NP7 7RD",
    "sg:province":"Herefordshire",
    "sg:tags":[
        "accountant"
    ],
    "wof:name":"Lesslie & Lesslie",
    "wof:placetype":"venue"
},
  "geometry": {"coordinates":[-3.0298199654,51.8254318237],"type":"Point"}
}