{
  "type": "Feature",
  "properties": {
    "iso:country":"GB",
    "sg:address":"11-12 Hogarth Place",
    "sg:city":"London",
    "sg:classifiers":[
        {
            "category":"Personal",
            "subcategory":"Beauty Salon",
            "type":"Services"
        }
    ],
    "sg:phone":"+44 20 8749 4588",
    "sg:postcode":"SW5 0QT",
    "sg:province":"Greater London",
    "wof:name":"Salon de Manila",
    "wof:placetype":"venue"
},
  "geometry": {"coordinates":[-0.192983,51.492825],"type":"Point"}
}