{
  "type": "Feature",
  "properties": {
    "addr:full":"600-602 Mansfield Road, Sherwood Nottingham Nottinghamshire NG5 2FS",
    "addr:housenumber":"600-602",
    "addr:postcode":"ng5 2fs",
    "addr:street":"Mansfield Road",
    "iso:country":"GB",
    "sg:address":"600-602 Mansfield Road, Sherwood",
    "sg:city":"Nottingham",
    "sg:classifiers":[
        {
            "category":"Shopping",
            "subcategory":"Computers & Home Electronics",
            "type":"Retail Goods"
        }
    ],
    "sg:phone":"+44 115 962 2150",
    "sg:postcode":"NG5 2FS",
    "sg:province":"Nottinghamshire",
    "sg:tags":[
        "hi-fi",
        "centre"
    ],
    "wof:name":"Forum Hi-Fi & Video Centre (Nottingham) Ltd.",
    "wof:placetype":"venue"
},
  "geometry": {"coordinates":[-1.1457159519,52.9818077087],"type":"Point"}
}