{
  "type": "Feature",
  "properties": {
    "addr:full":"Gordon Ho, Little Mead Indstl Est, Little Mead Cranleigh Surrey GU6 8ND",
    "addr:postcode":"gu6 8nd",
    "addr:street":"Little;Indstl Est Little Mead",
    "iso:country":"GB",
    "sg:address":"Gordon Ho, Little Mead Indstl Est, Little Mead",
    "sg:city":"Cranleigh",
    "sg:classifiers":[
        {
            "category":"Professional",
            "subcategory":"Management & Consulting",
            "type":"Services"
        }
    ],
    "sg:phone":"+44 1483 277411",
    "sg:postcode":"GU6 8ND",
    "sg:province":"Surrey",
    "sg:tags":[
        "consultant",
        "business"
    ],
    "wof:name":"Bridges Wright & Co Ltd",
    "wof:placetype":"venue"
},
  "geometry": {"coordinates":[-0.482998997,51.1415405273],"type":"Point"}
}