{
  "type": "Feature",
  "properties": {
    "iso:country":"GB",
    "sg:address":"111 Brixton Hill",
    "sg:city":"London",
    "sg:classifiers":[
        {
            "category":"Shopping",
            "subcategory":"Antiques",
            "type":"Retail Goods"
        }
    ],
    "sg:phone":"+44 20 8671 5173",
    "sg:postcode":"SW2 1AA",
    "sg:province":"Greater London",
    "wof:name":"Browns Too",
    "wof:placetype":"venue"
},
  "geometry": {"coordinates":[-0.119665,51.454571],"type":"Point"}
}