{
  "type": "Feature",
  "properties": {
    "addr:full":"40 Marlborough Road Bradford West Yorkshire BD8 7LE",
    "addr:housenumber":"40",
    "addr:postcode":"bd8 7le",
    "addr:street":"Marlborough Road",
    "iso:country":"GB",
    "sg:address":"40 Marlborough Road",
    "sg:city":"Bradford",
    "sg:classifiers":[
        {
            "category":"Community Center",
            "subcategory":"Youth",
            "type":"Public Place"
        }
    ],
    "sg:phone":"+44 1274 545720",
    "sg:postcode":"BD8 7LE",
    "sg:province":"West Yorkshire",
    "sg:tags":[
        "organisation",
        "centre"
    ],
    "wof:name":"Playspace",
    "wof:placetype":"venue"
},
  "geometry": {"coordinates":[-1.7663680315,53.8061599731],"type":"Point"}
}