{
  "type": "Feature",
  "properties": {
    "iso:country":"GB",
    "sg:address":"Shipbrook Rd, Rudheath",
    "sg:city":"Northwich",
    "sg:classifiers":[
        {
            "category":"Education",
            "subcategory":"School",
            "type":"Public Place"
        }
    ],
    "sg:phone":"+44 1606 42515",
    "sg:postcode":"CW9 7DT",
    "sg:province":"Cheshire",
    "sg:tags":[
        "local",
        "authority"
    ],
    "wof:name":"Rudheath County High School",
    "wof:placetype":"venue"
},
  "geometry": {"coordinates":[-2.49157,53.251366],"type":"Point"}
}