{
  "type": "Feature",
  "properties": {
    "addr:full":"6 The Broadway Woodhall Spa Lincolnshire LN10 6ST",
    "addr:housenumber":"6",
    "addr:postcode":"ln10 6st",
    "addr:street":"The Broadway",
    "iso:country":"GB",
    "sg:address":"6 The Broadway",
    "sg:city":"Woodhall Spa",
    "sg:classifiers":[
        {
            "category":"Restaurant",
            "type":"Food & Drink"
        }
    ],
    "sg:phone":"+44 1526 352223",
    "sg:postcode":"LN10 6ST",
    "sg:province":"Lincolnshire",
    "sg:tags":[
        "indian",
        "-"
    ],
    "wof:name":"India Village Restaurant & Takeaway",
    "wof:placetype":"venue"
},
  "geometry": {"coordinates":[-0.2146089971,53.1521568298],"type":"Point"}
}