{
  "type": "Feature",
  "properties": {
    "addr:full":"3 Kings Arcade Lancaster Lancashire LA1 1LE",
    "addr:housenumber":"3",
    "addr:postcode":"la1 1le",
    "addr:street":"Kings Arcade",
    "iso:country":"GB",
    "sg:address":"3 Kings Arcade",
    "sg:city":"Lancaster",
    "sg:classifiers":[
        {
            "category":"Professional",
            "subcategory":"Advertising",
            "type":"Services"
        },
        {
            "category":"Wholesale",
            "subcategory":"Books, Periodicals, & Newspapers",
            "type":"Manufacturing & Wholesale Goods"
        }
    ],
    "sg:postcode":"LA1 1LE",
    "sg:province":"Lancashire",
    "sg:tags":[
        "publishing"
    ],
    "wof:name":"FURNESS NEWSPAPERS LTD",
    "wof:placetype":"venue"
},
  "geometry": {"coordinates":[-2.802143,54.04797],"type":"Point"}
}