{
  "type": "Feature",
  "properties": {
    "iso:country":"GB",
    "sg:address":"24 Berkeley Square, Clifton",
    "sg:city":"Bristol",
    "sg:classifiers":[
        {
            "category":"Professional",
            "subcategory":"Advertising",
            "type":"Services"
        }
    ],
    "sg:phone":"+44 117 923 0027",
    "sg:postcode":"BS8 1HP",
    "sg:province":"City of Bristol",
    "sg:tags":[
        "agency"
    ],
    "wof:name":"Taylor & Taylor Advertising Ltd.",
    "wof:placetype":"venue"
},
  "geometry": {"coordinates":[-2.6060340405,51.4546966553],"type":"Point"}
}