{
  "type": "Feature",
  "properties": {
    "iso:country":"GB",
    "sg:address":"Old Rectory, Hall Rd",
    "sg:city":"Sudbury",
    "sg:classifiers":[
        {
            "category":"Building & Trades",
            "subcategory":"Equipment Rental",
            "type":"Services"
        }
    ],
    "sg:phone":"+44 1787 247255",
    "sg:postcode":"CO10 9NP",
    "sg:province":"Essex",
    "sg:tags":[
        "hire",
        "catering"
    ],
    "wof:name":"Ann Waller",
    "wof:placetype":"venue"
},
  "geometry": {"coordinates":[0.73439,52.038605],"type":"Point"}
}