{
  "type": "Feature",
  "properties": {
    "addr:full":"Birmingham International Airport, Departure Concourse Bookshop Birmingham West Midlands B26 3QJ",
    "addr:postcode":"b26 3qj",
    "addr:street":"Departure",
    "iso:country":"GB",
    "sg:address":"Birmingham International Airport, Departure Concourse Bookshop",
    "sg:city":"Birmingham",
    "sg:classifiers":[
        {
            "category":"Shopping",
            "subcategory":"Books",
            "type":"Retail Goods"
        }
    ],
    "sg:phone":"+44 121 767 7891",
    "sg:postcode":"B26 3QJ",
    "sg:province":"West Midlands",
    "sg:tags":[
        "bookseller"
    ],
    "wof:name":"W H Smith Trading Ltd.",
    "wof:placetype":"venue"
},
  "geometry": {"coordinates":[-1.7322460413,52.4529647827],"type":"Point"}
}