{
  "type": "Feature",
  "properties": {
    "addr:full":"Park Terrace Broxburn City of Edinburgh EH52 6EE",
    "addr:postcode":"eh52 6ee",
    "addr:street":"Park Terrace",
    "iso:country":"GB",
    "sg:address":"Park Terrace",
    "sg:city":"Broxburn",
    "sg:classifiers":[
        {
            "category":"Organizations",
            "subcategory":"Non-profit Organization",
            "type":"Services"
        }
    ],
    "sg:postcode":"EH52 6EE",
    "sg:province":"City of Edinburgh",
    "sg:tags":[
        "organisation",
        "voluntary",
        "charity"
    ],
    "wof:name":"Range Adventure Playground & Activity Gardens",
    "wof:placetype":"venue"
},
  "geometry": {"coordinates":[-3.4967489243,55.9353981018],"type":"Point"}
}