{
  "type": "Feature",
  "properties": {
    "addr:full":"9 Compstom Road Ambleside Cumbria LA22 9DJ",
    "addr:housenumber":"9",
    "addr:postcode":"la22 9dj",
    "addr:street":"Compstom Road",
    "iso:country":"GB",
    "sg:address":"9 Compstom Road",
    "sg:city":"Ambleside",
    "sg:classifiers":[
        {
            "category":"Sports & Exercise",
            "subcategory":"Bicycle Rental",
            "type":"Entertainment"
        }
    ],
    "sg:phone":"+44 15394 31505",
    "sg:postcode":"LA22 9DJ",
    "sg:province":"Cumbria",
    "sg:tags":[
        "renting",
        "cycle"
    ],
    "wof:name":"Bike Treks Mountain Bike Hire",
    "wof:placetype":"venue"
},
  "geometry": {"coordinates":[-2.964001894,54.4310722351],"type":"Point"}
}