{
  "type": "Feature",
  "properties": {
    "iso:country":"GB",
    "sg:address":"77 Watergate, Methley",
    "sg:city":"Leeds",
    "sg:classifiers":[
        {
            "category":"Banks & Credit Unions",
            "subcategory":"Financial Services",
            "type":"Services"
        }
    ],
    "sg:phone":"+44 1977 520220",
    "sg:postcode":"LS26 9DG",
    "sg:province":"West Yorkshire",
    "sg:tags":[
        "consultant"
    ],
    "wof:name":"T.T. Finance Mortgage Services",
    "wof:placetype":"venue"
},
  "geometry": {"coordinates":[-1.400649,53.7397],"type":"Point"}
}