{
  "type": "Feature",
  "properties": {
    "addr:full":"Norman-d-gate, Bedford Road Northampton Northamptonshire NN1 5NT",
    "addr:postcode":"nn1 5nt",
    "addr:street":"Bedford Road",
    "iso:country":"GB",
    "sg:address":"Norman-d-gate, Bedford Road",
    "sg:city":"Northampton",
    "sg:classifiers":[
        {
            "category":"Professional",
            "subcategory":"Printing & Photocopies",
            "type":"Services"
        }
    ],
    "sg:phone":"+44 1604 38703",
    "sg:postcode":"NN1 5NT",
    "sg:province":"Northamptonshire",
    "sg:tags":[
        "printer"
    ],
    "wof:name":"Xpres Printers Ltd.",
    "wof:placetype":"venue"
},
  "geometry": {"coordinates":[-0.882313,52.233467],"type":"Point"}
}