{
  "type": "Feature",
  "properties": {
    "iso:country":"GB",
    "sg:address":"Kennet Close, Tewkesbury Business Park",
    "sg:city":"Tewkesbury",
    "sg:classifiers":[
        {
            "category":"Shopping",
            "subcategory":"Crafts & Fabrics",
            "type":"Retail Goods"
        }
    ],
    "sg:phone":"+44 1684 299555",
    "sg:postcode":"GL20 8HF",
    "sg:province":"Gloucestershire",
    "sg:tags":[
        "ceramic"
    ],
    "wof:name":"Sterling Distribution",
    "wof:placetype":"venue"
},
  "geometry": {"coordinates":[-2.1254410744,52.0037269592],"type":"Point"}
}