{
  "type": "Feature",
  "properties": {
    "iso:country":"GB",
    "sg:address":"Barry Island Pleasure Park",
    "sg:city":"Barry",
    "sg:classifiers":[
        {
            "category":"Restaurant",
            "type":"Food & Drink"
        }
    ],
    "sg:phone":"+44 1446 721888",
    "sg:postcode":"CF62 5ZD",
    "sg:province":"The Vale of Glamorgan",
    "wof:name":"K R Restaurant (Bookings)",
    "wof:placetype":"venue"
},
  "geometry": {"coordinates":[-3.277994,51.401783],"type":"Point"}
}