{
  "type": "Feature",
  "properties": {
    "addr:full":"18 Autumn Close Enfield Greater London EN1 4JX",
    "addr:housenumber":"18",
    "addr:postcode":"en1 4jx",
    "addr:street":"Autumn Close",
    "iso:country":"GB",
    "sg:address":"18 Autumn Close",
    "sg:city":"Enfield",
    "sg:classifiers":[
        {
            "category":"Retail",
            "subcategory":"Driving School",
            "type":"Services"
        }
    ],
    "sg:phone":"+44 20 8363 9278",
    "sg:postcode":"EN1 4JX",
    "sg:province":"Greater London",
    "wof:name":"Victors School Of Motoring",
    "wof:placetype":"venue"
},
  "geometry": {"coordinates":[-0.0574450009,51.6603279114],"type":"Point"}
}