{
  "type": "Feature",
  "properties": {
    "iso:country":"GB",
    "sg:address":"48 Fernside Road, Winton",
    "sg:city":"Bournemouth",
    "sg:classifiers":[
        {
            "category":"Education",
            "subcategory":"Dance Studio",
            "type":"Public Place"
        }
    ],
    "sg:phone":"+44 1202 515514",
    "sg:postcode":"BH9 2LB",
    "sg:province":"Dorset",
    "sg:tags":[
        "school",
        "dancing"
    ],
    "wof:name":"Ford's School of Dancing",
    "wof:placetype":"venue"
},
  "geometry": {"coordinates":[-1.888978,50.744186],"type":"Point"}
}