{
  "type": "Feature",
  "properties": {
    "iso:country":"GB",
    "sg:address":"Unit 3 Comet House, Calleva Park, Aldermaston",
    "sg:city":"Reading",
    "sg:classifiers":[
        {
            "category":"Professional",
            "subcategory":"Management & Consulting",
            "type":"Services"
        }
    ],
    "sg:phone":"+44 118 981 0011",
    "sg:postcode":"RG7 8JA",
    "sg:province":"Berkshire",
    "sg:tags":[
        "marketing",
        "consultant"
    ],
    "wof:name":"Eurotech Marketing Services Ltd.",
    "wof:placetype":"venue"
},
  "geometry": {"coordinates":[-1.16434,51.361301],"type":"Point"}
}