{
  "type": "Feature",
  "properties": {
    "iso:country":"GB",
    "sg:address":"41 Dougrie Drive, Castlemilk",
    "sg:city":"Glasgow",
    "sg:classifiers":[
        {
            "category":"Bars & Pubs",
            "type":"Food & Drink"
        }
    ],
    "sg:phone":"+44 141 634 6196",
    "sg:postcode":"G45 9AD",
    "sg:province":"Glasgow City",
    "sg:tags":[
        "pubs",
        "inn"
    ],
    "wof:name":"The Oasis Bar",
    "wof:placetype":"venue"
},
  "geometry": {"coordinates":[-4.2351369858,55.8075065613],"type":"Point"}
}