{
  "type": "Feature",
  "properties": {
    "addr:full":"162 Eastfield Drive Penicuik Midlothian EH26 8DW",
    "addr:housenumber":"162",
    "addr:postcode":"eh26 8dw",
    "addr:street":"Eastfield Drive",
    "iso:country":"GB",
    "sg:address":"162 Eastfield Drive",
    "sg:city":"Penicuik",
    "sg:classifiers":[
        {
            "category":"Shopping",
            "subcategory":"News",
            "type":"Retail Goods"
        }
    ],
    "sg:phone":"+44 1968 674437",
    "sg:postcode":"EH26 8DW",
    "sg:province":"Midlothian",
    "sg:tags":[
        "newsagent"
    ],
    "wof:name":"Eastfield Newsagents",
    "wof:placetype":"venue"
},
  "geometry": {"coordinates":[-3.2121520042,55.8307876587],"type":"Point"}
}