{
  "type": "Feature",
  "properties": {
    "addr:full":"24 George Street Leamington Spa Warwickshire CV31 1HA",
    "addr:housenumber":"24",
    "addr:postcode":"cv31 1ha",
    "addr:street":"George Street",
    "iso:country":"GB",
    "sg:address":"24 George Street",
    "sg:city":"Leamington Spa",
    "sg:classifiers":[
        {
            "category":"Manufacturing",
            "subcategory":"Building Materials",
            "type":"Manufacturing & Wholesale Goods"
        }
    ],
    "sg:phone":"+44 1926 883286",
    "sg:postcode":"CV31 1HA",
    "sg:province":"Warwickshire",
    "sg:tags":[
        "tile",
        "mnfrs",
        "builder",
        "merchant"
    ],
    "wof:name":"M K C Fitting Service",
    "wof:placetype":"venue"
},
  "geometry": {"coordinates":[-1.530209,52.284767],"type":"Point"}
}