{
  "type": "Feature",
  "properties": {
    "addr:full":"8 Williscroft Place, Bellamour Way Rugeley Staffordshire WS15 3LN",
    "addr:housenumber":"8",
    "addr:postcode":"ws15 3ln",
    "addr:street":"Williscroft Place Bellamour Way",
    "iso:country":"GB",
    "sg:address":"8 Williscroft Place, Bellamour Way",
    "sg:city":"Rugeley",
    "sg:classifiers":[
        {
            "category":"Professional",
            "subcategory":"Engineering",
            "type":"Services"
        }
    ],
    "sg:postcode":"WS15 3LN",
    "sg:province":"Staffordshire",
    "sg:tags":[
        "civil",
        "engineer"
    ],
    "wof:name":"Colton Pavings",
    "wof:placetype":"venue"
},
  "geometry": {"coordinates":[-1.926344,52.781769],"type":"Point"}
}