{
  "type": "Feature",
  "properties": {
    "iso:country":"GB",
    "sg:address":"8 Williscroft Place, Bellamour Way",
    "sg:city":"Rugeley",
    "sg:classifiers":[
        {
            "category":"Professional",
            "subcategory":"Engineering",
            "type":"Services"
        }
    ],
    "sg:postcode":"WS15 3LN",
    "sg:province":"Staffordshire",
    "sg:tags":[
        "civil",
        "engineer"
    ],
    "wof:name":"Colton Pavings",
    "wof:placetype":"venue"
},
  "geometry": {"coordinates":[-1.926344,52.781769],"type":"Point"}
}