{
  "type": "Feature",
  "properties": {
    "addr:full":"117 Charing Cross Road London Greater London WC2H 0EA",
    "addr:housenumber":"117",
    "addr:postcode":"wc2h 0ea",
    "addr:street":"Charing Cross Road",
    "iso:country":"GB",
    "sg:address":"117 Charing Cross Road",
    "sg:city":"London",
    "sg:classifiers":[
        {
            "category":"Professional",
            "subcategory":"Art Services",
            "type":"Services"
        }
    ],
    "sg:phone":"+44 20 7734 6606",
    "sg:postcode":"WC2H 0EA",
    "sg:province":"Greater London",
    "sg:tags":[
        "graphic",
        "designer"
    ],
    "wof:name":"2 D Design Ltd.",
    "wof:placetype":"venue"
},
  "geometry": {"coordinates":[-0.1289899945,51.5129699707],"type":"Point"}
}