{
  "type": "Feature",
  "properties": {
    "addr:full":"45 Scarle Rd Wembley Greater London HA0 4SR",
    "addr:housenumber":"45",
    "addr:postcode":"ha0 4sr",
    "addr:street":"Scarle Rd",
    "iso:country":"GB",
    "sg:address":"45 Scarle Rd",
    "sg:city":"Wembley",
    "sg:classifiers":[
        {
            "category":"Professional",
            "subcategory":"Computer Services",
            "type":"Services"
        }
    ],
    "sg:phone":"+44 20 8902 1439",
    "sg:postcode":"HA0 4SR",
    "sg:province":"Greater London",
    "sg:tags":[
        "system",
        "software"
    ],
    "wof:name":"Multicom Business Systems Ltd",
    "wof:placetype":"venue"
},
  "geometry": {"coordinates":[-0.3005720079,51.5481109619],"type":"Point"}
}