{
  "type": "Feature",
  "properties": {
    "addr:full":"395 Hornsey Rd London Greater London N19 4DX",
    "addr:housenumber":"395",
    "addr:postcode":"n19 4dx",
    "addr:street":"Hornsey Rd",
    "iso:country":"GB",
    "sg:address":"395 Hornsey Rd",
    "sg:city":"London",
    "sg:classifiers":[
        {
            "category":"Building & Trades",
            "subcategory":"Locksmith",
            "type":"Services"
        }
    ],
    "sg:postcode":"N19 4DX",
    "sg:province":"Greater London",
    "wof:name":"Hrele,B,",
    "wof:placetype":"venue"
},
  "geometry": {"coordinates":[-0.121053,51.565945],"type":"Point"}
}