{
  "type": "Feature",
  "properties": {
    "iso:country":"GB",
    "sg:address":"Holmshaw Lane, Haslington",
    "sg:city":"Crewe",
    "sg:classifiers":[
        {
            "category":"Real Estate",
            "subcategory":"Developer",
            "type":"Services"
        }
    ],
    "sg:phone":"+44 1270 589282",
    "sg:postcode":"CW1 5TN",
    "sg:province":"Cheshire",
    "sg:tags":[
        "property"
    ],
    "wof:name":"Haslington Developments Ltd.",
    "wof:placetype":"venue"
},
  "geometry": {"coordinates":[-2.394339,53.097462],"type":"Point"}
}