{
  "type": "Feature",
  "properties": {
    "addr:full":"36 Park View Road Welling Kent DA16 1RT",
    "addr:housenumber":"36",
    "addr:postcode":"da16 1rt",
    "addr:street":"Park View Road",
    "iso:country":"GB",
    "sg:address":"36 Park View Road",
    "sg:city":"Welling",
    "sg:classifiers":[
        {
            "category":"Shopping",
            "subcategory":"News",
            "type":"Retail Goods"
        }
    ],
    "sg:postcode":"DA16 1RT",
    "sg:province":"Kent",
    "sg:tags":[
        "newsagent"
    ],
    "wof:name":"W C Forsey",
    "wof:placetype":"venue"
},
  "geometry": {"coordinates":[0.121694997,51.4602088928],"type":"Point"}
}