{
  "type": "Feature",
  "properties": {
    "iso:country":"GB",
    "sg:address":"38 Bazalgette Gardens",
    "sg:city":"New Malden",
    "sg:classifiers":[
        {
            "category":"Recreation",
            "subcategory":"Gun Range",
            "type":"Entertainment"
        }
    ],
    "sg:postcode":"KT3 5HF",
    "sg:province":"Surrey",
    "sg:tags":[
        "operator",
        "tour"
    ],
    "wof:name":"Highdrive Ltd.",
    "wof:placetype":"venue"
},
  "geometry": {"coordinates":[-0.267533,51.394817],"type":"Point"}
}