{
  "type": "Feature",
  "properties": {
    "addr:full":"55 Red Lion Street London Greater London WC1R 4PD",
    "addr:housenumber":"55",
    "addr:postcode":"wc1r 4pd",
    "addr:street":"Red Lion Street",
    "iso:country":"GB",
    "sg:address":"55 Red Lion Street",
    "sg:city":"London",
    "sg:classifiers":[
        {
            "category":"Real Estate",
            "subcategory":"Surveying",
            "type":"Services"
        }
    ],
    "sg:postcode":"WC1R 4PD",
    "sg:province":"Greater London",
    "sg:tags":[
        "surveyor",
        "quantity"
    ],
    "wof:name":"W King",
    "wof:placetype":"venue"
},
  "geometry": {"coordinates":[-0.117355,51.519421],"type":"Point"}
}