{
  "type": "Feature",
  "properties": {
    "addr:full":"39 Chapel La Bradford West Yorkshire BD13 2QA",
    "addr:housenumber":"39",
    "addr:postcode":"bd13 2qa",
    "addr:street":"Chapel La Bradford West",
    "iso:country":"GB",
    "sg:address":"39 Chapel La",
    "sg:city":"Bradford",
    "sg:classifiers":[
        {
            "category":"Building & Trades",
            "subcategory":"Plumbing",
            "type":"Services"
        }
    ],
    "sg:postcode":"BD13 2QA",
    "sg:province":"West Yorkshire",
    "sg:tags":[
        "heating"
    ],
    "wof:name":"Mundy,Brian & Nicholas,",
    "wof:placetype":"venue"
},
  "geometry": {"coordinates":[-1.744587,53.795269],"type":"Point"}
}