{
  "type": "Feature",
  "properties": {
    "addr:full":"85 Granville Road Northwich Cheshire CW9 8EU",
    "addr:housenumber":"85",
    "addr:postcode":"cw9 8eu",
    "addr:street":"Granville Road",
    "iso:country":"GB",
    "sg:address":"85 Granville Road",
    "sg:city":"Northwich",
    "sg:classifiers":[
        {
            "category":"Home & Garden",
            "subcategory":"Household Appliances",
            "type":"Retail Goods"
        },
        {
            "category":"Retail",
            "subcategory":"Repair Shop",
            "type":"Services"
        }
    ],
    "sg:phone":"+44 1606 46988",
    "sg:postcode":"CW9 8EU",
    "sg:province":"Cheshire",
    "sg:tags":[
        "machine",
        "electrical",
        "washing"
    ],
    "wof:name":"BRYANS DOMESTIC APPLIANCE SERVICE",
    "wof:placetype":"venue"
},
  "geometry": {"coordinates":[-2.5080740452,53.2427444458],"type":"Point"}
}