{
  "type": "Feature",
  "properties": {
    "addr:full":"Graham Park Way, Colindale London Greater London NW9 5RA",
    "addr:postcode":"nw9 5ra",
    "addr:street":"Park Way",
    "iso:country":"GB",
    "sg:address":"Graham Park Way, Colindale",
    "sg:city":"London",
    "sg:classifiers":[
        {
            "category":"Education",
            "subcategory":"Special Training",
            "type":"Public Place"
        }
    ],
    "sg:phone":"+44 20 8205 9219",
    "sg:postcode":"NW9 5RA",
    "sg:province":"Greater London",
    "sg:tags":[
        "product",
        "centre"
    ],
    "wof:name":"Business Training & Advisory Service",
    "wof:placetype":"venue"
},
  "geometry": {"coordinates":[-0.241809994,51.603099823],"type":"Point"}
}