{
  "type": "Feature",
  "properties": {
    "iso:country":"GB",
    "sg:address":"12-14 Wilford Road, Ruddington",
    "sg:city":"Nottingham",
    "sg:classifiers":[
        {
            "category":"Communications",
            "type":"Services"
        }
    ],
    "sg:phone":"+44 115 921 1085",
    "sg:postcode":"NG11 6ER",
    "sg:province":"Nottinghamshire",
    "sg:tags":[
        "tv",
        "video",
        "radio"
    ],
    "wof:name":"R Grice & Sons Ltd.",
    "wof:placetype":"venue"
},
  "geometry": {"coordinates":[-1.149529,52.893276],"type":"Point"}
}