{
  "type": "Feature",
  "properties": {
    "addr:full":"16 Rudlands, Brookwood Ipswich Suffolk IP8 3RQ",
    "addr:housenumber":"16",
    "addr:postcode":"ip8 3rq",
    "addr:street":"Rudlands Brookwood",
    "iso:country":"GB",
    "sg:address":"16 Rudlands, Brookwood",
    "sg:city":"Ipswich",
    "sg:classifiers":[
        {
            "category":"Home & Garden",
            "subcategory":"Building Materials",
            "type":"Retail Goods"
        },
        {
            "category":"Building & Trades",
            "subcategory":"Construction",
            "type":"Services"
        }
    ],
    "sg:postcode":"IP8 3RQ",
    "sg:province":"Suffolk",
    "sg:tags":[
        "dry",
        "plasterers",
        "installers",
        "lining",
        "insulation",
        "screeders"
    ],
    "wof:name":"Rudland Plasterers",
    "wof:placetype":"venue"
},
  "geometry": {"coordinates":[1.1094989777,52.0375213623],"type":"Point"}
}