{
  "type": "Feature",
  "properties": {
    "addr:full":"5 North Bailey Durham Durham DH1 3EY",
    "addr:housenumber":"5",
    "addr:postcode":"dh1 3ey",
    "addr:street":"North Bailey",
    "iso:country":"GB",
    "sg:address":"5 North Bailey",
    "sg:city":"Durham",
    "sg:classifiers":[
        {
            "category":"Professional",
            "subcategory":"Lawyer & Legal Services",
            "type":"Services"
        }
    ],
    "sg:phone":"+44 191 384 7455",
    "sg:postcode":"DH1 3EY",
    "sg:province":"Durham",
    "sg:tags":[
        "solicitor"
    ],
    "wof:name":"J Davidson",
    "wof:placetype":"venue"
},
  "geometry": {"coordinates":[-1.574453,54.774067],"type":"Point"}
}