{
  "type": "Feature",
  "properties": {
    "addr:full":"Middlemore Road Smethwick West Midlands B66 2DQ",
    "addr:postcode":"b66 2dq",
    "addr:street":"Middlemore Road",
    "iso:country":"GB",
    "sg:address":"Middlemore Road",
    "sg:city":"Smethwick",
    "sg:classifiers":[
        {
            "category":"Wholesale",
            "subcategory":"Medical Equipment & Supplies",
            "type":"Manufacturing & Wholesale Goods"
        }
    ],
    "sg:phone":"+44 121 558 3601",
    "sg:postcode":"B66 2DQ",
    "sg:province":"West Midlands",
    "sg:tags":[
        "dental"
    ],
    "wof:name":"Plas-dent Co. Ltd.",
    "wof:placetype":"venue"
},
  "geometry": {"coordinates":[-1.9631379843,52.5049285889],"type":"Point"}
}