{
  "type": "Feature",
  "properties": {
    "iso:country":"GB",
    "sg:address":"Denmark Street",
    "sg:city":"Maidenhead",
    "sg:classifiers":[
        {
            "category":"Professional",
            "subcategory":"Engineering",
            "type":"Services"
        }
    ],
    "sg:postcode":"SL6 7BN",
    "sg:province":"Berkshire",
    "sg:tags":[
        "precision",
        "engineer"
    ],
    "wof:name":"Langton Engineering",
    "wof:placetype":"venue"
},
  "geometry": {"coordinates":[-0.727038,51.529129],"type":"Point"}
}