{
  "type": "Feature",
  "properties": {
    "addr:full":"Dockland Business Centre, 12 Tiller Rd London Greater London E14 8PX",
    "addr:housenumber":"12",
    "addr:postcode":"e14 8px",
    "addr:street":"Tiller Rd",
    "iso:country":"GB",
    "sg:address":"Dockland Business Centre, 12 Tiller Rd",
    "sg:city":"London",
    "sg:classifiers":[
        {
            "category":"Communications",
            "type":"Services"
        }
    ],
    "sg:postcode":"E14 8PX",
    "sg:province":"Greater London",
    "sg:tags":[
        "telecommunication"
    ],
    "wof:name":"Active Blend",
    "wof:placetype":"venue"
},
  "geometry": {"coordinates":[-0.025344,51.496178],"type":"Point"}
}