{
  "type": "Feature",
  "properties": {
    "iso:country":"GB",
    "sg:address":"Units 2 & 3,12 Bull Lane Indstl Est, Acton",
    "sg:city":"Sudbury",
    "sg:classifiers":[
        {
            "category":"Professional",
            "subcategory":"Computer Services",
            "type":"Services"
        }
    ],
    "sg:phone":"+44 1787 312783",
    "sg:postcode":"CO10 0BD",
    "sg:province":"Essex",
    "sg:tags":[
        "system",
        "software"
    ],
    "wof:name":"Dps Computer Systems (East Anglia) Ltd",
    "wof:placetype":"venue"
},
  "geometry": {"coordinates":[0.723405,52.079628],"type":"Point"}
}