{
  "type": "Feature",
  "properties": {
    "iso:country":"GB",
    "sg:address":"8 Shadwell Lane, Moortown",
    "sg:city":"Leeds",
    "sg:classifiers":[
        {
            "category":"Organizations",
            "subcategory":"Community Association",
            "type":"Services"
        }
    ],
    "sg:postcode":"LS17 6DR",
    "sg:province":"North Yorkshire",
    "sg:tags":[
        "relation",
        "public"
    ],
    "wof:name":"Sinclair Mason Ltd.",
    "wof:placetype":"venue"
},
  "geometry": {"coordinates":[-1.533465,53.844349],"type":"Point"}
}