{
  "type": "Feature",
  "properties": {
    "addr:full":"3 Crackenedge La Dewsbury West Yorkshire WF13 1QD",
    "addr:housenumber":"3",
    "addr:postcode":"wf13 1qd",
    "addr:street":"Crackenedge La Dewsbury West",
    "iso:country":"GB",
    "sg:address":"3 Crackenedge La",
    "sg:city":"Dewsbury",
    "sg:classifiers":[
        {
            "category":"Shopping",
            "subcategory":"Hobbies, Toys, & Games",
            "type":"Retail Goods"
        }
    ],
    "sg:postcode":"WF13 1QD",
    "sg:province":"West Yorkshire",
    "sg:tags":[
        "computer"
    ],
    "wof:name":"Ralph,Thomas,",
    "wof:placetype":"venue"
},
  "geometry": {"coordinates":[-1.629379034,53.6965713501],"type":"Point"}
}