{
  "type": "Feature",
  "properties": {
    "addr:full":"Angerstein Business Park London Greater London SE10 0RT",
    "addr:postcode":"se10 0rt",
    "addr:street":"Business Park",
    "iso:country":"GB",
    "sg:address":"Angerstein Business Park",
    "sg:city":"London",
    "sg:classifiers":[
        {
            "category":"Freight",
            "type":"Transportation"
        }
    ],
    "sg:phone":"+44 20 8858 2868",
    "sg:postcode":"SE10 0RT",
    "sg:province":"Greater London",
    "sg:tags":[
        "haulage",
        "road"
    ],
    "wof:name":"G Roberts Transport",
    "wof:placetype":"venue"
},
  "geometry": {"coordinates":[0.0177200008,51.4882087708],"type":"Point"}
}