{
  "type": "Feature",
  "properties": {
    "iso:country":"GB",
    "sg:address":"Spar Stores 19 Wordsley Green S, Hopping Centre",
    "sg:city":"Stourbridge",
    "sg:classifiers":[
        {
            "category":"Food & Beverages",
            "subcategory":"Supermarket",
            "type":"Retail Goods"
        }
    ],
    "sg:phone":"+44 1384 401933",
    "sg:postcode":"DY8 5PD",
    "sg:province":"Staffordshire",
    "wof:name":"Jacques & Son Ltd.",
    "wof:placetype":"venue"
},
  "geometry": {"coordinates":[-2.16479,52.480579],"type":"Point"}
}