{
  "type": "Feature",
  "properties": {
    "addr:full":"2 Imperial House, Main Street Grange-over-sands Cumbria LA11 6DP",
    "addr:housenumber":"2",
    "addr:postcode":"la11 6dp",
    "addr:street":"Imperial;Main Street",
    "iso:country":"GB",
    "sg:address":"2 Imperial House, Main Street",
    "sg:city":"Grange-over-sands",
    "sg:classifiers":[
        {
            "category":"Health Services",
            "subcategory":"Dentist",
            "type":"Services"
        }
    ],
    "sg:postcode":"LA11 6DP",
    "sg:province":"Cumbria",
    "wof:name":"Humphreys Entwistle & Broadbent",
    "wof:placetype":"venue"
},
  "geometry": {"coordinates":[-2.9216399193,54.1841583252],"type":"Point"}
}