{
  "type": "Feature",
  "properties": {
    "addr:full":"1 Bankfield Lane Huddersfield West Yorkshire HD5 0JE",
    "addr:housenumber":"1",
    "addr:postcode":"hd5 0je",
    "addr:street":"Bankfield Lane",
    "iso:country":"GB",
    "sg:address":"1 Bankfield Lane",
    "sg:city":"Huddersfield",
    "sg:classifiers":[
        {
            "category":"Shopping",
            "subcategory":"Pharmacy",
            "type":"Retail Goods"
        }
    ],
    "sg:phone":"+44 1484 424912",
    "sg:postcode":"HD5 0JE",
    "sg:province":"West Yorkshire",
    "sg:tags":[
        "pharmacist",
        "chemist"
    ],
    "wof:name":"Kirkheaton Pharmacy",
    "wof:placetype":"venue"
},
  "geometry": {"coordinates":[-1.728585,53.658516],"type":"Point"}
}