{
  "type": "Feature",
  "properties": {
    "iso:country":"GB",
    "sg:address":"Wynnstay Road",
    "sg:city":"Colwyn Bay",
    "sg:classifiers":[
        {
            "category":"Food & Beverages",
            "subcategory":"Bakery",
            "type":"Retail Goods"
        }
    ],
    "sg:phone":"+44 1492 532760",
    "sg:postcode":"LL29 8NB",
    "sg:province":"Conwy",
    "sg:tags":[
        "baker"
    ],
    "wof:name":"Corner Cupboard Bakery",
    "wof:placetype":"venue"
},
  "geometry": {"coordinates":[-3.729899,53.296761],"type":"Point"}
}