{
  "type": "Feature",
  "properties": {
    "iso:country":"GB",
    "sg:address":"Galford Farm",
    "sg:city":"Okehampton",
    "sg:classifiers":[
        {
            "category":"Farming",
            "subcategory":"Livestock Farm",
            "type":"Manufacturing & Wholesale Goods"
        }
    ],
    "sg:phone":"+44 1566 783264",
    "sg:postcode":"EX20 4PL",
    "sg:province":"Devon",
    "sg:tags":[
        "others"
    ],
    "wof:name":"F J Harding",
    "wof:placetype":"venue"
},
  "geometry": {"coordinates":[-4.1201691628,50.6798706055],"type":"Point"}
}