{
  "type": "Feature",
  "properties": {
    "iso:country":"GB",
    "sg:address":"12 Maurice Gaymer Rd, Gaymer's Indstl Es",
    "sg:city":"Attleborough",
    "sg:classifiers":[
        {
            "category":"Shopping",
            "subcategory":"Department Store",
            "type":"Retail Goods"
        }
    ],
    "sg:postcode":"NR17 2QZ",
    "sg:province":"Norfolk",
    "wof:name":"Britannia Lighting Ltd",
    "wof:placetype":"venue"
},
  "geometry": {"coordinates":[1.0202009678,52.511592865],"type":"Point"}
}