{
  "type": "Feature",
  "properties": {
    "iso:country":"GB",
    "sg:address":"Arts Centre, University Park",
    "sg:city":"Nottingham",
    "sg:classifiers":[
        {
            "category":"Landmark",
            "subcategory":"Tourist Attraction",
            "type":"Public Place"
        }
    ],
    "sg:phone":"+44 115 951 5791",
    "sg:postcode":"NG7 2RD",
    "sg:province":"Nottinghamshire",
    "sg:tags":[
        "interest"
    ],
    "wof:name":"Angear Visitors Centre",
    "wof:placetype":"venue"
},
  "geometry": {"coordinates":[-1.1877399683,52.9421005249],"type":"Point"}
}