{
  "type": "Feature",
  "properties": {
    "iso:country":"GB",
    "sg:address":"The Barn Cedars Courtyard, Brockford",
    "sg:city":"Stowmarket",
    "sg:classifiers":[
        {
            "category":"Building & Trades",
            "subcategory":"Construction",
            "type":"Services"
        }
    ],
    "sg:postcode":"IP14 5PQ",
    "sg:province":"Suffolk",
    "sg:tags":[
        "window",
        "replacement"
    ],
    "wof:name":"Ventrolla",
    "wof:placetype":"venue"
},
  "geometry": {"coordinates":[1.102779,52.233227],"type":"Point"}
}