{
  "type": "Feature",
  "properties": {
    "iso:country":"GB",
    "sg:address":"10 Oken Rd",
    "sg:city":"Warwick",
    "sg:classifiers":[
        {
            "category":"Retail",
            "subcategory":"Driving School",
            "type":"Services"
        }
    ],
    "sg:postcode":"CV34 5EA",
    "sg:province":"Warwickshire",
    "wof:name":"Ashwell,V,",
    "wof:placetype":"venue"
},
  "geometry": {"coordinates":[-1.591779,52.28894],"type":"Point"}
}