{
  "type": "Feature",
  "properties": {
    "iso:country":"GB",
    "sg:address":"10 Waterside Close",
    "sg:city":"Barking",
    "sg:classifiers":[
        {
            "category":"Bus Charters",
            "type":"Transportation"
        }
    ],
    "sg:phone":"+44 20 8517 3534",
    "sg:postcode":"IG11 9EQ",
    "sg:province":"Essex",
    "sg:tags":[
        "hire",
        "coach"
    ],
    "wof:name":"Paul Phillips",
    "wof:placetype":"venue"
},
  "geometry": {"coordinates":[0.1075240001,51.5503692627],"type":"Point"}
}