{
  "type": "Feature",
  "properties": {
    "addr:full":"10 The Broadway Woodhall Spa Lincolnshire LN10 6ST",
    "addr:housenumber":"10",
    "addr:postcode":"ln10 6st",
    "addr:street":"The Broadway",
    "iso:country":"GB",
    "sg:address":"10 The Broadway",
    "sg:city":"Woodhall Spa",
    "sg:classifiers":[
        {
            "category":"Food & Beverages",
            "subcategory":"Fruits & Vegetables",
            "type":"Retail Goods"
        }
    ],
    "sg:postcode":"LN10 6ST",
    "sg:province":"Lincolnshire",
    "sg:tags":[
        "greengrocer"
    ],
    "wof:name":"Kitchen Gardens",
    "wof:placetype":"venue"
},
  "geometry": {"coordinates":[-0.2129170001,53.1524772644],"type":"Point"}
}