{
  "type": "Feature",
  "properties": {
    "iso:country":"GB",
    "sg:address":"38 Banks Road, West Kirby",
    "sg:city":"Wirral",
    "sg:classifiers":[
        {
            "category":"Sports & Exercise",
            "subcategory":"Gym",
            "type":"Entertainment"
        },
        {
            "category":"Education",
            "subcategory":"Dance Studio",
            "type":"Public Place"
        }
    ],
    "sg:phone":"+44 151 625 9600",
    "sg:postcode":"CH48 0RB",
    "sg:province":"Merseyside",
    "sg:tags":[
        "toning",
        "fitness",
        "health",
        "centre"
    ],
    "wof:name":"The Figure Firm",
    "wof:placetype":"venue"
},
  "geometry": {"coordinates":[-3.184603,53.37149],"type":"Point"}
}