{
  "type": "Feature",
  "properties": {
    "addr:full":"128 Castle St Forfar Angus DD8 3HS",
    "addr:housenumber":"128",
    "addr:postcode":"dd8 3hs",
    "addr:street":"Castle St",
    "iso:country":"GB",
    "sg:address":"128 Castle St",
    "sg:city":"Forfar",
    "sg:classifiers":[
        {
            "category":"Professional",
            "subcategory":"Lawyer & Legal Services",
            "type":"Services"
        }
    ],
    "sg:phone":"+44 1307 461234",
    "sg:postcode":"DD8 3HS",
    "sg:province":"Angus",
    "sg:tags":[
        "solicitor"
    ],
    "wof:name":"Blackadder Reid Johnston",
    "wof:placetype":"venue"
},
  "geometry": {"coordinates":[-2.888431,56.646965],"type":"Point"}
}