{
  "type": "Feature",
  "properties": {
    "iso:country":"GB",
    "sg:address":"New Sreet Garage",
    "sg:city":"Telford",
    "sg:classifiers":[
        {
            "category":"Retail",
            "subcategory":"Auto Repair",
            "type":"Services"
        }
    ],
    "sg:phone":"+44 1952 612377",
    "sg:postcode":"TF2 9AT",
    "sg:province":"Shropshire",
    "sg:tags":[
        "modification",
        "garage"
    ],
    "wof:name":"C Walsh",
    "wof:placetype":"venue"
},
  "geometry": {"coordinates":[-2.441628,52.695557],"type":"Point"}
}