{
  "type": "Feature",
  "properties": {
    "addr:full":"Bedminster Road Bristol City of Bristol BS3 5NR",
    "addr:postcode":"bs3 5nr",
    "addr:street":"Bedminster Road",
    "iso:country":"GB",
    "sg:address":"Bedminster Road",
    "sg:city":"Bristol",
    "sg:classifiers":[
        {
            "category":"Education",
            "subcategory":"School",
            "type":"Public Place"
        },
        {
            "category":"Government",
            "subcategory":"Office",
            "type":"Public Place"
        }
    ],
    "sg:phone":"+44 117 966 3679",
    "sg:postcode":"BS3 5NR",
    "sg:province":"City of Bristol",
    "sg:tags":[
        "local",
        "authority"
    ],
    "wof:name":"Bristol City Council",
    "wof:placetype":"venue"
},
  "geometry": {"coordinates":[-2.5996980667,51.4354782104],"type":"Point"}
}