{
  "type": "Feature",
  "properties": {
    "addr:full":"16 Thornly Leys Business Park Witney Oxfordshire OX28 4GE",
    "addr:housenumber":"16",
    "addr:postcode":"ox28 4ge",
    "addr:street":"Thornly Leys Business Park",
    "iso:country":"GB",
    "sg:address":"16 Thornly Leys Business Park",
    "sg:city":"Witney",
    "sg:classifiers":[
        {
            "category":"Manufacturing",
            "subcategory":"Glass & Minerals",
            "type":"Manufacturing & Wholesale Goods"
        }
    ],
    "sg:phone":"+44 1993 700800",
    "sg:postcode":"OX28 4GE",
    "sg:province":"Oxfordshire",
    "sg:tags":[
        "fibre",
        "optic"
    ],
    "wof:name":"Uniphase Ltd.",
    "wof:placetype":"venue"
},
  "geometry": {"coordinates":[-1.494524,51.776905],"type":"Point"}
}