{
  "type": "Feature",
  "properties": {
    "addr:full":"5 Bulmer Way Middlesbrough North Yorkshire TS1 5JT",
    "addr:housenumber":"5",
    "addr:postcode":"ts1 5jt",
    "addr:street":"Bulmer Way",
    "iso:country":"GB",
    "sg:address":"5 Bulmer Way",
    "sg:city":"Middlesbrough",
    "sg:classifiers":[
        {
            "category":"Personal",
            "type":"Services"
        }
    ],
    "sg:phone":"+44 1642 225867",
    "sg:postcode":"TS1 5JT",
    "sg:province":"North Yorkshire",
    "sg:tags":[
        "wedding"
    ],
    "wof:name":"County Print",
    "wof:placetype":"venue"
},
  "geometry": {"coordinates":[-1.2504429817,54.5754203796],"type":"Point"}
}