{
  "type": "Feature",
  "properties": {
    "addr:full":"Gatcombe Drive, Hilsea Portsmouth Hampshire PO2 0TX",
    "addr:postcode":"hampshire po2 0tx",
    "addr:street":"Gatcombe Drive",
    "iso:country":"GB",
    "sg:address":"Gatcombe Drive, Hilsea",
    "sg:city":"Portsmouth",
    "sg:classifiers":[
        {
            "category":"Social Services",
            "subcategory":"Retirement Home",
            "type":"Services"
        },
        {
            "category":"Government",
            "subcategory":"Office",
            "type":"Public Place"
        }
    ],
    "sg:phone":"+44 23 9266 0152",
    "sg:postcode":"PO2 0TX",
    "sg:province":"Hampshire",
    "sg:tags":[
        "residential",
        "local",
        "care"
    ],
    "wof:name":"Hilsea Lodge",
    "wof:placetype":"venue"
},
  "geometry": {"coordinates":[-1.070089,50.826736],"type":"Point"}
}