{
  "type": "Feature",
  "properties": {
    "iso:country":"GB",
    "sg:address":"31 Gauze Street",
    "sg:city":"Paisley",
    "sg:classifiers":[
        {
            "category":"Fast Food",
            "type":"Food & Drink"
        }
    ],
    "sg:phone":"+44 141 889 1111",
    "sg:postcode":"PA1 1ES",
    "sg:province":"Renfrewshire",
    "sg:tags":[
        "away",
        "meal",
        "outlet",
        "take"
    ],
    "wof:name":"The Sandwich Bar",
    "wof:placetype":"venue"
},
  "geometry": {"coordinates":[-4.4188051224,55.8464126587],"type":"Point"}
}