{
  "type": "Feature",
  "properties": {
    "addr:full":"Leycester House, Farmer Ward Rd Kenilworth Warwickshire CV8 2DH",
    "addr:postcode":"cv8 2dh",
    "addr:street":"Farmer Ward Rd",
    "iso:country":"GB",
    "sg:address":"Leycester House, Farmer Ward Rd",
    "sg:city":"Kenilworth",
    "sg:classifiers":[
        {
            "category":"Manufacturing",
            "subcategory":"Tools & Machinery",
            "type":"Manufacturing & Wholesale Goods"
        }
    ],
    "sg:phone":"+44 1926 511185",
    "sg:postcode":"CV8 2DH",
    "sg:province":"Warwickshire",
    "sg:tags":[
        "society",
        "friendly"
    ],
    "wof:name":"J R Dunbar & Co",
    "wof:placetype":"venue"
},
  "geometry": {"coordinates":[-1.57150805,52.337436676],"type":"Point"}
}