{
  "type": "Feature",
  "properties": {
    "iso:country":"GB",
    "sg:address":"28 High Street, Hadleigh",
    "sg:city":"Ipswich",
    "sg:classifiers":[
        {
            "category":"Shopping",
            "subcategory":"Crafts & Fabrics",
            "type":"Retail Goods"
        }
    ],
    "sg:phone":"+44 1473 824040",
    "sg:postcode":"IP7 5AP",
    "sg:province":"Suffolk",
    "sg:tags":[
        "shop",
        "retailer"
    ],
    "wof:name":"Threadneedle Fabrics",
    "wof:placetype":"venue"
},
  "geometry": {"coordinates":[0.955385,52.042042],"type":"Point"}
}