{
  "type": "Feature",
  "properties": {
    "addr:full":"170 Mount Rd, Penn Wolverhampton Staffordshire WV4 5RU",
    "addr:housenumber":"170",
    "addr:postcode":"wv4 5ru",
    "addr:street":"Mount Rd",
    "iso:country":"GB",
    "sg:address":"170 Mount Rd, Penn",
    "sg:city":"Wolverhampton",
    "sg:classifiers":[
        {
            "category":"Building & Trades",
            "subcategory":"Construction",
            "type":"Services"
        }
    ],
    "sg:postcode":"WV4 5RU",
    "sg:province":"Staffordshire",
    "sg:tags":[
        "builder"
    ],
    "wof:name":"Prior,M E,Builders and Contractors",
    "wof:placetype":"venue"
},
  "geometry": {"coordinates":[-2.148248,52.556686],"type":"Point"}
}