{
  "type": "Feature",
  "properties": {
    "iso:country":"GB",
    "sg:address":"Main Street, Harthill",
    "sg:city":"Shotts",
    "sg:classifiers":[
        {
            "category":"Government",
            "subcategory":"Office",
            "type":"Public Place"
        }
    ],
    "sg:phone":"+44 1501 752604",
    "sg:postcode":"ML7 5QE",
    "sg:province":"North Lanarkshire",
    "sg:tags":[
        "local"
    ],
    "wof:name":"Harthill Community Education Centre",
    "wof:placetype":"venue"
},
  "geometry": {"coordinates":[-3.751729,55.860336],"type":"Point"}
}