{
  "type": "Feature",
  "properties": {
    "iso:country":"GB",
    "sg:address":"Salters Hall, 4 Fore Street",
    "sg:city":"London",
    "sg:classifiers":[
        {
            "category":"Banks & Credit Unions",
            "subcategory":"Investment Brokerage",
            "type":"Services"
        }
    ],
    "sg:phone":"+44 20 7920 9209",
    "sg:postcode":"EC2Y 5DE",
    "sg:province":"Greater London",
    "sg:tags":[
        "stockbroker"
    ],
    "wof:name":"I A Pritchard Stockbrokers Ltd.",
    "wof:placetype":"venue"
},
  "geometry": {"coordinates":[-0.09248,51.518311],"type":"Point"}
}