{
  "type": "Feature",
  "properties": {
    "addr:full":"9 Callendar Riggs Falkirk Falkirk FK1 1UZ",
    "addr:housenumber":"9",
    "addr:postcode":"fk1 1uz",
    "addr:street":"Callendar Riggs",
    "iso:country":"GB",
    "sg:address":"9 Callendar Riggs",
    "sg:city":"Falkirk",
    "sg:classifiers":[
        {
            "category":"Shopping",
            "subcategory":"Clothing, Apparel, & Fashions",
            "type":"Retail Goods"
        }
    ],
    "sg:phone":"+44 1324 624588",
    "sg:postcode":"FK1 1UZ",
    "sg:province":"Falkirk",
    "sg:tags":[
        "menswear"
    ],
    "wof:name":"Brookes",
    "wof:placetype":"venue"
},
  "geometry": {"coordinates":[-3.7808039188,55.9991645813],"type":"Point"}
}