{
  "type": "Feature",
  "properties": {
    "iso:country":"GB",
    "sg:address":"12 Church Alley",
    "sg:city":"Liverpool",
    "sg:classifiers":[
        {
            "category":"Organizations",
            "subcategory":"Community Association",
            "type":"Services"
        },
        {
            "category":"Organizations",
            "subcategory":"Membership Organization",
            "type":"Services"
        }
    ],
    "sg:phone":"+44 151 709 7770",
    "sg:postcode":"L1 3DD",
    "sg:province":"Merseyside",
    "sg:tags":[
        "club",
        "social"
    ],
    "wof:name":"The Athenaeum",
    "wof:placetype":"venue"
},
  "geometry": {"coordinates":[-3.010643959,53.4630889893],"type":"Point"}
}