{
  "type": "Feature",
  "properties": {
    "iso:country":"GB",
    "sg:address":"21 Sedgemere Road",
    "sg:city":"Birmingham",
    "sg:classifiers":[
        {
            "category":"Arena",
            "subcategory":"Sports Club",
            "type":"Entertainment"
        }
    ],
    "sg:phone":"+44 121 783 4007",
    "sg:postcode":"B26 2AX",
    "sg:province":"West Midlands",
    "wof:name":"Sedgemere Sports & Social Club",
    "wof:placetype":"venue"
},
  "geometry": {"coordinates":[-1.7948219776,52.4728279114],"type":"Point"}
}