{
  "type": "Feature",
  "properties": {
    "iso:country":"GB",
    "sg:address":"50 Victoria Centre",
    "sg:city":"Nottingham",
    "sg:classifiers":[
        {
            "category":"Shopping",
            "subcategory":"Clothing, Apparel, & Fashions",
            "type":"Retail Goods"
        }
    ],
    "sg:phone":"+44 115 950 7446",
    "sg:postcode":"NG1 3QG",
    "sg:province":"Nottinghamshire",
    "sg:tags":[
        "menswear"
    ],
    "wof:name":"Ciro Citterio",
    "wof:placetype":"venue"
},
  "geometry": {"coordinates":[-1.146779,52.955219],"type":"Point"}
}