{
  "type": "Feature",
  "properties": {
    "iso:country":"GB",
    "sg:address":"7 Old Kings Head Court, 11 High Street",
    "sg:city":"Dorking",
    "sg:classifiers":[
        {
            "category":"Home & Garden",
            "subcategory":"Furniture",
            "type":"Retail Goods"
        }
    ],
    "sg:phone":"+44 1306 877994",
    "sg:postcode":"RH4 1AR",
    "sg:province":"Surrey",
    "wof:name":"The Fig Tree",
    "wof:placetype":"venue"
},
  "geometry": {"coordinates":[-0.3288139999,51.233341217],"type":"Point"}
}