{
  "type": "Feature",
  "properties": {
    "iso:country":"GB",
    "sg:address":"20 Brook St",
    "sg:city":"Sutton In Ashfield",
    "sg:classifiers":[
        {
            "category":"Health Services",
            "subcategory":"Medical Lab",
            "type":"Services"
        }
    ],
    "sg:phone":"+44 1623 552682",
    "sg:postcode":"NG17 1AL",
    "sg:province":"Nottinghamshire",
    "sg:tags":[
        "dental"
    ],
    "wof:name":"Ashfield Dental Laboratory",
    "wof:placetype":"venue"
},
  "geometry": {"coordinates":[-1.2646900415,53.1238021851],"type":"Point"}
}