{
  "type": "Feature",
  "properties": {
    "iso:country":"GB",
    "sg:address":"446 Westgate Road",
    "sg:city":"Newcastle-upon-tyne",
    "sg:classifiers":[
        {
            "category":"Banks & Credit Unions",
            "subcategory":"Bank",
            "type":"Services"
        }
    ],
    "sg:phone":"+44 845 755 5555",
    "sg:postcode":"NE4 9BN",
    "sg:province":"Tyne and Wear",
    "sg:tags":[
        "financial",
        "institution"
    ],
    "wof:name":"Barclays Bank plc",
    "wof:placetype":"venue"
},
  "geometry": {"coordinates":[-1.647963047,54.9748153687],"type":"Point"}
}