{
  "type": "Feature",
  "properties": {
    "iso:country":"GB",
    "sg:address":"Lower St Dennis",
    "sg:city":"Shipston-on-stour",
    "sg:classifiers":[
        {
            "category":"Building & Trades",
            "subcategory":"Construction",
            "type":"Services"
        }
    ],
    "sg:phone":"+44 1608 663344",
    "sg:postcode":"CV36 5EN",
    "sg:province":"Warwickshire",
    "sg:tags":[
        "builder"
    ],
    "wof:name":"Townfield Estates (Leamington Spa) Ltd.",
    "wof:placetype":"venue"
},
  "geometry": {"coordinates":[-1.568624,52.028473],"type":"Point"}
}