{
  "type": "Feature",
  "properties": {
    "addr:full":"Tamworth Manor High School, Wide Way Mitcham Greater London CR4 1BP",
    "addr:postcode":"cr4 1bp",
    "addr:street":"Wide Way",
    "iso:country":"GB",
    "sg:address":"Tamworth Manor High School, Wide Way",
    "sg:city":"Mitcham",
    "sg:classifiers":[
        {
            "category":"Professional",
            "type":"Services"
        }
    ],
    "sg:phone":"+44 20 8764 7835",
    "sg:postcode":"CR4 1BP",
    "sg:province":"Greater London",
    "sg:tags":[
        "caterer"
    ],
    "wof:name":"B E T Catering Services Ltd",
    "wof:placetype":"venue"
},
  "geometry": {"coordinates":[-0.164255,51.40715],"type":"Point"}
}