{
  "type": "Feature",
  "properties": {
    "addr:full":"641 Watford Way London Greater London NW7 3JR",
    "addr:housenumber":"641",
    "addr:postcode":"nw7 3jr",
    "addr:street":"Watford Way",
    "iso:country":"GB",
    "sg:address":"641 Watford Way",
    "sg:city":"London",
    "sg:classifiers":[
        {
            "category":"Shopping",
            "subcategory":"Pharmacy",
            "type":"Retail Goods"
        }
    ],
    "sg:phone":"+44 20 8959 3520",
    "sg:postcode":"NW7 3JR",
    "sg:province":"Greater London",
    "sg:tags":[
        "pharmacist",
        "chemist"
    ],
    "wof:name":"Acorn Pharmacy",
    "wof:placetype":"venue"
},
  "geometry": {"coordinates":[-0.250011,51.619129],"type":"Point"}
}