{
  "type": "Feature",
  "properties": {
    "addr:full":"Renacres Lane, Halsall Ormskirk Lancashire L39 8SE",
    "addr:postcode":"l39 8se",
    "addr:street":"Renacres Lane",
    "iso:country":"GB",
    "sg:address":"Renacres Lane, Halsall",
    "sg:city":"Ormskirk",
    "sg:classifiers":[
        {
            "category":"Health Services",
            "subcategory":"Hospital",
            "type":"Services"
        }
    ],
    "sg:phone":"+44 1704 841133",
    "sg:postcode":"L39 8SE",
    "sg:province":"Lancashire",
    "wof:name":"Renacres Hall Hospital",
    "wof:placetype":"venue"
},
  "geometry": {"coordinates":[-2.968289,53.608189],"type":"Point"}
}