{
  "type": "Feature",
  "properties": {
    "iso:country":"GB",
    "sg:address":"7 Colinbar Circle, Barrhead",
    "sg:city":"Glasgow",
    "sg:classifiers":[
        {
            "category":"Autos & Motor Vehicles",
            "subcategory":"Motorcycle Sales",
            "type":"Retail Goods"
        }
    ],
    "sg:phone":"+44 141 876 4156",
    "sg:postcode":"G78 2BE",
    "sg:province":"East Ayrshire",
    "sg:tags":[
        "chauffeur",
        "driven",
        "car"
    ],
    "wof:name":"Acorn Chauffeur Services",
    "wof:placetype":"venue"
},
  "geometry": {"coordinates":[-4.398749,55.79266],"type":"Point"}
}