{
  "type": "Feature",
  "properties": {
    "iso:country":"GB",
    "sg:address":"22 Parish Way, Monk Bretton",
    "sg:city":"Barnsley",
    "sg:classifiers":[
        {
            "category":"Retail",
            "subcategory":"Driving School",
            "type":"Services"
        },
        {
            "category":"Education",
            "subcategory":"University",
            "type":"Public Place"
        }
    ],
    "sg:phone":"+44 1226 245589",
    "sg:postcode":"S71 2JW",
    "sg:province":"South Yorkshire",
    "sg:tags":[
        "higher"
    ],
    "wof:name":"G Cooper",
    "wof:placetype":"venue"
},
  "geometry": {"coordinates":[-1.446966,53.560242],"type":"Point"}
}