{
  "type": "Feature",
  "properties": {
    "addr:full":"Long Rock Garage, Marazion Penzance Cornwall TR20 8LD",
    "addr:postcode":"tr20 8ld",
    "iso:country":"GB",
    "sg:address":"Long Rock Garage, Marazion",
    "sg:city":"Penzance",
    "sg:classifiers":[
        {
            "category":"Retail",
            "subcategory":"Auto Repair",
            "type":"Services"
        }
    ],
    "sg:phone":"+44 1736 711211",
    "sg:postcode":"TR20 8LD",
    "sg:province":"Cornwall",
    "sg:tags":[
        "body",
        "car"
    ],
    "wof:name":"St Ives Motor Co",
    "wof:placetype":"venue"
},
  "geometry": {"coordinates":[-5.502269,50.128868],"type":"Point"}
}