{
  "type": "Feature",
  "properties": {
    "iso:country":"GB",
    "sg:address":"2a Sandbrook Lane",
    "sg:city":"Wirral",
    "sg:classifiers":[
        {
            "category":"Building & Trades",
            "subcategory":"Construction",
            "type":"Services"
        }
    ],
    "sg:phone":"+44 151 605 1411",
    "sg:postcode":"CH46 0QW",
    "sg:province":"Merseyside",
    "sg:tags":[
        "flooring"
    ],
    "wof:name":"Arrowe Flooring UK Ltd",
    "wof:placetype":"venue"
},
  "geometry": {"coordinates":[-3.108894,53.400402],"type":"Point"}
}