{
  "type": "Feature",
  "properties": {
    "addr:full":"Unit 29 Brockley Cross Business, Centre London Greater London SE4 2PD",
    "addr:housenumber":"unit 29",
    "addr:postcode":"se4 2pd",
    "addr:street":"Cross",
    "iso:country":"GB",
    "sg:address":"Unit 29 Brockley Cross Business, Centre",
    "sg:city":"London",
    "sg:classifiers":[
        {
            "category":"Professional",
            "subcategory":"Business Services",
            "type":"Services"
        }
    ],
    "sg:phone":"+44 20 7635 6384",
    "sg:postcode":"SE4 2PD",
    "sg:province":"Greater London",
    "sg:tags":[
        "planning",
        "design"
    ],
    "wof:name":"Streamline Installations Ltd.",
    "wof:placetype":"venue"
},
  "geometry": {"coordinates":[-0.036433,51.46553],"type":"Point"}
}