{
  "type": "Feature",
  "properties": {
    "addr:full":"9a Upr Church Rd St Leonards-on-sea East Sussex TN37 7AT",
    "addr:housenumber":"9a",
    "addr:postcode":"tn37 7at",
    "addr:street":"Upr Church Rd",
    "iso:country":"GB",
    "sg:address":"9a Upr Church Rd",
    "sg:city":"St Leonards-on-sea",
    "sg:classifiers":[
        {
            "category":"Education",
            "subcategory":"Special Training",
            "type":"Public Place"
        }
    ],
    "sg:postcode":"TN37 7AT",
    "sg:province":"East Sussex",
    "sg:tags":[
        "product",
        "centre"
    ],
    "wof:name":"McCh Society",
    "wof:placetype":"venue"
},
  "geometry": {"coordinates":[0.5514829755,50.8787231445],"type":"Point"}
}