{
  "type": "Feature",
  "properties": {
    "addr:full":"Southleaze Farm, Ewen Cirencester Gloucestershire GL7 6BZ",
    "addr:postcode":"gl7 6bz",
    "iso:country":"GB",
    "sg:address":"Southleaze Farm, Ewen",
    "sg:city":"Cirencester",
    "sg:classifiers":[
        {
            "category":"Farming",
            "subcategory":"Crops",
            "type":"Manufacturing & Wholesale Goods"
        },
        {
            "category":"Farming",
            "subcategory":"Farm",
            "type":"Manufacturing & Wholesale Goods"
        }
    ],
    "sg:phone":"+44 1285 862028",
    "sg:postcode":"GL7 6BZ",
    "sg:province":"Gloucestershire",
    "sg:tags":[
        "mixed",
        "arable"
    ],
    "wof:name":"Andrew T Timbrell",
    "wof:placetype":"venue"
},
  "geometry": {"coordinates":[-1.9949339628,51.676651001],"type":"Point"}
}