{
  "type": "Feature",
  "properties": {
    "addr:full":"11 Elgin Crescent London Greater London W11 2JA",
    "addr:housenumber":"11",
    "addr:postcode":"w11 2ja",
    "addr:street":"Elgin Crescent",
    "iso:country":"GB",
    "sg:address":"11 Elgin Crescent",
    "sg:city":"London",
    "sg:classifiers":[
        {
            "category":"Deli",
            "type":"Food & Drink"
        }
    ],
    "sg:phone":"+44 20 7229 0501",
    "sg:postcode":"W11 2JA",
    "sg:province":"Greater London",
    "sg:tags":[
        "delicatessen"
    ],
    "wof:name":"Mr Christian Provisions",
    "wof:placetype":"venue"
},
  "geometry": {"coordinates":[-0.204957,51.514881],"type":"Point"}
}