{
  "type": "Feature",
  "properties": {
    "addr:full":"14 Mostyn Street Llandudno Conwy LL30 2UA",
    "addr:housenumber":"14",
    "addr:postcode":"ll30 2ua",
    "addr:street":"Mostyn Street",
    "iso:country":"GB",
    "sg:address":"14 Mostyn Street",
    "sg:city":"Llandudno",
    "sg:classifiers":[
        {
            "category":"Travel",
            "subcategory":"Travel Agent",
            "type":"Entertainment"
        }
    ],
    "sg:phone":"+44 1492 860330",
    "sg:postcode":"LL30 2UA",
    "sg:province":"Conwy",
    "wof:name":"Carlson Worldchoice",
    "wof:placetype":"venue"
},
  "geometry": {"coordinates":[-3.825834,53.322392],"type":"Point"}
}