{
  "type": "Feature",
  "properties": {
    "addr:full":"2 Church Street Inverkeithing Fife KY11 1LJ",
    "addr:housenumber":"2",
    "addr:postcode":"ky11 1lj",
    "addr:street":"Church Street",
    "iso:country":"GB",
    "sg:address":"2 Church Street",
    "sg:city":"Inverkeithing",
    "sg:classifiers":[
        {
            "category":"Personal",
            "subcategory":"Beauty Salon",
            "type":"Services"
        }
    ],
    "sg:phone":"+44 1383 413197",
    "sg:postcode":"KY11 1LJ",
    "sg:province":"Fife",
    "sg:tags":[
        "lady",
        "hairdresser"
    ],
    "wof:name":"Maurenns",
    "wof:placetype":"venue"
},
  "geometry": {"coordinates":[-3.3976449966,56.0314598083],"type":"Point"}
}