{
  "type": "Feature",
  "properties": {
    "addr:full":"415 Bath Road Slough Berkshire SL1 5QL",
    "addr:housenumber":"415",
    "addr:postcode":"sl1 5ql",
    "addr:street":"Bath Road",
    "iso:country":"GB",
    "sg:address":"415 Bath Road",
    "sg:city":"Slough",
    "sg:classifiers":[
        {
            "category":"Food & Beverages",
            "subcategory":"Fruits & Vegetables",
            "type":"Retail Goods"
        },
        {
            "category":"Food & Beverages",
            "subcategory":"Groceries & Convenience Stores",
            "type":"Retail Goods"
        }
    ],
    "sg:phone":"+44 1628 602792",
    "sg:postcode":"SL1 5QL",
    "sg:province":"Berkshire",
    "sg:tags":[
        "grocer",
        "greengrocer"
    ],
    "wof:name":"D & G Stores",
    "wof:placetype":"venue"
},
  "geometry": {"coordinates":[-0.6485180259,51.520198822],"type":"Point"}
}