{
  "type": "Feature",
  "properties": {
    "iso:country":"GB",
    "sg:address":"Maryland, Mill Lane, Halford",
    "sg:city":"Shipston-on-stour",
    "sg:classifiers":[
        {
            "category":"Social Services",
            "subcategory":"Job Training",
            "type":"Services"
        },
        {
            "category":"Professional",
            "subcategory":"Management & Consulting",
            "type":"Services"
        }
    ],
    "sg:phone":"+44 1789 740930",
    "sg:postcode":"CV36 5BY",
    "sg:province":"Warwickshire",
    "sg:tags":[
        "consultant",
        "business"
    ],
    "wof:name":"Stephen Hughes Associates",
    "wof:placetype":"venue"
},
  "geometry": {"coordinates":[-1.620935,52.108517],"type":"Point"}
}