{
  "type": "Feature",
  "properties": {
    "addr:full":"22 Bullen Close, Thorverton Exeter Devon EX5 5NW",
    "addr:housenumber":"22",
    "addr:postcode":"ex5 5nw",
    "addr:street":"Bullen Close",
    "iso:country":"GB",
    "sg:address":"22 Bullen Close, Thorverton",
    "sg:city":"Exeter",
    "sg:classifiers":[
        {
            "category":"Social Services",
            "subcategory":"Adult Care",
            "type":"Services"
        },
        {
            "category":"Government",
            "subcategory":"Office",
            "type":"Public Place"
        }
    ],
    "sg:phone":"+44 1392 860080",
    "sg:postcode":"EX5 5NW",
    "sg:province":"Devon",
    "sg:tags":[
        "housing",
        "local",
        "sheltered"
    ],
    "wof:name":"Bullens Close Sheltered Housing",
    "wof:placetype":"venue"
},
  "geometry": {"coordinates":[-3.5294489861,50.8066444397],"type":"Point"}
}