{
  "type": "Feature",
  "properties": {
    "iso:country":"GB",
    "sg:address":"35 Welsh Road",
    "sg:city":"Deeside",
    "sg:classifiers":[
        {
            "category":"Shopping",
            "subcategory":"News",
            "type":"Retail Goods"
        },
        {
            "category":"Shopping",
            "subcategory":"Pharmacy",
            "type":"Retail Goods"
        }
    ],
    "sg:phone":"+44 1244 830284",
    "sg:postcode":"CH5 2HU",
    "sg:province":"Flintshire",
    "sg:tags":[
        "pharmacist",
        "newsagent",
        "chemist"
    ],
    "wof:name":"Garden City Post Office",
    "wof:placetype":"venue"
},
  "geometry": {"coordinates":[-3.008109,53.214302],"type":"Point"}
}