{
  "type": "Feature",
  "properties": {
    "iso:country":"GB",
    "sg:address":"White House, High Street, Newport",
    "sg:city":"Saffron Walden",
    "sg:classifiers":[
        {
            "category":"Wholesale",
            "subcategory":"Medical Equipment & Supplies",
            "type":"Manufacturing & Wholesale Goods"
        }
    ],
    "sg:postcode":"CB11 3PQ",
    "sg:province":"Essex",
    "sg:tags":[
        "hospital"
    ],
    "wof:name":"Nichols Institute Diagnostics Ltd.",
    "wof:placetype":"venue"
},
  "geometry": {"coordinates":[0.26351,51.977386],"type":"Point"}
}