{
  "type": "Feature",
  "properties": {
    "addr:full":"67 Cranmer Avenue Hove East Sussex BN3 7JP",
    "addr:housenumber":"67",
    "addr:postcode":"bn3 7jp",
    "addr:street":"Cranmer Avenue",
    "iso:country":"GB",
    "sg:address":"67 Cranmer Avenue",
    "sg:city":"Hove",
    "sg:classifiers":[
        {
            "category":"Education",
            "subcategory":"Music School",
            "type":"Public Place"
        },
        {
            "category":"Home & Garden",
            "subcategory":"Home Furnishings",
            "type":"Retail Goods"
        }
    ],
    "sg:phone":"+44 1273 885656",
    "sg:postcode":"BN3 7JP",
    "sg:province":"East Sussex",
    "sg:tags":[
        "awning",
        "conservatory",
        "canopy",
        "blinds"
    ],
    "wof:name":"The Conservatory Blind Co",
    "wof:placetype":"venue"
},
  "geometry": {"coordinates":[-0.187998,50.840023],"type":"Point"}
}