{
  "type": "Feature",
  "properties": {
    "iso:country":"GB",
    "sg:address":"High Road",
    "sg:city":"Broxbourne",
    "sg:classifiers":[
        {
            "category":"Restaurant",
            "type":"Food & Drink"
        }
    ],
    "sg:phone":"+44 1992 462807",
    "sg:postcode":"EN10 6DB",
    "sg:province":"Essex",
    "wof:name":"New River Arms",
    "wof:placetype":"venue"
},
  "geometry": {"coordinates":[-0.022596,51.739559],"type":"Point"}
}