{
  "type": "Feature",
  "properties": {
    "addr:full":"69 Gondar Gardens Kilburn Greater London NW6 1EP",
    "addr:housenumber":"69",
    "addr:postcode":"nw6 1ep",
    "addr:street":"Gondar Gardens",
    "iso:country":"GB",
    "sg:address":"69 Gondar Gardens",
    "sg:city":"Kilburn",
    "sg:classifiers":[
        {
            "category":"Real Estate",
            "subcategory":"Architect",
            "type":"Services"
        }
    ],
    "sg:phone":"+44 20 7431 0172",
    "sg:postcode":"NW6 1EP",
    "sg:province":"Greater London",
    "wof:name":"Brian Murray",
    "wof:placetype":"venue"
},
  "geometry": {"coordinates":[-0.202586,51.553078],"type":"Point"}
}