{
  "type": "Feature",
  "properties": {
    "addr:full":"11-13 Victoria Road Ellesmere Port Cheshire CH65 8BU",
    "addr:housenumber":"11-13",
    "addr:postcode":"ch65 8bu",
    "addr:street":"Victoria Road",
    "iso:country":"GB",
    "sg:address":"11-13 Victoria Road",
    "sg:city":"Ellesmere Port",
    "sg:classifiers":[
        {
            "category":"Professional",
            "subcategory":"Printing & Photocopies",
            "type":"Services"
        }
    ],
    "sg:phone":"+44 151 356 0019",
    "sg:postcode":"CH65 8BU",
    "sg:province":"Cheshire",
    "sg:tags":[
        "printer"
    ],
    "wof:name":"David Wright Printers",
    "wof:placetype":"venue"
},
  "geometry": {"coordinates":[-2.900042057,53.2799758911],"type":"Point"}
}