{
  "type": "Feature",
  "properties": {
    "addr:full":"Unit 2 King Court, High Street Wimborne Dorset BH21 1HS",
    "addr:housenumber":"unit 2",
    "addr:postcode":"bh21 1hs",
    "addr:street":"King Court High Street",
    "iso:country":"GB",
    "sg:address":"Unit 2 King Court, High Street",
    "sg:city":"Wimborne",
    "sg:classifiers":[
        {
            "category":"Shopping",
            "subcategory":"Shoes",
            "type":"Retail Goods"
        }
    ],
    "sg:phone":"+44 1202 881238",
    "sg:postcode":"BH21 1HS",
    "sg:province":"Dorset",
    "wof:name":"Leather Craft",
    "wof:placetype":"venue"
},
  "geometry": {"coordinates":[-1.9877790213,50.7994804382],"type":"Point"}
}