{
  "type": "Feature",
  "properties": {
    "iso:country":"GB",
    "sg:address":"5 Barnfield Way, Copmanthorpe",
    "sg:city":"York",
    "sg:classifiers":[
        {
            "category":"Professional",
            "subcategory":"Secretarial Services",
            "type":"Services"
        }
    ],
    "sg:postcode":"YO23 3RT",
    "sg:province":"North Yorkshire",
    "wof:name":"Wendy A Bramall",
    "wof:placetype":"venue"
},
  "geometry": {"coordinates":[-1.144103,53.91206],"type":"Point"}
}