{
  "type": "Feature",
  "properties": {
    "addr:full":"9a High Street, Higham Ferrers Rushden Bedfordshire NN10 8BW",
    "addr:housenumber":"9a",
    "addr:postcode":"nn10 8bw",
    "addr:street":"High Street",
    "iso:country":"GB",
    "sg:address":"9a High Street, Higham Ferrers",
    "sg:city":"Rushden",
    "sg:classifiers":[
        {
            "category":"Shopping",
            "subcategory":"Clothing, Apparel, & Fashions",
            "type":"Retail Goods"
        }
    ],
    "sg:phone":"+44 1933 314970",
    "sg:postcode":"NN10 8BW",
    "sg:province":"Bedfordshire",
    "sg:tags":[
        "dresswear"
    ],
    "wof:name":"Special Occasions",
    "wof:placetype":"venue"
},
  "geometry": {"coordinates":[-0.593911,52.304951],"type":"Point"}
}