{
  "type": "Feature",
  "properties": {
    "addr:full":"17 Granary Road, Great Bedwin Marlborough Berkshire SN8 3UE",
    "addr:housenumber":"17",
    "addr:postcode":"sn8 3ue",
    "addr:street":"Granary Road",
    "iso:country":"GB",
    "sg:address":"17 Granary Road, Great Bedwin",
    "sg:city":"Marlborough",
    "sg:classifiers":[
        {
            "category":"Travel",
            "subcategory":"Hotels & Motels",
            "type":"Entertainment"
        }
    ],
    "sg:postcode":"SN8 3UE",
    "sg:province":"Berkshire",
    "sg:tags":[
        "self",
        "catering"
    ],
    "wof:name":"Mark Thomas",
    "wof:placetype":"venue"
},
  "geometry": {"coordinates":[-1.6027040482,51.3772583008],"type":"Point"}
}