{
  "type": "Feature",
  "properties": {
    "addr:full":"59 Cleeve Drive Ivybridge Devon PL21 9BP",
    "addr:housenumber":"59",
    "addr:postcode":"pl21 9bp",
    "addr:street":"Cleeve Drive",
    "iso:country":"GB",
    "sg:address":"59 Cleeve Drive",
    "sg:city":"Ivybridge",
    "sg:classifiers":[
        {
            "category":"Building & Trades",
            "subcategory":"Construction",
            "type":"Services"
        }
    ],
    "sg:phone":"+44 1752 892724",
    "sg:postcode":"PL21 9BP",
    "sg:province":"Devon",
    "sg:tags":[
        "joinery",
        "joiner",
        "carpenter",
        "carpentry"
    ],
    "wof:name":"Bernard King",
    "wof:placetype":"venue"
},
  "geometry": {"coordinates":[-3.9309420586,50.3895645142],"type":"Point"}
}