{
  "type": "Feature",
  "properties": {
    "addr:full":"Carlisle Street East Sheffield South Yorkshire S4 7QN",
    "addr:postcode":"s4 7qn",
    "addr:street":"Carlisle Street East",
    "iso:country":"GB",
    "sg:address":"Carlisle Street East",
    "sg:city":"Sheffield",
    "sg:classifiers":[
        {
            "category":"Manufacturing",
            "subcategory":"Metals",
            "type":"Manufacturing & Wholesale Goods"
        }
    ],
    "sg:phone":"+44 114 276 7011",
    "sg:postcode":"S4 7QN",
    "sg:province":"South Yorkshire",
    "sg:tags":[
        "product",
        "fabricated"
    ],
    "wof:name":"George Shaw Engineering (Sheffield) (1994) Ltd.",
    "wof:placetype":"venue"
},
  "geometry": {"coordinates":[-1.447544,53.396381],"type":"Point"}
}