{
  "type": "Feature",
  "properties": {
    "addr:full":"Longacres Nursery, London Rd Bagshot Berkshire GU19 5JB",
    "addr:postcode":"gu19 5jb",
    "addr:street":"London Rd",
    "iso:country":"GB",
    "sg:address":"Longacres Nursery, London Rd",
    "sg:city":"Bagshot",
    "sg:classifiers":[
        {
            "category":"Building & Trades",
            "subcategory":"Construction",
            "type":"Services"
        }
    ],
    "sg:phone":"+44 1276 451626",
    "sg:postcode":"GU19 5JB",
    "sg:province":"Berkshire",
    "sg:tags":[
        "window",
        "replacement"
    ],
    "wof:name":"Anglian Home Improvements",
    "wof:placetype":"venue"
},
  "geometry": {"coordinates":[-0.6961200237,51.3587989807],"type":"Point"}
}