{
  "type": "Feature",
  "properties": {
    "iso:country":"GB",
    "sg:address":"62 Station Road",
    "sg:city":"Hayling Island",
    "sg:classifiers":[
        {
            "category":"Retail",
            "subcategory":"Auto Repair",
            "type":"Services"
        }
    ],
    "sg:phone":"+44 23 9246 2660",
    "sg:postcode":"PO11 0EL",
    "sg:province":"Hampshire",
    "sg:tags":[
        "body",
        "car",
        "repairer"
    ],
    "sg:website":"http://www.haydenvehiclerentals.co.uk",
    "wof:name":"Hayden Garages",
    "wof:placetype":"venue"
},
  "geometry": {"coordinates":[-0.992398,50.792122],"type":"Point"}
}