{
  "type": "Feature",
  "properties": {
    "iso:country":"GB",
    "sg:address":"50 Bury New Road, Prestwich",
    "sg:city":"Manchester",
    "sg:classifiers":[
        {
            "category":"Cafe",
            "type":"Food & Drink"
        }
    ],
    "sg:phone":"+44 161 773 8818",
    "sg:postcode":"M25 0JU",
    "sg:province":"Greater Manchester",
    "sg:tags":[
        "tea",
        "room"
    ],
    "wof:name":"Sedgley Snax",
    "wof:placetype":"venue"
},
  "geometry": {"coordinates":[-2.271771,53.519085],"type":"Point"}
}