{
  "type": "Feature",
  "properties": {
    "iso:country":"GB",
    "sg:address":"Gartref",
    "sg:city":"Prenton",
    "sg:classifiers":[
        {
            "category":"Building & Trades",
            "subcategory":"Construction",
            "type":"Services"
        }
    ],
    "sg:postcode":"CH43 9UB",
    "sg:province":"Merseyside",
    "sg:tags":[
        "builder"
    ],
    "wof:name":"John Barry Construction",
    "wof:placetype":"venue"
},
  "geometry": {"coordinates":[-3.0663199425,53.3848800659],"type":"Point"}
}