{
  "type": "Feature",
  "properties": {
    "iso:country":"GB",
    "sg:address":"The White Cottage, The Common, Wacton",
    "sg:city":"Norwich",
    "sg:classifiers":[
        {
            "category":"Professional",
            "subcategory":"Engineering",
            "type":"Services"
        },
        {
            "category":"Real Estate",
            "subcategory":"Architect",
            "type":"Services"
        }
    ],
    "sg:phone":"+44 1508 530094",
    "sg:postcode":"NR15 2UP",
    "sg:province":"Norfolk",
    "sg:tags":[
        "consultant",
        "structural"
    ],
    "wof:name":"E T John Castle",
    "wof:placetype":"venue"
},
  "geometry": {"coordinates":[1.2048300505,52.4775390625],"type":"Point"}
}