{
  "type": "Feature",
  "properties": {
    "iso:country":"GB",
    "sg:address":"First Floor, 9a Verney St",
    "sg:city":"Exeter",
    "sg:classifiers":[
        {
            "category":"Sports & Exercise",
            "subcategory":"Gym",
            "type":"Entertainment"
        }
    ],
    "sg:phone":"+44 1392 276091",
    "sg:postcode":"EX1 2AW",
    "sg:province":"Devon",
    "sg:tags":[
        "fitness",
        "health",
        "centre"
    ],
    "wof:name":"Body 2000",
    "wof:placetype":"venue"
},
  "geometry": {"coordinates":[-3.52135,50.72747],"type":"Point"}
}