{
  "type": "Feature",
  "properties": {
    "addr:full":"Kingsland High Street Hackney Greater London E8 2LX",
    "addr:postcode":"e8 2lx",
    "addr:street":"Kingsland High Street",
    "iso:country":"GB",
    "sg:address":"Kingsland High Street",
    "sg:city":"Hackney",
    "sg:classifiers":[
        {
            "category":"Real Estate",
            "subcategory":"Developer",
            "type":"Services"
        }
    ],
    "sg:phone":"+44 20 7241 5455",
    "sg:postcode":"E8 2LX",
    "sg:province":"Greater London",
    "sg:tags":[
        "property"
    ],
    "wof:name":"P D F M Property Partnership",
    "wof:placetype":"venue"
},
  "geometry": {"coordinates":[-0.0756290033,51.5471153259],"type":"Point"}
}