{
  "type": "Feature",
  "properties": {
    "iso:country":"GB",
    "sg:address":"North Lane",
    "sg:city":"East Boldon",
    "sg:classifiers":[
        {
            "category":"Education",
            "subcategory":"School",
            "type":"Public Place"
        },
        {
            "category":"Government",
            "subcategory":"Office",
            "type":"Public Place"
        }
    ],
    "sg:postcode":"NE36 0DL",
    "sg:province":"Tyne and Wear",
    "sg:tags":[
        "local",
        "authority"
    ],
    "wof:name":"East Boldon Junior Mixed School",
    "wof:placetype":"venue"
},
  "geometry": {"coordinates":[-1.431614995,54.9454536438],"type":"Point"}
}