{
  "type": "Feature",
  "properties": {
    "iso:country":"GB",
    "sg:address":"152 Yarmouth Road",
    "sg:city":"Norwich",
    "sg:classifiers":[
        {
            "category":"Shopping",
            "subcategory":"Stationery & Office Supplies",
            "type":"Retail Goods"
        },
        {
            "category":"Education",
            "subcategory":"University",
            "type":"Public Place"
        },
        {
            "category":"Home & Garden",
            "subcategory":"Furniture",
            "type":"Retail Goods"
        }
    ],
    "sg:phone":"+44 1603 435617",
    "sg:postcode":"NR7 0AD",
    "sg:province":"Norfolk",
    "sg:tags":[
        "equipment",
        "educational",
        "school",
        "outlet"
    ],
    "wof:name":"Frank Howard",
    "wof:placetype":"venue"
},
  "geometry": {"coordinates":[1.3580340147,52.6281204224],"type":"Point"}
}