{
  "type": "Feature",
  "properties": {
    "iso:country":"GB",
    "sg:address":"10 Trewelm La",
    "sg:city":"Redruth",
    "sg:classifiers":[
        {
            "category":"Communications",
            "type":"Services"
        }
    ],
    "sg:phone":"+44 1209 820667",
    "sg:postcode":"TR16 5JW",
    "sg:province":"Cornwall",
    "sg:tags":[
        "tv",
        "video",
        "radio"
    ],
    "wof:name":"Abbey Aerials",
    "wof:placetype":"venue"
},
  "geometry": {"coordinates":[-5.176564,50.238144],"type":"Point"}
}