{
  "type": "Feature",
  "properties": {
    "iso:country":"GB",
    "sg:address":"21 Lethbridge Road",
    "sg:city":"Southport",
    "sg:classifiers":[
        {
            "category":"Social Services",
            "subcategory":"Retirement Home",
            "type":"Services"
        }
    ],
    "sg:postcode":"PR8 6JA",
    "sg:province":"Lancashire",
    "sg:tags":[
        "residential",
        "care"
    ],
    "wof:name":"Lyndhurst Residential Home",
    "wof:placetype":"venue"
},
  "geometry": {"coordinates":[-2.9882609844,53.6403465271],"type":"Point"}
}