{
  "type": "Feature",
  "properties": {
    "addr:full":"Child Assessment Unit, New Cross Hospital, Wolverhampton Rd Wolverhampton Staffordshire WV10 0QP",
    "addr:housenumber":"unit",
    "addr:postcode":"wv10 0qp",
    "addr:street":"Wolverhampton Rd",
    "iso:country":"GB",
    "sg:address":"Child Assessment Unit, New Cross Hospital, Wolverhampton Rd",
    "sg:city":"Wolverhampton",
    "sg:classifiers":[
        {
            "category":"Government",
            "subcategory":"Office",
            "type":"Public Place"
        }
    ],
    "sg:phone":"+44 1902 642901",
    "sg:postcode":"WV10 0QP",
    "sg:province":"Staffordshire",
    "sg:tags":[
        "local"
    ],
    "wof:name":"Wolverhampton Borough Council",
    "wof:placetype":"venue"
},
  "geometry": {"coordinates":[-2.121669,52.58865],"type":"Point"}
}