{
  "type": "Feature",
  "properties": {
    "iso:country":"GB",
    "sg:address":"2a Granville Square",
    "sg:city":"Stone",
    "sg:classifiers":[
        {
            "category":"Shopping",
            "subcategory":"Gifts & Souvenirs",
            "type":"Retail Goods"
        }
    ],
    "sg:postcode":"ST15 8DA",
    "sg:province":"Staffordshire",
    "sg:tags":[
        "shop"
    ],
    "wof:name":"Toddy Woodgate's",
    "wof:placetype":"venue"
},
  "geometry": {"coordinates":[-2.14855,52.903561],"type":"Point"}
}