{
  "type": "Feature",
  "properties": {
    "iso:country":"GB",
    "sg:address":"32 High St, Steeple Ashton",
    "sg:city":"Trowbridge",
    "sg:classifiers":[
        {
            "category":"Shopping",
            "subcategory":"Department Store",
            "type":"Retail Goods"
        },
        {
            "category":"Government",
            "subcategory":"Post Office",
            "type":"Public Place"
        }
    ],
    "sg:postcode":"BA14 6EL",
    "sg:province":"Wiltshire",
    "wof:name":"Post Office Counters Ltd",
    "wof:placetype":"venue"
},
  "geometry": {"coordinates":[-2.1354410648,51.3111152649],"type":"Point"}
}