{
  "type": "Feature",
  "properties": {
    "addr:full":"13 Briar Road, Harold Hill Romford Essex RM3 8AH",
    "addr:housenumber":"13",
    "addr:postcode":"rm3 8ah",
    "addr:street":"Briar Road",
    "iso:country":"GB",
    "sg:address":"13 Briar Road, Harold Hill",
    "sg:city":"Romford",
    "sg:classifiers":[
        {
            "category":"Personal",
            "subcategory":"Beauty Salon",
            "type":"Services"
        }
    ],
    "sg:phone":"+44 1708 376524",
    "sg:postcode":"RM3 8AH",
    "sg:province":"Essex",
    "sg:tags":[
        "unisex",
        "hairdresser"
    ],
    "wof:name":"Hair by Suzanne Jane",
    "wof:placetype":"venue"
},
  "geometry": {"coordinates":[0.2138579935,51.6006202698],"type":"Point"}
}