{
  "type": "Feature",
  "properties": {
    "addr:full":"25 Shepperton Rd Staines Berkshire TW18 1SE",
    "addr:housenumber":"25",
    "addr:postcode":"tw18 1se",
    "addr:street":"Shepperton Rd",
    "iso:country":"GB",
    "sg:address":"25 Shepperton Rd",
    "sg:city":"Staines",
    "sg:classifiers":[
        {
            "category":"Bars & Pubs",
            "type":"Food & Drink"
        }
    ],
    "sg:phone":"+44 1784 452617",
    "sg:postcode":"TW18 1SE",
    "sg:province":"Berkshire",
    "sg:tags":[
        "pubs",
        "inn"
    ],
    "wof:name":"The Three Horseshoes",
    "wof:placetype":"venue"
},
  "geometry": {"coordinates":[-0.4892170131,51.4080963135],"type":"Point"}
}