{
  "type": "Feature",
  "properties": {
    "addr:full":"Hill Top Farm, Ash Lane Loughborough Leicestershire LE12 6UX",
    "addr:postcode":"le12 6ux",
    "addr:street":"Ash Lane",
    "iso:country":"GB",
    "sg:address":"Hill Top Farm, Ash Lane",
    "sg:city":"Loughborough",
    "sg:classifiers":[
        {
            "category":"Farming",
            "subcategory":"Farm",
            "type":"Manufacturing & Wholesale Goods"
        }
    ],
    "sg:postcode":"LE12 6UX",
    "sg:province":"Leicestershire",
    "sg:tags":[
        "mixed",
        "crop"
    ],
    "wof:name":"Peter Simpson",
    "wof:placetype":"venue"
},
  "geometry": {"coordinates":[-1.15229,52.84621],"type":"Point"}
}