{
  "type": "Feature",
  "properties": {
    "addr:full":"Bournemouth Airport, Hurn Christchurch Dorset BH23 6NW",
    "addr:postcode":"bh23 6nw",
    "iso:country":"GB",
    "sg:address":"Bournemouth Airport, Hurn",
    "sg:city":"Christchurch",
    "sg:classifiers":[
        {
            "category":"Freight",
            "type":"Transportation"
        }
    ],
    "sg:phone":"+44 1202 582330",
    "sg:postcode":"BH23 6NW",
    "sg:province":"Dorset",
    "sg:tags":[
        "forwarders"
    ],
    "wof:name":"R H Freight Services Ltd.",
    "wof:placetype":"venue"
},
  "geometry": {"coordinates":[-1.8490799665,50.7848396301],"type":"Point"}
}