{
  "type": "Feature",
  "properties": {
    "addr:full":"London Road Towcester Buckinghamshire NN12 6AJ",
    "addr:postcode":"nn12 6aj",
    "addr:street":"London Road",
    "iso:country":"GB",
    "sg:address":"London Road",
    "sg:city":"Towcester",
    "sg:classifiers":[
        {
            "category":"Autos & Motor Vehicles",
            "subcategory":"Automobile Sales",
            "type":"Retail Goods"
        }
    ],
    "sg:postcode":"NN12 6AJ",
    "sg:province":"Buckinghamshire",
    "sg:tags":[
        "car"
    ],
    "wof:name":"White Bear Car Sales",
    "wof:placetype":"venue"
},
  "geometry": {"coordinates":[-0.9851139784,52.1293487549],"type":"Point"}
}