{
  "type": "Feature",
  "properties": {
    "addr:full":"2 Napsbury Avenue, London Colney St Albans Hertfordshire AL2 1LU",
    "addr:housenumber":"2",
    "addr:postcode":"al2 1lu",
    "addr:street":"Napsbury Avenue",
    "iso:country":"GB",
    "sg:address":"2 Napsbury Avenue, London Colney",
    "sg:city":"St Albans",
    "sg:classifiers":[
        {
            "category":"Building & Trades",
            "subcategory":"Landscaping Services",
            "type":"Services"
        }
    ],
    "sg:postcode":"AL2 1LU",
    "sg:province":"Hertfordshire",
    "sg:tags":[
        "designer",
        "architect",
        "landscape"
    ],
    "wof:name":"Gardens for You",
    "wof:placetype":"venue"
},
  "geometry": {"coordinates":[-0.302188009,51.7256965637],"type":"Point"}
}