{
  "type": "Feature",
  "properties": {
    "addr:full":"60-62 Newgate Street Bishop Auckland Durham DL14 7EQ",
    "addr:housenumber":"60-62",
    "addr:postcode":"dl14 7eq",
    "addr:street":"Newgate Street",
    "iso:country":"GB",
    "sg:address":"60-62 Newgate Street",
    "sg:city":"Bishop Auckland",
    "sg:classifiers":[
        {
            "category":"Communications",
            "type":"Services"
        }
    ],
    "sg:postcode":"DL14 7EQ",
    "sg:province":"Durham",
    "sg:tags":[
        "tv",
        "video",
        "radio"
    ],
    "wof:name":"J C Ellis",
    "wof:placetype":"venue"
},
  "geometry": {"coordinates":[-1.6755470037,54.661895752],"type":"Point"}
}