{
  "type": "Feature",
  "properties": {
    "addr:full":"18 Bracebridge Street Nuneaton Leicestershire CV11 5PA",
    "addr:housenumber":"18",
    "addr:postcode":"cv11 5pa",
    "addr:street":"Bracebridge Street",
    "iso:country":"GB",
    "sg:address":"18 Bracebridge Street",
    "sg:city":"Nuneaton",
    "sg:classifiers":[
        {
            "category":"Health Services",
            "subcategory":"Doctor",
            "type":"Services"
        }
    ],
    "sg:phone":"+44 24 7664 1979",
    "sg:postcode":"CV11 5PA",
    "sg:province":"Leicestershire",
    "sg:tags":[
        "practitioners"
    ],
    "wof:name":"Prima A Kumar",
    "wof:placetype":"venue"
},
  "geometry": {"coordinates":[-1.475654,52.521645],"type":"Point"}
}