{
  "type": "Feature",
  "properties": {
    "addr:full":"106 Main Street, Little Downham Ely Cambridgeshire CB6 2SX",
    "addr:housenumber":"106",
    "addr:postcode":"cb6 2sx",
    "addr:street":"Main Street",
    "iso:country":"GB",
    "sg:address":"106 Main Street, Little Downham",
    "sg:city":"Ely",
    "sg:classifiers":[
        {
            "category":"Bars & Pubs",
            "type":"Food & Drink"
        }
    ],
    "sg:phone":"+44 1353 698297",
    "sg:postcode":"CB6 2SX",
    "sg:province":"Cambridgeshire",
    "sg:tags":[
        "pubs",
        "inn"
    ],
    "wof:name":"The Plough Inn",
    "wof:placetype":"venue"
},
  "geometry": {"coordinates":[0.234208,52.431591],"type":"Point"}
}