{
  "type": "Feature",
  "properties": {
    "iso:country":"GB",
    "sg:address":"Queen St",
    "sg:city":"Leighton Buzzard",
    "sg:classifiers":[
        {
            "category":"Professional",
            "subcategory":"Management & Consulting",
            "type":"Services"
        }
    ],
    "sg:postcode":"LU7 1BZ",
    "sg:province":"Bedfordshire",
    "sg:tags":[
        "consultant",
        "business"
    ],
    "wof:name":"Crisp,R N,",
    "wof:placetype":"venue"
},
  "geometry": {"coordinates":[-0.663605,51.922089],"type":"Point"}
}