{
  "type": "Feature",
  "properties": {
    "iso:country":"GB",
    "sg:address":"37 Holland Gardens",
    "sg:city":"Watford",
    "sg:classifiers":[
        {
            "category":"Professional",
            "subcategory":"Engineering",
            "type":"Services"
        },
        {
            "category":"Shopping",
            "subcategory":"Computers & Home Electronics",
            "type":"Retail Goods"
        }
    ],
    "sg:phone":"+44 1923 671708",
    "sg:postcode":"WD25 9JN",
    "sg:province":"Hertfordshire",
    "sg:tags":[
        "television",
        "aerial",
        "contractor",
        "electrical",
        "radio",
        "engineer"
    ],
    "wof:name":"Supervision Aerials",
    "wof:placetype":"venue"
},
  "geometry": {"coordinates":[-0.3944169879,51.6841087341],"type":"Point"}
}