{
  "type": "Feature",
  "properties": {
    "addr:full":"98a Long Cross Bristol City of Bristol BS11 0LP",
    "addr:housenumber":"98a",
    "addr:postcode":"bs11 0lp",
    "addr:street":"Long Cross",
    "iso:country":"GB",
    "sg:address":"98a Long Cross",
    "sg:city":"Bristol",
    "sg:classifiers":[
        {
            "category":"Community Center",
            "subcategory":"Youth",
            "type":"Public Place"
        }
    ],
    "sg:phone":"+44 117 982 3406",
    "sg:postcode":"BS11 0LP",
    "sg:province":"City of Bristol",
    "sg:tags":[
        "organisation",
        "centre"
    ],
    "wof:name":"Avon Club",
    "wof:placetype":"venue"
},
  "geometry": {"coordinates":[-2.6674640179,51.4975585938],"type":"Point"}
}