{
  "type": "Feature",
  "properties": {
    "iso:country":"GB",
    "sg:address":"S10 Dunfermline Business Centre, Izatt Avenue",
    "sg:city":"Dunfermline",
    "sg:classifiers":[
        {
            "category":"Professional",
            "type":"Services"
        }
    ],
    "sg:postcode":"KY11 3BZ",
    "sg:province":"Fife",
    "sg:tags":[
        "repair",
        "tech",
        "maintenance"
    ],
    "wof:name":"I T M",
    "wof:placetype":"venue"
},
  "geometry": {"coordinates":[-3.47746,56.03484],"type":"Point"}
}