{
  "type": "Feature",
  "properties": {
    "addr:full":"4 Walmersley Old Rd Bury Lancashire BL9 6SQ",
    "addr:housenumber":"4",
    "addr:postcode":"bl9 6sq",
    "addr:street":"Walmersley Old Rd",
    "iso:country":"GB",
    "sg:address":"4 Walmersley Old Rd",
    "sg:city":"Bury",
    "sg:classifiers":[
        {
            "category":"Shopping",
            "subcategory":"Clothing, Apparel, & Fashions",
            "type":"Retail Goods"
        }
    ],
    "sg:phone":"+44 161 764 3463",
    "sg:postcode":"BL9 6SQ",
    "sg:province":"Lancashire",
    "sg:tags":[
        "shop"
    ],
    "wof:name":"G I Fashions",
    "wof:placetype":"venue"
},
  "geometry": {"coordinates":[-2.2942669392,53.6179122925],"type":"Point"}
}