{
  "type": "Feature",
  "properties": {
    "addr:full":"56 Gloucester Rd South Kensington Greater London SW7 4UB",
    "addr:housenumber":"56",
    "addr:postcode":"sw7 4ub",
    "addr:street":"Gloucester Rd",
    "iso:country":"GB",
    "sg:address":"56 Gloucester Rd",
    "sg:city":"South Kensington",
    "sg:classifiers":[
        {
            "category":"Professional",
            "subcategory":"Printing & Photocopies",
            "type":"Services"
        }
    ],
    "sg:phone":"+44 20 7460 3355",
    "sg:postcode":"SW7 4UB",
    "sg:province":"Greater London",
    "sg:tags":[
        "top",
        "publishing",
        "desk"
    ],
    "wof:name":"Continuum Business Works Ltd",
    "wof:placetype":"venue"
},
  "geometry": {"coordinates":[-0.183365,51.496838],"type":"Point"}
}