{
  "type": "Feature",
  "properties": {
    "iso:country":"GB",
    "sg:address":"River La, Saltney",
    "sg:city":"Chester",
    "sg:classifiers":[
        {
            "category":"Autos & Motor Vehicles",
            "subcategory":"Automobile Sales",
            "type":"Retail Goods"
        }
    ],
    "sg:postcode":"CH4 8RH",
    "sg:province":"Cheshire",
    "sg:tags":[
        "car"
    ],
    "wof:name":"Skyway Direct",
    "wof:placetype":"venue"
},
  "geometry": {"coordinates":[-2.935514,53.174385],"type":"Point"}
}