{
  "type": "Feature",
  "properties": {
    "iso:country":"GB",
    "sg:address":"Unit 5, Kilmory Industrial Estate",
    "sg:city":"Lochgilphead",
    "sg:classifiers":[
        {
            "category":"Building & Trades",
            "subcategory":"Plumbing",
            "type":"Services"
        }
    ],
    "sg:phone":"+44 1546 603158",
    "sg:postcode":"PA31 8RR",
    "sg:province":"Argyll and Bute",
    "sg:tags":[
        "heating"
    ],
    "wof:name":"Samborek A (Plumbing & Heating) Engineers",
    "wof:placetype":"venue"
},
  "geometry": {"coordinates":[-5.431824,56.036106],"type":"Point"}
}