{
  "type": "Feature",
  "properties": {
    "iso:country":"GB",
    "sg:address":"George Hay, Brigham House High Street",
    "sg:city":"Biggleswade",
    "sg:classifiers":[
        {
            "category":"Organizations",
            "subcategory":"Membership Organization",
            "type":"Services"
        }
    ],
    "sg:postcode":"SG18 0LD",
    "sg:province":"Bedfordshire",
    "sg:tags":[
        "club"
    ],
    "wof:name":"Grovelands Road Management Co  (No. 2) L",
    "wof:placetype":"venue"
},
  "geometry": {"coordinates":[-0.261729,52.086975],"type":"Point"}
}