{
  "type": "Feature",
  "properties": {
    "addr:full":"Water St Rossendale Lancashire BB4 8AP",
    "addr:postcode":"bb4 8ap",
    "addr:street":"Water St",
    "iso:country":"GB",
    "sg:address":"Water St",
    "sg:city":"Rossendale",
    "sg:classifiers":[
        {
            "category":"Building & Trades",
            "subcategory":"Construction",
            "type":"Services"
        }
    ],
    "sg:phone":"+44 1706 216868",
    "sg:postcode":"BB4 8AP",
    "sg:province":"Lancashire",
    "sg:tags":[
        "conversion",
        "loft"
    ],
    "wof:name":"Use-A-Loft (Loft Conversions) Ltd",
    "wof:placetype":"venue"
},
  "geometry": {"coordinates":[-2.2852709293,53.7258262634],"type":"Point"}
}