{
  "type": "Feature",
  "properties": {
    "addr:full":"Jubilee Business Centre, Gate St Blackburn Lancashire BB1 3AQ",
    "addr:postcode":"bb1 3aq",
    "addr:street":"Jubilee;Centre Gate St",
    "iso:country":"GB",
    "sg:address":"Jubilee Business Centre, Gate St",
    "sg:city":"Blackburn",
    "sg:classifiers":[
        {
            "category":"Home & Garden",
            "subcategory":"Household Appliances",
            "type":"Retail Goods"
        }
    ],
    "sg:postcode":"BB1 3AQ",
    "sg:province":"Lancashire",
    "sg:tags":[
        "cleaner",
        "domestic",
        "vacuum"
    ],
    "wof:name":"K C Systems Ltd",
    "wof:placetype":"venue"
},
  "geometry": {"coordinates":[-2.4803988934,53.7485160828],"type":"Point"}
}