{
  "type": "Feature",
  "properties": {
    "addr:full":"Bidford Primary School, Bramley Way Alcester Warwickshire B50 4QG",
    "addr:postcode":"b50 4qg",
    "addr:street":"Bramley Way",
    "iso:country":"GB",
    "sg:address":"Bidford Primary School, Bramley Way",
    "sg:city":"Alcester",
    "sg:classifiers":[
        {
            "category":"Farming",
            "subcategory":"Nursery",
            "type":"Manufacturing & Wholesale Goods"
        }
    ],
    "sg:phone":"+44 1789 773041",
    "sg:postcode":"B50 4QG",
    "sg:province":"Warwickshire",
    "sg:tags":[
        "creche"
    ],
    "wof:name":"Willow Tree Nursery School",
    "wof:placetype":"venue"
},
  "geometry": {"coordinates":[-1.85879004,52.1668395996],"type":"Point"}
}