{
  "type": "Feature",
  "properties": {
    "addr:full":"Field Lane Surgery, 42 Field Lane, Kessingland Lowestoft Suffolk NR33 7QA",
    "addr:housenumber":"42",
    "addr:postcode":"nr33 7qa",
    "addr:street":"Field;Field Lane",
    "iso:country":"GB",
    "sg:address":"Field Lane Surgery, 42 Field Lane, Kessingland",
    "sg:city":"Lowestoft",
    "sg:classifiers":[
        {
            "category":"Health Services",
            "subcategory":"Doctor",
            "type":"Services"
        },
        {
            "category":"Health Services",
            "subcategory":"Clinic",
            "type":"Services"
        }
    ],
    "sg:phone":"+44 1502 740203",
    "sg:postcode":"NR33 7QA",
    "sg:province":"Suffolk",
    "sg:tags":[
        "nh",
        "practitioners"
    ],
    "wof:name":"Field Lane Surgery",
    "wof:placetype":"venue"
},
  "geometry": {"coordinates":[1.71071,52.420673],"type":"Point"}
}