{
  "type": "Feature",
  "properties": {
    "addr:full":"Queen Street Penzance Cornwall TR18 4DE",
    "addr:postcode":"tr18 4de",
    "addr:street":"Queen Street",
    "iso:country":"GB",
    "sg:address":"Queen Street",
    "sg:city":"Penzance",
    "sg:classifiers":[
        {
            "category":"Retail",
            "subcategory":"Auto Repair",
            "type":"Services"
        }
    ],
    "sg:phone":"+44 1736 367938",
    "sg:postcode":"TR18 4DE",
    "sg:province":"Cornwall",
    "sg:tags":[
        "modification",
        "garage"
    ],
    "wof:name":"Britannia Motor Centre",
    "wof:placetype":"venue"
},
  "geometry": {"coordinates":[-5.5365791321,50.1176490784],"type":"Point"}
}