{
  "type": "Feature",
  "properties": {
    "addr:full":"4 Market Street Guildford Surrey GU1 4LB",
    "addr:housenumber":"4",
    "addr:postcode":"gu1 4lb",
    "addr:street":"Market Street",
    "iso:country":"GB",
    "sg:address":"4 Market Street",
    "sg:city":"Guildford",
    "sg:classifiers":[
        {
            "category":"Shopping",
            "subcategory":"Shoes",
            "type":"Retail Goods"
        }
    ],
    "sg:phone":"+44 1483 440566",
    "sg:postcode":"GU1 4LB",
    "sg:province":"Surrey",
    "sg:tags":[
        "shop"
    ],
    "wof:name":"Jones Bootmakers",
    "wof:placetype":"venue"
},
  "geometry": {"coordinates":[-0.572495997,51.2359466553],"type":"Point"}
}