{
  "type": "Feature",
  "properties": {
    "iso:country":"GB",
    "sg:address":"37/39 Millharbour, Isle Of Dogs",
    "sg:city":"London",
    "sg:classifiers":[
        {
            "category":"Communications",
            "subcategory":"Newspaper",
            "type":"Services"
        }
    ],
    "sg:phone":"+44 20 7972 6700",
    "sg:postcode":"E14 9TZ",
    "sg:province":"Greater London",
    "sg:tags":[
        "magazine"
    ],
    "wof:name":"Emap Images Ltd",
    "wof:placetype":"venue"
},
  "geometry": {"coordinates":[-0.018755,51.497986],"type":"Point"}
}