{
  "type": "Feature",
  "properties": {
    "addr:full":"Unit 28, Coppull Enterprise Centre, Mill Lane Chorley Lancashire PR7 5BW",
    "addr:housenumber":"unit 28 coppull enterprise centre",
    "addr:postcode":"pr7 5bw",
    "addr:street":"Mill Lane",
    "iso:country":"GB",
    "sg:address":"Unit 28, Coppull Enterprise Centre, Mill Lane",
    "sg:city":"Chorley",
    "sg:classifiers":[
        {
            "category":"Manufacturing",
            "subcategory":"Petroleum Products",
            "type":"Manufacturing & Wholesale Goods"
        }
    ],
    "sg:phone":"+44 1257 794844",
    "sg:postcode":"PR7 5BW",
    "sg:province":"Lancashire",
    "sg:tags":[
        "double",
        "glazing"
    ],
    "wof:name":"A Humphrey & Sons",
    "wof:placetype":"venue"
},
  "geometry": {"coordinates":[-2.6321339607,53.6520881653],"type":"Point"}
}