{
  "type": "Feature",
  "properties": {
    "addr:full":"66 Hampton Road, Forest Gate London Greater London E7 0NU",
    "addr:housenumber":"66",
    "addr:postcode":"e7 0nu",
    "addr:street":"Hampton Road",
    "iso:country":"GB",
    "sg:address":"66 Hampton Road, Forest Gate",
    "sg:city":"London",
    "sg:classifiers":[
        {
            "category":"Real Estate",
            "subcategory":"Architect",
            "type":"Services"
        }
    ],
    "sg:phone":"+44 20 8519 7669",
    "sg:postcode":"E7 0NU",
    "sg:province":"Greater London",
    "wof:name":"Blanchard Building Services",
    "wof:placetype":"venue"
},
  "geometry": {"coordinates":[0.0307839997,51.5498657227],"type":"Point"}
}