{
  "type": "Feature",
  "properties": {
    "addr:full":"Calthorpe Manor Gatehouses, Calthorpe Street Banbury Oxfordshire OX16 5EX",
    "addr:postcode":"ox16 5ex",
    "addr:street":"Calthorpe Street",
    "iso:country":"GB",
    "sg:address":"Calthorpe Manor Gatehouses, Calthorpe Street",
    "sg:city":"Banbury",
    "sg:classifiers":[
        {
            "category":"Shopping",
            "subcategory":"Department Store",
            "type":"Retail Goods"
        },
        {
            "category":"Home & Garden",
            "subcategory":"Household Appliances",
            "type":"Retail Goods"
        },
        {
            "category":"Utilities",
            "subcategory":"Fuel Oil & Lpg",
            "type":"Services"
        }
    ],
    "sg:phone":"+44 1295 254887",
    "sg:postcode":"OX16 5EX",
    "sg:province":"Oxfordshire",
    "sg:tags":[
        "coal",
        "gas",
        "smokeless"
    ],
    "wof:name":"Higham Solid Fuel Merchants",
    "wof:placetype":"venue"
},
  "geometry": {"coordinates":[-1.3382600546,52.0568275452],"type":"Point"}
}