{
  "type": "Feature",
  "properties": {
    "iso:country":"GB",
    "sg:address":"17 Salford Close",
    "sg:city":"Northampton",
    "sg:classifiers":[
        {
            "category":"Social Services",
            "subcategory":"Job Training",
            "type":"Services"
        }
    ],
    "sg:phone":"+44 1858 575268",
    "sg:postcode":"NN6 6JJ",
    "sg:province":"Northamptonshire",
    "sg:tags":[
        "translator",
        "interpreter"
    ],
    "wof:name":"Barry Ashby",
    "wof:placetype":"venue"
},
  "geometry": {"coordinates":[-1.056608,52.419846],"type":"Point"}
}