{
  "type": "Feature",
  "properties": {
    "addr:full":"5 Howard Park Corner Letchworth Hertfordshire SG6 1PQ",
    "addr:housenumber":"5",
    "addr:postcode":"sg6 1pq",
    "addr:street":"Howard Park;Letchworth",
    "iso:country":"GB",
    "sg:address":"5 Howard Park Corner",
    "sg:city":"Letchworth",
    "sg:classifiers":[
        {
            "category":"Sports & Exercise",
            "subcategory":"Sports Center",
            "type":"Entertainment"
        }
    ],
    "sg:phone":"+44 1462 621621",
    "sg:postcode":"SG6 1PQ",
    "sg:province":"Hertfordshire",
    "sg:tags":[
        "shop",
        "good"
    ],
    "wof:name":"Hydro Active Outdoor Pursuits",
    "wof:placetype":"venue"
},
  "geometry": {"coordinates":[-0.2235739976,51.9809341431],"type":"Point"}
}