{
  "type": "Feature",
  "properties": {
    "iso:country":"GB",
    "sg:address":"Unit 22 Mill St, Uppermill",
    "sg:city":"Oldham",
    "sg:classifiers":[
        {
            "category":"Personal",
            "type":"Services"
        }
    ],
    "sg:postcode":"OL3 6HT",
    "sg:province":"Lancashire",
    "sg:tags":[
        "wedding"
    ],
    "wof:name":"Party Print",
    "wof:placetype":"venue"
},
  "geometry": {"coordinates":[-2.0072538853,53.5465049744],"type":"Point"}
}