{
  "type": "Feature",
  "properties": {
    "addr:full":"1 Vale Road Exmouth Devon EX8 2LZ",
    "addr:housenumber":"1",
    "addr:postcode":"ex8 2lz",
    "addr:street":"Vale Road",
    "iso:country":"GB",
    "sg:address":"1 Vale Road",
    "sg:city":"Exmouth",
    "sg:classifiers":[
        {
            "category":"Building & Trades",
            "subcategory":"Plumbing",
            "type":"Services"
        }
    ],
    "sg:postcode":"EX8 2LZ",
    "sg:province":"Devon",
    "sg:tags":[
        "heating"
    ],
    "wof:name":"A W Howe",
    "wof:placetype":"venue"
},
  "geometry": {"coordinates":[-3.3931660652,50.6241226196],"type":"Point"}
}