{
  "type": "Feature",
  "properties": {
    "iso:country":"GB",
    "sg:address":"Manchester Road",
    "sg:city":"Northwich",
    "sg:classifiers":[
        {
            "category":"Home & Garden",
            "subcategory":"Hardware",
            "type":"Retail Goods"
        }
    ],
    "sg:phone":"+44 1606 48154",
    "sg:postcode":"CW9 5LY",
    "sg:province":"Cheshire",
    "sg:tags":[
        "retailer",
        "diy"
    ],
    "wof:name":"B & Q Supercentre",
    "wof:placetype":"venue"
},
  "geometry": {"coordinates":[-2.497923,53.261856],"type":"Point"}
}