{
  "type": "Feature",
  "properties": {
    "addr:full":"16 Royal Close Broadstairs Kent CT10 2JZ",
    "addr:housenumber":"16",
    "addr:postcode":"ct10 2jz",
    "addr:street":"Royal Close",
    "iso:country":"GB",
    "sg:address":"16 Royal Close",
    "sg:city":"Broadstairs",
    "sg:classifiers":[
        {
            "category":"Building & Trades",
            "subcategory":"Construction",
            "type":"Services"
        }
    ],
    "sg:phone":"+44 1843 869305",
    "sg:postcode":"CT10 2JZ",
    "sg:province":"Kent",
    "sg:tags":[
        "decorator",
        "painter"
    ],
    "wof:name":"Mark Price Decorating",
    "wof:placetype":"venue"
},
  "geometry": {"coordinates":[1.4246259928,51.35887146],"type":"Point"}
}