{
  "type": "Feature",
  "properties": {
    "iso:country":"GB",
    "sg:address":"90 Church Street, Starathleven",
    "sg:city":"Dumbarton",
    "sg:classifiers":[
        {
            "category":"Retail",
            "subcategory":"Funeral Services",
            "type":"Services"
        }
    ],
    "sg:postcode":"G82 1QA",
    "sg:province":"Argyll and Bute",
    "wof:name":"John Kane Funeral Directors",
    "wof:placetype":"venue"
},
  "geometry": {"coordinates":[-4.567622,55.944256],"type":"Point"}
}