{
  "type": "Feature",
  "properties": {
    "iso:country":"GB",
    "sg:address":"5-6 Cascade Centre",
    "sg:city":"Portsmouth",
    "sg:classifiers":[
        {
            "category":"Shopping",
            "subcategory":"Clothing, Apparel, & Fashions",
            "type":"Retail Goods"
        }
    ],
    "sg:phone":"+44 23 9285 1087",
    "sg:postcode":"PO1 4RJ",
    "sg:province":"Hampshire",
    "sg:tags":[
        "shop"
    ],
    "wof:name":"Etam Plc",
    "wof:placetype":"venue"
},
  "geometry": {"coordinates":[-1.087153,50.804382],"type":"Point"}
}