{
  "type": "Feature",
  "properties": {
    "addr:full":"3a Forrest Road Stirling Stirling FK8 1UH",
    "addr:housenumber":"3a",
    "addr:postcode":"fk8 1uh",
    "addr:street":"Forrest Road",
    "iso:country":"GB",
    "sg:address":"3a Forrest Road",
    "sg:city":"Stirling",
    "sg:classifiers":[
        {
            "category":"Building & Trades",
            "subcategory":"Landscaping Services",
            "type":"Services"
        }
    ],
    "sg:phone":"+44 1786 446446",
    "sg:postcode":"FK8 1UH",
    "sg:province":"Stirling",
    "sg:tags":[
        "designer",
        "architect",
        "landscape"
    ],
    "wof:name":"Ian White Associates",
    "wof:placetype":"venue"
},
  "geometry": {"coordinates":[-3.932503,56.124123],"type":"Point"}
}