{
  "type": "Feature",
  "properties": {
    "addr:full":"19-22 Market Place Loughborough Leicestershire LE11 3EB",
    "addr:housenumber":"19-22",
    "addr:postcode":"le11 3eb",
    "addr:street":"Market Place",
    "iso:country":"GB",
    "sg:address":"19-22 Market Place",
    "sg:city":"Loughborough",
    "sg:classifiers":[
        {
            "category":"Community Center",
            "subcategory":"Youth",
            "type":"Public Place"
        }
    ],
    "sg:postcode":"LE11 3EB",
    "sg:province":"Leicestershire",
    "sg:tags":[
        "children's",
        "activity"
    ],
    "wof:name":"Fun & Games",
    "wof:placetype":"venue"
},
  "geometry": {"coordinates":[-1.206604,52.771877],"type":"Point"}
}