{
  "type": "Feature",
  "properties": {
    "addr:full":"Pickham Mill, Watermill Lane, Pett Hastings East Sussex TN35 4HX",
    "addr:postcode":"tn35 4hx",
    "addr:street":"Watermill Lane",
    "iso:country":"GB",
    "sg:address":"Pickham Mill, Watermill Lane, Pett",
    "sg:city":"Hastings",
    "sg:classifiers":[
        {
            "category":"Home & Garden",
            "subcategory":"Furniture",
            "type":"Retail Goods"
        }
    ],
    "sg:phone":"+44 1424 813493",
    "sg:postcode":"TN35 4HX",
    "sg:province":"East Sussex",
    "wof:name":"Mobeltec UK",
    "wof:placetype":"venue"
},
  "geometry": {"coordinates":[0.6634899974,50.8948783875],"type":"Point"}
}