{
  "type": "Feature",
  "properties": {
    "addr:full":"69 Time Square Shopping Centre, High St Sutton Surrey SM1 1LF",
    "addr:postcode":"sm1 1lf",
    "addr:street":"High St",
    "iso:country":"GB",
    "sg:address":"69 Time Square Shopping Centre, High St",
    "sg:city":"Sutton",
    "sg:classifiers":[
        {
            "category":"Home & Garden",
            "subcategory":"Furniture",
            "type":"Retail Goods"
        }
    ],
    "sg:phone":"+44 20 8401 0171",
    "sg:postcode":"SM1 1LF",
    "sg:province":"Surrey",
    "wof:name":"Hughes,John,",
    "wof:placetype":"venue"
},
  "geometry": {"coordinates":[-0.192759,51.362785],"type":"Point"}
}