{
  "type": "Feature",
  "properties": {
    "iso:country":"GB",
    "sg:address":"Elizabeth House, Unit 3 St Oswald Street",
    "sg:city":"Castleford",
    "sg:classifiers":[
        {
            "category":"Professional",
            "subcategory":"Art Services",
            "type":"Services"
        }
    ],
    "sg:phone":"+44 1977 730307",
    "sg:postcode":"WF10 1HS",
    "sg:province":"West Yorkshire",
    "sg:tags":[
        "framing"
    ],
    "wof:name":"Perfections",
    "wof:placetype":"venue"
},
  "geometry": {"coordinates":[-1.353514,53.726452],"type":"Point"}
}