{
  "type": "Feature",
  "properties": {
    "iso:country":"GB",
    "sg:address":"11 West Street",
    "sg:city":"Tavistock",
    "sg:classifiers":[
        {
            "category":"Communications",
            "type":"Services"
        }
    ],
    "sg:phone":"+44 1822 616966",
    "sg:postcode":"PL19 8AD",
    "sg:province":"Devon",
    "sg:tags":[
        "tv",
        "video",
        "radio"
    ],
    "wof:name":"Spares & Repairs",
    "wof:placetype":"venue"
},
  "geometry": {"coordinates":[-4.1466,50.549538],"type":"Point"}
}