{
  "type": "Feature",
  "properties": {
    "addr:full":"24 Dock Street Fleetwood Lancashire FY7 6AG",
    "addr:housenumber":"24",
    "addr:postcode":"fy7 6ag",
    "addr:street":"Dock Street",
    "iso:country":"GB",
    "sg:address":"24 Dock Street",
    "sg:city":"Fleetwood",
    "sg:classifiers":[
        {
            "category":"Shopping",
            "subcategory":"Department Store",
            "type":"Retail Goods"
        }
    ],
    "sg:postcode":"FY7 6AG",
    "sg:province":"Lancashire",
    "wof:name":"Roger Peate",
    "wof:placetype":"venue"
},
  "geometry": {"coordinates":[-3.0064098835,53.9232215881],"type":"Point"}
}