{
  "type": "Feature",
  "properties": {
    "addr:full":"Unit B North Beck Mills, Becks Road Keighley West Yorkshire BD21 1SD",
    "addr:housenumber":"b",
    "addr:postcode":"bd21 1sd",
    "addr:street":"North Beck Mills Becks Road",
    "iso:country":"GB",
    "sg:address":"Unit B North Beck Mills, Becks Road",
    "sg:city":"Keighley",
    "sg:classifiers":[
        {
            "category":"Professional",
            "subcategory":"Business Services",
            "type":"Services"
        }
    ],
    "sg:postcode":"BD21 1SD",
    "sg:province":"West Yorkshire",
    "sg:tags":[
        "accomodation"
    ],
    "wof:name":"R D I (Airedale) Ltd",
    "wof:placetype":"venue"
},
  "geometry": {"coordinates":[-1.91676,53.865051],"type":"Point"}
}