{
  "type": "Feature",
  "properties": {
    "addr:full":"Unit 3 Back Peebles Street Ayr South Ayrshire KA8 8BY",
    "addr:housenumber":"unit 3",
    "addr:postcode":"ka8 8by",
    "addr:street":"Back Peebles Street",
    "iso:country":"GB",
    "sg:address":"Unit 3 Back Peebles Street",
    "sg:city":"Ayr",
    "sg:classifiers":[
        {
            "category":"Autos & Motor Vehicles",
            "subcategory":"Auto Supplies",
            "type":"Retail Goods"
        }
    ],
    "sg:phone":"+44 1292 265096",
    "sg:postcode":"KA8 8BY",
    "sg:province":"South Ayrshire",
    "sg:tags":[
        "component"
    ],
    "wof:name":"Partco Ltd.",
    "wof:placetype":"venue"
},
  "geometry": {"coordinates":[-4.6299791336,55.4704475403],"type":"Point"}
}