{
  "type": "Feature",
  "properties": {
    "addr:full":"Meadowside Granary, South Street Glasgow Glasgow City G11 6JY",
    "addr:postcode":"g11 6jy",
    "addr:street":"South Street",
    "iso:country":"GB",
    "sg:address":"Meadowside Granary, South Street",
    "sg:city":"Glasgow",
    "sg:classifiers":[
        {
            "category":"Professional",
            "subcategory":"Employment Agencies",
            "type":"Services"
        }
    ],
    "sg:phone":"+44 141 338 6898",
    "sg:postcode":"G11 6JY",
    "sg:province":"Glasgow City",
    "sg:tags":[
        "consultant"
    ],
    "wof:name":"Transline",
    "wof:placetype":"venue"
},
  "geometry": {"coordinates":[-4.2425107956,55.8578071594],"type":"Point"}
}