{
  "type": "Feature",
  "properties": {
    "addr:full":"1 West Street Reigate Surrey RH2 9BL",
    "addr:housenumber":"1",
    "addr:postcode":"rh2 9bl",
    "addr:street":"West Street",
    "iso:country":"GB",
    "sg:address":"1 West Street",
    "sg:city":"Reigate",
    "sg:classifiers":[
        {
            "category":"Home & Garden",
            "subcategory":"Home Furnishings",
            "type":"Retail Goods"
        },
        {
            "category":"Home & Garden",
            "subcategory":"Furniture",
            "type":"Retail Goods"
        }
    ],
    "sg:phone":"+44 1737 223473",
    "sg:postcode":"RH2 9BL",
    "sg:province":"Surrey",
    "sg:tags":[
        "pine"
    ],
    "wof:name":"Knotts Pine",
    "wof:placetype":"venue"
},
  "geometry": {"coordinates":[-0.2102919966,51.2380599976],"type":"Point"}
}