{
  "type": "Feature",
  "properties": {
    "addr:full":"Unit D3, Britannia Centre For Enterprise, Pengam Road Blackwood Caerphilly NP12 3SP",
    "addr:housenumber":"d3",
    "addr:postcode":"np12 3sp",
    "addr:street":"Pengam Road",
    "iso:country":"GB",
    "sg:address":"Unit D3, Britannia Centre For Enterprise, Pengam Road",
    "sg:city":"Blackwood",
    "sg:classifiers":[
        {
            "category":"Wholesale",
            "subcategory":"Machinery & Supplies",
            "type":"Manufacturing & Wholesale Goods"
        }
    ],
    "sg:postcode":"NP12 3SP",
    "sg:province":"Caerphilly",
    "sg:tags":[
        "hydraulic"
    ],
    "wof:name":"Dunstan Hydraulics",
    "wof:placetype":"venue"
},
  "geometry": {"coordinates":[-3.1956140995,51.6672744751],"type":"Point"}
}