{
  "type": "Feature",
  "properties": {
    "addr:full":"47 Rumbridge Street, Totton Southampton Hampshire SO40 9DR",
    "addr:housenumber":"47",
    "addr:postcode":"so40 9dr",
    "addr:street":"Rumbridge Street",
    "iso:country":"GB",
    "sg:address":"47 Rumbridge Street, Totton",
    "sg:city":"Southampton",
    "sg:classifiers":[
        {
            "category":"Building & Trades",
            "subcategory":"Cleaning & Sanitation",
            "type":"Services"
        }
    ],
    "sg:phone":"+44 23 8086 6711",
    "sg:postcode":"SO40 9DR",
    "sg:province":"Hampshire",
    "sg:tags":[
        "commercial"
    ],
    "wof:name":"Sparclean Cleaning Services",
    "wof:placetype":"venue"
},
  "geometry": {"coordinates":[-1.487011,50.914989],"type":"Point"}
}