{
  "type": "Feature",
  "properties": {
    "addr:full":"77 Southlands Drive, West Cross Swansea Swansea SA3 5RJ",
    "addr:housenumber":"77",
    "addr:postcode":"sa3 5rj",
    "addr:street":"Southlands Drive West Cross",
    "iso:country":"GB",
    "sg:address":"77 Southlands Drive, West Cross",
    "sg:city":"Swansea",
    "sg:classifiers":[
        {
            "category":"Utilities",
            "subcategory":"Fuel Oil & Lpg",
            "type":"Services"
        }
    ],
    "sg:postcode":"SA3 5RJ",
    "sg:province":"Swansea",
    "sg:tags":[
        "coal",
        "smokeless"
    ],
    "wof:name":"Bresnan Bros",
    "wof:placetype":"venue"
},
  "geometry": {"coordinates":[-4.0125961304,51.5793838501],"type":"Point"}
}