{
  "type": "Feature",
  "properties": {
    "addr:full":"Llanwern Works Newport East Riding of Yorkshire NP9 0XQ",
    "addr:housenumber":"llanwern",
    "addr:postcode":"0xq",
    "iso:country":"GB",
    "sg:address":"Llanwern Works",
    "sg:city":"Newport",
    "sg:classifiers":[
        {
            "category":"Wholesale",
            "subcategory":"Scrap",
            "type":"Manufacturing & Wholesale Goods"
        }
    ],
    "sg:postcode":"NP9 0XQ",
    "sg:province":"East Riding of Yorkshire",
    "sg:tags":[
        "waste",
        "metal"
    ],
    "wof:name":"Heckett Ltd.",
    "wof:placetype":"venue"
},
  "geometry": {"coordinates":[-2.9144101143,51.5890007019],"type":"Point"}
}