{
  "type": "Feature",
  "properties": {
    "iso:country":"GB",
    "sg:address":"Bryn-heulog Road, Croeserw",
    "sg:city":"Port Talbot",
    "sg:classifiers":[
        {
            "category":"Organizations",
            "subcategory":"Membership Organization",
            "type":"Services"
        }
    ],
    "sg:postcode":"SA13 3RS",
    "sg:province":"Neath Port Talbot",
    "sg:tags":[
        "club"
    ],
    "wof:name":"Croeserw Workmans Club",
    "wof:placetype":"venue"
},
  "geometry": {"coordinates":[-3.639737,51.649601],"type":"Point"}
}