{
  "type": "Feature",
  "properties": {
    "addr:full":"18 Hurricane Way Norwich Norfolk NR6 6EY",
    "addr:housenumber":"18",
    "addr:postcode":"nr6 6ey",
    "addr:street":"Hurricane Way",
    "iso:country":"GB",
    "sg:address":"18 Hurricane Way",
    "sg:city":"Norwich",
    "sg:classifiers":[
        {
            "category":"Autos & Motor Vehicles",
            "subcategory":"Automobile Sales",
            "type":"Retail Goods"
        }
    ],
    "sg:phone":"+44 1603 485651",
    "sg:postcode":"NR6 6EY",
    "sg:province":"Norfolk",
    "sg:tags":[
        "car"
    ],
    "wof:name":"Howes Of Fakenham",
    "wof:placetype":"venue"
},
  "geometry": {"coordinates":[1.288665,52.667809],"type":"Point"}
}