{
  "type": "Feature",
  "properties": {
    "iso:country":"GB",
    "sg:address":"422 Broomfield Road",
    "sg:city":"Glasgow",
    "sg:classifiers":[
        {
            "category":"Education",
            "subcategory":"School",
            "type":"Public Place"
        }
    ],
    "sg:phone":"+44 141 558 5224",
    "sg:postcode":"G21 3UT",
    "sg:province":"East Dunbartonshire",
    "sg:tags":[
        "local",
        "authority"
    ],
    "wof:name":"Balornock Primary School",
    "wof:placetype":"venue"
},
  "geometry": {"coordinates":[-4.2149291039,55.8840408325],"type":"Point"}
}