{
  "type": "Feature",
  "properties": {
    "iso:country":"GB",
    "sg:address":"38 Wellington Street",
    "sg:city":"London",
    "sg:classifiers":[
        {
            "category":"Bars & Pubs",
            "subcategory":"Nightclub",
            "type":"Food & Drink"
        }
    ],
    "sg:phone":"+44 20 8854 3933",
    "sg:postcode":"SE18 6PE",
    "sg:province":"Greater London",
    "sg:tags":[
        "club",
        "night"
    ],
    "wof:name":"Fufion",
    "wof:placetype":"venue"
},
  "geometry": {"coordinates":[0.063698,51.488983],"type":"Point"}
}