{
  "type": "Feature",
  "properties": {
    "addr:full":"106 Gifford Street London Greater London N1 0DF",
    "addr:housenumber":"106",
    "addr:postcode":"n1 0df",
    "addr:street":"Gifford Street",
    "iso:country":"GB",
    "sg:address":"106 Gifford Street",
    "sg:city":"London",
    "sg:classifiers":[
        {
            "category":"Autos & Motor Vehicles",
            "subcategory":"Motorcycle Sales",
            "type":"Retail Goods"
        }
    ],
    "sg:postcode":"N1 0DF",
    "sg:province":"Greater London",
    "sg:tags":[
        "chauffeur",
        "driven",
        "car"
    ],
    "wof:name":"Fleetwood Classic Limousines",
    "wof:placetype":"venue"
},
  "geometry": {"coordinates":[-0.121708,51.540516],"type":"Point"}
}