{
  "type": "Feature",
  "properties": {
    "addr:full":"Unit 56 Northumberland Dock, Hayhole Road North Shields Tyne and Wear NE29 6DY",
    "addr:housenumber":"unit 56",
    "addr:postcode":"ne29 6dy",
    "addr:street":"Northumberland Dock Hayhole Road",
    "iso:country":"GB",
    "sg:address":"Unit 56 Northumberland Dock, Hayhole Road",
    "sg:city":"North Shields",
    "sg:classifiers":[
        {
            "category":"Manufacturing",
            "subcategory":"Textiles",
            "type":"Manufacturing & Wholesale Goods"
        },
        {
            "category":"Home & Garden",
            "subcategory":"Furniture",
            "type":"Retail Goods"
        }
    ],
    "sg:phone":"+44 191 257 4607",
    "sg:postcode":"NE29 6DY",
    "sg:province":"Tyne and Wear",
    "sg:tags":[
        "made-up"
    ],
    "wof:name":"Ponden Mill Ltd.",
    "wof:placetype":"venue"
},
  "geometry": {"coordinates":[-1.4630500078,54.9907798767],"type":"Point"}
}