{
  "type": "Feature",
  "properties": {
    "addr:full":"110-112 Digbeth Birmingham West Midlands B5 6DH",
    "addr:housenumber":"110-112",
    "addr:postcode":"b5 6dh",
    "addr:street":"Digbeth",
    "iso:country":"GB",
    "sg:address":"110-112 Digbeth",
    "sg:city":"Birmingham",
    "sg:classifiers":[
        {
            "category":"Community Center",
            "subcategory":"Social",
            "type":"Public Place"
        }
    ],
    "sg:phone":"+44 121 643 4051",
    "sg:postcode":"B5 6DH",
    "sg:province":"West Midlands",
    "sg:tags":[
        "frozen",
        "food",
        "freezer",
        "centre"
    ],
    "wof:name":"R&Z Isalm",
    "wof:placetype":"venue"
},
  "geometry": {"coordinates":[-1.8902930021,52.4761695862],"type":"Point"}
}