{
  "type": "Feature",
  "properties": {
    "addr:full":"43a Chatsworth Road Morecambe Lancashire LA4 4JH",
    "addr:housenumber":"43a",
    "addr:postcode":"la4 4jh",
    "addr:street":"Chatsworth Road",
    "iso:country":"GB",
    "sg:address":"43a Chatsworth Road",
    "sg:city":"Morecambe",
    "sg:classifiers":[
        {
            "category":"Retail",
            "subcategory":"Veterinary Services",
            "type":"Services"
        }
    ],
    "sg:phone":"+44 1524 424817",
    "sg:postcode":"LA4 4JH",
    "sg:province":"Lancashire",
    "sg:tags":[
        "surgeon",
        "activity"
    ],
    "wof:name":"D J Longley",
    "wof:placetype":"venue"
},
  "geometry": {"coordinates":[-2.8768351078,54.0651283264],"type":"Point"}
}