{
  "type": "Feature",
  "properties": {
    "addr:full":"Pengam Road Industrial Estate, Aberbargoed Bargoed Caerphilly CF81 9FW",
    "addr:postcode":"cf81 9fw",
    "addr:street":"Pengam Road Industrial Estate",
    "iso:country":"GB",
    "sg:address":"Pengam Road Industrial Estate, Aberbargoed",
    "sg:city":"Bargoed",
    "sg:classifiers":[
        {
            "category":"Manufacturing",
            "subcategory":"Musical Instruments",
            "type":"Manufacturing & Wholesale Goods"
        },
        {
            "category":"Shopping",
            "type":"Retail Goods"
        }
    ],
    "sg:phone":"+44 1443 830830",
    "sg:postcode":"CF81 9FW",
    "sg:province":"Caerphilly",
    "sg:tags":[
        "med",
        "manufacturer",
        "scientific",
        "apparatus",
        "machinery"
    ],
    "wof:name":"Bibby Sterilin Ltd.",
    "wof:placetype":"venue"
},
  "geometry": {"coordinates":[-3.219684,51.68782],"type":"Point"}
}