{
  "type": "Feature",
  "properties": {
    "iso:country":"GB",
    "sg:address":"North Moors, Slyfield Indust Est",
    "sg:city":"Guildford",
    "sg:classifiers":[
        {
            "category":"Building & Trades",
            "subcategory":"Electrical",
            "type":"Services"
        }
    ],
    "sg:phone":"+44 1483 502202",
    "sg:postcode":"GU1 1SE",
    "sg:province":"Surrey",
    "sg:tags":[
        "consultant",
        "lighting"
    ],
    "wof:name":"Total Lighting Services Ltd",
    "wof:placetype":"venue"
},
  "geometry": {"coordinates":[-0.563809,51.263866],"type":"Point"}
}