{
  "type": "Feature",
  "properties": {
    "iso:country":"GB",
    "sg:address":"Stockton Business Centre",
    "sg:city":"Stockton-on-tees",
    "sg:classifiers":[
        {
            "category":"Manufacturing",
            "subcategory":"Glass & Minerals",
            "type":"Manufacturing & Wholesale Goods"
        }
    ],
    "sg:phone":"+44 1642 801020",
    "sg:postcode":"TS18 1DW",
    "sg:province":"Durham",
    "sg:tags":[
        "mnfr",
        "glassware",
        "china"
    ],
    "wof:name":"Artisans",
    "wof:placetype":"venue"
},
  "geometry": {"coordinates":[-1.3161599636,54.5633201599],"type":"Point"}
}