{
  "type": "Feature",
  "properties": {
    "addr:full":", Cilgerran Cardigan Ceredigion SA43 2TB",
    "addr:postcode":"sa43 2tb",
    "addr:street":"Cilgerran",
    "iso:country":"GB",
    "sg:address":", Cilgerran",
    "sg:city":"Cardigan",
    "sg:classifiers":[
        {
            "category":"Landmark",
            "subcategory":"Tourist Attraction",
            "type":"Public Place"
        }
    ],
    "sg:phone":"+44 1239 621600",
    "sg:postcode":"SA43 2TB",
    "sg:province":"Ceredigion",
    "sg:tags":[
        "interest"
    ],
    "wof:name":"The Welsh Wildlife Centre",
    "wof:placetype":"venue"
},
  "geometry": {"coordinates":[-4.633964,52.055576],"type":"Point"}
}