{
  "type": "Feature",
  "properties": {
    "iso:country":"GB",
    "sg:address":"Sombourne Drive, Leigh Park",
    "sg:city":"Havant",
    "sg:classifiers":[
        {
            "category":"Organizations",
            "subcategory":"Membership Organization",
            "type":"Services"
        }
    ],
    "sg:phone":"+44 23 9247 6321",
    "sg:postcode":"PO9 5AN",
    "sg:province":"Hampshire",
    "sg:tags":[
        "club",
        "social"
    ],
    "wof:name":"Crown Bingo & Social Club",
    "wof:placetype":"venue"
},
  "geometry": {"coordinates":[-0.9829800129,50.8688430786],"type":"Point"}
}