{
  "type": "Feature",
  "properties": {
    "iso:country":"GB",
    "sg:address":"75-79 Regent Street",
    "sg:city":"Cambridge",
    "sg:classifiers":[
        {
            "category":"Real Estate",
            "subcategory":"Developer",
            "type":"Services"
        }
    ],
    "sg:postcode":"CB2 1BE",
    "sg:province":"Cambridgeshire",
    "sg:tags":[
        "property"
    ],
    "wof:name":"East Anglian Cement Company,Limited(The)",
    "wof:placetype":"venue"
},
  "geometry": {"coordinates":[0.1265300065,52.2004623413],"type":"Point"}
}