{
  "type": "Feature",
  "properties": {
    "iso:country":"GB",
    "sg:address":"34b Broad Street",
    "sg:city":"Newent",
    "sg:classifiers":[
        {
            "category":"Retail",
            "subcategory":"Laundry & Dry Cleaning",
            "type":"Services"
        }
    ],
    "sg:postcode":"GL18 1AJ",
    "sg:province":"Gloucestershire",
    "sg:tags":[
        "alteration"
    ],
    "wof:name":"Newent Quality Cleaners",
    "wof:placetype":"venue"
},
  "geometry": {"coordinates":[-2.406384,51.930908],"type":"Point"}
}