{
  "type": "Feature",
  "properties": {
    "addr:full":"1 Cross Street, Aberfan Merthyr Tydfil Caerphilly CF48 4NX",
    "addr:housenumber":"1",
    "addr:postcode":"cf48 4nx",
    "addr:street":"Cross Street",
    "iso:country":"GB",
    "sg:address":"1 Cross Street, Aberfan",
    "sg:city":"Merthyr Tydfil",
    "sg:classifiers":[
        {
            "category":"Shopping",
            "subcategory":"Department Store",
            "type":"Retail Goods"
        },
        {
            "category":"Food & Beverages",
            "subcategory":"Groceries & Convenience Stores",
            "type":"Retail Goods"
        }
    ],
    "sg:phone":"+44 1443 690279",
    "sg:postcode":"CF48 4NX",
    "sg:province":"Caerphilly",
    "wof:name":"Lewis Stores",
    "wof:placetype":"venue"
},
  "geometry": {"coordinates":[-3.342174,51.686928],"type":"Point"}
}