{
  "type": "Feature",
  "properties": {
    "addr:full":"46 Dellmont Rd, Houghton Regis Dunstable Bedfordshire LU5 5HU",
    "addr:housenumber":"46",
    "addr:postcode":"lu5 5hu",
    "addr:street":"Dellmont Rd",
    "iso:country":"GB",
    "sg:address":"46 Dellmont Rd, Houghton Regis",
    "sg:city":"Dunstable",
    "sg:classifiers":[
        {
            "category":"Freight",
            "type":"Transportation"
        }
    ],
    "sg:postcode":"LU5 5HU",
    "sg:province":"Bedfordshire",
    "sg:tags":[
        "haulage",
        "road"
    ],
    "wof:name":"Heard,David,",
    "wof:placetype":"venue"
},
  "geometry": {"coordinates":[-0.5225039721,51.9074058533],"type":"Point"}
}