{
  "type": "Feature",
  "properties": {
    "iso:country":"GB",
    "sg:address":"Unit 3, Trellick Tower, 5 Golborne Rd",
    "sg:city":"London",
    "sg:classifiers":[
        {
            "category":"Social Services",
            "type":"Services"
        },
        {
            "category":"Government",
            "subcategory":"Office",
            "type":"Public Place"
        }
    ],
    "sg:postcode":"W10 5NX",
    "sg:province":"Greater London",
    "sg:tags":[
        "local"
    ],
    "wof:name":"Royal Borough of Kensington & Chelsea",
    "wof:placetype":"venue"
},
  "geometry": {"coordinates":[-0.20569,51.523998],"type":"Point"}
}