{
  "type": "Feature",
  "properties": {
    "addr:full":"Upper Lodge Farm, The Broyle, Ringmer Lewes East Sussex BN8 5AP",
    "addr:housenumber":"the;ringmer",
    "addr:postcode":"bn8 5ap",
    "iso:country":"GB",
    "sg:address":"Upper Lodge Farm, The Broyle, Ringmer",
    "sg:city":"Lewes",
    "sg:classifiers":[
        {
            "category":"Farming",
            "subcategory":"Dairy Farm",
            "type":"Manufacturing & Wholesale Goods"
        },
        {
            "category":"Farming",
            "subcategory":"Farm",
            "type":"Manufacturing & Wholesale Goods"
        }
    ],
    "sg:phone":"+44 1825 841011",
    "sg:postcode":"BN8 5AP",
    "sg:province":"East Sussex",
    "sg:tags":[
        "mixed",
        "crop",
        "farmer"
    ],
    "wof:name":"J R Farnes",
    "wof:placetype":"venue"
},
  "geometry": {"coordinates":[0.059079,50.894077],"type":"Point"}
}