{
  "type": "Feature",
  "properties": {
    "addr:full":"50 Knifesmithgate Chesterfield Derbyshire S40 1RQ",
    "addr:housenumber":"50",
    "addr:postcode":"s40 1rq",
    "addr:street":"Knifesmithgate",
    "iso:country":"GB",
    "sg:address":"50 Knifesmithgate",
    "sg:city":"Chesterfield",
    "sg:classifiers":[
        {
            "category":"Retail",
            "subcategory":"Laundry & Dry Cleaning",
            "type":"Services"
        }
    ],
    "sg:postcode":"S40 1RQ",
    "sg:province":"Derbyshire",
    "sg:tags":[
        "alteration"
    ],
    "wof:name":"Greenfields Tailors",
    "wof:placetype":"venue"
},
  "geometry": {"coordinates":[-1.4267259836,53.2361831665],"type":"Point"}
}