{
  "type": "Feature",
  "properties": {
    "addr:full":"Coedylade Farm, Trelydan Welshpool Shropshire SY21 9HL",
    "addr:postcode":"sy21 9hl",
    "iso:country":"GB",
    "sg:address":"Coedylade Farm, Trelydan",
    "sg:city":"Welshpool",
    "sg:classifiers":[
        {
            "category":"Farming",
            "subcategory":"Farm",
            "type":"Manufacturing & Wholesale Goods"
        }
    ],
    "sg:postcode":"SY21 9HL",
    "sg:province":"Shropshire",
    "sg:tags":[
        "mixed",
        "crop"
    ],
    "wof:name":"Clayton,Gareth",
    "wof:placetype":"venue"
},
  "geometry": {"coordinates":[-3.1414361,52.6883049011],"type":"Point"}
}