{
  "type": "Feature",
  "properties": {
    "iso:country":"GB",
    "sg:address":"134-135 London Road",
    "sg:city":"Dover",
    "sg:classifiers":[
        {
            "category":"Retail",
            "subcategory":"Event Space",
            "type":"Services"
        }
    ],
    "sg:phone":"+44 1304 201644",
    "sg:postcode":"CT17 0TG",
    "sg:province":"Kent",
    "sg:tags":[
        "exhibition",
        "organiser"
    ],
    "wof:name":"East Kent Fairs",
    "wof:placetype":"venue"
},
  "geometry": {"coordinates":[1.297228,51.136166],"type":"Point"}
}