{
  "type": "Feature",
  "properties": {
    "addr:full":"16 Bramley Road, Bramhall Stockport Cheshire SK7 2DP",
    "addr:housenumber":"16",
    "addr:postcode":"sk7 2dp",
    "addr:street":"Bramley Road",
    "iso:country":"GB",
    "sg:address":"16 Bramley Road, Bramhall",
    "sg:city":"Stockport",
    "sg:classifiers":[
        {
            "category":"Shopping",
            "subcategory":"Musical Instruments",
            "type":"Retail Goods"
        }
    ],
    "sg:phone":"+44 161 439 3894",
    "sg:postcode":"SK7 2DP",
    "sg:province":"Cheshire",
    "sg:tags":[
        "piano",
        "tuning",
        "maintenance"
    ],
    "wof:name":"MICHAEL DALE",
    "wof:placetype":"venue"
},
  "geometry": {"coordinates":[-2.1612899303,53.3588104248],"type":"Point"}
}