{
  "type": "Feature",
  "properties": {
    "addr:full":"8 Brampton Road Bexleyheath Kent DA7 4EY",
    "addr:housenumber":"8",
    "addr:postcode":"da7 4ey",
    "addr:street":"Brampton Road",
    "iso:country":"GB",
    "sg:address":"8 Brampton Road",
    "sg:city":"Bexleyheath",
    "sg:classifiers":[
        {
            "category":"Organizations",
            "subcategory":"Non-profit Organization",
            "type":"Services"
        }
    ],
    "sg:phone":"+44 20 8304 0911",
    "sg:postcode":"DA7 4EY",
    "sg:province":"Kent",
    "sg:tags":[
        "charitable",
        "organisation",
        "voluntary",
        "charity"
    ],
    "sg:website":"http://www.bvsc.co.uk",
    "wof:name":"Bexley Voluntary Service Council Ltd.",
    "wof:placetype":"venue"
},
  "geometry": {"coordinates":[0.1270789951,51.4612045288],"type":"Point"}
}