{
  "type": "Feature",
  "properties": {
    "iso:country":"GB",
    "sg:address":"1 North St, Downend",
    "sg:city":"Bristol",
    "sg:classifiers":[
        {
            "category":"Communications",
            "type":"Services"
        }
    ],
    "sg:postcode":"BS16 5SY",
    "sg:province":"City of Bristol",
    "sg:tags":[
        "tv",
        "video",
        "radio"
    ],
    "wof:name":"1ST Satellite & Aerial Shop",
    "wof:placetype":"venue"
},
  "geometry": {"coordinates":[-2.506597,51.483212],"type":"Point"}
}