{
  "type": "Feature",
  "properties": {
    "addr:full":"Unit 14, Steven Road Industrial Estate Huntly Aberdeenshire AB54 5SX",
    "addr:housenumber":"unit 14",
    "addr:postcode":"ab54 5sx",
    "addr:street":"Steven Road Industrial Estate",
    "iso:country":"GB",
    "sg:address":"Unit 14, Steven Road Industrial Estate",
    "sg:city":"Huntly",
    "sg:classifiers":[
        {
            "category":"Shopping",
            "type":"Retail Goods"
        }
    ],
    "sg:phone":"+44 1466 792413",
    "sg:postcode":"AB54 5SX",
    "sg:province":"Aberdeenshire",
    "sg:tags":[
        "merchant"
    ],
    "wof:name":"Towns & Carnie Ltd.",
    "wof:placetype":"venue"
},
  "geometry": {"coordinates":[-2.7934091091,57.4425811768],"type":"Point"}
}