{
  "type": "Feature",
  "properties": {
    "addr:full":"Lonsdale House, High Street Lutterworth Leicestershire LE17 4AD",
    "addr:postcode":"le17 4ad",
    "addr:street":"High Street",
    "iso:country":"GB",
    "sg:address":"Lonsdale House, High Street",
    "sg:city":"Lutterworth",
    "sg:classifiers":[
        {
            "category":"Professional",
            "subcategory":"Accounting & Tax Preparation",
            "type":"Services"
        }
    ],
    "sg:phone":"+44 1455 556143",
    "sg:postcode":"LE17 4AD",
    "sg:province":"Leicestershire",
    "sg:tags":[
        "accountant",
        "activity"
    ],
    "wof:name":"Crowfoot & Co.",
    "wof:placetype":"venue"
},
  "geometry": {"coordinates":[-1.200097,52.45507],"type":"Point"}
}