{
  "type": "Feature",
  "properties": {
    "iso:country":"GB",
    "sg:address":"302 High Street",
    "sg:city":"Slough",
    "sg:classifiers":[
        {
            "category":"Banks & Credit Unions",
            "subcategory":"Financial Services",
            "type":"Services"
        }
    ],
    "sg:phone":"+44 1753 573211",
    "sg:postcode":"SL1 1ED",
    "sg:province":"Berkshire",
    "sg:tags":[
        "consultant"
    ],
    "wof:name":"British Credit Trust Finance Ltd.",
    "wof:placetype":"venue"
},
  "geometry": {"coordinates":[-0.586179,51.507545],"type":"Point"}
}