{
  "type": "Feature",
  "properties": {
    "addr:full":"20 Hawkes Drive, Heathcote Industrial Estate Warwick Warwickshire CV34 6LX",
    "addr:housenumber":"20",
    "addr:postcode":"cv34 6lx",
    "addr:street":"Hawkes Drive;Industrial Estate",
    "iso:country":"GB",
    "sg:address":"20 Hawkes Drive, Heathcote Industrial Estate",
    "sg:city":"Warwick",
    "sg:classifiers":[
        {
            "category":"Shopping",
            "subcategory":"Computers & Home Electronics",
            "type":"Retail Goods"
        }
    ],
    "sg:phone":"+44 1926 431249",
    "sg:postcode":"CV34 6LX",
    "sg:province":"Warwickshire",
    "sg:tags":[
        "mnfr",
        "system",
        "intercom"
    ],
    "wof:name":"Autocom Products Ltd.",
    "wof:placetype":"venue"
},
  "geometry": {"coordinates":[-1.5484249592,52.2718887329],"type":"Point"}
}