{
  "type": "Feature",
  "properties": {
    "iso:country":"GB",
    "sg:address":"26 Evelyn Street",
    "sg:city":"London",
    "sg:classifiers":[
        {
            "category":"Shopping",
            "subcategory":"Department Store",
            "type":"Retail Goods"
        }
    ],
    "sg:phone":"+44 20 8692 1684",
    "sg:postcode":"SE8 5DG",
    "sg:province":"Greater London",
    "wof:name":"Evelyn Street Post Office",
    "wof:placetype":"venue"
},
  "geometry": {"coordinates":[-0.040423,51.488861],"type":"Point"}
}