{
  "type": "Feature",
  "properties": {
    "addr:full":"43 Piccadilly, Hanley Stoke-on-trent Staffordshire ST1 1EN",
    "addr:housenumber":"43",
    "addr:postcode":"staffordshire st1 1en",
    "addr:street":"Piccadilly",
    "iso:country":"GB",
    "sg:address":"43 Piccadilly, Hanley",
    "sg:city":"Stoke-on-trent",
    "sg:classifiers":[
        {
            "category":"Shopping",
            "subcategory":"Thrift Store",
            "type":"Retail Goods"
        }
    ],
    "sg:phone":"+44 1782 208513",
    "sg:postcode":"ST1 1EN",
    "sg:province":"Staffordshire",
    "sg:tags":[
        "shop",
        "charity"
    ],
    "wof:name":"Sue Ryder Foundation",
    "wof:placetype":"venue"
},
  "geometry": {"coordinates":[-2.1771171093,53.0245246887],"type":"Point"}
}