{
  "type": "Feature",
  "properties": {
    "addr:full":"5 Adbert Drive, East Farleigh Maidstone Kent ME15 0DE",
    "addr:housenumber":"5",
    "addr:postcode":"me15 0de",
    "addr:street":"Adbert Drive East",
    "iso:country":"GB",
    "sg:address":"5 Adbert Drive, East Farleigh",
    "sg:city":"Maidstone",
    "sg:classifiers":[
        {
            "category":"Professional",
            "subcategory":"Secretarial Services",
            "type":"Services"
        }
    ],
    "sg:phone":"+44 1622 741730",
    "sg:postcode":"ME15 0DE",
    "sg:province":"Kent",
    "wof:name":"Classic Secretarial Services",
    "wof:placetype":"venue"
},
  "geometry": {"coordinates":[0.486712,51.237556],"type":"Point"}
}