{
  "type": "Feature",
  "properties": {
    "iso:country":"GB",
    "sg:address":"Melrose Ho, 1st Floor, 15-23 Cadogan St",
    "sg:city":"Glasgow",
    "sg:classifiers":[
        {
            "category":"Organizations",
            "subcategory":"Non-profit Organization",
            "type":"Services"
        }
    ],
    "sg:phone":"+44 141 204 2270",
    "sg:postcode":"G2 6QQ",
    "sg:province":"Glasgow City",
    "sg:tags":[
        "organisation",
        "voluntary",
        "charity"
    ],
    "wof:name":"Glasgow Association For Mental Health",
    "wof:placetype":"venue"
},
  "geometry": {"coordinates":[-4.26024,55.859631],"type":"Point"}
}