{
  "type": "Feature",
  "properties": {
    "addr:full":"20 Portland Terrace, Jesmond Newcastle-upon-tyne Tyne and Wear NE2 1QQ",
    "addr:housenumber":"20",
    "addr:postcode":"ne2 1qq",
    "addr:street":"Portland Terrace",
    "iso:country":"GB",
    "sg:address":"20 Portland Terrace, Jesmond",
    "sg:city":"Newcastle-upon-tyne",
    "sg:classifiers":[
        {
            "category":"Building & Trades",
            "subcategory":"Construction",
            "type":"Services"
        }
    ],
    "sg:phone":"+44 191 281 0835",
    "sg:postcode":"NE2 1QQ",
    "sg:province":"Tyne and Wear",
    "sg:tags":[
        "builder"
    ],
    "wof:name":"Sendrig Construction Ltd.",
    "wof:placetype":"venue"
},
  "geometry": {"coordinates":[-1.6024849415,54.9814682007],"type":"Point"}
}