{
  "type": "Feature",
  "properties": {
    "iso:country":"GB",
    "sg:address":"Concorde Rd",
    "sg:city":"Norwich",
    "sg:classifiers":[
        {
            "category":"Autos & Motor Vehicles",
            "subcategory":"Auto Supplies",
            "type":"Retail Goods"
        }
    ],
    "sg:phone":"+44 1603 787474",
    "sg:postcode":"NR6 6BE",
    "sg:province":"Norfolk",
    "sg:tags":[
        "car",
        "lacquer",
        "paint"
    ],
    "wof:name":"Movac  Group Ltd (Norwich Depot)",
    "wof:placetype":"venue"
},
  "geometry": {"coordinates":[1.287538,52.659866],"type":"Point"}
}