{
  "type": "Feature",
  "properties": {
    "addr:full":"Coldeast Way Southampton Hampshire SO31 7ZT",
    "addr:postcode":"so31 7zt",
    "addr:street":"Coldeast Way",
    "iso:country":"GB",
    "sg:address":"Coldeast Way",
    "sg:city":"Southampton",
    "sg:classifiers":[
        {
            "category":"Health Services",
            "subcategory":"Hospital",
            "type":"Services"
        }
    ],
    "sg:phone":"+44 1489 578847",
    "sg:postcode":"SO31 7ZT",
    "sg:province":"Hampshire",
    "wof:name":"Rivendale",
    "wof:placetype":"venue"
},
  "geometry": {"coordinates":[-1.276949,50.873169],"type":"Point"}
}