{
  "type": "Feature",
  "properties": {
    "addr:full":"11 Percy Terrace Beltring Road Tunbridge Wells Kent TN4 9RH",
    "addr:housenumber":"11",
    "addr:postcode":"tn4 9rh",
    "addr:street":"Percy Terrace Beltring Road",
    "iso:country":"GB",
    "sg:address":"11 Percy Terrace Beltring Road",
    "sg:city":"Tunbridge Wells",
    "sg:classifiers":[
        {
            "category":"Professional",
            "subcategory":"Computer Services",
            "type":"Services"
        }
    ],
    "sg:postcode":"TN4 9RH",
    "sg:province":"Kent",
    "sg:tags":[
        "consultant"
    ],
    "wof:name":"Chromel Ltd",
    "wof:placetype":"venue"
},
  "geometry": {"coordinates":[0.2585000098,51.1432189941],"type":"Point"}
}