{
  "type": "Feature",
  "properties": {
    "addr:full":"Pantoily, Cefngorwydd Llangammarch Wells Powys LD4 4DL",
    "addr:postcode":"ld4 4dl",
    "addr:street":"Llangammarch Wells",
    "iso:country":"GB",
    "sg:address":"Pantoily, Cefngorwydd",
    "sg:city":"Llangammarch Wells",
    "sg:classifiers":[
        {
            "category":"Banks & Credit Unions",
            "subcategory":"Investment Brokerage",
            "type":"Services"
        }
    ],
    "sg:postcode":"LD4 4DL",
    "sg:province":"Powys",
    "sg:tags":[
        "contractor"
    ],
    "wof:name":"Richard C & Susan Martin",
    "wof:placetype":"venue"
},
  "geometry": {"coordinates":[-3.5557758808,52.1129798889],"type":"Point"}
}