{
  "type": "Feature",
  "properties": {
    "addr:full":"Hawk Works, Mary Street Sheffield South Yorkshire S1 3JN",
    "addr:postcode":"s1 3jn",
    "addr:street":"Mary Street",
    "iso:country":"GB",
    "sg:address":"Hawk Works, Mary Street",
    "sg:city":"Sheffield",
    "sg:classifiers":[
        {
            "category":"Manufacturing",
            "subcategory":"Tools & Machinery",
            "type":"Manufacturing & Wholesale Goods"
        }
    ],
    "sg:postcode":"S1 3JN",
    "sg:province":"South Yorkshire",
    "sg:tags":[
        "stone",
        "cutting"
    ],
    "wof:name":"P F Osborne & Sons Ltd.",
    "wof:placetype":"venue"
},
  "geometry": {"coordinates":[-1.464544,53.38311],"type":"Point"}
}