{
  "type": "Feature",
  "properties": {
    "addr:full":"Atlantic Ho, 351 Oxford St London Greater London W1C 2JF",
    "addr:housenumber":"351",
    "addr:postcode":"w1c 2jf",
    "addr:street":"Oxford St",
    "iso:country":"GB",
    "sg:address":"Atlantic Ho, 351 Oxford St",
    "sg:city":"London",
    "sg:classifiers":[
        {
            "category":"Professional",
            "subcategory":"Management & Consulting",
            "type":"Services"
        }
    ],
    "sg:postcode":"W1C 2JF",
    "sg:province":"Greater London",
    "sg:tags":[
        "consultant",
        "business"
    ],
    "wof:name":"Human Resource Partnership Ltd",
    "wof:placetype":"venue"
},
  "geometry": {"coordinates":[-0.1478800029,51.5144386292],"type":"Point"}
}