{
  "type": "Feature",
  "properties": {
    "iso:country":"GB",
    "sg:address":"Mission Hall, Shaw Lane",
    "sg:city":"Markfield",
    "sg:classifiers":[
        {
            "category":"Arts & Performance",
            "subcategory":"Music",
            "type":"Entertainment"
        }
    ],
    "sg:phone":"+44 1530 244615",
    "sg:postcode":"LE67 9PU",
    "sg:province":"Leicestershire",
    "sg:tags":[
        "musician",
        "composer"
    ],
    "wof:name":"William Davis Construction Group Band",
    "wof:placetype":"venue"
},
  "geometry": {"coordinates":[-1.2769340277,52.6901893616],"type":"Point"}
}