{
  "type": "Feature",
  "properties": {
    "iso:country":"GB",
    "sg:address":"99 Manor Rd",
    "sg:city":"Erith",
    "sg:classifiers":[
        {
            "category":"Food & Beverages",
            "subcategory":"Groceries & Convenience Stores",
            "type":"Retail Goods"
        }
    ],
    "sg:phone":"+44 1322 348278",
    "sg:postcode":"DA8 2AE",
    "sg:province":"Kent",
    "sg:website":"http://www.londis.co.uk",
    "wof:name":"Londis",
    "wof:placetype":"venue"
},
  "geometry": {"coordinates":[0.185683,51.478313],"type":"Point"}
}