{
  "type": "Feature",
  "properties": {
    "iso:country":"GB",
    "sg:address":"19 Westminster Rd",
    "sg:city":"Exeter",
    "sg:classifiers":[
        {
            "category":"Building & Trades",
            "subcategory":"Construction",
            "type":"Services"
        }
    ],
    "sg:phone":"+44 1392 426195",
    "sg:postcode":"EX4 2LL",
    "sg:province":"Devon",
    "sg:tags":[
        "concrete"
    ],
    "wof:name":"MAINTENANCE PLUS",
    "wof:placetype":"venue"
},
  "geometry": {"coordinates":[-3.5581469536,50.7241401672],"type":"Point"}
}