{
  "type": "Feature",
  "properties": {
    "addr:full":"Temple House, 8a Temple Square Aylesbury Buckinghamshire HP20 2QD",
    "addr:housenumber":"8a",
    "addr:postcode":"hp20 2qd",
    "addr:street":"Temple Square",
    "iso:country":"GB",
    "sg:address":"Temple House, 8a Temple Square",
    "sg:city":"Aylesbury",
    "sg:classifiers":[
        {
            "category":"Professional",
            "subcategory":"Computer Services",
            "type":"Services"
        }
    ],
    "sg:phone":"+44 1296 437601",
    "sg:postcode":"HP20 2QD",
    "sg:province":"Buckinghamshire",
    "sg:tags":[
        "consultant"
    ],
    "wof:name":"Harlequin Technology",
    "wof:placetype":"venue"
},
  "geometry": {"coordinates":[-0.813938,51.816223],"type":"Point"}
}