{
  "type": "Feature",
  "properties": {
    "iso:country":"GB",
    "sg:address":"Bowes Street",
    "sg:city":"Blyth",
    "sg:classifiers":[
        {
            "category":"Food & Beverages",
            "subcategory":"Supermarket",
            "type":"Retail Goods"
        }
    ],
    "sg:phone":"+44 1670 366071",
    "sg:postcode":"NE24 1EB",
    "sg:province":"Northumberland",
    "wof:name":"North Eastern & Cumbrian Co-Op Fod Stores",
    "wof:placetype":"venue"
},
  "geometry": {"coordinates":[-1.512849,55.127323],"type":"Point"}
}