{
  "type": "Feature",
  "properties": {
    "addr:full":"170 Church Road London Greater London NW10 9NH",
    "addr:housenumber":"170",
    "addr:postcode":"nw10 9nh",
    "addr:street":"Church Road",
    "iso:country":"GB",
    "sg:address":"170 Church Road",
    "sg:city":"London",
    "sg:classifiers":[
        {
            "category":"Food & Beverages",
            "subcategory":"Bakery",
            "type":"Retail Goods"
        },
        {
            "category":"Shopping",
            "subcategory":"Discount & Variety Stores",
            "type":"Retail Goods"
        },
        {
            "category":"Home & Garden",
            "subcategory":"Kitchen Supply",
            "type":"Retail Goods"
        }
    ],
    "sg:phone":"+44 20 8459 1646",
    "sg:postcode":"NW10 9NH",
    "sg:province":"Greater London",
    "sg:tags":[
        "confectioner",
        "baker",
        "equipment"
    ],
    "wof:name":"D Dontas",
    "wof:placetype":"venue"
},
  "geometry": {"coordinates":[-0.249668,51.547436],"type":"Point"}
}