{
  "type": "Feature",
  "properties": {
    "iso:country":"GB",
    "sg:address":"47 Hencroft Street South",
    "sg:city":"Slough",
    "sg:classifiers":[
        {
            "category":"Building & Trades",
            "subcategory":"Construction",
            "type":"Services"
        }
    ],
    "sg:phone":"+44 1753 574828",
    "sg:postcode":"SL1 1RF",
    "sg:province":"Berkshire",
    "sg:tags":[
        "builder"
    ],
    "wof:name":"Fantasy Builders Ltd.",
    "wof:placetype":"venue"
},
  "geometry": {"coordinates":[-0.5906310081,51.5058708191],"type":"Point"}
}