{
  "type": "Feature",
  "properties": {
    "addr:full":"2 Beach Station Road Felixstowe Suffolk IP11 2DR",
    "addr:housenumber":"2",
    "addr:postcode":"ip11 2dr",
    "addr:street":"Beach Station Road",
    "iso:country":"GB",
    "sg:address":"2 Beach Station Road",
    "sg:city":"Felixstowe",
    "sg:classifiers":[
        {
            "category":"Retail",
            "subcategory":"Driving School",
            "type":"Services"
        }
    ],
    "sg:phone":"+44 1394 273050",
    "sg:postcode":"IP11 2DR",
    "sg:province":"Suffolk",
    "wof:name":"Test Busters",
    "wof:placetype":"venue"
},
  "geometry": {"coordinates":[1.337773,51.951847],"type":"Point"}
}