{
  "type": "Feature",
  "properties": {
    "iso:country":"GB",
    "sg:address":"Rose Farm, Rainford Road, Bickerstaffe",
    "sg:city":"Ormskirk",
    "sg:classifiers":[
        {
            "category":"Farming",
            "subcategory":"Livestock Farm",
            "type":"Manufacturing & Wholesale Goods"
        }
    ],
    "sg:phone":"+44 1695 722230",
    "sg:postcode":"L39 0HF",
    "sg:province":"Lancashire",
    "sg:tags":[
        "others"
    ],
    "wof:name":"Alfred Heyes & Son",
    "wof:placetype":"venue"
},
  "geometry": {"coordinates":[-2.838433,53.531841],"type":"Point"}
}