{
  "type": "Feature",
  "properties": {
    "addr:full":"Rose Ash, Bishops Nympton South Molton Devon EX36 4PS",
    "addr:housenumber":"molton",
    "addr:postcode":"ex36 4ps",
    "addr:street":"Rose Ash;South",
    "iso:country":"GB",
    "sg:address":"Rose Ash, Bishops Nympton",
    "sg:city":"South Molton",
    "sg:classifiers":[
        {
            "category":"Farming",
            "subcategory":"Livestock Farm",
            "type":"Manufacturing & Wholesale Goods"
        }
    ],
    "sg:phone":"+44 1769 550429",
    "sg:postcode":"EX36 4PS",
    "sg:province":"Devon",
    "sg:tags":[
        "others"
    ],
    "wof:name":"Gill Baker",
    "wof:placetype":"venue"
},
  "geometry": {"coordinates":[-3.7709488869,51.0009918213],"type":"Point"}
}