{
  "type": "Feature",
  "properties": {
    "iso:country":"GB",
    "sg:address":"Unit 42 2 Manor Gardens",
    "sg:city":"Holloway",
    "sg:classifiers":[
        {
            "category":"Food & Beverages",
            "subcategory":"Candy",
            "type":"Retail Goods"
        },
        {
            "category":"Personal",
            "type":"Services"
        }
    ],
    "sg:phone":"+44 20 7281 6161",
    "sg:postcode":"N7 6JY",
    "sg:province":"Greater London",
    "sg:tags":[
        "confectionery",
        "gift"
    ],
    "wof:name":"Chocolate Paradise Ltd",
    "wof:placetype":"venue"
},
  "geometry": {"coordinates":[-0.122518,51.560459],"type":"Point"}
}