{
  "type": "Feature",
  "properties": {
    "addr:full":"21 Watson Rd Worksop Nottinghamshire S80 2BA",
    "addr:housenumber":"21",
    "addr:postcode":"s80 2ba",
    "addr:street":"Watson Rd",
    "iso:country":"GB",
    "sg:address":"21 Watson Rd",
    "sg:city":"Worksop",
    "sg:classifiers":[
        {
            "category":"Fast Food",
            "type":"Food & Drink"
        }
    ],
    "sg:postcode":"S80 2BA",
    "sg:province":"Nottinghamshire",
    "sg:tags":[
        "away",
        "take"
    ],
    "wof:name":"Donatos Italian Restaurant",
    "wof:placetype":"venue"
},
  "geometry": {"coordinates":[-1.12218,53.30608],"type":"Point"}
}