{
  "type": "Feature",
  "properties": {
    "iso:country":"GB",
    "sg:address":"67 Osmond Gardens",
    "sg:city":"Wallington",
    "sg:classifiers":[
        {
            "category":"Professional",
            "subcategory":"Business Services",
            "type":"Services"
        }
    ],
    "sg:phone":"+44 20 8669 4507",
    "sg:postcode":"SM6 8SX",
    "sg:province":"Surrey",
    "sg:tags":[
        "shop",
        "cleaning"
    ],
    "wof:name":"Avco Cleaning Services",
    "wof:placetype":"venue"
},
  "geometry": {"coordinates":[-0.1418049932,51.3635749817],"type":"Point"}
}