{
  "type": "Feature",
  "properties": {
    "addr:full":"30 Lincoln Clo Bicester Oxfordshire OX6 7YF",
    "addr:housenumber":"30",
    "addr:postcode":"ox6 7yf",
    "addr:street":"Lincoln Clo",
    "iso:country":"GB",
    "sg:address":"30 Lincoln Clo",
    "sg:city":"Bicester",
    "sg:classifiers":[
        {
            "category":"Retail",
            "subcategory":"Driving School",
            "type":"Services"
        }
    ],
    "sg:phone":"+44 1869 248737",
    "sg:postcode":"OX6 7YF",
    "sg:province":"Oxfordshire",
    "wof:name":"Starlaine School Of Motoring",
    "wof:placetype":"venue"
},
  "geometry": {"coordinates":[-1.1400610209,51.9088096619],"type":"Point"}
}