{
  "type": "Feature",
  "properties": {
    "addr:full":"76 Tower Road Newquay Cornwall TR7 1LY",
    "addr:housenumber":"76",
    "addr:postcode":"tr7 1ly",
    "addr:street":"Tower Road",
    "iso:country":"GB",
    "sg:address":"76 Tower Road",
    "sg:city":"Newquay",
    "sg:classifiers":[
        {
            "category":"Travel",
            "subcategory":"Hotels & Motels",
            "type":"Entertainment"
        }
    ],
    "sg:phone":"+44 1637 875640",
    "sg:postcode":"TR7 1LY",
    "sg:province":"Cornwall",
    "sg:tags":[
        "house",
        "guest"
    ],
    "wof:name":"Carrington Guest House",
    "wof:placetype":"venue"
},
  "geometry": {"coordinates":[-5.091105,50.414616],"type":"Point"}
}