{
  "type": "Feature",
  "properties": {
    "addr:full":"G440 Royal Ordanance Group Sewardstone R Waltham Abbey Essex EN9 1AY",
    "addr:housenumber":"g440",
    "addr:postcode":"en9 1ay",
    "addr:street":"Royal;R Waltham Abbey",
    "iso:country":"GB",
    "sg:address":"G440 Royal Ordanance Group Sewardstone R",
    "sg:city":"Waltham Abbey",
    "sg:classifiers":[
        {
            "category":"Building & Trades",
            "subcategory":"Construction",
            "type":"Services"
        }
    ],
    "sg:postcode":"EN9 1AY",
    "sg:province":"Essex",
    "sg:tags":[
        "builder"
    ],
    "wof:name":"Harris Fabrication",
    "wof:placetype":"venue"
},
  "geometry": {"coordinates":[0.0014900001,51.6864204407],"type":"Point"}
}