{
  "type": "Feature",
  "properties": {
    "addr:full":"Hendre Fawr Farm, Llandissilio Clynderwen Carmarthenshire SA66 7JJ",
    "addr:postcode":"sa66 7jj",
    "iso:country":"GB",
    "sg:address":"Hendre Fawr Farm, Llandissilio",
    "sg:city":"Clynderwen",
    "sg:classifiers":[
        {
            "category":"Farming",
            "subcategory":"Livestock Farm",
            "type":"Manufacturing & Wholesale Goods"
        }
    ],
    "sg:postcode":"SA66 7JJ",
    "sg:province":"Carmarthenshire",
    "sg:tags":[
        "others"
    ],
    "wof:name":"A D John",
    "wof:placetype":"venue"
},
  "geometry": {"coordinates":[-4.72922,51.839973],"type":"Point"}
}