{
  "type": "Feature",
  "properties": {
    "iso:country":"GB",
    "sg:address":"16 The Office Village, Exchange Quay",
    "sg:city":"Salford",
    "sg:classifiers":[
        {
            "category":"Education",
            "subcategory":"Special Training",
            "type":"Public Place"
        },
        {
            "category":"Professional",
            "subcategory":"Computer Services",
            "type":"Services"
        }
    ],
    "sg:postcode":"M5 3EQ",
    "sg:province":"Greater Manchester",
    "sg:tags":[
        "product",
        "software",
        "system",
        "centre"
    ],
    "wof:name":"Long,S,",
    "wof:placetype":"venue"
},
  "geometry": {"coordinates":[-2.2806398869,53.4655990601],"type":"Point"}
}