{
  "type": "Feature",
  "properties": {
    "iso:country":"GB",
    "sg:address":"56 North Street",
    "sg:city":"Cannock",
    "sg:classifiers":[
        {
            "category":"Home & Garden",
            "subcategory":"Household Appliances",
            "type":"Retail Goods"
        }
    ],
    "sg:phone":"+44 1543 467707",
    "sg:postcode":"WS11 3BA",
    "sg:province":"Staffordshire",
    "sg:tags":[
        "electrical",
        "domestic"
    ],
    "wof:name":"Andrews Electrical",
    "wof:placetype":"venue"
},
  "geometry": {"coordinates":[-2.02893,52.676067],"type":"Point"}
}