{
  "type": "Feature",
  "properties": {
    "iso:country":"GB",
    "sg:address":"61 Rainham Road",
    "sg:city":"Gillingham",
    "sg:classifiers":[
        {
            "category":"Food & Beverages",
            "subcategory":"Groceries & Convenience Stores",
            "type":"Retail Goods"
        }
    ],
    "sg:phone":"+44 1634 851645",
    "sg:postcode":"ME7 5NG",
    "sg:province":"Kent",
    "wof:name":"Mace Convenience Express",
    "wof:placetype":"venue"
},
  "geometry": {"coordinates":[0.5492600203,51.3740882874],"type":"Point"}
}