{
  "type": "Feature",
  "properties": {
    "iso:country":"GB",
    "sg:address":"48 High Street, West End",
    "sg:city":"Southampton",
    "sg:classifiers":[
        {
            "category":"Personal",
            "subcategory":"Barber",
            "type":"Services"
        }
    ],
    "sg:phone":"+44 23 8047 3578",
    "sg:postcode":"SO30 3DR",
    "sg:province":"Hampshire",
    "sg:tags":[
        "men's",
        "hairdresser"
    ],
    "wof:name":"E & Sons Beale",
    "wof:placetype":"venue"
},
  "geometry": {"coordinates":[-1.33631,50.927483],"type":"Point"}
}