{
  "type": "Feature",
  "properties": {
    "iso:country":"GB",
    "sg:address":"The Stonebows, Hackthorn Road, Welton",
    "sg:city":"Lincoln",
    "sg:classifiers":[
        {
            "category":"Farming",
            "subcategory":"Livestock Farm",
            "type":"Manufacturing & Wholesale Goods"
        }
    ],
    "sg:phone":"+44 1673 860304",
    "sg:postcode":"LN2 3PA",
    "sg:province":"Lincolnshire",
    "sg:tags":[
        "others"
    ],
    "wof:name":"C Ottewell & Son (Haulage) Ltd.",
    "wof:placetype":"venue"
},
  "geometry": {"coordinates":[-0.507649,53.328831],"type":"Point"}
}