{
  "type": "Feature",
  "properties": {
    "iso:country":"GB",
    "sg:address":"Unit 607 Delta Business Park, Welton Road",
    "sg:city":"Swindon",
    "sg:classifiers":[
        {
            "category":"Building & Trades",
            "subcategory":"Cleaning & Sanitation",
            "type":"Services"
        }
    ],
    "sg:phone":"+44 1793 488339",
    "sg:postcode":"SN5 7XF",
    "sg:province":"Wiltshire",
    "sg:tags":[
        "facility"
    ],
    "wof:name":"Miquest Ltd.",
    "wof:placetype":"venue"
},
  "geometry": {"coordinates":[-1.8163160086,51.5575027466],"type":"Point"}
}