{
  "type": "Feature",
  "properties": {
    "iso:country":"GB",
    "sg:address":"Burstow Park, Antlands Lane",
    "sg:city":"Horley",
    "sg:classifiers":[
        {
            "category":"Professional",
            "subcategory":"Computer Services",
            "type":"Services"
        }
    ],
    "sg:phone":"+44 1293 772201",
    "sg:postcode":"RH6 9TF",
    "sg:province":"Surrey",
    "sg:tags":[
        "development",
        "consultant",
        "software"
    ],
    "sg:website":"http://www.laserbyte.com",
    "wof:name":"Laser Byte Ltd",
    "wof:placetype":"venue"
},
  "geometry": {"coordinates":[-0.169289,51.175365],"type":"Point"}
}