{
  "type": "Feature",
  "properties": {
    "addr:full":"52 Neville Road Scunthorpe Lincolnshire DN16 1TN",
    "addr:housenumber":"52",
    "addr:postcode":"dn16 1tn",
    "addr:street":"Neville Road",
    "iso:country":"GB",
    "sg:address":"52 Neville Road",
    "sg:city":"Scunthorpe",
    "sg:classifiers":[
        {
            "category":"Professional",
            "subcategory":"Engineering",
            "type":"Services"
        }
    ],
    "sg:phone":"+44 1724 855548",
    "sg:postcode":"DN16 1TN",
    "sg:province":"Lincolnshire",
    "sg:tags":[
        "civil",
        "engineer"
    ],
    "wof:name":"M Togher",
    "wof:placetype":"venue"
},
  "geometry": {"coordinates":[-0.637236,53.585403],"type":"Point"}
}