{
  "type": "Feature",
  "properties": {
    "addr:full":"379 London Road St Leonards-on-sea East Sussex TN37 6PA",
    "addr:housenumber":"379",
    "addr:postcode":"leonards-on-sea;tn37 6pa",
    "addr:street":"London Road St",
    "iso:country":"GB",
    "sg:address":"379 London Road",
    "sg:city":"St Leonards-on-sea",
    "sg:classifiers":[
        {
            "category":"Real Estate",
            "subcategory":"Real Estate Agent",
            "type":"Services"
        }
    ],
    "sg:postcode":"TN37 6PA",
    "sg:province":"East Sussex",
    "wof:name":"Shearer's Estate Letting Agents",
    "wof:placetype":"venue"
},
  "geometry": {"coordinates":[0.5562149882,50.8667221069],"type":"Point"}
}