{
  "type": "Feature",
  "properties": {
    "addr:full":"Axholme Av Edgware Greater London HA8 5BE",
    "addr:postcode":"ha8 5be",
    "addr:street":"Av Edgware",
    "iso:country":"GB",
    "sg:address":"Axholme Av",
    "sg:city":"Edgware",
    "sg:classifiers":[
        {
            "category":"Professional",
            "subcategory":"Computer Services",
            "type":"Services"
        }
    ],
    "sg:phone":"+44 20 8381 2848",
    "sg:postcode":"HA8 5BE",
    "sg:province":"Greater London",
    "sg:tags":[
        "system",
        "software"
    ],
    "wof:name":"Somtek Systems",
    "wof:placetype":"venue"
},
  "geometry": {"coordinates":[-0.275791,51.603371],"type":"Point"}
}