{
  "type": "Feature",
  "properties": {
    "iso:country":"GB",
    "sg:address":"219 Greenway Rd",
    "sg:city":"Taunton",
    "sg:classifiers":[
        {
            "category":"Health Services",
            "subcategory":"Clinic",
            "type":"Services"
        }
    ],
    "sg:phone":"+44 1823 333041",
    "sg:postcode":"TA2 6LN",
    "sg:province":"Somerset",
    "sg:tags":[
        "injury",
        "sport"
    ],
    "wof:name":"E Mortimer White M.C.S.P. O.N.C S.R.P.",
    "wof:placetype":"venue"
},
  "geometry": {"coordinates":[-3.1202530861,51.0283927917],"type":"Point"}
}