{
  "type": "Feature",
  "properties": {
    "addr:full":"High Street, Tutbury Burton-on-trent Derbyshire DE13 9LS",
    "addr:postcode":"de13 9ls",
    "addr:street":"High Street",
    "iso:country":"GB",
    "sg:address":"High Street, Tutbury",
    "sg:city":"Burton-on-trent",
    "sg:classifiers":[
        {
            "category":"Travel",
            "subcategory":"Hotels & Motels",
            "type":"Entertainment"
        }
    ],
    "sg:phone":"+44 1283 813030",
    "sg:postcode":"DE13 9LS",
    "sg:province":"Derbyshire",
    "wof:name":"Ye Olde Dog & Partridge Inn Ltd.",
    "wof:placetype":"venue"
},
  "geometry": {"coordinates":[-1.6858160496,52.8572158813],"type":"Point"}
}