{
  "type": "Feature",
  "properties": {
    "iso:country":"GB",
    "sg:address":"Waves Farm, Saxilby Road",
    "sg:city":"Lincoln",
    "sg:classifiers":[
        {
            "category":"Farming",
            "subcategory":"Livestock Farm",
            "type":"Manufacturing & Wholesale Goods"
        }
    ],
    "sg:phone":"+44 1522 524435",
    "sg:postcode":"LN1 2BG",
    "sg:province":"Lincolnshire",
    "sg:tags":[
        "others"
    ],
    "wof:name":"J Wright & Partners",
    "wof:placetype":"venue"
},
  "geometry": {"coordinates":[-0.655976,53.271435],"type":"Point"}
}