{
  "type": "Feature",
  "properties": {
    "iso:country":"GB",
    "sg:address":"Liverpool Rd",
    "sg:city":"Skelmersdale",
    "sg:classifiers":[
        {
            "category":"Place Of Worship",
            "type":"Public Place"
        }
    ],
    "sg:phone":"+44 1695 724476",
    "sg:postcode":"WN8 8BX",
    "sg:province":"Lancashire",
    "wof:name":"St Richard R C Church",
    "wof:placetype":"venue"
},
  "geometry": {"coordinates":[-2.805084,53.54723],"type":"Point"}
}