{
  "type": "Feature",
  "properties": {
    "iso:country":"GB",
    "sg:address":"60 Lemon Street",
    "sg:city":"Truro",
    "sg:classifiers":[
        {
            "category":"Shopping",
            "subcategory":"Used Merchandise",
            "type":"Retail Goods"
        }
    ],
    "sg:phone":"+44 1872 261821",
    "sg:postcode":"TR1 2PE",
    "sg:province":"Cornwall",
    "sg:tags":[
        "shop",
        "second-hand"
    ],
    "wof:name":"Sue Wagstaff",
    "wof:placetype":"venue"
},
  "geometry": {"coordinates":[-5.052968,50.261135],"type":"Point"}
}