{
  "type": "Feature",
  "properties": {
    "iso:country":"GB",
    "sg:address":"39 Jacklin Dr",
    "sg:city":"Coventry",
    "sg:classifiers":[
        {
            "category":"Building & Trades",
            "subcategory":"Construction",
            "type":"Services"
        }
    ],
    "sg:postcode":"CV3 6QG",
    "sg:province":"Warwickshire",
    "sg:tags":[
        "glazier"
    ],
    "wof:name":"Tolley,D,",
    "wof:placetype":"venue"
},
  "geometry": {"coordinates":[-1.51083,52.377625],"type":"Point"}
}