{
  "type": "Feature",
  "properties": {
    "addr:full":"5 Fellgate Court Newcastle Staffordshire ST5 2UA",
    "addr:housenumber":"5",
    "addr:postcode":"st5 2ua",
    "addr:street":"Fellgate Court",
    "iso:country":"GB",
    "sg:address":"5 Fellgate Court",
    "sg:city":"Newcastle",
    "sg:classifiers":[
        {
            "category":"Professional",
            "subcategory":"Management & Consulting",
            "type":"Services"
        }
    ],
    "sg:phone":"+44 1782 631151",
    "sg:postcode":"ST5 2UA",
    "sg:province":"Staffordshire",
    "sg:tags":[
        "consultant",
        "business"
    ],
    "wof:name":"O.C.M Ltd",
    "wof:placetype":"venue"
},
  "geometry": {"coordinates":[-2.230511,53.012348],"type":"Point"}
}