{
  "type": "Feature",
  "properties": {
    "iso:country":"GB",
    "sg:address":"24 Marshalsea Road",
    "sg:city":"London",
    "sg:classifiers":[
        {
            "category":"Professional",
            "subcategory":"Art Services",
            "type":"Services"
        }
    ],
    "sg:postcode":"SE1 1HE",
    "sg:province":"Greater London",
    "sg:tags":[
        "graphic",
        "designer"
    ],
    "wof:name":"Karen Wilks",
    "wof:placetype":"venue"
},
  "geometry": {"coordinates":[-0.095629,51.502396],"type":"Point"}
}