{
  "type": "Feature",
  "properties": {
    "addr:full":"Commercial Yard Knaresborough North Yorkshire HG5 0HG",
    "addr:postcode":"hg5 0hg",
    "iso:country":"GB",
    "sg:address":"Commercial Yard",
    "sg:city":"Knaresborough",
    "sg:classifiers":[
        {
            "category":"Professional",
            "type":"Services"
        }
    ],
    "sg:phone":"+44 1423 862273",
    "sg:postcode":"HG5 0HG",
    "sg:province":"North Yorkshire",
    "sg:tags":[
        "auctioneer"
    ],
    "wof:name":"Knaresborough Auction Mart",
    "wof:placetype":"venue"
},
  "geometry": {"coordinates":[-1.467333,54.009369],"type":"Point"}
}