{
  "type": "Feature",
  "properties": {
    "addr:full":"5 Dixon Street Hamilton South Lanarkshire ML3 6PZ",
    "addr:housenumber":"5",
    "addr:postcode":"ml3 6pz",
    "addr:street":"Dixon Street",
    "iso:country":"GB",
    "sg:address":"5 Dixon Street",
    "sg:city":"Hamilton",
    "sg:classifiers":[
        {
            "category":"Home & Garden",
            "subcategory":"Hardware",
            "type":"Retail Goods"
        }
    ],
    "sg:phone":"+44 1698 422521",
    "sg:postcode":"ML3 6PZ",
    "sg:province":"South Lanarkshire",
    "sg:tags":[
        "retailer",
        "diy"
    ],
    "wof:name":"Kelvin Timber (East) Ltd.",
    "wof:placetype":"venue"
},
  "geometry": {"coordinates":[-4.047454834,55.7717208862],"type":"Point"}
}