{
  "type": "Feature",
  "properties": {
    "addr:full":"Thornton Manor, Warwick Road, Ettington Stratford-upon-avon Warwickshire CV37 7PN",
    "addr:postcode":"cv37 7pn",
    "addr:street":"Warwick Road",
    "iso:country":"GB",
    "sg:address":"Thornton Manor, Warwick Road, Ettington",
    "sg:city":"Stratford-upon-avon",
    "sg:classifiers":[
        {
            "category":"Farming",
            "subcategory":"Farm",
            "type":"Manufacturing & Wholesale Goods"
        }
    ],
    "sg:phone":"+44 1789 740210",
    "sg:postcode":"CV37 7PN",
    "sg:province":"Warwickshire",
    "sg:tags":[
        "mixed",
        "crop"
    ],
    "wof:name":"Kenneth & Richard Hutsby",
    "wof:placetype":"venue"
},
  "geometry": {"coordinates":[-1.608049,52.137959],"type":"Point"}
}