{
  "type": "Feature",
  "properties": {
    "addr:full":"Sarnia Cutlers Green, Thaxted Dunmow Essex CM6 2PZ",
    "addr:housenumber":"thaxted",
    "addr:postcode":"cm6 2pz",
    "addr:street":"Green",
    "iso:country":"GB",
    "sg:address":"Sarnia Cutlers Green, Thaxted",
    "sg:city":"Dunmow",
    "sg:classifiers":[
        {
            "category":"Professional",
            "subcategory":"Advertising",
            "type":"Services"
        }
    ],
    "sg:postcode":"CM6 2PZ",
    "sg:province":"Essex",
    "sg:tags":[
        "agency"
    ],
    "wof:name":"Action Shots Ltd",
    "wof:placetype":"venue"
},
  "geometry": {"coordinates":[0.344765,51.953163],"type":"Point"}
}