{
  "type": "Feature",
  "properties": {
    "addr:full":"8 Bronwlow Hill Liverpool Merseyside L3 5RE",
    "addr:housenumber":"8",
    "addr:postcode":"l3 5re",
    "addr:street":"Bronwlow Hill",
    "iso:country":"GB",
    "sg:address":"8 Bronwlow Hill",
    "sg:city":"Liverpool",
    "sg:classifiers":[
        {
            "category":"Retail",
            "subcategory":"Auto Rental",
            "type":"Services"
        }
    ],
    "sg:phone":"+44 151 708 9150",
    "sg:postcode":"L3 5RE",
    "sg:province":"Merseyside",
    "sg:tags":[
        "car"
    ],
    "wof:name":"Europcar Uk",
    "wof:placetype":"venue"
},
  "geometry": {"coordinates":[-2.9749519825,53.4051856995],"type":"Point"}
}