{
  "type": "Feature",
  "properties": {
    "iso:country":"GB",
    "sg:address":"36 Ise View Road, Desborough",
    "sg:city":"Kettering",
    "sg:classifiers":[
        {
            "category":"Professional",
            "subcategory":"Engineering",
            "type":"Services"
        }
    ],
    "sg:phone":"+44 1536 761919",
    "sg:postcode":"NN14 2PX",
    "sg:province":"Northamptonshire",
    "sg:tags":[
        "contractor",
        "electrical",
        "engineer"
    ],
    "wof:name":"M G Electrical Services",
    "wof:placetype":"venue"
},
  "geometry": {"coordinates":[-0.811501,52.442238],"type":"Point"}
}