{
  "type": "Feature",
  "properties": {
    "addr:full":"46 Main Street, Cambuslang Glasgow South Lanarkshire G72 7EP",
    "addr:housenumber":"46",
    "addr:postcode":"g72 7ep",
    "addr:street":"Main Street",
    "iso:country":"GB",
    "sg:address":"46 Main Street, Cambuslang",
    "sg:city":"Glasgow",
    "sg:classifiers":[
        {
            "category":"Health Services",
            "subcategory":"Dentist",
            "type":"Services"
        }
    ],
    "sg:phone":"+44 141 641 3498",
    "sg:postcode":"G72 7EP",
    "sg:province":"South Lanarkshire",
    "wof:name":"MACARTHUR & OTOOLE",
    "wof:placetype":"venue"
},
  "geometry": {"coordinates":[-4.165746,55.818642],"type":"Point"}
}