{
  "type": "Feature",
  "properties": {
    "addr:full":"Middle Hill, Hook Norton Banbury Oxfordshire OX15 5PL",
    "addr:postcode":"ox15 5pl",
    "addr:street":"Middle Hill",
    "iso:country":"GB",
    "sg:address":"Middle Hill, Hook Norton",
    "sg:city":"Banbury",
    "sg:classifiers":[
        {
            "category":"Professional",
            "subcategory":"Employment Agencies",
            "type":"Services"
        }
    ],
    "sg:phone":"+44 1608 737888",
    "sg:postcode":"OX15 5PL",
    "sg:province":"Oxfordshire",
    "sg:tags":[
        "agricultural",
        "advice"
    ],
    "wof:name":"Ray Gasson & Associates Ltd.",
    "wof:placetype":"venue"
},
  "geometry": {"coordinates":[-1.4817370176,51.9974365234],"type":"Point"}
}