{
  "type": "Feature",
  "properties": {
    "iso:country":"GB",
    "sg:address":"91 Tudor Way",
    "sg:city":"Rickmansworth",
    "sg:classifiers":[
        {
            "category":"Professional",
            "subcategory":"Accounting & Tax Preparation",
            "type":"Services"
        }
    ],
    "sg:postcode":"WD3 8HY",
    "sg:province":"Hertfordshire",
    "sg:tags":[
        "accountant"
    ],
    "wof:name":"Devlyn Business Services",
    "wof:placetype":"venue"
},
  "geometry": {"coordinates":[-0.492935,51.639446],"type":"Point"}
}