{
  "type": "Feature",
  "properties": {
    "iso:country":"GB",
    "sg:address":"Little Holwell, Collipriest",
    "sg:city":"Tiverton",
    "sg:classifiers":[
        {
            "category":"Travel",
            "subcategory":"Hotels & Motels",
            "type":"Entertainment"
        },
        {
            "category":"Manufacturing",
            "subcategory":"Signs",
            "type":"Manufacturing & Wholesale Goods"
        }
    ],
    "sg:postcode":"EX16 4PT",
    "sg:province":"Devon",
    "sg:tags":[
        "house",
        "guest",
        "nameplate"
    ],
    "wof:name":"Devonshire Crafts",
    "wof:placetype":"venue"
},
  "geometry": {"coordinates":[-3.489229,50.889938],"type":"Point"}
}