{
  "type": "Feature",
  "properties": {
    "addr:full":"20 Porlock Gardens, Nailsea Bristol Somerset BS48 2QX",
    "addr:housenumber":"20",
    "addr:postcode":"bs48 2qx",
    "addr:street":"Porlock Gardens",
    "iso:country":"GB",
    "sg:address":"20 Porlock Gardens, Nailsea",
    "sg:city":"Bristol",
    "sg:classifiers":[
        {
            "category":"Freight",
            "type":"Transportation"
        }
    ],
    "sg:phone":"+44 1275 790799",
    "sg:postcode":"BS48 2QX",
    "sg:province":"Somerset",
    "sg:tags":[
        "haulage",
        "road"
    ],
    "wof:name":"Eager Delivery Service",
    "wof:placetype":"venue"
},
  "geometry": {"coordinates":[-2.759085,51.428711],"type":"Point"}
}