{
  "type": "Feature",
  "properties": {
    "addr:full":"Crewe Avenue Macclesfield Cheshire SK10 2RZ",
    "addr:postcode":"sk10 2rz",
    "addr:street":"Crewe Avenue",
    "iso:country":"GB",
    "sg:address":"Crewe Avenue",
    "sg:city":"Macclesfield",
    "sg:classifiers":[
        {
            "category":"Social Services",
            "subcategory":"Adult Care",
            "type":"Services"
        },
        {
            "category":"Social Services",
            "subcategory":"Retirement Home",
            "type":"Services"
        }
    ],
    "sg:phone":"+44 1625 511495",
    "sg:postcode":"SK10 2RZ",
    "sg:province":"Cheshire",
    "sg:tags":[
        "housing",
        "sheltered",
        "accommodation"
    ],
    "wof:name":"Harry Lawson Court Sheltered Housing",
    "wof:placetype":"venue"
},
  "geometry": {"coordinates":[-2.118865,53.264381],"type":"Point"}
}