{
  "type": "Feature",
  "properties": {
    "addr:full":"1 School End, Aynho Banbury Banbury Northamptonshire OX17 3BS",
    "addr:housenumber":"1",
    "addr:postcode":"ox17 3bs",
    "addr:street":"School End",
    "iso:country":"GB",
    "sg:address":"1 School End, Aynho Banbury",
    "sg:city":"Banbury",
    "sg:classifiers":[
        {
            "category":"Banks & Credit Unions",
            "subcategory":"Investment Brokerage",
            "type":"Services"
        }
    ],
    "sg:phone":"+44 1869 810061",
    "sg:postcode":"OX17 3BS",
    "sg:province":"Northamptonshire",
    "wof:name":"W T M Income Investment Specialists",
    "wof:placetype":"venue"
},
  "geometry": {"coordinates":[-1.2521569729,51.9955444336],"type":"Point"}
}