{
  "type": "Feature",
  "properties": {
    "iso:country":"GB",
    "sg:address":"Country Gardens, London Rd",
    "sg:city":"Sittingbourne",
    "sg:classifiers":[
        {
            "category":"Home & Garden",
            "subcategory":"Hardware",
            "type":"Retail Goods"
        }
    ],
    "sg:phone":"+44 1795 522995",
    "sg:postcode":"ME9 9JY",
    "sg:province":"Kent",
    "sg:tags":[
        "lawnmowers",
        "machinery"
    ],
    "wof:name":"Garden And Orchard Mowers",
    "wof:placetype":"venue"
},
  "geometry": {"coordinates":[0.82268,51.321171],"type":"Point"}
}