{
  "type": "Feature",
  "properties": {
    "iso:country":"GB",
    "sg:address":"Unit 6",
    "sg:city":"Northampton",
    "sg:classifiers":[
        {
            "category":"Home & Garden",
            "subcategory":"Building Materials",
            "type":"Retail Goods"
        },
        {
            "category":"Building & Trades",
            "subcategory":"Construction",
            "type":"Services"
        }
    ],
    "sg:phone":"+44 870 366 6525",
    "sg:postcode":"NN2 6NA",
    "sg:province":"Northamptonshire",
    "sg:tags":[
        "gate",
        "window",
        "door",
        "barrier"
    ],
    "wof:name":"Axis (Northampton) Ltd.",
    "wof:placetype":"venue"
},
  "geometry": {"coordinates":[-0.8958489895,52.2574043274],"type":"Point"}
}