{
  "type": "Feature",
  "properties": {
    "iso:country":"GB",
    "sg:address":"20 Station Road",
    "sg:city":"Batley",
    "sg:classifiers":[
        {
            "category":"Professional",
            "type":"Services"
        }
    ],
    "sg:postcode":"WF17 5SU",
    "sg:province":"West Yorkshire",
    "sg:tags":[
        "auctioneer"
    ],
    "wof:name":"Dalewood & Co. Auctioneers & Valuers",
    "wof:placetype":"venue"
},
  "geometry": {"coordinates":[-1.62558496,53.7105178833],"type":"Point"}
}