{
  "type": "Feature",
  "properties": {
    "iso:country":"GB",
    "sg:address":"194 Addiscombe Road",
    "sg:city":"Croydon",
    "sg:classifiers":[
        {
            "category":"Sports & Exercise",
            "subcategory":"Golf",
            "type":"Entertainment"
        }
    ],
    "sg:phone":"+44 20 8654 8767",
    "sg:postcode":"CR0 7LB",
    "sg:province":"Surrey",
    "sg:tags":[
        "equipment"
    ],
    "wof:name":"Mick Taylor",
    "wof:placetype":"venue"
},
  "geometry": {"coordinates":[-0.063278,51.375648],"type":"Point"}
}