{
  "type": "Feature",
  "properties": {
    "iso:country":"GB",
    "sg:address":"183 Queens Road",
    "sg:city":"Manchester",
    "sg:classifiers":[
        {
            "category":"Fast Food",
            "type":"Food & Drink"
        }
    ],
    "sg:postcode":"M8 0RB",
    "sg:province":"Greater Manchester",
    "sg:tags":[
        "away",
        "take"
    ],
    "wof:name":"Golden Phoenix",
    "wof:placetype":"venue"
},
  "geometry": {"coordinates":[-2.2281479836,53.5019035339],"type":"Point"}
}