{
  "type": "Feature",
  "properties": {
    "addr:full":"103 High St West Wickham Kent BR4 0LT",
    "addr:housenumber":"103",
    "addr:postcode":"br4 0lt",
    "addr:street":"High St",
    "iso:country":"GB",
    "sg:address":"103 High St",
    "sg:city":"West Wickham",
    "sg:classifiers":[
        {
            "category":"Organizations",
            "subcategory":"Non-profit Organization",
            "type":"Services"
        }
    ],
    "sg:phone":"+44 20 8777 0223",
    "sg:postcode":"BR4 0LT",
    "sg:province":"Kent",
    "sg:tags":[
        "organisation",
        "voluntary",
        "charity"
    ],
    "wof:name":"Spastics Society",
    "wof:placetype":"venue"
},
  "geometry": {"coordinates":[-0.0194819998,51.3767089844],"type":"Point"}
}