{
  "type": "Feature",
  "properties": {
    "addr:full":"Unit 4 Imperial Park, Empress Road, St Denys Southampton Hampshire SO14 0JW",
    "addr:housenumber":"unit 4",
    "addr:postcode":"so14 0jw",
    "addr:street":"Imperial Park Empress Road St",
    "iso:country":"GB",
    "sg:address":"Unit 4 Imperial Park, Empress Road, St Denys",
    "sg:city":"Southampton",
    "sg:classifiers":[
        {
            "category":"Manufacturing",
            "subcategory":"Wood Products",
            "type":"Manufacturing & Wholesale Goods"
        }
    ],
    "sg:phone":"+44 23 8023 3722",
    "sg:postcode":"SO14 0JW",
    "sg:province":"Hampshire",
    "sg:tags":[
        "maker",
        "cabinet"
    ],
    "wof:name":"Nicholson Interiors Ltd.",
    "wof:placetype":"venue"
},
  "geometry": {"coordinates":[-1.3937599659,50.916431427],"type":"Point"}
}