{
  "type": "Feature",
  "properties": {
    "addr:full":"Hill Top Drive Rochdale Lancashire OL11 2EH",
    "addr:postcode":"ol11 2eh",
    "addr:street":"Hill Top Drive",
    "iso:country":"GB",
    "sg:address":"Hill Top Drive",
    "sg:city":"Rochdale",
    "sg:classifiers":[
        {
            "category":"Education",
            "subcategory":"School",
            "type":"Public Place"
        },
        {
            "category":"Government",
            "subcategory":"Office",
            "type":"Public Place"
        }
    ],
    "sg:phone":"+44 1706 648019",
    "sg:postcode":"OL11 2EH",
    "sg:province":"Lancashire",
    "sg:tags":[
        "local",
        "authority"
    ],
    "wof:name":"Hill Top County Primary School",
    "wof:placetype":"venue"
},
  "geometry": {"coordinates":[-2.146743,53.595612],"type":"Point"}
}