{
  "type": "Feature",
  "properties": {
    "addr:full":"79 Main Street, Bishop Wilton York East Riding of Yorkshire YO42 1SP",
    "addr:housenumber":"79",
    "addr:postcode":"yo42 1sp",
    "addr:street":"Main Street",
    "iso:country":"GB",
    "sg:address":"79 Main Street, Bishop Wilton",
    "sg:city":"York",
    "sg:classifiers":[
        {
            "category":"Wholesale",
            "subcategory":"Chemicals & Plastics",
            "type":"Manufacturing & Wholesale Goods"
        }
    ],
    "sg:phone":"+44 1759 368276",
    "sg:postcode":"YO42 1SP",
    "sg:province":"East Riding of Yorkshire",
    "sg:tags":[
        "glass",
        "metal"
    ],
    "wof:name":"Another Fine Mesh",
    "wof:placetype":"venue"
},
  "geometry": {"coordinates":[-0.7857980132,53.9864768982],"type":"Point"}
}