{
  "type": "Feature",
  "properties": {
    "addr:full":"Firbeck Skelmersdale Lancashire WN8 6PN",
    "addr:postcode":"wn8 6pn",
    "iso:country":"GB",
    "sg:address":"Firbeck",
    "sg:city":"Skelmersdale",
    "sg:classifiers":[
        {
            "category":"Place Of Worship",
            "type":"Public Place"
        }
    ],
    "sg:phone":"+44 1695 725014",
    "sg:postcode":"WN8 6PN",
    "sg:province":"Lancashire",
    "wof:name":"Ecumenical Centre",
    "wof:placetype":"venue"
},
  "geometry": {"coordinates":[-2.7717339993,53.5522499084],"type":"Point"}
}