{
  "type": "Feature",
  "properties": {
    "addr:full":"36 Cheltenham Place Brighton East Sussex BN1 4AB",
    "addr:housenumber":"36",
    "addr:postcode":"bn1 4ab",
    "addr:street":"Cheltenham Place",
    "iso:country":"GB",
    "sg:address":"36 Cheltenham Place",
    "sg:city":"Brighton",
    "sg:classifiers":[
        {
            "category":"Shopping",
            "subcategory":"Clothing, Apparel, & Fashions",
            "type":"Retail Goods"
        }
    ],
    "sg:phone":"+44 1273 677258",
    "sg:postcode":"BN1 4AB",
    "sg:province":"East Sussex",
    "sg:tags":[
        "t-shirt"
    ],
    "wof:name":"Positive Exposure T Shirts",
    "wof:placetype":"venue"
},
  "geometry": {"coordinates":[-0.1366599947,50.8261413574],"type":"Point"}
}