{
  "type": "Feature",
  "properties": {
    "addr:full":"55 Westbury Road, Westbury-on-trym Bristol City of Bristol BS9 3AS",
    "addr:housenumber":"55",
    "addr:postcode":"bs9 3as",
    "addr:street":"Westbury Road",
    "iso:country":"GB",
    "sg:address":"55 Westbury Road, Westbury-on-trym",
    "sg:city":"Bristol",
    "sg:classifiers":[
        {
            "category":"Health Services",
            "subcategory":"Nursing And Care Facility",
            "type":"Services"
        }
    ],
    "sg:phone":"+44 117 962 2331",
    "sg:postcode":"BS9 3AS",
    "sg:province":"City of Bristol",
    "sg:tags":[
        "home"
    ],
    "wof:name":"Rosewood House",
    "wof:placetype":"venue"
},
  "geometry": {"coordinates":[-2.617405,51.492409],"type":"Point"}
}