{
  "type": "Feature",
  "properties": {
    "iso:country":"GB",
    "sg:address":"27 Ribocon Way, Progress Park, Leagrave",
    "sg:city":"Luton",
    "sg:classifiers":[
        {
            "category":"Home & Garden",
            "subcategory":"Building Materials",
            "type":"Retail Goods"
        }
    ],
    "sg:phone":"+44 1582 491171",
    "sg:postcode":"LU4 9TR",
    "sg:province":"Bedfordshire",
    "sg:tags":[
        "system",
        "staircase"
    ],
    "wof:name":"Kensington Traders Ltd.",
    "wof:placetype":"venue"
},
  "geometry": {"coordinates":[-0.477353,51.914715],"type":"Point"}
}