{
  "type": "Feature",
  "properties": {
    "addr:full":"Pennant, Melin Y Coed Llanrwst Conwy LL26 0TR",
    "addr:postcode":"ll26 0tr",
    "iso:country":"GB",
    "sg:address":"Pennant, Melin Y Coed",
    "sg:city":"Llanrwst",
    "sg:classifiers":[
        {
            "category":"Farming",
            "subcategory":"Livestock Farm",
            "type":"Manufacturing & Wholesale Goods"
        }
    ],
    "sg:phone":"+44 1492 640529",
    "sg:postcode":"LL26 0TR",
    "sg:province":"Conwy",
    "sg:tags":[
        "others"
    ],
    "wof:name":"R H & M G Williams",
    "wof:placetype":"venue"
},
  "geometry": {"coordinates":[-3.7976999283,53.1376609802],"type":"Point"}
}