{
  "type": "Feature",
  "properties": {
    "addr:full":"Midtown, Duntelchaig Inverness Highland IV2 6AW",
    "addr:postcode":"iv2 6aw",
    "iso:country":"GB",
    "sg:address":"Midtown, Duntelchaig",
    "sg:city":"Inverness",
    "sg:classifiers":[
        {
            "category":"Farming",
            "subcategory":"Livestock Farm",
            "type":"Manufacturing & Wholesale Goods"
        }
    ],
    "sg:phone":"+44 1808 521237",
    "sg:postcode":"IV2 6AW",
    "sg:province":"Highland",
    "sg:tags":[
        "others"
    ],
    "wof:name":"John W Mackintosh",
    "wof:placetype":"venue"
},
  "geometry": {"coordinates":[-4.2836499214,57.3690681458],"type":"Point"}
}