{
  "type": "Feature",
  "properties": {
    "addr:full":"Duckpool Farm, Beckington Frome Somerset BA11 6TX",
    "addr:housenumber":"beckington",
    "addr:postcode":"ba11 6tx",
    "iso:country":"GB",
    "sg:address":"Duckpool Farm, Beckington",
    "sg:city":"Frome",
    "sg:classifiers":[
        {
            "category":"Home & Garden",
            "subcategory":"Kitchen Supply",
            "type":"Retail Goods"
        }
    ],
    "sg:postcode":"BA11 6TX",
    "sg:province":"Somerset",
    "sg:tags":[
        "equipment",
        "catering"
    ],
    "wof:name":"Catering Concepts Ltd.",
    "wof:placetype":"venue"
},
  "geometry": {"coordinates":[-2.287089,51.265766],"type":"Point"}
}