{
  "type": "Feature",
  "properties": {
    "iso:country":"GB",
    "sg:address":"18 Newbridge Avenue",
    "sg:city":"Sunderland",
    "sg:classifiers":[
        {
            "category":"Building & Trades",
            "subcategory":"Construction",
            "type":"Services"
        }
    ],
    "sg:postcode":"SR5 1LD",
    "sg:province":"Tyne and Wear",
    "sg:tags":[
        "decorator",
        "painter"
    ],
    "wof:name":"Derek Hayman",
    "wof:placetype":"venue"
},
  "geometry": {"coordinates":[-1.38918,54.921818],"type":"Point"}
}