{
  "type": "Feature",
  "properties": {
    "addr:full":"Swansea Yacht Haven, Pilot House Wharf Swansea Neath Port Talbot SA1 1UN",
    "addr:postcode":"sa1 1un",
    "addr:street":"Wharf",
    "iso:country":"GB",
    "sg:address":"Swansea Yacht Haven, Pilot House Wharf",
    "sg:city":"Swansea",
    "sg:classifiers":[
        {
            "category":"Home & Garden",
            "subcategory":"Hardware",
            "type":"Retail Goods"
        }
    ],
    "sg:phone":"+44 1792 643554",
    "sg:postcode":"SA1 1UN",
    "sg:province":"Neath Port Talbot",
    "sg:tags":[
        "component",
        "electronic"
    ],
    "wof:name":"Marconi Communications Marine Divison",
    "wof:placetype":"venue"
},
  "geometry": {"coordinates":[-3.940929,51.623154],"type":"Point"}
}