{
  "type": "Feature",
  "properties": {
    "addr:full":"54 Fleet Street London Greater London EC4Y 1JU",
    "addr:housenumber":"54",
    "addr:postcode":"ec4y 1ju",
    "addr:street":"Fleet Street",
    "iso:country":"GB",
    "sg:address":"54 Fleet Street",
    "sg:city":"London",
    "sg:classifiers":[
        {
            "category":"Home & Garden",
            "subcategory":"Household Appliances",
            "type":"Retail Goods"
        }
    ],
    "sg:phone":"+44 20 7353 0575",
    "sg:postcode":"EC4Y 1JU",
    "sg:province":"Greater London",
    "sg:tags":[
        "electrical",
        "domestic"
    ],
    "wof:name":"Ryness Electrical Supplies Ltd.",
    "wof:placetype":"venue"
},
  "geometry": {"coordinates":[-0.108646,51.514076],"type":"Point"}
}