{
  "type": "Feature",
  "properties": {
    "addr:full":"179a City Road, Roath Cardiff Cardiff CF24 3JB",
    "addr:housenumber":"179a",
    "addr:postcode":"cf24 3jb",
    "addr:street":"City Road",
    "iso:country":"GB",
    "sg:address":"179a City Road, Roath",
    "sg:city":"Cardiff",
    "sg:classifiers":[
        {
            "category":"Sports & Exercise",
            "subcategory":"Gym",
            "type":"Entertainment"
        }
    ],
    "sg:phone":"+44 29 2046 5970",
    "sg:postcode":"CF24 3JB",
    "sg:province":"Cardiff",
    "sg:tags":[
        "fitness",
        "health",
        "centre"
    ],
    "wof:name":"The Health Spa",
    "wof:placetype":"venue"
},
  "geometry": {"coordinates":[-3.170589,51.490665],"type":"Point"}
}