{
  "type": "Feature",
  "properties": {
    "iso:country":"GB",
    "sg:address":"3 Old Barrack Yd, Knightsbridge",
    "sg:city":"London",
    "sg:classifiers":[
        {
            "category":"Communications",
            "type":"Services"
        }
    ],
    "sg:postcode":"SW1X 7NP",
    "sg:province":"Greater London",
    "sg:tags":[
        "telecommunication"
    ],
    "wof:name":"A 5 Direct Ltd",
    "wof:placetype":"venue"
},
  "geometry": {"coordinates":[-0.15485,51.50177],"type":"Point"}
}