{
  "type": "Feature",
  "properties": {
    "addr:full":"10-14 Crossway, Stoke Newington London Greater London N16 8XH",
    "addr:housenumber":"10-14",
    "addr:postcode":"n16 8xh",
    "addr:street":"Crossway",
    "iso:country":"GB",
    "sg:address":"10-14 Crossway, Stoke Newington",
    "sg:city":"London",
    "sg:classifiers":[
        {
            "category":"Manufacturing",
            "subcategory":"Building Materials",
            "type":"Manufacturing & Wholesale Goods"
        }
    ],
    "sg:phone":"+44 20 7254 1117",
    "sg:postcode":"N16 8XH",
    "sg:province":"Greater London",
    "sg:tags":[
        "merchant",
        "builder"
    ],
    "wof:name":"Deben Buildbase",
    "wof:placetype":"venue"
},
  "geometry": {"coordinates":[-0.0758080035,51.5505485535],"type":"Point"}
}