{
  "type": "Feature",
  "properties": {
    "addr:full":"25 Halleys Terrace York North Yorkshire YO31 8SB",
    "addr:housenumber":"25",
    "addr:postcode":"yo31 8sb",
    "addr:street":"Halleys Terrace",
    "iso:country":"GB",
    "sg:address":"25 Halleys Terrace",
    "sg:city":"York",
    "sg:classifiers":[
        {
            "category":"Autos & Motor Vehicles",
            "subcategory":"Motorcycle Sales",
            "type":"Retail Goods"
        }
    ],
    "sg:phone":"+44 1904 636589",
    "sg:postcode":"YO31 8SB",
    "sg:province":"North Yorkshire",
    "wof:name":"Honda City York",
    "wof:placetype":"venue"
},
  "geometry": {"coordinates":[-1.07443,53.974712],"type":"Point"}
}