{
  "type": "Feature",
  "properties": {
    "iso:country":"GB",
    "sg:address":"98 Ford Road, Upton",
    "sg:city":"Wirral",
    "sg:classifiers":[
        {
            "category":"Banks & Credit Unions",
            "subcategory":"Bank",
            "type":"Services"
        }
    ],
    "sg:phone":"+44 151 677 5123",
    "sg:postcode":"CH49 0TQ",
    "sg:province":"Merseyside",
    "wof:name":"Barclays Bank Plc",
    "wof:placetype":"venue"
},
  "geometry": {"coordinates":[-3.09513,53.384624],"type":"Point"}
}