{
  "type": "Feature",
  "properties": {
    "iso:country":"GB",
    "sg:address":"2 Springfield Gro",
    "sg:city":"Sunbury-on-thames",
    "sg:classifiers":[
        {
            "category":"Building & Trades",
            "subcategory":"Construction",
            "type":"Services"
        }
    ],
    "sg:phone":"+44 1932 785852",
    "sg:postcode":"TW16 6NT",
    "sg:province":"Surrey",
    "sg:tags":[
        "decorator",
        "painter"
    ],
    "wof:name":"Rainbow Painting Contractors",
    "wof:placetype":"venue"
},
  "geometry": {"coordinates":[-0.418659,51.415054],"type":"Point"}
}