{
  "type": "Feature",
  "properties": {
    "addr:full":"Monkton Down Farm, Monkton Honiton Devon EX14 9NJ",
    "addr:postcode":"ex14 9nj",
    "addr:street":"Monkton",
    "iso:country":"GB",
    "sg:address":"Monkton Down Farm, Monkton",
    "sg:city":"Honiton",
    "sg:classifiers":[
        {
            "category":"Farming",
            "subcategory":"Livestock Farm",
            "type":"Manufacturing & Wholesale Goods"
        }
    ],
    "sg:postcode":"EX14 9NJ",
    "sg:province":"Devon",
    "sg:tags":[
        "others"
    ],
    "wof:name":"S O Sparks & Son",
    "wof:placetype":"venue"
},
  "geometry": {"coordinates":[-3.1526880264,50.8237342834],"type":"Point"}
}