{
  "type": "Feature",
  "properties": {
    "addr:full":"The Lido, Worthy Lane Winchester Hampshire SO23 7AB",
    "addr:postcode":"so23 7ab",
    "addr:street":"Worthy Lane",
    "iso:country":"GB",
    "sg:address":"The Lido, Worthy Lane",
    "sg:city":"Winchester",
    "sg:classifiers":[
        {
            "category":"Education",
            "subcategory":"Preschool",
            "type":"Public Place"
        }
    ],
    "sg:phone":"+44 1962 855412",
    "sg:postcode":"SO23 7AB",
    "sg:province":"Hampshire",
    "sg:tags":[
        "pre-school",
        "playgroups"
    ],
    "wof:name":"Hartley House Montessori Ltd.",
    "wof:placetype":"venue"
},
  "geometry": {"coordinates":[-1.3168090582,51.0630683899],"type":"Point"}
}