{
  "type": "Feature",
  "properties": {
    "addr:full":"28 Muirhall Road Larbert Falkirk FK5 4AP",
    "addr:housenumber":"28",
    "addr:postcode":"fk5 4ap",
    "addr:street":"Muirhall Road",
    "iso:country":"GB",
    "sg:address":"28 Muirhall Road",
    "sg:city":"Larbert",
    "sg:classifiers":[
        {
            "category":"Fast Food",
            "type":"Food & Drink"
        }
    ],
    "sg:phone":"+44 1324 555295",
    "sg:postcode":"FK5 4AP",
    "sg:province":"Falkirk",
    "sg:tags":[
        "away",
        "take"
    ],
    "wof:name":"Rainbow Rolls",
    "wof:placetype":"venue"
},
  "geometry": {"coordinates":[-3.8296589851,56.0242614746],"type":"Point"}
}