{
  "type": "Feature",
  "properties": {
    "iso:country":"GB",
    "sg:address":"95 Mill Lane, Portslade",
    "sg:city":"Brighton",
    "sg:classifiers":[
        {
            "category":"Government",
            "subcategory":"Post Office",
            "type":"Public Place"
        }
    ],
    "sg:postcode":"BN41 2DF",
    "sg:province":"East Sussex",
    "wof:name":"Mill Lane Post Office",
    "wof:placetype":"venue"
},
  "geometry": {"coordinates":[-0.2107349932,50.8434486389],"type":"Point"}
}