{
  "type": "Feature",
  "properties": {
    "iso:country":"GB",
    "sg:address":"7 Bellfield Drive, North Kessock",
    "sg:city":"Inverness",
    "sg:classifiers":[
        {
            "category":"Communications",
            "type":"Services"
        }
    ],
    "sg:postcode":"IV1 3XT",
    "sg:province":"Highland",
    "sg:tags":[
        "system",
        "music",
        "public",
        "address"
    ],
    "wof:name":"Tuckwell Cable Visions Enterprises",
    "wof:placetype":"venue"
},
  "geometry": {"coordinates":[-4.261935,57.503723],"type":"Point"}
}