{
  "type": "Feature",
  "properties": {
    "addr:full":"11 Church Street, Staveley Chesterfield Derbyshire S43 3TL",
    "addr:housenumber":"11",
    "addr:postcode":"s43 3tl",
    "addr:street":"Church Street",
    "iso:country":"GB",
    "sg:address":"11 Church Street, Staveley",
    "sg:city":"Chesterfield",
    "sg:classifiers":[
        {
            "category":"Professional",
            "subcategory":"Business Services",
            "type":"Services"
        },
        {
            "category":"Shopping",
            "subcategory":"Pets & Pet Supplies",
            "type":"Retail Goods"
        }
    ],
    "sg:phone":"+44 1246 477878",
    "sg:postcode":"S43 3TL",
    "sg:province":"Derbyshire",
    "sg:tags":[
        "import",
        "export",
        "agent"
    ],
    "wof:name":"Aquatik",
    "wof:placetype":"venue"
},
  "geometry": {"coordinates":[-1.3503960371,53.2685852051],"type":"Point"}
}