{
  "type": "Feature",
  "properties": {
    "iso:country":"GB",
    "sg:address":"Richmond Farm, Langholme Crossroads, Haxey",
    "sg:city":"Doncaster",
    "sg:classifiers":[
        {
            "category":"Shopping",
            "subcategory":"Jewelry",
            "type":"Retail Goods"
        }
    ],
    "sg:phone":"+44 1427 890198",
    "sg:postcode":"DN9 2NP",
    "sg:province":"Lincolnshire",
    "sg:tags":[
        "gold",
        "silversmith"
    ],
    "wof:name":"Alexandra Austin",
    "wof:placetype":"venue"
},
  "geometry": {"coordinates":[-0.833937,53.488667],"type":"Point"}
}