{
  "type": "Feature",
  "properties": {
    "addr:full":"40 Forge Road Port Talbot Neath Port Talbot SA13 1NU",
    "addr:housenumber":"40",
    "addr:postcode":"sa13 1nu",
    "addr:street":"Forge Road",
    "iso:country":"GB",
    "sg:address":"40 Forge Road",
    "sg:city":"Port Talbot",
    "sg:classifiers":[
        {
            "category":"Banks & Credit Unions",
            "subcategory":"Financial Services",
            "type":"Services"
        }
    ],
    "sg:phone":"+44 1639 885905",
    "sg:postcode":"SA13 1NU",
    "sg:province":"Neath Port Talbot",
    "sg:tags":[
        "consultant"
    ],
    "wof:name":"Shopacheck Financial Services Ltd.",
    "wof:placetype":"venue"
},
  "geometry": {"coordinates":[-3.7808969021,51.5961532593],"type":"Point"}
}