{
  "type": "Feature",
  "properties": {
    "addr:full":"London Road Louth Lincolnshire LN11 9QP",
    "addr:postcode":"ln11 9qp",
    "addr:street":"London Road Louth",
    "iso:country":"GB",
    "sg:address":"London Road",
    "sg:city":"Louth",
    "sg:classifiers":[
        {
            "category":"Arena",
            "subcategory":"Sports Club",
            "type":"Entertainment"
        }
    ],
    "sg:phone":"+44 1507 608068",
    "sg:postcode":"LN11 9QP",
    "sg:province":"Lincolnshire",
    "wof:name":"Louth Sports Association",
    "wof:placetype":"venue"
},
  "geometry": {"coordinates":[-0.003473,53.359673],"type":"Point"}
}