{
  "type": "Feature",
  "properties": {
    "addr:full":"Glenlyon Place Leven Fife KY8 4QY",
    "addr:postcode":"ky8 4qy",
    "addr:street":"Glenlyon Place Leven",
    "iso:country":"GB",
    "sg:address":"Glenlyon Place",
    "sg:city":"Leven",
    "sg:classifiers":[
        {
            "category":"Retail",
            "subcategory":"Auto Repair",
            "type":"Services"
        }
    ],
    "sg:phone":"+44 1333 427868",
    "sg:postcode":"KY8 4QY",
    "sg:province":"Fife",
    "sg:tags":[
        "modification",
        "garage"
    ],
    "wof:name":"Firs Garage Leven",
    "wof:placetype":"venue"
},
  "geometry": {"coordinates":[-3.0026960373,56.196937561],"type":"Point"}
}