{
  "type": "Feature",
  "properties": {
    "iso:country":"GB",
    "sg:address":"22 Capel Road, Clydach",
    "sg:city":"Swansea",
    "sg:classifiers":[
        {
            "category":"Retail",
            "subcategory":"Auto Repair",
            "type":"Services"
        }
    ],
    "sg:phone":"+44 1792 844819",
    "sg:postcode":"SA6 5PZ",
    "sg:province":"Swansea",
    "sg:tags":[
        "body",
        "car"
    ],
    "wof:name":"G M D Body Repairs",
    "wof:placetype":"venue"
},
  "geometry": {"coordinates":[-3.88807,51.697487],"type":"Point"}
}