{
  "type": "Feature",
  "properties": {
    "addr:full":"70 Grafton Way London Greater London W1T 5DT",
    "addr:housenumber":"70",
    "addr:postcode":"w1t 5dt",
    "addr:street":"Grafton Way",
    "iso:country":"GB",
    "sg:address":"70 Grafton Way",
    "sg:city":"London",
    "sg:classifiers":[
        {
            "category":"Professional",
            "subcategory":"Research",
            "type":"Services"
        }
    ],
    "sg:phone":"+44 20 7554 5100",
    "sg:postcode":"W1T 5DT",
    "sg:province":"Greater London",
    "sg:tags":[
        "market"
    ],
    "wof:name":"Macon Consulting Ltd.",
    "wof:placetype":"venue"
},
  "geometry": {"coordinates":[-0.13856,51.523239],"type":"Point"}
}