{
  "type": "Feature",
  "properties": {
    "addr:full":"124 Bramcote Lane, Wollaton Nottingham Nottinghamshire NG8 2QG",
    "addr:housenumber":"124",
    "addr:postcode":"ng8 2qg",
    "addr:street":"Bramcote Lane",
    "iso:country":"GB",
    "sg:address":"124 Bramcote Lane, Wollaton",
    "sg:city":"Nottingham",
    "sg:classifiers":[
        {
            "category":"Health Services",
            "subcategory":"Podiatrist",
            "type":"Services"
        }
    ],
    "sg:postcode":"NG8 2QG",
    "sg:province":"Nottinghamshire",
    "sg:tags":[
        "podiatrists",
        "chiropodist"
    ],
    "wof:name":"John Goodliffe Mssch Mecha",
    "wof:placetype":"venue"
},
  "geometry": {"coordinates":[-1.227833,52.948772],"type":"Point"}
}