{
  "type": "Feature",
  "properties": {
    "iso:country":"GB",
    "sg:address":"The Dale",
    "sg:city":"Matlock",
    "sg:classifiers":[
        {
            "category":"Wholesale",
            "subcategory":"Metals & Minerals",
            "type":"Manufacturing & Wholesale Goods"
        }
    ],
    "sg:phone":"+44 1629 582245",
    "sg:postcode":"DE4 3PT",
    "sg:province":"Derbyshire",
    "sg:tags":[
        "merchant"
    ],
    "wof:name":"The Via Gellia Investment Co.",
    "wof:placetype":"venue"
},
  "geometry": {"coordinates":[-1.560694,53.144981],"type":"Point"}
}