{
  "type": "Feature",
  "properties": {
    "addr:full":"22b Oxford Road, Penmill Trading Estate Yeovil Somerset BA21 5HR",
    "addr:housenumber":"22b",
    "addr:postcode":"ba21 5hr",
    "addr:street":"Oxford Road Penmill Trading Estate",
    "iso:country":"GB",
    "sg:address":"22b Oxford Road, Penmill Trading Estate",
    "sg:city":"Yeovil",
    "sg:classifiers":[
        {
            "category":"Train Station",
            "subcategory":"Rail",
            "type":"Transportation"
        }
    ],
    "sg:phone":"+44 1935 412203",
    "sg:postcode":"BA21 5HR",
    "sg:province":"Somerset",
    "sg:tags":[
        "caravan"
    ],
    "wof:name":"Yeovil Trailers",
    "wof:placetype":"venue"
},
  "geometry": {"coordinates":[-2.6052830219,50.9516525269],"type":"Point"}
}