{
  "type": "Feature",
  "properties": {
    "addr:full":"Ampfield House, Winchester Road, Ampfield Romsey Hampshire SO51 9PA",
    "addr:postcode":"so51 9pa",
    "addr:street":"Winchester Road",
    "iso:country":"GB",
    "sg:address":"Ampfield House, Winchester Road, Ampfield",
    "sg:city":"Romsey",
    "sg:classifiers":[
        {
            "category":"Home & Garden",
            "subcategory":"Garden Supply",
            "type":"Retail Goods"
        }
    ],
    "sg:phone":"+44 1794 368733",
    "sg:postcode":"SO51 9PA",
    "sg:province":"Hampshire",
    "sg:tags":[
        "nursery",
        "centre"
    ],
    "wof:name":"Hillier Nurseries Ltd.",
    "wof:placetype":"venue"
},
  "geometry": {"coordinates":[-1.463681,50.997368],"type":"Point"}
}