{
  "type": "Feature",
  "properties": {
    "iso:country":"GB",
    "sg:address":"Exhibition Centre, Warwick Rd",
    "sg:city":"Earl's Court",
    "sg:classifiers":[
        {
            "category":"Professional",
            "type":"Services"
        }
    ],
    "sg:phone":"+44 20 7244 6233",
    "sg:postcode":"SW5 9TA",
    "sg:province":"Greater London",
    "sg:tags":[
        "exhibition"
    ],
    "wof:name":"P & O Exhibition Services Ltd",
    "wof:placetype":"venue"
},
  "geometry": {"coordinates":[-0.19322,51.48875],"type":"Point"}
}