{
  "type": "Feature",
  "properties": {
    "iso:country":"GB",
    "sg:address":"387 London Road",
    "sg:city":"Croydon",
    "sg:classifiers":[
        {
            "category":"Shopping",
            "subcategory":"Pharmacy",
            "type":"Retail Goods"
        }
    ],
    "sg:postcode":"CR0 3PB",
    "sg:province":"Surrey",
    "sg:tags":[
        "pharmacist",
        "chemist"
    ],
    "wof:name":"Mc Car Sales",
    "wof:placetype":"venue"
},
  "geometry": {"coordinates":[-0.1107309982,51.3863220215],"type":"Point"}
}