{
  "type": "Feature",
  "properties": {
    "addr:full":"20-22 Pages Walk Southwark Greater London SE1 4SB",
    "addr:housenumber":"20-22",
    "addr:postcode":"se1 4sb",
    "addr:street":"Pages Walk",
    "iso:country":"GB",
    "sg:address":"20-22 Pages Walk",
    "sg:city":"Southwark",
    "sg:classifiers":[
        {
            "category":"Home & Garden",
            "subcategory":"Home Furnishings",
            "type":"Retail Goods"
        }
    ],
    "sg:phone":"+44 20 7237 4421",
    "sg:postcode":"SE1 4SB",
    "sg:province":"Greater London",
    "sg:tags":[
        "tube",
        "fitting",
        "stockist"
    ],
    "wof:name":"Pipeline Centre",
    "wof:placetype":"venue"
},
  "geometry": {"coordinates":[-0.0803290009,51.4952278137],"type":"Point"}
}