{
  "type": "Feature",
  "properties": {
    "addr:full":"Muckhart Dollar Clackmannanshire FK14 7JN",
    "addr:postcode":"fk14 7jn",
    "iso:country":"GB",
    "sg:address":"Muckhart",
    "sg:city":"Dollar",
    "sg:classifiers":[
        {
            "category":"Bars & Pubs",
            "type":"Food & Drink"
        },
        {
            "category":"Community Center",
            "subcategory":"Social",
            "type":"Public Place"
        }
    ],
    "sg:phone":"+44 1259 781324",
    "sg:postcode":"FK14 7JN",
    "sg:province":"Clackmannanshire",
    "sg:tags":[
        "pubs",
        "house",
        "inn",
        "activity"
    ],
    "wof:name":"The Inn",
    "wof:placetype":"venue"
},
  "geometry": {"coordinates":[-3.6740090847,56.1627616882],"type":"Point"}
}