{
  "type": "Feature",
  "properties": {
    "iso:country":"GB",
    "sg:address":"9 The Cent Crescent",
    "sg:city":"Spalding",
    "sg:classifiers":[
        {
            "category":"Health Services",
            "subcategory":"Dentist",
            "type":"Services"
        }
    ],
    "sg:phone":"+44 1775 760364",
    "sg:postcode":"PE11 1AE",
    "sg:province":"Lincolnshire",
    "wof:name":"J V Syson",
    "wof:placetype":"venue"
},
  "geometry": {"coordinates":[-0.1532720029,52.7867355347],"type":"Point"}
}