{
  "type": "Feature",
  "properties": {
    "addr:full":"Unit 15a, Hoo Farm Industrial Estate, Worcester Road Kidderminster Staffordshire DY11 7RA",
    "addr:housenumber":"unit 15a hoo;industrial estate",
    "addr:postcode":"dy11 7ra",
    "addr:street":"Worcester Road",
    "iso:country":"GB",
    "sg:address":"Unit 15a, Hoo Farm Industrial Estate, Worcester Road",
    "sg:city":"Kidderminster",
    "sg:classifiers":[
        {
            "category":"Utilities",
            "subcategory":"Natural Gas",
            "type":"Services"
        },
        {
            "category":"Military Area",
            "subcategory":"Air Force Base",
            "type":"Public Place"
        }
    ],
    "sg:phone":"+44 1562 747756",
    "sg:postcode":"DY11 7RA",
    "sg:province":"Staffordshire",
    "sg:tags":[
        "supplier",
        "sanitary"
    ],
    "wof:name":"Kromschroder (U K) Ltd.",
    "wof:placetype":"venue"
},
  "geometry": {"coordinates":[-2.260479,52.37302],"type":"Point"}
}