{
  "type": "Feature",
  "properties": {
    "iso:country":"GB",
    "sg:address":"15 Haxey Lane",
    "sg:city":"Doncaster",
    "sg:classifiers":[
        {
            "category":"Home & Garden",
            "subcategory":"Home Furnishings",
            "type":"Retail Goods"
        },
        {
            "category":"Building & Trades",
            "subcategory":"Construction",
            "type":"Services"
        }
    ],
    "sg:phone":"+44 1427 754022",
    "sg:postcode":"DN9 2ND",
    "sg:province":"Lincolnshire",
    "sg:tags":[
        "furnishers",
        "builder",
        "planner",
        "kitchen"
    ],
    "wof:name":"A P A Contracts",
    "wof:placetype":"venue"
},
  "geometry": {"coordinates":[-0.834392,53.487797],"type":"Point"}
}