{
  "type": "Feature",
  "properties": {
    "addr:full":"64 Mary St Birmingham West Midlands B12 9ST",
    "addr:housenumber":"64",
    "addr:postcode":"b12 9st",
    "addr:street":"Mary St",
    "iso:country":"GB",
    "sg:address":"64 Mary St",
    "sg:city":"Birmingham",
    "sg:classifiers":[
        {
            "category":"Retail",
            "subcategory":"Driving School",
            "type":"Services"
        }
    ],
    "sg:phone":"+44 121 779 5934",
    "sg:postcode":"B12 9ST",
    "sg:province":"West Midlands",
    "wof:name":"Heartlands",
    "wof:placetype":"venue"
},
  "geometry": {"coordinates":[-1.8912409544,52.4595222473],"type":"Point"}
}