{
  "type": "Feature",
  "properties": {
    "addr:full":"London Road Brandon Norfolk IP27 0NE",
    "addr:postcode":"ip27 0ne",
    "addr:street":"London Road",
    "iso:country":"GB",
    "sg:address":"London Road",
    "sg:city":"Brandon",
    "sg:classifiers":[
        {
            "category":"Manufacturing",
            "subcategory":"Buildings",
            "type":"Manufacturing & Wholesale Goods"
        },
        {
            "category":"Professional",
            "subcategory":"Business Services",
            "type":"Services"
        }
    ],
    "sg:phone":"+44 1908 646767",
    "sg:postcode":"IP27 0NE",
    "sg:province":"Norfolk",
    "sg:tags":[
        "mobile",
        "caravan",
        "manufacturer",
        "home"
    ],
    "wof:name":"Omar Homes Ltd",
    "wof:placetype":"venue"
},
  "geometry": {"coordinates":[0.623352,52.447582],"type":"Point"}
}