{
  "type": "Feature",
  "properties": {
    "addr:full":"170 Nuncargate Road, Kirkby-in-ashfield Nottingham Nottinghamshire NG17 9EA",
    "addr:housenumber":"170",
    "addr:postcode":"ng17 9ea",
    "addr:street":"Nuncargate Road",
    "iso:country":"GB",
    "sg:address":"170 Nuncargate Road, Kirkby-in-ashfield",
    "sg:city":"Nottingham",
    "sg:classifiers":[
        {
            "category":"Shopping",
            "subcategory":"News",
            "type":"Retail Goods"
        },
        {
            "category":"Government",
            "subcategory":"Post Office",
            "type":"Public Place"
        }
    ],
    "sg:phone":"+44 1623 753102",
    "sg:postcode":"NG17 9EA",
    "sg:province":"Nottinghamshire",
    "sg:tags":[
        "newsagent"
    ],
    "wof:name":"Nuncargate Post Office",
    "wof:placetype":"venue"
},
  "geometry": {"coordinates":[-1.252042,53.082569],"type":"Point"}
}