{
  "type": "Feature",
  "properties": {
    "addr:full":"Fifth Floor, Castle Chambers, 43 Castle St Liverpool Merseyside L2 9TG",
    "addr:housenumber":"43",
    "addr:postcode":"l2 9tg",
    "addr:street":"Castle St",
    "iso:country":"GB",
    "sg:address":"Fifth Floor, Castle Chambers, 43 Castle St",
    "sg:city":"Liverpool",
    "sg:classifiers":[
        {
            "category":"Manufacturing",
            "subcategory":"Tools & Machinery",
            "type":"Manufacturing & Wholesale Goods"
        }
    ],
    "sg:phone":"+44 151 236 8001",
    "sg:postcode":"L2 9TG",
    "sg:province":"Merseyside",
    "sg:tags":[
        "society",
        "friendly"
    ],
    "wof:name":"Ellis & Buckle",
    "wof:placetype":"venue"
},
  "geometry": {"coordinates":[-2.9900300503,53.4060211182],"type":"Point"}
}