{
  "type": "Feature",
  "properties": {
    "addr:full":"15 Knightsbridge Westminster Greater London SW1X 7LY",
    "addr:housenumber":"15",
    "addr:postcode":"sw1x 7ly",
    "addr:street":"Knightsbridge",
    "iso:country":"GB",
    "sg:address":"15 Knightsbridge",
    "sg:city":"Westminster",
    "sg:classifiers":[
        {
            "category":"Banks & Credit Unions",
            "subcategory":"Bank",
            "type":"Services"
        }
    ],
    "sg:phone":"+44 20 7761 2600",
    "sg:postcode":"SW1X 7LY",
    "sg:province":"Greater London",
    "wof:name":"The Osmanli Bankasi",
    "wof:placetype":"venue"
},
  "geometry": {"coordinates":[-0.1532330066,51.5026855469],"type":"Point"}
}