{
  "type": "Feature",
  "properties": {
    "addr:full":"236 High Street, London Colney St Albans Hertfordshire AL2 1HP",
    "addr:housenumber":"236",
    "addr:postcode":"al2 1hp",
    "addr:street":"High Street",
    "iso:country":"GB",
    "sg:address":"236 High Street, London Colney",
    "sg:city":"St Albans",
    "sg:classifiers":[
        {
            "category":"Retail",
            "subcategory":"Laundry & Dry Cleaning",
            "type":"Services"
        }
    ],
    "sg:postcode":"AL2 1HP",
    "sg:province":"Hertfordshire",
    "sg:tags":[
        "launderette"
    ],
    "wof:name":"Posh Wash",
    "wof:placetype":"venue"
},
  "geometry": {"coordinates":[-0.29741,51.725876],"type":"Point"}
}