{
  "type": "Feature",
  "properties": {
    "addr:full":"High Street, Clee Hill Ludlow Herefordshire SY8 3LZ",
    "addr:postcode":"sy8 3lz",
    "addr:street":"High Street",
    "iso:country":"GB",
    "sg:address":"High Street, Clee Hill",
    "sg:city":"Ludlow",
    "sg:classifiers":[
        {
            "category":"Bars & Pubs",
            "type":"Food & Drink"
        }
    ],
    "sg:phone":"+44 1584 890741",
    "sg:postcode":"SY8 3LZ",
    "sg:province":"Herefordshire",
    "sg:tags":[
        "pubs",
        "inn"
    ],
    "wof:name":"The Golden Cross",
    "wof:placetype":"venue"
},
  "geometry": {"coordinates":[-2.597629,52.374596],"type":"Point"}
}