{
  "type": "Feature",
  "properties": {
    "addr:full":"3 Wynter Road, Somers Road Industrial Estate Rugby Warwickshire CV22 7EB",
    "addr:housenumber":"3",
    "addr:postcode":"cv22 7eb",
    "addr:street":"Wynter Road Somers Road Industrial Estate",
    "iso:country":"GB",
    "sg:address":"3 Wynter Road, Somers Road Industrial Estate",
    "sg:city":"Rugby",
    "sg:classifiers":[
        {
            "category":"Professional",
            "type":"Services"
        }
    ],
    "sg:postcode":"CV22 7EB",
    "sg:province":"Warwickshire",
    "sg:tags":[
        "pattern",
        "industrial",
        "maker"
    ],
    "wof:name":"S S Patterns",
    "wof:placetype":"venue"
},
  "geometry": {"coordinates":[-1.285319,52.37159],"type":"Point"}
}