{
  "type": "Feature",
  "properties": {
    "addr:full":"155 Blackburn Road Darwen Lancashire BB3 1ET",
    "addr:housenumber":"155",
    "addr:postcode":"bb3 1et",
    "addr:street":"Blackburn Road",
    "iso:country":"GB",
    "sg:address":"155 Blackburn Road",
    "sg:city":"Darwen",
    "sg:classifiers":[
        {
            "category":"Food & Beverages",
            "subcategory":"Meat & Fish",
            "type":"Retail Goods"
        },
        {
            "category":"Food & Beverages",
            "subcategory":"Groceries & Convenience Stores",
            "type":"Retail Goods"
        }
    ],
    "sg:phone":"+44 1254 703940",
    "sg:postcode":"BB3 1ET",
    "sg:province":"Lancashire",
    "sg:tags":[
        "shop",
        "chip"
    ],
    "wof:name":"Hollins Grove Fish & Chip Shop",
    "wof:placetype":"venue"
},
  "geometry": {"coordinates":[-2.4781160355,53.7059707642],"type":"Point"}
}