{
  "type": "Feature",
  "properties": {
    "addr:full":"577 Lanark Rd Juniper Green City of Edinburgh EH14 5DB",
    "addr:housenumber":"577",
    "addr:postcode":"eh14 5db",
    "addr:street":"Lanark Rd",
    "iso:country":"GB",
    "sg:address":"577 Lanark Rd",
    "sg:city":"Juniper Green",
    "sg:classifiers":[
        {
            "category":"Health Services",
            "subcategory":"Dentist",
            "type":"Services"
        }
    ],
    "sg:phone":"+44 131 453 4038",
    "sg:postcode":"EH14 5DB",
    "sg:province":"City of Edinburgh",
    "wof:name":"L.C Chong Kwan B.D.S",
    "wof:placetype":"venue"
},
  "geometry": {"coordinates":[-3.2885980606,55.9020652771],"type":"Point"}
}