{
  "type": "Feature",
  "properties": {
    "iso:country":"GB",
    "sg:address":"Unit 1 Rockfield Road",
    "sg:city":"Hereford",
    "sg:classifiers":[
        {
            "category":"Professional",
            "subcategory":"Engineering",
            "type":"Services"
        },
        {
            "category":"Building & Trades",
            "subcategory":"Construction",
            "type":"Services"
        }
    ],
    "sg:phone":"+44 1432 269282",
    "sg:postcode":"HR1 2UA",
    "sg:province":"Herefordshire",
    "sg:tags":[
        "engineer",
        "mechanical",
        "pipework",
        "contractor"
    ],
    "wof:name":"Northsound Ltd.",
    "wof:placetype":"venue"
},
  "geometry": {"coordinates":[-2.704694,52.059631],"type":"Point"}
}