{
  "type": "Feature",
  "properties": {
    "addr:full":"129 Wandsworth Bridge Road London Greater London SW6 2TT",
    "addr:housenumber":"129",
    "addr:postcode":"sw6 2tt",
    "addr:street":"Wandsworth Bridge Road",
    "iso:country":"GB",
    "sg:address":"129 Wandsworth Bridge Road",
    "sg:city":"London",
    "sg:classifiers":[
        {
            "category":"Home & Garden",
            "subcategory":"Carpets & Floor Coverings",
            "type":"Retail Goods"
        }
    ],
    "sg:phone":"+44 20 7731 7819",
    "sg:postcode":"SW6 2TT",
    "sg:province":"Greater London",
    "sg:tags":[
        "carpets",
        "rug",
        "matting"
    ],
    "wof:name":"Baluch Oriental Carpets",
    "wof:placetype":"venue"
},
  "geometry": {"coordinates":[-0.191227,51.471294],"type":"Point"}
}