{
  "type": "Feature",
  "properties": {
    "addr:full":"71 Lea Bridge Road London Greater London E10 7QL",
    "addr:housenumber":"71",
    "addr:postcode":"e10 7ql",
    "addr:street":"Lea Bridge Road",
    "iso:country":"GB",
    "sg:address":"71 Lea Bridge Road",
    "sg:city":"London",
    "sg:classifiers":[
        {
            "category":"Sports & Exercise",
            "subcategory":"Stables",
            "type":"Entertainment"
        }
    ],
    "sg:phone":"+44 20 8556 2629",
    "sg:postcode":"E10 7QL",
    "sg:province":"Greater London",
    "sg:tags":[
        "education",
        "equestrian"
    ],
    "wof:name":"Lee Valley Riding Centre",
    "wof:placetype":"venue"
},
  "geometry": {"coordinates":[-0.037414,51.56583],"type":"Point"}
}