{
  "type": "Feature",
  "properties": {
    "addr:full":"50 Farren Rd Coventry Warwickshire CV2 5EN",
    "addr:housenumber":"50",
    "addr:postcode":"cv2 5en",
    "addr:street":"Farren Rd",
    "iso:country":"GB",
    "sg:address":"50 Farren Rd",
    "sg:city":"Coventry",
    "sg:classifiers":[
        {
            "category":"Retail",
            "subcategory":"Auto Repair",
            "type":"Services"
        }
    ],
    "sg:phone":"+44 24 7672 3436",
    "sg:postcode":"CV2 5EN",
    "sg:province":"Warwickshire",
    "sg:tags":[
        "car",
        "specialist",
        "customizing"
    ],
    "wof:name":"Tyre Master Mobile Tyre Fitting",
    "wof:placetype":"venue"
},
  "geometry": {"coordinates":[-1.4569790363,52.4170532227],"type":"Point"}
}