{
  "type": "Feature",
  "properties": {
    "iso:country":"GB",
    "sg:address":"Coton Road",
    "sg:city":"Nuneaton",
    "sg:classifiers":[
        {
            "category":"Bars & Pubs",
            "type":"Food & Drink"
        },
        {
            "category":"Community Center",
            "subcategory":"Social",
            "type":"Public Place"
        }
    ],
    "sg:postcode":"CV11 5TS",
    "sg:province":"Leicestershire",
    "sg:tags":[
        "pubs",
        "house",
        "inn",
        "activity"
    ],
    "wof:name":"Marston Thompson & Evershed Ltd.",
    "wof:placetype":"venue"
},
  "geometry": {"coordinates":[-1.467913,52.521309],"type":"Point"}
}