{
  "type": "Feature",
  "properties": {
    "addr:full":"551 Green Lane London Greater London N8 0RL",
    "addr:housenumber":"551",
    "addr:postcode":"n8 0rl",
    "addr:street":"Green Lane",
    "iso:country":"GB",
    "sg:address":"551 Green Lane",
    "sg:city":"London",
    "sg:classifiers":[
        {
            "category":"Restaurant",
            "type":"Food & Drink"
        }
    ],
    "sg:phone":"+44 20 8340 9691",
    "sg:postcode":"N8 0RL",
    "sg:province":"Greater London",
    "wof:name":"Kosem Restaurant",
    "wof:placetype":"venue"
},
  "geometry": {"coordinates":[-0.1000310034,51.5828323364],"type":"Point"}
}