{
  "type": "Feature",
  "properties": {
    "addr:full":"Beva Quorum Centre, Belfield Rd Rochdale Lancashire OL16 2UX",
    "addr:postcode":"ol16 2ux",
    "addr:street":"Belfield Rd",
    "iso:country":"GB",
    "sg:address":"Beva Quorum Centre, Belfield Rd",
    "sg:city":"Rochdale",
    "sg:classifiers":[
        {
            "category":"Retail",
            "subcategory":"Storage",
            "type":"Services"
        }
    ],
    "sg:phone":"+44 1706 651116",
    "sg:postcode":"OL16 2UX",
    "sg:province":"Lancashire",
    "sg:tags":[
        "household",
        "removal"
    ],
    "wof:name":"Beva Storage & Distribution Ltd",
    "wof:placetype":"venue"
},
  "geometry": {"coordinates":[-2.138999939,53.6217918396],"type":"Point"}
}