{
  "type": "Feature",
  "properties": {
    "iso:country":"GB",
    "sg:address":"Po Box 3, Willowyard Rd",
    "sg:city":"Beith",
    "sg:classifiers":[
        {
            "category":"Home & Garden",
            "subcategory":"Hardware",
            "type":"Retail Goods"
        }
    ],
    "sg:phone":"+44 1505 502206",
    "sg:postcode":"KA15 1JQ",
    "sg:province":"North Ayrshire",
    "sg:tags":[
        "heat",
        "mech",
        "exchanger"
    ],
    "wof:name":"Chemtec B V",
    "wof:placetype":"venue"
},
  "geometry": {"coordinates":[-4.6250391006,55.7398910522],"type":"Point"}
}