{
  "type": "Feature",
  "properties": {
    "addr:full":"Unit 9 Worcester Court, Mannesman Close, Enterprise Park Swansea Neath Port Talbot SA7 9AH",
    "addr:housenumber":"unit 9",
    "addr:postcode":"sa7 9ah",
    "addr:street":"Worcester Court Mannesman Close Enterprise Park",
    "iso:country":"GB",
    "sg:address":"Unit 9 Worcester Court, Mannesman Close, Enterprise Park",
    "sg:city":"Swansea",
    "sg:classifiers":[
        {
            "category":"Autos & Motor Vehicles",
            "subcategory":"Auto Supplies",
            "type":"Retail Goods"
        }
    ],
    "sg:phone":"+44 1792 792723",
    "sg:postcode":"SA7 9AH",
    "sg:province":"Neath Port Talbot",
    "sg:tags":[
        "windscreen"
    ],
    "wof:name":"Auto Windscreens",
    "wof:placetype":"venue"
},
  "geometry": {"coordinates":[-3.9049789906,51.6587181091],"type":"Point"}
}