{
  "type": "Feature",
  "properties": {
    "addr:full":"B P C House, Unit 12, Romsey Industrial Estate Romsey Hampshire SO51 0HR",
    "addr:housenumber":"p c house unit 12",
    "addr:postcode":"so51 0hr",
    "addr:street":"B;Industrial",
    "iso:country":"GB",
    "sg:address":"B P C House, Unit 12, Romsey Industrial Estate",
    "sg:city":"Romsey",
    "sg:classifiers":[
        {
            "category":"Professional",
            "subcategory":"Computer Services",
            "type":"Services"
        }
    ],
    "sg:phone":"+44 1794 521200",
    "sg:postcode":"SO51 0HR",
    "sg:province":"Hampshire",
    "sg:tags":[
        "security",
        "retail"
    ],
    "wof:name":"B P C Ltd.",
    "wof:placetype":"venue"
},
  "geometry": {"coordinates":[-1.4970289469,50.9958152771],"type":"Point"}
}