{
  "type": "Feature",
  "properties": {
    "addr:full":"Wellington Avenue Princes Risborough Buckinghamshire HP27 9HY",
    "addr:postcode":"hp27 9hy",
    "addr:street":"Wellington Avenue",
    "iso:country":"GB",
    "sg:address":"Wellington Avenue",
    "sg:city":"Princes Risborough",
    "sg:classifiers":[
        {
            "category":"Education",
            "subcategory":"School",
            "type":"Public Place"
        }
    ],
    "sg:phone":"+44 1844 345251",
    "sg:postcode":"HP27 9HY",
    "sg:province":"Buckinghamshire",
    "sg:tags":[
        "local",
        "authority"
    ],
    "wof:name":"Icknield County Middle School",
    "wof:placetype":"venue"
},
  "geometry": {"coordinates":[-0.827539,51.730015],"type":"Point"}
}