{
  "type": "Feature",
  "properties": {
    "iso:country":"GB",
    "sg:address":"23 Lower Trinity Street",
    "sg:city":"Birmingham",
    "sg:classifiers":[
        {
            "category":"Professional",
            "subcategory":"Engineering",
            "type":"Services"
        }
    ],
    "sg:postcode":"B9 4AG",
    "sg:province":"West Midlands",
    "sg:tags":[
        "engineer"
    ],
    "wof:name":"J A M Engineering",
    "wof:placetype":"venue"
},
  "geometry": {"coordinates":[-1.880959,52.474922],"type":"Point"}
}