{
  "type": "Feature",
  "properties": {
    "addr:full":"Crawley Down Health Centre, Bowers Pl Crawley Surrey RH10 4HY",
    "addr:postcode":"rh10 4hy",
    "addr:street":"Crawley;Bowers Pl",
    "iso:country":"GB",
    "sg:address":"Crawley Down Health Centre, Bowers Pl",
    "sg:city":"Crawley",
    "sg:classifiers":[
        {
            "category":"Health Services",
            "subcategory":"Doctor",
            "type":"Services"
        }
    ],
    "sg:phone":"+44 1342 713031",
    "sg:postcode":"RH10 4HY",
    "sg:province":"Surrey",
    "sg:tags":[
        "practitioners"
    ],
    "wof:name":"Clifford, A D",
    "wof:placetype":"venue"
},
  "geometry": {"coordinates":[-0.0860290006,51.12292099],"type":"Point"}
}