{
  "type": "Feature",
  "properties": {
    "addr:full":"40 Landseer Road Ipswich Suffolk IP3 0DG",
    "addr:housenumber":"40",
    "addr:postcode":"ip3 0dg",
    "addr:street":"Landseer Road",
    "iso:country":"GB",
    "sg:address":"40 Landseer Road",
    "sg:city":"Ipswich",
    "sg:classifiers":[
        {
            "category":"Utilities",
            "subcategory":"Fuel Oil & Lpg",
            "type":"Services"
        },
        {
            "category":"Wholesale",
            "subcategory":"Petroleum",
            "type":"Manufacturing & Wholesale Goods"
        }
    ],
    "sg:phone":"+44 1473 211212",
    "sg:postcode":"IP3 0DG",
    "sg:province":"Suffolk",
    "sg:tags":[
        "distributor"
    ],
    "wof:name":"Hardy Craske Fuels Ltd",
    "wof:placetype":"venue"
},
  "geometry": {"coordinates":[1.17133,52.038078],"type":"Point"}
}