{
  "type": "Feature",
  "properties": {
    "addr:full":"Noble Road Dundee Dundee City DD2 4UH",
    "addr:postcode":"dd2 4uh",
    "addr:street":"Noble Road",
    "iso:country":"GB",
    "sg:address":"Noble Road",
    "sg:city":"Dundee",
    "sg:classifiers":[
        {
            "category":"Manufacturing",
            "subcategory":"Wood Products",
            "type":"Manufacturing & Wholesale Goods"
        }
    ],
    "sg:phone":"+44 1382 624422",
    "sg:postcode":"DD2 4UH",
    "sg:province":"Dundee City",
    "sg:tags":[
        "packaging",
        "crate",
        "pallets"
    ],
    "wof:name":"G & D Pallets",
    "wof:placetype":"venue"
},
  "geometry": {"coordinates":[-3.0569090843,56.4762649536],"type":"Point"}
}