{
  "type": "Feature",
  "properties": {
    "addr:full":"5 Ovingham Clo, Horsley Grange Washington Durham NE38 8NP",
    "addr:housenumber":"5",
    "addr:postcode":"ne38 8np",
    "addr:street":"Ovingham Clo",
    "iso:country":"GB",
    "sg:address":"5 Ovingham Clo, Horsley Grange",
    "sg:city":"Washington",
    "sg:classifiers":[
        {
            "category":"Professional",
            "subcategory":"Secretarial Services",
            "type":"Services"
        }
    ],
    "sg:postcode":"NE38 8NP",
    "sg:province":"Durham",
    "wof:name":"Karen,Quinn,",
    "wof:placetype":"venue"
},
  "geometry": {"coordinates":[-1.509384,54.898239],"type":"Point"}
}