{
  "type": "Feature",
  "properties": {
    "iso:country":"GB",
    "sg:address":"45 Hildyard Clo",
    "sg:city":"Gloucester",
    "sg:classifiers":[
        {
            "category":"Building & Trades",
            "subcategory":"Construction",
            "type":"Services"
        }
    ],
    "sg:phone":"+44 1452 728144",
    "sg:postcode":"GL2 4PZ",
    "sg:province":"Gloucestershire",
    "sg:tags":[
        "builder"
    ],
    "wof:name":"J R Townsend",
    "wof:placetype":"venue"
},
  "geometry": {"coordinates":[-2.282842,51.816414],"type":"Point"}
}