{
  "type": "Feature",
  "properties": {
    "addr:full":"9 King Street London Greater London EC2V 8EA",
    "addr:housenumber":"9",
    "addr:postcode":"ec2v 8ea",
    "addr:street":"King Street",
    "iso:country":"GB",
    "sg:address":"9 King Street",
    "sg:city":"London",
    "sg:classifiers":[
        {
            "category":"Real Estate",
            "subcategory":"Surveying",
            "type":"Services"
        }
    ],
    "sg:phone":"+44 20 7600 8787",
    "sg:postcode":"EC2V 8EA",
    "sg:province":"Greater London",
    "sg:tags":[
        "surveyor",
        "quantity"
    ],
    "wof:name":"Currie & Brown Consulting",
    "wof:placetype":"venue"
},
  "geometry": {"coordinates":[-0.0921,51.514561],"type":"Point"}
}