{
  "type": "Feature",
  "properties": {
    "iso:country":"GB",
    "sg:address":"18 Horsforth Avenue",
    "sg:city":"Bridlington",
    "sg:classifiers":[
        {
            "category":"Travel",
            "subcategory":"Hotels & Motels",
            "type":"Entertainment"
        }
    ],
    "sg:postcode":"YO15 3DF",
    "sg:province":"East Riding of Yorkshire",
    "sg:tags":[
        "house",
        "guest"
    ],
    "wof:name":"Sunnyside Guest House",
    "wof:placetype":"venue"
},
  "geometry": {"coordinates":[-0.198137,54.079536],"type":"Point"}
}