{
  "type": "Feature",
  "properties": {
    "iso:country":"GB",
    "sg:address":"231 Narborough Road",
    "sg:city":"Leicester",
    "sg:classifiers":[
        {
            "category":"Retail",
            "subcategory":"Laundry & Dry Cleaning",
            "type":"Services"
        }
    ],
    "sg:phone":"+44 116 282 6241",
    "sg:postcode":"LE3 2QR",
    "sg:province":"Leicestershire",
    "sg:tags":[
        "launderette"
    ],
    "wof:name":"Superwash Launderette",
    "wof:placetype":"venue"
},
  "geometry": {"coordinates":[-1.1546430588,52.6230621338],"type":"Point"}
}