{
  "type": "Feature",
  "properties": {
    "iso:country":"GB",
    "sg:address":"73 Ridgewood Drive",
    "sg:city":"Wirral",
    "sg:classifiers":[
        {
            "category":"Shopping",
            "subcategory":"Department Store",
            "type":"Retail Goods"
        },
        {
            "category":"Food & Beverages",
            "subcategory":"Groceries & Convenience Stores",
            "type":"Retail Goods"
        }
    ],
    "sg:postcode":"CH61 8RF",
    "sg:province":"Merseyside",
    "wof:name":"RIDGEWOODS",
    "wof:placetype":"venue"
},
  "geometry": {"coordinates":[-3.1024999619,53.3485069275],"type":"Point"}
}