{
  "type": "Feature",
  "properties": {
    "iso:country":"GB",
    "sg:address":"The Vicarage, 80 Main Rd",
    "sg:city":"Ilkeston",
    "sg:classifiers":[
        {
            "category":"Place Of Worship",
            "type":"Public Place"
        }
    ],
    "sg:phone":"+44 1332 880380",
    "sg:postcode":"DE7 6EF",
    "sg:province":"Derbyshire",
    "wof:name":"St John The Baptist C of E Church",
    "wof:placetype":"venue"
},
  "geometry": {"coordinates":[-1.3101890087,52.9786109924],"type":"Point"}
}