{
  "type": "Feature",
  "properties": {
    "addr:full":"7 Holme Lane, Bottesford Scunthorpe Lincolnshire DN16 3RP",
    "addr:housenumber":"7",
    "addr:postcode":"dn16 3rp",
    "addr:street":"Holme Lane",
    "iso:country":"GB",
    "sg:address":"7 Holme Lane, Bottesford",
    "sg:city":"Scunthorpe",
    "sg:classifiers":[
        {
            "category":"Building & Trades",
            "subcategory":"Construction",
            "type":"Services"
        }
    ],
    "sg:postcode":"DN16 3RP",
    "sg:province":"Lincolnshire",
    "sg:tags":[
        "builder"
    ],
    "wof:name":"R G B Construction",
    "wof:placetype":"venue"
},
  "geometry": {"coordinates":[-0.6431959867,53.5540809631],"type":"Point"}
}