{
  "type": "Feature",
  "properties": {
    "iso:country":"GB",
    "sg:address":"Loomer Rd Ind Est, Chesterton",
    "sg:city":"Newcastle",
    "sg:classifiers":[
        {
            "category":"Wholesale",
            "subcategory":"Electrical",
            "type":"Manufacturing & Wholesale Goods"
        }
    ],
    "sg:phone":"+44 1782 561440",
    "sg:postcode":"ST5 7JZ",
    "sg:province":"Staffordshire",
    "sg:tags":[
        "equipment",
        "refrigeration"
    ],
    "wof:name":"Beldam Lascar Seals & Autoklean Filtration Ltd",
    "wof:placetype":"venue"
},
  "geometry": {"coordinates":[-2.248469,53.036201],"type":"Point"}
}