{
  "type": "Feature",
  "properties": {
    "iso:country":"GB",
    "sg:address":"16 Ralli Courts, West Rverside",
    "sg:city":"Manchester",
    "sg:classifiers":[
        {
            "category":"Professional",
            "subcategory":"Advertising",
            "type":"Services"
        }
    ],
    "sg:postcode":"M3 5FT",
    "sg:province":"Greater Manchester",
    "wof:name":"Justinsure Ltd.",
    "wof:placetype":"venue"
},
  "geometry": {"coordinates":[-2.248809,53.479622],"type":"Point"}
}