{
  "type": "Feature",
  "properties": {
    "iso:country":"GB",
    "sg:address":"Wyvern House, Bunbury Lane, Bunbury",
    "sg:city":"Tarporley",
    "sg:classifiers":[
        {
            "category":"Professional",
            "subcategory":"Advertising",
            "type":"Services"
        }
    ],
    "sg:phone":"+44 1829 260330",
    "sg:postcode":"CW6 9QS",
    "sg:province":"Cheshire",
    "sg:tags":[
        "telemarketing"
    ],
    "wof:name":"Phone Power North",
    "wof:placetype":"venue"
},
  "geometry": {"coordinates":[-2.653347,53.11105],"type":"Point"}
}