{
  "type": "Feature",
  "properties": {
    "addr:full":"Willows End, Kelmscott Lechlade Lechlade Gloucestershire GL7 3HG",
    "addr:postcode":"gl7 3hg",
    "iso:country":"GB",
    "sg:address":"Willows End, Kelmscott Lechlade",
    "sg:city":"Lechlade",
    "sg:classifiers":[
        {
            "category":"Professional",
            "subcategory":"Computer Services",
            "type":"Services"
        }
    ],
    "sg:phone":"+44 1367 250024",
    "sg:postcode":"GL7 3HG",
    "sg:province":"Gloucestershire",
    "sg:tags":[
        "system",
        "software"
    ],
    "wof:name":"S A R Computing Ltd.",
    "wof:placetype":"venue"
},
  "geometry": {"coordinates":[-1.691909,51.694077],"type":"Point"}
}