{
  "type": "Feature",
  "properties": {
    "addr:full":"Unit 7 The Old Pottery, Fore Street, Chudleigh Newton Abbot Devon TQ13 0HX",
    "addr:housenumber":"unit 7 the old",
    "addr:postcode":"tq13 0hx",
    "addr:street":"Fore Street",
    "iso:country":"GB",
    "sg:address":"Unit 7 The Old Pottery, Fore Street, Chudleigh",
    "sg:city":"Newton Abbot",
    "sg:classifiers":[
        {
            "category":"Home & Garden",
            "subcategory":"Home Furnishings",
            "type":"Retail Goods"
        }
    ],
    "sg:phone":"+44 1626 852500",
    "sg:postcode":"TQ13 0HX",
    "sg:province":"Devon",
    "sg:tags":[
        "soft"
    ],
    "wof:name":"Beau-Monde",
    "wof:placetype":"venue"
},
  "geometry": {"coordinates":[-3.6016008854,50.6042289734],"type":"Point"}
}