{
  "type": "Feature",
  "properties": {
    "iso:country":"GB",
    "sg:address":"Woodroyd Mills, South Pde",
    "sg:city":"Cleckheaton",
    "sg:classifiers":[
        {
            "category":"Personal",
            "subcategory":"Skin Care",
            "type":"Services"
        }
    ],
    "sg:postcode":"BD19 3AF",
    "sg:province":"West Yorkshire",
    "sg:tags":[
        "leather",
        "merchant"
    ],
    "wof:name":"Snape,Marshall,",
    "wof:placetype":"venue"
},
  "geometry": {"coordinates":[-1.711889,53.72517],"type":"Point"}
}