{
  "type": "Feature",
  "properties": {
    "iso:country":"GB",
    "sg:address":"Ammerdown Park",
    "sg:city":"Radstock",
    "sg:classifiers":[
        {
            "category":"Community Center",
            "type":"Public Place"
        }
    ],
    "sg:postcode":"BA3 5SW",
    "sg:province":"Somerset",
    "sg:tags":[
        "conference",
        "room",
        "centre"
    ],
    "wof:name":"The Ammerdown Centre Limited",
    "wof:placetype":"venue"
},
  "geometry": {"coordinates":[-2.408921,51.279984],"type":"Point"}
}