{
  "type": "Feature",
  "properties": {
    "addr:full":"81 Maytree Avenue Worthing West Sussex BN14 0HP",
    "addr:housenumber":"81",
    "addr:postcode":"bn14 0hp",
    "addr:street":"Maytree Avenue",
    "iso:country":"GB",
    "sg:address":"81 Maytree Avenue",
    "sg:city":"Worthing",
    "sg:classifiers":[
        {
            "category":"Building & Trades",
            "subcategory":"Plumbing",
            "type":"Services"
        }
    ],
    "sg:phone":"+44 1903 872224",
    "sg:postcode":"BN14 0HP",
    "sg:province":"West Sussex",
    "sg:tags":[
        "central",
        "heating"
    ],
    "wof:name":"A & P Heating",
    "wof:placetype":"venue"
},
  "geometry": {"coordinates":[-0.401013,50.856403],"type":"Point"}
}