{
  "type": "Feature",
  "properties": {
    "addr:full":"Unit 8, Clock 17 Paisley Renfrewshire PA1 1TJ",
    "addr:housenumber":"unit 8;17",
    "addr:postcode":"pa1 1tj",
    "addr:street":"Clock",
    "iso:country":"GB",
    "sg:address":"Unit 8, Clock 17",
    "sg:city":"Paisley",
    "sg:classifiers":[
        {
            "category":"Wholesale",
            "subcategory":"Office Equipment",
            "type":"Manufacturing & Wholesale Goods"
        },
        {
            "category":"Government",
            "subcategory":"Office",
            "type":"Public Place"
        }
    ],
    "sg:phone":"+44 141 889 0688",
    "sg:postcode":"PA1 1TJ",
    "sg:province":"Renfrewshire",
    "sg:tags":[
        "agency",
        "local",
        "business",
        "enterprise"
    ],
    "wof:name":"New Enterprise Workshop",
    "wof:placetype":"venue"
},
  "geometry": {"coordinates":[-4.40504,55.842869],"type":"Point"}
}