{
  "type": "Feature",
  "properties": {
    "addr:full":"21a Station Road, Cheadle Hulme Cheadle Cheshire SK8 5AF",
    "addr:housenumber":"21a",
    "addr:postcode":"sk8 5af",
    "addr:street":"Station Road",
    "iso:country":"GB",
    "sg:address":"21a Station Road, Cheadle Hulme",
    "sg:city":"Cheadle",
    "sg:classifiers":[
        {
            "category":"Building & Trades",
            "subcategory":"Construction",
            "type":"Services"
        }
    ],
    "sg:phone":"+44 161 485 8900",
    "sg:postcode":"SK8 5AF",
    "sg:province":"Cheshire",
    "sg:tags":[
        "roofing"
    ],
    "wof:name":"Northern Roofing Services",
    "wof:placetype":"venue"
},
  "geometry": {"coordinates":[-2.1894440651,53.3771247864],"type":"Point"}
}