{
  "type": "Feature",
  "properties": {
    "iso:country":"GB",
    "sg:address":"Pen Y Bryn, Llanmaes",
    "sg:city":"Llantwit Major",
    "sg:classifiers":[
        {
            "category":"Retail",
            "subcategory":"Storage",
            "type":"Services"
        }
    ],
    "sg:phone":"+44 1446 792403",
    "sg:postcode":"CF61 2XR",
    "sg:province":"The Vale of Glamorgan",
    "sg:tags":[
        "caravan",
        "household",
        "removal"
    ],
    "wof:name":"Janig Stephens",
    "wof:placetype":"venue"
},
  "geometry": {"coordinates":[-3.4678890705,51.4175796509],"type":"Point"}
}