{
  "type": "Feature",
  "properties": {
    "iso:country":"GB",
    "sg:address":"3 Hatcher Close",
    "sg:city":"Honiton",
    "sg:classifiers":[
        {
            "category":"Professional",
            "subcategory":"Accounting & Tax Preparation",
            "type":"Services"
        }
    ],
    "sg:postcode":"EX14 2YG",
    "sg:province":"Devon",
    "sg:tags":[
        "accountant"
    ],
    "wof:name":"Ninelives Ltd.",
    "wof:placetype":"venue"
},
  "geometry": {"coordinates":[-3.189673,50.788502],"type":"Point"}
}