{
  "type": "Feature",
  "properties": {
    "addr:full":"12 Museum Street Colchester Essex CO1 1TN",
    "addr:housenumber":"12",
    "addr:postcode":"co1 1tn",
    "addr:street":"Museum Street",
    "iso:country":"GB",
    "sg:address":"12 Museum Street",
    "sg:city":"Colchester",
    "sg:classifiers":[
        {
            "category":"Home & Garden",
            "subcategory":"Household Appliances",
            "type":"Retail Goods"
        }
    ],
    "sg:phone":"+44 1206 547641",
    "sg:postcode":"CO1 1TN",
    "sg:province":"Essex",
    "sg:tags":[
        "electrical"
    ],
    "wof:name":"Ajax Domestic Spares Centre",
    "wof:placetype":"venue"
},
  "geometry": {"coordinates":[0.902561,51.889889],"type":"Point"}
}