{
  "type": "Feature",
  "properties": {
    "addr:full":"Station Road Carmarthen Carmarthenshire SA33 4DG",
    "addr:postcode":"sa33 4dg",
    "addr:street":"Station Road",
    "iso:country":"GB",
    "sg:address":"Station Road",
    "sg:city":"Carmarthen",
    "sg:classifiers":[
        {
            "category":"Food & Beverages",
            "subcategory":"Fruits & Vegetables",
            "type":"Retail Goods"
        }
    ],
    "sg:phone":"+44 1994 231350",
    "sg:postcode":"SA33 4DG",
    "sg:province":"Carmarthenshire",
    "sg:tags":[
        "greengrocer"
    ],
    "wof:name":"Happy Shopper Markets",
    "wof:placetype":"venue"
},
  "geometry": {"coordinates":[-4.4924111366,51.8257598877],"type":"Point"}
}