{
  "type": "Feature",
  "properties": {
    "addr:full":"4 Buckfast Rd, Hollin Manchester Greater Manchester M24 6HN",
    "addr:housenumber":"4",
    "addr:postcode":"m24 6hn",
    "addr:street":"Buckfast Rd",
    "iso:country":"GB",
    "sg:address":"4 Buckfast Rd, Hollin",
    "sg:city":"Manchester",
    "sg:classifiers":[
        {
            "category":"Shopping",
            "subcategory":"Party Supplies",
            "type":"Retail Goods"
        }
    ],
    "sg:phone":"+44 161 653 3205",
    "sg:postcode":"M24 6HN",
    "sg:province":"Greater Manchester",
    "sg:tags":[
        "inflatables",
        "bouncy",
        "castle"
    ],
    "wof:name":"Bounce Away",
    "wof:placetype":"venue"
},
  "geometry": {"coordinates":[-2.2022049427,53.5636825562],"type":"Point"}
}