{
  "type": "Feature",
  "properties": {
    "addr:full":"Four Acres, Old Mill La Uxbridge Buckinghamshire UB8 2JH",
    "addr:housenumber":"old",
    "addr:postcode":"ub8 2jh",
    "addr:street":"La Uxbridge",
    "iso:country":"GB",
    "sg:address":"Four Acres, Old Mill La",
    "sg:city":"Uxbridge",
    "sg:classifiers":[
        {
            "category":"Retail",
            "subcategory":"Auto Repair",
            "type":"Services"
        }
    ],
    "sg:postcode":"UB8 2JH",
    "sg:province":"Buckinghamshire",
    "sg:tags":[
        "modification",
        "garage"
    ],
    "wof:name":"Philips,A J,",
    "wof:placetype":"venue"
},
  "geometry": {"coordinates":[-0.474536,51.544071],"type":"Point"}
}