{
  "type": "Feature",
  "properties": {
    "addr:full":"Cliton House, 12 Lombard Street Newark Nottinghamshire NG24 1XB",
    "addr:housenumber":"12",
    "addr:postcode":"ng24 1xb",
    "addr:street":"Lombard Street",
    "iso:country":"GB",
    "sg:address":"Cliton House, 12 Lombard Street",
    "sg:city":"Newark",
    "sg:classifiers":[
        {
            "category":"Insurance",
            "subcategory":"Insurance Agent",
            "type":"Services"
        }
    ],
    "sg:phone":"+44 1636 707606",
    "sg:postcode":"NG24 1XB",
    "sg:province":"Nottinghamshire",
    "sg:tags":[
        "broker"
    ],
    "wof:name":"Noble Marine Insurance Brokers Ltd",
    "wof:placetype":"venue"
},
  "geometry": {"coordinates":[-0.8097090125,53.0746879578],"type":"Point"}
}