{
  "type": "Feature",
  "properties": {
    "addr:full":"83-93 Stonebridge Lane, Croxteth Liverpool Merseyside L11 4SJ",
    "addr:housenumber":"83-93",
    "addr:postcode":"l11 4sj",
    "addr:street":"Stonebridge Lane",
    "iso:country":"GB",
    "sg:address":"83-93 Stonebridge Lane, Croxteth",
    "sg:city":"Liverpool",
    "sg:classifiers":[
        {
            "category":"Organizations",
            "subcategory":"Non-profit Organization",
            "type":"Services"
        }
    ],
    "sg:phone":"+44 151 546 1141",
    "sg:postcode":"L11 4SJ",
    "sg:province":"Merseyside",
    "sg:tags":[
        "charitable",
        "organisation",
        "voluntary",
        "charity"
    ],
    "wof:name":"S H A D O",
    "wof:placetype":"venue"
},
  "geometry": {"coordinates":[-2.9032580853,53.4519233704],"type":"Point"}
}