{
  "type": "Feature",
  "properties": {
    "iso:country":"GB",
    "sg:address":"Kingston Smith & Partners, 105 Saint Peters Street",
    "sg:city":"St Albans",
    "sg:classifiers":[
        {
            "category":"Home & Garden",
            "subcategory":"Home Furnishings",
            "type":"Retail Goods"
        }
    ],
    "sg:postcode":"AL1 3EJ",
    "sg:province":"Hertfordshire",
    "sg:tags":[
        "pipe",
        "fitting"
    ],
    "wof:name":"Valmorr International Ltd",
    "wof:placetype":"venue"
},
  "geometry": {"coordinates":[-0.335563,51.755974],"type":"Point"}
}