{
  "type": "Feature",
  "properties": {
    "addr:full":"The Studio 17 Lincoln Rd London Greater London N2 9DJ",
    "addr:housenumber":"17",
    "addr:postcode":"n2 9dj",
    "addr:street":"Lincoln Rd",
    "iso:country":"GB",
    "sg:address":"The Studio 17 Lincoln Rd",
    "sg:city":"London",
    "sg:classifiers":[
        {
            "category":"Home & Garden",
            "subcategory":"Carpets & Floor Coverings",
            "type":"Retail Goods"
        }
    ],
    "sg:postcode":"N2 9DJ",
    "sg:province":"Greater London",
    "sg:tags":[
        "carpets",
        "rug",
        "matting"
    ],
    "wof:name":"Essential Flooring Co Ltd (The)",
    "wof:placetype":"venue"
},
  "geometry": {"coordinates":[-0.1634099931,51.5903015137],"type":"Point"}
}