{
  "type": "Feature",
  "properties": {
    "addr:full":"95 Holborn St Aberdeen Aberdeen City AB106BQ",
    "addr:housenumber":"95",
    "addr:postcode":"ab106bq",
    "addr:street":"Holborn St",
    "iso:country":"GB",
    "sg:address":"95 Holborn St",
    "sg:city":"Aberdeen",
    "sg:classifiers":[
        {
            "category":"Autos & Motor Vehicles",
            "subcategory":"Auto Supplies",
            "type":"Retail Goods"
        }
    ],
    "sg:postcode":"AB106BQ",
    "sg:province":"Aberdeen City",
    "sg:tags":[
        "windscreen"
    ],
    "wof:name":"Heywood Williams Automotive Ltd",
    "wof:placetype":"venue"
},
  "geometry": {"coordinates":[-2.113248,57.140469],"type":"Point"}
}