{
  "type": "Feature",
  "properties": {
    "addr:full":"St. Ives Rd Huntingdon Cambridgeshire PE17 3ER",
    "addr:postcode":"pe17 3er",
    "addr:street":"St. Ives Rd",
    "iso:country":"GB",
    "sg:address":"St. Ives Rd",
    "sg:city":"Huntingdon",
    "sg:classifiers":[
        {
            "category":"Retail",
            "subcategory":"Driving School",
            "type":"Services"
        }
    ],
    "sg:phone":"+44 1487 840446",
    "sg:postcode":"PE17 3ER",
    "sg:province":"Cambridgeshire",
    "wof:name":"Haynes School of Motoring",
    "wof:placetype":"venue"
},
  "geometry": {"coordinates":[-0.0964180008,52.3187103271],"type":"Point"}
}