{
  "type": "Feature",
  "properties": {
    "iso:country":"GB",
    "sg:address":"4 South Terrace, Cornsay Colliery",
    "sg:city":"Durham",
    "sg:classifiers":[
        {
            "category":"Building & Trades",
            "subcategory":"Construction",
            "type":"Services"
        }
    ],
    "sg:phone":"+44 191 373 4338",
    "sg:postcode":"DH7 9ED",
    "sg:province":"Durham",
    "sg:tags":[
        "dry",
        "lining",
        "plasterers",
        "screeders"
    ],
    "wof:name":"McKenna (Plasterers) Ltd.",
    "wof:placetype":"venue"
},
  "geometry": {"coordinates":[-1.699361,54.772755],"type":"Point"}
}