{
  "type": "Feature",
  "properties": {
    "iso:country":"GB",
    "sg:address":"83 Prospect Avenue, Seaton Delaval",
    "sg:city":"Whitley Bay",
    "sg:classifiers":[
        {
            "category":"Retail",
            "subcategory":"Photofinishing",
            "type":"Services"
        }
    ],
    "sg:postcode":"NE25 0EQ",
    "sg:province":"Northumberland",
    "sg:tags":[
        "photographic",
        "processor"
    ],
    "wof:name":"Photoprint",
    "wof:placetype":"venue"
},
  "geometry": {"coordinates":[-1.531116,55.069366],"type":"Point"}
}