{
  "type": "Feature",
  "properties": {
    "iso:country":"GB",
    "sg:address":"St James Place, Otley Road, Baildon",
    "sg:city":"Shipley",
    "sg:classifiers":[
        {
            "category":"Professional",
            "subcategory":"Art Services",
            "type":"Services"
        }
    ],
    "sg:phone":"+44 1274 581142",
    "sg:postcode":"BD17 7LD",
    "sg:province":"West Yorkshire",
    "sg:tags":[
        "picture",
        "framing"
    ],
    "wof:name":"Park Lane Studio",
    "wof:placetype":"venue"
},
  "geometry": {"coordinates":[-1.747372,53.851307],"type":"Point"}
}