{
  "type": "Feature",
  "properties": {
    "addr:full":"86 Miller Street Manchester Greater Manchester M4 4DY",
    "addr:housenumber":"86",
    "addr:postcode":"m4 4dy",
    "addr:street":"Miller Street",
    "iso:country":"GB",
    "sg:address":"86 Miller Street",
    "sg:city":"Manchester",
    "sg:classifiers":[
        {
            "category":"Professional",
            "subcategory":"Art Services",
            "type":"Services"
        }
    ],
    "sg:postcode":"M4 4DY",
    "sg:province":"Greater Manchester",
    "sg:tags":[
        "framing"
    ],
    "wof:name":"Northern Framing Co. Ltd.",
    "wof:placetype":"venue"
},
  "geometry": {"coordinates":[-2.2395579815,53.4877586365],"type":"Point"}
}