{
  "type": "Feature",
  "properties": {
    "addr:full":"501a Prescot Road, Old Swan Liverpool Merseyside L13 3BU",
    "addr:housenumber":"501a",
    "addr:postcode":"l13 3bu",
    "addr:street":"Prescot Road",
    "iso:country":"GB",
    "sg:address":"501a Prescot Road, Old Swan",
    "sg:city":"Liverpool",
    "sg:classifiers":[
        {
            "category":"Professional",
            "subcategory":"Lawyer & Legal Services",
            "type":"Services"
        }
    ],
    "sg:phone":"+44 151 282 2828",
    "sg:postcode":"L13 3BU",
    "sg:province":"Merseyside",
    "sg:tags":[
        "solicitor"
    ],
    "wof:name":"Liffey Court Management Co. Ltd.",
    "wof:placetype":"venue"
},
  "geometry": {"coordinates":[-2.9151580334,53.4141960144],"type":"Point"}
}