{
  "type": "Feature",
  "properties": {
    "addr:full":"83 Widemarsh Street Hereford Herefordshire HR4 9EU",
    "addr:housenumber":"83",
    "addr:postcode":"hr4 9eu",
    "addr:street":"Widemarsh Street",
    "iso:country":"GB",
    "sg:address":"83 Widemarsh Street",
    "sg:city":"Hereford",
    "sg:classifiers":[
        {
            "category":"Retail",
            "subcategory":"Repair Shop",
            "type":"Services"
        }
    ],
    "sg:phone":"+44 1432 271044",
    "sg:postcode":"HR4 9EU",
    "sg:province":"Herefordshire",
    "sg:tags":[
        "clocks",
        "watch",
        "sale",
        "clock"
    ],
    "wof:name":"M Goddard",
    "wof:placetype":"venue"
},
  "geometry": {"coordinates":[-2.7153589725,52.0592155457],"type":"Point"}
}