{
  "type": "Feature",
  "properties": {
    "addr:full":"Douglas Mews, Postling Hythe Kent CT21 4ET",
    "addr:postcode":"ct21 4et",
    "addr:street":"Douglas;Postling",
    "iso:country":"GB",
    "sg:address":"Douglas Mews, Postling",
    "sg:city":"Hythe",
    "sg:classifiers":[
        {
            "category":"Professional",
            "subcategory":"Art Services",
            "type":"Services"
        }
    ],
    "sg:postcode":"CT21 4ET",
    "sg:province":"Kent",
    "sg:tags":[
        "consultant",
        "design"
    ],
    "wof:name":"Rutt,Philip,",
    "wof:placetype":"venue"
},
  "geometry": {"coordinates":[1.064161,51.110134],"type":"Point"}
}