{
  "type": "Feature",
  "properties": {
    "addr:full":"Suite 23 Thatcham House Station, Road Thatcham Berkshire RG19 4QD",
    "addr:postcode":"rg19 4qd",
    "addr:street":"Suite 23 Thatcham;Station Road",
    "iso:country":"GB",
    "sg:address":"Suite 23 Thatcham House Station, Road",
    "sg:city":"Thatcham",
    "sg:classifiers":[
        {
            "category":"Professional",
            "subcategory":"Engineering",
            "type":"Services"
        }
    ],
    "sg:phone":"+44 1635 873733",
    "sg:postcode":"RG19 4QD",
    "sg:province":"Berkshire",
    "sg:tags":[
        "civil",
        "engineer"
    ],
    "wof:name":"Van Elle Underpinning Ltd.",
    "wof:placetype":"venue"
},
  "geometry": {"coordinates":[-1.2548010349,51.4015274048],"type":"Point"}
}