{
  "type": "Feature",
  "properties": {
    "addr:full":"Station Road Indstl Est, Old Station Rd, Luddenden Foot Halifax West Yorkshire HX2 6AD",
    "addr:postcode":"hx2 6ad",
    "addr:street":"Station Road Indstl Est Old Station Rd",
    "iso:country":"GB",
    "sg:address":"Station Road Indstl Est, Old Station Rd, Luddenden Foot",
    "sg:city":"Halifax",
    "sg:classifiers":[
        {
            "category":"Freight",
            "type":"Transportation"
        }
    ],
    "sg:postcode":"HX2 6AD",
    "sg:province":"West Yorkshire",
    "sg:tags":[
        "haulage",
        "road"
    ],
    "wof:name":"Midgley,Richard A,",
    "wof:placetype":"venue"
},
  "geometry": {"coordinates":[-1.9455239773,53.7219352722],"type":"Point"}
}