{
  "type": "Feature",
  "properties": {
    "addr:full":"The Briary, Reading Road North Fleet Hampshire GU51 4AG",
    "addr:postcode":"gu51 4ag",
    "addr:street":"Reading Road North",
    "iso:country":"GB",
    "sg:address":"The Briary, Reading Road North",
    "sg:city":"Fleet",
    "sg:classifiers":[
        {
            "category":"Health Services",
            "subcategory":"Nursing And Care Facility",
            "type":"Services"
        }
    ],
    "sg:phone":"+44 1252 614583",
    "sg:postcode":"GU51 4AG",
    "sg:province":"Hampshire",
    "sg:tags":[
        "home"
    ],
    "wof:name":"Briary Nursing & Residential Home",
    "wof:placetype":"venue"
},
  "geometry": {"coordinates":[-0.855459,51.283974],"type":"Point"}
}