{
  "type": "Feature",
  "properties": {
    "iso:country":"GB",
    "sg:address":"3 Broad Street, Hay On Wye",
    "sg:city":"Hereford",
    "sg:classifiers":[
        {
            "category":"Community Center",
            "subcategory":"Youth",
            "type":"Public Place"
        }
    ],
    "sg:postcode":"HR3 5DB",
    "sg:province":"Herefordshire",
    "sg:tags":[
        "forestry",
        "consultant"
    ],
    "wof:name":"Graham Sinclair",
    "wof:placetype":"venue"
},
  "geometry": {"coordinates":[-3.125557,52.075855],"type":"Point"}
}