{
  "type": "Feature",
  "properties": {
    "addr:full":"87 Newark Road, North Hykeham Lincoln Lincolnshire LN6 8RA",
    "addr:housenumber":"87",
    "addr:postcode":"ln6 8ra",
    "addr:street":"Newark Road North",
    "iso:country":"GB",
    "sg:address":"87 Newark Road, North Hykeham",
    "sg:city":"Lincoln",
    "sg:classifiers":[
        {
            "category":"Freight",
            "type":"Transportation"
        },
        {
            "category":"Professional",
            "subcategory":"Business Services",
            "type":"Services"
        }
    ],
    "sg:phone":"+44 1522 691286",
    "sg:postcode":"LN6 8RA",
    "sg:province":"Lincolnshire",
    "sg:tags":[
        "haulage",
        "road",
        "courier"
    ],
    "wof:name":"Winthorpe Special Deliveries",
    "wof:placetype":"venue"
},
  "geometry": {"coordinates":[-0.58508,53.193001],"type":"Point"}
}