{
  "type": "Feature",
  "properties": {
    "addr:full":"186-188 Hilldene Avenue Romford Essex RM3 8DB",
    "addr:postcode":"186-188;rm3 8db",
    "addr:street":"Hilldene Avenue",
    "iso:country":"GB",
    "sg:address":"186-188 Hilldene Avenue",
    "sg:city":"Romford",
    "sg:classifiers":[
        {
            "category":"Shopping",
            "subcategory":"Pharmacy",
            "type":"Retail Goods"
        }
    ],
    "sg:phone":"+44 1708 346634",
    "sg:postcode":"RM3 8DB",
    "sg:province":"Essex",
    "sg:tags":[
        "pharmacist",
        "chemist"
    ],
    "wof:name":"Wavemill Ltd.",
    "wof:placetype":"venue"
},
  "geometry": {"coordinates":[0.2188069969,51.6074371338],"type":"Point"}
}