{
  "type": "Feature",
  "properties": {
    "iso:country":"GB",
    "sg:address":"Units 3-4 St Andrews Business C, Tr, High Glencairn Street",
    "sg:city":"Kilmarnock",
    "sg:classifiers":[
        {
            "category":"Sports & Exercise",
            "subcategory":"Gym",
            "type":"Entertainment"
        }
    ],
    "sg:phone":"+44 1563 573345",
    "sg:postcode":"KA1 4AD",
    "sg:province":"East Ayrshire",
    "sg:tags":[
        "club",
        "fitness",
        "health",
        "centre"
    ],
    "wof:name":"Callenetics Kilmarnock",
    "wof:placetype":"venue"
},
  "geometry": {"coordinates":[-4.50973,55.608894],"type":"Point"}
}