{
  "type": "Feature",
  "properties": {
    "addr:full":"Units 3-4 St Andrews Business C, Tr, High Glencairn Street Kilmarnock East Ayrshire KA1 4AD",
    "addr:housenumber":"units 3-4",
    "addr:postcode":"ka1 4ad",
    "addr:street":"St Andrews;C Tr High Glencairn Street",
    "iso:country":"GB",
    "sg:address":"Units 3-4 St Andrews Business C, Tr, High Glencairn Street",
    "sg:city":"Kilmarnock",
    "sg:classifiers":[
        {
            "category":"Sports & Exercise",
            "subcategory":"Gym",
            "type":"Entertainment"
        }
    ],
    "sg:phone":"+44 1563 573345",
    "sg:postcode":"KA1 4AD",
    "sg:province":"East Ayrshire",
    "sg:tags":[
        "club",
        "fitness",
        "health",
        "centre"
    ],
    "wof:name":"Callenetics Kilmarnock",
    "wof:placetype":"venue"
},
  "geometry": {"coordinates":[-4.50973,55.608894],"type":"Point"}
}