{
  "type": "Feature",
  "properties": {
    "iso:country":"GB",
    "sg:address":"Poulton Close Industrial Estate",
    "sg:city":"Dover",
    "sg:classifiers":[
        {
            "category":"Autos & Motor Vehicles",
            "subcategory":"Auto Supplies",
            "type":"Retail Goods"
        },
        {
            "category":"Retail",
            "subcategory":"Auto Repair",
            "type":"Services"
        }
    ],
    "sg:postcode":"CT17 0HL",
    "sg:province":"Kent",
    "sg:tags":[
        "modification",
        "exhaust",
        "absorber",
        "shock",
        "garage"
    ],
    "wof:name":"Poulton Service & Exhaust Centre",
    "wof:placetype":"venue"
},
  "geometry": {"coordinates":[1.284353,51.130348],"type":"Point"}
}