{
  "type": "Feature",
  "properties": {
    "iso:country":"GB",
    "sg:address":"Southdown Indust Est, Southdown Rd",
    "sg:city":"Harpenden",
    "sg:classifiers":[
        {
            "category":"Professional",
            "subcategory":"Engineering",
            "type":"Services"
        }
    ],
    "sg:postcode":"AL5 1PW",
    "sg:province":"Hertfordshire",
    "sg:tags":[
        "precision",
        "engineer"
    ],
    "wof:name":"C T Precision",
    "wof:placetype":"venue"
},
  "geometry": {"coordinates":[-0.354224,51.814095],"type":"Point"}
}