{
  "type": "Feature",
  "properties": {
    "addr:full":"St Philips Causeway, Bath Road, Arnos Vale Bristol City of Bristol BS4 3BD",
    "addr:postcode":"bs4 3bd",
    "addr:street":"St;Causeway Bath Road",
    "iso:country":"GB",
    "sg:address":"St Philips Causeway, Bath Road, Arnos Vale",
    "sg:city":"Bristol",
    "sg:classifiers":[
        {
            "category":"Fast Food",
            "type":"Food & Drink"
        }
    ],
    "sg:phone":"+44 117 977 0791",
    "sg:postcode":"BS4 3BD",
    "sg:province":"City of Bristol",
    "sg:tags":[
        "away",
        "take"
    ],
    "wof:name":"Burger King",
    "wof:placetype":"venue"
},
  "geometry": {"coordinates":[-2.559769,51.444981],"type":"Point"}
}