{
  "type": "Feature",
  "properties": {
    "addr:full":"55 Neal Street London Greater London WC2H 9PJ",
    "addr:housenumber":"55",
    "addr:postcode":"wc2h 9pj",
    "addr:street":"Neal Street",
    "iso:country":"GB",
    "sg:address":"55 Neal Street",
    "sg:city":"London",
    "sg:classifiers":[
        {
            "category":"Shopping",
            "subcategory":"Beauty & Cosmetics",
            "type":"Retail Goods"
        }
    ],
    "sg:phone":"+44 20 7836 5588",
    "sg:postcode":"WC2H 9PJ",
    "sg:province":"Greater London",
    "sg:tags":[
        "product"
    ],
    "wof:name":"Shu Uemura Head Office",
    "wof:placetype":"venue"
},
  "geometry": {"coordinates":[-0.1264120042,51.5146980286],"type":"Point"}
}