{
  "type": "Feature",
  "properties": {
    "addr:full":"1330 High Road, Whetstone London Greater London N20 9DU",
    "addr:housenumber":"1330",
    "addr:postcode":"n20 9du",
    "addr:street":"High Road",
    "iso:country":"GB",
    "sg:address":"1330 High Road, Whetstone",
    "sg:city":"London",
    "sg:classifiers":[
        {
            "category":"Retail",
            "subcategory":"Laundry & Dry Cleaning",
            "type":"Services"
        }
    ],
    "sg:phone":"+44 20 8445 2022",
    "sg:postcode":"N20 9DU",
    "sg:province":"Greater London",
    "sg:tags":[
        "alteration"
    ],
    "wof:name":"Toffs Dry Cleaners",
    "wof:placetype":"venue"
},
  "geometry": {"coordinates":[-0.175507,51.631538],"type":"Point"}
}