{
  "type": "Feature",
  "properties": {
    "iso:country":"GB",
    "sg:address":"8 Dorset Road, Tottenham",
    "sg:city":"London",
    "sg:classifiers":[
        {
            "category":"Professional",
            "subcategory":"Engineering",
            "type":"Services"
        },
        {
            "category":"Shopping",
            "subcategory":"Photographic Equipment",
            "type":"Retail Goods"
        }
    ],
    "sg:phone":"+44 1483 740099",
    "sg:postcode":"N15 5AJ",
    "sg:province":"Greater London",
    "sg:tags":[
        "engineer",
        "mechanical"
    ],
    "wof:name":"Climpex Ltd.",
    "wof:placetype":"venue"
},
  "geometry": {"coordinates":[-0.083454,51.58585],"type":"Point"}
}