{
  "type": "Feature",
  "properties": {
    "iso:country":"GB",
    "sg:address":"Warrington Road, Bold Heath",
    "sg:city":"Widnes",
    "sg:classifiers":[
        {
            "category":"Sports & Exercise",
            "subcategory":"Golf",
            "type":"Entertainment"
        }
    ],
    "sg:phone":"+44 151 424 6060",
    "sg:postcode":"WA8 3XL",
    "sg:province":"Cheshire",
    "sg:tags":[
        "club",
        "course"
    ],
    "wof:name":"Greenfinch Openair Leisure Facilities Ltd.",
    "wof:placetype":"venue"
},
  "geometry": {"coordinates":[-2.711695,53.398022],"type":"Point"}
}