{
  "type": "Feature",
  "properties": {
    "iso:country":"GB",
    "sg:address":"9 Lonsdale Road, Rackheath",
    "sg:city":"Norwich",
    "sg:classifiers":[
        {
            "category":"Professional",
            "subcategory":"Engineering",
            "type":"Services"
        },
        {
            "category":"Building & Trades",
            "subcategory":"Electrical",
            "type":"Services"
        }
    ],
    "sg:phone":"+44 1603 720928",
    "sg:postcode":"NR13 6QW",
    "sg:province":"Norfolk",
    "sg:tags":[
        "engineer",
        "electrician",
        "contractor"
    ],
    "wof:name":"DENNIS FREW",
    "wof:placetype":"venue"
},
  "geometry": {"coordinates":[1.3816879988,52.6624412537],"type":"Point"}
}