{
  "type": "Feature",
  "properties": {
    "addr:full":"Shute Road Catterick Garrison North Yorkshire DL9 4AF",
    "addr:postcode":"dl9 4af",
    "addr:street":"Shute Road",
    "iso:country":"GB",
    "sg:address":"Shute Road",
    "sg:city":"Catterick Garrison",
    "sg:classifiers":[
        {
            "category":"Bars & Pubs",
            "type":"Food & Drink"
        }
    ],
    "sg:phone":"+44 1748 836232",
    "sg:postcode":"DL9 4AF",
    "sg:province":"North Yorkshire",
    "sg:tags":[
        "pubs",
        "inn"
    ],
    "wof:name":"Harry's",
    "wof:placetype":"venue"
},
  "geometry": {"coordinates":[-1.721237,54.377403],"type":"Point"}
}