{
  "type": "Feature",
  "properties": {
    "addr:full":"Bank Street Irvine North Ayrshire KA12 0NE",
    "addr:postcode":"ka12 0ne",
    "addr:street":"Bank Street",
    "iso:country":"GB",
    "sg:address":"Bank Street",
    "sg:city":"Irvine",
    "sg:classifiers":[
        {
            "category":"Education",
            "subcategory":"School",
            "type":"Public Place"
        }
    ],
    "sg:phone":"+44 1294 272481",
    "sg:postcode":"KA12 0NE",
    "sg:province":"North Ayrshire",
    "sg:tags":[
        "local",
        "authority"
    ],
    "wof:name":"Haysholm School",
    "wof:placetype":"venue"
},
  "geometry": {"coordinates":[-4.6455821991,55.6250534058],"type":"Point"}
}