{
  "type": "Feature",
  "properties": {
    "addr:full":"80 Cricklewood Broadway London Greater London NW2 3EP",
    "addr:housenumber":"80",
    "addr:postcode":"nw2 3ep",
    "addr:street":"Cricklewood Broadway",
    "iso:country":"GB",
    "sg:address":"80 Cricklewood Broadway",
    "sg:city":"London",
    "sg:classifiers":[
        {
            "category":"Communications",
            "type":"Services"
        }
    ],
    "sg:postcode":"NW2 3EP",
    "sg:province":"Greater London",
    "sg:tags":[
        "tv",
        "video",
        "radio"
    ],
    "wof:name":"Beach Electronics",
    "wof:placetype":"venue"
},
  "geometry": {"coordinates":[-0.208962,51.551697],"type":"Point"}
}