{
  "type": "Feature",
  "properties": {
    "iso:country":"GB",
    "sg:address":"Ingoldmells Road, Burgh Le Marsh",
    "sg:city":"Skegness",
    "sg:classifiers":[
        {
            "category":"Manufacturing",
            "subcategory":"Buildings",
            "type":"Manufacturing & Wholesale Goods"
        }
    ],
    "sg:phone":"+44 1754 810385",
    "sg:postcode":"PE24 5HE",
    "sg:province":"Lincolnshire",
    "sg:tags":[
        "mobile",
        "home"
    ],
    "wof:name":"Windmill Caravan Park",
    "wof:placetype":"venue"
},
  "geometry": {"coordinates":[0.242941007,53.1613540649],"type":"Point"}
}