{
  "type": "Feature",
  "properties": {
    "addr:full":"New Abbey House Andover Hampshire SP11 8DN",
    "addr:postcode":"sp11 8dn",
    "iso:country":"GB",
    "sg:address":"New Abbey House",
    "sg:city":"Andover",
    "sg:classifiers":[
        {
            "category":"Food & Beverages",
            "subcategory":"Liquor & Beverages",
            "type":"Retail Goods"
        }
    ],
    "sg:phone":"+44 1264 774700",
    "sg:postcode":"SP11 8DN",
    "sg:province":"Hampshire",
    "sg:tags":[
        "beer",
        "spirit",
        "wines"
    ],
    "wof:name":"J Chandler & Co. (Buckfast) Ltd.",
    "wof:placetype":"venue"
},
  "geometry": {"coordinates":[-1.587732,51.20718],"type":"Point"}
}