{
  "type": "Feature",
  "properties": {
    "addr:full":"11 Crompton Road Lowestoft Suffolk NR33 9NG",
    "addr:housenumber":"11",
    "addr:postcode":"nr33 9ng",
    "addr:street":"Crompton Road",
    "iso:country":"GB",
    "sg:address":"11 Crompton Road",
    "sg:city":"Lowestoft",
    "sg:classifiers":[
        {
            "category":"Health Services",
            "subcategory":"Health Practitioner",
            "type":"Services"
        }
    ],
    "sg:postcode":"NR33 9NG",
    "sg:province":"Suffolk",
    "sg:tags":[
        "hypnotherapists"
    ],
    "wof:name":"Roz Fotherby",
    "wof:placetype":"venue"
},
  "geometry": {"coordinates":[1.714936,52.472298],"type":"Point"}
}