{
  "type": "Feature",
  "properties": {
    "addr:full":"Gull Bank, Whaplode Drove Spalding Cambridgeshire PE12 0SS",
    "addr:postcode":"pe12 0ss",
    "addr:street":"Whaplode Drove Spalding",
    "iso:country":"GB",
    "sg:address":"Gull Bank, Whaplode Drove",
    "sg:city":"Spalding",
    "sg:classifiers":[
        {
            "category":"Home & Garden",
            "subcategory":"Garden Supply",
            "type":"Retail Goods"
        }
    ],
    "sg:phone":"+44 1406 330077",
    "sg:postcode":"PE12 0SS",
    "sg:province":"Cambridgeshire",
    "sg:tags":[
        "nursery",
        "centre"
    ],
    "wof:name":"Sunningdale Nurseries",
    "wof:placetype":"venue"
},
  "geometry": {"coordinates":[-0.0640499964,52.7146072388],"type":"Point"}
}