{
  "type": "Feature",
  "properties": {
    "addr:full":"16-18 Upland Road, Dulwich London Greater London SE22 9GG",
    "addr:housenumber":"16-18",
    "addr:postcode":"se22 9gg",
    "addr:street":"Upland Road",
    "iso:country":"GB",
    "sg:address":"16-18 Upland Road, Dulwich",
    "sg:city":"London",
    "sg:classifiers":[
        {
            "category":"Professional",
            "subcategory":"Detective & Security Services",
            "type":"Services"
        }
    ],
    "sg:postcode":"SE22 9GG",
    "sg:province":"Greater London",
    "wof:name":"Independent Security Contracts Ltd",
    "wof:placetype":"venue"
},
  "geometry": {"coordinates":[-0.069619,51.45718],"type":"Point"}
}