{
  "type": "Feature",
  "properties": {
    "addr:full":"139 Earlham Road Norwich Norfolk NR2 3RG",
    "addr:housenumber":"139",
    "addr:postcode":"nr2 3rg",
    "addr:street":"Earlham Road Norwich Norfolk",
    "iso:country":"GB",
    "sg:address":"139 Earlham Road",
    "sg:city":"Norwich",
    "sg:classifiers":[
        {
            "category":"Travel",
            "subcategory":"Hotels & Motels",
            "type":"Entertainment"
        }
    ],
    "sg:phone":"+44 1603 451410",
    "sg:postcode":"NR2 3RG",
    "sg:province":"Norfolk",
    "sg:tags":[
        "house",
        "guest"
    ],
    "wof:name":"Fuchsia Guest House",
    "wof:placetype":"venue"
},
  "geometry": {"coordinates":[1.2707699537,52.6299324036],"type":"Point"}
}