{
  "type": "Feature",
  "properties": {
    "iso:country":"GB",
    "sg:address":"1 Amos Road",
    "sg:city":"Leicester",
    "sg:classifiers":[
        {
            "category":"Retail",
            "subcategory":"Auto Repair",
            "type":"Services"
        }
    ],
    "sg:postcode":"LE3 6NA",
    "sg:province":"Leicestershire",
    "sg:tags":[
        "modification",
        "garage"
    ],
    "wof:name":"Numark Garage",
    "wof:placetype":"venue"
},
  "geometry": {"coordinates":[-1.19462,52.637062],"type":"Point"}
}