{
  "type": "Feature",
  "properties": {
    "addr:full":"4 Clarence Arcade Ashton-under-lyne Greater Manchester OL6 7PT",
    "addr:housenumber":"4;arcade",
    "addr:postcode":"ol6 7pt",
    "addr:street":"Clarence",
    "iso:country":"GB",
    "sg:address":"4 Clarence Arcade",
    "sg:city":"Ashton-under-lyne",
    "sg:classifiers":[
        {
            "category":"Real Estate",
            "subcategory":"Real Estate Agent",
            "type":"Services"
        }
    ],
    "sg:postcode":"OL6 7PT",
    "sg:province":"Greater Manchester",
    "wof:name":"W C Dawson & Son",
    "wof:placetype":"venue"
},
  "geometry": {"coordinates":[-2.0936388969,53.4872398376],"type":"Point"}
}