{
  "type": "Feature",
  "properties": {
    "iso:country":"GB",
    "sg:address":"Foxdown Farm, Marshwood",
    "sg:city":"Bridport",
    "sg:classifiers":[
        {
            "category":"Farming",
            "subcategory":"Livestock Farm",
            "type":"Manufacturing & Wholesale Goods"
        }
    ],
    "sg:phone":"+44 1297 678391",
    "sg:postcode":"DT6 5QB",
    "sg:province":"Dorset",
    "sg:tags":[
        "others"
    ],
    "wof:name":"JAMES P STRAWBRIDGE",
    "wof:placetype":"venue"
},
  "geometry": {"coordinates":[-2.8780488968,50.7931404114],"type":"Point"}
}