{
  "type": "Feature",
  "properties": {
    "addr:full":"226 Great Western Road Glasgow Glasgow City G4 9EJ",
    "addr:housenumber":"226",
    "addr:postcode":"g4 9ej",
    "addr:street":"Great Western Road",
    "iso:country":"GB",
    "sg:address":"226 Great Western Road",
    "sg:city":"Glasgow",
    "sg:classifiers":[
        {
            "category":"Bars & Pubs",
            "type":"Food & Drink"
        },
        {
            "category":"Community Center",
            "subcategory":"Social",
            "type":"Public Place"
        }
    ],
    "sg:phone":"+44 141 332 3532",
    "sg:postcode":"G4 9EJ",
    "sg:province":"Glasgow City",
    "sg:tags":[
        "pubs",
        "house",
        "inn",
        "activity"
    ],
    "wof:name":"Wintersgills Bar",
    "wof:placetype":"venue"
},
  "geometry": {"coordinates":[-4.2729930878,55.872718811],"type":"Point"}
}