{
  "type": "Feature",
  "properties": {
    "iso:country":"GB",
    "sg:address":"12 St Andrews Close, Long Stratton",
    "sg:city":"Norwich",
    "sg:classifiers":[
        {
            "category":"Farming",
            "subcategory":"Dairy Farm",
            "type":"Manufacturing & Wholesale Goods"
        }
    ],
    "sg:postcode":"NR15 2PN",
    "sg:province":"Norfolk",
    "wof:name":"Colindale Dairy",
    "wof:placetype":"venue"
},
  "geometry": {"coordinates":[1.234814,52.491184],"type":"Point"}
}