{
  "type": "Feature",
  "properties": {
    "iso:country":"GB",
    "sg:address":"Hemington House, Hemington",
    "sg:city":"Derby",
    "sg:classifiers":[
        {
            "category":"Sports & Exercise",
            "subcategory":"Stables",
            "type":"Entertainment"
        },
        {
            "category":"Farming",
            "subcategory":"Livestock Farm",
            "type":"Manufacturing & Wholesale Goods"
        }
    ],
    "sg:phone":"+44 1332 810243",
    "sg:postcode":"DE74 2RB",
    "sg:province":"Leicestershire",
    "sg:tags":[
        "equestrian",
        "centre",
        "livery",
        "others",
        "schools",
        "riding"
    ],
    "wof:name":"Messrs Radford & Collumbell",
    "wof:placetype":"venue"
},
  "geometry": {"coordinates":[-1.3276770115,52.843837738],"type":"Point"}
}