{
  "type": "Feature",
  "properties": {
    "addr:full":"6 Wall End Rd, East Ham London Greater London E6 2NR",
    "addr:housenumber":"6",
    "addr:postcode":"e6 2nr",
    "addr:street":"Wall End Rd",
    "iso:country":"GB",
    "sg:address":"6 Wall End Rd, East Ham",
    "sg:city":"London",
    "sg:classifiers":[
        {
            "category":"Professional",
            "subcategory":"Printing & Photocopies",
            "type":"Services"
        }
    ],
    "sg:postcode":"E6 2NR",
    "sg:province":"Greater London",
    "sg:tags":[
        "printer"
    ],
    "wof:name":"Kenley Press",
    "wof:placetype":"venue"
},
  "geometry": {"coordinates":[0.0626320019,51.5344467163],"type":"Point"}
}