{
  "type": "Feature",
  "properties": {
    "iso:country":"GB",
    "sg:address":"Stuart Rd",
    "sg:city":"Runcorn",
    "sg:classifiers":[
        {
            "category":"Professional",
            "subcategory":"Computer Services",
            "type":"Services"
        }
    ],
    "sg:phone":"+44 20 8327 5000",
    "sg:postcode":"WA7 1TH",
    "sg:province":"Cheshire",
    "sg:tags":[
        "system",
        "software"
    ],
    "wof:name":"Inmac",
    "wof:placetype":"venue"
},
  "geometry": {"coordinates":[-2.673124,53.350815],"type":"Point"}
}