{
  "type": "Feature",
  "properties": {
    "addr:full":"Bishopsdown Farm, Dundridge Lane, Bishops Waltham Southampton Hampshire SO32 1GD",
    "addr:postcode":"so32 1gd",
    "addr:street":"Dundridge Lane",
    "iso:country":"GB",
    "sg:address":"Bishopsdown Farm, Dundridge Lane, Bishops Waltham",
    "sg:city":"Southampton",
    "sg:classifiers":[
        {
            "category":"Farming",
            "subcategory":"Livestock Farm",
            "type":"Manufacturing & Wholesale Goods"
        }
    ],
    "sg:postcode":"SO32 1GD",
    "sg:province":"Hampshire",
    "sg:tags":[
        "stud"
    ],
    "wof:name":"Bishopsdown Farm",
    "wof:placetype":"venue"
},
  "geometry": {"coordinates":[-1.2120419741,50.9547996521],"type":"Point"}
}