{
  "type": "Feature",
  "properties": {
    "addr:full":"22 High Street Congleton Cheshire CW12 1BD",
    "addr:housenumber":"22",
    "addr:postcode":"cw12 1bd",
    "addr:street":"High Street",
    "iso:country":"GB",
    "sg:address":"22 High Street",
    "sg:city":"Congleton",
    "sg:classifiers":[
        {
            "category":"Bars & Pubs",
            "type":"Food & Drink"
        }
    ],
    "sg:phone":"+44 1260 272702",
    "sg:postcode":"CW12 1BD",
    "sg:province":"Cheshire",
    "sg:tags":[
        "pubs",
        "house",
        "inn",
        "public",
        "activity"
    ],
    "wof:name":"Ye Olde White Lion Ltd",
    "wof:placetype":"venue"
},
  "geometry": {"coordinates":[-2.2111809254,53.1627578735],"type":"Point"}
}