{
  "type": "Feature",
  "properties": {
    "addr:full":"Ridge House, Beech Hill Rd Ascot Berkshire SL5 0BN",
    "addr:postcode":"sl5 0bn",
    "addr:street":"Beech Hill Rd",
    "iso:country":"GB",
    "sg:address":"Ridge House, Beech Hill Rd",
    "sg:city":"Ascot",
    "sg:classifiers":[
        {
            "category":"Professional",
            "subcategory":"Advertising",
            "type":"Services"
        }
    ],
    "sg:phone":"+44 1344 874847",
    "sg:postcode":"SL5 0BN",
    "sg:province":"Berkshire",
    "sg:tags":[
        "agency"
    ],
    "wof:name":"Graham Hockman Associates",
    "wof:placetype":"venue"
},
  "geometry": {"coordinates":[-0.642657,51.396736],"type":"Point"}
}