{
  "type": "Feature",
  "properties": {
    "iso:country":"GB",
    "sg:address":"5 Clifton Villas",
    "sg:city":"Bradford",
    "sg:classifiers":[
        {
            "category":"Organizations",
            "subcategory":"Community Association",
            "type":"Services"
        },
        {
            "category":"Organizations",
            "subcategory":"Membership Organization",
            "type":"Services"
        }
    ],
    "sg:phone":"+44 1274 546235",
    "sg:postcode":"BD8 7BY",
    "sg:province":"West Yorkshire",
    "sg:tags":[
        "club",
        "social"
    ],
    "wof:name":"Latvian Welfare Fund & Club",
    "wof:placetype":"venue"
},
  "geometry": {"coordinates":[-1.76324296,53.8062553406],"type":"Point"}
}