{
  "type": "Feature",
  "properties": {
    "iso:country":"GB",
    "sg:address":"150 Hunts Cross Ave",
    "sg:city":"Liverpool",
    "sg:classifiers":[
        {
            "category":"Farming",
            "subcategory":"Livestock Farm",
            "type":"Manufacturing & Wholesale Goods"
        }
    ],
    "sg:postcode":"L25 8SQ",
    "sg:province":"Merseyside",
    "sg:tags":[
        "breeder"
    ],
    "wof:name":"Blowes,Patricia,",
    "wof:placetype":"venue"
},
  "geometry": {"coordinates":[-2.8581790924,53.3760604858],"type":"Point"}
}