{
  "type": "Feature",
  "properties": {
    "addr:full":"3 Gore Cross Way Bridport Dorset DT6 3EN",
    "addr:housenumber":"3",
    "addr:postcode":"dt6 3en",
    "addr:street":"Gore Cross Way",
    "iso:country":"GB",
    "sg:address":"3 Gore Cross Way",
    "sg:city":"Bridport",
    "sg:classifiers":[
        {
            "category":"Food & Beverages",
            "subcategory":"Supermarket",
            "type":"Retail Goods"
        }
    ],
    "sg:postcode":"DT6 3EN",
    "sg:province":"Dorset",
    "wof:name":"Farr,D G,",
    "wof:placetype":"venue"
},
  "geometry": {"coordinates":[-2.739882946,50.7470169067],"type":"Point"}
}