{
  "type": "Feature",
  "properties": {
    "addr:full":"54 Fore St Salcombe Devon TQ8 8JE",
    "addr:housenumber":"54",
    "addr:postcode":"tq8 8je",
    "addr:street":"Fore St",
    "iso:country":"GB",
    "sg:address":"54 Fore St",
    "sg:city":"Salcombe",
    "sg:classifiers":[
        {
            "category":"Shopping",
            "subcategory":"Clothing, Apparel, & Fashions",
            "type":"Retail Goods"
        }
    ],
    "sg:phone":"+44 1548 842977",
    "sg:postcode":"TQ8 8JE",
    "sg:province":"Devon",
    "sg:tags":[
        "wear",
        "leisure"
    ],
    "wof:name":"Tricot Designer Leisurewear",
    "wof:placetype":"venue"
},
  "geometry": {"coordinates":[-3.766983,50.236683],"type":"Point"}
}