{
  "type": "Feature",
  "properties": {
    "addr:full":"Hawke Street Sheffield South Yorkshire S9 2SU",
    "addr:postcode":"s9 2su",
    "addr:street":"Hawke Street",
    "iso:country":"GB",
    "sg:address":"Hawke Street",
    "sg:city":"Sheffield",
    "sg:classifiers":[
        {
            "category":"Manufacturing",
            "subcategory":"Metals",
            "type":"Manufacturing & Wholesale Goods"
        }
    ],
    "sg:phone":"+44 114 256 1200",
    "sg:postcode":"S9 2SU",
    "sg:province":"South Yorkshire",
    "sg:tags":[
        "steel",
        "stockholder"
    ],
    "wof:name":"Ulbrich of U K Ltd.",
    "wof:placetype":"venue"
},
  "geometry": {"coordinates":[-1.425242,53.403641],"type":"Point"}
}