{
  "type": "Feature",
  "properties": {
    "iso:country":"GB",
    "sg:address":"33 Cyprus Road",
    "sg:city":"Burgess Hill",
    "sg:classifiers":[
        {
            "category":"Health Services",
            "subcategory":"Podiatrist",
            "type":"Services"
        },
        {
            "category":"Health Services",
            "subcategory":"Chiropractor",
            "type":"Services"
        }
    ],
    "sg:phone":"+44 1444 232437",
    "sg:postcode":"RH15 8DX",
    "sg:province":"East Sussex",
    "sg:tags":[
        "podiatrists",
        "chiropodist"
    ],
    "wof:name":"Barry Walker",
    "wof:placetype":"venue"
},
  "geometry": {"coordinates":[-0.1295209974,50.9560928345],"type":"Point"}
}