{
  "type": "Feature",
  "properties": {
    "iso:country":"GB",
    "sg:address":"Bonny Blacks Farm, Howgill Lane, Gisburn",
    "sg:city":"Clitheroe",
    "sg:classifiers":[
        {
            "category":"Home & Garden",
            "subcategory":"Home Furnishings",
            "type":"Retail Goods"
        }
    ],
    "sg:phone":"+44 1200 445346",
    "sg:postcode":"BB7 4JL",
    "sg:province":"Lancashire",
    "sg:tags":[
        "household",
        "furniture"
    ],
    "wof:name":"Ribble Reproduction Furniture",
    "wof:placetype":"venue"
},
  "geometry": {"coordinates":[-2.260546,53.935184],"type":"Point"}
}