{
  "type": "Feature",
  "properties": {
    "addr:full":"Mere Lane Southport Lancashire PR9 8DA",
    "addr:postcode":"pr9 8da",
    "addr:street":"Mere Lane",
    "iso:country":"GB",
    "sg:address":"Mere Lane",
    "sg:city":"Southport",
    "sg:classifiers":[
        {
            "category":"Farming",
            "subcategory":"Nursery",
            "type":"Manufacturing & Wholesale Goods"
        },
        {
            "category":"Home & Garden",
            "subcategory":"Garden Supply",
            "type":"Retail Goods"
        }
    ],
    "sg:phone":"+44 1704 214150",
    "sg:postcode":"PR9 8DA",
    "sg:province":"Lancashire",
    "sg:tags":[
        "centre"
    ],
    "wof:name":"Larkfield Nurseries",
    "wof:placetype":"venue"
},
  "geometry": {"coordinates":[-2.9187049866,53.6642875671],"type":"Point"}
}