{
  "type": "Feature",
  "properties": {
    "iso:country":"GB",
    "sg:address":"360 High Road, Leavesden",
    "sg:city":"Watford",
    "sg:classifiers":[
        {
            "category":"Building & Trades",
            "subcategory":"Construction",
            "type":"Services"
        }
    ],
    "sg:phone":"+44 1923 893200",
    "sg:postcode":"WD25 7EQ",
    "sg:province":"Hertfordshire",
    "sg:tags":[
        "roofing"
    ],
    "wof:name":"E Scott & Sons",
    "wof:placetype":"venue"
},
  "geometry": {"coordinates":[-0.402647,51.700733],"type":"Point"}
}