{
  "type": "Feature",
  "properties": {
    "iso:country":"GB",
    "sg:address":"55 Wenlock Road",
    "sg:city":"Shrewsbury",
    "sg:classifiers":[
        {
            "category":"Building & Trades",
            "subcategory":"Construction",
            "type":"Services"
        }
    ],
    "sg:phone":"+44 1743 353733",
    "sg:postcode":"SY2 6JR",
    "sg:province":"Shropshire",
    "sg:tags":[
        "builder"
    ],
    "wof:name":"William John Gittins",
    "wof:placetype":"venue"
},
  "geometry": {"coordinates":[-2.7297420502,52.7005348206],"type":"Point"}
}