{
  "type": "Feature",
  "properties": {
    "addr:full":"51 Duncumb Road Sutton Coldfield Staffordshire B75 7PR",
    "addr:housenumber":"51",
    "addr:postcode":"b75 7pr",
    "addr:street":"Duncumb Road",
    "iso:country":"GB",
    "sg:address":"51 Duncumb Road",
    "sg:city":"Sutton Coldfield",
    "sg:classifiers":[
        {
            "category":"Social Services",
            "subcategory":"Adult Care",
            "type":"Services"
        }
    ],
    "sg:postcode":"B75 7PR",
    "sg:province":"Staffordshire",
    "sg:tags":[
        "domestic",
        "cleaning"
    ],
    "wof:name":"Unique Domestic Cleaning Services",
    "wof:placetype":"venue"
},
  "geometry": {"coordinates":[-1.789679,52.564739],"type":"Point"}
}