{
  "type": "Feature",
  "properties": {
    "iso:country":"GB",
    "sg:address":"198 Church Road",
    "sg:city":"London",
    "sg:classifiers":[
        {
            "category":"Autos & Motor Vehicles",
            "subcategory":"Auto Supplies",
            "type":"Retail Goods"
        }
    ],
    "sg:postcode":"NW10 2NP",
    "sg:province":"Greater London",
    "sg:tags":[
        "component"
    ],
    "wof:name":"Church Autos",
    "wof:placetype":"venue"
},
  "geometry": {"coordinates":[-0.247574,51.548904],"type":"Point"}
}