{
  "type": "Feature",
  "properties": {
    "addr:full":"100 Lower Clapton Road London Greater London E14 9UH",
    "addr:housenumber":"100",
    "addr:postcode":"e14 9uh",
    "addr:street":"Lower Clapton Road",
    "iso:country":"GB",
    "sg:address":"100 Lower Clapton Road",
    "sg:city":"London",
    "sg:classifiers":[
        {
            "category":"Health Services",
            "subcategory":"Doctor",
            "type":"Services"
        }
    ],
    "sg:phone":"+44 20 8985 2020",
    "sg:postcode":"E14 9UH",
    "sg:province":"Greater London",
    "sg:tags":[
        "practitioners"
    ],
    "wof:name":"J A Garfoot",
    "wof:placetype":"venue"
},
  "geometry": {"coordinates":[-0.053146,51.553459],"type":"Point"}
}