{
  "type": "Feature",
  "properties": {
    "addr:full":"1 Longford Ave Stockport Cheshire SK5 6LN",
    "addr:housenumber":"1",
    "addr:postcode":"sk5 6ln",
    "addr:street":"Longford Ave",
    "iso:country":"GB",
    "sg:address":"1 Longford Ave",
    "sg:city":"Stockport",
    "sg:classifiers":[
        {
            "category":"Autos & Motor Vehicles",
            "subcategory":"Automobile Sales",
            "type":"Retail Goods"
        }
    ],
    "sg:postcode":"SK5 6LN",
    "sg:province":"Cheshire",
    "sg:tags":[
        "car"
    ],
    "wof:name":"Melrose Garage",
    "wof:placetype":"venue"
},
  "geometry": {"coordinates":[-2.1551320553,53.4450454712],"type":"Point"}
}