{
  "type": "Feature",
  "properties": {
    "iso:country":"GB",
    "sg:address":"192 Mount St, Nechells",
    "sg:city":"Birmingham",
    "sg:classifiers":[
        {
            "category":"Retail",
            "subcategory":"Storage",
            "type":"Services"
        }
    ],
    "sg:phone":"+44 121 326 7817",
    "sg:postcode":"B7 5QP",
    "sg:province":"West Midlands",
    "sg:tags":[
        "household",
        "activity",
        "domestic",
        "removal"
    ],
    "wof:name":"A.arron Removals",
    "wof:placetype":"venue"
},
  "geometry": {"coordinates":[-1.861975,52.501587],"type":"Point"}
}