{
  "type": "Feature",
  "properties": {
    "iso:country":"GB",
    "sg:address":"65 Lychgate Lane",
    "sg:city":"Broxburn",
    "sg:classifiers":[
        {
            "category":"Organizations",
            "subcategory":"Community Association",
            "type":"Services"
        }
    ],
    "sg:phone":"+44 1506 855855",
    "sg:postcode":"EH52 5NQ",
    "sg:province":"City of Edinburgh",
    "sg:tags":[
        "society",
        "housing"
    ],
    "wof:name":"Edinvar Housing Association Ltd.",
    "wof:placetype":"venue"
},
  "geometry": {"coordinates":[-3.477068,55.935009],"type":"Point"}
}