{
  "type": "Feature",
  "properties": {
    "iso:country":"GB",
    "sg:address":"76 Oxhill Road",
    "sg:city":"Birmingham",
    "sg:classifiers":[
        {
            "category":"Health Services",
            "subcategory":"Optometrist",
            "type":"Services"
        },
        {
            "category":"Shopping",
            "subcategory":"Optician",
            "type":"Retail Goods"
        }
    ],
    "sg:phone":"+44 121 554 8949",
    "sg:postcode":"B21 9RH",
    "sg:province":"West Midlands",
    "sg:tags":[
        "ophthalmic"
    ],
    "wof:name":"Richard P J Ward Opticians",
    "wof:placetype":"venue"
},
  "geometry": {"coordinates":[-1.938533,52.514343],"type":"Point"}
}