{
  "type": "Feature",
  "properties": {
    "addr:full":"Ganwick Corner, Barnet Road Barnet Hertfordshire EN5 4SG",
    "addr:postcode":"en5 4sg",
    "addr:street":"Barnet Road",
    "iso:country":"GB",
    "sg:address":"Ganwick Corner, Barnet Road",
    "sg:city":"Barnet",
    "sg:classifiers":[
        {
            "category":"Building & Trades",
            "subcategory":"Construction",
            "type":"Services"
        }
    ],
    "sg:phone":"+44 20 8441 2686",
    "sg:postcode":"EN5 4SG",
    "sg:province":"Hertfordshire",
    "sg:tags":[
        "builder"
    ],
    "wof:name":"Leonard Flowerday Ltd.",
    "wof:placetype":"venue"
},
  "geometry": {"coordinates":[-0.2049989998,51.6587257385],"type":"Point"}
}