{
  "type": "Feature",
  "properties": {
    "addr:full":"161 Yorkshire Street Rochdale Lancashire OL12 0DR",
    "addr:housenumber":"161",
    "addr:postcode":"ol12 0dr",
    "addr:street":"Yorkshire Street",
    "iso:country":"GB",
    "sg:address":"161 Yorkshire Street",
    "sg:city":"Rochdale",
    "sg:classifiers":[
        {
            "category":"Recreation",
            "subcategory":"Fishing",
            "type":"Entertainment"
        }
    ],
    "sg:phone":"+44 1706 527604",
    "sg:postcode":"OL12 0DR",
    "sg:province":"Lancashire",
    "sg:tags":[
        "angling"
    ],
    "wof:name":"Rochdale Angling Centre",
    "wof:placetype":"venue"
},
  "geometry": {"coordinates":[-2.1508879662,53.6213264465],"type":"Point"}
}