{
  "type": "Feature",
  "properties": {
    "addr:full":"42 The Square Newton Abbot Devon TQ13 8EL",
    "addr:housenumber":"42",
    "addr:postcode":"tq13 8el",
    "addr:street":"The Square",
    "iso:country":"GB",
    "sg:address":"42 The Square",
    "sg:city":"Newton Abbot",
    "sg:classifiers":[
        {
            "category":"Professional",
            "subcategory":"Art Services",
            "type":"Services"
        }
    ],
    "sg:phone":"+44 1647 432575",
    "sg:postcode":"TQ13 8EL",
    "sg:province":"Devon",
    "sg:tags":[
        "consultant",
        "design"
    ],
    "wof:name":"Squirrel Design & Construction Ltd",
    "wof:placetype":"venue"
},
  "geometry": {"coordinates":[-3.840477,50.672813],"type":"Point"}
}