{
  "type": "Feature",
  "properties": {
    "addr:full":"Mill Farm, Wressle Selby East Riding of Yorkshire YO8 6EP",
    "addr:housenumber":"wressle",
    "addr:postcode":"yo8 6ep",
    "addr:street":"Selby",
    "iso:country":"GB",
    "sg:address":"Mill Farm, Wressle",
    "sg:city":"Selby",
    "sg:classifiers":[
        {
            "category":"Home & Garden",
            "subcategory":"Garden Supply",
            "type":"Retail Goods"
        },
        {
            "category":"Farming",
            "subcategory":"Farm",
            "type":"Manufacturing & Wholesale Goods"
        }
    ],
    "sg:phone":"+44 1757 638267",
    "sg:postcode":"YO8 6EP",
    "sg:province":"East Riding of Yorkshire",
    "sg:tags":[
        "mixed",
        "bulb",
        "crop",
        "grower"
    ],
    "wof:name":"J R & C Leak",
    "wof:placetype":"venue"
},
  "geometry": {"coordinates":[-0.9257360101,53.7752952576],"type":"Point"}
}