{
  "type": "Feature",
  "properties": {
    "addr:full":"134 Chewton Street Nottingham Derbyshire NG16 3JN",
    "addr:housenumber":"134",
    "addr:postcode":"ng16 3jn",
    "addr:street":"Chewton Street",
    "iso:country":"GB",
    "sg:address":"134 Chewton Street",
    "sg:city":"Nottingham",
    "sg:classifiers":[
        {
            "category":"Retail",
            "subcategory":"Auto Repair",
            "type":"Services"
        }
    ],
    "sg:phone":"+44 1773 530586",
    "sg:postcode":"NG16 3JN",
    "sg:province":"Derbyshire",
    "sg:tags":[
        "modification",
        "garage"
    ],
    "wof:name":"Geoff Bramley Motors",
    "wof:placetype":"venue"
},
  "geometry": {"coordinates":[-1.305967,53.010506],"type":"Point"}
}