{
  "type": "Feature",
  "properties": {
    "iso:country":"GB",
    "sg:address":"6-8 Wilson Street",
    "sg:city":"Guisborough",
    "sg:classifiers":[
        {
            "category":"Organizations",
            "subcategory":"Political Organization",
            "type":"Services"
        }
    ],
    "sg:phone":"+44 1287 610878",
    "sg:postcode":"TS14 6NA",
    "sg:province":"North Yorkshire",
    "sg:tags":[
        "party"
    ],
    "wof:name":"Middlesbrough South & East Cleveland Labour Party",
    "wof:placetype":"venue"
},
  "geometry": {"coordinates":[-1.059069,54.53344],"type":"Point"}
}