{
  "type": "Feature",
  "properties": {
    "iso:country":"GB",
    "sg:address":"Penley Industrial Estate",
    "sg:city":"Wrexham",
    "sg:classifiers":[
        {
            "category":"Organizations",
            "subcategory":"Non-profit Organization",
            "type":"Services"
        }
    ],
    "sg:phone":"+44 1948 830730",
    "sg:postcode":"LL13 0LQ",
    "sg:province":"Wrexham",
    "sg:tags":[
        "organisation",
        "voluntary",
        "charity"
    ],
    "wof:name":"The Rainbow Centre",
    "wof:placetype":"venue"
},
  "geometry": {"coordinates":[-2.871019,52.953876],"type":"Point"}
}