{
  "type": "Feature",
  "properties": {
    "addr:full":"16-18 Old Queen St Westminster Greater London SW1H 9HP",
    "addr:housenumber":"16-18",
    "addr:postcode":"sw1h 9hp",
    "addr:street":"Old Queen St",
    "iso:country":"GB",
    "sg:address":"16-18 Old Queen St",
    "sg:city":"Westminster",
    "sg:classifiers":[
        {
            "category":"Professional",
            "subcategory":"Engineering",
            "type":"Services"
        }
    ],
    "sg:phone":"+44 20 7976 7070",
    "sg:postcode":"SW1H 9HP",
    "sg:province":"Greater London",
    "sg:tags":[
        "consulting",
        "engineer"
    ],
    "wof:name":"English Partnerships",
    "wof:placetype":"venue"
},
  "geometry": {"coordinates":[-0.1304879934,51.5009651184],"type":"Point"}
}