{
  "type": "Feature",
  "properties": {
    "iso:country":"GB",
    "sg:address":"Cragg Rd Works, Cragg Rd, Mytholmroyd",
    "sg:city":"Hebden Bridge",
    "sg:classifiers":[
        {
            "category":"Home & Garden",
            "subcategory":"Hardware",
            "type":"Retail Goods"
        }
    ],
    "sg:phone":"+44 1422 884761",
    "sg:postcode":"HX7 5EY",
    "sg:province":"West Yorkshire",
    "sg:tags":[
        "fixing",
        "nuts",
        "bolt"
    ],
    "wof:name":"P.S.G",
    "wof:placetype":"venue"
},
  "geometry": {"coordinates":[-1.9921089411,53.7108535767],"type":"Point"}
}