{
  "type": "Feature",
  "properties": {
    "iso:country":"GB",
    "sg:address":"22 Eve Road, Tottenham",
    "sg:city":"London",
    "sg:classifiers":[
        {
            "category":"Building & Trades",
            "subcategory":"Plumbing",
            "type":"Services"
        }
    ],
    "sg:phone":"+44 20 8885 1697",
    "sg:postcode":"N17 6YD",
    "sg:province":"Greater London",
    "sg:tags":[
        "heating"
    ],
    "wof:name":"A-Z Plumbing & Heating",
    "wof:placetype":"venue"
},
  "geometry": {"coordinates":[-0.075927,51.592285],"type":"Point"}
}