{
  "type": "Feature",
  "properties": {
    "iso:country":"GB",
    "sg:address":"180 Wandsworth Bridge Road",
    "sg:city":"London",
    "sg:classifiers":[
        {
            "category":"Building & Trades",
            "subcategory":"Electrical",
            "type":"Services"
        }
    ],
    "sg:phone":"+44 20 7731 8830",
    "sg:postcode":"SW6 2UF",
    "sg:province":"Greater London",
    "sg:tags":[
        "lighting"
    ],
    "wof:name":"Christopher Hyde Ltd.",
    "wof:placetype":"venue"
},
  "geometry": {"coordinates":[-0.1913069934,51.4707221985],"type":"Point"}
}