{
  "type": "Feature",
  "properties": {
    "iso:country":"GB",
    "sg:address":"1st Floor Paris House, 3 Market Square",
    "sg:city":"Rugeley",
    "sg:classifiers":[
        {
            "category":"Shopping",
            "subcategory":"Clothing, Apparel, & Fashions",
            "type":"Retail Goods"
        }
    ],
    "sg:phone":"+44 1889 570500",
    "sg:postcode":"WS15 2BL",
    "sg:province":"Staffordshire",
    "sg:tags":[
        "clothing"
    ],
    "wof:name":"Sunrise Import & Export Ltd.",
    "wof:placetype":"venue"
},
  "geometry": {"coordinates":[-1.934527,52.761162],"type":"Point"}
}