{
  "type": "Feature",
  "properties": {
    "iso:country":"GB",
    "sg:address":"19 Station Road, Trimley",
    "sg:city":"Felixstowe",
    "sg:classifiers":[
        {
            "category":"Building & Trades",
            "subcategory":"Construction",
            "type":"Services"
        }
    ],
    "sg:postcode":"IP11 0TS",
    "sg:province":"Suffolk",
    "sg:tags":[
        "decorator",
        "painter"
    ],
    "wof:name":"A P McCallum",
    "wof:placetype":"venue"
},
  "geometry": {"coordinates":[1.3199739456,51.977722168],"type":"Point"}
}