{
  "type": "Feature",
  "properties": {
    "addr:full":"Quadrant Court, 44-45 Calthorpe Rd, Edgbaston Birmingham West Midlands B15 1TH",
    "addr:housenumber":"44-45",
    "addr:postcode":"b15 1th",
    "addr:street":"Calthorpe Rd",
    "iso:country":"GB",
    "sg:address":"Quadrant Court, 44-45 Calthorpe Rd, Edgbaston",
    "sg:city":"Birmingham",
    "sg:classifiers":[
        {
            "category":"Professional",
            "subcategory":"Engineering",
            "type":"Services"
        }
    ],
    "sg:phone":"+44 121 452 7400",
    "sg:postcode":"B15 1TH",
    "sg:province":"West Midlands",
    "sg:tags":[
        "design",
        "engineer"
    ],
    "wof:name":"PB Kennedy & Donkin Ltd",
    "wof:placetype":"venue"
},
  "geometry": {"coordinates":[-1.9202840328,52.4698257446],"type":"Point"}
}