{
  "type": "Feature",
  "properties": {
    "addr:full":"Po Box 2365 Iver Berkshire SL0 9WD",
    "addr:housenumber":"po",
    "addr:postcode":"2365;sl0 9wd",
    "addr:street":"Box",
    "iso:country":"GB",
    "sg:address":"Po Box 2365",
    "sg:city":"Iver",
    "sg:classifiers":[
        {
            "category":"Communications",
            "type":"Services"
        }
    ],
    "sg:phone":"+44 1753 630701",
    "sg:postcode":"SL0 9WD",
    "sg:province":"Berkshire",
    "sg:tags":[
        "data",
        "network"
    ],
    "wof:name":"C S N Digimedia",
    "wof:placetype":"venue"
},
  "geometry": {"coordinates":[-0.503779,51.517792],"type":"Point"}
}