{
  "type": "Feature",
  "properties": {
    "addr:full":"P O Box 1000 St Albans Hertfordshire AL3 5NY",
    "addr:housenumber":"p o;1000",
    "addr:postcode":"al3 5ny",
    "addr:street":"St",
    "iso:country":"GB",
    "sg:address":"P O Box 1000",
    "sg:city":"St Albans",
    "sg:classifiers":[
        {
            "category":"Professional",
            "subcategory":"Computer Services",
            "type":"Services"
        }
    ],
    "sg:phone":"+44 1727 852801",
    "sg:postcode":"AL3 5NY",
    "sg:province":"Hertfordshire",
    "sg:tags":[
        "consultant"
    ],
    "wof:name":"Mine of Information Ltd.",
    "wof:placetype":"venue"
},
  "geometry": {"coordinates":[-0.3397499919,51.7594985962],"type":"Point"}
}