{
  "type": "Feature",
  "properties": {
    "addr:full":"Suite 41, The Westgate Centre Oxford Oxfordshire OX1 1PD",
    "addr:postcode":"ox1 1pd",
    "addr:street":"Suite 41 The Westgate Centre",
    "iso:country":"GB",
    "sg:address":"Suite 41, The Westgate Centre",
    "sg:city":"Oxford",
    "sg:classifiers":[
        {
            "category":"Communications",
            "type":"Services"
        }
    ],
    "sg:phone":"+44 1865 724442",
    "sg:postcode":"OX1 1PD",
    "sg:province":"Oxfordshire",
    "sg:tags":[
        "broadcasting"
    ],
    "wof:name":"Fusion Radio Group Ltd.",
    "wof:placetype":"venue"
},
  "geometry": {"coordinates":[-1.2657990456,51.7513008118],"type":"Point"}
}