{
  "type": "Feature",
  "properties": {
    "iso:country":"GB",
    "sg:address":"22 Eggbuckland Road, Mannamead",
    "sg:city":"Plymouth",
    "sg:classifiers":[
        {
            "category":"Health Services",
            "subcategory":"Doctor",
            "type":"Services"
        }
    ],
    "sg:phone":"+44 1752 256517",
    "sg:postcode":"PL3 5HE",
    "sg:province":"Devon",
    "sg:tags":[
        "practitioners"
    ],
    "wof:name":"THE SURGERY",
    "wof:placetype":"venue"
},
  "geometry": {"coordinates":[-4.129131,50.38966],"type":"Point"}
}