{
  "type": "Feature",
  "properties": {
    "iso:country":"GB",
    "sg:address":"12 School Road",
    "sg:city":"Hounslow",
    "sg:classifiers":[
        {
            "category":"Organizations",
            "subcategory":"Non-profit Organization",
            "type":"Services"
        }
    ],
    "sg:phone":"+44 20 8569 5366",
    "sg:postcode":"TW3 1QZ",
    "sg:province":"Greater London",
    "sg:tags":[
        "charitable",
        "organisation",
        "voluntary",
        "charity"
    ],
    "wof:name":"HOSPITAL ALERT",
    "wof:placetype":"venue"
},
  "geometry": {"coordinates":[-0.356647,51.469772],"type":"Point"}
}