{
  "type": "Feature",
  "properties": {
    "iso:country":"GB",
    "sg:address":"Mill House",
    "sg:city":"Morpeth",
    "sg:classifiers":[
        {
            "category":"Shopping",
            "subcategory":"Photographic Equipment",
            "type":"Retail Goods"
        }
    ],
    "sg:phone":"+44 1670 515515",
    "sg:postcode":"NE61 6SP",
    "sg:province":"Northumberland",
    "wof:name":"Photography by Hank",
    "wof:placetype":"venue"
},
  "geometry": {"coordinates":[-1.6548919678,55.1466064453],"type":"Point"}
}