{
  "type": "Feature",
  "properties": {
    "iso:country":"GB",
    "sg:address":"Carisbrooke Castle, Castle Hill",
    "sg:city":"Newport",
    "sg:classifiers":[
        {
            "category":"Cafe",
            "type":"Food & Drink"
        }
    ],
    "sg:phone":"+44 1983 530602",
    "sg:postcode":"PO30 1XY",
    "sg:province":"Isle of Wight",
    "sg:tags":[
        "tea",
        "snack",
        "bar",
        "room"
    ],
    "wof:name":"Historic Buildings & Monuments Commission For England",
    "wof:placetype":"venue"
},
  "geometry": {"coordinates":[-1.298949,50.698471],"type":"Point"}
}