{
  "type": "Feature",
  "properties": {
    "addr:full":"The Furniture Village, London Road Chalfont St Giles Buckinghamshire HP8 4NN",
    "addr:postcode":"hp8 4nn",
    "addr:street":"Village London Road",
    "iso:country":"GB",
    "sg:address":"The Furniture Village, London Road",
    "sg:city":"Chalfont St Giles",
    "sg:classifiers":[
        {
            "category":"Home & Garden",
            "subcategory":"Home Furnishings",
            "type":"Retail Goods"
        }
    ],
    "sg:phone":"+44 1494 871077",
    "sg:postcode":"HP8 4NN",
    "sg:province":"Buckinghamshire",
    "sg:tags":[
        "blind",
        "curtain",
        "fitting"
    ],
    "wof:name":"Village Curtains",
    "wof:placetype":"venue"
},
  "geometry": {"coordinates":[-0.576628983,51.6299247742],"type":"Point"}
}