{
  "type": "Feature",
  "properties": {
    "addr:full":"330 Four Oaks Rd, Walton Summit Centre, Bamber Bridge Preston Lancashire PR5 8AP",
    "addr:housenumber":"330",
    "addr:postcode":"pr5 8ap",
    "addr:street":"Four Oaks Rd",
    "iso:country":"GB",
    "sg:address":"330 Four Oaks Rd, Walton Summit Centre, Bamber Bridge",
    "sg:city":"Preston",
    "sg:classifiers":[
        {
            "category":"Autos & Motor Vehicles",
            "subcategory":"Auto Supplies",
            "type":"Retail Goods"
        }
    ],
    "sg:phone":"+44 1772 334851",
    "sg:postcode":"PR5 8AP",
    "sg:province":"Lancashire",
    "sg:tags":[
        "exhaust",
        "absorber",
        "shock"
    ],
    "wof:name":"Bosal Distribution Ltd.",
    "wof:placetype":"venue"
},
  "geometry": {"coordinates":[-2.6454529762,53.7195892334],"type":"Point"}
}