{
  "type": "Feature",
  "properties": {
    "addr:full":"13a Museum Street Warrington Cheshire WA1 1JA",
    "addr:housenumber":"13a",
    "addr:postcode":"wa1 1ja",
    "addr:street":"Museum Street",
    "iso:country":"GB",
    "sg:address":"13a Museum Street",
    "sg:city":"Warrington",
    "sg:classifiers":[
        {
            "category":"Professional",
            "subcategory":"Accounting & Tax Preparation",
            "type":"Services"
        }
    ],
    "sg:postcode":"WA1 1JA",
    "sg:province":"Cheshire",
    "sg:tags":[
        "accountant"
    ],
    "wof:name":"Davies Downs & Co-Chartered Accountants",
    "wof:placetype":"venue"
},
  "geometry": {"coordinates":[-2.5970070362,53.3869895935],"type":"Point"}
}