{
  "type": "Feature",
  "properties": {
    "addr:full":"1 Victoria Street Forfar Angus DD8 3HU",
    "addr:housenumber":"1",
    "addr:postcode":"dd8 3hu",
    "addr:street":"Victoria Street",
    "iso:country":"GB",
    "sg:address":"1 Victoria Street",
    "sg:city":"Forfar",
    "sg:classifiers":[
        {
            "category":"Building & Trades",
            "subcategory":"Construction",
            "type":"Services"
        }
    ],
    "sg:postcode":"DD8 3HU",
    "sg:province":"Angus",
    "sg:tags":[
        "roofing",
        "builder"
    ],
    "wof:name":"W M Welsh",
    "wof:placetype":"venue"
},
  "geometry": {"coordinates":[-2.887662,56.647465],"type":"Point"}
}