{
  "type": "Feature",
  "properties": {
    "iso:country":"GB",
    "sg:address":"10 Manor Rd",
    "sg:city":"Coventry",
    "sg:classifiers":[
        {
            "category":"Professional",
            "subcategory":"Lawyer & Legal Services",
            "type":"Services"
        }
    ],
    "sg:phone":"+44 24 7622 4090",
    "sg:postcode":"CV1 2LH",
    "sg:province":"West Midlands",
    "sg:tags":[
        "advice",
        "counselling"
    ],
    "wof:name":"Mesmen Project",
    "wof:placetype":"venue"
},
  "geometry": {"coordinates":[-1.512222,52.40239],"type":"Point"}
}