{
  "type": "Feature",
  "properties": {
    "iso:country":"GB",
    "sg:address":"Brooklands Mill, English Street",
    "sg:city":"Leigh",
    "sg:classifiers":[
        {
            "category":"Arts & Performance",
            "subcategory":"Theater",
            "type":"Entertainment"
        }
    ],
    "sg:postcode":"WN7 3EJ",
    "sg:province":"Lancashire",
    "sg:tags":[
        "rehearsal",
        "studio",
        "facility"
    ],
    "wof:name":"Time Studios Rehearsal Rooms",
    "wof:placetype":"venue"
},
  "geometry": {"coordinates":[-2.521944,53.489368],"type":"Point"}
}