{
  "type": "Feature",
  "properties": {
    "iso:country":"GB",
    "sg:address":"37 Barnnock Burn Road",
    "sg:city":"Stirling",
    "sg:classifiers":[
        {
            "category":"Taxi",
            "type":"Transportation"
        }
    ],
    "sg:phone":"+44 1786 447177",
    "sg:postcode":"FK7 0BU",
    "sg:province":"Falkirk",
    "sg:tags":[
        "mini",
        "cab"
    ],
    "wof:name":"1A Scorpio Taxis",
    "wof:placetype":"venue"
},
  "geometry": {"coordinates":[-3.934976,56.100025],"type":"Point"}
}