{
  "type": "Feature",
  "properties": {
    "addr:full":"Swallow House, 11-21 Northdown Street London Greater London N1 9BN",
    "addr:housenumber":"11-21",
    "addr:postcode":"n1 9bn",
    "addr:street":"Northdown Street",
    "iso:country":"GB",
    "sg:address":"Swallow House, 11-21 Northdown Street",
    "sg:city":"London",
    "sg:classifiers":[
        {
            "category":"Social Services",
            "subcategory":"Job Training",
            "type":"Services"
        }
    ],
    "sg:phone":"+44 20 7520 1400",
    "sg:postcode":"N1 9BN",
    "sg:province":"Greater London",
    "sg:tags":[
        "translator",
        "interpreter"
    ],
    "wof:name":"Ll Shell Ltd.",
    "wof:placetype":"venue"
},
  "geometry": {"coordinates":[-0.1196009964,51.5312957764],"type":"Point"}
}