{
  "type": "Feature",
  "properties": {
    "addr:full":"24 Althorne Way Rochford Essex SS4 3PS",
    "addr:housenumber":"24",
    "addr:postcode":"ss4 3ps",
    "addr:street":"Althorne Way",
    "iso:country":"GB",
    "sg:address":"24 Althorne Way",
    "sg:city":"Rochford",
    "sg:classifiers":[
        {
            "category":"Retail",
            "subcategory":"Repair Shop",
            "type":"Services"
        }
    ],
    "sg:phone":"+44 1702 258084",
    "sg:postcode":"SS4 3PS",
    "sg:province":"Essex",
    "sg:tags":[
        "radio",
        "television",
        "video"
    ],
    "wof:name":"Tele Man The",
    "wof:placetype":"venue"
},
  "geometry": {"coordinates":[0.747424,51.618305],"type":"Point"}
}