{
  "type": "Feature",
  "properties": {
    "addr:full":"45 Clifton Road London Greater London N3 2AS",
    "addr:housenumber":"45",
    "addr:postcode":"n3 2as",
    "addr:street":"Clifton Road",
    "iso:country":"GB",
    "sg:address":"45 Clifton Road",
    "sg:city":"London",
    "sg:classifiers":[
        {
            "category":"Professional",
            "type":"Services"
        }
    ],
    "sg:postcode":"N3 2AS",
    "sg:province":"Greater London",
    "sg:tags":[
        "entertainer"
    ],
    "wof:name":"Universal Entertainments Agency",
    "wof:placetype":"venue"
},
  "geometry": {"coordinates":[-0.177786,51.603374],"type":"Point"}
}