{
  "type": "Feature",
  "properties": {
    "iso:country":"GB",
    "sg:address":"45 Clifton Road",
    "sg:city":"London",
    "sg:classifiers":[
        {
            "category":"Professional",
            "type":"Services"
        }
    ],
    "sg:postcode":"N3 2AS",
    "sg:province":"Greater London",
    "sg:tags":[
        "entertainer"
    ],
    "wof:name":"Universal Entertainments Agency",
    "wof:placetype":"venue"
},
  "geometry": {"coordinates":[-0.177786,51.603374],"type":"Point"}
}