{
  "type": "Feature",
  "properties": {
    "addr:full":"10 Wyvern Gro Birmingham West Midlands B29 6RN",
    "addr:housenumber":"10",
    "addr:postcode":"b29 6rn",
    "addr:street":"Gro",
    "iso:country":"GB",
    "sg:address":"10 Wyvern Gro",
    "sg:city":"Birmingham",
    "sg:classifiers":[
        {
            "category":"Retail",
            "subcategory":"Driving School",
            "type":"Services"
        }
    ],
    "sg:postcode":"B29 6RN",
    "sg:province":"West Midlands",
    "wof:name":"Excalibur",
    "wof:placetype":"venue"
},
  "geometry": {"coordinates":[-1.9552570581,52.4439201355],"type":"Point"}
}