{
  "type": "Feature",
  "properties": {
    "iso:country":"GB",
    "sg:address":"27 Bellview Rd",
    "sg:city":"Worthing",
    "sg:classifiers":[
        {
            "category":"Retail",
            "subcategory":"Driving School",
            "type":"Services"
        }
    ],
    "sg:phone":"+44 1903 232533",
    "sg:postcode":"BN13 1HA",
    "sg:province":"West Sussex",
    "wof:name":"Motor-Vation",
    "wof:placetype":"venue"
},
  "geometry": {"coordinates":[-0.396442,50.827],"type":"Point"}
}