{
  "type": "Feature",
  "properties": {
    "iso:country":"GB",
    "sg:address":"14-16 King St",
    "sg:city":"East Grinstead",
    "sg:classifiers":[
        {
            "category":"Juice Bar",
            "subcategory":"None",
            "type":"Food & Drink"
        }
    ],
    "sg:phone":"+44 1342 324097",
    "sg:postcode":"RH19 3DJ",
    "sg:province":"East Sussex",
    "sg:tags":[
        "fruit"
    ],
    "wof:name":"Meridian Line Products Ltd",
    "wof:placetype":"venue"
},
  "geometry": {"coordinates":[-0.0088099996,51.1266403198],"type":"Point"}
}