{
  "type": "Feature",
  "properties": {
    "iso:country":"GB",
    "sg:address":"Unit 1 Shires Industrial Estate, Essington Close",
    "sg:city":"Lichfield",
    "sg:classifiers":[
        {
            "category":"Professional",
            "subcategory":"Business Services",
            "type":"Services"
        },
        {
            "category":"Home & Garden",
            "subcategory":"Building Materials",
            "type":"Retail Goods"
        }
    ],
    "sg:postcode":"WS14 9AZ",
    "sg:province":"Staffordshire",
    "sg:tags":[
        "fencing",
        "agent",
        "manufacturers'"
    ],
    "wof:name":"Watkins",
    "wof:placetype":"venue"
},
  "geometry": {"coordinates":[-1.832508,52.673374],"type":"Point"}
}