{
  "type": "Feature",
  "properties": {
    "addr:full":"33-34 Bury Street London Greater London EC3A 5AR",
    "addr:housenumber":"33-34",
    "addr:postcode":"ec3a 5ar",
    "addr:street":"Bury Street",
    "iso:country":"GB",
    "sg:address":"33-34 Bury Street",
    "sg:city":"London",
    "sg:classifiers":[
        {
            "category":"Organizations",
            "subcategory":"Community Association",
            "type":"Services"
        }
    ],
    "sg:postcode":"EC3A 5AR",
    "sg:province":"Greater London",
    "sg:tags":[
        "relation",
        "public"
    ],
    "wof:name":"Trocki Ltd.",
    "wof:placetype":"venue"
},
  "geometry": {"coordinates":[-0.0797929987,51.5141181946],"type":"Point"}
}