{
  "type": "Feature",
  "properties": {
    "iso:country":"GB",
    "sg:address":"62 Bridgnorth Road, Wollaston",
    "sg:city":"Stourbridge",
    "sg:classifiers":[
        {
            "category":"Real Estate",
            "subcategory":"Developer",
            "type":"Services"
        },
        {
            "category":"Building & Trades",
            "subcategory":"Construction",
            "type":"Services"
        }
    ],
    "sg:phone":"+44 1384 376909",
    "sg:postcode":"DY8 3PA",
    "sg:province":"Staffordshire",
    "sg:tags":[
        "builder",
        "property"
    ],
    "wof:name":"Middleton Scriven Investments Ltd",
    "wof:placetype":"venue"
},
  "geometry": {"coordinates":[-2.1639978886,52.4604110718],"type":"Point"}
}