{
  "type": "Feature",
  "properties": {
    "addr:full":"8-13 Angle Park Terrace Edinburgh City of Edinburgh EH11 2JX",
    "addr:housenumber":"8-13",
    "addr:postcode":"eh11 2jx",
    "addr:street":"Angle Park Terrace",
    "iso:country":"GB",
    "sg:address":"8-13 Angle Park Terrace",
    "sg:city":"Edinburgh",
    "sg:classifiers":[
        {
            "category":"Home & Garden",
            "subcategory":"Furniture",
            "type":"Retail Goods"
        }
    ],
    "sg:phone":"+44 131 337 9284",
    "sg:postcode":"EH11 2JX",
    "sg:province":"City of Edinburgh",
    "wof:name":"Olympian Pine Ltd.",
    "wof:placetype":"venue"
},
  "geometry": {"coordinates":[-3.2241020203,55.9389457703],"type":"Point"}
}