{
  "type": "Feature",
  "properties": {
    "addr:full":"Carters Way Cambridge Cambridgeshire CB4 5RZ",
    "addr:postcode":"cb4 5rz",
    "addr:street":"Carters Way",
    "iso:country":"GB",
    "sg:address":"Carters Way",
    "sg:city":"Cambridge",
    "sg:classifiers":[
        {
            "category":"Professional",
            "subcategory":"Engineering",
            "type":"Services"
        },
        {
            "category":"Professional",
            "subcategory":"Management & Consulting",
            "type":"Services"
        }
    ],
    "sg:postcode":"CB4 5RZ",
    "sg:province":"Cambridgeshire",
    "sg:tags":[
        "consultant",
        "business",
        "engineer"
    ],
    "wof:name":"Hughes Consultancy",
    "wof:placetype":"venue"
},
  "geometry": {"coordinates":[-0.004408,52.297253],"type":"Point"}
}