{
  "type": "Feature",
  "properties": {
    "addr:full":"70 Turnpike Road, Red Lodge Bury St Edmunds Cambridgeshire IP28 8LB",
    "addr:housenumber":"70",
    "addr:postcode":"ip28 8lb",
    "addr:street":"Turnpike Road;St",
    "iso:country":"GB",
    "sg:address":"70 Turnpike Road, Red Lodge",
    "sg:city":"Bury St Edmunds",
    "sg:classifiers":[
        {
            "category":"Cafe",
            "type":"Food & Drink"
        }
    ],
    "sg:phone":"+44 1638 750529",
    "sg:postcode":"IP28 8LB",
    "sg:province":"Cambridgeshire",
    "sg:tags":[
        "tea",
        "snack",
        "bar",
        "room"
    ],
    "wof:name":"Red Lodge Cafe",
    "wof:placetype":"venue"
},
  "geometry": {"coordinates":[0.4836899936,52.301990509],"type":"Point"}
}