{
  "type": "Feature",
  "properties": {
    "addr:full":"5 Hales Hall Road, Cheadle Stoke-on-trent Staffordshire ST10 1BU",
    "addr:housenumber":"5",
    "addr:postcode":"st10 1bu",
    "addr:street":"Hales Hall Road Cheadle",
    "iso:country":"GB",
    "sg:address":"5 Hales Hall Road, Cheadle",
    "sg:city":"Stoke-on-trent",
    "sg:classifiers":[
        {
            "category":"Home & Garden",
            "subcategory":"Building Materials",
            "type":"Retail Goods"
        }
    ],
    "sg:phone":"+44 1538 756750",
    "sg:postcode":"ST10 1BU",
    "sg:province":"Staffordshire",
    "sg:tags":[
        "gate",
        "door",
        "barrier"
    ],
    "wof:name":"Faulkner Fencing",
    "wof:placetype":"venue"
},
  "geometry": {"coordinates":[-1.9780950546,52.9903030396],"type":"Point"}
}