{
  "type": "Feature",
  "properties": {
    "iso:country":"GB",
    "sg:address":"6 Station Road, Caerleon",
    "sg:city":"Newport",
    "sg:classifiers":[
        {
            "category":"Personal",
            "subcategory":"Beauty Salon",
            "type":"Services"
        },
        {
            "category":"Personal",
            "subcategory":"Barber",
            "type":"Services"
        }
    ],
    "sg:phone":"+44 1633 421726",
    "sg:postcode":"NP18 1NH",
    "sg:province":"Monmouthshire",
    "sg:tags":[
        "unisex",
        "hairdresser"
    ],
    "wof:name":"LESLEY HARVEY",
    "wof:placetype":"venue"
},
  "geometry": {"coordinates":[-2.958124,51.614285],"type":"Point"}
}