{
  "type": "Feature",
  "properties": {
    "addr:full":"5 Heol Y Felin, Pontyberem Llanelli Carmarthenshire SA15 5EB",
    "addr:housenumber":"5",
    "addr:postcode":"sa15 5eb",
    "addr:street":"Heol Y Felin",
    "iso:country":"GB",
    "sg:address":"5 Heol Y Felin, Pontyberem",
    "sg:city":"Llanelli",
    "sg:classifiers":[
        {
            "category":"Fast Food",
            "type":"Food & Drink"
        }
    ],
    "sg:phone":"+44 1269 871489",
    "sg:postcode":"SA15 5EB",
    "sg:province":"Carmarthenshire",
    "sg:tags":[
        "away",
        "meal",
        "outlet",
        "take"
    ],
    "wof:name":"Ponty Berem Balti",
    "wof:placetype":"venue"
},
  "geometry": {"coordinates":[-4.174734,51.779446],"type":"Point"}
}