{
  "type": "Feature",
  "properties": {
    "addr:full":"10 Station Rd London Greater London NW10 4UE",
    "addr:housenumber":"10",
    "addr:postcode":"nw10 4ue",
    "addr:street":"Station Rd",
    "iso:country":"GB",
    "sg:address":"10 Station Rd",
    "sg:city":"London",
    "sg:classifiers":[
        {
            "category":"Social Services",
            "subcategory":"Adult Care",
            "type":"Services"
        },
        {
            "category":"Organizations",
            "subcategory":"Community Association",
            "type":"Services"
        }
    ],
    "sg:postcode":"NW10 4UE",
    "sg:province":"Greater London",
    "sg:tags":[
        "society",
        "housing",
        "sheltered"
    ],
    "wof:name":"Network Housing Association Ltd",
    "wof:placetype":"venue"
},
  "geometry": {"coordinates":[-0.248546,51.535378],"type":"Point"}
}