{
  "type": "Feature",
  "properties": {
    "iso:country":"GB",
    "sg:address":"Low Meadows Farm, Wanes Blades La",
    "sg:city":"Ormskirk",
    "sg:classifiers":[
        {
            "category":"Farming",
            "subcategory":"Livestock Farm",
            "type":"Manufacturing & Wholesale Goods"
        }
    ],
    "sg:phone":"+44 1704 895323",
    "sg:postcode":"L40 4BN",
    "sg:province":"Lancashire",
    "sg:tags":[
        "others"
    ],
    "wof:name":"R & A Cowburn",
    "wof:placetype":"venue"
},
  "geometry": {"coordinates":[-2.79358,53.605831],"type":"Point"}
}