{
  "type": "Feature",
  "properties": {
    "iso:country":"GB",
    "sg:address":"B1 Commerce Way, Whitehall Industrial Estate",
    "sg:city":"Colchester",
    "sg:classifiers":[
        {
            "category":"Shopping",
            "subcategory":"Beauty & Cosmetics",
            "type":"Retail Goods"
        }
    ],
    "sg:phone":"+44 1206 790089",
    "sg:postcode":"CO2 8HH",
    "sg:province":"Essex",
    "sg:tags":[
        "equipment",
        "supply",
        "hairdressing"
    ],
    "wof:name":"Nexxus Essex",
    "wof:placetype":"venue"
},
  "geometry": {"coordinates":[0.903514,51.8853],"type":"Point"}
}