{
  "type": "Feature",
  "properties": {
    "iso:country":"GB",
    "sg:address":"27-31 High St",
    "sg:city":"Kidlington",
    "sg:classifiers":[
        {
            "category":"Social Services",
            "subcategory":"Retirement Home",
            "type":"Services"
        }
    ],
    "sg:phone":"+44 1865 370707",
    "sg:postcode":"OX5 2DH",
    "sg:province":"Buckinghamshire",
    "sg:tags":[
        "care"
    ],
    "wof:name":"Helping Hands Oxford Care Companions",
    "wof:placetype":"venue"
},
  "geometry": {"coordinates":[-1.289666,51.823383],"type":"Point"}
}