{
  "type": "Feature",
  "properties": {
    "addr:full":"Flat 178 Hetherlow Towers Liverpool Merseyside L4 6SP",
    "addr:housenumber":"flat 178 hetherlow towers",
    "addr:postcode":"l4 6sp",
    "iso:country":"GB",
    "sg:address":"Flat 178 Hetherlow Towers",
    "sg:city":"Liverpool",
    "sg:classifiers":[
        {
            "category":"Organizations",
            "subcategory":"Non-profit Organization",
            "type":"Services"
        }
    ],
    "sg:phone":"+44 151 523 7300",
    "sg:postcode":"L4 6SP",
    "sg:province":"Merseyside",
    "sg:tags":[
        "organisation",
        "voluntary",
        "charity"
    ],
    "wof:name":"Hetherlow Community Association",
    "wof:placetype":"venue"
},
  "geometry": {"coordinates":[-2.9567790031,53.4439888],"type":"Point"}
}