{
  "type": "Feature",
  "properties": {
    "iso:country":"GB",
    "sg:address":"70 Taff Street",
    "sg:city":"Pontypridd",
    "sg:classifiers":[
        {
            "category":"Shopping",
            "subcategory":"Thrift Store",
            "type":"Retail Goods"
        },
        {
            "category":"Organizations",
            "subcategory":"Non-profit Organization",
            "type":"Services"
        }
    ],
    "sg:phone":"+44 1443 485720",
    "sg:postcode":"CF37 4SU",
    "sg:province":"Caerphilly",
    "sg:tags":[
        "shop",
        "charitable",
        "organisation",
        "charity"
    ],
    "wof:name":"Imperial Cancer Research Fund",
    "wof:placetype":"venue"
},
  "geometry": {"coordinates":[-3.3406999111,51.6018943787],"type":"Point"}
}