{
  "type": "Feature",
  "properties": {
    "iso:country":"GB",
    "sg:address":"63 Cornwall St",
    "sg:city":"Plymouth",
    "sg:classifiers":[
        {
            "category":"Travel",
            "subcategory":"Travel Agent",
            "type":"Entertainment"
        }
    ],
    "sg:phone":"+44 1752 612740",
    "sg:postcode":"PL1 1NS",
    "sg:province":"Devon",
    "wof:name":"Thomas Cook Bureaux de Change",
    "wof:placetype":"venue"
},
  "geometry": {"coordinates":[-4.143561,50.372429],"type":"Point"}
}