{
  "type": "Feature",
  "properties": {
    "addr:full":"Berryfield Road Bradford-on-avon Wiltshire BA15 1ST",
    "addr:postcode":"ba15 1st",
    "addr:street":"Berryfield Road",
    "iso:country":"GB",
    "sg:address":"Berryfield Road",
    "sg:city":"Bradford-on-avon",
    "sg:classifiers":[
        {
            "category":"Education",
            "subcategory":"School",
            "type":"Public Place"
        },
        {
            "category":"Government",
            "subcategory":"Office",
            "type":"Public Place"
        }
    ],
    "sg:phone":"+44 1225 863444",
    "sg:postcode":"BA15 1ST",
    "sg:province":"Wiltshire",
    "sg:tags":[
        "local",
        "authority"
    ],
    "wof:name":"Christ Church Church of England Primary School",
    "wof:placetype":"venue"
},
  "geometry": {"coordinates":[-2.249398,51.353176],"type":"Point"}
}