{
  "type": "Feature",
  "properties": {
    "addr:full":"34 Harthill Rise, Gildersome Morley Leeds West Yorkshire LS27 7TT",
    "addr:housenumber":"34",
    "addr:postcode":"ls27 7tt",
    "addr:street":"Harthill Rise",
    "iso:country":"GB",
    "sg:address":"34 Harthill Rise, Gildersome Morley",
    "sg:city":"Leeds",
    "sg:classifiers":[
        {
            "category":"Building & Trades",
            "subcategory":"Construction",
            "type":"Services"
        }
    ],
    "sg:phone":"+44 113 252 0795",
    "sg:postcode":"LS27 7TT",
    "sg:province":"West Yorkshire",
    "sg:tags":[
        "decorator",
        "painter"
    ],
    "wof:name":"Goddard Bros of Leeds",
    "wof:placetype":"venue"
},
  "geometry": {"coordinates":[-1.6258209944,53.7599754333],"type":"Point"}
}