{
  "type": "Feature",
  "properties": {
    "iso:country":"GB",
    "sg:address":"24-30 Liscard Road",
    "sg:city":"Wallasey",
    "sg:classifiers":[
        {
            "category":"Shopping",
            "subcategory":"Baby Store",
            "type":"Retail Goods"
        }
    ],
    "sg:phone":"+44 151 638 2834",
    "sg:postcode":"L44 6LW",
    "sg:province":"Merseyside",
    "sg:tags":[
        "babywear",
        "childrens"
    ],
    "wof:name":"Ethel Austin Ltd.",
    "wof:placetype":"venue"
},
  "geometry": {"coordinates":[-3.043567,53.41959],"type":"Point"}
}