{
  "type": "Feature",
  "properties": {
    "addr:full":"Telephone Exchange, Fleet Street Burton-on-trent Derbyshire DE14 3RS",
    "addr:postcode":"de14 3rs",
    "addr:street":"Fleet Street",
    "iso:country":"GB",
    "sg:address":"Telephone Exchange, Fleet Street",
    "sg:city":"Burton-on-trent",
    "sg:classifiers":[
        {
            "category":"Building & Trades",
            "subcategory":"Construction",
            "type":"Services"
        }
    ],
    "sg:postcode":"DE14 3RS",
    "sg:province":"Derbyshire",
    "sg:tags":[
        "fork",
        "lift",
        "truck"
    ],
    "wof:name":"A & J Forklift Services",
    "wof:placetype":"venue"
},
  "geometry": {"coordinates":[-1.6324,52.799179],"type":"Point"}
}