{
  "type": "Feature",
  "properties": {
    "addr:full":"962 Shields Rd, Walkergate Newcastle Upon Tyne Tyne and Wear NE6 4XS",
    "addr:housenumber":"962",
    "addr:postcode":"ne6 4xs",
    "addr:street":"Shields Rd Walkergate",
    "iso:country":"GB",
    "sg:address":"962 Shields Rd, Walkergate",
    "sg:city":"Newcastle Upon Tyne",
    "sg:classifiers":[
        {
            "category":"Manufacturing",
            "subcategory":"Signs",
            "type":"Manufacturing & Wholesale Goods"
        }
    ],
    "sg:phone":"+44 191 295 3939",
    "sg:postcode":"NE6 4XS",
    "sg:province":"Tyne and Wear",
    "sg:tags":[
        "commercial",
        "maker"
    ],
    "wof:name":"Britannia Banners",
    "wof:placetype":"venue"
},
  "geometry": {"coordinates":[-1.553626,54.985783],"type":"Point"}
}