{
  "type": "Feature",
  "properties": {
    "addr:full":"Goslings Cottage, Sheepcotes Lane Braintree Essex CM7 8ER",
    "addr:postcode":"cm7 8er",
    "addr:street":"Sheepcotes Lane",
    "iso:country":"GB",
    "sg:address":"Goslings Cottage, Sheepcotes Lane",
    "sg:city":"Braintree",
    "sg:classifiers":[
        {
            "category":"Building & Trades",
            "subcategory":"Construction",
            "type":"Services"
        }
    ],
    "sg:postcode":"CM7 8ER",
    "sg:province":"Essex",
    "sg:tags":[
        "decorator",
        "painter"
    ],
    "wof:name":"Cooper & North (Building Services) Limit",
    "wof:placetype":"venue"
},
  "geometry": {"coordinates":[0.553242,51.877758],"type":"Point"}
}