{
  "type": "Feature",
  "properties": {
    "iso:country":"GB",
    "sg:address":"55 George Street",
    "sg:city":"Newcastle-upon-tyne",
    "sg:classifiers":[
        {
            "category":"Shopping",
            "subcategory":"Clothing, Apparel, & Fashions",
            "type":"Retail Goods"
        }
    ],
    "sg:phone":"+44 191 273 5157",
    "sg:postcode":"NE4 7JN",
    "sg:province":"Tyne and Wear",
    "sg:tags":[
        "clothing"
    ],
    "wof:name":"Paul's International Ltd.",
    "wof:placetype":"venue"
},
  "geometry": {"coordinates":[-1.625291,54.967312],"type":"Point"}
}