{
  "type": "Feature",
  "properties": {
    "addr:full":"14 Victoria Chase Colchester Essex CO1 1WN",
    "addr:housenumber":"14",
    "addr:postcode":"co1 1wn",
    "addr:street":"Victoria Chase Colchester",
    "iso:country":"GB",
    "sg:address":"14 Victoria Chase",
    "sg:city":"Colchester",
    "sg:classifiers":[
        {
            "category":"Building & Trades",
            "subcategory":"Construction",
            "type":"Services"
        }
    ],
    "sg:postcode":"CO1 1WN",
    "sg:province":"Essex",
    "sg:tags":[
        "builder"
    ],
    "wof:name":"D P C Contracts",
    "wof:placetype":"venue"
},
  "geometry": {"coordinates":[0.8951479793,51.8949661255],"type":"Point"}
}