{
  "type": "Feature",
  "properties": {
    "addr:full":"37 Waterside Street Largs North Ayrshire KA30 9LW",
    "addr:housenumber":"37",
    "addr:postcode":"ka30 9lw",
    "addr:street":"Waterside Street",
    "iso:country":"GB",
    "sg:address":"37 Waterside Street",
    "sg:city":"Largs",
    "sg:classifiers":[
        {
            "category":"Organizations",
            "subcategory":"Non-profit Organization",
            "type":"Services"
        }
    ],
    "sg:phone":"+44 1475 686200",
    "sg:postcode":"KA30 9LW",
    "sg:province":"North Ayrshire",
    "sg:tags":[
        "organisation",
        "voluntary",
        "charity"
    ],
    "wof:name":"British Red Cross Society",
    "wof:placetype":"venue"
},
  "geometry": {"coordinates":[-4.8614230156,55.7937774658],"type":"Point"}
}