{
  "type": "Feature",
  "properties": {
    "addr:full":"Dalton Mills, Dalton Lane Keighley West Yorkshire BD21 4JH",
    "addr:postcode":"bd21 4jh",
    "addr:street":"Dalton Lane",
    "iso:country":"GB",
    "sg:address":"Dalton Mills, Dalton Lane",
    "sg:city":"Keighley",
    "sg:classifiers":[
        {
            "category":"Professional",
            "subcategory":"Employment Agencies",
            "type":"Services"
        }
    ],
    "sg:phone":"+44 1535 691392",
    "sg:postcode":"BD21 4JH",
    "sg:province":"West Yorkshire",
    "sg:tags":[
        "consultant"
    ],
    "wof:name":"Tradesmen North Ltd.",
    "wof:placetype":"venue"
},
  "geometry": {"coordinates":[-1.909674,53.866364],"type":"Point"}
}