{
  "type": "Feature",
  "properties": {
    "addr:full":"6 Brighton Rd Horley Surrey RH6 7ES",
    "addr:housenumber":"6",
    "addr:postcode":"rh6 7es",
    "addr:street":"Brighton Rd",
    "iso:country":"GB",
    "sg:address":"6 Brighton Rd",
    "sg:city":"Horley",
    "sg:classifiers":[
        {
            "category":"Home & Garden",
            "subcategory":"Building Materials",
            "type":"Retail Goods"
        },
        {
            "category":"Building & Trades",
            "subcategory":"Construction",
            "type":"Services"
        }
    ],
    "sg:postcode":"RH6 7ES",
    "sg:province":"Surrey",
    "sg:tags":[
        "gate",
        "builder",
        "door",
        "barrier"
    ],
    "wof:name":"N A Davies",
    "wof:placetype":"venue"
},
  "geometry": {"coordinates":[-0.1748169959,51.1688995361],"type":"Point"}
}