{
  "type": "Feature",
  "properties": {
    "addr:full":"High Street, Kinver Stourbridge Shropshire DY7 6HL",
    "addr:postcode":"dy7 6hl",
    "addr:street":"High Street",
    "iso:country":"GB",
    "sg:address":"High Street, Kinver",
    "sg:city":"Stourbridge",
    "sg:classifiers":[
        {
            "category":"Organizations",
            "subcategory":"Membership Organization",
            "type":"Services"
        }
    ],
    "sg:phone":"+44 1384 872044",
    "sg:postcode":"DY7 6HL",
    "sg:province":"Shropshire",
    "sg:tags":[
        "club",
        "social"
    ],
    "wof:name":"Kinver Constitutional Club",
    "wof:placetype":"venue"
},
  "geometry": {"coordinates":[-2.229276,52.449036],"type":"Point"}
}