{
  "type": "Feature",
  "properties": {
    "addr:full":"7 High St, Sileby Loughborough Leicestershire LE12 7RX",
    "addr:housenumber":"7",
    "addr:postcode":"le12 7rx",
    "addr:street":"High St",
    "iso:country":"GB",
    "sg:address":"7 High St, Sileby",
    "sg:city":"Loughborough",
    "sg:classifiers":[
        {
            "category":"Shopping",
            "subcategory":"Shoes",
            "type":"Retail Goods"
        }
    ],
    "sg:postcode":"LE12 7RX",
    "sg:province":"Leicestershire",
    "wof:name":"Winder,Robert,",
    "wof:placetype":"venue"
},
  "geometry": {"coordinates":[-1.111152,52.730747],"type":"Point"}
}