{
  "type": "Feature",
  "properties": {
    "iso:country":"GB",
    "sg:address":"498 Hoe Street",
    "sg:city":"London",
    "sg:classifiers":[
        {
            "category":"Shopping",
            "subcategory":"News",
            "type":"Retail Goods"
        }
    ],
    "sg:phone":"+44 20 8558 1515",
    "sg:postcode":"E17 9AH",
    "sg:province":"Greater London",
    "sg:tags":[
        "newsagent"
    ],
    "wof:name":"Awan News",
    "wof:placetype":"venue"
},
  "geometry": {"coordinates":[-0.013234,51.57552],"type":"Point"}
}