{
  "type": "Feature",
  "properties": {
    "iso:country":"GB",
    "sg:address":"Peel Chambers, Peel Street",
    "sg:city":"Accrington",
    "sg:classifiers":[
        {
            "category":"Professional",
            "subcategory":"Management & Consulting",
            "type":"Services"
        },
        {
            "category":"Personal",
            "type":"Services"
        }
    ],
    "sg:phone":"+44 1254 237317",
    "sg:postcode":"BB5 1HB",
    "sg:province":"Lancashire",
    "sg:tags":[
        "consultant",
        "beauty",
        "specialist"
    ],
    "wof:name":"Health & Beauty",
    "wof:placetype":"venue"
},
  "geometry": {"coordinates":[-2.370644,53.755329],"type":"Point"}
}