{
  "type": "Feature",
  "properties": {
    "addr:full":"Ellesmead, Stable Lane, Calf Heath Wolverhampton Staffordshire WV10 7DN",
    "addr:postcode":"wv10 7dn",
    "addr:street":"Stable Lane",
    "iso:country":"GB",
    "sg:address":"Ellesmead, Stable Lane, Calf Heath",
    "sg:city":"Wolverhampton",
    "sg:classifiers":[
        {
            "category":"Retail",
            "subcategory":"Repair Shop",
            "type":"Services"
        }
    ],
    "sg:phone":"+44 1902 791620",
    "sg:postcode":"WV10 7DN",
    "sg:province":"Staffordshire",
    "sg:tags":[
        "upholsterer"
    ],
    "wof:name":"Lloyd Upholstery",
    "wof:placetype":"venue"
},
  "geometry": {"coordinates":[-2.0987989902,52.681060791],"type":"Point"}
}