{
  "type": "Feature",
  "properties": {
    "iso:country":"GB",
    "sg:address":"Low Plains Farm, Armathwaite",
    "sg:city":"Carlisle",
    "sg:classifiers":[
        {
            "category":"Home & Garden",
            "subcategory":"Garden Supply",
            "type":"Retail Goods"
        },
        {
            "category":"Farming",
            "subcategory":"Farm",
            "type":"Manufacturing & Wholesale Goods"
        }
    ],
    "sg:phone":"+44 1768 885251",
    "sg:postcode":"CA4 9TR",
    "sg:province":"Cumbria",
    "sg:tags":[
        "mixed",
        "bulb",
        "crop",
        "grower"
    ],
    "wof:name":"M & E M Bowe",
    "wof:placetype":"venue"
},
  "geometry": {"coordinates":[-2.7708389759,54.8069458008],"type":"Point"}
}