{
  "type": "Feature",
  "properties": {
    "iso:country":"GB",
    "sg:address":"5 Creek Road",
    "sg:city":"East Molesey",
    "sg:classifiers":[
        {
            "category":"Fast Food",
            "type":"Food & Drink"
        }
    ],
    "sg:postcode":"KT8 9BE",
    "sg:province":"Greater London",
    "sg:tags":[
        "away",
        "take"
    ],
    "wof:name":"King,Nadia,",
    "wof:placetype":"venue"
},
  "geometry": {"coordinates":[-0.3435840011,51.4027481079],"type":"Point"}
}