{
  "type": "Feature",
  "properties": {
    "iso:country":"GB",
    "sg:address":"80 Sedgefield Crescent, Harold Hill",
    "sg:city":"Romford",
    "sg:classifiers":[
        {
            "category":"Building & Trades",
            "subcategory":"Construction",
            "type":"Services"
        }
    ],
    "sg:postcode":"RM3 9RL",
    "sg:province":"Essex",
    "sg:tags":[
        "bricklaying"
    ],
    "wof:name":"N L Blake",
    "wof:placetype":"venue"
},
  "geometry": {"coordinates":[0.233285,51.610424],"type":"Point"}
}