{
  "type": "Feature",
  "properties": {
    "iso:country":"GB",
    "sg:address":"120-124 Thatto Heath Road",
    "sg:city":"St Helens",
    "sg:classifiers":[
        {
            "category":"Shopping",
            "subcategory":"Shoes",
            "type":"Retail Goods"
        }
    ],
    "sg:postcode":"WA9 5PE",
    "sg:province":"Cheshire",
    "wof:name":"Thatto Heath Shoe Repairs",
    "wof:placetype":"venue"
},
  "geometry": {"coordinates":[-2.758962,53.436737],"type":"Point"}
}