{
  "type": "Feature",
  "properties": {
    "iso:country":"GB",
    "sg:address":"41-42 Castle Market",
    "sg:city":"Sheffield",
    "sg:classifiers":[
        {
            "category":"Food & Beverages",
            "subcategory":"Fruits & Vegetables",
            "type":"Retail Goods"
        }
    ],
    "sg:phone":"+44 114 272 1788",
    "sg:postcode":"S1 2AG",
    "sg:province":"South Yorkshire",
    "sg:tags":[
        "greengrocer"
    ],
    "wof:name":"Bingham & Browne",
    "wof:placetype":"venue"
},
  "geometry": {"coordinates":[-1.465615,53.383099],"type":"Point"}
}