{
  "type": "Feature",
  "properties": {
    "addr:full":"Lower St Andrews Wood Farm, Kentisbeare Cullompton Devon EX15 2DF",
    "addr:postcode":"ex15 2df",
    "addr:street":"Lower St",
    "iso:country":"GB",
    "sg:address":"Lower St Andrews Wood Farm, Kentisbeare",
    "sg:city":"Cullompton",
    "sg:classifiers":[
        {
            "category":"Farming",
            "subcategory":"Livestock Farm",
            "type":"Manufacturing & Wholesale Goods"
        }
    ],
    "sg:phone":"+44 1884 266274",
    "sg:postcode":"EX15 2DF",
    "sg:province":"Devon",
    "sg:tags":[
        "others"
    ],
    "wof:name":"L A Shere",
    "wof:placetype":"venue"
},
  "geometry": {"coordinates":[-3.3281359673,50.865486145],"type":"Point"}
}