{
  "type": "Feature",
  "properties": {
    "iso:country":"GB",
    "sg:address":"15a Union Street",
    "sg:city":"Edinburgh",
    "sg:classifiers":[
        {
            "category":"Professional",
            "subcategory":"Management & Consulting",
            "type":"Services"
        }
    ],
    "sg:postcode":"EH1 3LT",
    "sg:province":"City of Edinburgh",
    "sg:tags":[
        "consultant",
        "business"
    ],
    "wof:name":"Fazakerley Associates",
    "wof:placetype":"venue"
},
  "geometry": {"coordinates":[-3.185968,55.958015],"type":"Point"}
}