{
  "type": "Feature",
  "properties": {
    "iso:country":"GB",
    "sg:address":"3 New Street, Oundle",
    "sg:city":"Peterborough",
    "sg:classifiers":[
        {
            "category":"Shopping",
            "subcategory":"Gifts & Souvenirs",
            "type":"Retail Goods"
        }
    ],
    "sg:phone":"+44 1832 274467",
    "sg:postcode":"PE8 4EA",
    "sg:province":"Cambridgeshire",
    "sg:tags":[
        "shop"
    ],
    "wof:name":"Crackers",
    "wof:placetype":"venue"
},
  "geometry": {"coordinates":[-0.468877,52.480995],"type":"Point"}
}