{
  "type": "Feature",
  "properties": {
    "addr:full":"1 Janefield Avenue Dumfries Dumfries and Galloway DG2 7PZ",
    "addr:housenumber":"1",
    "addr:postcode":"dg2 7pz",
    "addr:street":"Janefield Avenue",
    "iso:country":"GB",
    "sg:address":"1 Janefield Avenue",
    "sg:city":"Dumfries",
    "sg:classifiers":[
        {
            "category":"Building & Trades",
            "subcategory":"Cleaning & Sanitation",
            "type":"Services"
        }
    ],
    "sg:postcode":"DG2 7PZ",
    "sg:province":"Dumfries and Galloway",
    "sg:tags":[
        "cleaner",
        "window"
    ],
    "wof:name":"Thomas Maclagan Window Cleaning Services",
    "wof:placetype":"venue"
},
  "geometry": {"coordinates":[-3.6250240803,55.0618629456],"type":"Point"}
}