{
  "type": "Feature",
  "properties": {
    "addr:full":"50 Wallasea Gardens Chelmsford Essex CM1 6JZ",
    "addr:housenumber":"50",
    "addr:postcode":"cm1 6jz",
    "addr:street":"Wallasea Gardens",
    "iso:country":"GB",
    "sg:address":"50 Wallasea Gardens",
    "sg:city":"Chelmsford",
    "sg:classifiers":[
        {
            "category":"Organizations",
            "subcategory":"Membership Organization",
            "type":"Services"
        }
    ],
    "sg:phone":"+44 1245 267352",
    "sg:postcode":"CM1 6JZ",
    "sg:province":"Essex",
    "sg:tags":[
        "club"
    ],
    "wof:name":"Eighteen Plus",
    "wof:placetype":"venue"
},
  "geometry": {"coordinates":[0.497895,51.745796],"type":"Point"}
}