{
  "type": "Feature",
  "properties": {
    "addr:full":"Dock Road South, Wirrel Intl Bussiness Park Wirral Cheshire CH62 4SQ",
    "addr:postcode":"ch62 4sq",
    "addr:street":"Dock Road South Wirrel;Bussiness Park",
    "iso:country":"GB",
    "sg:address":"Dock Road South, Wirrel Intl Bussiness Park",
    "sg:city":"Wirral",
    "sg:classifiers":[
        {
            "category":"Professional",
            "subcategory":"Computer Services",
            "type":"Services"
        }
    ],
    "sg:phone":"+44 151 343 0200",
    "sg:postcode":"CH62 4SQ",
    "sg:province":"Cheshire",
    "sg:tags":[
        "system",
        "software"
    ],
    "wof:name":"Parity Computers Ltd.",
    "wof:placetype":"venue"
},
  "geometry": {"coordinates":[-2.985806942,53.3559989929],"type":"Point"}
}