{
  "type": "Feature",
  "properties": {
    "iso:country":"GB",
    "sg:address":"18 Twyford Way",
    "sg:city":"Poole",
    "sg:classifiers":[
        {
            "category":"Building & Trades",
            "subcategory":"Construction",
            "type":"Services"
        }
    ],
    "sg:phone":"+44 1202 385887",
    "sg:postcode":"BH17 8BL",
    "sg:province":"Dorset",
    "sg:tags":[
        "bricklayer",
        "bricklaying"
    ],
    "wof:name":"D S Baxter",
    "wof:placetype":"venue"
},
  "geometry": {"coordinates":[-1.953033,50.751755],"type":"Point"}
}