{
  "type": "Feature",
  "properties": {
    "addr:full":"82 Centre Street Glasgow Glasgow City G5 8EE",
    "addr:housenumber":"82",
    "addr:postcode":"g5 8ee",
    "addr:street":"Centre Street",
    "iso:country":"GB",
    "sg:address":"82 Centre Street",
    "sg:city":"Glasgow",
    "sg:classifiers":[
        {
            "category":"Wholesale",
            "subcategory":"Sporting Goods",
            "type":"Manufacturing & Wholesale Goods"
        }
    ],
    "sg:postcode":"G5 8EE",
    "sg:province":"Glasgow City",
    "sg:tags":[
        "mnfr",
        "sport",
        "equipment"
    ],
    "wof:name":"G C C (U K) Ltd",
    "wof:placetype":"venue"
},
  "geometry": {"coordinates":[-4.262339,55.852623],"type":"Point"}
}