{
  "type": "Feature",
  "properties": {
    "addr:full":"133 Rawlinson Street Barrow-in-furness Cumbria LA14 2DN",
    "addr:housenumber":"133",
    "addr:postcode":"la14 2dn",
    "addr:street":"Rawlinson Street",
    "iso:country":"GB",
    "sg:address":"133 Rawlinson Street",
    "sg:city":"Barrow-in-furness",
    "sg:classifiers":[
        {
            "category":"Retail",
            "subcategory":"Auto Repair",
            "type":"Services"
        }
    ],
    "sg:postcode":"LA14 2DN",
    "sg:province":"Cumbria",
    "sg:tags":[
        "modification",
        "garage"
    ],
    "wof:name":"W J Maddrick",
    "wof:placetype":"venue"
},
  "geometry": {"coordinates":[-3.2204051018,54.1118392944],"type":"Point"}
}