{
  "type": "Feature",
  "properties": {
    "iso:country":"GB",
    "sg:address":"399 Roman Road, Bow",
    "sg:city":"London",
    "sg:classifiers":[
        {
            "category":"Utilities",
            "subcategory":"Natural Gas",
            "type":"Services"
        }
    ],
    "sg:postcode":"E3 5QS",
    "sg:province":"Greater London",
    "sg:tags":[
        "supplier"
    ],
    "wof:name":"Always Call Global Gases",
    "wof:placetype":"venue"
},
  "geometry": {"coordinates":[-0.037325,51.531609],"type":"Point"}
}