{
  "type": "Feature",
  "properties": {
    "addr:full":"8 Richmond Close Sale Cheshire M33 2PX",
    "addr:housenumber":"8",
    "addr:postcode":"m33 2px",
    "addr:street":"Richmond Close",
    "iso:country":"GB",
    "sg:address":"8 Richmond Close",
    "sg:city":"Sale",
    "sg:classifiers":[
        {
            "category":"Retail",
            "subcategory":"Driving School",
            "type":"Services"
        }
    ],
    "sg:postcode":"M33 2PX",
    "sg:province":"Cheshire",
    "wof:name":"A1 Apollo Driving Tuition",
    "wof:placetype":"venue"
},
  "geometry": {"coordinates":[-2.2909610271,53.4191703796],"type":"Point"}
}