{
  "type": "Feature",
  "properties": {
    "iso:country":"GB",
    "sg:address":"36 The Byway",
    "sg:city":"Darlington",
    "sg:classifiers":[
        {
            "category":"Manufacturing",
            "subcategory":"Metals",
            "type":"Manufacturing & Wholesale Goods"
        },
        {
            "category":"Retail",
            "subcategory":"Driving School",
            "type":"Services"
        }
    ],
    "sg:phone":"+44 1325 467478",
    "sg:postcode":"DL1 1EQ",
    "sg:province":"Durham",
    "sg:tags":[
        "steel",
        "fabricator",
        "erectors"
    ],
    "wof:name":"Carole's School of Motoring",
    "wof:placetype":"venue"
},
  "geometry": {"coordinates":[-1.526479,54.524097],"type":"Point"}
}