{
  "type": "Feature",
  "properties": {
    "iso:country":"GB",
    "sg:address":"311 Great Western Street",
    "sg:city":"Manchester",
    "sg:classifiers":[
        {
            "category":"Food & Beverages",
            "subcategory":"Meat & Fish",
            "type":"Retail Goods"
        }
    ],
    "sg:phone":"+44 161 256 3884",
    "sg:postcode":"M14 4BZ",
    "sg:province":"Greater Manchester",
    "sg:tags":[
        "chip"
    ],
    "wof:name":"Mei Mei",
    "wof:placetype":"venue"
},
  "geometry": {"coordinates":[-2.231301,53.456448],"type":"Point"}
}