{
  "type": "Feature",
  "properties": {
    "iso:country":"GB",
    "sg:address":"Foxley Manor, Forest Green Road",
    "sg:city":"Maidenhead",
    "sg:classifiers":[
        {
            "category":"Real Estate",
            "subcategory":"Architect",
            "type":"Services"
        }
    ],
    "sg:postcode":"SL6 2NW",
    "sg:province":"Berkshire",
    "wof:name":"Christopher Chapman Associates Ltd.",
    "wof:placetype":"venue"
},
  "geometry": {"coordinates":[-0.693734,51.478115],"type":"Point"}
}