{
  "type": "Feature",
  "properties": {
    "iso:country":"GB",
    "sg:address":"204 Woodhead Road, Holmbridge",
    "sg:city":"Huddersfield",
    "sg:classifiers":[
        {
            "category":"Recreation",
            "subcategory":"Dog Park",
            "type":"Entertainment"
        }
    ],
    "sg:phone":"+44 1226 792636",
    "sg:postcode":"HD9 2NL",
    "sg:province":"South Yorkshire",
    "wof:name":"Newlaithe Boxers",
    "wof:placetype":"venue"
},
  "geometry": {"coordinates":[-1.818373,53.557934],"type":"Point"}
}