{
  "type": "Feature",
  "properties": {
    "addr:full":"Strauss House, 41-45 Goswell Road London Greater London EC1V 7EH",
    "addr:housenumber":"41-45",
    "addr:postcode":"ec1v 7eh",
    "addr:street":"Goswell Road",
    "iso:country":"GB",
    "sg:address":"Strauss House, 41-45 Goswell Road",
    "sg:city":"London",
    "sg:classifiers":[
        {
            "category":"Professional",
            "subcategory":"Management & Consulting",
            "type":"Services"
        },
        {
            "category":"Recreation",
            "subcategory":"Gun Range",
            "type":"Entertainment"
        }
    ],
    "sg:postcode":"EC1V 7EH",
    "sg:province":"Greater London",
    "sg:tags":[
        "operator",
        "marketing",
        "tour",
        "consultant"
    ],
    "wof:name":"Destination Marketing Ltd.",
    "wof:placetype":"venue"
},
  "geometry": {"coordinates":[-0.0990649983,51.5238838196],"type":"Point"}
}