{
  "type": "Feature",
  "properties": {
    "addr:full":"253 Deerlands Avenue Sheffield South Yorkshire S5 7WW",
    "addr:housenumber":"253",
    "addr:postcode":"s5 7ww",
    "addr:street":"Deerlands Avenue",
    "iso:country":"GB",
    "sg:address":"253 Deerlands Avenue",
    "sg:city":"Sheffield",
    "sg:classifiers":[
        {
            "category":"Retail",
            "subcategory":"Auto Repair",
            "type":"Services"
        }
    ],
    "sg:phone":"+44 114 240 1182",
    "sg:postcode":"S5 7WW",
    "sg:province":"South Yorkshire",
    "sg:tags":[
        "engine",
        "car",
        "specialist"
    ],
    "wof:name":"Andrew C Hobson",
    "wof:placetype":"venue"
},
  "geometry": {"coordinates":[-1.474722,53.427013],"type":"Point"}
}