{
  "type": "Feature",
  "properties": {
    "addr:full":"107 Boldon Lane South Shields Tyne and Wear NE34 0AS",
    "addr:housenumber":"107",
    "addr:postcode":"ne34 0as",
    "addr:street":"Boldon Lane",
    "iso:country":"GB",
    "sg:address":"107 Boldon Lane",
    "sg:city":"South Shields",
    "sg:classifiers":[
        {
            "category":"Building & Trades",
            "subcategory":"Construction",
            "type":"Services"
        }
    ],
    "sg:phone":"+44 191 455 3924",
    "sg:postcode":"NE34 0AS",
    "sg:province":"Tyne and Wear",
    "sg:tags":[
        "glazier"
    ],
    "wof:name":"D J Glazier",
    "wof:placetype":"venue"
},
  "geometry": {"coordinates":[-1.439609,54.972515],"type":"Point"}
}