{
  "type": "Feature",
  "properties": {
    "iso:country":"GB",
    "sg:address":"199 Springthorpe Road, Erdington",
    "sg:city":"Birmingham",
    "sg:classifiers":[
        {
            "category":"Shopping",
            "subcategory":"Hobbies, Toys, & Games",
            "type":"Retail Goods"
        },
        {
            "category":"Military Area",
            "subcategory":"Air Force Base",
            "type":"Public Place"
        }
    ],
    "sg:phone":"+44 121 373 2020",
    "sg:postcode":"B24 0SJ",
    "sg:province":"West Midlands",
    "sg:tags":[
        "coin",
        "medal"
    ],
    "wof:name":"March Medals",
    "wof:placetype":"venue"
},
  "geometry": {"coordinates":[-1.814432025,52.526008606],"type":"Point"}
}