{
  "type": "Feature",
  "properties": {
    "addr:full":"30 Lansdown Pl Lewes East Sussex BN7 2JU",
    "addr:housenumber":"30",
    "addr:postcode":"bn7 2ju",
    "addr:street":"Lansdown Pl",
    "iso:country":"GB",
    "sg:address":"30 Lansdown Pl",
    "sg:city":"Lewes",
    "sg:classifiers":[
        {
            "category":"Building & Trades",
            "subcategory":"Cleaning & Sanitation",
            "type":"Services"
        }
    ],
    "sg:phone":"+44 1273 471236",
    "sg:postcode":"BN7 2JU",
    "sg:province":"East Sussex",
    "sg:tags":[
        "sweep",
        "chimney"
    ],
    "wof:name":"Brighton Hove & Lewes Chimney Services",
    "wof:placetype":"venue"
},
  "geometry": {"coordinates":[0.0116659999,50.8719711304],"type":"Point"}
}