{
  "type": "Feature",
  "properties": {
    "addr:full":"Unit 11 Whitehall Farm Hertford Hertfordshire SG14 3RP",
    "addr:housenumber":"unit 11",
    "addr:postcode":"sg14 3rp",
    "addr:street":"Whitehall Farm Hertford",
    "iso:country":"GB",
    "sg:address":"Unit 11 Whitehall Farm",
    "sg:city":"Hertford",
    "sg:classifiers":[
        {
            "category":"Wholesale",
            "subcategory":"Construction Materials",
            "type":"Manufacturing & Wholesale Goods"
        }
    ],
    "sg:phone":"+44 1920 831066",
    "sg:postcode":"SG14 3RP",
    "sg:province":"Hertfordshire",
    "sg:tags":[
        "distributor",
        "spring"
    ],
    "wof:name":"Coiltech Ltd.",
    "wof:placetype":"venue"
},
  "geometry": {"coordinates":[-0.082699,51.796341],"type":"Point"}
}