{
  "type": "Feature",
  "properties": {
    "iso:country":"GB",
    "sg:address":"171 Redland Rd",
    "sg:city":"Bristol",
    "sg:classifiers":[
        {
            "category":"Health Services",
            "subcategory":"Nursing And Care Facility",
            "type":"Services"
        }
    ],
    "sg:phone":"+44 117 973 9086",
    "sg:postcode":"BS6 6YE",
    "sg:province":"City of Bristol",
    "sg:tags":[
        "home"
    ],
    "wof:name":"Manor House Nursing Home",
    "wof:placetype":"venue"
},
  "geometry": {"coordinates":[-2.6005890369,51.4625511169],"type":"Point"}
}