{
  "type": "Feature",
  "properties": {
    "iso:country":"GB",
    "sg:address":"Sudbury Road, Little Whelnetham",
    "sg:city":"Bury St Edmunds",
    "sg:classifiers":[
        {
            "category":"Professional",
            "subcategory":"Engineering",
            "type":"Services"
        }
    ],
    "sg:phone":"+44 1284 386555",
    "sg:postcode":"IP30 0UL",
    "sg:province":"Suffolk",
    "wof:name":"Blyth & Pawsey Ltd.",
    "wof:placetype":"venue"
},
  "geometry": {"coordinates":[0.7600089908,52.2003173828],"type":"Point"}
}