{
  "type": "Feature",
  "properties": {
    "iso:country":"GB",
    "sg:address":"9 George Street",
    "sg:city":"Glossop",
    "sg:classifiers":[
        {
            "category":"Personal",
            "subcategory":"Sauna",
            "type":"Services"
        }
    ],
    "sg:phone":"+44 1457 861216",
    "sg:postcode":"SK13 8AY",
    "sg:province":"Derbyshire",
    "sg:tags":[
        "equipment",
        "sunbed"
    ],
    "wof:name":"Health Mate (U K) Ltd.",
    "wof:placetype":"venue"
},
  "geometry": {"coordinates":[-1.9523580074,53.4432106018],"type":"Point"}
}