{
  "type": "Feature",
  "properties": {
    "iso:country":"GB",
    "sg:address":"57 Cable Road",
    "sg:city":"Wirral",
    "sg:classifiers":[
        {
            "category":"Health Services",
            "subcategory":"Nursing And Care Facility",
            "type":"Services"
        },
        {
            "category":"Social Services",
            "subcategory":"Retirement Home",
            "type":"Services"
        },
        {
            "category":"Government",
            "subcategory":"Office",
            "type":"Public Place"
        }
    ],
    "sg:phone":"+44 151 632 5064",
    "sg:postcode":"CH47 2AZ",
    "sg:province":"Merseyside",
    "sg:tags":[
        "residential",
        "central"
    ],
    "wof:name":"Hollies Residential Home",
    "wof:placetype":"venue"
},
  "geometry": {"coordinates":[-3.182098,53.393723],"type":"Point"}
}