{
  "type": "Feature",
  "properties": {
    "iso:country":"GB",
    "sg:address":"428 Foleshill Road",
    "sg:city":"Coventry",
    "sg:classifiers":[
        {
            "category":"Shopping",
            "subcategory":"Pharmacy",
            "type":"Retail Goods"
        }
    ],
    "sg:phone":"+44 24 7668 8384",
    "sg:postcode":"CV6 5JX",
    "sg:province":"Warwickshire",
    "sg:tags":[
        "pharmacist",
        "chemist"
    ],
    "wof:name":"J S Dhaliwal Dispensing Chemist",
    "wof:placetype":"venue"
},
  "geometry": {"coordinates":[-1.498244,52.429588],"type":"Point"}
}