{
  "type": "Feature",
  "properties": {
    "addr:full":"The Kingsfold Garage, Dorking Rd Horsham West Sussex RH12 3SB",
    "addr:postcode":"rh12 3sb",
    "addr:street":"Dorking Rd",
    "iso:country":"GB",
    "sg:address":"The Kingsfold Garage, Dorking Rd",
    "sg:city":"Horsham",
    "sg:classifiers":[
        {
            "category":"Retail",
            "subcategory":"Auto Repair",
            "type":"Services"
        },
        {
            "category":"Real Estate",
            "subcategory":"Architect",
            "type":"Services"
        }
    ],
    "sg:postcode":"RH12 3SB",
    "sg:province":"West Sussex",
    "sg:tags":[
        "modification",
        "garage"
    ],
    "wof:name":"Crombie,Andy,",
    "wof:placetype":"venue"
},
  "geometry": {"coordinates":[-0.3291069865,51.0651817322],"type":"Point"}
}