{
  "type": "Feature",
  "properties": {
    "iso:country":"GB",
    "sg:address":"3 Lorne Street",
    "sg:city":"Lytham St Annes",
    "sg:classifiers":[
        {
            "category":"Professional",
            "subcategory":"Engineering",
            "type":"Services"
        }
    ],
    "sg:phone":"+44 1253 735567",
    "sg:postcode":"FY8 5BU",
    "sg:province":"Lancashire",
    "sg:tags":[
        "contractor",
        "electrical",
        "engineer"
    ],
    "wof:name":"Booker Associates Ltd.",
    "wof:placetype":"venue"
},
  "geometry": {"coordinates":[-2.94787,53.740459],"type":"Point"}
}