{
  "type": "Feature",
  "properties": {
    "addr:full":"33 Bannister Close Greenford Greater London UB6 0SW",
    "addr:housenumber":"33",
    "addr:postcode":"ub6 0sw",
    "addr:street":"Bannister Close",
    "iso:country":"GB",
    "sg:address":"33 Bannister Close",
    "sg:city":"Greenford",
    "sg:classifiers":[
        {
            "category":"Building & Trades",
            "subcategory":"Cleaning & Sanitation",
            "type":"Services"
        }
    ],
    "sg:postcode":"UB6 0SW",
    "sg:province":"Greater London",
    "sg:tags":[
        "commercial"
    ],
    "wof:name":"General Cleaning & Maintenance Services",
    "wof:placetype":"venue"
},
  "geometry": {"coordinates":[-0.346442,51.556347],"type":"Point"}
}