{
  "type": "Feature",
  "properties": {
    "iso:country":"GB",
    "sg:address":"7 Digbeth",
    "sg:city":"Walsall",
    "sg:classifiers":[
        {
            "category":"Food & Beverages",
            "subcategory":"Meat & Fish",
            "type":"Retail Goods"
        }
    ],
    "sg:phone":"+44 1922 621943",
    "sg:postcode":"WS1 1QZ",
    "sg:province":"West Midlands",
    "sg:tags":[
        "butcher"
    ],
    "wof:name":"Midland Meat",
    "wof:placetype":"venue"
},
  "geometry": {"coordinates":[-1.9810340405,52.5836982727],"type":"Point"}
}