{
  "type": "Feature",
  "properties": {
    "iso:country":"GB",
    "sg:address":"69 Garnet Street",
    "sg:city":"London",
    "sg:classifiers":[
        {
            "category":"Food & Beverages",
            "subcategory":"Liquor & Beverages",
            "type":"Retail Goods"
        }
    ],
    "sg:phone":"+44 20 7481 4019",
    "sg:postcode":"E1 9QT",
    "sg:province":"Greater London",
    "sg:tags":[
        "beer",
        "spirit",
        "wines"
    ],
    "wof:name":"Fuller Smith & Turner",
    "wof:placetype":"venue"
},
  "geometry": {"coordinates":[-0.0543019995,51.505897522],"type":"Point"}
}