{
  "type": "Feature",
  "properties": {
    "iso:country":"GB",
    "sg:address":"23 Star Road, Partridge Grn",
    "sg:city":"Horsham",
    "sg:classifiers":[
        {
            "category":"Professional",
            "subcategory":"Printing & Photocopies",
            "type":"Services"
        }
    ],
    "sg:postcode":"RH13 8RA",
    "sg:province":"West Sussex",
    "sg:tags":[
        "printer"
    ],
    "wof:name":"Claremont Press Ltd.",
    "wof:placetype":"venue"
},
  "geometry": {"coordinates":[-0.3051809967,50.9573402405],"type":"Point"}
}