{
  "type": "Feature",
  "properties": {
    "addr:full":"2-4 Upper Tollington Park London Greater London N4 3EL",
    "addr:housenumber":"2-4",
    "addr:postcode":"n4 3el",
    "addr:street":"Upper Tollington Park",
    "iso:country":"GB",
    "sg:address":"2-4 Upper Tollington Park",
    "sg:city":"London",
    "sg:classifiers":[
        {
            "category":"Taxi",
            "type":"Transportation"
        }
    ],
    "sg:phone":"+44 20 8292 4141",
    "sg:postcode":"N4 3EL",
    "sg:province":"Greater London",
    "sg:tags":[
        "mini",
        "cab"
    ],
    "wof:name":"Paphos Cars",
    "wof:placetype":"venue"
},
  "geometry": {"coordinates":[-0.10966,51.56926],"type":"Point"}
}