{
  "type": "Feature",
  "properties": {
    "addr:full":"Enquiries, Mountfield Road Lewes East Sussex BN7 2XG",
    "addr:postcode":"bn7 2xg",
    "addr:street":"Mountfield Road",
    "iso:country":"GB",
    "sg:address":"Enquiries, Mountfield Road",
    "sg:city":"Lewes",
    "sg:classifiers":[
        {
            "category":"Community Center",
            "type":"Public Place"
        },
        {
            "category":"Government",
            "subcategory":"Office",
            "type":"Public Place"
        }
    ],
    "sg:phone":"+44 1273 486000",
    "sg:postcode":"BN7 2XG",
    "sg:province":"East Sussex",
    "sg:tags":[
        "recreation",
        "local",
        "leisure",
        "centre"
    ],
    "wof:name":"Lewes Leisure Centre",
    "wof:placetype":"venue"
},
  "geometry": {"coordinates":[0.01062,50.873203],"type":"Point"}
}