{
  "type": "Feature",
  "properties": {
    "addr:full":"Ravenside Retail & Leisure Park Bexhill On Sea East Sussex TN40 2JS",
    "addr:postcode":"tn40 2js",
    "addr:street":"Park",
    "iso:country":"GB",
    "sg:address":"Ravenside Retail & Leisure Park",
    "sg:city":"Bexhill On Sea",
    "sg:classifiers":[
        {
            "category":"Home & Garden",
            "subcategory":"Household Appliances",
            "type":"Retail Goods"
        }
    ],
    "sg:phone":"+44 1424 733550",
    "sg:postcode":"TN40 2JS",
    "sg:province":"East Sussex",
    "sg:tags":[
        "electrical",
        "domestic"
    ],
    "wof:name":"Seeboard Superstores",
    "wof:placetype":"venue"
},
  "geometry": {"coordinates":[0.49957,50.844341],"type":"Point"}
}