{
  "type": "Feature",
  "properties": {
    "iso:country":"GB",
    "sg:address":"17 William Street",
    "sg:city":"Windsor",
    "sg:classifiers":[
        {
            "category":"Retail",
            "subcategory":"Photofinishing",
            "type":"Services"
        }
    ],
    "sg:phone":"+44 1753 859111",
    "sg:postcode":"SL4 1BB",
    "sg:province":"Berkshire",
    "sg:tags":[
        "photographic",
        "processor"
    ],
    "wof:name":"Gretag Imaging U K Ltd.",
    "wof:placetype":"venue"
},
  "geometry": {"coordinates":[-0.610592,51.480522],"type":"Point"}
}