{
  "type": "Feature",
  "properties": {
    "addr:full":"1 Collingwood Houses, Front St North Shields Tyne and Wear NE29 0LA",
    "addr:housenumber":"1",
    "addr:postcode":"ne29 0la",
    "addr:street":"Collingwood Houses Front St",
    "iso:country":"GB",
    "sg:address":"1 Collingwood Houses, Front St",
    "sg:city":"North Shields",
    "sg:classifiers":[
        {
            "category":"Food & Beverages",
            "subcategory":"Fruits & Vegetables",
            "type":"Retail Goods"
        }
    ],
    "sg:phone":"+44 191 296 3100",
    "sg:postcode":"NE29 0LA",
    "sg:province":"Tyne and Wear",
    "sg:tags":[
        "greengrocer"
    ],
    "wof:name":"Lindy's Fruit Bowl",
    "wof:placetype":"venue"
},
  "geometry": {"coordinates":[-1.4612400532,55.0084991455],"type":"Point"}
}