{
  "type": "Feature",
  "properties": {
    "addr:full":"Hannah Way, Gordleton Industrial Park Lymington Hampshire SO41 8JD",
    "addr:postcode":"so41 8jd",
    "addr:street":"Hannah Way Gordleton Industrial Park",
    "iso:country":"GB",
    "sg:address":"Hannah Way, Gordleton Industrial Park",
    "sg:city":"Lymington",
    "sg:classifiers":[
        {
            "category":"Food & Beverages",
            "subcategory":"Supermarket",
            "type":"Retail Goods"
        }
    ],
    "sg:phone":"+44 1590 683988",
    "sg:postcode":"SO41 8JD",
    "sg:province":"Hampshire",
    "sg:tags":[
        "frozen"
    ],
    "wof:name":"Express Products Ltd.",
    "wof:placetype":"venue"
},
  "geometry": {"coordinates":[-1.538911,50.758938],"type":"Point"}
}