{
  "type": "Feature",
  "properties": {
    "iso:country":"GB",
    "sg:address":"Elizabeth House, Frances Rd",
    "sg:city":"Basingstoke",
    "sg:classifiers":[
        {
            "category":"Professional",
            "subcategory":"Printing & Photocopies",
            "type":"Services"
        }
    ],
    "sg:phone":"+44 1256 869646",
    "sg:postcode":"RG21 3DB",
    "sg:province":"Hampshire",
    "sg:tags":[
        "t-shirt"
    ],
    "wof:name":"D B Printing",
    "wof:placetype":"venue"
},
  "geometry": {"coordinates":[-1.092389,51.260578],"type":"Point"}
}