{
  "type": "Feature",
  "properties": {
    "iso:country":"GB",
    "sg:address":"281 Aldridge Road, Perry Barr",
    "sg:city":"Birmingham",
    "sg:classifiers":[
        {
            "category":"Food & Beverages",
            "subcategory":"Liquor & Beverages",
            "type":"Retail Goods"
        }
    ],
    "sg:phone":"+44 121 331 1233",
    "sg:postcode":"B42 2EY",
    "sg:province":"West Midlands",
    "sg:tags":[
        "beer",
        "spirit",
        "wines"
    ],
    "wof:name":"Perry Park News",
    "wof:placetype":"venue"
},
  "geometry": {"coordinates":[-1.897205,52.527008],"type":"Point"}
}