{
  "type": "Feature",
  "properties": {
    "iso:country":"GB",
    "sg:address":"23 Bobbin Lane, Westwood",
    "sg:city":"Bradford-on-avon",
    "sg:classifiers":[
        {
            "category":"Organizations",
            "subcategory":"Non-profit Organization",
            "type":"Services"
        }
    ],
    "sg:phone":"+44 1225 863114",
    "sg:postcode":"BA15 2DL",
    "sg:province":"Wiltshire",
    "sg:tags":[
        "charitable",
        "organisation",
        "voluntary",
        "charity"
    ],
    "wof:name":"LEUKAEMIA RESEARCH FUND LTD",
    "wof:placetype":"venue"
},
  "geometry": {"coordinates":[-2.278936,51.335175],"type":"Point"}
}