{
  "type": "Feature",
  "properties": {
    "iso:country":"GB",
    "sg:address":"Scope Ho, Weston Rd",
    "sg:city":"Crewe",
    "sg:classifiers":[
        {
            "category":"Professional",
            "subcategory":"Management & Consulting",
            "type":"Services"
        },
        {
            "category":"Shopping",
            "subcategory":"Mobile Phones",
            "type":"Retail Goods"
        }
    ],
    "sg:postcode":"CW1 6DD",
    "sg:province":"Cheshire",
    "sg:tags":[
        "consultant"
    ],
    "wof:name":"Sequence Communications Ltd",
    "wof:placetype":"venue"
},
  "geometry": {"coordinates":[-2.446105,53.100578],"type":"Point"}
}