{
  "type": "Feature",
  "properties": {
    "addr:full":"1 Station Road, Purton Swindon Wiltshire SN5 4AQ",
    "addr:housenumber":"1",
    "addr:postcode":"sn5 4aq",
    "addr:street":"Station Road",
    "iso:country":"GB",
    "sg:address":"1 Station Road, Purton",
    "sg:city":"Swindon",
    "sg:classifiers":[
        {
            "category":"Shopping",
            "subcategory":"Department Store",
            "type":"Retail Goods"
        }
    ],
    "sg:phone":"+44 1793 770775",
    "sg:postcode":"SN5 4AQ",
    "sg:province":"Wiltshire",
    "wof:name":"Harford House Store",
    "wof:placetype":"venue"
},
  "geometry": {"coordinates":[-1.866,51.588551],"type":"Point"}
}