{
  "type": "Feature",
  "properties": {
    "iso:country":"GB",
    "sg:address":"13 The Wynd, Marske By The Sea",
    "sg:city":"Redcar",
    "sg:classifiers":[
        {
            "category":"Home & Garden",
            "subcategory":"Household Appliances",
            "type":"Retail Goods"
        }
    ],
    "sg:phone":"+44 1642 477414",
    "sg:postcode":"TS11 7LD",
    "sg:province":"North Yorkshire",
    "sg:tags":[
        "electrical"
    ],
    "wof:name":"The Electric Shop",
    "wof:placetype":"venue"
},
  "geometry": {"coordinates":[-1.0184019804,54.5919036865],"type":"Point"}
}