{
  "type": "Feature",
  "properties": {
    "addr:full":"1 High Street, Lewknor Watlington Oxfordshire OX49 5TW",
    "addr:housenumber":"1",
    "addr:postcode":"ox49 5tw",
    "addr:street":"High Street",
    "iso:country":"GB",
    "sg:address":"1 High Street, Lewknor",
    "sg:city":"Watlington",
    "sg:classifiers":[
        {
            "category":"Bars & Pubs",
            "type":"Food & Drink"
        }
    ],
    "sg:postcode":"OX49 5TW",
    "sg:province":"Oxfordshire",
    "sg:tags":[
        "pubs",
        "inn"
    ],
    "wof:name":"Leathern Bottle",
    "wof:placetype":"venue"
},
  "geometry": {"coordinates":[-0.9680960178,51.6720314026],"type":"Point"}
}