{
  "type": "Feature",
  "properties": {
    "addr:full":"861a Ashton New Road Manchester Greater Manchester M11 4PA",
    "addr:housenumber":"861a",
    "addr:postcode":"m11 4pa",
    "addr:street":"Ashton New Road",
    "iso:country":"GB",
    "sg:address":"861a Ashton New Road",
    "sg:city":"Manchester",
    "sg:classifiers":[
        {
            "category":"Shopping",
            "subcategory":"Pharmacy",
            "type":"Retail Goods"
        }
    ],
    "sg:phone":"+44 161 370 9227",
    "sg:postcode":"M11 4PA",
    "sg:province":"Greater Manchester",
    "sg:tags":[
        "pharmacist",
        "dispensing",
        "chemist"
    ],
    "wof:name":"Cohens Chemist",
    "wof:placetype":"venue"
},
  "geometry": {"coordinates":[-2.1834840775,53.4831962585],"type":"Point"}
}