{
  "type": "Feature",
  "properties": {
    "addr:full":"Coulton House, Coulton Avenue Gravesend Kent DA11 8DY",
    "addr:housenumber":"coulton",
    "addr:postcode":"da11 8dy",
    "addr:street":"Coulton Avenue",
    "iso:country":"GB",
    "sg:address":"Coulton House, Coulton Avenue",
    "sg:city":"Gravesend",
    "sg:classifiers":[
        {
            "category":"Professional",
            "subcategory":"Engineering",
            "type":"Services"
        }
    ],
    "sg:phone":"+44 1474 320066",
    "sg:postcode":"DA11 8DY",
    "sg:province":"Kent",
    "sg:tags":[
        "contractor",
        "electrical",
        "engineer"
    ],
    "wof:name":"C.T.E Ltd Electrical & Mechanical Contractors",
    "wof:placetype":"venue"
},
  "geometry": {"coordinates":[0.348093003,51.4365386963],"type":"Point"}
}