{
  "type": "Feature",
  "properties": {
    "addr:full":"Unit 1 Neath Rd Swansea Neath Port Talbot SA1 2LF",
    "addr:housenumber":"unit 1",
    "addr:postcode":"sa1 2lf",
    "addr:street":"Neath Rd",
    "iso:country":"GB",
    "sg:address":"Unit 1 Neath Rd",
    "sg:city":"Swansea",
    "sg:classifiers":[
        {
            "category":"Retail",
            "subcategory":"Auto Repair",
            "type":"Services"
        }
    ],
    "sg:postcode":"SA1 2LF",
    "sg:province":"Neath Port Talbot",
    "sg:tags":[
        "modification",
        "garage"
    ],
    "wof:name":"Hafod M O T Centre",
    "wof:placetype":"venue"
},
  "geometry": {"coordinates":[-3.9381940365,51.6372909546],"type":"Point"}
}