{
  "type": "Feature",
  "properties": {
    "iso:country":"GB",
    "sg:address":"109 West Main Street",
    "sg:city":"Bathgate",
    "sg:classifiers":[
        {
            "category":"Ice Cream",
            "type":"Food & Drink"
        }
    ],
    "sg:phone":"+44 1501 740378",
    "sg:postcode":"EH47 0QE",
    "sg:province":"North Lanarkshire",
    "sg:tags":[
        "mnfr"
    ],
    "wof:name":"A & L Franchitti",
    "wof:placetype":"venue"
},
  "geometry": {"coordinates":[-3.6896619797,55.8659248352],"type":"Point"}
}