{
  "type": "Feature",
  "properties": {
    "addr:full":"Brandon Crescent Leeds North Yorkshire LS17 9JH",
    "addr:postcode":"ls17 9jh",
    "addr:street":"Brandon Crescent",
    "iso:country":"GB",
    "sg:address":"Brandon Crescent",
    "sg:city":"Leeds",
    "sg:classifiers":[
        {
            "category":"Building & Trades",
            "subcategory":"Landscaping Services",
            "type":"Services"
        },
        {
            "category":"Home & Garden",
            "subcategory":"Garden Supply",
            "type":"Retail Goods"
        }
    ],
    "sg:phone":"+44 113 289 2922",
    "sg:postcode":"LS17 9JH",
    "sg:province":"North Yorkshire",
    "sg:tags":[
        "nurseryman",
        "nursery",
        "centre"
    ],
    "wof:name":"Greenscapes Nursery & Garden Design Centre",
    "wof:placetype":"venue"
},
  "geometry": {"coordinates":[-1.480372,53.86454],"type":"Point"}
}