{
  "type": "Feature",
  "properties": {
    "iso:country":"GB",
    "sg:address":"19 Pudding Lane",
    "sg:city":"Maidstone",
    "sg:classifiers":[
        {
            "category":"Personal",
            "subcategory":"Beauty Salon",
            "type":"Services"
        }
    ],
    "sg:phone":"+44 1622 758248",
    "sg:postcode":"ME14 1NY",
    "sg:province":"Kent",
    "sg:tags":[
        "unisex",
        "hairdresser"
    ],
    "wof:name":"Headlines",
    "wof:placetype":"venue"
},
  "geometry": {"coordinates":[0.5203490257,51.2739524841],"type":"Point"}
}