{
  "type": "Feature",
  "properties": {
    "addr:full":"The Workshop, Weald Manor Farm, Weald Bampton Gloucestershire OX18 2HW",
    "addr:postcode":"ox18 2hw",
    "addr:street":"Weald Manor;Weald",
    "iso:country":"GB",
    "sg:address":"The Workshop, Weald Manor Farm, Weald",
    "sg:city":"Bampton",
    "sg:classifiers":[
        {
            "category":"Retail",
            "subcategory":"Repair Shop",
            "type":"Services"
        }
    ],
    "sg:postcode":"OX18 2HW",
    "sg:province":"Gloucestershire",
    "sg:tags":[
        "upholsterer"
    ],
    "wof:name":"S Whipp",
    "wof:placetype":"venue"
},
  "geometry": {"coordinates":[-1.546758,51.727924],"type":"Point"}
}