{
  "type": "Feature",
  "properties": {
    "iso:country":"GB",
    "sg:address":"51 Rae Street",
    "sg:city":"Dumfries",
    "sg:classifiers":[
        {
            "category":"Health Services",
            "subcategory":"Podiatrist",
            "type":"Services"
        }
    ],
    "sg:phone":"+44 1387 262225",
    "sg:postcode":"DG1 1JD",
    "sg:province":"Dumfries and Galloway",
    "sg:tags":[
        "podiatrists",
        "chiropodist"
    ],
    "wof:name":"Dransfield D M M Ch S  S R Ch",
    "wof:placetype":"venue"
},
  "geometry": {"coordinates":[-3.608239,55.071362],"type":"Point"}
}