{
  "type": "Feature",
  "properties": {
    "iso:country":"GB",
    "sg:address":"Pye Cottage, Cadney",
    "sg:city":"Brigg",
    "sg:classifiers":[
        {
            "category":"Building & Trades",
            "subcategory":"Construction",
            "type":"Services"
        }
    ],
    "sg:phone":"+44 1652 678670",
    "sg:postcode":"DN20 9HR",
    "sg:province":"Lincolnshire",
    "sg:tags":[
        "builder"
    ],
    "wof:name":"Keith Cooper",
    "wof:placetype":"venue"
},
  "geometry": {"coordinates":[-0.470509,53.518276],"type":"Point"}
}