{
  "type": "Feature",
  "properties": {
    "addr:full":"69 Woodbridge Road Guildford Surrey GU1 4RD",
    "addr:housenumber":"69",
    "addr:postcode":"gu1 4rd",
    "addr:street":"Woodbridge Road",
    "iso:country":"GB",
    "sg:address":"69 Woodbridge Road",
    "sg:city":"Guildford",
    "sg:classifiers":[
        {
            "category":"Organizations",
            "subcategory":"Non-profit Organization",
            "type":"Services"
        }
    ],
    "sg:phone":"+44 1483 505555",
    "sg:postcode":"GU1 4RD",
    "sg:province":"Surrey",
    "sg:tags":[
        "organisation",
        "voluntary",
        "charity"
    ],
    "wof:name":"The Samaritans",
    "wof:placetype":"venue"
},
  "geometry": {"coordinates":[-0.5759270191,51.2405319214],"type":"Point"}
}