{
  "type": "Feature",
  "properties": {
    "iso:country":"GB",
    "sg:address":"15 Carnegie Drive",
    "sg:city":"Dunfermline",
    "sg:classifiers":[
        {
            "category":"Home & Garden",
            "subcategory":"Home Furnishings",
            "type":"Retail Goods"
        }
    ],
    "sg:phone":"+44 1383 729939",
    "sg:postcode":"KY12 7AN",
    "sg:province":"Fife",
    "sg:tags":[
        "blind",
        "curtain",
        "fitting"
    ],
    "wof:name":"J A Davidson",
    "wof:placetype":"venue"
},
  "geometry": {"coordinates":[-3.463019,56.07291],"type":"Point"}
}