{
  "type": "Feature",
  "properties": {
    "addr:full":"27-29 Glebe Street Stoke-on-trent Staffordshire ST4 1HL",
    "addr:housenumber":"27-29",
    "addr:postcode":"st4 1hl",
    "addr:street":"Glebe Street",
    "iso:country":"GB",
    "sg:address":"27-29 Glebe Street",
    "sg:city":"Stoke-on-trent",
    "sg:classifiers":[
        {
            "category":"Bars & Pubs",
            "subcategory":"Wine Bar",
            "type":"Food & Drink"
        }
    ],
    "sg:phone":"+44 1782 416567",
    "sg:postcode":"ST4 1HL",
    "sg:province":"Staffordshire",
    "wof:name":"Harry's Bar",
    "wof:placetype":"venue"
},
  "geometry": {"coordinates":[-2.181859,53.00433],"type":"Point"}
}