{
  "type": "Feature",
  "properties": {
    "addr:full":"Shelley House, Farm House Way, Monksparth Solihull West Midlands B90 4EH",
    "addr:postcode":"b90 4eh",
    "addr:street":"House Way Monksparth",
    "iso:country":"GB",
    "sg:address":"Shelley House, Farm House Way, Monksparth",
    "sg:city":"Solihull",
    "sg:classifiers":[
        {
            "category":"Organizations",
            "subcategory":"Professional Association",
            "type":"Services"
        }
    ],
    "sg:phone":"+44 121 712 1000",
    "sg:postcode":"B90 4EH",
    "sg:province":"West Midlands",
    "sg:tags":[
        "institute"
    ],
    "wof:name":"I B P M Education Ltd.",
    "wof:placetype":"venue"
},
  "geometry": {"coordinates":[-1.78522,52.391323],"type":"Point"}
}