{
  "type": "Feature",
  "properties": {
    "iso:country":"GB",
    "sg:address":"1 Carron Ho, Carron Way",
    "sg:city":"Glasgow",
    "sg:classifiers":[
        {
            "category":"Health Services",
            "subcategory":"Clinic",
            "type":"Services"
        }
    ],
    "sg:phone":"+44 1236 781958",
    "sg:postcode":"G67 1ER",
    "sg:province":"Falkirk",
    "sg:tags":[
        "aromatherapy"
    ],
    "wof:name":"K Mooney",
    "wof:placetype":"venue"
},
  "geometry": {"coordinates":[-3.9907200336,55.9474983215],"type":"Point"}
}