{
  "type": "Feature",
  "properties": {
    "addr:full":"Victoria Square House, Victoria Square Birmingham West Midlands B2 4AJ",
    "addr:postcode":"b2 4aj",
    "addr:street":"Victoria Square",
    "iso:country":"GB",
    "sg:address":"Victoria Square House, Victoria Square",
    "sg:city":"Birmingham",
    "sg:classifiers":[
        {
            "category":"Professional",
            "subcategory":"Lawyer & Legal Services",
            "type":"Services"
        }
    ],
    "sg:phone":"+44 845 111 1111",
    "sg:postcode":"B2 4AJ",
    "sg:province":"West Midlands",
    "sg:tags":[
        "solicitor"
    ],
    "wof:name":"D L A",
    "wof:placetype":"venue"
},
  "geometry": {"coordinates":[-1.902207,52.479416],"type":"Point"}
}