{
  "type": "Feature",
  "properties": {
    "iso:country":"GB",
    "sg:address":"Market Place",
    "sg:city":"Burton-on-trent",
    "sg:classifiers":[
        {
            "category":"Food & Beverages",
            "subcategory":"Meat & Fish",
            "type":"Retail Goods"
        }
    ],
    "sg:postcode":"DE14 1HE",
    "sg:province":"Derbyshire",
    "sg:tags":[
        "butcher"
    ],
    "wof:name":"Wightmans of Barton",
    "wof:placetype":"venue"
},
  "geometry": {"coordinates":[-1.630014,52.801529],"type":"Point"}
}