{
  "type": "Feature",
  "properties": {
    "addr:full":"Balerno High School, 5 Bridge Road Balerno City of Edinburgh EH14 7AQ",
    "addr:housenumber":"5",
    "addr:postcode":"eh14 7aq",
    "addr:street":"Bridge Road",
    "iso:country":"GB",
    "sg:address":"Balerno High School, 5 Bridge Road",
    "sg:city":"Balerno",
    "sg:classifiers":[
        {
            "category":"Education",
            "subcategory":"University",
            "type":"Public Place"
        }
    ],
    "sg:phone":"+44 131 477 7733",
    "sg:postcode":"EH14 7AQ",
    "sg:province":"City of Edinburgh",
    "sg:tags":[
        "adult"
    ],
    "wof:name":"Balerno Community Education Office",
    "wof:placetype":"venue"
},
  "geometry": {"coordinates":[-3.343444109,55.8885040283],"type":"Point"}
}