{
  "type": "Feature",
  "properties": {
    "iso:country":"GB",
    "sg:address":"4 Morst House",
    "sg:city":"Billericay",
    "sg:classifiers":[
        {
            "category":"Professional",
            "subcategory":"Accounting & Tax Preparation",
            "type":"Services"
        }
    ],
    "sg:postcode":"CM12 0BT",
    "sg:province":"Essex",
    "sg:tags":[
        "accountant"
    ],
    "wof:name":"Whittington Blake Ltd.",
    "wof:placetype":"venue"
},
  "geometry": {"coordinates":[0.416855,51.624748],"type":"Point"}
}