{
  "type": "Feature",
  "properties": {
    "iso:country":"GB",
    "sg:address":"Unit 5, Fox Industrial Estate, Holyoake Avenue",
    "sg:city":"Blackpool",
    "sg:classifiers":[
        {
            "category":"Education",
            "subcategory":"Music School",
            "type":"Public Place"
        }
    ],
    "sg:phone":"+44 1253 356189",
    "sg:postcode":"FY2 0QX",
    "sg:province":"Lancashire",
    "sg:tags":[
        "conservatory"
    ],
    "wof:name":"Macdale Windows & Joinery Ltd.",
    "wof:placetype":"venue"
},
  "geometry": {"coordinates":[-3.02729,53.837391],"type":"Point"}
}