{
  "type": "Feature",
  "properties": {
    "iso:country":"GB",
    "sg:address":"19 Hafnant, Winch Wen",
    "sg:city":"Swansea",
    "sg:classifiers":[
        {
            "category":"Building & Trades",
            "subcategory":"Construction",
            "type":"Services"
        }
    ],
    "sg:postcode":"SA6 7LG",
    "sg:province":"Swansea",
    "sg:tags":[
        "builder"
    ],
    "wof:name":"Carmichaels Building Services Ltd.",
    "wof:placetype":"venue"
},
  "geometry": {"coordinates":[-3.9515600204,51.6643486023],"type":"Point"}
}