{
  "type": "Feature",
  "properties": {
    "addr:full":"335 Eaglesham Road, East Kilbride Glasgow South Lanarkshire G75 8RW",
    "addr:housenumber":"335",
    "addr:postcode":"g75 8rw",
    "addr:street":"Eaglesham Road",
    "iso:country":"GB",
    "sg:address":"335 Eaglesham Road, East Kilbride",
    "sg:city":"Glasgow",
    "sg:classifiers":[
        {
            "category":"Building & Trades",
            "subcategory":"Equipment Rental",
            "type":"Services"
        }
    ],
    "sg:postcode":"G75 8RW",
    "sg:province":"South Lanarkshire",
    "sg:tags":[
        "plant",
        "machinery"
    ],
    "wof:name":"A Steel & Son",
    "wof:placetype":"venue"
},
  "geometry": {"coordinates":[-4.2438402176,55.7511558533],"type":"Point"}
}