{
  "type": "Feature",
  "properties": {
    "addr:full":"School Rd Pontyclun Bridgend CF72 8PG",
    "addr:postcode":"cf72 8pg",
    "addr:street":"School Rd",
    "iso:country":"GB",
    "sg:address":"School Rd",
    "sg:city":"Pontyclun",
    "sg:classifiers":[
        {
            "category":"Place Of Worship",
            "type":"Public Place"
        }
    ],
    "sg:phone":"+44 1443 228866",
    "sg:postcode":"CF72 8PG",
    "sg:province":"Bridgend",
    "wof:name":"All Hallows R C Church",
    "wof:placetype":"venue"
},
  "geometry": {"coordinates":[-3.3733489513,51.5327415466],"type":"Point"}
}