{
  "type": "Feature",
  "properties": {
    "addr:full":"45 Beak Street London Greater London W1F 9SD",
    "addr:housenumber":"45",
    "addr:postcode":"w1f 9sd",
    "addr:street":"Beak Street",
    "iso:country":"GB",
    "sg:address":"45 Beak Street",
    "sg:city":"London",
    "sg:classifiers":[
        {
            "category":"Shopping",
            "subcategory":"News",
            "type":"Retail Goods"
        }
    ],
    "sg:phone":"+44 20 7439 8979",
    "sg:postcode":"W1F 9SD",
    "sg:province":"Greater London",
    "sg:tags":[
        "newsagent"
    ],
    "wof:name":"Regents Newsagents",
    "wof:placetype":"venue"
},
  "geometry": {"coordinates":[-0.1374730021,51.5125808716],"type":"Point"}
}