{
  "type": "Feature",
  "properties": {
    "iso:country":"GB",
    "sg:address":"39 London Road",
    "sg:city":"Carlisle",
    "sg:classifiers":[
        {
            "category":"Autos & Motor Vehicles",
            "subcategory":"Motorcycle Sales",
            "type":"Retail Goods"
        }
    ],
    "sg:postcode":"CA1 2JZ",
    "sg:province":"Cumbria",
    "wof:name":"Jack Horsemen",
    "wof:placetype":"venue"
},
  "geometry": {"coordinates":[-2.9250938892,54.8882904053],"type":"Point"}
}