{
  "type": "Feature",
  "properties": {
    "addr:full":"Vicarage, Chapel La Morecambe Lancashire LA3 3HU",
    "addr:postcode":"la3 3hu",
    "iso:country":"GB",
    "sg:address":"Vicarage, Chapel La",
    "sg:city":"Morecambe",
    "sg:classifiers":[
        {
            "category":"Place Of Worship",
            "type":"Public Place"
        }
    ],
    "sg:phone":"+44 1524 858234",
    "sg:postcode":"LA3 3HU",
    "sg:province":"Lancashire",
    "wof:name":"St Helens C Of E Church",
    "wof:placetype":"venue"
},
  "geometry": {"coordinates":[-2.8568189144,54.0585975647],"type":"Point"}
}