{
  "type": "Feature",
  "properties": {
    "iso:country":"GB",
    "sg:address":"Ivy House Farm, North Green Road, Pulham St Mary",
    "sg:city":"Diss",
    "sg:classifiers":[
        {
            "category":"Farming",
            "subcategory":"Livestock Farm",
            "type":"Manufacturing & Wholesale Goods"
        }
    ],
    "sg:phone":"+44 1379 676296",
    "sg:postcode":"IP21 4YG",
    "sg:province":"Norfolk",
    "sg:tags":[
        "others"
    ],
    "wof:name":"W H Wharton & Son",
    "wof:placetype":"venue"
},
  "geometry": {"coordinates":[1.2501499653,52.4291114807],"type":"Point"}
}