{
  "type": "Feature",
  "properties": {
    "addr:full":"31 Ripon Way, Carlton Minniott Thirsk North Yorkshire YO7 4LR",
    "addr:housenumber":"31",
    "addr:postcode":"yo7 4lr",
    "addr:street":"Ripon Way;Minniott",
    "iso:country":"GB",
    "sg:address":"31 Ripon Way, Carlton Minniott",
    "sg:city":"Thirsk",
    "sg:classifiers":[
        {
            "category":"Professional",
            "subcategory":"Engineering",
            "type":"Services"
        }
    ],
    "sg:postcode":"YO7 4LR",
    "sg:province":"North Yorkshire",
    "sg:tags":[
        "contractor",
        "electrical",
        "engineer"
    ],
    "wof:name":"Kenneth Banks",
    "wof:placetype":"venue"
},
  "geometry": {"coordinates":[-1.3784329891,54.2290534973],"type":"Point"}
}