{
  "type": "Feature",
  "properties": {
    "iso:country":"GB",
    "sg:address":"50 Clarence Street",
    "sg:city":"Kingston-upon-thames",
    "sg:classifiers":[
        {
            "category":"Shopping",
            "subcategory":"Stationery & Office Supplies",
            "type":"Retail Goods"
        }
    ],
    "sg:phone":"+44 20 8974 5979",
    "sg:postcode":"KT1 1NR",
    "sg:province":"Greater London",
    "wof:name":"A - Z Office Centre",
    "wof:placetype":"venue"
},
  "geometry": {"coordinates":[-0.302434,51.410576],"type":"Point"}
}