{
  "type": "Feature",
  "properties": {
    "addr:full":"27 Wensum St Norwich Norfolk NR3 1LA",
    "addr:housenumber":"27",
    "addr:postcode":"nr3 1la",
    "addr:street":"Wensum St",
    "iso:country":"GB",
    "sg:address":"27 Wensum St",
    "sg:city":"Norwich",
    "sg:classifiers":[
        {
            "category":"Fast Food",
            "type":"Food & Drink"
        }
    ],
    "sg:phone":"+44 1603 667376",
    "sg:postcode":"NR3 1LA",
    "sg:province":"Norfolk",
    "sg:tags":[
        "away",
        "take"
    ],
    "wof:name":"Istanbul Kebab House",
    "wof:placetype":"venue"
},
  "geometry": {"coordinates":[1.2974669933,52.6327781677],"type":"Point"}
}