{
  "type": "Feature",
  "properties": {
    "iso:country":"GB",
    "sg:address":"Risdale Rd",
    "sg:city":"Bristol",
    "sg:classifiers":[
        {
            "category":"Community Center",
            "type":"Public Place"
        }
    ],
    "sg:phone":"+44 117 923 1286",
    "sg:postcode":"BS3 2QY",
    "sg:province":"City of Bristol",
    "sg:tags":[
        "centre"
    ],
    "wof:name":"Ashton Vale Community Centre",
    "wof:placetype":"venue"
},
  "geometry": {"coordinates":[-2.627044,51.4319],"type":"Point"}
}