{
  "type": "Feature",
  "properties": {
    "iso:country":"GB",
    "sg:address":"Maughans Yd, St. Cuthberts Rd",
    "sg:city":"Newcastle-upon-tyne",
    "sg:classifiers":[
        {
            "category":"Education",
            "subcategory":"Music School",
            "type":"Public Place"
        },
        {
            "category":"Organizations",
            "subcategory":"Professional Association",
            "type":"Services"
        }
    ],
    "sg:postcode":"NE27 0DE",
    "sg:province":"Northumberland",
    "sg:tags":[
        "specialist",
        "calendar",
        "conservatory"
    ],
    "wof:name":"Bertram,Alan,",
    "wof:placetype":"venue"
},
  "geometry": {"coordinates":[-1.53165,55.02644],"type":"Point"}
}