{
  "type": "Feature",
  "properties": {
    "iso:country":"GB",
    "sg:address":"249 Clarendon Park Road",
    "sg:city":"Leicester",
    "sg:classifiers":[
        {
            "category":"Retail",
            "subcategory":"Repair Shop",
            "type":"Services"
        }
    ],
    "sg:phone":"+44 116 270 7489",
    "sg:postcode":"LE2 3AQ",
    "sg:province":"Leicestershire",
    "sg:tags":[
        "television",
        "good",
        "video",
        "servicing",
        "maintenance",
        "radio"
    ],
    "wof:name":"S R Electronics",
    "wof:placetype":"venue"
},
  "geometry": {"coordinates":[-1.1215330362,52.6148376465],"type":"Point"}
}