{
  "type": "Feature",
  "properties": {
    "iso:country":"GB",
    "sg:address":"1 Rufus Close, Chandlers Ford",
    "sg:city":"Eastleigh",
    "sg:classifiers":[
        {
            "category":"Professional",
            "subcategory":"Engineering",
            "type":"Services"
        }
    ],
    "sg:postcode":"SO53 1FL",
    "sg:province":"Hampshire",
    "sg:tags":[
        "contractor",
        "electrical",
        "engineer"
    ],
    "wof:name":"On-Site Electrical Services Ltd.",
    "wof:placetype":"venue"
},
  "geometry": {"coordinates":[-1.37284,50.992271],"type":"Point"}
}