{
  "type": "Feature",
  "properties": {
    "addr:full":"264 Fakenham Road, Taverham Norwich Norfolk NR8 6AD",
    "addr:housenumber":"264",
    "addr:postcode":"nr8 6ad",
    "addr:street":"Fakenham Road;Norwich Norfolk",
    "iso:country":"GB",
    "sg:address":"264 Fakenham Road, Taverham",
    "sg:city":"Norwich",
    "sg:classifiers":[
        {
            "category":"Bars & Pubs",
            "type":"Food & Drink"
        },
        {
            "category":"Community Center",
            "subcategory":"Social",
            "type":"Public Place"
        }
    ],
    "sg:phone":"+44 1603 868212",
    "sg:postcode":"NR8 6AD",
    "sg:province":"Norfolk",
    "sg:tags":[
        "pubs",
        "house",
        "inn",
        "activity"
    ],
    "wof:name":"Silver Fox",
    "wof:placetype":"venue"
},
  "geometry": {"coordinates":[1.2074450254,52.6820755005],"type":"Point"}
}