{
  "type": "Feature",
  "properties": {
    "addr:full":"15 Cosgrove House, Whiston Road London Greater London E2 8SE",
    "addr:housenumber":"15",
    "addr:postcode":"e2 8se",
    "addr:street":"Cosgrove House Whiston Road",
    "iso:country":"GB",
    "sg:address":"15 Cosgrove House, Whiston Road",
    "sg:city":"London",
    "sg:classifiers":[
        {
            "category":"Shopping",
            "subcategory":"Department Store",
            "type":"Retail Goods"
        }
    ],
    "sg:postcode":"E2 8SE",
    "sg:province":"Greater London",
    "wof:name":"Glory of God Unique Fashion Ltd",
    "wof:placetype":"venue"
},
  "geometry": {"coordinates":[-0.06466,51.53521],"type":"Point"}
}