{
  "type": "Feature",
  "properties": {
    "iso:country":"GB",
    "sg:address":"Beaver Road, (off South Beach Pde)",
    "sg:city":"Great Yarmouth",
    "sg:classifiers":[
        {
            "category":"Professional",
            "type":"Services"
        }
    ],
    "sg:phone":"+44 1493 332668",
    "sg:postcode":"NR30 3PS",
    "sg:province":"Norfolk",
    "sg:tags":[
        "auctioneer"
    ],
    "wof:name":"Garry M  Emms & Co. Ltd.",
    "wof:placetype":"venue"
},
  "geometry": {"coordinates":[1.73468,52.587456],"type":"Point"}
}