{
  "type": "Feature",
  "properties": {
    "addr:full":"Court Barton, Aveton Gifford Kingsbridge Devon TQ7 4LE",
    "addr:housenumber":"gifford",
    "addr:postcode":"tq7 4le",
    "addr:street":"Court",
    "iso:country":"GB",
    "sg:address":"Court Barton, Aveton Gifford",
    "sg:city":"Kingsbridge",
    "sg:classifiers":[
        {
            "category":"Travel",
            "subcategory":"Hotels & Motels",
            "type":"Entertainment"
        }
    ],
    "sg:phone":"+44 1548 550312",
    "sg:postcode":"TQ7 4LE",
    "sg:province":"Devon",
    "sg:tags":[
        "house",
        "guest"
    ],
    "wof:name":"Court Barton Farm House",
    "wof:placetype":"venue"
},
  "geometry": {"coordinates":[-3.839934,50.315063],"type":"Point"}
}