{
  "type": "Feature",
  "properties": {
    "addr:full":"Roseheath Drive Liverpool Merseyside L26 9UH",
    "addr:postcode":"l26 9uh",
    "addr:street":"Roseheath Drive",
    "iso:country":"GB",
    "sg:address":"Roseheath Drive",
    "sg:city":"Liverpool",
    "sg:classifiers":[
        {
            "category":"Health Services",
            "subcategory":"Doctor",
            "type":"Services"
        },
        {
            "category":"Health Services",
            "subcategory":"Clinic",
            "type":"Services"
        }
    ],
    "sg:phone":"+44 151 486 5848",
    "sg:postcode":"L26 9UH",
    "sg:province":"Merseyside",
    "sg:tags":[
        "nh"
    ],
    "wof:name":"Halewood Health Centre",
    "wof:placetype":"venue"
},
  "geometry": {"coordinates":[-2.831164,53.359547],"type":"Point"}
}