{
  "type": "Feature",
  "properties": {
    "iso:country":"GB",
    "sg:address":"61 Union Street",
    "sg:city":"Wednesbury",
    "sg:classifiers":[
        {
            "category":"Health Services",
            "subcategory":"Optometrist",
            "type":"Services"
        },
        {
            "category":"Shopping",
            "subcategory":"Optician",
            "type":"Retail Goods"
        }
    ],
    "sg:phone":"+44 121 556 5564",
    "sg:postcode":"WS10 7HB",
    "sg:province":"West Midlands",
    "sg:tags":[
        "ophthalmic"
    ],
    "wof:name":"Chapmans Opticians",
    "wof:placetype":"venue"
},
  "geometry": {"coordinates":[-2.020116,52.552872],"type":"Point"}
}