{
  "type": "Feature",
  "properties": {
    "iso:country":"GB",
    "sg:address":"Unit 1 Crown Point Retail Park, Junction Street",
    "sg:city":"Leeds",
    "sg:classifiers":[
        {
            "category":"Shopping",
            "subcategory":"Catalog Store",
            "type":"Retail Goods"
        }
    ],
    "sg:phone":"+44 113 245 6153",
    "sg:postcode":"LS10 1ET",
    "sg:province":"West Yorkshire",
    "sg:tags":[
        "catalogue",
        "showroom"
    ],
    "wof:name":"Argos",
    "wof:placetype":"venue"
},
  "geometry": {"coordinates":[-1.540609,53.789566],"type":"Point"}
}