{
  "type": "Feature",
  "properties": {
    "addr:full":"High Street Llandysul Carmarthenshire SA44 4DG",
    "addr:postcode":"sa44 4dg",
    "addr:street":"High Street",
    "iso:country":"GB",
    "sg:address":"High Street",
    "sg:city":"Llandysul",
    "sg:classifiers":[
        {
            "category":"Food & Beverages",
            "subcategory":"Bakery",
            "type":"Retail Goods"
        }
    ],
    "sg:postcode":"SA44 4DG",
    "sg:province":"Carmarthenshire",
    "sg:tags":[
        "baker"
    ],
    "wof:name":"Paris House Bakery",
    "wof:placetype":"venue"
},
  "geometry": {"coordinates":[-4.3079681396,52.0436286926],"type":"Point"}
}