{
  "type": "Feature",
  "properties": {
    "addr:full":"River St Truro Cornwall TR1 2SJ",
    "addr:postcode":"tr1 2sj",
    "addr:street":"River St",
    "iso:country":"GB",
    "sg:address":"River St",
    "sg:city":"Truro",
    "sg:classifiers":[
        {
            "category":"Education",
            "subcategory":"Library",
            "type":"Public Place"
        }
    ],
    "sg:phone":"+44 1872 272205",
    "sg:postcode":"TR1 2SJ",
    "sg:province":"Cornwall",
    "sg:tags":[
        "book"
    ],
    "wof:name":"Courtney Library & Cornish History Archive",
    "wof:placetype":"venue"
},
  "geometry": {"coordinates":[-5.054212,50.26347],"type":"Point"}
}