{
  "type": "Feature",
  "properties": {
    "iso:country":"GB",
    "sg:address":"Unit 8 Southwall Road Industrial Estate, Southwall Road",
    "sg:city":"Deal",
    "sg:classifiers":[
        {
            "category":"Retail",
            "subcategory":"Auto Repair",
            "type":"Services"
        }
    ],
    "sg:phone":"+44 1304 381733",
    "sg:postcode":"CT14 9QB",
    "sg:province":"Kent",
    "sg:tags":[
        "modification",
        "garage"
    ],
    "wof:name":"S Stanford",
    "wof:placetype":"venue"
},
  "geometry": {"coordinates":[1.390615,51.225029],"type":"Point"}
}