{
  "type": "Feature",
  "properties": {
    "addr:full":"44 Drake Circus Plymouth Devon PL4 8AB",
    "addr:housenumber":"44",
    "addr:postcode":"pl4 8ab",
    "addr:street":"Drake Circus",
    "iso:country":"GB",
    "sg:address":"44 Drake Circus",
    "sg:city":"Plymouth",
    "sg:classifiers":[
        {
            "category":"Education",
            "subcategory":"Special Training",
            "type":"Public Place"
        }
    ],
    "sg:phone":"+44 1752 204134",
    "sg:postcode":"PL4 8AB",
    "sg:province":"Devon",
    "sg:tags":[
        "product",
        "centre"
    ],
    "wof:name":"Training For Employment",
    "wof:placetype":"venue"
},
  "geometry": {"coordinates":[-4.1373519897,50.3747596741],"type":"Point"}
}