{
  "type": "Feature",
  "properties": {
    "addr:full":"Unit 1 Holly House Estate, Middlewich Road Middlewich Cheshire CW10 9LT",
    "addr:housenumber":"unit 1",
    "addr:postcode":"cw10 9lt",
    "addr:street":"Holly;Estate Middlewich Road",
    "iso:country":"GB",
    "sg:address":"Unit 1 Holly House Estate, Middlewich Road",
    "sg:city":"Middlewich",
    "sg:classifiers":[
        {
            "category":"Professional",
            "subcategory":"Engineering",
            "type":"Services"
        }
    ],
    "sg:phone":"+44 1606 737464",
    "sg:postcode":"CW10 9LT",
    "sg:province":"Cheshire",
    "wof:name":"Mostons",
    "wof:placetype":"venue"
},
  "geometry": {"coordinates":[-2.4250519276,53.2140464783],"type":"Point"}
}