{
  "type": "Feature",
  "properties": {
    "addr:full":"Well Street, Rhosymedre Wrexham Wrexham LL14 3YD",
    "addr:postcode":"ll14 3yd",
    "addr:street":"Well Street Rhosymedre",
    "iso:country":"GB",
    "sg:address":"Well Street, Rhosymedre",
    "sg:city":"Wrexham",
    "sg:classifiers":[
        {
            "category":"Food & Beverages",
            "subcategory":"Supermarket",
            "type":"Retail Goods"
        }
    ],
    "sg:phone":"+44 1978 822073",
    "sg:postcode":"LL14 3YD",
    "sg:province":"Wrexham",
    "wof:name":"Kwik Save Stores",
    "wof:placetype":"venue"
},
  "geometry": {"coordinates":[-3.072534,52.97316],"type":"Point"}
}