{
  "type": "Feature",
  "properties": {
    "addr:full":"Walmer Castle, Kingsdown Rd, Kingsdown Deal Kent CT14 7LJ",
    "addr:postcode":"ct14 7lj",
    "addr:street":"Kingsdown Rd",
    "iso:country":"GB",
    "sg:address":"Walmer Castle, Kingsdown Rd, Kingsdown",
    "sg:city":"Deal",
    "sg:classifiers":[
        {
            "category":"Cafe",
            "type":"Food & Drink"
        }
    ],
    "sg:phone":"+44 1304 363887",
    "sg:postcode":"CT14 7LJ",
    "sg:province":"Kent",
    "sg:tags":[
        "tea",
        "room"
    ],
    "wof:name":"Walmer Castle Tea Rooms",
    "wof:placetype":"venue"
},
  "geometry": {"coordinates":[1.393775,51.20327],"type":"Point"}
}