{
  "type": "Feature",
  "properties": {
    "iso:country":"GB",
    "sg:address":"34-36 Market Square",
    "sg:city":"Witney",
    "sg:classifiers":[
        {
            "category":"Community Center",
            "type":"Public Place"
        }
    ],
    "sg:phone":"+44 1993 779877",
    "sg:postcode":"OX28 6AD",
    "sg:province":"Oxfordshire",
    "sg:tags":[
        "recreation",
        "leisure",
        "centre"
    ],
    "wof:name":"Go Bananas",
    "wof:placetype":"venue"
},
  "geometry": {"coordinates":[-1.485706,51.783962],"type":"Point"}
}