{
  "type": "Feature",
  "properties": {
    "addr:full":"519 Evesham Road Redditch Warwickshire B97 5JP",
    "addr:housenumber":"519",
    "addr:postcode":"b97 5jp",
    "addr:street":"Evesham Road",
    "iso:country":"GB",
    "sg:address":"519 Evesham Road",
    "sg:city":"Redditch",
    "sg:classifiers":[
        {
            "category":"Farming",
            "subcategory":"Livestock Farm",
            "type":"Manufacturing & Wholesale Goods"
        },
        {
            "category":"Shopping",
            "subcategory":"Florist",
            "type":"Retail Goods"
        }
    ],
    "sg:phone":"+44 1527 550700",
    "sg:postcode":"B97 5JP",
    "sg:province":"Warwickshire",
    "sg:tags":[
        "breeder"
    ],
    "wof:name":"Nursery Shop",
    "wof:placetype":"venue"
},
  "geometry": {"coordinates":[-1.9399650097,52.2796058655],"type":"Point"}
}