{
  "type": "Feature",
  "properties": {
    "addr:full":"Dalmally, Church Hill, Plumtree Nottingham Nottinghamshire NG12 5ND",
    "addr:postcode":"ng12 5nd",
    "addr:street":"Church Hill Plumtree",
    "iso:country":"GB",
    "sg:address":"Dalmally, Church Hill, Plumtree",
    "sg:city":"Nottingham",
    "sg:classifiers":[
        {
            "category":"Professional",
            "subcategory":"Management & Consulting",
            "type":"Services"
        },
        {
            "category":"Organizations",
            "subcategory":"Community Association",
            "type":"Services"
        }
    ],
    "sg:phone":"+44 115 937 4291",
    "sg:postcode":"NG12 5ND",
    "sg:province":"Nottinghamshire",
    "sg:tags":[
        "consultant",
        "relation",
        "public"
    ],
    "wof:name":"John Lawson Associates",
    "wof:placetype":"venue"
},
  "geometry": {"coordinates":[-1.0886490345,52.8915557861],"type":"Point"}
}