{
  "type": "Feature",
  "properties": {
    "addr:full":"20 West Street Leominster Herefordshire HR6 8ES",
    "addr:housenumber":"20",
    "addr:postcode":"hr6 8es",
    "addr:street":"West Street",
    "iso:country":"GB",
    "sg:address":"20 West Street",
    "sg:city":"Leominster",
    "sg:classifiers":[
        {
            "category":"Personal",
            "subcategory":"Beauty Salon",
            "type":"Services"
        },
        {
            "category":"Personal",
            "subcategory":"Barber",
            "type":"Services"
        }
    ],
    "sg:phone":"+44 1568 613041",
    "sg:postcode":"HR6 8ES",
    "sg:province":"Herefordshire",
    "sg:tags":[
        "unisex",
        "hairdresser"
    ],
    "wof:name":"The Klippers",
    "wof:placetype":"venue"
},
  "geometry": {"coordinates":[-2.740009,52.226936],"type":"Point"}
}