{
  "type": "Feature",
  "properties": {
    "addr:full":"342 Regents Park Road, Finchley London Greater London N3 2LJ",
    "addr:housenumber":"342",
    "addr:postcode":"n3 2lj",
    "addr:street":"Regents Park Road",
    "iso:country":"GB",
    "sg:address":"342 Regents Park Road, Finchley",
    "sg:city":"London",
    "sg:classifiers":[
        {
            "category":"Professional",
            "subcategory":"Computer Services",
            "type":"Services"
        }
    ],
    "sg:postcode":"N3 2LJ",
    "sg:province":"Greater London",
    "sg:tags":[
        "system",
        "software"
    ],
    "wof:name":"Serial 2000 Ltd",
    "wof:placetype":"venue"
},
  "geometry": {"coordinates":[-0.193867,51.600952],"type":"Point"}
}