{
  "type": "Feature",
  "properties": {
    "addr:full":"Bridge Farm, Michaelston-y-fedw Cardiff Caerphilly CF3 6XT",
    "addr:postcode":"cf3 6xt",
    "addr:street":"Bridge;Michaelston-Y-Fedw",
    "iso:country":"GB",
    "sg:address":"Bridge Farm, Michaelston-y-fedw",
    "sg:city":"Cardiff",
    "sg:classifiers":[
        {
            "category":"Farming",
            "subcategory":"Livestock Farm",
            "type":"Manufacturing & Wholesale Goods"
        }
    ],
    "sg:phone":"+44 1633 681199",
    "sg:postcode":"CF3 6XT",
    "sg:province":"Caerphilly",
    "sg:tags":[
        "others"
    ],
    "wof:name":"W R Jones & Sons",
    "wof:placetype":"venue"
},
  "geometry": {"coordinates":[-3.0939900875,51.5616493225],"type":"Point"}
}