{
  "type": "Feature",
  "properties": {
    "addr:full":"36-38 Windsor Street Leamington Spa Warwickshire CV32 5EB",
    "addr:housenumber":"36-38",
    "addr:postcode":"cv32 5eb",
    "addr:street":"Windsor Street",
    "iso:country":"GB",
    "sg:address":"36-38 Windsor Street",
    "sg:city":"Leamington Spa",
    "sg:classifiers":[
        {
            "category":"Insurance",
            "subcategory":"Insurance Agent",
            "type":"Services"
        }
    ],
    "sg:phone":"+44 1926 420555",
    "sg:postcode":"CV32 5EB",
    "sg:province":"Warwickshire",
    "sg:tags":[
        "broker"
    ],
    "wof:name":"Heartland Ltd.",
    "wof:placetype":"venue"
},
  "geometry": {"coordinates":[-1.538299,52.290417],"type":"Point"}
}