{
  "type": "Feature",
  "properties": {
    "iso:country":"GB",
    "sg:address":"11a Leopold Street",
    "sg:city":"Nairn",
    "sg:classifiers":[
        {
            "category":"Shopping",
            "subcategory":"Comic Books",
            "type":"Retail Goods"
        }
    ],
    "sg:phone":"+44 1667 453127",
    "sg:postcode":"IV12 4BE",
    "sg:province":"Highland",
    "sg:tags":[
        "jeweller"
    ],
    "wof:name":"Dallas Jewellers",
    "wof:placetype":"venue"
},
  "geometry": {"coordinates":[-3.871018,57.58437],"type":"Point"}
}