{
  "type": "Feature",
  "properties": {
    "addr:full":"Inverdruie Fisheries, Rothiemurchus Aviemore Highland PH22 1QH",
    "addr:postcode":"ph22 1qh",
    "iso:country":"GB",
    "sg:address":"Inverdruie Fisheries, Rothiemurchus",
    "sg:city":"Aviemore",
    "sg:classifiers":[
        {
            "category":"Farming",
            "subcategory":"Fish & Marine Products",
            "type":"Manufacturing & Wholesale Goods"
        },
        {
            "category":"Farming",
            "subcategory":"Farm",
            "type":"Manufacturing & Wholesale Goods"
        },
        {
            "category":"Landmark",
            "subcategory":"Tourist Attraction",
            "type":"Public Place"
        }
    ],
    "sg:phone":"+44 1479 811185",
    "sg:postcode":"PH22 1QH",
    "sg:province":"Highland",
    "sg:tags":[
        "hatchery",
        "interest"
    ],
    "wof:name":"Rothiemurchus Fish Farm",
    "wof:placetype":"venue"
},
  "geometry": {"coordinates":[-3.8287789822,57.1986694336],"type":"Point"}
}