{
  "type": "Feature",
  "properties": {
    "addr:full":"Unit 2 Tweedale Buildings, High Street Fort William Highland PH33 6EU",
    "addr:housenumber":"unit 2",
    "addr:postcode":"ph33 6eu",
    "addr:street":"Tweedale Buildings High Street",
    "iso:country":"GB",
    "sg:address":"Unit 2 Tweedale Buildings, High Street",
    "sg:city":"Fort William",
    "sg:classifiers":[
        {
            "category":"Home & Garden",
            "subcategory":"Home Furnishings",
            "type":"Retail Goods"
        }
    ],
    "sg:phone":"+44 1397 702855",
    "sg:postcode":"PH33 6EU",
    "sg:province":"Highland",
    "sg:tags":[
        "wall",
        "wallpaper",
        "covering"
    ],
    "wof:name":"Homestyle by Fads",
    "wof:placetype":"venue"
},
  "geometry": {"coordinates":[-5.1084589958,56.8184318542],"type":"Point"}
}