{
  "type": "Feature",
  "properties": {
    "addr:full":"Unit 6, 19-21 Penhall Road London Greater London SE7 8RX",
    "addr:housenumber":"unit 6",
    "addr:postcode":"19-21;se7 8rx",
    "addr:street":"Penhall Road",
    "iso:country":"GB",
    "sg:address":"Unit 6, 19-21 Penhall Road",
    "sg:city":"London",
    "sg:classifiers":[
        {
            "category":"Retail",
            "subcategory":"Auto Repair",
            "type":"Services"
        }
    ],
    "sg:phone":"+44 20 8293 9091",
    "sg:postcode":"SE7 8RX",
    "sg:province":"Greater London",
    "sg:tags":[
        "modification",
        "garage",
        "related"
    ],
    "wof:name":"L R R Range Rovers",
    "wof:placetype":"venue"
},
  "geometry": {"coordinates":[0.037162,51.490971],"type":"Point"}
}