{
  "type": "Feature",
  "properties": {
    "iso:country":"GB",
    "sg:address":"95 Commercial Road, Parkstone",
    "sg:city":"Poole",
    "sg:classifiers":[
        {
            "category":"Shopping",
            "subcategory":"Discount & Variety Stores",
            "type":"Retail Goods"
        }
    ],
    "sg:phone":"+44 1202 746964",
    "sg:postcode":"BH14 0JD",
    "sg:province":"Dorset",
    "sg:tags":[
        "shop",
        "model"
    ],
    "wof:name":"Plastic Past Times",
    "wof:placetype":"venue"
},
  "geometry": {"coordinates":[-1.953004,50.723255],"type":"Point"}
}