{
  "type": "Feature",
  "properties": {
    "addr:full":"Prince Regent Lane, Custom House London Greater London E16 3JJ",
    "addr:postcode":"e16 3jj",
    "addr:street":"Prince Regent Lane Custom House",
    "iso:country":"GB",
    "sg:address":"Prince Regent Lane, Custom House",
    "sg:city":"London",
    "sg:classifiers":[
        {
            "category":"Education",
            "subcategory":"Library",
            "type":"Public Place"
        },
        {
            "category":"Government",
            "subcategory":"Office",
            "type":"Public Place"
        }
    ],
    "sg:phone":"+44 20 7476 1565",
    "sg:postcode":"E16 3JJ",
    "sg:province":"Greater London",
    "sg:tags":[
        "book",
        "local"
    ],
    "wof:name":"Custom House Library",
    "wof:placetype":"venue"
},
  "geometry": {"coordinates":[0.0317149982,51.5133514404],"type":"Point"}
}