{
  "type": "Feature",
  "properties": {
    "iso:country":"GB",
    "sg:address":"223 Elmsleigh Drive",
    "sg:city":"Leigh-on-sea",
    "sg:classifiers":[
        {
            "category":"Food & Beverages",
            "subcategory":"Liquor & Beverages",
            "type":"Retail Goods"
        }
    ],
    "sg:phone":"+44 1702 713334",
    "sg:postcode":"SS9 4JL",
    "sg:province":"Essex",
    "sg:tags":[
        "beer",
        "spirit",
        "wines"
    ],
    "wof:name":"Essex Wines",
    "wof:placetype":"venue"
},
  "geometry": {"coordinates":[0.655775,51.556309],"type":"Point"}
}