{
  "type": "Feature",
  "properties": {
    "addr:full":"41 Dalton Way Newton Aycliffe Durham DL5 4DJ",
    "addr:housenumber":"41",
    "addr:postcode":"dl5 4dj",
    "addr:street":"Dalton Way",
    "iso:country":"GB",
    "sg:address":"41 Dalton Way",
    "sg:city":"Newton Aycliffe",
    "sg:classifiers":[
        {
            "category":"Food & Beverages",
            "subcategory":"Liquor & Beverages",
            "type":"Retail Goods"
        }
    ],
    "sg:phone":"+44 1325 312703",
    "sg:postcode":"DL5 4DJ",
    "sg:province":"Durham",
    "sg:tags":[
        "beer",
        "wine",
        "spirit",
        "wines"
    ],
    "wof:name":"Booze Buster",
    "wof:placetype":"venue"
},
  "geometry": {"coordinates":[-1.571708,54.621151],"type":"Point"}
}