{
  "type": "Feature",
  "properties": {
    "addr:full":"Leckwith Road, Netherton Industrial Estate, Aintree Liverpool Merseyside L30 6UF",
    "addr:housenumber":"estate",
    "addr:postcode":"l30 6uf",
    "addr:street":"Leckwith Road;Industrial",
    "iso:country":"GB",
    "sg:address":"Leckwith Road, Netherton Industrial Estate, Aintree",
    "sg:city":"Liverpool",
    "sg:classifiers":[
        {
            "category":"Manufacturing",
            "subcategory":"Metals",
            "type":"Manufacturing & Wholesale Goods"
        }
    ],
    "sg:phone":"+44 151 521 6414",
    "sg:postcode":"L30 6UF",
    "sg:province":"Merseyside",
    "sg:tags":[
        "steel",
        "stockholder"
    ],
    "wof:name":"Towerward Ltd.",
    "wof:placetype":"venue"
},
  "geometry": {"coordinates":[-2.957089901,53.4821510315],"type":"Point"}
}