{
  "type": "Feature",
  "properties": {
    "addr:full":"Sprint Industrial Estate, Four Ashes Wolverhampton Staffordshire WV10 7DA",
    "addr:postcode":"wv10 7da",
    "addr:street":"Industrial Estate;Ashes",
    "iso:country":"GB",
    "sg:address":"Sprint Industrial Estate, Four Ashes",
    "sg:city":"Wolverhampton",
    "sg:classifiers":[
        {
            "category":"Freight",
            "type":"Transportation"
        }
    ],
    "sg:phone":"+44 1902 791661",
    "sg:postcode":"WV10 7DA",
    "sg:province":"Staffordshire",
    "sg:tags":[
        "haulage",
        "road"
    ],
    "wof:name":"Alex & Gwenda M McGarrie",
    "wof:placetype":"venue"
},
  "geometry": {"coordinates":[-2.1226139069,52.6733207703],"type":"Point"}
}