{
  "type": "Feature",
  "properties": {
    "addr:full":"84-90 High Street Uckfield East Sussex TN22 5AD",
    "addr:housenumber":"84-90",
    "addr:postcode":"tn22 5ad",
    "addr:street":"High Street",
    "iso:country":"GB",
    "sg:address":"84-90 High Street",
    "sg:city":"Uckfield",
    "sg:classifiers":[
        {
            "category":"Autos & Motor Vehicles",
            "subcategory":"Automobile Sales",
            "type":"Retail Goods"
        }
    ],
    "sg:phone":"+44 1825 764255",
    "sg:postcode":"TN22 5AD",
    "sg:province":"East Sussex",
    "sg:tags":[
        "car"
    ],
    "wof:name":"Caffyns",
    "wof:placetype":"venue"
},
  "geometry": {"coordinates":[0.09611,50.969105],"type":"Point"}
}