{
  "type": "Feature",
  "properties": {
    "addr:full":"1 Upper Brig Royd Sowerby Bridge West Yorkshire HX6 4BH",
    "addr:housenumber":"1",
    "addr:postcode":"hx6 4bh",
    "addr:street":"Upper Brig Royd;West",
    "iso:country":"GB",
    "sg:address":"1 Upper Brig Royd",
    "sg:city":"Sowerby Bridge",
    "sg:classifiers":[
        {
            "category":"Social Services",
            "subcategory":"Adult Care",
            "type":"Services"
        }
    ],
    "sg:phone":"+44 1422 822370",
    "sg:postcode":"HX6 4BH",
    "sg:province":"West Yorkshire",
    "sg:tags":[
        "housing",
        "sheltered"
    ],
    "wof:name":"Upper Brig Royd Sheltered Housing",
    "wof:placetype":"venue"
},
  "geometry": {"coordinates":[-1.941581,53.676132],"type":"Point"}
}