{
  "type": "Feature",
  "properties": {
    "iso:country":"GB",
    "sg:address":"29 Croft Road, Cosby",
    "sg:city":"Leicester",
    "sg:classifiers":[
        {
            "category":"Building & Trades",
            "subcategory":"Construction",
            "type":"Services"
        }
    ],
    "sg:phone":"+44 116 286 5236",
    "sg:postcode":"LE9 1SF",
    "sg:province":"Leicestershire",
    "sg:tags":[
        "builder"
    ],
    "wof:name":"Brian Randall Builders",
    "wof:placetype":"venue"
},
  "geometry": {"coordinates":[-1.197908,52.549023],"type":"Point"}
}