{
  "type": "Feature",
  "properties": {
    "iso:country":"GB",
    "sg:address":"Braich Farm, Clawddnewydd",
    "sg:city":"Ruthin",
    "sg:classifiers":[
        {
            "category":"Farming",
            "subcategory":"Farm",
            "type":"Manufacturing & Wholesale Goods"
        }
    ],
    "sg:postcode":"LL15 2NL",
    "sg:province":"Denbighshire",
    "sg:tags":[
        "mixed",
        "crop"
    ],
    "wof:name":"A Johnson & S Dunsdon",
    "wof:placetype":"venue"
},
  "geometry": {"coordinates":[-3.368924,53.061977],"type":"Point"}
}