{
  "type": "Feature",
  "properties": {
    "addr:full":"1 Austhorpe Road, Cross Gates Leeds West Yorkshire LS15 8QR",
    "addr:housenumber":"1",
    "addr:postcode":"ls15 8qr",
    "addr:street":"Austhorpe Road",
    "iso:country":"GB",
    "sg:address":"1 Austhorpe Road, Cross Gates",
    "sg:city":"Leeds",
    "sg:classifiers":[
        {
            "category":"Home & Garden",
            "subcategory":"Carpets & Floor Coverings",
            "type":"Retail Goods"
        }
    ],
    "sg:phone":"+44 113 293 1717",
    "sg:postcode":"LS15 8QR",
    "sg:province":"West Yorkshire",
    "sg:tags":[
        "carpets",
        "rug",
        "matting"
    ],
    "wof:name":"Carpet Kingdom",
    "wof:placetype":"venue"
},
  "geometry": {"coordinates":[-1.4519569874,53.807674408],"type":"Point"}
}