{
  "type": "Feature",
  "properties": {
    "iso:country":"GB",
    "sg:address":"8 Brigham Hill Mansion, Brigham",
    "sg:city":"Cockermouth",
    "sg:classifiers":[
        {
            "category":"Retail",
            "subcategory":"Driving School",
            "type":"Services"
        }
    ],
    "sg:postcode":"CA13 0TL",
    "sg:province":"Cumbria",
    "wof:name":"Cashmore School of Motoring",
    "wof:placetype":"venue"
},
  "geometry": {"coordinates":[-3.371016,54.658718],"type":"Point"}
}