{
  "type": "Feature",
  "properties": {
    "addr:full":"Oakfield, Station Road, Salwick Preston Lancashire PR4 0YH",
    "addr:postcode":"pr4 0yh",
    "addr:street":"Station Road Salwick",
    "iso:country":"GB",
    "sg:address":"Oakfield, Station Road, Salwick",
    "sg:city":"Preston",
    "sg:classifiers":[
        {
            "category":"Farming",
            "subcategory":"Nursery",
            "type":"Manufacturing & Wholesale Goods"
        }
    ],
    "sg:phone":"+44 1772 687709",
    "sg:postcode":"PR4 0YH",
    "sg:province":"Lancashire",
    "sg:tags":[
        "creche"
    ],
    "wof:name":"Oakfield Nursery",
    "wof:placetype":"venue"
},
  "geometry": {"coordinates":[-2.8171200752,53.7808494568],"type":"Point"}
}