{
  "type": "Feature",
  "properties": {
    "iso:country":"GB",
    "sg:address":"34 Park View Terrace, New Coundon",
    "sg:city":"Bishop Auckland",
    "sg:classifiers":[
        {
            "category":"Bars & Pubs",
            "type":"Food & Drink"
        }
    ],
    "sg:phone":"+44 1388 601715",
    "sg:postcode":"DL14 8QB",
    "sg:province":"Durham",
    "sg:tags":[
        "pubs",
        "inn"
    ],
    "wof:name":"Whitbread Hotel Co. Ltd.",
    "wof:placetype":"venue"
},
  "geometry": {"coordinates":[-1.647287,54.66684],"type":"Point"}
}