{
  "type": "Feature",
  "properties": {
    "addr:full":"97 Turners Hill, Cheshunt Waltham Cross Essex EN8 9BD",
    "addr:housenumber":"97",
    "addr:postcode":"en8 9bd",
    "addr:street":"Turners Hill Cheshunt;Cross",
    "iso:country":"GB",
    "sg:address":"97 Turners Hill, Cheshunt",
    "sg:city":"Waltham Cross",
    "sg:classifiers":[
        {
            "category":"Professional",
            "subcategory":"Lawyer & Legal Services",
            "type":"Services"
        }
    ],
    "sg:phone":"+44 7754 947915",
    "sg:postcode":"EN8 9BD",
    "sg:province":"Essex",
    "sg:tags":[
        "solicitor"
    ],
    "wof:name":"Macdonald & Co.",
    "wof:placetype":"venue"
},
  "geometry": {"coordinates":[-0.0345220007,51.7026557922],"type":"Point"}
}