{
  "type": "Feature",
  "properties": {
    "addr:full":"Windyhills, Craggie Burn, Daviot Inverness Highland IV1 2XQ",
    "addr:postcode":"iv1 2xq",
    "addr:street":"Burn Daviot",
    "iso:country":"GB",
    "sg:address":"Windyhills, Craggie Burn, Daviot",
    "sg:city":"Inverness",
    "sg:classifiers":[
        {
            "category":"Building & Trades",
            "subcategory":"Construction",
            "type":"Services"
        }
    ],
    "sg:postcode":"IV1 2XQ",
    "sg:province":"Highland",
    "sg:tags":[
        "roofing"
    ],
    "wof:name":"Inverness Flat Roofing Services Ltd",
    "wof:placetype":"venue"
},
  "geometry": {"coordinates":[-4.1284298897,57.4275283813],"type":"Point"}
}