{
  "type": "Feature",
  "properties": {
    "addr:full":"Unit 1/2 Block 2, Bandeath Industrial Estate, Throsk Stirling Falkirk FK7 7NP",
    "addr:housenumber":"unit 1 / 2 block",
    "addr:postcode":"fk7 7np",
    "addr:street":"Bandeath Industrial Estate Throsk",
    "iso:country":"GB",
    "sg:address":"Unit 1/2 Block 2, Bandeath Industrial Estate, Throsk",
    "sg:city":"Stirling",
    "sg:classifiers":[
        {
            "category":"Home & Garden",
            "subcategory":"Furniture",
            "type":"Retail Goods"
        }
    ],
    "sg:phone":"+44 1786 812220",
    "sg:postcode":"FK7 7NP",
    "sg:province":"Falkirk",
    "wof:name":"Bio chem Research Ltd.",
    "wof:placetype":"venue"
},
  "geometry": {"coordinates":[-3.847524,56.09893],"type":"Point"}
}