{
  "type": "Feature",
  "properties": {
    "addr:full":"20 Allandale Road Leicester Leicestershire LE2 2DA",
    "addr:housenumber":"20",
    "addr:postcode":"le2 2da",
    "addr:street":"Allandale Road",
    "iso:country":"GB",
    "sg:address":"20 Allandale Road",
    "sg:city":"Leicester",
    "sg:classifiers":[
        {
            "category":"Shopping",
            "subcategory":"Clothing, Apparel, & Fashions",
            "type":"Retail Goods"
        }
    ],
    "sg:phone":"+44 116 270 2555",
    "sg:postcode":"LE2 2DA",
    "sg:province":"Leicestershire",
    "sg:tags":[
        "shop",
        "retailer",
        "clothing"
    ],
    "wof:name":"L T Overseas Ltd.",
    "wof:placetype":"venue"
},
  "geometry": {"coordinates":[-1.099766016,52.6166992188],"type":"Point"}
}