{
  "type": "Feature",
  "properties": {
    "iso:country":"GB",
    "sg:address":"43 High Street, Burley Marsh",
    "sg:city":"Skegness",
    "sg:classifiers":[
        {
            "category":"Fast Food",
            "type":"Food & Drink"
        }
    ],
    "sg:phone":"+44 1754 810406",
    "sg:postcode":"PE24 5JP",
    "sg:province":"Lincolnshire",
    "sg:tags":[
        "away",
        "meal",
        "outlet",
        "take"
    ],
    "wof:name":"Golden Mill Takeaway",
    "wof:placetype":"venue"
},
  "geometry": {"coordinates":[0.2445430011,53.1619262695],"type":"Point"}
}