{
  "type": "Feature",
  "properties": {
    "iso:country":"GB",
    "sg:address":"Jersey Marine Works, Fabian Way",
    "sg:city":"Swansea",
    "sg:classifiers":[
        {
            "category":"Autos & Motor Vehicles",
            "subcategory":"Fuel & Gas Station",
            "type":"Retail Goods"
        }
    ],
    "sg:phone":"+44 1792 814156",
    "sg:postcode":"SA1 8SD",
    "sg:province":"Neath Port Talbot",
    "sg:tags":[
        "petrol",
        "filling"
    ],
    "wof:name":"Gulf Service Station",
    "wof:placetype":"venue"
},
  "geometry": {"coordinates":[-3.940929,51.623154],"type":"Point"}
}