{
  "type": "Feature",
  "properties": {
    "iso:country":"GB",
    "sg:address":"39 Beast Banks",
    "sg:city":"Kendal",
    "sg:classifiers":[
        {
            "category":"Professional",
            "subcategory":"Computer Services",
            "type":"Services"
        }
    ],
    "sg:postcode":"LA9 4JJ",
    "sg:province":"Cumbria",
    "sg:tags":[
        "system",
        "software"
    ],
    "wof:name":"Hi-Drive I T  Ltd.",
    "wof:placetype":"venue"
},
  "geometry": {"coordinates":[-2.751281,54.325417],"type":"Point"}
}