{
  "type": "Feature",
  "properties": {
    "addr:full":"Castle Road, Wroxall Ventnor Isle of Wight PO38 3DP",
    "addr:postcode":"po38 3dp",
    "addr:street":"Castle Road",
    "iso:country":"GB",
    "sg:address":"Castle Road, Wroxall",
    "sg:city":"Ventnor",
    "sg:classifiers":[
        {
            "category":"Education",
            "subcategory":"School",
            "type":"Public Place"
        },
        {
            "category":"Government",
            "subcategory":"Office",
            "type":"Public Place"
        }
    ],
    "sg:phone":"+44 1983 852290",
    "sg:postcode":"PO38 3DP",
    "sg:province":"Isle of Wight",
    "sg:tags":[
        "local",
        "authority"
    ],
    "wof:name":"Wroxall County Primary School",
    "wof:placetype":"venue"
},
  "geometry": {"coordinates":[-1.2228820324,50.6154060364],"type":"Point"}
}