{
  "type": "Feature",
  "properties": {
    "addr:full":"20 Providence Pl Melton Constable Norfolk NR24 2HZ",
    "addr:housenumber":"20",
    "addr:postcode":"nr24 2hz",
    "addr:street":"Providence Pl",
    "iso:country":"GB",
    "sg:address":"20 Providence Pl",
    "sg:city":"Melton Constable",
    "sg:classifiers":[
        {
            "category":"Building & Trades",
            "subcategory":"Equipment Rental",
            "type":"Services"
        }
    ],
    "sg:phone":"+44 1263 861080",
    "sg:postcode":"NR24 2HZ",
    "sg:province":"Norfolk",
    "sg:tags":[
        "plant",
        "machinery"
    ],
    "wof:name":"N Clarke",
    "wof:placetype":"venue"
},
  "geometry": {"coordinates":[1.0642420053,52.8570213318],"type":"Point"}
}