{
  "type": "Feature",
  "properties": {
    "iso:country":"GB",
    "sg:address":"Redworth Road",
    "sg:city":"Shildon",
    "sg:classifiers":[
        {
            "category":"Autos & Motor Vehicles",
            "subcategory":"Automobile Sales",
            "type":"Retail Goods"
        }
    ],
    "sg:phone":"+44 1388 778492",
    "sg:postcode":"DL4 2JP",
    "sg:province":"Durham",
    "sg:tags":[
        "car"
    ],
    "wof:name":"Shildon Motor Co",
    "wof:placetype":"venue"
},
  "geometry": {"coordinates":[-1.646429,54.625336],"type":"Point"}
}