{
  "type": "Feature",
  "properties": {
    "addr:full":"97 Lumley Rd Skegness Lincolnshire PE25 3LY",
    "addr:housenumber":"97",
    "addr:postcode":"pe25 3ly",
    "addr:street":"Lumley Rd",
    "iso:country":"GB",
    "sg:address":"97 Lumley Rd",
    "sg:city":"Skegness",
    "sg:classifiers":[
        {
            "category":"Banks & Credit Unions",
            "subcategory":"Bank",
            "type":"Services"
        }
    ],
    "sg:phone":"+44 1754 764785",
    "sg:postcode":"PE25 3LY",
    "sg:province":"Lincolnshire",
    "wof:name":"NatWest",
    "wof:placetype":"venue"
},
  "geometry": {"coordinates":[0.3416849971,53.1424560547],"type":"Point"}
}