{
  "type": "Feature",
  "properties": {
    "iso:country":"GB",
    "sg:address":"14-16 Old Market",
    "sg:city":"Halifax",
    "sg:classifiers":[
        {
            "category":"Education",
            "subcategory":"Dance Studio",
            "type":"Public Place"
        }
    ],
    "sg:phone":"+44 1422 351958",
    "sg:postcode":"HX1 1TN",
    "sg:province":"West Yorkshire",
    "sg:tags":[
        "school",
        "dancing"
    ],
    "wof:name":"Starburst",
    "wof:placetype":"venue"
},
  "geometry": {"coordinates":[-1.8599640131,53.7235984802],"type":"Point"}
}