{
  "type": "Feature",
  "properties": {
    "addr:full":"C/o Peter Augustie & Co, 1 Dukes Passage Brighton East Sussex BN1 1BS",
    "addr:housenumber":"/ o;1",
    "addr:postcode":"bn1 1bs",
    "addr:street":"C;Dukes Passage",
    "iso:country":"GB",
    "sg:address":"C/o Peter Augustie & Co, 1 Dukes Passage",
    "sg:city":"Brighton",
    "sg:classifiers":[
        {
            "category":"Professional",
            "subcategory":"Engineering",
            "type":"Services"
        },
        {
            "category":"Building & Trades",
            "subcategory":"Construction",
            "type":"Services"
        }
    ],
    "sg:postcode":"BN1 1BS",
    "sg:province":"East Sussex",
    "sg:tags":[
        "consulting",
        "builder",
        "engineer"
    ],
    "wof:name":"Environ Construction Ltd",
    "wof:placetype":"venue"
},
  "geometry": {"coordinates":[-0.14276,50.82288],"type":"Point"}
}