{
  "type": "Feature",
  "properties": {
    "iso:country":"GB",
    "sg:address":"58 Canterbury Road",
    "sg:city":"Whitstable",
    "sg:classifiers":[
        {
            "category":"Restaurant",
            "type":"Food & Drink"
        }
    ],
    "sg:phone":"+44 1227 261268",
    "sg:postcode":"CT5 4HD",
    "sg:province":"Kent",
    "sg:tags":[
        "-",
        "english"
    ],
    "wof:name":"Dave's Place",
    "wof:placetype":"venue"
},
  "geometry": {"coordinates":[1.023833,51.352547],"type":"Point"}
}