{
  "type": "Feature",
  "properties": {
    "iso:country":"GB",
    "sg:address":"Unit 2, Manchester Chambers",
    "sg:city":"Oldham",
    "sg:classifiers":[
        {
            "category":"Shopping",
            "subcategory":"Florist",
            "type":"Retail Goods"
        }
    ],
    "sg:phone":"+44 161 624 4775",
    "sg:postcode":"OL1 1LF",
    "sg:province":"Lancashire",
    "wof:name":"Elle Floral Design",
    "wof:placetype":"venue"
},
  "geometry": {"coordinates":[-2.115819,53.541538],"type":"Point"}
}