{
  "type": "Feature",
  "properties": {
    "addr:full":"24 Molesworth Terrace, Millbrook Torpoint Cornwall PL10 1DH",
    "addr:housenumber":"24",
    "addr:postcode":"pl10 1dh",
    "addr:street":"Molesworth Terrace",
    "iso:country":"GB",
    "sg:address":"24 Molesworth Terrace, Millbrook",
    "sg:city":"Torpoint",
    "sg:classifiers":[
        {
            "category":"Professional",
            "subcategory":"Accounting & Tax Preparation",
            "type":"Services"
        }
    ],
    "sg:postcode":"PL10 1DH",
    "sg:province":"Cornwall",
    "sg:tags":[
        "accountant"
    ],
    "wof:name":"Clive Murphy & Co.",
    "wof:placetype":"venue"
},
  "geometry": {"coordinates":[-4.212434,50.34779],"type":"Point"}
}