{
  "type": "Feature",
  "properties": {
    "addr:full":"Manor Farm Lincoln Lincolnshire LN1 2JR",
    "addr:postcode":"ln1 2jr",
    "addr:street":"Manor",
    "iso:country":"GB",
    "sg:address":"Manor Farm",
    "sg:city":"Lincoln",
    "sg:classifiers":[
        {
            "category":"Home & Garden",
            "subcategory":"Garden Supply",
            "type":"Retail Goods"
        }
    ],
    "sg:phone":"+44 1777 228641",
    "sg:postcode":"LN1 2JR",
    "sg:province":"Lincolnshire",
    "sg:tags":[
        "bulb",
        "grower"
    ],
    "wof:name":"Furrowland Ltd.",
    "wof:placetype":"venue"
},
  "geometry": {"coordinates":[-0.662635982,53.3160209656],"type":"Point"}
}