{
  "type": "Feature",
  "properties": {
    "addr:full":"16 Broadway North Walsall West Midlands WS1 2AN",
    "addr:housenumber":"16",
    "addr:postcode":"ws1 2an",
    "addr:street":"Broadway North",
    "iso:country":"GB",
    "sg:address":"16 Broadway North",
    "sg:city":"Walsall",
    "sg:classifiers":[
        {
            "category":"Wholesale",
            "subcategory":"Construction Materials",
            "type":"Manufacturing & Wholesale Goods"
        }
    ],
    "sg:postcode":"WS1 2AN",
    "sg:province":"West Midlands",
    "sg:tags":[
        "coating",
        "powder"
    ],
    "wof:name":"Altra Alloys Ltd",
    "wof:placetype":"venue"
},
  "geometry": {"coordinates":[-1.9733339548,52.5884246826],"type":"Point"}
}