{
  "type": "Feature",
  "properties": {
    "iso:country":"GB",
    "sg:address":"67 Union Street, Bridgtown",
    "sg:city":"Cannock",
    "sg:classifiers":[
        {
            "category":"Autos & Motor Vehicles",
            "subcategory":"Automobile Sales",
            "type":"Retail Goods"
        }
    ],
    "sg:phone":"+44 1543 506463",
    "sg:postcode":"WS11 3BS",
    "sg:province":"Staffordshire",
    "sg:tags":[
        "car"
    ],
    "wof:name":"Tudor Motors",
    "wof:placetype":"venue"
},
  "geometry": {"coordinates":[-2.025569,52.674267],"type":"Point"}
}