{
  "type": "Feature",
  "properties": {
    "addr:full":"5 Buckingham Road West Stockport Cheshire SK4 4AZ",
    "addr:housenumber":"5",
    "addr:postcode":"sk4 4az",
    "addr:street":"Buckingham Road West",
    "iso:country":"GB",
    "sg:address":"5 Buckingham Road West",
    "sg:city":"Stockport",
    "sg:classifiers":[
        {
            "category":"Building & Trades",
            "subcategory":"Landscaping Services",
            "type":"Services"
        }
    ],
    "sg:phone":"+44 161 432 2658",
    "sg:postcode":"SK4 4AZ",
    "sg:province":"Cheshire",
    "sg:tags":[
        "landscape",
        "contractor"
    ],
    "wof:name":"Mike Heneghan Gardening Services",
    "wof:placetype":"venue"
},
  "geometry": {"coordinates":[-2.188459,53.424423],"type":"Point"}
}