{
  "type": "Feature",
  "properties": {
    "iso:country":"GB",
    "sg:address":"20 Highbury Gro",
    "sg:city":"London",
    "sg:classifiers":[
        {
            "category":"Professional",
            "subcategory":"Computer Services",
            "type":"Services"
        }
    ],
    "sg:phone":"+44 20 7354 2219",
    "sg:postcode":"N5 2EA",
    "sg:province":"Greater London",
    "sg:tags":[
        "system",
        "software"
    ],
    "wof:name":"Raspberry Computing",
    "wof:placetype":"venue"
},
  "geometry": {"coordinates":[-0.0971840024,51.5481567383],"type":"Point"}
}