{
  "type": "Feature",
  "properties": {
    "iso:country":"GB",
    "sg:address":"251 Marsland Rd, Sale",
    "sg:city":"Manchester",
    "sg:classifiers":[
        {
            "category":"Shopping",
            "subcategory":"Florist",
            "type":"Retail Goods"
        }
    ],
    "sg:postcode":"M33 7UN",
    "sg:province":"Cheshire",
    "wof:name":"Gardners Corner",
    "wof:placetype":"venue"
},
  "geometry": {"coordinates":[-2.328797102,53.4183578491],"type":"Point"}
}