{
  "type": "Feature",
  "properties": {
    "addr:full":"111a High Street Lincoln Lincolnshire LN5 7PY",
    "addr:housenumber":"111a",
    "addr:postcode":"ln5 7py",
    "addr:street":"High Street",
    "iso:country":"GB",
    "sg:address":"111a High Street",
    "sg:city":"Lincoln",
    "sg:classifiers":[
        {
            "category":"Shopping",
            "subcategory":"Music",
            "type":"Retail Goods"
        },
        {
            "category":"Retail",
            "subcategory":"Repair Shop",
            "type":"Services"
        }
    ],
    "sg:phone":"+44 1522 512353",
    "sg:postcode":"LN5 7PY",
    "sg:province":"Lincolnshire",
    "sg:tags":[
        "instrument",
        "restoration",
        "musical"
    ],
    "wof:name":"The City Music Workshop",
    "wof:placetype":"venue"
},
  "geometry": {"coordinates":[-0.544531,53.222054],"type":"Point"}
}