{
  "type": "Feature",
  "properties": {
    "addr:full":"58 Rollesby Rd Chessington Surrey KT9 2BZ",
    "addr:housenumber":"58",
    "addr:postcode":"kt9 2bz",
    "addr:street":"Rollesby Rd",
    "iso:country":"GB",
    "sg:address":"58 Rollesby Rd",
    "sg:city":"Chessington",
    "sg:classifiers":[
        {
            "category":"Recreation",
            "subcategory":"Dog Park",
            "type":"Entertainment"
        }
    ],
    "sg:postcode":"KT9 2BZ",
    "sg:province":"Surrey",
    "wof:name":"Dogs Naturally",
    "wof:placetype":"venue"
},
  "geometry": {"coordinates":[-0.289285,51.358994],"type":"Point"}
}