{
  "type": "Feature",
  "properties": {
    "addr:full":"18 Levens Walk Wigan Lancashire WN5 9LU",
    "addr:housenumber":"18",
    "addr:postcode":"wn5 9lu",
    "addr:street":"Levens Walk",
    "iso:country":"GB",
    "sg:address":"18 Levens Walk",
    "sg:city":"Wigan",
    "sg:classifiers":[
        {
            "category":"Bus Charters",
            "type":"Transportation"
        }
    ],
    "sg:phone":"+44 1942 217000",
    "sg:postcode":"WN5 9LU",
    "sg:province":"Lancashire",
    "sg:tags":[
        "hire",
        "coach"
    ],
    "wof:name":"Aries Travel Services",
    "wof:placetype":"venue"
},
  "geometry": {"coordinates":[-2.676004,53.542477],"type":"Point"}
}