{
  "type": "Feature",
  "properties": {
    "iso:country":"GB",
    "sg:address":"4 Ynys Bridge Court, Gwaelod-y-garth",
    "sg:city":"Cardiff",
    "sg:classifiers":[
        {
            "category":"Professional",
            "subcategory":"Accounting & Tax Preparation",
            "type":"Services"
        }
    ],
    "sg:phone":"+44 29 2081 4114",
    "sg:postcode":"CF15 9SS",
    "sg:province":"Caerphilly",
    "sg:tags":[
        "accountant",
        "activity"
    ],
    "wof:name":"Williams Ross Ltd",
    "wof:placetype":"venue"
},
  "geometry": {"coordinates":[-3.261314,51.535191],"type":"Point"}
}