{
  "type": "Feature",
  "properties": {
    "addr:full":"50 Wrawby Street Brigg Lincolnshire DN20 8JB",
    "addr:housenumber":"50",
    "addr:postcode":"dn20 8jb",
    "addr:street":"Wrawby Street",
    "iso:country":"GB",
    "sg:address":"50 Wrawby Street",
    "sg:city":"Brigg",
    "sg:classifiers":[
        {
            "category":"Shopping",
            "subcategory":"Florist",
            "type":"Retail Goods"
        }
    ],
    "sg:postcode":"DN20 8JB",
    "sg:province":"Lincolnshire",
    "wof:name":"The Wold Florist",
    "wof:placetype":"venue"
},
  "geometry": {"coordinates":[-0.489051,53.552242],"type":"Point"}
}