{
  "type": "Feature",
  "properties": {
    "iso:country":"GB",
    "sg:address":"18 Wynn Stay Road",
    "sg:city":"Colwyn Bay",
    "sg:classifiers":[
        {
            "category":"Professional",
            "subcategory":"Computer Services",
            "type":"Services"
        }
    ],
    "sg:phone":"+44 1492 535000",
    "sg:postcode":"LL29 8NB",
    "sg:province":"Conwy",
    "sg:tags":[
        "system",
        "software"
    ],
    "wof:name":"Computer Solutions Cymru Ltd.",
    "wof:placetype":"venue"
},
  "geometry": {"coordinates":[-3.729637,53.296783],"type":"Point"}
}