{
  "type": "Feature",
  "properties": {
    "addr:full":"4 Berkeley Avenue Ilford Essex IG5 0UR",
    "addr:housenumber":"4",
    "addr:postcode":"ig5 0ur",
    "addr:street":"Berkeley Avenue Ilford",
    "iso:country":"GB",
    "sg:address":"4 Berkeley Avenue",
    "sg:city":"Ilford",
    "sg:classifiers":[
        {
            "category":"Manufacturing",
            "subcategory":"Building Materials",
            "type":"Manufacturing & Wholesale Goods"
        }
    ],
    "sg:postcode":"IG5 0UR",
    "sg:province":"Essex",
    "sg:tags":[
        "tarmac",
        "asphalt"
    ],
    "wof:name":"Asmac & Co. (Surfacing) Ltd.",
    "wof:placetype":"venue"
},
  "geometry": {"coordinates":[0.069382,51.591724],"type":"Point"}
}