{
  "type": "Feature",
  "properties": {
    "iso:country":"GB",
    "sg:address":"72 Cathcart Road, Rutherglen",
    "sg:city":"Glasgow",
    "sg:classifiers":[
        {
            "category":"Retail",
            "subcategory":"Laundry & Dry Cleaning",
            "type":"Services"
        }
    ],
    "sg:phone":"+44 141 647 4601",
    "sg:postcode":"G73 2RD",
    "sg:province":"Glasgow City",
    "sg:tags":[
        "alteration"
    ],
    "wof:name":"Giffen & Bissett Ltd.",
    "wof:placetype":"venue"
},
  "geometry": {"coordinates":[-4.223704,55.826],"type":"Point"}
}