{
  "type": "Feature",
  "properties": {
    "addr:full":"West Sherford, Brixton Plymouth Devon PL8 2DP",
    "addr:postcode":"pl8 2dp",
    "addr:street":"West Sherford",
    "iso:country":"GB",
    "sg:address":"West Sherford, Brixton",
    "sg:city":"Plymouth",
    "sg:classifiers":[
        {
            "category":"Farming",
            "subcategory":"Livestock Farm",
            "type":"Manufacturing & Wholesale Goods"
        }
    ],
    "sg:phone":"+44 1752 880253",
    "sg:postcode":"PL8 2DP",
    "sg:province":"Devon",
    "sg:tags":[
        "others"
    ],
    "wof:name":"J Haimes & Son",
    "wof:placetype":"venue"
},
  "geometry": {"coordinates":[-4.034558773,50.3514595032],"type":"Point"}
}