{
  "type": "Feature",
  "properties": {
    "iso:country":"GB",
    "sg:address":"21 Llwyn-yr-eos",
    "sg:city":"Swansea",
    "sg:classifiers":[
        {
            "category":"Community Center",
            "type":"Public Place"
        }
    ],
    "sg:phone":"+44 1792 702660",
    "sg:postcode":"SA6 6AT",
    "sg:province":"Swansea",
    "sg:tags":[
        "recreation",
        "leisure",
        "centre"
    ],
    "wof:name":"C.W Leisure",
    "wof:placetype":"venue"
},
  "geometry": {"coordinates":[-3.9355471134,51.6703796387],"type":"Point"}
}