{
  "type": "Feature",
  "properties": {
    "addr:full":"702 London Rd Sutton Surrey SM3 9BY",
    "addr:housenumber":"702",
    "addr:postcode":"sm3 9by",
    "addr:street":"London Rd",
    "iso:country":"GB",
    "sg:address":"702 London Rd",
    "sg:city":"Sutton",
    "sg:classifiers":[
        {
            "category":"Shopping",
            "subcategory":"Stationery & Office Supplies",
            "type":"Retail Goods"
        }
    ],
    "sg:phone":"+44 20 8641 1122",
    "sg:postcode":"SM3 9BY",
    "sg:province":"Surrey",
    "wof:name":"Cosmic Business Centre Ltd",
    "wof:placetype":"venue"
},
  "geometry": {"coordinates":[-0.221967,51.376171],"type":"Point"}
}