{
  "type": "Feature",
  "properties": {
    "iso:country":"GB",
    "sg:address":"Jacobs Well Manchester Rd",
    "sg:city":"Bradford",
    "sg:classifiers":[
        {
            "category":"Museum",
            "subcategory":"Art Museum",
            "type":"Entertainment"
        }
    ],
    "sg:phone":"+44 1274 754009",
    "sg:postcode":"BD1 5RW",
    "sg:province":"West Yorkshire",
    "sg:tags":[
        "gallery"
    ],
    "wof:name":"The Peace Museum",
    "wof:placetype":"venue"
},
  "geometry": {"coordinates":[-1.753999,53.789734],"type":"Point"}
}