{
  "type": "Feature",
  "properties": {
    "addr:full":"Victoria Centre, Knifesmithgate Chesterfield Derbyshire S40 1RL",
    "addr:postcode":"s40 1rl",
    "addr:street":"Knifesmithgate",
    "iso:country":"GB",
    "sg:address":"Victoria Centre, Knifesmithgate",
    "sg:city":"Chesterfield",
    "sg:classifiers":[
        {
            "category":"Shopping",
            "subcategory":"Crafts & Fabrics",
            "type":"Retail Goods"
        }
    ],
    "sg:postcode":"S40 1RL",
    "sg:province":"Derbyshire",
    "sg:tags":[
        "shop",
        "needlecraft",
        "wool"
    ],
    "wof:name":"The Wool Shop",
    "wof:placetype":"venue"
},
  "geometry": {"coordinates":[-1.4281769991,53.236415863],"type":"Point"}
}