{
  "type": "Feature",
  "properties": {
    "iso:country":"GB",
    "sg:address":"16 Brearley Way",
    "sg:city":"Gateshead",
    "sg:classifiers":[
        {
            "category":"Shopping",
            "subcategory":"Department Store",
            "type":"Retail Goods"
        }
    ],
    "sg:postcode":"NE10 9JL",
    "sg:province":"Tyne and Wear",
    "wof:name":"Brearley Way Stores",
    "wof:placetype":"venue"
},
  "geometry": {"coordinates":[-1.5762269497,54.9509620667],"type":"Point"}
}