{
  "type": "Feature",
  "properties": {
    "addr:full":"Unit 42, Hissmans Ho, London Greater London SW6 4TJ",
    "addr:housenumber":"unit 42",
    "addr:postcode":"sw6 4tj",
    "addr:street":"Hissmans Ho",
    "iso:country":"GB",
    "sg:address":"Unit 42, Hissmans Ho,",
    "sg:city":"London",
    "sg:classifiers":[
        {
            "category":"Professional",
            "subcategory":"Business Services",
            "type":"Services"
        }
    ],
    "sg:postcode":"SW6 4TJ",
    "sg:province":"Greater London",
    "sg:tags":[
        "import",
        "export",
        "agent"
    ],
    "wof:name":"Wright Beverages International Ltd",
    "wof:placetype":"venue"
},
  "geometry": {"coordinates":[-0.2026,51.473999],"type":"Point"}
}