{
  "type": "Feature",
  "properties": {
    "addr:full":"121 Elliott Road March Cambridgeshire PE15 8BT",
    "addr:housenumber":"121",
    "addr:postcode":"pe15 8bt",
    "addr:street":"Elliott Road",
    "iso:country":"GB",
    "sg:address":"121 Elliott Road",
    "sg:city":"March",
    "sg:classifiers":[
        {
            "category":"Real Estate",
            "subcategory":"Architect",
            "type":"Services"
        }
    ],
    "sg:postcode":"PE15 8BT",
    "sg:province":"Cambridgeshire",
    "sg:tags":[
        "architectural"
    ],
    "wof:name":"Johnson Design Partnership",
    "wof:placetype":"venue"
},
  "geometry": {"coordinates":[0.073357,52.55452],"type":"Point"}
}