{
  "type": "Feature",
  "properties": {
    "iso:country":"GB",
    "sg:address":"Pityoulish Farm Cottage",
    "sg:city":"Aviemore",
    "sg:classifiers":[
        {
            "category":"Banks & Credit Unions",
            "subcategory":"Investment Brokerage",
            "type":"Services"
        }
    ],
    "sg:postcode":"PH22 1RD",
    "sg:province":"Highland",
    "sg:tags":[
        "contractor"
    ],
    "wof:name":"Stephen & Colin George",
    "wof:placetype":"venue"
},
  "geometry": {"coordinates":[-3.828779,57.198669],"type":"Point"}
}