{
  "type": "Feature",
  "properties": {
    "addr:full":"78 Midway Road, Midway Swadlincote Derbyshire DE11 7PG",
    "addr:housenumber":"78",
    "addr:postcode":"de11 7pg",
    "addr:street":"Midway Road",
    "iso:country":"GB",
    "sg:address":"78 Midway Road, Midway",
    "sg:city":"Swadlincote",
    "sg:classifiers":[
        {
            "category":"Freight",
            "type":"Transportation"
        }
    ],
    "sg:postcode":"DE11 7PG",
    "sg:province":"Derbyshire",
    "sg:tags":[
        "haulage",
        "road"
    ],
    "wof:name":"A R Cantrill Road Haulage",
    "wof:placetype":"venue"
},
  "geometry": {"coordinates":[-1.549217,52.781006],"type":"Point"}
}