{
  "type": "Feature",
  "properties": {
    "addr:full":"46 Highclere Gardens, Knaphill Woking Surrey GU21 2LR",
    "addr:housenumber":"46",
    "addr:postcode":"gu21 2lr",
    "addr:street":"Highclere Gardens;Woking",
    "iso:country":"GB",
    "sg:address":"46 Highclere Gardens, Knaphill",
    "sg:city":"Woking",
    "sg:classifiers":[
        {
            "category":"Building & Trades",
            "subcategory":"Construction",
            "type":"Services"
        }
    ],
    "sg:phone":"+44 1483 480498",
    "sg:postcode":"GU21 2LR",
    "sg:province":"Surrey",
    "sg:tags":[
        "bricklayer",
        "roofing",
        "bricklaying"
    ],
    "wof:name":"Edmond E Hodges-Stubbs",
    "wof:placetype":"venue"
},
  "geometry": {"coordinates":[-0.615760982,51.3197669983],"type":"Point"}
}