{
  "type": "Feature",
  "properties": {
    "iso:country":"GB",
    "sg:address":"Seagate",
    "sg:city":"Peterhead",
    "sg:classifiers":[
        {
            "category":"Building & Trades",
            "subcategory":"Pest Control",
            "type":"Services"
        },
        {
            "category":"Building & Trades",
            "subcategory":"Construction",
            "type":"Services"
        }
    ],
    "sg:phone":"+44 1779 474455",
    "sg:postcode":"AB42 1JP",
    "sg:province":"Aberdeenshire",
    "sg:tags":[
        "painting",
        "decorator",
        "painter",
        "contractor"
    ],
    "wof:name":"Davidsons",
    "wof:placetype":"venue"
},
  "geometry": {"coordinates":[-1.775414,57.506409],"type":"Point"}
}