{
  "type": "Feature",
  "properties": {
    "iso:country":"GB",
    "sg:address":"225-227 Gannow La",
    "sg:city":"Burnley",
    "sg:classifiers":[
        {
            "category":"Health Services",
            "subcategory":"Doctor",
            "type":"Services"
        }
    ],
    "sg:phone":"+44 1282 423295",
    "sg:postcode":"BB12 6HY",
    "sg:province":"Lancashire",
    "sg:tags":[
        "practitioners"
    ],
    "wof:name":"Rosegrove Surgery",
    "wof:placetype":"venue"
},
  "geometry": {"coordinates":[-2.279886961,53.789226532],"type":"Point"}
}