{
  "type": "Feature",
  "properties": {
    "addr:full":"16 West End, Holbeach Spalding Cambridgeshire PE12 7LW",
    "addr:housenumber":"16",
    "addr:postcode":"pe12 7lw",
    "addr:street":"West End",
    "iso:country":"GB",
    "sg:address":"16 West End, Holbeach",
    "sg:city":"Spalding",
    "sg:classifiers":[
        {
            "category":"Personal",
            "subcategory":"Beauty Salon",
            "type":"Services"
        },
        {
            "category":"Personal",
            "subcategory":"Barber",
            "type":"Services"
        }
    ],
    "sg:phone":"+44 1406 423224",
    "sg:postcode":"PE12 7LW",
    "sg:province":"Cambridgeshire",
    "sg:tags":[
        "unisex",
        "hairdresser"
    ],
    "wof:name":"The Hairport",
    "wof:placetype":"venue"
},
  "geometry": {"coordinates":[0.0123220002,52.8041114807],"type":"Point"}
}