{
  "type": "Feature",
  "properties": {
    "iso:country":"GB",
    "sg:address":"131 Portland Street",
    "sg:city":"Manchester",
    "sg:classifiers":[
        {
            "category":"Fast Food",
            "type":"Food & Drink"
        }
    ],
    "sg:phone":"+44 161 236 7527",
    "sg:postcode":"M1 4PY",
    "sg:province":"Greater Manchester",
    "sg:tags":[
        "away",
        "take"
    ],
    "wof:name":"K F C",
    "wof:placetype":"venue"
},
  "geometry": {"coordinates":[-2.242127,53.47617],"type":"Point"}
}