{
  "type": "Feature",
  "properties": {
    "addr:full":"174 Boreham Rd Warminster Somerset BA12 9HD",
    "addr:housenumber":"174",
    "addr:postcode":"ba12 9hd",
    "addr:street":"Boreham Rd",
    "iso:country":"GB",
    "sg:address":"174 Boreham Rd",
    "sg:city":"Warminster",
    "sg:classifiers":[
        {
            "category":"Bars & Pubs",
            "type":"Food & Drink"
        }
    ],
    "sg:phone":"+44 1985 212335",
    "sg:postcode":"BA12 9HD",
    "sg:province":"Somerset",
    "sg:tags":[
        "pubs",
        "inn"
    ],
    "wof:name":"The Yew Tree",
    "wof:placetype":"venue"
},
  "geometry": {"coordinates":[-2.165301,51.19949],"type":"Point"}
}