{
  "type": "Feature",
  "properties": {
    "iso:country":"GB",
    "sg:address":"6 Ashton Sq",
    "sg:city":"Dunstable",
    "sg:classifiers":[
        {
            "category":"Organizations",
            "subcategory":"Community Association",
            "type":"Services"
        }
    ],
    "sg:postcode":"LU6 3SN",
    "sg:province":"Bedfordshire",
    "sg:tags":[
        "relation",
        "public"
    ],
    "wof:name":"Arnold Harris Associates",
    "wof:placetype":"venue"
},
  "geometry": {"coordinates":[-0.525939,51.890862],"type":"Point"}
}