{
  "type": "Feature",
  "properties": {
    "addr:full":"Hazelhead Park Aberdeen Aberdeen City AB15 8BB",
    "addr:postcode":"ab15 8bb",
    "addr:street":"Park",
    "iso:country":"GB",
    "sg:address":"Hazelhead Park",
    "sg:city":"Aberdeen",
    "sg:classifiers":[
        {
            "category":"Sports & Exercise",
            "subcategory":"Stables",
            "type":"Entertainment"
        }
    ],
    "sg:phone":"+44 1224 315703",
    "sg:postcode":"AB15 8BB",
    "sg:province":"Aberdeen City",
    "sg:tags":[
        "education",
        "equestrian"
    ],
    "wof:name":"Hayfield International Ltd.",
    "wof:placetype":"venue"
},
  "geometry": {"coordinates":[-2.17037,57.14072],"type":"Point"}
}