{
  "type": "Feature",
  "properties": {
    "iso:country":"GB",
    "sg:address":"1a Howard Street",
    "sg:city":"Oxford",
    "sg:classifiers":[
        {
            "category":"Organizations",
            "subcategory":"Non-profit Organization",
            "type":"Services"
        }
    ],
    "sg:phone":"+44 1865 245156",
    "sg:postcode":"OX4 3AY",
    "sg:province":"Oxfordshire",
    "sg:tags":[
        "organisation",
        "voluntary",
        "charity"
    ],
    "wof:name":"I F A W",
    "wof:placetype":"venue"
},
  "geometry": {"coordinates":[-1.2349499464,51.7393074036],"type":"Point"}
}