{
  "type": "Feature",
  "properties": {
    "iso:country":"GB",
    "sg:address":"2 Mottram Moor, Mottram",
    "sg:city":"Hyde",
    "sg:classifiers":[
        {
            "category":"Retail",
            "subcategory":"Event Space",
            "type":"Services"
        }
    ],
    "sg:phone":"+44 1457 763102",
    "sg:postcode":"SK14 6LA",
    "sg:province":"Cheshire",
    "sg:tags":[
        "function",
        "room"
    ],
    "wof:name":"The Junction Inn",
    "wof:placetype":"venue"
},
  "geometry": {"coordinates":[-2.0184791088,53.4441986084],"type":"Point"}
}