{
  "type": "Feature",
  "properties": {
    "iso:country":"GB",
    "sg:address":"3 The Precinct",
    "sg:city":"Porthcawl",
    "sg:classifiers":[
        {
            "category":"Personal",
            "subcategory":"Beauty Salon",
            "type":"Services"
        },
        {
            "category":"Personal",
            "subcategory":"Barber",
            "type":"Services"
        }
    ],
    "sg:phone":"+44 1656 788338",
    "sg:postcode":"CF36 3RF",
    "sg:province":"Bridgend",
    "sg:tags":[
        "unisex",
        "hairdresser"
    ],
    "wof:name":"Classic Look",
    "wof:placetype":"venue"
},
  "geometry": {"coordinates":[-3.7051229477,51.4902877808],"type":"Point"}
}