{
  "type": "Feature",
  "properties": {
    "iso:country":"GB",
    "sg:address":"74 Eastworth Rd",
    "sg:city":"Chertsey",
    "sg:classifiers":[
        {
            "category":"Arts & Performance",
            "subcategory":"Music",
            "type":"Entertainment"
        }
    ],
    "sg:phone":"+44 1932 561281",
    "sg:postcode":"KT16 8DR",
    "sg:province":"Surrey",
    "sg:tags":[
        "mobile",
        "disco"
    ],
    "wof:name":"Golden Action Disco",
    "wof:placetype":"venue"
},
  "geometry": {"coordinates":[-0.5021809936,51.3856773376],"type":"Point"}
}