{
  "type": "Feature",
  "properties": {
    "addr:full":"Longbridge, Cherry Tree La Iver Berkshire SL0 0EE",
    "addr:postcode":"sl0 0ee",
    "addr:street":"Longbridge;La Iver",
    "iso:country":"GB",
    "sg:address":"Longbridge, Cherry Tree La",
    "sg:city":"Iver",
    "sg:classifiers":[
        {
            "category":"Communications",
            "subcategory":"Film & Video Production",
            "type":"Services"
        }
    ],
    "sg:phone":"+44 1895 234723",
    "sg:postcode":"SL0 0EE",
    "sg:province":"Berkshire",
    "sg:tags":[
        "tv",
        "studio"
    ],
    "wof:name":"C & D Rigging Equipment",
    "wof:placetype":"venue"
},
  "geometry": {"coordinates":[-0.494724,51.542145],"type":"Point"}
}