{
  "type": "Feature",
  "properties": {
    "iso:country":"GB",
    "sg:address":"165/167 Dalry Road",
    "sg:city":"Edinburgh",
    "sg:classifiers":[
        {
            "category":"Professional",
            "subcategory":"Computer Services",
            "type":"Services"
        }
    ],
    "sg:phone":"+44 131 346 0719",
    "sg:postcode":"EH11 2EA",
    "sg:province":"City of Edinburgh",
    "sg:tags":[
        "system",
        "software"
    ],
    "wof:name":"E-Net Computers Ltd.",
    "wof:placetype":"venue"
},
  "geometry": {"coordinates":[-3.2213120461,55.9425964355],"type":"Point"}
}