{
  "type": "Feature",
  "properties": {
    "iso:country":"GB",
    "sg:address":"Hazel Farm, Hooks Cross, Watton-at-stone",
    "sg:city":"Hertford",
    "sg:classifiers":[
        {
            "category":"Farming",
            "subcategory":"Livestock Farm",
            "type":"Manufacturing & Wholesale Goods"
        }
    ],
    "sg:postcode":"SG14 2RL",
    "sg:province":"Hertfordshire",
    "sg:tags":[
        "others"
    ],
    "wof:name":"W S Jefferies",
    "wof:placetype":"venue"
},
  "geometry": {"coordinates":[-0.082699,51.796341],"type":"Point"}
}