{
  "type": "Feature",
  "properties": {
    "addr:full":"66 St James Mill Road Industrial Estate, St James Northampton Northamptonshire NN5 5JP",
    "addr:housenumber":"66",
    "addr:postcode":"nn5 5jp",
    "addr:street":"St James Mill Road Industrial Estate",
    "iso:country":"GB",
    "sg:address":"66 St James Mill Road Industrial Estate, St James",
    "sg:city":"Northampton",
    "sg:classifiers":[
        {
            "category":"Retail",
            "subcategory":"Auto Repair",
            "type":"Services"
        }
    ],
    "sg:postcode":"NN5 5JP",
    "sg:province":"Northamptonshire",
    "sg:tags":[
        "car",
        "servicing",
        "radiator"
    ],
    "wof:name":"Northampton Radiators",
    "wof:placetype":"venue"
},
  "geometry": {"coordinates":[-0.9094099998,52.2311782837],"type":"Point"}
}