{
  "type": "Feature",
  "properties": {
    "addr:full":"1 Clifton Street Scarborough North Yorkshire YO12 7SR",
    "addr:housenumber":"1",
    "addr:postcode":"yo12 7sr",
    "addr:street":"Clifton Street",
    "iso:country":"GB",
    "sg:address":"1 Clifton Street",
    "sg:city":"Scarborough",
    "sg:classifiers":[
        {
            "category":"Retail",
            "subcategory":"Auto Repair",
            "type":"Services"
        }
    ],
    "sg:postcode":"YO12 7SR",
    "sg:province":"North Yorkshire",
    "sg:tags":[
        "body",
        "car"
    ],
    "wof:name":"K Smith Autos",
    "wof:placetype":"venue"
},
  "geometry": {"coordinates":[-0.4042490125,54.2836608887],"type":"Point"}
}