{
  "type": "Feature",
  "properties": {
    "addr:full":"39 Blackburn Road, Ribchester Preston Lancashire PR3 3YP",
    "addr:housenumber":"39",
    "addr:postcode":"pr3 3yp",
    "addr:street":"Blackburn Road",
    "iso:country":"GB",
    "sg:address":"39 Blackburn Road, Ribchester",
    "sg:city":"Preston",
    "sg:classifiers":[
        {
            "category":"Food & Beverages",
            "subcategory":"Meat & Fish",
            "type":"Retail Goods"
        }
    ],
    "sg:postcode":"PR3 3YP",
    "sg:province":"Lancashire",
    "sg:tags":[
        "butcher"
    ],
    "wof:name":"D & W Leach",
    "wof:placetype":"venue"
},
  "geometry": {"coordinates":[-2.5321309566,53.8136253357],"type":"Point"}
}