{
  "type": "Feature",
  "properties": {
    "iso:country":"GB",
    "sg:address":"Unit 10 Murdock Rd, Manton La",
    "sg:city":"Bedford",
    "sg:classifiers":[
        {
            "category":"Military Area",
            "subcategory":"Air Force Base",
            "type":"Public Place"
        }
    ],
    "sg:phone":"+44 1234 330000",
    "sg:postcode":"MK41 7PE",
    "sg:province":"Bedfordshire",
    "sg:tags":[
        "taxi",
        "hire",
        "private"
    ],
    "wof:name":"County Cars Executive Travel",
    "wof:placetype":"venue"
},
  "geometry": {"coordinates":[-0.473625,52.154575],"type":"Point"}
}