{
  "type": "Feature",
  "properties": {
    "iso:country":"GB",
    "sg:address":"Bolton Farm, Lyonshall",
    "sg:city":"Kington",
    "sg:classifiers":[
        {
            "category":"Manufacturing",
            "subcategory":"Wood Products",
            "type":"Manufacturing & Wholesale Goods"
        }
    ],
    "sg:phone":"+44 1544 340657",
    "sg:postcode":"HR5 3JY",
    "sg:province":"Herefordshire",
    "sg:tags":[
        "craftsman"
    ],
    "wof:name":"Kingslake Resources Ltd.",
    "wof:placetype":"venue"
},
  "geometry": {"coordinates":[-3.029478,52.203629],"type":"Point"}
}