{
  "type": "Feature",
  "properties": {
    "addr:full":"1-5 The Drive Thornton Heath Surrey CR7 8LB",
    "addr:housenumber":"1-5",
    "addr:postcode":"cr7 8lb",
    "addr:street":"The Drive",
    "iso:country":"GB",
    "sg:address":"1-5 The Drive",
    "sg:city":"Thornton Heath",
    "sg:classifiers":[
        {
            "category":"Personal",
            "type":"Services"
        }
    ],
    "sg:postcode":"CR7 8LB",
    "sg:province":"Surrey",
    "sg:tags":[
        "dressmaker"
    ],
    "wof:name":"Fashion Art",
    "wof:placetype":"venue"
},
  "geometry": {"coordinates":[-0.0956889987,51.398639679],"type":"Point"}
}