{
  "type": "Feature",
  "properties": {
    "addr:full":"Unit 3 Sturminster Newton Dorset DT10 1AZ",
    "addr:housenumber":"unit 3",
    "addr:postcode":"dt10 1az",
    "iso:country":"GB",
    "sg:address":"Unit 3",
    "sg:city":"Sturminster Newton",
    "sg:classifiers":[
        {
            "category":"Manufacturing",
            "subcategory":"Petroleum Products",
            "type":"Manufacturing & Wholesale Goods"
        }
    ],
    "sg:phone":"+44 1258 473377",
    "sg:postcode":"DT10 1AZ",
    "sg:province":"Dorset",
    "sg:tags":[
        "double",
        "glazing"
    ],
    "wof:name":"Newglaze Windows Ltd.",
    "wof:placetype":"venue"
},
  "geometry": {"coordinates":[-2.3066289425,50.9459686279],"type":"Point"}
}