{
  "type": "Feature",
  "properties": {
    "addr:full":"Brick House Farm, Galhampton Yeovil Dorset BA22 7BQ",
    "addr:postcode":"ba22 7bq",
    "addr:street":"Galhampton",
    "iso:country":"GB",
    "sg:address":"Brick House Farm, Galhampton",
    "sg:city":"Yeovil",
    "sg:classifiers":[
        {
            "category":"Farming",
            "subcategory":"Livestock Farm",
            "type":"Manufacturing & Wholesale Goods"
        }
    ],
    "sg:phone":"+44 1963 440429",
    "sg:postcode":"BA22 7BQ",
    "sg:province":"Dorset",
    "sg:tags":[
        "others"
    ],
    "wof:name":"E G Harding",
    "wof:placetype":"venue"
},
  "geometry": {"coordinates":[-2.578948,51.017838],"type":"Point"}
}