{
  "type": "Feature",
  "properties": {
    "iso:country":"GB",
    "sg:address":"Penshurst",
    "sg:city":"Hythe",
    "sg:classifiers":[
        {
            "category":"Building & Trades",
            "subcategory":"Construction",
            "type":"Services"
        }
    ],
    "sg:phone":"+44 1303 268047",
    "sg:postcode":"CT21 5ER",
    "sg:province":"Kent",
    "sg:tags":[
        "builder"
    ],
    "wof:name":"Lainson & Co.  (Lyminge) Ltd.",
    "wof:placetype":"venue"
},
  "geometry": {"coordinates":[1.0804810524,51.0708274841],"type":"Point"}
}