{
  "type": "Feature",
  "properties": {
    "iso:country":"GB",
    "sg:address":"Brook Business Complex, Bennett Street, West Gorton",
    "sg:city":"Manchester",
    "sg:classifiers":[
        {
            "category":"Building & Trades",
            "subcategory":"Equipment Rental",
            "type":"Services"
        }
    ],
    "sg:phone":"+44 161 273 8900",
    "sg:postcode":"M12 5AU",
    "sg:province":"Greater Manchester",
    "sg:tags":[
        "plant",
        "machinery"
    ],
    "wof:name":"Philip Shovlin Plant Hire Ltd.",
    "wof:placetype":"venue"
},
  "geometry": {"coordinates":[-2.20304,53.470261],"type":"Point"}
}