{
  "type": "Feature",
  "properties": {
    "iso:country":"GB",
    "sg:address":"Helland, North Curry",
    "sg:city":"Taunton",
    "sg:classifiers":[
        {
            "category":"Wholesale",
            "subcategory":"Books, Periodicals, & Newspapers",
            "type":"Manufacturing & Wholesale Goods"
        }
    ],
    "sg:phone":"+44 1823 490684",
    "sg:postcode":"TA3 6DU",
    "sg:province":"Devon",
    "sg:tags":[
        "publisher",
        "book",
        "publishing"
    ],
    "wof:name":"Tony Williams Publications Ltd.",
    "wof:placetype":"venue"
},
  "geometry": {"coordinates":[-2.970339,51.022926],"type":"Point"}
}