{
  "type": "Feature",
  "properties": {
    "addr:full":"14 Maxwell Road, Woodston Peterborough Cambridgeshire PE2 7HU",
    "addr:housenumber":"14",
    "addr:postcode":"pe2 7hu",
    "addr:street":"Maxwell Road",
    "iso:country":"GB",
    "sg:address":"14 Maxwell Road, Woodston",
    "sg:city":"Peterborough",
    "sg:classifiers":[
        {
            "category":"Coffee & Tea",
            "type":"Food & Drink"
        }
    ],
    "sg:phone":"+44 1733 361965",
    "sg:postcode":"PE2 7HU",
    "sg:province":"Cambridgeshire",
    "sg:tags":[
        "merchant"
    ],
    "wof:name":"Ringtons Tea",
    "wof:placetype":"venue"
},
  "geometry": {"coordinates":[-0.260249,52.557899],"type":"Point"}
}