{
  "type": "Feature",
  "properties": {
    "addr:full":"28-31 St Ebbes Street Oxford Oxfordshire OX1 1PU",
    "addr:housenumber":"28-31",
    "addr:postcode":"ox1 1pu",
    "addr:street":"St Ebbes Street",
    "iso:country":"GB",
    "sg:address":"28-31 St Ebbes Street",
    "sg:city":"Oxford",
    "sg:classifiers":[
        {
            "category":"Food & Beverages",
            "subcategory":"Meat & Fish",
            "type":"Retail Goods"
        }
    ],
    "sg:phone":"+44 1865 202404",
    "sg:postcode":"OX1 1PU",
    "sg:province":"Oxfordshire",
    "sg:tags":[
        "chip"
    ],
    "wof:name":"Riverside Restaurants Ltd.",
    "wof:placetype":"venue"
},
  "geometry": {"coordinates":[-1.2595499754,51.750743866],"type":"Point"}
}