{
  "type": "Feature",
  "properties": {
    "iso:country":"GB",
    "sg:address":"8 Wilford Road, Ruddington",
    "sg:city":"Nottingham",
    "sg:classifiers":[
        {
            "category":"Shopping",
            "subcategory":"Crafts & Fabrics",
            "type":"Retail Goods"
        }
    ],
    "sg:phone":"+44 115 921 1509",
    "sg:postcode":"NG11 6EN",
    "sg:province":"Nottinghamshire",
    "sg:tags":[
        "lace"
    ],
    "wof:name":"Preston's",
    "wof:placetype":"venue"
},
  "geometry": {"coordinates":[-1.149467,52.89312],"type":"Point"}
}