{
  "type": "Feature",
  "properties": {
    "addr:full":"271 Creighton Avenue London Greater London N2 9BP",
    "addr:housenumber":"271",
    "addr:postcode":"n2 9bp",
    "addr:street":"Creighton Avenue",
    "iso:country":"GB",
    "sg:address":"271 Creighton Avenue",
    "sg:city":"London",
    "sg:classifiers":[
        {
            "category":"Professional",
            "subcategory":"Engineering",
            "type":"Services"
        }
    ],
    "sg:phone":"+44 20 8444 0803",
    "sg:postcode":"N2 9BP",
    "sg:province":"Greater London",
    "sg:tags":[
        "consulting",
        "engineer"
    ],
    "wof:name":"David A Berle Consulting Engineers",
    "wof:placetype":"venue"
},
  "geometry": {"coordinates":[-0.166887,51.59343],"type":"Point"}
}