{
  "type": "Feature",
  "properties": {
    "addr:full":"Delaware Rd, Shoeburyness Southend On Sea Essex SS3 9NS",
    "addr:postcode":"ss3 9ns",
    "addr:street":"Delaware Rd;Southend;Sea",
    "iso:country":"GB",
    "sg:address":"Delaware Rd, Shoeburyness",
    "sg:city":"Southend On Sea",
    "sg:classifiers":[
        {
            "category":"Community Center",
            "type":"Public Place"
        }
    ],
    "sg:phone":"+44 1702 293558",
    "sg:postcode":"SS3 9NS",
    "sg:province":"Essex",
    "sg:tags":[
        "recreation",
        "leisure",
        "centre"
    ],
    "wof:name":"Shoeburyness Leisure Centre",
    "wof:placetype":"venue"
},
  "geometry": {"coordinates":[0.76914,51.535557],"type":"Point"}
}