{
  "type": "Feature",
  "properties": {
    "iso:country":"GB",
    "sg:address":"Station App",
    "sg:city":"Bridgnorth",
    "sg:classifiers":[
        {
            "category":"Professional",
            "subcategory":"Testing Lab",
            "type":"Services"
        }
    ],
    "sg:phone":"+44 1746 764400",
    "sg:postcode":"WV16 5DP",
    "sg:province":"Shropshire",
    "sg:tags":[
        "inspection",
        "calibration"
    ],
    "wof:name":"Eurodisc (U K) Ltd.",
    "wof:placetype":"venue"
},
  "geometry": {"coordinates":[-2.420479,52.536819],"type":"Point"}
}