{
  "type": "Feature",
  "properties": {
    "addr:full":"Christchurch St West Frome Somerset BA11 1EB",
    "addr:postcode":"ba11 1eb",
    "addr:street":"Christchurch St",
    "iso:country":"GB",
    "sg:address":"Christchurch St West",
    "sg:city":"Frome",
    "sg:classifiers":[
        {
            "category":"Professional",
            "subcategory":"Printing & Photocopies",
            "type":"Services"
        }
    ],
    "sg:postcode":"BA11 1EB",
    "sg:province":"Somerset",
    "sg:tags":[
        "printer"
    ],
    "wof:name":"B K T Dowland",
    "wof:placetype":"venue"
},
  "geometry": {"coordinates":[-2.3250091076,51.229598999],"type":"Point"}
}