{
  "type": "Feature",
  "properties": {
    "iso:country":"GB",
    "sg:address":"Rear Of Talbot Hotel, Blandford Road, Iwerne Minster",
    "sg:city":"Blandford Forum",
    "sg:classifiers":[
        {
            "category":"Professional",
            "subcategory":"Art Services",
            "type":"Services"
        }
    ],
    "sg:postcode":"DT11 8QN",
    "sg:province":"Dorset",
    "sg:tags":[
        "model",
        "maker"
    ],
    "wof:name":"Distribution Geraldine Ltd.",
    "wof:placetype":"venue"
},
  "geometry": {"coordinates":[-2.192621,50.92841],"type":"Point"}
}