{
  "type": "Feature",
  "properties": {
    "addr:full":"Rear Of Talbot Hotel, Blandford Road, Iwerne Minster Blandford Forum Dorset DT11 8QN",
    "addr:housenumber":"rear of",
    "addr:postcode":"dt11 8qn",
    "addr:street":"Blandford Road",
    "iso:country":"GB",
    "sg:address":"Rear Of Talbot Hotel, Blandford Road, Iwerne Minster",
    "sg:city":"Blandford Forum",
    "sg:classifiers":[
        {
            "category":"Professional",
            "subcategory":"Art Services",
            "type":"Services"
        }
    ],
    "sg:postcode":"DT11 8QN",
    "sg:province":"Dorset",
    "sg:tags":[
        "model",
        "maker"
    ],
    "wof:name":"Distribution Geraldine Ltd.",
    "wof:placetype":"venue"
},
  "geometry": {"coordinates":[-2.192621,50.92841],"type":"Point"}
}