{
  "type": "Feature",
  "properties": {
    "addr:full":"36 Caldy Road Wirral Merseyside CH48 2HQ",
    "addr:housenumber":"36",
    "addr:postcode":"ch48 2hq",
    "addr:street":"Caldy Road",
    "iso:country":"GB",
    "sg:address":"36 Caldy Road",
    "sg:city":"Wirral",
    "sg:classifiers":[
        {
            "category":"Education",
            "subcategory":"Music School",
            "type":"Public Place"
        },
        {
            "category":"Education",
            "subcategory":"School",
            "type":"Public Place"
        },
        {
            "category":"Organizations",
            "subcategory":"Professional Association",
            "type":"Services"
        }
    ],
    "sg:phone":"+44 151 625 2619",
    "sg:postcode":"CH48 2HQ",
    "sg:province":"Merseyside",
    "sg:tags":[
        "advice",
        "information",
        "dyslexia",
        "organisation",
        "private",
        "tuition",
        "support"
    ],
    "wof:name":"Successful Learning",
    "wof:placetype":"venue"
},
  "geometry": {"coordinates":[-3.1729300022,53.3627662659],"type":"Point"}
}