{
  "type": "Feature",
  "properties": {
    "iso:country":"GB",
    "sg:address":"265a Portswood Road",
    "sg:city":"Southampton",
    "sg:classifiers":[
        {
            "category":"Real Estate",
            "subcategory":"Real Estate Agent",
            "type":"Services"
        }
    ],
    "sg:postcode":"SO17 2LA",
    "sg:province":"Hampshire",
    "wof:name":"Godfrey Olson & Co.",
    "wof:placetype":"venue"
},
  "geometry": {"coordinates":[-1.391028,50.926937],"type":"Point"}
}