{
  "type": "Feature",
  "properties": {
    "iso:country":"GB",
    "sg:address":"Wises Oast, Wises Lane, Borden",
    "sg:city":"Sittingbourne",
    "sg:classifiers":[
        {
            "category":"Building & Trades",
            "subcategory":"Cleaning & Sanitation",
            "type":"Services"
        },
        {
            "category":"Building & Trades",
            "subcategory":"Pest Control",
            "type":"Services"
        }
    ],
    "sg:phone":"+44 1795 423716",
    "sg:postcode":"ME9 8LR",
    "sg:province":"Kent",
    "sg:tags":[
        "use",
        "industrial",
        "door",
        "manufacturer"
    ],
    "wof:name":"Swale Shutter & Door Services Ltd",
    "wof:placetype":"venue"
},
  "geometry": {"coordinates":[0.7044799924,51.3333930969],"type":"Point"}
}