{
  "type": "Feature",
  "properties": {
    "iso:country":"GB",
    "sg:address":"19 Smith's Pl",
    "sg:city":"Edinburgh",
    "sg:classifiers":[
        {
            "category":"Organizations",
            "subcategory":"Non-profit Organization",
            "type":"Services"
        }
    ],
    "sg:phone":"+44 131 553 4737",
    "sg:postcode":"EH6 8NT",
    "sg:province":"City of Edinburgh",
    "sg:tags":[
        "organisation",
        "voluntary",
        "charity"
    ],
    "wof:name":"Leith Sikh Community Groups The",
    "wof:placetype":"venue"
},
  "geometry": {"coordinates":[-3.1872138977,55.9491157532],"type":"Point"}
}