{
  "type": "Feature",
  "properties": {
    "addr:full":"37 Hammerton Street Burnley Lancashire BB11 1LT",
    "addr:housenumber":"37",
    "addr:postcode":"bb11 1lt",
    "addr:street":"Hammerton Street",
    "iso:country":"GB",
    "sg:address":"37 Hammerton Street",
    "sg:city":"Burnley",
    "sg:classifiers":[
        {
            "category":"Professional",
            "subcategory":"Business Services",
            "type":"Services"
        }
    ],
    "sg:postcode":"BB11 1LT",
    "sg:province":"Lancashire",
    "sg:tags":[
        "import",
        "export",
        "agent"
    ],
    "wof:name":"David Harrison",
    "wof:placetype":"venue"
},
  "geometry": {"coordinates":[-2.2462770939,53.788772583],"type":"Point"}
}