{
  "type": "Feature",
  "properties": {
    "iso:country":"GB",
    "sg:address":"37 Caldy Rd",
    "sg:city":"Belvedere",
    "sg:classifiers":[
        {
            "category":"Building & Trades",
            "subcategory":"Construction",
            "type":"Services"
        }
    ],
    "sg:phone":"+44 20 8312 9161",
    "sg:postcode":"DA17 6JT",
    "sg:province":"Kent",
    "sg:tags":[
        "resurfacing",
        "laying",
        "floor"
    ],
    "wof:name":"Spring Cleaning",
    "wof:placetype":"venue"
},
  "geometry": {"coordinates":[0.1532689929,51.4931678772],"type":"Point"}
}