{
  "type": "Feature",
  "properties": {
    "addr:full":"104 Victoria Road North Southsea Hampshire PO5 1QE",
    "addr:housenumber":"104",
    "addr:postcode":"po5 1qe",
    "addr:street":"Victoria Road North",
    "iso:country":"GB",
    "sg:address":"104 Victoria Road North",
    "sg:city":"Southsea",
    "sg:classifiers":[
        {
            "category":"Organizations",
            "subcategory":"Membership Organization",
            "type":"Services"
        }
    ],
    "sg:phone":"+44 23 9275 2020",
    "sg:postcode":"PO5 1QE",
    "sg:province":"Hampshire",
    "sg:tags":[
        "club"
    ],
    "wof:name":"Frog Hall Residents Management Co Ltd",
    "wof:placetype":"venue"
},
  "geometry": {"coordinates":[-1.079287,50.793911],"type":"Point"}
}