{
  "type": "Feature",
  "properties": {
    "addr:full":"38 Station Road Harpenden Hertfordshire AL5 4ST",
    "addr:housenumber":"38",
    "addr:postcode":"al5 4st",
    "addr:street":"Station Road",
    "iso:country":"GB",
    "sg:address":"38 Station Road",
    "sg:city":"Harpenden",
    "sg:classifiers":[
        {
            "category":"Insurance",
            "subcategory":"Insurance Agent",
            "type":"Services"
        }
    ],
    "sg:phone":"+44 1582 769696",
    "sg:postcode":"AL5 4ST",
    "sg:province":"Hertfordshire",
    "wof:name":"Humbergrove Insurance Centre",
    "wof:placetype":"venue"
},
  "geometry": {"coordinates":[-0.352837,51.815323],"type":"Point"}
}