{
  "type": "Feature",
  "properties": {
    "addr:full":"75 Burdett Road London Greater London E3 4JN",
    "addr:housenumber":"75",
    "addr:postcode":"e3 4jn",
    "addr:street":"Burdett Road",
    "iso:country":"GB",
    "sg:address":"75 Burdett Road",
    "sg:city":"London",
    "sg:classifiers":[
        {
            "category":"Taxi",
            "type":"Transportation"
        }
    ],
    "sg:postcode":"E3 4JN",
    "sg:province":"Greater London",
    "sg:tags":[
        "mini",
        "cab"
    ],
    "wof:name":"Eastenders Cars",
    "wof:placetype":"venue"
},
  "geometry": {"coordinates":[-0.033595,51.522026],"type":"Point"}
}