{
  "type": "Feature",
  "properties": {
    "iso:country":"GB",
    "sg:address":"75 Burdett Road",
    "sg:city":"London",
    "sg:classifiers":[
        {
            "category":"Taxi",
            "type":"Transportation"
        }
    ],
    "sg:postcode":"E3 4JN",
    "sg:province":"Greater London",
    "sg:tags":[
        "mini",
        "cab"
    ],
    "wof:name":"Eastenders Cars",
    "wof:placetype":"venue"
},
  "geometry": {"coordinates":[-0.033595,51.522026],"type":"Point"}
}