{
  "type": "Feature",
  "properties": {
    "addr:full":"Aberporth Cardigan Ceredigion SA43 2DA",
    "addr:housenumber":"aberporth",
    "addr:postcode":"sa43 2da",
    "iso:country":"GB",
    "sg:address":"Aberporth",
    "sg:city":"Cardigan",
    "sg:classifiers":[
        {
            "category":"Education",
            "subcategory":"School",
            "type":"Public Place"
        }
    ],
    "sg:phone":"+44 1239 810081",
    "sg:postcode":"SA43 2DA",
    "sg:province":"Ceredigion",
    "sg:tags":[
        "local",
        "authority"
    ],
    "wof:name":"Aberporth County Primary School",
    "wof:placetype":"venue"
},
  "geometry": {"coordinates":[-4.5434231758,52.1325035095],"type":"Point"}
}