{
  "type": "Feature",
  "properties": {
    "addr:full":"Airedale General Hospital, Skipton Rd Keighley North Yorkshire BD20 6TD",
    "addr:postcode":"bd20 6td",
    "addr:street":"Skipton Rd",
    "iso:country":"GB",
    "sg:address":"Airedale General Hospital, Skipton Rd",
    "sg:city":"Keighley",
    "sg:classifiers":[
        {
            "category":"Health Services",
            "subcategory":"Clinic",
            "type":"Services"
        }
    ],
    "sg:phone":"+44 1535 652511",
    "sg:postcode":"BD20 6TD",
    "sg:province":"North Yorkshire",
    "sg:tags":[
        "planning",
        "family",
        "centre"
    ],
    "wof:name":"Family Planning Clinic",
    "wof:placetype":"venue"
},
  "geometry": {"coordinates":[-1.9627,53.898022],"type":"Point"}
}