{
  "type": "Feature",
  "properties": {
    "addr:full":"Dudnance La Redruth Cornwall TR15 3QZ",
    "addr:postcode":"tr15 3qz",
    "addr:street":"La",
    "iso:country":"GB",
    "sg:address":"Dudnance La",
    "sg:city":"Redruth",
    "sg:classifiers":[
        {
            "category":"Utilities",
            "subcategory":"Refuse",
            "type":"Services"
        }
    ],
    "sg:phone":"+44 1209 713700",
    "sg:postcode":"TR15 3QZ",
    "sg:province":"Cornwall",
    "sg:tags":[
        "disposal",
        "waste"
    ],
    "wof:name":"Cory Environmental Workshop",
    "wof:placetype":"venue"
},
  "geometry": {"coordinates":[-5.2738909721,50.2224464417],"type":"Point"}
}