{
  "type": "Feature",
  "properties": {
    "addr:full":"24 Chichester Park Woolacombe Devon EX34 7BZ",
    "addr:housenumber":"24",
    "addr:postcode":"ex34 7bz",
    "addr:street":"Chichester Park Woolacombe",
    "iso:country":"GB",
    "sg:address":"24 Chichester Park",
    "sg:city":"Woolacombe",
    "sg:classifiers":[
        {
            "category":"Coffee & Tea",
            "type":"Food & Drink"
        }
    ],
    "sg:phone":"+44 1271 870438",
    "sg:postcode":"EX34 7BZ",
    "sg:province":"Devon",
    "wof:name":"Lee Woodbridge",
    "wof:placetype":"venue"
},
  "geometry": {"coordinates":[-4.2004480362,51.1738739014],"type":"Point"}
}