{
  "type": "Feature",
  "properties": {
    "addr:full":"7-8 Randolph Place Edinburgh City of Edinburgh EH3 7TE",
    "addr:housenumber":"7-8",
    "addr:postcode":"eh3 7te",
    "addr:street":"Randolph Place Edinburgh",
    "iso:country":"GB",
    "sg:address":"7-8 Randolph Place",
    "sg:city":"Edinburgh",
    "sg:classifiers":[
        {
            "category":"Professional",
            "subcategory":"Employment Agencies",
            "type":"Services"
        }
    ],
    "sg:phone":"+44 131 225 4270",
    "sg:postcode":"EH3 7TE",
    "sg:province":"City of Edinburgh",
    "sg:tags":[
        "consultant"
    ],
    "wof:name":"Evolution I T Ltd.",
    "wof:placetype":"venue"
},
  "geometry": {"coordinates":[-3.210224,55.952171],"type":"Point"}
}