{
  "type": "Feature",
  "properties": {
    "iso:country":"GB",
    "sg:address":"Parc-y-justice, Capel Llanilltern",
    "sg:city":"Cardiff",
    "sg:classifiers":[
        {
            "category":"Farming",
            "subcategory":"Livestock Farm",
            "type":"Manufacturing & Wholesale Goods"
        }
    ],
    "sg:postcode":"CF5 6JH",
    "sg:province":"Cardiff",
    "sg:tags":[
        "others"
    ],
    "wof:name":"John Porter & Son",
    "wof:placetype":"venue"
},
  "geometry": {"coordinates":[-3.3068790436,51.5117149353],"type":"Point"}
}