{
  "type": "Feature",
  "properties": {
    "addr:full":"Unit 2b Staincliffe Garage, Halifax Road Dewsbury West Yorkshire WF13 4AA",
    "addr:housenumber":"unit 2b",
    "addr:postcode":"wf13 4aa",
    "addr:street":"Halifax Road",
    "iso:country":"GB",
    "sg:address":"Unit 2b Staincliffe Garage, Halifax Road",
    "sg:city":"Dewsbury",
    "sg:classifiers":[
        {
            "category":"Retail",
            "subcategory":"Auto Repair",
            "type":"Services"
        }
    ],
    "sg:phone":"+44 1924 465519",
    "sg:postcode":"WF13 4AA",
    "sg:province":"West Yorkshire",
    "sg:tags":[
        "modification",
        "garage"
    ],
    "wof:name":"Pro Diesels",
    "wof:placetype":"venue"
},
  "geometry": {"coordinates":[-1.6311089993,53.6916046143],"type":"Point"}
}