{
  "type": "Feature",
  "properties": {
    "iso:country":"GB",
    "sg:address":"283 Blackburn Road",
    "sg:city":"Bolton",
    "sg:classifiers":[
        {
            "category":"Health Services",
            "subcategory":"Doctor",
            "type":"Services"
        }
    ],
    "sg:phone":"+44 1204 524770",
    "sg:postcode":"BL1 8HB",
    "sg:province":"Lancashire",
    "sg:tags":[
        "practitioners"
    ],
    "wof:name":"M Chandra",
    "wof:placetype":"venue"
},
  "geometry": {"coordinates":[-2.43157,53.593452],"type":"Point"}
}