{
  "type": "Feature",
  "properties": {
    "addr:full":"62 Church Road Cinderford Gloucestershire GL14 2EA",
    "addr:housenumber":"62",
    "addr:postcode":"gl14 2ea",
    "addr:street":"Church Road",
    "iso:country":"GB",
    "sg:address":"62 Church Road",
    "sg:city":"Cinderford",
    "sg:classifiers":[
        {
            "category":"Personal",
            "subcategory":"Beauty Salon",
            "type":"Services"
        }
    ],
    "sg:phone":"+44 1594 822314",
    "sg:postcode":"GL14 2EA",
    "sg:province":"Gloucestershire",
    "sg:tags":[
        "ladies",
        "lady",
        "hairdresser"
    ],
    "wof:name":"Doreen Rogers",
    "wof:placetype":"venue"
},
  "geometry": {"coordinates":[-2.501553,51.817883],"type":"Point"}
}