{
  "type": "Feature",
  "properties": {
    "iso:country":"GB",
    "sg:address":"57 Market Street",
    "sg:city":"Manchester",
    "sg:classifiers":[
        {
            "category":"Shopping",
            "subcategory":"Department Store",
            "type":"Retail Goods"
        }
    ],
    "sg:phone":"+44 161 834 1151",
    "sg:postcode":"M1 1WN",
    "sg:province":"Greater Manchester",
    "wof:name":"Bhs",
    "wof:placetype":"venue"
},
  "geometry": {"coordinates":[-2.241117,53.482712],"type":"Point"}
}