{
  "type": "Feature",
  "properties": {
    "iso:country":"GB",
    "sg:address":"50 Main Street, Garforth",
    "sg:city":"Leeds",
    "sg:classifiers":[
        {
            "category":"Building & Trades",
            "subcategory":"Cleaning & Sanitation",
            "type":"Services"
        }
    ],
    "sg:phone":"+44 113 287 6300",
    "sg:postcode":"LS25 1AA",
    "sg:province":"North Yorkshire",
    "sg:tags":[
        "door",
        "manufacturer"
    ],
    "wof:name":"Boon Edam",
    "wof:placetype":"venue"
},
  "geometry": {"coordinates":[-1.388100028,53.7945747375],"type":"Point"}
}