{
  "type": "Feature",
  "properties": {
    "addr:full":"Ensign Warehouse, Hamble Lane, Hamble Southampton Hampshire SO31 4RS",
    "addr:postcode":"so31 4rs",
    "addr:street":"Hamble Lane",
    "iso:country":"GB",
    "sg:address":"Ensign Warehouse, Hamble Lane, Hamble",
    "sg:city":"Southampton",
    "sg:classifiers":[
        {
            "category":"Autos & Motor Vehicles",
            "subcategory":"Boat Sales",
            "type":"Retail Goods"
        }
    ],
    "sg:phone":"+44 23 8045 3424",
    "sg:postcode":"SO31 4RS",
    "sg:province":"Hampshire",
    "sg:tags":[
        "repair",
        "builder"
    ],
    "wof:name":"Sacha Nice",
    "wof:placetype":"venue"
},
  "geometry": {"coordinates":[-1.31737,50.8601],"type":"Point"}
}