{
  "type": "Feature",
  "properties": {
    "addr:full":"101 Long Street, Easingwold York North Yorkshire YO61 3HY",
    "addr:housenumber":"101",
    "addr:postcode":"yo61 3hy",
    "addr:street":"Long Street",
    "iso:country":"GB",
    "sg:address":"101 Long Street, Easingwold",
    "sg:city":"York",
    "sg:classifiers":[
        {
            "category":"Shopping",
            "subcategory":"Antiques",
            "type":"Retail Goods"
        }
    ],
    "sg:postcode":"YO61 3HY",
    "sg:province":"North Yorkshire",
    "wof:name":"Milestone Antiques",
    "wof:placetype":"venue"
},
  "geometry": {"coordinates":[-1.195348,54.120441],"type":"Point"}
}