{
  "type": "Feature",
  "properties": {
    "iso:country":"GB",
    "sg:address":"101 Long Street, Easingwold",
    "sg:city":"York",
    "sg:classifiers":[
        {
            "category":"Shopping",
            "subcategory":"Antiques",
            "type":"Retail Goods"
        }
    ],
    "sg:postcode":"YO61 3HY",
    "sg:province":"North Yorkshire",
    "wof:name":"Milestone Antiques",
    "wof:placetype":"venue"
},
  "geometry": {"coordinates":[-1.195348,54.120441],"type":"Point"}
}