{
  "type": "Feature",
  "properties": {
    "addr:full":"187 Waterloo Road London Greater London SE1 8UX",
    "addr:housenumber":"187",
    "addr:postcode":"se1 8ux",
    "addr:street":"Waterloo Road",
    "iso:country":"GB",
    "sg:address":"187 Waterloo Road",
    "sg:city":"London",
    "sg:classifiers":[
        {
            "category":"Food & Beverages",
            "subcategory":"Liquor & Beverages",
            "type":"Retail Goods"
        }
    ],
    "sg:phone":"+44 20 7928 3630",
    "sg:postcode":"SE1 8UX",
    "sg:province":"Greater London",
    "sg:tags":[
        "beer",
        "spirit",
        "wines"
    ],
    "wof:name":"World Wines",
    "wof:placetype":"venue"
},
  "geometry": {"coordinates":[-0.108099,51.50061],"type":"Point"}
}