{
  "type": "Feature",
  "properties": {
    "addr:full":"Hills Rd Cambridge Cambridgeshire CB2 2QQ",
    "addr:postcode":"cb2 2qq",
    "addr:street":"Hills Rd",
    "iso:country":"GB",
    "sg:address":"Hills Rd",
    "sg:city":"Cambridge",
    "sg:classifiers":[
        {
            "category":"Social Services",
            "type":"Services"
        }
    ],
    "sg:phone":"+44 1223 216540",
    "sg:postcode":"CB2 2QQ",
    "sg:province":"Cambridgeshire",
    "wof:name":"Social Services",
    "wof:placetype":"venue"
},
  "geometry": {"coordinates":[0.135975,52.189152],"type":"Point"}
}