{
  "type": "Feature",
  "properties": {
    "addr:full":"4 South View, Wrockwardine Telford Shropshire TF6 5DJ",
    "addr:housenumber":"4",
    "addr:postcode":"tf6 5dj",
    "addr:street":"South View",
    "iso:country":"GB",
    "sg:address":"4 South View, Wrockwardine",
    "sg:city":"Telford",
    "sg:classifiers":[
        {
            "category":"Sports & Exercise",
            "subcategory":"Swimming Pool",
            "type":"Entertainment"
        }
    ],
    "sg:postcode":"TF6 5DJ",
    "sg:province":"Shropshire",
    "sg:tags":[
        "bee"
    ],
    "wof:name":"Wrekin Honey",
    "wof:placetype":"venue"
},
  "geometry": {"coordinates":[-2.555889,52.70274],"type":"Point"}
}