{
  "type": "Feature",
  "properties": {
    "addr:full":"18 Thanet St Bloomsbury Greater London WC1H 9TR",
    "addr:postcode":"wc1h 9tr",
    "addr:street":"St",
    "iso:country":"GB",
    "sg:address":"18 Thanet St",
    "sg:city":"Bloomsbury",
    "sg:classifiers":[
        {
            "category":"Professional",
            "subcategory":"Lawyer & Legal Services",
            "type":"Services"
        },
        {
            "category":"Organizations",
            "subcategory":"Non-profit Organization",
            "type":"Services"
        }
    ],
    "sg:phone":"+44 20 7388 2025",
    "sg:postcode":"WC1H 9TR",
    "sg:province":"Greater London",
    "sg:tags":[
        "advice",
        "organisation",
        "voluntary",
        "counselling",
        "charity"
    ],
    "wof:name":"Salvation Army Housing Association",
    "wof:placetype":"venue"
},
  "geometry": {"coordinates":[-0.1258900017,51.5280990601],"type":"Point"}
}