{
  "type": "Feature",
  "properties": {
    "iso:country":"GB",
    "sg:address":"65 Battlefield Road",
    "sg:city":"Shrewsbury",
    "sg:classifiers":[
        {
            "category":"Government",
            "subcategory":"Department Of Motor Vehicles",
            "type":"Public Place"
        }
    ],
    "sg:phone":"+44 1743 440205",
    "sg:postcode":"SY1 4AB",
    "sg:province":"Shropshire",
    "sg:tags":[
        "commercial"
    ],
    "wof:name":"Malcolm Martin Trucks Ltd.",
    "wof:placetype":"venue"
},
  "geometry": {"coordinates":[-2.71944,52.745216],"type":"Point"}
}