{
  "type": "Feature",
  "properties": {
    "addr:full":"142 Horn Lane London Greater London W3 6PG",
    "addr:housenumber":"142",
    "addr:postcode":"w3 6pg",
    "addr:street":"Horn Lane",
    "iso:country":"GB",
    "sg:address":"142 Horn Lane",
    "sg:city":"London",
    "sg:classifiers":[
        {
            "category":"Shopping",
            "subcategory":"News",
            "type":"Retail Goods"
        }
    ],
    "sg:phone":"+44 20 8992 4413",
    "sg:postcode":"W3 6PG",
    "sg:province":"Greater London",
    "sg:tags":[
        "newsagent"
    ],
    "wof:name":"Jay Vee",
    "wof:placetype":"venue"
},
  "geometry": {"coordinates":[-0.2692329884,51.5140838623],"type":"Point"}
}