{
  "type": "Feature",
  "properties": {
    "addr:full":"27 High Street, Shrivenham Swindon Gloucestershire SN6 8AN",
    "addr:housenumber":"27",
    "addr:postcode":"sn6 8an",
    "addr:street":"High Street",
    "iso:country":"GB",
    "sg:address":"27 High Street, Shrivenham",
    "sg:city":"Swindon",
    "sg:classifiers":[
        {
            "category":"Communications",
            "type":"Services"
        }
    ],
    "sg:phone":"+44 1793 784177",
    "sg:postcode":"SN6 8AN",
    "sg:province":"Gloucestershire",
    "sg:tags":[
        "telecommunication"
    ],
    "wof:name":"Low Cost Telephone Service",
    "wof:placetype":"venue"
},
  "geometry": {"coordinates":[-1.653123,51.59893],"type":"Point"}
}