{
  "type": "Feature",
  "properties": {
    "addr:full":"31 Upper Walthamstow Road, Upper Walthamstow London Greater London E17 3QG",
    "addr:housenumber":"31",
    "addr:postcode":"e17 3qg",
    "addr:street":"Upper Walthamstow Road",
    "iso:country":"GB",
    "sg:address":"31 Upper Walthamstow Road, Upper Walthamstow",
    "sg:city":"London",
    "sg:classifiers":[
        {
            "category":"Building & Trades",
            "subcategory":"Plumbing",
            "type":"Services"
        }
    ],
    "sg:phone":"+44 20 8520 0460",
    "sg:postcode":"E17 3QG",
    "sg:province":"Greater London",
    "sg:tags":[
        "heating"
    ],
    "wof:name":"T E B Plumbing & Heating Ltd.",
    "wof:placetype":"venue"
},
  "geometry": {"coordinates":[0.001924,51.5877532959],"type":"Point"}
}