{
  "type": "Feature",
  "properties": {
    "iso:country":"GB",
    "sg:address":"80-84 Canterbury Road",
    "sg:city":"Herne Bay",
    "sg:classifiers":[
        {
            "category":"Autos & Motor Vehicles",
            "subcategory":"Automobile Sales",
            "type":"Retail Goods"
        }
    ],
    "sg:postcode":"CT6 5SB",
    "sg:province":"Kent",
    "sg:tags":[
        "car"
    ],
    "wof:name":"DUMPTON PARK GARAGE",
    "wof:placetype":"venue"
},
  "geometry": {"coordinates":[1.132761,51.367847],"type":"Point"}
}