{
  "type": "Feature",
  "properties": {
    "iso:country":"GB",
    "sg:address":"24 King Street",
    "sg:city":"Southport",
    "sg:classifiers":[
        {
            "category":"Home & Garden",
            "subcategory":"Home Furnishings",
            "type":"Retail Goods"
        },
        {
            "category":"Wholesale",
            "subcategory":"Home Furnishings",
            "type":"Manufacturing & Wholesale Goods"
        }
    ],
    "sg:phone":"+44 1704 532875",
    "sg:postcode":"PR8 1JX",
    "sg:province":"Lancashire",
    "sg:tags":[
        "blind",
        "manufacture",
        "fitting",
        "curtain"
    ],
    "wof:name":"Curtain Shop",
    "wof:placetype":"venue"
},
  "geometry": {"coordinates":[-3.0077590942,53.6459617615],"type":"Point"}
}