{
  "type": "Feature",
  "properties": {
    "iso:country":"GB",
    "sg:address":"Blenheim Camp, Newmarket Rd",
    "sg:city":"Bury St Edmunds",
    "sg:classifiers":[
        {
            "category":"Government",
            "subcategory":"Office",
            "type":"Public Place"
        }
    ],
    "sg:phone":"+44 1284 767027",
    "sg:postcode":"IP33 3SW",
    "sg:province":"Suffolk",
    "sg:tags":[
        "armed",
        "reserve"
    ],
    "wof:name":"301 Squadron Air Traing Corps",
    "wof:placetype":"venue"
},
  "geometry": {"coordinates":[0.70932,52.249905],"type":"Point"}
}