{
  "type": "Feature",
  "properties": {
    "iso:country":"GB",
    "sg:address":"Linden, Manor Rd",
    "sg:city":"Barnet",
    "sg:classifiers":[
        {
            "category":"Home & Garden",
            "subcategory":"Home Furnishings",
            "type":"Retail Goods"
        }
    ],
    "sg:phone":"+44 20 8449 0609",
    "sg:postcode":"EN5 2LE",
    "sg:province":"Hertfordshire",
    "sg:tags":[
        "blind",
        "curtain",
        "fitting"
    ],
    "wof:name":"Eileen Griffin",
    "wof:placetype":"venue"
},
  "geometry": {"coordinates":[-0.2041800022,51.6491394043],"type":"Point"}
}