{
  "type": "Feature",
  "properties": {
    "addr:full":"16 Kendal Close Bromsgrove Worcestershire B60 2HW",
    "addr:housenumber":"16",
    "addr:postcode":"b60 2hw",
    "addr:street":"Kendal Close",
    "iso:country":"GB",
    "sg:address":"16 Kendal Close",
    "sg:city":"Bromsgrove",
    "sg:classifiers":[
        {
            "category":"Government",
            "subcategory":"Post Office",
            "type":"Public Place"
        }
    ],
    "sg:phone":"+44 1527 837722",
    "sg:postcode":"B60 2HW",
    "sg:province":"Worcestershire",
    "sg:tags":[
        "messenger",
        "courier"
    ],
    "wof:name":"Handi-van",
    "wof:placetype":"venue"
},
  "geometry": {"coordinates":[-2.050039,52.331314],"type":"Point"}
}