{
  "type": "Feature",
  "properties": {
    "iso:country":"GB",
    "sg:address":"57 Whippendell Rd",
    "sg:city":"Watford",
    "sg:classifiers":[
        {
            "category":"Place Of Worship",
            "type":"Public Place"
        }
    ],
    "sg:phone":"+44 1923 248739",
    "sg:postcode":"WD1 7LY",
    "sg:province":"Hertfordshire",
    "wof:name":"St Michael & All Angels Church West Watford",
    "wof:placetype":"venue"
},
  "geometry": {"coordinates":[-0.404659,51.654617],"type":"Point"}
}