{
  "type": "Feature",
  "properties": {
    "addr:full":"Unit 6 Sir Building, Axe Rd Bridgwater Somerset TA6 5LJ",
    "addr:housenumber":"unit 6",
    "addr:postcode":"ta6 5lj",
    "addr:street":"Sir;Axe Rd",
    "iso:country":"GB",
    "sg:address":"Unit 6 Sir Building, Axe Rd",
    "sg:city":"Bridgwater",
    "sg:classifiers":[
        {
            "category":"Wholesale",
            "subcategory":"Medical Equipment & Supplies",
            "type":"Manufacturing & Wholesale Goods"
        }
    ],
    "sg:phone":"+44 1278 431525",
    "sg:postcode":"TA6 5LJ",
    "sg:province":"Somerset",
    "sg:tags":[
        "hospital"
    ],
    "wof:name":"Medipak Mailing Systems Ltd",
    "wof:placetype":"venue"
},
  "geometry": {"coordinates":[-3.0138239861,51.1275558472],"type":"Point"}
}