{
  "type": "Feature",
  "properties": {
    "addr:full":"40 Catherine Street Chester Cheshire CH1 4JY",
    "addr:housenumber":"40",
    "addr:postcode":"ch1 4jy",
    "addr:street":"Catherine Street",
    "iso:country":"GB",
    "sg:address":"40 Catherine Street",
    "sg:city":"Chester",
    "sg:classifiers":[
        {
            "category":"Food & Beverages",
            "subcategory":"Liquor & Beverages",
            "type":"Retail Goods"
        }
    ],
    "sg:phone":"+44 1244 377954",
    "sg:postcode":"CH1 4JY",
    "sg:province":"Cheshire",
    "sg:tags":[
        "beer",
        "wine",
        "spirit",
        "wines"
    ],
    "wof:name":"The Keg",
    "wof:placetype":"venue"
},
  "geometry": {"coordinates":[-2.9014589787,53.1938514709],"type":"Point"}
}