{
  "type": "Feature",
  "properties": {
    "iso:country":"GB",
    "sg:address":"76 High Street",
    "sg:city":"Lincoln",
    "sg:classifiers":[
        {
            "category":"Food & Beverages",
            "subcategory":"Meat & Fish",
            "type":"Retail Goods"
        }
    ],
    "sg:phone":"+44 1522 532671",
    "sg:postcode":"LN5 8AA",
    "sg:province":"Lincolnshire",
    "sg:tags":[
        "chip"
    ],
    "wof:name":"King Neptune Fish Bar",
    "wof:placetype":"venue"
},
  "geometry": {"coordinates":[-0.545195,53.219307],"type":"Point"}
}