{
  "type": "Feature",
  "properties": {
    "iso:country":"GB",
    "sg:address":"7 Meadows Close, Ingrave",
    "sg:city":"Brentwood",
    "sg:classifiers":[
        {
            "category":"Professional",
            "subcategory":"Accounting & Tax Preparation",
            "type":"Services"
        }
    ],
    "sg:phone":"+44 1277 810688",
    "sg:postcode":"CM13 3RF",
    "sg:province":"Essex",
    "sg:tags":[
        "accountant"
    ],
    "wof:name":"G & P Management Services-Integrated Solutions Group",
    "wof:placetype":"venue"
},
  "geometry": {"coordinates":[0.339507,51.603264],"type":"Point"}
}