{
  "type": "Feature",
  "properties": {
    "addr:full":"First Floor Suite, Enterprise House Loughton Essex IG10 1LA",
    "addr:housenumber":"suite",
    "addr:postcode":"ig10 1la",
    "iso:country":"GB",
    "sg:address":"First Floor Suite, Enterprise House",
    "sg:city":"Loughton",
    "sg:classifiers":[
        {
            "category":"Building & Trades",
            "subcategory":"Construction",
            "type":"Services"
        }
    ],
    "sg:postcode":"IG10 1LA",
    "sg:province":"Essex",
    "sg:tags":[
        "flooring"
    ],
    "wof:name":"Ongar Industrial Flooring Limited",
    "wof:placetype":"venue"
},
  "geometry": {"coordinates":[0.0551789999,51.6473731995],"type":"Point"}
}