{
  "type": "Feature",
  "properties": {
    "addr:full":"181-185 High Street New Malden Surrey KT3 4BH",
    "addr:housenumber":"181-185",
    "addr:postcode":"kt3 4bh",
    "addr:street":"High Street",
    "iso:country":"GB",
    "sg:address":"181-185 High Street",
    "sg:city":"New Malden",
    "sg:classifiers":[
        {
            "category":"Professional",
            "subcategory":"Management & Consulting",
            "type":"Services"
        }
    ],
    "sg:postcode":"KT3 4BH",
    "sg:province":"Surrey",
    "sg:tags":[
        "consultant",
        "business"
    ],
    "wof:name":"Howtech Ltd",
    "wof:placetype":"venue"
},
  "geometry": {"coordinates":[-0.2558279932,51.3992385864],"type":"Point"}
}