{
  "type": "Feature",
  "properties": {
    "addr:full":"52 Wessex Close Calne Wiltshire SN11 8NY",
    "addr:housenumber":"52",
    "addr:postcode":"sn11 8ny",
    "addr:street":"Wessex Close",
    "iso:country":"GB",
    "sg:address":"52 Wessex Close",
    "sg:city":"Calne",
    "sg:classifiers":[
        {
            "category":"Freight",
            "type":"Transportation"
        }
    ],
    "sg:phone":"+44 1249 812809",
    "sg:postcode":"SN11 8NY",
    "sg:province":"Wiltshire",
    "sg:tags":[
        "haulage",
        "transport",
        "road"
    ],
    "wof:name":"E G SLADE",
    "wof:placetype":"venue"
},
  "geometry": {"coordinates":[-1.9938739538,51.4416732788],"type":"Point"}
}