{
  "type": "Feature",
  "properties": {
    "iso:country":"GB",
    "sg:address":"183 Gladstone Road, Walmer",
    "sg:city":"Deal",
    "sg:classifiers":[
        {
            "category":"Retail",
            "subcategory":"Funeral Services",
            "type":"Services"
        }
    ],
    "sg:phone":"+44 1304 380914",
    "sg:postcode":"CT14 7EL",
    "sg:province":"Kent",
    "sg:tags":[
        "cemetery",
        "crematorium"
    ],
    "wof:name":"J Dilnot-Smith & Son",
    "wof:placetype":"venue"
},
  "geometry": {"coordinates":[1.396901,51.214108],"type":"Point"}
}