{
  "type": "Feature",
  "properties": {
    "addr:full":"36 Walpole Street, Chelsea London Greater London SW3 4QS",
    "addr:housenumber":"36",
    "addr:postcode":"sw3 4qs",
    "addr:street":"Walpole Street",
    "iso:country":"GB",
    "sg:address":"36 Walpole Street, Chelsea",
    "sg:city":"London",
    "sg:classifiers":[
        {
            "category":"Transit Center",
            "subcategory":"Passenger",
            "type":"Transportation"
        }
    ],
    "sg:phone":"+44 20 7730 5777",
    "sg:postcode":"SW3 4QS",
    "sg:province":"Greater London",
    "sg:tags":[
        "ship",
        "broker"
    ],
    "wof:name":"Norstar Shipping Co.  Ltd.",
    "wof:placetype":"venue"
},
  "geometry": {"coordinates":[-0.160059,51.48933],"type":"Point"}
}