{
  "type": "Feature",
  "properties": {
    "addr:full":"Lower Moorhayne, Yarcombe Honiton Devon EX14 9BE",
    "addr:housenumber":"yarcombe",
    "addr:postcode":"ex14 9be",
    "iso:country":"GB",
    "sg:address":"Lower Moorhayne, Yarcombe",
    "sg:city":"Honiton",
    "sg:classifiers":[
        {
            "category":"Professional",
            "subcategory":"Employment Agencies",
            "type":"Services"
        }
    ],
    "sg:phone":"+44 1404 861284",
    "sg:postcode":"EX14 9BE",
    "sg:province":"Devon",
    "sg:tags":[
        "agricultural",
        "advice"
    ],
    "wof:name":"Landowning Initiatives (Finance) Ltd.",
    "wof:placetype":"venue"
},
  "geometry": {"coordinates":[-3.074371,50.86795],"type":"Point"}
}