{
  "type": "Feature",
  "properties": {
    "iso:country":"GB",
    "sg:address":"58 Guildhall Street",
    "sg:city":"Folkestone",
    "sg:classifiers":[
        {
            "category":"Shopping",
            "subcategory":"News",
            "type":"Retail Goods"
        }
    ],
    "sg:phone":"+44 1303 257073",
    "sg:postcode":"CT20 1EE",
    "sg:province":"Kent",
    "sg:tags":[
        "newsagent"
    ],
    "wof:name":"Mayfair Newsagents",
    "wof:placetype":"venue"
},
  "geometry": {"coordinates":[1.1760400534,51.0837211609],"type":"Point"}
}