{
  "type": "Feature",
  "properties": {
    "addr:full":"75a Stoney Rock La Leeds West Yorkshire LS9 7TB",
    "addr:housenumber":"75a",
    "addr:postcode":"ls9 7tb",
    "addr:street":"Stoney Rock La Leeds West",
    "iso:country":"GB",
    "sg:address":"75a Stoney Rock La",
    "sg:city":"Leeds",
    "sg:classifiers":[
        {
            "category":"Professional",
            "subcategory":"Detective & Security Services",
            "type":"Services"
        },
        {
            "category":"Shopping",
            "subcategory":"Computers & Home Electronics",
            "type":"Retail Goods"
        }
    ],
    "sg:postcode":"LS9 7TB",
    "sg:province":"West Yorkshire",
    "sg:tags":[
        "installers",
        "video",
        "cctv",
        "equipment"
    ],
    "wof:name":"City Security Holdings Ltd",
    "wof:placetype":"venue"
},
  "geometry": {"coordinates":[-1.5184390545,53.8030700684],"type":"Point"}
}