{
  "type": "Feature",
  "properties": {
    "addr:full":"Unit 1n Hawthorne Business Park, Hawthorne Street Warrington Cheshire WA5 0BY",
    "addr:housenumber":"unit 1n",
    "addr:postcode":"wa5 0by",
    "addr:street":"Business Park Hawthorne Street",
    "iso:country":"GB",
    "sg:address":"Unit 1n Hawthorne Business Park, Hawthorne Street",
    "sg:city":"Warrington",
    "sg:classifiers":[
        {
            "category":"Real Estate",
            "subcategory":"Surveying",
            "type":"Services"
        }
    ],
    "sg:phone":"+44 1925 629616",
    "sg:postcode":"WA5 0BY",
    "sg:province":"Cheshire",
    "sg:tags":[
        "surveyor",
        "quantity"
    ],
    "wof:name":"Commercial Management Consultants Ltd.",
    "wof:placetype":"venue"
},
  "geometry": {"coordinates":[-2.6145501137,53.3969917297],"type":"Point"}
}