{
  "type": "Feature",
  "properties": {
    "iso:country":"GB",
    "sg:address":"1a Risborough Road, Stoke Mandeville",
    "sg:city":"Aylesbury",
    "sg:classifiers":[
        {
            "category":"Personal",
            "subcategory":"Beauty Salon",
            "type":"Services"
        }
    ],
    "sg:phone":"+44 1296 612255",
    "sg:postcode":"HP22 5UP",
    "sg:province":"Buckinghamshire",
    "sg:tags":[
        "unisex",
        "hairdresser"
    ],
    "wof:name":"Face 2 Face",
    "wof:placetype":"venue"
},
  "geometry": {"coordinates":[-0.7911319733,51.7860145569],"type":"Point"}
}