{
  "type": "Feature",
  "properties": {
    "addr:full":"159 Colney Heath Lane St Albans Hertfordshire AL4 0TN",
    "addr:housenumber":"159",
    "addr:postcode":"al4 0tn",
    "addr:street":"Colney Heath Lane",
    "iso:country":"GB",
    "sg:address":"159 Colney Heath Lane",
    "sg:city":"St Albans",
    "sg:classifiers":[
        {
            "category":"Professional",
            "subcategory":"Engineering",
            "type":"Services"
        }
    ],
    "sg:postcode":"AL4 0TN",
    "sg:province":"Hertfordshire",
    "sg:tags":[
        "contractor",
        "electrical",
        "engineer"
    ],
    "wof:name":"J & J Electrical Ltd",
    "wof:placetype":"venue"
},
  "geometry": {"coordinates":[-0.279069,51.745834],"type":"Point"}
}