{
  "type": "Feature",
  "properties": {
    "addr:full":"9 Highburgh Drive, Burnside Glasgow Glasgow City G73 3RR",
    "addr:housenumber":"9",
    "addr:postcode":"g73 3rr",
    "addr:street":"Highburgh Drive",
    "iso:country":"GB",
    "sg:address":"9 Highburgh Drive, Burnside",
    "sg:city":"Glasgow",
    "sg:classifiers":[
        {
            "category":"Professional",
            "subcategory":"Engineering",
            "type":"Services"
        }
    ],
    "sg:phone":"+44 141 647 1487",
    "sg:postcode":"G73 3RR",
    "sg:province":"Glasgow City",
    "sg:tags":[
        "contractor",
        "electrical",
        "engineer"
    ],
    "wof:name":"Ian J McCredie Electrical",
    "wof:placetype":"venue"
},
  "geometry": {"coordinates":[-4.202854,55.817513],"type":"Point"}
}