{
  "type": "Feature",
  "properties": {
    "addr:full":"P O Box 101 Warrington Cheshire WA6 8FD",
    "addr:housenumber":"101",
    "addr:postcode":"wa6 8fd",
    "addr:street":"P O Box",
    "iso:country":"GB",
    "sg:address":"P O Box 101",
    "sg:city":"Warrington",
    "sg:classifiers":[
        {
            "category":"Social Services",
            "subcategory":"Job Training",
            "type":"Services"
        }
    ],
    "sg:phone":"+44 1928 787922",
    "sg:postcode":"WA6 8FD",
    "sg:province":"Cheshire",
    "sg:tags":[
        "translator",
        "interpreter"
    ],
    "wof:name":"Accent",
    "wof:placetype":"venue"
},
  "geometry": {"coordinates":[-2.673489,53.26305],"type":"Point"}
}