{
  "type": "Feature",
  "properties": {
    "addr:full":"Princess Way, Bridgend Indust Estate Bridgend Bridgend CF31 2LN",
    "addr:postcode":"cf31 2ln",
    "addr:street":"Princess Way;Indust Estate",
    "iso:country":"GB",
    "sg:address":"Princess Way, Bridgend Indust Estate",
    "sg:city":"Bridgend",
    "sg:classifiers":[
        {
            "category":"Train Station",
            "subcategory":"Rail",
            "type":"Transportation"
        }
    ],
    "sg:phone":"+44 1656 657007",
    "sg:postcode":"CF31 2LN",
    "sg:province":"Bridgend",
    "sg:tags":[
        "caravan"
    ],
    "wof:name":"Lpr Transport",
    "wof:placetype":"venue"
},
  "geometry": {"coordinates":[-3.567096,51.507309],"type":"Point"}
}