{
  "type": "Feature",
  "properties": {
    "addr:full":"24 Oak Bank Bdwy, Oakworth Keighley North Yorkshire BD22 7LQ",
    "addr:housenumber":"24",
    "addr:postcode":"bd22 7lq",
    "addr:street":"Oak Bank Bdwy",
    "iso:country":"GB",
    "sg:address":"24 Oak Bank Bdwy, Oakworth",
    "sg:city":"Keighley",
    "sg:classifiers":[
        {
            "category":"Building & Trades",
            "subcategory":"Construction",
            "type":"Services"
        }
    ],
    "sg:postcode":"BD22 7LQ",
    "sg:province":"North Yorkshire",
    "sg:tags":[
        "roofing"
    ],
    "wof:name":"Ian Abbey",
    "wof:placetype":"venue"
},
  "geometry": {"coordinates":[-1.930629015,53.8575782776],"type":"Point"}
}