{
  "type": "Feature",
  "properties": {
    "iso:country":"GB",
    "sg:address":"259 Canterbury Road",
    "sg:city":"Herne Bay",
    "sg:classifiers":[
        {
            "category":"Bus Charters",
            "type":"Transportation"
        }
    ],
    "sg:postcode":"CT6 7HD",
    "sg:province":"Kent",
    "sg:tags":[
        "hire",
        "coach"
    ],
    "wof:name":"Leo's Pride Ltd.",
    "wof:placetype":"venue"
},
  "geometry": {"coordinates":[1.132595,51.352512],"type":"Point"}
}