{
  "type": "Feature",
  "properties": {
    "iso:country":"GB",
    "sg:address":"2 Clarendon Road",
    "sg:city":"Southsea",
    "sg:classifiers":[
        {
            "category":"Shopping",
            "subcategory":"Florist",
            "type":"Retail Goods"
        }
    ],
    "sg:phone":"+44 23 9282 4025",
    "sg:postcode":"PO5 2EE",
    "sg:province":"Hampshire",
    "wof:name":"Shiela Love",
    "wof:placetype":"venue"
},
  "geometry": {"coordinates":[-1.0887210369,50.7847328186],"type":"Point"}
}