{
  "type": "Feature",
  "properties": {
    "iso:country":"GB",
    "sg:address":"Burngreen Park",
    "sg:city":"Glasgow",
    "sg:classifiers":[
        {
            "category":"Health Services",
            "subcategory":"Doctor",
            "type":"Services"
        }
    ],
    "sg:phone":"+44 1236 822081",
    "sg:postcode":"G65 0HU",
    "sg:province":"East Dunbartonshire",
    "sg:tags":[
        "practitioners"
    ],
    "wof:name":"Dove, P",
    "wof:placetype":"venue"
},
  "geometry": {"coordinates":[-4.0536999702,55.9771347046],"type":"Point"}
}