{
  "type": "Feature",
  "properties": {
    "addr:full":"Corwen Bryn, Saith Marchog Corwen Conwy LL21 9SB",
    "addr:housenumber":"corwen",
    "addr:postcode":"ll21 9sb",
    "addr:street":"Bryn Saith Marchog",
    "iso:country":"GB",
    "sg:address":"Corwen Bryn, Saith Marchog",
    "sg:city":"Corwen",
    "sg:classifiers":[
        {
            "category":"Autos & Motor Vehicles",
            "subcategory":"Automobile Sales",
            "type":"Retail Goods"
        }
    ],
    "sg:phone":"+44 1824 750325",
    "sg:postcode":"LL21 9SB",
    "sg:province":"Conwy",
    "sg:tags":[
        "car"
    ],
    "wof:name":"N W Morris",
    "wof:placetype":"venue"
},
  "geometry": {"coordinates":[-3.3736679554,52.9806480408],"type":"Point"}
}