{
  "type": "Feature",
  "properties": {
    "addr:full":"30 Trevarrick Rd St Austell Cornwall PL25 5JW",
    "addr:housenumber":"30",
    "addr:postcode":"pl25 5jw",
    "addr:street":"Trevarrick Rd",
    "iso:country":"GB",
    "sg:address":"30 Trevarrick Rd",
    "sg:city":"St Austell",
    "sg:classifiers":[
        {
            "category":"Retail",
            "subcategory":"Veterinary Services",
            "type":"Services"
        }
    ],
    "sg:phone":"+44 1726 75342",
    "sg:postcode":"PL25 5JW",
    "sg:province":"Cornwall",
    "sg:tags":[
        "surgeon"
    ],
    "wof:name":"I S Fielding",
    "wof:placetype":"venue"
},
  "geometry": {"coordinates":[-4.8040161133,50.3383674622],"type":"Point"}
}