{
  "type": "Feature",
  "properties": {
    "iso:country":"GB",
    "sg:address":"33 Market Street, Longton",
    "sg:city":"Stoke-on-trent",
    "sg:classifiers":[
        {
            "category":"Sports & Exercise",
            "subcategory":"Sports Center",
            "type":"Entertainment"
        }
    ],
    "sg:phone":"+44 1782 315885",
    "sg:postcode":"ST3 1BJ",
    "sg:province":"Staffordshire",
    "sg:tags":[
        "shop",
        "good"
    ],
    "wof:name":"Sportscene",
    "wof:placetype":"venue"
},
  "geometry": {"coordinates":[-2.1338300705,52.9888381958],"type":"Point"}
}