{
  "type": "Feature",
  "properties": {
    "addr:full":"183 Victoria Rd Aldershot Hampshire GU11 1JU",
    "addr:housenumber":"183",
    "addr:postcode":"gu11 1ju",
    "addr:street":"Victoria Rd",
    "iso:country":"GB",
    "sg:address":"183 Victoria Rd",
    "sg:city":"Aldershot",
    "sg:classifiers":[
        {
            "category":"Banks & Credit Unions",
            "subcategory":"Bank",
            "type":"Services"
        }
    ],
    "sg:phone":"+44 1252 344303",
    "sg:postcode":"GU11 1JU",
    "sg:province":"Hampshire",
    "sg:tags":[
        "broker",
        "mortgage"
    ],
    "wof:name":"Seekers Estate Agents",
    "wof:placetype":"venue"
},
  "geometry": {"coordinates":[-0.7668359876,51.24842453],"type":"Point"}
}