{
  "type": "Feature",
  "properties": {
    "iso:country":"GB",
    "sg:address":"Belton House, 31a Belton Street, Shepshed",
    "sg:city":"Loughborough",
    "sg:classifiers":[
        {
            "category":"Retail",
            "subcategory":"Funeral Services",
            "type":"Services"
        },
        {
            "category":"Building & Trades",
            "subcategory":"Construction",
            "type":"Services"
        }
    ],
    "sg:phone":"+44 1509 503234",
    "sg:postcode":"LE12 9AA",
    "sg:province":"Leicestershire",
    "sg:tags":[
        "director",
        "monumental",
        "mason"
    ],
    "wof:name":"Shepshed & District Funeral Service",
    "wof:placetype":"venue"
},
  "geometry": {"coordinates":[-1.2928609848,52.774066925],"type":"Point"}
}