{
  "type": "Feature",
  "properties": {
    "iso:country":"GB",
    "sg:address":"Borewell Farm, Scremerston",
    "sg:city":"Berwick-upon-tweed",
    "sg:classifiers":[
        {
            "category":"Farming",
            "subcategory":"Livestock Farm",
            "type":"Manufacturing & Wholesale Goods"
        }
    ],
    "sg:phone":"+44 1289 307507",
    "sg:postcode":"TD15 2RJ",
    "sg:province":"Northumberland",
    "sg:tags":[
        "others"
    ],
    "sg:website":"http://www.rdplus.net",
    "wof:name":"Daniel Whiteford & Co",
    "wof:placetype":"venue"
},
  "geometry": {"coordinates":[-2.0070240498,55.7714347839],"type":"Point"}
}