{
  "type": "Feature",
  "properties": {
    "iso:country":"GB",
    "sg:address":"Exton Park, Exton",
    "sg:city":"Exeter",
    "sg:classifiers":[
        {
            "category":"Farming",
            "subcategory":"Livestock Farm",
            "type":"Manufacturing & Wholesale Goods"
        }
    ],
    "sg:phone":"+44 1392 874128",
    "sg:postcode":"EX3 0PT",
    "sg:province":"Devon",
    "sg:tags":[
        "others"
    ],
    "wof:name":"John Hallett & Partners",
    "wof:placetype":"venue"
},
  "geometry": {"coordinates":[-3.441214,50.669308],"type":"Point"}
}