{
  "type": "Feature",
  "properties": {
    "addr:full":"42 Commercial Street Tredegar Blaenau Gwent NP22 3DJ",
    "addr:housenumber":"42",
    "addr:postcode":"np22 3dj",
    "addr:street":"Commercial Street;Gwent",
    "iso:country":"GB",
    "sg:address":"42 Commercial Street",
    "sg:city":"Tredegar",
    "sg:classifiers":[
        {
            "category":"Travel",
            "subcategory":"Travel Agent",
            "type":"Entertainment"
        }
    ],
    "sg:postcode":"NP22 3DJ",
    "sg:province":"Blaenau Gwent",
    "wof:name":"Garys Coaches",
    "wof:placetype":"venue"
},
  "geometry": {"coordinates":[-3.246401,51.774872],"type":"Point"}
}