{
  "type": "Feature",
  "properties": {
    "iso:country":"GB",
    "sg:address":"Laurel Cottage, Burton Grn, Rossett",
    "sg:city":"Wrexham",
    "sg:classifiers":[
        {
            "category":"Professional",
            "subcategory":"Engineering",
            "type":"Services"
        },
        {
            "category":"Building & Trades",
            "subcategory":"Electrical",
            "type":"Services"
        }
    ],
    "sg:phone":"+44 1244 570692",
    "sg:postcode":"LL12 0AW",
    "sg:province":"Wrexham",
    "sg:tags":[
        "engineer",
        "electrician",
        "contractor"
    ],
    "wof:name":"David Evans",
    "wof:placetype":"venue"
},
  "geometry": {"coordinates":[-2.943889,53.109631],"type":"Point"}
}