{
  "type": "Feature",
  "properties": {
    "addr:full":"Co-op Travel, Rookery Street, Wednesfield Wolverhampton Staffordshire WV11 1UP",
    "addr:postcode":"wv11 1up",
    "addr:street":"Rookery Street",
    "iso:country":"GB",
    "sg:address":"Co-op Travel, Rookery Street, Wednesfield",
    "sg:city":"Wolverhampton",
    "sg:classifiers":[
        {
            "category":"Travel",
            "subcategory":"Travel Agent",
            "type":"Entertainment"
        }
    ],
    "sg:phone":"+44 1902 304333",
    "sg:postcode":"WV11 1UP",
    "sg:province":"Staffordshire",
    "wof:name":"West Midlands Co-Operative Society Ltd.",
    "wof:placetype":"venue"
},
  "geometry": {"coordinates":[-2.121669,52.58865],"type":"Point"}
}