{
  "type": "Feature",
  "properties": {
    "iso:country":"GB",
    "sg:address":"International House, Rochester Way",
    "sg:city":"Dartford",
    "sg:classifiers":[
        {
            "category":"Freight",
            "type":"Transportation"
        }
    ],
    "sg:phone":"+44 20 8303 6261",
    "sg:postcode":"DA1 3QY",
    "sg:province":"Kent",
    "sg:tags":[
        "overseas",
        "shipping",
        "removal"
    ],
    "wof:name":"Doree Holdings Ltd.",
    "wof:placetype":"venue"
},
  "geometry": {"coordinates":[0.17417,51.441406],"type":"Point"}
}