{
  "type": "Feature",
  "properties": {
    "addr:full":"2b Prosser St Wolverhampton Staffordshire WV10 9AR",
    "addr:housenumber":"2b",
    "addr:postcode":"wv10 9ar",
    "addr:street":"Prosser St",
    "iso:country":"GB",
    "sg:address":"2b Prosser St",
    "sg:city":"Wolverhampton",
    "sg:classifiers":[
        {
            "category":"Food & Beverages",
            "subcategory":"Meat & Fish",
            "type":"Retail Goods"
        }
    ],
    "sg:phone":"+44 1902 451975",
    "sg:postcode":"WV10 9AR",
    "sg:province":"Staffordshire",
    "sg:tags":[
        "chip"
    ],
    "wof:name":"Shalimar Fish Bar",
    "wof:placetype":"venue"
},
  "geometry": {"coordinates":[-2.113005,52.597015],"type":"Point"}
}