{
  "type": "Feature",
  "properties": {
    "addr:full":"27 Guildford Road Southport Lancashire PR8 4JU",
    "addr:housenumber":"27",
    "addr:postcode":"pr8 4ju",
    "addr:street":"Guildford Road",
    "iso:country":"GB",
    "sg:address":"27 Guildford Road",
    "sg:city":"Southport",
    "sg:classifiers":[
        {
            "category":"Retail",
            "subcategory":"Repair Shop",
            "type":"Services"
        }
    ],
    "sg:phone":"+44 1704 564126",
    "sg:postcode":"PR8 4JU",
    "sg:province":"Lancashire",
    "sg:tags":[
        "maintenance"
    ],
    "wof:name":"Bob Forshaw",
    "wof:placetype":"venue"
},
  "geometry": {"coordinates":[-3.0028069019,53.6236457825],"type":"Point"}
}