{
  "type": "Feature",
  "properties": {
    "addr:full":"Unit 1 Holmdale, Fontwell Avenue, Eastergate Chichester West Sussex PO20 6RY",
    "addr:housenumber":"unit 1",
    "addr:postcode":"po20 6ry",
    "addr:street":"Holmdale Fontwell Avenue Eastergate",
    "iso:country":"GB",
    "sg:address":"Unit 1 Holmdale, Fontwell Avenue, Eastergate",
    "sg:city":"Chichester",
    "sg:classifiers":[
        {
            "category":"Recreation",
            "subcategory":"Gun Range",
            "type":"Entertainment"
        }
    ],
    "sg:postcode":"PO20 6RY",
    "sg:province":"West Sussex",
    "sg:tags":[
        "chainsaw"
    ],
    "wof:name":"Britannia Industrial Saws Limited",
    "wof:placetype":"venue"
},
  "geometry": {"coordinates":[-0.66144,50.842091],"type":"Point"}
}