{
  "type": "Feature",
  "properties": {
    "addr:full":"Winchs Field Herne Bay Kent CT6 8NN",
    "addr:postcode":"ct6 8nn",
    "iso:country":"GB",
    "sg:address":"Winchs Field",
    "sg:city":"Herne Bay",
    "sg:classifiers":[
        {
            "category":"Organizations",
            "subcategory":"Membership Organization",
            "type":"Services"
        },
        {
            "category":"Arena",
            "subcategory":"Sports Club",
            "type":"Entertainment"
        }
    ],
    "sg:phone":"+44 1227 374156",
    "sg:postcode":"CT6 8NN",
    "sg:province":"Kent",
    "wof:name":"Herne Bay Football Club",
    "wof:placetype":"venue"
},
  "geometry": {"coordinates":[1.1251000166,51.3712158203],"type":"Point"}
}