{
  "type": "Feature",
  "properties": {
    "iso:country":"GB",
    "sg:address":"Mill Lane, Radford",
    "sg:city":"Worcester",
    "sg:classifiers":[
        {
            "category":"Utilities",
            "subcategory":"Refuse",
            "type":"Services"
        }
    ],
    "sg:phone":"+44 1386 792354",
    "sg:postcode":"WR7 4LP",
    "sg:province":"Worcestershire",
    "sg:tags":[
        "skip",
        "hire"
    ],
    "wof:name":"M H F Plant & Skip Hire Ltd.",
    "wof:placetype":"venue"
},
  "geometry": {"coordinates":[-1.993458,52.192112],"type":"Point"}
}