{
  "type": "Feature",
  "properties": {
    "addr:full":"Shalford Hall, Shalford Braintree Essex CM7 5HH",
    "addr:postcode":"cm7 5hh",
    "iso:country":"GB",
    "sg:address":"Shalford Hall, Shalford",
    "sg:city":"Braintree",
    "sg:classifiers":[
        {
            "category":"Building & Trades",
            "subcategory":"Equipment Rental",
            "type":"Services"
        }
    ],
    "sg:phone":"+44 1371 850659",
    "sg:postcode":"CM7 5HH",
    "sg:province":"Essex",
    "sg:tags":[
        "plant",
        "machinery"
    ],
    "wof:name":"Labrador Plant Hire Ltd.",
    "wof:placetype":"venue"
},
  "geometry": {"coordinates":[0.5017449856,51.9362983704],"type":"Point"}
}