{
  "type": "Feature",
  "properties": {
    "addr:full":"Weston Street London Greater London SE1 3ER",
    "addr:postcode":"se1 3er",
    "addr:street":"Weston Street",
    "iso:country":"GB",
    "sg:address":"Weston Street",
    "sg:city":"London",
    "sg:classifiers":[
        {
            "category":"Professional",
            "subcategory":"Business Services",
            "type":"Services"
        },
        {
            "category":"Conference Center",
            "type":"Public Place"
        }
    ],
    "sg:phone":"+44 20 7357 8941",
    "sg:postcode":"SE1 3ER",
    "sg:province":"Greater London",
    "sg:tags":[
        "accomodation",
        "centre"
    ],
    "wof:name":"The Leathermarket",
    "wof:placetype":"venue"
},
  "geometry": {"coordinates":[-0.085569,51.502594],"type":"Point"}
}