{
  "type": "Feature",
  "properties": {
    "addr:full":"Cromer House, Caxton Way Stevenage Hertfordshire SG1 2DF",
    "addr:postcode":"sg1 2df",
    "addr:street":"Caxton Way",
    "iso:country":"GB",
    "sg:address":"Cromer House, Caxton Way",
    "sg:city":"Stevenage",
    "sg:classifiers":[
        {
            "category":"Shopping",
            "subcategory":"Optical Goods",
            "type":"Retail Goods"
        },
        {
            "category":"Professional",
            "subcategory":"Engineering",
            "type":"Services"
        }
    ],
    "sg:phone":"+44 1438 314134",
    "sg:postcode":"SG1 2DF",
    "sg:province":"Hertfordshire",
    "sg:tags":[
        "precision",
        "engineer"
    ],
    "wof:name":"For Your Eyes Only",
    "wof:placetype":"venue"
},
  "geometry": {"coordinates":[-0.2167389989,51.8998413086],"type":"Point"}
}