{
  "type": "Feature",
  "properties": {
    "iso:country":"GB",
    "sg:address":"236 Southwell Road East, Rainworth",
    "sg:city":"Mansfield",
    "sg:classifiers":[
        {
            "category":"Professional",
            "type":"Services"
        }
    ],
    "sg:postcode":"NG21 0EQ",
    "sg:province":"Nottinghamshire",
    "sg:tags":[
        "caterer"
    ],
    "wof:name":"Crown Deli & Professional Outside Catering",
    "wof:placetype":"venue"
},
  "geometry": {"coordinates":[-1.123099,53.120541],"type":"Point"}
}