{
  "type": "Feature",
  "properties": {
    "addr:full":"84 Monastery Drive Solihull West Midlands B91 1DP",
    "addr:housenumber":"84",
    "addr:postcode":"b91 1dp",
    "addr:street":"Monastery Drive",
    "iso:country":"GB",
    "sg:address":"84 Monastery Drive",
    "sg:city":"Solihull",
    "sg:classifiers":[
        {
            "category":"Professional",
            "type":"Services"
        }
    ],
    "sg:postcode":"B91 1DP",
    "sg:province":"West Midlands",
    "sg:tags":[
        "exhibition"
    ],
    "wof:name":"Ritchie Haldane & Co",
    "wof:placetype":"venue"
},
  "geometry": {"coordinates":[-1.8046159744,52.4265861511],"type":"Point"}
}