{
  "type": "Feature",
  "properties": {
    "addr:full":"Garrick Grn Norwich Norfolk NR6 7AL",
    "addr:postcode":"nr6 7al",
    "addr:street":"Garrick Grn Norwich Norfolk",
    "iso:country":"GB",
    "sg:address":"Garrick Grn",
    "sg:city":"Norwich",
    "sg:classifiers":[
        {
            "category":"Education",
            "subcategory":"School",
            "type":"Public Place"
        }
    ],
    "sg:phone":"+44 1603 409078",
    "sg:postcode":"NR6 7AL",
    "sg:province":"Norfolk",
    "sg:tags":[
        "local",
        "authority"
    ],
    "wof:name":"Norfolk County Council",
    "wof:placetype":"venue"
},
  "geometry": {"coordinates":[1.3006949425,52.664264679],"type":"Point"}
}