{
  "type": "Feature",
  "properties": {
    "addr:full":"Southend Road Penrith Cumbria CA11 8HT",
    "addr:postcode":"ca11 8ht",
    "addr:street":"Southend Road",
    "iso:country":"GB",
    "sg:address":"Southend Road",
    "sg:city":"Penrith",
    "sg:classifiers":[
        {
            "category":"Bars & Pubs",
            "subcategory":"Nightclub",
            "type":"Food & Drink"
        }
    ],
    "sg:phone":"+44 1768 863212",
    "sg:postcode":"CA11 8HT",
    "sg:province":"Cumbria",
    "sg:tags":[
        "club",
        "night"
    ],
    "wof:name":"R J H Ltd.",
    "wof:placetype":"venue"
},
  "geometry": {"coordinates":[-2.7492001057,54.6610298157],"type":"Point"}
}