{
  "type": "Feature",
  "properties": {
    "iso:country":"GB",
    "sg:address":"79 Elizabeth Avenue",
    "sg:city":"Newbury",
    "sg:classifiers":[
        {
            "category":"Taxi",
            "type":"Transportation"
        }
    ],
    "sg:phone":"+44 1635 30312",
    "sg:postcode":"RG14 6HG",
    "sg:province":"Berkshire",
    "sg:tags":[
        "mini",
        "cab"
    ],
    "wof:name":"Kingfisher Taxi Services",
    "wof:placetype":"venue"
},
  "geometry": {"coordinates":[-1.344182,51.38332],"type":"Point"}
}