{
  "type": "Feature",
  "properties": {
    "iso:country":"GB",
    "sg:address":"52 Hall Gate, Diseworth",
    "sg:city":"Derby",
    "sg:classifiers":[
        {
            "category":"Government",
            "subcategory":"Post Office",
            "type":"Public Place"
        }
    ],
    "sg:phone":"+44 1332 812745",
    "sg:postcode":"DE74 2QJ",
    "sg:province":"Leicestershire",
    "wof:name":"Diseworth Post Office",
    "wof:placetype":"venue"
},
  "geometry": {"coordinates":[-1.3296500444,52.8165054321],"type":"Point"}
}