{
  "type": "Feature",
  "properties": {
    "addr:full":"33 Talbot Road, Talbot Grn Pontyclun Bridgend CF72 8AD",
    "addr:housenumber":"33",
    "addr:postcode":"cf72 8ad",
    "addr:street":"Talbot Road Talbot Grn Pontyclun",
    "iso:country":"GB",
    "sg:address":"33 Talbot Road, Talbot Grn",
    "sg:city":"Pontyclun",
    "sg:classifiers":[
        {
            "category":"Real Estate",
            "subcategory":"Real Estate Agent",
            "type":"Services"
        }
    ],
    "sg:phone":"+44 1443 226834",
    "sg:postcode":"CF72 8AD",
    "sg:province":"Bridgend",
    "wof:name":"Nick Davies",
    "wof:placetype":"venue"
},
  "geometry": {"coordinates":[-3.3851459026,51.537071228],"type":"Point"}
}