{
  "type": "Feature",
  "properties": {
    "addr:full":"Unit 6 Prors Way Industrial Estate Maidenhead Berkshire SL6 2HP",
    "addr:housenumber":"unit 6;estate",
    "addr:postcode":"sl6 2hp",
    "addr:street":"Prors Way Industrial",
    "iso:country":"GB",
    "sg:address":"Unit 6 Prors Way Industrial Estate",
    "sg:city":"Maidenhead",
    "sg:classifiers":[
        {
            "category":"Building & Trades",
            "subcategory":"Construction",
            "type":"Services"
        }
    ],
    "sg:phone":"+44 1628 811811",
    "sg:postcode":"SL6 2HP",
    "sg:province":"Berkshire",
    "sg:tags":[
        "glazier"
    ],
    "wof:name":"David W Price (Glass) Ltd.",
    "wof:placetype":"venue"
},
  "geometry": {"coordinates":[-0.7076900005,51.5011253357],"type":"Point"}
}