{
  "type": "Feature",
  "properties": {
    "iso:country":"GB",
    "sg:address":"103a Golden Hillock Road, Small Heath",
    "sg:city":"Birmingham",
    "sg:classifiers":[
        {
            "category":"Health Services",
            "subcategory":"Dentist",
            "type":"Services"
        }
    ],
    "sg:phone":"+44 121 772 0266",
    "sg:postcode":"B10 0DP",
    "sg:province":"West Midlands",
    "wof:name":"V M Soni",
    "wof:placetype":"venue"
},
  "geometry": {"coordinates":[-1.8590619564,52.4658050537],"type":"Point"}
}