{
  "type": "Feature",
  "properties": {
    "addr:full":"92 South Biggar Road Airdrie North Lanarkshire ML6 9PE",
    "addr:housenumber":"92",
    "addr:postcode":"ml6 9pe",
    "addr:street":"South Biggar Road",
    "iso:country":"GB",
    "sg:address":"92 South Biggar Road",
    "sg:city":"Airdrie",
    "sg:classifiers":[
        {
            "category":"Manufacturing",
            "subcategory":"Building Materials",
            "type":"Manufacturing & Wholesale Goods"
        }
    ],
    "sg:phone":"+44 1236 764884",
    "sg:postcode":"ML6 9PE",
    "sg:province":"North Lanarkshire",
    "sg:tags":[
        "merchant",
        "builder"
    ],
    "wof:name":"Andrew M Goldie & Co. Ltd.",
    "wof:placetype":"venue"
},
  "geometry": {"coordinates":[-3.9661490917,55.8631401062],"type":"Point"}
}