{
  "type": "Feature",
  "properties": {
    "addr:full":"279-283 Old Road Clacton-on-sea Essex CO15 3NR",
    "addr:housenumber":"279-283",
    "addr:postcode":"co15 3nr",
    "addr:street":"Old Road",
    "iso:country":"GB",
    "sg:address":"279-283 Old Road",
    "sg:city":"Clacton-on-sea",
    "sg:classifiers":[
        {
            "category":"Manufacturing",
            "subcategory":"Building Materials",
            "type":"Manufacturing & Wholesale Goods"
        }
    ],
    "sg:phone":"+44 1255 423262",
    "sg:postcode":"CO15 3NR",
    "sg:province":"Essex",
    "sg:tags":[
        "stonemason"
    ],
    "wof:name":"Austin E P",
    "wof:placetype":"venue"
},
  "geometry": {"coordinates":[1.151454,51.800159],"type":"Point"}
}