{
  "type": "Feature",
  "properties": {
    "addr:full":"23 Bournemouth Road, Lower Parkstone Poole Dorset BH14 0EF",
    "addr:housenumber":"23",
    "addr:postcode":"bh14 0ef",
    "addr:street":"Bournemouth Road Lower",
    "iso:country":"GB",
    "sg:address":"23 Bournemouth Road, Lower Parkstone",
    "sg:city":"Poole",
    "sg:classifiers":[
        {
            "category":"Shopping",
            "subcategory":"Clothing, Apparel, & Fashions",
            "type":"Retail Goods"
        }
    ],
    "sg:phone":"+44 1202 738606",
    "sg:postcode":"BH14 0EF",
    "sg:province":"Dorset",
    "sg:tags":[
        "shop",
        "hat"
    ],
    "wof:name":"Abigail's Hat Hire",
    "wof:placetype":"venue"
},
  "geometry": {"coordinates":[-1.9425990582,50.7249984741],"type":"Point"}
}