{
  "type": "Feature",
  "properties": {
    "addr:full":"Exton Brook, Shoe Lane Southampton Hampshire SO32 3NT",
    "addr:postcode":"so32 3nt",
    "addr:street":"Exton Brook Shoe Lane",
    "iso:country":"GB",
    "sg:address":"Exton Brook, Shoe Lane",
    "sg:city":"Southampton",
    "sg:classifiers":[
        {
            "category":"Real Estate",
            "subcategory":"Architect",
            "type":"Services"
        }
    ],
    "sg:phone":"+44 1489 877330",
    "sg:postcode":"SO32 3NT",
    "sg:province":"Hampshire",
    "wof:name":"Keith N Denham",
    "wof:placetype":"venue"
},
  "geometry": {"coordinates":[-1.1269899607,50.9851074219],"type":"Point"}
}