{
  "type": "Feature",
  "properties": {
    "addr:full":"Heroper House London Greater London W1F 7JU",
    "addr:postcode":"w1f 7ju",
    "iso:country":"GB",
    "sg:address":"Heroper House",
    "sg:city":"London",
    "sg:classifiers":[
        {
            "category":"Recreation",
            "subcategory":"Gun Range",
            "type":"Entertainment"
        }
    ],
    "sg:phone":"+44 20 7734 6655",
    "sg:postcode":"W1F 7JU",
    "sg:province":"Greater London",
    "sg:tags":[
        "operator",
        "tour"
    ],
    "wof:name":"River Thames Cruises & Charters Ltd.",
    "wof:placetype":"venue"
},
  "geometry": {"coordinates":[-0.087914,51.50737],"type":"Point"}
}