{
  "type": "Feature",
  "properties": {
    "addr:full":"Unit 3, Clements Court, Clements Lane Ilford Essex IG1 2QY",
    "addr:housenumber":"unit 3",
    "addr:postcode":"ig1 2qy",
    "addr:street":"Clements Court Clements Lane",
    "iso:country":"GB",
    "sg:address":"Unit 3, Clements Court, Clements Lane",
    "sg:city":"Ilford",
    "sg:classifiers":[
        {
            "category":"Freight",
            "type":"Transportation"
        }
    ],
    "sg:phone":"+44 20 8478 9764",
    "sg:postcode":"IG1 2QY",
    "sg:province":"Essex",
    "sg:tags":[
        "forwarders"
    ],
    "wof:name":"C I Freight Services Ltd",
    "wof:placetype":"venue"
},
  "geometry": {"coordinates":[0.0710979998,51.5576324463],"type":"Point"}
}