{
  "type": "Feature",
  "properties": {
    "iso:country":"GB",
    "sg:address":"Johnsons Lane",
    "sg:city":"Bristol",
    "sg:classifiers":[
        {
            "category":"Arena",
            "subcategory":"Sports Club",
            "type":"Entertainment"
        }
    ],
    "sg:phone":"+44 117 951 6888",
    "sg:postcode":"BS5 9AZ",
    "sg:province":"City of Bristol",
    "wof:name":"Old Georgian Sports & Social Club",
    "wof:placetype":"venue"
},
  "geometry": {"coordinates":[-2.555135,51.464218],"type":"Point"}
}