{
  "type": "Feature",
  "properties": {
    "addr:full":"Arglyn Workshops, Glan-mula, Kerry Newtown Powys SY16 4LW",
    "addr:postcode":"sy16 4lw",
    "addr:street":"Kerry",
    "iso:country":"GB",
    "sg:address":"Arglyn Workshops, Glan-mula, Kerry",
    "sg:city":"Newtown",
    "sg:classifiers":[
        {
            "category":"Shopping",
            "subcategory":"Musical Instruments",
            "type":"Retail Goods"
        }
    ],
    "sg:phone":"+44 1686 670940",
    "sg:postcode":"SY16 4LW",
    "sg:province":"Powys",
    "sg:tags":[
        "music",
        "sheet"
    ],
    "wof:name":"Tony Revell (Luthier)",
    "wof:placetype":"venue"
},
  "geometry": {"coordinates":[-3.2594239712,52.5011482239],"type":"Point"}
}