{
  "type": "Feature",
  "properties": {
    "addr:full":"396 Stanstead Road London Greater London SE6 4XB",
    "addr:housenumber":"396",
    "addr:postcode":"se6 4xb",
    "addr:street":"Stanstead Road",
    "iso:country":"GB",
    "sg:address":"396 Stanstead Road",
    "sg:city":"London",
    "sg:classifiers":[
        {
            "category":"Food & Beverages",
            "subcategory":"Liquor & Beverages",
            "type":"Retail Goods"
        }
    ],
    "sg:phone":"+44 20 8690 4217",
    "sg:postcode":"SE6 4XB",
    "sg:province":"Greater London",
    "sg:tags":[
        "beer",
        "spirit",
        "wines"
    ],
    "wof:name":"Wine Bargains",
    "wof:placetype":"venue"
},
  "geometry": {"coordinates":[-0.0289420001,51.4428977966],"type":"Point"}
}