{
  "type": "Feature",
  "properties": {
    "addr:full":"North Glen Medical Practice, 1 Huntsmans Ct Glenrothes Fife KY7 6SX",
    "addr:housenumber":"1",
    "addr:postcode":"ky7 6sx",
    "addr:street":"North;Huntsmans Ct",
    "iso:country":"GB",
    "sg:address":"North Glen Medical Practice, 1 Huntsmans Ct",
    "sg:city":"Glenrothes",
    "sg:classifiers":[
        {
            "category":"Health Services",
            "subcategory":"Doctor",
            "type":"Services"
        }
    ],
    "sg:phone":"+44 1592 620062",
    "sg:postcode":"KY7 6SX",
    "sg:province":"Fife",
    "sg:tags":[
        "practitioners"
    ],
    "wof:name":"McElhinney, J",
    "wof:placetype":"venue"
},
  "geometry": {"coordinates":[-3.1737439632,56.1972084045],"type":"Point"}
}