{
  "type": "Feature",
  "properties": {
    "addr:full":"1 Inverness Road Southall Greater London UB2 5QG",
    "addr:housenumber":"1",
    "addr:postcode":"ub2 5qg",
    "addr:street":"Inverness Road",
    "iso:country":"GB",
    "sg:address":"1 Inverness Road",
    "sg:city":"Southall",
    "sg:classifiers":[
        {
            "category":"Freight",
            "type":"Transportation"
        }
    ],
    "sg:phone":"+44 20 8890 8088",
    "sg:postcode":"UB2 5QG",
    "sg:province":"Greater London",
    "sg:tags":[
        "haulage",
        "road"
    ],
    "wof:name":"Bi-Trudex Construction",
    "wof:placetype":"venue"
},
  "geometry": {"coordinates":[-0.382178992,51.4968070984],"type":"Point"}
}