{
  "type": "Feature",
  "properties": {
    "addr:full":"Hillside House Lincoln Lincolnshire LN5 0PP",
    "addr:postcode":"ln5 0pp",
    "iso:country":"GB",
    "sg:address":"Hillside House",
    "sg:city":"Lincoln",
    "sg:classifiers":[
        {
            "category":"Farming",
            "subcategory":"Farm",
            "type":"Manufacturing & Wholesale Goods"
        }
    ],
    "sg:postcode":"LN5 0PP",
    "sg:province":"Lincolnshire",
    "sg:tags":[
        "mixed",
        "crop"
    ],
    "wof:name":"Roy Ward (Farms) Ltd.",
    "wof:placetype":"venue"
},
  "geometry": {"coordinates":[-0.5780490041,53.0793609619],"type":"Point"}
}