{
  "type": "Feature",
  "properties": {
    "addr:full":"1 Dudley Grove Edinburgh City of Edinburgh EH6 4QP",
    "addr:housenumber":"1",
    "addr:postcode":"eh6 4qp",
    "addr:street":"Dudley Grove",
    "iso:country":"GB",
    "sg:address":"1 Dudley Grove",
    "sg:city":"Edinburgh",
    "sg:classifiers":[
        {
            "category":"Arena",
            "subcategory":"Sports Club",
            "type":"Entertainment"
        }
    ],
    "sg:phone":"+44 131 554 7912",
    "sg:postcode":"EH6 4QP",
    "sg:province":"City of Edinburgh",
    "wof:name":"Dudley Bowling Club",
    "wof:placetype":"venue"
},
  "geometry": {"coordinates":[-3.1859109402,55.9751853943],"type":"Point"}
}