{
  "type": "Feature",
  "properties": {
    "addr:full":"124-128 City Road London Greater London EC1V 2NJ",
    "addr:housenumber":"124-128",
    "addr:postcode":"ec1v 2nj",
    "addr:street":"City Road",
    "iso:country":"GB",
    "sg:address":"124-128 City Road",
    "sg:city":"London",
    "sg:classifiers":[
        {
            "category":"Professional",
            "subcategory":"Printing & Photocopies",
            "type":"Services"
        }
    ],
    "sg:phone":"+44 1904 421729",
    "sg:postcode":"EC1V 2NJ",
    "sg:province":"Greater London",
    "sg:tags":[
        "printer"
    ],
    "wof:name":"Image Print (York) Ltd.",
    "wof:placetype":"venue"
},
  "geometry": {"coordinates":[-0.0883089975,51.5270385742],"type":"Point"}
}