{
  "type": "Feature",
  "properties": {
    "addr:full":"14 Queens Terr Cardigan Ceredigion SA43 1LJ",
    "addr:housenumber":"14",
    "addr:postcode":"sa43 1lj",
    "addr:street":"Queens Terr",
    "iso:country":"GB",
    "sg:address":"14 Queens Terr",
    "sg:city":"Cardigan",
    "sg:classifiers":[
        {
            "category":"Shopping",
            "subcategory":"Used Merchandise",
            "type":"Retail Goods"
        }
    ],
    "sg:postcode":"SA43 1LJ",
    "sg:province":"Ceredigion",
    "sg:tags":[
        "furniture"
    ],
    "wof:name":"Edwards,P A,",
    "wof:placetype":"venue"
},
  "geometry": {"coordinates":[-4.6621289253,52.0836105347],"type":"Point"}
}