{
  "type": "Feature",
  "properties": {
    "addr:full":"319 Shady Lane Birmingham West Midlands B44 9ER",
    "addr:housenumber":"319",
    "addr:postcode":"b44 9er",
    "addr:street":"Shady Lane",
    "iso:country":"GB",
    "sg:address":"319 Shady Lane",
    "sg:city":"Birmingham",
    "sg:classifiers":[
        {
            "category":"Professional",
            "subcategory":"Art Services",
            "type":"Services"
        }
    ],
    "sg:postcode":"B44 9ER",
    "sg:province":"West Midlands",
    "sg:tags":[
        "picture",
        "restoration",
        "framing"
    ],
    "wof:name":"Frames",
    "wof:placetype":"venue"
},
  "geometry": {"coordinates":[-1.9053399563,52.5496482849],"type":"Point"}
}