{
  "type": "Feature",
  "properties": {
    "addr:full":"100 High Storrs Drive Sheffield Derbyshire S11 7LN",
    "addr:housenumber":"100",
    "addr:postcode":"s11 7ln",
    "addr:street":"High Storrs Drive",
    "iso:country":"GB",
    "sg:address":"100 High Storrs Drive",
    "sg:city":"Sheffield",
    "sg:classifiers":[
        {
            "category":"Building & Trades",
            "subcategory":"Construction",
            "type":"Services"
        }
    ],
    "sg:postcode":"S11 7LN",
    "sg:province":"Derbyshire",
    "sg:tags":[
        "window",
        "replacement"
    ],
    "wof:name":"Senior Property Services",
    "wof:placetype":"venue"
},
  "geometry": {"coordinates":[-1.52131,53.360699],"type":"Point"}
}