{
  "type": "Feature",
  "properties": {
    "iso:country":"GB",
    "sg:address":"Little Acre, Perryfields Road",
    "sg:city":"Bromsgrove",
    "sg:classifiers":[
        {
            "category":"Professional",
            "subcategory":"Management & Consulting",
            "type":"Services"
        }
    ],
    "sg:phone":"+44 1527 875277",
    "sg:postcode":"B61 8QW",
    "sg:province":"Worcestershire",
    "sg:tags":[
        "consultant",
        "business"
    ],
    "wof:name":"John H Smith",
    "wof:placetype":"venue"
},
  "geometry": {"coordinates":[-2.058112,52.336594],"type":"Point"}
}