{
  "type": "Feature",
  "properties": {
    "addr:full":"265 Norwich Road Ipswich Suffolk IP1 4BS",
    "addr:housenumber":"265",
    "addr:postcode":"ip1 4bs",
    "addr:street":"Norwich Road",
    "iso:country":"GB",
    "sg:address":"265 Norwich Road",
    "sg:city":"Ipswich",
    "sg:classifiers":[
        {
            "category":"Fast Food",
            "type":"Food & Drink"
        }
    ],
    "sg:phone":"+44 1473 214328",
    "sg:postcode":"IP1 4BS",
    "sg:province":"Suffolk",
    "sg:tags":[
        "away",
        "meal",
        "outlet",
        "take"
    ],
    "wof:name":"Chop Suey House",
    "wof:placetype":"venue"
},
  "geometry": {"coordinates":[1.1380549669,52.0666999817],"type":"Point"}
}