{
  "type": "Feature",
  "properties": {
    "addr:full":"31 Sycamore Lane Ely Cambridgeshire CB7 4TP",
    "addr:housenumber":"31",
    "addr:postcode":"cb7 4tp",
    "addr:street":"Sycamore Lane",
    "iso:country":"GB",
    "sg:address":"31 Sycamore Lane",
    "sg:city":"Ely",
    "sg:classifiers":[
        {
            "category":"Building & Trades",
            "subcategory":"Plumbing",
            "type":"Services"
        }
    ],
    "sg:phone":"+44 1353 666466",
    "sg:postcode":"CB7 4TP",
    "sg:province":"Cambridgeshire",
    "sg:tags":[
        "central",
        "heating"
    ],
    "wof:name":"Spencer Day",
    "wof:placetype":"venue"
},
  "geometry": {"coordinates":[0.2784230113,52.4042243958],"type":"Point"}
}