{
  "type": "Feature",
  "properties": {
    "addr:full":"40 Turnpike Lane, Tottenham London Greater London N8 0PS",
    "addr:housenumber":"40",
    "addr:postcode":"n8 0ps",
    "addr:street":"Turnpike Lane",
    "iso:country":"GB",
    "sg:address":"40 Turnpike Lane, Tottenham",
    "sg:city":"London",
    "sg:classifiers":[
        {
            "category":"Health Services",
            "subcategory":"Health Practitioner",
            "type":"Services"
        }
    ],
    "sg:phone":"+44 20 8888 2782",
    "sg:postcode":"N8 0PS",
    "sg:province":"Greater London",
    "sg:tags":[
        "psychotherapist"
    ],
    "wof:name":"Women & Medical Practice Ltd.",
    "wof:placetype":"venue"
},
  "geometry": {"coordinates":[-0.105979003,51.5895462036],"type":"Point"}
}