{
  "type": "Feature",
  "properties": {
    "addr:full":"Unit 3 Crown Works, Rotherham Road Sheffield South Yorkshire S20 1AH",
    "addr:housenumber":"unit 3",
    "addr:postcode":"s20 1ah",
    "addr:street":"Crown Works Rotherham Road",
    "iso:country":"GB",
    "sg:address":"Unit 3 Crown Works, Rotherham Road",
    "sg:city":"Sheffield",
    "sg:classifiers":[
        {
            "category":"Professional",
            "type":"Services"
        }
    ],
    "sg:postcode":"S20 1AH",
    "sg:province":"South Yorkshire",
    "sg:tags":[
        "specialist",
        "coating"
    ],
    "wof:name":"Electrode Coating Systems Ltd.",
    "wof:placetype":"venue"
},
  "geometry": {"coordinates":[-1.33505,53.350941],"type":"Point"}
}