{
  "type": "Feature",
  "properties": {
    "iso:country":"GB",
    "sg:address":"38 Mountsorrel Lane, Sileby",
    "sg:city":"Loughborough",
    "sg:classifiers":[
        {
            "category":"Social Services",
            "subcategory":"Retirement Home",
            "type":"Services"
        }
    ],
    "sg:postcode":"LE12 7NF",
    "sg:province":"Leicestershire",
    "sg:tags":[
        "residential",
        "care"
    ],
    "wof:name":"Highbury",
    "wof:placetype":"venue"
},
  "geometry": {"coordinates":[-1.11685,52.730057],"type":"Point"}
}