{
  "type": "Feature",
  "properties": {
    "iso:country":"GB",
    "sg:address":"Unit 4, Second Avenue, Westfield Ind Est, Midsomer Norton Bath",
    "sg:city":"Bath",
    "sg:classifiers":[
        {
            "category":"Professional",
            "subcategory":"Printing & Photocopies",
            "type":"Services"
        }
    ],
    "sg:phone":"+44 1761 411155",
    "sg:postcode":"BA3 4AR",
    "sg:province":"Somerset",
    "sg:tags":[
        "printer"
    ],
    "wof:name":"Compass",
    "wof:placetype":"venue"
},
  "geometry": {"coordinates":[-2.467368,51.279449],"type":"Point"}
}