{
  "type": "Feature",
  "properties": {
    "iso:country":"GB",
    "sg:address":"70 Grasmere Road",
    "sg:city":"Bradford",
    "sg:classifiers":[
        {
            "category":"Building & Trades",
            "subcategory":"Construction",
            "type":"Services"
        }
    ],
    "sg:phone":"+44 1274 639518",
    "sg:postcode":"BD2 4HX",
    "sg:province":"West Yorkshire",
    "sg:tags":[
        "joiner",
        "carpenter"
    ],
    "wof:name":"Peter H Close",
    "wof:placetype":"venue"
},
  "geometry": {"coordinates":[-1.7382340431,53.8123092651],"type":"Point"}
}