{
  "type": "Feature",
  "properties": {
    "addr:full":"Old Lode Lane Solihull West Midlands B92 8LW",
    "addr:postcode":"b92 8lw",
    "addr:street":"Lode Lane",
    "iso:country":"GB",
    "sg:address":"Old Lode Lane",
    "sg:city":"Solihull",
    "sg:classifiers":[
        {
            "category":"Education",
            "subcategory":"School",
            "type":"Public Place"
        },
        {
            "category":"Government",
            "subcategory":"Office",
            "type":"Public Place"
        }
    ],
    "sg:phone":"+44 121 743 4691",
    "sg:postcode":"B92 8LW",
    "sg:province":"West Midlands",
    "sg:tags":[
        "local",
        "authority"
    ],
    "wof:name":"Hatchford Brook Junior & Infant School",
    "wof:placetype":"venue"
},
  "geometry": {"coordinates":[-1.779799,52.44936],"type":"Point"}
}