{
  "type": "Feature",
  "properties": {
    "addr:full":"Alpha Grove Community Centre, Alpha Gro London Greater London E14 8LH",
    "addr:postcode":"e14 8lh",
    "addr:street":"Alpha;Gro",
    "iso:country":"GB",
    "sg:address":"Alpha Grove Community Centre, Alpha Gro",
    "sg:city":"London",
    "sg:classifiers":[
        {
            "category":"Organizations",
            "subcategory":"Membership Organization",
            "type":"Services"
        }
    ],
    "sg:phone":"+44 20 7538 1714",
    "sg:postcode":"E14 8LH",
    "sg:province":"Greater London",
    "sg:tags":[
        "club"
    ],
    "wof:name":"Alpha Grove Development Trust",
    "wof:placetype":"venue"
},
  "geometry": {"coordinates":[-0.02371,51.499081],"type":"Point"}
}