{
  "type": "Feature",
  "properties": {
    "addr:full":"98 High Street, Eton Windsor Berkshire SL4 6AF",
    "addr:housenumber":"98",
    "addr:postcode":"sl4 6af",
    "addr:street":"High Street",
    "iso:country":"GB",
    "sg:address":"98 High Street, Eton",
    "sg:city":"Windsor",
    "sg:classifiers":[
        {
            "category":"Shopping",
            "subcategory":"Antiques",
            "type":"Retail Goods"
        }
    ],
    "sg:phone":"+44 1753 863939",
    "sg:postcode":"SL4 6AF",
    "sg:province":"Berkshire",
    "wof:name":"Turks Head Antiques",
    "wof:placetype":"venue"
},
  "geometry": {"coordinates":[-0.6091449857,51.4875259399],"type":"Point"}
}