{
  "type": "Feature",
  "properties": {
    "addr:full":"Station Road, Penketh Warrington Cheshire WA5 2UG",
    "addr:postcode":"wa5 2ug",
    "addr:street":"Station Road",
    "iso:country":"GB",
    "sg:address":"Station Road, Penketh",
    "sg:city":"Warrington",
    "sg:classifiers":[
        {
            "category":"Social Services",
            "subcategory":"Retirement Home",
            "type":"Services"
        }
    ],
    "sg:phone":"+44 1925 723274",
    "sg:postcode":"WA5 2UG",
    "sg:province":"Cheshire",
    "sg:tags":[
        "residential",
        "care"
    ],
    "wof:name":"Three Elms Residential Home Ltd.",
    "wof:placetype":"venue"
},
  "geometry": {"coordinates":[-2.6466588974,53.385219574],"type":"Point"}
}