{
  "type": "Feature",
  "properties": {
    "addr:full":"Thorpe Street, Raunds Wellingborough Northamptonshire NN9 6LY",
    "addr:postcode":"nn9 6ly",
    "addr:street":"Thorpe Street",
    "iso:country":"GB",
    "sg:address":"Thorpe Street, Raunds",
    "sg:city":"Wellingborough",
    "sg:classifiers":[
        {
            "category":"Building & Trades",
            "subcategory":"Equipment Rental",
            "type":"Services"
        }
    ],
    "sg:phone":"+44 1933 622370",
    "sg:postcode":"NN9 6LY",
    "sg:province":"Northamptonshire",
    "sg:tags":[
        "hire",
        "centre"
    ],
    "wof:name":"U-Hire Ltd.",
    "wof:placetype":"venue"
},
  "geometry": {"coordinates":[-0.5468440056,52.3433532715],"type":"Point"}
}