{
  "type": "Feature",
  "properties": {
    "addr:full":"Unit 2, Cae-bach, Off Builder Street Llandudno Conwy LL30 1DR",
    "addr:housenumber":"unit 2",
    "addr:postcode":"ll30 1dr",
    "addr:street":"Cae-Bach Off Builder Street",
    "iso:country":"GB",
    "sg:address":"Unit 2, Cae-bach, Off Builder Street",
    "sg:city":"Llandudno",
    "sg:classifiers":[
        {
            "category":"Retail",
            "subcategory":"Auto Repair",
            "type":"Services"
        }
    ],
    "sg:phone":"+44 1492 870150",
    "sg:postcode":"LL30 1DR",
    "sg:province":"Conwy",
    "sg:tags":[
        "modification",
        "garage"
    ],
    "wof:name":"North Wales Jaguar Centre",
    "wof:placetype":"venue"
},
  "geometry": {"coordinates":[-3.818764,53.322433],"type":"Point"}
}