{
  "type": "Feature",
  "properties": {
    "addr:full":"Oakwing Ho, Swan La Winchester Hampshire SO23 7AA",
    "addr:postcode":"so23 7aa",
    "addr:street":"La Winchester",
    "iso:country":"GB",
    "sg:address":"Oakwing Ho, Swan La",
    "sg:city":"Winchester",
    "sg:classifiers":[
        {
            "category":"Building & Trades",
            "subcategory":"Construction",
            "type":"Services"
        }
    ],
    "sg:phone":"+44 1962 868853",
    "sg:postcode":"SO23 7AA",
    "sg:province":"Hampshire",
    "sg:tags":[
        "heating",
        "contractor"
    ],
    "wof:name":"Privett Heating",
    "wof:placetype":"venue"
},
  "geometry": {"coordinates":[-1.3168090582,51.0630683899],"type":"Point"}
}