{
  "type": "Feature",
  "properties": {
    "addr:full":"1b Tenters Street Bishop Auckland Durham DL14 7AB",
    "addr:housenumber":"1b",
    "addr:postcode":"dl14 7ab",
    "addr:street":"Tenters Street",
    "iso:country":"GB",
    "sg:address":"1b Tenters Street",
    "sg:city":"Bishop Auckland",
    "sg:classifiers":[
        {
            "category":"Professional",
            "subcategory":"Business Services",
            "type":"Services"
        }
    ],
    "sg:phone":"+44 1388 603268",
    "sg:postcode":"DL14 7AB",
    "sg:province":"Durham",
    "sg:tags":[
        "bookmaker"
    ],
    "wof:name":"G R Racing",
    "wof:placetype":"venue"
},
  "geometry": {"coordinates":[-1.675988,54.663742],"type":"Point"}
}