{
  "type": "Feature",
  "properties": {
    "addr:full":"102 Eamont Ct, Shannon Pl St John's Wood Greater London NW8 7DN",
    "addr:housenumber":"102",
    "addr:postcode":"nw8 7dn",
    "addr:street":"Eamont Ct;Pl;John'S",
    "iso:country":"GB",
    "sg:address":"102 Eamont Ct, Shannon Pl",
    "sg:city":"St John's Wood",
    "sg:classifiers":[
        {
            "category":"Professional",
            "subcategory":"Management & Consulting",
            "type":"Services"
        }
    ],
    "sg:phone":"+44 70 5060 1017",
    "sg:postcode":"NW8 7DN",
    "sg:province":"Greater London",
    "sg:tags":[
        "consultant"
    ],
    "wof:name":"Viceroy Marketing",
    "wof:placetype":"venue"
},
  "geometry": {"coordinates":[-0.1663500071,51.5346183777],"type":"Point"}
}