{
  "type": "Feature",
  "properties": {
    "addr:full":"Lyon Road, Windsor Avenue London Greater London SW19 2SE",
    "addr:postcode":"sw19 2se",
    "addr:street":"Lyon Road Windsor Avenue",
    "iso:country":"GB",
    "sg:address":"Lyon Road, Windsor Avenue",
    "sg:city":"London",
    "sg:classifiers":[
        {
            "category":"Professional",
            "subcategory":"Printing & Photocopies",
            "type":"Services"
        }
    ],
    "sg:postcode":"SW19 2SE",
    "sg:province":"Greater London",
    "sg:tags":[
        "printer"
    ],
    "wof:name":"Clifford Frost Ltd.",
    "wof:placetype":"venue"
},
  "geometry": {"coordinates":[-0.1856739968,51.4118690491],"type":"Point"}
}