{
  "type": "Feature",
  "properties": {
    "iso:country":"GB",
    "sg:address":"8o Vere Road, Kirkmuirhill",
    "sg:city":"Lanark",
    "sg:classifiers":[
        {
            "category":"Government",
            "subcategory":"Post Office",
            "type":"Public Place"
        }
    ],
    "sg:phone":"+44 1555 895040",
    "sg:postcode":"ML11 9RP",
    "sg:province":"South Lanarkshire",
    "sg:tags":[
        "messenger",
        "courier"
    ],
    "wof:name":"Direct Express Parcels",
    "wof:placetype":"venue"
},
  "geometry": {"coordinates":[-3.923558,55.670761],"type":"Point"}
}