{
  "type": "Feature",
  "properties": {
    "iso:country":"GB",
    "sg:address":"Canal Road",
    "sg:city":"Worksop",
    "sg:classifiers":[
        {
            "category":"Retail",
            "subcategory":"Auto Repair",
            "type":"Services"
        }
    ],
    "sg:phone":"+44 1909 472420",
    "sg:postcode":"S80 2EH",
    "sg:province":"Nottinghamshire",
    "sg:tags":[
        "modification",
        "garage"
    ],
    "wof:name":"John Speak Motor Engineer",
    "wof:placetype":"venue"
},
  "geometry": {"coordinates":[-1.121317,53.306862],"type":"Point"}
}