{
  "type": "Feature",
  "properties": {
    "iso:country":"GB",
    "sg:address":"Hanley Barn, Hanley Lane",
    "sg:city":"Haywards Heath",
    "sg:classifiers":[
        {
            "category":"Home & Garden",
            "subcategory":"Building Materials",
            "type":"Retail Goods"
        }
    ],
    "sg:postcode":"RH17 5HR",
    "sg:province":"East Sussex",
    "sg:tags":[
        "furnishers",
        "bathroom",
        "planner"
    ],
    "wof:name":"Handbuilt Traditional Furniture by Graham Bond",
    "wof:placetype":"venue"
},
  "geometry": {"coordinates":[-0.1221499965,51.0148582458],"type":"Point"}
}