{
  "type": "Feature",
  "properties": {
    "addr:full":"8 Second Avenue, Daison Torquay Devon TQ1 4JE",
    "addr:housenumber":"8",
    "addr:postcode":"tq1 4je",
    "addr:street":"Second Avenue Daison",
    "iso:country":"GB",
    "sg:address":"8 Second Avenue, Daison",
    "sg:city":"Torquay",
    "sg:classifiers":[
        {
            "category":"Retail",
            "subcategory":"Driving School",
            "type":"Services"
        }
    ],
    "sg:postcode":"TQ1 4JE",
    "sg:province":"Devon",
    "wof:name":"Keith McIver Driving School",
    "wof:placetype":"venue"
},
  "geometry": {"coordinates":[-3.533672,50.480286],"type":"Point"}
}