{
  "type": "Feature",
  "properties": {
    "addr:full":"37-43 South Mall, Edmonton London Greater London N9 0TT",
    "addr:housenumber":"37-43",
    "addr:postcode":"n9 0tt",
    "addr:street":"South Mall",
    "iso:country":"GB",
    "sg:address":"37-43 South Mall, Edmonton",
    "sg:city":"London",
    "sg:classifiers":[
        {
            "category":"Commercial Area",
            "type":"Public Place"
        }
    ],
    "sg:phone":"+44 20 8803 7157",
    "sg:postcode":"N9 0TT",
    "sg:province":"Greater London",
    "sg:tags":[
        "shop",
        "centre"
    ],
    "wof:name":"In Shops Centre",
    "wof:placetype":"venue"
},
  "geometry": {"coordinates":[-0.05881,51.623711],"type":"Point"}
}