{
  "type": "Feature",
  "properties": {
    "iso:country":"GB",
    "sg:address":"Unit 29, Greenfield Business Park, Bagillt Road",
    "sg:city":"Holywell",
    "sg:classifiers":[
        {
            "category":"Shopping",
            "subcategory":"Computers & Home Electronics",
            "type":"Retail Goods"
        },
        {
            "category":"Home & Garden",
            "subcategory":"Furniture",
            "type":"Retail Goods"
        }
    ],
    "sg:phone":"+44 1352 714131",
    "sg:postcode":"CH8 7HJ",
    "sg:province":"Denbighshire",
    "wof:name":"Deeside Furniture Ltd.",
    "wof:placetype":"venue"
},
  "geometry": {"coordinates":[-3.202814,53.28709],"type":"Point"}
}