{
  "type": "Feature",
  "properties": {
    "addr:full":"Wath Rd, Elsecar Barnsley South Yorkshire S74 8HJ",
    "addr:postcode":"s74 8hj",
    "addr:street":"Wath Rd;Yorkshire",
    "iso:country":"GB",
    "sg:address":"Wath Rd, Elsecar",
    "sg:city":"Barnsley",
    "sg:classifiers":[
        {
            "category":"Shopping",
            "subcategory":"Photographic Equipment",
            "type":"Retail Goods"
        }
    ],
    "sg:phone":"+44 1226 360400",
    "sg:postcode":"S74 8HJ",
    "sg:province":"South Yorkshire",
    "wof:name":"Northern Lights Portrature",
    "wof:placetype":"venue"
},
  "geometry": {"coordinates":[-1.4186500311,53.4962348938],"type":"Point"}
}