{
  "type": "Feature",
  "properties": {
    "addr:full":"Beachley Walk Bristol City of Bristol BS11 9PU",
    "addr:postcode":"bs11 9pu",
    "addr:street":"Beachley Walk",
    "iso:country":"GB",
    "sg:address":"Beachley Walk",
    "sg:city":"Bristol",
    "sg:classifiers":[
        {
            "category":"Community Center",
            "type":"Public Place"
        }
    ],
    "sg:phone":"+44 117 982 2142",
    "sg:postcode":"BS11 9PU",
    "sg:province":"City of Bristol",
    "sg:tags":[
        "centre"
    ],
    "wof:name":"Freshways Resource Centre",
    "wof:placetype":"venue"
},
  "geometry": {"coordinates":[-2.682109,51.491482],"type":"Point"}
}