{
  "type": "Feature",
  "properties": {
    "iso:country":"GB",
    "sg:address":"Unit 46, Parkengue",
    "sg:city":"Penryn",
    "sg:classifiers":[
        {
            "category":"Professional",
            "subcategory":"Engineering",
            "type":"Services"
        }
    ],
    "sg:phone":"+44 1326 375063",
    "sg:postcode":"TR10 9EP",
    "sg:province":"Cornwall",
    "sg:tags":[
        "contractor",
        "electrical",
        "engineer"
    ],
    "wof:name":"Associated Electrical Repairs",
    "wof:placetype":"venue"
},
  "geometry": {"coordinates":[-5.122569,50.167469],"type":"Point"}
}