{
  "type": "Feature",
  "properties": {
    "iso:country":"GB",
    "sg:address":"133a Vicarage Road, Wollaston",
    "sg:city":"Stourbridge",
    "sg:classifiers":[
        {
            "category":"Personal",
            "type":"Services"
        }
    ],
    "sg:postcode":"DY8 4QZ",
    "sg:province":"Staffordshire",
    "sg:tags":[
        "wedding"
    ],
    "wof:name":"Rolls Royce Wedding Cars",
    "wof:placetype":"venue"
},
  "geometry": {"coordinates":[-2.169442,52.462959],"type":"Point"}
}