{
  "type": "Feature",
  "properties": {
    "addr:full":"17 St Leonards Close Watlington Oxfordshire OX49 5PQ",
    "addr:housenumber":"17",
    "addr:postcode":"ox49 5pq",
    "addr:street":"St Leonards Close",
    "iso:country":"GB",
    "sg:address":"17 St Leonards Close",
    "sg:city":"Watlington",
    "sg:classifiers":[
        {
            "category":"Communications",
            "subcategory":"Film & Video Production",
            "type":"Services"
        }
    ],
    "sg:postcode":"OX49 5PQ",
    "sg:province":"Oxfordshire",
    "sg:tags":[
        "illustrator",
        "artist"
    ],
    "wof:name":"Fed",
    "wof:placetype":"venue"
},
  "geometry": {"coordinates":[-1.0104299784,51.6479797363],"type":"Point"}
}