{
  "type": "Feature",
  "properties": {
    "addr:full":"507 Newport Rd Cardiff Caerphilly CF3 7AD",
    "addr:housenumber":"507",
    "addr:postcode":"cf3 7ad",
    "addr:street":"Newport Rd",
    "iso:country":"GB",
    "sg:address":"507 Newport Rd",
    "sg:city":"Cardiff",
    "sg:classifiers":[
        {
            "category":"Home & Garden",
            "subcategory":"Household Appliances",
            "type":"Retail Goods"
        }
    ],
    "sg:phone":"+44 29 2049 8582",
    "sg:postcode":"CF3 7AD",
    "sg:province":"Caerphilly",
    "sg:tags":[
        "electrical",
        "domestic"
    ],
    "wof:name":"Courts Electrical",
    "wof:placetype":"venue"
},
  "geometry": {"coordinates":[-3.1420209408,51.4975891113],"type":"Point"}
}