{
  "type": "Feature",
  "properties": {
    "iso:country":"GB",
    "sg:address":"34 Saxon Close, Warsash",
    "sg:city":"Southampton",
    "sg:classifiers":[
        {
            "category":"Banks & Credit Unions",
            "subcategory":"Bank",
            "type":"Services"
        }
    ],
    "sg:postcode":"SO31 9TS",
    "sg:province":"Hampshire",
    "sg:tags":[
        "broker",
        "mortgage"
    ],
    "wof:name":"Mortgageline",
    "wof:placetype":"venue"
},
  "geometry": {"coordinates":[-1.2885739803,50.8554229736],"type":"Point"}
}