{
  "type": "Feature",
  "properties": {
    "addr:full":"Rickmansworth Road, Chorleywood Rickmansworth Hertfordshire WD3 5SQ",
    "addr:postcode":"wd3 5sq",
    "addr:street":"Rickmansworth Road",
    "iso:country":"GB",
    "sg:address":"Rickmansworth Road, Chorleywood",
    "sg:city":"Rickmansworth",
    "sg:classifiers":[
        {
            "category":"Social Services",
            "subcategory":"Retirement Home",
            "type":"Services"
        }
    ],
    "sg:phone":"+44 1923 282818",
    "sg:postcode":"WD3 5SQ",
    "sg:province":"Hertfordshire",
    "sg:tags":[
        "residential",
        "care"
    ],
    "wof:name":"Burford House",
    "wof:placetype":"venue"
},
  "geometry": {"coordinates":[-0.521474,51.654804],"type":"Point"}
}