{
  "type": "Feature",
  "properties": {
    "addr:full":"Unit 3 Chaloners House, Bow Street Guisborough North Yorkshire TS14 6PR",
    "addr:housenumber":"unit 3 chaloners house",
    "addr:postcode":"ts14 6pr",
    "addr:street":"Street",
    "iso:country":"GB",
    "sg:address":"Unit 3 Chaloners House, Bow Street",
    "sg:city":"Guisborough",
    "sg:classifiers":[
        {
            "category":"Shopping",
            "type":"Retail Goods"
        }
    ],
    "sg:phone":"+44 1287 630067",
    "sg:postcode":"TS14 6PR",
    "sg:province":"North Yorkshire",
    "sg:tags":[
        "merchant"
    ],
    "wof:name":"Kenneth Wilson",
    "wof:placetype":"venue"
},
  "geometry": {"coordinates":[-1.0508129597,54.535446167],"type":"Point"}
}