{
  "type": "Feature",
  "properties": {
    "iso:country":"GB",
    "sg:address":"65 King Street",
    "sg:city":"Peterhead",
    "sg:classifiers":[
        {
            "category":"Travel",
            "subcategory":"Hotels & Motels",
            "type":"Entertainment"
        }
    ],
    "sg:postcode":"AB42 6QJ",
    "sg:province":"Aberdeenshire",
    "sg:tags":[
        "house",
        "guest"
    ],
    "wof:name":"Anns Guest House",
    "wof:placetype":"venue"
},
  "geometry": {"coordinates":[-1.7848229408,57.5076217651],"type":"Point"}
}