{
  "type": "Feature",
  "properties": {
    "addr:full":"Unit 8 Station Road Industrial Estate St Helens Cheshire WA9 3JG",
    "addr:housenumber":"unit 8",
    "addr:postcode":"wa9 3jg",
    "addr:street":"Station Road Industrial Estate",
    "iso:country":"GB",
    "sg:address":"Unit 8 Station Road Industrial Estate",
    "sg:city":"St Helens",
    "sg:classifiers":[
        {
            "category":"Manufacturing",
            "subcategory":"Metals",
            "type":"Manufacturing & Wholesale Goods"
        }
    ],
    "sg:postcode":"WA9 3JG",
    "sg:province":"Cheshire",
    "sg:tags":[
        "work",
        "sheet"
    ],
    "wof:name":"Davies Fabrication",
    "wof:placetype":"venue"
},
  "geometry": {"coordinates":[-2.7031540871,53.4346885681],"type":"Point"}
}