{
  "type": "Feature",
  "properties": {
    "addr:full":"Unit 3, Mount Ind Est, Mount Rd Stone Staffordshire ST15 8LL",
    "addr:housenumber":"unit 3",
    "addr:postcode":"st15 8ll",
    "addr:street":"Mount Ind Est Mount Rd",
    "iso:country":"GB",
    "sg:address":"Unit 3, Mount Ind Est, Mount Rd",
    "sg:city":"Stone",
    "sg:classifiers":[
        {
            "category":"Professional",
            "subcategory":"Engineering",
            "type":"Services"
        }
    ],
    "sg:phone":"+44 1785 812949",
    "sg:postcode":"ST15 8LL",
    "sg:province":"Staffordshire",
    "sg:tags":[
        "engineer",
        "mechanical"
    ],
    "wof:name":"Alstone Engineering",
    "wof:placetype":"venue"
},
  "geometry": {"coordinates":[-2.1434729099,52.9008255005],"type":"Point"}
}