{
  "type": "Feature",
  "properties": {
    "addr:full":"86 Clifden Road London Greater London E5 0LN",
    "addr:housenumber":"86",
    "addr:postcode":"e5 0ln",
    "addr:street":"Clifden Road",
    "iso:country":"GB",
    "sg:address":"86 Clifden Road",
    "sg:city":"London",
    "sg:classifiers":[
        {
            "category":"Health Services",
            "subcategory":"Health Practitioner",
            "type":"Services"
        }
    ],
    "sg:phone":"+44 20 8533 0022",
    "sg:postcode":"E5 0LN",
    "sg:province":"Greater London",
    "sg:tags":[
        "psychotherapist"
    ],
    "wof:name":"John Slade",
    "wof:placetype":"venue"
},
  "geometry": {"coordinates":[-0.0437909998,51.5519371033],"type":"Point"}
}