{
  "type": "Feature",
  "properties": {
    "iso:country":"GB",
    "sg:address":"64 South Spey, South Spey",
    "sg:city":"Grantown-on-spey",
    "sg:classifiers":[
        {
            "category":"Retail",
            "subcategory":"Funeral Services",
            "type":"Services"
        }
    ],
    "sg:phone":"+44 1479 872774",
    "sg:postcode":"PH26 3PF",
    "sg:province":"Highland",
    "wof:name":"John Ross & Co.",
    "wof:placetype":"venue"
},
  "geometry": {"coordinates":[-3.606779,57.332001],"type":"Point"}
}