{
  "type": "Feature",
  "properties": {
    "addr:full":"Westwood, Stonestile Lane Hastings East Sussex TN35 4PG",
    "addr:postcode":"tn35 4pg",
    "addr:street":"Stonestile Lane",
    "iso:country":"GB",
    "sg:address":"Westwood, Stonestile Lane",
    "sg:city":"Hastings",
    "sg:classifiers":[
        {
            "category":"Travel",
            "subcategory":"Hotels & Motels",
            "type":"Entertainment"
        }
    ],
    "sg:postcode":"TN35 4PG",
    "sg:province":"East Sussex",
    "sg:tags":[
        "house",
        "guest"
    ],
    "wof:name":"Westwood Farm",
    "wof:placetype":"venue"
},
  "geometry": {"coordinates":[0.58643502,50.8841362],"type":"Point"}
}