{
  "type": "Feature",
  "properties": {
    "iso:country":"GB",
    "sg:address":"106 East Hill",
    "sg:city":"Dartford",
    "sg:classifiers":[
        {
            "category":"Bars & Pubs",
            "type":"Food & Drink"
        }
    ],
    "sg:phone":"+44 1322 220125",
    "sg:postcode":"DA1 1SB",
    "sg:province":"Kent",
    "sg:tags":[
        "pubs",
        "inn"
    ],
    "wof:name":"Inntrepreneur Pub Co. (C P C)",
    "wof:placetype":"venue"
},
  "geometry": {"coordinates":[0.228302,51.442646],"type":"Point"}
}