{
  "type": "Feature",
  "properties": {
    "addr:full":"Stonycroft, Alexandra Road St Ives Cornwall TR26 1ER",
    "addr:postcode":"tr26 1er",
    "addr:street":"Alexandra Road",
    "iso:country":"GB",
    "sg:address":"Stonycroft, Alexandra Road",
    "sg:city":"St Ives",
    "sg:classifiers":[
        {
            "category":"Retail",
            "subcategory":"Repair Shop",
            "type":"Services"
        }
    ],
    "sg:phone":"+44 1736 796699",
    "sg:postcode":"TR26 1ER",
    "sg:province":"Cornwall",
    "sg:tags":[
        "radio",
        "television",
        "video"
    ],
    "wof:name":"John Barber Electronics",
    "wof:placetype":"venue"
},
  "geometry": {"coordinates":[-5.4857401848,50.2103614807],"type":"Point"}
}