{
  "type": "Feature",
  "properties": {
    "iso:country":"GB",
    "sg:address":"74 Leytonstone Road",
    "sg:city":"London",
    "sg:classifiers":[
        {
            "category":"Real Estate",
            "subcategory":"Real Estate Services",
            "type":"Services"
        },
        {
            "category":"Retail",
            "subcategory":"Repair Shop",
            "type":"Services"
        }
    ],
    "sg:phone":"+44 20 8502 7107",
    "sg:postcode":"E15 1SQ",
    "sg:province":"Greater London",
    "sg:tags":[
        "property",
        "maintenance"
    ],
    "wof:name":"Home Maintenance Service",
    "wof:placetype":"venue"
},
  "geometry": {"coordinates":[0.005311,51.549454],"type":"Point"}
}