{
  "type": "Feature",
  "properties": {
    "addr:full":"Willow Wood Clarbeston Road Pembrokeshire SA63 4UN",
    "addr:postcode":"sa63 4un",
    "iso:country":"GB",
    "sg:address":"Willow Wood",
    "sg:city":"Clarbeston Road",
    "sg:classifiers":[
        {
            "category":"Utilities",
            "subcategory":"Fuel Oil & Lpg",
            "type":"Services"
        }
    ],
    "sg:phone":"+44 1437 731464",
    "sg:postcode":"SA63 4UN",
    "sg:province":"Pembrokeshire",
    "sg:tags":[
        "distributor"
    ],
    "wof:name":"J E Lawrence (Transport) Ltd.",
    "wof:placetype":"venue"
},
  "geometry": {"coordinates":[-4.8799791336,51.8500785828],"type":"Point"}
}