{
  "type": "Feature",
  "properties": {
    "addr:full":"Ropers Hall Farm, Assington Road Bures Essex CO8 5JX",
    "addr:postcode":"co8 5jx",
    "addr:street":"Assington Road",
    "iso:country":"GB",
    "sg:address":"Ropers Hall Farm, Assington Road",
    "sg:city":"Bures",
    "sg:classifiers":[
        {
            "category":"Manufacturing",
            "subcategory":"Chemicals & Compounds",
            "type":"Manufacturing & Wholesale Goods"
        }
    ],
    "sg:phone":"+44 1787 228034",
    "sg:postcode":"CO8 5JX",
    "sg:province":"Essex",
    "sg:tags":[
        "pesticide"
    ],
    "wof:name":"Attack Chemicals Ltd.",
    "wof:placetype":"venue"
},
  "geometry": {"coordinates":[0.77066,51.971802],"type":"Point"}
}