{
  "type": "Feature",
  "properties": {
    "addr:full":"Blamires St Garage, Cliffe Mills Bradford West Yorkshire BD7 4QE",
    "addr:postcode":"bd7 4qe",
    "addr:street":"West",
    "iso:country":"GB",
    "sg:address":"Blamires St Garage, Cliffe Mills",
    "sg:city":"Bradford",
    "sg:classifiers":[
        {
            "category":"Building & Trades",
            "subcategory":"Construction",
            "type":"Services"
        }
    ],
    "sg:postcode":"BD7 4QE",
    "sg:province":"West Yorkshire",
    "sg:tags":[
        "equipment"
    ],
    "wof:name":"Nolan,J T,",
    "wof:placetype":"venue"
},
  "geometry": {"coordinates":[-1.7935039997,53.7766304016],"type":"Point"}
}