{
  "type": "Feature",
  "properties": {
    "addr:full":"238 Grange Rd Plaistow Greater London E13 0HG",
    "addr:housenumber":"238",
    "addr:postcode":"e13 0hg",
    "addr:street":"Grange Rd",
    "iso:country":"GB",
    "sg:address":"238 Grange Rd",
    "sg:city":"Plaistow",
    "sg:classifiers":[
        {
            "category":"Professional",
            "subcategory":"Business Services",
            "type":"Services"
        }
    ],
    "sg:phone":"+44 20 7474 0774",
    "sg:postcode":"E13 0HG",
    "sg:province":"Greater London",
    "sg:tags":[
        "bookmaker"
    ],
    "wof:name":"Tatts",
    "wof:placetype":"venue"
},
  "geometry": {"coordinates":[0.0142729999,51.5252532959],"type":"Point"}
}