{
  "type": "Feature",
  "properties": {
    "iso:country":"GB",
    "sg:address":"Unit C, Highgrove Industrial Park, Quartremaine Road",
    "sg:city":"Portsmouth",
    "sg:classifiers":[
        {
            "category":"Professional",
            "subcategory":"Business Services",
            "type":"Services"
        }
    ],
    "sg:phone":"+44 23 9265 4388",
    "sg:postcode":"PO3 5QQ",
    "sg:province":"Hampshire",
    "sg:tags":[
        "import",
        "export",
        "agent"
    ],
    "wof:name":"E M J Supplies",
    "wof:placetype":"venue"
},
  "geometry": {"coordinates":[-1.05415,50.824379],"type":"Point"}
}