{
  "type": "Feature",
  "properties": {
    "iso:country":"GB",
    "sg:address":"67-70 Mott Street",
    "sg:city":"Birmingham",
    "sg:classifiers":[
        {
            "category":"Manufacturing",
            "subcategory":"Metals",
            "type":"Manufacturing & Wholesale Goods"
        }
    ],
    "sg:phone":"+44 121 233 3505",
    "sg:postcode":"B19 3HE",
    "sg:province":"West Midlands",
    "wof:name":"Hi-Lite Metal Finishing",
    "wof:placetype":"venue"
},
  "geometry": {"coordinates":[-1.9052820206,52.4891624451],"type":"Point"}
}