{
  "type": "Feature",
  "properties": {
    "addr:full":"47 Hall Farm Road, Duffield Belper Derbyshire DE56 4FJ",
    "addr:housenumber":"47",
    "addr:postcode":"de56 4fj",
    "addr:street":"Hall Farm Road",
    "iso:country":"GB",
    "sg:address":"47 Hall Farm Road, Duffield",
    "sg:city":"Belper",
    "sg:classifiers":[
        {
            "category":"Professional",
            "subcategory":"Management & Consulting",
            "type":"Services"
        }
    ],
    "sg:phone":"+44 1332 840377",
    "sg:postcode":"DE56 4FJ",
    "sg:province":"Derbyshire",
    "sg:tags":[
        "consultant",
        "safety"
    ],
    "wof:name":"Hudson Health & Safety Services",
    "wof:placetype":"venue"
},
  "geometry": {"coordinates":[-1.4913289547,52.9823188782],"type":"Point"}
}