{
  "type": "Feature",
  "properties": {
    "addr:full":"5-6 The Parade, Southend Arterial Road, Gallows Corner Romford Essex RM3 0DB",
    "addr:housenumber":"5-6",
    "addr:postcode":"rm3 0db",
    "addr:street":"The Parade Southend Arterial Road Gallows Corner",
    "iso:country":"GB",
    "sg:address":"5-6 The Parade, Southend Arterial Road, Gallows Corner",
    "sg:city":"Romford",
    "sg:classifiers":[
        {
            "category":"Autos & Motor Vehicles",
            "subcategory":"Auto Supplies",
            "type":"Retail Goods"
        }
    ],
    "sg:phone":"+44 1708 349016",
    "sg:postcode":"RM3 0DB",
    "sg:province":"Essex",
    "sg:tags":[
        "windscreen"
    ],
    "wof:name":"Nationwide Autoglazing",
    "wof:placetype":"venue"
},
  "geometry": {"coordinates":[0.242272,51.601292],"type":"Point"}
}