{
  "type": "Feature",
  "properties": {
    "iso:country":"GB",
    "sg:address":"43 Oak Road, Horfield",
    "sg:city":"Bristol",
    "sg:classifiers":[
        {
            "category":"Professional",
            "subcategory":"Computer Services",
            "type":"Services"
        }
    ],
    "sg:phone":"+44 117 908 0268",
    "sg:postcode":"BS7 8RZ",
    "sg:province":"City of Bristol",
    "sg:tags":[
        "system",
        "software"
    ],
    "wof:name":"Dinescom Ltd.",
    "wof:placetype":"venue"
},
  "geometry": {"coordinates":[-2.5879209042,51.4832267761],"type":"Point"}
}