{
  "type": "Feature",
  "properties": {
    "addr:full":"43 Weston Lane Otley North Yorkshire LS21 2DB",
    "addr:housenumber":"43",
    "addr:postcode":"ls21 2db",
    "addr:street":"Weston Lane",
    "iso:country":"GB",
    "sg:address":"43 Weston Lane",
    "sg:city":"Otley",
    "sg:classifiers":[
        {
            "category":"Military Area",
            "subcategory":"Air Force Base",
            "type":"Public Place"
        }
    ],
    "sg:postcode":"LS21 2DB",
    "sg:province":"North Yorkshire",
    "sg:tags":[
        "taxi",
        "hire",
        "private"
    ],
    "wof:name":"Chevin Private Hire",
    "wof:placetype":"venue"
},
  "geometry": {"coordinates":[-1.7020510435,53.9117774963],"type":"Point"}
}