{
  "type": "Feature",
  "properties": {
    "iso:country":"GB",
    "sg:address":"1 North Hill, Highgate",
    "sg:city":"London",
    "sg:classifiers":[
        {
            "category":"Bars & Pubs",
            "type":"Food & Drink"
        }
    ],
    "sg:phone":"+44 20 8340 8054",
    "sg:postcode":"N6 4AA",
    "sg:province":"Greater London",
    "sg:tags":[
        "pubs",
        "inn"
    ],
    "wof:name":"The Gate House",
    "wof:placetype":"venue"
},
  "geometry": {"coordinates":[-0.150985,51.576225],"type":"Point"}
}