{
  "type": "Feature",
  "properties": {
    "addr:full":"Dawns Farm, Orton Penrith Cumbria CA10 3RZ",
    "addr:postcode":"ca10 3rz",
    "iso:country":"GB",
    "sg:address":"Dawns Farm, Orton",
    "sg:city":"Penrith",
    "sg:classifiers":[
        {
            "category":"Shopping",
            "subcategory":"Clothing, Apparel, & Fashions",
            "type":"Retail Goods"
        }
    ],
    "sg:phone":"+44 585064617",
    "sg:postcode":"CA10 3RZ",
    "sg:province":"Cumbria",
    "sg:tags":[
        "clothing"
    ],
    "wof:name":"Keith David Douglas Beevor",
    "wof:placetype":"venue"
},
  "geometry": {"coordinates":[-2.583199,54.4692],"type":"Point"}
}