{
  "type": "Feature",
  "properties": {
    "iso:country":"GB",
    "sg:address":"Queen Street, Cefn Mawr",
    "sg:city":"Wrexham",
    "sg:classifiers":[
        {
            "category":"Travel",
            "subcategory":"Hotels & Motels",
            "type":"Entertainment"
        }
    ],
    "sg:phone":"+44 1978 820395",
    "sg:postcode":"LL14 3BD",
    "sg:province":"Wrexham",
    "wof:name":"The Queens",
    "wof:placetype":"venue"
},
  "geometry": {"coordinates":[-3.072534,52.97316],"type":"Point"}
}