{
  "type": "Feature",
  "properties": {
    "addr:full":"14 Station Hill Bromley Kent BR2 7DJ",
    "addr:housenumber":"14",
    "addr:postcode":"br2 7dj",
    "addr:street":"Station Hill",
    "iso:country":"GB",
    "sg:address":"14 Station Hill",
    "sg:city":"Bromley",
    "sg:classifiers":[
        {
            "category":"Organizations",
            "subcategory":"Membership Organization",
            "type":"Services"
        }
    ],
    "sg:phone":"+44 20 8462 1723",
    "sg:postcode":"BR2 7DJ",
    "sg:province":"Kent",
    "sg:tags":[
        "club"
    ],
    "wof:name":"The Royal British Legion",
    "wof:placetype":"venue"
},
  "geometry": {"coordinates":[0.0116210002,51.3746185303],"type":"Point"}
}