{
  "type": "Feature",
  "properties": {
    "addr:full":"37 Denison Rd Selby East Riding of Yorkshire YO8 8AN",
    "addr:housenumber":"37",
    "addr:postcode":"yo8 8an",
    "addr:street":"Denison Rd",
    "iso:country":"GB",
    "sg:address":"37 Denison Rd",
    "sg:city":"Selby",
    "sg:classifiers":[
        {
            "category":"Shopping",
            "subcategory":"Department Store",
            "type":"Retail Goods"
        }
    ],
    "sg:phone":"+44 1757 702720",
    "sg:postcode":"YO8 8AN",
    "sg:province":"East Riding of Yorkshire",
    "wof:name":"Fairway Stores",
    "wof:placetype":"venue"
},
  "geometry": {"coordinates":[-1.0522309542,53.7788887024],"type":"Point"}
}