{
  "type": "Feature",
  "properties": {
    "iso:country":"GB",
    "sg:address":"80 Highgate",
    "sg:city":"Kendal",
    "sg:classifiers":[
        {
            "category":"Shopping",
            "subcategory":"Antiques",
            "type":"Retail Goods"
        }
    ],
    "sg:postcode":"LA9 4NE",
    "sg:province":"Cumbria",
    "wof:name":"Malone,Jacqueline,",
    "wof:placetype":"venue"
},
  "geometry": {"coordinates":[-2.7477469444,54.3257827759],"type":"Point"}
}