{
  "type": "Feature",
  "properties": {
    "iso:country":"GB",
    "sg:address":"1 Watts Street, Clayton",
    "sg:city":"Bradford",
    "sg:classifiers":[
        {
            "category":"Building & Trades",
            "subcategory":"Plumbing",
            "type":"Services"
        }
    ],
    "sg:phone":"+44 1274 880012",
    "sg:postcode":"BD14 6QX",
    "sg:province":"West Yorkshire",
    "sg:tags":[
        "heating"
    ],
    "wof:name":"B Taylor",
    "wof:placetype":"venue"
},
  "geometry": {"coordinates":[-1.821385026,53.7804641724],"type":"Point"}
}