{
  "type": "Feature",
  "properties": {
    "addr:full":"Lindon Ho, 40-42 Charles St Largs North Ayrshire KA30 8HL",
    "addr:housenumber":"40-42",
    "addr:postcode":"ka30 8hl",
    "addr:street":"Charles St",
    "iso:country":"GB",
    "sg:address":"Lindon Ho, 40-42 Charles St",
    "sg:city":"Largs",
    "sg:classifiers":[
        {
            "category":"Building & Trades",
            "subcategory":"Construction",
            "type":"Services"
        }
    ],
    "sg:phone":"+44 1475 676290",
    "sg:postcode":"KA30 8HL",
    "sg:province":"North Ayrshire",
    "sg:tags":[
        "builder"
    ],
    "wof:name":"North Ayrshire Developments Ltd",
    "wof:placetype":"venue"
},
  "geometry": {"coordinates":[-4.8600149155,55.788734436],"type":"Point"}
}