{
  "type": "Feature",
  "properties": {
    "addr:full":"Chaplins Close Cambridge Cambridgeshire CB1 5HU",
    "addr:postcode":"cb1 5hu",
    "addr:street":"Chaplins Close",
    "iso:country":"GB",
    "sg:address":"Chaplins Close",
    "sg:city":"Cambridge",
    "sg:classifiers":[
        {
            "category":"Social Services",
            "subcategory":"Adult Care",
            "type":"Services"
        }
    ],
    "sg:postcode":"CB1 5HU",
    "sg:province":"Cambridgeshire",
    "sg:tags":[
        "housing",
        "sheltered"
    ],
    "wof:name":"Chaplins Close Sheltered Housing",
    "wof:placetype":"venue"
},
  "geometry": {"coordinates":[0.2152500004,52.182800293],"type":"Point"}
}