{
  "type": "Feature",
  "properties": {
    "addr:full":"94 Heather Court, Ty Canol Cwmbran Monmouthshire NP44 6JR",
    "addr:housenumber":"94",
    "addr:postcode":"np44 6jr",
    "addr:street":"Heather Court Ty Canol",
    "iso:country":"GB",
    "sg:address":"94 Heather Court, Ty Canol",
    "sg:city":"Cwmbran",
    "sg:classifiers":[
        {
            "category":"Building & Trades",
            "subcategory":"Construction",
            "type":"Services"
        }
    ],
    "sg:postcode":"NP44 6JR",
    "sg:province":"Monmouthshire",
    "sg:tags":[
        "builder"
    ],
    "wof:name":"D J Sealants Ltd",
    "wof:placetype":"venue"
},
  "geometry": {"coordinates":[-3.060125,51.642223],"type":"Point"}
}