{
  "type": "Feature",
  "properties": {
    "iso:country":"GB",
    "sg:address":"38 Maiden La",
    "sg:city":"Dartford",
    "sg:classifiers":[
        {
            "category":"Food & Beverages",
            "subcategory":"Liquor & Beverages",
            "type":"Retail Goods"
        }
    ],
    "sg:phone":"+44 1322 220849",
    "sg:postcode":"DA1 4AF",
    "sg:province":"Kent",
    "sg:tags":[
        "beer",
        "spirit",
        "wines"
    ],
    "wof:name":"Paul & Sons Off Licence",
    "wof:placetype":"venue"
},
  "geometry": {"coordinates":[0.1917060018,51.4497756958],"type":"Point"}
}