{
  "type": "Feature",
  "properties": {
    "iso:country":"GB",
    "sg:address":"Unit 2, 782-786 Fishponds Road",
    "sg:city":"Bristol",
    "sg:classifiers":[
        {
            "category":"Shopping",
            "subcategory":"Pharmacy",
            "type":"Retail Goods"
        }
    ],
    "sg:phone":"+44 117 965 2718",
    "sg:postcode":"BS16 3TT",
    "sg:province":"City of Bristol",
    "sg:tags":[
        "pharmacist",
        "chemist"
    ],
    "wof:name":"Lloyds Pharmacy",
    "wof:placetype":"venue"
},
  "geometry": {"coordinates":[-2.530719,51.479599],"type":"Point"}
}