{
  "type": "Feature",
  "properties": {
    "addr:full":"Gwynne House, 11 West Street Epsom Surrey KT18 7RL",
    "addr:housenumber":"11",
    "addr:postcode":"kt18 7rl",
    "addr:street":"West Street",
    "iso:country":"GB",
    "sg:address":"Gwynne House, 11 West Street",
    "sg:city":"Epsom",
    "sg:classifiers":[
        {
            "category":"Banks & Credit Unions",
            "subcategory":"Financial Services",
            "type":"Services"
        }
    ],
    "sg:phone":"+44 1372 726162",
    "sg:postcode":"KT18 7RL",
    "sg:province":"Surrey",
    "sg:tags":[
        "adviser"
    ],
    "wof:name":"Grayside Ltd.",
    "wof:placetype":"venue"
},
  "geometry": {"coordinates":[-0.2717689872,51.3331108093],"type":"Point"}
}