{
  "type": "Feature",
  "properties": {
    "iso:country":"GB",
    "sg:address":"15 Leyton Grn",
    "sg:city":"Harpenden",
    "sg:classifiers":[
        {
            "category":"Bars & Pubs",
            "type":"Food & Drink"
        }
    ],
    "sg:phone":"+44 1582 763850",
    "sg:postcode":"AL5 2TG",
    "sg:province":"Hertfordshire",
    "sg:tags":[
        "pubs",
        "inn"
    ],
    "wof:name":"The Oak Tree",
    "wof:placetype":"venue"
},
  "geometry": {"coordinates":[-0.356618,51.814507],"type":"Point"}
}