{
  "type": "Feature",
  "properties": {
    "addr:full":"The Hollins Neath Neath Port Talbot SA11 3BQ",
    "addr:postcode":"sa11 3bq",
    "iso:country":"GB",
    "sg:address":"The Hollins",
    "sg:city":"Neath",
    "sg:classifiers":[
        {
            "category":"Health Services",
            "subcategory":"Nursing And Care Facility",
            "type":"Services"
        }
    ],
    "sg:phone":"+44 1639 635828",
    "sg:postcode":"SA11 3BQ",
    "sg:province":"Neath Port Talbot",
    "sg:tags":[
        "home"
    ],
    "wof:name":"Hollinswood Nursing Home",
    "wof:placetype":"venue"
},
  "geometry": {"coordinates":[-3.7998130322,51.6627120972],"type":"Point"}
}