{
  "type": "Feature",
  "properties": {
    "iso:country":"GB",
    "sg:address":"Central Garage",
    "sg:city":"Workington",
    "sg:classifiers":[
        {
            "category":"Professional",
            "subcategory":"Business Services",
            "type":"Services"
        }
    ],
    "sg:postcode":"CA14 3BL",
    "sg:province":"Cumbria",
    "sg:tags":[
        "agent",
        "manufacturers'"
    ],
    "wof:name":"F R Dawson Agencies",
    "wof:placetype":"venue"
},
  "geometry": {"coordinates":[-3.550002,54.638981],"type":"Point"}
}