{
  "type": "Feature",
  "properties": {
    "addr:full":"31-33 Theobald Street Borehamwood Hertfordshire WD6 4RN",
    "addr:housenumber":"31-33",
    "addr:postcode":"wd6 4rn",
    "addr:street":"Theobald Street",
    "iso:country":"GB",
    "sg:address":"31-33 Theobald Street",
    "sg:city":"Borehamwood",
    "sg:classifiers":[
        {
            "category":"Manufacturing",
            "subcategory":"Rubber & Plastics",
            "type":"Manufacturing & Wholesale Goods"
        }
    ],
    "sg:postcode":"WD6 4RN",
    "sg:province":"Hertfordshire",
    "sg:tags":[
        "product"
    ],
    "wof:name":"Binder Co",
    "wof:placetype":"venue"
},
  "geometry": {"coordinates":[-0.2806909978,51.6550445557],"type":"Point"}
}