{
  "type": "Feature",
  "properties": {
    "iso:country":"GB",
    "sg:address":"Yateley Lodge, Reading Road",
    "sg:city":"Yateley",
    "sg:classifiers":[
        {
            "category":"Professional",
            "subcategory":"Management & Consulting",
            "type":"Services"
        },
        {
            "category":"Education",
            "subcategory":"Special Training",
            "type":"Public Place"
        }
    ],
    "sg:phone":"+44 1252 862400",
    "sg:postcode":"GU46 7AA",
    "sg:province":"Hampshire",
    "sg:tags":[
        "consultant",
        "product",
        "centre"
    ],
    "wof:name":"Gbs Corporate Training Plc",
    "wof:placetype":"venue"
},
  "geometry": {"coordinates":[-0.827109,51.342319],"type":"Point"}
}