{
  "type": "Feature",
  "properties": {
    "iso:country":"GB",
    "sg:address":"99 Barberry Avenue",
    "sg:city":"Chatham",
    "sg:classifiers":[
        {
            "category":"Retail",
            "subcategory":"Driving School",
            "type":"Services"
        }
    ],
    "sg:phone":"+44 1634 668863",
    "sg:postcode":"ME5 9TF",
    "sg:province":"Kent",
    "wof:name":"Concorde School of Motoring",
    "wof:placetype":"venue"
},
  "geometry": {"coordinates":[0.511863,51.350166],"type":"Point"}
}