{
  "type": "Feature",
  "properties": {
    "iso:country":"GB",
    "sg:address":"72 High Street",
    "sg:city":"Yarm",
    "sg:classifiers":[
        {
            "category":"Fast Food",
            "type":"Food & Drink"
        }
    ],
    "sg:phone":"+44 1642 862322",
    "sg:postcode":"TS15 9AH",
    "sg:province":"North Yorkshire",
    "sg:tags":[
        "away",
        "take"
    ],
    "wof:name":"Crumbs Sandwich Shop",
    "wof:placetype":"venue"
},
  "geometry": {"coordinates":[-1.354591012,54.5097923279],"type":"Point"}
}