{
  "type": "Feature",
  "properties": {
    "iso:country":"GB",
    "sg:address":"57b-59 Westway",
    "sg:city":"Caterham",
    "sg:classifiers":[
        {
            "category":"Food & Beverages",
            "subcategory":"Groceries & Convenience Stores",
            "type":"Retail Goods"
        }
    ],
    "sg:phone":"+44 1883 345091",
    "sg:postcode":"CR3 5TP",
    "sg:province":"Surrey",
    "wof:name":"News-sweet",
    "wof:placetype":"venue"
},
  "geometry": {"coordinates":[-0.097492,51.287773],"type":"Point"}
}