{
  "type": "Feature",
  "properties": {
    "addr:full":"24 Hill Street Corbridge Northumberland NE45 5AA",
    "addr:housenumber":"24",
    "addr:postcode":"ne45 5aa",
    "addr:street":"Hill Street;Northumberland",
    "iso:country":"GB",
    "sg:address":"24 Hill Street",
    "sg:city":"Corbridge",
    "sg:classifiers":[
        {
            "category":"Cafe",
            "type":"Food & Drink"
        }
    ],
    "sg:postcode":"NE45 5AA",
    "sg:province":"Northumberland",
    "sg:tags":[
        "tea",
        "room"
    ],
    "wof:name":"The Chatterbox",
    "wof:placetype":"venue"
},
  "geometry": {"coordinates":[-2.0189371109,54.9747543335],"type":"Point"}
}