{
  "type": "Feature",
  "properties": {
    "addr:full":"Greengables, Newmarket Road, Bottisham Cambridge Cambridgeshire CB5 9BD",
    "addr:postcode":"cb5 9bd",
    "addr:street":"Newmarket Road",
    "iso:country":"GB",
    "sg:address":"Greengables, Newmarket Road, Bottisham",
    "sg:city":"Cambridge",
    "sg:classifiers":[
        {
            "category":"Wholesale",
            "subcategory":"Auto Parts",
            "type":"Manufacturing & Wholesale Goods"
        },
        {
            "category":"Retail",
            "subcategory":"Auto Repair",
            "type":"Services"
        }
    ],
    "sg:phone":"+44 1223 812291",
    "sg:postcode":"CB5 9BD",
    "sg:province":"Cambridgeshire",
    "sg:tags":[
        "modification",
        "garage",
        "breaker",
        "car"
    ],
    "wof:name":"Autos & Sons",
    "wof:placetype":"venue"
},
  "geometry": {"coordinates":[0.2364989966,52.2191162109],"type":"Point"}
}