{
  "type": "Feature",
  "properties": {
    "iso:country":"GB",
    "sg:address":"61 Heol Celyn, Coedpoeth",
    "sg:city":"Wrexham",
    "sg:classifiers":[
        {
            "category":"Shopping",
            "subcategory":"News",
            "type":"Retail Goods"
        }
    ],
    "sg:phone":"+44 1978 755275",
    "sg:postcode":"LL11 3HR",
    "sg:province":"Wrexham",
    "sg:tags":[
        "newsagent"
    ],
    "wof:name":"Nicholas Newsagents",
    "wof:placetype":"venue"
},
  "geometry": {"coordinates":[-3.0708770752,53.0530014038],"type":"Point"}
}