{
  "type": "Feature",
  "properties": {
    "addr:full":"5 Henfield Road Eastbourne East Sussex BN22 9RJ",
    "addr:housenumber":"5",
    "addr:postcode":"bn22 9rj",
    "addr:street":"Henfield Road",
    "iso:country":"GB",
    "sg:address":"5 Henfield Road",
    "sg:city":"Eastbourne",
    "sg:classifiers":[
        {
            "category":"Shopping",
            "subcategory":"Computers & Home Electronics",
            "type":"Retail Goods"
        }
    ],
    "sg:postcode":"BN22 9RJ",
    "sg:province":"East Sussex",
    "sg:tags":[
        "aerial",
        "television",
        "radio"
    ],
    "wof:name":"Reliable Aerial Service",
    "wof:placetype":"venue"
},
  "geometry": {"coordinates":[0.272529006,50.8011894226],"type":"Point"}
}