{
  "type": "Feature",
  "properties": {
    "iso:country":"GB",
    "sg:address":"The Quay",
    "sg:city":"Poole",
    "sg:classifiers":[
        {
            "category":"Professional",
            "subcategory":"Management & Consulting",
            "type":"Services"
        }
    ],
    "sg:phone":"+44 1202 243243",
    "sg:postcode":"BH15 1HA",
    "sg:province":"Dorset",
    "sg:tags":[
        "consultant",
        "business"
    ],
    "wof:name":"T M S Partnership",
    "wof:placetype":"venue"
},
  "geometry": {"coordinates":[-1.9904769659,50.7122688293],"type":"Point"}
}