{
  "type": "Feature",
  "properties": {
    "addr:full":"Wicker Lane Sheffield South Yorkshire S3 8HQ",
    "addr:postcode":"s3 8hq",
    "addr:street":"Wicker Lane",
    "iso:country":"GB",
    "sg:address":"Wicker Lane",
    "sg:city":"Sheffield",
    "sg:classifiers":[
        {
            "category":"Real Estate",
            "subcategory":"Architect",
            "type":"Services"
        }
    ],
    "sg:postcode":"S3 8HQ",
    "sg:province":"South Yorkshire",
    "wof:name":"Sowerby Maxted Partnership",
    "wof:placetype":"venue"
},
  "geometry": {"coordinates":[-1.4632040262,53.3873596191],"type":"Point"}
}