{
  "type": "Feature",
  "properties": {
    "iso:country":"GB",
    "sg:address":"Leigh Marshes",
    "sg:city":"Leigh-on-sea",
    "sg:classifiers":[
        {
            "category":"Sports & Exercise",
            "subcategory":"Golf",
            "type":"Entertainment"
        }
    ],
    "sg:phone":"+44 1702 710586",
    "sg:postcode":"SS9 2EU",
    "sg:province":"Essex",
    "sg:tags":[
        "range",
        "driving"
    ],
    "wof:name":"Leigh Golf Range",
    "wof:placetype":"venue"
},
  "geometry": {"coordinates":[0.6422950029,51.547088623],"type":"Point"}
}