{
  "type": "Feature",
  "properties": {
    "addr:full":"C/o B S G Valentine, Lynton, House,7-12,tavistock Square, London Greater London WC1H 9BQ",
    "addr:housenumber":"7-12",
    "addr:postcode":"/ o;wc1h 9bq",
    "addr:street":"C;S;Tavistock Square",
    "iso:country":"GB",
    "sg:address":"C/o B S G Valentine, Lynton, House,7-12,tavistock Square,",
    "sg:city":"London",
    "sg:classifiers":[
        {
            "category":"Manufacturing",
            "subcategory":"Metals",
            "type":"Manufacturing & Wholesale Goods"
        }
    ],
    "sg:postcode":"WC1H 9BQ",
    "sg:province":"Greater London",
    "sg:tags":[
        "work",
        "sheet"
    ],
    "wof:name":"Fabratech Ltd",
    "wof:placetype":"venue"
},
  "geometry": {"coordinates":[-0.1300600022,51.5254936218],"type":"Point"}
}