{
  "type": "Feature",
  "properties": {
    "iso:country":"GB",
    "sg:address":"The Warehouse, Duke St, Hadleigh",
    "sg:city":"Ipswich",
    "sg:classifiers":[
        {
            "category":"Retail",
            "subcategory":"Auto Repair",
            "type":"Services"
        }
    ],
    "sg:phone":"+44 1473 827272",
    "sg:postcode":"IP7 5DP",
    "sg:province":"Suffolk",
    "sg:tags":[
        "modification",
        "garage"
    ],
    "wof:name":"Hadleigh Car Centre",
    "wof:placetype":"venue"
},
  "geometry": {"coordinates":[0.9528999925,52.0448646545],"type":"Point"}
}