{
  "type": "Feature",
  "properties": {
    "iso:country":"GB",
    "sg:address":"Chilton Ind Est",
    "sg:city":"Sudbury",
    "sg:classifiers":[
        {
            "category":"Home & Garden",
            "subcategory":"Building Materials",
            "type":"Retail Goods"
        }
    ],
    "sg:phone":"+44 1787 375077",
    "sg:postcode":"CO10 2XQ",
    "sg:province":"Essex",
    "sg:tags":[
        "ready",
        "mixed",
        "concrete"
    ],
    "wof:name":"RMC Readymix East Anglia",
    "wof:placetype":"venue"
},
  "geometry": {"coordinates":[0.73439,52.038605],"type":"Point"}
}