{
  "type": "Feature",
  "properties": {
    "iso:country":"GB",
    "sg:address":"22 Fowler Street",
    "sg:city":"South Shields",
    "sg:classifiers":[
        {
            "category":"Shopping",
            "subcategory":"Shoes",
            "type":"Retail Goods"
        }
    ],
    "sg:phone":"+44 191 456 0504",
    "sg:postcode":"NE33 1NA",
    "sg:province":"Tyne and Wear",
    "sg:tags":[
        "shop"
    ],
    "wof:name":"Riddicks (South Shields) Ltd.",
    "wof:placetype":"venue"
},
  "geometry": {"coordinates":[-1.4312269688,54.9977684021],"type":"Point"}
}