{
  "type": "Feature",
  "properties": {
    "iso:country":"GB",
    "sg:address":"The Vale",
    "sg:city":"Gerrards Cross",
    "sg:classifiers":[
        {
            "category":"Communications",
            "subcategory":"Newspaper",
            "type":"Services"
        }
    ],
    "sg:phone":"+44 1753 888333",
    "sg:postcode":"SL9 9SD",
    "sg:province":"Buckinghamshire",
    "sg:tags":[
        "magazine"
    ],
    "wof:name":"Amersham Advertiser The",
    "wof:placetype":"venue"
},
  "geometry": {"coordinates":[-0.561179,51.608887],"type":"Point"}
}