{
  "type": "Feature",
  "properties": {
    "iso:country":"GB",
    "sg:address":"Station Approach",
    "sg:city":"Camberley",
    "sg:classifiers":[
        {
            "category":"Professional",
            "subcategory":"Computer Services",
            "type":"Services"
        }
    ],
    "sg:phone":"+44 870 523 9633",
    "sg:postcode":"GU17 9PD",
    "sg:province":"Hampshire",
    "sg:tags":[
        "system",
        "software"
    ],
    "wof:name":"Database 2000",
    "wof:placetype":"venue"
},
  "geometry": {"coordinates":[-0.774848,51.332542],"type":"Point"}
}