{
  "type": "Feature",
  "properties": {
    "addr:full":"Sebay Farm, Tankerness Orkney Orkney Islands KW17 2QU",
    "addr:housenumber":"orkney orkney",
    "addr:postcode":"kw17 2qu",
    "iso:country":"GB",
    "sg:address":"Sebay Farm, Tankerness",
    "sg:city":"Orkney",
    "sg:classifiers":[
        {
            "category":"Farming",
            "subcategory":"Farm",
            "type":"Manufacturing & Wholesale Goods"
        }
    ],
    "sg:phone":"+44 1856 861259",
    "sg:postcode":"KW17 2QU",
    "sg:province":"Orkney Islands",
    "sg:tags":[
        "mixed",
        "crop"
    ],
    "wof:name":"J S Baillie & Co",
    "wof:placetype":"venue"
},
  "geometry": {"coordinates":[-2.7428839207,58.9370002747],"type":"Point"}
}