{
  "type": "Feature",
  "properties": {
    "iso:country":"GB",
    "sg:address":"Flat 18 Oakham Court, 15 Laurel Gro",
    "sg:city":"London",
    "sg:classifiers":[
        {
            "category":"Building & Trades",
            "subcategory":"Construction",
            "type":"Services"
        }
    ],
    "sg:postcode":"SE20 8QJ",
    "sg:province":"Greater London",
    "sg:tags":[
        "dry",
        "lining",
        "plasterers",
        "screeders"
    ],
    "wof:name":"Chris Vanstone",
    "wof:placetype":"venue"
},
  "geometry": {"coordinates":[-0.0592500009,51.4150390625],"type":"Point"}
}