{
  "type": "Feature",
  "properties": {
    "addr:full":"12 Warlbeck, Kings Road Ilkley North Yorkshire LS29 9RH",
    "addr:housenumber":"12",
    "addr:postcode":"ls29 9rh",
    "addr:street":"Warlbeck Kings Road",
    "iso:country":"GB",
    "sg:address":"12 Warlbeck, Kings Road",
    "sg:city":"Ilkley",
    "sg:classifiers":[
        {
            "category":"Professional",
            "subcategory":"Management & Consulting",
            "type":"Services"
        }
    ],
    "sg:postcode":"LS29 9RH",
    "sg:province":"North Yorkshire",
    "sg:tags":[
        "consultant",
        "business"
    ],
    "wof:name":"T. W. McRae  &  Associates Ltd",
    "wof:placetype":"venue"
},
  "geometry": {"coordinates":[-1.8348139524,53.9246139526],"type":"Point"}
}