{
  "type": "Feature",
  "properties": {
    "iso:country":"GB",
    "sg:address":"Unit 7 Little Balmer, Buckingham Industrial Es",
    "sg:city":"Buckingham",
    "sg:classifiers":[
        {
            "category":"Professional",
            "subcategory":"Art Services",
            "type":"Services"
        }
    ],
    "sg:postcode":"MK18 1TF",
    "sg:province":"Buckinghamshire",
    "sg:tags":[
        "consultant",
        "design"
    ],
    "wof:name":"Racing Designs Ltd",
    "wof:placetype":"venue"
},
  "geometry": {"coordinates":[-0.9864789844,52.0007514954],"type":"Point"}
}