{
  "type": "Feature",
  "properties": {
    "iso:country":"GB",
    "sg:address":"Imperial Chambers, 10-17 Seven Ways Parade Woodford Avenue",
    "sg:city":"Ilford",
    "sg:classifiers":[
        {
            "category":"Education",
            "subcategory":"School",
            "type":"Public Place"
        }
    ],
    "sg:postcode":"IG2 6JX",
    "sg:province":"Essex",
    "sg:tags":[
        "local",
        "authority"
    ],
    "wof:name":"Rodwell Recruitment And Training Ltd",
    "wof:placetype":"venue"
},
  "geometry": {"coordinates":[0.0665099993,51.5767211914],"type":"Point"}
}