{
  "type": "Feature",
  "properties": {
    "iso:country":"GB",
    "sg:address":"Stapleford Road, Trowell",
    "sg:city":"Nottingham",
    "sg:classifiers":[
        {
            "category":"Manufacturing",
            "subcategory":"Buildings",
            "type":"Manufacturing & Wholesale Goods"
        }
    ],
    "sg:phone":"+44 115 932 3280",
    "sg:postcode":"NG9 3PS",
    "sg:province":"Nottinghamshire",
    "sg:tags":[
        "portable"
    ],
    "wof:name":"B S Sectional Buildings",
    "wof:placetype":"venue"
},
  "geometry": {"coordinates":[-1.281635046,52.9525947571],"type":"Point"}
}