{
  "type": "Feature",
  "properties": {
    "iso:country":"GB",
    "sg:address":"Stainton Quarry, Long La",
    "sg:city":"Barrow In Furness",
    "sg:classifiers":[
        {
            "category":"Manufacturing",
            "subcategory":"Building Materials",
            "type":"Manufacturing & Wholesale Goods"
        }
    ],
    "sg:phone":"+44 1229 468094",
    "sg:postcode":"LA13 0NN",
    "sg:province":"Cumbria",
    "sg:tags":[
        "concrete",
        "product"
    ],
    "wof:name":"Concrete Products North West",
    "wof:placetype":"venue"
},
  "geometry": {"coordinates":[-3.15223,54.1427],"type":"Point"}
}