{
  "type": "Feature",
  "properties": {
    "addr:full":"154 Harbour Way Shoreham-by-sea West Sussex BN43 5HJ",
    "addr:housenumber":"154",
    "addr:postcode":"bn43 5hj",
    "addr:street":"Harbour Way",
    "iso:country":"GB",
    "sg:address":"154 Harbour Way",
    "sg:city":"Shoreham-by-sea",
    "sg:classifiers":[
        {
            "category":"Retail",
            "subcategory":"Driving School",
            "type":"Services"
        }
    ],
    "sg:postcode":"BN43 5HJ",
    "sg:province":"West Sussex",
    "wof:name":"Hiltons Driving School",
    "wof:placetype":"venue"
},
  "geometry": {"coordinates":[-0.255663991,50.829460144],"type":"Point"}
}