{
  "type": "Feature",
  "properties": {
    "addr:full":"284 - 288 Western Road London Greater London SW19 2QA",
    "addr:housenumber":"288",
    "addr:postcode":"sw19 2qa",
    "addr:street":"Western Road",
    "iso:country":"GB",
    "sg:address":"284 - 288 Western Road",
    "sg:city":"London",
    "sg:classifiers":[
        {
            "category":"Food & Beverages",
            "subcategory":"Supermarket",
            "type":"Retail Goods"
        }
    ],
    "sg:phone":"+44 20 8648 9898",
    "sg:postcode":"SW19 2QA",
    "sg:province":"Greater London",
    "sg:tags":[
        "frozen"
    ],
    "wof:name":"Kim's Food",
    "wof:placetype":"venue"
},
  "geometry": {"coordinates":[-0.1763599962,51.4123001099],"type":"Point"}
}