{
  "type": "Feature",
  "properties": {
    "addr:full":"8 The Chare Peterlee Durham SR8 5AE",
    "addr:housenumber":"8",
    "addr:postcode":"sr8 5ae",
    "addr:street":"The Chare",
    "iso:country":"GB",
    "sg:address":"8 The Chare",
    "sg:city":"Peterlee",
    "sg:classifiers":[
        {
            "category":"Shopping",
            "subcategory":"Gifts & Souvenirs",
            "type":"Retail Goods"
        }
    ],
    "sg:phone":"+44 191 587 1292",
    "sg:postcode":"SR8 5AE",
    "sg:province":"Durham",
    "sg:tags":[
        "poster",
        "card"
    ],
    "wof:name":"Clintons Card",
    "wof:placetype":"venue"
},
  "geometry": {"coordinates":[-1.3322190046,54.7617492676],"type":"Point"}
}