{
  "type": "Feature",
  "properties": {
    "addr:full":"151 Mansfield Road, Clipstone Village Mansfield Nottinghamshire NG21 9AA",
    "addr:housenumber":"151",
    "addr:postcode":"ng21 9aa",
    "addr:street":"Mansfield Road",
    "iso:country":"GB",
    "sg:address":"151 Mansfield Road, Clipstone Village",
    "sg:city":"Mansfield",
    "sg:classifiers":[
        {
            "category":"Cinema",
            "subcategory":"Movie Rental",
            "type":"Entertainment"
        }
    ],
    "sg:phone":"+44 1623 649693",
    "sg:postcode":"NG21 9AA",
    "sg:province":"Nottinghamshire",
    "sg:tags":[
        "video",
        "library"
    ],
    "wof:name":"Clipstone Video Centre",
    "wof:placetype":"venue"
},
  "geometry": {"coordinates":[-1.1252590418,53.1599617004],"type":"Point"}
}