{
  "type": "Feature",
  "properties": {
    "addr:full":"10 Marmion Road Galashiels Scottish Borders TD1 2DE",
    "addr:housenumber":"10",
    "addr:postcode":"td1 2de",
    "addr:street":"Marmion Road",
    "iso:country":"GB",
    "sg:address":"10 Marmion Road",
    "sg:city":"Galashiels",
    "sg:classifiers":[
        {
            "category":"Government",
            "subcategory":"Post Office",
            "type":"Public Place"
        }
    ],
    "sg:postcode":"TD1 2DE",
    "sg:province":"Scottish Borders",
    "wof:name":"Langlee Post Office",
    "wof:placetype":"venue"
},
  "geometry": {"coordinates":[-2.7777910233,55.6102256775],"type":"Point"}
}