{
  "type": "Feature",
  "properties": {
    "addr:full":"9 Dereham Road, Mattishall Dereham Norfolk NR20 3QB",
    "addr:housenumber":"9",
    "addr:postcode":"nr20 3qb",
    "addr:street":"Dereham Road",
    "iso:country":"GB",
    "sg:address":"9 Dereham Road, Mattishall",
    "sg:city":"Dereham",
    "sg:classifiers":[
        {
            "category":"Shopping",
            "subcategory":"Pharmacy",
            "type":"Retail Goods"
        }
    ],
    "sg:postcode":"NR20 3QB",
    "sg:province":"Norfolk",
    "sg:tags":[
        "pharmacist",
        "chemist"
    ],
    "wof:name":"Mattishall Pharmacy",
    "wof:placetype":"venue"
},
  "geometry": {"coordinates":[1.034552,52.65881],"type":"Point"}
}