{
  "type": "Feature",
  "properties": {
    "iso:country":"GB",
    "sg:address":"Wilkin& Sons Ltd (international Farm Camp), Brook Road, Tiptree",
    "sg:city":"Colchester",
    "sg:classifiers":[
        {
            "category":"Food & Beverages",
            "subcategory":"Candy",
            "type":"Retail Goods"
        },
        {
            "category":"Manufacturing",
            "subcategory":"Food",
            "type":"Manufacturing & Wholesale Goods"
        }
    ],
    "sg:phone":"+44 1621 815407",
    "sg:postcode":"CO5 0RF",
    "sg:province":"Essex",
    "sg:tags":[
        "merchant",
        "product",
        "produce",
        "manufacturer"
    ],
    "sg:website":"http://www.tiptree.com",
    "wof:name":"Wilkin & Sons Ltd.",
    "wof:placetype":"venue"
},
  "geometry": {"coordinates":[0.75374,51.807301],"type":"Point"}
}