{
  "type": "Feature",
  "properties": {
    "addr:full":"35 Wellstead Avenue London Greater London N9 8QA",
    "addr:housenumber":"35",
    "addr:postcode":"n9 8qa",
    "addr:street":"Wellstead Avenue",
    "iso:country":"GB",
    "sg:address":"35 Wellstead Avenue",
    "sg:city":"London",
    "sg:classifiers":[
        {
            "category":"Real Estate",
            "subcategory":"Real Estate Services",
            "type":"Services"
        },
        {
            "category":"Building & Trades",
            "subcategory":"Cleaning & Sanitation",
            "type":"Services"
        }
    ],
    "sg:postcode":"N9 8QA",
    "sg:province":"Greater London",
    "sg:tags":[
        "commercial"
    ],
    "wof:name":"UNIVERSAL WINDOW & GENERAL CLEANING CO",
    "wof:placetype":"venue"
},
  "geometry": {"coordinates":[-0.0421020016,51.6342277527],"type":"Point"}
}