{
  "type": "Feature",
  "properties": {
    "iso:country":"GB",
    "sg:address":"Back Cross Lane",
    "sg:city":"Newton-le-willows",
    "sg:classifiers":[
        {
            "category":"Professional",
            "subcategory":"Printing & Photocopies",
            "type":"Services"
        }
    ],
    "sg:phone":"+44 1925 224444",
    "sg:postcode":"WA12 9YE",
    "sg:province":"Cheshire",
    "sg:tags":[
        "computer",
        "tag",
        "label"
    ],
    "wof:name":"Kenneth Smith",
    "wof:placetype":"venue"
},
  "geometry": {"coordinates":[-2.639489,53.455784],"type":"Point"}
}