{
  "type": "Feature",
  "properties": {
    "iso:country":"GB",
    "sg:address":"Lion Ho, 86 Station Rd",
    "sg:city":"West Wickham",
    "sg:classifiers":[
        {
            "category":"Building & Trades",
            "subcategory":"Construction",
            "type":"Services"
        }
    ],
    "sg:phone":"+44 20 8777 8077",
    "sg:postcode":"BR4 0PU",
    "sg:province":"Kent",
    "sg:tags":[
        "conversion",
        "loft"
    ],
    "wof:name":"Wickham Lofts Ltd",
    "wof:placetype":"venue"
},
  "geometry": {"coordinates":[-0.009324,51.374588],"type":"Point"}
}