{
  "type": "Feature",
  "properties": {
    "iso:country":"GB",
    "sg:address":"78 Crispin Street, Rothwell",
    "sg:city":"Kettering",
    "sg:classifiers":[
        {
            "category":"Food & Beverages",
            "subcategory":"Groceries & Convenience Stores",
            "type":"Retail Goods"
        }
    ],
    "sg:phone":"+44 1536 712614",
    "sg:postcode":"NN14 6DB",
    "sg:province":"Northamptonshire",
    "wof:name":"Crispin Street Stores",
    "wof:placetype":"venue"
},
  "geometry": {"coordinates":[-0.7930170298,52.4229469299],"type":"Point"}
}