{
  "type": "Feature",
  "properties": {
    "addr:full":"181 Woodford Av Ilford Essex IG4 5LH",
    "addr:housenumber":"181",
    "addr:postcode":"ig4 5lh",
    "addr:street":"Woodford Av Ilford",
    "iso:country":"GB",
    "sg:address":"181 Woodford Av",
    "sg:city":"Ilford",
    "sg:classifiers":[
        {
            "category":"Professional",
            "type":"Services"
        }
    ],
    "sg:phone":"+44 20 8550 2796",
    "sg:postcode":"IG4 5LH",
    "sg:province":"Essex",
    "sg:tags":[
        "entertainer"
    ],
    "wof:name":"Mysterel",
    "wof:placetype":"venue"
},
  "geometry": {"coordinates":[0.0555029996,51.584022522],"type":"Point"}
}