{
  "type": "Feature",
  "properties": {
    "addr:full":"Gilcar Street Normanton West Yorkshire WF6 1RD",
    "addr:postcode":"wf6 1rd",
    "addr:street":"Gilcar Street",
    "iso:country":"GB",
    "sg:address":"Gilcar Street",
    "sg:city":"Normanton",
    "sg:classifiers":[
        {
            "category":"Professional",
            "subcategory":"Testing Lab",
            "type":"Services"
        }
    ],
    "sg:postcode":"WF6 1RD",
    "sg:province":"West Yorkshire",
    "sg:tags":[
        "mot"
    ],
    "wof:name":"D & M M O T Centre",
    "wof:placetype":"venue"
},
  "geometry": {"coordinates":[-1.400684,53.707031],"type":"Point"}
}