{
  "type": "Feature",
  "properties": {
    "addr:full":"145 Bradford Road Shipley West Yorkshire BD18 3TH",
    "addr:housenumber":"145",
    "addr:postcode":"bd18 3th",
    "addr:street":"Bradford Road",
    "iso:country":"GB",
    "sg:address":"145 Bradford Road",
    "sg:city":"Shipley",
    "sg:classifiers":[
        {
            "category":"Travel",
            "subcategory":"Hotels & Motels",
            "type":"Entertainment"
        }
    ],
    "sg:postcode":"BD18 3TH",
    "sg:province":"West Yorkshire",
    "sg:tags":[
        "house",
        "guest"
    ],
    "wof:name":"South Gate House",
    "wof:placetype":"venue"
},
  "geometry": {"coordinates":[-1.778976,53.825169],"type":"Point"}
}