{
  "type": "Feature",
  "properties": {
    "addr:full":"1018 Dumbarton Road Glasgow Glasgow City G14 9UJ",
    "addr:housenumber":"1018",
    "addr:postcode":"g14 9uj",
    "addr:street":"Dumbarton Road",
    "iso:country":"GB",
    "sg:address":"1018 Dumbarton Road",
    "sg:city":"Glasgow",
    "sg:classifiers":[
        {
            "category":"Personal",
            "type":"Services"
        }
    ],
    "sg:postcode":"G14 9UJ",
    "sg:province":"Glasgow City",
    "sg:tags":[
        "dressmaker"
    ],
    "wof:name":"West End Dance Boutique",
    "wof:placetype":"venue"
},
  "geometry": {"coordinates":[-4.3311681747,55.8729934692],"type":"Point"}
}