{
  "type": "Feature",
  "properties": {
    "addr:full":"Suite 19 Immingham Centre, Margaret Street Immingham Lincolnshire DN40 1LE",
    "addr:postcode":"dn40 1le",
    "addr:street":"Suite 19 Immingham Centre Margaret Street",
    "iso:country":"GB",
    "sg:address":"Suite 19 Immingham Centre, Margaret Street",
    "sg:city":"Immingham",
    "sg:classifiers":[
        {
            "category":"Building & Trades",
            "subcategory":"Construction",
            "type":"Services"
        }
    ],
    "sg:postcode":"DN40 1LE",
    "sg:province":"Lincolnshire",
    "sg:tags":[
        "window",
        "replacement"
    ],
    "wof:name":"Trevor John Hopper",
    "wof:placetype":"venue"
},
  "geometry": {"coordinates":[-0.223969996,53.6114807129],"type":"Point"}
}