{
  "type": "Feature",
  "properties": {
    "iso:country":"GB",
    "sg:address":"Olympus Close",
    "sg:city":"Ipswich",
    "sg:classifiers":[
        {
            "category":"Freight",
            "type":"Transportation"
        },
        {
            "category":"Professional",
            "subcategory":"Printing & Photocopies",
            "type":"Services"
        }
    ],
    "sg:postcode":"IP1 5LN",
    "sg:province":"Suffolk",
    "sg:tags":[
        "haulage",
        "duplicating",
        "road",
        "copying"
    ],
    "wof:name":"I B T Ltd.",
    "wof:placetype":"venue"
},
  "geometry": {"coordinates":[1.11557,52.080315],"type":"Point"}
}