{
  "type": "Feature",
  "properties": {
    "iso:country":"GB",
    "sg:address":"Room 15 Bell Court House, 11 Blomfield Street",
    "sg:city":"London",
    "sg:classifiers":[
        {
            "category":"Manufacturing",
            "subcategory":"Tools & Machinery",
            "type":"Manufacturing & Wholesale Goods"
        }
    ],
    "sg:phone":"+44 1892 519677",
    "sg:postcode":"EC2M 7AY",
    "sg:province":"Greater London",
    "sg:tags":[
        "society",
        "friendly"
    ],
    "wof:name":"Garrods",
    "wof:placetype":"venue"
},
  "geometry": {"coordinates":[-0.084289,51.517872],"type":"Point"}
}