{
  "type": "Feature",
  "properties": {
    "addr:full":"30 Queens Terrace Southampton Hampshire SO14 3BQ",
    "addr:housenumber":"30",
    "addr:postcode":"so14 3bq",
    "addr:street":"Queens Terrace",
    "iso:country":"GB",
    "sg:address":"30 Queens Terrace",
    "sg:city":"Southampton",
    "sg:classifiers":[
        {
            "category":"Personal",
            "subcategory":"Beauty Salon",
            "type":"Services"
        }
    ],
    "sg:phone":"+44 23 8033 4354",
    "sg:postcode":"SO14 3BQ",
    "sg:province":"Hampshire",
    "sg:tags":[
        "unisex",
        "hairdresser"
    ],
    "wof:name":"Concepts Hair Salon",
    "wof:placetype":"venue"
},
  "geometry": {"coordinates":[-1.397611,50.897587],"type":"Point"}
}