{
  "type": "Feature",
  "properties": {
    "iso:country":"GB",
    "sg:address":"Reardon Court, Woodloes Avenue, Woodloes Park",
    "sg:city":"Warwick",
    "sg:classifiers":[
        {
            "category":"Food & Beverages",
            "subcategory":"Liquor & Beverages",
            "type":"Retail Goods"
        },
        {
            "category":"Shopping",
            "subcategory":"Pharmacy",
            "type":"Retail Goods"
        }
    ],
    "sg:phone":"+44 1926 494041",
    "sg:postcode":"CV34 5RN",
    "sg:province":"Warwickshire",
    "sg:tags":[
        "beer",
        "pharmacist",
        "spirit",
        "chemist",
        "wines"
    ],
    "wof:name":"Stratwicks Ltd.",
    "wof:placetype":"venue"
},
  "geometry": {"coordinates":[-1.581185,52.297695],"type":"Point"}
}