{
  "type": "Feature",
  "properties": {
    "addr:full":"Unit J7, Springhead Enterprise Park Gravesend Kent DA11 8HL",
    "addr:housenumber":"unit j7 springhead",
    "addr:postcode":"da11 8hl",
    "addr:street":"Enterprise Park",
    "iso:country":"GB",
    "sg:address":"Unit J7, Springhead Enterprise Park",
    "sg:city":"Gravesend",
    "sg:classifiers":[
        {
            "category":"Professional",
            "subcategory":"Printing & Photocopies",
            "type":"Services"
        }
    ],
    "sg:postcode":"DA11 8HL",
    "sg:province":"Kent",
    "sg:tags":[
        "process",
        "screen",
        "printer"
    ],
    "wof:name":"Print Graphics",
    "wof:placetype":"venue"
},
  "geometry": {"coordinates":[0.3330470026,51.4328727722],"type":"Point"}
}