{
  "type": "Feature",
  "properties": {
    "addr:full":"33 Topcliffe Street Hartlepool Durham TS26 8LL",
    "addr:housenumber":"33",
    "addr:postcode":"ts26 8ll",
    "addr:street":"Topcliffe Street",
    "iso:country":"GB",
    "sg:address":"33 Topcliffe Street",
    "sg:city":"Hartlepool",
    "sg:classifiers":[
        {
            "category":"Home & Garden",
            "subcategory":"Household Appliances",
            "type":"Retail Goods"
        }
    ],
    "sg:phone":"+44 1429 272600",
    "sg:postcode":"TS26 8LL",
    "sg:province":"Durham",
    "sg:tags":[
        "gas"
    ],
    "wof:name":"Chambers Heating Services",
    "wof:placetype":"venue"
},
  "geometry": {"coordinates":[-1.228483,54.688557],"type":"Point"}
}