{
  "type": "Feature",
  "properties": {
    "iso:country":"GB",
    "sg:address":"91 Dinsdale Crescent",
    "sg:city":"Darlington",
    "sg:classifiers":[
        {
            "category":"Arts & Performance",
            "subcategory":"Music",
            "type":"Entertainment"
        }
    ],
    "sg:phone":"+44 1325 355233",
    "sg:postcode":"DL1 1EZ",
    "sg:province":"Durham",
    "sg:tags":[
        "mobile",
        "disco"
    ],
    "wof:name":"Apollo's Roadshow",
    "wof:placetype":"venue"
},
  "geometry": {"coordinates":[-1.535692,54.524246],"type":"Point"}
}