{
  "type": "Feature",
  "properties": {
    "iso:country":"GB",
    "sg:address":"56 Ashfield Crescent, Netherton",
    "sg:city":"Dudley",
    "sg:classifiers":[
        {
            "category":"Building & Trades",
            "subcategory":"Construction",
            "type":"Services"
        }
    ],
    "sg:phone":"+44 1384 635750",
    "sg:postcode":"DY2 0BQ",
    "sg:province":"West Midlands",
    "sg:tags":[
        "roofing",
        "contracting"
    ],
    "wof:name":"Craig Shakespeare",
    "wof:placetype":"venue"
},
  "geometry": {"coordinates":[-2.0884389877,52.4816627502],"type":"Point"}
}