{
  "type": "Feature",
  "properties": {
    "iso:country":"GB",
    "sg:address":"5 Nelson Road, Westward House",
    "sg:city":"Bideford",
    "sg:classifiers":[
        {
            "category":"Bars & Pubs",
            "type":"Food & Drink"
        }
    ],
    "sg:postcode":"EX39 1LF",
    "sg:province":"Devon",
    "sg:tags":[
        "pubs",
        "inn"
    ],
    "wof:name":"The Nelson Inn",
    "wof:placetype":"venue"
},
  "geometry": {"coordinates":[-4.23894,51.03989],"type":"Point"}
}