{
  "type": "Feature",
  "properties": {
    "iso:country":"GB",
    "sg:address":"241 Albert Road",
    "sg:city":"Southsea",
    "sg:classifiers":[
        {
            "category":"Food & Beverages",
            "subcategory":"Specialty",
            "type":"Retail Goods"
        }
    ],
    "sg:phone":"+44 23 9275 3458",
    "sg:postcode":"PO4 0JR",
    "sg:province":"Hampshire",
    "sg:tags":[
        "retailer",
        "product",
        "health"
    ],
    "wof:name":"Southsea Health Shop",
    "wof:placetype":"venue"
},
  "geometry": {"coordinates":[-1.0713649988,50.7865219116],"type":"Point"}
}