{
  "type": "Feature",
  "properties": {
    "addr:full":"7 Leys Av Letchworth Hertfordshire SG6 3EA",
    "addr:housenumber":"7",
    "addr:postcode":"sg6 3ea",
    "addr:street":"Leys Av Letchworth",
    "iso:country":"GB",
    "sg:address":"7 Leys Av",
    "sg:city":"Letchworth",
    "sg:classifiers":[
        {
            "category":"Education",
            "subcategory":"Special Training",
            "type":"Public Place"
        }
    ],
    "sg:phone":"+44 1462 676333",
    "sg:postcode":"SG6 3EA",
    "sg:province":"Hertfordshire",
    "sg:tags":[
        "product",
        "centre"
    ],
    "wof:name":"Stacs Network Ltd",
    "wof:placetype":"venue"
},
  "geometry": {"coordinates":[-0.227348,51.979076],"type":"Point"}
}