{
  "type": "Feature",
  "properties": {
    "iso:country":"GB",
    "sg:address":"37 Priory Avenue",
    "sg:city":"Taunton",
    "sg:classifiers":[
        {
            "category":"Manufacturing",
            "subcategory":"Signs",
            "type":"Manufacturing & Wholesale Goods"
        }
    ],
    "sg:phone":"+44 1823 283985",
    "sg:postcode":"TA1 1XZ",
    "sg:province":"Somerset",
    "sg:tags":[
        "nameplate"
    ],
    "wof:name":"P J Signs",
    "wof:placetype":"venue"
},
  "geometry": {"coordinates":[-3.096492,51.018829],"type":"Point"}
}