{
  "type": "Feature",
  "properties": {
    "iso:country":"GB",
    "sg:address":"38 Lawrence Clo, Higham",
    "sg:city":"Barnsley",
    "sg:classifiers":[
        {
            "category":"Retail",
            "subcategory":"Event Space",
            "type":"Services"
        }
    ],
    "sg:phone":"+44 1226 386677",
    "sg:postcode":"S75 1PE",
    "sg:province":"South Yorkshire",
    "sg:tags":[
        "exhibition",
        "organiser"
    ],
    "wof:name":"D M P Promotions (U K) Ltd",
    "wof:placetype":"venue"
},
  "geometry": {"coordinates":[-1.5313869715,53.5620880127],"type":"Point"}
}