{
  "type": "Feature",
  "properties": {
    "iso:country":"GB",
    "sg:address":"Birley Lane, Hathersage",
    "sg:city":"Hope Valley",
    "sg:classifiers":[
        {
            "category":"Travel",
            "subcategory":"Hotels & Motels",
            "type":"Entertainment"
        }
    ],
    "sg:phone":"+44 1433 650838",
    "sg:postcode":"S32 1BR",
    "sg:province":"Derbyshire",
    "sg:tags":[
        "house",
        "guest"
    ],
    "wof:name":"Peak Park Joint Planning Board",
    "wof:placetype":"venue"
},
  "geometry": {"coordinates":[-1.659096,53.341877],"type":"Point"}
}