{
  "type": "Feature",
  "properties": {
    "addr:full":"43 Sandringham Rd Stafford Staffordshire ST17 0AA",
    "addr:housenumber":"43",
    "addr:postcode":"st17 0aa",
    "addr:street":"Sandringham Rd",
    "iso:country":"GB",
    "sg:address":"43 Sandringham Rd",
    "sg:city":"Stafford",
    "sg:classifiers":[
        {
            "category":"Government",
            "subcategory":"Office",
            "type":"Public Place"
        }
    ],
    "sg:phone":"+44 1785 229197",
    "sg:postcode":"ST17 0AA",
    "sg:province":"Staffordshire",
    "sg:tags":[
        "central"
    ],
    "wof:name":"The Gaming Board for Great Britain",
    "wof:placetype":"venue"
},
  "geometry": {"coordinates":[-2.087505,52.793411],"type":"Point"}
}