{
  "type": "Feature",
  "properties": {
    "iso:country":"GB",
    "sg:address":"29 Egerton Street, Canton",
    "sg:city":"Cardiff",
    "sg:classifiers":[
        {
            "category":"Manufacturing",
            "subcategory":"Signs",
            "type":"Manufacturing & Wholesale Goods"
        }
    ],
    "sg:phone":"+44 29 2023 0808",
    "sg:postcode":"CF5 1RF",
    "sg:province":"Cardiff",
    "sg:tags":[
        "writer"
    ],
    "wof:name":"Moonsigns Ltd.",
    "wof:placetype":"venue"
},
  "geometry": {"coordinates":[-3.210351,51.483948],"type":"Point"}
}