{
  "type": "Feature",
  "properties": {
    "addr:full":"234 Stockton Road Hartlepool Durham TS25 5DE",
    "addr:housenumber":"234",
    "addr:postcode":"ts25 5de",
    "addr:street":"Stockton Road",
    "iso:country":"GB",
    "sg:address":"234 Stockton Road",
    "sg:city":"Hartlepool",
    "sg:classifiers":[
        {
            "category":"Retail",
            "subcategory":"Auto Repair",
            "type":"Services"
        }
    ],
    "sg:phone":"+44 1429 277981",
    "sg:postcode":"TS25 5DE",
    "sg:province":"Durham",
    "sg:tags":[
        "modification",
        "car",
        "vehicle",
        "commercial",
        "garage"
    ],
    "wof:name":"J R M Motor Engineers",
    "wof:placetype":"venue"
},
  "geometry": {"coordinates":[-1.219521,54.665051],"type":"Point"}
}