{
  "type": "Feature",
  "properties": {
    "iso:country":"GB",
    "sg:address":"21 Chipstead Valley Road",
    "sg:city":"Coulsdon",
    "sg:classifiers":[
        {
            "category":"Home & Garden",
            "subcategory":"Hardware",
            "type":"Retail Goods"
        }
    ],
    "sg:phone":"+44 20 8668 1055",
    "sg:postcode":"CR5 2RB",
    "sg:province":"Surrey",
    "wof:name":"R P Johnson",
    "wof:placetype":"venue"
},
  "geometry": {"coordinates":[-0.139158,51.320541],"type":"Point"}
}