{
  "type": "Feature",
  "properties": {
    "iso:country":"GB",
    "sg:address":"9 Churchill Dr",
    "sg:city":"Wrexham",
    "sg:classifiers":[
        {
            "category":"Shopping",
            "subcategory":"Pharmacy",
            "type":"Retail Goods"
        }
    ],
    "sg:postcode":"LL13 9HH",
    "sg:province":"Wrexham",
    "sg:tags":[
        "pharmacist",
        "chemist"
    ],
    "wof:name":"Edwards,Adrian,",
    "wof:placetype":"venue"
},
  "geometry": {"coordinates":[-2.970115,53.047474],"type":"Point"}
}