{
  "type": "Feature",
  "properties": {
    "addr:full":"Albemarle House, 1 Albemarle Street London Greater London W1S 4HA",
    "addr:housenumber":"1",
    "addr:postcode":"w1s 4ha",
    "addr:street":"Albemarle Street",
    "iso:country":"GB",
    "sg:address":"Albemarle House, 1 Albemarle Street",
    "sg:city":"London",
    "sg:classifiers":[
        {
            "category":"Real Estate",
            "subcategory":"Developer",
            "type":"Services"
        }
    ],
    "sg:postcode":"W1S 4HA",
    "sg:province":"Greater London",
    "sg:tags":[
        "property"
    ],
    "wof:name":"Meydale Ltd",
    "wof:placetype":"venue"
},
  "geometry": {"coordinates":[-0.1405930072,51.5079803467],"type":"Point"}
}