{
  "type": "Feature",
  "properties": {
    "addr:full":"239 Bensham Road Gateshead Tyne and Wear NE8 1US",
    "addr:housenumber":"239",
    "addr:postcode":"ne8 1us",
    "addr:street":"Bensham Road",
    "iso:country":"GB",
    "sg:address":"239 Bensham Road",
    "sg:city":"Gateshead",
    "sg:classifiers":[
        {
            "category":"Retail",
            "subcategory":"Laundry & Dry Cleaning",
            "type":"Services"
        }
    ],
    "sg:phone":"+44 191 478 4602",
    "sg:postcode":"NE8 1US",
    "sg:province":"Tyne and Wear",
    "sg:tags":[
        "launderette"
    ],
    "wof:name":"Washeteria",
    "wof:placetype":"venue"
},
  "geometry": {"coordinates":[-1.614380002,54.9546356201],"type":"Point"}
}