{
  "type": "Feature",
  "properties": {
    "iso:country":"GB",
    "sg:address":"Main Street, New Blyth",
    "sg:city":"Turriff",
    "sg:classifiers":[
        {
            "category":"Education",
            "subcategory":"School",
            "type":"Public Place"
        },
        {
            "category":"Government",
            "subcategory":"Office",
            "type":"Public Place"
        }
    ],
    "sg:phone":"+44 1888 544204",
    "sg:postcode":"AB53 5XD",
    "sg:province":"Aberdeenshire",
    "sg:tags":[
        "local",
        "authority"
    ],
    "wof:name":"New Blyth Primary School",
    "wof:placetype":"venue"
},
  "geometry": {"coordinates":[-2.335203886,57.5426597595],"type":"Point"}
}