{
  "type": "Feature",
  "properties": {
    "iso:country":"GB",
    "sg:address":"Unit 3a Bessemer Close, Ebblake Industrial Estate",
    "sg:city":"Verwood",
    "sg:classifiers":[
        {
            "category":"Professional",
            "subcategory":"Engineering",
            "type":"Services"
        },
        {
            "category":"Building & Trades",
            "subcategory":"Plumbing",
            "type":"Services"
        }
    ],
    "sg:phone":"+44 1202 821340",
    "sg:postcode":"BH31 6AZ",
    "sg:province":"Dorset",
    "sg:tags":[
        "civil",
        "clearance",
        "drain",
        "engineer",
        "sewer"
    ],
    "wof:name":"Environmental Drain Services Ltd.",
    "wof:placetype":"venue"
},
  "geometry": {"coordinates":[-1.8526690006,50.8675498962],"type":"Point"}
}