{
  "type": "Feature",
  "properties": {
    "addr:full":"1 Wylva Road Liverpool Merseyside L4 0TS",
    "addr:housenumber":"1",
    "addr:postcode":"l4 0ts",
    "addr:street":"Wylva Road",
    "iso:country":"GB",
    "sg:address":"1 Wylva Road",
    "sg:city":"Liverpool",
    "sg:classifiers":[
        {
            "category":"Retail",
            "subcategory":"Auto Repair",
            "type":"Services"
        }
    ],
    "sg:postcode":"L4 0TS",
    "sg:province":"Merseyside",
    "sg:tags":[
        "modification",
        "garage"
    ],
    "wof:name":"Auto Electrics",
    "wof:placetype":"venue"
},
  "geometry": {"coordinates":[-2.959688,53.429657],"type":"Point"}
}