{
  "type": "Feature",
  "properties": {
    "iso:country":"GB",
    "sg:address":"5 The Green, North Wingfield",
    "sg:city":"Chesterfield",
    "sg:classifiers":[
        {
            "category":"Autos & Motor Vehicles",
            "subcategory":"Automobile Sales",
            "type":"Retail Goods"
        }
    ],
    "sg:postcode":"S42 5NF",
    "sg:province":"Derbyshire",
    "sg:tags":[
        "car"
    ],
    "wof:name":"B & H Autos",
    "wof:placetype":"venue"
},
  "geometry": {"coordinates":[-1.387751,53.180809],"type":"Point"}
}