{
  "type": "Feature",
  "properties": {
    "addr:full":"Dobbies Gardening World, Melville Nurseries Lasswade City of Edinburgh EH18 1AZ",
    "addr:postcode":"eh18 1az",
    "addr:street":"Lasswade",
    "iso:country":"GB",
    "sg:address":"Dobbies Gardening World, Melville Nurseries",
    "sg:city":"Lasswade",
    "sg:classifiers":[
        {
            "category":"Education",
            "subcategory":"Music School",
            "type":"Public Place"
        }
    ],
    "sg:postcode":"EH18 1AZ",
    "sg:province":"City of Edinburgh",
    "sg:tags":[
        "conservatory"
    ],
    "wof:name":"Fersina Edinburgh",
    "wof:placetype":"venue"
},
  "geometry": {"coordinates":[-3.114514,55.883186],"type":"Point"}
}