{
  "type": "Feature",
  "properties": {
    "addr:full":"Militair House, Stag Business Park, Christchurch Road Ringwood Dorset BH24 3RP",
    "addr:postcode":"bh24 3rp",
    "addr:street":"Christchurch Road",
    "iso:country":"GB",
    "sg:address":"Militair House, Stag Business Park, Christchurch Road",
    "sg:city":"Ringwood",
    "sg:classifiers":[
        {
            "category":"Airport",
            "subcategory":"General Aviation",
            "type":"Transportation"
        }
    ],
    "sg:phone":"+44 1425 474760",
    "sg:postcode":"BH24 3RP",
    "sg:province":"Dorset",
    "wof:name":"Militair Aviation Ltd.",
    "wof:placetype":"venue"
},
  "geometry": {"coordinates":[-1.7929890156,50.8463287354],"type":"Point"}
}