{
  "type": "Feature",
  "properties": {
    "addr:full":"Post Office Road, Inkpen, Hungerford Newbury Berkshire RG17 9PY",
    "addr:postcode":"rg17 9py",
    "addr:street":"Office Road",
    "iso:country":"GB",
    "sg:address":"Post Office Road, Inkpen, Hungerford",
    "sg:city":"Newbury",
    "sg:classifiers":[
        {
            "category":"Professional",
            "subcategory":"Art Services",
            "type":"Services"
        }
    ],
    "sg:phone":"+44 1488 668975",
    "sg:postcode":"RG17 9PY",
    "sg:province":"Berkshire",
    "sg:tags":[
        "graphic",
        "designer"
    ],
    "wof:name":"Origin Eight",
    "wof:placetype":"venue"
},
  "geometry": {"coordinates":[-1.4643419981,51.3781280518],"type":"Point"}
}