{
  "type": "Feature",
  "properties": {
    "iso:country":"GB",
    "sg:address":"Main Road, Flax Bourton",
    "sg:city":"Bristol",
    "sg:classifiers":[
        {
            "category":"Travel",
            "subcategory":"Hotels & Motels",
            "type":"Entertainment"
        }
    ],
    "sg:phone":"+44 1275 462461",
    "sg:postcode":"BS48 3QQ",
    "sg:province":"Somerset",
    "sg:tags":[
        "house",
        "guest"
    ],
    "wof:name":"Castle Farm",
    "wof:placetype":"venue"
},
  "geometry": {"coordinates":[-2.710031,51.420906],"type":"Point"}
}