{
  "type": "Feature",
  "properties": {
    "addr:full":"59a Chesson Road London Greater London W14 9QS",
    "addr:housenumber":"59a",
    "addr:postcode":"w14 9qs",
    "addr:street":"Chesson Road",
    "iso:country":"GB",
    "sg:address":"59a Chesson Road",
    "sg:city":"London",
    "sg:classifiers":[
        {
            "category":"Professional",
            "subcategory":"Management & Consulting",
            "type":"Services"
        }
    ],
    "sg:postcode":"W14 9QS",
    "sg:province":"Greater London",
    "sg:tags":[
        "music"
    ],
    "wof:name":"Seven Publishing & Management",
    "wof:placetype":"venue"
},
  "geometry": {"coordinates":[-0.2058009952,51.4858283997],"type":"Point"}
}