{
  "type": "Feature",
  "properties": {
    "addr:full":"120 Finney La, Heald Grn Cheadle Cheshire SK8 3DY",
    "addr:housenumber":"120",
    "addr:postcode":"sk8 3dy",
    "addr:street":"Finney La Heald Grn Cheadle",
    "iso:country":"GB",
    "sg:address":"120 Finney La, Heald Grn",
    "sg:city":"Cheadle",
    "sg:classifiers":[
        {
            "category":"Travel",
            "subcategory":"Travel Agent",
            "type":"Entertainment"
        }
    ],
    "sg:postcode":"SK8 3DY",
    "sg:province":"Cheshire",
    "wof:name":"Giddings,Howard,",
    "wof:placetype":"venue"
},
  "geometry": {"coordinates":[-2.238052,53.370785],"type":"Point"}
}