{
  "type": "Feature",
  "properties": {
    "addr:full":"Sharrington Hall, Lower Hall Lane, Sharrington Melton Constable Norfolk NR24 2PQ",
    "addr:postcode":"nr24 2pq",
    "addr:street":"Lower Hall Lane",
    "iso:country":"GB",
    "sg:address":"Sharrington Hall, Lower Hall Lane, Sharrington",
    "sg:city":"Melton Constable",
    "sg:classifiers":[
        {
            "category":"Shopping",
            "subcategory":"Antiques",
            "type":"Retail Goods"
        }
    ],
    "sg:phone":"+44 1263 861411",
    "sg:postcode":"NR24 2PQ",
    "sg:province":"Norfolk",
    "wof:name":"Sharrington Antiques",
    "wof:placetype":"venue"
},
  "geometry": {"coordinates":[1.0384149551,52.8566246033],"type":"Point"}
}