{
  "type": "Feature",
  "properties": {
    "addr:full":"King Street Gravesend Kent DA12 2EB",
    "addr:postcode":"da12 2eb",
    "addr:street":"King Street",
    "iso:country":"GB",
    "sg:address":"King Street",
    "sg:city":"Gravesend",
    "sg:classifiers":[
        {
            "category":"Cinema",
            "subcategory":"Movie Theater",
            "type":"Entertainment"
        }
    ],
    "sg:phone":"+44 1474 356947",
    "sg:postcode":"DA12 2EB",
    "sg:province":"Kent",
    "wof:name":"Cannon Cinemas",
    "wof:placetype":"venue"
},
  "geometry": {"coordinates":[0.3702250123,51.4423179626],"type":"Point"}
}