{
  "type": "Feature",
  "properties": {
    "iso:country":"GB",
    "sg:address":"4 Church St West, Radcliffe",
    "sg:city":"Manchester",
    "sg:classifiers":[
        {
            "category":"Wholesale",
            "subcategory":"Vending Machines",
            "type":"Manufacturing & Wholesale Goods"
        }
    ],
    "sg:postcode":"M26 2SQ",
    "sg:province":"Greater Manchester",
    "sg:tags":[
        "sale"
    ],
    "wof:name":"The Pipe Bowl",
    "wof:placetype":"venue"
},
  "geometry": {"coordinates":[-2.324535,53.559093],"type":"Point"}
}