{
  "type": "Feature",
  "properties": {
    "iso:country":"GB",
    "sg:address":"342-348 Blackpool Road, Fulwood",
    "sg:city":"Preston",
    "sg:classifiers":[
        {
            "category":"Home & Garden",
            "subcategory":"Carpets & Floor Coverings",
            "type":"Retail Goods"
        }
    ],
    "sg:phone":"+44 1772 715522",
    "sg:postcode":"PR2 3AA",
    "sg:province":"Lancashire",
    "sg:tags":[
        "carpets",
        "retailer",
        "rug",
        "matting"
    ],
    "wof:name":"David Hall Carpets",
    "wof:placetype":"venue"
},
  "geometry": {"coordinates":[-2.713381,53.773945],"type":"Point"}
}