{
  "type": "Feature",
  "properties": {
    "addr:full":"Unit 7 Flexi-units, Budlake Road, Marsh Barton Exeter Devon EX2 8PY",
    "addr:housenumber":"unit 7",
    "addr:postcode":"ex2 8py",
    "addr:street":"Budlake Road",
    "iso:country":"GB",
    "sg:address":"Unit 7 Flexi-units, Budlake Road, Marsh Barton",
    "sg:city":"Exeter",
    "sg:classifiers":[
        {
            "category":"Building & Trades",
            "subcategory":"Landscaping Services",
            "type":"Services"
        },
        {
            "category":"Autos & Motor Vehicles",
            "subcategory":"Auto Supplies",
            "type":"Retail Goods"
        }
    ],
    "sg:phone":"+44 1392 278701",
    "sg:postcode":"EX2 8PY",
    "sg:province":"Devon",
    "sg:tags":[
        "horticultural",
        "towbars",
        "consultant"
    ],
    "wof:name":"Britannia Towing Centre",
    "wof:placetype":"venue"
},
  "geometry": {"coordinates":[-3.5271201134,50.7005500793],"type":"Point"}
}