{
  "type": "Feature",
  "properties": {
    "iso:country":"GB",
    "sg:address":"Robins Wood, Nibley Lane, Iron Acton",
    "sg:city":"Bristol",
    "sg:classifiers":[
        {
            "category":"Retail",
            "subcategory":"Auto Repair",
            "type":"Services"
        }
    ],
    "sg:postcode":"BS37 9UR",
    "sg:province":"Gloucestershire",
    "sg:tags":[
        "engine",
        "specialist",
        "garage",
        "modification",
        "car"
    ],
    "wof:name":"C & B Engineering Services",
    "wof:placetype":"venue"
},
  "geometry": {"coordinates":[-2.4605131149,51.5501823425],"type":"Point"}
}