{
  "type": "Feature",
  "properties": {
    "addr:full":"75 Queen St Pembroke Dock Pembrokeshire SA72 6JE",
    "addr:housenumber":"75",
    "addr:postcode":"sa72 6je",
    "addr:street":"Queen St",
    "iso:country":"GB",
    "sg:address":"75 Queen St",
    "sg:city":"Pembroke Dock",
    "sg:classifiers":[
        {
            "category":"Communications",
            "subcategory":"Film & Video Production",
            "type":"Services"
        }
    ],
    "sg:phone":"+44 1646 683248",
    "sg:postcode":"SA72 6JE",
    "sg:province":"Pembrokeshire",
    "sg:tags":[
        "tv"
    ],
    "wof:name":"Granada Home Technology",
    "wof:placetype":"venue"
},
  "geometry": {"coordinates":[-4.943171978,51.6940040588],"type":"Point"}
}