{
  "type": "Feature",
  "properties": {
    "addr:full":"8 Borough Road Darwen Lancashire BB3 1PL",
    "addr:housenumber":"8",
    "addr:postcode":"bb3 1pl",
    "addr:street":"Borough Road",
    "iso:country":"GB",
    "sg:address":"8 Borough Road",
    "sg:city":"Darwen",
    "sg:classifiers":[
        {
            "category":"Building & Trades",
            "subcategory":"Construction",
            "type":"Services"
        }
    ],
    "sg:phone":"+44 1254 209030",
    "sg:postcode":"BB3 1PL",
    "sg:province":"Lancashire",
    "sg:tags":[
        "builder"
    ],
    "wof:name":"W H Bailey Construction (Darwen) Ltd.",
    "wof:placetype":"venue"
},
  "geometry": {"coordinates":[-2.468864,53.69582],"type":"Point"}
}