{
  "type": "Feature",
  "properties": {
    "addr:full":"20 Wycombe Road, Holmer Grn High Wycombe Buckinghamshire HP15 6RY",
    "addr:housenumber":"20",
    "addr:postcode":"hp15 6ry",
    "addr:street":"Wycombe Road Holmer Grn",
    "iso:country":"GB",
    "sg:address":"20 Wycombe Road, Holmer Grn",
    "sg:city":"High Wycombe",
    "sg:classifiers":[
        {
            "category":"Retail",
            "subcategory":"Storage",
            "type":"Services"
        }
    ],
    "sg:phone":"+44 1494 712228",
    "sg:postcode":"HP15 6RY",
    "sg:province":"Buckinghamshire",
    "sg:tags":[
        "household",
        "activity",
        "domestic",
        "removal"
    ],
    "wof:name":"G F Howland & Son",
    "wof:placetype":"venue"
},
  "geometry": {"coordinates":[-0.703817,51.661617],"type":"Point"}
}