{
  "type": "Feature",
  "properties": {
    "addr:full":"The Street Norwich Norfolk NR14 6AA",
    "addr:postcode":"nr14 6aa",
    "addr:street":"The Street",
    "iso:country":"GB",
    "sg:address":"The Street",
    "sg:city":"Norwich",
    "sg:classifiers":[
        {
            "category":"Recreation",
            "subcategory":"Campground",
            "type":"Entertainment"
        }
    ],
    "sg:phone":"+44 1502 677265",
    "sg:postcode":"NR14 6AA",
    "sg:province":"Norfolk",
    "sg:tags":[
        "caravan",
        "park"
    ],
    "wof:name":"Pampas Lodge Caravan Site",
    "wof:placetype":"venue"
},
  "geometry": {"coordinates":[1.6035410166,52.5160942078],"type":"Point"}
}