{
  "type": "Feature",
  "properties": {
    "iso:country":"GB",
    "sg:address":"26 Cromwell Road, Alperton",
    "sg:city":"Wembley",
    "sg:classifiers":[
        {
            "category":"Building & Trades",
            "subcategory":"Construction",
            "type":"Services"
        }
    ],
    "sg:phone":"+44 20 8991 5646",
    "sg:postcode":"HA0 1JS",
    "sg:province":"Greater London",
    "sg:tags":[
        "builder"
    ],
    "wof:name":"M J O'Malley",
    "wof:placetype":"venue"
},
  "geometry": {"coordinates":[-0.298892,51.536514],"type":"Point"}
}