{
  "type": "Feature",
  "properties": {
    "iso:country":"GB",
    "sg:address":"Sandoes, Feock",
    "sg:city":"Truro",
    "sg:classifiers":[
        {
            "category":"Organizations",
            "subcategory":"Non-profit Organization",
            "type":"Services"
        }
    ],
    "sg:postcode":"TR3 6QN",
    "sg:province":"Cornwall",
    "sg:tags":[
        "organisation",
        "voluntary",
        "charity"
    ],
    "wof:name":"The Mission to Seamen",
    "wof:placetype":"venue"
},
  "geometry": {"coordinates":[-5.0518932343,50.2067642212],"type":"Point"}
}