{
  "type": "Feature",
  "properties": {
    "addr:full":"The Angel, The Ash, Little Hadham Ware Hertfordshire SG11 2DG",
    "addr:housenumber":"hadham",
    "addr:postcode":"sg11 2dg",
    "addr:street":"The;Ware",
    "iso:country":"GB",
    "sg:address":"The Angel, The Ash, Little Hadham",
    "sg:city":"Ware",
    "sg:classifiers":[
        {
            "category":"Professional",
            "subcategory":"Management & Consulting",
            "type":"Services"
        }
    ],
    "sg:phone":"+44 1279 771996",
    "sg:postcode":"SG11 2DG",
    "sg:province":"Hertfordshire",
    "sg:tags":[
        "marketing",
        "consultant"
    ],
    "wof:name":"Speednet",
    "wof:placetype":"venue"
},
  "geometry": {"coordinates":[0.089898,51.884453],"type":"Point"}
}