{
  "type": "Feature",
  "properties": {
    "addr:full":"Ashendene Farm, White Stubbs Lane, Bayford Hertford Hertfordshire SG13 8PZ",
    "addr:housenumber":"white",
    "addr:postcode":"sg13 8pz",
    "addr:street":"Stubbs Lane",
    "iso:country":"GB",
    "sg:address":"Ashendene Farm, White Stubbs Lane, Bayford",
    "sg:city":"Hertford",
    "sg:classifiers":[
        {
            "category":"Real Estate",
            "subcategory":"Architect",
            "type":"Services"
        }
    ],
    "sg:phone":"+44 1992 511204",
    "sg:postcode":"SG13 8PZ",
    "sg:province":"Hertfordshire",
    "sg:tags":[
        "architectural"
    ],
    "wof:name":"Ashendene Ltd.",
    "wof:placetype":"venue"
},
  "geometry": {"coordinates":[-0.102728,51.759243],"type":"Point"}
}