{
  "type": "Feature",
  "properties": {
    "addr:full":"51 Benvie Road Dundee Dundee City DD2 2PB",
    "addr:housenumber":"51",
    "addr:postcode":"dd2 2pb",
    "addr:street":"Benvie Road",
    "iso:country":"GB",
    "sg:address":"51 Benvie Road",
    "sg:city":"Dundee",
    "sg:classifiers":[
        {
            "category":"Retail",
            "subcategory":"Auto Repair",
            "type":"Services"
        }
    ],
    "sg:phone":"+44 1382 641300",
    "sg:postcode":"DD2 2PB",
    "sg:province":"Dundee City",
    "sg:tags":[
        "body",
        "car"
    ],
    "wof:name":"J Bogan",
    "wof:placetype":"venue"
},
  "geometry": {"coordinates":[-2.995993,56.465378],"type":"Point"}
}