{
  "type": "Feature",
  "properties": {
    "addr:full":"49 Bateman Rd, East Leake Loughborough Loughborough Leicestershire LE12 6NL",
    "addr:housenumber":"49",
    "addr:postcode":"le12 6nl",
    "addr:street":"Bateman Rd",
    "iso:country":"GB",
    "sg:address":"49 Bateman Rd, East Leake Loughborough",
    "sg:city":"Loughborough",
    "sg:classifiers":[
        {
            "category":"Professional",
            "subcategory":"Management & Consulting",
            "type":"Services"
        }
    ],
    "sg:phone":"+44 1509 820198",
    "sg:postcode":"LE12 6NL",
    "sg:province":"Leicestershire",
    "sg:tags":[
        "environmental",
        "consultant"
    ],
    "wof:name":"Arksafe",
    "wof:placetype":"venue"
},
  "geometry": {"coordinates":[-1.186462,52.83326],"type":"Point"}
}