{
  "type": "Feature",
  "properties": {
    "iso:country":"GB",
    "sg:address":"Thrupp House, Merrow Street, Merrow",
    "sg:city":"Guildford",
    "sg:classifiers":[
        {
            "category":"Social Services",
            "subcategory":"Retirement Home",
            "type":"Services"
        }
    ],
    "sg:postcode":"GU4 7DE",
    "sg:province":"Surrey",
    "sg:tags":[
        "rest"
    ],
    "wof:name":"Guildford Sunset Homes",
    "wof:placetype":"venue"
},
  "geometry": {"coordinates":[-0.529959,51.248631],"type":"Point"}
}