{
  "type": "Feature",
  "properties": {
    "iso:country":"GB",
    "sg:address":"Unit 28, Llantarnam Indstl Pk",
    "sg:city":"Cwmbran",
    "sg:classifiers":[
        {
            "category":"Manufacturing",
            "subcategory":"Metals",
            "type":"Manufacturing & Wholesale Goods"
        }
    ],
    "sg:postcode":"NP44 3AX",
    "sg:province":"Monmouthshire",
    "sg:tags":[
        "work",
        "sheet"
    ],
    "wof:name":"Randle,Lawrie,",
    "wof:placetype":"venue"
},
  "geometry": {"coordinates":[-3.0186889172,51.6454162598],"type":"Point"}
}