{
  "type": "Feature",
  "properties": {
    "iso:country":"GB",
    "sg:address":"38 Lower Herne Rd",
    "sg:city":"Herne Bay",
    "sg:classifiers":[
        {
            "category":"Travel",
            "subcategory":"Travel Agent",
            "type":"Entertainment"
        }
    ],
    "sg:phone":"+44 1227 366664",
    "sg:postcode":"CT6 7NA",
    "sg:province":"Kent",
    "wof:name":"Holiday Coach",
    "wof:placetype":"venue"
},
  "geometry": {"coordinates":[1.12917,51.353783],"type":"Point"}
}