{
  "type": "Feature",
  "properties": {
    "addr:full":"3 Falconwood Parade Welling Kent DA16 2PL",
    "addr:housenumber":"3",
    "addr:postcode":"da16 2pl",
    "addr:street":"Falconwood Parade Welling",
    "iso:country":"GB",
    "sg:address":"3 Falconwood Parade",
    "sg:city":"Welling",
    "sg:classifiers":[
        {
            "category":"Shopping",
            "subcategory":"Pharmacy",
            "type":"Retail Goods"
        }
    ],
    "sg:phone":"+44 20 8303 7064",
    "sg:postcode":"DA16 2PL",
    "sg:province":"Kent",
    "sg:tags":[
        "pharmacist",
        "chemist"
    ],
    "wof:name":"Jacaranda Pharmacy",
    "wof:placetype":"venue"
},
  "geometry": {"coordinates":[0.0947209969,51.4563293457],"type":"Point"}
}