{
  "type": "Feature",
  "properties": {
    "addr:full":"221 Deepdale Road Preston Lancashire PR1 6NY",
    "addr:housenumber":"221",
    "addr:postcode":"pr1 6ny",
    "addr:street":"Deepdale Road",
    "iso:country":"GB",
    "sg:address":"221 Deepdale Road",
    "sg:city":"Preston",
    "sg:classifiers":[
        {
            "category":"Education",
            "subcategory":"Special Training",
            "type":"Public Place"
        }
    ],
    "sg:phone":"+44 1772 253671",
    "sg:postcode":"PR1 6NY",
    "sg:province":"Lancashire",
    "sg:tags":[
        "product",
        "centre"
    ],
    "wof:name":"Preston Transport Holdings Ltd.",
    "wof:placetype":"venue"
},
  "geometry": {"coordinates":[-2.6910870075,53.7686386108],"type":"Point"}
}