{
  "type": "Feature",
  "properties": {
    "addr:full":"Schopwick Surgery, Romeland Borehamwood Hertfordshire WD6 3BJ",
    "addr:postcode":"wd6 3bj",
    "addr:street":"Romeland Borehamwood",
    "iso:country":"GB",
    "sg:address":"Schopwick Surgery, Romeland",
    "sg:city":"Borehamwood",
    "sg:classifiers":[
        {
            "category":"Health Services",
            "subcategory":"Doctor",
            "type":"Services"
        }
    ],
    "sg:phone":"+44 20 8953 1008",
    "sg:postcode":"WD6 3BJ",
    "sg:province":"Hertfordshire",
    "sg:tags":[
        "practitioners"
    ],
    "wof:name":"Small, N",
    "wof:placetype":"venue"
},
  "geometry": {"coordinates":[-0.2757540047,51.6558189392],"type":"Point"}
}