{
  "type": "Feature",
  "properties": {
    "addr:full":"136 North Road Hertford Hertfordshire SG14 2BZ",
    "addr:housenumber":"136",
    "addr:postcode":"sg14 2bz",
    "addr:street":"North Road",
    "iso:country":"GB",
    "sg:address":"136 North Road",
    "sg:city":"Hertford",
    "sg:classifiers":[
        {
            "category":"Real Estate",
            "subcategory":"Real Estate Agent",
            "type":"Services"
        }
    ],
    "sg:phone":"+44 1992 422178",
    "sg:postcode":"SG14 2BZ",
    "sg:province":"Hertfordshire",
    "wof:name":"Stephen Hurford Ltd",
    "wof:placetype":"venue"
},
  "geometry": {"coordinates":[-0.0945990011,51.80260849],"type":"Point"}
}