{
  "type": "Feature",
  "properties": {
    "addr:full":"83 Dairsie Road, Eltham London Greater London SE9 1XN",
    "addr:housenumber":"83",
    "addr:postcode":"se9 1xn",
    "addr:street":"Dairsie Road",
    "iso:country":"GB",
    "sg:address":"83 Dairsie Road, Eltham",
    "sg:city":"London",
    "sg:classifiers":[
        {
            "category":"Building & Trades",
            "subcategory":"Plumbing",
            "type":"Services"
        }
    ],
    "sg:postcode":"SE9 1XN",
    "sg:province":"Greater London",
    "sg:tags":[
        "drain",
        "clearance",
        "sewer"
    ],
    "wof:name":"C & R Plumbing Services",
    "wof:placetype":"venue"
},
  "geometry": {"coordinates":[0.061838001,51.4626083374],"type":"Point"}
}