{
  "type": "Feature",
  "properties": {
    "iso:country":"GB",
    "sg:address":"Gwendolen Rd",
    "sg:city":"Leicester",
    "sg:classifiers":[
        {
            "category":"Health Services",
            "subcategory":"Doctor",
            "type":"Services"
        }
    ],
    "sg:phone":"+44 116 258 8101",
    "sg:postcode":"LE5 4PW",
    "sg:province":"Leicestershire",
    "sg:tags":[
        "practitioners"
    ],
    "wof:name":"Allen, M J",
    "wof:placetype":"venue"
},
  "geometry": {"coordinates":[-1.0880160332,52.630569458],"type":"Point"}
}