{
  "type": "Feature",
  "properties": {
    "addr:full":"The Oaks, Brown Street, Old Newton Stowmarket Suffolk IP14 4QB",
    "addr:postcode":"ip14 4qb",
    "addr:street":"Brown Street",
    "iso:country":"GB",
    "sg:address":"The Oaks, Brown Street, Old Newton",
    "sg:city":"Stowmarket",
    "sg:classifiers":[
        {
            "category":"Professional",
            "subcategory":"Engineering",
            "type":"Services"
        }
    ],
    "sg:phone":"+44 1449 673421",
    "sg:postcode":"IP14 4QB",
    "sg:province":"Suffolk",
    "sg:tags":[
        "civil",
        "engineer"
    ],
    "wof:name":"Four Mills Construction Ltd",
    "wof:placetype":"venue"
},
  "geometry": {"coordinates":[0.999819,52.222794],"type":"Point"}
}