{
  "type": "Feature",
  "properties": {
    "iso:country":"GB",
    "sg:address":"1a Hazelwood Close",
    "sg:city":"Cambridge",
    "sg:classifiers":[
        {
            "category":"Shopping",
            "subcategory":"News",
            "type":"Retail Goods"
        }
    ],
    "sg:phone":"+44 1223 362756",
    "sg:postcode":"CB4 3SN",
    "sg:province":"Cambridgeshire",
    "sg:tags":[
        "newsagent"
    ],
    "wof:name":"Hazelwood General Stores",
    "wof:placetype":"venue"
},
  "geometry": {"coordinates":[0.112699,52.228771],"type":"Point"}
}