{
  "type": "Feature",
  "properties": {
    "addr:full":"43 Andrews Road, Cambridge Heath London Greater London E8 4RN",
    "addr:housenumber":"43",
    "addr:postcode":"e8 4rn",
    "addr:street":"Andrews Road",
    "iso:country":"GB",
    "sg:address":"43 Andrews Road, Cambridge Heath",
    "sg:city":"London",
    "sg:classifiers":[
        {
            "category":"Shopping",
            "subcategory":"Computers & Home Electronics",
            "type":"Retail Goods"
        },
        {
            "category":"Home & Garden",
            "subcategory":"Furniture",
            "type":"Retail Goods"
        }
    ],
    "sg:phone":"+44 20 7254 1262",
    "sg:postcode":"E8 4RN",
    "sg:province":"Greater London",
    "wof:name":"Cintique Ltd.",
    "wof:placetype":"venue"
},
  "geometry": {"coordinates":[-0.0577110015,51.5345726013],"type":"Point"}
}