{
  "type": "Feature",
  "properties": {
    "iso:country":"GB",
    "sg:address":"Park Road Industrial Estate",
    "sg:city":"Consett",
    "sg:classifiers":[
        {
            "category":"Autos & Motor Vehicles",
            "subcategory":"Automobile Sales",
            "type":"Retail Goods"
        }
    ],
    "sg:phone":"+44 1207 504755",
    "sg:postcode":"DH8 5PY",
    "sg:province":"Durham",
    "sg:tags":[
        "commercial"
    ],
    "wof:name":"T A & N White Ltd.",
    "wof:placetype":"venue"
},
  "geometry": {"coordinates":[-1.835914,54.860989],"type":"Point"}
}