{
  "type": "Feature",
  "properties": {
    "iso:country":"GB",
    "sg:address":"The Workshop, Bridge End",
    "sg:city":"Kendal",
    "sg:classifiers":[
        {
            "category":"Building & Trades",
            "subcategory":"Construction",
            "type":"Services"
        }
    ],
    "sg:postcode":"LA8 0NH",
    "sg:province":"Cumbria",
    "sg:tags":[
        "builder"
    ],
    "wof:name":"A Nelson & Son Ltd.",
    "wof:placetype":"venue"
},
  "geometry": {"coordinates":[-2.6702001095,54.2895584106],"type":"Point"}
}