{
  "type": "Feature",
  "properties": {
    "addr:full":"6 London Road, Purbrook Waterlooville Hampshire PO7 5LJ",
    "addr:housenumber":"6",
    "addr:postcode":"po7 5lj",
    "addr:street":"London Road",
    "iso:country":"GB",
    "sg:address":"6 London Road, Purbrook",
    "sg:city":"Waterlooville",
    "sg:classifiers":[
        {
            "category":"Autos & Motor Vehicles",
            "subcategory":"Motorcycle Sales",
            "type":"Retail Goods"
        }
    ],
    "sg:phone":"+44 23 9223 0746",
    "sg:postcode":"PO7 5LJ",
    "sg:province":"Hampshire",
    "sg:tags":[
        "scooter",
        "cycle"
    ],
    "wof:name":"Ray Dentith Motorcycles",
    "wof:placetype":"venue"
},
  "geometry": {"coordinates":[-1.045524,50.866302],"type":"Point"}
}