{
  "type": "Feature",
  "properties": {
    "addr:full":"Rothamsted Lodge, Hatching Green Harpenden Hertfordshire AL5 2JS",
    "addr:postcode":"al5 2js",
    "addr:street":"Hatching Green",
    "iso:country":"GB",
    "sg:address":"Rothamsted Lodge, Hatching Green",
    "sg:city":"Harpenden",
    "sg:classifiers":[
        {
            "category":"Farming",
            "subcategory":"Nursery",
            "type":"Manufacturing & Wholesale Goods"
        }
    ],
    "sg:phone":"+44 1582 462533",
    "sg:postcode":"AL5 2JS",
    "sg:province":"Hertfordshire",
    "sg:tags":[
        "creche"
    ],
    "wof:name":"Copperbeech Day Nursery",
    "wof:placetype":"venue"
},
  "geometry": {"coordinates":[-0.3565590084,51.8162155151],"type":"Point"}
}