{
  "type": "Feature",
  "properties": {
    "iso:country":"GB",
    "sg:address":"R C Comprehensive School, Patching Hall Lane",
    "sg:city":"Chelmsford",
    "sg:classifiers":[
        {
            "category":"Community Center",
            "type":"Public Place"
        }
    ],
    "sg:phone":"+44 1245 490559",
    "sg:postcode":"CM1 4DH",
    "sg:province":"Essex",
    "sg:tags":[
        "centre"
    ],
    "wof:name":"St John Payne Former Pupil Community Centre",
    "wof:placetype":"venue"
},
  "geometry": {"coordinates":[0.46742,51.750729],"type":"Point"}
}