{
  "type": "Feature",
  "properties": {
    "addr:full":"41-43 St Marys Gate, The Lace Market Nottingham Nottinghamshire NG1 1PU",
    "addr:housenumber":"41-43",
    "addr:postcode":"ng1 1pu",
    "addr:street":"St Marys Gate The",
    "iso:country":"GB",
    "sg:address":"41-43 St Marys Gate, The Lace Market",
    "sg:city":"Nottingham",
    "sg:classifiers":[
        {
            "category":"Bars & Pubs",
            "subcategory":"Nightclub",
            "type":"Food & Drink"
        }
    ],
    "sg:phone":"+44 115 952 3264",
    "sg:postcode":"NG1 1PU",
    "sg:province":"Nottinghamshire",
    "sg:tags":[
        "club",
        "night"
    ],
    "wof:name":"Lounge Lizard Ltd.",
    "wof:placetype":"venue"
},
  "geometry": {"coordinates":[-1.143925,52.951546],"type":"Point"}
}