{
  "type": "Feature",
  "properties": {
    "addr:full":"155 Roman Bank Skegness Lincolnshire PE25 1RY",
    "addr:housenumber":"155",
    "addr:postcode":"pe25 1ry",
    "addr:street":"Roman Bank",
    "iso:country":"GB",
    "sg:address":"155 Roman Bank",
    "sg:city":"Skegness",
    "sg:classifiers":[
        {
            "category":"Shopping",
            "subcategory":"Department Store",
            "type":"Retail Goods"
        },
        {
            "category":"Shopping",
            "subcategory":"Bicycles & Sporting Goods",
            "type":"Retail Goods"
        },
        {
            "category":"Recreation",
            "subcategory":"Fishing",
            "type":"Entertainment"
        }
    ],
    "sg:phone":"+44 1754 611172",
    "sg:postcode":"PE25 1RY",
    "sg:province":"Lincolnshire",
    "sg:tags":[
        "equipment",
        "angling"
    ],
    "wof:name":"Skegness Fishing Tackle",
    "wof:placetype":"venue"
},
  "geometry": {"coordinates":[0.3400300145,53.1506462097],"type":"Point"}
}