{
  "type": "Feature",
  "properties": {
    "iso:country":"GB",
    "sg:address":"80 Vivian Avenue",
    "sg:city":"London",
    "sg:classifiers":[
        {
            "category":"Health Services",
            "subcategory":"Dentist",
            "type":"Services"
        }
    ],
    "sg:phone":"+44 20 8202 9537",
    "sg:postcode":"NW4 3XG",
    "sg:province":"Greater London",
    "wof:name":"Peter Wagerman",
    "wof:placetype":"venue"
},
  "geometry": {"coordinates":[-0.2320329994,51.5824813843],"type":"Point"}
}