{
  "type": "Feature",
  "properties": {
    "iso:country":"GB",
    "sg:address":"80 Headstone Lane",
    "sg:city":"Harrow",
    "sg:classifiers":[
        {
            "category":"Building & Trades",
            "subcategory":"Construction",
            "type":"Services"
        }
    ],
    "sg:postcode":"HA2 6HW",
    "sg:province":"Greater London",
    "sg:tags":[
        "restoration",
        "refurbishment"
    ],
    "wof:name":"Rangeform Interiors Ltd.",
    "wof:placetype":"venue"
},
  "geometry": {"coordinates":[-0.361014,51.593685],"type":"Point"}
}