{
  "type": "Feature",
  "properties": {
    "iso:country":"GB",
    "sg:address":"1 Goods Way",
    "sg:city":"Camden",
    "sg:classifiers":[
        {
            "category":"Shopping",
            "subcategory":"Photographic Equipment",
            "type":"Retail Goods"
        }
    ],
    "sg:phone":"+44 20 7837 6443",
    "sg:postcode":"NW1 1UR",
    "sg:province":"Greater London",
    "wof:name":"Goodsway Studios",
    "wof:placetype":"venue"
},
  "geometry": {"coordinates":[-0.1260479987,51.5345115662],"type":"Point"}
}