{
  "type": "Feature",
  "properties": {
    "addr:full":"(studio & Resource), 50 St Stephens Road Leicester Leicestershire LE2 1GG",
    "addr:housenumber":"50",
    "addr:postcode":"le2 1gg",
    "addr:street":"St Stephens Road",
    "iso:country":"GB",
    "sg:address":"(studio & Resource), 50 St Stephens Road",
    "sg:city":"Leicester",
    "sg:classifiers":[
        {
            "category":"Arts & Performance",
            "subcategory":"Arts Center",
            "type":"Entertainment"
        }
    ],
    "sg:postcode":"LE2 1GG",
    "sg:province":"Leicestershire",
    "sg:tags":[
        "centre"
    ],
    "wof:name":"Leicester Print Workshop",
    "wof:placetype":"venue"
},
  "geometry": {"coordinates":[-1.113626,52.627216],"type":"Point"}
}