{
  "type": "Feature",
  "properties": {
    "addr:full":"Chapelside, 27 Hargham Rd Attleborough Norfolk NR17 2ES",
    "addr:housenumber":"27",
    "addr:postcode":"nr17 2es",
    "addr:street":"Chapelside;Hargham Rd",
    "iso:country":"GB",
    "sg:address":"Chapelside, 27 Hargham Rd",
    "sg:city":"Attleborough",
    "sg:classifiers":[
        {
            "category":"Building & Trades",
            "subcategory":"Construction",
            "type":"Services"
        }
    ],
    "sg:postcode":"NR17 2ES",
    "sg:province":"Norfolk",
    "sg:tags":[
        "builder"
    ],
    "wof:name":"Baker & Nisbet",
    "wof:placetype":"venue"
},
  "geometry": {"coordinates":[1.0144350529,52.5190544128],"type":"Point"}
}