{
  "type": "Feature",
  "properties": {
    "addr:full":"The Spinney Leeds West Yorkshire LS27 0QN",
    "addr:housenumber":"leeds",
    "addr:postcode":"ls27 0qn",
    "addr:street":"The Spinney",
    "iso:country":"GB",
    "sg:address":"The Spinney",
    "sg:city":"Leeds",
    "sg:classifiers":[
        {
            "category":"Autos & Motor Vehicles",
            "subcategory":"Auto Supplies",
            "type":"Retail Goods"
        },
        {
            "category":"Shopping",
            "type":"Retail Goods"
        }
    ],
    "sg:phone":"+44 113 252 2742",
    "sg:postcode":"LS27 0QN",
    "sg:province":"West Yorkshire",
    "sg:tags":[
        "car",
        "part",
        "accessory",
        "audio"
    ],
    "wof:name":"Motor World Ltd.",
    "wof:placetype":"venue"
},
  "geometry": {"coordinates":[-1.5244530439,53.7936286926],"type":"Point"}
}