{
  "type": "Feature",
  "properties": {
    "iso:country":"GB",
    "sg:address":"35 Rose St",
    "sg:city":"Dunfermline",
    "sg:classifiers":[
        {
            "category":"Professional",
            "subcategory":"Engineering",
            "type":"Services"
        }
    ],
    "sg:postcode":"KY12 0QT",
    "sg:province":"Fife",
    "sg:tags":[
        "contractor",
        "electrical",
        "engineer"
    ],
    "wof:name":"Duffy,Norman,",
    "wof:placetype":"venue"
},
  "geometry": {"coordinates":[-3.455997,56.076511],"type":"Point"}
}