{
  "type": "Feature",
  "properties": {
    "addr:full":"Peewit Park, Walton Avenue Felixstowe Suffolk IP11 2HB",
    "addr:postcode":"ip11 2hb",
    "addr:street":"Peewit Park Walton Avenue",
    "iso:country":"GB",
    "sg:address":"Peewit Park, Walton Avenue",
    "sg:city":"Felixstowe",
    "sg:classifiers":[
        {
            "category":"Recreation",
            "subcategory":"Campground",
            "type":"Entertainment"
        }
    ],
    "sg:phone":"+44 1394 284511",
    "sg:postcode":"IP11 2HB",
    "sg:province":"Suffolk",
    "sg:tags":[
        "caravan",
        "park"
    ],
    "wof:name":"Peewit Caravans Ltd.",
    "wof:placetype":"venue"
},
  "geometry": {"coordinates":[1.32822,51.959766],"type":"Point"}
}