{
  "type": "Feature",
  "properties": {
    "addr:full":"3 Grand Parade, Forty Avenue Wembley Greater London HA9 9JS",
    "addr:housenumber":"3",
    "addr:postcode":"ha9 9js",
    "addr:street":"Grand Parade Forty Avenue",
    "iso:country":"GB",
    "sg:address":"3 Grand Parade, Forty Avenue",
    "sg:city":"Wembley",
    "sg:classifiers":[
        {
            "category":"Food & Beverages",
            "subcategory":"Meat & Fish",
            "type":"Retail Goods"
        }
    ],
    "sg:phone":"+44 20 8904 3141",
    "sg:postcode":"HA9 9JS",
    "sg:province":"Greater London",
    "sg:tags":[
        "butcher"
    ],
    "wof:name":"Tariq Halal Butchers",
    "wof:placetype":"venue"
},
  "geometry": {"coordinates":[-0.278127,51.565529],"type":"Point"}
}