{
  "type": "Feature",
  "properties": {
    "addr:full":"Station Road Wilmslow Cheshire SK9 1BU",
    "addr:postcode":"sk9 1bu",
    "addr:street":"Station Road",
    "iso:country":"GB",
    "sg:address":"Station Road",
    "sg:city":"Wilmslow",
    "sg:classifiers":[
        {
            "category":"Autos & Motor Vehicles",
            "subcategory":"Auto Supplies",
            "type":"Retail Goods"
        }
    ],
    "sg:phone":"+44 1625 524477",
    "sg:postcode":"SK9 1BU",
    "sg:province":"Cheshire",
    "sg:tags":[
        "exhaust",
        "absorber",
        "shock"
    ],
    "wof:name":"Kwik-Fit",
    "wof:placetype":"venue"
},
  "geometry": {"coordinates":[-2.228954,53.327267],"type":"Point"}
}