{
  "type": "Feature",
  "properties": {
    "addr:full":"3 Tan Bank Newport Shropshire TF10 7LJ",
    "addr:housenumber":"3",
    "addr:postcode":"tf10 7lj",
    "addr:street":"Tan Bank",
    "iso:country":"GB",
    "sg:address":"3 Tan Bank",
    "sg:city":"Newport",
    "sg:classifiers":[
        {
            "category":"Autos & Motor Vehicles",
            "subcategory":"Auto Supplies",
            "type":"Retail Goods"
        }
    ],
    "sg:phone":"+44 1952 820257",
    "sg:postcode":"TF10 7LJ",
    "sg:province":"Shropshire",
    "sg:tags":[
        "tyre"
    ],
    "wof:name":"Newport Tyre Centre Ltd",
    "wof:placetype":"venue"
},
  "geometry": {"coordinates":[-2.3765239716,52.770690918],"type":"Point"}
}