{
  "type": "Feature",
  "properties": {
    "iso:country":"GB",
    "sg:address":"2 Broad Street",
    "sg:city":"Bristol",
    "sg:classifiers":[
        {
            "category":"Shopping",
            "subcategory":"Music",
            "type":"Retail Goods"
        }
    ],
    "sg:phone":"+44 117 914 7770",
    "sg:postcode":"BS16 5NX",
    "sg:province":"City of Bristol",
    "sg:tags":[
        "record",
        "tape",
        "cd"
    ],
    "wof:name":"Revolution",
    "wof:placetype":"venue"
},
  "geometry": {"coordinates":[-2.506682,51.481049],"type":"Point"}
}