{
  "type": "Feature",
  "properties": {
    "addr:full":"81-85 Talbot Street Nottingham Nottinghamshire NG1 5GN",
    "addr:housenumber":"81-85",
    "addr:postcode":"ng1 5gn",
    "addr:street":"Talbot Street",
    "iso:country":"GB",
    "sg:address":"81-85 Talbot Street",
    "sg:city":"Nottingham",
    "sg:classifiers":[
        {
            "category":"Autos & Motor Vehicles",
            "subcategory":"Automobile Sales",
            "type":"Retail Goods"
        }
    ],
    "sg:phone":"+44 115 959 8849",
    "sg:postcode":"NG1 5GN",
    "sg:province":"Nottinghamshire",
    "sg:tags":[
        "car"
    ],
    "wof:name":"Beechdale Motor Group Ltd.",
    "wof:placetype":"venue"
},
  "geometry": {"coordinates":[-1.15997,52.956139],"type":"Point"}
}