{
  "type": "Feature",
  "properties": {
    "iso:country":"GB",
    "sg:address":"222 Old Christchurch Road",
    "sg:city":"Bournemouth",
    "sg:classifiers":[
        {
            "category":"Banks & Credit Unions",
            "subcategory":"Bureau De Change",
            "type":"Services"
        }
    ],
    "sg:postcode":"BH1 1PE",
    "sg:province":"Dorset",
    "wof:name":"W & G (Finance Services) Ltd.",
    "wof:placetype":"venue"
},
  "geometry": {"coordinates":[-1.869818,50.722115],"type":"Point"}
}