{
  "type": "Feature",
  "properties": {
    "addr:full":"8 Park Road Sandy Bedfordshire SG19 1JB",
    "addr:housenumber":"8",
    "addr:postcode":"sg19 1jb",
    "addr:street":"Park Road",
    "iso:country":"GB",
    "sg:address":"8 Park Road",
    "sg:city":"Sandy",
    "sg:classifiers":[
        {
            "category":"Fast Food",
            "type":"Food & Drink"
        }
    ],
    "sg:phone":"+44 1767 692430",
    "sg:postcode":"SG19 1JB",
    "sg:province":"Bedfordshire",
    "sg:tags":[
        "away",
        "take"
    ],
    "wof:name":"Sandy Pizza & Kebab House",
    "wof:placetype":"venue"
},
  "geometry": {"coordinates":[-0.2881189883,52.1284713745],"type":"Point"}
}