{
  "type": "Feature",
  "properties": {
    "iso:country":"GB",
    "sg:address":"341 Griffiths Drive",
    "sg:city":"Wolverhampton",
    "sg:classifiers":[
        {
            "category":"Personal",
            "subcategory":"Beauty Salon",
            "type":"Services"
        }
    ],
    "sg:phone":"+44 1902 305660",
    "sg:postcode":"WV11 2LD",
    "sg:province":"Staffordshire",
    "sg:tags":[
        "unisex",
        "hairdresser"
    ],
    "wof:name":"Belle Hair",
    "wof:placetype":"venue"
},
  "geometry": {"coordinates":[-2.0549089909,52.6189956665],"type":"Point"}
}