{
  "type": "Feature",
  "properties": {
    "iso:country":"GB",
    "sg:address":"Unit 2b, Station Yard, Earby",
    "sg:city":"Barnoldswick",
    "sg:classifiers":[
        {
            "category":"Recreation",
            "subcategory":"Arcade",
            "type":"Entertainment"
        }
    ],
    "sg:phone":"+44 1282 841403",
    "sg:postcode":"BB18 6XD",
    "sg:province":"Lancashire",
    "sg:tags":[
        "machine",
        "amusement"
    ],
    "wof:name":"N T Leisure",
    "wof:placetype":"venue"
},
  "geometry": {"coordinates":[-2.146199,53.914486],"type":"Point"}
}