{
  "type": "Feature",
  "properties": {
    "iso:country":"GB",
    "sg:address":"Unit 9, Catherinefield Industrial Estate",
    "sg:city":"Dumfries",
    "sg:classifiers":[
        {
            "category":"Manufacturing",
            "subcategory":"Tools & Machinery",
            "type":"Manufacturing & Wholesale Goods"
        }
    ],
    "sg:postcode":"DG1 3PQ",
    "sg:province":"Dumfries and Galloway",
    "sg:tags":[
        "power"
    ],
    "wof:name":"Catherinefield Industrial Supplies Ltd.",
    "wof:placetype":"venue"
},
  "geometry": {"coordinates":[-3.563913,55.096409],"type":"Point"}
}