{
  "type": "Feature",
  "properties": {
    "iso:country":"GB",
    "sg:address":"2 West St",
    "sg:city":"Bradford",
    "sg:classifiers":[
        {
            "category":"Shopping",
            "subcategory":"Computers & Home Electronics",
            "type":"Retail Goods"
        }
    ],
    "sg:phone":"+44 1274 780400",
    "sg:postcode":"BD2 3BS",
    "sg:province":"West Yorkshire",
    "sg:tags":[
        "consumables"
    ],
    "wof:name":"Complete Office Supplies",
    "wof:placetype":"venue"
},
  "geometry": {"coordinates":[-1.7316479683,53.8148193359],"type":"Point"}
}