{
  "type": "Feature",
  "properties": {
    "addr:full":"80 The Pavilion Waltham Cross Essex EN8 7BZ",
    "addr:housenumber":"80",
    "addr:postcode":"en8 7bz",
    "addr:street":"Cross",
    "iso:country":"GB",
    "sg:address":"80 The Pavilion",
    "sg:city":"Waltham Cross",
    "sg:classifiers":[
        {
            "category":"Communications",
            "type":"Services"
        }
    ],
    "sg:postcode":"EN8 7BZ",
    "sg:province":"Essex",
    "sg:tags":[
        "tv",
        "video",
        "radio"
    ],
    "wof:name":"Sony Centre",
    "wof:placetype":"venue"
},
  "geometry": {"coordinates":[-0.0338140018,51.6905097961],"type":"Point"}
}