{
  "type": "Feature",
  "properties": {
    "addr:full":"33 West Park, Clifton Bristol City of Bristol BS8 2LX",
    "addr:housenumber":"33",
    "addr:postcode":"bs8 2lx",
    "addr:street":"West Park",
    "iso:country":"GB",
    "sg:address":"33 West Park, Clifton",
    "sg:city":"Bristol",
    "sg:classifiers":[
        {
            "category":"Building & Trades",
            "subcategory":"Construction",
            "type":"Services"
        }
    ],
    "sg:phone":"+44 117 973 4202",
    "sg:postcode":"BS8 2LX",
    "sg:province":"City of Bristol",
    "sg:tags":[
        "restoration",
        "refurbishment"
    ],
    "wof:name":"Clifton Renovations Ltd.",
    "wof:placetype":"venue"
},
  "geometry": {"coordinates":[-2.6487309933,51.4914970398],"type":"Point"}
}