{
  "type": "Feature",
  "properties": {
    "addr:full":"Long Street Road, Hanslope Milton Keynes Buckinghamshire MK19 7BL",
    "addr:postcode":"mk19 7bl",
    "addr:street":"Long Street Road",
    "iso:country":"GB",
    "sg:address":"Long Street Road, Hanslope",
    "sg:city":"Milton Keynes",
    "sg:classifiers":[
        {
            "category":"Education",
            "subcategory":"School",
            "type":"Public Place"
        }
    ],
    "sg:phone":"+44 1908 510245",
    "sg:postcode":"MK19 7BL",
    "sg:province":"Buckinghamshire",
    "sg:tags":[
        "local",
        "authority"
    ],
    "wof:name":"Hanslope Combined School",
    "wof:placetype":"venue"
},
  "geometry": {"coordinates":[-0.8341190219,52.1201057434],"type":"Point"}
}