{
  "type": "Feature",
  "properties": {
    "iso:country":"GB",
    "sg:address":"Unit 8 Acorn Park Indust Est",
    "sg:city":"Shipley",
    "sg:classifiers":[
        {
            "category":"Building & Trades",
            "subcategory":"Electrical",
            "type":"Services"
        }
    ],
    "sg:phone":"+44 1274 532910",
    "sg:postcode":"BD17 7SW",
    "sg:province":"West Yorkshire",
    "sg:tags":[
        "lighting"
    ],
    "wof:name":"Arma Electronics Ltd",
    "wof:placetype":"venue"
},
  "geometry": {"coordinates":[-1.7547069788,53.8442878723],"type":"Point"}
}