{
  "type": "Feature",
  "properties": {
    "addr:full":"Corpus Christi Priory Manchester Greater Manchester M40 8EE",
    "addr:postcode":"m40 8ee",
    "addr:street":"Priory",
    "iso:country":"GB",
    "sg:address":"Corpus Christi Priory",
    "sg:city":"Manchester",
    "sg:classifiers":[
        {
            "category":"Organizations",
            "subcategory":"Membership Organization",
            "type":"Services"
        }
    ],
    "sg:phone":"+44 161 205 1215",
    "sg:postcode":"M40 8EE",
    "sg:province":"Greater Manchester",
    "sg:tags":[
        "club"
    ],
    "wof:name":"Corpus Christi Parochial Centre",
    "wof:placetype":"venue"
},
  "geometry": {"coordinates":[-2.2115950584,53.4962158203],"type":"Point"}
}