{
  "type": "Feature",
  "properties": {
    "addr:full":"1 Delf Mews Cotts Sandwich Kent CT13 9DZ",
    "addr:housenumber":"1",
    "addr:postcode":"ct13 9dz",
    "addr:street":"Delf Mews;Sandwich",
    "iso:country":"GB",
    "sg:address":"1 Delf Mews Cotts",
    "sg:city":"Sandwich",
    "sg:classifiers":[
        {
            "category":"Wholesale",
            "subcategory":"Books, Periodicals, & Newspapers",
            "type":"Manufacturing & Wholesale Goods"
        }
    ],
    "sg:phone":"+44 1304 617398",
    "sg:postcode":"CT13 9DZ",
    "sg:province":"Kent",
    "sg:tags":[
        "publishing"
    ],
    "wof:name":"Saraton Ltd.",
    "wof:placetype":"venue"
},
  "geometry": {"coordinates":[1.342304,51.276169],"type":"Point"}
}