{
  "type": "Feature",
  "properties": {
    "iso:country":"GB",
    "sg:address":"102 High Street",
    "sg:city":"Chatham",
    "sg:classifiers":[
        {
            "category":"Arts & Performance",
            "subcategory":"Theater",
            "type":"Entertainment"
        }
    ],
    "sg:phone":"+44 1634 831028",
    "sg:postcode":"ME4 4BY",
    "sg:province":"Kent",
    "sg:tags":[
        "hall",
        "theatre",
        "concert"
    ],
    "wof:name":"The Theatre Royal Chatham Trust",
    "wof:placetype":"venue"
},
  "geometry": {"coordinates":[0.521188,51.383514],"type":"Point"}
}