{
  "type": "Feature",
  "properties": {
    "iso:country":"GB",
    "sg:address":"Unit 2 Drury Way Industrial Estate, Laxcon Close",
    "sg:city":"Willesden",
    "sg:classifiers":[
        {
            "category":"Building & Trades",
            "subcategory":"Construction",
            "type":"Services"
        }
    ],
    "sg:phone":"+44 20 8830 1964",
    "sg:postcode":"NW10 0TG",
    "sg:province":"Greater London",
    "sg:tags":[
        "builder"
    ],
    "wof:name":"Reed Cross Ltd",
    "wof:placetype":"venue"
},
  "geometry": {"coordinates":[-0.26246,51.555328],"type":"Point"}
}