{
  "type": "Feature",
  "properties": {
    "iso:country":"GB",
    "sg:address":"28 Wingfield Street",
    "sg:city":"Bungay",
    "sg:classifiers":[
        {
            "category":"Food & Beverages",
            "subcategory":"Meat & Fish",
            "type":"Retail Goods"
        }
    ],
    "sg:phone":"+44 1986 895105",
    "sg:postcode":"NR35 1EZ",
    "sg:province":"Norfolk",
    "sg:tags":[
        "butcher"
    ],
    "wof:name":"John Groom",
    "wof:placetype":"venue"
},
  "geometry": {"coordinates":[1.442321,52.453072],"type":"Point"}
}