{
  "type": "Feature",
  "properties": {
    "addr:full":"88 High Rd Wood Green Greater London N22 6HE",
    "addr:housenumber":"88",
    "addr:postcode":"n22 6he",
    "addr:street":"High Rd",
    "iso:country":"GB",
    "sg:address":"88 High Rd",
    "sg:city":"Wood Green",
    "sg:classifiers":[
        {
            "category":"Home & Garden",
            "subcategory":"Furniture",
            "type":"Retail Goods"
        }
    ],
    "sg:phone":"+44 20 8889 2620",
    "sg:postcode":"N22 6HE",
    "sg:province":"Greater London",
    "wof:name":"Shopper Direct",
    "wof:placetype":"venue"
},
  "geometry": {"coordinates":[-0.107691,51.593987],"type":"Point"}
}