{
  "type": "Feature",
  "properties": {
    "addr:full":"35 High St Crawley Surrey RH10 1BQ",
    "addr:housenumber":"35",
    "addr:postcode":"rh10 1bq",
    "addr:street":"High St",
    "iso:country":"GB",
    "sg:address":"35 High St",
    "sg:city":"Crawley",
    "sg:classifiers":[
        {
            "category":"Banks & Credit Unions",
            "subcategory":"Financial Services",
            "type":"Services"
        }
    ],
    "sg:phone":"+44 1293 417964",
    "sg:postcode":"RH10 1BQ",
    "sg:province":"Surrey",
    "sg:tags":[
        "adviser"
    ],
    "wof:name":"Mortgage Matters",
    "wof:placetype":"venue"
},
  "geometry": {"coordinates":[-0.190259,51.113979],"type":"Point"}
}