{
  "type": "Feature",
  "properties": {
    "addr:full":"44 Wordsworth Place, Dutchels Copse Horsham West Sussex RH12 5PS",
    "addr:housenumber":"44",
    "addr:postcode":"rh12 5ps",
    "addr:street":"Wordsworth Place Dutchels Copse",
    "iso:country":"GB",
    "sg:address":"44 Wordsworth Place, Dutchels Copse",
    "sg:city":"Horsham",
    "sg:classifiers":[
        {
            "category":"Building & Trades",
            "subcategory":"Plumbing",
            "type":"Services"
        }
    ],
    "sg:phone":"+44 1403 269228",
    "sg:postcode":"RH12 5PS",
    "sg:province":"West Sussex",
    "sg:tags":[
        "heating"
    ],
    "wof:name":"Holbrook Heating & Plumbing",
    "wof:placetype":"venue"
},
  "geometry": {"coordinates":[-0.312218,51.085472],"type":"Point"}
}