{
  "type": "Feature",
  "properties": {
    "addr:full":"4 Carisbrooke Dr Worthing West Sussex BN13 3QT",
    "addr:housenumber":"4",
    "addr:postcode":"bn13 3qt",
    "addr:street":"Carisbrooke Dr",
    "iso:country":"GB",
    "sg:address":"4 Carisbrooke Dr",
    "sg:city":"Worthing",
    "sg:classifiers":[
        {
            "category":"Building & Trades",
            "subcategory":"Construction",
            "type":"Services"
        }
    ],
    "sg:postcode":"BN13 3QT",
    "sg:province":"West Sussex",
    "sg:tags":[
        "builder"
    ],
    "wof:name":"Waters,Robert,",
    "wof:placetype":"venue"
},
  "geometry": {"coordinates":[-0.429191,50.826801],"type":"Point"}
}