{
  "type": "Feature",
  "properties": {
    "addr:full":"5 Keil Croft Oban Argyll and Bute PA37 1QS",
    "addr:housenumber":"5",
    "addr:postcode":"pa37 1qs",
    "addr:street":"Keil Croft",
    "iso:country":"GB",
    "sg:address":"5 Keil Croft",
    "sg:city":"Oban",
    "sg:classifiers":[
        {
            "category":"Restaurant",
            "type":"Food & Drink"
        }
    ],
    "sg:postcode":"PA37 1QS",
    "sg:province":"Argyll and Bute",
    "wof:name":"Hawthorn Cottage Restaurant",
    "wof:placetype":"venue"
},
  "geometry": {"coordinates":[-5.41399,56.49897],"type":"Point"}
}