{
  "type": "Feature",
  "properties": {
    "addr:full":"100 North Hill Street Liverpool Merseyside L8 8AG",
    "addr:housenumber":"100",
    "addr:postcode":"l8 8ag",
    "addr:street":"North Hill Street",
    "iso:country":"GB",
    "sg:address":"100 North Hill Street",
    "sg:city":"Liverpool",
    "sg:classifiers":[
        {
            "category":"Food & Beverages",
            "subcategory":"Supermarket",
            "type":"Retail Goods"
        }
    ],
    "sg:postcode":"L8 8AG",
    "sg:province":"Merseyside",
    "wof:name":"Sue Food & Wine",
    "wof:placetype":"venue"
},
  "geometry": {"coordinates":[-2.9638199806,53.3888931274],"type":"Point"}
}