{
  "type": "Feature",
  "properties": {
    "addr:full":"Unit 12 Easton Business Centre, Felix Road Bristol City of Bristol BS5 0HE",
    "addr:housenumber":"unit 12",
    "addr:postcode":"bs5 0he",
    "addr:street":"Easton Business Centre Felix Road",
    "iso:country":"GB",
    "sg:address":"Unit 12 Easton Business Centre, Felix Road",
    "sg:city":"Bristol",
    "sg:classifiers":[
        {
            "category":"Utilities",
            "subcategory":"Telephone",
            "type":"Services"
        }
    ],
    "sg:href":"http://api.simplegeo.com/1.0/features/SG_7CQ15IXkXAYwYTnJGpM3yW_51.478825_-2.691964@1300740015.json",
    "sg:phone":"+44 117 941 5816",
    "sg:postcode":"BS5 0HE",
    "sg:province":"City of Bristol",
    "sg:tags":[
        "radio"
    ],
    "wof:name":"Contact Communication Services",
    "wof:placetype":"venue"
},
  "geometry": {"coordinates":[-2.691964,51.478825],"type":"Point"}
}