{"geometry":{"type":"Point","coordinates":[-2.691964,51.478825]},"type":"Feature","id":102560213,"bbox":[-2.691964,51.478825,-2.691964,51.478825],"properties":{"sg:province":"City of Bristol","sg:tags":["radio"],"geom:longitude":-2.691964,"wof:breaches":[],"sg:href":"http://api.simplegeo.com/1.0/features/SG_7CQ15IXkXAYwYTnJGpM3yW_51.478825_-2.691964@1300740015.json","sg:owner":"simplegeo","sg:postcode":"BS5 0HE","geom:latitude":51.478825,"sg:classifiers":[{"category":"Utilities","type":"Services","subcategory":"Telephone"}],"sg:address":"Unit 12 Easton Business Centre, Felix Road","sg:phone":"+44 117 941 5816","wof:hierarchy":[{"venue_id":102560213,"country_id":85633159,"neighbourhood_id":85789823,"region_id":85683793}],"geom:area":0.000000,"sg:city":"Bristol","wof:lastmodified":1438093213,"iso:country":"GB","wof:geomhash":"916c693a9074a8c89761b29e73fef002","wof:name":"Contact Communication Services","wof:belongsto":[85633159,85789823,85683793],"src:geom":"simplegeo","wof:placetype":"venue","wof:supersedes":[],"wof:id":102560213,"wof:superseded_by":[],"wof:concordances":{"sg:id":"SG_7CQ15IXkXAYwYTnJGpM3yW_51.478825_-2.691964@1300740015"},"wof:parent_id":85789823}}