{
  "type": "Feature",
  "properties": {
    "iso:country":"GB",
    "sg:address":"19 Marshall Avenue",
    "sg:city":"Bridlington",
    "sg:classifiers":[
        {
            "category":"Travel",
            "subcategory":"Hotels & Motels",
            "type":"Entertainment"
        }
    ],
    "sg:phone":"+44 1262 674270",
    "sg:postcode":"YO15 2DT",
    "sg:province":"East Riding of Yorkshire",
    "sg:tags":[
        "house",
        "guest"
    ],
    "wof:name":"St.Albans Guest House",
    "wof:placetype":"venue"
},
  "geometry": {"coordinates":[-0.191197,54.083145],"type":"Point"}
}