{
  "type": "Feature",
  "properties": {
    "addr:full":"32 High Road, Orsett Grays Essex RM16 3HB",
    "addr:housenumber":"32",
    "addr:postcode":"rm16 3hb",
    "addr:street":"High Road",
    "iso:country":"GB",
    "sg:address":"32 High Road, Orsett",
    "sg:city":"Grays",
    "sg:classifiers":[
        {
            "category":"Retail",
            "subcategory":"Funeral Services",
            "type":"Services"
        }
    ],
    "sg:phone":"+44 1375 891238",
    "sg:postcode":"RM16 3HB",
    "sg:province":"Essex",
    "wof:name":"W Howard & Son",
    "wof:placetype":"venue"
},
  "geometry": {"coordinates":[0.365756005,51.5123786926],"type":"Point"}
}