{
  "type": "Feature",
  "properties": {
    "addr:full":"151 Petersgate, Scawthorpe Doncaster South Yorkshire DN5 9JW",
    "addr:housenumber":"151",
    "addr:postcode":"dn5 9jw",
    "addr:street":"Petersgate Scawthorpe",
    "iso:country":"GB",
    "sg:address":"151 Petersgate, Scawthorpe",
    "sg:city":"Doncaster",
    "sg:classifiers":[
        {
            "category":"Food & Beverages",
            "subcategory":"Supermarket",
            "type":"Retail Goods"
        }
    ],
    "sg:phone":"+44 1302 780661",
    "sg:postcode":"DN5 9JW",
    "sg:province":"South Yorkshire",
    "wof:name":"Spar",
    "wof:placetype":"venue"
},
  "geometry": {"coordinates":[-1.169149,53.549221],"type":"Point"}
}