{
  "type": "Feature",
  "properties": {
    "addr:full":"30 Norton Terrace Newhaven East Sussex BN9 0BT",
    "addr:housenumber":"30",
    "addr:postcode":"bn9 0bt",
    "addr:street":"Norton Terrace",
    "iso:country":"GB",
    "sg:address":"30 Norton Terrace",
    "sg:city":"Newhaven",
    "sg:classifiers":[
        {
            "category":"Health Services",
            "subcategory":"Health Practitioner",
            "type":"Services"
        }
    ],
    "sg:phone":"+44 1273 513107",
    "sg:postcode":"BN9 0BT",
    "sg:province":"East Sussex",
    "sg:tags":[
        "homoeopathic"
    ],
    "wof:name":"Stuart Deeks",
    "wof:placetype":"venue"
},
  "geometry": {"coordinates":[0.0567030013,50.7920646667],"type":"Point"}
}