{
  "type": "Feature",
  "properties": {
    "addr:full":"71 Alma Road Southport Lancashire PR8 4BL",
    "addr:housenumber":"71",
    "addr:postcode":"pr8 4bl",
    "addr:street":"Alma Road",
    "iso:country":"GB",
    "sg:address":"71 Alma Road",
    "sg:city":"Southport",
    "sg:classifiers":[
        {
            "category":"Home & Garden",
            "subcategory":"Household Appliances",
            "type":"Retail Goods"
        }
    ],
    "sg:postcode":"PR8 4BL",
    "sg:province":"Lancashire",
    "sg:tags":[
        "cleaner",
        "domestic",
        "vacuum"
    ],
    "wof:name":"Steven Rimmer",
    "wof:placetype":"venue"
},
  "geometry": {"coordinates":[-3.012938,53.63406],"type":"Point"}
}