{
  "type": "Feature",
  "properties": {
    "iso:country":"GB",
    "sg:address":"5 Selsdon Way",
    "sg:city":"London",
    "sg:classifiers":[
        {
            "category":"Professional",
            "subcategory":"Advertising",
            "type":"Services"
        }
    ],
    "sg:phone":"+44 20 7510 5900",
    "sg:postcode":"E14 9GL",
    "sg:province":"Greater London",
    "sg:tags":[
        "agency"
    ],
    "wof:name":"Ellison Communications Ltd.",
    "wof:placetype":"venue"
},
  "geometry": {"coordinates":[-0.015143,51.495491],"type":"Point"}
}