{
  "type": "Feature",
  "properties": {
    "iso:country":"GB",
    "sg:address":"1 Graham St",
    "sg:city":"Southampton",
    "sg:classifiers":[
        {
            "category":"Fast Food",
            "type":"Food & Drink"
        }
    ],
    "sg:phone":"+44 23 8022 0808",
    "sg:postcode":"SO14 5RY",
    "sg:province":"Hampshire",
    "sg:tags":[
        "away",
        "take"
    ],
    "wof:name":"Shanghai Take-Away",
    "wof:placetype":"venue"
},
  "geometry": {"coordinates":[-1.393966,50.911682],"type":"Point"}
}