{
  "type": "Feature",
  "properties": {
    "addr:full":"57 Ridgeway Lane, Warsop Mansfield Derbyshire NG20 0LJ",
    "addr:housenumber":"57",
    "addr:postcode":"ng20 0lj",
    "addr:street":"Ridgeway Lane",
    "iso:country":"GB",
    "sg:address":"57 Ridgeway Lane, Warsop",
    "sg:city":"Mansfield",
    "sg:classifiers":[
        {
            "category":"Professional",
            "subcategory":"Art Services",
            "type":"Services"
        }
    ],
    "sg:postcode":"NG20 0LJ",
    "sg:province":"Derbyshire",
    "sg:tags":[
        "graphic",
        "designer"
    ],
    "wof:name":"Src Designs",
    "wof:placetype":"venue"
},
  "geometry": {"coordinates":[-1.1521480083,53.1993865967],"type":"Point"}
}