{
  "type": "Feature",
  "properties": {
    "addr:full":"44 Castlemaine Avenue South Croydon Surrey CR2 7HR",
    "addr:housenumber":"44",
    "addr:postcode":"cr2 7hr",
    "addr:street":"Castlemaine Avenue",
    "iso:country":"GB",
    "sg:address":"44 Castlemaine Avenue",
    "sg:city":"South Croydon",
    "sg:classifiers":[
        {
            "category":"Education",
            "subcategory":"School",
            "type":"Public Place"
        }
    ],
    "sg:postcode":"CR2 7HR",
    "sg:province":"Surrey",
    "sg:tags":[
        "private",
        "tuition"
    ],
    "wof:name":"Hawkins Chemistry Tuition",
    "wof:placetype":"venue"
},
  "geometry": {"coordinates":[-0.080003,51.362946],"type":"Point"}
}