{
  "type": "Feature",
  "properties": {
    "iso:country":"GB",
    "sg:address":"94 Chatsworth Rd",
    "sg:city":"Clapton",
    "sg:classifiers":[
        {
            "category":"Food & Beverages",
            "subcategory":"Bakery",
            "type":"Retail Goods"
        }
    ],
    "sg:phone":"+44 20 8985 1336",
    "sg:postcode":"E5 0LS",
    "sg:province":"Greater London",
    "sg:tags":[
        "baker"
    ],
    "wof:name":"Chatsworth Bakery",
    "wof:placetype":"venue"
},
  "geometry": {"coordinates":[-0.0451700017,51.5545578003],"type":"Point"}
}