{
  "type": "Feature",
  "properties": {
    "addr:full":"Unit 2, The Old Foundry, Market St, Shipdham Thetford Norfolk IP25 7LY",
    "addr:housenumber":"unit 2",
    "addr:postcode":"ip25 7ly",
    "addr:street":"The Old;Market St",
    "iso:country":"GB",
    "sg:address":"Unit 2, The Old Foundry, Market St, Shipdham",
    "sg:city":"Thetford",
    "sg:classifiers":[
        {
            "category":"Retail",
            "subcategory":"Auto Repair",
            "type":"Services"
        }
    ],
    "sg:postcode":"IP25 7LY",
    "sg:province":"Norfolk",
    "sg:tags":[
        "modification",
        "garage"
    ],
    "wof:name":"Greaves,Eric Russell,",
    "wof:placetype":"venue"
},
  "geometry": {"coordinates":[0.897466,52.62994],"type":"Point"}
}