{
  "type": "Feature",
  "properties": {
    "addr:full":"21 Euston Road Great Yarmouth Norfolk NR30 1DZ",
    "addr:housenumber":"21",
    "addr:postcode":"nr30 1dz",
    "addr:street":"Euston Road",
    "iso:country":"GB",
    "sg:address":"21 Euston Road",
    "sg:city":"Great Yarmouth",
    "sg:classifiers":[
        {
            "category":"Organizations",
            "subcategory":"Community Association",
            "type":"Services"
        },
        {
            "category":"Organizations",
            "subcategory":"Membership Organization",
            "type":"Services"
        }
    ],
    "sg:phone":"+44 1493 843509",
    "sg:postcode":"NR30 1DZ",
    "sg:province":"Norfolk",
    "sg:tags":[
        "club",
        "social"
    ],
    "wof:name":"ST CLOUD LABOUR CLUB",
    "wof:placetype":"venue"
},
  "geometry": {"coordinates":[1.7364549637,52.6101417542],"type":"Point"}
}