{
  "type": "Feature",
  "properties": {
    "addr:full":"Westhay, Charmouth Bridport Dorset DT6 6SD",
    "addr:housenumber":"charmouth",
    "addr:postcode":"dt6 6sd",
    "iso:country":"GB",
    "sg:address":"Westhay, Charmouth",
    "sg:city":"Bridport",
    "sg:classifiers":[
        {
            "category":"Professional",
            "subcategory":"Management & Consulting",
            "type":"Services"
        }
    ],
    "sg:phone":"+44 1297 560037",
    "sg:postcode":"DT6 6SD",
    "sg:province":"Dorset",
    "sg:tags":[
        "marketing",
        "consultant"
    ],
    "wof:name":"Publishers Direct",
    "wof:placetype":"venue"
},
  "geometry": {"coordinates":[-2.9032599926,50.7386207581],"type":"Point"}
}