{
  "type": "Feature",
  "properties": {
    "addr:full":"15 Clover Park Haverfordwest Pembrokeshire SA61 1UE",
    "addr:housenumber":"15",
    "addr:postcode":"sa61 1ue",
    "addr:street":"Clover Park",
    "iso:country":"GB",
    "sg:address":"15 Clover Park",
    "sg:city":"Haverfordwest",
    "sg:classifiers":[
        {
            "category":"Home & Garden",
            "subcategory":"Household Appliances",
            "type":"Retail Goods"
        }
    ],
    "sg:phone":"+44 1437 760932",
    "sg:postcode":"SA61 1UE",
    "sg:province":"Pembrokeshire",
    "sg:tags":[
        "electrical"
    ],
    "wof:name":"Don Stephens",
    "wof:placetype":"venue"
},
  "geometry": {"coordinates":[-4.9531011581,51.800945282],"type":"Point"}
}