{
  "type": "Feature",
  "properties": {
    "addr:full":"Wira House, Ring Road Leeds West Yorkshire LS16 6EB",
    "addr:postcode":"ls16 6eb",
    "addr:street":"Ring Road",
    "iso:country":"GB",
    "sg:address":"Wira House, Ring Road",
    "sg:city":"Leeds",
    "sg:classifiers":[
        {
            "category":"Real Estate",
            "subcategory":"Surveying",
            "type":"Services"
        }
    ],
    "sg:phone":"+44 113 275 4101",
    "sg:postcode":"LS16 6EB",
    "sg:province":"West Yorkshire",
    "sg:tags":[
        "building",
        "surveyor"
    ],
    "wof:name":"Summers (Project Management) Ltd.",
    "wof:placetype":"venue"
},
  "geometry": {"coordinates":[-1.6104309559,53.8381958008],"type":"Point"}
}