{
  "type": "Feature",
  "properties": {
    "iso:country":"GB",
    "sg:address":"East Lodge Woodlands Park, Woodlands Lane Stoke D'abernon",
    "sg:city":"Cobham",
    "sg:classifiers":[
        {
            "category":"Professional",
            "subcategory":"Art Services",
            "type":"Services"
        }
    ],
    "sg:postcode":"KT11 3PZ",
    "sg:province":"Surrey",
    "sg:tags":[
        "graphic",
        "designer"
    ],
    "wof:name":"A Carroll & J Bloor",
    "wof:placetype":"venue"
},
  "geometry": {"coordinates":[-0.3572100103,51.3153686523],"type":"Point"}
}