{
  "type": "Feature",
  "properties": {
    "addr:full":"36-37 Phoenix Road Washington Durham NE38 0AD",
    "addr:housenumber":"36-37",
    "addr:postcode":"ne38 0ad",
    "addr:street":"Phoenix Road",
    "iso:country":"GB",
    "sg:address":"36-37 Phoenix Road",
    "sg:city":"Washington",
    "sg:classifiers":[
        {
            "category":"Professional",
            "subcategory":"Art Services",
            "type":"Services"
        }
    ],
    "sg:postcode":"NE38 0AD",
    "sg:province":"Durham",
    "sg:tags":[
        "picture",
        "restoration",
        "framing"
    ],
    "wof:name":"Premier Crafts",
    "wof:placetype":"venue"
},
  "geometry": {"coordinates":[-1.5556750298,54.9038658142],"type":"Point"}
}