{
  "type": "Feature",
  "properties": {
    "iso:country":"GB",
    "sg:address":"Mains Of Doune Farm, King Street",
    "sg:city":"Doune",
    "sg:classifiers":[
        {
            "category":"Farming",
            "subcategory":"Farm",
            "type":"Manufacturing & Wholesale Goods"
        }
    ],
    "sg:postcode":"FK16 6DN",
    "sg:province":"Stirling",
    "sg:tags":[
        "mixed",
        "crop"
    ],
    "wof:name":"D R Morrison",
    "wof:placetype":"venue"
},
  "geometry": {"coordinates":[-4.0532431602,56.1901168823],"type":"Point"}
}