{
  "type": "Feature",
  "properties": {
    "addr:full":"22 The Parade Margate Kent CT9 1EX",
    "addr:housenumber":"22",
    "addr:postcode":"ct9 1ex",
    "addr:street":"The Parade Margate",
    "iso:country":"GB",
    "sg:address":"22 The Parade",
    "sg:city":"Margate",
    "sg:classifiers":[
        {
            "category":"Shopping",
            "subcategory":"Hobbies, Toys, & Games",
            "type":"Retail Goods"
        }
    ],
    "sg:phone":"+44 1843 221100",
    "sg:postcode":"CT9 1EX",
    "sg:province":"Kent",
    "sg:tags":[
        "shop",
        "toy"
    ],
    "wof:name":"Relax",
    "wof:placetype":"venue"
},
  "geometry": {"coordinates":[1.380341,51.389545],"type":"Point"}
}