{
  "type": "Feature",
  "properties": {
    "iso:country":"GB",
    "sg:address":"43 Cambridge Street, Godmanchester",
    "sg:city":"Huntingdon",
    "sg:classifiers":[
        {
            "category":"Professional",
            "subcategory":"Engineering",
            "type":"Services"
        }
    ],
    "sg:phone":"+44 1480 52341",
    "sg:postcode":"PE29 2AY",
    "sg:province":"Cambridgeshire",
    "sg:tags":[
        "contractor",
        "electrical",
        "engineer"
    ],
    "wof:name":"Ian Stuart Munro",
    "wof:placetype":"venue"
},
  "geometry": {"coordinates":[-0.1718029976,52.3188400269],"type":"Point"}
}