{
  "type": "Feature",
  "properties": {
    "iso:country":"GB",
    "sg:address":"Heathley Farm, Drayton Bassett",
    "sg:city":"Tamworth",
    "sg:classifiers":[
        {
            "category":"Home & Garden",
            "subcategory":"Garden Supply",
            "type":"Retail Goods"
        },
        {
            "category":"Farming",
            "subcategory":"Livestock Farm",
            "type":"Manufacturing & Wholesale Goods"
        }
    ],
    "sg:phone":"+44 1827 289540",
    "sg:postcode":"B78 3TT",
    "sg:province":"Staffordshire",
    "sg:tags":[
        "bulb",
        "grower",
        "others"
    ],
    "wof:name":"William L Lockhart",
    "wof:placetype":"venue"
},
  "geometry": {"coordinates":[-1.719596,52.598198],"type":"Point"}
}