{
  "type": "Feature",
  "properties": {
    "iso:country":"GB",
    "sg:address":"Glebe Avenue",
    "sg:city":"Braintree",
    "sg:classifiers":[
        {
            "category":"Government",
            "subcategory":"City Hall",
            "type":"Public Place"
        }
    ],
    "sg:phone":"+44 1376 320029",
    "sg:postcode":"CM7 5RB",
    "sg:province":"Essex",
    "wof:name":"Glebe Hall",
    "wof:placetype":"venue"
},
  "geometry": {"coordinates":[0.549505,51.896175],"type":"Point"}
}