{
  "type": "Feature",
  "properties": {
    "addr:full":"110 Burton Road Derby Derbyshire DE1 1TG",
    "addr:housenumber":"110",
    "addr:postcode":"de1 1tg",
    "addr:street":"Burton Road",
    "iso:country":"GB",
    "sg:address":"110 Burton Road",
    "sg:city":"Derby",
    "sg:classifiers":[
        {
            "category":"Shopping",
            "subcategory":"Thrift Store",
            "type":"Retail Goods"
        },
        {
            "category":"Organizations",
            "subcategory":"Non-profit Organization",
            "type":"Services"
        }
    ],
    "sg:phone":"+44 1332 364444",
    "sg:postcode":"DE1 1TG",
    "sg:province":"Derbyshire",
    "sg:tags":[
        "shop",
        "organisation",
        "voluntary",
        "charity"
    ],
    "wof:name":"The Samaritans",
    "wof:placetype":"venue"
},
  "geometry": {"coordinates":[-1.480514,52.915947],"type":"Point"}
}