{
  "type": "Feature",
  "properties": {
    "iso:country":"GB",
    "sg:address":"High Street, Shrivenham",
    "sg:city":"Swindon",
    "sg:classifiers":[
        {
            "category":"Bars & Pubs",
            "type":"Food & Drink"
        }
    ],
    "sg:phone":"+44 1793 782225",
    "sg:postcode":"SN6 8AN",
    "sg:province":"Gloucestershire",
    "sg:tags":[
        "pubs",
        "inn"
    ],
    "wof:name":"The Barrington Arms",
    "wof:placetype":"venue"
},
  "geometry": {"coordinates":[-1.659094,51.598389],"type":"Point"}
}