{
  "type": "Feature",
  "properties": {
    "iso:country":"GB",
    "sg:address":"2a Westmoreland Street",
    "sg:city":"Skipton",
    "sg:classifiers":[
        {
            "category":"Government",
            "subcategory":"Post Office",
            "type":"Public Place"
        }
    ],
    "sg:phone":"+44 1756 799591",
    "sg:postcode":"BD23 2EA",
    "sg:province":"Lancashire",
    "wof:name":"Middle Town Post Office",
    "wof:placetype":"venue"
},
  "geometry": {"coordinates":[-2.014109,53.957497],"type":"Point"}
}