{
  "type": "Feature",
  "properties": {
    "addr:full":"Cedar House, 14 The Parade Camberley Hampshire GU16 7HY",
    "addr:housenumber":"14",
    "addr:postcode":"gu16 7hy",
    "addr:street":"The Parade",
    "iso:country":"GB",
    "sg:address":"Cedar House, 14 The Parade",
    "sg:city":"Camberley",
    "sg:classifiers":[
        {
            "category":"Professional",
            "subcategory":"Engineering",
            "type":"Services"
        }
    ],
    "sg:postcode":"GU16 7HY",
    "sg:province":"Hampshire",
    "sg:tags":[
        "consulting",
        "engineer"
    ],
    "wof:name":"M Horwell",
    "wof:placetype":"venue"
},
  "geometry": {"coordinates":[-0.7457219958,51.3136863708],"type":"Point"}
}