{
  "type": "Feature",
  "properties": {
    "addr:full":"Foxden, Drift Rd, Wallington Fareham Hampshire PO16 8SY",
    "addr:postcode":"po16 8sy",
    "addr:street":"Foxden Drift Rd",
    "iso:country":"GB",
    "sg:address":"Foxden, Drift Rd, Wallington",
    "sg:city":"Fareham",
    "sg:classifiers":[
        {
            "category":"Building & Trades",
            "subcategory":"Construction",
            "type":"Services"
        }
    ],
    "sg:postcode":"PO16 8SY",
    "sg:province":"Hampshire",
    "sg:tags":[
        "builder"
    ],
    "wof:name":"Classic Construction Ltd",
    "wof:placetype":"venue"
},
  "geometry": {"coordinates":[-1.16958,50.857922],"type":"Point"}
}