{
  "type": "Feature",
  "properties": {
    "addr:full":"6 Meneage Street Helston Cornwall TR13 8AB",
    "addr:housenumber":"6",
    "addr:postcode":"tr13 8ab",
    "addr:street":"Meneage Street",
    "iso:country":"GB",
    "sg:address":"6 Meneage Street",
    "sg:city":"Helston",
    "sg:classifiers":[
        {
            "category":"Food & Beverages",
            "subcategory":"Bakery",
            "type":"Retail Goods"
        }
    ],
    "sg:phone":"+44 1326 564341",
    "sg:postcode":"TR13 8AB",
    "sg:province":"Cornwall",
    "sg:tags":[
        "baker"
    ],
    "wof:name":"W T Warren & Son (Hayle) Ltd.",
    "wof:placetype":"venue"
},
  "geometry": {"coordinates":[-5.2683749199,50.0955581665],"type":"Point"}
}