{
  "type": "Feature",
  "properties": {
    "addr:full":"8 Brooksville Avenue London Greater London NW6 6TG",
    "addr:housenumber":"8",
    "addr:postcode":"nw6 6tg",
    "addr:street":"Brooksville Avenue",
    "iso:country":"GB",
    "sg:address":"8 Brooksville Avenue",
    "sg:city":"London",
    "sg:classifiers":[
        {
            "category":"Shopping",
            "subcategory":"Antiques",
            "type":"Retail Goods"
        }
    ],
    "sg:postcode":"NW6 6TG",
    "sg:province":"Greater London",
    "wof:name":"Ian Christie",
    "wof:placetype":"venue"
},
  "geometry": {"coordinates":[-0.207969,51.53796],"type":"Point"}
}