{
  "type": "Feature",
  "properties": {
    "addr:full":"20 Lansdowne Place Bradford West Yorkshire BD5 0BN",
    "addr:housenumber":"20",
    "addr:postcode":"bd5 0bn",
    "addr:street":"Lansdowne Place Bradford West",
    "iso:country":"GB",
    "sg:address":"20 Lansdowne Place",
    "sg:city":"Bradford",
    "sg:classifiers":[
        {
            "category":"Food & Beverages",
            "subcategory":"Meat & Fish",
            "type":"Retail Goods"
        }
    ],
    "sg:phone":"+44 1274 724976",
    "sg:postcode":"BD5 0BN",
    "sg:province":"West Yorkshire",
    "sg:tags":[
        "butcher"
    ],
    "wof:name":"MOHAMMED YUNIS",
    "wof:placetype":"venue"
},
  "geometry": {"coordinates":[-1.7611370087,53.789390564],"type":"Point"}
}