{
  "type": "Feature",
  "properties": {
    "addr:full":"Unit 46 Nutwood Trading Estate, Limestone Cottage Lane Sheffield South Yorkshire S6 1NJ",
    "addr:housenumber":"unit 46",
    "addr:postcode":"s6 1nj",
    "addr:street":"Nutwood Trading Estate Limestone Cottage Lane",
    "iso:country":"GB",
    "sg:address":"Unit 46 Nutwood Trading Estate, Limestone Cottage Lane",
    "sg:city":"Sheffield",
    "sg:classifiers":[
        {
            "category":"Retail",
            "subcategory":"Repair Shop",
            "type":"Services"
        }
    ],
    "sg:phone":"+44 114 285 4625",
    "sg:postcode":"S6 1NJ",
    "sg:province":"South Yorkshire",
    "sg:tags":[
        "maintenance"
    ],
    "wof:name":"Ddh Building & Maintenance Services Ltd.",
    "wof:placetype":"venue"
},
  "geometry": {"coordinates":[-1.50896,53.422401],"type":"Point"}
}