{
  "type": "Feature",
  "properties": {
    "iso:country":"GB",
    "sg:address":"3rd Floor, Dukes Keep Marsh Lane",
    "sg:city":"Southampton",
    "sg:classifiers":[
        {
            "category":"Government",
            "subcategory":"Court House",
            "type":"Public Place"
        }
    ],
    "sg:phone":"+44 23 8063 9555",
    "sg:postcode":"SO14 3EX",
    "sg:province":"Hampshire",
    "wof:name":"The Industrial Tribunals",
    "wof:placetype":"venue"
},
  "geometry": {"coordinates":[-1.39644,50.900341],"type":"Point"}
}