{
  "type": "Feature",
  "properties": {
    "iso:country":"GB",
    "sg:address":"Selby Road",
    "sg:city":"Goole",
    "sg:classifiers":[
        {
            "category":"Manufacturing",
            "subcategory":"Food",
            "type":"Manufacturing & Wholesale Goods"
        }
    ],
    "sg:phone":"+44 1977 661202",
    "sg:postcode":"DN14 0LH",
    "sg:province":"East Riding of Yorkshire",
    "sg:tags":[
        "miller",
        "mill"
    ],
    "wof:name":"Bowmans",
    "wof:placetype":"venue"
},
  "geometry": {"coordinates":[-1.153809,53.701935],"type":"Point"}
}