{
  "type": "Feature",
  "properties": {
    "addr:full":"203 Kilburn High Rd Kilburn Greater London NW6 7HY",
    "addr:housenumber":"203",
    "addr:postcode":"nw6 7hy",
    "addr:street":"Kilburn High Rd",
    "iso:country":"GB",
    "sg:address":"203 Kilburn High Rd",
    "sg:city":"Kilburn",
    "sg:classifiers":[
        {
            "category":"Professional",
            "subcategory":"Accounting & Tax Preparation",
            "type":"Services"
        }
    ],
    "sg:phone":"+44 20 7624 6623",
    "sg:postcode":"NW6 7HY",
    "sg:province":"Greater London",
    "sg:tags":[
        "accountant"
    ],
    "wof:name":"TKG Agencies Ltd",
    "wof:placetype":"venue"
},
  "geometry": {"coordinates":[-0.197922,51.541733],"type":"Point"}
}