{
  "type": "Feature",
  "properties": {
    "iso:country":"GB",
    "sg:address":"1-11 Huddersfield Road",
    "sg:city":"Barnsley",
    "sg:classifiers":[
        {
            "category":"Professional",
            "subcategory":"Lawyer & Legal Services",
            "type":"Services"
        }
    ],
    "sg:phone":"+44 1226 210000",
    "sg:postcode":"S70 2LP",
    "sg:province":"South Yorkshire",
    "sg:tags":[
        "solicitor"
    ],
    "sg:website":"http://www.mkbrown.co.uk",
    "wof:name":"Mills Kemp & Brown",
    "wof:placetype":"venue"
},
  "geometry": {"coordinates":[-1.4835809469,53.5571861267],"type":"Point"}
}