{
  "type": "Feature",
  "properties": {
    "addr:full":"Eastgate, Scotland Gate Choppington Northumberland NE62 5RR",
    "addr:postcode":"ne62 5rr",
    "addr:street":"Eastgate Scotland Gate;Northumberland",
    "iso:country":"GB",
    "sg:address":"Eastgate, Scotland Gate",
    "sg:city":"Choppington",
    "sg:classifiers":[
        {
            "category":"Farming",
            "subcategory":"Nursery",
            "type":"Manufacturing & Wholesale Goods"
        },
        {
            "category":"Education",
            "subcategory":"School",
            "type":"Public Place"
        },
        {
            "category":"Government",
            "subcategory":"Office",
            "type":"Public Place"
        }
    ],
    "sg:phone":"+44 1670 822718",
    "sg:postcode":"NE62 5RR",
    "sg:province":"Northumberland",
    "sg:tags":[
        "creche",
        "local",
        "authority"
    ],
    "wof:name":"Choppington First School Nursery",
    "wof:placetype":"venue"
},
  "geometry": {"coordinates":[-1.600085,55.146175],"type":"Point"}
}