{
  "type": "Feature",
  "properties": {
    "addr:full":"The Birches, Raskelf Road, Helperby York North Yorkshire YO61 2RF",
    "addr:postcode":"yo61 2rf",
    "addr:street":"Raskelf Road",
    "iso:country":"GB",
    "sg:address":"The Birches, Raskelf Road, Helperby",
    "sg:city":"York",
    "sg:classifiers":[
        {
            "category":"Building & Trades",
            "subcategory":"Equipment Rental",
            "type":"Services"
        }
    ],
    "sg:phone":"+44 1423 360636",
    "sg:postcode":"YO61 2RF",
    "sg:province":"North Yorkshire",
    "sg:tags":[
        "plant",
        "machinery"
    ],
    "wof:name":"Peacock Plant Hire",
    "wof:placetype":"venue"
},
  "geometry": {"coordinates":[-1.329149,54.122784],"type":"Point"}
}