{
  "type": "Feature",
  "properties": {
    "addr:full":"Flat 418 Holmefield House, Hazlewood Crescent London Greater London W10 5FS",
    "addr:housenumber":"flat 418",
    "addr:postcode":"w10 5fs",
    "addr:street":"Hazlewood Crescent",
    "iso:country":"GB",
    "sg:address":"Flat 418 Holmefield House, Hazlewood Crescent",
    "sg:city":"London",
    "sg:classifiers":[
        {
            "category":"Organizations",
            "subcategory":"Non-profit Organization",
            "type":"Services"
        },
        {
            "category":"Professional",
            "subcategory":"Computer Services",
            "type":"Services"
        }
    ],
    "sg:phone":"+44 20 8964 0606",
    "sg:postcode":"W10 5FS",
    "sg:province":"Greater London",
    "sg:tags":[
        "consultant",
        "organisation",
        "charity",
        "charitable"
    ],
    "wof:name":"BARAKA USED ASSOCIATION",
    "wof:placetype":"venue"
},
  "geometry": {"coordinates":[-0.2069900036,51.5250816345],"type":"Point"}
}