{
  "type": "Feature",
  "properties": {
    "iso:country":"GB",
    "sg:address":"4 Loughbrow Park",
    "sg:city":"Hexham",
    "sg:classifiers":[
        {
            "category":"Building & Trades",
            "subcategory":"Cleaning & Sanitation",
            "type":"Services"
        }
    ],
    "sg:phone":"+44 1434 600012",
    "sg:postcode":"NE46 2QD",
    "sg:province":"Northumberland",
    "sg:tags":[
        "commercial"
    ],
    "wof:name":"Dublcheck",
    "wof:placetype":"venue"
},
  "geometry": {"coordinates":[-2.0979249477,54.961025238],"type":"Point"}
}