{
  "type": "Feature",
  "properties": {
    "addr:full":"17 Belgrave Ind Est, Belgrave Rd Southampton Hampshire SO17 3EA",
    "addr:housenumber":"17",
    "addr:postcode":"so17 3ea",
    "addr:street":"Belgrave Ind Est Belgrave Rd",
    "iso:country":"GB",
    "sg:address":"17 Belgrave Ind Est, Belgrave Rd",
    "sg:city":"Southampton",
    "sg:classifiers":[
        {
            "category":"Manufacturing",
            "subcategory":"Metals",
            "type":"Manufacturing & Wholesale Goods"
        }
    ],
    "sg:phone":"+44 23 8055 4760",
    "sg:postcode":"SO17 3EA",
    "sg:province":"Hampshire",
    "wof:name":"Woodside Metal Polishing",
    "wof:placetype":"venue"
},
  "geometry": {"coordinates":[-1.38389,50.931],"type":"Point"}
}