{
  "type": "Feature",
  "properties": {
    "addr:full":"Hoe Hall Dereham Norfolk NR20 4BD",
    "addr:postcode":"nr20 4bd",
    "addr:street":"Dereham",
    "iso:country":"GB",
    "sg:address":"Hoe Hall",
    "sg:city":"Dereham",
    "sg:classifiers":[
        {
            "category":"Farming",
            "subcategory":"Livestock Farm",
            "type":"Manufacturing & Wholesale Goods"
        }
    ],
    "sg:phone":"+44 1362 693172",
    "sg:postcode":"NR20 4BD",
    "sg:province":"Norfolk",
    "sg:tags":[
        "others"
    ],
    "wof:name":"Swanton Morley Farms Ltd.",
    "wof:placetype":"venue"
},
  "geometry": {"coordinates":[0.947579,52.724937],"type":"Point"}
}