{
  "type": "Feature",
  "properties": {
    "iso:country":"GB",
    "sg:address":"13-15 Victoria Street, Church",
    "sg:city":"Accrington",
    "sg:classifiers":[
        {
            "category":"Food & Beverages",
            "subcategory":"Liquor & Beverages",
            "type":"Retail Goods"
        }
    ],
    "sg:phone":"+44 1254 237989",
    "sg:postcode":"BB5 4LB",
    "sg:province":"Lancashire",
    "sg:tags":[
        "beer",
        "wine",
        "spirit",
        "wines"
    ],
    "wof:name":"Barry & Gails",
    "wof:placetype":"venue"
},
  "geometry": {"coordinates":[-2.3896729946,53.7550125122],"type":"Point"}
}