{
  "type": "Feature",
  "properties": {
    "addr:full":"Reedyford Road Nelson Lancashire BB9 8ST",
    "addr:postcode":"bb9 8st",
    "addr:street":"Reedyford Road",
    "iso:country":"GB",
    "sg:address":"Reedyford Road",
    "sg:city":"Nelson",
    "sg:classifiers":[
        {
            "category":"Education",
            "subcategory":"School",
            "type":"Public Place"
        }
    ],
    "sg:postcode":"BB9 8ST",
    "sg:province":"Lancashire",
    "sg:tags":[
        "local",
        "authority"
    ],
    "wof:name":"Holy Saviour R C Primary School",
    "wof:placetype":"venue"
},
  "geometry": {"coordinates":[-2.206139,53.842628],"type":"Point"}
}