{
  "type": "Feature",
  "properties": {
    "addr:full":"191 Swanston St Glasgow Glasgow City G40 4HG",
    "addr:housenumber":"191",
    "addr:postcode":"g40 4hg",
    "addr:street":"Swanston St",
    "iso:country":"GB",
    "sg:address":"191 Swanston St",
    "sg:city":"Glasgow",
    "sg:classifiers":[
        {
            "category":"Recreation",
            "subcategory":"Amusement Park",
            "type":"Entertainment"
        }
    ],
    "sg:phone":"+44 141 554 0941",
    "sg:postcode":"G40 4HG",
    "sg:province":"Glasgow City",
    "sg:tags":[
        "arcade"
    ],
    "wof:name":"Childrens Corner The",
    "wof:placetype":"venue"
},
  "geometry": {"coordinates":[-4.2185811996,55.8403396606],"type":"Point"}
}