{
  "type": "Feature",
  "properties": {
    "addr:full":"64 Oxford Road, Denham Uxbridge Buckinghamshire UB9 4DN",
    "addr:housenumber":"64",
    "addr:postcode":"ub9 4dn",
    "addr:street":"Oxford Road",
    "iso:country":"GB",
    "sg:address":"64 Oxford Road, Denham",
    "sg:city":"Uxbridge",
    "sg:classifiers":[
        {
            "category":"Shopping",
            "subcategory":"Computers & Home Electronics",
            "type":"Retail Goods"
        }
    ],
    "sg:postcode":"UB9 4DN",
    "sg:province":"Buckinghamshire",
    "sg:tags":[
        "equipment",
        "audio-visual"
    ],
    "wof:name":"Location Technical Facilities Ltd.",
    "wof:placetype":"venue"
},
  "geometry": {"coordinates":[-0.4890730083,51.5544319153],"type":"Point"}
}