{
  "type": "Feature",
  "properties": {
    "addr:full":"Carew Road, Hendra Truro Cornwall TR1 3TP",
    "addr:postcode":"tr1 3tp",
    "addr:street":"Carew Road",
    "iso:country":"GB",
    "sg:address":"Carew Road, Hendra",
    "sg:city":"Truro",
    "sg:classifiers":[
        {
            "category":"Government",
            "subcategory":"Office",
            "type":"Public Place"
        },
        {
            "category":"Arena",
            "subcategory":"Sports Club",
            "type":"Entertainment"
        }
    ],
    "sg:phone":"+44 1872 278992",
    "sg:postcode":"TR1 3TP",
    "sg:province":"Cornwall",
    "sg:tags":[
        "local"
    ],
    "wof:name":"Carrick Sports & Recreational Centre",
    "wof:placetype":"venue"
},
  "geometry": {"coordinates":[-5.059247,50.265724],"type":"Point"}
}