{
  "type": "Feature",
  "properties": {
    "addr:full":"Graphic House, 38-40 Warwick Street London Greater London W1B 5JT",
    "addr:housenumber":"38-40",
    "addr:postcode":"w1b 5jt",
    "addr:street":"Warwick Street",
    "iso:country":"GB",
    "sg:address":"Graphic House, 38-40 Warwick Street",
    "sg:city":"London",
    "sg:classifiers":[
        {
            "category":"Shopping",
            "subcategory":"Crafts & Fabrics",
            "type":"Retail Goods"
        }
    ],
    "sg:phone":"+44 20 7437 9945",
    "sg:postcode":"W1B 5JT",
    "sg:province":"Greater London",
    "sg:tags":[
        "material",
        "graphic",
        "art"
    ],
    "wof:name":"Langford & Hill Ltd.",
    "wof:placetype":"venue"
},
  "geometry": {"coordinates":[-0.05759,51.56588],"type":"Point"}
}