{
  "type": "Feature",
  "properties": {
    "addr:full":"95 Horsefair, Broadmead Bristol City of Bristol BS1 3JR",
    "addr:housenumber":"95",
    "addr:postcode":"bs1 3jr",
    "addr:street":"Horsefair",
    "iso:country":"GB",
    "sg:address":"95 Horsefair, Broadmead",
    "sg:city":"Bristol",
    "sg:classifiers":[
        {
            "category":"Banks & Credit Unions",
            "subcategory":"Financial Services",
            "type":"Services"
        }
    ],
    "sg:phone":"+44 117 929 0295",
    "sg:postcode":"BS1 3JR",
    "sg:province":"City of Bristol",
    "sg:tags":[
        "building",
        "society"
    ],
    "wof:name":"Birmingham Midshires Building Society",
    "wof:placetype":"venue"
},
  "geometry": {"coordinates":[-2.591056,51.456985],"type":"Point"}
}