{
  "type": "Feature",
  "properties": {
    "addr:full":"115 Heatherstone Av Southampton Hampshire SO45 4LD",
    "addr:housenumber":"115",
    "addr:postcode":"so45 4ld",
    "addr:street":"Heatherstone Av",
    "iso:country":"GB",
    "sg:address":"115 Heatherstone Av",
    "sg:city":"Southampton",
    "sg:classifiers":[
        {
            "category":"Organizations",
            "subcategory":"Political Organization",
            "type":"Services"
        }
    ],
    "sg:phone":"+44 23 8084 7307",
    "sg:postcode":"SO45 4LD",
    "sg:province":"Hampshire",
    "sg:tags":[
        "party"
    ],
    "wof:name":"Newforest East Liberal Democrats",
    "wof:placetype":"venue"
},
  "geometry": {"coordinates":[-1.410557,50.849953],"type":"Point"}
}