{
  "type": "Feature",
  "properties": {
    "addr:full":"Unit 5 Church Lane, Thorngumbald Hull East Riding of Yorkshire HU12 9PD",
    "addr:housenumber":"unit 5",
    "addr:postcode":"hu12 9pd",
    "addr:street":"Church Lane",
    "iso:country":"GB",
    "sg:address":"Unit 5 Church Lane, Thorngumbald",
    "sg:city":"Hull",
    "sg:classifiers":[
        {
            "category":"Food & Beverages",
            "subcategory":"Supermarket",
            "type":"Retail Goods"
        }
    ],
    "sg:phone":"+44 1964 623640",
    "sg:postcode":"HU12 9PD",
    "sg:province":"East Riding of Yorkshire",
    "wof:name":"Tates Ltd.",
    "wof:placetype":"venue"
},
  "geometry": {"coordinates":[-0.139202,53.734516],"type":"Point"}
}