{
  "type": "Feature",
  "properties": {
    "addr:full":"Grove House, Stitchcombe Marlborough Berkshire SN8 2NG",
    "addr:postcode":"sn8 2ng",
    "addr:street":"Stitchcombe",
    "iso:country":"GB",
    "sg:address":"Grove House, Stitchcombe",
    "sg:city":"Marlborough",
    "sg:classifiers":[
        {
            "category":"Shopping",
            "subcategory":"Department Store",
            "type":"Retail Goods"
        }
    ],
    "sg:postcode":"SN8 2NG",
    "sg:province":"Berkshire",
    "wof:name":"Rebecca Dawes",
    "wof:placetype":"venue"
},
  "geometry": {"coordinates":[-1.673589,51.422363],"type":"Point"}
}