{
  "type": "Feature",
  "properties": {
    "addr:full":"Marksview Bus Cent, Oxford Rd, Pen Mill Trading Est Yeovil Somerset BA21 5HZ",
    "addr:postcode":"ba21 5hz",
    "addr:street":"Oxford Rd",
    "iso:country":"GB",
    "sg:address":"Marksview Bus Cent, Oxford Rd, Pen Mill Trading Est",
    "sg:city":"Yeovil",
    "sg:classifiers":[
        {
            "category":"Home & Garden",
            "subcategory":"Carpets & Floor Coverings",
            "type":"Retail Goods"
        }
    ],
    "sg:phone":"+44 1935 411108",
    "sg:postcode":"BA21 5HZ",
    "sg:province":"Somerset",
    "sg:tags":[
        "textile",
        "floorcoverings"
    ],
    "wof:name":"Mike Roberts",
    "wof:placetype":"venue"
},
  "geometry": {"coordinates":[-2.6047289371,50.9528503418],"type":"Point"}
}