{
  "type": "Feature",
  "properties": {
    "addr:full":"Unit 1, Surrey Cl Weymouth Dorset DT4 9TY",
    "addr:housenumber":"unit 1",
    "addr:postcode":"dt4 9ty",
    "iso:country":"GB",
    "sg:address":"Unit 1, Surrey Cl",
    "sg:city":"Weymouth",
    "sg:classifiers":[
        {
            "category":"Professional",
            "subcategory":"Engineering",
            "type":"Services"
        }
    ],
    "sg:phone":"+44 1305 780125",
    "sg:postcode":"DT4 9TY",
    "sg:province":"Dorset",
    "wof:name":"M G Model Products",
    "wof:placetype":"venue"
},
  "geometry": {"coordinates":[-2.486862,50.616959],"type":"Point"}
}