{
  "type": "Feature",
  "properties": {
    "addr:full":"1 Elm Cottage, The Street Basingstoke Hampshire RG25 1BN",
    "addr:housenumber":"1",
    "addr:postcode":"rg25 1bn",
    "addr:street":"The Street",
    "iso:country":"GB",
    "sg:address":"1 Elm Cottage, The Street",
    "sg:city":"Basingstoke",
    "sg:classifiers":[
        {
            "category":"Building & Trades",
            "subcategory":"Construction",
            "type":"Services"
        }
    ],
    "sg:postcode":"RG25 1BN",
    "sg:province":"Hampshire",
    "sg:tags":[
        "builder"
    ],
    "wof:name":"Tom R J Keens",
    "wof:placetype":"venue"
},
  "geometry": {"coordinates":[-1.08309,51.26244],"type":"Point"}
}