{
  "type": "Feature",
  "properties": {
    "addr:full":"122 High Street Staines Berkshire TW18 4BY",
    "addr:housenumber":"122",
    "addr:postcode":"tw18 4by",
    "addr:street":"High Street",
    "iso:country":"GB",
    "sg:address":"122 High Street",
    "sg:city":"Staines",
    "sg:classifiers":[
        {
            "category":"Professional",
            "subcategory":"Business Services",
            "type":"Services"
        }
    ],
    "sg:phone":"+44 1784 466592",
    "sg:postcode":"TW18 4BY",
    "sg:province":"Berkshire",
    "sg:tags":[
        "import",
        "export",
        "agent"
    ],
    "wof:name":"Pets Paradise",
    "wof:placetype":"venue"
},
  "geometry": {"coordinates":[-0.5078709722,51.4352035522],"type":"Point"}
}