{
  "type": "Feature",
  "properties": {
    "addr:full":"Paddock Hill Lane, Mobberley Knutsford Cheshire WA16 7DE",
    "addr:postcode":"wa16 7de",
    "addr:street":"Paddock Hill Lane",
    "iso:country":"GB",
    "sg:address":"Paddock Hill Lane, Mobberley",
    "sg:city":"Knutsford",
    "sg:classifiers":[
        {
            "category":"Restaurant",
            "type":"Food & Drink"
        }
    ],
    "sg:phone":"+44 1565 873537",
    "sg:postcode":"WA16 7DE",
    "sg:province":"Cheshire",
    "wof:name":"The Plough & Flail",
    "wof:placetype":"venue"
},
  "geometry": {"coordinates":[-2.2896289825,53.3134613037],"type":"Point"}
}