{
  "type": "Feature",
  "properties": {
    "addr:full":"352 Kings Park Avenue Glasgow Glasgow City G73 2AL",
    "addr:housenumber":"352",
    "addr:postcode":"g73 2al",
    "addr:street":"Kings Park Avenue",
    "iso:country":"GB",
    "sg:address":"352 Kings Park Avenue",
    "sg:city":"Glasgow",
    "sg:classifiers":[
        {
            "category":"Fast Food",
            "type":"Food & Drink"
        }
    ],
    "sg:phone":"+44 141 643 0806",
    "sg:postcode":"G73 2AL",
    "sg:province":"Glasgow City",
    "sg:tags":[
        "away",
        "take"
    ],
    "wof:name":"Silver Dragon",
    "wof:placetype":"venue"
},
  "geometry": {"coordinates":[-4.2264828682,55.8186569214],"type":"Point"}
}