{
  "type": "Feature",
  "properties": {
    "addr:full":"University Of Hull, University House Hull East Riding of Yorkshire HU6 7RX",
    "addr:postcode":"hu6 7rx",
    "iso:country":"GB",
    "sg:address":"University Of Hull, University House",
    "sg:city":"Hull",
    "sg:classifiers":[
        {
            "category":"Shopping",
            "subcategory":"Books",
            "type":"Retail Goods"
        }
    ],
    "sg:phone":"+44 1482 444190",
    "sg:postcode":"HU6 7RX",
    "sg:province":"East Riding of Yorkshire",
    "sg:tags":[
        "bookseller"
    ],
    "wof:name":"Waterstones Booksellers",
    "wof:placetype":"venue"
},
  "geometry": {"coordinates":[-0.37013,53.76746],"type":"Point"}
}