{
  "type": "Feature",
  "properties": {
    "addr:full":"79 Bury New Rd, Whitefield Manchester Lancashire M45 7EG",
    "addr:housenumber":"79",
    "addr:postcode":"m45 7eg",
    "addr:street":"Bury New Rd",
    "iso:country":"GB",
    "sg:address":"79 Bury New Rd, Whitefield",
    "sg:city":"Manchester",
    "sg:classifiers":[
        {
            "category":"Shopping",
            "subcategory":"Computers & Home Electronics",
            "type":"Retail Goods"
        }
    ],
    "sg:phone":"+44 161 834 7066",
    "sg:postcode":"M45 7EG",
    "sg:province":"Lancashire",
    "sg:tags":[
        "electrical"
    ],
    "wof:name":"S.T.C Ltd",
    "wof:placetype":"venue"
},
  "geometry": {"coordinates":[-2.2906,53.542366],"type":"Point"}
}