{
  "type": "Feature",
  "properties": {
    "iso:country":"GB",
    "sg:address":"151 Belgrave Road",
    "sg:city":"Stoke-on-trent",
    "sg:classifiers":[
        {
            "category":"Personal",
            "subcategory":"Beauty Salon",
            "type":"Services"
        }
    ],
    "sg:phone":"+44 1782 312504",
    "sg:postcode":"ST3 4NL",
    "sg:province":"Staffordshire",
    "sg:tags":[
        "unisex",
        "hairdresser"
    ],
    "wof:name":"Belgrave Salon",
    "wof:placetype":"venue"
},
  "geometry": {"coordinates":[-2.130066,52.97847],"type":"Point"}
}