{
  "type": "Feature",
  "properties": {
    "iso:country":"GB",
    "sg:address":"1 Park Road, Narborough",
    "sg:city":"Leicester",
    "sg:classifiers":[
        {
            "category":"Taxi",
            "type":"Transportation"
        },
        {
            "category":"Military Area",
            "subcategory":"Air Force Base",
            "type":"Public Place"
        }
    ],
    "sg:phone":"+44 116 284 8444",
    "sg:postcode":"LE19 2GQ",
    "sg:province":"Leicestershire",
    "sg:tags":[
        "hire",
        "private",
        "vehicle"
    ],
    "wof:name":"Narborough Taxis",
    "wof:placetype":"venue"
},
  "geometry": {"coordinates":[-1.20815,52.571533],"type":"Point"}
}