{
  "type": "Feature",
  "properties": {
    "iso:country":"GB",
    "sg:address":"57 Commercial Road",
    "sg:city":"Newport",
    "sg:classifiers":[
        {
            "category":"Food & Beverages",
            "subcategory":"Meat & Fish",
            "type":"Retail Goods"
        }
    ],
    "sg:phone":"+44 1633 262250",
    "sg:postcode":"NP20 2PF",
    "sg:province":"Newport",
    "sg:tags":[
        "butcher"
    ],
    "wof:name":"Keith Yendle",
    "wof:placetype":"venue"
},
  "geometry": {"coordinates":[-2.989564,51.578876],"type":"Point"}
}