{
  "type": "Feature",
  "properties": {
    "iso:country":"GB",
    "sg:address":"45 Stirling Rd",
    "sg:city":"Alloa",
    "sg:classifiers":[
        {
            "category":"Manufacturing",
            "subcategory":"Petroleum Products",
            "type":"Manufacturing & Wholesale Goods"
        }
    ],
    "sg:phone":"+44 1259 213838",
    "sg:postcode":"FK10 2QD",
    "sg:province":"Clackmannanshire",
    "sg:tags":[
        "double",
        "glazing"
    ],
    "wof:name":"Bilson Window Co",
    "wof:placetype":"venue"
},
  "geometry": {"coordinates":[-3.838756,56.135277],"type":"Point"}
}