{
  "type": "Feature",
  "properties": {
    "addr:full":"147a Paper Mill Lane, Bramford Ipswich Suffolk IP8 4BY",
    "addr:housenumber":"147a",
    "addr:postcode":"ip8 4by",
    "addr:street":"Paper Mill Lane",
    "iso:country":"GB",
    "sg:address":"147a Paper Mill Lane, Bramford",
    "sg:city":"Ipswich",
    "sg:classifiers":[
        {
            "category":"Building & Trades",
            "subcategory":"Construction",
            "type":"Services"
        }
    ],
    "sg:postcode":"IP8 4BY",
    "sg:province":"Suffolk",
    "sg:tags":[
        "builder"
    ],
    "wof:name":"Emhart Construction Services Ltd",
    "wof:placetype":"venue"
},
  "geometry": {"coordinates":[1.1027040482,52.0925636292],"type":"Point"}
}