{
  "type": "Feature",
  "properties": {
    "addr:full":"490 Bearwood Road Smethwick West Midlands B66 4HB",
    "addr:housenumber":"490",
    "addr:postcode":"b66 4hb",
    "addr:street":"Bearwood Road",
    "iso:country":"GB",
    "sg:address":"490 Bearwood Road",
    "sg:city":"Smethwick",
    "sg:classifiers":[
        {
            "category":"Home & Garden",
            "subcategory":"Hardware",
            "type":"Retail Goods"
        }
    ],
    "sg:phone":"+44 121 420 1230",
    "sg:postcode":"B66 4HB",
    "sg:province":"West Midlands",
    "sg:tags":[
        "merchant",
        "ironmonger"
    ],
    "wof:name":"Bearwood Hardware",
    "wof:placetype":"venue"
},
  "geometry": {"coordinates":[-1.9696229696,52.4767456055],"type":"Point"}
}