{
  "type": "Feature",
  "properties": {
    "iso:country":"GB",
    "sg:address":"6 Waterside, 44-48 Wharf Road",
    "sg:city":"London",
    "sg:classifiers":[
        {
            "category":"Manufacturing",
            "subcategory":"Wood Products",
            "type":"Manufacturing & Wholesale Goods"
        }
    ],
    "sg:postcode":"N1 7UX",
    "sg:province":"Greater London",
    "sg:tags":[
        "maker",
        "cabinet"
    ],
    "wof:name":"Groves Furniture",
    "wof:placetype":"venue"
},
  "geometry": {"coordinates":[-0.09614,51.531921],"type":"Point"}
}