{
  "type": "Feature",
  "properties": {
    "addr:full":"55 The Avenue Richmond Greater London TW9 2AL",
    "addr:housenumber":"55",
    "addr:postcode":"tw9 2al",
    "addr:street":"The Avenue",
    "iso:country":"GB",
    "sg:address":"55 The Avenue",
    "sg:city":"Richmond",
    "sg:classifiers":[
        {
            "category":"Professional",
            "subcategory":"Management & Consulting",
            "type":"Services"
        }
    ],
    "sg:postcode":"TW9 2AL",
    "sg:province":"Greater London",
    "sg:tags":[
        "consultant",
        "business"
    ],
    "wof:name":"De Speville & Associates",
    "wof:placetype":"venue"
},
  "geometry": {"coordinates":[-0.289835,51.473694],"type":"Point"}
}