{
  "type": "Feature",
  "properties": {
    "addr:full":"Shirehall, Abbey Foregate Shrewsbury Shropshire SY2 6ND",
    "addr:postcode":"sy2 6nd",
    "addr:street":"Foregate",
    "iso:country":"GB",
    "sg:address":"Shirehall, Abbey Foregate",
    "sg:city":"Shrewsbury",
    "sg:classifiers":[
        {
            "category":"Government",
            "subcategory":"Office",
            "type":"Public Place"
        }
    ],
    "sg:phone":"+44 1743 251000",
    "sg:postcode":"SY2 6ND",
    "sg:province":"Shropshire",
    "sg:tags":[
        "local"
    ],
    "wof:name":"Shropshire County Council",
    "wof:placetype":"venue"
},
  "geometry": {"coordinates":[-2.745173,52.707241],"type":"Point"}
}