{
  "type": "Feature",
  "properties": {
    "iso:country":"GB",
    "sg:address":"12 New Street",
    "sg:city":"Porthmadog",
    "sg:classifiers":[
        {
            "category":"Taxi",
            "type":"Transportation"
        }
    ],
    "sg:phone":"+44 1766 514799",
    "sg:postcode":"LL49 9ED",
    "sg:province":"Gwynedd",
    "sg:tags":[
        "equipment",
        "navigation",
        "supply"
    ],
    "wof:name":"Dukes Taxi's",
    "wof:placetype":"venue"
},
  "geometry": {"coordinates":[-4.131324,52.929119],"type":"Point"}
}