{
  "type": "Feature",
  "properties": {
    "addr:full":"Trattoria Italia, 68-70 St Benedicts Street Norwich Norfolk NR2 4AR",
    "addr:housenumber":"68-70",
    "addr:postcode":"nr2 4ar",
    "addr:street":"St Benedicts Street",
    "iso:country":"GB",
    "sg:address":"Trattoria Italia, 68-70 St Benedicts Street",
    "sg:city":"Norwich",
    "sg:classifiers":[
        {
            "category":"Restaurant",
            "type":"Food & Drink"
        }
    ],
    "sg:phone":"+44 1603 615581",
    "sg:postcode":"NR2 4AR",
    "sg:province":"Norfolk",
    "sg:tags":[
        "italian"
    ],
    "wof:name":"Umberto's",
    "wof:placetype":"venue"
},
  "geometry": {"coordinates":[1.288079977,52.6311798096],"type":"Point"}
}