{
  "type": "Feature",
  "properties": {
    "iso:country":"GB",
    "sg:address":"Old Press Room, Bisley N R A",
    "sg:city":"Woking",
    "sg:classifiers":[
        {
            "category":"Taxi",
            "type":"Transportation"
        }
    ],
    "sg:phone":"+44 1483 474849",
    "sg:postcode":"GU24 0PB",
    "sg:province":"Surrey",
    "sg:tags":[
        "mini",
        "cab"
    ],
    "wof:name":"First Choice Private Hire",
    "wof:placetype":"venue"
},
  "geometry": {"coordinates":[-0.65567,51.311489],"type":"Point"}
}