{
  "type": "Feature",
  "properties": {
    "addr:full":"Training Centre, Stareton Kenilworth Warwickshire CV8 2LJ",
    "addr:postcode":"cv8 2lj",
    "iso:country":"GB",
    "sg:address":"Training Centre, Stareton",
    "sg:city":"Kenilworth",
    "sg:classifiers":[
        {
            "category":"Education",
            "subcategory":"Special Training",
            "type":"Public Place"
        }
    ],
    "sg:phone":"+44 24 7653 1000",
    "sg:postcode":"CV8 2LJ",
    "sg:province":"Warwickshire",
    "sg:tags":[
        "product",
        "centre"
    ],
    "wof:name":"Massey-Ferguson (Uk) Ltd",
    "wof:placetype":"venue"
},
  "geometry": {"coordinates":[-1.579441,52.342937],"type":"Point"}
}