{
  "type": "Feature",
  "properties": {
    "iso:country":"GB",
    "sg:address":"16 Chestnut Way",
    "sg:city":"Godalming",
    "sg:classifiers":[
        {
            "category":"Professional",
            "subcategory":"Computer Services",
            "type":"Services"
        }
    ],
    "sg:postcode":"GU7 1TS",
    "sg:province":"Surrey",
    "sg:tags":[
        "system",
        "software"
    ],
    "wof:name":"Ocean Projects Ltd",
    "wof:placetype":"venue"
},
  "geometry": {"coordinates":[-0.6048769951,51.1749839783],"type":"Point"}
}