{
  "type": "Feature",
  "properties": {
    "addr:full":"Mastrick Dr Aberdeen Aberdeen City AB16 6UE",
    "addr:postcode":"ab16 6ue",
    "addr:street":"Mastrick Dr",
    "iso:country":"GB",
    "sg:address":"Mastrick Dr",
    "sg:city":"Aberdeen",
    "sg:classifiers":[
        {
            "category":"Social Services",
            "type":"Services"
        }
    ],
    "sg:phone":"+44 1224 692638",
    "sg:postcode":"AB16 6UE",
    "sg:province":"Aberdeen City",
    "wof:name":"Burnside Centre",
    "wof:placetype":"venue"
},
  "geometry": {"coordinates":[-2.1550939083,57.1546630859],"type":"Point"}
}