{
  "type": "Feature",
  "properties": {
    "iso:country":"GB",
    "sg:address":"139 Keith Lucas Rd",
    "sg:city":"Farnborough",
    "sg:classifiers":[
        {
            "category":"Social Services",
            "subcategory":"Adult Care",
            "type":"Services"
        }
    ],
    "sg:postcode":"GU14 0DL",
    "sg:province":"Hampshire",
    "sg:tags":[
        "domestic",
        "cleaning"
    ],
    "wof:name":"Deans,J,",
    "wof:placetype":"venue"
},
  "geometry": {"coordinates":[-0.770329,51.287159],"type":"Point"}
}