{
  "type": "Feature",
  "properties": {
    "iso:country":"GB",
    "sg:address":"Berthlwyd, Llangynin, St Clears",
    "sg:city":"Carmarthen",
    "sg:classifiers":[
        {
            "category":"Farming",
            "subcategory":"Dairy Farm",
            "type":"Manufacturing & Wholesale Goods"
        }
    ],
    "sg:phone":"+44 1994 230448",
    "sg:postcode":"SA33 4LA",
    "sg:province":"Carmarthenshire",
    "wof:name":"A R & E Caswell",
    "wof:placetype":"venue"
},
  "geometry": {"coordinates":[-4.55564,51.84642],"type":"Point"}
}