{
  "type": "Feature",
  "properties": {
    "addr:full":"Ronald St Whitechapel Greater London E1 0DT",
    "addr:postcode":"e1 0dt",
    "addr:street":"Ronald St",
    "iso:country":"GB",
    "sg:address":"Ronald St",
    "sg:city":"Whitechapel",
    "sg:classifiers":[
        {
            "category":"Health Services",
            "subcategory":"Hospital",
            "type":"Services"
        }
    ],
    "sg:phone":"+44 20 7702 8199",
    "sg:postcode":"E1 0DT",
    "sg:province":"Greater London",
    "wof:name":"Stepney Day Hospital",
    "wof:placetype":"venue"
},
  "geometry": {"coordinates":[-0.0491390005,51.5129966736],"type":"Point"}
}