{
  "type": "Feature",
  "properties": {
    "addr:full":"29 East Street Shoreham-by-sea West Sussex BN43 5ZD",
    "addr:housenumber":"29",
    "addr:postcode":"bn43 5zd",
    "addr:street":"East Street",
    "iso:country":"GB",
    "sg:address":"29 East Street",
    "sg:city":"Shoreham-by-sea",
    "sg:classifiers":[
        {
            "category":"Health Services",
            "subcategory":"Dentist",
            "type":"Services"
        }
    ],
    "sg:postcode":"BN43 5ZD",
    "sg:province":"West Sussex",
    "wof:name":"Church House Dental Laboratory",
    "wof:placetype":"venue"
},
  "geometry": {"coordinates":[-0.273624,50.832626],"type":"Point"}
}