{
  "type": "Feature",
  "properties": {
    "addr:full":"Lee House, Highfield Road Birmingham West Midlands B15 3ED",
    "addr:postcode":"b15 3ed",
    "addr:street":"Highfield Road",
    "iso:country":"GB",
    "sg:address":"Lee House, Highfield Road",
    "sg:city":"Birmingham",
    "sg:classifiers":[
        {
            "category":"Conference Center",
            "type":"Public Place"
        }
    ],
    "sg:phone":"+44 121 248 4455",
    "sg:postcode":"B15 3ED",
    "sg:province":"West Midlands",
    "wof:name":"V R G",
    "wof:placetype":"venue"
},
  "geometry": {"coordinates":[-1.923617,52.46936],"type":"Point"}
}