{
  "type": "Feature",
  "properties": {
    "addr:full":"23 South Trinity Road, Trinity Edinburgh City of Edinburgh EH5 3PN",
    "addr:housenumber":"23",
    "addr:postcode":"eh5 3pn",
    "addr:street":"South Trinity Road",
    "iso:country":"GB",
    "sg:address":"23 South Trinity Road, Trinity",
    "sg:city":"Edinburgh",
    "sg:classifiers":[
        {
            "category":"Building & Trades",
            "subcategory":"Construction",
            "type":"Services"
        }
    ],
    "sg:phone":"+44 131 657 3030",
    "sg:postcode":"EH5 3PN",
    "sg:province":"City of Edinburgh",
    "sg:tags":[
        "roofing"
    ],
    "wof:name":"Trintiy Roofing",
    "wof:placetype":"venue"
},
  "geometry": {"coordinates":[-3.209542,55.974174],"type":"Point"}
}