{
  "type": "Feature",
  "properties": {
    "iso:country":"GB",
    "sg:address":"25 Grove Avenue",
    "sg:city":"London",
    "sg:classifiers":[
        {
            "category":"Health Services",
            "subcategory":"Health Practitioner",
            "type":"Services"
        }
    ],
    "sg:postcode":"N3 1QS",
    "sg:province":"Greater London",
    "sg:tags":[
        "psychotherapist"
    ],
    "wof:name":"NORTH LONDON LINK CONSULTANCY & PSYCHOTHERAPY PRACTICE",
    "wof:placetype":"venue"
},
  "geometry": {"coordinates":[-0.193171,51.604244],"type":"Point"}
}