{
  "type": "Feature",
  "properties": {
    "iso:country":"GB",
    "sg:address":"76 Upminster Road South",
    "sg:city":"Rainham",
    "sg:classifiers":[
        {
            "category":"Shopping",
            "subcategory":"Hobbies, Toys, & Games",
            "type":"Retail Goods"
        }
    ],
    "sg:phone":"+44 1708 522081",
    "sg:postcode":"RM13 9AA",
    "sg:province":"Essex",
    "sg:tags":[
        "shop",
        "toy"
    ],
    "wof:name":"Aladdins Cave",
    "wof:placetype":"venue"
},
  "geometry": {"coordinates":[0.194516,51.518932],"type":"Point"}
}