{
  "type": "Feature",
  "properties": {
    "iso:country":"GB",
    "sg:address":"Cove Bay",
    "sg:city":"Aberdeen",
    "sg:classifiers":[
        {
            "category":"Home & Garden",
            "subcategory":"Garden Supply",
            "type":"Retail Goods"
        }
    ],
    "sg:phone":"+44 1224 897216",
    "sg:postcode":"AB12 3LA",
    "sg:province":"Aberdeen City",
    "sg:tags":[
        "nursery",
        "centre"
    ],
    "wof:name":"David Penny",
    "wof:placetype":"venue"
},
  "geometry": {"coordinates":[-2.07675,57.099281],"type":"Point"}
}