{
  "type": "Feature",
  "properties": {
    "addr:full":"2 Sylvanus, Wooden Hill Bracknell Berkshire RG12 8XX",
    "addr:housenumber":"2",
    "addr:postcode":"rg12 8xx",
    "addr:street":"Sylvanus Wooden Hill",
    "iso:country":"GB",
    "sg:address":"2 Sylvanus, Wooden Hill",
    "sg:city":"Bracknell",
    "sg:classifiers":[
        {
            "category":"Professional",
            "subcategory":"Management & Consulting",
            "type":"Services"
        }
    ],
    "sg:postcode":"RG12 8XX",
    "sg:province":"Berkshire",
    "sg:tags":[
        "consultant",
        "business"
    ],
    "wof:name":"Mountain Consultants Ltd",
    "wof:placetype":"venue"
},
  "geometry": {"coordinates":[-0.7715830207,51.392036438],"type":"Point"}
}