{
  "type": "Feature",
  "properties": {
    "iso:country":"GB",
    "sg:address":"33 Dale Lane, Beeston",
    "sg:city":"Nottingham",
    "sg:classifiers":[
        {
            "category":"Building & Trades",
            "subcategory":"Landscaping Services",
            "type":"Services"
        }
    ],
    "sg:phone":"+44 115 967 8742",
    "sg:postcode":"NG9 4EA",
    "sg:province":"Nottinghamshire",
    "sg:tags":[
        "gardening"
    ],
    "wof:name":"All Seasons Landscape & Gardening",
    "wof:placetype":"venue"
},
  "geometry": {"coordinates":[-1.2265059948,52.923740387],"type":"Point"}
}