{
  "type": "Feature",
  "properties": {
    "addr:full":"Ide Exeter Devon EX2 9SU",
    "addr:postcode":"ex2 9su",
    "addr:street":"Ide",
    "iso:country":"GB",
    "sg:address":"Ide",
    "sg:city":"Exeter",
    "sg:classifiers":[
        {
            "category":"Farming",
            "subcategory":"Livestock Farm",
            "type":"Manufacturing & Wholesale Goods"
        }
    ],
    "sg:phone":"+44 1392 430432",
    "sg:postcode":"EX2 9SU",
    "sg:province":"Devon",
    "sg:tags":[
        "others"
    ],
    "wof:name":"David E F Martin",
    "wof:placetype":"venue"
},
  "geometry": {"coordinates":[-3.56332,50.70816],"type":"Point"}
}