{
  "type": "Feature",
  "properties": {
    "iso:country":"GB",
    "sg:address":"6 High Street",
    "sg:city":"Haddington",
    "sg:classifiers":[
        {
            "category":"Cafe",
            "type":"Food & Drink"
        }
    ],
    "sg:phone":"+44 1620 822330",
    "sg:postcode":"EH41 3ES",
    "sg:province":"East Lothian",
    "sg:tags":[
        "tea",
        "snack",
        "bar",
        "room"
    ],
    "wof:name":"The Carlyle Cafe",
    "wof:placetype":"venue"
},
  "geometry": {"coordinates":[-2.775492,55.95525],"type":"Point"}
}