{
  "type": "Feature",
  "properties": {
    "addr:full":"5 Wellington Road London Greater London E11 2AN",
    "addr:housenumber":"5",
    "addr:postcode":"e11 2an",
    "addr:street":"Wellington Road",
    "iso:country":"GB",
    "sg:address":"5 Wellington Road",
    "sg:city":"London",
    "sg:classifiers":[
        {
            "category":"Farming",
            "subcategory":"Nursery",
            "type":"Manufacturing & Wholesale Goods"
        }
    ],
    "sg:postcode":"E11 2AN",
    "sg:province":"Greater London",
    "sg:tags":[
        "creche"
    ],
    "wof:name":"Oak Lodge Day Nursery",
    "wof:placetype":"venue"
},
  "geometry": {"coordinates":[0.025183,51.579899],"type":"Point"}
}