{
  "type": "Feature",
  "properties": {
    "iso:country":"GB",
    "sg:address":"3 Wellington Terrace",
    "sg:city":"Bristol",
    "sg:classifiers":[
        {
            "category":"Bars & Pubs",
            "type":"Food & Drink"
        }
    ],
    "sg:postcode":"BS8 4LE",
    "sg:province":"City of Bristol",
    "sg:tags":[
        "pubs",
        "inn"
    ],
    "wof:name":"The Portcullis",
    "wof:placetype":"venue"
},
  "geometry": {"coordinates":[-2.624291,51.452965],"type":"Point"}
}