{
  "type": "Feature",
  "properties": {
    "addr:full":"14 The Mall London Greater London W5 2PJ",
    "addr:housenumber":"14",
    "addr:postcode":"w5 2pj",
    "addr:street":"The Mall",
    "iso:country":"GB",
    "sg:address":"14 The Mall",
    "sg:city":"London",
    "sg:classifiers":[
        {
            "category":"Food & Beverages",
            "subcategory":"Supermarket",
            "type":"Retail Goods"
        }
    ],
    "sg:phone":"+44 20 8810 0348",
    "sg:postcode":"W5 2PJ",
    "sg:province":"Greater London",
    "wof:name":"Royal Foods",
    "wof:placetype":"venue"
},
  "geometry": {"coordinates":[-0.29916,51.513996],"type":"Point"}
}