{
  "type": "Feature",
  "properties": {
    "addr:full":"438 Kings Road London Greater London SW10 0LJ",
    "addr:housenumber":"438",
    "addr:postcode":"sw10 0lj",
    "addr:street":"Kings Road",
    "iso:country":"GB",
    "sg:address":"438 Kings Road",
    "sg:city":"London",
    "sg:classifiers":[
        {
            "category":"Restaurant",
            "type":"Food & Drink"
        }
    ],
    "sg:phone":"+44 20 7351 4118",
    "sg:postcode":"SW10 0LJ",
    "sg:province":"Greater London",
    "sg:tags":[
        "indian"
    ],
    "wof:name":"Vama the Indian Room",
    "wof:placetype":"venue"
},
  "geometry": {"coordinates":[-0.177809,51.4830627441],"type":"Point"}
}