{
  "type": "Feature",
  "properties": {
    "addr:full":"132 Station Road, North Hykeham Lincoln Lincolnshire LN6 9AT",
    "addr:housenumber":"132",
    "addr:postcode":"ln6 9at",
    "addr:street":"Station Road North",
    "iso:country":"GB",
    "sg:address":"132 Station Road, North Hykeham",
    "sg:city":"Lincoln",
    "sg:classifiers":[
        {
            "category":"Shopping",
            "subcategory":"Department Store",
            "type":"Retail Goods"
        },
        {
            "category":"Shopping",
            "subcategory":"News",
            "type":"Retail Goods"
        }
    ],
    "sg:phone":"+44 1522 681596",
    "sg:postcode":"LN6 9AT",
    "sg:province":"Lincolnshire",
    "sg:tags":[
        "newsagent",
        "departmental"
    ],
    "wof:name":"Open All Hours",
    "wof:placetype":"venue"
},
  "geometry": {"coordinates":[-0.599797,53.193787],"type":"Point"}
}