{
  "type": "Feature",
  "properties": {
    "addr:full":"Unit 22 Rippleside Comm Estate, Ripple Road Barking Essex IG11 0RL",
    "addr:housenumber":"unit 22",
    "addr:postcode":"ig11 0rl",
    "addr:street":"Ripple Road",
    "iso:country":"GB",
    "sg:address":"Unit 22 Rippleside Comm Estate, Ripple Road",
    "sg:city":"Barking",
    "sg:classifiers":[
        {
            "category":"Shopping",
            "subcategory":"Computers & Home Electronics",
            "type":"Retail Goods"
        }
    ],
    "sg:phone":"+44 20 8592 0506",
    "sg:postcode":"IG11 0RL",
    "sg:province":"Essex",
    "wof:name":"O-So-Kozee Ltd.",
    "wof:placetype":"venue"
},
  "geometry": {"coordinates":[0.0811149999,51.539100647],"type":"Point"}
}