{
  "type": "Feature",
  "properties": {
    "addr:full":"28 Cranbrook Drive, Gidea Park Romford Essex RM2 6PA",
    "addr:housenumber":"28",
    "addr:postcode":"rm2 6pa",
    "addr:street":"Cranbrook Drive",
    "iso:country":"GB",
    "sg:address":"28 Cranbrook Drive, Gidea Park",
    "sg:city":"Romford",
    "sg:classifiers":[
        {
            "category":"Personal",
            "type":"Services"
        }
    ],
    "sg:postcode":"RM2 6PA",
    "sg:province":"Essex",
    "sg:tags":[
        "wedding"
    ],
    "wof:name":"Isabella",
    "wof:placetype":"venue"
},
  "geometry": {"coordinates":[0.207743,51.583237],"type":"Point"}
}