{
  "type": "Feature",
  "properties": {
    "addr:full":"114 Brighton Road Shoreham-by-sea West Sussex BN43 6RH",
    "addr:housenumber":"114",
    "addr:postcode":"bn43 6rh",
    "addr:street":"Brighton Road",
    "iso:country":"GB",
    "sg:address":"114 Brighton Road",
    "sg:city":"Shoreham-by-sea",
    "sg:classifiers":[
        {
            "category":"Manufacturing",
            "subcategory":"Metals",
            "type":"Manufacturing & Wholesale Goods"
        }
    ],
    "sg:phone":"+44 1273 597733",
    "sg:postcode":"BN43 6RH",
    "sg:province":"West Sussex",
    "sg:tags":[
        "steel",
        "fabricator",
        "erectors"
    ],
    "wof:name":"Prefab Steel Co.",
    "wof:placetype":"venue"
},
  "geometry": {"coordinates":[-0.2677679956,50.8326797485],"type":"Point"}
}