{
  "type": "Feature",
  "properties": {
    "addr:full":"218 Preston New Road Southport Lancashire PR9 8NY",
    "addr:housenumber":"218",
    "addr:postcode":"pr9 8ny",
    "addr:street":"Preston New Road",
    "iso:country":"GB",
    "sg:address":"218 Preston New Road",
    "sg:city":"Southport",
    "sg:classifiers":[
        {
            "category":"Building & Trades",
            "subcategory":"Construction",
            "type":"Services"
        }
    ],
    "sg:phone":"+44 1704 229201",
    "sg:postcode":"PR9 8NY",
    "sg:province":"Lancashire",
    "sg:tags":[
        "builder"
    ],
    "wof:name":"J.A.S Cropper",
    "wof:placetype":"venue"
},
  "geometry": {"coordinates":[-2.954867,53.672318],"type":"Point"}
}