{
  "type": "Feature",
  "properties": {
    "addr:full":"2 Middleton Road Heywood Lancashire OL10 2HT",
    "addr:housenumber":"2",
    "addr:postcode":"ol10 2ht",
    "addr:street":"Middleton Road",
    "iso:country":"GB",
    "sg:address":"2 Middleton Road",
    "sg:city":"Heywood",
    "sg:classifiers":[
        {
            "category":"Bars & Pubs",
            "subcategory":"Oxygen Bar",
            "type":"Food & Drink"
        },
        {
            "category":"Building & Trades",
            "subcategory":"Construction",
            "type":"Services"
        }
    ],
    "sg:phone":"+44 1706 628524",
    "sg:postcode":"OL10 2HT",
    "sg:province":"Lancashire",
    "sg:tags":[
        "roofing",
        "ventilation",
        "system"
    ],
    "wof:name":"A C S Lining Ltd.",
    "wof:placetype":"venue"
},
  "geometry": {"coordinates":[-2.209356,53.585239],"type":"Point"}
}