{
  "type": "Feature",
  "properties": {
    "iso:country":"GB",
    "sg:address":"175 Shirley Road",
    "sg:city":"Croydon",
    "sg:classifiers":[
        {
            "category":"Health Services",
            "subcategory":"Nursing And Care Facility",
            "type":"Services"
        },
        {
            "category":"Shopping",
            "subcategory":"Pharmacy",
            "type":"Retail Goods"
        }
    ],
    "sg:phone":"+44 20 8654 1065",
    "sg:postcode":"CR0 8SS",
    "sg:province":"Surrey",
    "sg:tags":[
        "supplier",
        "pharmaceutical",
        "wholesaler",
        "pharmacist",
        "chemist"
    ],
    "wof:name":"Shirley Pharmacy",
    "wof:placetype":"venue"
},
  "geometry": {"coordinates":[-0.059390001,51.3762359619],"type":"Point"}
}