{
  "type": "Feature",
  "properties": {
    "addr:full":"Wellington Road Taunton Somerset TA1 5AX",
    "addr:postcode":"ta1 5ax",
    "addr:street":"Wellington Road",
    "iso:country":"GB",
    "sg:address":"Wellington Road",
    "sg:city":"Taunton",
    "sg:classifiers":[
        {
            "category":"Education",
            "subcategory":"University",
            "type":"Public Place"
        },
        {
            "category":"Government",
            "subcategory":"Office",
            "type":"Public Place"
        }
    ],
    "sg:phone":"+44 1823 366435",
    "sg:postcode":"TA1 5AX",
    "sg:province":"Somerset",
    "sg:tags":[
        "college",
        "local",
        "higher"
    ],
    "sg:website":"http://www.somerset.ac.uk",
    "wof:name":"Somerset College Of Arts & Technology",
    "wof:placetype":"venue"
},
  "geometry": {"coordinates":[-3.117435,51.015213],"type":"Point"}
}