{
  "type": "Feature",
  "properties": {
    "iso:country":"GB",
    "sg:address":"284 Upper Richmond Rd",
    "sg:city":"Putney",
    "sg:classifiers":[
        {
            "category":"Banks & Credit Unions",
            "subcategory":"Financial Services",
            "type":"Services"
        }
    ],
    "sg:phone":"+44 20 8785 9741",
    "sg:postcode":"SW15 6TH",
    "sg:province":"Greater London",
    "sg:tags":[
        "consultant",
        "pension"
    ],
    "wof:name":"Freeman G H Financial Services Ltd",
    "wof:placetype":"venue"
},
  "geometry": {"coordinates":[-0.220921,51.461945],"type":"Point"}
}