{
  "type": "Feature",
  "properties": {
    "addr:full":"2 Zetland Avenue Fort William Highland PH33 6LL",
    "addr:housenumber":"2",
    "addr:postcode":"ph33 6ll",
    "addr:street":"Zetland Avenue",
    "iso:country":"GB",
    "sg:address":"2 Zetland Avenue",
    "sg:city":"Fort William",
    "sg:classifiers":[
        {
            "category":"Education",
            "subcategory":"School",
            "type":"Public Place"
        },
        {
            "category":"Government",
            "subcategory":"Office",
            "type":"Public Place"
        }
    ],
    "sg:phone":"+44 1397 702059",
    "sg:postcode":"PH33 6LL",
    "sg:province":"Highland",
    "sg:tags":[
        "local",
        "authority"
    ],
    "wof:name":"Upper Achintore Primary School",
    "wof:placetype":"venue"
},
  "geometry": {"coordinates":[-5.1158971786,56.8087692261],"type":"Point"}
}