{
  "type": "Feature",
  "properties": {
    "addr:full":"Honey Pot Lane Market Harborough Leicestershire LE17 6LU",
    "addr:postcode":"le17 6lu",
    "addr:street":"Pot Lane",
    "iso:country":"GB",
    "sg:address":"Honey Pot Lane",
    "sg:city":"Market Harborough",
    "sg:classifiers":[
        {
            "category":"Farming",
            "subcategory":"Dairy Farm",
            "type":"Manufacturing & Wholesale Goods"
        },
        {
            "category":"Farming",
            "subcategory":"Livestock Farm",
            "type":"Manufacturing & Wholesale Goods"
        }
    ],
    "sg:phone":"+44 1858 880282",
    "sg:postcode":"LE17 6LU",
    "sg:province":"Leicestershire",
    "sg:tags":[
        "others",
        "farmer"
    ],
    "wof:name":"Garner & Wade",
    "wof:placetype":"venue"
},
  "geometry": {"coordinates":[-1.05226,52.454491],"type":"Point"}
}