{
  "type": "Feature",
  "properties": {
    "addr:full":"1 Warwick Pl Leamington Spa Warwickshire CV32 5BH",
    "addr:housenumber":"1",
    "addr:postcode":"cv32 5bh",
    "addr:street":"Warwick Pl",
    "iso:country":"GB",
    "sg:address":"1 Warwick Pl",
    "sg:city":"Leamington Spa",
    "sg:classifiers":[
        {
            "category":"Food & Beverages",
            "subcategory":"Fruits & Vegetables",
            "type":"Retail Goods"
        }
    ],
    "sg:postcode":"CV32 5BH",
    "sg:province":"Warwickshire",
    "sg:tags":[
        "greengrocer"
    ],
    "wof:name":"Chamberlain,F,& Son",
    "wof:placetype":"venue"
},
  "geometry": {"coordinates":[-1.5422029495,52.2917785645],"type":"Point"}
}