{
  "type": "Feature",
  "properties": {
    "iso:country":"GB",
    "sg:address":"Unit 11 Northfield Way, Aycliffe Industrial Estate",
    "sg:city":"Newton Aycliffe",
    "sg:classifiers":[
        {
            "category":"Professional",
            "subcategory":"Engineering",
            "type":"Services"
        }
    ],
    "sg:phone":"+44 1325 315564",
    "sg:postcode":"DL5 6EJ",
    "sg:province":"Durham",
    "sg:tags":[
        "precision",
        "engineer"
    ],
    "wof:name":"Ronald C Anderson",
    "wof:placetype":"venue"
},
  "geometry": {"coordinates":[-1.579988,54.611778],"type":"Point"}
}