{
  "type": "Feature",
  "properties": {
    "iso:country":"GB",
    "sg:address":"Great Western Studios, Great Western Rd",
    "sg:city":"Maida Vale",
    "sg:classifiers":[
        {
            "category":"Manufacturing",
            "subcategory":"Apparel",
            "type":"Manufacturing & Wholesale Goods"
        }
    ],
    "sg:phone":"+44 20 7286 4331",
    "sg:postcode":"W9 3NY",
    "sg:province":"Greater London",
    "sg:tags":[
        "garment",
        "designer"
    ],
    "wof:name":"3 Ny Designs",
    "wof:placetype":"venue"
},
  "geometry": {"coordinates":[-0.1952590048,51.5258712769],"type":"Point"}
}