{
  "type": "Feature",
  "properties": {
    "iso:country":"GB",
    "sg:address":"Monffordd Quarry",
    "sg:city":"Penrhyndeudraeth",
    "sg:classifiers":[
        {
            "category":"Manufacturing",
            "subcategory":"Glass & Minerals",
            "type":"Manufacturing & Wholesale Goods"
        }
    ],
    "sg:phone":"+44 1766 770212",
    "sg:postcode":"LL48 6HP",
    "sg:province":"Gwynedd",
    "sg:tags":[
        "chalk",
        "stone",
        "slate"
    ],
    "wof:name":"Tarmac Quarry Products Ltd",
    "wof:placetype":"venue"
},
  "geometry": {"coordinates":[-4.0673141479,52.9303207397],"type":"Point"}
}