{
  "type": "Feature",
  "properties": {
    "iso:country":"GB",
    "sg:address":"35 Tillotson Avenue",
    "sg:city":"Sowerby Bridge",
    "sg:classifiers":[
        {
            "category":"Food & Beverages",
            "subcategory":"Meat & Fish",
            "type":"Retail Goods"
        }
    ],
    "sg:phone":"+44 1422 832045",
    "sg:postcode":"HX6 1BX",
    "sg:province":"West Yorkshire",
    "sg:tags":[
        "chip"
    ],
    "wof:name":"Beechwood Fisheries",
    "wof:placetype":"venue"
},
  "geometry": {"coordinates":[-1.92556,53.705917],"type":"Point"}
}