{
  "type": "Feature",
  "properties": {
    "iso:country":"GB",
    "sg:address":"284 Kingsland Road",
    "sg:city":"London",
    "sg:classifiers":[
        {
            "category":"Autos & Motor Vehicles",
            "subcategory":"Automobile Sales",
            "type":"Retail Goods"
        }
    ],
    "sg:phone":"+44 20 7249 3050",
    "sg:postcode":"E8 4DG",
    "sg:province":"Greater London",
    "sg:tags":[
        "car"
    ],
    "wof:name":"Pendragon Plc",
    "wof:placetype":"venue"
},
  "geometry": {"coordinates":[-0.076554,51.538265],"type":"Point"}
}