{
  "type": "Feature",
  "properties": {
    "addr:full":"Prince Of Wales Drive Ipswich Suffolk IP2 8PY",
    "addr:postcode":"ip2 8py",
    "addr:street":"Prince Of Wales Drive",
    "iso:country":"GB",
    "sg:address":"Prince Of Wales Drive",
    "sg:city":"Ipswich",
    "sg:classifiers":[
        {
            "category":"Education",
            "subcategory":"School",
            "type":"Public Place"
        }
    ],
    "sg:phone":"+44 1473 683932",
    "sg:postcode":"IP2 8PY",
    "sg:province":"Suffolk",
    "sg:tags":[
        "local",
        "authority"
    ],
    "wof:name":"Halifax Primary School",
    "wof:placetype":"venue"
},
  "geometry": {"coordinates":[1.143321,52.04192],"type":"Point"}
}