{
  "type": "Feature",
  "properties": {
    "iso:country":"GB",
    "sg:address":"Lewes Road",
    "sg:city":"Haywards Heath",
    "sg:classifiers":[
        {
            "category":"Travel",
            "subcategory":"Hotels & Motels",
            "type":"Entertainment"
        }
    ],
    "sg:phone":"+44 1444 451565",
    "sg:postcode":"RH17 7SF",
    "sg:province":"East Sussex",
    "wof:name":"Heathland Hotels Ltd.",
    "wof:placetype":"venue"
},
  "geometry": {"coordinates":[-0.0702129975,50.9954452515],"type":"Point"}
}