{
  "type": "Feature",
  "properties": {
    "addr:full":"Penmaenmawr Rd Llanfairfechan Conwy LL33 0PA",
    "addr:postcode":"ll33 0pa",
    "addr:street":"Penmaenmawr Rd",
    "iso:country":"GB",
    "sg:address":"Penmaenmawr Rd",
    "sg:city":"Llanfairfechan",
    "sg:classifiers":[
        {
            "category":"Retail",
            "subcategory":"Auto Repair",
            "type":"Services"
        }
    ],
    "sg:phone":"+44 1248 681238",
    "sg:postcode":"LL33 0PA",
    "sg:province":"Conwy",
    "sg:tags":[
        "modification",
        "garage"
    ],
    "wof:name":"Penlan Garage",
    "wof:placetype":"venue"
},
  "geometry": {"coordinates":[-3.9681990147,53.2619934082],"type":"Point"}
}