{
  "type": "Feature",
  "properties": {
    "addr:full":"15-17 Crown Street Halifax West Yorkshire HX1 1TT",
    "addr:housenumber":"15-17",
    "addr:postcode":"hx1 1tt",
    "addr:street":"Crown Street",
    "iso:country":"GB",
    "sg:address":"15-17 Crown Street",
    "sg:city":"Halifax",
    "sg:classifiers":[
        {
            "category":"Shopping",
            "subcategory":"Shoes",
            "type":"Retail Goods"
        }
    ],
    "sg:phone":"+44 1422 342405",
    "sg:postcode":"HX1 1TT",
    "sg:province":"West Yorkshire",
    "sg:tags":[
        "shop"
    ],
    "wof:name":"Dolcis",
    "wof:placetype":"venue"
},
  "geometry": {"coordinates":[-1.8617089987,53.7233200073],"type":"Point"}
}