{
  "type": "Feature",
  "properties": {
    "addr:full":"Millhams Craft Centre, Millhams Street Christchurch Dorset BH23 1DN",
    "addr:postcode":"bh23 1dn",
    "addr:street":"Millhams Street",
    "iso:country":"GB",
    "sg:address":"Millhams Craft Centre, Millhams Street",
    "sg:city":"Christchurch",
    "sg:classifiers":[
        {
            "category":"Manufacturing",
            "subcategory":"Glass & Minerals",
            "type":"Manufacturing & Wholesale Goods"
        }
    ],
    "sg:phone":"+44 1202 486398",
    "sg:postcode":"BH23 1DN",
    "sg:province":"Dorset",
    "sg:tags":[
        "stained"
    ],
    "wof:name":"Arts Translucent",
    "wof:placetype":"venue"
},
  "geometry": {"coordinates":[-1.776564002,50.7340698242],"type":"Point"}
}