{
  "type": "Feature",
  "properties": {
    "addr:full":"Unit 1 Thames Industrial Estate, High Street Dunstable Bedfordshire LU6 3HD",
    "addr:housenumber":"unit 1",
    "addr:postcode":"lu6 3hd",
    "addr:street":"Thames Industrial;High Street",
    "iso:country":"GB",
    "sg:address":"Unit 1 Thames Industrial Estate, High Street",
    "sg:city":"Dunstable",
    "sg:classifiers":[
        {
            "category":"Professional",
            "subcategory":"Printing & Photocopies",
            "type":"Services"
        }
    ],
    "sg:phone":"+44 1582 751965",
    "sg:postcode":"LU6 3HD",
    "sg:province":"Bedfordshire",
    "sg:tags":[
        "printer"
    ],
    "wof:name":"Flayre Press Printing Services",
    "wof:placetype":"venue"
},
  "geometry": {"coordinates":[-0.520663,51.885803],"type":"Point"}
}