{
  "type": "Feature",
  "properties": {
    "iso:country":"GB",
    "sg:address":"The Common",
    "sg:city":"Alfreton",
    "sg:classifiers":[
        {
            "category":"Place Of Worship",
            "type":"Public Place"
        }
    ],
    "sg:phone":"+44 1773 863338",
    "sg:postcode":"DE55 2ER",
    "sg:province":"Derbyshire",
    "wof:name":"Assemblies Of God",
    "wof:placetype":"venue"
},
  "geometry": {"coordinates":[-1.336714,53.10067],"type":"Point"}
}