{
  "type": "Feature",
  "properties": {
    "iso:country":"GB",
    "sg:address":"14 The Burgate",
    "sg:city":"Canterbury",
    "sg:classifiers":[
        {
            "category":"Health Services",
            "subcategory":"Dentist",
            "type":"Services"
        }
    ],
    "sg:phone":"+44 1227 462857",
    "sg:postcode":"CT1 2HG",
    "sg:province":"Kent",
    "wof:name":"A.I Craig",
    "wof:placetype":"venue"
},
  "geometry": {"coordinates":[1.083372,51.278557],"type":"Point"}
}