{
  "type": "Feature",
  "properties": {
    "iso:country":"GB",
    "sg:address":"Cefn Myddfai Farm, Velindre",
    "sg:city":"Swansea",
    "sg:classifiers":[
        {
            "category":"Home & Garden",
            "subcategory":"Garden Supply",
            "type":"Retail Goods"
        }
    ],
    "sg:postcode":"SA5 7NH",
    "sg:province":"Swansea",
    "sg:tags":[
        "nursery",
        "centre"
    ],
    "wof:name":"Cefn Myddfai Nursery",
    "wof:placetype":"venue"
},
  "geometry": {"coordinates":[-3.964119,51.717293],"type":"Point"}
}