{
  "type": "Feature",
  "properties": {
    "addr:full":"Oakenshore Manor Road, Wickhamford Evesham Gloucestershire WR11 7SA",
    "addr:postcode":"wr11 7sa",
    "addr:street":"Manor Road",
    "iso:country":"GB",
    "sg:address":"Oakenshore Manor Road, Wickhamford",
    "sg:city":"Evesham",
    "sg:classifiers":[
        {
            "category":"Shopping",
            "subcategory":"Clothing, Apparel, & Fashions",
            "type":"Retail Goods"
        }
    ],
    "sg:phone":"+44 1386 831022",
    "sg:postcode":"WR11 7SA",
    "sg:province":"Gloucestershire",
    "sg:tags":[
        "dresswear"
    ],
    "wof:name":"Hat Tricks",
    "wof:placetype":"venue"
},
  "geometry": {"coordinates":[-1.9030729532,52.0694313049],"type":"Point"}
}