{
  "type": "Feature",
  "properties": {
    "addr:full":"Arcadian Centre, Ladywell Walk Birmingham West Midlands B5 4ST",
    "addr:housenumber":"b5",
    "addr:postcode":"4st",
    "addr:street":"Ladywell Walk",
    "iso:country":"GB",
    "sg:address":"Arcadian Centre, Ladywell Walk",
    "sg:city":"Birmingham",
    "sg:classifiers":[
        {
            "category":"Shopping",
            "subcategory":"Books",
            "type":"Retail Goods"
        }
    ],
    "sg:phone":"+44 121 622 3882",
    "sg:postcode":"B5 4ST",
    "sg:province":"West Midlands",
    "sg:tags":[
        "bookseller"
    ],
    "wof:name":"New World Bookshop",
    "wof:placetype":"venue"
},
  "geometry": {"coordinates":[-1.8966399431,52.475189209],"type":"Point"}
}