{
  "type": "Feature",
  "properties": {
    "iso:country":"GB",
    "sg:address":"Sugarbrook Lane",
    "sg:city":"Bromsgrove",
    "sg:classifiers":[
        {
            "category":"Bars & Pubs",
            "type":"Food & Drink"
        }
    ],
    "sg:phone":"+44 1527 877777",
    "sg:postcode":"B60 3AU",
    "sg:province":"Worcestershire",
    "sg:tags":[
        "pubs",
        "inn"
    ],
    "wof:name":"Queens Head The",
    "wof:placetype":"venue"
},
  "geometry": {"coordinates":[-2.058599,52.319946],"type":"Point"}
}