{
  "type": "Feature",
  "properties": {
    "addr:full":"1 Tower Place, Leith Edinburgh City of Edinburgh EH6 7DB",
    "addr:housenumber":"1",
    "addr:postcode":"eh6 7db",
    "addr:street":"Tower Place",
    "iso:country":"GB",
    "sg:address":"1 Tower Place, Leith",
    "sg:city":"Edinburgh",
    "sg:classifiers":[
        {
            "category":"Travel",
            "subcategory":"Hotels & Motels",
            "type":"Entertainment"
        }
    ],
    "sg:phone":"+44 131 468 5000",
    "sg:postcode":"EH6 7DB",
    "sg:province":"City of Edinburgh",
    "wof:name":"M H E Ltd.",
    "wof:placetype":"venue"
},
  "geometry": {"coordinates":[-3.1681449413,55.9784927368],"type":"Point"}
}