{
  "type": "Feature",
  "properties": {
    "addr:full":"29 Wood Street Swindon Wiltshire SN1 4AN",
    "addr:housenumber":"29",
    "addr:postcode":"sn1 4an",
    "addr:street":"Wood Street",
    "iso:country":"GB",
    "sg:address":"29 Wood Street",
    "sg:city":"Swindon",
    "sg:classifiers":[
        {
            "category":"Shopping",
            "subcategory":"Gifts & Souvenirs",
            "type":"Retail Goods"
        },
        {
            "category":"Professional",
            "subcategory":"Art Services",
            "type":"Services"
        }
    ],
    "sg:postcode":"SN1 4AN",
    "sg:province":"Wiltshire",
    "sg:tags":[
        "shop",
        "framing"
    ],
    "wof:name":"Gifts From Gullivers",
    "wof:placetype":"venue"
},
  "geometry": {"coordinates":[-1.776115,51.552322],"type":"Point"}
}