{
  "type": "Feature",
  "properties": {
    "iso:country":"GB",
    "sg:address":"30a Slad Rd",
    "sg:city":"Stroud",
    "sg:classifiers":[
        {
            "category":"Retail",
            "subcategory":"Auto Repair",
            "type":"Services"
        }
    ],
    "sg:phone":"+44 1453 751066",
    "sg:postcode":"GL5 1QW",
    "sg:province":"Gloucestershire",
    "sg:tags":[
        "modification",
        "garage"
    ],
    "wof:name":"P A Boylan Motor Engineering",
    "wof:placetype":"venue"
},
  "geometry": {"coordinates":[-2.2141690254,51.7476882935],"type":"Point"}
}