{
  "type": "Feature",
  "properties": {
    "addr:full":"9a High Street, Woburn Sands Milton Keynes Bedfordshire MK17 8RF",
    "addr:housenumber":"9a",
    "addr:postcode":"mk17 8rf",
    "addr:street":"High Street",
    "iso:country":"GB",
    "sg:address":"9a High Street, Woburn Sands",
    "sg:city":"Milton Keynes",
    "sg:classifiers":[
        {
            "category":"Professional",
            "subcategory":"Computer Services",
            "type":"Services"
        }
    ],
    "sg:postcode":"MK17 8RF",
    "sg:province":"Bedfordshire",
    "sg:tags":[
        "system",
        "software"
    ],
    "wof:name":"Directdisc Ltd",
    "wof:placetype":"venue"
},
  "geometry": {"coordinates":[-0.6465730071,52.0108261108],"type":"Point"}
}