{
  "type": "Feature",
  "properties": {
    "iso:country":"GB",
    "sg:address":"70 Westbourne Gro",
    "sg:city":"London",
    "sg:classifiers":[
        {
            "category":"Home & Garden",
            "subcategory":"Kitchen Supply",
            "type":"Retail Goods"
        }
    ],
    "sg:postcode":"W2 5SH",
    "sg:province":"Greater London",
    "sg:tags":[
        "ware"
    ],
    "wof:name":"Kitchen Ideas",
    "wof:placetype":"venue"
},
  "geometry": {"coordinates":[-0.193145,51.518219],"type":"Point"}
}