{
  "type": "Feature",
  "properties": {
    "addr:full":"The Street, Dickleburgh Diss Norfolk IP21 4NQ",
    "addr:postcode":"ip21 4nq",
    "addr:street":"The Street",
    "iso:country":"GB",
    "sg:address":"The Street, Dickleburgh",
    "sg:city":"Diss",
    "sg:classifiers":[
        {
            "category":"Food & Beverages",
            "subcategory":"Meat & Fish",
            "type":"Retail Goods"
        }
    ],
    "sg:phone":"+44 1379 741207",
    "sg:postcode":"IP21 4NQ",
    "sg:province":"Norfolk",
    "sg:tags":[
        "butcher"
    ],
    "wof:name":"T Wilby & Sons",
    "wof:placetype":"venue"
},
  "geometry": {"coordinates":[1.148281,52.366749],"type":"Point"}
}