{
  "type": "Feature",
  "properties": {
    "addr:full":"82 West Green Road London Greater London N15 5NS",
    "addr:housenumber":"82",
    "addr:postcode":"n15 5ns",
    "addr:street":"West Green Road",
    "iso:country":"GB",
    "sg:address":"82 West Green Road",
    "sg:city":"London",
    "sg:classifiers":[
        {
            "category":"Shopping",
            "subcategory":"Music",
            "type":"Retail Goods"
        }
    ],
    "sg:phone":"+44 20 8800 8838",
    "sg:postcode":"N15 5NS",
    "sg:province":"Greater London",
    "sg:tags":[
        "record",
        "tape",
        "cd"
    ],
    "wof:name":"Blackstar Records",
    "wof:placetype":"venue"
},
  "geometry": {"coordinates":[-0.0764599964,51.5847358704],"type":"Point"}
}