{
  "type": "Feature",
  "properties": {
    "addr:full":"95 Milestone Lane, Pinchbeck Spalding Lincolnshire PE11 3XR",
    "addr:housenumber":"95",
    "addr:postcode":"pe11 3xr",
    "addr:street":"Milestone Lane",
    "iso:country":"GB",
    "sg:address":"95 Milestone Lane, Pinchbeck",
    "sg:city":"Spalding",
    "sg:classifiers":[
        {
            "category":"Retail",
            "subcategory":"Auto Repair",
            "type":"Services"
        }
    ],
    "sg:phone":"+44 1775 725160",
    "sg:postcode":"PE11 3XR",
    "sg:province":"Lincolnshire",
    "sg:tags":[
        "modification",
        "garage",
        "related"
    ],
    "wof:name":"G M Motors",
    "wof:placetype":"venue"
},
  "geometry": {"coordinates":[-0.156581,52.824326],"type":"Point"}
}