{
  "type": "Feature",
  "properties": {
    "addr:full":"Langlands Mill, Langlands Pl Melrose Scottish Borders TD6 0SF",
    "addr:postcode":"td6 0sf",
    "addr:street":"Langlands Mill Langlands Pl",
    "iso:country":"GB",
    "sg:address":"Langlands Mill, Langlands Pl",
    "sg:city":"Melrose",
    "sg:classifiers":[
        {
            "category":"Home & Garden",
            "subcategory":"Carpets & Floor Coverings",
            "type":"Retail Goods"
        }
    ],
    "sg:phone":"+44 1835 822277",
    "sg:postcode":"TD6 0SF",
    "sg:province":"Scottish Borders",
    "sg:tags":[
        "carpets",
        "rug",
        "matting"
    ],
    "wof:name":"Thomson Carpets Ltd",
    "wof:placetype":"venue"
},
  "geometry": {"coordinates":[-2.662919,55.57431],"type":"Point"}
}