{
  "type": "Feature",
  "properties": {
    "addr:full":"75 Stanley Street Glasgow Glasgow City G41 1JF",
    "addr:housenumber":"75",
    "addr:postcode":"g41 1jf",
    "addr:street":"Stanley Street",
    "iso:country":"GB",
    "sg:address":"75 Stanley Street",
    "sg:city":"Glasgow",
    "sg:classifiers":[
        {
            "category":"Food & Beverages",
            "subcategory":"Candy",
            "type":"Retail Goods"
        }
    ],
    "sg:postcode":"G41 1JF",
    "sg:province":"Glasgow City",
    "sg:tags":[
        "confectioner"
    ],
    "wof:name":"Gray Dunn & Co. Ltd.",
    "wof:placetype":"venue"
},
  "geometry": {"coordinates":[-4.2800917625,55.8520965576],"type":"Point"}
}