{
  "type": "Feature",
  "properties": {
    "addr:full":"22 Rathbone Street London Greater London W1T 1LA",
    "addr:housenumber":"22",
    "addr:postcode":"w1t 1la",
    "addr:street":"Rathbone Street",
    "iso:country":"GB",
    "sg:address":"22 Rathbone Street",
    "sg:city":"London",
    "sg:classifiers":[
        {
            "category":"Insurance",
            "subcategory":"Insurance Agent",
            "type":"Services"
        }
    ],
    "sg:phone":"+44 20 7413 0999",
    "sg:postcode":"W1T 1LA",
    "sg:province":"Greater London",
    "sg:tags":[
        "broker"
    ],
    "wof:name":"Lucas Fettes Plc",
    "wof:placetype":"venue"
},
  "geometry": {"coordinates":[-0.135279,51.518471],"type":"Point"}
}