{
  "type": "Feature",
  "properties": {
    "addr:full":"Unit 1 4a Cromwell St Coventry Warwickshire CV6 5EZ",
    "addr:housenumber":"unit 1 4a",
    "addr:postcode":"cv6 5ez",
    "addr:street":"Cromwell St",
    "iso:country":"GB",
    "sg:address":"Unit 1 4a Cromwell St",
    "sg:city":"Coventry",
    "sg:classifiers":[
        {
            "category":"Autos & Motor Vehicles",
            "subcategory":"Automobile Sales",
            "type":"Retail Goods"
        }
    ],
    "sg:phone":"+44 24 7668 6111",
    "sg:postcode":"CV6 5EZ",
    "sg:province":"Warwickshire",
    "sg:tags":[
        "car"
    ],
    "wof:name":"Banger Land",
    "wof:placetype":"venue"
},
  "geometry": {"coordinates":[-1.493182,52.420532],"type":"Point"}
}