{
  "type": "Feature",
  "properties": {
    "addr:full":"23 Sims Clo Romford Essex RM1 3QT",
    "addr:housenumber":"23",
    "addr:postcode":"rm1 3qt",
    "addr:street":"Sims Clo",
    "iso:country":"GB",
    "sg:address":"23 Sims Clo",
    "sg:city":"Romford",
    "sg:classifiers":[
        {
            "category":"Shopping",
            "subcategory":"Computers & Home Electronics",
            "type":"Retail Goods"
        }
    ],
    "sg:phone":"+44 1708 747200",
    "sg:postcode":"RM1 3QT",
    "sg:province":"Essex",
    "sg:tags":[
        "aerial",
        "television",
        "radio"
    ],
    "wof:name":"BLS Aerials",
    "wof:placetype":"venue"
},
  "geometry": {"coordinates":[0.1909780055,51.5800628662],"type":"Point"}
}