{
  "type": "Feature",
  "properties": {
    "iso:country":"GB",
    "sg:address":"Bay Hall Mills, Bay Hall Common Road, Birkby",
    "sg:city":"Huddersfield",
    "sg:classifiers":[
        {
            "category":"Manufacturing",
            "subcategory":"Textiles",
            "type":"Manufacturing & Wholesale Goods"
        }
    ],
    "sg:phone":"+44 1484 424283",
    "sg:postcode":"HD1 5EP",
    "sg:province":"West Yorkshire",
    "sg:tags":[
        "knitwear"
    ],
    "wof:name":"Stork Brothers Ltd.",
    "wof:placetype":"venue"
},
  "geometry": {"coordinates":[-1.789164,53.65836],"type":"Point"}
}