{
  "type": "Feature",
  "properties": {
    "iso:country":"GB",
    "sg:address":"1 Woodburn Road",
    "sg:city":"Smethwick",
    "sg:classifiers":[
        {
            "category":"Manufacturing",
            "subcategory":"Textiles",
            "type":"Manufacturing & Wholesale Goods"
        }
    ],
    "sg:phone":"+44 121 555 7885",
    "sg:postcode":"B66 2PU",
    "sg:province":"West Midlands",
    "sg:tags":[
        "made-up"
    ],
    "wof:name":"Red Rose Enterprises Ltd.",
    "wof:placetype":"venue"
},
  "geometry": {"coordinates":[-1.943799,52.499306],"type":"Point"}
}