{
  "type": "Feature",
  "properties": {
    "iso:country":"GB",
    "sg:address":"108 Windsor Rd",
    "sg:city":"Newmarket",
    "sg:classifiers":[
        {
            "category":"Retail",
            "subcategory":"Animal Services",
            "type":"Services"
        }
    ],
    "sg:phone":"+44 1638 668118",
    "sg:postcode":"CB8 0PY",
    "sg:province":"Cambridgeshire",
    "sg:tags":[
        "box",
        "horse",
        "transporting"
    ],
    "wof:name":"T.J.W Wall",
    "wof:placetype":"venue"
},
  "geometry": {"coordinates":[0.394241,52.24575],"type":"Point"}
}