{
  "type": "Feature",
  "properties": {
    "addr:full":"121 Portobello High St Edinburgh City of Edinburgh EH15 1AF",
    "addr:housenumber":"121",
    "addr:postcode":"eh15 1af",
    "addr:street":"Portobello High St",
    "iso:country":"GB",
    "sg:address":"121 Portobello High St",
    "sg:city":"Edinburgh",
    "sg:classifiers":[
        {
            "category":"Government",
            "subcategory":"Post Office",
            "type":"Public Place"
        }
    ],
    "sg:phone":"+44 131 669 2020",
    "sg:postcode":"EH15 1AF",
    "sg:province":"City of Edinburgh",
    "wof:name":"Portobello Post Office",
    "wof:placetype":"venue"
},
  "geometry": {"coordinates":[-3.114995,55.953274],"type":"Point"}
}