{
  "type": "Feature",
  "properties": {
    "iso:country":"GB",
    "sg:address":"162 Redland Road, Redland",
    "sg:city":"Bristol",
    "sg:classifiers":[
        {
            "category":"Real Estate",
            "subcategory":"Surveying",
            "type":"Services"
        }
    ],
    "sg:phone":"+44 117 940 1605",
    "sg:postcode":"BS6 6YG",
    "sg:province":"City of Bristol",
    "sg:tags":[
        "surveyor",
        "quantity"
    ],
    "wof:name":"Cawley Billing Partnership",
    "wof:placetype":"venue"
},
  "geometry": {"coordinates":[-2.6091649532,51.4720420837],"type":"Point"}
}