{
  "type": "Feature",
  "properties": {
    "addr:full":"17 Albert Road Harrow Greater London HA2 6PS",
    "addr:housenumber":"17",
    "addr:postcode":"ha2 6ps",
    "addr:street":"Albert Road",
    "iso:country":"GB",
    "sg:address":"17 Albert Road",
    "sg:city":"Harrow",
    "sg:classifiers":[
        {
            "category":"Personal",
            "type":"Services"
        }
    ],
    "sg:postcode":"HA2 6PS",
    "sg:province":"Greater London",
    "sg:tags":[
        "wedding"
    ],
    "wof:name":"Ace of Hearts Wedding Photography",
    "wof:placetype":"venue"
},
  "geometry": {"coordinates":[-0.350933,51.592712],"type":"Point"}
}