{
  "type": "Feature",
  "properties": {
    "iso:country":"GB",
    "sg:address":"31 North Street",
    "sg:city":"Exmouth",
    "sg:classifiers":[
        {
            "category":"Building & Trades",
            "subcategory":"Construction",
            "type":"Services"
        }
    ],
    "sg:postcode":"EX8 1JZ",
    "sg:province":"Devon",
    "sg:tags":[
        "decorator",
        "painter"
    ],
    "wof:name":"Michael J Hayne",
    "wof:placetype":"venue"
},
  "geometry": {"coordinates":[-3.4090270996,50.6220664978],"type":"Point"}
}