{
  "type": "Feature",
  "properties": {
    "iso:country":"GB",
    "sg:address":"2 Hagley Road",
    "sg:city":"Stourbridge",
    "sg:classifiers":[
        {
            "category":"Insurance",
            "subcategory":"Insurance Agent",
            "type":"Services"
        }
    ],
    "sg:phone":"+44 1384 390909",
    "sg:postcode":"DY8 1QG",
    "sg:province":"Staffordshire",
    "sg:tags":[
        "broker"
    ],
    "wof:name":"K G J Insurance Brokers (Stourbridge) Ltd.",
    "wof:placetype":"venue"
},
  "geometry": {"coordinates":[-2.1436259747,52.4541816711],"type":"Point"}
}