{
  "type": "Feature",
  "properties": {
    "addr:full":"Unit K5 Taylor Business Park, Warrington Road Warrington Cheshire WA3 6BL",
    "addr:postcode":"wa3 6bl",
    "addr:street":"Business Park Warrington Road",
    "iso:country":"GB",
    "sg:address":"Unit K5 Taylor Business Park, Warrington Road",
    "sg:city":"Warrington",
    "sg:classifiers":[
        {
            "category":"Home & Garden",
            "subcategory":"Hardware",
            "type":"Retail Goods"
        }
    ],
    "sg:phone":"+44 1925 763311",
    "sg:postcode":"WA3 6BL",
    "sg:province":"Cheshire",
    "sg:tags":[
        "device",
        "fixing",
        "fastener"
    ],
    "wof:name":"Powerplus Fixings",
    "wof:placetype":"venue"
},
  "geometry": {"coordinates":[-2.524946928,53.4305076599],"type":"Point"}
}