{
  "type": "Feature",
  "properties": {
    "iso:country":"GB",
    "sg:address":"2 Burnside Road",
    "sg:city":"Aviemore",
    "sg:classifiers":[
        {
            "category":"Education",
            "subcategory":"School",
            "type":"Public Place"
        },
        {
            "category":"Sports & Exercise",
            "subcategory":"Tennis Court",
            "type":"Entertainment"
        }
    ],
    "sg:phone":"+44 7773 489128",
    "sg:postcode":"PH22 1SQ",
    "sg:province":"Highland",
    "sg:tags":[
        "activities",
        "based",
        "leisure"
    ],
    "wof:name":"Aviemore Ski School",
    "wof:placetype":"venue"
},
  "geometry": {"coordinates":[-3.8257501125,57.1993255615],"type":"Point"}
}