{
  "type": "Feature",
  "properties": {
    "addr:full":"1 Tai-bach, Pentrebach Merthyr Tydfil Caerphilly CF48 4BY",
    "addr:housenumber":"1",
    "addr:postcode":"cf48 4by",
    "addr:street":"Tai-Bach Pentrebach",
    "iso:country":"GB",
    "sg:address":"1 Tai-bach, Pentrebach",
    "sg:city":"Merthyr Tydfil",
    "sg:classifiers":[
        {
            "category":"Organizations",
            "subcategory":"Community Association",
            "type":"Services"
        },
        {
            "category":"Organizations",
            "subcategory":"Membership Organization",
            "type":"Services"
        }
    ],
    "sg:phone":"+44 1443 690291",
    "sg:postcode":"CF48 4BY",
    "sg:province":"Caerphilly",
    "sg:tags":[
        "club",
        "social"
    ],
    "wof:name":"Pentrebach Labour Club",
    "wof:placetype":"venue"
},
  "geometry": {"coordinates":[-3.3550999165,51.7230911255],"type":"Point"}
}