{
  "type": "Feature",
  "properties": {
    "addr:full":"38 North Parade Bradford West Yorkshire BD1 3HZ",
    "addr:housenumber":"38",
    "addr:postcode":"bd1 3hz",
    "addr:street":"North Parade",
    "iso:country":"GB",
    "sg:address":"38 North Parade",
    "sg:city":"Bradford",
    "sg:classifiers":[
        {
            "category":"Shopping",
            "subcategory":"Optician",
            "type":"Retail Goods"
        }
    ],
    "sg:postcode":"BD1 3HZ",
    "sg:province":"West Yorkshire",
    "wof:name":"Jbr1910 Ltd.",
    "wof:placetype":"venue"
},
  "geometry": {"coordinates":[-1.7566740513,53.7975654602],"type":"Point"}
}