{
  "type": "Feature",
  "properties": {
    "addr:full":"Unit 2 Low Mills Road, Lower Wortley Leeds West Yorkshire LS12 4UR",
    "addr:housenumber":"unit 2",
    "addr:postcode":"ls12 4ur",
    "addr:street":"Low Mills Road",
    "iso:country":"GB",
    "sg:address":"Unit 2 Low Mills Road, Lower Wortley",
    "sg:city":"Leeds",
    "sg:classifiers":[
        {
            "category":"Building & Trades",
            "subcategory":"Plumbing",
            "type":"Services"
        }
    ],
    "sg:phone":"+44 113 279 9199",
    "sg:postcode":"LS12 4UR",
    "sg:province":"West Yorkshire",
    "sg:tags":[
        "merchant",
        "plumbers'"
    ],
    "wof:name":"City Plumbing & Heating Supplies Ltd.",
    "wof:placetype":"venue"
},
  "geometry": {"coordinates":[-1.597517,53.782536],"type":"Point"}
}