{
  "type": "Feature",
  "properties": {
    "iso:country":"GB",
    "sg:address":"45 Charlbert Street",
    "sg:city":"London",
    "sg:classifiers":[
        {
            "category":"Shopping",
            "subcategory":"Department Store",
            "type":"Retail Goods"
        }
    ],
    "sg:phone":"+44 20 7586 1919",
    "sg:postcode":"NW8 6JN",
    "sg:province":"Greater London",
    "wof:name":"St Johns Wood Foodstore",
    "wof:placetype":"venue"
},
  "geometry": {"coordinates":[-0.168569,51.534641],"type":"Point"}
}