{
  "type": "Feature",
  "properties": {
    "addr:full":"38 Long St Wotton-under-edge Gloucestershire GL12 7BT",
    "addr:housenumber":"38",
    "addr:postcode":"gl12 7bt",
    "addr:street":"Long St",
    "iso:country":"GB",
    "sg:address":"38 Long St",
    "sg:city":"Wotton-under-edge",
    "sg:classifiers":[
        {
            "category":"Food & Beverages",
            "subcategory":"Supermarket",
            "type":"Retail Goods"
        }
    ],
    "sg:phone":"+44 1453 842112",
    "sg:postcode":"GL12 7BT",
    "sg:province":"Gloucestershire",
    "wof:name":"Oxford Swindon & Gloucester Co-Operative",
    "wof:placetype":"venue"
},
  "geometry": {"coordinates":[-2.352987051,51.6376914978],"type":"Point"}
}