{
  "type": "Feature",
  "properties": {
    "iso:country":"GB",
    "sg:address":"Carr La, Hyde Park",
    "sg:city":"Doncaster",
    "sg:classifiers":[
        {
            "category":"Education",
            "subcategory":"Special Training",
            "type":"Public Place"
        }
    ],
    "sg:phone":"+44 1302 769911",
    "sg:postcode":"DN4 5AA",
    "sg:province":"South Yorkshire",
    "sg:tags":[
        "product",
        "centre"
    ],
    "wof:name":"Doncaster Itec Ltd",
    "wof:placetype":"venue"
},
  "geometry": {"coordinates":[-1.130836,53.513699],"type":"Point"}
}