{
  "type": "Feature",
  "properties": {
    "iso:country":"GB",
    "sg:address":"66-68 Margaret Street",
    "sg:city":"West End",
    "sg:classifiers":[
        {
            "category":"Shopping",
            "type":"Retail Goods"
        }
    ],
    "sg:phone":"+44 1438 221009",
    "sg:postcode":"W1N 8PX",
    "sg:province":"Hampshire",
    "sg:tags":[
        "product",
        "disposable"
    ],
    "wof:name":"Tristar (uk) Ltd",
    "wof:placetype":"venue"
},
  "geometry": {"coordinates":[-0.139937,51.516754],"type":"Point"}
}