{
  "type": "Feature",
  "properties": {
    "addr:full":"43 Heol Fach, North Cornelly Bridgend Bridgend CF33 4LN",
    "addr:housenumber":"43",
    "addr:postcode":"cf33 4ln",
    "addr:street":"Heol Fach North;Bridgend",
    "iso:country":"GB",
    "sg:address":"43 Heol Fach, North Cornelly",
    "sg:city":"Bridgend",
    "sg:classifiers":[
        {
            "category":"Health Services",
            "subcategory":"Dentist",
            "type":"Services"
        }
    ],
    "sg:phone":"+44 1656 740650",
    "sg:postcode":"CF33 4LN",
    "sg:province":"Bridgend",
    "wof:name":"Cornelly Dental Practice",
    "wof:placetype":"venue"
},
  "geometry": {"coordinates":[-3.700421,51.521473],"type":"Point"}
}