{
  "type": "Feature",
  "properties": {
    "addr:full":"230 Somercotes Hill Alfreton Derbyshire DE55 4JS",
    "addr:housenumber":"230",
    "addr:postcode":"de55 4js",
    "addr:street":"Somercotes Hill",
    "iso:country":"GB",
    "sg:address":"230 Somercotes Hill",
    "sg:city":"Alfreton",
    "sg:classifiers":[
        {
            "category":"Retail",
            "subcategory":"Auto Repair",
            "type":"Services"
        }
    ],
    "sg:phone":"+44 1773 604650",
    "sg:postcode":"DE55 4JS",
    "sg:province":"Derbyshire",
    "sg:tags":[
        "modification",
        "garage"
    ],
    "wof:name":"Peter's Motors",
    "wof:placetype":"venue"
},
  "geometry": {"coordinates":[-1.3643079996,53.077545166],"type":"Point"}
}