{
  "type": "Feature",
  "properties": {
    "iso:country":"GB",
    "sg:address":"51 Mackworth Dr",
    "sg:city":"Neath",
    "sg:classifiers":[
        {
            "category":"Recreation",
            "type":"Entertainment"
        }
    ],
    "sg:phone":"+44 1639 638522",
    "sg:postcode":"SA11 2QA",
    "sg:province":"Neath Port Talbot",
    "sg:tags":[
        "snooker",
        "billiards",
        "pool"
    ],
    "wof:name":"Snooker Wales",
    "wof:placetype":"venue"
},
  "geometry": {"coordinates":[-3.777457,51.653252],"type":"Point"}
}