{
  "type": "Feature",
  "properties": {
    "addr:full":"1a Deerlands Av Sheffield South Yorkshire S5 7WP",
    "addr:housenumber":"1a",
    "addr:postcode":"s5 7wp",
    "addr:street":"Deerlands Av",
    "iso:country":"GB",
    "sg:address":"1a Deerlands Av",
    "sg:city":"Sheffield",
    "sg:classifiers":[
        {
            "category":"Organizations",
            "subcategory":"Membership Organization",
            "type":"Services"
        }
    ],
    "sg:phone":"+44 114 240 2370",
    "sg:postcode":"S5 7WP",
    "sg:province":"South Yorkshire",
    "sg:tags":[
        "club"
    ],
    "wof:name":"St Patricks Social Club",
    "wof:placetype":"venue"
},
  "geometry": {"coordinates":[-1.4575190544,53.428188324],"type":"Point"}
}