{
  "type": "Feature",
  "properties": {
    "addr:full":"Unit 12 Chanters Industrial Estate, Tyldesley Old Road, Atherton Manchester Greater Manchester M46 9BE",
    "addr:housenumber":"unit 12",
    "addr:postcode":"m46 9be",
    "addr:street":"Chanters Industrial Estate Tyldesley Old Road",
    "iso:country":"GB",
    "sg:address":"Unit 12 Chanters Industrial Estate, Tyldesley Old Road, Atherton",
    "sg:city":"Manchester",
    "sg:classifiers":[
        {
            "category":"Retail",
            "subcategory":"Auto Repair",
            "type":"Services"
        }
    ],
    "sg:phone":"+44 1942 870900",
    "sg:postcode":"M46 9BE",
    "sg:province":"Greater Manchester",
    "sg:tags":[
        "modification",
        "garage",
        "related"
    ],
    "wof:name":"Chanters Service Centre",
    "wof:placetype":"venue"
},
  "geometry": {"coordinates":[-2.4791460037,53.5202217102],"type":"Point"}
}