{
  "type": "Feature",
  "properties": {
    "addr:full":"33 Freehold Street, Quorn Loughborough Leicestershire LE12 8AY",
    "addr:housenumber":"33",
    "addr:postcode":"le12 8ay",
    "addr:street":"Freehold Street",
    "iso:country":"GB",
    "sg:address":"33 Freehold Street, Quorn",
    "sg:city":"Loughborough",
    "sg:classifiers":[
        {
            "category":"Professional",
            "subcategory":"Art Services",
            "type":"Services"
        }
    ],
    "sg:phone":"+44 1509 263865",
    "sg:postcode":"LE12 8AY",
    "sg:province":"Leicestershire",
    "sg:tags":[
        "model",
        "maker"
    ],
    "wof:name":"Marshall Novelcrafts Ltd.",
    "wof:placetype":"venue"
},
  "geometry": {"coordinates":[-1.163059,52.74633],"type":"Point"}
}