{
  "type": "Feature",
  "properties": {
    "addr:full":"9 Telford Way Hayes Greater London UB4 9SS",
    "addr:housenumber":"9",
    "addr:postcode":"ub4 9ss",
    "addr:street":"Telford Way",
    "iso:country":"GB",
    "sg:address":"9 Telford Way",
    "sg:city":"Hayes",
    "sg:classifiers":[
        {
            "category":"Building & Trades",
            "subcategory":"Construction",
            "type":"Services"
        }
    ],
    "sg:phone":"+44 118 978 6873",
    "sg:postcode":"UB4 9SS",
    "sg:province":"Greater London",
    "sg:tags":[
        "builder"
    ],
    "wof:name":"Baker Stout Ltd",
    "wof:placetype":"venue"
},
  "geometry": {"coordinates":[-0.383425,51.523685],"type":"Point"}
}