{
  "type": "Feature",
  "properties": {
    "addr:full":"Kingsmills Hotel, Damfield Road Inverness Highland IV2 3LP",
    "addr:postcode":"iv2 3lp",
    "addr:street":"Damfield Road",
    "iso:country":"GB",
    "sg:address":"Kingsmills Hotel, Damfield Road",
    "sg:city":"Inverness",
    "sg:classifiers":[
        {
            "category":"Personal",
            "subcategory":"Beauty Salon",
            "type":"Services"
        },
        {
            "category":"Sports & Exercise",
            "subcategory":"Gym",
            "type":"Entertainment"
        }
    ],
    "sg:phone":"+44 1463 243244",
    "sg:postcode":"IV2 3LP",
    "sg:province":"Highland",
    "sg:tags":[
        "club",
        "unisex",
        "health",
        "hairdresser"
    ],
    "wof:name":"Fantasia Health & Beauty Clinic",
    "wof:placetype":"venue"
},
  "geometry": {"coordinates":[-4.2069530487,57.4719924927],"type":"Point"}
}