{
  "type": "Feature",
  "properties": {
    "addr:full":"59-61 Southgate Sleaford Lincolnshire NG34 7SY",
    "addr:housenumber":"59-61",
    "addr:postcode":"ng34 7sy",
    "addr:street":"Southgate Sleaford",
    "iso:country":"GB",
    "sg:address":"59-61 Southgate",
    "sg:city":"Sleaford",
    "sg:classifiers":[
        {
            "category":"Shopping",
            "subcategory":"Thrift Store",
            "type":"Retail Goods"
        }
    ],
    "sg:phone":"+44 1529 304655",
    "sg:postcode":"NG34 7SY",
    "sg:province":"Lincolnshire",
    "sg:tags":[
        "shop",
        "charity"
    ],
    "wof:name":"Help The Aged",
    "wof:placetype":"venue"
},
  "geometry": {"coordinates":[-0.413209,52.998661],"type":"Point"}
}