{
  "type": "Feature",
  "properties": {
    "iso:country":"GB",
    "sg:address":"Station Road",
    "sg:city":"Edenbridge",
    "sg:classifiers":[
        {
            "category":"Building & Trades",
            "subcategory":"Construction",
            "type":"Services"
        }
    ],
    "sg:postcode":"TN8 6HG",
    "sg:province":"East Sussex",
    "sg:tags":[
        "builder"
    ],
    "wof:name":"Doric Building Consultancy",
    "wof:placetype":"venue"
},
  "geometry": {"coordinates":[0.0623609982,51.204246521],"type":"Point"}
}