{
  "type": "Feature",
  "properties": {
    "addr:full":"Station Road, Geldeston Beccles Norfolk NR34 0LS",
    "addr:postcode":"nr34 0ls",
    "addr:street":"Station Road",
    "iso:country":"GB",
    "sg:address":"Station Road, Geldeston",
    "sg:city":"Beccles",
    "sg:classifiers":[
        {
            "category":"Professional",
            "subcategory":"Engineering",
            "type":"Services"
        }
    ],
    "sg:postcode":"NR34 0LS",
    "sg:province":"Norfolk",
    "sg:tags":[
        "precision",
        "engineer"
    ],
    "wof:name":"Godfrey Engineering",
    "wof:placetype":"venue"
},
  "geometry": {"coordinates":[1.5154819489,52.4726066589],"type":"Point"}
}