{
  "type": "Feature",
  "properties": {
    "addr:full":"Heritage House, 48 Chorley New Road Bolton Lancashire BL1 4AP",
    "addr:housenumber":"48",
    "addr:postcode":"bl1 4ap",
    "addr:street":"Chorley New Road",
    "iso:country":"GB",
    "sg:address":"Heritage House, 48 Chorley New Road",
    "sg:city":"Bolton",
    "sg:classifiers":[
        {
            "category":"Communications",
            "subcategory":"Film & Video Production",
            "type":"Services"
        },
        {
            "category":"Professional",
            "subcategory":"Printing & Photocopies",
            "type":"Services"
        }
    ],
    "sg:phone":"+44 1204 371188",
    "sg:postcode":"BL1 4AP",
    "sg:province":"Lancashire",
    "sg:tags":[
        "supplier",
        "duplicating",
        "copying",
        "photocopier"
    ],
    "wof:name":"M & S Reprographics Ltd.",
    "wof:placetype":"venue"
},
  "geometry": {"coordinates":[-2.426594,53.578289],"type":"Point"}
}