{
  "type": "Feature",
  "properties": {
    "addr:full":"72 Alma Road Peterborough Cambridgeshire PE1 3AW",
    "addr:housenumber":"72",
    "addr:postcode":"pe1 3aw",
    "addr:street":"Alma Road",
    "iso:country":"GB",
    "sg:address":"72 Alma Road",
    "sg:city":"Peterborough",
    "sg:classifiers":[
        {
            "category":"Travel",
            "subcategory":"Hotels & Motels",
            "type":"Entertainment"
        }
    ],
    "sg:phone":"+44 1733 349980",
    "sg:postcode":"PE1 3AW",
    "sg:province":"Cambridgeshire",
    "sg:tags":[
        "house",
        "guest"
    ],
    "wof:name":"R Davey",
    "wof:placetype":"venue"
},
  "geometry": {"coordinates":[-0.2435660064,52.5869941711],"type":"Point"}
}