{
  "type": "Feature",
  "properties": {
    "addr:full":"Charlottefield, Ballinluig Pitlochry Perth and Kinross PH9 0NE",
    "addr:postcode":"ph9 0ne",
    "iso:country":"GB",
    "sg:address":"Charlottefield, Ballinluig",
    "sg:city":"Pitlochry",
    "sg:classifiers":[
        {
            "category":"Transit Center",
            "subcategory":"Passenger",
            "type":"Transportation"
        }
    ],
    "sg:phone":"+44 1796 482442",
    "sg:postcode":"PH9 0NE",
    "sg:province":"Perth and Kinross",
    "sg:tags":[
        "taxidermist"
    ],
    "wof:name":"Highland Trophy Taxidermy Services",
    "wof:placetype":"venue"
},
  "geometry": {"coordinates":[-3.6697070599,56.6565742493],"type":"Point"}
}