{
  "type": "Feature",
  "properties": {
    "addr:full":"59 Lichfield Street Stoke-on-trent Staffordshire ST1 3EA",
    "addr:housenumber":"59",
    "addr:postcode":"st1 3ea",
    "addr:street":"Lichfield Street",
    "iso:country":"GB",
    "sg:address":"59 Lichfield Street",
    "sg:city":"Stoke-on-trent",
    "sg:classifiers":[
        {
            "category":"Professional",
            "subcategory":"Art Services",
            "type":"Services"
        }
    ],
    "sg:phone":"+44 1782 855000",
    "sg:postcode":"ST1 3EA",
    "sg:province":"Staffordshire",
    "sg:tags":[
        "photographer"
    ],
    "wof:name":"Olan Mills Photographic Studio",
    "wof:placetype":"venue"
},
  "geometry": {"coordinates":[-2.1738638878,53.0228881836],"type":"Point"}
}