{
  "type": "Feature",
  "properties": {
    "addr:full":"Downsview Road Wantage Berkshire OX12 9FA",
    "addr:postcode":"ox12 9fa",
    "addr:street":"Downsview Road",
    "iso:country":"GB",
    "sg:address":"Downsview Road",
    "sg:city":"Wantage",
    "sg:classifiers":[
        {
            "category":"Retail",
            "subcategory":"Auto Repair",
            "type":"Services"
        }
    ],
    "sg:phone":"+44 1235 768321",
    "sg:postcode":"OX12 9FA",
    "sg:province":"Berkshire",
    "sg:tags":[
        "modification",
        "garage",
        "related"
    ],
    "wof:name":"T A Collins Motor Engineers",
    "wof:placetype":"venue"
},
  "geometry": {"coordinates":[-1.4354510307,51.5993690491],"type":"Point"}
}