{
  "type": "Feature",
  "properties": {
    "iso:country":"GB",
    "sg:address":"55 North Road, Kirkburton",
    "sg:city":"Huddersfield",
    "sg:classifiers":[
        {
            "category":"Professional",
            "subcategory":"Management & Consulting",
            "type":"Services"
        }
    ],
    "sg:postcode":"HD8 0RH",
    "sg:province":"South Yorkshire",
    "sg:tags":[
        "consultant",
        "business"
    ],
    "wof:name":"Quest Management Services",
    "wof:placetype":"venue"
},
  "geometry": {"coordinates":[-1.706081,53.613029],"type":"Point"}
}