{
  "type": "Feature",
  "properties": {
    "addr:full":"93 Rayleigh Road, Eastwood Leigh-on-sea Essex SS9 5UZ",
    "addr:housenumber":"93",
    "addr:postcode":"ss9 5uz",
    "addr:street":"Rayleigh Road",
    "iso:country":"GB",
    "sg:address":"93 Rayleigh Road, Eastwood",
    "sg:city":"Leigh-on-sea",
    "sg:classifiers":[
        {
            "category":"Government",
            "subcategory":"Post Office",
            "type":"Public Place"
        }
    ],
    "sg:phone":"+44 1702 421136",
    "sg:postcode":"SS9 5UZ",
    "sg:province":"Essex",
    "sg:tags":[
        "messenger",
        "courier"
    ],
    "wof:name":"Orbital Express",
    "wof:placetype":"venue"
},
  "geometry": {"coordinates":[0.662261,51.565449],"type":"Point"}
}