{
  "type": "Feature",
  "properties": {
    "addr:full":"Unit 6, Keldholme Lane, Alvaston Derby Derbyshire DE24 0RY",
    "addr:housenumber":"unit 6",
    "addr:postcode":"de24 0ry",
    "addr:street":"Keldholme Lane",
    "iso:country":"GB",
    "sg:address":"Unit 6, Keldholme Lane, Alvaston",
    "sg:city":"Derby",
    "sg:classifiers":[
        {
            "category":"Fast Food",
            "type":"Food & Drink"
        }
    ],
    "sg:phone":"+44 1332 756955",
    "sg:postcode":"DE24 0RY",
    "sg:province":"Derbyshire",
    "sg:tags":[
        "away",
        "take"
    ],
    "wof:name":"Lucky Rainbow",
    "wof:placetype":"venue"
},
  "geometry": {"coordinates":[-1.417174,52.893826],"type":"Point"}
}