{
  "type": "Feature",
  "properties": {
    "addr:full":"Dibbinsdale Road, Bromborough Wirral Merseyside CH63 0HJ",
    "addr:postcode":"ch63 0hj",
    "addr:street":"Dibbinsdale Road",
    "iso:country":"GB",
    "sg:address":"Dibbinsdale Road, Bromborough",
    "sg:city":"Wirral",
    "sg:classifiers":[
        {
            "category":"Travel",
            "subcategory":"Hotels & Motels",
            "type":"Entertainment"
        }
    ],
    "sg:phone":"+44 151 334 5171",
    "sg:postcode":"CH63 0HJ",
    "sg:province":"Merseyside",
    "wof:name":"Dibbinsdale Inn",
    "wof:placetype":"venue"
},
  "geometry": {"coordinates":[-2.9933559895,53.3242988586],"type":"Point"}
}