{
  "type": "Feature",
  "properties": {
    "addr:full":"16 Douglas Road, Hazel Grove Stockport Cheshire SK7 4JE",
    "addr:housenumber":"16",
    "addr:postcode":"sk7 4je",
    "addr:street":"Douglas Road",
    "iso:country":"GB",
    "sg:address":"16 Douglas Road, Hazel Grove",
    "sg:city":"Stockport",
    "sg:classifiers":[
        {
            "category":"Social Services",
            "subcategory":"Child Care",
            "type":"Services"
        },
        {
            "category":"Social Services",
            "subcategory":"Retirement Home",
            "type":"Services"
        }
    ],
    "sg:phone":"+44 161 456 8423",
    "sg:postcode":"SK7 4JE",
    "sg:province":"Cheshire",
    "sg:tags":[
        "children's",
        "residential"
    ],
    "wof:name":"Choices Home For Children Ltd",
    "wof:placetype":"venue"
},
  "geometry": {"coordinates":[-2.1151580811,53.3798484802],"type":"Point"}
}