{
  "type": "Feature",
  "properties": {
    "iso:country":"GB",
    "sg:address":"151 The Fairway",
    "sg:city":"Manchester",
    "sg:classifiers":[
        {
            "category":"Professional",
            "subcategory":"Engineering",
            "type":"Services"
        }
    ],
    "sg:postcode":"M40 3WA",
    "sg:province":"Greater Manchester",
    "sg:tags":[
        "contractor",
        "electrical",
        "engineer"
    ],
    "wof:name":"A R M Electrical & Security",
    "wof:placetype":"venue"
},
  "geometry": {"coordinates":[-2.1689488888,53.5170783997],"type":"Point"}
}