{
  "type": "Feature",
  "properties": {
    "addr:full":"Unit F, Gunnels Wood Park, Gunnels Wood Road Stevenage Hertfordshire SG1 2BH",
    "addr:postcode":"sg1 2bh",
    "addr:street":"Wood Park Gunnels Wood Road",
    "iso:country":"GB",
    "sg:address":"Unit F, Gunnels Wood Park, Gunnels Wood Road",
    "sg:city":"Stevenage",
    "sg:classifiers":[
        {
            "category":"Manufacturing",
            "subcategory":"Tools & Machinery",
            "type":"Manufacturing & Wholesale Goods"
        },
        {
            "category":"Shopping",
            "subcategory":"Jewelry",
            "type":"Retail Goods"
        }
    ],
    "sg:phone":"+44 1438 748758",
    "sg:postcode":"SG1 2BH",
    "sg:province":"Hertfordshire",
    "sg:tags":[
        "manufacture",
        "diamond"
    ],
    "wof:name":"Hertfordshire (Diamond) Products Ltd",
    "wof:placetype":"venue"
},
  "geometry": {"coordinates":[-0.18868,51.905609],"type":"Point"}
}