{
  "type": "Feature",
  "properties": {
    "iso:country":"GB",
    "sg:address":"5 Meadow Lea, Sutton-in-craven",
    "sg:city":"Keighley",
    "sg:classifiers":[
        {
            "category":"Home & Garden",
            "subcategory":"Building Materials",
            "type":"Retail Goods"
        }
    ],
    "sg:postcode":"BD20 8BY",
    "sg:province":"North Yorkshire",
    "sg:tags":[
        "drystone",
        "walling"
    ],
    "wof:name":"Stuart Walker Farm Equipment",
    "wof:placetype":"venue"
},
  "geometry": {"coordinates":[-1.9940949678,53.8977355957],"type":"Point"}
}