{
  "type": "Feature",
  "properties": {
    "addr:full":"45 Valley Road, Lye Stourbridge West Midlands DY9 8JG",
    "addr:housenumber":"45",
    "addr:postcode":"dy9 8jg",
    "addr:street":"Valley Road",
    "iso:country":"GB",
    "sg:address":"45 Valley Road, Lye",
    "sg:city":"Stourbridge",
    "sg:classifiers":[
        {
            "category":"Professional",
            "subcategory":"Engineering",
            "type":"Services"
        }
    ],
    "sg:phone":"+44 1384 423811",
    "sg:postcode":"DY9 8JG",
    "sg:province":"West Midlands",
    "sg:tags":[
        "precision",
        "engineer"
    ],
    "wof:name":"B & E Engineering",
    "wof:placetype":"venue"
},
  "geometry": {"coordinates":[-2.1094501019,52.4594421387],"type":"Point"}
}