{
  "type": "Feature",
  "properties": {
    "iso:country":"GB",
    "sg:address":"559 Leeds Road",
    "sg:city":"Wakefield",
    "sg:classifiers":[
        {
            "category":"Recreation",
            "subcategory":"Fishing",
            "type":"Entertainment"
        }
    ],
    "sg:phone":"+44 1924 835443",
    "sg:postcode":"WF1 2JL",
    "sg:province":"West Yorkshire",
    "sg:tags":[
        "angling"
    ],
    "wof:name":"Outwood Anglers",
    "wof:placetype":"venue"
},
  "geometry": {"coordinates":[-1.5025629997,53.7096824646],"type":"Point"}
}