{
  "type": "Feature",
  "properties": {
    "iso:country":"GB",
    "sg:address":"38 Sandgate Road",
    "sg:city":"Folkestone",
    "sg:classifiers":[
        {
            "category":"Shopping",
            "subcategory":"Jewelry",
            "type":"Retail Goods"
        },
        {
            "category":"Shopping",
            "subcategory":"Comic Books",
            "type":"Retail Goods"
        }
    ],
    "sg:phone":"+44 1303 245410",
    "sg:postcode":"CT20 1DW",
    "sg:province":"Kent",
    "sg:tags":[
        "jeweller",
        "sale",
        "jewellery"
    ],
    "sg:website":"http://www.fhinds.co.uk",
    "wof:name":"F Hinds Ltd.",
    "wof:placetype":"venue"
},
  "geometry": {"coordinates":[1.152741,51.07547],"type":"Point"}
}