{
  "type": "Feature",
  "properties": {
    "iso:country":"GB",
    "sg:address":"17 Irvine Pl",
    "sg:city":"Stirling",
    "sg:classifiers":[
        {
            "category":"Organizations",
            "subcategory":"Non-profit Organization",
            "type":"Services"
        }
    ],
    "sg:phone":"+44 1786 446442",
    "sg:postcode":"FK8 1BZ",
    "sg:province":"Stirling",
    "sg:tags":[
        "organisation",
        "voluntary",
        "charity"
    ],
    "wof:name":"Stirling Initiative Community Forum",
    "wof:placetype":"venue"
},
  "geometry": {"coordinates":[-3.9410450459,56.1221084595],"type":"Point"}
}