{
  "type": "Feature",
  "properties": {
    "iso:country":"GB",
    "sg:address":"Doctors Surgery, 24 Adwick Rd",
    "sg:city":"Mexborough",
    "sg:classifiers":[
        {
            "category":"Health Services",
            "subcategory":"Doctor",
            "type":"Services"
        }
    ],
    "sg:phone":"+44 1709 514443",
    "sg:postcode":"S64 0DB",
    "sg:province":"South Yorkshire",
    "sg:tags":[
        "practitioners"
    ],
    "wof:name":"Nagpal, I C",
    "wof:placetype":"venue"
},
  "geometry": {"coordinates":[-1.299808979,53.4953536987],"type":"Point"}
}