{
  "type": "Feature",
  "properties": {
    "iso:country":"GB",
    "sg:address":"New Inn Lane",
    "sg:city":"Stoke-on-trent",
    "sg:classifiers":[
        {
            "category":"Retail",
            "subcategory":"Auto Repair",
            "type":"Services"
        }
    ],
    "sg:postcode":"ST4 8PS",
    "sg:province":"Staffordshire",
    "sg:tags":[
        "modification",
        "garage"
    ],
    "wof:name":"Cars R Us Trentley Garage",
    "wof:placetype":"venue"
},
  "geometry": {"coordinates":[-2.192899,52.973019],"type":"Point"}
}