{
  "type": "Feature",
  "properties": {
    "addr:full":"Manor Farm, Hermitage Dorchester Dorset DT2 7BB",
    "addr:housenumber":"hermitage",
    "addr:postcode":"dt2 7bb",
    "addr:street":"Manor;Dorchester Dorset",
    "iso:country":"GB",
    "sg:address":"Manor Farm, Hermitage",
    "sg:city":"Dorchester",
    "sg:classifiers":[
        {
            "category":"Farming",
            "subcategory":"Livestock Farm",
            "type":"Manufacturing & Wholesale Goods"
        }
    ],
    "sg:phone":"+44 1963 210230",
    "sg:postcode":"DT2 7BB",
    "sg:province":"Dorset",
    "sg:tags":[
        "others"
    ],
    "wof:name":"E M Mitchell & Sons",
    "wof:placetype":"venue"
},
  "geometry": {"coordinates":[-2.501995,50.860855],"type":"Point"}
}