{
  "type": "Feature",
  "properties": {
    "iso:country":"GB",
    "sg:address":"4 Chapel Close",
    "sg:city":"Dukinfield",
    "sg:classifiers":[
        {
            "category":"Professional",
            "subcategory":"Engineering",
            "type":"Services"
        }
    ],
    "sg:phone":"+44 161 308 2544",
    "sg:postcode":"SK16 4DF",
    "sg:province":"Greater Manchester",
    "wof:name":"D G Back",
    "wof:placetype":"venue"
},
  "geometry": {"coordinates":[-2.083501,53.477955],"type":"Point"}
}