{
  "type": "Feature",
  "properties": {
    "iso:country":"GB",
    "sg:address":"Combe Heights, Woolacombe Rise",
    "sg:city":"Woolacombe",
    "sg:classifiers":[
        {
            "category":"Landmark",
            "subcategory":"Tourist Attraction",
            "type":"Public Place"
        }
    ],
    "sg:phone":"+44 1271 870555",
    "sg:postcode":"EX34 7AS",
    "sg:province":"Devon",
    "sg:tags":[
        "interest"
    ],
    "wof:name":"The National Trust",
    "wof:placetype":"venue"
},
  "geometry": {"coordinates":[-4.2064838409,51.1728668213],"type":"Point"}
}