{
  "type": "Feature",
  "properties": {
    "addr:full":"17 Roeselare Avenue Torpoint Cornwall PL11 2LN",
    "addr:housenumber":"17",
    "addr:postcode":"pl11 2ln",
    "addr:street":"Roeselare Avenue",
    "iso:country":"GB",
    "sg:address":"17 Roeselare Avenue",
    "sg:city":"Torpoint",
    "sg:classifiers":[
        {
            "category":"Military Area",
            "subcategory":"Air Force Base",
            "type":"Public Place"
        }
    ],
    "sg:postcode":"PL11 2LN",
    "sg:province":"Cornwall",
    "sg:tags":[
        "taxi",
        "hire",
        "private"
    ],
    "wof:name":"Kev's Taxis",
    "wof:placetype":"venue"
},
  "geometry": {"coordinates":[-4.203637,50.376129],"type":"Point"}
}