{
  "type": "Feature",
  "properties": {
    "addr:full":"391 Langmuir Rd, Baillieston Glasgow East Dunbartonshire G69 7TU",
    "addr:housenumber":"391",
    "addr:postcode":"g69 7tu",
    "addr:street":"Langmuir Rd",
    "iso:country":"GB",
    "sg:address":"391 Langmuir Rd, Baillieston",
    "sg:city":"Glasgow",
    "sg:classifiers":[
        {
            "category":"Utilities",
            "subcategory":"Refuse",
            "type":"Services"
        }
    ],
    "sg:postcode":"G69 7TU",
    "sg:province":"East Dunbartonshire",
    "sg:tags":[
        "skip",
        "hire"
    ],
    "wof:name":"Bright Skip Hire",
    "wof:placetype":"venue"
},
  "geometry": {"coordinates":[-4.069270134,55.8490943909],"type":"Point"}
}