{
  "type": "Feature",
  "properties": {
    "addr:full":"Holme House, Cumwhinton Carlisle Cumbria CA4 8DH",
    "addr:postcode":"ca4 8dh",
    "addr:street":"Cumwhinton",
    "iso:country":"GB",
    "sg:address":"Holme House, Cumwhinton",
    "sg:city":"Carlisle",
    "sg:classifiers":[
        {
            "category":"Farming",
            "subcategory":"Dairy Farm",
            "type":"Manufacturing & Wholesale Goods"
        }
    ],
    "sg:phone":"+44 1228 561690",
    "sg:postcode":"CA4 8DH",
    "sg:province":"Cumbria",
    "wof:name":"J S Bainbridge & Sons",
    "wof:placetype":"venue"
},
  "geometry": {"coordinates":[-2.853275,54.868359],"type":"Point"}
}