{
  "type": "Feature",
  "properties": {
    "iso:country":"GB",
    "sg:address":"20 Church Street, Whittlesey",
    "sg:city":"Peterborough",
    "sg:classifiers":[
        {
            "category":"Retail",
            "subcategory":"Auto Repair",
            "type":"Services"
        },
        {
            "category":"Sports & Exercise",
            "subcategory":"Tennis Court",
            "type":"Entertainment"
        }
    ],
    "sg:phone":"+44 1733 351448",
    "sg:postcode":"PE7 1DB",
    "sg:province":"Cambridgeshire",
    "sg:tags":[
        "breakdown",
        "garage",
        "modification",
        "recovery"
    ],
    "wof:name":"Csg 24 Hr Recovery Ltd.",
    "wof:placetype":"venue"
},
  "geometry": {"coordinates":[-0.132821,52.554379],"type":"Point"}
}