{
  "type": "Feature",
  "properties": {
    "addr:full":"The Cathedral Office, New Street, Guy Harlings Chelmsford Essex CM1 1AT",
    "addr:postcode":"cm1 1at",
    "addr:street":"New Street Guy Harlings",
    "iso:country":"GB",
    "sg:address":"The Cathedral Office, New Street, Guy Harlings",
    "sg:city":"Chelmsford",
    "sg:classifiers":[
        {
            "category":"Organizations",
            "subcategory":"Non-profit Organization",
            "type":"Services"
        }
    ],
    "sg:phone":"+44 1245 359890",
    "sg:postcode":"CM1 1AT",
    "sg:province":"Essex",
    "sg:tags":[
        "organisation",
        "voluntary",
        "charity"
    ],
    "wof:name":"The Chelmsford Cathedral Festival Ltd.",
    "wof:placetype":"venue"
},
  "geometry": {"coordinates":[0.4734700024,51.7355384827],"type":"Point"}
}