{
  "type": "Feature",
  "properties": {
    "addr:full":"Church Street West Bromwich West Midlands B70 8RP",
    "addr:postcode":"b70 8rp",
    "addr:street":"Church Street",
    "iso:country":"GB",
    "sg:address":"Church Street",
    "sg:city":"West Bromwich",
    "sg:classifiers":[
        {
            "category":"Professional",
            "subcategory":"Employment Agencies",
            "type":"Services"
        },
        {
            "category":"Government",
            "subcategory":"Office",
            "type":"Public Place"
        }
    ],
    "sg:phone":"+44 121 525 2558",
    "sg:postcode":"B70 8RP",
    "sg:province":"West Midlands",
    "sg:tags":[
        "career",
        "guidance",
        "enterprise"
    ],
    "wof:name":"Sandwell Women's Enterprise Development Agency",
    "wof:placetype":"venue"
},
  "geometry": {"coordinates":[-1.9963480234,52.5214347839],"type":"Point"}
}