{
  "type": "Feature",
  "properties": {
    "addr:full":"22 Welsh Road Deeside Flintshire CH5 2RA",
    "addr:housenumber":"22",
    "addr:postcode":"ch5 2ra",
    "addr:street":"Welsh Road",
    "iso:country":"GB",
    "sg:address":"22 Welsh Road",
    "sg:city":"Deeside",
    "sg:classifiers":[
        {
            "category":"Autos & Motor Vehicles",
            "subcategory":"Automobile Sales",
            "type":"Retail Goods"
        }
    ],
    "sg:phone":"+44 1244 811181",
    "sg:postcode":"CH5 2RA",
    "sg:province":"Flintshire",
    "sg:tags":[
        "car"
    ],
    "wof:name":"Lookers North West Ltd.",
    "wof:placetype":"venue"
},
  "geometry": {"coordinates":[-3.0124220848,53.2124977112],"type":"Point"}
}