{
  "type": "Feature",
  "properties": {
    "iso:country":"GB",
    "sg:address":"Eringarth, The Beeches, Armadale",
    "sg:city":"Bathgate",
    "sg:classifiers":[
        {
            "category":"Building & Trades",
            "subcategory":"Plumbing",
            "type":"Services"
        },
        {
            "category":"Building & Trades",
            "subcategory":"Construction",
            "type":"Services"
        }
    ],
    "sg:phone":"+44 1501 730717",
    "sg:postcode":"EH48 3LT",
    "sg:province":"West Lothian",
    "sg:tags":[
        "heating",
        "contractor"
    ],
    "wof:name":"J H Plumbing & Heating Services",
    "wof:placetype":"venue"
},
  "geometry": {"coordinates":[-3.6416289806,55.9007568359],"type":"Point"}
}