{
  "type": "Feature",
  "properties": {
    "addr:full":"Moullions, Humfrey Lane, Boughton Northampton Northamptonshire NN2 8RQ",
    "addr:postcode":"nn2 8rq",
    "addr:street":"Humfrey Lane",
    "iso:country":"GB",
    "sg:address":"Moullions, Humfrey Lane, Boughton",
    "sg:city":"Northampton",
    "sg:classifiers":[
        {
            "category":"Professional",
            "subcategory":"Business Services",
            "type":"Services"
        }
    ],
    "sg:phone":"+44 1604 821244",
    "sg:postcode":"NN2 8RQ",
    "sg:province":"Northamptonshire",
    "sg:tags":[
        "publishers'"
    ],
    "wof:name":"Boullemier Communications Ltd.",
    "wof:placetype":"venue"
},
  "geometry": {"coordinates":[-0.897174,52.285881],"type":"Point"}
}