{
  "type": "Feature",
  "properties": {
    "addr:full":"3 Lister Gate Square, The Broad Marsh Centre Nottingham Nottinghamshire NG1 7LB",
    "addr:housenumber":"3",
    "addr:postcode":"ng1 7lb",
    "addr:street":"Lister Gate Square The",
    "iso:country":"GB",
    "sg:address":"3 Lister Gate Square, The Broad Marsh Centre",
    "sg:city":"Nottingham",
    "sg:classifiers":[
        {
            "category":"Shopping",
            "subcategory":"Department Store",
            "type":"Retail Goods"
        }
    ],
    "sg:phone":"+44 115 958 0524",
    "sg:postcode":"NG1 7LB",
    "sg:province":"Nottinghamshire",
    "sg:tags":[
        "departmental"
    ],
    "sg:website":"http://www.bhs.co.uk",
    "wof:name":"Bhs",
    "wof:placetype":"venue"
},
  "geometry": {"coordinates":[-1.148438,52.951351],"type":"Point"}
}