{
  "type": "Feature",
  "properties": {
    "iso:country":"GB",
    "sg:address":"11 Allerton Road, Mossley Hill",
    "sg:city":"Liverpool",
    "sg:classifiers":[
        {
            "category":"Shopping",
            "subcategory":"Gifts & Souvenirs",
            "type":"Retail Goods"
        }
    ],
    "sg:phone":"+44 151 734 3214",
    "sg:postcode":"L18 1LG",
    "sg:province":"Merseyside",
    "sg:tags":[
        "poster",
        "card"
    ],
    "wof:name":"Forget-Me-Not",
    "wof:placetype":"venue"
},
  "geometry": {"coordinates":[-2.912816,53.388805],"type":"Point"}
}