{
  "type": "Feature",
  "properties": {
    "addr:full":"3 Saville Street Malton North Yorkshire YO17 7LL",
    "addr:housenumber":"3",
    "addr:postcode":"yo17 7ll",
    "addr:street":"Saville Street",
    "iso:country":"GB",
    "sg:address":"3 Saville Street",
    "sg:city":"Malton",
    "sg:classifiers":[
        {
            "category":"Professional",
            "subcategory":"Printing & Photocopies",
            "type":"Services"
        }
    ],
    "sg:postcode":"YO17 7LL",
    "sg:province":"North Yorkshire",
    "sg:tags":[
        "embroiderer"
    ],
    "wof:name":"The Silver Thimble",
    "wof:placetype":"venue"
},
  "geometry": {"coordinates":[-0.7978010178,54.1346626282],"type":"Point"}
}