{
  "type": "Feature",
  "properties": {
    "addr:full":"4 Lacey Grn Wilmslow Cheshire SK9 4BA",
    "addr:housenumber":"4",
    "addr:postcode":"sk9 4ba",
    "addr:street":"Lacey Grn",
    "iso:country":"GB",
    "sg:address":"4 Lacey Grn",
    "sg:city":"Wilmslow",
    "sg:classifiers":[
        {
            "category":"Food & Beverages",
            "subcategory":"Supermarket",
            "type":"Retail Goods"
        }
    ],
    "sg:phone":"+44 1625 524904",
    "sg:postcode":"SK9 4BA",
    "sg:province":"Cheshire",
    "wof:name":"Spar",
    "wof:placetype":"venue"
},
  "geometry": {"coordinates":[-2.229926,53.334206],"type":"Point"}
}