{
  "type": "Feature",
  "properties": {
    "addr:full":"Brick Kiln Lane Solihull West Midlands B91 3LE",
    "addr:postcode":"b91 3le",
    "addr:street":"Brick Kiln Lane",
    "iso:country":"GB",
    "sg:address":"Brick Kiln Lane",
    "sg:city":"Solihull",
    "sg:classifiers":[
        {
            "category":"Arena",
            "subcategory":"Sports Club",
            "type":"Entertainment"
        }
    ],
    "sg:phone":"+44 121 709 2233",
    "sg:postcode":"B91 3LE",
    "sg:province":"West Midlands",
    "wof:name":"Solihull Indoor Bowls Club Ltd",
    "wof:placetype":"venue"
},
  "geometry": {"coordinates":[-1.797499,52.400349],"type":"Point"}
}