{
  "type": "Feature",
  "properties": {
    "iso:country":"GB",
    "sg:address":"13 Castle St",
    "sg:city":"Aberdeen",
    "sg:classifiers":[
        {
            "category":"Cafe",
            "type":"Food & Drink"
        }
    ],
    "sg:phone":"+44 1224 641705",
    "sg:postcode":"AB11 5BQ",
    "sg:province":"Aberdeen City",
    "sg:tags":[
        "tea",
        "room"
    ],
    "wof:name":"Premier Grill",
    "wof:placetype":"venue"
},
  "geometry": {"coordinates":[-2.086923,57.148697],"type":"Point"}
}