{
  "type": "Feature",
  "properties": {
    "addr:full":"Swan House, Queens Road Brentwood Essex CM14 4HE",
    "addr:postcode":"cm14 4he",
    "addr:street":"Queens Road",
    "iso:country":"GB",
    "sg:address":"Swan House, Queens Road",
    "sg:city":"Brentwood",
    "sg:classifiers":[
        {
            "category":"Home & Garden",
            "subcategory":"Home Furnishings",
            "type":"Retail Goods"
        }
    ],
    "sg:postcode":"CM14 4HE",
    "sg:province":"Essex",
    "sg:tags":[
        "furnishers",
        "planner",
        "kitchen"
    ],
    "wof:name":"Quote Buster Kitchens",
    "wof:placetype":"venue"
},
  "geometry": {"coordinates":[0.305351,51.61882],"type":"Point"}
}