{
  "type": "Feature",
  "properties": {
    "iso:country":"GB",
    "sg:address":"12 Colehill",
    "sg:city":"Tamworth",
    "sg:classifiers":[
        {
            "category":"Travel",
            "subcategory":"Travel Agent",
            "type":"Entertainment"
        }
    ],
    "sg:phone":"+44 1827 62794",
    "sg:postcode":"B79 7HE",
    "sg:province":"Staffordshire",
    "wof:name":"Wide Horizon Travel Bureau (Tamworth) Ltd.",
    "wof:placetype":"venue"
},
  "geometry": {"coordinates":[-1.692734,52.63377],"type":"Point"}
}