{
  "type": "Feature",
  "properties": {
    "iso:country":"GB",
    "sg:address":"Challacombe, Exmoor",
    "sg:city":"Barnstaple",
    "sg:classifiers":[
        {
            "category":"Bars & Pubs",
            "type":"Food & Drink"
        },
        {
            "category":"Community Center",
            "subcategory":"Social",
            "type":"Public Place"
        }
    ],
    "sg:phone":"+44 1598 763251",
    "sg:postcode":"EX31 4TT",
    "sg:province":"Devon",
    "sg:tags":[
        "pubs",
        "house",
        "inn",
        "activity"
    ],
    "wof:name":"The Black Venus Inn",
    "wof:placetype":"venue"
},
  "geometry": {"coordinates":[-3.8675301075,51.1535186768],"type":"Point"}
}