{
  "type": "Feature",
  "properties": {
    "addr:full":"Unit 2-4 Kingsway, Swansea West Industrial Park Swansea Swansea SA5 4DL",
    "addr:housenumber":"unit 2-4;swansea",
    "addr:postcode":"sa5 4dl",
    "addr:street":"Kingsway;West Industrial Park",
    "iso:country":"GB",
    "sg:address":"Unit 2-4 Kingsway, Swansea West Industrial Park",
    "sg:city":"Swansea",
    "sg:classifiers":[
        {
            "category":"Banks & Credit Unions",
            "subcategory":"Financial Services",
            "type":"Services"
        },
        {
            "category":"Professional",
            "subcategory":"Printing & Photocopies",
            "type":"Services"
        }
    ],
    "sg:phone":"+44 1792 581441",
    "sg:postcode":"SA5 4DL",
    "sg:province":"Swansea",
    "sg:tags":[
        "building",
        "society",
        "duplicating",
        "copying"
    ],
    "wof:name":"Trans Media Technology Ltd.",
    "wof:placetype":"venue"
},
  "geometry": {"coordinates":[-3.9849150181,51.6449050903],"type":"Point"}
}