{
  "type": "Feature",
  "properties": {
    "addr:full":"Llandough Trading Estate, Penarth Road Cardiff Cardiff CF11 8RR",
    "addr:postcode":"cf11 8rr",
    "addr:street":"Penarth Road",
    "iso:country":"GB",
    "sg:address":"Llandough Trading Estate, Penarth Road",
    "sg:city":"Cardiff",
    "sg:classifiers":[
        {
            "category":"Retail",
            "subcategory":"Auto Rental",
            "type":"Services"
        }
    ],
    "sg:phone":"+44 29 2070 5433",
    "sg:postcode":"CF11 8RR",
    "sg:province":"Cardiff",
    "sg:tags":[
        "truck",
        "hire",
        "van"
    ],
    "wof:name":"Ryder's Truck Rental",
    "wof:placetype":"venue"
},
  "geometry": {"coordinates":[-3.2010099888,51.4551200867],"type":"Point"}
}