{
  "type": "Feature",
  "properties": {
    "addr:full":"New Wellington Street, Mill Hill Blackburn Lancashire BB2 4PJ",
    "addr:postcode":"bb2 4pj",
    "addr:street":"Wellington Street",
    "iso:country":"GB",
    "sg:address":"New Wellington Street, Mill Hill",
    "sg:city":"Blackburn",
    "sg:classifiers":[
        {
            "category":"Farming",
            "subcategory":"Fish & Marine Products",
            "type":"Manufacturing & Wholesale Goods"
        },
        {
            "category":"Shopping",
            "subcategory":"Crafts & Fabrics",
            "type":"Retail Goods"
        }
    ],
    "sg:phone":"+44 1254 262431",
    "sg:postcode":"BB2 4PJ",
    "sg:province":"Lancashire",
    "sg:tags":[
        "neting",
        "netting",
        "manufacturer"
    ],
    "sg:website":"http://www.netlon.co.uk",
    "wof:name":"Netlon Ltd.",
    "wof:placetype":"venue"
},
  "geometry": {"coordinates":[-2.5022039413,53.7328987122],"type":"Point"}
}