{
  "type": "Feature",
  "properties": {
    "addr:full":"25 High St, Titchfield Fareham Hampshire PO14 4AQ",
    "addr:housenumber":"25",
    "addr:postcode":"po14 4aq",
    "addr:street":"High St",
    "iso:country":"GB",
    "sg:address":"25 High St, Titchfield",
    "sg:city":"Fareham",
    "sg:classifiers":[
        {
            "category":"Building & Trades",
            "subcategory":"Construction",
            "type":"Services"
        }
    ],
    "sg:phone":"+44 1329 846025",
    "sg:postcode":"PO14 4AQ",
    "sg:province":"Hampshire",
    "sg:tags":[
        "builder"
    ],
    "wof:name":"Creative Building Contracts Ltd",
    "wof:placetype":"venue"
},
  "geometry": {"coordinates":[-1.2345689535,50.8492736816],"type":"Point"}
}