{
  "type": "Feature",
  "properties": {
    "addr:full":"19 Kirk Street, Oldmeldrum Inverurie Aberdeenshire AB51 0DF",
    "addr:housenumber":"19",
    "addr:postcode":"ab51 0df",
    "addr:street":"Kirk Street",
    "iso:country":"GB",
    "sg:address":"19 Kirk Street, Oldmeldrum",
    "sg:city":"Inverurie",
    "sg:classifiers":[
        {
            "category":"Building & Trades",
            "subcategory":"Construction",
            "type":"Services"
        }
    ],
    "sg:phone":"+44 1651 872922",
    "sg:postcode":"AB51 0DF",
    "sg:province":"Aberdeenshire",
    "sg:tags":[
        "joiner",
        "carpenter"
    ],
    "wof:name":"J D Penny Ltd.",
    "wof:placetype":"venue"
},
  "geometry": {"coordinates":[-2.316925,57.334938],"type":"Point"}
}