{
  "type": "Feature",
  "properties": {
    "addr:full":"Colchester Road Colchester Essex CO7 7NP",
    "addr:postcode":"co7 7np",
    "addr:street":"Colchester Road Colchester",
    "iso:country":"GB",
    "sg:address":"Colchester Road",
    "sg:city":"Colchester",
    "sg:classifiers":[
        {
            "category":"Fast Food",
            "type":"Food & Drink"
        },
        {
            "category":"Restaurant",
            "type":"Food & Drink"
        }
    ],
    "sg:phone":"+44 1206 231459",
    "sg:postcode":"CO7 7NP",
    "sg:province":"Essex",
    "sg:tags":[
        "away",
        "take"
    ],
    "wof:name":"Ancient House Brasserie",
    "wof:placetype":"venue"
},
  "geometry": {"coordinates":[1.000072,51.906162],"type":"Point"}
}