{
  "type": "Feature",
  "properties": {
    "addr:full":"Saddledon St Warwick Warwickshire CV35 0SH",
    "addr:postcode":"cv35 0sh",
    "addr:street":"St",
    "iso:country":"GB",
    "sg:address":"Saddledon St",
    "sg:city":"Warwick",
    "sg:classifiers":[
        {
            "category":"Education",
            "subcategory":"School",
            "type":"Public Place"
        }
    ],
    "sg:phone":"+44 1295 680624",
    "sg:postcode":"CV35 0SH",
    "sg:province":"Warwickshire",
    "sg:tags":[
        "local",
        "authority"
    ],
    "wof:name":"Tysoe Pre-School",
    "wof:placetype":"venue"
},
  "geometry": {"coordinates":[-1.504903,52.096073],"type":"Point"}
}