{
  "type": "Feature",
  "properties": {
    "addr:full":"3 Portland Buildings, Commercial Street Pontypool Monmouthshire NP4 6JS",
    "addr:housenumber":"3",
    "addr:postcode":"np4 6js",
    "addr:street":"Portland Buildings Commercial Street",
    "iso:country":"GB",
    "sg:address":"3 Portland Buildings, Commercial Street",
    "sg:city":"Pontypool",
    "sg:classifiers":[
        {
            "category":"Sports & Exercise",
            "subcategory":"Sports Center",
            "type":"Entertainment"
        }
    ],
    "sg:postcode":"NP4 6JS",
    "sg:province":"Monmouthshire",
    "sg:tags":[
        "shop",
        "good"
    ],
    "wof:name":"Michael Larcombe",
    "wof:placetype":"venue"
},
  "geometry": {"coordinates":[-3.04319,51.703087],"type":"Point"}
}