{
  "type": "Feature",
  "properties": {
    "addr:full":"8 Lancelyn Precinct, Spital Rd Wirral Merseyside CH63 9JP",
    "addr:housenumber":"8",
    "addr:postcode":"ch63 9jp",
    "addr:street":"Precinct Spital Rd",
    "iso:country":"GB",
    "sg:address":"8 Lancelyn Precinct, Spital Rd",
    "sg:city":"Wirral",
    "sg:classifiers":[
        {
            "category":"Food & Beverages",
            "subcategory":"Groceries & Convenience Stores",
            "type":"Retail Goods"
        }
    ],
    "sg:phone":"+44 151 334 1879",
    "sg:postcode":"CH63 9JP",
    "sg:province":"Merseyside",
    "wof:name":"Spar 8 Till Late",
    "wof:placetype":"venue"
},
  "geometry": {"coordinates":[-3.004464,53.340343],"type":"Point"}
}