{
  "type": "Feature",
  "properties": {
    "addr:full":"67 Riverdale London Greater London SE13 7ER",
    "addr:housenumber":"67",
    "addr:postcode":"se13 7er",
    "addr:street":"Riverdale",
    "iso:country":"GB",
    "sg:address":"67 Riverdale",
    "sg:city":"London",
    "sg:classifiers":[
        {
            "category":"Food & Beverages",
            "subcategory":"Specialty",
            "type":"Retail Goods"
        }
    ],
    "sg:phone":"+44 20 8297 9559",
    "sg:postcode":"SE13 7ER",
    "sg:province":"Greater London",
    "sg:tags":[
        "product",
        "health"
    ],
    "wof:name":"Holland & Barrett",
    "wof:placetype":"venue"
},
  "geometry": {"coordinates":[0.0961999968,51.4837303162],"type":"Point"}
}