{
  "type": "Feature",
  "properties": {
    "addr:full":"32 Devonshire Place London Greater London W1G 6JL",
    "addr:housenumber":"32",
    "addr:postcode":"w1g 6jl",
    "addr:street":"Devonshire Place",
    "iso:country":"GB",
    "sg:address":"32 Devonshire Place",
    "sg:city":"London",
    "sg:classifiers":[
        {
            "category":"Health Services",
            "subcategory":"Doctor",
            "type":"Services"
        }
    ],
    "sg:phone":"+44 20 7935 0328",
    "sg:postcode":"W1G 6JL",
    "sg:province":"Greater London",
    "sg:tags":[
        "surgeon"
    ],
    "wof:name":"J W P Hazell",
    "wof:placetype":"venue"
},
  "geometry": {"coordinates":[-0.150387004,51.5218009949],"type":"Point"}
}