{
  "type": "Feature",
  "properties": {
    "addr:full":"68 Hart St Southport Lancashire PR8 6BN",
    "addr:housenumber":"68",
    "addr:postcode":"pr8 6bn",
    "addr:street":"Hart St",
    "iso:country":"GB",
    "sg:address":"68 Hart St",
    "sg:city":"Southport",
    "sg:classifiers":[
        {
            "category":"Building & Trades",
            "subcategory":"Construction",
            "type":"Services"
        }
    ],
    "sg:phone":"+44 1704 538538",
    "sg:postcode":"PR8 6BN",
    "sg:province":"Lancashire",
    "sg:tags":[
        "decorator",
        "painter"
    ],
    "wof:name":"The Southport Stripping Co",
    "wof:placetype":"venue"
},
  "geometry": {"coordinates":[-2.9824919701,53.6422042847],"type":"Point"}
}