{
  "type": "Feature",
  "properties": {
    "addr:full":"8 Heathlands Rise Dartford Kent DA1 3HS",
    "addr:housenumber":"8",
    "addr:postcode":"da1 3hs",
    "addr:street":"Heathlands Rise",
    "iso:country":"GB",
    "sg:address":"8 Heathlands Rise",
    "sg:city":"Dartford",
    "sg:classifiers":[
        {
            "category":"Building & Trades",
            "subcategory":"Construction",
            "type":"Services"
        }
    ],
    "sg:phone":"+44 1322 221237",
    "sg:postcode":"DA1 3HS",
    "sg:province":"Kent",
    "sg:tags":[
        "glazier"
    ],
    "wof:name":"Norman Dyer",
    "wof:placetype":"venue"
},
  "geometry": {"coordinates":[0.195365,51.44487],"type":"Point"}
}