{
  "type": "Feature",
  "properties": {
    "addr:full":"Unit 7 Chancel Indust Est, Hickman Av Wolverhampton West Midlands WV1 2UA",
    "addr:housenumber":"unit 7",
    "addr:postcode":"wv1 2ua",
    "addr:street":"Indust;Hickman Av Wolverhampton",
    "iso:country":"GB",
    "sg:address":"Unit 7 Chancel Indust Est, Hickman Av",
    "sg:city":"Wolverhampton",
    "sg:classifiers":[
        {
            "category":"Autos & Motor Vehicles",
            "subcategory":"Auto Supplies",
            "type":"Retail Goods"
        }
    ],
    "sg:phone":"+44 1902 452793",
    "sg:postcode":"WV1 2UA",
    "sg:province":"West Midlands",
    "sg:tags":[
        "component"
    ],
    "wof:name":"Truck Parts Wolverhampton",
    "wof:placetype":"venue"
},
  "geometry": {"coordinates":[-2.1036319733,52.582359314],"type":"Point"}
}