{
  "type": "Feature",
  "properties": {
    "iso:country":"GB",
    "sg:address":"The Collian, Box",
    "sg:city":"Stroud",
    "sg:classifiers":[
        {
            "category":"Personal",
            "type":"Services"
        },
        {
            "category":"Health Services",
            "subcategory":"Health Practitioner",
            "type":"Services"
        }
    ],
    "sg:phone":"+44 1453 836660",
    "sg:postcode":"GL6 9AE",
    "sg:province":"Gloucestershire",
    "sg:tags":[
        "stress",
        "management",
        "hypnotherapists"
    ],
    "wof:name":"Stress Management Consultant",
    "wof:placetype":"venue"
},
  "geometry": {"coordinates":[-2.20786,51.700939],"type":"Point"}
}