{
  "type": "Feature",
  "properties": {
    "addr:full":"29-31 Risborough Road Maidenhead Berkshire SL6 7YT",
    "addr:housenumber":"29-31",
    "addr:postcode":"sl6 7yt",
    "addr:street":"Risborough Road",
    "iso:country":"GB",
    "sg:address":"29-31 Risborough Road",
    "sg:city":"Maidenhead",
    "sg:classifiers":[
        {
            "category":"Government",
            "subcategory":"Office",
            "type":"Public Place"
        }
    ],
    "sg:phone":"+44 1628 670573",
    "sg:postcode":"SL6 7YT",
    "sg:province":"Berkshire",
    "sg:tags":[
        "chamber",
        "commerce"
    ],
    "wof:name":"Maidenhead & District Chamber of Commerce",
    "wof:placetype":"venue"
},
  "geometry": {"coordinates":[-0.725943,51.527267],"type":"Point"}
}