{
  "type": "Feature",
  "properties": {
    "addr:full":"Prospect Gardens, Sutton Howgrave Bedale North Yorkshire DL8 2NS",
    "addr:postcode":"dl8 2ns",
    "addr:street":"Prospect Gardens",
    "iso:country":"GB",
    "sg:address":"Prospect Gardens, Sutton Howgrave",
    "sg:city":"Bedale",
    "sg:classifiers":[
        {
            "category":"Home & Garden",
            "subcategory":"Building Materials",
            "type":"Retail Goods"
        },
        {
            "category":"Building & Trades",
            "subcategory":"Construction",
            "type":"Services"
        }
    ],
    "sg:phone":"+44 1765 640623",
    "sg:postcode":"DL8 2NS",
    "sg:province":"North Yorkshire",
    "sg:tags":[
        "fencing",
        "builder"
    ],
    "wof:name":"A L Phillips Fencing",
    "wof:placetype":"venue"
},
  "geometry": {"coordinates":[-1.5173829794,54.2086105347],"type":"Point"}
}