{
  "type": "Feature",
  "properties": {
    "addr:full":"Units 3 & 4 Manor Way Frome Somerset BA11 4RB",
    "addr:housenumber":"units 3 & 4",
    "addr:postcode":"ba11 4rb",
    "addr:street":"Manor Way",
    "iso:country":"GB",
    "sg:address":"Units 3 & 4 Manor Way",
    "sg:city":"Frome",
    "sg:classifiers":[
        {
            "category":"Shopping",
            "subcategory":"Computers & Home Electronics",
            "type":"Retail Goods"
        }
    ],
    "sg:phone":"+44 1373 451277",
    "sg:postcode":"BA11 4RB",
    "sg:province":"Somerset",
    "sg:tags":[
        "electrical"
    ],
    "wof:name":"Lockwell Lectrics",
    "wof:placetype":"venue"
},
  "geometry": {"coordinates":[-2.32459,51.21991],"type":"Point"}
}