{
  "type": "Feature",
  "properties": {
    "addr:full":"Bridges Bodmin Cornwall PL30 5EF",
    "addr:postcode":"pl30 5ef",
    "iso:country":"GB",
    "sg:address":"Bridges",
    "sg:city":"Bodmin",
    "sg:classifiers":[
        {
            "category":"Place Of Worship",
            "type":"Public Place"
        }
    ],
    "sg:phone":"+44 1726 850222",
    "sg:postcode":"PL30 5EF",
    "sg:province":"Cornwall",
    "wof:name":"Bridges Methodist Church",
    "wof:placetype":"venue"
},
  "geometry": {"coordinates":[-4.74764,50.389511],"type":"Point"}
}