{
  "type": "Feature",
  "properties": {
    "addr:full":"Bentley Lane Walsall West Midlands WS2 7LU",
    "addr:postcode":"ws2 7lu",
    "addr:street":"Bentley Lane",
    "iso:country":"GB",
    "sg:address":"Bentley Lane",
    "sg:city":"Walsall",
    "sg:classifiers":[
        {
            "category":"Education",
            "subcategory":"Special Training",
            "type":"Public Place"
        },
        {
            "category":"Government",
            "subcategory":"Office",
            "type":"Public Place"
        }
    ],
    "sg:phone":"+44 1902 368045",
    "sg:postcode":"WS2 7LU",
    "sg:province":"West Midlands",
    "sg:tags":[
        "school",
        "local"
    ],
    "wof:name":"Old Hall School",
    "wof:placetype":"venue"
},
  "geometry": {"coordinates":[-2.014989,52.598469],"type":"Point"}
}