{
  "type": "Feature",
  "properties": {
    "addr:full":"Waterwells Drive Gloucester Gloucestershire GL2 2AA",
    "addr:postcode":"gl2 2aa",
    "addr:street":"Waterwells Drive",
    "iso:country":"GB",
    "sg:address":"Waterwells Drive",
    "sg:city":"Gloucester",
    "sg:classifiers":[
        {
            "category":"Professional",
            "subcategory":"Printing & Photocopies",
            "type":"Services"
        }
    ],
    "sg:phone":"+44 1452 887000",
    "sg:postcode":"GL2 2AA",
    "sg:province":"Gloucestershire",
    "sg:tags":[
        "printer"
    ],
    "wof:name":"Alpha Colour Printers Ltd.",
    "wof:placetype":"venue"
},
  "geometry": {"coordinates":[-2.276809,51.814121],"type":"Point"}
}