{
  "type": "Feature",
  "properties": {
    "addr:full":"Clay Ho, Penny La Liverpool Merseyside L18 1DG",
    "addr:postcode":"l18 1dg",
    "addr:street":"Clay;La",
    "iso:country":"GB",
    "sg:address":"Clay Ho, Penny La",
    "sg:city":"Liverpool",
    "sg:classifiers":[
        {
            "category":"Shopping",
            "subcategory":"Beauty & Cosmetics",
            "type":"Retail Goods"
        }
    ],
    "sg:phone":"+44 151 722 5151",
    "sg:postcode":"L18 1DG",
    "sg:province":"Merseyside",
    "sg:tags":[
        "product"
    ],
    "wof:name":"Clay Co The",
    "wof:placetype":"venue"
},
  "geometry": {"coordinates":[-2.9784810543,53.4097747803],"type":"Point"}
}