{
  "type": "Feature",
  "properties": {
    "addr:full":"30 St Hildas Mt Leeds West Yorkshire LS9 0BY",
    "addr:housenumber":"30",
    "addr:postcode":"ls9 0by",
    "addr:street":"St Hildas Mt Leeds West",
    "iso:country":"GB",
    "sg:address":"30 St Hildas Mt",
    "sg:city":"Leeds",
    "sg:classifiers":[
        {
            "category":"Food & Beverages",
            "subcategory":"Supermarket",
            "type":"Retail Goods"
        }
    ],
    "sg:postcode":"LS9 0BY",
    "sg:province":"West Yorkshire",
    "wof:name":"Roth,Jasminda,",
    "wof:placetype":"venue"
},
  "geometry": {"coordinates":[-1.5177090168,53.7891044617],"type":"Point"}
}