{
  "type": "Feature",
  "properties": {
    "iso:country":"GB",
    "sg:address":"Borgue",
    "sg:city":"Kirkcudbright",
    "sg:classifiers":[
        {
            "category":"Travel",
            "subcategory":"Hotels & Motels",
            "type":"Entertainment"
        }
    ],
    "sg:postcode":"DG6 4TS",
    "sg:province":"Dumfries and Galloway",
    "sg:tags":[
        "self",
        "catering"
    ],
    "wof:name":"Brighouse Bay Holiday Park",
    "wof:placetype":"venue"
},
  "geometry": {"coordinates":[-4.0511488914,54.8354492188],"type":"Point"}
}