{
  "type": "Feature",
  "properties": {
    "addr:full":"77 Malham Rd, Forest Hill London Greater London SE23 1AH",
    "addr:housenumber":"77",
    "addr:postcode":"se23 1ah",
    "addr:street":"Malham Rd",
    "iso:country":"GB",
    "sg:address":"77 Malham Rd, Forest Hill",
    "sg:city":"London",
    "sg:classifiers":[
        {
            "category":"Wholesale",
            "subcategory":"Medical Equipment & Supplies",
            "type":"Manufacturing & Wholesale Goods"
        }
    ],
    "sg:postcode":"SE23 1AH",
    "sg:province":"Greater London",
    "sg:tags":[
        "hospital"
    ],
    "wof:name":"Howden,Roger A,",
    "wof:placetype":"venue"
},
  "geometry": {"coordinates":[-0.0459790006,51.4430389404],"type":"Point"}
}