{
  "type": "Feature",
  "properties": {
    "iso:country":"GB",
    "sg:address":"Canal Street",
    "sg:city":"Stockport",
    "sg:classifiers":[
        {
            "category":"Wholesale",
            "subcategory":"Construction Materials",
            "type":"Manufacturing & Wholesale Goods"
        }
    ],
    "sg:phone":"+44 161 477 6672",
    "sg:postcode":"SK1 3BZ",
    "sg:province":"Cheshire",
    "sg:tags":[
        "merchant",
        "glass"
    ],
    "wof:name":"Wentworth Glass Co",
    "wof:placetype":"venue"
},
  "geometry": {"coordinates":[-2.1521699429,53.4061584473],"type":"Point"}
}