{
  "type": "Feature",
  "properties": {
    "iso:country":"GB",
    "sg:address":"New Mills Wharf, Hibbert Street, New Mills",
    "sg:city":"High Peak",
    "sg:classifiers":[
        {
            "category":"Autos & Motor Vehicles",
            "subcategory":"Boat Sales",
            "type":"Retail Goods"
        }
    ],
    "sg:phone":"+44 1663 747434",
    "sg:postcode":"SK22 3JJ",
    "sg:province":"Cheshire",
    "sg:tags":[
        "repair",
        "builder"
    ],
    "wof:name":"Narrowboat Salvage & Repair Service",
    "wof:placetype":"venue"
},
  "geometry": {"coordinates":[-2.0021839142,53.3655662537],"type":"Point"}
}