{
  "type": "Feature",
  "properties": {
    "addr:full":"Pool Road Industrial Estate, Pool Road Nuneaton Leicestershire CV10 9AE",
    "addr:postcode":"cv10 9ae",
    "addr:street":"Pool Road Industrial Estate Pool Road",
    "iso:country":"GB",
    "sg:address":"Pool Road Industrial Estate, Pool Road",
    "sg:city":"Nuneaton",
    "sg:classifiers":[
        {
            "category":"Military Area",
            "subcategory":"Air Force Base",
            "type":"Public Place"
        }
    ],
    "sg:postcode":"CV10 9AE",
    "sg:province":"Leicestershire",
    "sg:tags":[
        "taxi",
        "hire",
        "private"
    ],
    "wof:name":"A M Taxi's",
    "wof:placetype":"venue"
},
  "geometry": {"coordinates":[-1.490954,52.527275],"type":"Point"}
}