{
  "type": "Feature",
  "properties": {
    "addr:full":"10-12 Love Lane Pinner Greater London HA5 3EF",
    "addr:housenumber":"10-12",
    "addr:postcode":"ha5 3ef",
    "addr:street":"Love Lane",
    "iso:country":"GB",
    "sg:address":"10-12 Love Lane",
    "sg:city":"Pinner",
    "sg:classifiers":[
        {
            "category":"Professional",
            "subcategory":"Accounting & Tax Preparation",
            "type":"Services"
        }
    ],
    "sg:phone":"+44 20 8429 2959",
    "sg:postcode":"HA5 3EF",
    "sg:province":"Greater London",
    "sg:tags":[
        "accountant",
        "activity"
    ],
    "wof:name":"Lawrence Hurst & Co",
    "wof:placetype":"venue"
},
  "geometry": {"coordinates":[-0.382708,51.595135],"type":"Point"}
}