{
  "type": "Feature",
  "properties": {
    "addr:full":"28 Parsons Green Terr Edinburgh City of Edinburgh EH8 7AF",
    "addr:housenumber":"28",
    "addr:postcode":"eh8 7af",
    "addr:street":"Parsons Green Terr",
    "iso:country":"GB",
    "sg:address":"28 Parsons Green Terr",
    "sg:city":"Edinburgh",
    "sg:classifiers":[
        {
            "category":"Building & Trades",
            "subcategory":"Construction",
            "type":"Services"
        }
    ],
    "sg:phone":"+44 131 659 6491",
    "sg:postcode":"EH8 7AF",
    "sg:province":"City of Edinburgh",
    "sg:tags":[
        "tiling",
        "contractor"
    ],
    "wof:name":"Capital Tiling",
    "wof:placetype":"venue"
},
  "geometry": {"coordinates":[-3.15358,55.954708],"type":"Point"}
}