{
  "type": "Feature",
  "properties": {
    "addr:full":"Northcott Close, Bury Hall Lane Gosport Hampshire PO12 2PP",
    "addr:postcode":"po12 2pp",
    "addr:street":"Northcott Close;Hall Lane",
    "iso:country":"GB",
    "sg:address":"Northcott Close, Bury Hall Lane",
    "sg:city":"Gosport",
    "sg:classifiers":[
        {
            "category":"Health Services",
            "subcategory":"Nursing And Care Facility",
            "type":"Services"
        },
        {
            "category":"Social Services",
            "subcategory":"Retirement Home",
            "type":"Services"
        }
    ],
    "sg:phone":"+44 23 9251 0003",
    "sg:postcode":"PO12 2PP",
    "sg:province":"Hampshire",
    "sg:tags":[
        "residential"
    ],
    "wof:name":"Northcott House",
    "wof:placetype":"venue"
},
  "geometry": {"coordinates":[-1.151245,50.790039],"type":"Point"}
}