{
  "type": "Feature",
  "properties": {
    "iso:country":"GB",
    "sg:address":"Black Bear Bridge, 529 Knutsford Rd",
    "sg:city":"Warrington",
    "sg:classifiers":[
        {
            "category":"Wholesale",
            "subcategory":"Scrap",
            "type":"Manufacturing & Wholesale Goods"
        }
    ],
    "sg:phone":"+44 1925 235283",
    "sg:postcode":"WA4 1HN",
    "sg:province":"Cheshire",
    "sg:tags":[
        "breaker",
        "dismantlers"
    ],
    "wof:name":"Black Bear Spares & Dismantlers",
    "wof:placetype":"venue"
},
  "geometry": {"coordinates":[-2.57139,53.382198],"type":"Point"}
}