{
  "type": "Feature",
  "properties": {
    "addr:full":"Milhaven, Portlethen Aberdeen Aberdeen City AB12 4RJ",
    "addr:postcode":"ab12 4rj",
    "addr:street":"Milhaven",
    "iso:country":"GB",
    "sg:address":"Milhaven, Portlethen",
    "sg:city":"Aberdeen",
    "sg:classifiers":[
        {
            "category":"Building & Trades",
            "subcategory":"Construction",
            "type":"Services"
        }
    ],
    "sg:phone":"+44 1224 781342",
    "sg:postcode":"AB12 4RJ",
    "sg:province":"Aberdeen City",
    "sg:tags":[
        "joiner",
        "carpenter"
    ],
    "wof:name":"Ridgeway Construction Ltd",
    "wof:placetype":"venue"
},
  "geometry": {"coordinates":[-2.137104,57.057838],"type":"Point"}
}