{
  "type": "Feature",
  "properties": {
    "addr:full":"Unit 11, Nuffield Road, Chesterton Cambridge Cambridgeshire CB4 1TF",
    "addr:housenumber":"unit 11",
    "addr:postcode":"cb4 1tf",
    "addr:street":"Nuffield Road",
    "iso:country":"GB",
    "sg:address":"Unit 11, Nuffield Road, Chesterton",
    "sg:city":"Cambridge",
    "sg:classifiers":[
        {
            "category":"Retail",
            "subcategory":"Auto Repair",
            "type":"Services"
        }
    ],
    "sg:postcode":"CB4 1TF",
    "sg:province":"Cambridgeshire",
    "sg:tags":[
        "body",
        "car"
    ],
    "wof:name":"R J Tyrer",
    "wof:placetype":"venue"
},
  "geometry": {"coordinates":[0.1502580047,52.225063324],"type":"Point"}
}