{
  "type": "Feature",
  "properties": {
    "iso:country":"GB",
    "sg:address":"28 Cannon Street, Bedminster",
    "sg:city":"Bristol",
    "sg:classifiers":[
        {
            "category":"Professional",
            "subcategory":"Lawyer & Legal Services",
            "type":"Services"
        }
    ],
    "sg:phone":"+44 117 963 5261",
    "sg:postcode":"BS3 1BN",
    "sg:province":"City of Bristol",
    "sg:tags":[
        "solicitor"
    ],
    "wof:name":"Bradford & Co",
    "wof:placetype":"venue"
},
  "geometry": {"coordinates":[-2.601125,51.441326],"type":"Point"}
}