{
  "type": "Feature",
  "properties": {
    "addr:full":"7 Jubilee Terrace Ryton Tyne and Wear NE40 4HL",
    "addr:housenumber":"7",
    "addr:postcode":"ne40 4hl",
    "addr:street":"Jubilee Terrace",
    "iso:country":"GB",
    "sg:address":"7 Jubilee Terrace",
    "sg:city":"Ryton",
    "sg:classifiers":[
        {
            "category":"Retail",
            "subcategory":"Veterinary Services",
            "type":"Services"
        },
        {
            "category":"Organizations",
            "subcategory":"Non-profit Organization",
            "type":"Services"
        }
    ],
    "sg:phone":"+44 191 413 6706",
    "sg:postcode":"NE40 4HL",
    "sg:province":"Tyne and Wear",
    "sg:tags":[
        "organisation",
        "welfare",
        "animal",
        "activity"
    ],
    "wof:name":"Tyne Veterinary Clinic",
    "wof:placetype":"venue"
},
  "geometry": {"coordinates":[-1.790724,54.965351],"type":"Point"}
}