{
  "type": "Feature",
  "properties": {
    "iso:country":"GB",
    "sg:address":"35a St Georges Terrace, Jesmond",
    "sg:city":"Newcastle-upon-tyne",
    "sg:classifiers":[
        {
            "category":"Restaurant",
            "type":"Food & Drink"
        },
        {
            "category":"Cafe",
            "type":"Food & Drink"
        }
    ],
    "sg:phone":"+44 191 281 6874",
    "sg:postcode":"NE2 2SU",
    "sg:province":"Tyne and Wear",
    "sg:tags":[
        "tea",
        "-",
        "room",
        "spanish"
    ],
    "wof:name":"The Willow Tree",
    "wof:placetype":"venue"
},
  "geometry": {"coordinates":[-1.6067199707,54.9921722412],"type":"Point"}
}