{
  "type": "Feature",
  "properties": {
    "addr:full":"Glynteg, Whitemill Carmarthen Carmarthenshire SA32 7EN",
    "addr:postcode":"sa32 7en",
    "addr:street":"Whitemill;Carmarthenshire",
    "iso:country":"GB",
    "sg:address":"Glynteg, Whitemill",
    "sg:city":"Carmarthen",
    "sg:classifiers":[
        {
            "category":"Shopping",
            "subcategory":"Computers & Home Electronics",
            "type":"Retail Goods"
        }
    ],
    "sg:phone":"+44 1267 290566",
    "sg:postcode":"SA32 7EN",
    "sg:province":"Carmarthenshire",
    "sg:tags":[
        "aerial",
        "television",
        "radio"
    ],
    "wof:name":"Dyfed Aerials & Satellite Services",
    "wof:placetype":"venue"
},
  "geometry": {"coordinates":[-4.2320690155,51.8703117371],"type":"Point"}
}