{
  "type": "Feature",
  "properties": {
    "addr:full":"11 Blind Lane, New Silksworth Sunderland Tyne and Wear SR3 1AT",
    "addr:housenumber":"11",
    "addr:postcode":"sr3 1at",
    "addr:street":"Blind Lane",
    "iso:country":"GB",
    "sg:address":"11 Blind Lane, New Silksworth",
    "sg:city":"Sunderland",
    "sg:classifiers":[
        {
            "category":"Shopping",
            "subcategory":"News",
            "type":"Retail Goods"
        }
    ],
    "sg:phone":"+44 191 521 0551",
    "sg:postcode":"SR3 1AT",
    "sg:province":"Tyne and Wear",
    "sg:tags":[
        "newsagent"
    ],
    "wof:name":"P Wightman",
    "wof:placetype":"venue"
},
  "geometry": {"coordinates":[-1.40088,54.873447],"type":"Point"}
}