{
  "type": "Feature",
  "properties": {
    "addr:full":"Unit 5 Acorn Factory Units, Acton Place Industrial Estate Sudbury Essex CO10 0BB",
    "addr:housenumber":"unit 5;units",
    "addr:postcode":"co10 0bb",
    "addr:street":"Acorn Factory;Place Industrial Estate",
    "iso:country":"GB",
    "sg:address":"Unit 5 Acorn Factory Units, Acton Place Industrial Estate",
    "sg:city":"Sudbury",
    "sg:classifiers":[
        {
            "category":"Professional",
            "subcategory":"Art Services",
            "type":"Services"
        }
    ],
    "sg:phone":"+44 1787 312397",
    "sg:postcode":"CO10 0BB",
    "sg:province":"Essex",
    "sg:tags":[
        "graphic",
        "designer"
    ],
    "wof:name":"J S Graphic Arts",
    "wof:placetype":"venue"
},
  "geometry": {"coordinates":[0.7343900204,52.0386047363],"type":"Point"}
}