{
  "type": "Feature",
  "properties": {
    "addr:full":"24 Cudham Lane North Orpington Kent BR6 6BZ",
    "addr:housenumber":"24",
    "addr:postcode":"br6 6bz",
    "addr:street":"Cudham Lane North Orpington",
    "iso:country":"GB",
    "sg:address":"24 Cudham Lane North",
    "sg:city":"Orpington",
    "sg:classifiers":[
        {
            "category":"Building & Trades",
            "subcategory":"Construction",
            "type":"Services"
        }
    ],
    "sg:phone":"+44 1689 850208",
    "sg:postcode":"BR6 6BZ",
    "sg:province":"Kent",
    "sg:tags":[
        "joiner",
        "carpenter"
    ],
    "wof:name":"David Graty",
    "wof:placetype":"venue"
},
  "geometry": {"coordinates":[0.081113,51.341408],"type":"Point"}
}