{
  "type": "Feature",
  "properties": {
    "iso:country":"GB",
    "sg:address":"365 Romford Road",
    "sg:city":"London",
    "sg:classifiers":[
        {
            "category":"Travel",
            "subcategory":"Hotels & Motels",
            "type":"Entertainment"
        }
    ],
    "sg:phone":"+44 20 8534 8586",
    "sg:postcode":"E7 8AA",
    "sg:province":"Greater London",
    "wof:name":"Hartley Hotel",
    "wof:placetype":"venue"
},
  "geometry": {"coordinates":[0.03069,51.547031],"type":"Point"}
}