{
  "type": "Feature",
  "properties": {
    "iso:country":"GB",
    "sg:address":"Network House, Basing View",
    "sg:city":"Basingstoke",
    "sg:classifiers":[
        {
            "category":"Professional",
            "subcategory":"Employment Agencies",
            "type":"Services"
        }
    ],
    "sg:phone":"+44 1252 846250",
    "sg:postcode":"RG21 4HG",
    "sg:province":"Hampshire",
    "sg:tags":[
        "consultant"
    ],
    "wof:name":"Progressive Recruitment Ltd.",
    "wof:placetype":"venue"
},
  "geometry": {"coordinates":[-1.0735419989,51.2688407898],"type":"Point"}
}