{
  "type": "Feature",
  "properties": {
    "addr:full":"6 Wellingborough Road, Mears Ashby Northampton Northamptonshire NN6 0DZ",
    "addr:housenumber":"6",
    "addr:postcode":"nn6 0dz",
    "addr:street":"Wellingborough Road",
    "iso:country":"GB",
    "sg:address":"6 Wellingborough Road, Mears Ashby",
    "sg:city":"Northampton",
    "sg:classifiers":[
        {
            "category":"Professional",
            "subcategory":"Management & Consulting",
            "type":"Services"
        }
    ],
    "sg:phone":"+44 1604 810630",
    "sg:postcode":"NN6 0DZ",
    "sg:province":"Northamptonshire",
    "sg:tags":[
        "consultant",
        "business"
    ],
    "wof:name":"Global Development Services",
    "wof:placetype":"venue"
},
  "geometry": {"coordinates":[-0.7474470139,52.2685775757],"type":"Point"}
}