{
  "type": "Feature",
  "properties": {
    "iso:country":"GB",
    "sg:address":"High Hyton Farm, Bootle",
    "sg:city":"Millom",
    "sg:classifiers":[
        {
            "category":"Farming",
            "subcategory":"Livestock Farm",
            "type":"Manufacturing & Wholesale Goods"
        }
    ],
    "sg:postcode":"LA19 5XJ",
    "sg:province":"Cumbria",
    "sg:tags":[
        "others"
    ],
    "wof:name":"T L Sharp",
    "wof:placetype":"venue"
},
  "geometry": {"coordinates":[-3.372381,54.282368],"type":"Point"}
}