{
  "type": "Feature",
  "properties": {
    "addr:full":"1 Belfield Crescent Liverpool Merseyside L36 5TR",
    "addr:housenumber":"1",
    "addr:postcode":"l36 5tr",
    "addr:street":"Belfield Crescent",
    "iso:country":"GB",
    "sg:address":"1 Belfield Crescent",
    "sg:city":"Liverpool",
    "sg:classifiers":[
        {
            "category":"Building & Trades",
            "subcategory":"Cleaning & Sanitation",
            "type":"Services"
        }
    ],
    "sg:postcode":"L36 5TR",
    "sg:province":"Merseyside",
    "sg:tags":[
        "dry",
        "control",
        "damp",
        "rot"
    ],
    "wof:name":"Britannia Property Preservation",
    "wof:placetype":"venue"
},
  "geometry": {"coordinates":[-2.8416171074,53.4050788879],"type":"Point"}
}