{
  "type": "Feature",
  "properties": {
    "addr:full":"Island House Tamworth Staffordshire B79 7GN",
    "addr:postcode":"b79 7gn",
    "addr:street":"Staffordshire",
    "iso:country":"GB",
    "sg:address":"Island House",
    "sg:city":"Tamworth",
    "sg:classifiers":[
        {
            "category":"Building & Trades",
            "subcategory":"Construction",
            "type":"Services"
        }
    ],
    "sg:phone":"+44 1827 61634",
    "sg:postcode":"B79 7GN",
    "sg:province":"Staffordshire",
    "sg:tags":[
        "builder"
    ],
    "wof:name":"R B Williams (Building Contractor) Ltd.",
    "wof:placetype":"venue"
},
  "geometry": {"coordinates":[-1.6876840591,52.6340942383],"type":"Point"}
}