{
  "type": "Feature",
  "properties": {
    "iso:country":"GB",
    "sg:address":"266 Heigham Street",
    "sg:city":"Norwich",
    "sg:classifiers":[
        {
            "category":"Personal",
            "subcategory":"Barber",
            "type":"Services"
        }
    ],
    "sg:phone":"+44 1603 622523",
    "sg:postcode":"NR2 4LQ",
    "sg:province":"Norfolk",
    "sg:tags":[
        "men's",
        "hairdresser"
    ],
    "wof:name":"Upper Cuts Gents Hairdressing",
    "wof:placetype":"venue"
},
  "geometry": {"coordinates":[1.278571,52.64027],"type":"Point"}
}