{
  "type": "Feature",
  "properties": {
    "iso:country":"GB",
    "sg:address":"192 Piccadilly",
    "sg:city":"London",
    "sg:classifiers":[
        {
            "category":"Manufacturing",
            "subcategory":"Textiles",
            "type":"Manufacturing & Wholesale Goods"
        }
    ],
    "sg:postcode":"W1J 9ET",
    "sg:province":"Greater London",
    "sg:tags":[
        "knitwear"
    ],
    "wof:name":"Peal,N,& Co Ltd",
    "wof:placetype":"venue"
},
  "geometry": {"coordinates":[-0.135579,51.50946],"type":"Point"}
}