{
  "type": "Feature",
  "properties": {
    "addr:full":"Junction Road Eastbourne East Sussex BN21 3QY",
    "addr:postcode":"bn21 3qy",
    "addr:street":"Junction Road",
    "iso:country":"GB",
    "sg:address":"Junction Road",
    "sg:city":"Eastbourne",
    "sg:classifiers":[
        {
            "category":"Parking",
            "type":"Transportation"
        }
    ],
    "sg:phone":"+44 20 7499 7050",
    "sg:postcode":"BN21 3QY",
    "sg:province":"East Sussex",
    "sg:tags":[
        "car",
        "park"
    ],
    "wof:name":"Ncp",
    "wof:placetype":"venue"
},
  "geometry": {"coordinates":[0.284224987,50.7701644897],"type":"Point"}
}