{
  "type": "Feature",
  "properties": {
    "addr:full":"Vicarage, 84 Hunningley La Barnsley South Yorkshire S70 3DT",
    "addr:housenumber":"84",
    "addr:postcode":"s70 3dt",
    "addr:street":"Hunningley La Barnsley South",
    "iso:country":"GB",
    "sg:address":"Vicarage, 84 Hunningley La",
    "sg:city":"Barnsley",
    "sg:classifiers":[
        {
            "category":"Place Of Worship",
            "type":"Public Place"
        }
    ],
    "sg:phone":"+44 1226 203906",
    "sg:postcode":"S70 3DT",
    "sg:province":"South Yorkshire",
    "wof:name":"St Andrews C of E Church",
    "wof:placetype":"venue"
},
  "geometry": {"coordinates":[-1.4847379923,53.5531921387],"type":"Point"}
}