{
  "type": "Feature",
  "properties": {
    "iso:country":"GB",
    "sg:address":"15 Leicester Street, Bulkington",
    "sg:city":"Nuneaton",
    "sg:classifiers":[
        {
            "category":"Banks & Credit Unions",
            "subcategory":"Financial Services",
            "type":"Services"
        }
    ],
    "sg:phone":"+44 24 7631 9180",
    "sg:postcode":"CV12 9NQ",
    "sg:province":"Warwickshire",
    "sg:tags":[
        "building",
        "society"
    ],
    "wof:name":"Coventry Building Society",
    "wof:placetype":"venue"
},
  "geometry": {"coordinates":[-1.424209,52.476128],"type":"Point"}
}