{
  "type": "Feature",
  "properties": {
    "addr:full":"39-41 North Road, Islington London Greater London N7 9DP",
    "addr:housenumber":"39-41",
    "addr:postcode":"n7 9dp",
    "addr:street":"North Road",
    "iso:country":"GB",
    "sg:address":"39-41 North Road, Islington",
    "sg:city":"London",
    "sg:classifiers":[
        {
            "category":"Wholesale",
            "subcategory":"Books, Periodicals, & Newspapers",
            "type":"Manufacturing & Wholesale Goods"
        }
    ],
    "sg:phone":"+44 20 7607 0517",
    "sg:postcode":"N7 9DP",
    "sg:province":"Greater London",
    "sg:tags":[
        "publishing"
    ],
    "wof:name":"Pen Press Publishers Ltd.",
    "wof:placetype":"venue"
},
  "geometry": {"coordinates":[-0.120551,51.549191],"type":"Point"}
}