{
  "type": "Feature",
  "properties": {
    "iso:country":"GB",
    "sg:address":"Pelham Road",
    "sg:city":"Seaford",
    "sg:classifiers":[
        {
            "category":"Travel",
            "subcategory":"Hotels & Motels",
            "type":"Entertainment"
        }
    ],
    "sg:postcode":"BN25 1ES",
    "sg:province":"East Sussex",
    "sg:tags":[
        "house",
        "guest"
    ],
    "wof:name":"Bentley Guest House",
    "wof:placetype":"venue"
},
  "geometry": {"coordinates":[0.0998940021,50.7718315125],"type":"Point"}
}