{
  "type": "Feature",
  "properties": {
    "iso:country":"GB",
    "sg:address":"Stanley St, Killamarsh",
    "sg:city":"Sheffield",
    "sg:classifiers":[
        {
            "category":"Food & Beverages",
            "subcategory":"Supermarket",
            "type":"Retail Goods"
        }
    ],
    "sg:phone":"+44 114 247 2412",
    "sg:postcode":"S21 1EL",
    "sg:province":"Derbyshire",
    "wof:name":"Kwik Save Foodstores",
    "wof:placetype":"venue"
},
  "geometry": {"coordinates":[-1.313054,53.326721],"type":"Point"}
}