{
  "type": "Feature",
  "properties": {
    "iso:country":"GB",
    "sg:address":"29 Hyde Road",
    "sg:city":"Paignton",
    "sg:classifiers":[
        {
            "category":"Restaurant",
            "type":"Food & Drink"
        }
    ],
    "sg:phone":"+44 1803 522544",
    "sg:postcode":"TQ4 5BP",
    "sg:province":"Devon",
    "wof:name":"Backstage Bistro",
    "wof:placetype":"venue"
},
  "geometry": {"coordinates":[-3.5660068989,50.4372520447],"type":"Point"}
}