{
  "type": "Feature",
  "properties": {
    "iso:country":"GB",
    "sg:address":"828 Kingstanding Road",
    "sg:city":"Birmingham",
    "sg:classifiers":[
        {
            "category":"Retail",
            "subcategory":"Veterinary Services",
            "type":"Services"
        }
    ],
    "sg:phone":"+44 121 355 3305",
    "sg:postcode":"B44 9RT",
    "sg:province":"West Midlands",
    "sg:tags":[
        "surgeon",
        "activity"
    ],
    "wof:name":"RODERICK LYDON",
    "wof:placetype":"venue"
},
  "geometry": {"coordinates":[-1.883279,52.556988],"type":"Point"}
}