{
  "type": "Feature",
  "properties": {
    "iso:country":"GB",
    "sg:address":"10 Maiden La",
    "sg:city":"Stamford",
    "sg:classifiers":[
        {
            "category":"Arts & Performance",
            "subcategory":"Art Gallery",
            "type":"Entertainment"
        }
    ],
    "sg:phone":"+44 1780 764074",
    "sg:postcode":"PE9 2AZ",
    "sg:province":"Cambridgeshire",
    "wof:name":"Stamford Artists Gallery & Picture Framing",
    "wof:placetype":"venue"
},
  "geometry": {"coordinates":[-0.476612,52.652088],"type":"Point"}
}