{
  "type": "Feature",
  "properties": {
    "iso:country":"GB",
    "sg:address":"Kennet Holme Farm, Bath Road, Midgham",
    "sg:city":"Reading",
    "sg:classifiers":[
        {
            "category":"Retail",
            "subcategory":"Event Space",
            "type":"Services"
        }
    ],
    "sg:phone":"+44 118 971 4623",
    "sg:postcode":"RG7 5UX",
    "sg:province":"Berkshire",
    "sg:tags":[
        "exhibition",
        "organiser"
    ],
    "wof:name":"The Real Exhibition Co",
    "wof:placetype":"venue"
},
  "geometry": {"coordinates":[-1.204383,51.402229],"type":"Point"}
}