{
  "type": "Feature",
  "properties": {
    "addr:full":"Church Street, Slaidburn Clitheroe Lancashire BB7 3ER",
    "addr:postcode":"bb7 3er",
    "addr:street":"Church Street",
    "iso:country":"GB",
    "sg:address":"Church Street, Slaidburn",
    "sg:city":"Clitheroe",
    "sg:classifiers":[
        {
            "category":"Education",
            "subcategory":"School",
            "type":"Public Place"
        }
    ],
    "sg:phone":"+44 1200 446664",
    "sg:postcode":"BB7 3ER",
    "sg:province":"Lancashire",
    "sg:tags":[
        "local",
        "authority"
    ],
    "wof:name":"Slaidburn Brennands Endowed Primary School",
    "wof:placetype":"venue"
},
  "geometry": {"coordinates":[-2.441257,53.966885],"type":"Point"}
}