{
  "type": "Feature",
  "properties": {
    "addr:full":"5 Springhill Road Saffron Walden Essex CB11 4AH",
    "addr:housenumber":"5",
    "addr:postcode":"cb11 4ah",
    "addr:street":"Springhill Road",
    "iso:country":"GB",
    "sg:address":"5 Springhill Road",
    "sg:city":"Saffron Walden",
    "sg:classifiers":[
        {
            "category":"Shopping",
            "subcategory":"Musical Instruments",
            "type":"Retail Goods"
        }
    ],
    "sg:phone":"+44 1799 527743",
    "sg:postcode":"CB11 4AH",
    "sg:province":"Essex",
    "wof:name":"Phase Three Services",
    "wof:placetype":"venue"
},
  "geometry": {"coordinates":[0.2378869951,52.0168151855],"type":"Point"}
}