{
  "type": "Feature",
  "properties": {
    "iso:country":"GB",
    "sg:address":"34 Thistle Centre",
    "sg:city":"Stirling",
    "sg:classifiers":[
        {
            "category":"Health Services",
            "subcategory":"Optometrist",
            "type":"Services"
        }
    ],
    "sg:phone":"+44 1786 449567",
    "sg:postcode":"FK8 2EE",
    "sg:province":"Stirling",
    "sg:tags":[
        "optician"
    ],
    "wof:name":"Smokey J (Three) Ltd.",
    "wof:placetype":"venue"
},
  "geometry": {"coordinates":[-3.9425690174,56.1120605469],"type":"Point"}
}