{
  "type": "Feature",
  "properties": {
    "addr:full":"5 Hardhorn Road Poulton-le-fylde Lancashire FY6 7SR",
    "addr:housenumber":"5",
    "addr:postcode":"fy6 7sr",
    "addr:street":"Hardhorn Road Poulton-Le-Fylde",
    "iso:country":"GB",
    "sg:address":"5 Hardhorn Road",
    "sg:city":"Poulton-le-fylde",
    "sg:classifiers":[
        {
            "category":"Restaurant",
            "type":"Food & Drink"
        }
    ],
    "sg:phone":"+44 1253 884477",
    "sg:postcode":"FY6 7SR",
    "sg:province":"Lancashire",
    "wof:name":"Hi-Life Diners Club",
    "wof:placetype":"venue"
},
  "geometry": {"coordinates":[-2.991928,53.84613],"type":"Point"}
}