{
  "type": "Feature",
  "properties": {
    "addr:full":"Syke Road Wigton Cumbria CA7 9NE",
    "addr:postcode":"ca7 9ne",
    "addr:street":"Syke Road",
    "iso:country":"GB",
    "sg:address":"Syke Road",
    "sg:city":"Wigton",
    "sg:classifiers":[
        {
            "category":"Manufacturing",
            "subcategory":"Metals",
            "type":"Manufacturing & Wholesale Goods"
        },
        {
            "category":"Building & Trades",
            "subcategory":"Construction",
            "type":"Services"
        }
    ],
    "sg:phone":"+44 16973 49073",
    "sg:postcode":"CA7 9NE",
    "sg:province":"Cumbria",
    "sg:tags":[
        "steel",
        "fabricator",
        "builder",
        "erectors"
    ],
    "wof:name":"Richard Douglas",
    "wof:placetype":"venue"
},
  "geometry": {"coordinates":[-3.1559340954,54.8168106079],"type":"Point"}
}