{
  "type": "Feature",
  "properties": {
    "addr:full":"The Evesham Road, Bidford On Avon Alcester Warwickshire B50 4LN",
    "addr:postcode":"avon;b50 4ln",
    "addr:street":"Evesham Road",
    "iso:country":"GB",
    "sg:address":"The Evesham Road, Bidford On Avon",
    "sg:city":"Alcester",
    "sg:classifiers":[
        {
            "category":"Transit Center",
            "subcategory":"Passenger",
            "type":"Transportation"
        }
    ],
    "sg:postcode":"B50 4LN",
    "sg:province":"Warwickshire",
    "sg:tags":[
        "boarding",
        "kennel",
        "catteries"
    ],
    "wof:name":"Cranhill Kennels & Cattery",
    "wof:placetype":"venue"
},
  "geometry": {"coordinates":[-1.860054,52.164616],"type":"Point"}
}