{
  "type": "Feature",
  "properties": {
    "iso:country":"GB",
    "sg:address":"14 Devon Square",
    "sg:city":"Newton Abbot",
    "sg:classifiers":[
        {
            "category":"Professional",
            "subcategory":"Lawyer & Legal Services",
            "type":"Services"
        }
    ],
    "sg:phone":"+44 1626 203366",
    "sg:postcode":"TQ12 2HR",
    "sg:province":"Devon",
    "sg:tags":[
        "solicitor"
    ],
    "wof:name":"Kitsons Hutchings",
    "wof:placetype":"venue"
},
  "geometry": {"coordinates":[-3.603579,50.528797],"type":"Point"}
}