{
  "type": "Feature",
  "properties": {
    "addr:full":"Unit 5 Canal Yard, Shieldhill Road, Glen Village Falkirk Falkirk FK1 2BE",
    "addr:housenumber":"unit 5",
    "addr:postcode":"fk1 2be",
    "addr:street":"Canal Yard Shieldhill Road",
    "iso:country":"GB",
    "sg:address":"Unit 5 Canal Yard, Shieldhill Road, Glen Village",
    "sg:city":"Falkirk",
    "sg:classifiers":[
        {
            "category":"Manufacturing",
            "subcategory":"Buildings",
            "type":"Manufacturing & Wholesale Goods"
        }
    ],
    "sg:phone":"+44 1324 622590",
    "sg:postcode":"FK1 2BE",
    "sg:province":"Falkirk",
    "sg:tags":[
        "shed",
        "greenhouse"
    ],
    "wof:name":"The Shed Centre",
    "wof:placetype":"venue"
},
  "geometry": {"coordinates":[-3.778592,55.987492],"type":"Point"}
}