{
  "type": "Feature",
  "properties": {
    "addr:full":"38 St Stephens Street Norwich Norfolk NR1 3SF",
    "addr:housenumber":"38",
    "addr:postcode":"nr1 3sf",
    "addr:street":"St Stephens Street",
    "iso:country":"GB",
    "sg:address":"38 St Stephens Street",
    "sg:city":"Norwich",
    "sg:classifiers":[
        {
            "category":"Banks & Credit Unions",
            "subcategory":"Bank",
            "type":"Services"
        }
    ],
    "sg:phone":"+44 845 603 3610",
    "sg:postcode":"NR1 3SF",
    "sg:province":"Norfolk",
    "wof:name":"Halifax Plc",
    "wof:placetype":"venue"
},
  "geometry": {"coordinates":[1.2922029495,52.6254272461],"type":"Point"}
}