{
  "type": "Feature",
  "properties": {
    "iso:country":"GB",
    "sg:address":"Southgate, Cuddy Lonning",
    "sg:city":"Wigton",
    "sg:classifiers":[
        {
            "category":"Retail",
            "subcategory":"Driving School",
            "type":"Services"
        }
    ],
    "sg:phone":"+44 16973 45054",
    "sg:postcode":"CA7 0AA",
    "sg:province":"Cumbria",
    "wof:name":"Bryceson School Of Motoring",
    "wof:placetype":"venue"
},
  "geometry": {"coordinates":[-3.181874,54.819988],"type":"Point"}
}