{
  "type": "Feature",
  "properties": {
    "iso:country":"GB",
    "sg:address":"331 Carlton Rd",
    "sg:city":"Worksop",
    "sg:classifiers":[
        {
            "category":"Home & Garden",
            "subcategory":"Building Materials",
            "type":"Retail Goods"
        }
    ],
    "sg:phone":"+44 1909 470370",
    "sg:postcode":"S81 7LA",
    "sg:province":"Nottinghamshire",
    "sg:tags":[
        "brick"
    ],
    "wof:name":"Carlton Fire Surrounds",
    "wof:placetype":"venue"
},
  "geometry": {"coordinates":[-1.121049,53.320545],"type":"Point"}
}