{
  "type": "Feature",
  "properties": {
    "iso:country":"GB",
    "sg:address":"Ellison Terrace, Ellison Place",
    "sg:city":"Newcastle-upon-tyne",
    "sg:classifiers":[
        {
            "category":"Cafe",
            "type":"Food & Drink"
        }
    ],
    "sg:phone":"+44 191 227 4148",
    "sg:postcode":"NE1 8ST",
    "sg:province":"Tyne and Wear",
    "sg:tags":[
        "tea",
        "room"
    ],
    "wof:name":"U N N Commercial Enterprises Ltd.",
    "wof:placetype":"venue"
},
  "geometry": {"coordinates":[-1.608099,54.976265],"type":"Point"}
}