{
  "type": "Feature",
  "properties": {
    "iso:country":"GB",
    "sg:address":"Ford Road",
    "sg:city":"Clacton-on-sea",
    "sg:classifiers":[
        {
            "category":"Health Services",
            "subcategory":"Dentist",
            "type":"Services"
        }
    ],
    "sg:phone":"+44 1255 474942",
    "sg:postcode":"CO15 3DS",
    "sg:province":"Essex",
    "wof:name":"The Ford Road Dental Surgery",
    "wof:placetype":"venue"
},
  "geometry": {"coordinates":[1.142044,51.79314],"type":"Point"}
}