{
  "type": "Feature",
  "properties": {
    "addr:full":"Wardens Farm, Green Lane, Althorne Chelmsford Essex CM3 6BJ",
    "addr:postcode":"cm3 6bj",
    "addr:street":"Green Lane",
    "iso:country":"GB",
    "sg:address":"Wardens Farm, Green Lane, Althorne",
    "sg:city":"Chelmsford",
    "sg:classifiers":[
        {
            "category":"Utilities",
            "subcategory":"Refuse",
            "type":"Services"
        }
    ],
    "sg:phone":"+44 1621 744438",
    "sg:postcode":"CM3 6BJ",
    "sg:province":"Essex",
    "sg:tags":[
        "disposal",
        "waste"
    ],
    "wof:name":"Ashwaste",
    "wof:placetype":"venue"
},
  "geometry": {"coordinates":[0.76038,51.659233],"type":"Point"}
}