{
  "type": "Feature",
  "properties": {
    "addr:full":"Lavender Farm, Main Road, Ford End Chelmsford Essex CM3 1LL",
    "addr:postcode":"cm3 1ll",
    "addr:street":"Main Road",
    "iso:country":"GB",
    "sg:address":"Lavender Farm, Main Road, Ford End",
    "sg:city":"Chelmsford",
    "sg:classifiers":[
        {
            "category":"Farming",
            "subcategory":"Livestock Farm",
            "type":"Manufacturing & Wholesale Goods"
        }
    ],
    "sg:phone":"+44 1245 237218",
    "sg:postcode":"CM3 1LL",
    "sg:province":"Essex",
    "sg:tags":[
        "others"
    ],
    "wof:name":"R G FREEMAN",
    "wof:placetype":"venue"
},
  "geometry": {"coordinates":[0.431581,51.824989],"type":"Point"}
}