{
  "type": "Feature",
  "properties": {
    "addr:full":"6 High Street Swadlincote Derbyshire DE11 8HY",
    "addr:housenumber":"6",
    "addr:postcode":"de11 8hy",
    "addr:street":"High Street",
    "iso:country":"GB",
    "sg:address":"6 High Street",
    "sg:city":"Swadlincote",
    "sg:classifiers":[
        {
            "category":"Food & Beverages",
            "subcategory":"Meat & Fish",
            "type":"Retail Goods"
        }
    ],
    "sg:postcode":"DE11 8HY",
    "sg:province":"Derbyshire",
    "sg:tags":[
        "butcher"
    ],
    "wof:name":"B Hunt",
    "wof:placetype":"venue"
},
  "geometry": {"coordinates":[-1.576694,52.785278],"type":"Point"}
}