{
  "type": "Feature",
  "properties": {
    "iso:country":"GB",
    "sg:address":"Penycoedcae Road, Beddau",
    "sg:city":"Pontypridd",
    "sg:classifiers":[
        {
            "category":"Education",
            "subcategory":"School",
            "type":"Public Place"
        },
        {
            "category":"Organizations",
            "subcategory":"Non-profit Organization",
            "type":"Services"
        }
    ],
    "sg:phone":"+44 1443 203411",
    "sg:postcode":"CF38 2AE",
    "sg:province":"Rhondda, Cynon, Taff",
    "sg:tags":[
        "organisation",
        "local",
        "voluntary",
        "authority",
        "charity"
    ],
    "wof:name":"Bryn Celynnog Comprehensive School",
    "wof:placetype":"venue"
},
  "geometry": {"coordinates":[-3.358221,51.570793],"type":"Point"}
}