{
  "type": "Feature",
  "properties": {
    "addr:full":"4 Bridge Street Salisbury Wiltshire SP1 2LX",
    "addr:housenumber":"4",
    "addr:postcode":"sp1 2lx",
    "addr:street":"Bridge Street",
    "iso:country":"GB",
    "sg:address":"4 Bridge Street",
    "sg:city":"Salisbury",
    "sg:classifiers":[
        {
            "category":"Professional",
            "subcategory":"Lawyer & Legal Services",
            "type":"Services"
        }
    ],
    "sg:phone":"+44 1722 333306",
    "sg:postcode":"SP1 2LX",
    "sg:province":"Wiltshire",
    "sg:tags":[
        "advice",
        "counselling"
    ],
    "wof:name":"The Ombudsman for Estate Agents Co. Ltd.",
    "wof:placetype":"venue"
},
  "geometry": {"coordinates":[-1.7973849773,51.0686531067],"type":"Point"}
}