{
  "type": "Feature",
  "properties": {
    "addr:full":"Little Heath Road, Tilehurst Reading Berkshire RG31 5TY",
    "addr:postcode":"rg31 5ty",
    "addr:street":"Little Heath Road",
    "iso:country":"GB",
    "sg:address":"Little Heath Road, Tilehurst",
    "sg:city":"Reading",
    "sg:classifiers":[
        {
            "category":"Education",
            "subcategory":"School",
            "type":"Public Place"
        },
        {
            "category":"Government",
            "subcategory":"Office",
            "type":"Public Place"
        }
    ],
    "sg:phone":"+44 118 942 7337",
    "sg:postcode":"RG31 5TY",
    "sg:province":"Berkshire",
    "sg:tags":[
        "local",
        "authority"
    ],
    "wof:name":"Little Heath Comprehensive School",
    "wof:placetype":"venue"
},
  "geometry": {"coordinates":[-1.05595,51.458912],"type":"Point"}
}