{
  "type": "Feature",
  "properties": {
    "addr:full":"19 Lonsdale Road Blackpool Lancashire FY1 6EE",
    "addr:housenumber":"19",
    "addr:postcode":"fy1 6ee",
    "addr:street":"Lonsdale Road",
    "iso:country":"GB",
    "sg:address":"19 Lonsdale Road",
    "sg:city":"Blackpool",
    "sg:classifiers":[
        {
            "category":"Travel",
            "subcategory":"Hotels & Motels",
            "type":"Entertainment"
        }
    ],
    "sg:phone":"+44 1253 345807",
    "sg:postcode":"FY1 6EE",
    "sg:province":"Lancashire",
    "wof:name":"Holme Lea Hotel",
    "wof:placetype":"venue"
},
  "geometry": {"coordinates":[-3.0518090725,53.80519104],"type":"Point"}
}