{
  "type": "Feature",
  "properties": {
    "addr:full":"Unit 6 Rosebery Estate London Greater London N17 9SD",
    "addr:housenumber":"unit 6",
    "addr:postcode":"n17 9sd",
    "addr:street":"Rosebery Estate",
    "iso:country":"GB",
    "sg:address":"Unit 6 Rosebery Estate",
    "sg:city":"London",
    "sg:classifiers":[
        {
            "category":"Professional",
            "subcategory":"Accounting & Tax Preparation",
            "type":"Services"
        }
    ],
    "sg:phone":"+44 20 8365 1525",
    "sg:postcode":"N17 9SD",
    "sg:province":"Greater London",
    "sg:tags":[
        "accountant"
    ],
    "wof:name":"Ozlem Ltd.",
    "wof:placetype":"venue"
},
  "geometry": {"coordinates":[-0.061619,51.596657],"type":"Point"}
}