{
  "type": "Feature",
  "properties": {
    "addr:full":"81 Old Church Road London Greater London E4 6ST",
    "addr:housenumber":"81",
    "addr:postcode":"e4 6st",
    "addr:street":"Old Church Road",
    "iso:country":"GB",
    "sg:address":"81 Old Church Road",
    "sg:city":"London",
    "sg:classifiers":[
        {
            "category":"Autos & Motor Vehicles",
            "subcategory":"Automobile Sales",
            "type":"Retail Goods"
        }
    ],
    "sg:phone":"+44 20 8529 1308",
    "sg:postcode":"E4 6ST",
    "sg:province":"Greater London",
    "sg:tags":[
        "car",
        "commercial"
    ],
    "wof:name":"Alexander Motor Co.",
    "wof:placetype":"venue"
},
  "geometry": {"coordinates":[-0.0169830006,51.6196212769],"type":"Point"}
}