{
  "type": "Feature",
  "properties": {
    "addr:full":"15 Anne Close Norwich Norfolk NR7 0PH",
    "addr:housenumber":"15",
    "addr:postcode":"nr7 0ph",
    "addr:street":"Anne Close",
    "iso:country":"GB",
    "sg:address":"15 Anne Close",
    "sg:city":"Norwich",
    "sg:classifiers":[
        {
            "category":"Professional",
            "subcategory":"Detective & Security Services",
            "type":"Services"
        }
    ],
    "sg:phone":"+44 1603 701472",
    "sg:postcode":"NR7 0PH",
    "sg:province":"Norfolk",
    "sg:tags":[
        "activity"
    ],
    "wof:name":"Intacept Security Ltd.",
    "wof:placetype":"venue"
},
  "geometry": {"coordinates":[1.351746,52.636909],"type":"Point"}
}