{
  "type": "Feature",
  "properties": {
    "addr:full":"682 King Street Aberdeen Aberdeen City AB24 1SL",
    "addr:housenumber":"682",
    "addr:postcode":"ab24 1sl",
    "addr:street":"King Street",
    "iso:country":"GB",
    "sg:address":"682 King Street",
    "sg:city":"Aberdeen",
    "sg:classifiers":[
        {
            "category":"Building & Trades",
            "subcategory":"Construction",
            "type":"Services"
        }
    ],
    "sg:phone":"+44 1224 480180",
    "sg:postcode":"AB24 1SL",
    "sg:province":"Aberdeen City",
    "sg:tags":[
        "management"
    ],
    "wof:name":"P D B Construction",
    "wof:placetype":"venue"
},
  "geometry": {"coordinates":[-2.098999,57.167011],"type":"Point"}
}