{
  "type": "Feature",
  "properties": {
    "addr:full":"81a Selwyn Av Richmond Greater London TW9 2HB",
    "addr:housenumber":"81a",
    "addr:postcode":"tw9 2hb",
    "addr:street":"Selwyn Av",
    "iso:country":"GB",
    "sg:address":"81a Selwyn Av",
    "sg:city":"Richmond",
    "sg:classifiers":[
        {
            "category":"Professional",
            "subcategory":"Secretarial Services",
            "type":"Services"
        }
    ],
    "sg:phone":"+44 20 8948 8694",
    "sg:postcode":"TW9 2HB",
    "sg:province":"Greater London",
    "wof:name":"Janice Kendall",
    "wof:placetype":"venue"
},
  "geometry": {"coordinates":[-0.297099,51.46656],"type":"Point"}
}