{
  "type": "Feature",
  "properties": {
    "addr:full":"Wallace House, Dunsop Road, Newton In Bowland Clitheroe Lancashire BB7 3ED",
    "addr:postcode":"bb7 3ed",
    "addr:street":"Dunsop Road",
    "iso:country":"GB",
    "sg:address":"Wallace House, Dunsop Road, Newton In Bowland",
    "sg:city":"Clitheroe",
    "sg:classifiers":[
        {
            "category":"Building & Trades",
            "subcategory":"Construction",
            "type":"Services"
        }
    ],
    "sg:phone":"+44 1200 446385",
    "sg:postcode":"BB7 3ED",
    "sg:province":"Lancashire",
    "sg:tags":[
        "builder"
    ],
    "wof:name":"William Cecil Rhodes",
    "wof:placetype":"venue"
},
  "geometry": {"coordinates":[-2.463099,53.949379],"type":"Point"}
}