{
  "type": "Feature",
  "properties": {
    "addr:full":"Unit 9a, Old Airfield Industrial Estate, Cheddington Lane Tring Buckinghamshire HP23 4QR",
    "addr:housenumber":"unit 9a",
    "addr:postcode":"hp23 4qr",
    "addr:street":"Old Airfield Industrial;Cheddington Lane",
    "iso:country":"GB",
    "sg:address":"Unit 9a, Old Airfield Industrial Estate, Cheddington Lane",
    "sg:city":"Tring",
    "sg:classifiers":[
        {
            "category":"Home & Garden",
            "subcategory":"Garden Supply",
            "type":"Retail Goods"
        }
    ],
    "sg:phone":"+44 1296 662703",
    "sg:postcode":"HP23 4QR",
    "sg:province":"Buckinghamshire",
    "sg:tags":[
        "turfing"
    ],
    "wof:name":"Flux Soils",
    "wof:placetype":"venue"
},
  "geometry": {"coordinates":[-0.6639800072,51.7932701111],"type":"Point"}
}