{
  "type": "Feature",
  "properties": {
    "iso:country":"GB",
    "sg:address":"29 & 31 Kelsall Terrace",
    "sg:city":"Leeds",
    "sg:classifiers":[
        {
            "category":"Building & Trades",
            "subcategory":"Construction",
            "type":"Services"
        }
    ],
    "sg:phone":"+44 113 274 6887",
    "sg:postcode":"LS6 1RD",
    "sg:province":"West Yorkshire",
    "sg:tags":[
        "roofing"
    ],
    "wof:name":"Headingley Roofing",
    "wof:placetype":"venue"
},
  "geometry": {"coordinates":[-1.571211,53.806454],"type":"Point"}
}