{
  "type": "Feature",
  "properties": {
    "addr:full":"380 Hornsey Road London Greater London N19 4HT",
    "addr:housenumber":"380",
    "addr:postcode":"n19 4ht",
    "addr:street":"Hornsey Road",
    "iso:country":"GB",
    "sg:address":"380 Hornsey Road",
    "sg:city":"London",
    "sg:classifiers":[
        {
            "category":"Food & Beverages",
            "subcategory":"Meat & Fish",
            "type":"Retail Goods"
        }
    ],
    "sg:phone":"+44 20 7281 6222",
    "sg:postcode":"N19 4HT",
    "sg:province":"Greater London",
    "sg:tags":[
        "chip"
    ],
    "wof:name":"Ocean Fresh Fish Bar",
    "wof:placetype":"venue"
},
  "geometry": {"coordinates":[-0.1194399968,51.5646934509],"type":"Point"}
}