{
  "type": "Feature",
  "properties": {
    "iso:country":"GB",
    "sg:address":"High Road",
    "sg:city":"Willenhall",
    "sg:classifiers":[
        {
            "category":"Autos & Motor Vehicles",
            "subcategory":"Fuel & Gas Station",
            "type":"Retail Goods"
        }
    ],
    "sg:phone":"+44 1902 605553",
    "sg:postcode":"WV12 4JQ",
    "sg:province":"West Midlands",
    "sg:tags":[
        "petrol",
        "filling"
    ],
    "wof:name":"Lane Head Service Station",
    "wof:placetype":"venue"
},
  "geometry": {"coordinates":[-2.0370700359,52.6014938354],"type":"Point"}
}