{
  "type": "Feature",
  "properties": {
    "addr:full":"101 Maidstone Road Rochester Kent ME1 1RN",
    "addr:housenumber":"101",
    "addr:postcode":"me1 1rn",
    "addr:street":"Maidstone Road Rochester",
    "iso:country":"GB",
    "sg:address":"101 Maidstone Road",
    "sg:city":"Rochester",
    "sg:classifiers":[
        {
            "category":"Shopping",
            "subcategory":"Clothing, Apparel, & Fashions",
            "type":"Retail Goods"
        }
    ],
    "sg:postcode":"ME1 1RN",
    "sg:province":"Kent",
    "sg:tags":[
        "dresswear"
    ],
    "wof:name":"Dotty Dot's",
    "wof:placetype":"venue"
},
  "geometry": {"coordinates":[0.5034649968,51.3839416504],"type":"Point"}
}