{
  "type": "Feature",
  "properties": {
    "iso:country":"GB",
    "sg:address":"1155 Pollockshaws Road",
    "sg:city":"Glasgow",
    "sg:classifiers":[
        {
            "category":"Health Services",
            "subcategory":"Dentist",
            "type":"Services"
        }
    ],
    "sg:phone":"+44 141 632 0047",
    "sg:postcode":"G41 3NG",
    "sg:province":"Glasgow City",
    "wof:name":"F.G Macdonald",
    "wof:placetype":"venue"
},
  "geometry": {"coordinates":[-4.2822289467,55.8300857544],"type":"Point"}
}