{
  "type": "Feature",
  "properties": {
    "addr:full":"102 Copthorne Road Shrewsbury Shropshire SY3 8NA",
    "addr:housenumber":"102",
    "addr:postcode":"sy3 8na",
    "addr:street":"Copthorne Road",
    "iso:country":"GB",
    "sg:address":"102 Copthorne Road",
    "sg:city":"Shrewsbury",
    "sg:classifiers":[
        {
            "category":"Travel",
            "subcategory":"Hotels & Motels",
            "type":"Entertainment"
        }
    ],
    "sg:phone":"+44 1743 232208",
    "sg:postcode":"SY3 8NA",
    "sg:province":"Shropshire",
    "sg:tags":[
        "house",
        "guest"
    ],
    "wof:name":"Jasmine Guest House",
    "wof:placetype":"venue"
},
  "geometry": {"coordinates":[-2.77088,52.710831],"type":"Point"}
}