{
  "type": "Feature",
  "properties": {
    "iso:country":"GB",
    "sg:address":"52 Bunkers Drive, Cotton End",
    "sg:city":"Bedford",
    "sg:classifiers":[
        {
            "category":"Building & Trades",
            "subcategory":"Construction",
            "type":"Services"
        }
    ],
    "sg:postcode":"MK45 3AT",
    "sg:province":"Bedfordshire",
    "sg:tags":[
        "contractor",
        "paving",
        "driveway"
    ],
    "wof:name":"Simpkins Garden Services",
    "wof:placetype":"venue"
},
  "geometry": {"coordinates":[-0.4129230082,52.0937385559],"type":"Point"}
}