{
  "type": "Feature",
  "properties": {
    "iso:country":"GB",
    "sg:address":"40 Anchor Road",
    "sg:city":"Rochester",
    "sg:classifiers":[
        {
            "category":"Bakery",
            "type":"Food & Drink"
        }
    ],
    "sg:postcode":"ME1 2PR",
    "sg:province":"Kent",
    "sg:tags":[
        "cake",
        "maker"
    ],
    "wof:name":"Sheila's Cake Artistry",
    "wof:placetype":"venue"
},
  "geometry": {"coordinates":[0.505296,51.366928],"type":"Point"}
}