{
  "type": "Feature",
  "properties": {
    "iso:country":"GB",
    "sg:address":"Unit 17 Walkers Road, Moons Moat North Industrial Estate",
    "sg:city":"Redditch",
    "sg:classifiers":[
        {
            "category":"Professional",
            "subcategory":"Engineering",
            "type":"Services"
        }
    ],
    "sg:phone":"+44 1527 591079",
    "sg:postcode":"B98 9HE",
    "sg:province":"Warwickshire",
    "wof:name":"Mike Hadden",
    "wof:placetype":"venue"
},
  "geometry": {"coordinates":[-1.895059,52.315647],"type":"Point"}
}