{
  "type": "Feature",
  "properties": {
    "iso:country":"GB",
    "sg:address":"24 Woodlands Close",
    "sg:city":"Maidstone",
    "sg:classifiers":[
        {
            "category":"Communications",
            "type":"Services"
        }
    ],
    "sg:phone":"+44 1622 751578",
    "sg:postcode":"ME14 2EX",
    "sg:province":"Kent",
    "sg:tags":[
        "audio-visual"
    ],
    "wof:name":"Heselwood Audio Service",
    "wof:placetype":"venue"
},
  "geometry": {"coordinates":[0.5307660103,51.2880249023],"type":"Point"}
}