{
  "type": "Feature",
  "properties": {
    "addr:full":"248 Oxford Gardens Stafford Staffordshire ST16 3JG",
    "addr:housenumber":"248",
    "addr:postcode":"st16 3jg",
    "addr:street":"Oxford Gardens",
    "iso:country":"GB",
    "sg:address":"248 Oxford Gardens",
    "sg:city":"Stafford",
    "sg:classifiers":[
        {
            "category":"Personal",
            "subcategory":"Beauty Salon",
            "type":"Services"
        }
    ],
    "sg:phone":"+44 1785 226692",
    "sg:postcode":"ST16 3JG",
    "sg:province":"Staffordshire",
    "sg:tags":[
        "unisex",
        "hairdresser"
    ],
    "wof:name":"New Image",
    "wof:placetype":"venue"
},
  "geometry": {"coordinates":[-2.1093571186,52.8188323975],"type":"Point"}
}