{
  "type": "Feature",
  "properties": {
    "iso:country":"GB",
    "sg:address":"801 Bath Road, Cranford",
    "sg:city":"Hounslow",
    "sg:classifiers":[
        {
            "category":"Autos & Motor Vehicles",
            "subcategory":"Motorcycle Sales",
            "type":"Retail Goods"
        },
        {
            "category":"Government",
            "subcategory":"Post Office",
            "type":"Public Place"
        }
    ],
    "sg:phone":"+44 20 8897 0555",
    "sg:postcode":"TW5 9UJ",
    "sg:province":"Greater London",
    "sg:tags":[
        "chauffeur",
        "car",
        "messenger",
        "driven",
        "courier"
    ],
    "wof:name":"Hugh Damien Executive Chauffeur Drive Ltd.",
    "wof:placetype":"venue"
},
  "geometry": {"coordinates":[-0.414541,51.48085],"type":"Point"}
}