{
  "type": "Feature",
  "properties": {
    "addr:full":"58 Fore Street Kingsbridge Devon TQ7 1NY",
    "addr:housenumber":"58",
    "addr:postcode":"tq7 1ny",
    "addr:street":"Fore Street",
    "iso:country":"GB",
    "sg:address":"58 Fore Street",
    "sg:city":"Kingsbridge",
    "sg:classifiers":[
        {
            "category":"Shopping",
            "subcategory":"Clothing, Apparel, & Fashions",
            "type":"Retail Goods"
        }
    ],
    "sg:phone":"+44 1548 852207",
    "sg:postcode":"TQ7 1NY",
    "sg:province":"Devon",
    "sg:tags":[
        "ladieswear"
    ],
    "wof:name":"Brights",
    "wof:placetype":"venue"
},
  "geometry": {"coordinates":[-3.778152,50.285713],"type":"Point"}
}