{
  "type": "Feature",
  "properties": {
    "iso:country":"GB",
    "sg:address":"62 Grosvenor Street",
    "sg:city":"London",
    "sg:classifiers":[
        {
            "category":"Organizations",
            "subcategory":"Non-profit Organization",
            "type":"Services"
        }
    ],
    "sg:postcode":"W1K 3JF",
    "sg:province":"Greater London",
    "sg:tags":[
        "organisation",
        "voluntary",
        "charity"
    ],
    "wof:name":"The British Technion Society",
    "wof:placetype":"venue"
},
  "geometry": {"coordinates":[-0.144879,51.511589],"type":"Point"}
}