{
  "type": "Feature",
  "properties": {
    "addr:full":"10c West Road, Ponteland Newcastle-upon-tyne Northumberland NE20 9SU",
    "addr:housenumber":"10c",
    "addr:postcode":"ne20 9su",
    "addr:street":"West Road",
    "iso:country":"GB",
    "sg:address":"10c West Road, Ponteland",
    "sg:city":"Newcastle-upon-tyne",
    "sg:classifiers":[
        {
            "category":"Home & Garden",
            "subcategory":"Home Furnishings",
            "type":"Retail Goods"
        }
    ],
    "sg:postcode":"NE20 9SU",
    "sg:province":"Northumberland",
    "sg:tags":[
        "furnishers",
        "planner",
        "kitchen"
    ],
    "wof:name":"Das Kitchen Co",
    "wof:placetype":"venue"
},
  "geometry": {"coordinates":[-1.7463799715,55.0496101379],"type":"Point"}
}