{
  "type": "Feature",
  "properties": {
    "addr:full":"3 Groesffordd, Waungilwen Llandysul Carmarthenshire SA44 5YQ",
    "addr:housenumber":"3",
    "addr:postcode":"sa44 5yq",
    "addr:street":"Groesffordd Waungilwen",
    "iso:country":"GB",
    "sg:address":"3 Groesffordd, Waungilwen",
    "sg:city":"Llandysul",
    "sg:classifiers":[
        {
            "category":"Autos & Motor Vehicles",
            "subcategory":"Auto Supplies",
            "type":"Retail Goods"
        }
    ],
    "sg:postcode":"SA44 5YQ",
    "sg:province":"Carmarthenshire",
    "sg:tags":[
        "tyre"
    ],
    "wof:name":"Kev's Mobile Tyres",
    "wof:placetype":"venue"
},
  "geometry": {"coordinates":[-4.3840517998,52.047580719],"type":"Point"}
}