{
  "type": "Feature",
  "properties": {
    "addr:full":"Middle Farm, Northill Road, Cople Bedford Bedfordshire MK44 3UA",
    "addr:postcode":"mk44 3ua",
    "addr:street":"Middle;Northill Road",
    "iso:country":"GB",
    "sg:address":"Middle Farm, Northill Road, Cople",
    "sg:city":"Bedford",
    "sg:classifiers":[
        {
            "category":"Farming",
            "subcategory":"Livestock Farm",
            "type":"Manufacturing & Wholesale Goods"
        }
    ],
    "sg:phone":"+44 1234 838237",
    "sg:postcode":"MK44 3UA",
    "sg:province":"Bedfordshire",
    "sg:tags":[
        "others"
    ],
    "wof:name":"New Farm Partnership",
    "wof:placetype":"venue"
},
  "geometry": {"coordinates":[-0.389146,52.128078],"type":"Point"}
}