{
  "type": "Feature",
  "properties": {
    "addr:full":"Willow House Uckfield East Sussex TN22 3AA",
    "addr:postcode":"tn22 3aa",
    "addr:street":"Uckfield",
    "iso:country":"GB",
    "sg:address":"Willow House",
    "sg:city":"Uckfield",
    "sg:classifiers":[
        {
            "category":"Professional",
            "subcategory":"Computer Services",
            "type":"Services"
        }
    ],
    "sg:postcode":"TN22 3AA",
    "sg:province":"East Sussex",
    "sg:tags":[
        "system",
        "software"
    ],
    "wof:name":"Synergetix",
    "wof:placetype":"venue"
},
  "geometry": {"coordinates":[0.071218,51.012474],"type":"Point"}
}