{
  "type": "Feature",
  "properties": {
    "addr:full":"Scarne Industrial Estate Launceston Cornwall PL15 9HS",
    "addr:postcode":"pl15 9hs",
    "addr:street":"Estate Launceston",
    "iso:country":"GB",
    "sg:address":"Scarne Industrial Estate",
    "sg:city":"Launceston",
    "sg:classifiers":[
        {
            "category":"Shopping",
            "type":"Retail Goods"
        }
    ],
    "sg:phone":"+44 1566 772387",
    "sg:postcode":"PL15 9HS",
    "sg:province":"Cornwall",
    "sg:tags":[
        "merchant"
    ],
    "wof:name":"Wd & N C Farmers Ltd",
    "wof:placetype":"venue"
},
  "geometry": {"coordinates":[-4.363344,50.636707],"type":"Point"}
}