{
  "type": "Feature",
  "properties": {
    "iso:country":"GB",
    "sg:address":"Deerbolt, Bowes Road",
    "sg:city":"Barnard Castle",
    "sg:classifiers":[
        {
            "category":"Government",
            "subcategory":"Office",
            "type":"Public Place"
        }
    ],
    "sg:phone":"+44 1833 633200",
    "sg:postcode":"DL12 9BG",
    "sg:province":"Cumbria",
    "sg:tags":[
        "local"
    ],
    "wof:name":"H M Young Offenders Institution",
    "wof:placetype":"venue"
},
  "geometry": {"coordinates":[-1.930334,54.543018],"type":"Point"}
}