{
  "type": "Feature",
  "properties": {
    "iso:country":"GB",
    "sg:address":"179 Replingham Rd",
    "sg:city":"Wandsworth",
    "sg:classifiers":[
        {
            "category":"Professional",
            "subcategory":"Employment Agencies",
            "type":"Services"
        }
    ],
    "sg:phone":"+44 20 8870 7784",
    "sg:postcode":"SW18 5LY",
    "sg:province":"Greater London",
    "sg:tags":[
        "consultant"
    ],
    "wof:name":"Scot-Baker Agency",
    "wof:placetype":"venue"
},
  "geometry": {"coordinates":[-0.200511,51.445728],"type":"Point"}
}