{
  "type": "Feature",
  "properties": {
    "addr:full":"Quayside Ho, 110 Quayside Newcastle Upon Tyne Tyne and Wear NE1 3DU",
    "addr:housenumber":"110",
    "addr:postcode":"ne1 3du",
    "addr:street":"Quayside",
    "iso:country":"GB",
    "sg:address":"Quayside Ho, 110 Quayside",
    "sg:city":"Newcastle Upon Tyne",
    "sg:classifiers":[
        {
            "category":"Building & Trades",
            "subcategory":"Cleaning & Sanitation",
            "type":"Services"
        }
    ],
    "sg:phone":"+44 191 261 1582",
    "sg:postcode":"NE1 3DU",
    "sg:province":"Tyne and Wear",
    "sg:tags":[
        "facility"
    ],
    "wof:name":"Nationwide Europa Facility Management Ltd",
    "wof:placetype":"venue"
},
  "geometry": {"coordinates":[-1.60119,54.96991],"type":"Point"}
}