{
  "type": "Feature",
  "properties": {
    "iso:country":"GB",
    "sg:address":"Hargreaves House, Plumbe Street",
    "sg:city":"Burnley",
    "sg:classifiers":[
        {
            "category":"Professional",
            "subcategory":"Lawyer & Legal Services",
            "type":"Services"
        }
    ],
    "sg:postcode":"BB11 3AB",
    "sg:province":"Lancashire",
    "sg:tags":[
        "advice",
        "counselling"
    ],
    "wof:name":"Burnley Staying Put Project",
    "wof:placetype":"venue"
},
  "geometry": {"coordinates":[-2.236088,53.788677],"type":"Point"}
}