{
  "type": "Feature",
  "properties": {
    "addr:full":"7 Lower Bore St Fowey Cornwall PL23 1LA",
    "addr:housenumber":"7",
    "addr:postcode":"pl23 1la",
    "addr:street":"Lower Bore St",
    "iso:country":"GB",
    "sg:address":"7 Lower Bore St",
    "sg:city":"Fowey",
    "sg:classifiers":[
        {
            "category":"Organizations",
            "subcategory":"Non-profit Organization",
            "type":"Services"
        }
    ],
    "sg:phone":"+44 1208 77760",
    "sg:postcode":"PL23 1LA",
    "sg:province":"Cornwall",
    "sg:tags":[
        "organisation",
        "voluntary",
        "charity"
    ],
    "wof:name":"Mencap",
    "wof:placetype":"venue"
},
  "geometry": {"coordinates":[-4.639648,50.336273],"type":"Point"}
}