{
  "type": "Feature",
  "properties": {
    "addr:full":"44 Canons Road Ware Hertfordshire SG12 0BT",
    "addr:housenumber":"44",
    "addr:postcode":"sg12 0bt",
    "addr:street":"Canons Road Ware",
    "iso:country":"GB",
    "sg:address":"44 Canons Road",
    "sg:city":"Ware",
    "sg:classifiers":[
        {
            "category":"Building & Trades",
            "subcategory":"Construction",
            "type":"Services"
        }
    ],
    "sg:phone":"+44 1920 484323",
    "sg:postcode":"SG12 0BT",
    "sg:province":"Hertfordshire",
    "sg:tags":[
        "decorator",
        "painter"
    ],
    "wof:name":"D M G Painters & Decorators",
    "wof:placetype":"venue"
},
  "geometry": {"coordinates":[-0.036669,51.815533],"type":"Point"}
}