{
  "type": "Feature",
  "properties": {
    "iso:country":"GB",
    "sg:address":"31 Evenlode Close, Grove",
    "sg:city":"Wantage",
    "sg:classifiers":[
        {
            "category":"Taxi",
            "type":"Transportation"
        },
        {
            "category":"Military Area",
            "subcategory":"Air Force Base",
            "type":"Public Place"
        }
    ],
    "sg:phone":"+44 1235 762035",
    "sg:postcode":"OX12 0NW",
    "sg:province":"Berkshire",
    "sg:tags":[
        "hire",
        "private"
    ],
    "wof:name":"Evenlode Taxis",
    "wof:placetype":"venue"
},
  "geometry": {"coordinates":[-1.427477,51.609455],"type":"Point"}
}