{
  "type": "Feature",
  "properties": {
    "addr:full":"41 Church Street, Clifton Shefford Bedfordshire SG17 5ET",
    "addr:housenumber":"41",
    "addr:postcode":"sg17 5et",
    "addr:street":"Church Street",
    "iso:country":"GB",
    "sg:address":"41 Church Street, Clifton",
    "sg:city":"Shefford",
    "sg:classifiers":[
        {
            "category":"Shopping",
            "subcategory":"Stationery & Office Supplies",
            "type":"Retail Goods"
        }
    ],
    "sg:phone":"+44 1462 811485",
    "sg:postcode":"SG17 5ET",
    "sg:province":"Bedfordshire",
    "sg:tags":[
        "equipment",
        "school"
    ],
    "wof:name":"Pippin Products",
    "wof:placetype":"venue"
},
  "geometry": {"coordinates":[-0.301419,52.039288],"type":"Point"}
}