{
  "type": "Feature",
  "properties": {
    "addr:full":"2 Buttrills Road Barry The Vale of Glamorgan CF62 8EF",
    "addr:housenumber":"2",
    "addr:postcode":"cf62 8ef",
    "addr:street":"Buttrills Road;Vale",
    "iso:country":"GB",
    "sg:address":"2 Buttrills Road",
    "sg:city":"Barry",
    "sg:classifiers":[
        {
            "category":"Wholesale",
            "subcategory":"Scrap",
            "type":"Manufacturing & Wholesale Goods"
        },
        {
            "category":"Wholesale",
            "subcategory":"Auto Parts",
            "type":"Manufacturing & Wholesale Goods"
        }
    ],
    "sg:postcode":"CF62 8EF",
    "sg:province":"The Vale of Glamorgan",
    "sg:tags":[
        "car",
        "waste",
        "metal",
        "breaker"
    ],
    "wof:name":"WOODHAM BROTHERS LTD",
    "wof:placetype":"venue"
},
  "geometry": {"coordinates":[-3.280887,51.409363],"type":"Point"}
}