{
  "type": "Feature",
  "properties": {
    "iso:country":"GB",
    "sg:address":"C/o Norman Alexander & Co, 5th Floor, Grosvenor Gdns. House",
    "sg:city":"London",
    "sg:classifiers":[
        {
            "category":"Shopping",
            "subcategory":"Gifts & Souvenirs",
            "type":"Retail Goods"
        }
    ],
    "sg:phone":"+44 20 8642 1116",
    "sg:postcode":"SW1W 0BS",
    "sg:province":"Greater London",
    "sg:tags":[
        "giftware"
    ],
    "wof:name":"Noble Giftware Ltd",
    "wof:placetype":"venue"
},
  "geometry": {"coordinates":[-0.14536,51.497089],"type":"Point"}
}