{
  "type": "Feature",
  "properties": {
    "iso:country":"GB",
    "sg:address":"25 Wharton Av",
    "sg:city":"Thornton Cleveleys",
    "sg:classifiers":[
        {
            "category":"Building & Trades",
            "subcategory":"Construction",
            "type":"Services"
        }
    ],
    "sg:phone":"+44 1253 865269",
    "sg:postcode":"FY5 4DQ",
    "sg:province":"Lancashire",
    "sg:tags":[
        "builder"
    ],
    "wof:name":"Kingfisher Developments",
    "wof:placetype":"venue"
},
  "geometry": {"coordinates":[-2.9966259003,53.8728370667],"type":"Point"}
}