{
  "type": "Feature",
  "properties": {
    "addr:full":"297-301 Station Road Harrow Greater London HA1 2TA",
    "addr:housenumber":"297-301",
    "addr:postcode":"ha1 2ta",
    "addr:street":"Station Road",
    "iso:country":"GB",
    "sg:address":"297-301 Station Road",
    "sg:city":"Harrow",
    "sg:classifiers":[
        {
            "category":"Shopping",
            "subcategory":"Pharmacy",
            "type":"Retail Goods"
        }
    ],
    "sg:phone":"+44 20 8424 8413",
    "sg:postcode":"HA1 2TA",
    "sg:province":"Greater London",
    "sg:tags":[
        "store",
        "drug",
        "outlet"
    ],
    "sg:website":"http://www.superdrug.com",
    "wof:name":"Superdrug Stores plc",
    "wof:placetype":"venue"
},
  "geometry": {"coordinates":[-0.333131,51.581898],"type":"Point"}
}