{
  "type": "Feature",
  "properties": {
    "iso:country":"GB",
    "sg:address":"9 Valley Road, Chandlers Ford",
    "sg:city":"Southampton",
    "sg:classifiers":[
        {
            "category":"Health Services",
            "subcategory":"Nursing And Care Facility",
            "type":"Services"
        }
    ],
    "sg:phone":"+44 23 8025 2547",
    "sg:postcode":"SO53 1GQ",
    "sg:province":"Hampshire",
    "sg:tags":[
        "home"
    ],
    "wof:name":"High Clear Home",
    "wof:placetype":"venue"
},
  "geometry": {"coordinates":[-1.3833999634,50.9912796021],"type":"Point"}
}