{
  "type": "Feature",
  "properties": {
    "iso:country":"GB",
    "sg:address":"Croxteth Hall, Croxteth Country Park",
    "sg:city":"Liverpool",
    "sg:classifiers":[
        {
            "category":"Organizations",
            "subcategory":"Non-profit Organization",
            "type":"Services"
        }
    ],
    "sg:phone":"+44 151 228 8966",
    "sg:postcode":"L12 0HB",
    "sg:province":"Merseyside",
    "sg:tags":[
        "organisation",
        "voluntary",
        "charity"
    ],
    "wof:name":"Btcv",
    "wof:placetype":"venue"
},
  "geometry": {"coordinates":[-2.899656,53.446369],"type":"Point"}
}