{
  "type": "Feature",
  "properties": {
    "addr:full":"180-182 Soho Hill Birmingham West Midlands B19 1AG",
    "addr:housenumber":"180-182",
    "addr:postcode":"b19 1ag",
    "addr:street":"Soho Hill",
    "iso:country":"GB",
    "sg:address":"180-182 Soho Hill",
    "sg:city":"Birmingham",
    "sg:classifiers":[
        {
            "category":"Professional",
            "subcategory":"Lawyer & Legal Services",
            "type":"Services"
        }
    ],
    "sg:phone":"+44 121 554 4900",
    "sg:postcode":"B19 1AG",
    "sg:province":"West Midlands",
    "sg:tags":[
        "solicitor"
    ],
    "wof:name":"Maurice Andrews Solicitors",
    "wof:placetype":"venue"
},
  "geometry": {"coordinates":[-1.92112,52.500031],"type":"Point"}
}