{
  "type": "Feature",
  "properties": {
    "iso:country":"GB",
    "sg:address":"2 Portsmouth Road, Cosham",
    "sg:city":"Portsmouth",
    "sg:classifiers":[
        {
            "category":"Real Estate",
            "subcategory":"Surveying",
            "type":"Services"
        },
        {
            "category":"Real Estate",
            "subcategory":"Real Estate Agent",
            "type":"Services"
        }
    ],
    "sg:phone":"+44 23 9237 7800",
    "sg:postcode":"PO6 2SG",
    "sg:province":"Hampshire",
    "sg:tags":[
        "surveyor",
        "valuer"
    ],
    "wof:name":"Holloway Iliffe & Mitchell",
    "wof:placetype":"venue"
},
  "geometry": {"coordinates":[-1.068323,50.840782],"type":"Point"}
}