{
  "type": "Feature",
  "properties": {
    "iso:country":"GB",
    "sg:address":"Bradshaws Farm, Smithy Lane, Stalmine",
    "sg:city":"Poulton Le Fylde",
    "sg:classifiers":[
        {
            "category":"Farming",
            "subcategory":"Dairy Farm",
            "type":"Manufacturing & Wholesale Goods"
        }
    ],
    "sg:phone":"+44 1253 700837",
    "sg:postcode":"FY6 0LE",
    "sg:province":"Lancashire",
    "wof:name":"Henderson's Farm & Dairy",
    "wof:placetype":"venue"
},
  "geometry": {"coordinates":[-2.95252,53.900791],"type":"Point"}
}