{
  "type": "Feature",
  "properties": {
    "iso:country":"GB",
    "sg:address":"Spey Avenue",
    "sg:city":"Grantown-on-spey",
    "sg:classifiers":[
        {
            "category":"Autos & Motor Vehicles",
            "subcategory":"Fuel & Gas Station",
            "type":"Retail Goods"
        }
    ],
    "sg:phone":"+44 1479 872964",
    "sg:postcode":"PH26 3EJ",
    "sg:province":"Highland",
    "sg:tags":[
        "petrol",
        "filling"
    ],
    "wof:name":"Alistair L Grant",
    "wof:placetype":"venue"
},
  "geometry": {"coordinates":[-3.609004,57.328876],"type":"Point"}
}