{
  "type": "Feature",
  "properties": {
    "addr:full":"Hart Warren Hartlepool Durham TS24 9QF",
    "addr:postcode":"ts24 9qf",
    "addr:street":"Hart",
    "iso:country":"GB",
    "sg:address":"Hart Warren",
    "sg:city":"Hartlepool",
    "sg:classifiers":[
        {
            "category":"Sports & Exercise",
            "subcategory":"Golf",
            "type":"Entertainment"
        }
    ],
    "sg:phone":"+44 1429 274398",
    "sg:postcode":"TS24 9QF",
    "sg:province":"Durham",
    "sg:tags":[
        "club",
        "course"
    ],
    "wof:name":"Hartlepool Golf Club Ltd.",
    "wof:placetype":"venue"
},
  "geometry": {"coordinates":[-1.2256280184,54.7009811401],"type":"Point"}
}