{
  "type": "Feature",
  "properties": {
    "iso:country":"GB",
    "sg:address":"7 Dunvant Square",
    "sg:city":"Swansea",
    "sg:classifiers":[
        {
            "category":"Fast Food",
            "type":"Food & Drink"
        }
    ],
    "sg:phone":"+44 1792 297908",
    "sg:postcode":"SA2 7TA",
    "sg:province":"Swansea",
    "sg:tags":[
        "away",
        "take"
    ],
    "wof:name":"Full Moon Cantonese Cuisine",
    "wof:placetype":"venue"
},
  "geometry": {"coordinates":[-4.0338711739,51.6257781982],"type":"Point"}
}