{
  "type": "Feature",
  "properties": {
    "iso:country":"GB",
    "sg:address":"32 High Street",
    "sg:city":"Forres",
    "sg:classifiers":[
        {
            "category":"Shopping",
            "subcategory":"Bicycles & Sporting Goods",
            "type":"Retail Goods"
        }
    ],
    "sg:postcode":"IV36 1DB",
    "sg:province":"Moray",
    "sg:tags":[
        "cycle",
        "accessory"
    ],
    "wof:name":"Stuarts Cycles",
    "wof:placetype":"venue"
},
  "geometry": {"coordinates":[-3.611035,57.611031],"type":"Point"}
}