{
  "type": "Feature",
  "properties": {
    "addr:full":"12 North Rd Blackburn Lancashire BB1 1PR",
    "addr:housenumber":"12",
    "addr:postcode":"bb1 1pr",
    "addr:street":"North Rd",
    "iso:country":"GB",
    "sg:address":"12 North Rd",
    "sg:city":"Blackburn",
    "sg:classifiers":[
        {
            "category":"Home & Garden",
            "subcategory":"Household Appliances",
            "type":"Retail Goods"
        }
    ],
    "sg:postcode":"BB1 1PR",
    "sg:province":"Lancashire",
    "sg:tags":[
        "domestic",
        "oven",
        "microwave"
    ],
    "wof:name":"Oldale,K,",
    "wof:placetype":"venue"
},
  "geometry": {"coordinates":[-2.4578750134,53.745929718],"type":"Point"}
}