{
  "type": "Feature",
  "properties": {
    "addr:full":"48-50 Milton Road Westcliff-on-sea Essex SS0 7JX",
    "addr:housenumber":"48-50",
    "addr:postcode":"ss0 7jx",
    "addr:street":"Milton Road",
    "iso:country":"GB",
    "sg:address":"48-50 Milton Road",
    "sg:city":"Westcliff-on-sea",
    "sg:classifiers":[
        {
            "category":"Professional",
            "subcategory":"Printing & Photocopies",
            "type":"Services"
        }
    ],
    "sg:phone":"+44 1702 391887",
    "sg:postcode":"SS0 7JX",
    "sg:province":"Essex",
    "sg:tags":[
        "process",
        "screen",
        "printer"
    ],
    "wof:name":"Phoenix Promotional Merchandise Ltd.",
    "wof:placetype":"venue"
},
  "geometry": {"coordinates":[0.701023,51.539284],"type":"Point"}
}