{
  "type": "Feature",
  "properties": {
    "iso:country":"GB",
    "sg:address":"Pontathel, Bronllys",
    "sg:city":"Brecon",
    "sg:classifiers":[
        {
            "category":"Travel",
            "subcategory":"Hotels & Motels",
            "type":"Entertainment"
        }
    ],
    "sg:postcode":"LD3 0RY",
    "sg:province":"Powys",
    "sg:tags":[
        "house",
        "guest"
    ],
    "wof:name":"McLean,Edmund,",
    "wof:placetype":"venue"
},
  "geometry": {"coordinates":[-3.2484250069,52.0067672729],"type":"Point"}
}