{
  "type": "Feature",
  "properties": {
    "addr:full":"2 Brook Street, Hartshorne Swadlincote Derbyshire DE11 7AH",
    "addr:housenumber":"2",
    "addr:postcode":"de11 7ah",
    "addr:street":"Brook Street",
    "iso:country":"GB",
    "sg:address":"2 Brook Street, Hartshorne",
    "sg:city":"Swadlincote",
    "sg:classifiers":[
        {
            "category":"Building & Trades",
            "subcategory":"Pest Control",
            "type":"Services"
        }
    ],
    "sg:postcode":"DE11 7AH",
    "sg:province":"Derbyshire",
    "sg:tags":[
        "woodworm"
    ],
    "wof:name":"Derbyshire Damp (South)",
    "wof:placetype":"venue"
},
  "geometry": {"coordinates":[-1.5249899626,52.7883453369],"type":"Point"}
}