{
  "type": "Feature",
  "properties": {
    "iso:country":"GB",
    "sg:address":"Hill Top, West Farleigh, Hunton",
    "sg:city":"Maidstone",
    "sg:classifiers":[
        {
            "category":"Bars & Pubs",
            "type":"Food & Drink"
        }
    ],
    "sg:phone":"+44 1622 820520",
    "sg:postcode":"ME15 0QN",
    "sg:province":"Kent",
    "sg:tags":[
        "pubs",
        "inn"
    ],
    "wof:name":"The White House",
    "wof:placetype":"venue"
},
  "geometry": {"coordinates":[0.461803,51.235199],"type":"Point"}
}