{
  "type": "Feature",
  "properties": {
    "addr:full":"Flat 1 37 West Hill Road St Leonards-on-sea East Sussex TN38 0NA",
    "addr:housenumber":"37",
    "addr:postcode":"leonards-on-sea;tn38 0na",
    "addr:street":"West Hill Road St",
    "iso:country":"GB",
    "sg:address":"Flat 1 37 West Hill Road",
    "sg:city":"St Leonards-on-sea",
    "sg:classifiers":[
        {
            "category":"Building & Trades",
            "subcategory":"Construction",
            "type":"Services"
        }
    ],
    "sg:postcode":"TN38 0NA",
    "sg:province":"East Sussex",
    "sg:tags":[
        "decorator",
        "painter"
    ],
    "wof:name":"Hilary Bannock Decorating",
    "wof:placetype":"venue"
},
  "geometry": {"coordinates":[0.5525149703,50.8557434082],"type":"Point"}
}