{
  "type": "Feature",
  "properties": {
    "addr:full":"47-49 Borough High Street London Greater London SE1 1NB",
    "addr:housenumber":"47-49",
    "addr:postcode":"se1 1nb",
    "addr:street":"Borough High Street",
    "iso:country":"GB",
    "sg:address":"47-49 Borough High Street",
    "sg:city":"London",
    "sg:classifiers":[
        {
            "category":"Fast Food",
            "type":"Food & Drink"
        }
    ],
    "sg:phone":"+44 20 7407 7663",
    "sg:postcode":"SE1 1NB",
    "sg:province":"Greater London",
    "sg:tags":[
        "away",
        "take"
    ],
    "wof:name":"The Luncheonette",
    "wof:placetype":"venue"
},
  "geometry": {"coordinates":[-0.0898099989,51.5048294067],"type":"Point"}
}