{
  "type": "Feature",
  "properties": {
    "addr:full":"11 Shannon Square Canvey Island Essex SS8 0PE",
    "addr:housenumber":"11",
    "addr:postcode":"ss8 0pe",
    "addr:street":"Shannon Square Canvey Island",
    "iso:country":"GB",
    "sg:address":"11 Shannon Square",
    "sg:city":"Canvey Island",
    "sg:classifiers":[
        {
            "category":"Retail",
            "subcategory":"Auto Rental",
            "type":"Services"
        }
    ],
    "sg:phone":"+44 1268 514829",
    "sg:postcode":"SS8 0PE",
    "sg:province":"Essex",
    "sg:tags":[
        "car"
    ],
    "wof:name":"Auto Hire",
    "wof:placetype":"venue"
},
  "geometry": {"coordinates":[0.5594699979,51.5197715759],"type":"Point"}
}