{
  "type": "Feature",
  "properties": {
    "addr:full":"Beck Garage, Clayworth Retford Nottinghamshire DN22 9AQ",
    "addr:postcode":"dn22 9aq",
    "iso:country":"GB",
    "sg:address":"Beck Garage, Clayworth",
    "sg:city":"Retford",
    "sg:classifiers":[
        {
            "category":"Bus Charters",
            "type":"Transportation"
        }
    ],
    "sg:phone":"+44 1777 817556",
    "sg:postcode":"DN22 9AQ",
    "sg:province":"Nottinghamshire",
    "sg:tags":[
        "hire",
        "coach"
    ],
    "wof:name":"Unity Coaches",
    "wof:placetype":"venue"
},
  "geometry": {"coordinates":[-0.9032790065,53.3840332031],"type":"Point"}
}