{
  "type": "Feature",
  "properties": {
    "addr:full":"219 Saltings Rd Snodland Kent ME6 5HP",
    "addr:housenumber":"219",
    "addr:postcode":"me6 5hp",
    "addr:street":"Saltings Rd",
    "iso:country":"GB",
    "sg:address":"219 Saltings Rd",
    "sg:city":"Snodland",
    "sg:classifiers":[
        {
            "category":"Wholesale",
            "subcategory":"Toys & Hobbies",
            "type":"Manufacturing & Wholesale Goods"
        }
    ],
    "sg:phone":"+44 1634 244372",
    "sg:postcode":"ME6 5HP",
    "sg:province":"Kent",
    "sg:tags":[
        "balloon",
        "novelty"
    ],
    "wof:name":"Any Occasion Balloons",
    "wof:placetype":"venue"
},
  "geometry": {"coordinates":[0.444141,51.326324],"type":"Point"}
}