{
  "type": "Feature",
  "properties": {
    "iso:country":"GB",
    "sg:address":"121a Swan Street",
    "sg:city":"Halstead",
    "sg:classifiers":[
        {
            "category":"Food & Beverages",
            "subcategory":"Fruits & Vegetables",
            "type":"Retail Goods"
        }
    ],
    "sg:phone":"+44 1787 460772",
    "sg:postcode":"CO9 3HP",
    "sg:province":"Essex",
    "sg:tags":[
        "greengrocer"
    ],
    "wof:name":"Top of the Tree",
    "wof:placetype":"venue"
},
  "geometry": {"coordinates":[0.592566,51.977356],"type":"Point"}
}