{
  "type": "Feature",
  "properties": {
    "addr:full":"20 Spencer Food Hall, High Street Stockton-on-tees Durham TS18 1BW",
    "addr:housenumber":"20",
    "addr:postcode":"ts18 1bw",
    "addr:street":"High Street",
    "iso:country":"GB",
    "sg:address":"20 Spencer Food Hall, High Street",
    "sg:city":"Stockton-on-tees",
    "sg:classifiers":[
        {
            "category":"Food & Beverages",
            "subcategory":"Meat & Fish",
            "type":"Retail Goods"
        }
    ],
    "sg:phone":"+44 1642 676014",
    "sg:postcode":"TS18 1BW",
    "sg:province":"Durham",
    "sg:tags":[
        "butcher"
    ],
    "wof:name":"Fox & Monkhouse",
    "wof:placetype":"venue"
},
  "geometry": {"coordinates":[-1.3120499849,54.5627098083],"type":"Point"}
}