{
  "type": "Feature",
  "properties": {
    "iso:country":"GB",
    "sg:address":"Museum Road",
    "sg:city":"Torquay",
    "sg:classifiers":[
        {
            "category":"Social Services",
            "subcategory":"Retirement Home",
            "type":"Services"
        }
    ],
    "sg:phone":"+44 1803 293084",
    "sg:postcode":"TQ1 1DW",
    "sg:province":"Devon",
    "sg:tags":[
        "rest"
    ],
    "wof:name":"Whitbourne Rest Home",
    "wof:placetype":"venue"
},
  "geometry": {"coordinates":[-3.5201249123,50.4627494812],"type":"Point"}
}