{
  "type": "Feature",
  "properties": {
    "addr:full":"1 Westborough Scarborough North Yorkshire YO11 1UH",
    "addr:housenumber":"1",
    "addr:postcode":"yo11 1uh",
    "addr:street":"Westborough",
    "iso:country":"GB",
    "sg:address":"1 Westborough",
    "sg:city":"Scarborough",
    "sg:classifiers":[
        {
            "category":"Shopping",
            "subcategory":"Gifts & Souvenirs",
            "type":"Retail Goods"
        }
    ],
    "sg:phone":"+44 1723 371229",
    "sg:postcode":"YO11 1UH",
    "sg:province":"North Yorkshire",
    "sg:tags":[
        "poster",
        "card"
    ],
    "wof:name":"Memory Lane",
    "wof:placetype":"venue"
},
  "geometry": {"coordinates":[-0.4089300036,54.2784767151],"type":"Point"}
}