{
  "type": "Feature",
  "properties": {
    "iso:country":"GB",
    "sg:address":"Dorset Avenue",
    "sg:city":"Thornton-cleveleys",
    "sg:classifiers":[
        {
            "category":"Retail",
            "subcategory":"Auto Repair",
            "type":"Services"
        }
    ],
    "sg:phone":"+44 1253 866976",
    "sg:postcode":"FY5 2DB",
    "sg:province":"Lancashire",
    "sg:tags":[
        "modification",
        "garage",
        "related"
    ],
    "sg:website":"http://www.harrops.co.uk",
    "wof:name":"John Harrop Service Centre",
    "wof:placetype":"venue"
},
  "geometry": {"coordinates":[-3.03818,53.88446],"type":"Point"}
}