{
  "type": "Feature",
  "properties": {
    "addr:full":"The Orchard, Warrens Hill Cheddar Somerset BS27 3LN",
    "addr:postcode":"bs27 3ln",
    "addr:street":"Warrens Hill",
    "iso:country":"GB",
    "sg:address":"The Orchard, Warrens Hill",
    "sg:city":"Cheddar",
    "sg:classifiers":[
        {
            "category":"Food & Beverages",
            "subcategory":"Supermarket",
            "type":"Retail Goods"
        }
    ],
    "sg:postcode":"BS27 3LN",
    "sg:province":"Somerset",
    "wof:name":"Lukees of Chedder",
    "wof:placetype":"venue"
},
  "geometry": {"coordinates":[-2.777659,51.279659],"type":"Point"}
}