{
  "type": "Feature",
  "properties": {
    "addr:full":"110 Langney Rd Eastbourne East Sussex BN22 8AQ",
    "addr:housenumber":"110",
    "addr:postcode":"bn22 8aq",
    "addr:street":"Langney Rd",
    "iso:country":"GB",
    "sg:address":"110 Langney Rd",
    "sg:city":"Eastbourne",
    "sg:classifiers":[
        {
            "category":"Retail",
            "subcategory":"Repair Shop",
            "type":"Services"
        }
    ],
    "sg:phone":"+44 1323 734206",
    "sg:postcode":"BN22 8AQ",
    "sg:province":"East Sussex",
    "sg:tags":[
        "upholsterer"
    ],
    "wof:name":"Smith,J E,& Son (Upholsterers) Ltd",
    "wof:placetype":"venue"
},
  "geometry": {"coordinates":[0.292400986,50.7708396912],"type":"Point"}
}