{
  "type": "Feature",
  "properties": {
    "addr:full":"3 Lightwood Road Buxton Derbyshire SK17 7BJ",
    "addr:housenumber":"3",
    "addr:postcode":"sk17 7bj",
    "addr:street":"Lightwood Road",
    "iso:country":"GB",
    "sg:address":"3 Lightwood Road",
    "sg:city":"Buxton",
    "sg:classifiers":[
        {
            "category":"Health Services",
            "subcategory":"Dentist",
            "type":"Services"
        }
    ],
    "sg:phone":"+44 1298 27077",
    "sg:postcode":"SK17 7BJ",
    "sg:province":"Derbyshire",
    "wof:name":"Lightwood Dental Practice",
    "wof:placetype":"venue"
},
  "geometry": {"coordinates":[-1.905691,53.260448],"type":"Point"}
}