{
  "type": "Feature",
  "properties": {
    "iso:country":"GB",
    "sg:address":"76 The Street",
    "sg:city":"Ashtead",
    "sg:classifiers":[
        {
            "category":"Food & Beverages",
            "subcategory":"Bakery",
            "type":"Retail Goods"
        }
    ],
    "sg:phone":"+44 1372 272822",
    "sg:postcode":"KT21 1AW",
    "sg:province":"Surrey",
    "sg:tags":[
        "baker"
    ],
    "wof:name":"Watson's Bakeries",
    "wof:placetype":"venue"
},
  "geometry": {"coordinates":[-0.298606,51.309711],"type":"Point"}
}