{
  "type": "Feature",
  "properties": {
    "addr:full":"785 Fulham Rd Fulham Greater London SW6 5HD",
    "addr:housenumber":"785",
    "addr:postcode":"sw6 5hd",
    "addr:street":"Fulham Rd",
    "iso:country":"GB",
    "sg:address":"785 Fulham Rd",
    "sg:city":"Fulham",
    "sg:classifiers":[
        {
            "category":"Shopping",
            "subcategory":"Clothing, Apparel, & Fashions",
            "type":"Retail Goods"
        }
    ],
    "sg:phone":"+44 20 7736 5006",
    "sg:postcode":"SW6 5HD",
    "sg:province":"Greater London",
    "sg:tags":[
        "shop"
    ],
    "wof:name":"785 Ltd",
    "wof:placetype":"venue"
},
  "geometry": {"coordinates":[-0.2044769973,51.4762535095],"type":"Point"}
}