{
  "type": "Feature",
  "properties": {
    "iso:country":"GB",
    "sg:address":"1 The Street",
    "sg:city":"Swindon",
    "sg:classifiers":[
        {
            "category":"Community Center",
            "type":"Public Place"
        }
    ],
    "sg:phone":"+44 1793 535887",
    "sg:postcode":"SN25 3ER",
    "sg:province":"Wiltshire",
    "sg:tags":[
        "centre"
    ],
    "wof:name":"Moredon Community Centre",
    "wof:placetype":"venue"
},
  "geometry": {"coordinates":[-1.810978055,51.5869750977],"type":"Point"}
}