{
  "type": "Feature",
  "properties": {
    "addr:full":"77 Golborne Rd London Greater London W10 5NP",
    "addr:housenumber":"77",
    "addr:postcode":"w10 5np",
    "addr:street":"Golborne Rd",
    "iso:country":"GB",
    "sg:address":"77 Golborne Rd",
    "sg:city":"London",
    "sg:classifiers":[
        {
            "category":"Manufacturing",
            "subcategory":"Paper Products",
            "type":"Manufacturing & Wholesale Goods"
        }
    ],
    "sg:postcode":"W10 5NP",
    "sg:province":"Greater London",
    "sg:tags":[
        "cardboard"
    ],
    "wof:name":"Omnihome Ltd",
    "wof:placetype":"venue"
},
  "geometry": {"coordinates":[-0.208311,51.521896],"type":"Point"}
}