{
  "type": "Feature",
  "properties": {
    "addr:full":"32 Main St Glasgow Argyll and Bute G63 9RQ",
    "addr:housenumber":"32",
    "addr:postcode":"g63 9rq",
    "addr:street":"Main St",
    "iso:country":"GB",
    "sg:address":"32 Main St",
    "sg:city":"Glasgow",
    "sg:classifiers":[
        {
            "category":"Professional",
            "subcategory":"Engineering",
            "type":"Services"
        }
    ],
    "sg:postcode":"G63 9RQ",
    "sg:province":"Argyll and Bute",
    "sg:tags":[
        "contractor",
        "electrical",
        "engineer"
    ],
    "wof:name":"Mearns,A J,(Killearn)",
    "wof:placetype":"venue"
},
  "geometry": {"coordinates":[-4.3688611984,56.0426940918],"type":"Point"}
}