{
  "type": "Feature",
  "properties": {
    "addr:full":"Fieldings, Stoneheap Road, East Studdal Dover Kent CT15 5BU",
    "addr:postcode":"ct15 5bu",
    "addr:street":"Stoneheap Road East Studdal Dover",
    "iso:country":"GB",
    "sg:address":"Fieldings, Stoneheap Road, East Studdal",
    "sg:city":"Dover",
    "sg:classifiers":[
        {
            "category":"Bus Charters",
            "type":"Transportation"
        }
    ],
    "sg:phone":"+44 1304 374732",
    "sg:postcode":"CT15 5BU",
    "sg:province":"Kent",
    "sg:tags":[
        "hire",
        "coach"
    ],
    "wof:name":"A J  & P J  Seath",
    "wof:placetype":"venue"
},
  "geometry": {"coordinates":[1.31805,51.198708],"type":"Point"}
}