{
  "type": "Feature",
  "properties": {
    "iso:country":"GB",
    "sg:address":"14 Bramall Clo",
    "sg:city":"London",
    "sg:classifiers":[
        {
            "category":"Bars & Pubs",
            "type":"Food & Drink"
        }
    ],
    "sg:postcode":"E15 1RR",
    "sg:province":"Greater London",
    "sg:tags":[
        "pubs",
        "inn"
    ],
    "wof:name":"Mohamed,Farah,",
    "wof:placetype":"venue"
},
  "geometry": {"coordinates":[0.011709,51.549965],"type":"Point"}
}