{
  "type": "Feature",
  "properties": {
    "iso:country":"GB",
    "sg:address":"C/o Railfrieght Distribution, 61 Landor Street",
    "sg:city":"Birmingham",
    "sg:classifiers":[
        {
            "category":"Building & Trades",
            "subcategory":"Electrical",
            "type":"Services"
        }
    ],
    "sg:phone":"+44 121 359 8200",
    "sg:postcode":"B8 1AE",
    "sg:province":"West Midlands",
    "sg:tags":[
        "lighting"
    ],
    "wof:name":"Fitzgerald Lighting Ltd.",
    "wof:placetype":"venue"
},
  "geometry": {"coordinates":[-1.86865,52.482422],"type":"Point"}
}