{
  "type": "Feature",
  "properties": {
    "addr:full":"Glebe Farm, Mope Lane Witham Essex CM8 3JP",
    "addr:postcode":"cm8 3jp",
    "addr:street":"Mope Lane",
    "iso:country":"GB",
    "sg:address":"Glebe Farm, Mope Lane",
    "sg:city":"Witham",
    "sg:classifiers":[
        {
            "category":"Sports & Exercise",
            "subcategory":"Stables",
            "type":"Entertainment"
        }
    ],
    "sg:postcode":"CM8 3JP",
    "sg:province":"Essex",
    "sg:tags":[
        "education",
        "equestrian"
    ],
    "wof:name":"Cecil Williams Show Centre",
    "wof:placetype":"venue"
},
  "geometry": {"coordinates":[0.639991,51.800713],"type":"Point"}
}