{
  "type": "Feature",
  "properties": {
    "addr:full":"267 Demesne Drive Stalybridge Greater Manchester SK15 2QG",
    "addr:housenumber":"267",
    "addr:postcode":"sk15 2qg",
    "addr:street":"Demesne Drive",
    "iso:country":"GB",
    "sg:address":"267 Demesne Drive",
    "sg:city":"Stalybridge",
    "sg:classifiers":[
        {
            "category":"Food & Beverages",
            "subcategory":"Meat & Fish",
            "type":"Retail Goods"
        }
    ],
    "sg:phone":"+44 161 303 1074",
    "sg:postcode":"SK15 2QG",
    "sg:province":"Greater Manchester",
    "sg:tags":[
        "chip"
    ],
    "wof:name":"Cheong-Hing",
    "wof:placetype":"venue"
},
  "geometry": {"coordinates":[-2.039049,53.483841],"type":"Point"}
}