{
  "type": "Feature",
  "properties": {
    "addr:full":"217 Devonshire Road, Forest Hill London Greater London SE23 3NJ",
    "addr:housenumber":"217",
    "addr:postcode":"se23 3nj",
    "addr:street":"Devonshire Road",
    "iso:country":"GB",
    "sg:address":"217 Devonshire Road, Forest Hill",
    "sg:city":"London",
    "sg:classifiers":[
        {
            "category":"Professional",
            "type":"Services"
        }
    ],
    "sg:phone":"+44 20 8291 2223",
    "sg:postcode":"SE23 3NJ",
    "sg:province":"Greater London",
    "sg:tags":[
        "repair",
        "tech",
        "maintenance"
    ],
    "wof:name":"Atlantic Field Maintenance",
    "wof:placetype":"venue"
},
  "geometry": {"coordinates":[-0.048055,51.448261],"type":"Point"}
}