{
  "type": "Feature",
  "properties": {
    "addr:full":"Doncaster Wks, Kirk Sandall Doncaster South Yorkshire DN3 1HW",
    "addr:postcode":"dn3 1hw",
    "iso:country":"GB",
    "sg:address":"Doncaster Wks, Kirk Sandall",
    "sg:city":"Doncaster",
    "sg:classifiers":[
        {
            "category":"Wholesale",
            "subcategory":"Construction Materials",
            "type":"Manufacturing & Wholesale Goods"
        }
    ],
    "sg:phone":"+44 1302 882661",
    "sg:postcode":"DN3 1HW",
    "sg:province":"South Yorkshire",
    "sg:tags":[
        "merchant",
        "glass"
    ],
    "wof:name":"Pilkington Glass Products Ltd",
    "wof:placetype":"venue"
},
  "geometry": {"coordinates":[-1.0850900412,53.5613098145],"type":"Point"}
}