{
  "type": "Feature",
  "properties": {
    "addr:full":"19 Annetyard Drive Skelmorlie North Ayrshire PA17 5BN",
    "addr:housenumber":"19",
    "addr:postcode":"pa17 5bn",
    "addr:street":"Annetyard Drive",
    "iso:country":"GB",
    "sg:address":"19 Annetyard Drive",
    "sg:city":"Skelmorlie",
    "sg:classifiers":[
        {
            "category":"Professional",
            "subcategory":"Accounting & Tax Preparation",
            "type":"Services"
        }
    ],
    "sg:phone":"+44 1475 520699",
    "sg:postcode":"PA17 5BN",
    "sg:province":"North Ayrshire",
    "sg:tags":[
        "accountant"
    ],
    "wof:name":"R A Woollard Chartered Accountant",
    "wof:placetype":"venue"
},
  "geometry": {"coordinates":[-4.88377,55.864342],"type":"Point"}
}