{
  "type": "Feature",
  "properties": {
    "addr:full":"1 Lower Street, Ninfield Battle East Sussex TN33 9EA",
    "addr:housenumber":"1",
    "addr:postcode":"tn33 9ea",
    "addr:street":"Lower Street;Battle",
    "iso:country":"GB",
    "sg:address":"1 Lower Street, Ninfield",
    "sg:city":"Battle",
    "sg:classifiers":[
        {
            "category":"Shopping",
            "subcategory":"Department Store",
            "type":"Retail Goods"
        }
    ],
    "sg:phone":"+44 1424 892281",
    "sg:postcode":"TN33 9EA",
    "sg:province":"East Sussex",
    "wof:name":"The Village Stores",
    "wof:placetype":"venue"
},
  "geometry": {"coordinates":[0.4272809923,50.8840370178],"type":"Point"}
}