{
  "type": "Feature",
  "properties": {
    "addr:full":"Manygates La Wakefield West Yorkshire WF1 5NJ",
    "addr:postcode":"wf1 5nj",
    "addr:street":"La Wakefield West",
    "iso:country":"GB",
    "sg:address":"Manygates La",
    "sg:city":"Wakefield",
    "sg:classifiers":[
        {
            "category":"Social Services",
            "type":"Services"
        }
    ],
    "sg:phone":"+44 1924 303306",
    "sg:postcode":"WF1 5NJ",
    "sg:province":"West Yorkshire",
    "sg:tags":[
        "educational"
    ],
    "wof:name":"Manygates Music Centre",
    "wof:placetype":"venue"
},
  "geometry": {"coordinates":[-1.487446,53.667183],"type":"Point"}
}