{
  "type": "Feature",
  "properties": {
    "iso:country":"GB",
    "sg:address":"Knowle Pad Farm, Inskip",
    "sg:city":"Preston",
    "sg:classifiers":[
        {
            "category":"Building & Trades",
            "subcategory":"Plumbing",
            "type":"Services"
        }
    ],
    "sg:phone":"+44 1995 679265",
    "sg:postcode":"PR4 0UA",
    "sg:province":"Lancashire",
    "sg:tags":[
        "central",
        "heating"
    ],
    "wof:name":"Everchain Services Ltd.",
    "wof:placetype":"venue"
},
  "geometry": {"coordinates":[-2.818501,53.834274],"type":"Point"}
}