{
  "type": "Feature",
  "properties": {
    "addr:full":"1 Cooper Drive, Springwood Industrial Estate Braintree Essex CM7 2RF",
    "addr:housenumber":"1",
    "addr:postcode":"cm7 2rf",
    "addr:street":"Cooper Drive;Industrial Estate",
    "iso:country":"GB",
    "sg:address":"1 Cooper Drive, Springwood Industrial Estate",
    "sg:city":"Braintree",
    "sg:classifiers":[
        {
            "category":"Shopping",
            "subcategory":"Optical Goods",
            "type":"Retail Goods"
        }
    ],
    "sg:postcode":"CM7 2RF",
    "sg:province":"Essex",
    "wof:name":"H E Bishop & Partners Ltd.",
    "wof:placetype":"venue"
},
  "geometry": {"coordinates":[0.536138,51.886505],"type":"Point"}
}