{
  "type": "Feature",
  "properties": {
    "addr:full":"18 Coleshill Rd Nuneaton Leicestershire CV10 0NY",
    "addr:housenumber":"18",
    "addr:postcode":"cv10 0ny",
    "addr:street":"Coleshill Rd",
    "iso:country":"GB",
    "sg:address":"18 Coleshill Rd",
    "sg:city":"Nuneaton",
    "sg:classifiers":[
        {
            "category":"Cinema",
            "subcategory":"Movie Rental",
            "type":"Entertainment"
        }
    ],
    "sg:phone":"+44 24 7639 4777",
    "sg:postcode":"CV10 0NY",
    "sg:province":"Leicestershire",
    "sg:tags":[
        "video",
        "library"
    ],
    "wof:name":"Plaza Video",
    "wof:placetype":"venue"
},
  "geometry": {"coordinates":[-1.5190910101,52.5370674133],"type":"Point"}
}