{
  "type": "Feature",
  "properties": {
    "iso:country":"GB",
    "sg:address":"1 Littleworth Lane, Monk Bretton",
    "sg:city":"Barnsley",
    "sg:classifiers":[
        {
            "category":"Retail",
            "subcategory":"Auto Repair",
            "type":"Services"
        }
    ],
    "sg:phone":"+44 1226 245088",
    "sg:postcode":"S71 2JR",
    "sg:province":"South Yorkshire",
    "sg:tags":[
        "modification",
        "garage",
        "related"
    ],
    "wof:name":"Centaur Motors",
    "wof:placetype":"venue"
},
  "geometry": {"coordinates":[-1.449831,53.564102],"type":"Point"}
}