{
  "type": "Feature",
  "properties": {
    "iso:country":"GB",
    "sg:address":"Bullocks Lane, Sutton",
    "sg:city":"Macclesfield",
    "sg:classifiers":[
        {
            "category":"Restaurant",
            "type":"Food & Drink"
        }
    ],
    "sg:phone":"+44 1260 253211",
    "sg:postcode":"SK11 0HE",
    "sg:province":"Cheshire",
    "wof:name":"Sutton Hall",
    "wof:placetype":"venue"
},
  "geometry": {"coordinates":[-2.118166,53.23806],"type":"Point"}
}