{
  "type": "Feature",
  "properties": {
    "iso:country":"GB",
    "sg:address":"Unit 304 The Chequers Centre",
    "sg:city":"Maidstone",
    "sg:classifiers":[
        {
            "category":"Shopping",
            "subcategory":"Shoes",
            "type":"Retail Goods"
        }
    ],
    "sg:phone":"+44 1622 690275",
    "sg:postcode":"ME15 6AW",
    "sg:province":"Kent",
    "wof:name":"Steadservices",
    "wof:placetype":"venue"
},
  "geometry": {"coordinates":[0.513423,51.262123],"type":"Point"}
}