{
  "type": "Feature",
  "properties": {
    "iso:country":"GB",
    "sg:address":"9 Western Street",
    "sg:city":"Brighton",
    "sg:classifiers":[
        {
            "category":"Real Estate",
            "subcategory":"Architect",
            "type":"Services"
        }
    ],
    "sg:postcode":"BN1 2PG",
    "sg:province":"East Sussex",
    "wof:name":"David Garbutt",
    "wof:placetype":"venue"
},
  "geometry": {"coordinates":[-0.1559329927,50.8236236572],"type":"Point"}
}