{
  "type": "Feature",
  "properties": {
    "addr:full":"Unit 2, Dens Road Arbroath Angus DD11 1RU",
    "addr:housenumber":"unit 2",
    "addr:postcode":"dd11 1ru",
    "addr:street":"Dens Road",
    "iso:country":"GB",
    "sg:address":"Unit 2, Dens Road",
    "sg:city":"Arbroath",
    "sg:classifiers":[
        {
            "category":"Autos & Motor Vehicles",
            "subcategory":"Auto Supplies",
            "type":"Retail Goods"
        }
    ],
    "sg:phone":"+44 1241 878676",
    "sg:postcode":"DD11 1RU",
    "sg:province":"Angus",
    "sg:tags":[
        "tyre"
    ],
    "wof:name":"P J Tyres",
    "wof:placetype":"venue"
},
  "geometry": {"coordinates":[-2.5890851021,56.5646629333],"type":"Point"}
}