{
  "type": "Feature",
  "properties": {
    "addr:full":"355 Norwood Road, Tulse Hill London Greater London SE27 9BQ",
    "addr:housenumber":"355",
    "addr:postcode":"se27 9bq",
    "addr:street":"Norwood Road",
    "iso:country":"GB",
    "sg:address":"355 Norwood Road, Tulse Hill",
    "sg:city":"London",
    "sg:classifiers":[
        {
            "category":"Building & Trades",
            "subcategory":"Construction",
            "type":"Services"
        }
    ],
    "sg:phone":"+44 20 8671 4342",
    "sg:postcode":"SE27 9BQ",
    "sg:province":"Greater London",
    "sg:tags":[
        "builder"
    ],
    "wof:name":"Harvey (London) Ltd.",
    "wof:placetype":"venue"
},
  "geometry": {"coordinates":[-0.105967,51.440155],"type":"Point"}
}