{
  "type": "Feature",
  "properties": {
    "addr:full":"98a High Street Hoddesdon Essex EN11 8HD",
    "addr:housenumber":"98a",
    "addr:postcode":"en11 8hd",
    "addr:street":"High Street",
    "iso:country":"GB",
    "sg:address":"98a High Street",
    "sg:city":"Hoddesdon",
    "sg:classifiers":[
        {
            "category":"Education",
            "subcategory":"Library",
            "type":"Public Place"
        }
    ],
    "sg:phone":"+44 1438 737333",
    "sg:postcode":"EN11 8HD",
    "sg:province":"Essex",
    "sg:tags":[
        "book"
    ],
    "wof:name":"Hoddesdon Library",
    "wof:placetype":"venue"
},
  "geometry": {"coordinates":[-0.011431,51.76062],"type":"Point"}
}