{
  "type": "Feature",
  "properties": {
    "iso:country":"GB",
    "sg:address":"Fairways, Church La",
    "sg:city":"Hastings",
    "sg:classifiers":[
        {
            "category":"Building & Trades",
            "subcategory":"Construction",
            "type":"Services"
        }
    ],
    "sg:phone":"+44 1424 752634",
    "sg:postcode":"TN35 4QB",
    "sg:province":"East Sussex",
    "sg:tags":[
        "dry",
        "lining",
        "plasterers",
        "screeders"
    ],
    "wof:name":"Coney Bros Dry Construction",
    "wof:placetype":"venue"
},
  "geometry": {"coordinates":[0.5751399994,50.9092597961],"type":"Point"}
}