{
  "type": "Feature",
  "properties": {
    "addr:full":"18 Hermes Rd, Gilmore Indust Est Liverpool Merseyside L11 0ED",
    "addr:housenumber":"18",
    "addr:postcode":"l11 0ed",
    "addr:street":"Hermes Rd;Indust",
    "iso:country":"GB",
    "sg:address":"18 Hermes Rd, Gilmore Indust Est",
    "sg:city":"Liverpool",
    "sg:classifiers":[
        {
            "category":"Home & Garden",
            "subcategory":"Building Materials",
            "type":"Retail Goods"
        }
    ],
    "sg:phone":"+44 151 549 2220",
    "sg:postcode":"L11 0ED",
    "sg:province":"Merseyside",
    "sg:tags":[
        "insulation",
        "installers"
    ],
    "wof:name":"Kilmond 1995 Ltd",
    "wof:placetype":"venue"
},
  "geometry": {"coordinates":[-2.904057,53.463928],"type":"Point"}
}