{
  "type": "Feature",
  "properties": {
    "addr:full":"Banchory Delivery Office, Tillybrake Road Banchory Aberdeen City AB31 5WW",
    "addr:postcode":"ab31 5ww",
    "addr:street":"Tillybrake Road;Aberdeen",
    "iso:country":"GB",
    "sg:address":"Banchory Delivery Office, Tillybrake Road",
    "sg:city":"Banchory",
    "sg:classifiers":[
        {
            "category":"Government",
            "subcategory":"Post Office",
            "type":"Public Place"
        }
    ],
    "sg:phone":"+44 1330 822512",
    "sg:postcode":"AB31 5WW",
    "sg:province":"Aberdeen City",
    "wof:name":"Royal Mail",
    "wof:placetype":"venue"
},
  "geometry": {"coordinates":[-2.501389,57.051174],"type":"Point"}
}