{
  "type": "Feature",
  "properties": {
    "addr:full":"Greenland Rd Hartlepool Durham TS24 0RQ",
    "addr:postcode":"ts24 0rq",
    "addr:street":"Greenland Rd",
    "iso:country":"GB",
    "sg:address":"Greenland Rd",
    "sg:city":"Hartlepool",
    "sg:classifiers":[
        {
            "category":"Professional",
            "subcategory":"Business Services",
            "type":"Services"
        }
    ],
    "sg:phone":"+44 1429 234241",
    "sg:postcode":"TS24 0RQ",
    "sg:province":"Durham",
    "sg:tags":[
        "import",
        "export",
        "agent"
    ],
    "wof:name":"Mansped Automotive",
    "wof:placetype":"venue"
},
  "geometry": {"coordinates":[-1.2059990168,54.6951560974],"type":"Point"}
}