{
  "type": "Feature",
  "properties": {
    "addr:full":"18e Vyse Street, Hockley Birmingham West Midlands B18 6LE",
    "addr:housenumber":"18e",
    "addr:postcode":"b18 6le",
    "addr:street":"Vyse Street",
    "iso:country":"GB",
    "sg:address":"18e Vyse Street, Hockley",
    "sg:city":"Birmingham",
    "sg:classifiers":[
        {
            "category":"Manufacturing",
            "subcategory":"Jewelry",
            "type":"Manufacturing & Wholesale Goods"
        }
    ],
    "sg:postcode":"B18 6LE",
    "sg:province":"West Midlands",
    "sg:tags":[
        "repair",
        "jewellery"
    ],
    "wof:name":"Glens Jewellery Repairs",
    "wof:placetype":"venue"
},
  "geometry": {"coordinates":[-1.912865,52.488808],"type":"Point"}
}