{
  "type": "Feature",
  "properties": {
    "addr:full":"22 Ash St Sheffield South Yorkshire S20 5AR",
    "addr:housenumber":"22",
    "addr:postcode":"s20 5ar",
    "addr:street":"Ash St",
    "iso:country":"GB",
    "sg:address":"22 Ash St",
    "sg:city":"Sheffield",
    "sg:classifiers":[
        {
            "category":"Building & Trades",
            "subcategory":"Construction",
            "type":"Services"
        }
    ],
    "sg:phone":"+44 114 248 3024",
    "sg:postcode":"S20 5AR",
    "sg:province":"South Yorkshire",
    "sg:tags":[
        "builder"
    ],
    "wof:name":"Ash Building & Glazing Services",
    "wof:placetype":"venue"
},
  "geometry": {"coordinates":[-1.3640960455,53.3288230896],"type":"Point"}
}