{
  "type": "Feature",
  "properties": {
    "addr:full":"Jubilee Surgery, School La Scunthorpe Lincolnshire DN17 3LB",
    "addr:postcode":"dn17 3lb",
    "addr:street":"La Scunthorpe",
    "iso:country":"GB",
    "sg:address":"Jubilee Surgery, School La",
    "sg:city":"Scunthorpe",
    "sg:classifiers":[
        {
            "category":"Health Services",
            "subcategory":"Doctor",
            "type":"Services"
        }
    ],
    "sg:phone":"+44 1724 783446",
    "sg:postcode":"DN17 3LB",
    "sg:province":"Lincolnshire",
    "sg:tags":[
        "practitioners"
    ],
    "wof:name":"Gallagher Dr J M",
    "wof:placetype":"venue"
},
  "geometry": {"coordinates":[-0.742299974,53.5431404114],"type":"Point"}
}