{
  "type": "Feature",
  "properties": {
    "iso:country":"GB",
    "sg:address":"Black Cat Industrial Estate, Ditton Road",
    "sg:city":"Widnes",
    "sg:classifiers":[
        {
            "category":"Wholesale",
            "subcategory":"Scrap",
            "type":"Manufacturing & Wholesale Goods"
        },
        {
            "category":"Manufacturing",
            "subcategory":"Lumber",
            "type":"Manufacturing & Wholesale Goods"
        }
    ],
    "sg:phone":"+44 151 424 3944",
    "sg:postcode":"WA8 0NS",
    "sg:province":"Cheshire",
    "sg:tags":[
        "merchants",
        "metal",
        "agent",
        "importer",
        "waste",
        "timber"
    ],
    "wof:name":"S Evans & Sons Ltd.",
    "wof:placetype":"venue"
},
  "geometry": {"coordinates":[-2.735484,53.35527],"type":"Point"}
}