{
  "type": "Feature",
  "properties": {
    "addr:full":"17 Seymour Rd Bristol City of Bristol BS7 9HR",
    "addr:housenumber":"17",
    "addr:postcode":"bs7 9hr",
    "addr:street":"Seymour Rd",
    "iso:country":"GB",
    "sg:address":"17 Seymour Rd",
    "sg:city":"Bristol",
    "sg:classifiers":[
        {
            "category":"Building & Trades",
            "subcategory":"Construction",
            "type":"Services"
        }
    ],
    "sg:phone":"+44 117 924 8914",
    "sg:postcode":"BS7 9HR",
    "sg:province":"City of Bristol",
    "sg:tags":[
        "joiner",
        "carpenter"
    ],
    "wof:name":"Borel Carpentry Services",
    "wof:placetype":"venue"
},
  "geometry": {"coordinates":[-2.585365057,51.4799613953],"type":"Point"}
}