{
  "type": "Feature",
  "properties": {
    "iso:country":"GB",
    "sg:address":"49-51 Terrace Road",
    "sg:city":"Mansfield",
    "sg:classifiers":[
        {
            "category":"Bars & Pubs",
            "type":"Food & Drink"
        },
        {
            "category":"Food & Beverages",
            "subcategory":"Liquor & Beverages",
            "type":"Retail Goods"
        }
    ],
    "sg:postcode":"NG18 2BP",
    "sg:province":"Nottinghamshire",
    "sg:tags":[
        "pubs",
        "beer",
        "inn",
        "spirit",
        "wines"
    ],
    "wof:name":"Carr Bank Stores",
    "wof:placetype":"venue"
},
  "geometry": {"coordinates":[-1.192362,53.148972],"type":"Point"}
}