{
  "type": "Feature",
  "properties": {
    "addr:full":"Glasgow Airport, Abbotsinch Paisley Renfrewshire PA3 2ST",
    "iso:country":"GB",
    "sg:address":"Glasgow Airport, Abbotsinch",
    "sg:city":"Paisley",
    "sg:classifiers":[
        {
            "category":"Airline",
            "type":"Transportation"
        }
    ],
    "sg:phone":"+44 141 887 1111",
    "sg:postcode":"PA3 2ST",
    "sg:province":"Renfrewshire",
    "sg:tags":[
        "airport"
    ],
    "wof:name":"Glasgow Airport Ltd.",
    "wof:placetype":"venue"
},
  "geometry": {"coordinates":[-4.4334797859,55.8640785217],"type":"Point"}
}