{
  "type": "Feature",
  "properties": {
    "iso:country":"GB",
    "sg:address":"20 Grafton Road",
    "sg:city":"Gloucester",
    "sg:classifiers":[
        {
            "category":"Social Services",
            "subcategory":"Adult Care",
            "type":"Services"
        }
    ],
    "sg:phone":"+44 1452 311599",
    "sg:postcode":"GL2 0QW",
    "sg:province":"Gloucestershire",
    "sg:tags":[
        "day",
        "centre"
    ],
    "wof:name":"Grafton Road Day Centre",
    "wof:placetype":"venue"
},
  "geometry": {"coordinates":[-2.221826,51.870708],"type":"Point"}
}