{
  "type": "Feature",
  "properties": {
    "addr:full":"Flat2, Clarondene, View Road Lyme Regis Devon DT7 3AA",
    "addr:postcode":"dt7 3aa",
    "addr:street":"View Road",
    "iso:country":"GB",
    "sg:address":"Flat2, Clarondene, View Road",
    "sg:city":"Lyme Regis",
    "sg:classifiers":[
        {
            "category":"Health Services",
            "subcategory":"Nursing And Care Facility",
            "type":"Services"
        },
        {
            "category":"Social Services",
            "subcategory":"Retirement Home",
            "type":"Services"
        }
    ],
    "sg:phone":"+44 1297 442876",
    "sg:postcode":"DT7 3AA",
    "sg:province":"Devon",
    "sg:tags":[
        "residential"
    ],
    "wof:name":"Clarondene Residential Care Homes",
    "wof:placetype":"venue"
},
  "geometry": {"coordinates":[-2.9380500317,50.7271842957],"type":"Point"}
}