{
  "type": "Feature",
  "properties": {
    "addr:full":"Strand Swansea Neath Port Talbot SA1 2AB",
    "addr:postcode":"sa1 2ab",
    "addr:street":"Strand",
    "iso:country":"GB",
    "sg:address":"Strand",
    "sg:city":"Swansea",
    "sg:classifiers":[
        {
            "category":"Home & Garden",
            "subcategory":"Kitchen Supply",
            "type":"Retail Goods"
        }
    ],
    "sg:phone":"+44 1792 473399",
    "sg:postcode":"SA1 2AB",
    "sg:province":"Neath Port Talbot",
    "sg:tags":[
        "equipment",
        "catering"
    ],
    "wof:name":"H F P Caterware Ltd",
    "wof:placetype":"venue"
},
  "geometry": {"coordinates":[-3.9405090809,51.6243858337],"type":"Point"}
}