{
  "type": "Feature",
  "properties": {
    "addr:full":"4a Nantwich Drive Edinburgh City of Edinburgh EH7 6QW",
    "addr:housenumber":"4a",
    "addr:postcode":"eh7 6qw",
    "addr:street":"Nantwich Drive",
    "iso:country":"GB",
    "sg:address":"4a Nantwich Drive",
    "sg:city":"Edinburgh",
    "sg:classifiers":[
        {
            "category":"Building & Trades",
            "subcategory":"Construction",
            "type":"Services"
        }
    ],
    "sg:postcode":"EH7 6QW",
    "sg:province":"City of Edinburgh",
    "sg:tags":[
        "builder"
    ],
    "wof:name":"Colgan Builders & Plant Hire",
    "wof:placetype":"venue"
},
  "geometry": {"coordinates":[-3.1303009987,55.961555481],"type":"Point"}
}