{
  "type": "Feature",
  "properties": {
    "iso:country":"GB",
    "sg:address":"9 Priory Terrace",
    "sg:city":"Cheltenham",
    "sg:classifiers":[
        {
            "category":"Professional",
            "subcategory":"Art Services",
            "type":"Services"
        }
    ],
    "sg:phone":"+44 1242 230500",
    "sg:postcode":"GL52 6DS",
    "sg:province":"Gloucestershire",
    "sg:tags":[
        "graphic",
        "designer"
    ],
    "wof:name":"PAUL MANNING",
    "wof:placetype":"venue"
},
  "geometry": {"coordinates":[-2.0648739338,51.8970146179],"type":"Point"}
}