{
  "type": "Feature",
  "properties": {
    "addr:full":"59 Tyes Ct, Lings Northampton Northamptonshire NN3 8LP",
    "addr:housenumber":"59",
    "addr:postcode":"nn3 8lp",
    "addr:street":"Tyes Ct Lings",
    "iso:country":"GB",
    "sg:address":"59 Tyes Ct, Lings",
    "sg:city":"Northampton",
    "sg:classifiers":[
        {
            "category":"Taxi",
            "type":"Transportation"
        }
    ],
    "sg:postcode":"NN3 8LP",
    "sg:province":"Northamptonshire",
    "sg:tags":[
        "mini",
        "cab"
    ],
    "wof:name":"Burbidge Limousines Ltd",
    "wof:placetype":"venue"
},
  "geometry": {"coordinates":[-0.830097,52.261814],"type":"Point"}
}