{
  "type": "Feature",
  "properties": {
    "iso:country":"GB",
    "sg:address":"58-61 Riches Street, Tettenhall",
    "sg:city":"Wolverhampton",
    "sg:classifiers":[
        {
            "category":"Professional",
            "subcategory":"Testing Lab",
            "type":"Services"
        }
    ],
    "sg:phone":"+44 1902 427766",
    "sg:postcode":"WV6 0DY",
    "sg:province":"Shropshire",
    "sg:tags":[
        "mot"
    ],
    "wof:name":"Riches Street Garage",
    "wof:placetype":"venue"
},
  "geometry": {"coordinates":[-2.150719,52.590431],"type":"Point"}
}