{
  "type": "Feature",
  "properties": {
    "addr:full":"Adult Residential Community, Somerset Ct, Harp Rd Highbridge Somerset TA9 4HQ",
    "addr:postcode":"ta9 4hq",
    "addr:street":"Somerset Ct Harp Rd",
    "iso:country":"GB",
    "sg:address":"Adult Residential Community, Somerset Ct, Harp Rd",
    "sg:city":"Highbridge",
    "sg:classifiers":[
        {
            "category":"Social Services",
            "subcategory":"Retirement Home",
            "type":"Services"
        },
        {
            "category":"Organizations",
            "subcategory":"Non-profit Organization",
            "type":"Services"
        }
    ],
    "sg:phone":"+44 1278 760555",
    "sg:postcode":"TA9 4HQ",
    "sg:province":"Somerset",
    "sg:tags":[
        "charity",
        "residential",
        "organisation",
        "care",
        "charitable"
    ],
    "sg:website":"http://www.nas.org.uk",
    "wof:name":"Autism The National Autistic Society",
    "wof:placetype":"venue"
},
  "geometry": {"coordinates":[-2.9749140739,51.2223243713],"type":"Point"}
}