{
  "type": "Feature",
  "properties": {
    "addr:full":"Pioneer Buildings, Halifax Road Dewsbury West Yorkshire WF13 2BS",
    "addr:postcode":"wf13 2bs",
    "addr:street":"Halifax Road",
    "iso:country":"GB",
    "sg:address":"Pioneer Buildings, Halifax Road",
    "sg:city":"Dewsbury",
    "sg:classifiers":[
        {
            "category":"Recreation",
            "subcategory":"Amusement Park",
            "type":"Entertainment"
        }
    ],
    "sg:phone":"+44 1924 451671",
    "sg:postcode":"WF13 2BS",
    "sg:province":"West Yorkshire",
    "sg:tags":[
        "arcade"
    ],
    "wof:name":"Lynx Leisure Ltd.",
    "wof:placetype":"venue"
},
  "geometry": {"coordinates":[-1.6311089993,53.6916046143],"type":"Point"}
}