{
  "type": "Feature",
  "properties": {
    "addr:full":"32 Halcombe Estate Chard Devon TA20 2DS",
    "addr:housenumber":"32",
    "addr:postcode":"ta20 2ds",
    "addr:street":"Halcombe Estate",
    "iso:country":"GB",
    "sg:address":"32 Halcombe Estate",
    "sg:city":"Chard",
    "sg:classifiers":[
        {
            "category":"Home & Garden",
            "subcategory":"Carpets & Floor Coverings",
            "type":"Retail Goods"
        }
    ],
    "sg:postcode":"TA20 2DS",
    "sg:province":"Devon",
    "sg:tags":[
        "cleaner",
        "upholstery"
    ],
    "wof:name":"Frank Page",
    "wof:placetype":"venue"
},
  "geometry": {"coordinates":[-2.963229,50.86554],"type":"Point"}
}