{
  "type": "Feature",
  "properties": {
    "iso:country":"GB",
    "sg:address":"Rye Rd",
    "sg:city":"Hoddesdon",
    "sg:classifiers":[
        {
            "category":"Place Of Worship",
            "type":"Public Place"
        }
    ],
    "sg:phone":"+44 1992 446383",
    "sg:postcode":"EN11 0JB",
    "sg:province":"Essex",
    "wof:name":"Elim Pentecostal Church",
    "wof:placetype":"venue"
},
  "geometry": {"coordinates":[0.004065,51.768936],"type":"Point"}
}