{
  "type": "Feature",
  "properties": {
    "addr:full":"Tangley Gardens, Worplesdon Road Guildford Surrey GU3 3LQ",
    "addr:postcode":"gu3 3lq",
    "addr:street":"Tangley Gardens Worplesdon Road",
    "iso:country":"GB",
    "sg:address":"Tangley Gardens, Worplesdon Road",
    "sg:city":"Guildford",
    "sg:classifiers":[
        {
            "category":"Home & Garden",
            "subcategory":"Garden Supply",
            "type":"Retail Goods"
        }
    ],
    "sg:phone":"+44 1483 232243",
    "sg:postcode":"GU3 3LQ",
    "sg:province":"Surrey",
    "sg:tags":[
        "nursery",
        "centre"
    ],
    "wof:name":"Tangley Gardens Nursery",
    "wof:placetype":"venue"
},
  "geometry": {"coordinates":[-0.602363,51.265049],"type":"Point"}
}