{
  "type": "Feature",
  "properties": {
    "addr:full":"87-89 South Street Romford Essex RM1 1NX",
    "addr:housenumber":"87-89",
    "addr:postcode":"rm1 1nx",
    "addr:street":"South Street",
    "iso:country":"GB",
    "sg:address":"87-89 South Street",
    "sg:city":"Romford",
    "sg:classifiers":[
        {
            "category":"Bars & Pubs",
            "type":"Food & Drink"
        }
    ],
    "sg:phone":"+44 1708 748244",
    "sg:postcode":"RM1 1NX",
    "sg:province":"Essex",
    "sg:tags":[
        "pubs",
        "inn"
    ],
    "wof:name":"Yates' Wine Lodges Ltd.",
    "wof:placetype":"venue"
},
  "geometry": {"coordinates":[0.182577,51.576363],"type":"Point"}
}