{
  "type": "Feature",
  "properties": {
    "iso:country":"GB",
    "sg:address":"Lower Fulshaw Farm, Pasture Lane, Barrowford",
    "sg:city":"Nelson",
    "sg:classifiers":[
        {
            "category":"Farming",
            "subcategory":"Livestock Farm",
            "type":"Manufacturing & Wholesale Goods"
        }
    ],
    "sg:phone":"+44 1282 611861",
    "sg:postcode":"BB9 6QZ",
    "sg:province":"Lancashire",
    "sg:tags":[
        "others"
    ],
    "wof:name":"S  & P Hanson",
    "wof:placetype":"venue"
},
  "geometry": {"coordinates":[-2.22941,53.855381],"type":"Point"}
}