{
  "type": "Feature",
  "properties": {
    "addr:full":"17 Chapel St Leeds West Yorkshire LS6 3HZ",
    "addr:housenumber":"17",
    "addr:postcode":"ls6 3hz",
    "addr:street":"Chapel St",
    "iso:country":"GB",
    "sg:address":"17 Chapel St",
    "sg:city":"Leeds",
    "sg:classifiers":[
        {
            "category":"Utilities",
            "type":"Services"
        }
    ],
    "sg:phone":"+44 113 294 4273",
    "sg:postcode":"LS6 3HZ",
    "sg:province":"West Yorkshire",
    "sg:tags":[
        "connection",
        "provider",
        "internet"
    ],
    "wof:name":"Netbytes Internet Ltd",
    "wof:placetype":"venue"
},
  "geometry": {"coordinates":[-1.579477,53.821533],"type":"Point"}
}