{
  "type": "Feature",
  "properties": {
    "addr:full":"Parciau Farm, Griffiths Crossing Caernarfon Gwynedd LL55 1TS",
    "addr:postcode":"ll55 1ts",
    "addr:street":"Griffiths Crossing",
    "iso:country":"GB",
    "sg:address":"Parciau Farm, Griffiths Crossing",
    "sg:city":"Caernarfon",
    "sg:classifiers":[
        {
            "category":"Farming",
            "subcategory":"Livestock Farm",
            "type":"Manufacturing & Wholesale Goods"
        }
    ],
    "sg:phone":"+44 1286 672262",
    "sg:postcode":"LL55 1TS",
    "sg:province":"Gwynedd",
    "sg:tags":[
        "others"
    ],
    "wof:name":"R M Evans & Son",
    "wof:placetype":"venue"
},
  "geometry": {"coordinates":[-4.2718091011,53.1425933838],"type":"Point"}
}