{
  "type": "Feature",
  "properties": {
    "iso:country":"GB",
    "sg:address":"44a Micklegate",
    "sg:city":"Selby",
    "sg:classifiers":[
        {
            "category":"Home & Garden",
            "subcategory":"Hardware",
            "type":"Retail Goods"
        }
    ],
    "sg:phone":"+44 1757 213140",
    "sg:postcode":"YO8 0EQ",
    "sg:province":"East Riding of Yorkshire",
    "wof:name":"Ironside",
    "wof:placetype":"venue"
},
  "geometry": {"coordinates":[-1.068254,53.785019],"type":"Point"}
}