{
  "type": "Feature",
  "properties": {
    "addr:full":"75 Fleetgate Barton-upon-humber Lincolnshire DN18 5QD",
    "addr:housenumber":"75",
    "addr:postcode":"dn18 5qd",
    "addr:street":"Fleetgate",
    "iso:country":"GB",
    "sg:address":"75 Fleetgate",
    "sg:city":"Barton-upon-humber",
    "sg:classifiers":[
        {
            "category":"Professional",
            "subcategory":"Business Services",
            "type":"Services"
        },
        {
            "category":"Organizations",
            "subcategory":"Non-profit Organization",
            "type":"Services"
        }
    ],
    "sg:phone":"+44 1652 634160",
    "sg:postcode":"DN18 5QD",
    "sg:province":"Lincolnshire",
    "sg:tags":[
        "voluntary",
        "organisation",
        "agent",
        "export",
        "import",
        "charity"
    ],
    "wof:name":"North Lincolnshire Home-Start",
    "wof:placetype":"venue"
},
  "geometry": {"coordinates":[-0.4441649914,53.687877655],"type":"Point"}
}