{
  "type": "Feature",
  "properties": {
    "addr:full":"St Helens Road Hostel, 90 St Helens Road Swansea Neath Port Talbot SA1 3UW",
    "addr:housenumber":"90",
    "addr:postcode":"sa1 3uw",
    "addr:street":"St Helens Road;St Helens Road",
    "iso:country":"GB",
    "sg:address":"St Helens Road Hostel, 90 St Helens Road",
    "sg:city":"Swansea",
    "sg:classifiers":[
        {
            "category":"Organizations",
            "subcategory":"Community Association",
            "type":"Services"
        }
    ],
    "sg:phone":"+44 1792 461069",
    "sg:postcode":"SA1 3UW",
    "sg:province":"Neath Port Talbot",
    "sg:tags":[
        "society",
        "housing"
    ],
    "wof:name":"Family Housing Association (Wales) Ltd.",
    "wof:placetype":"venue"
},
  "geometry": {"coordinates":[-3.940928936,51.6231536865],"type":"Point"}
}