{
  "type": "Feature",
  "properties": {
    "iso:country":"GB",
    "sg:address":"112 Shaldon Drive",
    "sg:city":"Morden",
    "sg:classifiers":[
        {
            "category":"Building & Trades",
            "subcategory":"Construction",
            "type":"Services"
        },
        {
            "category":"Home & Garden",
            "subcategory":"Carpets & Floor Coverings",
            "type":"Retail Goods"
        }
    ],
    "sg:phone":"+44 20 8540 5334",
    "sg:postcode":"SM4 4BH",
    "sg:province":"Surrey",
    "sg:tags":[
        "carpets",
        "rug",
        "flooring",
        "matting"
    ],
    "wof:name":"Lawless Flooring",
    "wof:placetype":"venue"
},
  "geometry": {"coordinates":[-0.2174270004,51.3943595886],"type":"Point"}
}