{
  "type": "Feature",
  "properties": {
    "addr:full":"30 Ratten Lane, Hutton Preston Lancashire PR4 5TE",
    "addr:housenumber":"30",
    "addr:postcode":"pr4 5te",
    "addr:street":"Ratten Lane",
    "iso:country":"GB",
    "sg:address":"30 Ratten Lane, Hutton",
    "sg:city":"Preston",
    "sg:classifiers":[
        {
            "category":"Professional",
            "subcategory":"Accounting & Tax Preparation",
            "type":"Services"
        }
    ],
    "sg:phone":"+44 1772 616176",
    "sg:postcode":"PR4 5TE",
    "sg:province":"Lancashire",
    "sg:tags":[
        "accountant"
    ],
    "wof:name":"Winstanley Gerald A Accountancy & Pensions",
    "wof:placetype":"venue"
},
  "geometry": {"coordinates":[-2.761043,53.738338],"type":"Point"}
}