{
  "type": "Feature",
  "properties": {
    "addr:full":"Reedham Close London Greater London N17 9PX",
    "addr:postcode":"n17 9px",
    "addr:street":"Reedham Close",
    "iso:country":"GB",
    "sg:address":"Reedham Close",
    "sg:city":"London",
    "sg:classifiers":[
        {
            "category":"Bars & Pubs",
            "type":"Food & Drink"
        }
    ],
    "sg:phone":"+44 20 7288 9821",
    "sg:postcode":"N17 9PX",
    "sg:province":"Greater London",
    "sg:tags":[
        "pubs",
        "inn"
    ],
    "wof:name":"The Narrow Boat",
    "wof:placetype":"venue"
},
  "geometry": {"coordinates":[-0.0570360012,51.5855789185],"type":"Point"}
}