{
  "type": "Feature",
  "properties": {
    "addr:full":"Goodiwindi, Berrow Grn Worcester Herefordshire WR6 6PL",
    "addr:postcode":"wr6 6pl",
    "addr:street":"Berrow Grn",
    "iso:country":"GB",
    "sg:address":"Goodiwindi, Berrow Grn",
    "sg:city":"Worcester",
    "sg:classifiers":[
        {
            "category":"Food & Beverages",
            "subcategory":"Farmers Market",
            "type":"Retail Goods"
        }
    ],
    "sg:phone":"+44 1886 821295",
    "sg:postcode":"WR6 6PL",
    "sg:province":"Herefordshire",
    "sg:tags":[
        "farm",
        "shop",
        "pyo"
    ],
    "wof:name":"B H Patrick",
    "wof:placetype":"venue"
},
  "geometry": {"coordinates":[-2.37032,52.222771],"type":"Point"}
}