{
  "type": "Feature",
  "properties": {
    "addr:full":"9 Watermeetings Lane, Romiley Stockport Cheshire SK6 4HJ",
    "addr:housenumber":"9",
    "addr:postcode":"sk6 4hj",
    "addr:street":"Watermeetings Lane",
    "iso:country":"GB",
    "sg:address":"9 Watermeetings Lane, Romiley",
    "sg:city":"Stockport",
    "sg:classifiers":[
        {
            "category":"Building & Trades",
            "subcategory":"Landscaping Services",
            "type":"Services"
        }
    ],
    "sg:postcode":"SK6 4HJ",
    "sg:province":"Cheshire",
    "sg:tags":[
        "gardening"
    ],
    "wof:name":"M Weeks Landscape Services",
    "wof:placetype":"venue"
},
  "geometry": {"coordinates":[-2.0699119568,53.4118804932],"type":"Point"}
}