{
  "type": "Feature",
  "properties": {
    "addr:full":"4 Thorney Lane North Iver Berkshire SL0 9HF",
    "addr:housenumber":"4",
    "addr:postcode":"sl0 9hf",
    "addr:street":"Thorney Lane North Iver",
    "iso:country":"GB",
    "sg:address":"4 Thorney Lane North",
    "sg:city":"Iver",
    "sg:classifiers":[
        {
            "category":"Manufacturing",
            "subcategory":"Wood Products",
            "type":"Manufacturing & Wholesale Goods"
        }
    ],
    "sg:phone":"+44 1753 655344",
    "sg:postcode":"SL0 9HF",
    "sg:province":"Berkshire",
    "sg:tags":[
        "packaging",
        "crate",
        "pallets"
    ],
    "wof:name":"Packaging Supplies Ltd.",
    "wof:placetype":"venue"
},
  "geometry": {"coordinates":[-0.5038149953,51.519947052],"type":"Point"}
}