{
  "type": "Feature",
  "properties": {
    "addr:full":"120 Charles Street Stockport Cheshire SK1 3JT",
    "addr:housenumber":"120",
    "addr:postcode":"sk1 3jt",
    "addr:street":"Charles Street",
    "iso:country":"GB",
    "sg:address":"120 Charles Street",
    "sg:city":"Stockport",
    "sg:classifiers":[
        {
            "category":"Organizations",
            "subcategory":"Membership Organization",
            "type":"Services"
        }
    ],
    "sg:phone":"+44 161 480 8841",
    "sg:postcode":"SK1 3JT",
    "sg:province":"Cheshire",
    "sg:tags":[
        "club"
    ],
    "wof:name":"G M T Social Athletic Club (Stockport)",
    "wof:placetype":"venue"
},
  "geometry": {"coordinates":[-2.1501948833,53.4007987976],"type":"Point"}
}