{
  "type": "Feature",
  "properties": {
    "iso:country":"GB",
    "sg:address":"189 Mudford Road",
    "sg:city":"Yeovil",
    "sg:classifiers":[
        {
            "category":"Building & Trades",
            "subcategory":"Construction",
            "type":"Services"
        }
    ],
    "sg:phone":"+44 1935 422106",
    "sg:postcode":"BA21 4NL",
    "sg:province":"Somerset",
    "sg:tags":[
        "joiner",
        "carpenter"
    ],
    "wof:name":"S G Evans",
    "wof:placetype":"venue"
},
  "geometry": {"coordinates":[-2.632979,50.957062],"type":"Point"}
}