{
  "type": "Feature",
  "properties": {
    "iso:country":"GB",
    "sg:address":"Trawscoed Hall",
    "sg:city":"Welshpool",
    "sg:classifiers":[
        {
            "category":"Home & Garden",
            "subcategory":"Garden Supply",
            "type":"Retail Goods"
        },
        {
            "category":"Farming",
            "subcategory":"Livestock Farm",
            "type":"Manufacturing & Wholesale Goods"
        }
    ],
    "sg:postcode":"SY21 9NX",
    "sg:province":"Shropshire",
    "sg:tags":[
        "bulb",
        "grower",
        "others"
    ],
    "wof:name":"J T K Trevor",
    "wof:placetype":"venue"
},
  "geometry": {"coordinates":[-3.1452031136,52.661190033],"type":"Point"}
}