{
  "type": "Feature",
  "properties": {
    "addr:full":"39 Main Street, Grassington Skipton Lancashire BD23 5AA",
    "addr:housenumber":"39",
    "addr:postcode":"bd23 5aa",
    "addr:street":"Main Street",
    "iso:country":"GB",
    "sg:address":"39 Main Street, Grassington",
    "sg:city":"Skipton",
    "sg:classifiers":[
        {
            "category":"Communications",
            "subcategory":"Film & Video Production",
            "type":"Services"
        },
        {
            "category":"Professional",
            "subcategory":"Art Services",
            "type":"Services"
        }
    ],
    "sg:phone":"+44 1756 752692",
    "sg:postcode":"BD23 5AA",
    "sg:province":"Lancashire",
    "sg:tags":[
        "illustrator",
        "artist"
    ],
    "wof:name":"Shenstone Gallery",
    "wof:placetype":"venue"
},
  "geometry": {"coordinates":[-1.9973829985,54.072933197],"type":"Point"}
}