{
  "type": "Feature",
  "properties": {
    "addr:full":"8 Mallinson Close Hornchurch Essex RM12 5HA",
    "addr:housenumber":"8",
    "addr:postcode":"rm12 5ha",
    "addr:street":"Mallinson Close",
    "iso:country":"GB",
    "sg:address":"8 Mallinson Close",
    "sg:city":"Hornchurch",
    "sg:classifiers":[
        {
            "category":"Professional",
            "subcategory":"Accounting & Tax Preparation",
            "type":"Services"
        }
    ],
    "sg:phone":"+44 1708 438284",
    "sg:postcode":"RM12 5HA",
    "sg:province":"Essex",
    "sg:tags":[
        "accountant"
    ],
    "wof:name":"Jan Watkinson & Co",
    "wof:placetype":"venue"
},
  "geometry": {"coordinates":[0.20971,51.544106],"type":"Point"}
}