{
  "type": "Feature",
  "properties": {
    "iso:country":"GB",
    "sg:address":"Unit A Rear Of 1440 Lincoln Rd",
    "sg:city":"Peterborough",
    "sg:classifiers":[
        {
            "category":"Retail",
            "subcategory":"Auto Repair",
            "type":"Services"
        }
    ],
    "sg:phone":"+44 1733 570606",
    "sg:postcode":"PE4 6LU",
    "sg:province":"Cambridgeshire",
    "sg:tags":[
        "modification",
        "garage"
    ],
    "wof:name":"D G Car & Commercial Vehicle Engineers",
    "wof:placetype":"venue"
},
  "geometry": {"coordinates":[-0.2854799926,52.6181106567],"type":"Point"}
}