{
  "type": "Feature",
  "properties": {
    "iso:country":"GB",
    "sg:address":"10 Inchvannie Ct",
    "sg:city":"Dingwall",
    "sg:classifiers":[
        {
            "category":"Shopping",
            "subcategory":"Gifts & Souvenirs",
            "type":"Retail Goods"
        }
    ],
    "sg:phone":"+44 1349 864186",
    "sg:postcode":"IV15 9SE",
    "sg:province":"Highland",
    "sg:tags":[
        "shop"
    ],
    "wof:name":"Envy",
    "wof:placetype":"venue"
},
  "geometry": {"coordinates":[-4.4325690269,57.6038856506],"type":"Point"}
}