{
  "type": "Feature",
  "properties": {
    "iso:country":"GB",
    "sg:address":"Birchden Farm, Groombridge",
    "sg:city":"Tunbridge Wells",
    "sg:classifiers":[
        {
            "category":"Building & Trades",
            "subcategory":"Landscaping Services",
            "type":"Services"
        }
    ],
    "sg:phone":"+44 1892 861305",
    "sg:postcode":"TN3 9NR",
    "sg:province":"East Sussex",
    "sg:tags":[
        "forestry",
        "tree"
    ],
    "wof:name":"Tilhill Forestry Ltd.",
    "wof:placetype":"venue"
},
  "geometry": {"coordinates":[0.17858,51.111626],"type":"Point"}
}