{
  "type": "Feature",
  "properties": {
    "iso:country":"GB",
    "sg:address":"8 Prince St",
    "sg:city":"Ryde",
    "sg:classifiers":[
        {
            "category":"Building & Trades",
            "subcategory":"Construction",
            "type":"Services"
        }
    ],
    "sg:phone":"+44 1983 562722",
    "sg:postcode":"PO33 2SE",
    "sg:province":"Isle of Wight",
    "sg:tags":[
        "decorator",
        "painter"
    ],
    "wof:name":"G White",
    "wof:placetype":"venue"
},
  "geometry": {"coordinates":[-1.161844,50.725208],"type":"Point"}
}