{
  "type": "Feature",
  "properties": {
    "iso:country":"GB",
    "sg:address":"3 St Michaels Court, Stoney Stanton",
    "sg:city":"Leicester",
    "sg:classifiers":[
        {
            "category":"Personal",
            "subcategory":"Beauty Salon",
            "type":"Services"
        }
    ],
    "sg:postcode":"LE9 4TH",
    "sg:province":"Leicestershire",
    "sg:tags":[
        "unisex",
        "hairdresser"
    ],
    "wof:name":"Kiss Curl Hair Salon",
    "wof:placetype":"venue"
},
  "geometry": {"coordinates":[-1.278904,52.548485],"type":"Point"}
}