{
  "type": "Feature",
  "properties": {
    "iso:country":"GB",
    "sg:address":"28 Blackwood Crescent, Blue Bridge",
    "sg:city":"Milton Keynes",
    "sg:classifiers":[
        {
            "category":"Building & Trades",
            "subcategory":"Construction",
            "type":"Services"
        }
    ],
    "sg:phone":"+44 1908 310811",
    "sg:postcode":"MK13 0LP",
    "sg:province":"Buckinghamshire",
    "sg:tags":[
        "builder"
    ],
    "wof:name":"Arcadia Contracts Ltd",
    "wof:placetype":"venue"
},
  "geometry": {"coordinates":[-0.798023,52.058907],"type":"Point"}
}