{
  "type": "Feature",
  "properties": {
    "addr:full":"7 Hanover Rd Tunbridge Wells Kent TN1 1EY",
    "addr:housenumber":"7",
    "addr:postcode":"tn1 1ey",
    "addr:street":"Hanover Rd",
    "iso:country":"GB",
    "sg:address":"7 Hanover Rd",
    "sg:city":"Tunbridge Wells",
    "sg:classifiers":[
        {
            "category":"Professional",
            "subcategory":"Accounting & Tax Preparation",
            "type":"Services"
        }
    ],
    "sg:postcode":"TN1 1EY",
    "sg:province":"Kent",
    "sg:tags":[
        "accountant"
    ],
    "wof:name":"Powell,Norman,",
    "wof:placetype":"venue"
},
  "geometry": {"coordinates":[0.261518,51.135128],"type":"Point"}
}