{
  "type": "Feature",
  "properties": {
    "iso:country":"GB",
    "sg:address":"New Barn Farm, Swan La",
    "sg:city":"Bromsgrove",
    "sg:classifiers":[
        {
            "category":"Professional",
            "type":"Services"
        },
        {
            "category":"Banks & Credit Unions",
            "subcategory":"Investment Brokerage",
            "type":"Services"
        }
    ],
    "sg:phone":"+44 1527 832490",
    "sg:postcode":"B61 0BU",
    "sg:province":"Worcestershire",
    "sg:tags":[
        "farm",
        "agricultural",
        "contractor"
    ],
    "wof:name":"K B Griffin",
    "wof:placetype":"venue"
},
  "geometry": {"coordinates":[-2.058112,52.336594],"type":"Point"}
}