{
  "type": "Feature",
  "properties": {
    "addr:full":"18 Station Road Letchworth Hertfordshire SG6 3AU",
    "addr:housenumber":"18",
    "addr:postcode":"sg6 3au",
    "addr:street":"Station Road",
    "iso:country":"GB",
    "sg:address":"18 Station Road",
    "sg:city":"Letchworth",
    "sg:classifiers":[
        {
            "category":"Autos & Motor Vehicles",
            "subcategory":"Automobile Sales",
            "type":"Retail Goods"
        }
    ],
    "sg:phone":"+44 1462 487632",
    "sg:postcode":"SG6 3AU",
    "sg:province":"Hertfordshire",
    "sg:tags":[
        "car"
    ],
    "wof:name":"Meridian Audi",
    "wof:placetype":"venue"
},
  "geometry": {"coordinates":[-0.2273609936,51.9800987244],"type":"Point"}
}