{
  "type": "Feature",
  "properties": {
    "iso:country":"GB",
    "sg:address":"Emerson Street Studios 4-8 Emerson Street",
    "sg:city":"London",
    "sg:classifiers":[
        {
            "category":"Professional",
            "subcategory":"Computer Services",
            "type":"Services"
        }
    ],
    "sg:postcode":"SE1 9DU",
    "sg:tags":[
        "quidco",
        "cashback",
        "voucher-codes",
        "money-saving",
        "discounts"
    ],
    "sg:website":"http://www.quidco.com",
    "wof:name":"Quidco",
    "wof:placetype":"venue"
},
  "geometry": {"coordinates":[0.2139465,51.4418908],"type":"Point"}
}