{
  "type": "Feature",
  "properties": {
    "iso:country":"GB",
    "sg:address":"41 Willow Street",
    "sg:city":"Oswestry",
    "sg:classifiers":[
        {
            "category":"Home & Garden",
            "subcategory":"Carpets & Floor Coverings",
            "type":"Retail Goods"
        }
    ],
    "sg:postcode":"SY11 1AQ",
    "sg:province":"Shropshire",
    "sg:tags":[
        "carpets",
        "rug",
        "matting"
    ],
    "wof:name":"G J Davies",
    "wof:placetype":"venue"
},
  "geometry": {"coordinates":[-3.057376,52.860237],"type":"Point"}
}