{
  "type": "Feature",
  "properties": {
    "addr:full":"Thornfield Altrincham Cheshire WA14 2NG",
    "addr:postcode":"wa14 2ng",
    "addr:street":"Cheshire",
    "iso:country":"GB",
    "sg:address":"Thornfield",
    "sg:city":"Altrincham",
    "sg:classifiers":[
        {
            "category":"Fast Food",
            "type":"Food & Drink"
        }
    ],
    "sg:postcode":"WA14 2NG",
    "sg:province":"Cheshire",
    "sg:tags":[
        "away",
        "take"
    ],
    "wof:name":"Genesis Fast Food Ltd.",
    "wof:placetype":"venue"
},
  "geometry": {"coordinates":[-2.349209,53.386726],"type":"Point"}
}