{
  "type": "Feature",
  "properties": {
    "addr:full":"Marklye Heathfield East Sussex TN21 9PN",
    "addr:postcode":"tn21 9pn",
    "iso:country":"GB",
    "sg:address":"Marklye",
    "sg:city":"Heathfield",
    "sg:classifiers":[
        {
            "category":"Professional",
            "type":"Services"
        }
    ],
    "sg:phone":"+44 1435 830902",
    "sg:postcode":"TN21 9PN",
    "sg:province":"East Sussex",
    "sg:tags":[
        "interior",
        "furnishers",
        "designer"
    ],
    "wof:name":"Watchmass Ltd",
    "wof:placetype":"venue"
},
  "geometry": {"coordinates":[0.303415,50.954323],"type":"Point"}
}