{
  "type": "Feature",
  "properties": {
    "iso:country":"GB",
    "sg:address":"Radway Grn",
    "sg:city":"Crewe",
    "sg:classifiers":[
        {
            "category":"Shopping",
            "subcategory":"Hobbies, Toys, & Games",
            "type":"Retail Goods"
        }
    ],
    "sg:phone":"+44 1270 886708",
    "sg:postcode":"CW2 5PJ",
    "sg:province":"Cheshire",
    "sg:tags":[
        "gunsmith"
    ],
    "wof:name":"Ba Systems",
    "wof:placetype":"venue"
},
  "geometry": {"coordinates":[-2.3407649994,53.0760421753],"type":"Point"}
}