{
  "type": "Feature",
  "properties": {
    "addr:full":"Lloyds Bank Chambers, 41 Broad Street Welshpool Shropshire SY21 7RR",
    "addr:housenumber":"41",
    "addr:postcode":"sy21 7rr",
    "addr:street":"Broad Street",
    "iso:country":"GB",
    "sg:address":"Lloyds Bank Chambers, 41 Broad Street",
    "sg:city":"Welshpool",
    "sg:classifiers":[
        {
            "category":"Professional",
            "subcategory":"Accounting & Tax Preparation",
            "type":"Services"
        }
    ],
    "sg:phone":"+44 1938 552311",
    "sg:postcode":"SY21 7RR",
    "sg:province":"Shropshire",
    "sg:tags":[
        "accountant"
    ],
    "wof:name":"Kidsons Impey",
    "wof:placetype":"venue"
},
  "geometry": {"coordinates":[-3.1452031136,52.661190033],"type":"Point"}
}