{
  "type": "Feature",
  "properties": {
    "addr:full":"Crawshay Court Llantwit Major The Vale of Glamorgan CF61 2GE",
    "addr:postcode":"cf61 2ge",
    "iso:country":"GB",
    "sg:address":"Crawshay Court",
    "sg:city":"Llantwit Major",
    "sg:classifiers":[
        {
            "category":"Government",
            "subcategory":"Office",
            "type":"Public Place"
        },
        {
            "category":"Social Services",
            "subcategory":"Adult Care",
            "type":"Services"
        },
        {
            "category":"Social Services",
            "subcategory":"Retirement Home",
            "type":"Services"
        }
    ],
    "sg:phone":"+44 1446 792803",
    "sg:postcode":"CF61 2GE",
    "sg:province":"The Vale of Glamorgan",
    "sg:tags":[
        "housing",
        "local",
        "accommodation",
        "sheltered"
    ],
    "wof:name":"Crawshay Court Sheltered Housing",
    "wof:placetype":"venue"
},
  "geometry": {"coordinates":[-3.4733040333,51.4109191895],"type":"Point"}
}