{
  "type": "Feature",
  "properties": {
    "addr:full":"Minnybae Farm, Kirkoswald Maybole East Ayrshire KA19 8HU",
    "addr:housenumber":"kirkoswald",
    "addr:postcode":"ka19 8hu",
    "addr:street":"Maybole East",
    "iso:country":"GB",
    "sg:address":"Minnybae Farm, Kirkoswald",
    "sg:city":"Maybole",
    "sg:classifiers":[
        {
            "category":"Farming",
            "subcategory":"Dairy Farm",
            "type":"Manufacturing & Wholesale Goods"
        }
    ],
    "sg:postcode":"KA19 8HU",
    "sg:province":"East Ayrshire",
    "wof:name":"J W & D Thomson",
    "wof:placetype":"venue"
},
  "geometry": {"coordinates":[-4.769749,55.33091],"type":"Point"}
}