{
  "type": "Feature",
  "properties": {
    "iso:country":"GB",
    "sg:address":"Leek Farm, High Street, Cranford",
    "sg:city":"Kettering",
    "sg:classifiers":[
        {
            "category":"Professional",
            "subcategory":"Computer Services",
            "type":"Services"
        }
    ],
    "sg:phone":"+44 1536 330555",
    "sg:postcode":"NN14 4AA",
    "sg:province":"Northamptonshire",
    "sg:tags":[
        "system",
        "software"
    ],
    "wof:name":"K D Systems",
    "wof:placetype":"venue"
},
  "geometry": {"coordinates":[-0.6438040137,52.3824157715],"type":"Point"}
}