{
  "type": "Feature",
  "properties": {
    "iso:country":"GB",
    "sg:address":"Tapton Lock Visitors Centre, Lockoford Lane",
    "sg:city":"Chesterfield",
    "sg:classifiers":[
        {
            "category":"Landmark",
            "subcategory":"Tourist Information",
            "type":"Public Place"
        }
    ],
    "sg:phone":"+44 1246 551035",
    "sg:postcode":"S41 7JB",
    "sg:province":"Derbyshire",
    "wof:name":"Three Valleys Tourism Project",
    "wof:placetype":"venue"
},
  "geometry": {"coordinates":[-1.4215010405,53.251247406],"type":"Point"}
}