{
  "type": "Feature",
  "properties": {
    "addr:full":"1 Middlewich Road, Holmes Chapel Crewe Cheshire CW4 7EA",
    "addr:housenumber":"1",
    "addr:postcode":"cw4 7ea",
    "addr:street":"Middlewich Road",
    "iso:country":"GB",
    "sg:address":"1 Middlewich Road, Holmes Chapel",
    "sg:city":"Crewe",
    "sg:classifiers":[
        {
            "category":"Building & Trades",
            "subcategory":"Construction",
            "type":"Services"
        }
    ],
    "sg:postcode":"CW4 7EA",
    "sg:province":"Cheshire",
    "sg:tags":[
        "builder"
    ],
    "wof:name":"Nusafe Ltd.",
    "wof:placetype":"venue"
},
  "geometry": {"coordinates":[-2.385852,53.200733],"type":"Point"}
}