{
  "type": "Feature",
  "properties": {
    "iso:country":"GB",
    "sg:address":"47 Cranley Dr, Newbury Pk",
    "sg:city":"Ilford",
    "sg:classifiers":[
        {
            "category":"Building & Trades",
            "subcategory":"Construction",
            "type":"Services"
        }
    ],
    "sg:postcode":"IG2 6AJ",
    "sg:province":"Essex",
    "sg:tags":[
        "joiner",
        "carpenter"
    ],
    "wof:name":"Saw Carpentry & Joinery",
    "wof:placetype":"venue"
},
  "geometry": {"coordinates":[0.0805080011,51.5705947876],"type":"Point"}
}