{
  "type": "Feature",
  "properties": {
    "addr:full":"Unit 3 Mangochi House, 107-115 Gwendolen Road Leicester Leicestershire LE5 5FL",
    "addr:housenumber":"unit 3 mangochi;107-115",
    "addr:postcode":"le5 5fl",
    "addr:street":"Gwendolen Road",
    "iso:country":"GB",
    "sg:address":"Unit 3 Mangochi House, 107-115 Gwendolen Road",
    "sg:city":"Leicester",
    "sg:classifiers":[
        {
            "category":"Manufacturing",
            "subcategory":"Textiles",
            "type":"Manufacturing & Wholesale Goods"
        }
    ],
    "sg:phone":"+44 116 212 1234",
    "sg:postcode":"LE5 5FL",
    "sg:province":"Leicestershire",
    "sg:tags":[
        "printer"
    ],
    "wof:name":"Rotaprint Textiles Ltd.",
    "wof:placetype":"venue"
},
  "geometry": {"coordinates":[-1.100952,52.630581],"type":"Point"}
}