{
  "type": "Feature",
  "properties": {
    "addr:full":"29 Winchendon Rd Fulham Greater London SW6 5DH",
    "addr:housenumber":"29",
    "addr:postcode":"sw6 5dh",
    "addr:street":"Winchendon Rd",
    "iso:country":"GB",
    "sg:address":"29 Winchendon Rd",
    "sg:city":"Fulham",
    "sg:classifiers":[
        {
            "category":"Home & Garden",
            "subcategory":"Home Furnishings",
            "type":"Retail Goods"
        }
    ],
    "sg:phone":"+44 1737 354392",
    "sg:postcode":"SW6 5DH",
    "sg:province":"Greater London",
    "sg:tags":[
        "mantelpiece",
        "fireplace"
    ],
    "wof:name":"N G Lemon",
    "wof:placetype":"venue"
},
  "geometry": {"coordinates":[-0.204178,51.477509],"type":"Point"}
}