{
  "type": "Feature",
  "properties": {
    "addr:full":"57 Marine Parade Great Yarmouth Norfolk NR30 2EJ",
    "addr:housenumber":"57",
    "addr:postcode":"nr30 2ej",
    "addr:street":"Marine Parade",
    "iso:country":"GB",
    "sg:address":"57 Marine Parade",
    "sg:city":"Great Yarmouth",
    "sg:classifiers":[
        {
            "category":"Restaurant",
            "type":"Food & Drink"
        }
    ],
    "sg:phone":"+44 1493 332533",
    "sg:postcode":"NR30 2EJ",
    "sg:province":"Norfolk",
    "wof:name":"Sizzlers Family Restaurant",
    "wof:placetype":"venue"
},
  "geometry": {"coordinates":[1.736577,52.607018],"type":"Point"}
}