{
  "type": "Feature",
  "properties": {
    "addr:full":"Mansion Ho, 1 Ardgowan Sq Greenock Inverclyde PA16 8NG",
    "addr:housenumber":"ho 1",
    "addr:postcode":"pa16 8ng",
    "addr:street":"Ardgowan Sq Greenock",
    "iso:country":"GB",
    "sg:address":"Mansion Ho, 1 Ardgowan Sq",
    "sg:city":"Greenock",
    "sg:classifiers":[
        {
            "category":"Professional",
            "subcategory":"Accounting & Tax Preparation",
            "type":"Services"
        }
    ],
    "sg:phone":"+44 1475 720466",
    "sg:postcode":"PA16 8NG",
    "sg:province":"Inverclyde",
    "sg:tags":[
        "accountant"
    ],
    "wof:name":"Steele Robertson & Co",
    "wof:placetype":"venue"
},
  "geometry": {"coordinates":[-4.7674999237,55.9524002075],"type":"Point"}
}