{
  "type": "Feature",
  "properties": {
    "iso:country":"GB",
    "sg:address":"4 Waltham Cres",
    "sg:city":"Nuneaton",
    "sg:classifiers":[
        {
            "category":"Home & Garden",
            "subcategory":"Household Appliances",
            "type":"Retail Goods"
        }
    ],
    "sg:postcode":"CV10 9JG",
    "sg:province":"Leicestershire",
    "sg:tags":[
        "electrical"
    ],
    "wof:name":"Prince,James,",
    "wof:placetype":"venue"
},
  "geometry": {"coordinates":[-1.515138,52.525585],"type":"Point"}
}