{
  "type": "Feature",
  "properties": {
    "iso:country":"GB",
    "sg:address":"23 Gower St",
    "sg:city":"St Helens",
    "sg:classifiers":[
        {
            "category":"Personal",
            "type":"Services"
        }
    ],
    "sg:postcode":"WA9 3DP",
    "sg:province":"Cheshire",
    "sg:tags":[
        "dressmaker"
    ],
    "wof:name":"Crahon,Jenny,",
    "wof:placetype":"venue"
},
  "geometry": {"coordinates":[-2.7130899429,53.4445114136],"type":"Point"}
}