{
  "type": "Feature",
  "properties": {
    "iso:country":"GB",
    "sg:address":"1 Myrtle Street",
    "sg:city":"Bolton",
    "sg:classifiers":[
        {
            "category":"Real Estate",
            "subcategory":"Architect",
            "type":"Services"
        }
    ],
    "sg:phone":"+44 1204 361776",
    "sg:postcode":"BL1 3AH",
    "sg:province":"Lancashire",
    "wof:name":"Good & Tillotson Ltd.",
    "wof:placetype":"venue"
},
  "geometry": {"coordinates":[-2.442132,53.582897],"type":"Point"}
}