{
  "type": "Feature",
  "properties": {
    "addr:full":"Albert Close Mill, Whitefield Manchester Lancashire M45 6EH",
    "addr:postcode":"m45 6eh",
    "addr:street":"Albert Close",
    "iso:country":"GB",
    "sg:address":"Albert Close Mill, Whitefield",
    "sg:city":"Manchester",
    "sg:classifiers":[
        {
            "category":"Recreation",
            "type":"Entertainment"
        }
    ],
    "sg:phone":"+44 161 766 1396",
    "sg:postcode":"M45 6EH",
    "sg:province":"Lancashire",
    "sg:tags":[
        "snooker",
        "billiards",
        "hall",
        "pool"
    ],
    "wof:name":"RILEYS WHITEFIELDS SNOOKER CLUB",
    "wof:placetype":"venue"
},
  "geometry": {"coordinates":[-2.2790598869,53.5443115234],"type":"Point"}
}