{
  "type": "Feature",
  "properties": {
    "addr:full":"3 Enmore Road London Greater London SE25 5NT",
    "addr:housenumber":"3",
    "addr:postcode":"se25 5nt",
    "addr:street":"Enmore Road",
    "iso:country":"GB",
    "sg:address":"3 Enmore Road",
    "sg:city":"London",
    "sg:classifiers":[
        {
            "category":"Health Services",
            "subcategory":"Doctor",
            "type":"Services"
        }
    ],
    "sg:phone":"+44 20 8656 5790",
    "sg:postcode":"SE25 5NT",
    "sg:province":"Greater London",
    "sg:tags":[
        "practitioners"
    ],
    "wof:name":"Woodside Health Centre",
    "wof:placetype":"venue"
},
  "geometry": {"coordinates":[-0.0674099997,51.3931274414],"type":"Point"}
}