{
  "type": "Feature",
  "properties": {
    "addr:full":"734 Stratford Rd, Sparkhill Birmingham West Midlands B11 4BP",
    "addr:housenumber":"734",
    "addr:postcode":"b11 4bp",
    "addr:street":"Stratford Rd",
    "iso:country":"GB",
    "sg:address":"734 Stratford Rd, Sparkhill",
    "sg:city":"Birmingham",
    "sg:classifiers":[
        {
            "category":"Retail",
            "subcategory":"Laundry & Dry Cleaning",
            "type":"Services"
        }
    ],
    "sg:postcode":"B11 4BP",
    "sg:province":"West Midlands",
    "sg:tags":[
        "launderette"
    ],
    "wof:name":"Chaudhy Launderette",
    "wof:placetype":"venue"
},
  "geometry": {"coordinates":[-1.860139966,52.4472160339],"type":"Point"}
}