{
  "type": "Feature",
  "properties": {
    "iso:country":"GB",
    "sg:address":"Gleadtail, Quarnford",
    "sg:city":"Buxton",
    "sg:classifiers":[
        {
            "category":"Manufacturing",
            "subcategory":"Building Materials",
            "type":"Manufacturing & Wholesale Goods"
        }
    ],
    "sg:phone":"+44 1298 74026",
    "sg:postcode":"SK17 0TG",
    "sg:province":"Derbyshire",
    "sg:tags":[
        "adhesives",
        "resin",
        "gum"
    ],
    "wof:name":"Benring Ltd.",
    "wof:placetype":"venue"
},
  "geometry": {"coordinates":[-1.9130489826,53.2603874207],"type":"Point"}
}