{
  "type": "Feature",
  "properties": {
    "addr:full":"24 The Green, Ingham Lincoln Lincolnshire LN1 2XT",
    "addr:housenumber":"24",
    "addr:postcode":"ln1 2xt",
    "addr:street":"The Green",
    "iso:country":"GB",
    "sg:address":"24 The Green, Ingham",
    "sg:city":"Lincoln",
    "sg:classifiers":[
        {
            "category":"Government",
            "subcategory":"Post Office",
            "type":"Public Place"
        }
    ],
    "sg:phone":"+44 1522 730366",
    "sg:postcode":"LN1 2XT",
    "sg:province":"Lincolnshire",
    "wof:name":"Ingham Post Office",
    "wof:placetype":"venue"
},
  "geometry": {"coordinates":[-0.5798979998,53.3394966125],"type":"Point"}
}