{
  "type": "Feature",
  "properties": {
    "addr:full":"242 Morden Road London Greater London SW19 3BZ",
    "addr:housenumber":"242",
    "addr:postcode":"sw19 3bz",
    "addr:street":"Morden Road",
    "iso:country":"GB",
    "sg:address":"242 Morden Road",
    "sg:city":"London",
    "sg:classifiers":[
        {
            "category":"Autos & Motor Vehicles",
            "subcategory":"Automobile Sales",
            "type":"Retail Goods"
        }
    ],
    "sg:phone":"+44 20 8542 8221",
    "sg:postcode":"SW19 3BZ",
    "sg:province":"Greater London",
    "sg:tags":[
        "car"
    ],
    "wof:name":"Manegerton",
    "wof:placetype":"venue"
},
  "geometry": {"coordinates":[-0.191608,51.404202],"type":"Point"}
}