{
  "type": "Feature",
  "properties": {
    "iso:country":"GB",
    "sg:address":"12 Blake Grove",
    "sg:city":"Leeds",
    "sg:classifiers":[
        {
            "category":"Shopping",
            "subcategory":"Pets & Pet Supplies",
            "type":"Retail Goods"
        }
    ],
    "sg:phone":"+44 113 262 1137",
    "sg:postcode":"LS7 3LT",
    "sg:province":"West Yorkshire",
    "wof:name":"Murray & Mills",
    "wof:placetype":"venue"
},
  "geometry": {"coordinates":[-1.5357730389,53.8246154785],"type":"Point"}
}