{
  "type": "Feature",
  "properties": {
    "iso:country":"GB",
    "sg:address":"131 Gosport Road",
    "sg:city":"Fareham",
    "sg:classifiers":[
        {
            "category":"Bars & Pubs",
            "type":"Food & Drink"
        }
    ],
    "sg:phone":"+44 1329 280841",
    "sg:postcode":"PO16 0PZ",
    "sg:province":"Hampshire",
    "sg:tags":[
        "pubs",
        "house",
        "inn",
        "public",
        "activity"
    ],
    "wof:name":"The Bird in Hand",
    "wof:placetype":"venue"
},
  "geometry": {"coordinates":[-1.182614,50.846508],"type":"Point"}
}