{
  "type": "Feature",
  "properties": {
    "addr:full":"19-23 Market Street Huddersfield West Yorkshire HD1 2HL",
    "addr:housenumber":"19-23",
    "addr:postcode":"hd1 2hl",
    "addr:street":"Market Street",
    "iso:country":"GB",
    "sg:address":"19-23 Market Street",
    "sg:city":"Huddersfield",
    "sg:classifiers":[
        {
            "category":"Shopping",
            "subcategory":"Discount & Variety Stores",
            "type":"Retail Goods"
        }
    ],
    "sg:phone":"+44 1484 421969",
    "sg:postcode":"HD1 2HL",
    "sg:province":"West Yorkshire",
    "sg:tags":[
        "centre"
    ],
    "wof:name":"The Bargain Street",
    "wof:placetype":"venue"
},
  "geometry": {"coordinates":[-1.7842110395,53.6460227966],"type":"Point"}
}