{
  "type": "Feature",
  "properties": {
    "iso:country":"GB",
    "sg:address":"42 King St",
    "sg:city":"Belper",
    "sg:classifiers":[
        {
            "category":"Farming",
            "subcategory":"Fish & Marine Products",
            "type":"Manufacturing & Wholesale Goods"
        }
    ],
    "sg:postcode":"DE56 1PL",
    "sg:province":"Derbyshire",
    "sg:tags":[
        "fishmonger"
    ],
    "wof:name":"Booth,J G,",
    "wof:placetype":"venue"
},
  "geometry": {"coordinates":[-1.482019,53.023113],"type":"Point"}
}