{
  "type": "Feature",
  "properties": {
    "addr:full":"90 Compton Road West Wolverhampton Staffordshire WV3 9DZ",
    "addr:housenumber":"90",
    "addr:postcode":"wv3 9dz",
    "addr:street":"Compton Road West",
    "iso:country":"GB",
    "sg:address":"90 Compton Road West",
    "sg:city":"Wolverhampton",
    "sg:classifiers":[
        {
            "category":"Health Services",
            "subcategory":"Health Practitioner",
            "type":"Services"
        }
    ],
    "sg:postcode":"WV3 9DZ",
    "sg:province":"Staffordshire",
    "sg:tags":[
        "physiotherapist"
    ],
    "wof:name":"Dennis Conyerd",
    "wof:placetype":"venue"
},
  "geometry": {"coordinates":[-2.160751,52.586334],"type":"Point"}
}