{
  "type": "Feature",
  "properties": {
    "addr:full":"Unit 5 Coach Close, Shireoaks Triangle Worksop Nottinghamshire S81 8AP",
    "addr:housenumber":"unit 5",
    "addr:postcode":"s81 8ap",
    "addr:street":"Coach Close",
    "iso:country":"GB",
    "sg:address":"Unit 5 Coach Close, Shireoaks Triangle",
    "sg:city":"Worksop",
    "sg:classifiers":[
        {
            "category":"Shopping",
            "subcategory":"Computers & Home Electronics",
            "type":"Retail Goods"
        }
    ],
    "sg:phone":"+44 1909 506042",
    "sg:postcode":"S81 8AP",
    "sg:province":"Nottinghamshire",
    "sg:tags":[
        "electrical"
    ],
    "wof:name":"Claylands Electrical & Engineering Distributors Ltd.",
    "wof:placetype":"venue"
},
  "geometry": {"coordinates":[-1.157254,53.32304],"type":"Point"}
}