{
  "type": "Feature",
  "properties": {
    "addr:full":"138-140 High Street Wallsend Tyne and Wear NE28 8HZ",
    "addr:housenumber":"138-140",
    "addr:postcode":"ne28 8hz",
    "addr:street":"High Street",
    "iso:country":"GB",
    "sg:address":"138-140 High Street",
    "sg:city":"Wallsend",
    "sg:classifiers":[
        {
            "category":"Bars & Pubs",
            "type":"Food & Drink"
        }
    ],
    "sg:postcode":"NE28 8HZ",
    "sg:province":"Tyne and Wear",
    "sg:tags":[
        "pubs",
        "inn"
    ],
    "wof:name":"G Gilbert",
    "wof:placetype":"venue"
},
  "geometry": {"coordinates":[-1.5382230282,54.9901237488],"type":"Point"}
}