{
  "type": "Feature",
  "properties": {
    "iso:country":"GB",
    "sg:address":"148 Valley Drive",
    "sg:city":"Harrogate",
    "sg:classifiers":[
        {
            "category":"Shopping",
            "subcategory":"Hobbies, Toys, & Games",
            "type":"Retail Goods"
        }
    ],
    "sg:postcode":"HG2 0JS",
    "sg:province":"North Yorkshire",
    "sg:tags":[
        "computer"
    ],
    "wof:name":"Gamesworld",
    "wof:placetype":"venue"
},
  "geometry": {"coordinates":[-1.5496180058,53.9887161255],"type":"Point"}
}