{
  "type": "Feature",
  "properties": {
    "iso:country":"GB",
    "sg:address":"12 Millfield Terr",
    "sg:city":"Sunderland",
    "sg:classifiers":[
        {
            "category":"Home & Garden",
            "subcategory":"Carpets & Floor Coverings",
            "type":"Retail Goods"
        }
    ],
    "sg:postcode":"SR6 7HH",
    "sg:province":"Tyne and Wear",
    "sg:tags":[
        "carpets",
        "rug",
        "matting"
    ],
    "wof:name":"Whitburn Carpet Centre",
    "wof:placetype":"venue"
},
  "geometry": {"coordinates":[-1.36631,54.960129],"type":"Point"}
}