{
  "type": "Feature",
  "properties": {
    "addr:full":"Ivy Place Works, Idle Road Bradford West Yorkshire BD2 2AZ",
    "addr:postcode":"bd2 2az",
    "addr:street":"Ivy Place;Idle Road",
    "iso:country":"GB",
    "sg:address":"Ivy Place Works, Idle Road",
    "sg:city":"Bradford",
    "sg:classifiers":[
        {
            "category":"Retail",
            "subcategory":"Funeral Services",
            "type":"Services"
        }
    ],
    "sg:postcode":"BD2 2AZ",
    "sg:province":"West Yorkshire",
    "wof:name":"W F Popple & Sons",
    "wof:placetype":"venue"
},
  "geometry": {"coordinates":[-1.735033989,53.818775177],"type":"Point"}
}