{
  "type": "Feature",
  "properties": {
    "addr:full":"Pembrokeshire College Haverfordwest Pembrokeshire SA61 1SZ",
    "addr:postcode":"sa61 1sz",
    "iso:country":"GB",
    "sg:address":"Pembrokeshire College",
    "sg:city":"Haverfordwest",
    "sg:classifiers":[
        {
            "category":"Restaurant",
            "type":"Food & Drink"
        }
    ],
    "sg:phone":"+44 1437 767878",
    "sg:postcode":"SA61 1SZ",
    "sg:province":"Pembrokeshire",
    "wof:name":"Academy Restaurant",
    "wof:placetype":"venue"
},
  "geometry": {"coordinates":[-4.977350235,51.7987632751],"type":"Point"}
}