{
  "type": "Feature",
  "properties": {
    "addr:full":"Footfield Road Bellshill North Lanarkshire ML4 2BY",
    "addr:postcode":"ml4 2by",
    "addr:street":"Footfield Road",
    "iso:country":"GB",
    "sg:address":"Footfield Road",
    "sg:city":"Bellshill",
    "sg:classifiers":[
        {
            "category":"Education",
            "subcategory":"School",
            "type":"Public Place"
        }
    ],
    "sg:phone":"+44 1698 747130",
    "sg:postcode":"ML4 2BY",
    "sg:province":"North Lanarkshire",
    "sg:tags":[
        "local",
        "authority"
    ],
    "wof:name":"Lawmuir Primary School",
    "wof:placetype":"venue"
},
  "geometry": {"coordinates":[-4.028531,55.812088],"type":"Point"}
}