{
  "type": "Feature",
  "properties": {
    "addr:full":"30 Parkside, Snettisham King's Lynn Norfolk PE31 7QE",
    "addr:housenumber":"30;snettisham",
    "addr:postcode":"pe31 7qe",
    "addr:street":"Parkside;Lynn",
    "iso:country":"GB",
    "sg:address":"30 Parkside, Snettisham",
    "sg:city":"King's Lynn",
    "sg:classifiers":[
        {
            "category":"Cinema",
            "subcategory":"Movie Rental",
            "type":"Entertainment"
        }
    ],
    "sg:phone":"+44 1485 544699",
    "sg:postcode":"PE31 7QE",
    "sg:province":"Norfolk",
    "sg:tags":[
        "video",
        "library"
    ],
    "wof:name":"Dial-a-film",
    "wof:placetype":"venue"
},
  "geometry": {"coordinates":[0.5033100247,52.8746109009],"type":"Point"}
}