{
  "type": "Feature",
  "properties": {
    "addr:full":"Grainger Court, Dunholme Road Newcastle-upon-tyne Tyne and Wear NE4 6XE",
    "addr:postcode":"ne4 6xe",
    "addr:street":"Grainger Court Dunholme Road",
    "iso:country":"GB",
    "sg:address":"Grainger Court, Dunholme Road",
    "sg:city":"Newcastle-upon-tyne",
    "sg:classifiers":[
        {
            "category":"Health Services",
            "subcategory":"Nursing And Care Facility",
            "type":"Services"
        },
        {
            "category":"Organizations",
            "subcategory":"Community Association",
            "type":"Services"
        }
    ],
    "sg:phone":"+44 191 273 1483",
    "sg:postcode":"NE4 6XE",
    "sg:province":"Tyne and Wear",
    "sg:tags":[
        "co-operatives",
        "residential",
        "housing",
        "trust",
        "society"
    ],
    "sg:website":"http://www.anchor.org.uk",
    "wof:name":"Anchor Trust",
    "wof:placetype":"venue"
},
  "geometry": {"coordinates":[-1.6449689865,54.9738235474],"type":"Point"}
}