{
  "type": "Feature",
  "properties": {
    "addr:full":"58 Market Street Lancaster Lancashire LA1 1HS",
    "addr:housenumber":"58",
    "addr:postcode":"la1 1hs",
    "addr:street":"Market Street",
    "iso:country":"GB",
    "sg:address":"58 Market Street",
    "sg:city":"Lancaster",
    "sg:classifiers":[
        {
            "category":"Real Estate",
            "subcategory":"Real Estate Agent",
            "type":"Services"
        }
    ],
    "sg:phone":"+44 1524 36311",
    "sg:postcode":"LA1 1HS",
    "sg:province":"Lancashire",
    "wof:name":"Aspden Gallagher Mortimer Royle Ltd.",
    "wof:placetype":"venue"
},
  "geometry": {"coordinates":[-2.80291,54.048851],"type":"Point"}
}