{
  "type": "Feature",
  "properties": {
    "iso:country":"GB",
    "sg:address":"King Edwards Parade",
    "sg:city":"Eastbourne",
    "sg:classifiers":[
        {
            "category":"Cafe",
            "type":"Food & Drink"
        }
    ],
    "sg:postcode":"BN21 4DS",
    "sg:province":"East Sussex",
    "sg:tags":[
        "tea",
        "room"
    ],
    "wof:name":"Holywell Tea Chalet",
    "wof:placetype":"venue"
},
  "geometry": {"coordinates":[0.2868149877,50.7626991272],"type":"Point"}
}