{
  "type": "Feature",
  "properties": {
    "addr:full":"Southall Park, Boyd Avenue Southall Greater London UB1 3BT",
    "addr:postcode":"ub1 3bt",
    "addr:street":"Park Boyd Avenue",
    "iso:country":"GB",
    "sg:address":"Southall Park, Boyd Avenue",
    "sg:city":"Southall",
    "sg:classifiers":[
        {
            "category":"Education",
            "subcategory":"Preschool",
            "type":"Public Place"
        }
    ],
    "sg:phone":"+44 20 8813 8263",
    "sg:postcode":"UB1 3BT",
    "sg:province":"Greater London",
    "sg:tags":[
        "pre-school",
        "playgroups"
    ],
    "wof:name":"Southall Park Playcentre",
    "wof:placetype":"venue"
},
  "geometry": {"coordinates":[-0.378334,51.511379],"type":"Point"}
}