{
  "type": "Feature",
  "properties": {
    "iso:country":"GB",
    "sg:address":"17 Campbell Street",
    "sg:city":"Hamilton",
    "sg:classifiers":[
        {
            "category":"Restaurant",
            "type":"Food & Drink"
        }
    ],
    "sg:phone":"+44 1698 282233",
    "sg:postcode":"ML3 6AS",
    "sg:province":"South Lanarkshire",
    "sg:tags":[
        "greek"
    ],
    "wof:name":"COSTA'S RESTAURANT",
    "wof:placetype":"venue"
},
  "geometry": {"coordinates":[-4.035229,55.776588],"type":"Point"}
}