{
  "type": "Feature",
  "properties": {
    "addr:full":"4 Girton Gardens, Shirley Croydon Surrey CR0 8PX",
    "addr:housenumber":"4",
    "addr:postcode":"cr0 8px",
    "addr:street":"Girton Gardens",
    "iso:country":"GB",
    "sg:address":"4 Girton Gardens, Shirley",
    "sg:city":"Croydon",
    "sg:classifiers":[
        {
            "category":"Building & Trades",
            "subcategory":"Landscaping Services",
            "type":"Services"
        }
    ],
    "sg:postcode":"CR0 8PX",
    "sg:province":"Surrey",
    "sg:tags":[
        "landscape",
        "contractor"
    ],
    "wof:name":"Lillypond Landscapes",
    "wof:placetype":"venue"
},
  "geometry": {"coordinates":[-0.032275,51.371414],"type":"Point"}
}