{
  "type": "Feature",
  "properties": {
    "iso:country":"GB",
    "sg:address":"12 Ermen Road",
    "sg:city":"Manchester",
    "sg:classifiers":[
        {
            "category":"Home & Garden",
            "subcategory":"Home Furnishings",
            "type":"Retail Goods"
        }
    ],
    "sg:phone":"+44 161 789 3168",
    "sg:postcode":"M30 7AR",
    "sg:province":"Greater Manchester",
    "sg:tags":[
        "furnishers",
        "planner",
        "bedroom"
    ],
    "wof:name":"Trimfit Bedrooms",
    "wof:placetype":"venue"
},
  "geometry": {"coordinates":[-2.3569710255,53.4768447876],"type":"Point"}
}