{
  "type": "Feature",
  "properties": {
    "iso:country":"GB",
    "sg:address":"Ambley Road",
    "sg:city":"Gillingham",
    "sg:classifiers":[
        {
            "category":"Professional",
            "subcategory":"Testing Lab",
            "type":"Services"
        }
    ],
    "sg:phone":"+44 1634 232754",
    "sg:postcode":"ME8 0SJ",
    "sg:province":"Kent",
    "sg:tags":[
        "mot"
    ],
    "wof:name":"Vosa M O T Testing",
    "wof:placetype":"venue"
},
  "geometry": {"coordinates":[0.5784900188,51.3609924316],"type":"Point"}
}