{
  "type": "Feature",
  "properties": {
    "iso:country":"GB",
    "sg:address":"3b Coronet Parade, Ealing Road",
    "sg:city":"Wembley",
    "sg:classifiers":[
        {
            "category":"Food & Beverages",
            "subcategory":"Candy",
            "type":"Retail Goods"
        },
        {
            "category":"Restaurant",
            "type":"Food & Drink"
        }
    ],
    "sg:phone":"+44 20 8903 5539",
    "sg:postcode":"HA0 4AY",
    "sg:province":"Greater London",
    "sg:tags":[
        "confectioner"
    ],
    "wof:name":"CHETNAS SWEET SHOP",
    "wof:placetype":"venue"
},
  "geometry": {"coordinates":[-0.29892,51.551929],"type":"Point"}
}