{
  "type": "Feature",
  "properties": {
    "addr:full":"5 London Rd,, Rainham, Gillingham Kent ME8 7RG",
    "addr:housenumber":"5",
    "addr:postcode":"me8 7rg",
    "addr:street":"London Rd",
    "iso:country":"GB",
    "sg:address":"5 London Rd,, Rainham,",
    "sg:city":"Gillingham",
    "sg:classifiers":[
        {
            "category":"Professional",
            "subcategory":"Engineering",
            "type":"Services"
        }
    ],
    "sg:postcode":"ME8 7RG",
    "sg:province":"Kent",
    "sg:tags":[
        "civil",
        "engineer"
    ],
    "wof:name":"Cheema Plant Hire Ltd",
    "wof:placetype":"venue"
},
  "geometry": {"coordinates":[0.602603,51.36488],"type":"Point"}
}