{
  "type": "Feature",
  "properties": {
    "iso:country":"GB",
    "sg:address":"34-36 Kennington Road",
    "sg:city":"London",
    "sg:classifiers":[
        {
            "category":"Professional",
            "subcategory":"Detective & Security Services",
            "type":"Services"
        }
    ],
    "sg:phone":"+44 20 7928 0639",
    "sg:postcode":"SE1 7BL",
    "sg:province":"Greater London",
    "sg:tags":[
        "locksmith"
    ],
    "wof:name":"Trafalgar Lock & Key Co. Ltd.",
    "wof:placetype":"venue"
},
  "geometry": {"coordinates":[-0.1119500026,51.4975471497],"type":"Point"}
}