{
  "type": "Feature",
  "properties": {
    "addr:full":"2 Fron Uchaf Colwyn Bay Conwy LL29 6DS",
    "addr:housenumber":"2",
    "addr:postcode":"ll29 6ds",
    "iso:country":"GB",
    "sg:address":"2 Fron Uchaf",
    "sg:city":"Colwyn Bay",
    "sg:classifiers":[
        {
            "category":"Professional",
            "type":"Services"
        }
    ],
    "sg:phone":"+44 1492 533783",
    "sg:postcode":"LL29 6DS",
    "sg:province":"Conwy",
    "sg:tags":[
        "aircraft",
        "maintenance"
    ],
    "wof:name":"R P Rogers",
    "wof:placetype":"venue"
},
  "geometry": {"coordinates":[-3.736107111,53.2847595215],"type":"Point"}
}