{
  "type": "Feature",
  "properties": {
    "addr:full":"50 Westgate Chichester West Sussex PO19 3HE",
    "addr:housenumber":"50",
    "addr:postcode":"po19 3he",
    "addr:street":"Westgate",
    "iso:country":"GB",
    "sg:address":"50 Westgate",
    "sg:city":"Chichester",
    "sg:classifiers":[
        {
            "category":"Professional",
            "subcategory":"Lawyer & Legal Services",
            "type":"Services"
        }
    ],
    "sg:phone":"+44 1243 780211",
    "sg:postcode":"PO19 3HE",
    "sg:province":"West Sussex",
    "sg:tags":[
        "solicitor"
    ],
    "wof:name":"Stone Milward",
    "wof:placetype":"venue"
},
  "geometry": {"coordinates":[-0.7868160009,50.8368721008],"type":"Point"}
}