{
  "type": "Feature",
  "properties": {
    "addr:full":"Rhiwlas, Llanwddyn Oswestry Shropshire SY10 0NN",
    "addr:postcode":"sy10 0nn",
    "addr:street":"Llanwddyn",
    "iso:country":"GB",
    "sg:address":"Rhiwlas, Llanwddyn",
    "sg:city":"Oswestry",
    "sg:classifiers":[
        {
            "category":"Farming",
            "subcategory":"Farm",
            "type":"Manufacturing & Wholesale Goods"
        }
    ],
    "sg:phone":"+44 1691 870222",
    "sg:postcode":"SY10 0NN",
    "sg:province":"Shropshire",
    "sg:tags":[
        "mixed",
        "crop"
    ],
    "wof:name":"J H & E M Lloyd",
    "wof:placetype":"venue"
},
  "geometry": {"coordinates":[-3.4524440765,52.7612037659],"type":"Point"}
}