{
  "type": "Feature",
  "properties": {
    "iso:country":"GB",
    "sg:address":"Long Lane, Attenborough, Beeston",
    "sg:city":"Nottingham",
    "sg:classifiers":[
        {
            "category":"Home & Garden",
            "subcategory":"Building Materials",
            "type":"Retail Goods"
        }
    ],
    "sg:phone":"+44 115 922 0660",
    "sg:postcode":"NG9 6BL",
    "sg:province":"Nottinghamshire",
    "sg:tags":[
        "ready",
        "mixed",
        "concrete"
    ],
    "wof:name":"Ready Mixed Concrete (East Midlands) Ltd.",
    "wof:placetype":"venue"
},
  "geometry": {"coordinates":[-1.220713973,52.9136199951],"type":"Point"}
}