{
  "type": "Feature",
  "properties": {
    "iso:country":"GB",
    "sg:address":"St Davids Road, Letterston",
    "sg:city":"Haverfordwest",
    "sg:classifiers":[
        {
            "category":"Education",
            "subcategory":"School",
            "type":"Public Place"
        }
    ],
    "sg:phone":"+44 1348 840248",
    "sg:postcode":"SA62 5SL",
    "sg:province":"Pembrokeshire",
    "sg:tags":[
        "local",
        "authority"
    ],
    "wof:name":"Letterston V C School",
    "wof:placetype":"venue"
},
  "geometry": {"coordinates":[-5.0072741508,51.9304618835],"type":"Point"}
}