{
  "type": "Feature",
  "properties": {
    "addr:full":"North Witham Road, South Witham Grantham Leicestershire NG33 5QQ",
    "addr:postcode":"ng33 5qq",
    "addr:street":"North Witham Road South Witham",
    "iso:country":"GB",
    "sg:address":"North Witham Road, South Witham",
    "sg:city":"Grantham",
    "sg:classifiers":[
        {
            "category":"Real Estate",
            "subcategory":"Developer",
            "type":"Services"
        }
    ],
    "sg:phone":"+44 1572 768477",
    "sg:postcode":"NG33 5QQ",
    "sg:province":"Leicestershire",
    "sg:tags":[
        "property"
    ],
    "wof:name":"Twyford Estates Ltd.",
    "wof:placetype":"venue"
},
  "geometry": {"coordinates":[-0.6275780201,52.7680282593],"type":"Point"}
}