{
  "type": "Feature",
  "properties": {
    "iso:country":"GB",
    "sg:address":"Kingmoor Road",
    "sg:city":"Carlisle",
    "sg:classifiers":[
        {
            "category":"Bars & Pubs",
            "type":"Food & Drink"
        }
    ],
    "sg:phone":"+44 1228 527253",
    "sg:postcode":"CA3 9PS",
    "sg:province":"Cumbria",
    "sg:tags":[
        "pubs",
        "inn"
    ],
    "wof:name":"The Redfern Inn",
    "wof:placetype":"venue"
},
  "geometry": {"coordinates":[-2.9564700127,54.911655426],"type":"Point"}
}