{
  "type": "Feature",
  "properties": {
    "iso:country":"GB",
    "sg:address":"134 Harley St",
    "sg:city":"West End",
    "sg:classifiers":[
        {
            "category":"Health Services",
            "subcategory":"Doctor",
            "type":"Services"
        }
    ],
    "sg:phone":"+44 20 7486 9493",
    "sg:postcode":"W1N 1AH",
    "sg:province":"Hampshire",
    "sg:tags":[
        "practitioners"
    ],
    "wof:name":"R.W Awad",
    "wof:placetype":"venue"
},
  "geometry": {"coordinates":[-0.148358,51.52261],"type":"Point"}
}