{
  "type": "Feature",
  "properties": {
    "addr:full":"105 St Johns Hill Sevenoaks Kent TN13 3PE",
    "addr:housenumber":"105",
    "addr:postcode":"tn13 3pe",
    "addr:street":"St Johns Hill",
    "iso:country":"GB",
    "sg:address":"105 St Johns Hill",
    "sg:city":"Sevenoaks",
    "sg:classifiers":[
        {
            "category":"Professional",
            "subcategory":"Management & Consulting",
            "type":"Services"
        }
    ],
    "sg:phone":"+44 1732 452473",
    "sg:postcode":"TN13 3PE",
    "sg:province":"Kent",
    "sg:tags":[
        "marketing",
        "consultant"
    ],
    "wof:name":"Gray Martin Associates",
    "wof:placetype":"venue"
},
  "geometry": {"coordinates":[0.1948789954,51.2872848511],"type":"Point"}
}