{
  "type": "Feature",
  "properties": {
    "addr:full":"260 Boldmere Rd Sutton Coldfield West Midlands B73 5LW",
    "addr:housenumber":"260",
    "addr:postcode":"b73 5lw",
    "addr:street":"Boldmere Rd",
    "iso:country":"GB",
    "sg:address":"260 Boldmere Rd",
    "sg:city":"Sutton Coldfield",
    "sg:classifiers":[
        {
            "category":"Professional",
            "subcategory":"Art Services",
            "type":"Services"
        }
    ],
    "sg:phone":"+44 121 373 8586",
    "sg:postcode":"B73 5LW",
    "sg:province":"West Midlands",
    "sg:tags":[
        "graphic",
        "designer"
    ],
    "wof:name":"T & C Designs",
    "wof:placetype":"venue"
},
  "geometry": {"coordinates":[-1.8381090164,52.5414657593],"type":"Point"}
}