{
  "type": "Feature",
  "properties": {
    "addr:full":"7 Station Road Edenbridge East Sussex TN8 5HP",
    "addr:housenumber":"7",
    "addr:postcode":"tn8 5hp",
    "addr:street":"Station Road",
    "iso:country":"GB",
    "sg:address":"7 Station Road",
    "sg:city":"Edenbridge",
    "sg:classifiers":[
        {
            "category":"Personal",
            "subcategory":"Beauty Salon",
            "type":"Services"
        }
    ],
    "sg:postcode":"TN8 5HP",
    "sg:province":"East Sussex",
    "sg:tags":[
        "unisex",
        "hairdresser"
    ],
    "wof:name":"Martins Hairdressing",
    "wof:placetype":"venue"
},
  "geometry": {"coordinates":[0.063794,51.199375],"type":"Point"}
}