{
  "type": "Feature",
  "properties": {
    "iso:country":"GB",
    "sg:address":"115b Church Road, Tarleton",
    "sg:city":"Preston",
    "sg:classifiers":[
        {
            "category":"Personal",
            "subcategory":"Beauty Salon",
            "type":"Services"
        }
    ],
    "sg:phone":"+44 1772 813913",
    "sg:postcode":"PR4 6UP",
    "sg:province":"Lancashire",
    "sg:tags":[
        "lady",
        "hairdresser"
    ],
    "wof:name":"Joy Charles",
    "wof:placetype":"venue"
},
  "geometry": {"coordinates":[-2.830084,53.680038],"type":"Point"}
}