{
  "type": "Feature",
  "properties": {
    "iso:country":"GB",
    "sg:address":"Warden, Cliff Park Close",
    "sg:city":"Peacehaven",
    "sg:classifiers":[
        {
            "category":"Social Services",
            "subcategory":"Adult Care",
            "type":"Services"
        },
        {
            "category":"Government",
            "subcategory":"Office",
            "type":"Public Place"
        }
    ],
    "sg:postcode":"BN10 8TR",
    "sg:province":"East Sussex",
    "sg:tags":[
        "housing",
        "local",
        "sheltered"
    ],
    "wof:name":"Cliff Park Close Sheltered Housing",
    "wof:placetype":"venue"
},
  "geometry": {"coordinates":[0.0208100006,50.7925262451],"type":"Point"}
}