{
  "type": "Feature",
  "properties": {
    "addr:full":"42 Bristol Road Gloucester Gloucestershire GL1 5SD",
    "addr:housenumber":"42",
    "addr:postcode":"gl1 5sd",
    "addr:street":"Bristol Road",
    "iso:country":"GB",
    "sg:address":"42 Bristol Road",
    "sg:city":"Gloucester",
    "sg:classifiers":[
        {
            "category":"Restaurant",
            "type":"Food & Drink"
        }
    ],
    "sg:phone":"+44 1452 300615",
    "sg:postcode":"GL1 5SD",
    "sg:province":"Gloucestershire",
    "sg:tags":[
        "indian"
    ],
    "wof:name":"INDIAN PARADISE TANDOORI RESTAURANT",
    "wof:placetype":"venue"
},
  "geometry": {"coordinates":[-2.252307,51.856041],"type":"Point"}
}