{
  "type": "Feature",
  "properties": {
    "iso:country":"GB",
    "sg:address":"19 County Arcade, Victoria Quarter",
    "sg:city":"Leeds",
    "sg:classifiers":[
        {
            "category":"Food & Beverages",
            "subcategory":"Candy",
            "type":"Retail Goods"
        }
    ],
    "sg:phone":"+44 113 245 2627",
    "sg:postcode":"LS1 6BW",
    "sg:province":"West Yorkshire",
    "sg:tags":[
        "confectioner"
    ],
    "wof:name":"Maxwell & Kennedy",
    "wof:placetype":"venue"
},
  "geometry": {"coordinates":[-1.540454,53.798336],"type":"Point"}
}