{
  "type": "Feature",
  "properties": {
    "addr:full":"Scotland Road Penrith Cumbria CA11 7NR",
    "addr:postcode":"ca11 7nr",
    "addr:street":"Scotland Road",
    "iso:country":"GB",
    "sg:address":"Scotland Road",
    "sg:city":"Penrith",
    "sg:classifiers":[
        {
            "category":"Autos & Motor Vehicles",
            "subcategory":"Fuel & Gas Station",
            "type":"Retail Goods"
        },
        {
            "category":"Retail",
            "subcategory":"Auto Repair",
            "type":"Services"
        }
    ],
    "sg:phone":"+44 1768 862456",
    "sg:postcode":"CA11 7NR",
    "sg:province":"Cumbria",
    "sg:tags":[
        "petrol",
        "garage",
        "modification"
    ],
    "wof:name":"Davidsons Garage Penrith Ltd",
    "wof:placetype":"venue"
},
  "geometry": {"coordinates":[-2.7594349384,54.6691932678],"type":"Point"}
}