{
  "type": "Feature",
  "properties": {
    "addr:full":"64 Bede Street, Braunstone Gate Leicester Leicestershire LE3 5LD",
    "addr:housenumber":"64",
    "addr:postcode":"le3 5ld",
    "addr:street":"Bede Street Braunstone Gate",
    "iso:country":"GB",
    "sg:address":"64 Bede Street, Braunstone Gate",
    "sg:city":"Leicester",
    "sg:classifiers":[
        {
            "category":"Manufacturing",
            "subcategory":"Textiles",
            "type":"Manufacturing & Wholesale Goods"
        }
    ],
    "sg:postcode":"LE3 5LD",
    "sg:province":"Leicestershire",
    "sg:tags":[
        "knitwear"
    ],
    "wof:name":"David Rudkin",
    "wof:placetype":"venue"
},
  "geometry": {"coordinates":[-1.1460950375,52.6310424805],"type":"Point"}
}