{
  "type": "Feature",
  "properties": {
    "iso:country":"GB",
    "sg:address":"14 New Hythe La",
    "sg:city":"Aylesford",
    "sg:classifiers":[
        {
            "category":"Shopping",
            "type":"Retail Goods"
        }
    ],
    "sg:phone":"+44 1732 781200",
    "sg:postcode":"ME20 6PN",
    "sg:province":"Kent",
    "sg:tags":[
        "merchant"
    ],
    "wof:name":"Willmot Pertwee",
    "wof:placetype":"venue"
},
  "geometry": {"coordinates":[0.44269,51.304611],"type":"Point"}
}