{
  "type": "Feature",
  "properties": {
    "addr:full":"Unit 8 Beachampton Business Park, Potash Milton Keynes Buckinghamshire MK19 6EA",
    "addr:housenumber":"unit 8 beachampton business",
    "addr:postcode":"mk19 6ea",
    "addr:street":"Park Potash",
    "iso:country":"GB",
    "sg:address":"Unit 8 Beachampton Business Park, Potash",
    "sg:city":"Milton Keynes",
    "sg:classifiers":[
        {
            "category":"Personal",
            "type":"Services"
        }
    ],
    "sg:postcode":"MK19 6EA",
    "sg:province":"Buckinghamshire",
    "sg:tags":[
        "delivery"
    ],
    "wof:name":"S T S Deliveries",
    "wof:placetype":"venue"
},
  "geometry": {"coordinates":[-0.727749,52.005856],"type":"Point"}
}