{
  "type": "Feature",
  "properties": {
    "iso:country":"GB",
    "sg:address":"196 Christchurch Road, West Parley",
    "sg:city":"Ferndown",
    "sg:classifiers":[
        {
            "category":"Bars & Pubs",
            "type":"Food & Drink"
        }
    ],
    "sg:postcode":"BH22 8SS",
    "sg:province":"Dorset",
    "sg:tags":[
        "pubs",
        "inn"
    ],
    "wof:name":"The Owl's Nest",
    "wof:placetype":"venue"
},
  "geometry": {"coordinates":[-1.889223,50.781879],"type":"Point"}
}