{
  "type": "Feature",
  "properties": {
    "iso:country":"GB",
    "sg:address":"Broad Street Common, Peterstone Wentlooge",
    "sg:city":"Cardiff",
    "sg:classifiers":[
        {
            "category":"Bars & Pubs",
            "type":"Food & Drink"
        },
        {
            "category":"Community Center",
            "subcategory":"Social",
            "type":"Public Place"
        }
    ],
    "sg:phone":"+44 1633 682031",
    "sg:postcode":"CF3 2TN",
    "sg:province":"Caerphilly",
    "sg:tags":[
        "pubs",
        "house",
        "inn",
        "activity"
    ],
    "wof:name":"Six Bells Hotel",
    "wof:placetype":"venue"
},
  "geometry": {"coordinates":[-3.0559129715,51.5163993835],"type":"Point"}
}