{
  "type": "Feature",
  "properties": {
    "iso:country":"GB",
    "sg:address":"Burghill, Oast House, Chiddingly",
    "sg:city":"Lewes",
    "sg:classifiers":[
        {
            "category":"Manufacturing",
            "subcategory":"Wood Products",
            "type":"Manufacturing & Wholesale Goods"
        },
        {
            "category":"Manufacturing",
            "subcategory":"Lumber",
            "type":"Manufacturing & Wholesale Goods"
        }
    ],
    "sg:phone":"+44 1825 872150",
    "sg:postcode":"BN8 6JF",
    "sg:province":"East Sussex",
    "sg:tags":[
        "merchant",
        "shaving",
        "sawmill",
        "timber"
    ],
    "wof:name":"Nigel Braden Timber",
    "wof:placetype":"venue"
},
  "geometry": {"coordinates":[0.194841,50.907276],"type":"Point"}
}