{
  "type": "Feature",
  "properties": {
    "addr:full":"Warden, Cox's Close, Stapleford Cambridge Cambridgeshire CB2 5SP",
    "addr:postcode":"cb2 5sp",
    "addr:street":"Cox'S Close",
    "iso:country":"GB",
    "sg:address":"Warden, Cox's Close, Stapleford",
    "sg:city":"Cambridge",
    "sg:classifiers":[
        {
            "category":"Social Services",
            "subcategory":"Adult Care",
            "type":"Services"
        },
        {
            "category":"Government",
            "subcategory":"Office",
            "type":"Public Place"
        }
    ],
    "sg:phone":"+44 1223 844540",
    "sg:postcode":"CB2 5SP",
    "sg:province":"Cambridgeshire",
    "sg:tags":[
        "housing",
        "local",
        "sheltered"
    ],
    "wof:name":"Cox's Close Sheltered Housing",
    "wof:placetype":"venue"
},
  "geometry": {"coordinates":[0.14859,52.145199],"type":"Point"}
}