{
  "type": "Feature",
  "properties": {
    "addr:full":"Chapel Street Tregaron Ceredigion SY25 6HD",
    "addr:postcode":"sy25 6hd",
    "addr:street":"Chapel Street",
    "iso:country":"GB",
    "sg:address":"Chapel Street",
    "sg:city":"Tregaron",
    "sg:classifiers":[
        {
            "category":"Cafe",
            "type":"Food & Drink"
        }
    ],
    "sg:postcode":"SY25 6HD",
    "sg:province":"Ceredigion",
    "sg:tags":[
        "tea",
        "room"
    ],
    "wof:name":"Cambrian Coffee Shop",
    "wof:placetype":"venue"
},
  "geometry": {"coordinates":[-3.936046,52.219116],"type":"Point"}
}