{
  "type": "Feature",
  "properties": {
    "addr:full":"17 Aird Street, Portsoy Banff Aberdeenshire AB45 2RB",
    "addr:housenumber":"17",
    "addr:postcode":"ab45 2rb",
    "addr:street":"Aird Street",
    "iso:country":"GB",
    "sg:address":"17 Aird Street, Portsoy",
    "sg:city":"Banff",
    "sg:classifiers":[
        {
            "category":"Professional",
            "subcategory":"Business Services",
            "type":"Services"
        }
    ],
    "sg:postcode":"AB45 2RB",
    "sg:province":"Aberdeenshire",
    "sg:tags":[
        "answering"
    ],
    "wof:name":"First Impressions",
    "wof:placetype":"venue"
},
  "geometry": {"coordinates":[-2.6865999699,57.6811752319],"type":"Point"}
}