{
  "type": "Feature",
  "properties": {
    "addr:full":"2 Derwent Place Newcastle Staffordshire ST5 9HG",
    "addr:housenumber":"2",
    "addr:postcode":"st5 9hg",
    "addr:street":"Derwent Place",
    "iso:country":"GB",
    "sg:address":"2 Derwent Place",
    "sg:city":"Newcastle",
    "sg:classifiers":[
        {
            "category":"Organizations",
            "subcategory":"Membership Organization",
            "type":"Services"
        }
    ],
    "sg:phone":"+44 1782 614297",
    "sg:postcode":"ST5 9HG",
    "sg:province":"Staffordshire",
    "sg:tags":[
        "club"
    ],
    "wof:name":"Newcastle Working Mens Club",
    "wof:placetype":"venue"
},
  "geometry": {"coordinates":[-2.2327950001,53.022190094],"type":"Point"}
}