{
  "type": "Feature",
  "properties": {
    "iso:country":"GB",
    "sg:address":"Varnak Ho, 25a Abbey Manufacturing Est",
    "sg:city":"Wembley",
    "sg:classifiers":[
        {
            "category":"Professional",
            "subcategory":"Business Services",
            "type":"Services"
        }
    ],
    "sg:postcode":"HA0 1NR",
    "sg:province":"Greater London",
    "sg:tags":[
        "import",
        "export",
        "agent"
    ],
    "wof:name":"U P D Import Export Ltd",
    "wof:placetype":"venue"
},
  "geometry": {"coordinates":[-0.29182,51.539871],"type":"Point"}
}