{
  "type": "Feature",
  "properties": {
    "addr:full":"24 London Road Bromley Kent BR1 3QR",
    "addr:housenumber":"24",
    "addr:postcode":"br1 3qr",
    "addr:street":"London Road",
    "iso:country":"GB",
    "sg:address":"24 London Road",
    "sg:city":"Bromley",
    "sg:classifiers":[
        {
            "category":"Cafe",
            "type":"Food & Drink"
        }
    ],
    "sg:postcode":"BR1 3QR",
    "sg:province":"Kent",
    "sg:tags":[
        "tea",
        "room"
    ],
    "wof:name":"Cafe Kai",
    "wof:placetype":"venue"
},
  "geometry": {"coordinates":[0.0108359996,51.409122467],"type":"Point"}
}