{
  "type": "Feature",
  "properties": {
    "iso:country":"GB",
    "sg:address":"23 Aston Park Road, Queensferry",
    "sg:city":"Deeside",
    "sg:classifiers":[
        {
            "category":"Shopping",
            "subcategory":"Discount & Variety Stores",
            "type":"Retail Goods"
        }
    ],
    "sg:postcode":"CH5 1UA",
    "sg:province":"Flintshire",
    "sg:tags":[
        "centre"
    ],
    "wof:name":"Aston Thrift",
    "wof:placetype":"venue"
},
  "geometry": {"coordinates":[-3.040012,53.200428],"type":"Point"}
}