{
  "type": "Feature",
  "properties": {
    "iso:country":"GB",
    "sg:address":"2 Kenilworth Rd",
    "sg:city":"Stirling",
    "sg:classifiers":[
        {
            "category":"Education",
            "subcategory":"University",
            "type":"Public Place"
        }
    ],
    "sg:phone":"+44 1786 834814",
    "sg:postcode":"FK9 4DU",
    "sg:province":"Clackmannanshire",
    "sg:tags":[
        "higher"
    ],
    "wof:name":"Viewforth School Of Healthcare",
    "wof:placetype":"venue"
},
  "geometry": {"coordinates":[-3.960273,56.146347],"type":"Point"}
}