{
  "type": "Feature",
  "properties": {
    "addr:full":"22 Church Street, Holbeach Spalding Cambridgeshire PE12 7LL",
    "addr:housenumber":"22",
    "addr:postcode":"pe12 7ll",
    "addr:street":"Church Street",
    "iso:country":"GB",
    "sg:address":"22 Church Street, Holbeach",
    "sg:city":"Spalding",
    "sg:classifiers":[
        {
            "category":"Professional",
            "subcategory":"Accounting & Tax Preparation",
            "type":"Services"
        }
    ],
    "sg:phone":"+44 1406 424680",
    "sg:postcode":"PE12 7LL",
    "sg:province":"Cambridgeshire",
    "sg:tags":[
        "accountant"
    ],
    "wof:name":"Duncan Temple",
    "wof:placetype":"venue"
},
  "geometry": {"coordinates":[0.0134220002,52.8033027649],"type":"Point"}
}