{
  "type": "Feature",
  "properties": {
    "iso:country":"GB",
    "sg:address":"P O Box 7",
    "sg:city":"Caterham",
    "sg:classifiers":[
        {
            "category":"Shopping",
            "subcategory":"Discount & Variety Stores",
            "type":"Retail Goods"
        }
    ],
    "sg:postcode":"CR3 6UB",
    "sg:province":"Surrey",
    "sg:tags":[
        "cleaning",
        "supply"
    ],
    "wof:name":"Formula 7 Marketing",
    "wof:placetype":"venue"
},
  "geometry": {"coordinates":[-0.078669,51.277809],"type":"Point"}
}