{
  "type": "Feature",
  "properties": {
    "addr:full":"Elwell Street West Bromwich West Midlands B70 0DL",
    "addr:postcode":"b70 0dl",
    "addr:street":"Elwell Street",
    "iso:country":"GB",
    "sg:address":"Elwell Street",
    "sg:city":"West Bromwich",
    "sg:classifiers":[
        {
            "category":"Manufacturing",
            "subcategory":"Metals",
            "type":"Manufacturing & Wholesale Goods"
        }
    ],
    "sg:phone":"+44 121 522 3332",
    "sg:postcode":"B70 0DL",
    "sg:province":"West Midlands",
    "sg:tags":[
        "steel",
        "mnfrs"
    ],
    "wof:name":"B C D Cold Rolled Strip Ltd.",
    "wof:placetype":"venue"
},
  "geometry": {"coordinates":[-2.02515,52.529411],"type":"Point"}
}