{
  "type": "Feature",
  "properties": {
    "iso:country":"GB",
    "sg:address":"9 Brendon Road",
    "sg:city":"Watchet",
    "sg:classifiers":[
        {
            "category":"Professional",
            "subcategory":"Accounting & Tax Preparation",
            "type":"Services"
        }
    ],
    "sg:phone":"+44 1984 631750",
    "sg:postcode":"TA23 0AU",
    "sg:province":"Somerset",
    "sg:tags":[
        "accountant",
        "activity"
    ],
    "wof:name":"Lockyer & Co",
    "wof:placetype":"venue"
},
  "geometry": {"coordinates":[-3.330963,51.179459],"type":"Point"}
}