{
  "type": "Feature",
  "properties": {
    "iso:country":"GB",
    "sg:address":"47 Euston Rd",
    "sg:city":"Morecambe",
    "sg:classifiers":[
        {
            "category":"Shopping",
            "subcategory":"News",
            "type":"Retail Goods"
        }
    ],
    "sg:phone":"+44 1524 420909",
    "sg:postcode":"LA4 5DQ",
    "sg:province":"Lancashire",
    "sg:tags":[
        "newsagent"
    ],
    "wof:name":"Supacigs",
    "wof:placetype":"venue"
},
  "geometry": {"coordinates":[-2.863879,54.071892],"type":"Point"}
}