{
  "type": "Feature",
  "properties": {
    "iso:country":"GB",
    "sg:address":"Midlands & Wales Office, Somerville House, 20-22 Harbourne Road",
    "sg:city":"Birmingham",
    "sg:classifiers":[
        {
            "category":"Communications",
            "subcategory":"Newspaper",
            "type":"Services"
        }
    ],
    "sg:phone":"+44 121 454 0922",
    "sg:postcode":"B15 2AA",
    "sg:province":"West Midlands",
    "sg:tags":[
        "magazine"
    ],
    "wof:name":"The Financial Times Ltd.",
    "wof:placetype":"venue"
},
  "geometry": {"coordinates":[-1.9213199615,52.4711685181],"type":"Point"}
}