{
  "type": "Feature",
  "properties": {
    "addr:full":"327 Wakefield Road, Denby Dale Huddersfield South Yorkshire HD8 8RX",
    "addr:housenumber":"327",
    "addr:postcode":"hd8 8rx",
    "addr:street":"Wakefield Road",
    "iso:country":"GB",
    "sg:address":"327 Wakefield Road, Denby Dale",
    "sg:city":"Huddersfield",
    "sg:classifiers":[
        {
            "category":"Professional",
            "subcategory":"Art Services",
            "type":"Services"
        },
        {
            "category":"Military Area",
            "subcategory":"Air Force Base",
            "type":"Public Place"
        }
    ],
    "sg:phone":"+44 1484 864949",
    "sg:postcode":"HD8 8RX",
    "sg:province":"South Yorkshire",
    "sg:tags":[
        "picture",
        "frame",
        "restoration",
        "cleaning"
    ],
    "wof:name":"Helios Publications & Gallery",
    "wof:placetype":"venue"
},
  "geometry": {"coordinates":[-1.6539950371,53.5732917786],"type":"Point"}
}