{
  "type": "Feature",
  "properties": {
    "addr:full":"Afonig, St Clears Carmarthen Carmarthenshire SA33 4AD",
    "addr:postcode":"sa33 4ad",
    "iso:country":"GB",
    "sg:address":"Afonig, St Clears",
    "sg:city":"Carmarthen",
    "sg:classifiers":[
        {
            "category":"Professional",
            "subcategory":"Management & Consulting",
            "type":"Services"
        }
    ],
    "sg:postcode":"SA33 4AD",
    "sg:province":"Carmarthenshire",
    "sg:tags":[
        "consultant",
        "business"
    ],
    "wof:name":"R M Greenhalgh",
    "wof:placetype":"venue"
},
  "geometry": {"coordinates":[-4.4990901947,51.8198318481],"type":"Point"}
}