{
  "type": "Feature",
  "properties": {
    "iso:country":"GB",
    "sg:address":"Unit 5, 1-4 North Rd",
    "sg:city":"Durham",
    "sg:classifiers":[
        {
            "category":"Travel",
            "subcategory":"Travel Agent",
            "type":"Entertainment"
        }
    ],
    "sg:phone":"+44 191 384 7690",
    "sg:postcode":"DH1 4SH",
    "sg:province":"Durham",
    "wof:name":"Hays Travel",
    "wof:placetype":"venue"
},
  "geometry": {"coordinates":[-1.579167,54.776272],"type":"Point"}
}