{
  "type": "Feature",
  "properties": {
    "iso:country":"GB",
    "sg:address":"9 Nelson Road, New Rossington",
    "sg:city":"Doncaster",
    "sg:classifiers":[
        {
            "category":"Health Services",
            "subcategory":"Optometrist",
            "type":"Services"
        }
    ],
    "sg:phone":"+44 1302 868638",
    "sg:postcode":"DN11 0PJ",
    "sg:province":"South Yorkshire",
    "sg:tags":[
        "optician"
    ],
    "wof:name":"Bell Bros (Opticians)",
    "wof:placetype":"venue"
},
  "geometry": {"coordinates":[-1.080019,53.478607],"type":"Point"}
}