{
  "type": "Feature",
  "properties": {
    "iso:country":"GB",
    "sg:address":"17 Cavendish Road",
    "sg:city":"Rotherham",
    "sg:classifiers":[
        {
            "category":"Sports & Exercise",
            "subcategory":"Gym",
            "type":"Entertainment"
        }
    ],
    "sg:postcode":"S61 1BW",
    "sg:province":"South Yorkshire",
    "sg:tags":[
        "club",
        "fitness",
        "health",
        "centre"
    ],
    "wof:name":"Julies Fitness 'N' Fun",
    "wof:placetype":"venue"
},
  "geometry": {"coordinates":[-1.378597,53.429348],"type":"Point"}
}