{
  "type": "Feature",
  "properties": {
    "iso:country":"GB",
    "sg:address":"21 Beechway Lincoln Gdns",
    "sg:city":"Scunthorpe",
    "sg:classifiers":[
        {
            "category":"Organizations",
            "subcategory":"Non-profit Organization",
            "type":"Services"
        }
    ],
    "sg:postcode":"DN16 2HF",
    "sg:province":"Lincolnshire",
    "sg:tags":[
        "organisation",
        "voluntary",
        "charity"
    ],
    "wof:name":"Disc Outreach",
    "wof:placetype":"venue"
},
  "geometry": {"coordinates":[-0.646329999,53.5726852417],"type":"Point"}
}