{
  "type": "Feature",
  "properties": {
    "iso:country":"GB",
    "sg:address":"10 Old Burlington Street",
    "sg:city":"London",
    "sg:classifiers":[
        {
            "category":"Communications",
            "type":"Services"
        }
    ],
    "sg:phone":"+44 20 7439 2738",
    "sg:postcode":"W1S 3AQ",
    "sg:province":"Greater London",
    "sg:tags":[
        "audio-visual"
    ],
    "wof:name":"Extra Affairs",
    "wof:placetype":"venue"
},
  "geometry": {"coordinates":[-0.14081,51.510811],"type":"Point"}
}