{
  "type": "Feature",
  "properties": {
    "addr:full":"767 Attercliffe Rd Sheffield South Yorkshire S9 3RF",
    "addr:housenumber":"767",
    "addr:postcode":"s9 3rf",
    "addr:street":"Attercliffe Rd",
    "iso:country":"GB",
    "sg:address":"767 Attercliffe Rd",
    "sg:city":"Sheffield",
    "sg:classifiers":[
        {
            "category":"Home & Garden",
            "subcategory":"Household Appliances",
            "type":"Retail Goods"
        }
    ],
    "sg:phone":"+44 114 256 1888",
    "sg:postcode":"S9 3RF",
    "sg:province":"South Yorkshire",
    "sg:tags":[
        "cleaner",
        "vacuum"
    ],
    "wof:name":"Environmental Appliances Tristar UK",
    "wof:placetype":"venue"
},
  "geometry": {"coordinates":[-1.429976,53.395813],"type":"Point"}
}