{
  "type": "Feature",
  "properties": {
    "iso:country":"GB",
    "sg:address":"Crinan Cottage, Moss Road",
    "sg:city":"Dalbeattie",
    "sg:classifiers":[
        {
            "category":"Transit Center",
            "subcategory":"Passenger",
            "type":"Transportation"
        }
    ],
    "sg:phone":"+44 1556 610713",
    "sg:postcode":"DG5 4NW",
    "sg:province":"Dumfries and Galloway",
    "sg:tags":[
        "boarding",
        "kennel",
        "catteries"
    ],
    "wof:name":"Crinan Cottage Boarding Kennels",
    "wof:placetype":"venue"
},
  "geometry": {"coordinates":[-3.823039,54.933456],"type":"Point"}
}