{
  "type": "Feature",
  "properties": {
    "addr:full":"Priory Street Monmouth Monmouthshire NP5 3BR",
    "addr:postcode":"np5 3br",
    "addr:street":"Priory Street",
    "iso:country":"GB",
    "sg:address":"Priory Street",
    "sg:city":"Monmouth",
    "sg:classifiers":[
        {
            "category":"Government",
            "subcategory":"Court House",
            "type":"Public Place"
        }
    ],
    "sg:phone":"+44 1600 713291",
    "sg:postcode":"NP5 3BR",
    "sg:province":"Monmouthshire",
    "wof:name":"County Courts",
    "wof:placetype":"venue"
},
  "geometry": {"coordinates":[-2.713482,51.814068],"type":"Point"}
}