{
  "type": "Feature",
  "properties": {
    "iso:country":"GB",
    "sg:address":"Suite 5-6, 1st Floor 151 Stamford Hill",
    "sg:city":"Stoke Newington",
    "sg:classifiers":[
        {
            "category":"Professional",
            "subcategory":"Lawyer & Legal Services",
            "type":"Services"
        }
    ],
    "sg:phone":"+44 20 8809 5080",
    "sg:postcode":"N16 5LG",
    "sg:province":"Greater London",
    "sg:tags":[
        "solicitor"
    ],
    "wof:name":"Hayat & Co",
    "wof:placetype":"venue"
},
  "geometry": {"coordinates":[-0.07251,51.57378],"type":"Point"}
}