{
  "type": "Feature",
  "properties": {
    "iso:country":"GB",
    "sg:address":"Fidelis, Manchester Road, Sway",
    "sg:city":"Lymington",
    "sg:classifiers":[
        {
            "category":"Building & Trades",
            "subcategory":"Construction",
            "type":"Services"
        }
    ],
    "sg:phone":"+44 1590 682289",
    "sg:postcode":"SO41 6AS",
    "sg:province":"Hampshire",
    "sg:tags":[
        "builder"
    ],
    "wof:name":"Jfe Partnership",
    "wof:placetype":"venue"
},
  "geometry": {"coordinates":[-1.601032,50.785069],"type":"Point"}
}