{
  "type": "Feature",
  "properties": {
    "addr:full":"444 Linthorpe Road Middlesbrough North Yorkshire TS5 6HW",
    "addr:housenumber":"444",
    "addr:postcode":"ts5 6hw",
    "addr:street":"Linthorpe Road",
    "iso:country":"GB",
    "sg:address":"444 Linthorpe Road",
    "sg:city":"Middlesbrough",
    "sg:classifiers":[
        {
            "category":"Food & Beverages",
            "subcategory":"Fruits & Vegetables",
            "type":"Retail Goods"
        }
    ],
    "sg:phone":"+44 1642 818547",
    "sg:postcode":"TS5 6HW",
    "sg:province":"North Yorkshire",
    "sg:tags":[
        "greengrocer"
    ],
    "wof:name":"Fruit Fayre",
    "wof:placetype":"venue"
},
  "geometry": {"coordinates":[-1.2424449921,54.5611038208],"type":"Point"}
}