{
  "type": "Feature",
  "properties": {
    "addr:full":"Unit 29 Buspace Studios Conlan St London Greater London W10 5AP",
    "addr:housenumber":"unit 29",
    "addr:postcode":"w10 5ap",
    "addr:street":"Conlan St",
    "iso:country":"GB",
    "sg:address":"Unit 29 Buspace Studios Conlan St",
    "sg:city":"London",
    "sg:classifiers":[
        {
            "category":"Communications",
            "subcategory":"Film & Video Production",
            "type":"Services"
        }
    ],
    "sg:phone":"+44 20 8964 3559",
    "sg:postcode":"W10 5AP",
    "sg:province":"Greater London",
    "sg:tags":[
        "recording",
        "studio"
    ],
    "wof:name":"Doves Hit Songs Ltd",
    "wof:placetype":"venue"
},
  "geometry": {"coordinates":[-0.2112500072,51.5254211426],"type":"Point"}
}