{
  "type": "Feature",
  "properties": {
    "iso:country":"GB",
    "sg:address":"Dene Drive",
    "sg:city":"Winsford",
    "sg:classifiers":[
        {
            "category":"Community Center",
            "type":"Public Place"
        },
        {
            "category":"Government",
            "subcategory":"Office",
            "type":"Public Place"
        }
    ],
    "sg:phone":"+44 1606 592944",
    "sg:postcode":"CW7 1AX",
    "sg:province":"Cheshire",
    "sg:tags":[
        "entertainment",
        "local",
        "centre"
    ],
    "wof:name":"The Civic Hall",
    "wof:placetype":"venue"
},
  "geometry": {"coordinates":[-2.529714,53.190685],"type":"Point"}
}