{
  "type": "Feature",
  "properties": {
    "addr:full":"265 Haselbury Road London Greater London N9 9TL",
    "addr:housenumber":"265",
    "addr:postcode":"n9 9tl",
    "addr:street":"Haselbury Road",
    "iso:country":"GB",
    "sg:address":"265 Haselbury Road",
    "sg:city":"London",
    "sg:classifiers":[
        {
            "category":"Shopping",
            "subcategory":"News",
            "type":"Retail Goods"
        }
    ],
    "sg:phone":"+44 20 8807 7434",
    "sg:postcode":"N9 9TL",
    "sg:province":"Greater London",
    "sg:tags":[
        "newsagent"
    ],
    "wof:name":"Sri Sai Krupa",
    "wof:placetype":"venue"
},
  "geometry": {"coordinates":[-0.074357,51.624077],"type":"Point"}
}