{
  "type": "Feature",
  "properties": {
    "addr:full":"252 Newchurch Road Bacup Lancashire OL13 0UE",
    "addr:housenumber":"252",
    "addr:postcode":"ol13 0ue",
    "addr:street":"Newchurch Road",
    "iso:country":"GB",
    "sg:address":"252 Newchurch Road",
    "sg:city":"Bacup",
    "sg:classifiers":[
        {
            "category":"Retail",
            "subcategory":"Auto Repair",
            "type":"Services"
        }
    ],
    "sg:postcode":"OL13 0UE",
    "sg:province":"Lancashire",
    "sg:tags":[
        "modification",
        "garage"
    ],
    "wof:name":"Bowness Garage",
    "wof:placetype":"venue"
},
  "geometry": {"coordinates":[-2.218893,53.692841],"type":"Point"}
}