{
  "type": "Feature",
  "properties": {
    "addr:full":"Fleet Services, 46 Morfa Road Swansea Neath Port Talbot SA1 2EL",
    "addr:housenumber":"46",
    "addr:postcode":"sa1 2el",
    "addr:street":"Morfa Road",
    "iso:country":"GB",
    "sg:address":"Fleet Services, 46 Morfa Road",
    "sg:city":"Swansea",
    "sg:classifiers":[
        {
            "category":"Farming",
            "subcategory":"Dairy Farm",
            "type":"Manufacturing & Wholesale Goods"
        }
    ],
    "sg:postcode":"SA1 2EL",
    "sg:province":"Neath Port Talbot",
    "wof:name":"Unigate Dairies Ltd.",
    "wof:placetype":"venue"
},
  "geometry": {"coordinates":[-3.940928936,51.6231536865],"type":"Point"}
}