{
  "type": "Feature",
  "properties": {
    "addr:full":"Frith Manor Farm, Lingfield Road East Grinstead East Sussex RH19 2JW",
    "addr:postcode":"rh19 2jw",
    "addr:street":"Frith;Lingfield Road",
    "iso:country":"GB",
    "sg:address":"Frith Manor Farm, Lingfield Road",
    "sg:city":"East Grinstead",
    "sg:classifiers":[
        {
            "category":"Food & Beverages",
            "subcategory":"Liquor & Beverages",
            "type":"Retail Goods"
        },
        {
            "category":"Utilities",
            "subcategory":"Natural Gas",
            "type":"Services"
        }
    ],
    "sg:phone":"+44 1342 871555",
    "sg:postcode":"RH19 2JW",
    "sg:province":"East Sussex",
    "sg:tags":[
        "wholesale",
        "beer",
        "wine",
        "spirit",
        "wines"
    ],
    "wof:name":"Park Lane Champagne Ltd.",
    "wof:placetype":"venue"
},
  "geometry": {"coordinates":[-0.0075679999,51.1239814758],"type":"Point"}
}