{
  "type": "Feature",
  "properties": {
    "iso:country":"GB",
    "sg:address":"The Old Farm",
    "sg:city":"Witney",
    "sg:classifiers":[
        {
            "category":"Shopping",
            "subcategory":"Stationery & Office Supplies",
            "type":"Retail Goods"
        },
        {
            "category":"Professional",
            "subcategory":"Computer Services",
            "type":"Services"
        }
    ],
    "sg:phone":"+44 870 990 8079",
    "sg:postcode":"OX29 9PX",
    "sg:province":"Oxfordshire",
    "sg:tags":[
        "development",
        "recording",
        "software",
        "machine",
        "time"
    ],
    "wof:name":"Thinking Software Ltd.",
    "wof:placetype":"venue"
},
  "geometry": {"coordinates":[-1.548569,51.826035],"type":"Point"}
}