{
  "type": "Feature",
  "properties": {
    "iso:country":"GB",
    "sg:address":"41 Wellowgate",
    "sg:city":"Grimsby",
    "sg:classifiers":[
        {
            "category":"Shopping",
            "subcategory":"News",
            "type":"Retail Goods"
        }
    ],
    "sg:phone":"+44 1472 251407",
    "sg:postcode":"DN32 0RA",
    "sg:province":"Lincolnshire",
    "sg:tags":[
        "newsagent"
    ],
    "wof:name":"Wellowgate Newsagents",
    "wof:placetype":"venue"
},
  "geometry": {"coordinates":[-0.0859630033,53.56199646],"type":"Point"}
}