{
  "type": "Feature",
  "properties": {
    "iso:country":"GB",
    "sg:address":"Brook Mill, Brook Street, Adlington",
    "sg:city":"Chorley",
    "sg:classifiers":[
        {
            "category":"Building & Trades",
            "subcategory":"Construction",
            "type":"Services"
        }
    ],
    "sg:phone":"+44 1257 482231",
    "sg:postcode":"PR6 9LE",
    "sg:province":"Lancashire",
    "sg:tags":[
        "joinery"
    ],
    "wof:name":"Eden Joinery",
    "wof:placetype":"venue"
},
  "geometry": {"coordinates":[-2.600064,53.615597],"type":"Point"}
}