{
  "type": "Feature",
  "properties": {
    "addr:full":"Old Woolwich Road London Greater London SE10 9NY",
    "addr:postcode":"se10 9ny",
    "addr:street":"Old Woolwich Road",
    "iso:country":"GB",
    "sg:address":"Old Woolwich Road",
    "sg:city":"London",
    "sg:classifiers":[
        {
            "category":"Education",
            "subcategory":"School",
            "type":"Public Place"
        },
        {
            "category":"Government",
            "subcategory":"Office",
            "type":"Public Place"
        }
    ],
    "sg:phone":"+44 20 8858 3572",
    "sg:postcode":"SE10 9NY",
    "sg:province":"Greater London",
    "sg:tags":[
        "local",
        "authority"
    ],
    "wof:name":"Meridian Primary School",
    "wof:placetype":"venue"
},
  "geometry": {"coordinates":[0.002714,51.485344],"type":"Point"}
}