{
  "type": "Feature",
  "properties": {
    "iso:country":"GB",
    "sg:address":"289 Duke Street",
    "sg:city":"Glasgow",
    "sg:classifiers":[
        {
            "category":"Home & Garden",
            "subcategory":"Furniture",
            "type":"Retail Goods"
        }
    ],
    "sg:postcode":"G31 1HX",
    "sg:province":"Glasgow City",
    "wof:name":"Abbey Furniture",
    "wof:placetype":"venue"
},
  "geometry": {"coordinates":[-4.225893,55.858566],"type":"Point"}
}