{
  "type": "Feature",
  "properties": {
    "addr:full":"64 London Rd Liverpool Merseyside L3 5NF",
    "addr:housenumber":"64",
    "addr:postcode":"l3 5nf",
    "addr:street":"London Rd",
    "iso:country":"GB",
    "sg:address":"64 London Rd",
    "sg:city":"Liverpool",
    "sg:classifiers":[
        {
            "category":"Home & Garden",
            "subcategory":"Home Furnishings",
            "type":"Retail Goods"
        }
    ],
    "sg:phone":"+44 151 708 0529",
    "sg:postcode":"L3 5NF",
    "sg:province":"Merseyside",
    "sg:tags":[
        "blind",
        "curtain",
        "fitting"
    ],
    "wof:name":"Russells",
    "wof:placetype":"venue"
},
  "geometry": {"coordinates":[-2.9759531021,53.4090995789],"type":"Point"}
}