{
  "type": "Feature",
  "properties": {
    "addr:full":"91 High Street, Long Eaton Nottingham Derbyshire NG10 1JB",
    "addr:housenumber":"91",
    "addr:postcode":"ng10 1jb",
    "addr:street":"High Street",
    "iso:country":"GB",
    "sg:address":"91 High Street, Long Eaton",
    "sg:city":"Nottingham",
    "sg:classifiers":[
        {
            "category":"Community Center",
            "subcategory":"Social",
            "type":"Public Place"
        }
    ],
    "sg:phone":"+44 115 946 5820",
    "sg:postcode":"NG10 1JB",
    "sg:province":"Derbyshire",
    "sg:tags":[
        "frozen",
        "food",
        "freezer",
        "centre"
    ],
    "wof:name":"Heron Frozen Foods Ltd.",
    "wof:placetype":"venue"
},
  "geometry": {"coordinates":[-1.2704069614,52.8974952698],"type":"Point"}
}