{
  "type": "Feature",
  "properties": {
    "addr:full":"41 Lanark Road Carluke South Lanarkshire ML8 4HE",
    "addr:housenumber":"41",
    "addr:postcode":"ml8 4he",
    "addr:street":"Lanark Road",
    "iso:country":"GB",
    "sg:address":"41 Lanark Road",
    "sg:city":"Carluke",
    "sg:classifiers":[
        {
            "category":"Building & Trades",
            "subcategory":"Construction",
            "type":"Services"
        }
    ],
    "sg:postcode":"ML8 4HE",
    "sg:province":"South Lanarkshire",
    "sg:tags":[
        "dry",
        "lining",
        "plasterers",
        "screeders"
    ],
    "wof:name":"Camplemans",
    "wof:placetype":"venue"
},
  "geometry": {"coordinates":[-3.834471941,55.7283630371],"type":"Point"}
}