{
  "type": "Feature",
  "properties": {
    "iso:country":"GB",
    "sg:address":"46 Belvedere Mews",
    "sg:city":"Stroud",
    "sg:classifiers":[
        {
            "category":"Professional",
            "subcategory":"Management & Consulting",
            "type":"Services"
        }
    ],
    "sg:phone":"+44 1453 887499",
    "sg:postcode":"GL6 8PF",
    "sg:province":"Gloucestershire",
    "sg:tags":[
        "consultant",
        "business"
    ],
    "wof:name":"Lawtec",
    "wof:placetype":"venue"
},
  "geometry": {"coordinates":[-2.161058,51.7202],"type":"Point"}
}