{
  "type": "Feature",
  "properties": {
    "iso:country":"GB",
    "sg:address":"Baileys Court, Webbs Wood Road, Bradley Stoke",
    "sg:city":"Bristol",
    "sg:classifiers":[
        {
            "category":"Education",
            "subcategory":"University",
            "type":"Public Place"
        }
    ],
    "sg:phone":"+44 117 979 4190",
    "sg:postcode":"BS13 8EJ",
    "sg:province":"City of Bristol",
    "sg:tags":[
        "adult"
    ],
    "wof:name":"Swindon College",
    "wof:placetype":"venue"
},
  "geometry": {"coordinates":[-2.62492,51.417648],"type":"Point"}
}