{
  "type": "Feature",
  "properties": {
    "addr:full":"65 Market Place Cannock Staffordshire WS11 1BP",
    "addr:housenumber":"65",
    "addr:postcode":"ws11 1bp",
    "addr:street":"Market Place",
    "iso:country":"GB",
    "sg:address":"65 Market Place",
    "sg:city":"Cannock",
    "sg:classifiers":[
        {
            "category":"Shopping",
            "subcategory":"Shoes",
            "type":"Retail Goods"
        }
    ],
    "sg:phone":"+44 1543 468836",
    "sg:postcode":"WS11 1BP",
    "sg:province":"Staffordshire",
    "wof:name":"Cannock Shoe Repairs",
    "wof:placetype":"venue"
},
  "geometry": {"coordinates":[-2.0321850777,52.6894073486],"type":"Point"}
}