{
  "type": "Feature",
  "properties": {
    "addr:full":"19 Greenwood Rd Crowthorne Berkshire RG45 6QX",
    "addr:housenumber":"19",
    "addr:postcode":"rg45 6qx",
    "addr:street":"Greenwood Rd",
    "iso:country":"GB",
    "sg:address":"19 Greenwood Rd",
    "sg:city":"Crowthorne",
    "sg:classifiers":[
        {
            "category":"Food & Beverages",
            "subcategory":"Liquor & Beverages",
            "type":"Retail Goods"
        }
    ],
    "sg:phone":"+44 1344 750868",
    "sg:postcode":"RG45 6QX",
    "sg:province":"Berkshire",
    "sg:tags":[
        "beer",
        "spirit",
        "wines"
    ],
    "wof:name":"Victoria Wine",
    "wof:placetype":"venue"
},
  "geometry": {"coordinates":[-0.799736,51.377155],"type":"Point"}
}