{
  "type": "Feature",
  "properties": {
    "iso:country":"GB",
    "sg:address":"9 William Street",
    "sg:city":"Cleethorpes",
    "sg:classifiers":[
        {
            "category":"Professional",
            "subcategory":"Detective & Security Services",
            "type":"Services"
        }
    ],
    "sg:phone":"+44 1472 291002",
    "sg:postcode":"DN35 8PT",
    "sg:province":"Lincolnshire",
    "wof:name":"Granada Securities",
    "wof:placetype":"venue"
},
  "geometry": {"coordinates":[-0.0311110001,53.5556640625],"type":"Point"}
}