{
  "type": "Feature",
  "properties": {
    "iso:country":"GB",
    "sg:address":"370 Southmead Road, Westbury-on-trym",
    "sg:city":"Bristol",
    "sg:classifiers":[
        {
            "category":"Military Area",
            "subcategory":"Air Force Base",
            "type":"Public Place"
        }
    ],
    "sg:phone":"+44 117 959 0590",
    "sg:postcode":"BS10 5LP",
    "sg:province":"City of Bristol",
    "sg:tags":[
        "taxi",
        "hire",
        "private"
    ],
    "wof:name":"Crown Cars",
    "wof:placetype":"venue"
},
  "geometry": {"coordinates":[-2.5958309174,51.4981079102],"type":"Point"}
}