{
  "type": "Feature",
  "properties": {
    "addr:full":"Unit 12b Scar Lane, Milnsbridge Huddersfield West Yorkshire HD3 4PE",
    "addr:housenumber":"unit 12b",
    "addr:postcode":"hd3 4pe",
    "addr:street":"Scar Lane;West",
    "iso:country":"GB",
    "sg:address":"Unit 12b Scar Lane, Milnsbridge",
    "sg:city":"Huddersfield",
    "sg:classifiers":[
        {
            "category":"Organizations",
            "subcategory":"Labor Organization",
            "type":"Services"
        }
    ],
    "sg:phone":"+44 1484 641641",
    "sg:postcode":"HD3 4PE",
    "sg:province":"West Yorkshire",
    "sg:tags":[
        "woodworking",
        "machinery"
    ],
    "wof:name":"Central C N C Machinery Ltd",
    "wof:placetype":"venue"
},
  "geometry": {"coordinates":[-1.8268890381,53.6406288147],"type":"Point"}
}