{
  "type": "Feature",
  "properties": {
    "addr:full":"Lower Shorrock Hey Farm, Meins Rd Blackburn Lancashire BB2 6QU",
    "addr:postcode":"bb2 6qu",
    "addr:street":"Meins Rd",
    "iso:country":"GB",
    "sg:address":"Lower Shorrock Hey Farm, Meins Rd",
    "sg:city":"Blackburn",
    "sg:classifiers":[
        {
            "category":"Farming",
            "subcategory":"Livestock Farm",
            "type":"Manufacturing & Wholesale Goods"
        }
    ],
    "sg:postcode":"BB2 6QU",
    "sg:province":"Lancashire",
    "sg:tags":[
        "others"
    ],
    "wof:name":"N Cross",
    "wof:placetype":"venue"
},
  "geometry": {"coordinates":[-2.53241,53.75502],"type":"Point"}
}