{
  "type": "Feature",
  "properties": {
    "iso:country":"GB",
    "sg:address":"4 Aviemore Close, Arnold",
    "sg:city":"Nottingham",
    "sg:classifiers":[
        {
            "category":"Education",
            "subcategory":"School",
            "type":"Public Place"
        },
        {
            "category":"Education",
            "subcategory":"University",
            "type":"Public Place"
        }
    ],
    "sg:phone":"+44 115 920 2119",
    "sg:postcode":"NG5 8QW",
    "sg:province":"Nottinghamshire",
    "sg:tags":[
        "private",
        "tuition"
    ],
    "wof:name":"Languages At Work",
    "wof:placetype":"venue"
},
  "geometry": {"coordinates":[-1.1088680029,53.0079154968],"type":"Point"}
}