{
  "type": "Feature",
  "properties": {
    "addr:full":"307 Norwich Rd Ipswich Suffolk IP1 4BW",
    "addr:housenumber":"307",
    "addr:postcode":"ip1 4bw",
    "addr:street":"Norwich Rd",
    "iso:country":"GB",
    "sg:address":"307 Norwich Rd",
    "sg:city":"Ipswich",
    "sg:classifiers":[
        {
            "category":"Home & Garden",
            "subcategory":"Furniture",
            "type":"Retail Goods"
        }
    ],
    "sg:phone":"+44 1473 744467",
    "sg:postcode":"IP1 4BW",
    "sg:province":"Suffolk",
    "wof:name":"Emporium The",
    "wof:placetype":"venue"
},
  "geometry": {"coordinates":[1.1363350153,52.068069458],"type":"Point"}
}