{
  "type": "Feature",
  "properties": {
    "addr:full":"North Street, Stilton Peterborough Cambridgeshire PE7 3RR",
    "addr:postcode":"pe7 3rr",
    "addr:street":"North Street",
    "iso:country":"GB",
    "sg:address":"North Street, Stilton",
    "sg:city":"Peterborough",
    "sg:classifiers":[
        {
            "category":"Professional",
            "subcategory":"Detective & Security Services",
            "type":"Services"
        }
    ],
    "sg:phone":"+44 1733 244322",
    "sg:postcode":"PE7 3RR",
    "sg:province":"Cambridgeshire",
    "sg:tags":[
        "alarm",
        "burglar",
        "system"
    ],
    "wof:name":"Crimecure Security Systems Ltd.",
    "wof:placetype":"venue"
},
  "geometry": {"coordinates":[-0.2895709872,52.4910926819],"type":"Point"}
}