{
  "type": "Feature",
  "properties": {
    "addr:full":"Gannaway Farm House, Gannaway, Norton Lindsey Warwick Warwickshire CV35 8JT",
    "addr:housenumber":"lindsey",
    "addr:postcode":"cv35 8jt",
    "iso:country":"GB",
    "sg:address":"Gannaway Farm House, Gannaway, Norton Lindsey",
    "sg:city":"Warwick",
    "sg:classifiers":[
        {
            "category":"Government",
            "subcategory":"Department Of Motor Vehicles",
            "type":"Public Place"
        },
        {
            "category":"Farming",
            "subcategory":"Livestock Farm",
            "type":"Manufacturing & Wholesale Goods"
        },
        {
            "category":"Farming",
            "subcategory":"Farm",
            "type":"Manufacturing & Wholesale Goods"
        }
    ],
    "sg:phone":"+44 1926 842330",
    "sg:postcode":"CV35 8JT",
    "sg:province":"Warwickshire",
    "sg:tags":[
        "hire",
        "horse",
        "crop",
        "others",
        "mixed",
        "drawn"
    ],
    "wof:name":"M E Fox",
    "wof:placetype":"venue"
},
  "geometry": {"coordinates":[-1.666894,52.265396],"type":"Point"}
}