{
  "type": "Feature",
  "properties": {
    "addr:full":"8 Mertoun Road, Walton Warrington Cheshire WA4 6JB",
    "addr:housenumber":"8",
    "addr:postcode":"wa4 6jb",
    "addr:street":"Mertoun Road",
    "iso:country":"GB",
    "sg:address":"8 Mertoun Road, Walton",
    "sg:city":"Warrington",
    "sg:classifiers":[
        {
            "category":"Professional",
            "subcategory":"Detective & Security Services",
            "type":"Services"
        }
    ],
    "sg:phone":"+44 1925 266366",
    "sg:postcode":"WA4 6JB",
    "sg:province":"Cheshire",
    "sg:tags":[
        "car"
    ],
    "wof:name":"Ajay Engineering",
    "wof:placetype":"venue"
},
  "geometry": {"coordinates":[-2.5901629925,53.3703269958],"type":"Point"}
}