{
  "type": "Feature",
  "properties": {
    "addr:full":"The Old Stables, Bridge St Ellon Aberdeenshire AB41 9AX",
    "addr:postcode":"ab41 9ax",
    "addr:street":"Bridge St",
    "iso:country":"GB",
    "sg:address":"The Old Stables, Bridge St",
    "sg:city":"Ellon",
    "sg:classifiers":[
        {
            "category":"Building & Trades",
            "subcategory":"Construction",
            "type":"Services"
        }
    ],
    "sg:phone":"+44 1358 723324",
    "sg:postcode":"AB41 9AX",
    "sg:province":"Aberdeenshire",
    "sg:tags":[
        "builder"
    ],
    "wof:name":"Cairn Developments Ltd",
    "wof:placetype":"venue"
},
  "geometry": {"coordinates":[-2.072814,57.364136],"type":"Point"}
}