{
  "type": "Feature",
  "properties": {
    "addr:full":"Hilton House, Lord Street Stockport Cheshire SK1 3NA",
    "addr:postcode":"sk1 3na",
    "addr:street":"Lord Street",
    "iso:country":"GB",
    "sg:address":"Hilton House, Lord Street",
    "sg:city":"Stockport",
    "sg:classifiers":[
        {
            "category":"Professional",
            "subcategory":"Business Services",
            "type":"Services"
        }
    ],
    "sg:phone":"+44 161 476 4050",
    "sg:postcode":"SK1 3NA",
    "sg:province":"Cheshire",
    "sg:tags":[
        "import",
        "export",
        "agent"
    ],
    "wof:name":"Aseco (Uk)",
    "wof:placetype":"venue"
},
  "geometry": {"coordinates":[-2.159124,53.40752],"type":"Point"}
}