{
  "type": "Feature",
  "properties": {
    "addr:full":"78 Highfield Road Blackpool Lancashire FY4 2JF",
    "addr:housenumber":"78",
    "addr:postcode":"fy4 2jf",
    "addr:street":"Highfield Road",
    "iso:country":"GB",
    "sg:address":"78 Highfield Road",
    "sg:city":"Blackpool",
    "sg:classifiers":[
        {
            "category":"Food & Beverages",
            "subcategory":"Fruits & Vegetables",
            "type":"Retail Goods"
        }
    ],
    "sg:phone":"+44 1253 341864",
    "sg:postcode":"FY4 2JF",
    "sg:province":"Lancashire",
    "sg:tags":[
        "greengrocer"
    ],
    "wof:name":"Farm Fresh Fruit & Veg",
    "wof:placetype":"venue"
},
  "geometry": {"coordinates":[-3.0440380573,53.7859687805],"type":"Point"}
}