{
  "type": "Feature",
  "properties": {
    "iso:country":"GB",
    "sg:address":"3-8 Bolsover Street",
    "sg:city":"London",
    "sg:classifiers":[
        {
            "category":"Professional",
            "subcategory":"Employment Agencies",
            "type":"Services"
        }
    ],
    "sg:phone":"+44 20 7486 8011",
    "sg:postcode":"W1P 7HG",
    "sg:province":"Greater London",
    "sg:tags":[
        "modelling"
    ],
    "wof:name":"I M G Models",
    "wof:placetype":"venue"
},
  "geometry": {"coordinates":[-0.143216,51.523296],"type":"Point"}
}