{
  "type": "Feature",
  "properties": {
    "addr:full":"The Old Ryeford Sawmills, Ryeford Industrial Estate Stonehouse Gloucestershire GL10 3HE",
    "addr:postcode":"gl10 3he",
    "addr:street":"Estate",
    "iso:country":"GB",
    "sg:address":"The Old Ryeford Sawmills, Ryeford Industrial Estate",
    "sg:city":"Stonehouse",
    "sg:classifiers":[
        {
            "category":"Manufacturing",
            "subcategory":"Building Materials",
            "type":"Manufacturing & Wholesale Goods"
        }
    ],
    "sg:phone":"+44 1453 828232",
    "sg:postcode":"GL10 3HE",
    "sg:province":"Gloucestershire",
    "sg:tags":[
        "merchant",
        "builder"
    ],
    "wof:name":"Tamwood Builders Supplies Ltd.",
    "wof:placetype":"venue"
},
  "geometry": {"coordinates":[-2.2713940144,51.7388038635],"type":"Point"}
}