{
  "type": "Feature",
  "properties": {
    "addr:full":"29 Tyler Street Sheffield South Yorkshire S9 1DH",
    "addr:housenumber":"29",
    "addr:postcode":"s9 1dh",
    "addr:street":"Tyler Street",
    "iso:country":"GB",
    "sg:address":"29 Tyler Street",
    "sg:city":"Sheffield",
    "sg:classifiers":[
        {
            "category":"Personal",
            "subcategory":"Beauty Salon",
            "type":"Services"
        }
    ],
    "sg:postcode":"S9 1DH",
    "sg:province":"South Yorkshire",
    "sg:tags":[
        "unisex",
        "hairdresser"
    ],
    "wof:name":"Klipps Hairdressing Salon",
    "wof:placetype":"venue"
},
  "geometry": {"coordinates":[-1.420319,53.413204],"type":"Point"}
}