{
  "type": "Feature",
  "properties": {
    "addr:full":"27 Corporation Street Lincoln Lincolnshire LN2 1HL",
    "addr:housenumber":"27",
    "addr:postcode":"ln2 1hl",
    "addr:street":"Corporation Street",
    "iso:country":"GB",
    "sg:address":"27 Corporation Street",
    "sg:city":"Lincoln",
    "sg:classifiers":[
        {
            "category":"Military Area",
            "subcategory":"Air Force Base",
            "type":"Public Place"
        }
    ],
    "sg:postcode":"LN2 1HL",
    "sg:province":"Lincolnshire",
    "sg:tags":[
        "taxi",
        "hire",
        "private"
    ],
    "wof:name":"Sam's Taxis & Minibuses",
    "wof:placetype":"venue"
},
  "geometry": {"coordinates":[-0.54059,53.230499],"type":"Point"}
}