{
  "type": "Feature",
  "properties": {
    "iso:country":"GB",
    "sg:address":"33 Greenhill Lane, Leabrooks",
    "sg:city":"Alfreton",
    "sg:classifiers":[
        {
            "category":"Manufacturing",
            "subcategory":"Building Materials",
            "type":"Manufacturing & Wholesale Goods"
        }
    ],
    "sg:phone":"+44 1773 602727",
    "sg:postcode":"DE55 1LU",
    "sg:province":"Derbyshire",
    "sg:tags":[
        "merchant",
        "builder"
    ],
    "wof:name":"Builders Supply Co. (Leabrooks) Ltd.",
    "wof:placetype":"venue"
},
  "geometry": {"coordinates":[-1.372865,53.074612],"type":"Point"}
}