{
  "type": "Feature",
  "properties": {
    "iso:country":"GB",
    "sg:address":"9 Brooklands Close",
    "sg:city":"Sunbury-on-thames",
    "sg:classifiers":[
        {
            "category":"Wholesale",
            "subcategory":"Medical Equipment & Supplies",
            "type":"Manufacturing & Wholesale Goods"
        }
    ],
    "sg:phone":"+44 1932 765988",
    "sg:postcode":"TW16 7DX",
    "sg:province":"Surrey",
    "sg:tags":[
        "hospital"
    ],
    "wof:name":"Medaes Ltd.",
    "wof:placetype":"venue"
},
  "geometry": {"coordinates":[-0.427946,51.415257],"type":"Point"}
}