{
  "type": "Feature",
  "properties": {
    "addr:full":"2 Harpur Avenue, Littleover Derby Derbyshire DE23 7EJ",
    "addr:housenumber":"2",
    "addr:postcode":"de23 7ej",
    "addr:street":"Harpur Avenue",
    "iso:country":"GB",
    "sg:address":"2 Harpur Avenue, Littleover",
    "sg:city":"Derby",
    "sg:classifiers":[
        {
            "category":"Retail",
            "subcategory":"Driving School",
            "type":"Services"
        }
    ],
    "sg:phone":"+44 1332 768517",
    "sg:postcode":"DE23 7EJ",
    "sg:province":"Derbyshire",
    "wof:name":"Michael Burden",
    "wof:placetype":"venue"
},
  "geometry": {"coordinates":[-1.52224,52.9011],"type":"Point"}
}