{
  "type": "Feature",
  "properties": {
    "iso:country":"GB",
    "sg:address":"Britannia Enterprise Centre, Waterworks Road",
    "sg:city":"Hastings",
    "sg:classifiers":[
        {
            "category":"Organizations",
            "subcategory":"Non-profit Organization",
            "type":"Services"
        }
    ],
    "sg:postcode":"TN34 1RT",
    "sg:province":"East Sussex",
    "sg:tags":[
        "organisation",
        "voluntary",
        "charity"
    ],
    "wof:name":"Hastings Sheltered Workshop",
    "wof:placetype":"venue"
},
  "geometry": {"coordinates":[0.578698,50.85619],"type":"Point"}
}