{
  "type": "Feature",
  "properties": {
    "addr:full":"341 Portway, Wythenshawe Manchester Greater Manchester M22 0EJ",
    "addr:housenumber":"341",
    "addr:postcode":"m22 0ej",
    "addr:street":"Portway",
    "iso:country":"GB",
    "sg:address":"341 Portway, Wythenshawe",
    "sg:city":"Manchester",
    "sg:classifiers":[
        {
            "category":"Food & Beverages",
            "subcategory":"Liquor & Beverages",
            "type":"Retail Goods"
        }
    ],
    "sg:phone":"+44 161 499 1467",
    "sg:postcode":"M22 0EJ",
    "sg:province":"Greater Manchester",
    "sg:tags":[
        "beer",
        "wine",
        "spirit",
        "wines"
    ],
    "wof:name":"Victoria Wine",
    "wof:placetype":"venue"
},
  "geometry": {"coordinates":[-2.259567976,53.3737716675],"type":"Point"}
}