{
  "type": "Feature",
  "properties": {
    "iso:country":"GB",
    "sg:address":"Rawlinson Lane, Heath Charnock",
    "sg:city":"Chorley",
    "sg:classifiers":[
        {
            "category":"Recreation",
            "subcategory":"Boat Charter",
            "type":"Entertainment"
        }
    ],
    "sg:phone":"+44 1257 480825",
    "sg:postcode":"PR7 4DE",
    "sg:province":"Lancashire",
    "sg:tags":[
        "excursion"
    ],
    "wof:name":"L & L Cruisers Ltd.",
    "wof:placetype":"venue"
},
  "geometry": {"coordinates":[-2.616298,53.626179],"type":"Point"}
}