{
  "type": "Feature",
  "properties": {
    "iso:country":"GB",
    "sg:address":"135 Wakefield Rd, Scissett",
    "sg:city":"Huddersfield",
    "sg:classifiers":[
        {
            "category":"Food & Beverages",
            "subcategory":"Bakery",
            "type":"Retail Goods"
        }
    ],
    "sg:phone":"+44 1484 866654",
    "sg:postcode":"HD8 9HR",
    "sg:province":"South Yorkshire",
    "sg:tags":[
        "shop",
        "baker"
    ],
    "wof:name":"Croft House Bakery",
    "wof:placetype":"venue"
},
  "geometry": {"coordinates":[-1.6230130196,53.5908927917],"type":"Point"}
}