{
  "type": "Feature",
  "properties": {
    "iso:country":"GB",
    "sg:address":"Oakfield Terrace",
    "sg:city":"Prudhoe",
    "sg:classifiers":[
        {
            "category":"Food & Beverages",
            "subcategory":"Supermarket",
            "type":"Retail Goods"
        }
    ],
    "sg:phone":"+44 1661 836036",
    "sg:postcode":"NE42 5HF",
    "sg:province":"Northumberland",
    "wof:name":"North Eastern & Cumbrian Co-Op Food Store",
    "wof:placetype":"venue"
},
  "geometry": {"coordinates":[-1.8513300419,54.9614028931],"type":"Point"}
}