{
  "type": "Feature",
  "properties": {
    "addr:full":"27 Boscombe Road Worcester Park Surrey KT4 8PJ",
    "addr:housenumber":"27",
    "addr:postcode":"kt4 8pj",
    "addr:street":"Boscombe Road",
    "iso:country":"GB",
    "sg:address":"27 Boscombe Road",
    "sg:city":"Worcester Park",
    "sg:classifiers":[
        {
            "category":"Professional",
            "subcategory":"Computer Services",
            "type":"Services"
        }
    ],
    "sg:postcode":"KT4 8PJ",
    "sg:province":"Surrey",
    "sg:tags":[
        "system",
        "software"
    ],
    "wof:name":"Maplegrade Ltd",
    "wof:placetype":"venue"
},
  "geometry": {"coordinates":[-0.22679,51.380676],"type":"Point"}
}