{
  "type": "Feature",
  "properties": {
    "addr:full":"Collenna Rd Porth Bridgend CF39 8EL",
    "addr:postcode":"cf39 8el",
    "addr:street":"Collenna Rd",
    "iso:country":"GB",
    "sg:address":"Collenna Rd",
    "sg:city":"Porth",
    "sg:classifiers":[
        {
            "category":"Organizations",
            "subcategory":"Community Association",
            "type":"Services"
        },
        {
            "category":"Organizations",
            "subcategory":"Membership Organization",
            "type":"Services"
        }
    ],
    "sg:phone":"+44 1443 670250",
    "sg:postcode":"CF39 8EL",
    "sg:province":"Bridgend",
    "sg:tags":[
        "club",
        "social"
    ],
    "wof:name":"Savoy Bingo & Social Club",
    "wof:placetype":"venue"
},
  "geometry": {"coordinates":[-3.4251909256,51.5925216675],"type":"Point"}
}