{
  "type": "Feature",
  "properties": {
    "addr:full":"215 Walsall Road Wednesbury West Midlands WS10 9SQ",
    "addr:housenumber":"215",
    "addr:postcode":"ws10 9sq",
    "addr:street":"Walsall Road",
    "iso:country":"GB",
    "sg:address":"215 Walsall Road",
    "sg:city":"Wednesbury",
    "sg:classifiers":[
        {
            "category":"Shopping",
            "subcategory":"Used Merchandise",
            "type":"Retail Goods"
        }
    ],
    "sg:phone":"+44 121 526 3823",
    "sg:postcode":"WS10 9SQ",
    "sg:province":"West Midlands",
    "sg:tags":[
        "shop",
        "second-hand"
    ],
    "wof:name":"Second Hands",
    "wof:placetype":"venue"
},
  "geometry": {"coordinates":[-2.020117,52.571732],"type":"Point"}
}