{
  "type": "Feature",
  "properties": {
    "addr:full":"Clifton House, Bunnian Place Basingstoke Hampshire RG21 7JE",
    "addr:postcode":"rg21 7je",
    "addr:street":"Bunnian Place",
    "iso:country":"GB",
    "sg:address":"Clifton House, Bunnian Place",
    "sg:city":"Basingstoke",
    "sg:classifiers":[
        {
            "category":"Professional",
            "subcategory":"Accounting & Tax Preparation",
            "type":"Services"
        }
    ],
    "sg:postcode":"RG21 7JE",
    "sg:province":"Hampshire",
    "sg:tags":[
        "accountant"
    ],
    "wof:name":"D A Mayes",
    "wof:placetype":"venue"
},
  "geometry": {"coordinates":[-1.0855540037,51.2681159973],"type":"Point"}
}