{
  "type": "Feature",
  "properties": {
    "addr:full":"Bodarran, Smithfield Square Dolgellau Gwynedd LL40 1EU",
    "addr:postcode":"ll40 1eu",
    "addr:street":"Smithfield Square",
    "iso:country":"GB",
    "sg:address":"Bodarran, Smithfield Square",
    "sg:city":"Dolgellau",
    "sg:classifiers":[
        {
            "category":"Shopping",
            "subcategory":"Stationery & Office Supplies",
            "type":"Retail Goods"
        },
        {
            "category":"Home & Garden",
            "subcategory":"Carpets & Floor Coverings",
            "type":"Retail Goods"
        }
    ],
    "sg:phone":"+44 1341 423947",
    "sg:postcode":"LL40 1EU",
    "sg:province":"Gwynedd",
    "sg:tags":[
        "carpets",
        "commercial",
        "rug",
        "matting"
    ],
    "wof:name":"Y Siop Stationery",
    "wof:placetype":"venue"
},
  "geometry": {"coordinates":[-3.885034,52.744324],"type":"Point"}
}