{
  "type": "Feature",
  "properties": {
    "iso:country":"GB",
    "sg:address":"26 Norfolk Street",
    "sg:city":"King's Lynn",
    "sg:classifiers":[
        {
            "category":"Shopping",
            "subcategory":"Gifts & Souvenirs",
            "type":"Retail Goods"
        },
        {
            "category":"Home & Garden",
            "subcategory":"Furniture",
            "type":"Retail Goods"
        }
    ],
    "sg:phone":"+44 1553 766826",
    "sg:postcode":"PE30 1AL",
    "sg:province":"Norfolk",
    "sg:tags":[
        "shop"
    ],
    "wof:name":"Enjoyable Co. Ltd.",
    "wof:placetype":"venue"
},
  "geometry": {"coordinates":[0.398593,52.755501],"type":"Point"}
}