{
  "type": "Feature",
  "properties": {
    "iso:country":"GB",
    "sg:address":"27 Boynston Gro, Sedgefield",
    "sg:city":"Stockton-on-tees",
    "sg:classifiers":[
        {
            "category":"Retail",
            "subcategory":"Driving School",
            "type":"Services"
        }
    ],
    "sg:postcode":"TS21 3BD",
    "sg:province":"Durham",
    "wof:name":"Sedgefield School of Motoring",
    "wof:placetype":"venue"
},
  "geometry": {"coordinates":[-1.4471369982,54.6555252075],"type":"Point"}
}