{
  "type": "Feature",
  "properties": {
    "addr:full":"19 Coleridge Cres Taunton Somerset TA1 2HS",
    "addr:housenumber":"19",
    "addr:postcode":"ta1 2hs",
    "addr:street":"Coleridge Cres",
    "iso:country":"GB",
    "sg:address":"19 Coleridge Cres",
    "sg:city":"Taunton",
    "sg:classifiers":[
        {
            "category":"Building & Trades",
            "subcategory":"Construction",
            "type":"Services"
        }
    ],
    "sg:postcode":"TA1 2HS",
    "sg:province":"Somerset",
    "sg:tags":[
        "roofing"
    ],
    "wof:name":"Jordan,Darren,",
    "wof:placetype":"venue"
},
  "geometry": {"coordinates":[-3.0867249966,51.0124588013],"type":"Point"}
}