{
  "type": "Feature",
  "properties": {
    "iso:country":"GB",
    "sg:address":"Units 3-4, Stillington Road Business Centre, Stillington Road",
    "sg:city":"York",
    "sg:classifiers":[
        {
            "category":"Shopping",
            "subcategory":"Computers & Home Electronics",
            "type":"Retail Goods"
        }
    ],
    "sg:phone":"+44 1347 822911",
    "sg:postcode":"YO61 3JE",
    "sg:province":"North Yorkshire",
    "wof:name":"Falcon Office Furniture",
    "wof:placetype":"venue"
},
  "geometry": {"coordinates":[-1.18714,54.117599],"type":"Point"}
}