{
  "type": "Feature",
  "properties": {
    "iso:country":"GB",
    "sg:address":"Scalford Drive",
    "sg:city":"Peterborough",
    "sg:classifiers":[
        {
            "category":"Education",
            "subcategory":"School",
            "type":"Public Place"
        },
        {
            "category":"Government",
            "subcategory":"Office",
            "type":"Public Place"
        }
    ],
    "sg:phone":"+44 1733 763663",
    "sg:postcode":"PE1 4TR",
    "sg:province":"Cambridgeshire",
    "sg:tags":[
        "local",
        "authority"
    ],
    "wof:name":"Welland Primary School",
    "wof:placetype":"venue"
},
  "geometry": {"coordinates":[-0.222784,52.600117],"type":"Point"}
}