{
  "type": "Feature",
  "properties": {
    "addr:full":"23-24 Great James Street London Greater London WC1N 3ES",
    "addr:housenumber":"23-24",
    "addr:postcode":"wc1n 3es",
    "addr:street":"Great James Street",
    "iso:country":"GB",
    "sg:address":"23-24 Great James Street",
    "sg:city":"London",
    "sg:classifiers":[
        {
            "category":"Professional",
            "subcategory":"Art Services",
            "type":"Services"
        }
    ],
    "sg:phone":"+44 20 7831 1333",
    "sg:postcode":"WC1N 3ES",
    "sg:province":"Greater London",
    "sg:tags":[
        "graphic",
        "designer"
    ],
    "wof:name":"Ranch Associates Ltd.",
    "wof:placetype":"venue"
},
  "geometry": {"coordinates":[-0.1172130033,51.5215950012],"type":"Point"}
}