{
  "type": "Feature",
  "properties": {
    "iso:country":"GB",
    "sg:address":"Unit 5 Bert Smith Way",
    "sg:city":"Market Drayton",
    "sg:classifiers":[
        {
            "category":"Retail",
            "subcategory":"Auto Repair",
            "type":"Services"
        }
    ],
    "sg:phone":"+44 1630 658626",
    "sg:postcode":"TF9 3SN",
    "sg:province":"Shropshire",
    "sg:tags":[
        "modification",
        "garage"
    ],
    "wof:name":"Steve Raines",
    "wof:placetype":"venue"
},
  "geometry": {"coordinates":[-2.490099,52.909985],"type":"Point"}
}