{
  "type": "Feature",
  "properties": {
    "addr:full":"Thompson Rd, Trafford Park Manchester Cheshire M17 1SE",
    "addr:postcode":"m17 1se",
    "addr:street":"Thompson Rd",
    "iso:country":"GB",
    "sg:address":"Thompson Rd, Trafford Park",
    "sg:city":"Manchester",
    "sg:classifiers":[
        {
            "category":"Building & Trades",
            "subcategory":"Cleaning & Sanitation",
            "type":"Services"
        }
    ],
    "sg:phone":"+44 161 848 0821",
    "sg:postcode":"M17 1SE",
    "sg:province":"Cheshire",
    "sg:tags":[
        "repairing",
        "tank"
    ],
    "wof:name":"Tanktainer Thurroclean Group",
    "wof:placetype":"venue"
},
  "geometry": {"coordinates":[-2.3448410034,53.4748306274],"type":"Point"}
}