{
  "type": "Feature",
  "properties": {
    "addr:full":"Row Farm, Seend Cleeve Melksham Wiltshire SN12 6PS",
    "addr:housenumber":"seend",
    "addr:postcode":"sn12 6ps",
    "addr:street":"Row",
    "iso:country":"GB",
    "sg:address":"Row Farm, Seend Cleeve",
    "sg:city":"Melksham",
    "sg:classifiers":[
        {
            "category":"Farming",
            "subcategory":"Livestock Farm",
            "type":"Manufacturing & Wholesale Goods"
        }
    ],
    "sg:postcode":"SN12 6PS",
    "sg:province":"Wiltshire",
    "sg:tags":[
        "others"
    ],
    "wof:name":"Geoffrey Newman",
    "wof:placetype":"venue"
},
  "geometry": {"coordinates":[-2.073717,51.349827],"type":"Point"}
}