{
  "type": "Feature",
  "properties": {
    "addr:full":"Pennythree Park Lane, Lane End High Wycombe Buckinghamshire HP14 3DE",
    "addr:postcode":"hp14 3de",
    "addr:street":"Park Lane",
    "iso:country":"GB",
    "sg:address":"Pennythree Park Lane, Lane End",
    "sg:city":"High Wycombe",
    "sg:classifiers":[
        {
            "category":"Building & Trades",
            "subcategory":"Cleaning & Sanitation",
            "type":"Services"
        }
    ],
    "sg:phone":"+44 1494 883022",
    "sg:postcode":"HP14 3DE",
    "sg:province":"Buckinghamshire",
    "sg:tags":[
        "blast"
    ],
    "wof:name":"Blastborn",
    "wof:placetype":"venue"
},
  "geometry": {"coordinates":[-0.83202,51.622791],"type":"Point"}
}