{
  "type": "Feature",
  "properties": {
    "iso:country":"GB",
    "sg:address":"3 Edinburgh Place",
    "sg:city":"Harlow",
    "sg:classifiers":[
        {
            "category":"Airport",
            "subcategory":"General Aviation",
            "type":"Transportation"
        }
    ],
    "sg:phone":"+44 1279 442081",
    "sg:postcode":"CM20 2DJ",
    "sg:province":"Essex",
    "wof:name":"Meggitt Avionics",
    "wof:placetype":"venue"
},
  "geometry": {"coordinates":[0.117078,51.785126],"type":"Point"}
}