{
  "type": "Feature",
  "properties": {
    "addr:full":"40 Rushenden Road Queenborough Kent ME11 5LG",
    "addr:housenumber":"40",
    "addr:postcode":"me11 5lg",
    "addr:street":"Rushenden Road",
    "iso:country":"GB",
    "sg:address":"40 Rushenden Road",
    "sg:city":"Queenborough",
    "sg:classifiers":[
        {
            "category":"Food & Beverages",
            "subcategory":"Meat & Fish",
            "type":"Retail Goods"
        }
    ],
    "sg:postcode":"ME11 5LG",
    "sg:province":"Kent",
    "sg:tags":[
        "butcher"
    ],
    "wof:name":"Martin Gooding",
    "wof:placetype":"venue"
},
  "geometry": {"coordinates":[0.7434380054,51.4076576233],"type":"Point"}
}