{
  "type": "Feature",
  "properties": {
    "iso:country":"GB",
    "sg:address":"Unit B5 Bersham Entprise Centre, Plas Grono Road",
    "sg:city":"Wrexham",
    "sg:classifiers":[
        {
            "category":"Home & Garden",
            "subcategory":"Household Appliances",
            "type":"Retail Goods"
        }
    ],
    "sg:postcode":"LL14 4EG",
    "sg:province":"Wrexham",
    "sg:tags":[
        "cleaner",
        "domestic",
        "vacuum"
    ],
    "wof:name":"Kirby (U K) Ltd.",
    "wof:placetype":"venue"
},
  "geometry": {"coordinates":[-3.0237300396,53.026309967],"type":"Point"}
}