{
  "type": "Feature",
  "properties": {
    "iso:country":"GB",
    "sg:address":"Unit 1, Wood Street",
    "sg:city":"Poulton-le-fylde",
    "sg:classifiers":[
        {
            "category":"Manufacturing",
            "subcategory":"Building Materials",
            "type":"Manufacturing & Wholesale Goods"
        }
    ],
    "sg:phone":"+44 1253 882747",
    "sg:postcode":"FY6 8JY",
    "sg:province":"Lancashire",
    "sg:tags":[
        "tile",
        "mnfrs"
    ],
    "wof:name":"Furness Tiles",
    "wof:placetype":"venue"
},
  "geometry": {"coordinates":[-2.974199,53.843575],"type":"Point"}
}