{
  "type": "Feature",
  "properties": {
    "addr:full":"11 Boyces Street Brighton East Sussex BN1 1AN",
    "addr:housenumber":"11",
    "addr:postcode":"bn1 1an",
    "addr:street":"Boyces Street",
    "iso:country":"GB",
    "sg:address":"11 Boyces Street",
    "sg:city":"Brighton",
    "sg:classifiers":[
        {
            "category":"Bars & Pubs",
            "type":"Food & Drink"
        }
    ],
    "sg:phone":"+44 1273 325850",
    "sg:postcode":"BN1 1AN",
    "sg:province":"East Sussex",
    "sg:tags":[
        "pubs",
        "inn"
    ],
    "wof:name":"Tibsco Ltd.",
    "wof:placetype":"venue"
},
  "geometry": {"coordinates":[-0.143781,50.822041],"type":"Point"}
}