{
  "type": "Feature",
  "properties": {
    "addr:full":"Care Of Allied Carpets, Ashford Business Park Ashford Kent TN24 0SG",
    "addr:postcode":"tn24 0sg",
    "addr:street":"Ashford Business Park",
    "iso:country":"GB",
    "sg:address":"Care Of Allied Carpets, Ashford Business Park",
    "sg:city":"Ashford",
    "sg:classifiers":[
        {
            "category":"Home & Garden",
            "subcategory":"Home Furnishings",
            "type":"Retail Goods"
        }
    ],
    "sg:postcode":"TN24 0SG",
    "sg:province":"Kent",
    "sg:tags":[
        "furnishers",
        "planner",
        "kitchen"
    ],
    "wof:name":"Magnet Ltd.",
    "wof:placetype":"venue"
},
  "geometry": {"coordinates":[0.9039999843,51.1300201416],"type":"Point"}
}