{
  "type": "Feature",
  "properties": {
    "iso:country":"GB",
    "sg:address":"91 Foundry Road, Parton",
    "sg:city":"Whitehaven",
    "sg:classifiers":[
        {
            "category":"Bars & Pubs",
            "type":"Food & Drink"
        },
        {
            "category":"Community Center",
            "subcategory":"Social",
            "type":"Public Place"
        }
    ],
    "sg:phone":"+44 1946 65694",
    "sg:postcode":"CA28 6PA",
    "sg:province":"Cumbria",
    "sg:tags":[
        "pubs",
        "house",
        "inn",
        "activity"
    ],
    "wof:name":"Beachcomber Club",
    "wof:placetype":"venue"
},
  "geometry": {"coordinates":[-3.578881,54.570873],"type":"Point"}
}