{
  "type": "Feature",
  "properties": {
    "iso:country":"GB",
    "sg:address":"Lynwood Ho, North Rd",
    "sg:city":"Newcastle Upon Tyne",
    "sg:classifiers":[
        {
            "category":"Home & Garden",
            "subcategory":"Home Furnishings",
            "type":"Retail Goods"
        }
    ],
    "sg:phone":"+44 191 236 4488",
    "sg:postcode":"NE13 6LN",
    "sg:province":"Northumberland",
    "sg:tags":[
        "awning",
        "canopy",
        "blinds"
    ],
    "wof:name":"Solo Blinds",
    "wof:placetype":"venue"
},
  "geometry": {"coordinates":[-1.6245199442,55.0482788086],"type":"Point"}
}