{
  "type": "Feature",
  "properties": {
    "iso:country":"GB",
    "sg:address":"85 Basford Park Road",
    "sg:city":"Newcastle",
    "sg:classifiers":[
        {
            "category":"Building & Trades",
            "subcategory":"Construction",
            "type":"Services"
        }
    ],
    "sg:postcode":"ST5 0PS",
    "sg:province":"Staffordshire",
    "sg:tags":[
        "glazier",
        "decorator",
        "painter"
    ],
    "wof:name":"P F Tilsley Decorating Services",
    "wof:placetype":"venue"
},
  "geometry": {"coordinates":[-2.2130179405,53.0220108032],"type":"Point"}
}