{
  "type": "Feature",
  "properties": {
    "addr:full":"3 Samuel Street Macclesfield Cheshire SK11 6UW",
    "addr:housenumber":"3",
    "addr:postcode":"sk11 6uw",
    "addr:street":"Samuel Street",
    "iso:country":"GB",
    "sg:address":"3 Samuel Street",
    "sg:city":"Macclesfield",
    "sg:classifiers":[
        {
            "category":"Insurance",
            "subcategory":"Insurance Agent",
            "type":"Services"
        }
    ],
    "sg:phone":"+44 1625 422276",
    "sg:postcode":"SK11 6UW",
    "sg:province":"Cheshire",
    "wof:name":"National Farmers Union",
    "wof:placetype":"venue"
},
  "geometry": {"coordinates":[-2.12552,53.256657],"type":"Point"}
}