{
  "type": "Feature",
  "properties": {
    "addr:full":"High Street Clacton-on-sea Essex CO16 0DY",
    "addr:postcode":"co16 0dy",
    "addr:street":"High Street",
    "iso:country":"GB",
    "sg:address":"High Street",
    "sg:city":"Clacton-on-sea",
    "sg:classifiers":[
        {
            "category":"Communications",
            "type":"Services"
        }
    ],
    "sg:postcode":"CO16 0DY",
    "sg:province":"Essex",
    "sg:tags":[
        "tv",
        "video",
        "radio"
    ],
    "wof:name":"R I & Y P Gunfield",
    "wof:placetype":"venue"
},
  "geometry": {"coordinates":[1.15792,51.859978],"type":"Point"}
}