{
  "type": "Feature",
  "properties": {
    "addr:full":"4 Dunelm Ct, South St Durham Durham DH1 4QX",
    "addr:housenumber":"4",
    "addr:postcode":"dh1 4qx",
    "addr:street":"Dunelm Ct South St",
    "iso:country":"GB",
    "sg:address":"4 Dunelm Ct, South St",
    "sg:city":"Durham",
    "sg:classifiers":[
        {
            "category":"Personal",
            "subcategory":"Skin Care",
            "type":"Services"
        }
    ],
    "sg:phone":"+44 191 384 5667",
    "sg:postcode":"DH1 4QX",
    "sg:province":"Durham",
    "sg:tags":[
        "leather",
        "merchant"
    ],
    "wof:name":"AQUArelle",
    "wof:placetype":"venue"
},
  "geometry": {"coordinates":[-1.574608,54.777534],"type":"Point"}
}