{
  "type": "Feature",
  "properties": {
    "iso:country":"GB",
    "sg:address":"11 Hill View",
    "sg:city":"Pontypridd",
    "sg:classifiers":[
        {
            "category":"Social Services",
            "subcategory":"Child Care",
            "type":"Services"
        }
    ],
    "sg:phone":"+44 1443 202600",
    "sg:postcode":"CF38 2DS",
    "sg:province":"Rhondda, Cynon, Taff",
    "sg:tags":[
        "children's",
        "home"
    ],
    "wof:name":"Beddau Children's Home",
    "wof:placetype":"venue"
},
  "geometry": {"coordinates":[-3.3527219296,51.554145813],"type":"Point"}
}