{
  "type": "Feature",
  "properties": {
    "iso:country":"GB",
    "sg:address":"P O Box 4",
    "sg:city":"Doncaster",
    "sg:classifiers":[
        {
            "category":"Organizations",
            "subcategory":"Political Organization",
            "type":"Services"
        }
    ],
    "sg:postcode":"DN4 5PA",
    "sg:province":"South Yorkshire",
    "sg:tags":[
        "party"
    ],
    "wof:name":"Liberal Democrats",
    "wof:placetype":"venue"
},
  "geometry": {"coordinates":[-1.130836,53.513699],"type":"Point"}
}