{
  "type": "Feature",
  "properties": {
    "addr:full":"Dale Farm, Dale Road Brough East Riding of Yorkshire HU15 1QN",
    "addr:postcode":"hu15 1qn",
    "addr:street":"Dale;Dale Road",
    "iso:country":"GB",
    "sg:address":"Dale Farm, Dale Road",
    "sg:city":"Brough",
    "sg:classifiers":[
        {
            "category":"Professional",
            "subcategory":"Management & Consulting",
            "type":"Services"
        }
    ],
    "sg:postcode":"HU15 1QN",
    "sg:province":"East Riding of Yorkshire",
    "sg:tags":[
        "consultant",
        "business"
    ],
    "wof:name":"Buckenham Milner",
    "wof:placetype":"venue"
},
  "geometry": {"coordinates":[-0.572144,53.729919],"type":"Point"}
}