{
  "type": "Feature",
  "properties": {
    "iso:country":"GB",
    "sg:address":"17 East Reach",
    "sg:city":"Taunton",
    "sg:classifiers":[
        {
            "category":"Fast Food",
            "type":"Food & Drink"
        }
    ],
    "sg:phone":"+44 1823 330995",
    "sg:postcode":"TA1 3EW",
    "sg:province":"Somerset",
    "sg:tags":[
        "away",
        "meal",
        "outlet",
        "take"
    ],
    "wof:name":"Seema Cuisine",
    "wof:placetype":"venue"
},
  "geometry": {"coordinates":[-3.0950009823,51.0152511597],"type":"Point"}
}