{
  "type": "Feature",
  "properties": {
    "iso:country":"GB",
    "sg:address":"6c Commercial Road",
    "sg:city":"London",
    "sg:classifiers":[
        {
            "category":"Shopping",
            "subcategory":"Clothing, Apparel, & Fashions",
            "type":"Retail Goods"
        }
    ],
    "sg:phone":"+44 20 8803 7137",
    "sg:postcode":"N18 1HS",
    "sg:province":"Greater London",
    "sg:tags":[
        "clothing",
        "fabric"
    ],
    "wof:name":"H Topuzoglu",
    "wof:placetype":"venue"
},
  "geometry": {"coordinates":[-0.0723880008,51.608745575],"type":"Point"}
}