{
  "type": "Feature",
  "properties": {
    "addr:full":"15 St Georges Villas Truro Cornwall TR1 3NL",
    "addr:housenumber":"15",
    "addr:postcode":"tr1 3nl",
    "addr:street":"St Georges Villas",
    "iso:country":"GB",
    "sg:address":"15 St Georges Villas",
    "sg:city":"Truro",
    "sg:classifiers":[
        {
            "category":"Building & Trades",
            "subcategory":"Plumbing",
            "type":"Services"
        }
    ],
    "sg:postcode":"TR1 3NL",
    "sg:province":"Cornwall",
    "sg:tags":[
        "heating"
    ],
    "wof:name":"M J S Plumbing Services",
    "wof:placetype":"venue"
},
  "geometry": {"coordinates":[-5.058382988,50.2642669678],"type":"Point"}
}