{
  "type": "Feature",
  "properties": {
    "iso:country":"GB",
    "sg:address":"Didcot Enterprise Centre, Southmead Industrial Estate, Hawksworth",
    "sg:city":"Didcot",
    "sg:classifiers":[
        {
            "category":"Manufacturing",
            "subcategory":"Wood Products",
            "type":"Manufacturing & Wholesale Goods"
        }
    ],
    "sg:phone":"+44 1235 818668",
    "sg:postcode":"OX11 7PH",
    "sg:province":"Oxfordshire",
    "sg:tags":[
        "packaging",
        "crate",
        "pallets"
    ],
    "wof:name":"H & L Packaging",
    "wof:placetype":"venue"
},
  "geometry": {"coordinates":[-1.2549,51.620071],"type":"Point"}
}