{
  "type": "Feature",
  "properties": {
    "iso:country":"GB",
    "sg:address":"45 Preston Road",
    "sg:city":"Weymouth",
    "sg:classifiers":[
        {
            "category":"Health Services",
            "subcategory":"Doctor",
            "type":"Services"
        }
    ],
    "sg:phone":"+44 1305 854636",
    "sg:postcode":"DT3 6PX",
    "sg:province":"Dorset",
    "sg:tags":[
        "practitioners"
    ],
    "wof:name":"Susan Bunn",
    "wof:placetype":"venue"
},
  "geometry": {"coordinates":[-2.433134079,50.6374397278],"type":"Point"}
}