{
  "type": "Feature",
  "properties": {
    "iso:country":"GB",
    "sg:address":"Bardfield",
    "sg:city":"Basildon",
    "sg:classifiers":[
        {
            "category":"Place Of Worship",
            "type":"Public Place"
        }
    ],
    "sg:phone":"+44 1268 555816",
    "sg:postcode":"SS16 4JW",
    "sg:province":"Essex",
    "wof:name":"Kingdom Hall Of Jehovah's Witnesses",
    "wof:placetype":"venue"
},
  "geometry": {"coordinates":[0.487941,51.565083],"type":"Point"}
}