{
  "type": "Feature",
  "properties": {
    "addr:full":"Unit A5 54 Marlow Bottom Road, Marlow Bottom Marlow Berkshire SL7 3NB",
    "addr:housenumber":"a5 54",
    "addr:postcode":"sl7 3nb",
    "addr:street":"Bottom Road",
    "iso:country":"GB",
    "sg:address":"Unit A5 54 Marlow Bottom Road, Marlow Bottom",
    "sg:city":"Marlow",
    "sg:classifiers":[
        {
            "category":"Shopping",
            "subcategory":"Crafts & Fabrics",
            "type":"Retail Goods"
        },
        {
            "category":"Manufacturing",
            "subcategory":"Textiles",
            "type":"Manufacturing & Wholesale Goods"
        }
    ],
    "sg:postcode":"SL7 3NB",
    "sg:province":"Berkshire",
    "sg:tags":[
        "knitwear",
        "yarn"
    ],
    "wof:name":"Peter James of London Ltd.",
    "wof:placetype":"venue"
},
  "geometry": {"coordinates":[-0.7772330046,51.5866966248],"type":"Point"}
}