{
  "type": "Feature",
  "properties": {
    "iso:country":"GB",
    "sg:address":"Unit 2 Bow Cranwell Close",
    "sg:city":"London",
    "sg:classifiers":[
        {
            "category":"Professional",
            "subcategory":"Printing & Photocopies",
            "type":"Services"
        }
    ],
    "sg:postcode":"E3 3QY",
    "sg:province":"Greater London",
    "sg:tags":[
        "print",
        "finisher"
    ],
    "wof:name":"B P F",
    "wof:placetype":"venue"
},
  "geometry": {"coordinates":[-0.017694,51.522114],"type":"Point"}
}