{
  "type": "Feature",
  "properties": {
    "addr:full":"Market Hall Swindon Wiltshire SN1 1RZ",
    "addr:postcode":"sn1 1rz",
    "addr:street":"Swindon",
    "iso:country":"GB",
    "sg:address":"Market Hall",
    "sg:city":"Swindon",
    "sg:classifiers":[
        {
            "category":"Shopping",
            "subcategory":"Gifts & Souvenirs",
            "type":"Retail Goods"
        }
    ],
    "sg:postcode":"SN1 1RZ",
    "sg:province":"Wiltshire",
    "sg:tags":[
        "greeting",
        "card"
    ],
    "wof:name":"Swindon Wholesale Greetings Ltd",
    "wof:placetype":"venue"
},
  "geometry": {"coordinates":[-1.7818139791,51.5617637634],"type":"Point"}
}