{
  "type": "Feature",
  "properties": {
    "addr:full":"Hagg Farm, East Street, Doe Lea Chesterfield Derbyshire S44 5NP",
    "addr:postcode":"s44 5np",
    "addr:street":"East Street",
    "iso:country":"GB",
    "sg:address":"Hagg Farm, East Street, Doe Lea",
    "sg:city":"Chesterfield",
    "sg:classifiers":[
        {
            "category":"Farming",
            "subcategory":"Livestock Farm",
            "type":"Manufacturing & Wholesale Goods"
        }
    ],
    "sg:phone":"+44 1246 850383",
    "sg:postcode":"S44 5NP",
    "sg:province":"Derbyshire",
    "sg:tags":[
        "others"
    ],
    "wof:name":"Hagg Farm",
    "wof:placetype":"venue"
},
  "geometry": {"coordinates":[-1.309634,53.191589],"type":"Point"}
}