{
  "type": "Feature",
  "properties": {
    "iso:country":"GB",
    "sg:address":"Unit 1 Meridian Trading Estate, 22 Lombard Wall",
    "sg:city":"London",
    "sg:classifiers":[
        {
            "category":"Professional",
            "subcategory":"Business Services",
            "type":"Services"
        }
    ],
    "sg:phone":"+44 20 8293 1233",
    "sg:postcode":"SE7 7SW",
    "sg:province":"Greater London",
    "sg:tags":[
        "tile",
        "stockist"
    ],
    "wof:name":"Topps Tile Kingdom",
    "wof:placetype":"venue"
},
  "geometry": {"coordinates":[0.02569,51.490528],"type":"Point"}
}