{
  "type": "Feature",
  "properties": {
    "addr:full":"Jokers Wild, Cottenham Road, Histon Cambridge Cambridgeshire CB4 9ET",
    "addr:postcode":"cb4 9et",
    "addr:street":"Cottenham Road",
    "iso:country":"GB",
    "sg:address":"Jokers Wild, Cottenham Road, Histon",
    "sg:city":"Cambridge",
    "sg:classifiers":[
        {
            "category":"Farming",
            "subcategory":"Livestock Farm",
            "type":"Manufacturing & Wholesale Goods"
        }
    ],
    "sg:postcode":"CB4 9ET",
    "sg:province":"Cambridgeshire",
    "sg:tags":[
        "others"
    ],
    "wof:name":"A H Scott & Sons",
    "wof:placetype":"venue"
},
  "geometry": {"coordinates":[0.1112549976,52.2446517944],"type":"Point"}
}