{
  "type": "Feature",
  "properties": {
    "addr:full":"33 Newlands Park London Greater London SE26 5PN",
    "addr:housenumber":"33",
    "addr:postcode":"se26 5pn",
    "addr:street":"Newlands Park",
    "iso:country":"GB",
    "sg:address":"33 Newlands Park",
    "sg:city":"London",
    "sg:classifiers":[
        {
            "category":"Professional",
            "subcategory":"Management & Consulting",
            "type":"Services"
        }
    ],
    "sg:postcode":"SE26 5PN",
    "sg:province":"Greater London",
    "sg:tags":[
        "consultant",
        "safety"
    ],
    "wof:name":"Safety Logic (U K)",
    "wof:placetype":"venue"
},
  "geometry": {"coordinates":[-0.053055,51.420498],"type":"Point"}
}