{
  "type": "Feature",
  "properties": {
    "iso:country":"GB",
    "sg:address":"The Rose Nursery, Lodge Hill",
    "sg:city":"Abingdon",
    "sg:classifiers":[
        {
            "category":"Home & Garden",
            "subcategory":"Garden Supply",
            "type":"Retail Goods"
        }
    ],
    "sg:phone":"+44 1865 735382",
    "sg:postcode":"OX14 2JD",
    "sg:province":"Oxfordshire",
    "sg:tags":[
        "planting",
        "tree",
        "shrub"
    ],
    "wof:name":"Robert Mattock Containerised Roses",
    "wof:placetype":"venue"
},
  "geometry": {"coordinates":[-1.270179,51.68755],"type":"Point"}
}