{
  "type": "Feature",
  "properties": {
    "addr:full":"P O Box 309 Stockton-on-tees Durham TS20 1XP",
    "addr:housenumber":"309",
    "addr:postcode":"ts20 1xp",
    "addr:street":"P O Box",
    "iso:country":"GB",
    "sg:address":"P O Box 309",
    "sg:city":"Stockton-on-tees",
    "sg:classifiers":[
        {
            "category":"Professional",
            "subcategory":"Research",
            "type":"Services"
        }
    ],
    "sg:phone":"+44 1642 360982",
    "sg:postcode":"TS20 1XP",
    "sg:province":"Durham",
    "sg:tags":[
        "market"
    ],
    "wof:name":"N W A Market Research",
    "wof:placetype":"venue"
},
  "geometry": {"coordinates":[-1.31868,54.591259],"type":"Point"}
}