{
  "type": "Feature",
  "properties": {
    "iso:country":"GB",
    "sg:address":"177 Goswell Road",
    "sg:city":"London",
    "sg:classifiers":[
        {
            "category":"Building & Trades",
            "subcategory":"Plumbing",
            "type":"Services"
        }
    ],
    "sg:phone":"+44 20 7251 3418",
    "sg:postcode":"EC1V 7HJ",
    "sg:province":"Greater London",
    "sg:tags":[
        "heating"
    ],
    "wof:name":"Angel Plumbing Services",
    "wof:placetype":"venue"
},
  "geometry": {"coordinates":[-0.100589,51.527557],"type":"Point"}
}