{
  "type": "Feature",
  "properties": {
    "iso:country":"GB",
    "sg:address":"52 Queen Street, Great Harwood",
    "sg:city":"Blackburn",
    "sg:classifiers":[
        {
            "category":"Home & Garden",
            "subcategory":"Home Furnishings",
            "type":"Retail Goods"
        }
    ],
    "sg:postcode":"BB6 7QQ",
    "sg:province":"Lancashire",
    "sg:tags":[
        "furnishers",
        "planner",
        "kitchen"
    ],
    "wof:name":"Claire Dewhurst",
    "wof:placetype":"venue"
},
  "geometry": {"coordinates":[-2.405097,53.786148],"type":"Point"}
}