{
  "type": "Feature",
  "properties": {
    "addr:full":"120 Buckley Rd Rochdale Lancashire OL12 9DL",
    "addr:housenumber":"120",
    "addr:postcode":"ol12 9dl",
    "addr:street":"Buckley Rd",
    "iso:country":"GB",
    "sg:address":"120 Buckley Rd",
    "sg:city":"Rochdale",
    "sg:classifiers":[
        {
            "category":"Bars & Pubs",
            "type":"Food & Drink"
        }
    ],
    "sg:postcode":"OL12 9DL",
    "sg:province":"Lancashire",
    "sg:tags":[
        "pubs",
        "inn"
    ],
    "wof:name":"Ford,Robert,",
    "wof:placetype":"venue"
},
  "geometry": {"coordinates":[-2.14211,53.632114],"type":"Point"}
}