{
  "type": "Feature",
  "properties": {
    "addr:full":"25 West Row Stockton-on-tees Durham TS18 1BT",
    "addr:housenumber":"25",
    "addr:postcode":"ts18 1bt",
    "addr:street":"West Row",
    "iso:country":"GB",
    "sg:address":"25 West Row",
    "sg:city":"Stockton-on-tees",
    "sg:classifiers":[
        {
            "category":"Shopping",
            "subcategory":"Pets & Pet Supplies",
            "type":"Retail Goods"
        }
    ],
    "sg:postcode":"TS18 1BT",
    "sg:province":"Durham",
    "wof:name":"Hill's Pet Shop",
    "wof:placetype":"venue"
},
  "geometry": {"coordinates":[-1.3142640591,54.5635299683],"type":"Point"}
}