{
  "type": "Feature",
  "properties": {
    "addr:full":"Unit 5b Causeway Park, Central Road Warrington Cheshire WA4 6RF",
    "addr:housenumber":"unit 5b",
    "addr:postcode":"wa4 6rf",
    "addr:street":"Causeway Park Central Road",
    "iso:country":"GB",
    "sg:address":"Unit 5b Causeway Park, Central Road",
    "sg:city":"Warrington",
    "sg:classifiers":[
        {
            "category":"Home & Garden",
            "subcategory":"Home Furnishings",
            "type":"Retail Goods"
        },
        {
            "category":"Manufacturing",
            "subcategory":"Textiles",
            "type":"Manufacturing & Wholesale Goods"
        }
    ],
    "sg:phone":"+44 1925 245496",
    "sg:postcode":"WA4 6RF",
    "sg:province":"Cheshire",
    "sg:tags":[
        "merchant",
        "beds",
        "bedding",
        "blanket",
        "agent"
    ],
    "wof:name":"Decotex Ltd.",
    "wof:placetype":"venue"
},
  "geometry": {"coordinates":[-2.587049,53.379887],"type":"Point"}
}