{
  "type": "Feature",
  "properties": {
    "iso:country":"GB",
    "sg:address":"41 High Street",
    "sg:city":"Swanley",
    "sg:classifiers":[
        {
            "category":"Shopping",
            "subcategory":"Clothing, Apparel, & Fashions",
            "type":"Retail Goods"
        }
    ],
    "sg:phone":"+44 1322 662837",
    "sg:postcode":"BR8 8AE",
    "sg:province":"Kent",
    "sg:tags":[
        "ladieswear"
    ],
    "wof:name":"Betty's Fashions",
    "wof:placetype":"venue"
},
  "geometry": {"coordinates":[0.1795009971,51.3944091797],"type":"Point"}
}