{
  "type": "Feature",
  "properties": {
    "iso:country":"GB",
    "sg:address":"Dovesdale House, Stonehouse",
    "sg:city":"Larkhall",
    "sg:classifiers":[
        {
            "category":"Freight",
            "type":"Transportation"
        }
    ],
    "sg:phone":"+44 1698 792211",
    "sg:postcode":"ML9 3PR",
    "sg:province":"South Lanarkshire",
    "sg:tags":[
        "haulage",
        "transport",
        "road"
    ],
    "wof:name":"William Hamilton & Sons (Contractors) Ltd.",
    "wof:placetype":"venue"
},
  "geometry": {"coordinates":[-3.94614,55.6842],"type":"Point"}
}