{
  "type": "Feature",
  "properties": {
    "addr:full":"4 Willows Road Bourne End Berkshire SL8 5HG",
    "addr:housenumber":"4",
    "addr:postcode":"sl8 5hg",
    "addr:street":"Willows Road Bourne",
    "iso:country":"GB",
    "sg:address":"4 Willows Road",
    "sg:city":"Bourne End",
    "sg:classifiers":[
        {
            "category":"Building & Trades",
            "subcategory":"Plumbing",
            "type":"Services"
        }
    ],
    "sg:postcode":"SL8 5HG",
    "sg:province":"Berkshire",
    "sg:tags":[
        "central",
        "heating"
    ],
    "wof:name":"R J Wilkinson Plumbing & Heating",
    "wof:placetype":"venue"
},
  "geometry": {"coordinates":[-0.7030900121,51.5783157349],"type":"Point"}
}