{
  "type": "Feature",
  "properties": {
    "addr:full":"198 Upper Richmond Road West London Greater London SW14 8AN",
    "addr:housenumber":"198",
    "addr:postcode":"sw14 8an",
    "addr:street":"Upper Richmond Road West",
    "iso:country":"GB",
    "sg:address":"198 Upper Richmond Road West",
    "sg:city":"London",
    "sg:classifiers":[
        {
            "category":"Shopping",
            "subcategory":"Clothing, Apparel, & Fashions",
            "type":"Retail Goods"
        }
    ],
    "sg:phone":"+44 20 8878 2526",
    "sg:postcode":"SW14 8AN",
    "sg:province":"Greater London",
    "sg:tags":[
        "shop",
        "hat"
    ],
    "wof:name":"Felicity Hat Hire",
    "wof:placetype":"venue"
},
  "geometry": {"coordinates":[-0.2610040009,51.4650230408],"type":"Point"}
}