{
  "type": "Feature",
  "properties": {
    "addr:full":"22-23 Chadderton Shop Precinct, Middleton Road, Chadderton Oldham Lancashire OL9 0LQ",
    "addr:housenumber":"22-23",
    "addr:postcode":"ol9 0lq",
    "addr:street":"Middleton Road",
    "iso:country":"GB",
    "sg:address":"22-23 Chadderton Shop Precinct, Middleton Road, Chadderton",
    "sg:city":"Oldham",
    "sg:classifiers":[
        {
            "category":"Home & Garden",
            "subcategory":"Household Appliances",
            "type":"Retail Goods"
        }
    ],
    "sg:phone":"+44 161 665 2424",
    "sg:postcode":"OL9 0LQ",
    "sg:province":"Lancashire",
    "sg:tags":[
        "electrical",
        "domestic"
    ],
    "wof:name":"Tandy",
    "wof:placetype":"venue"
},
  "geometry": {"coordinates":[-2.155456,53.548763],"type":"Point"}
}