{
  "type": "Feature",
  "properties": {
    "addr:full":"Central Exchange Buildings, 128 Grainger Street Newcastle-upon-tyne Tyne and Wear NE1 5AF",
    "addr:housenumber":"128",
    "addr:postcode":"ne1 5af",
    "addr:street":"Grainger Street",
    "iso:country":"GB",
    "sg:address":"Central Exchange Buildings, 128 Grainger Street",
    "sg:city":"Newcastle-upon-tyne",
    "sg:classifiers":[
        {
            "category":"Manufacturing",
            "subcategory":"Tools & Machinery",
            "type":"Manufacturing & Wholesale Goods"
        }
    ],
    "sg:phone":"+44 191 232 2233",
    "sg:postcode":"NE1 5AF",
    "sg:province":"Tyne and Wear",
    "sg:tags":[
        "society",
        "friendly"
    ],
    "wof:name":"Miller Fisher",
    "wof:placetype":"venue"
},
  "geometry": {"coordinates":[-1.612369,54.977917],"type":"Point"}
}