{
  "type": "Feature",
  "properties": {
    "iso:country":"GB",
    "sg:address":"193 Newhaven Road",
    "sg:city":"Edinburgh",
    "sg:classifiers":[
        {
            "category":"Social Services",
            "subcategory":"Adult Care",
            "type":"Services"
        }
    ],
    "sg:postcode":"EH6 4QD",
    "sg:province":"City of Edinburgh",
    "sg:tags":[
        "domestic",
        "cleaning"
    ],
    "wof:name":"Home Agency",
    "wof:placetype":"venue"
},
  "geometry": {"coordinates":[-3.1925959587,55.9767723083],"type":"Point"}
}