{
  "type": "Feature",
  "properties": {
    "addr:full":"15 June Meadows Midhurst West Sussex GU29 9ER",
    "addr:housenumber":"15",
    "addr:postcode":"gu29 9er",
    "addr:street":"June Meadows",
    "iso:country":"GB",
    "sg:address":"15 June Meadows",
    "sg:city":"Midhurst",
    "sg:classifiers":[
        {
            "category":"Professional",
            "type":"Services"
        }
    ],
    "sg:phone":"+44 1730 814979",
    "sg:postcode":"GU29 9ER",
    "sg:province":"West Sussex",
    "sg:tags":[
        "repair",
        "tech",
        "maintenance"
    ],
    "wof:name":"JPR Computers",
    "wof:placetype":"venue"
},
  "geometry": {"coordinates":[-0.7487490177,50.9900398254],"type":"Point"}
}