{
  "type": "Feature",
  "properties": {
    "iso:country":"GB",
    "sg:address":"20 Regent Street",
    "sg:city":"Nottingham",
    "sg:classifiers":[
        {
            "category":"Organizations",
            "subcategory":"Professional Association",
            "type":"Services"
        }
    ],
    "sg:phone":"+44 115 941 7301",
    "sg:postcode":"NG1 5DF",
    "sg:province":"Nottinghamshire",
    "sg:tags":[
        "union",
        "trade"
    ],
    "wof:name":"Usdaw",
    "wof:placetype":"venue"
},
  "geometry": {"coordinates":[-1.1569540501,52.9531784058],"type":"Point"}
}