{
  "type": "Feature",
  "properties": {
    "iso:country":"GB",
    "sg:address":"Invincible Works, Marriner Road",
    "sg:city":"Keighley",
    "sg:classifiers":[
        {
            "category":"Freight",
            "type":"Transportation"
        }
    ],
    "sg:phone":"+44 1535 600151",
    "sg:postcode":"BD21 5LW",
    "sg:province":"West Yorkshire",
    "sg:tags":[
        "haulage",
        "transport",
        "road"
    ],
    "wof:name":"Watkinson Lifting & Transportation Ltd.",
    "wof:placetype":"venue"
},
  "geometry": {"coordinates":[-1.9096740484,53.8663635254],"type":"Point"}
}