{
  "type": "Feature",
  "properties": {
    "addr:full":"51 Chambersbury Lane Hemel Hempstead Hertfordshire HP3 8AZ",
    "addr:housenumber":"51",
    "addr:postcode":"hp3 8az",
    "addr:street":"Chambersbury Lane",
    "iso:country":"GB",
    "sg:address":"51 Chambersbury Lane",
    "sg:city":"Hemel Hempstead",
    "sg:classifiers":[
        {
            "category":"Professional",
            "subcategory":"Engineering",
            "type":"Services"
        }
    ],
    "sg:postcode":"HP3 8AZ",
    "sg:province":"Hertfordshire",
    "sg:tags":[
        "contractor",
        "electrical",
        "engineer"
    ],
    "wof:name":"Harbro Electric",
    "wof:placetype":"venue"
},
  "geometry": {"coordinates":[-0.448859,51.732792],"type":"Point"}
}