{
  "type": "Feature",
  "properties": {
    "iso:country":"GB",
    "sg:address":"6 Holme Street",
    "sg:city":"Grimsby",
    "sg:classifiers":[
        {
            "category":"Retail",
            "subcategory":"Auto Repair",
            "type":"Services"
        }
    ],
    "sg:phone":"+44 1472 350081",
    "sg:postcode":"DN32 9AD",
    "sg:province":"Lincolnshire",
    "sg:tags":[
        "modification",
        "garage"
    ],
    "wof:name":"Gollings & Johnstone Motor Services",
    "wof:placetype":"venue"
},
  "geometry": {"coordinates":[-0.0771280006,53.566368103],"type":"Point"}
}