{
  "type": "Feature",
  "properties": {
    "iso:country":"GB",
    "sg:address":"179-183 Streatham Road",
    "sg:city":"Mitcham",
    "sg:classifiers":[
        {
            "category":"Building & Trades",
            "subcategory":"Plumbing",
            "type":"Services"
        }
    ],
    "sg:phone":"+44 20 8685 9498",
    "sg:postcode":"CR4 2AG",
    "sg:province":"Greater London",
    "sg:tags":[
        "central",
        "heating"
    ],
    "wof:name":"Glowarm Central Heating Ltd.",
    "wof:placetype":"venue"
},
  "geometry": {"coordinates":[-0.153485,51.415688],"type":"Point"}
}