{
  "type": "Feature",
  "properties": {
    "iso:country":"GB",
    "sg:address":"Chancery Lane, Thrapston",
    "sg:city":"Kettering",
    "sg:classifiers":[
        {
            "category":"Education",
            "subcategory":"Preschool",
            "type":"Public Place"
        }
    ],
    "sg:phone":"+44 1832 732470",
    "sg:postcode":"NN14 4JL",
    "sg:province":"Northamptonshire",
    "sg:tags":[
        "pre-school",
        "playgroups"
    ],
    "wof:name":"Rainbow Playgroup",
    "wof:placetype":"venue"
},
  "geometry": {"coordinates":[-0.536835,52.39856],"type":"Point"}
}