{
  "type": "Feature",
  "properties": {
    "iso:country":"GB",
    "sg:address":"135 Irish Street",
    "sg:city":"Dumfries",
    "sg:classifiers":[
        {
            "category":"Professional",
            "subcategory":"Lawyer & Legal Services",
            "type":"Services"
        }
    ],
    "sg:phone":"+44 1387 255351",
    "sg:postcode":"DG1 2NT",
    "sg:province":"Dumfries and Galloway",
    "sg:tags":[
        "solicitor"
    ],
    "sg:website":"http://www.ggblaw.co.uk",
    "wof:name":"Gillespie Gifford & Brown",
    "wof:placetype":"venue"
},
  "geometry": {"coordinates":[-3.6126410961,55.0688171387],"type":"Point"}
}