{
  "type": "Feature",
  "properties": {
    "iso:country":"GB",
    "sg:address":"15 John Wood Street",
    "sg:city":"Port Glasgow",
    "sg:classifiers":[
        {
            "category":"Food & Beverages",
            "subcategory":"Liquor & Beverages",
            "type":"Retail Goods"
        }
    ],
    "sg:phone":"+44 1475 741037",
    "sg:postcode":"PA14 5HU",
    "sg:province":"Inverclyde",
    "sg:tags":[
        "beer",
        "wine",
        "spirit",
        "wines"
    ],
    "wof:name":"Haddows",
    "wof:placetype":"venue"
},
  "geometry": {"coordinates":[-4.680089,55.93224],"type":"Point"}
}