{
  "type": "Feature",
  "properties": {
    "iso:country":"GB",
    "sg:address":"Unit 2 Elm Lea Trading Estate, Leeside Rd",
    "sg:city":"Tottenham",
    "sg:classifiers":[
        {
            "category":"Retail",
            "subcategory":"Auto Repair",
            "type":"Services"
        }
    ],
    "sg:phone":"+44 20 8807 6905",
    "sg:postcode":"N17 0XR",
    "sg:province":"Greater London",
    "sg:tags":[
        "modification",
        "garage"
    ],
    "wof:name":"Neptune Accident & Repair Centre Ltd",
    "wof:placetype":"venue"
},
  "geometry": {"coordinates":[-0.047694,51.60553],"type":"Point"}
}