{
  "type": "Feature",
  "properties": {
    "addr:full":"300 Southcoates La Hull East Riding of Yorkshire HU9 3TN",
    "addr:housenumber":"300",
    "addr:postcode":"hu9 3tn",
    "addr:street":"Southcoates La Hull",
    "iso:country":"GB",
    "sg:address":"300 Southcoates La",
    "sg:city":"Hull",
    "sg:classifiers":[
        {
            "category":"Shopping",
            "subcategory":"Thrift Store",
            "type":"Retail Goods"
        }
    ],
    "sg:phone":"+44 1482 709685",
    "sg:postcode":"HU9 3TN",
    "sg:province":"East Riding of Yorkshire",
    "sg:tags":[
        "shop",
        "charity"
    ],
    "wof:name":"Peoples Dispensary for Sick Animals",
    "wof:placetype":"venue"
},
  "geometry": {"coordinates":[-0.2944940031,53.7579345703],"type":"Point"}
}