{
  "type": "Feature",
  "properties": {
    "addr:full":"9 Yates Lane, Rowley Regis Smethwick West Midlands B65 0RA",
    "addr:housenumber":"9",
    "addr:postcode":"b65 0ra",
    "addr:street":"Yates Lane",
    "iso:country":"GB",
    "sg:address":"9 Yates Lane, Rowley Regis",
    "sg:city":"Smethwick",
    "sg:classifiers":[
        {
            "category":"Building & Trades",
            "subcategory":"Construction",
            "type":"Services"
        }
    ],
    "sg:phone":"+44 121 559 1072",
    "sg:postcode":"B65 0RA",
    "sg:province":"West Midlands",
    "sg:tags":[
        "builder"
    ],
    "wof:name":"D Bastable & Son Ltd.",
    "wof:placetype":"venue"
},
  "geometry": {"coordinates":[-2.023265,52.479134],"type":"Point"}
}