{
  "type": "Feature",
  "properties": {
    "addr:full":"32 St Christophers Mews Wallington Surrey SM6 8AP",
    "addr:housenumber":"32",
    "addr:postcode":"sm6 8ap",
    "addr:street":"St Christophers Mews",
    "iso:country":"GB",
    "sg:address":"32 St Christophers Mews",
    "sg:city":"Wallington",
    "sg:classifiers":[
        {
            "category":"Banks & Credit Unions",
            "subcategory":"Financial Services",
            "type":"Services"
        }
    ],
    "sg:phone":"+44 20 8773 9633",
    "sg:postcode":"SM6 8AP",
    "sg:province":"Surrey",
    "sg:tags":[
        "adviser",
        "independent"
    ],
    "wof:name":"CITYVIEW FINANCIAL SERVICES",
    "wof:placetype":"venue"
},
  "geometry": {"coordinates":[-0.145248,51.362488],"type":"Point"}
}