{
  "type": "Feature",
  "properties": {
    "iso:country":"GB",
    "sg:address":"40 Hetherington Road",
    "sg:city":"Shepperton",
    "sg:classifiers":[
        {
            "category":"Building & Trades",
            "subcategory":"Cleaning & Sanitation",
            "type":"Services"
        }
    ],
    "sg:phone":"+44 1932 765582",
    "sg:postcode":"TW17 0SP",
    "sg:province":"Surrey",
    "sg:tags":[
        "commercial"
    ],
    "wof:name":"A J Procter Cleaning Contractors Co. Ltd.",
    "wof:placetype":"venue"
},
  "geometry": {"coordinates":[-0.443732,51.411194],"type":"Point"}
}