{
  "type": "Feature",
  "properties": {
    "addr:full":"162 Dewsbury Road Wakefield West Yorkshire WF2 9BE",
    "addr:housenumber":"162",
    "addr:postcode":"wf2 9be",
    "addr:street":"Dewsbury Road",
    "iso:country":"GB",
    "sg:address":"162 Dewsbury Road",
    "sg:city":"Wakefield",
    "sg:classifiers":[
        {
            "category":"Manufacturing",
            "subcategory":"Tools & Machinery",
            "type":"Manufacturing & Wholesale Goods"
        },
        {
            "category":"Insurance",
            "subcategory":"Insurance Agent",
            "type":"Services"
        }
    ],
    "sg:phone":"+44 1924 365369",
    "sg:postcode":"WF2 9BE",
    "sg:province":"West Yorkshire",
    "sg:tags":[
        "society",
        "friendly"
    ],
    "sg:website":"http://www.insurancebrokercompany.co.uk",
    "wof:name":"Reliance Insurance Agency",
    "wof:placetype":"venue"
},
  "geometry": {"coordinates":[-1.5192129612,53.678730011],"type":"Point"}
}