{
  "type": "Feature",
  "properties": {
    "iso:country":"GB",
    "sg:address":"89-95 Fountainbridge",
    "sg:city":"Edinburgh",
    "sg:classifiers":[
        {
            "category":"Organizations",
            "subcategory":"Non-profit Organization",
            "type":"Services"
        }
    ],
    "sg:phone":"+44 131 622 7083",
    "sg:postcode":"EH3 9PU",
    "sg:province":"City of Edinburgh",
    "sg:tags":[
        "organisation",
        "voluntary",
        "charity"
    ],
    "wof:name":"Pathway (Supporting Survivors)",
    "wof:placetype":"venue"
},
  "geometry": {"coordinates":[-3.206336,55.944221],"type":"Point"}
}