{
  "type": "Feature",
  "properties": {
    "addr:full":"14 Tunstall Villas Sunderland Tyne and Wear SR3 2BE",
    "addr:housenumber":"14",
    "addr:postcode":"sr3 2be",
    "addr:street":"Tunstall Villas",
    "iso:country":"GB",
    "sg:address":"14 Tunstall Villas",
    "sg:city":"Sunderland",
    "sg:classifiers":[
        {
            "category":"Place Of Worship",
            "type":"Public Place"
        }
    ],
    "sg:phone":"+44 191 567 4995",
    "sg:postcode":"SR3 2BE",
    "sg:province":"Tyne and Wear",
    "wof:name":"New Silksworth Methodist Church",
    "wof:placetype":"venue"
},
  "geometry": {"coordinates":[-1.3957649469,54.8739051819],"type":"Point"}
}