{
  "type": "Feature",
  "properties": {
    "iso:country":"GB",
    "sg:address":"Unit 2 Parkside Centre, Potters Way",
    "sg:city":"Southend-on-sea",
    "sg:classifiers":[
        {
            "category":"Retail",
            "subcategory":"Auto Repair",
            "type":"Services"
        }
    ],
    "sg:phone":"+44 1702 466072",
    "sg:postcode":"SS2 5SJ",
    "sg:province":"Essex",
    "sg:tags":[
        "electrical",
        "centre"
    ],
    "wof:name":"Eastwood Auto Electrical Service Ltd",
    "wof:placetype":"venue"
},
  "geometry": {"coordinates":[0.70741,51.562111],"type":"Point"}
}