{
  "type": "Feature",
  "properties": {
    "addr:full":"Suit 101 Linton House London Greater London SE1 0LH",
    "addr:housenumber":"101",
    "addr:postcode":"se1 0lh",
    "addr:street":"Linton House",
    "iso:country":"GB",
    "sg:address":"Suit 101 Linton House",
    "sg:city":"London",
    "sg:classifiers":[
        {
            "category":"Communications",
            "subcategory":"Film & Video Production",
            "type":"Services"
        }
    ],
    "sg:phone":"+44 20 7928 0100",
    "sg:postcode":"SE1 0LH",
    "sg:province":"Greater London",
    "sg:tags":[
        "illustrator",
        "artist"
    ],
    "wof:name":"International Art & Antique Loss Register Ltd.",
    "wof:placetype":"venue"
},
  "geometry": {"coordinates":[-0.09893,51.503792],"type":"Point"}
}