{
  "type": "Feature",
  "properties": {
    "iso:country":"GB",
    "sg:address":"Unit 5, White Lion Retail Park, Boscombe Road, Dunstable",
    "sg:city":"Dunstable",
    "sg:classifiers":[
        {
            "category":"Home & Garden",
            "subcategory":"Household Appliances",
            "type":"Retail Goods"
        }
    ],
    "sg:phone":"+44 1582 672604",
    "sg:postcode":"LU5 4WL",
    "sg:province":"Bedfordshire",
    "sg:tags":[
        "electrical",
        "domestic"
    ],
    "wof:name":"Powerhouse Retail Ltd",
    "wof:placetype":"venue"
},
  "geometry": {"coordinates":[-0.50513,51.877121],"type":"Point"}
}