{
  "type": "Feature",
  "properties": {
    "iso:country":"GB",
    "sg:address":"13 Pyecroft Avenue",
    "sg:city":"Bristol",
    "sg:classifiers":[
        {
            "category":"Professional",
            "subcategory":"Computer Services",
            "type":"Services"
        }
    ],
    "sg:phone":"+44 117 962 3121",
    "sg:postcode":"BS9 4NL",
    "sg:province":"City of Bristol",
    "sg:tags":[
        "system",
        "software"
    ],
    "wof:name":"Simple Solutions",
    "wof:placetype":"venue"
},
  "geometry": {"coordinates":[-2.601509,51.49073],"type":"Point"}
}