{
  "type": "Feature",
  "properties": {
    "addr:full":"3 Union Street Newton Abbot Devon TQ12 2JX",
    "addr:housenumber":"3",
    "addr:postcode":"tq12 2jx",
    "addr:street":"Union Street",
    "iso:country":"GB",
    "sg:address":"3 Union Street",
    "sg:city":"Newton Abbot",
    "sg:classifiers":[
        {
            "category":"Shopping",
            "subcategory":"Hobbies, Toys, & Games",
            "type":"Retail Goods"
        }
    ],
    "sg:phone":"+44 1626 202825",
    "sg:postcode":"TQ12 2JX",
    "sg:province":"Devon",
    "sg:tags":[
        "computer"
    ],
    "wof:name":"Game on",
    "wof:placetype":"venue"
},
  "geometry": {"coordinates":[-3.609803,50.530136],"type":"Point"}
}