{
  "type": "Feature",
  "properties": {
    "addr:full":"36 Upper St James' Street Brighton East Sussex BN2 1JN",
    "addr:housenumber":"36",
    "addr:postcode":"bn2 1jn",
    "addr:street":"Upper St;' Street",
    "iso:country":"GB",
    "sg:address":"36 Upper St James' Street",
    "sg:city":"Brighton",
    "sg:classifiers":[
        {
            "category":"Professional",
            "subcategory":"Secretarial Services",
            "type":"Services"
        }
    ],
    "sg:postcode":"BN2 1JN",
    "sg:province":"East Sussex",
    "wof:name":"Centrex",
    "wof:placetype":"venue"
},
  "geometry": {"coordinates":[-0.1276309937,50.819442749],"type":"Point"}
}