{
  "type": "Feature",
  "properties": {
    "addr:full":"42 Riding House St West End Hampshire W1P 7PL",
    "addr:housenumber":"42",
    "addr:postcode":"w1p 7pl",
    "addr:street":"Riding House St",
    "iso:country":"GB",
    "sg:address":"42 Riding House St",
    "sg:city":"West End",
    "sg:classifiers":[
        {
            "category":"Travel",
            "subcategory":"Travel Agent",
            "type":"Entertainment"
        }
    ],
    "sg:phone":"+44 20 7636 6888",
    "sg:postcode":"W1P 7PL",
    "sg:province":"Hampshire",
    "sg:tags":[
        "hotel",
        "agency",
        "booking"
    ],
    "wof:name":"Room Service",
    "wof:placetype":"venue"
},
  "geometry": {"coordinates":[-0.1393669993,51.5189743042],"type":"Point"}
}