{
  "type": "Feature",
  "properties": {
    "iso:country":"GB",
    "sg:address":"News House, 7-15 Kelvin Way",
    "sg:city":"Crawley",
    "sg:classifiers":[
        {
            "category":"Shopping",
            "subcategory":"Books",
            "type":"Retail Goods"
        },
        {
            "category":"Wholesale",
            "subcategory":"Books, Periodicals, & Newspapers",
            "type":"Manufacturing & Wholesale Goods"
        }
    ],
    "sg:phone":"+44 1293 562502",
    "sg:postcode":"RH10 9PW",
    "sg:province":"Surrey",
    "sg:tags":[
        "bookseller",
        "newsagent"
    ],
    "wof:name":"W H Smith News",
    "wof:placetype":"venue"
},
  "geometry": {"coordinates":[-0.177002,51.132229],"type":"Point"}
}