{
  "type": "Feature",
  "properties": {
    "addr:full":"121 West Percy Street North Shields Tyne and Wear NE29 0BY",
    "addr:housenumber":"121",
    "addr:postcode":"ne29 0by",
    "addr:street":"West Percy Street",
    "iso:country":"GB",
    "sg:address":"121 West Percy Street",
    "sg:city":"North Shields",
    "sg:classifiers":[
        {
            "category":"Professional",
            "subcategory":"Printing & Photocopies",
            "type":"Services"
        }
    ],
    "sg:phone":"+44 191 259 1819",
    "sg:postcode":"NE29 0BY",
    "sg:province":"Tyne and Wear",
    "sg:tags":[
        "printer"
    ],
    "wof:name":"Jem Print",
    "wof:placetype":"venue"
},
  "geometry": {"coordinates":[-1.452499032,55.0081481934],"type":"Point"}
}