{
  "type": "Feature",
  "properties": {
    "addr:full":"273 Park Rd Barnsley South Yorkshire S70 1QL",
    "addr:housenumber":"273",
    "addr:postcode":"s70 1ql",
    "addr:street":"Park Rd;Yorkshire",
    "iso:country":"GB",
    "sg:address":"273 Park Rd",
    "sg:city":"Barnsley",
    "sg:classifiers":[
        {
            "category":"Professional",
            "subcategory":"Secretarial Services",
            "type":"Services"
        }
    ],
    "sg:phone":"+44 7741 064024",
    "sg:postcode":"S70 1QL",
    "sg:province":"South Yorkshire",
    "wof:name":"J B Secretarial Services",
    "wof:placetype":"venue"
},
  "geometry": {"coordinates":[-1.489995,53.544453],"type":"Point"}
}