{
  "type": "Feature",
  "properties": {
    "iso:country":"GB",
    "sg:address":"Classic Works, Holyhead Road",
    "sg:city":"Wednesbury",
    "sg:classifiers":[
        {
            "category":"Autos & Motor Vehicles",
            "subcategory":"Automobile Sales",
            "type":"Retail Goods"
        },
        {
            "category":"Shopping",
            "subcategory":"Gifts & Souvenirs",
            "type":"Retail Goods"
        }
    ],
    "sg:phone":"+44 121 556 1471",
    "sg:postcode":"WS10 7PD",
    "sg:province":"West Midlands",
    "sg:tags":[
        "giftware",
        "tableware"
    ],
    "wof:name":"Queen Anne Tableware Ltd.",
    "wof:placetype":"venue"
},
  "geometry": {"coordinates":[-2.0192539692,52.5527305603],"type":"Point"}
}