{
  "type": "Feature",
  "properties": {
    "addr:full":"61 Reddish Lane Manchester Greater Manchester M18 7JH",
    "addr:housenumber":"61",
    "addr:postcode":"m18 7jh",
    "addr:street":"Reddish Lane",
    "iso:country":"GB",
    "sg:address":"61 Reddish Lane",
    "sg:city":"Manchester",
    "sg:classifiers":[
        {
            "category":"Fast Food",
            "type":"Food & Drink"
        },
        {
            "category":"Restaurant",
            "type":"Food & Drink"
        }
    ],
    "sg:phone":"+44 161 223 3672",
    "sg:postcode":"M18 7JH",
    "sg:province":"Greater Manchester",
    "sg:tags":[
        "away",
        "take"
    ],
    "wof:name":"THE TAK FOOD RESTAURANT",
    "wof:placetype":"venue"
},
  "geometry": {"coordinates":[-2.159668,53.456013],"type":"Point"}
}