{
  "type": "Feature",
  "properties": {
    "iso:country":"GB",
    "sg:address":"35 Portland Street",
    "sg:city":"Manchester",
    "sg:classifiers":[
        {
            "category":"Travel",
            "subcategory":"Hotels & Motels",
            "type":"Entertainment"
        }
    ],
    "sg:phone":"+44 161 228 2288",
    "sg:postcode":"M1 3LA",
    "sg:province":"Greater Manchester",
    "wof:name":"Britannia Hotel Manchester Ltd",
    "wof:placetype":"venue"
},
  "geometry": {"coordinates":[-2.237733,53.478897],"type":"Point"}
}