{
  "type": "Feature",
  "properties": {
    "iso:country":"GB",
    "sg:address":"1 Abbey Road",
    "sg:city":"Malvern",
    "sg:classifiers":[
        {
            "category":"Government",
            "subcategory":"Post Office",
            "type":"Public Place"
        }
    ],
    "sg:phone":"+44 1684 573003",
    "sg:postcode":"WR14 3HJ",
    "sg:province":"Herefordshire",
    "wof:name":"Great Malvern Post Office",
    "wof:placetype":"venue"
},
  "geometry": {"coordinates":[-2.329029,52.109558],"type":"Point"}
}