{
  "type": "Feature",
  "properties": {
    "addr:full":"31 Welbeck Drive Bradford West Yorkshire BD7 4BT",
    "addr:housenumber":"31",
    "addr:postcode":"bd7 4bt",
    "addr:street":"Welbeck Drive",
    "iso:country":"GB",
    "sg:address":"31 Welbeck Drive",
    "sg:city":"Bradford",
    "sg:classifiers":[
        {
            "category":"Communications",
            "subcategory":"Film & Video Production",
            "type":"Services"
        },
        {
            "category":"Professional",
            "subcategory":"Art Services",
            "type":"Services"
        }
    ],
    "sg:phone":"+44 1274 574780",
    "sg:postcode":"BD7 4BT",
    "sg:province":"West Yorkshire",
    "sg:tags":[
        "illustrator",
        "artist"
    ],
    "wof:name":"Stephen Abbey",
    "wof:placetype":"venue"
},
  "geometry": {"coordinates":[-1.801563,53.779598],"type":"Point"}
}