{
  "type": "Feature",
  "properties": {
    "addr:full":"Mill Road Industrial Estate Fareham Hampshire PO16 0TW",
    "addr:postcode":"po16 0tw",
    "addr:street":"Mill Road Industrial Estate",
    "iso:country":"GB",
    "sg:address":"Mill Road Industrial Estate",
    "sg:city":"Fareham",
    "sg:classifiers":[
        {
            "category":"Autos & Motor Vehicles",
            "subcategory":"Boat Sales",
            "type":"Retail Goods"
        }
    ],
    "sg:phone":"+44 1329 232103",
    "sg:postcode":"PO16 0TW",
    "sg:province":"Hampshire",
    "sg:tags":[
        "equipment"
    ],
    "wof:name":"International Sailing Products",
    "wof:placetype":"venue"
},
  "geometry": {"coordinates":[-1.182149,50.847462],"type":"Point"}
}