{
  "type": "Feature",
  "properties": {
    "iso:country":"GB",
    "sg:address":"Langdale Road",
    "sg:city":"Barnsley",
    "sg:classifiers":[
        {
            "category":"Retail",
            "subcategory":"Auto Repair",
            "type":"Services"
        }
    ],
    "sg:phone":"+44 1226 770669",
    "sg:postcode":"S71 1AQ",
    "sg:province":"South Yorkshire",
    "sg:tags":[
        "body",
        "car",
        "repairer"
    ],
    "wof:name":"E Whittle & Son",
    "wof:placetype":"venue"
},
  "geometry": {"coordinates":[-1.472383976,53.5505485535],"type":"Point"}
}