{
  "type": "Feature",
  "properties": {
    "addr:full":"Manor Farm, School Lane, Hints Tamworth Staffordshire B78 3DW",
    "addr:postcode":"b78 3dw",
    "addr:street":"Manor Farm School Lane",
    "iso:country":"GB",
    "sg:address":"Manor Farm, School Lane, Hints",
    "sg:city":"Tamworth",
    "sg:classifiers":[
        {
            "category":"Food & Beverages",
            "subcategory":"Farmers Market",
            "type":"Retail Goods"
        },
        {
            "category":"Farming",
            "subcategory":"Livestock Farm",
            "type":"Manufacturing & Wholesale Goods"
        }
    ],
    "sg:phone":"+44 1543 483308",
    "sg:postcode":"B78 3DW",
    "sg:province":"Staffordshire",
    "sg:tags":[
        "shop",
        "others"
    ],
    "wof:name":"J R Clarke & Partners",
    "wof:placetype":"venue"
},
  "geometry": {"coordinates":[-1.7680790424,52.6246147156],"type":"Point"}
}