{
  "type": "Feature",
  "properties": {
    "addr:full":"Chater Lea Building, Icknield Way Letchworth Hertfordshire SG6 1EZ",
    "addr:postcode":"sg6 1ez",
    "addr:street":"Icknield Way",
    "iso:country":"GB",
    "sg:address":"Chater Lea Building, Icknield Way",
    "sg:city":"Letchworth",
    "sg:classifiers":[
        {
            "category":"Manufacturing",
            "subcategory":"Wood Products",
            "type":"Manufacturing & Wholesale Goods"
        }
    ],
    "sg:phone":"+44 1462 480764",
    "sg:postcode":"SG6 1EZ",
    "sg:province":"Hertfordshire",
    "sg:tags":[
        "packaging",
        "crate",
        "pallets"
    ],
    "wof:name":"Cedesa Ltd.",
    "wof:placetype":"venue"
},
  "geometry": {"coordinates":[-0.222243,51.972549],"type":"Point"}
}