{
  "type": "Feature",
  "properties": {
    "iso:country":"GB",
    "sg:address":"Harris St",
    "sg:city":"Manchester",
    "sg:classifiers":[
        {
            "category":"Sports & Exercise",
            "subcategory":"Sports Center",
            "type":"Entertainment"
        }
    ],
    "sg:phone":"+44 161 832 2133",
    "sg:postcode":"M8 8EG",
    "sg:province":"Greater Manchester",
    "sg:tags":[
        "shop",
        "good"
    ],
    "wof:name":"Sports Factory",
    "wof:placetype":"venue"
},
  "geometry": {"coordinates":[-2.250998,53.493332],"type":"Point"}
}