{
  "type": "Feature",
  "properties": {
    "iso:country":"GB",
    "sg:address":"57 Lwr Forster St",
    "sg:city":"Walsall",
    "sg:classifiers":[
        {
            "category":"Shopping",
            "subcategory":"Pets & Pet Supplies",
            "type":"Retail Goods"
        }
    ],
    "sg:phone":"+44 1922 746697",
    "sg:postcode":"WS1 1XB",
    "sg:province":"West Midlands",
    "sg:tags":[
        "equestrian"
    ],
    "wof:name":"On Course Ltd",
    "wof:placetype":"venue"
},
  "geometry": {"coordinates":[-1.9779100418,52.5879974365],"type":"Point"}
}