{
  "type": "Feature",
  "properties": {
    "addr:full":"360 Evesham Road, Crabbs Cross Redditch Warwickshire B97 5JB",
    "addr:housenumber":"360",
    "addr:postcode":"b97 5jb",
    "addr:street":"Evesham Road",
    "iso:country":"GB",
    "sg:address":"360 Evesham Road, Crabbs Cross",
    "sg:city":"Redditch",
    "sg:classifiers":[
        {
            "category":"Shopping",
            "subcategory":"Pets & Pet Supplies",
            "type":"Retail Goods"
        }
    ],
    "sg:phone":"+44 1527 541982",
    "sg:postcode":"B97 5JB",
    "sg:province":"Warwickshire",
    "wof:name":"The Corn Stores",
    "wof:placetype":"venue"
},
  "geometry": {"coordinates":[-1.943399,52.28318],"type":"Point"}
}