{
  "type": "Feature",
  "properties": {
    "iso:country":"GB",
    "sg:address":"242 Lower High St",
    "sg:city":"Watford",
    "sg:classifiers":[
        {
            "category":"Autos & Motor Vehicles",
            "subcategory":"Automobile Sales",
            "type":"Retail Goods"
        }
    ],
    "sg:phone":"+44 1923 230909",
    "sg:postcode":"WD1 2JR",
    "sg:province":"Hertfordshire",
    "sg:tags":[
        "car"
    ],
    "wof:name":"Palace Fiat & Alfa Romeo",
    "wof:placetype":"venue"
},
  "geometry": {"coordinates":[-0.390143,51.651428],"type":"Point"}
}