{
  "type": "Feature",
  "properties": {
    "iso:country":"GB",
    "sg:address":"Melbourne View, Station Road, Melbourne",
    "sg:city":"Derby",
    "sg:classifiers":[
        {
            "category":"Retail",
            "subcategory":"Auto Repair",
            "type":"Services"
        }
    ],
    "sg:phone":"+44 1332 864625",
    "sg:postcode":"DE73 1BR",
    "sg:province":"Derbyshire",
    "sg:tags":[
        "modification",
        "garage"
    ],
    "wof:name":"S A S",
    "wof:placetype":"venue"
},
  "geometry": {"coordinates":[-1.427308,52.826107],"type":"Point"}
}