{
  "type": "Feature",
  "properties": {
    "iso:country":"GB",
    "sg:address":"Tawney Common, Theydon Mount",
    "sg:city":"Epping",
    "sg:classifiers":[
        {
            "category":"Bars & Pubs",
            "type":"Food & Drink"
        }
    ],
    "sg:phone":"+44 1992 522394",
    "sg:postcode":"CM16 7PU",
    "sg:province":"Essex",
    "sg:tags":[
        "pubs",
        "inn"
    ],
    "wof:name":"Moletrap Inn",
    "wof:placetype":"venue"
},
  "geometry": {"coordinates":[0.1688150018,51.6944389343],"type":"Point"}
}