{
  "type": "Feature",
  "properties": {
    "iso:country":"GB",
    "sg:address":"50 The Broadway",
    "sg:city":"Leigh-on-sea",
    "sg:classifiers":[
        {
            "category":"Real Estate",
            "subcategory":"Real Estate Agent",
            "type":"Services"
        }
    ],
    "sg:phone":"+44 1702 471371",
    "sg:postcode":"SS9 1AG",
    "sg:province":"Essex",
    "wof:name":"Essex Homes Property Management Ltd.",
    "wof:placetype":"venue"
},
  "geometry": {"coordinates":[0.6579790115,51.5414123535],"type":"Point"}
}