{
  "type": "Feature",
  "properties": {
    "addr:full":"Edinburh House, Great Portland Street London Greater London W1W 7RZ",
    "addr:postcode":"w1w 7rz",
    "addr:street":"Great Portland Street",
    "iso:country":"GB",
    "sg:address":"Edinburh House, Great Portland Street",
    "sg:city":"London",
    "sg:classifiers":[
        {
            "category":"Professional",
            "subcategory":"Management & Consulting",
            "type":"Services"
        }
    ],
    "sg:phone":"+44 20 7436 1111",
    "sg:postcode":"W1W 7RZ",
    "sg:province":"Greater London",
    "sg:tags":[
        "marketing",
        "consultant"
    ],
    "wof:name":"Roche Communications",
    "wof:placetype":"venue"
},
  "geometry": {"coordinates":[-0.1420300007,51.5176086426],"type":"Point"}
}