{
  "type": "Feature",
  "properties": {
    "addr:full":"Strangford House, Church Road Ashford Kent TN23 1RD",
    "addr:postcode":"tn23 1rd",
    "addr:street":"Church Road",
    "iso:country":"GB",
    "sg:address":"Strangford House, Church Road",
    "sg:city":"Ashford",
    "sg:classifiers":[
        {
            "category":"Shopping",
            "subcategory":"Department Store",
            "type":"Retail Goods"
        }
    ],
    "sg:postcode":"TN23 1RD",
    "sg:province":"Kent",
    "wof:name":"Express Music (london) Ltd",
    "wof:placetype":"venue"
},
  "geometry": {"coordinates":[0.87248,51.146191],"type":"Point"}
}