{
  "type": "Feature",
  "properties": {
    "iso:country":"GB",
    "sg:address":"22-26 Invincible Dr, Armstrong Centre Indust Park",
    "sg:city":"Newcastle Upon Tyne",
    "sg:classifiers":[
        {
            "category":"Home & Garden",
            "subcategory":"Kitchen Supply",
            "type":"Retail Goods"
        }
    ],
    "sg:phone":"+44 191 226 0188",
    "sg:postcode":"NE4 7HX",
    "sg:province":"Tyne and Wear",
    "sg:tags":[
        "equipment",
        "catering"
    ],
    "wof:name":"Party Palace",
    "wof:placetype":"venue"
},
  "geometry": {"coordinates":[-1.63624,54.962059],"type":"Point"}
}