{
  "type": "Feature",
  "properties": {
    "addr:full":"High Path London Greater London SW19 2JY",
    "addr:postcode":"sw19 2jy",
    "addr:street":"High Path",
    "iso:country":"GB",
    "sg:address":"High Path",
    "sg:city":"London",
    "sg:classifiers":[
        {
            "category":"Bars & Pubs",
            "type":"Food & Drink"
        }
    ],
    "sg:phone":"+44 20 8542 5342",
    "sg:postcode":"SW19 2JY",
    "sg:province":"Greater London",
    "sg:tags":[
        "pubs",
        "inn"
    ],
    "wof:name":"The Trafalgar",
    "wof:placetype":"venue"
},
  "geometry": {"coordinates":[-0.1912599951,51.4140014648],"type":"Point"}
}