{
  "type": "Feature",
  "properties": {
    "addr:full":"Limers Lane Bideford Devon EX39 2RG",
    "addr:postcode":"ex39 2rg",
    "addr:street":"Limers Lane",
    "iso:country":"GB",
    "sg:address":"Limers Lane",
    "sg:city":"Bideford",
    "sg:classifiers":[
        {
            "category":"Travel",
            "subcategory":"Hotels & Motels",
            "type":"Entertainment"
        }
    ],
    "sg:phone":"+44 1237 474239",
    "sg:postcode":"EX39 2RG",
    "sg:province":"Devon",
    "wof:name":"N M & Anthony S Jarrad",
    "wof:placetype":"venue"
},
  "geometry": {"coordinates":[-4.204259,51.019249],"type":"Point"}
}