{
  "type": "Feature",
  "properties": {
    "addr:full":"2 Gibson Street, Close House Bishop Auckland Durham DL14 8RT",
    "addr:housenumber":"2",
    "addr:postcode":"dl14 8rt",
    "addr:street":"Gibson Street Close House",
    "iso:country":"GB",
    "sg:address":"2 Gibson Street, Close House",
    "sg:city":"Bishop Auckland",
    "sg:classifiers":[
        {
            "category":"Retail",
            "subcategory":"Funeral Services",
            "type":"Services"
        }
    ],
    "sg:phone":"+44 1388 772724",
    "sg:postcode":"DL14 8RT",
    "sg:province":"Durham",
    "wof:name":"G H Raine",
    "wof:placetype":"venue"
},
  "geometry": {"coordinates":[-1.6414870024,54.6463813782],"type":"Point"}
}