{
  "type": "Feature",
  "properties": {
    "iso:country":"GB",
    "sg:address":"Oakland Croft Lane, Chipperfield",
    "sg:city":"King's Langley",
    "sg:classifiers":[
        {
            "category":"Home & Garden",
            "subcategory":"Hardware",
            "type":"Retail Goods"
        }
    ],
    "sg:phone":"+44 1923 264834",
    "sg:postcode":"WD4 9DX",
    "sg:province":"Hertfordshire",
    "sg:tags":[
        "heat",
        "mech",
        "exchanger"
    ],
    "wof:name":"Holmlea Refrigeration",
    "wof:placetype":"venue"
},
  "geometry": {"coordinates":[-0.491050005,51.7084617615],"type":"Point"}
}