{
  "type": "Feature",
  "properties": {
    "iso:country":"GB",
    "sg:address":"44 Dart Rd",
    "sg:city":"Newport",
    "sg:classifiers":[
        {
            "category":"Building & Trades",
            "subcategory":"Construction",
            "type":"Services"
        }
    ],
    "sg:phone":"+44 1633 850463",
    "sg:postcode":"NP9 6BT",
    "sg:province":"East Riding of Yorkshire",
    "sg:tags":[
        "roofing"
    ],
    "wof:name":"A S & M Roofing",
    "wof:placetype":"venue"
},
  "geometry": {"coordinates":[-3.022084,51.607643],"type":"Point"}
}