{
  "type": "Feature",
  "properties": {
    "addr:full":"Unit 4 Carlton Trading Estate Leeds West Yorkshire LS12 2QG",
    "addr:housenumber":"unit 4",
    "addr:postcode":"ls12 2qg",
    "addr:street":"Carlton Trading Estate",
    "iso:country":"GB",
    "sg:address":"Unit 4 Carlton Trading Estate",
    "sg:city":"Leeds",
    "sg:classifiers":[
        {
            "category":"Utilities",
            "subcategory":"Telephone",
            "type":"Services"
        }
    ],
    "sg:postcode":"LS12 2QG",
    "sg:province":"West Yorkshire",
    "sg:tags":[
        "telecommunication"
    ],
    "wof:name":"Ashwood Communications Ltd",
    "wof:placetype":"venue"
},
  "geometry": {"coordinates":[-1.5780860186,53.8009185791],"type":"Point"}
}