{
  "type": "Feature",
  "properties": {
    "addr:full":"100 Hilldene Avenue Romford Essex RM3 8DT",
    "addr:housenumber":"100",
    "addr:postcode":"rm3 8dt",
    "addr:street":"Hilldene Avenue",
    "iso:country":"GB",
    "sg:address":"100 Hilldene Avenue",
    "sg:city":"Romford",
    "sg:classifiers":[
        {
            "category":"Food & Beverages",
            "subcategory":"Bakery",
            "type":"Retail Goods"
        }
    ],
    "sg:phone":"+44 1708 377811",
    "sg:postcode":"RM3 8DT",
    "sg:province":"Essex",
    "sg:tags":[
        "baker"
    ],
    "wof:name":"Williams Bakery",
    "wof:placetype":"venue"
},
  "geometry": {"coordinates":[0.2167370021,51.6068534851],"type":"Point"}
}