{
  "type": "Feature",
  "properties": {
    "iso:country":"GB",
    "sg:address":"The Sporting View, Sports Centre, Bassett",
    "sg:city":"Southampton",
    "sg:classifiers":[
        {
            "category":"Bars & Pubs",
            "type":"Food & Drink"
        }
    ],
    "sg:phone":"+44 23 8079 0708",
    "sg:postcode":"SO16 7AY",
    "sg:province":"Hampshire",
    "sg:tags":[
        "pubs",
        "inn"
    ],
    "wof:name":"Southampton Sports Club Ltd.",
    "wof:placetype":"venue"
},
  "geometry": {"coordinates":[-1.413214,50.951431],"type":"Point"}
}