{
  "type": "Feature",
  "properties": {
    "addr:full":"23-25 Baldwin Street Bristol City of Bristol BS1 1NF",
    "addr:housenumber":"23-25",
    "addr:postcode":"bs1 1nf",
    "addr:street":"Baldwin Street",
    "iso:country":"GB",
    "sg:address":"23-25 Baldwin Street",
    "sg:city":"Bristol",
    "sg:classifiers":[
        {
            "category":"Banks & Credit Unions",
            "subcategory":"Financial Services",
            "type":"Services"
        }
    ],
    "sg:phone":"+44 117 948 0300",
    "sg:postcode":"BS1 1NF",
    "sg:province":"City of Bristol",
    "sg:tags":[
        "building",
        "society"
    ],
    "wof:name":"Nationwide",
    "wof:placetype":"venue"
},
  "geometry": {"coordinates":[-2.5952019691,51.453502655],"type":"Point"}
}