{
  "type": "Feature",
  "properties": {
    "addr:full":"Appledyke, Potteries Lane, Mytchett Camberley Hampshire GU16 6EX",
    "addr:postcode":"gu16 6ex",
    "addr:street":"Appledyke Potteries Lane",
    "iso:country":"GB",
    "sg:address":"Appledyke, Potteries Lane, Mytchett",
    "sg:city":"Camberley",
    "sg:classifiers":[
        {
            "category":"Professional",
            "subcategory":"Accounting & Tax Preparation",
            "type":"Services"
        }
    ],
    "sg:postcode":"GU16 6EX",
    "sg:province":"Hampshire",
    "sg:tags":[
        "accountant"
    ],
    "wof:name":"Silverflight Ltd",
    "wof:placetype":"venue"
},
  "geometry": {"coordinates":[-0.72549,51.287422],"type":"Point"}
}