{
  "type": "Feature",
  "properties": {
    "iso:country":"GB",
    "sg:address":"2-4 Exbourne Road",
    "sg:city":"Abingdon",
    "sg:classifiers":[
        {
            "category":"Government",
            "subcategory":"Post Office",
            "type":"Public Place"
        }
    ],
    "sg:postcode":"OX14 1DH",
    "sg:province":"Oxfordshire",
    "wof:name":"West End Post Office",
    "wof:placetype":"venue"
},
  "geometry": {"coordinates":[-1.2948960066,51.6704216003],"type":"Point"}
}