{
  "type": "Feature",
  "properties": {
    "addr:full":"Bramble Ho, Bramble St Derby Derbyshire DE1 1HU",
    "addr:postcode":"de1 1hu",
    "addr:street":"Bramble St",
    "iso:country":"GB",
    "sg:address":"Bramble Ho, Bramble St",
    "sg:city":"Derby",
    "sg:classifiers":[
        {
            "category":"Organizations",
            "subcategory":"Religious Organization",
            "type":"Services"
        }
    ],
    "sg:phone":"+44 1332 367367",
    "sg:postcode":"DE1 1HU",
    "sg:province":"Derbyshire",
    "sg:tags":[
        "organisation"
    ],
    "wof:name":"Christian Resource Centre",
    "wof:placetype":"venue"
},
  "geometry": {"coordinates":[-1.483684,52.925171],"type":"Point"}
}