{
  "type": "Feature",
  "properties": {
    "iso:country":"GB",
    "sg:address":"London Road",
    "sg:city":"Arundel",
    "sg:classifiers":[
        {
            "category":"Place Of Worship",
            "type":"Public Place"
        }
    ],
    "sg:phone":"+44 1903 882262",
    "sg:postcode":"BN18 9AT",
    "sg:province":"West Sussex",
    "wof:name":"St. Nicholas C E Church",
    "wof:placetype":"venue"
},
  "geometry": {"coordinates":[-0.5621690154,50.8569984436],"type":"Point"}
}