{
  "type": "Feature",
  "properties": {
    "addr:full":"47 Allerton Road, Woolton Liverpool Merseyside L25 7RE",
    "addr:housenumber":"47",
    "addr:postcode":"l25 7re",
    "addr:street":"Allerton Road",
    "iso:country":"GB",
    "sg:address":"47 Allerton Road, Woolton",
    "sg:city":"Liverpool",
    "sg:classifiers":[
        {
            "category":"Personal",
            "subcategory":"Beauty Salon",
            "type":"Services"
        }
    ],
    "sg:phone":"+44 151 428 5474",
    "sg:postcode":"L25 7RE",
    "sg:province":"Merseyside",
    "sg:tags":[
        "unisex",
        "hairdresser"
    ],
    "wof:name":"Maurice of Woolton",
    "wof:placetype":"venue"
},
  "geometry": {"coordinates":[-2.8686859608,53.3743629456],"type":"Point"}
}