{
  "type": "Feature",
  "properties": {
    "iso:country":"GB",
    "sg:address":"58 Westgate",
    "sg:city":"Bradford",
    "sg:classifiers":[
        {
            "category":"Shopping",
            "subcategory":"Used Merchandise",
            "type":"Retail Goods"
        }
    ],
    "sg:phone":"+44 1274 726660",
    "sg:postcode":"BD1 2QR",
    "sg:province":"West Yorkshire",
    "sg:tags":[
        "shop",
        "second-hand"
    ],
    "wof:name":"Everyday Things",
    "wof:placetype":"venue"
},
  "geometry": {"coordinates":[-1.757207,53.795227],"type":"Point"}
}