{
  "type": "Feature",
  "properties": {
    "addr:full":"Chilton Industrial Estate, 2 Addison Road Sudbury Essex CO10 2YW",
    "addr:housenumber":"2",
    "addr:postcode":"co10 2yw",
    "addr:street":"Industrial Estate;Addison Road",
    "iso:country":"GB",
    "sg:address":"Chilton Industrial Estate, 2 Addison Road",
    "sg:city":"Sudbury",
    "sg:classifiers":[
        {
            "category":"Home & Garden",
            "subcategory":"Home Furnishings",
            "type":"Retail Goods"
        }
    ],
    "sg:phone":"+44 1787 882582",
    "sg:postcode":"CO10 2YW",
    "sg:province":"Essex",
    "sg:tags":[
        "awning",
        "canopy",
        "blinds"
    ],
    "wof:name":"Caribbean Blinds (U K) Ltd.",
    "wof:placetype":"venue"
},
  "geometry": {"coordinates":[0.7343900204,52.0386047363],"type":"Point"}
}