{
  "type": "Feature",
  "properties": {
    "iso:country":"GB",
    "sg:address":"Recreation Ground, Callis Court Rd",
    "sg:city":"Broadstairs",
    "sg:classifiers":[
        {
            "category":"Arena",
            "subcategory":"Sports Club",
            "type":"Entertainment"
        }
    ],
    "sg:phone":"+44 1843 866608",
    "sg:postcode":"CT10 3AE",
    "sg:province":"Kent",
    "wof:name":"Broadstairs & St. Peters Lawn Tennis Club",
    "wof:placetype":"venue"
},
  "geometry": {"coordinates":[1.44106,51.358604],"type":"Point"}
}