{
  "type": "Feature",
  "properties": {
    "addr:full":"9 Rishworth Clo Stockport Cheshire SK2 5NG",
    "addr:housenumber":"9",
    "addr:postcode":"sk2 5ng",
    "addr:street":"Rishworth Clo",
    "iso:country":"GB",
    "sg:address":"9 Rishworth Clo",
    "sg:city":"Stockport",
    "sg:classifiers":[
        {
            "category":"Building & Trades",
            "subcategory":"Plumbing",
            "type":"Services"
        }
    ],
    "sg:phone":"+44 161 483 9196",
    "sg:postcode":"SK2 5NG",
    "sg:province":"Cheshire",
    "sg:tags":[
        "heating"
    ],
    "wof:name":"T Pound",
    "wof:placetype":"venue"
},
  "geometry": {"coordinates":[-2.1269049644,53.3920402527],"type":"Point"}
}