{
  "type": "Feature",
  "properties": {
    "iso:country":"GB",
    "sg:address":"The Street, Castle Combe",
    "sg:city":"Chippenham",
    "sg:classifiers":[
        {
            "category":"Shopping",
            "subcategory":"Gifts & Souvenirs",
            "type":"Retail Goods"
        },
        {
            "category":"Government",
            "subcategory":"Post Office",
            "type":"Public Place"
        }
    ],
    "sg:postcode":"SN14 7HU",
    "sg:province":"Gloucestershire",
    "sg:tags":[
        "shop"
    ],
    "wof:name":"THE OLD POST OFFICE",
    "wof:placetype":"venue"
},
  "geometry": {"coordinates":[-2.268149,51.514595],"type":"Point"}
}