{
  "type": "Feature",
  "properties": {
    "addr:full":"Charford Rd Bromsgrove Worcestershire B60 3NJ",
    "addr:postcode":"b60 3nj",
    "addr:street":"Charford Rd",
    "iso:country":"GB",
    "sg:address":"Charford Rd",
    "sg:city":"Bromsgrove",
    "sg:classifiers":[
        {
            "category":"Military Area",
            "subcategory":"Air Force Base",
            "type":"Public Place"
        }
    ],
    "sg:phone":"+44 1527 873008",
    "sg:postcode":"B60 3NJ",
    "sg:province":"Worcestershire",
    "sg:tags":[
        "taxi",
        "hire",
        "private"
    ],
    "wof:name":"His N Her Taxis",
    "wof:placetype":"venue"
},
  "geometry": {"coordinates":[-2.0695309639,52.3267211914],"type":"Point"}
}