{
  "type": "Feature",
  "properties": {
    "addr:full":"2 Chatfield Slough Berkshire SL2 1SE",
    "addr:housenumber":"2",
    "addr:postcode":"sl2 1se",
    "addr:street":"Chatfield",
    "iso:country":"GB",
    "sg:address":"2 Chatfield",
    "sg:city":"Slough",
    "sg:classifiers":[
        {
            "category":"Building & Trades",
            "subcategory":"Construction",
            "type":"Services"
        }
    ],
    "sg:postcode":"SL2 1SE",
    "sg:province":"Berkshire",
    "sg:tags":[
        "roofing"
    ],
    "wof:name":"Ajax Roofing",
    "wof:placetype":"venue"
},
  "geometry": {"coordinates":[-0.627424,51.529259],"type":"Point"}
}