{
  "type": "Feature",
  "properties": {
    "iso:country":"GB",
    "sg:address":"29 Colwyn Avenue, Rhos On Sea",
    "sg:city":"Colwyn Bay",
    "sg:classifiers":[
        {
            "category":"Food & Beverages",
            "subcategory":"Liquor & Beverages",
            "type":"Retail Goods"
        }
    ],
    "sg:phone":"+44 1492 545449",
    "sg:postcode":"LL28 4RB",
    "sg:province":"Conwy",
    "sg:tags":[
        "beer",
        "spirit",
        "wines"
    ],
    "wof:name":"B & J Wines",
    "wof:placetype":"venue"
},
  "geometry": {"coordinates":[-3.740995,53.309658],"type":"Point"}
}