{
  "type": "Feature",
  "properties": {
    "iso:country":"GB",
    "sg:address":"35 High Street",
    "sg:city":"Maidstone",
    "sg:classifiers":[
        {
            "category":"Shopping",
            "subcategory":"Mobile Phones",
            "type":"Retail Goods"
        }
    ],
    "sg:phone":"+44 1622 756605",
    "sg:postcode":"ME14 1JH",
    "sg:province":"Kent",
    "wof:name":"Tagrose Ltd.",
    "wof:placetype":"venue"
},
  "geometry": {"coordinates":[0.519886,51.272846],"type":"Point"}
}