{
  "type": "Feature",
  "properties": {
    "addr:full":"9 St Georges Street Chorley Lancashire PR7 2AA",
    "addr:housenumber":"9",
    "addr:postcode":"pr7 2aa",
    "addr:street":"St Georges Street",
    "iso:country":"GB",
    "sg:address":"9 St Georges Street",
    "sg:city":"Chorley",
    "sg:classifiers":[
        {
            "category":"Personal",
            "type":"Services"
        },
        {
            "category":"Professional",
            "subcategory":"Lawyer & Legal Services",
            "type":"Services"
        }
    ],
    "sg:phone":"+44 1257 272828",
    "sg:postcode":"PR7 2AA",
    "sg:province":"Lancashire",
    "sg:tags":[
        "advice",
        "counselling"
    ],
    "wof:name":"Chorley Life Group",
    "wof:placetype":"venue"
},
  "geometry": {"coordinates":[-2.6316809654,53.6522789001],"type":"Point"}
}