{
  "type": "Feature",
  "properties": {
    "iso:country":"GB",
    "sg:address":"257-259 Halliwell Road",
    "sg:city":"Bolton",
    "sg:classifiers":[
        {
            "category":"Building & Trades",
            "subcategory":"Plumbing",
            "type":"Services"
        },
        {
            "category":"Wholesale",
            "subcategory":"Electrical",
            "type":"Manufacturing & Wholesale Goods"
        }
    ],
    "sg:phone":"+44 1204 388448",
    "sg:postcode":"BL1 3NT",
    "sg:province":"Lancashire",
    "sg:tags":[
        "wholesaler",
        "merchant",
        "plumbers'"
    ],
    "wof:name":"Northern Electrical & Plumbing Supplies",
    "wof:placetype":"venue"
},
  "geometry": {"coordinates":[-2.436685,53.592033],"type":"Point"}
}