{
  "type": "Feature",
  "properties": {
    "addr:full":"East Solent Corporate Business Centre, 176 London Rd Portsmouth Hampshire PO2 9DR",
    "addr:housenumber":"176",
    "addr:postcode":"hampshire po2 9dr",
    "addr:street":"East;London Rd",
    "iso:country":"GB",
    "sg:address":"East Solent Corporate Business Centre, 176 London Rd",
    "sg:city":"Portsmouth",
    "sg:classifiers":[
        {
            "category":"Banks & Credit Unions",
            "subcategory":"Bank",
            "type":"Services"
        }
    ],
    "sg:phone":"+44 23 9266 5060",
    "sg:postcode":"PO2 9DR",
    "sg:province":"Hampshire",
    "wof:name":"NatWest",
    "wof:placetype":"venue"
},
  "geometry": {"coordinates":[-1.07717,50.8195],"type":"Point"}
}