{
  "type": "Feature",
  "properties": {
    "addr:full":"Queens Drive West Peterborough Cambridgeshire PE1 2UU",
    "addr:postcode":"pe1 2uu",
    "addr:street":"Queens Drive West",
    "iso:country":"GB",
    "sg:address":"Queens Drive West",
    "sg:city":"Peterborough",
    "sg:classifiers":[
        {
            "category":"Education",
            "subcategory":"School",
            "type":"Public Place"
        }
    ],
    "sg:phone":"+44 1733 343914",
    "sg:postcode":"PE1 2UU",
    "sg:province":"Cambridgeshire",
    "sg:tags":[
        "local",
        "authority"
    ],
    "wof:name":"Queen's Drive Infant School",
    "wof:placetype":"venue"
},
  "geometry": {"coordinates":[-0.240304,52.586094],"type":"Point"}
}