{
  "type": "Feature",
  "properties": {
    "iso:country":"GB",
    "sg:address":"34 Goodymoor Av",
    "sg:city":"Wells",
    "sg:classifiers":[
        {
            "category":"Building & Trades",
            "subcategory":"Construction",
            "type":"Services"
        }
    ],
    "sg:phone":"+44 1749 675215",
    "sg:postcode":"BA5 2JH",
    "sg:province":"Somerset",
    "sg:tags":[
        "joiner",
        "carpenter"
    ],
    "wof:name":"Ernest Adams",
    "wof:placetype":"venue"
},
  "geometry": {"coordinates":[-2.662482,51.213512],"type":"Point"}
}