{
  "type": "Feature",
  "properties": {
    "addr:full":"New Lands, Otley Rd Woodbridge Suffolk IP13 6RY",
    "addr:postcode":"ip13 6ry",
    "addr:street":"New Lands Otley Rd",
    "iso:country":"GB",
    "sg:address":"New Lands, Otley Rd",
    "sg:city":"Woodbridge",
    "sg:classifiers":[
        {
            "category":"Building & Trades",
            "subcategory":"Landscaping Services",
            "type":"Services"
        }
    ],
    "sg:phone":"+44 1473 738363",
    "sg:postcode":"IP13 6RY",
    "sg:province":"Suffolk",
    "sg:tags":[
        "pond",
        "aquarium"
    ],
    "wof:name":"Coral World Aquatics",
    "wof:placetype":"venue"
},
  "geometry": {"coordinates":[1.2189699411,52.1290512085],"type":"Point"}
}