{
  "type": "Feature",
  "properties": {
    "iso:country":"GB",
    "sg:address":"Kimberley Street",
    "sg:city":"Norwich",
    "sg:classifiers":[
        {
            "category":"Retail",
            "subcategory":"Funeral Services",
            "type":"Services"
        },
        {
            "category":"Building & Trades",
            "subcategory":"Construction",
            "type":"Services"
        }
    ],
    "sg:phone":"+44 1603 625625",
    "sg:postcode":"NR2 2RJ",
    "sg:province":"Norfolk",
    "sg:tags":[
        "builder"
    ],
    "wof:name":"G W Gooch & Sons Ltd.",
    "wof:placetype":"venue"
},
  "geometry": {"coordinates":[1.283055,52.626331],"type":"Point"}
}