{
  "type": "Feature",
  "properties": {
    "iso:country":"GB",
    "sg:address":"32 Moor Lane",
    "sg:city":"Bolton",
    "sg:classifiers":[
        {
            "category":"Professional",
            "subcategory":"Lawyer & Legal Services",
            "type":"Services"
        }
    ],
    "sg:postcode":"BL1 4TE",
    "sg:province":"Lancashire",
    "sg:tags":[
        "solicitor"
    ],
    "wof:name":"Dearden Tonge & Co",
    "wof:placetype":"venue"
},
  "geometry": {"coordinates":[-2.434793,53.577736],"type":"Point"}
}