{
  "type": "Feature",
  "properties": {
    "iso:country":"GB",
    "sg:address":"Longmead",
    "sg:city":"Shaftesbury",
    "sg:classifiers":[
        {
            "category":"Food & Beverages",
            "subcategory":"Supermarket",
            "type":"Retail Goods"
        }
    ],
    "sg:phone":"+44 1747 851511",
    "sg:postcode":"SP7 8PL",
    "sg:province":"Dorset",
    "sg:tags":[
        "frozen"
    ],
    "wof:name":"Dorset Chilled Foods",
    "wof:placetype":"venue"
},
  "geometry": {"coordinates":[-2.190876,51.009705],"type":"Point"}
}