{
  "type": "Feature",
  "properties": {
    "addr:full":"The Boat Store, Steyne Road Seaview Isle of Wight PO34 5EW",
    "addr:postcode":"po34 5ew",
    "addr:street":"Steyne Road",
    "iso:country":"GB",
    "sg:address":"The Boat Store, Steyne Road",
    "sg:city":"Seaview",
    "sg:classifiers":[
        {
            "category":"Social Services",
            "subcategory":"Retirement Home",
            "type":"Services"
        },
        {
            "category":"Real Estate",
            "subcategory":"Architect",
            "type":"Services"
        }
    ],
    "sg:phone":"+44 1983 811927",
    "sg:postcode":"PO34 5EW",
    "sg:province":"Isle of Wight",
    "sg:tags":[
        "naval"
    ],
    "wof:name":"T T Boat Design Ltd",
    "wof:placetype":"venue"
},
  "geometry": {"coordinates":[-1.1102739573,50.7195587158],"type":"Point"}
}