{
  "type": "Feature",
  "properties": {
    "iso:country":"GB",
    "sg:address":"1 Howard Close, Burley",
    "sg:city":"Ringwood",
    "sg:classifiers":[
        {
            "category":"Home & Garden",
            "subcategory":"Hardware",
            "type":"Retail Goods"
        }
    ],
    "sg:phone":"+44 1425 402066",
    "sg:postcode":"BH24 4AJ",
    "sg:province":"Dorset",
    "sg:tags":[
        "gear",
        "cutter"
    ],
    "wof:name":"South Coast Diesels",
    "wof:placetype":"venue"
},
  "geometry": {"coordinates":[-1.7025159597,50.8265075684],"type":"Point"}
}