{
  "type": "Feature",
  "properties": {
    "iso:country":"GB",
    "sg:address":"2 The Moor",
    "sg:city":"Sheffield",
    "sg:classifiers":[
        {
            "category":"Professional",
            "subcategory":"Art Services",
            "type":"Services"
        }
    ],
    "sg:phone":"+44 114 276 7055",
    "sg:postcode":"S1 3LR",
    "sg:province":"South Yorkshire",
    "sg:tags":[
        "photographer"
    ],
    "wof:name":"Parasol Portrait Photography Ltd",
    "wof:placetype":"venue"
},
  "geometry": {"coordinates":[-1.472835,53.377075],"type":"Point"}
}