{
  "type": "Feature",
  "properties": {
    "addr:full":"Kingston House, 85 Main Street Pembroke Pembrokeshire SA71 4DB",
    "addr:housenumber":"85",
    "addr:postcode":"sa71 4db",
    "addr:street":"Main Street",
    "iso:country":"GB",
    "sg:address":"Kingston House, 85 Main Street",
    "sg:city":"Pembroke",
    "sg:classifiers":[
        {
            "category":"Retail",
            "subcategory":"Veterinary Services",
            "type":"Services"
        }
    ],
    "sg:phone":"+44 1646 622943",
    "sg:postcode":"SA71 4DB",
    "sg:province":"Pembrokeshire",
    "sg:tags":[
        "surgeon"
    ],
    "wof:name":"Graham Goodrich",
    "wof:placetype":"venue"
},
  "geometry": {"coordinates":[-4.91354,51.674793],"type":"Point"}
}