{
  "type": "Feature",
  "properties": {
    "addr:full":"54 Northridge Road Gravesend Kent DA12 5AY",
    "addr:housenumber":"54",
    "addr:postcode":"da12 5ay",
    "addr:street":"Northridge Road",
    "iso:country":"GB",
    "sg:address":"54 Northridge Road",
    "sg:city":"Gravesend",
    "sg:classifiers":[
        {
            "category":"Organizations",
            "subcategory":"Membership Organization",
            "type":"Services"
        }
    ],
    "sg:postcode":"DA12 5AY",
    "sg:province":"Kent",
    "sg:tags":[
        "club"
    ],
    "wof:name":"Barry Greenstreet Associates Ltd",
    "wof:placetype":"venue"
},
  "geometry": {"coordinates":[0.373925,51.425705],"type":"Point"}
}