{
  "type": "Feature",
  "properties": {
    "addr:full":"Unit 21/23, Dockray Hall Industrial Estate, Dockray Hall Road Kendal Cumbria LA9 4RU",
    "addr:housenumber":"unit 21 / 23",
    "addr:postcode":"la9 4ru",
    "addr:street":"Dockray Hall Industrial Estate Dockray Hall Road",
    "iso:country":"GB",
    "sg:address":"Unit 21/23, Dockray Hall Industrial Estate, Dockray Hall Road",
    "sg:city":"Kendal",
    "sg:classifiers":[
        {
            "category":"Manufacturing",
            "subcategory":"Petroleum Products",
            "type":"Manufacturing & Wholesale Goods"
        },
        {
            "category":"Wholesale",
            "subcategory":"Construction Materials",
            "type":"Manufacturing & Wholesale Goods"
        }
    ],
    "sg:phone":"+44 1539 722022",
    "sg:postcode":"LA9 4RU",
    "sg:province":"Cumbria",
    "sg:tags":[
        "supplier",
        "double",
        "glazing"
    ],
    "wof:name":"D J Glazing Ltd",
    "wof:placetype":"venue"
},
  "geometry": {"coordinates":[-2.7480840683,54.3240013123],"type":"Point"}
}