{
  "type": "Feature",
  "properties": {
    "addr:full":"Ludlow Road, Clee Hill Ludlow Herefordshire SY8 3PE",
    "addr:postcode":"sy8 3pe",
    "addr:street":"Ludlow Road",
    "iso:country":"GB",
    "sg:address":"Ludlow Road, Clee Hill",
    "sg:city":"Ludlow",
    "sg:classifiers":[
        {
            "category":"Bars & Pubs",
            "type":"Food & Drink"
        }
    ],
    "sg:postcode":"SY8 3PE",
    "sg:province":"Herefordshire",
    "sg:tags":[
        "pubs",
        "inn"
    ],
    "wof:name":"The Royal Oak",
    "wof:placetype":"venue"
},
  "geometry": {"coordinates":[-2.6816449165,52.3824996948],"type":"Point"}
}