{
  "type": "Feature",
  "properties": {
    "addr:full":"40 Yarrow Cres Wishaw North Lanarkshire ML2 7JX",
    "addr:housenumber":"40",
    "addr:postcode":"ml2 7jx",
    "addr:street":"Yarrow Cres",
    "iso:country":"GB",
    "sg:address":"40 Yarrow Cres",
    "sg:city":"Wishaw",
    "sg:classifiers":[
        {
            "category":"Professional",
            "type":"Services"
        }
    ],
    "sg:phone":"+44 1698 358057",
    "sg:postcode":"ML2 7JX",
    "sg:province":"North Lanarkshire",
    "sg:tags":[
        "caterer"
    ],
    "wof:name":"Ace Catering",
    "wof:placetype":"venue"
},
  "geometry": {"coordinates":[-3.919105,55.781807],"type":"Point"}
}