{
  "type": "Feature",
  "properties": {
    "iso:country":"GB",
    "sg:address":"8 Shoppers Walk Oxford Street",
    "sg:city":"Swansea",
    "sg:classifiers":[
        {
            "category":"Wholesale",
            "subcategory":"Medical Equipment & Supplies",
            "type":"Manufacturing & Wholesale Goods"
        }
    ],
    "sg:phone":"+44 1792 651388",
    "sg:postcode":"SA1 3AZ",
    "sg:province":"Neath Port Talbot",
    "sg:tags":[
        "aid",
        "hearing"
    ],
    "wof:name":"Ingrams Ltd.",
    "wof:placetype":"venue"
},
  "geometry": {"coordinates":[-3.940928936,51.6231536865],"type":"Point"}
}