{
  "type": "Feature",
  "properties": {
    "iso:country":"GB",
    "sg:address":"104 Marchmont Crescent",
    "sg:city":"Edinburgh",
    "sg:classifiers":[
        {
            "category":"Real Estate",
            "subcategory":"Real Estate Agent",
            "type":"Services"
        }
    ],
    "sg:postcode":"EH9 1HD",
    "sg:province":"City of Edinburgh",
    "wof:name":"Edinburgh Property Management",
    "wof:placetype":"venue"
},
  "geometry": {"coordinates":[-3.193969,55.93642],"type":"Point"}
}