{
  "type": "Feature",
  "properties": {
    "addr:full":"33 Arundel Street Portsmouth Hampshire PO1 1NB",
    "addr:housenumber":"33",
    "addr:postcode":"hampshire po1 1nb",
    "addr:street":"Arundel Street",
    "iso:country":"GB",
    "sg:address":"33 Arundel Street",
    "sg:city":"Portsmouth",
    "sg:classifiers":[
        {
            "category":"Shopping",
            "subcategory":"News",
            "type":"Retail Goods"
        }
    ],
    "sg:phone":"+44 23 9281 6020",
    "sg:postcode":"PO1 1NB",
    "sg:province":"Hampshire",
    "sg:tags":[
        "newsagent"
    ],
    "wof:name":"H R & A M Burden",
    "wof:placetype":"venue"
},
  "geometry": {"coordinates":[-1.086337,50.799828],"type":"Point"}
}