{
  "type": "Feature",
  "properties": {
    "addr:full":"18-20 The Colosseum Manchester Greater Manchester M4 1PL",
    "addr:housenumber":"18-20",
    "addr:postcode":"m4 1pl",
    "addr:street":"The Colosseum",
    "iso:country":"GB",
    "sg:address":"18-20 The Colosseum",
    "sg:city":"Manchester",
    "sg:classifiers":[
        {
            "category":"Shopping",
            "type":"Retail Goods"
        }
    ],
    "sg:phone":"+44 161 907 3383",
    "sg:postcode":"M4 1PL",
    "sg:province":"Greater Manchester",
    "sg:tags":[
        "shop",
        "new age"
    ],
    "wof:name":"Isis",
    "wof:placetype":"venue"
},
  "geometry": {"coordinates":[-2.23484,53.483681],"type":"Point"}
}