{
  "type": "Feature",
  "properties": {
    "addr:full":"4 St Georges Parade Wolverhampton West Midlands WV2 1BA",
    "addr:housenumber":"4",
    "addr:postcode":"wv2 1ba",
    "addr:street":"St Georges Parade",
    "iso:country":"GB",
    "sg:address":"4 St Georges Parade",
    "sg:city":"Wolverhampton",
    "sg:classifiers":[
        {
            "category":"Wholesale",
            "subcategory":"Home Furnishings",
            "type":"Manufacturing & Wholesale Goods"
        },
        {
            "category":"Home & Garden",
            "subcategory":"Carpets & Floor Coverings",
            "type":"Retail Goods"
        }
    ],
    "sg:phone":"+44 1902 426429",
    "sg:postcode":"WV2 1BA",
    "sg:province":"West Midlands",
    "sg:tags":[
        "carpets",
        "rug",
        "matting",
        "wsale"
    ],
    "wof:name":"Virgo Carpets Ltd.",
    "wof:placetype":"venue"
},
  "geometry": {"coordinates":[-2.1229760647,52.5819206238],"type":"Point"}
}