{
  "type": "Feature",
  "properties": {
    "iso:country":"GB",
    "sg:address":"32 Highlands Way, Dibden Purlieu",
    "sg:city":"Southampton",
    "sg:classifiers":[
        {
            "category":"Professional",
            "subcategory":"Art Services",
            "type":"Services"
        }
    ],
    "sg:postcode":"SO45 4HX",
    "sg:province":"Hampshire",
    "sg:tags":[
        "photographer"
    ],
    "wof:name":"Malcolm Flux Wedding Photographer",
    "wof:placetype":"venue"
},
  "geometry": {"coordinates":[-1.406366,50.858326],"type":"Point"}
}