{
  "type": "Feature",
  "properties": {
    "addr:full":"46 Guash Way, Ryhall Road Stamford Cambridgeshire PE9 1XU",
    "addr:housenumber":"46",
    "addr:postcode":"pe9 1xu",
    "addr:street":"Guash Way Ryhall Road",
    "iso:country":"GB",
    "sg:address":"46 Guash Way, Ryhall Road",
    "sg:city":"Stamford",
    "sg:classifiers":[
        {
            "category":"Autos & Motor Vehicles",
            "subcategory":"Auto Supplies",
            "type":"Retail Goods"
        }
    ],
    "sg:phone":"+44 1780 752063",
    "sg:postcode":"PE9 1XU",
    "sg:province":"Cambridgeshire",
    "sg:tags":[
        "tyre"
    ],
    "wof:name":"Kingsway Tyres (Stamford) Ltd.",
    "wof:placetype":"venue"
},
  "geometry": {"coordinates":[-0.465563,52.664146],"type":"Point"}
}