{
  "type": "Feature",
  "properties": {
    "iso:country":"GB",
    "sg:address":"21 East Hill Road, Houghton Regis",
    "sg:city":"Dunstable",
    "sg:classifiers":[
        {
            "category":"Communications",
            "subcategory":"News Services",
            "type":"Services"
        }
    ],
    "sg:phone":"+44 1582 862674",
    "sg:postcode":"LU5 5EQ",
    "sg:province":"Bedfordshire",
    "sg:tags":[
        "illustrator"
    ],
    "wof:name":"T G Wood",
    "wof:placetype":"venue"
},
  "geometry": {"coordinates":[-0.515165,51.908615],"type":"Point"}
}