{
  "type": "Feature",
  "properties": {
    "iso:country":"GB",
    "sg:address":"The Paddocks, Crouchley Lane",
    "sg:city":"Lymm",
    "sg:classifiers":[
        {
            "category":"Education",
            "subcategory":"Special Training",
            "type":"Public Place"
        }
    ],
    "sg:postcode":"WA13 0AT",
    "sg:province":"Cheshire",
    "sg:tags":[
        "aid",
        "first"
    ],
    "wof:name":"Dingle Training Centre Ltd",
    "wof:placetype":"venue"
},
  "geometry": {"coordinates":[-2.487556,53.379574],"type":"Point"}
}