{
  "type": "Feature",
  "properties": {
    "addr:full":"Fferm Tyllwyd, Felingwm Uchaf Carmarthen Carmarthenshire SA32 7QE",
    "addr:postcode":"sa32 7qe",
    "addr:street":"Felingwm Uchaf",
    "iso:country":"GB",
    "sg:address":"Fferm Tyllwyd, Felingwm Uchaf",
    "sg:city":"Carmarthen",
    "sg:classifiers":[
        {
            "category":"Farming",
            "subcategory":"Livestock Farm",
            "type":"Manufacturing & Wholesale Goods"
        }
    ],
    "sg:phone":"+44 1267 290537",
    "sg:postcode":"SA32 7QE",
    "sg:province":"Carmarthenshire",
    "sg:tags":[
        "others"
    ],
    "wof:name":"J & H James",
    "wof:placetype":"venue"
},
  "geometry": {"coordinates":[-4.1683602333,51.9102210999],"type":"Point"}
}