{
  "type": "Feature",
  "properties": {
    "addr:full":"78 Main Street, Uddingston Glasgow Glasgow City G71 7LR",
    "addr:housenumber":"78",
    "addr:postcode":"g71 7lr",
    "addr:street":"Main Street",
    "iso:country":"GB",
    "sg:address":"78 Main Street, Uddingston",
    "sg:city":"Glasgow",
    "sg:classifiers":[
        {
            "category":"Personal",
            "subcategory":"Beauty Salon",
            "type":"Services"
        },
        {
            "category":"Personal",
            "subcategory":"Barber",
            "type":"Services"
        }
    ],
    "sg:phone":"+44 1698 814137",
    "sg:postcode":"G71 7LR",
    "sg:province":"Glasgow City",
    "sg:tags":[
        "unisex",
        "hairdresser"
    ],
    "wof:name":"Fabio Unisex Hairdressers",
    "wof:placetype":"venue"
},
  "geometry": {"coordinates":[-4.083222,55.821419],"type":"Point"}
}