{
  "type": "Feature",
  "properties": {
    "iso:country":"GB",
    "sg:address":"4 Medway Ct, Judd St",
    "sg:city":"Bloomsbury",
    "sg:classifiers":[
        {
            "category":"Recreation",
            "subcategory":"Gun Range",
            "type":"Entertainment"
        }
    ],
    "sg:phone":"+44 20 7388 8878",
    "sg:postcode":"WC1H 9QX",
    "sg:province":"Greater London",
    "sg:tags":[
        "operator",
        "tour"
    ],
    "wof:name":"Crane Associates",
    "wof:placetype":"venue"
},
  "geometry": {"coordinates":[-0.12454,51.526852],"type":"Point"}
}