{
  "type": "Feature",
  "properties": {
    "iso:country":"GB",
    "sg:address":"Bewsey Rd",
    "sg:city":"Warrington",
    "sg:classifiers":[
        {
            "category":"Retail",
            "subcategory":"Funeral Services",
            "type":"Services"
        }
    ],
    "sg:phone":"+44 1925 445555",
    "sg:postcode":"WA2 7LW",
    "sg:province":"Cheshire",
    "wof:name":"United Norwest Co-Operative Funeral Service",
    "wof:placetype":"venue"
},
  "geometry": {"coordinates":[-2.601449,53.394661],"type":"Point"}
}