{
  "type": "Feature",
  "properties": {
    "addr:full":"Westway Rd, Alexandra Docks Newport Newport NP20 2WD",
    "addr:postcode":"np20 2wd",
    "addr:street":"Westway Rd",
    "iso:country":"GB",
    "sg:address":"Westway Rd, Alexandra Docks",
    "sg:city":"Newport",
    "sg:classifiers":[
        {
            "category":"Building & Trades",
            "subcategory":"Construction",
            "type":"Services"
        }
    ],
    "sg:phone":"+44 1633 223023",
    "sg:postcode":"NP20 2WD",
    "sg:province":"Newport",
    "sg:tags":[
        "joinery"
    ],
    "wof:name":"National Roof Truss Company",
    "wof:placetype":"venue"
},
  "geometry": {"coordinates":[-2.997701,51.569363],"type":"Point"}
}