{
  "type": "Feature",
  "properties": {
    "iso:country":"GB",
    "sg:address":"Raebhat House, North Shawbost",
    "sg:city":"Isle Of Lewis",
    "sg:classifiers":[
        {
            "category":"Shopping",
            "subcategory":"Hobbies, Toys, & Games",
            "type":"Retail Goods"
        }
    ],
    "sg:phone":"+44 1851 710553",
    "sg:postcode":"HS2 9BD",
    "sg:province":"Eilean Siar",
    "sg:tags":[
        "toy"
    ],
    "wof:name":"Raebhat Originals",
    "wof:placetype":"venue"
},
  "geometry": {"coordinates":[-6.66865,58.330582],"type":"Point"}
}