{
  "type": "Feature",
  "properties": {
    "iso:country":"GB",
    "sg:address":"Garden Studios, 11-15 Betterton Street",
    "sg:city":"London",
    "sg:classifiers":[
        {
            "category":"Real Estate",
            "subcategory":"Real Estate Operator",
            "type":"Services"
        }
    ],
    "sg:phone":"+44 20 7379 0344",
    "sg:postcode":"WC2H 9BP",
    "sg:province":"Greater London",
    "sg:tags":[
        "letting",
        "agent"
    ],
    "wof:name":"Student Homes",
    "wof:placetype":"venue"
},
  "geometry": {"coordinates":[-0.12351,51.515079],"type":"Point"}
}