{
  "type": "Feature",
  "properties": {
    "addr:full":"31 Auckland Rd Upper Norwood Greater London SE19 2DR",
    "addr:housenumber":"31",
    "addr:postcode":"se19 2dr",
    "addr:street":"Auckland Rd",
    "iso:country":"GB",
    "sg:address":"31 Auckland Rd",
    "sg:city":"Upper Norwood",
    "sg:classifiers":[
        {
            "category":"Building & Trades",
            "subcategory":"Construction",
            "type":"Services"
        }
    ],
    "sg:phone":"+44 20 8771 6508",
    "sg:postcode":"SE19 2DR",
    "sg:province":"Greater London",
    "sg:tags":[
        "builder"
    ],
    "wof:name":"Swift Builders",
    "wof:placetype":"venue"
},
  "geometry": {"coordinates":[-0.0794809982,51.4065055847],"type":"Point"}
}