{
  "type": "Feature",
  "properties": {
    "addr:full":"3 Alcester Road Birmingham West Midlands B13 8AR",
    "addr:housenumber":"3",
    "addr:postcode":"b13 8ar",
    "addr:street":"Alcester Road",
    "iso:country":"GB",
    "sg:address":"3 Alcester Road",
    "sg:city":"Birmingham",
    "sg:classifiers":[
        {
            "category":"Shopping",
            "subcategory":"News",
            "type":"Retail Goods"
        }
    ],
    "sg:phone":"+44 121 449 2275",
    "sg:postcode":"B13 8AR",
    "sg:province":"West Midlands",
    "sg:tags":[
        "newsagent"
    ],
    "wof:name":"N S R News",
    "wof:placetype":"venue"
},
  "geometry": {"coordinates":[-1.887435,52.452881],"type":"Point"}
}