{
  "type": "Feature",
  "properties": {
    "addr:full":"Abbey Farm, Abbey Road, Bardney Lincoln Lincolnshire LN3 5XD",
    "addr:postcode":"ln3 5xd",
    "addr:street":"Abbey Road",
    "iso:country":"GB",
    "sg:address":"Abbey Farm, Abbey Road, Bardney",
    "sg:city":"Lincoln",
    "sg:classifiers":[
        {
            "category":"Farming",
            "subcategory":"Crops",
            "type":"Manufacturing & Wholesale Goods"
        },
        {
            "category":"Farming",
            "subcategory":"Farm",
            "type":"Manufacturing & Wholesale Goods"
        }
    ],
    "sg:phone":"+44 1526 398915",
    "sg:postcode":"LN3 5XD",
    "sg:province":"Lincolnshire",
    "sg:tags":[
        "mixed",
        "arable"
    ],
    "wof:name":"D C Armstrong",
    "wof:placetype":"venue"
},
  "geometry": {"coordinates":[-0.3236840069,53.2112960815],"type":"Point"}
}