{
  "type": "Feature",
  "properties": {
    "addr:full":"137 The Fairway Wembley Greater London HA0 3TQ",
    "addr:housenumber":"137",
    "addr:postcode":"ha0 3tq",
    "addr:street":"The Fairway",
    "iso:country":"GB",
    "sg:address":"137 The Fairway",
    "sg:city":"Wembley",
    "sg:classifiers":[
        {
            "category":"Building & Trades",
            "subcategory":"Construction",
            "type":"Services"
        }
    ],
    "sg:phone":"+44 20 8904 0182",
    "sg:postcode":"HA0 3TQ",
    "sg:province":"Greater London",
    "sg:tags":[
        "builder"
    ],
    "wof:name":"Mosley Contractors",
    "wof:placetype":"venue"
},
  "geometry": {"coordinates":[-0.313752,51.571259],"type":"Point"}
}