{
  "type": "Feature",
  "properties": {
    "addr:full":"34 Portland Walk Barrow-in-furness Cumbria LA14 1DB",
    "addr:housenumber":"34",
    "addr:postcode":"la14 1db",
    "addr:street":"Portland Walk",
    "iso:country":"GB",
    "sg:address":"34 Portland Walk",
    "sg:city":"Barrow-in-furness",
    "sg:classifiers":[
        {
            "category":"Shopping",
            "subcategory":"Shoes",
            "type":"Retail Goods"
        }
    ],
    "sg:phone":"+44 1229 433690",
    "sg:postcode":"LA14 1DB",
    "sg:province":"Cumbria",
    "sg:tags":[
        "shop",
        "retailer",
        "footwear"
    ],
    "wof:name":"Clarks Shoes Ltd",
    "wof:placetype":"venue"
},
  "geometry": {"coordinates":[-3.2154591084,54.1360054016],"type":"Point"}
}