{
  "type": "Feature",
  "properties": {
    "addr:full":"Manor Farm West Road, Pointon Sleaford Lincolnshire NG34 0NA",
    "addr:postcode":"ng34 0na",
    "addr:street":"Manor;West Road",
    "iso:country":"GB",
    "sg:address":"Manor Farm West Road, Pointon",
    "sg:city":"Sleaford",
    "sg:classifiers":[
        {
            "category":"Home & Garden",
            "subcategory":"Garden Supply",
            "type":"Retail Goods"
        },
        {
            "category":"Sports & Exercise",
            "subcategory":"Skate Park",
            "type":"Entertainment"
        }
    ],
    "sg:postcode":"NG34 0NA",
    "sg:province":"Lincolnshire",
    "sg:tags":[
        "bulb",
        "grower",
        "mushroom"
    ],
    "wof:name":"Charles M Richardson",
    "wof:placetype":"venue"
},
  "geometry": {"coordinates":[-0.341642,52.872604],"type":"Point"}
}