{
  "type": "Feature",
  "properties": {
    "addr:full":"Crewe Road, Haslington Crewe Cheshire CW1 5SL",
    "addr:postcode":"cw1 5sl",
    "addr:street":"Crewe Road",
    "iso:country":"GB",
    "sg:address":"Crewe Road, Haslington",
    "sg:city":"Crewe",
    "sg:classifiers":[
        {
            "category":"Education",
            "subcategory":"School",
            "type":"Public Place"
        },
        {
            "category":"Government",
            "subcategory":"Office",
            "type":"Public Place"
        }
    ],
    "sg:phone":"+44 1270 581327",
    "sg:postcode":"CW1 5SL",
    "sg:province":"Cheshire",
    "sg:tags":[
        "local",
        "authority"
    ],
    "wof:name":"Cheshire County Council",
    "wof:placetype":"venue"
},
  "geometry": {"coordinates":[-2.394339,53.097462],"type":"Point"}
}