{
  "type": "Feature",
  "properties": {
    "addr:full":"50 High Street Pinner Greater London HA5 5PW",
    "addr:housenumber":"50",
    "addr:postcode":"ha5 5pw",
    "addr:street":"High Street",
    "iso:country":"GB",
    "sg:address":"50 High Street",
    "sg:city":"Pinner",
    "sg:classifiers":[
        {
            "category":"Shopping",
            "subcategory":"Clothing, Apparel, & Fashions",
            "type":"Retail Goods"
        }
    ],
    "sg:phone":"+44 20 8866 9366",
    "sg:postcode":"HA5 5PW",
    "sg:province":"Greater London",
    "sg:tags":[
        "shop"
    ],
    "wof:name":"Laural",
    "wof:placetype":"venue"
},
  "geometry": {"coordinates":[-0.380068,51.594284],"type":"Point"}
}