{
  "type": "Feature",
  "properties": {
    "addr:full":"1 Wykeham Road, Merrow Guildford Surrey GU21 2SE",
    "addr:housenumber":"1",
    "addr:postcode":"gu21 2se",
    "addr:street":"Wykeham Road",
    "iso:country":"GB",
    "sg:address":"1 Wykeham Road, Merrow",
    "sg:city":"Guildford",
    "sg:classifiers":[
        {
            "category":"Professional",
            "subcategory":"Advertising",
            "type":"Services"
        }
    ],
    "sg:postcode":"GU21 2SE",
    "sg:province":"Surrey",
    "sg:tags":[
        "agency"
    ],
    "wof:name":"D B F Advertising Ltd.",
    "wof:placetype":"venue"
},
  "geometry": {"coordinates":[-0.5346999764,51.2447013855],"type":"Point"}
}