{
  "type": "Feature",
  "properties": {
    "iso:country":"GB",
    "sg:address":"10-14 Cardwell Rd",
    "sg:city":"Gourock",
    "sg:classifiers":[
        {
            "category":"Retail",
            "subcategory":"Auto Repair",
            "type":"Services"
        }
    ],
    "sg:phone":"+44 1475 633000",
    "sg:postcode":"PA19 1UH",
    "sg:province":"Inverclyde",
    "sg:tags":[
        "modification",
        "garage"
    ],
    "wof:name":"Clyde Gas Co",
    "wof:placetype":"venue"
},
  "geometry": {"coordinates":[-4.807656765,55.9558296204],"type":"Point"}
}