{
  "type": "Feature",
  "properties": {
    "addr:full":"4 Deanwood Close Gillingham Kent ME8 9ET",
    "addr:housenumber":"4",
    "addr:postcode":"me8 9et",
    "addr:street":"Deanwood Close",
    "iso:country":"GB",
    "sg:address":"4 Deanwood Close",
    "sg:city":"Gillingham",
    "sg:classifiers":[
        {
            "category":"Retail",
            "subcategory":"Driving School",
            "type":"Services"
        }
    ],
    "sg:phone":"+44 1634 364828",
    "sg:postcode":"ME8 9ET",
    "sg:province":"Kent",
    "wof:name":"Prima Driving Tuition",
    "wof:placetype":"venue"
},
  "geometry": {"coordinates":[0.59848,51.346519],"type":"Point"}
}