{
  "type": "Feature",
  "properties": {
    "addr:full":"North Harringay Schools, Falkland Centre, Falkland Rd Hornsey Greater London N8 0NU",
    "addr:postcode":"n8 0nu",
    "addr:street":"North;Falkland;Falkland Rd",
    "iso:country":"GB",
    "sg:address":"North Harringay Schools, Falkland Centre, Falkland Rd",
    "sg:city":"Hornsey",
    "sg:classifiers":[
        {
            "category":"Organizations",
            "subcategory":"Non-profit Organization",
            "type":"Services"
        }
    ],
    "sg:phone":"+44 20 8348 1100",
    "sg:postcode":"N8 0NU",
    "sg:province":"Greater London",
    "sg:tags":[
        "organisation",
        "voluntary",
        "charity"
    ],
    "wof:name":"Volunteer Reading Help",
    "wof:placetype":"venue"
},
  "geometry": {"coordinates":[-0.1061699986,51.5856704712],"type":"Point"}
}