{
  "type": "Feature",
  "properties": {
    "addr:full":"20 Lake Gro Morecambe Lancashire LA4 4LH",
    "addr:housenumber":"20",
    "addr:postcode":"la4 4lh",
    "addr:street":"Lake Gro Morecambe",
    "iso:country":"GB",
    "sg:address":"20 Lake Gro",
    "sg:city":"Morecambe",
    "sg:classifiers":[
        {
            "category":"Retail",
            "subcategory":"Storage",
            "type":"Services"
        }
    ],
    "sg:phone":"+44 1524 832069",
    "sg:postcode":"LA4 4LH",
    "sg:province":"Lancashire",
    "sg:tags":[
        "household",
        "removal"
    ],
    "wof:name":"A & P Removals",
    "wof:placetype":"venue"
},
  "geometry": {"coordinates":[-2.872428894,54.065372467],"type":"Point"}
}