{
  "type": "Feature",
  "properties": {
    "addr:full":"11 Albion St Derby Derbyshire DE1 2PR",
    "addr:housenumber":"11",
    "addr:postcode":"de1 2pr",
    "addr:street":"Albion St",
    "iso:country":"GB",
    "sg:address":"11 Albion St",
    "sg:city":"Derby",
    "sg:classifiers":[
        {
            "category":"Shopping",
            "subcategory":"Hobbies, Toys, & Games",
            "type":"Retail Goods"
        }
    ],
    "sg:phone":"+44 1332 380421",
    "sg:postcode":"DE1 2PR",
    "sg:province":"Derbyshire",
    "sg:tags":[
        "shop",
        "toy"
    ],
    "wof:name":"Early Learning Centre",
    "wof:placetype":"venue"
},
  "geometry": {"coordinates":[-1.473976016,52.9206962585],"type":"Point"}
}