{
  "type": "Feature",
  "properties": {
    "iso:country":"GB",
    "sg:address":"71 Dartford Rd",
    "sg:city":"Sevenoaks",
    "sg:classifiers":[
        {
            "category":"Health Services",
            "subcategory":"Dentist",
            "type":"Services"
        }
    ],
    "sg:phone":"+44 1732 452082",
    "sg:postcode":"TN13 3TE",
    "sg:province":"Kent",
    "sg:tags":[
        "technician",
        "dental"
    ],
    "wof:name":"A Parsons",
    "wof:placetype":"venue"
},
  "geometry": {"coordinates":[0.193862,51.278831],"type":"Point"}
}