{
  "type": "Feature",
  "properties": {
    "addr:full":"1st Floor Elgin House, 106 St Mary's Street Cardiff Cardiff CF10 1DX",
    "addr:housenumber":"106",
    "addr:postcode":"cf10 1dx",
    "addr:street":"St Mary'S Street",
    "iso:country":"GB",
    "sg:address":"1st Floor Elgin House, 106 St Mary's Street",
    "sg:city":"Cardiff",
    "sg:classifiers":[
        {
            "category":"Manufacturing",
            "subcategory":"Tools & Machinery",
            "type":"Manufacturing & Wholesale Goods"
        }
    ],
    "sg:phone":"+44 29 2039 6946",
    "sg:postcode":"CF10 1DX",
    "sg:province":"Cardiff",
    "sg:tags":[
        "society",
        "friendly"
    ],
    "wof:name":"Abbey Life Assurance Co. Ltd.",
    "wof:placetype":"venue"
},
  "geometry": {"coordinates":[-3.177864,51.478554],"type":"Point"}
}