{
  "type": "Feature",
  "properties": {
    "addr:full":"Market Place, Uppingham Oakham Leicestershire LE15 9QH",
    "addr:postcode":"le15 9qh",
    "addr:street":"Market Place",
    "iso:country":"GB",
    "sg:address":"Market Place, Uppingham",
    "sg:city":"Oakham",
    "sg:classifiers":[
        {
            "category":"Home & Garden",
            "subcategory":"Hardware",
            "type":"Retail Goods"
        }
    ],
    "sg:phone":"+44 1572 823326",
    "sg:postcode":"LE15 9QH",
    "sg:province":"Leicestershire",
    "sg:tags":[
        "merchant",
        "ironmonger"
    ],
    "wof:name":"D Norton & Sons",
    "wof:placetype":"venue"
},
  "geometry": {"coordinates":[-0.7226520181,52.5878257751],"type":"Point"}
}