{
  "type": "Feature",
  "properties": {
    "iso:country":"GB",
    "sg:address":"Station Buildings, Queensway",
    "sg:city":"Newport",
    "sg:classifiers":[
        {
            "category":"Taxi",
            "type":"Transportation"
        },
        {
            "category":"Military Area",
            "subcategory":"Air Force Base",
            "type":"Public Place"
        }
    ],
    "sg:phone":"+44 1633 216216",
    "sg:postcode":"NP20 4AX",
    "sg:province":"Newport",
    "sg:tags":[
        "mini",
        "hire",
        "cab",
        "private",
        "vehicle"
    ],
    "wof:name":"Dragon Taxis",
    "wof:placetype":"venue"
},
  "geometry": {"coordinates":[-2.9979,51.589882],"type":"Point"}
}