{
  "type": "Feature",
  "properties": {
    "iso:country":"GB",
    "sg:address":"7-13 Richmond Hill",
    "sg:city":"Blackburn",
    "sg:classifiers":[
        {
            "category":"Shopping",
            "subcategory":"Stationery & Office Supplies",
            "type":"Retail Goods"
        },
        {
            "category":"Shopping",
            "subcategory":"Clothing, Apparel, & Fashions",
            "type":"Retail Goods"
        }
    ],
    "sg:phone":"+44 1254 51567",
    "sg:postcode":"BB1 7LB",
    "sg:province":"Lancashire",
    "sg:tags":[
        "clothing",
        "fabric"
    ],
    "wof:name":"J Stott & Sons Ltd.",
    "wof:placetype":"venue"
},
  "geometry": {"coordinates":[-2.483722,53.751316],"type":"Point"}
}