{
  "type": "Feature",
  "properties": {
    "addr:full":"9b Caunce Street Blackpool Lancashire FY1 3DN",
    "addr:housenumber":"9b",
    "addr:postcode":"fy1 3dn",
    "addr:street":"Caunce Street",
    "iso:country":"GB",
    "sg:address":"9b Caunce Street",
    "sg:city":"Blackpool",
    "sg:classifiers":[
        {
            "category":"Shopping",
            "subcategory":"Music",
            "type":"Retail Goods"
        }
    ],
    "sg:phone":"+44 1253 624718",
    "sg:postcode":"FY1 3DN",
    "sg:province":"Lancashire",
    "sg:tags":[
        "dvd",
        "record",
        "tape",
        "vinyl",
        "cd"
    ],
    "wof:name":"Records & Relics",
    "wof:placetype":"venue"
},
  "geometry": {"coordinates":[-3.0470759869,53.8184585571],"type":"Point"}
}