{
  "type": "Feature",
  "properties": {
    "addr:full":"428 West Wycombe Road High Wycombe Buckinghamshire HP12 4AH",
    "addr:housenumber":"428",
    "addr:postcode":"hp12 4ah",
    "addr:street":"West Wycombe Road",
    "iso:country":"GB",
    "sg:address":"428 West Wycombe Road",
    "sg:city":"High Wycombe",
    "sg:classifiers":[
        {
            "category":"Building & Trades",
            "subcategory":"Construction",
            "type":"Services"
        },
        {
            "category":"Home & Garden",
            "subcategory":"Carpets & Floor Coverings",
            "type":"Retail Goods"
        }
    ],
    "sg:phone":"+44 1494 436460",
    "sg:postcode":"HP12 4AH",
    "sg:province":"Buckinghamshire",
    "sg:tags":[
        "carpets",
        "tiling",
        "rug",
        "matting",
        "contractor"
    ],
    "wof:name":"Flair Flooring",
    "wof:placetype":"venue"
},
  "geometry": {"coordinates":[-0.7910619974,51.6431388855],"type":"Point"}
}