{
  "type": "Feature",
  "properties": {
    "addr:full":"139 Henhurst Hill Burton-on-trent Derbyshire DE13 9SX",
    "addr:housenumber":"139",
    "addr:postcode":"de13 9sx",
    "addr:street":"Henhurst Hill",
    "iso:country":"GB",
    "sg:address":"139 Henhurst Hill",
    "sg:city":"Burton-on-trent",
    "sg:classifiers":[
        {
            "category":"Building & Trades",
            "subcategory":"Landscaping Services",
            "type":"Services"
        }
    ],
    "sg:phone":"+44 1283 545601",
    "sg:postcode":"DE13 9SX",
    "sg:province":"Derbyshire",
    "sg:tags":[
        "forestry",
        "tree"
    ],
    "wof:name":"Garden Services & Tree Surgery",
    "wof:placetype":"venue"
},
  "geometry": {"coordinates":[-1.688916,52.812252],"type":"Point"}
}