{
  "type": "Feature",
  "properties": {
    "iso:country":"GB",
    "sg:address":"19 Broadfield Avenue",
    "sg:city":"Bristol",
    "sg:classifiers":[
        {
            "category":"Building & Trades",
            "subcategory":"Construction",
            "type":"Services"
        }
    ],
    "sg:postcode":"BS15 1HX",
    "sg:province":"City of Bristol",
    "sg:tags":[
        "builder"
    ],
    "wof:name":"N A Lee",
    "wof:placetype":"venue"
},
  "geometry": {"coordinates":[-2.5167360306,51.4637527466],"type":"Point"}
}