{
  "type": "Feature",
  "properties": {
    "iso:country":"GB",
    "sg:address":"Mason Street",
    "sg:city":"Stoke-on-trent",
    "sg:classifiers":[
        {
            "category":"Manufacturing",
            "subcategory":"Pottery",
            "type":"Manufacturing & Wholesale Goods"
        }
    ],
    "sg:postcode":"ST4 3LS",
    "sg:province":"Staffordshire",
    "wof:name":"Aston China",
    "wof:placetype":"venue"
},
  "geometry": {"coordinates":[-2.154107,52.996494],"type":"Point"}
}