{
  "type": "Feature",
  "properties": {
    "iso:country":"GB",
    "sg:address":"201 Back La",
    "sg:city":"Bolton",
    "sg:classifiers":[
        {
            "category":"Retail",
            "subcategory":"Auto Repair",
            "type":"Services"
        }
    ],
    "sg:postcode":"BL1 2LD",
    "sg:province":"Lancashire",
    "sg:tags":[
        "modification",
        "garage"
    ],
    "wof:name":"Bennett,P,",
    "wof:placetype":"venue"
},
  "geometry": {"coordinates":[-2.4365489483,53.5823402405],"type":"Point"}
}