{
  "type": "Feature",
  "properties": {
    "addr:full":"Unit 53, Weaver Industrial Estate Liverpool Merseyside L19 8JA",
    "addr:housenumber":"unit 53",
    "addr:postcode":"l19 8ja",
    "addr:street":"Weaver Industrial Estate",
    "iso:country":"GB",
    "sg:address":"Unit 53, Weaver Industrial Estate",
    "sg:city":"Liverpool",
    "sg:classifiers":[
        {
            "category":"Shopping",
            "subcategory":"Stationery & Office Supplies",
            "type":"Retail Goods"
        }
    ],
    "sg:phone":"+44 151 494 1520",
    "sg:postcode":"L19 8JA",
    "sg:province":"Merseyside",
    "wof:name":"S & K Direct Ltd.",
    "wof:placetype":"venue"
},
  "geometry": {"coordinates":[-2.897539,53.344769],"type":"Point"}
}