{
  "type": "Feature",
  "properties": {
    "addr:full":", Llangoedmor Cardigan Ceredigion SA43 2LY",
    "addr:housenumber":"llangoedmor",
    "addr:postcode":"sa43 2ly",
    "iso:country":"GB",
    "sg:address":", Llangoedmor",
    "sg:city":"Cardigan",
    "sg:classifiers":[
        {
            "category":"Bars & Pubs",
            "type":"Food & Drink"
        }
    ],
    "sg:phone":"+44 1239 682533",
    "sg:postcode":"SA43 2LY",
    "sg:province":"Ceredigion",
    "sg:tags":[
        "pubs",
        "inn"
    ],
    "wof:name":"Penllwyndu Inn",
    "wof:placetype":"venue"
},
  "geometry": {"coordinates":[-4.624104023,52.0820083618],"type":"Point"}
}