{
  "type": "Feature",
  "properties": {
    "iso:country":"GB",
    "sg:address":"Alvanley Practice, 1 Auburn Av",
    "sg:city":"Stockport",
    "sg:classifiers":[
        {
            "category":"Health Services",
            "subcategory":"Doctor",
            "type":"Services"
        }
    ],
    "sg:phone":"+44 161 430 2727",
    "sg:postcode":"SK6 2AH",
    "sg:province":"Cheshire",
    "sg:tags":[
        "practitioners"
    ],
    "wof:name":"Ghosh, B N",
    "wof:placetype":"venue"
},
  "geometry": {"coordinates":[-2.11405,53.422909],"type":"Point"}
}