{
  "type": "Feature",
  "properties": {
    "addr:full":"11 The Spinney, Parklands Business Park, Forest Rd, Denm Portsmouth Hampshire PO7 6AR",
    "addr:housenumber":"11",
    "addr:postcode":"hampshire po7 6ar",
    "addr:street":"The Spinney;Business Park Forest Rd",
    "iso:country":"GB",
    "sg:address":"11 The Spinney, Parklands Business Park, Forest Rd, Denm",
    "sg:city":"Portsmouth",
    "sg:classifiers":[
        {
            "category":"Banks & Credit Unions",
            "subcategory":"Financial Services",
            "type":"Services"
        }
    ],
    "sg:postcode":"PO7 6AR",
    "sg:province":"Hampshire",
    "sg:tags":[
        "consultant"
    ],
    "wof:name":"Business Finance Ltd",
    "wof:placetype":"venue"
},
  "geometry": {"coordinates":[-1.0689300299,50.8955001831],"type":"Point"}
}