{
  "type": "Feature",
  "properties": {
    "addr:full":"398 Topsham Road Exeter Devon EX2 6HE",
    "addr:housenumber":"398",
    "addr:postcode":"ex2 6he",
    "addr:street":"Topsham Road",
    "iso:country":"GB",
    "sg:address":"398 Topsham Road",
    "sg:city":"Exeter",
    "sg:classifiers":[
        {
            "category":"Restaurant",
            "type":"Food & Drink"
        }
    ],
    "sg:phone":"+44 1392 875441",
    "sg:postcode":"EX2 6HE",
    "sg:province":"Devon",
    "wof:name":"Countess Wear Beefeater",
    "wof:placetype":"venue"
},
  "geometry": {"coordinates":[-3.5055251122,50.7070045471],"type":"Point"}
}