{
  "type": "Feature",
  "properties": {
    "iso:country":"GB",
    "sg:address":"The Cross",
    "sg:city":"Dalbeattie",
    "sg:classifiers":[
        {
            "category":"Farming",
            "subcategory":"Fish & Marine Products",
            "type":"Manufacturing & Wholesale Goods"
        },
        {
            "category":"Food & Beverages",
            "subcategory":"Meat & Fish",
            "type":"Retail Goods"
        }
    ],
    "sg:phone":"+44 1556 610384",
    "sg:postcode":"DG5 4HD",
    "sg:province":"Dumfries and Galloway",
    "sg:tags":[
        "fishmonger",
        "butcher"
    ],
    "wof:name":"T H Carson Butchers",
    "wof:placetype":"venue"
},
  "geometry": {"coordinates":[-3.830293,54.936966],"type":"Point"}
}