{
  "type": "Feature",
  "properties": {
    "addr:full":"Unit 6, Station Yard Haddington East Lothian EH41 3PP",
    "addr:housenumber":"unit 6",
    "addr:postcode":"eh41 3pp",
    "addr:street":"Station Yard",
    "iso:country":"GB",
    "sg:address":"Unit 6, Station Yard",
    "sg:city":"Haddington",
    "sg:classifiers":[
        {
            "category":"Home & Garden",
            "subcategory":"Household Appliances",
            "type":"Retail Goods"
        }
    ],
    "sg:postcode":"EH41 3PP",
    "sg:province":"East Lothian",
    "sg:tags":[
        "electrical"
    ],
    "wof:name":"C V S",
    "wof:placetype":"venue"
},
  "geometry": {"coordinates":[-2.788459,55.955833],"type":"Point"}
}