{
  "type": "Feature",
  "properties": {
    "addr:full":"117 Leman St Whitechapel Greater London E1 8EY",
    "addr:housenumber":"117",
    "addr:postcode":"e1 8ey",
    "addr:street":"Leman St",
    "iso:country":"GB",
    "sg:address":"117 Leman St",
    "sg:city":"Whitechapel",
    "sg:classifiers":[
        {
            "category":"Travel",
            "subcategory":"Travel Agent",
            "type":"Entertainment"
        }
    ],
    "sg:phone":"+44 20 7480 6767",
    "sg:postcode":"E1 8EY",
    "sg:province":"Greater London",
    "wof:name":"Utopia Travel",
    "wof:placetype":"venue"
},
  "geometry": {"coordinates":[-0.068894,51.511913],"type":"Point"}
}