{
  "type": "Feature",
  "properties": {
    "addr:full":"56 Lilyville Road, Fulham London Greater London SW6 5DW",
    "addr:housenumber":"56",
    "addr:postcode":"sw6 5dw",
    "addr:street":"Lilyville Road",
    "iso:country":"GB",
    "sg:address":"56 Lilyville Road, Fulham",
    "sg:city":"London",
    "sg:classifiers":[
        {
            "category":"Professional",
            "subcategory":"Management & Consulting",
            "type":"Services"
        }
    ],
    "sg:phone":"+44 20 7736 9232",
    "sg:postcode":"SW6 5DW",
    "sg:province":"Greater London",
    "sg:tags":[
        "consultant",
        "business"
    ],
    "wof:name":"M L K Consultants Ltd.",
    "wof:placetype":"venue"
},
  "geometry": {"coordinates":[-0.2057749927,51.477722168],"type":"Point"}
}