{
  "type": "Feature",
  "properties": {
    "addr:full":"Greenwood, Stoppers Hill, Brinkworth Chippenham Wiltshire SN15 5AW",
    "addr:postcode":"sn15 5aw",
    "iso:country":"GB",
    "sg:address":"Greenwood, Stoppers Hill, Brinkworth",
    "sg:city":"Chippenham",
    "sg:classifiers":[
        {
            "category":"Professional",
            "subcategory":"Engineering",
            "type":"Services"
        }
    ],
    "sg:phone":"+44 1666 510300",
    "sg:postcode":"SN15 5AW",
    "sg:province":"Wiltshire",
    "sg:tags":[
        "contractor",
        "electrical",
        "engineer"
    ],
    "wof:name":"R A Fields",
    "wof:placetype":"venue"
},
  "geometry": {"coordinates":[-1.9741990566,51.5609664917],"type":"Point"}
}