{
  "type": "Feature",
  "properties": {
    "iso:country":"GB",
    "sg:address":"Old Anglers, Unit 1 Heritage Court, Nottingham Road",
    "sg:city":"Derby",
    "sg:classifiers":[
        {
            "category":"Education",
            "subcategory":"Music School",
            "type":"Public Place"
        }
    ],
    "sg:phone":"+44 70 0066 6123",
    "sg:postcode":"DE21 7NP",
    "sg:province":"Derbyshire",
    "sg:tags":[
        "conservatory"
    ],
    "wof:name":"G L K Manufacturers of U P V C Windows",
    "wof:placetype":"venue"
},
  "geometry": {"coordinates":[-1.4028539658,52.910774231],"type":"Point"}
}