{
  "type": "Feature",
  "properties": {
    "iso:country":"GB",
    "sg:address":"11 High St",
    "sg:city":"Saltburn By The Sea",
    "sg:classifiers":[
        {
            "category":"Personal",
            "subcategory":"Beauty Salon",
            "type":"Services"
        }
    ],
    "sg:phone":"+44 1287 650262",
    "sg:postcode":"TS12 2EF",
    "sg:province":"North Yorkshire",
    "sg:tags":[
        "lady",
        "hairdresser"
    ],
    "wof:name":"Karadon",
    "wof:placetype":"venue"
},
  "geometry": {"coordinates":[-0.987125,54.560532],"type":"Point"}
}