{
  "type": "Feature",
  "properties": {
    "iso:country":"GB",
    "sg:address":"Red Lion, Babcary",
    "sg:city":"Somerton",
    "sg:classifiers":[
        {
            "category":"Bars & Pubs",
            "type":"Food & Drink"
        }
    ],
    "sg:phone":"+44 1458 223230",
    "sg:postcode":"TA11 7ED",
    "sg:province":"Somerset",
    "sg:tags":[
        "pubs",
        "inn"
    ],
    "wof:name":"The Red Lion Inn",
    "wof:placetype":"venue"
},
  "geometry": {"coordinates":[-2.6252889633,51.0559310913],"type":"Point"}
}