{
  "type": "Feature",
  "properties": {
    "iso:country":"GB",
    "sg:address":"1 Sopwith Crescent, Hurricane Way",
    "sg:city":"Wickford",
    "sg:classifiers":[
        {
            "category":"Professional",
            "subcategory":"Accounting & Tax Preparation",
            "type":"Services"
        }
    ],
    "sg:phone":"+44 1268 561800",
    "sg:postcode":"SS11 8YU",
    "sg:province":"Essex",
    "sg:tags":[
        "accountant"
    ],
    "wof:name":"Pittock Hamilton",
    "wof:placetype":"venue"
},
  "geometry": {"coordinates":[0.548659,51.60104],"type":"Point"}
}