{
  "type": "Feature",
  "properties": {
    "addr:full":"Burlington House, Burlington Arcade Barnsley South Yorkshire S70 1SZ",
    "addr:postcode":"s70 1sz",
    "addr:street":"Burlington Arcade;Yorkshire",
    "iso:country":"GB",
    "sg:address":"Burlington House, Burlington Arcade",
    "sg:city":"Barnsley",
    "sg:classifiers":[
        {
            "category":"Banks & Credit Unions",
            "subcategory":"Financial Services",
            "type":"Services"
        }
    ],
    "sg:phone":"+44 1226 779575",
    "sg:postcode":"S70 1SZ",
    "sg:province":"South Yorkshire",
    "sg:tags":[
        "cashing",
        "cheque"
    ],
    "wof:name":"Barnsley Cheque Exchange",
    "wof:placetype":"venue"
},
  "geometry": {"coordinates":[-1.4799389839,53.5528106689],"type":"Point"}
}