{
  "type": "Feature",
  "properties": {
    "addr:full":"Station Road Cramlington Northumberland NE23 2DL",
    "addr:postcode":"ne23 2dl",
    "addr:street":"Station Road;Northumberland",
    "iso:country":"GB",
    "sg:address":"Station Road",
    "sg:city":"Cramlington",
    "sg:classifiers":[
        {
            "category":"Military Area",
            "subcategory":"Air Force Base",
            "type":"Public Place"
        }
    ],
    "sg:phone":"+44 1670 712244",
    "sg:postcode":"NE23 2DL",
    "sg:province":"Northumberland",
    "sg:tags":[
        "taxi",
        "hire",
        "private"
    ],
    "wof:name":"Target Taxis",
    "wof:placetype":"venue"
},
  "geometry": {"coordinates":[-1.5956840515,55.0874862671],"type":"Point"}
}