{
  "type": "Feature",
  "properties": {
    "addr:full":"255 Tamworth Road, Long Eaton Nottingham Derbyshire NG10 1AS",
    "addr:housenumber":"255",
    "addr:postcode":"ng10 1as",
    "addr:street":"Tamworth Road",
    "iso:country":"GB",
    "sg:address":"255 Tamworth Road, Long Eaton",
    "sg:city":"Nottingham",
    "sg:classifiers":[
        {
            "category":"Health Services",
            "subcategory":"Nursing And Care Facility",
            "type":"Services"
        },
        {
            "category":"Social Services",
            "subcategory":"Retirement Home",
            "type":"Services"
        }
    ],
    "sg:phone":"+44 115 946 1506",
    "sg:postcode":"NG10 1AS",
    "sg:province":"Derbyshire",
    "sg:tags":[
        "residential"
    ],
    "wof:name":"Glendale House Residential Home",
    "wof:placetype":"venue"
},
  "geometry": {"coordinates":[-1.2788829803,52.8901786804],"type":"Point"}
}