{
  "type": "Feature",
  "properties": {
    "iso:country":"GB",
    "sg:address":"Bagshaw Hill",
    "sg:city":"Bakewell",
    "sg:classifiers":[
        {
            "category":"Real Estate",
            "subcategory":"Real Estate Services",
            "type":"Services"
        },
        {
            "category":"Real Estate",
            "subcategory":"Developer",
            "type":"Services"
        }
    ],
    "sg:phone":"+44 1629 813712",
    "sg:postcode":"DE45 1DL",
    "sg:province":"Derbyshire",
    "sg:tags":[
        "property",
        "management"
    ],
    "wof:name":"Cressbrook Investments Ltd.",
    "wof:placetype":"venue"
},
  "geometry": {"coordinates":[-1.677324,53.21423],"type":"Point"}
}