{
  "type": "Feature",
  "properties": {
    "iso:country":"GB",
    "sg:address":"16 Heathbrook, Llanishen",
    "sg:city":"Cardiff",
    "sg:classifiers":[
        {
            "category":"Taxi",
            "type":"Transportation"
        }
    ],
    "sg:postcode":"CF14 5FA",
    "sg:province":"Cardiff",
    "sg:tags":[
        "mini",
        "cab"
    ],
    "wof:name":"G Evans Contracts Ltd.",
    "wof:placetype":"venue"
},
  "geometry": {"coordinates":[-3.182554,51.521366],"type":"Point"}
}