{
  "type": "Feature",
  "properties": {
    "iso:country":"GB",
    "sg:address":"61 Cannon Street",
    "sg:city":"London",
    "sg:classifiers":[
        {
            "category":"Cafe",
            "type":"Food & Drink"
        }
    ],
    "sg:phone":"+44 20 7248 1132",
    "sg:postcode":"EC4N 5AA",
    "sg:province":"Greater London",
    "sg:tags":[
        "tea",
        "room"
    ],
    "wof:name":"Conti's Snack Bar",
    "wof:placetype":"venue"
},
  "geometry": {"coordinates":[-0.0934,51.512409],"type":"Point"}
}