{
  "type": "Feature",
  "properties": {
    "addr:full":"96a Burford Street Hoddesdon Essex EN11 8JL",
    "addr:housenumber":"96a",
    "addr:postcode":"en11 8jl",
    "addr:street":"Burford Street",
    "iso:country":"GB",
    "sg:address":"96a Burford Street",
    "sg:city":"Hoddesdon",
    "sg:classifiers":[
        {
            "category":"Autos & Motor Vehicles",
            "subcategory":"Automobile Sales",
            "type":"Retail Goods"
        }
    ],
    "sg:postcode":"EN11 8JL",
    "sg:province":"Essex",
    "sg:tags":[
        "car"
    ],
    "wof:name":"Country Cars",
    "wof:placetype":"venue"
},
  "geometry": {"coordinates":[-0.0086329998,51.7650489807],"type":"Point"}
}