{
  "type": "Feature",
  "properties": {
    "addr:full":"Unit 1 North View Shopping Mews, 86 Camb, St Neots Huntingdon Bedfordshire PE19 1PJ",
    "addr:housenumber":"unit 1;86",
    "addr:postcode":"pe19 1pj",
    "addr:street":"North;Shopping;Camb",
    "iso:country":"GB",
    "sg:address":"Unit 1 North View Shopping Mews, 86 Camb, St Neots",
    "sg:city":"Huntingdon",
    "sg:classifiers":[
        {
            "category":"Communications",
            "type":"Services"
        }
    ],
    "sg:postcode":"PE19 1PJ",
    "sg:province":"Bedfordshire",
    "sg:tags":[
        "tv",
        "video",
        "radio"
    ],
    "wof:name":"James,Andrew",
    "wof:placetype":"venue"
},
  "geometry": {"coordinates":[-0.25832,52.228168],"type":"Point"}
}