{
  "type": "Feature",
  "properties": {
    "addr:full":"17 Jubilee Close, Isleham Ely Cambridgeshire CB7 5RW",
    "addr:housenumber":"17",
    "addr:postcode":"cb7 5rw",
    "addr:street":"Jubilee Close",
    "iso:country":"GB",
    "sg:address":"17 Jubilee Close, Isleham",
    "sg:city":"Ely",
    "sg:classifiers":[
        {
            "category":"Retail",
            "subcategory":"Storage",
            "type":"Services"
        },
        {
            "category":"Communications",
            "type":"Services"
        }
    ],
    "sg:phone":"+44 1638 780518",
    "sg:postcode":"CB7 5RW",
    "sg:province":"Cambridgeshire",
    "sg:tags":[
        "tv",
        "recording",
        "video",
        "radio",
        "equipment"
    ],
    "wof:name":"Stack Electronics",
    "wof:placetype":"venue"
},
  "geometry": {"coordinates":[0.413484,52.342022],"type":"Point"}
}