{
  "type": "Feature",
  "properties": {
    "addr:full":"Atom House, Bartelotte Rd, Horsham Horsham West Sussex RH12 1JD",
    "addr:postcode":"rh12 1jd",
    "addr:street":"Bartelotte Rd",
    "iso:country":"GB",
    "sg:address":"Atom House, Bartelotte Rd, Horsham",
    "sg:city":"Horsham",
    "sg:classifiers":[
        {
            "category":"Banks & Credit Unions",
            "subcategory":"Bank",
            "type":"Services"
        }
    ],
    "sg:phone":"+44 1892 654908",
    "sg:postcode":"RH12 1JD",
    "sg:province":"West Sussex",
    "sg:tags":[
        "broker",
        "mortgage"
    ],
    "wof:name":"Atlas Mortgages",
    "wof:placetype":"venue"
},
  "geometry": {"coordinates":[-0.32436,51.061974],"type":"Point"}
}