{
  "type": "Feature",
  "properties": {
    "iso:country":"GB",
    "sg:address":"Cross Houses",
    "sg:city":"Shrewsbury",
    "sg:classifiers":[
        {
            "category":"Bars & Pubs",
            "type":"Food & Drink"
        }
    ],
    "sg:postcode":"SY5 6JJ",
    "sg:province":"Shropshire",
    "sg:tags":[
        "pubs",
        "inn"
    ],
    "wof:name":"Fox Inn (The)",
    "wof:placetype":"venue"
},
  "geometry": {"coordinates":[-2.6826300621,52.6628913879],"type":"Point"}
}