{
  "type": "Feature",
  "properties": {
    "iso:country":"GB",
    "sg:address":"Fleet Walk",
    "sg:city":"Torquay",
    "sg:classifiers":[
        {
            "category":"Fast Food",
            "type":"Food & Drink"
        }
    ],
    "sg:postcode":"TQ1 1BX",
    "sg:province":"Devon",
    "sg:tags":[
        "away",
        "take"
    ],
    "wof:name":"Philomenas Coffee Plus",
    "wof:placetype":"venue"
},
  "geometry": {"coordinates":[-3.526266098,50.4630393982],"type":"Point"}
}