{
  "type": "Feature",
  "properties": {
    "iso:country":"GB",
    "sg:address":"7 Crown La",
    "sg:city":"Ely",
    "sg:classifiers":[
        {
            "category":"Home & Garden",
            "subcategory":"Furniture",
            "type":"Retail Goods"
        }
    ],
    "sg:postcode":"CB6 1PP",
    "sg:province":"Cambridgeshire",
    "wof:name":"Dovetails Quality Furniture",
    "wof:placetype":"venue"
},
  "geometry": {"coordinates":[0.3045470119,52.4572219849],"type":"Point"}
}