{
  "type": "Feature",
  "properties": {
    "addr:full":"18 Anderson Street Airdrie North Lanarkshire ML6 0AA",
    "addr:housenumber":"18",
    "addr:postcode":"ml6 0aa",
    "addr:street":"Anderson Street",
    "iso:country":"GB",
    "sg:address":"18 Anderson Street",
    "sg:city":"Airdrie",
    "sg:classifiers":[
        {
            "category":"Professional",
            "subcategory":"Lawyer & Legal Services",
            "type":"Services"
        }
    ],
    "sg:postcode":"ML6 0AA",
    "sg:province":"North Lanarkshire",
    "sg:tags":[
        "solicitor"
    ],
    "wof:name":"Hamilton Ross",
    "wof:placetype":"venue"
},
  "geometry": {"coordinates":[-3.9821090698,55.8670883179],"type":"Point"}
}