{
  "type": "Feature",
  "properties": {
    "addr:full":"50 Holyrood Street Chard Devon TA20 2AJ",
    "addr:housenumber":"50",
    "addr:postcode":"ta20 2aj",
    "addr:street":"Holyrood Street",
    "iso:country":"GB",
    "sg:address":"50 Holyrood Street",
    "sg:city":"Chard",
    "sg:classifiers":[
        {
            "category":"Shopping",
            "subcategory":"Pets & Pet Supplies",
            "type":"Retail Goods"
        }
    ],
    "sg:phone":"+44 1460 68388",
    "sg:postcode":"TA20 2AJ",
    "sg:province":"Devon",
    "sg:tags":[
        "shop"
    ],
    "wof:name":"ANIMAL FAYRE",
    "wof:placetype":"venue"
},
  "geometry": {"coordinates":[-2.9652240276,50.8709487915],"type":"Point"}
}