{
  "type": "Feature",
  "properties": {
    "iso:country":"GB",
    "sg:address":"29 Montpellier Parade",
    "sg:city":"Harrogate",
    "sg:classifiers":[
        {
            "category":"Shopping",
            "subcategory":"Antiques",
            "type":"Retail Goods"
        }
    ],
    "sg:phone":"+44 1423 507810",
    "sg:postcode":"HG1 2TG",
    "sg:province":"North Yorkshire",
    "wof:name":"John Weatherell Antiques",
    "wof:placetype":"venue"
},
  "geometry": {"coordinates":[-1.54494,53.993324],"type":"Point"}
}