{
  "type": "Feature",
  "properties": {
    "iso:country":"GB",
    "sg:address":"3 Edgeware Road",
    "sg:city":"Huddersfield",
    "sg:classifiers":[
        {
            "category":"Food & Beverages",
            "subcategory":"Meat & Fish",
            "type":"Retail Goods"
        }
    ],
    "sg:postcode":"HD5 9US",
    "sg:province":"West Yorkshire",
    "sg:tags":[
        "butcher"
    ],
    "wof:name":"Prime Cut",
    "wof:placetype":"venue"
},
  "geometry": {"coordinates":[-1.741004,53.648624],"type":"Point"}
}