{
  "type": "Feature",
  "properties": {
    "addr:full":"Moor Lodge, Oldfield Keighley North Yorkshire BD22 0JL",
    "addr:postcode":"bd22 0jl",
    "addr:street":"Oldfield",
    "iso:country":"GB",
    "sg:address":"Moor Lodge, Oldfield",
    "sg:city":"Keighley",
    "sg:classifiers":[
        {
            "category":"Home & Garden",
            "subcategory":"Home Furnishings",
            "type":"Retail Goods"
        },
        {
            "category":"Home & Garden",
            "subcategory":"Furniture",
            "type":"Retail Goods"
        }
    ],
    "sg:phone":"+44 1535 642585",
    "sg:postcode":"BD22 0JL",
    "sg:province":"North Yorkshire",
    "sg:tags":[
        "pine"
    ],
    "sg:website":"http://www.scartop.com",
    "wof:name":"Scartop Pine Villages",
    "wof:placetype":"venue"
},
  "geometry": {"coordinates":[-2.034070015,53.8372001648],"type":"Point"}
}