{
  "type": "Feature",
  "properties": {
    "addr:full":"1 Wellington Road Dereham Norfolk NR19 2BP",
    "addr:housenumber":"1",
    "addr:postcode":"nr19 2bp",
    "addr:street":"Wellington Road",
    "iso:country":"GB",
    "sg:address":"1 Wellington Road",
    "sg:city":"Dereham",
    "sg:classifiers":[
        {
            "category":"Autos & Motor Vehicles",
            "subcategory":"Automobile Sales",
            "type":"Retail Goods"
        },
        {
            "category":"Shopping",
            "type":"Retail Goods"
        }
    ],
    "sg:phone":"+44 1362 699460",
    "sg:postcode":"NR19 2BP",
    "sg:province":"Norfolk",
    "sg:tags":[
        "shop",
        "new age",
        "car"
    ],
    "wof:name":"Fantoosh",
    "wof:placetype":"venue"
},
  "geometry": {"coordinates":[0.9410600066,52.68227005],"type":"Point"}
}