{
  "type": "Feature",
  "properties": {
    "addr:full":"55 High Street, Wilburton Ely Cambridgeshire CB6 3RA",
    "addr:housenumber":"55",
    "addr:postcode":"cb6 3ra",
    "addr:street":"High Street",
    "iso:country":"GB",
    "sg:address":"55 High Street, Wilburton",
    "sg:city":"Ely",
    "sg:classifiers":[
        {
            "category":"Real Estate",
            "subcategory":"Architect",
            "type":"Services"
        }
    ],
    "sg:phone":"+44 1353 741030",
    "sg:postcode":"CB6 3RA",
    "sg:province":"Cambridgeshire",
    "wof:name":"Restoration Consultants",
    "wof:placetype":"venue"
},
  "geometry": {"coordinates":[0.174169004,52.3524246216],"type":"Point"}
}