{
  "type": "Feature",
  "properties": {
    "addr:full":"23 Queen Street Derby Derbyshire DE1 3DS",
    "addr:housenumber":"23",
    "addr:postcode":"de1 3ds",
    "addr:street":"Queen Street",
    "iso:country":"GB",
    "sg:address":"23 Queen Street",
    "sg:city":"Derby",
    "sg:classifiers":[
        {
            "category":"Autos & Motor Vehicles",
            "subcategory":"Fuel & Gas Station",
            "type":"Retail Goods"
        }
    ],
    "sg:phone":"+44 1332 340057",
    "sg:postcode":"DE1 3DS",
    "sg:province":"Derbyshire",
    "sg:tags":[
        "aga",
        "cooker"
    ],
    "wof:name":"The Aga Shop",
    "wof:placetype":"venue"
},
  "geometry": {"coordinates":[-1.4786880016,52.9261550903],"type":"Point"}
}