{
  "type": "Feature",
  "properties": {
    "iso:country":"GB",
    "sg:address":"Suite 112 Regent House, 24-25 Nutford Place",
    "sg:city":"London",
    "sg:classifiers":[
        {
            "category":"Manufacturing",
            "subcategory":"Textiles",
            "type":"Manufacturing & Wholesale Goods"
        }
    ],
    "sg:phone":"+44 20 7569 3118",
    "sg:postcode":"W1H 5YN",
    "sg:province":"Greater London",
    "sg:tags":[
        "merchant",
        "agent"
    ],
    "wof:name":"Larkrose Ltd.",
    "wof:placetype":"venue"
},
  "geometry": {"coordinates":[-0.164113,51.5165023804],"type":"Point"}
}