{
  "type": "Feature",
  "properties": {
    "addr:full":"121 Grey Street North Shields Tyne and Wear NE30 2EG",
    "addr:housenumber":"121",
    "addr:postcode":"ne30 2eg",
    "addr:street":"Grey Street",
    "iso:country":"GB",
    "sg:address":"121 Grey Street",
    "sg:city":"North Shields",
    "sg:classifiers":[
        {
            "category":"Transit Center",
            "subcategory":"Freight",
            "type":"Transportation"
        }
    ],
    "sg:postcode":"NE30 2EG",
    "sg:province":"Tyne and Wear",
    "sg:tags":[
        "piano",
        "accessory"
    ],
    "wof:name":"Piano Corner",
    "wof:placetype":"venue"
},
  "geometry": {"coordinates":[-1.438665,55.013702],"type":"Point"}
}