{
  "type": "Feature",
  "properties": {
    "iso:country":"GB",
    "sg:address":"5 Wimborne Place, Ashby Fields",
    "sg:city":"Daventry",
    "sg:classifiers":[
        {
            "category":"Health Services",
            "subcategory":"Dentist",
            "type":"Services"
        }
    ],
    "sg:phone":"+44 1327 704493",
    "sg:postcode":"NN11 5XY",
    "sg:province":"Northamptonshire",
    "wof:name":"Ashby Fields Dental Centre",
    "wof:placetype":"venue"
},
  "geometry": {"coordinates":[-1.160396,52.273373],"type":"Point"}
}