{
  "type": "Feature",
  "properties": {
    "addr:full":"4 Eld Lane Colchester Essex CO1 1LT",
    "addr:housenumber":"4",
    "addr:postcode":"co1 1lt",
    "addr:street":"Eld Lane",
    "iso:country":"GB",
    "sg:address":"4 Eld Lane",
    "sg:city":"Colchester",
    "sg:classifiers":[
        {
            "category":"Home & Garden",
            "subcategory":"Household Appliances",
            "type":"Retail Goods"
        }
    ],
    "sg:phone":"+44 1206 577786",
    "sg:postcode":"CO1 1LT",
    "sg:province":"Essex",
    "sg:tags":[
        "electrical"
    ],
    "wof:name":"Modern Appliances",
    "wof:placetype":"venue"
},
  "geometry": {"coordinates":[0.89987,51.887901],"type":"Point"}
}