{
  "type": "Feature",
  "properties": {
    "addr:full":"6 Orchard Court, Binley Business Park Coventry Warwickshire CV3 2TQ",
    "addr:housenumber":"6",
    "addr:postcode":"cv3 2tq",
    "addr:street":"Orchard Court",
    "iso:country":"GB",
    "sg:address":"6 Orchard Court, Binley Business Park",
    "sg:city":"Coventry",
    "sg:classifiers":[
        {
            "category":"Wholesale",
            "subcategory":"Painting Supplies",
            "type":"Manufacturing & Wholesale Goods"
        }
    ],
    "sg:phone":"+44 24 7644 7272",
    "sg:postcode":"CV3 2TQ",
    "sg:province":"Warwickshire",
    "sg:tags":[
        "carbon",
        "product"
    ],
    "wof:name":"Grafil Inc",
    "wof:placetype":"venue"
},
  "geometry": {"coordinates":[-1.4409480095,52.4009857178],"type":"Point"}
}