{
  "type": "Feature",
  "properties": {
    "addr:full":"Little Acorn, 17 Highwold, Chepstead Coulsdon Surrey CR3 3LG",
    "addr:housenumber":"17",
    "addr:postcode":"cr3 3lg",
    "addr:street":"Highwold Chepstead",
    "iso:country":"GB",
    "sg:address":"Little Acorn, 17 Highwold, Chepstead",
    "sg:city":"Coulsdon",
    "sg:classifiers":[
        {
            "category":"Communications",
            "type":"Services"
        }
    ],
    "sg:phone":"+44 1737 557777",
    "sg:postcode":"CR3 3LG",
    "sg:province":"Surrey",
    "sg:tags":[
        "telecommunication"
    ],
    "wof:name":"Telecom Specialist Supply Ltd.",
    "wof:placetype":"venue"
},
  "geometry": {"coordinates":[-0.068400003,51.2893295288],"type":"Point"}
}