{
  "type": "Feature",
  "properties": {
    "addr:full":"26 Lyng Lane West Bromwich West Midlands B70 7RP",
    "addr:housenumber":"26",
    "addr:postcode":"b70 7rp",
    "addr:street":"Lyng Lane West",
    "iso:country":"GB",
    "sg:address":"26 Lyng Lane",
    "sg:city":"West Bromwich",
    "sg:classifiers":[
        {
            "category":"Building & Trades",
            "subcategory":"Cleaning & Sanitation",
            "type":"Services"
        }
    ],
    "sg:phone":"+44 121 525 2505",
    "sg:postcode":"B70 7RP",
    "sg:province":"West Midlands",
    "sg:tags":[
        "hygiene",
        "cleansing"
    ],
    "wof:name":"Abbachem Ltd.",
    "wof:placetype":"venue"
},
  "geometry": {"coordinates":[-1.990224,52.518623],"type":"Point"}
}