{
  "type": "Feature",
  "properties": {
    "addr:full":"122 Fir Tree Av Coventry Warwickshire CV4 9FP",
    "addr:housenumber":"122",
    "addr:postcode":"cv4 9fp",
    "addr:street":"Fir Tree Av",
    "iso:country":"GB",
    "sg:address":"122 Fir Tree Av",
    "sg:city":"Coventry",
    "sg:classifiers":[
        {
            "category":"Professional",
            "subcategory":"Accounting & Tax Preparation",
            "type":"Services"
        }
    ],
    "sg:phone":"+44 24 7646 1826",
    "sg:postcode":"CV4 9FP",
    "sg:province":"Warwickshire",
    "sg:tags":[
        "accountant"
    ],
    "wof:name":"Amanti",
    "wof:placetype":"venue"
},
  "geometry": {"coordinates":[-1.563884,52.406464],"type":"Point"}
}