{
  "type": "Feature",
  "properties": {
    "addr:full":"Moorfield, Brae Shetland Shetland Islands ZE2 9SZ",
    "addr:postcode":"ze2 9sz",
    "addr:street":"Moorfield Brae;Shetland",
    "iso:country":"GB",
    "sg:address":"Moorfield, Brae",
    "sg:city":"Shetland",
    "sg:classifiers":[
        {
            "category":"Building & Trades",
            "subcategory":"Equipment Rental",
            "type":"Services"
        }
    ],
    "sg:phone":"+44 1806 522365",
    "sg:postcode":"ZE2 9SZ",
    "sg:province":"Shetland Islands",
    "sg:tags":[
        "plant",
        "machinery"
    ],
    "wof:name":"Nicolson Plant",
    "wof:placetype":"venue"
},
  "geometry": {"coordinates":[-1.2359160185,60.3495178223],"type":"Point"}
}