{
  "type": "Feature",
  "properties": {
    "iso:country":"GB",
    "sg:address":"25 Church Rd",
    "sg:city":"Poole",
    "sg:classifiers":[
        {
            "category":"Social Services",
            "subcategory":"Adult Care",
            "type":"Services"
        }
    ],
    "sg:phone":"+44 1202 722252",
    "sg:postcode":"BH14 8UF",
    "sg:province":"Dorset",
    "sg:tags":[
        "mnfr",
        "aid",
        "hearing"
    ],
    "wof:name":"L.A Desmond & Partners",
    "wof:placetype":"venue"
},
  "geometry": {"coordinates":[-1.949728,50.724159],"type":"Point"}
}