{
  "type": "Feature",
  "properties": {
    "iso:country":"GB",
    "sg:address":"5a Fishwives Causeway",
    "sg:city":"Edinburgh",
    "sg:classifiers":[
        {
            "category":"Home & Garden",
            "subcategory":"Building Materials",
            "type":"Retail Goods"
        }
    ],
    "sg:phone":"+44 131 657 1578",
    "sg:postcode":"EH15 1DF",
    "sg:province":"City of Edinburgh",
    "sg:tags":[
        "shutter",
        "door"
    ],
    "wof:name":"The Door Centre Ltd.",
    "wof:placetype":"venue"
},
  "geometry": {"coordinates":[-3.119455,55.955429],"type":"Point"}
}