{
  "type": "Feature",
  "properties": {
    "addr:full":"Bell House Lane, Anslow Burton-on-trent Derbyshire DE13 9PA",
    "addr:postcode":"de13 9pa",
    "addr:street":"House Lane",
    "iso:country":"GB",
    "sg:address":"Bell House Lane, Anslow",
    "sg:city":"Burton-on-trent",
    "sg:classifiers":[
        {
            "category":"Professional",
            "subcategory":"Engineering",
            "type":"Services"
        }
    ],
    "sg:phone":"+44 1283 563756",
    "sg:postcode":"DE13 9PA",
    "sg:province":"Derbyshire",
    "wof:name":"Tilke Engineering",
    "wof:placetype":"venue"
},
  "geometry": {"coordinates":[-1.716272,52.817974],"type":"Point"}
}