{
  "type": "Feature",
  "properties": {
    "addr:full":"Belle Vue Terr Malvern Herefordshire WR14 4PZ",
    "addr:postcode":"wr14 4pz",
    "addr:street":"Belle Vue Terr;Herefordshire",
    "iso:country":"GB",
    "sg:address":"Belle Vue Terr",
    "sg:city":"Malvern",
    "sg:classifiers":[
        {
            "category":"Communications",
            "type":"Services"
        }
    ],
    "sg:phone":"+44 1684 584800",
    "sg:postcode":"WR14 4PZ",
    "sg:province":"Herefordshire",
    "sg:tags":[
        "data",
        "network"
    ],
    "wof:name":"Secure Dimensions Ltd",
    "wof:placetype":"venue"
},
  "geometry": {"coordinates":[-2.330139,52.111938],"type":"Point"}
}