{
  "type": "Feature",
  "properties": {
    "addr:full":"2 New Rd Ayr South Ayrshire KA8 8EX",
    "addr:housenumber":"2",
    "addr:postcode":"ka8 8ex",
    "addr:street":"New Rd",
    "iso:country":"GB",
    "sg:address":"2 New Rd",
    "sg:city":"Ayr",
    "sg:classifiers":[
        {
            "category":"Professional",
            "subcategory":"Management & Consulting",
            "type":"Services"
        }
    ],
    "sg:phone":"+44 1292 266680",
    "sg:postcode":"KA8 8EX",
    "sg:province":"South Ayrshire",
    "sg:tags":[
        "consultant",
        "safety"
    ],
    "wof:name":"Safe North Ayr",
    "wof:placetype":"venue"
},
  "geometry": {"coordinates":[-4.62817,55.469742],"type":"Point"}
}