{
  "type": "Feature",
  "properties": {
    "addr:full":"4 Balmoral Road, Gidea Park Romford Essex RM2 5XD",
    "addr:housenumber":"4",
    "addr:postcode":"rm2 5xd",
    "addr:street":"Balmoral Road",
    "iso:country":"GB",
    "sg:address":"4 Balmoral Road, Gidea Park",
    "sg:city":"Romford",
    "sg:classifiers":[
        {
            "category":"Professional",
            "subcategory":"Detective & Security Services",
            "type":"Services"
        }
    ],
    "sg:phone":"+44 1708 454043",
    "sg:postcode":"RM2 5XD",
    "sg:province":"Essex",
    "sg:tags":[
        "alarm",
        "burglar",
        "system"
    ],
    "wof:name":"Owl Security Systems",
    "wof:placetype":"venue"
},
  "geometry": {"coordinates":[0.2037120014,51.578037262],"type":"Point"}
}