{
  "type": "Feature",
  "properties": {
    "addr:full":"East Mains Of Barras Stonehaven Aberdeenshire AB39 2TR",
    "addr:postcode":"ab39 2tr",
    "addr:street":"Stonehaven",
    "iso:country":"GB",
    "sg:address":"East Mains Of Barras",
    "sg:city":"Stonehaven",
    "sg:classifiers":[
        {
            "category":"Home & Garden",
            "subcategory":"Garden Supply",
            "type":"Retail Goods"
        },
        {
            "category":"Farming",
            "subcategory":"Livestock Farm",
            "type":"Manufacturing & Wholesale Goods"
        }
    ],
    "sg:phone":"+44 1569 750226",
    "sg:postcode":"AB39 2TR",
    "sg:province":"Aberdeenshire",
    "sg:tags":[
        "bulb",
        "grower",
        "others"
    ],
    "wof:name":"James & Isobel Wood",
    "wof:placetype":"venue"
},
  "geometry": {"coordinates":[-2.208759,56.963741],"type":"Point"}
}