{
  "type": "Feature",
  "properties": {
    "addr:full":"38 Parkfield Colliery Wolverhampton Staffordshire WV4 6HR",
    "addr:housenumber":"38",
    "addr:postcode":"wv4 6hr",
    "addr:street":"Parkfield Colliery",
    "iso:country":"GB",
    "sg:address":"38 Parkfield Colliery",
    "sg:city":"Wolverhampton",
    "sg:classifiers":[
        {
            "category":"Shopping",
            "subcategory":"Florist",
            "type":"Retail Goods"
        }
    ],
    "sg:phone":"+44 1902 492954",
    "sg:postcode":"WV4 6HR",
    "sg:province":"Staffordshire",
    "wof:name":"G T Pritchard & Son",
    "wof:placetype":"venue"
},
  "geometry": {"coordinates":[-2.113499,52.560631],"type":"Point"}
}