{
  "type": "Feature",
  "properties": {
    "addr:full":"2 Drummers Corner Peterhead Aberdeenshire AB42 1ZP",
    "addr:housenumber":"2",
    "addr:postcode":"ab42 1zp",
    "addr:street":"Drummers Corner",
    "iso:country":"GB",
    "sg:address":"2 Drummers Corner",
    "sg:city":"Peterhead",
    "sg:classifiers":[
        {
            "category":"Professional",
            "subcategory":"Accounting & Tax Preparation",
            "type":"Services"
        }
    ],
    "sg:phone":"+44 1779 471825",
    "sg:postcode":"AB42 1ZP",
    "sg:province":"Aberdeenshire",
    "sg:tags":[
        "accountant"
    ],
    "wof:name":"Hmd Opticians Ltd.",
    "wof:placetype":"venue"
},
  "geometry": {"coordinates":[-1.797219038,57.5065345764],"type":"Point"}
}