{
  "type": "Feature",
  "properties": {
    "addr:full":"Kenilworth Road London Greater London SE20 7QG",
    "addr:postcode":"se20 7qg",
    "addr:street":"Kenilworth Road",
    "iso:country":"GB",
    "sg:address":"Kenilworth Road",
    "sg:city":"London",
    "sg:classifiers":[
        {
            "category":"Place Of Worship",
            "type":"Public Place"
        }
    ],
    "sg:phone":"+44 20 8659 1260",
    "sg:postcode":"SE20 7QG",
    "sg:province":"Greater London",
    "wof:name":"Penge Congregational Church",
    "wof:placetype":"venue"
},
  "geometry": {"coordinates":[-0.050762,51.411411],"type":"Point"}
}