{
  "type": "Feature",
  "properties": {
    "addr:full":"5 Fulwell Park Ave Twickenham Greater London TW2 5HF",
    "addr:housenumber":"5",
    "addr:postcode":"tw2 5hf",
    "addr:street":"Fulwell Park Ave",
    "iso:country":"GB",
    "sg:address":"5 Fulwell Park Ave",
    "sg:city":"Twickenham",
    "sg:classifiers":[
        {
            "category":"Professional",
            "subcategory":"Employment Agencies",
            "type":"Services"
        }
    ],
    "sg:phone":"+44 20 8241 7878",
    "sg:postcode":"TW2 5HF",
    "sg:province":"Greater London",
    "sg:tags":[
        "consultant"
    ],
    "wof:name":"Amecom Computing Ltd",
    "wof:placetype":"venue"
},
  "geometry": {"coordinates":[-0.36092,51.439999],"type":"Point"}
}