{
  "type": "Feature",
  "properties": {
    "addr:full":"253-255 High Street Dorking Surrey RH4 1RP",
    "addr:housenumber":"253-255",
    "addr:postcode":"rh4 1rp",
    "addr:street":"High Street",
    "iso:country":"GB",
    "sg:address":"253-255 High Street",
    "sg:city":"Dorking",
    "sg:classifiers":[
        {
            "category":"Real Estate",
            "subcategory":"Real Estate Operator",
            "type":"Services"
        },
        {
            "category":"Real Estate",
            "subcategory":"Real Estate Agent",
            "type":"Services"
        }
    ],
    "sg:phone":"+44 1306 884685",
    "sg:postcode":"RH4 1RP",
    "sg:province":"Surrey",
    "sg:tags":[
        "letting"
    ],
    "sg:website":"http://www.martin-brownuk.com",
    "wof:name":"Martin Brown",
    "wof:placetype":"venue"
},
  "geometry": {"coordinates":[-0.328031987,51.2340164185],"type":"Point"}
}