{
  "type": "Feature",
  "properties": {
    "iso:country":"GB",
    "sg:address":"47 Ball Street",
    "sg:city":"Sheffield",
    "sg:classifiers":[
        {
            "category":"Professional",
            "subcategory":"Engineering",
            "type":"Services"
        }
    ],
    "sg:phone":"+44 114 275 8422",
    "sg:postcode":"S3 8DB",
    "sg:province":"South Yorkshire",
    "wof:name":"Merment Engineering Ltd.",
    "wof:placetype":"venue"
},
  "geometry": {"coordinates":[-1.47604,53.390369],"type":"Point"}
}