{
  "type": "Feature",
  "properties": {
    "addr:full":"4 Milton Road West Edinburgh City of Edinburgh EH15 1LF",
    "addr:housenumber":"4",
    "addr:postcode":"eh15 1lf",
    "addr:street":"Milton Road West Edinburgh",
    "iso:country":"GB",
    "sg:address":"4 Milton Road West",
    "sg:city":"Edinburgh",
    "sg:classifiers":[
        {
            "category":"Government",
            "subcategory":"Post Office",
            "type":"Public Place"
        }
    ],
    "sg:phone":"+44 131 669 3317",
    "sg:postcode":"EH15 1LF",
    "sg:province":"City of Edinburgh",
    "wof:name":"Milton Road West Sub Post Office",
    "wof:placetype":"venue"
},
  "geometry": {"coordinates":[-3.117554903,55.9436607361],"type":"Point"}
}