{
  "type": "Feature",
  "properties": {
    "iso:country":"GB",
    "sg:address":"22 Sussex Street",
    "sg:city":"London",
    "sg:classifiers":[
        {
            "category":"Professional",
            "subcategory":"Management & Consulting",
            "type":"Services"
        }
    ],
    "sg:phone":"+44 20 7233 6364",
    "sg:postcode":"SW1V 4RW",
    "sg:province":"Greater London",
    "sg:tags":[
        "consultant",
        "business"
    ],
    "wof:name":"Avery 2000 Ltd.",
    "wof:placetype":"venue"
},
  "geometry": {"coordinates":[-0.144191,51.48877],"type":"Point"}
}