{
  "type": "Feature",
  "properties": {
    "iso:country":"GB",
    "sg:address":"The Coach Yard, Main St",
    "sg:city":"Warwick",
    "sg:classifiers":[
        {
            "category":"Retail",
            "subcategory":"Auto Repair",
            "type":"Services"
        }
    ],
    "sg:phone":"+44 1295 680255",
    "sg:postcode":"CV35 0SE",
    "sg:province":"Warwickshire",
    "sg:tags":[
        "modification",
        "garage"
    ],
    "wof:name":"Forge Garage",
    "wof:placetype":"venue"
},
  "geometry": {"coordinates":[-1.515787,52.153526],"type":"Point"}
}