{
  "type": "Feature",
  "properties": {
    "iso:country":"GB",
    "sg:address":"2 Market Square",
    "sg:city":"Bishops Stortford",
    "sg:classifiers":[
        {
            "category":"Banks & Credit Unions",
            "subcategory":"Financial Services",
            "type":"Services"
        }
    ],
    "sg:phone":"+44 1279 757757",
    "sg:postcode":"CM23 3UU",
    "sg:province":"Essex",
    "sg:tags":[
        "adviser"
    ],
    "wof:name":"Saffron Walden Herts & Essex Building Society",
    "wof:placetype":"venue"
},
  "geometry": {"coordinates":[0.158637,51.870861],"type":"Point"}
}