{
  "type": "Feature",
  "properties": {
    "addr:full":"Church Street Wedmore Somerset BS28 4AA",
    "addr:postcode":"bs28 4aa",
    "addr:street":"Church Street",
    "iso:country":"GB",
    "sg:address":"Church Street",
    "sg:city":"Wedmore",
    "sg:classifiers":[
        {
            "category":"Government",
            "subcategory":"Post Office",
            "type":"Public Place"
        }
    ],
    "sg:postcode":"BS28 4AA",
    "sg:province":"Somerset",
    "wof:name":"Wedmore Post Office",
    "wof:placetype":"venue"
},
  "geometry": {"coordinates":[-2.8120410442,51.2275390625],"type":"Point"}
}