{
  "type": "Feature",
  "properties": {
    "addr:full":"48 Dalmeny Street Edinburgh City of Edinburgh EH6 8RG",
    "addr:housenumber":"48",
    "addr:postcode":"eh6 8rg",
    "addr:street":"Dalmeny Street",
    "iso:country":"GB",
    "sg:address":"48 Dalmeny Street",
    "sg:city":"Edinburgh",
    "sg:classifiers":[
        {
            "category":"Professional",
            "subcategory":"Printing & Photocopies",
            "type":"Services"
        }
    ],
    "sg:phone":"+44 131 555 3697",
    "sg:postcode":"EH6 8RG",
    "sg:province":"City of Edinburgh",
    "sg:tags":[
        "process",
        "screen",
        "printer"
    ],
    "wof:name":"Paragon Print Co",
    "wof:placetype":"venue"
},
  "geometry": {"coordinates":[-3.173604,55.964725],"type":"Point"}
}