{
  "type": "Feature",
  "properties": {
    "addr:full":"20 Eynsford Road Luton Bedfordshire LU4 9FH",
    "addr:housenumber":"20",
    "addr:postcode":"lu4 9fh",
    "addr:street":"Eynsford Road",
    "iso:country":"GB",
    "sg:address":"20 Eynsford Road",
    "sg:city":"Luton",
    "sg:classifiers":[
        {
            "category":"Professional",
            "subcategory":"Engineering",
            "type":"Services"
        }
    ],
    "sg:postcode":"LU4 9FH",
    "sg:province":"Bedfordshire",
    "sg:tags":[
        "design",
        "engineer"
    ],
    "wof:name":"The Ideas Farm Ltd.",
    "wof:placetype":"venue"
},
  "geometry": {"coordinates":[-0.4669350088,51.8995361328],"type":"Point"}
}