{
  "type": "Feature",
  "properties": {
    "iso:country":"GB",
    "sg:address":"76 Kilbirnie Street",
    "sg:city":"Glasgow",
    "sg:classifiers":[
        {
            "category":"Shopping",
            "type":"Retail Goods"
        }
    ],
    "sg:phone":"+44 141 429 6000",
    "sg:postcode":"G5 8JD",
    "sg:province":"Glasgow City",
    "sg:tags":[
        "part",
        "accessory"
    ],
    "wof:name":"Gils",
    "wof:placetype":"venue"
},
  "geometry": {"coordinates":[-4.264929,55.847195],"type":"Point"}
}