{
  "type": "Feature",
  "properties": {
    "addr:full":"117a London Rd Leicester Leicestershire LE2 0QT",
    "addr:housenumber":"117a",
    "addr:postcode":"le2 0qt",
    "addr:street":"London Rd",
    "iso:country":"GB",
    "sg:address":"117a London Rd",
    "sg:city":"Leicester",
    "sg:classifiers":[
        {
            "category":"Professional",
            "subcategory":"Advertising",
            "type":"Services"
        }
    ],
    "sg:phone":"+44 116 255 0181",
    "sg:postcode":"LE2 0QT",
    "sg:province":"Leicestershire",
    "sg:tags":[
        "agency"
    ],
    "wof:name":"Rhino Advertising & Design",
    "wof:placetype":"venue"
},
  "geometry": {"coordinates":[-1.121711,52.628532],"type":"Point"}
}