{
  "type": "Feature",
  "properties": {
    "iso:country":"GB",
    "sg:address":"Kings Wharf, 20-30 Kings Road",
    "sg:city":"Reading",
    "sg:classifiers":[
        {
            "category":"Professional",
            "subcategory":"Accounting & Tax Preparation",
            "type":"Services"
        }
    ],
    "sg:phone":"+44 118 957 6582",
    "sg:postcode":"RG1 3EX",
    "sg:province":"Berkshire",
    "sg:tags":[
        "accountant",
        "chartered"
    ],
    "wof:name":"Bdo Stoy Hayward",
    "wof:placetype":"venue"
},
  "geometry": {"coordinates":[-0.9630089998,51.4535217285],"type":"Point"}
}