{
  "type": "Feature",
  "properties": {
    "addr:full":"Blakey Cottages, Marley Bingley West Yorkshire BD16 2DN",
    "addr:postcode":"bd16 2dn",
    "addr:street":"West",
    "iso:country":"GB",
    "sg:address":"Blakey Cottages, Marley",
    "sg:city":"Bingley",
    "sg:classifiers":[
        {
            "category":"Social Services",
            "subcategory":"Job Training",
            "type":"Services"
        }
    ],
    "sg:postcode":"BD16 2DN",
    "sg:province":"West Yorkshire",
    "sg:tags":[
        "draughtsman",
        "drawing"
    ],
    "wof:name":"Blakey Engineering Services Ltd.",
    "wof:placetype":"venue"
},
  "geometry": {"coordinates":[-1.8389270306,53.8492584229],"type":"Point"}
}