{
  "type": "Feature",
  "properties": {
    "iso:country":"GB",
    "sg:address":"70 Worcester Road",
    "sg:city":"Bromsgrove",
    "sg:classifiers":[
        {
            "category":"Bars & Pubs",
            "type":"Food & Drink"
        },
        {
            "category":"Community Center",
            "subcategory":"Social",
            "type":"Public Place"
        }
    ],
    "sg:phone":"+44 1527 876052",
    "sg:postcode":"B61 7AG",
    "sg:province":"Worcestershire",
    "sg:tags":[
        "pubs",
        "house",
        "inn",
        "activity"
    ],
    "wof:name":"Ye Olde Black Cross",
    "wof:placetype":"venue"
},
  "geometry": {"coordinates":[-2.064814,52.331905],"type":"Point"}
}