{
  "type": "Feature",
  "properties": {
    "iso:country":"GB",
    "sg:address":"Leybourne Hold, Birtley",
    "sg:city":"Chester-le-street",
    "sg:classifiers":[
        {
            "category":"Professional",
            "subcategory":"Business Services",
            "type":"Services"
        }
    ],
    "sg:postcode":"DH3 1QF",
    "sg:province":"Durham",
    "sg:tags":[
        "bookmaker"
    ],
    "wof:name":"Joe Inness Ltd",
    "wof:placetype":"venue"
},
  "geometry": {"coordinates":[-1.5749640465,54.8591346741],"type":"Point"}
}