{
  "type": "Feature",
  "properties": {
    "addr:full":"Unit 12, St Andrews Industrial Estate, Sydney Road Birmingham West Midlands B9 4QB",
    "addr:housenumber":"unit 12",
    "addr:postcode":"b9 4qb",
    "addr:street":"St Andrews Industrial Estate Sydney Road",
    "iso:country":"GB",
    "sg:address":"Unit 12, St Andrews Industrial Estate, Sydney Road",
    "sg:city":"Birmingham",
    "sg:classifiers":[
        {
            "category":"Building & Trades",
            "subcategory":"Construction",
            "type":"Services"
        }
    ],
    "sg:phone":"+44 121 245 0575",
    "sg:postcode":"B9 4QB",
    "sg:province":"West Midlands",
    "sg:tags":[
        "builder"
    ],
    "wof:name":"Landmark Builders Ltd.",
    "wof:placetype":"venue"
},
  "geometry": {"coordinates":[-1.8677229881,52.4783248901],"type":"Point"}
}