{
  "type": "Feature",
  "properties": {
    "addr:full":"544 Uxbridge Road Hayes Greater London UB4 0SA",
    "addr:housenumber":"544",
    "addr:postcode":"ub4 0sa",
    "addr:street":"Uxbridge Road",
    "iso:country":"GB",
    "sg:address":"544 Uxbridge Road",
    "sg:city":"Hayes",
    "sg:classifiers":[
        {
            "category":"Retail",
            "subcategory":"Veterinary Services",
            "type":"Services"
        }
    ],
    "sg:phone":"+44 20 8569 2059",
    "sg:postcode":"UB4 0SA",
    "sg:province":"Greater London",
    "sg:tags":[
        "surgeon"
    ],
    "wof:name":"Currow Veterinary Care",
    "wof:placetype":"venue"
},
  "geometry": {"coordinates":[-0.4109320045,51.518913269],"type":"Point"}
}