{
  "type": "Feature",
  "properties": {
    "addr:full":"14 Withins Lane Bolton Lancashire BL2 5DY",
    "addr:housenumber":"14",
    "addr:postcode":"bl2 5dy",
    "addr:street":"Withins Lane",
    "iso:country":"GB",
    "sg:address":"14 Withins Lane",
    "sg:city":"Bolton",
    "sg:classifiers":[
        {
            "category":"Building & Trades",
            "subcategory":"Construction",
            "type":"Services"
        }
    ],
    "sg:postcode":"BL2 5DY",
    "sg:province":"Lancashire",
    "sg:tags":[
        "tiling",
        "contractor"
    ],
    "wof:name":"Quality Ceramic Tiling",
    "wof:placetype":"venue"
},
  "geometry": {"coordinates":[-2.393177,53.583412],"type":"Point"}
}