{
  "type": "Feature",
  "properties": {
    "iso:country":"GB",
    "sg:address":"Elliott House, Rhyl Road",
    "sg:city":"Rhyl",
    "sg:classifiers":[
        {
            "category":"Food & Beverages",
            "subcategory":"Meat & Fish",
            "type":"Retail Goods"
        }
    ],
    "sg:postcode":"LL18 2TR",
    "sg:province":"Conwy",
    "sg:tags":[
        "chip"
    ],
    "wof:name":"Village Chippy",
    "wof:placetype":"venue"
},
  "geometry": {"coordinates":[-3.472384,53.311581],"type":"Point"}
}