{
  "type": "Feature",
  "properties": {
    "addr:full":"Canning Road Indstl Est Canning Rd London Greater London E15 3ND",
    "addr:postcode":"greater;e15 3nd",
    "addr:street":"Canning Road Indstl Est Canning Rd",
    "iso:country":"GB",
    "sg:address":"Canning Road Indstl Est Canning Rd",
    "sg:city":"London",
    "sg:classifiers":[
        {
            "category":"Utilities",
            "subcategory":"Refuse",
            "type":"Services"
        }
    ],
    "sg:postcode":"E15 3ND",
    "sg:province":"Greater London",
    "sg:tags":[
        "skip",
        "hire"
    ],
    "wof:name":"Johnson,George William,",
    "wof:placetype":"venue"
},
  "geometry": {"coordinates":[0.00396,51.530529],"type":"Point"}
}