{
  "type": "Feature",
  "properties": {
    "addr:full":"Malvern Drive, Llanishen Cardiff Cardiff CF14 5DR",
    "addr:postcode":"cf14 5dr",
    "addr:street":"Malvern Drive",
    "iso:country":"GB",
    "sg:address":"Malvern Drive, Llanishen",
    "sg:city":"Cardiff",
    "sg:classifiers":[
        {
            "category":"Manufacturing",
            "subcategory":"Building Materials",
            "type":"Manufacturing & Wholesale Goods"
        }
    ],
    "sg:phone":"+44 29 2076 6721",
    "sg:postcode":"CF14 5DR",
    "sg:province":"Cardiff",
    "sg:tags":[
        "merchant",
        "builder"
    ],
    "wof:name":"Travis Perkins Trading Co.  Ltd.",
    "wof:placetype":"venue"
},
  "geometry": {"coordinates":[-3.1950769424,51.5227737427],"type":"Point"}
}