{
  "type": "Feature",
  "properties": {
    "addr:full":"Kenmay House, Cemetery Road Manchester Greater Manchester M26 4EU",
    "addr:postcode":"m26 4eu",
    "addr:street":"Cemetery Road",
    "iso:country":"GB",
    "sg:address":"Kenmay House, Cemetery Road",
    "sg:city":"Manchester",
    "sg:classifiers":[
        {
            "category":"Retail",
            "subcategory":"Funeral Services",
            "type":"Services"
        }
    ],
    "sg:postcode":"M26 4EU",
    "sg:province":"Greater Manchester",
    "sg:tags":[
        "mnfr",
        "monumental",
        "mason"
    ],
    "wof:name":"A K Memorials",
    "wof:placetype":"venue"
},
  "geometry": {"coordinates":[-2.3345689774,53.5681152344],"type":"Point"}
}