{
  "type": "Feature",
  "properties": {
    "addr:full":"Water Street Bakewell Derbyshire DE45 1EW",
    "addr:postcode":"de45 1ew",
    "addr:street":"Water Street",
    "iso:country":"GB",
    "sg:address":"Water Street",
    "sg:city":"Bakewell",
    "sg:classifiers":[
        {
            "category":"Professional",
            "subcategory":"Accounting & Tax Preparation",
            "type":"Services"
        }
    ],
    "sg:phone":"+44 1629 814606",
    "sg:postcode":"DE45 1EW",
    "sg:province":"Derbyshire",
    "sg:tags":[
        "accountant",
        "activity"
    ],
    "wof:name":"West & Foster",
    "wof:placetype":"venue"
},
  "geometry": {"coordinates":[-1.6739439964,53.2130661011],"type":"Point"}
}