{
  "type": "Feature",
  "properties": {
    "addr:full":"Town Hall Chambers, Town Hall Lydney Gloucestershire GL15 5DY",
    "addr:postcode":"gl15 5dy",
    "iso:country":"GB",
    "sg:address":"Town Hall Chambers, Town Hall",
    "sg:city":"Lydney",
    "sg:classifiers":[
        {
            "category":"Social Services",
            "type":"Services"
        }
    ],
    "sg:postcode":"GL15 5DY",
    "sg:province":"Gloucestershire",
    "sg:tags":[
        "need",
        "disability",
        "special"
    ],
    "wof:name":"Lydney Dial-A-Ride & Community Transport",
    "wof:placetype":"venue"
},
  "geometry": {"coordinates":[-2.5358190536,51.7244911194],"type":"Point"}
}