{
  "type": "Feature",
  "properties": {
    "addr:full":"Unit 2a Delphwood Drive, Sherdley Road Industrial Estate St Helens Cheshire WA9 5JE",
    "addr:housenumber":"unit 2a",
    "addr:postcode":"wa9 5je",
    "addr:street":"Delphwood Drive Sherdley Road Industrial Estate",
    "iso:country":"GB",
    "sg:address":"Unit 2a Delphwood Drive, Sherdley Road Industrial Estate",
    "sg:city":"St Helens",
    "sg:classifiers":[
        {
            "category":"Wholesale",
            "subcategory":"Vending Machines",
            "type":"Manufacturing & Wholesale Goods"
        }
    ],
    "sg:phone":"+44 1744 613066",
    "sg:postcode":"WA9 5JE",
    "sg:province":"Cheshire",
    "wof:name":"U K Automatic Vending Supplies Ltd.",
    "wof:placetype":"venue"
},
  "geometry": {"coordinates":[-2.7289540768,53.4433784485],"type":"Point"}
}