{
  "type": "Feature",
  "properties": {
    "addr:full":"Surrey Quays Shopping Centre, Redriff Road London Greater London SE16 7LL",
    "addr:postcode":"se16 7ll",
    "addr:street":"Redriff Road",
    "iso:country":"GB",
    "sg:address":"Surrey Quays Shopping Centre, Redriff Road",
    "sg:city":"London",
    "sg:classifiers":[
        {
            "category":"Shopping",
            "subcategory":"Mobile Phones",
            "type":"Retail Goods"
        }
    ],
    "sg:phone":"+44 20 7252 0787",
    "sg:postcode":"SE16 7LL",
    "sg:province":"Greater London",
    "wof:name":"Mobile Phone Centre",
    "wof:placetype":"venue"
},
  "geometry": {"coordinates":[-0.045819,51.497787],"type":"Point"}
}