{
  "type": "Feature",
  "properties": {
    "iso:country":"GB",
    "sg:address":"33 Apple Tree Gr",
    "sg:city":"Ferndown",
    "sg:classifiers":[
        {
            "category":"Personal",
            "type":"Services"
        }
    ],
    "sg:postcode":"BH22 9LA",
    "sg:province":"Dorset",
    "sg:tags":[
        "delivery"
    ],
    "wof:name":"Greyhound Delivery & Courier Services",
    "wof:placetype":"venue"
},
  "geometry": {"coordinates":[-1.8839479685,50.8041763306],"type":"Point"}
}