{
  "type": "Feature",
  "properties": {
    "iso:country":"GB",
    "sg:address":"79 Church St",
    "sg:city":"Neath",
    "sg:classifiers":[
        {
            "category":"Retail",
            "subcategory":"Auto Repair",
            "type":"Services"
        }
    ],
    "sg:phone":"+44 1639 821969",
    "sg:postcode":"SA11 2JW",
    "sg:province":"Neath Port Talbot",
    "sg:tags":[
        "modification",
        "garage"
    ],
    "wof:name":"Lewis Fred Auto's",
    "wof:placetype":"venue"
},
  "geometry": {"coordinates":[-3.824029,51.632],"type":"Point"}
}