{
  "type": "Feature",
  "properties": {
    "iso:country":"GB",
    "sg:address":"4 Bishops Court, Kennoway",
    "sg:city":"Leven",
    "sg:classifiers":[
        {
            "category":"Health Services",
            "subcategory":"Dentist",
            "type":"Services"
        }
    ],
    "sg:phone":"+44 1333 350841",
    "sg:postcode":"KY8 5LA",
    "sg:province":"Fife",
    "wof:name":"Graham Warner",
    "wof:placetype":"venue"
},
  "geometry": {"coordinates":[-3.0483,56.210339],"type":"Point"}
}