{
  "type": "Feature",
  "properties": {
    "iso:country":"GB",
    "sg:address":"26 Wharfside, Bletchely",
    "sg:city":"Milton Keynes",
    "sg:classifiers":[
        {
            "category":"Professional",
            "subcategory":"Engineering",
            "type":"Services"
        }
    ],
    "sg:phone":"+44 1908 648792",
    "sg:postcode":"MK2 2AZ",
    "sg:province":"Buckinghamshire",
    "sg:tags":[
        "precision",
        "engineer"
    ],
    "wof:name":"K & K Specialised Engineering Ltd.",
    "wof:placetype":"venue"
},
  "geometry": {"coordinates":[-0.715037,51.997025],"type":"Point"}
}