{
  "type": "Feature",
  "properties": {
    "iso:country":"GB",
    "sg:address":"6 Cross Court",
    "sg:city":"High Wycombe",
    "sg:classifiers":[
        {
            "category":"Food & Beverages",
            "subcategory":"Bakery",
            "type":"Retail Goods"
        }
    ],
    "sg:postcode":"HP13 5UW",
    "sg:province":"Buckinghamshire",
    "sg:tags":[
        "pizza"
    ],
    "wof:name":"Giant Pizza (Downley) Ltd.",
    "wof:placetype":"venue"
},
  "geometry": {"coordinates":[-0.780502,51.629002],"type":"Point"}
}