{
  "type": "Feature",
  "properties": {
    "addr:full":"The White House, 3 Sandygate Park Sheffield South Yorkshire S10 5TZ",
    "addr:housenumber":"3",
    "addr:postcode":"s10 5tz",
    "addr:street":"Sandygate Park",
    "iso:country":"GB",
    "sg:address":"The White House, 3 Sandygate Park",
    "sg:city":"Sheffield",
    "sg:classifiers":[
        {
            "category":"Health Services",
            "subcategory":"Health Practitioner",
            "type":"Services"
        }
    ],
    "sg:phone":"+44 114 230 2030",
    "sg:postcode":"S10 5TZ",
    "sg:province":"South Yorkshire",
    "sg:tags":[
        "physiotherapist"
    ],
    "wof:name":"White House Physiotherapy & Sports Injury Clinic (",
    "wof:placetype":"venue"
},
  "geometry": {"coordinates":[-1.5375059843,53.3756713867],"type":"Point"}
}