{
  "type": "Feature",
  "properties": {
    "addr:full":"100 Palmerstone Road Southsea Hampshire PO5 3PT",
    "addr:housenumber":"100",
    "addr:postcode":"po5 3pt",
    "addr:street":"Palmerstone Road",
    "iso:country":"GB",
    "sg:address":"100 Palmerstone Road",
    "sg:city":"Southsea",
    "sg:classifiers":[
        {
            "category":"Banks & Credit Unions",
            "subcategory":"Financial Services",
            "type":"Services"
        }
    ],
    "sg:phone":"+44 23 9235 2312",
    "sg:postcode":"PO5 3PT",
    "sg:province":"Hampshire",
    "sg:tags":[
        "consultant"
    ],
    "wof:name":"Douglas & Rolls",
    "wof:placetype":"venue"
},
  "geometry": {"coordinates":[-1.089074,50.784168],"type":"Point"}
}