{
  "type": "Feature",
  "properties": {
    "iso:country":"GB",
    "sg:address":"320 Portland Road",
    "sg:city":"Hove",
    "sg:classifiers":[
        {
            "category":"Professional",
            "type":"Services"
        }
    ],
    "sg:postcode":"BN3 5LP",
    "sg:province":"East Sussex",
    "sg:tags":[
        "caterer"
    ],
    "wof:name":"Munchies",
    "wof:placetype":"venue"
},
  "geometry": {"coordinates":[-0.195758,50.8344],"type":"Point"}
}