{
  "type": "Feature",
  "properties": {
    "iso:country":"GB",
    "sg:address":"C/o 1r Blake Road, Cumbernauld",
    "sg:city":"Glasgow",
    "sg:classifiers":[
        {
            "category":"Place Of Worship",
            "type":"Public Place"
        }
    ],
    "sg:phone":"+44 1236 721599",
    "sg:postcode":"G67 1AG",
    "sg:province":"Falkirk",
    "wof:name":"Scottish Episcopal Church",
    "wof:placetype":"venue"
},
  "geometry": {"coordinates":[-3.9859900475,55.9515800476],"type":"Point"}
}