{
  "type": "Feature",
  "properties": {
    "iso:country":"GB",
    "sg:address":"Unit 16a The Spinneys Industrial Estate, Swepstone Road, Heather",
    "sg:city":"Coalville",
    "sg:classifiers":[
        {
            "category":"Building & Trades",
            "subcategory":"Construction",
            "type":"Services"
        }
    ],
    "sg:phone":"+44 1530 260506",
    "sg:postcode":"LE67 2RE",
    "sg:province":"Leicestershire",
    "sg:tags":[
        "joinery"
    ],
    "wof:name":"Heather Joinery",
    "wof:placetype":"venue"
},
  "geometry": {"coordinates":[-1.4240640402,52.6929893494],"type":"Point"}
}