{
  "type": "Feature",
  "properties": {
    "addr:full":"Hollygate Farm, Stragglethorpe, Radcliffe On Trent Nottingham Nottinghamshire NG12 2JW",
    "addr:postcode":"ng12 2jw",
    "addr:street":"Hollygate;Stragglethorpe",
    "iso:country":"GB",
    "sg:address":"Hollygate Farm, Stragglethorpe, Radcliffe On Trent",
    "sg:city":"Nottingham",
    "sg:classifiers":[
        {
            "category":"Farming",
            "subcategory":"Farm",
            "type":"Manufacturing & Wholesale Goods"
        }
    ],
    "sg:phone":"+44 115 989 4646",
    "sg:postcode":"NG12 2JW",
    "sg:province":"Nottinghamshire",
    "sg:tags":[
        "mixed",
        "crop"
    ],
    "wof:name":"Peter W Gadd",
    "wof:placetype":"venue"
},
  "geometry": {"coordinates":[-1.028711,52.946136],"type":"Point"}
}