{
  "type": "Feature",
  "properties": {
    "addr:full":"30b High Street Paisley Renfrewshire PA1 2BZ",
    "addr:housenumber":"30b",
    "addr:postcode":"pa1 2bz",
    "addr:street":"High Street",
    "iso:country":"GB",
    "sg:address":"30b High Street",
    "sg:city":"Paisley",
    "sg:classifiers":[
        {
            "category":"Shopping",
            "subcategory":"Clothing, Apparel, & Fashions",
            "type":"Retail Goods"
        }
    ],
    "sg:phone":"+44 141 887 3543",
    "sg:postcode":"PA1 2BZ",
    "sg:province":"Renfrewshire",
    "sg:tags":[
        "shop"
    ],
    "wof:name":"Uniques",
    "wof:placetype":"venue"
},
  "geometry": {"coordinates":[-4.426407,55.845413],"type":"Point"}
}