{
  "type": "Feature",
  "properties": {
    "addr:full":"378 Bideford Grn Leighton Buzzard Bedfordshire LU7 2TY",
    "addr:housenumber":"378",
    "addr:postcode":"lu7 2ty",
    "addr:street":"Bideford Grn",
    "iso:country":"GB",
    "sg:address":"378 Bideford Grn",
    "sg:city":"Leighton Buzzard",
    "sg:classifiers":[
        {
            "category":"Manufacturing",
            "subcategory":"Signs",
            "type":"Manufacturing & Wholesale Goods"
        }
    ],
    "sg:phone":"+44 1525 370949",
    "sg:postcode":"LU7 2TY",
    "sg:province":"Bedfordshire",
    "sg:tags":[
        "nameplate"
    ],
    "wof:name":"John Hopkins",
    "wof:placetype":"venue"
},
  "geometry": {"coordinates":[-0.686793,51.920929],"type":"Point"}
}