{
  "type": "Feature",
  "properties": {
    "iso:country":"GB",
    "sg:address":"21 Main Street, Barrowden",
    "sg:city":"Oakham",
    "sg:classifiers":[
        {
            "category":"Building & Trades",
            "subcategory":"Construction",
            "type":"Services"
        }
    ],
    "sg:phone":"+44 1572 747680",
    "sg:postcode":"LE15 8EQ",
    "sg:province":"Leicestershire",
    "sg:tags":[
        "builder"
    ],
    "wof:name":"Moss Beck Ltd.",
    "wof:placetype":"venue"
},
  "geometry": {"coordinates":[-0.6027709842,52.5899963379],"type":"Point"}
}