{
  "type": "Feature",
  "properties": {
    "addr:full":"53 Highgate Road London Greater London NW5 1TL",
    "addr:housenumber":"53",
    "addr:postcode":"nw5 1tl",
    "addr:street":"Highgate Road",
    "iso:country":"GB",
    "sg:address":"53 Highgate Road",
    "sg:city":"London",
    "sg:classifiers":[
        {
            "category":"Organizations",
            "subcategory":"Non-profit Organization",
            "type":"Services"
        }
    ],
    "sg:phone":"+44 20 7485 0900",
    "sg:postcode":"NW5 1TL",
    "sg:province":"Greater London",
    "sg:tags":[
        "organisation",
        "voluntary",
        "charity"
    ],
    "wof:name":"Friends United Network",
    "wof:placetype":"venue"
},
  "geometry": {"coordinates":[-0.144722,51.55447],"type":"Point"}
}