{
  "type": "Feature",
  "properties": {
    "iso:country":"GB",
    "sg:address":"Barrie, Fibbards Rd",
    "sg:city":"Brockenhurst",
    "sg:classifiers":[
        {
            "category":"Health Services",
            "subcategory":"Health Practitioner",
            "type":"Services"
        }
    ],
    "sg:phone":"+44 1590 623589",
    "sg:postcode":"SO42 7RD",
    "sg:province":"Hampshire",
    "sg:tags":[
        "homoeopathic"
    ],
    "wof:name":"Anson",
    "wof:placetype":"venue"
},
  "geometry": {"coordinates":[-1.572004,50.818642],"type":"Point"}
}