{
  "type": "Feature",
  "properties": {
    "addr:full":"89 Bedfont Lane Feltham Greater London TW14 9BH",
    "addr:housenumber":"89",
    "addr:postcode":"tw14 9bh",
    "addr:street":"Bedfont Lane",
    "iso:country":"GB",
    "sg:address":"89 Bedfont Lane",
    "sg:city":"Feltham",
    "sg:classifiers":[
        {
            "category":"Personal",
            "subcategory":"Beauty Salon",
            "type":"Services"
        }
    ],
    "sg:phone":"+44 20 8890 2203",
    "sg:postcode":"TW14 9BH",
    "sg:province":"Greater London",
    "sg:tags":[
        "unisex",
        "hairdresser"
    ],
    "wof:name":"Mack-Habes",
    "wof:placetype":"venue"
},
  "geometry": {"coordinates":[-0.4128099978,51.4482841492],"type":"Point"}
}