{
  "type": "Feature",
  "properties": {
    "iso:country":"GB",
    "sg:address":"31a The Broadway, Thatcham",
    "sg:city":"Newbury",
    "sg:classifiers":[
        {
            "category":"Shopping",
            "subcategory":"Florist",
            "type":"Retail Goods"
        }
    ],
    "sg:phone":"+44 1635 871129",
    "sg:postcode":"RG19 3HX",
    "sg:province":"Berkshire",
    "wof:name":"Meadow Fresh Florists",
    "wof:placetype":"venue"
},
  "geometry": {"coordinates":[-1.2572989464,51.4035339355],"type":"Point"}
}