{
  "type": "Feature",
  "properties": {
    "iso:country":"GB",
    "sg:address":"19 Market Street",
    "sg:city":"Bacup",
    "sg:classifiers":[
        {
            "category":"Shopping",
            "subcategory":"Comic Books",
            "type":"Retail Goods"
        }
    ],
    "sg:phone":"+44 1706 873986",
    "sg:postcode":"OL13 8EX",
    "sg:province":"Lancashire",
    "sg:tags":[
        "jeweller"
    ],
    "wof:name":"A A Hallywell",
    "wof:placetype":"venue"
},
  "geometry": {"coordinates":[-2.201325,53.702652],"type":"Point"}
}