{
  "type": "Feature",
  "properties": {
    "addr:full":"10a Greenwich Market London Greater London SE10 9HZ",
    "addr:housenumber":"10a",
    "addr:postcode":"se10 9hz",
    "addr:street":"Market",
    "iso:country":"GB",
    "sg:address":"10a Greenwich Market",
    "sg:city":"London",
    "sg:classifiers":[
        {
            "category":"Home & Garden",
            "subcategory":"Home Furnishings",
            "type":"Retail Goods"
        }
    ],
    "sg:phone":"+44 20 8858 0099",
    "sg:postcode":"SE10 9HZ",
    "sg:province":"Greater London",
    "sg:tags":[
        "candle"
    ],
    "wof:name":"Thinking of You",
    "wof:placetype":"venue"
},
  "geometry": {"coordinates":[-0.000627,51.483936],"type":"Point"}
}