{
  "type": "Feature",
  "properties": {
    "addr:full":"1 Burden Way Guildford Surrey GU2 9PB",
    "addr:housenumber":"1",
    "addr:postcode":"gu2 9pb",
    "addr:street":"Burden Way",
    "iso:country":"GB",
    "sg:address":"1 Burden Way",
    "sg:city":"Guildford",
    "sg:classifiers":[
        {
            "category":"Food & Beverages",
            "subcategory":"Groceries & Convenience Stores",
            "type":"Retail Goods"
        }
    ],
    "sg:phone":"+44 1483 232260",
    "sg:postcode":"GU2 9PB",
    "sg:province":"Surrey",
    "wof:name":"Grange Park Stores",
    "wof:placetype":"venue"
},
  "geometry": {"coordinates":[-0.5853700042,51.2642059326],"type":"Point"}
}