{
  "type": "Feature",
  "properties": {
    "addr:full":"5 Lawn Rd London Greater London NW3 2XS",
    "addr:housenumber":"5",
    "addr:postcode":"nw3 2xs",
    "addr:street":"Lawn Rd",
    "iso:country":"GB",
    "sg:address":"5 Lawn Rd",
    "sg:city":"London",
    "sg:classifiers":[
        {
            "category":"Food & Beverages",
            "subcategory":"Specialty",
            "type":"Retail Goods"
        }
    ],
    "sg:postcode":"NW3 2XS",
    "sg:province":"Greater London",
    "sg:tags":[
        "product",
        "health"
    ],
    "wof:name":"Triolet International Ltd",
    "wof:placetype":"venue"
},
  "geometry": {"coordinates":[-0.161689,51.549438],"type":"Point"}
}