{
  "type": "Feature",
  "properties": {
    "iso:country":"GB",
    "sg:address":"Ash Farm, Tamworth Road, Corley",
    "sg:city":"Coventry",
    "sg:classifiers":[
        {
            "category":"Farming",
            "subcategory":"Livestock Farm",
            "type":"Manufacturing & Wholesale Goods"
        }
    ],
    "sg:postcode":"CV7 8BP",
    "sg:province":"Warwickshire",
    "sg:tags":[
        "others"
    ],
    "wof:name":"A A & R Knowles",
    "wof:placetype":"venue"
},
  "geometry": {"coordinates":[-1.558937,52.464916],"type":"Point"}
}