{
  "type": "Feature",
  "properties": {
    "addr:full":"Ilkley Abattoir, Little Lane Ilkley North Yorkshire LS29 8HX",
    "addr:postcode":"ls29 8hx",
    "addr:street":"Little Lane",
    "iso:country":"GB",
    "sg:address":"Ilkley Abattoir, Little Lane",
    "sg:city":"Ilkley",
    "sg:classifiers":[
        {
            "category":"Wholesale",
            "subcategory":"Meat",
            "type":"Manufacturing & Wholesale Goods"
        },
        {
            "category":"Food & Beverages",
            "subcategory":"Meat & Fish",
            "type":"Retail Goods"
        }
    ],
    "sg:phone":"+44 1943 608042",
    "sg:postcode":"LS29 8HX",
    "sg:province":"North Yorkshire",
    "sg:tags":[
        "-",
        "butcher"
    ],
    "wof:name":"Rowland Agar (Wholesale Butchers) Ltd",
    "wof:placetype":"venue"
},
  "geometry": {"coordinates":[-1.821754,53.924461],"type":"Point"}
}