{
  "type": "Feature",
  "properties": {
    "iso:country":"GB",
    "sg:address":"15-17 Newgate Street Village",
    "sg:city":"Hertford",
    "sg:classifiers":[
        {
            "category":"Utilities",
            "subcategory":"Telephone",
            "type":"Services"
        }
    ],
    "sg:phone":"+44 1707 874775",
    "sg:postcode":"SG13 8RA",
    "sg:province":"Hertfordshire",
    "sg:tags":[
        "telecommunication"
    ],
    "wof:name":"Telic Ltd",
    "wof:placetype":"venue"
},
  "geometry": {"coordinates":[-0.118614,51.730125],"type":"Point"}
}