{
  "type": "Feature",
  "properties": {
    "addr:full":"46 Brook Street Chester Cheshire CH1 3DZ",
    "addr:housenumber":"46",
    "addr:postcode":"ch1 3dz",
    "addr:street":"Brook Street",
    "iso:country":"GB",
    "sg:address":"46 Brook Street",
    "sg:city":"Chester",
    "sg:classifiers":[
        {
            "category":"Banks & Credit Unions",
            "subcategory":"Financial Services",
            "type":"Services"
        }
    ],
    "sg:phone":"+44 1244 505505",
    "sg:postcode":"CH1 3DZ",
    "sg:province":"Cheshire",
    "sg:tags":[
        "cashing",
        "cheque"
    ],
    "wof:name":"Cash Centres Ltd",
    "wof:placetype":"venue"
},
  "geometry": {"coordinates":[-2.8858981133,53.1950302124],"type":"Point"}
}