{
  "type": "Feature",
  "properties": {
    "addr:full":"Units 25-26, Templars Sq Oxford Oxfordshire OX4 3UZ",
    "addr:housenumber":"units 25-26",
    "addr:postcode":"ox4 3uz",
    "addr:street":"Templars Sq",
    "iso:country":"GB",
    "sg:address":"Units 25-26, Templars Sq",
    "sg:city":"Oxford",
    "sg:classifiers":[
        {
            "category":"Shopping",
            "subcategory":"Clothing, Apparel, & Fashions",
            "type":"Retail Goods"
        }
    ],
    "sg:phone":"+44 1865 717975",
    "sg:postcode":"OX4 3UZ",
    "sg:province":"Oxfordshire",
    "sg:tags":[
        "ladieswear"
    ],
    "wof:name":"Arcadia Group Plc",
    "wof:placetype":"venue"
},
  "geometry": {"coordinates":[-1.21651,51.731609],"type":"Point"}
}