{
  "type": "Feature",
  "properties": {
    "addr:full":"Po Box 481a Addlestone Surrey KT15 3YZ",
    "addr:housenumber":"po;481a",
    "addr:postcode":"kt15 3yz",
    "addr:street":"Box",
    "iso:country":"GB",
    "sg:address":"Po Box 481a",
    "sg:city":"Addlestone",
    "sg:classifiers":[
        {
            "category":"Professional",
            "type":"Services"
        }
    ],
    "sg:phone":"+44 20 8398 7914",
    "sg:postcode":"KT15 3YZ",
    "sg:province":"Surrey",
    "sg:tags":[
        "exhibition"
    ],
    "wof:name":"M J Display",
    "wof:placetype":"venue"
},
  "geometry": {"coordinates":[-0.5027490258,51.3477210999],"type":"Point"}
}