{
  "type": "Feature",
  "properties": {
    "iso:country":"GB",
    "sg:address":"Unit 7 Churchills Yard, Jubilee Road",
    "sg:city":"Waterlooville",
    "sg:classifiers":[
        {
            "category":"Professional",
            "subcategory":"Engineering",
            "type":"Services"
        }
    ],
    "sg:postcode":"PO7 7RE",
    "sg:province":"Hampshire",
    "sg:tags":[
        "precision",
        "engineer"
    ],
    "wof:name":"Lines Engineering",
    "wof:placetype":"venue"
},
  "geometry": {"coordinates":[-1.0288540125,50.8826332092],"type":"Point"}
}