{
  "type": "Feature",
  "properties": {
    "addr:full":"3 Penn Court, West Moors Ferndown Dorset BH22 0JJ",
    "addr:housenumber":"3",
    "addr:postcode":"bh22 0jj",
    "addr:street":"Penn Court",
    "iso:country":"GB",
    "sg:address":"3 Penn Court, West Moors",
    "sg:city":"Ferndown",
    "sg:classifiers":[
        {
            "category":"Personal",
            "subcategory":"Beauty Salon",
            "type":"Services"
        },
        {
            "category":"Personal",
            "subcategory":"Barber",
            "type":"Services"
        }
    ],
    "sg:phone":"+44 1202 870200",
    "sg:postcode":"BH22 0JJ",
    "sg:province":"Dorset",
    "sg:tags":[
        "unisex",
        "hairdresser"
    ],
    "wof:name":"Studio One Hair Designs Ltd",
    "wof:placetype":"venue"
},
  "geometry": {"coordinates":[-1.889014,50.824951],"type":"Point"}
}