{
  "type": "Feature",
  "properties": {
    "iso:country":"GB",
    "sg:address":"28 Cork Street",
    "sg:city":"Leicester",
    "sg:classifiers":[
        {
            "category":"Wholesale",
            "subcategory":"Non-durable Goods",
            "type":"Manufacturing & Wholesale Goods"
        },
        {
            "category":"Wholesale",
            "subcategory":"Groceries",
            "type":"Manufacturing & Wholesale Goods"
        }
    ],
    "sg:phone":"+44 116 254 4278",
    "sg:postcode":"LE5 5AN",
    "sg:province":"Leicestershire",
    "sg:tags":[
        "food",
        "drink",
        "cash",
        "wholesaler",
        "carry",
        "supplier"
    ],
    "wof:name":"Sabat Bros",
    "wof:placetype":"venue"
},
  "geometry": {"coordinates":[-1.109581,52.630936],"type":"Point"}
}