{
  "type": "Feature",
  "properties": {
    "iso:country":"GB",
    "sg:address":"69 Old Woking Rd",
    "sg:city":"West Byfleet",
    "sg:classifiers":[
        {
            "category":"Professional",
            "subcategory":"Management & Consulting",
            "type":"Services"
        }
    ],
    "sg:phone":"+44 1932 344007",
    "sg:postcode":"KT14 6LF",
    "sg:province":"Surrey",
    "sg:tags":[
        "consultant",
        "promotion",
        "direct",
        "sale"
    ],
    "wof:name":"Just Promotions Ltd",
    "wof:placetype":"venue"
},
  "geometry": {"coordinates":[-0.505519,51.336811],"type":"Point"}
}