{
  "type": "Feature",
  "properties": {
    "addr:full":"481 Harrow Road London Greater London W10 4RG",
    "addr:housenumber":"481",
    "addr:postcode":"w10 4rg",
    "addr:street":"Harrow Road",
    "iso:country":"GB",
    "sg:address":"481 Harrow Road",
    "sg:city":"London",
    "sg:classifiers":[
        {
            "category":"Professional",
            "subcategory":"Computer Services",
            "type":"Services"
        }
    ],
    "sg:phone":"+44 20 8968 6611",
    "sg:postcode":"W10 4RG",
    "sg:province":"Greater London",
    "sg:tags":[
        "system",
        "software"
    ],
    "wof:name":"Britech 2000 Computer Systems",
    "wof:placetype":"venue"
},
  "geometry": {"coordinates":[-0.2112269998,51.5268135071],"type":"Point"}
}