{
  "type": "Feature",
  "properties": {
    "iso:country":"GB",
    "sg:address":"Unit 1, Barton Road, Long Eaton",
    "sg:city":"Nottingham",
    "sg:classifiers":[
        {
            "category":"Wholesale",
            "subcategory":"Vending Machines",
            "type":"Manufacturing & Wholesale Goods"
        }
    ],
    "sg:phone":"+44 115 946 0304",
    "sg:postcode":"NG10 2FN",
    "sg:province":"Derbyshire",
    "wof:name":"Staff Support Services Ltd.",
    "wof:placetype":"venue"
},
  "geometry": {"coordinates":[-1.254752,52.892597],"type":"Point"}
}