{
  "type": "Feature",
  "properties": {
    "iso:country":"GB",
    "sg:address":"Howell House, Middlehill Road",
    "sg:city":"Wimborne",
    "sg:classifiers":[
        {
            "category":"Organizations",
            "subcategory":"Non-profit Organization",
            "type":"Services"
        }
    ],
    "sg:phone":"+44 1202 886143",
    "sg:postcode":"BH21 2EY",
    "sg:province":"Dorset",
    "sg:tags":[
        "organisation",
        "voluntary",
        "charity"
    ],
    "wof:name":"Rotary Housing Association",
    "wof:placetype":"venue"
},
  "geometry": {"coordinates":[-1.956552,50.809814],"type":"Point"}
}