{
  "type": "Feature",
  "properties": {
    "iso:country":"GB",
    "sg:address":"Office 531, 28 Old Brompton Road",
    "sg:city":"London",
    "sg:classifiers":[
        {
            "category":"Professional",
            "subcategory":"Computer Services",
            "type":"Services"
        }
    ],
    "sg:postcode":"SW7 3SS",
    "sg:province":"Greater London",
    "sg:tags":[
        "system",
        "software"
    ],
    "wof:name":"Europe on the Net Ltd",
    "wof:placetype":"venue"
},
  "geometry": {"coordinates":[-0.175388,51.493641],"type":"Point"}
}