{
  "type": "Feature",
  "properties": {
    "iso:country":"GB",
    "sg:address":"303-305 Lode Lane",
    "sg:city":"Solihull",
    "sg:classifiers":[
        {
            "category":"Autos & Motor Vehicles",
            "subcategory":"Auto Supplies",
            "type":"Retail Goods"
        }
    ],
    "sg:phone":"+44 121 705 4561",
    "sg:postcode":"B91 2HP",
    "sg:province":"West Midlands",
    "sg:tags":[
        "exhaust",
        "absorber",
        "shock"
    ],
    "wof:name":"Kwik-Fit",
    "wof:placetype":"venue"
},
  "geometry": {"coordinates":[-1.781053,52.431114],"type":"Point"}
}