{
  "type": "Feature",
  "properties": {
    "iso:country":"GB",
    "sg:address":"Bessie Surtees House, Sandhill",
    "sg:city":"Newcastle-upon-tyne",
    "sg:classifiers":[
        {
            "category":"Landmark",
            "subcategory":"Tourist Attraction",
            "type":"Public Place"
        }
    ],
    "sg:phone":"+44 191 269 1200",
    "sg:postcode":"NE1 3JF",
    "sg:province":"Tyne and Wear",
    "sg:tags":[
        "interest"
    ],
    "wof:name":"English Heritage",
    "wof:placetype":"venue"
},
  "geometry": {"coordinates":[-1.608,54.968658],"type":"Point"}
}