{
  "type": "Feature",
  "properties": {
    "addr:full":"Rosebery Avenue London Greater London EC1R 4SQ",
    "addr:postcode":"ec1r 4sq",
    "addr:street":"Rosebery Avenue",
    "iso:country":"GB",
    "sg:address":"Rosebery Avenue",
    "sg:city":"London",
    "sg:classifiers":[
        {
            "category":"Government",
            "subcategory":"Post Office",
            "type":"Public Place"
        }
    ],
    "sg:phone":"+44 20 7837 6525",
    "sg:postcode":"EC1R 4SQ",
    "sg:province":"Greater London",
    "wof:name":"Mount Pleasant Post Office",
    "wof:placetype":"venue"
},
  "geometry": {"coordinates":[-0.111554,51.523045],"type":"Point"}
}