{
  "type": "Feature",
  "properties": {
    "addr:full":"6 Park Avenue Sittingbourne Kent ME10 1QX",
    "addr:housenumber":"6",
    "addr:postcode":"me10 1qx",
    "addr:street":"Park Avenue",
    "iso:country":"GB",
    "sg:address":"6 Park Avenue",
    "sg:city":"Sittingbourne",
    "sg:classifiers":[
        {
            "category":"Real Estate",
            "subcategory":"Architect",
            "type":"Services"
        }
    ],
    "sg:phone":"+44 1795 423998",
    "sg:postcode":"ME10 1QX",
    "sg:province":"Kent",
    "wof:name":"D J Pamplin",
    "wof:placetype":"venue"
},
  "geometry": {"coordinates":[0.725655973,51.330329895],"type":"Point"}
}