{
  "type": "Feature",
  "properties": {
    "iso:country":"GB",
    "sg:address":"Elmsdale Ho 31 The Grn",
    "sg:city":"West Drayton",
    "sg:classifiers":[
        {
            "category":"Professional",
            "subcategory":"Detective & Security Services",
            "type":"Services"
        }
    ],
    "sg:postcode":"UB7 7PN",
    "sg:province":"Greater London",
    "wof:name":"Sigma Security",
    "wof:placetype":"venue"
},
  "geometry": {"coordinates":[-0.47399,51.509117],"type":"Point"}
}