{
  "type": "Feature",
  "properties": {
    "iso:country":"GB",
    "sg:address":"Jackson Street",
    "sg:city":"St Helens",
    "sg:classifiers":[
        {
            "category":"Home & Garden",
            "subcategory":"Building Materials",
            "type":"Retail Goods"
        }
    ],
    "sg:phone":"+44 1744 730628",
    "sg:postcode":"WA9 3AZ",
    "sg:province":"Cheshire",
    "sg:tags":[
        "fencing"
    ],
    "wof:name":"Betakreet Products",
    "wof:placetype":"venue"
},
  "geometry": {"coordinates":[-2.719029,53.445259],"type":"Point"}
}