{
  "type": "Feature",
  "properties": {
    "iso:country":"GB",
    "sg:address":"Glasgow Road, Blantyre",
    "sg:city":"Glasgow",
    "sg:classifiers":[
        {
            "category":"Education",
            "subcategory":"School",
            "type":"Public Place"
        },
        {
            "category":"Government",
            "subcategory":"Office",
            "type":"Public Place"
        }
    ],
    "sg:phone":"+44 1698 825121",
    "sg:postcode":"G72 0YJ",
    "sg:province":"South Lanarkshire",
    "sg:tags":[
        "local",
        "authority"
    ],
    "wof:name":"St Joseph's Primary School",
    "wof:placetype":"venue"
},
  "geometry": {"coordinates":[-4.092808,55.78466],"type":"Point"}
}