{
  "type": "Feature",
  "properties": {
    "addr:full":"200 Church Street, Eccles Manchester Greater Manchester M30 0LZ",
    "addr:housenumber":"200",
    "addr:postcode":"m30 0lz",
    "addr:street":"Church Street",
    "iso:country":"GB",
    "sg:address":"200 Church Street, Eccles",
    "sg:city":"Manchester",
    "sg:classifiers":[
        {
            "category":"Retail",
            "subcategory":"Repair Shop",
            "type":"Services"
        },
        {
            "category":"Manufacturing",
            "subcategory":"Furniture",
            "type":"Manufacturing & Wholesale Goods"
        }
    ],
    "sg:phone":"+44 161 789 0275",
    "sg:postcode":"M30 0LZ",
    "sg:province":"Greater Manchester",
    "sg:tags":[
        "antique",
        "mnfr",
        "restoration",
        "upholsterer"
    ],
    "wof:name":"Smiths Upholstery",
    "wof:placetype":"venue"
},
  "geometry": {"coordinates":[-2.344301939,53.4833450317],"type":"Point"}
}