{
  "type": "Feature",
  "properties": {
    "addr:full":"93a Rivington Street London Greater London EC2A 3AY",
    "addr:housenumber":"93a",
    "addr:postcode":"ec2a 3ay",
    "addr:street":"Rivington Street",
    "iso:country":"GB",
    "sg:address":"93a Rivington Street",
    "sg:city":"London",
    "sg:classifiers":[
        {
            "category":"Professional",
            "subcategory":"Business Services",
            "type":"Services"
        }
    ],
    "sg:phone":"+44 20 7729 8222",
    "sg:postcode":"EC2A 3AY",
    "sg:province":"Greater London",
    "sg:tags":[
        "registrar"
    ],
    "wof:name":"Chalfen Services Ltd.",
    "wof:placetype":"venue"
},
  "geometry": {"coordinates":[-0.0784669966,51.526424408],"type":"Point"}
}