{
  "type": "Feature",
  "properties": {
    "addr:full":"115 Ellingham Industrial Centre, Ellingham Way Ashford Kent TN23 6LZ",
    "addr:housenumber":"115",
    "addr:postcode":"tn23 6lz",
    "addr:street":"Ellingham;Ellingham Way",
    "iso:country":"GB",
    "sg:address":"115 Ellingham Industrial Centre, Ellingham Way",
    "sg:city":"Ashford",
    "sg:classifiers":[
        {
            "category":"Recreation",
            "subcategory":"Fishing",
            "type":"Entertainment"
        }
    ],
    "sg:phone":"+44 1233 630914",
    "sg:postcode":"TN23 6LZ",
    "sg:province":"Kent",
    "sg:tags":[
        "equipment",
        "angling"
    ],
    "wof:name":"Ashford Tackle Shop",
    "wof:placetype":"venue"
},
  "geometry": {"coordinates":[0.8640620112,51.1288604736],"type":"Point"}
}