{
  "type": "Feature",
  "properties": {
    "addr:full":"2 The Arcade, Brinnington Stockport Cheshire SK5 8LR",
    "addr:housenumber":"2;arcade",
    "addr:postcode":"sk5 8lr",
    "addr:street":"The",
    "iso:country":"GB",
    "sg:address":"2 The Arcade, Brinnington",
    "sg:city":"Stockport",
    "sg:classifiers":[
        {
            "category":"Personal",
            "subcategory":"Barber",
            "type":"Services"
        }
    ],
    "sg:phone":"+44 161 430 4605",
    "sg:postcode":"SK5 8LR",
    "sg:province":"Cheshire",
    "sg:tags":[
        "men's",
        "hairdresser"
    ],
    "wof:name":"The Barber Shop",
    "wof:placetype":"venue"
},
  "geometry": {"coordinates":[-2.1368670464,53.4238700867],"type":"Point"}
}