{
  "type": "Feature",
  "properties": {
    "addr:full":"5-7 Clevedon Road Weston-super-mare Somerset BS23 1DA",
    "addr:housenumber":"5-7",
    "addr:postcode":"bs23 1da",
    "addr:street":"Clevedon Road",
    "iso:country":"GB",
    "sg:address":"5-7 Clevedon Road",
    "sg:city":"Weston-super-mare",
    "sg:classifiers":[
        {
            "category":"Travel",
            "subcategory":"Hotels & Motels",
            "type":"Entertainment"
        }
    ],
    "sg:phone":"+44 1934 632501",
    "sg:postcode":"BS23 1DA",
    "sg:province":"Somerset",
    "wof:name":"Lewinsdale Lodge Hotel",
    "wof:placetype":"venue"
},
  "geometry": {"coordinates":[-2.980312,51.340714],"type":"Point"}
}