{
  "type": "Feature",
  "properties": {
    "addr:full":"Aviation Way Southend-on-sea Essex SS2 6UN",
    "addr:postcode":"ss2 6un",
    "addr:street":"Aviation Way",
    "iso:country":"GB",
    "sg:address":"Aviation Way",
    "sg:city":"Southend-on-sea",
    "sg:classifiers":[
        {
            "category":"Manufacturing",
            "subcategory":"Aerospace",
            "type":"Manufacturing & Wholesale Goods"
        }
    ],
    "sg:phone":"+44 1702 549371",
    "sg:postcode":"SS2 6UN",
    "sg:province":"Essex",
    "sg:tags":[
        "aircraft",
        "furnishing",
        "fitting"
    ],
    "wof:name":"Ipeco Europe",
    "wof:placetype":"venue"
},
  "geometry": {"coordinates":[0.6834899783,51.5681343079],"type":"Point"}
}