{
  "type": "Feature",
  "properties": {
    "iso:country":"GB",
    "sg:address":"12 Denmark Street",
    "sg:city":"Bristol",
    "sg:classifiers":[
        {
            "category":"Food & Beverages",
            "subcategory":"Liquor & Beverages",
            "type":"Retail Goods"
        }
    ],
    "sg:phone":"+44 117 927 5000",
    "sg:postcode":"BS1 5DQ",
    "sg:province":"City of Bristol",
    "sg:tags":[
        "beer",
        "spirit",
        "wines"
    ],
    "wof:name":"John Harvey & Sons Ltd.",
    "wof:placetype":"venue"
},
  "geometry": {"coordinates":[-2.599724,51.453262],"type":"Point"}
}