{
  "type": "Feature",
  "properties": {
    "iso:country":"GB",
    "sg:address":"74 Farnborough Road",
    "sg:city":"Farnborough",
    "sg:classifiers":[
        {
            "category":"Food & Beverages",
            "subcategory":"Liquor & Beverages",
            "type":"Retail Goods"
        }
    ],
    "sg:phone":"+44 1252 541223",
    "sg:postcode":"GU14 6TH",
    "sg:province":"Hampshire",
    "sg:tags":[
        "beer",
        "spirit",
        "wines"
    ],
    "wof:name":"Unwins Wine Merchants",
    "wof:placetype":"venue"
},
  "geometry": {"coordinates":[-0.752849,51.28212],"type":"Point"}
}