{
  "type": "Feature",
  "properties": {
    "addr:full":"2 Rose Crescent Perth Perth and Kinross PH1 1NS",
    "addr:housenumber":"2",
    "addr:postcode":"ph1 1ns",
    "addr:street":"Rose Crescent",
    "iso:country":"GB",
    "sg:address":"2 Rose Crescent",
    "sg:city":"Perth",
    "sg:classifiers":[
        {
            "category":"Health Services",
            "subcategory":"Doctor",
            "type":"Services"
        }
    ],
    "sg:postcode":"PH1 1NS",
    "sg:province":"Perth and Kinross",
    "sg:tags":[
        "practitioners"
    ],
    "wof:name":"Perth Back Pain Clinic",
    "wof:placetype":"venue"
},
  "geometry": {"coordinates":[-3.4488279819,56.3958129883],"type":"Point"}
}