{
  "type": "Feature",
  "properties": {
    "addr:full":"2 Kensington Avenue Cheltenham Gloucestershire GL50 2NQ",
    "addr:housenumber":"2",
    "addr:postcode":"gl50 2nq",
    "addr:street":"Kensington Avenue",
    "iso:country":"GB",
    "sg:address":"2 Kensington Avenue",
    "sg:city":"Cheltenham",
    "sg:classifiers":[
        {
            "category":"Building & Trades",
            "subcategory":"Construction",
            "type":"Services"
        }
    ],
    "sg:phone":"+44 1242 244721",
    "sg:postcode":"GL50 2NQ",
    "sg:province":"Gloucestershire",
    "sg:tags":[
        "ceiling",
        "contractor"
    ],
    "wof:name":"Champion Ceilings",
    "wof:placetype":"venue"
},
  "geometry": {"coordinates":[-2.098536,51.896446],"type":"Point"}
}