{
  "type": "Feature",
  "properties": {
    "addr:full":"90 Cannon Street London Greater London EC4N 6HA",
    "addr:housenumber":"90",
    "addr:postcode":"ec4n 6ha",
    "addr:street":"Cannon Street",
    "iso:country":"GB",
    "sg:address":"90 Cannon Street",
    "sg:city":"London",
    "sg:classifiers":[
        {
            "category":"Banks & Credit Unions",
            "subcategory":"Bank",
            "type":"Services"
        }
    ],
    "sg:phone":"+44 20 7282 8888",
    "sg:postcode":"EC4N 6HA",
    "sg:province":"Greater London",
    "wof:name":"Bank of China International (U K) Ltd.",
    "wof:placetype":"venue"
},
  "geometry": {"coordinates":[-0.0891000032,51.5110702515],"type":"Point"}
}