{
  "type": "Feature",
  "properties": {
    "addr:full":"58 Stamford New Road Altrincham Cheshire WA14 1EE",
    "addr:housenumber":"58",
    "addr:postcode":"wa14 1ee",
    "addr:street":"Stamford New Road",
    "iso:country":"GB",
    "sg:address":"58 Stamford New Road",
    "sg:city":"Altrincham",
    "sg:classifiers":[
        {
            "category":"Shopping",
            "subcategory":"Stationery & Office Supplies",
            "type":"Retail Goods"
        }
    ],
    "sg:postcode":"WA14 1EE",
    "sg:province":"Cheshire",
    "wof:name":"Ryman the Stationer",
    "wof:placetype":"venue"
},
  "geometry": {"coordinates":[-2.349282,53.386887],"type":"Point"}
}