{
  "type": "Feature",
  "properties": {
    "iso:country":"GB",
    "sg:address":"24 Smithy Parade",
    "sg:city":"Dewsbury",
    "sg:classifiers":[
        {
            "category":"Building & Trades",
            "subcategory":"Construction",
            "type":"Services"
        }
    ],
    "sg:phone":"+44 1924 466341",
    "sg:postcode":"WF12 0HG",
    "sg:province":"West Yorkshire",
    "sg:tags":[
        "roofing"
    ],
    "wof:name":"Fibre Fixed Roofing",
    "wof:placetype":"venue"
},
  "geometry": {"coordinates":[-1.6153359413,53.6582183838],"type":"Point"}
}