{
  "type": "Feature",
  "properties": {
    "addr:full":"11 Hessle Gro Epsom Surrey KT17 1JS",
    "addr:housenumber":"11;gro",
    "addr:postcode":"kt17 1js",
    "iso:country":"GB",
    "sg:address":"11 Hessle Gro",
    "sg:city":"Epsom",
    "sg:classifiers":[
        {
            "category":"Home & Garden",
            "subcategory":"Building Materials",
            "type":"Retail Goods"
        }
    ],
    "sg:phone":"+44 20 8393 7876",
    "sg:postcode":"KT17 1JS",
    "sg:province":"Surrey",
    "sg:tags":[
        "fencing"
    ],
    "wof:name":"Derwent Fencing Specialists",
    "wof:placetype":"venue"
},
  "geometry": {"coordinates":[-0.2546119988,51.3430252075],"type":"Point"}
}