{
  "type": "Feature",
  "properties": {
    "addr:full":"676 Pershore Road, Selly Park, Selly Oak Birmingham West Midlands B29 7NX",
    "addr:housenumber":"676",
    "addr:postcode":"b29 7nx",
    "addr:street":"Pershore Road",
    "iso:country":"GB",
    "sg:address":"676 Pershore Road, Selly Park, Selly Oak",
    "sg:city":"Birmingham",
    "sg:classifiers":[
        {
            "category":"Utilities",
            "subcategory":"Natural Gas",
            "type":"Services"
        }
    ],
    "sg:phone":"+44 121 472 7293",
    "sg:postcode":"B29 7NX",
    "sg:province":"West Midlands",
    "wof:name":"G A (Gas) Services Ltd.",
    "wof:placetype":"venue"
},
  "geometry": {"coordinates":[-1.9146620035,52.4453125],"type":"Point"}
}