{
  "type": "Feature",
  "properties": {
    "iso:country":"GB",
    "sg:address":"7a Gerard Street, Ashton-in-makerfieldgerard",
    "sg:city":"Wigan",
    "sg:classifiers":[
        {
            "category":"Professional",
            "subcategory":"Management & Consulting",
            "type":"Services"
        }
    ],
    "sg:phone":"+44 1626 772212",
    "sg:postcode":"WN4 9AG",
    "sg:province":"Lancashire",
    "sg:tags":[
        "marketing",
        "consultant"
    ],
    "wof:name":"Westerfell Associates Ltd.",
    "wof:placetype":"venue"
},
  "geometry": {"coordinates":[-2.636519,53.487541],"type":"Point"}
}