{
  "type": "Feature",
  "properties": {
    "iso:country":"GB",
    "sg:address":"13 Old Park Road",
    "sg:city":"Clevedon",
    "sg:classifiers":[
        {
            "category":"Manufacturing",
            "subcategory":"Tools & Machinery",
            "type":"Manufacturing & Wholesale Goods"
        }
    ],
    "sg:phone":"+44 1275 874223",
    "sg:postcode":"BS21 7JH",
    "sg:province":"Somerset",
    "sg:tags":[
        "society",
        "friendly"
    ],
    "wof:name":"R T A Financial Recovery",
    "wof:placetype":"venue"
},
  "geometry": {"coordinates":[-2.855847,51.44574],"type":"Point"}
}