{
  "type": "Feature",
  "properties": {
    "iso:country":"GB",
    "sg:address":"Henry Street",
    "sg:city":"Leigh",
    "sg:classifiers":[
        {
            "category":"Building & Trades",
            "subcategory":"Construction",
            "type":"Services"
        }
    ],
    "sg:phone":"+44 1942 675696",
    "sg:postcode":"WN7 2PG",
    "sg:province":"Lancashire",
    "sg:tags":[
        "joinery"
    ],
    "wof:name":"Yates & Green",
    "wof:placetype":"venue"
},
  "geometry": {"coordinates":[-2.511197,53.494751],"type":"Point"}
}