{
  "type": "Feature",
  "properties": {
    "addr:full":"Balm Road Industrial Estate, Beza Street Leeds West Yorkshire LS10 1DY",
    "addr:postcode":"ls10 1dy",
    "addr:street":"Balm Road Industrial Estate Beza Street",
    "iso:country":"GB",
    "sg:address":"Balm Road Industrial Estate, Beza Street",
    "sg:city":"Leeds",
    "sg:classifiers":[
        {
            "category":"Autos & Motor Vehicles",
            "subcategory":"Automobile Sales",
            "type":"Retail Goods"
        }
    ],
    "sg:phone":"+44 113 277 1199",
    "sg:postcode":"LS10 1DY",
    "sg:province":"West Yorkshire",
    "sg:tags":[
        "car"
    ],
    "wof:name":"D M Keith Ltd.",
    "wof:placetype":"venue"
},
  "geometry": {"coordinates":[-1.546587,53.794495],"type":"Point"}
}