{
  "type": "Feature",
  "properties": {
    "iso:country":"GB",
    "sg:address":"Rhos Farm",
    "sg:city":"Pentraeth",
    "sg:classifiers":[
        {
            "category":"Farming",
            "subcategory":"Livestock Farm",
            "type":"Manufacturing & Wholesale Goods"
        }
    ],
    "sg:postcode":"LL75 8DZ",
    "sg:province":"Isle of Anglesey",
    "sg:tags":[
        "others"
    ],
    "wof:name":"O A Owen",
    "wof:placetype":"venue"
},
  "geometry": {"coordinates":[-4.217468,53.286034],"type":"Point"}
}