{
  "type": "Feature",
  "properties": {
    "addr:full":"Rock-a-nore Road Hastings East Sussex TN34 3DW",
    "addr:postcode":"tn34 3dw",
    "addr:street":"Rock-A-Nore Road",
    "iso:country":"GB",
    "sg:address":"Rock-a-nore Road",
    "sg:city":"Hastings",
    "sg:classifiers":[
        {
            "category":"Retail",
            "subcategory":"Auto Repair",
            "type":"Services"
        }
    ],
    "sg:phone":"+44 1424 437384",
    "sg:postcode":"TN34 3DW",
    "sg:province":"East Sussex",
    "sg:tags":[
        "modification",
        "garage"
    ],
    "wof:name":"Hastings Bodypanels",
    "wof:placetype":"venue"
},
  "geometry": {"coordinates":[0.5931249857,50.8561134338],"type":"Point"}
}