{
  "type": "Feature",
  "properties": {
    "addr:full":"23 Faraday Road, Rabans Lane Industrial Area Aylesbury Buckinghamshire HP19 8RY",
    "addr:housenumber":"23",
    "addr:postcode":"hp19 8ry",
    "addr:street":"Faraday Road Rabans Lane",
    "iso:country":"GB",
    "sg:address":"23 Faraday Road, Rabans Lane Industrial Area",
    "sg:city":"Aylesbury",
    "sg:classifiers":[
        {
            "category":"Manufacturing",
            "subcategory":"Food",
            "type":"Manufacturing & Wholesale Goods"
        },
        {
            "category":"Food & Beverages",
            "subcategory":"Supermarket",
            "type":"Retail Goods"
        }
    ],
    "sg:phone":"+44 1296 399704",
    "sg:postcode":"HP19 8RY",
    "sg:province":"Buckinghamshire",
    "sg:tags":[
        "frozen",
        "product",
        "manufacturer"
    ],
    "wof:name":"Chiltern Salads Ltd",
    "wof:placetype":"venue"
},
  "geometry": {"coordinates":[-0.841584,51.824139],"type":"Point"}
}