{
  "type": "Feature",
  "properties": {
    "addr:full":"23 High Street Cradley Heath West Midlands B64 5HG",
    "addr:housenumber":"23",
    "addr:postcode":"b64 5hg",
    "addr:street":"High Street",
    "iso:country":"GB",
    "sg:address":"23 High Street",
    "sg:city":"Cradley Heath",
    "sg:classifiers":[
        {
            "category":"Shopping",
            "subcategory":"Used Merchandise",
            "type":"Retail Goods"
        }
    ],
    "sg:postcode":"B64 5HG",
    "sg:province":"West Midlands",
    "sg:tags":[
        "shop",
        "second-hand"
    ],
    "wof:name":"Glad Rags",
    "wof:placetype":"venue"
},
  "geometry": {"coordinates":[-2.0815269947,52.4722671509],"type":"Point"}
}