{
  "type": "Feature",
  "properties": {
    "iso:country":"GB",
    "sg:address":"Farm Cottage, Tremlett Hall",
    "sg:city":"Wellington",
    "sg:classifiers":[
        {
            "category":"Farming",
            "subcategory":"Farm",
            "type":"Manufacturing & Wholesale Goods"
        }
    ],
    "sg:phone":"+44 1823 672012",
    "sg:postcode":"TA21 0JJ",
    "sg:province":"Devon",
    "sg:tags":[
        "mixed",
        "crop"
    ],
    "wof:name":"C L W Hill",
    "wof:placetype":"venue"
},
  "geometry": {"coordinates":[-3.3176999092,50.9730682373],"type":"Point"}
}