{
  "type": "Feature",
  "properties": {
    "addr:full":"6a Montague Rd Richmond Greater London TW10 6QW",
    "addr:housenumber":"6a",
    "addr:postcode":"tw10 6qw",
    "addr:street":"Montague Rd",
    "iso:country":"GB",
    "sg:address":"6a Montague Rd",
    "sg:city":"Richmond",
    "sg:classifiers":[
        {
            "category":"Farming",
            "subcategory":"Nursery",
            "type":"Manufacturing & Wholesale Goods"
        }
    ],
    "sg:postcode":"TW10 6QW",
    "sg:province":"Greater London",
    "sg:tags":[
        "creche"
    ],
    "wof:name":"Mabbs,Tracey,",
    "wof:placetype":"venue"
},
  "geometry": {"coordinates":[-0.298426,51.455589],"type":"Point"}
}