{
  "type": "Feature",
  "properties": {
    "addr:full":"P O Box 1116 Ebbw Vale Blaenau Gwent NP23 8XW",
    "addr:housenumber":"p o;1116",
    "addr:postcode":"np23 8xw",
    "iso:country":"GB",
    "sg:address":"P O Box 1116",
    "sg:city":"Ebbw Vale",
    "sg:classifiers":[
        {
            "category":"Communications",
            "type":"Services"
        }
    ],
    "sg:phone":"+44 1495 301116",
    "sg:postcode":"NP23 8XW",
    "sg:province":"Blaenau Gwent",
    "sg:tags":[
        "broadcasting"
    ],
    "wof:name":"Valleys Radio",
    "wof:placetype":"venue"
},
  "geometry": {"coordinates":[-3.2146859169,51.7970275879],"type":"Point"}
}