{
  "type": "Feature",
  "properties": {
    "addr:full":"Mortimer House, 65-77 Malham Road, Malham Business Area London Greater London SE23 1AH",
    "addr:housenumber":"65-77",
    "addr:postcode":"se23 1ah",
    "addr:street":"Malham Road",
    "iso:country":"GB",
    "sg:address":"Mortimer House, 65-77 Malham Road, Malham Business Area",
    "sg:city":"London",
    "sg:classifiers":[
        {
            "category":"Building & Trades",
            "subcategory":"Equipment Rental",
            "type":"Services"
        }
    ],
    "sg:phone":"+44 20 8291 0880",
    "sg:postcode":"SE23 1AH",
    "sg:province":"Greater London",
    "sg:tags":[
        "hire",
        "centre"
    ],
    "wof:name":"Rentatool",
    "wof:placetype":"venue"
},
  "geometry": {"coordinates":[-0.0488299988,51.4429359436],"type":"Point"}
}