{
  "type": "Feature",
  "properties": {
    "addr:full":"Unit 3h Mullacott Industrial Estate Ilfracombe Devon EX34 8PL",
    "addr:housenumber":"3h;estate",
    "addr:postcode":"ex34 8pl",
    "addr:street":"Mullacott Industrial",
    "iso:country":"GB",
    "sg:address":"Unit 3h Mullacott Industrial Estate",
    "sg:city":"Ilfracombe",
    "sg:classifiers":[
        {
            "category":"Farming",
            "subcategory":"Fish & Marine Products",
            "type":"Manufacturing & Wholesale Goods"
        },
        {
            "category":"Wholesale",
            "subcategory":"Groceries",
            "type":"Manufacturing & Wholesale Goods"
        }
    ],
    "sg:phone":"+44 1271 866155",
    "sg:postcode":"EX34 8PL",
    "sg:province":"Devon",
    "sg:tags":[
        "food",
        "supplier",
        "drink",
        "fishmonger"
    ],
    "wof:name":"Clarke's Butcher",
    "wof:placetype":"venue"
},
  "geometry": {"coordinates":[-4.125414,51.179161],"type":"Point"}
}