{
  "type": "Feature",
  "properties": {
    "addr:full":"2 Charlotte Street Aberdeen Aberdeen City AB25 1LR",
    "addr:housenumber":"2",
    "addr:postcode":"ab25 1lr",
    "addr:street":"Charlotte Street",
    "iso:country":"GB",
    "sg:address":"2 Charlotte Street",
    "sg:city":"Aberdeen",
    "sg:classifiers":[
        {
            "category":"Travel",
            "subcategory":"Hostel",
            "type":"Entertainment"
        }
    ],
    "sg:phone":"+44 1224 634966",
    "sg:postcode":"AB25 1LR",
    "sg:province":"Aberdeen City",
    "wof:name":"Aberdeen Ywca Housing Association Gb",
    "wof:placetype":"venue"
},
  "geometry": {"coordinates":[-2.1030409336,57.1499786377],"type":"Point"}
}