{
  "type": "Feature",
  "properties": {
    "iso:country":"GB",
    "sg:address":"25 Woodlands Rd",
    "sg:city":"Gillingham",
    "sg:classifiers":[
        {
            "category":"Professional",
            "subcategory":"Art Services",
            "type":"Services"
        }
    ],
    "sg:postcode":"ME7 2BT",
    "sg:province":"Kent",
    "sg:tags":[
        "graphic",
        "designer"
    ],
    "wof:name":"Curran,Babette,",
    "wof:placetype":"venue"
},
  "geometry": {"coordinates":[0.566178,51.377174],"type":"Point"}
}