{
  "type": "Feature",
  "properties": {
    "iso:country":"GB",
    "sg:address":"30 Clune Road, Gowkhall",
    "sg:city":"Dunfermline",
    "sg:classifiers":[
        {
            "category":"Education",
            "subcategory":"Special Training",
            "type":"Public Place"
        }
    ],
    "sg:postcode":"KY12 9NZ",
    "sg:province":"Fife",
    "sg:tags":[
        "product",
        "centre"
    ],
    "wof:name":"United Kingdom Telecommunications Academy",
    "wof:placetype":"venue"
},
  "geometry": {"coordinates":[-3.520524,56.086037],"type":"Point"}
}