{
  "type": "Feature",
  "properties": {
    "iso:country":"GB",
    "sg:address":"Holme La",
    "sg:city":"Selby",
    "sg:classifiers":[
        {
            "category":"Structure",
            "subcategory":"Warehouse",
            "type":"Public Place"
        }
    ],
    "sg:phone":"+44 1757 703642",
    "sg:postcode":"YO8 0EL",
    "sg:province":"East Riding of Yorkshire",
    "wof:name":"Onward Group",
    "wof:placetype":"venue"
},
  "geometry": {"coordinates":[-1.067489,53.787251],"type":"Point"}
}