{
  "type": "Feature",
  "properties": {
    "addr:full":"12-14 Chandos Road London Greater London NW10 6NF",
    "addr:housenumber":"12-14",
    "addr:postcode":"nw10 6nf",
    "addr:street":"Chandos Road",
    "iso:country":"GB",
    "sg:address":"12-14 Chandos Road",
    "sg:city":"London",
    "sg:classifiers":[
        {
            "category":"Social Services",
            "subcategory":"Retirement Home",
            "type":"Services"
        }
    ],
    "sg:phone":"+44 20 8838 4400",
    "sg:postcode":"NW10 6NF",
    "sg:province":"Greater London",
    "sg:tags":[
        "glazing",
        "safety"
    ],
    "wof:name":"Toughglaze (U K) Ltd.",
    "wof:placetype":"venue"
},
  "geometry": {"coordinates":[-0.224813,51.551411],"type":"Point"}
}