{
  "type": "Feature",
  "properties": {
    "addr:full":"Hospital Drove Spalding Cambridgeshire PE12 9EL",
    "addr:postcode":"pe12 9el",
    "addr:street":"Drove Spalding",
    "iso:country":"GB",
    "sg:address":"Hospital Drove",
    "sg:city":"Spalding",
    "sg:classifiers":[
        {
            "category":"Home & Garden",
            "subcategory":"Garden Supply",
            "type":"Retail Goods"
        }
    ],
    "sg:postcode":"PE12 9EL",
    "sg:province":"Cambridgeshire",
    "sg:tags":[
        "nursery",
        "centre"
    ],
    "wof:name":"Hospital Drove Nurseries",
    "wof:placetype":"venue"
},
  "geometry": {"coordinates":[0.153283,52.790958],"type":"Point"}
}