{
  "type": "Feature",
  "properties": {
    "iso:country":"GB",
    "sg:address":"Units 1 & 2, Block 1",
    "sg:city":"Perth",
    "sg:classifiers":[
        {
            "category":"Retail",
            "subcategory":"Auto Repair",
            "type":"Services"
        }
    ],
    "sg:phone":"+44 1738 631351",
    "sg:postcode":"PH1 1PP",
    "sg:province":"Perth and Kinross",
    "sg:tags":[
        "car",
        "servicing",
        "radiator"
    ],
    "wof:name":"Serck Marston",
    "wof:placetype":"venue"
},
  "geometry": {"coordinates":[-3.452117,56.404316],"type":"Point"}
}