{
  "type": "Feature",
  "properties": {
    "iso:country":"GB",
    "sg:address":"94 Brighton Rd",
    "sg:city":"Horley",
    "sg:classifiers":[
        {
            "category":"Shopping",
            "subcategory":"Computers & Home Electronics",
            "type":"Retail Goods"
        }
    ],
    "sg:phone":"+44 1293 781234",
    "sg:postcode":"RH6 7JQ",
    "sg:province":"Surrey",
    "sg:tags":[
        "electrical"
    ],
    "wof:name":"Qvs Electrical Wholesale Ltd",
    "wof:placetype":"venue"
},
  "geometry": {"coordinates":[-0.166744,51.177856],"type":"Point"}
}