{
  "type": "Feature",
  "properties": {
    "iso:country":"GB",
    "sg:address":"Alexandra Dock",
    "sg:city":"Grimsby",
    "sg:classifiers":[
        {
            "category":"Professional",
            "subcategory":"Business Services",
            "type":"Services"
        },
        {
            "category":"Government",
            "subcategory":"Office",
            "type":"Public Place"
        }
    ],
    "sg:phone":"+44 1472 324695",
    "sg:postcode":"DN31 1UL",
    "sg:province":"Lincolnshire",
    "sg:tags":[
        "accomodation",
        "local"
    ],
    "wof:name":"Alexandra Dock Business Centre",
    "wof:placetype":"venue"
},
  "geometry": {"coordinates":[-0.084547,53.568695],"type":"Point"}
}