{
  "type": "Feature",
  "properties": {
    "iso:country":"GB",
    "sg:address":"Unit 5 Lymore Gardens, Oldfield Park",
    "sg:city":"Bath",
    "sg:classifiers":[
        {
            "category":"Home & Garden",
            "subcategory":"Home Furnishings",
            "type":"Retail Goods"
        }
    ],
    "sg:phone":"+44 1225 424467",
    "sg:postcode":"BA2 1AQ",
    "sg:province":"Somerset",
    "sg:tags":[
        "furnishers",
        "planner",
        "kitchen"
    ],
    "wof:name":"Countertops Ltd.",
    "wof:placetype":"venue"
},
  "geometry": {"coordinates":[-2.3846890926,51.3748245239],"type":"Point"}
}