{
  "type": "Feature",
  "properties": {
    "iso:country":"GB",
    "sg:address":"1 Boughton",
    "sg:city":"Chester",
    "sg:classifiers":[
        {
            "category":"Bars & Pubs",
            "type":"Food & Drink"
        }
    ],
    "sg:postcode":"CH3 5AE",
    "sg:province":"Cheshire",
    "sg:tags":[
        "pubs",
        "inn"
    ],
    "wof:name":"Bells",
    "wof:placetype":"venue"
},
  "geometry": {"coordinates":[-2.880975008,53.1923408508],"type":"Point"}
}