{
  "type": "Feature",
  "properties": {
    "addr:full":"6 Westcliff Road, Westbrook Margate Kent CT9 5DH",
    "addr:housenumber":"6",
    "addr:postcode":"ct9 5dh",
    "addr:street":"Westcliff Road",
    "iso:country":"GB",
    "sg:address":"6 Westcliff Road, Westbrook",
    "sg:city":"Margate",
    "sg:classifiers":[
        {
            "category":"Home & Garden",
            "subcategory":"Household Appliances",
            "type":"Retail Goods"
        }
    ],
    "sg:postcode":"CT9 5DH",
    "sg:province":"Kent",
    "sg:tags":[
        "electrical"
    ],
    "wof:name":"Anchor Domestic Appliances",
    "wof:placetype":"venue"
},
  "geometry": {"coordinates":[1.3637759686,51.3838157654],"type":"Point"}
}