{
  "type": "Feature",
  "properties": {
    "addr:full":"Parrett Works Martock Somerset TA12 6AE",
    "addr:postcode":"ta12 6ae",
    "iso:country":"GB",
    "sg:address":"Parrett Works",
    "sg:city":"Martock",
    "sg:classifiers":[
        {
            "category":"Retail",
            "subcategory":"Auto Repair",
            "type":"Services"
        }
    ],
    "sg:phone":"+44 1935 823694",
    "sg:postcode":"TA12 6AE",
    "sg:province":"Somerset",
    "sg:tags":[
        "body",
        "car",
        "repairer"
    ],
    "wof:name":"Auto Mobile Crash Repairs",
    "wof:placetype":"venue"
},
  "geometry": {"coordinates":[-2.7706689835,50.9672470093],"type":"Point"}
}