{
  "type": "Feature",
  "properties": {
    "iso:country":"GB",
    "sg:address":"2 South Sq, Grays Inn",
    "sg:city":"London",
    "sg:classifiers":[
        {
            "category":"Organizations",
            "subcategory":"Community Association",
            "type":"Services"
        }
    ],
    "sg:postcode":"WC1R 5HP",
    "sg:province":"Greater London",
    "sg:tags":[
        "national"
    ],
    "wof:name":"Academy of Experts (The)",
    "wof:placetype":"venue"
},
  "geometry": {"coordinates":[-0.112456,51.518806],"type":"Point"}
}