{
  "type": "Feature",
  "properties": {
    "addr:full":"Castle House, Castle Hill Avenue Folkestone Kent CT20 2TQ",
    "addr:postcode":"ct20 2tq",
    "addr:street":"Castle Hill Avenue",
    "iso:country":"GB",
    "sg:address":"Castle House, Castle Hill Avenue",
    "sg:city":"Folkestone",
    "sg:classifiers":[
        {
            "category":"Shopping",
            "subcategory":"Books",
            "type":"Retail Goods"
        }
    ],
    "sg:postcode":"CT20 2TQ",
    "sg:province":"Kent",
    "wof:name":"Independent Travel Publishing Ltd",
    "wof:placetype":"venue"
},
  "geometry": {"coordinates":[1.1713910103,51.0786781311],"type":"Point"}
}