{
  "type": "Feature",
  "properties": {
    "addr:full":"Lowgate Hexham Northumberland NE46 2NN",
    "addr:postcode":"ne46 2nn",
    "addr:street":"Lowgate",
    "iso:country":"GB",
    "sg:address":"Lowgate",
    "sg:city":"Hexham",
    "sg:classifiers":[
        {
            "category":"Education",
            "subcategory":"School",
            "type":"Public Place"
        }
    ],
    "sg:postcode":"NE46 2NN",
    "sg:province":"Northumberland",
    "sg:tags":[
        "local",
        "authority"
    ],
    "wof:name":"Lowgate County First School",
    "wof:placetype":"venue"
},
  "geometry": {"coordinates":[-2.101294,54.970036],"type":"Point"}
}