{
  "type": "Feature",
  "properties": {
    "addr:full":"52 Hadley Road Barnet Hertfordshire EN5 5QS",
    "addr:housenumber":"52",
    "addr:postcode":"en5 5qs",
    "addr:street":"Hadley Road",
    "iso:country":"GB",
    "sg:address":"52 Hadley Road",
    "sg:city":"Barnet",
    "sg:classifiers":[
        {
            "category":"Professional",
            "subcategory":"Computer Services",
            "type":"Services"
        }
    ],
    "sg:phone":"+44 1462 624327",
    "sg:postcode":"EN5 5QS",
    "sg:province":"Hertfordshire",
    "sg:tags":[
        "bureau",
        "facility"
    ],
    "wof:name":"Extended Data Processing Ltd.",
    "wof:placetype":"venue"
},
  "geometry": {"coordinates":[-0.1829530001,51.6539802551],"type":"Point"}
}