{
  "type": "Feature",
  "properties": {
    "addr:full":"16 Central Avenue, Parkstone Poole Dorset BH12 2ER",
    "addr:housenumber":"16",
    "addr:postcode":"bh12 2er",
    "addr:street":"Central Avenue",
    "iso:country":"GB",
    "sg:address":"16 Central Avenue, Parkstone",
    "sg:city":"Poole",
    "sg:classifiers":[
        {
            "category":"Home & Garden",
            "subcategory":"Furniture",
            "type":"Retail Goods"
        }
    ],
    "sg:phone":"+44 1202 740003",
    "sg:postcode":"BH12 2ER",
    "sg:province":"Dorset",
    "wof:name":"Paul Thompson",
    "wof:placetype":"venue"
},
  "geometry": {"coordinates":[-1.924759984,50.7352218628],"type":"Point"}
}