{
  "type": "Feature",
  "properties": {
    "addr:full":"Hurstbourne Park Whitchurch Hampshire RG28 7RN",
    "addr:postcode":"rg28 7rn",
    "addr:street":"Hurstbourne Park",
    "iso:country":"GB",
    "sg:address":"Hurstbourne Park",
    "sg:city":"Whitchurch",
    "sg:classifiers":[
        {
            "category":"Shopping",
            "subcategory":"Clothing, Apparel, & Fashions",
            "type":"Retail Goods"
        }
    ],
    "sg:postcode":"RG28 7RN",
    "sg:province":"Hampshire",
    "sg:tags":[
        "ladieswear"
    ],
    "wof:name":"The Pump House",
    "wof:placetype":"venue"
},
  "geometry": {"coordinates":[-1.338904,51.22979],"type":"Point"}
}