{
  "type": "Feature",
  "properties": {
    "iso:country":"GB",
    "sg:address":"3 Nuffield Clo",
    "sg:city":"Cambridge",
    "sg:classifiers":[
        {
            "category":"Manufacturing",
            "subcategory":"Petroleum Products",
            "type":"Manufacturing & Wholesale Goods"
        }
    ],
    "sg:phone":"+44 1223 426742",
    "sg:postcode":"CB4 1SS",
    "sg:province":"Cambridgeshire",
    "sg:tags":[
        "double",
        "glazing"
    ],
    "wof:name":"Abacus Windows",
    "wof:placetype":"venue"
},
  "geometry": {"coordinates":[0.1522690058,52.2279319763],"type":"Point"}
}