{
  "type": "Feature",
  "properties": {
    "iso:country":"GB",
    "sg:address":"81 North Rd",
    "sg:city":"Brighton",
    "sg:classifiers":[
        {
            "category":"Fast Food",
            "type":"Food & Drink"
        }
    ],
    "sg:postcode":"BN1 1YD",
    "sg:province":"East Sussex",
    "sg:tags":[
        "away",
        "take"
    ],
    "wof:name":"Movahed,Mahamed,",
    "wof:placetype":"venue"
},
  "geometry": {"coordinates":[-0.139355,50.825733],"type":"Point"}
}