{
  "type": "Feature",
  "properties": {
    "addr:full":"39 Cranbrook Road Ilford Essex IG1 4PA",
    "addr:housenumber":"39",
    "addr:postcode":"ig1 4pa",
    "addr:street":"Cranbrook Road",
    "iso:country":"GB",
    "sg:address":"39 Cranbrook Road",
    "sg:city":"Ilford",
    "sg:classifiers":[
        {
            "category":"Health Services",
            "subcategory":"Dentist",
            "type":"Services"
        }
    ],
    "sg:phone":"+44 20 8478 1150",
    "sg:postcode":"IG1 4PA",
    "sg:province":"Essex",
    "wof:name":"Lambert Surgery",
    "wof:placetype":"venue"
},
  "geometry": {"coordinates":[0.0698349997,51.5597877502],"type":"Point"}
}