{
  "type": "Feature",
  "properties": {
    "addr:full":"Bethesda Street Burnley Lancashire BB11 1PR",
    "addr:postcode":"bb11 1pr",
    "addr:street":"Bethesda Street",
    "iso:country":"GB",
    "sg:address":"Bethesda Street",
    "sg:city":"Burnley",
    "sg:classifiers":[
        {
            "category":"Bars & Pubs",
            "subcategory":"Nightclub",
            "type":"Food & Drink"
        }
    ],
    "sg:phone":"+44 1282 412288",
    "sg:postcode":"BB11 1PR",
    "sg:province":"Lancashire",
    "sg:tags":[
        "club",
        "night"
    ],
    "wof:name":"V I P's Nightclub",
    "wof:placetype":"venue"
},
  "geometry": {"coordinates":[-2.2455360889,53.7900390625],"type":"Point"}
}