{
  "type": "Feature",
  "properties": {
    "addr:full":"Sannox Brodick North Ayrshire KA27 8JD",
    "addr:postcode":"ka27 8jd",
    "iso:country":"GB",
    "sg:address":"Sannox",
    "sg:city":"Brodick",
    "sg:classifiers":[
        {
            "category":"Sports & Exercise",
            "subcategory":"Golf",
            "type":"Entertainment"
        }
    ],
    "sg:phone":"+44 1770 810223",
    "sg:postcode":"KA27 8JD",
    "sg:province":"North Ayrshire",
    "sg:tags":[
        "club",
        "course"
    ],
    "wof:name":"Corrie Golf Club",
    "wof:placetype":"venue"
},
  "geometry": {"coordinates":[-5.1523189545,55.5775756836],"type":"Point"}
}