{
  "type": "Feature",
  "properties": {
    "iso:country":"GB",
    "sg:address":"Liverpool Rd",
    "sg:city":"Manchester",
    "sg:classifiers":[
        {
            "category":"Place Of Worship",
            "type":"Public Place"
        }
    ],
    "sg:phone":"+44 161 775 2294",
    "sg:postcode":"M44 6DP",
    "sg:province":"Greater Manchester",
    "wof:name":"St Pauls Methodist Church",
    "wof:placetype":"venue"
},
  "geometry": {"coordinates":[-2.402097,53.456161],"type":"Point"}
}