{
  "type": "Feature",
  "properties": {
    "iso:country":"GB",
    "sg:address":"38-39 Reddal Hill Road",
    "sg:city":"Smethwick",
    "sg:classifiers":[
        {
            "category":"Home & Garden",
            "subcategory":"Furniture",
            "type":"Retail Goods"
        }
    ],
    "sg:phone":"+44 1384 635157",
    "sg:postcode":"B64 5JN",
    "sg:province":"West Midlands",
    "wof:name":"The Fitted Wardrobe Shop",
    "wof:placetype":"venue"
},
  "geometry": {"coordinates":[-2.07395,52.476292],"type":"Point"}
}