{
  "type": "Feature",
  "properties": {
    "addr:full":"84 Avon Crescent, Brockworth Gloucester Gloucestershire GL3 4LQ",
    "addr:housenumber":"84",
    "addr:postcode":"gl3 4lq",
    "addr:street":"Avon Crescent",
    "iso:country":"GB",
    "sg:address":"84 Avon Crescent, Brockworth",
    "sg:city":"Gloucester",
    "sg:classifiers":[
        {
            "category":"Personal",
            "type":"Services"
        }
    ],
    "sg:phone":"+44 1452 552061",
    "sg:postcode":"GL3 4LQ",
    "sg:province":"Gloucestershire",
    "sg:tags":[
        "wedding"
    ],
    "wof:name":"Stephanie Old",
    "wof:placetype":"venue"
},
  "geometry": {"coordinates":[-2.1466429234,51.8454284668],"type":"Point"}
}