{
  "type": "Feature",
  "properties": {
    "addr:full":"174 High Street Rochester Kent ME1 1EX",
    "addr:housenumber":"174",
    "addr:postcode":"me1 1ex",
    "addr:street":"High Street",
    "iso:country":"GB",
    "sg:address":"174 High Street",
    "sg:city":"Rochester",
    "sg:classifiers":[
        {
            "category":"Home & Garden",
            "subcategory":"Household Appliances",
            "type":"Retail Goods"
        },
        {
            "category":"Home & Garden",
            "subcategory":"Kitchen Supply",
            "type":"Retail Goods"
        }
    ],
    "sg:phone":"+44 1634 847936",
    "sg:postcode":"ME1 1EX",
    "sg:province":"Kent",
    "sg:tags":[
        "ware",
        "kitchenware"
    ],
    "wof:name":"Pastures New Ltd.",
    "wof:placetype":"venue"
},
  "geometry": {"coordinates":[0.458828,51.350796],"type":"Point"}
}