{
  "type": "Feature",
  "properties": {
    "addr:full":"209a High St, Cheriton Folkestone Kent CT19 4HW",
    "addr:housenumber":"209a",
    "addr:postcode":"ct19 4hw",
    "addr:street":"High St",
    "iso:country":"GB",
    "sg:address":"209a High St, Cheriton",
    "sg:city":"Folkestone",
    "sg:classifiers":[
        {
            "category":"Shopping",
            "subcategory":"News",
            "type":"Retail Goods"
        }
    ],
    "sg:phone":"+44 1303 275791",
    "sg:postcode":"CT19 4HW",
    "sg:province":"Kent",
    "sg:tags":[
        "newsagent"
    ],
    "wof:name":"D News",
    "wof:placetype":"venue"
},
  "geometry": {"coordinates":[1.137691,51.087254],"type":"Point"}
}