{
  "type": "Feature",
  "properties": {
    "addr:full":"30 Myrtle Crescent, Bilston Roslin Midlothian EH25 9SF",
    "addr:housenumber":"30",
    "addr:postcode":"eh25 9sf",
    "addr:street":"Myrtle Crescent",
    "iso:country":"GB",
    "sg:address":"30 Myrtle Crescent, Bilston",
    "sg:city":"Roslin",
    "sg:classifiers":[
        {
            "category":"Building & Trades",
            "subcategory":"Plumbing",
            "type":"Services"
        }
    ],
    "sg:phone":"+44 131 440 1873",
    "sg:postcode":"EH25 9SF",
    "sg:province":"Midlothian",
    "sg:tags":[
        "plumber",
        "heating"
    ],
    "wof:name":"G & M Plumbers",
    "wof:placetype":"venue"
},
  "geometry": {"coordinates":[-3.1797049046,55.8703804016],"type":"Point"}
}