{
  "type": "Feature",
  "properties": {
    "iso:country":"GB",
    "sg:address":"434 London Road",
    "sg:city":"Portsmouth",
    "sg:classifiers":[
        {
            "category":"Cafe",
            "type":"Food & Drink"
        }
    ],
    "sg:phone":"+44 23 9269 7915",
    "sg:postcode":"PO2 9LD",
    "sg:province":"Hampshire",
    "sg:tags":[
        "tea",
        "room"
    ],
    "wof:name":"Eves Too Cafe",
    "wof:placetype":"venue"
},
  "geometry": {"coordinates":[-1.072512,50.825718],"type":"Point"}
}