{
  "type": "Feature",
  "properties": {
    "addr:full":"472 Hessle Road Hull East Riding of Yorkshire HU3 3LD",
    "addr:housenumber":"472",
    "addr:postcode":"hu3 3ld",
    "addr:street":"Hessle Road",
    "iso:country":"GB",
    "sg:address":"472 Hessle Road",
    "sg:city":"Hull",
    "sg:classifiers":[
        {
            "category":"Professional",
            "subcategory":"Computer Services",
            "type":"Services"
        }
    ],
    "sg:phone":"+44 1482 322676",
    "sg:postcode":"HU3 3LD",
    "sg:province":"East Riding of Yorkshire",
    "sg:tags":[
        "system",
        "software"
    ],
    "wof:name":"Memory Warehouse Ltd.",
    "wof:placetype":"venue"
},
  "geometry": {"coordinates":[-0.372891,53.734203],"type":"Point"}
}