{
  "type": "Feature",
  "properties": {
    "addr:full":"26 St James Mall Hebburn Tyne and Wear NE31 1LS",
    "addr:housenumber":"26",
    "addr:postcode":"ne31 1ls",
    "addr:street":"St James Mall",
    "iso:country":"GB",
    "sg:address":"26 St James Mall",
    "sg:city":"Hebburn",
    "sg:classifiers":[
        {
            "category":"Food & Beverages",
            "subcategory":"Meat & Fish",
            "type":"Retail Goods"
        }
    ],
    "sg:phone":"+44 191 483 5385",
    "sg:postcode":"NE31 1LS",
    "sg:province":"Tyne and Wear",
    "sg:tags":[
        "butcher"
    ],
    "wof:name":"A & P Thompson",
    "wof:placetype":"venue"
},
  "geometry": {"coordinates":[-1.511698,54.97385],"type":"Point"}
}