{
  "type": "Feature",
  "properties": {
    "iso:country":"GB",
    "sg:address":"7-12 Leinster Square",
    "sg:city":"Bayswater",
    "sg:classifiers":[
        {
            "category":"Travel",
            "subcategory":"Hostel",
            "type":"Entertainment"
        }
    ],
    "sg:phone":"+44 20 7229 9641",
    "sg:postcode":"W2 4PP",
    "sg:province":"Greater London",
    "sg:tags":[
        "youth"
    ],
    "wof:name":"Leinster Hotel",
    "wof:placetype":"venue"
},
  "geometry": {"coordinates":[-0.192949,51.514198],"type":"Point"}
}