{
  "type": "Feature",
  "properties": {
    "iso:country":"GB",
    "sg:address":"34 Egerton Street, Farnworth",
    "sg:city":"Bolton",
    "sg:classifiers":[
        {
            "category":"Home & Garden",
            "subcategory":"Household Appliances",
            "type":"Retail Goods"
        }
    ],
    "sg:phone":"+44 1204 709259",
    "sg:postcode":"BL4 7LE",
    "sg:province":"Lancashire",
    "sg:tags":[
        "electrical"
    ],
    "wof:name":"L S Domestics",
    "wof:placetype":"venue"
},
  "geometry": {"coordinates":[-2.401781,53.554913],"type":"Point"}
}