{
  "type": "Feature",
  "properties": {
    "iso:country":"GB",
    "sg:address":"4 Cooper House, Ravens Lane",
    "sg:city":"Berkhamsted",
    "sg:classifiers":[
        {
            "category":"Retail",
            "subcategory":"Storage",
            "type":"Services"
        }
    ],
    "sg:phone":"+44 1442 875900",
    "sg:postcode":"HP4 2DX",
    "sg:province":"Bedfordshire",
    "sg:tags":[
        "recording",
        "equipment"
    ],
    "wof:name":"Harrison By GLW",
    "wof:placetype":"venue"
},
  "geometry": {"coordinates":[-0.564559,51.760414],"type":"Point"}
}