{
  "type": "Feature",
  "properties": {
    "addr:full":"3 Church Street Launceston Cornwall PL15 8AW",
    "addr:housenumber":"3",
    "addr:postcode":"pl15 8aw",
    "addr:street":"Church Street",
    "iso:country":"GB",
    "sg:address":"3 Church Street",
    "sg:city":"Launceston",
    "sg:classifiers":[
        {
            "category":"Shopping",
            "subcategory":"Pets & Pet Supplies",
            "type":"Retail Goods"
        }
    ],
    "sg:phone":"+44 1566 773494",
    "sg:postcode":"PL15 8AW",
    "sg:province":"Cornwall",
    "wof:name":"Castle Pet Supplies",
    "wof:placetype":"venue"
},
  "geometry": {"coordinates":[-4.360296,50.637581],"type":"Point"}
}