{
  "type": "Feature",
  "properties": {
    "iso:country":"GB",
    "sg:address":"20 Ditchfield Road",
    "sg:city":"Widnes",
    "sg:classifiers":[
        {
            "category":"Health Services",
            "subcategory":"Doctor",
            "type":"Services"
        }
    ],
    "sg:postcode":"WA8 8QS",
    "sg:province":"Cheshire",
    "sg:tags":[
        "practitioners"
    ],
    "wof:name":"The Beeches Medical Centre",
    "wof:placetype":"venue"
},
  "geometry": {"coordinates":[-2.764937,53.363338],"type":"Point"}
}