{
  "type": "Feature",
  "properties": {
    "iso:country":"GB",
    "sg:address":"58 Camden Lock Place, Camden",
    "sg:city":"London",
    "sg:classifiers":[
        {
            "category":"Recreation",
            "subcategory":"Boat Charter",
            "type":"Entertainment"
        }
    ],
    "sg:phone":"+44 20 7482 2550",
    "sg:postcode":"NW1 8AF",
    "sg:province":"Greater London",
    "sg:tags":[
        "excursion"
    ],
    "wof:name":"London Waterbus Co.",
    "wof:placetype":"venue"
},
  "geometry": {"coordinates":[-0.1465850025,51.5412750244],"type":"Point"}
}