{
  "type": "Feature",
  "properties": {
    "addr:full":"2 Wellesley Rd Wanstead Greater London E11 2HF",
    "addr:housenumber":"2",
    "addr:postcode":"e11 2hf",
    "addr:street":"Wellesley Rd",
    "iso:country":"GB",
    "sg:address":"2 Wellesley Rd",
    "sg:city":"Wanstead",
    "sg:classifiers":[
        {
            "category":"Food & Beverages",
            "subcategory":"Groceries & Convenience Stores",
            "type":"Retail Goods"
        }
    ],
    "sg:phone":"+44 181 989 2866",
    "sg:postcode":"E11 2HF",
    "sg:province":"Greater London",
    "wof:name":"Toms",
    "wof:placetype":"venue"
},
  "geometry": {"coordinates":[0.0239279997,51.580493927],"type":"Point"}
}