{
  "type": "Feature",
  "properties": {
    "addr:full":"Wherry House, 300 St Faiths Road, Old Catton Norwich Norfolk NR6 7BJ",
    "addr:housenumber":"300",
    "addr:postcode":"nr6 7bj",
    "addr:street":"St Faiths Road",
    "iso:country":"GB",
    "sg:address":"Wherry House, 300 St Faiths Road, Old Catton",
    "sg:city":"Norwich",
    "sg:classifiers":[
        {
            "category":"Social Services",
            "subcategory":"Adult Care",
            "type":"Services"
        }
    ],
    "sg:phone":"+44 1603 787822",
    "sg:postcode":"NR6 7BJ",
    "sg:province":"Norfolk",
    "sg:tags":[
        "housing",
        "sheltered"
    ],
    "wof:name":"Wherry Housing Association Ltd.",
    "wof:placetype":"venue"
},
  "geometry": {"coordinates":[1.296157,52.667084],"type":"Point"}
}