{
  "type": "Feature",
  "properties": {
    "iso:country":"GB",
    "sg:address":"60 Gro Street",
    "sg:city":"Wilmslow",
    "sg:classifiers":[
        {
            "category":"Organizations",
            "subcategory":"Non-profit Organization",
            "type":"Services"
        }
    ],
    "sg:phone":"+44 1625 528926",
    "sg:postcode":"SK9 1DS",
    "sg:province":"Cheshire",
    "sg:tags":[
        "charitable",
        "organisation",
        "voluntary",
        "charity"
    ],
    "wof:name":"British Heart Foundation",
    "wof:placetype":"venue"
},
  "geometry": {"coordinates":[-2.232401,53.32642],"type":"Point"}
}