{
  "type": "Feature",
  "properties": {
    "iso:country":"GB",
    "sg:address":"94 Leyland Rd, Penwortham",
    "sg:city":"Preston",
    "sg:classifiers":[
        {
            "category":"Communications",
            "type":"Services"
        }
    ],
    "sg:postcode":"PR1 9QJ",
    "sg:province":"Lancashire",
    "sg:tags":[
        "tv",
        "video",
        "radio"
    ],
    "wof:name":"Direct Aerial Supplies",
    "wof:placetype":"venue"
},
  "geometry": {"coordinates":[-2.712237,53.745346],"type":"Point"}
}