{
  "type": "Feature",
  "properties": {
    "addr:full":"6 Seath Rd Glasgow Glasgow City G73 1RW",
    "addr:housenumber":"6",
    "addr:postcode":"g73 1rw",
    "addr:street":"Seath Rd",
    "iso:country":"GB",
    "sg:address":"6 Seath Rd",
    "sg:city":"Glasgow",
    "sg:classifiers":[
        {
            "category":"Professional",
            "subcategory":"Detective & Security Services",
            "type":"Services"
        }
    ],
    "sg:phone":"+44 141 647 9437",
    "sg:postcode":"G73 1RW",
    "sg:province":"Glasgow City",
    "wof:name":"Guarda Security (Scotland) Ltd",
    "wof:placetype":"venue"
},
  "geometry": {"coordinates":[-4.2179160118,55.8334579468],"type":"Point"}
}