{
  "type": "Feature",
  "properties": {
    "addr:full":"17 Hill Clo Barnet Hertfordshire EN5 3AG",
    "addr:housenumber":"17",
    "addr:postcode":"en5 3ag",
    "addr:street":"Hill Clo",
    "iso:country":"GB",
    "sg:address":"17 Hill Clo",
    "sg:city":"Barnet",
    "sg:classifiers":[
        {
            "category":"Sports & Exercise",
            "subcategory":"Tennis Court",
            "type":"Entertainment"
        }
    ],
    "sg:phone":"+44 20 8447 0438",
    "sg:postcode":"EN5 3AG",
    "sg:province":"Hertfordshire",
    "sg:tags":[
        "breakdown",
        "recovery"
    ],
    "wof:name":"Vehicle Recovery Service",
    "wof:placetype":"venue"
},
  "geometry": {"coordinates":[-0.2203299999,51.6467247009],"type":"Point"}
}