{
  "type": "Feature",
  "properties": {
    "addr:full":"191 Victoria Street London Greater London SW1E 5NE",
    "addr:housenumber":"191",
    "addr:postcode":"sw1e 5ne",
    "addr:street":"Victoria Street",
    "iso:country":"GB",
    "sg:address":"191 Victoria Street",
    "sg:city":"London",
    "sg:classifiers":[
        {
            "category":"Banks & Credit Unions",
            "subcategory":"Bank",
            "type":"Services"
        }
    ],
    "sg:phone":"+44 20 7630 8955",
    "sg:postcode":"SW1E 5NE",
    "sg:province":"Greater London",
    "wof:name":"Pastor S A Banco",
    "wof:placetype":"venue"
},
  "geometry": {"coordinates":[-0.1438080072,51.4965705872],"type":"Point"}
}