{
  "type": "Feature",
  "properties": {
    "addr:full":"Grange Farm, Cross Moor Lane, Haxby York North Yorkshire YO32 2QR",
    "addr:postcode":"yo32 2qr",
    "addr:street":"Cross Moor Lane",
    "iso:country":"GB",
    "sg:address":"Grange Farm, Cross Moor Lane, Haxby",
    "sg:city":"York",
    "sg:classifiers":[
        {
            "category":"Retail",
            "subcategory":"Auto Repair",
            "type":"Services"
        }
    ],
    "sg:phone":"+44 1904 766613",
    "sg:postcode":"YO32 2QR",
    "sg:province":"North Yorkshire",
    "sg:tags":[
        "modification",
        "garage"
    ],
    "wof:name":"G W Motor Engineers",
    "wof:placetype":"venue"
},
  "geometry": {"coordinates":[-1.0697499514,54.031539917],"type":"Point"}
}