{
  "type": "Feature",
  "properties": {
    "addr:full":"John O'gaunts Service Station, Leeds Road Leeds West Yorkshire LS26 0JF",
    "addr:postcode":"ls26 0jf",
    "addr:street":"Leeds Road",
    "iso:country":"GB",
    "sg:address":"John O'gaunts Service Station, Leeds Road",
    "sg:city":"Leeds",
    "sg:classifiers":[
        {
            "category":"Retail",
            "subcategory":"Auto Repair",
            "type":"Services"
        }
    ],
    "sg:postcode":"LS26 0JF",
    "sg:province":"West Yorkshire",
    "sg:tags":[
        "modification",
        "garage"
    ],
    "wof:name":"J S Auto Repairs",
    "wof:placetype":"venue"
},
  "geometry": {"coordinates":[-1.4773900509,53.7580986023],"type":"Point"}
}