{
  "type": "Feature",
  "properties": {
    "addr:full":"36 Manor Way Lee-on-the-solent Hampshire PO13 9JH",
    "addr:housenumber":"36",
    "addr:postcode":"po13 9jh",
    "addr:street":"Manor Way",
    "iso:country":"GB",
    "sg:address":"36 Manor Way",
    "sg:city":"Lee-on-the-solent",
    "sg:classifiers":[
        {
            "category":"Bars & Pubs",
            "type":"Food & Drink"
        }
    ],
    "sg:phone":"+44 23 9255 0214",
    "sg:postcode":"PO13 9JH",
    "sg:province":"Hampshire",
    "sg:tags":[
        "pubs",
        "inn"
    ],
    "wof:name":"The Bun Penny",
    "wof:placetype":"venue"
},
  "geometry": {"coordinates":[-1.200263,50.804222],"type":"Point"}
}