{
  "type": "Feature",
  "properties": {
    "addr:full":"Village Green, Inkberrow Worcester Worcestershire WR7 4DZ",
    "addr:postcode":"wr7 4dz",
    "iso:country":"GB",
    "sg:address":"Village Green, Inkberrow",
    "sg:city":"Worcester",
    "sg:classifiers":[
        {
            "category":"Professional",
            "subcategory":"Detective & Security Services",
            "type":"Services"
        }
    ],
    "sg:phone":"+44 1386 792522",
    "sg:postcode":"WR7 4DZ",
    "sg:province":"Worcestershire",
    "wof:name":"Specialised Security Systems Ltd.",
    "wof:placetype":"venue"
},
  "geometry": {"coordinates":[-1.9805569649,52.2132301331],"type":"Point"}
}