{
  "type": "Feature",
  "properties": {
    "addr:full":"358 Stag La Colindale Greater London NW9 9AG",
    "addr:housenumber":"358",
    "addr:postcode":"nw9 9ag",
    "addr:street":"Stag La Colindale",
    "iso:country":"GB",
    "sg:address":"358 Stag La",
    "sg:city":"Colindale",
    "sg:classifiers":[
        {
            "category":"Professional",
            "subcategory":"Engineering",
            "type":"Services"
        }
    ],
    "sg:phone":"+44 20 8204 1474",
    "sg:postcode":"NW9 9AG",
    "sg:province":"Greater London",
    "sg:tags":[
        "contractor",
        "electrical",
        "engineer"
    ],
    "wof:name":"A & V Electrical",
    "wof:placetype":"venue"
},
  "geometry": {"coordinates":[-0.2660489976,51.5899200439],"type":"Point"}
}