{
  "type": "Feature",
  "properties": {
    "iso:country":"GB",
    "sg:address":"100 Drake Street",
    "sg:city":"Rochdale",
    "sg:classifiers":[
        {
            "category":"Shopping",
            "subcategory":"Antiques",
            "type":"Retail Goods"
        }
    ],
    "sg:phone":"+44 1706 648114",
    "sg:postcode":"OL16 1PQ",
    "sg:province":"Lancashire",
    "wof:name":"Antiques & Bygones",
    "wof:placetype":"venue"
},
  "geometry": {"coordinates":[-2.1538770199,53.6145362854],"type":"Point"}
}