{
  "type": "Feature",
  "properties": {
    "iso:country":"GB",
    "sg:address":"2 Westfield Rd",
    "sg:city":"Budleigh Salterton",
    "sg:classifiers":[
        {
            "category":"Social Services",
            "subcategory":"Retirement Home",
            "type":"Services"
        }
    ],
    "sg:phone":"+44 1395 443670",
    "sg:postcode":"EX9 6SS",
    "sg:province":"Devon",
    "sg:tags":[
        "residential",
        "care"
    ],
    "wof:name":"Westfield House",
    "wof:placetype":"venue"
},
  "geometry": {"coordinates":[-3.327454,50.631233],"type":"Point"}
}