{
  "type": "Feature",
  "properties": {
    "addr:full":"100 Liverpool Road South, Maghull Liverpool Lancashire L31 7AG",
    "addr:housenumber":"100",
    "addr:postcode":"l31 7ag",
    "addr:street":"Liverpool Road South",
    "iso:country":"GB",
    "sg:address":"100 Liverpool Road South, Maghull",
    "sg:city":"Liverpool",
    "sg:classifiers":[
        {
            "category":"Insurance",
            "subcategory":"Insurance Agent",
            "type":"Services"
        }
    ],
    "sg:postcode":"L31 7AG",
    "sg:province":"Lancashire",
    "wof:name":"Swinton",
    "wof:placetype":"venue"
},
  "geometry": {"coordinates":[-2.946283102,53.5059280396],"type":"Point"}
}