{
  "type": "Feature",
  "properties": {
    "addr:full":"211 City Road, Roath Cardiff Cardiff CF24 3JD",
    "addr:housenumber":"211",
    "addr:postcode":"cf24 3jd",
    "addr:street":"City Road",
    "iso:country":"GB",
    "sg:address":"211 City Road, Roath",
    "sg:city":"Cardiff",
    "sg:classifiers":[
        {
            "category":"Professional",
            "type":"Services"
        }
    ],
    "sg:phone":"+44 29 2047 0473",
    "sg:postcode":"CF24 3JD",
    "sg:province":"Cardiff",
    "sg:tags":[
        "directory",
        "pub"
    ],
    "wof:name":"Andrew Summers",
    "wof:placetype":"venue"
},
  "geometry": {"coordinates":[-3.171381,51.49173],"type":"Point"}
}