{
  "type": "Feature",
  "properties": {
    "addr:full":"St John's Chambers, Love Street Chester Cheshire CH1 1QN",
    "addr:postcode":"ch1 1qn",
    "addr:street":"Love Street",
    "iso:country":"GB",
    "sg:address":"St John's Chambers, Love Street",
    "sg:city":"Chester",
    "sg:classifiers":[
        {
            "category":"Real Estate",
            "subcategory":"Developer",
            "type":"Services"
        }
    ],
    "sg:phone":"+44 151 652 7170",
    "sg:postcode":"CH1 1QN",
    "sg:province":"Cheshire",
    "sg:tags":[
        "property"
    ],
    "wof:name":"Powells Orchard Ltd.",
    "wof:placetype":"venue"
},
  "geometry": {"coordinates":[-2.88447,53.19046],"type":"Point"}
}