{
  "type": "Feature",
  "properties": {
    "iso:country":"GB",
    "sg:address":"51 Norton Hill Drive",
    "sg:city":"Coventry",
    "sg:classifiers":[
        {
            "category":"Social Services",
            "subcategory":"Job Training",
            "type":"Services"
        }
    ],
    "sg:phone":"+44 24 7677 4527",
    "sg:postcode":"CV2 3AX",
    "sg:province":"Warwickshire",
    "sg:tags":[
        "translator",
        "interpreter"
    ],
    "wof:name":"Global Translations",
    "wof:placetype":"venue"
},
  "geometry": {"coordinates":[-1.452983,52.423031],"type":"Point"}
}