{
  "type": "Feature",
  "properties": {
    "iso:country":"GB",
    "sg:address":"Ty Cerrig, Llewelyn Rd",
    "sg:city":"Wrexham",
    "sg:classifiers":[
        {
            "category":"Farming",
            "subcategory":"Livestock Farm",
            "type":"Manufacturing & Wholesale Goods"
        }
    ],
    "sg:phone":"+44 1978 758980",
    "sg:postcode":"LL11 5TL",
    "sg:province":"Wrexham",
    "sg:tags":[
        "others"
    ],
    "wof:name":"R & B E Wilkins & Son",
    "wof:placetype":"venue"
},
  "geometry": {"coordinates":[-3.05855,53.063419],"type":"Point"}
}