{
  "type": "Feature",
  "properties": {
    "iso:country":"GB",
    "sg:address":"High Green",
    "sg:city":"Norwich",
    "sg:classifiers":[
        {
            "category":"Freight",
            "type":"Transportation"
        }
    ],
    "sg:phone":"+44 1379 677200",
    "sg:postcode":"NR15 2HU",
    "sg:province":"Norfolk",
    "sg:tags":[
        "haulage",
        "road"
    ],
    "wof:name":"Heather Haulage",
    "wof:placetype":"venue"
},
  "geometry": {"coordinates":[1.18657,52.462971],"type":"Point"}
}