{
  "type": "Feature",
  "properties": {
    "iso:country":"GB",
    "sg:address":"Hamble Point Marina, School Lane, Hamble",
    "sg:city":"Southampton",
    "sg:classifiers":[
        {
            "category":"Autos & Motor Vehicles",
            "subcategory":"Boat Sales",
            "type":"Retail Goods"
        }
    ],
    "sg:phone":"+44 23 8045 6482",
    "sg:postcode":"SO31 4HB",
    "sg:province":"Hampshire",
    "sg:tags":[
        "equipment"
    ],
    "wof:name":"Performance Rigging",
    "wof:placetype":"venue"
},
  "geometry": {"coordinates":[-1.317763,50.86026],"type":"Point"}
}