{
  "type": "Feature",
  "properties": {
    "addr:full":"Rear Of 236 City Rd Cardiff Cardiff CF2 3JJ",
    "addr:postcode":"cf2 3jj",
    "addr:street":"City Rd",
    "iso:country":"GB",
    "sg:address":"Rear Of 236 City Rd",
    "sg:city":"Cardiff",
    "sg:classifiers":[
        {
            "category":"Home & Garden",
            "subcategory":"Building Materials",
            "type":"Retail Goods"
        }
    ],
    "sg:phone":"+44 29 2048 8725",
    "sg:postcode":"CF2 3JJ",
    "sg:province":"Cardiff",
    "sg:tags":[
        "ironwork",
        "diy",
        "wrought"
    ],
    "wof:name":"Wrought Iron Fabricators",
    "wof:placetype":"venue"
},
  "geometry": {"coordinates":[-3.18067,51.481258],"type":"Point"}
}