{
  "type": "Feature",
  "properties": {
    "addr:full":"62 Whitchurch Rd Manchester Greater Manchester M20 1EY",
    "addr:housenumber":"62",
    "addr:postcode":"m20 1ey",
    "addr:street":"Whitchurch Rd",
    "iso:country":"GB",
    "sg:address":"62 Whitchurch Rd",
    "sg:city":"Manchester",
    "sg:classifiers":[
        {
            "category":"Health Services",
            "subcategory":"Clinic",
            "type":"Services"
        }
    ],
    "sg:phone":"+44 161 445 5907",
    "sg:postcode":"M20 1EY",
    "sg:province":"Greater Manchester",
    "sg:tags":[
        "private"
    ],
    "wof:name":"Borchardt Medical Centre",
    "wof:placetype":"venue"
},
  "geometry": {"coordinates":[-2.237621,53.434216],"type":"Point"}
}