{
  "type": "Feature",
  "properties": {
    "addr:full":"Stuart Terrace, Talbot Green Pontyclun Bridgend CF72 8AA",
    "addr:postcode":"cf72 8aa",
    "addr:street":"Stuart Terrace",
    "iso:country":"GB",
    "sg:address":"Stuart Terrace, Talbot Green",
    "sg:city":"Pontyclun",
    "sg:classifiers":[
        {
            "category":"Education",
            "subcategory":"School",
            "type":"Public Place"
        },
        {
            "category":"Government",
            "subcategory":"Office",
            "type":"Public Place"
        }
    ],
    "sg:phone":"+44 1443 237953",
    "sg:postcode":"CF72 8AA",
    "sg:province":"Bridgend",
    "sg:tags":[
        "local",
        "authority"
    ],
    "wof:name":"Tonysguboriau Primary School",
    "wof:placetype":"venue"
},
  "geometry": {"coordinates":[-3.3866839409,51.5363883972],"type":"Point"}
}