{
  "type": "Feature",
  "properties": {
    "iso:country":"GB",
    "sg:address":"28a Veryan Pl",
    "sg:city":"Milton Keynes",
    "sg:classifiers":[
        {
            "category":"Arts & Performance",
            "subcategory":"Music",
            "type":"Entertainment"
        }
    ],
    "sg:phone":"+44 1908 667870",
    "sg:postcode":"MK6 2DH",
    "sg:province":"Buckinghamshire",
    "sg:tags":[
        "mobile",
        "disco"
    ],
    "wof:name":"J K T",
    "wof:placetype":"venue"
},
  "geometry": {"coordinates":[-0.740231,52.037556],"type":"Point"}
}