{
  "type": "Feature",
  "properties": {
    "addr:full":"Mytton Oak Road Shrewsbury Shropshire SY3 8UG",
    "addr:postcode":"sy3 8ug",
    "addr:street":"Mytton Oak Road",
    "iso:country":"GB",
    "sg:address":"Mytton Oak Road",
    "sg:city":"Shrewsbury",
    "sg:classifiers":[
        {
            "category":"Government",
            "subcategory":"Post Office",
            "type":"Public Place"
        }
    ],
    "sg:phone":"+44 1743 344333",
    "sg:postcode":"SY3 8UG",
    "sg:province":"Shropshire",
    "wof:name":"Copthorne Post Office",
    "wof:placetype":"venue"
},
  "geometry": {"coordinates":[-2.7934439182,52.7067718506],"type":"Point"}
}