{
  "type": "Feature",
  "properties": {
    "addr:full":"Station Road Redhill Surrey RH1 1NZ",
    "addr:postcode":"rh1 1nz",
    "addr:street":"Station Road",
    "iso:country":"GB",
    "sg:address":"Station Road",
    "sg:city":"Redhill",
    "sg:classifiers":[
        {
            "category":"Recreation",
            "subcategory":"Dance Hall",
            "type":"Entertainment"
        }
    ],
    "sg:phone":"+44 1737 764226",
    "sg:postcode":"RH1 1NZ",
    "sg:province":"Surrey",
    "sg:tags":[
        "disco"
    ],
    "wof:name":"Kingfisher Leisure Operations Ltd.",
    "wof:placetype":"venue"
},
  "geometry": {"coordinates":[-0.1694390029,51.2404518127],"type":"Point"}
}