{
  "type": "Feature",
  "properties": {
    "addr:full":"107 Chandag Road, Keynsham Bristol City of Bristol BS31 1QE",
    "addr:housenumber":"107",
    "addr:postcode":"bs31 1qe",
    "addr:street":"Chandag Road",
    "iso:country":"GB",
    "sg:address":"107 Chandag Road, Keynsham",
    "sg:city":"Bristol",
    "sg:classifiers":[
        {
            "category":"Retail",
            "subcategory":"Repair Shop",
            "type":"Services"
        }
    ],
    "sg:postcode":"BS31 1QE",
    "sg:province":"City of Bristol",
    "sg:tags":[
        "radio",
        "television",
        "video"
    ],
    "wof:name":"Derek Farler",
    "wof:placetype":"venue"
},
  "geometry": {"coordinates":[-2.4893438816,51.4065704346],"type":"Point"}
}