{
  "type": "Feature",
  "properties": {
    "addr:full":"Cock Farm, Spa Lane, Lathom Ormskirk Lancashire L40 6JQ",
    "addr:postcode":"l40 6jq",
    "addr:street":"Spa Lane",
    "iso:country":"GB",
    "sg:address":"Cock Farm, Spa Lane, Lathom",
    "sg:city":"Ormskirk",
    "sg:classifiers":[
        {
            "category":"Home & Garden",
            "subcategory":"Home Furnishings",
            "type":"Retail Goods"
        },
        {
            "category":"Manufacturing",
            "subcategory":"Furniture",
            "type":"Manufacturing & Wholesale Goods"
        }
    ],
    "sg:phone":"+44 1695 732315",
    "sg:postcode":"L40 6JQ",
    "sg:province":"Lancashire",
    "sg:tags":[
        "manufacture",
        "mnfr",
        "patio"
    ],
    "wof:name":"Classic Garden Furniture Co",
    "wof:placetype":"venue"
},
  "geometry": {"coordinates":[-2.80969,53.563831],"type":"Point"}
}