{
  "type": "Feature",
  "properties": {
    "iso:country":"GB",
    "sg:address":"71 Lashford Lane, Dry Sandford",
    "sg:city":"Abingdon",
    "sg:classifiers":[
        {
            "category":"Building & Trades",
            "subcategory":"Landscaping Services",
            "type":"Services"
        }
    ],
    "sg:phone":"+44 1865 736767",
    "sg:postcode":"OX13 6DZ",
    "sg:province":"Oxfordshire",
    "sg:tags":[
        "gardening"
    ],
    "wof:name":"D C L Services",
    "wof:placetype":"venue"
},
  "geometry": {"coordinates":[-1.321837,51.705269],"type":"Point"}
}