{
  "type": "Feature",
  "properties": {
    "iso:country":"GB",
    "sg:address":"192 Hawthorn Rd",
    "sg:city":"Ashington",
    "sg:classifiers":[
        {
            "category":"Personal",
            "subcategory":"Beauty Salon",
            "type":"Services"
        }
    ],
    "sg:phone":"+44 1670 812684",
    "sg:postcode":"NE63 9AU",
    "sg:province":"Northumberland",
    "sg:tags":[
        "unisex",
        "hairdresser"
    ],
    "wof:name":"Carol Dickson",
    "wof:placetype":"venue"
},
  "geometry": {"coordinates":[-1.5601,55.178879],"type":"Point"}
}