{
  "type": "Feature",
  "properties": {
    "addr:full":"Unit 18 Jarvis Street Indust Est Leicester Leicestershire LE3 5BN",
    "addr:housenumber":"unit 18",
    "addr:postcode":"le3 5bn",
    "addr:street":"Jarvis Street",
    "iso:country":"GB",
    "sg:address":"Unit 18 Jarvis Street Indust Est",
    "sg:city":"Leicester",
    "sg:classifiers":[
        {
            "category":"Building & Trades",
            "subcategory":"Cleaning & Sanitation",
            "type":"Services"
        }
    ],
    "sg:phone":"+44 116 262 8209",
    "sg:postcode":"LE3 5BN",
    "sg:province":"Leicestershire",
    "sg:tags":[
        "dry",
        "control",
        "damp",
        "rot"
    ],
    "wof:name":"Home & Dry Damp Proofing Co Ltd",
    "wof:placetype":"venue"
},
  "geometry": {"coordinates":[-1.142449975,52.6381111145],"type":"Point"}
}