{
  "type": "Feature",
  "properties": {
    "addr:full":"26 Station Parade, Elm Park Hornchurch Essex RM12 5AB",
    "addr:housenumber":"26",
    "addr:postcode":"rm12 5ab",
    "addr:street":"Station Parade Elm",
    "iso:country":"GB",
    "sg:address":"26 Station Parade, Elm Park",
    "sg:city":"Hornchurch",
    "sg:classifiers":[
        {
            "category":"Farming",
            "subcategory":"Fish & Marine Products",
            "type":"Manufacturing & Wholesale Goods"
        }
    ],
    "sg:phone":"+44 1708 475237",
    "sg:postcode":"RM12 5AB",
    "sg:province":"Essex",
    "sg:tags":[
        "fishmonger"
    ],
    "wof:name":"Elm Park Fisheries",
    "wof:placetype":"venue"
},
  "geometry": {"coordinates":[0.199126,51.549103],"type":"Point"}
}