{
  "type": "Feature",
  "properties": {
    "iso:country":"GB",
    "sg:address":"Elwood House, Cross Road, Albrighton",
    "sg:city":"Wolverhampton",
    "sg:classifiers":[
        {
            "category":"Professional",
            "subcategory":"Engineering",
            "type":"Services"
        },
        {
            "category":"Professional",
            "subcategory":"Computer Services",
            "type":"Services"
        }
    ],
    "sg:phone":"+44 1902 820345",
    "sg:postcode":"WV7 3RA",
    "sg:province":"Shropshire",
    "sg:tags":[
        "civil",
        "consulting",
        "software",
        "system",
        "engineer"
    ],
    "wof:name":"Elwood International Ltd.",
    "wof:placetype":"venue"
},
  "geometry": {"coordinates":[-2.2787239552,52.6345481873],"type":"Point"}
}