{
  "type": "Feature",
  "properties": {
    "addr:full":"Sunningdale, London Rd Attleborough Norfolk NR17 1BQ",
    "addr:postcode":"nr17 1bq",
    "addr:street":"London Rd",
    "iso:country":"GB",
    "sg:address":"Sunningdale, London Rd",
    "sg:city":"Attleborough",
    "sg:classifiers":[
        {
            "category":"Professional",
            "type":"Services"
        }
    ],
    "sg:postcode":"NR17 1BQ",
    "sg:province":"Norfolk",
    "sg:tags":[
        "leasing"
    ],
    "wof:name":"Marrison,Ron,Group Ltd",
    "wof:placetype":"venue"
},
  "geometry": {"coordinates":[1.014435,52.519054],"type":"Point"}
}