{
  "type": "Feature",
  "properties": {
    "addr:full":"Middle Block, St Josephs, Watford Way London Greater London NW4 4TY",
    "addr:postcode":"nw4 4ty",
    "addr:street":"Middle Block St;Watford Way",
    "iso:country":"GB",
    "sg:address":"Middle Block, St Josephs, Watford Way",
    "sg:city":"London",
    "sg:classifiers":[
        {
            "category":"Organizations",
            "subcategory":"Non-profit Organization",
            "type":"Services"
        }
    ],
    "sg:phone":"+44 20 8203 6290",
    "sg:postcode":"NW4 4TY",
    "sg:province":"Greater London",
    "sg:tags":[
        "charitable",
        "organisation",
        "voluntary",
        "charity"
    ],
    "wof:name":"Movement of Christian Workers",
    "wof:placetype":"venue"
},
  "geometry": {"coordinates":[-0.23139,51.587238],"type":"Point"}
}