{
  "type": "Feature",
  "properties": {
    "iso:country":"GB",
    "sg:address":"St Martins Cottage, Western Road",
    "sg:city":"Crowborough",
    "sg:classifiers":[
        {
            "category":"Professional",
            "subcategory":"Computer Services",
            "type":"Services"
        }
    ],
    "sg:postcode":"TN6 3EH",
    "sg:province":"East Sussex",
    "sg:tags":[
        "consultant"
    ],
    "wof:name":"Pan Technology",
    "wof:placetype":"venue"
},
  "geometry": {"coordinates":[0.171893,51.053196],"type":"Point"}
}