{
  "type": "Feature",
  "properties": {
    "addr:full":"52 Copthorne Avenue Ilford Essex IG6 2SQ",
    "addr:housenumber":"52",
    "addr:postcode":"ig6 2sq",
    "addr:street":"Copthorne Avenue Ilford",
    "iso:country":"GB",
    "sg:address":"52 Copthorne Avenue",
    "sg:city":"Ilford",
    "sg:classifiers":[
        {
            "category":"Professional",
            "subcategory":"Computer Services",
            "type":"Services"
        }
    ],
    "sg:phone":"+44 70 5012 3500",
    "sg:postcode":"IG6 2SQ",
    "sg:province":"Essex",
    "sg:tags":[
        "system",
        "software"
    ],
    "wof:name":"A M Consultancy Services Ltd.",
    "wof:placetype":"venue"
},
  "geometry": {"coordinates":[0.075382,51.604675],"type":"Point"}
}