{
  "type": "Feature",
  "properties": {
    "iso:country":"GB",
    "sg:address":"Alexander Rd",
    "sg:city":"Swansea",
    "sg:classifiers":[
        {
            "category":"Education",
            "subcategory":"Library",
            "type":"Public Place"
        }
    ],
    "sg:phone":"+44 1792 516753",
    "sg:postcode":"SA1 5DX",
    "sg:province":"Neath Port Talbot",
    "sg:tags":[
        "book"
    ],
    "wof:name":"Swansea Reference Library",
    "wof:placetype":"venue"
},
  "geometry": {"coordinates":[-3.941998,51.624866],"type":"Point"}
}