{
  "type": "Feature",
  "properties": {
    "addr:full":"118 Hayes Lane Kenley Surrey CR8 5HR",
    "addr:housenumber":"118",
    "addr:postcode":"cr8 5hr",
    "addr:street":"Hayes Lane",
    "iso:country":"GB",
    "sg:address":"118 Hayes Lane",
    "sg:city":"Kenley",
    "sg:classifiers":[
        {
            "category":"Professional",
            "subcategory":"Management & Consulting",
            "type":"Services"
        }
    ],
    "sg:phone":"+44 20 8645 0814",
    "sg:postcode":"CR8 5HR",
    "sg:province":"Surrey",
    "sg:tags":[
        "consultant",
        "business"
    ],
    "wof:name":"Julian Jenkins Associates",
    "wof:placetype":"venue"
},
  "geometry": {"coordinates":[-0.1075149998,51.3151168823],"type":"Point"}
}