{
  "type": "Feature",
  "properties": {
    "addr:full":"Highfields, 4 Moor End, Kelfield York North Yorkshire YO19 6RJ",
    "addr:housenumber":"4",
    "addr:postcode":"yo19 6rj",
    "addr:street":"Highfields;Moor End",
    "iso:country":"GB",
    "sg:address":"Highfields, 4 Moor End, Kelfield",
    "sg:city":"York",
    "sg:classifiers":[
        {
            "category":"Building & Trades",
            "subcategory":"Construction",
            "type":"Services"
        }
    ],
    "sg:phone":"+44 1757 248229",
    "sg:postcode":"YO19 6RJ",
    "sg:province":"North Yorkshire",
    "sg:tags":[
        "dry",
        "lining",
        "plasterers",
        "screeders"
    ],
    "wof:name":"A.H & P.A Kneeshaw",
    "wof:placetype":"venue"
},
  "geometry": {"coordinates":[-1.0981760025,53.8382911682],"type":"Point"}
}