{
  "type": "Feature",
  "properties": {
    "iso:country":"GB",
    "sg:address":"45 Holme Road",
    "sg:city":"Hatfield",
    "sg:classifiers":[
        {
            "category":"Professional",
            "subcategory":"Detective & Security Services",
            "type":"Services"
        }
    ],
    "sg:phone":"+44 1707 882233",
    "sg:postcode":"AL10 9LG",
    "sg:province":"Hertfordshire",
    "wof:name":"Daise & Knights",
    "wof:placetype":"venue"
},
  "geometry": {"coordinates":[-0.236182,51.77372],"type":"Point"}
}