{
  "type": "Feature",
  "properties": {
    "addr:full":"30 Gainsborough Road Felixstowe Suffolk IP11 7HR",
    "addr:housenumber":"30",
    "addr:postcode":"ip11 7hr",
    "addr:street":"Gainsborough Road",
    "iso:country":"GB",
    "sg:address":"30 Gainsborough Road",
    "sg:city":"Felixstowe",
    "sg:classifiers":[
        {
            "category":"Fast Food",
            "type":"Food & Drink"
        }
    ],
    "sg:phone":"+44 1394 286306",
    "sg:postcode":"IP11 7HR",
    "sg:province":"Suffolk",
    "sg:tags":[
        "away",
        "take"
    ],
    "wof:name":"Golden Gate Chinese Takeaway",
    "wof:placetype":"venue"
},
  "geometry": {"coordinates":[1.3561650515,51.9645309448],"type":"Point"}
}