{
  "type": "Feature",
  "properties": {
    "addr:full":"126 Victoria Crescent Burton On Trent Derbyshire DE14 2QQ",
    "addr:housenumber":"126",
    "addr:postcode":"de14 2qq",
    "addr:street":"Victoria Crescent",
    "iso:country":"GB",
    "sg:address":"126 Victoria Crescent",
    "sg:city":"Burton On Trent",
    "sg:classifiers":[
        {
            "category":"Farming",
            "subcategory":"Dairy Farm",
            "type":"Manufacturing & Wholesale Goods"
        }
    ],
    "sg:phone":"+44 1283 568022",
    "sg:postcode":"DE14 2QQ",
    "sg:province":"Derbyshire",
    "wof:name":"A.W Lester",
    "wof:placetype":"venue"
},
  "geometry": {"coordinates":[-1.641975,52.814957],"type":"Point"}
}