{
  "type": "Feature",
  "properties": {
    "iso:country":"GB",
    "sg:address":"Unit 1, Pleck Ind Est, Pleck Rd",
    "sg:city":"Walsall",
    "sg:classifiers":[
        {
            "category":"Wholesale",
            "subcategory":"Non-durable Goods",
            "type":"Manufacturing & Wholesale Goods"
        }
    ],
    "sg:phone":"+44 1922 647878",
    "sg:postcode":"WS2 9HD",
    "sg:province":"West Midlands",
    "sg:tags":[
        "carry",
        "cash"
    ],
    "wof:name":"M & T Caters Cash & Carry",
    "wof:placetype":"venue"
},
  "geometry": {"coordinates":[-2.00138,52.57629],"type":"Point"}
}