{
  "type": "Feature",
  "properties": {
    "iso:country":"GB",
    "sg:address":"183-187 Staines Road",
    "sg:city":"Feltham",
    "sg:classifiers":[
        {
            "category":"Retail",
            "subcategory":"Emissions Testing",
            "type":"Services"
        },
        {
            "category":"Professional",
            "subcategory":"Testing Lab",
            "type":"Services"
        }
    ],
    "sg:phone":"+44 20 8890 8253",
    "sg:postcode":"TW14 9EA",
    "sg:province":"Greater London",
    "sg:tags":[
        "mot"
    ],
    "wof:name":"The Test Centre",
    "wof:placetype":"venue"
},
  "geometry": {"coordinates":[-0.413816,51.456661],"type":"Point"}
}