{
  "type": "Feature",
  "properties": {
    "iso:country":"GB",
    "sg:address":"19 Market Street",
    "sg:city":"Sheffield",
    "sg:classifiers":[
        {
            "category":"Food & Beverages",
            "subcategory":"Meat & Fish",
            "type":"Retail Goods"
        },
        {
            "category":"Food & Beverages",
            "subcategory":"Groceries & Convenience Stores",
            "type":"Retail Goods"
        }
    ],
    "sg:phone":"+44 114 269 6631",
    "sg:postcode":"S13 7PD",
    "sg:province":"South Yorkshire",
    "sg:tags":[
        "shop",
        "chip"
    ],
    "wof:name":"Mannings Fish Bar",
    "wof:placetype":"venue"
},
  "geometry": {"coordinates":[-1.3676290512,53.3586425781],"type":"Point"}
}