{
  "type": "Feature",
  "properties": {
    "iso:country":"GB",
    "sg:address":"Oaktree House, 2 Pheonix Place",
    "sg:city":"Nottingham",
    "sg:classifiers":[
        {
            "category":"Banks & Credit Unions",
            "subcategory":"Financial Services",
            "type":"Services"
        }
    ],
    "sg:phone":"+44 870 012 5555",
    "sg:postcode":"NG8 6BA",
    "sg:province":"Nottinghamshire",
    "sg:tags":[
        "adviser"
    ],
    "wof:name":"Oaktree Financial Services Ltd.",
    "wof:placetype":"venue"
},
  "geometry": {"coordinates":[-1.2036540508,52.9882736206],"type":"Point"}
}