{
  "type": "Feature",
  "properties": {
    "addr:full":"Unit 15 Sandybridge Lane Business, Park Barnsley South Yorkshire S72 8PQ",
    "addr:housenumber":"unit 15",
    "addr:postcode":"s72 8pq",
    "addr:street":"Sandybridge Lane Business Park;Yorkshire",
    "iso:country":"GB",
    "sg:address":"Unit 15 Sandybridge Lane Business, Park",
    "sg:city":"Barnsley",
    "sg:classifiers":[
        {
            "category":"Shopping",
            "type":"Retail Goods"
        }
    ],
    "sg:postcode":"S72 8PQ",
    "sg:province":"South Yorkshire",
    "sg:tags":[
        "part",
        "accessory"
    ],
    "wof:name":"Autoprep",
    "wof:placetype":"venue"
},
  "geometry": {"coordinates":[-1.417268,53.601524],"type":"Point"}
}