{
  "type": "Feature",
  "properties": {
    "addr:full":"303 Burnley Road Accrington Lancashire BB5 6HA",
    "addr:housenumber":"303",
    "addr:postcode":"bb5 6ha",
    "addr:street":"Burnley Road",
    "iso:country":"GB",
    "sg:address":"303 Burnley Road",
    "sg:city":"Accrington",
    "sg:classifiers":[
        {
            "category":"Bus Charters",
            "type":"Transportation"
        }
    ],
    "sg:postcode":"BB5 6HA",
    "sg:province":"Lancashire",
    "sg:tags":[
        "hire",
        "coach"
    ],
    "wof:name":"Newline Travel",
    "wof:placetype":"venue"
},
  "geometry": {"coordinates":[-2.352335,53.761894],"type":"Point"}
}