{
  "type": "Feature",
  "properties": {
    "addr:full":"47 Sandford Road Wareham Dorset BH20 4DQ",
    "addr:housenumber":"47",
    "addr:postcode":"bh20 4dq",
    "addr:street":"Sandford Road",
    "iso:country":"GB",
    "sg:address":"47 Sandford Road",
    "sg:city":"Wareham",
    "sg:classifiers":[
        {
            "category":"Building & Trades",
            "subcategory":"Landscaping Services",
            "type":"Services"
        }
    ],
    "sg:postcode":"BH20 4DQ",
    "sg:province":"Dorset",
    "sg:tags":[
        "landscape",
        "contractor"
    ],
    "wof:name":"Jorg Annaheim",
    "wof:placetype":"venue"
},
  "geometry": {"coordinates":[-2.1098709106,50.6979141235],"type":"Point"}
}