{
  "type": "Feature",
  "properties": {
    "addr:full":"24 Challands Way, Hasland Chesterfield Derbyshire S41 0ER",
    "addr:housenumber":"24",
    "addr:postcode":"s41 0er",
    "addr:street":"Challands Way",
    "iso:country":"GB",
    "sg:address":"24 Challands Way, Hasland",
    "sg:city":"Chesterfield",
    "sg:classifiers":[
        {
            "category":"Utilities",
            "subcategory":"Natural Gas",
            "type":"Services"
        }
    ],
    "sg:phone":"+44 1246 271523",
    "sg:postcode":"S41 0ER",
    "sg:province":"Derbyshire",
    "sg:tags":[
        "control",
        "energy",
        "management",
        "system"
    ],
    "wof:name":"Simon Favell Industries Ltd.",
    "wof:placetype":"venue"
},
  "geometry": {"coordinates":[-1.410958,53.224751],"type":"Point"}
}