{
  "type": "Feature",
  "properties": {
    "iso:country":"GB",
    "sg:address":"Allt-y-ffynnon, Alltami Rd, Alltami",
    "sg:city":"Mold",
    "sg:classifiers":[
        {
            "category":"Utilities",
            "subcategory":"Water",
            "type":"Services"
        }
    ],
    "sg:phone":"+44 1244 550015",
    "sg:postcode":"CH7 6HD",
    "sg:province":"Denbighshire",
    "wof:name":"Dwr Cymru Welsh Water",
    "wof:placetype":"venue"
},
  "geometry": {"coordinates":[-3.0988199711,53.1819992065],"type":"Point"}
}