{
  "type": "Feature",
  "properties": {
    "iso:country":"GB",
    "sg:address":"Abbey Fields, Mill Street",
    "sg:city":"Uttoxeter",
    "sg:classifiers":[
        {
            "category":"Shopping",
            "type":"Retail Goods"
        }
    ],
    "sg:phone":"+44 1889 590922",
    "sg:postcode":"ST14 5JX",
    "sg:province":"Derbyshire",
    "sg:tags":[
        "merchant"
    ],
    "wof:name":"W E Atkins & Sons",
    "wof:placetype":"venue"
},
  "geometry": {"coordinates":[-1.836119,52.949551],"type":"Point"}
}