{
  "type": "Feature",
  "properties": {
    "addr:full":"27 Roman Bank, Mansfield Woodhouse Mansfield Derbyshire NG19 9DE",
    "addr:housenumber":"27",
    "addr:postcode":"ng19 9de",
    "addr:street":"Roman Bank",
    "iso:country":"GB",
    "sg:address":"27 Roman Bank, Mansfield Woodhouse",
    "sg:city":"Mansfield",
    "sg:classifiers":[
        {
            "category":"Professional",
            "subcategory":"Management & Consulting",
            "type":"Services"
        },
        {
            "category":"Professional",
            "subcategory":"Computer Services",
            "type":"Services"
        }
    ],
    "sg:phone":"+44 1623 645781",
    "sg:postcode":"NG19 9DE",
    "sg:province":"Derbyshire",
    "sg:tags":[
        "consultant",
        "business"
    ],
    "wof:name":"Acro Logic",
    "wof:placetype":"venue"
},
  "geometry": {"coordinates":[-1.182369,53.164837],"type":"Point"}
}