{
  "type": "Feature",
  "properties": {
    "addr:full":"232 Liverpool Road, Longton Preston Lancashire PR4 5YB",
    "addr:housenumber":"232",
    "addr:postcode":"pr4 5yb",
    "addr:street":"Liverpool Road",
    "iso:country":"GB",
    "sg:address":"232 Liverpool Road, Longton",
    "sg:city":"Preston",
    "sg:classifiers":[
        {
            "category":"Building & Trades",
            "subcategory":"Construction",
            "type":"Services"
        }
    ],
    "sg:postcode":"PR4 5YB",
    "sg:province":"Lancashire",
    "sg:tags":[
        "demolition",
        "contractor"
    ],
    "wof:name":"John Rhind Demolition Ltd.",
    "wof:placetype":"venue"
},
  "geometry": {"coordinates":[-2.7770359516,53.73072052],"type":"Point"}
}