{
  "type": "Feature",
  "properties": {
    "addr:full":"10 Pendlebury Road, Swinton Manchester Greater Manchester M27 4AR",
    "addr:housenumber":"10",
    "addr:postcode":"m27 4ar",
    "addr:street":"Pendlebury Road",
    "iso:country":"GB",
    "sg:address":"10 Pendlebury Road, Swinton",
    "sg:city":"Manchester",
    "sg:classifiers":[
        {
            "category":"Shopping",
            "subcategory":"News",
            "type":"Retail Goods"
        }
    ],
    "sg:phone":"+44 161 794 1849",
    "sg:postcode":"M27 4AR",
    "sg:province":"Greater Manchester",
    "sg:tags":[
        "newsagent"
    ],
    "wof:name":"B B Newsplus",
    "wof:placetype":"venue"
},
  "geometry": {"coordinates":[-2.335285902,53.5104217529],"type":"Point"}
}