{
  "type": "Feature",
  "properties": {
    "addr:full":"15 Forndon Close, Lower Earley Reading Berkshire RG6 3XR",
    "addr:housenumber":"15",
    "addr:postcode":"rg6 3xr",
    "addr:street":"Forndon Close",
    "iso:country":"GB",
    "sg:address":"15 Forndon Close, Lower Earley",
    "sg:city":"Reading",
    "sg:classifiers":[
        {
            "category":"Professional",
            "subcategory":"Lawyer & Legal Services",
            "type":"Services"
        }
    ],
    "sg:phone":"+44 118 966 7618",
    "sg:postcode":"RG6 3XR",
    "sg:province":"Berkshire",
    "sg:tags":[
        "solicitor"
    ],
    "wof:name":"Judith Gifford",
    "wof:placetype":"venue"
},
  "geometry": {"coordinates":[-0.9046279788,51.4290809631],"type":"Point"}
}