{
  "type": "Feature",
  "properties": {
    "addr:full":"Unit 7 Moss Lane Industrial Estate, Hayside Oldham Lancashire OL2 6HR",
    "addr:housenumber":"unit 7",
    "addr:postcode":"ol2 6hr",
    "addr:street":"Moss Lane Industrial Estate",
    "iso:country":"GB",
    "sg:address":"Unit 7 Moss Lane Industrial Estate, Hayside",
    "sg:city":"Oldham",
    "sg:classifiers":[
        {
            "category":"Home & Garden",
            "subcategory":"Home Furnishings",
            "type":"Retail Goods"
        }
    ],
    "sg:phone":"+44 1706 880355",
    "sg:postcode":"OL2 6HR",
    "sg:province":"Lancashire",
    "sg:tags":[
        "racking",
        "shelving",
        "diy"
    ],
    "wof:name":"Monarch Shelving & Racking",
    "wof:placetype":"venue"
},
  "geometry": {"coordinates":[-2.102166,53.560768],"type":"Point"}
}