{
  "type": "Feature",
  "properties": {
    "addr:full":"12-28 Glen St Hebburn Tyne and Wear NE31 1NU",
    "addr:housenumber":"12-28",
    "addr:postcode":"ne31 1nu",
    "addr:street":"Glen St",
    "iso:country":"GB",
    "sg:address":"12-28 Glen St",
    "sg:city":"Hebburn",
    "sg:classifiers":[
        {
            "category":"Health Services",
            "subcategory":"Doctor",
            "type":"Services"
        }
    ],
    "sg:phone":"+44 191 428 2212",
    "sg:postcode":"NE31 1NU",
    "sg:province":"Tyne and Wear",
    "sg:tags":[
        "practitioners"
    ],
    "wof:name":"Vineyak Dr I.P",
    "wof:placetype":"venue"
},
  "geometry": {"coordinates":[-1.521493,54.973698],"type":"Point"}
}