{
  "type": "Feature",
  "properties": {
    "iso:country":"GB",
    "sg:address":"16 The Royals, High St",
    "sg:city":"Southend On Sea",
    "sg:classifiers":[
        {
            "category":"Food & Beverages",
            "subcategory":"Specialty",
            "type":"Retail Goods"
        }
    ],
    "sg:phone":"+44 1702 469223",
    "sg:postcode":"SS1 1DQ",
    "sg:province":"Essex",
    "sg:tags":[
        "product",
        "health"
    ],
    "wof:name":"Musby Nuts & Spices",
    "wof:placetype":"venue"
},
  "geometry": {"coordinates":[0.70516,51.540386],"type":"Point"}
}