{
  "type": "Feature",
  "properties": {
    "addr:full":"57-63 Lea Road Northampton Northamptonshire NN1 4PE",
    "addr:housenumber":"57-63",
    "addr:postcode":"nn1 4pe",
    "addr:street":"Lea Road",
    "iso:country":"GB",
    "sg:address":"57-63 Lea Road",
    "sg:city":"Northampton",
    "sg:classifiers":[
        {
            "category":"Home & Garden",
            "subcategory":"Household Appliances",
            "type":"Retail Goods"
        }
    ],
    "sg:phone":"+44 1604 472525",
    "sg:postcode":"NN1 4PE",
    "sg:province":"Northamptonshire",
    "sg:tags":[
        "refrigeration",
        "air conditioning"
    ],
    "wof:name":"Shires Technical Services Ltd.",
    "wof:placetype":"venue"
},
  "geometry": {"coordinates":[-0.875591,52.246876],"type":"Point"}
}