{
  "type": "Feature",
  "properties": {
    "iso:country":"GB",
    "sg:address":"37 Ashfield Way, Hazlemere",
    "sg:city":"High Wycombe",
    "sg:classifiers":[
        {
            "category":"Building & Trades",
            "subcategory":"Construction",
            "type":"Services"
        }
    ],
    "sg:postcode":"HP15 7RL",
    "sg:province":"Buckinghamshire",
    "sg:tags":[
        "flooring"
    ],
    "wof:name":"Contrast Flooring",
    "wof:placetype":"venue"
},
  "geometry": {"coordinates":[-0.7050079703,51.6472244263],"type":"Point"}
}