{
  "type": "Feature",
  "properties": {
    "iso:country":"GB",
    "sg:address":"2 Buxton Rd",
    "sg:city":"Stockport",
    "sg:classifiers":[
        {
            "category":"Fast Food",
            "type":"Food & Drink"
        }
    ],
    "sg:phone":"+44 161 483 6241",
    "sg:postcode":"SK7 6AD",
    "sg:province":"Cheshire",
    "sg:tags":[
        "away",
        "take"
    ],
    "wof:name":"Tandoori Cottage",
    "wof:placetype":"venue"
},
  "geometry": {"coordinates":[-2.113018,53.375172],"type":"Point"}
}