{
  "type": "Feature",
  "properties": {
    "iso:country":"GB",
    "sg:address":"Market Place, Aylesham",
    "sg:city":"Canterbury",
    "sg:classifiers":[
        {
            "category":"Fast Food",
            "type":"Food & Drink"
        }
    ],
    "sg:phone":"+44 1304 840287",
    "sg:postcode":"CT3 3EY",
    "sg:province":"Kent",
    "sg:tags":[
        "away",
        "meal",
        "outlet",
        "take"
    ],
    "wof:name":"Lucky Star",
    "wof:placetype":"venue"
},
  "geometry": {"coordinates":[1.20096,51.226166],"type":"Point"}
}