{
  "type": "Feature",
  "properties": {
    "iso:country":"GB",
    "sg:address":"75-77 Hawthorn Rd",
    "sg:city":"Bognor Regis",
    "sg:classifiers":[
        {
            "category":"Retail",
            "subcategory":"Self-service Laundry",
            "type":"Services"
        },
        {
            "category":"Shopping",
            "subcategory":"Used Merchandise",
            "type":"Retail Goods"
        }
    ],
    "sg:phone":"+44 1243 868213",
    "sg:postcode":"PO21 2BE",
    "sg:province":"West Sussex",
    "sg:tags":[
        "shop",
        "sale",
        "second-hand"
    ],
    "wof:name":"Magpie Second Hand Shop",
    "wof:placetype":"venue"
},
  "geometry": {"coordinates":[-0.683736,50.791092],"type":"Point"}
}