{
  "type": "Feature",
  "properties": {
    "addr:full":"Oaktree School, Chase Side London Greater London N14 4HN",
    "addr:postcode":"n14 4hn",
    "addr:street":"Chase Side",
    "iso:country":"GB",
    "sg:address":"Oaktree School, Chase Side",
    "sg:city":"London",
    "sg:classifiers":[
        {
            "category":"Education",
            "subcategory":"Special Training",
            "type":"Public Place"
        },
        {
            "category":"Education",
            "subcategory":"School",
            "type":"Public Place"
        },
        {
            "category":"Government",
            "subcategory":"Office",
            "type":"Public Place"
        }
    ],
    "sg:phone":"+44 20 8440 3100",
    "sg:postcode":"N14 4HN",
    "sg:province":"Greater London",
    "sg:tags":[
        "local"
    ],
    "wof:name":"Oaktree Special School",
    "wof:placetype":"venue"
},
  "geometry": {"coordinates":[-0.1414200068,51.6426315308],"type":"Point"}
}