{
  "type": "Feature",
  "properties": {
    "addr:full":"Coventry Rd Warwick Warwickshire CV34 5YH",
    "addr:postcode":"cv34 5yh",
    "addr:street":"Coventry Rd",
    "iso:country":"GB",
    "sg:address":"Coventry Rd",
    "sg:city":"Warwick",
    "sg:classifiers":[
        {
            "category":"Autos & Motor Vehicles",
            "subcategory":"Fuel & Gas Station",
            "type":"Retail Goods"
        }
    ],
    "sg:postcode":"CV34 5YH",
    "sg:province":"Warwickshire",
    "sg:tags":[
        "hr",
        "petrol"
    ],
    "wof:name":"Andrews,D,",
    "wof:placetype":"venue"
},
  "geometry": {"coordinates":[-1.5779989958,52.2911453247],"type":"Point"}
}