{
  "type": "Feature",
  "properties": {
    "addr:full":"107 Commercial Road, Paddock Wood Tonbridge Kent TN12 6DS",
    "addr:housenumber":"107",
    "addr:postcode":"tn12 6ds",
    "addr:street":"Commercial Road Paddock",
    "iso:country":"GB",
    "sg:address":"107 Commercial Road, Paddock Wood",
    "sg:city":"Tonbridge",
    "sg:classifiers":[
        {
            "category":"Personal",
            "subcategory":"Beauty Salon",
            "type":"Services"
        }
    ],
    "sg:phone":"+44 1892 834100",
    "sg:postcode":"TN12 6DS",
    "sg:province":"Kent",
    "sg:tags":[
        "unisex",
        "hairdresser"
    ],
    "wof:name":"Hair Workshop",
    "wof:placetype":"venue"
},
  "geometry": {"coordinates":[0.387166,51.179451],"type":"Point"}
}