{
  "type": "Feature",
  "properties": {
    "addr:full":"Unit 1 Chelworth Lodge, Cricklade Swindon Gloucestershire SN6 6HB",
    "addr:housenumber":"unit 1 chelworth",
    "addr:postcode":"sn6 6hb",
    "iso:country":"GB",
    "sg:address":"Unit 1 Chelworth Lodge, Cricklade",
    "sg:city":"Swindon",
    "sg:classifiers":[
        {
            "category":"Building & Trades",
            "subcategory":"Construction",
            "type":"Services"
        }
    ],
    "sg:phone":"+44 1793 752333",
    "sg:postcode":"SN6 6HB",
    "sg:province":"Gloucestershire",
    "sg:tags":[
        "fork",
        "lift",
        "truck"
    ],
    "wof:name":"Moonraker Forklifts Ltd.",
    "wof:placetype":"venue"
},
  "geometry": {"coordinates":[-1.864225,51.636711],"type":"Point"}
}