{
  "type": "Feature",
  "properties": {
    "iso:country":"GB",
    "sg:address":"George House, Boroughbriggs Road",
    "sg:city":"Elgin",
    "sg:classifiers":[
        {
            "category":"Food & Beverages",
            "subcategory":"Liquor & Beverages",
            "type":"Retail Goods"
        }
    ],
    "sg:postcode":"IV30 1AP",
    "sg:province":"Moray",
    "sg:tags":[
        "beer",
        "spirit",
        "wines"
    ],
    "wof:name":"Speymalt Whisky Distributors Ltd.",
    "wof:placetype":"venue"
},
  "geometry": {"coordinates":[-3.317122,57.651985],"type":"Point"}
}