{
  "type": "Feature",
  "properties": {
    "addr:full":"West Hinden Farm, Woodland Bishop Auckland Durham DL13 5RT",
    "addr:postcode":"dl13 5rt",
    "addr:street":"West Hinden Farm Woodland;Auckland",
    "iso:country":"GB",
    "sg:address":"West Hinden Farm, Woodland",
    "sg:city":"Bishop Auckland",
    "sg:classifiers":[
        {
            "category":"Farming",
            "subcategory":"Livestock Farm",
            "type":"Manufacturing & Wholesale Goods"
        }
    ],
    "sg:phone":"+44 1833 690119",
    "sg:postcode":"DL13 5RT",
    "sg:province":"Durham",
    "sg:tags":[
        "others"
    ],
    "wof:name":"I & R A Watson",
    "wof:placetype":"venue"
},
  "geometry": {"coordinates":[-1.886117,54.633629],"type":"Point"}
}