{
  "type": "Feature",
  "properties": {
    "addr:full":"21 Clerkenwell Grn London Greater London EC1R 0DP",
    "addr:housenumber":"21",
    "addr:postcode":"ec1r 0dp",
    "addr:street":"Clerkenwell Grn",
    "iso:country":"GB",
    "sg:address":"21 Clerkenwell Grn",
    "sg:city":"London",
    "sg:classifiers":[
        {
            "category":"Communications",
            "subcategory":"Film & Video Production",
            "type":"Services"
        },
        {
            "category":"Professional",
            "subcategory":"Art Services",
            "type":"Services"
        }
    ],
    "sg:phone":"+44 20 7608 0163",
    "sg:postcode":"EC1R 0DP",
    "sg:province":"Greater London",
    "sg:tags":[
        "photographer",
        "illustrator",
        "artist"
    ],
    "wof:name":"Linsey Design",
    "wof:placetype":"venue"
},
  "geometry": {"coordinates":[-0.1062569991,51.5241012573],"type":"Point"}
}