{
  "type": "Feature",
  "properties": {
    "addr:full":"19 Flats Lane, Weeford Lichfield Staffordshire WS14 9QG",
    "addr:postcode":"ws14 9qg",
    "addr:street":"Flats Lane",
    "iso:country":"GB",
    "sg:address":"19 Flats Lane, Weeford",
    "sg:city":"Lichfield",
    "sg:classifiers":[
        {
            "category":"Food & Beverages",
            "subcategory":"Groceries & Convenience Stores",
            "type":"Retail Goods"
        }
    ],
    "sg:phone":"+44 1543 481227",
    "sg:postcode":"WS14 9QG",
    "sg:province":"Staffordshire",
    "sg:tags":[
        "merchant",
        "potato"
    ],
    "wof:name":"W B Deakin & Sons",
    "wof:placetype":"venue"
},
  "geometry": {"coordinates":[-1.787621,52.639511],"type":"Point"}
}