{
  "type": "Feature",
  "properties": {
    "addr:full":"100 Grove Lane, Cheadle Hulme Cheadle Cheshire SK8 7ND",
    "addr:housenumber":"100",
    "addr:postcode":"sk8 7nd",
    "addr:street":"Grove Lane",
    "iso:country":"GB",
    "sg:address":"100 Grove Lane, Cheadle Hulme",
    "sg:city":"Cheadle",
    "sg:classifiers":[
        {
            "category":"Professional",
            "subcategory":"Management & Consulting",
            "type":"Services"
        }
    ],
    "sg:phone":"+44 161 439 1248",
    "sg:postcode":"SK8 7ND",
    "sg:province":"Cheshire",
    "sg:tags":[
        "consultant",
        "business"
    ],
    "wof:name":"Pragma Consultants",
    "wof:placetype":"venue"
},
  "geometry": {"coordinates":[-2.1895799637,53.3581161499],"type":"Point"}
}