{
  "type": "Feature",
  "properties": {
    "iso:country":"GB",
    "sg:address":"31 Lower Brown Street",
    "sg:city":"Leicester",
    "sg:classifiers":[
        {
            "category":"Professional",
            "subcategory":"Lawyer & Legal Services",
            "type":"Services"
        }
    ],
    "sg:phone":"+44 800 975 7330",
    "sg:postcode":"LE1 5TH",
    "sg:province":"Leicestershire",
    "sg:tags":[
        "solicitor"
    ],
    "wof:name":"Andrew M Ford Solicitor",
    "wof:placetype":"venue"
},
  "geometry": {"coordinates":[-1.1352490187,52.6307449341],"type":"Point"}
}