{
  "type": "Feature",
  "properties": {
    "iso:country":"GB",
    "sg:address":"Dipton Mill Road",
    "sg:city":"Hexham",
    "sg:classifiers":[
        {
            "category":"Bars & Pubs",
            "type":"Food & Drink"
        },
        {
            "category":"Community Center",
            "subcategory":"Social",
            "type":"Public Place"
        }
    ],
    "sg:phone":"+44 1434 606577",
    "sg:postcode":"NE46 1YA",
    "sg:province":"Northumberland",
    "sg:tags":[
        "pubs",
        "house",
        "inn",
        "activity"
    ],
    "wof:name":"Dipton Mill Inn",
    "wof:placetype":"venue"
},
  "geometry": {"coordinates":[-2.1001670361,54.9662628174],"type":"Point"}
}