{
  "type": "Feature",
  "properties": {
    "addr:full":"17 Broadgate Crescent Huddersfield West Yorkshire HD5 8HU",
    "addr:housenumber":"17",
    "addr:postcode":"hd5 8hu",
    "addr:street":"Broadgate Crescent",
    "iso:country":"GB",
    "sg:address":"17 Broadgate Crescent",
    "sg:city":"Huddersfield",
    "sg:classifiers":[
        {
            "category":"Recreation",
            "subcategory":"Amusement Park",
            "type":"Entertainment"
        }
    ],
    "sg:phone":"+44 1484 510881",
    "sg:postcode":"HD5 8HU",
    "sg:province":"West Yorkshire",
    "sg:tags":[
        "arcade"
    ],
    "wof:name":"Leisureforce",
    "wof:placetype":"venue"
},
  "geometry": {"coordinates":[-1.7640140057,53.6397514343],"type":"Point"}
}