{
  "type": "Feature",
  "properties": {
    "addr:full":"Pattinson North Industrial Estate Washington Durham NE38 8QA",
    "addr:postcode":"ne38 8qa",
    "addr:street":"North Industrial Estate",
    "iso:country":"GB",
    "sg:address":"Pattinson North Industrial Estate",
    "sg:city":"Washington",
    "sg:classifiers":[
        {
            "category":"Professional",
            "subcategory":"Business Services",
            "type":"Services"
        }
    ],
    "sg:phone":"+44 191 417 5555",
    "sg:postcode":"NE38 8QA",
    "sg:province":"Durham",
    "sg:tags":[
        "distribution"
    ],
    "wof:name":"Asda S A C 2",
    "wof:placetype":"venue"
},
  "geometry": {"coordinates":[-1.531789,54.898144],"type":"Point"}
}