{
  "type": "Feature",
  "properties": {
    "iso:country":"GB",
    "sg:address":"5 Joyce Dawson Way",
    "sg:city":"London",
    "sg:classifiers":[
        {
            "category":"Home & Garden",
            "subcategory":"Carpets & Floor Coverings",
            "type":"Retail Goods"
        }
    ],
    "sg:phone":"+44 20 8311 3666",
    "sg:postcode":"SE28 8RA",
    "sg:province":"Greater London",
    "sg:tags":[
        "carpets",
        "rug",
        "matting"
    ],
    "wof:name":"Thamesmead Carpets",
    "wof:placetype":"venue"
},
  "geometry": {"coordinates":[0.1068300009,51.5068016052],"type":"Point"}
}