{
  "type": "Feature",
  "properties": {
    "addr:full":"154 Main Street, Cambuslang Glasgow South Lanarkshire G72 7EL",
    "addr:housenumber":"154",
    "addr:postcode":"g72 7el",
    "addr:street":"Main Street",
    "iso:country":"GB",
    "sg:address":"154 Main Street, Cambuslang",
    "sg:city":"Glasgow",
    "sg:classifiers":[
        {
            "category":"Travel",
            "subcategory":"Travel Agent",
            "type":"Entertainment"
        }
    ],
    "sg:phone":"+44 141 641 4932",
    "sg:postcode":"G72 7EL",
    "sg:province":"South Lanarkshire",
    "wof:name":"Cambuslang Travel Ltd.",
    "wof:placetype":"venue"
},
  "geometry": {"coordinates":[-4.168027,55.818966],"type":"Point"}
}