{
  "type": "Feature",
  "properties": {
    "addr:full":"6 Springwell Lane Northallerton North Yorkshire DL7 8QE",
    "addr:housenumber":"6",
    "addr:postcode":"dl7 8qe",
    "addr:street":"Springwell Lane",
    "iso:country":"GB",
    "sg:address":"6 Springwell Lane",
    "sg:city":"Northallerton",
    "sg:classifiers":[
        {
            "category":"Retail",
            "subcategory":"Driving School",
            "type":"Services"
        }
    ],
    "sg:phone":"+44 1609 780264",
    "sg:postcode":"DL7 8QE",
    "sg:province":"North Yorkshire",
    "wof:name":"M S M School Of Motoring",
    "wof:placetype":"venue"
},
  "geometry": {"coordinates":[-1.437651,54.337868],"type":"Point"}
}