{
  "type": "Feature",
  "properties": {
    "iso:country":"GB",
    "sg:address":"5 Ashes Lane",
    "sg:city":"Stalybridge",
    "sg:classifiers":[
        {
            "category":"Building & Trades",
            "subcategory":"Construction",
            "type":"Services"
        }
    ],
    "sg:phone":"+44 161 303 2017",
    "sg:postcode":"SK15 2RH",
    "sg:province":"Greater Manchester",
    "sg:tags":[
        "builder"
    ],
    "wof:name":"J.W Ratchford",
    "wof:placetype":"venue"
},
  "geometry": {"coordinates":[-2.040019,53.477032],"type":"Point"}
}