{
  "type": "Feature",
  "properties": {
    "addr:full":"Linwood Croft York North Yorkshire YO31 9LT",
    "addr:postcode":"yo31 9lt",
    "addr:street":"Linwood Croft",
    "iso:country":"GB",
    "sg:address":"Linwood Croft",
    "sg:city":"York",
    "sg:classifiers":[
        {
            "category":"Building & Trades",
            "subcategory":"Cleaning & Sanitation",
            "type":"Services"
        }
    ],
    "sg:postcode":"YO31 9LT",
    "sg:province":"North Yorkshire",
    "sg:tags":[
        "cleaner",
        "window"
    ],
    "wof:name":"A E & S G Travis",
    "wof:placetype":"venue"
},
  "geometry": {"coordinates":[-1.0578700304,53.9756393433],"type":"Point"}
}