{
  "type": "Feature",
  "properties": {
    "addr:full":"37 St Johns Rd Wembley Greater London HA9 7JB",
    "addr:housenumber":"37",
    "addr:postcode":"ha9 7jb",
    "addr:street":"St Johns Rd",
    "iso:country":"GB",
    "sg:address":"37 St Johns Rd",
    "sg:city":"Wembley",
    "sg:classifiers":[
        {
            "category":"Building & Trades",
            "subcategory":"Construction",
            "type":"Services"
        }
    ],
    "sg:phone":"+44 20 8795 4154",
    "sg:postcode":"HA9 7JB",
    "sg:province":"Greater London",
    "sg:tags":[
        "decorator",
        "painter"
    ],
    "wof:name":"Creative Strokes",
    "wof:placetype":"venue"
},
  "geometry": {"coordinates":[-0.2969999909,51.5538482666],"type":"Point"}
}