{
  "type": "Feature",
  "properties": {
    "iso:country":"GB",
    "sg:address":"Church Road, Eccleston",
    "sg:city":"Chester",
    "sg:classifiers":[
        {
            "category":"Government",
            "subcategory":"Post Office",
            "type":"Public Place"
        }
    ],
    "sg:postcode":"CH4 9HT",
    "sg:province":"Cheshire",
    "wof:name":"Eccleston Post Office",
    "wof:placetype":"venue"
},
  "geometry": {"coordinates":[-2.9457399845,53.149356842],"type":"Point"}
}