{
  "type": "Feature",
  "properties": {
    "addr:full":"30 Woodcroft Harlow Essex CM18 6XY",
    "addr:housenumber":"30",
    "addr:postcode":"cm18 6xy",
    "addr:street":"Woodcroft",
    "iso:country":"GB",
    "sg:address":"30 Woodcroft",
    "sg:city":"Harlow",
    "sg:classifiers":[
        {
            "category":"Professional",
            "subcategory":"Lawyer & Legal Services",
            "type":"Services"
        }
    ],
    "sg:phone":"+44 1279 427885",
    "sg:postcode":"CM18 6XY",
    "sg:province":"Essex",
    "sg:tags":[
        "advice",
        "counselling"
    ],
    "wof:name":"(pre-menstrual Syndrome) Pms Support Services",
    "wof:placetype":"venue"
},
  "geometry": {"coordinates":[0.0918809995,51.755859375],"type":"Point"}
}