{
  "type": "Feature",
  "properties": {
    "addr:full":"Daedalus House, Station Road Cambridge Cambridgeshire CB1 2RE",
    "addr:postcode":"cb1 2re",
    "addr:street":"Station Road",
    "iso:country":"GB",
    "sg:address":"Daedalus House, Station Road",
    "sg:city":"Cambridge",
    "sg:classifiers":[
        {
            "category":"Professional",
            "subcategory":"Lawyer & Legal Services",
            "type":"Services"
        }
    ],
    "sg:postcode":"CB1 2RE",
    "sg:province":"Cambridgeshire",
    "sg:tags":[
        "patent",
        "agent"
    ],
    "wof:name":"Reddie & Grose",
    "wof:placetype":"venue"
},
  "geometry": {"coordinates":[0.1313350052,52.1951217651],"type":"Point"}
}