{
  "type": "Feature",
  "properties": {
    "iso:country":"GB",
    "sg:address":"29 Steeley Lane",
    "sg:city":"Chorley",
    "sg:classifiers":[
        {
            "category":"Home & Garden",
            "subcategory":"Home Furnishings",
            "type":"Retail Goods"
        },
        {
            "category":"Building & Trades",
            "subcategory":"Construction",
            "type":"Services"
        }
    ],
    "sg:phone":"+44 1257 231751",
    "sg:postcode":"PR6 0RJ",
    "sg:province":"Lancashire",
    "sg:tags":[
        "installers",
        "planner",
        "kitchen",
        "furnishers"
    ],
    "wof:name":"Steeley Lane Kitchens & Bathrooms",
    "wof:placetype":"venue"
},
  "geometry": {"coordinates":[-2.625137,53.652275],"type":"Point"}
}