{
  "type": "Feature",
  "properties": {
    "addr:full":"Unit 11, Yalberton Tor Industrial Estate Paignton Devon TQ4 7QN",
    "addr:housenumber":"unit 11",
    "addr:postcode":"tq4 7qn",
    "addr:street":"Yalberton Tor Industrial Estate",
    "iso:country":"GB",
    "sg:address":"Unit 11, Yalberton Tor Industrial Estate",
    "sg:city":"Paignton",
    "sg:classifiers":[
        {
            "category":"Manufacturing",
            "subcategory":"Metals",
            "type":"Manufacturing & Wholesale Goods"
        }
    ],
    "sg:phone":"+44 1803 664020",
    "sg:postcode":"TQ4 7QN",
    "sg:province":"Devon",
    "sg:tags":[
        "steel",
        "stockholder"
    ],
    "wof:name":"Austen Knapman Ltd.",
    "wof:placetype":"venue"
},
  "geometry": {"coordinates":[-3.593391,50.422157],"type":"Point"}
}