{
  "type": "Feature",
  "properties": {
    "addr:full":"14b Maldon Rd, Tiptree Colchester Essex CO5 0LL",
    "addr:housenumber":"14b",
    "addr:postcode":"co5 0ll",
    "addr:street":"Maldon Rd",
    "iso:country":"GB",
    "sg:address":"14b Maldon Rd, Tiptree",
    "sg:city":"Colchester",
    "sg:classifiers":[
        {
            "category":"Shopping",
            "subcategory":"Beauty & Cosmetics",
            "type":"Retail Goods"
        }
    ],
    "sg:postcode":"CO5 0LL",
    "sg:province":"Essex",
    "sg:tags":[
        "product"
    ],
    "wof:name":"Aha  Natural Beauty Ltd",
    "wof:placetype":"venue"
},
  "geometry": {"coordinates":[0.7440270185,51.8162078857],"type":"Point"}
}