{
  "type": "Feature",
  "properties": {
    "iso:country":"GB",
    "sg:address":"Briggs House, Derby Street",
    "sg:city":"Burton-on-trent",
    "sg:classifiers":[
        {
            "category":"Home & Garden",
            "subcategory":"Kitchen Supply",
            "type":"Retail Goods"
        }
    ],
    "sg:phone":"+44 1283 566661",
    "sg:postcode":"DE14 2LH",
    "sg:province":"Derbyshire",
    "sg:tags":[
        "equipment",
        "brewer"
    ],
    "wof:name":"Burnett & Rolfe Ltd.",
    "wof:placetype":"venue"
},
  "geometry": {"coordinates":[-1.6361589432,52.813129425],"type":"Point"}
}