{
  "type": "Feature",
  "properties": {
    "iso:country":"GB",
    "sg:address":"22 Bridge Street",
    "sg:city":"Worksop",
    "sg:classifiers":[
        {
            "category":"Shopping",
            "subcategory":"Music",
            "type":"Retail Goods"
        }
    ],
    "sg:phone":"+44 1909 500720",
    "sg:postcode":"S80 1JQ",
    "sg:province":"Nottinghamshire",
    "sg:tags":[
        "record",
        "tape",
        "cd"
    ],
    "wof:name":"Our Price",
    "wof:placetype":"venue"
},
  "geometry": {"coordinates":[-1.124608,53.304527],"type":"Point"}
}