{
  "type": "Feature",
  "properties": {
    "addr:full":"2 Whitaker Road Coventry West Midlands CV5 9JE",
    "addr:housenumber":"2",
    "addr:postcode":"cv5 9je",
    "addr:street":"Whitaker Road",
    "iso:country":"GB",
    "sg:address":"2 Whitaker Road",
    "sg:city":"Coventry",
    "sg:classifiers":[
        {
            "category":"Health Services",
            "subcategory":"Doctor",
            "type":"Services"
        }
    ],
    "sg:phone":"+44 24 7667 4123",
    "sg:postcode":"CV5 9JE",
    "sg:province":"West Midlands",
    "sg:tags":[
        "practitioners"
    ],
    "wof:name":"Allesley Pk Medical Centre",
    "wof:placetype":"venue"
},
  "geometry": {"coordinates":[-1.555439,52.413029],"type":"Point"}
}