{
  "type": "Feature",
  "properties": {
    "iso:country":"GB",
    "sg:address":"3 Gordon Road",
    "sg:city":"Lincoln",
    "sg:classifiers":[
        {
            "category":"Shopping",
            "subcategory":"Optician",
            "type":"Retail Goods"
        }
    ],
    "sg:phone":"+44 1522 530088",
    "sg:postcode":"LN1 3AJ",
    "sg:province":"Lincolnshire",
    "sg:tags":[
        "dispensing"
    ],
    "wof:name":"Julian Gunn Contact Lenses",
    "wof:placetype":"venue"
},
  "geometry": {"coordinates":[-0.538863,53.235069],"type":"Point"}
}