{
  "type": "Feature",
  "properties": {
    "iso:country":"GB",
    "sg:address":"Ysglade, Yarnold Lane, Dodford",
    "sg:city":"Bromsgrove",
    "sg:classifiers":[
        {
            "category":"Building & Trades",
            "subcategory":"Construction",
            "type":"Services"
        }
    ],
    "sg:phone":"+44 1527 579280",
    "sg:postcode":"B61 9JG",
    "sg:province":"Worcestershire",
    "sg:tags":[
        "builder"
    ],
    "wof:name":"Gold Coast Builders Ltd.",
    "wof:placetype":"venue"
},
  "geometry": {"coordinates":[-2.0971570015,52.3560142517],"type":"Point"}
}