{
  "type": "Feature",
  "properties": {
    "iso:country":"GB",
    "sg:address":"77 Banbury Rd",
    "sg:city":"Oxford",
    "sg:classifiers":[
        {
            "category":"Shopping",
            "subcategory":"Books",
            "type":"Retail Goods"
        }
    ],
    "sg:phone":"+44 1865 514408",
    "sg:postcode":"OX2 6LF",
    "sg:province":"Oxfordshire",
    "wof:name":"Family Publications",
    "wof:placetype":"venue"
},
  "geometry": {"coordinates":[-1.260956,51.764931],"type":"Point"}
}