{
  "type": "Feature",
  "properties": {
    "iso:country":"GB",
    "sg:address":"Unit 2a Spencer Mews, Spencer Ave",
    "sg:city":"London",
    "sg:classifiers":[
        {
            "category":"Building & Trades",
            "subcategory":"Construction",
            "type":"Services"
        }
    ],
    "sg:postcode":"N13 4TR",
    "sg:province":"Greater London",
    "sg:tags":[
        "builder"
    ],
    "wof:name":"K C F Maintenance",
    "wof:placetype":"venue"
},
  "geometry": {"coordinates":[-0.112291,51.608868],"type":"Point"}
}