{
  "type": "Feature",
  "properties": {
    "addr:full":"Gillhurst House Sunderland Tyne and Wear SR1 3QP",
    "addr:postcode":"sr1 3qp",
    "iso:country":"GB",
    "sg:address":"Gillhurst House",
    "sg:city":"Sunderland",
    "sg:classifiers":[
        {
            "category":"Social Services",
            "subcategory":"Adult Care",
            "type":"Services"
        },
        {
            "category":"Government",
            "subcategory":"Office",
            "type":"Public Place"
        }
    ],
    "sg:phone":"+44 191 553 2863",
    "sg:postcode":"SR1 3QP",
    "sg:province":"Tyne and Wear",
    "sg:tags":[
        "housing",
        "local",
        "sheltered"
    ],
    "wof:name":"Gillhurst House",
    "wof:placetype":"venue"
},
  "geometry": {"coordinates":[-1.38629,54.90229],"type":"Point"}
}