{
  "type": "Feature",
  "properties": {
    "iso:country":"GB",
    "sg:address":"3a White Dirt Lane",
    "sg:city":"Waterlooville",
    "sg:classifiers":[
        {
            "category":"Professional",
            "type":"Services"
        }
    ],
    "sg:postcode":"PO8 0NB",
    "sg:province":"Hampshire",
    "sg:tags":[
        "caterer"
    ],
    "wof:name":"Alfred Guffick",
    "wof:placetype":"venue"
},
  "geometry": {"coordinates":[-1.0000400543,50.9351387024],"type":"Point"}
}