{
  "type": "Feature",
  "properties": {
    "iso:country":"GB",
    "sg:address":"Between 60-62 The Crest Way",
    "sg:city":"Chatham",
    "sg:classifiers":[
        {
            "category":"Government",
            "subcategory":"City Hall",
            "type":"Public Place"
        }
    ],
    "sg:phone":"+44 1634 844354",
    "sg:postcode":"ME5 0BD",
    "sg:province":"Kent",
    "wof:name":"Crestway Community Centre",
    "wof:placetype":"venue"
},
  "geometry": {"coordinates":[0.54118,51.36496],"type":"Point"}
}