{
  "type": "Feature",
  "properties": {
    "iso:country":"GB",
    "sg:address":"Park Road",
    "sg:city":"Wrexham",
    "sg:classifiers":[
        {
            "category":"Military Area",
            "subcategory":"Coast Guard Base",
            "type":"Public Place"
        }
    ],
    "sg:phone":"+44 1978 822231",
    "sg:postcode":"LL14 3YR",
    "sg:province":"Wrexham",
    "wof:name":"Radiotronic Uk",
    "wof:placetype":"venue"
},
  "geometry": {"coordinates":[-3.065704,52.975857],"type":"Point"}
}