{
  "type": "Feature",
  "properties": {
    "iso:country":"GB",
    "sg:address":"41a Whitton Rd",
    "sg:city":"Hounslow",
    "sg:classifiers":[
        {
            "category":"Professional",
            "subcategory":"Accounting & Tax Preparation",
            "type":"Services"
        }
    ],
    "sg:phone":"+44 20 8570 0230",
    "sg:postcode":"TW3 2DB",
    "sg:province":"Greater London",
    "sg:tags":[
        "accountant"
    ],
    "wof:name":"Argent Associates",
    "wof:placetype":"venue"
},
  "geometry": {"coordinates":[-0.362928,51.463982],"type":"Point"}
}