{
  "type": "Feature",
  "properties": {
    "iso:country":"GB",
    "sg:address":"345a Victoria Park Road",
    "sg:city":"London",
    "sg:classifiers":[
        {
            "category":"Arena",
            "subcategory":"Sports Club",
            "type":"Entertainment"
        }
    ],
    "sg:phone":"+44 20 8985 4125",
    "sg:postcode":"E9 5DX",
    "sg:province":"Greater London",
    "wof:name":"LITHUANIAN SPORTS & SOCIAL CLUB",
    "wof:placetype":"venue"
},
  "geometry": {"coordinates":[-0.034428,51.54398],"type":"Point"}
}