{
  "type": "Feature",
  "properties": {
    "iso:country":"GB",
    "sg:address":"23 Essington Light Industrial Estate, Bognop Road, Essington",
    "sg:city":"Wolverhampton",
    "sg:classifiers":[
        {
            "category":"Sports & Exercise",
            "subcategory":"Tennis Court",
            "type":"Entertainment"
        }
    ],
    "sg:phone":"+44 1922 401667",
    "sg:postcode":"WV11 2BH",
    "sg:province":"Staffordshire",
    "sg:tags":[
        "breakdown",
        "recovery"
    ],
    "wof:name":"J Boardman (Garages) Ltd.",
    "wof:placetype":"venue"
},
  "geometry": {"coordinates":[-2.121669,52.58865],"type":"Point"}
}