{
  "type": "Feature",
  "properties": {
    "addr:full":"168 Huddersfield Road Mirfield West Yorkshire WF14 8AN",
    "addr:housenumber":"168",
    "addr:postcode":"wf14 8an",
    "addr:street":"Huddersfield Road",
    "iso:country":"GB",
    "sg:address":"168 Huddersfield Road",
    "sg:city":"Mirfield",
    "sg:classifiers":[
        {
            "category":"Food & Beverages",
            "subcategory":"Fruits & Vegetables",
            "type":"Retail Goods"
        }
    ],
    "sg:postcode":"WF14 8AN",
    "sg:province":"West Yorkshire",
    "sg:tags":[
        "greengrocer"
    ],
    "wof:name":"Dysons Trade Reserve",
    "wof:placetype":"venue"
},
  "geometry": {"coordinates":[-1.6943750381,53.6740989685],"type":"Point"}
}