{
  "type": "Feature",
  "properties": {
    "iso:country":"GB",
    "sg:address":"46 Waites Yard, Burrowgate",
    "sg:city":"Penrith",
    "sg:classifiers":[
        {
            "category":"Taxi",
            "type":"Transportation"
        }
    ],
    "sg:phone":"+44 1768 895969",
    "sg:postcode":"CA11 7TA",
    "sg:province":"Cumbria",
    "sg:tags":[
        "mini",
        "cab"
    ],
    "wof:name":"Beacon Taxis",
    "wof:placetype":"venue"
},
  "geometry": {"coordinates":[-2.751385,54.66515],"type":"Point"}
}