{
  "type": "Feature",
  "properties": {
    "addr:full":"Harrytown, Romiley Stockport Cheshire SK6 3BU",
    "addr:postcode":"sk6 3bu",
    "addr:street":"Harrytown",
    "iso:country":"GB",
    "sg:address":"Harrytown, Romiley",
    "sg:city":"Stockport",
    "sg:classifiers":[
        {
            "category":"Education",
            "subcategory":"School",
            "type":"Public Place"
        }
    ],
    "sg:phone":"+44 161 430 5277",
    "sg:postcode":"SK6 3BU",
    "sg:province":"Cheshire",
    "sg:tags":[
        "local",
        "authority"
    ],
    "wof:name":"Stockport Metropolitan Borough Council",
    "wof:placetype":"venue"
},
  "geometry": {"coordinates":[-2.091184,53.413841],"type":"Point"}
}