{
  "type": "Feature",
  "properties": {
    "addr:full":"Bamar Works, Aston Hall Road, Aston Birmingham West Midlands B6 7LD",
    "addr:postcode":"b6 7ld",
    "addr:street":"Aston Hall Road",
    "iso:country":"GB",
    "sg:address":"Bamar Works, Aston Hall Road, Aston",
    "sg:city":"Birmingham",
    "sg:classifiers":[
        {
            "category":"Building & Trades",
            "subcategory":"Construction",
            "type":"Services"
        }
    ],
    "sg:postcode":"B6 7LD",
    "sg:province":"West Midlands",
    "sg:tags":[
        "joinery"
    ],
    "wof:name":"Solid Fabrications Ltd.",
    "wof:placetype":"venue"
},
  "geometry": {"coordinates":[-1.869979,52.506935],"type":"Point"}
}