{
  "type": "Feature",
  "properties": {
    "addr:full":"26 Borough Rd Dunstable Bedfordshire LU5 4DA",
    "addr:housenumber":"26",
    "addr:postcode":"lu5 4da",
    "addr:street":"Borough Rd",
    "iso:country":"GB",
    "sg:address":"26 Borough Rd",
    "sg:city":"Dunstable",
    "sg:classifiers":[
        {
            "category":"Building & Trades",
            "subcategory":"Landscaping Services",
            "type":"Services"
        }
    ],
    "sg:phone":"+44 1582 666380",
    "sg:postcode":"LU5 4DA",
    "sg:province":"Bedfordshire",
    "sg:tags":[
        "landscape",
        "contractor"
    ],
    "wof:name":"Greenacre Garden Services",
    "wof:placetype":"venue"
},
  "geometry": {"coordinates":[-0.5108370185,51.8817443848],"type":"Point"}
}