{
  "type": "Feature",
  "properties": {
    "iso:country":"GB",
    "sg:address":"142 Bury Old Road",
    "sg:city":"Manchester",
    "sg:classifiers":[
        {
            "category":"Organizations",
            "subcategory":"Religious Organization",
            "type":"Services"
        }
    ],
    "sg:phone":"+44 161 740 1825",
    "sg:postcode":"M8 4HD",
    "sg:province":"Greater Manchester",
    "sg:tags":[
        "organisation"
    ],
    "wof:name":"Zionist Central Council of Manchester & District",
    "wof:placetype":"venue"
},
  "geometry": {"coordinates":[-2.248769,53.518696],"type":"Point"}
}