{
  "type": "Feature",
  "properties": {
    "addr:full":"258 Stockport Road, Timperley Altrincham Cheshire WA15 7UT",
    "addr:housenumber":"258",
    "addr:postcode":"wa15 7ut",
    "addr:street":"Stockport Road",
    "iso:country":"GB",
    "sg:address":"258 Stockport Road, Timperley",
    "sg:city":"Altrincham",
    "sg:classifiers":[
        {
            "category":"Community Center",
            "subcategory":"Social",
            "type":"Public Place"
        }
    ],
    "sg:phone":"+44 161 904 8117",
    "sg:postcode":"WA15 7UT",
    "sg:province":"Cheshire",
    "sg:tags":[
        "frozen",
        "food",
        "freezer",
        "centre"
    ],
    "wof:name":"Iceland Foods Plc",
    "wof:placetype":"venue"
},
  "geometry": {"coordinates":[-2.3176419735,53.3975486755],"type":"Point"}
}