{
  "type": "Feature",
  "properties": {
    "addr:full":"9 Station Road, Middleton St George Darlington Durham DL2 1JG",
    "addr:housenumber":"9",
    "addr:postcode":"dl2 1jg",
    "addr:street":"Station Road Middleton",
    "iso:country":"GB",
    "sg:address":"9 Station Road, Middleton St George",
    "sg:city":"Darlington",
    "sg:classifiers":[
        {
            "category":"Manufacturing",
            "subcategory":"Signs",
            "type":"Manufacturing & Wholesale Goods"
        }
    ],
    "sg:phone":"+44 1325 332947",
    "sg:postcode":"DL2 1JG",
    "sg:province":"Durham",
    "sg:tags":[
        "writer"
    ],
    "wof:name":"Ian Rennolds",
    "wof:placetype":"venue"
},
  "geometry": {"coordinates":[-1.4705779552,54.5188560486],"type":"Point"}
}