{
  "type": "Feature",
  "properties": {
    "iso:country":"GB",
    "sg:address":"85 Northbrook St",
    "sg:city":"Newbury",
    "sg:classifiers":[
        {
            "category":"Shopping",
            "subcategory":"Clothing, Apparel, & Fashions",
            "type":"Retail Goods"
        }
    ],
    "sg:phone":"+44 1635 32603",
    "sg:postcode":"RG13 1AE",
    "sg:province":"Berkshire",
    "sg:tags":[
        "shop"
    ],
    "wof:name":"Hamells",
    "wof:placetype":"venue"
},
  "geometry": {"coordinates":[-1.324804,51.40379],"type":"Point"}
}