{
  "type": "Feature",
  "properties": {
    "addr:full":"39 High Street, Norley Warrington Cheshire WA6 8JD",
    "addr:housenumber":"39",
    "addr:postcode":"wa6 8jd",
    "addr:street":"High Street",
    "iso:country":"GB",
    "sg:address":"39 High Street, Norley",
    "sg:city":"Warrington",
    "sg:classifiers":[
        {
            "category":"Professional",
            "subcategory":"Management & Consulting",
            "type":"Services"
        }
    ],
    "sg:phone":"+44 1928 787536",
    "sg:postcode":"WA6 8JD",
    "sg:province":"Cheshire",
    "sg:tags":[
        "consultant",
        "business"
    ],
    "wof:name":"Norley Consulting",
    "wof:placetype":"venue"
},
  "geometry": {"coordinates":[-2.647811,53.246277],"type":"Point"}
}