{
  "type": "Feature",
  "properties": {
    "iso:country":"GB",
    "sg:address":"Lee Ho, Eves Corner",
    "sg:city":"Chelmsford",
    "sg:classifiers":[
        {
            "category":"Health Services",
            "subcategory":"Doctor",
            "type":"Services"
        }
    ],
    "sg:phone":"+44 1245 225522",
    "sg:postcode":"CM3 4QA",
    "sg:province":"Essex",
    "sg:tags":[
        "practitioners"
    ],
    "wof:name":"Sutcliff, J",
    "wof:placetype":"venue"
},
  "geometry": {"coordinates":[0.58215,51.717281],"type":"Point"}
}