{
  "type": "Feature",
  "properties": {
    "iso:country":"GB",
    "sg:address":"Eastfield Road, Fauldhouse",
    "sg:city":"Bathgate",
    "sg:classifiers":[
        {
            "category":"Health Services",
            "subcategory":"Nursing And Care Facility",
            "type":"Services"
        }
    ],
    "sg:phone":"+44 1501 772613",
    "sg:postcode":"EH47 9EF",
    "sg:province":"North Lanarkshire",
    "sg:tags":[
        "home"
    ],
    "wof:name":"Crofthead House Christian Nursing Home",
    "wof:placetype":"venue"
},
  "geometry": {"coordinates":[-3.7066040039,55.8278808594],"type":"Point"}
}