{
  "type": "Feature",
  "properties": {
    "iso:country":"GB",
    "sg:address":"Gurney House, Godinton Road",
    "sg:city":"Ashford",
    "sg:classifiers":[
        {
            "category":"Shopping",
            "subcategory":"Stationery & Office Supplies",
            "type":"Retail Goods"
        },
        {
            "category":"Professional",
            "subcategory":"Printing & Photocopies",
            "type":"Services"
        }
    ],
    "sg:phone":"+44 1233 610602",
    "sg:postcode":"TN23 1LH",
    "sg:province":"Kent",
    "sg:tags":[
        "duplicating",
        "copying"
    ],
    "wof:name":"Geerings of Ashford",
    "wof:placetype":"venue"
},
  "geometry": {"coordinates":[0.8626099825,51.1498718262],"type":"Point"}
}