{
  "type": "Feature",
  "properties": {
    "addr:full":"77 Hinckley Road Leicester Leicestershire LE3 0TD",
    "addr:housenumber":"77",
    "addr:postcode":"le3 0td",
    "addr:street":"Hinckley Road",
    "iso:country":"GB",
    "sg:address":"77 Hinckley Road",
    "sg:city":"Leicester",
    "sg:classifiers":[
        {
            "category":"Shopping",
            "subcategory":"News",
            "type":"Retail Goods"
        }
    ],
    "sg:phone":"+44 116 254 6111",
    "sg:postcode":"LE3 0TD",
    "sg:province":"Leicestershire",
    "sg:tags":[
        "newsagent"
    ],
    "wof:name":"Wedge's",
    "wof:placetype":"venue"
},
  "geometry": {"coordinates":[-1.150835,52.631664],"type":"Point"}
}