{
  "type": "Feature",
  "properties": {
    "iso:country":"GB",
    "sg:address":"Unit 11 Lyndean Industrial Estate, 141 Felixstowe Road",
    "sg:city":"London",
    "sg:classifiers":[
        {
            "category":"Food & Beverages",
            "subcategory":"Dairy",
            "type":"Retail Goods"
        }
    ],
    "sg:phone":"+44 20 8311 4634",
    "sg:postcode":"SE2 9SG",
    "sg:province":"Greater London",
    "sg:tags":[
        "produce"
    ],
    "wof:name":"Staple Dairy",
    "wof:placetype":"venue"
},
  "geometry": {"coordinates":[0.11884,51.492222],"type":"Point"}
}