{
  "type": "Feature",
  "properties": {
    "iso:country":"GB",
    "sg:address":"11 Cooke Close, South Lowestoft Industrial Estate",
    "sg:city":"Lowestoft",
    "sg:classifiers":[
        {
            "category":"Home & Garden",
            "subcategory":"Home Furnishings",
            "type":"Retail Goods"
        }
    ],
    "sg:postcode":"NR33 7NW",
    "sg:province":"Suffolk",
    "sg:tags":[
        "awning",
        "canopy",
        "blinds"
    ],
    "wof:name":"Premier Blinds & Fabrics Ltd.",
    "wof:placetype":"venue"
},
  "geometry": {"coordinates":[1.7182569504,52.446975708],"type":"Point"}
}