{
  "type": "Feature",
  "properties": {
    "iso:country":"GB",
    "sg:address":"33 High Street",
    "sg:city":"Rochester",
    "sg:classifiers":[
        {
            "category":"Shopping",
            "subcategory":"Antiques",
            "type":"Retail Goods"
        }
    ],
    "sg:postcode":"ME1 1LN",
    "sg:province":"Kent",
    "wof:name":"Hard Times",
    "wof:placetype":"venue"
},
  "geometry": {"coordinates":[0.5031509995,51.3906517029],"type":"Point"}
}