{
  "type": "Feature",
  "properties": {
    "addr:full":"9 Sycamore Road, Hollingwood Chesterfield Derbyshire S43 2HQ",
    "addr:housenumber":"9",
    "addr:postcode":"s43 2hq",
    "addr:street":"Sycamore Road",
    "iso:country":"GB",
    "sg:address":"9 Sycamore Road, Hollingwood",
    "sg:city":"Chesterfield",
    "sg:classifiers":[
        {
            "category":"Education",
            "subcategory":"School",
            "type":"Public Place"
        }
    ],
    "sg:phone":"+44 1246 476147",
    "sg:postcode":"S43 2HQ",
    "sg:province":"Derbyshire",
    "sg:tags":[
        "private",
        "tuition"
    ],
    "wof:name":"Janie's Mobile School",
    "wof:placetype":"venue"
},
  "geometry": {"coordinates":[-1.382875,53.265678],"type":"Point"}
}