{
  "type": "Feature",
  "properties": {
    "addr:full":"16 Overdale Av Sutton Coldfield Warwickshire B76 1HJ",
    "addr:housenumber":"16",
    "addr:postcode":"b76 1hj",
    "addr:street":"Overdale Av",
    "iso:country":"GB",
    "sg:address":"16 Overdale Av",
    "sg:city":"Sutton Coldfield",
    "sg:classifiers":[
        {
            "category":"Organizations",
            "subcategory":"Non-profit Organization",
            "type":"Services"
        }
    ],
    "sg:phone":"+44 121 351 3323",
    "sg:postcode":"B76 1HJ",
    "sg:province":"Warwickshire",
    "sg:tags":[
        "organisation",
        "voluntary",
        "charity"
    ],
    "wof:name":"Multiple Sclerosis Society Of Great Britain & Northern Ireland",
    "wof:placetype":"venue"
},
  "geometry": {"coordinates":[-1.795635,52.530502],"type":"Point"}
}