{
  "type": "Feature",
  "properties": {
    "addr:full":"44 Hylton Street Birmingham West Midlands B18 6HN",
    "addr:housenumber":"44",
    "addr:postcode":"b18 6hn",
    "addr:street":"Hylton Street",
    "iso:country":"GB",
    "sg:address":"44 Hylton Street",
    "sg:city":"Birmingham",
    "sg:classifiers":[
        {
            "category":"Shopping",
            "subcategory":"Comic Books",
            "type":"Retail Goods"
        }
    ],
    "sg:phone":"+44 121 507 1177",
    "sg:postcode":"B18 6HN",
    "sg:province":"West Midlands",
    "sg:tags":[
        "jeweller"
    ],
    "wof:name":"S & P Jewellery Services",
    "wof:placetype":"venue"
},
  "geometry": {"coordinates":[-1.912877,52.49128],"type":"Point"}
}