{
  "type": "Feature",
  "properties": {
    "addr:full":"44 Market Place Willenhall West Midlands WV13 2AA",
    "addr:housenumber":"44",
    "addr:postcode":"wv13 2aa",
    "addr:street":"Market Place",
    "iso:country":"GB",
    "sg:address":"44 Market Place",
    "sg:city":"Willenhall",
    "sg:classifiers":[
        {
            "category":"Home & Garden",
            "subcategory":"Hardware",
            "type":"Retail Goods"
        }
    ],
    "sg:phone":"+44 1902 605082",
    "sg:postcode":"WV13 2AA",
    "sg:province":"West Midlands",
    "wof:name":"Henly & Co. (Willenhall) Ltd.",
    "wof:placetype":"venue"
},
  "geometry": {"coordinates":[-2.0545558929,52.5834007263],"type":"Point"}
}