{
  "type": "Feature",
  "properties": {
    "addr:full":"7 Hankinson Way Salford Greater Manchester M6 5SD",
    "addr:housenumber":"7",
    "addr:postcode":"m6 5sd",
    "addr:street":"Hankinson Way",
    "iso:country":"GB",
    "sg:address":"7 Hankinson Way",
    "sg:city":"Salford",
    "sg:classifiers":[
        {
            "category":"Shopping",
            "subcategory":"Stationery & Office Supplies",
            "type":"Retail Goods"
        }
    ],
    "sg:postcode":"M6 5SD",
    "sg:province":"Greater Manchester",
    "wof:name":"Stationery Box Ltd",
    "wof:placetype":"venue"
},
  "geometry": {"coordinates":[-2.2861359119,53.4895133972],"type":"Point"}
}