{
  "type": "Feature",
  "properties": {
    "iso:country":"GB",
    "sg:address":"New Market Street",
    "sg:city":"Ulverston",
    "sg:classifiers":[
        {
            "category":"Home & Garden",
            "subcategory":"Furniture",
            "type":"Retail Goods"
        }
    ],
    "sg:phone":"+44 1229 584724",
    "sg:postcode":"LA12 7LJ",
    "sg:province":"Cumbria",
    "wof:name":"D S E Furnishings",
    "wof:placetype":"venue"
},
  "geometry": {"coordinates":[-3.09528,54.195789],"type":"Point"}
}