{
  "type": "Feature",
  "properties": {
    "iso:country":"GB",
    "sg:address":"1 Cumberland Street",
    "sg:city":"Skipton",
    "sg:classifiers":[
        {
            "category":"Food & Beverages",
            "subcategory":"Bakery",
            "type":"Retail Goods"
        }
    ],
    "sg:phone":"+44 1756 799501",
    "sg:postcode":"BD23 2NL",
    "sg:province":"Lancashire",
    "sg:tags":[
        "shop",
        "baker"
    ],
    "wof:name":"Farmhouse Fare Bakery",
    "wof:placetype":"venue"
},
  "geometry": {"coordinates":[-2.0172190666,53.9571914673],"type":"Point"}
}