{
  "type": "Feature",
  "properties": {
    "iso:country":"GB",
    "sg:address":"Unit 16, Dockray Hall Industrial Estate, Dockray Hall Road",
    "sg:city":"Kendal",
    "sg:classifiers":[
        {
            "category":"Building & Trades",
            "subcategory":"Construction",
            "type":"Services"
        }
    ],
    "sg:phone":"+44 1539 731857",
    "sg:postcode":"LA9 4RU",
    "sg:province":"Cumbria",
    "sg:tags":[
        "joinery",
        "joiner",
        "carpenter",
        "carpentry"
    ],
    "wof:name":"ENSUREOPEN LTD",
    "wof:placetype":"venue"
},
  "geometry": {"coordinates":[-2.7479379177,54.3352508545],"type":"Point"}
}