{
  "type": "Feature",
  "properties": {
    "addr:full":"20 Shelley Walk, Rhydyfelin Pontypridd Caerphilly CF37 5EY",
    "addr:housenumber":"20",
    "addr:postcode":"cf37 5ey",
    "addr:street":"Shelley Walk",
    "iso:country":"GB",
    "sg:address":"20 Shelley Walk, Rhydyfelin",
    "sg:city":"Pontypridd",
    "sg:classifiers":[
        {
            "category":"Professional",
            "subcategory":"Management & Consulting",
            "type":"Services"
        }
    ],
    "sg:phone":"+44 1443 405356",
    "sg:postcode":"CF37 5EY",
    "sg:province":"Caerphilly",
    "sg:tags":[
        "consultant",
        "business"
    ],
    "wof:name":"J C B Management Services",
    "wof:placetype":"venue"
},
  "geometry": {"coordinates":[-3.310254,51.589886],"type":"Point"}
}