{
  "type": "Feature",
  "properties": {
    "addr:full":"24 High West Street Dorchester Dorset DT1 1UW",
    "addr:housenumber":"24",
    "addr:postcode":"dt1 1uw",
    "addr:street":"High West Street",
    "iso:country":"GB",
    "sg:address":"24 High West Street",
    "sg:city":"Dorchester",
    "sg:classifiers":[
        {
            "category":"Insurance",
            "subcategory":"Insurance Agent",
            "type":"Services"
        }
    ],
    "sg:phone":"+44 1305 264368",
    "sg:postcode":"DT1 1UW",
    "sg:province":"Dorset",
    "wof:name":"Britannic Assurance Plc",
    "wof:placetype":"venue"
},
  "geometry": {"coordinates":[-2.439587,50.715076],"type":"Point"}
}