{
  "type": "Feature",
  "properties": {
    "addr:full":", Lingen Bucknell Herefordshire SY7 0DY",
    "addr:postcode":"sy7 0dy",
    "addr:street":"Herefordshire",
    "iso:country":"GB",
    "sg:address":", Lingen",
    "sg:city":"Bucknell",
    "sg:classifiers":[
        {
            "category":"Bars & Pubs",
            "type":"Food & Drink"
        }
    ],
    "sg:phone":"+44 1544 267322",
    "sg:postcode":"SY7 0DY",
    "sg:province":"Herefordshire",
    "sg:tags":[
        "pubs",
        "inn"
    ],
    "wof:name":"Royal George",
    "wof:placetype":"venue"
},
  "geometry": {"coordinates":[-2.945099,52.359005],"type":"Point"}
}