{
  "type": "Feature",
  "properties": {
    "addr:full":"7 Hill View, The Fairway Halifax West Yorkshire HX2 9QA",
    "addr:housenumber":"7",
    "addr:postcode":"hx2 9qa",
    "addr:street":"Hill View The Fairway",
    "iso:country":"GB",
    "sg:address":"7 Hill View, The Fairway",
    "sg:city":"Halifax",
    "sg:classifiers":[
        {
            "category":"Building & Trades",
            "subcategory":"Construction",
            "type":"Services"
        }
    ],
    "sg:postcode":"HX2 9QA",
    "sg:province":"West Yorkshire",
    "sg:tags":[
        "joiner",
        "carpenter"
    ],
    "wof:name":"P Dawson Joinery",
    "wof:placetype":"venue"
},
  "geometry": {"coordinates":[-1.8817839622,53.7587432861],"type":"Point"}
}