{
  "type": "Feature",
  "properties": {
    "addr:full":"4 Ruskin Clo Coventry Warwickshire CV6 1PN",
    "addr:housenumber":"4",
    "addr:postcode":"cv6 1pn",
    "iso:country":"GB",
    "sg:address":"4 Ruskin Clo",
    "sg:city":"Coventry",
    "sg:classifiers":[
        {
            "category":"Personal",
            "subcategory":"Psychics & Astrologers",
            "type":"Services"
        }
    ],
    "sg:phone":"+44 24 7659 2740",
    "sg:postcode":"CV6 1PN",
    "sg:province":"Warwickshire",
    "sg:tags":[
        "clairvoyant",
        "palmist"
    ],
    "wof:name":"Maureen",
    "wof:placetype":"venue"
},
  "geometry": {"coordinates":[-1.5474380255,52.4220275879],"type":"Point"}
}