{
  "type": "Feature",
  "properties": {
    "addr:full":"Llys Meddyg, Victoria Rd Caernarfon Gwynedd LL54 6HD",
    "addr:postcode":"ll54 6hd",
    "addr:street":"Llys;Victoria Rd",
    "iso:country":"GB",
    "sg:address":"Llys Meddyg, Victoria Rd",
    "sg:city":"Caernarfon",
    "sg:classifiers":[
        {
            "category":"Health Services",
            "subcategory":"Doctor",
            "type":"Services"
        }
    ],
    "sg:phone":"+44 1286 880207",
    "sg:postcode":"LL54 6HD",
    "sg:province":"Gwynedd",
    "sg:tags":[
        "practitioners"
    ],
    "wof:name":"Jones, J S",
    "wof:placetype":"venue"
},
  "geometry": {"coordinates":[-4.28127,53.052929],"type":"Point"}
}