{
  "type": "Feature",
  "properties": {
    "iso:country":"GB",
    "sg:address":"Carraway House, Durham Road Laindon",
    "sg:city":"Basildon",
    "sg:classifiers":[
        {
            "category":"Government",
            "subcategory":"Office",
            "type":"Public Place"
        }
    ],
    "sg:phone":"+44 1268 412241",
    "sg:postcode":"SS15 6PH",
    "sg:province":"Essex",
    "sg:tags":[
        "central"
    ],
    "wof:name":"The Probation Service",
    "wof:placetype":"venue"
},
  "geometry": {"coordinates":[0.4103490114,51.5749893188],"type":"Point"}
}