{
  "type": "Feature",
  "properties": {
    "iso:country":"GB",
    "sg:address":"Sunnyside Farm Whitelea La, Tansley",
    "sg:city":"Matlock",
    "sg:classifiers":[
        {
            "category":"Building & Trades",
            "subcategory":"Cleaning & Sanitation",
            "type":"Services"
        }
    ],
    "sg:postcode":"DE4 5FL",
    "sg:province":"Derbyshire",
    "sg:tags":[
        "blast"
    ],
    "wof:name":"Advance Surface Coatings",
    "wof:placetype":"venue"
},
  "geometry": {"coordinates":[-1.518149,53.131901],"type":"Point"}
}