{
  "type": "Feature",
  "properties": {
    "addr:full":"Hydes Farm, Abridge Romford Essex RM4 1TU",
    "addr:postcode":"rm4 1tu",
    "iso:country":"GB",
    "sg:address":"Hydes Farm, Abridge",
    "sg:city":"Romford",
    "sg:classifiers":[
        {
            "category":"Community Center",
            "type":"Public Place"
        }
    ],
    "sg:postcode":"RM4 1TU",
    "sg:province":"Essex",
    "sg:tags":[
        "conference",
        "room",
        "centre"
    ],
    "wof:name":"Hydes Farm Conference",
    "wof:placetype":"venue"
},
  "geometry": {"coordinates":[0.118167,51.651249],"type":"Point"}
}