{
  "type": "Feature",
  "properties": {
    "iso:country":"GB",
    "sg:address":"32 Castle Street",
    "sg:city":"Tayport",
    "sg:classifiers":[
        {
            "category":"Shopping",
            "subcategory":"Pharmacy",
            "type":"Retail Goods"
        }
    ],
    "sg:postcode":"DD6 9AF",
    "sg:province":"Fife",
    "sg:tags":[
        "pharmacist",
        "chemist"
    ],
    "wof:name":"Blacks Chemists",
    "wof:placetype":"venue"
},
  "geometry": {"coordinates":[-2.8806960583,56.4492950439],"type":"Point"}
}