{
  "type": "Feature",
  "properties": {
    "addr:full":"North St Ferryhill Durham DL17 8HX",
    "addr:postcode":"dl17 8hx",
    "addr:street":"North St",
    "iso:country":"GB",
    "sg:address":"North St",
    "sg:city":"Ferryhill",
    "sg:classifiers":[
        {
            "category":"Organizations",
            "subcategory":"Membership Organization",
            "type":"Services"
        }
    ],
    "sg:phone":"+44 1740 651844",
    "sg:postcode":"DL17 8HX",
    "sg:province":"Durham",
    "sg:tags":[
        "club"
    ],
    "wof:name":"Ferryhill Working Men's Club",
    "wof:placetype":"venue"
},
  "geometry": {"coordinates":[-1.551666,54.690346],"type":"Point"}
}