{
  "type": "Feature",
  "properties": {
    "addr:full":"11 Beach Road Paignton Devon TQ4 6AY",
    "addr:housenumber":"11",
    "addr:postcode":"tq4 6ay",
    "addr:street":"Beach Road",
    "iso:country":"GB",
    "sg:address":"11 Beach Road",
    "sg:city":"Paignton",
    "sg:classifiers":[
        {
            "category":"Travel",
            "subcategory":"Hotels & Motels",
            "type":"Entertainment"
        }
    ],
    "sg:phone":"+44 1803 665389",
    "sg:postcode":"TQ4 6AY",
    "sg:province":"Devon",
    "sg:tags":[
        "house",
        "guest"
    ],
    "wof:name":"Brampton Hotel",
    "wof:placetype":"venue"
},
  "geometry": {"coordinates":[-3.5622880459,50.4366226196],"type":"Point"}
}