{
  "type": "Feature",
  "properties": {
    "addr:full":"476 Price Street Birkenhead Merseyside CH41 8BQ",
    "addr:housenumber":"476",
    "addr:postcode":"ch41 8bq",
    "addr:street":"Price Street",
    "iso:country":"GB",
    "sg:address":"476 Price Street",
    "sg:city":"Birkenhead",
    "sg:classifiers":[
        {
            "category":"Bars & Pubs",
            "type":"Food & Drink"
        }
    ],
    "sg:postcode":"CH41 8BQ",
    "sg:province":"Merseyside",
    "sg:tags":[
        "pubs",
        "inn"
    ],
    "wof:name":"The Pacific Hotel",
    "wof:placetype":"venue"
},
  "geometry": {"coordinates":[-3.039748,53.399666],"type":"Point"}
}