{
  "type": "Feature",
  "properties": {
    "iso:country":"GB",
    "sg:address":"54 Darby Street",
    "sg:city":"Ormskirk",
    "sg:classifiers":[
        {
            "category":"Shopping",
            "subcategory":"Clothing, Apparel, & Fashions",
            "type":"Retail Goods"
        }
    ],
    "sg:phone":"+44 1695 572372",
    "sg:postcode":"L39 2DG",
    "sg:province":"Lancashire",
    "sg:tags":[
        "lingerie",
        "hosiery"
    ],
    "wof:name":"Nufold Bindings",
    "wof:placetype":"venue"
},
  "geometry": {"coordinates":[-2.8863,53.566277],"type":"Point"}
}