{
  "type": "Feature",
  "properties": {
    "iso:country":"GB",
    "sg:address":"Oxney Flatt, Crossroad",
    "sg:city":"Darlington",
    "sg:classifiers":[
        {
            "category":"Farming",
            "subcategory":"Livestock Farm",
            "type":"Manufacturing & Wholesale Goods"
        }
    ],
    "sg:postcode":"DL2 2SD",
    "sg:province":"Durham",
    "sg:tags":[
        "others"
    ],
    "wof:name":"E W & M L Pratt",
    "wof:placetype":"venue"
},
  "geometry": {"coordinates":[-1.57495,54.497879],"type":"Point"}
}