{
  "type": "Feature",
  "properties": {
    "addr:full":"Townsend Cottage, Dilwyn Hereford Herefordshire HR4 8HL",
    "addr:housenumber":"dilwyn",
    "addr:postcode":"hr4 8hl",
    "iso:country":"GB",
    "sg:address":"Townsend Cottage, Dilwyn",
    "sg:city":"Hereford",
    "sg:classifiers":[
        {
            "category":"Building & Trades",
            "subcategory":"Plumbing",
            "type":"Services"
        },
        {
            "category":"Building & Trades",
            "subcategory":"Construction",
            "type":"Services"
        }
    ],
    "sg:phone":"+44 1544 318528",
    "sg:postcode":"HR4 8HL",
    "sg:province":"Herefordshire",
    "sg:tags":[
        "heating",
        "contractor"
    ],
    "wof:name":"Peter Charles Stilwell",
    "wof:placetype":"venue"
},
  "geometry": {"coordinates":[-2.8581209183,52.1895332336],"type":"Point"}
}