{
  "type": "Feature",
  "properties": {
    "iso:country":"GB",
    "sg:address":"528 St. Vincent St",
    "sg:city":"Glasgow",
    "sg:classifiers":[
        {
            "category":"Food & Beverages",
            "subcategory":"Meat & Fish",
            "type":"Retail Goods"
        }
    ],
    "sg:postcode":"G3 8XZ",
    "sg:province":"Glasgow City",
    "sg:tags":[
        "chip"
    ],
    "wof:name":"Micheles",
    "wof:placetype":"venue"
},
  "geometry": {"coordinates":[-4.2775130272,55.8632698059],"type":"Point"}
}