{
  "type": "Feature",
  "properties": {
    "addr:full":"9 The Woolmead Farnham Surrey GU9 7TY",
    "addr:housenumber":"9",
    "addr:postcode":"gu9 7ty",
    "addr:street":"Woolmead Farnham",
    "iso:country":"GB",
    "sg:address":"9 The Woolmead",
    "sg:city":"Farnham",
    "sg:classifiers":[
        {
            "category":"Government",
            "subcategory":"Office",
            "type":"Public Place"
        }
    ],
    "sg:phone":"+44 1252 736000",
    "sg:postcode":"GU9 7TY",
    "sg:province":"Surrey",
    "sg:tags":[
        "central"
    ],
    "wof:name":"Wey Valley West Inland Revenue",
    "wof:placetype":"venue"
},
  "geometry": {"coordinates":[-0.7983689904,51.2118492126],"type":"Point"}
}