{
  "type": "Feature",
  "properties": {
    "addr:full":"536 Tottenham High Road London Greater London N17 6SB",
    "addr:housenumber":"536",
    "addr:postcode":"n17 6sb",
    "addr:street":"High Road",
    "iso:country":"GB",
    "sg:address":"536 Tottenham High Road",
    "sg:city":"London",
    "sg:classifiers":[
        {
            "category":"Shopping",
            "subcategory":"Comic Books",
            "type":"Retail Goods"
        }
    ],
    "sg:phone":"+44 20 8801 1187",
    "sg:postcode":"N17 6SB",
    "sg:province":"Greater London",
    "sg:tags":[
        "jeweller"
    ],
    "wof:name":"Paradise Gems",
    "wof:placetype":"venue"
},
  "geometry": {"coordinates":[-0.06885,51.595871],"type":"Point"}
}