{
  "type": "Feature",
  "properties": {
    "iso:country":"GB",
    "sg:address":"221 Hamil Road",
    "sg:city":"Stoke-on-trent",
    "sg:classifiers":[
        {
            "category":"Food & Beverages",
            "subcategory":"Liquor & Beverages",
            "type":"Retail Goods"
        }
    ],
    "sg:postcode":"ST6 1BA",
    "sg:province":"Staffordshire",
    "sg:tags":[
        "beer",
        "spirit",
        "wines"
    ],
    "wof:name":"Jobi's",
    "wof:placetype":"venue"
},
  "geometry": {"coordinates":[-2.187577,53.051399],"type":"Point"}
}