{
  "type": "Feature",
  "properties": {
    "addr:full":"Invicta House Baker Street, Farthinghoe Brackley Buckinghamshire NN13 5PH",
    "addr:postcode":"nn13 5ph",
    "addr:street":"Baker Street",
    "iso:country":"GB",
    "sg:address":"Invicta House Baker Street, Farthinghoe",
    "sg:city":"Brackley",
    "sg:classifiers":[
        {
            "category":"Real Estate",
            "subcategory":"Real Estate Agent",
            "type":"Services"
        }
    ],
    "sg:postcode":"NN13 5PH",
    "sg:province":"Buckinghamshire",
    "wof:name":"Installation & Maintenance Services Ltd",
    "wof:placetype":"venue"
},
  "geometry": {"coordinates":[-1.219657,52.053661],"type":"Point"}
}