{
  "type": "Feature",
  "properties": {
    "addr:full":"48 Newhampton Road West, Whitmore Reans Wolverhampton Shropshire WV6 0RY",
    "addr:housenumber":"48",
    "addr:postcode":"wv6 0ry",
    "addr:street":"Newhampton Road West;Reans",
    "iso:country":"GB",
    "sg:address":"48 Newhampton Road West, Whitmore Reans",
    "sg:city":"Wolverhampton",
    "sg:classifiers":[
        {
            "category":"Professional",
            "subcategory":"Engineering",
            "type":"Services"
        }
    ],
    "sg:phone":"+44 1902 422968",
    "sg:postcode":"WV6 0RY",
    "sg:province":"Shropshire",
    "sg:tags":[
        "contractor",
        "electrical",
        "engineer"
    ],
    "wof:name":"Burns & Dudgon Ltd.",
    "wof:placetype":"venue"
},
  "geometry": {"coordinates":[-2.148194,52.5947],"type":"Point"}
}