{
  "type": "Feature",
  "properties": {
    "addr:full":"490-492 Gorgie Rd Edinburgh City of Edinburgh EH11 3HF",
    "addr:housenumber":"490-492",
    "addr:postcode":"eh11 3hf",
    "addr:street":"Gorgie Rd",
    "iso:country":"GB",
    "sg:address":"490-492 Gorgie Rd",
    "sg:city":"Edinburgh",
    "sg:classifiers":[
        {
            "category":"Professional",
            "subcategory":"Engineering",
            "type":"Services"
        }
    ],
    "sg:postcode":"EH11 3HF",
    "sg:province":"City of Edinburgh",
    "sg:tags":[
        "design",
        "engineer"
    ],
    "wof:name":"Myers,A F,Partnership",
    "wof:placetype":"venue"
},
  "geometry": {"coordinates":[-3.2504320145,55.9320755005],"type":"Point"}
}