{
  "type": "Feature",
  "properties": {
    "addr:full":"Unit Abc Victoria Works, Fallows Road Sparkbrook Birmingham West Midlands B11 1PQ",
    "addr:postcode":"b11 1pq",
    "addr:street":"Fallows Road",
    "iso:country":"GB",
    "sg:address":"Unit Abc Victoria Works, Fallows Road Sparkbrook",
    "sg:city":"Birmingham",
    "sg:classifiers":[
        {
            "category":"Wholesale",
            "subcategory":"Scrap",
            "type":"Manufacturing & Wholesale Goods"
        }
    ],
    "sg:postcode":"B11 1PQ",
    "sg:province":"West Midlands",
    "sg:tags":[
        "breaker",
        "dismantlers"
    ],
    "wof:name":"B & D Engineering Services Ltd.",
    "wof:placetype":"venue"
},
  "geometry": {"coordinates":[-1.8759969473,52.4630889893],"type":"Point"}
}