{
  "type": "Feature",
  "properties": {
    "addr:full":"16 Ravenoak Rd Cheadle Cheshire SK8 7DL",
    "addr:housenumber":"16",
    "addr:postcode":"sk8 7dl",
    "addr:street":"Ravenoak Rd Cheadle",
    "iso:country":"GB",
    "sg:address":"16 Ravenoak Rd",
    "sg:city":"Cheadle",
    "sg:classifiers":[
        {
            "category":"Building & Trades",
            "subcategory":"Construction",
            "type":"Services"
        }
    ],
    "sg:phone":"+44 161 439 0102",
    "sg:postcode":"SK8 7DL",
    "sg:province":"Cheshire",
    "sg:tags":[
        "builder"
    ],
    "wof:name":"D Tibbott Joiners & Building Contractors",
    "wof:placetype":"venue"
},
  "geometry": {"coordinates":[-2.1824100018,53.3716697693],"type":"Point"}
}