{
  "type": "Feature",
  "properties": {
    "addr:full":"35 Cheapside Spennymoor Durham DL16 6QF",
    "addr:housenumber":"35",
    "addr:postcode":"dl16 6qf",
    "addr:street":"Cheapside",
    "iso:country":"GB",
    "sg:address":"35 Cheapside",
    "sg:city":"Spennymoor",
    "sg:classifiers":[
        {
            "category":"Farming",
            "subcategory":"Fish & Marine Products",
            "type":"Manufacturing & Wholesale Goods"
        }
    ],
    "sg:phone":"+44 1388 814319",
    "sg:postcode":"DL16 6QF",
    "sg:province":"Durham",
    "sg:tags":[
        "fishmonger"
    ],
    "wof:name":"Lawsons",
    "wof:placetype":"venue"
},
  "geometry": {"coordinates":[-1.599795,54.700401],"type":"Point"}
}