{
  "type": "Feature",
  "properties": {
    "addr:full":"432 Buxton Road Stockport Cheshire SK2 7JQ",
    "addr:housenumber":"432",
    "addr:postcode":"sk2 7jq",
    "addr:street":"Buxton Road",
    "iso:country":"GB",
    "sg:address":"432 Buxton Road",
    "sg:city":"Stockport",
    "sg:classifiers":[
        {
            "category":"Health Services",
            "subcategory":"Doctor",
            "type":"Services"
        }
    ],
    "sg:phone":"+44 161 483 9333",
    "sg:postcode":"SK2 7JQ",
    "sg:province":"Cheshire",
    "sg:tags":[
        "surgeon",
        "practitioners"
    ],
    "wof:name":"Dr I D Nuttall",
    "wof:placetype":"venue"
},
  "geometry": {"coordinates":[-2.1310579777,53.3862342834],"type":"Point"}
}