{
  "type": "Feature",
  "properties": {
    "addr:full":"Stewarton Kilmarnock East Ayrshire KA3 3ED",
    "addr:postcode":"ka3 3ed",
    "addr:street":"East",
    "iso:country":"GB",
    "sg:address":"Stewarton",
    "sg:city":"Kilmarnock",
    "sg:classifiers":[
        {
            "category":"Travel",
            "subcategory":"Hotels & Motels",
            "type":"Entertainment"
        }
    ],
    "sg:postcode":"KA3 3ED",
    "sg:province":"East Ayrshire",
    "wof:name":"The Chapeltoun House Hotel",
    "wof:placetype":"venue"
},
  "geometry": {"coordinates":[-4.5529899597,55.6650505066],"type":"Point"}
}