{
  "type": "Feature",
  "properties": {
    "addr:full":"31 Brunswick Rd Buckley Denbighshire CH7 2ED",
    "addr:housenumber":"31",
    "addr:postcode":"ch7 2ed",
    "addr:street":"Brunswick Rd",
    "iso:country":"GB",
    "sg:address":"31 Brunswick Rd",
    "sg:city":"Buckley",
    "sg:classifiers":[
        {
            "category":"Professional",
            "subcategory":"Management & Consulting",
            "type":"Services"
        },
        {
            "category":"Professional",
            "subcategory":"Advertising",
            "type":"Services"
        }
    ],
    "sg:postcode":"CH7 2ED",
    "sg:province":"Denbighshire",
    "sg:tags":[
        "marketing",
        "agency",
        "consultant"
    ],
    "wof:name":"Tinsley,Barbara,",
    "wof:placetype":"venue"
},
  "geometry": {"coordinates":[-3.078201,53.168175],"type":"Point"}
}