{
  "type": "Feature",
  "properties": {
    "addr:full":"Lincoln Road, Bassingham Lincoln Lincolnshire LN5 9HQ",
    "addr:postcode":"ln5 9hq",
    "addr:street":"Lincoln Road",
    "iso:country":"GB",
    "sg:address":"Lincoln Road, Bassingham",
    "sg:city":"Lincoln",
    "sg:classifiers":[
        {
            "category":"Education",
            "subcategory":"School",
            "type":"Public Place"
        },
        {
            "category":"Government",
            "subcategory":"Office",
            "type":"Public Place"
        }
    ],
    "sg:phone":"+44 1522 788395",
    "sg:postcode":"LN5 9HQ",
    "sg:province":"Lincolnshire",
    "sg:tags":[
        "local",
        "authority"
    ],
    "wof:name":"Bassingham County Primary School",
    "wof:placetype":"venue"
},
  "geometry": {"coordinates":[-0.6389759779,53.1281890869],"type":"Point"}
}