{
  "type": "Feature",
  "properties": {
    "addr:full":"Unit S Vulcan Business Centre, Vulcan Rd Leicester Leicestershire LE5 3EE",
    "addr:postcode":"le5 3ee",
    "addr:street":"Vulcan Rd",
    "iso:country":"GB",
    "sg:address":"Unit S Vulcan Business Centre, Vulcan Rd",
    "sg:city":"Leicester",
    "sg:classifiers":[
        {
            "category":"Autos & Motor Vehicles",
            "subcategory":"Auto Supplies",
            "type":"Retail Goods"
        }
    ],
    "sg:phone":"+44 116 262 9727",
    "sg:postcode":"LE5 3EE",
    "sg:province":"Leicestershire",
    "sg:tags":[
        "component"
    ],
    "wof:name":"Central Car Parts",
    "wof:placetype":"venue"
},
  "geometry": {"coordinates":[-1.1122699976,52.6370201111],"type":"Point"}
}