{
  "type": "Feature",
  "properties": {
    "iso:country":"GB",
    "sg:address":"Newline Industrial Estate, Newline",
    "sg:city":"Bacup",
    "sg:classifiers":[
        {
            "category":"Professional",
            "subcategory":"Engineering",
            "type":"Services"
        }
    ],
    "sg:postcode":"OL13 9RW",
    "sg:province":"Lancashire",
    "wof:name":"Mattress Production Technology Group Ltd.",
    "wof:placetype":"venue"
},
  "geometry": {"coordinates":[-2.194012,53.692894],"type":"Point"}
}