{
  "type": "Feature",
  "properties": {
    "addr:full":"Old Road, Brixton Plymouth Devon PL8 2BS",
    "addr:postcode":"pl8 2bs",
    "addr:street":"Old Road",
    "iso:country":"GB",
    "sg:address":"Old Road, Brixton",
    "sg:city":"Plymouth",
    "sg:classifiers":[
        {
            "category":"Farming",
            "subcategory":"Nursery",
            "type":"Manufacturing & Wholesale Goods"
        }
    ],
    "sg:postcode":"PL8 2BS",
    "sg:province":"Devon",
    "sg:tags":[
        "creche"
    ],
    "wof:name":"Valerie Nyree",
    "wof:placetype":"venue"
},
  "geometry": {"coordinates":[-4.033461,50.351555],"type":"Point"}
}