{
  "type": "Feature",
  "properties": {
    "iso:country":"GB",
    "sg:address":"Wilton Road",
    "sg:city":"Salisbury",
    "sg:classifiers":[
        {
            "category":"Autos & Motor Vehicles",
            "subcategory":"Fuel & Gas Station",
            "type":"Retail Goods"
        }
    ],
    "sg:postcode":"SP2 7EE",
    "sg:province":"Wiltshire",
    "sg:tags":[
        "petrol",
        "filling"
    ],
    "wof:name":"New Rampart Service Station",
    "wof:placetype":"venue"
},
  "geometry": {"coordinates":[-1.8219619989,51.0753326416],"type":"Point"}
}