{
  "type": "Feature",
  "properties": {
    "iso:country":"GB",
    "sg:address":"28 Yarmouth Road",
    "sg:city":"North Walsham",
    "sg:classifiers":[
        {
            "category":"Health Services",
            "subcategory":"Nursing And Care Facility",
            "type":"Services"
        },
        {
            "category":"Social Services",
            "subcategory":"Retirement Home",
            "type":"Services"
        }
    ],
    "sg:phone":"+44 1692 404502",
    "sg:postcode":"NR28 9AT",
    "sg:province":"Norfolk",
    "sg:tags":[
        "residential"
    ],
    "wof:name":"Aitken House",
    "wof:placetype":"venue"
},
  "geometry": {"coordinates":[1.388776,52.817963],"type":"Point"}
}