{
  "type": "Feature",
  "properties": {
    "addr:full":"54 Aneurin Crescent Brynmawr Blaenau Gwent NP3 4RR",
    "addr:housenumber":"54",
    "addr:postcode":"np3 4rr",
    "addr:street":"Aneurin Crescent",
    "iso:country":"GB",
    "sg:address":"54 Aneurin Crescent",
    "sg:city":"Brynmawr",
    "sg:classifiers":[
        {
            "category":"Professional",
            "subcategory":"Accounting & Tax Preparation",
            "type":"Services"
        }
    ],
    "sg:phone":"+44 1495 310903",
    "sg:postcode":"NP3 4RR",
    "sg:province":"Blaenau Gwent",
    "sg:tags":[
        "accountant"
    ],
    "wof:name":"Robert Smith & Co",
    "wof:placetype":"venue"
},
  "geometry": {"coordinates":[-3.1738140583,51.8050689697],"type":"Point"}
}