{
  "type": "Feature",
  "properties": {
    "addr:full":"45 - 47 Stratford Rd Newcastle-upon-tyne Tyne and Wear NE6 5PB",
    "addr:housenumber":"47",
    "addr:postcode":"ne6 5pb",
    "addr:street":"Stratford Rd",
    "iso:country":"GB",
    "sg:address":"45 - 47 Stratford Rd",
    "sg:city":"Newcastle-upon-tyne",
    "sg:classifiers":[
        {
            "category":"Travel",
            "subcategory":"Hotels & Motels",
            "type":"Entertainment"
        }
    ],
    "sg:postcode":"NE6 5PB",
    "sg:province":"Tyne and Wear",
    "sg:tags":[
        "house",
        "guest"
    ],
    "wof:name":"Stratford Guest House",
    "wof:placetype":"venue"
},
  "geometry": {"coordinates":[-1.5894889832,54.9788589478],"type":"Point"}
}