{
  "type": "Feature",
  "properties": {
    "iso:country":"GB",
    "sg:address":"157 High Street, Wanstead",
    "sg:city":"London",
    "sg:classifiers":[
        {
            "category":"Recreation",
            "type":"Entertainment"
        }
    ],
    "sg:phone":"+44 20 8989 4384",
    "sg:postcode":"E11 2RL",
    "sg:province":"Greater London",
    "sg:tags":[
        "snooker",
        "billiards",
        "pool"
    ],
    "wof:name":"Wanstead Snooker Centre",
    "wof:placetype":"venue"
},
  "geometry": {"coordinates":[0.0277100001,51.5766487122],"type":"Point"}
}