{
  "type": "Feature",
  "properties": {
    "addr:full":"Unit 5, Drake House Way, Waterthorpe Sheffield South Yorkshire S20 7JJ",
    "addr:housenumber":"unit 5 drake",
    "addr:postcode":"s20 7jj",
    "addr:street":"House Way",
    "iso:country":"GB",
    "sg:address":"Unit 5, Drake House Way, Waterthorpe",
    "sg:city":"Sheffield",
    "sg:classifiers":[
        {
            "category":"Home & Garden",
            "subcategory":"Furniture",
            "type":"Retail Goods"
        }
    ],
    "sg:phone":"+44 114 251 1727",
    "sg:postcode":"S20 7JJ",
    "sg:province":"South Yorkshire",
    "wof:name":"Textile World",
    "wof:placetype":"venue"
},
  "geometry": {"coordinates":[-1.3546839952,53.3434944153],"type":"Point"}
}