{
  "type": "Feature",
  "properties": {
    "iso:country":"GB",
    "sg:address":"Eastoft Road, Crowle",
    "sg:city":"Scunthorpe",
    "sg:classifiers":[
        {
            "category":"Autos & Motor Vehicles",
            "subcategory":"Automobile Sales",
            "type":"Retail Goods"
        }
    ],
    "sg:phone":"+44 1724 710319",
    "sg:postcode":"DN17 4LP",
    "sg:province":"Lincolnshire",
    "sg:tags":[
        "car"
    ],
    "wof:name":"F Long Howard & Son Ltd.",
    "wof:placetype":"venue"
},
  "geometry": {"coordinates":[-0.832983017,53.606552124],"type":"Point"}
}