{
  "type": "Feature",
  "properties": {
    "addr:full":"1 Cuxton Ho, Cuxton Rd Rochester Kent ME2 2BT",
    "addr:housenumber":"1",
    "addr:postcode":"me2 2bt",
    "addr:street":"Cuxton Ho Cuxton Rd",
    "iso:country":"GB",
    "sg:address":"1 Cuxton Ho, Cuxton Rd",
    "sg:city":"Rochester",
    "sg:classifiers":[
        {
            "category":"Professional",
            "subcategory":"Engineering",
            "type":"Services"
        }
    ],
    "sg:phone":"+44 1634 290356",
    "sg:postcode":"ME2 2BT",
    "sg:province":"Kent",
    "sg:tags":[
        "contractor",
        "electrical",
        "engineer"
    ],
    "wof:name":"C J Evans & Son (Electrical Services) Ltd",
    "wof:placetype":"venue"
},
  "geometry": {"coordinates":[0.4887830019,51.3963699341],"type":"Point"}
}