{
  "type": "Feature",
  "properties": {
    "iso:country":"GB",
    "sg:address":"26 Knowle Avenue",
    "sg:city":"Blackpool",
    "sg:classifiers":[
        {
            "category":"Travel",
            "subcategory":"Hotels & Motels",
            "type":"Entertainment"
        }
    ],
    "sg:phone":"+44 1253 352617",
    "sg:postcode":"FY2 9RX",
    "sg:province":"Lancashire",
    "wof:name":"Silverdale Private Hotel",
    "wof:placetype":"venue"
},
  "geometry": {"coordinates":[-3.051343,53.837929],"type":"Point"}
}