{
  "type": "Feature",
  "properties": {
    "addr:full":"Orecombe, Loxwood Road, Alfold Cranleigh Surrey GU6 8HL",
    "addr:postcode":"gu6 8hl",
    "addr:street":"Loxwood Road",
    "iso:country":"GB",
    "sg:address":"Orecombe, Loxwood Road, Alfold",
    "sg:city":"Cranleigh",
    "sg:classifiers":[
        {
            "category":"Building & Trades",
            "subcategory":"Construction",
            "type":"Services"
        }
    ],
    "sg:phone":"+44 1403 752459",
    "sg:postcode":"GU6 8HL",
    "sg:province":"Surrey",
    "sg:tags":[
        "builder"
    ],
    "wof:name":"Sunridge Building Services",
    "wof:placetype":"venue"
},
  "geometry": {"coordinates":[-0.5179370046,51.0959701538],"type":"Point"}
}