{
  "type": "Feature",
  "properties": {
    "iso:country":"GB",
    "sg:address":"23 Currievale Drive",
    "sg:city":"Currie",
    "sg:classifiers":[
        {
            "category":"Home & Garden",
            "subcategory":"Household Appliances",
            "type":"Retail Goods"
        }
    ],
    "sg:phone":"+44 131 449 2924",
    "sg:postcode":"EH14 5RN",
    "sg:province":"City of Edinburgh",
    "sg:tags":[
        "electrical"
    ],
    "wof:name":"Alan Stewart",
    "wof:placetype":"venue"
},
  "geometry": {"coordinates":[-3.319442,55.897743],"type":"Point"}
}