{
  "type": "Feature",
  "properties": {
    "addr:full":"Enterprise House Norwich Norfolk NR15 1EN",
    "addr:postcode":"nr15 1en",
    "addr:street":"Norwich",
    "iso:country":"GB",
    "sg:address":"Enterprise House",
    "sg:city":"Norwich",
    "sg:classifiers":[
        {
            "category":"Shopping",
            "subcategory":"Bicycles & Sporting Goods",
            "type":"Retail Goods"
        }
    ],
    "sg:postcode":"NR15 1EN",
    "sg:province":"Norfolk",
    "sg:tags":[
        "equipment",
        "marine",
        "supply"
    ],
    "wof:name":"Britannia Marine Towing Equipment Ltd.",
    "wof:placetype":"venue"
},
  "geometry": {"coordinates":[1.3351,52.52969],"type":"Point"}
}