{
  "type": "Feature",
  "properties": {
    "addr:full":"Stony La Bradford West Yorkshire BD2 2HL",
    "addr:postcode":"bd2 2hl",
    "addr:street":"Stony La Bradford West",
    "iso:country":"GB",
    "sg:address":"Stony La",
    "sg:city":"Bradford",
    "sg:classifiers":[
        {
            "category":"Bars & Pubs",
            "type":"Food & Drink"
        }
    ],
    "sg:phone":"+44 1274 639182",
    "sg:postcode":"BD2 2HL",
    "sg:province":"West Yorkshire",
    "sg:tags":[
        "pubs",
        "inn"
    ],
    "wof:name":"The Royal Oak",
    "wof:placetype":"venue"
},
  "geometry": {"coordinates":[-1.723322,53.82122],"type":"Point"}
}