{
  "type": "Feature",
  "properties": {
    "iso:country":"GB",
    "sg:address":"351 Carmunnock Road, Croftfoot",
    "sg:city":"Glasgow",
    "sg:classifiers":[
        {
            "category":"Food & Beverages",
            "subcategory":"Supermarket",
            "type":"Retail Goods"
        }
    ],
    "sg:phone":"+44 141 634 6725",
    "sg:postcode":"G44 5HH",
    "sg:province":"East Renfrewshire",
    "wof:name":"Somerfield",
    "wof:placetype":"venue"
},
  "geometry": {"coordinates":[-4.244473,55.811092],"type":"Point"}
}