{
  "type": "Feature",
  "properties": {
    "addr:full":"Offley Road Sandbach Cheshire CW11 1GY",
    "addr:postcode":"cw11 1gy",
    "addr:street":"Offley Road",
    "iso:country":"GB",
    "sg:address":"Offley Road",
    "sg:city":"Sandbach",
    "sg:classifiers":[
        {
            "category":"Education",
            "subcategory":"School",
            "type":"Public Place"
        },
        {
            "category":"Government",
            "subcategory":"Office",
            "type":"Public Place"
        }
    ],
    "sg:phone":"+44 1270 764894",
    "sg:postcode":"CW11 1GY",
    "sg:province":"Cheshire",
    "sg:tags":[
        "local",
        "authority"
    ],
    "wof:name":"Cheshire County Council",
    "wof:placetype":"venue"
},
  "geometry": {"coordinates":[-2.363879,53.148636],"type":"Point"}
}