{
  "type": "Feature",
  "properties": {
    "iso:country":"GB",
    "sg:address":"2 Dukes Gate, Acton Lane",
    "sg:city":"London",
    "sg:classifiers":[
        {
            "category":"Shopping",
            "subcategory":"Computers & Home Electronics",
            "type":"Retail Goods"
        },
        {
            "category":"Professional",
            "subcategory":"Computer Services",
            "type":"Services"
        }
    ],
    "sg:phone":"+44 20 8742 2165",
    "sg:postcode":"W4 5DX",
    "sg:province":"Greater London",
    "sg:tags":[
        "software",
        "sales",
        "system"
    ],
    "sg:website":"http://www.ascent400.com",
    "wof:name":"Ascent Information Technology Ltd",
    "wof:placetype":"venue"
},
  "geometry": {"coordinates":[-0.268059,51.493752],"type":"Point"}
}