{
  "type": "Feature",
  "properties": {
    "addr:full":"Unit 2, 20 Brook Road London Greater London N22 6TR",
    "addr:housenumber":"unit;20",
    "addr:postcode":"n22 6tr",
    "addr:street":"Brook Road",
    "iso:country":"GB",
    "sg:address":"Unit 2, 20 Brook Road",
    "sg:city":"London",
    "sg:classifiers":[
        {
            "category":"Personal",
            "type":"Services"
        }
    ],
    "sg:postcode":"N22 6TR",
    "sg:province":"Greater London",
    "sg:tags":[
        "dressmaker"
    ],
    "wof:name":"Marina Fashion",
    "wof:placetype":"venue"
},
  "geometry": {"coordinates":[-0.111944,51.593838],"type":"Point"}
}