{
  "type": "Feature",
  "properties": {
    "iso:country":"GB",
    "sg:address":"19-23 Blackfriars Road",
    "sg:city":"London",
    "sg:classifiers":[
        {
            "category":"Building & Trades",
            "subcategory":"Cleaning & Sanitation",
            "type":"Services"
        }
    ],
    "sg:phone":"+44 20 7902 2000",
    "sg:postcode":"SE1 8NY",
    "sg:province":"Greater London",
    "sg:tags":[
        "facility"
    ],
    "wof:name":"Building & Property (Holdings) Ltd.",
    "wof:placetype":"venue"
},
  "geometry": {"coordinates":[-0.1045489982,51.5070571899],"type":"Point"}
}