{
  "type": "Feature",
  "properties": {
    "iso:country":"GB",
    "sg:address":"Tor Court Farm, Torbryan",
    "sg:city":"Newton Abbot",
    "sg:classifiers":[
        {
            "category":"Farming",
            "subcategory":"Livestock Farm",
            "type":"Manufacturing & Wholesale Goods"
        }
    ],
    "sg:phone":"+44 1803 812393",
    "sg:postcode":"TQ12 5UR",
    "sg:province":"Devon",
    "sg:tags":[
        "others"
    ],
    "wof:name":"E J Adams",
    "wof:placetype":"venue"
},
  "geometry": {"coordinates":[-3.662351,50.491341],"type":"Point"}
}