{
  "type": "Feature",
  "properties": {
    "addr:full":"2-26 Anthony Rd Birmingham West Midlands B8 3AA",
    "addr:housenumber":"2-26",
    "addr:postcode":"b8 3aa",
    "addr:street":"Anthony Rd",
    "iso:country":"GB",
    "sg:address":"2-26 Anthony Rd",
    "sg:city":"Birmingham",
    "sg:classifiers":[
        {
            "category":"Shopping",
            "subcategory":"Pharmacy",
            "type":"Retail Goods"
        }
    ],
    "sg:phone":"+44 121 327 3600",
    "sg:postcode":"B8 3AA",
    "sg:province":"West Midlands",
    "sg:tags":[
        "pharmaceutical"
    ],
    "wof:name":"Pharmaco Jiba Ltd",
    "wof:placetype":"venue"
},
  "geometry": {"coordinates":[-1.849079,52.483879],"type":"Point"}
}