{
  "type": "Feature",
  "properties": {
    "addr:full":"16 High Street, Pittenweem Anstruther Fife KY10 2LA",
    "addr:housenumber":"16",
    "addr:postcode":"ky10 2la",
    "addr:street":"High Street",
    "iso:country":"GB",
    "sg:address":"16 High Street, Pittenweem",
    "sg:city":"Anstruther",
    "sg:classifiers":[
        {
            "category":"Food & Beverages",
            "subcategory":"Meat & Fish",
            "type":"Retail Goods"
        }
    ],
    "sg:postcode":"KY10 2LA",
    "sg:province":"Fife",
    "sg:tags":[
        "butcher"
    ],
    "wof:name":"George Donald Butchers",
    "wof:placetype":"venue"
},
  "geometry": {"coordinates":[-2.729318,56.213501],"type":"Point"}
}