{
  "type": "Feature",
  "properties": {
    "addr:full":"603 West Derby Road Liverpool Merseyside L13 8AE",
    "addr:housenumber":"603",
    "addr:postcode":"l13 8ae",
    "addr:street":"West Derby Road",
    "iso:country":"GB",
    "sg:address":"603 West Derby Road",
    "sg:city":"Liverpool",
    "sg:classifiers":[
        {
            "category":"Shopping",
            "subcategory":"Baby Store",
            "type":"Retail Goods"
        },
        {
            "category":"Shopping",
            "subcategory":"Clothing, Apparel, & Fashions",
            "type":"Retail Goods"
        }
    ],
    "sg:phone":"+44 151 220 6798",
    "sg:postcode":"L13 8AE",
    "sg:province":"Merseyside",
    "sg:tags":[
        "shop",
        "childrens",
        "babywear"
    ],
    "wof:name":"Ethel Austin",
    "wof:placetype":"venue"
},
  "geometry": {"coordinates":[-2.9311549664,53.4251556396],"type":"Point"}
}