{
  "type": "Feature",
  "properties": {
    "iso:country":"GB",
    "sg:address":"1052 Coventry Road, Hay Mills",
    "sg:city":"Birmingham",
    "sg:classifiers":[
        {
            "category":"Autos & Motor Vehicles",
            "subcategory":"Auto Supplies",
            "type":"Retail Goods"
        },
        {
            "category":"Personal",
            "subcategory":"Skin Care",
            "type":"Services"
        }
    ],
    "sg:phone":"+44 121 766 7665",
    "sg:postcode":"B25 8DP",
    "sg:province":"West Midlands",
    "sg:tags":[
        "part",
        "motorcycle",
        "manufacturer",
        "accessory"
    ],
    "wof:name":"J & S Accessories Ltd.",
    "wof:placetype":"venue"
},
  "geometry": {"coordinates":[-1.835703969,52.4636878967],"type":"Point"}
}