{
  "type": "Feature",
  "properties": {
    "addr:full":"96 Charminster Avenue Bournemouth Dorset BH9 1SE",
    "addr:housenumber":"96",
    "addr:postcode":"bh9 1se",
    "addr:street":"Charminster Avenue",
    "iso:country":"GB",
    "sg:address":"96 Charminster Avenue",
    "sg:city":"Bournemouth",
    "sg:classifiers":[
        {
            "category":"Food & Beverages",
            "subcategory":"Specialty",
            "type":"Retail Goods"
        },
        {
            "category":"Food & Beverages",
            "subcategory":"Bakery",
            "type":"Retail Goods"
        }
    ],
    "sg:phone":"+44 1202 525723",
    "sg:postcode":"BH9 1SE",
    "sg:province":"Dorset",
    "sg:tags":[
        "delivery",
        "baker",
        "snack",
        "sandwich"
    ],
    "wof:name":"The Granary Bakery",
    "wof:placetype":"venue"
},
  "geometry": {"coordinates":[-1.865687,50.74876],"type":"Point"}
}