{
  "type": "Feature",
  "properties": {
    "addr:full":"7 York Avenue East Cowes Isle of Wight PO32 6QY",
    "addr:housenumber":"7",
    "addr:postcode":"po32 6qy",
    "addr:street":"York Avenue",
    "iso:country":"GB",
    "sg:address":"7 York Avenue",
    "sg:city":"East Cowes",
    "sg:classifiers":[
        {
            "category":"Shopping",
            "subcategory":"Gifts & Souvenirs",
            "type":"Retail Goods"
        }
    ],
    "sg:postcode":"PO32 6QY",
    "sg:province":"Isle of Wight",
    "sg:tags":[
        "shop"
    ],
    "wof:name":"Millennium Creations",
    "wof:placetype":"venue"
},
  "geometry": {"coordinates":[-1.2890429497,50.7579917908],"type":"Point"}
}