{
  "type": "Feature",
  "properties": {
    "iso:country":"GB",
    "sg:address":"Red Wharf Bay",
    "sg:city":"Pentraeth",
    "sg:classifiers":[
        {
            "category":"Travel",
            "subcategory":"Hotels & Motels",
            "type":"Entertainment"
        }
    ],
    "sg:phone":"+44 1248 852366",
    "sg:postcode":"LL75 8RZ",
    "sg:province":"Isle of Anglesey",
    "wof:name":"Bryn Tirion Hotel",
    "wof:placetype":"venue"
},
  "geometry": {"coordinates":[-4.216624,53.282597],"type":"Point"}
}