{
  "type": "Feature",
  "properties": {
    "addr:full":"10 The Beach Deal Kent CT14 7HE",
    "addr:housenumber":"10",
    "addr:postcode":"ct14 7he",
    "addr:street":"The",
    "iso:country":"GB",
    "sg:address":"10 The Beach",
    "sg:city":"Deal",
    "sg:classifiers":[
        {
            "category":"Health Services",
            "subcategory":"Nursing And Care Facility",
            "type":"Services"
        }
    ],
    "sg:phone":"+44 1304 380043",
    "sg:postcode":"CT14 7HE",
    "sg:province":"Kent",
    "sg:tags":[
        "home"
    ],
    "wof:name":"Regency House",
    "wof:placetype":"venue"
},
  "geometry": {"coordinates":[1.402516,51.211266],"type":"Point"}
}