{
  "type": "Feature",
  "properties": {
    "addr:full":"43 Rosebery Avenue London Greater London EC1R 4SH",
    "addr:housenumber":"43",
    "addr:postcode":"ec1r 4sh",
    "addr:street":"Rosebery Avenue",
    "iso:country":"GB",
    "sg:address":"43 Rosebery Avenue",
    "sg:city":"London",
    "sg:classifiers":[
        {
            "category":"Professional",
            "subcategory":"Business Services",
            "type":"Services"
        }
    ],
    "sg:phone":"+44 20 7833 2002",
    "sg:postcode":"EC1R 4SH",
    "sg:province":"Greater London",
    "sg:tags":[
        "fashion",
        "agent"
    ],
    "wof:name":"Antoni & Alison",
    "wof:placetype":"venue"
},
  "geometry": {"coordinates":[-0.110924,51.524426],"type":"Point"}
}