{
  "type": "Feature",
  "properties": {
    "iso:country":"GB",
    "sg:address":"35 Elliot Close, South Woodham Ferrers",
    "sg:city":"Chelmsford",
    "sg:classifiers":[
        {
            "category":"Professional",
            "subcategory":"Management & Consulting",
            "type":"Services"
        }
    ],
    "sg:postcode":"CM3 5YN",
    "sg:province":"Essex",
    "sg:tags":[
        "consultant",
        "business"
    ],
    "wof:name":"Claridge Associates Ltd.",
    "wof:placetype":"venue"
},
  "geometry": {"coordinates":[0.623197,51.640354],"type":"Point"}
}