{
  "type": "Feature",
  "properties": {
    "iso:country":"GB",
    "sg:address":"Killigarth Manor Holiday Estate, Polperro",
    "sg:city":"Looe",
    "sg:classifiers":[
        {
            "category":"Recreation",
            "subcategory":"Campground",
            "type":"Entertainment"
        }
    ],
    "sg:phone":"+44 1503 272216",
    "sg:postcode":"PL13 2JQ",
    "sg:province":"Cornwall",
    "sg:tags":[
        "caravan",
        "park"
    ],
    "wof:name":"Keropega Ltd.",
    "wof:placetype":"venue"
},
  "geometry": {"coordinates":[-4.462355,50.356121],"type":"Point"}
}