{
  "type": "Feature",
  "properties": {
    "addr:full":"5 East Street London Greater London SE17 2DJ",
    "addr:housenumber":"5",
    "addr:postcode":"se17 2dj",
    "addr:street":"East Street",
    "iso:country":"GB",
    "sg:address":"5 East Street",
    "sg:city":"London",
    "sg:classifiers":[
        {
            "category":"Food & Beverages",
            "subcategory":"Meat & Fish",
            "type":"Retail Goods"
        }
    ],
    "sg:phone":"+44 20 7703 2471",
    "sg:postcode":"SE17 2DJ",
    "sg:province":"Greater London",
    "sg:tags":[
        "butcher"
    ],
    "wof:name":"A A Fisher",
    "wof:placetype":"venue"
},
  "geometry": {"coordinates":[-0.094644,51.488094],"type":"Point"}
}