{
  "type": "Feature",
  "properties": {
    "addr:full":"8 Trading Est, Kelvin Way West Bromwich West Midlands B70 7TN",
    "addr:housenumber":"8",
    "addr:postcode":"b70 7tn",
    "addr:street":"Trading Est Kelvin Way",
    "iso:country":"GB",
    "sg:address":"8 Trading Est, Kelvin Way",
    "sg:city":"West Bromwich",
    "sg:classifiers":[
        {
            "category":"Food & Beverages",
            "subcategory":"Candy",
            "type":"Retail Goods"
        }
    ],
    "sg:phone":"+44 121 525 6006",
    "sg:postcode":"B70 7TN",
    "sg:province":"West Midlands",
    "sg:tags":[
        "confectioner"
    ],
    "wof:name":"Sweets By Post",
    "wof:placetype":"venue"
},
  "geometry": {"coordinates":[-1.990224,52.518623],"type":"Point"}
}