{
  "type": "Feature",
  "properties": {
    "addr:full":"Fairholme, Collingham Street, Cheetham Manchester Greater Manchester M8 8RQ",
    "addr:postcode":"m8 8rq",
    "addr:street":"Fairholme Collingham Street",
    "iso:country":"GB",
    "sg:address":"Fairholme, Collingham Street, Cheetham",
    "sg:city":"Manchester",
    "sg:classifiers":[
        {
            "category":"Park",
            "subcategory":"Town Common",
            "type":"Public Place"
        }
    ],
    "sg:phone":"+44 161 835 2731",
    "sg:postcode":"M8 8RQ",
    "sg:province":"Greater Manchester",
    "sg:tags":[
        "funfair"
    ],
    "wof:name":"M Wallis",
    "wof:placetype":"venue"
},
  "geometry": {"coordinates":[-2.2345540524,53.4939918518],"type":"Point"}
}