{
  "type": "Feature",
  "properties": {
    "iso:country":"GB",
    "sg:address":"2 Spurway Pde, Woodford Ave",
    "sg:city":"Ilford",
    "sg:classifiers":[
        {
            "category":"Banks & Credit Unions",
            "subcategory":"Financial Services",
            "type":"Services"
        }
    ],
    "sg:postcode":"IG2 6UU",
    "sg:province":"Essex",
    "sg:tags":[
        "claim",
        "assessor"
    ],
    "wof:name":"Alexander Howard Assessors",
    "wof:placetype":"venue"
},
  "geometry": {"coordinates":[0.0585450009,51.5813369751],"type":"Point"}
}