{
  "type": "Feature",
  "properties": {
    "iso:country":"GB",
    "sg:address":"The Oak Tree Health Centre, Lostock Pl",
    "sg:city":"Didcot",
    "sg:classifiers":[
        {
            "category":"Health Services",
            "subcategory":"Doctor",
            "type":"Services"
        }
    ],
    "sg:phone":"+44 1235 810099",
    "sg:postcode":"OX11 7XT",
    "sg:province":"Oxfordshire",
    "sg:tags":[
        "practitioners"
    ],
    "wof:name":"Mackenzie, I",
    "wof:placetype":"venue"
},
  "geometry": {"coordinates":[-1.257941,51.613384],"type":"Point"}
}