{
  "type": "Feature",
  "properties": {
    "addr:full":"Unit 7 The Acorn Centre, Chestnut Avenue Biggleswade Bedfordshire SG18 0RA",
    "addr:housenumber":"unit 7",
    "addr:postcode":"sg18 0ra",
    "addr:street":"The;Chestnut Avenue",
    "iso:country":"GB",
    "sg:address":"Unit 7 The Acorn Centre, Chestnut Avenue",
    "sg:city":"Biggleswade",
    "sg:classifiers":[
        {
            "category":"Professional",
            "subcategory":"Employment Agencies",
            "type":"Services"
        }
    ],
    "sg:phone":"+44 1767 318100",
    "sg:postcode":"SG18 0RA",
    "sg:province":"Bedfordshire",
    "sg:tags":[
        "consultant"
    ],
    "wof:name":"Mary Innes Recruitment",
    "wof:placetype":"venue"
},
  "geometry": {"coordinates":[-0.261729002,52.0869750977],"type":"Point"}
}