{
  "type": "Feature",
  "properties": {
    "addr:full":"5a Underwood Street Islington Greater London N1 7LY",
    "addr:housenumber":"5a",
    "addr:postcode":"n1 7ly",
    "addr:street":"Underwood Street",
    "iso:country":"GB",
    "sg:address":"5a Underwood Street",
    "sg:city":"Islington",
    "sg:classifiers":[
        {
            "category":"Bars & Pubs",
            "type":"Food & Drink"
        }
    ],
    "sg:postcode":"N1 7LY",
    "sg:province":"Greater London",
    "sg:tags":[
        "pubs",
        "inn"
    ],
    "wof:name":"Chromelink Ltd",
    "wof:placetype":"venue"
},
  "geometry": {"coordinates":[-0.091179,51.529701],"type":"Point"}
}