{
  "type": "Feature",
  "properties": {
    "addr:full":"6 The Mews, College Road Grays Essex RM17 5PB",
    "addr:housenumber":"6",
    "addr:postcode":"rm17 5pb",
    "addr:street":"The Mews College Road",
    "iso:country":"GB",
    "sg:address":"6 The Mews, College Road",
    "sg:city":"Grays",
    "sg:classifiers":[
        {
            "category":"Travel",
            "subcategory":"Travel Agent",
            "type":"Entertainment"
        }
    ],
    "sg:phone":"+44 1375 372601",
    "sg:postcode":"RM17 5PB",
    "sg:province":"Essex",
    "wof:name":"Ecoventures Ltd.",
    "wof:placetype":"venue"
},
  "geometry": {"coordinates":[0.326975,51.479614],"type":"Point"}
}