{
  "type": "Feature",
  "properties": {
    "addr:full":"81 Russell Court, Ross Road Wallington Surrey SM6 8QT",
    "addr:housenumber":"81",
    "addr:postcode":"sm6 8qt",
    "addr:street":"Russell Court Ross Road",
    "iso:country":"GB",
    "sg:address":"81 Russell Court, Ross Road",
    "sg:city":"Wallington",
    "sg:classifiers":[
        {
            "category":"Professional",
            "type":"Services"
        }
    ],
    "sg:phone":"+44 20 8669 3074",
    "sg:postcode":"SM6 8QT",
    "sg:province":"Surrey",
    "sg:tags":[
        "entertainer"
    ],
    "wof:name":"Major Entertainments",
    "wof:placetype":"venue"
},
  "geometry": {"coordinates":[-0.1498979926,51.3601226807],"type":"Point"}
}