{
  "type": "Feature",
  "properties": {
    "addr:full":"High Street, Staplehurst Tonbridge Kent TN12 0AD",
    "addr:postcode":"tn12 0ad",
    "addr:street":"High Street",
    "iso:country":"GB",
    "sg:address":"High Street, Staplehurst",
    "sg:city":"Tonbridge",
    "sg:classifiers":[
        {
            "category":"Personal",
            "subcategory":"Beauty Salon",
            "type":"Services"
        }
    ],
    "sg:phone":"+44 1580 891462",
    "sg:postcode":"TN12 0AD",
    "sg:province":"Kent",
    "sg:tags":[
        "unisex",
        "hairdresser"
    ],
    "wof:name":"Michael's",
    "wof:placetype":"venue"
},
  "geometry": {"coordinates":[0.55258,51.164875],"type":"Point"}
}