{
  "type": "Feature",
  "properties": {
    "iso:country":"GB",
    "sg:address":"203 Gorgie Rd",
    "sg:city":"Edinburgh",
    "sg:classifiers":[
        {
            "category":"Communications",
            "type":"Services"
        }
    ],
    "sg:phone":"+44 131 313 1156",
    "sg:postcode":"EH11 1TT",
    "sg:province":"City of Edinburgh",
    "sg:tags":[
        "telecommunication"
    ],
    "wof:name":"Thomson Communications",
    "wof:placetype":"venue"
},
  "geometry": {"coordinates":[-3.216409,55.941124],"type":"Point"}
}