{
  "type": "Feature",
  "properties": {
    "iso:country":"GB",
    "sg:address":"31 Acton Rd",
    "sg:city":"Whitstable",
    "sg:classifiers":[
        {
            "category":"Building & Trades",
            "subcategory":"Construction",
            "type":"Services"
        }
    ],
    "sg:postcode":"CT5 1JJ",
    "sg:province":"Kent",
    "sg:tags":[
        "ceiling",
        "contractor"
    ],
    "wof:name":"Earl,B,Artexing",
    "wof:placetype":"venue"
},
  "geometry": {"coordinates":[1.028488,51.358921],"type":"Point"}
}