{
  "type": "Feature",
  "properties": {
    "iso:country":"GB",
    "sg:address":"38 Lansdown Road",
    "sg:city":"Bude",
    "sg:classifiers":[
        {
            "category":"Professional",
            "subcategory":"Accounting & Tax Preparation",
            "type":"Services"
        }
    ],
    "sg:phone":"+44 1288 353194",
    "sg:postcode":"EX23 8BN",
    "sg:province":"Cornwall",
    "sg:tags":[
        "accountant",
        "activity"
    ],
    "wof:name":"Potter Baker",
    "wof:placetype":"venue"
},
  "geometry": {"coordinates":[-4.543575,50.829975],"type":"Point"}
}