{
  "type": "Feature",
  "properties": {
    "addr:full":"53 Huntly Street Aberdeen Aberdeen City AB10 1TH",
    "addr:housenumber":"53",
    "addr:postcode":"ab10 1th",
    "addr:street":"Huntly Street",
    "iso:country":"GB",
    "sg:address":"53 Huntly Street",
    "sg:city":"Aberdeen",
    "sg:classifiers":[
        {
            "category":"Professional",
            "subcategory":"Engineering",
            "type":"Services"
        }
    ],
    "sg:phone":"+44 1224 645060",
    "sg:postcode":"AB10 1TH",
    "sg:province":"Aberdeen City",
    "sg:tags":[
        "engineer",
        "mechanical"
    ],
    "wof:name":"Crown House Engineering",
    "wof:placetype":"venue"
},
  "geometry": {"coordinates":[-2.107959,57.145592],"type":"Point"}
}