{
  "type": "Feature",
  "properties": {
    "addr:full":"8 Seymour Street Cambridge Cambridgeshire CB1 3DQ",
    "addr:housenumber":"8",
    "addr:postcode":"cb1 3dq",
    "addr:street":"Seymour Street",
    "iso:country":"GB",
    "sg:address":"8 Seymour Street",
    "sg:city":"Cambridge",
    "sg:classifiers":[
        {
            "category":"Utilities",
            "subcategory":"Mobile Phone",
            "type":"Services"
        },
        {
            "category":"Home & Garden",
            "subcategory":"Building Materials",
            "type":"Retail Goods"
        }
    ],
    "sg:phone":"+44 1223 246425",
    "sg:postcode":"CB1 3DQ",
    "sg:province":"Cambridgeshire",
    "sg:tags":[
        "equipment",
        "disability",
        "mobility"
    ],
    "wof:name":"Bee Mobile",
    "wof:placetype":"venue"
},
  "geometry": {"coordinates":[0.152215,52.198635],"type":"Point"}
}