{
  "type": "Feature",
  "properties": {
    "addr:full":"Unit 3, H W Baines Industrial Estate, Fisher Grn Ripon North Yorkshire HG4 1NN",
    "addr:housenumber":"unit 3 h",
    "addr:postcode":"hg4 1nn",
    "addr:street":"W Baines Industrial;Fisher Grn",
    "iso:country":"GB",
    "sg:address":"Unit 3, H W Baines Industrial Estate, Fisher Grn",
    "sg:city":"Ripon",
    "sg:classifiers":[
        {
            "category":"Professional",
            "subcategory":"Engineering",
            "type":"Services"
        },
        {
            "category":"Building & Trades",
            "subcategory":"Electrical",
            "type":"Services"
        }
    ],
    "sg:phone":"+44 1765 607297",
    "sg:postcode":"HG4 1NN",
    "sg:province":"North Yorkshire",
    "sg:tags":[
        "engineer",
        "electrician",
        "contractor"
    ],
    "wof:name":"W E Dixon",
    "wof:placetype":"venue"
},
  "geometry": {"coordinates":[-1.523579,54.136795],"type":"Point"}
}