{
  "type": "Feature",
  "properties": {
    "addr:full":"North Western Street Manchester Greater Manchester M12 6DX",
    "addr:postcode":"m12 6dx",
    "addr:street":"North Western Street",
    "iso:country":"GB",
    "sg:address":"North Western Street",
    "sg:city":"Manchester",
    "sg:classifiers":[
        {
            "category":"Manufacturing",
            "subcategory":"Wood Products",
            "type":"Manufacturing & Wholesale Goods"
        }
    ],
    "sg:phone":"+44 161 273 5257",
    "sg:postcode":"M12 6DX",
    "sg:province":"Greater Manchester",
    "sg:tags":[
        "packaging",
        "crate",
        "pallets"
    ],
    "wof:name":"Platting Pallets",
    "wof:placetype":"venue"
},
  "geometry": {"coordinates":[-2.22389,53.476048],"type":"Point"}
}