{
  "type": "Feature",
  "properties": {
    "iso:country":"GB",
    "sg:address":"Unit 5c Mays Yd, Down Rd, Horndean",
    "sg:city":"Waterlooville",
    "sg:classifiers":[
        {
            "category":"Professional",
            "subcategory":"Engineering",
            "type":"Services"
        }
    ],
    "sg:postcode":"PO8 0YP",
    "sg:province":"Hampshire",
    "sg:tags":[
        "electronic",
        "engineer"
    ],
    "wof:name":"Batten,Adrian,",
    "wof:placetype":"venue"
},
  "geometry": {"coordinates":[-0.99973,50.91991],"type":"Point"}
}