{
  "type": "Feature",
  "properties": {
    "addr:full":"34 Hirstead Rd Scarborough North Yorkshire YO12 6TW",
    "addr:housenumber":"34",
    "addr:postcode":"yo12 6tw",
    "addr:street":"Hirstead Rd",
    "iso:country":"GB",
    "sg:address":"34 Hirstead Rd",
    "sg:city":"Scarborough",
    "sg:classifiers":[
        {
            "category":"Retail",
            "subcategory":"Driving School",
            "type":"Services"
        }
    ],
    "sg:phone":"+44 1723 364292",
    "sg:postcode":"YO12 6TW",
    "sg:province":"North Yorkshire",
    "wof:name":"T S Patrick",
    "wof:placetype":"venue"
},
  "geometry": {"coordinates":[-0.4362500012,54.2944259644],"type":"Point"}
}