{
  "type": "Feature",
  "properties": {
    "addr:full":"Civic Offices, Guildhall Square Portsmouth Hampshire PO1 2AL",
    "addr:postcode":"hampshire po1 2al",
    "addr:street":"Guildhall Square",
    "iso:country":"GB",
    "sg:address":"Civic Offices, Guildhall Square",
    "sg:city":"Portsmouth",
    "sg:classifiers":[
        {
            "category":"Government",
            "subcategory":"Office",
            "type":"Public Place"
        }
    ],
    "sg:phone":"+44 23 9282 2251",
    "sg:postcode":"PO1 2AL",
    "sg:province":"Hampshire",
    "sg:tags":[
        "local"
    ],
    "wof:name":"Portsmouth City Council",
    "wof:placetype":"venue"
},
  "geometry": {"coordinates":[-1.087284,50.804008],"type":"Point"}
}