{
  "type": "Feature",
  "properties": {
    "iso:country":"GB",
    "sg:address":"54 Wern Street",
    "sg:city":"Tonypandy",
    "sg:classifiers":[
        {
            "category":"Shopping",
            "subcategory":"Department Store",
            "type":"Retail Goods"
        }
    ],
    "sg:postcode":"CF40 2BN",
    "sg:province":"Rhondda, Cynon, Taff",
    "wof:name":"Cambrian General Stores & Off Licence",
    "wof:placetype":"venue"
},
  "geometry": {"coordinates":[-3.480361,51.626709],"type":"Point"}
}