{
  "type": "Feature",
  "properties": {
    "iso:country":"GB",
    "sg:address":"43 Burleigh Rd",
    "sg:city":"Hinckley",
    "sg:classifiers":[
        {
            "category":"Travel",
            "subcategory":"Travel Agent",
            "type":"Entertainment"
        }
    ],
    "sg:phone":"+44 1455 449019",
    "sg:postcode":"LE10 0DG",
    "sg:province":"Leicestershire",
    "wof:name":"Dodds Destinations",
    "wof:placetype":"venue"
},
  "geometry": {"coordinates":[-1.380809,52.549797],"type":"Point"}
}