{
  "type": "Feature",
  "properties": {
    "iso:country":"GB",
    "sg:address":"305 High Road",
    "sg:city":"Ilford",
    "sg:classifiers":[
        {
            "category":"Shopping",
            "subcategory":"News",
            "type":"Retail Goods"
        }
    ],
    "sg:phone":"+44 20 8478 2104",
    "sg:postcode":"IG1 1NR",
    "sg:province":"Essex",
    "sg:tags":[
        "newsagent"
    ],
    "wof:name":"Richards News",
    "wof:placetype":"venue"
},
  "geometry": {"coordinates":[0.088858,51.562359],"type":"Point"}
}