{
  "type": "Feature",
  "properties": {
    "addr:full":"Trafalgar Rd Horsham West Sussex RH12 2QD",
    "addr:postcode":"rh12 2qd",
    "addr:street":"Trafalgar Rd",
    "iso:country":"GB",
    "sg:address":"Trafalgar Rd",
    "sg:city":"Horsham",
    "sg:classifiers":[
        {
            "category":"Place Of Worship",
            "type":"Public Place"
        }
    ],
    "sg:phone":"+44 1403 240729",
    "sg:postcode":"RH12 2QD",
    "sg:province":"West Sussex",
    "wof:name":"Trafalgar Road Baptist Church",
    "wof:placetype":"venue"
},
  "geometry": {"coordinates":[-0.329639,51.073963],"type":"Point"}
}