{
  "type": "Feature",
  "properties": {
    "addr:full":"84 Barkby Road Leicester Leicestershire LE4 9LF",
    "addr:housenumber":"84",
    "addr:postcode":"le4 9lf",
    "addr:street":"Barkby Road",
    "iso:country":"GB",
    "sg:address":"84 Barkby Road",
    "sg:city":"Leicester",
    "sg:classifiers":[
        {
            "category":"Retail",
            "subcategory":"Auto Repair",
            "type":"Services"
        }
    ],
    "sg:phone":"+44 116 276 1102",
    "sg:postcode":"LE4 9LF",
    "sg:province":"Leicestershire",
    "sg:tags":[
        "body",
        "car"
    ],
    "wof:name":"Dean Hollowood",
    "wof:placetype":"venue"
},
  "geometry": {"coordinates":[-1.0973030329,52.6578979492],"type":"Point"}
}