{
  "type": "Feature",
  "properties": {
    "addr:full":"Northwick Circle, Kenton Harrow Greater London HA3 0EL",
    "addr:postcode":"ha3 0el",
    "addr:street":"Northwick Circle",
    "iso:country":"GB",
    "sg:address":"Northwick Circle, Kenton",
    "sg:city":"Harrow",
    "sg:classifiers":[
        {
            "category":"Organizations",
            "subcategory":"Membership Organization",
            "type":"Services"
        }
    ],
    "sg:postcode":"HA3 0EL",
    "sg:province":"Greater London",
    "sg:tags":[
        "club"
    ],
    "wof:name":"Harrow District Masonic Council",
    "wof:placetype":"venue"
},
  "geometry": {"coordinates":[-0.309394,51.582275],"type":"Point"}
}