{
  "type": "Feature",
  "properties": {
    "addr:full":"36 Lovelace Road Surbiton Surrey KT6 6ND",
    "addr:housenumber":"36",
    "addr:postcode":"kt6 6nd",
    "addr:street":"Lovelace Road",
    "iso:country":"GB",
    "sg:address":"36 Lovelace Road",
    "sg:city":"Surbiton",
    "sg:classifiers":[
        {
            "category":"Professional",
            "subcategory":"Employment Agencies",
            "type":"Services"
        }
    ],
    "sg:postcode":"KT6 6ND",
    "sg:province":"Surrey",
    "sg:tags":[
        "consultant"
    ],
    "wof:name":"Alan Perriam Associates",
    "wof:placetype":"venue"
},
  "geometry": {"coordinates":[-0.3106290102,51.3870124817],"type":"Point"}
}