{
  "type": "Feature",
  "properties": {
    "iso:country":"GB",
    "sg:address":"Rear Of 25 East St",
    "sg:city":"Leigh-on-sea",
    "sg:classifiers":[
        {
            "category":"Communications",
            "subcategory":"Film & Video Production",
            "type":"Services"
        }
    ],
    "sg:phone":"+44 1702 470490",
    "sg:postcode":"SS9 1QF",
    "sg:province":"Essex",
    "sg:tags":[
        "illustrator",
        "artist"
    ],
    "wof:name":"Appleton,Sheila,",
    "wof:placetype":"venue"
},
  "geometry": {"coordinates":[0.6509950161,51.5484809875],"type":"Point"}
}