{
  "type": "Feature",
  "properties": {
    "addr:full":"Balfour House, Churchfield Road Walton-on-thames Surrey KT12 2TD",
    "addr:postcode":"kt12 2td",
    "addr:street":"Churchfield Road",
    "iso:country":"GB",
    "sg:address":"Balfour House, Churchfield Road",
    "sg:city":"Walton-on-thames",
    "sg:classifiers":[
        {
            "category":"Social Services",
            "subcategory":"Job Training",
            "type":"Services"
        }
    ],
    "sg:phone":"+44 1932 256000",
    "sg:postcode":"KT12 2TD",
    "sg:province":"Surrey",
    "sg:tags":[
        "engineering",
        "marine"
    ],
    "wof:name":"Fmc Technologies Ltd.",
    "wof:placetype":"venue"
},
  "geometry": {"coordinates":[-0.4149639904,51.3875617981],"type":"Point"}
}