{
  "type": "Feature",
  "properties": {
    "addr:full":"Office 4 88 Bushey Road London Greater London SW20 0JH",
    "addr:housenumber":"88",
    "addr:postcode":"sw20 0jh",
    "addr:street":"4;Bushey Road",
    "iso:country":"GB",
    "sg:address":"Office 4 88 Bushey Road",
    "sg:city":"London",
    "sg:classifiers":[
        {
            "category":"Wholesale",
            "subcategory":"Scrap",
            "type":"Manufacturing & Wholesale Goods"
        }
    ],
    "sg:postcode":"SW20 0JH",
    "sg:province":"Greater London",
    "sg:tags":[
        "waste",
        "metal"
    ],
    "wof:name":"New Leaf Recycling Ltd.",
    "wof:placetype":"venue"
},
  "geometry": {"coordinates":[-0.2399239987,51.4042282104],"type":"Point"}
}