{
  "type": "Feature",
  "properties": {
    "addr:full":"Unit 8, Acorn Way, Hawthorne Road Bootle Merseyside L20 6QA",
    "addr:housenumber":"unit 8",
    "addr:postcode":"l20 6qa",
    "addr:street":"Acorn Way Hawthorne Road",
    "iso:country":"GB",
    "sg:address":"Unit 8, Acorn Way, Hawthorne Road",
    "sg:city":"Bootle",
    "sg:classifiers":[
        {
            "category":"Building & Trades",
            "subcategory":"Construction",
            "type":"Services"
        }
    ],
    "sg:phone":"+44 151 922 7788",
    "sg:postcode":"L20 6QA",
    "sg:province":"Merseyside",
    "sg:tags":[
        "excavation",
        "groundwork",
        "contractor"
    ],
    "wof:name":"F J C Supplies",
    "wof:placetype":"venue"
},
  "geometry": {"coordinates":[-2.9855840206,53.4584388733],"type":"Point"}
}