{
  "type": "Feature",
  "properties": {
    "addr:full":"Unit 6 & 7 Alpine Business Centre, Eastbury Rd East Ham Greater London E6 4LP",
    "addr:housenumber":"unit 6 & 7",
    "addr:postcode":"e6 4lp",
    "addr:street":"Alpine Business Centre Eastbury Rd",
    "iso:country":"GB",
    "sg:address":"Unit 6 & 7 Alpine Business Centre, Eastbury Rd",
    "sg:city":"East Ham",
    "sg:classifiers":[
        {
            "category":"Professional",
            "subcategory":"Printing & Photocopies",
            "type":"Services"
        }
    ],
    "sg:phone":"+44 20 7474 6402",
    "sg:postcode":"E6 4LP",
    "sg:province":"Greater London",
    "sg:tags":[
        "printer"
    ],
    "wof:name":"Arboreal Print Group",
    "wof:placetype":"venue"
},
  "geometry": {"coordinates":[0.065275,51.518883],"type":"Point"}
}