{
  "type": "Feature",
  "properties": {
    "iso:country":"GB",
    "sg:address":"38 King Street",
    "sg:city":"London",
    "sg:classifiers":[
        {
            "category":"Restaurant",
            "type":"Food & Drink"
        }
    ],
    "sg:phone":"+44 20 7836 1976",
    "sg:postcode":"WC2E 8JS",
    "sg:province":"Greater London",
    "wof:name":"Calabash Restaurant",
    "wof:placetype":"venue"
},
  "geometry": {"coordinates":[-0.124385,51.511852],"type":"Point"}
}