{
  "type": "Feature",
  "properties": {
    "addr:full":"Quadrant Shopping Centre, Main Street Coatbridge North Lanarkshire ML5 3EG",
    "addr:postcode":"ml5 3eg",
    "addr:street":"Main Street",
    "iso:country":"GB",
    "sg:address":"Quadrant Shopping Centre, Main Street",
    "sg:city":"Coatbridge",
    "sg:classifiers":[
        {
            "category":"Deli",
            "type":"Food & Drink"
        }
    ],
    "sg:phone":"+44 1236 432365",
    "sg:postcode":"ML5 3EG",
    "sg:province":"North Lanarkshire",
    "sg:tags":[
        "delicatessen"
    ],
    "wof:name":"R Mathieson & Sons Ltd.",
    "wof:placetype":"venue"
},
  "geometry": {"coordinates":[-4.0358390808,55.8587532043],"type":"Point"}
}