{
  "type": "Feature",
  "properties": {
    "addr:full":"Eurolink Business Centre, 49 Effra Rd Brixton Greater London SW2 1BZ",
    "addr:housenumber":"49",
    "addr:postcode":"sw2 1bz",
    "addr:street":"Effra Rd",
    "iso:country":"GB",
    "sg:address":"Eurolink Business Centre, 49 Effra Rd",
    "sg:city":"Brixton",
    "sg:classifiers":[
        {
            "category":"Communications",
            "type":"Services"
        }
    ],
    "sg:phone":"+44 20 7733 1177",
    "sg:postcode":"SW2 1BZ",
    "sg:province":"Greater London",
    "sg:tags":[
        "data",
        "network"
    ],
    "wof:name":"Gateway Education",
    "wof:placetype":"venue"
},
  "geometry": {"coordinates":[-0.11446,51.457581],"type":"Point"}
}