{
  "type": "Feature",
  "properties": {
    "addr:full":"812 Springfield Road Glasgow Glasgow City G31 4HL",
    "addr:housenumber":"812",
    "addr:postcode":"g31 4hl",
    "addr:street":"Springfield Road",
    "iso:country":"GB",
    "sg:address":"812 Springfield Road",
    "sg:city":"Glasgow",
    "sg:classifiers":[
        {
            "category":"Food & Beverages",
            "subcategory":"Meat & Fish",
            "type":"Retail Goods"
        }
    ],
    "sg:phone":"+44 141 554 6621",
    "sg:postcode":"G31 4HL",
    "sg:province":"Glasgow City",
    "sg:tags":[
        "butcher"
    ],
    "wof:name":"Frank Cross Butchers",
    "wof:placetype":"venue"
},
  "geometry": {"coordinates":[-4.199764,55.849644],"type":"Point"}
}