{
  "type": "Feature",
  "properties": {
    "addr:full":"100 George St Oban Argyll and Bute PA34 5NR",
    "addr:housenumber":"100",
    "addr:postcode":"pa34 5nr",
    "addr:street":"George St",
    "iso:country":"GB",
    "sg:address":"100 George St",
    "sg:city":"Oban",
    "sg:classifiers":[
        {
            "category":"Sports & Exercise",
            "subcategory":"Sports Center",
            "type":"Entertainment"
        }
    ],
    "sg:phone":"+44 1631 565491",
    "sg:postcode":"PA34 5NR",
    "sg:province":"Argyll and Bute",
    "sg:tags":[
        "shop",
        "good"
    ],
    "wof:name":"Leisure Sport",
    "wof:placetype":"venue"
},
  "geometry": {"coordinates":[-5.4726891518,56.415813446],"type":"Point"}
}