{
  "type": "Feature",
  "properties": {
    "addr:full":"30a The Green Twickenham Greater London TW2 5AB",
    "addr:housenumber":"30a",
    "addr:postcode":"tw2 5ab",
    "addr:street":"The Green",
    "iso:country":"GB",
    "sg:address":"30a The Green",
    "sg:city":"Twickenham",
    "sg:classifiers":[
        {
            "category":"Professional",
            "subcategory":"Management & Consulting",
            "type":"Services"
        }
    ],
    "sg:postcode":"TW2 5AB",
    "sg:province":"Greater London",
    "sg:tags":[
        "consultant",
        "business"
    ],
    "wof:name":"Studdert Consultancy Ltd.",
    "wof:placetype":"venue"
},
  "geometry": {"coordinates":[-0.340839,51.444756],"type":"Point"}
}