{
  "type": "Feature",
  "properties": {
    "addr:full":"2 Broadway Road, Aston Somerville Broadway Gloucestershire WR12 7JF",
    "addr:housenumber":"2",
    "addr:postcode":"wr12 7jf",
    "addr:street":"Broadway Road;Broadway",
    "iso:country":"GB",
    "sg:address":"2 Broadway Road, Aston Somerville",
    "sg:city":"Broadway",
    "sg:classifiers":[
        {
            "category":"Communications",
            "type":"Services"
        }
    ],
    "sg:postcode":"WR12 7JF",
    "sg:province":"Gloucestershire",
    "sg:tags":[
        "telecommunication"
    ],
    "wof:name":"Tempus Communications Ltd",
    "wof:placetype":"venue"
},
  "geometry": {"coordinates":[-1.932329,52.041031],"type":"Point"}
}