{
  "type": "Feature",
  "properties": {
    "iso:country":"GB",
    "sg:address":"77a Roundwell Street, Tunstall",
    "sg:city":"Stoke-on-trent",
    "sg:classifiers":[
        {
            "category":"Shopping",
            "subcategory":"Antiques",
            "type":"Retail Goods"
        }
    ],
    "sg:postcode":"ST6 5AW",
    "sg:province":"Staffordshire",
    "wof:name":"Ravensdale Studios",
    "wof:placetype":"venue"
},
  "geometry": {"coordinates":[-2.212892,53.059448],"type":"Point"}
}