{
  "type": "Feature",
  "properties": {
    "iso:country":"GB",
    "sg:address":"20 Lowther St",
    "sg:city":"Whitehaven",
    "sg:classifiers":[
        {
            "category":"Real Estate",
            "subcategory":"Real Estate Agent",
            "type":"Services"
        }
    ],
    "sg:phone":"+44 1946 693931",
    "sg:postcode":"CA28 7AL",
    "sg:province":"Cumbria",
    "wof:name":"Mitchells Lakeland Properties",
    "wof:placetype":"venue"
},
  "geometry": {"coordinates":[-3.587534,54.5476],"type":"Point"}
}