{
  "type": "Feature",
  "properties": {
    "iso:country":"GB",
    "sg:address":"Micrographic House, Reeves Street",
    "sg:city":"Leigh",
    "sg:classifiers":[
        {
            "category":"Communications",
            "subcategory":"Film & Video Production",
            "type":"Services"
        }
    ],
    "sg:phone":"+44 1942 608921",
    "sg:postcode":"WN7 1NZ",
    "sg:province":"Lancashire",
    "sg:tags":[
        "microfilming"
    ],
    "wof:name":"Micrographic Equipment Services Ltd.",
    "wof:placetype":"venue"
},
  "geometry": {"coordinates":[-2.515727,53.502048],"type":"Point"}
}