{
  "type": "Feature",
  "properties": {
    "iso:country":"GB",
    "sg:address":"25 Glengagals",
    "sg:city":"Chester",
    "sg:classifiers":[
        {
            "category":"Building & Trades",
            "subcategory":"Construction",
            "type":"Services"
        }
    ],
    "sg:phone":"+44 1244 341396",
    "sg:postcode":"CH3 5HW",
    "sg:province":"Cheshire",
    "sg:tags":[
        "builder"
    ],
    "wof:name":"Peter R Dunning",
    "wof:placetype":"venue"
},
  "geometry": {"coordinates":[-2.860019,53.192909],"type":"Point"}
}