{
  "type": "Feature",
  "properties": {
    "iso:country":"GB",
    "sg:address":"Unit 12, Wick 2 Industrial Estate",
    "sg:city":"New Milton",
    "sg:classifiers":[
        {
            "category":"Professional",
            "subcategory":"Business Services",
            "type":"Services"
        }
    ],
    "sg:phone":"+44 1425 621173",
    "sg:postcode":"BH25 6TJ",
    "sg:province":"Hampshire",
    "sg:tags":[
        "tile",
        "stockist"
    ],
    "wof:name":"Atlas Ceramics (Southern) Ltd.",
    "wof:placetype":"venue"
},
  "geometry": {"coordinates":[-1.670149,50.752289],"type":"Point"}
}