{
  "type": "Feature",
  "properties": {
    "addr:full":"294 Broxtowe Lane Nottingham Nottinghamshire NG8 5NB",
    "addr:housenumber":"294",
    "addr:postcode":"ng8 5nb",
    "addr:street":"Broxtowe Lane",
    "iso:country":"GB",
    "sg:address":"294 Broxtowe Lane",
    "sg:city":"Nottingham",
    "sg:classifiers":[
        {
            "category":"Communications",
            "type":"Services"
        }
    ],
    "sg:phone":"+44 115 929 1665",
    "sg:postcode":"NG8 5NB",
    "sg:province":"Nottinghamshire",
    "sg:tags":[
        "tv",
        "video",
        "radio"
    ],
    "wof:name":"Telescene Audio Visual Ltd.",
    "wof:placetype":"venue"
},
  "geometry": {"coordinates":[-1.2113850117,52.976146698],"type":"Point"}
}