{
  "type": "Feature",
  "properties": {
    "addr:full":"East Moulin Road Pitlochry Perth and Kinross PH16 5ET",
    "addr:postcode":"ph16 5et",
    "addr:street":"East Moulin Road",
    "iso:country":"GB",
    "sg:address":"East Moulin Road",
    "sg:city":"Pitlochry",
    "sg:classifiers":[
        {
            "category":"Education",
            "subcategory":"School",
            "type":"Public Place"
        }
    ],
    "sg:postcode":"PH16 5ET",
    "sg:province":"Perth and Kinross",
    "sg:tags":[
        "local",
        "authority"
    ],
    "wof:name":"Pitlochry High School",
    "wof:placetype":"venue"
},
  "geometry": {"coordinates":[-3.726088047,56.7114181519],"type":"Point"}
}