{
  "type": "Feature",
  "properties": {
    "iso:country":"GB",
    "sg:address":"Oak Street",
    "sg:city":"Oswestry",
    "sg:classifiers":[
        {
            "category":"Retail",
            "subcategory":"Auto Repair",
            "type":"Services"
        }
    ],
    "sg:phone":"+44 1691 657551",
    "sg:postcode":"SY11 1LJ",
    "sg:province":"Shropshire",
    "sg:tags":[
        "body",
        "car"
    ],
    "wof:name":"Roy Evans",
    "wof:placetype":"venue"
},
  "geometry": {"coordinates":[-3.057890892,52.8618431091],"type":"Point"}
}