{
  "type": "Feature",
  "properties": {
    "iso:country":"GB",
    "sg:address":"103 Sylvan Avenue",
    "sg:city":"Wood Green",
    "sg:classifiers":[
        {
            "category":"Organizations",
            "subcategory":"Community Association",
            "type":"Services"
        }
    ],
    "sg:phone":"+44 20 8888 1305",
    "sg:postcode":"N22 5JB",
    "sg:province":"Greater London",
    "sg:tags":[
        "relation",
        "public"
    ],
    "wof:name":"Anita Devi Consultants",
    "wof:placetype":"venue"
},
  "geometry": {"coordinates":[-0.1050499976,51.6061706543],"type":"Point"}
}