{
  "type": "Feature",
  "properties": {
    "addr:full":"39-41 Commercial Road Bournemouth Dorset BH2 5RH",
    "addr:housenumber":"39-41",
    "addr:postcode":"bh2 5rh",
    "addr:street":"Commercial Road",
    "iso:country":"GB",
    "sg:address":"39-41 Commercial Road",
    "sg:city":"Bournemouth",
    "sg:classifiers":[
        {
            "category":"Shopping",
            "subcategory":"Clothing, Apparel, & Fashions",
            "type":"Retail Goods"
        }
    ],
    "sg:phone":"+44 1202 319090",
    "sg:postcode":"BH2 5RH",
    "sg:province":"Dorset",
    "sg:tags":[
        "shop"
    ],
    "wof:name":"Cromwells Madhouse Plc",
    "wof:placetype":"venue"
},
  "geometry": {"coordinates":[-1.882805,50.720531],"type":"Point"}
}