{
  "type": "Feature",
  "properties": {
    "iso:country":"GB",
    "sg:address":"133 Yarmouth Road",
    "sg:city":"Norwich",
    "sg:classifiers":[
        {
            "category":"Health Services",
            "subcategory":"Nursing And Care Facility",
            "type":"Services"
        }
    ],
    "sg:phone":"+44 1603 437358",
    "sg:postcode":"NR7 0RF",
    "sg:province":"Norfolk",
    "sg:tags":[
        "home"
    ],
    "wof:name":"Bondcare (Larchwood) Ltd.",
    "wof:placetype":"venue"
},
  "geometry": {"coordinates":[1.351476,52.627407],"type":"Point"}
}