{
  "type": "Feature",
  "properties": {
    "iso:country":"GB",
    "sg:address":"Hindley Wk",
    "sg:city":"Bradford",
    "sg:classifiers":[
        {
            "category":"Building & Trades",
            "subcategory":"Construction",
            "type":"Services"
        },
        {
            "category":"Manufacturing",
            "subcategory":"Paper Products",
            "type":"Manufacturing & Wholesale Goods"
        }
    ],
    "sg:phone":"+44 1274 571703",
    "sg:postcode":"BD7 4NA",
    "sg:province":"West Yorkshire",
    "sg:tags":[
        "cardboard",
        "decorator",
        "painter"
    ],
    "wof:name":"Bean,Malcolm,",
    "wof:placetype":"venue"
},
  "geometry": {"coordinates":[-1.805739,53.773727],"type":"Point"}
}