{
  "type": "Feature",
  "properties": {
    "addr:full":"Lower Road, East Farleigh Maidstone Kent ME15 0HD",
    "addr:postcode":"me15 0hd",
    "addr:street":"Lower Road East",
    "iso:country":"GB",
    "sg:address":"Lower Road, East Farleigh",
    "sg:city":"Maidstone",
    "sg:classifiers":[
        {
            "category":"Bars & Pubs",
            "type":"Food & Drink"
        },
        {
            "category":"Community Center",
            "subcategory":"Social",
            "type":"Public Place"
        }
    ],
    "sg:phone":"+44 1622 726282",
    "sg:postcode":"ME15 0HD",
    "sg:province":"Kent",
    "sg:tags":[
        "pubs",
        "house",
        "inn",
        "activity"
    ],
    "wof:name":"Bull Inn",
    "wof:placetype":"venue"
},
  "geometry": {"coordinates":[0.4653950036,51.2545509338],"type":"Point"}
}