{
  "type": "Feature",
  "properties": {
    "addr:full":"289 Green Lanes London Greater London N13 4XS",
    "addr:housenumber":"289",
    "addr:postcode":"n13 4xs",
    "addr:street":"Green Lanes",
    "iso:country":"GB",
    "sg:address":"289 Green Lanes",
    "sg:city":"London",
    "sg:classifiers":[
        {
            "category":"Insurance",
            "subcategory":"Insurance Agent",
            "type":"Services"
        }
    ],
    "sg:phone":"+44 20 8447 9038",
    "sg:postcode":"N13 4XS",
    "sg:province":"Greater London",
    "wof:name":"Coversure Insurance Services",
    "wof:placetype":"venue"
},
  "geometry": {"coordinates":[-0.109411,51.617153],"type":"Point"}
}