{
  "type": "Feature",
  "properties": {
    "addr:full":"Doctors Surgery, 181 Burton Road Lincoln Lincolnshire LN1 3LT",
    "addr:housenumber":"181",
    "addr:postcode":"ln1 3lt",
    "addr:street":"Burton Road",
    "iso:country":"GB",
    "sg:address":"Doctors Surgery, 181 Burton Road",
    "sg:city":"Lincoln",
    "sg:classifiers":[
        {
            "category":"Health Services",
            "subcategory":"Doctor",
            "type":"Services"
        }
    ],
    "sg:phone":"+44 1522 544222",
    "sg:postcode":"LN1 3LT",
    "sg:province":"Lincolnshire",
    "sg:tags":[
        "practitioners"
    ],
    "wof:name":"S N Khatib",
    "wof:placetype":"venue"
},
  "geometry": {"coordinates":[-0.5464,53.241268],"type":"Point"}
}