{
  "type": "Feature",
  "properties": {
    "addr:full":"Meadowfields Bridport Dorset DT6 3FB",
    "addr:postcode":"dt6 3fb",
    "iso:country":"GB",
    "sg:address":"Meadowfields",
    "sg:city":"Bridport",
    "sg:classifiers":[
        {
            "category":"Building & Trades",
            "subcategory":"Construction",
            "type":"Services"
        }
    ],
    "sg:phone":"+44 1380 427147",
    "sg:postcode":"DT6 3FB",
    "sg:province":"Dorset",
    "sg:tags":[
        "builder"
    ],
    "wof:name":"Prowting Homes",
    "wof:placetype":"venue"
},
  "geometry": {"coordinates":[-2.7580189705,50.7335662842],"type":"Point"}
}