{
  "type": "Feature",
  "properties": {
    "addr:full":"8 Sandmartin Clo Dudley West Midlands DY2 9TA",
    "addr:housenumber":"8",
    "addr:postcode":"dy2 9ta",
    "addr:street":"Sandmartin Clo",
    "iso:country":"GB",
    "sg:address":"8 Sandmartin Clo",
    "sg:city":"Dudley",
    "sg:classifiers":[
        {
            "category":"Building & Trades",
            "subcategory":"Construction",
            "type":"Services"
        }
    ],
    "sg:phone":"+44 1384 633266",
    "sg:postcode":"DY2 9TA",
    "sg:province":"West Midlands",
    "sg:tags":[
        "roofing"
    ],
    "wof:name":"Harper Roofing",
    "wof:placetype":"venue"
},
  "geometry": {"coordinates":[-2.0820429325,52.4785652161],"type":"Point"}
}