{
  "type": "Feature",
  "properties": {
    "addr:full":"43 Poplar Av Castleford West Yorkshire WF10 3QJ",
    "addr:housenumber":"43",
    "addr:postcode":"wf10 3qj",
    "addr:street":"Poplar Av Castleford West",
    "iso:country":"GB",
    "sg:address":"43 Poplar Av",
    "sg:city":"Castleford",
    "sg:classifiers":[
        {
            "category":"Personal",
            "subcategory":"Beauty Salon",
            "type":"Services"
        }
    ],
    "sg:phone":"+44 1977 558296",
    "sg:postcode":"WF10 3QJ",
    "sg:province":"West Yorkshire",
    "sg:tags":[
        "unisex",
        "hairdresser"
    ],
    "wof:name":"Hairem",
    "wof:placetype":"venue"
},
  "geometry": {"coordinates":[-1.314249,53.721481],"type":"Point"}
}