{
  "type": "Feature",
  "properties": {
    "addr:full":"Turner House, 14 King Square Bridgwater Somerset TA6 3DG",
    "addr:housenumber":"14",
    "addr:postcode":"ta6 3dg",
    "addr:street":"King Square",
    "iso:country":"GB",
    "sg:address":"Turner House, 14 King Square",
    "sg:city":"Bridgwater",
    "sg:classifiers":[
        {
            "category":"Insurance",
            "subcategory":"Insurance Agent",
            "type":"Services"
        }
    ],
    "sg:phone":"+44 1278 424345",
    "sg:postcode":"TA6 3DG",
    "sg:province":"Somerset",
    "sg:tags":[
        "broker"
    ],
    "wof:name":"Eke John & Partners Ltd.",
    "wof:placetype":"venue"
},
  "geometry": {"coordinates":[-3.0039560795,51.1296882629],"type":"Point"}
}