{
  "type": "Feature",
  "properties": {
    "addr:full":"127 Armada Way Plymouth Devon PL1 1HH",
    "addr:housenumber":"127",
    "addr:postcode":"pl1 1hh",
    "addr:street":"Armada Way",
    "iso:country":"GB",
    "sg:address":"127 Armada Way",
    "sg:city":"Plymouth",
    "sg:classifiers":[
        {
            "category":"Shopping",
            "subcategory":"Clothing, Apparel, & Fashions",
            "type":"Retail Goods"
        }
    ],
    "sg:phone":"+44 1752 260785",
    "sg:postcode":"PL1 1HH",
    "sg:province":"Devon",
    "sg:tags":[
        "menswear"
    ],
    "wof:name":"Top Man",
    "wof:placetype":"venue"
},
  "geometry": {"coordinates":[-4.1429481506,50.371509552],"type":"Point"}
}