{
  "type": "Feature",
  "properties": {
    "addr:full":"Unit 2 Dross Hill Works Bradford West Yorkshire BD12 0QP",
    "addr:housenumber":"unit 2",
    "addr:postcode":"bd12 0qp",
    "addr:street":"Dross Hill;Bradford West",
    "iso:country":"GB",
    "sg:address":"Unit 2 Dross Hill Works",
    "sg:city":"Bradford",
    "sg:classifiers":[
        {
            "category":"Professional",
            "subcategory":"Engineering",
            "type":"Services"
        }
    ],
    "sg:phone":"+44 1274 679115",
    "sg:postcode":"BD12 0QP",
    "sg:province":"West Yorkshire",
    "wof:name":"Low Moor Swift Co",
    "wof:placetype":"venue"
},
  "geometry": {"coordinates":[-1.7583060265,53.7957382202],"type":"Point"}
}