{
  "type": "Feature",
  "properties": {
    "iso:country":"GB",
    "sg:address":"125 Alexandra Road, Winshill",
    "sg:city":"Burton-on-trent",
    "sg:classifiers":[
        {
            "category":"Place Of Worship",
            "type":"Public Place"
        }
    ],
    "sg:postcode":"DE15 0JD",
    "sg:province":"Derbyshire",
    "wof:name":"Holy Rosary Roman Catholic Church",
    "wof:placetype":"venue"
},
  "geometry": {"coordinates":[-1.609584,52.805145],"type":"Point"}
}