{
  "type": "Feature",
  "properties": {
    "iso:country":"GB",
    "sg:address":"Johnsey Trading Est, Gaskell St",
    "sg:city":"Newport",
    "sg:classifiers":[
        {
            "category":"Retail",
            "subcategory":"Auto Repair",
            "type":"Services"
        }
    ],
    "sg:postcode":"NP19 0GL",
    "sg:province":"Newport",
    "sg:tags":[
        "modification",
        "garage"
    ],
    "wof:name":"Dodson,William H,",
    "wof:placetype":"venue"
},
  "geometry": {"coordinates":[-2.988257,51.591049],"type":"Point"}
}