{
  "type": "Feature",
  "properties": {
    "addr:full":"54 West Wycombe Road High Wycombe Buckinghamshire HP11 2LP",
    "addr:housenumber":"54",
    "addr:postcode":"hp11 2lp",
    "addr:street":"West Wycombe Road",
    "iso:country":"GB",
    "sg:address":"54 West Wycombe Road",
    "sg:city":"High Wycombe",
    "sg:classifiers":[
        {
            "category":"Retail",
            "subcategory":"Veterinary Services",
            "type":"Services"
        }
    ],
    "sg:phone":"+44 1494 459095",
    "sg:postcode":"HP11 2LP",
    "sg:province":"Buckinghamshire",
    "sg:tags":[
        "surgeon",
        "activity"
    ],
    "wof:name":"Crossroads Veterinary Centre",
    "wof:placetype":"venue"
},
  "geometry": {"coordinates":[-0.761675,51.634212],"type":"Point"}
}