{
  "type": "Feature",
  "properties": {
    "addr:full":"95 Eltham High St Eltham Greater London SE9 1TD",
    "addr:housenumber":"95",
    "addr:postcode":"se9 1td",
    "addr:street":"Eltham High St",
    "iso:country":"GB",
    "sg:address":"95 Eltham High St",
    "sg:city":"Eltham",
    "sg:classifiers":[
        {
            "category":"Restaurant",
            "type":"Food & Drink"
        }
    ],
    "sg:phone":"+44 20 8850 8801",
    "sg:postcode":"SE9 1TD",
    "sg:province":"Greater London",
    "wof:name":"Wimpy Bar",
    "wof:placetype":"venue"
},
  "geometry": {"coordinates":[0.0538760014,51.4508628845],"type":"Point"}
}