{
  "type": "Feature",
  "properties": {
    "iso:country":"GB",
    "sg:address":"481 New Cross Rd",
    "sg:city":"London",
    "sg:classifiers":[
        {
            "category":"Food & Beverages",
            "subcategory":"Meat & Fish",
            "type":"Retail Goods"
        }
    ],
    "sg:postcode":"SE14 6TA",
    "sg:province":"Greater London",
    "sg:tags":[
        "chip"
    ],
    "wof:name":"Blackburn Fish Bar",
    "wof:placetype":"venue"
},
  "geometry": {"coordinates":[-0.030019,51.475716],"type":"Point"}
}