{
  "type": "Feature",
  "properties": {
    "addr:full":"Queen's Cross, 40 Albyn Place Aberdeen Aberdeen City AB10 1YN",
    "addr:housenumber":"40",
    "addr:postcode":"ab10 1yn",
    "addr:street":"Albyn Place",
    "iso:country":"GB",
    "sg:address":"Queen's Cross, 40 Albyn Place",
    "sg:city":"Aberdeen",
    "sg:classifiers":[
        {
            "category":"Banks & Credit Unions",
            "subcategory":"Bank",
            "type":"Services"
        }
    ],
    "sg:phone":"+44 1224 321212",
    "sg:postcode":"AB10 1YN",
    "sg:province":"Aberdeen City",
    "wof:name":"The Royal Bank of Scotland Plc",
    "wof:placetype":"venue"
},
  "geometry": {"coordinates":[-2.1242508888,57.1430587769],"type":"Point"}
}