{
  "type": "Feature",
  "properties": {
    "addr:full":"57 Kings Road St Leonards-on-sea East Sussex TN37 6DY",
    "addr:housenumber":"57",
    "addr:postcode":"leonards-on-sea;tn37 6dy",
    "addr:street":"Kings Road St",
    "iso:country":"GB",
    "sg:address":"57 Kings Road",
    "sg:city":"St Leonards-on-sea",
    "sg:classifiers":[
        {
            "category":"Building & Trades",
            "subcategory":"Construction",
            "type":"Services"
        }
    ],
    "sg:phone":"+44 1424 421550",
    "sg:postcode":"TN37 6DY",
    "sg:province":"East Sussex",
    "sg:tags":[
        "builder"
    ],
    "wof:name":"Hastings Building Co",
    "wof:placetype":"venue"
},
  "geometry": {"coordinates":[0.560152,50.855125],"type":"Point"}
}