{
  "type": "Feature",
  "properties": {
    "addr:full":"Unit B, North St, Stanground Peterborough Cambridgeshire PE2 8HR",
    "addr:housenumber":"b",
    "addr:postcode":"pe2 8hr",
    "addr:street":"North St",
    "iso:country":"GB",
    "sg:address":"Unit B, North St, Stanground",
    "sg:city":"Peterborough",
    "sg:classifiers":[
        {
            "category":"Professional",
            "subcategory":"Engineering",
            "type":"Services"
        }
    ],
    "sg:phone":"+44 1733 345700",
    "sg:postcode":"PE2 8HR",
    "sg:province":"Cambridgeshire",
    "sg:tags":[
        "contractor",
        "electrical",
        "engineer"
    ],
    "wof:name":"J J M Electrical & Mechanical Services",
    "wof:placetype":"venue"
},
  "geometry": {"coordinates":[-0.2127960026,52.5545272827],"type":"Point"}
}