{
  "type": "Feature",
  "properties": {
    "iso:country":"GB",
    "sg:address":"Malt House Farm, Grove Lane, Lapworth",
    "sg:city":"Warwick",
    "sg:classifiers":[
        {
            "category":"Building & Trades",
            "subcategory":"Construction",
            "type":"Services"
        }
    ],
    "sg:postcode":"B94 6AR",
    "sg:province":"Warwickshire",
    "sg:tags":[
        "builder"
    ],
    "wof:name":"Salvus Construction",
    "wof:placetype":"venue"
},
  "geometry": {"coordinates":[-1.752736,52.346653],"type":"Point"}
}