{
  "type": "Feature",
  "properties": {
    "addr:full":"282a Kensington High Street London Greater London W14 8NZ",
    "addr:housenumber":"282a",
    "addr:postcode":"w14 8nz",
    "addr:street":"Kensington High Street",
    "iso:country":"GB",
    "sg:address":"282a Kensington High Street",
    "sg:city":"London",
    "sg:classifiers":[
        {
            "category":"Shopping",
            "subcategory":"Florist",
            "type":"Retail Goods"
        }
    ],
    "sg:phone":"+44 20 7602 1314",
    "sg:postcode":"W14 8NZ",
    "sg:province":"Greater London",
    "wof:name":"Fluer of Kensington",
    "wof:placetype":"venue"
},
  "geometry": {"coordinates":[-0.2013230026,51.4983253479],"type":"Point"}
}