{
  "type": "Feature",
  "properties": {
    "addr:full":"59 St Martins Lane London Greater London WC2N 4JS",
    "addr:housenumber":"59",
    "addr:postcode":"wc2n 4js",
    "addr:street":"St Martins Lane",
    "iso:country":"GB",
    "sg:address":"59 St Martins Lane",
    "sg:city":"London",
    "sg:classifiers":[
        {
            "category":"Professional",
            "subcategory":"Business Services",
            "type":"Services"
        }
    ],
    "sg:phone":"+44 20 7379 4074",
    "sg:postcode":"WC2N 4JS",
    "sg:province":"Greater London",
    "sg:tags":[
        "import",
        "export",
        "agent"
    ],
    "wof:name":"Multiservicios Suramerica Ltd.",
    "wof:placetype":"venue"
},
  "geometry": {"coordinates":[-0.12701,51.51136],"type":"Point"}
}