{
  "type": "Feature",
  "properties": {
    "addr:full":"Raebarn House, 100 Northolt Road Harrow Greater London HA2 0YJ",
    "addr:housenumber":"100",
    "addr:postcode":"ha2 0yj",
    "addr:street":"Northolt Road",
    "iso:country":"GB",
    "sg:address":"Raebarn House, 100 Northolt Road",
    "sg:city":"Harrow",
    "sg:classifiers":[
        {
            "category":"Real Estate",
            "subcategory":"Surveying",
            "type":"Services"
        }
    ],
    "sg:phone":"+44 20 8864 7522",
    "sg:postcode":"HA2 0YJ",
    "sg:province":"Greater London",
    "sg:tags":[
        "surveyor",
        "valuer"
    ],
    "wof:name":"Lawrence Vacher Partnerships",
    "wof:placetype":"venue"
},
  "geometry": {"coordinates":[-0.34968,51.567413],"type":"Point"}
}