{
  "type": "Feature",
  "properties": {
    "addr:full":"Unit 21, Battersea Business Centre, 99 Lavender Hill London Greater London SW11 5QL",
    "addr:housenumber":"unit 21;99",
    "addr:postcode":"sw11 5ql",
    "addr:street":"Battersea Business;Lavender Hill",
    "iso:country":"GB",
    "sg:address":"Unit 21, Battersea Business Centre, 99 Lavender Hill",
    "sg:city":"London",
    "sg:classifiers":[
        {
            "category":"Shopping",
            "subcategory":"Gifts & Souvenirs",
            "type":"Retail Goods"
        }
    ],
    "sg:phone":"+44 20 7228 8451",
    "sg:postcode":"SW11 5QL",
    "sg:province":"Greater London",
    "sg:tags":[
        "greeting",
        "card"
    ],
    "wof:name":"Select Cards",
    "wof:placetype":"venue"
},
  "geometry": {"coordinates":[-0.1562100053,51.4654006958],"type":"Point"}
}