{
  "type": "Feature",
  "properties": {
    "iso:country":"GB",
    "sg:address":"St Francis Family Centre, Pricne Charles Avenue",
    "sg:city":"Derby",
    "sg:classifiers":[
        {
            "category":"Government",
            "subcategory":"City Hall",
            "type":"Public Place"
        },
        {
            "category":"Organizations",
            "subcategory":"Membership Organization",
            "type":"Services"
        }
    ],
    "sg:phone":"+44 1332 297774",
    "sg:postcode":"DE22 4BH",
    "sg:province":"Derbyshire",
    "sg:tags":[
        "club"
    ],
    "wof:name":"Saints & Sinners Club St.Francis Family Centre",
    "wof:placetype":"venue"
},
  "geometry": {"coordinates":[-1.51638,52.928249],"type":"Point"}
}