{
  "type": "Feature",
  "properties": {
    "iso:country":"GB",
    "sg:address":"1 Puckpool Cottages Puckpool Pa",
    "sg:city":"Seaview",
    "sg:classifiers":[
        {
            "category":"Museum",
            "subcategory":"Art Museum",
            "type":"Entertainment"
        },
        {
            "category":"Museum",
            "type":"Entertainment"
        }
    ],
    "sg:phone":"+44 1983 567665",
    "sg:postcode":"PO34 5AR",
    "sg:province":"Isle of Wight",
    "sg:tags":[
        "gallery"
    ],
    "wof:name":"The Wireless Museum",
    "wof:placetype":"venue"
},
  "geometry": {"coordinates":[-1.110274,50.719559],"type":"Point"}
}