{
  "type": "Feature",
  "properties": {
    "addr:full":"40 St. Johns Hill Battersea Greater London SW11 1RZ",
    "addr:housenumber":"40",
    "addr:postcode":"sw11 1rz",
    "addr:street":"St. Johns Hill",
    "iso:country":"GB",
    "sg:address":"40 St. Johns Hill",
    "sg:city":"Battersea",
    "sg:classifiers":[
        {
            "category":"Internet Cafe",
            "subcategory":"None",
            "type":"Food & Drink"
        },
        {
            "category":"Utilities",
            "type":"Services"
        }
    ],
    "sg:phone":"+44 20 7738 0015",
    "sg:postcode":"SW11 1RZ",
    "sg:province":"Greater London",
    "wof:name":"Battersea Net",
    "wof:placetype":"venue"
},
  "geometry": {"coordinates":[-0.1732500046,51.4619483948],"type":"Point"}
}