{
  "type": "Feature",
  "properties": {
    "addr:full":"3 Lakes Pde, Ennerdale Dr Barrow-in-furness Cumbria LA14 4PR",
    "addr:postcode":"la14 4pr",
    "addr:street":"Ennerdale Dr",
    "iso:country":"GB",
    "sg:address":"3 Lakes Pde, Ennerdale Dr",
    "sg:city":"Barrow-in-furness",
    "sg:classifiers":[
        {
            "category":"Food & Beverages",
            "subcategory":"Liquor & Beverages",
            "type":"Retail Goods"
        }
    ],
    "sg:postcode":"LA14 4PR",
    "sg:province":"Cumbria",
    "sg:tags":[
        "beer",
        "spirit",
        "wines"
    ],
    "wof:name":"McAllister,M,",
    "wof:placetype":"venue"
},
  "geometry": {"coordinates":[-3.2258470058,54.1110877991],"type":"Point"}
}