{
  "type": "Feature",
  "properties": {
    "iso:country":"GB",
    "sg:address":"165 Clayponds Gardens",
    "sg:city":"London",
    "sg:classifiers":[
        {
            "category":"Professional",
            "subcategory":"Management & Consulting",
            "type":"Services"
        },
        {
            "category":"Real Estate",
            "subcategory":"Real Estate Agent",
            "type":"Services"
        }
    ],
    "sg:phone":"+44 20 7727 2323",
    "sg:postcode":"W5 4RQ",
    "sg:province":"Greater London",
    "sg:tags":[
        "consultant",
        "business"
    ],
    "wof:name":"Axum Ltd.",
    "wof:placetype":"venue"
},
  "geometry": {"coordinates":[-0.30351,51.495419],"type":"Point"}
}