{
  "type": "Feature",
  "properties": {
    "iso:country":"GB",
    "sg:address":"166 London Road, Hazel Grove",
    "sg:city":"Stockport",
    "sg:classifiers":[
        {
            "category":"Sports & Exercise",
            "subcategory":"Athletic Track",
            "type":"Entertainment"
        },
        {
            "category":"Shopping",
            "subcategory":"Luggage & Leather Goods",
            "type":"Retail Goods"
        }
    ],
    "sg:phone":"+44 161 456 5995",
    "sg:postcode":"SK7 4DJ",
    "sg:province":"Cheshire",
    "sg:tags":[
        "handbag",
        "bags",
        "belt",
        "retailer",
        "accessory"
    ],
    "wof:name":"The Discount Bag Shop",
    "wof:placetype":"venue"
},
  "geometry": {"coordinates":[-2.122732,53.380577],"type":"Point"}
}