{
  "type": "Feature",
  "properties": {
    "iso:country":"GB",
    "sg:address":"Merseyway",
    "sg:city":"Stockport",
    "sg:classifiers":[
        {
            "category":"Shopping",
            "subcategory":"Clothing, Apparel, & Fashions",
            "type":"Retail Goods"
        }
    ],
    "sg:phone":"+44 161 477 7350",
    "sg:postcode":"SK1 1PL",
    "sg:province":"Cheshire",
    "sg:tags":[
        "ladieswear"
    ],
    "wof:name":"Sears Ltd.",
    "wof:placetype":"venue"
},
  "geometry": {"coordinates":[-2.1593260765,53.4117965698],"type":"Point"}
}