{
  "type": "Feature",
  "properties": {
    "addr:full":"7 Alderson Drive, Smithies Barnsley South Yorkshire S71 1UU",
    "addr:housenumber":"7",
    "addr:postcode":"s71 1uu",
    "addr:street":"Alderson Drive;Yorkshire",
    "iso:country":"GB",
    "sg:address":"7 Alderson Drive, Smithies",
    "sg:city":"Barnsley",
    "sg:classifiers":[
        {
            "category":"Professional",
            "subcategory":"Printing & Photocopies",
            "type":"Services"
        }
    ],
    "sg:postcode":"S71 1UU",
    "sg:province":"South Yorkshire",
    "sg:tags":[
        "printer"
    ],
    "wof:name":"K Gale",
    "wof:placetype":"venue"
},
  "geometry": {"coordinates":[-1.4715909958,53.5732727051],"type":"Point"}
}