{
  "type": "Feature",
  "properties": {
    "addr:full":"1 Comberton Road Kidderminster Staffordshire DY10 1UA",
    "addr:housenumber":"1",
    "addr:postcode":"dy10 1ua",
    "addr:street":"Comberton Road",
    "iso:country":"GB",
    "sg:address":"1 Comberton Road",
    "sg:city":"Kidderminster",
    "sg:classifiers":[
        {
            "category":"Shopping",
            "subcategory":"Clothing, Apparel, & Fashions",
            "type":"Retail Goods"
        }
    ],
    "sg:postcode":"DY10 1UA",
    "sg:province":"Staffordshire",
    "sg:tags":[
        "shop"
    ],
    "wof:name":"U S of A Trading Post",
    "wof:placetype":"venue"
},
  "geometry": {"coordinates":[-2.239131,52.384991],"type":"Point"}
}