{
  "type": "Feature",
  "properties": {
    "addr:full":"Dunsfold Park, Stovolds Hill Cranleigh Surrey GU6 8TB",
    "addr:postcode":"gu6 8tb",
    "addr:street":"Dunsfold Park Stovolds Hill",
    "iso:country":"GB",
    "sg:address":"Dunsfold Park, Stovolds Hill",
    "sg:city":"Cranleigh",
    "sg:classifiers":[
        {
            "category":"Shopping",
            "subcategory":"Mobile Phones",
            "type":"Retail Goods"
        },
        {
            "category":"Professional",
            "subcategory":"Computer Services",
            "type":"Services"
        }
    ],
    "sg:phone":"+44 1483 275926",
    "sg:postcode":"GU6 8TB",
    "sg:province":"Surrey",
    "sg:tags":[
        "system",
        "software"
    ],
    "wof:name":"Motiontouch Ltd.",
    "wof:placetype":"venue"
},
  "geometry": {"coordinates":[-0.5223829746,51.1135826111],"type":"Point"}
}