{
  "type": "Feature",
  "properties": {
    "addr:full":"31 Main Av Enfield Greater London EN1 1DJ",
    "addr:housenumber":"31",
    "addr:postcode":"en1 1dj",
    "addr:street":"Main Av",
    "iso:country":"GB",
    "sg:address":"31 Main Av",
    "sg:city":"Enfield",
    "sg:classifiers":[
        {
            "category":"Food & Beverages",
            "subcategory":"Meat & Fish",
            "type":"Retail Goods"
        }
    ],
    "sg:phone":"+44 20 8363 2929",
    "sg:postcode":"EN1 1DJ",
    "sg:province":"Greater London",
    "sg:tags":[
        "butcher"
    ],
    "wof:name":"M J Evans",
    "wof:placetype":"venue"
},
  "geometry": {"coordinates":[-0.065403,51.644909],"type":"Point"}
}