{
  "type": "Feature",
  "properties": {
    "iso:country":"GB",
    "sg:address":"100-102 Gigg Lane, Bury Grounds",
    "sg:city":"Bury",
    "sg:classifiers":[
        {
            "category":"Autos & Motor Vehicles",
            "subcategory":"Auto Supplies",
            "type":"Retail Goods"
        }
    ],
    "sg:phone":"+44 161 797 7782",
    "sg:postcode":"BL9 9EW",
    "sg:province":"Lancashire",
    "sg:tags":[
        "electric"
    ],
    "wof:name":"Holt & Martin Ltd.",
    "wof:placetype":"venue"
},
  "geometry": {"coordinates":[-2.288281,53.58255],"type":"Point"}
}