{
  "type": "Feature",
  "properties": {
    "iso:country":"GB",
    "sg:address":"13 Dormer Place",
    "sg:city":"Leamington Spa",
    "sg:classifiers":[
        {
            "category":"Home & Garden",
            "subcategory":"Building Materials",
            "type":"Retail Goods"
        }
    ],
    "sg:phone":"+44 1926 450650",
    "sg:postcode":"CV32 5AA",
    "sg:province":"Warwickshire",
    "sg:tags":[
        "dust",
        "extraction",
        "ventilation",
        "system",
        "ventilator"
    ],
    "wof:name":"Colt International Ltd.",
    "wof:placetype":"venue"
},
  "geometry": {"coordinates":[-1.535552,52.28809],"type":"Point"}
}