{
  "type": "Feature",
  "properties": {
    "iso:country":"GB",
    "sg:address":"18 Arlington Gardens, Saltdean",
    "sg:city":"Brighton",
    "sg:classifiers":[
        {
            "category":"Real Estate",
            "subcategory":"Architect",
            "type":"Services"
        }
    ],
    "sg:phone":"+44 1273 300090",
    "sg:postcode":"BN2 8QE",
    "sg:province":"East Sussex",
    "sg:tags":[
        "architectural"
    ],
    "wof:name":"Building Technical Services",
    "wof:placetype":"venue"
},
  "geometry": {"coordinates":[-0.0329149999,50.8096237183],"type":"Point"}
}