{
  "type": "Feature",
  "properties": {
    "iso:country":"GB",
    "sg:address":"63 High Street",
    "sg:city":"Nairn",
    "sg:classifiers":[
        {
            "category":"Shopping",
            "subcategory":"Clothing, Apparel, & Fashions",
            "type":"Retail Goods"
        }
    ],
    "sg:phone":"+44 1667 455271",
    "sg:postcode":"IV12 4BW",
    "sg:province":"Highland",
    "sg:tags":[
        "shop"
    ],
    "sg:website":"http://www.mackays.co.uk",
    "wof:name":"Mackays Stores Ltd",
    "wof:placetype":"venue"
},
  "geometry": {"coordinates":[-3.868165,57.584778],"type":"Point"}
}