{
  "type": "Feature",
  "properties": {
    "addr:full":"New Street Woodbridge Suffolk IP12 1DT",
    "addr:postcode":"ip12 1dt",
    "addr:street":"New Street",
    "iso:country":"GB",
    "sg:address":"New Street",
    "sg:city":"Woodbridge",
    "sg:classifiers":[
        {
            "category":"Banks & Credit Unions",
            "subcategory":"Financial Services",
            "type":"Services"
        }
    ],
    "sg:phone":"+44 1394 380537",
    "sg:postcode":"IP12 1DT",
    "sg:province":"Suffolk",
    "sg:tags":[
        "building",
        "society"
    ],
    "wof:name":"Ipswich Building Society",
    "wof:placetype":"venue"
},
  "geometry": {"coordinates":[1.3180749416,52.0941505432],"type":"Point"}
}