{
  "type": "Feature",
  "properties": {
    "iso:country":"GB",
    "sg:address":"89-90 Lammas Street",
    "sg:city":"Carmarthen",
    "sg:classifiers":[
        {
            "category":"Organizations",
            "subcategory":"Community Association",
            "type":"Services"
        }
    ],
    "sg:phone":"+44 1267 232714",
    "sg:postcode":"SA31 3AH",
    "sg:province":"Carmarthenshire",
    "sg:tags":[
        "society",
        "housing"
    ],
    "wof:name":"Bro Myrddin Housing Association",
    "wof:placetype":"venue"
},
  "geometry": {"coordinates":[-4.313726,51.856365],"type":"Point"}
}