{
  "type": "Feature",
  "properties": {
    "addr:full":"Unit 16 Parkway Court, Glaisdale Industrial Estate, Bilborough Nottingham Nottinghamshire NG8 4GN",
    "addr:housenumber":"unit 16",
    "addr:postcode":"ng8 4gn",
    "addr:street":"Parkway Court;Industrial Estate",
    "iso:country":"GB",
    "sg:address":"Unit 16 Parkway Court, Glaisdale Industrial Estate, Bilborough",
    "sg:city":"Nottingham",
    "sg:classifiers":[
        {
            "category":"Autos & Motor Vehicles",
            "subcategory":"Auto Supplies",
            "type":"Retail Goods"
        }
    ],
    "sg:phone":"+44 870 077 7701",
    "sg:postcode":"NG8 4GN",
    "sg:province":"Nottinghamshire",
    "sg:tags":[
        "part",
        "motorcycle",
        "accessory"
    ],
    "wof:name":"A R T",
    "wof:placetype":"venue"
},
  "geometry": {"coordinates":[-1.228364,52.958382],"type":"Point"}
}