{
  "type": "Feature",
  "properties": {
    "iso:country":"GB",
    "sg:address":"Courtleigh House, 74-75 Lemon Street",
    "sg:city":"Truro",
    "sg:classifiers":[
        {
            "category":"Banks & Credit Unions",
            "subcategory":"Financial Services",
            "type":"Services"
        }
    ],
    "sg:phone":"+44 1872 354000",
    "sg:postcode":"TR1 2PN",
    "sg:province":"Cornwall",
    "sg:tags":[
        "consultant"
    ],
    "wof:name":"Abbey Life Assurance Co",
    "wof:placetype":"venue"
},
  "geometry": {"coordinates":[-5.052037,50.262058],"type":"Point"}
}