{
  "type": "Feature",
  "properties": {
    "addr:full":"12 Eastbury Road Northwood Greater London HA6 3AL",
    "addr:housenumber":"12",
    "addr:postcode":"ha6 3al",
    "addr:street":"Eastbury Road",
    "iso:country":"GB",
    "sg:address":"12 Eastbury Road",
    "sg:city":"Northwood",
    "sg:classifiers":[
        {
            "category":"Health Services",
            "subcategory":"Nursing And Care Facility",
            "type":"Services"
        }
    ],
    "sg:phone":"+44 1923 823816",
    "sg:postcode":"HA6 3AL",
    "sg:province":"Greater London",
    "sg:tags":[
        "home"
    ],
    "wof:name":"The Eastbury Nursing Home",
    "wof:placetype":"venue"
},
  "geometry": {"coordinates":[-0.4226610065,51.6142501831],"type":"Point"}
}