{
  "type": "Feature",
  "properties": {
    "addr:full":"Woodside Terrace Ellon Aberdeenshire AB41 6QJ",
    "addr:postcode":"ab41 6qj",
    "addr:street":"Woodside Terrace",
    "iso:country":"GB",
    "sg:address":"Woodside Terrace",
    "sg:city":"Ellon",
    "sg:classifiers":[
        {
            "category":"Health Services",
            "subcategory":"Doctor",
            "type":"Services"
        }
    ],
    "sg:postcode":"AB41 6QJ",
    "sg:province":"Aberdeenshire",
    "sg:tags":[
        "practitioners"
    ],
    "wof:name":"The Surgery",
    "wof:placetype":"venue"
},
  "geometry": {"coordinates":[-2.151414,57.309883],"type":"Point"}
}