{
  "type": "Feature",
  "properties": {
    "addr:full":"Upper Wharf Street Salford Greater Manchester M5 4TY",
    "addr:postcode":"m5 4ty",
    "addr:street":"Upper Wharf Street",
    "iso:country":"GB",
    "sg:address":"Upper Wharf Street",
    "sg:city":"Salford",
    "sg:classifiers":[
        {
            "category":"Building & Trades",
            "subcategory":"Equipment Rental",
            "type":"Services"
        }
    ],
    "sg:phone":"+44 161 737 4545",
    "sg:postcode":"M5 4TY",
    "sg:province":"Greater Manchester",
    "sg:tags":[
        "plant",
        "machinery"
    ],
    "wof:name":"J W S Waste & Recycling Services Ltd.",
    "wof:placetype":"venue"
},
  "geometry": {"coordinates":[-2.267089,53.481747],"type":"Point"}
}