{
  "type": "Feature",
  "properties": {
    "addr:full":"Dunston La Chesterfield Derbyshire S41 8HA",
    "addr:postcode":"s41 8ha",
    "iso:country":"GB",
    "sg:address":"Dunston La",
    "sg:city":"Chesterfield",
    "sg:classifiers":[
        {
            "category":"Bars & Pubs",
            "type":"Food & Drink"
        }
    ],
    "sg:postcode":"S41 8HA",
    "sg:province":"Derbyshire",
    "sg:tags":[
        "pubs",
        "inn"
    ],
    "wof:name":"Mansfield Brewery Trading Ltd",
    "wof:placetype":"venue"
},
  "geometry": {"coordinates":[-1.4489250183,53.2623825073],"type":"Point"}
}