{
  "type": "Feature",
  "properties": {
    "iso:country":"GB",
    "sg:address":"168a Silver Road",
    "sg:city":"Norwich",
    "sg:classifiers":[
        {
            "category":"Health Services",
            "subcategory":"Dentist",
            "type":"Services"
        }
    ],
    "sg:postcode":"NR3 4TH",
    "sg:province":"Norfolk",
    "sg:tags":[
        "technician",
        "dental"
    ],
    "wof:name":"Ladysmith Dental Laboratory",
    "wof:placetype":"venue"
},
  "geometry": {"coordinates":[1.302535,52.642063],"type":"Point"}
}