{
  "type": "Feature",
  "properties": {
    "iso:country":"GB",
    "sg:address":"22 Woodside Avenue",
    "sg:city":"Amersham",
    "sg:classifiers":[
        {
            "category":"Social Services",
            "subcategory":"Job Training",
            "type":"Services"
        }
    ],
    "sg:phone":"+44 1494 727038",
    "sg:postcode":"HP6 6BG",
    "sg:province":"Buckinghamshire",
    "sg:tags":[
        "translator",
        "interpreter"
    ],
    "wof:name":"Litera Polish Translation Services",
    "wof:placetype":"venue"
},
  "geometry": {"coordinates":[-0.596952,51.683403],"type":"Point"}
}