{
  "type": "Feature",
  "properties": {
    "iso:country":"GB",
    "sg:address":"Park Rd",
    "sg:city":"Winchester",
    "sg:classifiers":[
        {
            "category":"Health Services",
            "subcategory":"Nursing And Care Facility",
            "type":"Services"
        }
    ],
    "sg:phone":"+44 1962 854731",
    "sg:postcode":"SO23 7BE",
    "sg:province":"Hampshire",
    "sg:tags":[
        "home"
    ],
    "wof:name":"Brendon House",
    "wof:placetype":"venue"
},
  "geometry": {"coordinates":[-1.315634,51.075008],"type":"Point"}
}