{
  "type": "Feature",
  "properties": {
    "iso:country":"GB",
    "sg:address":"Unit 1 Arun Business Park",
    "sg:city":"Bognor Regis",
    "sg:classifiers":[
        {
            "category":"Parking",
            "type":"Transportation"
        }
    ],
    "sg:phone":"+44 1243 822030",
    "sg:postcode":"PO22 9SX",
    "sg:province":"West Sussex",
    "sg:tags":[
        "car",
        "valet"
    ],
    "wof:name":"K & W Valeting",
    "wof:placetype":"venue"
},
  "geometry": {"coordinates":[-0.66731,50.795921],"type":"Point"}
}