{
  "type": "Feature",
  "properties": {
    "iso:country":"GB",
    "sg:address":"Box Office, Catherine Street",
    "sg:city":"Rotherham",
    "sg:classifiers":[
        {
            "category":"Government",
            "subcategory":"Office",
            "type":"Public Place"
        },
        {
            "category":"Arts & Performance",
            "subcategory":"Theater",
            "type":"Entertainment"
        }
    ],
    "sg:phone":"+44 1709 823640",
    "sg:postcode":"S65 1EB",
    "sg:province":"South Yorkshire",
    "sg:tags":[
        "local",
        "concert",
        "theatre",
        "hall"
    ],
    "wof:name":"Civic Theatre Rotherham",
    "wof:placetype":"venue"
},
  "geometry": {"coordinates":[-1.3518999815,53.4310798645],"type":"Point"}
}