{
  "type": "Feature",
  "properties": {
    "iso:country":"GB",
    "sg:address":"131 Market Street",
    "sg:city":"Dalton-in-furness",
    "sg:classifiers":[
        {
            "category":"Shopping",
            "subcategory":"Florist",
            "type":"Retail Goods"
        }
    ],
    "sg:phone":"+44 1229 462652",
    "sg:postcode":"LA15 8RG",
    "sg:province":"Cumbria",
    "wof:name":"DODDS DESIGNER FLORIST",
    "wof:placetype":"venue"
},
  "geometry": {"coordinates":[-3.179056,54.156776],"type":"Point"}
}