{
  "type": "Feature",
  "properties": {
    "addr:full":"17 Marine Parade Whitstable Kent CT5 2BG",
    "addr:housenumber":"17",
    "addr:postcode":"ct5 2bg",
    "addr:street":"Marine Parade Whitstable",
    "iso:country":"GB",
    "sg:address":"17 Marine Parade",
    "sg:city":"Whitstable",
    "sg:classifiers":[
        {
            "category":"Health Services",
            "subcategory":"Nursing And Care Facility",
            "type":"Services"
        }
    ],
    "sg:phone":"+44 1227 275466",
    "sg:postcode":"CT5 2BG",
    "sg:province":"Kent",
    "sg:tags":[
        "home"
    ],
    "wof:name":"Whitecrofts Nursing Home",
    "wof:placetype":"venue"
},
  "geometry": {"coordinates":[1.0411649942,51.3645133972],"type":"Point"}
}