{
  "type": "Feature",
  "properties": {
    "addr:full":"41 Wordsworth Road Worthing West Sussex BN11 3HZ",
    "addr:housenumber":"41",
    "addr:postcode":"bn11 3hz",
    "addr:street":"Wordsworth Road",
    "iso:country":"GB",
    "sg:address":"41 Wordsworth Road",
    "sg:city":"Worthing",
    "sg:classifiers":[
        {
            "category":"Organizations",
            "subcategory":"Non-profit Organization",
            "type":"Services"
        }
    ],
    "sg:phone":"+44 1903 231020",
    "sg:postcode":"BN11 3HZ",
    "sg:province":"West Sussex",
    "sg:tags":[
        "organisation",
        "voluntary",
        "charity"
    ],
    "wof:name":"British Red Cross",
    "wof:placetype":"venue"
},
  "geometry": {"coordinates":[-0.383051,50.810535],"type":"Point"}
}