{
  "type": "Feature",
  "properties": {
    "iso:country":"GB",
    "sg:address":"222 Commercial Road",
    "sg:city":"Portsmouth",
    "sg:classifiers":[
        {
            "category":"Sports & Exercise",
            "subcategory":"Sports Center",
            "type":"Entertainment"
        }
    ],
    "sg:phone":"+44 23 9282 5222",
    "sg:postcode":"PO1 1HG",
    "sg:province":"Hampshire",
    "sg:tags":[
        "shop",
        "good"
    ],
    "wof:name":"First Sport Ltd.",
    "wof:placetype":"venue"
},
  "geometry": {"coordinates":[-1.088522,50.80151],"type":"Point"}
}