{
  "type": "Feature",
  "properties": {
    "addr:full":"24 Nicholas Street Chester Cheshire CH1 2AU",
    "addr:housenumber":"24",
    "addr:postcode":"ch1 2au",
    "addr:street":"Nicholas Street",
    "iso:country":"GB",
    "sg:address":"24 Nicholas Street",
    "sg:city":"Chester",
    "sg:classifiers":[
        {
            "category":"Professional",
            "subcategory":"Accounting & Tax Preparation",
            "type":"Services"
        }
    ],
    "sg:postcode":"CH1 2AU",
    "sg:province":"Cheshire",
    "sg:tags":[
        "accountant"
    ],
    "wof:name":"Mitchell Charlesworth Chartered Accountants",
    "wof:placetype":"venue"
},
  "geometry": {"coordinates":[-2.89497,53.188774],"type":"Point"}
}