{
  "type": "Feature",
  "properties": {
    "addr:full":"8 The Newlands Witham Essex CM8 2AP",
    "addr:housenumber":"8",
    "addr:postcode":"cm8 2ap",
    "addr:street":"The Newlands Witham",
    "iso:country":"GB",
    "sg:address":"8 The Newlands",
    "sg:city":"Witham",
    "sg:classifiers":[
        {
            "category":"Shopping",
            "subcategory":"Clothing, Apparel, & Fashions",
            "type":"Retail Goods"
        }
    ],
    "sg:phone":"+44 1376 501132",
    "sg:postcode":"CM8 2AP",
    "sg:province":"Essex",
    "sg:tags":[
        "ladieswear"
    ],
    "wof:name":"Impressions",
    "wof:placetype":"venue"
},
  "geometry": {"coordinates":[0.642283,51.801659],"type":"Point"}
}