{
  "type": "Feature",
  "properties": {
    "addr:full":"142 Don Street, Woodside Aberdeen Aberdeen City AB24 2SB",
    "addr:housenumber":"142",
    "addr:postcode":"ab24 2sb",
    "addr:street":"Don Street",
    "iso:country":"GB",
    "sg:address":"142 Don Street, Woodside",
    "sg:city":"Aberdeen",
    "sg:classifiers":[
        {
            "category":"Professional",
            "subcategory":"Art Services",
            "type":"Services"
        }
    ],
    "sg:phone":"+44 1224 481838",
    "sg:postcode":"AB24 2SB",
    "sg:province":"Aberdeen City",
    "sg:tags":[
        "graphic",
        "designer"
    ],
    "wof:name":"Elfin",
    "wof:placetype":"venue"
},
  "geometry": {"coordinates":[-2.124527,57.17384],"type":"Point"}
}