{
  "type": "Feature",
  "properties": {
    "iso:country":"GB",
    "sg:address":"60 Main Road, Ridgeway",
    "sg:city":"Sheffield",
    "sg:classifiers":[
        {
            "category":"Government",
            "subcategory":"Post Office",
            "type":"Public Place"
        }
    ],
    "sg:postcode":"S12 3XR",
    "sg:province":"Derbyshire",
    "wof:name":"Ridgeway Post Office",
    "wof:placetype":"venue"
},
  "geometry": {"coordinates":[-1.3970810175,53.3299407959],"type":"Point"}
}