{
  "type": "Feature",
  "properties": {
    "iso:country":"GB",
    "sg:address":"Balloch Filling Station, Balloch Road",
    "sg:city":"Alexandria",
    "sg:classifiers":[
        {
            "category":"Autos & Motor Vehicles",
            "subcategory":"Automobile Sales",
            "type":"Retail Goods"
        }
    ],
    "sg:phone":"+44 1389 751404",
    "sg:postcode":"G83 8LG",
    "sg:province":"Argyll and Bute",
    "sg:tags":[
        "car"
    ],
    "wof:name":"Robert Andrews Car Sales",
    "wof:placetype":"venue"
},
  "geometry": {"coordinates":[-4.579449,56.004051],"type":"Point"}
}