{
  "type": "Feature",
  "properties": {
    "addr:full":"34 Paddockhall Road Haywards Heath East Sussex RH16 1HL",
    "addr:housenumber":"34",
    "addr:postcode":"rh16 1hl",
    "addr:street":"Paddockhall Road",
    "iso:country":"GB",
    "sg:address":"34 Paddockhall Road",
    "sg:city":"Haywards Heath",
    "sg:classifiers":[
        {
            "category":"Health Services",
            "subcategory":"Nursing And Care Facility",
            "type":"Services"
        }
    ],
    "sg:postcode":"RH16 1HL",
    "sg:province":"East Sussex",
    "sg:tags":[
        "home"
    ],
    "wof:name":"S Patal",
    "wof:placetype":"venue"
},
  "geometry": {"coordinates":[-0.109404,51.002399],"type":"Point"}
}