{
  "type": "Feature",
  "properties": {
    "iso:country":"GB",
    "sg:address":"5-7 Sherrards Green Road",
    "sg:city":"Malvern",
    "sg:classifiers":[
        {
            "category":"Organizations",
            "subcategory":"Non-profit Organization",
            "type":"Services"
        }
    ],
    "sg:phone":"+44 1684 569002",
    "sg:postcode":"WR14 2ED",
    "sg:province":"Herefordshire",
    "sg:tags":[
        "organisation",
        "voluntary",
        "charity"
    ],
    "wof:name":"Mencap",
    "wof:placetype":"venue"
},
  "geometry": {"coordinates":[-2.30707407,52.1127052307],"type":"Point"}
}