{
  "type": "Feature",
  "properties": {
    "addr:full":"1 Olde Mill Houses, Mill St Wells Somerset BA5 2AT",
    "addr:housenumber":"1",
    "addr:postcode":"ba5 2at",
    "addr:street":"Olde Mill Houses Mill St",
    "iso:country":"GB",
    "sg:address":"1 Olde Mill Houses, Mill St",
    "sg:city":"Wells",
    "sg:classifiers":[
        {
            "category":"Building & Trades",
            "subcategory":"Construction",
            "type":"Services"
        }
    ],
    "sg:postcode":"BA5 2AT",
    "sg:province":"Somerset",
    "sg:tags":[
        "contractor"
    ],
    "wof:name":"Ambrosini,A,",
    "wof:placetype":"venue"
},
  "geometry": {"coordinates":[-2.645954,51.211349],"type":"Point"}
}