{
  "type": "Feature",
  "properties": {
    "addr:full":"14 Kingland Crescent Poole Dorset BH15 1TB",
    "addr:housenumber":"14",
    "addr:postcode":"bh15 1tb",
    "addr:street":"Kingland Crescent",
    "iso:country":"GB",
    "sg:address":"14 Kingland Crescent",
    "sg:city":"Poole",
    "sg:classifiers":[
        {
            "category":"Food & Beverages",
            "subcategory":"Specialty",
            "type":"Retail Goods"
        }
    ],
    "sg:phone":"+44 1202 671449",
    "sg:postcode":"BH15 1TB",
    "sg:province":"Dorset",
    "sg:tags":[
        "product",
        "health"
    ],
    "wof:name":"Holland & Barrett",
    "wof:placetype":"venue"
},
  "geometry": {"coordinates":[-1.9746,50.717621],"type":"Point"}
}