{
  "type": "Feature",
  "properties": {
    "iso:country":"GB",
    "sg:address":"Chester Road",
    "sg:city":"Greenock",
    "sg:classifiers":[
        {
            "category":"Farming",
            "subcategory":"Nursery",
            "type":"Manufacturing & Wholesale Goods"
        },
        {
            "category":"Education",
            "subcategory":"Preschool",
            "type":"Public Place"
        }
    ],
    "sg:phone":"+44 1475 630157",
    "sg:postcode":"PA16 0TT",
    "sg:province":"Inverclyde",
    "sg:tags":[
        "school",
        "creche"
    ],
    "wof:name":"Ladybird Pre-Five Centre",
    "wof:placetype":"venue"
},
  "geometry": {"coordinates":[-4.815151,55.94479],"type":"Point"}
}