{
  "type": "Feature",
  "properties": {
    "addr:full":"22 Howden Avenue, Newhouse Industrial Estate Motherwell North Lanarkshire ML1 5RX",
    "addr:housenumber":"22",
    "addr:postcode":"ml1 5rx",
    "addr:street":"Howden Avenue Newhouse Industrial Estate",
    "iso:country":"GB",
    "sg:address":"22 Howden Avenue, Newhouse Industrial Estate",
    "sg:city":"Motherwell",
    "sg:classifiers":[
        {
            "category":"Manufacturing",
            "subcategory":"Furniture",
            "type":"Manufacturing & Wholesale Goods"
        }
    ],
    "sg:postcode":"ML1 5RX",
    "sg:province":"North Lanarkshire",
    "sg:tags":[
        "mnfr",
        "upholsterer"
    ],
    "wof:name":"Qudos Furniture Ltd",
    "wof:placetype":"venue"
},
  "geometry": {"coordinates":[-3.9518330097,55.8319587708],"type":"Point"}
}