{
  "type": "Feature",
  "properties": {
    "addr:full":"Town Quay, Fowey St Austell Cornwall PL23 1AT",
    "addr:postcode":"pl23 1at",
    "addr:street":"Town Quay Fowey",
    "iso:country":"GB",
    "sg:address":"Town Quay, Fowey",
    "sg:city":"St Austell",
    "sg:classifiers":[
        {
            "category":"Travel",
            "subcategory":"Hotels & Motels",
            "type":"Entertainment"
        }
    ],
    "sg:phone":"+44 1726 832450",
    "sg:postcode":"PL23 1AT",
    "sg:province":"Cornwall",
    "wof:name":"King of Prussia Hotel",
    "wof:placetype":"venue"
},
  "geometry": {"coordinates":[-4.639648,50.336273],"type":"Point"}
}