{
  "type": "Feature",
  "properties": {
    "iso:country":"GB",
    "sg:address":"81 Elmdale Drive, Carlton Colville",
    "sg:city":"Lowestoft",
    "sg:classifiers":[
        {
            "category":"Professional",
            "subcategory":"Testing Lab",
            "type":"Services"
        }
    ],
    "sg:phone":"+44 1502 511691",
    "sg:postcode":"NR33 8DQ",
    "sg:province":"Suffolk",
    "sg:tags":[
        "inspection",
        "calibration"
    ],
    "wof:name":"Amtech Services Ltd.",
    "wof:placetype":"venue"
},
  "geometry": {"coordinates":[1.703079,52.455887],"type":"Point"}
}