{
  "type": "Feature",
  "properties": {
    "addr:full":"Devonshire Buildings, Works Road Chesterfield Derbyshire S43 2PE",
    "addr:postcode":"s43 2pe",
    "addr:street":"Works Road",
    "iso:country":"GB",
    "sg:address":"Devonshire Buildings, Works Road",
    "sg:city":"Chesterfield",
    "sg:classifiers":[
        {
            "category":"Home & Garden",
            "subcategory":"Garden Supply",
            "type":"Retail Goods"
        }
    ],
    "sg:postcode":"S43 2PE",
    "sg:province":"Derbyshire",
    "sg:tags":[
        "ornament"
    ],
    "wof:name":"Old Empire",
    "wof:placetype":"venue"
},
  "geometry": {"coordinates":[-1.400359,53.272755],"type":"Point"}
}