{
  "type": "Feature",
  "properties": {
    "addr:full":"Tidal Harbour Port Talbot Neath Port Talbot SA13 1BU",
    "addr:postcode":"sa13 1bu",
    "addr:street":"Tidal Harbour",
    "iso:country":"GB",
    "sg:address":"Tidal Harbour",
    "sg:city":"Port Talbot",
    "sg:classifiers":[
        {
            "category":"Organizations",
            "subcategory":"Non-profit Organization",
            "type":"Services"
        }
    ],
    "sg:phone":"+44 1639 883854",
    "sg:postcode":"SA13 1BU",
    "sg:province":"Neath Port Talbot",
    "sg:tags":[
        "organisation",
        "voluntary",
        "charity"
    ],
    "wof:name":"The Missions to Seamen Club",
    "wof:placetype":"venue"
},
  "geometry": {"coordinates":[-3.78517,51.596649],"type":"Point"}
}