{
  "type": "Feature",
  "properties": {
    "iso:country":"GB",
    "sg:address":"Walnut House, Blackhill Drive, Wolverton Mill South",
    "sg:city":"Milton Keynes",
    "sg:classifiers":[
        {
            "category":"Banks & Credit Unions",
            "subcategory":"Financial Services",
            "type":"Services"
        }
    ],
    "sg:phone":"+44 1908 322600",
    "sg:postcode":"MK12 5TS",
    "sg:province":"Buckinghamshire",
    "sg:tags":[
        "adviser"
    ],
    "wof:name":"Peter Hill Risk Solutions Ltd.",
    "wof:placetype":"venue"
},
  "geometry": {"coordinates":[-0.8324890137,52.0576553345],"type":"Point"}
}