{
  "type": "Feature",
  "properties": {
    "iso:country":"GB",
    "sg:address":"18 Broad Street",
    "sg:city":"Hereford",
    "sg:classifiers":[
        {
            "category":"Communications",
            "type":"Services"
        }
    ],
    "sg:phone":"+44 1432 279594",
    "sg:postcode":"HR4 9NJ",
    "sg:province":"Herefordshire",
    "sg:tags":[
        "broadcasting"
    ],
    "wof:name":"Radio Wyvern & Classic Gold",
    "wof:placetype":"venue"
},
  "geometry": {"coordinates":[-2.717128,52.054947],"type":"Point"}
}