{
  "type": "Feature",
  "properties": {
    "addr:full":"3-4 Queen Street Market Rasen Lincolnshire LN8 3EH",
    "addr:housenumber":"3-4",
    "addr:postcode":"ln8 3eh",
    "addr:street":"Queen Street",
    "iso:country":"GB",
    "sg:address":"3-4 Queen Street",
    "sg:city":"Market Rasen",
    "sg:classifiers":[
        {
            "category":"Shopping",
            "subcategory":"Pharmacy",
            "type":"Retail Goods"
        }
    ],
    "sg:phone":"+44 1673 843336",
    "sg:postcode":"LN8 3EH",
    "sg:province":"Lincolnshire",
    "sg:tags":[
        "pharmacist",
        "chemist"
    ],
    "wof:name":"Boots the Chemists Ltd.",
    "wof:placetype":"venue"
},
  "geometry": {"coordinates":[-0.3369300067,53.3876113892],"type":"Point"}
}