{
  "type": "Feature",
  "properties": {
    "addr:full":"Eastgate, North Newbald York East Riding of Yorkshire YO43 4SD",
    "addr:postcode":"yo43 4sd",
    "addr:street":"Eastgate North Newbald",
    "iso:country":"GB",
    "sg:address":"Eastgate, North Newbald",
    "sg:city":"York",
    "sg:classifiers":[
        {
            "category":"Wholesale",
            "subcategory":"Machinery & Supplies",
            "type":"Manufacturing & Wholesale Goods"
        }
    ],
    "sg:phone":"+44 1430 827377",
    "sg:postcode":"YO43 4SD",
    "sg:province":"East Riding of Yorkshire",
    "wof:name":"South Cave Tractors Ltd.",
    "wof:placetype":"venue"
},
  "geometry": {"coordinates":[-0.612865,53.820873],"type":"Point"}
}