{
  "type": "Feature",
  "properties": {
    "iso:country":"GB",
    "sg:address":"1 Market Street, Hetton Le Hole",
    "sg:city":"Houghton-le-spring",
    "sg:classifiers":[
        {
            "category":"Autos & Motor Vehicles",
            "subcategory":"Auto Supplies",
            "type":"Retail Goods"
        }
    ],
    "sg:phone":"+44 191 517 3784",
    "sg:postcode":"DH5 9DZ",
    "sg:province":"Durham",
    "sg:tags":[
        "component",
        "factor"
    ],
    "wof:name":"L T A Motorparts",
    "wof:placetype":"venue"
},
  "geometry": {"coordinates":[-1.448202014,54.8243408203],"type":"Point"}
}