{
  "type": "Feature",
  "properties": {
    "addr:full":"Unit 27 One Stop Shopping Centre, Walsall Road, Perry Barr Birmingham West Midlands B42 1AA",
    "addr:housenumber":"unit 27",
    "addr:postcode":"b42 1aa",
    "addr:street":"Walsall Road",
    "iso:country":"GB",
    "sg:address":"Unit 27 One Stop Shopping Centre, Walsall Road, Perry Barr",
    "sg:city":"Birmingham",
    "sg:classifiers":[
        {
            "category":"Shopping",
            "subcategory":"Shoes",
            "type":"Retail Goods"
        }
    ],
    "sg:phone":"+44 121 344 3884",
    "sg:postcode":"B42 1AA",
    "sg:province":"West Midlands",
    "sg:tags":[
        "shop"
    ],
    "wof:name":"Shoe Express",
    "wof:placetype":"venue"
},
  "geometry": {"coordinates":[-1.9048589468,52.522518158],"type":"Point"}
}