{
  "type": "Feature",
  "properties": {
    "iso:country":"GB",
    "sg:address":"Pottal Pool Road, Penkridge",
    "sg:city":"Stafford",
    "sg:classifiers":[
        {
            "category":"Arena",
            "subcategory":"Sports Club",
            "type":"Entertainment"
        }
    ],
    "sg:phone":"+44 1785 851337",
    "sg:postcode":"ST19 5RN",
    "sg:province":"Shropshire",
    "sg:tags":[
        "ground"
    ],
    "wof:name":"Edwards Farms Ltd.",
    "wof:placetype":"venue"
},
  "geometry": {"coordinates":[-2.060544014,52.7247238159],"type":"Point"}
}