{
  "type": "Feature",
  "properties": {
    "addr:full":"136 Nelson St Glasgow Glasgow City G5 8EJ",
    "addr:housenumber":"136",
    "addr:postcode":"g5 8ej",
    "addr:street":"Nelson St",
    "iso:country":"GB",
    "sg:address":"136 Nelson St",
    "sg:city":"Glasgow",
    "sg:classifiers":[
        {
            "category":"Government",
            "subcategory":"Fire Station",
            "type":"Public Place"
        }
    ],
    "sg:phone":"+44 141 418 0400",
    "sg:postcode":"G5 8EJ",
    "sg:province":"Glasgow City",
    "sg:tags":[
        "w'sale",
        "lighting"
    ],
    "wof:name":"Millenium Lighting Ltd",
    "wof:placetype":"venue"
},
  "geometry": {"coordinates":[-4.263805,55.853443],"type":"Point"}
}