{
  "type": "Feature",
  "properties": {
    "addr:full":"Park Grange Farm, Hazel Road Loughborough Leicestershire LE11 2JQ",
    "addr:postcode":"le11 2jq",
    "addr:street":"Park;Hazel Road",
    "iso:country":"GB",
    "sg:address":"Park Grange Farm, Hazel Road",
    "sg:city":"Loughborough",
    "sg:classifiers":[
        {
            "category":"Farming",
            "subcategory":"Dairy Farm",
            "type":"Manufacturing & Wholesale Goods"
        }
    ],
    "sg:phone":"+44 1509 215120",
    "sg:postcode":"LE11 2JQ",
    "sg:province":"Leicestershire",
    "wof:name":"F H Moss",
    "wof:placetype":"venue"
},
  "geometry": {"coordinates":[-1.205374,52.759666],"type":"Point"}
}