{
  "type": "Feature",
  "properties": {
    "iso:country":"GB",
    "sg:address":"Gauntlet House, Works Lane",
    "sg:city":"Nottingham",
    "sg:classifiers":[
        {
            "category":"Professional",
            "subcategory":"Detective & Security Services",
            "type":"Services"
        }
    ],
    "sg:postcode":"NG13 9JN",
    "sg:province":"Leicestershire",
    "wof:name":"F Goodbourne",
    "wof:placetype":"venue"
},
  "geometry": {"coordinates":[-0.908514,52.908878],"type":"Point"}
}