{
  "type": "Feature",
  "properties": {
    "iso:country":"GB",
    "sg:address":"West Road, Pogmoor",
    "sg:city":"Barnsley",
    "sg:classifiers":[
        {
            "category":"Utilities",
            "subcategory":"Refuse",
            "type":"Services"
        }
    ],
    "sg:phone":"+44 1226 285635",
    "sg:postcode":"S75 2DH",
    "sg:province":"South Yorkshire",
    "sg:tags":[
        "skip",
        "hire"
    ],
    "wof:name":"Andrich Skip Hire",
    "wof:placetype":"venue"
},
  "geometry": {"coordinates":[-1.503934,53.555359],"type":"Point"}
}