{
  "type": "Feature",
  "properties": {
    "iso:country":"GB",
    "sg:address":"10 Cornwall Terrace, Regent's Park",
    "sg:city":"London",
    "sg:classifiers":[
        {
            "category":"Banks & Credit Unions",
            "subcategory":"Financial Services",
            "type":"Services"
        }
    ],
    "sg:phone":"+44 1224 645420",
    "sg:postcode":"NW1 4QP",
    "sg:province":"Greater London",
    "sg:tags":[
        "consultant"
    ],
    "wof:name":"Blu Securities Ltd.",
    "wof:placetype":"venue"
},
  "geometry": {"coordinates":[-0.10533,51.455029],"type":"Point"}
}