{
  "type": "Feature",
  "properties": {
    "iso:country":"GB",
    "sg:address":"2a London Road",
    "sg:city":"Kingston-upon-thames",
    "sg:classifiers":[
        {
            "category":"Professional",
            "subcategory":"Engineering",
            "type":"Services"
        }
    ],
    "sg:phone":"+44 20 8549 7115",
    "sg:postcode":"KT2 6SN",
    "sg:province":"Greater London",
    "wof:name":"Kingston Technical Resources Ltd.",
    "wof:placetype":"venue"
},
  "geometry": {"coordinates":[-0.2966929972,51.4105682373],"type":"Point"}
}