{
  "type": "Feature",
  "properties": {
    "addr:full":"Unit 10, Southgate Industrial Centre, Southgate Morecambe Lancashire LA3 3PB",
    "addr:housenumber":"unit 10",
    "addr:postcode":"la3 3pb",
    "addr:street":"Southgate Industrial Centre Southgate Morecambe",
    "iso:country":"GB",
    "sg:address":"Unit 10, Southgate Industrial Centre, Southgate",
    "sg:city":"Morecambe",
    "sg:classifiers":[
        {
            "category":"Home & Garden",
            "subcategory":"Home Furnishings",
            "type":"Retail Goods"
        }
    ],
    "sg:phone":"+44 1524 381978",
    "sg:postcode":"LA3 3PB",
    "sg:province":"Lancashire",
    "sg:tags":[
        "wall",
        "wallpaper",
        "covering"
    ],
    "wof:name":"Paint & Decorative Supplies Ltd.",
    "wof:placetype":"venue"
},
  "geometry": {"coordinates":[-2.8400189877,54.0575523376],"type":"Point"}
}