{
  "type": "Feature",
  "properties": {
    "addr:full":"Hall Farm, Main Street, Hovingham York North Yorkshire YO62 4LF",
    "addr:postcode":"yo62 4lf",
    "addr:street":"Hall;Main Street",
    "iso:country":"GB",
    "sg:address":"Hall Farm, Main Street, Hovingham",
    "sg:city":"York",
    "sg:classifiers":[
        {
            "category":"Farming",
            "subcategory":"Livestock Farm",
            "type":"Manufacturing & Wholesale Goods"
        }
    ],
    "sg:postcode":"YO62 4LF",
    "sg:province":"North Yorkshire",
    "sg:tags":[
        "others"
    ],
    "wof:name":"Charles R Wainwright",
    "wof:placetype":"venue"
},
  "geometry": {"coordinates":[-0.9789389968,54.1717147827],"type":"Point"}
}