{
  "type": "Feature",
  "properties": {
    "addr:full":"8 Paganel Road, Selly Oak Birmingham West Midlands B29 5TG",
    "addr:housenumber":"8",
    "addr:postcode":"b29 5tg",
    "addr:street":"Paganel Road",
    "iso:country":"GB",
    "sg:address":"8 Paganel Road, Selly Oak",
    "sg:city":"Birmingham",
    "sg:classifiers":[
        {
            "category":"Retail",
            "subcategory":"Driving School",
            "type":"Services"
        }
    ],
    "sg:phone":"+44 121 608 6127",
    "sg:postcode":"B29 5TG",
    "sg:province":"West Midlands",
    "wof:name":"Trevor S O M  Mountford",
    "wof:placetype":"venue"
},
  "geometry": {"coordinates":[-1.968685,52.443733],"type":"Point"}
}