{
  "type": "Feature",
  "properties": {
    "addr:full":"348 Waylett Pl, West Norwood Tulse Hill Greater London SE27 0TB",
    "addr:housenumber":"348",
    "addr:postcode":"se27 0tb",
    "addr:street":"Waylett Pl;Hill",
    "iso:country":"GB",
    "sg:address":"348 Waylett Pl, West Norwood",
    "sg:city":"Tulse Hill",
    "sg:classifiers":[
        {
            "category":"Retail",
            "subcategory":"Repair Shop",
            "type":"Services"
        }
    ],
    "sg:phone":"+44 20 8766 7585",
    "sg:postcode":"SE27 0TB",
    "sg:province":"Greater London",
    "sg:tags":[
        "radio",
        "television",
        "video"
    ],
    "wof:name":"M & M TV & Videos",
    "wof:placetype":"venue"
},
  "geometry": {"coordinates":[-0.10679,51.428719],"type":"Point"}
}