{
  "type": "Feature",
  "properties": {
    "addr:full":"Stall 39, Bury Market Hall Bury Lancashire BL9 0SW",
    "addr:housenumber":"39",
    "addr:postcode":"bl9 0sw",
    "addr:street":"Stall;Bury Market Hall",
    "iso:country":"GB",
    "sg:address":"Stall 39, Bury Market Hall",
    "sg:city":"Bury",
    "sg:classifiers":[
        {
            "category":"Deli",
            "type":"Food & Drink"
        }
    ],
    "sg:phone":"+44 161 797 5132",
    "sg:postcode":"BL9 0SW",
    "sg:province":"Lancashire",
    "sg:tags":[
        "delicatessen"
    ],
    "wof:name":"David Quality Meats",
    "wof:placetype":"venue"
},
  "geometry": {"coordinates":[-2.29955,53.59235],"type":"Point"}
}