{
  "type": "Feature",
  "properties": {
    "addr:full":"240 Thornton Road Croydon Surrey CR0 3EU",
    "addr:housenumber":"240",
    "addr:postcode":"cr0 3eu",
    "addr:street":"Thornton Road",
    "iso:country":"GB",
    "sg:address":"240 Thornton Road",
    "sg:city":"Croydon",
    "sg:classifiers":[
        {
            "category":"Autos & Motor Vehicles",
            "subcategory":"Fuel & Gas Station",
            "type":"Retail Goods"
        }
    ],
    "sg:phone":"+44 20 8689 1806",
    "sg:postcode":"CR0 3EU",
    "sg:province":"Surrey",
    "sg:tags":[
        "injection"
    ],
    "wof:name":"First Diesel Injection (Croydon) Ltd.",
    "wof:placetype":"venue"
},
  "geometry": {"coordinates":[-0.121152997,51.3880462646],"type":"Point"}
}