{
  "type": "Feature",
  "properties": {
    "iso:country":"GB",
    "sg:address":"Bonson Wood Farm, Fiddington",
    "sg:city":"Bridgwater",
    "sg:classifiers":[
        {
            "category":"Farming",
            "subcategory":"Livestock Farm",
            "type":"Manufacturing & Wholesale Goods"
        },
        {
            "category":"Farming",
            "subcategory":"Farm",
            "type":"Manufacturing & Wholesale Goods"
        }
    ],
    "sg:phone":"+44 1278 652249",
    "sg:postcode":"TA5 1JW",
    "sg:province":"Somerset",
    "sg:tags":[
        "mixed",
        "crop",
        "others"
    ],
    "wof:name":"Robin Pardoe Game Farm",
    "wof:placetype":"venue"
},
  "geometry": {"coordinates":[-3.121454,51.159195],"type":"Point"}
}