{
  "type": "Feature",
  "properties": {
    "iso:country":"GB",
    "sg:address":"90 Warwick Road",
    "sg:city":"Carlisle",
    "sg:classifiers":[
        {
            "category":"Travel",
            "subcategory":"Hotels & Motels",
            "type":"Entertainment"
        }
    ],
    "sg:phone":"+44 1228 529842",
    "sg:postcode":"CA1 1JU",
    "sg:province":"Cumbria",
    "sg:tags":[
        "house",
        "guest"
    ],
    "wof:name":"Howard Lodge Guest House",
    "wof:placetype":"venue"
},
  "geometry": {"coordinates":[-2.92526,54.894299],"type":"Point"}
}