{
  "type": "Feature",
  "properties": {
    "iso:country":"GB",
    "sg:address":"Corner Of St Fagan's & Fairwater, Road, Fairwater",
    "sg:city":"Cardiff",
    "sg:classifiers":[
        {
            "category":"Farming",
            "subcategory":"Nursery",
            "type":"Manufacturing & Wholesale Goods"
        },
        {
            "category":"Place Of Worship",
            "type":"Public Place"
        },
        {
            "category":"Organizations",
            "subcategory":"Non-profit Organization",
            "type":"Services"
        }
    ],
    "sg:phone":"+44 29 2056 1911",
    "sg:postcode":"CF5 3HT",
    "sg:province":"Cardiff",
    "sg:tags":[
        "charitable",
        "organisation",
        "creche",
        "charity"
    ],
    "wof:name":"ST DAVID LUTHERAN CHURCH",
    "wof:placetype":"venue"
},
  "geometry": {"coordinates":[-3.2389199734,51.4902000427],"type":"Point"}
}