{
  "type": "Feature",
  "properties": {
    "addr:full":"Grant Road Crowthorne Berkshire RG45 7JL",
    "addr:postcode":"rg45 7jl",
    "addr:street":"Grant Road",
    "iso:country":"GB",
    "sg:address":"Grant Road",
    "sg:city":"Crowthorne",
    "sg:classifiers":[
        {
            "category":"Community Center",
            "type":"Public Place"
        },
        {
            "category":"Government",
            "subcategory":"Office",
            "type":"Public Place"
        }
    ],
    "sg:phone":"+44 1344 776211",
    "sg:postcode":"RG45 7JL",
    "sg:province":"Berkshire",
    "sg:tags":[
        "recreation",
        "local",
        "leisure",
        "centre"
    ],
    "wof:name":"Edgbarrow & Sandhurst Sports Centre",
    "wof:placetype":"venue"
},
  "geometry": {"coordinates":[-0.7914839983,51.3650932312],"type":"Point"}
}