{
  "type": "Feature",
  "properties": {
    "addr:full":"20 Walpole Gdns, Chiswick London Greater London W4 4HG",
    "addr:housenumber":"20",
    "addr:postcode":"w4 4hg",
    "addr:street":"Walpole Gdns",
    "iso:country":"GB",
    "sg:address":"20 Walpole Gdns, Chiswick",
    "sg:city":"London",
    "sg:classifiers":[
        {
            "category":"Shopping",
            "subcategory":"Pharmacy",
            "type":"Retail Goods"
        }
    ],
    "sg:phone":"+44 20 8994 2025",
    "sg:postcode":"W4 4HG",
    "sg:province":"Greater London",
    "sg:tags":[
        "pharmacist",
        "chemist"
    ],
    "wof:name":"Arlington Park Pharmacy Ltd",
    "wof:placetype":"venue"
},
  "geometry": {"coordinates":[-0.2691220045,51.4910507202],"type":"Point"}
}