{
  "type": "Feature",
  "properties": {
    "addr:full":"Burr Street Luton Bedfordshire LU2 0HN",
    "addr:postcode":"lu2 0hn",
    "addr:street":"Burr Street",
    "iso:country":"GB",
    "sg:address":"Burr Street",
    "sg:city":"Luton",
    "sg:classifiers":[
        {
            "category":"Manufacturing",
            "subcategory":"Lumber",
            "type":"Manufacturing & Wholesale Goods"
        }
    ],
    "sg:phone":"+44 1582 727707",
    "sg:postcode":"LU2 0HN",
    "sg:province":"Bedfordshire",
    "sg:tags":[
        "importer",
        "merchants",
        "agent",
        "timber"
    ],
    "wof:name":"Travis Perkins Trading Co. Ltd.",
    "wof:placetype":"venue"
},
  "geometry": {"coordinates":[-0.411244,51.883354],"type":"Point"}
}