{
  "type": "Feature",
  "properties": {
    "addr:full":"4 Kennard Rise Bristol City of Bristol BS15 8AF",
    "addr:housenumber":"4",
    "addr:postcode":"bs15 8af",
    "addr:street":"Kennard Rise",
    "iso:country":"GB",
    "sg:address":"4 Kennard Rise",
    "sg:city":"Bristol",
    "sg:classifiers":[
        {
            "category":"Building & Trades",
            "subcategory":"Construction",
            "type":"Services"
        }
    ],
    "sg:phone":"+44 117 960 1038",
    "sg:postcode":"BS15 8AF",
    "sg:province":"City of Bristol",
    "sg:tags":[
        "joiner",
        "carpenter"
    ],
    "wof:name":"Christopher Batt",
    "wof:placetype":"venue"
},
  "geometry": {"coordinates":[-2.5184481144,51.4593391418],"type":"Point"}
}