{
  "type": "Feature",
  "properties": {
    "addr:full":"Watts Lane, Bishops Lydeard Taunton Devon TA4 3HR",
    "addr:postcode":"ta4 3hr",
    "addr:street":"Watts Lane",
    "iso:country":"GB",
    "sg:address":"Watts Lane, Bishops Lydeard",
    "sg:city":"Taunton",
    "sg:classifiers":[
        {
            "category":"Arena",
            "subcategory":"Sports Club",
            "type":"Entertainment"
        }
    ],
    "sg:phone":"+44 1823 432112",
    "sg:postcode":"TA4 3HR",
    "sg:province":"Devon",
    "wof:name":"Bishops Lydeard Cricket Club",
    "wof:placetype":"venue"
},
  "geometry": {"coordinates":[-3.1885941029,51.0555038452],"type":"Point"}
}