{
  "type": "Feature",
  "properties": {
    "addr:full":"13 Highweek Street Newton Abbot Devon TQ12 1TG",
    "addr:housenumber":"13",
    "addr:postcode":"tq12 1tg",
    "addr:street":"Highweek Street",
    "iso:country":"GB",
    "sg:address":"13 Highweek Street",
    "sg:city":"Newton Abbot",
    "sg:classifiers":[
        {
            "category":"Shopping",
            "subcategory":"Bicycles & Sporting Goods",
            "type":"Retail Goods"
        }
    ],
    "sg:postcode":"TQ12 1TG",
    "sg:province":"Devon",
    "sg:tags":[
        "riding",
        "saddlery",
        "wear"
    ],
    "wof:name":"Leonard Coombe Saddlers",
    "wof:placetype":"venue"
},
  "geometry": {"coordinates":[-3.6143219471,50.5306625366],"type":"Point"}
}