{
  "type": "Feature",
  "properties": {
    "addr:full":"125 Gloucester Terrace London Greater London W2 6DX",
    "addr:housenumber":"125",
    "addr:postcode":"w2 6dx",
    "addr:street":"Gloucester Terrace",
    "iso:country":"GB",
    "sg:address":"125 Gloucester Terrace",
    "sg:city":"London",
    "sg:classifiers":[
        {
            "category":"Travel",
            "subcategory":"Hotels & Motels",
            "type":"Entertainment"
        }
    ],
    "sg:phone":"+44 20 7262 3161",
    "sg:postcode":"W2 6DX",
    "sg:province":"Greater London",
    "wof:name":"Casserly Court Hotel",
    "wof:placetype":"venue"
},
  "geometry": {"coordinates":[-0.1594180018,51.5210151672],"type":"Point"}
}