{
  "type": "Feature",
  "properties": {
    "addr:full":"2 Hambletonian Yard, High Street Stockton-on-tees Durham TS18 1BT",
    "addr:housenumber":"2",
    "addr:postcode":"ts18 1bt",
    "addr:street":"Hambletonian Yard High Street",
    "iso:country":"GB",
    "sg:address":"2 Hambletonian Yard, High Street",
    "sg:city":"Stockton-on-tees",
    "sg:classifiers":[
        {
            "category":"Home & Garden",
            "subcategory":"Home Furnishings",
            "type":"Retail Goods"
        }
    ],
    "sg:phone":"+44 1642 608130",
    "sg:postcode":"TS18 1BT",
    "sg:province":"Durham",
    "sg:tags":[
        "mantelpiece",
        "fireplace"
    ],
    "wof:name":"Cleveland Fire Grates",
    "wof:placetype":"venue"
},
  "geometry": {"coordinates":[-1.3138840199,54.5633888245],"type":"Point"}
}