{
  "type": "Feature",
  "properties": {
    "addr:full":"Unit C4, Cunliffe Road, Whitebirk Industrial Estate Blackburn Lancashire BB1 5UA",
    "addr:postcode":"bb1 5ua",
    "addr:street":"Cunliffe Road Whitebirk Industrial Estate",
    "iso:country":"GB",
    "sg:address":"Unit C4, Cunliffe Road, Whitebirk Industrial Estate",
    "sg:city":"Blackburn",
    "sg:classifiers":[
        {
            "category":"Manufacturing",
            "subcategory":"Petroleum Products",
            "type":"Manufacturing & Wholesale Goods"
        }
    ],
    "sg:phone":"+44 1254 681436",
    "sg:postcode":"BB1 5UA",
    "sg:province":"Lancashire",
    "sg:tags":[
        "double",
        "glazing"
    ],
    "wof:name":"Visions in Glass Ltd.",
    "wof:placetype":"venue"
},
  "geometry": {"coordinates":[-2.461943,53.769726],"type":"Point"}
}