{
  "type": "Feature",
  "properties": {
    "iso:country":"GB",
    "sg:address":"Broadway Centre",
    "sg:city":"Sunderland",
    "sg:classifiers":[
        {
            "category":"Government",
            "subcategory":"Office",
            "type":"Public Place"
        }
    ],
    "sg:phone":"+44 191 553 5695",
    "sg:postcode":"SR3 4HA",
    "sg:province":"Tyne and Wear",
    "sg:tags":[
        "local"
    ],
    "wof:name":"City of Sunderland Council",
    "wof:placetype":"venue"
},
  "geometry": {"coordinates":[-1.42513,54.888229],"type":"Point"}
}