{
  "type": "Feature",
  "properties": {
    "addr:full":"19 Kidwells Close Maidenhead Berkshire SL6 8AZ",
    "addr:housenumber":"19",
    "addr:postcode":"sl6 8az",
    "addr:street":"Kidwells Close",
    "iso:country":"GB",
    "sg:address":"19 Kidwells Close",
    "sg:city":"Maidenhead",
    "sg:classifiers":[
        {
            "category":"Building & Trades",
            "subcategory":"Construction",
            "type":"Services"
        }
    ],
    "sg:phone":"+44 1628 776739",
    "sg:postcode":"SL6 8AZ",
    "sg:province":"Berkshire",
    "sg:tags":[
        "joinery",
        "joiner",
        "carpenter",
        "carpentry"
    ],
    "wof:name":"James C Doran",
    "wof:placetype":"venue"
},
  "geometry": {"coordinates":[-0.7215149999,51.5254707336],"type":"Point"}
}