{
  "type": "Feature",
  "properties": {
    "addr:full":"11 Lyon Way Trading Estate, Lyon Way Greenford Greater London UB6 0BN",
    "addr:housenumber":"11",
    "addr:postcode":"ub6 0bn",
    "addr:street":"Lyon Way Trading Estate Lyon Way",
    "iso:country":"GB",
    "sg:address":"11 Lyon Way Trading Estate, Lyon Way",
    "sg:city":"Greenford",
    "sg:classifiers":[
        {
            "category":"Retail",
            "subcategory":"Storage",
            "type":"Services"
        }
    ],
    "sg:phone":"+44 20 8813 1951",
    "sg:postcode":"UB6 0BN",
    "sg:province":"Greater London",
    "sg:tags":[
        "household",
        "removal"
    ],
    "wof:name":"B D M",
    "wof:placetype":"venue"
},
  "geometry": {"coordinates":[-0.3399,51.549271],"type":"Point"}
}