{
  "type": "Feature",
  "properties": {
    "addr:full":"1 Old Exchange, 27 Hamble Lane Southampton Hampshire SO31 4JR",
    "addr:housenumber":"1;27",
    "addr:postcode":"so31 4jr",
    "addr:street":"Old;Hamble Lane",
    "iso:country":"GB",
    "sg:address":"1 Old Exchange, 27 Hamble Lane",
    "sg:city":"Southampton",
    "sg:classifiers":[
        {
            "category":"Manufacturing",
            "subcategory":"Building Materials",
            "type":"Manufacturing & Wholesale Goods"
        }
    ],
    "sg:postcode":"SO31 4JR",
    "sg:province":"Hampshire",
    "sg:tags":[
        "flag",
        "banner"
    ],
    "wof:name":"The Old Hamble Exchange Management Co.  Ltd.",
    "wof:placetype":"venue"
},
  "geometry": {"coordinates":[-1.32504,50.860039],"type":"Point"}
}