{
  "type": "Feature",
  "properties": {
    "iso:country":"GB",
    "sg:address":"4 Haydon Road",
    "sg:city":"Watford",
    "sg:classifiers":[
        {
            "category":"Shopping",
            "subcategory":"Pharmacy",
            "type":"Retail Goods"
        }
    ],
    "sg:phone":"+44 1923 235253",
    "sg:postcode":"WD19 4DD",
    "sg:province":"Hertfordshire",
    "sg:tags":[
        "pharmacist",
        "chemist"
    ],
    "wof:name":"Abell Chemists",
    "wof:placetype":"venue"
},
  "geometry": {"coordinates":[-0.378246,51.646423],"type":"Point"}
}