{
  "type": "Feature",
  "properties": {
    "addr:full":"Waterpark House, Green Lane Llantwit Major The Vale of Glamorgan CF61 1YW",
    "addr:postcode":"cf61 1yw",
    "addr:street":"Green Lane",
    "iso:country":"GB",
    "sg:address":"Waterpark House, Green Lane",
    "sg:city":"Llantwit Major",
    "sg:classifiers":[
        {
            "category":"Manufacturing",
            "subcategory":"Glass & Minerals",
            "type":"Manufacturing & Wholesale Goods"
        }
    ],
    "sg:phone":"+44 1446 794649",
    "sg:postcode":"CF61 1YW",
    "sg:province":"The Vale of Glamorgan",
    "sg:tags":[
        "mnfrs",
        "moulding",
        "fibre"
    ],
    "wof:name":"U K Hydroslides Ltd.",
    "wof:placetype":"venue"
},
  "geometry": {"coordinates":[-3.498299,51.407681],"type":"Point"}
}