{
  "type": "Feature",
  "properties": {
    "iso:country":"GB",
    "sg:address":"Pennyfields, Feltham",
    "sg:city":"Bognor Regis",
    "sg:classifiers":[
        {
            "category":"Education",
            "subcategory":"School",
            "type":"Public Place"
        }
    ],
    "sg:postcode":"PO22 6BN",
    "sg:province":"West Sussex",
    "sg:tags":[
        "local",
        "authority"
    ],
    "wof:name":"Bishop Tufnell Junior School",
    "wof:placetype":"venue"
},
  "geometry": {"coordinates":[-0.634163,50.795082],"type":"Point"}
}