{
  "type": "Feature",
  "properties": {
    "iso:country":"GB",
    "sg:address":"15 Bond Street",
    "sg:city":"Redruth",
    "sg:classifiers":[
        {
            "category":"Communications",
            "type":"Services"
        }
    ],
    "sg:postcode":"TR15 2QA",
    "sg:province":"Cornwall",
    "sg:tags":[
        "telecommunication"
    ],
    "wof:name":"Christopher Land",
    "wof:placetype":"venue"
},
  "geometry": {"coordinates":[-5.226444,50.231804],"type":"Point"}
}