{
  "type": "Feature",
  "properties": {
    "addr:full":"41 Hatfield Road St Albans Hertfordshire AL1 4JE",
    "addr:housenumber":"41",
    "addr:postcode":"al1 4je",
    "addr:street":"Hatfield Road",
    "iso:country":"GB",
    "sg:address":"41 Hatfield Road",
    "sg:city":"St Albans",
    "sg:classifiers":[
        {
            "category":"Insurance",
            "subcategory":"Insurance Agent",
            "type":"Services"
        }
    ],
    "sg:phone":"+44 1727 840464",
    "sg:postcode":"AL1 4JE",
    "sg:province":"Hertfordshire",
    "sg:website":"http://www.swinton.co.uk",
    "wof:name":"Swinton",
    "wof:placetype":"venue"
},
  "geometry": {"coordinates":[-0.323128,51.75156],"type":"Point"}
}