{
  "type": "Feature",
  "properties": {
    "iso:country":"GB",
    "sg:address":"37 Bellhouse Road",
    "sg:city":"Sheffield",
    "sg:classifiers":[
        {
            "category":"Food & Beverages",
            "subcategory":"Fruits & Vegetables",
            "type":"Retail Goods"
        }
    ],
    "sg:postcode":"S5 6HJ",
    "sg:province":"South Yorkshire",
    "sg:tags":[
        "greengrocer"
    ],
    "wof:name":"The Orchard",
    "wof:placetype":"venue"
},
  "geometry": {"coordinates":[-1.4471670389,53.4189071655],"type":"Point"}
}