{
  "type": "Feature",
  "properties": {
    "addr:full":"4 Harrington Road, Brinkhill Louth Lincolnshire LN11 8QY",
    "addr:housenumber":"4",
    "addr:postcode":"ln11 8qy",
    "addr:street":"Harrington Road;Louth",
    "iso:country":"GB",
    "sg:address":"4 Harrington Road, Brinkhill",
    "sg:city":"Louth",
    "sg:classifiers":[
        {
            "category":"Social Services",
            "subcategory":"Adult Care",
            "type":"Services"
        }
    ],
    "sg:postcode":"LN11 8QY",
    "sg:province":"Lincolnshire",
    "sg:tags":[
        "domestic",
        "cleaning"
    ],
    "wof:name":"B & C Cleaning Services",
    "wof:placetype":"venue"
},
  "geometry": {"coordinates":[0.054719,53.241966],"type":"Point"}
}