{
  "type": "Feature",
  "properties": {
    "iso:country":"GB",
    "sg:address":"24 Clovelly Rd, Glenfield",
    "sg:city":"Leicester",
    "sg:classifiers":[
        {
            "category":"Building & Trades",
            "subcategory":"Cleaning & Sanitation",
            "type":"Services"
        }
    ],
    "sg:postcode":"LE3 8AA",
    "sg:province":"Leicestershire",
    "sg:tags":[
        "cleaner",
        "window"
    ],
    "wof:name":"Theobold,David,",
    "wof:placetype":"venue"
},
  "geometry": {"coordinates":[-1.189562,52.64904],"type":"Point"}
}