{
  "type": "Feature",
  "properties": {
    "iso:country":"GB",
    "sg:address":"5 Farnborough Drive, Cantley",
    "sg:city":"Doncaster",
    "sg:classifiers":[
        {
            "category":"Building & Trades",
            "subcategory":"Construction",
            "type":"Services"
        }
    ],
    "sg:postcode":"DN4 6PR",
    "sg:province":"South Yorkshire",
    "sg:tags":[
        "glazier",
        "decorator",
        "painter"
    ],
    "wof:name":"Paul Eric King",
    "wof:placetype":"venue"
},
  "geometry": {"coordinates":[-1.062021,53.500229],"type":"Point"}
}