{
  "type": "Feature",
  "properties": {
    "iso:country":"GB",
    "sg:address":"The Coach Station, Lymington Road",
    "sg:city":"Torquay",
    "sg:classifiers":[
        {
            "category":"Shopping",
            "subcategory":"Event Tickets",
            "type":"Retail Goods"
        },
        {
            "category":"Government",
            "subcategory":"Post Office",
            "type":"Public Place"
        }
    ],
    "sg:phone":"+44 1803 329531",
    "sg:postcode":"TQ1 4BD",
    "sg:province":"Devon",
    "sg:tags":[
        "operation",
        "agency"
    ],
    "wof:name":"Connections",
    "wof:placetype":"venue"
},
  "geometry": {"coordinates":[-3.5359499454,50.4738502502],"type":"Point"}
}