{
  "type": "Feature",
  "properties": {
    "iso:country":"GB",
    "sg:address":"The Hall, Bedingfield",
    "sg:city":"Eye",
    "sg:classifiers":[
        {
            "category":"Farming",
            "subcategory":"Farm",
            "type":"Manufacturing & Wholesale Goods"
        }
    ],
    "sg:phone":"+44 1728 628351",
    "sg:postcode":"IP23 7LJ",
    "sg:province":"Suffolk",
    "sg:tags":[
        "mixed",
        "crop"
    ],
    "wof:name":"E P Clarke Farms Ltd",
    "wof:placetype":"venue"
},
  "geometry": {"coordinates":[1.145876,52.322071],"type":"Point"}
}