{
  "type": "Feature",
  "properties": {
    "addr:full":"Office 7 8/10 Glasgow Road, Kirkintilloch Glasgow East Dunbartonshire G66 1SH",
    "addr:housenumber":"8 / 10",
    "addr:postcode":"g66 1sh",
    "addr:street":"Glasgow Road",
    "iso:country":"GB",
    "sg:address":"Office 7 8/10 Glasgow Road, Kirkintilloch",
    "sg:city":"Glasgow",
    "sg:classifiers":[
        {
            "category":"Professional",
            "subcategory":"Business Services",
            "type":"Services"
        }
    ],
    "sg:phone":"+44 141 578 4355",
    "sg:postcode":"G66 1SH",
    "sg:province":"East Dunbartonshire",
    "sg:tags":[
        "shop",
        "cleaning"
    ],
    "wof:name":"Admiral Solutions Ltd.",
    "wof:placetype":"venue"
},
  "geometry": {"coordinates":[-4.1635580063,55.9409675598],"type":"Point"}
}