{
  "type": "Feature",
  "properties": {
    "iso:country":"GB",
    "sg:address":"1a Wellington Way",
    "sg:city":"London",
    "sg:classifiers":[
        {
            "category":"Health Services",
            "subcategory":"Clinic",
            "type":"Services"
        }
    ],
    "sg:phone":"+44 20 8980 3510",
    "sg:postcode":"E3 4NE",
    "sg:province":"Greater London",
    "sg:tags":[
        "nh"
    ],
    "wof:name":"Wellington Way Centre",
    "wof:placetype":"venue"
},
  "geometry": {"coordinates":[-0.025113,51.526104],"type":"Point"}
}