{
  "type": "Feature",
  "properties": {
    "addr:full":"411 Hoe Street London Greater London E17 9AP",
    "addr:housenumber":"411",
    "addr:postcode":"e17 9ap",
    "addr:street":"Hoe Street",
    "iso:country":"GB",
    "sg:address":"411 Hoe Street",
    "sg:city":"London",
    "sg:classifiers":[
        {
            "category":"Restaurant",
            "type":"Food & Drink"
        }
    ],
    "sg:postcode":"E17 9AP",
    "sg:province":"Greater London",
    "wof:name":"Kebabish No 1 Ltd.",
    "wof:placetype":"venue"
},
  "geometry": {"coordinates":[-0.01317,51.575737],"type":"Point"}
}