{
  "type": "Feature",
  "properties": {
    "iso:country":"GB",
    "sg:address":"14 High St",
    "sg:city":"Melksham",
    "sg:classifiers":[
        {
            "category":"Shopping",
            "subcategory":"Discount & Variety Stores",
            "type":"Retail Goods"
        }
    ],
    "sg:phone":"+44 1225 793259",
    "sg:postcode":"SN12 6JU",
    "sg:province":"Wiltshire",
    "sg:tags":[
        "centre"
    ],
    "wof:name":"Discount House",
    "wof:placetype":"venue"
},
  "geometry": {"coordinates":[-2.138142,51.37265],"type":"Point"}
}