{
  "type": "Feature",
  "properties": {
    "addr:full":"A3 Liphook By-pass Liphook Hampshire GU30 7TT",
    "addr:postcode":"gu30 7tt",
    "addr:street":"Liphook By-Pass",
    "iso:country":"GB",
    "sg:address":"A3 Liphook By-pass",
    "sg:city":"Liphook",
    "sg:classifiers":[
        {
            "category":"Restaurant",
            "type":"Food & Drink"
        }
    ],
    "sg:phone":"+44 1428 727450",
    "sg:postcode":"GU30 7TT",
    "sg:province":"Hampshire",
    "wof:name":"Little Chef",
    "wof:placetype":"venue"
},
  "geometry": {"coordinates":[-0.7695900202,51.0924301147],"type":"Point"}
}