{
  "type": "Feature",
  "properties": {
    "iso:country":"GB",
    "sg:address":"48 Stawberry Fields, Hedgend",
    "sg:city":"Southampton",
    "sg:classifiers":[
        {
            "category":"Education",
            "subcategory":"College",
            "type":"Public Place"
        }
    ],
    "sg:phone":"+44 1489 795995",
    "sg:postcode":"SO30 4QY",
    "sg:province":"Hampshire",
    "sg:tags":[
        "technical",
        "agricultural"
    ],
    "wof:name":"The English Rose Beauty School",
    "wof:placetype":"venue"
},
  "geometry": {"coordinates":[-1.316689,50.910629],"type":"Point"}
}