{
  "type": "Feature",
  "properties": {
    "iso:country":"GB",
    "sg:address":"Smallshaw Indust Est, Accrington Rd",
    "sg:city":"Burnley",
    "sg:classifiers":[
        {
            "category":"Manufacturing",
            "subcategory":"Rubber & Plastics",
            "type":"Manufacturing & Wholesale Goods"
        }
    ],
    "sg:phone":"+44 1282 839099",
    "sg:postcode":"BB11 5SX",
    "sg:province":"Lancashire",
    "sg:tags":[
        "injection",
        "moulding"
    ],
    "wof:name":"Smallshaw Precision Plastics",
    "wof:placetype":"venue"
},
  "geometry": {"coordinates":[-2.243809,53.78801],"type":"Point"}
}