{
  "type": "Feature",
  "properties": {
    "iso:country":"GB",
    "sg:address":"27 Salcombe Rd",
    "sg:city":"Ashford",
    "sg:classifiers":[
        {
            "category":"Professional",
            "subcategory":"Art Services",
            "type":"Services"
        }
    ],
    "sg:phone":"+44 1784 240637",
    "sg:postcode":"TW15 3BS",
    "sg:province":"Greater London",
    "sg:tags":[
        "graphic",
        "designer"
    ],
    "wof:name":"Gray Graphiques",
    "wof:placetype":"venue"
},
  "geometry": {"coordinates":[-0.474251,51.437984],"type":"Point"}
}