{
  "type": "Feature",
  "properties": {
    "addr:full":"Harcourt Sands Ryde Isle of Wight PO33 1PJ",
    "addr:postcode":"po33 1pj",
    "addr:street":"Harcourt",
    "iso:country":"GB",
    "sg:address":"Harcourt Sands",
    "sg:city":"Ryde",
    "sg:classifiers":[
        {
            "category":"Recreation",
            "subcategory":"Campground",
            "type":"Entertainment"
        }
    ],
    "sg:phone":"+44 1983 567321",
    "sg:postcode":"PO33 1PJ",
    "sg:province":"Isle of Wight",
    "sg:tags":[
        "holiday",
        "centre",
        "camp"
    ],
    "wof:name":"Harcourt Sands Holiday Village",
    "wof:placetype":"venue"
},
  "geometry": {"coordinates":[-1.168666,50.727566],"type":"Point"}
}