{
  "type": "Feature",
  "properties": {
    "iso:country":"GB",
    "sg:address":"Cheethams House, 96 Market Street",
    "sg:city":"Stalybridge",
    "sg:classifiers":[
        {
            "category":"Real Estate",
            "subcategory":"Developer",
            "type":"Services"
        }
    ],
    "sg:phone":"+44 161 338 2568",
    "sg:postcode":"SK15 2AB",
    "sg:province":"Greater Manchester",
    "sg:tags":[
        "property"
    ],
    "wof:name":"Staley Properties Investment Ltd.",
    "wof:placetype":"venue"
},
  "geometry": {"coordinates":[-2.056947,53.4841],"type":"Point"}
}