{
  "type": "Feature",
  "properties": {
    "iso:country":"GB",
    "sg:address":"20 Woodland Park",
    "sg:city":"Paignton",
    "sg:classifiers":[
        {
            "category":"Professional",
            "subcategory":"Printing & Photocopies",
            "type":"Services"
        }
    ],
    "sg:postcode":"TQ3 2ST",
    "sg:province":"Devon",
    "sg:tags":[
        "printer"
    ],
    "wof:name":"Tozer & Co. (Printers) Ltd.",
    "wof:placetype":"venue"
},
  "geometry": {"coordinates":[-3.569985,50.440056],"type":"Point"}
}