{
  "type": "Feature",
  "properties": {
    "iso:country":"GB",
    "sg:address":"Unit 11 Parnall Road Industrial Estate, Fishponds",
    "sg:city":"Bristol",
    "sg:classifiers":[
        {
            "category":"Retail",
            "subcategory":"Auto Repair",
            "type":"Services"
        }
    ],
    "sg:postcode":"BS16 3JQ",
    "sg:province":"City of Bristol",
    "sg:tags":[
        "garage",
        "mechanic"
    ],
    "wof:name":"Safety Micron Systems U K Ltd.",
    "wof:placetype":"venue"
},
  "geometry": {"coordinates":[-2.5332989693,51.476348877],"type":"Point"}
}