{
  "type": "Feature",
  "properties": {
    "addr:full":"Cunard Ho, 15 Regent St Westminster Greater London SW1Y 4LR",
    "addr:housenumber":"15",
    "addr:postcode":"sw1y 4lr",
    "addr:street":"Regent St",
    "iso:country":"GB",
    "sg:address":"Cunard Ho, 15 Regent St",
    "sg:city":"Westminster",
    "sg:classifiers":[
        {
            "category":"Professional",
            "subcategory":"Management & Consulting",
            "type":"Services"
        }
    ],
    "sg:phone":"+44 20 7389 6505",
    "sg:postcode":"SW1Y 4LR",
    "sg:province":"Greater London",
    "sg:tags":[
        "consultant",
        "business"
    ],
    "wof:name":"Risk Solutions",
    "wof:placetype":"venue"
},
  "geometry": {"coordinates":[-0.13394,51.508629],"type":"Point"}
}