{
  "type": "Feature",
  "properties": {
    "iso:country":"GB",
    "sg:address":"St. Dominic Sq",
    "sg:city":"King's Lynn",
    "sg:classifiers":[
        {
            "category":"Shopping",
            "subcategory":"Gifts & Souvenirs",
            "type":"Retail Goods"
        }
    ],
    "sg:phone":"+44 1553 764655",
    "sg:postcode":"PE30 1DT",
    "sg:province":"Norfolk",
    "sg:tags":[
        "poster",
        "card"
    ],
    "wof:name":"Just Cards And",
    "wof:placetype":"venue"
},
  "geometry": {"coordinates":[0.3983800113,52.7542304993],"type":"Point"}
}