{
  "type": "Feature",
  "properties": {
    "iso:country":"GB",
    "sg:address":"57 Afton Bridgend, New Cumnock",
    "sg:city":"Cumnock",
    "sg:classifiers":[
        {
            "category":"Food & Beverages",
            "subcategory":"Groceries & Convenience Stores",
            "type":"Retail Goods"
        }
    ],
    "sg:phone":"+44 1290 338224",
    "sg:postcode":"KA18 4BA",
    "sg:province":"East Ayrshire",
    "wof:name":"D & M Edgar",
    "wof:placetype":"venue"
},
  "geometry": {"coordinates":[-4.1795711517,55.393535614],"type":"Point"}
}