{
  "type": "Feature",
  "properties": {
    "iso:country":"GB",
    "sg:address":"17 Southfields Drive",
    "sg:city":"Peterborough",
    "sg:classifiers":[
        {
            "category":"Professional",
            "type":"Services"
        }
    ],
    "sg:postcode":"PE2 8QA",
    "sg:province":"Cambridgeshire",
    "sg:tags":[
        "caterer"
    ],
    "wof:name":"Regency Catering Ltd.",
    "wof:placetype":"venue"
},
  "geometry": {"coordinates":[-0.219004,52.555614],"type":"Point"}
}