{
  "type": "Feature",
  "properties": {
    "addr:full":"27-33 Brander Street Leeds West Yorkshire LS9 6QH",
    "addr:housenumber":"27-33",
    "addr:postcode":"ls9 6qh",
    "addr:street":"Brander Street",
    "iso:country":"GB",
    "sg:address":"27-33 Brander Street",
    "sg:city":"Leeds",
    "sg:classifiers":[
        {
            "category":"Health Services",
            "subcategory":"Nursing And Care Facility",
            "type":"Services"
        },
        {
            "category":"Organizations",
            "subcategory":"Non-profit Organization",
            "type":"Services"
        }
    ],
    "sg:phone":"+44 113 248 1301",
    "sg:postcode":"LS9 6QH",
    "sg:province":"West Yorkshire",
    "sg:tags":[
        "charitable",
        "organisation",
        "charity",
        "home"
    ],
    "wof:name":"Gipton Supported Independent Living Ltd",
    "wof:placetype":"venue"
},
  "geometry": {"coordinates":[-1.491418,53.806374],"type":"Point"}
}