{
  "type": "Feature",
  "properties": {
    "addr:full":"Rossendale Street London Greater London E5 8TA",
    "addr:postcode":"e5 8ta",
    "addr:street":"Rossendale Street",
    "iso:country":"GB",
    "sg:address":"Rossendale Street",
    "sg:city":"London",
    "sg:classifiers":[
        {
            "category":"Place Of Worship",
            "type":"Public Place"
        }
    ],
    "sg:phone":"+44 20 8806 0346",
    "sg:postcode":"E5 8TA",
    "sg:province":"Greater London",
    "wof:name":"United Pentecostal Church of God",
    "wof:placetype":"venue"
},
  "geometry": {"coordinates":[-0.060099,51.563229],"type":"Point"}
}