{
  "type": "Feature",
  "properties": {
    "addr:full":"66-70 Holmethorpe Avenue Redhill Surrey RH1 2NL",
    "addr:housenumber":"66-70",
    "addr:postcode":"rh1 2nl",
    "addr:street":"Holmethorpe Avenue",
    "iso:country":"GB",
    "sg:address":"66-70 Holmethorpe Avenue",
    "sg:city":"Redhill",
    "sg:classifiers":[
        {
            "category":"Shopping",
            "subcategory":"Music",
            "type":"Retail Goods"
        }
    ],
    "sg:phone":"+44 1737 767171",
    "sg:postcode":"RH1 2NL",
    "sg:province":"Surrey",
    "sg:tags":[
        "record",
        "tape",
        "cd"
    ],
    "wof:name":"Zonal Ltd.",
    "wof:placetype":"venue"
},
  "geometry": {"coordinates":[-0.157058,51.250355],"type":"Point"}
}