{
  "type": "Feature",
  "properties": {
    "addr:full":"1650 Great Western Road Glasgow Glasgow City G13 1HH",
    "addr:housenumber":"1650",
    "addr:postcode":"g13 1hh",
    "addr:street":"Great Western Road",
    "iso:country":"GB",
    "sg:address":"1650 Great Western Road",
    "sg:city":"Glasgow",
    "sg:classifiers":[
        {
            "category":"Health Services",
            "subcategory":"Optometrist",
            "type":"Services"
        }
    ],
    "sg:phone":"+44 141 959 3175",
    "sg:postcode":"G13 1HH",
    "sg:province":"Glasgow City",
    "sg:tags":[
        "optician"
    ],
    "wof:name":"C Jeffrey Black (Opticians)",
    "wof:placetype":"venue"
},
  "geometry": {"coordinates":[-4.324901104,55.8902511597],"type":"Point"}
}