{
  "type": "Feature",
  "properties": {
    "addr:full":"17 Brixworth Rd, Spratton Northampton Northamptonshire NN6 8HH",
    "addr:housenumber":"17",
    "addr:postcode":"nn6 8hh",
    "addr:street":"Brixworth Rd",
    "iso:country":"GB",
    "sg:address":"17 Brixworth Rd, Spratton",
    "sg:city":"Northampton",
    "sg:classifiers":[
        {
            "category":"Personal",
            "subcategory":"Beauty Salon",
            "type":"Services"
        },
        {
            "category":"Personal",
            "subcategory":"Barber",
            "type":"Services"
        }
    ],
    "sg:phone":"+44 1604 847260",
    "sg:postcode":"NN6 8HH",
    "sg:province":"Northamptonshire",
    "sg:tags":[
        "unisex",
        "hairdresser"
    ],
    "wof:name":"Dawn Mallard",
    "wof:placetype":"venue"
},
  "geometry": {"coordinates":[-0.949475,52.324757],"type":"Point"}
}