{
  "type": "Feature",
  "properties": {
    "addr:full":"The Health Centre, 57 Oliver St, Ampthill Bedford Bedfordshire MK45 2SB",
    "addr:housenumber":"57",
    "addr:postcode":"mk45 2sb",
    "addr:street":"Oliver St",
    "iso:country":"GB",
    "sg:address":"The Health Centre, 57 Oliver St, Ampthill",
    "sg:city":"Bedford",
    "sg:classifiers":[
        {
            "category":"Health Services",
            "subcategory":"Doctor",
            "type":"Services"
        }
    ],
    "sg:phone":"+44 1525 402641",
    "sg:postcode":"MK45 2SB",
    "sg:province":"Bedfordshire",
    "sg:tags":[
        "practitioners"
    ],
    "wof:name":"Drs Aylward Scott Hopper Haslett & Allingham",
    "wof:placetype":"venue"
},
  "geometry": {"coordinates":[-0.4949940145,52.0279464722],"type":"Point"}
}