{
  "type": "Feature",
  "properties": {
    "addr:full":"A112-115 Riverside Business Ctre, Bendon Valley London Greater London SW18 4ND",
    "addr:postcode":"sw18 4nd",
    "addr:street":"Bendon Valley",
    "iso:country":"GB",
    "sg:address":"A112-115 Riverside Business Ctre, Bendon Valley",
    "sg:city":"London",
    "sg:classifiers":[
        {
            "category":"Shopping",
            "subcategory":"Pharmacy",
            "type":"Retail Goods"
        }
    ],
    "sg:phone":"+44 1628 850100",
    "sg:postcode":"SW18 4ND",
    "sg:province":"Greater London",
    "sg:tags":[
        "medical"
    ],
    "wof:name":"Neurosurgical Pattie Co. Ltd.",
    "wof:placetype":"venue"
},
  "geometry": {"coordinates":[-0.1927099973,51.4473304749],"type":"Point"}
}