{
  "type": "Feature",
  "properties": {
    "addr:full":"4 Tamar Grn Hemel Hempstead Hertfordshire HP2 6EP",
    "addr:housenumber":"4",
    "addr:postcode":"hp2 6ep",
    "addr:street":"Tamar Grn;Hempstead",
    "iso:country":"GB",
    "sg:address":"4 Tamar Grn",
    "sg:city":"Hemel Hempstead",
    "sg:classifiers":[
        {
            "category":"Taxi",
            "type":"Transportation"
        },
        {
            "category":"Bus Charters",
            "type":"Transportation"
        }
    ],
    "sg:postcode":"HP2 6EP",
    "sg:province":"Hertfordshire",
    "sg:tags":[
        "mini",
        "hire",
        "leasing",
        "cab"
    ],
    "wof:name":"Chancers Private Hire",
    "wof:placetype":"venue"
},
  "geometry": {"coordinates":[-0.4520849884,51.7761116028],"type":"Point"}
}