{
  "type": "Feature",
  "properties": {
    "addr:full":"41 King Street Belper Derbyshire DE56 1PX",
    "addr:housenumber":"41",
    "addr:postcode":"de56 1px",
    "addr:street":"King Street",
    "iso:country":"GB",
    "sg:address":"41 King Street",
    "sg:city":"Belper",
    "sg:classifiers":[
        {
            "category":"Shopping",
            "subcategory":"Clothing, Apparel, & Fashions",
            "type":"Retail Goods"
        }
    ],
    "sg:phone":"+44 1773 880506",
    "sg:postcode":"DE56 1PX",
    "sg:province":"Derbyshire",
    "sg:tags":[
        "shop"
    ],
    "wof:name":"New Look",
    "wof:placetype":"venue"
},
  "geometry": {"coordinates":[-1.4814829826,53.0233688354],"type":"Point"}
}