{
  "type": "Feature",
  "properties": {
    "iso:country":"GB",
    "sg:address":"Stores Road",
    "sg:city":"Derby",
    "sg:classifiers":[
        {
            "category":"Professional",
            "subcategory":"Engineering",
            "type":"Services"
        }
    ],
    "sg:postcode":"DE21 4BH",
    "sg:province":"Derbyshire",
    "sg:tags":[
        "engineer",
        "mechanical"
    ],
    "wof:name":"McDonald Engineering Ltd.",
    "wof:placetype":"venue"
},
  "geometry": {"coordinates":[-1.4664510489,52.9302444458],"type":"Point"}
}