{
  "type": "Feature",
  "properties": {
    "iso:country":"GB",
    "sg:address":"17 High St",
    "sg:city":"Maybole",
    "sg:classifiers":[
        {
            "category":"Professional",
            "subcategory":"Lawyer & Legal Services",
            "type":"Services"
        }
    ],
    "sg:phone":"+44 1655 884488",
    "sg:postcode":"KA19 7AB",
    "sg:province":"East Ayrshire",
    "sg:tags":[
        "solicitor"
    ],
    "wof:name":"Howat Associates",
    "wof:placetype":"venue"
},
  "geometry": {"coordinates":[-4.6812257767,55.3543968201],"type":"Point"}
}