{
  "type": "Feature",
  "properties": {
    "addr:full":"185 Upper Grosvenor Rd Tunbridge Wells Kent TN1 2EF",
    "addr:housenumber":"185",
    "addr:postcode":"tn1 2ef",
    "addr:street":"Upper Grosvenor Rd",
    "iso:country":"GB",
    "sg:address":"185 Upper Grosvenor Rd",
    "sg:city":"Tunbridge Wells",
    "sg:classifiers":[
        {
            "category":"Banks & Credit Unions",
            "subcategory":"Financial Services",
            "type":"Services"
        }
    ],
    "sg:phone":"+44 1892 546299",
    "sg:postcode":"TN1 2EF",
    "sg:province":"Kent",
    "sg:tags":[
        "adviser"
    ],
    "wof:name":"Maher & Co",
    "wof:placetype":"venue"
},
  "geometry": {"coordinates":[0.2716369927,51.1440696716],"type":"Point"}
}