{
  "type": "Feature",
  "properties": {
    "addr:full":"120 Kent Road Southampton Hampshire SO17 2LG",
    "addr:housenumber":"120",
    "addr:postcode":"so17 2lg",
    "addr:street":"Kent Road",
    "iso:country":"GB",
    "sg:address":"120 Kent Road",
    "sg:city":"Southampton",
    "sg:classifiers":[
        {
            "category":"Building & Trades",
            "subcategory":"Construction",
            "type":"Services"
        }
    ],
    "sg:postcode":"SO17 2LG",
    "sg:province":"Hampshire",
    "sg:tags":[
        "joiner",
        "carpenter"
    ],
    "wof:name":"A Moss",
    "wof:placetype":"venue"
},
  "geometry": {"coordinates":[-1.383636,50.928699],"type":"Point"}
}