{
  "type": "Feature",
  "properties": {
    "addr:full":"11-17 Highclere Road, Knaphill Woking Surrey GU21 2PN",
    "addr:housenumber":"11-17",
    "addr:postcode":"gu21 2pn",
    "addr:street":"Highclere Road",
    "iso:country":"GB",
    "sg:address":"11-17 Highclere Road, Knaphill",
    "sg:city":"Woking",
    "sg:classifiers":[
        {
            "category":"Retail",
            "subcategory":"Storage",
            "type":"Services"
        }
    ],
    "sg:phone":"+44 1483 797282",
    "sg:postcode":"GU21 2PN",
    "sg:province":"Surrey",
    "sg:tags":[
        "household",
        "removal"
    ],
    "wof:name":"G Chamberlain (Haulage & Removals) Ltd.",
    "wof:placetype":"venue"
},
  "geometry": {"coordinates":[-0.619057,51.318371],"type":"Point"}
}