{
  "type": "Feature",
  "properties": {
    "addr:full":"8 Brook Street Tonbridge Kent TN9 2PJ",
    "addr:housenumber":"8",
    "addr:postcode":"tn9 2pj",
    "addr:street":"Brook Street",
    "iso:country":"GB",
    "sg:address":"8 Brook Street",
    "sg:city":"Tonbridge",
    "sg:classifiers":[
        {
            "category":"Farming",
            "subcategory":"Nursery",
            "type":"Manufacturing & Wholesale Goods"
        },
        {
            "category":"Education",
            "subcategory":"Preschool",
            "type":"Public Place"
        }
    ],
    "sg:phone":"+44 1732 364344",
    "sg:postcode":"TN9 2PJ",
    "sg:province":"Kent",
    "sg:tags":[
        "school",
        "creche"
    ],
    "wof:name":"Oaklands Day Nursery",
    "wof:placetype":"venue"
},
  "geometry": {"coordinates":[0.2637540102,51.1877250671],"type":"Point"}
}