{
  "type": "Feature",
  "properties": {
    "addr:full":"536 Lordship La Wood Green Greater London N22 5BY",
    "addr:housenumber":"536",
    "addr:postcode":"n22 5by",
    "addr:street":"Lordship La Wood Green",
    "iso:country":"GB",
    "sg:address":"536 Lordship La",
    "sg:city":"Wood Green",
    "sg:classifiers":[
        {
            "category":"Retail",
            "subcategory":"Laundry & Dry Cleaning",
            "type":"Services"
        }
    ],
    "sg:phone":"+44 20 8889 1387",
    "sg:postcode":"N22 5BY",
    "sg:province":"Greater London",
    "sg:tags":[
        "alteration"
    ],
    "wof:name":"Pauls Dry Cleaners",
    "wof:placetype":"venue"
},
  "geometry": {"coordinates":[-0.096076,51.598534],"type":"Point"}
}