{
  "type": "Feature",
  "properties": {
    "addr:full":"Timpson Road, Baguley Manchester Cheshire M23 9NT",
    "addr:postcode":"m23 9nt",
    "addr:street":"Timpson Road",
    "iso:country":"GB",
    "sg:address":"Timpson Road, Baguley",
    "sg:city":"Manchester",
    "sg:classifiers":[
        {
            "category":"Arena",
            "subcategory":"Sports Club",
            "type":"Entertainment"
        }
    ],
    "sg:phone":"+44 161 998 5076",
    "sg:postcode":"M23 9NT",
    "sg:province":"Cheshire",
    "wof:name":"Wythenshawe Town Football Club",
    "wof:placetype":"venue"
},
  "geometry": {"coordinates":[-2.2949249744,53.3997154236],"type":"Point"}
}