{
  "type": "Feature",
  "properties": {
    "addr:full":"Beech Tree Farm, Main Street, Cantley Doncaster South Yorkshire DN3 3QH",
    "addr:postcode":"dn3 3qh",
    "addr:street":"Beech;Main Street",
    "iso:country":"GB",
    "sg:address":"Beech Tree Farm, Main Street, Cantley",
    "sg:city":"Doncaster",
    "sg:classifiers":[
        {
            "category":"Farming",
            "subcategory":"Livestock Farm",
            "type":"Manufacturing & Wholesale Goods"
        }
    ],
    "sg:phone":"+44 1302 536276",
    "sg:postcode":"DN3 3QH",
    "sg:province":"South Yorkshire",
    "sg:tags":[
        "stud"
    ],
    "wof:name":"G A Read",
    "wof:placetype":"venue"
},
  "geometry": {"coordinates":[-1.0549689531,53.5126686096],"type":"Point"}
}