{
  "type": "Feature",
  "properties": {
    "addr:full":"26 Forest St, Shepshed Loughborough Leicestershire LE12 9DA",
    "addr:housenumber":"26",
    "addr:postcode":"le12 9da",
    "addr:street":"Forest St",
    "iso:country":"GB",
    "sg:address":"26 Forest St, Shepshed",
    "sg:city":"Loughborough",
    "sg:classifiers":[
        {
            "category":"Communications",
            "subcategory":"Film & Video Production",
            "type":"Services"
        }
    ],
    "sg:phone":"+44 1509 600616",
    "sg:postcode":"LE12 9DA",
    "sg:province":"Leicestershire",
    "sg:tags":[
        "illustrator",
        "artist"
    ],
    "wof:name":"Bill Tidy",
    "wof:placetype":"venue"
},
  "geometry": {"coordinates":[-1.2854700089,52.772644043],"type":"Point"}
}