{
  "type": "Feature",
  "properties": {
    "addr:full":"Studio 3, 81 Vyse Street, Hockley Birmingham West Midlands B18 6HA",
    "addr:housenumber":"81",
    "addr:postcode":"b18 6ha",
    "addr:street":"Vyse Street",
    "iso:country":"GB",
    "sg:address":"Studio 3, 81 Vyse Street, Hockley",
    "sg:city":"Birmingham",
    "sg:classifiers":[
        {
            "category":"Shopping",
            "subcategory":"Jewelry",
            "type":"Retail Goods"
        }
    ],
    "sg:phone":"+44 121 523 5694",
    "sg:postcode":"B18 6HA",
    "sg:province":"West Midlands",
    "sg:tags":[
        "gold",
        "silversmith"
    ],
    "wof:name":"Sharon McSwiney",
    "wof:placetype":"venue"
},
  "geometry": {"coordinates":[-1.9123500586,52.4904289246],"type":"Point"}
}