{
  "type": "Feature",
  "properties": {
    "addr:full":"Devon Court Liverpool Merseyside L5 4TR",
    "addr:postcode":"l5 4tr",
    "addr:street":"Devon Court",
    "iso:country":"GB",
    "sg:address":"Devon Court",
    "sg:city":"Liverpool",
    "sg:classifiers":[
        {
            "category":"Social Services",
            "subcategory":"Adult Care",
            "type":"Services"
        }
    ],
    "sg:phone":"+44 151 260 4348",
    "sg:postcode":"L5 4TR",
    "sg:province":"Merseyside",
    "sg:tags":[
        "housing",
        "sheltered"
    ],
    "wof:name":"Grouped Accommodation for the Elderly",
    "wof:placetype":"venue"
},
  "geometry": {"coordinates":[-2.9622569084,53.4230422974],"type":"Point"}
}