{
  "type": "Feature",
  "properties": {
    "addr:full":"17 Carlisle St West End Hampshire W1V 5RE",
    "addr:housenumber":"17",
    "addr:postcode":"w1v 5re",
    "addr:street":"Carlisle St",
    "iso:country":"GB",
    "sg:address":"17 Carlisle St",
    "sg:city":"West End",
    "sg:classifiers":[
        {
            "category":"Professional",
            "subcategory":"Management & Consulting",
            "type":"Services"
        }
    ],
    "sg:phone":"+44 20 7313 5575",
    "sg:postcode":"W1V 5RE",
    "sg:province":"Hampshire",
    "sg:tags":[
        "marketing",
        "consultant"
    ],
    "wof:name":"Wrightson Dale",
    "wof:placetype":"venue"
},
  "geometry": {"coordinates":[-0.1336819977,51.5150337219],"type":"Point"}
}