{
  "type": "Feature",
  "properties": {
    "addr:full":"45 Hornsey Rd Holloway Greater London N7 7DD",
    "addr:housenumber":"45",
    "addr:postcode":"n7 7dd",
    "addr:street":"Hornsey Rd",
    "iso:country":"GB",
    "sg:address":"45 Hornsey Rd",
    "sg:city":"Holloway",
    "sg:classifiers":[
        {
            "category":"Retail",
            "subcategory":"Auto Repair",
            "type":"Services"
        }
    ],
    "sg:phone":"+44 20 7607 8199",
    "sg:postcode":"N7 7DD",
    "sg:province":"Greater London",
    "sg:tags":[
        "modification",
        "garage"
    ],
    "wof:name":"Davis Motors",
    "wof:placetype":"venue"
},
  "geometry": {"coordinates":[-0.110826,51.554043],"type":"Point"}
}