{
  "type": "Feature",
  "properties": {
    "iso:country":"GB",
    "sg:address":"8 Wantz Road",
    "sg:city":"Maldon",
    "sg:classifiers":[
        {
            "category":"Retail",
            "subcategory":"Veterinary Services",
            "type":"Services"
        }
    ],
    "sg:phone":"+44 1621 852910",
    "sg:postcode":"CM9 5DE",
    "sg:province":"Essex",
    "sg:tags":[
        "surgeon"
    ],
    "wof:name":"The Edgewood Veterinary Group",
    "wof:placetype":"venue"
},
  "geometry": {"coordinates":[0.681776,51.729912],"type":"Point"}
}