{
  "type": "Feature",
  "properties": {
    "addr:full":"1st Floor Suite, 24/26 Maid Marian Way Nottingham Nottinghamshire NG1 6JS",
    "addr:housenumber":"suite 24 / 26",
    "addr:postcode":"ng1 6js",
    "addr:street":"Maid Marian Way",
    "iso:country":"GB",
    "sg:address":"1st Floor Suite, 24/26 Maid Marian Way",
    "sg:city":"Nottingham",
    "sg:classifiers":[
        {
            "category":"Home & Garden",
            "subcategory":"Furniture",
            "type":"Retail Goods"
        }
    ],
    "sg:phone":"+44 1155 08966",
    "sg:postcode":"NG1 6JS",
    "sg:province":"Nottinghamshire",
    "wof:name":"Exclusive Furnishings",
    "wof:placetype":"venue"
},
  "geometry": {"coordinates":[-1.1535409689,52.9524612427],"type":"Point"}
}