{
  "type": "Feature",
  "properties": {
    "addr:full":"5 Queensland Road London Greater London N7 7AH",
    "addr:housenumber":"5",
    "addr:postcode":"n7 7ah",
    "addr:street":"Queensland Road",
    "iso:country":"GB",
    "sg:address":"5 Queensland Road",
    "sg:city":"London",
    "sg:classifiers":[
        {
            "category":"Cafe",
            "type":"Food & Drink"
        }
    ],
    "sg:postcode":"N7 7AH",
    "sg:province":"Greater London",
    "sg:tags":[
        "tea",
        "room"
    ],
    "wof:name":"Mary's Kitchen",
    "wof:placetype":"venue"
},
  "geometry": {"coordinates":[-0.108814,51.553684],"type":"Point"}
}