{
  "type": "Feature",
  "properties": {
    "iso:country":"GB",
    "sg:address":"36 Holbrook Road",
    "sg:city":"Belper",
    "sg:classifiers":[
        {
            "category":"Retail",
            "subcategory":"Repair Shop",
            "type":"Services"
        }
    ],
    "sg:phone":"+44 1773 823991",
    "sg:postcode":"DE56 1PA",
    "sg:province":"Derbyshire",
    "sg:tags":[
        "radio",
        "television",
        "video"
    ],
    "wof:name":"Trade Services (Belper) Ltd.",
    "wof:placetype":"venue"
},
  "geometry": {"coordinates":[-1.4806189537,53.0155792236],"type":"Point"}
}