{
  "type": "Feature",
  "properties": {
    "addr:full":"Bradford & Bingley House Stourport-on-severn Worcestershire DY13 8BE",
    "addr:postcode":"dy13 8be",
    "iso:country":"GB",
    "sg:address":"Bradford & Bingley House",
    "sg:city":"Stourport-on-severn",
    "sg:classifiers":[
        {
            "category":"Banks & Credit Unions",
            "subcategory":"Financial Services",
            "type":"Services"
        }
    ],
    "sg:phone":"+44 1299 878542",
    "sg:postcode":"DY13 8BE",
    "sg:province":"Worcestershire",
    "sg:tags":[
        "building",
        "society",
        "pension",
        "consultant"
    ],
    "wof:name":"Bradford & Bingley Plc",
    "wof:placetype":"venue"
},
  "geometry": {"coordinates":[-2.28038,52.339298],"type":"Point"}
}