{
  "type": "Feature",
  "properties": {
    "addr:full":"334 Allerton Shopping Centre, Allerton Rd, Allerton Bradford West Yorkshire BD15 7BN",
    "addr:housenumber":"334;shopping",
    "addr:postcode":"bd15 7bn",
    "addr:street":"Allerton;Allerton Rd",
    "iso:country":"GB",
    "sg:address":"334 Allerton Shopping Centre, Allerton Rd, Allerton",
    "sg:city":"Bradford",
    "sg:classifiers":[
        {
            "category":"Restaurant",
            "type":"Food & Drink"
        }
    ],
    "sg:phone":"+44 1274 493673",
    "sg:postcode":"BD15 7BN",
    "sg:province":"West Yorkshire",
    "sg:tags":[
        "indian"
    ],
    "wof:name":"Shehzad Tandoori Restaurant",
    "wof:placetype":"venue"
},
  "geometry": {"coordinates":[-1.8219419718,53.8053970337],"type":"Point"}
}