{
  "type": "Feature",
  "properties": {
    "addr:full":"Paisley Arts Centre, New Street Paisley Renfrewshire PA1 1EZ",
    "addr:postcode":"pa1 1ez",
    "addr:street":"New Street",
    "iso:country":"GB",
    "sg:address":"Paisley Arts Centre, New Street",
    "sg:city":"Paisley",
    "sg:classifiers":[
        {
            "category":"Arts & Performance",
            "subcategory":"Arts Center",
            "type":"Entertainment"
        },
        {
            "category":"Government",
            "subcategory":"Office",
            "type":"Public Place"
        }
    ],
    "sg:phone":"+44 141 887 1010",
    "sg:postcode":"PA1 1EZ",
    "sg:province":"Renfrewshire",
    "sg:tags":[
        "local",
        "centre"
    ],
    "wof:name":"Paisley Arts Centre",
    "wof:placetype":"venue"
},
  "geometry": {"coordinates":[-4.4243922234,55.8435821533],"type":"Point"}
}