{
  "type": "Feature",
  "properties": {
    "addr:full":"Thompson House, 296 Farnborough Road Farnborough Hampshire GU14 7NU",
    "addr:housenumber":"296",
    "addr:postcode":"gu14 7nu",
    "addr:street":"Farnborough Road",
    "iso:country":"GB",
    "sg:address":"Thompson House, 296 Farnborough Road",
    "sg:city":"Farnborough",
    "sg:classifiers":[
        {
            "category":"Building & Trades",
            "subcategory":"Construction",
            "type":"Services"
        }
    ],
    "sg:phone":"+44 1252 893900",
    "sg:postcode":"GU14 7NU",
    "sg:province":"Hampshire",
    "sg:tags":[
        "contractor"
    ],
    "wof:name":"Barnes & Elliott Ltd.",
    "wof:placetype":"venue"
},
  "geometry": {"coordinates":[-0.753105998,51.2965736389],"type":"Point"}
}