{
  "type": "Feature",
  "properties": {
    "addr:full":"Waterside St Albans Hertfordshire AL2 1HG",
    "addr:postcode":"al2 1hg",
    "addr:street":"Waterside",
    "iso:country":"GB",
    "sg:address":"Waterside",
    "sg:city":"St Albans",
    "sg:classifiers":[
        {
            "category":"Place Of Worship",
            "type":"Public Place"
        }
    ],
    "sg:phone":"+44 1727 769797",
    "sg:postcode":"AL2 1HG",
    "sg:province":"Hertfordshire",
    "wof:name":"St Peters C Of E Church",
    "wof:placetype":"venue"
},
  "geometry": {"coordinates":[-0.290801,51.719467],"type":"Point"}
}