{
  "type": "Feature",
  "properties": {
    "addr:full":"108 Peel Rd Bootle Merseyside L20 4LA",
    "addr:housenumber":"108",
    "addr:postcode":"l20 4la",
    "addr:street":"Peel Rd",
    "iso:country":"GB",
    "sg:address":"108 Peel Rd",
    "sg:city":"Bootle",
    "sg:classifiers":[
        {
            "category":"Food & Beverages",
            "subcategory":"Supermarket",
            "type":"Retail Goods"
        }
    ],
    "sg:postcode":"L20 4LA",
    "sg:province":"Merseyside",
    "wof:name":"Jaffar,S E,",
    "wof:placetype":"venue"
},
  "geometry": {"coordinates":[-3.00343,53.457596],"type":"Point"}
}