{
  "type": "Feature",
  "properties": {
    "addr:full":"Unit 1 Windmill Business Centre, Glassbrook Road Rushden Bedfordshire NN10 9TH",
    "addr:housenumber":"unit 1",
    "addr:postcode":"nn10 9th",
    "addr:street":"Windmill Business;Glassbrook Road",
    "iso:country":"GB",
    "sg:address":"Unit 1 Windmill Business Centre, Glassbrook Road",
    "sg:city":"Rushden",
    "sg:classifiers":[
        {
            "category":"Manufacturing",
            "subcategory":"Petroleum Products",
            "type":"Manufacturing & Wholesale Goods"
        }
    ],
    "sg:phone":"+44 1933 312734",
    "sg:postcode":"NN10 9TH",
    "sg:province":"Bedfordshire",
    "sg:tags":[
        "double",
        "glazing"
    ],
    "wof:name":"P C Cladding",
    "wof:placetype":"venue"
},
  "geometry": {"coordinates":[-0.598024,52.287624],"type":"Point"}
}