{
  "type": "Feature",
  "properties": {
    "addr:full":"Home Farm Aberlour Moray AB38 9LD",
    "addr:postcode":"ab38 9ld",
    "addr:street":"Aberlour",
    "iso:country":"GB",
    "sg:address":"Home Farm",
    "sg:city":"Aberlour",
    "sg:classifiers":[
        {
            "category":"Farming",
            "subcategory":"Farm",
            "type":"Manufacturing & Wholesale Goods"
        }
    ],
    "sg:postcode":"AB38 9LD",
    "sg:province":"Moray",
    "sg:tags":[
        "mixed",
        "crop"
    ],
    "wof:name":"A Stewart Mackay Ltd.",
    "wof:placetype":"venue"
},
  "geometry": {"coordinates":[-3.2241249084,57.4711647034],"type":"Point"}
}