{
  "type": "Feature",
  "properties": {
    "addr:full":"122a Nelson Road Twickenham Greater London TW2 7AY",
    "addr:housenumber":"122a",
    "addr:postcode":"tw2 7ay",
    "addr:street":"Nelson Road",
    "iso:country":"GB",
    "sg:address":"122a Nelson Road",
    "sg:city":"Twickenham",
    "sg:classifiers":[
        {
            "category":"Building & Trades",
            "subcategory":"Construction",
            "type":"Services"
        }
    ],
    "sg:postcode":"TW2 7AY",
    "sg:province":"Greater London",
    "sg:tags":[
        "builder"
    ],
    "wof:name":"D M H  Builders Ltd.",
    "wof:placetype":"venue"
},
  "geometry": {"coordinates":[-0.356633,51.453583],"type":"Point"}
}