{
  "type": "Feature",
  "properties": {
    "iso:country":"GB",
    "sg:address":"1-3 Hagley Road, Hayley Grn",
    "sg:city":"Halesowen",
    "sg:classifiers":[
        {
            "category":"Autos & Motor Vehicles",
            "subcategory":"Automobile Sales",
            "type":"Retail Goods"
        }
    ],
    "sg:phone":"+44 121 585 7598",
    "sg:postcode":"B63 1DG",
    "sg:province":"West Midlands",
    "sg:tags":[
        "car"
    ],
    "wof:name":"Hayley Green Properties Ltd.",
    "wof:placetype":"venue"
},
  "geometry": {"coordinates":[-2.0699989796,52.4406890869],"type":"Point"}
}