{
  "type": "Feature",
  "properties": {
    "addr:full":"58 Talbot Road, Talbot Green Pontyclun Bridgend CF72 8AF",
    "addr:housenumber":"58",
    "addr:postcode":"cf72 8af",
    "addr:street":"Talbot Road",
    "iso:country":"GB",
    "sg:address":"58 Talbot Road, Talbot Green",
    "sg:city":"Pontyclun",
    "sg:classifiers":[
        {
            "category":"Shopping",
            "subcategory":"News",
            "type":"Retail Goods"
        }
    ],
    "sg:phone":"+44 1443 223358",
    "sg:postcode":"CF72 8AF",
    "sg:province":"Bridgend",
    "sg:tags":[
        "newsagent"
    ],
    "wof:name":"Carols Newsagents",
    "wof:placetype":"venue"
},
  "geometry": {"coordinates":[-3.3838810921,51.5373268127],"type":"Point"}
}