{
  "type": "Feature",
  "properties": {
    "iso:country":"GB",
    "sg:address":"912 City Road",
    "sg:city":"Sheffield",
    "sg:classifiers":[
        {
            "category":"Food & Beverages",
            "subcategory":"Bakery",
            "type":"Retail Goods"
        },
        {
            "category":"Wholesale",
            "subcategory":"Groceries",
            "type":"Manufacturing & Wholesale Goods"
        }
    ],
    "sg:phone":"+44 114 281 9797",
    "sg:postcode":"S2 1GQ",
    "sg:province":"South Yorkshire",
    "sg:tags":[
        "supplier",
        "pizza"
    ],
    "wof:name":"Express Dial A Pizza",
    "wof:placetype":"venue"
},
  "geometry": {"coordinates":[-1.4312579632,53.3622169495],"type":"Point"}
}