{
  "type": "Feature",
  "properties": {
    "iso:country":"GB",
    "sg:address":"Unit 5, Victoria Mills",
    "sg:city":"Batley",
    "sg:classifiers":[
        {
            "category":"Building & Trades",
            "subcategory":"Construction",
            "type":"Services"
        }
    ],
    "sg:phone":"+44 1924 477555",
    "sg:postcode":"WF17 8LL",
    "sg:province":"West Yorkshire",
    "sg:tags":[
        "fork",
        "lift",
        "truck"
    ],
    "wof:name":"Trident Forktrucks",
    "wof:placetype":"venue"
},
  "geometry": {"coordinates":[-1.654499,53.726421],"type":"Point"}
}