{
  "type": "Feature",
  "properties": {
    "iso:country":"GB",
    "sg:address":"Stanmore College, Elm Park",
    "sg:city":"Stanmore",
    "sg:classifiers":[
        {
            "category":"Travel",
            "subcategory":"Travel Agent",
            "type":"Entertainment"
        }
    ],
    "sg:phone":"+44 20 8420 7444",
    "sg:postcode":"HA7 4BQ",
    "sg:province":"Greater London",
    "wof:name":"Travel Scope",
    "wof:placetype":"venue"
},
  "geometry": {"coordinates":[-0.310409,51.617546],"type":"Point"}
}