{
  "type": "Feature",
  "properties": {
    "iso:country":"GB",
    "sg:address":"89 Smeeth Road, Marshland St James",
    "sg:city":"Wisbech",
    "sg:classifiers":[
        {
            "category":"Building & Trades",
            "subcategory":"Construction",
            "type":"Services"
        }
    ],
    "sg:phone":"+44 1945 430380",
    "sg:postcode":"PE14 8JF",
    "sg:province":"Cambridgeshire",
    "sg:tags":[
        "builder"
    ],
    "wof:name":"Gordon Burlingham",
    "wof:placetype":"venue"
},
  "geometry": {"coordinates":[0.264876008,52.6737594604],"type":"Point"}
}