{
  "type": "Feature",
  "properties": {
    "addr:full":"868 Manchester Road, Castleton Rochdale Lancashire OL11 2SP",
    "addr:housenumber":"868",
    "addr:postcode":"ol11 2sp",
    "addr:street":"Manchester Road",
    "iso:country":"GB",
    "sg:address":"868 Manchester Road, Castleton",
    "sg:city":"Rochdale",
    "sg:classifiers":[
        {
            "category":"Bars & Pubs",
            "type":"Food & Drink"
        }
    ],
    "sg:phone":"+44 1706 646351",
    "sg:postcode":"OL11 2SP",
    "sg:province":"Lancashire",
    "sg:tags":[
        "pubs",
        "inn"
    ],
    "wof:name":"The Commercial",
    "wof:placetype":"venue"
},
  "geometry": {"coordinates":[-2.177359,53.590553],"type":"Point"}
}