{
  "type": "Feature",
  "properties": {
    "addr:full":"1 Wheeleys Road Birmingham West Midlands B15 2LD",
    "addr:housenumber":"1",
    "addr:postcode":"b15 2ld",
    "addr:street":"Wheeleys Road",
    "iso:country":"GB",
    "sg:address":"1 Wheeleys Road",
    "sg:city":"Birmingham",
    "sg:classifiers":[
        {
            "category":"Real Estate",
            "subcategory":"Architect",
            "type":"Services"
        }
    ],
    "sg:phone":"+44 121 440 5723",
    "sg:postcode":"B15 2LD",
    "sg:province":"West Midlands",
    "wof:name":"Seely Stiles Partnership",
    "wof:placetype":"venue"
},
  "geometry": {"coordinates":[-1.914464,52.464687],"type":"Point"}
}