{
  "type": "Feature",
  "properties": {
    "addr:full":"132 Coldharbour Lane Hayes Greater London UB3 3HQ",
    "addr:housenumber":"132",
    "addr:postcode":"ub3 3hq",
    "addr:street":"Coldharbour Lane",
    "iso:country":"GB",
    "sg:address":"132 Coldharbour Lane",
    "sg:city":"Hayes",
    "sg:classifiers":[
        {
            "category":"Autos & Motor Vehicles",
            "subcategory":"Fuel & Gas Station",
            "type":"Retail Goods"
        }
    ],
    "sg:phone":"+44 20 8573 0032",
    "sg:postcode":"UB3 3HQ",
    "sg:province":"Greater London",
    "sg:tags":[
        "hr",
        "petrol"
    ],
    "wof:name":"Hayes Service Station",
    "wof:placetype":"venue"
},
  "geometry": {"coordinates":[-0.412614,51.51173],"type":"Point"}
}