{
  "type": "Feature",
  "properties": {
    "addr:full":"Unit 3, The Cedars, Moor Farm Rd Airfield Ind Est Ashbourne Derbyshire DE6 1HD",
    "addr:housenumber":"unit 3",
    "addr:postcode":"de6 1hd",
    "addr:street":"The Cedars Moor Farm Rd",
    "iso:country":"GB",
    "sg:address":"Unit 3, The Cedars, Moor Farm Rd Airfield Ind Est",
    "sg:city":"Ashbourne",
    "sg:classifiers":[
        {
            "category":"Retail",
            "subcategory":"Storage",
            "type":"Services"
        }
    ],
    "sg:phone":"+44 1335 347598",
    "sg:postcode":"DE6 1HD",
    "sg:province":"Derbyshire",
    "sg:tags":[
        "household",
        "removal"
    ],
    "wof:name":"People Removals",
    "wof:placetype":"venue"
},
  "geometry": {"coordinates":[-1.7325639725,53.0182800293],"type":"Point"}
}