{
  "type": "Feature",
  "properties": {
    "addr:full":"114/116 The Broadway Bexleyheath Kent DA6 7DQ",
    "addr:housenumber":"114 / 116",
    "addr:postcode":"da6 7dq",
    "addr:street":"The Broadway",
    "iso:country":"GB",
    "sg:address":"114/116 The Broadway",
    "sg:city":"Bexleyheath",
    "sg:classifiers":[
        {
            "category":"Community Center",
            "subcategory":"Social",
            "type":"Public Place"
        }
    ],
    "sg:phone":"+44 20 8303 0325",
    "sg:postcode":"DA6 7DQ",
    "sg:province":"Kent",
    "sg:tags":[
        "frozen",
        "food",
        "freezer",
        "centre"
    ],
    "wof:name":"Iceland Foods Plc",
    "wof:placetype":"venue"
},
  "geometry": {"coordinates":[0.1450069994,51.4566917419],"type":"Point"}
}