{
  "type": "Feature",
  "properties": {
    "iso:country":"GB",
    "sg:address":"St. Christophers",
    "sg:city":"Bridport",
    "sg:classifiers":[
        {
            "category":"Airline",
            "type":"Transportation"
        }
    ],
    "sg:phone":"+44 1297 489700",
    "sg:postcode":"DT6 6EJ",
    "sg:province":"Dorset",
    "sg:tags":[
        "aircraft",
        "charter"
    ],
    "wof:name":"Flight Management",
    "wof:placetype":"venue"
},
  "geometry": {"coordinates":[-2.856389,50.74144],"type":"Point"}
}