{
  "type": "Feature",
  "properties": {
    "addr:full":"Paisley Abbatoir, Sandyford Road Paisley Renfrewshire PA3 4HP",
    "addr:postcode":"pa3 4hp",
    "addr:street":"Sandyford Road",
    "iso:country":"GB",
    "sg:address":"Paisley Abbatoir, Sandyford Road",
    "sg:city":"Paisley",
    "sg:classifiers":[
        {
            "category":"Wholesale",
            "subcategory":"Meat",
            "type":"Manufacturing & Wholesale Goods"
        }
    ],
    "sg:phone":"+44 141 889 3205",
    "sg:postcode":"PA3 4HP",
    "sg:province":"Renfrewshire",
    "sg:tags":[
        "-"
    ],
    "wof:name":"John Scott Meat (Paisley) Ltd.",
    "wof:placetype":"venue"
},
  "geometry": {"coordinates":[-4.4130997658,55.8619995117],"type":"Point"}
}