{
  "type": "Feature",
  "properties": {
    "addr:full":"Midgeley Farm, Allgreave Macclesfield Cheshire SK11 0BJ",
    "addr:postcode":"sk11 0bj",
    "iso:country":"GB",
    "sg:address":"Midgeley Farm, Allgreave",
    "sg:city":"Macclesfield",
    "sg:classifiers":[
        {
            "category":"Farming",
            "subcategory":"Livestock Farm",
            "type":"Manufacturing & Wholesale Goods"
        }
    ],
    "sg:phone":"+44 1260 227233",
    "sg:postcode":"SK11 0BJ",
    "sg:province":"Cheshire",
    "sg:tags":[
        "others"
    ],
    "wof:name":"G R Dean & Sons",
    "wof:placetype":"venue"
},
  "geometry": {"coordinates":[-2.0417339802,53.2005500793],"type":"Point"}
}