{
  "type": "Feature",
  "properties": {
    "iso:country":"GB",
    "sg:address":"Cleadon Lane, Whitburn",
    "sg:city":"Sunderland",
    "sg:classifiers":[
        {
            "category":"Education",
            "subcategory":"School",
            "type":"Public Place"
        },
        {
            "category":"Government",
            "subcategory":"Office",
            "type":"Public Place"
        }
    ],
    "sg:phone":"+44 191 529 3069",
    "sg:postcode":"SR6 7NS",
    "sg:province":"Tyne and Wear",
    "sg:tags":[
        "local",
        "authority"
    ],
    "wof:name":"Whitburn Village Primary School",
    "wof:placetype":"venue"
},
  "geometry": {"coordinates":[-1.399519,54.95396],"type":"Point"}
}