{
  "type": "Feature",
  "properties": {
    "iso:country":"GB",
    "sg:address":"29 Duke Street",
    "sg:city":"London",
    "sg:classifiers":[
        {
            "category":"Professional",
            "subcategory":"Printing & Photocopies",
            "type":"Services"
        }
    ],
    "sg:phone":"+44 20 7935 9539",
    "sg:postcode":"W1U 1LD",
    "sg:province":"Greater London",
    "sg:tags":[
        "duplicating",
        "copying"
    ],
    "wof:name":"Scale Reprographics Ltd.",
    "wof:placetype":"venue"
},
  "geometry": {"coordinates":[-0.151837,51.51527],"type":"Point"}
}