{
  "type": "Feature",
  "properties": {
    "addr:full":"89 High Street Rye East Sussex TN31 7JN",
    "addr:housenumber":"89",
    "addr:postcode":"tn31 7jn",
    "addr:street":"High Street",
    "iso:country":"GB",
    "sg:address":"89 High Street",
    "sg:city":"Rye",
    "sg:classifiers":[
        {
            "category":"Food & Beverages",
            "subcategory":"Bakery",
            "type":"Retail Goods"
        }
    ],
    "sg:phone":"+44 1797 222243",
    "sg:postcode":"TN31 7JN",
    "sg:province":"East Sussex",
    "sg:tags":[
        "baker"
    ],
    "wof:name":"Rye Bakeries",
    "wof:placetype":"venue"
},
  "geometry": {"coordinates":[0.7330610156,50.9507827759],"type":"Point"}
}