{
  "type": "Feature",
  "properties": {
    "addr:full":"Sutton Hill Vicarage, 1 Spencer Dr Telford Shropshire TF7 4JY",
    "addr:housenumber":"1",
    "addr:postcode":"tf7 4jy",
    "addr:street":"Sutton;Spencer Dr",
    "iso:country":"GB",
    "sg:address":"Sutton Hill Vicarage, 1 Spencer Dr",
    "sg:city":"Telford",
    "sg:classifiers":[
        {
            "category":"Place Of Worship",
            "type":"Public Place"
        }
    ],
    "sg:phone":"+44 1952 680004",
    "sg:postcode":"TF7 4JY",
    "sg:province":"Shropshire",
    "wof:name":"Sutton Hill C of E Church",
    "wof:placetype":"venue"
},
  "geometry": {"coordinates":[-2.4384799004,52.6272888184],"type":"Point"}
}