{
  "type": "Feature",
  "properties": {
    "addr:full":"3a Sun Street Hitchin Bedfordshire SG5 1AE",
    "addr:housenumber":"3a",
    "addr:postcode":"sg5 1ae",
    "addr:street":"Sun Street",
    "iso:country":"GB",
    "sg:address":"3a Sun Street",
    "sg:city":"Hitchin",
    "sg:classifiers":[
        {
            "category":"Restaurant",
            "type":"Food & Drink"
        }
    ],
    "sg:phone":"+44 1462 451896",
    "sg:postcode":"SG5 1AE",
    "sg:province":"Bedfordshire",
    "wof:name":"Wimpy International Ltd.",
    "wof:placetype":"venue"
},
  "geometry": {"coordinates":[-0.278414,51.946789],"type":"Point"}
}