{
  "type": "Feature",
  "properties": {
    "addr:full":"North Orbital Road, London Colney St Albans Hertfordshire AL2 1DL",
    "addr:postcode":"al2 1dl",
    "addr:street":"North Orbital Road",
    "iso:country":"GB",
    "sg:address":"North Orbital Road, London Colney",
    "sg:city":"St Albans",
    "sg:classifiers":[
        {
            "category":"Home & Garden",
            "subcategory":"Garden Supply",
            "type":"Retail Goods"
        }
    ],
    "sg:phone":"+44 1727 822139",
    "sg:postcode":"AL2 1DL",
    "sg:province":"Hertfordshire",
    "sg:tags":[
        "turfing"
    ],
    "wof:name":"Rolawn (Turf Growers) Ltd.",
    "wof:placetype":"venue"
},
  "geometry": {"coordinates":[-0.2953340113,51.7234992981],"type":"Point"}
}