{
  "type": "Feature",
  "properties": {
    "addr:full":"Club & Institute Stanley Durham DH9 7LW",
    "addr:postcode":"dh9 7lw",
    "addr:street":"Stanley",
    "iso:country":"GB",
    "sg:address":"Club & Institute",
    "sg:city":"Stanley",
    "sg:classifiers":[
        {
            "category":"Organizations",
            "subcategory":"Membership Organization",
            "type":"Services"
        }
    ],
    "sg:phone":"+44 1207 232587",
    "sg:postcode":"DH9 7LW",
    "sg:province":"Durham",
    "sg:tags":[
        "club"
    ],
    "wof:name":"Oxhill Central Workmen's Club & Institute Ltd.",
    "wof:placetype":"venue"
},
  "geometry": {"coordinates":[-1.7098100185,54.8658103943],"type":"Point"}
}