{
  "type": "Feature",
  "properties": {
    "addr:full":"65 Watergate Row Chester Cheshire CH1 2LE",
    "addr:housenumber":"65",
    "addr:postcode":"ch1 2le",
    "addr:street":"Watergate Row",
    "iso:country":"GB",
    "sg:address":"65 Watergate Row",
    "sg:city":"Chester",
    "sg:classifiers":[
        {
            "category":"Shopping",
            "subcategory":"Antiques",
            "type":"Retail Goods"
        }
    ],
    "sg:phone":"+44 1244 319421",
    "sg:postcode":"CH1 2LE",
    "sg:province":"Cheshire",
    "wof:name":"Bruce Adams Ltd.",
    "wof:placetype":"venue"
},
  "geometry": {"coordinates":[-2.8976290226,53.1891593933],"type":"Point"}
}