{
  "type": "Feature",
  "properties": {
    "iso:country":"GB",
    "sg:address":"5 Military Road",
    "sg:city":"Colchester",
    "sg:classifiers":[
        {
            "category":"Food & Beverages",
            "subcategory":"Specialty",
            "type":"Retail Goods"
        },
        {
            "category":"Autos & Motor Vehicles",
            "subcategory":"Auto Supplies",
            "type":"Retail Goods"
        }
    ],
    "sg:phone":"+44 1206 549006",
    "sg:postcode":"CO1 2AA",
    "sg:province":"Essex",
    "sg:tags":[
        "health",
        "component",
        "retailer"
    ],
    "wof:name":"AUTO VALET NORFOLK",
    "wof:placetype":"venue"
},
  "geometry": {"coordinates":[0.905581,51.885532],"type":"Point"}
}