{
  "type": "Feature",
  "properties": {
    "addr:full":"Wingate House, 340-348 Ilford Lane Ilford Essex IG1 2LX",
    "addr:housenumber":"340-348",
    "addr:postcode":"ig1 2lx",
    "addr:street":"Ilford Lane",
    "iso:country":"GB",
    "sg:address":"Wingate House, 340-348 Ilford Lane",
    "sg:city":"Ilford",
    "sg:classifiers":[
        {
            "category":"Manufacturing",
            "subcategory":"Building Materials",
            "type":"Manufacturing & Wholesale Goods"
        }
    ],
    "sg:phone":"+44 20 8553 2677",
    "sg:postcode":"IG1 2LX",
    "sg:province":"Essex",
    "sg:tags":[
        "merchant",
        "builder"
    ],
    "wof:name":"WINGATE BUILDERS MERCHANTS",
    "wof:placetype":"venue"
},
  "geometry": {"coordinates":[0.0754870027,51.548740387],"type":"Point"}
}