{
  "type": "Feature",
  "properties": {
    "iso:country":"GB",
    "sg:address":"148a Stock Road",
    "sg:city":"Billericay",
    "sg:classifiers":[
        {
            "category":"Food & Beverages",
            "subcategory":"Supermarket",
            "type":"Retail Goods"
        }
    ],
    "sg:phone":"+44 1277 657453",
    "sg:postcode":"CM12 0RT",
    "sg:province":"Essex",
    "wof:name":"Fresh Options Ltd.",
    "wof:placetype":"venue"
},
  "geometry": {"coordinates":[0.431257,51.640961],"type":"Point"}
}