{
  "type": "Feature",
  "properties": {
    "iso:country":"GB",
    "sg:address":"130 Lime Street",
    "sg:city":"Wolverhampton",
    "sg:classifiers":[
        {
            "category":"Shopping",
            "subcategory":"News",
            "type":"Retail Goods"
        }
    ],
    "sg:phone":"+44 1902 420592",
    "sg:postcode":"WV3 0EX",
    "sg:province":"Staffordshire",
    "sg:tags":[
        "newsagent"
    ],
    "wof:name":"Patel's Newsagents",
    "wof:placetype":"venue"
},
  "geometry": {"coordinates":[-2.140395,52.578762],"type":"Point"}
}