{
  "type": "Feature",
  "properties": {
    "addr:full":"22 Compley Avenue Poulton-le-fylde Lancashire FY6 8AL",
    "addr:housenumber":"22",
    "addr:postcode":"fy6 8al",
    "addr:street":"Compley Avenue Poulton-Le-Fylde",
    "iso:country":"GB",
    "sg:address":"22 Compley Avenue",
    "sg:city":"Poulton-le-fylde",
    "sg:classifiers":[
        {
            "category":"Building & Trades",
            "subcategory":"Landscaping Services",
            "type":"Services"
        }
    ],
    "sg:phone":"+44 1253 891609",
    "sg:postcode":"FY6 8AL",
    "sg:province":"Lancashire",
    "sg:tags":[
        "gardening",
        "landscape",
        "contractor"
    ],
    "wof:name":"KENNETH T LEAK",
    "wof:placetype":"venue"
},
  "geometry": {"coordinates":[-2.9981739521,53.8413696289],"type":"Point"}
}