{
  "type": "Feature",
  "properties": {
    "addr:full":"26 Rowsley Avenue, Hendon London Greater London NW4 1AJ",
    "addr:housenumber":"26",
    "addr:postcode":"nw4 1aj",
    "addr:street":"Rowsley Avenue",
    "iso:country":"GB",
    "sg:address":"26 Rowsley Avenue, Hendon",
    "sg:city":"London",
    "sg:classifiers":[
        {
            "category":"Building & Trades",
            "subcategory":"Pest Control",
            "type":"Services"
        }
    ],
    "sg:postcode":"NW4 1AJ",
    "sg:province":"Greater London",
    "sg:tags":[
        "vermin"
    ],
    "wof:name":"Greenway Pest Control Services",
    "wof:placetype":"venue"
},
  "geometry": {"coordinates":[-0.2237599939,51.5946884155],"type":"Point"}
}