{
  "type": "Feature",
  "properties": {
    "addr:full":"60 Springfield Road Leighton Buzzard Bedfordshire LU7 2QS",
    "addr:housenumber":"60",
    "addr:postcode":"lu7 2qs",
    "addr:street":"Springfield Road",
    "iso:country":"GB",
    "sg:address":"60 Springfield Road",
    "sg:city":"Leighton Buzzard",
    "sg:classifiers":[
        {
            "category":"Building & Trades",
            "subcategory":"Plumbing",
            "type":"Services"
        }
    ],
    "sg:postcode":"LU7 2QS",
    "sg:province":"Bedfordshire",
    "sg:tags":[
        "heating"
    ],
    "wof:name":"J R S Plumbing & Heating",
    "wof:placetype":"venue"
},
  "geometry": {"coordinates":[-0.679166,51.917198],"type":"Point"}
}