{
  "type": "Feature",
  "properties": {
    "addr:full":"102 Southlands Road Bromley Kent BR2 9QS",
    "addr:housenumber":"102",
    "addr:postcode":"br2 9qs",
    "addr:street":"Southlands Road",
    "iso:country":"GB",
    "sg:address":"102 Southlands Road",
    "sg:city":"Bromley",
    "sg:classifiers":[
        {
            "category":"Education",
            "subcategory":"Dance Studio",
            "type":"Public Place"
        }
    ],
    "sg:postcode":"BR2 9QS",
    "sg:province":"Kent",
    "sg:tags":[
        "school",
        "dancing"
    ],
    "wof:name":"Sara Phillips School of Dancing",
    "wof:placetype":"venue"
},
  "geometry": {"coordinates":[0.035257,51.39481],"type":"Point"}
}