{
  "type": "Feature",
  "properties": {
    "addr:full":"628-632 High Road, Leytonstone London Greater London E11 3DA",
    "addr:housenumber":"628-632",
    "addr:postcode":"e11 3da",
    "addr:street":"High Road",
    "iso:country":"GB",
    "sg:address":"628-632 High Road, Leytonstone",
    "sg:city":"London",
    "sg:classifiers":[
        {
            "category":"Food & Beverages",
            "subcategory":"Supermarket",
            "type":"Retail Goods"
        }
    ],
    "sg:phone":"+44 20 8539 8037",
    "sg:postcode":"E11 3DA",
    "sg:province":"Greater London",
    "wof:name":"Kwik Save Stores Ltd.",
    "wof:placetype":"venue"
},
  "geometry": {"coordinates":[0.01053,51.566959],"type":"Point"}
}