{
  "type": "Feature",
  "properties": {
    "addr:full":"95 Upper St. Giles St Norwich Norfolk NR2 1AB",
    "addr:housenumber":"95",
    "addr:postcode":"nr2 1ab",
    "addr:street":"Upper St. Giles St",
    "iso:country":"GB",
    "sg:address":"95 Upper St. Giles St",
    "sg:city":"Norwich",
    "sg:classifiers":[
        {
            "category":"Shopping",
            "subcategory":"News",
            "type":"Retail Goods"
        }
    ],
    "sg:postcode":"NR2 1AB",
    "sg:province":"Norfolk",
    "sg:tags":[
        "newsagent"
    ],
    "wof:name":"Gillon,A & F,",
    "wof:placetype":"venue"
},
  "geometry": {"coordinates":[1.285667,52.629482],"type":"Point"}
}