{
  "type": "Feature",
  "properties": {
    "iso:country":"GB",
    "sg:address":"22 Newstead Road",
    "sg:city":"Barnsley",
    "sg:classifiers":[
        {
            "category":"Building & Trades",
            "subcategory":"Cleaning & Sanitation",
            "type":"Services"
        }
    ],
    "sg:phone":"+44 1226 204562",
    "sg:postcode":"S71 3LY",
    "sg:province":"South Yorkshire",
    "sg:tags":[
        "cleaner",
        "window"
    ],
    "wof:name":"See Through Window Cleaners",
    "wof:placetype":"venue"
},
  "geometry": {"coordinates":[-1.481637001,53.5825767517],"type":"Point"}
}