{
  "type": "Feature",
  "properties": {
    "addr:full":"26 Sturrock Street Kilmarnock East Ayrshire KA1 3AH",
    "addr:housenumber":"26",
    "addr:postcode":"ka1 3ah",
    "addr:street":"Sturrock Street",
    "iso:country":"GB",
    "sg:address":"26 Sturrock Street",
    "sg:city":"Kilmarnock",
    "sg:classifiers":[
        {
            "category":"Professional",
            "subcategory":"Art Services",
            "type":"Services"
        },
        {
            "category":"Building & Trades",
            "subcategory":"Construction",
            "type":"Services"
        }
    ],
    "sg:phone":"+44 1563 522896",
    "sg:postcode":"KA1 3AH",
    "sg:province":"East Ayrshire",
    "sg:tags":[
        "decorator",
        "painter"
    ],
    "wof:name":"William Patterson & Co",
    "wof:placetype":"venue"
},
  "geometry": {"coordinates":[-4.4952812195,55.6083602905],"type":"Point"}
}