{
  "type": "Feature",
  "properties": {
    "iso:country":"GB",
    "sg:address":"20 Bristol Hill, Brislington",
    "sg:city":"Bristol",
    "sg:classifiers":[
        {
            "category":"Building & Trades",
            "subcategory":"Construction",
            "type":"Services"
        }
    ],
    "sg:phone":"+44 117 977 6069",
    "sg:postcode":"BS4 5AB",
    "sg:province":"City of Bristol",
    "sg:tags":[
        "roofing"
    ],
    "wof:name":"Tucker Roofing",
    "wof:placetype":"venue"
},
  "geometry": {"coordinates":[-2.551099,51.433872],"type":"Point"}
}