{
  "type": "Feature",
  "properties": {
    "iso:country":"GB",
    "sg:address":"96 Barr Road",
    "sg:city":"Gravesend",
    "sg:classifiers":[
        {
            "category":"Building & Trades",
            "subcategory":"Construction",
            "type":"Services"
        }
    ],
    "sg:phone":"+44 1474 323264",
    "sg:postcode":"DA12 5AH",
    "sg:province":"Kent",
    "sg:tags":[
        "roofing"
    ],
    "wof:name":"A H M Roofing",
    "wof:placetype":"venue"
},
  "geometry": {"coordinates":[0.398663,51.429058],"type":"Point"}
}