{
  "type": "Feature",
  "properties": {
    "addr:full":"314 Perth Road Dundee Dundee City DD1 4HL",
    "addr:housenumber":"314",
    "addr:postcode":"dd1 4hl",
    "addr:street":"Perth Road",
    "iso:country":"GB",
    "sg:address":"314 Perth Road",
    "sg:city":"Dundee",
    "sg:classifiers":[
        {
            "category":"Shopping",
            "subcategory":"Thrift Store",
            "type":"Retail Goods"
        }
    ],
    "sg:phone":"+44 1382 640050",
    "sg:postcode":"DD1 4HL",
    "sg:province":"Dundee City",
    "sg:tags":[
        "shop",
        "charity"
    ],
    "wof:name":"British Red Cross",
    "wof:placetype":"venue"
},
  "geometry": {"coordinates":[-2.9918589592,56.4560394287],"type":"Point"}
}