{
  "type": "Feature",
  "properties": {
    "iso:country":"GB",
    "sg:address":"16 Boston Parade, Boston Road",
    "sg:city":"London",
    "sg:classifiers":[
        {
            "category":"Building & Trades",
            "subcategory":"Electrical",
            "type":"Services"
        }
    ],
    "sg:phone":"+44 20 8840 6560",
    "sg:postcode":"W7 2DG",
    "sg:province":"Greater London",
    "sg:tags":[
        "lighting"
    ],
    "wof:name":"Ora Ltd.",
    "wof:placetype":"venue"
},
  "geometry": {"coordinates":[-0.3262299895,51.4954795837],"type":"Point"}
}