{
  "type": "Feature",
  "properties": {
    "iso:country":"GB",
    "sg:address":"The Coach House",
    "sg:city":"Kidwelly",
    "sg:classifiers":[
        {
            "category":"Building & Trades",
            "subcategory":"Construction",
            "type":"Services"
        }
    ],
    "sg:phone":"+44 1267 267428",
    "sg:postcode":"SA17 5AW",
    "sg:province":"Carmarthenshire",
    "sg:tags":[
        "flooring"
    ],
    "wof:name":"Swansea Floor Services",
    "wof:placetype":"venue"
},
  "geometry": {"coordinates":[-4.291579,51.777931],"type":"Point"}
}