{
  "type": "Feature",
  "properties": {
    "iso:country":"GB",
    "sg:address":"1197 Finchley Road",
    "sg:city":"London",
    "sg:classifiers":[
        {
            "category":"Professional",
            "subcategory":"Business Services",
            "type":"Services"
        }
    ],
    "sg:phone":"+44 20 8731 7723",
    "sg:postcode":"NW11 0AA",
    "sg:province":"Greater London",
    "sg:tags":[
        "tile",
        "stockist"
    ],
    "wof:name":"Stonell",
    "wof:placetype":"venue"
},
  "geometry": {"coordinates":[-0.197109,51.577049],"type":"Point"}
}