{
  "type": "Feature",
  "properties": {
    "addr:full":"60 Lawrence Road Liverpool Merseyside L15 0EG",
    "addr:housenumber":"60",
    "addr:postcode":"l15 0eg",
    "addr:street":"Lawrence Road",
    "iso:country":"GB",
    "sg:address":"60 Lawrence Road",
    "sg:city":"Liverpool",
    "sg:classifiers":[
        {
            "category":"Retail",
            "subcategory":"Driving School",
            "type":"Services"
        }
    ],
    "sg:postcode":"L15 0EG",
    "sg:province":"Merseyside",
    "wof:name":"Allerton School of Motoring",
    "wof:placetype":"venue"
},
  "geometry": {"coordinates":[-2.935118,53.397076],"type":"Point"}
}