{
  "type": "Feature",
  "properties": {
    "addr:full":"Unit 8 West Devon Business Park, Brook Lane Tavistock Devon PL19 9DP",
    "addr:housenumber":"unit 8",
    "addr:postcode":"pl19 9dp",
    "addr:street":"Park Brook Lane",
    "iso:country":"GB",
    "sg:address":"Unit 8 West Devon Business Park, Brook Lane",
    "sg:city":"Tavistock",
    "sg:classifiers":[
        {
            "category":"Home & Garden",
            "subcategory":"Garden Supply",
            "type":"Retail Goods"
        },
        {
            "category":"Shopping",
            "type":"Retail Goods"
        }
    ],
    "sg:postcode":"PL19 9DP",
    "sg:province":"Devon",
    "sg:tags":[
        "merchant",
        "seed"
    ],
    "wof:name":"West Devon & North Cornwall Farmers",
    "wof:placetype":"venue"
},
  "geometry": {"coordinates":[-4.1482372284,50.5381774902],"type":"Point"}
}