{
  "type": "Feature",
  "properties": {
    "iso:country":"GB",
    "sg:address":"Village Street",
    "sg:city":"Derby",
    "sg:classifiers":[
        {
            "category":"Bars & Pubs",
            "type":"Food & Drink"
        },
        {
            "category":"Community Center",
            "subcategory":"Social",
            "type":"Public Place"
        }
    ],
    "sg:phone":"+44 1332 766329",
    "sg:postcode":"DE23 8DF",
    "sg:province":"Derbyshire",
    "sg:tags":[
        "pubs",
        "house",
        "inn",
        "activity"
    ],
    "wof:name":"Norman Arms",
    "wof:placetype":"venue"
},
  "geometry": {"coordinates":[-1.479421,52.899326],"type":"Point"}
}