{
  "type": "Feature",
  "properties": {
    "addr:full":"Sterling House, 2a George Street, Kingsclere Newbury Berkshire RG20 5NQ",
    "addr:housenumber":"2a",
    "addr:postcode":"rg20 5nq",
    "addr:street":"George Street",
    "iso:country":"GB",
    "sg:address":"Sterling House, 2a George Street, Kingsclere",
    "sg:city":"Newbury",
    "sg:classifiers":[
        {
            "category":"Shopping",
            "subcategory":"Books",
            "type":"Retail Goods"
        }
    ],
    "sg:phone":"+44 1635 297995",
    "sg:postcode":"RG20 5NQ",
    "sg:province":"Berkshire",
    "sg:tags":[
        "retailer",
        "second-hand"
    ],
    "sg:website":"http://www.wyseby.co.uk",
    "wof:name":"Kingsclere Old Book Shop",
    "wof:placetype":"venue"
},
  "geometry": {"coordinates":[-1.2468010187,51.3246955872],"type":"Point"}
}