{
  "type": "Feature",
  "properties": {
    "addr:full":"1 Acacia Cott, Woodlands Dr Bradford West Yorkshire BD10 0PT",
    "addr:housenumber":"1;cott",
    "addr:postcode":"bd10 0pt",
    "addr:street":"Acacia;Woodlands Dr",
    "iso:country":"GB",
    "sg:address":"1 Acacia Cott, Woodlands Dr",
    "sg:city":"Bradford",
    "sg:classifiers":[
        {
            "category":"Retail",
            "subcategory":"Driving School",
            "type":"Services"
        }
    ],
    "sg:postcode":"BD10 0PT",
    "sg:province":"West Yorkshire",
    "wof:name":"Driving Academy",
    "wof:placetype":"venue"
},
  "geometry": {"coordinates":[-1.7583060265,53.7957382202],"type":"Point"}
}