{
  "type": "Feature",
  "properties": {
    "addr:full":"381 Stamfordham Road Newcastle-upon-tyne Tyne and Wear NE5 2LH",
    "addr:housenumber":"381",
    "addr:postcode":"ne5 2lh",
    "addr:street":"Stamfordham Road",
    "iso:country":"GB",
    "sg:address":"381 Stamfordham Road",
    "sg:city":"Newcastle-upon-tyne",
    "sg:classifiers":[
        {
            "category":"Shopping",
            "subcategory":"Pharmacy",
            "type":"Retail Goods"
        }
    ],
    "sg:phone":"+44 191 286 0587",
    "sg:postcode":"NE5 2LH",
    "sg:province":"Tyne and Wear",
    "sg:tags":[
        "pharmacist",
        "chemist"
    ],
    "wof:name":"Moss Chemists",
    "wof:placetype":"venue"
},
  "geometry": {"coordinates":[-1.6869479418,54.9981155396],"type":"Point"}
}