{
  "type": "Feature",
  "properties": {
    "iso:country":"GB",
    "sg:address":"Chadderton Indust Est, Greenside Way",
    "sg:city":"Manchester",
    "sg:classifiers":[
        {
            "category":"Building & Trades",
            "subcategory":"Cleaning & Sanitation",
            "type":"Services"
        }
    ],
    "sg:phone":"+44 161 284 4100",
    "sg:postcode":"M24 1SW",
    "sg:province":"Greater Manchester",
    "sg:tags":[
        "door",
        "manufacturer"
    ],
    "wof:name":"Accent Hansen",
    "wof:placetype":"venue"
},
  "geometry": {"coordinates":[-2.17767,53.534939],"type":"Point"}
}