{
  "type": "Feature",
  "properties": {
    "iso:country":"GB",
    "sg:address":"99 Park Street Lane, Park Street",
    "sg:city":"St Albans",
    "sg:classifiers":[
        {
            "category":"Manufacturing",
            "subcategory":"Tools & Machinery",
            "type":"Manufacturing & Wholesale Goods"
        },
        {
            "category":"Insurance",
            "subcategory":"Insurance Agent",
            "type":"Services"
        }
    ],
    "sg:phone":"+44 1727 874404",
    "sg:postcode":"AL2 2JA",
    "sg:province":"Hertfordshire",
    "sg:tags":[
        "society",
        "friendly"
    ],
    "wof:name":"Gilbert Insurance",
    "wof:placetype":"venue"
},
  "geometry": {"coordinates":[-0.345616,51.718098],"type":"Point"}
}