{
  "type": "Feature",
  "properties": {
    "addr:full":"Dunston Ho, Dunston Rd Chesterfield Derbyshire S41 9QD",
    "addr:postcode":"s41 9qd",
    "addr:street":"Dunston Rd",
    "iso:country":"GB",
    "sg:address":"Dunston Ho, Dunston Rd",
    "sg:city":"Chesterfield",
    "sg:classifiers":[
        {
            "category":"Professional",
            "subcategory":"Engineering",
            "type":"Services"
        }
    ],
    "sg:phone":"+44 1246 261938",
    "sg:postcode":"S41 9QD",
    "sg:province":"Derbyshire",
    "sg:tags":[
        "consulting",
        "engineer"
    ],
    "wof:name":"C A D Design",
    "wof:placetype":"venue"
},
  "geometry": {"coordinates":[-1.4603480101,53.2647895813],"type":"Point"}
}