{
  "type": "Feature",
  "properties": {
    "addr:full":"101 Bashley Road London Greater London NW10 6TE",
    "addr:housenumber":"101",
    "addr:postcode":"nw10 6te",
    "addr:street":"Bashley Road",
    "iso:country":"GB",
    "sg:address":"101 Bashley Road",
    "sg:city":"London",
    "sg:classifiers":[
        {
            "category":"Wholesale",
            "subcategory":"Music Publishers",
            "type":"Manufacturing & Wholesale Goods"
        }
    ],
    "sg:phone":"+44 20 8838 2000",
    "sg:postcode":"NW10 6TE",
    "sg:province":"Greater London",
    "sg:tags":[
        "record"
    ],
    "wof:name":"Intergroove Ltd.",
    "wof:placetype":"venue"
},
  "geometry": {"coordinates":[-0.2583940029,51.5277557373],"type":"Point"}
}