{
  "type": "Feature",
  "properties": {
    "iso:country":"GB",
    "sg:address":"4 William Street",
    "sg:city":"Windsor",
    "sg:classifiers":[
        {
            "category":"Health Services",
            "subcategory":"Optometrist",
            "type":"Services"
        },
        {
            "category":"Shopping",
            "subcategory":"Optician",
            "type":"Retail Goods"
        }
    ],
    "sg:phone":"+44 1753 858502",
    "sg:postcode":"SL4 1BA",
    "sg:province":"Berkshire",
    "sg:tags":[
        "ophthalmic"
    ],
    "wof:name":"Optique Opticians",
    "wof:placetype":"venue"
},
  "geometry": {"coordinates":[-0.610488,51.481018],"type":"Point"}
}