{
  "type": "Feature",
  "properties": {
    "addr:full":"Unit 11 The Quadrangle, Abbey Park Indust Est Romsey Hampshire SO51 9AQ",
    "addr:housenumber":"unit 11",
    "addr:postcode":"so51 9aq",
    "addr:street":"The Quadrangle Abbey Park Indust Est",
    "iso:country":"GB",
    "sg:address":"Unit 11 The Quadrangle, Abbey Park Indust Est",
    "sg:city":"Romsey",
    "sg:classifiers":[
        {
            "category":"Military Area",
            "subcategory":"Coast Guard Base",
            "type":"Public Place"
        }
    ],
    "sg:phone":"+44 1794 518411",
    "sg:postcode":"SO51 9AQ",
    "sg:province":"Hampshire",
    "sg:tags":[
        "supplier",
        "meter"
    ],
    "wof:name":"Eurometers Ltd",
    "wof:placetype":"venue"
},
  "geometry": {"coordinates":[-1.4629089832,50.9835472107],"type":"Point"}
}