{
  "type": "Feature",
  "properties": {
    "addr:full":"26 Cross Hills, Kippax Leeds North Yorkshire LS25 7JP",
    "addr:housenumber":"26",
    "addr:postcode":"ls25 7jp",
    "addr:street":"Cross Hills",
    "iso:country":"GB",
    "sg:address":"26 Cross Hills, Kippax",
    "sg:city":"Leeds",
    "sg:classifiers":[
        {
            "category":"Fast Food",
            "type":"Food & Drink"
        }
    ],
    "sg:postcode":"LS25 7JP",
    "sg:province":"North Yorkshire",
    "sg:tags":[
        "away",
        "take"
    ],
    "wof:name":"Mughal Balti",
    "wof:placetype":"venue"
},
  "geometry": {"coordinates":[-1.370709,53.768211],"type":"Point"}
}