{
  "type": "Feature",
  "properties": {
    "addr:full":"34 Main Street, Littleport Ely Cambridgeshire CB6 1PJ",
    "addr:housenumber":"34",
    "addr:postcode":"cb6 1pj",
    "addr:street":"Main Street",
    "iso:country":"GB",
    "sg:address":"34 Main Street, Littleport",
    "sg:city":"Ely",
    "sg:classifiers":[
        {
            "category":"Bars & Pubs",
            "type":"Food & Drink"
        },
        {
            "category":"Community Center",
            "subcategory":"Social",
            "type":"Public Place"
        }
    ],
    "sg:phone":"+44 1353 860202",
    "sg:postcode":"CB6 1PJ",
    "sg:province":"Cambridgeshire",
    "sg:tags":[
        "pubs",
        "house",
        "inn",
        "activity"
    ],
    "wof:name":"THE CROWN INN",
    "wof:placetype":"venue"
},
  "geometry": {"coordinates":[0.3048000038,52.4568939209],"type":"Point"}
}