{
  "type": "Feature",
  "properties": {
    "addr:full":"Caxton Mills, Edward Street, Dukinfield Road Hyde Cheshire SK14 2PE",
    "addr:postcode":"sk14 2pe",
    "addr:street":"Edward Street Dukinfield Road",
    "iso:country":"GB",
    "sg:address":"Caxton Mills, Edward Street, Dukinfield Road",
    "sg:city":"Hyde",
    "sg:classifiers":[
        {
            "category":"Shopping",
            "subcategory":"Clothing, Apparel, & Fashions",
            "type":"Retail Goods"
        }
    ],
    "sg:postcode":"SK14 2PE",
    "sg:province":"Cheshire",
    "sg:tags":[
        "clothing",
        "fabric"
    ],
    "wof:name":"G W Bedford Ltd.",
    "wof:placetype":"venue"
},
  "geometry": {"coordinates":[-2.0808839798,53.4543113708],"type":"Point"}
}