{
  "type": "Feature",
  "properties": {
    "addr:full":"1 Octavius St Deptford Greater London SE8 4LW",
    "addr:housenumber":"1",
    "addr:postcode":"se8 4lw",
    "addr:street":"Octavius St",
    "iso:country":"GB",
    "sg:address":"1 Octavius St",
    "sg:city":"Deptford",
    "sg:classifiers":[
        {
            "category":"Organizations",
            "subcategory":"Non-profit Organization",
            "type":"Services"
        }
    ],
    "sg:phone":"+44 20 8692 0290",
    "sg:postcode":"SE8 4LW",
    "sg:province":"Greater London",
    "sg:tags":[
        "organisation",
        "voluntary",
        "charity"
    ],
    "wof:name":"Rose Apple Day Centre",
    "wof:placetype":"venue"
},
  "geometry": {"coordinates":[-0.0274739992,51.4784584045],"type":"Point"}
}