{
  "type": "Feature",
  "properties": {
    "addr:full":"1059 London Road Leigh-on-sea Essex SS9 3JP",
    "addr:housenumber":"1059",
    "addr:postcode":"ss9 3jp",
    "addr:street":"London Road",
    "iso:country":"GB",
    "sg:address":"1059 London Road",
    "sg:city":"Leigh-on-sea",
    "sg:classifiers":[
        {
            "category":"Building & Trades",
            "subcategory":"Landscaping Services",
            "type":"Services"
        }
    ],
    "sg:postcode":"SS9 3JP",
    "sg:province":"Essex",
    "sg:tags":[
        "pond",
        "aquarium"
    ],
    "wof:name":"Pisces Aquarium",
    "wof:placetype":"venue"
},
  "geometry": {"coordinates":[0.663624,51.547592],"type":"Point"}
}