{
  "type": "Feature",
  "properties": {
    "addr:full":"2 St James Road Halifax West Yorkshire HX1 1YS",
    "addr:housenumber":"2",
    "addr:postcode":"hx1 1ys",
    "addr:street":"St James Road",
    "iso:country":"GB",
    "sg:address":"2 St James Road",
    "sg:city":"Halifax",
    "sg:classifiers":[
        {
            "category":"Fast Food",
            "type":"Food & Drink"
        },
        {
            "category":"Food & Beverages",
            "subcategory":"Meat & Fish",
            "type":"Retail Goods"
        }
    ],
    "sg:phone":"+44 1422 330043",
    "sg:postcode":"HX1 1YS",
    "sg:province":"West Yorkshire",
    "sg:tags":[
        "shop",
        "chip"
    ],
    "wof:name":"Wendy's Fisheries",
    "wof:placetype":"venue"
},
  "geometry": {"coordinates":[-1.86376,53.724693],"type":"Point"}
}