{
  "type": "Feature",
  "properties": {
    "addr:full":"Castle Road, Euro Link Business Park Sittingbourne Kent ME10 3AP",
    "addr:postcode":"me10 3ap",
    "addr:street":"Castle Road Euro Link Business Park",
    "iso:country":"GB",
    "sg:address":"Castle Road, Euro Link Business Park",
    "sg:city":"Sittingbourne",
    "sg:classifiers":[
        {
            "category":"Professional",
            "subcategory":"Business Services",
            "type":"Services"
        }
    ],
    "sg:postcode":"ME10 3AP",
    "sg:province":"Kent",
    "sg:tags":[
        "food",
        "import",
        "export",
        "agent"
    ],
    "wof:name":"Macleod McCombe (Properties) Ltd.",
    "wof:placetype":"venue"
},
  "geometry": {"coordinates":[0.754425,51.34901],"type":"Point"}
}