{
  "type": "Feature",
  "properties": {
    "addr:full":"2 Muir Road, Houstoun Industrial Estate Livingston West Lothian EH54 5DR",
    "addr:housenumber":"2",
    "addr:postcode":"eh54 5dr",
    "addr:street":"Muir Road Houstoun Industrial Estate",
    "iso:country":"GB",
    "sg:address":"2 Muir Road, Houstoun Industrial Estate",
    "sg:city":"Livingston",
    "sg:classifiers":[
        {
            "category":"Professional",
            "subcategory":"Engineering",
            "type":"Services"
        }
    ],
    "sg:phone":"+44 1506 434241",
    "sg:postcode":"EH54 5DR",
    "sg:province":"West Lothian",
    "sg:tags":[
        "precision",
        "engineer"
    ],
    "wof:name":"Baker Oil Tools",
    "wof:placetype":"venue"
},
  "geometry": {"coordinates":[-3.5027740002,55.9137611389],"type":"Point"}
}