{
  "type": "Feature",
  "properties": {
    "addr:full":"110 Bellegrove Road Welling Kent DA16 3QD",
    "addr:housenumber":"110",
    "addr:postcode":"da16 3qd",
    "addr:street":"Bellegrove Road",
    "iso:country":"GB",
    "sg:address":"110 Bellegrove Road",
    "sg:city":"Welling",
    "sg:classifiers":[
        {
            "category":"Professional",
            "subcategory":"Detective & Security Services",
            "type":"Services"
        }
    ],
    "sg:phone":"+44 20 8303 3862",
    "sg:postcode":"DA16 3QD",
    "sg:province":"Kent",
    "sg:tags":[
        "locksmith"
    ],
    "wof:name":"A W Keil & Co.",
    "wof:placetype":"venue"
},
  "geometry": {"coordinates":[0.1011909992,51.4635353088],"type":"Point"}
}