{
  "type": "Feature",
  "properties": {
    "addr:full":"211-213 West George Street Glasgow Glasgow City G2 2LW",
    "addr:housenumber":"211-213",
    "addr:postcode":"g2 2lw",
    "addr:street":"West George Street",
    "iso:country":"GB",
    "sg:address":"211-213 West George Street",
    "sg:city":"Glasgow",
    "sg:classifiers":[
        {
            "category":"Real Estate",
            "subcategory":"Surveying",
            "type":"Services"
        }
    ],
    "sg:postcode":"G2 2LW",
    "sg:province":"Glasgow City",
    "sg:tags":[
        "surveyor",
        "valuer"
    ],
    "wof:name":"Alan Watt & Co. Ltd.",
    "wof:placetype":"venue"
},
  "geometry": {"coordinates":[-4.260283,55.862656],"type":"Point"}
}