{
  "type": "Feature",
  "properties": {
    "addr:full":"14 Godwyne Road Dover Kent CT16 1SW",
    "addr:housenumber":"14",
    "addr:postcode":"ct16 1sw",
    "addr:street":"Godwyne Road",
    "iso:country":"GB",
    "sg:address":"14 Godwyne Road",
    "sg:city":"Dover",
    "sg:classifiers":[
        {
            "category":"Travel",
            "subcategory":"Hostel",
            "type":"Entertainment"
        }
    ],
    "sg:phone":"+44 1304 206045",
    "sg:postcode":"CT16 1SW",
    "sg:province":"Kent",
    "sg:tags":[
        "youth"
    ],
    "wof:name":"Youth Hostels Association (England & Wales)",
    "wof:placetype":"venue"
},
  "geometry": {"coordinates":[1.31269,51.130741],"type":"Point"}
}