{
  "type": "Feature",
  "properties": {
    "addr:full":"76 Grand Parade Brighton East Sussex BN2 9JA",
    "addr:housenumber":"76",
    "addr:postcode":"bn2 9ja",
    "addr:street":"Grand Parade",
    "iso:country":"GB",
    "sg:address":"76 Grand Parade",
    "sg:city":"Brighton",
    "sg:classifiers":[
        {
            "category":"Travel",
            "subcategory":"Hotels & Motels",
            "type":"Entertainment"
        }
    ],
    "sg:phone":"+44 1273 604182",
    "sg:postcode":"BN2 9JA",
    "sg:province":"East Sussex",
    "wof:name":"Barringtons Hotel",
    "wof:placetype":"venue"
},
  "geometry": {"coordinates":[-0.135847,50.82362],"type":"Point"}
}