{
  "type": "Feature",
  "properties": {
    "addr:full":"21 Morin Road Paignton Devon TQ3 2PL",
    "addr:housenumber":"21",
    "addr:postcode":"tq3 2pl",
    "addr:street":"Morin Road",
    "iso:country":"GB",
    "sg:address":"21 Morin Road",
    "sg:city":"Paignton",
    "sg:classifiers":[
        {
            "category":"Travel",
            "subcategory":"Hotels & Motels",
            "type":"Entertainment"
        }
    ],
    "sg:phone":"+44 1803 523226",
    "sg:postcode":"TQ3 2PL",
    "sg:province":"Devon",
    "wof:name":"Palm Sands Hotel",
    "wof:placetype":"venue"
},
  "geometry": {"coordinates":[-3.558626,50.444618],"type":"Point"}
}