{
  "type": "Feature",
  "properties": {
    "iso:country":"GB",
    "sg:address":"66a Market St",
    "sg:city":"Colne",
    "sg:classifiers":[
        {
            "category":"Restaurant",
            "type":"Food & Drink"
        }
    ],
    "sg:phone":"+44 1282 868676",
    "sg:postcode":"BB8 0HS",
    "sg:province":"Lancashire",
    "sg:tags":[
        "indian"
    ],
    "wof:name":"Spice Of Colne Valley The",
    "wof:placetype":"venue"
},
  "geometry": {"coordinates":[-2.1654260159,53.8572883606],"type":"Point"}
}