{
  "type": "Feature",
  "properties": {
    "iso:country":"GB",
    "sg:address":"17 Cornwall Road",
    "sg:city":"Ruislip",
    "sg:classifiers":[
        {
            "category":"Professional",
            "subcategory":"Computer Services",
            "type":"Services"
        }
    ],
    "sg:postcode":"HA4 6AJ",
    "sg:province":"Greater London",
    "sg:tags":[
        "system",
        "software"
    ],
    "wof:name":"Minter Associates Ltd",
    "wof:placetype":"venue"
},
  "geometry": {"coordinates":[-0.4152739942,51.5658798218],"type":"Point"}
}