{
  "type": "Feature",
  "properties": {
    "iso:country":"GB",
    "sg:address":"Church Workers Institute, Union Road",
    "sg:city":"Crediton",
    "sg:classifiers":[
        {
            "category":"Health Services",
            "subcategory":"Dentist",
            "type":"Services"
        }
    ],
    "sg:phone":"+44 1363 775971",
    "sg:postcode":"EX17 3AW",
    "sg:province":"Devon",
    "sg:tags":[
        "technician",
        "dental"
    ],
    "wof:name":"European Dental Laboratory Ltd.",
    "wof:placetype":"venue"
},
  "geometry": {"coordinates":[-3.6614038944,50.7908363342],"type":"Point"}
}