{
  "type": "Feature",
  "properties": {
    "addr:full":"45 York Street Heywood Lancashire OL10 4NN",
    "addr:housenumber":"45",
    "addr:postcode":"ol10 4nn",
    "addr:street":"York Street",
    "iso:country":"GB",
    "sg:address":"45 York Street",
    "sg:city":"Heywood",
    "sg:classifiers":[
        {
            "category":"Organizations",
            "subcategory":"Political Organization",
            "type":"Services"
        }
    ],
    "sg:phone":"+44 1706 361135",
    "sg:postcode":"OL10 4NN",
    "sg:province":"Lancashire",
    "sg:tags":[
        "party"
    ],
    "wof:name":"Jim Dobbin M P (Heywood & Middleton)",
    "wof:placetype":"venue"
},
  "geometry": {"coordinates":[-2.216809988,53.5935707092],"type":"Point"}
}