{
  "type": "Feature",
  "properties": {
    "addr:full":"294 Copster Hill Road Oldham Lancashire OL8 3DE",
    "addr:housenumber":"294",
    "addr:postcode":"ol8 3de",
    "addr:street":"Copster Hill Road",
    "iso:country":"GB",
    "sg:address":"294 Copster Hill Road",
    "sg:city":"Oldham",
    "sg:classifiers":[
        {
            "category":"Personal",
            "subcategory":"Beauty Salon",
            "type":"Services"
        }
    ],
    "sg:postcode":"OL8 3DE",
    "sg:province":"Lancashire",
    "sg:tags":[
        "lady",
        "hairdresser"
    ],
    "wof:name":"Copster Salon",
    "wof:placetype":"venue"
},
  "geometry": {"coordinates":[-2.1176660061,53.5257072449],"type":"Point"}
}