{
  "type": "Feature",
  "properties": {
    "addr:full":"3 Langham Gro, Timperley Altrincham Cheshire WA15 6DY",
    "addr:housenumber":"3",
    "addr:postcode":"wa15 6dy",
    "addr:street":"Langham Gro",
    "iso:country":"GB",
    "sg:address":"3 Langham Gro, Timperley",
    "sg:city":"Altrincham",
    "sg:classifiers":[
        {
            "category":"Wholesale",
            "subcategory":"Construction Materials",
            "type":"Manufacturing & Wholesale Goods"
        }
    ],
    "sg:phone":"+44 161 962 6575",
    "sg:postcode":"WA15 6DY",
    "sg:province":"Cheshire",
    "sg:tags":[
        "merchant",
        "glass"
    ],
    "wof:name":"Ringway Glass & Glazing",
    "wof:placetype":"venue"
},
  "geometry": {"coordinates":[-2.3218119144,53.4037132263],"type":"Point"}
}