{
  "type": "Feature",
  "properties": {
    "addr:full":"11-13 Downham Road, South Heswall Wirral Merseyside CH60 5RG",
    "addr:housenumber":"11-13",
    "addr:postcode":"ch60 5rg",
    "addr:street":"Downham Road South",
    "iso:country":"GB",
    "sg:address":"11-13 Downham Road, South Heswall",
    "sg:city":"Wirral",
    "sg:classifiers":[
        {
            "category":"Professional",
            "subcategory":"Business Services",
            "type":"Services"
        }
    ],
    "sg:postcode":"CH60 5RG",
    "sg:province":"Merseyside",
    "sg:tags":[
        "holding"
    ],
    "wof:name":"Gresty Developments Ltd.",
    "wof:placetype":"venue"
},
  "geometry": {"coordinates":[-3.0936949253,53.3289871216],"type":"Point"}
}