{
  "type": "Feature",
  "properties": {
    "iso:country":"GB",
    "sg:address":"123 Brandon Road, Watton",
    "sg:city":"Thetford",
    "sg:classifiers":[
        {
            "category":"Manufacturing",
            "subcategory":"Metals",
            "type":"Manufacturing & Wholesale Goods"
        }
    ],
    "sg:phone":"+44 1953 881202",
    "sg:postcode":"IP25 6LN",
    "sg:province":"Norfolk",
    "sg:tags":[
        "steel",
        "fabricator",
        "erectors"
    ],
    "wof:name":"J Abbey",
    "wof:placetype":"venue"
},
  "geometry": {"coordinates":[0.806886,52.570267],"type":"Point"}
}