{
  "type": "Feature",
  "properties": {
    "addr:full":"69 Wigmore Street London Greater London W1U 1PZ",
    "addr:housenumber":"69",
    "addr:postcode":"w1u 1pz",
    "addr:street":"Wigmore Street",
    "iso:country":"GB",
    "sg:address":"69 Wigmore Street",
    "sg:city":"London",
    "sg:classifiers":[
        {
            "category":"Professional",
            "subcategory":"Employment Agencies",
            "type":"Services"
        }
    ],
    "sg:phone":"+44 20 7935 9692",
    "sg:postcode":"W1U 1PZ",
    "sg:province":"Greater London",
    "sg:tags":[
        "consultant"
    ],
    "wof:name":"Crawford's",
    "wof:placetype":"venue"
},
  "geometry": {"coordinates":[-0.150397,51.516033],"type":"Point"}
}