{
  "type": "Feature",
  "properties": {
    "addr:full":"Amari House, 52 High Street Kingston-upon-thames Greater London KT1 1HN",
    "addr:housenumber":"52",
    "addr:postcode":"kt1 1hn",
    "addr:street":"High Street",
    "iso:country":"GB",
    "sg:address":"Amari House, 52 High Street",
    "sg:city":"Kingston-upon-thames",
    "sg:classifiers":[
        {
            "category":"Travel",
            "subcategory":"Travel Agent",
            "type":"Entertainment"
        }
    ],
    "sg:postcode":"KT1 1HN",
    "sg:province":"Greater London",
    "wof:name":"Pacesetter Travel Ltd.",
    "wof:placetype":"venue"
},
  "geometry": {"coordinates":[-0.307953,51.407436],"type":"Point"}
}