{
  "type": "Feature",
  "properties": {
    "addr:full":"Great Howarth Rochdale Lancashire OL12 9HJ",
    "addr:postcode":"ol12 9hj",
    "addr:street":"Rochdale",
    "iso:country":"GB",
    "sg:address":"Great Howarth",
    "sg:city":"Rochdale",
    "sg:classifiers":[
        {
            "category":"Education",
            "subcategory":"School",
            "type":"Public Place"
        },
        {
            "category":"Government",
            "subcategory":"Office",
            "type":"Public Place"
        }
    ],
    "sg:phone":"+44 1706 657993",
    "sg:postcode":"OL12 9HJ",
    "sg:province":"Lancashire",
    "sg:tags":[
        "local",
        "authority"
    ],
    "wof:name":"ROCHDALE METROPOLITAN BOROUGH COUNCIL",
    "wof:placetype":"venue"
},
  "geometry": {"coordinates":[-2.1388039589,53.6380081177],"type":"Point"}
}