{
  "type": "Feature",
  "properties": {
    "iso:country":"GB",
    "sg:address":"Kennards Yard, 46 Heathcote Road, Whitnash",
    "sg:city":"Leamington Spa",
    "sg:classifiers":[
        {
            "category":"Manufacturing",
            "subcategory":"Metals",
            "type":"Manufacturing & Wholesale Goods"
        }
    ],
    "sg:phone":"+44 1926 430525",
    "sg:postcode":"CV31 2NF",
    "sg:province":"Warwickshire",
    "sg:tags":[
        "steel",
        "fabricator",
        "erectors"
    ],
    "wof:name":"I C Fabrication",
    "wof:placetype":"venue"
},
  "geometry": {"coordinates":[-1.521892,52.269791],"type":"Point"}
}