{
  "type": "Feature",
  "properties": {
    "addr:full":"Oakcroft Wks, Oakcroft Rd Chessington Surrey KT9 1RH",
    "addr:postcode":"kt9 1rh",
    "addr:street":"Oakcroft Rd",
    "iso:country":"GB",
    "sg:address":"Oakcroft Wks, Oakcroft Rd",
    "sg:city":"Chessington",
    "sg:classifiers":[
        {
            "category":"Manufacturing",
            "subcategory":"Electronics",
            "type":"Manufacturing & Wholesale Goods"
        }
    ],
    "sg:phone":"+44 20 8397 8559",
    "sg:postcode":"KT9 1RH",
    "sg:province":"Surrey",
    "sg:tags":[
        "mnfrs",
        "transformer"
    ],
    "wof:name":"Surrey Transformers Ltd",
    "wof:placetype":"venue"
},
  "geometry": {"coordinates":[-0.30864501,51.3618736267],"type":"Point"}
}