{
  "type": "Feature",
  "properties": {
    "iso:country":"GB",
    "sg:address":"15 Kirkland",
    "sg:city":"Kendal",
    "sg:classifiers":[
        {
            "category":"Restaurant",
            "type":"Food & Drink"
        }
    ],
    "sg:phone":"+44 1539 722458",
    "sg:postcode":"LA9 5AF",
    "sg:province":"Cumbria",
    "wof:name":"The Union Jack",
    "wof:placetype":"venue"
},
  "geometry": {"coordinates":[-2.745829,54.322624],"type":"Point"}
}