{
  "type": "Feature",
  "properties": {
    "addr:full":"40 Stadon Road, Anstey Leicester Leicestershire LE7 7AY",
    "addr:housenumber":"40",
    "addr:postcode":"le7 7ay",
    "addr:street":"Stadon Road",
    "iso:country":"GB",
    "sg:address":"40 Stadon Road, Anstey",
    "sg:city":"Leicester",
    "sg:classifiers":[
        {
            "category":"Organizations",
            "subcategory":"Membership Organization",
            "type":"Services"
        }
    ],
    "sg:phone":"+44 116 236 4786",
    "sg:postcode":"LE7 7AY",
    "sg:province":"Leicestershire",
    "sg:tags":[
        "club"
    ],
    "wof:name":"Anstey Working Mens Club & Institute",
    "wof:placetype":"venue"
},
  "geometry": {"coordinates":[-1.1887049675,52.6732063293],"type":"Point"}
}