{
  "type": "Feature",
  "properties": {
    "iso:country":"GB",
    "sg:address":"11 Upper Crescent, Minster Lovell",
    "sg:city":"Witney",
    "sg:classifiers":[
        {
            "category":"Health Services",
            "subcategory":"Health Practitioner",
            "type":"Services"
        }
    ],
    "sg:phone":"+44 1993 776225",
    "sg:postcode":"OX29 0RT",
    "sg:province":"Oxfordshire",
    "sg:tags":[
        "osteopath"
    ],
    "wof:name":"Clive Power",
    "wof:placetype":"venue"
},
  "geometry": {"coordinates":[-1.547109,51.796082],"type":"Point"}
}