{
  "type": "Feature",
  "properties": {
    "addr:full":"98 Abbey Street Nuneaton Leicestershire CV11 5BX",
    "addr:housenumber":"98",
    "addr:postcode":"cv11 5bx",
    "addr:street":"Abbey Street",
    "iso:country":"GB",
    "sg:address":"98 Abbey Street",
    "sg:city":"Nuneaton",
    "sg:classifiers":[
        {
            "category":"Bars & Pubs",
            "type":"Food & Drink"
        },
        {
            "category":"Community Center",
            "subcategory":"Social",
            "type":"Public Place"
        }
    ],
    "sg:phone":"+44 24 7635 4005",
    "sg:postcode":"CV11 5BX",
    "sg:province":"Leicestershire",
    "sg:tags":[
        "pubs",
        "house",
        "inn",
        "activity"
    ],
    "wof:name":"Pig & Whistle",
    "wof:placetype":"venue"
},
  "geometry": {"coordinates":[-1.472937,52.525253],"type":"Point"}
}