{
  "type": "Feature",
  "properties": {
    "addr:full":"52 New George Street Plymouth Devon PL1 1RR",
    "addr:housenumber":"52",
    "addr:postcode":"pl1 1rr",
    "addr:street":"New George Street",
    "iso:country":"GB",
    "sg:address":"52 New George Street",
    "sg:city":"Plymouth",
    "sg:classifiers":[
        {
            "category":"Sports & Exercise",
            "subcategory":"Sports Center",
            "type":"Entertainment"
        }
    ],
    "sg:phone":"+44 1752 253807",
    "sg:postcode":"PL1 1RR",
    "sg:province":"Devon",
    "sg:tags":[
        "shop",
        "good"
    ],
    "wof:name":"First Sport",
    "wof:placetype":"venue"
},
  "geometry": {"coordinates":[-4.143218,50.371513],"type":"Point"}
}