{
  "type": "Feature",
  "properties": {
    "iso:country":"GB",
    "sg:address":"6 Brook Street",
    "sg:city":"Selby",
    "sg:classifiers":[
        {
            "category":"Home & Garden",
            "subcategory":"Home Furnishings",
            "type":"Retail Goods"
        }
    ],
    "sg:phone":"+44 1757 210597",
    "sg:postcode":"YO8 4AR",
    "sg:province":"East Riding of Yorkshire",
    "sg:tags":[
        "wall",
        "wallpaper",
        "covering"
    ],
    "wof:name":"Discount Wallpaper",
    "wof:placetype":"venue"
},
  "geometry": {"coordinates":[-1.074488,53.782387],"type":"Point"}
}