{
  "type": "Feature",
  "properties": {
    "addr:full":"677 Holloway Road London Greater London N19 5SE",
    "addr:housenumber":"677",
    "addr:postcode":"n19 5se",
    "addr:street":"Holloway Road",
    "iso:country":"GB",
    "sg:address":"677 Holloway Road",
    "sg:city":"London",
    "sg:classifiers":[
        {
            "category":"Shopping",
            "subcategory":"Comic Books",
            "type":"Retail Goods"
        }
    ],
    "sg:phone":"+44 20 7272 8017",
    "sg:postcode":"N19 5SE",
    "sg:province":"Greater London",
    "sg:tags":[
        "jeweller"
    ],
    "wof:name":"Lazlo Discount Jewellers",
    "wof:placetype":"venue"
},
  "geometry": {"coordinates":[-0.133573,51.565125],"type":"Point"}
}