{
  "type": "Feature",
  "properties": {
    "addr:full":"1 Battersea Square London Greater London SW11 3PZ",
    "addr:housenumber":"1",
    "addr:postcode":"sw11 3pz",
    "addr:street":"Battersea Square",
    "iso:country":"GB",
    "sg:address":"1 Battersea Square",
    "sg:city":"London",
    "sg:classifiers":[
        {
            "category":"Organizations",
            "subcategory":"Membership Organization",
            "type":"Services"
        }
    ],
    "sg:postcode":"SW11 3PZ",
    "sg:province":"Greater London",
    "sg:tags":[
        "club"
    ],
    "wof:name":"Sutton Court Homes (No 2) Ltd.",
    "wof:placetype":"venue"
},
  "geometry": {"coordinates":[-0.162746,51.465233],"type":"Point"}
}