{
  "type": "Feature",
  "properties": {
    "addr:full":"141-145 Central Road Worcester Park Surrey KT4 8DT",
    "addr:housenumber":"141-145",
    "addr:postcode":"kt4 8dt",
    "addr:street":"Central Road",
    "iso:country":"GB",
    "sg:address":"141-145 Central Road",
    "sg:city":"Worcester Park",
    "sg:classifiers":[
        {
            "category":"Community Center",
            "subcategory":"Social",
            "type":"Public Place"
        }
    ],
    "sg:phone":"+44 20 8337 9510",
    "sg:postcode":"KT4 8DT",
    "sg:province":"Surrey",
    "sg:tags":[
        "frozen",
        "food",
        "freezer",
        "centre"
    ],
    "wof:name":"Iceland Foods Plc",
    "wof:placetype":"venue"
},
  "geometry": {"coordinates":[-0.242988,51.379108],"type":"Point"}
}