{
  "type": "Feature",
  "properties": {
    "addr:full":"130 The Street Melksham Wiltshire SN12 8PH",
    "addr:housenumber":"130",
    "addr:postcode":"sn12 8ph",
    "addr:street":"The Street",
    "iso:country":"GB",
    "sg:address":"130 The Street",
    "sg:city":"Melksham",
    "sg:classifiers":[
        {
            "category":"Professional",
            "subcategory":"Lawyer & Legal Services",
            "type":"Services"
        }
    ],
    "sg:phone":"+44 1225 782040",
    "sg:postcode":"SN12 8PH",
    "sg:province":"Wiltshire",
    "sg:tags":[
        "advice",
        "counselling"
    ],
    "wof:name":"Gaunt F",
    "wof:placetype":"venue"
},
  "geometry": {"coordinates":[-2.175867,51.372581],"type":"Point"}
}