{
  "type": "Feature",
  "properties": {
    "iso:country":"GB",
    "sg:address":"114 Northfield Road",
    "sg:city":"Liverpool",
    "sg:classifiers":[
        {
            "category":"Shopping",
            "subcategory":"News",
            "type":"Retail Goods"
        }
    ],
    "sg:postcode":"L9 8BA",
    "sg:province":"Merseyside",
    "sg:tags":[
        "newsagent"
    ],
    "wof:name":"J & L HARFORD NEWSAGENTS",
    "wof:placetype":"venue"
},
  "geometry": {"coordinates":[-2.972606,53.462688],"type":"Point"}
}