{
  "type": "Feature",
  "properties": {
    "addr:full":"2 Grantley Place, Bradley Manor Huddersfield West Yorkshire HD2 1LZ",
    "addr:housenumber":"2",
    "addr:postcode":"hd2 1lz",
    "addr:street":"Grantley Place Bradley Manor",
    "iso:country":"GB",
    "sg:address":"2 Grantley Place, Bradley Manor",
    "sg:city":"Huddersfield",
    "sg:classifiers":[
        {
            "category":"Building & Trades",
            "subcategory":"Landscaping Services",
            "type":"Services"
        }
    ],
    "sg:postcode":"HD2 1LZ",
    "sg:province":"West Yorkshire",
    "sg:tags":[
        "irrigation",
        "system"
    ],
    "wof:name":"Watergleam Ltd",
    "wof:placetype":"venue"
},
  "geometry": {"coordinates":[-1.762456,53.67691],"type":"Point"}
}