{
  "type": "Feature",
  "properties": {
    "iso:country":"GB",
    "sg:address":"2 Topping St",
    "sg:city":"Bury",
    "sg:classifiers":[
        {
            "category":"Recreation",
            "type":"Entertainment"
        }
    ],
    "sg:phone":"+44 161 761 7586",
    "sg:postcode":"BL9 6DR",
    "sg:province":"Lancashire",
    "sg:tags":[
        "snooker",
        "billiards",
        "pool"
    ],
    "wof:name":"A Cook Leisure",
    "wof:placetype":"venue"
},
  "geometry": {"coordinates":[-2.2888429165,53.5986099243],"type":"Point"}
}