{
  "type": "Feature",
  "properties": {
    "iso:country":"GB",
    "sg:address":"Ongar Campus Fyfield Rd",
    "sg:city":"Ongar",
    "sg:classifiers":[
        {
            "category":"Government",
            "subcategory":"Customs House",
            "type":"Public Place"
        }
    ],
    "sg:postcode":"CM5 0PT",
    "sg:province":"Essex",
    "sg:tags":[
        "clearance"
    ],
    "wof:name":"The Ongar Auction Centre",
    "wof:placetype":"venue"
},
  "geometry": {"coordinates":[0.271495,51.739071],"type":"Point"}
}