{
  "type": "Feature",
  "properties": {
    "addr:full":"9 Woodburn Drive Leyburn North Yorkshire DL8 5HU",
    "addr:housenumber":"9",
    "addr:postcode":"dl8 5hu",
    "addr:street":"Woodburn Drive",
    "iso:country":"GB",
    "sg:address":"9 Woodburn Drive",
    "sg:city":"Leyburn",
    "sg:classifiers":[
        {
            "category":"Freight",
            "type":"Transportation"
        }
    ],
    "sg:postcode":"DL8 5HU",
    "sg:province":"North Yorkshire",
    "sg:tags":[
        "haulage",
        "road"
    ],
    "wof:name":"Ray Nicholson Haulage",
    "wof:placetype":"venue"
},
  "geometry": {"coordinates":[-1.8288010359,54.3134078979],"type":"Point"}
}