{
  "type": "Feature",
  "properties": {
    "iso:country":"GB",
    "sg:address":"Long View, Ironstone Road, Prospect Village",
    "sg:city":"Cannock",
    "sg:classifiers":[
        {
            "category":"Home & Garden",
            "subcategory":"Building Materials",
            "type":"Retail Goods"
        }
    ],
    "sg:phone":"+44 1543 277347",
    "sg:postcode":"WS12 5QB",
    "sg:province":"Staffordshire",
    "sg:tags":[
        "fencing"
    ],
    "wof:name":"G Bailey Fencing Contractors",
    "wof:placetype":"venue"
},
  "geometry": {"coordinates":[-1.947174,52.704235],"type":"Point"}
}