{
  "type": "Feature",
  "properties": {
    "iso:country":"GB",
    "sg:address":"2 Duncote Cotts, Walcot",
    "sg:city":"Telford",
    "sg:classifiers":[
        {
            "category":"Professional",
            "subcategory":"Engineering",
            "type":"Services"
        }
    ],
    "sg:phone":"+44 1743 709375",
    "sg:postcode":"TF6 5EP",
    "sg:province":"Shropshire",
    "sg:tags":[
        "contractor",
        "electrical",
        "engineer"
    ],
    "wof:name":"M Wakeley Electrical Contractors",
    "wof:placetype":"venue"
},
  "geometry": {"coordinates":[-2.6023368835,52.7030601501],"type":"Point"}
}