{
  "type": "Feature",
  "properties": {
    "iso:country":"GB",
    "sg:address":"23 Camden High Street",
    "sg:city":"London",
    "sg:classifiers":[
        {
            "category":"Restaurant",
            "type":"Food & Drink"
        }
    ],
    "sg:phone":"+44 20 7387 0349",
    "sg:postcode":"NW1 7JE",
    "sg:province":"Greater London",
    "sg:tags":[
        "indian"
    ],
    "wof:name":"Bharat Tandoori Restaurant",
    "wof:placetype":"venue"
},
  "geometry": {"coordinates":[-0.138847,51.535206],"type":"Point"}
}