{
  "type": "Feature",
  "properties": {
    "addr:full":"6b Littlebrook Centre Melksham Wiltshire SN12 6LP",
    "addr:housenumber":"6b",
    "addr:postcode":"sn12 6lp",
    "iso:country":"GB",
    "sg:address":"6b Littlebrook Centre",
    "sg:city":"Melksham",
    "sg:classifiers":[
        {
            "category":"Shopping",
            "subcategory":"Crafts & Fabrics",
            "type":"Retail Goods"
        },
        {
            "category":"Professional",
            "subcategory":"Art Services",
            "type":"Services"
        }
    ],
    "sg:phone":"+44 1225 707524",
    "sg:postcode":"SN12 6LP",
    "sg:province":"Wiltshire",
    "sg:tags":[
        "shop",
        "photographer",
        "needlecraft",
        "wool"
    ],
    "wof:name":"Peter Lodge Photography",
    "wof:placetype":"venue"
},
  "geometry": {"coordinates":[-2.1208889484,51.3602790833],"type":"Point"}
}