{
  "type": "Feature",
  "properties": {
    "iso:country":"GB",
    "sg:address":"15 Avenue St, Stewarton",
    "sg:city":"Kilmarnock",
    "sg:classifiers":[
        {
            "category":"Building & Trades",
            "subcategory":"Plumbing",
            "type":"Services"
        }
    ],
    "sg:phone":"+44 1560 482506",
    "sg:postcode":"KA3 5AP",
    "sg:province":"East Ayrshire",
    "sg:tags":[
        "heating"
    ],
    "wof:name":"Robert Miller & Sons",
    "wof:placetype":"venue"
},
  "geometry": {"coordinates":[-4.51552,55.682095],"type":"Point"}
}