{
  "type": "Feature",
  "properties": {
    "addr:full":"83a Newcastle Road Stone Staffordshire ST15 8LD",
    "addr:housenumber":"83a",
    "addr:postcode":"st15 8ld",
    "addr:street":"Newcastle Road",
    "iso:country":"GB",
    "sg:address":"83a Newcastle Road",
    "sg:city":"Stone",
    "sg:classifiers":[
        {
            "category":"Home & Garden",
            "subcategory":"Home Furnishings",
            "type":"Retail Goods"
        }
    ],
    "sg:phone":"+44 1785 817115",
    "sg:postcode":"ST15 8LD",
    "sg:province":"Staffordshire",
    "sg:tags":[
        "furnishers",
        "planner",
        "bedroom"
    ],
    "wof:name":"F K B Interiors",
    "wof:placetype":"venue"
},
  "geometry": {"coordinates":[-2.1539580822,52.9046821594],"type":"Point"}
}