{
  "type": "Feature",
  "properties": {
    "iso:country":"GB",
    "sg:address":"34 Peckover St",
    "sg:city":"Bradford",
    "sg:classifiers":[
        {
            "category":"Professional",
            "subcategory":"Art Services",
            "type":"Services"
        }
    ],
    "sg:postcode":"BD1 5BD",
    "sg:province":"West Yorkshire",
    "sg:tags":[
        "photographer"
    ],
    "wof:name":"David Riley Graphics",
    "wof:placetype":"venue"
},
  "geometry": {"coordinates":[-1.7458740473,53.7948913574],"type":"Point"}
}