{
  "type": "Feature",
  "properties": {
    "addr:full":"Front Street, Rothbury Morpeth Northumberland NE65 7ST",
    "addr:postcode":"ne65 7st",
    "addr:street":"Front Street",
    "iso:country":"GB",
    "sg:address":"Front Street, Rothbury",
    "sg:city":"Morpeth",
    "sg:classifiers":[
        {
            "category":"Shopping",
            "subcategory":"Crafts & Fabrics",
            "type":"Retail Goods"
        }
    ],
    "sg:phone":"+44 1669 620560",
    "sg:postcode":"NE65 7ST",
    "sg:province":"Northumberland",
    "sg:tags":[
        "shop",
        "needlecraft",
        "wool"
    ],
    "wof:name":"Mosaic Crafts & Wool",
    "wof:placetype":"venue"
},
  "geometry": {"coordinates":[-1.913994,55.309254],"type":"Point"}
}