{
  "type": "Feature",
  "properties": {
    "addr:full":"Unit 5, Waverley Road Kirkcaldy Fife KY1 3LT",
    "addr:housenumber":"unit 5",
    "addr:postcode":"ky1 3lt",
    "addr:street":"Waverley Road",
    "iso:country":"GB",
    "sg:address":"Unit 5, Waverley Road",
    "sg:city":"Kirkcaldy",
    "sg:classifiers":[
        {
            "category":"Professional",
            "subcategory":"Detective & Security Services",
            "type":"Services"
        }
    ],
    "sg:phone":"+44 1592 653661",
    "sg:postcode":"KY1 3LT",
    "sg:province":"Fife",
    "sg:tags":[
        "alarm",
        "burglar",
        "system"
    ],
    "wof:name":"Fife Alarms Ltd.",
    "wof:placetype":"venue"
},
  "geometry": {"coordinates":[-3.1371209621,56.1355552673],"type":"Point"}
}