{
  "type": "Feature",
  "properties": {
    "iso:country":"GB",
    "sg:address":"Lymm Road, Little Bollington",
    "sg:city":"Altrincham",
    "sg:classifiers":[
        {
            "category":"Restaurant",
            "type":"Food & Drink"
        }
    ],
    "sg:phone":"+44 1565 830018",
    "sg:postcode":"WA14 4SU",
    "sg:province":"Cheshire",
    "wof:name":"The Laurel Pub Co Ltd",
    "wof:placetype":"venue"
},
  "geometry": {"coordinates":[-2.409339,53.37859],"type":"Point"}
}