{
  "type": "Feature",
  "properties": {
    "addr:full":"6 Blenheim Drive Colchester Essex CO2 0AR",
    "addr:housenumber":"6",
    "addr:postcode":"co2 0ar",
    "addr:street":"Blenheim Drive",
    "iso:country":"GB",
    "sg:address":"6 Blenheim Drive",
    "sg:city":"Colchester",
    "sg:classifiers":[
        {
            "category":"Personal",
            "type":"Services"
        },
        {
            "category":"Autos & Motor Vehicles",
            "subcategory":"Motorcycle Sales",
            "type":"Retail Goods"
        }
    ],
    "sg:phone":"+44 1206 545788",
    "sg:postcode":"CO2 0AR",
    "sg:province":"Essex",
    "sg:tags":[
        "chauffeur",
        "driven",
        "car",
        "wedding"
    ],
    "wof:name":"Aston's Vintage Rolls Royce",
    "wof:placetype":"venue"
},
  "geometry": {"coordinates":[0.9085549712,51.8592987061],"type":"Point"}
}