{
  "type": "Feature",
  "properties": {
    "addr:full":"40 Holwell Rd, Holwell Hitchin Bedfordshire SG5 3SG",
    "addr:housenumber":"40",
    "addr:postcode":"sg5 3sg",
    "addr:street":"Holwell Rd",
    "iso:country":"GB",
    "sg:address":"40 Holwell Rd, Holwell",
    "sg:city":"Hitchin",
    "sg:classifiers":[
        {
            "category":"Professional",
            "subcategory":"Management & Consulting",
            "type":"Services"
        }
    ],
    "sg:postcode":"SG5 3SG",
    "sg:province":"Bedfordshire",
    "sg:tags":[
        "consultant"
    ],
    "wof:name":"Enigma Management Solutions Ltd",
    "wof:placetype":"venue"
},
  "geometry": {"coordinates":[-0.2933810055,51.9856948853],"type":"Point"}
}