{
  "type": "Feature",
  "properties": {
    "addr:full":"10 Buckingham Avenue, Vicars Cross Chester Cheshire CH3 5JR",
    "addr:housenumber":"10",
    "addr:postcode":"ch3 5jr",
    "addr:street":"Buckingham Avenue Vicars Cross",
    "iso:country":"GB",
    "sg:address":"10 Buckingham Avenue, Vicars Cross",
    "sg:city":"Chester",
    "sg:classifiers":[
        {
            "category":"Shopping",
            "subcategory":"Pharmacy",
            "type":"Retail Goods"
        }
    ],
    "sg:phone":"+44 1244 348621",
    "sg:postcode":"CH3 5JR",
    "sg:province":"Cheshire",
    "sg:tags":[
        "medicine",
        "therapy"
    ],
    "wof:name":"P Trainer",
    "wof:placetype":"venue"
},
  "geometry": {"coordinates":[-2.8613250256,53.1964225769],"type":"Point"}
}