{
  "type": "Feature",
  "properties": {
    "addr:full":"Wittas House, Two Rivers, Station Lane Witney Oxfordshire OX28 4BH",
    "addr:postcode":"ox28 4bh",
    "addr:street":"Rivers Station Lane",
    "iso:country":"GB",
    "sg:address":"Wittas House, Two Rivers, Station Lane",
    "sg:city":"Witney",
    "sg:classifiers":[
        {
            "category":"Professional",
            "subcategory":"Accounting & Tax Preparation",
            "type":"Services"
        }
    ],
    "sg:postcode":"OX28 4BH",
    "sg:province":"Oxfordshire",
    "sg:tags":[
        "accountant"
    ],
    "wof:name":"Morgan & Murphy Ltd.",
    "wof:placetype":"venue"
},
  "geometry": {"coordinates":[-1.496171,51.782642],"type":"Point"}
}