{
  "type": "Feature",
  "properties": {
    "iso:country":"GB",
    "sg:address":"6-8 Bell Street",
    "sg:city":"Shaftesbury",
    "sg:classifiers":[
        {
            "category":"Home & Garden",
            "subcategory":"Hardware",
            "type":"Retail Goods"
        }
    ],
    "sg:phone":"+44 1747 852978",
    "sg:postcode":"SP7 8AR",
    "sg:province":"Dorset",
    "sg:tags":[
        "retailer",
        "diy"
    ],
    "wof:name":"The Colour Centre",
    "wof:placetype":"venue"
},
  "geometry": {"coordinates":[-2.19738,51.006779],"type":"Point"}
}