{
  "type": "Feature",
  "properties": {
    "addr:full":"124 High Street, Midsomer Norton Bath Somerset BA3 4QG",
    "addr:housenumber":"124",
    "addr:postcode":"ba3 4qg",
    "addr:street":"High Street",
    "iso:country":"GB",
    "sg:address":"124 High Street, Midsomer Norton",
    "sg:city":"Bath",
    "sg:classifiers":[
        {
            "category":"Building & Trades",
            "subcategory":"Construction",
            "type":"Services"
        }
    ],
    "sg:postcode":"BA3 4QG",
    "sg:province":"Somerset",
    "sg:tags":[
        "roofing"
    ],
    "wof:name":"Heatherpeak Ltd",
    "wof:placetype":"venue"
},
  "geometry": {"coordinates":[-2.49007,51.25716],"type":"Point"}
}