{
  "type": "Feature",
  "properties": {
    "iso:country":"GB",
    "sg:address":"259 Prestwick Rd",
    "sg:city":"Watford",
    "sg:classifiers":[
        {
            "category":"Health Services",
            "subcategory":"Doctor",
            "type":"Services"
        }
    ],
    "sg:phone":"+44 20 8428 2432",
    "sg:postcode":"WD1 6XU",
    "sg:province":"Hertfordshire",
    "sg:tags":[
        "practitioners"
    ],
    "wof:name":"Mir, R S",
    "wof:placetype":"venue"
},
  "geometry": {"coordinates":[-0.388558,51.6199],"type":"Point"}
}