{
  "type": "Feature",
  "properties": {
    "iso:country":"GB",
    "sg:address":"52 High St",
    "sg:city":"Stamford",
    "sg:classifiers":[
        {
            "category":"Professional",
            "subcategory":"Engineering",
            "type":"Services"
        }
    ],
    "sg:phone":"+44 1780 766636",
    "sg:postcode":"PE9 2LG",
    "sg:province":"Cambridgeshire",
    "sg:tags":[
        "consulting",
        "engineer"
    ],
    "wof:name":"Rowland Structural Consultants",
    "wof:placetype":"venue"
},
  "geometry": {"coordinates":[-0.477087,52.652668],"type":"Point"}
}