{
  "type": "Feature",
  "properties": {
    "iso:country":"GB",
    "sg:address":"Unit 3 16 Hersham Centre, The Green, Hersham",
    "sg:city":"Walton On Thames",
    "sg:classifiers":[
        {
            "category":"Fast Food",
            "type":"Food & Drink"
        }
    ],
    "sg:phone":"+44 1932 244940",
    "sg:postcode":"KT12 4HP",
    "sg:province":"Surrey",
    "sg:tags":[
        "away",
        "take"
    ],
    "wof:name":"Truffles",
    "wof:placetype":"venue"
},
  "geometry": {"coordinates":[-0.4207040071,51.3843460083],"type":"Point"}
}