{
  "type": "Feature",
  "properties": {
    "addr:full":"Unit 11 Merchiston Indust Est, Bankside Falkirk Falkirk FK2 7PD",
    "addr:housenumber":"unit 11",
    "addr:postcode":"fk2 7pd",
    "addr:street":"Indust;Bankside",
    "iso:country":"GB",
    "sg:address":"Unit 11 Merchiston Indust Est, Bankside",
    "sg:city":"Falkirk",
    "sg:classifiers":[
        {
            "category":"Shopping",
            "subcategory":"Florist",
            "type":"Retail Goods"
        }
    ],
    "sg:phone":"+44 1324 639785",
    "sg:postcode":"FK2 7PD",
    "sg:province":"Falkirk",
    "wof:name":"Glemhath Flowers",
    "wof:placetype":"venue"
},
  "geometry": {"coordinates":[-3.7920389175,56.017288208],"type":"Point"}
}