{
  "type": "Feature",
  "properties": {
    "iso:country":"GB",
    "sg:address":"24a Stuart Road, Waterloo",
    "sg:city":"Liverpool",
    "sg:classifiers":[
        {
            "category":"Personal",
            "subcategory":"Beauty Salon",
            "type":"Services"
        }
    ],
    "sg:postcode":"L22 4QR",
    "sg:province":"Merseyside",
    "sg:tags":[
        "unisex",
        "hairdresser"
    ],
    "wof:name":"Sylvia Lyn Miller",
    "wof:placetype":"venue"
},
  "geometry": {"coordinates":[-3.019383,53.479897],"type":"Point"}
}