{
  "type": "Feature",
  "properties": {
    "iso:country":"GB",
    "sg:address":"St Stephens Cottage, East Harting",
    "sg:city":"Petersfield",
    "sg:classifiers":[
        {
            "category":"Health Services",
            "subcategory":"Health Practitioner",
            "type":"Services"
        }
    ],
    "sg:phone":"+44 1730 825250",
    "sg:postcode":"GU31 5NE",
    "sg:province":"Hampshire",
    "sg:tags":[
        "psychologist"
    ],
    "wof:name":"Dave Williamson Counselling Psychologist",
    "wof:placetype":"venue"
},
  "geometry": {"coordinates":[-0.863115,50.970062],"type":"Point"}
}