{
  "type": "Feature",
  "properties": {
    "iso:country":"GB",
    "sg:address":"10-12 Arthur Street",
    "sg:city":"Newton Stewart",
    "sg:classifiers":[
        {
            "category":"Insurance",
            "subcategory":"Insurance Agent",
            "type":"Services"
        }
    ],
    "sg:phone":"+44 1671 403332",
    "sg:postcode":"DG8 6DE",
    "sg:province":"Dumfries and Galloway",
    "sg:tags":[
        "broker"
    ],
    "wof:name":"Giles Insurance Brokers Ltd.",
    "wof:placetype":"venue"
},
  "geometry": {"coordinates":[-4.483579,54.96003],"type":"Point"}
}