{
  "type": "Feature",
  "properties": {
    "iso:country":"GB",
    "sg:address":"6 Carcut Rd",
    "sg:city":"Middlesbrough",
    "sg:classifiers":[
        {
            "category":"Building & Trades",
            "subcategory":"Construction",
            "type":"Services"
        }
    ],
    "sg:phone":"+44 1642 220721",
    "sg:postcode":"TS3 6QL",
    "sg:province":"North Yorkshire",
    "sg:tags":[
        "platform",
        "work",
        "scaffolding"
    ],
    "wof:name":"Harper Contract Scaffolding Ltd",
    "wof:placetype":"venue"
},
  "geometry": {"coordinates":[-1.205402,54.57336],"type":"Point"}
}