{
  "type": "Feature",
  "properties": {
    "addr:full":"15 Raleigh Street Plymouth Devon PL1 1ET",
    "addr:housenumber":"15",
    "addr:postcode":"pl1 1et",
    "addr:street":"Raleigh Street",
    "iso:country":"GB",
    "sg:address":"15 Raleigh Street",
    "sg:city":"Plymouth",
    "sg:classifiers":[
        {
            "category":"Food & Beverages",
            "subcategory":"Bakery",
            "type":"Retail Goods"
        }
    ],
    "sg:phone":"+44 1752 257030",
    "sg:postcode":"PL1 1ET",
    "sg:province":"Devon",
    "sg:tags":[
        "baker"
    ],
    "wof:name":"Oggie Oggie Pasty Co",
    "wof:placetype":"venue"
},
  "geometry": {"coordinates":[-4.14622,50.370956],"type":"Point"}
}