{
  "type": "Feature",
  "properties": {
    "addr:full":"Cemetery Rd Pudsey West Yorkshire LS28 7LW",
    "addr:postcode":"ls28 7lw",
    "addr:street":"Cemetery Rd",
    "iso:country":"GB",
    "sg:address":"Cemetery Rd",
    "sg:city":"Pudsey",
    "sg:classifiers":[
        {
            "category":"Retail",
            "subcategory":"Funeral Services",
            "type":"Services"
        }
    ],
    "sg:phone":"+44 113 267 3188",
    "sg:postcode":"LS28 7LW",
    "sg:province":"West Yorkshire",
    "sg:tags":[
        "cemetery",
        "crematorium"
    ],
    "wof:name":"Pudsey Cemetery",
    "wof:placetype":"venue"
},
  "geometry": {"coordinates":[-1.675779,53.798306],"type":"Point"}
}