{
  "type": "Feature",
  "properties": {
    "iso:country":"GB",
    "sg:address":"Lancaster Terr",
    "sg:city":"London",
    "sg:classifiers":[
        {
            "category":"Retail",
            "subcategory":"Auto Rental",
            "type":"Services"
        }
    ],
    "sg:postcode":"W2 3PF",
    "sg:province":"Greater London",
    "sg:tags":[
        "car"
    ],
    "wof:name":"Davis,Godfrey,Motor Group Ltd",
    "wof:placetype":"venue"
},
  "geometry": {"coordinates":[-0.175689,51.51297],"type":"Point"}
}