{
  "type": "Feature",
  "properties": {
    "addr:full":"120 Westminster Road, Handsworth Birmingham West Midlands B20 3LX",
    "addr:housenumber":"120",
    "addr:postcode":"b20 3lx",
    "addr:street":"Westminster Road",
    "iso:country":"GB",
    "sg:address":"120 Westminster Road, Handsworth",
    "sg:city":"Birmingham",
    "sg:classifiers":[
        {
            "category":"Building & Trades",
            "subcategory":"Cleaning & Sanitation",
            "type":"Services"
        },
        {
            "category":"Home & Garden",
            "subcategory":"Carpets & Floor Coverings",
            "type":"Retail Goods"
        }
    ],
    "sg:phone":"+44 121 356 7657",
    "sg:postcode":"B20 3LX",
    "sg:province":"West Midlands",
    "sg:tags":[
        "cleaner",
        "upholstery"
    ],
    "wof:name":"Abbeywest Domestic & Commercial Cleaning Services",
    "wof:placetype":"venue"
},
  "geometry": {"coordinates":[-1.908107,52.513256],"type":"Point"}
}