{
  "type": "Feature",
  "properties": {
    "addr:full":"Woodleigh, Northampton Rd, Chapel Brampton Northampton Northamptonshire NN6 8AE",
    "addr:housenumber":"woodleigh",
    "addr:postcode":"nn6 8ae",
    "addr:street":"Northampton Rd",
    "iso:country":"GB",
    "sg:address":"Woodleigh, Northampton Rd, Chapel Brampton",
    "sg:city":"Northampton",
    "sg:classifiers":[
        {
            "category":"Building & Trades",
            "subcategory":"Construction",
            "type":"Services"
        },
        {
            "category":"Real Estate",
            "subcategory":"Architect",
            "type":"Services"
        }
    ],
    "sg:phone":"+44 1604 820566",
    "sg:postcode":"NN6 8AE",
    "sg:province":"Northamptonshire",
    "sg:tags":[
        "installers",
        "gas"
    ],
    "wof:name":"David J Payne",
    "wof:placetype":"venue"
},
  "geometry": {"coordinates":[-0.9335049987,52.2913818359],"type":"Point"}
}