{
  "type": "Feature",
  "properties": {
    "addr:full":"11 Mayford Road, Lordswood Chatham Kent ME5 8SZ",
    "addr:housenumber":"11",
    "addr:postcode":"me5 8sz",
    "addr:street":"Mayford Road Lordswood",
    "iso:country":"GB",
    "sg:address":"11 Mayford Road, Lordswood",
    "sg:city":"Chatham",
    "sg:classifiers":[
        {
            "category":"Building & Trades",
            "subcategory":"Construction",
            "type":"Services"
        }
    ],
    "sg:postcode":"ME5 8SZ",
    "sg:province":"Kent",
    "sg:tags":[
        "dry",
        "lining",
        "plasterers",
        "screeders"
    ],
    "wof:name":"A G N Plastering",
    "wof:placetype":"venue"
},
  "geometry": {"coordinates":[0.5515249968,51.3356666565],"type":"Point"}
}