{
  "type": "Feature",
  "properties": {
    "addr:full":"Unit 5 The Metropolitan Railway, Arcade, Liverpool Street London Greater London EC2M 7PY",
    "addr:housenumber":"unit 5",
    "addr:postcode":"ec2m 7py",
    "addr:street":"The;Liverpool Street",
    "iso:country":"GB",
    "sg:address":"Unit 5 The Metropolitan Railway, Arcade, Liverpool Street",
    "sg:city":"London",
    "sg:classifiers":[
        {
            "category":"Professional",
            "type":"Services"
        }
    ],
    "sg:phone":"+44 20 7626 6150",
    "sg:postcode":"EC2M 7PY",
    "sg:province":"Greater London",
    "sg:tags":[
        "caterer"
    ],
    "wof:name":"Gigi's Expresso Bar",
    "wof:placetype":"venue"
},
  "geometry": {"coordinates":[-0.1045570001,51.4984474182],"type":"Point"}
}