{
  "type": "Feature",
  "properties": {
    "iso:country":"GB",
    "sg:address":"Vincent House, 5 Pembridge Square",
    "sg:city":"London",
    "sg:classifiers":[
        {
            "category":"Real Estate",
            "subcategory":"Real Estate Operator",
            "type":"Services"
        }
    ],
    "sg:phone":"+44 20 7229 1133",
    "sg:postcode":"W2 4EG",
    "sg:province":"Greater London",
    "sg:tags":[
        "letting",
        "agent"
    ],
    "wof:name":"Vincent Housing Association Ltd.",
    "wof:placetype":"venue"
},
  "geometry": {"coordinates":[-0.196426,51.511196],"type":"Point"}
}