{
  "type": "Feature",
  "properties": {
    "iso:country":"GB",
    "sg:address":"383 Lincoln Road",
    "sg:city":"Peterborough",
    "sg:classifiers":[
        {
            "category":"Banks & Credit Unions",
            "subcategory":"Financial Services",
            "type":"Services"
        }
    ],
    "sg:phone":"+44 1733 896141",
    "sg:postcode":"PE1 2PF",
    "sg:province":"Cambridgeshire",
    "sg:tags":[
        "cashing",
        "cheque"
    ],
    "wof:name":"Cash-A-Cheque (G B) Ltd.",
    "wof:placetype":"venue"
},
  "geometry": {"coordinates":[-0.247782,52.588493],"type":"Point"}
}