{
  "type": "Feature",
  "properties": {
    "iso:country":"GB",
    "sg:address":"82 Northgate Street",
    "sg:city":"Great Yarmouth",
    "sg:classifiers":[
        {
            "category":"Home & Garden",
            "subcategory":"Furniture",
            "type":"Retail Goods"
        }
    ],
    "sg:postcode":"NR30 1BN",
    "sg:province":"Norfolk",
    "wof:name":"Northgate Trading Centre",
    "wof:placetype":"venue"
},
  "geometry": {"coordinates":[1.7275400162,52.6154403687],"type":"Point"}
}