{
  "type": "Feature",
  "properties": {
    "addr:full":"Unit 9, Pippin Bank Bacup Lancashire OL13 0BU",
    "addr:housenumber":"unit 9",
    "addr:postcode":"ol13 0bu",
    "addr:street":"Pippin Bank Bacup",
    "iso:country":"GB",
    "sg:address":"Unit 9, Pippin Bank",
    "sg:city":"Bacup",
    "sg:classifiers":[
        {
            "category":"Real Estate",
            "subcategory":"Developer",
            "type":"Services"
        },
        {
            "category":"Building & Trades",
            "subcategory":"Construction",
            "type":"Services"
        }
    ],
    "sg:phone":"+44 1706 879366",
    "sg:postcode":"OL13 0BU",
    "sg:province":"Lancashire",
    "sg:tags":[
        "builder",
        "property"
    ],
    "wof:name":"J & K Butterworth Ltd.",
    "wof:placetype":"venue"
},
  "geometry": {"coordinates":[-2.204923,53.69532],"type":"Point"}
}