{
  "type": "Feature",
  "properties": {
    "iso:country":"GB",
    "sg:address":"Buckwell Farm, Hoath Road, Hoath",
    "sg:city":"Canterbury",
    "sg:classifiers":[
        {
            "category":"Farming",
            "subcategory":"Livestock Farm",
            "type":"Manufacturing & Wholesale Goods"
        }
    ],
    "sg:phone":"+44 1227 712654",
    "sg:postcode":"CT3 4JW",
    "sg:province":"Kent",
    "sg:tags":[
        "others"
    ],
    "wof:name":"Lawrence & Sons",
    "wof:placetype":"venue"
},
  "geometry": {"coordinates":[1.163307,51.334782],"type":"Point"}
}