{
  "type": "Feature",
  "properties": {
    "addr:full":"11 Barnsdale Road Stirling Falkirk FK7 0PT",
    "addr:housenumber":"11",
    "addr:postcode":"fk7 0pt",
    "addr:street":"Barnsdale Road",
    "iso:country":"GB",
    "sg:address":"11 Barnsdale Road",
    "sg:city":"Stirling",
    "sg:classifiers":[
        {
            "category":"Personal",
            "subcategory":"Beauty Salon",
            "type":"Services"
        },
        {
            "category":"Personal",
            "subcategory":"Barber",
            "type":"Services"
        }
    ],
    "sg:phone":"+44 1786 470203",
    "sg:postcode":"FK7 0PT",
    "sg:province":"Falkirk",
    "sg:tags":[
        "unisex",
        "hairdresser"
    ],
    "wof:name":"Jacki's Salon",
    "wof:placetype":"venue"
},
  "geometry": {"coordinates":[-3.938867,56.098717],"type":"Point"}
}