{
  "type": "Feature",
  "properties": {
    "addr:full":"West Lane, Baildon Shipley West Yorkshire BD17 5DH",
    "addr:postcode":"bd17 5dh",
    "addr:street":"West Lane",
    "iso:country":"GB",
    "sg:address":"West Lane, Baildon",
    "sg:city":"Shipley",
    "sg:classifiers":[
        {
            "category":"Community Center",
            "subcategory":"Youth",
            "type":"Public Place"
        },
        {
            "category":"Government",
            "subcategory":"Office",
            "type":"Public Place"
        }
    ],
    "sg:postcode":"BD17 5DH",
    "sg:province":"West Yorkshire",
    "sg:tags":[
        "organisation",
        "local",
        "centre"
    ],
    "wof:name":"BAILDON YOUTH CLUB",
    "wof:placetype":"venue"
},
  "geometry": {"coordinates":[-1.7717579603,53.8516807556],"type":"Point"}
}