{
  "type": "Feature",
  "properties": {
    "addr:full":"47 Station Road, Puckeridge Ware Hertfordshire SG11 1TE",
    "addr:housenumber":"47",
    "addr:postcode":"sg11 1te",
    "addr:street":"Station Road;Ware",
    "iso:country":"GB",
    "sg:address":"47 Station Road, Puckeridge",
    "sg:city":"Ware",
    "sg:classifiers":[
        {
            "category":"Professional",
            "subcategory":"Art Services",
            "type":"Services"
        }
    ],
    "sg:phone":"+44 1920 822076",
    "sg:postcode":"SG11 1TE",
    "sg:province":"Hertfordshire",
    "sg:tags":[
        "graphic",
        "designer"
    ],
    "wof:name":"Tinker Design",
    "wof:placetype":"venue"
},
  "geometry": {"coordinates":[0.0157219991,51.8893852234],"type":"Point"}
}