{
  "type": "Feature",
  "properties": {
    "addr:full":"8 Cardoness Rd Sheffield South Yorkshire S10 5RU",
    "addr:housenumber":"8",
    "addr:postcode":"s10 5ru",
    "addr:street":"Cardoness Rd",
    "iso:country":"GB",
    "sg:address":"8 Cardoness Rd",
    "sg:city":"Sheffield",
    "sg:classifiers":[
        {
            "category":"Professional",
            "subcategory":"Management & Consulting",
            "type":"Services"
        }
    ],
    "sg:phone":"+44 114 230 6564",
    "sg:postcode":"S10 5RU",
    "sg:province":"South Yorkshire",
    "sg:tags":[
        "environmental",
        "consultant"
    ],
    "wof:name":"AT RISK",
    "wof:placetype":"venue"
},
  "geometry": {"coordinates":[-1.5227710009,53.3783874512],"type":"Point"}
}