{
  "type": "Feature",
  "properties": {
    "iso:country":"GB",
    "sg:address":"24 Tippings Lane, Woodley",
    "sg:city":"Reading",
    "sg:classifiers":[
        {
            "category":"Home & Garden",
            "subcategory":"Home Furnishings",
            "type":"Retail Goods"
        }
    ],
    "sg:phone":"+44 118 962 8826",
    "sg:postcode":"RG5 4RY",
    "sg:province":"Berkshire",
    "sg:tags":[
        "furnishers",
        "planner",
        "kitchen"
    ],
    "wof:name":"Alan King Interiors",
    "wof:placetype":"venue"
},
  "geometry": {"coordinates":[-0.889514029,51.4593467712],"type":"Point"}
}