{
  "type": "Feature",
  "properties": {
    "addr:full":"Victoria Square St Austell Cornwall PL26 8LQ",
    "addr:postcode":"pl26 8lq",
    "addr:street":"Victoria Square",
    "iso:country":"GB",
    "sg:address":"Victoria Square",
    "sg:city":"St Austell",
    "sg:classifiers":[
        {
            "category":"Shopping",
            "subcategory":"Clothing, Apparel, & Fashions",
            "type":"Retail Goods"
        }
    ],
    "sg:postcode":"PL26 8LQ",
    "sg:province":"Cornwall",
    "sg:tags":[
        "ladieswear"
    ],
    "wof:name":"Silken Ladder",
    "wof:placetype":"venue"
},
  "geometry": {"coordinates":[-4.8326,50.421291],"type":"Point"}
}