{
  "type": "Feature",
  "properties": {
    "addr:full":"91 Howard Avenue, Bexley London Greater London SE3 7JW",
    "addr:housenumber":"91",
    "addr:postcode":"se3 7jw",
    "addr:street":"Howard Avenue",
    "iso:country":"GB",
    "sg:address":"91 Howard Avenue, Bexley",
    "sg:city":"London",
    "sg:classifiers":[
        {
            "category":"Building & Trades",
            "subcategory":"Landscaping Services",
            "type":"Services"
        }
    ],
    "sg:postcode":"SE3 7JW",
    "sg:province":"Greater London",
    "sg:tags":[
        "landscape",
        "contractor"
    ],
    "wof:name":"Blackheath Landscaping & Garden Design",
    "wof:placetype":"venue"
},
  "geometry": {"coordinates":[0.1213,51.442039],"type":"Point"}
}