{
  "type": "Feature",
  "properties": {
    "addr:full":"Cecil Road London Greater London E13 0LX",
    "addr:postcode":"e13 0lx",
    "addr:street":"Cecil Road",
    "iso:country":"GB",
    "sg:address":"Cecil Road",
    "sg:city":"London",
    "sg:classifiers":[
        {
            "category":"Government",
            "subcategory":"Office",
            "type":"Public Place"
        }
    ],
    "sg:phone":"+44 20 8471 6173",
    "sg:postcode":"E13 0LX",
    "sg:province":"Greater London",
    "sg:tags":[
        "local"
    ],
    "wof:name":"Selwyn Infants School",
    "wof:placetype":"venue"
},
  "geometry": {"coordinates":[0.0232410002,51.5361633301],"type":"Point"}
}