{
  "type": "Feature",
  "properties": {
    "addr:full":"160 Manchester Road Bolton Lancashire BL2 1HE",
    "addr:housenumber":"160",
    "addr:postcode":"bl2 1he",
    "addr:street":"Manchester Road",
    "iso:country":"GB",
    "sg:address":"160 Manchester Road",
    "sg:city":"Bolton",
    "sg:classifiers":[
        {
            "category":"Bars & Pubs",
            "type":"Food & Drink"
        }
    ],
    "sg:postcode":"BL2 1HE",
    "sg:province":"Lancashire",
    "sg:tags":[
        "pubs",
        "inn"
    ],
    "wof:name":"The Wagon & Horses",
    "wof:placetype":"venue"
},
  "geometry": {"coordinates":[-2.42044,53.570339],"type":"Point"}
}