{
  "type": "Feature",
  "properties": {
    "iso:country":"GB",
    "sg:address":"Redwood House, 65 Bristol Road, Keynsham",
    "sg:city":"Bristol",
    "sg:classifiers":[
        {
            "category":"Organizations",
            "subcategory":"Political Organization",
            "type":"Services"
        }
    ],
    "sg:phone":"+44 117 987 2313",
    "sg:postcode":"BS31 2WB",
    "sg:province":"City of Bristol",
    "sg:tags":[
        "party"
    ],
    "wof:name":"Wansdyke Conservative Association",
    "wof:placetype":"venue"
},
  "geometry": {"coordinates":[-2.506234,51.418163],"type":"Point"}
}