{
  "type": "Feature",
  "properties": {
    "addr:full":"22 Purcell Avenue Lichfield Staffordshire WS13 7PJ",
    "addr:housenumber":"22",
    "addr:postcode":"ws13 7pj",
    "addr:street":"Purcell Avenue",
    "iso:country":"GB",
    "sg:address":"22 Purcell Avenue",
    "sg:city":"Lichfield",
    "sg:classifiers":[
        {
            "category":"Retail",
            "subcategory":"Driving School",
            "type":"Services"
        }
    ],
    "sg:phone":"+44 1543 300433",
    "sg:postcode":"WS13 7PJ",
    "sg:province":"Staffordshire",
    "wof:name":"Tony Wilkins",
    "wof:placetype":"venue"
},
  "geometry": {"coordinates":[-1.8252689838,52.6957359314],"type":"Point"}
}