{
  "type": "Feature",
  "properties": {
    "addr:full":"Townsend Farm, The Street, Stinchcombe Dursley Gloucestershire GL11 6AP",
    "addr:postcode":"gl11 6ap",
    "addr:street":"The Street",
    "iso:country":"GB",
    "sg:address":"Townsend Farm, The Street, Stinchcombe",
    "sg:city":"Dursley",
    "sg:classifiers":[
        {
            "category":"Farming",
            "subcategory":"Livestock Farm",
            "type":"Manufacturing & Wholesale Goods"
        }
    ],
    "sg:phone":"+44 1453 542563",
    "sg:postcode":"GL11 6AP",
    "sg:province":"Gloucestershire",
    "sg:tags":[
        "others"
    ],
    "wof:name":"H G Workman & Son",
    "wof:placetype":"venue"
},
  "geometry": {"coordinates":[-2.3924069405,51.6881752014],"type":"Point"}
}