{
  "type": "Feature",
  "properties": {
    "iso:country":"GB",
    "sg:address":"27 Frys Lane",
    "sg:city":"Yateley",
    "sg:classifiers":[
        {
            "category":"Health Services",
            "subcategory":"Podiatrist",
            "type":"Services"
        },
        {
            "category":"Health Services",
            "subcategory":"Chiropractor",
            "type":"Services"
        }
    ],
    "sg:phone":"+44 1252 870760",
    "sg:postcode":"GU46 7TJ",
    "sg:province":"Hampshire",
    "sg:tags":[
        "podiatrists",
        "chiropodist"
    ],
    "wof:name":"KAY KNIGHT",
    "wof:placetype":"venue"
},
  "geometry": {"coordinates":[-0.8226360083,51.3444099426],"type":"Point"}
}