{
  "type": "Feature",
  "properties": {
    "addr:full":"Unit 8 Cranleigh Gdns Ind Est Southall Greater London UB1 2BZ",
    "addr:housenumber":"unit 8",
    "addr:postcode":"ub1 2bz",
    "addr:street":"Cranleigh Gdns",
    "iso:country":"GB",
    "sg:address":"Unit 8 Cranleigh Gdns Ind Est",
    "sg:city":"Southall",
    "sg:classifiers":[
        {
            "category":"Shopping",
            "subcategory":"Stationery & Office Supplies",
            "type":"Retail Goods"
        }
    ],
    "sg:postcode":"UB1 2BZ",
    "sg:province":"Greater London",
    "wof:name":"Balfour,Kenneth,Ltd",
    "wof:placetype":"venue"
},
  "geometry": {"coordinates":[-0.3777,51.521019],"type":"Point"}
}