{
  "type": "Feature",
  "properties": {
    "iso:country":"GB",
    "sg:address":"8 High View",
    "sg:city":"Hatfield",
    "sg:classifiers":[
        {
            "category":"Shopping",
            "subcategory":"Pharmacy",
            "type":"Retail Goods"
        }
    ],
    "sg:phone":"+44 1707 262748",
    "sg:postcode":"AL10 8HZ",
    "sg:province":"Hertfordshire",
    "sg:tags":[
        "pharmacist",
        "chemist"
    ],
    "wof:name":"Hodson",
    "wof:placetype":"venue"
},
  "geometry": {"coordinates":[-0.23384,51.747452],"type":"Point"}
}