{
  "type": "Feature",
  "properties": {
    "addr:full":"Castleford Farm Cottage, Ford Salisbury Hampshire SP4 6DX",
    "addr:postcode":"sp4 6dx",
    "iso:country":"GB",
    "sg:address":"Castleford Farm Cottage, Ford",
    "sg:city":"Salisbury",
    "sg:classifiers":[
        {
            "category":"Farming",
            "subcategory":"Livestock Farm",
            "type":"Manufacturing & Wholesale Goods"
        }
    ],
    "sg:phone":"+44 1722 322509",
    "sg:postcode":"SP4 6DX",
    "sg:province":"Hampshire",
    "sg:tags":[
        "others"
    ],
    "wof:name":"Castleford Farm",
    "wof:placetype":"venue"
},
  "geometry": {"coordinates":[-1.7777739763,51.0948066711],"type":"Point"}
}