{
  "type": "Feature",
  "properties": {
    "addr:full":"38 Bridge Street Heywood Lancashire OL10 1JF",
    "addr:housenumber":"38",
    "addr:postcode":"ol10 1jf",
    "addr:street":"Bridge Street",
    "iso:country":"GB",
    "sg:address":"38 Bridge Street",
    "sg:city":"Heywood",
    "sg:classifiers":[
        {
            "category":"Fast Food",
            "type":"Food & Drink"
        },
        {
            "category":"Food & Beverages",
            "subcategory":"Bakery",
            "type":"Retail Goods"
        }
    ],
    "sg:phone":"+44 1706 360371",
    "sg:postcode":"OL10 1JF",
    "sg:province":"Lancashire",
    "sg:tags":[
        "delivery",
        "baker",
        "snack",
        "sandwich"
    ],
    "wof:name":"Greenwoods",
    "wof:placetype":"venue"
},
  "geometry": {"coordinates":[-2.225787,53.594059],"type":"Point"}
}