{
  "type": "Feature",
  "properties": {
    "addr:full":"Nadder Road Tidworth Hampshire SP9 7QN",
    "addr:postcode":"sp9 7qn",
    "addr:street":"Nadder Road",
    "iso:country":"GB",
    "sg:address":"Nadder Road",
    "sg:city":"Tidworth",
    "sg:classifiers":[
        {
            "category":"Education",
            "subcategory":"Library",
            "type":"Public Place"
        }
    ],
    "sg:phone":"+44 1980 843460",
    "sg:postcode":"SP9 7QN",
    "sg:province":"Hampshire",
    "sg:tags":[
        "book"
    ],
    "wof:name":"Tidworth Library",
    "wof:placetype":"venue"
},
  "geometry": {"coordinates":[-1.6619910002,51.2374610901],"type":"Point"}
}