{
  "type": "Feature",
  "properties": {
    "addr:full":"26 Swain Street Watchet Somerset TA23 0AD",
    "addr:housenumber":"26",
    "addr:postcode":"ta23 0ad",
    "addr:street":"Swain Street",
    "iso:country":"GB",
    "sg:address":"26 Swain Street",
    "sg:city":"Watchet",
    "sg:classifiers":[
        {
            "category":"Government",
            "subcategory":"Post Office",
            "type":"Public Place"
        }
    ],
    "sg:phone":"+44 1984 631223",
    "sg:postcode":"TA23 0AD",
    "sg:province":"Somerset",
    "wof:name":"Watchet Post Office",
    "wof:placetype":"venue"
},
  "geometry": {"coordinates":[-3.330132,51.180614],"type":"Point"}
}