{
  "type": "Feature",
  "properties": {
    "iso:country":"GB",
    "sg:address":"217/219 High Street",
    "sg:city":"Orpington",
    "sg:classifiers":[
        {
            "category":"Professional",
            "subcategory":"Management & Consulting",
            "type":"Services"
        }
    ],
    "sg:postcode":"BR6 0NZ",
    "sg:province":"Kent",
    "sg:tags":[
        "consultant",
        "business"
    ],
    "wof:name":"M & P Consultants Ltd",
    "wof:placetype":"venue"
},
  "geometry": {"coordinates":[0.099777,51.37608],"type":"Point"}
}