{
  "type": "Feature",
  "properties": {
    "iso:country":"GB",
    "sg:address":"Churchill House, 85 Mount Pleasant Road",
    "sg:city":"Tunbridge Wells",
    "sg:classifiers":[
        {
            "category":"Real Estate",
            "subcategory":"Real Estate Agent",
            "type":"Services"
        }
    ],
    "sg:phone":"+44 1892 515035",
    "sg:postcode":"TN1 1PX",
    "sg:province":"Kent",
    "sg:website":"http://www.knightfrank.com",
    "wof:name":"Knight Frank",
    "wof:placetype":"venue"
},
  "geometry": {"coordinates":[0.2632550001,51.1329803467],"type":"Point"}
}