{
  "type": "Feature",
  "properties": {
    "iso:country":"GB",
    "sg:address":"P O Box 26",
    "sg:city":"Bridgend",
    "sg:classifiers":[
        {
            "category":"Professional",
            "subcategory":"Lawyer & Legal Services",
            "type":"Services"
        }
    ],
    "sg:phone":"+44 1656 766139",
    "sg:postcode":"CF31 3YJ",
    "sg:province":"Bridgend",
    "sg:tags":[
        "advice",
        "counselling"
    ],
    "wof:name":"Ogwr Women's Aid",
    "wof:placetype":"venue"
},
  "geometry": {"coordinates":[-3.5399138927,51.5031890869],"type":"Point"}
}