{
  "type": "Feature",
  "properties": {
    "iso:country":"GB",
    "sg:address":"13 Carnaby Street",
    "sg:city":"London",
    "sg:classifiers":[
        {
            "category":"Home & Garden",
            "subcategory":"Building Materials",
            "type":"Retail Goods"
        }
    ],
    "sg:phone":"+44 121 233 1599",
    "sg:postcode":"W1F 9PB",
    "sg:province":"Greater London",
    "sg:tags":[
        "furnishers",
        "bathroom",
        "planner"
    ],
    "wof:name":"Qualitex Ltd",
    "wof:placetype":"venue"
},
  "geometry": {"coordinates":[-0.138359,51.512711],"type":"Point"}
}