{
  "type": "Feature",
  "properties": {
    "addr:full":"26 Mill Street Evesham Gloucestershire WR11 4PP",
    "addr:housenumber":"26",
    "addr:postcode":"wr11 4pp",
    "addr:street":"Mill Street",
    "iso:country":"GB",
    "sg:address":"26 Mill Street",
    "sg:city":"Evesham",
    "sg:classifiers":[
        {
            "category":"Personal",
            "subcategory":"Beauty Salon",
            "type":"Services"
        }
    ],
    "sg:phone":"+44 1386 443417",
    "sg:postcode":"WR11 4PP",
    "sg:province":"Gloucestershire",
    "sg:tags":[
        "unisex",
        "hairdresser"
    ],
    "wof:name":"D'Capelli",
    "wof:placetype":"venue"
},
  "geometry": {"coordinates":[-1.944333,52.09201],"type":"Point"}
}