{
  "type": "Feature",
  "properties": {
    "iso:country":"GB",
    "sg:address":"7 Mount Crescent, Penllergaer",
    "sg:city":"Swansea",
    "sg:classifiers":[
        {
            "category":"Home & Garden",
            "subcategory":"Household Appliances",
            "type":"Retail Goods"
        }
    ],
    "sg:postcode":"SA4 9BG",
    "sg:province":"Carmarthenshire",
    "sg:tags":[
        "electrical"
    ],
    "wof:name":"D A R",
    "wof:placetype":"venue"
},
  "geometry": {"coordinates":[-4.013887,51.669453],"type":"Point"}
}