{
  "type": "Feature",
  "properties": {
    "addr:full":"63 Harpur Street Bedford Bedfordshire MK40 2SR",
    "addr:housenumber":"63",
    "addr:postcode":"mk40 2sr",
    "addr:street":"Harpur Street",
    "iso:country":"GB",
    "sg:address":"63 Harpur Street",
    "sg:city":"Bedford",
    "sg:classifiers":[
        {
            "category":"Professional",
            "subcategory":"Lawyer & Legal Services",
            "type":"Services"
        }
    ],
    "sg:phone":"+44 1234 218171",
    "sg:postcode":"MK40 2SR",
    "sg:province":"Bedfordshire",
    "sg:tags":[
        "solicitor"
    ],
    "wof:name":"Cowley Di Giorgio",
    "wof:placetype":"venue"
},
  "geometry": {"coordinates":[-0.4685139954,52.1393241882],"type":"Point"}
}