{
  "type": "Feature",
  "properties": {
    "iso:country":"GB",
    "sg:address":"Lichfield Rd",
    "sg:city":"Rugeley",
    "sg:classifiers":[
        {
            "category":"Retail",
            "subcategory":"Auto Repair",
            "type":"Services"
        }
    ],
    "sg:postcode":"WS15 4DE",
    "sg:province":"Staffordshire",
    "sg:tags":[
        "modification",
        "garage"
    ],
    "wof:name":"Smith,S S,",
    "wof:placetype":"venue"
},
  "geometry": {"coordinates":[-1.866319,52.738041],"type":"Point"}
}