{
  "type": "Feature",
  "properties": {
    "addr:full":"14a George Street Tamworth Staffordshire B79 7LN",
    "addr:housenumber":"14a",
    "addr:postcode":"b79 7ln",
    "addr:street":"George Street",
    "iso:country":"GB",
    "sg:address":"14a George Street",
    "sg:city":"Tamworth",
    "sg:classifiers":[
        {
            "category":"Food & Beverages",
            "subcategory":"Specialty",
            "type":"Retail Goods"
        }
    ],
    "sg:phone":"+44 1827 65891",
    "sg:postcode":"B79 7LN",
    "sg:province":"Staffordshire",
    "sg:tags":[
        "retailer",
        "product",
        "health"
    ],
    "wof:name":"Holland & Barrett Ltd",
    "wof:placetype":"venue"
},
  "geometry": {"coordinates":[-1.693874,52.63303],"type":"Point"}
}