{
  "type": "Feature",
  "properties": {
    "addr:full":"Quadrant House, 80-82 Regent Street London Greater London W1B 5RP",
    "addr:housenumber":"80-82",
    "addr:postcode":"w1b 5rp",
    "addr:street":"Regent Street",
    "iso:country":"GB",
    "sg:address":"Quadrant House, 80-82 Regent Street",
    "sg:city":"London",
    "sg:classifiers":[
        {
            "category":"Professional",
            "subcategory":"Management & Consulting",
            "type":"Services"
        }
    ],
    "sg:phone":"+44 20 7304 4646",
    "sg:postcode":"W1B 5RP",
    "sg:province":"Greater London",
    "sg:tags":[
        "consultant",
        "business"
    ],
    "wof:name":"Willott Kingston Smith",
    "wof:placetype":"venue"
},
  "geometry": {"coordinates":[-0.1368030012,51.5100059509],"type":"Point"}
}