{
  "type": "Feature",
  "properties": {
    "iso:country":"GB",
    "sg:address":"Warwick Flats, Granby Drive, Bottesford",
    "sg:city":"Nottingham",
    "sg:classifiers":[
        {
            "category":"Government",
            "subcategory":"Office",
            "type":"Public Place"
        },
        {
            "category":"Social Services",
            "subcategory":"Adult Care",
            "type":"Services"
        },
        {
            "category":"Social Services",
            "subcategory":"Retirement Home",
            "type":"Services"
        }
    ],
    "sg:phone":"+44 1949 842334",
    "sg:postcode":"NG13 0BU",
    "sg:province":"Leicestershire",
    "sg:tags":[
        "housing",
        "local",
        "accommodation",
        "sheltered"
    ],
    "wof:name":"Warwick Flats Sheltered Housing",
    "wof:placetype":"venue"
},
  "geometry": {"coordinates":[-0.805259,52.939758],"type":"Point"}
}