{
  "type": "Feature",
  "properties": {
    "addr:full":"93-95 Marsden Rd Blackpool Lancashire FY4 3BY",
    "addr:housenumber":"93-95",
    "addr:postcode":"fy4 3by",
    "addr:street":"Marsden Rd",
    "iso:country":"GB",
    "sg:address":"93-95 Marsden Rd",
    "sg:city":"Blackpool",
    "sg:classifiers":[
        {
            "category":"Food & Beverages",
            "subcategory":"Fruits & Vegetables",
            "type":"Retail Goods"
        }
    ],
    "sg:postcode":"FY4 3BY",
    "sg:province":"Lancashire",
    "sg:tags":[
        "greengrocer"
    ],
    "wof:name":"Horrlicks,Marion,",
    "wof:placetype":"venue"
},
  "geometry": {"coordinates":[-3.037197113,53.7969741821],"type":"Point"}
}