{
  "type": "Feature",
  "properties": {
    "addr:full":"15 Newlands Avenue Southampton Hampshire SO15 5EP",
    "addr:housenumber":"15",
    "addr:postcode":"so15 5ep",
    "addr:street":"Newlands Avenue",
    "iso:country":"GB",
    "sg:address":"15 Newlands Avenue",
    "sg:city":"Southampton",
    "sg:classifiers":[
        {
            "category":"Health Services",
            "subcategory":"Dentist",
            "type":"Services"
        }
    ],
    "sg:phone":"+44 23 8077 1331",
    "sg:postcode":"SO15 5EP",
    "sg:province":"Hampshire",
    "wof:name":"Dental Surgery",
    "wof:placetype":"venue"
},
  "geometry": {"coordinates":[-1.425709,50.917889],"type":"Point"}
}