{
  "type": "Feature",
  "properties": {
    "addr:full":"26 Berridges Lane, Husbands Bosworth Lutterworth Leicestershire LE17 6LE",
    "addr:housenumber":"26",
    "addr:postcode":"le17 6le",
    "addr:street":"Berridges Lane",
    "iso:country":"GB",
    "sg:address":"26 Berridges Lane, Husbands Bosworth",
    "sg:city":"Lutterworth",
    "sg:classifiers":[
        {
            "category":"Health Services",
            "subcategory":"Nursing And Care Facility",
            "type":"Services"
        }
    ],
    "sg:phone":"+44 1858 880538",
    "sg:postcode":"LE17 6LE",
    "sg:province":"Leicestershire",
    "sg:tags":[
        "home"
    ],
    "wof:name":"Hunters Lodge Residential Home For Learning Disabiabled",
    "wof:placetype":"venue"
},
  "geometry": {"coordinates":[-1.057184,52.45488],"type":"Point"}
}