{
  "type": "Feature",
  "properties": {
    "iso:country":"GB",
    "sg:address":"St Hughs Av",
    "sg:city":"Cleethorpes",
    "sg:classifiers":[
        {
            "category":"Government",
            "subcategory":"Office",
            "type":"Public Place"
        }
    ],
    "sg:phone":"+44 1472 324866",
    "sg:postcode":"DN35 8ED",
    "sg:province":"Lincolnshire",
    "sg:tags":[
        "marriage",
        "death",
        "births"
    ],
    "wof:name":"Registration Of Births Deaths & Marriages",
    "wof:placetype":"venue"
},
  "geometry": {"coordinates":[-0.0395539999,53.5589599609],"type":"Point"}
}