{
  "type": "Feature",
  "properties": {
    "iso:country":"GB",
    "sg:address":"29 St Evox Close, Rownhams",
    "sg:city":"Southampton",
    "sg:classifiers":[
        {
            "category":"Professional",
            "subcategory":"Secretarial Services",
            "type":"Services"
        }
    ],
    "sg:postcode":"SO16 8FS",
    "sg:province":"Hampshire",
    "wof:name":"The Bidey Bureau",
    "wof:placetype":"venue"
},
  "geometry": {"coordinates":[-1.452263,50.945778],"type":"Point"}
}