{
  "type": "Feature",
  "properties": {
    "iso:country":"GB",
    "sg:address":"Bank Lane, Warton",
    "sg:city":"Preston",
    "sg:classifiers":[
        {
            "category":"Food & Beverages",
            "subcategory":"Supermarket",
            "type":"Retail Goods"
        },
        {
            "category":"Food & Beverages",
            "subcategory":"Fruits & Vegetables",
            "type":"Retail Goods"
        }
    ],
    "sg:postcode":"PR4 1TB",
    "sg:province":"Lancashire",
    "sg:tags":[
        "greengrocer"
    ],
    "wof:name":"Philip Goodwin",
    "wof:placetype":"venue"
},
  "geometry": {"coordinates":[-2.9033,53.74596],"type":"Point"}
}