{
  "type": "Feature",
  "properties": {
    "addr:full":"Apsley Rd Oxford Oxfordshire OX2 7QX",
    "addr:postcode":"ox2 7qx",
    "addr:street":"Apsley Rd",
    "iso:country":"GB",
    "sg:address":"Apsley Rd",
    "sg:city":"Oxford",
    "sg:classifiers":[
        {
            "category":"Farming",
            "subcategory":"Nursery",
            "type":"Manufacturing & Wholesale Goods"
        }
    ],
    "sg:phone":"+44 1865 511237",
    "sg:postcode":"OX2 7QX",
    "sg:province":"Oxfordshire",
    "sg:tags":[
        "creche"
    ],
    "wof:name":"Mansion House Nursery",
    "wof:placetype":"venue"
},
  "geometry": {"coordinates":[-1.2711490393,51.7843551636],"type":"Point"}
}