{
  "type": "Feature",
  "properties": {
    "addr:full":"41 Lincoln Road, Welton Lincoln Lincolnshire LN2 3JA",
    "addr:housenumber":"41",
    "addr:postcode":"ln2 3ja",
    "addr:street":"Lincoln Road",
    "iso:country":"GB",
    "sg:address":"41 Lincoln Road, Welton",
    "sg:city":"Lincoln",
    "sg:classifiers":[
        {
            "category":"Building & Trades",
            "subcategory":"Construction",
            "type":"Services"
        }
    ],
    "sg:postcode":"LN2 3JA",
    "sg:province":"Lincolnshire",
    "sg:tags":[
        "decorator",
        "painter"
    ],
    "wof:name":"Barry J Davis",
    "wof:placetype":"venue"
},
  "geometry": {"coordinates":[-0.4698089957,53.2974662781],"type":"Point"}
}