{
  "type": "Feature",
  "properties": {
    "addr:full":"3 Kingswood Creek, Wraysbery Staines Berkshire TW19 5EN",
    "addr:housenumber":"3",
    "addr:postcode":"tw19 5en",
    "addr:street":"Kingswood Creek Wraysbery",
    "iso:country":"GB",
    "sg:address":"3 Kingswood Creek, Wraysbery",
    "sg:city":"Staines",
    "sg:classifiers":[
        {
            "category":"Professional",
            "subcategory":"Management & Consulting",
            "type":"Services"
        }
    ],
    "sg:postcode":"TW19 5EN",
    "sg:province":"Berkshire",
    "sg:tags":[
        "marketing",
        "consultant"
    ],
    "wof:name":"Philip Shefras Ltd.",
    "wof:placetype":"venue"
},
  "geometry": {"coordinates":[-0.567508,51.461468],"type":"Point"}
}