{
  "type": "Feature",
  "properties": {
    "addr:full":"The Atrium Court, Appex Plaza, Forbury Road Reading Berkshire RG1 1AX",
    "addr:postcode":"rg1 1ax",
    "addr:street":"Plaza Forbury Road",
    "iso:country":"GB",
    "sg:address":"The Atrium Court, Appex Plaza, Forbury Road",
    "sg:city":"Reading",
    "sg:classifiers":[
        {
            "category":"Professional",
            "subcategory":"Computer Services",
            "type":"Services"
        }
    ],
    "sg:phone":"+44 118 956 7150",
    "sg:postcode":"RG1 1AX",
    "sg:province":"Berkshire",
    "sg:tags":[
        "system",
        "software"
    ],
    "wof:name":"Restrac Inc",
    "wof:placetype":"venue"
},
  "geometry": {"coordinates":[-0.9630089998,51.4535217285],"type":"Point"}
}