{
  "type": "Feature",
  "properties": {
    "addr:full":"122 Hart Road Benfleet Essex SS7 3PS",
    "addr:housenumber":"122",
    "addr:postcode":"ss7 3ps",
    "addr:street":"Hart Road",
    "iso:country":"GB",
    "sg:address":"122 Hart Road",
    "sg:city":"Benfleet",
    "sg:classifiers":[
        {
            "category":"Food & Beverages",
            "subcategory":"Meat & Fish",
            "type":"Retail Goods"
        }
    ],
    "sg:postcode":"SS7 3PS",
    "sg:province":"Essex",
    "sg:tags":[
        "butcher"
    ],
    "wof:name":"M & J Berrett",
    "wof:placetype":"venue"
},
  "geometry": {"coordinates":[0.583401978,51.5698547363],"type":"Point"}
}