{
  "type": "Feature",
  "properties": {
    "addr:full":"Park Valley Mills, Meltham Road, Lockwood Huddersfield West Yorkshire HD4 7BH",
    "addr:postcode":"hd4 7bh",
    "addr:street":"Park Valley;Meltham Road;West",
    "iso:country":"GB",
    "sg:address":"Park Valley Mills, Meltham Road, Lockwood",
    "sg:city":"Huddersfield",
    "sg:classifiers":[
        {
            "category":"Manufacturing",
            "subcategory":"Textiles",
            "type":"Manufacturing & Wholesale Goods"
        }
    ],
    "sg:phone":"+44 1484 668400",
    "sg:postcode":"HD4 7BH",
    "sg:province":"West Yorkshire",
    "sg:tags":[
        "dyer"
    ],
    "wof:name":"Paul Speak Fabrics Ltd.",
    "wof:placetype":"venue"
},
  "geometry": {"coordinates":[-1.795279,53.61956],"type":"Point"}
}