{
  "type": "Feature",
  "properties": {
    "iso:country":"GB",
    "sg:address":"Hithercroft Industrial Estate, Moreton Avenue",
    "sg:city":"Wallingford",
    "sg:classifiers":[
        {
            "category":"Manufacturing",
            "subcategory":"Chemicals & Compounds",
            "type":"Manufacturing & Wholesale Goods"
        }
    ],
    "sg:phone":"+44 1737 221761",
    "sg:postcode":"OX10 9DE",
    "sg:province":"Oxfordshire",
    "sg:tags":[
        "pesticide"
    ],
    "wof:name":"Norsan Kemi (U K) Ltd.",
    "wof:placetype":"venue"
},
  "geometry": {"coordinates":[-1.1256229877,51.6009101868],"type":"Point"}
}