{
  "type": "Feature",
  "properties": {
    "addr:full":"60 Cannons Street London Greater London EC4N 6JP",
    "addr:housenumber":"60",
    "addr:postcode":"ec4n 6jp",
    "addr:street":"Cannons Street",
    "iso:country":"GB",
    "sg:address":"60 Cannons Street",
    "sg:city":"London",
    "sg:classifiers":[
        {
            "category":"Manufacturing",
            "subcategory":"Wood Products",
            "type":"Manufacturing & Wholesale Goods"
        }
    ],
    "sg:phone":"+44 20 7653 3300",
    "sg:postcode":"EC4N 6JP",
    "sg:province":"Greater London",
    "sg:tags":[
        "packaging",
        "crate",
        "pallets"
    ],
    "wof:name":"A P I Group Plc",
    "wof:placetype":"venue"
},
  "geometry": {"coordinates":[-0.0923599973,51.5117988586],"type":"Point"}
}