{
  "type": "Feature",
  "properties": {
    "addr:full":"104 Cambridge Street Coventry West Midlands CV1 5HW",
    "addr:housenumber":"104",
    "addr:postcode":"cv1 5hw",
    "addr:street":"Cambridge Street",
    "iso:country":"GB",
    "sg:address":"104 Cambridge Street",
    "sg:city":"Coventry",
    "sg:classifiers":[
        {
            "category":"Shopping",
            "subcategory":"Clothing, Apparel, & Fashions",
            "type":"Retail Goods"
        }
    ],
    "sg:phone":"+44 24 7652 5995",
    "sg:postcode":"CV1 5HW",
    "sg:province":"West Midlands",
    "sg:tags":[
        "clothing"
    ],
    "wof:name":"Unique Clothing",
    "wof:placetype":"venue"
},
  "geometry": {"coordinates":[-1.497992,52.417702],"type":"Point"}
}