{
  "type": "Feature",
  "properties": {
    "iso:country":"GB",
    "sg:address":"61 Copley Road",
    "sg:city":"Doncaster",
    "sg:classifiers":[
        {
            "category":"Home & Garden",
            "subcategory":"Hardware",
            "type":"Retail Goods"
        }
    ],
    "sg:phone":"+44 1302 811163",
    "sg:postcode":"DN1 2QP",
    "sg:province":"South Yorkshire",
    "sg:tags":[
        "retailer",
        "diy"
    ],
    "wof:name":"Timber & Things",
    "wof:placetype":"venue"
},
  "geometry": {"coordinates":[-1.128336,53.526783],"type":"Point"}
}