{
  "type": "Feature",
  "properties": {
    "addr:full":"Unit 4, Mark Way Swanley Kent BR8 8NJ",
    "addr:housenumber":"unit 4",
    "addr:postcode":"br8 8nj",
    "addr:street":"Mark Way",
    "iso:country":"GB",
    "sg:address":"Unit 4, Mark Way",
    "sg:city":"Swanley",
    "sg:classifiers":[
        {
            "category":"Building & Trades",
            "subcategory":"Construction",
            "type":"Services"
        }
    ],
    "sg:phone":"+44 1322 669731",
    "sg:postcode":"BR8 8NJ",
    "sg:province":"Kent",
    "sg:tags":[
        "window",
        "replacement"
    ],
    "wof:name":"Anglian Home Improvements",
    "wof:placetype":"venue"
},
  "geometry": {"coordinates":[0.188076,51.388283],"type":"Point"}
}