{
  "type": "Feature",
  "properties": {
    "addr:full":"Bigws, Woodstock, Clarbeston Road Haverfordwest Pembrokeshire SA63 4TH",
    "addr:postcode":"sa63 4th",
    "addr:street":"Clarbeston Road",
    "iso:country":"GB",
    "sg:address":"Bigws, Woodstock, Clarbeston Road",
    "sg:city":"Haverfordwest",
    "sg:classifiers":[
        {
            "category":"Farming",
            "subcategory":"Livestock Farm",
            "type":"Manufacturing & Wholesale Goods"
        }
    ],
    "sg:phone":"+44 1437 731431",
    "sg:postcode":"SA63 4TH",
    "sg:province":"Pembrokeshire",
    "sg:tags":[
        "others"
    ],
    "wof:name":"S H & A E M Smith",
    "wof:placetype":"venue"
},
  "geometry": {"coordinates":[-4.8694901466,51.9012107849],"type":"Point"}
}