{
  "type": "Feature",
  "properties": {
    "addr:full":"Unit 5 Tinsley Shopping Centre, Bawtry Road Sheffield South Yorkshire S9 1UY",
    "addr:housenumber":"unit 5",
    "addr:postcode":"s9 1uy",
    "addr:street":"Tinsley Shopping;Bawtry Road",
    "iso:country":"GB",
    "sg:address":"Unit 5 Tinsley Shopping Centre, Bawtry Road",
    "sg:city":"Sheffield",
    "sg:classifiers":[
        {
            "category":"Banks & Credit Unions",
            "subcategory":"Financial Services",
            "type":"Services"
        }
    ],
    "sg:phone":"+44 1226 765929",
    "sg:postcode":"S9 1UY",
    "sg:province":"South Yorkshire",
    "sg:tags":[
        "consultant"
    ],
    "wof:name":"M J M Finance",
    "wof:placetype":"venue"
},
  "geometry": {"coordinates":[-1.3961600065,53.4116592407],"type":"Point"}
}