{
  "type": "Feature",
  "properties": {
    "iso:country":"GB",
    "sg:address":"356 St. Pauls Rd",
    "sg:city":"Smethwick",
    "sg:classifiers":[
        {
            "category":"Utilities",
            "subcategory":"Mobile Phone",
            "type":"Services"
        }
    ],
    "sg:phone":"+44 121 558 2991",
    "sg:postcode":"B66 1EU",
    "sg:province":"West Midlands",
    "sg:tags":[
        "battery",
        "supplier"
    ],
    "wof:name":"MBD Group Ltd",
    "wof:placetype":"venue"
},
  "geometry": {"coordinates":[-1.980072,52.499596],"type":"Point"}
}