{
  "type": "Feature",
  "properties": {
    "iso:country":"GB",
    "sg:address":"122 Clay Lane",
    "sg:city":"Coventry",
    "sg:classifiers":[
        {
            "category":"Cinema",
            "subcategory":"Movie Rental",
            "type":"Entertainment"
        }
    ],
    "sg:phone":"+44 24 7645 4430",
    "sg:postcode":"CV2 4LT",
    "sg:province":"Warwickshire",
    "sg:tags":[
        "video",
        "library"
    ],
    "wof:name":"Raja Videos",
    "wof:placetype":"venue"
},
  "geometry": {"coordinates":[-1.4827309847,52.4136428833],"type":"Point"}
}