{
  "type": "Feature",
  "properties": {
    "iso:country":"GB",
    "sg:address":"12 Edwin Road",
    "sg:city":"Didcot",
    "sg:classifiers":[
        {
            "category":"Building & Trades",
            "subcategory":"Construction",
            "type":"Services"
        }
    ],
    "sg:phone":"+44 1235 812658",
    "sg:postcode":"OX11 8LE",
    "sg:province":"Oxfordshire",
    "sg:tags":[
        "glazier"
    ],
    "wof:name":"North Berks Glass",
    "wof:placetype":"venue"
},
  "geometry": {"coordinates":[-1.255587,51.598385],"type":"Point"}
}