{
  "type": "Feature",
  "properties": {
    "addr:full":"25 Sefton Avenue, Mill Hill London Greater London NW7 3QB",
    "addr:housenumber":"25",
    "addr:postcode":"nw7 3qb",
    "addr:street":"Sefton Avenue",
    "iso:country":"GB",
    "sg:address":"25 Sefton Avenue, Mill Hill",
    "sg:city":"London",
    "sg:classifiers":[
        {
            "category":"Retail",
            "subcategory":"Storage",
            "type":"Services"
        }
    ],
    "sg:phone":"+44 20 8959 2865",
    "sg:postcode":"NW7 3QB",
    "sg:province":"Greater London",
    "sg:tags":[
        "household",
        "removal"
    ],
    "wof:name":"T & M Services Removals",
    "wof:placetype":"venue"
},
  "geometry": {"coordinates":[-0.2601140141,51.6145210266],"type":"Point"}
}