{
  "type": "Feature",
  "properties": {
    "addr:full":"139 Silverdale Road Tunbridge Wells Kent TN4 9HX",
    "addr:housenumber":"139",
    "addr:postcode":"tn4 9hx",
    "addr:street":"Silverdale Road",
    "iso:country":"GB",
    "sg:address":"139 Silverdale Road",
    "sg:city":"Tunbridge Wells",
    "sg:classifiers":[
        {
            "category":"Professional",
            "subcategory":"Engineering",
            "type":"Services"
        }
    ],
    "sg:phone":"+44 1892 549600",
    "sg:postcode":"TN4 9HX",
    "sg:province":"Kent",
    "sg:tags":[
        "precision",
        "engineer"
    ],
    "wof:name":"F R M Precision Engineers Ltd.",
    "wof:placetype":"venue"
},
  "geometry": {"coordinates":[0.2718990147,51.1467399597],"type":"Point"}
}