{
  "type": "Feature",
  "properties": {
    "addr:full":"Tynewdd, Rhiw Road, Munythd Pwllheli Gwynedd LL53 7SN",
    "addr:postcode":"ll53 7sn",
    "addr:street":"Tynewdd Rhiw Road Munythd Pwllheli",
    "iso:country":"GB",
    "sg:address":"Tynewdd, Rhiw Road, Munythd",
    "sg:city":"Pwllheli",
    "sg:classifiers":[
        {
            "category":"Freight",
            "type":"Transportation"
        },
        {
            "category":"Building & Trades",
            "subcategory":"Construction",
            "type":"Services"
        }
    ],
    "sg:phone":"+44 1758 730710",
    "sg:postcode":"LL53 7SN",
    "sg:province":"Gwynedd",
    "sg:tags":[
        "haulage",
        "builder",
        "transport",
        "road"
    ],
    "wof:name":"Dylan Vaughan Evans",
    "wof:placetype":"venue"
},
  "geometry": {"coordinates":[-4.54276,52.84547],"type":"Point"}
}