{
  "type": "Feature",
  "properties": {
    "addr:full":"492 Lady Margaret Road Southall Greater London UB1 2QD",
    "addr:housenumber":"492",
    "addr:postcode":"ub1 2qd",
    "addr:street":"Lady Margaret Road",
    "iso:country":"GB",
    "sg:address":"492 Lady Margaret Road",
    "sg:city":"Southall",
    "sg:classifiers":[
        {
            "category":"Wholesale",
            "subcategory":"Furniture",
            "type":"Manufacturing & Wholesale Goods"
        }
    ],
    "sg:phone":"+44 20 8575 1589",
    "sg:postcode":"UB1 2QD",
    "sg:province":"Greater London",
    "sg:tags":[
        "shop",
        "fitting"
    ],
    "wof:name":"Walton Wilson Shop Equipment",
    "wof:placetype":"venue"
},
  "geometry": {"coordinates":[-0.372068,51.530178],"type":"Point"}
}