{
  "type": "Feature",
  "properties": {
    "iso:country":"GB",
    "sg:address":"Sprowston Road",
    "sg:city":"Norwich",
    "sg:classifiers":[
        {
            "category":"Education",
            "subcategory":"Library",
            "type":"Public Place"
        },
        {
            "category":"Government",
            "subcategory":"Office",
            "type":"Public Place"
        }
    ],
    "sg:phone":"+44 1603 425452",
    "sg:postcode":"NR3 4HZ",
    "sg:province":"Norfolk",
    "sg:tags":[
        "book",
        "local"
    ],
    "wof:name":"NORFOLK COUNTY COUNCIL",
    "wof:placetype":"venue"
},
  "geometry": {"coordinates":[1.310305,52.651508],"type":"Point"}
}