{
  "type": "Feature",
  "properties": {
    "addr:full":"70 Guildford Street Chertsey Surrey KT16 9BB",
    "addr:housenumber":"70",
    "addr:postcode":"kt16 9bb",
    "addr:street":"Guildford Street",
    "iso:country":"GB",
    "sg:address":"70 Guildford Street",
    "sg:city":"Chertsey",
    "sg:classifiers":[
        {
            "category":"Professional",
            "subcategory":"Printing & Photocopies",
            "type":"Services"
        }
    ],
    "sg:postcode":"KT16 9BB",
    "sg:province":"Surrey",
    "sg:tags":[
        "printer"
    ],
    "wof:name":"Abbey Green Printers Ltd.",
    "wof:placetype":"venue"
},
  "geometry": {"coordinates":[-0.5052559972,51.3899612427],"type":"Point"}
}