{
  "type": "Feature",
  "properties": {
    "addr:full":"54 Oxgangs Avenue Edinburgh City of Edinburgh EH13 9JP",
    "addr:housenumber":"54",
    "addr:postcode":"eh13 9jp",
    "addr:street":"Oxgangs Avenue Edinburgh",
    "iso:country":"GB",
    "sg:address":"54 Oxgangs Avenue",
    "sg:city":"Edinburgh",
    "sg:classifiers":[
        {
            "category":"Social Services",
            "subcategory":"Child Care",
            "type":"Services"
        }
    ],
    "sg:phone":"+44 131 447 7971",
    "sg:postcode":"EH13 9JP",
    "sg:province":"City of Edinburgh",
    "sg:tags":[
        "children's",
        "home"
    ],
    "wof:name":"Oxgangs Children & Young People's Centre",
    "wof:placetype":"venue"
},
  "geometry": {"coordinates":[-3.2182838917,55.9123840332],"type":"Point"}
}