{
  "type": "Feature",
  "properties": {
    "addr:full":"7o-72 Quay Side Road, Bitterne Manor Southampton Hampshire SO18 1AD",
    "addr:postcode":"so18 1ad",
    "addr:street":"7O-72 Quay Side Road",
    "iso:country":"GB",
    "sg:address":"7o-72 Quay Side Road, Bitterne Manor",
    "sg:city":"Southampton",
    "sg:classifiers":[
        {
            "category":"Manufacturing",
            "subcategory":"Tools & Machinery",
            "type":"Manufacturing & Wholesale Goods"
        },
        {
            "category":"Social Services",
            "subcategory":"Job Training",
            "type":"Services"
        }
    ],
    "sg:phone":"+44 23 8063 9366",
    "sg:postcode":"SO18 1AD",
    "sg:province":"Hampshire",
    "sg:tags":[
        "equipment",
        "engineering",
        "marine",
        "manufacturer"
    ],
    "wof:name":"C J R Propulsion Ltd",
    "wof:placetype":"venue"
},
  "geometry": {"coordinates":[-1.3816460371,50.9166030884],"type":"Point"}
}