{
  "type": "Feature",
  "properties": {
    "iso:country":"GB",
    "sg:address":"1 Angelo Close",
    "sg:city":"Waterlooville",
    "sg:classifiers":[
        {
            "category":"Professional",
            "subcategory":"Management & Consulting",
            "type":"Services"
        }
    ],
    "sg:phone":"+44 23 9223 0978",
    "sg:postcode":"PO7 8JS",
    "sg:province":"Hampshire",
    "sg:tags":[
        "consultant",
        "business"
    ],
    "wof:name":"Impact Corporate Development",
    "wof:placetype":"venue"
},
  "geometry": {"coordinates":[-1.0141450167,50.8820877075],"type":"Point"}
}