{
  "type": "Feature",
  "properties": {
    "iso:country":"GB",
    "sg:address":"High Street",
    "sg:city":"Bangor",
    "sg:classifiers":[
        {
            "category":"Personal",
            "subcategory":"Beauty Salon",
            "type":"Services"
        }
    ],
    "sg:postcode":"LL57 3AY",
    "sg:province":"Gwynedd",
    "sg:tags":[
        "unisex",
        "hairdresser"
    ],
    "wof:name":"Siswrn Arian",
    "wof:placetype":"venue"
},
  "geometry": {"coordinates":[-4.062989,53.180511],"type":"Point"}
}