{
  "type": "Feature",
  "properties": {
    "addr:full":"7 Anworth Close Woodford Green Essex IG8 0DR",
    "addr:housenumber":"7",
    "addr:postcode":"ig8 0dr",
    "addr:street":"Anworth Close",
    "iso:country":"GB",
    "sg:address":"7 Anworth Close",
    "sg:city":"Woodford Green",
    "sg:classifiers":[
        {
            "category":"Autos & Motor Vehicles",
            "subcategory":"Motorcycle Sales",
            "type":"Retail Goods"
        }
    ],
    "sg:phone":"+44 20 8506 0298",
    "sg:postcode":"IG8 0DR",
    "sg:province":"Essex",
    "sg:tags":[
        "chauffeur",
        "driven",
        "car"
    ],
    "wof:name":"Scorpio Car Services",
    "wof:placetype":"venue"
},
  "geometry": {"coordinates":[0.0287999995,51.6070175171],"type":"Point"}
}