{
  "type": "Feature",
  "properties": {
    "addr:full":"17 St Lukes Road Southport Lancashire PR9 0SH",
    "addr:housenumber":"17",
    "addr:postcode":"pr9 0sh",
    "addr:street":"St Lukes Road",
    "iso:country":"GB",
    "sg:address":"17 St Lukes Road",
    "sg:city":"Southport",
    "sg:classifiers":[
        {
            "category":"Building & Trades",
            "subcategory":"Construction",
            "type":"Services"
        }
    ],
    "sg:phone":"+44 1704 535093",
    "sg:postcode":"PR9 0SH",
    "sg:province":"Lancashire",
    "sg:tags":[
        "double",
        "window",
        "glazing",
        "installers",
        "replacement"
    ],
    "wof:name":"Southport Window Company",
    "wof:placetype":"venue"
},
  "geometry": {"coordinates":[-2.9883139133,53.6448020935],"type":"Point"}
}