{
  "type": "Feature",
  "properties": {
    "addr:full":"60 Thistle St Edinburgh City of Edinburgh EH2 1EN",
    "addr:housenumber":"60",
    "addr:postcode":"eh2 1en",
    "addr:street":"Thistle St Edinburgh",
    "iso:country":"GB",
    "sg:address":"60 Thistle St",
    "sg:city":"Edinburgh",
    "sg:classifiers":[
        {
            "category":"Shopping",
            "subcategory":"Antiques",
            "type":"Retail Goods"
        }
    ],
    "sg:phone":"+44 131 220 3387",
    "sg:postcode":"EH2 1EN",
    "sg:province":"City of Edinburgh",
    "wof:name":"Laurance Black",
    "wof:placetype":"venue"
},
  "geometry": {"coordinates":[-3.1994099617,55.9538192749],"type":"Point"}
}