{
  "type": "Feature",
  "properties": {
    "addr:full":"Graylyn Mill Road, Walpole Highway Wisbech Cambridgeshire PE14 7QL",
    "addr:postcode":"pe14 7ql",
    "addr:street":"Graylyn Mill Road Walpole Highway",
    "iso:country":"GB",
    "sg:address":"Graylyn Mill Road, Walpole Highway",
    "sg:city":"Wisbech",
    "sg:classifiers":[
        {
            "category":"Retail",
            "subcategory":"Animal Services",
            "type":"Services"
        }
    ],
    "sg:phone":"+44 1945 780255",
    "sg:postcode":"PE14 7QL",
    "sg:province":"Cambridgeshire",
    "sg:tags":[
        "breeder",
        "livestock"
    ],
    "wof:name":"G G Jackson",
    "wof:placetype":"venue"
},
  "geometry": {"coordinates":[0.2445400059,52.7017784119],"type":"Point"}
}