{
  "type": "Feature",
  "properties": {
    "iso:country":"GB",
    "sg:address":"1325 Ashton Old Road",
    "sg:city":"Manchester",
    "sg:classifiers":[
        {
            "category":"Food & Beverages",
            "subcategory":"Meat & Fish",
            "type":"Retail Goods"
        }
    ],
    "sg:phone":"+44 161 370 1993",
    "sg:postcode":"M11 1JT",
    "sg:province":"Greater Manchester",
    "sg:tags":[
        "butcher"
    ],
    "wof:name":"R Edwards",
    "wof:placetype":"venue"
},
  "geometry": {"coordinates":[-2.1620090008,53.4729423523],"type":"Point"}
}