{
  "type": "Feature",
  "properties": {
    "iso:country":"GB",
    "sg:address":"158 Abbots Way, Preston Farm",
    "sg:city":"North Shields",
    "sg:classifiers":[
        {
            "category":"Real Estate",
            "subcategory":"Real Estate Agent",
            "type":"Services"
        }
    ],
    "sg:phone":"+44 191 257 3837",
    "sg:postcode":"NE29 8LY",
    "sg:province":"Tyne and Wear",
    "wof:name":"Pendlecroft Ltd.",
    "wof:placetype":"venue"
},
  "geometry": {"coordinates":[-1.466241,55.022167],"type":"Point"}
}