{
  "type": "Feature",
  "properties": {
    "addr:full":"47 Bonet Lane Rotherham South Yorkshire S60 5NE",
    "addr:housenumber":"47",
    "addr:postcode":"s60 5ne",
    "addr:street":"Bonet Lane",
    "iso:country":"GB",
    "sg:address":"47 Bonet Lane",
    "sg:city":"Rotherham",
    "sg:classifiers":[
        {
            "category":"Building & Trades",
            "subcategory":"Plumbing",
            "type":"Services"
        }
    ],
    "sg:phone":"+44 1709 366983",
    "sg:postcode":"S60 5NE",
    "sg:province":"South Yorkshire",
    "sg:tags":[
        "heating"
    ],
    "wof:name":"M Gulliver",
    "wof:placetype":"venue"
},
  "geometry": {"coordinates":[-1.3778330088,53.4062538147],"type":"Point"}
}