{
  "type": "Feature",
  "properties": {
    "addr:full":"16 Royalist Drive Norwich Norfolk NR7 0YN",
    "addr:housenumber":"16",
    "addr:postcode":"nr7 0yn",
    "addr:street":"Royalist Drive",
    "iso:country":"GB",
    "sg:address":"16 Royalist Drive",
    "sg:city":"Norwich",
    "sg:classifiers":[
        {
            "category":"Home & Garden",
            "subcategory":"Carpets & Floor Coverings",
            "type":"Retail Goods"
        }
    ],
    "sg:postcode":"NR7 0YN",
    "sg:province":"Norfolk",
    "sg:tags":[
        "carpets",
        "rug",
        "matting"
    ],
    "wof:name":"Chris Laws Carpets",
    "wof:placetype":"venue"
},
  "geometry": {"coordinates":[1.3650130033,52.6341323853],"type":"Point"}
}