{
  "type": "Feature",
  "properties": {
    "addr:full":"6 Gibb Street, Long Eaton Nottingham Derbyshire NG10 1EE",
    "addr:housenumber":"6",
    "addr:postcode":"ng10 1ee",
    "addr:street":"Gibb Street",
    "iso:country":"GB",
    "sg:address":"6 Gibb Street, Long Eaton",
    "sg:city":"Nottingham",
    "sg:classifiers":[
        {
            "category":"Shopping",
            "subcategory":"Clothing, Apparel, & Fashions",
            "type":"Retail Goods"
        }
    ],
    "sg:phone":"+44 115 973 4090",
    "sg:postcode":"NG10 1EE",
    "sg:province":"Derbyshire",
    "sg:tags":[
        "dresswear"
    ],
    "wof:name":"Manns Menswear",
    "wof:placetype":"venue"
},
  "geometry": {"coordinates":[-1.2688560486,52.8964767456],"type":"Point"}
}