{
  "type": "Feature",
  "properties": {
    "addr:full":"635 Newport Road, Rumney Cardiff Caerphilly CF3 4FB",
    "addr:housenumber":"635",
    "addr:postcode":"cf3 4fb",
    "addr:street":"Newport Road",
    "iso:country":"GB",
    "sg:address":"635 Newport Road, Rumney",
    "sg:city":"Cardiff",
    "sg:classifiers":[
        {
            "category":"Restaurant",
            "type":"Food & Drink"
        }
    ],
    "sg:phone":"+44 29 2077 9911",
    "sg:postcode":"CF3 4FB",
    "sg:province":"Caerphilly",
    "wof:name":"Morgans",
    "wof:placetype":"venue"
},
  "geometry": {"coordinates":[-3.1378269196,51.5039405823],"type":"Point"}
}