{
  "type": "Feature",
  "properties": {
    "iso:country":"GB",
    "sg:address":"9 Northumberland Avenue",
    "sg:city":"Holborn",
    "sg:classifiers":[
        {
            "category":"Organizations",
            "subcategory":"Non-profit Organization",
            "type":"Services"
        }
    ],
    "sg:phone":"+44 20 7976 1493",
    "sg:postcode":"WC2N 5BW",
    "sg:province":"Greater London",
    "sg:tags":[
        "organisation",
        "voluntary",
        "charity"
    ],
    "wof:name":"The West India Committee",
    "wof:placetype":"venue"
},
  "geometry": {"coordinates":[-0.122912,51.506744],"type":"Point"}
}