{
  "type": "Feature",
  "properties": {
    "addr:full":"1 Hampstead High Street London Greater London NW3 1PR",
    "addr:housenumber":"1",
    "addr:postcode":"nw3 1pr",
    "addr:street":"Hampstead High Street",
    "iso:country":"GB",
    "sg:address":"1 Hampstead High Street",
    "sg:city":"London",
    "sg:classifiers":[
        {
            "category":"Shopping",
            "subcategory":"Clothing, Apparel, & Fashions",
            "type":"Retail Goods"
        }
    ],
    "sg:phone":"+44 20 7435 1726",
    "sg:postcode":"NW3 1PR",
    "sg:province":"Greater London",
    "sg:tags":[
        "shop",
        "accessory"
    ],
    "wof:name":"Monsoon Fashions",
    "wof:placetype":"venue"
},
  "geometry": {"coordinates":[-0.1752900034,51.5555686951],"type":"Point"}
}