{
  "type": "Feature",
  "properties": {
    "addr:full":"Lingfield Rd Edenbridge East Sussex TN8 5DR",
    "addr:postcode":"tn8 5dr",
    "addr:street":"Lingfield Rd",
    "iso:country":"GB",
    "sg:address":"Lingfield Rd",
    "sg:city":"Edenbridge",
    "sg:classifiers":[
        {
            "category":"Cafe",
            "type":"Food & Drink"
        }
    ],
    "sg:postcode":"TN8 5DR",
    "sg:province":"East Sussex",
    "sg:tags":[
        "tea",
        "room"
    ],
    "wof:name":"The Kabin Kitchens",
    "wof:placetype":"venue"
},
  "geometry": {"coordinates":[0.06465,51.196404],"type":"Point"}
}