{
  "type": "Feature",
  "properties": {
    "addr:full":"59 Southmoor Lane, Armthorpe Doncaster South Yorkshire DN3 3TQ",
    "addr:housenumber":"59",
    "addr:postcode":"dn3 3tq",
    "addr:street":"Southmoor Lane",
    "iso:country":"GB",
    "sg:address":"59 Southmoor Lane, Armthorpe",
    "sg:city":"Doncaster",
    "sg:classifiers":[
        {
            "category":"Real Estate",
            "subcategory":"Architect",
            "type":"Services"
        }
    ],
    "sg:postcode":"DN3 3TQ",
    "sg:province":"South Yorkshire",
    "wof:name":"C & M Associates Ltd.",
    "wof:placetype":"venue"
},
  "geometry": {"coordinates":[-1.0628839731,53.531539917],"type":"Point"}
}