{
  "type": "Feature",
  "properties": {
    "addr:full":"3 Bare Lane Morecambe Lancashire LA4 6DE",
    "addr:housenumber":"3",
    "addr:postcode":"la4 6de",
    "addr:street":"Bare Lane",
    "iso:country":"GB",
    "sg:address":"3 Bare Lane",
    "sg:city":"Morecambe",
    "sg:classifiers":[
        {
            "category":"Shopping",
            "subcategory":"News",
            "type":"Retail Goods"
        }
    ],
    "sg:phone":"+44 1524 410662",
    "sg:postcode":"LA4 6DE",
    "sg:province":"Lancashire",
    "sg:tags":[
        "newsagent"
    ],
    "wof:name":"Bare Lane News",
    "wof:placetype":"venue"
},
  "geometry": {"coordinates":[-2.8381800652,54.0775909424],"type":"Point"}
}