{
  "type": "Feature",
  "properties": {
    "addr:full":"13 Queens Hill Monmouth Gloucestershire NP25 4BE",
    "addr:housenumber":"13",
    "addr:postcode":"np25 4be",
    "addr:street":"Queens Hill",
    "iso:country":"GB",
    "sg:address":"13 Queens Hill",
    "sg:city":"Monmouth",
    "sg:classifiers":[
        {
            "category":"Government",
            "subcategory":"Post Office",
            "type":"Public Place"
        }
    ],
    "sg:phone":"+44 1600 740664",
    "sg:postcode":"NP25 4BE",
    "sg:province":"Gloucestershire",
    "wof:name":"Dingestow Post Office & Stores",
    "wof:placetype":"venue"
},
  "geometry": {"coordinates":[-2.7871830463,51.787815094],"type":"Point"}
}