{
  "type": "Feature",
  "properties": {
    "addr:full":"79 Preston Road Poole Dorset BH15 3EQ",
    "addr:housenumber":"79",
    "addr:postcode":"bh15 3eq",
    "addr:street":"Preston Road",
    "iso:country":"GB",
    "sg:address":"79 Preston Road",
    "sg:city":"Poole",
    "sg:classifiers":[
        {
            "category":"Professional",
            "subcategory":"Engineering",
            "type":"Services"
        },
        {
            "category":"Building & Trades",
            "subcategory":"Electrical",
            "type":"Services"
        }
    ],
    "sg:phone":"+44 1202 671268",
    "sg:postcode":"BH15 3EQ",
    "sg:province":"Dorset",
    "sg:tags":[
        "engineer",
        "electrician",
        "contractor"
    ],
    "wof:name":"Oakdale Electrical",
    "wof:placetype":"venue"
},
  "geometry": {"coordinates":[-1.983985,50.734982],"type":"Point"}
}