{
  "type": "Feature",
  "properties": {
    "addr:full":"Tyr-pwl Farm, Hardwick Abergavenny Herefordshire NP7 9AB",
    "addr:postcode":"np7 9ab",
    "iso:country":"GB",
    "sg:address":"Tyr-pwl Farm, Hardwick",
    "sg:city":"Abergavenny",
    "sg:classifiers":[
        {
            "category":"Farming",
            "subcategory":"Livestock Farm",
            "type":"Manufacturing & Wholesale Goods"
        }
    ],
    "sg:postcode":"NP7 9AB",
    "sg:province":"Herefordshire",
    "sg:tags":[
        "others"
    ],
    "wof:name":"E P Hunt",
    "wof:placetype":"venue"
},
  "geometry": {"coordinates":[-3.0014429092,51.7958564758],"type":"Point"}
}