{
  "type": "Feature",
  "properties": {
    "addr:full":"Sprucely Farm, Sedgefield Stockton-on-tees Durham TS21 2BD",
    "addr:postcode":"ts21 2bd",
    "addr:street":"Sedgefield",
    "iso:country":"GB",
    "sg:address":"Sprucely Farm, Sedgefield",
    "sg:city":"Stockton-on-tees",
    "sg:classifiers":[
        {
            "category":"Home & Garden",
            "subcategory":"Garden Supply",
            "type":"Retail Goods"
        }
    ],
    "sg:phone":"+44 1740 620378",
    "sg:postcode":"TS21 2BD",
    "sg:province":"Durham",
    "sg:tags":[
        "bulb",
        "grower"
    ],
    "wof:name":"S R & B A Harris",
    "wof:placetype":"venue"
},
  "geometry": {"coordinates":[-1.4639300108,54.673828125],"type":"Point"}
}