{
  "type": "Feature",
  "properties": {
    "addr:full":"Lewis Street Stranraer Dumfries and Galloway DG9 7AR",
    "addr:postcode":"dg9 7ar",
    "addr:street":"Lewis Street",
    "iso:country":"GB",
    "sg:address":"Lewis Street",
    "sg:city":"Stranraer",
    "sg:classifiers":[
        {
            "category":"Education",
            "subcategory":"School",
            "type":"Public Place"
        },
        {
            "category":"Government",
            "subcategory":"Office",
            "type":"Public Place"
        }
    ],
    "sg:phone":"+44 1776 703460",
    "sg:postcode":"DG9 7AR",
    "sg:province":"Dumfries and Galloway",
    "sg:tags":[
        "local",
        "authority"
    ],
    "wof:name":"St Joseph's R C Primary School",
    "wof:placetype":"venue"
},
  "geometry": {"coordinates":[-5.027234,54.903126],"type":"Point"}
}