{
  "type": "Feature",
  "properties": {
    "addr:full":"Westhill House Westhill Aberdeen City AB32 6YH",
    "addr:postcode":"ab32 6yh",
    "addr:street":"Westhill Aberdeen",
    "iso:country":"GB",
    "sg:address":"Westhill House",
    "sg:city":"Westhill",
    "sg:classifiers":[
        {
            "category":"Banks & Credit Unions",
            "subcategory":"Financial Services",
            "type":"Services"
        }
    ],
    "sg:phone":"+44 1224 747747",
    "sg:postcode":"AB32 6YH",
    "sg:province":"Aberdeen City",
    "sg:tags":[
        "adviser"
    ],
    "wof:name":"Douglas Will & Co",
    "wof:placetype":"venue"
},
  "geometry": {"coordinates":[-2.2926840782,57.1494445801],"type":"Point"}
}