{
  "type": "Feature",
  "properties": {
    "addr:full":"Unit 19, Mill House Lane Sowerby Bridge West Yorkshire HX6 3LN",
    "addr:housenumber":"unit 19",
    "addr:postcode":"hx6 3ln",
    "addr:street":"Mill House Lane",
    "iso:country":"GB",
    "sg:address":"Unit 19, Mill House Lane",
    "sg:city":"Sowerby Bridge",
    "sg:classifiers":[
        {
            "category":"Manufacturing",
            "subcategory":"Metals",
            "type":"Manufacturing & Wholesale Goods"
        }
    ],
    "sg:postcode":"HX6 3LN",
    "sg:province":"West Yorkshire",
    "sg:tags":[
        "steel",
        "stockholder"
    ],
    "wof:name":"Contracut",
    "wof:placetype":"venue"
},
  "geometry": {"coordinates":[-1.9139339924,53.7065391541],"type":"Point"}
}