{
  "type": "Feature",
  "properties": {
    "iso:country":"GB",
    "sg:address":"27 Studholme Av",
    "sg:city":"Preston",
    "sg:classifiers":[
        {
            "category":"Professional",
            "subcategory":"Engineering",
            "type":"Services"
        }
    ],
    "sg:phone":"+44 1772 745259",
    "sg:postcode":"PR1 9PA",
    "sg:province":"Lancashire",
    "sg:tags":[
        "contractor",
        "electrical",
        "engineer"
    ],
    "wof:name":"Roy Finney",
    "wof:placetype":"venue"
},
  "geometry": {"coordinates":[-2.707885,53.736423],"type":"Point"}
}