{
  "type": "Feature",
  "properties": {
    "addr:full":"Czar Street, Holbeck Leeds West Yorkshire LS11 9DG",
    "addr:postcode":"ls11 9dg",
    "addr:street":"Czar Street",
    "iso:country":"GB",
    "sg:address":"Czar Street, Holbeck",
    "sg:city":"Leeds",
    "sg:classifiers":[
        {
            "category":"Arts & Performance",
            "subcategory":"Theater",
            "type":"Entertainment"
        }
    ],
    "sg:postcode":"LS11 9DG",
    "sg:province":"West Yorkshire",
    "sg:tags":[
        "rehearsal",
        "studio",
        "facility"
    ],
    "wof:name":"Old Chapel Studios",
    "wof:placetype":"venue"
},
  "geometry": {"coordinates":[-1.5591939688,53.7881698608],"type":"Point"}
}