{
  "type": "Feature",
  "properties": {
    "addr:full":"43 Highgate High Street London Greater London N6 5JX",
    "addr:housenumber":"43",
    "addr:postcode":"n6 5jx",
    "addr:street":"Highgate High Street",
    "iso:country":"GB",
    "sg:address":"43 Highgate High Street",
    "sg:city":"London",
    "sg:classifiers":[
        {
            "category":"Shopping",
            "subcategory":"Pharmacy",
            "type":"Retail Goods"
        }
    ],
    "sg:phone":"+44 20 8347 6188",
    "sg:postcode":"N6 5JX",
    "sg:province":"Greater London",
    "sg:tags":[
        "medicine",
        "therapy"
    ],
    "wof:name":"Ming Imperial Herbal Medicine",
    "wof:placetype":"venue"
},
  "geometry": {"coordinates":[-0.14905,51.57095],"type":"Point"}
}