{
  "type": "Feature",
  "properties": {
    "addr:full":"22 Highwood Gro London Greater London NW7 3LY",
    "addr:housenumber":"22",
    "addr:postcode":"nw7 3ly",
    "addr:street":"Highwood Gro",
    "iso:country":"GB",
    "sg:address":"22 Highwood Gro",
    "sg:city":"London",
    "sg:classifiers":[
        {
            "category":"Banks & Credit Unions",
            "subcategory":"Financial Services",
            "type":"Services"
        },
        {
            "category":"Manufacturing",
            "subcategory":"Building Materials",
            "type":"Manufacturing & Wholesale Goods"
        }
    ],
    "sg:phone":"+44 20 8959 3646",
    "sg:postcode":"NW7 3LY",
    "sg:province":"Greater London",
    "sg:tags":[
        "supp",
        "claim",
        "shutter",
        "door",
        "assessor"
    ],
    "wof:name":"Injury Claims Consultants Ltd.",
    "wof:placetype":"venue"
},
  "geometry": {"coordinates":[-0.254498,51.617004],"type":"Point"}
}