{
  "type": "Feature",
  "properties": {
    "iso:country":"GB",
    "sg:address":"7 Fettiplace Rd",
    "sg:city":"Witney",
    "sg:classifiers":[
        {
            "category":"Health Services",
            "subcategory":"Chiropractor",
            "type":"Services"
        }
    ],
    "sg:phone":"+44 1993 774418",
    "sg:postcode":"OX8 5AP",
    "sg:province":"Oxfordshire",
    "wof:name":"Tower Hill Chiropractic Clinic",
    "wof:placetype":"venue"
},
  "geometry": {"coordinates":[-1.50239,51.787579],"type":"Point"}
}