{
  "type": "Feature",
  "properties": {
    "iso:country":"GB",
    "sg:address":"Cwmwdig Farm, Berea",
    "sg:city":"Haverfordwest",
    "sg:classifiers":[
        {
            "category":"Farming",
            "subcategory":"Farm",
            "type":"Manufacturing & Wholesale Goods"
        }
    ],
    "sg:phone":"+44 1348 831375",
    "sg:postcode":"SA62 6DN",
    "sg:province":"Pembrokeshire",
    "sg:tags":[
        "mixed",
        "crop"
    ],
    "wof:name":"Nicholas & Jeremy",
    "wof:placetype":"venue"
},
  "geometry": {"coordinates":[-5.201764,51.925915],"type":"Point"}
}