{
  "type": "Feature",
  "properties": {
    "addr:full":"Market St Centre, Market Street Alfreton Derbyshire DE55 2AB",
    "addr:postcode":"de55 2ab",
    "addr:street":"Market St Centre Market Street",
    "iso:country":"GB",
    "sg:address":"Market St Centre, Market Street",
    "sg:city":"Alfreton",
    "sg:classifiers":[
        {
            "category":"Shopping",
            "subcategory":"Crafts & Fabrics",
            "type":"Retail Goods"
        }
    ],
    "sg:postcode":"DE55 2AB",
    "sg:province":"Derbyshire",
    "sg:tags":[
        "shop"
    ],
    "wof:name":"Fabric Corner",
    "wof:placetype":"venue"
},
  "geometry": {"coordinates":[-1.3423739672,53.1056060791],"type":"Point"}
}