{
  "type": "Feature",
  "properties": {
    "iso:country":"GB",
    "sg:address":"18 St Peters Avenue, Anlaby",
    "sg:city":"Hull",
    "sg:classifiers":[
        {
            "category":"Real Estate",
            "subcategory":"Architect",
            "type":"Services"
        }
    ],
    "sg:phone":"+44 1482 653555",
    "sg:postcode":"HU10 7AP",
    "sg:province":"East Riding of Yorkshire",
    "wof:name":"Korus Engineering Ltd.",
    "wof:placetype":"venue"
},
  "geometry": {"coordinates":[-0.4346860051,53.7473106384],"type":"Point"}
}