{
  "type": "Feature",
  "properties": {
    "addr:full":"187-189 Douglas Place Blackburn Lancashire BB1 9ST",
    "addr:housenumber":"187-189",
    "addr:postcode":"bb1 9st",
    "addr:street":"Douglas Place",
    "iso:country":"GB",
    "sg:address":"187-189 Douglas Place",
    "sg:city":"Blackburn",
    "sg:classifiers":[
        {
            "category":"Social Services",
            "type":"Services"
        }
    ],
    "sg:phone":"+44 1254 672747",
    "sg:postcode":"BB1 9ST",
    "sg:province":"Lancashire",
    "sg:tags":[
        "ds"
    ],
    "wof:name":"Community Support Team",
    "wof:placetype":"venue"
},
  "geometry": {"coordinates":[-2.473507,53.769249],"type":"Point"}
}