{
  "type": "Feature",
  "properties": {
    "addr:full":"6 Ferndene Road London Greater London SE24 0AQ",
    "addr:housenumber":"6",
    "addr:postcode":"se24 0aq",
    "addr:street":"Ferndene Road",
    "iso:country":"GB",
    "sg:address":"6 Ferndene Road",
    "sg:city":"London",
    "sg:classifiers":[
        {
            "category":"Bus Charters",
            "type":"Transportation"
        }
    ],
    "sg:phone":"+44 20 7274 6900",
    "sg:postcode":"SE24 0AQ",
    "sg:province":"Greater London",
    "sg:tags":[
        "coach"
    ],
    "wof:name":"Mini Trips",
    "wof:placetype":"venue"
},
  "geometry": {"coordinates":[-0.097664997,51.4604454041],"type":"Point"}
}