{
  "type": "Feature",
  "properties": {
    "addr:full":"1 Knighten St Whitechapel Greater London E1 9PW",
    "addr:housenumber":"1",
    "addr:postcode":"e1 9pw",
    "addr:street":"Knighten St",
    "iso:country":"GB",
    "sg:address":"1 Knighten St",
    "sg:city":"Whitechapel",
    "sg:classifiers":[
        {
            "category":"Farming",
            "subcategory":"Nursery",
            "type":"Manufacturing & Wholesale Goods"
        }
    ],
    "sg:phone":"+44 20 7709 0709",
    "sg:postcode":"E1 9PW",
    "sg:province":"Greater London",
    "sg:tags":[
        "creche"
    ],
    "wof:name":"Buddy's Day Nursery",
    "wof:placetype":"venue"
},
  "geometry": {"coordinates":[-0.05736,51.517979],"type":"Point"}
}