{
  "type": "Feature",
  "properties": {
    "iso:country":"GB",
    "sg:address":"Sunset View",
    "sg:city":"Pembroke",
    "sg:classifiers":[
        {
            "category":"Building & Trades",
            "subcategory":"Construction",
            "type":"Services"
        }
    ],
    "sg:phone":"+44 1646 681646",
    "sg:postcode":"SA71 5BU",
    "sg:province":"Pembrokeshire",
    "sg:tags":[
        "builder"
    ],
    "wof:name":"Reliable Builder & Decorator",
    "wof:placetype":"venue"
},
  "geometry": {"coordinates":[-4.9158887863,51.6747245789],"type":"Point"}
}