{
  "type": "Feature",
  "properties": {
    "addr:full":"14 Kyleside, Kyleakin Isle Of Skye Highland IV41 8PW",
    "addr:housenumber":"14",
    "addr:postcode":"iv41 8pw",
    "addr:street":"Kyleside Kyleakin Isle",
    "iso:country":"GB",
    "sg:address":"14 Kyleside, Kyleakin",
    "sg:city":"Isle Of Skye",
    "sg:classifiers":[
        {
            "category":"Real Estate",
            "subcategory":"Architect",
            "type":"Services"
        }
    ],
    "sg:phone":"+44 1599 534900",
    "sg:postcode":"IV41 8PW",
    "sg:province":"Highland",
    "wof:name":"Stuart Duncan Architects",
    "wof:placetype":"venue"
},
  "geometry": {"coordinates":[-5.7359461784,57.2733955383],"type":"Point"}
}