{
  "type": "Feature",
  "properties": {
    "iso:country":"GB",
    "sg:address":"15 Manor Road, Lake",
    "sg:city":"Sandown",
    "sg:classifiers":[
        {
            "category":"Sports & Exercise",
            "subcategory":"Bowling",
            "type":"Entertainment"
        }
    ],
    "sg:postcode":"PO36 9JA",
    "sg:province":"Isle of Wight",
    "sg:tags":[
        "photography"
    ],
    "wof:name":"Don French Island Photos",
    "wof:placetype":"venue"
},
  "geometry": {"coordinates":[-1.1728329659,50.6480522156],"type":"Point"}
}