{
  "type": "Feature",
  "properties": {
    "iso:country":"GB",
    "sg:address":"28 Millhouse Units, Triangle",
    "sg:city":"Sowerby Bridge",
    "sg:classifiers":[
        {
            "category":"Shopping",
            "subcategory":"Stationery & Office Supplies",
            "type":"Retail Goods"
        }
    ],
    "sg:postcode":"HX6 3LF",
    "sg:province":"West Yorkshire",
    "sg:tags":[
        "merchant",
        "paper"
    ],
    "wof:name":"Paper Convertors",
    "wof:placetype":"venue"
},
  "geometry": {"coordinates":[-1.9139339924,53.7065391541],"type":"Point"}
}