{
  "type": "Feature",
  "properties": {
    "iso:country":"GB",
    "sg:address":"Halford Farm",
    "sg:city":"Craven Arms",
    "sg:classifiers":[
        {
            "category":"Freight",
            "type":"Transportation"
        }
    ],
    "sg:phone":"+44 1588 672951",
    "sg:postcode":"SY7 9JG",
    "sg:province":"Herefordshire",
    "sg:tags":[
        "haulage",
        "road"
    ],
    "wof:name":"Alan R Jones",
    "wof:placetype":"venue"
},
  "geometry": {"coordinates":[-2.832793951,52.4415245056],"type":"Point"}
}