{
  "type": "Feature",
  "properties": {
    "iso:country":"GB",
    "sg:address":"74 Hathersage Road",
    "sg:city":"Manchester",
    "sg:classifiers":[
        {
            "category":"Food & Beverages",
            "subcategory":"Liquor & Beverages",
            "type":"Retail Goods"
        }
    ],
    "sg:phone":"+44 161 224 2005",
    "sg:postcode":"M13 0FN",
    "sg:province":"Greater Manchester",
    "sg:tags":[
        "beer",
        "spirit",
        "wines"
    ],
    "wof:name":"Kwik Sale",
    "wof:placetype":"venue"
},
  "geometry": {"coordinates":[-2.2199618816,53.4593963623],"type":"Point"}
}