{
  "type": "Feature",
  "properties": {
    "iso:country":"GB",
    "sg:address":"The Studio, 57 Main Street, Baston",
    "sg:city":"Peterborough",
    "sg:classifiers":[
        {
            "category":"Real Estate",
            "subcategory":"Architect",
            "type":"Services"
        }
    ],
    "sg:phone":"+44 1778 560090",
    "sg:postcode":"PE6 9PB",
    "sg:province":"Cambridgeshire",
    "wof:name":"Peter Smith Associates",
    "wof:placetype":"venue"
},
  "geometry": {"coordinates":[-0.356869,52.710545],"type":"Point"}
}