{
  "type": "Feature",
  "properties": {
    "addr:full":"88 Leicester Road, Mount Sorrel Loughborough Leicestershire LE12 7AN",
    "addr:housenumber":"88",
    "addr:postcode":"le12 7an",
    "addr:street":"Leicester Road",
    "iso:country":"GB",
    "sg:address":"88 Leicester Road, Mount Sorrel",
    "sg:city":"Loughborough",
    "sg:classifiers":[
        {
            "category":"Autos & Motor Vehicles",
            "subcategory":"Fuel & Gas Station",
            "type":"Retail Goods"
        }
    ],
    "sg:postcode":"LE12 7AN",
    "sg:province":"Leicestershire",
    "sg:tags":[
        "petrol",
        "filling"
    ],
    "wof:name":"Castle Hill Service Station",
    "wof:placetype":"venue"
},
  "geometry": {"coordinates":[-1.1379790306,52.7288818359],"type":"Point"}
}