{
  "type": "Feature",
  "properties": {
    "addr:full":"Angel Ho, 12 Cheapside Nottingham Nottinghamshire NG1 2HU",
    "addr:housenumber":"12",
    "addr:postcode":"ng1 2hu",
    "addr:street":"Cheapside",
    "iso:country":"GB",
    "sg:address":"Angel Ho, 12 Cheapside",
    "sg:city":"Nottingham",
    "sg:classifiers":[
        {
            "category":"Retail",
            "subcategory":"Portrait Studio",
            "type":"Services"
        }
    ],
    "sg:phone":"+44 115 958 6066",
    "sg:postcode":"NG1 2HU",
    "sg:province":"Nottinghamshire",
    "sg:tags":[
        "photographic"
    ],
    "wof:name":"Envisage",
    "wof:placetype":"venue"
},
  "geometry": {"coordinates":[-1.1439239979,52.9492263794],"type":"Point"}
}