{
  "type": "Feature",
  "properties": {
    "addr:full":"Bradford Court, Bradford St Birmingham West Midlands B12 0NS",
    "addr:postcode":"b12 0ns",
    "addr:street":"Bradford Court;St",
    "iso:country":"GB",
    "sg:address":"Bradford Court, Bradford St",
    "sg:city":"Birmingham",
    "sg:classifiers":[
        {
            "category":"Communications",
            "subcategory":"News Services",
            "type":"Services"
        }
    ],
    "sg:phone":"+44 121 608 1166",
    "sg:postcode":"B12 0NS",
    "sg:province":"West Midlands",
    "sg:tags":[
        "photo",
        "agency"
    ],
    "wof:name":"24 7 Media",
    "wof:placetype":"venue"
},
  "geometry": {"coordinates":[-1.880164,52.471184],"type":"Point"}
}