{
  "type": "Feature",
  "properties": {
    "iso:country":"GB",
    "sg:address":"2 Lon Glyn",
    "sg:city":"Denbigh",
    "sg:classifiers":[
        {
            "category":"Manufacturing",
            "subcategory":"Petroleum Products",
            "type":"Manufacturing & Wholesale Goods"
        },
        {
            "category":"Building & Trades",
            "subcategory":"Construction",
            "type":"Services"
        }
    ],
    "sg:postcode":"LL16 5YG",
    "sg:province":"Conwy",
    "sg:tags":[
        "double",
        "glazing",
        "installers"
    ],
    "wof:name":"Michael E Hargraves",
    "wof:placetype":"venue"
},
  "geometry": {"coordinates":[-3.405824,53.192303],"type":"Point"}
}