{
  "type": "Feature",
  "properties": {
    "addr:full":"Carver Barracks Saffron Walden Cambridgeshire CB10 2YA",
    "addr:postcode":"cb10 2ya",
    "addr:street":"Walden",
    "iso:country":"GB",
    "sg:address":"Carver Barracks",
    "sg:city":"Saffron Walden",
    "sg:classifiers":[
        {
            "category":"Community Center",
            "subcategory":"Youth",
            "type":"Public Place"
        }
    ],
    "sg:phone":"+44 1799 521447",
    "sg:postcode":"CB10 2YA",
    "sg:province":"Cambridgeshire",
    "sg:tags":[
        "organisation",
        "centre"
    ],
    "wof:name":"Headquarters East Essex Wing Air Training Corps",
    "wof:placetype":"venue"
},
  "geometry": {"coordinates":[0.239938,52.020576],"type":"Point"}
}