{
  "type": "Feature",
  "properties": {
    "addr:full":"Unit Z1-z2 Market Hall, Trinity Square Gateshead Tyne and Wear NE8 1AG",
    "addr:postcode":"ne8 1ag",
    "addr:street":"Trinity Square",
    "iso:country":"GB",
    "sg:address":"Unit Z1-z2 Market Hall, Trinity Square",
    "sg:city":"Gateshead",
    "sg:classifiers":[
        {
            "category":"Personal",
            "subcategory":"Barber",
            "type":"Services"
        }
    ],
    "sg:phone":"+44 191 477 7398",
    "sg:postcode":"NE8 1AG",
    "sg:province":"Tyne and Wear",
    "sg:tags":[
        "men's",
        "hairdresser"
    ],
    "wof:name":"The Barber Shop",
    "wof:placetype":"venue"
},
  "geometry": {"coordinates":[-1.6020460129,54.9610404968],"type":"Point"}
}