{
  "type": "Feature",
  "properties": {
    "iso:country":"GB",
    "sg:address":"5 Swinbourne Court",
    "sg:city":"Basildon",
    "sg:classifiers":[
        {
            "category":"Home & Garden",
            "subcategory":"Furniture",
            "type":"Retail Goods"
        }
    ],
    "sg:phone":"+44 1268 724700",
    "sg:postcode":"SS13 1QA",
    "sg:province":"Essex",
    "wof:name":"Success Furniture Ltd.",
    "wof:placetype":"venue"
},
  "geometry": {"coordinates":[0.51434,51.586315],"type":"Point"}
}