{
  "type": "Feature",
  "properties": {
    "addr:full":"Dartside Quay, Galmpton Brixham Devon TQ5 0EH",
    "addr:postcode":"tq5 0eh",
    "addr:street":"Dartside Quay",
    "iso:country":"GB",
    "sg:address":"Dartside Quay, Galmpton",
    "sg:city":"Brixham",
    "sg:classifiers":[
        {
            "category":"Professional",
            "type":"Services"
        }
    ],
    "sg:phone":"+44 1803 843877",
    "sg:postcode":"TQ5 0EH",
    "sg:province":"Devon",
    "sg:tags":[
        "marine"
    ],
    "wof:name":"Pedros Yacht Refinishing",
    "wof:placetype":"venue"
},
  "geometry": {"coordinates":[-3.556352,50.396938],"type":"Point"}
}