{
  "type": "Feature",
  "properties": {
    "addr:full":"Offa Street Hereford Herefordshire HR1 2LH",
    "addr:postcode":"hr1 2lh",
    "addr:street":"Offa Street",
    "iso:country":"GB",
    "sg:address":"Offa Street",
    "sg:city":"Hereford",
    "sg:classifiers":[
        {
            "category":"Retail",
            "subcategory":"Repair Shop",
            "type":"Services"
        }
    ],
    "sg:postcode":"HR1 2LH",
    "sg:province":"Herefordshire",
    "sg:tags":[
        "upholsterer"
    ],
    "wof:name":"Wilkes",
    "wof:placetype":"venue"
},
  "geometry": {"coordinates":[-2.7142140865,52.0558662415],"type":"Point"}
}