{
  "type": "Feature",
  "properties": {
    "addr:full":"Brookfield, Mawdesley Ormskirk Lancashire L40 2QJ",
    "addr:postcode":"l40 2qj",
    "iso:country":"GB",
    "sg:address":"Brookfield, Mawdesley",
    "sg:city":"Ormskirk",
    "sg:classifiers":[
        {
            "category":"Building & Trades",
            "subcategory":"Construction",
            "type":"Services"
        }
    ],
    "sg:postcode":"L40 2QJ",
    "sg:province":"Lancashire",
    "sg:tags":[
        "decorator",
        "painter"
    ],
    "wof:name":"Pye & Collier",
    "wof:placetype":"venue"
},
  "geometry": {"coordinates":[-2.7711389065,53.6262512207],"type":"Point"}
}