{
  "type": "Feature",
  "properties": {
    "addr:full":"Unit 1 Lakeside Indust Est, Lakeside Rd Slough Berkshire SL3 0ED",
    "addr:housenumber":"unit 1",
    "addr:postcode":"sl3 0ed",
    "addr:street":"Indust Est Lakeside Rd",
    "iso:country":"GB",
    "sg:address":"Unit 1 Lakeside Indust Est, Lakeside Rd",
    "sg:city":"Slough",
    "sg:classifiers":[
        {
            "category":"Professional",
            "subcategory":"Computer Services",
            "type":"Services"
        }
    ],
    "sg:phone":"+44 1753 687008",
    "sg:postcode":"SL3 0ED",
    "sg:province":"Berkshire",
    "sg:tags":[
        "system",
        "software"
    ],
    "wof:name":"Computer Truck Internationnal Ltd",
    "wof:placetype":"venue"
},
  "geometry": {"coordinates":[-0.50179,51.488838],"type":"Point"}
}