{
  "type": "Feature",
  "properties": {
    "iso:country":"GB",
    "sg:address":"2 Esplanade",
    "sg:city":"Burnham-on-sea",
    "sg:classifiers":[
        {
            "category":"Recreation",
            "subcategory":"Amusement Park",
            "type":"Entertainment"
        },
        {
            "category":"Autos & Motor Vehicles",
            "subcategory":"Boat Sales",
            "type":"Retail Goods"
        }
    ],
    "sg:phone":"+44 1278 786996",
    "sg:postcode":"TA8 1BB",
    "sg:province":"Somerset",
    "sg:tags":[
        "machine",
        "gaming",
        "arcade"
    ],
    "wof:name":"Sunspot Amusements",
    "wof:placetype":"venue"
},
  "geometry": {"coordinates":[-2.9990530014,51.2346878052],"type":"Point"}
}