{
  "type": "Feature",
  "properties": {
    "addr:full":"Plas Y Grn, Mold Road Denbigh Conwy LL16 4BH",
    "addr:postcode":"ll16 4bh",
    "addr:street":"Plas Y Grn Mold Road",
    "iso:country":"GB",
    "sg:address":"Plas Y Grn, Mold Road",
    "sg:city":"Denbigh",
    "sg:classifiers":[
        {
            "category":"Education",
            "subcategory":"School",
            "type":"Public Place"
        }
    ],
    "sg:phone":"+44 1745 815228",
    "sg:postcode":"LL16 4BH",
    "sg:province":"Conwy",
    "sg:tags":[
        "local",
        "authority"
    ],
    "wof:name":"St Brigids School",
    "wof:placetype":"venue"
},
  "geometry": {"coordinates":[-3.421149,53.183411],"type":"Point"}
}