{
  "type": "Feature",
  "properties": {
    "addr:full":"31 Wessex Trade Centre, Ringwood Road Poole Dorset BH12 3PF",
    "addr:housenumber":"31;trade centre",
    "addr:postcode":"bh12 3pf",
    "addr:street":"Wessex;Ringwood Road",
    "iso:country":"GB",
    "sg:address":"31 Wessex Trade Centre, Ringwood Road",
    "sg:city":"Poole",
    "sg:classifiers":[
        {
            "category":"Home & Garden",
            "subcategory":"Home Furnishings",
            "type":"Retail Goods"
        },
        {
            "category":"Social Services",
            "subcategory":"Adult Care",
            "type":"Services"
        }
    ],
    "sg:phone":"+44 1202 722420",
    "sg:postcode":"BH12 3PF",
    "sg:province":"Dorset",
    "sg:tags":[
        "merchant",
        "decorator",
        "diy",
        "decorators'"
    ],
    "wof:name":"Crown Brolac Decorator Centre",
    "wof:placetype":"venue"
},
  "geometry": {"coordinates":[-1.949499,50.741985],"type":"Point"}
}