{
  "type": "Feature",
  "properties": {
    "iso:country":"GB",
    "sg:address":"Hamilton Road",
    "sg:city":"Newmarket",
    "sg:classifiers":[
        {
            "category":"Personal",
            "subcategory":"Adult",
            "type":"Services"
        }
    ],
    "sg:phone":"+44 1638 661508",
    "sg:postcode":"CB8 0NY",
    "sg:province":"Cambridgeshire",
    "sg:tags":[
        "equestrian"
    ],
    "wof:name":"Chestnut Tree Stables",
    "wof:placetype":"venue"
},
  "geometry": {"coordinates":[0.3888179958,52.2433204651],"type":"Point"}
}