{
  "type": "Feature",
  "properties": {
    "addr:full":"Temple Road, Cowley Oxford Oxfordshire OX4 2EX",
    "addr:postcode":"ox4 2ex",
    "addr:street":"Temple Road",
    "iso:country":"GB",
    "sg:address":"Temple Road, Cowley",
    "sg:city":"Oxford",
    "sg:classifiers":[
        {
            "category":"Farming",
            "subcategory":"Nursery",
            "type":"Manufacturing & Wholesale Goods"
        }
    ],
    "sg:postcode":"OX4 2EX",
    "sg:province":"Oxfordshire",
    "sg:tags":[
        "creche"
    ],
    "wof:name":"Bean Stalk Nursery School",
    "wof:placetype":"venue"
},
  "geometry": {"coordinates":[-1.2100139856,51.7337532043],"type":"Point"}
}