{
  "type": "Feature",
  "properties": {
    "addr:full":"43 Eastwood Rd Shrewsbury Shropshire SY3 8YJ",
    "addr:housenumber":"43",
    "addr:postcode":"sy3 8yj",
    "addr:street":"Eastwood Rd",
    "iso:country":"GB",
    "sg:address":"43 Eastwood Rd",
    "sg:city":"Shrewsbury",
    "sg:classifiers":[
        {
            "category":"Professional",
            "subcategory":"Engineering",
            "type":"Services"
        }
    ],
    "sg:phone":"+44 1743 362335",
    "sg:postcode":"SY3 8YJ",
    "sg:province":"Shropshire",
    "sg:tags":[
        "contractor",
        "electrical",
        "engineer"
    ],
    "wof:name":"Ron Edwards",
    "wof:placetype":"venue"
},
  "geometry": {"coordinates":[-2.779179,52.71204],"type":"Point"}
}