{
  "type": "Feature",
  "properties": {
    "addr:full":"110 Dunstable Street, Ampthill Bedford Bedfordshire MK45 2JP",
    "addr:housenumber":"110",
    "addr:postcode":"mk45 2jp",
    "addr:street":"Dunstable Street",
    "iso:country":"GB",
    "sg:address":"110 Dunstable Street, Ampthill",
    "sg:city":"Bedford",
    "sg:classifiers":[
        {
            "category":"Retail",
            "subcategory":"Repair Shop",
            "type":"Services"
        }
    ],
    "sg:phone":"+44 1525 402203",
    "sg:postcode":"MK45 2JP",
    "sg:province":"Bedfordshire",
    "sg:tags":[
        "radio",
        "television",
        "video"
    ],
    "wof:name":"Ampthill Television Centre Ltd.",
    "wof:placetype":"venue"
},
  "geometry": {"coordinates":[-0.4935140014,52.0313262939],"type":"Point"}
}