{
  "type": "Feature",
  "properties": {
    "addr:full":"Jubilee Ho, 74 High St Telford Shropshire TF7 5AQ",
    "addr:housenumber":"74",
    "addr:postcode":"tf7 5aq",
    "addr:street":"High St",
    "iso:country":"GB",
    "sg:address":"Jubilee Ho, 74 High St",
    "sg:city":"Telford",
    "sg:classifiers":[
        {
            "category":"Professional",
            "subcategory":"Lawyer & Legal Services",
            "type":"Services"
        }
    ],
    "sg:phone":"+44 1952 278000",
    "sg:postcode":"TF7 5AQ",
    "sg:province":"Shropshire",
    "sg:tags":[
        "advice",
        "counselling"
    ],
    "wof:name":"Axis In Shropshire",
    "wof:placetype":"venue"
},
  "geometry": {"coordinates":[-2.4493401051,52.6365890503],"type":"Point"}
}