{
  "type": "Feature",
  "properties": {
    "iso:country":"GB",
    "sg:address":"86-87 Royal Parade",
    "sg:city":"Eastbourne",
    "sg:classifiers":[
        {
            "category":"Travel",
            "subcategory":"Hotels & Motels",
            "type":"Entertainment"
        }
    ],
    "sg:postcode":"BN22 7AE",
    "sg:province":"East Sussex",
    "wof:name":"Hotel Marina",
    "wof:placetype":"venue"
},
  "geometry": {"coordinates":[0.300364,50.775593],"type":"Point"}
}