{
  "type": "Feature",
  "properties": {
    "addr:full":"86-87 Royal Parade Eastbourne East Sussex BN22 7AE",
    "addr:housenumber":"86-87",
    "addr:postcode":"bn22 7ae",
    "addr:street":"Royal Parade",
    "iso:country":"GB",
    "sg:address":"86-87 Royal Parade",
    "sg:city":"Eastbourne",
    "sg:classifiers":[
        {
            "category":"Travel",
            "subcategory":"Hotels & Motels",
            "type":"Entertainment"
        }
    ],
    "sg:postcode":"BN22 7AE",
    "sg:province":"East Sussex",
    "wof:name":"Hotel Marina",
    "wof:placetype":"venue"
},
  "geometry": {"coordinates":[0.300364,50.775593],"type":"Point"}
}