{
  "type": "Feature",
  "properties": {
    "iso:country":"GB",
    "sg:address":"44 Vermont Woods",
    "sg:city":"Wokingham",
    "sg:classifiers":[
        {
            "category":"Professional",
            "subcategory":"Engineering",
            "type":"Services"
        }
    ],
    "sg:phone":"+44 118 973 2353",
    "sg:postcode":"RG40 4PF",
    "sg:province":"Berkshire",
    "sg:tags":[
        "contractor",
        "electrical",
        "engineer"
    ],
    "wof:name":"D S Electrical",
    "wof:placetype":"venue"
},
  "geometry": {"coordinates":[-0.8657209873,51.3817596436],"type":"Point"}
}