{
  "type": "Feature",
  "properties": {
    "addr:full":"Windermere Drive Worcester Worcestershire WR4 9HY",
    "addr:postcode":"wr4 9hy",
    "addr:street":"Windermere Drive",
    "iso:country":"GB",
    "sg:address":"Windermere Drive",
    "sg:city":"Worcester",
    "sg:classifiers":[
        {
            "category":"Bars & Pubs",
            "type":"Food & Drink"
        }
    ],
    "sg:phone":"+44 1905 25800",
    "sg:postcode":"WR4 9HY",
    "sg:province":"Worcestershire",
    "sg:tags":[
        "pubs",
        "inn"
    ],
    "wof:name":"Prince of Wales",
    "wof:placetype":"venue"
},
  "geometry": {"coordinates":[-2.192806,52.209572],"type":"Point"}
}