{
  "type": "Feature",
  "properties": {
    "addr:full":"13 Crescent Walk Bradford West Yorkshire BD14 6EH",
    "addr:housenumber":"13",
    "addr:postcode":"bd14 6eh",
    "addr:street":"Crescent Walk",
    "iso:country":"GB",
    "sg:address":"13 Crescent Walk",
    "sg:city":"Bradford",
    "sg:classifiers":[
        {
            "category":"Farming",
            "subcategory":"Poultry Farm",
            "type":"Manufacturing & Wholesale Goods"
        }
    ],
    "sg:phone":"+44 1274 818282",
    "sg:postcode":"BD14 6EH",
    "sg:province":"West Yorkshire",
    "wof:name":"Kamal Poultry",
    "wof:placetype":"venue"
},
  "geometry": {"coordinates":[-1.806000948,53.7871704102],"type":"Point"}
}