{
  "type": "Feature",
  "properties": {
    "addr:full":"Cuckoo Hill Bures Essex CO8 5JH",
    "addr:postcode":"co8 5jh",
    "addr:street":"Cuckoo Hill",
    "iso:country":"GB",
    "sg:address":"Cuckoo Hill",
    "sg:city":"Bures",
    "sg:classifiers":[
        {
            "category":"Retail",
            "subcategory":"Auto Repair",
            "type":"Services"
        }
    ],
    "sg:phone":"+44 1787 227236",
    "sg:postcode":"CO8 5JH",
    "sg:province":"Essex",
    "sg:tags":[
        "modification",
        "garage"
    ],
    "wof:name":"Pilgrim Garage",
    "wof:placetype":"venue"
},
  "geometry": {"coordinates":[0.781008,51.974571],"type":"Point"}
}