{
  "type": "Feature",
  "properties": {
    "addr:full":"Druan Cottage, Craigie Kilmarnock East Ayrshire KA1 5NE",
    "addr:postcode":"ka1 5ne",
    "addr:street":"Craigie;East",
    "iso:country":"GB",
    "sg:address":"Druan Cottage, Craigie",
    "sg:city":"Kilmarnock",
    "sg:classifiers":[
        {
            "category":"Banks & Credit Unions",
            "subcategory":"Financial Services",
            "type":"Services"
        }
    ],
    "sg:phone":"+44 1292 541898",
    "sg:postcode":"KA1 5NE",
    "sg:province":"East Ayrshire",
    "sg:tags":[
        "consultant"
    ],
    "wof:name":"Andrew Glover Finance",
    "wof:placetype":"venue"
},
  "geometry": {"coordinates":[-4.4911608696,55.5602111816],"type":"Point"}
}