{
  "type": "Feature",
  "properties": {
    "addr:full":"Manor Road Erith Kent DA8 2AD",
    "addr:postcode":"da8 2ad",
    "addr:street":"Manor Road",
    "iso:country":"GB",
    "sg:address":"Manor Road",
    "sg:city":"Erith",
    "sg:classifiers":[
        {
            "category":"Social Services",
            "subcategory":"Job Training",
            "type":"Services"
        },
        {
            "category":"Education",
            "subcategory":"Special Training",
            "type":"Public Place"
        }
    ],
    "sg:phone":"+44 1322 349638",
    "sg:postcode":"DA8 2AD",
    "sg:province":"Kent",
    "sg:tags":[
        "product",
        "centre"
    ],
    "wof:name":"Construction Industry Training Board",
    "wof:placetype":"venue"
},
  "geometry": {"coordinates":[0.183935,51.478371],"type":"Point"}
}