{
  "type": "Feature",
  "properties": {
    "addr:full":"12 Pentregwenlais Road, Llandybie Ammanford Carmarthenshire SA18 3JQ",
    "addr:housenumber":"12",
    "addr:postcode":"sa18 3jq",
    "addr:street":"Pentregwenlais Road",
    "iso:country":"GB",
    "sg:address":"12 Pentregwenlais Road, Llandybie",
    "sg:city":"Ammanford",
    "sg:classifiers":[
        {
            "category":"Building & Trades",
            "subcategory":"Construction",
            "type":"Services"
        }
    ],
    "sg:phone":"+44 1269 850532",
    "sg:postcode":"SA18 3JQ",
    "sg:province":"Carmarthenshire",
    "sg:tags":[
        "builder"
    ],
    "wof:name":"D M Davies & Co.",
    "wof:placetype":"venue"
},
  "geometry": {"coordinates":[-4.0103487968,51.8266067505],"type":"Point"}
}