{
  "type": "Feature",
  "properties": {
    "iso:country":"GB",
    "sg:address":"Robins Yard, Station Road",
    "sg:city":"Battle",
    "sg:classifiers":[
        {
            "category":"Retail",
            "subcategory":"Auto Repair",
            "type":"Services"
        }
    ],
    "sg:phone":"+44 1424 775824",
    "sg:postcode":"TN33 0DE",
    "sg:province":"East Sussex",
    "sg:tags":[
        "modification",
        "garage"
    ],
    "wof:name":"Senlac Garage",
    "wof:placetype":"venue"
},
  "geometry": {"coordinates":[0.489025,50.914616],"type":"Point"}
}