{
  "type": "Feature",
  "properties": {
    "addr:full":"47 High Street Warminster Somerset BA12 9AQ",
    "addr:housenumber":"47",
    "addr:postcode":"ba12 9aq",
    "addr:street":"High Street",
    "iso:country":"GB",
    "sg:address":"47 High Street",
    "sg:city":"Warminster",
    "sg:classifiers":[
        {
            "category":"Personal",
            "subcategory":"Tattoo Parlor",
            "type":"Services"
        }
    ],
    "sg:postcode":"BA12 9AQ",
    "sg:province":"Somerset",
    "sg:tags":[
        "tattooing",
        "piercing"
    ],
    "wof:name":"Gipsy Moon Tattoo Studio",
    "wof:placetype":"venue"
},
  "geometry": {"coordinates":[-2.183609,51.205402],"type":"Point"}
}