{
  "type": "Feature",
  "properties": {
    "addr:full":"Union Garage, Bacup Road, Rawtenstall Rossendale Lancashire BB4 7JJ",
    "addr:postcode":"bb4 7jj",
    "addr:street":"Bacup Road",
    "iso:country":"GB",
    "sg:address":"Union Garage, Bacup Road, Rawtenstall",
    "sg:city":"Rossendale",
    "sg:classifiers":[
        {
            "category":"Transit Center",
            "subcategory":"Freight",
            "type":"Transportation"
        },
        {
            "category":"Autos & Motor Vehicles",
            "subcategory":"Auto Supplies",
            "type":"Retail Goods"
        }
    ],
    "sg:phone":"+44 1706 223366",
    "sg:postcode":"BB4 7JJ",
    "sg:province":"Lancashire",
    "sg:tags":[
        "exhaust",
        "absorber",
        "shock",
        "centre"
    ],
    "wof:name":"Rossendale Exhaust Centre",
    "wof:placetype":"venue"
},
  "geometry": {"coordinates":[-2.2798690796,53.7003707886],"type":"Point"}
}