{
  "type": "Feature",
  "properties": {
    "iso:country":"GB",
    "sg:address":"113 Narborough Rd",
    "sg:city":"Leicester",
    "sg:classifiers":[
        {
            "category":"Shopping",
            "subcategory":"Clothing, Apparel, & Fashions",
            "type":"Retail Goods"
        }
    ],
    "sg:postcode":"LE3 0PA",
    "sg:province":"Leicestershire",
    "sg:tags":[
        "clothing",
        "fabric"
    ],
    "wof:name":"Singh,A,",
    "wof:placetype":"venue"
},
  "geometry": {"coordinates":[-1.150515,52.627178],"type":"Point"}
}