{
  "type": "Feature",
  "properties": {
    "iso:country":"GB",
    "sg:address":"77-79 High Street, Barkingside",
    "sg:city":"Ilford",
    "sg:classifiers":[
        {
            "category":"Shopping",
            "subcategory":"Department Store",
            "type":"Retail Goods"
        }
    ],
    "sg:phone":"+44 20 8550 8598",
    "sg:postcode":"IG6 2AF",
    "sg:province":"Essex",
    "wof:name":"Woolworths Plc",
    "wof:placetype":"venue"
},
  "geometry": {"coordinates":[0.082163,51.590618],"type":"Point"}
}