{
  "type": "Feature",
  "properties": {
    "iso:country":"GB",
    "sg:address":"Lon Yr Eglwys, Morfa Nefyn",
    "sg:city":"Pwllheli",
    "sg:classifiers":[
        {
            "category":"Education",
            "subcategory":"School",
            "type":"Public Place"
        }
    ],
    "sg:phone":"+44 1758 720870",
    "sg:postcode":"LL53 6AR",
    "sg:province":"Gwynedd",
    "sg:tags":[
        "local",
        "authority"
    ],
    "wof:name":"Ysgol Morfa Nefyn",
    "wof:placetype":"venue"
},
  "geometry": {"coordinates":[-4.548805,52.931408],"type":"Point"}
}