{
  "type": "Feature",
  "properties": {
    "iso:country":"GB",
    "sg:address":"3 Hollycroft Avenue",
    "sg:city":"Wembley",
    "sg:classifiers":[
        {
            "category":"Professional",
            "subcategory":"Computer Services",
            "type":"Services"
        }
    ],
    "sg:postcode":"HA9 8LG",
    "sg:province":"Greater London",
    "sg:tags":[
        "system",
        "software"
    ],
    "wof:name":"Metrology Technology Ltd",
    "wof:placetype":"venue"
},
  "geometry": {"coordinates":[-0.289832,51.564606],"type":"Point"}
}