{
  "type": "Feature",
  "properties": {
    "iso:country":"GB",
    "sg:address":"58/60 Waterloo Road",
    "sg:city":"Smethwick",
    "sg:classifiers":[
        {
            "category":"Organizations",
            "subcategory":"Non-profit Organization",
            "type":"Services"
        }
    ],
    "sg:postcode":"B66 4JN",
    "sg:province":"West Midlands",
    "sg:tags":[
        "organisation",
        "voluntary",
        "charity"
    ],
    "wof:name":"Smethwick Asian Resource Project",
    "wof:placetype":"venue"
},
  "geometry": {"coordinates":[-1.962907,52.485947],"type":"Point"}
}