{
  "type": "Feature",
  "properties": {
    "addr:full":"15 Russell Street Leek Staffordshire ST13 5JF",
    "addr:housenumber":"15",
    "addr:postcode":"st13 5jf",
    "addr:street":"Russell Street",
    "iso:country":"GB",
    "sg:address":"15 Russell Street",
    "sg:city":"Leek",
    "sg:classifiers":[
        {
            "category":"Shopping",
            "subcategory":"Clothing, Apparel, & Fashions",
            "type":"Retail Goods"
        }
    ],
    "sg:phone":"+44 1538 383106",
    "sg:postcode":"ST13 5JF",
    "sg:province":"Staffordshire",
    "sg:tags":[
        "lingerie",
        "hosiery"
    ],
    "wof:name":"Edna Dale",
    "wof:placetype":"venue"
},
  "geometry": {"coordinates":[-2.02404809,53.1053504944],"type":"Point"}
}