{
  "type": "Feature",
  "properties": {
    "iso:country":"GB",
    "sg:address":"516 Walton Road",
    "sg:city":"West Molesey",
    "sg:classifiers":[
        {
            "category":"Professional",
            "subcategory":"Art Services",
            "type":"Services"
        }
    ],
    "sg:postcode":"KT8 2QF",
    "sg:province":"Greater London",
    "sg:tags":[
        "consultant",
        "design"
    ],
    "wof:name":"Services Design Associates",
    "wof:placetype":"venue"
},
  "geometry": {"coordinates":[-0.373302,51.402485],"type":"Point"}
}