{
  "type": "Feature",
  "properties": {
    "iso:country":"GB",
    "sg:address":"Kirkburn Mills, Manse Street",
    "sg:city":"Peterhead",
    "sg:classifiers":[
        {
            "category":"Shopping",
            "subcategory":"Crafts & Fabrics",
            "type":"Retail Goods"
        }
    ],
    "sg:phone":"+44 1779 871400",
    "sg:postcode":"AB42 1SA",
    "sg:province":"Aberdeenshire",
    "sg:tags":[
        "knitwear",
        "yarn"
    ],
    "wof:name":"Thomas Smith & Co. (Peterhead) Ltd.",
    "wof:placetype":"venue"
},
  "geometry": {"coordinates":[-1.795259,57.506901],"type":"Point"}
}