{
  "type": "Feature",
  "properties": {
    "iso:country":"GB",
    "sg:address":"56 Battersea Park Road",
    "sg:city":"London",
    "sg:classifiers":[
        {
            "category":"Shopping",
            "subcategory":"News",
            "type":"Retail Goods"
        }
    ],
    "sg:phone":"+44 20 7622 2772",
    "sg:postcode":"SW11 4JP",
    "sg:province":"Greater London",
    "sg:tags":[
        "newsagent"
    ],
    "wof:name":"Battersea Park Newsagent",
    "wof:placetype":"venue"
},
  "geometry": {"coordinates":[-0.151144,51.475513],"type":"Point"}
}