{
  "type": "Feature",
  "properties": {
    "addr:full":"37 Market Street, Chapel En Le Frith High Peak Cheshire SK23 0HP",
    "addr:housenumber":"37",
    "addr:postcode":"sk23 0hp",
    "addr:street":"Market Street",
    "iso:country":"GB",
    "sg:address":"37 Market Street, Chapel En Le Frith",
    "sg:city":"High Peak",
    "sg:classifiers":[
        {
            "category":"Personal",
            "subcategory":"Beauty Salon",
            "type":"Services"
        }
    ],
    "sg:phone":"+44 1298 812256",
    "sg:postcode":"SK23 0HP",
    "sg:province":"Cheshire",
    "sg:tags":[
        "unisex",
        "hairdresser"
    ],
    "wof:name":"Kathy's Salon",
    "wof:placetype":"venue"
},
  "geometry": {"coordinates":[-1.913241,53.323753],"type":"Point"}
}