{
  "type": "Feature",
  "properties": {
    "addr:full":"27-34 Greyfriars Stafford Staffordshire ST16 2SE",
    "addr:housenumber":"27-34",
    "addr:postcode":"st16 2se",
    "addr:street":"Greyfriars",
    "iso:country":"GB",
    "sg:address":"27-34 Greyfriars",
    "sg:city":"Stafford",
    "sg:classifiers":[
        {
            "category":"Autos & Motor Vehicles",
            "subcategory":"Auto Supplies",
            "type":"Retail Goods"
        }
    ],
    "sg:phone":"+44 1785 253641",
    "sg:postcode":"ST16 2SE",
    "sg:province":"Staffordshire",
    "sg:tags":[
        "tyre"
    ],
    "wof:name":"National Tyres and Autocare",
    "wof:placetype":"venue"
},
  "geometry": {"coordinates":[-2.1231100559,52.8150215149],"type":"Point"}
}