{
  "type": "Feature",
  "properties": {
    "iso:country":"GB",
    "sg:address":"4-5 High Street",
    "sg:city":"Huntingdon",
    "sg:classifiers":[
        {
            "category":"Professional",
            "subcategory":"Secretarial Services",
            "type":"Services"
        }
    ],
    "sg:phone":"+44 1480 455002",
    "sg:postcode":"PE29 3TE",
    "sg:province":"Cambridgeshire",
    "wof:name":"Cromwell Secrertarial Services",
    "wof:placetype":"venue"
},
  "geometry": {"coordinates":[-0.17946,52.328018],"type":"Point"}
}