{
  "type": "Feature",
  "properties": {
    "iso:country":"GB",
    "sg:address":"52 Lodge Drive, Culcheth",
    "sg:city":"Warrington",
    "sg:classifiers":[
        {
            "category":"Shopping",
            "subcategory":"Comic Books",
            "type":"Retail Goods"
        }
    ],
    "sg:phone":"+44 1925 763744",
    "sg:postcode":"WA3 4ER",
    "sg:province":"Cheshire",
    "sg:tags":[
        "jeweller"
    ],
    "wof:name":"The Village Goldsmith",
    "wof:placetype":"venue"
},
  "geometry": {"coordinates":[-2.521003,53.453754],"type":"Point"}
}