{
  "type": "Feature",
  "properties": {
    "addr:full":"34 The Portway, Kingswinford Brierley Hill Staffordshire DY6 8HB",
    "addr:housenumber":"34",
    "addr:postcode":"dy6 8hb",
    "addr:street":"The Portway",
    "iso:country":"GB",
    "sg:address":"34 The Portway, Kingswinford",
    "sg:city":"Brierley Hill",
    "sg:classifiers":[
        {
            "category":"Building & Trades",
            "subcategory":"Construction",
            "type":"Services"
        }
    ],
    "sg:phone":"+44 1384 271847",
    "sg:postcode":"DY6 8HB",
    "sg:province":"Staffordshire",
    "sg:tags":[
        "roofing"
    ],
    "wof:name":"D P S Roofing",
    "wof:placetype":"venue"
},
  "geometry": {"coordinates":[-2.1627810001,52.4914550781],"type":"Point"}
}