{
  "type": "Feature",
  "properties": {
    "iso:country":"GB",
    "sg:address":"5 Forster Road, Walthamstow",
    "sg:city":"London",
    "sg:classifiers":[
        {
            "category":"Building & Trades",
            "subcategory":"Plumbing",
            "type":"Services"
        }
    ],
    "sg:phone":"+44 20 8509 3477",
    "sg:postcode":"E17 8AU",
    "sg:province":"Greater London",
    "sg:tags":[
        "heating"
    ],
    "wof:name":"Curland Plumbing & Heating Engineers",
    "wof:placetype":"venue"
},
  "geometry": {"coordinates":[-0.035591,51.577278],"type":"Point"}
}