{
  "type": "Feature",
  "properties": {
    "addr:full":"13 Ingram Drive Newcastle-upon-tyne Tyne and Wear NE5 1TG",
    "addr:housenumber":"13",
    "addr:postcode":"ne5 1tg",
    "addr:street":"Ingram Drive",
    "iso:country":"GB",
    "sg:address":"13 Ingram Drive",
    "sg:city":"Newcastle-upon-tyne",
    "sg:classifiers":[
        {
            "category":"Banks & Credit Unions",
            "subcategory":"Financial Services",
            "type":"Services"
        }
    ],
    "sg:postcode":"NE5 1TG",
    "sg:province":"Tyne and Wear",
    "sg:tags":[
        "adviser"
    ],
    "wof:name":"John R Wood",
    "wof:placetype":"venue"
},
  "geometry": {"coordinates":[-1.711383,55.003311],"type":"Point"}
}