{
  "type": "Feature",
  "properties": {
    "addr:full":"Andrewes Street Leicester Leicestershire LE3 5PA",
    "addr:postcode":"le3 5pa",
    "addr:street":"Andrewes Street",
    "iso:country":"GB",
    "sg:address":"Andrewes Street",
    "sg:city":"Leicester",
    "sg:classifiers":[
        {
            "category":"Education",
            "subcategory":"School",
            "type":"Public Place"
        }
    ],
    "sg:phone":"+44 116 262 1905",
    "sg:postcode":"LE3 5PA",
    "sg:province":"Leicestershire",
    "sg:tags":[
        "local",
        "authority"
    ],
    "wof:name":"King Richard I I I Infant School",
    "wof:placetype":"venue"
},
  "geometry": {"coordinates":[-1.1491390467,52.6334342957],"type":"Point"}
}