{
  "type": "Feature",
  "properties": {
    "addr:full":"Soverign Ho,, 16a Queens Rd, Coventry West Midlands CV1 3EG",
    "addr:housenumber":"16a",
    "addr:postcode":"cv1 3eg",
    "addr:street":"Queens Rd",
    "iso:country":"GB",
    "sg:address":"Soverign Ho,, 16a Queens Rd,",
    "sg:city":"Coventry",
    "sg:classifiers":[
        {
            "category":"Real Estate",
            "subcategory":"Developer",
            "type":"Services"
        }
    ],
    "sg:postcode":"CV1 3EG",
    "sg:province":"West Midlands",
    "sg:tags":[
        "property"
    ],
    "wof:name":"Ardenvale Developments Ltd",
    "wof:placetype":"venue"
},
  "geometry": {"coordinates":[-1.507768,52.406986],"type":"Point"}
}