{
  "type": "Feature",
  "properties": {
    "addr:full":"180 Okehampton Crescent Welling Kent DA16 1DB",
    "addr:housenumber":"180",
    "addr:postcode":"da16 1db",
    "addr:street":"Okehampton Crescent",
    "iso:country":"GB",
    "sg:address":"180 Okehampton Crescent",
    "sg:city":"Welling",
    "sg:classifiers":[
        {
            "category":"Shopping",
            "type":"Retail Goods"
        }
    ],
    "sg:phone":"+44 20 8304 7545",
    "sg:postcode":"DA16 1DB",
    "sg:province":"Kent",
    "sg:tags":[
        "merchant"
    ],
    "wof:name":"Pjs China Trader Ltd.",
    "wof:placetype":"venue"
},
  "geometry": {"coordinates":[0.124585,51.47393],"type":"Point"}
}