{
  "type": "Feature",
  "properties": {
    "addr:full":"Winghay Close, Longbridge Hayes Stoke-on-trent Staffordshire ST6 4DU",
    "addr:postcode":"staffordshire st6 4du",
    "addr:street":"Winghay Close",
    "iso:country":"GB",
    "sg:address":"Winghay Close, Longbridge Hayes",
    "sg:city":"Stoke-on-trent",
    "sg:classifiers":[
        {
            "category":"Professional",
            "subcategory":"Engineering",
            "type":"Services"
        },
        {
            "category":"Real Estate",
            "subcategory":"Real Estate Agent",
            "type":"Services"
        }
    ],
    "sg:phone":"+44 1782 811089",
    "sg:postcode":"ST6 4DU",
    "sg:province":"Staffordshire",
    "sg:tags":[
        "precision",
        "engineer"
    ],
    "wof:name":"S & H Denton Engineering Holdings Ltd.",
    "wof:placetype":"venue"
},
  "geometry": {"coordinates":[-2.220989,53.044987],"type":"Point"}
}