{
  "type": "Feature",
  "properties": {
    "addr:full":"2-2a Mornington Road Bingley West Yorkshire BD16 4JS",
    "addr:housenumber":"2-2a",
    "addr:postcode":"bd16 4js",
    "addr:street":"Mornington Road",
    "iso:country":"GB",
    "sg:address":"2-2a Mornington Road",
    "sg:city":"Bingley",
    "sg:classifiers":[
        {
            "category":"Fast Food",
            "type":"Food & Drink"
        }
    ],
    "sg:phone":"+44 1274 551481",
    "sg:postcode":"BD16 4JS",
    "sg:province":"West Yorkshire",
    "sg:tags":[
        "away",
        "meal",
        "outlet",
        "take"
    ],
    "wof:name":"The Granary",
    "wof:placetype":"venue"
},
  "geometry": {"coordinates":[-1.832062006,53.8496856689],"type":"Point"}
}