{
  "type": "Feature",
  "properties": {
    "iso:country":"GB",
    "sg:address":"50 Palace Meadow, Chudleigh",
    "sg:city":"Newton Abbot",
    "sg:classifiers":[
        {
            "category":"Building & Trades",
            "subcategory":"Cleaning & Sanitation",
            "type":"Services"
        }
    ],
    "sg:phone":"+44 1626 853934",
    "sg:postcode":"TQ13 0PJ",
    "sg:province":"Devon",
    "sg:tags":[
        "commercial"
    ],
    "wof:name":"Bridgeman,Derek,",
    "wof:placetype":"venue"
},
  "geometry": {"coordinates":[-3.604091,50.60041],"type":"Point"}
}