{
  "type": "Feature",
  "properties": {
    "addr:full":"30 Albert Street Newark Nottinghamshire NG24 4BJ",
    "addr:housenumber":"30",
    "addr:postcode":"ng24 4bj",
    "addr:street":"Albert Street",
    "iso:country":"GB",
    "sg:address":"30 Albert Street",
    "sg:city":"Newark",
    "sg:classifiers":[
        {
            "category":"Shopping",
            "subcategory":"Pets & Pet Supplies",
            "type":"Retail Goods"
        }
    ],
    "sg:phone":"+44 1636 678552",
    "sg:postcode":"NG24 4BJ",
    "sg:province":"Nottinghamshire",
    "sg:tags":[
        "food"
    ],
    "wof:name":"Pets Pantry",
    "wof:placetype":"venue"
},
  "geometry": {"coordinates":[-0.8116260171,53.0732116699],"type":"Point"}
}