{
  "type": "Feature",
  "properties": {
    "addr:full":"73 The Sidings, Riverside View, Norton Malton North Yorkshire YO17 9RB",
    "addr:housenumber":"73",
    "addr:postcode":"yo17 9rb",
    "addr:street":"The Sidings Riverside View",
    "iso:country":"GB",
    "sg:address":"73 The Sidings, Riverside View, Norton",
    "sg:city":"Malton",
    "sg:classifiers":[
        {
            "category":"Community Center",
            "subcategory":"Youth",
            "type":"Public Place"
        }
    ],
    "sg:phone":"+44 1653 691400",
    "sg:postcode":"YO17 9RB",
    "sg:province":"North Yorkshire",
    "sg:tags":[
        "organisation",
        "centre"
    ],
    "wof:name":"Rydel Y M C A",
    "wof:placetype":"venue"
},
  "geometry": {"coordinates":[-0.785139,54.132477],"type":"Point"}
}