{
  "type": "Feature",
  "properties": {
    "addr:full":"The Market Place Ringwood Dorset BH24 1AW",
    "addr:postcode":"bh24 1aw",
    "addr:street":"Place",
    "iso:country":"GB",
    "sg:address":"The Market Place",
    "sg:city":"Ringwood",
    "sg:classifiers":[
        {
            "category":"Communications",
            "subcategory":"Film & Video Production",
            "type":"Services"
        }
    ],
    "sg:phone":"+44 1425 472707",
    "sg:postcode":"BH24 1AW",
    "sg:province":"Dorset",
    "sg:tags":[
        "tv"
    ],
    "wof:name":"Granada Home Technology",
    "wof:placetype":"venue"
},
  "geometry": {"coordinates":[-1.795593977,50.847278595],"type":"Point"}
}