{
  "type": "Feature",
  "properties": {
    "iso:country":"GB",
    "sg:address":"Llandaff North Community Centre",
    "sg:city":"Cardiff",
    "sg:classifiers":[
        {
            "category":"Personal",
            "type":"Services"
        }
    ],
    "sg:phone":"+44 29 2064 5125",
    "sg:postcode":"CF5 2DX",
    "sg:province":"Cardiff",
    "sg:tags":[
        "slimming",
        "product"
    ],
    "wof:name":"Slimming World",
    "wof:placetype":"venue"
},
  "geometry": {"coordinates":[-3.214187,51.493484],"type":"Point"}
}