{
  "type": "Feature",
  "properties": {
    "iso:country":"GB",
    "sg:address":"189 High Street",
    "sg:city":"Willesden",
    "sg:classifiers":[
        {
            "category":"Professional",
            "subcategory":"Computer Services",
            "type":"Services"
        }
    ],
    "sg:postcode":"NW10 4TE",
    "sg:province":"Greater London",
    "sg:tags":[
        "system",
        "software"
    ],
    "wof:name":"Grandborder Ltd",
    "wof:placetype":"venue"
},
  "geometry": {"coordinates":[-0.241517,51.534027],"type":"Point"}
}