{
  "type": "Feature",
  "properties": {
    "iso:country":"GB",
    "sg:address":"Westerland House, Westerland, Marldon",
    "sg:city":"Paignton",
    "sg:classifiers":[
        {
            "category":"Home & Garden",
            "subcategory":"Garden Supply",
            "type":"Retail Goods"
        }
    ],
    "sg:phone":"+44 1803 214421",
    "sg:postcode":"TQ3 1RR",
    "sg:province":"Devon",
    "sg:tags":[
        "pool",
        "swimming"
    ],
    "wof:name":"Mediterranean Pools",
    "wof:placetype":"venue"
},
  "geometry": {"coordinates":[-3.5930769444,50.454875946],"type":"Point"}
}