{
  "type": "Feature",
  "properties": {
    "addr:full":"6 Fountain Street Guisborough North Yorkshire TS14 6PP",
    "addr:housenumber":"6",
    "addr:postcode":"ts14 6pp",
    "addr:street":"Fountain Street",
    "iso:country":"GB",
    "sg:address":"6 Fountain Street",
    "sg:city":"Guisborough",
    "sg:classifiers":[
        {
            "category":"Personal",
            "subcategory":"Beauty Salon",
            "type":"Services"
        }
    ],
    "sg:phone":"+44 1287 638883",
    "sg:postcode":"TS14 6PP",
    "sg:province":"North Yorkshire",
    "sg:tags":[
        "unisex",
        "hairdresser"
    ],
    "wof:name":"Enrico Hair Design",
    "wof:placetype":"venue"
},
  "geometry": {"coordinates":[-1.0512290001,54.5347938538],"type":"Point"}
}