{
  "type": "Feature",
  "properties": {
    "iso:country":"GB",
    "sg:address":"10 Court Lane",
    "sg:city":"Portsmouth",
    "sg:classifiers":[
        {
            "category":"Building & Trades",
            "subcategory":"Plumbing",
            "type":"Services"
        }
    ],
    "sg:phone":"+44 23 9232 4737",
    "sg:postcode":"PO6 2LN",
    "sg:province":"Hampshire",
    "sg:tags":[
        "plumber",
        "heating"
    ],
    "wof:name":"D Harwood",
    "wof:placetype":"venue"
},
  "geometry": {"coordinates":[-1.0565880537,50.8450965881],"type":"Point"}
}