{
  "type": "Feature",
  "properties": {
    "iso:country":"GB",
    "sg:address":"22 Coten End",
    "sg:city":"Warwick",
    "sg:classifiers":[
        {
            "category":"Retail",
            "subcategory":"Auto Repair",
            "type":"Services"
        }
    ],
    "sg:phone":"+44 1926 495496",
    "sg:postcode":"CV34 4NP",
    "sg:province":"Warwickshire",
    "sg:tags":[
        "modification",
        "garage"
    ],
    "wof:name":"Hm Bryan & Sons Ltd.",
    "wof:placetype":"venue"
},
  "geometry": {"coordinates":[-1.5783250332,52.2843780518],"type":"Point"}
}