{
  "type": "Feature",
  "properties": {
    "addr:full":"6a Station Road, Holme Peterborough Cambridgeshire PE7 3PH",
    "addr:housenumber":"6a",
    "addr:postcode":"pe7 3ph",
    "addr:street":"Station Road",
    "iso:country":"GB",
    "sg:address":"6a Station Road, Holme",
    "sg:city":"Peterborough",
    "sg:classifiers":[
        {
            "category":"Utilities",
            "subcategory":"Fuel Oil & Lpg",
            "type":"Services"
        }
    ],
    "sg:postcode":"PE7 3PH",
    "sg:province":"Cambridgeshire",
    "sg:tags":[
        "coal",
        "smokeless"
    ],
    "wof:name":"W Ayres & Sons",
    "wof:placetype":"venue"
},
  "geometry": {"coordinates":[-0.244545,52.474068],"type":"Point"}
}