{
  "type": "Feature",
  "properties": {
    "addr:full":"The Whitehouse, Wilsthorpe Bridlington East Riding of Yorkshire YO15 3QN",
    "addr:postcode":"yo15 3qn",
    "iso:country":"GB",
    "sg:address":"The Whitehouse, Wilsthorpe",
    "sg:city":"Bridlington",
    "sg:classifiers":[
        {
            "category":"Recreation",
            "subcategory":"Campground",
            "type":"Entertainment"
        }
    ],
    "sg:postcode":"YO15 3QN",
    "sg:province":"East Riding of Yorkshire",
    "sg:tags":[
        "caravan",
        "park"
    ],
    "wof:name":"Whitehouse Caravan Parks",
    "wof:placetype":"venue"
},
  "geometry": {"coordinates":[-0.220714,54.061298],"type":"Point"}
}