{
  "type": "Feature",
  "properties": {
    "addr:full":"Lake Farm, Eavestone Ripon North Yorkshire HG4 3HD",
    "addr:postcode":"hg4 3hd",
    "addr:street":"Lake",
    "iso:country":"GB",
    "sg:address":"Lake Farm, Eavestone",
    "sg:city":"Ripon",
    "sg:classifiers":[
        {
            "category":"Autos & Motor Vehicles",
            "subcategory":"Automobile Sales",
            "type":"Retail Goods"
        },
        {
            "category":"Utilities",
            "subcategory":"Natural Gas",
            "type":"Services"
        }
    ],
    "sg:phone":"+44 1765 620684",
    "sg:postcode":"HG4 3HD",
    "sg:province":"North Yorkshire",
    "sg:tags":[
        "supplier",
        "car"
    ],
    "wof:name":"North Riding Automotive",
    "wof:placetype":"venue"
},
  "geometry": {"coordinates":[-1.6574039459,54.1024246216],"type":"Point"}
}