{
  "type": "Feature",
  "properties": {
    "addr:full":"Colmar House, Middleton Gardens, Middleton Manchester Greater Manchester M24 4DB",
    "addr:postcode":"m24 4db",
    "addr:street":"Middleton Gardens",
    "iso:country":"GB",
    "sg:address":"Colmar House, Middleton Gardens, Middleton",
    "sg:city":"Manchester",
    "sg:classifiers":[
        {
            "category":"Professional",
            "subcategory":"Lawyer & Legal Services",
            "type":"Services"
        }
    ],
    "sg:phone":"+44 161 653 6200",
    "sg:postcode":"M24 4DB",
    "sg:province":"Greater Manchester",
    "sg:tags":[
        "solicitor"
    ],
    "wof:name":"Allan Walsh",
    "wof:placetype":"venue"
},
  "geometry": {"coordinates":[-2.235722,53.54147],"type":"Point"}
}