{
  "type": "Feature",
  "properties": {
    "addr:full":"Langport Road Somerton Somerset TA11 6RS",
    "addr:postcode":"ta11 6rs",
    "addr:street":"Langport Road",
    "iso:country":"GB",
    "sg:address":"Langport Road",
    "sg:city":"Somerton",
    "sg:classifiers":[
        {
            "category":"Retail",
            "subcategory":"Auto Repair",
            "type":"Services"
        }
    ],
    "sg:phone":"+44 1458 272342",
    "sg:postcode":"TA11 6RS",
    "sg:province":"Somerset",
    "sg:tags":[
        "modification",
        "garage"
    ],
    "wof:name":"Corkhill Motors",
    "wof:placetype":"venue"
},
  "geometry": {"coordinates":[-2.7428679466,51.0548324585],"type":"Point"}
}