{
  "type": "Feature",
  "properties": {
    "iso:country":"GB",
    "sg:address":"32 Kimpton Road",
    "sg:city":"Sutton",
    "sg:classifiers":[
        {
            "category":"Manufacturing",
            "subcategory":"Tools & Machinery",
            "type":"Manufacturing & Wholesale Goods"
        }
    ],
    "sg:phone":"+44 20 8644 1133",
    "sg:postcode":"SM3 9RB",
    "sg:province":"Surrey",
    "sg:tags":[
        "design",
        "maker"
    ],
    "wof:name":"Southern Tools Ltd.",
    "wof:placetype":"venue"
},
  "geometry": {"coordinates":[-0.2088990062,51.3757209778],"type":"Point"}
}