{
  "type": "Feature",
  "properties": {
    "addr:full":"95a Euston Road Morecambe Lancashire LA4 5JY",
    "addr:housenumber":"95a",
    "addr:postcode":"la4 5jy",
    "addr:street":"Euston Road",
    "iso:country":"GB",
    "sg:address":"95a Euston Road",
    "sg:city":"Morecambe",
    "sg:classifiers":[
        {
            "category":"Social Services",
            "type":"Services"
        }
    ],
    "sg:phone":"+44 1524 411613",
    "sg:postcode":"LA4 5JY",
    "sg:province":"Lancashire",
    "sg:tags":[
        "need",
        "disability",
        "special"
    ],
    "wof:name":"James Nesbit",
    "wof:placetype":"venue"
},
  "geometry": {"coordinates":[-2.8640809059,54.070892334],"type":"Point"}
}