{
  "type": "Feature",
  "properties": {
    "addr:full":"Unit 2 Glass Court, Finney Lane, Heald Green Cheadle Cheshire SK8 3QA",
    "addr:housenumber":"unit 2",
    "addr:postcode":"sk8 3qa",
    "addr:street":"Glass Court Finney Lane",
    "iso:country":"GB",
    "sg:address":"Unit 2 Glass Court, Finney Lane, Heald Green",
    "sg:city":"Cheadle",
    "sg:classifiers":[
        {
            "category":"Shopping",
            "subcategory":"Pets & Pet Supplies",
            "type":"Retail Goods"
        }
    ],
    "sg:phone":"+44 161 498 0912",
    "sg:postcode":"SK8 3QA",
    "sg:province":"Cheshire",
    "sg:tags":[
        "food"
    ],
    "wof:name":"Heald Green Pet Supplies",
    "wof:placetype":"venue"
},
  "geometry": {"coordinates":[-2.2381539345,53.3706665039],"type":"Point"}
}