{
  "type": "Feature",
  "properties": {
    "iso:country":"GB",
    "sg:address":"The Sawmills Caravan, Durham Road, Wolsingham",
    "sg:city":"Bishop Auckland",
    "sg:classifiers":[
        {
            "category":"Autos & Motor Vehicles",
            "subcategory":"Auto Supplies",
            "type":"Retail Goods"
        },
        {
            "category":"Retail",
            "subcategory":"Auto Repair",
            "type":"Services"
        }
    ],
    "sg:phone":"+44 1388 527440",
    "sg:postcode":"DL13 3JB",
    "sg:province":"Durham",
    "sg:tags":[
        "garage",
        "related",
        "tyre"
    ],
    "wof:name":"J D & J Watson & Son",
    "wof:placetype":"venue"
},
  "geometry": {"coordinates":[-1.8722100258,54.7304115295],"type":"Point"}
}