{
  "type": "Feature",
  "properties": {
    "iso:country":"GB",
    "sg:address":"Fencepiece Road",
    "sg:city":"Ilford",
    "sg:classifiers":[
        {
            "category":"Bars & Pubs",
            "type":"Food & Drink"
        }
    ],
    "sg:phone":"+44 20 8501 4483",
    "sg:postcode":"IG6 2NG",
    "sg:province":"Essex",
    "sg:tags":[
        "pubs",
        "inn"
    ],
    "wof:name":"The Old Maypole",
    "wof:placetype":"venue"
},
  "geometry": {"coordinates":[0.0832249969,51.6063613892],"type":"Point"}
}