{
  "type": "Feature",
  "properties": {
    "addr:full":"Brading Crescent, Park Road, Wanstead London Greater London E12 5HG",
    "addr:postcode":"london e12 5hg",
    "addr:street":"Brading Crescent Park Road",
    "iso:country":"GB",
    "sg:address":"Brading Crescent, Park Road, Wanstead",
    "sg:city":"London",
    "sg:classifiers":[
        {
            "category":"Education",
            "subcategory":"Dance Studio",
            "type":"Public Place"
        }
    ],
    "sg:postcode":"E12 5HG",
    "sg:province":"Greater London",
    "sg:tags":[
        "school",
        "dancing"
    ],
    "wof:name":"Variations Dance Studio",
    "wof:placetype":"venue"
},
  "geometry": {"coordinates":[0.0326099992,51.5646781921],"type":"Point"}
}