{
  "type": "Feature",
  "properties": {
    "iso:country":"GB",
    "sg:address":"46-48 Westgate St",
    "sg:city":"Ipswich",
    "sg:classifiers":[
        {
            "category":"Shopping",
            "subcategory":"Thrift Store",
            "type":"Retail Goods"
        }
    ],
    "sg:phone":"+44 1473 211233",
    "sg:postcode":"IP1 3ED",
    "sg:province":"Suffolk",
    "sg:tags":[
        "shop",
        "charity"
    ],
    "wof:name":"PDSA Shop",
    "wof:placetype":"venue"
},
  "geometry": {"coordinates":[1.1501940489,52.0589370728],"type":"Point"}
}