{
  "type": "Feature",
  "properties": {
    "addr:full":"School Farm, Newcastle Road, Smallwood Sandbach Cheshire CW11 2TZ",
    "addr:postcode":"cw11 2tz",
    "addr:street":"Newcastle Road",
    "iso:country":"GB",
    "sg:address":"School Farm, Newcastle Road, Smallwood",
    "sg:city":"Sandbach",
    "sg:classifiers":[
        {
            "category":"Building & Trades",
            "subcategory":"Landscaping Services",
            "type":"Services"
        }
    ],
    "sg:phone":"+44 1270 762786",
    "sg:postcode":"CW11 2TZ",
    "sg:province":"Cheshire",
    "sg:tags":[
        "landscape",
        "contractor"
    ],
    "wof:name":"R J Pugh",
    "wof:placetype":"venue"
},
  "geometry": {"coordinates":[-2.291324,53.137825],"type":"Point"}
}