{
  "type": "Feature",
  "properties": {
    "addr:full":"54 The Broadwalk, The Bdwy, Ealing London Greater London W5 5JN",
    "addr:housenumber":"54",
    "addr:postcode":"w5 5jn",
    "addr:street":"The Broadwalk The Bdwy",
    "iso:country":"GB",
    "sg:address":"54 The Broadwalk, The Bdwy, Ealing",
    "sg:city":"London",
    "sg:classifiers":[
        {
            "category":"Professional",
            "subcategory":"Computer Services",
            "type":"Services"
        }
    ],
    "sg:phone":"+44 20 8566 2330",
    "sg:postcode":"W5 5JN",
    "sg:province":"Greater London",
    "sg:tags":[
        "system",
        "software"
    ],
    "wof:name":"Crystal Decisions (U K) Ltd.",
    "wof:placetype":"venue"
},
  "geometry": {"coordinates":[-0.3027999997,51.5136985779],"type":"Point"}
}