{
  "type": "Feature",
  "properties": {
    "addr:full":"Coppas, Labour In Vain Rd, Wrotham Sevenoaks Kent TN15 7PA",
    "addr:postcode":"tn15 7pa",
    "addr:street":"Vain Rd",
    "iso:country":"GB",
    "sg:address":"Coppas, Labour In Vain Rd, Wrotham",
    "sg:city":"Sevenoaks",
    "sg:classifiers":[
        {
            "category":"Real Estate",
            "subcategory":"Architect",
            "type":"Services"
        }
    ],
    "sg:phone":"+44 1732 823523",
    "sg:postcode":"TN15 7PA",
    "sg:province":"Kent",
    "wof:name":"Axis Partnership",
    "wof:placetype":"venue"
},
  "geometry": {"coordinates":[0.3090850115,51.3082962036],"type":"Point"}
}