{
  "type": "Feature",
  "properties": {
    "iso:country":"GB",
    "sg:address":"Beech Lane, Longcroft",
    "sg:city":"Bonnybridge",
    "sg:classifiers":[
        {
            "category":"Building & Trades",
            "subcategory":"Landscaping Services",
            "type":"Services"
        }
    ],
    "sg:phone":"+44 1324 840223",
    "sg:postcode":"FK4 1SX",
    "sg:province":"Falkirk",
    "sg:tags":[
        "landscape",
        "contractor"
    ],
    "wof:name":"Horticulture Services",
    "wof:placetype":"venue"
},
  "geometry": {"coordinates":[-3.881618,56.002949],"type":"Point"}
}