{
  "type": "Feature",
  "properties": {
    "addr:full":"Stalheim, Hastingwood Rd Harlow Essex CM17 9JU",
    "addr:postcode":"cm17 9ju",
    "addr:street":"Hastingwood Rd",
    "iso:country":"GB",
    "sg:address":"Stalheim, Hastingwood Rd",
    "sg:city":"Harlow",
    "sg:classifiers":[
        {
            "category":"Wholesale",
            "subcategory":"Books, Periodicals, & Newspapers",
            "type":"Manufacturing & Wholesale Goods"
        }
    ],
    "sg:phone":"+44 1279 421696",
    "sg:postcode":"CM17 9JU",
    "sg:province":"Essex",
    "sg:tags":[
        "publishing"
    ],
    "wof:name":"Folan & Parris Publishing Ltd",
    "wof:placetype":"venue"
},
  "geometry": {"coordinates":[0.1556899995,51.7497825623],"type":"Point"}
}