{
  "type": "Feature",
  "properties": {
    "addr:full":"3a Gravel Walk Rochester Kent ME1 1XP",
    "addr:housenumber":"3a",
    "addr:postcode":"me1 1xp",
    "addr:street":"Gravel Walk",
    "iso:country":"GB",
    "sg:address":"3a Gravel Walk",
    "sg:city":"Rochester",
    "sg:classifiers":[
        {
            "category":"Place Of Worship",
            "type":"Public Place"
        }
    ],
    "sg:phone":"+44 1634 849023",
    "sg:postcode":"ME1 1XP",
    "sg:province":"Kent",
    "wof:name":"Jehovah's Witnesses",
    "wof:placetype":"venue"
},
  "geometry": {"coordinates":[0.505947,51.384758],"type":"Point"}
}