{
  "type": "Feature",
  "properties": {
    "iso:country":"GB",
    "sg:address":"113 Beech Hill Avenue",
    "sg:city":"Wigan",
    "sg:classifiers":[
        {
            "category":"Professional",
            "subcategory":"Computer Services",
            "type":"Services"
        }
    ],
    "sg:phone":"+44 1942 731700",
    "sg:postcode":"WN6 7RP",
    "sg:province":"Lancashire",
    "sg:tags":[
        "system",
        "software"
    ],
    "wof:name":"O B S Computers",
    "wof:placetype":"venue"
},
  "geometry": {"coordinates":[-2.6544909477,53.559261322],"type":"Point"}
}