{
  "type": "Feature",
  "properties": {
    "addr:full":"The Boat House Lodge, Lintrathen Reservoir, Lintrathen Kirriemuir Angus DD8 5JJ",
    "addr:housenumber":"house",
    "addr:postcode":"dd8 5jj",
    "addr:street":"Lintrathen;Lintrathen",
    "iso:country":"GB",
    "sg:address":"The Boat House Lodge, Lintrathen Reservoir, Lintrathen",
    "sg:city":"Kirriemuir",
    "sg:classifiers":[
        {
            "category":"Organizations",
            "subcategory":"Community Association",
            "type":"Services"
        },
        {
            "category":"Organizations",
            "subcategory":"Membership Organization",
            "type":"Services"
        }
    ],
    "sg:phone":"+44 1575 560327",
    "sg:postcode":"DD8 5JJ",
    "sg:province":"Angus",
    "sg:tags":[
        "club",
        "social"
    ],
    "wof:name":"Lintrathen Angling Club",
    "wof:placetype":"venue"
},
  "geometry": {"coordinates":[-3.166960001,56.6783447266],"type":"Point"}
}