{
  "type": "Feature",
  "properties": {
    "addr:full":"Unit 41 Evelyn St, Beeston Nottingham Nottinghamshire NG9 2EU",
    "addr:housenumber":"unit 41",
    "addr:postcode":"ng9 2eu",
    "addr:street":"Evelyn St",
    "iso:country":"GB",
    "sg:address":"Unit 41 Evelyn St, Beeston",
    "sg:city":"Nottingham",
    "sg:classifiers":[
        {
            "category":"Professional",
            "subcategory":"Business Services",
            "type":"Services"
        }
    ],
    "sg:phone":"+44 115 922 9902",
    "sg:postcode":"NG9 2EU",
    "sg:province":"Nottinghamshire",
    "sg:tags":[
        "import",
        "export",
        "agent"
    ],
    "wof:name":"Florence Uk Ltd",
    "wof:placetype":"venue"
},
  "geometry": {"coordinates":[-1.2043449879,52.9282951355],"type":"Point"}
}