{
  "type": "Feature",
  "properties": {
    "addr:full":"35 Gorsey Road Manchester Greater Manchester M22 9HQ",
    "addr:housenumber":"35",
    "addr:postcode":"m22 9hq",
    "addr:street":"Gorsey Road",
    "iso:country":"GB",
    "sg:address":"35 Gorsey Road",
    "sg:city":"Manchester",
    "sg:classifiers":[
        {
            "category":"Personal",
            "subcategory":"Psychics & Astrologers",
            "type":"Services"
        }
    ],
    "sg:postcode":"M22 9HQ",
    "sg:province":"Greater Manchester",
    "sg:tags":[
        "clairvoyant",
        "palmist"
    ],
    "wof:name":"Karmel Clairvoyant",
    "wof:placetype":"venue"
},
  "geometry": {"coordinates":[-2.270244,53.388336],"type":"Point"}
}