{
  "type": "Feature",
  "properties": {
    "addr:full":"Camwal Road, Starbeck Harrogate North Yorkshire HG1 4PY",
    "addr:postcode":"hg1 4py",
    "addr:street":"Camwal Road",
    "iso:country":"GB",
    "sg:address":"Camwal Road, Starbeck",
    "sg:city":"Harrogate",
    "sg:classifiers":[
        {
            "category":"Food & Beverages",
            "subcategory":"Candy",
            "type":"Retail Goods"
        }
    ],
    "sg:postcode":"HG1 4PY",
    "sg:province":"North Yorkshire",
    "sg:tags":[
        "confectionery"
    ],
    "wof:name":"John Farrah & Harrogate Toffee",
    "wof:placetype":"venue"
},
  "geometry": {"coordinates":[-1.500756,53.999817],"type":"Point"}
}