{
  "type": "Feature",
  "properties": {
    "addr:full":"1 Pudding Lane London Greater London EC3R 8AB",
    "addr:housenumber":"1",
    "addr:postcode":"ec3r 8ab",
    "addr:street":"Pudding Lane",
    "iso:country":"GB",
    "sg:address":"1 Pudding Lane",
    "sg:city":"London",
    "sg:classifiers":[
        {
            "category":"Professional",
            "subcategory":"Employment Agencies",
            "type":"Services"
        }
    ],
    "sg:phone":"+44 20 7929 5284",
    "sg:postcode":"EC3R 8AB",
    "sg:province":"Greater London",
    "sg:tags":[
        "consultant"
    ],
    "wof:name":"Manpower Plc",
    "wof:placetype":"venue"
},
  "geometry": {"coordinates":[-0.085474,51.510456],"type":"Point"}
}