{
  "type": "Feature",
  "properties": {
    "iso:country":"GB",
    "sg:address":"Mile Oak Industrial Estate",
    "sg:city":"Oswestry",
    "sg:classifiers":[
        {
            "category":"Cafe",
            "type":"Food & Drink"
        }
    ],
    "sg:phone":"+44 1691 655033",
    "sg:postcode":"SY10 8HA",
    "sg:province":"Shropshire",
    "sg:tags":[
        "tea",
        "room"
    ],
    "wof:name":"Miriam Susan Williams",
    "wof:placetype":"venue"
},
  "geometry": {"coordinates":[-3.04378,52.848431],"type":"Point"}
}