{
  "type": "Feature",
  "properties": {
    "iso:country":"GB",
    "sg:address":"7 G 2 The Leather Market, Weston Street",
    "sg:city":"London",
    "sg:classifiers":[
        {
            "category":"Banks & Credit Unions",
            "subcategory":"Investment Brokerage",
            "type":"Services"
        }
    ],
    "sg:phone":"+44 20 7403 8383",
    "sg:postcode":"SE1 3ER",
    "sg:province":"Greater London",
    "wof:name":"Derivatives Management Services Ltd.",
    "wof:placetype":"venue"
},
  "geometry": {"coordinates":[-0.08446,51.500389],"type":"Point"}
}