{
  "type": "Feature",
  "properties": {
    "addr:full":"Shugden Barn, Roper Lane, Queensbury Bradford West Yorkshire BD13 2NT",
    "addr:postcode":"bd13 2nt",
    "addr:street":"Roper Lane;Bradford West",
    "iso:country":"GB",
    "sg:address":"Shugden Barn, Roper Lane, Queensbury",
    "sg:city":"Bradford",
    "sg:classifiers":[
        {
            "category":"Building & Trades",
            "subcategory":"Construction",
            "type":"Services"
        }
    ],
    "sg:phone":"+44 1274 880120",
    "sg:postcode":"BD13 2NT",
    "sg:province":"West Yorkshire",
    "sg:tags":[
        "bricklaying"
    ],
    "wof:name":"D C Liptrot Building Contractors",
    "wof:placetype":"venue"
},
  "geometry": {"coordinates":[-1.8459240198,53.7682495117],"type":"Point"}
}