{
  "type": "Feature",
  "properties": {
    "iso:country":"GB",
    "sg:address":"Exhibition Centre, Parker Lane",
    "sg:city":"Burnley",
    "sg:classifiers":[
        {
            "category":"Sports & Exercise",
            "subcategory":"Gym",
            "type":"Entertainment"
        }
    ],
    "sg:phone":"+44 1282 412800",
    "sg:postcode":"BB11 2BY",
    "sg:province":"Lancashire",
    "sg:tags":[
        "fitness",
        "health",
        "centre"
    ],
    "wof:name":"Classic World of Fitness Ltd.",
    "wof:placetype":"venue"
},
  "geometry": {"coordinates":[-2.243809,53.78801],"type":"Point"}
}