{
  "type": "Feature",
  "properties": {
    "addr:full":"7 Long Clo, Fowlmere Royston Bedfordshire SG8 7SG",
    "addr:housenumber":"7",
    "addr:postcode":"sg8 7sg",
    "addr:street":"Long Clo Fowlmere",
    "iso:country":"GB",
    "sg:address":"7 Long Clo, Fowlmere",
    "sg:city":"Royston",
    "sg:classifiers":[
        {
            "category":"Home & Garden",
            "subcategory":"Furniture",
            "type":"Retail Goods"
        }
    ],
    "sg:postcode":"SG8 7SG",
    "sg:province":"Bedfordshire",
    "wof:name":"Buckhurst Furnishing",
    "wof:placetype":"venue"
},
  "geometry": {"coordinates":[0.07271,52.090672],"type":"Point"}
}