{
  "type": "Feature",
  "properties": {
    "iso:country":"GB",
    "sg:address":"18 Essex Ave",
    "sg:city":"Manchester",
    "sg:classifiers":[
        {
            "category":"Professional",
            "subcategory":"Art Services",
            "type":"Services"
        }
    ],
    "sg:postcode":"M20 6AN",
    "sg:province":"Greater Manchester",
    "sg:tags":[
        "graphic",
        "designer"
    ],
    "wof:name":"Jeffs,Howard,",
    "wof:placetype":"venue"
},
  "geometry": {"coordinates":[-2.226099,53.415852],"type":"Point"}
}