{
  "type": "Feature",
  "properties": {
    "iso:country":"GB",
    "sg:address":"77 Capel Rd",
    "sg:city":"Swansea",
    "sg:classifiers":[
        {
            "category":"Professional",
            "subcategory":"Detective & Security Services",
            "type":"Services"
        }
    ],
    "sg:phone":"+44 1792 845526",
    "sg:postcode":"SA6 5PY",
    "sg:province":"Swansea",
    "sg:tags":[
        "agency"
    ],
    "wof:name":"Confidential Services",
    "wof:placetype":"venue"
},
  "geometry": {"coordinates":[-3.885596,51.698914],"type":"Point"}
}