{
  "type": "Feature",
  "properties": {
    "iso:country":"GB",
    "sg:address":"91 Front Street",
    "sg:city":"Stanley",
    "sg:classifiers":[
        {
            "category":"Real Estate",
            "subcategory":"Real Estate Agent",
            "type":"Services"
        }
    ],
    "sg:phone":"+44 1207 235221",
    "sg:postcode":"DH9 0TB",
    "sg:province":"Durham",
    "wof:name":"J W Wood Ltd.",
    "wof:placetype":"venue"
},
  "geometry": {"coordinates":[-1.700059,54.868259],"type":"Point"}
}