{
  "type": "Feature",
  "properties": {
    "iso:country":"GB",
    "sg:address":"43 High Street, Great Shelford",
    "sg:city":"Cambridge",
    "sg:classifiers":[
        {
            "category":"Farming",
            "subcategory":"Fish & Marine Products",
            "type":"Manufacturing & Wholesale Goods"
        },
        {
            "category":"Food & Beverages",
            "subcategory":"Meat & Fish",
            "type":"Retail Goods"
        }
    ],
    "sg:phone":"+44 1223 843292",
    "sg:postcode":"CB2 5EH",
    "sg:province":"Cambridgeshire",
    "sg:tags":[
        "fishmonger",
        "butcher"
    ],
    "wof:name":"Barker Bros",
    "wof:placetype":"venue"
},
  "geometry": {"coordinates":[0.036432,52.1278],"type":"Point"}
}