{
  "type": "Feature",
  "properties": {
    "addr:full":"309 Camberwell Road London Greater London SE5 0HQ",
    "addr:housenumber":"309",
    "addr:postcode":"se5 0hq",
    "addr:street":"Camberwell Road",
    "iso:country":"GB",
    "sg:address":"309 Camberwell Road",
    "sg:city":"London",
    "sg:classifiers":[
        {
            "category":"Personal",
            "subcategory":"Beauty Salon",
            "type":"Services"
        }
    ],
    "sg:phone":"+44 20 7277 1007",
    "sg:postcode":"SE5 0HQ",
    "sg:province":"Greater London",
    "sg:tags":[
        "unisex",
        "hairdresser"
    ],
    "wof:name":"Penelope Emery",
    "wof:placetype":"venue"
},
  "geometry": {"coordinates":[-0.093488,51.47583],"type":"Point"}
}