{
  "type": "Feature",
  "properties": {
    "addr:full":"The Co-op Centre, 11 Mowll Street London Greater London SW9 6BG",
    "addr:housenumber":"11",
    "addr:postcode":"sw9 6bg",
    "addr:street":"Mowll Street",
    "iso:country":"GB",
    "sg:address":"The Co-op Centre, 11 Mowll Street",
    "sg:city":"London",
    "sg:classifiers":[
        {
            "category":"Organizations",
            "subcategory":"Non-profit Organization",
            "type":"Services"
        }
    ],
    "sg:phone":"+44 20 7820 3800",
    "sg:postcode":"SW9 6BG",
    "sg:province":"Greater London",
    "sg:tags":[
        "organisation",
        "voluntary",
        "charity"
    ],
    "wof:name":"Playlink",
    "wof:placetype":"venue"
},
  "geometry": {"coordinates":[-0.113476,51.477627],"type":"Point"}
}