{
  "type": "Feature",
  "properties": {
    "addr:full":"Heber Road London Greater London SE22 9LA",
    "addr:postcode":"se22 9la",
    "addr:street":"Heber Road",
    "iso:country":"GB",
    "sg:address":"Heber Road",
    "sg:city":"London",
    "sg:classifiers":[
        {
            "category":"Organizations",
            "subcategory":"Non-profit Organization",
            "type":"Services"
        }
    ],
    "sg:postcode":"SE22 9LA",
    "sg:province":"Greater London",
    "sg:tags":[
        "organisation",
        "voluntary",
        "charity"
    ],
    "wof:name":"Southwark Childrens Foundation",
    "wof:placetype":"venue"
},
  "geometry": {"coordinates":[-0.075319,51.453186],"type":"Point"}
}