{
  "type": "Feature",
  "properties": {
    "addr:full":"10 Warren Avenue South Fleetwood Lancashire FY7 7AT",
    "addr:housenumber":"10",
    "addr:postcode":"fy7 7at",
    "addr:street":"Warren Avenue South",
    "iso:country":"GB",
    "sg:address":"10 Warren Avenue South",
    "sg:city":"Fleetwood",
    "sg:classifiers":[
        {
            "category":"Building & Trades",
            "subcategory":"Construction",
            "type":"Services"
        }
    ],
    "sg:phone":"+44 1253 873778",
    "sg:postcode":"FY7 7AT",
    "sg:province":"Lancashire",
    "sg:tags":[
        "repair",
        "guttering"
    ],
    "wof:name":"Fylde Coast Fascias",
    "wof:placetype":"venue"
},
  "geometry": {"coordinates":[-3.0226531029,53.9223937988],"type":"Point"}
}