{
  "type": "Feature",
  "properties": {
    "addr:full":"298 High Road Benfleet Essex SS7 5HB",
    "addr:housenumber":"298",
    "addr:postcode":"ss7 5hb",
    "addr:street":"High Road",
    "iso:country":"GB",
    "sg:address":"298 High Road",
    "sg:city":"Benfleet",
    "sg:classifiers":[
        {
            "category":"Communications",
            "type":"Services"
        }
    ],
    "sg:phone":"+44 1268 757860",
    "sg:postcode":"SS7 5HB",
    "sg:province":"Essex",
    "sg:tags":[
        "tv",
        "video",
        "radio"
    ],
    "wof:name":"Benfleet Electronic Services",
    "wof:placetype":"venue"
},
  "geometry": {"coordinates":[0.5584769845,51.5541496277],"type":"Point"}
}