{
  "type": "Feature",
  "properties": {
    "iso:country":"GB",
    "sg:address":"88 Davigdor Road",
    "sg:city":"Hove",
    "sg:classifiers":[
        {
            "category":"Shopping",
            "subcategory":"Pharmacy",
            "type":"Retail Goods"
        }
    ],
    "sg:phone":"+44 1273 208233",
    "sg:postcode":"BN3 1RF",
    "sg:province":"East Sussex",
    "sg:tags":[
        "store",
        "drug"
    ],
    "wof:name":"Manjit Panbsar",
    "wof:placetype":"venue"
},
  "geometry": {"coordinates":[-0.157119,50.831348],"type":"Point"}
}