{
  "type": "Feature",
  "properties": {
    "addr:full":"222 Kentish Town Road London Greater London NW5 2AD",
    "addr:housenumber":"222",
    "addr:postcode":"nw5 2ad",
    "addr:street":"Kentish Town Road",
    "iso:country":"GB",
    "sg:address":"222 Kentish Town Road",
    "sg:city":"London",
    "sg:classifiers":[
        {
            "category":"Home & Garden",
            "subcategory":"Home Furnishings",
            "type":"Retail Goods"
        }
    ],
    "sg:phone":"+44 20 7485 3266",
    "sg:postcode":"NW5 2AD",
    "sg:province":"Greater London",
    "sg:tags":[
        "furnishers",
        "planner",
        "kitchen"
    ],
    "wof:name":"Space Savers (London) Ltd.",
    "wof:placetype":"venue"
},
  "geometry": {"coordinates":[-0.140982,51.548656],"type":"Point"}
}