{
  "type": "Feature",
  "properties": {
    "iso:country":"GB",
    "sg:address":"Regent House, 16 West Walk",
    "sg:city":"Leicester",
    "sg:classifiers":[
        {
            "category":"Professional",
            "type":"Services"
        }
    ],
    "sg:phone":"+44 116 222 0200",
    "sg:postcode":"LE1 7NA",
    "sg:province":"Leicestershire",
    "sg:tags":[
        "aircraft",
        "maintenance"
    ],
    "wof:name":"Luggage Express Ltd",
    "wof:placetype":"venue"
},
  "geometry": {"coordinates":[-1.124739,52.626652],"type":"Point"}
}