{
  "type": "Feature",
  "properties": {
    "addr:full":"Unit 1-4 Sherwood Industrial Estate Bonnyrigg Midlothian EH19 3LW",
    "addr:housenumber":"unit 1-4",
    "addr:postcode":"eh19 3lw",
    "addr:street":"Sherwood Industrial Estate",
    "iso:country":"GB",
    "sg:address":"Unit 1-4 Sherwood Industrial Estate",
    "sg:city":"Bonnyrigg",
    "sg:classifiers":[
        {
            "category":"Professional",
            "subcategory":"Printing & Photocopies",
            "type":"Services"
        }
    ],
    "sg:postcode":"EH19 3LW",
    "sg:province":"Midlothian",
    "sg:tags":[
        "printer"
    ],
    "wof:name":"Printhaus Plc",
    "wof:placetype":"venue"
},
  "geometry": {"coordinates":[-3.1040699482,55.8740348816],"type":"Point"}
}