{
  "type": "Feature",
  "properties": {
    "iso:country":"GB",
    "sg:address":"94 Nottingham Road",
    "sg:city":"Ripley",
    "sg:classifiers":[
        {
            "category":"Personal",
            "subcategory":"Tattoo Parlor",
            "type":"Services"
        }
    ],
    "sg:phone":"+44 1773 570361",
    "sg:postcode":"DE5 3AX",
    "sg:province":"Derbyshire",
    "sg:tags":[
        "tattooing",
        "piercing"
    ],
    "wof:name":"Dragonclaw",
    "wof:placetype":"venue"
},
  "geometry": {"coordinates":[-1.3971569538,53.0516891479],"type":"Point"}
}