{
  "type": "Feature",
  "properties": {
    "addr:full":"1 Marylebone High Street London Greater London W1U 4NQ",
    "addr:housenumber":"1",
    "addr:postcode":"w1u 4nq",
    "addr:street":"Marylebone High Street",
    "iso:country":"GB",
    "sg:address":"1 Marylebone High Street",
    "sg:city":"London",
    "sg:classifiers":[
        {
            "category":"Shopping",
            "subcategory":"Books",
            "type":"Retail Goods"
        }
    ],
    "sg:postcode":"W1U 4NQ",
    "sg:province":"Greater London",
    "wof:name":"Gmg Publishing Ltd",
    "wof:placetype":"venue"
},
  "geometry": {"coordinates":[-0.151889,51.520748],"type":"Point"}
}