{
  "type": "Feature",
  "properties": {
    "addr:full":"Main Office, Windmill La East Grinstead East Sussex RH19 2DT",
    "addr:postcode":"rh19 2dt",
    "addr:street":"Windmill La East",
    "iso:country":"GB",
    "sg:address":"Main Office, Windmill La",
    "sg:city":"East Grinstead",
    "sg:classifiers":[
        {
            "category":"Education",
            "subcategory":"University",
            "type":"Public Place"
        }
    ],
    "sg:phone":"+44 1342 321874",
    "sg:postcode":"RH19 2DT",
    "sg:province":"East Sussex",
    "sg:tags":[
        "adult"
    ],
    "wof:name":"East Grinstead Adult Education Centre",
    "wof:placetype":"venue"
},
  "geometry": {"coordinates":[-0.007568,51.123981],"type":"Point"}
}