{
  "type": "Feature",
  "properties": {
    "addr:full":"17 Lynwood Avenue Exeter Devon EX4 1EF",
    "addr:housenumber":"17",
    "addr:postcode":"ex4 1ef",
    "addr:street":"Lynwood Avenue",
    "iso:country":"GB",
    "sg:address":"17 Lynwood Avenue",
    "sg:city":"Exeter",
    "sg:classifiers":[
        {
            "category":"Retail",
            "subcategory":"Repair Shop",
            "type":"Services"
        }
    ],
    "sg:postcode":"EX4 1EF",
    "sg:province":"Devon",
    "sg:tags":[
        "radio",
        "television",
        "video"
    ],
    "wof:name":"S A Conway",
    "wof:placetype":"venue"
},
  "geometry": {"coordinates":[-3.544303,50.721043],"type":"Point"}
}