{
  "type": "Feature",
  "properties": {
    "iso:country":"GB",
    "sg:address":"16 Longthorpe Clo",
    "sg:city":"Swindon",
    "sg:classifiers":[
        {
            "category":"Professional",
            "type":"Services"
        }
    ],
    "sg:phone":"+44 1793 511421",
    "sg:postcode":"SN5 8AD",
    "sg:province":"Wiltshire",
    "sg:tags":[
        "caterer"
    ],
    "wof:name":"Stephen Port",
    "wof:placetype":"venue"
},
  "geometry": {"coordinates":[-1.818595,51.554157],"type":"Point"}
}