{
  "type": "Feature",
  "properties": {
    "addr:full":"8 Clampitt Road Newton Abbot Devon TQ12 5RJ",
    "addr:housenumber":"8",
    "addr:postcode":"tq12 5rj",
    "addr:street":"Clampitt Road",
    "iso:country":"GB",
    "sg:address":"8 Clampitt Road",
    "sg:city":"Newton Abbot",
    "sg:classifiers":[
        {
            "category":"Building & Trades",
            "subcategory":"Construction",
            "type":"Services"
        }
    ],
    "sg:postcode":"TQ12 5RJ",
    "sg:province":"Devon",
    "sg:tags":[
        "builder"
    ],
    "wof:name":"W H Osborn",
    "wof:placetype":"venue"
},
  "geometry": {"coordinates":[-3.64193,50.486279],"type":"Point"}
}