{
  "type": "Feature",
  "properties": {
    "addr:full":"2 Cotswold Ct, The Green Broadway Gloucestershire WR12 7AA",
    "addr:housenumber":"2",
    "addr:postcode":"wr12 7aa",
    "addr:street":"Cotswold Ct The Green Broadway",
    "iso:country":"GB",
    "sg:address":"2 Cotswold Ct, The Green",
    "sg:city":"Broadway",
    "sg:classifiers":[
        {
            "category":"Shopping",
            "subcategory":"Baby Store",
            "type":"Retail Goods"
        }
    ],
    "sg:postcode":"WR12 7AA",
    "sg:province":"Gloucestershire",
    "sg:tags":[
        "babywear",
        "childrens"
    ],
    "wof:name":"Beale,Barbara A,",
    "wof:placetype":"venue"
},
  "geometry": {"coordinates":[-1.855794,52.040409],"type":"Point"}
}