{
  "type": "Feature",
  "properties": {
    "addr:full":"123 Wordsworth Drive Taunton Somerset TA1 2HJ",
    "addr:housenumber":"123",
    "addr:postcode":"ta1 2hj",
    "addr:street":"Wordsworth Drive",
    "iso:country":"GB",
    "sg:address":"123 Wordsworth Drive",
    "sg:city":"Taunton",
    "sg:classifiers":[
        {
            "category":"Bars & Pubs",
            "type":"Food & Drink"
        }
    ],
    "sg:phone":"+44 1823 259470",
    "sg:postcode":"TA1 2HJ",
    "sg:province":"Somerset",
    "sg:tags":[
        "pubs",
        "inn"
    ],
    "wof:name":"The Dolphin Inn",
    "wof:placetype":"venue"
},
  "geometry": {"coordinates":[-3.086955,51.011436],"type":"Point"}
}