{
  "type": "Feature",
  "properties": {
    "addr:full":"2 Hyde Square, Beeding Steyning West Sussex BN44 3JE",
    "addr:housenumber":"2",
    "addr:postcode":"bn44 3je",
    "addr:street":"Hyde Square Beeding",
    "iso:country":"GB",
    "sg:address":"2 Hyde Square, Beeding",
    "sg:city":"Steyning",
    "sg:classifiers":[
        {
            "category":"Personal",
            "subcategory":"Beauty Salon",
            "type":"Services"
        }
    ],
    "sg:phone":"+44 1903 812621",
    "sg:postcode":"BN44 3JE",
    "sg:province":"West Sussex",
    "sg:tags":[
        "unisex",
        "hairdresser"
    ],
    "wof:name":"Eclipse At His & Hers",
    "wof:placetype":"venue"
},
  "geometry": {"coordinates":[-0.300673,50.881435],"type":"Point"}
}