{
  "type": "Feature",
  "properties": {
    "addr:full":"Jingling Gate Poultry Farm, Twizell Lane, West Pelton Stanley Durham DH9 6SL",
    "addr:postcode":"dh9 6sl",
    "addr:street":"Jingling Gate Poultry;Twizell Lane West Pelton Stanley",
    "iso:country":"GB",
    "sg:address":"Jingling Gate Poultry Farm, Twizell Lane, West Pelton",
    "sg:city":"Stanley",
    "sg:classifiers":[
        {
            "category":"Farming",
            "subcategory":"Poultry Farm",
            "type":"Manufacturing & Wholesale Goods"
        }
    ],
    "sg:phone":"+44 191 370 0194",
    "sg:postcode":"DH9 6SL",
    "sg:province":"Durham",
    "sg:tags":[
        "game"
    ],
    "wof:name":"Morison Hamish",
    "wof:placetype":"venue"
},
  "geometry": {"coordinates":[-1.637754,54.871944],"type":"Point"}
}