{
  "type": "Feature",
  "properties": {
    "addr:full":"34 Cobden Street Leicester Leicestershire LE1 2LB",
    "addr:housenumber":"34",
    "addr:postcode":"le1 2lb",
    "addr:street":"Cobden Street",
    "iso:country":"GB",
    "sg:address":"34 Cobden Street",
    "sg:city":"Leicester",
    "sg:classifiers":[
        {
            "category":"Wholesale",
            "subcategory":"Hardware",
            "type":"Manufacturing & Wholesale Goods"
        },
        {
            "category":"Home & Garden",
            "subcategory":"Hardware",
            "type":"Retail Goods"
        }
    ],
    "sg:phone":"+44 116 253 0777",
    "sg:postcode":"LE1 2LB",
    "sg:province":"Leicestershire",
    "sg:tags":[
        "merchant",
        "plumber",
        "ironmonger"
    ],
    "wof:name":"DECCO LTD",
    "wof:placetype":"venue"
},
  "geometry": {"coordinates":[-1.116299,52.642559],"type":"Point"}
}