{
  "type": "Feature",
  "properties": {
    "addr:full":"Wellington Rd Boston Lincolnshire PE21 0NX",
    "addr:postcode":"pe21 0nx",
    "addr:street":"Wellington Rd",
    "iso:country":"GB",
    "sg:address":"Wellington Rd",
    "sg:city":"Boston",
    "sg:classifiers":[
        {
            "category":"Bars & Pubs",
            "type":"Food & Drink"
        }
    ],
    "sg:phone":"+44 1205 369220",
    "sg:postcode":"PE21 0NX",
    "sg:province":"Lincolnshire",
    "sg:tags":[
        "pubs",
        "inn"
    ],
    "wof:name":"Queen of Spades",
    "wof:placetype":"venue"
},
  "geometry": {"coordinates":[-0.008834,52.976543],"type":"Point"}
}