{
  "type": "Feature",
  "properties": {
    "addr:full":"163/165 Central Mkt Cardiff Cardiff CF10 1AU",
    "addr:housenumber":"163 / 165",
    "addr:postcode":"cf10 1au",
    "addr:street":"Central",
    "iso:country":"GB",
    "sg:address":"163/165 Central Mkt",
    "sg:city":"Cardiff",
    "sg:classifiers":[
        {
            "category":"Food & Beverages",
            "subcategory":"Supermarket",
            "type":"Retail Goods"
        }
    ],
    "sg:phone":"+44 29 2034 5601",
    "sg:postcode":"CF10 1AU",
    "sg:province":"Cardiff",
    "wof:name":"Dolbears Limited",
    "wof:placetype":"venue"
},
  "geometry": {"coordinates":[-3.179269,51.47765],"type":"Point"}
}