{
  "type": "Feature",
  "properties": {
    "iso:country":"GB",
    "sg:address":"70 The High Street, Horne Lane",
    "sg:city":"Bedford",
    "sg:classifiers":[
        {
            "category":"Shopping",
            "subcategory":"Clothing, Apparel, & Fashions",
            "type":"Retail Goods"
        },
        {
            "category":"Shopping",
            "subcategory":"Jewelry",
            "type":"Retail Goods"
        }
    ],
    "sg:phone":"+44 1234 328100",
    "sg:postcode":"MK40 1UH",
    "sg:province":"Bedfordshire",
    "sg:tags":[
        "accessory",
        "gold",
        "silversmith"
    ],
    "wof:name":"Additions",
    "wof:placetype":"venue"
},
  "geometry": {"coordinates":[-0.466927,52.137447],"type":"Point"}
}