{
  "type": "Feature",
  "properties": {
    "addr:full":"3 Exeter Close, Cheadle Hulme Cheadle Cheshire SK8 6JE",
    "addr:housenumber":"3",
    "addr:postcode":"sk8 6je",
    "addr:street":"Exeter Close",
    "iso:country":"GB",
    "sg:address":"3 Exeter Close, Cheadle Hulme",
    "sg:city":"Cheadle",
    "sg:classifiers":[
        {
            "category":"Home & Garden",
            "subcategory":"Household Appliances",
            "type":"Retail Goods"
        }
    ],
    "sg:phone":"+44 161 486 1122",
    "sg:postcode":"SK8 6JE",
    "sg:province":"Cheshire",
    "sg:tags":[
        "electrical"
    ],
    "wof:name":"Prestige Domestic Services",
    "wof:placetype":"venue"
},
  "geometry": {"coordinates":[-2.2017440796,53.3660812378],"type":"Point"}
}