{
  "type": "Feature",
  "properties": {
    "addr:full":"38 Hampton Rd Twickenham Greater London TW2 5QB",
    "addr:housenumber":"38",
    "addr:postcode":"tw2 5qb",
    "addr:street":"Hampton Rd",
    "iso:country":"GB",
    "sg:address":"38 Hampton Rd",
    "sg:city":"Twickenham",
    "sg:classifiers":[
        {
            "category":"Food & Beverages",
            "subcategory":"Supermarket",
            "type":"Retail Goods"
        }
    ],
    "sg:phone":"+44 20 8893 9601",
    "sg:postcode":"TW2 5QB",
    "sg:province":"Greater London",
    "sg:tags":[
        "frozen"
    ],
    "wof:name":"Traditional Preserves Corporation",
    "wof:placetype":"venue"
},
  "geometry": {"coordinates":[-0.3444100022,51.4419288635],"type":"Point"}
}