{
  "type": "Feature",
  "properties": {
    "addr:full":"385 Main Street Wishaw North Lanarkshire ML2 7NG",
    "addr:housenumber":"385",
    "addr:postcode":"ml2 7ng",
    "addr:street":"Main Street",
    "iso:country":"GB",
    "sg:address":"385 Main Street",
    "sg:city":"Wishaw",
    "sg:classifiers":[
        {
            "category":"Fast Food",
            "type":"Food & Drink"
        }
    ],
    "sg:phone":"+44 1698 355428",
    "sg:postcode":"ML2 7NG",
    "sg:province":"North Lanarkshire",
    "sg:tags":[
        "away",
        "take"
    ],
    "wof:name":"Asia Tandoori",
    "wof:placetype":"venue"
},
  "geometry": {"coordinates":[-3.9269769192,55.7767448425],"type":"Point"}
}