{
  "type": "Feature",
  "properties": {
    "addr:full":"29c Belair Rd Plymouth Devon PL2 3QH",
    "addr:housenumber":"29c",
    "addr:postcode":"pl2 3qh",
    "addr:street":"Belair Rd",
    "iso:country":"GB",
    "sg:address":"29c Belair Rd",
    "sg:city":"Plymouth",
    "sg:classifiers":[
        {
            "category":"Building & Trades",
            "subcategory":"Construction",
            "type":"Services"
        }
    ],
    "sg:phone":"+44 1752 769135",
    "sg:postcode":"PL2 3QH",
    "sg:province":"Devon",
    "sg:tags":[
        "builder"
    ],
    "wof:name":"S & S Building Maintenance & Groundwork",
    "wof:placetype":"venue"
},
  "geometry": {"coordinates":[-4.150742,50.393555],"type":"Point"}
}