{
  "type": "Feature",
  "properties": {
    "iso:country":"GB",
    "sg:address":"The Barn, Lovedean Lane, Lovedean",
    "sg:city":"Waterlooville",
    "sg:classifiers":[
        {
            "category":"Retail",
            "subcategory":"Auto Repair",
            "type":"Services"
        }
    ],
    "sg:phone":"+44 23 9259 2010",
    "sg:postcode":"PO8 0UA",
    "sg:province":"Hampshire",
    "sg:tags":[
        "modification",
        "garage"
    ],
    "wof:name":"ABA Vans & Truck Sales",
    "wof:placetype":"venue"
},
  "geometry": {"coordinates":[-1.017961,50.927044],"type":"Point"}
}