{
  "type": "Feature",
  "properties": {
    "addr:full":"125 East Gomeldon Rd Salisbury Hampshire SP4 6LZ",
    "addr:housenumber":"125",
    "addr:postcode":"sp4 6lz",
    "addr:street":"East Gomeldon Rd",
    "iso:country":"GB",
    "sg:address":"125 East Gomeldon Rd",
    "sg:city":"Salisbury",
    "sg:classifiers":[
        {
            "category":"Farming",
            "subcategory":"Poultry Farm",
            "type":"Manufacturing & Wholesale Goods"
        }
    ],
    "sg:phone":"+44 1980 610090",
    "sg:postcode":"SP4 6LZ",
    "sg:province":"Hampshire",
    "sg:tags":[
        "game"
    ],
    "wof:name":"Rupert Cady Games Services",
    "wof:placetype":"venue"
},
  "geometry": {"coordinates":[-1.7243310213,51.1186065674],"type":"Point"}
}