{
  "type": "Feature",
  "properties": {
    "addr:full":"Unit 3 Bradley Road Telford Shropshire TF2 7RG",
    "addr:housenumber":"unit 3",
    "addr:postcode":"tf2 7rg",
    "addr:street":"Bradley Road",
    "iso:country":"GB",
    "sg:address":"Unit 3 Bradley Road",
    "sg:city":"Telford",
    "sg:classifiers":[
        {
            "category":"Manufacturing",
            "subcategory":"Petroleum Products",
            "type":"Manufacturing & Wholesale Goods"
        }
    ],
    "sg:phone":"+44 1952 608486",
    "sg:postcode":"TF2 7RG",
    "sg:province":"Shropshire",
    "sg:tags":[
        "lubricant"
    ],
    "wof:name":"Dee-Anel Ltd.",
    "wof:placetype":"venue"
},
  "geometry": {"coordinates":[-2.4294040203,52.7124938965],"type":"Point"}
}