{
  "type": "Feature",
  "properties": {
    "iso:country":"GB",
    "sg:address":"187 High Street, Yelling",
    "sg:city":"Huntingdon",
    "sg:classifiers":[
        {
            "category":"Retail",
            "subcategory":"Auto Repair",
            "type":"Services"
        }
    ],
    "sg:phone":"+44 1480 880129",
    "sg:postcode":"PE19 6SB",
    "sg:province":"Bedfordshire",
    "sg:tags":[
        "garage",
        "mechanic"
    ],
    "wof:name":"Electronic Services",
    "wof:placetype":"venue"
},
  "geometry": {"coordinates":[-0.160218,52.247673],"type":"Point"}
}