{
  "type": "Feature",
  "properties": {
    "addr:full":"89 Chandos Avenue London Greater London N20 9EG",
    "addr:housenumber":"89",
    "addr:postcode":"n20 9eg",
    "addr:street":"Chandos Avenue",
    "iso:country":"GB",
    "sg:address":"89 Chandos Avenue",
    "sg:city":"London",
    "sg:classifiers":[
        {
            "category":"Professional",
            "subcategory":"Engineering",
            "type":"Services"
        }
    ],
    "sg:phone":"+44 20 8446 2776",
    "sg:postcode":"N20 9EG",
    "sg:province":"Greater London",
    "sg:tags":[
        "consulting",
        "engineer"
    ],
    "wof:name":"Information Search & Analysis Consultants",
    "wof:placetype":"venue"
},
  "geometry": {"coordinates":[-0.168393,51.636707],"type":"Point"}
}