{
  "type": "Feature",
  "properties": {
    "addr:full":"Five Acre Farm, Winkfield Plain Windsor Berkshire SL4 4QU",
    "addr:postcode":"sl4 4qu",
    "addr:street":"Five",
    "iso:country":"GB",
    "sg:address":"Five Acre Farm, Winkfield Plain",
    "sg:city":"Windsor",
    "sg:classifiers":[
        {
            "category":"Autos & Motor Vehicles",
            "subcategory":"Automobile Sales",
            "type":"Retail Goods"
        }
    ],
    "sg:phone":"+44 1406 330022",
    "sg:postcode":"SL4 4QU",
    "sg:province":"Berkshire",
    "sg:tags":[
        "car",
        "specialist",
        "sales",
        "classic"
    ],
    "wof:name":"J C Pitney",
    "wof:placetype":"venue"
},
  "geometry": {"coordinates":[-0.697399,51.44202],"type":"Point"}
}