{
  "type": "Feature",
  "properties": {
    "iso:country":"GB",
    "sg:address":"68 Hutton Close, Crowther",
    "sg:city":"Washington",
    "sg:classifiers":[
        {
            "category":"Home & Garden",
            "subcategory":"Hardware",
            "type":"Retail Goods"
        }
    ],
    "sg:phone":"+44 191 417 6688",
    "sg:postcode":"NE38 0AH",
    "sg:province":"Durham",
    "sg:tags":[
        "gear",
        "cutter"
    ],
    "wof:name":"Browning Automatic Transmissions",
    "wof:placetype":"venue"
},
  "geometry": {"coordinates":[-1.5550709963,54.9016113281],"type":"Point"}
}