{
  "type": "Feature",
  "properties": {
    "iso:country":"GB",
    "sg:address":"High Street, Hardington Mandeville",
    "sg:city":"Yeovil",
    "sg:classifiers":[
        {
            "category":"Bars & Pubs",
            "type":"Food & Drink"
        },
        {
            "category":"Community Center",
            "subcategory":"Social",
            "type":"Public Place"
        }
    ],
    "sg:phone":"+44 1935 862418",
    "sg:postcode":"BA22 9PQ",
    "sg:province":"Dorset",
    "sg:tags":[
        "pubs",
        "house",
        "inn",
        "activity"
    ],
    "wof:name":"The Mandeville Arms",
    "wof:placetype":"venue"
},
  "geometry": {"coordinates":[-2.69513,50.90366],"type":"Point"}
}