{
  "type": "Feature",
  "properties": {
    "iso:country":"GB",
    "sg:address":"27 The Avenue, Cheam",
    "sg:city":"Sutton",
    "sg:classifiers":[
        {
            "category":"Building & Trades",
            "subcategory":"Construction",
            "type":"Services"
        }
    ],
    "sg:postcode":"SM2 7QA",
    "sg:province":"Surrey",
    "sg:tags":[
        "builder"
    ],
    "wof:name":"Jengar Home Developments Ltd.",
    "wof:placetype":"venue"
},
  "geometry": {"coordinates":[-0.211212,51.349022],"type":"Point"}
}