{
  "type": "Feature",
  "properties": {
    "iso:country":"GB",
    "sg:address":"369 Aigburth Road",
    "sg:city":"Liverpool",
    "sg:classifiers":[
        {
            "category":"Retail",
            "subcategory":"Laundry & Dry Cleaning",
            "type":"Services"
        }
    ],
    "sg:phone":"+44 151 280 7793",
    "sg:postcode":"L17 0BP",
    "sg:province":"Merseyside",
    "sg:tags":[
        "launderette"
    ],
    "wof:name":"Associated Liver Launderettes Ltd",
    "wof:placetype":"venue"
},
  "geometry": {"coordinates":[-2.932411,53.370991],"type":"Point"}
}