{
  "type": "Feature",
  "properties": {
    "iso:country":"GB",
    "sg:address":"13 Lancaster Buildings",
    "sg:city":"Newcastle",
    "sg:classifiers":[
        {
            "category":"Shopping",
            "subcategory":"News",
            "type":"Retail Goods"
        }
    ],
    "sg:postcode":"ST5 1PG",
    "sg:province":"Staffordshire",
    "sg:tags":[
        "newsagent"
    ],
    "wof:name":"Good News",
    "wof:placetype":"venue"
},
  "geometry": {"coordinates":[-2.215323925,53.0074729919],"type":"Point"}
}