{
  "type": "Feature",
  "properties": {
    "iso:country":"GB",
    "sg:address":"14 Eastfield, Amotherby",
    "sg:city":"Malton",
    "sg:classifiers":[
        {
            "category":"Building & Trades",
            "subcategory":"Construction",
            "type":"Services"
        }
    ],
    "sg:phone":"+44 1653 693665",
    "sg:postcode":"YO17 6TJ",
    "sg:province":"North Yorkshire",
    "sg:tags":[
        "decorator",
        "painter"
    ],
    "wof:name":"Arthur L Wright",
    "wof:placetype":"venue"
},
  "geometry": {"coordinates":[-0.7959820032,54.1767311096],"type":"Point"}
}