{
  "type": "Feature",
  "properties": {
    "iso:country":"GB",
    "sg:address":"338 Bath Road, Burnham",
    "sg:city":"Slough",
    "sg:classifiers":[
        {
            "category":"Autos & Motor Vehicles",
            "subcategory":"Automobile Sales",
            "type":"Retail Goods"
        }
    ],
    "sg:phone":"+44 1753 773763",
    "sg:postcode":"SL1 6JA",
    "sg:province":"Berkshire",
    "sg:tags":[
        "car"
    ],
    "wof:name":"Trade Sales",
    "wof:placetype":"venue"
},
  "geometry": {"coordinates":[-0.6442909837,51.5198974609],"type":"Point"}
}