{
  "type": "Feature",
  "properties": {
    "addr:full":"74-75 Battersea Bridge Road London Greater London SW11 3AG",
    "addr:housenumber":"74-75",
    "addr:postcode":"sw11 3ag",
    "addr:street":"Battersea Bridge Road",
    "iso:country":"GB",
    "sg:address":"74-75 Battersea Bridge Road",
    "sg:city":"London",
    "sg:classifiers":[
        {
            "category":"Restaurant",
            "type":"Food & Drink"
        },
        {
            "category":"Wholesale",
            "subcategory":"Apparel",
            "type":"Manufacturing & Wholesale Goods"
        },
        {
            "category":"Retail",
            "subcategory":"Storage",
            "type":"Services"
        }
    ],
    "sg:postcode":"SW11 3AG",
    "sg:province":"Greater London",
    "sg:tags":[
        "w'sale",
        "household",
        "removal",
        "french",
        "ladieswear"
    ],
    "wof:name":"A Cote Cote",
    "wof:placetype":"venue"
},
  "geometry": {"coordinates":[-0.1704269946,51.4787750244],"type":"Point"}
}