{
  "type": "Feature",
  "properties": {
    "addr:full":"Hall Farm Bury St Edmunds Cambridgeshire IP28 6HX",
    "addr:postcode":"ip28 6hx",
    "addr:street":"Hall;Bury St Edmunds",
    "iso:country":"GB",
    "sg:address":"Hall Farm",
    "sg:city":"Bury St Edmunds",
    "sg:classifiers":[
        {
            "category":"Professional",
            "subcategory":"Computer Services",
            "type":"Services"
        }
    ],
    "sg:postcode":"IP28 6HX",
    "sg:province":"Cambridgeshire",
    "sg:tags":[
        "system",
        "software"
    ],
    "wof:name":"Programs for Profit",
    "wof:placetype":"venue"
},
  "geometry": {"coordinates":[0.64079,52.30407],"type":"Point"}
}