{
  "type": "Feature",
  "properties": {
    "iso:country":"GB",
    "sg:address":"39 Union Street",
    "sg:city":"Bridgwater",
    "sg:classifiers":[
        {
            "category":"Retail",
            "subcategory":"Driving School",
            "type":"Services"
        }
    ],
    "sg:phone":"+44 1278 455810",
    "sg:postcode":"TA6 4BY",
    "sg:province":"Somerset",
    "wof:name":"Bradleys Driving School",
    "wof:placetype":"venue"
},
  "geometry": {"coordinates":[-2.9935441017,51.1347122192],"type":"Point"}
}