{
  "type": "Feature",
  "properties": {
    "addr:full":"9 Market Hill Royston Bedfordshire SG8 9JL",
    "addr:housenumber":"9",
    "addr:postcode":"sg8 9jl",
    "addr:street":"Market Hill",
    "iso:country":"GB",
    "sg:address":"9 Market Hill",
    "sg:city":"Royston",
    "sg:classifiers":[
        {
            "category":"Shopping",
            "subcategory":"Clothing, Apparel, & Fashions",
            "type":"Retail Goods"
        }
    ],
    "sg:phone":"+44 1763 246334",
    "sg:postcode":"SG8 9JL",
    "sg:province":"Bedfordshire",
    "sg:tags":[
        "menswear"
    ],
    "wof:name":"Dysons",
    "wof:placetype":"venue"
},
  "geometry": {"coordinates":[-0.022581,52.046753],"type":"Point"}
}