{
  "type": "Feature",
  "properties": {
    "addr:full":"3 Mill Close, Houghton Grn Warrington Cheshire WA2 0ST",
    "addr:housenumber":"3",
    "addr:postcode":"wa2 0st",
    "addr:street":"Mill Close;Grn",
    "iso:country":"GB",
    "sg:address":"3 Mill Close, Houghton Grn",
    "sg:city":"Warrington",
    "sg:classifiers":[
        {
            "category":"Retail",
            "subcategory":"Driving School",
            "type":"Services"
        }
    ],
    "sg:phone":"+44 1925 852226",
    "sg:postcode":"WA2 0ST",
    "sg:province":"Cheshire",
    "wof:name":"Oakmere School of Motoring",
    "wof:placetype":"venue"
},
  "geometry": {"coordinates":[-2.566356,53.419548],"type":"Point"}
}