{
  "type": "Feature",
  "properties": {
    "addr:full":"380 Kensington High Street London Greater London W14 8NL",
    "addr:housenumber":"380",
    "addr:postcode":"w14 8nl",
    "addr:street":"Kensington High Street",
    "iso:country":"GB",
    "sg:address":"380 Kensington High Street",
    "sg:city":"London",
    "sg:classifiers":[
        {
            "category":"Travel",
            "subcategory":"Hotels & Motels",
            "type":"Entertainment"
        }
    ],
    "sg:phone":"+44 20 7603 3333",
    "sg:postcode":"W14 8NL",
    "sg:province":"Greater London",
    "wof:name":"Hilton National Olympia London",
    "wof:placetype":"venue"
},
  "geometry": {"coordinates":[-0.2067990005,51.4963912964],"type":"Point"}
}