{
  "type": "Feature",
  "properties": {
    "iso:country":"GB",
    "sg:address":"20 Saffrons Road",
    "sg:city":"Eastbourne",
    "sg:classifiers":[
        {
            "category":"Social Services",
            "subcategory":"Retirement Home",
            "type":"Services"
        }
    ],
    "sg:phone":"+44 1323 720430",
    "sg:postcode":"BN21 1DU",
    "sg:province":"East Sussex",
    "sg:tags":[
        "rest"
    ],
    "wof:name":"Saffrons Rest Home",
    "wof:placetype":"venue"
},
  "geometry": {"coordinates":[0.275568,50.768398],"type":"Point"}
}