{
  "type": "Feature",
  "properties": {
    "iso:country":"GB",
    "sg:address":"Unit G Enterprise Centre, Paycocke Road",
    "sg:city":"Basildon",
    "sg:classifiers":[
        {
            "category":"Professional",
            "subcategory":"Engineering",
            "type":"Services"
        }
    ],
    "sg:phone":"+44 1268 523187",
    "sg:postcode":"SS14 3DR",
    "sg:province":"Essex",
    "sg:tags":[
        "engineer"
    ],
    "wof:name":"Essex Engineers Supplies Ltd.",
    "wof:placetype":"venue"
},
  "geometry": {"coordinates":[0.48562,51.589909],"type":"Point"}
}