{
  "type": "Feature",
  "properties": {
    "iso:country":"GB",
    "sg:address":"18a Hart Street",
    "sg:city":"Southport",
    "sg:classifiers":[
        {
            "category":"Manufacturing",
            "subcategory":"Building Materials",
            "type":"Manufacturing & Wholesale Goods"
        }
    ],
    "sg:phone":"+44 1704 501486",
    "sg:postcode":"PR8 6BT",
    "sg:province":"Lancashire",
    "sg:tags":[
        "concrete",
        "product"
    ],
    "wof:name":"Dale Stone",
    "wof:placetype":"venue"
},
  "geometry": {"coordinates":[-2.9860110283,53.6431159973],"type":"Point"}
}