{
  "type": "Feature",
  "properties": {
    "iso:country":"GB",
    "sg:address":"Unit 13 Thatcham Business Village",
    "sg:city":"Thatcham",
    "sg:classifiers":[
        {
            "category":"Autos & Motor Vehicles",
            "subcategory":"Fuel & Gas Station",
            "type":"Retail Goods"
        }
    ],
    "sg:phone":"+44 1635 876644",
    "sg:postcode":"RG19 4DN",
    "sg:province":"Berkshire",
    "sg:tags":[
        "petrol",
        "pump"
    ],
    "wof:name":"Wayne Europe-continental",
    "wof:placetype":"venue"
},
  "geometry": {"coordinates":[-1.22755,51.398602],"type":"Point"}
}