{
  "type": "Feature",
  "properties": {
    "addr:full":"81 Furness Road London Greater London NW10 5UJ",
    "addr:housenumber":"81",
    "addr:postcode":"nw10 5uj",
    "addr:street":"Furness Road",
    "iso:country":"GB",
    "sg:address":"81 Furness Road",
    "sg:city":"London",
    "sg:classifiers":[
        {
            "category":"Shopping",
            "subcategory":"Pharmacy",
            "type":"Retail Goods"
        }
    ],
    "sg:postcode":"NW10 5UJ",
    "sg:province":"Greater London",
    "sg:tags":[
        "medicine",
        "therapy"
    ],
    "wof:name":"S Ibbotson",
    "wof:placetype":"venue"
},
  "geometry": {"coordinates":[-0.2359450012,51.5357017517],"type":"Point"}
}