{
  "type": "Feature",
  "properties": {
    "iso:country":"GB",
    "sg:address":"Squires Gate Indust Est, Squires Gate La",
    "sg:city":"Blackpool",
    "sg:classifiers":[
        {
            "category":"Food & Beverages",
            "subcategory":"Meat & Fish",
            "type":"Retail Goods"
        }
    ],
    "sg:phone":"+44 1253 401153",
    "sg:postcode":"FY4 3RN",
    "sg:province":"Lancashire",
    "sg:tags":[
        "butcher"
    ],
    "wof:name":"Booker Butchery",
    "wof:placetype":"venue"
},
  "geometry": {"coordinates":[-3.022204,53.782784],"type":"Point"}
}