{
  "type": "Feature",
  "properties": {
    "iso:country":"GB",
    "sg:address":"Moor Lane Trading Estate, Perrywell Road, Witton",
    "sg:city":"Birmingham",
    "sg:classifiers":[
        {
            "category":"Freight",
            "type":"Transportation"
        }
    ],
    "sg:phone":"+44 121 356 1441",
    "sg:postcode":"B6 7AT",
    "sg:province":"West Midlands",
    "sg:tags":[
        "forwarders"
    ],
    "wof:name":"Chambers & Cook Freight Ltd.",
    "wof:placetype":"venue"
},
  "geometry": {"coordinates":[-1.884173,52.530067],"type":"Point"}
}