{
  "type": "Feature",
  "properties": {
    "iso:country":"GB",
    "sg:address":"16 St. James's Rd",
    "sg:city":"Hampton",
    "sg:classifiers":[
        {
            "category":"Retail",
            "subcategory":"Event Space",
            "type":"Services"
        }
    ],
    "sg:phone":"+44 20 8941 6143",
    "sg:postcode":"TW12 1DQ",
    "sg:province":"Greater London",
    "sg:tags":[
        "exhibition",
        "organiser"
    ],
    "wof:name":"Riverside Graphics",
    "wof:placetype":"venue"
},
  "geometry": {"coordinates":[-0.383883,51.422726],"type":"Point"}
}