{
  "type": "Feature",
  "properties": {
    "addr:full":"The Embassy Room, Meridian Pl Ilfracombe Devon EX34 9HH",
    "addr:postcode":"ex34 9hh",
    "addr:street":"Meridian Pl",
    "iso:country":"GB",
    "sg:address":"The Embassy Room, Meridian Pl",
    "sg:city":"Ilfracombe",
    "sg:classifiers":[
        {
            "category":"Shopping",
            "subcategory":"Clothing, Apparel, & Fashions",
            "type":"Retail Goods"
        }
    ],
    "sg:postcode":"EX34 9HH",
    "sg:province":"Devon",
    "sg:tags":[
        "clothing",
        "fabric"
    ],
    "wof:name":"Palmers Beach Wear",
    "wof:placetype":"venue"
},
  "geometry": {"coordinates":[-4.1235542297,51.2081604004],"type":"Point"}
}