{
  "type": "Feature",
  "properties": {
    "addr:full":"1 Station Yard Grange Over Sands Cumbria LA11 6DW",
    "addr:housenumber":"1",
    "addr:postcode":"la11 6dw",
    "addr:street":"Station Yard;Over Sands",
    "iso:country":"GB",
    "sg:address":"1 Station Yard",
    "sg:city":"Grange Over Sands",
    "sg:classifiers":[
        {
            "category":"Freight",
            "type":"Transportation"
        }
    ],
    "sg:phone":"+44 15395 34929",
    "sg:postcode":"LA11 6DW",
    "sg:province":"Cumbria",
    "sg:tags":[
        "haulage",
        "road"
    ],
    "wof:name":"Brennands",
    "wof:placetype":"venue"
},
  "geometry": {"coordinates":[-2.9016170502,54.1962585449],"type":"Point"}
}