{
  "type": "Feature",
  "properties": {
    "iso:country":"GB",
    "sg:address":"274 Harrow Road",
    "sg:city":"London",
    "sg:classifiers":[
        {
            "category":"Food & Beverages",
            "subcategory":"Groceries & Convenience Stores",
            "type":"Retail Goods"
        }
    ],
    "sg:phone":"+44 20 7266 0919",
    "sg:postcode":"W2 5ES",
    "sg:province":"Greater London",
    "wof:name":"Olayinka Adeleye",
    "wof:placetype":"venue"
},
  "geometry": {"coordinates":[-0.191591,51.520893],"type":"Point"}
}