{
  "type": "Feature",
  "properties": {
    "iso:country":"GB",
    "sg:address":"2 Drake Rd",
    "sg:city":"Walsall",
    "sg:classifiers":[
        {
            "category":"Utilities",
            "subcategory":"Refuse",
            "type":"Services"
        }
    ],
    "sg:phone":"+44 1922 403607",
    "sg:postcode":"WS3 3LS",
    "sg:province":"Staffordshire",
    "sg:tags":[
        "disposal",
        "waste"
    ],
    "wof:name":"Drake Waste Ltd",
    "wof:placetype":"venue"
},
  "geometry": {"coordinates":[-2.003512,52.618526],"type":"Point"}
}