{
  "type": "Feature",
  "properties": {
    "addr:full":"The Avenue Petersfield Hampshire GU31 4JQ",
    "addr:postcode":"gu31 4jq",
    "addr:street":"Avenue",
    "iso:country":"GB",
    "sg:address":"The Avenue",
    "sg:city":"Petersfield",
    "sg:classifiers":[
        {
            "category":"Manufacturing",
            "subcategory":"Electronics",
            "type":"Manufacturing & Wholesale Goods"
        }
    ],
    "sg:phone":"+44 1730 261912",
    "sg:postcode":"GU31 4JQ",
    "sg:province":"Hampshire",
    "sg:tags":[
        "printed",
        "circuit"
    ],
    "wof:name":"Viking Test Ltd.",
    "wof:placetype":"venue"
},
  "geometry": {"coordinates":[-0.9317139983,51.0015487671],"type":"Point"}
}