{
  "type": "Feature",
  "properties": {
    "addr:full":"Newport Road Market Drayton Shropshire TF9 2AA",
    "addr:postcode":"tf9 2aa",
    "addr:street":"Newport Road",
    "iso:country":"GB",
    "sg:address":"Newport Road",
    "sg:city":"Market Drayton",
    "sg:classifiers":[
        {
            "category":"Manufacturing",
            "subcategory":"Glass & Minerals",
            "type":"Manufacturing & Wholesale Goods"
        }
    ],
    "sg:phone":"+44 1630 658243",
    "sg:postcode":"TF9 2AA",
    "sg:province":"Shropshire",
    "sg:tags":[
        "fibre",
        "moulding"
    ],
    "wof:name":"Composite Developments",
    "wof:placetype":"venue"
},
  "geometry": {"coordinates":[-2.4749970436,52.8930206299],"type":"Point"}
}