{
  "type": "Feature",
  "properties": {
    "addr:full":"Ashtree House, Nawton York North Yorkshire YO62 7TR",
    "addr:postcode":"yo62 7tr",
    "iso:country":"GB",
    "sg:address":"Ashtree House, Nawton",
    "sg:city":"York",
    "sg:classifiers":[
        {
            "category":"Building & Trades",
            "subcategory":"Construction",
            "type":"Services"
        }
    ],
    "sg:postcode":"YO62 7TR",
    "sg:province":"North Yorkshire",
    "sg:tags":[
        "joiner",
        "carpenter"
    ],
    "wof:name":"Joseph S Featherstone",
    "wof:placetype":"venue"
},
  "geometry": {"coordinates":[-0.99584,54.254292],"type":"Point"}
}