{
  "type": "Feature",
  "properties": {
    "addr:full":"3 Bull Yard Coventry West Midlands CV1 1LH",
    "addr:housenumber":"3",
    "addr:postcode":"cv1 1lh",
    "addr:street":"Bull Yard",
    "iso:country":"GB",
    "sg:address":"3 Bull Yard",
    "sg:city":"Coventry",
    "sg:classifiers":[
        {
            "category":"Food & Beverages",
            "subcategory":"Candy",
            "type":"Retail Goods"
        }
    ],
    "sg:phone":"+44 24 7655 2141",
    "sg:postcode":"CV1 1LH",
    "sg:province":"West Midlands",
    "sg:tags":[
        "confectioner"
    ],
    "wof:name":"Thorntons plc",
    "wof:placetype":"venue"
},
  "geometry": {"coordinates":[-1.5128209591,52.4058685303],"type":"Point"}
}