{
  "type": "Feature",
  "properties": {
    "iso:country":"GB",
    "sg:address":"Dutlas, Lloyney",
    "sg:city":"Knighton",
    "sg:classifiers":[
        {
            "category":"Farming",
            "subcategory":"Livestock Farm",
            "type":"Manufacturing & Wholesale Goods"
        },
        {
            "category":"Farming",
            "subcategory":"Farm",
            "type":"Manufacturing & Wholesale Goods"
        }
    ],
    "sg:phone":"+44 1547 510241",
    "sg:postcode":"LD7 1RH",
    "sg:province":"Shropshire",
    "sg:tags":[
        "mixed",
        "crop",
        "others"
    ],
    "wof:name":"T A Swancott",
    "wof:placetype":"venue"
},
  "geometry": {"coordinates":[-3.0477099419,52.3430671692],"type":"Point"}
}