{
  "type": "Feature",
  "properties": {
    "iso:country":"GB",
    "sg:address":"6 Coventry Street",
    "sg:city":"Nuneaton",
    "sg:classifiers":[
        {
            "category":"Food & Beverages",
            "subcategory":"Specialty",
            "type":"Retail Goods"
        }
    ],
    "sg:phone":"+44 24 7634 6200",
    "sg:postcode":"CV11 5SZ",
    "sg:province":"Leicestershire",
    "sg:tags":[
        "retailer",
        "product",
        "health"
    ],
    "wof:name":"The Health Shop Nuneaton Ltd.",
    "wof:placetype":"venue"
},
  "geometry": {"coordinates":[-1.467414,52.522572],"type":"Point"}
}