{
  "type": "Feature",
  "properties": {
    "addr:full":"Rotherham Road Barnsley South Yorkshire S71 1UT",
    "addr:postcode":"s71 1ut",
    "addr:street":"Rotherham Road;Yorkshire",
    "iso:country":"GB",
    "sg:address":"Rotherham Road",
    "sg:city":"Barnsley",
    "sg:classifiers":[
        {
            "category":"Bars & Pubs",
            "type":"Food & Drink"
        }
    ],
    "sg:phone":"+44 1226 205314",
    "sg:postcode":"S71 1UT",
    "sg:province":"South Yorkshire",
    "sg:tags":[
        "pubs",
        "inn"
    ],
    "wof:name":"The Athersley",
    "wof:placetype":"venue"
},
  "geometry": {"coordinates":[-1.471372962,53.5748672485],"type":"Point"}
}