{
  "type": "Feature",
  "properties": {
    "addr:full":"5a Pavilion Parade, Wood Lane London Greater London W12 0HQ",
    "addr:housenumber":"5a",
    "addr:postcode":"w12 0hq",
    "addr:street":"Pavilion Parade Wood Lane",
    "iso:country":"GB",
    "sg:address":"5a Pavilion Parade, Wood Lane",
    "sg:city":"London",
    "sg:classifiers":[
        {
            "category":"Fast Food",
            "type":"Food & Drink"
        }
    ],
    "sg:phone":"+44 20 8740 8316",
    "sg:postcode":"W12 0HQ",
    "sg:province":"Greater London",
    "sg:tags":[
        "away",
        "take"
    ],
    "wof:name":"Curry Express",
    "wof:placetype":"venue"
},
  "geometry": {"coordinates":[-0.2276660055,51.5185165405],"type":"Point"}
}