{
  "type": "Feature",
  "properties": {
    "iso:country":"GB",
    "sg:address":"65 Headstone Gardens",
    "sg:city":"Harrow",
    "sg:classifiers":[
        {
            "category":"Building & Trades",
            "subcategory":"Landscaping Services",
            "type":"Services"
        }
    ],
    "sg:postcode":"HA2 6PU",
    "sg:province":"Greater London",
    "sg:tags":[
        "gardening"
    ],
    "wof:name":"Chelsea Gardens",
    "wof:placetype":"venue"
},
  "geometry": {"coordinates":[-0.3474999964,51.5922813416],"type":"Point"}
}