{
  "type": "Feature",
  "properties": {
    "addr:full":"Bawtry Road, Hatfield Woodhouse Doncaster South Yorkshire DN7 6PQ",
    "addr:postcode":"dn7 6pq",
    "addr:street":"Bawtry Road",
    "iso:country":"GB",
    "sg:address":"Bawtry Road, Hatfield Woodhouse",
    "sg:city":"Doncaster",
    "sg:classifiers":[
        {
            "category":"Shopping",
            "subcategory":"Hobbies, Toys, & Games",
            "type":"Retail Goods"
        }
    ],
    "sg:phone":"+44 1302 840526",
    "sg:postcode":"DN7 6PQ",
    "sg:province":"South Yorkshire",
    "sg:tags":[
        "gunsmith"
    ],
    "wof:name":"The Gun Shop",
    "wof:placetype":"venue"
},
  "geometry": {"coordinates":[-0.9815459847,53.5658226013],"type":"Point"}
}