{
  "type": "Feature",
  "properties": {
    "addr:full":"125 Moorefield Rd Uxbridge Buckinghamshire UB8 3SH",
    "addr:housenumber":"125",
    "addr:postcode":"ub8 3sh",
    "addr:street":"Moorefield Rd",
    "iso:country":"GB",
    "sg:address":"125 Moorefield Rd",
    "sg:city":"Uxbridge",
    "sg:classifiers":[
        {
            "category":"Shopping",
            "subcategory":"Department Store",
            "type":"Retail Goods"
        },
        {
            "category":"Food & Beverages",
            "subcategory":"Supermarket",
            "type":"Retail Goods"
        }
    ],
    "sg:postcode":"UB8 3SH",
    "sg:province":"Buckinghamshire",
    "wof:name":"Randhawa,Harbhajan Singh,",
    "wof:placetype":"venue"
},
  "geometry": {"coordinates":[-0.474536,51.544071],"type":"Point"}
}