{
  "type": "Feature",
  "properties": {
    "addr:full":"Off Smithies Lane Heckmondwike West Yorkshire WF16 0PL",
    "addr:postcode":"wf16 0pl",
    "addr:street":"Off Smithies Lane",
    "iso:country":"GB",
    "sg:address":"Off Smithies Lane",
    "sg:city":"Heckmondwike",
    "sg:classifiers":[
        {
            "category":"Landmark",
            "subcategory":"Tourist Attraction",
            "type":"Public Place"
        }
    ],
    "sg:phone":"+44 1924 235276",
    "sg:postcode":"WF16 0PL",
    "sg:province":"West Yorkshire",
    "sg:tags":[
        "interest"
    ],
    "wof:name":"Ponderosa Theraputic Centre",
    "wof:placetype":"venue"
},
  "geometry": {"coordinates":[-1.6775239706,53.7136611938],"type":"Point"}
}