{
  "type": "Feature",
  "properties": {
    "iso:country":"GB",
    "sg:address":"15 Tilgate Parade",
    "sg:city":"Crawley",
    "sg:classifiers":[
        {
            "category":"Food & Beverages",
            "subcategory":"Meat & Fish",
            "type":"Retail Goods"
        }
    ],
    "sg:phone":"+44 1293 526050",
    "sg:postcode":"RH10 5EQ",
    "sg:province":"Surrey",
    "sg:tags":[
        "butcher"
    ],
    "wof:name":"Hedley Vicars",
    "wof:placetype":"venue"
},
  "geometry": {"coordinates":[-0.180218,51.102261],"type":"Point"}
}