{
  "type": "Feature",
  "properties": {
    "iso:country":"GB",
    "sg:address":"1a Cranbrook Park",
    "sg:city":"Wood Green",
    "sg:classifiers":[
        {
            "category":"Retail",
            "subcategory":"Auto Repair",
            "type":"Services"
        }
    ],
    "sg:phone":"+44 20 8365 7889",
    "sg:postcode":"N22 5NA",
    "sg:province":"Greater London",
    "sg:tags":[
        "body",
        "car"
    ],
    "wof:name":"Spraybest Motors",
    "wof:placetype":"venue"
},
  "geometry": {"coordinates":[-0.1101490036,51.5985527039],"type":"Point"}
}