{
  "type": "Feature",
  "properties": {
    "addr:full":"Unit 9 Stanley Green Industrial Estate, Stanley Green Crescent Poole Dorset BH15 3TH",
    "addr:housenumber":"unit 9;estate",
    "addr:postcode":"bh15 3th",
    "addr:street":"Stanley Green Industrial;Stanley Green Crescent",
    "iso:country":"GB",
    "sg:address":"Unit 9 Stanley Green Industrial Estate, Stanley Green Crescent",
    "sg:city":"Poole",
    "sg:classifiers":[
        {
            "category":"Retail",
            "subcategory":"Auto Repair",
            "type":"Services"
        }
    ],
    "sg:postcode":"BH15 3TH",
    "sg:province":"Dorset",
    "sg:tags":[
        "modification",
        "garage"
    ],
    "wof:name":"Morgan Motors",
    "wof:placetype":"venue"
},
  "geometry": {"coordinates":[-1.986684,50.728836],"type":"Point"}
}