{
  "type": "Feature",
  "properties": {
    "addr:full":"Unit 2 Corinium Business Park, Speculation Road Cinderford Gloucestershire GL14 2YD",
    "addr:housenumber":"unit 2",
    "addr:postcode":"gl14 2yd",
    "addr:street":"Corinium Business Park Speculation Road",
    "iso:country":"GB",
    "sg:address":"Unit 2 Corinium Business Park, Speculation Road",
    "sg:city":"Cinderford",
    "sg:classifiers":[
        {
            "category":"Shopping",
            "subcategory":"Stationery & Office Supplies",
            "type":"Retail Goods"
        }
    ],
    "sg:phone":"+44 1594 826479",
    "sg:postcode":"GL14 2YD",
    "sg:province":"Gloucestershire",
    "sg:tags":[
        "box",
        "carton"
    ],
    "wof:name":"D Fellows",
    "wof:placetype":"venue"
},
  "geometry": {"coordinates":[-2.511693,51.833599],"type":"Point"}
}