{
  "type": "Feature",
  "properties": {
    "addr:full":"Nun House Sedbergh Cumbria LA10 5QY",
    "addr:postcode":"la10 5qy",
    "iso:country":"GB",
    "sg:address":"Nun House",
    "sg:city":"Sedbergh",
    "sg:classifiers":[
        {
            "category":"Military Area",
            "subcategory":"Air Force Base",
            "type":"Public Place"
        }
    ],
    "sg:phone":"+44 15396 25555",
    "sg:postcode":"LA10 5QY",
    "sg:province":"Cumbria",
    "sg:tags":[
        "taxi",
        "hire",
        "private"
    ],
    "wof:name":"Derek Henderson",
    "wof:placetype":"venue"
},
  "geometry": {"coordinates":[-2.527837038,54.3219451904],"type":"Point"}
}