{
  "type": "Feature",
  "properties": {
    "addr:full":"Bangor Street Caernarfon Gwynedd LL55 1AR",
    "addr:postcode":"ll55 1ar",
    "addr:street":"Bangor Street",
    "iso:country":"GB",
    "sg:address":"Bangor Street",
    "sg:city":"Caernarfon",
    "sg:classifiers":[
        {
            "category":"Food & Beverages",
            "subcategory":"Supermarket",
            "type":"Retail Goods"
        }
    ],
    "sg:phone":"+44 1286 678483",
    "sg:postcode":"LL55 1AR",
    "sg:province":"Gwynedd",
    "wof:name":"Kwik Save Stores Ltd.",
    "wof:placetype":"venue"
},
  "geometry": {"coordinates":[-4.2727189064,53.1432609558],"type":"Point"}
}