{
  "type": "Feature",
  "properties": {
    "iso:country":"GB",
    "sg:address":"Drake Cottage, Little Dartmouth",
    "sg:city":"Dartmouth",
    "sg:classifiers":[
        {
            "category":"Communications",
            "subcategory":"Film & Video Production",
            "type":"Services"
        }
    ],
    "sg:phone":"+44 1803 835720",
    "sg:postcode":"TQ6 0JP",
    "sg:province":"Devon",
    "sg:tags":[
        "illustrator",
        "artist"
    ],
    "wof:name":"Mark Denman",
    "wof:placetype":"venue"
},
  "geometry": {"coordinates":[-3.5850760937,50.3536186218],"type":"Point"}
}