{
  "type": "Feature",
  "properties": {
    "addr:full":"29 London Road, Isleworth Brentford Greater London TW8 8JB",
    "addr:housenumber":"29",
    "addr:postcode":"tw8 8jb",
    "addr:street":"London Road",
    "iso:country":"GB",
    "sg:address":"29 London Road, Isleworth",
    "sg:city":"Brentford",
    "sg:classifiers":[
        {
            "category":"Bars & Pubs",
            "type":"Food & Drink"
        }
    ],
    "sg:phone":"+44 20 8847 4586",
    "sg:postcode":"TW8 8JB",
    "sg:province":"Greater London",
    "sg:tags":[
        "pubs",
        "inn"
    ],
    "wof:name":"Six Continents Retail Ltd.",
    "wof:placetype":"venue"
},
  "geometry": {"coordinates":[-0.3138999939,51.4818153381],"type":"Point"}
}