{
  "type": "Feature",
  "properties": {
    "iso:country":"GB",
    "sg:address":"82 Devonshire Road",
    "sg:city":"Chorley",
    "sg:classifiers":[
        {
            "category":"Organizations",
            "subcategory":"Non-profit Organization",
            "type":"Services"
        }
    ],
    "sg:phone":"+44 1257 231660",
    "sg:postcode":"PR7 2DR",
    "sg:province":"Lancashire",
    "sg:tags":[
        "organisation",
        "voluntary",
        "charity"
    ],
    "wof:name":"Mind Chorley & South Ribble",
    "wof:placetype":"venue"
},
  "geometry": {"coordinates":[-2.636122,53.649689],"type":"Point"}
}