{
  "type": "Feature",
  "properties": {
    "iso:country":"GB",
    "sg:address":"Unit 9 Indescon Ct, Millharbour",
    "sg:city":"Poplar",
    "sg:classifiers":[
        {
            "category":"Building & Trades",
            "subcategory":"Construction",
            "type":"Services"
        }
    ],
    "sg:phone":"+44 20 7515 1892",
    "sg:postcode":"E14 9TN",
    "sg:province":"Greater London",
    "sg:tags":[
        "builder"
    ],
    "wof:name":"South Essex Building Services",
    "wof:placetype":"venue"
},
  "geometry": {"coordinates":[-0.0193990003,51.4984016418],"type":"Point"}
}