{
  "type": "Feature",
  "properties": {
    "addr:full":"18 Pensbury Street, Battersea London Greater London SW8 4TJ",
    "addr:housenumber":"18",
    "addr:postcode":"sw8 4tj",
    "addr:street":"Pensbury Street",
    "iso:country":"GB",
    "sg:address":"18 Pensbury Street, Battersea",
    "sg:city":"London",
    "sg:classifiers":[
        {
            "category":"Retail",
            "subcategory":"Event Space",
            "type":"Services"
        }
    ],
    "sg:phone":"+44 20 7498 3837",
    "sg:postcode":"SW8 4TJ",
    "sg:province":"Greater London",
    "sg:tags":[
        "exhibition",
        "organiser"
    ],
    "wof:name":"The Food Studio Ltd.",
    "wof:placetype":"venue"
},
  "geometry": {"coordinates":[-0.138252005,51.4715461731],"type":"Point"}
}