{
  "type": "Feature",
  "properties": {
    "addr:full":"26 The Grn, Hasland Chesterfield Derbyshire S41 0LJ",
    "addr:housenumber":"26",
    "addr:postcode":"s41 0lj",
    "addr:street":"The Grn",
    "iso:country":"GB",
    "sg:address":"26 The Grn, Hasland",
    "sg:city":"Chesterfield",
    "sg:classifiers":[
        {
            "category":"Farming",
            "subcategory":"Nursery",
            "type":"Manufacturing & Wholesale Goods"
        }
    ],
    "sg:phone":"+44 1246 555022",
    "sg:postcode":"S41 0LJ",
    "sg:province":"Derbyshire",
    "sg:tags":[
        "creche"
    ],
    "wof:name":"Mary Poppins Day Nursery",
    "wof:placetype":"venue"
},
  "geometry": {"coordinates":[-1.417802,53.220535],"type":"Point"}
}