{
  "type": "Feature",
  "properties": {
    "addr:full":"Centrum Park, Hagmill Road, Coatbridge Coatbridge North Lanarkshire ML5 4TD",
    "addr:postcode":"ml5 4td",
    "addr:street":"Hagmill Road",
    "iso:country":"GB",
    "sg:address":"Centrum Park, Hagmill Road, Coatbridge",
    "sg:city":"Coatbridge",
    "sg:classifiers":[
        {
            "category":"Professional",
            "subcategory":"Management & Consulting",
            "type":"Services"
        }
    ],
    "sg:phone":"+44 1236 438181",
    "sg:postcode":"ML5 4TD",
    "sg:province":"North Lanarkshire",
    "sg:tags":[
        "consultant",
        "safety",
        "business"
    ],
    "wof:name":"Salus Occupational Health & Safety",
    "wof:placetype":"venue"
},
  "geometry": {"coordinates":[-4.0180702209,55.8414306641],"type":"Point"}
}