{
  "type": "Feature",
  "properties": {
    "addr:full":"Fen Lane, Grainthorpe Louth Lincolnshire LN11 7JY",
    "addr:postcode":"ln11 7jy",
    "addr:street":"Fen Lane;Louth",
    "iso:country":"GB",
    "sg:address":"Fen Lane, Grainthorpe",
    "sg:city":"Louth",
    "sg:classifiers":[
        {
            "category":"Education",
            "subcategory":"School",
            "type":"Public Place"
        }
    ],
    "sg:phone":"+44 1472 388248",
    "sg:postcode":"LN11 7JY",
    "sg:province":"Lincolnshire",
    "sg:tags":[
        "local",
        "authority"
    ],
    "wof:name":"Grainthorpe County Primary School",
    "wof:placetype":"venue"
},
  "geometry": {"coordinates":[0.0809699968,53.4506721497],"type":"Point"}
}