{
  "type": "Feature",
  "properties": {
    "addr:full":"2 Waltham Rd Rayleigh Essex SS6 9BB",
    "addr:housenumber":"2",
    "addr:postcode":"ss6 9bb",
    "addr:street":"Waltham Rd",
    "iso:country":"GB",
    "sg:address":"2 Waltham Rd",
    "sg:city":"Rayleigh",
    "sg:classifiers":[
        {
            "category":"Home & Garden",
            "subcategory":"Home Furnishings",
            "type":"Retail Goods"
        }
    ],
    "sg:phone":"+44 1268 781994",
    "sg:postcode":"SS6 9BB",
    "sg:province":"Essex",
    "sg:tags":[
        "mantelpiece",
        "fireplace"
    ],
    "wof:name":"T G Swain",
    "wof:placetype":"venue"
},
  "geometry": {"coordinates":[0.593262,51.593864],"type":"Point"}
}