{
  "type": "Feature",
  "properties": {
    "iso:country":"GB",
    "sg:address":"The Old Military Hospital",
    "sg:city":"Tywyn",
    "sg:classifiers":[
        {
            "category":"Professional",
            "subcategory":"Management & Consulting",
            "type":"Services"
        }
    ],
    "sg:phone":"+44 1654 712555",
    "sg:postcode":"LL36 9UE",
    "sg:province":"Gwynedd",
    "sg:tags":[
        "consultant",
        "training"
    ],
    "wof:name":"Challenge Group Of Companies The",
    "wof:placetype":"venue"
},
  "geometry": {"coordinates":[-4.0884189606,52.5865859985],"type":"Point"}
}