{
  "type": "Feature",
  "properties": {
    "addr:full":"The Old Coach House Pontefract North Yorkshire WF8 4HT",
    "addr:postcode":"wf8 4ht",
    "addr:street":"Pontefract",
    "iso:country":"GB",
    "sg:address":"The Old Coach House",
    "sg:city":"Pontefract",
    "sg:classifiers":[
        {
            "category":"Professional",
            "subcategory":"Computer Services",
            "type":"Services"
        }
    ],
    "sg:phone":"+44 1977 690977",
    "sg:postcode":"WF8 4HT",
    "sg:province":"North Yorkshire",
    "sg:tags":[
        "system",
        "software"
    ],
    "wof:name":"Pcti Ltd.",
    "wof:placetype":"venue"
},
  "geometry": {"coordinates":[-1.3065040112,53.6925086975],"type":"Point"}
}