{
  "type": "Feature",
  "properties": {
    "addr:full":"Unit 2 Haddenham Business Park Cambridge Cambridgeshire CB6 3PS",
    "addr:housenumber":"unit 2 haddenham",
    "addr:postcode":"cb6 3ps",
    "addr:street":"Business Park",
    "iso:country":"GB",
    "sg:address":"Unit 2 Haddenham Business Park",
    "sg:city":"Cambridge",
    "sg:classifiers":[
        {
            "category":"Home & Garden",
            "subcategory":"Kitchen Supply",
            "type":"Retail Goods"
        }
    ],
    "sg:phone":"+44 1353 741661",
    "sg:postcode":"CB6 3PS",
    "sg:province":"Cambridgeshire",
    "sg:tags":[
        "equipment",
        "catering"
    ],
    "wof:name":"N J Marketing Ltd.",
    "wof:placetype":"venue"
},
  "geometry": {"coordinates":[0.1503,52.36898],"type":"Point"}
}