{
  "type": "Feature",
  "properties": {
    "addr:full":"Union Road, East Abergavenny Herefordshire NP7 5UL",
    "addr:postcode":"np7 5ul",
    "addr:street":"Union Road East",
    "iso:country":"GB",
    "sg:address":"Union Road, East",
    "sg:city":"Abergavenny",
    "sg:classifiers":[
        {
            "category":"Personal",
            "subcategory":"Beauty Salon",
            "type":"Services"
        },
        {
            "category":"Personal",
            "subcategory":"Barber",
            "type":"Services"
        }
    ],
    "sg:phone":"+44 1873 854135",
    "sg:postcode":"NP7 5UL",
    "sg:province":"Herefordshire",
    "sg:tags":[
        "unisex",
        "hairdresser"
    ],
    "wof:name":"ASTON HOUSE HAIRDRESSING",
    "wof:placetype":"venue"
},
  "geometry": {"coordinates":[-3.028074,51.821934],"type":"Point"}
}