{
  "type": "Feature",
  "properties": {
    "addr:full":"Teachers Assurance Ltd, Tringham House, Deansleigh Road Bournemouth Dorset BH7 7DT",
    "addr:housenumber":"tringham",
    "addr:postcode":"dorset bh7 7dt",
    "addr:street":"Deansleigh Road",
    "iso:country":"GB",
    "sg:address":"Teachers Assurance Ltd, Tringham House, Deansleigh Road",
    "sg:city":"Bournemouth",
    "sg:classifiers":[
        {
            "category":"Professional",
            "subcategory":"Management & Consulting",
            "type":"Services"
        }
    ],
    "sg:postcode":"BH7 7DT",
    "sg:province":"Dorset",
    "sg:tags":[
        "consultant",
        "specialist"
    ],
    "wof:name":"Opal Consultants Ltd",
    "wof:placetype":"venue"
},
  "geometry": {"coordinates":[-1.8183920383,50.7475090027],"type":"Point"}
}