{
  "type": "Feature",
  "properties": {
    "addr:full":"Blundells Road Tiverton Devon EX16 4PR",
    "addr:postcode":"ex16 4pr",
    "addr:street":"Blundells Road",
    "iso:country":"GB",
    "sg:address":"Blundells Road",
    "sg:city":"Tiverton",
    "sg:classifiers":[
        {
            "category":"Autos & Motor Vehicles",
            "subcategory":"Auto Supplies",
            "type":"Retail Goods"
        }
    ],
    "sg:phone":"+44 1884 251577",
    "sg:postcode":"EX16 4PR",
    "sg:province":"Devon",
    "sg:tags":[
        "towing",
        "eqpt",
        "trailer"
    ],
    "wof:name":"Admiral Trailers Ltd.",
    "wof:placetype":"venue"
},
  "geometry": {"coordinates":[-3.470471,50.905777],"type":"Point"}
}