{
  "type": "Feature",
  "properties": {
    "iso:country":"GB",
    "sg:address":"29 Ordnance Hill",
    "sg:city":"London",
    "sg:classifiers":[
        {
            "category":"Bars & Pubs",
            "type":"Food & Drink"
        }
    ],
    "sg:phone":"+44 20 7722 0278",
    "sg:postcode":"NW8 6PS",
    "sg:province":"Greater London",
    "sg:tags":[
        "pubs",
        "inn"
    ],
    "wof:name":"The Ordnance Arms",
    "wof:placetype":"venue"
},
  "geometry": {"coordinates":[-0.171514,51.535847],"type":"Point"}
}