{
  "type": "Feature",
  "properties": {
    "iso:country":"GB",
    "sg:address":"13 North Park Avenue, Barrowford",
    "sg:city":"Nelson",
    "sg:classifiers":[
        {
            "category":"Shopping",
            "subcategory":"Pharmacy",
            "type":"Retail Goods"
        }
    ],
    "sg:phone":"+44 1282 615143",
    "sg:postcode":"BB9 6DW",
    "sg:province":"Lancashire",
    "sg:tags":[
        "medical"
    ],
    "wof:name":"Pendle Medical Supplies",
    "wof:placetype":"venue"
},
  "geometry": {"coordinates":[-2.2242259979,53.8419456482],"type":"Point"}
}