{
  "type": "Feature",
  "properties": {
    "addr:full":"Southport Rd, Scarsbrick Ormskirk Lancashire L40 8HQ",
    "addr:postcode":"l40 8hq",
    "addr:street":"Southport Rd",
    "iso:country":"GB",
    "sg:address":"Southport Rd, Scarsbrick",
    "sg:city":"Ormskirk",
    "sg:classifiers":[
        {
            "category":"Bars & Pubs",
            "type":"Food & Drink"
        }
    ],
    "sg:phone":"+44 1704 840317",
    "sg:postcode":"L40 8HQ",
    "sg:province":"Lancashire",
    "sg:tags":[
        "pubs",
        "inn"
    ],
    "wof:name":"The Red Lion Hotel",
    "wof:placetype":"venue"
},
  "geometry": {"coordinates":[-2.8982419968,53.5804672241],"type":"Point"}
}