{
  "type": "Feature",
  "properties": {
    "iso:country":"GB",
    "sg:address":"Unit 3 Laurence Indust Est, Eastwoodbury La",
    "sg:city":"Southend On Sea",
    "sg:classifiers":[
        {
            "category":"Professional",
            "subcategory":"Printing & Photocopies",
            "type":"Services"
        }
    ],
    "sg:phone":"+44 1702 522044",
    "sg:postcode":"SS2 6RH",
    "sg:province":"Essex",
    "sg:tags":[
        "printer"
    ],
    "wof:name":"Northleigh Design & Print",
    "wof:placetype":"venue"
},
  "geometry": {"coordinates":[0.68176,51.567719],"type":"Point"}
}