{
  "type": "Feature",
  "properties": {
    "iso:country":"GB",
    "sg:address":"City Works, Lower City Road",
    "sg:city":"Smethwick",
    "sg:classifiers":[
        {
            "category":"Professional",
            "subcategory":"Engineering",
            "type":"Services"
        }
    ],
    "sg:postcode":"B69 2HP",
    "sg:province":"West Midlands",
    "wof:name":"Leafrock Ltd.",
    "wof:placetype":"venue"
},
  "geometry": {"coordinates":[-2.04557,52.51326],"type":"Point"}
}