{
  "type": "Feature",
  "properties": {
    "addr:full":"6c Heol-y-deri Cardiff Cardiff CF14 6HF",
    "addr:housenumber":"6c",
    "addr:postcode":"cf14 6hf",
    "addr:street":"Heol-Y-Deri Cardiff",
    "iso:country":"GB",
    "sg:address":"6c Heol-y-deri",
    "sg:city":"Cardiff",
    "sg:classifiers":[
        {
            "category":"Food & Beverages",
            "subcategory":"Fruits & Vegetables",
            "type":"Retail Goods"
        }
    ],
    "sg:phone":"+44 29 2052 2200",
    "sg:postcode":"CF14 6HF",
    "sg:province":"Cardiff",
    "sg:tags":[
        "greengrocer"
    ],
    "wof:name":"Grapes Fruit & Veg",
    "wof:placetype":"venue"
},
  "geometry": {"coordinates":[-3.2121939659,51.5227241516],"type":"Point"}
}