{
  "type": "Feature",
  "properties": {
    "addr:full":"Flat D 741 Garratt Lane London Greater London SW17 0PD",
    "addr:housenumber":"flat d 741",
    "addr:postcode":"sw17 0pd",
    "addr:street":"Garratt Lane",
    "iso:country":"GB",
    "sg:address":"Flat D 741 Garratt Lane",
    "sg:city":"London",
    "sg:classifiers":[
        {
            "category":"Real Estate",
            "subcategory":"Architect",
            "type":"Services"
        }
    ],
    "sg:postcode":"SW17 0PD",
    "sg:province":"Greater London",
    "wof:name":"Shannonvale Technology Ltd",
    "wof:placetype":"venue"
},
  "geometry": {"coordinates":[-0.1853400022,51.4346084595],"type":"Point"}
}