{
  "type": "Feature",
  "properties": {
    "addr:full":"244 Whifflet Street Coatbridge North Lanarkshire ML5 4EW",
    "addr:housenumber":"244",
    "addr:postcode":"ml5 4ew",
    "addr:street":"Whifflet Street",
    "iso:country":"GB",
    "sg:address":"244 Whifflet Street",
    "sg:city":"Coatbridge",
    "sg:classifiers":[
        {
            "category":"Military Area",
            "subcategory":"Air Force Base",
            "type":"Public Place"
        }
    ],
    "sg:phone":"+44 1236 440567",
    "sg:postcode":"ML5 4EW",
    "sg:province":"North Lanarkshire",
    "sg:tags":[
        "taxi",
        "hire",
        "private"
    ],
    "wof:name":"Town Taxis",
    "wof:placetype":"venue"
},
  "geometry": {"coordinates":[-4.023161,55.845337],"type":"Point"}
}