{
  "type": "Feature",
  "properties": {
    "addr:full":"83 Ancaster Avenue Grimsby Lincolnshire DN33 3LP",
    "addr:housenumber":"83",
    "addr:postcode":"dn33 3lp",
    "addr:street":"Ancaster Avenue",
    "iso:country":"GB",
    "sg:address":"83 Ancaster Avenue",
    "sg:city":"Grimsby",
    "sg:classifiers":[
        {
            "category":"Retail",
            "subcategory":"Driving School",
            "type":"Services"
        }
    ],
    "sg:postcode":"DN33 3LP",
    "sg:province":"Lincolnshire",
    "wof:name":"Roman May",
    "wof:placetype":"venue"
},
  "geometry": {"coordinates":[-0.1023520008,53.5320777893],"type":"Point"}
}