{
  "type": "Feature",
  "properties": {
    "addr:full":"Cilau Farm, Llangattock Crickhowell Monmouthshire NP8 1LE",
    "addr:housenumber":"llangattock crickhowell",
    "addr:postcode":"np8 1le",
    "iso:country":"GB",
    "sg:address":"Cilau Farm, Llangattock",
    "sg:city":"Crickhowell",
    "sg:classifiers":[
        {
            "category":"Farming",
            "subcategory":"Livestock Farm",
            "type":"Manufacturing & Wholesale Goods"
        },
        {
            "category":"Farming",
            "subcategory":"Farm",
            "type":"Manufacturing & Wholesale Goods"
        }
    ],
    "sg:phone":"+44 1873 810410",
    "sg:postcode":"NP8 1LE",
    "sg:province":"Monmouthshire",
    "sg:tags":[
        "mixed",
        "crop",
        "others"
    ],
    "wof:name":"Ian Harris",
    "wof:placetype":"venue"
},
  "geometry": {"coordinates":[-3.138122,51.861626],"type":"Point"}
}