{
  "type": "Feature",
  "properties": {
    "addr:full":"38 Broadhurst Walk Rainham Essex RM13 7HH",
    "addr:housenumber":"38",
    "addr:postcode":"rm13 7hh",
    "addr:street":"Broadhurst Walk",
    "iso:country":"GB",
    "sg:address":"38 Broadhurst Walk",
    "sg:city":"Rainham",
    "sg:classifiers":[
        {
            "category":"Building & Trades",
            "subcategory":"Plumbing",
            "type":"Services"
        }
    ],
    "sg:postcode":"RM13 7HH",
    "sg:province":"Essex",
    "sg:tags":[
        "heating"
    ],
    "wof:name":"Peter Reilly",
    "wof:placetype":"venue"
},
  "geometry": {"coordinates":[0.193595,51.54026],"type":"Point"}
}