{
  "type": "Feature",
  "properties": {
    "iso:country":"GB",
    "sg:address":"Halstow, Tedburn St Mary",
    "sg:city":"Exeter",
    "sg:classifiers":[
        {
            "category":"Professional",
            "subcategory":"Advertising",
            "type":"Services"
        },
        {
            "category":"Farming",
            "subcategory":"Livestock Farm",
            "type":"Manufacturing & Wholesale Goods"
        }
    ],
    "sg:phone":"+44 1647 61236",
    "sg:postcode":"EX6 6AN",
    "sg:province":"Devon",
    "sg:tags":[
        "cider",
        "maker",
        "others"
    ],
    "wof:name":"Grays Farm Cider",
    "wof:placetype":"venue"
},
  "geometry": {"coordinates":[-3.668489933,50.7161712646],"type":"Point"}
}