{
  "type": "Feature",
  "properties": {
    "iso:country":"GB",
    "sg:address":"Princes Road, Rhosllanerchrugog",
    "sg:city":"Wrexham",
    "sg:classifiers":[
        {
            "category":"Education",
            "subcategory":"Library",
            "type":"Public Place"
        },
        {
            "category":"Government",
            "subcategory":"Office",
            "type":"Public Place"
        }
    ],
    "sg:phone":"+44 1978 840328",
    "sg:postcode":"LL14 1AB",
    "sg:province":"Wrexham",
    "sg:tags":[
        "book",
        "local"
    ],
    "wof:name":"Rhosllannerchrugog Library",
    "wof:placetype":"venue"
},
  "geometry": {"coordinates":[-3.057684,53.009636],"type":"Point"}
}