{
  "type": "Feature",
  "properties": {
    "iso:country":"GB",
    "sg:address":"56 Norfolk Street",
    "sg:city":"Liverpool",
    "sg:classifiers":[
        {
            "category":"Retail",
            "subcategory":"Car Wash",
            "type":"Services"
        },
        {
            "category":"Retail",
            "subcategory":"Auto Repair",
            "type":"Services"
        }
    ],
    "sg:phone":"+44 151 708 8881",
    "sg:postcode":"L1 0BE",
    "sg:province":"Merseyside",
    "sg:tags":[
        "upholsterer",
        "trimmer"
    ],
    "wof:name":"Auto Interiors",
    "wof:placetype":"venue"
},
  "geometry": {"coordinates":[-2.9807949066,53.3963432312],"type":"Point"}
}