{
  "type": "Feature",
  "properties": {
    "addr:full":"39 Fore Street Kingsbridge Devon TQ7 1PG",
    "addr:housenumber":"39",
    "addr:postcode":"tq7 1pg",
    "addr:street":"Fore Street",
    "iso:country":"GB",
    "sg:address":"39 Fore Street",
    "sg:city":"Kingsbridge",
    "sg:classifiers":[
        {
            "category":"Sports & Exercise",
            "subcategory":"Athletic Track",
            "type":"Entertainment"
        }
    ],
    "sg:phone":"+44 1548 856780",
    "sg:postcode":"TQ7 1PG",
    "sg:province":"Devon",
    "sg:tags":[
        "bags",
        "accessory",
        "belt"
    ],
    "wof:name":"Bags of Choice",
    "wof:placetype":"venue"
},
  "geometry": {"coordinates":[-3.7774620056,50.2846870422],"type":"Point"}
}