{
  "type": "Feature",
  "properties": {
    "addr:full":"Express Trad Est, Stone Hill Bolton Lancashire BL4 9NN",
    "addr:postcode":"bl4 9nn",
    "addr:street":"Trad Est Stone Hill",
    "iso:country":"GB",
    "sg:address":"Express Trad Est, Stone Hill",
    "sg:city":"Bolton",
    "sg:classifiers":[
        {
            "category":"Manufacturing",
            "subcategory":"Metals",
            "type":"Manufacturing & Wholesale Goods"
        },
        {
            "category":"Government",
            "subcategory":"Post Office",
            "type":"Public Place"
        }
    ],
    "sg:postcode":"BL4 9NN",
    "sg:province":"Lancashire",
    "sg:tags":[
        "steel",
        "copper",
        "brass",
        "stockholder"
    ],
    "wof:name":"Amari Metals Ltd",
    "wof:placetype":"venue"
},
  "geometry": {"coordinates":[-2.3921298981,53.5397796631],"type":"Point"}
}