{
  "type": "Feature",
  "properties": {
    "addr:full":"234-236 Northolt Road, South Harrow Greater London HA2 8DU",
    "addr:housenumber":"234-236",
    "addr:postcode":"ha2 8du",
    "addr:street":"Northolt Road",
    "iso:country":"GB",
    "sg:address":"234-236 Northolt Road, South",
    "sg:city":"Harrow",
    "sg:classifiers":[
        {
            "category":"Shopping",
            "subcategory":"Department Store",
            "type":"Retail Goods"
        }
    ],
    "sg:postcode":"HA2 8DU",
    "sg:province":"Greater London",
    "wof:name":"South Harrow Food & Wines Co. Ltd.",
    "wof:placetype":"venue"
},
  "geometry": {"coordinates":[-0.353789,51.564533],"type":"Point"}
}