{
  "type": "Feature",
  "properties": {
    "iso:country":"GB",
    "sg:address":"Pavilion, Sports Field",
    "sg:city":"Lincoln",
    "sg:classifiers":[
        {
            "category":"Arena",
            "subcategory":"Sports Club",
            "type":"Entertainment"
        }
    ],
    "sg:phone":"+44 1522 690674",
    "sg:postcode":"LN6 0ED",
    "sg:province":"Lincolnshire",
    "wof:name":"Lincoln United Football Club",
    "wof:placetype":"venue"
},
  "geometry": {"coordinates":[-0.58277,53.212051],"type":"Point"}
}