{
  "type": "Feature",
  "properties": {
    "addr:full":"45 Ings La, Guiseley Leeds West Yorkshire LS20 9HR",
    "addr:housenumber":"45",
    "addr:postcode":"ls20 9hr",
    "addr:street":"Ings La Guiseley Leeds West",
    "iso:country":"GB",
    "sg:address":"45 Ings La, Guiseley",
    "sg:city":"Leeds",
    "sg:classifiers":[
        {
            "category":"Bars & Pubs",
            "type":"Food & Drink"
        }
    ],
    "sg:phone":"+44 1943 873315",
    "sg:postcode":"LS20 9HR",
    "sg:province":"West Yorkshire",
    "sg:tags":[
        "pubs",
        "inn"
    ],
    "wof:name":"Punch Inns (U K) Ltd",
    "wof:placetype":"venue"
},
  "geometry": {"coordinates":[-1.721356988,53.881023407],"type":"Point"}
}