{
  "type": "Feature",
  "properties": {
    "addr:full":"Ashley Rd Glenrothes Fife KY6 2SE",
    "addr:postcode":"ky6 2se",
    "addr:street":"Ashley Rd",
    "iso:country":"GB",
    "sg:address":"Ashley Rd",
    "sg:city":"Glenrothes",
    "sg:classifiers":[
        {
            "category":"Professional",
            "subcategory":"Business Services",
            "type":"Services"
        }
    ],
    "sg:phone":"+44 1592 775716",
    "sg:postcode":"KY6 2SE",
    "sg:province":"Fife",
    "sg:tags":[
        "distribution"
    ],
    "wof:name":"T D G Williams Distribution",
    "wof:placetype":"venue"
},
  "geometry": {"coordinates":[-3.183619,56.178864],"type":"Point"}
}