{
  "type": "Feature",
  "properties": {
    "iso:country":"GB",
    "sg:address":"Newburn Enterprise Centre, High Street, Newburn",
    "sg:city":"Newcastle Upon Tyne",
    "sg:classifiers":[
        {
            "category":"Professional",
            "type":"Services"
        }
    ],
    "sg:phone":"+44 191 229 1122",
    "sg:postcode":"NE15 8LN",
    "sg:province":"Northumberland",
    "sg:tags":[
        "directory",
        "pub"
    ],
    "wof:name":"Total Print Services",
    "wof:placetype":"venue"
},
  "geometry": {"coordinates":[-1.73822,54.981609],"type":"Point"}
}