{
  "type": "Feature",
  "properties": {
    "iso:country":"GB",
    "sg:address":"1 Bishops Ho, Market Place, Chalfont St Peter",
    "sg:city":"Gerrards Cross",
    "sg:classifiers":[
        {
            "category":"Shopping",
            "subcategory":"Pharmacy",
            "type":"Retail Goods"
        }
    ],
    "sg:postcode":"SL9 9QQ",
    "sg:province":"Buckinghamshire",
    "sg:tags":[
        "pharmacist",
        "chemist"
    ],
    "wof:name":"Bhadwaj,P C,",
    "wof:placetype":"venue"
},
  "geometry": {"coordinates":[-0.55582,51.607052],"type":"Point"}
}