{
  "type": "Feature",
  "properties": {
    "iso:country":"GB",
    "sg:address":"258 Merton Road, Wandsworth",
    "sg:city":"London",
    "sg:classifiers":[
        {
            "category":"Professional",
            "subcategory":"Accounting & Tax Preparation",
            "type":"Services"
        }
    ],
    "sg:phone":"+44 20 8870 7898",
    "sg:postcode":"SW18 5JL",
    "sg:province":"Greater London",
    "sg:tags":[
        "accountant"
    ],
    "wof:name":"Husain Bulman A & Co Chartered Accountants",
    "wof:placetype":"venue"
},
  "geometry": {"coordinates":[-0.199443,51.448292],"type":"Point"}
}