{
  "type": "Feature",
  "properties": {
    "iso:country":"GB",
    "sg:address":"County Hall, Croesyceiliog",
    "sg:city":"Cwmbran",
    "sg:classifiers":[
        {
            "category":"Real Estate",
            "subcategory":"Real Estate Services",
            "type":"Services"
        },
        {
            "category":"Professional",
            "subcategory":"Business Services",
            "type":"Services"
        }
    ],
    "sg:phone":"+44 1633 644099",
    "sg:postcode":"NP44 2XH",
    "sg:province":"Monmouthshire",
    "sg:tags":[
        "management",
        "facility"
    ],
    "wof:name":"Monitor Facilities Management Ltd",
    "wof:placetype":"venue"
},
  "geometry": {"coordinates":[-3.007425,51.660568],"type":"Point"}
}