{
  "type": "Feature",
  "properties": {
    "addr:full":"Singing Hills Golf Course, Albourne Hassocks East Sussex BN6 9EB",
    "addr:postcode":"bn6 9eb",
    "addr:street":"Singing;Albourne",
    "iso:country":"GB",
    "sg:address":"Singing Hills Golf Course, Albourne",
    "sg:city":"Hassocks",
    "sg:classifiers":[
        {
            "category":"Sports & Exercise",
            "subcategory":"Golf",
            "type":"Entertainment"
        }
    ],
    "sg:phone":"+44 1273 835353",
    "sg:postcode":"BN6 9EB",
    "sg:province":"East Sussex",
    "sg:tags":[
        "club",
        "course"
    ],
    "wof:name":"Singing Hills Golf Course Ltd.",
    "wof:placetype":"venue"
},
  "geometry": {"coordinates":[-0.2015070021,50.9333686829],"type":"Point"}
}