{
  "type": "Feature",
  "properties": {
    "addr:full":"Harbour House, Marine Parade Dover Kent CT17 9BU",
    "addr:postcode":"ct17 9bu",
    "addr:street":"Marine Parade Dover",
    "iso:country":"GB",
    "sg:address":"Harbour House, Marine Parade",
    "sg:city":"Dover",
    "sg:classifiers":[
        {
            "category":"Harbor",
            "type":"Transportation"
        }
    ],
    "sg:phone":"+44 1304 208288",
    "sg:postcode":"CT17 9BU",
    "sg:province":"Kent",
    "sg:tags":[
        "dock",
        "ports",
        "harbour"
    ],
    "wof:name":"Dover Coach Services",
    "wof:placetype":"venue"
},
  "geometry": {"coordinates":[1.3220139742,51.1251411438],"type":"Point"}
}