{
  "type": "Feature",
  "properties": {
    "iso:country":"GB",
    "sg:address":"3 Fieldhouse Road",
    "sg:city":"Rochdale",
    "sg:classifiers":[
        {
            "category":"Manufacturing",
            "subcategory":"Signs",
            "type":"Manufacturing & Wholesale Goods"
        }
    ],
    "sg:postcode":"OL12 0AA",
    "sg:province":"Lancashire",
    "sg:tags":[
        "nameplate"
    ],
    "wof:name":"Boss Graphics",
    "wof:placetype":"venue"
},
  "geometry": {"coordinates":[-2.153911,53.62833],"type":"Point"}
}