{
  "type": "Feature",
  "properties": {
    "iso:country":"GB",
    "sg:address":"Fisher Road, Bishops Itchington",
    "sg:city":"Southam",
    "sg:classifiers":[
        {
            "category":"Organizations",
            "subcategory":"Membership Organization",
            "type":"Services"
        }
    ],
    "sg:phone":"+44 1926 612349",
    "sg:postcode":"CV47 2RE",
    "sg:province":"Warwickshire",
    "sg:tags":[
        "club"
    ],
    "wof:name":"Greaves Club",
    "wof:placetype":"venue"
},
  "geometry": {"coordinates":[-1.430709,52.217182],"type":"Point"}
}