{
  "type": "Feature",
  "properties": {
    "iso:country":"GB",
    "sg:address":"57 Church Lane",
    "sg:city":"Skegness",
    "sg:classifiers":[
        {
            "category":"Food & Beverages",
            "subcategory":"Meat & Fish",
            "type":"Retail Goods"
        }
    ],
    "sg:phone":"+44 1754 760209",
    "sg:postcode":"PE25 1EG",
    "sg:province":"Lincolnshire",
    "sg:tags":[
        "chip"
    ],
    "wof:name":"The Friendly Fisheries",
    "wof:placetype":"venue"
},
  "geometry": {"coordinates":[0.3400210142,53.1629562378],"type":"Point"}
}