{
  "type": "Feature",
  "properties": {
    "addr:full":"103 Lower Clapton Road London Greater London E5 0NP",
    "addr:housenumber":"103",
    "addr:postcode":"e5 0np",
    "addr:street":"Lower Clapton Road",
    "iso:country":"GB",
    "sg:address":"103 Lower Clapton Road",
    "sg:city":"London",
    "sg:classifiers":[
        {
            "category":"Home & Garden",
            "subcategory":"Household Appliances",
            "type":"Retail Goods"
        }
    ],
    "sg:phone":"+44 20 8985 6086",
    "sg:postcode":"E5 0NP",
    "sg:province":"Greater London",
    "sg:tags":[
        "cleaner",
        "domestic",
        "vacuum"
    ],
    "wof:name":"Clapton Vac Centre",
    "wof:placetype":"venue"
},
  "geometry": {"coordinates":[-0.0525839999,51.5520896912],"type":"Point"}
}