{
  "type": "Feature",
  "properties": {
    "addr:full":"94 West Green Road London Greater London N15 5NS",
    "addr:housenumber":"94",
    "addr:postcode":"n15 5ns",
    "addr:street":"West Green Road",
    "iso:country":"GB",
    "sg:address":"94 West Green Road",
    "sg:city":"London",
    "sg:classifiers":[
        {
            "category":"Personal",
            "subcategory":"Beauty Salon",
            "type":"Services"
        }
    ],
    "sg:phone":"+44 20 8802 3316",
    "sg:postcode":"N15 5NS",
    "sg:province":"Greater London",
    "sg:tags":[
        "lady",
        "hairdresser"
    ],
    "wof:name":"Trimmindales",
    "wof:placetype":"venue"
},
  "geometry": {"coordinates":[-0.0768600032,51.5848464966],"type":"Point"}
}