{
  "type": "Feature",
  "properties": {
    "addr:full":"16 Damson Road, Thorngumbald Hull East Riding of Yorkshire HU12 9QL",
    "addr:housenumber":"16",
    "addr:postcode":"hu12 9ql",
    "addr:street":"Damson Road",
    "iso:country":"GB",
    "sg:address":"16 Damson Road, Thorngumbald",
    "sg:city":"Hull",
    "sg:classifiers":[
        {
            "category":"Building & Trades",
            "subcategory":"Construction",
            "type":"Services"
        }
    ],
    "sg:phone":"+44 1964 623249",
    "sg:postcode":"HU12 9QL",
    "sg:province":"East Riding of Yorkshire",
    "sg:tags":[
        "builder"
    ],
    "wof:name":"Roger Kirkham",
    "wof:placetype":"venue"
},
  "geometry": {"coordinates":[-0.1737540066,53.7182502747],"type":"Point"}
}