{
  "type": "Feature",
  "properties": {
    "iso:country":"GB",
    "sg:address":"24 Rose Lane",
    "sg:city":"Crewkerne",
    "sg:classifiers":[
        {
            "category":"Manufacturing",
            "subcategory":"Metals",
            "type":"Manufacturing & Wholesale Goods"
        },
        {
            "category":"Wholesale",
            "subcategory":"Scrap",
            "type":"Manufacturing & Wholesale Goods"
        }
    ],
    "sg:phone":"+44 1460 72176",
    "sg:postcode":"TA18 7ER",
    "sg:province":"Dorset",
    "sg:tags":[
        "waste"
    ],
    "wof:name":"E A Tuck",
    "wof:placetype":"venue"
},
  "geometry": {"coordinates":[-2.797685,50.886513],"type":"Point"}
}