{
  "type": "Feature",
  "properties": {
    "addr:full":"18-22 West Street Bridport Dorset DT6 3QP",
    "addr:housenumber":"18-22",
    "addr:postcode":"dt6 3qp",
    "addr:street":"West Street",
    "iso:country":"GB",
    "sg:address":"18-22 West Street",
    "sg:city":"Bridport",
    "sg:classifiers":[
        {
            "category":"Shopping",
            "subcategory":"Pharmacy",
            "type":"Retail Goods"
        }
    ],
    "sg:phone":"+44 1308 458015",
    "sg:postcode":"DT6 3QP",
    "sg:province":"Dorset",
    "sg:tags":[
        "store",
        "drug",
        "outlet"
    ],
    "wof:name":"Superdrug Stores plc",
    "wof:placetype":"venue"
},
  "geometry": {"coordinates":[-2.7592449188,50.7336845398],"type":"Point"}
}