{
  "type": "Feature",
  "properties": {
    "addr:full":"3-5 King Street Perth Perth and Kinross PH2 8HR",
    "addr:housenumber":"3-5",
    "addr:postcode":"ph2 8hr",
    "addr:street":"King Street",
    "iso:country":"GB",
    "sg:address":"3-5 King Street",
    "sg:city":"Perth",
    "sg:classifiers":[
        {
            "category":"Autos & Motor Vehicles",
            "subcategory":"Auto Supplies",
            "type":"Retail Goods"
        }
    ],
    "sg:phone":"+44 1738 623144",
    "sg:postcode":"PH2 8HR",
    "sg:province":"Perth and Kinross",
    "sg:tags":[
        "tyre"
    ],
    "wof:name":"Hi-Q Tyre Services",
    "wof:placetype":"venue"
},
  "geometry": {"coordinates":[-3.434377,56.395096],"type":"Point"}
}