{
  "type": "Feature",
  "properties": {
    "iso:country":"GB",
    "sg:address":"Unit 2 Holyrood Drive, Skipping Dale Industrial Estate",
    "sg:city":"Scunthorpe",
    "sg:classifiers":[
        {
            "category":"Home & Garden",
            "subcategory":"Home Furnishings",
            "type":"Retail Goods"
        }
    ],
    "sg:postcode":"DN15 8NN",
    "sg:province":"Lincolnshire",
    "sg:tags":[
        "mantelpiece",
        "fireplace"
    ],
    "wof:name":"Fireplace & Beams",
    "wof:placetype":"venue"
},
  "geometry": {"coordinates":[-0.6792889833,53.6058807373],"type":"Point"}
}