{
  "type": "Feature",
  "properties": {
    "iso:country":"GB",
    "sg:address":"240 Bath Street",
    "sg:city":"Glasgow",
    "sg:classifiers":[
        {
            "category":"Professional",
            "subcategory":"Management & Consulting",
            "type":"Services"
        }
    ],
    "sg:postcode":"G2 4JW",
    "sg:province":"Glasgow City",
    "sg:tags":[
        "consultant",
        "business"
    ],
    "wof:name":"Escabar Ltd.",
    "wof:placetype":"venue"
},
  "geometry": {"coordinates":[-4.2651181221,55.8649787903],"type":"Point"}
}