{
  "type": "Feature",
  "properties": {
    "addr:full":"Chaddock Lane, Astley Manchester Greater Manchester M29 7JY",
    "addr:postcode":"m29 7jy",
    "addr:street":"Chaddock Lane",
    "iso:country":"GB",
    "sg:address":"Chaddock Lane, Astley",
    "sg:city":"Manchester",
    "sg:classifiers":[
        {
            "category":"Deli",
            "type":"Food & Drink"
        },
        {
            "category":"Food & Beverages",
            "subcategory":"Meat & Fish",
            "type":"Retail Goods"
        }
    ],
    "sg:phone":"+44 1942 885320",
    "sg:postcode":"M29 7JY",
    "sg:province":"Greater Manchester",
    "sg:tags":[
        "delicatessen",
        "butcher"
    ],
    "wof:name":"Gabbotts Farm Ltd.",
    "wof:placetype":"venue"
},
  "geometry": {"coordinates":[-2.443189,53.503227],"type":"Point"}
}