{
  "type": "Feature",
  "properties": {
    "addr:full":"8 Handel Parade, Whitchurch Lane Edgware Greater London HA8 6LD",
    "addr:housenumber":"8",
    "addr:postcode":"ha8 6ld",
    "addr:street":"Handel Parade Whitchurch Lane",
    "iso:country":"GB",
    "sg:address":"8 Handel Parade, Whitchurch Lane",
    "sg:city":"Edgware",
    "sg:classifiers":[
        {
            "category":"Food & Beverages",
            "subcategory":"Meat & Fish",
            "type":"Retail Goods"
        }
    ],
    "sg:phone":"+44 20 8952 1163",
    "sg:postcode":"HA8 6LD",
    "sg:province":"Greater London",
    "sg:tags":[
        "chip"
    ],
    "wof:name":"Rock Ruby Fish Bar",
    "wof:placetype":"venue"
},
  "geometry": {"coordinates":[-0.2806929946,51.6094932556],"type":"Point"}
}