{
  "type": "Feature",
  "properties": {
    "addr:full":"Onyx House, 164 Cheetham Hill Road Manchester Greater Manchester M8 8LQ",
    "addr:housenumber":"164",
    "addr:postcode":"m8 8lq",
    "addr:street":"Cheetham Hill Road",
    "iso:country":"GB",
    "sg:address":"Onyx House, 164 Cheetham Hill Road",
    "sg:city":"Manchester",
    "sg:classifiers":[
        {
            "category":"Shopping",
            "subcategory":"Beauty & Cosmetics",
            "type":"Retail Goods"
        },
        {
            "category":"Wholesale",
            "subcategory":"Chemicals & Plastics",
            "type":"Manufacturing & Wholesale Goods"
        }
    ],
    "sg:phone":"+44 161 834 1387",
    "sg:postcode":"M8 8LQ",
    "sg:province":"Greater Manchester",
    "sg:tags":[
        "supplier",
        "product",
        "perfume"
    ],
    "wof:name":"Onyx Cosmetics",
    "wof:placetype":"venue"
},
  "geometry": {"coordinates":[-2.235374,53.498322],"type":"Point"}
}