{
  "type": "Feature",
  "properties": {
    "addr:full":"Acklington Rd Morpeth Northumberland NE65 9XD",
    "addr:postcode":"ne65 9xd",
    "addr:street":"Acklington Rd",
    "iso:country":"GB",
    "sg:address":"Acklington Rd",
    "sg:city":"Morpeth",
    "sg:classifiers":[
        {
            "category":"Personal",
            "type":"Services"
        }
    ],
    "sg:phone":"+44 1670 760247",
    "sg:postcode":"NE65 9XD",
    "sg:province":"Northumberland",
    "sg:tags":[
        "delivery"
    ],
    "wof:name":"H Smails Ltd",
    "wof:placetype":"venue"
},
  "geometry": {"coordinates":[-1.6185139418,55.3074989319],"type":"Point"}
}