{
  "type": "Feature",
  "properties": {
    "addr:full":"Ferndale, Britannia Road, Morley Leeds West Yorkshire LS27 0DW",
    "addr:postcode":"ls27 0dw",
    "addr:street":"Britannia Road",
    "iso:country":"GB",
    "sg:address":"Ferndale, Britannia Road, Morley",
    "sg:city":"Leeds",
    "sg:classifiers":[
        {
            "category":"Health Services",
            "subcategory":"Nursing And Care Facility",
            "type":"Services"
        }
    ],
    "sg:phone":"+44 113 253 3196",
    "sg:postcode":"LS27 0DW",
    "sg:province":"West Yorkshire",
    "sg:tags":[
        "home",
        "residential"
    ],
    "wof:name":"Ferndale Residential Home",
    "wof:placetype":"venue"
},
  "geometry": {"coordinates":[-1.610779,53.737373],"type":"Point"}
}