{
  "type": "Feature",
  "properties": {
    "addr:full":"34-36 London Street Norwich Norfolk NR2 1LD",
    "addr:housenumber":"34-36",
    "addr:postcode":"nr2 1ld",
    "addr:street":"London Street",
    "iso:country":"GB",
    "sg:address":"34-36 London Street",
    "sg:city":"Norwich",
    "sg:classifiers":[
        {
            "category":"Shopping",
            "subcategory":"Pharmacy",
            "type":"Retail Goods"
        }
    ],
    "sg:phone":"+44 1603 621295",
    "sg:postcode":"NR2 1LD",
    "sg:province":"Norfolk",
    "sg:tags":[
        "pharmacist",
        "chemist"
    ],
    "wof:name":"Boots the Chemists",
    "wof:placetype":"venue"
},
  "geometry": {"coordinates":[1.2951380014,52.6292114258],"type":"Point"}
}