{
  "type": "Feature",
  "properties": {
    "iso:country":"GB",
    "sg:address":"51 High St, Wombwell",
    "sg:city":"Barnsley",
    "sg:classifiers":[
        {
            "category":"Fast Food",
            "type":"Food & Drink"
        }
    ],
    "sg:phone":"+44 1226 756646",
    "sg:postcode":"S73 8HS",
    "sg:province":"South Yorkshire",
    "sg:tags":[
        "away",
        "take"
    ],
    "wof:name":"The Curry Hut",
    "wof:placetype":"venue"
},
  "geometry": {"coordinates":[-1.39958,53.522911],"type":"Point"}
}