{
  "type": "Feature",
  "properties": {
    "iso:country":"GB",
    "sg:address":"21a-21b South Street",
    "sg:city":"Dorchester",
    "sg:classifiers":[
        {
            "category":"Shopping",
            "subcategory":"Clothing, Apparel, & Fashions",
            "type":"Retail Goods"
        }
    ],
    "sg:phone":"+44 1305 251895",
    "sg:postcode":"DT1 1BY",
    "sg:province":"Dorset",
    "sg:tags":[
        "ladieswear"
    ],
    "wof:name":"Richleys",
    "wof:placetype":"venue"
},
  "geometry": {"coordinates":[-2.437174,50.712383],"type":"Point"}
}