{
  "type": "Feature",
  "properties": {
    "iso:country":"GB",
    "sg:address":"Church Lane",
    "sg:city":"Riding Mill",
    "sg:classifiers":[
        {
            "category":"Education",
            "subcategory":"School",
            "type":"Public Place"
        }
    ],
    "sg:phone":"+44 1434 682374",
    "sg:postcode":"NE44 6DR",
    "sg:province":"Northumberland",
    "sg:tags":[
        "local",
        "authority"
    ],
    "wof:name":"Broomhaugh C Of E First School",
    "wof:placetype":"venue"
},
  "geometry": {"coordinates":[-1.9718240499,54.9467048645],"type":"Point"}
}