{
  "type": "Feature",
  "properties": {
    "iso:country":"GB",
    "sg:address":"4 Cawley Terrace, Heaton Park Road",
    "sg:city":"Manchester",
    "sg:classifiers":[
        {
            "category":"Professional",
            "subcategory":"Detective & Security Services",
            "type":"Services"
        }
    ],
    "sg:phone":"+44 161 720 7436",
    "sg:postcode":"M9 0QR",
    "sg:province":"Greater Manchester",
    "sg:tags":[
        "alarm",
        "burglar",
        "system"
    ],
    "wof:name":"I L Electrical Services",
    "wof:placetype":"venue"
},
  "geometry": {"coordinates":[-2.238643,53.536686],"type":"Point"}
}