{
  "type": "Feature",
  "properties": {
    "addr:full":"10 Church St Runcorn Cheshire WA7 1LR",
    "addr:housenumber":"10",
    "addr:postcode":"wa7 1lr",
    "addr:street":"Church St",
    "iso:country":"GB",
    "sg:address":"10 Church St",
    "sg:city":"Runcorn",
    "sg:classifiers":[
        {
            "category":"Food & Beverages",
            "subcategory":"Supermarket",
            "type":"Retail Goods"
        }
    ],
    "sg:phone":"+44 1928 580733",
    "sg:postcode":"WA7 1LR",
    "sg:province":"Cheshire",
    "wof:name":"Kwik Save Foodstores",
    "wof:placetype":"venue"
},
  "geometry": {"coordinates":[-2.7316288948,53.3420600891],"type":"Point"}
}