{
  "type": "Feature",
  "properties": {
    "addr:full":"65 East St Barking Essex IG11 8EJ",
    "addr:housenumber":"65",
    "addr:postcode":"ig11 8ej",
    "addr:street":"East St",
    "iso:country":"GB",
    "sg:address":"65 East St",
    "sg:city":"Barking",
    "sg:classifiers":[
        {
            "category":"Health Services",
            "subcategory":"Optometrist",
            "type":"Services"
        }
    ],
    "sg:postcode":"IG11 8EJ",
    "sg:province":"Essex",
    "sg:tags":[
        "optician"
    ],
    "wof:name":"Cardtest Ltd",
    "wof:placetype":"venue"
},
  "geometry": {"coordinates":[0.078898,51.537506],"type":"Point"}
}