{
  "type": "Feature",
  "properties": {
    "addr:full":"Duddon Lodge Tarporley Cheshire CW6 0EP",
    "addr:postcode":"cw6 0ep",
    "addr:street":"Tarporley",
    "iso:country":"GB",
    "sg:address":"Duddon Lodge",
    "sg:city":"Tarporley",
    "sg:classifiers":[
        {
            "category":"Building & Trades",
            "subcategory":"Construction",
            "type":"Services"
        }
    ],
    "sg:phone":"+44 1829 781379",
    "sg:postcode":"CW6 0EP",
    "sg:province":"Cheshire",
    "sg:tags":[
        "contractor",
        "pool",
        "swimming"
    ],
    "wof:name":"C R F Swimming Pools",
    "wof:placetype":"venue"
},
  "geometry": {"coordinates":[-2.6687550545,53.1593551636],"type":"Point"}
}