{
  "type": "Feature",
  "properties": {
    "addr:full":"12 Nabbott Rd Chelmsford Essex CM1 2SW",
    "addr:housenumber":"12",
    "addr:postcode":"cm1 2sw",
    "addr:street":"Nabbott Rd",
    "iso:country":"GB",
    "sg:address":"12 Nabbott Rd",
    "sg:city":"Chelmsford",
    "sg:classifiers":[
        {
            "category":"Professional",
            "subcategory":"Engineering",
            "type":"Services"
        }
    ],
    "sg:phone":"+44 1245 281926",
    "sg:postcode":"CM1 2SW",
    "sg:province":"Essex",
    "sg:tags":[
        "engineer"
    ],
    "wof:name":"R.G Ellis Inspection",
    "wof:placetype":"venue"
},
  "geometry": {"coordinates":[0.4475600123,51.7341690063],"type":"Point"}
}