{
  "type": "Feature",
  "properties": {
    "addr:full":"Willfield Court, 9a Willfield Lane, Brown Edge Stoke-on-trent Staffordshire ST6 8RY",
    "addr:housenumber":"9a",
    "addr:postcode":"staffordshire st6 8ry",
    "addr:street":"Willfield Lane",
    "iso:country":"GB",
    "sg:address":"Willfield Court, 9a Willfield Lane, Brown Edge",
    "sg:city":"Stoke-on-trent",
    "sg:classifiers":[
        {
            "category":"Building & Trades",
            "subcategory":"Construction",
            "type":"Services"
        }
    ],
    "sg:phone":"+44 1782 502477",
    "sg:postcode":"ST6 8RY",
    "sg:province":"Staffordshire",
    "sg:tags":[
        "heating",
        "contractor"
    ],
    "wof:name":"A J Cartlich (Plumbing & Heating) Ltd.",
    "wof:placetype":"venue"
},
  "geometry": {"coordinates":[-2.1377999783,53.0748252869],"type":"Point"}
}