{
  "type": "Feature",
  "properties": {
    "addr:full":"86 Sevenoaks Close Romford Essex RM3 7EF",
    "addr:housenumber":"86",
    "addr:postcode":"rm3 7ef",
    "addr:street":"Sevenoaks Close",
    "iso:country":"GB",
    "sg:address":"86 Sevenoaks Close",
    "sg:city":"Romford",
    "sg:classifiers":[
        {
            "category":"Building & Trades",
            "subcategory":"Landscaping Services",
            "type":"Services"
        }
    ],
    "sg:phone":"+44 1708 375507",
    "sg:postcode":"RM3 7EF",
    "sg:province":"Essex",
    "sg:tags":[
        "landscape",
        "contractor"
    ],
    "wof:name":"Arcadia Garden Services",
    "wof:placetype":"venue"
},
  "geometry": {"coordinates":[0.21349,51.610802],"type":"Point"}
}