{
  "type": "Feature",
  "properties": {
    "iso:country":"GB",
    "sg:address":"Lon Parcwr Industrial Estate",
    "sg:city":"Ruthin",
    "sg:classifiers":[
        {
            "category":"Manufacturing",
            "subcategory":"Building Materials",
            "type":"Manufacturing & Wholesale Goods"
        }
    ],
    "sg:phone":"+44 1824 702870",
    "sg:postcode":"LL15 1NA",
    "sg:province":"Denbighshire",
    "sg:tags":[
        "tarmac",
        "asphalt"
    ],
    "wof:name":"Robert S Hunter",
    "wof:placetype":"venue"
},
  "geometry": {"coordinates":[-3.310729,53.119884],"type":"Point"}
}