{
  "type": "Feature",
  "properties": {
    "iso:country":"GB",
    "sg:address":"Mansfield Road",
    "sg:city":"Alfreton",
    "sg:classifiers":[
        {
            "category":"Health Services",
            "subcategory":"Nursing And Care Facility",
            "type":"Services"
        }
    ],
    "sg:phone":"+44 1773 520504",
    "sg:postcode":"DE55 7JL",
    "sg:province":"Derbyshire",
    "sg:tags":[
        "home"
    ],
    "wof:name":"MILFORD CARE LTD",
    "wof:placetype":"venue"
},
  "geometry": {"coordinates":[-1.371353,53.099503],"type":"Point"}
}