{
  "type": "Feature",
  "properties": {
    "addr:full":"668 Wimborne Road, Winton Bournemouth Dorset BH9 2EG",
    "addr:housenumber":"668",
    "addr:postcode":"bh9 2eg",
    "addr:street":"Wimborne Road",
    "iso:country":"GB",
    "sg:address":"668 Wimborne Road, Winton",
    "sg:city":"Bournemouth",
    "sg:classifiers":[
        {
            "category":"Personal",
            "subcategory":"Beauty Salon",
            "type":"Services"
        },
        {
            "category":"Personal",
            "subcategory":"Barber",
            "type":"Services"
        }
    ],
    "sg:phone":"+44 1202 529430",
    "sg:postcode":"BH9 2EG",
    "sg:province":"Dorset",
    "sg:tags":[
        "unisex",
        "hairdresser"
    ],
    "wof:name":"Siam Hair Design",
    "wof:placetype":"venue"
},
  "geometry": {"coordinates":[-1.877807,50.747772],"type":"Point"}
}