{
  "type": "Feature",
  "properties": {
    "iso:country":"GB",
    "sg:address":"Teesside Retail Park, Thornaby",
    "sg:city":"Stockton-on-tees",
    "sg:classifiers":[
        {
            "category":"Food & Beverages",
            "subcategory":"Bakery",
            "type":"Retail Goods"
        }
    ],
    "sg:phone":"+44 1642 634853",
    "sg:postcode":"TS17 7BT",
    "sg:province":"Durham",
    "sg:tags":[
        "pizza"
    ],
    "wof:name":"Pizza Hut",
    "wof:placetype":"venue"
},
  "geometry": {"coordinates":[-1.277931,54.558311],"type":"Point"}
}