{
  "type": "Feature",
  "properties": {
    "iso:country":"GB",
    "sg:address":"Dowsetts La",
    "sg:city":"Billericay",
    "sg:classifiers":[
        {
            "category":"Utilities",
            "subcategory":"Telephone",
            "type":"Services"
        }
    ],
    "sg:phone":"+44 1268 711775",
    "sg:postcode":"CM11 1HX",
    "sg:province":"Essex",
    "sg:tags":[
        "telecommunication"
    ],
    "wof:name":"Complete Wiring Co The",
    "wof:placetype":"venue"
},
  "geometry": {"coordinates":[0.468747,51.650589],"type":"Point"}
}