{
  "type": "Feature",
  "properties": {
    "addr:full":"57 Fore Bondgate Bishop Auckland Durham DL14 7PE",
    "addr:housenumber":"57",
    "addr:postcode":"dl14 7pe",
    "addr:street":"Fore Bondgate;Auckland",
    "iso:country":"GB",
    "sg:address":"57 Fore Bondgate",
    "sg:city":"Bishop Auckland",
    "sg:classifiers":[
        {
            "category":"Shopping",
            "subcategory":"Comic Books",
            "type":"Retail Goods"
        }
    ],
    "sg:phone":"+44 1388 606163",
    "sg:postcode":"DL14 7PE",
    "sg:province":"Durham",
    "sg:tags":[
        "jeweller"
    ],
    "wof:name":"Classyideal Ltd.",
    "wof:placetype":"venue"
},
  "geometry": {"coordinates":[-1.6755239964,54.6655807495],"type":"Point"}
}