{
  "type": "Feature",
  "properties": {
    "addr:full":"Chilton Moor County Jmi School, Chilton Houghton-le-spring Durham DH4 6LU",
    "addr:postcode":"dh4 6lu",
    "addr:street":"Chilton Moor;Houghton-Le-Spring",
    "iso:country":"GB",
    "sg:address":"Chilton Moor County Jmi School, Chilton",
    "sg:city":"Houghton-le-spring",
    "sg:classifiers":[
        {
            "category":"Building & Trades",
            "subcategory":"Construction",
            "type":"Services"
        }
    ],
    "sg:phone":"+44 191 385 4556",
    "sg:postcode":"DH4 6LU",
    "sg:province":"Durham",
    "sg:tags":[
        "heating",
        "contractor"
    ],
    "wof:name":"Ho'ton Heating Ltd.",
    "wof:placetype":"venue"
},
  "geometry": {"coordinates":[-1.498649,54.838299],"type":"Point"}
}