{
  "type": "Feature",
  "properties": {
    "addr:full":"Crossway, Walton Presteigne Herefordshire LD8 2RB",
    "addr:postcode":"ld8 2rb",
    "addr:street":"Crossway",
    "iso:country":"GB",
    "sg:address":"Crossway, Walton",
    "sg:city":"Presteigne",
    "sg:classifiers":[
        {
            "category":"Farming",
            "subcategory":"Farm",
            "type":"Manufacturing & Wholesale Goods"
        }
    ],
    "sg:phone":"+44 1544 267329",
    "sg:postcode":"LD8 2RB",
    "sg:province":"Herefordshire",
    "sg:tags":[
        "mixed",
        "crop"
    ],
    "wof:name":"Bowen-Jones & Sons",
    "wof:placetype":"venue"
},
  "geometry": {"coordinates":[-3.004454,52.270206],"type":"Point"}
}