{
  "type": "Feature",
  "properties": {
    "addr:full":"Ravenscliffe Close Halifax West Yorkshire HX3 0RZ",
    "addr:postcode":"hx3 0rz",
    "addr:street":"Ravenscliffe Close",
    "iso:country":"GB",
    "sg:address":"Ravenscliffe Close",
    "sg:city":"Halifax",
    "sg:classifiers":[
        {
            "category":"Education",
            "subcategory":"School",
            "type":"Public Place"
        }
    ],
    "sg:phone":"+44 1422 358621",
    "sg:postcode":"HX3 0RZ",
    "sg:province":"West Yorkshire",
    "sg:tags":[
        "local",
        "authority"
    ],
    "wof:name":"Ravenscliffe High School",
    "wof:placetype":"venue"
},
  "geometry": {"coordinates":[-1.863664031,53.7020301819],"type":"Point"}
}