{
  "type": "Feature",
  "properties": {
    "iso:country":"GB",
    "sg:address":"Mepal Road, Witcham",
    "sg:city":"Ely",
    "sg:classifiers":[
        {
            "category":"Sports & Exercise",
            "subcategory":"Stables",
            "type":"Entertainment"
        }
    ],
    "sg:phone":"+44 1353 777588",
    "sg:postcode":"CB6 2LD",
    "sg:province":"Cambridgeshire",
    "sg:tags":[
        "education",
        "equestrian"
    ],
    "wof:name":"Witcham Equestrian Centre",
    "wof:placetype":"venue"
},
  "geometry": {"coordinates":[0.114191,52.404881],"type":"Point"}
}