{
  "type": "Feature",
  "properties": {
    "iso:country":"GB",
    "sg:address":"South Lodge Court, Racecourse Road",
    "sg:city":"Ayr",
    "sg:classifiers":[
        {
            "category":"Health Services",
            "subcategory":"Nursing And Care Facility",
            "type":"Services"
        },
        {
            "category":"Organizations",
            "subcategory":"Community Association",
            "type":"Services"
        }
    ],
    "sg:phone":"+44 1292 610138",
    "sg:postcode":"KA7 2TA",
    "sg:province":"South Ayrshire",
    "sg:tags":[
        "residential",
        "housing",
        "society"
    ],
    "wof:name":"HANOVER (SCOTLAND) HOUSING ASSOCIATION LTD",
    "wof:placetype":"venue"
},
  "geometry": {"coordinates":[-4.6354689598,55.4581184387],"type":"Point"}
}