{
  "type": "Feature",
  "properties": {
    "addr:full":"Unit 1 North Powrie Farm Dundee Dundee City DD4 0QQ",
    "addr:housenumber":"unit 1",
    "addr:postcode":"dd4 0qq",
    "addr:street":"North Powrie Farm",
    "iso:country":"GB",
    "sg:address":"Unit 1 North Powrie Farm",
    "sg:city":"Dundee",
    "sg:classifiers":[
        {
            "category":"Shopping",
            "subcategory":"Pets & Pet Supplies",
            "type":"Retail Goods"
        }
    ],
    "sg:phone":"+44 1382 380621",
    "sg:postcode":"DD4 0QQ",
    "sg:province":"Dundee City",
    "sg:tags":[
        "food"
    ],
    "wof:name":"Redcastle Animal Care",
    "wof:placetype":"venue"
},
  "geometry": {"coordinates":[-2.95324,56.511681],"type":"Point"}
}