{
  "type": "Feature",
  "properties": {
    "iso:country":"GB",
    "sg:address":"The Mill, Bearwalden Business Park, Royston Road",
    "sg:city":"Saffron Walden",
    "sg:classifiers":[
        {
            "category":"Communications",
            "subcategory":"Newspaper",
            "type":"Services"
        }
    ],
    "sg:phone":"+44 1799 544200",
    "sg:postcode":"CB11 4JX",
    "sg:province":"Essex",
    "sg:tags":[
        "magazine"
    ],
    "wof:name":"Archant Specialist Ltd.",
    "wof:placetype":"venue"
},
  "geometry": {"coordinates":[0.20471,52.005501],"type":"Point"}
}