{
  "type": "Feature",
  "properties": {
    "iso:country":"GB",
    "sg:address":"45 Osborne Street",
    "sg:city":"Slough",
    "sg:classifiers":[
        {
            "category":"Health Services",
            "subcategory":"Clinic",
            "type":"Services"
        }
    ],
    "sg:phone":"+44 1753 520643",
    "sg:postcode":"SL1 1TT",
    "sg:province":"Berkshire",
    "sg:tags":[
        "nh"
    ],
    "wof:name":"The Herschel Medical Practice",
    "wof:placetype":"venue"
},
  "geometry": {"coordinates":[-0.5924370289,51.5063056946],"type":"Point"}
}