{
  "type": "Feature",
  "properties": {
    "addr:full":"18 Shore Road, Aberdour Burntisland Fife KY3 0TR",
    "addr:housenumber":"18",
    "addr:postcode":"ky3 0tr",
    "addr:street":"Shore Road",
    "iso:country":"GB",
    "sg:address":"18 Shore Road, Aberdour",
    "sg:city":"Burntisland",
    "sg:classifiers":[
        {
            "category":"Personal",
            "subcategory":"Beauty Salon",
            "type":"Services"
        },
        {
            "category":"Personal",
            "subcategory":"Barber",
            "type":"Services"
        },
        {
            "category":"Professional",
            "subcategory":"Management & Consulting",
            "type":"Services"
        }
    ],
    "sg:phone":"+44 1383 860933",
    "sg:postcode":"KY3 0TR",
    "sg:province":"Fife",
    "sg:tags":[
        "unisex",
        "specialist",
        "hairdresser",
        "consultant"
    ],
    "wof:name":"Fernando's Hair & Beauty",
    "wof:placetype":"venue"
},
  "geometry": {"coordinates":[-3.30096,56.053478],"type":"Point"}
}