{
  "type": "Feature",
  "properties": {
    "iso:country":"GB",
    "sg:address":"36 Main Street, Overseal",
    "sg:city":"Swadlincote",
    "sg:classifiers":[
        {
            "category":"Home & Garden",
            "subcategory":"Garden Supply",
            "type":"Retail Goods"
        },
        {
            "category":"Building & Trades",
            "subcategory":"Construction",
            "type":"Services"
        }
    ],
    "sg:phone":"+44 1283 762469",
    "sg:postcode":"DE12 6LG",
    "sg:province":"Derbyshire",
    "sg:tags":[
        "thatching",
        "manufacturers",
        "craft",
        "ornament",
        "conservation",
        "builder"
    ],
    "sg:website":"http://www.rafflesgb.com",
    "wof:name":"David Raffle",
    "wof:placetype":"venue"
},
  "geometry": {"coordinates":[-1.592654,52.746822],"type":"Point"}
}