{
  "type": "Feature",
  "properties": {
    "iso:country":"GB",
    "sg:address":"12 Amberley Drive, Irlam",
    "sg:city":"Manchester",
    "sg:classifiers":[
        {
            "category":"Personal",
            "type":"Services"
        }
    ],
    "sg:postcode":"M44 6BG",
    "sg:province":"Greater Manchester",
    "sg:tags":[
        "slimming",
        "product"
    ],
    "wof:name":"Slimming World",
    "wof:placetype":"venue"
},
  "geometry": {"coordinates":[-2.420765,53.445179],"type":"Point"}
}