{
  "type": "Feature",
  "properties": {
    "addr:full":"Duchy House, Tavistock Road Yelverton Devon PL20 6QF",
    "addr:postcode":"pl20 6qf",
    "addr:street":"Tavistock Road",
    "iso:country":"GB",
    "sg:address":"Duchy House, Tavistock Road",
    "sg:city":"Yelverton",
    "sg:classifiers":[
        {
            "category":"Cafe",
            "type":"Food & Drink"
        }
    ],
    "sg:postcode":"PL20 6QF",
    "sg:province":"Devon",
    "sg:tags":[
        "tea",
        "room"
    ],
    "wof:name":"Duchy House Tearooms",
    "wof:placetype":"venue"
},
  "geometry": {"coordinates":[-4.0981011391,50.500038147],"type":"Point"}
}