{
  "type": "Feature",
  "properties": {
    "addr:full":"Glebe Close, St Johns Worcester Worcestershire WR2 5AX",
    "addr:postcode":"wr2 5ax",
    "addr:street":"Glebe Close",
    "iso:country":"GB",
    "sg:address":"Glebe Close, St Johns",
    "sg:city":"Worcester",
    "sg:classifiers":[
        {
            "category":"Education",
            "subcategory":"Library",
            "type":"Public Place"
        }
    ],
    "sg:phone":"+44 1905 420400",
    "sg:postcode":"WR2 5AX",
    "sg:province":"Worcestershire",
    "sg:tags":[
        "book"
    ],
    "wof:name":"St Johns Library & Information Centre",
    "wof:placetype":"venue"
},
  "geometry": {"coordinates":[-2.235779,52.188839],"type":"Point"}
}