{
  "type": "Feature",
  "properties": {
    "iso:country":"GB",
    "sg:address":"97 Dymchurch Road",
    "sg:city":"Hythe",
    "sg:classifiers":[
        {
            "category":"Retail",
            "subcategory":"Repair Shop",
            "type":"Services"
        }
    ],
    "sg:phone":"+44 1303 264949",
    "sg:postcode":"CT21 6JN",
    "sg:province":"Kent",
    "sg:tags":[
        "television",
        "good",
        "video",
        "servicing",
        "maintenance",
        "radio"
    ],
    "wof:name":"Hythe Tv Service",
    "wof:placetype":"venue"
},
  "geometry": {"coordinates":[1.073565,51.070843],"type":"Point"}
}