{
  "type": "Feature",
  "properties": {
    "iso:country":"GB",
    "sg:address":"196 Dyke Road",
    "sg:city":"Brighton",
    "sg:classifiers":[
        {
            "category":"Communications",
            "subcategory":"Film & Video Production",
            "type":"Services"
        }
    ],
    "sg:phone":"+44 1273 561900",
    "sg:postcode":"BN1 5AA",
    "sg:province":"East Sussex",
    "sg:tags":[
        "recording",
        "studio"
    ],
    "wof:name":"The Esselle Beat Co",
    "wof:placetype":"venue"
},
  "geometry": {"coordinates":[-0.1533409953,50.8373565674],"type":"Point"}
}