{
  "type": "Feature",
  "properties": {
    "iso:country":"GB",
    "sg:address":"Security House, Sandgate Industrial Estate",
    "sg:city":"Hartlepool",
    "sg:classifiers":[
        {
            "category":"Professional",
            "subcategory":"Detective & Security Services",
            "type":"Services"
        }
    ],
    "sg:phone":"+44 1429 270138",
    "sg:postcode":"TS25 1UB",
    "sg:province":"Durham",
    "wof:name":"Lion Security Services",
    "wof:placetype":"venue"
},
  "geometry": {"coordinates":[-1.201506,54.677181],"type":"Point"}
}