{
  "type": "Feature",
  "properties": {
    "iso:country":"GB",
    "sg:address":"28 Commercial Street",
    "sg:city":"Tredegar",
    "sg:classifiers":[
        {
            "category":"Fast Food",
            "type":"Food & Drink"
        }
    ],
    "sg:phone":"+44 1495 722453",
    "sg:postcode":"NP22 3DH",
    "sg:province":"Blaenau Gwent",
    "sg:tags":[
        "away",
        "take"
    ],
    "wof:name":"Chop Suey House",
    "wof:placetype":"venue"
},
  "geometry": {"coordinates":[-3.246518,51.774399],"type":"Point"}
}