{
  "type": "Feature",
  "properties": {
    "iso:country":"GB",
    "sg:address":"Main Street, Bishampton",
    "sg:city":"Pershore",
    "sg:classifiers":[
        {
            "category":"Farming",
            "subcategory":"Livestock Farm",
            "type":"Manufacturing & Wholesale Goods"
        }
    ],
    "sg:phone":"+44 1386 462384",
    "sg:postcode":"WR10 2NH",
    "sg:province":"Worcestershire",
    "sg:tags":[
        "others"
    ],
    "wof:name":"Nightingale Farm",
    "wof:placetype":"venue"
},
  "geometry": {"coordinates":[-2.0175039768,52.1601333618],"type":"Point"}
}