{
  "type": "Feature",
  "properties": {
    "addr:full":"15 Ralston Drive Kirkcaldy Fife KY2 6HX",
    "addr:housenumber":"15",
    "addr:postcode":"ky2 6hx",
    "addr:street":"Ralston Drive",
    "iso:country":"GB",
    "sg:address":"15 Ralston Drive",
    "sg:city":"Kirkcaldy",
    "sg:classifiers":[
        {
            "category":"Professional",
            "subcategory":"Management & Consulting",
            "type":"Services"
        }
    ],
    "sg:phone":"+44 1592 591535",
    "sg:postcode":"KY2 6HX",
    "sg:province":"Fife",
    "sg:tags":[
        "environmental",
        "consultant"
    ],
    "wof:name":"Fife Health & Safety Consultants",
    "wof:placetype":"venue"
},
  "geometry": {"coordinates":[-3.1791319847,56.136428833],"type":"Point"}
}