{
  "type": "Feature",
  "properties": {
    "iso:country":"GB",
    "sg:address":"143 East Parade",
    "sg:city":"Keighley",
    "sg:classifiers":[
        {
            "category":"Shopping",
            "subcategory":"Department Store",
            "type":"Retail Goods"
        }
    ],
    "sg:phone":"+44 1535 661095",
    "sg:postcode":"BD21 5HX",
    "sg:province":"West Yorkshire",
    "wof:name":"Dorothy Fowler",
    "wof:placetype":"venue"
},
  "geometry": {"coordinates":[-1.9038939476,53.867313385],"type":"Point"}
}