{
  "type": "Feature",
  "properties": {
    "addr:full":"Rear Of Lincoln Ho, Old Parkbury La, Colney St St Albans Hertfordshire AL2 2DX",
    "addr:housenumber":"rear of",
    "addr:postcode":"al2 2dx",
    "addr:street":"La Colney St",
    "iso:country":"GB",
    "sg:address":"Rear Of Lincoln Ho, Old Parkbury La, Colney St",
    "sg:city":"St Albans",
    "sg:classifiers":[
        {
            "category":"Real Estate",
            "subcategory":"Architect",
            "type":"Services"
        }
    ],
    "sg:postcode":"AL2 2DX",
    "sg:province":"Hertfordshire",
    "wof:name":"Townsend,Dave,",
    "wof:placetype":"venue"
},
  "geometry": {"coordinates":[-0.34194,51.716789],"type":"Point"}
}