{
  "type": "Feature",
  "properties": {
    "addr:full":"Radford Road, Flyford Flavell Worcester Worcestershire WR7 4DL",
    "addr:postcode":"wr7 4dl",
    "addr:street":"Radford Road",
    "iso:country":"GB",
    "sg:address":"Radford Road, Flyford Flavell",
    "sg:city":"Worcester",
    "sg:classifiers":[
        {
            "category":"Building & Trades",
            "subcategory":"Construction",
            "type":"Services"
        }
    ],
    "sg:phone":"+44 1386 462600",
    "sg:postcode":"WR7 4DL",
    "sg:province":"Worcestershire",
    "sg:tags":[
        "builder"
    ],
    "wof:name":"R J & A Davis",
    "wof:placetype":"venue"
},
  "geometry": {"coordinates":[-2.0303719044,52.1928138733],"type":"Point"}
}