{
  "type": "Feature",
  "properties": {
    "addr:full":"3/5 Bayview Road Colwyn Bay Conwy LL29 8DW",
    "addr:housenumber":"3 / 5",
    "addr:postcode":"ll29 8dw",
    "addr:street":"Bayview Road",
    "iso:country":"GB",
    "sg:address":"3/5 Bayview Road",
    "sg:city":"Colwyn Bay",
    "sg:classifiers":[
        {
            "category":"Professional",
            "subcategory":"Employment Agencies",
            "type":"Services"
        },
        {
            "category":"Health Services",
            "subcategory":"Nursing And Care Facility",
            "type":"Services"
        }
    ],
    "sg:phone":"+44 1492 534433",
    "sg:postcode":"LL29 8DW",
    "sg:province":"Conwy",
    "sg:tags":[
        "consultant"
    ],
    "wof:name":"Jemini Nursing Agency",
    "wof:placetype":"venue"
},
  "geometry": {"coordinates":[-3.725035,53.294605],"type":"Point"}
}