{
  "type": "Feature",
  "properties": {
    "addr:full":"145 South Coast Road Peacehaven East Sussex BN10 8NN",
    "addr:housenumber":"145",
    "addr:postcode":"bn10 8nn",
    "addr:street":"South Coast Road Peacehaven",
    "iso:country":"GB",
    "sg:address":"145 South Coast Road",
    "sg:city":"Peacehaven",
    "sg:classifiers":[
        {
            "category":"Building & Trades",
            "subcategory":"Plumbing",
            "type":"Services"
        }
    ],
    "sg:phone":"+44 1273 514041",
    "sg:postcode":"BN10 8NN",
    "sg:province":"East Sussex",
    "sg:tags":[
        "central",
        "heating"
    ],
    "wof:name":"Giles & Ince",
    "wof:placetype":"venue"
},
  "geometry": {"coordinates":[0.0069289999,50.7899971008],"type":"Point"}
}