{
  "type": "Feature",
  "properties": {
    "iso:country":"GB",
    "sg:address":"Swarcliffe Hall, Birstwith",
    "sg:city":"Harrogate",
    "sg:classifiers":[
        {
            "category":"Education",
            "subcategory":"School",
            "type":"Public Place"
        }
    ],
    "sg:phone":"+44 1423 771029",
    "sg:postcode":"HG3 2JG",
    "sg:province":"North Yorkshire",
    "sg:tags":[
        "independent",
        "preparatory",
        "local",
        "authority"
    ],
    "wof:name":"BELMONT-BIRKLANDS SCHOOL TRUST LTD",
    "wof:placetype":"venue"
},
  "geometry": {"coordinates":[-1.635233,54.031197],"type":"Point"}
}