{
  "type": "Feature",
  "properties": {
    "iso:country":"GB",
    "sg:address":"49 Thomas Street",
    "sg:city":"Holyhead",
    "sg:classifiers":[
        {
            "category":"Food & Beverages",
            "subcategory":"Candy",
            "type":"Retail Goods"
        }
    ],
    "sg:phone":"+44 1407 762694",
    "sg:postcode":"LL65 1RS",
    "sg:province":"Isle of Anglesey",
    "sg:tags":[
        "confectioner"
    ],
    "wof:name":"British Stores",
    "wof:placetype":"venue"
},
  "geometry": {"coordinates":[-4.6363801956,53.3107566833],"type":"Point"}
}