{
  "type": "Feature",
  "properties": {
    "addr:full":"International House, Fryers Rd Walsall Staffordshire WS3 2XJ",
    "addr:postcode":"ws3 2xj",
    "addr:street":"Fryers Rd",
    "iso:country":"GB",
    "sg:address":"International House, Fryers Rd",
    "sg:city":"Walsall",
    "sg:classifiers":[
        {
            "category":"Professional",
            "subcategory":"Computer Services",
            "type":"Services"
        }
    ],
    "sg:phone":"+44 1922 712333",
    "sg:postcode":"WS3 2XJ",
    "sg:province":"Staffordshire",
    "sg:tags":[
        "system",
        "software"
    ],
    "wof:name":"Execom",
    "wof:placetype":"venue"
},
  "geometry": {"coordinates":[-2.0091888905,52.6097297668],"type":"Point"}
}