{
  "type": "Feature",
  "properties": {
    "addr:full":"196 Newark Avenue Peterborough Cambridgeshire PE1 4NP",
    "addr:housenumber":"196",
    "addr:postcode":"pe1 4np",
    "addr:street":"Newark Avenue",
    "iso:country":"GB",
    "sg:address":"196 Newark Avenue",
    "sg:city":"Peterborough",
    "sg:classifiers":[
        {
            "category":"Shopping",
            "subcategory":"Bicycles & Sporting Goods",
            "type":"Retail Goods"
        },
        {
            "category":"Recreation",
            "subcategory":"Fishing",
            "type":"Entertainment"
        }
    ],
    "sg:phone":"+44 1733 566466",
    "sg:postcode":"PE1 4NP",
    "sg:province":"Cambridgeshire",
    "sg:tags":[
        "equipment",
        "angling"
    ],
    "wof:name":"Webbs",
    "wof:placetype":"venue"
},
  "geometry": {"coordinates":[-0.23373,52.592838],"type":"Point"}
}