{
  "type": "Feature",
  "properties": {
    "addr:full":"Co Clev/ans Road Bridge Of Weir Inverclyde PA11 3HP",
    "addr:postcode":"pa11 3hp",
    "addr:street":"Ans Road",
    "iso:country":"GB",
    "sg:address":"Co Clev/ans Road",
    "sg:city":"Bridge Of Weir",
    "sg:classifiers":[
        {
            "category":"Travel",
            "subcategory":"Hotels & Motels",
            "type":"Entertainment"
        }
    ],
    "sg:phone":"+44 1505 614763",
    "sg:postcode":"PA11 3HP",
    "sg:province":"Inverclyde",
    "sg:tags":[
        "self",
        "catering"
    ],
    "wof:name":"Allscot Securities Ltd.",
    "wof:placetype":"venue"
},
  "geometry": {"coordinates":[-4.577569,55.856491],"type":"Point"}
}