{
  "type": "Feature",
  "properties": {
    "addr:full":"19 New Road Chippenham Wiltshire SN15 1HJ",
    "addr:housenumber":"19",
    "addr:postcode":"sn15 1hj",
    "addr:street":"New Road",
    "iso:country":"GB",
    "sg:address":"19 New Road",
    "sg:city":"Chippenham",
    "sg:classifiers":[
        {
            "category":"Recreation",
            "subcategory":"Fishing",
            "type":"Entertainment"
        }
    ],
    "sg:phone":"+44 1249 659210",
    "sg:postcode":"SN15 1HJ",
    "sg:province":"Wiltshire",
    "sg:tags":[
        "angling"
    ],
    "wof:name":"Premier Angling",
    "wof:placetype":"venue"
},
  "geometry": {"coordinates":[-2.117933,51.462612],"type":"Point"}
}