{
  "type": "Feature",
  "properties": {
    "addr:full":"38 The Broadway London Greater London SW19 1RQ",
    "addr:housenumber":"38",
    "addr:postcode":"sw19 1rq",
    "addr:street":"The Broadway",
    "iso:country":"GB",
    "sg:address":"38 The Broadway",
    "sg:city":"London",
    "sg:classifiers":[
        {
            "category":"Health Services",
            "subcategory":"Optometrist",
            "type":"Services"
        }
    ],
    "sg:phone":"+44 20 8542 4434",
    "sg:postcode":"SW19 1RQ",
    "sg:province":"Greater London",
    "sg:tags":[
        "optician"
    ],
    "wof:name":"Wimbledon Broadway Specsavers Ltd.",
    "wof:placetype":"venue"
},
  "geometry": {"coordinates":[-0.202698,51.419823],"type":"Point"}
}