{
  "type": "Feature",
  "properties": {
    "addr:full":"4 Longmoor Road Sutton Coldfield West Midlands B73 6UB",
    "addr:housenumber":"4",
    "addr:postcode":"b73 6ub",
    "addr:street":"Longmoor Road",
    "iso:country":"GB",
    "sg:address":"4 Longmoor Road",
    "sg:city":"Sutton Coldfield",
    "sg:classifiers":[
        {
            "category":"Building & Trades",
            "subcategory":"Construction",
            "type":"Services"
        }
    ],
    "sg:postcode":"B73 6UB",
    "sg:province":"West Midlands",
    "sg:tags":[
        "decorator",
        "painter"
    ],
    "wof:name":"Philco",
    "wof:placetype":"venue"
},
  "geometry": {"coordinates":[-1.87266,52.557114],"type":"Point"}
}