{
  "type": "Feature",
  "properties": {
    "addr:full":"14 St Martins Crescent, Scawby Brigg Lincolnshire DN20 9BQ",
    "addr:housenumber":"14",
    "addr:postcode":"dn20 9bq",
    "addr:street":"St Martins Crescent",
    "iso:country":"GB",
    "sg:address":"14 St Martins Crescent, Scawby",
    "sg:city":"Brigg",
    "sg:classifiers":[
        {
            "category":"Professional",
            "subcategory":"Accounting & Tax Preparation",
            "type":"Services"
        }
    ],
    "sg:phone":"+44 1652 654469",
    "sg:postcode":"DN20 9BQ",
    "sg:province":"Lincolnshire",
    "sg:tags":[
        "accountant"
    ],
    "wof:name":"J D Foster & Co",
    "wof:placetype":"venue"
},
  "geometry": {"coordinates":[-0.5442119837,53.5370254517],"type":"Point"}
}