{
  "type": "Feature",
  "properties": {
    "iso:country":"GB",
    "sg:address":"Berry Farm, Berry Pomeroy",
    "sg:city":"Totnes",
    "sg:classifiers":[
        {
            "category":"Farming",
            "subcategory":"Livestock Farm",
            "type":"Manufacturing & Wholesale Goods"
        }
    ],
    "sg:postcode":"TQ9 6LG",
    "sg:province":"Devon",
    "sg:tags":[
        "others"
    ],
    "wof:name":"Nicholls J R & Son",
    "wof:placetype":"venue"
},
  "geometry": {"coordinates":[-3.6518189907,50.4375762939],"type":"Point"}
}