{
  "type": "Feature",
  "properties": {
    "addr:full":"160 St Enochs Road Bradford West Yorkshire BD6 3BU",
    "addr:housenumber":"160",
    "addr:postcode":"bd6 3bu",
    "addr:street":"St Enochs Road",
    "iso:country":"GB",
    "sg:address":"160 St Enochs Road",
    "sg:city":"Bradford",
    "sg:classifiers":[
        {
            "category":"Personal",
            "subcategory":"Beauty Salon",
            "type":"Services"
        },
        {
            "category":"Personal",
            "subcategory":"Barber",
            "type":"Services"
        }
    ],
    "sg:phone":"+44 1274 602389",
    "sg:postcode":"BD6 3BU",
    "sg:province":"West Yorkshire",
    "sg:tags":[
        "unisex",
        "hairdresser"
    ],
    "wof:name":"Solitaire",
    "wof:placetype":"venue"
},
  "geometry": {"coordinates":[-1.7800660133,53.7695007324],"type":"Point"}
}