{
  "type": "Feature",
  "properties": {
    "addr:full":"122 Aldborough Road South Ilford Essex IG3 8EZ",
    "addr:housenumber":"122",
    "addr:postcode":"ig3 8ez",
    "addr:street":"Aldborough Road South",
    "iso:country":"GB",
    "sg:address":"122 Aldborough Road South",
    "sg:city":"Ilford",
    "sg:classifiers":[
        {
            "category":"Shopping",
            "subcategory":"Pets & Pet Supplies",
            "type":"Retail Goods"
        }
    ],
    "sg:postcode":"IG3 8EZ",
    "sg:province":"Essex",
    "wof:name":"Pets Pantry",
    "wof:placetype":"venue"
},
  "geometry": {"coordinates":[0.0959400013,51.5715713501],"type":"Point"}
}