{
  "type": "Feature",
  "properties": {
    "addr:full":"117 Parchmore Road Thornton Heath Surrey CR7 8LZ",
    "addr:housenumber":"117",
    "addr:postcode":"cr7 8lz",
    "addr:street":"Parchmore Road",
    "iso:country":"GB",
    "sg:address":"117 Parchmore Road",
    "sg:city":"Thornton Heath",
    "sg:classifiers":[
        {
            "category":"Personal",
            "subcategory":"Beauty Salon",
            "type":"Services"
        }
    ],
    "sg:phone":"+44 20 8771 9849",
    "sg:postcode":"CR7 8LZ",
    "sg:province":"Surrey",
    "sg:tags":[
        "lady",
        "hairdresser"
    ],
    "wof:name":"Marion's",
    "wof:placetype":"venue"
},
  "geometry": {"coordinates":[-0.101697,51.403702],"type":"Point"}
}