{
  "type": "Feature",
  "properties": {
    "iso:country":"GB",
    "sg:address":"70 Station Lane",
    "sg:city":"Hornchurch",
    "sg:classifiers":[
        {
            "category":"Health Services",
            "subcategory":"Dentist",
            "type":"Services"
        }
    ],
    "sg:phone":"+44 1708 442679",
    "sg:postcode":"RM12 6NA",
    "sg:province":"Essex",
    "wof:name":"Yogeshroy D Patel",
    "wof:placetype":"venue"
},
  "geometry": {"coordinates":[0.220325,51.559483],"type":"Point"}
}