{
  "type": "Feature",
  "properties": {
    "iso:country":"GB",
    "sg:address":"Quarry Road",
    "sg:city":"Tunbridge Wells",
    "sg:classifiers":[
        {
            "category":"Food & Beverages",
            "subcategory":"Candy",
            "type":"Retail Goods"
        }
    ],
    "sg:phone":"+44 1892 536633",
    "sg:postcode":"TN1 2EY",
    "sg:province":"Kent",
    "sg:tags":[
        "confectionery"
    ],
    "wof:name":"Charbonnel et Walker Ltd.",
    "wof:placetype":"venue"
},
  "geometry": {"coordinates":[0.270848006,51.1402893066],"type":"Point"}
}