{
  "type": "Feature",
  "properties": {
    "addr:full":"126 Park Rd Treorchy Rhondda, Cynon, Taff CF42 6LA",
    "addr:housenumber":"126",
    "addr:postcode":"cf42 6la",
    "addr:street":"Park Rd;Cynon Taff",
    "iso:country":"GB",
    "sg:address":"126 Park Rd",
    "sg:city":"Treorchy",
    "sg:classifiers":[
        {
            "category":"Professional",
            "subcategory":"Engineering",
            "type":"Services"
        },
        {
            "category":"Building & Trades",
            "subcategory":"Electrical",
            "type":"Services"
        }
    ],
    "sg:phone":"+44 1443 775655",
    "sg:postcode":"CF42 6LA",
    "sg:province":"Rhondda, Cynon, Taff",
    "sg:tags":[
        "engineer",
        "electrician",
        "contractor"
    ],
    "wof:name":"Gareth Pugh",
    "wof:placetype":"venue"
},
  "geometry": {"coordinates":[-3.51793,51.653389],"type":"Point"}
}