{
  "type": "Feature",
  "properties": {
    "addr:full":"9a St Johns's Hill Shrewsbury Shropshire SY1 1JD",
    "addr:housenumber":"9a",
    "addr:postcode":"sy1 1jd",
    "addr:street":"St Johns'S Hill",
    "iso:country":"GB",
    "sg:address":"9a St Johns's Hill",
    "sg:city":"Shrewsbury",
    "sg:classifiers":[
        {
            "category":"Professional",
            "subcategory":"Engineering",
            "type":"Services"
        }
    ],
    "sg:phone":"+44 1743 350893",
    "sg:postcode":"SY1 1JD",
    "sg:province":"Shropshire",
    "sg:tags":[
        "engineer",
        "structural"
    ],
    "wof:name":"Johnson Bob Consulting Structural Engineer",
    "wof:placetype":"venue"
},
  "geometry": {"coordinates":[-2.7563900948,52.7073783875],"type":"Point"}
}