{
  "type": "Feature",
  "properties": {
    "addr:full":"P O Box 626, Carlton Bedford Bedfordshire MK43 7ZR",
    "addr:housenumber":"626",
    "addr:postcode":"mk43 7zr",
    "addr:street":"P O Box",
    "iso:country":"GB",
    "sg:address":"P O Box 626, Carlton",
    "sg:city":"Bedford",
    "sg:classifiers":[
        {
            "category":"Professional",
            "subcategory":"Management & Consulting",
            "type":"Services"
        }
    ],
    "sg:postcode":"MK43 7ZR",
    "sg:province":"Bedfordshire",
    "sg:tags":[
        "marketing",
        "consultant"
    ],
    "wof:name":"Anglo German Marketing",
    "wof:placetype":"venue"
},
  "geometry": {"coordinates":[-0.5553190112,52.1878395081],"type":"Point"}
}