{
  "type": "Feature",
  "properties": {
    "addr:full":"7 Naseby Rd Solihull West Midlands B91 2DR",
    "addr:housenumber":"7",
    "addr:postcode":"b91 2dr",
    "addr:street":"Naseby Rd",
    "iso:country":"GB",
    "sg:address":"7 Naseby Rd",
    "sg:city":"Solihull",
    "sg:classifiers":[
        {
            "category":"Professional",
            "type":"Services"
        }
    ],
    "sg:phone":"+44 121 705 0577",
    "sg:postcode":"B91 2DR",
    "sg:province":"West Midlands",
    "sg:tags":[
        "caterer"
    ],
    "wof:name":"Lyndon Caterers",
    "wof:placetype":"venue"
},
  "geometry": {"coordinates":[-1.784035,52.422119],"type":"Point"}
}