{
  "type": "Feature",
  "properties": {
    "iso:country":"GB",
    "sg:address":"Cae Poeth, Forge",
    "sg:city":"Machynlleth",
    "sg:classifiers":[
        {
            "category":"Wholesale",
            "subcategory":"Scrap",
            "type":"Manufacturing & Wholesale Goods"
        }
    ],
    "sg:phone":"+44 1654 702465",
    "sg:postcode":"SY20 8RP",
    "sg:province":"Ceredigion",
    "sg:tags":[
        "car",
        "breaker",
        "dismantlers"
    ],
    "wof:name":"Machynlleth Car Breakers",
    "wof:placetype":"venue"
},
  "geometry": {"coordinates":[-3.8467230797,52.5909614563],"type":"Point"}
}