{
  "type": "Feature",
  "properties": {
    "iso:country":"GB",
    "sg:address":"126 Greys Rd",
    "sg:city":"Henley On Thames",
    "sg:classifiers":[
        {
            "category":"Fast Food",
            "type":"Food & Drink"
        }
    ],
    "sg:phone":"+44 1491 413883",
    "sg:postcode":"RG9 1QW",
    "sg:province":"Berkshire",
    "sg:tags":[
        "away",
        "take"
    ],
    "wof:name":"Classic Stir Fry",
    "wof:placetype":"venue"
},
  "geometry": {"coordinates":[-0.914516,51.529469],"type":"Point"}
}