{
  "type": "Feature",
  "properties": {
    "iso:country":"GB",
    "sg:address":"Bus Station, Royal Avenue",
    "sg:city":"Exmouth",
    "sg:classifiers":[
        {
            "category":"Bus Charters",
            "type":"Transportation"
        }
    ],
    "sg:phone":"+44 1395 272395",
    "sg:postcode":"EX8 1EN",
    "sg:province":"Devon",
    "sg:tags":[
        "coach"
    ],
    "wof:name":"Stagecoach Devon",
    "wof:placetype":"venue"
},
  "geometry": {"coordinates":[-3.413289,50.619415],"type":"Point"}
}