{
  "type": "Feature",
  "properties": {
    "addr:full":"The Grove Robertsbridge East Sussex TN32 5AP",
    "addr:postcode":"tn32 5ap",
    "iso:country":"GB",
    "sg:address":"The Grove",
    "sg:city":"Robertsbridge",
    "sg:classifiers":[
        {
            "category":"Community Center",
            "subcategory":"Youth",
            "type":"Public Place"
        }
    ],
    "sg:phone":"+44 1580 880206",
    "sg:postcode":"TN32 5AP",
    "sg:province":"East Sussex",
    "sg:tags":[
        "organisation",
        "centre"
    ],
    "wof:name":"Robertsbridge Youth Centre",
    "wof:placetype":"venue"
},
  "geometry": {"coordinates":[0.4744699895,50.9856491089],"type":"Point"}
}