{
  "type": "Feature",
  "properties": {
    "addr:full":"6-8 St Lukes Road Cheltenham Gloucestershire GL53 7JH",
    "addr:housenumber":"6-8",
    "addr:postcode":"gl53 7jh",
    "addr:street":"St Lukes Road",
    "iso:country":"GB",
    "sg:address":"6-8 St Lukes Road",
    "sg:city":"Cheltenham",
    "sg:classifiers":[
        {
            "category":"Retail",
            "subcategory":"Auto Repair",
            "type":"Services"
        }
    ],
    "sg:postcode":"GL53 7JH",
    "sg:province":"Gloucestershire",
    "sg:tags":[
        "modification",
        "garage"
    ],
    "wof:name":"Russ Ward Cars",
    "wof:placetype":"venue"
},
  "geometry": {"coordinates":[-2.074629,51.895405],"type":"Point"}
}