{
  "type": "Feature",
  "properties": {
    "addr:full":"Queenslie Indstl Est Glasgow Glasgow City G33 4DR",
    "addr:postcode":"g33 4dr",
    "iso:country":"GB",
    "sg:address":"Queenslie Indstl Est",
    "sg:city":"Glasgow",
    "sg:classifiers":[
        {
            "category":"Building & Trades",
            "subcategory":"Plumbing",
            "type":"Services"
        }
    ],
    "sg:postcode":"G33 4DR",
    "sg:province":"Glasgow City",
    "sg:tags":[
        "heating"
    ],
    "wof:name":"Craig & Duncan Ltd",
    "wof:placetype":"venue"
},
  "geometry": {"coordinates":[-4.138294,55.865555],"type":"Point"}
}