{
  "type": "Feature",
  "properties": {
    "iso:country":"GB",
    "sg:address":"Ivy Cottage 82 Grange Rd",
    "sg:city":"Billericay",
    "sg:classifiers":[
        {
            "category":"Building & Trades",
            "subcategory":"Construction",
            "type":"Services"
        }
    ],
    "sg:phone":"+44 1277 623162",
    "sg:postcode":"CM11 2RL",
    "sg:province":"Essex",
    "sg:tags":[
        "glass",
        "replacement"
    ],
    "wof:name":"A Billericay Glazing Service",
    "wof:placetype":"venue"
},
  "geometry": {"coordinates":[0.43265,51.61108],"type":"Point"}
}