{
  "type": "Feature",
  "properties": {
    "addr:full":"Unit 5a Haywood Industrial Estate, Northview, Staple Hill Bristol City of Bristol BS16 4NY",
    "addr:housenumber":"unit 5a;estate",
    "addr:postcode":"bs16 4ny",
    "iso:country":"GB",
    "sg:address":"Unit 5a Haywood Industrial Estate, Northview, Staple Hill",
    "sg:city":"Bristol",
    "sg:classifiers":[
        {
            "category":"Parking",
            "type":"Transportation"
        }
    ],
    "sg:phone":"+44 117 956 8675",
    "sg:postcode":"BS16 4NY",
    "sg:province":"City of Bristol",
    "sg:tags":[
        "car",
        "valet"
    ],
    "wof:name":"Shop & Shine",
    "wof:placetype":"venue"
},
  "geometry": {"coordinates":[-2.591429,51.453667],"type":"Point"}
}