{
  "type": "Feature",
  "properties": {
    "addr:full":"36 Park View Whitley Bay Northumberland NE26 2TH",
    "addr:housenumber":"36",
    "addr:postcode":"ne26 2th",
    "addr:street":"Park View",
    "iso:country":"GB",
    "sg:address":"36 Park View",
    "sg:city":"Whitley Bay",
    "sg:classifiers":[
        {
            "category":"Shopping",
            "subcategory":"Clothing, Apparel, & Fashions",
            "type":"Retail Goods"
        }
    ],
    "sg:phone":"+44 191 251 0963",
    "sg:postcode":"NE26 2TH",
    "sg:province":"Northumberland",
    "sg:tags":[
        "shop"
    ],
    "wof:name":"Gabrielle",
    "wof:placetype":"venue"
},
  "geometry": {"coordinates":[-1.4484100342,55.042137146],"type":"Point"}
}