{
  "type": "Feature",
  "properties": {
    "addr:full":"Riverside House, Milverton Hill Leamington Spa Warwickshire CV32 5HZ",
    "addr:postcode":"cv32 5hz",
    "addr:street":"Milverton Hill",
    "iso:country":"GB",
    "sg:address":"Riverside House, Milverton Hill",
    "sg:city":"Leamington Spa",
    "sg:classifiers":[
        {
            "category":"Government",
            "subcategory":"Office",
            "type":"Public Place"
        }
    ],
    "sg:postcode":"CV32 5HZ",
    "sg:province":"Warwickshire",
    "sg:tags":[
        "local"
    ],
    "wof:name":"Warwick District Council",
    "wof:placetype":"venue"
},
  "geometry": {"coordinates":[-1.5432280302,52.2897567749],"type":"Point"}
}