{
  "type": "Feature",
  "properties": {
    "iso:country":"GB",
    "sg:address":"15 Buckden Close, Woodley",
    "sg:city":"Reading",
    "sg:classifiers":[
        {
            "category":"Home & Garden",
            "subcategory":"Carpets & Floor Coverings",
            "type":"Retail Goods"
        }
    ],
    "sg:postcode":"RG5 4HB",
    "sg:province":"Berkshire",
    "sg:tags":[
        "carpets",
        "rug",
        "matting"
    ],
    "wof:name":"Floor to Door Discount Carpets",
    "wof:placetype":"venue"
},
  "geometry": {"coordinates":[-0.889588,51.448814],"type":"Point"}
}