{
  "type": "Feature",
  "properties": {
    "iso:country":"GB",
    "sg:address":"2 Sutton Farm Cottages, Sutton Mallet",
    "sg:city":"Bridgwater",
    "sg:classifiers":[
        {
            "category":"Building & Trades",
            "subcategory":"Plumbing",
            "type":"Services"
        }
    ],
    "sg:postcode":"TA7 9AW",
    "sg:province":"Somerset",
    "sg:tags":[
        "heating"
    ],
    "wof:name":"Adrian P Davis",
    "wof:placetype":"venue"
},
  "geometry": {"coordinates":[-2.89358,51.129978],"type":"Point"}
}