{
  "type": "Feature",
  "properties": {
    "iso:country":"GB",
    "sg:address":"Redbourne House, 24 Broom Road",
    "sg:city":"Rotherham",
    "sg:classifiers":[
        {
            "category":"Health Services",
            "subcategory":"Dentist",
            "type":"Services"
        }
    ],
    "sg:phone":"+44 1709 363661",
    "sg:postcode":"S60 2TA",
    "sg:province":"South Yorkshire",
    "wof:name":"M H  Walker",
    "wof:placetype":"venue"
},
  "geometry": {"coordinates":[-1.343653,53.425087],"type":"Point"}
}