{
  "type": "Feature",
  "properties": {
    "addr:full":"20a Ironmarket Newcastle Staffordshire ST5 1RF",
    "addr:housenumber":"20a",
    "addr:postcode":"st5 1rf",
    "addr:street":"Ironmarket",
    "iso:country":"GB",
    "sg:address":"20a Ironmarket",
    "sg:city":"Newcastle",
    "sg:classifiers":[
        {
            "category":"Fast Food",
            "type":"Food & Drink"
        },
        {
            "category":"Restaurant",
            "type":"Food & Drink"
        }
    ],
    "sg:postcode":"ST5 1RF",
    "sg:province":"Staffordshire",
    "sg:tags":[
        "away",
        "take"
    ],
    "wof:name":"Rumours Restaurant",
    "wof:placetype":"venue"
},
  "geometry": {"coordinates":[-2.2266600132,53.0119361877],"type":"Point"}
}