{
  "type": "Feature",
  "properties": {
    "iso:country":"GB",
    "sg:address":"62 Masters Lane",
    "sg:city":"Halesowen",
    "sg:classifiers":[
        {
            "category":"Freight",
            "type":"Transportation"
        }
    ],
    "sg:phone":"+44 121 559 3342",
    "sg:postcode":"B62 9HL",
    "sg:province":"West Midlands",
    "sg:tags":[
        "haulage",
        "transport",
        "road"
    ],
    "wof:name":"Rayven Transport",
    "wof:placetype":"venue"
},
  "geometry": {"coordinates":[-2.0273220539,52.4709205627],"type":"Point"}
}