{
  "type": "Feature",
  "properties": {
    "addr:full":"31 Looe Street Plymouth Devon PL4 0EA",
    "addr:housenumber":"31",
    "addr:postcode":"pl4 0ea",
    "addr:street":"Looe Street",
    "iso:country":"GB",
    "sg:address":"31 Looe Street",
    "sg:city":"Plymouth",
    "sg:classifiers":[
        {
            "category":"Bars & Pubs",
            "type":"Food & Drink"
        }
    ],
    "sg:postcode":"PL4 0EA",
    "sg:province":"Devon",
    "sg:tags":[
        "pubs",
        "inn"
    ],
    "wof:name":"The Minerva Inn",
    "wof:placetype":"venue"
},
  "geometry": {"coordinates":[-4.1366429329,50.3695106506],"type":"Point"}
}