{
  "type": "Feature",
  "properties": {
    "iso:country":"GB",
    "sg:address":"211-213 London Road",
    "sg:city":"Greenhithe",
    "sg:classifiers":[
        {
            "category":"Shopping",
            "subcategory":"Computers & Home Electronics",
            "type":"Retail Goods"
        }
    ],
    "sg:phone":"+44 1322 271171",
    "sg:postcode":"DA9 9DQ",
    "sg:province":"Kent",
    "sg:tags":[
        "electrical"
    ],
    "wof:name":"Gurney & White Ltd.",
    "wof:placetype":"venue"
},
  "geometry": {"coordinates":[0.2588579953,51.445350647],"type":"Point"}
}