{
  "type": "Feature",
  "properties": {
    "addr:full":"Park Road, Boxmoor Hemel Hempstead Hertfordshire HP1 1JT",
    "addr:postcode":"hp1 1jt",
    "addr:street":"Park Road;Hempstead",
    "iso:country":"GB",
    "sg:address":"Park Road, Boxmoor",
    "sg:city":"Hemel Hempstead",
    "sg:classifiers":[
        {
            "category":"Farming",
            "subcategory":"Nursery",
            "type":"Manufacturing & Wholesale Goods"
        }
    ],
    "sg:phone":"+44 1442 236506",
    "sg:postcode":"HP1 1JT",
    "sg:province":"Hertfordshire",
    "sg:tags":[
        "creche"
    ],
    "wof:name":"Lime Grove Day Nursery",
    "wof:placetype":"venue"
},
  "geometry": {"coordinates":[-0.4765290022,51.7479248047],"type":"Point"}
}