{
  "type": "Feature",
  "properties": {
    "iso:country":"GB",
    "sg:address":"223a Horsley Road",
    "sg:city":"Washington",
    "sg:classifiers":[
        {
            "category":"Food & Beverages",
            "subcategory":"Groceries & Convenience Stores",
            "type":"Retail Goods"
        }
    ],
    "sg:phone":"+44 191 416 1195",
    "sg:postcode":"NE38 8HW",
    "sg:province":"Durham",
    "wof:name":"Maughans Convenience Store",
    "wof:placetype":"venue"
},
  "geometry": {"coordinates":[-1.502571,54.899189],"type":"Point"}
}