{
  "type": "Feature",
  "properties": {
    "addr:full":"Henry Street Chesterfield Derbyshire S41 9BT",
    "addr:postcode":"s41 9bt",
    "addr:street":"Henry Street",
    "iso:country":"GB",
    "sg:address":"Henry Street",
    "sg:city":"Chesterfield",
    "sg:classifiers":[
        {
            "category":"Military Area",
            "subcategory":"Air Force Base",
            "type":"Public Place"
        }
    ],
    "sg:postcode":"S41 9BT",
    "sg:province":"Derbyshire",
    "sg:tags":[
        "taxi",
        "hire",
        "private"
    ],
    "wof:name":"Colin's Taxis",
    "wof:placetype":"venue"
},
  "geometry": {"coordinates":[-1.4215240479,53.2579612732],"type":"Point"}
}