{
  "type": "Feature",
  "properties": {
    "iso:country":"GB",
    "sg:address":"The Guild",
    "sg:city":"Chipping Campden",
    "sg:classifiers":[
        {
            "category":"Professional",
            "subcategory":"Printing & Photocopies",
            "type":"Services"
        }
    ],
    "sg:phone":"+44 1386 841186",
    "sg:postcode":"GL55 6DS",
    "sg:province":"Gloucestershire",
    "sg:tags":[
        "printer"
    ],
    "wof:name":"Clouds Hill Printers",
    "wof:placetype":"venue"
},
  "geometry": {"coordinates":[-1.779454,52.051388],"type":"Point"}
}