{
  "type": "Feature",
  "properties": {
    "iso:country":"GB",
    "sg:address":"19a Greengate Street",
    "sg:city":"Stafford",
    "sg:classifiers":[
        {
            "category":"Shopping",
            "subcategory":"Crafts & Fabrics",
            "type":"Retail Goods"
        }
    ],
    "sg:phone":"+44 1785 212953",
    "sg:postcode":"ST16 2HS",
    "sg:province":"Staffordshire",
    "sg:tags":[
        "material",
        "art"
    ],
    "wof:name":"The Paper House",
    "wof:placetype":"venue"
},
  "geometry": {"coordinates":[-2.1163949966,52.8057060242],"type":"Point"}
}