{
  "type": "Feature",
  "properties": {
    "iso:country":"GB",
    "sg:address":"Unit 5, Radfords Field Indstl Est, Maesbury Rd",
    "sg:city":"Oswestry",
    "sg:classifiers":[
        {
            "category":"Manufacturing",
            "subcategory":"Chemicals & Compounds",
            "type":"Manufacturing & Wholesale Goods"
        }
    ],
    "sg:phone":"+44 1691 657702",
    "sg:postcode":"SY10 8HA",
    "sg:province":"Shropshire",
    "wof:name":"Chemiplas Ltd",
    "wof:placetype":"venue"
},
  "geometry": {"coordinates":[-3.04466,52.849857],"type":"Point"}
}