{
  "type": "Feature",
  "properties": {
    "iso:country":"GB",
    "sg:address":"14 Monks Crescent",
    "sg:city":"Leicester",
    "sg:classifiers":[
        {
            "category":"Professional",
            "subcategory":"Engineering",
            "type":"Services"
        }
    ],
    "sg:phone":"+44 116 235 8411",
    "sg:postcode":"LE4 2WA",
    "sg:province":"Leicestershire",
    "sg:tags":[
        "ge",
        "engineer",
        "mechanical"
    ],
    "wof:name":"J & A Engineering",
    "wof:placetype":"venue"
},
  "geometry": {"coordinates":[-1.150649,52.683609],"type":"Point"}
}