{
  "type": "Feature",
  "properties": {
    "addr:full":"Queensway Business Centre, Dunlop Way Scunthorpe Lincolnshire DN16 3RT",
    "addr:postcode":"dn16 3rt",
    "addr:street":"Queensway;Dunlop Way",
    "iso:country":"GB",
    "sg:address":"Queensway Business Centre, Dunlop Way",
    "sg:city":"Scunthorpe",
    "sg:classifiers":[
        {
            "category":"Building & Trades",
            "subcategory":"Construction",
            "type":"Services"
        }
    ],
    "sg:postcode":"DN16 3RT",
    "sg:province":"Lincolnshire",
    "sg:tags":[
        "builder"
    ],
    "wof:name":"D A Able & Associates",
    "wof:placetype":"venue"
},
  "geometry": {"coordinates":[-0.6198400259,53.5717811584],"type":"Point"}
}