{
  "type": "Feature",
  "properties": {
    "addr:full":"98 Harley Street London Greater London W1G 7HZ",
    "addr:housenumber":"98",
    "addr:postcode":"w1g 7hz",
    "addr:street":"Harley Street",
    "iso:country":"GB",
    "sg:address":"98 Harley Street",
    "sg:city":"London",
    "sg:classifiers":[
        {
            "category":"Health Services",
            "subcategory":"Dentist",
            "type":"Services"
        }
    ],
    "sg:phone":"+44 20 7935 1794",
    "sg:postcode":"W1G 7HZ",
    "sg:province":"Greater London",
    "sg:tags":[
        "technician",
        "instrument",
        "dental"
    ],
    "wof:name":"John C Gordon Dental Laboratory",
    "wof:placetype":"venue"
},
  "geometry": {"coordinates":[-0.1476790011,51.5205802917],"type":"Point"}
}