{
  "type": "Feature",
  "properties": {
    "iso:country":"GB",
    "sg:address":"A Proctor Group Industrial Estat, Dunkeld Road",
    "sg:city":"Blairgowrie",
    "sg:classifiers":[
        {
            "category":"Shopping",
            "subcategory":"Hobbies, Toys, & Games",
            "type":"Retail Goods"
        },
        {
            "category":"Home & Garden",
            "subcategory":"Building Materials",
            "type":"Retail Goods"
        }
    ],
    "sg:phone":"+44 1250 876532",
    "sg:postcode":"PH10 6RT",
    "sg:province":"Perth and Kinross",
    "sg:tags":[
        "insulation",
        "installers",
        "toy"
    ],
    "wof:name":"A Proctor Group Ltd.",
    "wof:placetype":"venue"
},
  "geometry": {"coordinates":[-3.336929,56.591431],"type":"Point"}
}