{
  "type": "Feature",
  "properties": {
    "addr:full":"20 Greenfields, Nettleham Lincoln Lincolnshire LN2 2RY",
    "addr:housenumber":"20",
    "addr:postcode":"ln2 2ry",
    "addr:street":"Greenfields Nettleham Lincoln",
    "iso:country":"GB",
    "sg:address":"20 Greenfields, Nettleham",
    "sg:city":"Lincoln",
    "sg:classifiers":[
        {
            "category":"Retail",
            "subcategory":"Driving School",
            "type":"Services"
        }
    ],
    "sg:phone":"+44 1522 753078",
    "sg:postcode":"LN2 2RY",
    "sg:province":"Lincolnshire",
    "wof:name":"Highway School of Motoring",
    "wof:placetype":"venue"
},
  "geometry": {"coordinates":[-0.488849,53.26585],"type":"Point"}
}