{
  "type": "Feature",
  "properties": {
    "addr:full":"122-126 Kilburn High Road, Merlin House London Greater London NW6 4HY",
    "addr:housenumber":"122-126",
    "addr:postcode":"nw6 4hy",
    "addr:street":"Kilburn High Road Merlin House",
    "iso:country":"GB",
    "sg:address":"122-126 Kilburn High Road, Merlin House",
    "sg:city":"London",
    "sg:classifiers":[
        {
            "category":"Professional",
            "subcategory":"Computer Services",
            "type":"Services"
        }
    ],
    "sg:phone":"+44 20 7604 4440",
    "sg:postcode":"NW6 4HY",
    "sg:province":"Greater London",
    "sg:tags":[
        "system",
        "software"
    ],
    "wof:name":"P C N (Integration) Ltd.",
    "wof:placetype":"venue"
},
  "geometry": {"coordinates":[-0.195141,51.539715],"type":"Point"}
}