{
  "type": "Feature",
  "properties": {
    "addr:full":"109 Rochester Road Gravesend Kent DA12 2HU",
    "addr:housenumber":"109",
    "addr:postcode":"da12 2hu",
    "addr:street":"Rochester Road",
    "iso:country":"GB",
    "sg:address":"109 Rochester Road",
    "sg:city":"Gravesend",
    "sg:classifiers":[
        {
            "category":"Autos & Motor Vehicles",
            "subcategory":"Auto Supplies",
            "type":"Retail Goods"
        }
    ],
    "sg:phone":"+44 1474 533324",
    "sg:postcode":"DA12 2HU",
    "sg:province":"Kent",
    "sg:tags":[
        "exhaust",
        "absorber",
        "shock"
    ],
    "wof:name":"Gravesend Tyre & Exhaust Mart",
    "wof:placetype":"venue"
},
  "geometry": {"coordinates":[0.3902820051,51.4351348877],"type":"Point"}
}