{
  "type": "Feature",
  "properties": {
    "addr:full":"Old Kingsbury Road, Minworth Sutton Coldfield Warwickshire B76 9AE",
    "addr:postcode":"b76 9ae",
    "addr:street":"Old Kingsbury Road",
    "iso:country":"GB",
    "sg:address":"Old Kingsbury Road, Minworth",
    "sg:city":"Sutton Coldfield",
    "sg:classifiers":[
        {
            "category":"Autos & Motor Vehicles",
            "subcategory":"Auto Supplies",
            "type":"Retail Goods"
        }
    ],
    "sg:phone":"+44 121 351 1360",
    "sg:postcode":"B76 9AE",
    "sg:province":"Warwickshire",
    "sg:tags":[
        "rubber",
        "tyre"
    ],
    "wof:name":"All Wheels & Tyres",
    "wof:placetype":"venue"
},
  "geometry": {"coordinates":[-1.7678519487,52.5275726318],"type":"Point"}
}