{
  "type": "Feature",
  "properties": {
    "iso:country":"GB",
    "sg:address":"9 Corporation Road, Audenshaw",
    "sg:city":"Manchester",
    "sg:classifiers":[
        {
            "category":"Retail",
            "subcategory":"Auto Rental",
            "type":"Services"
        },
        {
            "category":"Autos & Motor Vehicles",
            "subcategory":"Motorcycle Sales",
            "type":"Retail Goods"
        }
    ],
    "sg:phone":"+44 7976 325538",
    "sg:postcode":"M34 5LY",
    "sg:province":"Greater Manchester",
    "sg:tags":[
        "chauffeur",
        "driven",
        "hire",
        "car"
    ],
    "wof:name":"Chauffeur 2000",
    "wof:placetype":"venue"
},
  "geometry": {"coordinates":[-2.124548912,53.4721183777],"type":"Point"}
}