{
  "type": "Feature",
  "properties": {
    "iso:country":"GB",
    "sg:address":"101 Hale Street, East Peckham",
    "sg:city":"Tonbridge",
    "sg:classifiers":[
        {
            "category":"Building & Trades",
            "subcategory":"Plumbing",
            "type":"Services"
        }
    ],
    "sg:phone":"+44 1622 871640",
    "sg:postcode":"TN12 5HN",
    "sg:province":"Kent",
    "sg:tags":[
        "heating"
    ],
    "wof:name":"Michael P Snell",
    "wof:placetype":"venue"
},
  "geometry": {"coordinates":[0.393553,51.217358],"type":"Point"}
}