{
  "type": "Feature",
  "properties": {
    "iso:country":"GB",
    "sg:address":"Visicks Yard",
    "sg:city":"Truro",
    "sg:classifiers":[
        {
            "category":"Home & Garden",
            "subcategory":"Hardware",
            "type":"Retail Goods"
        }
    ],
    "sg:phone":"+44 1872 865793",
    "sg:postcode":"TR3 7NR",
    "sg:province":"Cornwall",
    "sg:tags":[
        "lawnmowers",
        "machinery"
    ],
    "wof:name":"Ray-Gunn Garden Machinery",
    "wof:placetype":"venue"
},
  "geometry": {"coordinates":[-5.10095,50.212891],"type":"Point"}
}