{
  "type": "Feature",
  "properties": {
    "addr:full":"Rossefield Road Bradford West Yorkshire BD9 4DA",
    "addr:postcode":"bd9 4da",
    "addr:street":"Rossefield Road",
    "iso:country":"GB",
    "sg:address":"Rossefield Road",
    "sg:city":"Bradford",
    "sg:classifiers":[
        {
            "category":"Education",
            "subcategory":"School",
            "type":"Public Place"
        },
        {
            "category":"Government",
            "subcategory":"Office",
            "type":"Public Place"
        }
    ],
    "sg:phone":"+44 1274 545019",
    "sg:postcode":"BD9 4DA",
    "sg:province":"West Yorkshire",
    "sg:tags":[
        "local",
        "authority"
    ],
    "wof:name":"St Barnabas C of E First School",
    "wof:placetype":"venue"
},
  "geometry": {"coordinates":[-1.7862869501,53.816368103],"type":"Point"}
}