{
  "type": "Feature",
  "properties": {
    "iso:country":"GB",
    "sg:address":"5 Singer Court, Woburn Road Industrial Estate, Kempston",
    "sg:city":"Bedford",
    "sg:classifiers":[
        {
            "category":"Professional",
            "subcategory":"Printing & Photocopies",
            "type":"Services"
        }
    ],
    "sg:phone":"+44 1234 843030",
    "sg:postcode":"MK42 7AW",
    "sg:province":"Bedfordshire",
    "sg:tags":[
        "duplicating",
        "copying"
    ],
    "wof:name":"Copys",
    "wof:placetype":"venue"
},
  "geometry": {"coordinates":[-0.505067,52.114841],"type":"Point"}
}