{
  "type": "Feature",
  "properties": {
    "addr:full":"116 High Street, Sandridge St Albans Hertfordshire AL4 9BY",
    "addr:housenumber":"116",
    "addr:postcode":"al4 9by",
    "addr:street":"High Street",
    "iso:country":"GB",
    "sg:address":"116 High Street, Sandridge",
    "sg:city":"St Albans",
    "sg:classifiers":[
        {
            "category":"Building & Trades",
            "subcategory":"Cleaning & Sanitation",
            "type":"Services"
        }
    ],
    "sg:phone":"+44 1727 869907",
    "sg:postcode":"AL4 9BY",
    "sg:province":"Hertfordshire",
    "sg:tags":[
        "commercial"
    ],
    "wof:name":"Complete Cleaning Services",
    "wof:placetype":"venue"
},
  "geometry": {"coordinates":[-0.3064810038,51.7795677185],"type":"Point"}
}