{
  "type": "Feature",
  "properties": {
    "iso:country":"GB",
    "sg:address":"66 Hawthorn Road",
    "sg:city":"Bognor Regis",
    "sg:classifiers":[
        {
            "category":"Professional",
            "subcategory":"Printing & Photocopies",
            "type":"Services"
        }
    ],
    "sg:phone":"+44 1243 867932",
    "sg:postcode":"PO21 2DD",
    "sg:province":"West Sussex",
    "sg:tags":[
        "printer"
    ],
    "wof:name":"Mulberry Press",
    "wof:placetype":"venue"
},
  "geometry": {"coordinates":[-0.682909,50.792],"type":"Point"}
}