{
  "type": "Feature",
  "properties": {
    "addr:full":"Stannington Health Centre, Uppergate Rd Sheffield South Yorkshire S6 6BX",
    "addr:postcode":"s6 6bx",
    "addr:street":"Uppergate Rd",
    "iso:country":"GB",
    "sg:address":"Stannington Health Centre, Uppergate Rd",
    "sg:city":"Sheffield",
    "sg:classifiers":[
        {
            "category":"Health Services",
            "subcategory":"Doctor",
            "type":"Services"
        }
    ],
    "sg:phone":"+44 114 234 5303",
    "sg:postcode":"S6 6BX",
    "sg:province":"South Yorkshire",
    "sg:tags":[
        "practitioners"
    ],
    "wof:name":"Fitzgerald, D M",
    "wof:placetype":"venue"
},
  "geometry": {"coordinates":[-1.5470540524,53.3944091797],"type":"Point"}
}