{
  "type": "Feature",
  "properties": {
    "iso:country":"GB",
    "sg:address":"17 Priory Street",
    "sg:city":"Nuneaton",
    "sg:classifiers":[
        {
            "category":"Personal",
            "subcategory":"Beauty Salon",
            "type":"Services"
        }
    ],
    "sg:phone":"+44 24 7638 2632",
    "sg:postcode":"CV10 8JP",
    "sg:province":"Leicestershire",
    "sg:tags":[
        "lady",
        "hairdresser"
    ],
    "wof:name":"Vogue Salon",
    "wof:placetype":"venue"
},
  "geometry": {"coordinates":[-1.507415,52.51614],"type":"Point"}
}