{
  "type": "Feature",
  "properties": {
    "addr:full":"84 South Street Dorking Surrey RH4 2EZ",
    "addr:housenumber":"84",
    "addr:postcode":"rh4 2ez",
    "addr:street":"South Street",
    "iso:country":"GB",
    "sg:address":"84 South Street",
    "sg:city":"Dorking",
    "sg:classifiers":[
        {
            "category":"Restaurant",
            "type":"Food & Drink"
        }
    ],
    "sg:phone":"+44 1306 883239",
    "sg:postcode":"RH4 2EZ",
    "sg:province":"Surrey",
    "wof:name":"La Belle Epoque",
    "wof:placetype":"venue"
},
  "geometry": {"coordinates":[-0.3344889879,51.2305297852],"type":"Point"}
}