{
  "type": "Feature",
  "properties": {
    "addr:full":"The Laning, Dent Sedbergh Cumbria LA10 5QJ",
    "addr:postcode":"la10 5qj",
    "iso:country":"GB",
    "sg:address":"The Laning, Dent",
    "sg:city":"Sedbergh",
    "sg:classifiers":[
        {
            "category":"Education",
            "subcategory":"School",
            "type":"Public Place"
        }
    ],
    "sg:postcode":"LA10 5QJ",
    "sg:province":"Cumbria",
    "sg:tags":[
        "local",
        "authority"
    ],
    "wof:name":"Dent Church of England Primary School",
    "wof:placetype":"venue"
},
  "geometry": {"coordinates":[-2.527837038,54.3219451904],"type":"Point"}
}