{
  "type": "Feature",
  "properties": {
    "addr:full":"Community Centre, Brooklyn Road Cheltenham Gloucestershire GL51 8DS",
    "addr:postcode":"gl51 8ds",
    "addr:street":"Brooklyn Road",
    "iso:country":"GB",
    "sg:address":"Community Centre, Brooklyn Road",
    "sg:city":"Cheltenham",
    "sg:classifiers":[
        {
            "category":"Community Center",
            "type":"Public Place"
        }
    ],
    "sg:phone":"+44 1242 690025",
    "sg:postcode":"GL51 8DS",
    "sg:province":"Gloucestershire",
    "sg:tags":[
        "centre"
    ],
    "wof:name":"St Marks & Hesters Way Community Association",
    "wof:placetype":"venue"
},
  "geometry": {"coordinates":[-2.1104800701,51.9008712769],"type":"Point"}
}