{
  "type": "Feature",
  "properties": {
    "iso:country":"GB",
    "sg:address":"101 Weyhill",
    "sg:city":"Haslemere",
    "sg:classifiers":[
        {
            "category":"Professional",
            "subcategory":"Printing & Photocopies",
            "type":"Services"
        }
    ],
    "sg:phone":"+44 1428 656484",
    "sg:postcode":"GU27 1HS",
    "sg:province":"Hampshire",
    "sg:tags":[
        "duplicating",
        "copying"
    ],
    "wof:name":"The Soho Centre",
    "wof:placetype":"venue"
},
  "geometry": {"coordinates":[-0.7296490073,51.0924491882],"type":"Point"}
}