{
  "type": "Feature",
  "properties": {
    "iso:country":"GB",
    "sg:address":"Little Mill Cottage, Mill Lane",
    "sg:city":"Horsham",
    "sg:classifiers":[
        {
            "category":"Autos & Motor Vehicles",
            "subcategory":"Automobile Sales",
            "type":"Retail Goods"
        }
    ],
    "sg:postcode":"RH13 8JU",
    "sg:province":"West Sussex",
    "sg:tags":[
        "car"
    ],
    "wof:name":"Littleworth Commercials",
    "wof:placetype":"venue"
},
  "geometry": {"coordinates":[-0.3060159981,50.9605560303],"type":"Point"}
}