{
  "type": "Feature",
  "properties": {
    "addr:full":"Market Place, Swineshead Boston Lincolnshire PE20 3LJ",
    "addr:postcode":"pe20 3lj",
    "addr:street":"Market Place",
    "iso:country":"GB",
    "sg:address":"Market Place, Swineshead",
    "sg:city":"Boston",
    "sg:classifiers":[
        {
            "category":"Manufacturing",
            "subcategory":"Petroleum Products",
            "type":"Manufacturing & Wholesale Goods"
        }
    ],
    "sg:postcode":"PE20 3LJ",
    "sg:province":"Lincolnshire",
    "sg:tags":[
        "double",
        "glazing"
    ],
    "wof:name":"Westbridge Windows",
    "wof:placetype":"venue"
},
  "geometry": {"coordinates":[-0.1559219956,52.9412841797],"type":"Point"}
}