{
  "type": "Feature",
  "properties": {
    "iso:country":"GB",
    "sg:address":"Llandygai",
    "sg:city":"Bangor",
    "sg:classifiers":[
        {
            "category":"Transit Center",
            "subcategory":"Passenger",
            "type":"Transportation"
        }
    ],
    "sg:phone":"+44 1248 352861",
    "sg:postcode":"LL57 4BG",
    "sg:province":"Gwynedd",
    "sg:tags":[
        "boarding",
        "kennel",
        "catteries"
    ],
    "wof:name":"Gwyndy Kennels",
    "wof:placetype":"venue"
},
  "geometry": {"coordinates":[-4.100679,53.216492],"type":"Point"}
}