{
  "type": "Feature",
  "properties": {
    "iso:country":"GB",
    "sg:address":"Caudles Transport 236 Queens Road",
    "sg:city":"Sheffield",
    "sg:classifiers":[
        {
            "category":"Wholesale",
            "subcategory":"Groceries",
            "type":"Manufacturing & Wholesale Goods"
        }
    ],
    "sg:postcode":"S2 4DL",
    "sg:province":"South Yorkshire",
    "sg:tags":[
        "food",
        "supplier",
        "drink"
    ],
    "wof:name":"K P Foods Ltd.",
    "wof:placetype":"venue"
},
  "geometry": {"coordinates":[-1.46551,53.368641],"type":"Point"}
}