{
  "type": "Feature",
  "properties": {
    "addr:full":"Stanley Road Bradford West Yorkshire BD2 1AS",
    "addr:postcode":"bd2 1as",
    "addr:street":"Stanley Road",
    "iso:country":"GB",
    "sg:address":"Stanley Road",
    "sg:city":"Bradford",
    "sg:classifiers":[
        {
            "category":"Professional",
            "subcategory":"Engineering",
            "type":"Services"
        }
    ],
    "sg:phone":"+44 1274 723299",
    "sg:postcode":"BD2 1AS",
    "sg:province":"West Yorkshire",
    "sg:tags":[
        "engineer"
    ],
    "wof:name":"Sampson Engineering Co",
    "wof:placetype":"venue"
},
  "geometry": {"coordinates":[-1.761934042,53.8189239502],"type":"Point"}
}