{
  "type": "Feature",
  "properties": {
    "addr:full":"Kara-mara, Ongar Road Brentwood Essex CM15 0EE",
    "addr:postcode":"cm15 0ee",
    "addr:street":"Ongar Road",
    "iso:country":"GB",
    "sg:address":"Kara-mara, Ongar Road",
    "sg:city":"Brentwood",
    "sg:classifiers":[
        {
            "category":"Building & Trades",
            "subcategory":"Cleaning & Sanitation",
            "type":"Services"
        }
    ],
    "sg:postcode":"CM15 0EE",
    "sg:province":"Essex",
    "sg:tags":[
        "blast"
    ],
    "wof:name":"Blast Off",
    "wof:placetype":"venue"
},
  "geometry": {"coordinates":[0.2919700146,51.6796302795],"type":"Point"}
}