{
  "type": "Feature",
  "properties": {
    "addr:full":"6 Factory Road Kirkcaldy Fife KY1 2NJ",
    "addr:housenumber":"6",
    "addr:postcode":"ky1 2nj",
    "addr:street":"Factory Road",
    "iso:country":"GB",
    "sg:address":"6 Factory Road",
    "sg:city":"Kirkcaldy",
    "sg:classifiers":[
        {
            "category":"Retail",
            "subcategory":"Repair Shop",
            "type":"Services"
        }
    ],
    "sg:phone":"+44 1592 642220",
    "sg:postcode":"KY1 2NJ",
    "sg:province":"Fife",
    "sg:tags":[
        "upholstering",
        "upholsterer"
    ],
    "wof:name":"Fraser Interiors",
    "wof:placetype":"venue"
},
  "geometry": {"coordinates":[-3.145081,56.122032],"type":"Point"}
}