{
  "type": "Feature",
  "properties": {
    "iso:country":"GB",
    "sg:address":"Old Station Yard, Hawkhurst Road",
    "sg:city":"Cranbrook",
    "sg:classifiers":[
        {
            "category":"Utilities",
            "subcategory":"Natural Gas",
            "type":"Services"
        }
    ],
    "sg:phone":"+44 1580 713935",
    "sg:postcode":"TN17 2SR",
    "sg:province":"Kent",
    "sg:tags":[
        "supplier"
    ],
    "wof:name":"Eurogas Ltd.",
    "wof:placetype":"venue"
},
  "geometry": {"coordinates":[0.535245,51.0965],"type":"Point"}
}