{
  "type": "Feature",
  "properties": {
    "iso:country":"GB",
    "sg:address":"102 Derby St",
    "sg:city":"Bolton",
    "sg:classifiers":[
        {
            "category":"Home & Garden",
            "subcategory":"Household Appliances",
            "type":"Retail Goods"
        },
        {
            "category":"Shopping",
            "subcategory":"Computers & Home Electronics",
            "type":"Retail Goods"
        }
    ],
    "sg:postcode":"BL3 6HG",
    "sg:province":"Lancashire",
    "sg:tags":[
        "hi-fi",
        "electrical",
        "centre"
    ],
    "wof:name":"Kay,David,",
    "wof:placetype":"venue"
},
  "geometry": {"coordinates":[-2.436711,53.572037],"type":"Point"}
}