{
  "type": "Feature",
  "properties": {
    "iso:country":"GB",
    "sg:address":"Green La",
    "sg:city":"St Helens",
    "sg:classifiers":[
        {
            "category":"Organizations",
            "subcategory":"Religious Organization",
            "type":"Services"
        }
    ],
    "sg:phone":"+44 1744 28132",
    "sg:postcode":"WA10 5HH",
    "sg:province":"Merseyside",
    "sg:tags":[
        "organisation"
    ],
    "wof:name":"Carmelite Monastery",
    "wof:placetype":"venue"
},
  "geometry": {"coordinates":[-2.7854499817,53.4596824646],"type":"Point"}
}