{
  "type": "Feature",
  "properties": {
    "addr:full":"Unit 21, Number One Industrial Estate Consett Durham DH8 6SZ",
    "addr:housenumber":"unit 21",
    "addr:postcode":"dh8 6sz",
    "iso:country":"GB",
    "sg:address":"Unit 21, Number One Industrial Estate",
    "sg:city":"Consett",
    "sg:classifiers":[
        {
            "category":"Manufacturing",
            "subcategory":"Buildings",
            "type":"Manufacturing & Wholesale Goods"
        }
    ],
    "sg:phone":"+44 1207 590575",
    "sg:postcode":"DH8 6SZ",
    "sg:province":"Durham",
    "sg:tags":[
        "system",
        "air conditioning"
    ],
    "wof:name":"Barkell Ltd.",
    "wof:placetype":"venue"
},
  "geometry": {"coordinates":[-1.835914,54.860989],"type":"Point"}
}