{
  "type": "Feature",
  "properties": {
    "iso:country":"GB",
    "sg:address":"Park Road South",
    "sg:city":"Middlesbrough",
    "sg:classifiers":[
        {
            "category":"Museum",
            "subcategory":"Art Museum",
            "type":"Entertainment"
        },
        {
            "category":"Government",
            "subcategory":"Office",
            "type":"Public Place"
        }
    ],
    "sg:phone":"+44 1642 813781",
    "sg:postcode":"TS5 6LA",
    "sg:province":"North Yorkshire",
    "sg:tags":[
        "local",
        "gallery"
    ],
    "wof:name":"The Dorman Museum",
    "wof:placetype":"venue"
},
  "geometry": {"coordinates":[-1.2405289412,54.5637931824],"type":"Point"}
}