{
  "type": "Feature",
  "properties": {
    "addr:full":"21 Westhill, Skegby Sutton-in-ashfield Nottinghamshire NG17 3EP",
    "addr:housenumber":"21",
    "addr:postcode":"ng17 3ep",
    "addr:street":"Westhill Skegby Sutton-In-Ashfield",
    "iso:country":"GB",
    "sg:address":"21 Westhill, Skegby",
    "sg:city":"Sutton-in-ashfield",
    "sg:classifiers":[
        {
            "category":"Building & Trades",
            "subcategory":"Construction",
            "type":"Services"
        }
    ],
    "sg:phone":"+44 1623 555294",
    "sg:postcode":"NG17 3EP",
    "sg:province":"Nottinghamshire",
    "sg:tags":[
        "builder"
    ],
    "wof:name":"Kenneth Hunt Builders",
    "wof:placetype":"venue"
},
  "geometry": {"coordinates":[-1.2636499405,53.1463241577],"type":"Point"}
}