{
  "type": "Feature",
  "properties": {
    "addr:full":"4 Bilton Road Harrow Greater London UB6 7FB",
    "addr:housenumber":"4",
    "addr:postcode":"ub6 7fb",
    "addr:street":"Bilton Road",
    "iso:country":"GB",
    "sg:address":"4 Bilton Road",
    "sg:city":"Harrow",
    "sg:classifiers":[
        {
            "category":"Home & Garden",
            "subcategory":"Home Furnishings",
            "type":"Retail Goods"
        }
    ],
    "sg:phone":"+44 20 8998 9247",
    "sg:postcode":"UB6 7FB",
    "sg:province":"Greater London",
    "sg:tags":[
        "racking",
        "shelving",
        "diy"
    ],
    "wof:name":"Cornish Maintenance Co",
    "wof:placetype":"venue"
},
  "geometry": {"coordinates":[-0.3068400025,51.539478302],"type":"Point"}
}