{
  "type": "Feature",
  "properties": {
    "addr:full":"5/7 Shirley Business Park, Court Road, Shirley Southampton Hampshire SO15 3AT",
    "addr:housenumber":"5 / 7",
    "addr:postcode":"so15 3at",
    "addr:street":"Shirley Business Park Court Road",
    "iso:country":"GB",
    "sg:address":"5/7 Shirley Business Park, Court Road, Shirley",
    "sg:city":"Southampton",
    "sg:classifiers":[
        {
            "category":"Professional",
            "subcategory":"Printing & Photocopies",
            "type":"Services"
        }
    ],
    "sg:phone":"+44 23 8032 2440",
    "sg:postcode":"SO15 3AT",
    "sg:province":"Hampshire",
    "sg:tags":[
        "printer"
    ],
    "wof:name":"Hamtun Press Ltd.",
    "wof:placetype":"venue"
},
  "geometry": {"coordinates":[-1.4227399826,50.9112701416],"type":"Point"}
}