{
  "type": "Feature",
  "properties": {
    "iso:country":"GB",
    "sg:address":"43b St Andrews Street North",
    "sg:city":"Bury St Edmunds",
    "sg:classifiers":[
        {
            "category":"Professional",
            "subcategory":"Art Services",
            "type":"Services"
        }
    ],
    "sg:phone":"+44 1284 762651",
    "sg:postcode":"IP33 1TH",
    "sg:province":"Suffolk",
    "sg:tags":[
        "graphic",
        "designer"
    ],
    "wof:name":"ASAP Architectural Illustrators Graphic Design & Print",
    "wof:placetype":"venue"
},
  "geometry": {"coordinates":[0.711347,52.249588],"type":"Point"}
}