{
  "type": "Feature",
  "properties": {
    "addr:full":"4 Bonkle Road, Newmains Wishaw North Lanarkshire ML2 9AR",
    "addr:housenumber":"4",
    "addr:postcode":"ml2 9ar",
    "addr:street":"Bonkle Road",
    "iso:country":"GB",
    "sg:address":"4 Bonkle Road, Newmains",
    "sg:city":"Wishaw",
    "sg:classifiers":[
        {
            "category":"Building & Trades",
            "subcategory":"Construction",
            "type":"Services"
        }
    ],
    "sg:phone":"+44 1698 382233",
    "sg:postcode":"ML2 9AR",
    "sg:province":"North Lanarkshire",
    "sg:tags":[
        "builder"
    ],
    "wof:name":"Kirkton Developments",
    "wof:placetype":"venue"
},
  "geometry": {"coordinates":[-3.8764150143,55.7836036682],"type":"Point"}
}