{
  "type": "Feature",
  "properties": {
    "iso:country":"GB",
    "sg:address":"Raikes Road, Great Eccleston",
    "sg:city":"Preston",
    "sg:classifiers":[
        {
            "category":"Health Services",
            "subcategory":"Dentist",
            "type":"Services"
        }
    ],
    "sg:phone":"+44 1995 670546",
    "sg:postcode":"PR3 0ZA",
    "sg:province":"Lancashire",
    "wof:name":"D Vehal & P Sandhau",
    "wof:placetype":"venue"
},
  "geometry": {"coordinates":[-2.874309063,53.8559951782],"type":"Point"}
}