{
  "type": "Feature",
  "properties": {
    "addr:full":"74 Shakespeare Street Southport Lancashire PR8 5AJ",
    "addr:housenumber":"74",
    "addr:postcode":"pr8 5aj",
    "addr:street":"Shakespeare Street",
    "iso:country":"GB",
    "sg:address":"74 Shakespeare Street",
    "sg:city":"Southport",
    "sg:classifiers":[
        {
            "category":"Personal",
            "subcategory":"Beauty Salon",
            "type":"Services"
        }
    ],
    "sg:phone":"+44 1704 530030",
    "sg:postcode":"PR8 5AJ",
    "sg:province":"Lancashire",
    "sg:tags":[
        "ladies",
        "lady",
        "hairdresser"
    ],
    "wof:name":"Marions",
    "wof:placetype":"venue"
},
  "geometry": {"coordinates":[-3.004525,53.639771],"type":"Point"}
}