{
  "type": "Feature",
  "properties": {
    "addr:full":"Hayden Mill, Rabans Lane Aylesbury Buckinghamshire HP19 3ST",
    "addr:postcode":"hp19 3st",
    "addr:street":"Hayden;Rabans Lane",
    "iso:country":"GB",
    "sg:address":"Hayden Mill, Rabans Lane",
    "sg:city":"Aylesbury",
    "sg:classifiers":[
        {
            "category":"Professional",
            "subcategory":"Management & Consulting",
            "type":"Services"
        }
    ],
    "sg:phone":"+44 1296 427972",
    "sg:postcode":"HP19 3ST",
    "sg:province":"Buckinghamshire",
    "sg:tags":[
        "conservation"
    ],
    "wof:name":"Aylesbury Vale Countryside Service",
    "wof:placetype":"venue"
},
  "geometry": {"coordinates":[-0.83167,51.826302],"type":"Point"}
}