{
  "type": "Feature",
  "properties": {
    "iso:country":"GB",
    "sg:address":"1 Bowling Street",
    "sg:city":"Coatbridge",
    "sg:classifiers":[
        {
            "category":"Health Services",
            "subcategory":"Optometrist",
            "type":"Services"
        }
    ],
    "sg:phone":"+44 1236 424566",
    "sg:postcode":"ML5 1PP",
    "sg:province":"North Lanarkshire",
    "sg:tags":[
        "optician"
    ],
    "wof:name":"Hughes James G Bsc F.B.C.O",
    "wof:placetype":"venue"
},
  "geometry": {"coordinates":[-4.035886,55.861065],"type":"Point"}
}