{
  "type": "Feature",
  "properties": {
    "iso:country":"GB",
    "sg:address":"62 Tuxford Road, Boughton",
    "sg:city":"Newark",
    "sg:classifiers":[
        {
            "category":"Wholesale",
            "subcategory":"Machinery & Supplies",
            "type":"Manufacturing & Wholesale Goods"
        }
    ],
    "sg:postcode":"NG22 9HY",
    "sg:province":"Nottinghamshire",
    "sg:tags":[
        "pump"
    ],
    "wof:name":"David Critchley",
    "wof:placetype":"venue"
},
  "geometry": {"coordinates":[-0.9922829866,53.2055053711],"type":"Point"}
}