{
  "type": "Feature",
  "properties": {
    "iso:country":"GB",
    "sg:address":"Blenheim Road",
    "sg:city":"Maidenhead",
    "sg:classifiers":[
        {
            "category":"Education",
            "subcategory":"School",
            "type":"Public Place"
        }
    ],
    "sg:phone":"+44 1628 626958",
    "sg:postcode":"SL6 5HE",
    "sg:province":"Berkshire",
    "sg:tags":[
        "local",
        "authority"
    ],
    "wof:name":"Courthouse County Junior School",
    "wof:placetype":"venue"
},
  "geometry": {"coordinates":[-0.7485929728,51.5293273926],"type":"Point"}
}