{
  "type": "Feature",
  "properties": {
    "iso:country":"GB",
    "sg:address":"Southdown Road",
    "sg:city":"Harpenden",
    "sg:classifiers":[
        {
            "category":"Education",
            "subcategory":"School",
            "type":"Public Place"
        }
    ],
    "sg:phone":"+44 1582 760047",
    "sg:postcode":"AL5 1PF",
    "sg:province":"Hertfordshire",
    "sg:tags":[
        "local",
        "authority"
    ],
    "wof:name":"St Dominics R C Primary School",
    "wof:placetype":"venue"
},
  "geometry": {"coordinates":[-0.354224,51.814095],"type":"Point"}
}