{
  "type": "Feature",
  "properties": {
    "addr:full":"14 Leland Place Morpeth Northumberland NE61 2AN",
    "addr:housenumber":"14",
    "addr:postcode":"ne61 2an",
    "addr:street":"Leland Place",
    "iso:country":"GB",
    "sg:address":"14 Leland Place",
    "sg:city":"Morpeth",
    "sg:classifiers":[
        {
            "category":"Professional",
            "subcategory":"Computer Services",
            "type":"Services"
        }
    ],
    "sg:postcode":"NE61 2AN",
    "sg:province":"Northumberland",
    "sg:tags":[
        "development",
        "system",
        "software"
    ],
    "wof:name":"Softrite Ltd.",
    "wof:placetype":"venue"
},
  "geometry": {"coordinates":[-1.703778,55.160984],"type":"Point"}
}