{
  "type": "Feature",
  "properties": {
    "addr:full":"Unit 21 Brookside Business Park Uttoxeter Derbyshire ST14 8AU",
    "addr:housenumber":"unit 21",
    "addr:postcode":"st14 8au",
    "addr:street":"Brookside Business Park Uttoxeter",
    "iso:country":"GB",
    "sg:address":"Unit 21 Brookside Business Park",
    "sg:city":"Uttoxeter",
    "sg:classifiers":[
        {
            "category":"Shopping",
            "subcategory":"Clothing, Apparel, & Fashions",
            "type":"Retail Goods"
        }
    ],
    "sg:postcode":"ST14 8AU",
    "sg:province":"Derbyshire",
    "sg:tags":[
        "clothing",
        "fabric"
    ],
    "wof:name":"Jade Manufacturing",
    "wof:placetype":"venue"
},
  "geometry": {"coordinates":[-1.8575559855,52.8973922729],"type":"Point"}
}