{
  "type": "Feature",
  "properties": {
    "iso:country":"GB",
    "sg:address":"39 White Hart Lane",
    "sg:city":"Romford",
    "sg:classifiers":[
        {
            "category":"Shopping",
            "subcategory":"News",
            "type":"Retail Goods"
        }
    ],
    "sg:phone":"+44 1708 743779",
    "sg:postcode":"RM7 8JB",
    "sg:province":"Essex",
    "sg:tags":[
        "newsagent"
    ],
    "wof:name":"Jacksons",
    "wof:placetype":"venue"
},
  "geometry": {"coordinates":[0.158053,51.590843],"type":"Point"}
}