{
  "type": "Feature",
  "properties": {
    "iso:country":"GB",
    "sg:address":"Inverness Sports Centre, Bught",
    "sg:city":"Inverness",
    "sg:classifiers":[
        {
            "category":"Recreation",
            "type":"Entertainment"
        }
    ],
    "sg:phone":"+44 1463 714712",
    "sg:postcode":"IV3 5SR",
    "sg:province":"Highland",
    "sg:tags":[
        "outdoor",
        "pursuit"
    ],
    "wof:name":"World Orienteering Championships Event",
    "wof:placetype":"venue"
},
  "geometry": {"coordinates":[-4.2356119156,57.4790153503],"type":"Point"}
}