{
  "type": "Feature",
  "properties": {
    "addr:full":"17 Ware Road Hertford Hertfordshire SG13 7DZ",
    "addr:housenumber":"17",
    "addr:postcode":"sg13 7dz",
    "addr:street":"Ware Road",
    "iso:country":"GB",
    "sg:address":"17 Ware Road",
    "sg:city":"Hertford",
    "sg:classifiers":[
        {
            "category":"Professional",
            "subcategory":"Management & Consulting",
            "type":"Services"
        }
    ],
    "sg:postcode":"SG13 7DZ",
    "sg:province":"Hertfordshire",
    "sg:tags":[
        "consultant",
        "business"
    ],
    "wof:name":"Management Achievement",
    "wof:placetype":"venue"
},
  "geometry": {"coordinates":[-0.069472,51.7980613708],"type":"Point"}
}