{
  "type": "Feature",
  "properties": {
    "iso:country":"GB",
    "sg:address":"Bannerman Road",
    "sg:city":"Bristol",
    "sg:classifiers":[
        {
            "category":"Retail",
            "subcategory":"Auto Repair",
            "type":"Services"
        }
    ],
    "sg:phone":"+44 117 955 0833",
    "sg:postcode":"BS5 0RR",
    "sg:province":"City of Bristol",
    "sg:tags":[
        "body",
        "car"
    ],
    "wof:name":"Banners of Bristol",
    "wof:placetype":"venue"
},
  "geometry": {"coordinates":[-2.5648748875,51.4652366638],"type":"Point"}
}