{
  "type": "Feature",
  "properties": {
    "addr:full":"210a Broadway Didcot Oxfordshire OX11 8RN",
    "addr:housenumber":"210a",
    "addr:postcode":"ox11 8rn",
    "addr:street":"Broadway",
    "iso:country":"GB",
    "sg:address":"210a Broadway",
    "sg:city":"Didcot",
    "sg:classifiers":[
        {
            "category":"Personal",
            "subcategory":"Beauty Salon",
            "type":"Services"
        },
        {
            "category":"Personal",
            "subcategory":"Barber",
            "type":"Services"
        }
    ],
    "sg:phone":"+44 1235 812300",
    "sg:postcode":"OX11 8RN",
    "sg:province":"Oxfordshire",
    "sg:tags":[
        "unisex",
        "hairdresser"
    ],
    "wof:name":"Didcot Hair Stylists",
    "wof:placetype":"venue"
},
  "geometry": {"coordinates":[-1.240218997,51.6062011719],"type":"Point"}
}