{
  "type": "Feature",
  "properties": {
    "addr:full":"Green (the) Fareham Hampshire PO14 2JQ",
    "addr:postcode":"po14 2jq",
    "iso:country":"GB",
    "sg:address":"Green (the)",
    "sg:city":"Fareham",
    "sg:classifiers":[
        {
            "category":"Food & Beverages",
            "subcategory":"Bakery",
            "type":"Retail Goods"
        }
    ],
    "sg:postcode":"PO14 2JQ",
    "sg:province":"Hampshire",
    "sg:tags":[
        "baker"
    ],
    "wof:name":"Humby,C, & Sons",
    "wof:placetype":"venue"
},
  "geometry": {"coordinates":[-1.2172420025,50.8308906555],"type":"Point"}
}