{
  "type": "Feature",
  "properties": {
    "iso:country":"GB",
    "sg:address":"Anglian Region, Bromholme Lane, Brampton",
    "sg:city":"Huntingdon",
    "sg:classifiers":[
        {
            "category":"Government",
            "subcategory":"Office",
            "type":"Public Place"
        }
    ],
    "sg:postcode":"PE28 4NE",
    "sg:province":"Bedfordshire",
    "sg:tags":[
        "central"
    ],
    "wof:name":"Enviromental Agency",
    "wof:placetype":"venue"
},
  "geometry": {"coordinates":[-0.2227569968,52.3244552612],"type":"Point"}
}