{
  "type": "Feature",
  "properties": {
    "iso:country":"GB",
    "sg:address":"Unit C Castle Hil Court",
    "sg:city":"Huntingdon",
    "sg:classifiers":[
        {
            "category":"Manufacturing",
            "subcategory":"Wood Products",
            "type":"Manufacturing & Wholesale Goods"
        },
        {
            "category":"Manufacturing",
            "subcategory":"Paper Products",
            "type":"Manufacturing & Wholesale Goods"
        }
    ],
    "sg:phone":"+44 1480 216161",
    "sg:postcode":"PE19 8ET",
    "sg:province":"Bedfordshire",
    "sg:tags":[
        "manufacture",
        "adhesive",
        "crate",
        "packaging",
        "tape",
        "pallets"
    ],
    "wof:name":"Tapekraft Ltd.",
    "wof:placetype":"venue"
},
  "geometry": {"coordinates":[-0.289375,52.217472],"type":"Point"}
}