{
  "type": "Feature",
  "properties": {
    "addr:full":"Arch Farm, Llantrissent Usk Monmouthshire NP15 1LW",
    "addr:postcode":"np15 1lw",
    "addr:street":"Arch",
    "iso:country":"GB",
    "sg:address":"Arch Farm, Llantrissent",
    "sg:city":"Usk",
    "sg:classifiers":[
        {
            "category":"Farming",
            "subcategory":"Livestock Farm",
            "type":"Manufacturing & Wholesale Goods"
        }
    ],
    "sg:postcode":"NP15 1LW",
    "sg:province":"Monmouthshire",
    "sg:tags":[
        "others"
    ],
    "wof:name":"I D & T A Cantelo",
    "wof:placetype":"venue"
},
  "geometry": {"coordinates":[-2.902849,51.703735],"type":"Point"}
}