{
  "type": "Feature",
  "properties": {
    "addr:full":"16 The Oakes Redditch Warwickshire B98 7ST",
    "addr:housenumber":"16",
    "addr:postcode":"b98 7st",
    "addr:street":"The",
    "iso:country":"GB",
    "sg:address":"16 The Oakes",
    "sg:city":"Redditch",
    "sg:classifiers":[
        {
            "category":"Wholesale",
            "subcategory":"Medical Equipment & Supplies",
            "type":"Manufacturing & Wholesale Goods"
        }
    ],
    "sg:phone":"+44 1527 551155",
    "sg:postcode":"B98 7ST",
    "sg:province":"Warwickshire",
    "wof:name":"Surgicraft Ltd.",
    "wof:placetype":"venue"
},
  "geometry": {"coordinates":[-1.9300099611,52.2834510803],"type":"Point"}
}