{
  "type": "Feature",
  "properties": {
    "addr:full":"5a Castle St Maesteg Bridgend CF34 9UN",
    "addr:housenumber":"5a",
    "addr:postcode":"cf34 9un",
    "addr:street":"Castle St",
    "iso:country":"GB",
    "sg:address":"5a Castle St",
    "sg:city":"Maesteg",
    "sg:classifiers":[
        {
            "category":"Retail",
            "subcategory":"Funeral Services",
            "type":"Services"
        }
    ],
    "sg:phone":"+44 1656 731455",
    "sg:postcode":"CF34 9UN",
    "sg:province":"Bridgend",
    "sg:tags":[
        "mnfr",
        "monumental",
        "mason"
    ],
    "wof:name":"Edwards Memorials",
    "wof:placetype":"venue"
},
  "geometry": {"coordinates":[-3.6589961052,51.6104698181],"type":"Point"}
}