{
  "type": "Feature",
  "properties": {
    "iso:country":"GB",
    "sg:address":"Acre Ho, 11-15 William Rd",
    "sg:city":"London",
    "sg:classifiers":[
        {
            "category":"Wholesale",
            "subcategory":"Books, Periodicals, & Newspapers",
            "type":"Manufacturing & Wholesale Goods"
        }
    ],
    "sg:postcode":"NW1 3ER",
    "sg:province":"Greater London",
    "sg:tags":[
        "publishing"
    ],
    "wof:name":"Writers and Readers Ltd",
    "wof:placetype":"venue"
},
  "geometry": {"coordinates":[-0.14012,51.52692],"type":"Point"}
}