{
  "type": "Feature",
  "properties": {
    "iso:country":"GB",
    "sg:address":"33 Whiteley St",
    "sg:city":"Huddersfield",
    "sg:classifiers":[
        {
            "category":"Building & Trades",
            "subcategory":"Construction",
            "type":"Services"
        }
    ],
    "sg:phone":"+44 1484 644630",
    "sg:postcode":"HD3 4LT",
    "sg:province":"West Yorkshire",
    "sg:tags":[
        "roofing"
    ],
    "wof:name":"A M P W Roofing Contractors",
    "wof:placetype":"venue"
},
  "geometry": {"coordinates":[-1.823382,53.638294],"type":"Point"}
}