{
  "type": "Feature",
  "properties": {
    "addr:full":"Commercial Road, Ussculme Cullompton Devon EX15 3EB",
    "addr:postcode":"ex15 3eb",
    "addr:street":"Commercial Road Ussculme",
    "iso:country":"GB",
    "sg:address":"Commercial Road, Ussculme",
    "sg:city":"Cullompton",
    "sg:classifiers":[
        {
            "category":"Shopping",
            "subcategory":"Department Store",
            "type":"Retail Goods"
        }
    ],
    "sg:postcode":"EX15 3EB",
    "sg:province":"Devon",
    "wof:name":"Osmond House Stores",
    "wof:placetype":"venue"
},
  "geometry": {"coordinates":[-3.3281319141,50.9058799744],"type":"Point"}
}