{
  "type": "Feature",
  "properties": {
    "addr:full":"4 Milton Street, Clayton Le Moors Accrington Lancashire BB5 5QE",
    "addr:housenumber":"4",
    "addr:postcode":"bb5 5qe",
    "addr:street":"Milton Street",
    "iso:country":"GB",
    "sg:address":"4 Milton Street, Clayton Le Moors",
    "sg:city":"Accrington",
    "sg:classifiers":[
        {
            "category":"Food & Beverages",
            "subcategory":"Meat & Fish",
            "type":"Retail Goods"
        }
    ],
    "sg:phone":"+44 1254 236604",
    "sg:postcode":"BB5 5QE",
    "sg:province":"Lancashire",
    "sg:tags":[
        "chip"
    ],
    "wof:name":"Milton Street Chippie",
    "wof:placetype":"venue"
},
  "geometry": {"coordinates":[-2.3842720985,53.7785644531],"type":"Point"}
}