{
  "type": "Feature",
  "properties": {
    "iso:country":"GB",
    "sg:address":"Area 1 Riverside Works, Railshead Road",
    "sg:city":"Isleworth",
    "sg:classifiers":[
        {
            "category":"Home & Garden",
            "subcategory":"Furniture",
            "type":"Retail Goods"
        }
    ],
    "sg:postcode":"TW7 7BY",
    "sg:province":"Greater London",
    "wof:name":"David Jones Furniture Makers",
    "wof:placetype":"venue"
},
  "geometry": {"coordinates":[-0.338233,51.473915],"type":"Point"}
}