{
  "type": "Feature",
  "properties": {
    "addr:full":"Keyingham House, Abbey Road Alton Hampshire GU34 5PB",
    "addr:housenumber":"keyingham",
    "addr:postcode":"gu34 5pb",
    "addr:street":"Abbey Road",
    "iso:country":"GB",
    "sg:address":"Keyingham House, Abbey Road",
    "sg:city":"Alton",
    "sg:classifiers":[
        {
            "category":"Professional",
            "subcategory":"Management & Consulting",
            "type":"Services"
        }
    ],
    "sg:phone":"+44 1420 561334",
    "sg:postcode":"GU34 5PB",
    "sg:province":"Hampshire",
    "sg:tags":[
        "consultant",
        "business"
    ],
    "wof:name":"Novowork Ltd.",
    "wof:placetype":"venue"
},
  "geometry": {"coordinates":[-1.0444669724,51.1327438354],"type":"Point"}
}