{
  "type": "Feature",
  "properties": {
    "addr:full":"Moneys Mill, Carre Street Sleaford Lincolnshire NG34 7TW",
    "addr:postcode":"ng34 7tw",
    "addr:street":"Moneys;Carre Street",
    "iso:country":"GB",
    "sg:address":"Moneys Mill, Carre Street",
    "sg:city":"Sleaford",
    "sg:classifiers":[
        {
            "category":"Landmark",
            "subcategory":"Tourist Information",
            "type":"Public Place"
        }
    ],
    "sg:phone":"+44 1529 414294",
    "sg:postcode":"NG34 7TW",
    "sg:province":"Lincolnshire",
    "wof:name":"Tourist Information Centre",
    "wof:placetype":"venue"
},
  "geometry": {"coordinates":[-0.4118689895,52.9945869446],"type":"Point"}
}