{
  "type": "Feature",
  "properties": {
    "iso:country":"GB",
    "sg:address":"Unit 2",
    "sg:city":"Ormskirk",
    "sg:classifiers":[
        {
            "category":"Home & Garden",
            "subcategory":"Carpets & Floor Coverings",
            "type":"Retail Goods"
        }
    ],
    "sg:phone":"+44 1695 579831",
    "sg:postcode":"L39 3BH",
    "sg:province":"Lancashire",
    "sg:tags":[
        "carpets",
        "rug",
        "matting"
    ],
    "wof:name":"Ormskirk Carpet Centre Ltd.",
    "wof:placetype":"venue"
},
  "geometry": {"coordinates":[-2.893819,53.564442],"type":"Point"}
}