{
  "type": "Feature",
  "properties": {
    "addr:full":"Stoneythorpe, Southam Leamington Spa Warwickshire CV47 2DL",
    "addr:postcode":"cv47 2dl",
    "iso:country":"GB",
    "sg:address":"Stoneythorpe, Southam",
    "sg:city":"Leamington Spa",
    "sg:classifiers":[
        {
            "category":"Professional",
            "subcategory":"Computer Services",
            "type":"Services"
        }
    ],
    "sg:phone":"+44 1926 814132",
    "sg:postcode":"CV47 2DL",
    "sg:province":"Warwickshire",
    "sg:tags":[
        "system",
        "software"
    ],
    "wof:name":"The Codemasters Software Co. Ltd.",
    "wof:placetype":"venue"
},
  "geometry": {"coordinates":[-1.4140399694,52.2521781921],"type":"Point"}
}