{
  "type": "Feature",
  "properties": {
    "addr:full":"Manor Road, Crayford Dartford Kent DA1 4EP",
    "addr:postcode":"da1 4ep",
    "addr:street":"Manor Road",
    "iso:country":"GB",
    "sg:address":"Manor Road, Crayford",
    "sg:city":"Dartford",
    "sg:classifiers":[
        {
            "category":"Government",
            "subcategory":"City Hall",
            "type":"Public Place"
        },
        {
            "category":"Retail",
            "subcategory":"Event Space",
            "type":"Services"
        }
    ],
    "sg:phone":"+44 1322 522628",
    "sg:postcode":"DA1 4EP",
    "sg:province":"Kent",
    "sg:tags":[
        "function",
        "hire",
        "room"
    ],
    "wof:name":"St Paulinus Church Hall",
    "wof:placetype":"venue"
},
  "geometry": {"coordinates":[0.1775339991,51.4523735046],"type":"Point"}
}