{
  "type": "Feature",
  "properties": {
    "addr:full":"Oxford Road, Kidlington Oxford Buckinghamshire OX5 2NX",
    "addr:postcode":"ox5 2nx",
    "addr:street":"Oxford Road",
    "iso:country":"GB",
    "sg:address":"Oxford Road, Kidlington",
    "sg:city":"Oxford",
    "sg:classifiers":[
        {
            "category":"Government",
            "subcategory":"Police Station",
            "type":"Public Place"
        }
    ],
    "sg:phone":"+44 1865 846000",
    "sg:postcode":"OX5 2NX",
    "sg:province":"Buckinghamshire",
    "sg:tags":[
        "support"
    ],
    "wof:name":"Thames Valley Police Authority",
    "wof:placetype":"venue"
},
  "geometry": {"coordinates":[-1.2905290127,51.8229637146],"type":"Point"}
}