{
  "type": "Feature",
  "properties": {
    "iso:country":"GB",
    "sg:address":"Cookridge Lane, Cookridge",
    "sg:city":"Leeds",
    "sg:classifiers":[
        {
            "category":"Sports & Exercise",
            "subcategory":"Gym",
            "type":"Entertainment"
        }
    ],
    "sg:phone":"+44 113 261 9565",
    "sg:postcode":"LS16 7NL",
    "sg:province":"West Yorkshire",
    "sg:tags":[
        "fitness",
        "health",
        "centre"
    ],
    "wof:name":"Premier Training International Ltd.",
    "wof:placetype":"venue"
},
  "geometry": {"coordinates":[-1.620082,53.867268],"type":"Point"}
}