{
  "type": "Feature",
  "properties": {
    "addr:full":"38 High Street Criccieth Gwynedd LL52 0EY",
    "addr:housenumber":"38",
    "addr:postcode":"ll52 0ey",
    "addr:street":"High Street",
    "iso:country":"GB",
    "sg:address":"38 High Street",
    "sg:city":"Criccieth",
    "sg:classifiers":[
        {
            "category":"Restaurant",
            "type":"Food & Drink"
        }
    ],
    "sg:phone":"+44 1766 522165",
    "sg:postcode":"LL52 0EY",
    "sg:province":"Gwynedd",
    "wof:name":"Tiffin Restaurant",
    "wof:placetype":"venue"
},
  "geometry": {"coordinates":[-4.2325987816,52.9197540283],"type":"Point"}
}