{
  "type": "Feature",
  "properties": {
    "iso:country":"GB",
    "sg:address":"Broadway",
    "sg:city":"Cambridge",
    "sg:classifiers":[
        {
            "category":"Shopping",
            "subcategory":"Stationery & Office Supplies",
            "type":"Retail Goods"
        }
    ],
    "sg:phone":"+44 1954 719090",
    "sg:postcode":"CB3 7TE",
    "sg:province":"Cambridgeshire",
    "sg:tags":[
        "item",
        "promotional"
    ],
    "wof:name":"Cally's Town & Country",
    "wof:placetype":"venue"
},
  "geometry": {"coordinates":[-0.0463760011,52.2211227417],"type":"Point"}
}