{
  "type": "Feature",
  "properties": {
    "iso:country":"GB",
    "sg:address":"148 Stonecot Hill",
    "sg:city":"Sutton",
    "sg:classifiers":[
        {
            "category":"Social Services",
            "subcategory":"Job Training",
            "type":"Services"
        }
    ],
    "sg:postcode":"SM3 9HQ",
    "sg:province":"Surrey",
    "sg:tags":[
        "translator",
        "interpreter"
    ],
    "wof:name":"K Wilkinson Translations",
    "wof:placetype":"venue"
},
  "geometry": {"coordinates":[-0.2171719968,51.3810691833],"type":"Point"}
}