{
  "type": "Feature",
  "properties": {
    "iso:country":"GB",
    "sg:address":"137-138 Queensgate Market Arcade, Princess Alexand",
    "sg:city":"Huddersfield",
    "sg:classifiers":[
        {
            "category":"Home & Garden",
            "subcategory":"Home Furnishings",
            "type":"Retail Goods"
        }
    ],
    "sg:postcode":"HD1 2UJ",
    "sg:province":"West Yorkshire",
    "sg:tags":[
        "blind",
        "curtain",
        "fitting"
    ],
    "wof:name":"The Windowbox",
    "wof:placetype":"venue"
},
  "geometry": {"coordinates":[-1.7784889936,53.6445083618],"type":"Point"}
}