{
  "type": "Feature",
  "properties": {
    "addr:full":"Todleth Farm, Churchstoke Montgomery Shropshire SY15 6BH",
    "addr:postcode":"sy15 6bh",
    "iso:country":"GB",
    "sg:address":"Todleth Farm, Churchstoke",
    "sg:city":"Montgomery",
    "sg:classifiers":[
        {
            "category":"Building & Trades",
            "subcategory":"Construction",
            "type":"Services"
        }
    ],
    "sg:phone":"+44 1588 620269",
    "sg:postcode":"SY15 6BH",
    "sg:province":"Shropshire",
    "sg:tags":[
        "builder"
    ],
    "wof:name":"A L & R A Powell",
    "wof:placetype":"venue"
},
  "geometry": {"coordinates":[-3.146479,52.563564],"type":"Point"}
}