{
  "type": "Feature",
  "properties": {
    "addr:full":"28 Swadford Street Skipton Lancashire BD23 1RD",
    "addr:housenumber":"28",
    "addr:postcode":"bd23 1rd",
    "addr:street":"Swadford Street",
    "iso:country":"GB",
    "sg:address":"28 Swadford Street",
    "sg:city":"Skipton",
    "sg:classifiers":[
        {
            "category":"Shopping",
            "subcategory":"News",
            "type":"Retail Goods"
        }
    ],
    "sg:phone":"+44 1756 792829",
    "sg:postcode":"BD23 1RD",
    "sg:province":"Lancashire",
    "sg:tags":[
        "newsagent"
    ],
    "wof:name":"The News Shop",
    "wof:placetype":"venue"
},
  "geometry": {"coordinates":[-2.0172491074,53.9604568481],"type":"Point"}
}