{
  "type": "Feature",
  "properties": {
    "addr:full":"54 Mercaston Close, Holme Hall Estate Chesterfield Derbyshire S40 4UE",
    "addr:housenumber":"54",
    "addr:postcode":"s40 4ue",
    "addr:street":"Mercaston Close Holme Hall Estate",
    "iso:country":"GB",
    "sg:address":"54 Mercaston Close, Holme Hall Estate",
    "sg:city":"Chesterfield",
    "sg:classifiers":[
        {
            "category":"Building & Trades",
            "subcategory":"Landscaping Services",
            "type":"Services"
        }
    ],
    "sg:phone":"+44 1246 202868",
    "sg:postcode":"S40 4UE",
    "sg:province":"Derbyshire",
    "sg:tags":[
        "gardening"
    ],
    "wof:name":"Garden Pride",
    "wof:placetype":"venue"
},
  "geometry": {"coordinates":[-1.4717340469,53.2460441589],"type":"Point"}
}