{
  "type": "Feature",
  "properties": {
    "addr:full":"10-12 Middle Street, Watton Thetford Norfolk IP25 6AG",
    "addr:housenumber":"10-12",
    "addr:postcode":"ip25 6ag",
    "addr:street":"Middle Street",
    "iso:country":"GB",
    "sg:address":"10-12 Middle Street, Watton",
    "sg:city":"Thetford",
    "sg:classifiers":[
        {
            "category":"Home & Garden",
            "subcategory":"Household Appliances",
            "type":"Retail Goods"
        },
        {
            "category":"Communications",
            "type":"Services"
        }
    ],
    "sg:phone":"+44 1953 882156",
    "sg:postcode":"IP25 6AG",
    "sg:province":"Norfolk",
    "sg:tags":[
        "repairs",
        "tv",
        "domestic",
        "video",
        "servicing",
        "radio",
        "electrical"
    ],
    "wof:name":"B W B Domestics",
    "wof:placetype":"venue"
},
  "geometry": {"coordinates":[0.8260849714,52.5715408325],"type":"Point"}
}