{
  "type": "Feature",
  "properties": {
    "addr:full":"Candide, 92 Swinburne Rd London Greater London SW15 5EH",
    "addr:housenumber":"92",
    "addr:postcode":"sw15 5eh",
    "addr:street":"Candide;Swinburne Rd",
    "iso:country":"GB",
    "sg:address":"Candide, 92 Swinburne Rd",
    "sg:city":"London",
    "sg:classifiers":[
        {
            "category":"Professional",
            "subcategory":"Art Services",
            "type":"Services"
        }
    ],
    "sg:postcode":"SW15 5EH",
    "sg:province":"Greater London",
    "sg:tags":[
        "photographer"
    ],
    "wof:name":"Bloch,Steven,",
    "wof:placetype":"venue"
},
  "geometry": {"coordinates":[-0.2398000062,51.4605484009],"type":"Point"}
}