{
  "type": "Feature",
  "properties": {
    "addr:full":"99 London Road, Teynham Sittingbourne Kent ME9 9QJ",
    "addr:housenumber":"99",
    "addr:postcode":"me9 9qj",
    "addr:street":"London Road",
    "iso:country":"GB",
    "sg:address":"99 London Road, Teynham",
    "sg:city":"Sittingbourne",
    "sg:classifiers":[
        {
            "category":"Shopping",
            "subcategory":"Hobbies, Toys, & Games",
            "type":"Retail Goods"
        }
    ],
    "sg:phone":"+44 1795 522445",
    "sg:postcode":"ME9 9QJ",
    "sg:province":"Kent",
    "sg:tags":[
        "house",
        "dolls'",
        "doll"
    ],
    "wof:name":"Cara Dolls",
    "wof:placetype":"venue"
},
  "geometry": {"coordinates":[0.800369,51.327824],"type":"Point"}
}