{
  "type": "Feature",
  "properties": {
    "addr:full":"27 Ousegate Bussines Centre Selby East Riding of Yorkshire YO8 4NN",
    "addr:housenumber":"27",
    "addr:postcode":"yo8 4nn",
    "addr:street":"Ousegate Bussines Centre",
    "iso:country":"GB",
    "sg:address":"27 Ousegate Bussines Centre",
    "sg:city":"Selby",
    "sg:classifiers":[
        {
            "category":"Professional",
            "subcategory":"Engineering",
            "type":"Services"
        }
    ],
    "sg:postcode":"YO8 4NN",
    "sg:province":"East Riding of Yorkshire",
    "sg:tags":[
        "engineer",
        "structural"
    ],
    "wof:name":"Bolton Priestley",
    "wof:placetype":"venue"
},
  "geometry": {"coordinates":[-1.0703459978,53.783908844],"type":"Point"}
}