{
  "type": "Feature",
  "properties": {
    "addr:full":"15 Haddon Rd Maidenhead Berkshire SL6 4RA",
    "addr:housenumber":"15",
    "addr:postcode":"sl6 4ra",
    "addr:street":"Haddon Rd",
    "iso:country":"GB",
    "sg:address":"15 Haddon Rd",
    "sg:city":"Maidenhead",
    "sg:classifiers":[
        {
            "category":"Social Services",
            "subcategory":"Adult Care",
            "type":"Services"
        }
    ],
    "sg:phone":"+44 1628 621675",
    "sg:postcode":"SL6 4RA",
    "sg:province":"Berkshire",
    "sg:tags":[
        "domestic",
        "cleaning"
    ],
    "wof:name":"Andrella Cleaning Services",
    "wof:placetype":"venue"
},
  "geometry": {"coordinates":[-0.744176,51.515289],"type":"Point"}
}