{
  "type": "Feature",
  "properties": {
    "iso:country":"GB",
    "sg:address":"556-558 Great Horton Road",
    "sg:city":"Bradford",
    "sg:classifiers":[
        {
            "category":"Professional",
            "subcategory":"Detective & Security Services",
            "type":"Services"
        }
    ],
    "sg:phone":"+44 1274 575375",
    "sg:postcode":"BD7 3HG",
    "sg:province":"West Yorkshire",
    "sg:tags":[
        "alarm",
        "burglar",
        "system"
    ],
    "wof:name":"J A Security Systems",
    "wof:placetype":"venue"
},
  "geometry": {"coordinates":[-1.7819620371,53.7828445435],"type":"Point"}
}