{
  "type": "Feature",
  "properties": {
    "addr:full":"18 Shepherd Street London Greater London W1J 7JG",
    "addr:housenumber":"18",
    "addr:postcode":"w1j 7jg",
    "addr:street":"Shepherd Street",
    "iso:country":"GB",
    "sg:address":"18 Shepherd Street",
    "sg:city":"London",
    "sg:classifiers":[
        {
            "category":"Restaurant",
            "type":"Food & Drink"
        }
    ],
    "sg:phone":"+44 20 7493 3320",
    "sg:postcode":"W1J 7JG",
    "sg:province":"Greater London",
    "wof:name":"Lazon Ltd.",
    "wof:placetype":"venue"
},
  "geometry": {"coordinates":[-0.147141993,51.5063018799],"type":"Point"}
}