{
  "type": "Feature",
  "properties": {
    "iso:country":"GB",
    "sg:address":"2 Windsor Way",
    "sg:city":"Aldershot",
    "sg:classifiers":[
        {
            "category":"Building & Trades",
            "subcategory":"Construction",
            "type":"Services"
        }
    ],
    "sg:postcode":"GU11 1JG",
    "sg:province":"Hampshire",
    "sg:tags":[
        "builder"
    ],
    "wof:name":"Colonial (central Kitchens) Ltd",
    "wof:placetype":"venue"
},
  "geometry": {"coordinates":[-0.7584419847,51.2473869324],"type":"Point"}
}