{
  "type": "Feature",
  "properties": {
    "iso:country":"GB",
    "sg:address":"13 Riley Square",
    "sg:city":"Coventry",
    "sg:classifiers":[
        {
            "category":"Home & Garden",
            "subcategory":"Hardware",
            "type":"Retail Goods"
        }
    ],
    "sg:phone":"+44 24 7668 9851",
    "sg:postcode":"CV2 1LS",
    "sg:province":"Warwickshire",
    "wof:name":"Jones Hardware",
    "wof:placetype":"venue"
},
  "geometry": {"coordinates":[-1.472392,52.435947],"type":"Point"}
}