{
  "type": "Feature",
  "properties": {
    "iso:country":"GB",
    "sg:address":"29 Larch Close, Billinge",
    "sg:city":"Wigan",
    "sg:classifiers":[
        {
            "category":"Military Area",
            "subcategory":"Air Force Base",
            "type":"Public Place"
        }
    ],
    "sg:phone":"+44 1744 606006",
    "sg:postcode":"WN5 7PX",
    "sg:province":"Lancashire",
    "sg:tags":[
        "taxi",
        "hire",
        "private"
    ],
    "wof:name":"Z Cars Private Hire",
    "wof:placetype":"venue"
},
  "geometry": {"coordinates":[-2.712182,53.497795],"type":"Point"}
}