{
  "type": "Feature",
  "properties": {
    "addr:full":"Brunswick House, South Str Halifax West Yorkshire HX1 2EL",
    "addr:postcode":"hx1 2el",
    "addr:street":"South Str Halifax West",
    "iso:country":"GB",
    "sg:address":"Brunswick House, South Str",
    "sg:city":"Halifax",
    "sg:classifiers":[
        {
            "category":"Communications",
            "subcategory":"Film & Video Production",
            "type":"Services"
        }
    ],
    "sg:phone":"+44 1422 355510",
    "sg:postcode":"HX1 2EL",
    "sg:province":"West Yorkshire",
    "sg:tags":[
        "pr",
        "telemarketing"
    ],
    "wof:name":"On Line Communications",
    "wof:placetype":"venue"
},
  "geometry": {"coordinates":[-1.867209,53.719395],"type":"Point"}
}