{
  "type": "Feature",
  "properties": {
    "addr:full":"Winkworth House, 83 St. Judes Road Dagenham Surrey TW20 0DF",
    "addr:housenumber":"83",
    "addr:postcode":"tw20 0df",
    "addr:street":"St. Judes Road",
    "iso:country":"GB",
    "sg:address":"Winkworth House, 83 St. Judes Road",
    "sg:city":"Dagenham",
    "sg:classifiers":[
        {
            "category":"Professional",
            "subcategory":"Business Services",
            "type":"Services"
        }
    ],
    "sg:phone":"+44 1784 473005",
    "sg:postcode":"TW20 0DF",
    "sg:province":"Surrey",
    "sg:tags":[
        "trade"
    ],
    "wof:name":"InterForum",
    "wof:placetype":"venue"
},
  "geometry": {"coordinates":[-0.5727900267,51.4288291931],"type":"Point"}
}