{
  "type": "Feature",
  "properties": {
    "addr:full":"105 Station Road West Wickham Kent BR4 0PX",
    "addr:housenumber":"105",
    "addr:postcode":"br4 0px",
    "addr:street":"Station Road",
    "iso:country":"GB",
    "sg:address":"105 Station Road",
    "sg:city":"West Wickham",
    "sg:classifiers":[
        {
            "category":"Professional",
            "subcategory":"Employment Agencies",
            "type":"Services"
        }
    ],
    "sg:phone":"+44 1494 474000",
    "sg:postcode":"BR4 0PX",
    "sg:province":"Kent",
    "sg:tags":[
        "consultant"
    ],
    "wof:name":"Carlisle Staffing Plc",
    "wof:placetype":"venue"
},
  "geometry": {"coordinates":[-0.014387,51.37606],"type":"Point"}
}