{
  "type": "Feature",
  "properties": {
    "iso:country":"GB",
    "sg:address":"36 Fore Street",
    "sg:city":"Totnes",
    "sg:classifiers":[
        {
            "category":"Education",
            "subcategory":"University",
            "type":"Public Place"
        }
    ],
    "sg:phone":"+44 1803 867784",
    "sg:postcode":"TQ9 5RP",
    "sg:province":"Devon",
    "sg:tags":[
        "adult"
    ],
    "wof:name":"Adult Basic Education",
    "wof:placetype":"venue"
},
  "geometry": {"coordinates":[-3.68477,50.430927],"type":"Point"}
}