{
  "type": "Feature",
  "properties": {
    "iso:country":"GB",
    "sg:address":"19 Back Canning Street",
    "sg:city":"Liverpool",
    "sg:classifiers":[
        {
            "category":"Organizations",
            "subcategory":"Non-profit Organization",
            "type":"Services"
        }
    ],
    "sg:phone":"+44 151 709 0223",
    "sg:postcode":"L8 7PB",
    "sg:province":"Merseyside",
    "sg:tags":[
        "organisation",
        "voluntary",
        "charity"
    ],
    "wof:name":"Liverpool City Environment Centre",
    "wof:placetype":"venue"
},
  "geometry": {"coordinates":[-2.96945,53.399006],"type":"Point"}
}