{
  "type": "Feature",
  "properties": {
    "addr:full":"49d Crowland St Southport Lancashire PR9 7RX",
    "addr:housenumber":"49d",
    "addr:postcode":"pr9 7rx",
    "addr:street":"Crowland St",
    "iso:country":"GB",
    "sg:address":"49d Crowland St",
    "sg:city":"Southport",
    "sg:classifiers":[
        {
            "category":"Home & Garden",
            "subcategory":"Hardware",
            "type":"Retail Goods"
        }
    ],
    "sg:phone":"+44 1704 227536",
    "sg:postcode":"PR9 7RX",
    "sg:province":"Lancashire",
    "sg:tags":[
        "paint"
    ],
    "wof:name":"Special Colour Services",
    "wof:placetype":"venue"
},
  "geometry": {"coordinates":[-2.9631690979,53.6422080994],"type":"Point"}
}