{
  "type": "Feature",
  "properties": {
    "iso:country":"GB",
    "sg:address":"Barbara Street",
    "sg:city":"Tamworth",
    "sg:classifiers":[
        {
            "category":"Government",
            "subcategory":"Post Office",
            "type":"Public Place"
        }
    ],
    "sg:postcode":"B79 7EJ",
    "sg:province":"Staffordshire",
    "wof:name":"Leys Sub Post Office",
    "wof:placetype":"venue"
},
  "geometry": {"coordinates":[-1.6988339424,52.6363067627],"type":"Point"}
}