{
  "type": "Feature",
  "properties": {
    "iso:country":"GB",
    "sg:address":"26 St Marys Street",
    "sg:city":"Scarborough",
    "sg:classifiers":[
        {
            "category":"Bars & Pubs",
            "type":"Food & Drink"
        },
        {
            "category":"Community Center",
            "subcategory":"Social",
            "type":"Public Place"
        }
    ],
    "sg:phone":"+44 1723 361699",
    "sg:postcode":"YO11 1QW",
    "sg:province":"North Yorkshire",
    "sg:tags":[
        "pubs",
        "house",
        "inn",
        "activity"
    ],
    "wof:name":"Leeds Arms",
    "wof:placetype":"venue"
},
  "geometry": {"coordinates":[-0.3928380013,54.2847862244],"type":"Point"}
}