{
  "type": "Feature",
  "properties": {
    "iso:country":"GB",
    "sg:address":"Brookside Wks, Springfield Dr",
    "sg:city":"Westcliff-on-sea",
    "sg:classifiers":[
        {
            "category":"Shopping",
            "subcategory":"Crafts & Fabrics",
            "type":"Retail Goods"
        }
    ],
    "sg:postcode":"SS0 0RA",
    "sg:province":"Essex",
    "sg:tags":[
        "ceramic"
    ],
    "wof:name":"Decorite Ceramics",
    "wof:placetype":"venue"
},
  "geometry": {"coordinates":[0.684595,51.545525],"type":"Point"}
}