{
  "type": "Feature",
  "properties": {
    "addr:full":"Unit 1 Brittannia Way, Waters Meeting Road The Valley Bolton Lancashire BL2 2HH",
    "addr:housenumber":"unit 1",
    "addr:postcode":"bl2 2hh",
    "addr:street":"Brittannia Way;Meeting Road",
    "iso:country":"GB",
    "sg:address":"Unit 1 Brittannia Way, Waters Meeting Road The Valley",
    "sg:city":"Bolton",
    "sg:classifiers":[
        {
            "category":"Government",
            "subcategory":"Post Office",
            "type":"Public Place"
        }
    ],
    "sg:phone":"+44 1204 380560",
    "sg:postcode":"BL2 2HH",
    "sg:province":"Lancashire",
    "sg:tags":[
        "cutting"
    ],
    "wof:name":"Low Profiling & Grinding Ltd.",
    "wof:placetype":"venue"
},
  "geometry": {"coordinates":[-2.4193840027,53.5919837952],"type":"Point"}
}