{
  "type": "Feature",
  "properties": {
    "addr:full":"Clydach Rd Tonypandy Rhondda, Cynon, Taff CF40 2DG",
    "addr:postcode":"cf40 2dg",
    "addr:street":"Clydach Rd;Cynon Taff",
    "iso:country":"GB",
    "sg:address":"Clydach Rd",
    "sg:city":"Tonypandy",
    "sg:classifiers":[
        {
            "category":"Social Services",
            "subcategory":"Adult Care",
            "type":"Services"
        }
    ],
    "sg:phone":"+44 1443 434659",
    "sg:postcode":"CF40 2DG",
    "sg:province":"Rhondda, Cynon, Taff",
    "sg:tags":[
        "day",
        "centre"
    ],
    "wof:name":"Cambrian Day Centre",
    "wof:placetype":"venue"
},
  "geometry": {"coordinates":[-3.4579539299,51.624294281],"type":"Point"}
}