{
  "type": "Feature",
  "properties": {
    "iso:country":"GB",
    "sg:address":"216 Derby Road, Stapleford",
    "sg:city":"Nottingham",
    "sg:classifiers":[
        {
            "category":"Home & Garden",
            "subcategory":"Garden Supply",
            "type":"Retail Goods"
        }
    ],
    "sg:phone":"+44 115 939 7058",
    "sg:postcode":"NG9 7BG",
    "sg:province":"Nottinghamshire",
    "sg:tags":[
        "nursery",
        "centre"
    ],
    "wof:name":"Robert Bower Ltd.",
    "wof:placetype":"venue"
},
  "geometry": {"coordinates":[-1.281054,52.92403],"type":"Point"}
}