{
  "type": "Feature",
  "properties": {
    "addr:full":"99 Carterhatch Lane Enfield Greater London EN1 4LA",
    "addr:housenumber":"99",
    "addr:postcode":"en1 4la",
    "addr:street":"Carterhatch Lane",
    "iso:country":"GB",
    "sg:address":"99 Carterhatch Lane",
    "sg:city":"Enfield",
    "sg:classifiers":[
        {
            "category":"Health Services",
            "subcategory":"Doctor",
            "type":"Services"
        }
    ],
    "sg:phone":"+44 20 8804 5312",
    "sg:postcode":"EN1 4LA",
    "sg:province":"Greater London",
    "sg:tags":[
        "practitioners"
    ],
    "wof:name":"Rooban Dr R.A",
    "wof:placetype":"venue"
},
  "geometry": {"coordinates":[-0.0519430004,51.6597671509],"type":"Point"}
}