{
  "type": "Feature",
  "properties": {
    "addr:full":"Nottingham Road Mansfield Nottinghamshire NG18 4SE",
    "addr:postcode":"ng18 4se",
    "addr:street":"Nottingham Road",
    "iso:country":"GB",
    "sg:address":"Nottingham Road",
    "sg:city":"Mansfield",
    "sg:classifiers":[
        {
            "category":"Organizations",
            "subcategory":"Non-profit Organization",
            "type":"Services"
        }
    ],
    "sg:postcode":"NG18 4SE",
    "sg:province":"Nottinghamshire",
    "sg:tags":[
        "organisation",
        "voluntary",
        "charity"
    ],
    "wof:name":"The National Childbirth Trust",
    "wof:placetype":"venue"
},
  "geometry": {"coordinates":[-1.1968239546,53.1361045837],"type":"Point"}
}