{
  "type": "Feature",
  "properties": {
    "addr:full":"Whitegates, Crowborough Hill Crowborough East Sussex TN6 2SE",
    "addr:postcode":"tn6 2se",
    "addr:street":"Crowborough Hill",
    "iso:country":"GB",
    "sg:address":"Whitegates, Crowborough Hill",
    "sg:city":"Crowborough",
    "sg:classifiers":[
        {
            "category":"Real Estate",
            "subcategory":"Architect",
            "type":"Services"
        }
    ],
    "sg:postcode":"TN6 2SE",
    "sg:province":"East Sussex",
    "sg:tags":[
        "architectural"
    ],
    "wof:name":"Domicile Architectural & Interior Design",
    "wof:placetype":"venue"
},
  "geometry": {"coordinates":[0.171893,51.053196],"type":"Point"}
}