{
  "type": "Feature",
  "properties": {
    "addr:full":"3 Lea Valley Road, Chingford London Greater London E4 7PX",
    "addr:housenumber":"3",
    "addr:postcode":"e4 7px",
    "addr:street":"Lea Valley Road",
    "iso:country":"GB",
    "sg:address":"3 Lea Valley Road, Chingford",
    "sg:city":"London",
    "sg:classifiers":[
        {
            "category":"Autos & Motor Vehicles",
            "subcategory":"Automobile Sales",
            "type":"Retail Goods"
        },
        {
            "category":"Retail",
            "subcategory":"Auto Rental",
            "type":"Services"
        }
    ],
    "sg:phone":"+44 20 8559 4499",
    "sg:postcode":"E4 7PX",
    "sg:province":"Greater London",
    "sg:tags":[
        "car",
        "hire",
        "truck"
    ],
    "wof:name":"Lea Valley Motor Co. (Chingford) Ltd.",
    "wof:placetype":"venue"
},
  "geometry": {"coordinates":[-0.0134549998,51.6361465454],"type":"Point"}
}