{
  "type": "Feature",
  "properties": {
    "addr:full":"35 Kensington Park Road London Greater London W11 2EU",
    "addr:housenumber":"35",
    "addr:postcode":"w11 2eu",
    "addr:street":"Kensington Park Road",
    "iso:country":"GB",
    "sg:address":"35 Kensington Park Road",
    "sg:city":"London",
    "sg:classifiers":[
        {
            "category":"Travel",
            "subcategory":"Travel Agent",
            "type":"Entertainment"
        }
    ],
    "sg:phone":"+44 20 7221 8080",
    "sg:postcode":"W11 2EU",
    "sg:province":"Greater London",
    "wof:name":"Trade Promotion Travel Ltd.",
    "wof:placetype":"venue"
},
  "geometry": {"coordinates":[-0.2059870064,51.5155258179],"type":"Point"}
}