{
  "type": "Feature",
  "properties": {
    "addr:full":"61 Abbey Rd Malvern Herefordshire WR14 3HH",
    "addr:housenumber":"61",
    "addr:postcode":"wr14 3hh",
    "addr:street":"Abbey Rd;Herefordshire",
    "iso:country":"GB",
    "sg:address":"61 Abbey Rd",
    "sg:city":"Malvern",
    "sg:classifiers":[
        {
            "category":"Health Services",
            "subcategory":"Nursing And Care Facility",
            "type":"Services"
        }
    ],
    "sg:phone":"+44 1684 568688",
    "sg:postcode":"WR14 3HH",
    "sg:province":"Herefordshire",
    "sg:tags":[
        "home"
    ],
    "wof:name":"Malvernbury Nursing Home",
    "wof:placetype":"venue"
},
  "geometry": {"coordinates":[-2.327954,52.10463],"type":"Point"}
}