{
  "type": "Feature",
  "properties": {
    "iso:country":"GB",
    "sg:address":"14 Holyrood Street",
    "sg:city":"Chard",
    "sg:classifiers":[
        {
            "category":"Shopping",
            "subcategory":"Thrift Store",
            "type":"Retail Goods"
        }
    ],
    "sg:phone":"+44 1460 67939",
    "sg:postcode":"TA20 2AH",
    "sg:province":"Devon",
    "sg:tags":[
        "shop",
        "charity"
    ],
    "wof:name":"St Margarets Somerset Hospice",
    "wof:placetype":"venue"
},
  "geometry": {"coordinates":[-2.965941906,50.8720779419],"type":"Point"}
}