{
  "type": "Feature",
  "properties": {
    "addr:full":"3-5 Russell Road Rhyl Conwy LL18 3BF",
    "addr:housenumber":"3-5",
    "addr:postcode":"ll18 3bf",
    "addr:street":"Russell Road",
    "iso:country":"GB",
    "sg:address":"3-5 Russell Road",
    "sg:city":"Rhyl",
    "sg:classifiers":[
        {
            "category":"Real Estate",
            "subcategory":"Real Estate Agent",
            "type":"Services"
        }
    ],
    "sg:postcode":"LL18 3BF",
    "sg:province":"Conwy",
    "wof:name":"Jones & Redfearn",
    "wof:placetype":"venue"
},
  "geometry": {"coordinates":[-3.4861760139,53.323261261],"type":"Point"}
}