{
  "type": "Feature",
  "properties": {
    "iso:country":"GB",
    "sg:address":"The Old Coach House, Grafton Road",
    "sg:city":"Bournemouth",
    "sg:classifiers":[
        {
            "category":"Autos & Motor Vehicles",
            "subcategory":"Auto Supplies",
            "type":"Retail Goods"
        }
    ],
    "sg:postcode":"BH3 7JS",
    "sg:province":"Dorset",
    "sg:tags":[
        "exhaust",
        "absorber",
        "shock"
    ],
    "wof:name":"S J Streeter",
    "wof:placetype":"venue"
},
  "geometry": {"coordinates":[-1.870944,50.736881],"type":"Point"}
}