{
  "type": "Feature",
  "properties": {
    "iso:country":"GB",
    "sg:address":"Eight Acre Lane",
    "sg:city":"Wellington",
    "sg:classifiers":[
        {
            "category":"Arts & Performance",
            "subcategory":"Arts Center",
            "type":"Entertainment"
        }
    ],
    "sg:phone":"+44 1823 667774",
    "sg:postcode":"TA21 8PS",
    "sg:province":"Devon",
    "sg:tags":[
        "centre"
    ],
    "sg:website":"http://www.w-a-a.org",
    "wof:name":"Wellington Arts Centre",
    "wof:placetype":"venue"
},
  "geometry": {"coordinates":[-3.226129,50.974815],"type":"Point"}
}