{
  "type": "Feature",
  "properties": {
    "addr:full":"42 Milton Rd Gillingham Kent ME7 5LN",
    "addr:housenumber":"42",
    "addr:postcode":"me7 5ln",
    "addr:street":"Milton Rd",
    "iso:country":"GB",
    "sg:address":"42 Milton Rd",
    "sg:city":"Gillingham",
    "sg:classifiers":[
        {
            "category":"Professional",
            "subcategory":"Art Services",
            "type":"Services"
        }
    ],
    "sg:phone":"+44 1634 576682",
    "sg:postcode":"ME7 5LN",
    "sg:province":"Kent",
    "sg:tags":[
        "technical",
        "illustrator",
        "commercial"
    ],
    "wof:name":"Andre Hrydziuszko",
    "wof:placetype":"venue"
},
  "geometry": {"coordinates":[0.5478079915,51.3779182434],"type":"Point"}
}