{
  "type": "Feature",
  "properties": {
    "iso:country":"GB",
    "sg:address":"Unit, Clarendon House, 3-4 Le Flaive Business Park, Church Lane, Naphill",
    "sg:city":"High Wycombe",
    "sg:classifiers":[
        {
            "category":"Shopping",
            "subcategory":"Stationery & Office Supplies",
            "type":"Retail Goods"
        },
        {
            "category":"Sports & Exercise",
            "subcategory":"Playing Field",
            "type":"Entertainment"
        }
    ],
    "sg:phone":"+44 1494 565066",
    "sg:postcode":"HP14 4US",
    "sg:province":"Buckinghamshire",
    "sg:tags":[
        "equipment",
        "identification",
        "card",
        "producer"
    ],
    "wof:name":"Integrated Card Solutions Ltd.",
    "wof:placetype":"venue"
},
  "geometry": {"coordinates":[-0.76684,51.662601],"type":"Point"}
}