{
  "type": "Feature",
  "properties": {
    "iso:country":"GB",
    "sg:address":"Unit 1, Kirkbymoorside Business Centre, Kirkbymoorside",
    "sg:city":"York",
    "sg:classifiers":[
        {
            "category":"Home & Garden",
            "subcategory":"Hardware",
            "type":"Retail Goods"
        }
    ],
    "sg:postcode":"YO62 6AD",
    "sg:province":"North Yorkshire",
    "sg:tags":[
        "lawnmowers",
        "machinery"
    ],
    "wof:name":"Farrow,Andrew,",
    "wof:placetype":"venue"
},
  "geometry": {"coordinates":[-0.930924,54.269379],"type":"Point"}
}