{
  "type": "Feature",
  "properties": {
    "addr:full":"The Barn, Tan Yr Onnen Holywell Denbighshire CH8 8NF",
    "addr:postcode":"ch8 8nf",
    "addr:street":"Yr",
    "iso:country":"GB",
    "sg:address":"The Barn, Tan Yr Onnen",
    "sg:city":"Holywell",
    "sg:classifiers":[
        {
            "category":"Manufacturing",
            "subcategory":"Apparel",
            "type":"Manufacturing & Wholesale Goods"
        }
    ],
    "sg:postcode":"CH8 8NF",
    "sg:province":"Denbighshire",
    "sg:tags":[
        "mnfr",
        "lingerie",
        "hosiery"
    ],
    "wof:name":"William Baker Ltd.",
    "wof:placetype":"venue"
},
  "geometry": {"coordinates":[-3.225195,53.274548],"type":"Point"}
}