{
  "type": "Feature",
  "properties": {
    "iso:country":"GB",
    "sg:address":"68 Winslow Close",
    "sg:city":"Pinner",
    "sg:classifiers":[
        {
            "category":"Autos & Motor Vehicles",
            "subcategory":"Motorcycle Sales",
            "type":"Retail Goods"
        }
    ],
    "sg:postcode":"HA5 2QY",
    "sg:province":"Greater London",
    "sg:tags":[
        "chauffeur",
        "driven",
        "car"
    ],
    "wof:name":"O'Gorman Chauffeured Limousines",
    "wof:placetype":"venue"
},
  "geometry": {"coordinates":[-0.39993,51.582466],"type":"Point"}
}