{
  "type": "Feature",
  "properties": {
    "iso:country":"GB",
    "sg:address":"39a Eagle Centre",
    "sg:city":"Derby",
    "sg:classifiers":[
        {
            "category":"Food & Beverages",
            "subcategory":"Fruits & Vegetables",
            "type":"Retail Goods"
        }
    ],
    "sg:postcode":"DE1 2AZ",
    "sg:province":"Derbyshire",
    "sg:tags":[
        "greengrocer"
    ],
    "wof:name":"Walock,W,",
    "wof:placetype":"venue"
},
  "geometry": {"coordinates":[-1.466009,52.912369],"type":"Point"}
}