{
  "type": "Feature",
  "properties": {
    "addr:full":"2a Gathurst Lane, Shevington Wigan Lancashire WN6 8HA",
    "addr:housenumber":"2a",
    "addr:postcode":"wn6 8ha",
    "addr:street":"Gathurst Lane",
    "iso:country":"GB",
    "sg:address":"2a Gathurst Lane, Shevington",
    "sg:city":"Wigan",
    "sg:classifiers":[
        {
            "category":"Food & Beverages",
            "subcategory":"Meat & Fish",
            "type":"Retail Goods"
        }
    ],
    "sg:postcode":"WN6 8HA",
    "sg:province":"Lancashire",
    "sg:tags":[
        "butcher"
    ],
    "wof:name":"Village Butchers",
    "wof:placetype":"venue"
},
  "geometry": {"coordinates":[-2.694889,53.570549],"type":"Point"}
}