{
  "type": "Feature",
  "properties": {
    "addr:full":"Lombard Street Petworth West Sussex GU28 0AG",
    "addr:postcode":"gu28 0ag",
    "addr:street":"Lombard Street",
    "iso:country":"GB",
    "sg:address":"Lombard Street",
    "sg:city":"Petworth",
    "sg:classifiers":[
        {
            "category":"Shopping",
            "subcategory":"Gifts & Souvenirs",
            "type":"Retail Goods"
        }
    ],
    "sg:postcode":"GU28 0AG",
    "sg:province":"West Sussex",
    "sg:tags":[
        "shop"
    ],
    "wof:name":"The Orange Tree",
    "wof:placetype":"venue"
},
  "geometry": {"coordinates":[-0.609775,50.986961],"type":"Point"}
}