{
  "type": "Feature",
  "properties": {
    "iso:country":"GB",
    "sg:address":"The Street, Aldermaston",
    "sg:city":"Reading",
    "sg:classifiers":[
        {
            "category":"Personal",
            "subcategory":"Barber",
            "type":"Services"
        }
    ],
    "sg:phone":"+44 118 971 3718",
    "sg:postcode":"RG7 4LN",
    "sg:province":"Berkshire",
    "sg:tags":[
        "unisex",
        "men's",
        "hairdresser"
    ],
    "wof:name":"Blades",
    "wof:placetype":"venue"
},
  "geometry": {"coordinates":[-1.153339,51.383804],"type":"Point"}
}