{
  "type": "Feature",
  "properties": {
    "iso:country":"GB",
    "sg:address":"Tourist Information Centre, Guildhall",
    "sg:city":"Worcester",
    "sg:classifiers":[
        {
            "category":"Government",
            "subcategory":"Office",
            "type":"Public Place"
        }
    ],
    "sg:phone":"+44 1905 726311",
    "sg:postcode":"WR1 2EY",
    "sg:province":"Worcestershire",
    "sg:tags":[
        "local"
    ],
    "wof:name":"Worcester City Council",
    "wof:placetype":"venue"
},
  "geometry": {"coordinates":[-2.222274,52.191067],"type":"Point"}
}