{
  "type": "Feature",
  "properties": {
    "iso:country":"GB",
    "sg:address":"Dollar Park, Camelon Road",
    "sg:city":"Falkirk",
    "sg:classifiers":[
        {
            "category":"Organizations",
            "subcategory":"Membership Organization",
            "type":"Services"
        }
    ],
    "sg:phone":"+44 1324 627174",
    "sg:postcode":"FK1 5RU",
    "sg:province":"Falkirk",
    "sg:tags":[
        "club"
    ],
    "wof:name":"Arnotdale Day Centre",
    "wof:placetype":"venue"
},
  "geometry": {"coordinates":[-3.778592,55.987492],"type":"Point"}
}