{
  "type": "Feature",
  "properties": {
    "addr:full":"1 Rose Lane, Ripely Woking Surrey GU23 6NE",
    "addr:housenumber":"1",
    "addr:postcode":"gu23 6ne",
    "addr:street":"Rose Lane",
    "iso:country":"GB",
    "sg:address":"1 Rose Lane, Ripely",
    "sg:city":"Woking",
    "sg:classifiers":[
        {
            "category":"Organizations",
            "subcategory":"Community Association",
            "type":"Services"
        }
    ],
    "sg:phone":"+44 1483 222211",
    "sg:postcode":"GU23 6NE",
    "sg:province":"Surrey",
    "sg:tags":[
        "relation",
        "public"
    ],
    "wof:name":"Cane Communications Ltd.",
    "wof:placetype":"venue"
},
  "geometry": {"coordinates":[-0.477414,51.291973],"type":"Point"}
}