{
  "type": "Feature",
  "properties": {
    "iso:country":"GB",
    "sg:address":"Unit 3, Trinity Ind Est, Millbrook",
    "sg:city":"Southampton",
    "sg:classifiers":[
        {
            "category":"Utilities",
            "subcategory":"Mobile Phone",
            "type":"Services"
        }
    ],
    "sg:phone":"+44 23 8077 2400",
    "sg:postcode":"SO15 0LA",
    "sg:province":"Hampshire",
    "sg:tags":[
        "battery",
        "supplier"
    ],
    "wof:name":"M.B.D Group Ltd",
    "wof:placetype":"venue"
},
  "geometry": {"coordinates":[-1.45269,50.91581],"type":"Point"}
}