{
  "type": "Feature",
  "properties": {
    "addr:full":"431 Bromley Road, Downham Bromley Kent BR1 4PH",
    "addr:housenumber":"431",
    "addr:postcode":"br1 4ph",
    "addr:street":"Bromley Road",
    "iso:country":"GB",
    "sg:address":"431 Bromley Road, Downham",
    "sg:city":"Bromley",
    "sg:classifiers":[
        {
            "category":"Organizations",
            "subcategory":"Non-profit Organization",
            "type":"Services"
        }
    ],
    "sg:phone":"+44 20 8697 7637",
    "sg:postcode":"BR1 4PH",
    "sg:province":"Kent",
    "sg:tags":[
        "organisation",
        "voluntary",
        "charity"
    ],
    "wof:name":"Barnardo's",
    "wof:placetype":"venue"
},
  "geometry": {"coordinates":[-0.0051699998,51.4256477356],"type":"Point"}
}