{
  "type": "Feature",
  "properties": {
    "iso:country":"GB",
    "sg:address":"Talley, Llandeilo",
    "sg:city":"Llanrhystud",
    "sg:classifiers":[
        {
            "category":"Restaurant",
            "type":"Food & Drink"
        }
    ],
    "sg:phone":"+44 1558 685254",
    "sg:postcode":"SA19 7YR",
    "sg:province":"Carmarthenshire",
    "wof:name":"Edwinsford Arms",
    "wof:placetype":"venue"
},
  "geometry": {"coordinates":[-3.9873669147,51.9756393433],"type":"Point"}
}