{
  "type": "Feature",
  "properties": {
    "addr:full":"30 Crowtree Road Sunderland Tyne and Wear SR1 3JU",
    "addr:housenumber":"30",
    "addr:postcode":"sr1 3ju",
    "addr:street":"Crowtree Road",
    "iso:country":"GB",
    "sg:address":"30 Crowtree Road",
    "sg:city":"Sunderland",
    "sg:classifiers":[
        {
            "category":"Shopping",
            "subcategory":"Florist",
            "type":"Retail Goods"
        }
    ],
    "sg:postcode":"SR1 3JU",
    "sg:province":"Tyne and Wear",
    "wof:name":"Pescod's the Florists",
    "wof:placetype":"venue"
},
  "geometry": {"coordinates":[-1.385896,54.904922],"type":"Point"}
}