{
  "type": "Feature",
  "properties": {
    "addr:full":"South Mytton House, Montford Bridge Shrewsbury Shropshire SY4 1EU",
    "addr:postcode":"sy4 1eu",
    "addr:street":"South;Montford Bridge",
    "iso:country":"GB",
    "sg:address":"South Mytton House, Montford Bridge",
    "sg:city":"Shrewsbury",
    "sg:classifiers":[
        {
            "category":"Building & Trades",
            "subcategory":"Pest Control",
            "type":"Services"
        }
    ],
    "sg:phone":"+44 1743 850974",
    "sg:postcode":"SY4 1EU",
    "sg:province":"Shropshire",
    "sg:tags":[
        "vermin"
    ],
    "wof:name":"Crop Protection Systems",
    "wof:placetype":"venue"
},
  "geometry": {"coordinates":[-2.837428093,52.729309082],"type":"Point"}
}