{
  "type": "Feature",
  "properties": {
    "addr:full":"Linfit Hall Garage, Banks Road Linthwaite Huddersfield West Yorkshire HD7 5LW",
    "addr:postcode":"hd7 5lw",
    "addr:street":"Banks Road;West",
    "iso:country":"GB",
    "sg:address":"Linfit Hall Garage, Banks Road Linthwaite",
    "sg:city":"Huddersfield",
    "sg:classifiers":[
        {
            "category":"Retail",
            "subcategory":"Auto Repair",
            "type":"Services"
        }
    ],
    "sg:phone":"+44 1484 842514",
    "sg:postcode":"HD7 5LW",
    "sg:province":"West Yorkshire",
    "sg:tags":[
        "modification",
        "garage"
    ],
    "wof:name":"J B Sykes Motors",
    "wof:placetype":"venue"
},
  "geometry": {"coordinates":[-1.8474090099,53.6258544922],"type":"Point"}
}