{
  "type": "Feature",
  "properties": {
    "addr:full":"90 Beedell Avenue Westcliff On Sea Essex SS0 9JS",
    "addr:housenumber":"90",
    "addr:postcode":"ss0 9js",
    "addr:street":"Beedell Avenue",
    "iso:country":"GB",
    "sg:address":"90 Beedell Avenue",
    "sg:city":"Westcliff On Sea",
    "sg:classifiers":[
        {
            "category":"Building & Trades",
            "subcategory":"Construction",
            "type":"Services"
        }
    ],
    "sg:phone":"+44 1702 340813",
    "sg:postcode":"SS0 9JS",
    "sg:province":"Essex",
    "sg:tags":[
        "builder"
    ],
    "wof:name":"Owen Construction & Property Maintenance",
    "wof:placetype":"venue"
},
  "geometry": {"coordinates":[0.690799,51.54781],"type":"Point"}
}