{
  "type": "Feature",
  "properties": {
    "addr:full":"Brackley Service Station Brackley Buckinghamshire NN13 5SZ",
    "addr:postcode":"nn13 5sz",
    "addr:street":"Brackley",
    "iso:country":"GB",
    "sg:address":"Brackley Service Station",
    "sg:city":"Brackley",
    "sg:classifiers":[
        {
            "category":"Autos & Motor Vehicles",
            "subcategory":"Fuel & Gas Station",
            "type":"Retail Goods"
        }
    ],
    "sg:phone":"+44 1280 704757",
    "sg:postcode":"NN13 5SZ",
    "sg:province":"Buckinghamshire",
    "sg:tags":[
        "hr",
        "petrol"
    ],
    "wof:name":"B P Express Shopping Ltd.",
    "wof:placetype":"venue"
},
  "geometry": {"coordinates":[-1.0692089796,52.0671691895],"type":"Point"}
}