{
  "type": "Feature",
  "properties": {
    "iso:country":"GB",
    "sg:address":"Unit 1 Laurencekirk Business Pk, Aberdeen Rd",
    "sg:city":"Laurencekirk",
    "sg:classifiers":[
        {
            "category":"Shopping",
            "subcategory":"Crafts & Fabrics",
            "type":"Retail Goods"
        }
    ],
    "sg:postcode":"AB30 1EY",
    "sg:province":"Aberdeenshire",
    "sg:tags":[
        "ceramic"
    ],
    "wof:name":"Christie,Cindy,",
    "wof:placetype":"venue"
},
  "geometry": {"coordinates":[-2.469374,56.830662],"type":"Point"}
}