{
  "type": "Feature",
  "properties": {
    "iso:country":"GB",
    "sg:address":"Tolpits Lane",
    "sg:city":"Watford",
    "sg:classifiers":[
        {
            "category":"Organizations",
            "subcategory":"Non-profit Organization",
            "type":"Services"
        }
    ],
    "sg:phone":"+44 1923 425000",
    "sg:postcode":"WD18 9RN",
    "sg:province":"Hertfordshire",
    "sg:tags":[
        "fundraising",
        "charity"
    ],
    "wof:name":"Camelot Group Plc",
    "wof:placetype":"venue"
},
  "geometry": {"coordinates":[-0.416974,51.645859],"type":"Point"}
}