{
  "type": "Feature",
  "properties": {
    "addr:full":"6 Cavendish Place London Greater London W1G 9NB",
    "addr:housenumber":"6",
    "addr:postcode":"w1g 9nb",
    "addr:street":"Cavendish Place",
    "iso:country":"GB",
    "sg:address":"6 Cavendish Place",
    "sg:city":"London",
    "sg:classifiers":[
        {
            "category":"Shopping",
            "subcategory":"Clothing, Apparel, & Fashions",
            "type":"Retail Goods"
        }
    ],
    "sg:phone":"+44 20 7580 6066",
    "sg:postcode":"W1G 9NB",
    "sg:province":"Greater London",
    "sg:tags":[
        "clothing"
    ],
    "wof:name":"Escada (U K) Ltd.",
    "wof:placetype":"venue"
},
  "geometry": {"coordinates":[-0.143581003,51.517364502],"type":"Point"}
}