{
  "type": "Feature",
  "properties": {
    "iso:country":"GB",
    "sg:address":"76 Coventry Road",
    "sg:city":"Hinckley",
    "sg:classifiers":[
        {
            "category":"Food & Beverages",
            "subcategory":"Liquor & Beverages",
            "type":"Retail Goods"
        }
    ],
    "sg:postcode":"LE10 0JT",
    "sg:province":"Leicestershire",
    "sg:tags":[
        "beer",
        "spirit",
        "wines"
    ],
    "wof:name":"Onkar Stores",
    "wof:placetype":"venue"
},
  "geometry": {"coordinates":[-1.378344,52.539249],"type":"Point"}
}