{
  "type": "Feature",
  "properties": {
    "iso:country":"GB",
    "sg:address":"40 Halifax Road",
    "sg:city":"Todmorden",
    "sg:classifiers":[
        {
            "category":"Real Estate",
            "subcategory":"Architect",
            "type":"Services"
        }
    ],
    "sg:phone":"+44 1706 814885",
    "sg:postcode":"OL14 5QG",
    "sg:province":"Lancashire",
    "wof:name":"Deakin Design Associates",
    "wof:placetype":"venue"
},
  "geometry": {"coordinates":[-2.094835,53.713737],"type":"Point"}
}