{
  "type": "Feature",
  "properties": {
    "iso:country":"GB",
    "sg:address":"Lordshill Health Centre, Lordshill District Centre",
    "sg:city":"Southampton",
    "sg:classifiers":[
        {
            "category":"Health Services",
            "subcategory":"Doctor",
            "type":"Services"
        }
    ],
    "sg:phone":"+44 23 8073 8144",
    "sg:postcode":"SO16 8HY",
    "sg:province":"Hampshire",
    "sg:tags":[
        "practitioners"
    ],
    "wof:name":"Billington, T R M",
    "wof:placetype":"venue"
},
  "geometry": {"coordinates":[-1.448994,50.942394],"type":"Point"}
}