{
  "type": "Feature",
  "properties": {
    "addr:full":"51 Terrace Road Mansfield Nottinghamshire NG18 2BP",
    "addr:housenumber":"51",
    "addr:postcode":"ng18 2bp",
    "addr:street":"Terrace Road",
    "iso:country":"GB",
    "sg:address":"51 Terrace Road",
    "sg:city":"Mansfield",
    "sg:classifiers":[
        {
            "category":"Wholesale",
            "subcategory":"Office Equipment",
            "type":"Manufacturing & Wholesale Goods"
        }
    ],
    "sg:phone":"+44 1623 655482",
    "sg:postcode":"NG18 2BP",
    "sg:province":"Nottinghamshire",
    "sg:tags":[
        "register",
        "cash",
        "accessory"
    ],
    "wof:name":"Mansfield Cash Registers",
    "wof:placetype":"venue"
},
  "geometry": {"coordinates":[-1.192311,53.149021],"type":"Point"}
}