{
  "type": "Feature",
  "properties": {
    "addr:full":"13 Fleet Walk Shopping Centre, Fleet Street Torquay Devon TQ1 1DB",
    "addr:housenumber":"13",
    "addr:postcode":"tq1 1db",
    "addr:street":"Fleet Walk Shopping;Fleet Street",
    "iso:country":"GB",
    "sg:address":"13 Fleet Walk Shopping Centre, Fleet Street",
    "sg:city":"Torquay",
    "sg:classifiers":[
        {
            "category":"Shopping",
            "subcategory":"Clothing, Apparel, & Fashions",
            "type":"Retail Goods"
        }
    ],
    "sg:phone":"+44 1803 291622",
    "sg:postcode":"TQ1 1DB",
    "sg:province":"Devon",
    "sg:tags":[
        "shop"
    ],
    "wof:name":"New Look",
    "wof:placetype":"venue"
},
  "geometry": {"coordinates":[-3.52612,50.463112],"type":"Point"}
}