{
  "type": "Feature",
  "properties": {
    "iso:country":"GB",
    "sg:address":"96 Windmill Road",
    "sg:city":"Sunbury-on-thames",
    "sg:classifiers":[
        {
            "category":"Shopping",
            "subcategory":"Department Store",
            "type":"Retail Goods"
        }
    ],
    "sg:postcode":"TW16 7HB",
    "sg:province":"Surrey",
    "wof:name":"Windmill Stores",
    "wof:placetype":"venue"
},
  "geometry": {"coordinates":[-0.430819,51.416931],"type":"Point"}
}