{
  "type": "Feature",
  "properties": {
    "addr:full":"Grange Farm, Wetwang Driffield East Riding of Yorkshire YO25 3EZ",
    "addr:postcode":"yo25 3ez",
    "addr:street":"Wetwang",
    "iso:country":"GB",
    "sg:address":"Grange Farm, Wetwang",
    "sg:city":"Driffield",
    "sg:classifiers":[
        {
            "category":"Farming",
            "subcategory":"Crops",
            "type":"Manufacturing & Wholesale Goods"
        },
        {
            "category":"Farming",
            "subcategory":"Livestock Farm",
            "type":"Manufacturing & Wholesale Goods"
        }
    ],
    "sg:phone":"+44 1377 236254",
    "sg:postcode":"YO25 3EZ",
    "sg:province":"East Riding of Yorkshire",
    "sg:tags":[
        "arable",
        "others"
    ],
    "wof:name":"F W Hardy",
    "wof:placetype":"venue"
},
  "geometry": {"coordinates":[-0.436299,54.008968],"type":"Point"}
}