{
  "type": "Feature",
  "properties": {
    "addr:full":"81 Laburnum Gro Stirling Stirling FK8 2PR",
    "addr:housenumber":"81",
    "addr:postcode":"fk8 2pr",
    "addr:street":"Laburnum Gro",
    "iso:country":"GB",
    "sg:address":"81 Laburnum Gro",
    "sg:city":"Stirling",
    "sg:classifiers":[
        {
            "category":"Government",
            "subcategory":"Office",
            "type":"Public Place"
        }
    ],
    "sg:phone":"+44 1786 446696",
    "sg:postcode":"FK8 2PR",
    "sg:province":"Stirling",
    "sg:tags":[
        "education",
        "agency",
        "authority"
    ],
    "wof:name":"Catholic Education Commission",
    "wof:placetype":"venue"
},
  "geometry": {"coordinates":[-3.950057,56.106052],"type":"Point"}
}