{
  "type": "Feature",
  "properties": {
    "addr:full":"12 Caledion Rd Keighley West Yorkshire BD21 3JP",
    "addr:housenumber":"12",
    "addr:postcode":"bd21 3jp",
    "addr:street":"Caledion Rd",
    "iso:country":"GB",
    "sg:address":"12 Caledion Rd",
    "sg:city":"Keighley",
    "sg:classifiers":[
        {
            "category":"Professional",
            "subcategory":"Detective & Security Services",
            "type":"Services"
        }
    ],
    "sg:phone":"+44 70 7122 5279",
    "sg:postcode":"BD21 3JP",
    "sg:province":"West Yorkshire",
    "wof:name":"Smg Security Services",
    "wof:placetype":"venue"
},
  "geometry": {"coordinates":[-1.902499,53.873383],"type":"Point"}
}