{
  "type": "Feature",
  "properties": {
    "iso:country":"GB",
    "sg:address":"Off Davy Way, Llay",
    "sg:city":"Wrexham",
    "sg:classifiers":[
        {
            "category":"Home & Garden",
            "subcategory":"Household Appliances",
            "type":"Retail Goods"
        }
    ],
    "sg:phone":"+44 1978 855909",
    "sg:postcode":"LL12 0PG",
    "sg:province":"Wrexham",
    "sg:tags":[
        "electrical",
        "domestic"
    ],
    "wof:name":"Park Electrical Services",
    "wof:placetype":"venue"
},
  "geometry": {"coordinates":[-3.000814,53.093639],"type":"Point"}
}