{
  "type": "Feature",
  "properties": {
    "iso:country":"GB",
    "sg:address":"179-181 Wimborne Road West",
    "sg:city":"Wimborne",
    "sg:classifiers":[
        {
            "category":"Health Services",
            "subcategory":"Nursing And Care Facility",
            "type":"Services"
        }
    ],
    "sg:phone":"+44 1202 871172",
    "sg:postcode":"BH21 2DJ",
    "sg:province":"Dorset",
    "sg:tags":[
        "home"
    ],
    "wof:name":"Wimborne Nursing Home",
    "wof:placetype":"venue"
},
  "geometry": {"coordinates":[-1.937799,50.802628],"type":"Point"}
}