{
  "type": "Feature",
  "properties": {
    "iso:country":"GB",
    "sg:address":"224 Soho Road",
    "sg:city":"Birmingham",
    "sg:classifiers":[
        {
            "category":"Food & Beverages",
            "subcategory":"Meat & Fish",
            "type":"Retail Goods"
        }
    ],
    "sg:postcode":"B21 9LR",
    "sg:province":"West Midlands",
    "sg:tags":[
        "butcher"
    ],
    "wof:name":"Walter Smith (Birmingham) Ltd.",
    "wof:placetype":"venue"
},
  "geometry": {"coordinates":[-1.9356820583,52.5036888123],"type":"Point"}
}