{
  "type": "Feature",
  "properties": {
    "addr:full":"Unit 4 Poole Dorset BH12 4ND",
    "addr:housenumber":"unit 4",
    "addr:postcode":"bh12 4nd",
    "iso:country":"GB",
    "sg:address":"Unit 4",
    "sg:city":"Poole",
    "sg:classifiers":[
        {
            "category":"Retail",
            "subcategory":"Auto Repair",
            "type":"Services"
        }
    ],
    "sg:postcode":"BH12 4ND",
    "sg:province":"Dorset",
    "sg:tags":[
        "car",
        "sprayer",
        "painter"
    ],
    "wof:name":"P J S Autobody (1998)",
    "wof:placetype":"venue"
},
  "geometry": {"coordinates":[-1.9476200342,50.7437896729],"type":"Point"}
}