{
  "type": "Feature",
  "properties": {
    "iso:country":"GB",
    "sg:address":"190 Bridge Road, Sarisbury Green",
    "sg:city":"Southampton",
    "sg:classifiers":[
        {
            "category":"Health Services",
            "subcategory":"Health Practitioner",
            "type":"Services"
        }
    ],
    "sg:phone":"+44 1489 574670",
    "sg:postcode":"SO31 7ED",
    "sg:province":"Hampshire",
    "sg:tags":[
        "hypnotherapists"
    ],
    "wof:name":"Alanna Steele",
    "wof:placetype":"venue"
},
  "geometry": {"coordinates":[-1.2908689976,50.876991272],"type":"Point"}
}