{
  "type": "Feature",
  "properties": {
    "addr:full":"Scatterill Close, Bradwell Milton Keynes Buckinghamshire MK13 9EZ",
    "addr:postcode":"mk13 9ez",
    "addr:street":"Scatterill Close",
    "iso:country":"GB",
    "sg:address":"Scatterill Close, Bradwell",
    "sg:city":"Milton Keynes",
    "sg:classifiers":[
        {
            "category":"Education",
            "subcategory":"School",
            "type":"Public Place"
        }
    ],
    "sg:phone":"+44 1908 321646",
    "sg:postcode":"MK13 9EZ",
    "sg:province":"Buckinghamshire",
    "sg:tags":[
        "local",
        "authority"
    ],
    "wof:name":"Priory Common First School",
    "wof:placetype":"venue"
},
  "geometry": {"coordinates":[-0.783954,52.051079],"type":"Point"}
}