{
  "type": "Feature",
  "properties": {
    "addr:full":"1 Bannockburn Road Stirling Falkirk FK7 0BP",
    "addr:housenumber":"1",
    "addr:postcode":"fk7 0bp",
    "addr:street":"Bannockburn Road",
    "iso:country":"GB",
    "sg:address":"1 Bannockburn Road",
    "sg:city":"Stirling",
    "sg:classifiers":[
        {
            "category":"Building & Trades",
            "subcategory":"Construction",
            "type":"Services"
        }
    ],
    "sg:phone":"+44 1786 472385",
    "sg:postcode":"FK7 0BP",
    "sg:province":"Falkirk",
    "sg:tags":[
        "decorator",
        "painter"
    ],
    "wof:name":"G C Peebles & Son",
    "wof:placetype":"venue"
},
  "geometry": {"coordinates":[-3.936934948,56.1004219055],"type":"Point"}
}