{
  "type": "Feature",
  "properties": {
    "iso:country":"GB",
    "sg:address":"Suite 2, 9 West End, Kemsing",
    "sg:city":"Sevenoaks",
    "sg:classifiers":[
        {
            "category":"Professional",
            "subcategory":"Accounting & Tax Preparation",
            "type":"Services"
        }
    ],
    "sg:phone":"+44 1732 762886",
    "sg:postcode":"TN15 6PX",
    "sg:province":"Kent",
    "sg:tags":[
        "accountant"
    ],
    "wof:name":"Coplestons",
    "wof:placetype":"venue"
},
  "geometry": {"coordinates":[0.228493,51.30619],"type":"Point"}
}