{
  "type": "Feature",
  "properties": {
    "addr:full":"152 Walton Street London Greater London SW3 2JJ",
    "addr:housenumber":"152",
    "addr:postcode":"sw3 2jj",
    "addr:street":"Walton Street",
    "iso:country":"GB",
    "sg:address":"152 Walton Street",
    "sg:city":"London",
    "sg:classifiers":[
        {
            "category":"Home & Garden",
            "subcategory":"Carpets & Floor Coverings",
            "type":"Retail Goods"
        }
    ],
    "sg:phone":"+44 20 7581 2332",
    "sg:postcode":"SW3 2JJ",
    "sg:province":"Greater London",
    "sg:tags":[
        "carpets",
        "rug",
        "matting"
    ],
    "wof:name":"Orientalist Carpets",
    "wof:placetype":"venue"
},
  "geometry": {"coordinates":[-0.167389,51.494671],"type":"Point"}
}