{
  "type": "Feature",
  "properties": {
    "iso:country":"GB",
    "sg:address":"33 Little Meadows, Loughton",
    "sg:city":"Milton Keynes",
    "sg:classifiers":[
        {
            "category":"Building & Trades",
            "subcategory":"Construction",
            "type":"Services"
        }
    ],
    "sg:phone":"+44 1908 660806",
    "sg:postcode":"MK5 8EH",
    "sg:province":"Buckinghamshire",
    "sg:tags":[
        "tile",
        "fitting",
        "tiling",
        "laying",
        "contractor"
    ],
    "wof:name":"K A Ceramics",
    "wof:placetype":"venue"
},
  "geometry": {"coordinates":[-0.777754,52.025108],"type":"Point"}
}