{
  "type": "Feature",
  "properties": {
    "addr:full":"Pelham Av Nottingham Nottinghamshire NG5 1AL",
    "addr:postcode":"ng5 1al",
    "addr:street":"Pelham Av",
    "iso:country":"GB",
    "sg:address":"Pelham Av",
    "sg:city":"Nottingham",
    "sg:classifiers":[
        {
            "category":"Social Services",
            "subcategory":"Adult Care",
            "type":"Services"
        }
    ],
    "sg:phone":"+44 115 953 1440",
    "sg:postcode":"NG5 1AL",
    "sg:province":"Nottinghamshire",
    "sg:tags":[
        "day",
        "centre"
    ],
    "wof:name":"Clumber Day Centre",
    "wof:placetype":"venue"
},
  "geometry": {"coordinates":[-1.1544259787,52.9698562622],"type":"Point"}
}