{
  "type": "Feature",
  "properties": {
    "iso:country":"GB",
    "sg:address":"86 Woolridge Way, Loddiges Rd",
    "sg:city":"London",
    "sg:classifiers":[
        {
            "category":"Building & Trades",
            "subcategory":"Cleaning & Sanitation",
            "type":"Services"
        }
    ],
    "sg:postcode":"E9 6PR",
    "sg:province":"Greater London",
    "sg:tags":[
        "cleaner",
        "window"
    ],
    "wof:name":"Georgiou,Michael,",
    "wof:placetype":"venue"
},
  "geometry": {"coordinates":[-0.049304001,51.543094635],"type":"Point"}
}