{
  "type": "Feature",
  "properties": {
    "iso:country":"GB",
    "sg:address":"Sedgefield Industrial Estate, Salters Lane, Sedgefield",
    "sg:city":"Stockton-on-tees",
    "sg:classifiers":[
        {
            "category":"Food & Beverages",
            "subcategory":"Meat & Fish",
            "type":"Retail Goods"
        }
    ],
    "sg:phone":"+44 1740 621122",
    "sg:postcode":"TS21 3EE",
    "sg:province":"Durham",
    "sg:tags":[
        "butcher"
    ],
    "wof:name":"George Bolam (Foods) Ltd.",
    "wof:placetype":"venue"
},
  "geometry": {"coordinates":[-1.447875,54.662003],"type":"Point"}
}