{
  "type": "Feature",
  "properties": {
    "iso:country":"GB",
    "sg:address":"6 Tarrant Street",
    "sg:city":"Arundel",
    "sg:classifiers":[
        {
            "category":"Real Estate",
            "subcategory":"Real Estate Agent",
            "type":"Services"
        }
    ],
    "sg:phone":"+44 1903 883899",
    "sg:postcode":"BN18 9DG",
    "sg:province":"West Sussex",
    "wof:name":"Dockerills",
    "wof:placetype":"venue"
},
  "geometry": {"coordinates":[-0.555249,50.854362],"type":"Point"}
}