{
  "type": "Feature",
  "properties": {
    "addr:full":"25 Lidgate Crescent, Langthwaite Grange Industrial Es Pontefract West Yorkshire WF9 3NR",
    "addr:housenumber":"25",
    "addr:postcode":"wf9 3nr",
    "addr:street":"Lidgate Crescent Langthwaite Grange Industrial;West",
    "iso:country":"GB",
    "sg:address":"25 Lidgate Crescent, Langthwaite Grange Industrial Es",
    "sg:city":"Pontefract",
    "sg:classifiers":[
        {
            "category":"Manufacturing",
            "subcategory":"Motor Vehicles & Parts",
            "type":"Manufacturing & Wholesale Goods"
        }
    ],
    "sg:phone":"+44 1977 647455",
    "sg:postcode":"WF9 3NR",
    "sg:province":"West Yorkshire",
    "sg:tags":[
        "bearing"
    ],
    "wof:name":"Hayley Bearings",
    "wof:placetype":"venue"
},
  "geometry": {"coordinates":[-1.311809,53.59309],"type":"Point"}
}