{
  "type": "Feature",
  "properties": {
    "addr:full":"Cleveland House, College Road, Hanley Stoke-on-trent Staffordshire ST1 4DQ",
    "addr:postcode":"staffordshire st1 4dq",
    "addr:street":"College Road",
    "iso:country":"GB",
    "sg:address":"Cleveland House, College Road, Hanley",
    "sg:city":"Stoke-on-trent",
    "sg:classifiers":[
        {
            "category":"Education",
            "subcategory":"Special Training",
            "type":"Public Place"
        }
    ],
    "sg:phone":"+44 1782 279121",
    "sg:postcode":"ST1 4DQ",
    "sg:province":"Staffordshire",
    "sg:tags":[
        "product",
        "centre"
    ],
    "wof:name":"Project Management (Staffordshire) Ltd.",
    "wof:placetype":"venue"
},
  "geometry": {"coordinates":[-2.1800940037,53.018371582],"type":"Point"}
}