{
  "type": "Feature",
  "properties": {
    "iso:country":"GB",
    "sg:address":"Hay Street, Sheepfolds Industrial Estate",
    "sg:city":"Sunderland",
    "sg:classifiers":[
        {
            "category":"Wholesale",
            "subcategory":"Scrap",
            "type":"Manufacturing & Wholesale Goods"
        }
    ],
    "sg:phone":"+44 191 565 9316",
    "sg:postcode":"SR5 1BG",
    "sg:province":"Tyne and Wear",
    "sg:tags":[
        "waste",
        "metal"
    ],
    "wof:name":"Doyles Scrap Metal Processors",
    "wof:placetype":"venue"
},
  "geometry": {"coordinates":[-1.3857489824,54.9137496948],"type":"Point"}
}