{
  "type": "Feature",
  "properties": {
    "iso:country":"GB",
    "sg:address":"177 Barnsley Street",
    "sg:city":"Wigan",
    "sg:classifiers":[
        {
            "category":"Personal",
            "subcategory":"Beauty Salon",
            "type":"Services"
        }
    ],
    "sg:phone":"+44 1942 242379",
    "sg:postcode":"WN6 7HF",
    "sg:province":"Lancashire",
    "sg:tags":[
        "unisex",
        "hairdresser"
    ],
    "wof:name":"Star Centre",
    "wof:placetype":"venue"
},
  "geometry": {"coordinates":[-2.6422019005,53.5566978455],"type":"Point"}
}