{
  "type": "Feature",
  "properties": {
    "addr:full":"43-45 Acre Lane London Greater London SW2 5TN",
    "addr:housenumber":"43-45",
    "addr:postcode":"sw2 5tn",
    "addr:street":"Acre Lane",
    "iso:country":"GB",
    "sg:address":"43-45 Acre Lane",
    "sg:city":"London",
    "sg:classifiers":[
        {
            "category":"Retail",
            "subcategory":"Repair Shop",
            "type":"Services"
        },
        {
            "category":"Building & Trades",
            "subcategory":"Construction",
            "type":"Services"
        }
    ],
    "sg:phone":"+44 20 7274 2040",
    "sg:postcode":"SW2 5TN",
    "sg:province":"Greater London",
    "sg:tags":[
        "roofing",
        "decorator",
        "maintenance",
        "painter"
    ],
    "wof:name":"Sidevale (Building Contractors) Ltd.",
    "wof:placetype":"venue"
},
  "geometry": {"coordinates":[-0.120925,51.459846],"type":"Point"}
}