{
  "type": "Feature",
  "properties": {
    "addr:full":"132 Nottingham Road Ripley Derbyshire DE5 3AX",
    "addr:housenumber":"132",
    "addr:postcode":"de5 3ax",
    "addr:street":"Nottingham Road",
    "iso:country":"GB",
    "sg:address":"132 Nottingham Road",
    "sg:city":"Ripley",
    "sg:classifiers":[
        {
            "category":"Building & Trades",
            "subcategory":"Equipment Rental",
            "type":"Services"
        }
    ],
    "sg:phone":"+44 1773 740233",
    "sg:postcode":"DE5 3AX",
    "sg:province":"Derbyshire",
    "sg:tags":[
        "hire",
        "centre"
    ],
    "wof:name":"Dorinwell Ltd.",
    "wof:placetype":"venue"
},
  "geometry": {"coordinates":[-1.395037055,53.0523490906],"type":"Point"}
}