{
  "type": "Feature",
  "properties": {
    "iso:country":"GB",
    "sg:address":"Highlands Farm, Highlands Lane",
    "sg:city":"Henley On Thames",
    "sg:classifiers":[
        {
            "category":"Utilities",
            "subcategory":"Fuel Oil & Lpg",
            "type":"Services"
        }
    ],
    "sg:phone":"+44 1491 415400",
    "sg:postcode":"RG9 4PR",
    "sg:province":"Berkshire",
    "sg:tags":[
        "gas"
    ],
    "wof:name":"Quad Consulting",
    "wof:placetype":"venue"
},
  "geometry": {"coordinates":[-0.9031890035,51.5352973938],"type":"Point"}
}