{
  "type": "Feature",
  "properties": {
    "addr:full":"15 Green Acres Gro Halifax West Yorkshire HX3 7RN",
    "addr:housenumber":"15",
    "addr:postcode":"hx3 7rn",
    "addr:street":"Green Acres",
    "iso:country":"GB",
    "sg:address":"15 Green Acres Gro",
    "sg:city":"Halifax",
    "sg:classifiers":[
        {
            "category":"Building & Trades",
            "subcategory":"Construction",
            "type":"Services"
        }
    ],
    "sg:postcode":"HX3 7RN",
    "sg:province":"West Yorkshire",
    "sg:tags":[
        "builder"
    ],
    "wof:name":"Ashfield Construction",
    "wof:placetype":"venue"
},
  "geometry": {"coordinates":[-1.826502,53.739052],"type":"Point"}
}