{
  "type": "Feature",
  "properties": {
    "iso:country":"GB",
    "sg:address":"209 Albany Road",
    "sg:city":"Cardiff",
    "sg:classifiers":[
        {
            "category":"Home & Garden",
            "subcategory":"Household Appliances",
            "type":"Retail Goods"
        }
    ],
    "sg:postcode":"CF24 3NU",
    "sg:province":"Cardiff",
    "sg:tags":[
        "electrical"
    ],
    "wof:name":"Simelex",
    "wof:placetype":"venue"
},
  "geometry": {"coordinates":[-3.1608140469,51.4936027527],"type":"Point"}
}