{
  "type": "Feature",
  "properties": {
    "iso:country":"GB",
    "sg:address":"1 Church Street",
    "sg:city":"Llantwit Major",
    "sg:classifiers":[
        {
            "category":"Retail",
            "subcategory":"Veterinary Services",
            "type":"Services"
        }
    ],
    "sg:phone":"+44 1446 796961",
    "sg:postcode":"CF61 1SB",
    "sg:province":"The Vale of Glamorgan",
    "sg:tags":[
        "surgeon"
    ],
    "wof:name":"Animal Health Centre",
    "wof:placetype":"venue"
},
  "geometry": {"coordinates":[-3.486472,51.408089],"type":"Point"}
}