{
  "type": "Feature",
  "properties": {
    "addr:full":"10 Gunville Road, Carisbrooke Newport Isle of Wight PO30 5LB",
    "addr:housenumber":"10",
    "addr:postcode":"po30 5lb",
    "addr:street":"Gunville Road",
    "iso:country":"GB",
    "sg:address":"10 Gunville Road, Carisbrooke",
    "sg:city":"Newport",
    "sg:classifiers":[
        {
            "category":"Professional",
            "subcategory":"Art Services",
            "type":"Services"
        }
    ],
    "sg:phone":"+44 1983 528573",
    "sg:postcode":"PO30 5LB",
    "sg:province":"Isle of Wight",
    "sg:tags":[
        "photographer"
    ],
    "wof:name":"The Mobile Portrait Studio",
    "wof:placetype":"venue"
},
  "geometry": {"coordinates":[-1.3181359768,50.6936416626],"type":"Point"}
}