{
  "type": "Feature",
  "properties": {
    "iso:country":"GB",
    "sg:address":"Old Methodist Chapel, Tod Point Rd",
    "sg:city":"Redcar",
    "sg:classifiers":[
        {
            "category":"Building & Trades",
            "subcategory":"Cleaning & Sanitation",
            "type":"Services"
        }
    ],
    "sg:phone":"+44 1642 470707",
    "sg:postcode":"TS10 5AU",
    "sg:province":"North Yorkshire",
    "sg:tags":[
        "toilet",
        "portable"
    ],
    "wof:name":"Phone-A-Loo",
    "wof:placetype":"venue"
},
  "geometry": {"coordinates":[-1.068344,54.614059],"type":"Point"}
}