{
  "type": "Feature",
  "properties": {
    "addr:full":"204 Nithsdale Road Glasgow Glasgow City G41 5EU",
    "addr:housenumber":"204",
    "addr:postcode":"g41 5eu",
    "addr:street":"Nithsdale Road",
    "iso:country":"GB",
    "sg:address":"204 Nithsdale Road",
    "sg:city":"Glasgow",
    "sg:classifiers":[
        {
            "category":"Education",
            "subcategory":"School",
            "type":"Public Place"
        }
    ],
    "sg:phone":"+44 141 423 3703",
    "sg:postcode":"G41 5EU",
    "sg:province":"Glasgow City",
    "sg:tags":[
        "independent",
        "preparatory"
    ],
    "wof:name":"Craigholme Junior School",
    "wof:placetype":"venue"
},
  "geometry": {"coordinates":[-4.2873711586,55.8419647217],"type":"Point"}
}