{
  "type": "Feature",
  "properties": {
    "addr:full":"3 Broadleys Road Stirling Falkirk FK7 7TP",
    "addr:housenumber":"3",
    "addr:postcode":"fk7 7tp",
    "addr:street":"Broadleys Road",
    "iso:country":"GB",
    "sg:address":"3 Broadleys Road",
    "sg:city":"Stirling",
    "sg:classifiers":[
        {
            "category":"Retail",
            "subcategory":"Repair Shop",
            "type":"Services"
        }
    ],
    "sg:postcode":"FK7 7TP",
    "sg:province":"Falkirk",
    "sg:tags":[
        "radio",
        "television",
        "video"
    ],
    "wof:name":"C N G Television Services",
    "wof:placetype":"venue"
},
  "geometry": {"coordinates":[-3.9190690517,56.1166992188],"type":"Point"}
}