{
  "type": "Feature",
  "properties": {
    "addr:full":"38 Bempton Lane Bridlington East Riding of Yorkshire YO16 6HE",
    "addr:housenumber":"38",
    "addr:postcode":"yo16 6he",
    "addr:street":"Bempton Lane",
    "iso:country":"GB",
    "sg:address":"38 Bempton Lane",
    "sg:city":"Bridlington",
    "sg:classifiers":[
        {
            "category":"Building & Trades",
            "subcategory":"Plumbing",
            "type":"Services"
        }
    ],
    "sg:phone":"+44 1262 675667",
    "sg:postcode":"YO16 6HE",
    "sg:province":"East Riding of Yorkshire",
    "sg:tags":[
        "plumber",
        "heating"
    ],
    "wof:name":"SIMON M BUTTERFINT",
    "wof:placetype":"venue"
},
  "geometry": {"coordinates":[-0.1961590052,54.1020088196],"type":"Point"}
}