{
  "type": "Feature",
  "properties": {
    "addr:full":"2 Black Swan Court, 69 Westgate Road Newcastle-upon-tyne Tyne and Wear NE1 1SG",
    "addr:housenumber":"2;69",
    "addr:postcode":"ne1 1sg",
    "addr:street":"Black Swan;Westgate Road",
    "iso:country":"GB",
    "sg:address":"2 Black Swan Court, 69 Westgate Road",
    "sg:city":"Newcastle-upon-tyne",
    "sg:classifiers":[
        {
            "category":"Shopping",
            "subcategory":"Music",
            "type":"Retail Goods"
        }
    ],
    "sg:phone":"+44 191 230 2500",
    "sg:postcode":"NE1 1SG",
    "sg:province":"Tyne and Wear",
    "sg:tags":[
        "dvd",
        "record",
        "tape",
        "vinyl",
        "cd"
    ],
    "wof:name":"Roots Music",
    "wof:placetype":"venue"
},
  "geometry": {"coordinates":[-1.6123689413,54.9779167175],"type":"Point"}
}