{
  "type": "Feature",
  "properties": {
    "iso:country":"GB",
    "sg:address":"126 Morthen Road, Wickersley",
    "sg:city":"Rotherham",
    "sg:classifiers":[
        {
            "category":"Manufacturing",
            "subcategory":"Building Materials",
            "type":"Manufacturing & Wholesale Goods"
        }
    ],
    "sg:phone":"+44 1709 703717",
    "sg:postcode":"S66 1EA",
    "sg:province":"South Yorkshire",
    "sg:tags":[
        "tarmac",
        "asphalt"
    ],
    "wof:name":"Brown's Surfacing Tarmac & Asphalt Contractors",
    "wof:placetype":"venue"
},
  "geometry": {"coordinates":[-1.276123,53.411915],"type":"Point"}
}