{
  "type": "Feature",
  "properties": {
    "iso:country":"GB",
    "sg:address":"1 Moseley Street, Digbeth",
    "sg:city":"Birmingham",
    "sg:classifiers":[
        {
            "category":"Shopping",
            "subcategory":"Crafts & Fabrics",
            "type":"Retail Goods"
        }
    ],
    "sg:phone":"+44 121 622 6102",
    "sg:postcode":"B5 6JX",
    "sg:province":"West Midlands",
    "sg:tags":[
        "shop"
    ],
    "wof:name":"Barry's Fabric Market",
    "wof:placetype":"venue"
},
  "geometry": {"coordinates":[-1.887889,52.471909],"type":"Point"}
}