{
  "type": "Feature",
  "properties": {
    "addr:full":"C/o Durrants, 24 Wellington Business Park Crowthorne Berkshire RG45 6LS",
    "addr:housenumber":"24",
    "addr:postcode":"rg45 6ls",
    "addr:street":"C;Wellington Business Park",
    "iso:country":"GB",
    "sg:address":"C/o Durrants, 24 Wellington Business Park",
    "sg:city":"Crowthorne",
    "sg:classifiers":[
        {
            "category":"Professional",
            "subcategory":"Accounting & Tax Preparation",
            "type":"Services"
        }
    ],
    "sg:postcode":"RG45 6LS",
    "sg:province":"Berkshire",
    "sg:tags":[
        "accountant"
    ],
    "wof:name":"Durrants Ltd.",
    "wof:placetype":"venue"
},
  "geometry": {"coordinates":[-0.8019890189,51.3699493408],"type":"Point"}
}