{
  "type": "Feature",
  "properties": {
    "addr:full":"The Garage, Quarry Lane Milnthorpe Cumbria LA7 7HW",
    "addr:postcode":"la7 7hw",
    "addr:street":"Quarry Lane",
    "iso:country":"GB",
    "sg:address":"The Garage, Quarry Lane",
    "sg:city":"Milnthorpe",
    "sg:classifiers":[
        {
            "category":"Retail",
            "subcategory":"Auto Repair",
            "type":"Services"
        }
    ],
    "sg:phone":"+44 15395 63101",
    "sg:postcode":"LA7 7HW",
    "sg:province":"Cumbria",
    "sg:tags":[
        "modification",
        "garage"
    ],
    "wof:name":"Trevor Bingley",
    "wof:placetype":"venue"
},
  "geometry": {"coordinates":[-2.772592,54.226864],"type":"Point"}
}