{
  "type": "Feature",
  "properties": {
    "iso:country":"GB",
    "sg:address":"Main Street, Keyingham",
    "sg:city":"Hull",
    "sg:classifiers":[
        {
            "category":"Shopping",
            "subcategory":"Pharmacy",
            "type":"Retail Goods"
        }
    ],
    "sg:phone":"+44 1964 622251",
    "sg:postcode":"HU12 9RE",
    "sg:province":"East Riding of Yorkshire",
    "sg:tags":[
        "toiletry"
    ],
    "wof:name":"Genese (International) Ltd.",
    "wof:placetype":"venue"
},
  "geometry": {"coordinates":[-0.139284,53.73571],"type":"Point"}
}