{
  "type": "Feature",
  "properties": {
    "iso:country":"GB",
    "sg:address":"27 Lochend Road South",
    "sg:city":"Edinburgh",
    "sg:classifiers":[
        {
            "category":"Organizations",
            "subcategory":"Non-profit Organization",
            "type":"Services"
        }
    ],
    "sg:phone":"+44 131 661 2604",
    "sg:postcode":"EH7 6BF",
    "sg:province":"City of Edinburgh",
    "sg:tags":[
        "organisation",
        "voluntary",
        "charity"
    ],
    "wof:name":"Lochend Neighbourhood Centre",
    "wof:placetype":"venue"
},
  "geometry": {"coordinates":[-3.158501,55.960999],"type":"Point"}
}