{
  "type": "Feature",
  "properties": {
    "iso:country":"GB",
    "sg:address":"90 High Rd",
    "sg:city":"London",
    "sg:classifiers":[
        {
            "category":"Wholesale",
            "subcategory":"Non-durable Goods",
            "type":"Manufacturing & Wholesale Goods"
        }
    ],
    "sg:postcode":"N2 9EB",
    "sg:province":"Greater London",
    "sg:tags":[
        "carry",
        "cash"
    ],
    "wof:name":"Gof International Ltd",
    "wof:placetype":"venue"
},
  "geometry": {"coordinates":[-0.164199,51.587879],"type":"Point"}
}