{
  "type": "Feature",
  "properties": {
    "addr:full":"44 High Street Weybridge Surrey KT13 8BL",
    "addr:housenumber":"44",
    "addr:postcode":"kt13 8bl",
    "addr:street":"High Street",
    "iso:country":"GB",
    "sg:address":"44 High Street",
    "sg:city":"Weybridge",
    "sg:classifiers":[
        {
            "category":"Sports & Exercise",
            "subcategory":"Sports Center",
            "type":"Entertainment"
        }
    ],
    "sg:phone":"+44 1932 842893",
    "sg:postcode":"KT13 8BL",
    "sg:province":"Surrey",
    "sg:tags":[
        "shop",
        "good"
    ],
    "wof:name":"Weybridge Sports",
    "wof:placetype":"venue"
},
  "geometry": {"coordinates":[-0.4573099911,51.3732337952],"type":"Point"}
}