{
  "type": "Feature",
  "properties": {
    "iso:country":"GB",
    "sg:address":"Unit 9 Pomphlett Farm Industrial Estate, Plymstock",
    "sg:city":"Plymouth",
    "sg:classifiers":[
        {
            "category":"Home & Garden",
            "subcategory":"Household Appliances",
            "type":"Retail Goods"
        }
    ],
    "sg:phone":"+44 1752 481122",
    "sg:postcode":"PL9 7BG",
    "sg:province":"Devon",
    "sg:tags":[
        "parts",
        "spare",
        "heating"
    ],
    "wof:name":"Shoreheat Ltd",
    "wof:placetype":"venue"
},
  "geometry": {"coordinates":[-4.096109,50.368],"type":"Point"}
}