{
  "type": "Feature",
  "properties": {
    "iso:country":"GB",
    "sg:address":"34 Carlton Terrace",
    "sg:city":"Swansea",
    "sg:classifiers":[
        {
            "category":"Professional",
            "subcategory":"Employment Agencies",
            "type":"Services"
        },
        {
            "category":"Banks & Credit Unions",
            "subcategory":"Financial Services",
            "type":"Services"
        }
    ],
    "sg:phone":"+44 1792 468971",
    "sg:postcode":"SA1 6AD",
    "sg:province":"Neath Port Talbot",
    "sg:tags":[
        "vitae",
        "curriculum",
        "cv"
    ],
    "wof:name":"Lorien Business Services",
    "wof:placetype":"venue"
},
  "geometry": {"coordinates":[-3.9517390728,51.6212158203],"type":"Point"}
}