{
  "type": "Feature",
  "properties": {
    "addr:full":"7 Peartree Avenue Southampton Hampshire SO19 7JN",
    "addr:housenumber":"7",
    "addr:postcode":"so19 7jn",
    "addr:street":"Peartree Avenue",
    "iso:country":"GB",
    "sg:address":"7 Peartree Avenue",
    "sg:city":"Southampton",
    "sg:classifiers":[
        {
            "category":"Health Services",
            "subcategory":"Health Practitioner",
            "type":"Services"
        }
    ],
    "sg:postcode":"SO19 7JN",
    "sg:province":"Hampshire",
    "sg:tags":[
        "homoeopathic"
    ],
    "wof:name":"Alternative Therapy",
    "wof:placetype":"venue"
},
  "geometry": {"coordinates":[-1.3736469746,50.9060668945],"type":"Point"}
}