{
  "type": "Feature",
  "properties": {
    "iso:country":"GB",
    "sg:address":"The Old Quarry, High Street, Askern",
    "sg:city":"Doncaster",
    "sg:classifiers":[
        {
            "category":"Manufacturing",
            "subcategory":"Building Materials",
            "type":"Manufacturing & Wholesale Goods"
        }
    ],
    "sg:phone":"+44 1302 709427",
    "sg:postcode":"DN6 0AB",
    "sg:province":"North Yorkshire",
    "sg:tags":[
        "merchant",
        "builder"
    ],
    "wof:name":"Askern Builders Supplies",
    "wof:placetype":"venue"
},
  "geometry": {"coordinates":[-1.145399,53.616341],"type":"Point"}
}