{
  "type": "Feature",
  "properties": {
    "iso:country":"GB",
    "sg:address":"45 Orsett Road",
    "sg:city":"Grays",
    "sg:classifiers":[
        {
            "category":"Banks & Credit Unions",
            "subcategory":"Financial Services",
            "type":"Services"
        }
    ],
    "sg:phone":"+44 1375 385122",
    "sg:postcode":"RM17 5HJ",
    "sg:province":"Essex",
    "sg:tags":[
        "consultant"
    ],
    "wof:name":"Hambro Countrywide Financial Services",
    "wof:placetype":"venue"
},
  "geometry": {"coordinates":[0.325443,51.479172],"type":"Point"}
}