{
  "type": "Feature",
  "properties": {
    "addr:full":"Scott Lane, Northgate Cleckheaton West Yorkshire BD19 3LZ",
    "addr:postcode":"bd19 3lz",
    "addr:street":"Scott Lane;West",
    "iso:country":"GB",
    "sg:address":"Scott Lane, Northgate",
    "sg:city":"Cleckheaton",
    "sg:classifiers":[
        {
            "category":"Recreation",
            "type":"Entertainment"
        }
    ],
    "sg:phone":"+44 1274 869195",
    "sg:postcode":"BD19 3LZ",
    "sg:province":"West Yorkshire",
    "sg:tags":[
        "snooker",
        "billiards",
        "pool"
    ],
    "wof:name":"Ambassador Snooker Club",
    "wof:placetype":"venue"
},
  "geometry": {"coordinates":[-1.7127239704,53.7267951965],"type":"Point"}
}