{
  "type": "Feature",
  "properties": {
    "addr:full":"48 Queens Road Nuneaton Leicestershire CV11 5JX",
    "addr:housenumber":"48",
    "addr:postcode":"cv11 5jx",
    "addr:street":"Queens Road",
    "iso:country":"GB",
    "sg:address":"48 Queens Road",
    "sg:city":"Nuneaton",
    "sg:classifiers":[
        {
            "category":"Recreation",
            "subcategory":"Fishing",
            "type":"Entertainment"
        },
        {
            "category":"Shopping",
            "subcategory":"Pets & Pet Supplies",
            "type":"Retail Goods"
        }
    ],
    "sg:phone":"+44 24 7638 1745",
    "sg:postcode":"CV11 5JX",
    "sg:province":"Leicestershire",
    "sg:tags":[
        "shop",
        "angling"
    ],
    "wof:name":"Martins Pet Supplies",
    "wof:placetype":"venue"
},
  "geometry": {"coordinates":[-1.471454978,52.5225257874],"type":"Point"}
}