{
  "type": "Feature",
  "properties": {
    "iso:country":"GB",
    "sg:address":"142 Main Street",
    "sg:city":"Prestwick",
    "sg:classifiers":[
        {
            "category":"Cafe",
            "type":"Food & Drink"
        },
        {
            "category":"Food & Beverages",
            "subcategory":"Groceries & Convenience Stores",
            "type":"Retail Goods"
        }
    ],
    "sg:phone":"+44 1292 478712",
    "sg:postcode":"KA9 1PB",
    "sg:province":"South Ayrshire",
    "sg:tags":[
        "shop",
        "tea",
        "fish",
        "room",
        "chip"
    ],
    "wof:name":"Sandys",
    "wof:placetype":"venue"
},
  "geometry": {"coordinates":[-4.6126728058,55.4970970154],"type":"Point"}
}