{
  "type": "Feature",
  "properties": {
    "addr:full":"151 Leeds Rd Nelson Lancashire BB9 9XG",
    "addr:housenumber":"151",
    "addr:postcode":"bb9 9xg",
    "addr:street":"Leeds Rd",
    "iso:country":"GB",
    "sg:address":"151 Leeds Rd",
    "sg:city":"Nelson",
    "sg:classifiers":[
        {
            "category":"Shopping",
            "type":"Retail Goods"
        }
    ],
    "sg:phone":"+44 1282 612920",
    "sg:postcode":"BB9 9XG",
    "sg:province":"Lancashire",
    "sg:tags":[
        "part",
        "accessory"
    ],
    "wof:name":"Motowares Care Care",
    "wof:placetype":"venue"
},
  "geometry": {"coordinates":[-2.2068641186,53.8399429321],"type":"Point"}
}