{
  "type": "Feature",
  "properties": {
    "addr:full":"Mulberry House, 53 Church Street Weybridge Surrey KT13 8DJ",
    "addr:housenumber":"53",
    "addr:postcode":"kt13 8dj",
    "addr:street":"Church Street",
    "iso:country":"GB",
    "sg:address":"Mulberry House, 53 Church Street",
    "sg:city":"Weybridge",
    "sg:classifiers":[
        {
            "category":"Building & Trades",
            "subcategory":"Construction",
            "type":"Services"
        }
    ],
    "sg:postcode":"KT13 8DJ",
    "sg:province":"Surrey",
    "sg:tags":[
        "builder"
    ],
    "wof:name":"Elvaco Uk Limited",
    "wof:placetype":"venue"
},
  "geometry": {"coordinates":[-0.4617600143,51.3718910217],"type":"Point"}
}