{
  "type": "Feature",
  "properties": {
    "addr:full":"Unit 7 & 9 Crownest Industrial Estate, Rookery Road Barnoldswick Lancashire BB18 6YH",
    "addr:housenumber":"unit 7 & 9",
    "addr:postcode":"bb18 6yh",
    "addr:street":"Crownest Industrial Estate Rookery Road",
    "iso:country":"GB",
    "sg:address":"Unit 7 & 9 Crownest Industrial Estate, Rookery Road",
    "sg:city":"Barnoldswick",
    "sg:classifiers":[
        {
            "category":"Retail",
            "subcategory":"Auto Repair",
            "type":"Services"
        }
    ],
    "sg:postcode":"BB18 6YH",
    "sg:province":"Lancashire",
    "sg:tags":[
        "modification",
        "garage"
    ],
    "wof:name":"Penine 4X4 Service Centre",
    "wof:placetype":"venue"
},
  "geometry": {"coordinates":[-2.18195,53.919209],"type":"Point"}
}