{
  "type": "Feature",
  "properties": {
    "addr:full":"145 Manchester Road Northwich Cheshire CW9 7LS",
    "addr:housenumber":"145",
    "addr:postcode":"cw9 7ls",
    "addr:street":"Manchester Road",
    "iso:country":"GB",
    "sg:address":"145 Manchester Road",
    "sg:city":"Northwich",
    "sg:classifiers":[
        {
            "category":"Insurance",
            "subcategory":"Insurance Agent",
            "type":"Services"
        }
    ],
    "sg:phone":"+44 1606 46116",
    "sg:postcode":"CW9 7LS",
    "sg:province":"Cheshire",
    "wof:name":"National Farmers Union",
    "wof:placetype":"venue"
},
  "geometry": {"coordinates":[-2.487159,53.26535],"type":"Point"}
}