{
  "type": "Feature",
  "properties": {
    "iso:country":"GB",
    "sg:address":"37 Banbury Rd",
    "sg:city":"Stratford Upon Avon",
    "sg:classifiers":[
        {
            "category":"Food & Beverages",
            "subcategory":"Liquor & Beverages",
            "type":"Retail Goods"
        }
    ],
    "sg:phone":"+44 1789 293686",
    "sg:postcode":"CV37 7HW",
    "sg:province":"Warwickshire",
    "sg:tags":[
        "beer",
        "spirit",
        "wines"
    ],
    "wof:name":"Berkeley Wines",
    "wof:placetype":"venue"
},
  "geometry": {"coordinates":[-1.6769889593,52.1764984131],"type":"Point"}
}