{
  "type": "Feature",
  "properties": {
    "iso:country":"GB",
    "sg:address":"Customs Way, Ashton-on-ribble",
    "sg:city":"Preston",
    "sg:classifiers":[
        {
            "category":"Organizations",
            "subcategory":"Community Association",
            "type":"Services"
        }
    ],
    "sg:postcode":"PR2 2UW",
    "sg:province":"Lancashire",
    "sg:tags":[
        "relation",
        "public"
    ],
    "wof:name":"Glasgows Ltd.",
    "wof:placetype":"venue"
},
  "geometry": {"coordinates":[-2.726857,53.762184],"type":"Point"}
}