{
  "type": "Feature",
  "properties": {
    "addr:full":"173 Brookscroft Road Walthamstow Greater London E17 4JP",
    "addr:housenumber":"173",
    "addr:postcode":"e17 4jp",
    "addr:street":"Brookscroft Road",
    "iso:country":"GB",
    "sg:address":"173 Brookscroft Road",
    "sg:city":"Walthamstow",
    "sg:classifiers":[
        {
            "category":"Organizations",
            "subcategory":"Political Organization",
            "type":"Services"
        }
    ],
    "sg:phone":"+44 20 8527 8834",
    "sg:postcode":"E17 4JP",
    "sg:province":"Greater London",
    "sg:tags":[
        "party"
    ],
    "wof:name":"Chingford & Woodford Green Labour Party",
    "wof:placetype":"venue"
},
  "geometry": {"coordinates":[-0.008432,51.596474],"type":"Point"}
}