{
  "type": "Feature",
  "properties": {
    "addr:full":"26 Welburn Gro, Ormesby Middlesbrough North Yorkshire TS7 9BN",
    "addr:housenumber":"26",
    "addr:postcode":"ts7 9bn",
    "addr:street":"Welburn Gro",
    "iso:country":"GB",
    "sg:address":"26 Welburn Gro, Ormesby",
    "sg:city":"Middlesbrough",
    "sg:classifiers":[
        {
            "category":"Retail",
            "subcategory":"Repair Shop",
            "type":"Services"
        }
    ],
    "sg:phone":"+44 1642 312989",
    "sg:postcode":"TS7 9BN",
    "sg:province":"North Yorkshire",
    "sg:tags":[
        "upholstering",
        "upholsterer"
    ],
    "wof:name":"R K Upholstery",
    "wof:placetype":"venue"
},
  "geometry": {"coordinates":[-1.1805479527,54.5457077026],"type":"Point"}
}