{
  "type": "Feature",
  "properties": {
    "addr:full":"8 Packington Close, Old Shaw Swindon Wiltshire SN5 5PB",
    "addr:housenumber":"8",
    "addr:postcode":"sn5 5pb",
    "addr:street":"Packington Close",
    "iso:country":"GB",
    "sg:address":"8 Packington Close, Old Shaw",
    "sg:city":"Swindon",
    "sg:classifiers":[
        {
            "category":"Professional",
            "type":"Services"
        }
    ],
    "sg:phone":"+44 7808 643268",
    "sg:postcode":"SN5 5PB",
    "sg:province":"Wiltshire",
    "sg:tags":[
        "reflexologists"
    ],
    "wof:name":"Alison Deacon MIIR ART",
    "wof:placetype":"venue"
},
  "geometry": {"coordinates":[-1.833783,51.567997],"type":"Point"}
}