{
  "type": "Feature",
  "properties": {
    "addr:full":"2a Station Road Letchworth Hertfordshire SG6 3AU",
    "addr:housenumber":"2a",
    "addr:postcode":"sg6 3au",
    "addr:street":"Station Road",
    "iso:country":"GB",
    "sg:address":"2a Station Road",
    "sg:city":"Letchworth",
    "sg:classifiers":[
        {
            "category":"Organizations",
            "subcategory":"Membership Organization",
            "type":"Services"
        }
    ],
    "sg:phone":"+44 1462 623655",
    "sg:postcode":"SG6 3AU",
    "sg:province":"Hertfordshire",
    "sg:tags":[
        "club"
    ],
    "wof:name":"Four Emblems Club",
    "wof:placetype":"venue"
},
  "geometry": {"coordinates":[-0.2281920016,51.9798240662],"type":"Point"}
}