{
  "type": "Feature",
  "properties": {
    "iso:country":"GB",
    "sg:address":"1500 Warwick Rd",
    "sg:city":"Solihull",
    "sg:classifiers":[
        {
            "category":"Health Services",
            "subcategory":"Doctor",
            "type":"Services"
        }
    ],
    "sg:phone":"+44 1564 772010",
    "sg:postcode":"B93 9LE",
    "sg:province":"Warwickshire",
    "sg:tags":[
        "practitioners"
    ],
    "wof:name":"Morgan, R H",
    "wof:placetype":"venue"
},
  "geometry": {"coordinates":[-1.737703,52.390293],"type":"Point"}
}