{
  "type": "Feature",
  "properties": {
    "iso:country":"GB",
    "sg:address":"Torino Bryn Hyfryd Park",
    "sg:city":"Ruthin",
    "sg:classifiers":[
        {
            "category":"Wholesale",
            "subcategory":"Meat",
            "type":"Manufacturing & Wholesale Goods"
        },
        {
            "category":"Farming",
            "subcategory":"Farm",
            "type":"Manufacturing & Wholesale Goods"
        }
    ],
    "sg:postcode":"LL15 1EB",
    "sg:province":"Denbighshire",
    "sg:tags":[
        "egg",
        "-",
        "producer"
    ],
    "wof:name":"Brynhyfryd Eggs",
    "wof:placetype":"venue"
},
  "geometry": {"coordinates":[-3.304522,53.114017],"type":"Point"}
}