{
  "type": "Feature",
  "properties": {
    "addr:full":"85 Eastmoor St Charlton Greater London SE7 8LX",
    "addr:housenumber":"85",
    "addr:postcode":"se7 8lx",
    "addr:street":"Eastmoor St",
    "iso:country":"GB",
    "sg:address":"85 Eastmoor St",
    "sg:city":"Charlton",
    "sg:classifiers":[
        {
            "category":"Wholesale",
            "subcategory":"Scrap",
            "type":"Manufacturing & Wholesale Goods"
        }
    ],
    "sg:phone":"+44 20 8293 4563",
    "sg:postcode":"SE7 8LX",
    "sg:province":"Greater London",
    "sg:tags":[
        "breaker",
        "dismantlers"
    ],
    "wof:name":"A Car Breakers",
    "wof:placetype":"venue"
},
  "geometry": {"coordinates":[0.0387439989,51.4927711487],"type":"Point"}
}