{
  "type": "Feature",
  "properties": {
    "iso:country":"GB",
    "sg:address":"434 Hedgemans Rd",
    "sg:city":"Dagenham",
    "sg:classifiers":[
        {
            "category":"Shopping",
            "subcategory":"News",
            "type":"Retail Goods"
        }
    ],
    "sg:phone":"+44 20 8592 5673",
    "sg:postcode":"RM9 6BU",
    "sg:province":"Essex",
    "sg:tags":[
        "newsagent"
    ],
    "wof:name":"Gibbs Newsagents",
    "wof:placetype":"venue"
},
  "geometry": {"coordinates":[0.128422007,51.5389938354],"type":"Point"}
}