{
  "type": "Feature",
  "properties": {
    "addr:full":"Unit 9 Stour Valley Indust Est, Ashford Rd Canterbury Kent CT4 7HF",
    "addr:housenumber":"unit 9",
    "addr:postcode":"ct4 7hf",
    "addr:street":"Ashford Rd",
    "iso:country":"GB",
    "sg:address":"Unit 9 Stour Valley Indust Est, Ashford Rd",
    "sg:city":"Canterbury",
    "sg:classifiers":[
        {
            "category":"Building & Trades",
            "subcategory":"Equipment Rental",
            "type":"Services"
        }
    ],
    "sg:phone":"+44 7831 169455",
    "sg:postcode":"CT4 7HF",
    "sg:province":"Kent",
    "sg:tags":[
        "plant",
        "machinery"
    ],
    "wof:name":"Skelton Contractors T.J",
    "wof:placetype":"venue"
},
  "geometry": {"coordinates":[1.021465,51.254566],"type":"Point"}
}