{
  "type": "Feature",
  "properties": {
    "addr:full":"18 Glenister Road High Wycombe Buckinghamshire HP12 4RD",
    "addr:housenumber":"18",
    "addr:postcode":"hp12 4rd",
    "addr:street":"Glenister Road",
    "iso:country":"GB",
    "sg:address":"18 Glenister Road",
    "sg:city":"High Wycombe",
    "sg:classifiers":[
        {
            "category":"Manufacturing",
            "subcategory":"Paper Products",
            "type":"Manufacturing & Wholesale Goods"
        }
    ],
    "sg:phone":"+44 1494 437106",
    "sg:postcode":"HP12 4RD",
    "sg:province":"Buckinghamshire",
    "sg:tags":[
        "merchant",
        "waste"
    ],
    "wof:name":"John Day",
    "wof:placetype":"venue"
},
  "geometry": {"coordinates":[-0.7919949889,51.618724823],"type":"Point"}
}