{
  "type": "Feature",
  "properties": {
    "iso:country":"GB",
    "sg:address":"Albion Street, Felling",
    "sg:city":"Gateshead",
    "sg:classifiers":[
        {
            "category":"Wholesale",
            "subcategory":"Construction Materials",
            "type":"Manufacturing & Wholesale Goods"
        },
        {
            "category":"Manufacturing",
            "subcategory":"Building Materials",
            "type":"Manufacturing & Wholesale Goods"
        }
    ],
    "sg:phone":"+44 191 469 3004",
    "sg:postcode":"NE10 9SJ",
    "sg:province":"Tyne and Wear",
    "sg:tags":[
        "merchant",
        "builder",
        "brick"
    ],
    "sg:website":"http://www.wmcgovern.com",
    "wof:name":"W McGovern & Co. Ltd.",
    "wof:placetype":"venue"
},
  "geometry": {"coordinates":[-1.5691189766,54.9522285461],"type":"Point"}
}