{
  "type": "Feature",
  "properties": {
    "addr:full":"Granitehill Enterprise Centre, Granitehill Road Aberdeen Aberdeen City AB2 7AX",
    "addr:postcode":"ab2 7ax",
    "addr:street":"Granitehill Road",
    "iso:country":"GB",
    "sg:address":"Granitehill Enterprise Centre, Granitehill Road",
    "sg:city":"Aberdeen",
    "sg:classifiers":[
        {
            "category":"Building & Trades",
            "subcategory":"Cleaning & Sanitation",
            "type":"Services"
        }
    ],
    "sg:phone":"+44 1224 684540",
    "sg:postcode":"AB2 7AX",
    "sg:province":"Aberdeen City",
    "sg:tags":[
        "asbestos",
        "removal"
    ],
    "wof:name":"Whiteinch Asbestos Ltd.",
    "wof:placetype":"venue"
},
  "geometry": {"coordinates":[-2.10678,57.153931],"type":"Point"}
}