{
  "type": "Feature",
  "properties": {
    "addr:full":"7 Russell Way Leighton Buzzard Bedfordshire LU7 3NE",
    "addr:housenumber":"7",
    "addr:postcode":"lu7 3ne",
    "addr:street":"Russell Way",
    "iso:country":"GB",
    "sg:address":"7 Russell Way",
    "sg:city":"Leighton Buzzard",
    "sg:classifiers":[
        {
            "category":"Retail",
            "subcategory":"Auto Repair",
            "type":"Services"
        }
    ],
    "sg:phone":"+44 1525 853530",
    "sg:postcode":"LU7 3NE",
    "sg:province":"Bedfordshire",
    "sg:tags":[
        "bodybuilder",
        "repairer"
    ],
    "wof:name":"S P Commercials",
    "wof:placetype":"venue"
},
  "geometry": {"coordinates":[-0.6427760124,51.9162712097],"type":"Point"}
}