{
  "type": "Feature",
  "properties": {
    "addr:full":"2 Trafalgar Way, Purley Way Croydon Surrey CR0 4XT",
    "addr:housenumber":"2",
    "addr:postcode":"cr0 4xt",
    "addr:street":"Trafalgar Way Purley",
    "iso:country":"GB",
    "sg:address":"2 Trafalgar Way, Purley Way",
    "sg:city":"Croydon",
    "sg:classifiers":[
        {
            "category":"Food & Beverages",
            "subcategory":"Supermarket",
            "type":"Retail Goods"
        }
    ],
    "sg:phone":"+44 20 8681 5800",
    "sg:postcode":"CR0 4XT",
    "sg:province":"Surrey",
    "wof:name":"J Sainsbury",
    "wof:placetype":"venue"
},
  "geometry": {"coordinates":[-0.1177,51.375751],"type":"Point"}
}