{
  "type": "Feature",
  "properties": {
    "addr:full":"Simonside Terrace, Heaton Newcastle-upon-tyne Tyne and Wear NE6 5JY",
    "addr:postcode":"ne6 5jy",
    "addr:street":"Simonside Terrace",
    "iso:country":"GB",
    "sg:address":"Simonside Terrace, Heaton",
    "sg:city":"Newcastle-upon-tyne",
    "sg:classifiers":[
        {
            "category":"Travel",
            "subcategory":"Hostel",
            "type":"Entertainment"
        },
        {
            "category":"Organizations",
            "subcategory":"Non-profit Organization",
            "type":"Services"
        }
    ],
    "sg:phone":"+44 191 224 2605",
    "sg:postcode":"NE6 5JY",
    "sg:province":"Tyne and Wear",
    "sg:tags":[
        "organisation",
        "voluntary",
        "charity"
    ],
    "wof:name":"The Depaul Trust",
    "wof:placetype":"venue"
},
  "geometry": {"coordinates":[-1.5694439411,54.9867362976],"type":"Point"}
}