{
  "type": "Feature",
  "properties": {
    "iso:country":"GB",
    "sg:address":"138 Sutton Road",
    "sg:city":"Southend-on-sea",
    "sg:classifiers":[
        {
            "category":"Food & Beverages",
            "subcategory":"Candy",
            "type":"Retail Goods"
        }
    ],
    "sg:phone":"+44 1702 611236",
    "sg:postcode":"SS2 5ER",
    "sg:province":"Essex",
    "sg:tags":[
        "confectioner"
    ],
    "wof:name":"Gordon Babette",
    "wof:placetype":"venue"
},
  "geometry": {"coordinates":[0.718604,51.54348],"type":"Point"}
}