{
  "type": "Feature",
  "properties": {
    "iso:country":"GB",
    "sg:address":"P O Box 158",
    "sg:city":"Huntingdon",
    "sg:classifiers":[
        {
            "category":"Real Estate",
            "subcategory":"Real Estate Agent",
            "type":"Services"
        }
    ],
    "sg:postcode":"PE29 7PP",
    "sg:province":"Cambridgeshire",
    "sg:tags":[
        "trademark"
    ],
    "wof:name":"Baker Associates",
    "wof:placetype":"venue"
},
  "geometry": {"coordinates":[-0.189304,52.33514],"type":"Point"}
}