{
  "type": "Feature",
  "properties": {
    "addr:full":"205 Leeds Road Huddersfield West Yorkshire HD1 6NJ",
    "addr:housenumber":"205",
    "addr:postcode":"hd1 6nj",
    "addr:street":"Leeds Road",
    "iso:country":"GB",
    "sg:address":"205 Leeds Road",
    "sg:city":"Huddersfield",
    "sg:classifiers":[
        {
            "category":"Retail",
            "subcategory":"Auto Repair",
            "type":"Services"
        }
    ],
    "sg:phone":"+44 1484 535602",
    "sg:postcode":"HD1 6NJ",
    "sg:province":"West Yorkshire",
    "sg:tags":[
        "modification",
        "garage"
    ],
    "wof:name":"Kwik-Fit 2003 Ltd.",
    "wof:placetype":"venue"
},
  "geometry": {"coordinates":[-1.776748,53.653885],"type":"Point"}
}