{
  "type": "Feature",
  "properties": {
    "iso:country":"GB",
    "sg:address":"Bradbury House, Windsor End",
    "sg:city":"Beaconsfield",
    "sg:classifiers":[
        {
            "category":"Health Services",
            "subcategory":"Nursing And Care Facility",
            "type":"Services"
        },
        {
            "category":"Social Services",
            "subcategory":"Retirement Home",
            "type":"Services"
        }
    ],
    "sg:phone":"+44 1494 671780",
    "sg:postcode":"HP9 2JW",
    "sg:province":"Buckinghamshire",
    "sg:tags":[
        "housing",
        "accommodation",
        "sheltered"
    ],
    "sg:website":"http://www.bradburyhouse.co.uk",
    "wof:name":"Abbeyfield Beaconsfield Society Ltd",
    "wof:placetype":"venue"
},
  "geometry": {"coordinates":[-0.647023,51.61187],"type":"Point"}
}