{
  "type": "Feature",
  "properties": {
    "iso:country":"GB",
    "sg:address":"Unit 43 Edison Road, Bearbrook Industrial Precinct Rabans Lan",
    "sg:city":"Aylesbury",
    "sg:classifiers":[
        {
            "category":"Professional",
            "subcategory":"Engineering",
            "type":"Services"
        }
    ],
    "sg:phone":"+44 1296 415456",
    "sg:postcode":"HP19 8TE",
    "sg:province":"Buckinghamshire",
    "sg:tags":[
        "precision",
        "engineer"
    ],
    "wof:name":"Trev-Col Engineering Ltd.",
    "wof:placetype":"venue"
},
  "geometry": {"coordinates":[-0.8505449891,51.8224487305],"type":"Point"}
}