{
  "type": "Feature",
  "properties": {
    "addr:full":"Kiosk 14, The Mall Hyde Cheshire SK14 2QT",
    "addr:housenumber":"14",
    "addr:postcode":"sk14 2qt",
    "addr:street":"The Mall",
    "iso:country":"GB",
    "sg:address":"Kiosk 14, The Mall",
    "sg:city":"Hyde",
    "sg:classifiers":[
        {
            "category":"Shopping",
            "subcategory":"Comic Books",
            "type":"Retail Goods"
        }
    ],
    "sg:postcode":"SK14 2QT",
    "sg:province":"Cheshire",
    "sg:tags":[
        "jeweller"
    ],
    "wof:name":"Natures Treasures",
    "wof:placetype":"venue"
},
  "geometry": {"coordinates":[-2.0740890503,53.452911377],"type":"Point"}
}