{
  "type": "Feature",
  "properties": {
    "iso:country":"GB",
    "sg:address":"31 Galgate",
    "sg:city":"Barnard Castle",
    "sg:classifiers":[
        {
            "category":"Home & Garden",
            "subcategory":"Hardware",
            "type":"Retail Goods"
        }
    ],
    "sg:phone":"+44 1833 638660",
    "sg:postcode":"DL12 8EJ",
    "sg:province":"Cumbria",
    "sg:tags":[
        "retailer",
        "diy"
    ],
    "wof:name":"Maxwells Diy",
    "wof:placetype":"venue"
},
  "geometry": {"coordinates":[-1.923305,54.545052],"type":"Point"}
}