{
  "type": "Feature",
  "properties": {
    "iso:country":"GB",
    "sg:address":"Unit 59a, Milton Park",
    "sg:city":"Abingdon",
    "sg:classifiers":[
        {
            "category":"Building & Trades",
            "subcategory":"Construction",
            "type":"Services"
        }
    ],
    "sg:phone":"+44 1235 833037",
    "sg:postcode":"OX14 4RX",
    "sg:province":"Oxfordshire",
    "sg:tags":[
        "valve"
    ],
    "wof:name":"Delta Flow Systems Ltd.",
    "wof:placetype":"venue"
},
  "geometry": {"coordinates":[-1.3013240099,51.6222496033],"type":"Point"}
}