{
  "type": "Feature",
  "properties": {
    "addr:full":"Plumley Moor Road, Plumley Knutsford Cheshire WA16 9RX",
    "addr:postcode":"wa16 9rx",
    "addr:street":"Moor Road",
    "iso:country":"GB",
    "sg:address":"Plumley Moor Road, Plumley",
    "sg:city":"Knutsford",
    "sg:classifiers":[
        {
            "category":"Travel",
            "subcategory":"Hotels & Motels",
            "type":"Entertainment"
        }
    ],
    "sg:phone":"+44 1565 722261",
    "sg:postcode":"WA16 9RX",
    "sg:province":"Cheshire",
    "wof:name":"Golden Pheasant Hotel",
    "wof:placetype":"venue"
},
  "geometry": {"coordinates":[-2.41189,53.272663],"type":"Point"}
}