{
  "type": "Feature",
  "properties": {
    "addr:full":"26a Elm Gro Hayling Island Hampshire PO11 9EF",
    "addr:housenumber":"26a",
    "addr:postcode":"po11 9ef",
    "addr:street":"Elm Gro",
    "iso:country":"GB",
    "sg:address":"26a Elm Gro",
    "sg:city":"Hayling Island",
    "sg:classifiers":[
        {
            "category":"Taxi",
            "type":"Transportation"
        },
        {
            "category":"Military Area",
            "subcategory":"Air Force Base",
            "type":"Public Place"
        }
    ],
    "sg:postcode":"PO11 9EF",
    "sg:province":"Hampshire",
    "sg:tags":[
        "mini",
        "hire",
        "private",
        "cab"
    ],
    "wof:name":"Bella Vista Cars",
    "wof:placetype":"venue"
},
  "geometry": {"coordinates":[-0.976955,50.788815],"type":"Point"}
}