{
  "type": "Feature",
  "properties": {
    "addr:full":"1 Great Eastern Sq Felixstowe Suffolk IP11 7DY",
    "addr:housenumber":"1",
    "addr:postcode":"ip11 7dy",
    "addr:street":"Great Eastern Sq",
    "iso:country":"GB",
    "sg:address":"1 Great Eastern Sq",
    "sg:city":"Felixstowe",
    "sg:classifiers":[
        {
            "category":"Professional",
            "subcategory":"Business Services",
            "type":"Services"
        }
    ],
    "sg:phone":"+44 1394 283998",
    "sg:postcode":"IP11 7DY",
    "sg:province":"Suffolk",
    "sg:tags":[
        "trade"
    ],
    "wof:name":"Gulpher International Ltd",
    "wof:placetype":"venue"
},
  "geometry": {"coordinates":[1.342465,51.961369],"type":"Point"}
}