{
  "type": "Feature",
  "properties": {
    "addr:full":"The Coach House, Chamberlain Street Wells Somerset BA5 2PJ",
    "addr:postcode":"ba5 2pj",
    "addr:street":"Chamberlain Street",
    "iso:country":"GB",
    "sg:address":"The Coach House, Chamberlain Street",
    "sg:city":"Wells",
    "sg:classifiers":[
        {
            "category":"Professional",
            "subcategory":"Accounting & Tax Preparation",
            "type":"Services"
        }
    ],
    "sg:phone":"+44 1749 672600",
    "sg:postcode":"BA5 2PJ",
    "sg:province":"Somerset",
    "sg:tags":[
        "accountant"
    ],
    "wof:name":"Martin J Bowe",
    "wof:placetype":"venue"
},
  "geometry": {"coordinates":[-2.647777,51.210121],"type":"Point"}
}