{
  "type": "Feature",
  "properties": {
    "iso:country":"GB",
    "sg:address":"Southside St, The Barbican",
    "sg:city":"Plymouth",
    "sg:classifiers":[
        {
            "category":"Shopping",
            "subcategory":"Gifts & Souvenirs",
            "type":"Retail Goods"
        }
    ],
    "sg:postcode":"PL1 2NQ",
    "sg:province":"Devon",
    "sg:tags":[
        "shop"
    ],
    "wof:name":"Old Curiosity Shop (The)",
    "wof:placetype":"venue"
},
  "geometry": {"coordinates":[-4.140684,50.368355],"type":"Point"}
}