{
  "type": "Feature",
  "properties": {
    "addr:full":"47-53 St John Street London Greater London EC1M 4AN",
    "addr:housenumber":"47-53",
    "addr:postcode":"ec1m 4an",
    "addr:street":"St John Street",
    "iso:country":"GB",
    "sg:address":"47-53 St John Street",
    "sg:city":"London",
    "sg:classifiers":[
        {
            "category":"Shopping",
            "subcategory":"Stationery & Office Supplies",
            "type":"Retail Goods"
        }
    ],
    "sg:phone":"+44 20 7689 1234",
    "sg:postcode":"EC1M 4AN",
    "sg:province":"Greater London",
    "sg:tags":[
        "equipment"
    ],
    "wof:name":"Blacksco 34 Plc",
    "wof:placetype":"venue"
},
  "geometry": {"coordinates":[-0.1017649993,51.521232605],"type":"Point"}
}