{
  "type": "Feature",
  "properties": {
    "iso:country":"GB",
    "sg:address":"Unit 16a Whitebridge Estate, Whitebridge Lane",
    "sg:city":"Stone",
    "sg:classifiers":[
        {
            "category":"Shopping",
            "subcategory":"Beauty & Cosmetics",
            "type":"Retail Goods"
        }
    ],
    "sg:phone":"+44 1785 813085",
    "sg:postcode":"ST15 8LQ",
    "sg:province":"Staffordshire",
    "wof:name":"Jigsaw European Sales Ltd.",
    "wof:placetype":"venue"
},
  "geometry": {"coordinates":[-2.159197,52.909912],"type":"Point"}
}