{
  "type": "Feature",
  "properties": {
    "addr:full":"Tynet House, 41 Allison Close Cove Bay Aberdeen Aberdeen City AB12 3WG",
    "addr:housenumber":"41",
    "addr:postcode":"ab12 3wg",
    "addr:street":"Allison Close Cove",
    "iso:country":"GB",
    "sg:address":"Tynet House, 41 Allison Close Cove Bay",
    "sg:city":"Aberdeen",
    "sg:classifiers":[
        {
            "category":"Utilities",
            "type":"Services"
        }
    ],
    "sg:postcode":"AB12 3WG",
    "sg:province":"Aberdeen City",
    "sg:tags":[
        "internet"
    ],
    "wof:name":"Nettrak Global Ltd.",
    "wof:placetype":"venue"
},
  "geometry": {"coordinates":[-2.0895280838,57.1047897339],"type":"Point"}
}