{
  "type": "Feature",
  "properties": {
    "addr:full":"54 The Avenue Southampton Hampshire SO17 1XQ",
    "addr:housenumber":"54",
    "addr:postcode":"so17 1xq",
    "addr:street":"The Avenue",
    "iso:country":"GB",
    "sg:address":"54 The Avenue",
    "sg:city":"Southampton",
    "sg:classifiers":[
        {
            "category":"Education",
            "subcategory":"Special Training",
            "type":"Public Place"
        }
    ],
    "sg:postcode":"SO17 1XQ",
    "sg:province":"Hampshire",
    "sg:tags":[
        "school",
        "language"
    ],
    "wof:name":"SOLENT LANGUAGE CENTRE",
    "wof:placetype":"venue"
},
  "geometry": {"coordinates":[-1.4044859409,50.9205322266],"type":"Point"}
}