{
  "type": "Feature",
  "properties": {
    "addr:full":"465 Buxton Rd Stockport Cheshire SK2 7HE",
    "addr:housenumber":"465",
    "addr:postcode":"sk2 7he",
    "addr:street":"Buxton Rd",
    "iso:country":"GB",
    "sg:address":"465 Buxton Rd",
    "sg:city":"Stockport",
    "sg:classifiers":[
        {
            "category":"Travel",
            "subcategory":"Travel Agent",
            "type":"Entertainment"
        }
    ],
    "sg:phone":"+44 161 419 9555",
    "sg:postcode":"SK2 7HE",
    "sg:province":"Cheshire",
    "wof:name":"Global Travel",
    "wof:placetype":"venue"
},
  "geometry": {"coordinates":[-2.131743,53.387001],"type":"Point"}
}