{
  "type": "Feature",
  "properties": {
    "addr:full":"Oddington Grange Farm, Wendlebury Bicester Oxfordshire OX25 3QW",
    "addr:housenumber":"oddington",
    "addr:postcode":"ox25 3qw",
    "addr:street":"Grange Farm",
    "iso:country":"GB",
    "sg:address":"Oddington Grange Farm, Wendlebury",
    "sg:city":"Bicester",
    "sg:classifiers":[
        {
            "category":"Building & Trades",
            "subcategory":"Plumbing",
            "type":"Services"
        },
        {
            "category":"Building & Trades",
            "subcategory":"Construction",
            "type":"Services"
        }
    ],
    "sg:phone":"+44 1865 331731",
    "sg:postcode":"OX25 3QW",
    "sg:province":"Oxfordshire",
    "sg:tags":[
        "plumber",
        "pipework",
        "contractor"
    ],
    "wof:name":"KIDLINGTON PIPEWORK SERVICES LTD",
    "wof:placetype":"venue"
},
  "geometry": {"coordinates":[-1.211109,51.845928],"type":"Point"}
}