{
  "type": "Feature",
  "properties": {
    "iso:country":"GB",
    "sg:address":"11 Shaw Wood Way",
    "sg:city":"Doncaster",
    "sg:classifiers":[
        {
            "category":"Professional",
            "subcategory":"Advertising",
            "type":"Services"
        }
    ],
    "sg:phone":"+44 1302 329017",
    "sg:postcode":"DN2 5TB",
    "sg:province":"South Yorkshire",
    "sg:tags":[
        "agency"
    ],
    "wof:name":"Cooper & Cooper",
    "wof:placetype":"venue"
},
  "geometry": {"coordinates":[-1.0871510506,53.542514801],"type":"Point"}
}