{
  "type": "Feature",
  "properties": {
    "iso:country":"GB",
    "sg:address":"61 Long Street, Easingwold",
    "sg:city":"York",
    "sg:classifiers":[
        {
            "category":"Personal",
            "subcategory":"Beauty Salon",
            "type":"Services"
        }
    ],
    "sg:phone":"+44 1347 822886",
    "sg:postcode":"YO61 3HY",
    "sg:province":"North Yorkshire",
    "wof:name":"Bubbles Hair & Beauty Salon",
    "wof:placetype":"venue"
},
  "geometry": {"coordinates":[-1.196705,54.121189],"type":"Point"}
}