{
  "type": "Feature",
  "properties": {
    "addr:full":"30 Bryn Rhys, Glan Conwy Colwyn Bay Conwy LL28 5NU",
    "addr:housenumber":"30",
    "addr:postcode":"ll28 5nu",
    "addr:street":"Bryn Rhys Glan",
    "iso:country":"GB",
    "sg:address":"30 Bryn Rhys, Glan Conwy",
    "sg:city":"Colwyn Bay",
    "sg:classifiers":[
        {
            "category":"Shopping",
            "subcategory":"Musical Instruments",
            "type":"Retail Goods"
        }
    ],
    "sg:phone":"+44 1492 580610",
    "sg:postcode":"LL28 5NU",
    "sg:province":"Conwy",
    "sg:tags":[
        "piano",
        "tuning",
        "maintenance"
    ],
    "wof:name":"Piano Care",
    "wof:placetype":"venue"
},
  "geometry": {"coordinates":[-3.788779974,53.2696685791],"type":"Point"}
}