{
  "type": "Feature",
  "properties": {
    "addr:full":"52-56 Coatsworth Road Gateshead Tyne and Wear NE8 1QN",
    "addr:housenumber":"52-56",
    "addr:postcode":"ne8 1qn",
    "addr:street":"Coatsworth Road",
    "iso:country":"GB",
    "sg:address":"52-56 Coatsworth Road",
    "sg:city":"Gateshead",
    "sg:classifiers":[
        {
            "category":"Professional",
            "subcategory":"Accounting & Tax Preparation",
            "type":"Services"
        }
    ],
    "sg:phone":"+44 191 420 0177",
    "sg:postcode":"NE8 1QN",
    "sg:province":"Tyne and Wear",
    "sg:tags":[
        "accountant",
        "activity"
    ],
    "wof:name":"Thompson Kimti Ltd.",
    "wof:placetype":"venue"
},
  "geometry": {"coordinates":[-1.608932,54.95816],"type":"Point"}
}