{
  "type": "Feature",
  "properties": {
    "iso:country":"GB",
    "sg:address":"Modley Place",
    "sg:city":"Ellon",
    "sg:classifiers":[
        {
            "category":"Education",
            "subcategory":"School",
            "type":"Public Place"
        },
        {
            "category":"Government",
            "subcategory":"Office",
            "type":"Public Place"
        }
    ],
    "sg:phone":"+44 1358 720692",
    "sg:postcode":"AB41 9BB",
    "sg:province":"Aberdeenshire",
    "sg:tags":[
        "local",
        "authority"
    ],
    "wof:name":"Ellon Primary School",
    "wof:placetype":"venue"
},
  "geometry": {"coordinates":[-2.084876,57.366062],"type":"Point"}
}