{
  "type": "Feature",
  "properties": {
    "addr:full":"1-3 New Ferry Road Wirral Cheshire CH62 1BQ",
    "addr:housenumber":"1-3",
    "addr:postcode":"ch62 1bq",
    "addr:street":"New Ferry Road",
    "iso:country":"GB",
    "sg:address":"1-3 New Ferry Road",
    "sg:city":"Wirral",
    "sg:classifiers":[
        {
            "category":"Food & Beverages",
            "subcategory":"Meat & Fish",
            "type":"Retail Goods"
        }
    ],
    "sg:phone":"+44 151 645 4203",
    "sg:postcode":"CH62 1BQ",
    "sg:province":"Cheshire",
    "sg:tags":[
        "butcher"
    ],
    "wof:name":"G H Pearson",
    "wof:placetype":"venue"
},
  "geometry": {"coordinates":[-2.9973809719,53.3611869812],"type":"Point"}
}