{
  "type": "Feature",
  "properties": {
    "iso:country":"GB",
    "sg:address":"3 Tadworth Parade",
    "sg:city":"Hornchurch",
    "sg:classifiers":[
        {
            "category":"Food & Beverages",
            "subcategory":"Meat & Fish",
            "type":"Retail Goods"
        }
    ],
    "sg:phone":"+44 1708 451376",
    "sg:postcode":"RM12 5AS",
    "sg:province":"Essex",
    "sg:tags":[
        "chip"
    ],
    "wof:name":"New Regal Fish Bar",
    "wof:placetype":"venue"
},
  "geometry": {"coordinates":[0.2003670037,51.5488166809],"type":"Point"}
}