{
  "type": "Feature",
  "properties": {
    "iso:country":"GB",
    "sg:address":"41 Brooklands Park, Longlevens",
    "sg:city":"Gloucester",
    "sg:classifiers":[
        {
            "category":"Building & Trades",
            "subcategory":"Construction",
            "type":"Services"
        }
    ],
    "sg:phone":"+44 1452 303486",
    "sg:postcode":"GL2 0DN",
    "sg:province":"Gloucestershire",
    "sg:tags":[
        "roofing",
        "contracting"
    ],
    "wof:name":"Dunn & Hopkins",
    "wof:placetype":"venue"
},
  "geometry": {"coordinates":[-2.20994,51.879318],"type":"Point"}
}