{
  "type": "Feature",
  "properties": {
    "addr:full":"92 Marshfield Road Chippenham Wiltshire SN15 1JW",
    "addr:housenumber":"92",
    "addr:postcode":"sn15 1jw",
    "addr:street":"Marshfield Road",
    "iso:country":"GB",
    "sg:address":"92 Marshfield Road",
    "sg:city":"Chippenham",
    "sg:classifiers":[
        {
            "category":"Shopping",
            "subcategory":"Computers & Home Electronics",
            "type":"Retail Goods"
        }
    ],
    "sg:phone":"+44 1249 651149",
    "sg:postcode":"SN15 1JW",
    "sg:province":"Wiltshire",
    "sg:tags":[
        "aerial",
        "television",
        "radio"
    ],
    "wof:name":"Aerial Services Chippenham",
    "wof:placetype":"venue"
},
  "geometry": {"coordinates":[-2.123439,51.462791],"type":"Point"}
}