{
  "type": "Feature",
  "properties": {
    "addr:full":"209 Yorkshire Street Rochdale Lancashire OL12 0DS",
    "addr:housenumber":"209",
    "addr:postcode":"ol12 0ds",
    "addr:street":"Yorkshire Street",
    "iso:country":"GB",
    "sg:address":"209 Yorkshire Street",
    "sg:city":"Rochdale",
    "sg:classifiers":[
        {
            "category":"Bars & Pubs",
            "type":"Food & Drink"
        },
        {
            "category":"Travel",
            "subcategory":"Hotels & Motels",
            "type":"Entertainment"
        }
    ],
    "sg:phone":"+44 1706 642616",
    "sg:postcode":"OL12 0DS",
    "sg:province":"Lancashire",
    "sg:tags":[
        "pubs",
        "house",
        "inn",
        "guest"
    ],
    "wof:name":"THE RAILWAY INN",
    "wof:placetype":"venue"
},
  "geometry": {"coordinates":[-2.1487009525,53.6219406128],"type":"Point"}
}