{
  "type": "Feature",
  "properties": {
    "addr:full":"14a-b Albion Street, Wall Heath Brierley Hill Staffordshire DY6 0JP",
    "addr:housenumber":"14a-b",
    "addr:postcode":"dy6 0jp",
    "addr:street":"Albion Street Wall Heath",
    "iso:country":"GB",
    "sg:address":"14a-b Albion Street, Wall Heath",
    "sg:city":"Brierley Hill",
    "sg:classifiers":[
        {
            "category":"Professional",
            "type":"Services"
        }
    ],
    "sg:phone":"+44 1384 287483",
    "sg:postcode":"DY6 0JP",
    "sg:province":"Staffordshire",
    "sg:tags":[
        "repair",
        "tech",
        "maintenance"
    ],
    "wof:name":"Alliband Business Services",
    "wof:placetype":"venue"
},
  "geometry": {"coordinates":[-2.178913,52.504311],"type":"Point"}
}