{
  "type": "Feature",
  "properties": {
    "addr:full":"23 Wells Fold Close, Clayton Le Woods Chorley Lancashire PR6 7QJ",
    "addr:housenumber":"23",
    "addr:postcode":"pr6 7qj",
    "addr:street":"Wells Fold Close;Le",
    "iso:country":"GB",
    "sg:address":"23 Wells Fold Close, Clayton Le Woods",
    "sg:city":"Chorley",
    "sg:classifiers":[
        {
            "category":"Manufacturing",
            "subcategory":"Building Materials",
            "type":"Manufacturing & Wholesale Goods"
        }
    ],
    "sg:phone":"+44 1772 696580",
    "sg:postcode":"PR6 7QJ",
    "sg:province":"Lancashire",
    "sg:tags":[
        "tile",
        "mnfrs"
    ],
    "wof:name":"R.J. Garner",
    "wof:placetype":"venue"
},
  "geometry": {"coordinates":[-2.631362915,53.696144104],"type":"Point"}
}