{
  "type": "Feature",
  "properties": {
    "addr:full":"16 Wharfdale Rd Bournemouth Dorset BH4 9BT",
    "addr:housenumber":"16",
    "addr:postcode":"bh4 9bt",
    "addr:street":"Wharfdale Rd",
    "iso:country":"GB",
    "sg:address":"16 Wharfdale Rd",
    "sg:city":"Bournemouth",
    "sg:classifiers":[
        {
            "category":"Manufacturing",
            "subcategory":"Textiles",
            "type":"Manufacturing & Wholesale Goods"
        }
    ],
    "sg:phone":"+44 1202 540450",
    "sg:postcode":"BH4 9BT",
    "sg:province":"Dorset",
    "sg:tags":[
        "made-up"
    ],
    "wof:name":"The Bed Co",
    "wof:placetype":"venue"
},
  "geometry": {"coordinates":[-1.894633,50.723274],"type":"Point"}
}