{
  "type": "Feature",
  "properties": {
    "addr:full":"Longwhithy Lodge, Longwhithy Lane, Edgmond Newport Shropshire TF10 8EJ",
    "addr:postcode":"tf10 8ej",
    "addr:street":"Longwhithy Lane",
    "iso:country":"GB",
    "sg:address":"Longwhithy Lodge, Longwhithy Lane, Edgmond",
    "sg:city":"Newport",
    "sg:classifiers":[
        {
            "category":"Professional",
            "subcategory":"Employment Agencies",
            "type":"Services"
        }
    ],
    "sg:postcode":"TF10 8EJ",
    "sg:province":"Shropshire",
    "sg:tags":[
        "agricultural",
        "advice"
    ],
    "wof:name":"Maurice Eddowes",
    "wof:placetype":"venue"
},
  "geometry": {"coordinates":[-2.4108490944,52.7730445862],"type":"Point"}
}