{
  "type": "Feature",
  "properties": {
    "addr:full":"228 Stamford Street Central Ashton Under Lyne Greater Manchester OL6 7LJ",
    "addr:housenumber":"228",
    "addr:postcode":"ol6 7lj",
    "addr:street":"Stamford Street;Under Lyne",
    "iso:country":"GB",
    "sg:address":"228 Stamford Street Central",
    "sg:city":"Ashton Under Lyne",
    "sg:classifiers":[
        {
            "category":"Bars & Pubs",
            "subcategory":"Nightclub",
            "type":"Food & Drink"
        }
    ],
    "sg:phone":"+44 161 339 3090",
    "sg:postcode":"OL6 7LJ",
    "sg:province":"Greater Manchester",
    "sg:tags":[
        "club",
        "night"
    ],
    "wof:name":"Sparx Nightclub",
    "wof:placetype":"venue"
},
  "geometry": {"coordinates":[-2.0965809822,53.4865951538],"type":"Point"}
}