{
  "type": "Feature",
  "properties": {
    "addr:full":"16 Coppice Walk, Totteridge London Greater London N20 8BZ",
    "addr:housenumber":"16",
    "addr:postcode":"n20 8bz",
    "addr:street":"Coppice Walk",
    "iso:country":"GB",
    "sg:address":"16 Coppice Walk, Totteridge",
    "sg:city":"London",
    "sg:classifiers":[
        {
            "category":"Professional",
            "subcategory":"Detective & Security Services",
            "type":"Services"
        }
    ],
    "sg:postcode":"N20 8BZ",
    "sg:province":"Greater London",
    "sg:tags":[
        "locksmith"
    ],
    "wof:name":"Durkins Locksmiths",
    "wof:placetype":"venue"
},
  "geometry": {"coordinates":[-0.191399,51.626087],"type":"Point"}
}