{
  "type": "Feature",
  "properties": {
    "addr:full":"15 Market Place Cannock Staffordshire WS11 1BS",
    "addr:housenumber":"15",
    "addr:postcode":"ws11 1bs",
    "addr:street":"Market Place",
    "iso:country":"GB",
    "sg:address":"15 Market Place",
    "sg:city":"Cannock",
    "sg:classifiers":[
        {
            "category":"Health Services",
            "subcategory":"Optometrist",
            "type":"Services"
        }
    ],
    "sg:phone":"+44 1543 503343",
    "sg:postcode":"WS11 1BS",
    "sg:province":"Staffordshire",
    "sg:tags":[
        "optician"
    ],
    "wof:name":"Andrew L Bickley",
    "wof:placetype":"venue"
},
  "geometry": {"coordinates":[-2.030657053,52.688659668],"type":"Point"}
}