{
  "type": "Feature",
  "properties": {
    "iso:country":"GB",
    "sg:address":"Rockland, Ruthin Road, Gwernymynydd",
    "sg:city":"Mold",
    "sg:classifiers":[
        {
            "category":"Freight",
            "type":"Transportation"
        }
    ],
    "sg:phone":"+44 1352 758137",
    "sg:postcode":"CH7 5LG",
    "sg:province":"Denbighshire",
    "sg:tags":[
        "haulage",
        "road"
    ],
    "wof:name":"W Smith & Son",
    "wof:placetype":"venue"
},
  "geometry": {"coordinates":[-3.177687,53.152802],"type":"Point"}
}