{
  "type": "Feature",
  "properties": {
    "iso:country":"GB",
    "sg:address":"14 Station Crescent, Cold Norton",
    "sg:city":"Chelmsford",
    "sg:classifiers":[
        {
            "category":"Building & Trades",
            "subcategory":"Locksmith",
            "type":"Services"
        }
    ],
    "sg:phone":"+44 1621 784379",
    "sg:postcode":"CM3 6HY",
    "sg:province":"Essex",
    "wof:name":"Burnham Security",
    "wof:placetype":"venue"
},
  "geometry": {"coordinates":[0.671101,51.670666],"type":"Point"}
}