{
  "type": "Feature",
  "properties": {
    "addr:full":"High Street Gillingham Dorset SP8 4AA",
    "addr:postcode":"sp8 4aa",
    "addr:street":"High Street",
    "iso:country":"GB",
    "sg:address":"High Street",
    "sg:city":"Gillingham",
    "sg:classifiers":[
        {
            "category":"Shopping",
            "subcategory":"Pets & Pet Supplies",
            "type":"Retail Goods"
        }
    ],
    "sg:postcode":"SP8 4AA",
    "sg:province":"Dorset",
    "wof:name":"Paws Claws & Jaws",
    "wof:placetype":"venue"
},
  "geometry": {"coordinates":[-2.277444,51.0378],"type":"Point"}
}