{
  "type": "Feature",
  "properties": {
    "addr:full":"56a Waterloo Rd Southport Lancashire PR8 2LR",
    "addr:housenumber":"56a",
    "addr:postcode":"pr8 2lr",
    "addr:street":"Waterloo Rd",
    "iso:country":"GB",
    "sg:address":"56a Waterloo Rd",
    "sg:city":"Southport",
    "sg:classifiers":[
        {
            "category":"Health Services",
            "subcategory":"Doctor",
            "type":"Services"
        }
    ],
    "sg:phone":"+44 1704 566150",
    "sg:postcode":"PR8 2LR",
    "sg:province":"Lancashire",
    "sg:tags":[
        "practitioners"
    ],
    "wof:name":"Dr Bernard Samuels",
    "wof:placetype":"venue"
},
  "geometry": {"coordinates":[-3.027885,53.62466],"type":"Point"}
}