{
  "type": "Feature",
  "properties": {
    "addr:full":"Staple House, 7 Eleanors Cross Dunstable Bedfordshire LU6 1SU",
    "addr:housenumber":"staple;7",
    "addr:postcode":"lu6 1su",
    "addr:street":"Eleanors Cross",
    "iso:country":"GB",
    "sg:address":"Staple House, 7 Eleanors Cross",
    "sg:city":"Dunstable",
    "sg:classifiers":[
        {
            "category":"Real Estate",
            "subcategory":"Architect",
            "type":"Services"
        }
    ],
    "sg:phone":"+44 1582 476404",
    "sg:postcode":"LU6 1SU",
    "sg:province":"Bedfordshire",
    "sg:tags":[
        "architectural"
    ],
    "wof:name":"K J M Todd Associates",
    "wof:placetype":"venue"
},
  "geometry": {"coordinates":[-0.5228480101,51.8864173889],"type":"Point"}
}