{
  "type": "Feature",
  "properties": {
    "addr:full":"White Rose Close, York Business Park, Nether Poppleton York North Yorkshire YO23 1NY",
    "addr:postcode":"yo23 1ny",
    "addr:street":"Rose Close;Business Park",
    "iso:country":"GB",
    "sg:address":"White Rose Close, York Business Park, Nether Poppleton",
    "sg:city":"York",
    "sg:classifiers":[
        {
            "category":"Bars & Pubs",
            "type":"Food & Drink"
        }
    ],
    "sg:phone":"+44 1904 787630",
    "sg:postcode":"YO23 1NY",
    "sg:province":"North Yorkshire",
    "sg:tags":[
        "pubs",
        "inn"
    ],
    "wof:name":"Millfield Brewers Fayre & Travel Inn (The)",
    "wof:placetype":"venue"
},
  "geometry": {"coordinates":[-1.083427,53.953339],"type":"Point"}
}