{
  "type": "Feature",
  "properties": {
    "addr:full":"17-18 Opt Centre, Bryn Road, Tondu Bridgend Bridgend CF32 9BS",
    "addr:housenumber":"17-18",
    "addr:postcode":"cf32 9bs",
    "addr:street":"Opt Centre Bryn Road",
    "iso:country":"GB",
    "sg:address":"17-18 Opt Centre, Bryn Road, Tondu",
    "sg:city":"Bridgend",
    "sg:classifiers":[
        {
            "category":"Professional",
            "subcategory":"Accounting & Tax Preparation",
            "type":"Services"
        },
        {
            "category":"Shopping",
            "subcategory":"Clothing, Apparel, & Fashions",
            "type":"Retail Goods"
        },
        {
            "category":"Home & Garden",
            "subcategory":"Furniture",
            "type":"Retail Goods"
        }
    ],
    "sg:phone":"+44 1656 725551",
    "sg:postcode":"CF32 9BS",
    "sg:province":"Bridgend",
    "sg:tags":[
        "accountant",
        "protective",
        "workwear"
    ],
    "wof:name":"J & T Canopies",
    "wof:placetype":"venue"
},
  "geometry": {"coordinates":[-3.5998370647,51.5499343872],"type":"Point"}
}