{
  "type": "Feature",
  "properties": {
    "iso:country":"GB",
    "sg:address":"Long Shaw, Calcott Hill, Sturry",
    "sg:city":"Canterbury",
    "sg:classifiers":[
        {
            "category":"Shopping",
            "type":"Retail Goods"
        }
    ],
    "sg:phone":"+44 1227 710263",
    "sg:postcode":"CT3 4ND",
    "sg:province":"Kent",
    "sg:tags":[
        "merchant"
    ],
    "wof:name":"Long Shaw Farm",
    "wof:placetype":"venue"
},
  "geometry": {"coordinates":[1.118440032,51.3213882446],"type":"Point"}
}