{
  "type": "Feature",
  "properties": {
    "addr:full":"309 Millbrook Road West Southampton Hampshire SO15 0HU",
    "addr:housenumber":"309",
    "addr:postcode":"so15 0hu",
    "addr:street":"Millbrook Road West",
    "iso:country":"GB",
    "sg:address":"309 Millbrook Road West",
    "sg:city":"Southampton",
    "sg:classifiers":[
        {
            "category":"Bars & Pubs",
            "type":"Food & Drink"
        }
    ],
    "sg:postcode":"SO15 0HU",
    "sg:province":"Hampshire",
    "sg:tags":[
        "pubs",
        "inn"
    ],
    "wof:name":"The Sailors Return",
    "wof:placetype":"venue"
},
  "geometry": {"coordinates":[-1.4519389868,50.9147415161],"type":"Point"}
}