{
  "type": "Feature",
  "properties": {
    "iso:country":"GB",
    "sg:address":"Bank Top House, Lazonby",
    "sg:city":"Penrith",
    "sg:classifiers":[
        {
            "category":"Travel",
            "subcategory":"Hotels & Motels",
            "type":"Entertainment"
        }
    ],
    "sg:postcode":"CA10 1AQ",
    "sg:province":"Cumbria",
    "sg:tags":[
        "house",
        "guest"
    ],
    "wof:name":"Mary Carlyle",
    "wof:placetype":"venue"
},
  "geometry": {"coordinates":[-2.641319,54.706619],"type":"Point"}
}