{
  "type": "Feature",
  "properties": {
    "addr:full":"52 High Street, Ewell Epsom Surrey KT17 1RW",
    "addr:housenumber":"52",
    "addr:postcode":"kt17 1rw",
    "addr:street":"High Street",
    "iso:country":"GB",
    "sg:address":"52 High Street, Ewell",
    "sg:city":"Epsom",
    "sg:classifiers":[
        {
            "category":"Fast Food",
            "type":"Food & Drink"
        }
    ],
    "sg:phone":"+44 20 8394 0077",
    "sg:postcode":"KT17 1RW",
    "sg:province":"Surrey",
    "sg:tags":[
        "away",
        "take"
    ],
    "wof:name":"Paprika",
    "wof:placetype":"venue"
},
  "geometry": {"coordinates":[-0.249089,51.349079],"type":"Point"}
}