{
  "type": "Feature",
  "properties": {
    "iso:country":"GB",
    "sg:address":"63 Bradenstoke",
    "sg:city":"Chippenham",
    "sg:classifiers":[
        {
            "category":"Government",
            "subcategory":"Post Office",
            "type":"Public Place"
        }
    ],
    "sg:phone":"+44 1249 890357",
    "sg:postcode":"SN15 4EL",
    "sg:province":"Wiltshire",
    "wof:name":"Bradenstoke Post Office",
    "wof:placetype":"venue"
},
  "geometry": {"coordinates":[-2.0018,51.51302],"type":"Point"}
}