{
  "type": "Feature",
  "properties": {
    "addr:full":"41 The Plaza, Town Centre, East Kilbride Glasgow South Lanarkshire G74 1LW",
    "addr:housenumber":"41",
    "addr:postcode":"g74 1lw",
    "addr:street":"The",
    "iso:country":"GB",
    "sg:address":"41 The Plaza, Town Centre, East Kilbride",
    "sg:city":"Glasgow",
    "sg:classifiers":[
        {
            "category":"Shopping",
            "subcategory":"Books",
            "type":"Retail Goods"
        }
    ],
    "sg:phone":"+44 1355 220266",
    "sg:postcode":"G74 1LW",
    "sg:province":"South Lanarkshire",
    "sg:tags":[
        "bookseller"
    ],
    "wof:name":"Bargain Books",
    "wof:placetype":"venue"
},
  "geometry": {"coordinates":[-4.1799001694,55.7600784302],"type":"Point"}
}