{
  "type": "Feature",
  "properties": {
    "addr:full":"99 Richardson Drive, Wollaston Park Stourbridge Staffordshire DY8 4DN",
    "addr:housenumber":"99",
    "addr:postcode":"dy8 4dn",
    "addr:street":"Richardson Drive",
    "iso:country":"GB",
    "sg:address":"99 Richardson Drive, Wollaston Park",
    "sg:city":"Stourbridge",
    "sg:classifiers":[
        {
            "category":"Building & Trades",
            "subcategory":"Construction",
            "type":"Services"
        }
    ],
    "sg:phone":"+44 1384 441836",
    "sg:postcode":"DY8 4DN",
    "sg:province":"Staffordshire",
    "sg:tags":[
        "builder"
    ],
    "wof:name":"Jason P K Monkton",
    "wof:placetype":"venue"
},
  "geometry": {"coordinates":[-2.1594591141,52.4704971313],"type":"Point"}
}