{
  "type": "Feature",
  "properties": {
    "addr:full":"Flat 4, 8 Canterbury Rd Herne Bay Kent CT6 5HP",
    "addr:housenumber":"8",
    "addr:postcode":"ct6 5hp",
    "addr:street":"Canterbury Rd",
    "iso:country":"GB",
    "sg:address":"Flat 4, 8 Canterbury Rd",
    "sg:city":"Herne Bay",
    "sg:classifiers":[
        {
            "category":"Sports & Exercise",
            "subcategory":"Gym",
            "type":"Entertainment"
        }
    ],
    "sg:postcode":"CT6 5HP",
    "sg:province":"Kent",
    "sg:tags":[
        "fitness",
        "health",
        "centre"
    ],
    "wof:name":"Curry,M,",
    "wof:placetype":"venue"
},
  "geometry": {"coordinates":[1.1251,51.371216],"type":"Point"}
}