{
  "type": "Feature",
  "properties": {
    "iso:country":"GB",
    "sg:address":"30a St James Place, Magotsfield",
    "sg:city":"Bristol",
    "sg:classifiers":[
        {
            "category":"Banks & Credit Unions",
            "subcategory":"Financial Services",
            "type":"Services"
        }
    ],
    "sg:phone":"+44 117 956 1067",
    "sg:postcode":"BS16 9JB",
    "sg:province":"City of Bristol",
    "sg:tags":[
        "consultant"
    ],
    "wof:name":"Oakway Investments Ltd.",
    "wof:placetype":"venue"
},
  "geometry": {"coordinates":[-2.4851839542,51.4828224182],"type":"Point"}
}