{
  "type": "Feature",
  "properties": {
    "addr:full":"Area Office, 2-4 Victoria Road Kirkcaldy Fife KY1 2SA",
    "addr:housenumber":"2-4",
    "addr:postcode":"ky1 2sa",
    "addr:street":"Victoria Road",
    "iso:country":"GB",
    "sg:address":"Area Office, 2-4 Victoria Road",
    "sg:city":"Kirkcaldy",
    "sg:classifiers":[
        {
            "category":"Organizations",
            "subcategory":"Non-profit Organization",
            "type":"Services"
        }
    ],
    "sg:phone":"+44 1592 646474",
    "sg:postcode":"KY1 2SA",
    "sg:province":"Fife",
    "sg:tags":[
        "organisation",
        "voluntary",
        "charity"
    ],
    "wof:name":"W R V S",
    "wof:placetype":"venue"
},
  "geometry": {"coordinates":[-3.163029,56.109596],"type":"Point"}
}