{
  "type": "Feature",
  "properties": {
    "addr:full":"Unit E, Chequers Lane Derby Derbyshire DE21 6AW",
    "addr:postcode":"de21 6aw",
    "addr:street":"Chequers Lane",
    "iso:country":"GB",
    "sg:address":"Unit E, Chequers Lane",
    "sg:city":"Derby",
    "sg:classifiers":[
        {
            "category":"Retail",
            "subcategory":"Auto Repair",
            "type":"Services"
        }
    ],
    "sg:phone":"+44 1332 202620",
    "sg:postcode":"DE21 6AW",
    "sg:province":"Derbyshire",
    "sg:tags":[
        "modification",
        "garage"
    ],
    "wof:name":"Hughes Bros Vehicle Repairs",
    "wof:placetype":"venue"
},
  "geometry": {"coordinates":[-1.454848,52.924717],"type":"Point"}
}