{
  "type": "Feature",
  "properties": {
    "addr:full":"46 Bedford Place Southampton Hampshire SO15 2DG",
    "addr:housenumber":"46",
    "addr:postcode":"so15 2dg",
    "addr:street":"Bedford Place",
    "iso:country":"GB",
    "sg:address":"46 Bedford Place",
    "sg:city":"Southampton",
    "sg:classifiers":[
        {
            "category":"Personal",
            "subcategory":"Beauty Salon",
            "type":"Services"
        }
    ],
    "sg:phone":"+44 23 8063 1292",
    "sg:postcode":"SO15 2DG",
    "sg:province":"Hampshire",
    "sg:tags":[
        "unisex",
        "hairdresser"
    ],
    "wof:name":"Arcana Ltd.",
    "wof:placetype":"venue"
},
  "geometry": {"coordinates":[-1.406261,50.913525],"type":"Point"}
}