{
  "type": "Feature",
  "properties": {
    "iso:country":"GB",
    "sg:address":"Hanover Ct, 5 Queen St",
    "sg:city":"Lichfield",
    "sg:classifiers":[
        {
            "category":"Bus Stop",
            "subcategory":"None",
            "type":"Transportation"
        }
    ],
    "sg:postcode":"WS13 6QD",
    "sg:province":"Staffordshire",
    "sg:tags":[
        "curtain",
        "walling"
    ],
    "wof:name":"Curtainwall Engineering Ltd",
    "wof:placetype":"venue"
},
  "geometry": {"coordinates":[-1.81966,52.684029],"type":"Point"}
}