{
  "type": "Feature",
  "properties": {
    "addr:full":"Main Street, Symington Kilmarnock East Ayrshire KA1 5QB",
    "addr:postcode":"ka1 5qb",
    "addr:street":"Main Street",
    "iso:country":"GB",
    "sg:address":"Main Street, Symington",
    "sg:city":"Kilmarnock",
    "sg:classifiers":[
        {
            "category":"Bars & Pubs",
            "type":"Food & Drink"
        },
        {
            "category":"Restaurant",
            "type":"Food & Drink"
        }
    ],
    "sg:phone":"+44 1563 830307",
    "sg:postcode":"KA1 5QB",
    "sg:province":"East Ayrshire",
    "sg:tags":[
        "-"
    ],
    "wof:name":"Wheatsheaf Inn Symington",
    "wof:placetype":"venue"
},
  "geometry": {"coordinates":[-4.4911608696,55.5602111816],"type":"Point"}
}