{
  "type": "Feature",
  "properties": {
    "addr:full":"35 Tudor Crescent, Otford Sevenoaks Kent TN14 5QT",
    "addr:housenumber":"35",
    "addr:postcode":"tn14 5qt",
    "addr:street":"Tudor Crescent",
    "iso:country":"GB",
    "sg:address":"35 Tudor Crescent, Otford",
    "sg:city":"Sevenoaks",
    "sg:classifiers":[
        {
            "category":"Professional",
            "subcategory":"Engineering",
            "type":"Services"
        },
        {
            "category":"Professional",
            "subcategory":"Management & Consulting",
            "type":"Services"
        }
    ],
    "sg:postcode":"TN14 5QT",
    "sg:province":"Kent",
    "sg:tags":[
        "consultant",
        "safety",
        "engineer"
    ],
    "wof:name":"Phillip Machen & Associates",
    "wof:placetype":"venue"
},
  "geometry": {"coordinates":[0.2013289928,51.3097343445],"type":"Point"}
}