{
  "type": "Feature",
  "properties": {
    "addr:full":"285 Lever Street Bolton Lancashire BL3 6PD",
    "addr:housenumber":"285",
    "addr:postcode":"bl3 6pd",
    "addr:street":"Lever Street",
    "iso:country":"GB",
    "sg:address":"285 Lever Street",
    "sg:city":"Bolton",
    "sg:classifiers":[
        {
            "category":"Food & Beverages",
            "subcategory":"Candy",
            "type":"Retail Goods"
        }
    ],
    "sg:phone":"+44 1204 526983",
    "sg:postcode":"BL3 6PD",
    "sg:province":"Lancashire",
    "sg:tags":[
        "confectioner"
    ],
    "wof:name":"N & H Dutson",
    "wof:placetype":"venue"
},
  "geometry": {"coordinates":[-2.4323420525,53.5679550171],"type":"Point"}
}