{
  "type": "Feature",
  "properties": {
    "addr:full":"The Camden Centre, Market Square, Royal Victoria Place Tunbridge Wells Kent TN1 2SW",
    "addr:postcode":"tn1 2sw",
    "addr:street":"Market Square Royal Victoria Place;Wells",
    "iso:country":"GB",
    "sg:address":"The Camden Centre, Market Square, Royal Victoria Place",
    "sg:city":"Tunbridge Wells",
    "sg:classifiers":[
        {
            "category":"Recreation",
            "subcategory":"Dog Park",
            "type":"Entertainment"
        }
    ],
    "sg:phone":"+44 1892 528848",
    "sg:postcode":"TN1 2SW",
    "sg:province":"Kent",
    "wof:name":"Tunbridge Wells Dog Training Club",
    "wof:placetype":"venue"
},
  "geometry": {"coordinates":[0.26355,51.133373],"type":"Point"}
}