{
  "type": "Feature",
  "properties": {
    "iso:country":"GB",
    "sg:address":"77 Pinders Rd",
    "sg:city":"Hastings",
    "sg:classifiers":[
        {
            "category":"Arts & Performance",
            "subcategory":"Music",
            "type":"Entertainment"
        }
    ],
    "sg:phone":"+44 7885 301229",
    "sg:postcode":"TN35 5LJ",
    "sg:province":"East Sussex",
    "sg:tags":[
        "mobile",
        "disco"
    ],
    "wof:name":"Supreme Temptation",
    "wof:placetype":"venue"
},
  "geometry": {"coordinates":[0.6105350256,50.8663978577],"type":"Point"}
}