{
  "type": "Feature",
  "properties": {
    "addr:full":"30 Liverpool Street London Greater London EC2M 7PP",
    "addr:housenumber":"30",
    "addr:postcode":"ec2m 7pp",
    "addr:street":"Liverpool Street",
    "iso:country":"GB",
    "sg:address":"30 Liverpool Street",
    "sg:city":"London",
    "sg:classifiers":[
        {
            "category":"Shopping",
            "subcategory":"Comic Books",
            "type":"Retail Goods"
        }
    ],
    "sg:phone":"+44 20 7626 5051",
    "sg:postcode":"EC2M 7PP",
    "sg:province":"Greater London",
    "sg:tags":[
        "jeweller"
    ],
    "wof:name":"Johnathan Geeves Jewellers",
    "wof:placetype":"venue"
},
  "geometry": {"coordinates":[-0.0840319991,51.5175704956],"type":"Point"}
}