{
  "type": "Feature",
  "properties": {
    "iso:country":"GB",
    "sg:address":"5 Brynafon Road, Gorseinon",
    "sg:city":"Swansea",
    "sg:classifiers":[
        {
            "category":"Personal",
            "subcategory":"Beauty Salon",
            "type":"Services"
        }
    ],
    "sg:phone":"+44 1792 896990",
    "sg:postcode":"SA4 4YF",
    "sg:province":"Carmarthenshire",
    "sg:tags":[
        "unisex",
        "hairdresser"
    ],
    "wof:name":"Cut 'N' Curl",
    "wof:placetype":"venue"
},
  "geometry": {"coordinates":[-4.0534729958,51.673412323],"type":"Point"}
}