{
  "type": "Feature",
  "properties": {
    "addr:full":"38 Radford Rd Nottingham Nottinghamshire NG7 5FS",
    "addr:housenumber":"38",
    "addr:postcode":"ng7 5fs",
    "addr:street":"Radford Rd",
    "iso:country":"GB",
    "sg:address":"38 Radford Rd",
    "sg:city":"Nottingham",
    "sg:classifiers":[
        {
            "category":"Real Estate",
            "subcategory":"Real Estate Agent",
            "type":"Services"
        }
    ],
    "sg:phone":"+44 115 978 7740",
    "sg:postcode":"NG7 5FS",
    "sg:province":"Nottinghamshire",
    "wof:name":"G H L Property Services",
    "wof:placetype":"venue"
},
  "geometry": {"coordinates":[-1.1690789461,52.9635696411],"type":"Point"}
}