{
  "type": "Feature",
  "properties": {
    "addr:full":"3rd Floor Centre Point, 103 New Oxford Street London Greater London WC1A 1DP",
    "addr:housenumber":"3rd floor centre;103",
    "addr:postcode":"wc1a 1dp",
    "addr:street":"New Oxford Street",
    "iso:country":"GB",
    "sg:address":"3rd Floor Centre Point, 103 New Oxford Street",
    "sg:city":"London",
    "sg:classifiers":[
        {
            "category":"Professional",
            "subcategory":"Management & Consulting",
            "type":"Services"
        }
    ],
    "sg:phone":"+44 20 7316 1000",
    "sg:postcode":"WC1A 1DP",
    "sg:province":"Greater London",
    "sg:tags":[
        "consultant",
        "business"
    ],
    "wof:name":"Business Link London Central Ltd.",
    "wof:placetype":"venue"
},
  "geometry": {"coordinates":[-0.14439,51.514931],"type":"Point"}
}