{
  "type": "Feature",
  "properties": {
    "addr:full":"213a Belsize Road London Greater London NW6 4AA",
    "addr:housenumber":"213a",
    "addr:postcode":"nw6 4aa",
    "addr:street":"Belsize Road",
    "iso:country":"GB",
    "sg:address":"213a Belsize Road",
    "sg:city":"London",
    "sg:classifiers":[
        {
            "category":"Cinema",
            "subcategory":"Movie Rental",
            "type":"Entertainment"
        }
    ],
    "sg:phone":"+44 20 7328 7060",
    "sg:postcode":"NW6 4AA",
    "sg:province":"Greater London",
    "sg:tags":[
        "video",
        "library"
    ],
    "wof:name":"David's Video World",
    "wof:placetype":"venue"
},
  "geometry": {"coordinates":[-0.1908259988,51.538269043],"type":"Point"}
}