{
  "type": "Feature",
  "properties": {
    "addr:full":"Falcon Avenue Darwen Lancashire BB3 1QX",
    "addr:postcode":"bb3 1qx",
    "addr:street":"Falcon Avenue",
    "iso:country":"GB",
    "sg:address":"Falcon Avenue",
    "sg:city":"Darwen",
    "sg:classifiers":[
        {
            "category":"Organizations",
            "subcategory":"Community Association",
            "type":"Services"
        },
        {
            "category":"Organizations",
            "subcategory":"Membership Organization",
            "type":"Services"
        }
    ],
    "sg:phone":"+44 1254 703168",
    "sg:postcode":"BB3 1QX",
    "sg:province":"Lancashire",
    "sg:tags":[
        "club",
        "social"
    ],
    "wof:name":"Hollins Grove Liberal Club",
    "wof:placetype":"venue"
},
  "geometry": {"coordinates":[-2.4787490368,53.7058334351],"type":"Point"}
}