{
  "type": "Feature",
  "properties": {
    "iso:country":"GB",
    "sg:address":"47 St James Road",
    "sg:city":"London",
    "sg:classifiers":[
        {
            "category":"Health Services",
            "subcategory":"Clinic",
            "type":"Services"
        }
    ],
    "sg:phone":"+44 20 8520 4748",
    "sg:postcode":"E17 7PG",
    "sg:province":"Greater London",
    "sg:tags":[
        "nh",
        "private"
    ],
    "wof:name":"Walthamstow  Leyton & Leytonstone Primary Care Trust",
    "wof:placetype":"venue"
},
  "geometry": {"coordinates":[0.014072,51.549149],"type":"Point"}
}