{
  "type": "Feature",
  "properties": {
    "iso:country":"GB",
    "sg:address":"82 Tollwood Park",
    "sg:city":"Crowborough",
    "sg:classifiers":[
        {
            "category":"Social Services",
            "subcategory":"Child Care",
            "type":"Services"
        }
    ],
    "sg:postcode":"TN6 2XS",
    "sg:province":"East Sussex",
    "sg:tags":[
        "agency",
        "nanny"
    ],
    "wof:name":"East Green Child Care Services",
    "wof:placetype":"venue"
},
  "geometry": {"coordinates":[0.1782,51.049301],"type":"Point"}
}