{
  "type": "Feature",
  "properties": {
    "addr:full":"8 Guildford Street Chertsey Surrey KT16 9BQ",
    "addr:housenumber":"8",
    "addr:postcode":"kt16 9bq",
    "addr:street":"Guildford Street",
    "iso:country":"GB",
    "sg:address":"8 Guildford Street",
    "sg:city":"Chertsey",
    "sg:classifiers":[
        {
            "category":"Food & Beverages",
            "subcategory":"Bakery",
            "type":"Retail Goods"
        }
    ],
    "sg:phone":"+44 1932 563059",
    "sg:postcode":"KT16 9BQ",
    "sg:province":"Surrey",
    "sg:tags":[
        "baker"
    ],
    "wof:name":"Park Bakery",
    "wof:placetype":"venue"
},
  "geometry": {"coordinates":[-0.5093740225,51.3864822388],"type":"Point"}
}