{
  "type": "Feature",
  "properties": {
    "addr:full":"66 Hornsland Rd Canvey Island Essex SS8 8LY",
    "addr:housenumber":"66",
    "addr:postcode":"ss8 8ly",
    "addr:street":"Hornsland Rd",
    "iso:country":"GB",
    "sg:address":"66 Hornsland Rd",
    "sg:city":"Canvey Island",
    "sg:classifiers":[
        {
            "category":"Building & Trades",
            "subcategory":"Construction",
            "type":"Services"
        }
    ],
    "sg:phone":"+44 1268 698771",
    "sg:postcode":"SS8 8LY",
    "sg:province":"Essex",
    "sg:tags":[
        "platform",
        "work",
        "scaffolding"
    ],
    "wof:name":"C & K Scaffolding Contractors",
    "wof:placetype":"venue"
},
  "geometry": {"coordinates":[0.614251,51.521648],"type":"Point"}
}