{
  "type": "Feature",
  "properties": {
    "iso:country":"GB",
    "sg:address":"Unit 2, Victoria Business Park, Netherfield",
    "sg:city":"Nottingham",
    "sg:classifiers":[
        {
            "category":"Home & Garden",
            "subcategory":"Kitchen Supply",
            "type":"Retail Goods"
        }
    ],
    "sg:phone":"+44 115 987 2326",
    "sg:postcode":"NG4 2PE",
    "sg:province":"Nottinghamshire",
    "sg:tags":[
        "ware"
    ],
    "wof:name":"Moben Kitchens",
    "wof:placetype":"venue"
},
  "geometry": {"coordinates":[-1.068489,52.961514],"type":"Point"}
}