{
  "type": "Feature",
  "properties": {
    "iso:country":"GB",
    "sg:address":"Unit 1",
    "sg:city":"London",
    "sg:classifiers":[
        {
            "category":"Fast Food",
            "type":"Food & Drink"
        }
    ],
    "sg:phone":"+44 20 8532 9206",
    "sg:postcode":"E18 1AY",
    "sg:province":"Greater London",
    "sg:tags":[
        "away",
        "take"
    ],
    "wof:name":"Bib & Tucker",
    "wof:placetype":"venue"
},
  "geometry": {"coordinates":[0.02892,51.592972],"type":"Point"}
}