{
  "type": "Feature",
  "properties": {
    "addr:full":"1 Cemetery Lane, Charlton London Greater London SE7 8DU",
    "addr:housenumber":"1",
    "addr:postcode":"se7 8du",
    "addr:street":"Cemetery Lane",
    "iso:country":"GB",
    "sg:address":"1 Cemetery Lane, Charlton",
    "sg:city":"London",
    "sg:classifiers":[
        {
            "category":"Building & Trades",
            "subcategory":"Construction",
            "type":"Services"
        }
    ],
    "sg:phone":"+44 20 8859 0666",
    "sg:postcode":"SE7 8DU",
    "sg:province":"Greater London",
    "sg:tags":[
        "glass",
        "replacement"
    ],
    "wof:name":"Eltham Glass",
    "wof:placetype":"venue"
},
  "geometry": {"coordinates":[0.0462500006,51.4823226929],"type":"Point"}
}