{"geometry":{"type":"Point","coordinates":[-0.596114,51.674656]},"type":"Feature","id":102560547,"bbox":[-0.596114,51.674656,-0.596114,51.674656],"properties":{"sg:province":"Buckinghamshire","sg:tags":["importer","merchants","agent","timber"],"geom:longitude":-0.596114,"wof:breaches":[],"sg:href":"http://api.simplegeo.com/1.0/features/SG_5Ett1SaifSE6rcIYYMvRkO_51.674656_-0.596114@1300740015.json","sg:owner":"simplegeo","sg:postcode":"HP6 6PD","geom:latitude":51.674656,"sg:classifiers":[{"category":"Manufacturing","type":"Manufacturing & Wholesale Goods","subcategory":"Lumber"}],"sg:address":"Bell Lane, Amersham Common","sg:phone":"+44 1494 762503","wof:hierarchy":[{"locality_id":101854803,"venue_id":102560547,"country_id":85633159,"region_id":85684231}],"geom:area":0.000000,"sg:city":"Amersham","wof:lastmodified":1438093286,"iso:country":"GB","wof:geomhash":"0d077a9684ff1fdde1f93160ad75656f","wof:name":"Latimer Sawmills Ltd.","wof:belongsto":[101854803,85633159,85684231],"src:geom":"simplegeo","wof:placetype":"venue","wof:supersedes":[],"wof:id":102560547,"wof:superseded_by":[],"wof:concordances":{"sg:id":"SG_5Ett1SaifSE6rcIYYMvRkO_51.674656_-0.596114@1300740015"},"wof:parent_id":101854803}}