{
  "type": "Feature",
  "properties": {
    "addr:full":"Bell Lane, Amersham Common Amersham Buckinghamshire HP6 6PD",
    "addr:postcode":"amersham;hp6 6pd",
    "addr:street":"Bell Lane;Common",
    "iso:country":"GB",
    "sg:address":"Bell Lane, Amersham Common",
    "sg:city":"Amersham",
    "sg:classifiers":[
        {
            "category":"Manufacturing",
            "subcategory":"Lumber",
            "type":"Manufacturing & Wholesale Goods"
        }
    ],
    "sg:href":"http://api.simplegeo.com/1.0/features/SG_5Ett1SaifSE6rcIYYMvRkO_51.674656_-0.596114@1300740015.json",
    "sg:phone":"+44 1494 762503",
    "sg:postcode":"HP6 6PD",
    "sg:province":"Buckinghamshire",
    "sg:tags":[
        "importer",
        "merchants",
        "agent",
        "timber"
    ],
    "wof:name":"Latimer Sawmills Ltd.",
    "wof:placetype":"venue"
},
  "geometry": {"coordinates":[-0.596114,51.674656],"type":"Point"}
}