{
  "type": "Feature",
  "properties": {
    "addr:full":"68 Hollywood Way Woodford Green Essex IG8 9LQ",
    "addr:housenumber":"68",
    "addr:postcode":"ig8 9lq",
    "addr:street":"Hollywood Way",
    "iso:country":"GB",
    "sg:address":"68 Hollywood Way",
    "sg:city":"Woodford Green",
    "sg:classifiers":[
        {
            "category":"Home & Garden",
            "subcategory":"Household Appliances",
            "type":"Retail Goods"
        }
    ],
    "sg:phone":"+44 20 8527 4522",
    "sg:postcode":"IG8 9LQ",
    "sg:province":"Essex",
    "sg:tags":[
        "electrical"
    ],
    "wof:name":"J P Services",
    "wof:placetype":"venue"
},
  "geometry": {"coordinates":[0.0063840002,51.6054496765],"type":"Point"}
}