{
  "type": "Feature",
  "properties": {
    "addr:full":"P O Box 143 Ramsgate Kent CT12 6GE",
    "addr:housenumber":"143",
    "addr:postcode":"ct12 6ge",
    "addr:street":"P O Box;Ramsgate",
    "iso:country":"GB",
    "sg:address":"P O Box 143",
    "sg:city":"Ramsgate",
    "sg:classifiers":[
        {
            "category":"Professional",
            "subcategory":"Lawyer & Legal Services",
            "type":"Services"
        }
    ],
    "sg:phone":"+44 1843 591728",
    "sg:postcode":"CT12 6GE",
    "sg:province":"Kent",
    "sg:tags":[
        "writing"
    ],
    "wof:name":"Simply Wills Ltd",
    "wof:placetype":"venue"
},
  "geometry": {"coordinates":[1.400159955,51.3474006653],"type":"Point"}
}