{
  "type": "Feature",
  "properties": {
    "addr:full":"121e Woodcote Road Wallington Surrey SM6 0QL",
    "addr:housenumber":"121e",
    "addr:postcode":"sm6 0ql",
    "addr:street":"Woodcote Road",
    "iso:country":"GB",
    "sg:address":"121e Woodcote Road",
    "sg:city":"Wallington",
    "sg:classifiers":[
        {
            "category":"Real Estate",
            "subcategory":"Real Estate Agent",
            "type":"Services"
        }
    ],
    "sg:postcode":"SM6 0QL",
    "sg:province":"Surrey",
    "wof:name":"Barrons Properties Ltd",
    "wof:placetype":"venue"
},
  "geometry": {"coordinates":[-0.147912994,51.3498497009],"type":"Point"}
}