{
  "type": "Feature",
  "properties": {
    "iso:country":"GB",
    "sg:address":"4 Inchyra Road",
    "sg:city":"Grangemouth",
    "sg:classifiers":[
        {
            "category":"Professional",
            "subcategory":"Business Services",
            "type":"Services"
        }
    ],
    "sg:postcode":"FK3 9XB",
    "sg:province":"Falkirk",
    "sg:tags":[
        "assessment",
        "quality"
    ],
    "wof:name":"Bairdwear Bureau of Standards",
    "wof:placetype":"venue"
},
  "geometry": {"coordinates":[-3.705532074,56.0102348328],"type":"Point"}
}