{
  "type": "Feature",
  "properties": {
    "iso:country":"GB",
    "sg:address":"66 Central Hill, Gipsy Hill",
    "sg:city":"Upper Norwood",
    "sg:classifiers":[
        {
            "category":"Government",
            "subcategory":"Police Station",
            "type":"Public Place"
        }
    ],
    "sg:phone":"+44 20 8670 1212",
    "sg:postcode":"SE19 1DT",
    "sg:province":"Greater London",
    "sg:tags":[
        "support"
    ],
    "wof:name":"Police",
    "wof:placetype":"venue"
},
  "geometry": {"coordinates":[-0.084413,51.419621],"type":"Point"}
}