{
  "type": "Feature",
  "properties": {
    "iso:country":"GB",
    "sg:address":"1 Ethel Avenue",
    "sg:city":"Manchester",
    "sg:classifiers":[
        {
            "category":"Shopping",
            "subcategory":"Shoes",
            "type":"Retail Goods"
        }
    ],
    "sg:postcode":"M9 6RR",
    "sg:province":"Greater Manchester",
    "wof:name":"Alan Matthews",
    "wof:placetype":"venue"
},
  "geometry": {"coordinates":[-2.213636,53.532372],"type":"Point"}
}