{
  "type": "Feature",
  "properties": {
    "iso:country":"GB",
    "sg:address":"Glanrafon Cottage, Cefn Road, Abenbury",
    "sg:city":"Wrexham",
    "sg:classifiers":[
        {
            "category":"Building & Trades",
            "subcategory":"Construction",
            "type":"Services"
        }
    ],
    "sg:phone":"+44 1978 262537",
    "sg:postcode":"LL13 0PA",
    "sg:province":"Wrexham",
    "sg:tags":[
        "roofing"
    ],
    "wof:name":"M Gibson & Sons Roofing & Building",
    "wof:placetype":"venue"
},
  "geometry": {"coordinates":[-2.9457199574,53.0281600952],"type":"Point"}
}