{
  "type": "Feature",
  "properties": {
    "addr:full":"A B C House, Townsend Lane London Greater London NW9 8LL",
    "addr:postcode":"nw9 8ll",
    "addr:street":"A;Townsend Lane",
    "iso:country":"GB",
    "sg:address":"A B C House, Townsend Lane",
    "sg:city":"London",
    "sg:classifiers":[
        {
            "category":"Autos & Motor Vehicles",
            "subcategory":"Motorcycle Sales",
            "type":"Retail Goods"
        }
    ],
    "sg:phone":"+44 20 8930 3039",
    "sg:postcode":"NW9 8LL",
    "sg:province":"Greater London",
    "sg:tags":[
        "chauffeur",
        "driven",
        "car"
    ],
    "wof:name":"Goldmarsh Service",
    "wof:placetype":"venue"
},
  "geometry": {"coordinates":[-0.2567889988,51.5800514221],"type":"Point"}
}