{
  "type": "Feature",
  "properties": {
    "iso:country":"GB",
    "sg:address":"Potovens La",
    "sg:city":"Wakefield",
    "sg:classifiers":[
        {
            "category":"Social Services",
            "subcategory":"Adult Care",
            "type":"Services"
        }
    ],
    "sg:phone":"+44 1924 826881",
    "sg:postcode":"WF1 2LQ",
    "sg:province":"West Yorkshire",
    "sg:tags":[
        "housing",
        "sheltered"
    ],
    "wof:name":"Springhills Sheltered Housing",
    "wof:placetype":"venue"
},
  "geometry": {"coordinates":[-1.5098689795,53.7121734619],"type":"Point"}
}