{
  "type": "Feature",
  "properties": {
    "iso:country":"GB",
    "sg:address":"Northmere Road",
    "sg:city":"Poole",
    "sg:classifiers":[
        {
            "category":"Community Center",
            "subcategory":"Youth",
            "type":"Public Place"
        },
        {
            "category":"Government",
            "subcategory":"Office",
            "type":"Public Place"
        }
    ],
    "sg:phone":"+44 1202 740113",
    "sg:postcode":"BH12 4DY",
    "sg:province":"Dorset",
    "sg:tags":[
        "organisation",
        "local",
        "centre"
    ],
    "wof:name":"Bourne Valley Youth Centre",
    "wof:placetype":"venue"
},
  "geometry": {"coordinates":[-1.9230940342,50.7368659973],"type":"Point"}
}