{
  "type": "Feature",
  "properties": {
    "iso:country":"GB",
    "sg:address":"The Bridge, Norwich Rd",
    "sg:city":"Norwich",
    "sg:classifiers":[
        {
            "category":"Fast Food",
            "type":"Food & Drink"
        }
    ],
    "sg:phone":"+44 1603 782810",
    "sg:postcode":"NR12 8DA",
    "sg:province":"Norfolk",
    "sg:tags":[
        "away",
        "take"
    ],
    "wof:name":"Picnic Basket The",
    "wof:placetype":"venue"
},
  "geometry": {"coordinates":[1.405208,52.711136],"type":"Point"}
}