{
  "type": "Feature",
  "properties": {
    "addr:full":"12 Frogmore High Wycombe Buckinghamshire HP13 5DG",
    "addr:housenumber":"12",
    "addr:postcode":"hp13 5dg",
    "addr:street":"Frogmore High",
    "iso:country":"GB",
    "sg:address":"12 Frogmore",
    "sg:city":"High Wycombe",
    "sg:classifiers":[
        {
            "category":"Professional",
            "type":"Services"
        },
        {
            "category":"Fast Food",
            "type":"Food & Drink"
        }
    ],
    "sg:phone":"+44 1494 444333",
    "sg:postcode":"HP13 5DG",
    "sg:province":"Buckinghamshire",
    "sg:tags":[
        "away",
        "take",
        "caterer"
    ],
    "wof:name":"Taz Enterprises Ltd.",
    "wof:placetype":"venue"
},
  "geometry": {"coordinates":[-0.7524790168,51.6323509216],"type":"Point"}
}