{
  "type": "Feature",
  "properties": {
    "iso:country":"GB",
    "sg:address":"Hall Street, Long Melford",
    "sg:city":"Sudbury",
    "sg:classifiers":[
        {
            "category":"Health Services",
            "subcategory":"Nursing And Care Facility",
            "type":"Services"
        }
    ],
    "sg:phone":"+44 1787 880545",
    "sg:postcode":"CO10 9JA",
    "sg:province":"Essex",
    "sg:tags":[
        "home"
    ],
    "wof:name":"Melford Court Nursing Home",
    "wof:placetype":"venue"
},
  "geometry": {"coordinates":[0.71648,52.075264],"type":"Point"}
}