{
  "type": "Feature",
  "properties": {
    "iso:country":"GB",
    "sg:address":"The Barn, Lower Cowsden Farm, Upton Snodsbury",
    "sg:city":"Worcester",
    "sg:classifiers":[
        {
            "category":"Sports & Exercise",
            "subcategory":"Stables",
            "type":"Entertainment"
        }
    ],
    "sg:phone":"+44 1905 381077",
    "sg:postcode":"WR7 4NY",
    "sg:province":"Worcestershire",
    "sg:tags":[
        "education",
        "equestrian"
    ],
    "wof:name":"N A Smith",
    "wof:placetype":"venue"
},
  "geometry": {"coordinates":[-2.085764,52.188965],"type":"Point"}
}