{
  "type": "Feature",
  "properties": {
    "iso:country":"GB",
    "sg:address":"116 Stourbridge Road, Lye",
    "sg:city":"Stourbridge",
    "sg:classifiers":[
        {
            "category":"Shopping",
            "subcategory":"Antiques",
            "type":"Retail Goods"
        },
        {
            "category":"Home & Garden",
            "subcategory":"Furniture",
            "type":"Retail Goods"
        }
    ],
    "sg:phone":"+44 1384 868778",
    "sg:postcode":"DY9 7BU",
    "sg:province":"West Midlands",
    "wof:name":"Regency Antiques Trading Centre",
    "wof:placetype":"venue"
},
  "geometry": {"coordinates":[-2.122445,52.457623],"type":"Point"}
}