{
  "type": "Feature",
  "properties": {
    "addr:full":"Epworth House, 25-35 City Road London Greater London EC1Y 1AA",
    "addr:housenumber":"25-35",
    "addr:postcode":"ec1y 1aa",
    "addr:street":"City Road",
    "iso:country":"GB",
    "sg:address":"Epworth House, 25-35 City Road",
    "sg:city":"London",
    "sg:classifiers":[
        {
            "category":"Communications",
            "type":"Services"
        }
    ],
    "sg:phone":"+44 20 8874 4747",
    "sg:postcode":"EC1Y 1AA",
    "sg:province":"Greater London",
    "sg:tags":[
        "data",
        "network"
    ],
    "wof:name":"Updata Plc",
    "wof:placetype":"venue"
},
  "geometry": {"coordinates":[-0.086982,51.522896],"type":"Point"}
}