{
  "type": "Feature",
  "properties": {
    "addr:full":"49 Havelock Road Hastings East Sussex TN34 1BE",
    "addr:housenumber":"49",
    "addr:postcode":"tn34 1be",
    "addr:street":"Havelock Road",
    "iso:country":"GB",
    "sg:address":"49 Havelock Road",
    "sg:city":"Hastings",
    "sg:classifiers":[
        {
            "category":"Professional",
            "subcategory":"Accounting & Tax Preparation",
            "type":"Services"
        }
    ],
    "sg:postcode":"TN34 1BE",
    "sg:province":"East Sussex",
    "sg:tags":[
        "accountant"
    ],
    "wof:name":"McPherson & Partners",
    "wof:placetype":"venue"
},
  "geometry": {"coordinates":[0.578563,50.856541],"type":"Point"}
}