{
  "type": "Feature",
  "properties": {
    "iso:country":"GB",
    "sg:address":"Lower Noverton Farmhouse Barn, 37 Noverton Lane Prestbury",
    "sg:city":"Cheltenham",
    "sg:classifiers":[
        {
            "category":"Professional",
            "subcategory":"Management & Consulting",
            "type":"Services"
        }
    ],
    "sg:postcode":"GL52 5DD",
    "sg:province":"Gloucestershire",
    "sg:tags":[
        "consultant",
        "business"
    ],
    "wof:name":"Quotecost Ltd",
    "wof:placetype":"venue"
},
  "geometry": {"coordinates":[-2.03484,51.91161],"type":"Point"}
}