{
  "type": "Feature",
  "properties": {
    "addr:full":"184 High St, Cradley Heath Smethwick West Midlands B64 5HN",
    "addr:housenumber":"184",
    "addr:postcode":"b64 5hn",
    "addr:street":"High St",
    "iso:country":"GB",
    "sg:address":"184 High St, Cradley Heath",
    "sg:city":"Smethwick",
    "sg:classifiers":[
        {
            "category":"Building & Trades",
            "subcategory":"Construction",
            "type":"Services"
        }
    ],
    "sg:postcode":"B64 5HN",
    "sg:province":"West Midlands",
    "sg:tags":[
        "roofing"
    ],
    "wof:name":"B R J Erection Ltd",
    "wof:placetype":"venue"
},
  "geometry": {"coordinates":[-2.080942,52.472889],"type":"Point"}
}