{
  "type": "Feature",
  "properties": {
    "iso:country":"GB",
    "sg:address":"358 Handsworth Rd",
    "sg:city":"Sheffield",
    "sg:classifiers":[
        {
            "category":"Food & Beverages",
            "subcategory":"Meat & Fish",
            "type":"Retail Goods"
        }
    ],
    "sg:postcode":"S13 9BY",
    "sg:province":"South Yorkshire",
    "sg:tags":[
        "butcher"
    ],
    "wof:name":"Harrison,A & Da,",
    "wof:placetype":"venue"
},
  "geometry": {"coordinates":[-1.3869539499,53.3710517883],"type":"Point"}
}