{
  "type": "Feature",
  "properties": {
    "addr:full":"7 Cove Row Weymouth Dorset DT4 8TT",
    "addr:housenumber":"7",
    "addr:postcode":"dt4 8tt",
    "addr:street":"Cove Row",
    "iso:country":"GB",
    "sg:address":"7 Cove Row",
    "sg:city":"Weymouth",
    "sg:classifiers":[
        {
            "category":"Travel",
            "subcategory":"Hotels & Motels",
            "type":"Entertainment"
        }
    ],
    "sg:phone":"+44 1305 789737",
    "sg:postcode":"DT4 8TT",
    "sg:province":"Dorset",
    "sg:tags":[
        "self",
        "catering"
    ],
    "wof:name":"Cove Row Coffee Ho & Holiday Flats",
    "wof:placetype":"venue"
},
  "geometry": {"coordinates":[-2.45265,50.606281],"type":"Point"}
}