{
  "type": "Feature",
  "properties": {
    "addr:full":"31 Grosvenor Road Altrincham Cheshire WA14 1LA",
    "addr:housenumber":"31",
    "addr:postcode":"wa14 1la",
    "addr:street":"Grosvenor Road",
    "iso:country":"GB",
    "sg:address":"31 Grosvenor Road",
    "sg:city":"Altrincham",
    "sg:classifiers":[
        {
            "category":"Home & Garden",
            "subcategory":"Furniture",
            "type":"Retail Goods"
        }
    ],
    "sg:postcode":"WA14 1LA",
    "sg:province":"Cheshire",
    "wof:name":"1ST Classic Quality Pine Furniture",
    "wof:placetype":"venue"
},
  "geometry": {"coordinates":[-2.345289,53.391571],"type":"Point"}
}