{
  "type": "Feature",
  "properties": {
    "addr:full":"17 St Andrews Street St Ives Cornwall TR26 1AH",
    "addr:housenumber":"17",
    "addr:postcode":"tr26 1ah",
    "addr:street":"St Andrews Street",
    "iso:country":"GB",
    "sg:address":"17 St Andrews Street",
    "sg:city":"St Ives",
    "sg:classifiers":[
        {
            "category":"Restaurant",
            "type":"Food & Drink"
        }
    ],
    "sg:phone":"+44 1736 796661",
    "sg:postcode":"TR26 1AH",
    "sg:province":"Cornwall",
    "wof:name":"The Wave",
    "wof:placetype":"venue"
},
  "geometry": {"coordinates":[-5.480096817,50.2122535706],"type":"Point"}
}