{
  "type": "Feature",
  "properties": {
    "iso:country":"GB",
    "sg:address":"37 Whiteley Avenue",
    "sg:city":"Totnes",
    "sg:classifiers":[
        {
            "category":"Military Area",
            "subcategory":"Air Force Base",
            "type":"Public Place"
        }
    ],
    "sg:phone":"+44 1803 866772",
    "sg:postcode":"TQ9 5FQ",
    "sg:province":"Devon",
    "sg:tags":[
        "taxi",
        "hire",
        "private"
    ],
    "wof:name":"A B B A Taxis",
    "wof:placetype":"venue"
},
  "geometry": {"coordinates":[-3.711189,50.43433],"type":"Point"}
}