{
  "type": "Feature",
  "properties": {
    "iso:country":"GB",
    "sg:address":"5 Church Street",
    "sg:city":"Shoreham-by-sea",
    "sg:classifiers":[
        {
            "category":"Conference Center",
            "type":"Public Place"
        }
    ],
    "sg:phone":"+44 1273 464662",
    "sg:postcode":"BN43 5DQ",
    "sg:province":"West Sussex",
    "wof:name":"Travel Lines Ltd.",
    "wof:placetype":"venue"
},
  "geometry": {"coordinates":[-0.2755100131,50.8319854736],"type":"Point"}
}