{
  "type": "Feature",
  "properties": {
    "addr:full":"2 Hugh St, Balintore Fearn Highland IV20 1UJ",
    "addr:housenumber":"2",
    "addr:postcode":"iv20 1uj",
    "addr:street":"Hugh St;Fearn",
    "iso:country":"GB",
    "sg:address":"2 Hugh St, Balintore",
    "sg:city":"Fearn",
    "sg:classifiers":[
        {
            "category":"Shopping",
            "subcategory":"News",
            "type":"Retail Goods"
        }
    ],
    "sg:postcode":"IV20 1UJ",
    "sg:province":"Highland",
    "sg:tags":[
        "newsagent"
    ],
    "wof:name":"Barr,Andrew,",
    "wof:placetype":"venue"
},
  "geometry": {"coordinates":[-3.9124,57.755398],"type":"Point"}
}