{
  "type": "Feature",
  "properties": {
    "addr:full":"42 Oaklands, Curdworth Sutton Coldfield Warwickshire B76 9HD",
    "addr:housenumber":"42;curdworth",
    "addr:postcode":"b76 9hd",
    "addr:street":"Oaklands",
    "iso:country":"GB",
    "sg:address":"42 Oaklands, Curdworth",
    "sg:city":"Sutton Coldfield",
    "sg:classifiers":[
        {
            "category":"Real Estate",
            "subcategory":"Real Estate Agent",
            "type":"Services"
        }
    ],
    "sg:postcode":"B76 9HD",
    "sg:province":"Warwickshire",
    "wof:name":"Home-Let Property Management",
    "wof:placetype":"venue"
},
  "geometry": {"coordinates":[-1.751429,52.531872],"type":"Point"}
}