{
  "type": "Feature",
  "properties": {
    "addr:full":"The Surgery, 111 Station Rd Leicester Leicestershire LE3 8GS",
    "addr:housenumber":"111",
    "addr:postcode":"le3 8gs",
    "addr:street":"Station Rd",
    "iso:country":"GB",
    "sg:address":"The Surgery, 111 Station Rd",
    "sg:city":"Leicester",
    "sg:classifiers":[
        {
            "category":"Health Services",
            "subcategory":"Doctor",
            "type":"Services"
        }
    ],
    "sg:phone":"+44 116 233 3604",
    "sg:postcode":"LE3 8GS",
    "sg:province":"Leicestershire",
    "sg:tags":[
        "practitioners"
    ],
    "wof:name":"Salt, M J",
    "wof:placetype":"venue"
},
  "geometry": {"coordinates":[-1.19762,52.654621],"type":"Point"}
}