{
  "type": "Feature",
  "properties": {
    "iso:country":"GB",
    "sg:address":"17 Halkin Street",
    "sg:city":"Leicester",
    "sg:classifiers":[
        {
            "category":"Real Estate",
            "subcategory":"Developer",
            "type":"Services"
        }
    ],
    "sg:phone":"+44 116 261 1330",
    "sg:postcode":"LE4 6JX",
    "sg:province":"Leicestershire",
    "sg:tags":[
        "property"
    ],
    "wof:name":"Charlesland Property Development Ltd.",
    "wof:placetype":"venue"
},
  "geometry": {"coordinates":[-1.1200759411,52.6515884399],"type":"Point"}
}