{
  "type": "Feature",
  "properties": {
    "addr:full":"Unit 1, Staples Corner Business Park, 1000 North Circular Road London Greater London NW2 7JP",
    "addr:housenumber":"unit 1;1000",
    "addr:postcode":"nw2 7jp",
    "addr:street":"North Circular Road",
    "iso:country":"GB",
    "sg:address":"Unit 1, Staples Corner Business Park, 1000 North Circular Road",
    "sg:city":"London",
    "sg:classifiers":[
        {
            "category":"Shopping",
            "subcategory":"Computers & Home Electronics",
            "type":"Retail Goods"
        }
    ],
    "sg:phone":"+44 20 8452 8080",
    "sg:postcode":"NW2 7JP",
    "sg:province":"Greater London",
    "wof:name":"Berrys Direct Ltd.",
    "wof:placetype":"venue"
},
  "geometry": {"coordinates":[-0.233847,51.569202],"type":"Point"}
}