{
  "type": "Feature",
  "properties": {
    "addr:full":"Albert Street Bridgwater Somerset TA6 3RG",
    "addr:postcode":"ta6 3rg",
    "addr:street":"Albert Street",
    "iso:country":"GB",
    "sg:address":"Albert Street",
    "sg:city":"Bridgwater",
    "sg:classifiers":[
        {
            "category":"Social Services",
            "type":"Services"
        },
        {
            "category":"Government",
            "subcategory":"Office",
            "type":"Public Place"
        }
    ],
    "sg:phone":"+44 1278 424942",
    "sg:postcode":"TA6 3RG",
    "sg:province":"Somerset",
    "sg:tags":[
        "local"
    ],
    "wof:name":"Friarn Centre for Families",
    "wof:placetype":"venue"
},
  "geometry": {"coordinates":[-3.007654,51.126476],"type":"Point"}
}