{
  "type": "Feature",
  "properties": {
    "iso:country":"GB",
    "sg:address":"York Road",
    "sg:city":"Dorchester",
    "sg:classifiers":[
        {
            "category":"Farming",
            "subcategory":"Nursery",
            "type":"Manufacturing & Wholesale Goods"
        },
        {
            "category":"Education",
            "subcategory":"Preschool",
            "type":"Public Place"
        }
    ],
    "sg:phone":"+44 1305 265140",
    "sg:postcode":"DT1 1QA",
    "sg:province":"Dorset",
    "sg:tags":[
        "school",
        "creche"
    ],
    "wof:name":"Dorchester Community Nursery School",
    "wof:placetype":"venue"
},
  "geometry": {"coordinates":[-2.4328351021,50.7108192444],"type":"Point"}
}