{
  "type": "Feature",
  "properties": {
    "iso:country":"GB",
    "sg:address":"High Street",
    "sg:city":"Llandysul",
    "sg:classifiers":[
        {
            "category":"Travel",
            "subcategory":"Hotels & Motels",
            "type":"Entertainment"
        }
    ],
    "sg:phone":"+44 1559 362265",
    "sg:postcode":"SA44 4DL",
    "sg:province":"Carmarthenshire",
    "wof:name":"Kings Arms Hotel",
    "wof:placetype":"venue"
},
  "geometry": {"coordinates":[-4.3079681396,52.0436286926],"type":"Point"}
}