{
  "type": "Feature",
  "properties": {
    "iso:country":"GB",
    "sg:address":"Forest View Garage, Newborough Road, Needwood",
    "sg:city":"Burton-on-trent",
    "sg:classifiers":[
        {
            "category":"Retail",
            "subcategory":"Auto Repair",
            "type":"Services"
        }
    ],
    "sg:phone":"+44 1283 575297",
    "sg:postcode":"DE13 9PD",
    "sg:province":"Derbyshire",
    "sg:tags":[
        "modification",
        "garage"
    ],
    "wof:name":"John Ford Ltd.",
    "wof:placetype":"venue"
},
  "geometry": {"coordinates":[-1.678544,52.813545],"type":"Point"}
}