{
  "type": "Feature",
  "properties": {
    "addr:full":"The Old Barn, Long Wittenham Abingdon Oxfordshire OX14 4PS",
    "addr:housenumber":"long wittenham",
    "addr:postcode":"ox14 4ps",
    "addr:street":"Abingdon",
    "iso:country":"GB",
    "sg:address":"The Old Barn, Long Wittenham",
    "sg:city":"Abingdon",
    "sg:classifiers":[
        {
            "category":"Communications",
            "type":"Services"
        }
    ],
    "sg:phone":"+44 1235 816474",
    "sg:postcode":"OX14 4PS",
    "sg:province":"Oxfordshire",
    "sg:tags":[
        "data",
        "network"
    ],
    "wof:name":"Petards International Ltd.",
    "wof:placetype":"venue"
},
  "geometry": {"coordinates":[-1.2113779783,51.6404457092],"type":"Point"}
}