{
  "type": "Feature",
  "properties": {
    "iso:country":"GB",
    "sg:address":"Unit B 1 Plantation Lane, Hopwas",
    "sg:city":"Tamworth",
    "sg:classifiers":[
        {
            "category":"Utilities",
            "subcategory":"Refuse",
            "type":"Services"
        }
    ],
    "sg:phone":"+44 1827 66005",
    "sg:postcode":"B78 3AY",
    "sg:province":"Staffordshire",
    "sg:tags":[
        "skip",
        "hire"
    ],
    "wof:name":"Andyskips Ltd.",
    "wof:placetype":"venue"
},
  "geometry": {"coordinates":[-1.739234,52.642754],"type":"Point"}
}