{
  "type": "Feature",
  "properties": {
    "addr:full":"4 Old Market Place Ripon North Yorkshire HG4 1EQ",
    "addr:housenumber":"4",
    "addr:postcode":"hg4 1eq",
    "addr:street":"Old Market Place",
    "iso:country":"GB",
    "sg:address":"4 Old Market Place",
    "sg:city":"Ripon",
    "sg:classifiers":[
        {
            "category":"Shopping",
            "subcategory":"Stationery & Office Supplies",
            "type":"Retail Goods"
        }
    ],
    "sg:postcode":"HG4 1EQ",
    "sg:province":"North Yorkshire",
    "sg:tags":[
        "equipment"
    ],
    "wof:name":"Compuco Ltd",
    "wof:placetype":"venue"
},
  "geometry": {"coordinates":[-1.523061,54.137493],"type":"Point"}
}