{
  "type": "Feature",
  "properties": {
    "iso:country":"GB",
    "sg:address":"61-63 South Street",
    "sg:city":"Romford",
    "sg:classifiers":[
        {
            "category":"Shopping",
            "subcategory":"Clothing, Apparel, & Fashions",
            "type":"Retail Goods"
        }
    ],
    "sg:phone":"+44 1708 722246",
    "sg:postcode":"RM1 1NL",
    "sg:province":"Essex",
    "sg:tags":[
        "menswear"
    ],
    "wof:name":"Granditer Menswear",
    "wof:placetype":"venue"
},
  "geometry": {"coordinates":[0.184011,51.574051],"type":"Point"}
}