{
  "type": "Feature",
  "properties": {
    "iso:country":"GB",
    "sg:address":"Mortlake Railway Station, Sheen Lane",
    "sg:city":"London",
    "sg:classifiers":[
        {
            "category":"Taxi",
            "type":"Transportation"
        }
    ],
    "sg:postcode":"SW14 8LN",
    "sg:province":"Greater London",
    "sg:tags":[
        "mini",
        "cab"
    ],
    "wof:name":"Richmond & Quadrant Cars",
    "wof:placetype":"venue"
},
  "geometry": {"coordinates":[-0.2659089863,51.4648246765],"type":"Point"}
}