{
  "type": "Feature",
  "properties": {
    "addr:full":"23 Church Street Christchurch Dorset BH23 1BW",
    "addr:housenumber":"23",
    "addr:postcode":"bh23 1bw",
    "addr:street":"Church Street",
    "iso:country":"GB",
    "sg:address":"23 Church Street",
    "sg:city":"Christchurch",
    "sg:classifiers":[
        {
            "category":"Shopping",
            "subcategory":"Hobbies, Toys, & Games",
            "type":"Retail Goods"
        }
    ],
    "sg:postcode":"BH23 1BW",
    "sg:province":"Dorset",
    "sg:tags":[
        "computer"
    ],
    "wof:name":"Software Box",
    "wof:placetype":"venue"
},
  "geometry": {"coordinates":[-1.775020957,50.7328262329],"type":"Point"}
}