{
  "type": "Feature",
  "properties": {
    "addr:full":"18 Market Pl Lauder Scottish Borders TD2 6SR",
    "addr:housenumber":"18",
    "addr:postcode":"td2 6sr",
    "addr:street":"Market Pl",
    "iso:country":"GB",
    "sg:address":"18 Market Pl",
    "sg:city":"Lauder",
    "sg:classifiers":[
        {
            "category":"Government",
            "subcategory":"Post Office",
            "type":"Public Place"
        }
    ],
    "sg:phone":"+44 1578 722200",
    "sg:postcode":"TD2 6SR",
    "sg:province":"Scottish Borders",
    "wof:name":"Lauder Sub Post Office",
    "wof:placetype":"venue"
},
  "geometry": {"coordinates":[-2.748667,55.719322],"type":"Point"}
}