{
  "type": "Feature",
  "properties": {
    "addr:full":"Elizabeth Court, Higher Lane Plymouth Devon PL1 2AN",
    "addr:postcode":"pl1 2an",
    "addr:street":"Elizabeth;Higher Lane",
    "iso:country":"GB",
    "sg:address":"Elizabeth Court, Higher Lane",
    "sg:city":"Plymouth",
    "sg:classifiers":[
        {
            "category":"Government",
            "subcategory":"Police Station",
            "type":"Public Place"
        },
        {
            "category":"Government",
            "subcategory":"Office",
            "type":"Public Place"
        }
    ],
    "sg:phone":"+44 1752 671075",
    "sg:postcode":"PL1 2AN",
    "sg:province":"Devon",
    "sg:tags":[
        "support",
        "local"
    ],
    "wof:name":"The Probation Service",
    "wof:placetype":"venue"
},
  "geometry": {"coordinates":[-4.1386489868,50.3692512512],"type":"Point"}
}