{
  "type": "Feature",
  "properties": {
    "addr:full":"211 Piccadilly West End Hampshire W1V 9LD",
    "addr:housenumber":"211",
    "addr:postcode":"w1v 9ld",
    "addr:street":"Piccadilly",
    "iso:country":"GB",
    "sg:address":"211 Piccadilly",
    "sg:city":"West End",
    "sg:classifiers":[
        {
            "category":"Professional",
            "subcategory":"Employment Agencies",
            "type":"Services"
        }
    ],
    "sg:phone":"+44 870 607 1340",
    "sg:postcode":"W1V 9LD",
    "sg:province":"Hampshire",
    "sg:tags":[
        "consultant"
    ],
    "wof:name":"Chamberlains International",
    "wof:placetype":"venue"
},
  "geometry": {"coordinates":[-0.13899,51.50758],"type":"Point"}
}