{
  "type": "Feature",
  "properties": {
    "addr:full":"Brent Works, 396 Yardley Rd, South Yardley Birmingham West Midlands B25 8LT",
    "addr:housenumber":"396",
    "addr:postcode":"b25 8lt",
    "addr:street":"Yardley Rd South",
    "iso:country":"GB",
    "sg:address":"Brent Works, 396 Yardley Rd, South Yardley",
    "sg:city":"Birmingham",
    "sg:classifiers":[
        {
            "category":"Retail",
            "subcategory":"Storage",
            "type":"Services"
        }
    ],
    "sg:phone":"+44 121 708 2411",
    "sg:postcode":"B25 8LT",
    "sg:province":"West Midlands",
    "sg:tags":[
        "household",
        "removal"
    ],
    "wof:name":"Metroplant Ltd",
    "wof:placetype":"venue"
},
  "geometry": {"coordinates":[-1.8098920584,52.4695091248],"type":"Point"}
}