{
  "type": "Feature",
  "properties": {
    "iso:country":"GB",
    "sg:address":"48 Nearsby Drive, West Bridgford",
    "sg:city":"Nottingham",
    "sg:classifiers":[
        {
            "category":"Professional",
            "subcategory":"Management & Consulting",
            "type":"Services"
        }
    ],
    "sg:phone":"+44 115 923 2666",
    "sg:postcode":"NG2 6LB",
    "sg:province":"Nottinghamshire",
    "sg:tags":[
        "consultant",
        "business"
    ],
    "wof:name":"C.N.A",
    "wof:placetype":"venue"
},
  "geometry": {"coordinates":[-1.1131869555,52.9251022339],"type":"Point"}
}