{
  "type": "Feature",
  "properties": {
    "iso:country":"GB",
    "sg:address":"101 Woodhorn Road",
    "sg:city":"Ashington",
    "sg:classifiers":[
        {
            "category":"Autos & Motor Vehicles",
            "subcategory":"Automobile Sales",
            "type":"Retail Goods"
        }
    ],
    "sg:phone":"+44 1670 813592",
    "sg:postcode":"NE63 9EU",
    "sg:province":"Northumberland",
    "sg:tags":[
        "car"
    ],
    "wof:name":"Ashington Trade Centre",
    "wof:placetype":"venue"
},
  "geometry": {"coordinates":[-1.551901,55.186607],"type":"Point"}
}