{
  "type": "Feature",
  "properties": {
    "iso:country":"GB",
    "sg:address":"Melbourne Rd",
    "sg:city":"Ibstock",
    "sg:classifiers":[
        {
            "category":"Place Of Worship",
            "type":"Public Place"
        }
    ],
    "sg:phone":"+44 1530 812020",
    "sg:postcode":"LE67 6JS",
    "sg:province":"Leicestershire",
    "wof:name":"Ibstock Methodist Church",
    "wof:placetype":"venue"
},
  "geometry": {"coordinates":[-1.403594,52.685383],"type":"Point"}
}