{
  "type": "Feature",
  "properties": {
    "iso:country":"GB",
    "sg:address":"12 Shetland Road",
    "sg:city":"Dronfield",
    "sg:classifiers":[
        {
            "category":"Building & Trades",
            "subcategory":"Plumbing",
            "type":"Services"
        }
    ],
    "sg:phone":"+44 1246 412163",
    "sg:postcode":"S18 1WB",
    "sg:province":"Derbyshire",
    "sg:tags":[
        "heating"
    ],
    "wof:name":"Steven G Lee",
    "wof:placetype":"venue"
},
  "geometry": {"coordinates":[-1.466705,53.294411],"type":"Point"}
}