{
  "type": "Feature",
  "properties": {
    "iso:country":"GB",
    "sg:address":"122b Wollaton Road, Beeston",
    "sg:city":"Nottingham",
    "sg:classifiers":[
        {
            "category":"Personal",
            "subcategory":"Beauty Salon",
            "type":"Services"
        }
    ],
    "sg:postcode":"NG9 2PE",
    "sg:province":"Nottinghamshire",
    "sg:tags":[
        "unisex",
        "hairdresser"
    ],
    "wof:name":"Intricut",
    "wof:placetype":"venue"
},
  "geometry": {"coordinates":[-1.2187809944,52.9298210144],"type":"Point"}
}