{
  "type": "Feature",
  "properties": {
    "iso:country":"GB",
    "sg:address":"Wimbledon Bridge House, 1 Hartfield Rd",
    "sg:city":"Wimbledon",
    "sg:classifiers":[
        {
            "category":"Communications",
            "subcategory":"Newspaper",
            "type":"Services"
        }
    ],
    "sg:phone":"+44 20 8545 6260",
    "sg:postcode":"SW19 3RU",
    "sg:province":"Greater London",
    "sg:tags":[
        "magazine"
    ],
    "wof:name":"Business Week",
    "wof:placetype":"venue"
},
  "geometry": {"coordinates":[-0.206724,51.420265],"type":"Point"}
}