{
  "type": "Feature",
  "properties": {
    "addr:full":"128 Lea Village Birmingham West Midlands B33 9SL",
    "addr:housenumber":"128",
    "addr:postcode":"b33 9sl",
    "addr:street":"Lea Village",
    "iso:country":"GB",
    "sg:address":"128 Lea Village",
    "sg:city":"Birmingham",
    "sg:classifiers":[
        {
            "category":"Shopping",
            "subcategory":"News",
            "type":"Retail Goods"
        }
    ],
    "sg:phone":"+44 121 789 8987",
    "sg:postcode":"B33 9SL",
    "sg:province":"West Midlands",
    "sg:tags":[
        "newsagent"
    ],
    "wof:name":"Lea Village News",
    "wof:placetype":"venue"
},
  "geometry": {"coordinates":[-1.7791390419,52.4827957153],"type":"Point"}
}