{
  "type": "Feature",
  "properties": {
    "addr:full":"29 High Chelmer Chelmsford Essex CM1 1XR",
    "addr:housenumber":"29",
    "addr:postcode":"cm1 1xr",
    "addr:street":"High Chelmer",
    "iso:country":"GB",
    "sg:address":"29 High Chelmer",
    "sg:city":"Chelmsford",
    "sg:classifiers":[
        {
            "category":"Food & Beverages",
            "subcategory":"Supermarket",
            "type":"Retail Goods"
        }
    ],
    "sg:phone":"+44 1245 262811",
    "sg:postcode":"CM1 1XR",
    "sg:province":"Essex",
    "wof:name":"J Sainsbury PLC",
    "wof:placetype":"venue"
},
  "geometry": {"coordinates":[0.470246,51.734142],"type":"Point"}
}