{
  "type": "Feature",
  "properties": {
    "addr:full":"2 Brookside Cramlington Northumberland NE23 7DJ",
    "addr:housenumber":"2",
    "addr:postcode":"ne23 7dj",
    "addr:street":"Brookside;Northumberland",
    "iso:country":"GB",
    "sg:address":"2 Brookside",
    "sg:city":"Cramlington",
    "sg:classifiers":[
        {
            "category":"Utilities",
            "subcategory":"Telephone",
            "type":"Services"
        }
    ],
    "sg:phone":"+44 191 250 1700",
    "sg:postcode":"NE23 7DJ",
    "sg:province":"Northumberland",
    "sg:tags":[
        "telecommunication"
    ],
    "wof:name":"Meridian Services",
    "wof:placetype":"venue"
},
  "geometry": {"coordinates":[-1.590647,55.0546],"type":"Point"}
}