{
  "type": "Feature",
  "properties": {
    "iso:country":"GB",
    "sg:address":"133 Whalley Road, Ramsbottom",
    "sg:city":"Bury",
    "sg:classifiers":[
        {
            "category":"Building & Trades",
            "subcategory":"Plumbing",
            "type":"Services"
        }
    ],
    "sg:phone":"+44 1706 826836",
    "sg:postcode":"BL0 0DG",
    "sg:province":"Lancashire",
    "sg:tags":[
        "plumber",
        "heating"
    ],
    "wof:name":"A M B Plumbing & Heating",
    "wof:placetype":"venue"
},
  "geometry": {"coordinates":[-2.3036949635,53.6581726074],"type":"Point"}
}