{
  "type": "Feature",
  "properties": {
    "addr:full":"Unit 2 The Foremans Centre, High St Ashford Kent TN27 9NG",
    "addr:housenumber":"unit 2",
    "addr:postcode":"tn27 9ng",
    "addr:street":"The;High St",
    "iso:country":"GB",
    "sg:address":"Unit 2 The Foremans Centre, High St",
    "sg:city":"Ashford",
    "sg:classifiers":[
        {
            "category":"Shopping",
            "subcategory":"Florist",
            "type":"Retail Goods"
        }
    ],
    "sg:phone":"+44 1622 891767",
    "sg:postcode":"TN27 9NG",
    "sg:province":"Kent",
    "wof:name":"Flower Basket The",
    "wof:placetype":"venue"
},
  "geometry": {"coordinates":[0.62289,51.167702],"type":"Point"}
}