{
  "type": "Feature",
  "properties": {
    "iso:country":"GB",
    "sg:address":"Unit 2 The Foremans Centre, High St",
    "sg:city":"Ashford",
    "sg:classifiers":[
        {
            "category":"Shopping",
            "subcategory":"Florist",
            "type":"Retail Goods"
        }
    ],
    "sg:phone":"+44 1622 891767",
    "sg:postcode":"TN27 9NG",
    "sg:province":"Kent",
    "wof:name":"Flower Basket The",
    "wof:placetype":"venue"
},
  "geometry": {"coordinates":[0.62289,51.167702],"type":"Point"}
}