{
  "type": "Feature",
  "properties": {
    "iso:country":"GB",
    "sg:address":"Cow Lane, Garston",
    "sg:city":"Watford",
    "sg:classifiers":[
        {
            "category":"Retail",
            "subcategory":"Photofinishing",
            "type":"Services"
        },
        {
            "category":"Retail",
            "subcategory":"Laundry & Dry Cleaning",
            "type":"Services"
        }
    ],
    "sg:phone":"+44 1923 663792",
    "sg:postcode":"WD2 6JS",
    "sg:province":"Hertfordshire",
    "sg:tags":[
        "photographic",
        "alteration",
        "processor"
    ],
    "wof:name":"Sketchley Retail Ltd.",
    "wof:placetype":"venue"
},
  "geometry": {"coordinates":[-0.3824,51.68996],"type":"Point"}
}