{
  "type": "Feature",
  "properties": {
    "iso:country":"GB",
    "sg:address":"Oak, Lea Upper Chorlton Rd",
    "sg:city":"Manchester",
    "sg:classifiers":[
        {
            "category":"Organizations",
            "subcategory":"Community Association",
            "type":"Services"
        }
    ],
    "sg:phone":"+44 161 226 8256",
    "sg:postcode":"M16 7SG",
    "sg:province":"Cheshire",
    "sg:tags":[
        "society",
        "housing"
    ],
    "wof:name":"Anchor Trust",
    "wof:placetype":"venue"
},
  "geometry": {"coordinates":[-2.2582790852,53.4588088989],"type":"Point"}
}