{
  "type": "Feature",
  "properties": {
    "addr:full":"33 Elwyn Dr Liverpool Merseyside L26 0UU",
    "addr:housenumber":"33",
    "addr:postcode":"l26 0uu",
    "addr:street":"Elwyn Dr",
    "iso:country":"GB",
    "sg:address":"33 Elwyn Dr",
    "sg:city":"Liverpool",
    "sg:classifiers":[
        {
            "category":"Retail",
            "subcategory":"Auto Repair",
            "type":"Services"
        }
    ],
    "sg:postcode":"L26 0UU",
    "sg:province":"Merseyside",
    "sg:tags":[
        "engine",
        "car",
        "specialist"
    ],
    "wof:name":"Balberstone,A,",
    "wof:placetype":"venue"
},
  "geometry": {"coordinates":[-2.8253641129,53.3664665222],"type":"Point"}
}