{
  "type": "Feature",
  "properties": {
    "addr:full":"Hillside, Marham King's Lynn Norfolk PE33 9JJ",
    "addr:postcode":"pe33 9jj",
    "addr:street":"Lynn",
    "iso:country":"GB",
    "sg:address":"Hillside, Marham",
    "sg:city":"King's Lynn",
    "sg:classifiers":[
        {
            "category":"Education",
            "subcategory":"School",
            "type":"Public Place"
        }
    ],
    "sg:phone":"+44 1760 337346",
    "sg:postcode":"PE33 9JJ",
    "sg:province":"Norfolk",
    "sg:tags":[
        "local",
        "authority"
    ],
    "wof:name":"NORFOLK COUNTY COUNCIL",
    "wof:placetype":"venue"
},
  "geometry": {"coordinates":[0.53067,52.662048],"type":"Point"}
}