{
  "type": "Feature",
  "properties": {
    "iso:country":"GB",
    "sg:address":"663 Dewsbury Road",
    "sg:city":"Leeds",
    "sg:classifiers":[
        {
            "category":"Personal",
            "subcategory":"Beauty Salon",
            "type":"Services"
        },
        {
            "category":"Personal",
            "subcategory":"Barber",
            "type":"Services"
        }
    ],
    "sg:postcode":"LS11 5LF",
    "sg:province":"West Yorkshire",
    "sg:tags":[
        "unisex",
        "men's",
        "hairdresser"
    ],
    "wof:name":"Martin's Hairdressing for Men",
    "wof:placetype":"venue"
},
  "geometry": {"coordinates":[-1.556119,53.766659],"type":"Point"}
}