{
  "type": "Feature",
  "properties": {
    "addr:full":"316 Station Road, Balsall Common Coventry Warwickshire CV7 7EF",
    "addr:housenumber":"316",
    "addr:postcode":"cv7 7ef",
    "addr:street":"Station Road",
    "iso:country":"GB",
    "sg:address":"316 Station Road, Balsall Common",
    "sg:city":"Coventry",
    "sg:classifiers":[
        {
            "category":"Organizations",
            "subcategory":"Membership Organization",
            "type":"Services"
        }
    ],
    "sg:phone":"+44 1676 533462",
    "sg:postcode":"CV7 7EF",
    "sg:province":"Warwickshire",
    "sg:tags":[
        "club"
    ],
    "wof:name":"The Royal British Legion",
    "wof:placetype":"venue"
},
  "geometry": {"coordinates":[-1.643749,52.39341],"type":"Point"}
}