{
  "type": "Feature",
  "properties": {
    "addr:full":"Longfellow Rd Billingham Durham TS23 3TL",
    "addr:postcode":"ts23 3tl",
    "addr:street":"Longfellow Rd",
    "iso:country":"GB",
    "sg:address":"Longfellow Rd",
    "sg:city":"Billingham",
    "sg:classifiers":[
        {
            "category":"Bars & Pubs",
            "type":"Food & Drink"
        }
    ],
    "sg:phone":"+44 1642 373401",
    "sg:postcode":"TS23 3TL",
    "sg:province":"Durham",
    "sg:tags":[
        "pubs",
        "inn"
    ],
    "wof:name":"Owington Farm",
    "wof:placetype":"venue"
},
  "geometry": {"coordinates":[-1.2887070179,54.6255073547],"type":"Point"}
}