{
  "type": "Feature",
  "properties": {
    "addr:full":"43 Kirkgate Bradford West Yorkshire BD1 1QA",
    "addr:housenumber":"43",
    "addr:postcode":"bd1 1qa",
    "addr:street":"Kirkgate Bradford West",
    "iso:country":"GB",
    "sg:address":"43 Kirkgate",
    "sg:city":"Bradford",
    "sg:classifiers":[
        {
            "category":"Food & Beverages",
            "subcategory":"Candy",
            "type":"Retail Goods"
        }
    ],
    "sg:postcode":"BD1 1QA",
    "sg:province":"West Yorkshire",
    "sg:tags":[
        "confectioner"
    ],
    "wof:name":"Thorntons Plc",
    "wof:placetype":"venue"
},
  "geometry": {"coordinates":[-1.7532219887,53.7947921753],"type":"Point"}
}