{
  "type": "Feature",
  "properties": {
    "addr:full":"5c Woodford Rd, Bramhall Stockport Cheshire SK7 1JN",
    "addr:housenumber":"5c",
    "addr:postcode":"sk7 1jn",
    "addr:street":"Woodford Rd",
    "iso:country":"GB",
    "sg:address":"5c Woodford Rd, Bramhall",
    "sg:city":"Stockport",
    "sg:classifiers":[
        {
            "category":"Personal",
            "subcategory":"Barber",
            "type":"Services"
        }
    ],
    "sg:postcode":"SK7 1JN",
    "sg:province":"Cheshire",
    "sg:tags":[
        "men's",
        "hairdresser"
    ],
    "wof:name":"Bagnall,Paul,",
    "wof:placetype":"venue"
},
  "geometry": {"coordinates":[-2.1657409668,53.3572006226],"type":"Point"}
}