{
  "type": "Feature",
  "properties": {
    "addr:full":"21 Egerton Street Ashton-under-lyne Greater Manchester OL6 9NY",
    "addr:housenumber":"21",
    "addr:postcode":"ol6 9ny",
    "addr:street":"Egerton Street",
    "iso:country":"GB",
    "sg:address":"21 Egerton Street",
    "sg:city":"Ashton-under-lyne",
    "sg:classifiers":[
        {
            "category":"Food & Beverages",
            "subcategory":"Fruits & Vegetables",
            "type":"Retail Goods"
        },
        {
            "category":"Food & Beverages",
            "subcategory":"Groceries & Convenience Stores",
            "type":"Retail Goods"
        }
    ],
    "sg:phone":"+44 161 339 8079",
    "sg:postcode":"OL6 9NY",
    "sg:province":"Greater Manchester",
    "sg:tags":[
        "grocer",
        "greengrocer"
    ],
    "wof:name":"G HUSSAIN",
    "wof:placetype":"venue"
},
  "geometry": {"coordinates":[-2.086316,53.490887],"type":"Point"}
}