{
  "type": "Feature",
  "properties": {
    "addr:full":"22-28 High Street Tipton West Midlands DY4 7EP",
    "addr:housenumber":"22-28",
    "addr:postcode":"dy4 7ep",
    "addr:street":"High Street",
    "iso:country":"GB",
    "sg:address":"22-28 High Street",
    "sg:city":"Tipton",
    "sg:classifiers":[
        {
            "category":"Sports & Exercise",
            "subcategory":"Gym",
            "type":"Entertainment"
        }
    ],
    "sg:phone":"+44 121 520 7020",
    "sg:postcode":"DY4 7EP",
    "sg:province":"West Midlands",
    "sg:tags":[
        "fitness",
        "health",
        "centre"
    ],
    "wof:name":"Muscles Health & Fitness Centre",
    "wof:placetype":"venue"
},
  "geometry": {"coordinates":[-2.06973,52.540688],"type":"Point"}
}