{
  "type": "Feature",
  "properties": {
    "addr:full":"72 Durham St, Kinning Park Glasgow Glasgow City G41 1BS",
    "addr:housenumber":"72",
    "addr:postcode":"g41 1bs",
    "addr:street":"Durham St",
    "iso:country":"GB",
    "sg:address":"72 Durham St, Kinning Park",
    "sg:city":"Glasgow",
    "sg:classifiers":[
        {
            "category":"Wholesale",
            "subcategory":"Chemicals & Plastics",
            "type":"Manufacturing & Wholesale Goods"
        }
    ],
    "sg:phone":"+44 141 306 1300",
    "sg:postcode":"G41 1BS",
    "sg:province":"Glasgow City",
    "sg:tags":[
        "retail",
        "freezer",
        "refrigerator"
    ],
    "wof:name":"Hussmann Ltd",
    "wof:placetype":"venue"
},
  "geometry": {"coordinates":[-4.2888941765,55.8492851257],"type":"Point"}
}