{
  "type": "Feature",
  "properties": {
    "iso:country":"GB",
    "sg:address":"14 Church St West, Radcliffe",
    "sg:city":"Manchester",
    "sg:classifiers":[
        {
            "category":"Food & Beverages",
            "subcategory":"Meat & Fish",
            "type":"Retail Goods"
        }
    ],
    "sg:phone":"+44 161 723 2466",
    "sg:postcode":"M26 2SQ",
    "sg:province":"Greater Manchester",
    "sg:tags":[
        "butcher"
    ],
    "wof:name":"H Nolan & Son",
    "wof:placetype":"venue"
},
  "geometry": {"coordinates":[-2.32453,53.559475],"type":"Point"}
}