{
  "type": "Feature",
  "properties": {
    "addr:full":"44b Galgate Barnard Castle Cumbria DL12 8BH",
    "addr:housenumber":"44b",
    "addr:postcode":"dl12 8bh",
    "addr:street":"Galgate",
    "iso:country":"GB",
    "sg:address":"44b Galgate",
    "sg:city":"Barnard Castle",
    "sg:classifiers":[
        {
            "category":"Organizations",
            "subcategory":"Non-profit Organization",
            "type":"Services"
        }
    ],
    "sg:phone":"+44 1833 630049",
    "sg:postcode":"DL12 8BH",
    "sg:province":"Cumbria",
    "sg:tags":[
        "organisation",
        "voluntary",
        "charity"
    ],
    "wof:name":"Teesdale Crossroads",
    "wof:placetype":"venue"
},
  "geometry": {"coordinates":[-1.923292,54.545555],"type":"Point"}
}