{
  "type": "Feature",
  "properties": {
    "addr:full":"Largs Road Kilbirnie North Ayrshire KA25 7AT",
    "addr:postcode":"ka25 7at",
    "addr:street":"Largs Road",
    "iso:country":"GB",
    "sg:address":"Largs Road",
    "sg:city":"Kilbirnie",
    "sg:classifiers":[
        {
            "category":"Sports & Exercise",
            "subcategory":"Golf",
            "type":"Entertainment"
        }
    ],
    "sg:phone":"+44 1505 683398",
    "sg:postcode":"KA25 7AT",
    "sg:province":"North Ayrshire",
    "sg:tags":[
        "club",
        "course"
    ],
    "wof:name":"Kilbirnie Place Golf Club",
    "wof:placetype":"venue"
},
  "geometry": {"coordinates":[-4.6970591545,55.7536697388],"type":"Point"}
}