{
  "type": "Feature",
  "properties": {
    "addr:full":"Kildean Market Stirling Clackmannanshire FK9 4AA",
    "addr:postcode":"fk9 4aa",
    "iso:country":"GB",
    "sg:address":"Kildean Market",
    "sg:city":"Stirling",
    "sg:classifiers":[
        {
            "category":"Retail",
            "subcategory":"Veterinary Services",
            "type":"Services"
        }
    ],
    "sg:phone":"+44 1786 471363",
    "sg:postcode":"FK9 4AA",
    "sg:province":"Clackmannanshire",
    "sg:tags":[
        "pharmacy"
    ],
    "wof:name":"Wool Growers Goods",
    "wof:placetype":"venue"
},
  "geometry": {"coordinates":[-3.9675040245,56.1341667175],"type":"Point"}
}