{
  "type": "Feature",
  "properties": {
    "addr:full":"Glenvista, Cross Stone Road Todmorden Lancashire OL14 8AW",
    "addr:postcode":"ol14 8aw",
    "addr:street":"Glenvista Cross Stone Road",
    "iso:country":"GB",
    "sg:address":"Glenvista, Cross Stone Road",
    "sg:city":"Todmorden",
    "sg:classifiers":[
        {
            "category":"Recreation",
            "subcategory":"Dog Park",
            "type":"Entertainment"
        }
    ],
    "sg:postcode":"OL14 8AW",
    "sg:province":"Lancashire",
    "wof:name":"Hair & Hounds",
    "wof:placetype":"venue"
},
  "geometry": {"coordinates":[-2.0855441093,53.7195167542],"type":"Point"}
}