{
  "type": "Feature",
  "properties": {
    "addr:full":"Tinsley Shopping Centre Sheffield South Yorkshire S9 1WN",
    "addr:postcode":"s9 1wn",
    "addr:street":"Centre",
    "iso:country":"GB",
    "sg:address":"Tinsley Shopping Centre",
    "sg:city":"Sheffield",
    "sg:classifiers":[
        {
            "category":"Health Services",
            "subcategory":"Clinic",
            "type":"Services"
        }
    ],
    "sg:phone":"+44 114 244 2256",
    "sg:postcode":"S9 1WN",
    "sg:province":"South Yorkshire",
    "sg:tags":[
        "nh"
    ],
    "wof:name":"Highgate Surgery",
    "wof:placetype":"venue"
},
  "geometry": {"coordinates":[-1.3987389803,53.4130363464],"type":"Point"}
}