{
  "type": "Feature",
  "properties": {
    "iso:country":"GB",
    "sg:address":"8 Station St, Kibworth",
    "sg:city":"Leicester",
    "sg:classifiers":[
        {
            "category":"Shopping",
            "subcategory":"Pharmacy",
            "type":"Retail Goods"
        }
    ],
    "sg:phone":"+44 116 279 2263",
    "sg:postcode":"LE8 0LN",
    "sg:province":"Leicestershire",
    "sg:tags":[
        "pharmacist",
        "dispensing",
        "chemist"
    ],
    "wof:name":"Lloyds Pharmacy Ltd",
    "wof:placetype":"venue"
},
  "geometry": {"coordinates":[-0.994384,52.537975],"type":"Point"}
}