{
  "type": "Feature",
  "properties": {
    "addr:full":"3 High Street Barnstaple Devon EX31 1BG",
    "addr:housenumber":"3",
    "addr:postcode":"ex31 1bg",
    "addr:street":"High Street",
    "iso:country":"GB",
    "sg:address":"3 High Street",
    "sg:city":"Barnstaple",
    "sg:classifiers":[
        {
            "category":"Shopping",
            "subcategory":"Thrift Store",
            "type":"Retail Goods"
        }
    ],
    "sg:phone":"+44 1271 328799",
    "sg:postcode":"EX31 1BG",
    "sg:province":"Devon",
    "sg:tags":[
        "shop",
        "charity"
    ],
    "wof:name":"C L I C",
    "wof:placetype":"venue"
},
  "geometry": {"coordinates":[-4.058851,51.078899],"type":"Point"}
}