{
  "type": "Feature",
  "properties": {
    "iso:country":"GB",
    "sg:address":"Unit B3 Empress Park, Empress Road",
    "sg:city":"Southampton",
    "sg:classifiers":[
        {
            "category":"Manufacturing",
            "subcategory":"Tools & Machinery",
            "type":"Manufacturing & Wholesale Goods"
        },
        {
            "category":"Home & Garden",
            "subcategory":"Hardware",
            "type":"Retail Goods"
        }
    ],
    "sg:phone":"+44 23 8022 8668",
    "sg:postcode":"SO14 0JX",
    "sg:province":"Hampshire",
    "sg:tags":[
        "machine",
        "equipment",
        "welding",
        "manufacturer"
    ],
    "wof:name":"Triumph Property Ltd.",
    "wof:placetype":"venue"
},
  "geometry": {"coordinates":[-1.3923200369,50.9180107117],"type":"Point"}
}