{
  "type": "Feature",
  "properties": {
    "iso:country":"GB",
    "sg:address":"12 Cuff Point Columbia Rd",
    "sg:city":"Bethnal Green",
    "sg:classifiers":[
        {
            "category":"Professional",
            "type":"Services"
        }
    ],
    "sg:phone":"+44 20 7729 3767",
    "sg:postcode":"E2 7PP",
    "sg:province":"Greater London",
    "sg:tags":[
        "entertainer"
    ],
    "wof:name":"Patrick Cleary Singer Entertainment",
    "wof:placetype":"venue"
},
  "geometry": {"coordinates":[-0.0746940002,51.5281791687],"type":"Point"}
}