{
  "type": "Feature",
  "properties": {
    "addr:full":"Mulberry House, 46 Boxworth Road, Elsworth Cambridge Cambridgeshire CB3 8JQ",
    "addr:housenumber":"46",
    "addr:postcode":"cb3 8jq",
    "addr:street":"Boxworth Road",
    "iso:country":"GB",
    "sg:address":"Mulberry House, 46 Boxworth Road, Elsworth",
    "sg:city":"Cambridge",
    "sg:classifiers":[
        {
            "category":"Professional",
            "subcategory":"Engineering",
            "type":"Services"
        },
        {
            "category":"Real Estate",
            "subcategory":"Architect",
            "type":"Services"
        }
    ],
    "sg:phone":"+44 1954 267166",
    "sg:postcode":"CB3 8JQ",
    "sg:province":"Cambridgeshire",
    "sg:tags":[
        "consulting",
        "electronic",
        "engineer"
    ],
    "wof:name":"Pathway Systems",
    "wof:placetype":"venue"
},
  "geometry": {"coordinates":[-0.0652199984,52.2566986084],"type":"Point"}
}