{
  "type": "Feature",
  "properties": {
    "addr:full":"16-17 Old Bond Street Bath Bath and North East Somerset BA1 1BP",
    "addr:housenumber":"16-17",
    "addr:postcode":"ba1 1bp",
    "addr:street":"Old Bond Street",
    "iso:country":"GB",
    "sg:address":"16-17 Old Bond Street",
    "sg:city":"Bath",
    "sg:classifiers":[
        {
            "category":"Banks & Credit Unions",
            "subcategory":"Financial Services",
            "type":"Services"
        }
    ],
    "sg:phone":"+44 1225 469424",
    "sg:postcode":"BA1 1BP",
    "sg:province":"Bath and North East Somerset",
    "sg:tags":[
        "adviser"
    ],
    "wof:name":"Seymour Pierce Rowan",
    "wof:placetype":"venue"
},
  "geometry": {"coordinates":[-2.3613369465,51.3827934265],"type":"Point"}
}