{
  "type": "Feature",
  "properties": {
    "iso:country":"GB",
    "sg:address":"29 Wates Way",
    "sg:city":"Mitcham",
    "sg:classifiers":[
        {
            "category":"Wholesale",
            "subcategory":"Medical Equipment & Supplies",
            "type":"Manufacturing & Wholesale Goods"
        }
    ],
    "sg:postcode":"CR4 4HR",
    "sg:province":"Greater London",
    "sg:tags":[
        "hospital"
    ],
    "wof:name":"S T S Synergy Plc",
    "wof:placetype":"venue"
},
  "geometry": {"coordinates":[-0.164173007,51.3892402649],"type":"Point"}
}