{
  "type": "Feature",
  "properties": {
    "addr:full":"384 Filton Avenue, Horfield Bristol City of Bristol BS7 0BE",
    "addr:housenumber":"384",
    "addr:postcode":"bs7 0be",
    "addr:street":"Filton Avenue",
    "iso:country":"GB",
    "sg:address":"384 Filton Avenue, Horfield",
    "sg:city":"Bristol",
    "sg:classifiers":[
        {
            "category":"Health Services",
            "subcategory":"Optometrist",
            "type":"Services"
        }
    ],
    "sg:phone":"+44 117 979 9942",
    "sg:postcode":"BS7 0BE",
    "sg:province":"City of Bristol",
    "sg:tags":[
        "optician"
    ],
    "wof:name":"Christine Townsend Opticians",
    "wof:placetype":"venue"
},
  "geometry": {"coordinates":[-2.5742061138,51.4952316284],"type":"Point"}
}