{
  "type": "Feature",
  "properties": {
    "addr:full":"70 Goring Road, Goring-by-sea Worthing West Sussex BN12 4AB",
    "addr:housenumber":"70",
    "addr:postcode":"bn12 4ab",
    "addr:street":"Goring Road",
    "iso:country":"GB",
    "sg:address":"70 Goring Road, Goring-by-sea",
    "sg:city":"Worthing",
    "sg:classifiers":[
        {
            "category":"Professional",
            "subcategory":"Management & Consulting",
            "type":"Services"
        }
    ],
    "sg:phone":"+44 1903 700769",
    "sg:postcode":"BN12 4AB",
    "sg:province":"West Sussex",
    "sg:tags":[
        "consultant",
        "business"
    ],
    "wof:name":"Green & Kassab Management Consultants",
    "wof:placetype":"venue"
},
  "geometry": {"coordinates":[-0.4042060077,50.8133239746],"type":"Point"}
}