{
  "type": "Feature",
  "properties": {
    "addr:full":"The Causeway Worthing West Sussex BN99 6DA",
    "addr:postcode":"bn99 6da",
    "addr:street":"The Causeway",
    "iso:country":"GB",
    "sg:address":"The Causeway",
    "sg:city":"Worthing",
    "sg:classifiers":[
        {
            "category":"Banks & Credit Unions",
            "subcategory":"Bank",
            "type":"Services"
        }
    ],
    "sg:phone":"+44 1903 502541",
    "sg:postcode":"BN99 6DA",
    "sg:province":"West Sussex",
    "wof:name":"Lloyds Bank Registrars",
    "wof:placetype":"venue"
},
  "geometry": {"coordinates":[-0.411469,50.8195],"type":"Point"}
}