{
  "type": "Feature",
  "properties": {
    "iso:country":"GB",
    "sg:address":"The Bear Garage, Bath Road",
    "sg:city":"Melksham",
    "sg:classifiers":[
        {
            "category":"Autos & Motor Vehicles",
            "subcategory":"Automobile Sales",
            "type":"Retail Goods"
        },
        {
            "category":"Retail",
            "subcategory":"Auto Repair",
            "type":"Services"
        }
    ],
    "sg:phone":"+44 1225 707489",
    "sg:postcode":"SN12 8HN",
    "sg:province":"Wiltshire",
    "sg:tags":[
        "modification",
        "garage",
        "car"
    ],
    "wof:name":"Tipedge Ltd.",
    "wof:placetype":"venue"
},
  "geometry": {"coordinates":[-2.1356,51.374065],"type":"Point"}
}