{
  "type": "Feature",
  "properties": {
    "addr:full":"227 Weyhill Road Andover Hampshire SP10 3LL",
    "addr:housenumber":"227",
    "addr:postcode":"sp10 3ll",
    "addr:street":"Weyhill Road",
    "iso:country":"GB",
    "sg:address":"227 Weyhill Road",
    "sg:city":"Andover",
    "sg:classifiers":[
        {
            "category":"Bars & Pubs",
            "type":"Food & Drink"
        }
    ],
    "sg:phone":"+44 1264 323886",
    "sg:postcode":"SP10 3LL",
    "sg:province":"Hampshire",
    "sg:tags":[
        "pubs",
        "inn"
    ],
    "wof:name":"The Chestnut Tree",
    "wof:placetype":"venue"
},
  "geometry": {"coordinates":[-1.511453,51.209976],"type":"Point"}
}