{
  "type": "Feature",
  "properties": {
    "addr:full":"10 Palmerston Road Stockport Cheshire SK2 7EA",
    "addr:housenumber":"10",
    "addr:postcode":"sk2 7ea",
    "addr:street":"Palmerston Road",
    "iso:country":"GB",
    "sg:address":"10 Palmerston Road",
    "sg:city":"Stockport",
    "sg:classifiers":[
        {
            "category":"Building & Trades",
            "subcategory":"Landscaping Services",
            "type":"Services"
        }
    ],
    "sg:phone":"+44 161 456 0558",
    "sg:postcode":"SK2 7EA",
    "sg:province":"Cheshire",
    "sg:tags":[
        "landscape",
        "contractor"
    ],
    "wof:name":"Haughton Constructions",
    "wof:placetype":"venue"
},
  "geometry": {"coordinates":[-2.144358,53.383217],"type":"Point"}
}