{
  "type": "Feature",
  "properties": {
    "iso:country":"GB",
    "sg:address":"Unit 2, 9 Cellars Clough Business Park, Marsden",
    "sg:city":"Huddersfield",
    "sg:classifiers":[
        {
            "category":"Autos & Motor Vehicles",
            "subcategory":"Auto Supplies",
            "type":"Retail Goods"
        }
    ],
    "sg:phone":"+44 1484 840011",
    "sg:postcode":"HD7 6LY",
    "sg:province":"West Yorkshire",
    "sg:tags":[
        "towing",
        "eqpt",
        "trailer"
    ],
    "wof:name":"Taylors Trailers Ltd.",
    "wof:placetype":"venue"
},
  "geometry": {"coordinates":[-1.91386,53.60891],"type":"Point"}
}