{
  "type": "Feature",
  "properties": {
    "addr:full":"12 Cross Street Preston Lancashire PR1 3LT",
    "addr:housenumber":"12",
    "addr:postcode":"pr1 3lt",
    "addr:street":"Cross Street",
    "iso:country":"GB",
    "sg:address":"12 Cross Street",
    "sg:city":"Preston",
    "sg:classifiers":[
        {
            "category":"Banks & Credit Unions",
            "subcategory":"Investment Brokerage",
            "type":"Services"
        }
    ],
    "sg:postcode":"PR1 3LT",
    "sg:province":"Lancashire",
    "sg:tags":[
        "firework",
        "stockist"
    ],
    "wof:name":"M P L  Fireworks Ltd.",
    "wof:placetype":"venue"
},
  "geometry": {"coordinates":[-2.6999149323,53.7562141418],"type":"Point"}
}