{
  "type": "Feature",
  "properties": {
    "addr:full":"Stourport Locks, The Basin, Mart Lane Stourport-on-severn Worcestershire DY13 9EN",
    "addr:postcode":"dy13 9en",
    "addr:street":"Lane",
    "iso:country":"GB",
    "sg:address":"Stourport Locks, The Basin, Mart Lane",
    "sg:city":"Stourport-on-severn",
    "sg:classifiers":[
        {
            "category":"Wholesale",
            "subcategory":"Office Equipment",
            "type":"Manufacturing & Wholesale Goods"
        }
    ],
    "sg:phone":"+44 1299 877661",
    "sg:postcode":"DY13 9EN",
    "sg:province":"Worcestershire",
    "sg:tags":[
        "river",
        "authority"
    ],
    "wof:name":"British Waterways",
    "wof:placetype":"venue"
},
  "geometry": {"coordinates":[-2.281167,52.338997],"type":"Point"}
}