{
  "type": "Feature",
  "properties": {
    "iso:country":"GB",
    "sg:address":"27 Obelisk Way",
    "sg:city":"Camberley",
    "sg:classifiers":[
        {
            "category":"Sports & Exercise",
            "subcategory":"Sports Center",
            "type":"Entertainment"
        }
    ],
    "sg:phone":"+44 1276 677227",
    "sg:postcode":"GU15 3SG",
    "sg:province":"Berkshire",
    "sg:tags":[
        "shop",
        "good"
    ],
    "wof:name":"J J B Sports Plc",
    "wof:placetype":"venue"
},
  "geometry": {"coordinates":[-0.7450090051,51.3390197754],"type":"Point"}
}