{
  "type": "Feature",
  "properties": {
    "iso:country":"GB",
    "sg:address":"63 Park Rd",
    "sg:city":"St. Helens",
    "sg:classifiers":[
        {
            "category":"Professional",
            "subcategory":"Testing Lab",
            "type":"Services"
        }
    ],
    "sg:phone":"+44 1744 611093",
    "sg:postcode":"WA9 1DS",
    "sg:province":"Cheshire",
    "sg:tags":[
        "pregnancy"
    ],
    "wof:name":"Well Come In",
    "wof:placetype":"venue"
},
  "geometry": {"coordinates":[-2.718763,53.455315],"type":"Point"}
}