{
  "type": "Feature",
  "properties": {
    "addr:full":"Hillworth Road Devizes Wiltshire SN10 5HD",
    "addr:postcode":"sn10 5hd",
    "addr:street":"Hillworth Road",
    "iso:country":"GB",
    "sg:address":"Hillworth Road",
    "sg:city":"Devizes",
    "sg:classifiers":[
        {
            "category":"Home & Garden",
            "subcategory":"Garden Supply",
            "type":"Retail Goods"
        }
    ],
    "sg:postcode":"SN10 5HD",
    "sg:province":"Wiltshire",
    "sg:tags":[
        "planting",
        "tree",
        "shrub"
    ],
    "wof:name":"Wansdyke Nursery",
    "wof:placetype":"venue"
},
  "geometry": {"coordinates":[-1.9940999746,51.3484077454],"type":"Point"}
}