{
  "type": "Feature",
  "properties": {
    "addr:full":"88 Sackville Rd Hove East Sussex BN3 3HE",
    "addr:housenumber":"88",
    "addr:postcode":"bn3 3he",
    "addr:street":"Sackville Rd",
    "iso:country":"GB",
    "sg:address":"88 Sackville Rd",
    "sg:city":"Hove",
    "sg:classifiers":[
        {
            "category":"Place Of Worship",
            "type":"Public Place"
        }
    ],
    "sg:phone":"+44 1273 732427",
    "sg:postcode":"BN3 3HE",
    "sg:province":"East Sussex",
    "wof:name":"St Barnabas C Of E Church",
    "wof:placetype":"venue"
},
  "geometry": {"coordinates":[-0.177266,50.834557],"type":"Point"}
}