{
  "type": "Feature",
  "properties": {
    "iso:country":"GB",
    "sg:address":"20 Myatt Avenue, Aldridge",
    "sg:city":"Walsall",
    "sg:classifiers":[
        {
            "category":"Food & Beverages",
            "subcategory":"Meat & Fish",
            "type":"Retail Goods"
        }
    ],
    "sg:postcode":"WS9 0DR",
    "sg:province":"Staffordshire",
    "sg:tags":[
        "chip"
    ],
    "wof:name":"Pak-Nin-Pse",
    "wof:placetype":"venue"
},
  "geometry": {"coordinates":[-1.933228,52.60043],"type":"Point"}
}