{
  "type": "Feature",
  "properties": {
    "addr:full":"133-135 Castle Rd Scarborough North Yorkshire YO11 1HX",
    "addr:housenumber":"133-135",
    "addr:postcode":"yo11 1hx",
    "addr:street":"Castle Rd",
    "iso:country":"GB",
    "sg:address":"133-135 Castle Rd",
    "sg:city":"Scarborough",
    "sg:classifiers":[
        {
            "category":"Travel",
            "subcategory":"Hotels & Motels",
            "type":"Entertainment"
        }
    ],
    "sg:phone":"+44 1723 374853",
    "sg:postcode":"YO11 1HX",
    "sg:province":"North Yorkshire",
    "wof:name":"Cairn-Cleveleys Hotel",
    "wof:placetype":"venue"
},
  "geometry": {"coordinates":[-0.3954389989,54.2866897583],"type":"Point"}
}