{
  "type": "Feature",
  "properties": {
    "iso:country":"GB",
    "sg:address":"31 Aintree Road, Furnace Green",
    "sg:city":"Crawley",
    "sg:classifiers":[
        {
            "category":"Building & Trades",
            "subcategory":"Construction",
            "type":"Services"
        }
    ],
    "sg:phone":"+44 1293 560810",
    "sg:postcode":"RH10 6LR",
    "sg:province":"Surrey",
    "sg:tags":[
        "roofing"
    ],
    "wof:name":"C D Roofing",
    "wof:placetype":"venue"
},
  "geometry": {"coordinates":[-0.171232,51.1061782837],"type":"Point"}
}