{
  "type": "Feature",
  "properties": {
    "addr:full":"17 Lingfield Crescent London Greater London SE9 2RL",
    "addr:housenumber":"17",
    "addr:postcode":"se9 2rl",
    "addr:street":"Lingfield Crescent",
    "iso:country":"GB",
    "sg:address":"17 Lingfield Crescent",
    "sg:city":"London",
    "sg:classifiers":[
        {
            "category":"Fast Food",
            "type":"Food & Drink"
        },
        {
            "category":"Food & Beverages",
            "subcategory":"Meat & Fish",
            "type":"Retail Goods"
        }
    ],
    "sg:postcode":"SE9 2RL",
    "sg:province":"Greater London",
    "sg:tags":[
        "shop",
        "chip"
    ],
    "wof:name":"Falgonwood Fish Bar",
    "wof:placetype":"venue"
},
  "geometry": {"coordinates":[0.079723,51.458923],"type":"Point"}
}