{
  "type": "Feature",
  "properties": {
    "iso:country":"GB",
    "sg:address":"2 Marigold Close, Nettleham Fields",
    "sg:city":"Lincoln",
    "sg:classifiers":[
        {
            "category":"Building & Trades",
            "subcategory":"Construction",
            "type":"Services"
        }
    ],
    "sg:phone":"+44 1522 528192",
    "sg:postcode":"LN2 4SZ",
    "sg:province":"Lincolnshire",
    "sg:tags":[
        "decorator",
        "painter"
    ],
    "wof:name":"J B Smith",
    "wof:placetype":"venue"
},
  "geometry": {"coordinates":[-0.515507,53.251102],"type":"Point"}
}