{
  "type": "Feature",
  "properties": {
    "iso:country":"GB",
    "sg:address":"226 Cross Road, Mawneys",
    "sg:city":"Romford",
    "sg:classifiers":[
        {
            "category":"Building & Trades",
            "subcategory":"Construction",
            "type":"Services"
        }
    ],
    "sg:phone":"+44 1708 746844",
    "sg:postcode":"RM7 8HX",
    "sg:province":"Essex",
    "sg:tags":[
        "monumental",
        "mason"
    ],
    "wof:name":"C J Bradford",
    "wof:placetype":"venue"
},
  "geometry": {"coordinates":[0.159927,51.591385],"type":"Point"}
}