{
  "type": "Feature",
  "properties": {
    "iso:country":"GB",
    "sg:address":"110 Brooklands Avenue, Broughton",
    "sg:city":"Brigg",
    "sg:classifiers":[
        {
            "category":"Building & Trades",
            "subcategory":"Construction",
            "type":"Services"
        }
    ],
    "sg:phone":"+44 1652 653563",
    "sg:postcode":"DN20 0ED",
    "sg:province":"Lincolnshire",
    "sg:tags":[
        "joiner",
        "carpenter"
    ],
    "wof:name":"Simon Beedham",
    "wof:placetype":"venue"
},
  "geometry": {"coordinates":[-0.552747,53.569214],"type":"Point"}
}