{
  "type": "Feature",
  "properties": {
    "iso:country":"GB",
    "sg:address":"2 Green Lawn",
    "sg:city":"Liverpool",
    "sg:classifiers":[
        {
            "category":"Retail",
            "subcategory":"Driving School",
            "type":"Services"
        }
    ],
    "sg:phone":"+44 151 489 8122",
    "sg:postcode":"L36 1YA",
    "sg:province":"Merseyside",
    "wof:name":"Linway Driving School",
    "wof:placetype":"venue"
},
  "geometry": {"coordinates":[-2.822171,53.421043],"type":"Point"}
}