{
  "type": "Feature",
  "properties": {
    "addr:full":"Narrow Lane Farm, Clieves Hills, Aughton Ormskirk Lancashire L39 7HD",
    "addr:housenumber":"clieves",
    "addr:postcode":"l39 7hd",
    "addr:street":"Narrow Lane;Hills Aughton",
    "iso:country":"GB",
    "sg:address":"Narrow Lane Farm, Clieves Hills, Aughton",
    "sg:city":"Ormskirk",
    "sg:classifiers":[
        {
            "category":"Farming",
            "subcategory":"Farm",
            "type":"Manufacturing & Wholesale Goods"
        }
    ],
    "sg:postcode":"L39 7HD",
    "sg:province":"Lancashire",
    "sg:tags":[
        "mixed",
        "crop"
    ],
    "wof:name":"Serjeant,John,",
    "wof:placetype":"venue"
},
  "geometry": {"coordinates":[-2.9295430183,53.5681114197],"type":"Point"}
}