{
  "type": "Feature",
  "properties": {
    "addr:full":"12 Whitehills Rise, Cove Bay Aberdeen Aberdeen City AB12 3UH",
    "addr:housenumber":"12",
    "addr:postcode":"ab12 3uh",
    "addr:street":"Whitehills Rise Cove",
    "iso:country":"GB",
    "sg:address":"12 Whitehills Rise, Cove Bay",
    "sg:city":"Aberdeen",
    "sg:classifiers":[
        {
            "category":"Professional",
            "subcategory":"Accounting & Tax Preparation",
            "type":"Services"
        }
    ],
    "sg:postcode":"AB12 3UH",
    "sg:province":"Aberdeen City",
    "sg:tags":[
        "accountant"
    ],
    "wof:name":"Abacus Computerised Bookeeping Services",
    "wof:placetype":"venue"
},
  "geometry": {"coordinates":[-2.0904641151,57.0996894836],"type":"Point"}
}