{
  "type": "Feature",
  "properties": {
    "addr:full":"4 Court Close, Little Dewchurch Hereford Herefordshire HR2 6PT",
    "addr:housenumber":"4",
    "addr:postcode":"hr2 6pt",
    "addr:street":"Court Close",
    "iso:country":"GB",
    "sg:address":"4 Court Close, Little Dewchurch",
    "sg:city":"Hereford",
    "sg:classifiers":[
        {
            "category":"Building & Trades",
            "subcategory":"Construction",
            "type":"Services"
        }
    ],
    "sg:phone":"+44 1432 840384",
    "sg:postcode":"HR2 6PT",
    "sg:province":"Herefordshire",
    "sg:tags":[
        "builder"
    ],
    "wof:name":"Maurice A Savage",
    "wof:placetype":"venue"
},
  "geometry": {"coordinates":[-2.71596,52.04694],"type":"Point"}
}