{
  "type": "Feature",
  "properties": {
    "addr:full":"15 Partridge Drive, Fordham Colchester Essex CO6 3NH",
    "addr:housenumber":"15",
    "addr:postcode":"co6 3nh",
    "addr:street":"Partridge Drive",
    "iso:country":"GB",
    "sg:address":"15 Partridge Drive, Fordham",
    "sg:city":"Colchester",
    "sg:classifiers":[
        {
            "category":"Building & Trades",
            "subcategory":"Construction",
            "type":"Services"
        }
    ],
    "sg:phone":"+44 1206 212862",
    "sg:postcode":"CO6 3NH",
    "sg:province":"Essex",
    "sg:tags":[
        "roofing"
    ],
    "wof:name":"R  T  Roofing Services Ltd.",
    "wof:placetype":"venue"
},
  "geometry": {"coordinates":[0.800494,51.919201],"type":"Point"}
}