{
  "type": "Feature",
  "properties": {
    "addr:full":"147 High Street Lewes East Sussex BN7 1XT",
    "addr:housenumber":"147",
    "addr:postcode":"bn7 1xt",
    "addr:street":"High Street",
    "iso:country":"GB",
    "sg:address":"147 High Street",
    "sg:city":"Lewes",
    "sg:classifiers":[
        {
            "category":"Shopping",
            "subcategory":"Clothing, Apparel, & Fashions",
            "type":"Retail Goods"
        }
    ],
    "sg:phone":"+44 1273 472677",
    "sg:postcode":"BN7 1XT",
    "sg:province":"East Sussex",
    "sg:tags":[
        "shop"
    ],
    "wof:name":"Elegance",
    "wof:placetype":"venue"
},
  "geometry": {"coordinates":[0.0063430001,50.8720703125],"type":"Point"}
}