{
  "type": "Feature",
  "properties": {
    "addr:full":"66 Ferring Street, Ferring Worthing West Sussex BN12 5JP",
    "addr:housenumber":"66",
    "addr:postcode":"bn12 5jp",
    "addr:street":"Ferring Street",
    "iso:country":"GB",
    "sg:address":"66 Ferring Street, Ferring",
    "sg:city":"Worthing",
    "sg:classifiers":[
        {
            "category":"Shopping",
            "subcategory":"Thrift Store",
            "type":"Retail Goods"
        }
    ],
    "sg:phone":"+44 1903 700359",
    "sg:postcode":"BN12 5JP",
    "sg:province":"West Sussex",
    "sg:tags":[
        "shop",
        "charity"
    ],
    "wof:name":"St Barnabas Hospice",
    "wof:placetype":"venue"
},
  "geometry": {"coordinates":[-0.447122,50.815212],"type":"Point"}
}