{
  "type": "Feature",
  "properties": {
    "addr:full":"39 Bedford Avenue Hayes Greater London UB4 0DR",
    "addr:housenumber":"39",
    "addr:postcode":"ub4 0dr",
    "addr:street":"Bedford Avenue",
    "iso:country":"GB",
    "sg:address":"39 Bedford Avenue",
    "sg:city":"Hayes",
    "sg:classifiers":[
        {
            "category":"Professional",
            "subcategory":"Computer Services",
            "type":"Services"
        }
    ],
    "sg:phone":"+44 20 8848 8802",
    "sg:postcode":"UB4 0DR",
    "sg:province":"Greater London",
    "sg:tags":[
        "system",
        "software"
    ],
    "wof:name":"Kweku Associates Ltd.",
    "wof:placetype":"venue"
},
  "geometry": {"coordinates":[-0.4071390033,51.5199775696],"type":"Point"}
}