{
  "type": "Feature",
  "properties": {
    "iso:country":"GB",
    "sg:address":"High Street",
    "sg:city":"Aberdeen",
    "sg:classifiers":[
        {
            "category":"Retail",
            "subcategory":"Auto Repair",
            "type":"Services"
        }
    ],
    "sg:postcode":"AB15 8SL",
    "sg:province":"Aberdeen City",
    "sg:tags":[
        "modification",
        "garage"
    ],
    "wof:name":"J Marnoch",
    "wof:placetype":"venue"
},
  "geometry": {"coordinates":[-2.102189,57.166996],"type":"Point"}
}