{
  "type": "Feature",
  "properties": {
    "iso:country":"GB",
    "sg:address":"79a High Street",
    "sg:city":"Burton-on-trent",
    "sg:classifiers":[
        {
            "category":"Social Services",
            "subcategory":"Adult Care",
            "type":"Services"
        }
    ],
    "sg:phone":"+44 1283 566696",
    "sg:postcode":"DE14 1LQ",
    "sg:province":"Derbyshire",
    "sg:tags":[
        "day",
        "centre"
    ],
    "wof:name":"Mind in S.E. Staffs",
    "wof:placetype":"venue"
},
  "geometry": {"coordinates":[-1.629884,52.802612],"type":"Point"}
}