{
  "type": "Feature",
  "properties": {
    "iso:country":"GB",
    "sg:address":"Unit 3 South Pontypool Industrial Park",
    "sg:city":"Pontypool",
    "sg:classifiers":[
        {
            "category":"Shopping",
            "subcategory":"Stationery & Office Supplies",
            "type":"Retail Goods"
        }
    ],
    "sg:phone":"+44 1495 759828",
    "sg:postcode":"NP4 0LS",
    "sg:province":"Monmouthshire",
    "sg:tags":[
        "equipment"
    ],
    "wof:name":"Economy Office Supplies Ltd",
    "wof:placetype":"venue"
},
  "geometry": {"coordinates":[-3.052949,51.709805],"type":"Point"}
}