{
  "type": "Feature",
  "properties": {
    "iso:country":"GB",
    "sg:address":"67 New Street",
    "sg:city":"Mold",
    "sg:classifiers":[
        {
            "category":"Professional",
            "subcategory":"Engineering",
            "type":"Services"
        }
    ],
    "sg:phone":"+44 1352 759587",
    "sg:postcode":"CH7 1NY",
    "sg:province":"Denbighshire",
    "sg:tags":[
        "civil",
        "engineer"
    ],
    "wof:name":"B T Construction",
    "wof:placetype":"venue"
},
  "geometry": {"coordinates":[-3.1460740566,53.1645240784],"type":"Point"}
}