{
  "type": "Feature",
  "properties": {
    "addr:full":"7 Carlton Street Halifax West Yorkshire HX1 2AL",
    "addr:housenumber":"7",
    "addr:postcode":"hx1 2al",
    "addr:street":"Carlton Street",
    "iso:country":"GB",
    "sg:address":"7 Carlton Street",
    "sg:city":"Halifax",
    "sg:classifiers":[
        {
            "category":"Health Services",
            "subcategory":"Health Practitioner",
            "type":"Services"
        }
    ],
    "sg:phone":"+44 1422 360759",
    "sg:postcode":"HX1 2AL",
    "sg:province":"West Yorkshire",
    "sg:tags":[
        "osteopath"
    ],
    "wof:name":"David A Sykes & Associates",
    "wof:placetype":"venue"
},
  "geometry": {"coordinates":[-1.864084,53.720448],"type":"Point"}
}