{
  "type": "Feature",
  "properties": {
    "addr:full":"46 Darland Ave Gillingham Kent ME7 3AN",
    "addr:housenumber":"46",
    "addr:postcode":"me7 3an",
    "addr:street":"Darland Ave",
    "iso:country":"GB",
    "sg:address":"46 Darland Ave",
    "sg:city":"Gillingham",
    "sg:classifiers":[
        {
            "category":"Building & Trades",
            "subcategory":"Construction",
            "type":"Services"
        }
    ],
    "sg:postcode":"ME7 3AN",
    "sg:province":"Kent",
    "sg:tags":[
        "contractor",
        "paving",
        "driveway"
    ],
    "wof:name":"Burke,M,",
    "wof:placetype":"venue"
},
  "geometry": {"coordinates":[0.561891,51.369652],"type":"Point"}
}