{
  "type": "Feature",
  "properties": {
    "iso:country":"GB",
    "sg:address":"273 South Coast Road",
    "sg:city":"Peacehaven",
    "sg:classifiers":[
        {
            "category":"Shopping",
            "subcategory":"Pets & Pet Supplies",
            "type":"Retail Goods"
        }
    ],
    "sg:phone":"+44 1273 580311",
    "sg:postcode":"BN10 7JE",
    "sg:province":"East Sussex",
    "wof:name":"Haven Hutches & Pet Foods",
    "wof:placetype":"venue"
},
  "geometry": {"coordinates":[-0.005921,50.792152],"type":"Point"}
}