{
  "type": "Feature",
  "properties": {
    "addr:full":"28 Alfreton Road Sutton-in-ashfield Nottinghamshire NG17 1FW",
    "addr:housenumber":"28",
    "addr:postcode":"ng17 1fw",
    "addr:street":"Alfreton Road",
    "iso:country":"GB",
    "sg:address":"28 Alfreton Road",
    "sg:city":"Sutton-in-ashfield",
    "sg:classifiers":[
        {
            "category":"Building & Trades",
            "subcategory":"Construction",
            "type":"Services"
        }
    ],
    "sg:phone":"+44 1623 554472",
    "sg:postcode":"NG17 1FW",
    "sg:province":"Nottinghamshire",
    "sg:tags":[
        "builder"
    ],
    "wof:name":"H Evans & Son Sutton-In-Ashfield Ltd",
    "wof:placetype":"venue"
},
  "geometry": {"coordinates":[-1.2738980055,53.1223869324],"type":"Point"}
}