{
  "type": "Feature",
  "properties": {
    "addr:full":"Elvin Garth, Normanby Rise, Claxby Market Rasen Lincolnshire LN8 3YZ",
    "addr:housenumber":"claxby",
    "addr:postcode":"ln8 3yz",
    "addr:street":"Elvin Garth Normanby Rise;Rasen",
    "iso:country":"GB",
    "sg:address":"Elvin Garth, Normanby Rise, Claxby",
    "sg:city":"Market Rasen",
    "sg:classifiers":[
        {
            "category":"Professional",
            "subcategory":"Accounting & Tax Preparation",
            "type":"Services"
        }
    ],
    "sg:postcode":"LN8 3YZ",
    "sg:province":"Lincolnshire",
    "sg:tags":[
        "accountant"
    ],
    "wof:name":"Peter & Susan K Broadley",
    "wof:placetype":"venue"
},
  "geometry": {"coordinates":[-0.3330680132,53.3867874146],"type":"Point"}
}