{
  "type": "Feature",
  "properties": {
    "iso:country":"GB",
    "sg:address":"Hafod Farm",
    "sg:city":"Port Talbot",
    "sg:classifiers":[
        {
            "category":"Shopping",
            "subcategory":"Gifts & Souvenirs",
            "type":"Retail Goods"
        }
    ],
    "sg:phone":"+44 1639 895249",
    "sg:postcode":"SA13 2YR",
    "sg:province":"Neath Port Talbot",
    "sg:tags":[
        "giftware"
    ],
    "wof:name":"Gifts From The Grange",
    "wof:placetype":"venue"
},
  "geometry": {"coordinates":[-3.7323200703,51.594959259],"type":"Point"}
}