{
  "type": "Feature",
  "properties": {
    "addr:full":"17 Station Road, Puckeridge Ware Hertfordshire SG11 1SN",
    "addr:housenumber":"17",
    "addr:postcode":"sg11 1sn",
    "addr:street":"Station Road;Ware",
    "iso:country":"GB",
    "sg:address":"17 Station Road, Puckeridge",
    "sg:city":"Ware",
    "sg:classifiers":[
        {
            "category":"Professional",
            "subcategory":"Accounting & Tax Preparation",
            "type":"Services"
        }
    ],
    "sg:postcode":"SG11 1SN",
    "sg:province":"Hertfordshire",
    "sg:tags":[
        "accountant"
    ],
    "wof:name":"R Jackson & Co",
    "wof:placetype":"venue"
},
  "geometry": {"coordinates":[0.014357,51.890343],"type":"Point"}
}