{
  "type": "Feature",
  "properties": {
    "iso:country":"GB",
    "sg:address":"Bruntsfield House, 6b Bruntsfield Terrace",
    "sg:city":"Edinburgh",
    "sg:classifiers":[
        {
            "category":"Banks & Credit Unions",
            "subcategory":"Financial Services",
            "type":"Services"
        }
    ],
    "sg:postcode":"EH10 4EX",
    "sg:province":"City of Edinburgh",
    "sg:tags":[
        "adviser"
    ],
    "wof:name":"Brodie Maclean Ltd.",
    "wof:placetype":"venue"
},
  "geometry": {"coordinates":[-3.206387,55.936661],"type":"Point"}
}