{
  "type": "Feature",
  "properties": {
    "iso:country":"GB",
    "sg:address":"40 Kingsley Road",
    "sg:city":"Northampton",
    "sg:classifiers":[
        {
            "category":"Social Services",
            "type":"Services"
        },
        {
            "category":"Health Services",
            "subcategory":"Dentist",
            "type":"Services"
        }
    ],
    "sg:phone":"+44 1604 714149",
    "sg:postcode":"NN2 7BL",
    "sg:province":"Northamptonshire",
    "sg:tags":[
        "authority"
    ],
    "wof:name":"A S Robertson",
    "wof:placetype":"venue"
},
  "geometry": {"coordinates":[-0.881636,52.251709],"type":"Point"}
}