{
  "type": "Feature",
  "properties": {
    "iso:country":"GB",
    "sg:address":"49-51 Huddersfield Road, Holmfirth",
    "sg:city":"Huddersfield",
    "sg:classifiers":[
        {
            "category":"Landmark",
            "subcategory":"Tourist Information",
            "type":"Public Place"
        },
        {
            "category":"Government",
            "subcategory":"Office",
            "type":"Public Place"
        }
    ],
    "sg:phone":"+44 1484 222444",
    "sg:postcode":"HD7 1JP",
    "sg:province":"West Yorkshire",
    "sg:tags":[
        "local"
    ],
    "wof:name":"Tourist Information Centre",
    "wof:placetype":"venue"
},
  "geometry": {"coordinates":[-1.78268,53.64695],"type":"Point"}
}