{
  "type": "Feature",
  "properties": {
    "iso:country":"GB",
    "sg:address":"49 Taldwyn Terrace, Troedyrhiw",
    "sg:city":"Merthyr Tydfil",
    "sg:classifiers":[
        {
            "category":"Retail",
            "subcategory":"Repair Shop",
            "type":"Services"
        }
    ],
    "sg:phone":"+44 1443 692113",
    "sg:postcode":"CF48 4JL",
    "sg:province":"Caerphilly",
    "sg:tags":[
        "upholstering",
        "upholsterer"
    ],
    "wof:name":"Revival Upholstery",
    "wof:placetype":"venue"
},
  "geometry": {"coordinates":[-3.345824,51.71397],"type":"Point"}
}