{
  "type": "Feature",
  "properties": {
    "addr:full":"Hollow Oak Farm, Breach Oak Lane, Corley Coventry Warwickshire CV7 8AW",
    "addr:postcode":"cv7 8aw",
    "addr:street":"Hollow Oak;Breach Oak Lane",
    "iso:country":"GB",
    "sg:address":"Hollow Oak Farm, Breach Oak Lane, Corley",
    "sg:city":"Coventry",
    "sg:classifiers":[
        {
            "category":"Farming",
            "subcategory":"Livestock Farm",
            "type":"Manufacturing & Wholesale Goods"
        }
    ],
    "sg:postcode":"CV7 8AW",
    "sg:province":"Warwickshire",
    "sg:tags":[
        "others"
    ],
    "wof:name":"Arthur Brandreth",
    "wof:placetype":"venue"
},
  "geometry": {"coordinates":[-1.558937,52.464916],"type":"Point"}
}