{
  "type": "Feature",
  "properties": {
    "addr:full":"Whitefield Road, Bredbury Stockport Cheshire SK6 2SS",
    "addr:postcode":"sk6 2ss",
    "addr:street":"Whitefield Road",
    "iso:country":"GB",
    "sg:address":"Whitefield Road, Bredbury",
    "sg:city":"Stockport",
    "sg:classifiers":[
        {
            "category":"Recreation",
            "subcategory":"Boat Charter",
            "type":"Entertainment"
        }
    ],
    "sg:phone":"+44 161 430 6618",
    "sg:postcode":"SK6 2SS",
    "sg:province":"Cheshire",
    "sg:tags":[
        "excursion"
    ],
    "wof:name":"Luxury Dive Charters Ltd.",
    "wof:placetype":"venue"
},
  "geometry": {"coordinates":[-2.122762,53.42065],"type":"Point"}
}