{
  "type": "Feature",
  "properties": {
    "addr:full":"98 Turnhouse Road Edinburgh City of Edinburgh EH12 8ND",
    "addr:housenumber":"98",
    "addr:postcode":"eh12 8nd",
    "addr:street":"Turnhouse Road",
    "iso:country":"GB",
    "sg:address":"98 Turnhouse Road",
    "sg:city":"Edinburgh",
    "sg:classifiers":[
        {
            "category":"Wholesale",
            "subcategory":"Machinery & Supplies",
            "type":"Manufacturing & Wholesale Goods"
        }
    ],
    "sg:phone":"+44 131 339 1060",
    "sg:postcode":"EH12 8ND",
    "sg:province":"City of Edinburgh",
    "sg:tags":[
        "pump"
    ],
    "wof:name":"S L D Pumps",
    "wof:placetype":"venue"
},
  "geometry": {"coordinates":[-3.3180260658,55.9424858093],"type":"Point"}
}