{
  "type": "Feature",
  "properties": {
    "iso:country":"GB",
    "sg:address":"Central Drive",
    "sg:city":"Morecambe",
    "sg:classifiers":[
        {
            "category":"Education",
            "subcategory":"Library",
            "type":"Public Place"
        }
    ],
    "sg:phone":"+44 1524 415215",
    "sg:postcode":"LA4 5DL",
    "sg:province":"Lancashire",
    "sg:tags":[
        "book"
    ],
    "wof:name":"Morecambe Library",
    "wof:placetype":"venue"
},
  "geometry": {"coordinates":[-2.864201,54.071835],"type":"Point"}
}