{
  "type": "Feature",
  "properties": {
    "addr:full":"77-79 High Road London Greater London N22 6BB",
    "addr:housenumber":"77-79",
    "addr:postcode":"n22 6bb",
    "addr:street":"High Road",
    "iso:country":"GB",
    "sg:address":"77-79 High Road",
    "sg:city":"London",
    "sg:classifiers":[
        {
            "category":"Travel",
            "subcategory":"Travel Agent",
            "type":"Entertainment"
        }
    ],
    "sg:phone":"+44 845 308 9659",
    "sg:postcode":"N22 6BB",
    "sg:province":"Greater London",
    "sg:tags":[
        "agency",
        "activity"
    ],
    "wof:name":"Thomas Cook",
    "wof:placetype":"venue"
},
  "geometry": {"coordinates":[-0.106464,51.593136],"type":"Point"}
}