{
  "type": "Feature",
  "properties": {
    "iso:country":"GB",
    "sg:address":"Unit 2b Gaunts Busns Centre, Gaunts",
    "sg:city":"Wimborne",
    "sg:classifiers":[
        {
            "category":"Real Estate",
            "subcategory":"Surveying",
            "type":"Services"
        },
        {
            "category":"Real Estate",
            "subcategory":"Architect",
            "type":"Services"
        }
    ],
    "sg:phone":"+44 1202 840404",
    "sg:postcode":"BH21 4JT",
    "sg:province":"Dorset",
    "sg:tags":[
        "surveyor",
        "land"
    ],
    "wof:name":"Southern Land Surveys",
    "wof:placetype":"venue"
},
  "geometry": {"coordinates":[-1.974045,50.838261],"type":"Point"}
}