{
  "type": "Feature",
  "properties": {
    "addr:full":"Church Road Buckley Denbighshire CH7 3AD",
    "addr:postcode":"ch7 3ad",
    "addr:street":"Church Road",
    "iso:country":"GB",
    "sg:address":"Church Road",
    "sg:city":"Buckley",
    "sg:classifiers":[
        {
            "category":"Autos & Motor Vehicles",
            "subcategory":"Auto Supplies",
            "type":"Retail Goods"
        }
    ],
    "sg:postcode":"CH7 3AD",
    "sg:province":"Denbighshire",
    "sg:tags":[
        "tyre"
    ],
    "wof:name":"Buckley Tyre Services",
    "wof:placetype":"venue"
},
  "geometry": {"coordinates":[-3.072099,53.173386],"type":"Point"}
}