{
  "type": "Feature",
  "properties": {
    "addr:full":"20 Oxford Place Plymouth Devon PL1 5AJ",
    "addr:housenumber":"20",
    "addr:postcode":"pl1 5aj",
    "addr:street":"Oxford Place",
    "iso:country":"GB",
    "sg:address":"20 Oxford Place",
    "sg:city":"Plymouth",
    "sg:classifiers":[
        {
            "category":"Organizations",
            "subcategory":"Non-profit Organization",
            "type":"Services"
        }
    ],
    "sg:phone":"+44 1752 221666",
    "sg:postcode":"PL1 5AJ",
    "sg:province":"Devon",
    "sg:tags":[
        "organisation",
        "voluntary",
        "charity"
    ],
    "wof:name":"The Samaritans",
    "wof:placetype":"venue"
},
  "geometry": {"coordinates":[-4.144459,50.374573],"type":"Point"}
}