{
  "type": "Feature",
  "properties": {
    "addr:full":"24 Lingfield Close High Wycombe Buckinghamshire HP13 7ER",
    "addr:housenumber":"24",
    "addr:postcode":"hp13 7er",
    "addr:street":"Lingfield Close",
    "iso:country":"GB",
    "sg:address":"24 Lingfield Close",
    "sg:city":"High Wycombe",
    "sg:classifiers":[
        {
            "category":"Autos & Motor Vehicles",
            "subcategory":"Motorcycle Sales",
            "type":"Retail Goods"
        }
    ],
    "sg:phone":"+44 1494 465577",
    "sg:postcode":"HP13 7ER",
    "sg:province":"Buckinghamshire",
    "sg:tags":[
        "chauffeur",
        "driven",
        "car"
    ],
    "wof:name":"Mph Executive Chauffeur",
    "wof:placetype":"venue"
},
  "geometry": {"coordinates":[-0.714376,51.623699],"type":"Point"}
}