{
  "type": "Feature",
  "properties": {
    "addr:full":"33 College Street Swansea Neath Port Talbot SA1 5AE",
    "addr:housenumber":"33",
    "addr:postcode":"sa1 5ae",
    "addr:street":"College Street",
    "iso:country":"GB",
    "sg:address":"33 College Street",
    "sg:city":"Swansea",
    "sg:classifiers":[
        {
            "category":"Social Services",
            "type":"Services"
        },
        {
            "category":"Government",
            "subcategory":"Office",
            "type":"Public Place"
        }
    ],
    "sg:phone":"+44 1269 596885",
    "sg:postcode":"SA1 5AE",
    "sg:province":"Neath Port Talbot",
    "sg:tags":[
        "local"
    ],
    "wof:name":"Carmarthen & Dinefwr Child Resource Centre",
    "wof:placetype":"venue"
},
  "geometry": {"coordinates":[-3.942269,51.62167],"type":"Point"}
}