{
  "type": "Feature",
  "properties": {
    "addr:full":"39 Alan Rd Ipswich Suffolk IP3 8EY",
    "addr:housenumber":"39",
    "addr:postcode":"ip3 8ey",
    "addr:street":"Alan Rd",
    "iso:country":"GB",
    "sg:address":"39 Alan Rd",
    "sg:city":"Ipswich",
    "sg:classifiers":[
        {
            "category":"Building & Trades",
            "subcategory":"Plumbing",
            "type":"Services"
        }
    ],
    "sg:phone":"+44 1473 211154",
    "sg:postcode":"IP3 8EY",
    "sg:province":"Suffolk",
    "sg:tags":[
        "heating"
    ],
    "wof:name":"C.J. Robinson And Leverett Ltd",
    "wof:placetype":"venue"
},
  "geometry": {"coordinates":[1.176929,52.04932],"type":"Point"}
}