{
  "type": "Feature",
  "properties": {
    "addr:full":"Cross House, Churchtown, St Issey Wadebridge Cornwall PL27 7QB",
    "addr:postcode":"pl27 7qb",
    "addr:street":"Churchtown St",
    "iso:country":"GB",
    "sg:address":"Cross House, Churchtown, St Issey",
    "sg:city":"Wadebridge",
    "sg:classifiers":[
        {
            "category":"Farming",
            "subcategory":"Livestock Farm",
            "type":"Manufacturing & Wholesale Goods"
        }
    ],
    "sg:phone":"+44 1841 540454",
    "sg:postcode":"PL27 7QB",
    "sg:province":"Cornwall",
    "sg:tags":[
        "others"
    ],
    "wof:name":"Tony House",
    "wof:placetype":"venue"
},
  "geometry": {"coordinates":[-4.8380241394,50.5181884766],"type":"Point"}
}