{
  "type": "Feature",
  "properties": {
    "addr:full":"87 Main St Kilbirnie North Ayrshire KA25 7AA",
    "addr:housenumber":"87",
    "addr:postcode":"ka25 7aa",
    "addr:street":"Main St",
    "iso:country":"GB",
    "sg:address":"87 Main St",
    "sg:city":"Kilbirnie",
    "sg:classifiers":[
        {
            "category":"Shopping",
            "subcategory":"Thrift Store",
            "type":"Retail Goods"
        }
    ],
    "sg:postcode":"KA25 7AA",
    "sg:province":"North Ayrshire",
    "sg:tags":[
        "shop",
        "charity"
    ],
    "wof:name":"Ayrshire Cancer Support Group",
    "wof:placetype":"venue"
},
  "geometry": {"coordinates":[-4.6856031418,55.7551803589],"type":"Point"}
}