{
  "type": "Feature",
  "properties": {
    "iso:country":"GB",
    "sg:address":"5 Thickwood Moss Lane, Rainford",
    "sg:city":"St Helens",
    "sg:classifiers":[
        {
            "category":"Building & Trades",
            "subcategory":"Construction",
            "type":"Services"
        }
    ],
    "sg:phone":"+44 1744 884479",
    "sg:postcode":"WA11 8QL",
    "sg:province":"Lancashire",
    "sg:tags":[
        "builder"
    ],
    "wof:name":"T Draper & Son",
    "wof:placetype":"venue"
},
  "geometry": {"coordinates":[-2.7839679718,53.4963684082],"type":"Point"}
}