{
  "type": "Feature",
  "properties": {
    "iso:country":"GB",
    "sg:address":"Unit 1 & 2 Manor Farm Trading Est",
    "sg:city":"Gillingham",
    "sg:classifiers":[
        {
            "category":"Shopping",
            "subcategory":"Used Merchandise",
            "type":"Retail Goods"
        }
    ],
    "sg:phone":"+44 1258 820016",
    "sg:postcode":"SP8 5RR",
    "sg:province":"Dorset",
    "sg:tags":[
        "furniture"
    ],
    "wof:name":"Bill & Mary",
    "wof:placetype":"venue"
},
  "geometry": {"coordinates":[-2.3197200298,50.9901885986],"type":"Point"}
}