{
  "type": "Feature",
  "properties": {
    "iso:country":"GB",
    "sg:address":"14 Heol Brynhyfryd, Llantwit Fardre",
    "sg:city":"Pontypridd",
    "sg:classifiers":[
        {
            "category":"Building & Trades",
            "subcategory":"Pest Control",
            "type":"Services"
        }
    ],
    "sg:phone":"+44 1443 201997",
    "sg:postcode":"CF38 2RH",
    "sg:province":"Rhondda, Cynon, Taff",
    "sg:tags":[
        "vermin"
    ],
    "wof:name":"R C Pest Control Services",
    "wof:placetype":"venue"
},
  "geometry": {"coordinates":[-3.345975,51.560226],"type":"Point"}
}