{
  "type": "Feature",
  "properties": {
    "addr:full":"208 High St Berkhamsted Bedfordshire HP4 1AG",
    "addr:housenumber":"208",
    "addr:postcode":"hp4 1ag",
    "addr:street":"High St",
    "iso:country":"GB",
    "sg:address":"208 High St",
    "sg:city":"Berkhamsted",
    "sg:classifiers":[
        {
            "category":"Farming",
            "subcategory":"Fish & Marine Products",
            "type":"Manufacturing & Wholesale Goods"
        }
    ],
    "sg:phone":"+44 1442 877117",
    "sg:postcode":"HP4 1AG",
    "sg:province":"Bedfordshire",
    "sg:tags":[
        "fishmonger"
    ],
    "wof:name":"Berkhamsted Fisheries",
    "wof:placetype":"venue"
},
  "geometry": {"coordinates":[-0.5659760237,51.7609634399],"type":"Point"}
}