{
  "type": "Feature",
  "properties": {
    "iso:country":"GB",
    "sg:address":"Britannic Chambers, 21 South Street",
    "sg:city":"Dalkeith",
    "sg:classifiers":[
        {
            "category":"Professional",
            "subcategory":"Lawyer & Legal Services",
            "type":"Services"
        }
    ],
    "sg:phone":"+44 131 663 4327",
    "sg:postcode":"EH22 1AH",
    "sg:province":"City of Edinburgh",
    "sg:tags":[
        "solicitor"
    ],
    "wof:name":"Maurice R Wright",
    "wof:placetype":"venue"
},
  "geometry": {"coordinates":[-3.068613,55.892879],"type":"Point"}
}