{
  "type": "Feature",
  "properties": {
    "addr:full":"Tangham Outstation, Tangham Woodbridge Suffolk IP12 3NF",
    "addr:postcode":"ip12 3nf",
    "iso:country":"GB",
    "sg:address":"Tangham Outstation, Tangham",
    "sg:city":"Woodbridge",
    "sg:classifiers":[
        {
            "category":"Building & Trades",
            "subcategory":"Landscaping Services",
            "type":"Services"
        }
    ],
    "sg:phone":"+44 1394 450214",
    "sg:postcode":"IP12 3NF",
    "sg:province":"Suffolk",
    "sg:tags":[
        "forestry",
        "surgeon",
        "tree"
    ],
    "wof:name":"Forestry Commission England",
    "wof:placetype":"venue"
},
  "geometry": {"coordinates":[1.4348189831,52.0815734863],"type":"Point"}
}