{
  "type": "Feature",
  "properties": {
    "addr:full":"94 Nolton Street Bridgend Bridgend CF31 3BP",
    "addr:housenumber":"94",
    "addr:postcode":"cf31 3bp",
    "addr:street":"Nolton Street",
    "iso:country":"GB",
    "sg:address":"94 Nolton Street",
    "sg:city":"Bridgend",
    "sg:classifiers":[
        {
            "category":"Fast Food",
            "type":"Food & Drink"
        }
    ],
    "sg:phone":"+44 1656 653303",
    "sg:postcode":"CF31 3BP",
    "sg:province":"Bridgend",
    "sg:tags":[
        "away",
        "meal",
        "outlet",
        "take"
    ],
    "wof:name":"Jade Take Away",
    "wof:placetype":"venue"
},
  "geometry": {"coordinates":[-3.5767738819,51.5027427673],"type":"Point"}
}