{
  "type": "Feature",
  "properties": {
    "addr:full":"Primrose Farm, Arlington Polegate East Sussex BN26 6SJ",
    "addr:postcode":"bn26 6sj",
    "addr:street":"Polegate",
    "iso:country":"GB",
    "sg:address":"Primrose Farm, Arlington",
    "sg:city":"Polegate",
    "sg:classifiers":[
        {
            "category":"Farming",
            "subcategory":"Dairy Farm",
            "type":"Manufacturing & Wholesale Goods"
        }
    ],
    "sg:phone":"+44 1323 482429",
    "sg:postcode":"BN26 6SJ",
    "sg:province":"East Sussex",
    "wof:name":"W & A Appleton (Arlington) Ltd.",
    "wof:placetype":"venue"
},
  "geometry": {"coordinates":[0.244123,50.821339],"type":"Point"}
}