{
  "type": "Feature",
  "properties": {
    "iso:country":"GB",
    "sg:address":"39 King Street, Covent Garden",
    "sg:city":"London",
    "sg:classifiers":[
        {
            "category":"Professional",
            "subcategory":"Computer Services",
            "type":"Services"
        }
    ],
    "sg:postcode":"WC2E 8JS",
    "sg:province":"Greater London",
    "sg:tags":[
        "consultant"
    ],
    "wof:name":"Methods Consulting Ltd.",
    "wof:placetype":"venue"
},
  "geometry": {"coordinates":[-0.124316,51.511883],"type":"Point"}
}