{
  "type": "Feature",
  "properties": {
    "addr:full":"8 Noddington Avenue, Whittington Lichfield Staffordshire WS14 9NQ",
    "addr:housenumber":"8",
    "addr:postcode":"ws14 9nq",
    "addr:street":"Noddington Avenue",
    "iso:country":"GB",
    "sg:address":"8 Noddington Avenue, Whittington",
    "sg:city":"Lichfield",
    "sg:classifiers":[
        {
            "category":"Professional",
            "subcategory":"Art Services",
            "type":"Services"
        }
    ],
    "sg:phone":"+44 1543 432500",
    "sg:postcode":"WS14 9NQ",
    "sg:province":"Staffordshire",
    "sg:tags":[
        "photographer"
    ],
    "wof:name":"Lowe Photographers",
    "wof:placetype":"venue"
},
  "geometry": {"coordinates":[-1.7580410242,52.6768951416],"type":"Point"}
}