{
  "type": "Feature",
  "properties": {
    "addr:full":"73 Bower Lane Rugeley Staffordshire WS15 2RD",
    "addr:housenumber":"73",
    "addr:postcode":"ws15 2rd",
    "addr:street":"Bower Lane",
    "iso:country":"GB",
    "sg:address":"73 Bower Lane",
    "sg:city":"Rugeley",
    "sg:classifiers":[
        {
            "category":"Building & Trades",
            "subcategory":"Construction",
            "type":"Services"
        }
    ],
    "sg:postcode":"WS15 2RD",
    "sg:province":"Staffordshire",
    "sg:tags":[
        "heating",
        "contractor"
    ],
    "wof:name":"Nu-Warm",
    "wof:placetype":"venue"
},
  "geometry": {"coordinates":[-1.9531420469,52.7702598572],"type":"Point"}
}