{
  "type": "Feature",
  "properties": {
    "iso:country":"GB",
    "sg:address":"83 Aldborough Road",
    "sg:city":"Hornchurch",
    "sg:classifiers":[
        {
            "category":"Building & Trades",
            "subcategory":"Construction",
            "type":"Services"
        }
    ],
    "sg:postcode":"RM14 2RS",
    "sg:province":"Essex",
    "sg:tags":[
        "contractor"
    ],
    "wof:name":"Emmerson Construction",
    "wof:placetype":"venue"
},
  "geometry": {"coordinates":[0.23322,51.55719],"type":"Point"}
}