{
  "type": "Feature",
  "properties": {
    "iso:country":"GB",
    "sg:address":"78-80 Perry Hill",
    "sg:city":"Catford",
    "sg:classifiers":[
        {
            "category":"Bars & Pubs",
            "type":"Food & Drink"
        }
    ],
    "sg:phone":"+44 20 8699 5076",
    "sg:postcode":"SE6 4EY",
    "sg:province":"Greater London",
    "sg:tags":[
        "pubs",
        "house",
        "inn",
        "public",
        "activity"
    ],
    "wof:name":"The Two Brewers",
    "wof:placetype":"venue"
},
  "geometry": {"coordinates":[-0.034817,51.43512],"type":"Point"}
}