{
  "type": "Feature",
  "properties": {
    "addr:full":"Elwood House, Sycamore Street Newcastle Emlyn Carmarthenshire SA38 9AP",
    "addr:postcode":"sa38 9ap",
    "addr:street":"Sycamore Street",
    "iso:country":"GB",
    "sg:address":"Elwood House, Sycamore Street",
    "sg:city":"Newcastle Emlyn",
    "sg:classifiers":[
        {
            "category":"Shopping",
            "subcategory":"Clothing, Apparel, & Fashions",
            "type":"Retail Goods"
        }
    ],
    "sg:phone":"+44 1239 711152",
    "sg:postcode":"SA38 9AP",
    "sg:province":"Carmarthenshire",
    "sg:tags":[
        "shop"
    ],
    "wof:name":"Seconds Ahead",
    "wof:placetype":"venue"
},
  "geometry": {"coordinates":[-4.4679679871,52.038318634],"type":"Point"}
}