{
  "type": "Feature",
  "properties": {
    "addr:full":"2180-2182 Coventry Road, Sheldon Birmingham West Midlands B26 3JE",
    "addr:housenumber":"2180-2182",
    "addr:postcode":"b26 3je",
    "addr:street":"Coventry Road",
    "iso:country":"GB",
    "sg:address":"2180-2182 Coventry Road, Sheldon",
    "sg:city":"Birmingham",
    "sg:classifiers":[
        {
            "category":"Shopping",
            "subcategory":"Clothing, Apparel, & Fashions",
            "type":"Retail Goods"
        }
    ],
    "sg:phone":"+44 121 743 2843",
    "sg:postcode":"B26 3JE",
    "sg:province":"West Midlands",
    "sg:tags":[
        "ladieswear"
    ],
    "wof:name":"Bon Marche",
    "wof:placetype":"venue"
},
  "geometry": {"coordinates":[-1.782881,52.452168],"type":"Point"}
}