{
  "type": "Feature",
  "properties": {
    "iso:country":"GB",
    "sg:address":"2 West View, Northgate",
    "sg:city":"Morpeth",
    "sg:classifiers":[
        {
            "category":"Building & Trades",
            "subcategory":"Construction",
            "type":"Services"
        }
    ],
    "sg:phone":"+44 1670 511811",
    "sg:postcode":"NE61 3BT",
    "sg:province":"Northumberland",
    "sg:tags":[
        "builder"
    ],
    "wof:name":"Coulson Builders Ltd",
    "wof:placetype":"venue"
},
  "geometry": {"coordinates":[-1.715499,55.187141],"type":"Point"}
}