{
  "type": "Feature",
  "properties": {
    "addr:full":"6 Dalry Road Kilbirnie North Ayrshire KA25 6HY",
    "addr:housenumber":"6",
    "addr:postcode":"ka25 6hy",
    "addr:street":"Dalry Road",
    "iso:country":"GB",
    "sg:address":"6 Dalry Road",
    "sg:city":"Kilbirnie",
    "sg:classifiers":[
        {
            "category":"Government",
            "subcategory":"Post Office",
            "type":"Public Place"
        }
    ],
    "sg:postcode":"KA25 6HY",
    "sg:province":"North Ayrshire",
    "wof:name":"J & A Gilmour",
    "wof:placetype":"venue"
},
  "geometry": {"coordinates":[-4.687018,55.74712],"type":"Point"}
}