{
  "type": "Feature",
  "properties": {
    "addr:full":"71a Grenville Street Stockport Cheshire SK3 9ER",
    "addr:housenumber":"71a",
    "addr:postcode":"sk3 9er",
    "addr:street":"Grenville Street",
    "iso:country":"GB",
    "sg:address":"71a Grenville Street",
    "sg:city":"Stockport",
    "sg:classifiers":[
        {
            "category":"Shopping",
            "subcategory":"Computers & Home Electronics",
            "type":"Retail Goods"
        },
        {
            "category":"Home & Garden",
            "subcategory":"Carpets & Floor Coverings",
            "type":"Retail Goods"
        }
    ],
    "sg:phone":"+44 161 480 4406",
    "sg:postcode":"SK3 9ER",
    "sg:province":"Cheshire",
    "sg:tags":[
        "wall",
        "system",
        "sales",
        "tie",
        "replacement",
        "software"
    ],
    "wof:name":"Computerised Office Systems",
    "wof:placetype":"venue"
},
  "geometry": {"coordinates":[-2.170847,53.403732],"type":"Point"}
}