{
  "type": "Feature",
  "properties": {
    "addr:full":"Trafalgar House, High Street Treharris Caerphilly CF46 6RW",
    "addr:postcode":"cf46 6rw",
    "addr:street":"High Street",
    "iso:country":"GB",
    "sg:address":"Trafalgar House, High Street",
    "sg:city":"Treharris",
    "sg:classifiers":[
        {
            "category":"Farming",
            "subcategory":"Fish & Marine Products",
            "type":"Manufacturing & Wholesale Goods"
        }
    ],
    "sg:phone":"+44 1443 710230",
    "sg:postcode":"CF46 6RW",
    "sg:province":"Caerphilly",
    "sg:tags":[
        "fishmonger"
    ],
    "wof:name":"W E Handley",
    "wof:placetype":"venue"
},
  "geometry": {"coordinates":[-3.296806,51.671421],"type":"Point"}
}