{
  "type": "Feature",
  "properties": {
    "iso:country":"GB",
    "sg:address":"23 Balaam Street",
    "sg:city":"London",
    "sg:classifiers":[
        {
            "category":"Shopping",
            "subcategory":"Baby Store",
            "type":"Retail Goods"
        }
    ],
    "sg:postcode":"E13 8EB",
    "sg:province":"Greater London",
    "sg:tags":[
        "babywear",
        "childrens"
    ],
    "wof:name":"Shirley's",
    "wof:placetype":"venue"
},
  "geometry": {"coordinates":[0.022444,51.522911],"type":"Point"}
}