{
  "type": "Feature",
  "properties": {
    "addr:full":"57 Lostock Junction Lane, Lostock Bolton Lancashire BL6 4JN",
    "addr:housenumber":"57",
    "addr:postcode":"bl6 4jn",
    "addr:street":"Lostock Junction Lane",
    "iso:country":"GB",
    "sg:address":"57 Lostock Junction Lane, Lostock",
    "sg:city":"Bolton",
    "sg:classifiers":[
        {
            "category":"Building & Trades",
            "subcategory":"Construction",
            "type":"Services"
        }
    ],
    "sg:phone":"+44 1204 844635",
    "sg:postcode":"BL6 4JN",
    "sg:province":"Lancashire",
    "sg:tags":[
        "tiling",
        "contractor"
    ],
    "wof:name":"Lostock Tile Crafts",
    "wof:placetype":"venue"
},
  "geometry": {"coordinates":[-2.494959,53.57489],"type":"Point"}
}