{
  "type": "Feature",
  "properties": {
    "addr:full":"2b Heol-y-deri Cardiff Cardiff CF14 6HF",
    "addr:housenumber":"2b",
    "addr:postcode":"cf14 6hf",
    "addr:street":"Heol-Y-Deri Cardiff",
    "iso:country":"GB",
    "sg:address":"2b Heol-y-deri",
    "sg:city":"Cardiff",
    "sg:classifiers":[
        {
            "category":"Personal",
            "subcategory":"Beauty Salon",
            "type":"Services"
        }
    ],
    "sg:postcode":"CF14 6HF",
    "sg:province":"Cardiff",
    "sg:tags":[
        "unisex",
        "hairdresser"
    ],
    "wof:name":"Aquarius",
    "wof:placetype":"venue"
},
  "geometry": {"coordinates":[-3.2120139599,51.5225105286],"type":"Point"}
}