{
  "type": "Feature",
  "properties": {
    "addr:full":"7 Tamarind Close Guildford Surrey GU2 6YY",
    "addr:housenumber":"7",
    "addr:postcode":"gu2 6yy",
    "addr:street":"Tamarind Close",
    "iso:country":"GB",
    "sg:address":"7 Tamarind Close",
    "sg:city":"Guildford",
    "sg:classifiers":[
        {
            "category":"Home & Garden",
            "subcategory":"Building Materials",
            "type":"Retail Goods"
        },
        {
            "category":"Building & Trades",
            "subcategory":"Construction",
            "type":"Services"
        }
    ],
    "sg:postcode":"GU2 6YY",
    "sg:province":"Surrey",
    "sg:tags":[
        "dry",
        "plasterers",
        "installers",
        "lining",
        "insulation",
        "screeders"
    ],
    "wof:name":"N J Spall Plastering Contractor",
    "wof:placetype":"venue"
},
  "geometry": {"coordinates":[-0.5931959748,51.264213562],"type":"Point"}
}