{
  "type": "Feature",
  "properties": {
    "addr:full":"96 Midland Rd Luton Bedfordshire LU2 0BL",
    "addr:housenumber":"96",
    "addr:postcode":"lu2 0bl",
    "addr:street":"Midland Rd",
    "iso:country":"GB",
    "sg:address":"96 Midland Rd",
    "sg:city":"Luton",
    "sg:classifiers":[
        {
            "category":"Restaurant",
            "type":"Food & Drink"
        }
    ],
    "sg:postcode":"LU2 0BL",
    "sg:province":"Bedfordshire",
    "wof:name":"Smith,Patricia,",
    "wof:placetype":"venue"
},
  "geometry": {"coordinates":[-0.4137690067,51.8830299377],"type":"Point"}
}