{
  "type": "Feature",
  "properties": {
    "addr:full":"94 Wayside Road, St Leonards Ringwood Dorset BH24 2SL",
    "addr:housenumber":"94",
    "addr:postcode":"bh24 2sl",
    "addr:street":"Wayside Road",
    "iso:country":"GB",
    "sg:address":"94 Wayside Road, St Leonards",
    "sg:city":"Ringwood",
    "sg:classifiers":[
        {
            "category":"Transit Center",
            "subcategory":"Passenger",
            "type":"Transportation"
        }
    ],
    "sg:phone":"+44 1202 872463",
    "sg:postcode":"BH24 2SL",
    "sg:province":"Dorset",
    "sg:tags":[
        "boarding",
        "kennel",
        "catteries"
    ],
    "wof:name":"St.Leonards Boarding Kennels & Cattery",
    "wof:placetype":"venue"
},
  "geometry": {"coordinates":[-1.8424789906,50.8175086975],"type":"Point"}
}