{
  "type": "Feature",
  "properties": {
    "addr:full":"32 South Lodge Avenue Mitcham Greater London CR4 1LU",
    "addr:housenumber":"32",
    "addr:postcode":"cr4 1lu",
    "addr:street":"South Lodge Avenue",
    "iso:country":"GB",
    "sg:address":"32 South Lodge Avenue",
    "sg:city":"Mitcham",
    "sg:classifiers":[
        {
            "category":"Food & Beverages",
            "subcategory":"Groceries & Convenience Stores",
            "type":"Retail Goods"
        }
    ],
    "sg:phone":"+44 20 8764 5683",
    "sg:postcode":"CR4 1LU",
    "sg:province":"Greater London",
    "wof:name":"Alldays Stores Ltd.",
    "wof:placetype":"venue"
},
  "geometry": {"coordinates":[-0.132228,51.399796],"type":"Point"}
}