{
  "type": "Feature",
  "properties": {
    "addr:full":"North East Appeals Office, Victoria House, 4 High Chare Chester-le-street Durham DH3 3PX",
    "addr:housenumber":"4",
    "addr:postcode":"dh3 3px",
    "addr:street":"High Chare",
    "iso:country":"GB",
    "sg:address":"North East Appeals Office, Victoria House, 4 High Chare",
    "sg:city":"Chester-le-street",
    "sg:classifiers":[
        {
            "category":"Organizations",
            "subcategory":"Non-profit Organization",
            "type":"Services"
        }
    ],
    "sg:phone":"+44 191 387 3322",
    "sg:postcode":"DH3 3PX",
    "sg:province":"Durham",
    "sg:tags":[
        "organisation",
        "voluntary",
        "charity"
    ],
    "wof:name":"Marie Curie Cancer Care",
    "wof:placetype":"venue"
},
  "geometry": {"coordinates":[-1.573175,54.855148],"type":"Point"}
}