{
  "type": "Feature",
  "properties": {
    "iso:country":"GB",
    "sg:address":"1 Canning Way",
    "sg:city":"Bolton",
    "sg:classifiers":[
        {
            "category":"Shopping",
            "subcategory":"Clothing, Apparel, & Fashions",
            "type":"Retail Goods"
        }
    ],
    "sg:postcode":"BL1 8EZ",
    "sg:province":"Lancashire",
    "sg:tags":[
        "clothing",
        "fabric"
    ],
    "wof:name":"Canning Clothing",
    "wof:placetype":"venue"
},
  "geometry": {"coordinates":[-2.432753,53.5933],"type":"Point"}
}