{
  "type": "Feature",
  "properties": {
    "addr:full":"1 Brook Street, Fenny Compton Southam Warwickshire CV47 2YH",
    "addr:housenumber":"1",
    "addr:postcode":"cv47 2yh",
    "addr:street":"Brook Street",
    "iso:country":"GB",
    "sg:address":"1 Brook Street, Fenny Compton",
    "sg:city":"Southam",
    "sg:classifiers":[
        {
            "category":"Bars & Pubs",
            "type":"Food & Drink"
        }
    ],
    "sg:phone":"+44 1295 770881",
    "sg:postcode":"CV47 2YH",
    "sg:province":"Warwickshire",
    "sg:tags":[
        "pubs",
        "inn"
    ],
    "wof:name":"The Merrie Lion",
    "wof:placetype":"venue"
},
  "geometry": {"coordinates":[-1.3906309605,52.1682357788],"type":"Point"}
}