{
  "type": "Feature",
  "properties": {
    "addr:full":"26 Parkhurst Rd Bexhill On Sea East Sussex TN40 1DF",
    "addr:housenumber":"26",
    "addr:postcode":"tn40 1df",
    "addr:street":"Parkhurst Rd",
    "iso:country":"GB",
    "sg:address":"26 Parkhurst Rd",
    "sg:city":"Bexhill On Sea",
    "sg:classifiers":[
        {
            "category":"Health Services",
            "subcategory":"Dentist",
            "type":"Services"
        }
    ],
    "sg:phone":"+44 1424 222610",
    "sg:postcode":"TN40 1DF",
    "sg:province":"East Sussex",
    "wof:name":"G B Franklin",
    "wof:placetype":"venue"
},
  "geometry": {"coordinates":[0.472095,50.839642],"type":"Point"}
}