{
  "type": "Feature",
  "properties": {
    "iso:country":"GB",
    "sg:address":"9 The Street, Sculthorpe",
    "sg:city":"Fakenham",
    "sg:classifiers":[
        {
            "category":"Bars & Pubs",
            "type":"Food & Drink"
        },
        {
            "category":"Restaurant",
            "type":"Food & Drink"
        }
    ],
    "sg:phone":"+44 1328 856744",
    "sg:postcode":"NR21 9QD",
    "sg:province":"Norfolk",
    "sg:tags":[
        "pubs",
        "inn"
    ],
    "wof:name":"HORSE & GROOM",
    "wof:placetype":"venue"
},
  "geometry": {"coordinates":[0.8161180019,52.8415184021],"type":"Point"}
}