{
  "type": "Feature",
  "properties": {
    "addr:full":"2 Jubilee Way, Thakley Old Rd Shipley West Yorkshire BD18 1QG",
    "addr:housenumber":"2",
    "addr:postcode":"bd18 1qg",
    "addr:street":"Jubilee Way Thakley Old Rd",
    "iso:country":"GB",
    "sg:address":"2 Jubilee Way, Thakley Old Rd",
    "sg:city":"Shipley",
    "sg:classifiers":[
        {
            "category":"Farming",
            "subcategory":"Dairy Farm",
            "type":"Manufacturing & Wholesale Goods"
        }
    ],
    "sg:phone":"+44 1274 595186",
    "sg:postcode":"BD18 1QG",
    "sg:province":"West Yorkshire",
    "wof:name":"MD Foods",
    "wof:placetype":"venue"
},
  "geometry": {"coordinates":[-1.764974,53.836212],"type":"Point"}
}