{
  "type": "Feature",
  "properties": {
    "addr:full":"223 Northolt Road Harrow Greater London HA2 8HN",
    "addr:housenumber":"223",
    "addr:postcode":"ha2 8hn",
    "addr:street":"Northolt Road",
    "iso:country":"GB",
    "sg:address":"223 Northolt Road",
    "sg:city":"Harrow",
    "sg:classifiers":[
        {
            "category":"Professional",
            "subcategory":"Employment Agencies",
            "type":"Services"
        }
    ],
    "sg:phone":"+44 20 8426 8133",
    "sg:postcode":"HA2 8HN",
    "sg:province":"Greater London",
    "sg:tags":[
        "consultant"
    ],
    "wof:name":"SPR12 Ltd.",
    "wof:placetype":"venue"
},
  "geometry": {"coordinates":[-0.3524659872,51.5648498535],"type":"Point"}
}