{
  "type": "Feature",
  "properties": {
    "iso:country":"GB",
    "sg:address":"56 Leeds Road",
    "sg:city":"Ilkley",
    "sg:classifiers":[
        {
            "category":"Education",
            "subcategory":"School",
            "type":"Public Place"
        }
    ],
    "sg:postcode":"LS29 8EQ",
    "sg:province":"North Yorkshire",
    "sg:tags":[
        "local",
        "authority"
    ],
    "wof:name":"Skillwise Training Ltd",
    "wof:placetype":"venue"
},
  "geometry": {"coordinates":[-1.817049,53.92849],"type":"Point"}
}