{
  "type": "Feature",
  "properties": {
    "addr:full":"18 Pipers Croft Dunstable Bedfordshire LU6 3JZ",
    "addr:housenumber":"18",
    "addr:postcode":"lu6 3jz",
    "addr:street":"Pipers Croft",
    "iso:country":"GB",
    "sg:address":"18 Pipers Croft",
    "sg:city":"Dunstable",
    "sg:classifiers":[
        {
            "category":"Building & Trades",
            "subcategory":"Plumbing",
            "type":"Services"
        }
    ],
    "sg:phone":"+44 1582 667924",
    "sg:postcode":"LU6 3JZ",
    "sg:province":"Bedfordshire",
    "sg:tags":[
        "heating"
    ],
    "wof:name":"Grahame Pratt",
    "wof:placetype":"venue"
},
  "geometry": {"coordinates":[-0.535896,51.881397],"type":"Point"}
}