{
  "type": "Feature",
  "properties": {
    "iso:country":"GB",
    "sg:address":"The Hangars",
    "sg:city":"Lincoln",
    "sg:classifiers":[
        {
            "category":"Bus Charters",
            "type":"Transportation"
        }
    ],
    "sg:postcode":"LN6 9NX",
    "sg:province":"Lincolnshire",
    "sg:tags":[
        "hire",
        "coach"
    ],
    "wof:name":"Carlton Coaches Ltd.",
    "wof:placetype":"venue"
},
  "geometry": {"coordinates":[-0.6019300222,53.1699104309],"type":"Point"}
}