{
  "type": "Feature",
  "properties": {
    "addr:full":"95 Royal Crescent Ruislip Greater London HA4 0PL",
    "addr:housenumber":"95",
    "addr:postcode":"ha4 0pl",
    "addr:street":"Royal Crescent",
    "iso:country":"GB",
    "sg:address":"95 Royal Crescent",
    "sg:city":"Ruislip",
    "sg:classifiers":[
        {
            "category":"Professional",
            "subcategory":"Employment Agencies",
            "type":"Services"
        }
    ],
    "sg:postcode":"HA4 0PL",
    "sg:province":"Greater London",
    "sg:tags":[
        "consultant",
        "recruitment"
    ],
    "wof:name":"M K Recruitment Services",
    "wof:placetype":"venue"
},
  "geometry": {"coordinates":[-0.3845379949,51.5621566772],"type":"Point"}
}