{
  "type": "Feature",
  "properties": {
    "addr:full":"Croft Lane, Cherry Willingham Lincoln Lincolnshire LN3 4JW",
    "addr:postcode":"ln3 4jw",
    "addr:street":"Croft Lane",
    "iso:country":"GB",
    "sg:address":"Croft Lane, Cherry Willingham",
    "sg:city":"Lincoln",
    "sg:classifiers":[
        {
            "category":"Health Services",
            "subcategory":"Nursing And Care Facility",
            "type":"Services"
        }
    ],
    "sg:phone":"+44 1522 595391",
    "sg:postcode":"LN3 4JW",
    "sg:province":"Lincolnshire",
    "sg:tags":[
        "home"
    ],
    "wof:name":"Willow Court Nursing Home",
    "wof:placetype":"venue"
},
  "geometry": {"coordinates":[-0.4572120011,53.2460861206],"type":"Point"}
}