{
  "type": "Feature",
  "properties": {
    "iso:country":"GB",
    "sg:address":"Waterside Park, Caton Rd",
    "sg:city":"Lancaster",
    "sg:classifiers":[
        {
            "category":"Travel",
            "subcategory":"Hotels & Motels",
            "type":"Entertainment"
        }
    ],
    "sg:phone":"+44 1524 65999",
    "sg:postcode":"LA1 3RA",
    "sg:province":"Lancashire",
    "wof:name":"Forte Posthouse",
    "wof:placetype":"venue"
},
  "geometry": {"coordinates":[-2.799029,54.044537],"type":"Point"}
}