{
  "type": "Feature",
  "properties": {
    "iso:country":"GB",
    "sg:address":"53 Moor St",
    "sg:city":"Ormskirk",
    "sg:classifiers":[
        {
            "category":"Home & Garden",
            "subcategory":"Home Furnishings",
            "type":"Retail Goods"
        }
    ],
    "sg:phone":"+44 1695 575680",
    "sg:postcode":"L39 2AG",
    "sg:province":"Lancashire",
    "sg:tags":[
        "beds",
        "bedding",
        "blanket"
    ],
    "wof:name":"Ormskirk Pram and Bed Centre",
    "wof:placetype":"venue"
},
  "geometry": {"coordinates":[-2.882336,53.566971],"type":"Point"}
}