{
  "type": "Feature",
  "properties": {
    "iso:country":"GB",
    "sg:address":"72 Stamford New Road",
    "sg:city":"Altrincham",
    "sg:classifiers":[
        {
            "category":"Personal",
            "subcategory":"Beauty Salon",
            "type":"Services"
        }
    ],
    "sg:phone":"+44 161 941 2944",
    "sg:postcode":"WA14 1BS",
    "sg:province":"Cheshire",
    "sg:tags":[
        "unisex",
        "hairdresser"
    ],
    "wof:name":"Toni & Guy",
    "wof:placetype":"venue"
},
  "geometry": {"coordinates":[-2.349879,53.386478],"type":"Point"}
}