{
  "type": "Feature",
  "properties": {
    "addr:full":"70 Waters Grn Macclesfield Cheshire SK11 6JZ",
    "addr:housenumber":"70",
    "addr:postcode":"sk11 6jz",
    "addr:street":"Waters Grn",
    "iso:country":"GB",
    "sg:address":"70 Waters Grn",
    "sg:city":"Macclesfield",
    "sg:classifiers":[
        {
            "category":"Bars & Pubs",
            "type":"Food & Drink"
        }
    ],
    "sg:postcode":"SK11 6JZ",
    "sg:province":"Cheshire",
    "sg:tags":[
        "pubs",
        "inn"
    ],
    "wof:name":"Bar 108",
    "wof:placetype":"venue"
},
  "geometry": {"coordinates":[-2.123704,53.259583],"type":"Point"}
}