{
  "type": "Feature",
  "properties": {
    "addr:full":"33 Lewis Street Stranraer Dumfries and Galloway DG9 7LB",
    "addr:housenumber":"33",
    "addr:postcode":"dg9 7lb",
    "addr:street":"Lewis Street",
    "iso:country":"GB",
    "sg:address":"33 Lewis Street",
    "sg:city":"Stranraer",
    "sg:classifiers":[
        {
            "category":"Professional",
            "subcategory":"Accounting & Tax Preparation",
            "type":"Services"
        }
    ],
    "sg:phone":"+44 1776 703539",
    "sg:postcode":"DG9 7LB",
    "sg:province":"Dumfries and Galloway",
    "sg:tags":[
        "accountant",
        "activity"
    ],
    "wof:name":"McIntyre Craig & Peacock",
    "wof:placetype":"venue"
},
  "geometry": {"coordinates":[-5.0267748833,54.9028396606],"type":"Point"}
}