{
  "type": "Feature",
  "properties": {
    "iso:country":"GB",
    "sg:address":"Unit 2, Northcote Ind Est, Doncaster Rd",
    "sg:city":"Knottingley",
    "sg:classifiers":[
        {
            "category":"Manufacturing",
            "subcategory":"Food",
            "type":"Manufacturing & Wholesale Goods"
        }
    ],
    "sg:phone":"+44 1977 679510",
    "sg:postcode":"WF11 8NW",
    "sg:province":"North Yorkshire",
    "sg:tags":[
        "mech",
        "processing"
    ],
    "wof:name":"M & D Food Machinery",
    "wof:placetype":"venue"
},
  "geometry": {"coordinates":[-1.259355,53.707607],"type":"Point"}
}