{
  "type": "Feature",
  "properties": {
    "addr:full":"31 High Street Camberley Berkshire GU15 3RB",
    "addr:housenumber":"31",
    "addr:postcode":"gu15 3rb",
    "addr:street":"High Street",
    "iso:country":"GB",
    "sg:address":"31 High Street",
    "sg:city":"Camberley",
    "sg:classifiers":[
        {
            "category":"Food & Beverages",
            "subcategory":"Bakery",
            "type":"Retail Goods"
        }
    ],
    "sg:phone":"+44 1276 676377",
    "sg:postcode":"GU15 3RB",
    "sg:province":"Berkshire",
    "sg:tags":[
        "baker"
    ],
    "wof:name":"Good Taste",
    "wof:placetype":"venue"
},
  "geometry": {"coordinates":[-0.7445030212,51.3386039734],"type":"Point"}
}