{
  "type": "Feature",
  "properties": {
    "addr:full":"Unit 4, Hillside Court Rotherham South Yorkshire S61 4RP",
    "addr:housenumber":"unit 4",
    "addr:postcode":"s61 4rp",
    "addr:street":"Hillside Court",
    "iso:country":"GB",
    "sg:address":"Unit 4, Hillside Court",
    "sg:city":"Rotherham",
    "sg:classifiers":[
        {
            "category":"Building & Trades",
            "subcategory":"Construction",
            "type":"Services"
        }
    ],
    "sg:postcode":"S61 4RP",
    "sg:province":"South Yorkshire",
    "sg:tags":[
        "ceiling",
        "contractor"
    ],
    "wof:name":"P C P Systems Ltd.",
    "wof:placetype":"venue"
},
  "geometry": {"coordinates":[-1.354676,53.44516],"type":"Point"}
}