{
  "type": "Feature",
  "properties": {
    "iso:country":"GB",
    "sg:address":"Unit 5 Abbey Sports Centre, Meadow Street",
    "sg:city":"Nuneaton",
    "sg:classifiers":[
        {
            "category":"Home & Garden",
            "subcategory":"Home Furnishings",
            "type":"Retail Goods"
        }
    ],
    "sg:phone":"+44 24 7664 2361",
    "sg:postcode":"CV11 5JF",
    "sg:province":"Leicestershire",
    "sg:tags":[
        "furnishers",
        "planner",
        "kitchen"
    ],
    "wof:name":"Thomas Kitchens Installations",
    "wof:placetype":"venue"
},
  "geometry": {"coordinates":[-1.46445,52.52137],"type":"Point"}
}