{
  "type": "Feature",
  "properties": {
    "addr:full":"37 Whitaker St Derby Derbyshire DE23 8FD",
    "addr:housenumber":"37",
    "addr:postcode":"de23 8fd",
    "addr:street":"Whitaker St",
    "iso:country":"GB",
    "sg:address":"37 Whitaker St",
    "sg:city":"Derby",
    "sg:classifiers":[
        {
            "category":"Bars & Pubs",
            "type":"Food & Drink"
        }
    ],
    "sg:phone":"+44 1332 200998",
    "sg:postcode":"DE23 8FD",
    "sg:province":"Derbyshire",
    "sg:tags":[
        "pubs",
        "inn"
    ],
    "wof:name":"Vine Inn",
    "wof:placetype":"venue"
},
  "geometry": {"coordinates":[-1.476861,52.908604],"type":"Point"}
}