{
  "type": "Feature",
  "properties": {
    "addr:full":"Europa Ho, Earin Av, Righead Industrial Park Bellshill North Lanarkshire ML4 3JU",
    "addr:postcode":"ml4 3ju",
    "addr:street":"Av Righead Industrial Park Bellshill",
    "iso:country":"GB",
    "sg:address":"Europa Ho, Earin Av, Righead Industrial Park",
    "sg:city":"Bellshill",
    "sg:classifiers":[
        {
            "category":"Professional",
            "subcategory":"Engineering",
            "type":"Services"
        }
    ],
    "sg:phone":"+44 1698 747470",
    "sg:postcode":"ML4 3JU",
    "sg:province":"North Lanarkshire",
    "sg:tags":[
        "consulting",
        "engineer"
    ],
    "wof:name":"Vector Design",
    "wof:placetype":"venue"
},
  "geometry": {"coordinates":[-4.0363497734,55.8259010315],"type":"Point"}
}