{
  "type": "Feature",
  "properties": {
    "addr:full":"David Rd Coventry West Midlands CV1 2BW",
    "addr:postcode":"cv1 2bw",
    "addr:street":"David Rd",
    "iso:country":"GB",
    "sg:address":"David Rd",
    "sg:city":"Coventry",
    "sg:classifiers":[
        {
            "category":"Manufacturing",
            "subcategory":"Metals",
            "type":"Manufacturing & Wholesale Goods"
        }
    ],
    "sg:phone":"+44 24 7625 1388",
    "sg:postcode":"CV1 2BW",
    "sg:province":"West Midlands",
    "wof:name":"Gulson Plating Ltd",
    "wof:placetype":"venue"
},
  "geometry": {"coordinates":[-1.4951139688,52.4048156738],"type":"Point"}
}