{
  "type": "Feature",
  "properties": {
    "addr:full":"Magistrates Court, 160 Albert Road Middlesbrough North Yorkshire TS1 2PZ",
    "addr:housenumber":"160",
    "addr:postcode":"ts1 2pz",
    "addr:street":"Albert Road",
    "iso:country":"GB",
    "sg:address":"Magistrates Court, 160 Albert Road",
    "sg:city":"Middlesbrough",
    "sg:classifiers":[
        {
            "category":"Government",
            "subcategory":"Police Station",
            "type":"Public Place"
        }
    ],
    "sg:phone":"+44 1642 247438",
    "sg:postcode":"TS1 2PZ",
    "sg:province":"North Yorkshire",
    "sg:tags":[
        "support"
    ],
    "wof:name":"Teesside Probation Service",
    "wof:placetype":"venue"
},
  "geometry": {"coordinates":[-1.235505,54.573269],"type":"Point"}
}