{
  "type": "Feature",
  "properties": {
    "iso:country":"GB",
    "sg:address":"12 Beacon Hill",
    "sg:city":"Maldon",
    "sg:classifiers":[
        {
            "category":"Professional",
            "subcategory":"Accounting & Tax Preparation",
            "type":"Services"
        }
    ],
    "sg:phone":"+44 1621 850976",
    "sg:postcode":"CM9 6HR",
    "sg:province":"Essex",
    "sg:tags":[
        "accountant",
        "activity"
    ],
    "wof:name":"C Pocknell",
    "wof:placetype":"venue"
},
  "geometry": {"coordinates":[0.6675440073,51.731300354],"type":"Point"}
}