{
  "type": "Feature",
  "properties": {
    "iso:country":"GB",
    "sg:address":"30 Currieside Avenue",
    "sg:city":"Shotts",
    "sg:classifiers":[
        {
            "category":"Building & Trades",
            "subcategory":"Landscaping Services",
            "type":"Services"
        }
    ],
    "sg:postcode":"ML7 4AJ",
    "sg:province":"North Lanarkshire",
    "sg:tags":[
        "landscape",
        "contractor"
    ],
    "wof:name":"T & H CONTRACTS",
    "wof:placetype":"venue"
},
  "geometry": {"coordinates":[-3.8078188896,55.8180389404],"type":"Point"}
}