{
  "type": "Feature",
  "properties": {
    "addr:full":"158 London Road Wallington Surrey SM6 7HF",
    "addr:housenumber":"158",
    "addr:postcode":"sm6 7hf",
    "addr:street":"London Road",
    "iso:country":"GB",
    "sg:address":"158 London Road",
    "sg:city":"Wallington",
    "sg:classifiers":[
        {
            "category":"Food & Beverages",
            "subcategory":"Liquor & Beverages",
            "type":"Retail Goods"
        }
    ],
    "sg:phone":"+44 20 8647 5686",
    "sg:postcode":"SM6 7HF",
    "sg:province":"Surrey",
    "sg:tags":[
        "beer",
        "spirit",
        "wines"
    ],
    "wof:name":"Ganimead Ltd.",
    "wof:placetype":"venue"
},
  "geometry": {"coordinates":[-0.1556839943,51.379825592],"type":"Point"}
}