{
  "type": "Feature",
  "properties": {
    "iso:country":"GB",
    "sg:address":"Beechwood, Broadway",
    "sg:city":"Derby",
    "sg:classifiers":[
        {
            "category":"Organizations",
            "subcategory":"Religious Organization",
            "type":"Services"
        }
    ],
    "sg:phone":"+44 1332 558043",
    "sg:postcode":"DE22 1AU",
    "sg:province":"Derbyshire",
    "sg:tags":[
        "organisation",
        "place",
        "worship"
    ],
    "wof:name":"Convent Of Mercy",
    "wof:placetype":"venue"
},
  "geometry": {"coordinates":[-1.4870380163,52.9389953613],"type":"Point"}
}