{
  "type": "Feature",
  "properties": {
    "iso:country":"GB",
    "sg:address":"101 Wortley Rd",
    "sg:city":"Sheffield",
    "sg:classifiers":[
        {
            "category":"Bars & Pubs",
            "type":"Food & Drink"
        }
    ],
    "sg:phone":"+44 114 284 8287",
    "sg:postcode":"S30 4LS",
    "sg:province":"Derbyshire",
    "sg:tags":[
        "pubs",
        "inn"
    ],
    "wof:name":"White Hart The",
    "wof:placetype":"venue"
},
  "geometry": {"coordinates":[-1.49225,53.474937],"type":"Point"}
}