{
  "type": "Feature",
  "properties": {
    "addr:full":"P O Box 2006 Bristol Gloucestershire BS35 1YF",
    "addr:housenumber":"p o;2006",
    "addr:postcode":"bs35 1yf",
    "iso:country":"GB",
    "sg:address":"P O Box 2006",
    "sg:city":"Bristol",
    "sg:classifiers":[
        {
            "category":"Government",
            "subcategory":"Post Office",
            "type":"Public Place"
        }
    ],
    "sg:phone":"+44 1454 415415",
    "sg:postcode":"BS35 1YF",
    "sg:province":"Gloucestershire",
    "sg:tags":[
        "messenger",
        "courier"
    ],
    "wof:name":"A M Deliveries",
    "wof:placetype":"venue"
},
  "geometry": {"coordinates":[-2.517209,51.61721],"type":"Point"}
}