{
  "type": "Feature",
  "properties": {
    "addr:full":"158 Blackstock Road, Finsbury Park London Greater London N5 1HA",
    "addr:housenumber":"158",
    "addr:postcode":"n5 1ha",
    "addr:street":"Blackstock Road",
    "iso:country":"GB",
    "sg:address":"158 Blackstock Road, Finsbury Park",
    "sg:city":"London",
    "sg:classifiers":[
        {
            "category":"Autos & Motor Vehicles",
            "subcategory":"Auto Supplies",
            "type":"Retail Goods"
        }
    ],
    "sg:phone":"+44 20 7226 6066",
    "sg:postcode":"N5 1HA",
    "sg:province":"Greater London",
    "sg:tags":[
        "car",
        "audio"
    ],
    "wof:name":"Jancrest Ltd.",
    "wof:placetype":"venue"
},
  "geometry": {"coordinates":[-0.0987600014,51.5598716736],"type":"Point"}
}