{
  "type": "Feature",
  "properties": {
    "addr:full":"66 Osborne Road Blackpool Lancashire FY4 1HQ",
    "addr:housenumber":"66",
    "addr:postcode":"fy4 1hq",
    "addr:street":"Osborne Road",
    "iso:country":"GB",
    "sg:address":"66 Osborne Road",
    "sg:city":"Blackpool",
    "sg:classifiers":[
        {
            "category":"Travel",
            "subcategory":"Hotels & Motels",
            "type":"Entertainment"
        }
    ],
    "sg:postcode":"FY4 1HQ",
    "sg:province":"Lancashire",
    "sg:tags":[
        "house",
        "guest"
    ],
    "wof:name":"Rosawyn Guest Ho",
    "wof:placetype":"venue"
},
  "geometry": {"coordinates":[-3.0508029461,53.7946929932],"type":"Point"}
}