{
  "type": "Feature",
  "properties": {
    "addr:full":"8 Derwent Cres Wrexham Wrexham LL12 7YN",
    "addr:housenumber":"8",
    "addr:postcode":"ll12 7yn",
    "addr:street":"Derwent Cres",
    "iso:country":"GB",
    "sg:address":"8 Derwent Cres",
    "sg:city":"Wrexham",
    "sg:classifiers":[
        {
            "category":"Building & Trades",
            "subcategory":"Construction",
            "type":"Services"
        }
    ],
    "sg:postcode":"LL12 7YN",
    "sg:province":"Wrexham",
    "sg:tags":[
        "joiner",
        "carpenter"
    ],
    "wof:name":"Rogers,Lee,",
    "wof:placetype":"venue"
},
  "geometry": {"coordinates":[-2.987329,53.057838],"type":"Point"}
}