{
  "type": "Feature",
  "properties": {
    "addr:full":"143 Lower Church Road Burgess Hill East Sussex RH15 9AA",
    "addr:housenumber":"143",
    "addr:postcode":"rh15 9aa",
    "addr:street":"Lower Church Road",
    "iso:country":"GB",
    "sg:address":"143 Lower Church Road",
    "sg:city":"Burgess Hill",
    "sg:classifiers":[
        {
            "category":"Recreation",
            "subcategory":"Fishing",
            "type":"Entertainment"
        }
    ],
    "sg:phone":"+44 1444 232287",
    "sg:postcode":"RH15 9AA",
    "sg:province":"East Sussex",
    "sg:tags":[
        "equipment",
        "angling"
    ],
    "wof:name":"Burgess Hill Angling Centre Ltd.",
    "wof:placetype":"venue"
},
  "geometry": {"coordinates":[-0.136502,50.957256],"type":"Point"}
}