{
  "type": "Feature",
  "properties": {
    "addr:full":"5 Virgil Street Liverpool Merseyside L5 5BY",
    "addr:housenumber":"5",
    "addr:postcode":"l5 5by",
    "addr:street":"Virgil Street",
    "iso:country":"GB",
    "sg:address":"5 Virgil Street",
    "sg:city":"Liverpool",
    "sg:classifiers":[
        {
            "category":"Recreation",
            "subcategory":"Go Karts",
            "type":"Entertainment"
        }
    ],
    "sg:postcode":"L5 5BY",
    "sg:province":"Merseyside",
    "sg:tags":[
        "karting"
    ],
    "wof:name":"Go-Karting (North West) Ltd",
    "wof:placetype":"venue"
},
  "geometry": {"coordinates":[-2.979114,53.41938],"type":"Point"}
}