{
  "type": "Feature",
  "properties": {
    "addr:full":"6 Garthlands Maidenhead Berkshire SL6 7PJ",
    "addr:housenumber":"6",
    "addr:postcode":"sl6 7pj",
    "addr:street":"Garthlands",
    "iso:country":"GB",
    "sg:address":"6 Garthlands",
    "sg:city":"Maidenhead",
    "sg:classifiers":[
        {
            "category":"Professional",
            "subcategory":"Advertising",
            "type":"Services"
        }
    ],
    "sg:phone":"+44 1628 623621",
    "sg:postcode":"SL6 7PJ",
    "sg:province":"Berkshire",
    "sg:tags":[
        "mail",
        "direct"
    ],
    "wof:name":"Winning Post",
    "wof:placetype":"venue"
},
  "geometry": {"coordinates":[-0.735577,51.537685],"type":"Point"}
}