{
  "type": "Feature",
  "properties": {
    "addr:full":"22 Oxford Rd Newbury Berkshire RG14 1PA",
    "addr:housenumber":"22",
    "addr:postcode":"rg14 1pa",
    "addr:street":"Oxford Rd",
    "iso:country":"GB",
    "sg:address":"22 Oxford Rd",
    "sg:city":"Newbury",
    "sg:classifiers":[
        {
            "category":"Professional",
            "subcategory":"Art Services",
            "type":"Services"
        }
    ],
    "sg:phone":"+44 1635 529991",
    "sg:postcode":"RG14 1PA",
    "sg:province":"Berkshire",
    "sg:tags":[
        "photographer"
    ],
    "wof:name":"Instore Images Ltd",
    "wof:placetype":"venue"
},
  "geometry": {"coordinates":[-1.3280320168,51.4070892334],"type":"Point"}
}