{
  "type": "Feature",
  "properties": {
    "addr:full":"232 Priory Road Liverpool Merseyside L4 2SL",
    "addr:housenumber":"232",
    "addr:postcode":"l4 2sl",
    "addr:street":"Priory Road",
    "iso:country":"GB",
    "sg:address":"232 Priory Road",
    "sg:city":"Liverpool",
    "sg:classifiers":[
        {
            "category":"Retail",
            "subcategory":"Car Wash",
            "type":"Services"
        },
        {
            "category":"Retail",
            "subcategory":"Auto Repair",
            "type":"Services"
        }
    ],
    "sg:phone":"+44 151 263 2814",
    "sg:postcode":"L4 2SL",
    "sg:province":"Merseyside",
    "sg:tags":[
        "modification",
        "garage",
        "polishing",
        "washing"
    ],
    "wof:name":"Priory Garage",
    "wof:placetype":"venue"
},
  "geometry": {"coordinates":[-2.955112,53.433319],"type":"Point"}
}