{
  "type": "Feature",
  "properties": {
    "iso:country":"GB",
    "sg:address":"33 Grange Road",
    "sg:city":"Darlington",
    "sg:classifiers":[
        {
            "category":"Manufacturing",
            "subcategory":"Apparel",
            "type":"Manufacturing & Wholesale Goods"
        }
    ],
    "sg:phone":"+44 1325 381123",
    "sg:postcode":"DL1 5NB",
    "sg:province":"Durham",
    "sg:tags":[
        "garment",
        "designer"
    ],
    "wof:name":"Oleo",
    "wof:placetype":"venue"
},
  "geometry": {"coordinates":[-1.5579799414,54.5228347778],"type":"Point"}
}