{
  "type": "Feature",
  "properties": {
    "addr:full":"2 Glencraig Street Airdrie North Lanarkshire ML6 9AR",
    "addr:housenumber":"2",
    "addr:postcode":"ml6 9ar",
    "addr:street":"Glencraig Street",
    "iso:country":"GB",
    "sg:address":"2 Glencraig Street",
    "sg:city":"Airdrie",
    "sg:classifiers":[
        {
            "category":"Food & Beverages",
            "subcategory":"Fruits & Vegetables",
            "type":"Retail Goods"
        }
    ],
    "sg:postcode":"ML6 9AR",
    "sg:province":"North Lanarkshire",
    "sg:tags":[
        "greengrocer"
    ],
    "wof:name":"Zefar's Licencesed Grocers",
    "wof:placetype":"venue"
},
  "geometry": {"coordinates":[-3.998664,55.862617],"type":"Point"}
}