{
  "type": "Feature",
  "properties": {
    "addr:full":"Farnell Mill Brechin Aberdeenshire DD9 6UH",
    "addr:postcode":"dd9 6uh",
    "addr:street":"Farnell Mill",
    "iso:country":"GB",
    "sg:address":"Farnell Mill",
    "sg:city":"Brechin",
    "sg:classifiers":[
        {
            "category":"Shopping",
            "subcategory":"Computers & Home Electronics",
            "type":"Retail Goods"
        }
    ],
    "sg:postcode":"DD9 6UH",
    "sg:province":"Aberdeenshire",
    "wof:name":"Cheyne,Malcolm,",
    "wof:placetype":"venue"
},
  "geometry": {"coordinates":[-2.6101539135,56.6900901794],"type":"Point"}
}