{
  "type": "Feature",
  "properties": {
    "addr:full":"Rink Way Swadlincote Derbyshire DE11 8JL",
    "addr:postcode":"de11 8jl",
    "addr:street":"Rink Way",
    "iso:country":"GB",
    "sg:address":"Rink Way",
    "sg:city":"Swadlincote",
    "sg:classifiers":[
        {
            "category":"Professional",
            "subcategory":"Employment Agencies",
            "type":"Services"
        }
    ],
    "sg:phone":"+44 1283 817900",
    "sg:postcode":"DE11 8JL",
    "sg:province":"Derbyshire",
    "sg:tags":[
        "career",
        "guidance"
    ],
    "wof:name":"Swadlincote Careers Centre",
    "wof:placetype":"venue"
},
  "geometry": {"coordinates":[-1.556699,52.773075],"type":"Point"}
}