{
  "type": "Feature",
  "properties": {
    "addr:full":"126 Cross Gates Rd Leeds West Yorkshire LS15 7NG",
    "addr:housenumber":"126",
    "addr:postcode":"ls15 7ng",
    "addr:street":"Cross Gates Rd",
    "iso:country":"GB",
    "sg:address":"126 Cross Gates Rd",
    "sg:city":"Leeds",
    "sg:classifiers":[
        {
            "category":"Manufacturing",
            "subcategory":"Wood Products",
            "type":"Manufacturing & Wholesale Goods"
        }
    ],
    "sg:phone":"+44 113 260 5544",
    "sg:postcode":"LS15 7NG",
    "sg:province":"West Yorkshire",
    "sg:tags":[
        "maker",
        "cabinet"
    ],
    "wof:name":"Wholesale Kitchens & Bathrooms",
    "wof:placetype":"venue"
},
  "geometry": {"coordinates":[-1.454243,53.808079],"type":"Point"}
}