{
  "type": "Feature",
  "properties": {
    "addr:full":"Unit 12, The Broadlands Canterbury Kent CT2 9JJ",
    "addr:housenumber":"unit 12",
    "addr:postcode":"ct2 9jj",
    "addr:street":"The Broadlands",
    "iso:country":"GB",
    "sg:address":"Unit 12, The Broadlands",
    "sg:city":"Canterbury",
    "sg:classifiers":[
        {
            "category":"Government",
            "subcategory":"Post Office",
            "type":"Public Place"
        }
    ],
    "sg:phone":"+44 1227 763376",
    "sg:postcode":"CT2 9JJ",
    "sg:province":"Kent",
    "sg:tags":[
        "messenger",
        "courier"
    ],
    "wof:name":"Canterbury Couriers Ltd.",
    "wof:placetype":"venue"
},
  "geometry": {"coordinates":[1.0404599905,51.3091316223],"type":"Point"}
}