{
  "type": "Feature",
  "properties": {
    "addr:full":"Trelissick, Sithney Helston Cornwall TR13 0RL",
    "addr:postcode":"tr13 0rl",
    "iso:country":"GB",
    "sg:address":"Trelissick, Sithney",
    "sg:city":"Helston",
    "sg:classifiers":[
        {
            "category":"Farming",
            "subcategory":"Livestock Farm",
            "type":"Manufacturing & Wholesale Goods"
        }
    ],
    "sg:postcode":"TR13 0RL",
    "sg:province":"Cornwall",
    "sg:tags":[
        "others"
    ],
    "wof:name":"G H A & M U Faull",
    "wof:placetype":"venue"
},
  "geometry": {"coordinates":[-5.307935,50.113613],"type":"Point"}
}