{
  "type": "Feature",
  "properties": {
    "iso:country":"GB",
    "sg:address":"West Bridge St",
    "sg:city":"Falkirk",
    "sg:classifiers":[
        {
            "category":"Government",
            "subcategory":"Police Station",
            "type":"Public Place"
        }
    ],
    "sg:phone":"+44 1324 634212",
    "sg:postcode":"FK1 5AP",
    "sg:province":"Falkirk",
    "sg:tags":[
        "support"
    ],
    "wof:name":"Police",
    "wof:placetype":"venue"
},
  "geometry": {"coordinates":[-3.790829,56.000515],"type":"Point"}
}