{
  "type": "Feature",
  "properties": {
    "addr:full":"184 Nobes Avenue Gosport Hampshire PO13 0HY",
    "addr:housenumber":"184",
    "addr:postcode":"po13 0hy",
    "addr:street":"Nobes Avenue",
    "iso:country":"GB",
    "sg:address":"184 Nobes Avenue",
    "sg:city":"Gosport",
    "sg:classifiers":[
        {
            "category":"Fast Food",
            "type":"Food & Drink"
        }
    ],
    "sg:phone":"+44 1329 280940",
    "sg:postcode":"PO13 0HY",
    "sg:province":"Hampshire",
    "sg:tags":[
        "away",
        "meal",
        "outlet",
        "take"
    ],
    "wof:name":"The Chinese Food Centre",
    "wof:placetype":"venue"
},
  "geometry": {"coordinates":[-1.1758259535,50.8269500732],"type":"Point"}
}