{
  "type": "Feature",
  "properties": {
    "iso:country":"GB",
    "sg:address":"Marsh Lane, Holmes Chapel",
    "sg:city":"Crewe",
    "sg:classifiers":[
        {
            "category":"Shopping",
            "subcategory":"Party Supplies",
            "type":"Retail Goods"
        },
        {
            "category":"Professional",
            "subcategory":"Advertising",
            "type":"Services"
        }
    ],
    "sg:phone":"+44 1477 534913",
    "sg:postcode":"CW4 8QB",
    "sg:province":"Cheshire",
    "sg:tags":[
        "marquees",
        "hire",
        "marquee",
        "tent",
        "floor"
    ],
    "wof:name":"R P Marquee Hire",
    "wof:placetype":"venue"
},
  "geometry": {"coordinates":[-2.3452959061,53.1967544556],"type":"Point"}
}