{
  "type": "Feature",
  "properties": {
    "iso:country":"GB",
    "sg:address":"New Rd",
    "sg:city":"Wrexham",
    "sg:classifiers":[
        {
            "category":"Government",
            "subcategory":"Post Office",
            "type":"Public Place"
        }
    ],
    "sg:phone":"+44 1978 755801",
    "sg:postcode":"LL11 6SY",
    "sg:province":"Wrexham",
    "wof:name":"New Broughton Post Office",
    "wof:placetype":"venue"
},
  "geometry": {"coordinates":[-3.046827,53.073963],"type":"Point"}
}