{
  "type": "Feature",
  "properties": {
    "iso:country":"GB",
    "sg:address":"Retail, 163 Sutton Rd",
    "sg:city":"Birmingham",
    "sg:classifiers":[
        {
            "category":"Travel",
            "subcategory":"Travel Agent",
            "type":"Entertainment"
        }
    ],
    "sg:phone":"+44 121 382 5115",
    "sg:postcode":"B23 5TN",
    "sg:province":"West Midlands",
    "wof:name":"Cyprosun Travel Ltd",
    "wof:placetype":"venue"
},
  "geometry": {"coordinates":[-1.827739954,52.5345306396],"type":"Point"}
}