{
  "type": "Feature",
  "properties": {
    "addr:full":"37-39 Harboro Road Sale Cheshire M33 5AN",
    "addr:housenumber":"37-39",
    "addr:postcode":"m33 5an",
    "addr:street":"Harboro Road",
    "iso:country":"GB",
    "sg:address":"37-39 Harboro Road",
    "sg:city":"Sale",
    "sg:classifiers":[
        {
            "category":"Social Services",
            "subcategory":"Retirement Home",
            "type":"Services"
        }
    ],
    "sg:postcode":"M33 5AN",
    "sg:province":"Cheshire",
    "sg:tags":[
        "residential",
        "care"
    ],
    "wof:name":"Summerfield Residential Home",
    "wof:placetype":"venue"
},
  "geometry": {"coordinates":[-2.3388969898,53.4225769043],"type":"Point"}
}