{
  "type": "Feature",
  "properties": {
    "addr:full":"18 Terry Close Lichfield Staffordshire WS13 7EJ",
    "addr:housenumber":"18",
    "addr:postcode":"ws13 7ej",
    "addr:street":"Terry Close",
    "iso:country":"GB",
    "sg:address":"18 Terry Close",
    "sg:city":"Lichfield",
    "sg:classifiers":[
        {
            "category":"Building & Trades",
            "subcategory":"Construction",
            "type":"Services"
        }
    ],
    "sg:postcode":"WS13 7EJ",
    "sg:province":"Staffordshire",
    "sg:tags":[
        "roofing"
    ],
    "wof:name":"Elite Roofing",
    "wof:placetype":"venue"
},
  "geometry": {"coordinates":[-1.8456499577,52.6934242249],"type":"Point"}
}