{
  "type": "Feature",
  "properties": {
    "addr:full":"Garrad Way Swindon Wiltshire SN3 3HY",
    "addr:postcode":"sn3 3hy",
    "addr:street":"Garrad Way",
    "iso:country":"GB",
    "sg:address":"Garrad Way",
    "sg:city":"Swindon",
    "sg:classifiers":[
        {
            "category":"Home & Garden",
            "subcategory":"Hardware",
            "type":"Retail Goods"
        }
    ],
    "sg:phone":"+44 1793 693361",
    "sg:postcode":"SN3 3HY",
    "sg:province":"Wiltshire",
    "sg:tags":[
        "product",
        "wire",
        "electrical"
    ],
    "wof:name":"Kembrey Ltd.",
    "wof:placetype":"venue"
},
  "geometry": {"coordinates":[-1.7574759722,51.5702476501],"type":"Point"}
}