{
  "type": "Feature",
  "properties": {
    "addr:full":"8 Twydall Grn Gillingham Kent ME8 6JY",
    "addr:housenumber":"8",
    "addr:postcode":"me8 6jy",
    "addr:street":"Twydall Grn",
    "iso:country":"GB",
    "sg:address":"8 Twydall Grn",
    "sg:city":"Gillingham",
    "sg:classifiers":[
        {
            "category":"Education",
            "subcategory":"Library",
            "type":"Public Place"
        }
    ],
    "sg:phone":"+44 1634 232488",
    "sg:postcode":"ME8 6JY",
    "sg:province":"Kent",
    "sg:tags":[
        "book"
    ],
    "wof:name":"Twydall Library",
    "wof:placetype":"venue"
},
  "geometry": {"coordinates":[0.583071,51.374699],"type":"Point"}
}