{
  "type": "Feature",
  "properties": {
    "iso:country":"GB",
    "sg:address":"20 South Street",
    "sg:city":"Havant",
    "sg:classifiers":[
        {
            "category":"Professional",
            "subcategory":"Advertising",
            "type":"Services"
        }
    ],
    "sg:phone":"+44 23 9248 6566",
    "sg:postcode":"PO9 1DA",
    "sg:province":"Hampshire",
    "sg:tags":[
        "agency"
    ],
    "wof:name":"Havant Hallplace Ltd",
    "wof:placetype":"venue"
},
  "geometry": {"coordinates":[-0.982126,50.849155],"type":"Point"}
}