{
  "type": "Feature",
  "properties": {
    "iso:country":"GB",
    "sg:address":"102 Queen Street",
    "sg:city":"Newton Stewart",
    "sg:classifiers":[
        {
            "category":"Travel",
            "subcategory":"Hotels & Motels",
            "type":"Entertainment"
        }
    ],
    "sg:phone":"+44 1671 402727",
    "sg:postcode":"DG8 6JW",
    "sg:province":"Dumfries and Galloway",
    "wof:name":"The Crown Hotel",
    "wof:placetype":"venue"
},
  "geometry": {"coordinates":[-4.482288,54.953999],"type":"Point"}
}