{
  "type": "Feature",
  "properties": {
    "addr:full":"75 Colliers, Water Lane, Thornehay London Greater London SW16 4BB",
    "addr:housenumber":"75",
    "addr:postcode":"sw16 4bb",
    "addr:street":"Colliers Water Lane",
    "iso:country":"GB",
    "sg:address":"75 Colliers, Water Lane, Thornehay",
    "sg:city":"London",
    "sg:classifiers":[
        {
            "category":"Professional",
            "subcategory":"Engineering",
            "type":"Services"
        }
    ],
    "sg:phone":"+44 20 8689 7828",
    "sg:postcode":"SW16 4BB",
    "sg:province":"Greater London",
    "sg:tags":[
        "contractor",
        "electrical",
        "engineer"
    ],
    "wof:name":"P & D Electrical",
    "wof:placetype":"venue"
},
  "geometry": {"coordinates":[-0.12943,51.4058],"type":"Point"}
}