{
  "type": "Feature",
  "properties": {
    "addr:full":"17-23 West Wylam Drive Prudhoe Northumberland NE42 5ES",
    "addr:housenumber":"17-23",
    "addr:postcode":"ne42 5es",
    "addr:street":"West Wylam Drive",
    "iso:country":"GB",
    "sg:address":"17-23 West Wylam Drive",
    "sg:city":"Prudhoe",
    "sg:classifiers":[
        {
            "category":"Shopping",
            "subcategory":"News",
            "type":"Retail Goods"
        }
    ],
    "sg:phone":"+44 1661 836497",
    "sg:postcode":"NE42 5ES",
    "sg:province":"Northumberland",
    "sg:tags":[
        "newsagent"
    ],
    "wof:name":"JOHN BRIAN JONES NEWSAGENTS",
    "wof:placetype":"venue"
},
  "geometry": {"coordinates":[-1.83813,54.962009],"type":"Point"}
}