{
  "type": "Feature",
  "properties": {
    "iso:country":"GB",
    "sg:address":"103a-104 High Street",
    "sg:city":"Burton-on-trent",
    "sg:classifiers":[
        {
            "category":"Personal",
            "subcategory":"Beauty Salon",
            "type":"Services"
        }
    ],
    "sg:phone":"+44 1283 510841",
    "sg:postcode":"DE14 1LJ",
    "sg:province":"Derbyshire",
    "sg:tags":[
        "unisex",
        "hairdresser"
    ],
    "wof:name":"Ego",
    "wof:placetype":"venue"
},
  "geometry": {"coordinates":[-1.626418,52.80687],"type":"Point"}
}