{
  "type": "Feature",
  "properties": {
    "addr:full":"3 Teak Close Nottingham Nottinghamshire NG3 4PP",
    "addr:housenumber":"3",
    "addr:postcode":"ng3 4pp",
    "addr:street":"Teak Close",
    "iso:country":"GB",
    "sg:address":"3 Teak Close",
    "sg:city":"Nottingham",
    "sg:classifiers":[
        {
            "category":"Home & Garden",
            "subcategory":"Home Furnishings",
            "type":"Retail Goods"
        },
        {
            "category":"Home & Garden",
            "subcategory":"Carpets & Floor Coverings",
            "type":"Retail Goods"
        }
    ],
    "sg:postcode":"NG3 4PP",
    "sg:province":"Nottinghamshire",
    "sg:tags":[
        "fitting",
        "rug",
        "matting",
        "carpets"
    ],
    "wof:name":"John Edward Bird",
    "wof:placetype":"venue"
},
  "geometry": {"coordinates":[-1.1410349607,52.9647331238],"type":"Point"}
}