{
  "type": "Feature",
  "properties": {
    "iso:country":"GB",
    "sg:address":"12-24 Belle Vue Way",
    "sg:city":"Swansea",
    "sg:classifiers":[
        {
            "category":"Shopping",
            "subcategory":"Department Store",
            "type":"Retail Goods"
        }
    ],
    "sg:phone":"+44 1792 651411",
    "sg:postcode":"SA1 5DA",
    "sg:province":"Neath Port Talbot",
    "wof:name":"J T Morgan & Co. (Swansea) Ltd.",
    "wof:placetype":"venue"
},
  "geometry": {"coordinates":[-3.9441490173,51.621761322],"type":"Point"}
}