{
  "type": "Feature",
  "properties": {
    "addr:full":"184 Cropston Rd Leicester Leicestershire LE7 7BN",
    "addr:housenumber":"184",
    "addr:postcode":"le7 7bn",
    "addr:street":"Cropston Rd",
    "iso:country":"GB",
    "sg:address":"184 Cropston Rd",
    "sg:city":"Leicester",
    "sg:classifiers":[
        {
            "category":"Manufacturing",
            "subcategory":"Textiles",
            "type":"Manufacturing & Wholesale Goods"
        }
    ],
    "sg:phone":"+44 116 236 3301",
    "sg:postcode":"LE7 7BN",
    "sg:province":"Leicestershire",
    "sg:tags":[
        "knitwear"
    ],
    "wof:name":"Spinaway Yarns",
    "wof:placetype":"venue"
},
  "geometry": {"coordinates":[-1.179713,52.678871],"type":"Point"}
}