{
  "type": "Feature",
  "properties": {
    "iso:country":"GB",
    "sg:address":"180 West Regent Street",
    "sg:city":"Glasgow",
    "sg:classifiers":[
        {
            "category":"Communications",
            "subcategory":"Newspaper",
            "type":"Services"
        }
    ],
    "sg:phone":"+44 141 566 9130",
    "sg:postcode":"G2 4RW",
    "sg:province":"Glasgow City",
    "sg:tags":[
        "magazine"
    ],
    "wof:name":"Tron Enterprise",
    "wof:placetype":"venue"
},
  "geometry": {"coordinates":[-4.261743,55.863865],"type":"Point"}
}