{
  "type": "Feature",
  "properties": {
    "iso:country":"GB",
    "sg:address":"92a Coombe Lane",
    "sg:city":"Bristol",
    "sg:classifiers":[
        {
            "category":"Professional",
            "subcategory":"Management & Consulting",
            "type":"Services"
        }
    ],
    "sg:postcode":"BS9 2AP",
    "sg:province":"City of Bristol",
    "sg:tags":[
        "consultant",
        "energy",
        "conservation"
    ],
    "wof:name":"Essential Energy Ltd.",
    "wof:placetype":"venue"
},
  "geometry": {"coordinates":[-2.6370050907,51.4915084839],"type":"Point"}
}