{
  "type": "Feature",
  "properties": {
    "addr:full":"Queen Marys Hospital, Roehampton Lane London Greater London SW15 5NU",
    "addr:postcode":"sw15 5nu",
    "addr:street":"Roehampton Lane",
    "iso:country":"GB",
    "sg:address":"Queen Marys Hospital, Roehampton Lane",
    "sg:city":"London",
    "sg:classifiers":[
        {
            "category":"Organizations",
            "subcategory":"Non-profit Organization",
            "type":"Services"
        }
    ],
    "sg:phone":"+44 20 8789 4536",
    "sg:postcode":"SW15 5NU",
    "sg:province":"Greater London",
    "sg:tags":[
        "organisation",
        "voluntary",
        "charity"
    ],
    "wof:name":"League of Friends",
    "wof:placetype":"venue"
},
  "geometry": {"coordinates":[-0.243099,51.455521],"type":"Point"}
}