{
  "type": "Feature",
  "properties": {
    "addr:full":"Red House Lodge, South Green Eye Suffolk IP23 7NW",
    "addr:postcode":"ip23 7nw",
    "addr:street":"Green",
    "iso:country":"GB",
    "sg:address":"Red House Lodge, South Green",
    "sg:city":"Eye",
    "sg:classifiers":[
        {
            "category":"Farming",
            "subcategory":"Farm",
            "type":"Manufacturing & Wholesale Goods"
        }
    ],
    "sg:postcode":"IP23 7NW",
    "sg:province":"Suffolk",
    "sg:tags":[
        "mixed",
        "crop"
    ],
    "wof:name":"R G Ford (Farms) Ltd.",
    "wof:placetype":"venue"
},
  "geometry": {"coordinates":[1.145876,52.322071],"type":"Point"}
}