{
  "type": "Feature",
  "properties": {
    "addr:full":"2 The Courtyard, Chalvington Hailsham East Sussex BN27 3TD",
    "addr:housenumber":"2",
    "addr:postcode":"bn27 3td",
    "addr:street":"The Courtyard",
    "iso:country":"GB",
    "sg:address":"2 The Courtyard, Chalvington",
    "sg:city":"Hailsham",
    "sg:classifiers":[
        {
            "category":"Real Estate",
            "subcategory":"Developer",
            "type":"Services"
        }
    ],
    "sg:phone":"+44 1323 811701",
    "sg:postcode":"BN27 3TD",
    "sg:province":"East Sussex",
    "sg:tags":[
        "property"
    ],
    "wof:name":"G W Homes",
    "wof:placetype":"venue"
},
  "geometry": {"coordinates":[0.1597740054,50.8641319275],"type":"Point"}
}