{
  "type": "Feature",
  "properties": {
    "addr:full":"New Court, Tregoyd Brecon Powys LD3 0SS",
    "addr:postcode":"ld3 0ss",
    "iso:country":"GB",
    "sg:address":"New Court, Tregoyd",
    "sg:city":"Brecon",
    "sg:classifiers":[
        {
            "category":"Farming",
            "subcategory":"Farm",
            "type":"Manufacturing & Wholesale Goods"
        },
        {
            "category":"Recreation",
            "subcategory":"Campground",
            "type":"Entertainment"
        }
    ],
    "sg:phone":"+44 1497 847285",
    "sg:postcode":"LD3 0SS",
    "sg:province":"Powys",
    "sg:tags":[
        "operator",
        "mixed",
        "site",
        "crop",
        "camping"
    ],
    "wof:name":"Mills Bros",
    "wof:placetype":"venue"
},
  "geometry": {"coordinates":[-3.2328140736,51.9971542358],"type":"Point"}
}