{
  "type": "Feature",
  "properties": {
    "addr:full":"33 Regent St Runcorn Cheshire WA7 1LJ",
    "addr:housenumber":"33",
    "addr:postcode":"wa7 1lj",
    "addr:street":"Regent St",
    "iso:country":"GB",
    "sg:address":"33 Regent St",
    "sg:city":"Runcorn",
    "sg:classifiers":[
        {
            "category":"Shopping",
            "subcategory":"Pharmacy",
            "type":"Retail Goods"
        }
    ],
    "sg:phone":"+44 1928 564444",
    "sg:postcode":"WA7 1LJ",
    "sg:province":"Cheshire",
    "sg:tags":[
        "medicine",
        "therapy"
    ],
    "wof:name":"Body Balance Therapies",
    "wof:placetype":"venue"
},
  "geometry": {"coordinates":[-2.7355771065,53.3417510986],"type":"Point"}
}