{
  "type": "Feature",
  "properties": {
    "iso:country":"GB",
    "sg:address":"Central Evangelical Church, John Finnie St",
    "sg:city":"Kilmarnock",
    "sg:classifiers":[
        {
            "category":"Place Of Worship",
            "type":"Public Place"
        }
    ],
    "sg:phone":"+44 1563 530303",
    "sg:postcode":"KA1 1BL",
    "sg:province":"East Ayrshire",
    "wof:name":"Dial A Bible Message Service",
    "wof:placetype":"venue"
},
  "geometry": {"coordinates":[-4.4994702339,55.6096115112],"type":"Point"}
}