{
  "type": "Feature",
  "properties": {
    "addr:full":"Bay Hill Ilminster Somerset TA19 0AT",
    "addr:postcode":"ta19 0at",
    "addr:street":"Bay Hill",
    "iso:country":"GB",
    "sg:address":"Bay Hill",
    "sg:city":"Ilminster",
    "sg:classifiers":[
        {
            "category":"Bars & Pubs",
            "type":"Food & Drink"
        }
    ],
    "sg:phone":"+44 1460 54616",
    "sg:postcode":"TA19 0AT",
    "sg:province":"Somerset",
    "sg:tags":[
        "pubs",
        "inn"
    ],
    "wof:name":"The White Horse",
    "wof:placetype":"venue"
},
  "geometry": {"coordinates":[-2.90152,50.927013],"type":"Point"}
}