{
  "type": "Feature",
  "properties": {
    "addr:full":"Gorse Lodge, Upper Ruckinge Ashford Kent TN26 2PN",
    "addr:postcode":"tn26 2pn",
    "addr:street":"Upper",
    "iso:country":"GB",
    "sg:address":"Gorse Lodge, Upper Ruckinge",
    "sg:city":"Ashford",
    "sg:classifiers":[
        {
            "category":"Professional",
            "subcategory":"Engineering",
            "type":"Services"
        }
    ],
    "sg:phone":"+44 1233 732112",
    "sg:postcode":"TN26 2PN",
    "sg:province":"Kent",
    "sg:tags":[
        "agricultural",
        "engineer"
    ],
    "wof:name":"Hardings Bridge Engineering",
    "wof:placetype":"venue"
},
  "geometry": {"coordinates":[0.8895900249,51.0661697388],"type":"Point"}
}