{
  "type": "Feature",
  "properties": {
    "iso:country":"GB",
    "sg:address":"35 Wordsworth Road",
    "sg:city":"Loughborough",
    "sg:classifiers":[
        {
            "category":"Shopping",
            "subcategory":"Florist",
            "type":"Retail Goods"
        }
    ],
    "sg:postcode":"LE11 4LQ",
    "sg:province":"Leicestershire",
    "wof:name":"Sylvies Flowers",
    "wof:placetype":"venue"
},
  "geometry": {"coordinates":[-1.235028,52.773708],"type":"Point"}
}