{
  "type": "Feature",
  "properties": {
    "addr:full":"12 School Road, Tettneham Wood Wolverhampton Shropshire WV6 8EJ",
    "addr:housenumber":"12",
    "addr:postcode":"wv6 8ej",
    "addr:street":"School Road Tettneham Wood",
    "iso:country":"GB",
    "sg:address":"12 School Road, Tettneham Wood",
    "sg:city":"Wolverhampton",
    "sg:classifiers":[
        {
            "category":"Shopping",
            "subcategory":"Pharmacy",
            "type":"Retail Goods"
        }
    ],
    "sg:phone":"+44 1902 747647",
    "sg:postcode":"WV6 8EJ",
    "sg:province":"Shropshire",
    "sg:tags":[
        "pharmacist",
        "chemist"
    ],
    "wof:name":"Tettenhall Wood Ltd.",
    "wof:placetype":"venue"
},
  "geometry": {"coordinates":[-2.182388,52.590805],"type":"Point"}
}