{
  "type": "Feature",
  "properties": {
    "addr:full":"Unit 12-13 Atlas Court Coalville Leicestershire LE67 3FL",
    "addr:housenumber":"unit 12-13",
    "addr:postcode":"le67 3fl",
    "addr:street":"Atlas Court",
    "iso:country":"GB",
    "sg:address":"Unit 12-13 Atlas Court",
    "sg:city":"Coalville",
    "sg:classifiers":[
        {
            "category":"Wholesale",
            "subcategory":"Electrical",
            "type":"Manufacturing & Wholesale Goods"
        },
        {
            "category":"Shopping",
            "subcategory":"Computers & Home Electronics",
            "type":"Retail Goods"
        }
    ],
    "sg:phone":"+44 1530 839957",
    "sg:postcode":"LE67 3FL",
    "sg:province":"Leicestershire",
    "sg:tags":[
        "wholesaler"
    ],
    "wof:name":"Lockwell Lectrics Ltd",
    "wof:placetype":"venue"
},
  "geometry": {"coordinates":[-1.3691040277,52.7295799255],"type":"Point"}
}