{
  "type": "Feature",
  "properties": {
    "addr:full":"Wentloog Road, Rumney Cardiff Caerphilly CF3 3EB",
    "addr:postcode":"cf3 3eb",
    "addr:street":"Wentloog Road",
    "iso:country":"GB",
    "sg:address":"Wentloog Road, Rumney",
    "sg:city":"Cardiff",
    "sg:classifiers":[
        {
            "category":"Professional",
            "subcategory":"Business Services",
            "type":"Services"
        }
    ],
    "sg:postcode":"CF3 3EB",
    "sg:province":"Caerphilly",
    "sg:tags":[
        "bookmaker"
    ],
    "wof:name":"Chris Bullock Racing",
    "wof:placetype":"venue"
},
  "geometry": {"coordinates":[-3.1240649223,51.5094871521],"type":"Point"}
}