{
  "type": "Feature",
  "properties": {
    "addr:full":"Clease Hall Clease Rd Camelford Cornwall PL32 9QX",
    "addr:postcode":"pl32 9qx",
    "addr:street":"Clease Rd",
    "iso:country":"GB",
    "sg:address":"Clease Hall Clease Rd",
    "sg:city":"Camelford",
    "sg:classifiers":[
        {
            "category":"Home & Garden",
            "subcategory":"Furniture",
            "type":"Retail Goods"
        }
    ],
    "sg:phone":"+44 1840 212184",
    "sg:postcode":"PL32 9QX",
    "sg:province":"Cornwall",
    "wof:name":"Bliss Furniture",
    "wof:placetype":"venue"
},
  "geometry": {"coordinates":[-4.678636,50.623116],"type":"Point"}
}