{
  "type": "Feature",
  "properties": {
    "addr:full":"25 Windsor Terrace, Grangetown Sunderland Tyne and Wear SR1 1BA",
    "addr:housenumber":"25",
    "addr:postcode":"sr1 1ba",
    "addr:street":"Windsor Terrace",
    "iso:country":"GB",
    "sg:address":"25 Windsor Terrace, Grangetown",
    "sg:city":"Sunderland",
    "sg:classifiers":[
        {
            "category":"Shopping",
            "subcategory":"Pharmacy",
            "type":"Retail Goods"
        }
    ],
    "sg:phone":"+44 191 518 4559",
    "sg:postcode":"SR1 1BA",
    "sg:province":"Tyne and Wear",
    "sg:tags":[
        "pharmacist",
        "chemist"
    ],
    "wof:name":"C V Marshall Ltd.",
    "wof:placetype":"venue"
},
  "geometry": {"coordinates":[-1.38629,54.90229],"type":"Point"}
}