{
  "type": "Feature",
  "properties": {
    "iso:country":"GB",
    "sg:address":"2 Grange Road",
    "sg:city":"Weymouth",
    "sg:classifiers":[
        {
            "category":"Shopping",
            "subcategory":"Computers & Home Electronics",
            "type":"Retail Goods"
        },
        {
            "category":"Building & Trades",
            "subcategory":"Construction",
            "type":"Services"
        }
    ],
    "sg:postcode":"DT4 7PH",
    "sg:province":"Dorset",
    "sg:tags":[
        "joiner",
        "carpenter"
    ],
    "wof:name":"Heartwood Furniture",
    "wof:placetype":"venue"
},
  "geometry": {"coordinates":[-2.451956,50.618858],"type":"Point"}
}