{
  "type": "Feature",
  "properties": {
    "addr:full":"4 Southern Avenue Leominster Herefordshire HR6 0QF",
    "addr:housenumber":"4",
    "addr:postcode":"hr6 0qf",
    "addr:street":"Southern Avenue",
    "iso:country":"GB",
    "sg:address":"4 Southern Avenue",
    "sg:city":"Leominster",
    "sg:classifiers":[
        {
            "category":"Home & Garden",
            "subcategory":"Garden Supply",
            "type":"Retail Goods"
        }
    ],
    "sg:phone":"+44 1568 611281",
    "sg:postcode":"HR6 0QF",
    "sg:province":"Herefordshire",
    "sg:tags":[
        "nursery",
        "centre"
    ],
    "wof:name":"Queenswood Ltd.",
    "wof:placetype":"venue"
},
  "geometry": {"coordinates":[-2.733587,52.218208],"type":"Point"}
}