{
  "type": "Feature",
  "properties": {
    "iso:country":"GB",
    "sg:address":"Woodlands, Gowerton",
    "sg:city":"Swansea",
    "sg:classifiers":[
        {
            "category":"Shopping",
            "subcategory":"Antiques",
            "type":"Retail Goods"
        },
        {
            "category":"Social Services",
            "subcategory":"Retirement Home",
            "type":"Services"
        }
    ],
    "sg:postcode":"SA4 3DP",
    "sg:province":"Carmarthenshire",
    "sg:tags":[
        "residential",
        "care"
    ],
    "wof:name":"Woodlands Residential Home for the Elderly",
    "wof:placetype":"venue"
},
  "geometry": {"coordinates":[-4.04233,51.648598],"type":"Point"}
}