{
  "type": "Feature",
  "properties": {
    "iso:country":"GB",
    "sg:address":"55 Crosby Road North",
    "sg:city":"Liverpool",
    "sg:classifiers":[
        {
            "category":"Shopping",
            "subcategory":"Optician",
            "type":"Retail Goods"
        }
    ],
    "sg:phone":"+44 151 928 5982",
    "sg:postcode":"L22 4QD",
    "sg:province":"Merseyside",
    "sg:tags":[
        "dispensing"
    ],
    "wof:name":"Jonathan Kay Opticians",
    "wof:placetype":"venue"
},
  "geometry": {"coordinates":[-3.023726,53.480026],"type":"Point"}
}