{
  "type": "Feature",
  "properties": {
    "iso:country":"GB",
    "sg:address":"The Manor Ho, Gaulby Rd",
    "sg:city":"Leicester",
    "sg:classifiers":[
        {
            "category":"Health Services",
            "subcategory":"Health Practitioner",
            "type":"Services"
        }
    ],
    "sg:phone":"+44 116 259 6633",
    "sg:postcode":"LE7 9BA",
    "sg:province":"Leicestershire",
    "sg:tags":[
        "homoeopathic"
    ],
    "wof:name":"Jo Pickering",
    "wof:placetype":"venue"
},
  "geometry": {"coordinates":[-0.975973,52.602985],"type":"Point"}
}