{
  "type": "Feature",
  "properties": {
    "addr:full":"31 Ladybank Road, Mickleover Derby Derbyshire DE3 0RX",
    "addr:housenumber":"31",
    "addr:postcode":"de3 0rx",
    "addr:street":"Ladybank Road",
    "iso:country":"GB",
    "sg:address":"31 Ladybank Road, Mickleover",
    "sg:city":"Derby",
    "sg:classifiers":[
        {
            "category":"Professional",
            "subcategory":"Computer Services",
            "type":"Services"
        }
    ],
    "sg:postcode":"DE3 0RX",
    "sg:province":"Derbyshire",
    "sg:tags":[
        "system",
        "software"
    ],
    "wof:name":"Corrigan Systems Ltd.",
    "wof:placetype":"venue"
},
  "geometry": {"coordinates":[-1.545429945,52.9136047363],"type":"Point"}
}