{
  "type": "Feature",
  "properties": {
    "addr:full":"Unit 13 Trinity Centre, Sinclair Drive Wellingborough Northamptonshire NN8 6ZB",
    "addr:housenumber":"unit 13;centre",
    "addr:postcode":"nn8 6zb",
    "addr:street":"Trinity;Sinclair Drive",
    "iso:country":"GB",
    "sg:address":"Unit 13 Trinity Centre, Sinclair Drive",
    "sg:city":"Wellingborough",
    "sg:classifiers":[
        {
            "category":"Wholesale",
            "subcategory":"Chemicals & Plastics",
            "type":"Manufacturing & Wholesale Goods"
        }
    ],
    "sg:phone":"+44 1933 402257",
    "sg:postcode":"NN8 6ZB",
    "sg:province":"Northamptonshire",
    "sg:tags":[
        "ind"
    ],
    "wof:name":"Rotospeed Ltd.",
    "wof:placetype":"venue"
},
  "geometry": {"coordinates":[-0.696296,52.302422],"type":"Point"}
}