{
  "type": "Feature",
  "properties": {
    "iso:country":"GB",
    "sg:address":"45 East St",
    "sg:city":"Liverpool",
    "sg:classifiers":[
        {
            "category":"Bars & Pubs",
            "type":"Food & Drink"
        }
    ],
    "sg:phone":"+44 151 928 6594",
    "sg:postcode":"L22 8QR",
    "sg:province":"Merseyside",
    "sg:tags":[
        "pubs",
        "inn"
    ],
    "wof:name":"Volunteer Canteen",
    "wof:placetype":"venue"
},
  "geometry": {"coordinates":[-3.031621,53.475105],"type":"Point"}
}