{
  "type": "Feature",
  "properties": {
    "addr:full":"British Philatelic Centre, 107 Charterhouse Street London Greater London EC1M 6PT",
    "addr:housenumber":"107",
    "addr:postcode":"ec1m 6pt",
    "addr:street":"Charterhouse Street",
    "iso:country":"GB",
    "sg:address":"British Philatelic Centre, 107 Charterhouse Street",
    "sg:city":"London",
    "sg:classifiers":[
        {
            "category":"Organizations",
            "subcategory":"Membership Organization",
            "type":"Services"
        }
    ],
    "sg:phone":"+44 20 7490 3112",
    "sg:postcode":"EC1M 6PT",
    "sg:province":"Greater London",
    "sg:tags":[
        "club"
    ],
    "wof:name":"The British Philatelic Trust",
    "wof:placetype":"venue"
},
  "geometry": {"coordinates":[-0.1007900015,51.5203018188],"type":"Point"}
}