{
  "type": "Feature",
  "properties": {
    "addr:full":"Craghead Stanley Durham DH9 6AN",
    "addr:postcode":"dh9 6an",
    "addr:street":"Stanley",
    "iso:country":"GB",
    "sg:address":"Craghead",
    "sg:city":"Stanley",
    "sg:classifiers":[
        {
            "category":"Retail",
            "subcategory":"Auto Repair",
            "type":"Services"
        }
    ],
    "sg:phone":"+44 1207 282727",
    "sg:postcode":"DH9 6AN",
    "sg:province":"Durham",
    "sg:tags":[
        "modification",
        "garage"
    ],
    "wof:name":"Main Road Garages",
    "wof:placetype":"venue"
},
  "geometry": {"coordinates":[-1.6810200214,54.8573684692],"type":"Point"}
}