{
  "type": "Feature",
  "properties": {
    "addr:full":"Home Farm, Crittenden Road, Matfield Tonbridge Kent TN12 7EW",
    "addr:postcode":"tn12 7ew",
    "addr:street":"Crittenden Road",
    "iso:country":"GB",
    "sg:address":"Home Farm, Crittenden Road, Matfield",
    "sg:city":"Tonbridge",
    "sg:classifiers":[
        {
            "category":"Farming",
            "subcategory":"Poultry Farm",
            "type":"Manufacturing & Wholesale Goods"
        }
    ],
    "sg:postcode":"TN12 7EW",
    "sg:province":"Kent",
    "sg:tags":[
        "game"
    ],
    "wof:name":"L House",
    "wof:placetype":"venue"
},
  "geometry": {"coordinates":[0.3721359968,51.152973175],"type":"Point"}
}