{
  "type": "Feature",
  "properties": {
    "iso:country":"GB",
    "sg:address":"42 Smith St",
    "sg:city":"Ayr",
    "sg:classifiers":[
        {
            "category":"Fast Food",
            "type":"Food & Drink"
        }
    ],
    "sg:phone":"+44 1292 283787",
    "sg:postcode":"KA7 1TF",
    "sg:province":"South Ayrshire",
    "sg:tags":[
        "away",
        "take"
    ],
    "wof:name":"Lucky Fifteen",
    "wof:placetype":"venue"
},
  "geometry": {"coordinates":[-4.6271901131,55.4585113525],"type":"Point"}
}