{
  "type": "Feature",
  "properties": {
    "addr:full":"Lincoln Rd Enfield Greater London EN3 4AH",
    "addr:postcode":"en3 4ah",
    "addr:street":"Lincoln Rd",
    "iso:country":"GB",
    "sg:address":"Lincoln Rd",
    "sg:city":"Enfield",
    "sg:classifiers":[
        {
            "category":"Place Of Worship",
            "type":"Public Place"
        }
    ],
    "sg:phone":"+44 20 8443 3492",
    "sg:postcode":"EN3 4AH",
    "sg:province":"Greater London",
    "wof:name":"Lincoln Road Chapel",
    "wof:placetype":"venue"
},
  "geometry": {"coordinates":[-0.053119,51.6441955566],"type":"Point"}
}