{
  "type": "Feature",
  "properties": {
    "iso:country":"GB",
    "sg:address":"18 Plas Isaf, Rhosymedre",
    "sg:city":"Wrexham",
    "sg:classifiers":[
        {
            "category":"Professional",
            "subcategory":"Art Services",
            "type":"Services"
        },
        {
            "category":"Building & Trades",
            "subcategory":"Construction",
            "type":"Services"
        }
    ],
    "sg:phone":"+44 1978 810454",
    "sg:postcode":"LL14 3EN",
    "sg:province":"Wrexham",
    "sg:tags":[
        "decorator",
        "painter"
    ],
    "wof:name":"J A RICHARDS",
    "wof:placetype":"venue"
},
  "geometry": {"coordinates":[-3.0613660812,52.9790763855],"type":"Point"}
}