{
  "type": "Feature",
  "properties": {
    "addr:full":"43-47 Dudden Hill Lane, Willesden Willesden Greater London NW10 2ET",
    "addr:housenumber":"43-47",
    "addr:postcode":"nw10 2et",
    "addr:street":"Dudden Hill Lane",
    "iso:country":"GB",
    "sg:address":"43-47 Dudden Hill Lane, Willesden",
    "sg:city":"Willesden",
    "sg:classifiers":[
        {
            "category":"Professional",
            "subcategory":"Lawyer & Legal Services",
            "type":"Services"
        }
    ],
    "sg:phone":"+44 20 8451 0297",
    "sg:postcode":"NW10 2ET",
    "sg:province":"Greater London",
    "sg:tags":[
        "advice",
        "counselling"
    ],
    "wof:name":"Learie Constantine Centre",
    "wof:placetype":"venue"
},
  "geometry": {"coordinates":[-0.240222,51.549759],"type":"Point"}
}