{
  "type": "Feature",
  "properties": {
    "iso:country":"GB",
    "sg:address":"Spring Garden Road",
    "sg:city":"Hartlepool",
    "sg:classifiers":[
        {
            "category":"Autos & Motor Vehicles",
            "subcategory":"Auto Supplies",
            "type":"Retail Goods"
        }
    ],
    "sg:phone":"+44 1429 274554",
    "sg:postcode":"TS25 5AD",
    "sg:province":"Durham",
    "sg:tags":[
        "tyre"
    ],
    "wof:name":"National Tyres and Autocare",
    "wof:placetype":"venue"
},
  "geometry": {"coordinates":[-1.21629,54.674187],"type":"Point"}
}