{
  "type": "Feature",
  "properties": {
    "addr:full":"Croxteth Hall& Country Park, Croxteth Park Liverpool Merseyside L12 0HB",
    "addr:postcode":"l12 0hb",
    "iso:country":"GB",
    "sg:address":"Croxteth Hall& Country Park, Croxteth Park",
    "sg:city":"Liverpool",
    "sg:classifiers":[
        {
            "category":"Landmark",
            "subcategory":"Historic",
            "type":"Public Place"
        },
        {
            "category":"Organizations",
            "subcategory":"Non-profit Organization",
            "type":"Services"
        }
    ],
    "sg:phone":"+44 151 228 6309",
    "sg:postcode":"L12 0HB",
    "sg:province":"Merseyside",
    "sg:tags":[
        "voluntary",
        "house",
        "organisation",
        "charitable",
        "garden",
        "charity"
    ],
    "wof:name":"Friends Of Croxteth Hall & Country Park",
    "wof:placetype":"venue"
},
  "geometry": {"coordinates":[-2.899656,53.446369],"type":"Point"}
}