{
  "type": "Feature",
  "properties": {
    "iso:country":"GB",
    "sg:address":"2 Bath Road",
    "sg:city":"Worcester",
    "sg:classifiers":[
        {
            "category":"Professional",
            "subcategory":"Printing & Photocopies",
            "type":"Services"
        }
    ],
    "sg:phone":"+44 1905 764777",
    "sg:postcode":"WR5 3EJ",
    "sg:province":"Worcestershire",
    "sg:tags":[
        "printer"
    ],
    "wof:name":"Print & Copy Shop",
    "wof:placetype":"venue"
},
  "geometry": {"coordinates":[-2.2165019512,52.1869621277],"type":"Point"}
}