{
  "type": "Feature",
  "properties": {
    "iso:country":"GB",
    "sg:address":"Ravensworth Road",
    "sg:city":"London",
    "sg:classifiers":[
        {
            "category":"Education",
            "subcategory":"School",
            "type":"Public Place"
        }
    ],
    "sg:phone":"+44 20 8857 4181",
    "sg:postcode":"SE9 4LW",
    "sg:province":"Greater London",
    "sg:tags":[
        "local",
        "authority"
    ],
    "wof:name":"Mottingham Primary School",
    "wof:placetype":"venue"
},
  "geometry": {"coordinates":[0.050496,51.431377],"type":"Point"}
}