{
  "type": "Feature",
  "properties": {
    "iso:country":"GB",
    "sg:address":"168 Derby Road, Long Eaton",
    "sg:city":"Nottingham",
    "sg:classifiers":[
        {
            "category":"Farming",
            "subcategory":"Nursery",
            "type":"Manufacturing & Wholesale Goods"
        }
    ],
    "sg:phone":"+44 115 973 2600",
    "sg:postcode":"NG10 4BJ",
    "sg:province":"Derbyshire",
    "sg:tags":[
        "creche"
    ],
    "wof:name":"Breedon House Nurseries",
    "wof:placetype":"venue"
},
  "geometry": {"coordinates":[-1.287837,52.900867],"type":"Point"}
}