{
  "type": "Feature",
  "properties": {
    "iso:country":"GB",
    "sg:address":"C/o Christopher Pratts, North Parade",
    "sg:city":"Bradford",
    "sg:classifiers":[
        {
            "category":"Personal",
            "subcategory":"Beauty Salon",
            "type":"Services"
        }
    ],
    "sg:phone":"+44 1274 721760",
    "sg:postcode":"BD1 3JJ",
    "sg:province":"West Yorkshire",
    "sg:tags":[
        "unisex",
        "hairdresser"
    ],
    "wof:name":"Stage Door 2",
    "wof:placetype":"venue"
},
  "geometry": {"coordinates":[-1.758306,53.795738],"type":"Point"}
}