{
  "type": "Feature",
  "properties": {
    "addr:full":"Grand Hall, London Rd Kilmarnock East Ayrshire KA3 7AA",
    "addr:postcode":"ka3 7aa",
    "addr:street":"London Rd",
    "iso:country":"GB",
    "sg:address":"Grand Hall, London Rd",
    "sg:city":"Kilmarnock",
    "sg:classifiers":[
        {
            "category":"Education",
            "subcategory":"Dance Studio",
            "type":"Public Place"
        }
    ],
    "sg:phone":"+44 1563 520026",
    "sg:postcode":"KA3 7AA",
    "sg:province":"East Ayrshire",
    "sg:tags":[
        "school",
        "dancing"
    ],
    "wof:name":"Mar-Eli School Of Dancing",
    "wof:placetype":"venue"
},
  "geometry": {"coordinates":[-4.4935898781,55.6096687317],"type":"Point"}
}