{
  "type": "Feature",
  "properties": {
    "iso:country":"GB",
    "sg:address":"41 Hyde Road, Caddington",
    "sg:city":"Luton",
    "sg:classifiers":[
        {
            "category":"Shopping",
            "subcategory":"Computers & Home Electronics",
            "type":"Retail Goods"
        }
    ],
    "sg:phone":"+44 1582 405196",
    "sg:postcode":"LU1 4HD",
    "sg:province":"Bedfordshire",
    "sg:tags":[
        "aerial",
        "television",
        "radio"
    ],
    "wof:name":"Caddington Tv Services",
    "wof:placetype":"venue"
},
  "geometry": {"coordinates":[-0.452958,51.865997],"type":"Point"}
}