{
  "type": "Feature",
  "properties": {
    "addr:full":"34 Station Road, Ketley Telford Shropshire TF1 5AQ",
    "addr:housenumber":"34",
    "addr:postcode":"tf1 5aq",
    "addr:street":"Station Road",
    "iso:country":"GB",
    "sg:address":"34 Station Road, Ketley",
    "sg:city":"Telford",
    "sg:classifiers":[
        {
            "category":"Fast Food",
            "type":"Food & Drink"
        },
        {
            "category":"Food & Beverages",
            "subcategory":"Meat & Fish",
            "type":"Retail Goods"
        }
    ],
    "sg:phone":"+44 1952 252183",
    "sg:postcode":"TF1 5AQ",
    "sg:province":"Shropshire",
    "sg:tags":[
        "shop",
        "chip"
    ],
    "wof:name":"D D Loizou",
    "wof:placetype":"venue"
},
  "geometry": {"coordinates":[-2.4811029434,52.6958694458],"type":"Point"}
}