{
  "type": "Feature",
  "properties": {
    "addr:full":"Coulsdon North Goods Yard, Station App, Coulsdon North Coulsdon Surrey CR5 2NR",
    "addr:postcode":"cr5 2nr",
    "iso:country":"GB",
    "sg:address":"Coulsdon North Goods Yard, Station App, Coulsdon North",
    "sg:city":"Coulsdon",
    "sg:classifiers":[
        {
            "category":"Building & Trades",
            "subcategory":"Construction",
            "type":"Services"
        }
    ],
    "sg:phone":"+44 20 8660 4246",
    "sg:postcode":"CR5 2NR",
    "sg:province":"Surrey",
    "sg:tags":[
        "platform",
        "work",
        "scaffolding"
    ],
    "wof:name":"G B Scaffolding",
    "wof:placetype":"venue"
},
  "geometry": {"coordinates":[-0.1391790062,51.3189239502],"type":"Point"}
}