{
  "type": "Feature",
  "properties": {
    "addr:full":"Swillbrook House Rest Home, Rosemary Lane, Bartle Preston Lancashire PR4 0HB",
    "addr:postcode":"pr4 0hb",
    "addr:street":"Rosemary Lane",
    "iso:country":"GB",
    "sg:address":"Swillbrook House Rest Home, Rosemary Lane, Bartle",
    "sg:city":"Preston",
    "sg:classifiers":[
        {
            "category":"Health Services",
            "subcategory":"Nursing And Care Facility",
            "type":"Services"
        },
        {
            "category":"Social Services",
            "subcategory":"Retirement Home",
            "type":"Services"
        }
    ],
    "sg:phone":"+44 1772 690317",
    "sg:postcode":"PR4 0HB",
    "sg:province":"Lancashire",
    "sg:tags":[
        "residential"
    ],
    "wof:name":"Swillbrook House Rest Home",
    "wof:placetype":"venue"
},
  "geometry": {"coordinates":[-2.784518,53.805386],"type":"Point"}
}