{
  "type": "Feature",
  "properties": {
    "addr:full":"Highfield Industrial Estate, North Street Chorley Lancashire PR7 1QD",
    "addr:postcode":"pr7 1qd",
    "addr:street":"Industrial Estate North Street",
    "iso:country":"GB",
    "sg:address":"Highfield Industrial Estate, North Street",
    "sg:city":"Chorley",
    "sg:classifiers":[
        {
            "category":"Manufacturing",
            "subcategory":"Tools & Machinery",
            "type":"Manufacturing & Wholesale Goods"
        },
        {
            "category":"Home & Garden",
            "subcategory":"Hardware",
            "type":"Retail Goods"
        }
    ],
    "sg:phone":"+44 1257 279364",
    "sg:postcode":"PR7 1QD",
    "sg:province":"Lancashire",
    "sg:tags":[
        "machine",
        "equipment",
        "welding",
        "manufacturer"
    ],
    "sg:website":"http://www.adwelding.co.uk",
    "wof:name":"Adlington Welding Supplies Ltd",
    "wof:placetype":"venue"
},
  "geometry": {"coordinates":[-2.6328339577,53.6634483337],"type":"Point"}
}