{
  "type": "Feature",
  "properties": {
    "iso:country":"GB",
    "sg:address":"22 Miranda Road",
    "sg:city":"London",
    "sg:classifiers":[
        {
            "category":"Retail",
            "subcategory":"Storage",
            "type":"Services"
        }
    ],
    "sg:phone":"+44 20 7561 1196",
    "sg:postcode":"N19 3RB",
    "sg:province":"Greater London",
    "sg:tags":[
        "household",
        "removal"
    ],
    "wof:name":"North London Transport",
    "wof:placetype":"venue"
},
  "geometry": {"coordinates":[-0.1336710006,51.5682983398],"type":"Point"}
}