{
  "type": "Feature",
  "properties": {
    "addr:full":"11 Bank Street Newquay Cornwall TR7 1EP",
    "addr:housenumber":"11",
    "addr:postcode":"tr7 1ep",
    "addr:street":"Bank Street",
    "iso:country":"GB",
    "sg:address":"11 Bank Street",
    "sg:city":"Newquay",
    "sg:classifiers":[
        {
            "category":"Shopping",
            "subcategory":"Gifts & Souvenirs",
            "type":"Retail Goods"
        }
    ],
    "sg:phone":"+44 1637 876776",
    "sg:postcode":"TR7 1EP",
    "sg:province":"Cornwall",
    "sg:tags":[
        "shop"
    ],
    "wof:name":"Talk of the Town",
    "wof:placetype":"venue"
},
  "geometry": {"coordinates":[-5.0864448547,50.4134101868],"type":"Point"}
}