{
  "type": "Feature",
  "properties": {
    "addr:full":"Mary Ardens House, Wilmcote Stratford-upon-avon Warwickshire CV37 9YA",
    "addr:postcode":"cv37 9ya",
    "iso:country":"GB",
    "sg:address":"Mary Ardens House, Wilmcote",
    "sg:city":"Stratford-upon-avon",
    "sg:classifiers":[
        {
            "category":"Community Center",
            "type":"Public Place"
        },
        {
            "category":"Organizations",
            "subcategory":"Membership Organization",
            "type":"Services"
        }
    ],
    "sg:phone":"+44 1789 298365",
    "sg:postcode":"CV37 9YA",
    "sg:province":"Warwickshire",
    "sg:tags":[
        "club",
        "recreation",
        "leisure",
        "centre"
    ],
    "wof:name":"Heart of England Falconry",
    "wof:placetype":"venue"
},
  "geometry": {"coordinates":[-1.707269,52.194134],"type":"Point"}
}