{
  "type": "Feature",
  "properties": {
    "iso:country":"GB",
    "sg:address":"50 Jerusalem Road, Skellingthorpe",
    "sg:city":"Lincoln",
    "sg:classifiers":[
        {
            "category":"Shopping",
            "subcategory":"Department Store",
            "type":"Retail Goods"
        },
        {
            "category":"Food & Beverages",
            "subcategory":"Supermarket",
            "type":"Retail Goods"
        }
    ],
    "sg:postcode":"LN6 4RH",
    "sg:province":"Lincolnshire",
    "wof:name":"Top Shop",
    "wof:placetype":"venue"
},
  "geometry": {"coordinates":[-0.6258730292,53.2243270874],"type":"Point"}
}