{
  "type": "Feature",
  "properties": {
    "iso:country":"GB",
    "sg:address":"176 Wellingborough Road",
    "sg:city":"Rushden",
    "sg:classifiers":[
        {
            "category":"Shopping",
            "subcategory":"Florist",
            "type":"Retail Goods"
        }
    ],
    "sg:postcode":"NN10 9SU",
    "sg:province":"Bedfordshire",
    "wof:name":"Howes",
    "wof:placetype":"venue"
},
  "geometry": {"coordinates":[-0.60696,52.292351],"type":"Point"}
}