{
  "type": "Feature",
  "properties": {
    "iso:country":"GB",
    "sg:address":"89 Marylebone High Street",
    "sg:city":"London",
    "sg:classifiers":[
        {
            "category":"Health Services",
            "subcategory":"Health Practitioner",
            "type":"Services"
        }
    ],
    "sg:phone":"+44 20 7262 3807",
    "sg:postcode":"W1U 4QW",
    "sg:province":"Greater London",
    "sg:tags":[
        "psychotherapist"
    ],
    "wof:name":"Sherwood Psychotherapy Training Institute",
    "wof:placetype":"venue"
},
  "geometry": {"coordinates":[-0.152004,51.520199],"type":"Point"}
}