{
  "type": "Feature",
  "properties": {
    "addr:full":"Unit 1, Dale House Altrincham Cheshire WA14 5DH",
    "addr:housenumber":"unit 1 dale house",
    "addr:postcode":"wa14 5dh",
    "addr:street":"Altrincham Cheshire",
    "iso:country":"GB",
    "sg:address":"Unit 1, Dale House",
    "sg:city":"Altrincham",
    "sg:classifiers":[
        {
            "category":"Manufacturing",
            "subcategory":"Paper Products",
            "type":"Manufacturing & Wholesale Goods"
        }
    ],
    "sg:postcode":"WA14 5DH",
    "sg:province":"Cheshire",
    "sg:tags":[
        "stationery",
        "mnfr"
    ],
    "wof:name":"Folders",
    "wof:placetype":"venue"
},
  "geometry": {"coordinates":[-2.3626790047,53.3992500305],"type":"Point"}
}