{
  "type": "Feature",
  "properties": {
    "addr:full":"Ravensbank Farm, Moss Side, Formby Liverpool Lancashire L37 0AE",
    "addr:postcode":"l37 0ae",
    "iso:country":"GB",
    "sg:address":"Ravensbank Farm, Moss Side, Formby",
    "sg:city":"Liverpool",
    "sg:classifiers":[
        {
            "category":"Transit Center",
            "subcategory":"Passenger",
            "type":"Transportation"
        },
        {
            "category":"Retail",
            "subcategory":"Pet Boarding",
            "type":"Services"
        }
    ],
    "sg:phone":"+44 1704 873986",
    "sg:postcode":"L37 0AE",
    "sg:province":"Lancashire",
    "sg:tags":[
        "kennel",
        "catteries"
    ],
    "wof:name":"Ravensbank Farm Boarding Kennels",
    "wof:placetype":"venue"
},
  "geometry": {"coordinates":[-3.04415,53.563221],"type":"Point"}
}