{
  "type": "Feature",
  "properties": {
    "addr:full":"85 Pde Sutton Coldfield West Midlands B72 1PL",
    "addr:housenumber":"85",
    "addr:postcode":"b72 1pl",
    "addr:street":"Pde",
    "iso:country":"GB",
    "sg:address":"85 Pde",
    "sg:city":"Sutton Coldfield",
    "sg:classifiers":[
        {
            "category":"Food & Beverages",
            "subcategory":"Candy",
            "type":"Retail Goods"
        }
    ],
    "sg:phone":"+44 121 354 3606",
    "sg:postcode":"B72 1PL",
    "sg:province":"West Midlands",
    "sg:tags":[
        "confectioner"
    ],
    "wof:name":"Thorntons PLC",
    "wof:placetype":"venue"
},
  "geometry": {"coordinates":[-1.8241000175,52.5616989136],"type":"Point"}
}