{
  "type": "Feature",
  "properties": {
    "iso:country":"GB",
    "sg:address":"7 Newlyn Walk, Cupernham Grn",
    "sg:city":"Romsey",
    "sg:classifiers":[
        {
            "category":"Professional",
            "subcategory":"Accounting & Tax Preparation",
            "type":"Services"
        }
    ],
    "sg:phone":"+44 1794 523754",
    "sg:postcode":"SO51 7WB",
    "sg:province":"Hampshire",
    "sg:tags":[
        "accountant"
    ],
    "wof:name":"Frank A Stokes",
    "wof:placetype":"venue"
},
  "geometry": {"coordinates":[-1.486241,50.996552],"type":"Point"}
}