{
  "type": "Feature",
  "properties": {
    "addr:full":"5 Vicarage La East Ham Greater London E6 4AD",
    "addr:housenumber":"5",
    "addr:postcode":"e6 4ad",
    "addr:street":"Vicarage La East Ham",
    "iso:country":"GB",
    "sg:address":"5 Vicarage La",
    "sg:city":"East Ham",
    "sg:classifiers":[
        {
            "category":"Food & Beverages",
            "subcategory":"Fruits & Vegetables",
            "type":"Retail Goods"
        }
    ],
    "sg:phone":"+44 20 8552 0200",
    "sg:postcode":"E6 4AD",
    "sg:province":"Greater London",
    "sg:tags":[
        "greengrocer"
    ],
    "wof:name":"The Fruit Bowl",
    "wof:placetype":"venue"
},
  "geometry": {"coordinates":[0.0624700002,51.5247383118],"type":"Point"}
}