{
  "type": "Feature",
  "properties": {
    "addr:full":"19 Westoe Road South Shields Tyne and Wear NE33 4ND",
    "addr:housenumber":"19",
    "addr:postcode":"ne33 4nd",
    "addr:street":"Westoe Road",
    "iso:country":"GB",
    "sg:address":"19 Westoe Road",
    "sg:city":"South Shields",
    "sg:classifiers":[
        {
            "category":"Real Estate",
            "subcategory":"Surveying",
            "type":"Services"
        }
    ],
    "sg:phone":"+44 191 455 2528",
    "sg:postcode":"NE33 4ND",
    "sg:province":"Tyne and Wear",
    "sg:tags":[
        "surveyor",
        "valuer"
    ],
    "wof:name":"Finn & Irvin",
    "wof:placetype":"venue"
},
  "geometry": {"coordinates":[-1.429008007,54.9938964844],"type":"Point"}
}