{
  "type": "Feature",
  "properties": {
    "addr:full":"North Kelsey Road, Caistor Market Rasen Lincolnshire LN7 6SF",
    "addr:postcode":"ln7 6sf",
    "addr:street":"North Kelsey Road Caistor Market Rasen",
    "iso:country":"GB",
    "sg:address":"North Kelsey Road, Caistor",
    "sg:city":"Market Rasen",
    "sg:classifiers":[
        {
            "category":"Home & Garden",
            "subcategory":"Carpets & Floor Coverings",
            "type":"Retail Goods"
        }
    ],
    "sg:phone":"+44 1472 852909",
    "sg:postcode":"LN7 6SF",
    "sg:province":"Lincolnshire",
    "sg:tags":[
        "rubber",
        "plastic"
    ],
    "wof:name":"Marmax",
    "wof:placetype":"venue"
},
  "geometry": {"coordinates":[-0.334623009,53.4987068176],"type":"Point"}
}