{
  "type": "Feature",
  "properties": {
    "addr:full":"153 Great Bridge Street West Bromwich West Midlands B70 0DJ",
    "addr:housenumber":"153",
    "addr:postcode":"b70 0dj",
    "addr:street":"Great Bridge Street",
    "iso:country":"GB",
    "sg:address":"153 Great Bridge Street",
    "sg:city":"West Bromwich",
    "sg:classifiers":[
        {
            "category":"Building & Trades",
            "subcategory":"Construction",
            "type":"Services"
        }
    ],
    "sg:phone":"+44 121 557 7983",
    "sg:postcode":"B70 0DJ",
    "sg:province":"West Midlands",
    "sg:tags":[
        "builder"
    ],
    "wof:name":"Ward Builders (Tipton) Ltd.",
    "wof:placetype":"venue"
},
  "geometry": {"coordinates":[-2.024921,52.528683],"type":"Point"}
}