{
  "type": "Feature",
  "properties": {
    "iso:country":"GB",
    "sg:address":"125 Roman Rd",
    "sg:city":"Bethnal Green",
    "sg:classifiers":[
        {
            "category":"Real Estate",
            "subcategory":"Surveying",
            "type":"Services"
        }
    ],
    "sg:phone":"+44 20 8980 7799",
    "sg:postcode":"E3 5SN",
    "sg:province":"Greater London",
    "sg:tags":[
        "surveyor",
        "valuer"
    ],
    "wof:name":"Gillian McCarthy Chartered Surveyors",
    "wof:placetype":"venue"
},
  "geometry": {"coordinates":[-0.040229,51.530869],"type":"Point"}
}