{
  "type": "Feature",
  "properties": {
    "iso:country":"GB",
    "sg:address":"3 Lancelyn Precinct, Spital Road",
    "sg:city":"Wirral",
    "sg:classifiers":[
        {
            "category":"Government",
            "subcategory":"Post Office",
            "type":"Public Place"
        },
        {
            "category":"Shopping",
            "subcategory":"Pharmacy",
            "type":"Retail Goods"
        }
    ],
    "sg:phone":"+44 151 334 6428",
    "sg:postcode":"CH63 9JP",
    "sg:province":"Merseyside",
    "sg:tags":[
        "pharmacist",
        "chemist"
    ],
    "wof:name":"Lancelyn Court Post Office",
    "wof:placetype":"venue"
},
  "geometry": {"coordinates":[-3.004464,53.340343],"type":"Point"}
}