{
  "type": "Feature",
  "properties": {
    "addr:full":"353 Nottingham Rd Derby Derbyshire DE21 6FP",
    "addr:housenumber":"353",
    "addr:postcode":"de21 6fp",
    "addr:street":"Nottingham Rd",
    "iso:country":"GB",
    "sg:address":"353 Nottingham Rd",
    "sg:city":"Derby",
    "sg:classifiers":[
        {
            "category":"Professional",
            "type":"Services"
        }
    ],
    "sg:phone":"+44 1332 342766",
    "sg:postcode":"DE21 6FP",
    "sg:province":"Derbyshire",
    "sg:tags":[
        "caterer"
    ],
    "wof:name":"Cottams Catering Co",
    "wof:placetype":"venue"
},
  "geometry": {"coordinates":[-1.4465990067,52.9266891479],"type":"Point"}
}