{
  "type": "Feature",
  "properties": {
    "iso:country":"GB",
    "sg:address":"3 Harts Lane",
    "sg:city":"New Cross",
    "sg:classifiers":[
        {
            "category":"Retail",
            "subcategory":"Auto Repair",
            "type":"Services"
        }
    ],
    "sg:phone":"+44 20 7277 9618",
    "sg:postcode":"SE14 5UP",
    "sg:province":"Greater London",
    "sg:tags":[
        "modification",
        "garage"
    ],
    "wof:name":"James Motors",
    "wof:placetype":"venue"
},
  "geometry": {"coordinates":[-0.042373,51.475273],"type":"Point"}
}