{
  "type": "Feature",
  "properties": {
    "addr:full":"16 The Avenue Eastbourne East Sussex BN21 3YD",
    "addr:housenumber":"16",
    "addr:postcode":"bn21 3yd",
    "addr:street":"The Avenue",
    "iso:country":"GB",
    "sg:address":"16 The Avenue",
    "sg:city":"Eastbourne",
    "sg:classifiers":[
        {
            "category":"Professional",
            "subcategory":"Lawyer & Legal Services",
            "type":"Services"
        }
    ],
    "sg:phone":"+44 1323 720040",
    "sg:postcode":"BN21 3YD",
    "sg:province":"East Sussex",
    "sg:tags":[
        "solicitor"
    ],
    "wof:name":"Daltons Solicitors",
    "wof:placetype":"venue"
},
  "geometry": {"coordinates":[0.280646,50.77161],"type":"Point"}
}