{
  "type": "Feature",
  "properties": {
    "addr:full":"275 Station Road, New Waltham Grimsby Lincolnshire DN36 4QJ",
    "addr:housenumber":"275",
    "addr:postcode":"dn36 4qj",
    "addr:street":"Station Road",
    "iso:country":"GB",
    "sg:address":"275 Station Road, New Waltham",
    "sg:city":"Grimsby",
    "sg:classifiers":[
        {
            "category":"Government",
            "subcategory":"Post Office",
            "type":"Public Place"
        }
    ],
    "sg:phone":"+44 845 722 3344",
    "sg:postcode":"DN36 4QJ",
    "sg:province":"Lincolnshire",
    "wof:name":"New Waltham Post Office",
    "wof:placetype":"venue"
},
  "geometry": {"coordinates":[-0.060945,53.524883],"type":"Point"}
}