{
  "type": "Feature",
  "properties": {
    "iso:country":"GB",
    "sg:address":"Crookes Lane, Kewstoke",
    "sg:city":"Weston-super-mare",
    "sg:classifiers":[
        {
            "category":"Recreation",
            "subcategory":"Campground",
            "type":"Entertainment"
        }
    ],
    "sg:phone":"+44 1934 622319",
    "sg:postcode":"BS22 9XJ",
    "sg:province":"Somerset",
    "sg:tags":[
        "caravan",
        "park"
    ],
    "wof:name":"Ardnave Holiday Park",
    "wof:placetype":"venue"
},
  "geometry": {"coordinates":[-2.959024,51.368172],"type":"Point"}
}