{
  "type": "Feature",
  "properties": {
    "addr:full":"23 Market Pl Whitehaven Cumbria CA28 7JB",
    "addr:housenumber":"23",
    "addr:postcode":"ca28 7jb",
    "addr:street":"Market Pl",
    "iso:country":"GB",
    "sg:address":"23 Market Pl",
    "sg:city":"Whitehaven",
    "sg:classifiers":[
        {
            "category":"Food & Beverages",
            "subcategory":"Meat & Fish",
            "type":"Retail Goods"
        }
    ],
    "sg:postcode":"CA28 7JB",
    "sg:province":"Cumbria",
    "sg:tags":[
        "butcher"
    ],
    "wof:name":"Hambling Wils",
    "wof:placetype":"venue"
},
  "geometry": {"coordinates":[-3.5908520222,54.5466995239],"type":"Point"}
}