{
  "type": "Feature",
  "properties": {
    "iso:country":"GB",
    "sg:address":"133 Commercial Road",
    "sg:city":"London",
    "sg:classifiers":[
        {
            "category":"Wholesale",
            "subcategory":"Apparel",
            "type":"Manufacturing & Wholesale Goods"
        }
    ],
    "sg:phone":"+44 20 7377 0965",
    "sg:postcode":"E1 1PX",
    "sg:province":"Greater London",
    "sg:tags":[
        "supplier",
        "w'sale",
        "clothing",
        "ladieswear"
    ],
    "wof:name":"Flick Fashions Ltd.",
    "wof:placetype":"venue"
},
  "geometry": {"coordinates":[-0.062705,51.514889],"type":"Point"}
}