{
  "type": "Feature",
  "properties": {
    "addr:full":"The Quay Bideford Devon EX39 2EY",
    "addr:postcode":"ex39 2ey",
    "addr:street":"The Quay",
    "iso:country":"GB",
    "sg:address":"The Quay",
    "sg:city":"Bideford",
    "sg:classifiers":[
        {
            "category":"Education",
            "subcategory":"Special Training",
            "type":"Public Place"
        }
    ],
    "sg:phone":"+44 1237 422701",
    "sg:postcode":"EX39 2EY",
    "sg:province":"Devon",
    "sg:tags":[
        "product",
        "centre"
    ],
    "wof:name":"Bideford Open Access Centre",
    "wof:placetype":"venue"
},
  "geometry": {"coordinates":[-4.2047638893,51.0173492432],"type":"Point"}
}