{
  "type": "Feature",
  "properties": {
    "addr:full":"Unit C3, Kite Lane, New Yatt Witney Oxfordshire OX8 6TJ",
    "addr:postcode":"ox8 6tj",
    "addr:street":"Kite Lane",
    "iso:country":"GB",
    "sg:address":"Unit C3, Kite Lane, New Yatt",
    "sg:city":"Witney",
    "sg:classifiers":[
        {
            "category":"Autos & Motor Vehicles",
            "subcategory":"Automobile Sales",
            "type":"Retail Goods"
        }
    ],
    "sg:phone":"+44 1993 868014",
    "sg:postcode":"OX8 6TJ",
    "sg:province":"Oxfordshire",
    "sg:tags":[
        "commercial"
    ],
    "wof:name":"Oxfordshire Mini Centre",
    "wof:placetype":"venue"
},
  "geometry": {"coordinates":[-1.4633,51.805481],"type":"Point"}
}