{
  "type": "Feature",
  "properties": {
    "addr:full":"Corradee, Huntly Place Aboyne Aberdeenshire AB34 5HD",
    "addr:postcode":"ab34 5hd",
    "addr:street":"Huntly Place",
    "iso:country":"GB",
    "sg:address":"Corradee, Huntly Place",
    "sg:city":"Aboyne",
    "sg:classifiers":[
        {
            "category":"Building & Trades",
            "subcategory":"Construction",
            "type":"Services"
        }
    ],
    "sg:phone":"+44 1339 886459",
    "sg:postcode":"AB34 5HD",
    "sg:province":"Aberdeenshire",
    "sg:tags":[
        "roofing",
        "contracting"
    ],
    "wof:name":"Robert Wright & Son",
    "wof:placetype":"venue"
},
  "geometry": {"coordinates":[-2.7872788906,57.0725860596],"type":"Point"}
}