{
  "type": "Feature",
  "properties": {
    "addr:full":"146 High Street, Aston Birmingham West Midlands B6 4US",
    "addr:housenumber":"146",
    "addr:postcode":"b6 4us",
    "addr:street":"High Street",
    "iso:country":"GB",
    "sg:address":"146 High Street, Aston",
    "sg:city":"Birmingham",
    "sg:classifiers":[
        {
            "category":"Bars & Pubs",
            "subcategory":"Nightclub",
            "type":"Food & Drink"
        }
    ],
    "sg:phone":"+44 121 456 3117",
    "sg:postcode":"B6 4US",
    "sg:province":"West Midlands",
    "sg:tags":[
        "club",
        "night"
    ],
    "wof:name":"Gracesign Ltd.",
    "wof:placetype":"venue"
},
  "geometry": {"coordinates":[-1.895141,52.498669],"type":"Point"}
}