{
  "type": "Feature",
  "properties": {
    "addr:full":"The Old Dairy, Pinkney Park Malmesbury Wiltshire SN16 0NX",
    "addr:postcode":"sn16 0nx",
    "iso:country":"GB",
    "sg:address":"The Old Dairy, Pinkney Park",
    "sg:city":"Malmesbury",
    "sg:classifiers":[
        {
            "category":"Social Services",
            "type":"Services"
        },
        {
            "category":"Manufacturing",
            "subcategory":"Tobacco Products",
            "type":"Manufacturing & Wholesale Goods"
        }
    ],
    "sg:phone":"+44 1666 840060",
    "sg:postcode":"SN16 0NX",
    "sg:province":"Wiltshire",
    "sg:tags":[
        "equipment",
        "suppliers",
        "disability",
        "manufacturers"
    ],
    "wof:name":"Optimum Mobility Ltd.",
    "wof:placetype":"venue"
},
  "geometry": {"coordinates":[-2.196278,51.580215],"type":"Point"}
}