{
  "type": "Feature",
  "properties": {
    "addr:full":"93 Condover Industrial Estate Shrewsbury Shropshire SY5 7NH",
    "addr:housenumber":"93",
    "addr:postcode":"sy5 7nh",
    "addr:street":"Condover Industrial Estate",
    "iso:country":"GB",
    "sg:address":"93 Condover Industrial Estate",
    "sg:city":"Shrewsbury",
    "sg:classifiers":[
        {
            "category":"Building & Trades",
            "subcategory":"Equipment Rental",
            "type":"Services"
        }
    ],
    "sg:phone":"+44 1743 718498",
    "sg:postcode":"SY5 7NH",
    "sg:province":"Shropshire",
    "sg:tags":[
        "plant",
        "machinery"
    ],
    "wof:name":"Lux Traffic Controls Ltd.",
    "wof:placetype":"venue"
},
  "geometry": {"coordinates":[-2.733591,52.628864],"type":"Point"}
}