{
  "type": "Feature",
  "properties": {
    "iso:country":"GB",
    "sg:address":"Third Avenue, Denbigh West Industrial Estate",
    "sg:city":"Milton Keynes",
    "sg:classifiers":[
        {
            "category":"Wholesale",
            "subcategory":"Construction Materials",
            "type":"Manufacturing & Wholesale Goods"
        }
    ],
    "sg:phone":"+44 1908 449300",
    "sg:postcode":"MK1 1DR",
    "sg:province":"Buckinghamshire",
    "sg:tags":[
        "lift"
    ],
    "wof:name":"Sling & Tackle (Milton Keynes) Ltd.",
    "wof:placetype":"venue"
},
  "geometry": {"coordinates":[-0.734669,52.004345],"type":"Point"}
}