{
  "type": "Feature",
  "properties": {
    "iso:country":"GB",
    "sg:address":"7 Cashmore Road",
    "sg:city":"Kenilworth",
    "sg:classifiers":[
        {
            "category":"Professional",
            "subcategory":"Engineering",
            "type":"Services"
        }
    ],
    "sg:phone":"+44 1926 511393",
    "sg:postcode":"CV8 2SJ",
    "sg:province":"Warwickshire",
    "sg:tags":[
        "consulting",
        "engineer"
    ],
    "wof:name":"Environmental Management Associates Ltd.",
    "wof:placetype":"venue"
},
  "geometry": {"coordinates":[-1.554205,52.343193],"type":"Point"}
}