{
  "type": "Feature",
  "properties": {
    "addr:full":"287 Manningham Lane Bradford West Yorkshire BD8 7NA",
    "addr:housenumber":"287",
    "addr:postcode":"bd8 7na",
    "addr:street":"Manningham Lane",
    "iso:country":"GB",
    "sg:address":"287 Manningham Lane",
    "sg:city":"Bradford",
    "sg:classifiers":[
        {
            "category":"Professional",
            "subcategory":"Accounting & Tax Preparation",
            "type":"Services"
        },
        {
            "category":"Professional",
            "subcategory":"Management & Consulting",
            "type":"Services"
        }
    ],
    "sg:postcode":"BD8 7NA",
    "sg:province":"West Yorkshire",
    "sg:tags":[
        "accountant",
        "holding",
        "activity"
    ],
    "wof:name":"MCM (HOLDINGS) LTD",
    "wof:placetype":"venue"
},
  "geometry": {"coordinates":[-1.7671240568,53.8083229065],"type":"Point"}
}