{
  "type": "Feature",
  "properties": {
    "addr:full":"186 Fulham Road London Greater London SW10 9PN",
    "addr:housenumber":"186",
    "addr:postcode":"sw10 9pn",
    "addr:street":"Fulham Road",
    "iso:country":"GB",
    "sg:address":"186 Fulham Road",
    "sg:city":"London",
    "sg:classifiers":[
        {
            "category":"Retail",
            "subcategory":"Laundry & Dry Cleaning",
            "type":"Services"
        }
    ],
    "sg:phone":"+44 20 7376 7156",
    "sg:postcode":"SW10 9PN",
    "sg:province":"Greater London",
    "sg:tags":[
        "alteration"
    ],
    "wof:name":"Brooker Dry Cleaners",
    "wof:placetype":"venue"
},
  "geometry": {"coordinates":[-0.180835,51.486191],"type":"Point"}
}