{
  "type": "Feature",
  "properties": {
    "addr:full":"Old Coombe, Manor Farm Dartmouth Devon TQ6 0JA",
    "addr:housenumber":"dartmouth",
    "addr:postcode":"tq6 0ja",
    "addr:street":"Old;Devon",
    "iso:country":"GB",
    "sg:address":"Old Coombe, Manor Farm",
    "sg:city":"Dartmouth",
    "sg:classifiers":[
        {
            "category":"Travel",
            "subcategory":"Hotels & Motels",
            "type":"Entertainment"
        }
    ],
    "sg:phone":"+44 1803 722398",
    "sg:postcode":"TQ6 0JA",
    "sg:province":"Devon",
    "wof:name":"Fingals Hotel",
    "wof:placetype":"venue"
},
  "geometry": {"coordinates":[-3.5850760937,50.3536186218],"type":"Point"}
}