{
  "type": "Feature",
  "properties": {
    "addr:full":"Goodlass Road, Speke Liverpool Merseyside L24 9HJ",
    "addr:postcode":"l24 9hj",
    "addr:street":"Goodlass Road",
    "iso:country":"GB",
    "sg:address":"Goodlass Road, Speke",
    "sg:city":"Liverpool",
    "sg:classifiers":[
        {
            "category":"Coffee & Tea",
            "type":"Food & Drink"
        }
    ],
    "sg:phone":"+44 151 448 1223",
    "sg:postcode":"L24 9HJ",
    "sg:province":"Merseyside",
    "sg:tags":[
        "machine"
    ],
    "wof:name":"M C S Coffee",
    "wof:placetype":"venue"
},
  "geometry": {"coordinates":[-2.8679890633,53.3544502258],"type":"Point"}
}