{
  "type": "Feature",
  "properties": {
    "iso:country":"GB",
    "sg:address":"33 King Street, Enderby",
    "sg:city":"Leicester",
    "sg:classifiers":[
        {
            "category":"Professional",
            "type":"Services"
        },
        {
            "category":"Home & Garden",
            "subcategory":"Home Furnishings",
            "type":"Retail Goods"
        }
    ],
    "sg:phone":"+44 116 284 9079",
    "sg:postcode":"LE19 4NT",
    "sg:province":"Leicestershire",
    "sg:tags":[
        "interior",
        "furnishers",
        "designer",
        "soft",
        "sale"
    ],
    "wof:name":"MONART INTERIORS",
    "wof:placetype":"venue"
},
  "geometry": {"coordinates":[-1.2116400003,52.5873222351],"type":"Point"}
}