{
  "type": "Feature",
  "properties": {
    "iso:country":"GB",
    "sg:address":"12 Princes Street",
    "sg:city":"Perth",
    "sg:classifiers":[
        {
            "category":"Professional",
            "type":"Services"
        }
    ],
    "sg:phone":"+44 1738 441277",
    "sg:postcode":"PH2 8NG",
    "sg:province":"Perth and Kinross",
    "sg:tags":[
        "caterer"
    ],
    "wof:name":"Tandoori Knights",
    "wof:placetype":"venue"
},
  "geometry": {"coordinates":[-3.428022,56.394577],"type":"Point"}
}