{
  "type": "Feature",
  "properties": {
    "addr:full":"Bishopscroft Ashwell Road, Heaton Bradford West Yorkshire BD9 4AU",
    "addr:postcode":"yorkshire bd9 4au",
    "addr:street":"Ashwell Road",
    "iso:country":"GB",
    "sg:address":"Bishopscroft Ashwell Road, Heaton",
    "sg:city":"Bradford",
    "sg:classifiers":[
        {
            "category":"Organizations",
            "subcategory":"Religious Organization",
            "type":"Services"
        }
    ],
    "sg:phone":"+44 1274 545414",
    "sg:postcode":"BD9 4AU",
    "sg:province":"West Yorkshire",
    "sg:tags":[
        "organisation",
        "place",
        "worship"
    ],
    "wof:name":"Bishop of Bradford",
    "wof:placetype":"venue"
},
  "geometry": {"coordinates":[-1.772801,53.815567],"type":"Point"}
}