{
  "type": "Feature",
  "properties": {
    "addr:full":"77 Hobs Moat Road Solihull West Midlands B92 8JL",
    "addr:housenumber":"77",
    "addr:postcode":"b92 8jl",
    "addr:street":"Hobs Moat Road",
    "iso:country":"GB",
    "sg:address":"77 Hobs Moat Road",
    "sg:city":"Solihull",
    "sg:classifiers":[
        {
            "category":"Food & Beverages",
            "subcategory":"Meat & Fish",
            "type":"Retail Goods"
        },
        {
            "category":"Food & Beverages",
            "subcategory":"Groceries & Convenience Stores",
            "type":"Retail Goods"
        }
    ],
    "sg:phone":"+44 121 743 4827",
    "sg:postcode":"B92 8JL",
    "sg:province":"West Midlands",
    "sg:tags":[
        "shop",
        "chip"
    ],
    "wof:name":"Solihull Fish Bar",
    "wof:placetype":"venue"
},
  "geometry": {"coordinates":[-1.784904,52.443535],"type":"Point"}
}