{
  "type": "Feature",
  "properties": {
    "addr:full":"10 Toller Grove Bradford West Yorkshire BD9 5NP",
    "addr:housenumber":"10",
    "addr:postcode":"bd9 5np",
    "addr:street":"Toller Grove",
    "iso:country":"GB",
    "sg:address":"10 Toller Grove",
    "sg:city":"Bradford",
    "sg:classifiers":[
        {
            "category":"Freight",
            "type":"Transportation"
        }
    ],
    "sg:phone":"+44 1274 543333",
    "sg:postcode":"BD9 5NP",
    "sg:province":"West Yorkshire",
    "sg:tags":[
        "forwarders"
    ],
    "wof:name":"Brogan International Transport Services",
    "wof:placetype":"venue"
},
  "geometry": {"coordinates":[-1.7946430445,53.8136062622],"type":"Point"}
}