{
  "type": "Feature",
  "properties": {
    "addr:full":"370-386 Farnham Road Slough Berkshire SL2 1JD",
    "addr:housenumber":"370-386",
    "addr:postcode":"sl2 1jd",
    "addr:street":"Farnham Road",
    "iso:country":"GB",
    "sg:address":"370-386 Farnham Road",
    "sg:city":"Slough",
    "sg:classifiers":[
        {
            "category":"Wholesale",
            "subcategory":"Electrical",
            "type":"Manufacturing & Wholesale Goods"
        },
        {
            "category":"Shopping",
            "subcategory":"Computers & Home Electronics",
            "type":"Retail Goods"
        }
    ],
    "sg:phone":"+44 1753 537811",
    "sg:postcode":"SL2 1JD",
    "sg:province":"Berkshire",
    "sg:tags":[
        "wholesaler"
    ],
    "wof:name":"G F E Electrical Wholesale Ltd.",
    "wof:placetype":"venue"
},
  "geometry": {"coordinates":[-0.6162440181,51.5277748108],"type":"Point"}
}