{
  "type": "Feature",
  "properties": {
    "iso:country":"GB",
    "sg:address":"A405, Garston",
    "sg:city":"Watford",
    "sg:classifiers":[
        {
            "category":"Sports & Exercise",
            "subcategory":"Golf",
            "type":"Entertainment"
        }
    ],
    "sg:phone":"+44 1923 671365",
    "sg:postcode":"WD25 0GB",
    "sg:province":"Hertfordshire",
    "sg:tags":[
        "club",
        "course"
    ],
    "wof:name":"Penfold Golf Course",
    "wof:placetype":"venue"
},
  "geometry": {"coordinates":[-0.382562,51.705219],"type":"Point"}
}