{
  "type": "Feature",
  "properties": {
    "addr:full":"Carpenters Cottage, 2 Church Street, Easingwold York North Yorkshire YO61 3HF",
    "addr:housenumber":"2",
    "addr:postcode":"yo61 3hf",
    "addr:street":"Church Street",
    "iso:country":"GB",
    "sg:address":"Carpenters Cottage, 2 Church Street, Easingwold",
    "sg:city":"York",
    "sg:classifiers":[
        {
            "category":"Building & Trades",
            "subcategory":"Construction",
            "type":"Services"
        }
    ],
    "sg:postcode":"YO61 3HF",
    "sg:province":"North Yorkshire",
    "sg:tags":[
        "builder"
    ],
    "wof:name":"Franken Properties",
    "wof:placetype":"venue"
},
  "geometry": {"coordinates":[-1.19231,54.121414],"type":"Point"}
}