{
  "type": "Feature",
  "properties": {
    "iso:country":"GB",
    "sg:address":"18 Lower North Street",
    "sg:city":"Exeter",
    "sg:classifiers":[
        {
            "category":"Bars & Pubs",
            "type":"Food & Drink"
        }
    ],
    "sg:postcode":"EX4 3ET",
    "sg:province":"Devon",
    "sg:tags":[
        "pubs",
        "inn"
    ],
    "wof:name":"St. Annes Well Brewery Ltd",
    "wof:placetype":"venue"
},
  "geometry": {"coordinates":[-3.535818,50.724541],"type":"Point"}
}