{
  "type": "Feature",
  "properties": {
    "iso:country":"GB",
    "sg:address":"61 Castle Road",
    "sg:city":"Southsea",
    "sg:classifiers":[
        {
            "category":"Shopping",
            "subcategory":"Gifts & Souvenirs",
            "type":"Retail Goods"
        }
    ],
    "sg:postcode":"PO5 3AY",
    "sg:province":"Hampshire",
    "sg:tags":[
        "shop"
    ],
    "wof:name":"Orientations",
    "wof:placetype":"venue"
},
  "geometry": {"coordinates":[-1.093515,50.788788],"type":"Point"}
}