{
  "type": "Feature",
  "properties": {
    "iso:country":"GB",
    "sg:address":"60 Drumlanrig Street",
    "sg:city":"Thornhill",
    "sg:classifiers":[
        {
            "category":"Personal",
            "subcategory":"Beauty Salon",
            "type":"Services"
        }
    ],
    "sg:phone":"+44 1848 330211",
    "sg:postcode":"DG3 5LY",
    "sg:province":"Dumfries and Galloway",
    "sg:tags":[
        "unisex",
        "hairdresser"
    ],
    "wof:name":"G & I Rodgers Hair Studios",
    "wof:placetype":"venue"
},
  "geometry": {"coordinates":[-3.764461,55.240475],"type":"Point"}
}