{
  "type": "Feature",
  "properties": {
    "iso:country":"GB",
    "sg:address":"Lavender Walk, Moat La",
    "sg:city":"Battle",
    "sg:classifiers":[
        {
            "category":"Building & Trades",
            "subcategory":"Construction",
            "type":"Services"
        }
    ],
    "sg:phone":"+44 1424 756289",
    "sg:postcode":"TN33 0RY",
    "sg:province":"East Sussex",
    "sg:tags":[
        "builder"
    ],
    "wof:name":"Mayfair Construction",
    "wof:placetype":"venue"
},
  "geometry": {"coordinates":[0.489025,50.914616],"type":"Point"}
}