{
  "type": "Feature",
  "properties": {
    "iso:country":"GB",
    "sg:address":"42 Manners Gardens, Seaton Delaval",
    "sg:city":"Whitley Bay",
    "sg:classifiers":[
        {
            "category":"Building & Trades",
            "subcategory":"Construction",
            "type":"Services"
        }
    ],
    "sg:phone":"+44 191 237 5032",
    "sg:postcode":"NE25 0DR",
    "sg:province":"Northumberland",
    "sg:tags":[
        "builder"
    ],
    "wof:name":"A.K Construction",
    "wof:placetype":"venue"
},
  "geometry": {"coordinates":[-1.52847,55.074348],"type":"Point"}
}