{
  "type": "Feature",
  "properties": {
    "iso:country":"GB",
    "sg:address":"Tredomen Indstl Est, Nelson Rd, Ystrad Mynach",
    "sg:city":"Hengoed",
    "sg:classifiers":[
        {
            "category":"Retail",
            "subcategory":"Auto Repair",
            "type":"Services"
        }
    ],
    "sg:postcode":"CF82 7BP",
    "sg:province":"Caerphilly",
    "sg:tags":[
        "body",
        "car"
    ],
    "wof:name":"Clark,A,",
    "wof:placetype":"venue"
},
  "geometry": {"coordinates":[-3.231799,51.648319],"type":"Point"}
}