{
  "type": "Feature",
  "properties": {
    "addr:full":"21 Tavistock Road, Hindley Wigan Lancashire WN2 4QT",
    "addr:housenumber":"21",
    "addr:postcode":"wn2 4qt",
    "addr:street":"Tavistock Road",
    "iso:country":"GB",
    "sg:address":"21 Tavistock Road, Hindley",
    "sg:city":"Wigan",
    "sg:classifiers":[
        {
            "category":"Retail",
            "subcategory":"Driving School",
            "type":"Services"
        }
    ],
    "sg:phone":"+44 1942 256926",
    "sg:postcode":"WN2 4QT",
    "sg:province":"Lancashire",
    "wof:name":"Highway School Of Motoring",
    "wof:placetype":"venue"
},
  "geometry": {"coordinates":[-2.553145,53.529114],"type":"Point"}
}