{
  "type": "Feature",
  "properties": {
    "iso:country":"GB",
    "sg:address":"The Design Studio, Heights Lane, Delph",
    "sg:city":"Oldham",
    "sg:classifiers":[
        {
            "category":"Real Estate",
            "subcategory":"Surveying",
            "type":"Services"
        }
    ],
    "sg:phone":"+44 1457 876500",
    "sg:postcode":"OL3 5TU",
    "sg:province":"Lancashire",
    "sg:tags":[
        "building",
        "surveyor"
    ],
    "wof:name":"S Ingram & Associates",
    "wof:placetype":"venue"
},
  "geometry": {"coordinates":[-2.02309,53.566956],"type":"Point"}
}