{
  "type": "Feature",
  "properties": {
    "iso:country":"GB",
    "sg:address":"7 Market Precinct",
    "sg:city":"Llanelli",
    "sg:classifiers":[
        {
            "category":"Transit Center",
            "subcategory":"Freight",
            "type":"Transportation"
        },
        {
            "category":"Shopping",
            "subcategory":"Crafts & Fabrics",
            "type":"Retail Goods"
        }
    ],
    "sg:phone":"+44 1554 758825",
    "sg:postcode":"SA15 1YF",
    "sg:province":"Carmarthenshire",
    "sg:tags":[
        "shop",
        "outlet",
        "centre"
    ],
    "wof:name":"Welsh Textiles & Gifts",
    "wof:placetype":"venue"
},
  "geometry": {"coordinates":[-4.1342988014,51.6826820374],"type":"Point"}
}