{
  "type": "Feature",
  "properties": {
    "iso:country":"GB",
    "sg:address":"Dartmouth Road, Stoke Fleming",
    "sg:city":"Dartmouth",
    "sg:classifiers":[
        {
            "category":"Bars & Pubs",
            "type":"Food & Drink"
        },
        {
            "category":"Travel",
            "subcategory":"Hotels & Motels",
            "type":"Entertainment"
        }
    ],
    "sg:phone":"+44 1803 770253",
    "sg:postcode":"TQ6 0RF",
    "sg:province":"Devon",
    "sg:tags":[
        "pubs",
        "self",
        "inn",
        "catering"
    ],
    "wof:name":"Deer Park Inn",
    "wof:placetype":"venue"
},
  "geometry": {"coordinates":[-3.594689,50.332916],"type":"Point"}
}