{
  "type": "Feature",
  "properties": {
    "addr:full":"44 Albemarle Rd Ashford Kent TN24 0HN",
    "addr:housenumber":"44",
    "addr:postcode":"tn24 0hn",
    "addr:street":"Albemarle Rd",
    "iso:country":"GB",
    "sg:address":"44 Albemarle Rd",
    "sg:city":"Ashford",
    "sg:classifiers":[
        {
            "category":"Home & Garden",
            "subcategory":"Household Appliances",
            "type":"Retail Goods"
        }
    ],
    "sg:phone":"+44 1233 635950",
    "sg:postcode":"TN24 0HN",
    "sg:province":"Kent",
    "sg:tags":[
        "domestic",
        "centre"
    ],
    "wof:name":"D Pritchard",
    "wof:placetype":"venue"
},
  "geometry": {"coordinates":[0.8944860101,51.1417617798],"type":"Point"}
}