{
  "type": "Feature",
  "properties": {
    "addr:full":"Unit 9-10 Hill Street, Ty Coch Industrial Estate Cwmbran Monmouthshire NP44 7PG",
    "addr:housenumber":"9-10",
    "addr:postcode":"np44 7pg",
    "addr:street":"Hill Street Ty Coch Industrial Estate",
    "iso:country":"GB",
    "sg:address":"Unit 9-10 Hill Street, Ty Coch Industrial Estate",
    "sg:city":"Cwmbran",
    "sg:classifiers":[
        {
            "category":"Professional",
            "subcategory":"Computer Services",
            "type":"Services"
        }
    ],
    "sg:phone":"+44 1633 838382",
    "sg:postcode":"NP44 7PG",
    "sg:province":"Monmouthshire",
    "sg:tags":[
        "system",
        "software"
    ],
    "wof:name":"O E M Ribbon Ltd.",
    "wof:placetype":"venue"
},
  "geometry": {"coordinates":[-3.0230810642,51.6430892944],"type":"Point"}
}