{
  "type": "Feature",
  "properties": {
    "iso:country":"GB",
    "sg:address":"1 School Lane",
    "sg:city":"Wisbech",
    "sg:classifiers":[
        {
            "category":"Professional",
            "subcategory":"Accounting & Tax Preparation",
            "type":"Services"
        }
    ],
    "sg:phone":"+44 1945 465767",
    "sg:postcode":"PE13 1AW",
    "sg:province":"Cambridgeshire",
    "sg:tags":[
        "accountant"
    ],
    "wof:name":"Moore Thompson",
    "wof:placetype":"venue"
},
  "geometry": {"coordinates":[0.160556,52.666546],"type":"Point"}
}