{
  "type": "Feature",
  "properties": {
    "iso:country":"GB",
    "sg:address":"9 Uplands Mews",
    "sg:city":"East Dulwich",
    "sg:classifiers":[
        {
            "category":"Retail",
            "subcategory":"Auto Repair",
            "type":"Services"
        }
    ],
    "sg:phone":"+44 20 8299 4995",
    "sg:postcode":"SE22 9EG",
    "sg:province":"Greater London",
    "sg:tags":[
        "modification",
        "garage"
    ],
    "wof:name":"Pitstop Repairs",
    "wof:placetype":"venue"
},
  "geometry": {"coordinates":[-0.06995,51.457447],"type":"Point"}
}