{
  "type": "Feature",
  "properties": {
    "addr:full":"29 Glenwood Close Swindon Wiltshire SN1 4EB",
    "addr:housenumber":"29",
    "addr:postcode":"sn1 4eb",
    "addr:street":"Glenwood Close",
    "iso:country":"GB",
    "sg:address":"29 Glenwood Close",
    "sg:city":"Swindon",
    "sg:classifiers":[
        {
            "category":"Building & Trades",
            "subcategory":"Construction",
            "type":"Services"
        }
    ],
    "sg:postcode":"SN1 4EB",
    "sg:province":"Wiltshire",
    "sg:tags":[
        "supplier",
        "installers",
        "cladding"
    ],
    "wof:name":"Croft Cladding & Guttering Services",
    "wof:placetype":"venue"
},
  "geometry": {"coordinates":[-1.777893,51.542889],"type":"Point"}
}