{
  "type": "Feature",
  "properties": {
    "iso:country":"GB",
    "sg:address":"Bute Hall, Sutherland Road",
    "sg:city":"Brighton",
    "sg:classifiers":[
        {
            "category":"Shopping",
            "subcategory":"Department Store",
            "type":"Retail Goods"
        },
        {
            "category":"Building & Trades",
            "subcategory":"Construction",
            "type":"Services"
        }
    ],
    "sg:phone":"+44 1273 696929",
    "sg:postcode":"BN2 0EQ",
    "sg:province":"East Sussex",
    "sg:tags":[
        "flooring"
    ],
    "wof:name":"The Wood Gallery Ltd.",
    "wof:placetype":"venue"
},
  "geometry": {"coordinates":[-0.1196840033,50.8245315552],"type":"Point"}
}