{
  "type": "Feature",
  "properties": {
    "addr:full":"Agutter Khanderia, 21 Great Chapel Street London Greater London W1F 8FP",
    "addr:housenumber":"21",
    "addr:postcode":"w1f 8fp",
    "addr:street":"Great Chapel Street",
    "iso:country":"GB",
    "sg:address":"Agutter Khanderia, 21 Great Chapel Street",
    "sg:city":"London",
    "sg:classifiers":[
        {
            "category":"Communications",
            "type":"Services"
        }
    ],
    "sg:postcode":"W1F 8FP",
    "sg:province":"Greater London",
    "sg:tags":[
        "audio-visual"
    ],
    "wof:name":"The Accidental Film Co  Ltd",
    "wof:placetype":"venue"
},
  "geometry": {"coordinates":[-0.1345199943,51.5153808594],"type":"Point"}
}