{
  "type": "Feature",
  "properties": {
    "addr:full":"Ramada Hotel & Resort, Robinswood Hill Gloucester Gloucestershire GL4 6EA",
    "addr:postcode":"gl4 6ea",
    "addr:street":"Robinswood Hill",
    "iso:country":"GB",
    "sg:address":"Ramada Hotel & Resort, Robinswood Hill",
    "sg:city":"Gloucester",
    "sg:classifiers":[
        {
            "category":"Sports & Exercise",
            "subcategory":"Gym",
            "type":"Entertainment"
        }
    ],
    "sg:phone":"+44 1452 415242",
    "sg:postcode":"GL4 6EA",
    "sg:province":"Gloucestershire",
    "sg:tags":[
        "fitness",
        "health",
        "centre"
    ],
    "wof:name":"Sebastian Coe Health Club",
    "wof:placetype":"venue"
},
  "geometry": {"coordinates":[-2.2195999622,51.8354187012],"type":"Point"}
}