{
  "type": "Feature",
  "properties": {
    "addr:full":"133 Lordship Lane, East Dulwich London Greater London SE22 8HX",
    "addr:housenumber":"133",
    "addr:postcode":"se22 8hx",
    "addr:street":"Lordship Lane",
    "iso:country":"GB",
    "sg:address":"133 Lordship Lane, East Dulwich",
    "sg:city":"London",
    "sg:classifiers":[
        {
            "category":"Shopping",
            "subcategory":"Baby Store",
            "type":"Retail Goods"
        }
    ],
    "sg:phone":"+44 20 8693 5575",
    "sg:postcode":"SE22 8HX",
    "sg:province":"Greater London",
    "sg:tags":[
        "nursery",
        "accessory"
    ],
    "wof:name":"Hey Diddle Diddle",
    "wof:placetype":"venue"
},
  "geometry": {"coordinates":[-0.0757350028,51.456577301],"type":"Point"}
}