{
  "type": "Feature",
  "properties": {
    "addr:full":"71 Northgate Wakefield West Yorkshire WF1 3BS",
    "addr:housenumber":"71",
    "addr:postcode":"wf1 3bs",
    "addr:street":"Northgate",
    "iso:country":"GB",
    "sg:address":"71 Northgate",
    "sg:city":"Wakefield",
    "sg:classifiers":[
        {
            "category":"Government",
            "subcategory":"Office",
            "type":"Public Place"
        }
    ],
    "sg:phone":"+44 1924 302185",
    "sg:postcode":"WF1 3BS",
    "sg:province":"West Yorkshire",
    "sg:tags":[
        "marriage",
        "death",
        "births",
        "local"
    ],
    "wof:name":"Wakefield Register Office",
    "wof:placetype":"venue"
},
  "geometry": {"coordinates":[-1.500175,53.685143],"type":"Point"}
}