{
  "type": "Feature",
  "properties": {
    "addr:full":"21 Peterborough Avenue Oakham Leicestershire LE15 6EB",
    "addr:housenumber":"21",
    "addr:postcode":"le15 6eb",
    "addr:street":"Peterborough Avenue",
    "iso:country":"GB",
    "sg:address":"21 Peterborough Avenue",
    "sg:city":"Oakham",
    "sg:classifiers":[
        {
            "category":"Professional",
            "subcategory":"Employment Agencies",
            "type":"Services"
        }
    ],
    "sg:postcode":"LE15 6EB",
    "sg:province":"Leicestershire",
    "sg:tags":[
        "consultant"
    ],
    "wof:name":"C N A Executive Search (Rutland)",
    "wof:placetype":"venue"
},
  "geometry": {"coordinates":[-0.721227,52.671005],"type":"Point"}
}