{
  "type": "Feature",
  "properties": {
    "addr:full":"10 Stonehouse Avenue Willenhall West Midlands WV13 1AP",
    "addr:housenumber":"10",
    "addr:postcode":"wv13 1ap",
    "addr:street":"Stonehouse Avenue",
    "iso:country":"GB",
    "sg:address":"10 Stonehouse Avenue",
    "sg:city":"Willenhall",
    "sg:classifiers":[
        {
            "category":"Wholesale",
            "subcategory":"Machinery & Supplies",
            "type":"Manufacturing & Wholesale Goods"
        }
    ],
    "sg:phone":"+44 1902 634681",
    "sg:postcode":"WV13 1AP",
    "sg:province":"West Midlands",
    "sg:tags":[
        "control",
        "instrument",
        "industrial",
        "-"
    ],
    "wof:name":"Tuf Work & Safety Wear",
    "wof:placetype":"venue"
},
  "geometry": {"coordinates":[-2.060502,52.593513],"type":"Point"}
}