{
  "type": "Feature",
  "properties": {
    "iso:country":"GB",
    "sg:address":"P H I Ho, Enterprise Rd",
    "sg:city":"Southampton",
    "sg:classifiers":[
        {
            "category":"Utilities",
            "subcategory":"Fuel Oil & Lpg",
            "type":"Services"
        }
    ],
    "sg:phone":"+44 23 8076 9449",
    "sg:postcode":"SO16 7NS",
    "sg:province":"Hampshire",
    "sg:tags":[
        "gas"
    ],
    "wof:name":"Oilfield Systems Ltd",
    "wof:placetype":"venue"
},
  "geometry": {"coordinates":[-1.4251999855,50.9613800049],"type":"Point"}
}