{
  "type": "Feature",
  "properties": {
    "addr:full":"1 Giles Place Hexham Northumberland NE46 3QF",
    "addr:housenumber":"1",
    "addr:postcode":"ne46 3qf",
    "addr:street":"Giles Place",
    "iso:country":"GB",
    "sg:address":"1 Giles Place",
    "sg:city":"Hexham",
    "sg:classifiers":[
        {
            "category":"Banks & Credit Unions",
            "subcategory":"Financial Services",
            "type":"Services"
        }
    ],
    "sg:phone":"+44 1434 606853",
    "sg:postcode":"NE46 3QF",
    "sg:province":"Northumberland",
    "sg:tags":[
        "adviser"
    ],
    "wof:name":"Saxon Financial Advice Ltd.",
    "wof:placetype":"venue"
},
  "geometry": {"coordinates":[-2.1135189533,54.9735717773],"type":"Point"}
}