{
  "type": "Feature",
  "properties": {
    "addr:full":"Riverside Cottage, Warnford Rd, Corhampton Southampton Hampshire SO32 3ND",
    "addr:postcode":"so32 3nd",
    "addr:street":"Warnford Rd",
    "iso:country":"GB",
    "sg:address":"Riverside Cottage, Warnford Rd, Corhampton",
    "sg:city":"Southampton",
    "sg:classifiers":[
        {
            "category":"Professional",
            "subcategory":"Management & Consulting",
            "type":"Services"
        }
    ],
    "sg:phone":"+44 1489 877199",
    "sg:postcode":"SO32 3ND",
    "sg:province":"Hampshire",
    "sg:tags":[
        "consultant",
        "business"
    ],
    "wof:name":"Gilco Associates",
    "wof:placetype":"venue"
},
  "geometry": {"coordinates":[-1.1333470345,50.9782485962],"type":"Point"}
}