{
  "type": "Feature",
  "properties": {
    "addr:full":"Waterloo House, 56-60 High St Witney Oxfordshire OX8 6HJ",
    "addr:housenumber":"56-60",
    "addr:postcode":"ox8 6hj",
    "addr:street":"High St",
    "iso:country":"GB",
    "sg:address":"Waterloo House, 56-60 High St",
    "sg:city":"Witney",
    "sg:classifiers":[
        {
            "category":"Professional",
            "subcategory":"Employment Agencies",
            "type":"Services"
        }
    ],
    "sg:phone":"+44 1993 700986",
    "sg:postcode":"OX8 6HJ",
    "sg:province":"Oxfordshire",
    "sg:tags":[
        "consultant"
    ],
    "wof:name":"PCM Recruitment",
    "wof:placetype":"venue"
},
  "geometry": {"coordinates":[-1.483940959,51.7871627808],"type":"Point"}
}