{
  "type": "Feature",
  "properties": {
    "addr:full":"1-2 Hardwick St Clerkenwell Greater London EC1R 4RD",
    "addr:housenumber":"1-2",
    "addr:postcode":"ec1r 4rd",
    "addr:street":"Hardwick St",
    "iso:country":"GB",
    "sg:address":"1-2 Hardwick St",
    "sg:city":"Clerkenwell",
    "sg:classifiers":[
        {
            "category":"Professional",
            "subcategory":"Printing & Photocopies",
            "type":"Services"
        }
    ],
    "sg:phone":"+44 20 7837 4441",
    "sg:postcode":"EC1R 4RD",
    "sg:province":"Greater London",
    "sg:tags":[
        "printer"
    ],
    "wof:name":"M B Litho",
    "wof:placetype":"venue"
},
  "geometry": {"coordinates":[-0.109053,51.527534],"type":"Point"}
}