{
  "type": "Feature",
  "properties": {
    "addr:full":"33 Greenfields, St Neots Huntingdon Bedfordshire PE19 1TD",
    "addr:housenumber":"33",
    "addr:postcode":"pe19 1td",
    "addr:street":"Greenfields",
    "iso:country":"GB",
    "sg:address":"33 Greenfields, St Neots",
    "sg:city":"Huntingdon",
    "sg:classifiers":[
        {
            "category":"Building & Trades",
            "subcategory":"Plumbing",
            "type":"Services"
        }
    ],
    "sg:postcode":"PE19 1TD",
    "sg:province":"Bedfordshire",
    "sg:tags":[
        "central",
        "heating"
    ],
    "wof:name":"J R Thompson Plumbing & Heating",
    "wof:placetype":"venue"
},
  "geometry": {"coordinates":[-0.254052,52.231529],"type":"Point"}
}