{
  "type": "Feature",
  "properties": {
    "addr:full":"373 London Rd Warrington Cheshire WA4 5HP",
    "addr:housenumber":"373",
    "addr:postcode":"wa4 5hp",
    "addr:street":"London Rd",
    "iso:country":"GB",
    "sg:address":"373 London Rd",
    "sg:city":"Warrington",
    "sg:classifiers":[
        {
            "category":"Professional",
            "subcategory":"Management & Consulting",
            "type":"Services"
        }
    ],
    "sg:phone":"+44 1925 268489",
    "sg:postcode":"WA4 5HP",
    "sg:province":"Cheshire",
    "sg:tags":[
        "marketing",
        "consultant"
    ],
    "wof:name":"Robert Milner Associates",
    "wof:placetype":"venue"
},
  "geometry": {"coordinates":[-2.5766909122,53.3524093628],"type":"Point"}
}