{
  "type": "Feature",
  "properties": {
    "iso:country":"GB",
    "sg:address":"16 Lancaster Court, Fulham",
    "sg:city":"London",
    "sg:classifiers":[
        {
            "category":"Banks & Credit Unions",
            "subcategory":"Financial Services",
            "type":"Services"
        }
    ],
    "sg:postcode":"SW6 5TB",
    "sg:province":"Greater London",
    "sg:tags":[
        "consultant"
    ],
    "wof:name":"Weca Investments Ltd",
    "wof:placetype":"venue"
},
  "geometry": {"coordinates":[-0.178881,51.511452],"type":"Point"}
}