{
  "type": "Feature",
  "properties": {
    "addr:full":"25 Westby Street, Lytham Lytham St Annes Lancashire FY8 5JF",
    "addr:housenumber":"25",
    "addr:postcode":"fy8 5jf",
    "addr:street":"Westby Street;St Annes",
    "iso:country":"GB",
    "sg:address":"25 Westby Street, Lytham",
    "sg:city":"Lytham St Annes",
    "sg:classifiers":[
        {
            "category":"Health Services",
            "subcategory":"Health Practitioner",
            "type":"Services"
        }
    ],
    "sg:postcode":"FY8 5JF",
    "sg:province":"Lancashire",
    "sg:tags":[
        "physiotherapist"
    ],
    "wof:name":"Grant Smith Associates",
    "wof:placetype":"venue"
},
  "geometry": {"coordinates":[-2.9615130424,53.7382545471],"type":"Point"}
}