{
  "type": "Feature",
  "properties": {
    "addr:full":"Braunton Road Barnstaple Devon EX31 1JY",
    "addr:postcode":"ex31 1jy",
    "addr:street":"Braunton Road",
    "iso:country":"GB",
    "sg:address":"Braunton Road",
    "sg:city":"Barnstaple",
    "sg:classifiers":[
        {
            "category":"Professional",
            "subcategory":"Business Services",
            "type":"Services"
        }
    ],
    "sg:postcode":"EX31 1JY",
    "sg:province":"Devon",
    "sg:tags":[
        "tile",
        "stockist"
    ],
    "wof:name":"Bath & Tile Centre",
    "wof:placetype":"venue"
},
  "geometry": {"coordinates":[-4.0788578987,51.0878562927],"type":"Point"}
}