{
  "type": "Feature",
  "properties": {
    "iso:country":"GB",
    "sg:address":"62 New Cavendish Street",
    "sg:city":"London",
    "sg:classifiers":[
        {
            "category":"Communications",
            "type":"Services"
        }
    ],
    "sg:postcode":"W1G 8TA",
    "sg:province":"Greater London",
    "sg:tags":[
        "broadcasting"
    ],
    "wof:name":"Audioframe Ltd.",
    "wof:placetype":"venue"
},
  "geometry": {"coordinates":[-0.148422,51.51899],"type":"Point"}
}