{
  "type": "Feature",
  "properties": {
    "iso:country":"GB",
    "sg:address":"380 Silbury Court, Silbury Blvd",
    "sg:city":"Milton Keynes",
    "sg:classifiers":[
        {
            "category":"Professional",
            "subcategory":"Employment Agencies",
            "type":"Services"
        }
    ],
    "sg:phone":"+44 1908 672666",
    "sg:postcode":"MK9 2AF",
    "sg:province":"Buckinghamshire",
    "sg:tags":[
        "consultant"
    ],
    "wof:name":"Quality Personnel Services Ltd.",
    "wof:placetype":"venue"
},
  "geometry": {"coordinates":[-0.763221,52.041218],"type":"Point"}
}