{
  "type": "Feature",
  "properties": {
    "iso:country":"GB",
    "sg:address":"Unit B2, 83 Copers Cope Road",
    "sg:city":"Beckenham",
    "sg:classifiers":[
        {
            "category":"Professional",
            "subcategory":"Printing & Photocopies",
            "type":"Services"
        }
    ],
    "sg:phone":"+44 20 8650 6050",
    "sg:postcode":"BR3 1NR",
    "sg:province":"Kent",
    "sg:tags":[
        "printer"
    ],
    "wof:name":"Linnat Printing Services Ltd.",
    "wof:placetype":"venue"
},
  "geometry": {"coordinates":[-0.0337850004,51.4167938232],"type":"Point"}
}