{
  "type": "Feature",
  "properties": {
    "addr:full":"Unit 4 Royal Works, Elsinore Road Manchester Cheshire M16 0NF",
    "addr:housenumber":"unit 4",
    "addr:postcode":"m16 0nf",
    "addr:street":"Royal Works Elsinore Road",
    "iso:country":"GB",
    "sg:address":"Unit 4 Royal Works, Elsinore Road",
    "sg:city":"Manchester",
    "sg:classifiers":[
        {
            "category":"Retail",
            "subcategory":"Auto Repair",
            "type":"Services"
        }
    ],
    "sg:phone":"+44 161 929 9113",
    "sg:postcode":"M16 0NF",
    "sg:province":"Cheshire",
    "sg:tags":[
        "modification",
        "garage"
    ],
    "wof:name":"Mr Bug",
    "wof:placetype":"venue"
},
  "geometry": {"coordinates":[-2.273349,53.452888],"type":"Point"}
}