{
  "type": "Feature",
  "properties": {
    "iso:country":"GB",
    "sg:address":"100 Acre Moss Lane",
    "sg:city":"Morecambe",
    "sg:classifiers":[
        {
            "category":"Shopping",
            "subcategory":"News",
            "type":"Retail Goods"
        }
    ],
    "sg:phone":"+44 1524 412537",
    "sg:postcode":"LA4 4ND",
    "sg:province":"Lancashire",
    "sg:tags":[
        "newsagent"
    ],
    "wof:name":"K & J Whittaker",
    "wof:placetype":"venue"
},
  "geometry": {"coordinates":[-2.869682,54.064301],"type":"Point"}
}