{
  "type": "Feature",
  "properties": {
    "addr:full":"The Grove, Pipers Lane Harpenden Hertfordshire AL5 1AJ",
    "addr:postcode":"al5 1aj",
    "addr:street":"The Grove Pipers Lane",
    "iso:country":"GB",
    "sg:address":"The Grove, Pipers Lane",
    "sg:city":"Harpenden",
    "sg:classifiers":[
        {
            "category":"Organizations",
            "subcategory":"Non-profit Organization",
            "type":"Services"
        }
    ],
    "sg:phone":"+44 1582 762441",
    "sg:postcode":"AL5 1AJ",
    "sg:province":"Hertfordshire",
    "sg:tags":[
        "fundraising",
        "charity"
    ],
    "wof:name":"Craigmyle & Co. Ltd.",
    "wof:placetype":"venue"
},
  "geometry": {"coordinates":[-0.327134,51.805748],"type":"Point"}
}