{
  "type": "Feature",
  "properties": {
    "iso:country":"GB",
    "sg:address":"40 Great James Street",
    "sg:city":"London",
    "sg:classifiers":[
        {
            "category":"Professional",
            "subcategory":"Accounting & Tax Preparation",
            "type":"Services"
        }
    ],
    "sg:phone":"+44 20 7430 9292",
    "sg:postcode":"WC1N 3HB",
    "sg:province":"Greater London",
    "sg:tags":[
        "accountant"
    ],
    "wof:name":"S G Banister & Co",
    "wof:placetype":"venue"
},
  "geometry": {"coordinates":[-0.116743,51.520767],"type":"Point"}
}