{
  "type": "Feature",
  "properties": {
    "addr:full":"Whitehaven Road Cleator Moor Cumbria CA25 5QN",
    "addr:postcode":"ca25 5qn",
    "addr:street":"Whitehaven Road",
    "iso:country":"GB",
    "sg:address":"Whitehaven Road",
    "sg:city":"Cleator Moor",
    "sg:classifiers":[
        {
            "category":"Shopping",
            "subcategory":"News",
            "type":"Retail Goods"
        }
    ],
    "sg:phone":"+44 1946 810374",
    "sg:postcode":"CA25 5QN",
    "sg:province":"Cumbria",
    "sg:tags":[
        "newsagent"
    ],
    "wof:name":"Bowthorn Stores",
    "wof:placetype":"venue"
},
  "geometry": {"coordinates":[-3.529644,54.526363],"type":"Point"}
}