{
  "type": "Feature",
  "properties": {
    "addr:full":"Glenthorne House, 5-17 Hammersmith Gro London Greater London W6 0LG",
    "addr:housenumber":"5-17",
    "addr:postcode":"w6 0lg",
    "addr:street":"Hammersmith Gro",
    "iso:country":"GB",
    "sg:address":"Glenthorne House, 5-17 Hammersmith Gro",
    "sg:city":"London",
    "sg:classifiers":[
        {
            "category":"Professional",
            "subcategory":"Business Services",
            "type":"Services"
        }
    ],
    "sg:phone":"+44 20 8741 9333",
    "sg:postcode":"W6 0LG",
    "sg:province":"Greater London",
    "sg:tags":[
        "distributor",
        "film"
    ],
    "wof:name":"Cic Video Uk",
    "wof:placetype":"venue"
},
  "geometry": {"coordinates":[-0.22641,51.494011],"type":"Point"}
}