{
  "type": "Feature",
  "properties": {
    "addr:full":"Unit 2, Hale Industrial Estate Tipton West Midlands DY4 7PQ",
    "addr:housenumber":"unit 2",
    "addr:postcode":"dy4 7pq",
    "addr:street":"Hale Industrial Estate Tipton",
    "iso:country":"GB",
    "sg:address":"Unit 2, Hale Industrial Estate",
    "sg:city":"Tipton",
    "sg:classifiers":[
        {
            "category":"Bars & Pubs",
            "subcategory":"Wine Bar",
            "type":"Food & Drink"
        }
    ],
    "sg:phone":"+44 121 520 8883",
    "sg:postcode":"DY4 7PQ",
    "sg:province":"West Midlands",
    "sg:tags":[
        "industrial",
        "aerosol"
    ],
    "wof:name":"Minstergrove Ltd.",
    "wof:placetype":"venue"
},
  "geometry": {"coordinates":[-2.028951,52.536667],"type":"Point"}
}