{
  "type": "Feature",
  "properties": {
    "addr:full":"York House, 2-4 York Rd Felixstowe Suffolk IP11 7SS",
    "addr:housenumber":"2-4",
    "addr:postcode":"ip11 7ss",
    "addr:street":"York Rd",
    "iso:country":"GB",
    "sg:address":"York House, 2-4 York Rd",
    "sg:city":"Felixstowe",
    "sg:classifiers":[
        {
            "category":"Professional",
            "type":"Services"
        }
    ],
    "sg:phone":"+44 1394 671516",
    "sg:postcode":"IP11 7SS",
    "sg:province":"Suffolk",
    "sg:tags":[
        "repair",
        "tech",
        "maintenance"
    ],
    "wof:name":"Computer Network Services",
    "wof:placetype":"venue"
},
  "geometry": {"coordinates":[1.35207,51.9645],"type":"Point"}
}