{
  "type": "Feature",
  "properties": {
    "addr:full":"Unit 4 St Marys Centre, Thornbury Bristol Somerset BS20 6QP",
    "addr:housenumber":"unit 4 st marys centre",
    "addr:postcode":"bs20 6qp",
    "iso:country":"GB",
    "sg:address":"Unit 4 St Marys Centre, Thornbury",
    "sg:city":"Bristol",
    "sg:classifiers":[
        {
            "category":"Shopping",
            "subcategory":"Clothing, Apparel, & Fashions",
            "type":"Retail Goods"
        }
    ],
    "sg:phone":"+44 1454 419989",
    "sg:postcode":"BS20 6QP",
    "sg:province":"Somerset",
    "sg:tags":[
        "ladieswear"
    ],
    "wof:name":"Richleys",
    "wof:placetype":"venue"
},
  "geometry": {"coordinates":[-2.769319,51.476089],"type":"Point"}
}