{
  "type": "Feature",
  "properties": {
    "addr:full":"Downingbury Farm, Maidstone Road, Pembury Tunbridge Wells East Sussex TN2 4AD",
    "addr:postcode":"tn2 4ad",
    "addr:street":"Maidstone Road",
    "iso:country":"GB",
    "sg:address":"Downingbury Farm, Maidstone Road, Pembury",
    "sg:city":"Tunbridge Wells",
    "sg:classifiers":[
        {
            "category":"Food & Beverages",
            "subcategory":"Farmers Market",
            "type":"Retail Goods"
        }
    ],
    "sg:phone":"+44 1892 824282",
    "sg:postcode":"TN2 4AD",
    "sg:province":"East Sussex",
    "sg:tags":[
        "farm",
        "shop",
        "pyo"
    ],
    "wof:name":"Downingbury Farm",
    "wof:placetype":"venue"
},
  "geometry": {"coordinates":[0.3172099888,51.1432151794],"type":"Point"}
}