{
  "type": "Feature",
  "properties": {
    "iso:country":"GB",
    "sg:address":"Unit C2, Walton Road",
    "sg:city":"Portsmouth",
    "sg:classifiers":[
        {
            "category":"Freight",
            "type":"Transportation"
        }
    ],
    "sg:phone":"+44 23 9221 4216",
    "sg:postcode":"PO6 1TW",
    "sg:province":"Hampshire",
    "sg:tags":[
        "forwarders"
    ],
    "wof:name":"Fraser Freight",
    "wof:placetype":"venue"
},
  "geometry": {"coordinates":[-1.049375,50.837166],"type":"Point"}
}