{
  "type": "Feature",
  "properties": {
    "iso:country":"GB",
    "sg:address":"High Street, Rhuddlan",
    "sg:city":"Rhyl",
    "sg:classifiers":[
        {
            "category":"Shopping",
            "subcategory":"Shoes",
            "type":"Retail Goods"
        }
    ],
    "sg:postcode":"LL18 2UA",
    "sg:province":"Conwy",
    "wof:name":"Mark Stokes",
    "wof:placetype":"venue"
},
  "geometry": {"coordinates":[-3.4668939114,53.2909851074],"type":"Point"}
}