{
  "type": "Feature",
  "properties": {
    "iso:country":"GB",
    "sg:address":"1 Howden Ancrum",
    "sg:city":"Jedburgh",
    "sg:classifiers":[
        {
            "category":"Shopping",
            "subcategory":"Pharmacy",
            "type":"Retail Goods"
        }
    ],
    "sg:postcode":"TD8 6TX",
    "sg:province":"Scottish Borders",
    "sg:tags":[
        "medical"
    ],
    "wof:name":"Morter,Mike,",
    "wof:placetype":"venue"
},
  "geometry": {"coordinates":[-2.5473120213,55.4725227356],"type":"Point"}
}