{
  "type": "Feature",
  "properties": {
    "iso:country":"GB",
    "sg:address":"Unit 1, Stonebridge Shopping Precint",
    "sg:city":"London",
    "sg:classifiers":[
        {
            "category":"Professional",
            "subcategory":"Employment Agencies",
            "type":"Services"
        }
    ],
    "sg:phone":"+44 20 8965 5835",
    "sg:postcode":"NW10 8LT",
    "sg:province":"Greater London",
    "sg:tags":[
        "consultant"
    ],
    "wof:name":"Step",
    "wof:placetype":"venue"
},
  "geometry": {"coordinates":[-0.2615779936,51.5455627441],"type":"Point"}
}