{
  "type": "Feature",
  "properties": {
    "iso:country":"GB",
    "sg:address":"Halfpenny Green, Bobbington",
    "sg:city":"Stourbridge",
    "sg:classifiers":[
        {
            "category":"Restaurant",
            "type":"Food & Drink"
        }
    ],
    "sg:phone":"+44 1384 221464",
    "sg:postcode":"DY7 5DP",
    "sg:province":"Shropshire",
    "wof:name":"John & Doreen Morgan",
    "wof:placetype":"venue"
},
  "geometry": {"coordinates":[-2.283994,52.511806],"type":"Point"}
}