{
  "type": "Feature",
  "properties": {
    "addr:full":"50 Clayton St West Newcastle-upon-tyne Tyne and Wear NE1 4EX",
    "addr:housenumber":"50",
    "addr:postcode":"ne1 4ex",
    "addr:street":"Clayton St",
    "iso:country":"GB",
    "sg:address":"50 Clayton St West",
    "sg:city":"Newcastle-upon-tyne",
    "sg:classifiers":[
        {
            "category":"Retail",
            "subcategory":"Auto Rental",
            "type":"Services"
        }
    ],
    "sg:phone":"+44 191 232 5929",
    "sg:postcode":"NE1 4EX",
    "sg:province":"Tyne and Wear",
    "sg:tags":[
        "car"
    ],
    "wof:name":"Auto Hire",
    "wof:placetype":"venue"
},
  "geometry": {"coordinates":[-1.6197940111,54.9694862366],"type":"Point"}
}