{
  "type": "Feature",
  "properties": {
    "iso:country":"GB",
    "sg:address":"Lane Farm, Arley Lane, Shatterford",
    "sg:city":"Bewdley",
    "sg:classifiers":[
        {
            "category":"Farming",
            "subcategory":"Farm",
            "type":"Manufacturing & Wholesale Goods"
        }
    ],
    "sg:postcode":"DY12 1SB",
    "sg:province":"Shropshire",
    "sg:tags":[
        "mixed",
        "crop"
    ],
    "wof:name":"C J & J Braithwaite & Sons",
    "wof:placetype":"venue"
},
  "geometry": {"coordinates":[-2.344289,52.419842],"type":"Point"}
}