{
  "type": "Feature",
  "properties": {
    "addr:full":"221 Lauderdale Tower London Greater London EC2Y 8BY",
    "addr:housenumber":"221",
    "addr:postcode":"ec2y 8by",
    "addr:street":"Lauderdale Tower",
    "iso:country":"GB",
    "sg:address":"221 Lauderdale Tower",
    "sg:city":"London",
    "sg:classifiers":[
        {
            "category":"Professional",
            "subcategory":"Management & Consulting",
            "type":"Services"
        }
    ],
    "sg:phone":"+44 20 7374 4446",
    "sg:postcode":"EC2Y 8BY",
    "sg:province":"Greater London",
    "sg:tags":[
        "consultant",
        "business"
    ],
    "wof:name":"Strategic Consulting Ltd.",
    "wof:placetype":"venue"
},
  "geometry": {"coordinates":[-0.09678,51.519852],"type":"Point"}
}