{
  "type": "Feature",
  "properties": {
    "addr:full":"6 Sweeney Cres London Greater London SE1 2DS",
    "addr:housenumber":"6",
    "addr:postcode":"se1 2ds",
    "addr:street":"Sweeney Cres",
    "iso:country":"GB",
    "sg:address":"6 Sweeney Cres",
    "sg:city":"London",
    "sg:classifiers":[
        {
            "category":"Food & Beverages",
            "subcategory":"Supermarket",
            "type":"Retail Goods"
        }
    ],
    "sg:postcode":"SE1 2DS",
    "sg:province":"Greater London",
    "wof:name":"Sweeney General Store",
    "wof:placetype":"venue"
},
  "geometry": {"coordinates":[-0.07321,51.49987],"type":"Point"}
}