{
  "type": "Feature",
  "properties": {
    "iso:country":"GB",
    "sg:address":"Winter Rule & Partners, Lowin House, Tregolls Road",
    "sg:city":"Truro",
    "sg:classifiers":[
        {
            "category":"Health Services",
            "subcategory":"Chiropractor",
            "type":"Services"
        }
    ],
    "sg:postcode":"TR1 2NA",
    "sg:province":"Cornwall",
    "wof:name":"Cornwall Chiropractic Services Ltd",
    "wof:placetype":"venue"
},
  "geometry": {"coordinates":[-5.04415,50.26482],"type":"Point"}
}