{
  "type": "Feature",
  "properties": {
    "addr:full":"225 Warrington Road, Penketh Warrington Cheshire WA5 2RX",
    "addr:housenumber":"225",
    "addr:postcode":"wa5 2rx",
    "addr:street":"Warrington Road",
    "iso:country":"GB",
    "sg:address":"225 Warrington Road, Penketh",
    "sg:city":"Warrington",
    "sg:classifiers":[
        {
            "category":"Personal",
            "subcategory":"Beauty Salon",
            "type":"Services"
        }
    ],
    "sg:phone":"+44 1925 723601",
    "sg:postcode":"WA5 2RX",
    "sg:province":"Cheshire",
    "wof:name":"Penketh Hairdressers",
    "wof:placetype":"venue"
},
  "geometry": {"coordinates":[-2.6633601189,53.3832130432],"type":"Point"}
}