{
  "type": "Feature",
  "properties": {
    "addr:full":"Upper Wern Y Pentre, Clyro Hereford Herefordshire HR3 5SN",
    "addr:postcode":"hr3 5sn",
    "addr:street":"Upper Wern Y Pentre",
    "iso:country":"GB",
    "sg:address":"Upper Wern Y Pentre, Clyro",
    "sg:city":"Hereford",
    "sg:classifiers":[
        {
            "category":"Farming",
            "subcategory":"Livestock Farm",
            "type":"Manufacturing & Wholesale Goods"
        }
    ],
    "sg:phone":"+44 1497 820591",
    "sg:postcode":"HR3 5SN",
    "sg:province":"Herefordshire",
    "sg:tags":[
        "others"
    ],
    "wof:name":"J G Thomas & Son",
    "wof:placetype":"venue"
},
  "geometry": {"coordinates":[-3.1479051113,52.0869102478],"type":"Point"}
}