{
  "type": "Feature",
  "properties": {
    "iso:country":"GB",
    "sg:address":"Kettlebrook House, Wash Grn, Wirksworth",
    "sg:city":"Matlock",
    "sg:classifiers":[
        {
            "category":"Professional",
            "subcategory":"Testing Lab",
            "type":"Services"
        }
    ],
    "sg:phone":"+44 1629 824628",
    "sg:postcode":"DE4 4FD",
    "sg:province":"Derbyshire",
    "sg:tags":[
        "inspection",
        "calibration"
    ],
    "wof:name":"First Order Beats Ltd.",
    "wof:placetype":"venue"
},
  "geometry": {"coordinates":[-1.5740560293,53.0822143555],"type":"Point"}
}