{
  "type": "Feature",
  "properties": {
    "addr:full":"London Fruit Exchange, Brushfield Street London Greater London E1 6EX",
    "addr:postcode":"e1 6ex",
    "addr:street":"Brushfield Street",
    "iso:country":"GB",
    "sg:address":"London Fruit Exchange, Brushfield Street",
    "sg:city":"London",
    "sg:classifiers":[
        {
            "category":"Arena",
            "subcategory":"Sports Club",
            "type":"Entertainment"
        }
    ],
    "sg:phone":"+44 20 7247 2963",
    "sg:postcode":"E1 6EX",
    "sg:province":"Greater London",
    "wof:name":"South of England Athletics Association",
    "wof:placetype":"venue"
},
  "geometry": {"coordinates":[-0.0754199997,51.5187683105],"type":"Point"}
}