{
  "type": "Feature",
  "properties": {
    "iso:country":"GB",
    "sg:address":"4 Waterloo Street, Clifton",
    "sg:city":"Bristol",
    "sg:classifiers":[
        {
            "category":"Professional",
            "subcategory":"Employment Agencies",
            "type":"Services"
        }
    ],
    "sg:phone":"+44 117 929 1972",
    "sg:postcode":"BS8 4BT",
    "sg:province":"City of Bristol",
    "sg:tags":[
        "consultant"
    ],
    "wof:name":"Wilson Mitchell Associates",
    "wof:placetype":"venue"
},
  "geometry": {"coordinates":[-2.620379,51.454914],"type":"Point"}
}