{
  "type": "Feature",
  "properties": {
    "iso:country":"GB",
    "sg:address":"New Mills Farm",
    "sg:city":"Barnstaple",
    "sg:classifiers":[
        {
            "category":"Military Area",
            "subcategory":"Air Force Base",
            "type":"Public Place"
        }
    ],
    "sg:phone":"+44 1271 850859",
    "sg:postcode":"EX32 7JZ",
    "sg:province":"Devon",
    "sg:tags":[
        "water",
        "treatment"
    ],
    "wof:name":"A Giffard",
    "wof:placetype":"venue"
},
  "geometry": {"coordinates":[-4.0563139915,51.0827293396],"type":"Point"}
}