{
  "type": "Feature",
  "properties": {
    "addr:full":"St.radigunds Rd Dover Kent CT17 0JZ",
    "addr:postcode":"ct17 0jz",
    "addr:street":"St.Radigunds Rd",
    "iso:country":"GB",
    "sg:address":"St.radigunds Rd",
    "sg:city":"Dover",
    "sg:classifiers":[
        {
            "category":"Recreation",
            "type":"Entertainment"
        }
    ],
    "sg:phone":"+44 1304 204516",
    "sg:postcode":"CT17 0JZ",
    "sg:province":"Kent",
    "sg:tags":[
        "snooker",
        "billiards",
        "hall",
        "pool"
    ],
    "wof:name":"Rowleys Club",
    "wof:placetype":"venue"
},
  "geometry": {"coordinates":[1.298218,51.135212],"type":"Point"}
}