{
  "type": "Feature",
  "properties": {
    "iso:country":"GB",
    "sg:address":"Plymouth Road, Crabtree",
    "sg:city":"Plymouth",
    "sg:classifiers":[
        {
            "category":"Landmark",
            "subcategory":"Tourist Information",
            "type":"Public Place"
        }
    ],
    "sg:phone":"+44 1752 266030",
    "sg:postcode":"PL3 6RN",
    "sg:province":"Devon",
    "wof:name":"Plymouth Discovery Centre Tourist Information",
    "wof:placetype":"venue"
},
  "geometry": {"coordinates":[-4.08788,50.390728],"type":"Point"}
}