{
  "type": "Feature",
  "properties": {
    "iso:country":"GB",
    "sg:address":"Coast Road",
    "sg:city":"Norwich",
    "sg:classifiers":[
        {
            "category":"Government",
            "subcategory":"Post Office",
            "type":"Public Place"
        }
    ],
    "sg:postcode":"NR12 0AP",
    "sg:province":"Norfolk",
    "wof:name":"Walcott Post Office Stores",
    "wof:placetype":"venue"
},
  "geometry": {"coordinates":[1.4729850292,52.8550949097],"type":"Point"}
}