{
  "type": "Feature",
  "properties": {
    "addr:full":"Old Rectory, Naunton Beauchamp Pershore Worcestershire WR10 2LQ",
    "addr:postcode":"wr10 2lq",
    "addr:street":"Beauchamp",
    "iso:country":"GB",
    "sg:address":"Old Rectory, Naunton Beauchamp",
    "sg:city":"Pershore",
    "sg:classifiers":[
        {
            "category":"Shopping",
            "subcategory":"Catalog Store",
            "type":"Retail Goods"
        }
    ],
    "sg:phone":"+44 1386 462745",
    "sg:postcode":"WR10 2LQ",
    "sg:province":"Worcestershire",
    "sg:tags":[
        "mail",
        "order"
    ],
    "wof:name":"Pincox Ltd.",
    "wof:placetype":"venue"
},
  "geometry": {"coordinates":[-2.056402,52.169804],"type":"Point"}
}