{
  "type": "Feature",
  "properties": {
    "addr:full":"Belgrave Terrace Aberdeen Aberdeen City AB25 2NS",
    "addr:postcode":"ab25 2ns",
    "addr:street":"Belgrave Terrace",
    "iso:country":"GB",
    "sg:address":"Belgrave Terrace",
    "sg:city":"Aberdeen",
    "sg:classifiers":[
        {
            "category":"Government",
            "subcategory":"Office",
            "type":"Public Place"
        }
    ],
    "sg:postcode":"AB25 2NS",
    "sg:province":"Aberdeen City",
    "sg:tags":[
        "education",
        "agency",
        "authority"
    ],
    "wof:name":"Childrens Services Network",
    "wof:placetype":"venue"
},
  "geometry": {"coordinates":[-2.1172449589,57.1489257812],"type":"Point"}
}