{
  "type": "Feature",
  "properties": {
    "addr:full":"15 Lee Rd Birmingham Worcestershire B47 5NY",
    "addr:housenumber":"15",
    "addr:postcode":"b47 5ny",
    "addr:street":"Lee Rd",
    "iso:country":"GB",
    "sg:address":"15 Lee Rd",
    "sg:city":"Birmingham",
    "sg:classifiers":[
        {
            "category":"Health Services",
            "subcategory":"Health Practitioner",
            "type":"Services"
        }
    ],
    "sg:phone":"+44 1564 822967",
    "sg:postcode":"B47 5NY",
    "sg:province":"Worcestershire",
    "sg:tags":[
        "hypnotherapists"
    ],
    "wof:name":"Paul Birley",
    "wof:placetype":"venue"
},
  "geometry": {"coordinates":[-1.8798240423,52.3921699524],"type":"Point"}
}