{
  "type": "Feature",
  "properties": {
    "addr:full":"25 High Street, Stokesley Middlesbrough North Yorkshire TS9 5AD",
    "addr:housenumber":"25",
    "addr:postcode":"ts9 5ad",
    "addr:street":"High Street",
    "iso:country":"GB",
    "sg:address":"25 High Street, Stokesley",
    "sg:city":"Middlesbrough",
    "sg:classifiers":[
        {
            "category":"Banks & Credit Unions",
            "subcategory":"Bank",
            "type":"Services"
        }
    ],
    "sg:phone":"+44 845 740 4404",
    "sg:postcode":"TS9 5AD",
    "sg:province":"North Yorkshire",
    "wof:name":"Midland Bank",
    "wof:placetype":"venue"
},
  "geometry": {"coordinates":[-1.1914319992,54.4698219299],"type":"Point"}
}