{
  "type": "Feature",
  "properties": {
    "addr:full":"33 Ruskin Rd Carshalton Surrey SM5 3DD",
    "addr:housenumber":"33",
    "addr:postcode":"sm5 3dd",
    "addr:street":"Ruskin Rd",
    "iso:country":"GB",
    "sg:address":"33 Ruskin Rd",
    "sg:city":"Carshalton",
    "sg:classifiers":[
        {
            "category":"Shopping",
            "subcategory":"Antiques",
            "type":"Retail Goods"
        }
    ],
    "sg:postcode":"SM5 3DD",
    "sg:province":"Surrey",
    "wof:name":"Ollies Folly",
    "wof:placetype":"venue"
},
  "geometry": {"coordinates":[-0.161085,51.363255],"type":"Point"}
}