{
  "type": "Feature",
  "properties": {
    "addr:full":"Unit 5 Hall Farm, Church Lane, Martlesham Woodbridge Suffolk IP12 4PQ",
    "addr:housenumber":"unit 5",
    "addr:postcode":"ip12 4pq",
    "addr:street":"Hall;Church Lane",
    "iso:country":"GB",
    "sg:address":"Unit 5 Hall Farm, Church Lane, Martlesham",
    "sg:city":"Woodbridge",
    "sg:classifiers":[
        {
            "category":"Manufacturing",
            "subcategory":"Wood Products",
            "type":"Manufacturing & Wholesale Goods"
        }
    ],
    "sg:phone":"+44 1394 388464",
    "sg:postcode":"IP12 4PQ",
    "sg:province":"Suffolk",
    "sg:tags":[
        "maker",
        "cabinet"
    ],
    "wof:name":"Phillip Watkins",
    "wof:placetype":"venue"
},
  "geometry": {"coordinates":[1.2786990404,52.0717048645],"type":"Point"}
}