{
  "type": "Feature",
  "properties": {
    "addr:full":"136 Scotland Road Nelson Lancashire BB9 7XT",
    "addr:housenumber":"136",
    "addr:postcode":"bb9 7xt",
    "addr:street":"Scotland Road",
    "iso:country":"GB",
    "sg:address":"136 Scotland Road",
    "sg:city":"Nelson",
    "sg:classifiers":[
        {
            "category":"Professional",
            "subcategory":"Business Services",
            "type":"Services"
        },
        {
            "category":"Casinos & Gambling",
            "type":"Entertainment"
        }
    ],
    "sg:phone":"+44 1282 616148",
    "sg:postcode":"BB9 7XT",
    "sg:province":"Lancashire",
    "sg:tags":[
        "turf",
        "accountant",
        "bookmaker"
    ],
    "wof:name":"Thompsons",
    "wof:placetype":"venue"
},
  "geometry": {"coordinates":[-2.2144799232,53.8409843445],"type":"Point"}
}