{
  "type": "Feature",
  "properties": {
    "addr:full":"1 Whitmore Close Sandhurst Berkshire GU47 0SE",
    "addr:housenumber":"1",
    "addr:postcode":"gu47 0se",
    "addr:street":"Whitmore Close",
    "iso:country":"GB",
    "sg:address":"1 Whitmore Close",
    "sg:city":"Sandhurst",
    "sg:classifiers":[
        {
            "category":"Professional",
            "subcategory":"Computer Services",
            "type":"Services"
        }
    ],
    "sg:postcode":"GU47 0SE",
    "sg:province":"Berkshire",
    "sg:tags":[
        "system",
        "software"
    ],
    "wof:name":"Eleco Controls Ltd",
    "wof:placetype":"venue"
},
  "geometry": {"coordinates":[-0.7827860117,51.3506202698],"type":"Point"}
}