{
  "type": "Feature",
  "properties": {
    "addr:full":"Bristol Customer Service Centre, 740 Waterside Dr Bristol City of Bristol BS99 5BD",
    "addr:housenumber":"740",
    "addr:postcode":"bs99 5bd",
    "addr:street":"Waterside Dr",
    "iso:country":"GB",
    "sg:address":"Bristol Customer Service Centre, 740 Waterside Dr",
    "sg:city":"Bristol",
    "sg:classifiers":[
        {
            "category":"Banks & Credit Unions",
            "subcategory":"Bank",
            "type":"Services"
        }
    ],
    "sg:phone":"+44 1454 896103",
    "sg:postcode":"BS99 5BD",
    "sg:province":"City of Bristol",
    "wof:name":"NatWest",
    "wof:placetype":"venue"
},
  "geometry": {"coordinates":[-2.5909,51.452438],"type":"Point"}
}