{
  "type": "Feature",
  "properties": {
    "iso:country":"GB",
    "sg:address":"45 The Green, Hasland",
    "sg:city":"Chesterfield",
    "sg:classifiers":[
        {
            "category":"Health Services",
            "subcategory":"Nursing And Care Facility",
            "type":"Services"
        }
    ],
    "sg:phone":"+44 1246 556321",
    "sg:postcode":"S41 0LW",
    "sg:province":"Derbyshire",
    "sg:tags":[
        "home"
    ],
    "wof:name":"The Green Nursing Home",
    "wof:placetype":"venue"
},
  "geometry": {"coordinates":[-1.408339,53.219257],"type":"Point"}
}