{
  "type": "Feature",
  "properties": {
    "iso:country":"GB",
    "sg:address":"Unit 3, Fence Avenue Industrial Estate",
    "sg:city":"Macclesfield",
    "sg:classifiers":[
        {
            "category":"Professional",
            "subcategory":"Detective & Security Services",
            "type":"Services"
        }
    ],
    "sg:phone":"+44 1625 613707",
    "sg:postcode":"SK10 1LT",
    "sg:province":"Cheshire",
    "sg:tags":[
        "alarm",
        "burglar",
        "system"
    ],
    "wof:name":"C J Security Systems Ltd.",
    "wof:placetype":"venue"
},
  "geometry": {"coordinates":[-2.1164450645,53.2614822388],"type":"Point"}
}