{
  "type": "Feature",
  "properties": {
    "iso:country":"GB",
    "sg:address":"12 South Molton Street",
    "sg:city":"London",
    "sg:classifiers":[
        {
            "category":"Shopping",
            "subcategory":"Clothing, Apparel, & Fashions",
            "type":"Retail Goods"
        }
    ],
    "sg:postcode":"W1K 5QN",
    "sg:province":"Greater London",
    "sg:tags":[
        "ladieswear"
    ],
    "wof:name":"Arte Ltd.",
    "wof:placetype":"venue"
},
  "geometry": {"coordinates":[-0.147818,51.513493],"type":"Point"}
}