{
  "type": "Feature",
  "properties": {
    "addr:full":"23 Elstree Avenue Chester Cheshire CH3 5HJ",
    "addr:housenumber":"23",
    "addr:postcode":"ch3 5hj",
    "addr:street":"Elstree Avenue",
    "iso:country":"GB",
    "sg:address":"23 Elstree Avenue",
    "sg:city":"Chester",
    "sg:classifiers":[
        {
            "category":"Personal",
            "subcategory":"Barber",
            "type":"Services"
        }
    ],
    "sg:phone":"+44 1244 349340",
    "sg:postcode":"CH3 5HJ",
    "sg:province":"Cheshire",
    "sg:tags":[
        "men's",
        "hairdresser"
    ],
    "wof:name":"Tim Hurst Mobile",
    "wof:placetype":"venue"
},
  "geometry": {"coordinates":[-2.85727,53.197453],"type":"Point"}
}