{
  "type": "Feature",
  "properties": {
    "addr:full":"36 Longley Lane, Northenden Manchester Greater Manchester M22 4JH",
    "addr:housenumber":"36",
    "addr:postcode":"m22 4jh",
    "addr:street":"Longley Lane",
    "iso:country":"GB",
    "sg:address":"36 Longley Lane, Northenden",
    "sg:city":"Manchester",
    "sg:classifiers":[
        {
            "category":"Fast Food",
            "type":"Food & Drink"
        }
    ],
    "sg:postcode":"M22 4JH",
    "sg:province":"Greater Manchester",
    "sg:tags":[
        "away",
        "take"
    ],
    "wof:name":"The Sandwich Shop",
    "wof:placetype":"venue"
},
  "geometry": {"coordinates":[-2.2617390156,53.4052505493],"type":"Point"}
}