{
  "type": "Feature",
  "properties": {
    "addr:full":"19 Old Road, Crayford Dartford Kent DA1 4DW",
    "addr:housenumber":"19",
    "addr:postcode":"da1 4dw",
    "addr:street":"Old Road",
    "iso:country":"GB",
    "sg:address":"19 Old Road, Crayford",
    "sg:city":"Dartford",
    "sg:classifiers":[
        {
            "category":"Food & Beverages",
            "subcategory":"Fruits & Vegetables",
            "type":"Retail Goods"
        },
        {
            "category":"Food & Beverages",
            "subcategory":"Groceries & Convenience Stores",
            "type":"Retail Goods"
        }
    ],
    "sg:phone":"+44 1322 553622",
    "sg:postcode":"DA1 4DW",
    "sg:province":"Kent",
    "sg:tags":[
        "grocer",
        "greengrocer"
    ],
    "wof:name":"Old Road Stores",
    "wof:placetype":"venue"
},
  "geometry": {"coordinates":[0.1658519953,51.4537849426],"type":"Point"}
}