{
  "type": "Feature",
  "properties": {
    "addr:full":"170 Whitehall Rd Gateshead Tyne and Wear NE8 1TP",
    "addr:housenumber":"170",
    "addr:postcode":"ne8 1tp",
    "addr:street":"Whitehall Rd",
    "iso:country":"GB",
    "sg:address":"170 Whitehall Rd",
    "sg:city":"Gateshead",
    "sg:classifiers":[
        {
            "category":"Health Services",
            "subcategory":"Doctor",
            "type":"Services"
        }
    ],
    "sg:phone":"+44 191 477 1147",
    "sg:postcode":"NE8 1TP",
    "sg:province":"Tyne and Wear",
    "sg:tags":[
        "practitioners"
    ],
    "wof:name":"Robert Harris",
    "wof:placetype":"venue"
},
  "geometry": {"coordinates":[-1.6087130308,54.9520988464],"type":"Point"}
}