{
  "type": "Feature",
  "properties": {
    "iso:country":"GB",
    "sg:address":"Newlands Medical Centre, Chorley New Road",
    "sg:city":"Bolton",
    "sg:classifiers":[
        {
            "category":"Health Services",
            "subcategory":"Doctor",
            "type":"Services"
        },
        {
            "category":"Sports & Exercise",
            "subcategory":"Gym",
            "type":"Entertainment"
        }
    ],
    "sg:phone":"+44 1204 493975",
    "sg:postcode":"BL1 5BP",
    "sg:province":"Lancashire",
    "sg:tags":[
        "fitness",
        "practitioners",
        "centre"
    ],
    "wof:name":"Diet (Uk)",
    "wof:placetype":"venue"
},
  "geometry": {"coordinates":[-2.426594,53.578289],"type":"Point"}
}