{
  "type": "Feature",
  "properties": {
    "addr:full":"6 King Street Cleckheaton West Yorkshire BD19 3JX",
    "addr:housenumber":"6",
    "addr:postcode":"bd19 3jx",
    "addr:street":"King Street",
    "iso:country":"GB",
    "sg:address":"6 King Street",
    "sg:city":"Cleckheaton",
    "sg:classifiers":[
        {
            "category":"Manufacturing",
            "subcategory":"Metals",
            "type":"Manufacturing & Wholesale Goods"
        }
    ],
    "sg:phone":"+44 1274 878657",
    "sg:postcode":"BD19 3JX",
    "sg:province":"West Yorkshire",
    "sg:tags":[
        "steel",
        "fabricator",
        "erectors"
    ],
    "wof:name":"Arcform Fabrications",
    "wof:placetype":"venue"
},
  "geometry": {"coordinates":[-1.7123630047,53.7258491516],"type":"Point"}
}