{
  "type": "Feature",
  "properties": {
    "addr:full":"35 Grays Road Stockton-on-tees Durham TS18 4LL",
    "addr:housenumber":"35",
    "addr:postcode":"ts18 4ll",
    "addr:street":"Grays Road",
    "iso:country":"GB",
    "sg:address":"35 Grays Road",
    "sg:city":"Stockton-on-tees",
    "sg:classifiers":[
        {
            "category":"Building & Trades",
            "subcategory":"Construction",
            "type":"Services"
        }
    ],
    "sg:phone":"+44 1642 641102",
    "sg:postcode":"TS18 4LL",
    "sg:province":"Durham",
    "sg:tags":[
        "joinery"
    ],
    "wof:name":"Fast Fence",
    "wof:placetype":"venue"
},
  "geometry": {"coordinates":[-1.33024,54.568031],"type":"Point"}
}