{
  "type": "Feature",
  "properties": {
    "addr:full":"The Barn, 16 Mill Road, Kislingbury Northampton Buckinghamshire NN7 4BB",
    "addr:housenumber":"16",
    "addr:postcode":"nn7 4bb",
    "addr:street":"Mill Road",
    "iso:country":"GB",
    "sg:address":"The Barn, 16 Mill Road, Kislingbury",
    "sg:city":"Northampton",
    "sg:classifiers":[
        {
            "category":"Manufacturing",
            "subcategory":"Signs",
            "type":"Manufacturing & Wholesale Goods"
        }
    ],
    "sg:postcode":"NN7 4BB",
    "sg:province":"Buckinghamshire",
    "sg:tags":[
        "writer"
    ],
    "wof:name":"Orchard Vinyl Graphics",
    "wof:placetype":"venue"
},
  "geometry": {"coordinates":[-0.978904,52.228989],"type":"Point"}
}