{
  "type": "Feature",
  "properties": {
    "addr:full":"Unit 13 Kendal Court, Hurricane Way Wickford Essex SS11 8YB",
    "addr:housenumber":"unit 13",
    "addr:postcode":"ss11 8yb",
    "addr:street":"Kendal Court Hurricane Way",
    "iso:country":"GB",
    "sg:address":"Unit 13 Kendal Court, Hurricane Way",
    "sg:city":"Wickford",
    "sg:classifiers":[
        {
            "category":"Real Estate",
            "subcategory":"Architect",
            "type":"Services"
        }
    ],
    "sg:phone":"+44 1268 764383",
    "sg:postcode":"SS11 8YB",
    "sg:province":"Essex",
    "wof:name":"R & S Fire Engineering Ltd.",
    "wof:placetype":"venue"
},
  "geometry": {"coordinates":[0.544492,51.602749],"type":"Point"}
}