{
  "type": "Feature",
  "properties": {
    "iso:country":"GB",
    "sg:address":"Eign St",
    "sg:city":"Hereford",
    "sg:classifiers":[
        {
            "category":"Place Of Worship",
            "type":"Public Place"
        }
    ],
    "sg:phone":"+44 1432 274851",
    "sg:postcode":"HR4 0AJ",
    "sg:province":"Herefordshire",
    "wof:name":"Eignbrook United Reformed Church",
    "wof:placetype":"venue"
},
  "geometry": {"coordinates":[-2.72246,52.056973],"type":"Point"}
}