{
  "type": "Feature",
  "properties": {
    "addr:full":"36 Pennygillam Way, Pennygillam Industrial Estate Launceston Cornwall PL15 7ED",
    "addr:housenumber":"36",
    "addr:postcode":"pl15 7ed",
    "addr:street":"Pennygillam Way Pennygillam Industrial Estate",
    "iso:country":"GB",
    "sg:address":"36 Pennygillam Way, Pennygillam Industrial Estate",
    "sg:city":"Launceston",
    "sg:classifiers":[
        {
            "category":"Bars & Pubs",
            "subcategory":"Nightclub",
            "type":"Food & Drink"
        }
    ],
    "sg:phone":"+44 1566 776527",
    "sg:postcode":"PL15 7ED",
    "sg:province":"Cornwall",
    "sg:tags":[
        "club",
        "night",
        "activity"
    ],
    "wof:name":"OASIS NIGHT CLUB",
    "wof:placetype":"venue"
},
  "geometry": {"coordinates":[-4.3703489304,50.6277160645],"type":"Point"}
}