{
  "type": "Feature",
  "properties": {
    "iso:country":"GB",
    "sg:address":"1340 Greenford Rd",
    "sg:city":"Greenford",
    "sg:classifiers":[
        {
            "category":"Fast Food",
            "type":"Food & Drink"
        }
    ],
    "sg:phone":"+44 20 8422 6888",
    "sg:postcode":"UB6 0HL",
    "sg:province":"Greater London",
    "sg:tags":[
        "away",
        "take"
    ],
    "wof:name":"H R Takeaway",
    "wof:placetype":"venue"
},
  "geometry": {"coordinates":[-0.3390020132,51.551738739],"type":"Point"}
}