{
  "type": "Feature",
  "properties": {
    "addr:full":"St. Marks Church, Kennington Park Rd Lambeth Greater London SE11 4PW",
    "addr:postcode":"se11 4pw",
    "addr:street":"Kennington Park Rd",
    "iso:country":"GB",
    "sg:address":"St. Marks Church, Kennington Park Rd",
    "sg:city":"Lambeth",
    "sg:classifiers":[
        {
            "category":"Place Of Worship",
            "type":"Public Place"
        }
    ],
    "sg:phone":"+44 20 7820 0830",
    "sg:postcode":"SE11 4PW",
    "sg:province":"Greater London",
    "wof:name":"Glorious International Ministries",
    "wof:placetype":"venue"
},
  "geometry": {"coordinates":[-0.11219,51.4814],"type":"Point"}
}