{
  "type": "Feature",
  "properties": {
    "addr:full":"Trading Standards, County Hall, Martineau La Norwich Norfolk NR1 2SH",
    "addr:postcode":"nr1 2sh",
    "addr:street":"Martineau La Norwich Norfolk",
    "iso:country":"GB",
    "sg:address":"Trading Standards, County Hall, Martineau La",
    "sg:city":"Norwich",
    "sg:classifiers":[
        {
            "category":"Government",
            "subcategory":"Office",
            "type":"Public Place"
        }
    ],
    "sg:phone":"+44 1603 222147",
    "sg:postcode":"NR1 2SH",
    "sg:province":"Norfolk",
    "sg:tags":[
        "local"
    ],
    "wof:name":"Norfolk County Council",
    "wof:placetype":"venue"
},
  "geometry": {"coordinates":[1.2948999405,52.6224937439],"type":"Point"}
}