{
  "type": "Feature",
  "properties": {
    "addr:full":"42 Narrow Lane, Histon Cambridge Cambridgeshire CB4 9HD",
    "addr:housenumber":"42",
    "addr:postcode":"cb4 9hd",
    "addr:street":"Narrow Lane",
    "iso:country":"GB",
    "sg:address":"42 Narrow Lane, Histon",
    "sg:city":"Cambridge",
    "sg:classifiers":[
        {
            "category":"Communications",
            "type":"Services"
        }
    ],
    "sg:phone":"+44 1223 233031",
    "sg:postcode":"CB4 9HD",
    "sg:province":"Cambridgeshire",
    "sg:tags":[
        "audio-visual"
    ],
    "wof:name":"World Video Productions",
    "wof:placetype":"venue"
},
  "geometry": {"coordinates":[0.1086720005,52.2551765442],"type":"Point"}
}