{
  "type": "Feature",
  "properties": {
    "addr:full":"Old Walsall Road Birmingham West Midlands B42 1EA",
    "addr:postcode":"b42 1ea",
    "addr:street":"Old Walsall Road",
    "iso:country":"GB",
    "sg:address":"Old Walsall Road",
    "sg:city":"Birmingham",
    "sg:classifiers":[
        {
            "category":"Wholesale",
            "subcategory":"Electrical",
            "type":"Manufacturing & Wholesale Goods"
        }
    ],
    "sg:phone":"+44 121 357 2941",
    "sg:postcode":"B42 1EA",
    "sg:province":"West Midlands",
    "sg:tags":[
        "equipment",
        "refrigeration"
    ],
    "wof:name":"B F S Fans",
    "wof:placetype":"venue"
},
  "geometry": {"coordinates":[-1.929531,52.542938],"type":"Point"}
}