{
  "type": "Feature",
  "properties": {
    "addr:full":"Dryclough La Halifax West Yorkshire HX3 0LD",
    "addr:postcode":"hx3 0ld",
    "addr:street":"La;West",
    "iso:country":"GB",
    "sg:address":"Dryclough La",
    "sg:city":"Halifax",
    "sg:classifiers":[
        {
            "category":"Retail",
            "subcategory":"Auto Repair",
            "type":"Services"
        }
    ],
    "sg:phone":"+44 1422 321333",
    "sg:postcode":"HX3 0LD",
    "sg:province":"West Yorkshire",
    "sg:tags":[
        "modification",
        "garage"
    ],
    "wof:name":"Dryclough Motor Co",
    "wof:placetype":"venue"
},
  "geometry": {"coordinates":[-1.861839056,53.7063560486],"type":"Point"}
}