{
  "type": "Feature",
  "properties": {
    "addr:full":"15c High Street, West Wycombe High Wycombe Buckinghamshire HP14 3AB",
    "addr:housenumber":"15c",
    "addr:postcode":"hp14 3ab",
    "addr:street":"High Street",
    "iso:country":"GB",
    "sg:address":"15c High Street, West Wycombe",
    "sg:city":"High Wycombe",
    "sg:classifiers":[
        {
            "category":"Professional",
            "subcategory":"Art Services",
            "type":"Services"
        }
    ],
    "sg:phone":"+44 1494 462822",
    "sg:postcode":"HP14 3AB",
    "sg:province":"Buckinghamshire",
    "sg:tags":[
        "graphic",
        "designer"
    ],
    "wof:name":"Rage Design Ltd.",
    "wof:placetype":"venue"
},
  "geometry": {"coordinates":[-0.8040069938,51.644744873],"type":"Point"}
}