{
  "type": "Feature",
  "properties": {
    "iso:country":"GB",
    "sg:address":"1 Merlin Street, Johnstown",
    "sg:city":"Wrexham",
    "sg:classifiers":[
        {
            "category":"Personal",
            "subcategory":"Beauty Salon",
            "type":"Services"
        }
    ],
    "sg:phone":"+44 1978 844214",
    "sg:postcode":"LL14 1NH",
    "sg:province":"Wrexham",
    "sg:tags":[
        "unisex",
        "hairdresser"
    ],
    "wof:name":"Reflections Hairdressing",
    "wof:placetype":"venue"
},
  "geometry": {"coordinates":[-3.043389082,53.0091667175],"type":"Point"}
}