{
  "type": "Feature",
  "properties": {
    "addr:full":"2 Snowdon Road Bournemouth Dorset BH4 9HL",
    "addr:housenumber":"2",
    "addr:postcode":"bh4 9hl",
    "addr:street":"Snowdon Road",
    "iso:country":"GB",
    "sg:address":"2 Snowdon Road",
    "sg:city":"Bournemouth",
    "sg:classifiers":[
        {
            "category":"Farming",
            "subcategory":"Nursery",
            "type":"Manufacturing & Wholesale Goods"
        }
    ],
    "sg:postcode":"BH4 9HL",
    "sg:province":"Dorset",
    "sg:tags":[
        "creche"
    ],
    "wof:name":"Three Gables Day Nursery",
    "wof:placetype":"venue"
},
  "geometry": {"coordinates":[-1.9009059668,50.7247543335],"type":"Point"}
}