{
  "type": "Feature",
  "properties": {
    "addr:full":"38b Gainsborough Avenue, Wootton Bassett Swindon Wiltshire SN4 8LA",
    "addr:housenumber":"38b",
    "addr:postcode":"sn4 8la",
    "addr:street":"Gainsborough Avenue",
    "iso:country":"GB",
    "sg:address":"38b Gainsborough Avenue, Wootton Bassett",
    "sg:city":"Swindon",
    "sg:classifiers":[
        {
            "category":"Fast Food",
            "type":"Food & Drink"
        }
    ],
    "sg:phone":"+44 1793 850338",
    "sg:postcode":"SN4 8LA",
    "sg:province":"Wiltshire",
    "sg:tags":[
        "away",
        "meal",
        "outlet",
        "take"
    ],
    "wof:name":"Green Field Garden",
    "wof:placetype":"venue"
},
  "geometry": {"coordinates":[-1.893164,51.548206],"type":"Point"}
}