{
  "type": "Feature",
  "properties": {
    "iso:country":"GB",
    "sg:address":"9 Idle Rd",
    "sg:city":"Bradford",
    "sg:classifiers":[
        {
            "category":"Bus Charters",
            "type":"Transportation"
        }
    ],
    "sg:phone":"+44 1274 635000",
    "sg:postcode":"BD2 4QA",
    "sg:province":"West Yorkshire",
    "sg:tags":[
        "hire",
        "coach"
    ],
    "wof:name":"Nationwide Minibus Service",
    "wof:placetype":"venue"
},
  "geometry": {"coordinates":[-1.733008,53.807426],"type":"Point"}
}