{
  "type": "Feature",
  "properties": {
    "addr:full":"9 Ravensfield Road Dewsbury West Yorkshire WF13 3EQ",
    "addr:housenumber":"9",
    "addr:postcode":"wf13 3eq",
    "addr:street":"Ravensfield Road",
    "iso:country":"GB",
    "sg:address":"9 Ravensfield Road",
    "sg:city":"Dewsbury",
    "sg:classifiers":[
        {
            "category":"Building & Trades",
            "subcategory":"Construction",
            "type":"Services"
        }
    ],
    "sg:phone":"+44 1924 451121",
    "sg:postcode":"WF13 3EQ",
    "sg:province":"West Yorkshire",
    "sg:tags":[
        "decorator",
        "painter"
    ],
    "wof:name":"Gerald Munt",
    "wof:placetype":"venue"
},
  "geometry": {"coordinates":[-1.6513979435,53.681842804],"type":"Point"}
}