{
  "type": "Feature",
  "properties": {
    "addr:full":"41/43 West High Street Forfar Angus DD8 1BE",
    "addr:housenumber":"41 / 43",
    "addr:postcode":"dd8 1be",
    "addr:street":"West High Street",
    "iso:country":"GB",
    "sg:address":"41/43 West High Street",
    "sg:city":"Forfar",
    "sg:classifiers":[
        {
            "category":"Bars & Pubs",
            "type":"Food & Drink"
        }
    ],
    "sg:phone":"+44 1307 464350",
    "sg:postcode":"DD8 1BE",
    "sg:province":"Angus",
    "sg:tags":[
        "pubs",
        "inn"
    ],
    "wof:name":"Quadro International (Scotland) Ltd.",
    "wof:placetype":"venue"
},
  "geometry": {"coordinates":[-2.890701,56.643494],"type":"Point"}
}