{
  "type": "Feature",
  "properties": {
    "addr:full":"Domestic Road, Holbeck Leeds West Yorkshire LS12 6HG",
    "addr:postcode":"ls12 6hg",
    "addr:street":"Domestic Road",
    "iso:country":"GB",
    "sg:address":"Domestic Road, Holbeck",
    "sg:city":"Leeds",
    "sg:classifiers":[
        {
            "category":"Autos & Motor Vehicles",
            "subcategory":"Automobile Sales",
            "type":"Retail Goods"
        }
    ],
    "sg:phone":"+44 113 251 1400",
    "sg:postcode":"LS12 6HG",
    "sg:province":"West Yorkshire",
    "sg:tags":[
        "car"
    ],
    "wof:name":"Hartwell Leeds South",
    "wof:placetype":"venue"
},
  "geometry": {"coordinates":[-1.568986,53.787395],"type":"Point"}
}