{
  "type": "Feature",
  "properties": {
    "addr:full":"Station Road, Moretonhampstead Newton Abbot Devon TQ13 8SA",
    "addr:postcode":"tq13 8sa",
    "addr:street":"Station Road",
    "iso:country":"GB",
    "sg:address":"Station Road, Moretonhampstead",
    "sg:city":"Newton Abbot",
    "sg:classifiers":[
        {
            "category":"Freight",
            "type":"Transportation"
        }
    ],
    "sg:phone":"+44 1647 440505",
    "sg:postcode":"TQ13 8SA",
    "sg:province":"Devon",
    "sg:tags":[
        "haulage",
        "road"
    ],
    "wof:name":"B Thompson & Sons (Transport) Ltd.",
    "wof:placetype":"venue"
},
  "geometry": {"coordinates":[-3.7602040768,50.6580848694],"type":"Point"}
}