{
  "type": "Feature",
  "properties": {
    "iso:country":"GB",
    "sg:address":"201 Brighton Rd",
    "sg:city":"South Croydon",
    "sg:classifiers":[
        {
            "category":"Professional",
            "subcategory":"Engineering",
            "type":"Services"
        }
    ],
    "sg:phone":"+44 20 8649 8048",
    "sg:postcode":"CR2 6EG",
    "sg:province":"Surrey",
    "sg:tags":[
        "contractor",
        "electrical",
        "engineer"
    ],
    "wof:name":"Red Electrical",
    "wof:placetype":"venue"
},
  "geometry": {"coordinates":[-0.097609,51.355896],"type":"Point"}
}