{
  "type": "Feature",
  "properties": {
    "addr:full":"24 Bryn Hedydd Swansea Swansea SA6 8BS",
    "addr:housenumber":"24",
    "addr:postcode":"sa6 8bs",
    "addr:street":"Bryn Hedydd",
    "iso:country":"GB",
    "sg:address":"24 Bryn Hedydd",
    "sg:city":"Swansea",
    "sg:classifiers":[
        {
            "category":"Shopping",
            "subcategory":"Gifts & Souvenirs",
            "type":"Retail Goods"
        }
    ],
    "sg:phone":"+44 1792 310680",
    "sg:postcode":"SA6 8BS",
    "sg:province":"Swansea",
    "sg:tags":[
        "giftware"
    ],
    "wof:name":"Gift Basket Co The",
    "wof:placetype":"venue"
},
  "geometry": {"coordinates":[-3.9535079002,51.6664733887],"type":"Point"}
}