{
  "type": "Feature",
  "properties": {
    "iso:country":"GB",
    "sg:address":"12 Home Clo, Staverton",
    "sg:city":"Daventry",
    "sg:classifiers":[
        {
            "category":"Manufacturing",
            "subcategory":"Signs",
            "type":"Manufacturing & Wholesale Goods"
        }
    ],
    "sg:phone":"+44 1327 702081",
    "sg:postcode":"NN11 6JR",
    "sg:province":"Northamptonshire",
    "sg:tags":[
        "writer"
    ],
    "wof:name":"Aldous,R W,",
    "wof:placetype":"venue"
},
  "geometry": {"coordinates":[-1.20842,52.24966],"type":"Point"}
}