{
  "type": "Feature",
  "properties": {
    "iso:country":"GB",
    "sg:address":"17 Magdala Rd, Buckland",
    "sg:city":"Dover",
    "sg:classifiers":[
        {
            "category":"Wholesale",
            "subcategory":"Scrap",
            "type":"Manufacturing & Wholesale Goods"
        }
    ],
    "sg:postcode":"CT17 0JU",
    "sg:province":"Kent",
    "sg:tags":[
        "waste",
        "metal"
    ],
    "wof:name":"Beer,Tom,",
    "wof:placetype":"venue"
},
  "geometry": {"coordinates":[1.297373,51.134491],"type":"Point"}
}