{
  "type": "Feature",
  "properties": {
    "addr:full":"Elm Bank Training Centre, Stanley Rd Wakefield West Yorkshire WF1 4LH",
    "addr:postcode":"wf1 4lh",
    "addr:street":"Elm;Stanley Rd",
    "iso:country":"GB",
    "sg:address":"Elm Bank Training Centre, Stanley Rd",
    "sg:city":"Wakefield",
    "sg:classifiers":[
        {
            "category":"Health Services",
            "subcategory":"Hospital",
            "type":"Services"
        }
    ],
    "sg:postcode":"WF1 4LH",
    "sg:province":"West Yorkshire",
    "sg:tags":[
        "ambulance"
    ],
    "wof:name":"West Yorkshire Metropolitan Ambulance Se",
    "wof:placetype":"venue"
},
  "geometry": {"coordinates":[-1.48866,53.686699],"type":"Point"}
}