{
  "type": "Feature",
  "properties": {
    "addr:full":"10 The Market Plymouth Devon PL1 1PN",
    "addr:housenumber":"10",
    "addr:postcode":"pl1 1pn",
    "addr:street":"The Market",
    "iso:country":"GB",
    "sg:address":"10 The Market",
    "sg:city":"Plymouth",
    "sg:classifiers":[
        {
            "category":"Manufacturing",
            "subcategory":"Rubber & Plastics",
            "type":"Manufacturing & Wholesale Goods"
        },
        {
            "category":"Shopping",
            "subcategory":"Discount & Variety Stores",
            "type":"Retail Goods"
        }
    ],
    "sg:postcode":"PL1 1PN",
    "sg:province":"Devon",
    "sg:tags":[
        "product",
        "foam",
        "cleaning",
        "supply"
    ],
    "wof:name":"Langans Foam Shops",
    "wof:placetype":"venue"
},
  "geometry": {"coordinates":[-4.147047,50.371632],"type":"Point"}
}