{
  "type": "Feature",
  "properties": {
    "addr:full":"34 Bakers Lane Lichfield Staffordshire WS13 6NG",
    "addr:housenumber":"34",
    "addr:postcode":"ws13 6ng",
    "addr:street":"Bakers Lane",
    "iso:country":"GB",
    "sg:address":"34 Bakers Lane",
    "sg:city":"Lichfield",
    "sg:classifiers":[
        {
            "category":"Travel",
            "subcategory":"Travel Agent",
            "type":"Entertainment"
        }
    ],
    "sg:phone":"+44 1543 254484",
    "sg:postcode":"WS13 6NG",
    "sg:province":"Staffordshire",
    "wof:name":"Co-Op Travel",
    "wof:placetype":"venue"
},
  "geometry": {"coordinates":[-1.8248410225,52.682472229],"type":"Point"}
}