{
  "type": "Feature",
  "properties": {
    "iso:country":"GB",
    "sg:address":"19 Grove Street",
    "sg:city":"Wilmslow",
    "sg:classifiers":[
        {
            "category":"Shopping",
            "subcategory":"Gifts & Souvenirs",
            "type":"Retail Goods"
        }
    ],
    "sg:phone":"+44 1625 536486",
    "sg:postcode":"SK9 1DU",
    "sg:province":"Cheshire",
    "sg:tags":[
        "poster",
        "card"
    ],
    "wof:name":"Birthdays",
    "wof:placetype":"venue"
},
  "geometry": {"coordinates":[-2.231023,53.32703],"type":"Point"}
}