{
  "type": "Feature",
  "properties": {
    "iso:country":"GB",
    "sg:address":"Copped Hall, Chappel Road, Great Tey",
    "sg:city":"Colchester",
    "sg:classifiers":[
        {
            "category":"Building & Trades",
            "subcategory":"Construction",
            "type":"Services"
        }
    ],
    "sg:phone":"+44 1206 212603",
    "sg:postcode":"CO6 1JQ",
    "sg:province":"Essex",
    "sg:tags":[
        "builder"
    ],
    "wof:name":"L F Hermon Builders",
    "wof:placetype":"venue"
},
  "geometry": {"coordinates":[0.7464650273,51.899105072],"type":"Point"}
}