{
  "type": "Feature",
  "properties": {
    "addr:full":"12 Banastre Drive Newton-le-willows Cheshire WA12 8BE",
    "addr:housenumber":"12",
    "addr:postcode":"wa12 8be",
    "addr:street":"Banastre Drive Newton-Le-Willows",
    "iso:country":"GB",
    "sg:address":"12 Banastre Drive",
    "sg:city":"Newton-le-willows",
    "sg:classifiers":[
        {
            "category":"Social Services",
            "subcategory":"Child Care",
            "type":"Services"
        }
    ],
    "sg:postcode":"WA12 8BE",
    "sg:province":"Cheshire",
    "sg:tags":[
        "childminders"
    ],
    "wof:name":"M Ford",
    "wof:placetype":"venue"
},
  "geometry": {"coordinates":[-2.610532,53.451313],"type":"Point"}
}