{
  "type": "Feature",
  "properties": {
    "addr:full":"Strathearn, Rose Street Beauly Highland IV4 7DT",
    "addr:postcode":"iv4 7dt",
    "addr:street":"Rose Street",
    "iso:country":"GB",
    "sg:address":"Strathearn, Rose Street",
    "sg:city":"Beauly",
    "sg:classifiers":[
        {
            "category":"Building & Trades",
            "subcategory":"Plumbing",
            "type":"Services"
        }
    ],
    "sg:phone":"+44 1463 782908",
    "sg:postcode":"IV4 7DT",
    "sg:province":"Highland",
    "sg:tags":[
        "heating"
    ],
    "wof:name":"A & G Macdonald",
    "wof:placetype":"venue"
},
  "geometry": {"coordinates":[-4.460757,57.482918],"type":"Point"}
}