{
  "type": "Feature",
  "properties": {
    "addr:full":"211-213 Camp Rd St. Albans Hertfordshire AL1 5NB",
    "addr:housenumber":"211-213",
    "addr:postcode":"al1 5nb",
    "addr:street":"Camp Rd",
    "iso:country":"GB",
    "sg:address":"211-213 Camp Rd",
    "sg:city":"St. Albans",
    "sg:classifiers":[
        {
            "category":"Home & Garden",
            "subcategory":"Hardware",
            "type":"Retail Goods"
        }
    ],
    "sg:phone":"+44 1727 853000",
    "sg:postcode":"AL1 5NB",
    "sg:province":"Hertfordshire",
    "sg:tags":[
        "retailer",
        "diy"
    ],
    "wof:name":"John Dearman",
    "wof:placetype":"venue"
},
  "geometry": {"coordinates":[-0.310133,51.747211],"type":"Point"}
}