{
  "type": "Feature",
  "properties": {
    "iso:country":"GB",
    "sg:address":"4 George Street",
    "sg:city":"Alderley Edge",
    "sg:classifiers":[
        {
            "category":"Health Services",
            "subcategory":"Health Practitioner",
            "type":"Services"
        }
    ],
    "sg:phone":"+44 1625 590444",
    "sg:postcode":"SK9 7EJ",
    "sg:province":"Cheshire",
    "sg:tags":[
        "physiotherapist"
    ],
    "wof:name":"Angela Jackson",
    "wof:placetype":"venue"
},
  "geometry": {"coordinates":[-2.236615,53.300304],"type":"Point"}
}