{
  "type": "Feature",
  "properties": {
    "addr:full":"Mount Royal Hotel, Portman Street London Greater London W1H 7BJ",
    "addr:postcode":"w1h 7bj",
    "addr:street":"Portman Street",
    "iso:country":"GB",
    "sg:address":"Mount Royal Hotel, Portman Street",
    "sg:city":"London",
    "sg:classifiers":[
        {
            "category":"Shopping",
            "subcategory":"Clothing, Apparel, & Fashions",
            "type":"Retail Goods"
        }
    ],
    "sg:phone":"+44 20 7493 4847",
    "sg:postcode":"W1H 7BJ",
    "sg:province":"Greater London",
    "sg:tags":[
        "ladieswear"
    ],
    "wof:name":"Carolyn Taylor Boutique",
    "wof:placetype":"venue"
},
  "geometry": {"coordinates":[-0.15656,51.51395],"type":"Point"}
}