{
  "type": "Feature",
  "properties": {
    "addr:full":"24 High Street South Durham Durham DH7 8JW",
    "addr:housenumber":"24",
    "addr:postcode":"dh7 8jw",
    "addr:street":"High Street",
    "iso:country":"GB",
    "sg:address":"24 High Street South",
    "sg:city":"Durham",
    "sg:classifiers":[
        {
            "category":"Shopping",
            "subcategory":"Florist",
            "type":"Retail Goods"
        }
    ],
    "sg:phone":"+44 191 378 3598",
    "sg:postcode":"DH7 8JW",
    "sg:province":"Durham",
    "wof:name":"Floral Scene",
    "wof:placetype":"venue"
},
  "geometry": {"coordinates":[-1.610124,54.758076],"type":"Point"}
}