{
  "type": "Feature",
  "properties": {
    "addr:full":"Gelham Hall, Wickham Market Woodbridge Suffolk IP13 0NE",
    "addr:postcode":"ip13 0ne",
    "iso:country":"GB",
    "sg:address":"Gelham Hall, Wickham Market",
    "sg:city":"Woodbridge",
    "sg:classifiers":[
        {
            "category":"Food & Beverages",
            "subcategory":"Bakery",
            "type":"Retail Goods"
        },
        {
            "category":"Home & Garden",
            "subcategory":"Kitchen Supply",
            "type":"Retail Goods"
        }
    ],
    "sg:phone":"+44 1728 746344",
    "sg:postcode":"IP13 0NE",
    "sg:province":"Suffolk",
    "sg:tags":[
        "confectioner",
        "baker",
        "confectionery"
    ],
    "wof:name":"Farmhouse Cooking Ltd",
    "wof:placetype":"venue"
},
  "geometry": {"coordinates":[1.365257,52.142773],"type":"Point"}
}