{
  "type": "Feature",
  "properties": {
    "iso:country":"GB",
    "sg:address":"66 High Meadows, Midsomer Norton",
    "sg:city":"Bath",
    "sg:classifiers":[
        {
            "category":"Building & Trades",
            "subcategory":"Construction",
            "type":"Services"
        }
    ],
    "sg:phone":"+44 1761 418055",
    "sg:postcode":"BA3 2RZ",
    "sg:province":"Somerset",
    "sg:tags":[
        "insulation",
        "installers",
        "ceiling",
        "contractor"
    ],
    "wof:name":"D & O Interiors",
    "wof:placetype":"venue"
},
  "geometry": {"coordinates":[-2.49239,51.287827],"type":"Point"}
}