{
  "type": "Feature",
  "properties": {
    "iso:country":"GB",
    "sg:address":"26 Elizabeth Way, Bishoips Waltham",
    "sg:city":"Southampton",
    "sg:classifiers":[
        {
            "category":"Education",
            "subcategory":"Special Training",
            "type":"Public Place"
        }
    ],
    "sg:phone":"+44 1489 891265",
    "sg:postcode":"SO32 1SQ",
    "sg:province":"Hampshire",
    "sg:tags":[
        "product",
        "centre"
    ],
    "wof:name":"Sea Change Management & Team Development Ltd.",
    "wof:placetype":"venue"
},
  "geometry": {"coordinates":[-1.223132,50.953957],"type":"Point"}
}