{
  "type": "Feature",
  "properties": {
    "iso:country":"GB",
    "sg:address":"9 Albion Road, Pitstone",
    "sg:city":"Leighton Buzzard",
    "sg:classifiers":[
        {
            "category":"Building & Trades",
            "subcategory":"Plumbing",
            "type":"Services"
        }
    ],
    "sg:postcode":"LU7 9AY",
    "sg:province":"Bedfordshire",
    "sg:tags":[
        "heating"
    ],
    "wof:name":"Kenneth A Packer",
    "wof:placetype":"venue"
},
  "geometry": {"coordinates":[-0.6393479705,51.8342781067],"type":"Point"}
}