{
  "type": "Feature",
  "properties": {
    "iso:country":"GB",
    "sg:address":"43 Frederick St",
    "sg:city":"Birmingham",
    "sg:classifiers":[
        {
            "category":"Manufacturing",
            "subcategory":"Jewelry",
            "type":"Manufacturing & Wholesale Goods"
        }
    ],
    "sg:phone":"+44 121 233 4381",
    "sg:postcode":"B1 3HN",
    "sg:province":"West Midlands",
    "sg:tags":[
        "repair",
        "jewellery"
    ],
    "wof:name":"Ken Shaw Diamond Drilling Ltd",
    "wof:placetype":"venue"
},
  "geometry": {"coordinates":[-1.912465,52.486172],"type":"Point"}
}