{
  "type": "Feature",
  "properties": {
    "addr:full":"Nant-y-gwyddon Road Tonypandy Rhondda, Cynon, Taff CF40 2JF",
    "addr:postcode":"cf40 2jf",
    "addr:street":"Nant-Y-Gwyddon Road;Cynon Taff",
    "iso:country":"GB",
    "sg:address":"Nant-y-gwyddon Road",
    "sg:city":"Tonypandy",
    "sg:classifiers":[
        {
            "category":"Travel",
            "subcategory":"Hostel",
            "type":"Entertainment"
        }
    ],
    "sg:phone":"+44 1443 430859",
    "sg:postcode":"CF40 2JF",
    "sg:province":"Rhondda, Cynon, Taff",
    "sg:tags":[
        "youth"
    ],
    "wof:name":"Youth Hostels Association (England & Wales)",
    "wof:placetype":"venue"
},
  "geometry": {"coordinates":[-3.458159,51.639599],"type":"Point"}
}