{
  "type": "Feature",
  "properties": {
    "addr:full":"134 Drumfrochar Road Greenock Inverclyde PA15 4JG",
    "addr:housenumber":"134",
    "addr:postcode":"pa15 4jg",
    "addr:street":"Drumfrochar Road",
    "iso:country":"GB",
    "sg:address":"134 Drumfrochar Road",
    "sg:city":"Greenock",
    "sg:classifiers":[
        {
            "category":"Health Services",
            "subcategory":"Nursing And Care Facility",
            "type":"Services"
        }
    ],
    "sg:phone":"+44 1475 731122",
    "sg:postcode":"PA15 4JG",
    "sg:province":"Inverclyde",
    "sg:tags":[
        "home"
    ],
    "wof:name":"GREENOCK GRAMPIAN NURSING HOME",
    "wof:placetype":"venue"
},
  "geometry": {"coordinates":[-4.7689490318,55.9408798218],"type":"Point"}
}