{
  "type": "Feature",
  "properties": {
    "iso:country":"GB",
    "sg:address":"6 Church Close, Shapwick",
    "sg:city":"Bridgwater",
    "sg:classifiers":[
        {
            "category":"Education",
            "subcategory":"Preschool",
            "type":"Public Place"
        }
    ],
    "sg:phone":"+44 1458 210436",
    "sg:postcode":"TA7 9LS",
    "sg:province":"Somerset",
    "sg:tags":[
        "school",
        "nursery",
        "playgroups",
        "pre-school"
    ],
    "wof:name":"Cherrytrees Montessori",
    "wof:placetype":"venue"
},
  "geometry": {"coordinates":[-2.8335709572,51.1395759583],"type":"Point"}
}