{
  "type": "Feature",
  "properties": {
    "addr:full":"31 Battersea Bridge Rd Battersea Greater London SW11 3BA",
    "addr:housenumber":"31",
    "addr:postcode":"sw11 3ba",
    "addr:street":"Battersea Bridge Rd",
    "iso:country":"GB",
    "sg:address":"31 Battersea Bridge Rd",
    "sg:city":"Battersea",
    "sg:classifiers":[
        {
            "category":"Building & Trades",
            "subcategory":"Cleaning & Sanitation",
            "type":"Services"
        }
    ],
    "sg:phone":"+44 20 7350 2166",
    "sg:postcode":"SW11 3BA",
    "sg:province":"Greater London",
    "sg:tags":[
        "commercial"
    ],
    "wof:name":"Broadreach Services",
    "wof:placetype":"venue"
},
  "geometry": {"coordinates":[-0.170299,51.47884],"type":"Point"}
}