{
  "type": "Feature",
  "properties": {
    "addr:full":"28 Union Rd, Camelon Falkirk Falkirk FK1 4PG",
    "addr:housenumber":"28",
    "addr:postcode":"fk1 4pg",
    "addr:street":"Union Rd",
    "iso:country":"GB",
    "sg:address":"28 Union Rd, Camelon",
    "sg:city":"Falkirk",
    "sg:classifiers":[
        {
            "category":"Food & Beverages",
            "subcategory":"Fruits & Vegetables",
            "type":"Retail Goods"
        }
    ],
    "sg:postcode":"FK1 4PG",
    "sg:province":"Falkirk",
    "sg:tags":[
        "greengrocer"
    ],
    "wof:name":"Jones,Agnes,",
    "wof:placetype":"venue"
},
  "geometry": {"coordinates":[-3.8134291172,56.0025177002],"type":"Point"}
}