{
  "type": "Feature",
  "properties": {
    "addr:full":"11 Rippersley Road Welling Kent DA16 3BX",
    "addr:housenumber":"11",
    "addr:postcode":"da16 3bx",
    "addr:street":"Rippersley Road",
    "iso:country":"GB",
    "sg:address":"11 Rippersley Road",
    "sg:city":"Welling",
    "sg:classifiers":[
        {
            "category":"Shopping",
            "subcategory":"Party Supplies",
            "type":"Retail Goods"
        }
    ],
    "sg:phone":"+44 20 8854 2929",
    "sg:postcode":"DA16 3BX",
    "sg:province":"Kent",
    "sg:tags":[
        "inflatables",
        "bouncy",
        "castle"
    ],
    "wof:name":"Bouncy Castles",
    "wof:placetype":"venue"
},
  "geometry": {"coordinates":[0.103358,51.46957],"type":"Point"}
}