{
  "type": "Feature",
  "properties": {
    "addr:full":"170 Brooker Rd Waltham Abbey Essex EN9 1JH",
    "addr:housenumber":"170",
    "addr:postcode":"en9 1jh",
    "addr:street":"Brooker Rd;Abbey",
    "iso:country":"GB",
    "sg:address":"170 Brooker Rd",
    "sg:city":"Waltham Abbey",
    "sg:classifiers":[
        {
            "category":"Professional",
            "subcategory":"Art Services",
            "type":"Services"
        }
    ],
    "sg:phone":"+44 1992 707414",
    "sg:postcode":"EN9 1JH",
    "sg:province":"Essex",
    "sg:tags":[
        "graphic",
        "designer"
    ],
    "wof:name":"Echo 4",
    "wof:placetype":"venue"
},
  "geometry": {"coordinates":[-0.0039929999,51.6817703247],"type":"Point"}
}