{
  "type": "Feature",
  "properties": {
    "iso:country":"GB",
    "sg:address":"13 Castle Hill Av, Top Flat",
    "sg:city":"Folkestone",
    "sg:classifiers":[
        {
            "category":"Shopping",
            "subcategory":"Pharmacy",
            "type":"Retail Goods"
        }
    ],
    "sg:phone":"+44 1303 851294",
    "sg:postcode":"CT20 2TD",
    "sg:province":"Kent",
    "sg:tags":[
        "medicine",
        "therapy"
    ],
    "wof:name":"G B Lamb - Naturopath",
    "wof:placetype":"venue"
},
  "geometry": {"coordinates":[1.1779450178,51.0844306946],"type":"Point"}
}