{
  "type": "Feature",
  "properties": {
    "iso:country":"GB",
    "sg:address":"Unit 1 Little Park Enterprises, Charlwood Road, Ifield",
    "sg:city":"Crawley",
    "sg:classifiers":[
        {
            "category":"Government",
            "subcategory":"Post Office",
            "type":"Public Place"
        }
    ],
    "sg:phone":"+44 1293 524568",
    "sg:postcode":"RH11 0JZ",
    "sg:province":"West Sussex",
    "sg:tags":[
        "messenger",
        "courier"
    ],
    "wof:name":"Diamond Couriers Ltd.",
    "wof:placetype":"venue"
},
  "geometry": {"coordinates":[-0.2113800049,51.1221084595],"type":"Point"}
}