{
  "type": "Feature",
  "properties": {
    "addr:full":"51 Northbrook Street Newbury Berkshire RG14 1DT",
    "addr:housenumber":"51",
    "addr:postcode":"rg14 1dt",
    "addr:street":"Northbrook Street",
    "iso:country":"GB",
    "sg:address":"51 Northbrook Street",
    "sg:city":"Newbury",
    "sg:classifiers":[
        {
            "category":"Shopping",
            "type":"Retail Goods"
        }
    ],
    "sg:phone":"+44 1635 529898",
    "sg:postcode":"RG14 1DT",
    "sg:province":"Berkshire",
    "sg:tags":[
        "part",
        "accessory"
    ],
    "wof:name":"Les Smith",
    "wof:placetype":"venue"
},
  "geometry": {"coordinates":[-1.3247090578,51.4051017761],"type":"Point"}
}