{
  "type": "Feature",
  "properties": {
    "addr:full":"10-11 Trident House Clare Road, Stanwell Staines Berkshire TW19 7QU",
    "addr:housenumber":"10-11",
    "addr:postcode":"tw19 7qu",
    "addr:street":"Trident House Clare Road",
    "iso:country":"GB",
    "sg:address":"10-11 Trident House Clare Road, Stanwell",
    "sg:city":"Staines",
    "sg:classifiers":[
        {
            "category":"Food & Beverages",
            "subcategory":"Supermarket",
            "type":"Retail Goods"
        }
    ],
    "sg:phone":"+44 1784 255622",
    "sg:postcode":"TW19 7QU",
    "sg:province":"Berkshire",
    "wof:name":"S L Shaw",
    "wof:placetype":"venue"
},
  "geometry": {"coordinates":[-0.480125,51.457314],"type":"Point"}
}