{
  "type": "Feature",
  "properties": {
    "addr:full":"Sellicks Grn Taunton Devon TA3 7RY",
    "addr:postcode":"ta3 7ry",
    "addr:street":"Sellicks Grn",
    "iso:country":"GB",
    "sg:address":"Sellicks Grn",
    "sg:city":"Taunton",
    "sg:classifiers":[
        {
            "category":"Building & Trades",
            "subcategory":"Equipment Rental",
            "type":"Services"
        }
    ],
    "sg:phone":"+44 1823 421274",
    "sg:postcode":"TA3 7RY",
    "sg:province":"Devon",
    "sg:tags":[
        "plant",
        "machinery"
    ],
    "wof:name":"Taunton Excavating & Plant Hire Co. Ltd.",
    "wof:placetype":"venue"
},
  "geometry": {"coordinates":[-3.1232800484,50.9662208557],"type":"Point"}
}