{
  "type": "Feature",
  "properties": {
    "iso:country":"GB",
    "sg:address":"2-4 Wakefield Road",
    "sg:city":"Brighouse",
    "sg:classifiers":[
        {
            "category":"Bars & Pubs",
            "type":"Food & Drink"
        }
    ],
    "sg:postcode":"HD6 1SL",
    "sg:province":"West Yorkshire",
    "sg:tags":[
        "pubs",
        "inn"
    ],
    "wof:name":"Round Tavern",
    "wof:placetype":"venue"
},
  "geometry": {"coordinates":[-1.774149,53.701981],"type":"Point"}
}