{
  "type": "Feature",
  "properties": {
    "addr:full":"19 High Street, Weathampstead St Albans Hertfordshire AL4 8BB",
    "addr:housenumber":"19",
    "addr:postcode":"al4 8bb",
    "addr:street":"High Street Weathampstead",
    "iso:country":"GB",
    "sg:address":"19 High Street, Weathampstead",
    "sg:city":"St Albans",
    "sg:classifiers":[
        {
            "category":"Communications",
            "subcategory":"Film & Video Production",
            "type":"Services"
        }
    ],
    "sg:postcode":"AL4 8BB",
    "sg:province":"Hertfordshire",
    "sg:tags":[
        "tv"
    ],
    "wof:name":"Transport Video Publishing",
    "wof:placetype":"venue"
},
  "geometry": {"coordinates":[-0.2933090031,51.8129577637],"type":"Point"}
}