{
  "type": "Feature",
  "properties": {
    "addr:full":"1st Floor, 12 Bury St Stowmarket Suffolk IP14 1HA",
    "addr:housenumber":"12",
    "addr:postcode":"ip14 1ha",
    "addr:street":"Bury St",
    "iso:country":"GB",
    "sg:address":"1st Floor, 12 Bury St",
    "sg:city":"Stowmarket",
    "sg:classifiers":[
        {
            "category":"Education",
            "subcategory":"Special Training",
            "type":"Public Place"
        },
        {
            "category":"Organizations",
            "subcategory":"Non-profit Organization",
            "type":"Services"
        }
    ],
    "sg:phone":"+44 1449 612701",
    "sg:postcode":"IP14 1HA",
    "sg:province":"Suffolk",
    "sg:tags":[
        "charity",
        "product",
        "organisation",
        "voluntary",
        "centre"
    ],
    "wof:name":"YMCA Training",
    "wof:placetype":"venue"
},
  "geometry": {"coordinates":[0.9956510067,52.1886405945],"type":"Point"}
}