{
  "type": "Feature",
  "properties": {
    "addr:full":"6 George Street Brighton East Sussex BN2 1RH",
    "addr:housenumber":"6",
    "addr:postcode":"bn2 1rh",
    "addr:street":"George Street",
    "iso:country":"GB",
    "sg:address":"6 George Street",
    "sg:city":"Brighton",
    "sg:classifiers":[
        {
            "category":"Fast Food",
            "type":"Food & Drink"
        }
    ],
    "sg:phone":"+44 1273 670521",
    "sg:postcode":"BN2 1RH",
    "sg:province":"East Sussex",
    "sg:tags":[
        "away",
        "take"
    ],
    "wof:name":"The Ancient Curry Dome",
    "wof:placetype":"venue"
},
  "geometry": {"coordinates":[-0.134939,50.82122],"type":"Point"}
}