{
  "type": "Feature",
  "properties": {
    "iso:country":"GB",
    "sg:address":"Tregellas, North Down La",
    "sg:city":"Winscombe",
    "sg:classifiers":[
        {
            "category":"Shopping",
            "subcategory":"Clothing, Apparel, & Fashions",
            "type":"Retail Goods"
        }
    ],
    "sg:phone":"+44 1934 863863",
    "sg:postcode":"BS25 1SL",
    "sg:province":"Somerset",
    "sg:tags":[
        "workwear",
        "protective"
    ],
    "wof:name":"Country Innovations",
    "wof:placetype":"venue"
},
  "geometry": {"coordinates":[-2.831329,51.313171],"type":"Point"}
}