{
  "type": "Feature",
  "properties": {
    "iso:country":"GB",
    "sg:address":"9 Gravesend Road",
    "sg:city":"Rochester",
    "sg:classifiers":[
        {
            "category":"Fast Food",
            "type":"Food & Drink"
        }
    ],
    "sg:phone":"+44 1634 714245",
    "sg:postcode":"ME2 3PH",
    "sg:province":"Kent",
    "sg:tags":[
        "away",
        "take"
    ],
    "wof:name":"Good Luck Chinese Take Away",
    "wof:placetype":"venue"
},
  "geometry": {"coordinates":[0.483628,51.397205],"type":"Point"}
}