{
  "type": "Feature",
  "properties": {
    "iso:country":"GB",
    "sg:address":"36 Kew Road",
    "sg:city":"Southport",
    "sg:classifiers":[
        {
            "category":"Shopping",
            "subcategory":"Stationery & Office Supplies",
            "type":"Retail Goods"
        },
        {
            "category":"Manufacturing",
            "subcategory":"Wood Products",
            "type":"Manufacturing & Wholesale Goods"
        }
    ],
    "sg:phone":"+44 1704 569940",
    "sg:postcode":"PR8 4HW",
    "sg:province":"Lancashire",
    "sg:tags":[
        "packaging",
        "equipment",
        "crate",
        "pallets"
    ],
    "wof:name":"S B Industrial Agencies",
    "wof:placetype":"venue"
},
  "geometry": {"coordinates":[-3.0054929256,53.6265487671],"type":"Point"}
}