{
  "type": "Feature",
  "properties": {
    "addr:full":"Pheonix House, 2 Upper Teddington Road Kingston-upon-thames Greater London KT1 4DY",
    "addr:housenumber":"2",
    "addr:postcode":"kt1 4dy",
    "addr:street":"Upper Teddington Road",
    "iso:country":"GB",
    "sg:address":"Pheonix House, 2 Upper Teddington Road",
    "sg:city":"Kingston-upon-thames",
    "sg:classifiers":[
        {
            "category":"Shopping",
            "subcategory":"Pharmacy",
            "type":"Retail Goods"
        }
    ],
    "sg:postcode":"KT1 4DY",
    "sg:province":"Greater London",
    "sg:tags":[
        "medicine",
        "therapy"
    ],
    "wof:name":"Traditional Chinese Massotherapy & Training School",
    "wof:placetype":"venue"
},
  "geometry": {"coordinates":[-0.3138380051,51.4161682129],"type":"Point"}
}