{
  "type": "Feature",
  "properties": {
    "addr:full":"545 Garratt Lane London Greater London SW18 4SR",
    "addr:housenumber":"545",
    "addr:postcode":"sw18 4sr",
    "addr:street":"Garratt Lane",
    "iso:country":"GB",
    "sg:address":"545 Garratt Lane",
    "sg:city":"London",
    "sg:classifiers":[
        {
            "category":"Wholesale",
            "subcategory":"Construction Materials",
            "type":"Manufacturing & Wholesale Goods"
        },
        {
            "category":"Building & Trades",
            "subcategory":"Construction",
            "type":"Services"
        }
    ],
    "sg:phone":"+44 20 8879 1056",
    "sg:postcode":"SW18 4SR",
    "sg:province":"Greater London",
    "sg:tags":[
        "merchant",
        "glass",
        "glazier"
    ],
    "wof:name":"Beaumont Rose Ltd.",
    "wof:placetype":"venue"
},
  "geometry": {"coordinates":[-0.186799,51.441063],"type":"Point"}
}