{
  "type": "Feature",
  "properties": {
    "iso:country":"GB",
    "sg:address":"Vine Industrial Estate, Elland Road, Brookfoot",
    "sg:city":"Brighouse",
    "sg:classifiers":[
        {
            "category":"Retail",
            "subcategory":"Auto Rental",
            "type":"Services"
        }
    ],
    "sg:phone":"+44 1484 716989",
    "sg:postcode":"HD6 2QS",
    "sg:province":"West Yorkshire",
    "sg:tags":[
        "truck",
        "hire",
        "van"
    ],
    "wof:name":"Davisons van & Truck Rental",
    "wof:placetype":"venue"
},
  "geometry": {"coordinates":[-1.796601,53.703636],"type":"Point"}
}