{
  "type": "Feature",
  "properties": {
    "iso:country":"GB",
    "sg:address":"Unit 3, Quadants Speciality Shops",
    "sg:city":"Stoke-on-trent",
    "sg:classifiers":[
        {
            "category":"Shopping",
            "subcategory":"Discount & Variety Stores",
            "type":"Retail Goods"
        }
    ],
    "sg:postcode":"ST1 2JZ",
    "sg:province":"Staffordshire",
    "sg:tags":[
        "shop",
        "model"
    ],
    "wof:name":"Flightpath 747",
    "wof:placetype":"venue"
},
  "geometry": {"coordinates":[-2.175069,53.029369],"type":"Point"}
}