{
  "type": "Feature",
  "properties": {
    "iso:country":"GB",
    "sg:address":"Unit 3-4 Whitehall Industrial Estate, 2whitehall Road",
    "sg:city":"Ramsgate",
    "sg:classifiers":[
        {
            "category":"Home & Garden",
            "subcategory":"Building Materials",
            "type":"Retail Goods"
        }
    ],
    "sg:postcode":"CT12 6BU",
    "sg:province":"Kent",
    "sg:tags":[
        "ironwork",
        "diy",
        "wrought"
    ],
    "wof:name":"Scrollcraft",
    "wof:placetype":"venue"
},
  "geometry": {"coordinates":[1.40505,51.34383],"type":"Point"}
}