{
  "type": "Feature",
  "properties": {
    "addr:full":"23 Abbott Brow Blackburn Lancashire BB2 7HT",
    "addr:housenumber":"23",
    "addr:postcode":"bb2 7ht",
    "addr:street":"Abbott Brow",
    "iso:country":"GB",
    "sg:address":"23 Abbott Brow",
    "sg:city":"Blackburn",
    "sg:classifiers":[
        {
            "category":"Health Services",
            "subcategory":"Dentist",
            "type":"Services"
        }
    ],
    "sg:phone":"+44 1254 813274",
    "sg:postcode":"BB2 7HT",
    "sg:province":"Lancashire",
    "sg:tags":[
        "technician",
        "dental"
    ],
    "wof:name":"Bain Dental Tech Studio",
    "wof:placetype":"venue"
},
  "geometry": {"coordinates":[-2.5285921097,53.7783927917],"type":"Point"}
}