{
  "type": "Feature",
  "properties": {
    "addr:full":"Unit 5 Dobson Park Industrial Estate, Manchester Road, Ince Wigan Lancashire WN2 2ED",
    "addr:housenumber":"unit 5",
    "addr:postcode":"lancashire wn2 2ed",
    "addr:street":"Dobson Park Industrial;Manchester Road",
    "iso:country":"GB",
    "sg:address":"Unit 5 Dobson Park Industrial Estate, Manchester Road, Ince",
    "sg:city":"Wigan",
    "sg:classifiers":[
        {
            "category":"Manufacturing",
            "subcategory":"Metals",
            "type":"Manufacturing & Wholesale Goods"
        }
    ],
    "sg:phone":"+44 1942 322210",
    "sg:postcode":"WN2 2ED",
    "sg:province":"Lancashire",
    "sg:tags":[
        "steel",
        "stockholder"
    ],
    "wof:name":"Collins Reinforcements Ltd.",
    "wof:placetype":"venue"
},
  "geometry": {"coordinates":[-2.6028439999,53.5400848389],"type":"Point"}
}