{
  "type": "Feature",
  "properties": {
    "addr:full":"157 Main Road, Broomfield Chelmsford Essex CM1 7DJ",
    "addr:housenumber":"157",
    "addr:postcode":"cm1 7dj",
    "addr:street":"Main Road",
    "iso:country":"GB",
    "sg:address":"157 Main Road, Broomfield",
    "sg:city":"Chelmsford",
    "sg:classifiers":[
        {
            "category":"Autos & Motor Vehicles",
            "subcategory":"Boat Sales",
            "type":"Retail Goods"
        },
        {
            "category":"Retail",
            "subcategory":"Auto Repair",
            "type":"Services"
        }
    ],
    "sg:phone":"+44 1245 440501",
    "sg:postcode":"CM1 7DJ",
    "sg:province":"Essex",
    "sg:tags":[
        "engine",
        "car",
        "rebuilders",
        "specialist"
    ],
    "wof:name":"Star Engineers",
    "wof:placetype":"venue"
},
  "geometry": {"coordinates":[0.473265,51.760609],"type":"Point"}
}