{
  "type": "Feature",
  "properties": {
    "addr:full":"21 New Street Cromer Norfolk NR27 9HP",
    "addr:housenumber":"21",
    "addr:postcode":"nr27 9hp",
    "addr:street":"New Street",
    "iso:country":"GB",
    "sg:address":"21 New Street",
    "sg:city":"Cromer",
    "sg:classifiers":[
        {
            "category":"Shopping",
            "subcategory":"Department Store",
            "type":"Retail Goods"
        },
        {
            "category":"Recreation",
            "subcategory":"Fishing",
            "type":"Entertainment"
        }
    ],
    "sg:phone":"+44 1263 513676",
    "sg:postcode":"NR27 9HP",
    "sg:province":"Norfolk",
    "sg:tags":[
        "angling"
    ],
    "wof:name":"Marine Sports",
    "wof:placetype":"venue"
},
  "geometry": {"coordinates":[1.299026,52.932457],"type":"Point"}
}