{
  "type": "Feature",
  "properties": {
    "addr:full":"59 St Marys Road Poole Dorset BH15 2LH",
    "addr:housenumber":"59",
    "addr:postcode":"bh15 2lh",
    "addr:street":"St Marys Road",
    "iso:country":"GB",
    "sg:address":"59 St Marys Road",
    "sg:city":"Poole",
    "sg:classifiers":[
        {
            "category":"Professional",
            "subcategory":"Art Services",
            "type":"Services"
        }
    ],
    "sg:phone":"+44 1202 665726",
    "sg:postcode":"BH15 2LH",
    "sg:province":"Dorset",
    "sg:tags":[
        "graphic",
        "designer"
    ],
    "wof:name":"Alex Melliar",
    "wof:placetype":"venue"
},
  "geometry": {"coordinates":[-1.972671,50.723957],"type":"Point"}
}