{
  "type": "Feature",
  "properties": {
    "iso:country":"GB",
    "sg:address":"Stratford Rd",
    "sg:city":"Milton Keynes",
    "sg:classifiers":[
        {
            "category":"Professional",
            "subcategory":"Computer Services",
            "type":"Services"
        }
    ],
    "sg:phone":"+44 1908 225577",
    "sg:postcode":"MK12 5LJ",
    "sg:province":"Buckinghamshire",
    "sg:tags":[
        "system",
        "software"
    ],
    "wof:name":"On-Line Systems",
    "wof:placetype":"venue"
},
  "geometry": {"coordinates":[-0.809174,52.063305],"type":"Point"}
}