{
  "type": "Feature",
  "properties": {
    "iso:country":"GB",
    "sg:address":"Chapman House, 10 Blackheath Village",
    "sg:city":"London",
    "sg:classifiers":[
        {
            "category":"Professional",
            "subcategory":"Management & Consulting",
            "type":"Services"
        }
    ],
    "sg:phone":"+44 20 8297 1937",
    "sg:postcode":"SE3 9LE",
    "sg:province":"Greater London",
    "sg:tags":[
        "conservation"
    ],
    "wof:name":"The Blackheath Society",
    "wof:placetype":"venue"
},
  "geometry": {"coordinates":[0.0109719997,51.4640617371],"type":"Point"}
}