{
  "type": "Feature",
  "properties": {
    "iso:country":"GB",
    "sg:address":"Akeferry Road, Westwoodside",
    "sg:city":"Doncaster",
    "sg:classifiers":[
        {
            "category":"Professional",
            "subcategory":"Engineering",
            "type":"Services"
        }
    ],
    "sg:phone":"+44 1427 752449",
    "sg:postcode":"DN9 2DS",
    "sg:province":"Lincolnshire",
    "sg:tags":[
        "civil",
        "engineer"
    ],
    "wof:name":"Romav Plant & Construction",
    "wof:placetype":"venue"
},
  "geometry": {"coordinates":[-0.848689,53.480412],"type":"Point"}
}