{
  "type": "Feature",
  "properties": {
    "addr:full":"90 Bermondsey Street London Greater London SE1 3UB",
    "addr:housenumber":"90",
    "addr:postcode":"se1 3ub",
    "addr:street":"Bermondsey Street",
    "iso:country":"GB",
    "sg:address":"90 Bermondsey Street",
    "sg:city":"London",
    "sg:classifiers":[
        {
            "category":"Real Estate",
            "subcategory":"Real Estate Agent",
            "type":"Services"
        }
    ],
    "sg:phone":"+44 20 7407 4100",
    "sg:postcode":"SE1 3UB",
    "sg:province":"Greater London",
    "wof:name":"Williams Lynch Ltd.",
    "wof:placetype":"venue"
},
  "geometry": {"coordinates":[-0.082046,51.500961],"type":"Point"}
}