{
  "type": "Feature",
  "properties": {
    "addr:full":"59a Thorntree Road, Thornaby Stockton-on-tees Durham TS17 8LU",
    "addr:housenumber":"59a",
    "addr:postcode":"ts17 8lu",
    "addr:street":"Thorntree Road",
    "iso:country":"GB",
    "sg:address":"59a Thorntree Road, Thornaby",
    "sg:city":"Stockton-on-tees",
    "sg:classifiers":[
        {
            "category":"Personal",
            "subcategory":"Beauty Salon",
            "type":"Services"
        }
    ],
    "sg:postcode":"TS17 8LU",
    "sg:province":"Durham",
    "sg:tags":[
        "lady",
        "hairdresser"
    ],
    "wof:name":"A Cut Above",
    "wof:placetype":"venue"
},
  "geometry": {"coordinates":[-1.29861,54.545361],"type":"Point"}
}