{
  "type": "Feature",
  "properties": {
    "addr:full":"Cot Hill Trading Estate Plymouth Devon PL7 3SR",
    "addr:postcode":"pl7 3sr",
    "addr:street":"Cot Hill Trading Estate",
    "iso:country":"GB",
    "sg:address":"Cot Hill Trading Estate",
    "sg:city":"Plymouth",
    "sg:classifiers":[
        {
            "category":"Professional",
            "subcategory":"Business Services",
            "type":"Services"
        }
    ],
    "sg:phone":"+44 1752 339724",
    "sg:postcode":"PL7 3SR",
    "sg:province":"Devon",
    "sg:tags":[
        "tile",
        "stockist"
    ],
    "wof:name":"Nicobond International Ltd.",
    "wof:placetype":"venue"
},
  "geometry": {"coordinates":[-4.01741,50.424561],"type":"Point"}
}