{
  "type": "Feature",
  "properties": {
    "addr:full":"1 Isaacs Road Great Yarmouth Norfolk NR31 0BT",
    "addr:housenumber":"1",
    "addr:postcode":"nr31 0bt",
    "addr:street":"Isaacs Road",
    "iso:country":"GB",
    "sg:address":"1 Isaacs Road",
    "sg:city":"Great Yarmouth",
    "sg:classifiers":[
        {
            "category":"Personal",
            "subcategory":"Beauty Salon",
            "type":"Services"
        }
    ],
    "sg:phone":"+44 1493 652643",
    "sg:postcode":"NR31 0BT",
    "sg:province":"Norfolk",
    "sg:tags":[
        "unisex",
        "hairdresser"
    ],
    "wof:name":"Streaks Ahead",
    "wof:placetype":"venue"
},
  "geometry": {"coordinates":[1.718009,52.607937],"type":"Point"}
}