{
  "type": "Feature",
  "properties": {
    "iso:country":"GB",
    "sg:address":"Hebble End Mill, Hebble End",
    "sg:city":"Hebden Bridge",
    "sg:classifiers":[
        {
            "category":"Shopping",
            "subcategory":"Clothing, Apparel, & Fashions",
            "type":"Retail Goods"
        }
    ],
    "sg:phone":"+44 1422 846835",
    "sg:postcode":"HX7 8TE",
    "sg:province":"West Yorkshire",
    "sg:tags":[
        "shop",
        "clothing",
        "fabric"
    ],
    "wof:name":"Lounge Lizard Clothing Ltd",
    "wof:placetype":"venue"
},
  "geometry": {"coordinates":[-2.014491,53.741226],"type":"Point"}
}