{
  "type": "Feature",
  "properties": {
    "addr:full":"Victoria House, Victoria Street Taunton Somerset TA1 3FA",
    "addr:postcode":"ta1 3fa",
    "addr:street":"Victoria Street",
    "iso:country":"GB",
    "sg:address":"Victoria House, Victoria Street",
    "sg:city":"Taunton",
    "sg:classifiers":[
        {
            "category":"Real Estate",
            "subcategory":"Surveying",
            "type":"Services"
        }
    ],
    "sg:phone":"+44 1823 353033",
    "sg:postcode":"TA1 3FA",
    "sg:province":"Somerset",
    "sg:tags":[
        "building",
        "surveyor",
        "valuer"
    ],
    "wof:name":"Hatfield White Ltd",
    "wof:placetype":"venue"
},
  "geometry": {"coordinates":[-3.090784,51.015549],"type":"Point"}
}