{
  "type": "Feature",
  "properties": {
    "iso:country":"GB",
    "sg:address":"Nanphysick Farm, St Mewan",
    "sg:city":"St Austell",
    "sg:classifiers":[
        {
            "category":"Farming",
            "subcategory":"Dairy Farm",
            "type":"Manufacturing & Wholesale Goods"
        }
    ],
    "sg:phone":"+44 1726 73664",
    "sg:postcode":"PL26 7DT",
    "sg:province":"Cornwall",
    "wof:name":"E C Ferkin",
    "wof:placetype":"venue"
},
  "geometry": {"coordinates":[-4.82339,50.32518],"type":"Point"}
}