{
  "type": "Feature",
  "properties": {
    "addr:full":"6 The Heights Ilminster Somerset TA19 9AQ",
    "addr:housenumber":"6",
    "addr:postcode":"ta19 9aq",
    "addr:street":"The Heights",
    "iso:country":"GB",
    "sg:address":"6 The Heights",
    "sg:city":"Ilminster",
    "sg:classifiers":[
        {
            "category":"Building & Trades",
            "subcategory":"Construction",
            "type":"Services"
        }
    ],
    "sg:phone":"+44 1460 53085",
    "sg:postcode":"TA19 9AQ",
    "sg:province":"Somerset",
    "sg:tags":[
        "builder"
    ],
    "wof:name":"Brian T Edwards",
    "wof:placetype":"venue"
},
  "geometry": {"coordinates":[-2.917846,50.929714],"type":"Point"}
}