{
  "type": "Feature",
  "properties": {
    "iso:country":"GB",
    "sg:address":"Greens Road, Yaxham Road Industrial Estate",
    "sg:city":"Dereham",
    "sg:classifiers":[
        {
            "category":"Building & Trades",
            "subcategory":"Landscaping Services",
            "type":"Services"
        }
    ],
    "sg:phone":"+44 1362 699888",
    "sg:postcode":"NR20 3TG",
    "sg:province":"Norfolk",
    "sg:tags":[
        "horticultural",
        "consultant"
    ],
    "wof:name":"Randell Agriculture Ltd.",
    "wof:placetype":"venue"
},
  "geometry": {"coordinates":[0.9522299767,52.6736984253],"type":"Point"}
}