{
  "type": "Feature",
  "properties": {
    "addr:full":"130 Buckingham Palace Road London Greater London SW1W 9SA",
    "addr:housenumber":"130",
    "addr:postcode":"sw1w 9sa",
    "addr:street":"Buckingham Palace Road",
    "iso:country":"GB",
    "sg:address":"130 Buckingham Palace Road",
    "sg:city":"London",
    "sg:classifiers":[
        {
            "category":"Professional",
            "subcategory":"Advertising",
            "type":"Services"
        }
    ],
    "sg:phone":"+44 20 7233 6080",
    "sg:postcode":"SW1W 9SA",
    "sg:province":"Greater London",
    "sg:tags":[
        "agency"
    ],
    "wof:name":"Floyd Advertising Ltd.",
    "wof:placetype":"venue"
},
  "geometry": {"coordinates":[-0.1472409964,51.4935379028],"type":"Point"}
}