{
  "type": "Feature",
  "properties": {
    "iso:country":"GB",
    "sg:address":"Mart Office, Scots Gap",
    "sg:city":"Morpeth",
    "sg:classifiers":[
        {
            "category":"Professional",
            "type":"Services"
        }
    ],
    "sg:phone":"+44 1670 774287",
    "sg:postcode":"NE61 4DR",
    "sg:province":"Northumberland",
    "sg:tags":[
        "auctioneer"
    ],
    "wof:name":"Scots Gap Auction Mart Co",
    "wof:placetype":"venue"
},
  "geometry": {"coordinates":[-1.9369510412,55.172744751],"type":"Point"}
}