{
  "type": "Feature",
  "properties": {
    "iso:country":"GB",
    "sg:address":"Police Station, Rock Rd",
    "sg:city":"Newton Abbot",
    "sg:classifiers":[
        {
            "category":"Government",
            "subcategory":"Police Station",
            "type":"Public Place"
        }
    ],
    "sg:phone":"+44 870 577 7444",
    "sg:postcode":"TQ13 0JJ",
    "sg:province":"Devon",
    "sg:tags":[
        "support"
    ],
    "wof:name":"Devon & Cornwall Constabulary",
    "wof:placetype":"venue"
},
  "geometry": {"coordinates":[-3.60435009,50.5996818542],"type":"Point"}
}