{
  "type": "Feature",
  "properties": {
    "addr:full":"Icknield Street Drive, Washford West Redditch Warwickshire B98 0DE",
    "addr:postcode":"b98 0de",
    "addr:street":"Icknield Street Drive",
    "iso:country":"GB",
    "sg:address":"Icknield Street Drive, Washford West",
    "sg:city":"Redditch",
    "sg:classifiers":[
        {
            "category":"Shopping",
            "type":"Retail Goods"
        }
    ],
    "sg:phone":"+44 1527 517601",
    "sg:postcode":"B98 0DE",
    "sg:province":"Warwickshire",
    "sg:tags":[
        "part",
        "accessory"
    ],
    "wof:name":"Halfords Ltd.",
    "wof:placetype":"venue"
},
  "geometry": {"coordinates":[-1.902424,52.299335],"type":"Point"}
}