{
  "type": "Feature",
  "properties": {
    "iso:country":"GB",
    "sg:address":"130 Bebington Road, New Ferry",
    "sg:city":"Wirral",
    "sg:classifiers":[
        {
            "category":"Organizations",
            "subcategory":"Community Association",
            "type":"Services"
        },
        {
            "category":"Organizations",
            "subcategory":"Membership Organization",
            "type":"Services"
        }
    ],
    "sg:phone":"+44 151 645 1237",
    "sg:postcode":"CH62 5BJ",
    "sg:province":"Cheshire",
    "sg:tags":[
        "club",
        "social"
    ],
    "wof:name":"Bebington Liberal Club",
    "wof:placetype":"venue"
},
  "geometry": {"coordinates":[-3.00049,53.358822],"type":"Point"}
}