{
  "type": "Feature",
  "properties": {
    "addr:full":"8 Station Way Leeds West Yorkshire LS12 3HQ",
    "addr:housenumber":"8",
    "addr:postcode":"ls12 3hq",
    "addr:street":"Station Way",
    "iso:country":"GB",
    "sg:address":"8 Station Way",
    "sg:city":"Leeds",
    "sg:classifiers":[
        {
            "category":"Building & Trades",
            "subcategory":"Plumbing",
            "type":"Services"
        }
    ],
    "sg:phone":"+44 113 231 1104",
    "sg:postcode":"LS12 3HQ",
    "sg:province":"West Yorkshire",
    "sg:tags":[
        "heating"
    ],
    "wof:name":"Boiler & Heating Supplies Ltd.",
    "wof:placetype":"venue"
},
  "geometry": {"coordinates":[-1.595296979,53.7960472107],"type":"Point"}
}