{
  "type": "Feature",
  "properties": {
    "iso:country":"GB",
    "sg:address":"18 Portway, Bisley",
    "sg:city":"Woking",
    "sg:classifiers":[
        {
            "category":"Personal",
            "type":"Services"
        }
    ],
    "sg:phone":"+44 1483 476920",
    "sg:postcode":"GU24 9AJ",
    "sg:province":"Surrey",
    "sg:tags":[
        "wedding"
    ],
    "wof:name":"Bisley Private Hire",
    "wof:placetype":"venue"
},
  "geometry": {"coordinates":[-0.63562,51.32283],"type":"Point"}
}