{
  "type": "Feature",
  "properties": {
    "addr:full":"26 Great Percy Street London Greater London WC1X 9QP",
    "addr:housenumber":"26",
    "addr:postcode":"wc1x 9qp",
    "addr:street":"Great Percy Street",
    "iso:country":"GB",
    "sg:address":"26 Great Percy Street",
    "sg:city":"London",
    "sg:classifiers":[
        {
            "category":"Bars & Pubs",
            "type":"Food & Drink"
        }
    ],
    "sg:phone":"+44 20 7837 1399",
    "sg:postcode":"WC1X 9QP",
    "sg:province":"Greater London",
    "sg:tags":[
        "pubs",
        "inn"
    ],
    "wof:name":"The Percy Arms",
    "wof:placetype":"venue"
},
  "geometry": {"coordinates":[-0.113073,51.529346],"type":"Point"}
}