{
  "type": "Feature",
  "properties": {
    "addr:full":"Unit 9, Corinium Industrial Estate, Raans Road Amersham Buckinghamshire HP6 6JQ",
    "addr:housenumber":"unit 9",
    "addr:postcode":"hp6 6jq",
    "addr:street":"Corinium Industrial Estate Raans Road",
    "iso:country":"GB",
    "sg:address":"Unit 9, Corinium Industrial Estate, Raans Road",
    "sg:city":"Amersham",
    "sg:classifiers":[
        {
            "category":"Conference Center",
            "type":"Public Place"
        }
    ],
    "sg:phone":"+44 1494 431026",
    "sg:postcode":"HP6 6JQ",
    "sg:province":"Buckinghamshire",
    "wof:name":"Auditel Systems Ltd.",
    "wof:placetype":"venue"
},
  "geometry": {"coordinates":[-0.596114,51.674656],"type":"Point"}
}