{
  "type": "Feature",
  "properties": {
    "addr:full":"8 York Road, Ash Aldershot Hampshire GU12 6SN",
    "addr:housenumber":"8",
    "addr:postcode":"gu12 6sn",
    "addr:street":"York Road",
    "iso:country":"GB",
    "sg:address":"8 York Road, Ash",
    "sg:city":"Aldershot",
    "sg:classifiers":[
        {
            "category":"Building & Trades",
            "subcategory":"Landscaping Services",
            "type":"Services"
        }
    ],
    "sg:postcode":"GU12 6SN",
    "sg:province":"Hampshire",
    "sg:tags":[
        "gardening"
    ],
    "wof:name":"Stuart  Mulcaster",
    "wof:placetype":"venue"
},
  "geometry": {"coordinates":[-0.722326,51.252838],"type":"Point"}
}