{
  "type": "Feature",
  "properties": {
    "addr:full":"Mill Street Ullapool Highland IV26 2UN",
    "addr:postcode":"iv26 2un",
    "addr:street":"Mill Street",
    "iso:country":"GB",
    "sg:address":"Mill Street",
    "sg:city":"Ullapool",
    "sg:classifiers":[
        {
            "category":"Education",
            "subcategory":"School",
            "type":"Public Place"
        },
        {
            "category":"Government",
            "subcategory":"Office",
            "type":"Public Place"
        }
    ],
    "sg:phone":"+44 1854 612078",
    "sg:postcode":"IV26 2UN",
    "sg:province":"Highland",
    "sg:tags":[
        "local",
        "authority"
    ],
    "wof:name":"ULLAPOOL HIGH SCHOOL",
    "wof:placetype":"venue"
},
  "geometry": {"coordinates":[-5.155544,57.897476],"type":"Point"}
}