{
  "type": "Feature",
  "properties": {
    "iso:country":"GB",
    "sg:address":"Unit 14 Queensway Arches, Livery Street",
    "sg:city":"Birmingham",
    "sg:classifiers":[
        {
            "category":"Shopping",
            "subcategory":"Musical Instruments",
            "type":"Retail Goods"
        }
    ],
    "sg:phone":"+44 121 236 2229",
    "sg:postcode":"B3 1EU",
    "sg:province":"West Midlands",
    "sg:tags":[
        "music",
        "sheet"
    ],
    "wof:name":"City Music (Birmingham) Ltd.",
    "wof:placetype":"venue"
},
  "geometry": {"coordinates":[-1.9010740519,52.4842834473],"type":"Point"}
}