{
  "type": "Feature",
  "properties": {
    "addr:full":"14 Silver St Barnstaple Devon EX32 8HR",
    "addr:housenumber":"14",
    "addr:postcode":"ex32 8hr",
    "addr:street":"Silver St",
    "iso:country":"GB",
    "sg:address":"14 Silver St",
    "sg:city":"Barnstaple",
    "sg:classifiers":[
        {
            "category":"Shopping",
            "subcategory":"Department Store",
            "type":"Retail Goods"
        }
    ],
    "sg:postcode":"EX32 8HR",
    "sg:province":"Devon",
    "wof:name":"On the Bit",
    "wof:placetype":"venue"
},
  "geometry": {"coordinates":[-4.0567722321,51.0791625977],"type":"Point"}
}