{
  "type": "Feature",
  "properties": {
    "iso:country":"GB",
    "sg:address":"16 Pontmorlais",
    "sg:city":"Merthyr Tydfil",
    "sg:classifiers":[
        {
            "category":"Professional",
            "subcategory":"Art Services",
            "type":"Services"
        }
    ],
    "sg:postcode":"CF47 8UB",
    "sg:province":"Merthyr Tydfil",
    "sg:tags":[
        "photographer"
    ],
    "wof:name":"John Yates",
    "wof:placetype":"venue"
},
  "geometry": {"coordinates":[-3.378529,51.749092],"type":"Point"}
}