{
  "type": "Feature",
  "properties": {
    "addr:full":"P O Box 22 Loughton Essex IG10 3BJ",
    "addr:housenumber":"box 22",
    "addr:postcode":"ig10 3bj",
    "addr:street":"P O",
    "iso:country":"GB",
    "sg:address":"P O Box 22",
    "sg:city":"Loughton",
    "sg:classifiers":[
        {
            "category":"Professional",
            "subcategory":"Business Services",
            "type":"Services"
        }
    ],
    "sg:phone":"+44 20 8502 3494",
    "sg:postcode":"IG10 3BJ",
    "sg:province":"Essex",
    "sg:tags":[
        "hospitality",
        "corporate"
    ],
    "wof:name":"Camelot Corporation",
    "wof:placetype":"venue"
},
  "geometry": {"coordinates":[0.055179,51.647373],"type":"Point"}
}