{
  "type": "Feature",
  "properties": {
    "addr:full":"Sheffield House Windermere Cumbria LA23 1DY",
    "addr:postcode":"la23 1dy",
    "iso:country":"GB",
    "sg:address":"Sheffield House",
    "sg:city":"Windermere",
    "sg:classifiers":[
        {
            "category":"Professional",
            "subcategory":"Lawyer & Legal Services",
            "type":"Services"
        }
    ],
    "sg:phone":"+44 15394 88622",
    "sg:postcode":"LA23 1DY",
    "sg:province":"Cumbria",
    "sg:tags":[
        "solicitor"
    ],
    "wof:name":"Stephenson Reynell",
    "wof:placetype":"venue"
},
  "geometry": {"coordinates":[-2.906404,54.379665],"type":"Point"}
}