{
  "type": "Feature",
  "properties": {
    "iso:country":"GB",
    "sg:address":"D Moor Park Business Centre, Thornes Moor Road",
    "sg:city":"Wakefield",
    "sg:classifiers":[
        {
            "category":"Professional",
            "subcategory":"Business Services",
            "type":"Services"
        }
    ],
    "sg:phone":"+44 1924 367770",
    "sg:postcode":"WF2 8PF",
    "sg:province":"West Yorkshire",
    "sg:tags":[
        "distribution"
    ],
    "wof:name":"Abdee Haulage & Storage Ltd.",
    "wof:placetype":"venue"
},
  "geometry": {"coordinates":[-1.510274,53.67997],"type":"Point"}
}