{
  "type": "Feature",
  "properties": {
    "addr:full":"11 Victoria Road, Saltaire Shipley West Yorkshire BD18 3LA",
    "addr:housenumber":"11",
    "addr:postcode":"bd18 3la",
    "addr:street":"Victoria Road;West",
    "iso:country":"GB",
    "sg:address":"11 Victoria Road, Saltaire",
    "sg:city":"Shipley",
    "sg:classifiers":[
        {
            "category":"Real Estate",
            "subcategory":"Architect",
            "type":"Services"
        }
    ],
    "sg:postcode":"BD18 3LA",
    "sg:province":"West Yorkshire",
    "wof:name":"Rance Booth & Smith Llp",
    "wof:placetype":"venue"
},
  "geometry": {"coordinates":[-1.7898999453,53.837726593],"type":"Point"}
}