{
  "type": "Feature",
  "properties": {
    "addr:full":"The Croft, Lock Lane, Cosgrove Milton Keynes Buckinghamshire MK19 7JR",
    "addr:postcode":"mk19 7jr",
    "addr:street":"Lock Lane",
    "iso:country":"GB",
    "sg:address":"The Croft, Lock Lane, Cosgrove",
    "sg:city":"Milton Keynes",
    "sg:classifiers":[
        {
            "category":"Building & Trades",
            "subcategory":"Construction",
            "type":"Services"
        }
    ],
    "sg:phone":"+44 1908 565744",
    "sg:postcode":"MK19 7JR",
    "sg:province":"Buckinghamshire",
    "sg:tags":[
        "builder"
    ],
    "wof:name":"L J Wray Agricultural Engineering",
    "wof:placetype":"venue"
},
  "geometry": {"coordinates":[-0.847837,52.075878],"type":"Point"}
}