{
  "type": "Feature",
  "properties": {
    "addr:full":"The Elms Farm, Bentham Cheltenham Gloucestershire GL51 5TZ",
    "addr:postcode":"gl51 5tz",
    "iso:country":"GB",
    "sg:address":"The Elms Farm, Bentham",
    "sg:city":"Cheltenham",
    "sg:classifiers":[
        {
            "category":"Retail",
            "subcategory":"Auto Repair",
            "type":"Services"
        }
    ],
    "sg:phone":"+44 1452 864040",
    "sg:postcode":"GL51 5TZ",
    "sg:province":"Gloucestershire",
    "sg:tags":[
        "modification",
        "garage"
    ],
    "wof:name":"Bugs Buses & Automobiles",
    "wof:placetype":"venue"
},
  "geometry": {"coordinates":[-2.1272099018,51.8503799438],"type":"Point"}
}