{
  "type": "Feature",
  "properties": {
    "addr:full":"30 Norfolk Street King's Lynn Norfolk PE30 1AL",
    "addr:housenumber":"30",
    "addr:postcode":"pe30 1al",
    "addr:street":"Norfolk Street",
    "iso:country":"GB",
    "sg:address":"30 Norfolk Street",
    "sg:city":"King's Lynn",
    "sg:classifiers":[
        {
            "category":"Shopping",
            "subcategory":"Jewelry",
            "type":"Retail Goods"
        },
        {
            "category":"Real Estate",
            "subcategory":"Architect",
            "type":"Services"
        }
    ],
    "sg:phone":"+44 1553 762221",
    "sg:postcode":"PE30 1AL",
    "sg:province":"Norfolk",
    "sg:tags":[
        "sale",
        "jewellery",
        "gold",
        "silversmith"
    ],
    "wof:name":"Gold Craft",
    "wof:placetype":"venue"
},
  "geometry": {"coordinates":[0.398799,52.755535],"type":"Point"}
}