{
  "type": "Feature",
  "properties": {
    "addr:full":"5 Haden Way, Willingham Cambridge Cambridgeshire CB4 5HB",
    "addr:housenumber":"5",
    "addr:postcode":"cb4 5hb",
    "addr:street":"Haden Way",
    "iso:country":"GB",
    "sg:address":"5 Haden Way, Willingham",
    "sg:city":"Cambridge",
    "sg:classifiers":[
        {
            "category":"Freight",
            "type":"Transportation"
        }
    ],
    "sg:phone":"+44 1954 260161",
    "sg:postcode":"CB4 5HB",
    "sg:province":"Cambridgeshire",
    "sg:tags":[
        "haulage",
        "road"
    ],
    "wof:name":"D M Wells Transport",
    "wof:placetype":"venue"
},
  "geometry": {"coordinates":[0.049706,52.311413],"type":"Point"}
}