{
  "type": "Feature",
  "properties": {
    "addr:full":"Fife Court, Fife Crescent, Bothwell Glasgow Glasgow City G71 8DG",
    "addr:postcode":"g71 8dg",
    "addr:street":"Fife Court Fife Crescent",
    "iso:country":"GB",
    "sg:address":"Fife Court, Fife Crescent, Bothwell",
    "sg:city":"Glasgow",
    "sg:classifiers":[
        {
            "category":"Organizations",
            "subcategory":"Community Association",
            "type":"Services"
        }
    ],
    "sg:phone":"+44 1698 853430",
    "sg:postcode":"G71 8DG",
    "sg:province":"Glasgow City",
    "sg:tags":[
        "co-operatives",
        "society",
        "housing",
        "trust"
    ],
    "sg:website":"http://www.bield.co.uk",
    "wof:name":"Bield Housing Association Ltd",
    "wof:placetype":"venue"
},
  "geometry": {"coordinates":[-4.069311,55.801685],"type":"Point"}
}