{
  "type": "Feature",
  "properties": {
    "addr:full":"Chapel Loan Roslin Midlothian EH25 9PU",
    "addr:postcode":"eh25 9pu",
    "addr:street":"Loan",
    "iso:country":"GB",
    "sg:address":"Chapel Loan",
    "sg:city":"Roslin",
    "sg:classifiers":[
        {
            "category":"Landmark",
            "subcategory":"Tourist Attraction",
            "type":"Public Place"
        }
    ],
    "sg:phone":"+44 131 440 2159",
    "sg:postcode":"EH25 9PU",
    "sg:province":"Midlothian",
    "sg:tags":[
        "interest"
    ],
    "wof:name":"Rosslyn Chapel Trading Co. Ltd",
    "wof:placetype":"venue"
},
  "geometry": {"coordinates":[-3.16221,55.856243],"type":"Point"}
}