{
  "type": "Feature",
  "properties": {
    "iso:country":"GB",
    "sg:address":"Rochester Way",
    "sg:city":"Dartford",
    "sg:classifiers":[
        {
            "category":"Professional",
            "subcategory":"Engineering",
            "type":"Services"
        },
        {
            "category":"Professional",
            "subcategory":"Detective & Security Services",
            "type":"Services"
        }
    ],
    "sg:postcode":"DA1 3QU",
    "sg:province":"Kent",
    "sg:tags":[
        "burglar",
        "alarm",
        "system",
        "contractor",
        "electrical",
        "engineer"
    ],
    "wof:name":"Galco Electrical & Security Services",
    "wof:placetype":"venue"
},
  "geometry": {"coordinates":[0.17417,51.441406],"type":"Point"}
}