{
  "type": "Feature",
  "properties": {
    "addr:full":"55 Linden Gardens London Greater London W4 2EH",
    "addr:housenumber":"55",
    "addr:postcode":"w4 2eh",
    "addr:street":"Linden Gardens",
    "iso:country":"GB",
    "sg:address":"55 Linden Gardens",
    "sg:city":"London",
    "sg:classifiers":[
        {
            "category":"Arts & Performance",
            "subcategory":"Art Gallery",
            "type":"Entertainment"
        }
    ],
    "sg:postcode":"W4 2EH",
    "sg:province":"Greater London",
    "wof:name":"Narwhal Inuit Art Education Foundation",
    "wof:placetype":"venue"
},
  "geometry": {"coordinates":[-0.2583310008,51.4916038513],"type":"Point"}
}