{
  "type": "Feature",
  "properties": {
    "iso:country":"GB",
    "sg:address":"1 Cygnus Way",
    "sg:city":"West Bromwich",
    "sg:classifiers":[
        {
            "category":"Manufacturing",
            "subcategory":"Rubber & Plastics",
            "type":"Manufacturing & Wholesale Goods"
        }
    ],
    "sg:phone":"+44 121 557 1234",
    "sg:postcode":"B70 0XB",
    "sg:province":"West Midlands",
    "sg:tags":[
        "product",
        "foam"
    ],
    "wof:name":"E R Carpenter",
    "wof:placetype":"venue"
},
  "geometry": {"coordinates":[-2.022367,52.529724],"type":"Point"}
}