{
  "type": "Feature",
  "properties": {
    "iso:country":"GB",
    "sg:address":"Garrod House, Manby Park",
    "sg:city":"Louth",
    "sg:classifiers":[
        {
            "category":"Shopping",
            "subcategory":"Pharmacy",
            "type":"Retail Goods"
        }
    ],
    "sg:phone":"+44 1507 329100",
    "sg:postcode":"LN11 8UT",
    "sg:province":"Lincolnshire",
    "sg:tags":[
        "medicine",
        "therapy"
    ],
    "wof:name":"Good Healthkeeping Ltd.",
    "wof:placetype":"venue"
},
  "geometry": {"coordinates":[0.097396,53.367245],"type":"Point"}
}