{
  "type": "Feature",
  "properties": {
    "addr:full":"20-22 Regent Way Hamilton South Lanarkshire ML3 7DZ",
    "addr:housenumber":"20-22",
    "addr:postcode":"ml3 7dz",
    "addr:street":"Regent Way",
    "iso:country":"GB",
    "sg:address":"20-22 Regent Way",
    "sg:city":"Hamilton",
    "sg:classifiers":[
        {
            "category":"Shopping",
            "subcategory":"Clothing, Apparel, & Fashions",
            "type":"Retail Goods"
        }
    ],
    "sg:phone":"+44 1698 284429",
    "sg:postcode":"ML3 7DZ",
    "sg:province":"South Lanarkshire",
    "sg:tags":[
        "shop"
    ],
    "wof:name":"Evans Ltd",
    "wof:placetype":"venue"
},
  "geometry": {"coordinates":[-4.015937,55.768982],"type":"Point"}
}