{
  "type": "Feature",
  "properties": {
    "addr:full":"P O Box 203 Redhill Surrey RH1 6YU",
    "addr:housenumber":"203",
    "addr:postcode":"rh1 6yu",
    "addr:street":"P O Box",
    "iso:country":"GB",
    "sg:address":"P O Box 203",
    "sg:city":"Redhill",
    "sg:classifiers":[
        {
            "category":"Professional",
            "type":"Services"
        }
    ],
    "sg:phone":"+44 70 0056 0793",
    "sg:postcode":"RH1 6YU",
    "sg:province":"Surrey",
    "sg:tags":[
        "repair",
        "tech",
        "maintenance"
    ],
    "wof:name":"Orion Computing Ltd.",
    "wof:placetype":"venue"
},
  "geometry": {"coordinates":[-0.172549,51.230831],"type":"Point"}
}