{
  "type": "Feature",
  "properties": {
    "addr:full":"23 Ridgeway Close, Farnsfield Newark Nottinghamshire NG22 8DT",
    "addr:housenumber":"23",
    "addr:postcode":"ng22 8dt",
    "addr:street":"Ridgeway Close",
    "iso:country":"GB",
    "sg:address":"23 Ridgeway Close, Farnsfield",
    "sg:city":"Newark",
    "sg:classifiers":[
        {
            "category":"Building & Trades",
            "subcategory":"Construction",
            "type":"Services"
        }
    ],
    "sg:postcode":"NG22 8DT",
    "sg:province":"Nottinghamshire",
    "sg:tags":[
        "joiner",
        "carpenter"
    ],
    "wof:name":"Stuart Joinery",
    "wof:placetype":"venue"
},
  "geometry": {"coordinates":[-1.0307409763,53.1047935486],"type":"Point"}
}