{
  "type": "Feature",
  "properties": {
    "iso:country":"GB",
    "sg:address":"10 Station Rd",
    "sg:city":"Manningtree",
    "sg:classifiers":[
        {
            "category":"Shopping",
            "subcategory":"Department Store",
            "type":"Retail Goods"
        },
        {
            "category":"Shopping",
            "subcategory":"Crafts & Fabrics",
            "type":"Retail Goods"
        }
    ],
    "sg:postcode":"CO11 1AA",
    "sg:province":"Essex",
    "sg:tags":[
        "shop",
        "needlecraft",
        "wool"
    ],
    "wof:name":"Harding,Christine,",
    "wof:placetype":"venue"
},
  "geometry": {"coordinates":[1.060761,51.945602],"type":"Point"}
}