{
  "type": "Feature",
  "properties": {
    "iso:country":"GB",
    "sg:address":"95 Mansfield Rd",
    "sg:city":"Sutton In Ashfield",
    "sg:classifiers":[
        {
            "category":"Communications",
            "type":"Services"
        }
    ],
    "sg:phone":"+44 1623 472875",
    "sg:postcode":"NG17 4FL",
    "sg:province":"Nottinghamshire",
    "sg:tags":[
        "telecommunication"
    ],
    "wof:name":"Powercom",
    "wof:placetype":"venue"
},
  "geometry": {"coordinates":[-1.253013,53.131363],"type":"Point"}
}