{
  "type": "Feature",
  "properties": {
    "addr:full":"443-447 Millbrook Road West Southampton Hampshire SO15 0HX",
    "addr:housenumber":"443-447",
    "addr:postcode":"so15 0hx",
    "addr:street":"Millbrook Road West",
    "iso:country":"GB",
    "sg:address":"443-447 Millbrook Road West",
    "sg:city":"Southampton",
    "sg:classifiers":[
        {
            "category":"Food & Beverages",
            "subcategory":"Groceries & Convenience Stores",
            "type":"Retail Goods"
        }
    ],
    "sg:phone":"+44 23 8077 4384",
    "sg:postcode":"SO15 0HX",
    "sg:province":"Hampshire",
    "wof:name":"One Stop Community Stores Ltd",
    "wof:placetype":"venue"
},
  "geometry": {"coordinates":[-1.4475799799,50.9139556885],"type":"Point"}
}