{
  "type": "Feature",
  "properties": {
    "addr:full":"49 Carlton St Hartlepool Durham TS26 9EP",
    "addr:housenumber":"49",
    "addr:postcode":"ts26 9ep",
    "addr:street":"Carlton St",
    "iso:country":"GB",
    "sg:address":"49 Carlton St",
    "sg:city":"Hartlepool",
    "sg:classifiers":[
        {
            "category":"Home & Garden",
            "subcategory":"Hardware",
            "type":"Retail Goods"
        }
    ],
    "sg:phone":"+44 1429 281555",
    "sg:postcode":"TS26 9EP",
    "sg:province":"Durham",
    "sg:tags":[
        "equipment",
        "bathroom",
        "fitting"
    ],
    "wof:name":"Mansel Bathrooms Direct",
    "wof:placetype":"venue"
},
  "geometry": {"coordinates":[-1.219085,54.683224],"type":"Point"}
}