{
  "type": "Feature",
  "properties": {
    "addr:full":"7 Bradbourne Vale Road Sevenoaks Kent TN13 3QQ",
    "addr:housenumber":"7",
    "addr:postcode":"tn13 3qq",
    "addr:street":"Bradbourne Vale Road",
    "iso:country":"GB",
    "sg:address":"7 Bradbourne Vale Road",
    "sg:city":"Sevenoaks",
    "sg:classifiers":[
        {
            "category":"Government",
            "subcategory":"Office",
            "type":"Public Place"
        }
    ],
    "sg:phone":"+44 1732 465604",
    "sg:postcode":"TN13 3QQ",
    "sg:province":"Kent",
    "sg:tags":[
        "education",
        "agency",
        "authority"
    ],
    "wof:name":"Sevenoaks Vineyard Church",
    "wof:placetype":"venue"
},
  "geometry": {"coordinates":[0.1924930066,51.2878189087],"type":"Point"}
}