{
  "type": "Feature",
  "properties": {
    "addr:full":"8 Church End, Potterspury Towcester Buckinghamshire NN12 7PX",
    "addr:housenumber":"8",
    "addr:postcode":"nn12 7px",
    "addr:street":"Church End",
    "iso:country":"GB",
    "sg:address":"8 Church End, Potterspury",
    "sg:city":"Towcester",
    "sg:classifiers":[
        {
            "category":"Banks & Credit Unions",
            "subcategory":"Financial Services",
            "type":"Services"
        }
    ],
    "sg:phone":"+44 1908 542941",
    "sg:postcode":"NN12 7PX",
    "sg:province":"Buckinghamshire",
    "sg:tags":[
        "consultant"
    ],
    "wof:name":"Brian Taylor & Co.",
    "wof:placetype":"venue"
},
  "geometry": {"coordinates":[-0.890281,52.082127],"type":"Point"}
}