{
  "type": "Feature",
  "properties": {
    "addr:full":"148 Culvert Road Battersea Greater London SW11 5AY",
    "addr:housenumber":"148",
    "addr:postcode":"sw11 5ay",
    "addr:street":"Culvert Road",
    "iso:country":"GB",
    "sg:address":"148 Culvert Road",
    "sg:city":"Battersea",
    "sg:classifiers":[
        {
            "category":"Retail",
            "subcategory":"Auto Repair",
            "type":"Services"
        }
    ],
    "sg:phone":"+44 20 7622 4576",
    "sg:postcode":"SW11 5AY",
    "sg:province":"Greater London",
    "sg:tags":[
        "modification",
        "garage"
    ],
    "wof:name":"Latchmere Motor Spares",
    "wof:placetype":"venue"
},
  "geometry": {"coordinates":[-0.1569049954,51.4699516296],"type":"Point"}
}