{
  "type": "Feature",
  "properties": {
    "iso:country":"GB",
    "sg:address":"17 Boston Rd",
    "sg:city":"Boston",
    "sg:classifiers":[
        {
            "category":"Food & Beverages",
            "subcategory":"Supermarket",
            "type":"Retail Goods"
        }
    ],
    "sg:phone":"+44 1205 722327",
    "sg:postcode":"PE20 1DT",
    "sg:province":"Lincolnshire",
    "wof:name":"Costcutter",
    "wof:placetype":"venue"
},
  "geometry": {"coordinates":[-0.057865,52.930519],"type":"Point"}
}