{
  "type": "Feature",
  "properties": {
    "iso:country":"GB",
    "sg:address":"49-50 Mere St",
    "sg:city":"Diss",
    "sg:classifiers":[
        {
            "category":"Banks & Credit Unions",
            "subcategory":"Bank",
            "type":"Services"
        }
    ],
    "sg:phone":"+44 1603 219219",
    "sg:postcode":"IP22 3AJ",
    "sg:province":"Norfolk",
    "wof:name":"NatWest",
    "wof:placetype":"venue"
},
  "geometry": {"coordinates":[1.108816,52.375557],"type":"Point"}
}