{
  "type": "Feature",
  "properties": {
    "iso:country":"GB",
    "sg:address":"Suite 12, Hilton Ct, 2 North Hill Rd",
    "sg:city":"Leeds",
    "sg:classifiers":[
        {
            "category":"Health Services",
            "subcategory":"Health Practitioner",
            "type":"Services"
        }
    ],
    "sg:phone":"+44 113 274 6046",
    "sg:postcode":"LS6 2EN",
    "sg:province":"West Yorkshire",
    "sg:tags":[
        "homoeopathic"
    ],
    "wof:name":"Leeds Centre Of Homoeopathy",
    "wof:placetype":"venue"
},
  "geometry": {"coordinates":[-1.5671999454,53.8164291382],"type":"Point"}
}