{
  "type": "Feature",
  "properties": {
    "iso:country":"GB",
    "sg:address":"2-5 Bradley Street",
    "sg:city":"Brierley Hill",
    "sg:classifiers":[
        {
            "category":"Organizations",
            "subcategory":"Membership Organization",
            "type":"Services"
        }
    ],
    "sg:phone":"+44 1384 78014",
    "sg:postcode":"DY5 4RJ",
    "sg:province":"West Midlands",
    "sg:tags":[
        "club"
    ],
    "wof:name":"B Roger",
    "wof:placetype":"venue"
},
  "geometry": {"coordinates":[-2.133749,52.49987],"type":"Point"}
}