{
  "type": "Feature",
  "properties": {
    "addr:full":"1 The Cotts Fordingbridge Dorset SP6 2PH",
    "addr:housenumber":"1",
    "addr:postcode":"sp6 2ph",
    "addr:street":"The Cotts",
    "iso:country":"GB",
    "sg:address":"1 The Cotts",
    "sg:city":"Fordingbridge",
    "sg:classifiers":[
        {
            "category":"Autos & Motor Vehicles",
            "subcategory":"Automobile Sales",
            "type":"Retail Goods"
        }
    ],
    "sg:postcode":"SP6 2PH",
    "sg:province":"Dorset",
    "sg:tags":[
        "car"
    ],
    "wof:name":"Yeomans,G,",
    "wof:placetype":"venue"
},
  "geometry": {"coordinates":[-1.758113,50.942162],"type":"Point"}
}