{
  "type": "Feature",
  "properties": {
    "iso:country":"GB",
    "sg:address":"12a The Broadway",
    "sg:city":"Woking",
    "sg:classifiers":[
        {
            "category":"Professional",
            "subcategory":"Accounting & Tax Preparation",
            "type":"Services"
        }
    ],
    "sg:phone":"+44 1483 723952",
    "sg:postcode":"GU21 5AP",
    "sg:province":"Surrey",
    "sg:tags":[
        "accountant"
    ],
    "wof:name":"Key Pearson & Co.",
    "wof:placetype":"venue"
},
  "geometry": {"coordinates":[-0.556015,51.319359],"type":"Point"}
}