{
  "type": "Feature",
  "properties": {
    "iso:country":"GB",
    "sg:address":"The Boat House, Bridge Road",
    "sg:city":"Cardiff",
    "sg:classifiers":[
        {
            "category":"Professional",
            "subcategory":"Business Services",
            "type":"Services"
        },
        {
            "category":"Arena",
            "subcategory":"Sports Club",
            "type":"Entertainment"
        }
    ],
    "sg:postcode":"CF5 2PT",
    "sg:province":"Cardiff",
    "sg:tags":[
        "hospitality",
        "corporate"
    ],
    "wof:name":"Llandaff Rowing Club",
    "wof:placetype":"venue"
},
  "geometry": {"coordinates":[-3.225514,51.498211],"type":"Point"}
}