{
  "type": "Feature",
  "properties": {
    "addr:full":"190 Tulse Hill London Greater London SW2 3BU",
    "addr:housenumber":"190",
    "addr:postcode":"sw2 3bu",
    "addr:street":"Tulse Hill",
    "iso:country":"GB",
    "sg:address":"190 Tulse Hill",
    "sg:city":"London",
    "sg:classifiers":[
        {
            "category":"Fast Food",
            "type":"Food & Drink"
        }
    ],
    "sg:postcode":"SW2 3BU",
    "sg:province":"Greater London",
    "sg:tags":[
        "away",
        "take"
    ],
    "wof:name":"Safi Udin",
    "wof:placetype":"venue"
},
  "geometry": {"coordinates":[-0.107321,51.441166],"type":"Point"}
}