{
  "type": "Feature",
  "properties": {
    "addr:full":"1 Mottram Moor, Mottram Hyde Cheshire SK14 6LA",
    "addr:housenumber":"1",
    "addr:postcode":"sk14 6la",
    "addr:street":"Mottram Moor Mottram Hyde",
    "iso:country":"GB",
    "sg:address":"1 Mottram Moor, Mottram",
    "sg:city":"Hyde",
    "sg:classifiers":[
        {
            "category":"Shopping",
            "subcategory":"News",
            "type":"Retail Goods"
        }
    ],
    "sg:postcode":"SK14 6LA",
    "sg:province":"Cheshire",
    "sg:tags":[
        "newsagent"
    ],
    "wof:name":"G M & A Armstrong",
    "wof:placetype":"venue"
},
  "geometry": {"coordinates":[-2.0184791088,53.4441986084],"type":"Point"}
}