{
  "type": "Feature",
  "properties": {
    "iso:country":"GB",
    "sg:address":"9 Colvilles Road",
    "sg:city":"Glasgow",
    "sg:classifiers":[
        {
            "category":"Manufacturing",
            "subcategory":"Rubber & Plastics",
            "type":"Manufacturing & Wholesale Goods"
        }
    ],
    "sg:phone":"+44 1355 228777",
    "sg:postcode":"G75 0RS",
    "sg:province":"South Lanarkshire",
    "sg:tags":[
        "product"
    ],
    "wof:name":"M M K (Plastics) Ltd.",
    "wof:placetype":"venue"
},
  "geometry": {"coordinates":[-4.161315,55.748459],"type":"Point"}
}