{
  "type": "Feature",
  "properties": {
    "addr:full":"70 Aigburth Road, Aigburth Liverpool Merseyside L17 7BN",
    "addr:housenumber":"70",
    "addr:postcode":"l17 7bn",
    "addr:street":"Aigburth Road",
    "iso:country":"GB",
    "sg:address":"70 Aigburth Road, Aigburth",
    "sg:city":"Liverpool",
    "sg:classifiers":[
        {
            "category":"Retail",
            "subcategory":"Repair Shop",
            "type":"Services"
        }
    ],
    "sg:phone":"+44 151 727 7175",
    "sg:postcode":"L17 7BN",
    "sg:province":"Merseyside",
    "sg:tags":[
        "radio",
        "television",
        "video"
    ],
    "wof:name":"Aigburth T V",
    "wof:placetype":"venue"
},
  "geometry": {"coordinates":[-2.9535830021,53.3805580139],"type":"Point"}
}