{
  "type": "Feature",
  "properties": {
    "iso:country":"GB",
    "sg:address":"Richmond House, 1 Rumford Place",
    "sg:city":"Liverpool",
    "sg:classifiers":[
        {
            "category":"Professional",
            "subcategory":"Lawyer & Legal Services",
            "type":"Services"
        }
    ],
    "sg:phone":"+44 151 227 2601",
    "sg:postcode":"L3 9QW",
    "sg:province":"Merseyside",
    "sg:tags":[
        "solicitor"
    ],
    "wof:name":"Weightmans Ltd.",
    "wof:placetype":"venue"
},
  "geometry": {"coordinates":[-2.993997,53.407707],"type":"Point"}
}