{
  "type": "Feature",
  "properties": {
    "iso:country":"GB",
    "sg:address":"Woodpecker Lodge, Bere Aller",
    "sg:city":"Langport",
    "sg:classifiers":[
        {
            "category":"Farming",
            "subcategory":"Dairy Farm",
            "type":"Manufacturing & Wholesale Goods"
        },
        {
            "category":"Farming",
            "subcategory":"Livestock Farm",
            "type":"Manufacturing & Wholesale Goods"
        }
    ],
    "sg:phone":"+44 1458 250166",
    "sg:postcode":"TA10 0QX",
    "sg:province":"Somerset",
    "sg:tags":[
        "others",
        "farmer"
    ],
    "wof:name":"E J & A C M LOCKYEAR",
    "wof:placetype":"venue"
},
  "geometry": {"coordinates":[-2.857132,51.060043],"type":"Point"}
}