{
  "type": "Feature",
  "properties": {
    "addr:full":"103 Victoria Road Plymouth Devon PL5 1RX",
    "addr:housenumber":"103",
    "addr:postcode":"pl5 1rx",
    "addr:street":"Victoria Road",
    "iso:country":"GB",
    "sg:address":"103 Victoria Road",
    "sg:city":"Plymouth",
    "sg:classifiers":[
        {
            "category":"Home & Garden",
            "subcategory":"Household Appliances",
            "type":"Retail Goods"
        }
    ],
    "sg:postcode":"PL5 1RX",
    "sg:province":"Devon",
    "sg:tags":[
        "electrical"
    ],
    "wof:name":"Electricare",
    "wof:placetype":"venue"
},
  "geometry": {"coordinates":[-4.1818790436,50.4089012146],"type":"Point"}
}