{
  "type": "Feature",
  "properties": {
    "addr:full":"Unit 5, St Clare Business Park, Holly Road Hampton Greater London TW12 1PZ",
    "addr:housenumber":"unit 5",
    "addr:postcode":"tw12 1pz",
    "addr:street":"St Clare Business Park Holly Road",
    "iso:country":"GB",
    "sg:address":"Unit 5, St Clare Business Park, Holly Road",
    "sg:city":"Hampton",
    "sg:classifiers":[
        {
            "category":"Manufacturing",
            "subcategory":"Building Materials",
            "type":"Manufacturing & Wholesale Goods"
        }
    ],
    "sg:phone":"+44 20 8783 1776",
    "sg:postcode":"TW12 1PZ",
    "sg:province":"Greater London",
    "sg:tags":[
        "flag",
        "banner"
    ],
    "wof:name":"Banaman",
    "wof:placetype":"venue"
},
  "geometry": {"coordinates":[-0.362314,51.43071],"type":"Point"}
}