{
  "type": "Feature",
  "properties": {
    "addr:full":"4 Temple Chambers, Temple Street Swindon Wiltshire SN1 1SQ",
    "addr:housenumber":"4",
    "addr:postcode":"sn1 1sq",
    "addr:street":"Temple Chambers Temple Street",
    "iso:country":"GB",
    "sg:address":"4 Temple Chambers, Temple Street",
    "sg:city":"Swindon",
    "sg:classifiers":[
        {
            "category":"Professional",
            "subcategory":"Employment Agencies",
            "type":"Services"
        }
    ],
    "sg:phone":"+44 1793 549200",
    "sg:postcode":"SN1 1SQ",
    "sg:province":"Wiltshire",
    "sg:tags":[
        "career",
        "guidance"
    ],
    "wof:name":"Lifetime Careers Wiltshire Ltd.",
    "wof:placetype":"venue"
},
  "geometry": {"coordinates":[-1.7818139791,51.5617637634],"type":"Point"}
}