{
  "type": "Feature",
  "properties": {
    "addr:full":"Victoria Road Halesowen West Midlands B62 8HZ",
    "addr:postcode":"b62 8hz",
    "addr:street":"Victoria Road",
    "iso:country":"GB",
    "sg:address":"Victoria Road",
    "sg:city":"Halesowen",
    "sg:classifiers":[
        {
            "category":"Retail",
            "subcategory":"Auto Repair",
            "type":"Services"
        }
    ],
    "sg:phone":"+44 121 559 4433",
    "sg:postcode":"B62 8HZ",
    "sg:province":"West Midlands",
    "sg:tags":[
        "modification",
        "garage"
    ],
    "wof:name":"Peter Maddocks",
    "wof:placetype":"venue"
},
  "geometry": {"coordinates":[-2.0367050171,52.4715843201],"type":"Point"}
}