{
  "type": "Feature",
  "properties": {
    "iso:country":"GB",
    "sg:address":"Unit 1 Block 132 Colquhoun Park, Hillington Indust Est",
    "sg:city":"Glasgow",
    "sg:classifiers":[
        {
            "category":"Wholesale",
            "subcategory":"Home Furnishings",
            "type":"Manufacturing & Wholesale Goods"
        }
    ],
    "sg:phone":"+44 141 882 6240",
    "sg:postcode":"G52 2BP",
    "sg:province":"Glasgow City",
    "sg:tags":[
        "wsale",
        "rug",
        "carpet"
    ],
    "wof:name":"K I F Associates",
    "wof:placetype":"venue"
},
  "geometry": {"coordinates":[-4.34735,55.84734],"type":"Point"}
}