{
  "type": "Feature",
  "properties": {
    "addr:full":"Magdaline Cottage, 3 Sempringham Fen, Sempringham Sleaford Lincolnshire NG34 0LA",
    "addr:housenumber":"3",
    "addr:postcode":"ng34 0la",
    "addr:street":"Sempringham Fen",
    "iso:country":"GB",
    "sg:address":"Magdaline Cottage, 3 Sempringham Fen, Sempringham",
    "sg:city":"Sleaford",
    "sg:classifiers":[
        {
            "category":"Home & Garden",
            "subcategory":"Building Materials",
            "type":"Retail Goods"
        },
        {
            "category":"Building & Trades",
            "subcategory":"Locksmith",
            "type":"Services"
        }
    ],
    "sg:phone":"+44 1529 240609",
    "sg:postcode":"NG34 0LA",
    "sg:province":"Lincolnshire",
    "sg:tags":[
        "hinge"
    ],
    "wof:name":"MTM",
    "wof:placetype":"venue"
},
  "geometry": {"coordinates":[-0.3411990106,52.8852310181],"type":"Point"}
}