{
  "type": "Feature",
  "properties": {
    "addr:full":"181 Falcondale Road Bristol City of Bristol BS9 3JJ",
    "addr:housenumber":"181",
    "addr:postcode":"bs9 3jj",
    "addr:street":"Falcondale Road",
    "iso:country":"GB",
    "sg:address":"181 Falcondale Road",
    "sg:city":"Bristol",
    "sg:classifiers":[
        {
            "category":"Education",
            "subcategory":"Dance Studio",
            "type":"Public Place"
        }
    ],
    "sg:postcode":"BS9 3JJ",
    "sg:province":"City of Bristol",
    "sg:tags":[
        "school",
        "dancing"
    ],
    "wof:name":"Bristol Ballet Centre",
    "wof:placetype":"venue"
},
  "geometry": {"coordinates":[-2.6185200214,51.4972915649],"type":"Point"}
}