{
  "type": "Feature",
  "properties": {
    "addr:full":"41 Pingle Drive Bicester Oxfordshire OX26 6WD",
    "addr:housenumber":"41",
    "addr:postcode":"ox26 6wd",
    "addr:street":"Pingle Drive",
    "iso:country":"GB",
    "sg:address":"41 Pingle Drive",
    "sg:city":"Bicester",
    "sg:classifiers":[
        {
            "category":"Shopping",
            "subcategory":"Clothing, Apparel, & Fashions",
            "type":"Retail Goods"
        },
        {
            "category":"Home & Garden",
            "subcategory":"Kitchen Supply",
            "type":"Retail Goods"
        }
    ],
    "sg:phone":"+44 1869 323278",
    "sg:postcode":"OX26 6WD",
    "sg:province":"Oxfordshire",
    "sg:tags":[
        "outdoor",
        "equipment",
        "china",
        "glassware",
        "sport",
        "clothing"
    ],
    "sg:website":"http://www.top24.com",
    "wof:name":"Tog 24",
    "wof:placetype":"venue"
},
  "geometry": {"coordinates":[-1.1563600302,51.893081665],"type":"Point"}
}