{
  "type": "Feature",
  "properties": {
    "addr:full":"34 The Mkt, Wrythe La Carshalton Surrey SM5 1AG",
    "addr:housenumber":"34",
    "addr:postcode":"sm5 1ag",
    "addr:street":"The;La Carshalton",
    "iso:country":"GB",
    "sg:address":"34 The Mkt, Wrythe La",
    "sg:city":"Carshalton",
    "sg:classifiers":[
        {
            "category":"Shopping",
            "subcategory":"Gifts & Souvenirs",
            "type":"Retail Goods"
        }
    ],
    "sg:postcode":"SM5 1AG",
    "sg:province":"Surrey",
    "sg:tags":[
        "poster",
        "card"
    ],
    "wof:name":"Baldwin,R,",
    "wof:placetype":"venue"
},
  "geometry": {"coordinates":[-0.1712590009,51.3797912598],"type":"Point"}
}