{
  "type": "Feature",
  "properties": {
    "iso:country":"GB",
    "sg:address":"Riverside House",
    "sg:city":"Carlisle",
    "sg:classifiers":[
        {
            "category":"Taxi",
            "type":"Transportation"
        }
    ],
    "sg:phone":"+44 1228 542020",
    "sg:postcode":"CA1 2BS",
    "sg:province":"Cumbria",
    "sg:tags":[
        "mini",
        "cab"
    ],
    "wof:name":"Shankland Taxis",
    "wof:placetype":"venue"
},
  "geometry": {"coordinates":[-2.907959,54.89003],"type":"Point"}
}