{
  "type": "Feature",
  "properties": {
    "addr:full":"29 Sangers Drive Horley Surrey RH6 8AH",
    "addr:housenumber":"29",
    "addr:postcode":"rh6 8ah",
    "addr:street":"Sangers Drive",
    "iso:country":"GB",
    "sg:address":"29 Sangers Drive",
    "sg:city":"Horley",
    "sg:classifiers":[
        {
            "category":"Health Services",
            "subcategory":"Health Practitioner",
            "type":"Services"
        }
    ],
    "sg:postcode":"RH6 8AH",
    "sg:province":"Surrey",
    "sg:tags":[
        "acupuncture"
    ],
    "wof:name":"Eileen McManus",
    "wof:placetype":"venue"
},
  "geometry": {"coordinates":[-0.17121,51.172268],"type":"Point"}
}