{
  "type": "Feature",
  "properties": {
    "iso:country":"GB",
    "sg:address":"Kingfisher Drive, Merrow",
    "sg:city":"Guildford",
    "sg:classifiers":[
        {
            "category":"Food & Beverages",
            "subcategory":"Liquor & Beverages",
            "type":"Retail Goods"
        }
    ],
    "sg:phone":"+44 1483 571822",
    "sg:postcode":"GU4 7EW",
    "sg:province":"Surrey",
    "sg:tags":[
        "beer",
        "spirit",
        "wines"
    ],
    "wof:name":"Cheers Wine Merchants",
    "wof:placetype":"venue"
},
  "geometry": {"coordinates":[-0.536629,51.252361],"type":"Point"}
}