{
  "type": "Feature",
  "properties": {
    "addr:full":"22 High Street Romford Essex RM1 1HR",
    "addr:housenumber":"22",
    "addr:postcode":"rm1 1hr",
    "addr:street":"High Street",
    "iso:country":"GB",
    "sg:address":"22 High Street",
    "sg:city":"Romford",
    "sg:classifiers":[
        {
            "category":"Home & Garden",
            "subcategory":"Furniture",
            "type":"Retail Goods"
        }
    ],
    "sg:postcode":"RM1 1HR",
    "sg:province":"Essex",
    "wof:name":"Exmoor Pine",
    "wof:placetype":"venue"
},
  "geometry": {"coordinates":[0.1792950034,51.5780830383],"type":"Point"}
}