{
  "type": "Feature",
  "properties": {
    "addr:full":"Hazels Gararage Harwich Rd, Great Bromley Colchester Essex CO7 7UL",
    "addr:postcode":"co7 7ul",
    "addr:street":"Harwich Rd",
    "iso:country":"GB",
    "sg:address":"Hazels Gararage Harwich Rd, Great Bromley",
    "sg:city":"Colchester",
    "sg:classifiers":[
        {
            "category":"Retail",
            "subcategory":"Auto Repair",
            "type":"Services"
        }
    ],
    "sg:phone":"+44 1206 250999",
    "sg:postcode":"CO7 7UL",
    "sg:province":"Essex",
    "sg:tags":[
        "body",
        "car"
    ],
    "wof:name":"T Hastings Commercial Repairs",
    "wof:placetype":"venue"
},
  "geometry": {"coordinates":[1.027215004,51.8935279846],"type":"Point"}
}