{
  "type": "Feature",
  "properties": {
    "addr:full":"1 Brighton Hill Parade, Brighton Hill Shopping Centre Basingstoke Hampshire RG22 4EH",
    "addr:housenumber":"1",
    "addr:postcode":"rg22 4eh",
    "addr:street":"Brighton Hill Parade;Shopping Centre",
    "iso:country":"GB",
    "sg:address":"1 Brighton Hill Parade, Brighton Hill Shopping Centre",
    "sg:city":"Basingstoke",
    "sg:classifiers":[
        {
            "category":"Real Estate",
            "subcategory":"Real Estate Agent",
            "type":"Services"
        }
    ],
    "sg:phone":"+44 1256 816800",
    "sg:postcode":"RG22 4EH",
    "sg:province":"Hampshire",
    "wof:name":"Redwoods",
    "wof:placetype":"venue"
},
  "geometry": {"coordinates":[-1.1119630337,51.2481307983],"type":"Point"}
}