{
  "type": "Feature",
  "properties": {
    "addr:full":"Hall La Hitchin Hertfordshire SG4 8RD",
    "addr:postcode":"sg4 8rd",
    "addr:street":"La Hitchin",
    "iso:country":"GB",
    "sg:address":"Hall La",
    "sg:city":"Hitchin",
    "sg:classifiers":[
        {
            "category":"Government",
            "subcategory":"City Hall",
            "type":"Public Place"
        }
    ],
    "sg:phone":"+44 1438 833049",
    "sg:postcode":"SG4 8RD",
    "sg:province":"Hertfordshire",
    "wof:name":"Kimpton Memorial Hall",
    "wof:placetype":"venue"
},
  "geometry": {"coordinates":[-0.296833992,51.8506393433],"type":"Point"}
}