{
  "type": "Feature",
  "properties": {
    "addr:full":"The Old Bakehouse, 1242a Evesham Rd Redditch Warwickshire B96 6AA",
    "addr:housenumber":"1242a",
    "addr:postcode":"b96 6aa",
    "addr:street":"Evesham Rd",
    "iso:country":"GB",
    "sg:address":"The Old Bakehouse, 1242a Evesham Rd",
    "sg:city":"Redditch",
    "sg:classifiers":[
        {
            "category":"Arts & Performance",
            "subcategory":"Art Gallery",
            "type":"Entertainment"
        }
    ],
    "sg:phone":"+44 1527 893557",
    "sg:postcode":"B96 6AA",
    "sg:province":"Warwickshire",
    "wof:name":"Bracebridge Gallery",
    "wof:placetype":"venue"
},
  "geometry": {"coordinates":[-1.9376000166,52.2599487305],"type":"Point"}
}