{
  "type": "Feature",
  "properties": {
    "addr:full":"24 Woods Road, Caversham Reading Berkshire RG4 6NA",
    "addr:housenumber":"24",
    "addr:postcode":"rg4 6na",
    "addr:street":"Woods Road",
    "iso:country":"GB",
    "sg:address":"24 Woods Road, Caversham",
    "sg:city":"Reading",
    "sg:classifiers":[
        {
            "category":"Professional",
            "subcategory":"Management & Consulting",
            "type":"Services"
        }
    ],
    "sg:phone":"+44 118 947 5949",
    "sg:postcode":"RG4 6NA",
    "sg:province":"Berkshire",
    "sg:tags":[
        "consultant",
        "specialist"
    ],
    "wof:name":"Colour & Image Consultants",
    "wof:placetype":"venue"
},
  "geometry": {"coordinates":[-0.9472290277,51.4765319824],"type":"Point"}
}