{
  "type": "Feature",
  "properties": {
    "iso:country":"GB",
    "sg:address":"254 Histon Road, Cottenham",
    "sg:city":"Cambridge",
    "sg:classifiers":[
        {
            "category":"Utilities",
            "subcategory":"Refuse",
            "type":"Services"
        }
    ],
    "sg:phone":"+44 1223 232794",
    "sg:postcode":"CB4 8UG",
    "sg:province":"Cambridgeshire",
    "sg:tags":[
        "disposal",
        "waste"
    ],
    "wof:name":"Cottenham Skips Ltd.",
    "wof:placetype":"venue"
},
  "geometry": {"coordinates":[0.113723,52.271027],"type":"Point"}
}