{
  "type": "Feature",
  "properties": {
    "iso:country":"GB",
    "sg:address":"408 Uttoxeter Road, Blythe Bridge",
    "sg:city":"Stoke-on-trent",
    "sg:classifiers":[
        {
            "category":"Home & Garden",
            "subcategory":"Building Materials",
            "type":"Retail Goods"
        }
    ],
    "sg:postcode":"ST11 9ND",
    "sg:province":"Staffordshire",
    "sg:tags":[
        "garage",
        "door"
    ],
    "wof:name":"A R Barber Garage Doors",
    "wof:placetype":"venue"
},
  "geometry": {"coordinates":[-2.0510048866,52.9639625549],"type":"Point"}
}