{
  "type": "Feature",
  "properties": {
    "addr:full":", St. Neot Liskeard Cornwall PL14 6NG",
    "addr:postcode":"pl14 6ng",
    "iso:country":"GB",
    "sg:address":", St. Neot",
    "sg:city":"Liskeard",
    "sg:classifiers":[
        {
            "category":"Community Center",
            "type":"Public Place"
        }
    ],
    "sg:phone":"+44 1579 320585",
    "sg:postcode":"PL14 6NG",
    "sg:province":"Cornwall",
    "sg:tags":[
        "centre"
    ],
    "wof:name":"St. Neot Village Institute",
    "wof:placetype":"venue"
},
  "geometry": {"coordinates":[-4.5200090408,50.4714584351],"type":"Point"}
}