{
  "type": "Feature",
  "properties": {
    "addr:full":"18 North Town Road Maidenhead Berkshire SL6 7JF",
    "addr:housenumber":"18",
    "addr:postcode":"sl6 7jf",
    "addr:street":"North Town Road",
    "iso:country":"GB",
    "sg:address":"18 North Town Road",
    "sg:city":"Maidenhead",
    "sg:classifiers":[
        {
            "category":"Bars & Pubs",
            "type":"Food & Drink"
        }
    ],
    "sg:phone":"+44 1628 788845",
    "sg:postcode":"SL6 7JF",
    "sg:province":"Berkshire",
    "sg:tags":[
        "pubs",
        "inn"
    ],
    "wof:name":"The Masters Arms",
    "wof:placetype":"venue"
},
  "geometry": {"coordinates":[-0.719137013,51.5298614502],"type":"Point"}
}