{
  "type": "Feature",
  "properties": {
    "addr:full":"5 Windsor Place, Ynysybwl Pontypridd Caerphilly CF37 3HR",
    "addr:housenumber":"5",
    "addr:postcode":"cf37 3hr",
    "addr:street":"Windsor Place",
    "iso:country":"GB",
    "sg:address":"5 Windsor Place, Ynysybwl",
    "sg:city":"Pontypridd",
    "sg:classifiers":[
        {
            "category":"Government",
            "subcategory":"Post Office",
            "type":"Public Place"
        }
    ],
    "sg:postcode":"CF37 3HR",
    "sg:province":"Caerphilly",
    "wof:name":"Ynysybwl Sub Post Office",
    "wof:placetype":"venue"
},
  "geometry": {"coordinates":[-3.3598499298,51.6393356323],"type":"Point"}
}