{
  "type": "Feature",
  "properties": {
    "addr:full":"10 Little Copse Rd Hassocks East Sussex BN6 8PQ",
    "addr:housenumber":"10",
    "addr:postcode":"bn6 8pq",
    "addr:street":"Little Copse Rd",
    "iso:country":"GB",
    "sg:address":"10 Little Copse Rd",
    "sg:city":"Hassocks",
    "sg:classifiers":[
        {
            "category":"Building & Trades",
            "subcategory":"Construction",
            "type":"Services"
        }
    ],
    "sg:phone":"+44 1273 845038",
    "sg:postcode":"BN6 8PQ",
    "sg:province":"East Sussex",
    "sg:tags":[
        "builder"
    ],
    "wof:name":"Gunns Building Services",
    "wof:placetype":"venue"
},
  "geometry": {"coordinates":[-0.1461009979,50.9283485413],"type":"Point"}
}