{
  "type": "Feature",
  "properties": {
    "addr:full":", Llantarnam Cwmbran Monmouthshire NP44 3AY",
    "addr:postcode":"np44 3ay",
    "iso:country":"GB",
    "sg:address":", Llantarnam",
    "sg:city":"Cwmbran",
    "sg:classifiers":[
        {
            "category":"Bars & Pubs",
            "type":"Food & Drink"
        },
        {
            "category":"Community Center",
            "subcategory":"Social",
            "type":"Public Place"
        }
    ],
    "sg:phone":"+44 1633 483130",
    "sg:postcode":"NP44 3AY",
    "sg:province":"Monmouthshire",
    "sg:tags":[
        "pubs",
        "house",
        "inn",
        "activity"
    ],
    "wof:name":"Three Blackbirds Inn",
    "wof:placetype":"venue"
},
  "geometry": {"coordinates":[-3.0041840076,51.6323471069],"type":"Point"}
}