{
  "type": "Feature",
  "properties": {
    "addr:full":"Crud Yr Awel, Bryn Port Talbot Neath Port Talbot SA13 2RP",
    "addr:postcode":"sa13 2rp",
    "addr:street":"Bryn;Talbot",
    "iso:country":"GB",
    "sg:address":"Crud Yr Awel, Bryn",
    "sg:city":"Port Talbot",
    "sg:classifiers":[
        {
            "category":"Farming",
            "subcategory":"Livestock Farm",
            "type":"Manufacturing & Wholesale Goods"
        }
    ],
    "sg:postcode":"SA13 2RP",
    "sg:province":"Neath Port Talbot",
    "sg:tags":[
        "others"
    ],
    "wof:name":"Alan Thomas",
    "wof:placetype":"venue"
},
  "geometry": {"coordinates":[-3.7154989243,51.6160583496],"type":"Point"}
}