{
  "type": "Feature",
  "properties": {
    "iso:country":"GB",
    "sg:address":"70a Uxbridge Rd",
    "sg:city":"Shepherd's Bush",
    "sg:classifiers":[
        {
            "category":"Communications",
            "type":"Services"
        }
    ],
    "sg:phone":"+44 20 8723 3716",
    "sg:postcode":"W12 8LP",
    "sg:province":"Greater London",
    "sg:tags":[
        "audio-visual"
    ],
    "wof:name":"Yawning Dog Productions",
    "wof:placetype":"venue"
},
  "geometry": {"coordinates":[-0.219631,51.504539],"type":"Point"}
}