{
  "type": "Feature",
  "properties": {
    "iso:country":"GB",
    "sg:address":"New Market St",
    "sg:city":"Castle Douglas",
    "sg:classifiers":[
        {
            "category":"Shopping",
            "type":"Retail Goods"
        }
    ],
    "sg:phone":"+44 1556 504436",
    "sg:postcode":"DG7 1HY",
    "sg:province":"Dumfries and Galloway",
    "sg:tags":[
        "merchant"
    ],
    "wof:name":"Stewartry Agricultural Society",
    "wof:placetype":"venue"
},
  "geometry": {"coordinates":[-3.928704,54.94162],"type":"Point"}
}