{
  "type": "Feature",
  "properties": {
    "iso:country":"GB",
    "sg:address":"23 St Georges Street",
    "sg:city":"Ipswich",
    "sg:classifiers":[
        {
            "category":"Retail",
            "subcategory":"Auto Repair",
            "type":"Services"
        }
    ],
    "sg:phone":"+44 1473 251348",
    "sg:postcode":"IP1 3NF",
    "sg:province":"Suffolk",
    "sg:tags":[
        "modification",
        "garage",
        "related"
    ],
    "wof:name":"Prestige Car Repairs",
    "wof:placetype":"venue"
},
  "geometry": {"coordinates":[1.1498450041,52.0603294373],"type":"Point"}
}