{
  "type": "Feature",
  "properties": {
    "addr:full":"Merchants House, 1-7 Leeds Road Shipley West Yorkshire BD18 1BP",
    "addr:housenumber":"1-7",
    "addr:postcode":"bd18 1bp",
    "addr:street":"Leeds Road",
    "iso:country":"GB",
    "sg:address":"Merchants House, 1-7 Leeds Road",
    "sg:city":"Shipley",
    "sg:classifiers":[
        {
            "category":"Professional",
            "subcategory":"Business Services",
            "type":"Services"
        }
    ],
    "sg:phone":"+44 1274 593302",
    "sg:postcode":"BD18 1BP",
    "sg:province":"West Yorkshire",
    "sg:tags":[
        "planning",
        "supervisor",
        "trade"
    ],
    "wof:name":"Legal Personnel & Management Services Ltd.",
    "wof:placetype":"venue"
},
  "geometry": {"coordinates":[-1.768108964,53.8342399597],"type":"Point"}
}