{
  "type": "Feature",
  "properties": {
    "iso:country":"GB",
    "sg:address":"154 Coed Edeyrn, Llanedeyrn",
    "sg:city":"Cardiff",
    "sg:classifiers":[
        {
            "category":"Retail",
            "subcategory":"Repair Shop",
            "type":"Services"
        }
    ],
    "sg:phone":"+44 29 2073 1309",
    "sg:postcode":"CF23 9JY",
    "sg:province":"Cardiff",
    "sg:tags":[
        "maintenance"
    ],
    "wof:name":"Martess Properties Ltd.",
    "wof:placetype":"venue"
},
  "geometry": {"coordinates":[-3.149668932,51.5057487488],"type":"Point"}
}