{
  "type": "Feature",
  "properties": {
    "iso:country":"GB",
    "sg:address":"Loudon Way",
    "sg:city":"Ashford",
    "sg:classifiers":[
        {
            "category":"Personal",
            "subcategory":"Beauty Salon",
            "type":"Services"
        }
    ],
    "sg:phone":"+44 1233 660900",
    "sg:postcode":"TN23 3JJ",
    "sg:province":"Kent",
    "sg:tags":[
        "unisex",
        "hairdresser"
    ],
    "wof:name":"Family Aff'hair",
    "wof:placetype":"venue"
},
  "geometry": {"coordinates":[0.84895,51.153015],"type":"Point"}
}