{
  "type": "Feature",
  "properties": {
    "iso:country":"GB",
    "sg:address":"141 Liverpool Old Rd",
    "sg:city":"Preston",
    "sg:classifiers":[
        {
            "category":"Building & Trades",
            "subcategory":"Construction",
            "type":"Services"
        }
    ],
    "sg:phone":"+44 1772 617866",
    "sg:postcode":"PR4 4GB",
    "sg:province":"Lancashire",
    "sg:tags":[
        "decorator",
        "painter"
    ],
    "wof:name":"H Chadwick",
    "wof:placetype":"venue"
},
  "geometry": {"coordinates":[-2.801711,53.700619],"type":"Point"}
}