{
  "type": "Feature",
  "properties": {
    "iso:country":"GB",
    "sg:address":"Cheadle Rd, Cheddleton",
    "sg:city":"Leek",
    "sg:classifiers":[
        {
            "category":"Health Services",
            "subcategory":"Hospital",
            "type":"Services"
        }
    ],
    "sg:phone":"+44 1538 360421",
    "sg:postcode":"ST13 7EB",
    "sg:province":"Staffordshire",
    "wof:name":"St. Edwards Hospital",
    "wof:placetype":"venue"
},
  "geometry": {"coordinates":[-2.0432031155,53.0643424988],"type":"Point"}
}