{
  "type": "Feature",
  "properties": {
    "addr:full":"52 Eden Street Derby Derbyshire DE24 8RB",
    "addr:housenumber":"52",
    "addr:postcode":"de24 8rb",
    "addr:street":"Eden Street",
    "iso:country":"GB",
    "sg:address":"52 Eden Street",
    "sg:city":"Derby",
    "sg:classifiers":[
        {
            "category":"Building & Trades",
            "subcategory":"Construction",
            "type":"Services"
        }
    ],
    "sg:phone":"+44 1332 723870",
    "sg:postcode":"DE24 8RB",
    "sg:province":"Derbyshire",
    "sg:tags":[
        "roofing"
    ],
    "wof:name":"M A Bull Roofing",
    "wof:placetype":"venue"
},
  "geometry": {"coordinates":[-1.4292769432,52.8980026245],"type":"Point"}
}