{
  "type": "Feature",
  "properties": {
    "addr:full":"383 Soho Road Birmingham West Midlands B21 9SF",
    "addr:housenumber":"383",
    "addr:postcode":"b21 9sf",
    "addr:street":"Soho Road",
    "iso:country":"GB",
    "sg:address":"383 Soho Road",
    "sg:city":"Birmingham",
    "sg:classifiers":[
        {
            "category":"Professional",
            "subcategory":"Lawyer & Legal Services",
            "type":"Services"
        }
    ],
    "sg:postcode":"B21 9SF",
    "sg:province":"West Midlands",
    "sg:tags":[
        "solicitor"
    ],
    "wof:name":"Sehdev & Co.",
    "wof:placetype":"venue"
},
  "geometry": {"coordinates":[-1.941075,52.504406],"type":"Point"}
}