{
  "type": "Feature",
  "properties": {
    "addr:full":"Red House, Main Road, Potterhanworth Lincoln Lincolnshire LN4 2DT",
    "addr:postcode":"ln4 2dt",
    "addr:street":"Main Road Potterhanworth Lincoln",
    "iso:country":"GB",
    "sg:address":"Red House, Main Road, Potterhanworth",
    "sg:city":"Lincoln",
    "sg:classifiers":[
        {
            "category":"Farming",
            "subcategory":"Crops",
            "type":"Manufacturing & Wholesale Goods"
        },
        {
            "category":"Professional",
            "subcategory":"Employment Agencies",
            "type":"Services"
        },
        {
            "category":"Farming",
            "subcategory":"Farm",
            "type":"Manufacturing & Wholesale Goods"
        }
    ],
    "sg:phone":"+44 1522 791245",
    "sg:postcode":"LN4 2DT",
    "sg:province":"Lincolnshire",
    "sg:tags":[
        "mixed",
        "agricultural",
        "advice",
        "arable"
    ],
    "wof:name":"R & B L Brewer",
    "wof:placetype":"venue"
},
  "geometry": {"coordinates":[-0.4189540148,53.1663818359],"type":"Point"}
}