{
  "type": "Feature",
  "properties": {
    "addr:full":"14 York Arcade Grangemouth Falkirk FK3 8BA",
    "addr:housenumber":"14",
    "addr:postcode":"fk3 8ba",
    "addr:street":"York Arcade",
    "iso:country":"GB",
    "sg:address":"14 York Arcade",
    "sg:city":"Grangemouth",
    "sg:classifiers":[
        {
            "category":"Shopping",
            "subcategory":"Jewelry",
            "type":"Retail Goods"
        },
        {
            "category":"Shopping",
            "subcategory":"Comic Books",
            "type":"Retail Goods"
        }
    ],
    "sg:phone":"+44 1324 482293",
    "sg:postcode":"FK3 8BA",
    "sg:province":"Falkirk",
    "sg:tags":[
        "jeweller",
        "sale",
        "jewellery"
    ],
    "wof:name":"A. ROSS PHILIP (JEWELLERS) LTD",
    "wof:placetype":"venue"
},
  "geometry": {"coordinates":[-3.7238938808,56.0093307495],"type":"Point"}
}