{
  "type": "Feature",
  "properties": {
    "iso:country":"GB",
    "sg:address":"7 St. Olaves Precinct",
    "sg:city":"Bury St Edmunds",
    "sg:classifiers":[
        {
            "category":"Food & Beverages",
            "subcategory":"Fruits & Vegetables",
            "type":"Retail Goods"
        }
    ],
    "sg:phone":"+44 1284 753591",
    "sg:postcode":"IP32 6SP",
    "sg:province":"Suffolk",
    "sg:tags":[
        "greengrocer"
    ],
    "wof:name":"E & J Beardsmore",
    "wof:placetype":"venue"
},
  "geometry": {"coordinates":[0.698649,52.2561],"type":"Point"}
}