{
  "type": "Feature",
  "properties": {
    "addr:full":"30 Ashbourne Road Leek Staffordshire ST13 5AS",
    "addr:housenumber":"30",
    "addr:postcode":"st13 5as",
    "addr:street":"Ashbourne Road",
    "iso:country":"GB",
    "sg:address":"30 Ashbourne Road",
    "sg:city":"Leek",
    "sg:classifiers":[
        {
            "category":"Food & Beverages",
            "subcategory":"Candy",
            "type":"Retail Goods"
        }
    ],
    "sg:phone":"+44 1538 384803",
    "sg:postcode":"ST13 5AS",
    "sg:province":"Staffordshire",
    "sg:tags":[
        "confectioner"
    ],
    "wof:name":"Colin Victor Salt",
    "wof:placetype":"venue"
},
  "geometry": {"coordinates":[-2.0183770657,53.1047363281],"type":"Point"}
}