{
  "type": "Feature",
  "properties": {
    "iso:country":"GB",
    "sg:address":"The Bungalow, Harts Farm, Meadow Pit Lane",
    "sg:city":"Wigan",
    "sg:classifiers":[
        {
            "category":"Autos & Motor Vehicles",
            "subcategory":"Automobile Sales",
            "type":"Retail Goods"
        }
    ],
    "sg:phone":"+44 1942 831116",
    "sg:postcode":"WN2 1LL",
    "sg:province":"Lancashire",
    "sg:tags":[
        "commercial"
    ],
    "wof:name":"G Brandon & Son",
    "wof:placetype":"venue"
},
  "geometry": {"coordinates":[-2.60262,53.580231],"type":"Point"}
}