{
  "type": "Feature",
  "properties": {
    "iso:country":"GB",
    "sg:address":"14 Rochdale Road",
    "sg:city":"Manchester",
    "sg:classifiers":[
        {
            "category":"Retail",
            "subcategory":"Repair Shop",
            "type":"Services"
        }
    ],
    "sg:phone":"+44 161 655 3730",
    "sg:postcode":"M24 6DP",
    "sg:province":"Greater Manchester",
    "sg:tags":[
        "radio",
        "television",
        "video"
    ],
    "wof:name":"Telecare",
    "wof:placetype":"venue"
},
  "geometry": {"coordinates":[-2.196673,53.555138],"type":"Point"}
}