{
  "type": "Feature",
  "properties": {
    "addr:full":"Fen House, Dorrington Lincoln Lincolnshire LN4 3QB",
    "addr:postcode":"ln4 3qb",
    "addr:street":"Lincoln",
    "iso:country":"GB",
    "sg:address":"Fen House, Dorrington",
    "sg:city":"Lincoln",
    "sg:classifiers":[
        {
            "category":"Farming",
            "subcategory":"Farm",
            "type":"Manufacturing & Wholesale Goods"
        }
    ],
    "sg:postcode":"LN4 3QB",
    "sg:province":"Lincolnshire",
    "sg:tags":[
        "mixed",
        "crop"
    ],
    "wof:name":"J T & W E Drury",
    "wof:placetype":"venue"
},
  "geometry": {"coordinates":[-0.3862789869,53.0625991821],"type":"Point"}
}