{
  "type": "Feature",
  "properties": {
    "addr:full":"Charter House, Steeple Road, Mayland Chelmsford Essex CM3 6BB",
    "addr:postcode":"cm3 6bb",
    "addr:street":"Charter;Steeple Road",
    "iso:country":"GB",
    "sg:address":"Charter House, Steeple Road, Mayland",
    "sg:city":"Chelmsford",
    "sg:classifiers":[
        {
            "category":"Banks & Credit Unions",
            "subcategory":"Financial Services",
            "type":"Services"
        }
    ],
    "sg:phone":"+44 1621 742456",
    "sg:postcode":"CM3 6BB",
    "sg:province":"Essex",
    "sg:tags":[
        "adviser"
    ],
    "wof:name":"Charter Equity & General Independent Financial Advisers",
    "wof:placetype":"venue"
},
  "geometry": {"coordinates":[0.776359,51.680485],"type":"Point"}
}