{
  "type": "Feature",
  "properties": {
    "iso:country":"GB",
    "sg:address":"Greenways, Watling Street, Strood",
    "sg:city":"Rochester",
    "sg:classifiers":[
        {
            "category":"Autos & Motor Vehicles",
            "subcategory":"Boat Sales",
            "type":"Retail Goods"
        }
    ],
    "sg:postcode":"ME2 3UQ",
    "sg:province":"Kent",
    "sg:tags":[
        "surveyor",
        "yacht"
    ],
    "wof:name":"R N Denby",
    "wof:placetype":"venue"
},
  "geometry": {"coordinates":[0.488783,51.39637],"type":"Point"}
}