{
  "type": "Feature",
  "properties": {
    "addr:full":"Polhill Garden Centre, Shacklands Rd Sevenoaks Kent TN14 7BD",
    "addr:postcode":"tn14 7bd",
    "addr:street":"Shacklands Rd",
    "iso:country":"GB",
    "sg:address":"Polhill Garden Centre, Shacklands Rd",
    "sg:city":"Sevenoaks",
    "sg:classifiers":[
        {
            "category":"Home & Garden",
            "subcategory":"Furniture",
            "type":"Retail Goods"
        }
    ],
    "sg:postcode":"TN14 7BD",
    "sg:province":"Kent",
    "wof:name":"Repro-Furniture Ltd",
    "wof:placetype":"venue"
},
  "geometry": {"coordinates":[0.1557800025,51.3154907227],"type":"Point"}
}