{
  "type": "Feature",
  "properties": {
    "iso:country":"GB",
    "sg:address":"36 King Street, Sileby",
    "sg:city":"Loughborough",
    "sg:classifiers":[
        {
            "category":"Bars & Pubs",
            "type":"Food & Drink"
        }
    ],
    "sg:phone":"+44 1509 812447",
    "sg:postcode":"LE12 7NA",
    "sg:province":"Leicestershire",
    "sg:tags":[
        "pubs",
        "inn"
    ],
    "wof:name":"The Railway Inn",
    "wof:placetype":"venue"
},
  "geometry": {"coordinates":[-1.084517,52.753315],"type":"Point"}
}