{
  "type": "Feature",
  "properties": {
    "addr:full":"The Old Foundry, Common Lane, Watnall Nottingham Derbyshire NG16 1HD",
    "addr:postcode":"ng16 1hd",
    "addr:street":"Common Lane",
    "iso:country":"GB",
    "sg:address":"The Old Foundry, Common Lane, Watnall",
    "sg:city":"Nottingham",
    "sg:classifiers":[
        {
            "category":"Autos & Motor Vehicles",
            "subcategory":"Auto Supplies",
            "type":"Retail Goods"
        }
    ],
    "sg:phone":"+44 115 938 2241",
    "sg:postcode":"NG16 1HD",
    "sg:province":"Derbyshire",
    "sg:tags":[
        "exhaust",
        "absorber",
        "shock"
    ],
    "wof:name":"P D Gough & Associate",
    "wof:placetype":"venue"
},
  "geometry": {"coordinates":[-1.254873991,53.0086135864],"type":"Point"}
}