{
  "type": "Feature",
  "properties": {
    "iso:country":"GB",
    "sg:address":"35 Riverbank Enterprise Centre",
    "sg:city":"Dewsbury",
    "sg:classifiers":[
        {
            "category":"Building & Trades",
            "subcategory":"Equipment Rental",
            "type":"Services"
        }
    ],
    "sg:phone":"+44 1924 468664",
    "sg:postcode":"WF13 3SA",
    "sg:province":"West Yorkshire",
    "sg:tags":[
        "plant",
        "machinery"
    ],
    "wof:name":"Amber Signs & Signals Ltd",
    "wof:placetype":"venue"
},
  "geometry": {"coordinates":[-1.6582499743,53.6812286377],"type":"Point"}
}