{
  "type": "Feature",
  "properties": {
    "addr:full":"17 Ham Common Richmond Greater London TW10 7JB",
    "addr:housenumber":"17",
    "addr:postcode":"tw10 7jb",
    "addr:street":"Ham Common",
    "iso:country":"GB",
    "sg:address":"17 Ham Common",
    "sg:city":"Richmond",
    "sg:classifiers":[
        {
            "category":"Conference Center",
            "type":"Public Place"
        }
    ],
    "sg:phone":"+44 20 8940 7576",
    "sg:postcode":"TW10 7JB",
    "sg:province":"Greater London",
    "wof:name":"The Grape Connection Ltd.",
    "wof:placetype":"venue"
},
  "geometry": {"coordinates":[-0.3118939996,51.4363327026],"type":"Point"}
}