{
  "type": "Feature",
  "properties": {
    "iso:country":"GB",
    "sg:address":"Leonard House, Great Central Way",
    "sg:city":"Daventry",
    "sg:classifiers":[
        {
            "category":"Shopping",
            "subcategory":"Computers & Home Electronics",
            "type":"Retail Goods"
        }
    ],
    "sg:postcode":"NN11 3PZ",
    "sg:province":"Northamptonshire",
    "wof:name":"Qualform Computer Products",
    "wof:placetype":"venue"
},
  "geometry": {"coordinates":[-1.209879,52.17416],"type":"Point"}
}