{
  "type": "Feature",
  "properties": {
    "addr:full":"1 Hillmarton Road London Greater London N7 9JE",
    "addr:housenumber":"1",
    "addr:postcode":"n7 9je",
    "addr:street":"Hillmarton Road",
    "iso:country":"GB",
    "sg:address":"1 Hillmarton Road",
    "sg:city":"London",
    "sg:classifiers":[
        {
            "category":"Retail",
            "subcategory":"Auto Repair",
            "type":"Services"
        }
    ],
    "sg:phone":"+44 20 7609 1960",
    "sg:postcode":"N7 9JE",
    "sg:province":"Greater London",
    "sg:tags":[
        "modification",
        "garage",
        "related"
    ],
    "wof:name":"Exan Car Services",
    "wof:placetype":"venue"
},
  "geometry": {"coordinates":[-0.123464,51.553165],"type":"Point"}
}