{
  "type": "Feature",
  "properties": {
    "addr:full":"Torlundy Fort William Highland PH33 6SW",
    "addr:postcode":"ph33 6sw",
    "addr:street":"Torlundy Fort William",
    "iso:country":"GB",
    "sg:address":"Torlundy",
    "sg:city":"Fort William",
    "sg:classifiers":[
        {
            "category":"Building & Trades",
            "subcategory":"Construction",
            "type":"Services"
        }
    ],
    "sg:phone":"+44 1397 704802",
    "sg:postcode":"PH33 6SW",
    "sg:province":"Highland",
    "sg:tags":[
        "builder"
    ],
    "wof:name":"John McKinnon Building Contractors",
    "wof:placetype":"venue"
},
  "geometry": {"coordinates":[-5.1084589958,56.8184318542],"type":"Point"}
}