{
  "type": "Feature",
  "properties": {
    "addr:full":"1 Gardenia Drive, Allesley Coventry West Midlands CV5 9BN",
    "addr:housenumber":"1",
    "addr:postcode":"cv5 9bn",
    "addr:street":"Gardenia Drive",
    "iso:country":"GB",
    "sg:address":"1 Gardenia Drive, Allesley",
    "sg:city":"Coventry",
    "sg:classifiers":[
        {
            "category":"Personal",
            "subcategory":"Beauty Salon",
            "type":"Services"
        }
    ],
    "sg:phone":"+44 24 7640 3119",
    "sg:postcode":"CV5 9BN",
    "sg:province":"West Midlands",
    "sg:tags":[
        "unisex",
        "hairdresser"
    ],
    "wof:name":"Designers Too",
    "wof:placetype":"venue"
},
  "geometry": {"coordinates":[-1.5671390295,52.423538208],"type":"Point"}
}