{
  "type": "Feature",
  "properties": {
    "iso:country":"GB",
    "sg:address":"Forge House, Tewkesbury Road, Uckington",
    "sg:city":"Cheltenham",
    "sg:classifiers":[
        {
            "category":"Home & Garden",
            "subcategory":"Building Materials",
            "type":"Retail Goods"
        }
    ],
    "sg:postcode":"GL51 9SX",
    "sg:province":"Gloucestershire",
    "sg:tags":[
        "ironwork",
        "diy",
        "wrought"
    ],
    "wof:name":"Cotsvale Welding & Smithing",
    "wof:placetype":"venue"
},
  "geometry": {"coordinates":[-2.092699,51.910004],"type":"Point"}
}