{
  "type": "Feature",
  "properties": {
    "iso:country":"GB",
    "sg:address":"Unit 2, Phoenix Road",
    "sg:city":"Cannock",
    "sg:classifiers":[
        {
            "category":"Shopping",
            "subcategory":"Crafts & Fabrics",
            "type":"Retail Goods"
        }
    ],
    "sg:phone":"+44 1543 500893",
    "sg:postcode":"WS11 2LR",
    "sg:province":"Staffordshire",
    "sg:tags":[
        "ceramic"
    ],
    "wof:name":"Tile Accessories Ltd.",
    "wof:placetype":"venue"
},
  "geometry": {"coordinates":[-2.0111839771,52.6963653564],"type":"Point"}
}