{
  "type": "Feature",
  "properties": {
    "iso:country":"GB",
    "sg:address":"D D I House, 21 Elkstone Road",
    "sg:city":"London",
    "sg:classifiers":[
        {
            "category":"Government",
            "subcategory":"Post Office",
            "type":"Public Place"
        }
    ],
    "sg:phone":"+44 20 7724 4000",
    "sg:postcode":"W10 5NT",
    "sg:province":"Greater London",
    "sg:tags":[
        "messenger",
        "courier"
    ],
    "wof:name":"D D I Worldwide Ltd.",
    "wof:placetype":"venue"
},
  "geometry": {"coordinates":[-0.20248,51.522228],"type":"Point"}
}