{
  "type": "Feature",
  "properties": {
    "addr:full":"109 Glendale Road Burnham-on-crouch Essex CM0 8LY",
    "addr:housenumber":"109",
    "addr:postcode":"cm0 8ly",
    "addr:street":"Glendale Road",
    "iso:country":"GB",
    "sg:address":"109 Glendale Road",
    "sg:city":"Burnham-on-crouch",
    "sg:classifiers":[
        {
            "category":"Personal",
            "type":"Services"
        }
    ],
    "sg:phone":"+44 1621 784530",
    "sg:postcode":"CM0 8LY",
    "sg:province":"Essex",
    "sg:tags":[
        "delivery"
    ],
    "wof:name":"East Essex Transport Services",
    "wof:placetype":"venue"
},
  "geometry": {"coordinates":[0.818049,51.636776],"type":"Point"}
}