{
  "type": "Feature",
  "properties": {
    "addr:full":"218 Upton Road South Bexley Kent DA5 1QT",
    "addr:housenumber":"218",
    "addr:postcode":"da5 1qt",
    "addr:street":"Upton Road South",
    "iso:country":"GB",
    "sg:address":"218 Upton Road South",
    "sg:city":"Bexley",
    "sg:classifiers":[
        {
            "category":"Professional",
            "subcategory":"Computer Services",
            "type":"Services"
        }
    ],
    "sg:phone":"+44 1322 550502",
    "sg:postcode":"DA5 1QT",
    "sg:province":"Kent",
    "sg:tags":[
        "system",
        "software"
    ],
    "wof:name":"Cullin Communications",
    "wof:placetype":"venue"
},
  "geometry": {"coordinates":[0.1412619948,51.4453811646],"type":"Point"}
}