{
  "type": "Feature",
  "properties": {
    "addr:full":"Grange Farm, Higham Lane Tonbridge Kent TN11 9QR",
    "addr:postcode":"tn11 9qr",
    "addr:street":"Higham Lane",
    "iso:country":"GB",
    "sg:address":"Grange Farm, Higham Lane",
    "sg:city":"Tonbridge",
    "sg:classifiers":[
        {
            "category":"Farming",
            "subcategory":"Livestock Farm",
            "type":"Manufacturing & Wholesale Goods"
        }
    ],
    "sg:postcode":"TN11 9QR",
    "sg:province":"Kent",
    "sg:tags":[
        "others"
    ],
    "wof:name":"G R Petrie",
    "wof:placetype":"venue"
},
  "geometry": {"coordinates":[0.2981399894,51.2200088501],"type":"Point"}
}