{
  "type": "Feature",
  "properties": {
    "iso:country":"GB",
    "sg:address":"26 High St",
    "sg:city":"Ringwood",
    "sg:classifiers":[
        {
            "category":"Shopping",
            "subcategory":"Shoes",
            "type":"Retail Goods"
        }
    ],
    "sg:phone":"+44 1425 470490",
    "sg:postcode":"BH24 1AF",
    "sg:province":"Dorset",
    "wof:name":"Mastercraft",
    "wof:placetype":"venue"
},
  "geometry": {"coordinates":[-1.7924619913,50.8462562561],"type":"Point"}
}