{
  "type": "Feature",
  "properties": {
    "iso:country":"GB",
    "sg:address":"Lancaster Services, M6 Northbound, Bay Horse",
    "sg:city":"Lancaster",
    "sg:classifiers":[
        {
            "category":"Shopping",
            "subcategory":"Computers & Home Electronics",
            "type":"Retail Goods"
        }
    ],
    "sg:phone":"+44 1524 792772",
    "sg:postcode":"LA2 9DU",
    "sg:province":"Lancashire",
    "sg:tags":[
        "equipment",
        "radio"
    ],
    "wof:name":"B & D Electronics",
    "wof:placetype":"venue"
},
  "geometry": {"coordinates":[-2.76060009,53.9616508484],"type":"Point"}
}