{
  "type": "Feature",
  "properties": {
    "addr:full":"86 Narbeth Drive Aylesbury Buckinghamshire HP20 1NX",
    "addr:housenumber":"86",
    "addr:postcode":"hp20 1nx",
    "addr:street":"Narbeth Drive",
    "iso:country":"GB",
    "sg:address":"86 Narbeth Drive",
    "sg:city":"Aylesbury",
    "sg:classifiers":[
        {
            "category":"Building & Trades",
            "subcategory":"Construction",
            "type":"Services"
        }
    ],
    "sg:phone":"+44 1296 422330",
    "sg:postcode":"HP20 1NX",
    "sg:province":"Buckinghamshire",
    "sg:tags":[
        "builder"
    ],
    "wof:name":"M S B Bloke Paving",
    "wof:placetype":"venue"
},
  "geometry": {"coordinates":[-0.783559,51.816982],"type":"Point"}
}