{
  "type": "Feature",
  "properties": {
    "addr:full":"22 Tregaron Gardens New Malden Surrey KT3 3AF",
    "addr:housenumber":"22",
    "addr:postcode":"kt3 3af",
    "addr:street":"Tregaron Gardens",
    "iso:country":"GB",
    "sg:address":"22 Tregaron Gardens",
    "sg:city":"New Malden",
    "sg:classifiers":[
        {
            "category":"Professional",
            "subcategory":"Management & Consulting",
            "type":"Services"
        }
    ],
    "sg:postcode":"KT3 3AF",
    "sg:province":"Surrey",
    "sg:tags":[
        "consultant",
        "business"
    ],
    "wof:name":"Somerton Consultancy Ltd",
    "wof:placetype":"venue"
},
  "geometry": {"coordinates":[-0.257833,51.402565],"type":"Point"}
}