{
  "type": "Feature",
  "properties": {
    "iso:country":"GB",
    "sg:address":"Roots Lane, Catforth",
    "sg:city":"Preston",
    "sg:classifiers":[
        {
            "category":"Home & Garden",
            "subcategory":"Garden Supply",
            "type":"Retail Goods"
        }
    ],
    "sg:postcode":"PR4 0JB",
    "sg:province":"Lancashire",
    "sg:tags":[
        "nursery",
        "centre"
    ],
    "wof:name":"Catforth Gardens",
    "wof:placetype":"venue"
},
  "geometry": {"coordinates":[-2.79188,53.813087],"type":"Point"}
}