{
  "type": "Feature",
  "properties": {
    "iso:country":"GB",
    "sg:address":"1 Bishops Pl",
    "sg:city":"Paignton",
    "sg:classifiers":[
        {
            "category":"Health Services",
            "subcategory":"Doctor",
            "type":"Services"
        }
    ],
    "sg:phone":"+44 1803 559421",
    "sg:postcode":"TQ3 3DZ",
    "sg:province":"Devon",
    "sg:tags":[
        "practitioners"
    ],
    "wof:name":"Wander, G C A",
    "wof:placetype":"venue"
},
  "geometry": {"coordinates":[-3.569038,50.436062],"type":"Point"}
}