{
  "type": "Feature",
  "properties": {
    "iso:country":"GB",
    "sg:address":"32 Queesn Terrace",
    "sg:city":"Southampton",
    "sg:classifiers":[
        {
            "category":"Education",
            "subcategory":"Special Training",
            "type":"Public Place"
        }
    ],
    "sg:phone":"+44 23 8039 9920",
    "sg:postcode":"SO14 3BQ",
    "sg:province":"Hampshire",
    "sg:tags":[
        "product",
        "centre"
    ],
    "wof:name":"Futurekids",
    "wof:placetype":"venue"
},
  "geometry": {"coordinates":[-1.39743,50.897514],"type":"Point"}
}