{
  "type": "Feature",
  "properties": {
    "addr:full":"2nd Floor, 11 Stevenson Square Manchester Greater Manchester M1 1DN",
    "addr:housenumber":"2nd floor 11",
    "addr:postcode":"m1 1dn",
    "addr:street":"Stevenson Square",
    "iso:country":"GB",
    "sg:address":"2nd Floor, 11 Stevenson Square",
    "sg:city":"Manchester",
    "sg:classifiers":[
        {
            "category":"Shopping",
            "subcategory":"Clothing, Apparel, & Fashions",
            "type":"Retail Goods"
        }
    ],
    "sg:phone":"+44 161 228 6595",
    "sg:postcode":"M1 1DN",
    "sg:province":"Greater Manchester",
    "sg:tags":[
        "ladieswear"
    ],
    "wof:name":"Moving Fashion",
    "wof:placetype":"venue"
},
  "geometry": {"coordinates":[-2.2335240841,53.4826126099],"type":"Point"}
}