{
  "type": "Feature",
  "properties": {
    "addr:full":"Station App Derby Derbyshire DE1 2PW",
    "addr:postcode":"de1 2pw",
    "iso:country":"GB",
    "sg:address":"Station App",
    "sg:city":"Derby",
    "sg:classifiers":[
        {
            "category":"Autos & Motor Vehicles",
            "subcategory":"Auto Supplies",
            "type":"Retail Goods"
        }
    ],
    "sg:phone":"+44 1332 370515",
    "sg:postcode":"DE1 2PW",
    "sg:province":"Derbyshire",
    "sg:tags":[
        "windscreen"
    ],
    "wof:name":"R A C Auto Windscreens Ltd.",
    "wof:placetype":"venue"
},
  "geometry": {"coordinates":[-1.4693239927,52.9211082458],"type":"Point"}
}