{
  "type": "Feature",
  "properties": {
    "addr:full":"Regent Street, Beeston Nottingham Nottinghamshire NG9 2EB",
    "addr:postcode":"ng9 2eb",
    "addr:street":"Regent Street",
    "iso:country":"GB",
    "sg:address":"Regent Street, Beeston",
    "sg:city":"Nottingham",
    "sg:classifiers":[
        {
            "category":"Building & Trades",
            "subcategory":"Construction",
            "type":"Services"
        }
    ],
    "sg:phone":"+44 115 925 4455",
    "sg:postcode":"NG9 2EB",
    "sg:province":"Nottinghamshire",
    "sg:tags":[
        "builder"
    ],
    "wof:name":"Hofton & Son Ltd.",
    "wof:placetype":"venue"
},
  "geometry": {"coordinates":[-1.2109470367,52.9283714294],"type":"Point"}
}