{
  "type": "Feature",
  "properties": {
    "addr:full":"Palmeira Avenue Hove East Sussex BN3 3GE",
    "addr:postcode":"bn3 3ge",
    "addr:street":"Palmeira Avenue",
    "iso:country":"GB",
    "sg:address":"Palmeira Avenue",
    "sg:city":"Hove",
    "sg:classifiers":[
        {
            "category":"Place Of Worship",
            "type":"Public Place"
        }
    ],
    "sg:phone":"+44 1273 735343",
    "sg:postcode":"BN3 3GE",
    "sg:province":"East Sussex",
    "wof:name":"Brighton & Hove New Synagogue (Reform)",
    "wof:placetype":"venue"
},
  "geometry": {"coordinates":[-0.1625539958,50.8289031982],"type":"Point"}
}