{
  "type": "Feature",
  "properties": {
    "iso:country":"GB",
    "sg:address":"70 Lythalls La",
    "sg:city":"Coventry",
    "sg:classifiers":[
        {
            "category":"Food & Beverages",
            "subcategory":"Supermarket",
            "type":"Retail Goods"
        }
    ],
    "sg:postcode":"CV6 6FP",
    "sg:province":"Warwickshire",
    "wof:name":"Singh,C",
    "wof:placetype":"venue"
},
  "geometry": {"coordinates":[-1.496112,52.441063],"type":"Point"}
}