{
  "type": "Feature",
  "properties": {
    "addr:full":"61 Queens Road Watford Hertfordshire WD17 2QN",
    "addr:housenumber":"61",
    "addr:postcode":"wd17 2qn",
    "addr:street":"Queens Road",
    "iso:country":"GB",
    "sg:address":"61 Queens Road",
    "sg:city":"Watford",
    "sg:classifiers":[
        {
            "category":"Autos & Motor Vehicles",
            "subcategory":"Motorcycle Sales",
            "type":"Retail Goods"
        }
    ],
    "sg:phone":"+44 1923 221125",
    "sg:postcode":"WD17 2QN",
    "sg:province":"Hertfordshire",
    "wof:name":"Lloyd Cooper Motor Cycles Ltd.",
    "wof:placetype":"venue"
},
  "geometry": {"coordinates":[-0.392559,51.657318],"type":"Point"}
}