{
  "type": "Feature",
  "properties": {
    "iso:country":"GB",
    "sg:address":"17 Birchover Way, Allestree",
    "sg:city":"Derby",
    "sg:classifiers":[
        {
            "category":"Retail",
            "subcategory":"Laundry & Dry Cleaning",
            "type":"Services"
        }
    ],
    "sg:phone":"+44 1332 550526",
    "sg:postcode":"DE3 2QQ",
    "sg:province":"Derbyshire",
    "sg:tags":[
        "alteration"
    ],
    "wof:name":"Sketchley Retail Ltd.",
    "wof:placetype":"venue"
},
  "geometry": {"coordinates":[-1.4791200161,52.9534187317],"type":"Point"}
}