{
  "type": "Feature",
  "properties": {
    "iso:country":"GB",
    "sg:address":"Elm Farm, Doncaster Road",
    "sg:city":"Pontefract",
    "sg:classifiers":[
        {
            "category":"Freight",
            "type":"Transportation"
        }
    ],
    "sg:postcode":"WF9 2DY",
    "sg:province":"West Yorkshire",
    "sg:tags":[
        "haulage",
        "road"
    ],
    "wof:name":"G Smith & Son",
    "wof:placetype":"venue"
},
  "geometry": {"coordinates":[-1.287093,53.593868],"type":"Point"}
}