{
  "type": "Feature",
  "properties": {
    "addr:full":"Prospect Place Sidmouth Devon EX10 8AS",
    "addr:postcode":"ex10 8as",
    "addr:street":"Prospect Place",
    "iso:country":"GB",
    "sg:address":"Prospect Place",
    "sg:city":"Sidmouth",
    "sg:classifiers":[
        {
            "category":"Shopping",
            "subcategory":"News",
            "type":"Retail Goods"
        }
    ],
    "sg:phone":"+44 1395 513187",
    "sg:postcode":"EX10 8AS",
    "sg:province":"Devon",
    "sg:tags":[
        "newsagent"
    ],
    "wof:name":"Prospect Newsagency",
    "wof:placetype":"venue"
},
  "geometry": {"coordinates":[-3.238064,50.678413],"type":"Point"}
}