{
  "type": "Feature",
  "properties": {
    "addr:full":"The Quakers Farm, Michaelchurch Eskley Hereford Herefordshire HR2 0PT",
    "addr:postcode":"hr2 0pt",
    "addr:street":"Eskley",
    "iso:country":"GB",
    "sg:address":"The Quakers Farm, Michaelchurch Eskley",
    "sg:city":"Hereford",
    "sg:classifiers":[
        {
            "category":"Farming",
            "subcategory":"Livestock Farm",
            "type":"Manufacturing & Wholesale Goods"
        }
    ],
    "sg:phone":"+44 1981 510667",
    "sg:postcode":"HR2 0PT",
    "sg:province":"Herefordshire",
    "sg:tags":[
        "others"
    ],
    "wof:name":"L E Bigley",
    "wof:placetype":"venue"
},
  "geometry": {"coordinates":[-2.997519,52.001797],"type":"Point"}
}