{
  "type": "Feature",
  "properties": {
    "iso:country":"GB",
    "sg:address":"24 Aberford Road, Bramham",
    "sg:city":"Wetherby",
    "sg:classifiers":[
        {
            "category":"Professional",
            "subcategory":"Engineering",
            "type":"Services"
        }
    ],
    "sg:postcode":"LS23 6QN",
    "sg:province":"West Yorkshire",
    "sg:tags":[
        "contractor",
        "electrical",
        "engineer"
    ],
    "wof:name":"Andrew Scott Electrical",
    "wof:placetype":"venue"
},
  "geometry": {"coordinates":[-1.349178,53.880016],"type":"Point"}
}