{
  "type": "Feature",
  "properties": {
    "addr:full":"1st Floor, 2 Mill Street London Greater London W1S 2AT",
    "addr:housenumber":"2",
    "addr:postcode":"w1s 2at",
    "addr:street":"Mill Street",
    "iso:country":"GB",
    "sg:address":"1st Floor, 2 Mill Street",
    "sg:city":"London",
    "sg:classifiers":[
        {
            "category":"Wholesale",
            "subcategory":"Books, Periodicals, & Newspapers",
            "type":"Manufacturing & Wholesale Goods"
        }
    ],
    "sg:postcode":"W1S 2AT",
    "sg:province":"Greater London",
    "sg:tags":[
        "publishing"
    ],
    "wof:name":"Montignac Publishing (Uk) Ltd",
    "wof:placetype":"venue"
},
  "geometry": {"coordinates":[-0.142552,51.512543],"type":"Point"}
}