{
  "type": "Feature",
  "properties": {
    "iso:country":"GB",
    "sg:address":"London Road, Felbridge",
    "sg:city":"East Grinstead",
    "sg:classifiers":[
        {
            "category":"Autos & Motor Vehicles",
            "subcategory":"Auto Supplies",
            "type":"Retail Goods"
        }
    ],
    "sg:phone":"+44 1342 314111",
    "sg:postcode":"RH19 2RQ",
    "sg:province":"East Sussex",
    "sg:tags":[
        "exhaust",
        "absorber",
        "shock"
    ],
    "wof:name":"Kwik-Fit",
    "wof:placetype":"venue"
},
  "geometry": {"coordinates":[-0.045123,51.140224],"type":"Point"}
}