{
  "type": "Feature",
  "properties": {
    "iso:country":"GB",
    "sg:address":"Thelwall Road, Great Sutton",
    "sg:city":"Ellesmere Port",
    "sg:classifiers":[
        {
            "category":"Community Center",
            "type":"Public Place"
        },
        {
            "category":"Government",
            "subcategory":"Office",
            "type":"Public Place"
        }
    ],
    "sg:phone":"+44 151 339 3969",
    "sg:postcode":"CH66 3JT",
    "sg:province":"Cheshire",
    "sg:tags":[
        "local",
        "centre"
    ],
    "wof:name":"Thelwall Community Centre",
    "wof:placetype":"venue"
},
  "geometry": {"coordinates":[-2.9257740974,53.2772331238],"type":"Point"}
}