{
  "type": "Feature",
  "properties": {
    "addr:full":"Unit 31, Old Mill Industrial Estate, Bamber Bridge Preston Lancashire PR5 6SY",
    "addr:housenumber":"unit 31",
    "addr:postcode":"pr5 6sy",
    "addr:street":"Old Mill Industrial Estate",
    "iso:country":"GB",
    "sg:address":"Unit 31, Old Mill Industrial Estate, Bamber Bridge",
    "sg:city":"Preston",
    "sg:classifiers":[
        {
            "category":"Manufacturing",
            "subcategory":"Petroleum Products",
            "type":"Manufacturing & Wholesale Goods"
        }
    ],
    "sg:phone":"+44 1772 696796",
    "sg:postcode":"PR5 6SY",
    "sg:province":"Lancashire",
    "sg:tags":[
        "double",
        "glazing"
    ],
    "wof:name":"Security With Style (Windows) Ltd.",
    "wof:placetype":"venue"
},
  "geometry": {"coordinates":[-2.6605689526,53.7277641296],"type":"Point"}
}