{
  "type": "Feature",
  "properties": {
    "iso:country":"GB",
    "sg:address":"237 Brixton Hill, Brixton",
    "sg:city":"London",
    "sg:classifiers":[
        {
            "category":"Autos & Motor Vehicles",
            "subcategory":"Automobile Sales",
            "type":"Retail Goods"
        }
    ],
    "sg:phone":"+44 20 8674 7777",
    "sg:postcode":"SW2 1NR",
    "sg:province":"Greater London",
    "sg:tags":[
        "car"
    ],
    "wof:name":"Pinewood Motor Group Ltd.",
    "wof:placetype":"venue"
},
  "geometry": {"coordinates":[-0.1151669994,51.4610748291],"type":"Point"}
}