{
  "type": "Feature",
  "properties": {
    "addr:full":"6 Fold La, Cowling Keighley North Yorkshire BD22 0BG",
    "addr:housenumber":"6",
    "addr:postcode":"bd22 0bg",
    "addr:street":"Fold La Cowling",
    "iso:country":"GB",
    "sg:address":"6 Fold La, Cowling",
    "sg:city":"Keighley",
    "sg:classifiers":[
        {
            "category":"Building & Trades",
            "subcategory":"Construction",
            "type":"Services"
        }
    ],
    "sg:postcode":"BD22 0BG",
    "sg:province":"North Yorkshire",
    "sg:tags":[
        "joiner",
        "carpenter"
    ],
    "wof:name":"Anderson,Craig,",
    "wof:placetype":"venue"
},
  "geometry": {"coordinates":[-2.0415580273,53.8844833374],"type":"Point"}
}