{
  "type": "Feature",
  "properties": {
    "addr:full":"Bellingham Repair Depot, Bellingham Hexham Northumberland NE48 2HP",
    "addr:postcode":"ne48 2hp",
    "iso:country":"GB",
    "sg:address":"Bellingham Repair Depot, Bellingham",
    "sg:city":"Hexham",
    "sg:classifiers":[
        {
            "category":"Professional",
            "subcategory":"Engineering",
            "type":"Services"
        }
    ],
    "sg:phone":"+44 1434 220413",
    "sg:postcode":"NE48 2HP",
    "sg:province":"Northumberland",
    "wof:name":"Forestry Enterprise Workshops",
    "wof:placetype":"venue"
},
  "geometry": {"coordinates":[-2.253899,55.144741],"type":"Point"}
}