{
  "type": "Feature",
  "properties": {
    "iso:country":"GB",
    "sg:address":"Meridian Centre",
    "sg:city":"Peacehaven",
    "sg:classifiers":[
        {
            "category":"Food & Beverages",
            "subcategory":"Bakery",
            "type":"Retail Goods"
        }
    ],
    "sg:phone":"+44 1273 581207",
    "sg:postcode":"BN10 8BB",
    "sg:province":"East Sussex",
    "sg:tags":[
        "baker"
    ],
    "wof:name":"Forfars Bakers Ltd.",
    "wof:placetype":"venue"
},
  "geometry": {"coordinates":[-0.003642,50.791817],"type":"Point"}
}