{
  "type": "Feature",
  "properties": {
    "iso:country":"GB",
    "sg:address":"13 Willoughbys Lane, High Garrett",
    "sg:city":"Braintree",
    "sg:classifiers":[
        {
            "category":"Wholesale",
            "subcategory":"Electrical",
            "type":"Manufacturing & Wholesale Goods"
        },
        {
            "category":"Building & Trades",
            "subcategory":"Equipment Rental",
            "type":"Services"
        }
    ],
    "sg:phone":"+44 1376 325865",
    "sg:postcode":"CM7 9SJ",
    "sg:province":"Essex",
    "sg:tags":[
        "refrigeration",
        "firefighting"
    ],
    "wof:name":"N S T Fire Protection",
    "wof:placetype":"venue"
},
  "geometry": {"coordinates":[0.5807800293,51.9044799805],"type":"Point"}
}