{
  "type": "Feature",
  "properties": {
    "addr:full":"Fullerton Grange Andover Hampshire SP11 7LA",
    "addr:postcode":"sp11 7la",
    "iso:country":"GB",
    "sg:address":"Fullerton Grange",
    "sg:city":"Andover",
    "sg:classifiers":[
        {
            "category":"Farming",
            "subcategory":"Livestock Farm",
            "type":"Manufacturing & Wholesale Goods"
        }
    ],
    "sg:phone":"+44 1264 860242",
    "sg:postcode":"SP11 7LA",
    "sg:province":"Hampshire",
    "sg:tags":[
        "others"
    ],
    "wof:name":"Fullerton Farms",
    "wof:placetype":"venue"
},
  "geometry": {"coordinates":[-1.460298,51.152912],"type":"Point"}
}