{
  "type": "Feature",
  "properties": {
    "addr:full":"13-17 Sankey Street Warrington Cheshire WA1 1XG",
    "addr:housenumber":"13-17",
    "addr:postcode":"wa1 1xg",
    "addr:street":"Sankey Street",
    "iso:country":"GB",
    "sg:address":"13-17 Sankey Street",
    "sg:city":"Warrington",
    "sg:classifiers":[
        {
            "category":"Shopping",
            "subcategory":"Clothing, Apparel, & Fashions",
            "type":"Retail Goods"
        }
    ],
    "sg:phone":"+44 1925 230281",
    "sg:postcode":"WA1 1XG",
    "sg:province":"Cheshire",
    "sg:tags":[
        "shop"
    ],
    "wof:name":"Top Shop Retail",
    "wof:placetype":"venue"
},
  "geometry": {"coordinates":[-2.593941927,53.3889350891],"type":"Point"}
}