{
  "type": "Feature",
  "properties": {
    "iso:country":"GB",
    "sg:address":"16 Market Street",
    "sg:city":"Haverfordwest",
    "sg:classifiers":[
        {
            "category":"Shopping",
            "subcategory":"News",
            "type":"Retail Goods"
        }
    ],
    "sg:postcode":"SA61 1NH",
    "sg:province":"Pembrokeshire",
    "sg:tags":[
        "newsagent"
    ],
    "wof:name":"John Pile",
    "wof:placetype":"venue"
},
  "geometry": {"coordinates":[-4.97113,51.800873],"type":"Point"}
}