{
  "type": "Feature",
  "properties": {
    "addr:full":"Unit 8, Fernfield Farm, Little Horwood Milton Keynes Bedfordshire MK17 0PT",
    "addr:housenumber":"unit 8",
    "addr:postcode":"mk17 0pt",
    "addr:street":"Fernfield Farm",
    "iso:country":"GB",
    "sg:address":"Unit 8, Fernfield Farm, Little Horwood",
    "sg:city":"Milton Keynes",
    "sg:classifiers":[
        {
            "category":"Manufacturing",
            "subcategory":"Buildings",
            "type":"Manufacturing & Wholesale Goods"
        },
        {
            "category":"Building & Trades",
            "subcategory":"Construction",
            "type":"Services"
        }
    ],
    "sg:phone":"+44 1908 375025",
    "sg:postcode":"MK17 0PT",
    "sg:province":"Bedfordshire",
    "sg:tags":[
        "joinery",
        "shed",
        "greenhouse"
    ],
    "wof:name":"M K T P",
    "wof:placetype":"venue"
},
  "geometry": {"coordinates":[-0.8771060109,51.9741134644],"type":"Point"}
}