{
  "type": "Feature",
  "properties": {
    "addr:full":"Bromsgrove Business Centre, 55-57 High Street Bromsgrove Worcestershire B61 8AJ",
    "addr:housenumber":"55-57",
    "addr:postcode":"b61 8aj",
    "addr:street":"High Street",
    "iso:country":"GB",
    "sg:address":"Bromsgrove Business Centre, 55-57 High Street",
    "sg:city":"Bromsgrove",
    "sg:classifiers":[
        {
            "category":"Organizations",
            "subcategory":"Non-profit Organization",
            "type":"Services"
        }
    ],
    "sg:phone":"+44 1527 575032",
    "sg:postcode":"B61 8AJ",
    "sg:province":"Worcestershire",
    "sg:tags":[
        "organisation",
        "voluntary",
        "charity"
    ],
    "wof:name":"Bromsgrove Redditch & Droitwich Mencap Society",
    "wof:placetype":"venue"
},
  "geometry": {"coordinates":[-2.0581119061,52.3365936279],"type":"Point"}
}