{
  "type": "Feature",
  "properties": {
    "iso:country":"GB",
    "sg:address":"Broxhall Farm, Pett Bottom",
    "sg:city":"Canterbury",
    "sg:classifiers":[
        {
            "category":"Farming",
            "subcategory":"Dairy Farm",
            "type":"Manufacturing & Wholesale Goods"
        }
    ],
    "sg:phone":"+44 1227 700205",
    "sg:postcode":"CT4 5PE",
    "sg:province":"Kent",
    "wof:name":"S T Sole",
    "wof:placetype":"venue"
},
  "geometry": {"coordinates":[1.093781,51.226608],"type":"Point"}
}