{
  "type": "Feature",
  "properties": {
    "addr:full":"9 Bradfield Close, Finedon Road Industrial Estate Wellingborough Northamptonshire NN8 4RQ",
    "addr:housenumber":"9",
    "addr:postcode":"nn8 4rq",
    "addr:street":"Bradfield Close Finedon Road Industrial Estate",
    "iso:country":"GB",
    "sg:address":"9 Bradfield Close, Finedon Road Industrial Estate",
    "sg:city":"Wellingborough",
    "sg:classifiers":[
        {
            "category":"Building & Trades",
            "subcategory":"Construction",
            "type":"Services"
        }
    ],
    "sg:phone":"+44 1933 272113",
    "sg:postcode":"NN8 4RQ",
    "sg:province":"Northamptonshire",
    "sg:tags":[
        "fork",
        "lift",
        "truck"
    ],
    "wof:name":"M & C Services (Northampton) Ltd.",
    "wof:placetype":"venue"
},
  "geometry": {"coordinates":[-0.6942210197,52.3231811523],"type":"Point"}
}