{
  "type": "Feature",
  "properties": {
    "addr:full":"Unit 43 South Mall, Hill St Shopping Centre Middlesbrough North Yorkshire TS1 1SU",
    "addr:housenumber":"unit 43",
    "addr:postcode":"ts1 1su",
    "addr:street":"South Mall Hill St Shopping",
    "iso:country":"GB",
    "sg:address":"Unit 43 South Mall, Hill St Shopping Centre",
    "sg:city":"Middlesbrough",
    "sg:classifiers":[
        {
            "category":"Food & Beverages",
            "subcategory":"Fruits & Vegetables",
            "type":"Retail Goods"
        }
    ],
    "sg:phone":"+44 1642 210070",
    "sg:postcode":"TS1 1SU",
    "sg:province":"North Yorkshire",
    "sg:tags":[
        "greengrocer"
    ],
    "wof:name":"A Bookless & Co",
    "wof:placetype":"venue"
},
  "geometry": {"coordinates":[-1.239560008,54.5771713257],"type":"Point"}
}