{
  "type": "Feature",
  "properties": {
    "addr:full":"34 Cleveland Rd North Shields Tyne and Wear NE29 0NW",
    "addr:housenumber":"34",
    "addr:postcode":"ne29 0nw",
    "addr:street":"Cleveland Rd",
    "iso:country":"GB",
    "sg:address":"34 Cleveland Rd",
    "sg:city":"North Shields",
    "sg:classifiers":[
        {
            "category":"Building & Trades",
            "subcategory":"Construction",
            "type":"Services"
        }
    ],
    "sg:postcode":"NE29 0NW",
    "sg:province":"Tyne and Wear",
    "sg:tags":[
        "builder"
    ],
    "wof:name":"Allan & Southern",
    "wof:placetype":"venue"
},
  "geometry": {"coordinates":[-1.452308,55.013306],"type":"Point"}
}