{
  "type": "Feature",
  "properties": {
    "addr:full":"27 Regent Arc, Regent St Cheltenham Gloucestershire GL50 1JZ",
    "addr:housenumber":"27",
    "addr:postcode":"gl50 1jz",
    "addr:street":"Regent;Regent St",
    "iso:country":"GB",
    "sg:address":"27 Regent Arc, Regent St",
    "sg:city":"Cheltenham",
    "sg:classifiers":[
        {
            "category":"Shopping",
            "subcategory":"Clothing, Apparel, & Fashions",
            "type":"Retail Goods"
        }
    ],
    "sg:phone":"+44 1242 577988",
    "sg:postcode":"GL50 1JZ",
    "sg:province":"Gloucestershire",
    "sg:tags":[
        "shop"
    ],
    "wof:name":"Benetton",
    "wof:placetype":"venue"
},
  "geometry": {"coordinates":[-2.0784590244,51.8980484009],"type":"Point"}
}