{
  "type": "Feature",
  "properties": {
    "iso:country":"GB",
    "sg:address":"Lane End Works, Station House",
    "sg:city":"Leicester",
    "sg:classifiers":[
        {
            "category":"Home & Garden",
            "subcategory":"Building Materials",
            "type":"Retail Goods"
        }
    ],
    "sg:phone":"+44 116 286 7978",
    "sg:postcode":"LE8 6JS",
    "sg:province":"Leicestershire",
    "sg:tags":[
        "fencing"
    ],
    "wof:name":"D M Phipps",
    "wof:placetype":"venue"
},
  "geometry": {"coordinates":[-1.1776989698,52.5635795593],"type":"Point"}
}