{
  "type": "Feature",
  "properties": {
    "iso:country":"GB",
    "sg:address":"15 Morris Lane",
    "sg:city":"Leeds",
    "sg:classifiers":[
        {
            "category":"Health Services",
            "subcategory":"Doctor",
            "type":"Services"
        },
        {
            "category":"Health Services",
            "subcategory":"Clinic",
            "type":"Services"
        }
    ],
    "sg:phone":"+44 113 275 2098",
    "sg:postcode":"LS5 3DB",
    "sg:province":"West Yorkshire",
    "sg:tags":[
        "practitioners",
        "private"
    ],
    "wof:name":"Kirkstall Clinic",
    "wof:placetype":"venue"
},
  "geometry": {"coordinates":[-1.598959,53.816872],"type":"Point"}
}