{
  "type": "Feature",
  "properties": {
    "iso:country":"GB",
    "sg:address":"Amblehurst Manor Farm, Petworth Rd, Wisborough Green",
    "sg:city":"Billingshurst",
    "sg:classifiers":[
        {
            "category":"Real Estate",
            "subcategory":"Surveying",
            "type":"Services"
        }
    ],
    "sg:phone":"+44 1403 700012",
    "sg:postcode":"RH14 0EP",
    "sg:province":"West Sussex",
    "sg:tags":[
        "surveyor",
        "valuer"
    ],
    "wof:name":"J.F.E Scott",
    "wof:placetype":"venue"
},
  "geometry": {"coordinates":[-0.505825,51.023121],"type":"Point"}
}