{
  "type": "Feature",
  "properties": {
    "iso:country":"GB",
    "sg:address":"1a & 1b Halsall Lane",
    "sg:city":"Liverpool",
    "sg:classifiers":[
        {
            "category":"Restaurant",
            "type":"Food & Drink"
        }
    ],
    "sg:postcode":"L37 3NW",
    "sg:province":"Lancashire",
    "wof:name":"The Beacons Restaurant",
    "wof:placetype":"venue"
},
  "geometry": {"coordinates":[-3.0600640774,53.5578727722],"type":"Point"}
}