{
  "type": "Feature",
  "properties": {
    "addr:full":"43 St Johns Ave Newmarket Cambridgeshire CB8 8DE",
    "addr:housenumber":"43",
    "addr:postcode":"cb8 8de",
    "addr:street":"St Johns Ave",
    "iso:country":"GB",
    "sg:address":"43 St Johns Ave",
    "sg:city":"Newmarket",
    "sg:classifiers":[
        {
            "category":"Professional",
            "subcategory":"Employment Agencies",
            "type":"Services"
        }
    ],
    "sg:postcode":"CB8 8DE",
    "sg:province":"Cambridgeshire",
    "sg:tags":[
        "consultant"
    ],
    "wof:name":"Herod,Stephen,",
    "wof:placetype":"venue"
},
  "geometry": {"coordinates":[0.408607,52.23558],"type":"Point"}
}