{
  "type": "Feature",
  "properties": {
    "iso:country":"GB",
    "sg:address":"23 Woodlands Road",
    "sg:city":"Redhill",
    "sg:classifiers":[
        {
            "category":"Social Services",
            "subcategory":"Adult Care",
            "type":"Services"
        },
        {
            "category":"Social Services",
            "subcategory":"Retirement Home",
            "type":"Services"
        }
    ],
    "sg:postcode":"RH1 6EY",
    "sg:province":"Surrey",
    "sg:tags":[
        "accomodation",
        "housing",
        "sheltered"
    ],
    "wof:name":"Reigate & Banstead Borough Council",
    "wof:placetype":"venue"
},
  "geometry": {"coordinates":[-0.1716679931,51.2299385071],"type":"Point"}
}