{
  "type": "Feature",
  "properties": {
    "addr:full":"The Bungalow, Tenter St Rotherham South Yorkshire S60 1LB",
    "addr:postcode":"s60 1lb",
    "addr:street":"Tenter St",
    "iso:country":"GB",
    "sg:address":"The Bungalow, Tenter St",
    "sg:city":"Rotherham",
    "sg:classifiers":[
        {
            "category":"Retail",
            "subcategory":"Auto Rental",
            "type":"Services"
        }
    ],
    "sg:phone":"+44 1709 555565",
    "sg:postcode":"S60 1LB",
    "sg:province":"South Yorkshire",
    "sg:tags":[
        "truck",
        "hire",
        "van"
    ],
    "wof:name":"T G Commercial Self Drive",
    "wof:placetype":"venue"
},
  "geometry": {"coordinates":[-1.354243,53.429874],"type":"Point"}
}