{
  "type": "Feature",
  "properties": {
    "addr:full":"4 Perry Hill Road, Oldbury Smethwick West Midlands B68 0AZ",
    "addr:housenumber":"4",
    "addr:postcode":"b68 0az",
    "addr:street":"Perry Hill Road",
    "iso:country":"GB",
    "sg:address":"4 Perry Hill Road, Oldbury",
    "sg:city":"Smethwick",
    "sg:classifiers":[
        {
            "category":"Home & Garden",
            "subcategory":"Hardware",
            "type":"Retail Goods"
        }
    ],
    "sg:postcode":"B68 0AZ",
    "sg:province":"West Midlands",
    "sg:tags":[
        "retailer",
        "diy"
    ],
    "wof:name":"Jukes Diy",
    "wof:placetype":"venue"
},
  "geometry": {"coordinates":[-2.0009710789,52.4678153992],"type":"Point"}
}