{
  "type": "Feature",
  "properties": {
    "iso:country":"GB",
    "sg:address":"1 Beaconsfield Rd",
    "sg:city":"Widnes",
    "sg:classifiers":[
        {
            "category":"Health Services",
            "subcategory":"Doctor",
            "type":"Services"
        }
    ],
    "sg:phone":"+44 151 424 3986",
    "sg:postcode":"WA8 9LB",
    "sg:province":"Cheshire",
    "sg:tags":[
        "practitioners"
    ],
    "wof:name":"Martin, N L",
    "wof:placetype":"venue"
},
  "geometry": {"coordinates":[-2.729924,53.381191],"type":"Point"}
}