{
  "type": "Feature",
  "properties": {
    "iso:country":"GB",
    "sg:address":"89a High Street",
    "sg:city":"Alfreton",
    "sg:classifiers":[
        {
            "category":"Professional",
            "subcategory":"Engineering",
            "type":"Services"
        }
    ],
    "sg:postcode":"DE55 5NU",
    "sg:province":"Derbyshire",
    "sg:tags":[
        "precision",
        "engineer"
    ],
    "wof:name":"Calander Precision Co.",
    "wof:placetype":"venue"
},
  "geometry": {"coordinates":[-1.342056036,53.1437454224],"type":"Point"}
}