{
  "type": "Feature",
  "properties": {
    "addr:full":"344 Lakeside Shopping Centre, West Thurrock Grays Essex RM20 2ZT",
    "addr:housenumber":"344",
    "addr:postcode":"rm20 2zt",
    "addr:street":"Lakeside Shopping;West",
    "iso:country":"GB",
    "sg:address":"344 Lakeside Shopping Centre, West Thurrock",
    "sg:city":"Grays",
    "sg:classifiers":[
        {
            "category":"Fast Food",
            "type":"Food & Drink"
        }
    ],
    "sg:phone":"+44 1708 861650",
    "sg:postcode":"RM20 2ZT",
    "sg:province":"Essex",
    "sg:tags":[
        "away",
        "take"
    ],
    "wof:name":"McDonalds Restaurants Ltd.",
    "wof:placetype":"venue"
},
  "geometry": {"coordinates":[0.2844699919,51.4856796265],"type":"Point"}
}