{
  "type": "Feature",
  "properties": {
    "iso:country":"GB",
    "sg:address":"70 High St",
    "sg:city":"Northwood",
    "sg:classifiers":[
        {
            "category":"Shopping",
            "subcategory":"Computers & Home Electronics",
            "type":"Retail Goods"
        }
    ],
    "sg:phone":"+44 1923 835150",
    "sg:postcode":"HA6 1BL",
    "sg:province":"Greater London",
    "sg:tags":[
        "electrical"
    ],
    "wof:name":"Adams Electrical Wholesale",
    "wof:placetype":"venue"
},
  "geometry": {"coordinates":[-0.4159969985,51.6071777344],"type":"Point"}
}