{
  "type": "Feature",
  "properties": {
    "addr:full":"Exeter Road Braunton Devon EX33 2BJ",
    "addr:postcode":"ex33 2bj",
    "addr:street":"Exeter Road",
    "iso:country":"GB",
    "sg:address":"Exeter Road",
    "sg:city":"Braunton",
    "sg:classifiers":[
        {
            "category":"Shopping",
            "subcategory":"Florist",
            "type":"Retail Goods"
        }
    ],
    "sg:phone":"+44 1271 812110",
    "sg:postcode":"EX33 2BJ",
    "sg:province":"Devon",
    "wof:name":"Candar Florist",
    "wof:placetype":"venue"
},
  "geometry": {"coordinates":[-4.1612391472,51.1082763672],"type":"Point"}
}