{
  "type": "Feature",
  "properties": {
    "iso:country":"GB",
    "sg:address":"Alwyns Lane",
    "sg:city":"Chertsey",
    "sg:classifiers":[
        {
            "category":"Arena",
            "subcategory":"Stadium",
            "type":"Entertainment"
        },
        {
            "category":"Arena",
            "subcategory":"Sports Club",
            "type":"Entertainment"
        }
    ],
    "sg:phone":"+44 1932 561774",
    "sg:postcode":"KT16 9DW",
    "sg:province":"Surrey",
    "sg:tags":[
        "ground"
    ],
    "wof:name":"CHERTSEY TOWN FOOTBALL CLUB",
    "wof:placetype":"venue"
},
  "geometry": {"coordinates":[-0.507216,51.39323],"type":"Point"}
}