{
  "type": "Feature",
  "properties": {
    "iso:country":"GB",
    "sg:address":"Eastbury Road, Thornbury",
    "sg:city":"Bristol",
    "sg:classifiers":[
        {
            "category":"Government",
            "subcategory":"City Hall",
            "type":"Public Place"
        }
    ],
    "sg:postcode":"BS35 1DR",
    "sg:province":"Gloucestershire",
    "wof:name":"St.Marys Church Hall",
    "wof:placetype":"venue"
},
  "geometry": {"coordinates":[-2.516719,51.612289],"type":"Point"}
}