{
  "type": "Feature",
  "properties": {
    "addr:full":"109c Downs Road London Greater London E5 8DS",
    "addr:housenumber":"109c",
    "addr:postcode":"e5 8ds",
    "addr:street":"Downs Road",
    "iso:country":"GB",
    "sg:address":"109c Downs Road",
    "sg:city":"London",
    "sg:classifiers":[
        {
            "category":"Taxi",
            "type":"Transportation"
        }
    ],
    "sg:phone":"+44 20 8986 0007",
    "sg:postcode":"E5 8DS",
    "sg:province":"Greater London",
    "sg:tags":[
        "mini",
        "cab"
    ],
    "wof:name":"007 Cabs",
    "wof:placetype":"venue"
},
  "geometry": {"coordinates":[-0.0560490005,51.5559310913],"type":"Point"}
}