{
  "type": "Feature",
  "properties": {
    "addr:full":"21 Stanbrook Clo, Southend Reading Berkshire RG7 6EW",
    "addr:housenumber":"21",
    "addr:postcode":"rg7 6ew",
    "addr:street":"Stanbrook Clo Southend",
    "iso:country":"GB",
    "sg:address":"21 Stanbrook Clo, Southend",
    "sg:city":"Reading",
    "sg:classifiers":[
        {
            "category":"Manufacturing",
            "subcategory":"Tools & Machinery",
            "type":"Manufacturing & Wholesale Goods"
        }
    ],
    "sg:postcode":"RG7 6EW",
    "sg:province":"Berkshire",
    "sg:tags":[
        "society",
        "friendly"
    ],
    "wof:name":"Lapham,Phillip",
    "wof:placetype":"venue"
},
  "geometry": {"coordinates":[-1.148249,51.430962],"type":"Point"}
}