{
  "type": "Feature",
  "properties": {
    "iso:country":"GB",
    "sg:address":"18 Fiddlers Lane, Irlam",
    "sg:city":"Manchester",
    "sg:classifiers":[
        {
            "category":"Organizations",
            "subcategory":"Non-profit Organization",
            "type":"Services"
        }
    ],
    "sg:phone":"+44 161 775 5340",
    "sg:postcode":"M44 6HN",
    "sg:province":"Greater Manchester",
    "sg:tags":[
        "charitable",
        "organisation",
        "voluntary",
        "charity"
    ],
    "wof:name":"IRLAM FAMILY CENTRE",
    "wof:placetype":"venue"
},
  "geometry": {"coordinates":[-2.4113669395,53.4557189941],"type":"Point"}
}