{
  "type": "Feature",
  "properties": {
    "iso:country":"GB",
    "sg:address":"9 Palace Street",
    "sg:city":"Caernarfon",
    "sg:classifiers":[
        {
            "category":"Shopping",
            "subcategory":"Clothing, Apparel, & Fashions",
            "type":"Retail Goods"
        }
    ],
    "sg:phone":"+44 1286 675124",
    "sg:postcode":"LL55 1RR",
    "sg:province":"Gwynedd",
    "sg:tags":[
        "workwear",
        "protective"
    ],
    "wof:name":"14th Peak",
    "wof:placetype":"venue"
},
  "geometry": {"coordinates":[-4.276049,53.140266],"type":"Point"}
}