{
  "type": "Feature",
  "properties": {
    "addr:full":"Nunn Brook Road, Huthwaite Sutton-in-ashfield Nottinghamshire NG17 2HU",
    "addr:postcode":"ng17 2hu",
    "addr:street":"Nunn Brook Road",
    "iso:country":"GB",
    "sg:address":"Nunn Brook Road, Huthwaite",
    "sg:city":"Sutton-in-ashfield",
    "sg:classifiers":[
        {
            "category":"Building & Trades",
            "subcategory":"Equipment Rental",
            "type":"Services"
        }
    ],
    "sg:phone":"+44 1623 558767",
    "sg:postcode":"NG17 2HU",
    "sg:province":"Nottinghamshire",
    "sg:tags":[
        "plant",
        "machinery"
    ],
    "wof:name":"Handi Hire",
    "wof:placetype":"venue"
},
  "geometry": {"coordinates":[-1.307299,53.121319],"type":"Point"}
}