{
  "type": "Feature",
  "properties": {
    "iso:country":"GB",
    "sg:address":"18 Vivian Park",
    "sg:city":"Swanage",
    "sg:classifiers":[
        {
            "category":"Social Services",
            "subcategory":"Job Training",
            "type":"Services"
        }
    ],
    "sg:postcode":"BH19 1PJ",
    "sg:province":"Dorset",
    "sg:tags":[
        "translator",
        "interpreter"
    ],
    "wof:name":"Serrani Translations",
    "wof:placetype":"venue"
},
  "geometry": {"coordinates":[-1.961381,50.617599],"type":"Point"}
}