{
  "type": "Feature",
  "properties": {
    "addr:full":"17 St. Pauls Clo Stalybridge Greater Manchester SK15 3DS",
    "addr:housenumber":"17",
    "addr:postcode":"sk15 3ds",
    "addr:street":"St. Pauls Clo",
    "iso:country":"GB",
    "sg:address":"17 St. Pauls Clo",
    "sg:city":"Stalybridge",
    "sg:classifiers":[
        {
            "category":"Building & Trades",
            "subcategory":"Construction",
            "type":"Services"
        }
    ],
    "sg:phone":"+44 161 304 8917",
    "sg:postcode":"SK15 3DS",
    "sg:province":"Greater Manchester",
    "sg:tags":[
        "fork",
        "lift",
        "truck"
    ],
    "wof:name":"C T Fork Lift Trucks",
    "wof:placetype":"venue"
},
  "geometry": {"coordinates":[-2.043487,53.487419],"type":"Point"}
}