{
  "type": "Feature",
  "properties": {
    "iso:country":"GB",
    "sg:address":"73 Upton Hill",
    "sg:city":"Torquay",
    "sg:classifiers":[
        {
            "category":"Train Station",
            "subcategory":"Rail",
            "type":"Transportation"
        }
    ],
    "sg:phone":"+44 1803 325753",
    "sg:postcode":"TQ1 3ES",
    "sg:province":"Devon",
    "sg:tags":[
        "caravan"
    ],
    "wof:name":"Benney Trailers",
    "wof:placetype":"venue"
},
  "geometry": {"coordinates":[-3.53243,50.473782],"type":"Point"}
}