{
  "type": "Feature",
  "properties": {
    "iso:country":"GB",
    "sg:address":"Hare Law Farm, Hare Law",
    "sg:city":"Stanley",
    "sg:classifiers":[
        {
            "category":"Food & Beverages",
            "subcategory":"Farmers Market",
            "type":"Retail Goods"
        }
    ],
    "sg:phone":"+44 1207 283742",
    "sg:postcode":"DH9 8DA",
    "sg:province":"Durham",
    "sg:tags":[
        "farm",
        "shop",
        "pyo"
    ],
    "wof:name":"Hare Law Farm Shop",
    "wof:placetype":"venue"
},
  "geometry": {"coordinates":[-1.749244,54.86903],"type":"Point"}
}