{
  "type": "Feature",
  "properties": {
    "iso:country":"GB",
    "sg:address":"91 Commerce St",
    "sg:city":"Glasgow",
    "sg:classifiers":[
        {
            "category":"Wholesale",
            "subcategory":"Non-durable Goods",
            "type":"Manufacturing & Wholesale Goods"
        }
    ],
    "sg:postcode":"G5 8EP",
    "sg:province":"Glasgow City",
    "sg:tags":[
        "carry",
        "cash"
    ],
    "wof:name":"X S C Ltd",
    "wof:placetype":"venue"
},
  "geometry": {"coordinates":[-4.260455,55.852161],"type":"Point"}
}