{
  "type": "Feature",
  "properties": {
    "addr:full":"36 George Street Dumfries Dumfries and Galloway DG1 1EH",
    "addr:housenumber":"36",
    "addr:postcode":"dg1 1eh",
    "addr:street":"George Street",
    "iso:country":"GB",
    "sg:address":"36 George Street",
    "sg:city":"Dumfries",
    "sg:classifiers":[
        {
            "category":"Real Estate",
            "subcategory":"Surveying",
            "type":"Services"
        }
    ],
    "sg:phone":"+44 1387 254283",
    "sg:postcode":"DG1 1EH",
    "sg:province":"Dumfries and Galloway",
    "sg:tags":[
        "surveyor",
        "valuer"
    ],
    "wof:name":"McGowan Miller Partnership",
    "wof:placetype":"venue"
},
  "geometry": {"coordinates":[-3.6144371033,55.0708465576],"type":"Point"}
}