{
  "type": "Feature",
  "properties": {
    "iso:country":"GB",
    "sg:address":"20 White Lion Street",
    "sg:city":"Norwich",
    "sg:classifiers":[
        {
            "category":"Shopping",
            "subcategory":"Clothing, Apparel, & Fashions",
            "type":"Retail Goods"
        }
    ],
    "sg:phone":"+44 1603 633301",
    "sg:postcode":"NR2 1PX",
    "sg:province":"Norfolk",
    "sg:tags":[
        "menswear"
    ],
    "sg:website":"http://www.moss.co.uk",
    "wof:name":"Moss",
    "wof:placetype":"venue"
},
  "geometry": {"coordinates":[1.2948080301,52.6273422241],"type":"Point"}
}