{
  "type": "Feature",
  "properties": {
    "iso:country":"GB",
    "sg:address":"Wimbledon Bridge Ho, 1 Hartfield Rd, Wimbledon",
    "sg:city":"Wimbledon",
    "sg:classifiers":[
        {
            "category":"Banks & Credit Unions",
            "subcategory":"Financial Services",
            "type":"Services"
        }
    ],
    "sg:phone":"+44 20 7826 8580",
    "sg:postcode":"SW19 3RU",
    "sg:province":"Greater London",
    "sg:tags":[
        "consultant"
    ],
    "wof:name":"Standard & Poors Compustat Ims",
    "wof:placetype":"venue"
},
  "geometry": {"coordinates":[-0.20665,51.420471],"type":"Point"}
}