{
  "type": "Feature",
  "properties": {
    "addr:full":"Middle Farm, Newton Street, Newton St Faith Norwich Norfolk NR10 3LS",
    "addr:postcode":"nr10 3ls",
    "addr:street":"Middle;Newton Street;St;Norwich",
    "iso:country":"GB",
    "sg:address":"Middle Farm, Newton Street, Newton St Faith",
    "sg:city":"Norwich",
    "sg:classifiers":[
        {
            "category":"Home & Garden",
            "subcategory":"Garden Supply",
            "type":"Retail Goods"
        }
    ],
    "sg:postcode":"NR10 3LS",
    "sg:province":"Norfolk",
    "sg:tags":[
        "bulb",
        "grower"
    ],
    "wof:name":"A Howard",
    "wof:placetype":"venue"
},
  "geometry": {"coordinates":[1.2904299498,52.7080192566],"type":"Point"}
}