{
  "type": "Feature",
  "properties": {
    "addr:full":"136 Greyhound Rd London Greater London W6 8NS",
    "addr:housenumber":"136",
    "addr:postcode":"w6 8ns",
    "addr:street":"Greyhound Rd",
    "iso:country":"GB",
    "sg:address":"136 Greyhound Rd",
    "sg:city":"London",
    "sg:classifiers":[
        {
            "category":"Shopping",
            "subcategory":"News",
            "type":"Retail Goods"
        }
    ],
    "sg:phone":"+44 20 7385 8024",
    "sg:postcode":"W6 8NS",
    "sg:province":"Greater London",
    "sg:tags":[
        "newsagent"
    ],
    "wof:name":"W.A. Patterson and Sons Limited",
    "wof:placetype":"venue"
},
  "geometry": {"coordinates":[-0.2127459943,51.4860076904],"type":"Point"}
}