{
  "type": "Feature",
  "properties": {
    "addr:full":"220 Bishopsgate Moorgate Greater London EC2M 4QD",
    "addr:housenumber":"220",
    "addr:postcode":"ec2m 4qd",
    "addr:street":"Bishopsgate Moorgate",
    "iso:country":"GB",
    "sg:address":"220 Bishopsgate",
    "sg:city":"Moorgate",
    "sg:classifiers":[
        {
            "category":"Retail",
            "subcategory":"Photofinishing",
            "type":"Services"
        }
    ],
    "sg:phone":"+44 20 7377 5752",
    "sg:postcode":"EC2M 4QD",
    "sg:province":"Greater London",
    "sg:tags":[
        "photographic",
        "processor"
    ],
    "wof:name":"Snappy Snaps",
    "wof:placetype":"venue"
},
  "geometry": {"coordinates":[-0.079501003,51.5184173584],"type":"Point"}
}