{
  "type": "Feature",
  "properties": {
    "addr:full":"Little Gro, Winslow, Bromyard Hereford Herefordshire HR7 4SG",
    "addr:postcode":"hr7 4sg",
    "iso:country":"GB",
    "sg:address":"Little Gro, Winslow, Bromyard",
    "sg:city":"Hereford",
    "sg:classifiers":[
        {
            "category":"Utilities",
            "subcategory":"Fuel Oil & Lpg",
            "type":"Services"
        }
    ],
    "sg:phone":"+44 1885 400628",
    "sg:postcode":"HR7 4SG",
    "sg:province":"Herefordshire",
    "sg:tags":[
        "merchant",
        "coal"
    ],
    "wof:name":"A J Colley (Coal Merchant)",
    "wof:placetype":"venue"
},
  "geometry": {"coordinates":[-2.5103991032,52.1890983582],"type":"Point"}
}