{
  "type": "Feature",
  "properties": {
    "iso:country":"GB",
    "sg:address":"11 Campbell Court Business Park, Bramley",
    "sg:city":"Basingstoke",
    "sg:classifiers":[
        {
            "category":"Professional",
            "subcategory":"Computer Services",
            "type":"Services"
        }
    ],
    "sg:phone":"+44 5009800098",
    "sg:postcode":"RG26 5EG",
    "sg:province":"Berkshire",
    "sg:tags":[
        "consultant"
    ],
    "wof:name":"Olympia Training Ltd.",
    "wof:placetype":"venue"
},
  "geometry": {"coordinates":[-1.0454479456,51.3245544434],"type":"Point"}
}