{
  "type": "Feature",
  "properties": {
    "addr:full":"3 Toothill La Mansfield Nottinghamshire NG18 1NJ",
    "addr:housenumber":"3",
    "addr:postcode":"ng18 1nj",
    "addr:street":"Toothill La Mansfield",
    "iso:country":"GB",
    "sg:address":"3 Toothill La",
    "sg:city":"Mansfield",
    "sg:classifiers":[
        {
            "category":"Shopping",
            "subcategory":"Clothing, Apparel, & Fashions",
            "type":"Retail Goods"
        }
    ],
    "sg:phone":"+44 1623 621040",
    "sg:postcode":"NG18 1NJ",
    "sg:province":"Nottinghamshire",
    "sg:tags":[
        "shop"
    ],
    "wof:name":"Hardy,Jane,Ltd",
    "wof:placetype":"venue"
},
  "geometry": {"coordinates":[-1.195049,53.145531],"type":"Point"}
}