{
  "type": "Feature",
  "properties": {
    "addr:full":"29 St. Botolphs Rd Sevenoaks Kent TN13 3AQ",
    "addr:housenumber":"29",
    "addr:postcode":"tn13 3aq",
    "addr:street":"St. Botolphs Rd",
    "iso:country":"GB",
    "sg:address":"29 St. Botolphs Rd",
    "sg:city":"Sevenoaks",
    "sg:classifiers":[
        {
            "category":"Health Services",
            "subcategory":"Chiropractor",
            "type":"Services"
        }
    ],
    "sg:phone":"+44 1732 742120",
    "sg:postcode":"TN13 3AQ",
    "sg:province":"Kent",
    "wof:name":"Sevenoaks Chiropractic Clinic",
    "wof:placetype":"venue"
},
  "geometry": {"coordinates":[0.188361004,51.276725769],"type":"Point"}
}