{
  "type": "Feature",
  "properties": {
    "addr:full":"5 Brackendale Shopping Centre, Stroud Av Willenhall West Midlands WV12 4HA",
    "addr:housenumber":"5",
    "addr:postcode":"wv12 4ha",
    "addr:street":"Brackendale Shopping Centre;Av",
    "iso:country":"GB",
    "sg:address":"5 Brackendale Shopping Centre, Stroud Av",
    "sg:city":"Willenhall",
    "sg:classifiers":[
        {
            "category":"Food & Beverages",
            "subcategory":"Liquor & Beverages",
            "type":"Retail Goods"
        }
    ],
    "sg:phone":"+44 1902 601331",
    "sg:postcode":"WV12 4HA",
    "sg:province":"West Midlands",
    "sg:tags":[
        "beer",
        "spirit",
        "wines"
    ],
    "wof:name":"Dhillons Wines",
    "wof:placetype":"venue"
},
  "geometry": {"coordinates":[-2.0316100121,52.5945281982],"type":"Point"}
}