{
  "type": "Feature",
  "properties": {
    "addr:full":"Selsey Road, Edgbaston Birmingham West Midlands B17 8JR",
    "addr:postcode":"b17 8jr",
    "addr:street":"Selsey Road",
    "iso:country":"GB",
    "sg:address":"Selsey Road, Edgbaston",
    "sg:city":"Birmingham",
    "sg:classifiers":[
        {
            "category":"Shopping",
            "subcategory":"Stationery & Office Supplies",
            "type":"Retail Goods"
        },
        {
            "category":"Government",
            "subcategory":"Post Office",
            "type":"Public Place"
        }
    ],
    "sg:phone":"+44 121 429 1878",
    "sg:postcode":"B17 8JR",
    "sg:province":"West Midlands",
    "wof:name":"Selsey Post Office",
    "wof:placetype":"venue"
},
  "geometry": {"coordinates":[-1.9592139721,52.4825363159],"type":"Point"}
}