{
  "type": "Feature",
  "properties": {
    "addr:full":"Brynteg Farm, Gorad Holyhead Isle of Anglesey LL65 3BT",
    "addr:postcode":"ll65 3bt",
    "addr:street":"Holyhead",
    "iso:country":"GB",
    "sg:address":"Brynteg Farm, Gorad",
    "sg:city":"Holyhead",
    "sg:classifiers":[
        {
            "category":"Farming",
            "subcategory":"Livestock Farm",
            "type":"Manufacturing & Wholesale Goods"
        }
    ],
    "sg:phone":"+44 1407 740638",
    "sg:postcode":"LL65 3BT",
    "sg:province":"Isle of Anglesey",
    "sg:tags":[
        "others"
    ],
    "wof:name":"K W Evans",
    "wof:placetype":"venue"
},
  "geometry": {"coordinates":[-4.630714,53.30637],"type":"Point"}
}