{
  "type": "Feature",
  "properties": {
    "addr:full":"11 George Street, Snaith Goole East Riding of Yorkshire DN14 9HY",
    "addr:housenumber":"11",
    "addr:postcode":"dn14 9hy",
    "addr:street":"George Street",
    "iso:country":"GB",
    "sg:address":"11 George Street, Snaith",
    "sg:city":"Goole",
    "sg:classifiers":[
        {
            "category":"Freight",
            "type":"Transportation"
        }
    ],
    "sg:phone":"+44 1405 860936",
    "sg:postcode":"DN14 9HY",
    "sg:province":"East Riding of Yorkshire",
    "sg:tags":[
        "haulage",
        "transport",
        "road"
    ],
    "wof:name":"H Thorpe Haulage",
    "wof:placetype":"venue"
},
  "geometry": {"coordinates":[-1.027304,53.692806],"type":"Point"}
}