{
  "type": "Feature",
  "properties": {
    "addr:full":"Torrs Of Kelton Castle Douglas Dumfries and Galloway DG7 1NF",
    "addr:postcode":"dg7 1nf",
    "iso:country":"GB",
    "sg:address":"Torrs Of Kelton",
    "sg:city":"Castle Douglas",
    "sg:classifiers":[
        {
            "category":"Farming",
            "subcategory":"Farm",
            "type":"Manufacturing & Wholesale Goods"
        }
    ],
    "sg:postcode":"DG7 1NF",
    "sg:province":"Dumfries and Galloway",
    "sg:tags":[
        "mixed",
        "crop"
    ],
    "wof:name":"Messrs Smith John",
    "wof:placetype":"venue"
},
  "geometry": {"coordinates":[-3.9287040234,54.941619873],"type":"Point"}
}