{
  "type": "Feature",
  "properties": {
    "iso:country":"GB",
    "sg:address":"2 Park Pl",
    "sg:city":"Liverpool",
    "sg:classifiers":[
        {
            "category":"Bars & Pubs",
            "type":"Food & Drink"
        }
    ],
    "sg:postcode":"L8 5RA",
    "sg:province":"Merseyside",
    "sg:tags":[
        "pubs",
        "inn"
    ],
    "wof:name":"Volunteer Arms (The)",
    "wof:placetype":"venue"
},
  "geometry": {"coordinates":[-2.972409,53.392086],"type":"Point"}
}