{
  "type": "Feature",
  "properties": {
    "iso:country":"GB",
    "sg:address":"Widow Hill Rd",
    "sg:city":"Burnley",
    "sg:classifiers":[
        {
            "category":"Manufacturing",
            "subcategory":"Wood Products",
            "type":"Manufacturing & Wholesale Goods"
        }
    ],
    "sg:phone":"+44 1282 421957",
    "sg:postcode":"BB10 2BD",
    "sg:province":"Lancashire",
    "wof:name":"Lucas Aftermarket Operations",
    "wof:placetype":"venue"
},
  "geometry": {"coordinates":[-2.2182888985,53.8065299988],"type":"Point"}
}