{
  "type": "Feature",
  "properties": {
    "iso:country":"GB",
    "sg:address":"48 Bank Street",
    "sg:city":"Braintree",
    "sg:classifiers":[
        {
            "category":"Food & Beverages",
            "subcategory":"Meat & Fish",
            "type":"Retail Goods"
        }
    ],
    "sg:phone":"+44 1376 349559",
    "sg:postcode":"CM7 1UL",
    "sg:province":"Essex",
    "sg:tags":[
        "butcher"
    ],
    "wof:name":"Meat Inn Ltd.",
    "wof:placetype":"venue"
},
  "geometry": {"coordinates":[0.5513700247,51.8792762756],"type":"Point"}
}