{
  "type": "Feature",
  "properties": {
    "iso:country":"GB",
    "sg:address":"80 Fulham Palace Road",
    "sg:city":"London",
    "sg:classifiers":[
        {
            "category":"Bars & Pubs",
            "type":"Food & Drink"
        }
    ],
    "sg:phone":"+44 20 8748 6502",
    "sg:postcode":"W6 9PL",
    "sg:province":"Greater London",
    "sg:tags":[
        "pubs",
        "house",
        "inn",
        "public",
        "activity"
    ],
    "wof:name":"The Old Suffolk Punch",
    "wof:placetype":"venue"
},
  "geometry": {"coordinates":[-0.222891,51.488678],"type":"Point"}
}