{
  "type": "Feature",
  "properties": {
    "iso:country":"GB",
    "sg:address":"Comptons Yard, Grovebury Road",
    "sg:city":"Leighton Buzzard",
    "sg:classifiers":[
        {
            "category":"Autos & Motor Vehicles",
            "subcategory":"Automobile Sales",
            "type":"Retail Goods"
        }
    ],
    "sg:phone":"+44 1525 371707",
    "sg:postcode":"LU7 4TS",
    "sg:province":"Bedfordshire",
    "sg:tags":[
        "car",
        "commercial"
    ],
    "wof:name":"M F Compton Commercials",
    "wof:placetype":"venue"
},
  "geometry": {"coordinates":[-0.663909,51.917351],"type":"Point"}
}