{
  "type": "Feature",
  "properties": {
    "addr:full":"Pretty & Ellis, Station Road Amersham Buckinghamshire HP7 0AH",
    "addr:postcode":"hp7 0ah",
    "addr:street":"Station Road",
    "iso:country":"GB",
    "sg:address":"Pretty & Ellis, Station Road",
    "sg:city":"Amersham",
    "sg:classifiers":[
        {
            "category":"Professional",
            "type":"Services"
        }
    ],
    "sg:postcode":"HP7 0AH",
    "sg:province":"Buckinghamshire",
    "sg:tags":[
        "auctioneer"
    ],
    "wof:name":"Amersham Auction Rooms",
    "wof:placetype":"venue"
},
  "geometry": {"coordinates":[-0.60852,51.673859],"type":"Point"}
}