{
  "type": "Feature",
  "properties": {
    "addr:full":"Main Street, Lennoxtown Glasgow East Dunbartonshire G66 7HA",
    "addr:postcode":"g66 7ha",
    "addr:street":"Main Street",
    "iso:country":"GB",
    "sg:address":"Main Street, Lennoxtown",
    "sg:city":"Glasgow",
    "sg:classifiers":[
        {
            "category":"Government",
            "subcategory":"City Hall",
            "type":"Public Place"
        },
        {
            "category":"Retail",
            "subcategory":"Event Space",
            "type":"Services"
        },
        {
            "category":"Government",
            "subcategory":"Office",
            "type":"Public Place"
        }
    ],
    "sg:phone":"+44 1360 310123",
    "sg:postcode":"G66 7HA",
    "sg:province":"East Dunbartonshire",
    "sg:tags":[
        "function",
        "hire",
        "local",
        "room"
    ],
    "wof:name":"Campsie Memorial Hall",
    "wof:placetype":"venue"
},
  "geometry": {"coordinates":[-4.2027740479,55.9752807617],"type":"Point"}
}