{
  "type": "Feature",
  "properties": {
    "addr:full":"Insta House, Ivanhoe Road, Hogwood Business Park Wokingham Berkshire RG40 4PZ",
    "addr:postcode":"rg40 4pz",
    "addr:street":"Ivanhoe Road Hogwood Business Park",
    "iso:country":"GB",
    "sg:address":"Insta House, Ivanhoe Road, Hogwood Business Park",
    "sg:city":"Wokingham",
    "sg:classifiers":[
        {
            "category":"Professional",
            "subcategory":"Management & Consulting",
            "type":"Services"
        },
        {
            "category":"Home & Garden",
            "subcategory":"Building Materials",
            "type":"Retail Goods"
        }
    ],
    "sg:phone":"+44 118 932 8811",
    "sg:postcode":"RG40 4PZ",
    "sg:province":"Berkshire",
    "sg:tags":[
        "insulation",
        "installers",
        "holding",
        "activity"
    ],
    "wof:name":"Instaproperty Ltd.",
    "wof:placetype":"venue"
},
  "geometry": {"coordinates":[-0.8920339942,51.3749160767],"type":"Point"}
}