{
  "type": "Feature",
  "properties": {
    "addr:full":"95 Wembley Park Drive Edgware Greater London HA9 8HF",
    "addr:housenumber":"95",
    "addr:postcode":"ha9 8hf",
    "addr:street":"Wembley Park Drive",
    "iso:country":"GB",
    "sg:address":"95 Wembley Park Drive",
    "sg:city":"Edgware",
    "sg:classifiers":[
        {
            "category":"Shopping",
            "subcategory":"Pharmacy",
            "type":"Retail Goods"
        }
    ],
    "sg:postcode":"HA9 8HF",
    "sg:province":"Greater London",
    "sg:tags":[
        "pharmacist",
        "chemist"
    ],
    "wof:name":"Lewis,C G,",
    "wof:placetype":"venue"
},
  "geometry": {"coordinates":[-0.2832599878,51.5619697571],"type":"Point"}
}