{
  "type": "Feature",
  "properties": {
    "iso:country":"GB",
    "sg:address":"49 Patterdale Avenue, Marton",
    "sg:city":"Blackpool",
    "sg:classifiers":[
        {
            "category":"Professional",
            "subcategory":"Art Services",
            "type":"Services"
        },
        {
            "category":"Building & Trades",
            "subcategory":"Construction",
            "type":"Services"
        }
    ],
    "sg:phone":"+44 1253 768575",
    "sg:postcode":"FY3 9QR",
    "sg:province":"Lancashire",
    "sg:tags":[
        "decorator",
        "painter"
    ],
    "wof:name":"T A Eves & Sons",
    "wof:placetype":"venue"
},
  "geometry": {"coordinates":[-3.019511,53.805134],"type":"Point"}
}