{
  "type": "Feature",
  "properties": {
    "iso:country":"GB",
    "sg:address":"117 Unthank Road",
    "sg:city":"Norwich",
    "sg:classifiers":[
        {
            "category":"Cafe",
            "type":"Food & Drink"
        }
    ],
    "sg:phone":"+44 1603 624010",
    "sg:postcode":"NR2 2PE",
    "sg:province":"Norfolk",
    "sg:tags":[
        "tea",
        "room"
    ],
    "wof:name":"Unthank Kitchen",
    "wof:placetype":"venue"
},
  "geometry": {"coordinates":[1.277392,52.624424],"type":"Point"}
}