{
  "type": "Feature",
  "properties": {
    "addr:full":"2 Elliott Court, Stobhill Morpeth Northumberland NE61 2EW",
    "addr:housenumber":"2",
    "addr:postcode":"ne61 2ew",
    "addr:street":"Elliott Court",
    "iso:country":"GB",
    "sg:address":"2 Elliott Court, Stobhill",
    "sg:city":"Morpeth",
    "sg:classifiers":[
        {
            "category":"Professional",
            "subcategory":"Art Services",
            "type":"Services"
        }
    ],
    "sg:phone":"+44 1670 503731",
    "sg:postcode":"NE61 2EW",
    "sg:province":"Northumberland",
    "sg:tags":[
        "graphic",
        "designer"
    ],
    "wof:name":"Chase the Ace Design Consultancy",
    "wof:placetype":"venue"
},
  "geometry": {"coordinates":[-1.684391,55.160393],"type":"Point"}
}