{
  "type": "Feature",
  "properties": {
    "addr:full":"Polwarth Manse, Greenlaw Duns Scottish Borders TD10 6YR",
    "addr:postcode":"td10 6yr",
    "addr:street":"Duns",
    "iso:country":"GB",
    "sg:address":"Polwarth Manse, Greenlaw",
    "sg:city":"Duns",
    "sg:classifiers":[
        {
            "category":"Shopping",
            "subcategory":"Books",
            "type":"Retail Goods"
        }
    ],
    "sg:phone":"+44 1361 882306",
    "sg:postcode":"TD10 6YR",
    "sg:province":"Scottish Borders",
    "sg:tags":[
        "bookseller"
    ],
    "wof:name":"Polwarth Books",
    "wof:placetype":"venue"
},
  "geometry": {"coordinates":[-2.462529,55.706516],"type":"Point"}
}