{
  "type": "Feature",
  "properties": {
    "iso:country":"GB",
    "sg:address":"10 Crescent West, Hadley Wood",
    "sg:city":"Barnet",
    "sg:classifiers":[
        {
            "category":"Real Estate",
            "subcategory":"Real Estate Agent",
            "type":"Services"
        }
    ],
    "sg:phone":"+44 20 8440 9797",
    "sg:postcode":"EN4 0EJ",
    "sg:province":"Hertfordshire",
    "wof:name":"Statons Estate Agents",
    "wof:placetype":"venue"
},
  "geometry": {"coordinates":[-0.176183,51.668427],"type":"Point"}
}