{
  "type": "Feature",
  "properties": {
    "addr:full":"Dawson Lane, Dudley Hill Bradford West Yorkshire BD4 6HW",
    "addr:postcode":"bd4 6hw",
    "addr:street":"Dawson Lane",
    "iso:country":"GB",
    "sg:address":"Dawson Lane, Dudley Hill",
    "sg:city":"Bradford",
    "sg:classifiers":[
        {
            "category":"Shopping",
            "subcategory":"Gifts & Souvenirs",
            "type":"Retail Goods"
        }
    ],
    "sg:phone":"+44 1274 651188",
    "sg:postcode":"BD4 6HW",
    "sg:province":"West Yorkshire",
    "sg:tags":[
        "poster",
        "card"
    ],
    "wof:name":"Giftree Ltd.",
    "wof:placetype":"venue"
},
  "geometry": {"coordinates":[-1.720524,53.770836],"type":"Point"}
}