{
  "type": "Feature",
  "properties": {
    "iso:country":"GB",
    "sg:address":"Unit 20 Front Street Industrial Estate, Front Street, South Hetton",
    "sg:city":"Durham",
    "sg:classifiers":[
        {
            "category":"Manufacturing",
            "subcategory":"Tools & Machinery",
            "type":"Manufacturing & Wholesale Goods"
        }
    ],
    "sg:phone":"+44 191 526 8326",
    "sg:postcode":"DH6 2UZ",
    "sg:province":"Durham",
    "wof:name":"Anvil Engineering",
    "wof:placetype":"venue"
},
  "geometry": {"coordinates":[-1.4177039862,54.7848548889],"type":"Point"}
}