{
  "type": "Feature",
  "properties": {
    "addr:full":"8 Chester Street Chester Cheshire CH4 8BJ",
    "addr:housenumber":"8",
    "addr:postcode":"ch4 8bj",
    "addr:street":"Chester Street",
    "iso:country":"GB",
    "sg:address":"8 Chester Street",
    "sg:city":"Chester",
    "sg:classifiers":[
        {
            "category":"Home & Garden",
            "subcategory":"Household Appliances",
            "type":"Retail Goods"
        }
    ],
    "sg:phone":"+44 1244 314927",
    "sg:postcode":"CH4 8BJ",
    "sg:province":"Cheshire",
    "sg:tags":[
        "cleaner",
        "domestic",
        "vacuum"
    ],
    "wof:name":"Buttons Electrical",
    "wof:placetype":"venue"
},
  "geometry": {"coordinates":[-2.9161500931,53.1795539856],"type":"Point"}
}