{
  "type": "Feature",
  "properties": {
    "iso:country":"GB",
    "sg:address":"5 Waresley Road",
    "sg:city":"Sandy",
    "sg:classifiers":[
        {
            "category":"Building & Trades",
            "subcategory":"Construction",
            "type":"Services"
        }
    ],
    "sg:postcode":"SG19 3EH",
    "sg:province":"Bedfordshire",
    "sg:tags":[
        "builder"
    ],
    "wof:name":"John Huckle",
    "wof:placetype":"venue"
},
  "geometry": {"coordinates":[-0.193155,52.15572],"type":"Point"}
}