{
  "type": "Feature",
  "properties": {
    "addr:full":"Manor Street Forfar Angus DD8 1EX",
    "addr:postcode":"dd8 1ex",
    "addr:street":"Manor Street",
    "iso:country":"GB",
    "sg:address":"Manor Street",
    "sg:city":"Forfar",
    "sg:classifiers":[
        {
            "category":"Real Estate",
            "subcategory":"Surveying",
            "type":"Services"
        }
    ],
    "sg:phone":"+44 1307 462516",
    "sg:postcode":"DD8 1EX",
    "sg:province":"Angus",
    "sg:tags":[
        "surveyor",
        "valuer"
    ],
    "wof:name":"Youngs Chartered Surveyors",
    "wof:placetype":"venue"
},
  "geometry": {"coordinates":[-2.8895640373,56.6458892822],"type":"Point"}
}