{
  "type": "Feature",
  "properties": {
    "addr:full":"15 Winterburn Avenue Bolton Lancashire BL2 3FY",
    "addr:housenumber":"15",
    "addr:postcode":"bl2 3fy",
    "addr:street":"Winterburn Avenue",
    "iso:country":"GB",
    "sg:address":"15 Winterburn Avenue",
    "sg:city":"Bolton",
    "sg:classifiers":[
        {
            "category":"Building & Trades",
            "subcategory":"Plumbing",
            "type":"Services"
        }
    ],
    "sg:phone":"+44 1204 307399",
    "sg:postcode":"BL2 3FY",
    "sg:province":"Lancashire",
    "sg:tags":[
        "central",
        "heating"
    ],
    "wof:name":"Newave Heating",
    "wof:placetype":"venue"
},
  "geometry": {"coordinates":[-2.4107611179,53.6086540222],"type":"Point"}
}