{
  "type": "Feature",
  "properties": {
    "addr:full":"Unit 10 Cusson Road, Knowsley Industrial Park North Liverpool Lancashire L33 7BY",
    "addr:housenumber":"unit 10",
    "addr:postcode":"l33 7by",
    "addr:street":"Cusson Road;Industrial Park North",
    "iso:country":"GB",
    "sg:address":"Unit 10 Cusson Road, Knowsley Industrial Park North",
    "sg:city":"Liverpool",
    "sg:classifiers":[
        {
            "category":"Manufacturing",
            "subcategory":"Metals",
            "type":"Manufacturing & Wholesale Goods"
        },
        {
            "category":"Home & Garden",
            "subcategory":"Kitchen Supply",
            "type":"Retail Goods"
        }
    ],
    "sg:phone":"+44 151 547 3529",
    "sg:postcode":"L33 7BY",
    "sg:province":"Lancashire",
    "sg:tags":[
        "equipment",
        "work",
        "sheet",
        "catering"
    ],
    "wof:name":"Swift Sheet Metal & Fabrication Co",
    "wof:placetype":"venue"
},
  "geometry": {"coordinates":[-2.8647649288,53.476398468],"type":"Point"}
}