{
  "type": "Feature",
  "properties": {
    "addr:full":"Wixoldbury Farm, Wickwar Wotton-under-edge Gloucestershire GL12 8PE",
    "addr:postcode":"gl12 8pe",
    "iso:country":"GB",
    "sg:address":"Wixoldbury Farm, Wickwar",
    "sg:city":"Wotton-under-edge",
    "sg:classifiers":[
        {
            "category":"Farming",
            "subcategory":"Livestock Farm",
            "type":"Manufacturing & Wholesale Goods"
        }
    ],
    "sg:phone":"+44 1454 228278",
    "sg:postcode":"GL12 8PE",
    "sg:province":"Gloucestershire",
    "sg:tags":[
        "others"
    ],
    "wof:name":"E Alvis",
    "wof:placetype":"venue"
},
  "geometry": {"coordinates":[-2.399339,51.593262],"type":"Point"}
}