{
  "type": "Feature",
  "properties": {
    "addr:full":"The Boathouse, Riverside Road West, Newton Ferrers Plymouth Devon PL8 1AD",
    "addr:postcode":"pl8 1ad",
    "addr:street":"Riverside Road West;Ferrers",
    "iso:country":"GB",
    "sg:address":"The Boathouse, Riverside Road West, Newton Ferrers",
    "sg:city":"Plymouth",
    "sg:classifiers":[
        {
            "category":"Organizations",
            "subcategory":"Non-profit Organization",
            "type":"Services"
        }
    ],
    "sg:postcode":"PL8 1AD",
    "sg:province":"Devon",
    "sg:tags":[
        "organisation",
        "voluntary",
        "charity"
    ],
    "wof:name":"Royal National Lifeboat Institution",
    "wof:placetype":"venue"
},
  "geometry": {"coordinates":[-4.0379991531,50.3158302307],"type":"Point"}
}