{
  "type": "Feature",
  "properties": {
    "iso:country":"GB",
    "sg:address":"142 Ealing Rd",
    "sg:city":"Wembley",
    "sg:classifiers":[
        {
            "category":"Shopping",
            "subcategory":"Crafts & Fabrics",
            "type":"Retail Goods"
        }
    ],
    "sg:phone":"+44 20 8903 3449",
    "sg:postcode":"HA0 4PY",
    "sg:province":"Greater London",
    "sg:tags":[
        "shop"
    ],
    "wof:name":"Bhavneeta Novelties Ltd",
    "wof:placetype":"venue"
},
  "geometry": {"coordinates":[-0.297732,51.546574],"type":"Point"}
}