{
  "type": "Feature",
  "properties": {
    "addr:full":"43 The Bdwy Southall Greater London UB1 1JY",
    "addr:housenumber":"43",
    "addr:postcode":"ub1 1jy",
    "addr:street":"The Bdwy",
    "iso:country":"GB",
    "sg:address":"43 The Bdwy",
    "sg:city":"Southall",
    "sg:classifiers":[
        {
            "category":"Food & Beverages",
            "subcategory":"Bakery",
            "type":"Retail Goods"
        }
    ],
    "sg:phone":"+44 20 8574 4857",
    "sg:postcode":"UB1 1JY",
    "sg:province":"Greater London",
    "sg:tags":[
        "shop",
        "baker"
    ],
    "sg:website":"http://www.greggs.co.uk",
    "wof:name":"Greggs plc",
    "wof:placetype":"venue"
},
  "geometry": {"coordinates":[-0.3783339858,51.5113792419],"type":"Point"}
}