{
  "type": "Feature",
  "properties": {
    "addr:full":"3 Southfield Rd Waltham Cross Essex EN8 7HD",
    "addr:housenumber":"3",
    "addr:postcode":"en8 7hd",
    "addr:street":"Southfield Rd;Cross",
    "iso:country":"GB",
    "sg:address":"3 Southfield Rd",
    "sg:city":"Waltham Cross",
    "sg:classifiers":[
        {
            "category":"Building & Trades",
            "subcategory":"Cleaning & Sanitation",
            "type":"Services"
        }
    ],
    "sg:postcode":"EN8 7HD",
    "sg:province":"Essex",
    "sg:tags":[
        "commercial"
    ],
    "wof:name":"J & S Maintenance",
    "wof:placetype":"venue"
},
  "geometry": {"coordinates":[-0.030375,51.692902],"type":"Point"}
}