{
  "type": "Feature",
  "properties": {
    "iso:country":"GB",
    "sg:address":"11 Covey Way",
    "sg:city":"Alresford",
    "sg:classifiers":[
        {
            "category":"Retail",
            "subcategory":"Driving School",
            "type":"Services"
        }
    ],
    "sg:postcode":"SO24 9QN",
    "sg:province":"Hampshire",
    "wof:name":"Paul Middleton",
    "wof:placetype":"venue"
},
  "geometry": {"coordinates":[-1.174305,51.083221],"type":"Point"}
}