{
  "type": "Feature",
  "properties": {
    "addr:full":"44-50 New Market Hall, Queensgate Market Huddersfield West Yorkshire HD1 2UJ",
    "addr:housenumber":"44-50",
    "addr:postcode":"hd1 2uj",
    "addr:street":"New Market Hall Queensgate Market",
    "iso:country":"GB",
    "sg:address":"44-50 New Market Hall, Queensgate Market",
    "sg:city":"Huddersfield",
    "sg:classifiers":[
        {
            "category":"Food & Beverages",
            "subcategory":"Fruits & Vegetables",
            "type":"Retail Goods"
        }
    ],
    "sg:phone":"+44 1484 450038",
    "sg:postcode":"HD1 2UJ",
    "sg:province":"West Yorkshire",
    "sg:tags":[
        "greengrocer"
    ],
    "wof:name":"Philip Beaver",
    "wof:placetype":"venue"
},
  "geometry": {"coordinates":[-1.7832989693,53.6449165344],"type":"Point"}
}