{
  "type": "Feature",
  "properties": {
    "addr:full":"31 Leicester Road, Sharnford Hinckley Leicestershire LE10 3PP",
    "addr:housenumber":"31",
    "addr:postcode":"le10 3pp",
    "addr:street":"Leicester Road",
    "iso:country":"GB",
    "sg:address":"31 Leicester Road, Sharnford",
    "sg:city":"Hinckley",
    "sg:classifiers":[
        {
            "category":"Bars & Pubs",
            "type":"Food & Drink"
        }
    ],
    "sg:phone":"+44 1455 272384",
    "sg:postcode":"LE10 3PP",
    "sg:province":"Leicestershire",
    "sg:tags":[
        "pubs",
        "inn"
    ],
    "wof:name":"The Sharnford Arms",
    "wof:placetype":"venue"
},
  "geometry": {"coordinates":[-1.359788,52.492516],"type":"Point"}
}