{
  "type": "Feature",
  "properties": {
    "iso:country":"GB",
    "sg:address":"92 Cross Arthurlie Street, Barrhead",
    "sg:city":"Glasgow",
    "sg:classifiers":[
        {
            "category":"Building & Trades",
            "subcategory":"Construction",
            "type":"Services"
        }
    ],
    "sg:postcode":"G78 1RP",
    "sg:province":"East Ayrshire",
    "sg:tags":[
        "decorator",
        "painter"
    ],
    "wof:name":"Iain G Nicol Painting Contractor",
    "wof:placetype":"venue"
},
  "geometry": {"coordinates":[-4.397481,55.80125],"type":"Point"}
}