{
  "type": "Feature",
  "properties": {
    "iso:country":"GB",
    "sg:address":"84-86 Church Road",
    "sg:city":"Colchester",
    "sg:classifiers":[
        {
            "category":"Retail",
            "subcategory":"Auto Repair",
            "type":"Services"
        }
    ],
    "sg:phone":"+44 1206 302808",
    "sg:postcode":"CO7 0QH",
    "sg:province":"Essex",
    "sg:tags":[
        "modification",
        "garage"
    ],
    "wof:name":"R Smith",
    "wof:placetype":"venue"
},
  "geometry": {"coordinates":[1.022946,51.818069],"type":"Point"}
}