{
  "type": "Feature",
  "properties": {
    "addr:full":"Bokiddick, Lanivet Bodmin Cornwall PL30 5HP",
    "addr:postcode":"pl30 5hp",
    "addr:street":"Lanivet",
    "iso:country":"GB",
    "sg:address":"Bokiddick, Lanivet",
    "sg:city":"Bodmin",
    "sg:classifiers":[
        {
            "category":"Farming",
            "subcategory":"Dairy Farm",
            "type":"Manufacturing & Wholesale Goods"
        }
    ],
    "sg:phone":"+44 1208 831329",
    "sg:postcode":"PL30 5HP",
    "sg:province":"Cornwall",
    "wof:name":"Ivan J Phillips",
    "wof:placetype":"venue"
},
  "geometry": {"coordinates":[-4.745644,50.427639],"type":"Point"}
}