{
  "type": "Feature",
  "properties": {
    "addr:full":"Unit 6 Heathfield East Sussex TN21 8AW",
    "addr:housenumber":"unit 6",
    "addr:postcode":"tn21 8aw",
    "addr:street":"Heathfield",
    "iso:country":"GB",
    "sg:address":"Unit 6",
    "sg:city":"Heathfield",
    "sg:classifiers":[
        {
            "category":"Food & Beverages",
            "subcategory":"Supermarket",
            "type":"Retail Goods"
        }
    ],
    "sg:postcode":"TN21 8AW",
    "sg:province":"East Sussex",
    "sg:tags":[
        "frozen"
    ],
    "wof:name":"Mill Cooked Meats",
    "wof:placetype":"venue"
},
  "geometry": {"coordinates":[0.2577399909,50.9726104736],"type":"Point"}
}