{
  "type": "Feature",
  "properties": {
    "addr:full":"14 Vine Street, Hazel Gro Stockport Cheshire SK7 4JS",
    "addr:housenumber":"14",
    "addr:postcode":"sk7 4js",
    "addr:street":"Vine Street",
    "iso:country":"GB",
    "sg:address":"14 Vine Street, Hazel Gro",
    "sg:city":"Stockport",
    "sg:classifiers":[
        {
            "category":"Professional",
            "subcategory":"Detective & Security Services",
            "type":"Services"
        }
    ],
    "sg:phone":"+44 161 292 6540",
    "sg:postcode":"SK7 4JS",
    "sg:province":"Cheshire",
    "sg:tags":[
        "locksmith"
    ],
    "wof:name":"Comprehensive Locksmiths & Security Specialists",
    "wof:placetype":"venue"
},
  "geometry": {"coordinates":[-2.1211969852,53.38073349],"type":"Point"}
}