{
  "type": "Feature",
  "properties": {
    "iso:country":"GB",
    "sg:address":"Gourmet Food",
    "sg:city":"Bromsgrove",
    "sg:classifiers":[
        {
            "category":"Professional",
            "type":"Services"
        }
    ],
    "sg:postcode":"B60 3DN",
    "sg:province":"Worcestershire",
    "sg:tags":[
        "caterer"
    ],
    "wof:name":"Bon Appetit Ltd.",
    "wof:placetype":"venue"
},
  "geometry": {"coordinates":[-2.03368,52.328835],"type":"Point"}
}