{
  "type": "Feature",
  "properties": {
    "addr:full":"374-380 Holdenhurst Road Bournemouth Dorset BH8 8BJ",
    "addr:housenumber":"374-380",
    "addr:postcode":"bh8 8bj",
    "addr:street":"Holdenhurst Road",
    "iso:country":"GB",
    "sg:address":"374-380 Holdenhurst Road",
    "sg:city":"Bournemouth",
    "sg:classifiers":[
        {
            "category":"Autos & Motor Vehicles",
            "subcategory":"Automobile Sales",
            "type":"Retail Goods"
        }
    ],
    "sg:phone":"+44 1202 396342",
    "sg:postcode":"BH8 8BJ",
    "sg:province":"Dorset",
    "sg:tags":[
        "car"
    ],
    "wof:name":"Bramshaw Garage (Hampshire) Ltd.",
    "wof:placetype":"venue"
},
  "geometry": {"coordinates":[-1.85108,50.732319],"type":"Point"}
}