{
  "type": "Feature",
  "properties": {
    "addr:full":"66 Station Road Redcar North Yorkshire TS10 1DU",
    "addr:housenumber":"66",
    "addr:postcode":"ts10 1du",
    "addr:street":"Station Road",
    "iso:country":"GB",
    "sg:address":"66 Station Road",
    "sg:city":"Redcar",
    "sg:classifiers":[
        {
            "category":"Shopping",
            "subcategory":"Florist",
            "type":"Retail Goods"
        }
    ],
    "sg:phone":"+44 1642 474030",
    "sg:postcode":"TS10 1DU",
    "sg:province":"North Yorkshire",
    "wof:name":"Elaine's",
    "wof:placetype":"venue"
},
  "geometry": {"coordinates":[-1.070257,54.618053],"type":"Point"}
}