{
  "type": "Feature",
  "properties": {
    "iso:country":"GB",
    "sg:address":"25 Foryd Road, Kinmel Bay",
    "sg:city":"Rhyl",
    "sg:classifiers":[
        {
            "category":"Personal",
            "subcategory":"Beauty Salon",
            "type":"Services"
        }
    ],
    "sg:postcode":"LL18 5BA",
    "sg:province":"Conwy",
    "sg:tags":[
        "unisex",
        "hairdresser"
    ],
    "wof:name":"Gayle's Hair Studio",
    "wof:placetype":"venue"
},
  "geometry": {"coordinates":[-3.515347,53.312065],"type":"Point"}
}