{
  "type": "Feature",
  "properties": {
    "addr:full":"R N Wireless Station, Inskip Preston Lancashire PR4 0TF",
    "addr:postcode":"pr4 0tf",
    "addr:street":"R;Wireless;Inskip",
    "iso:country":"GB",
    "sg:address":"R N Wireless Station, Inskip",
    "sg:city":"Preston",
    "sg:classifiers":[
        {
            "category":"Community Center",
            "subcategory":"Youth",
            "type":"Public Place"
        }
    ],
    "sg:phone":"+44 1772 691033",
    "sg:postcode":"PR4 0TF",
    "sg:province":"Lancashire",
    "sg:tags":[
        "organisation",
        "centre"
    ],
    "wof:name":"The Sea Cadet Association",
    "wof:placetype":"venue"
},
  "geometry": {"coordinates":[-2.818501,53.834274],"type":"Point"}
}