{
  "type": "Feature",
  "properties": {
    "iso:country":"GB",
    "sg:address":"43 Stroud Green Rd",
    "sg:city":"London",
    "sg:classifiers":[
        {
            "category":"Food & Beverages",
            "subcategory":"Fruits & Vegetables",
            "type":"Retail Goods"
        }
    ],
    "sg:postcode":"N4 3EF",
    "sg:province":"Greater London",
    "sg:tags":[
        "greengrocer"
    ],
    "wof:name":"North London Emporium",
    "wof:placetype":"venue"
},
  "geometry": {"coordinates":[-0.109195,51.567558],"type":"Point"}
}