{
  "type": "Feature",
  "properties": {
    "iso:country":"GB",
    "sg:address":"9-11 Buccleuch Street",
    "sg:city":"Barrow-in-furness",
    "sg:classifiers":[
        {
            "category":"Retail",
            "subcategory":"Funeral Services",
            "type":"Services"
        }
    ],
    "sg:phone":"+44 1229 820514",
    "sg:postcode":"LA14 1SS",
    "sg:province":"Cumbria",
    "sg:tags":[
        "director",
        "cemetery",
        "crematorium"
    ],
    "wof:name":"George Hall & Son",
    "wof:placetype":"venue"
},
  "geometry": {"coordinates":[-3.2293379307,54.1139717102],"type":"Point"}
}