{
  "type": "Feature",
  "properties": {
    "iso:country":"GB",
    "sg:address":"98a Belgrave Road",
    "sg:city":"Leicester",
    "sg:classifiers":[
        {
            "category":"Shopping",
            "subcategory":"Jewelry",
            "type":"Retail Goods"
        },
        {
            "category":"Shopping",
            "subcategory":"Comic Books",
            "type":"Retail Goods"
        }
    ],
    "sg:phone":"+44 116 266 4670",
    "sg:postcode":"LE4 5AT",
    "sg:province":"Leicestershire",
    "sg:tags":[
        "jeweller",
        "sale",
        "jewellery"
    ],
    "wof:name":"Jadin Jewellers",
    "wof:placetype":"venue"
},
  "geometry": {"coordinates":[-1.1240799427,52.6480331421],"type":"Point"}
}