{
  "type": "Feature",
  "properties": {
    "addr:full":"40 St Leonards Road Bexhill-on-sea East Sussex TN40 1JB",
    "addr:housenumber":"40",
    "addr:postcode":"tn40 1jb",
    "addr:street":"St Leonards Road",
    "iso:country":"GB",
    "sg:address":"40 St Leonards Road",
    "sg:city":"Bexhill-on-sea",
    "sg:classifiers":[
        {
            "category":"Home & Garden",
            "subcategory":"Household Appliances",
            "type":"Retail Goods"
        }
    ],
    "sg:phone":"+44 1424 733200",
    "sg:postcode":"TN40 1JB",
    "sg:province":"East Sussex",
    "sg:tags":[
        "domestic",
        "centre"
    ],
    "wof:name":"C H Seymour",
    "wof:placetype":"venue"
},
  "geometry": {"coordinates":[0.4761399925,50.839630127],"type":"Point"}
}