{
  "type": "Feature",
  "properties": {
    "iso:country":"GB",
    "sg:address":"12-13 Holland Walk",
    "sg:city":"Barnstaple",
    "sg:classifiers":[
        {
            "category":"Farming",
            "subcategory":"Livestock Farm",
            "type":"Manufacturing & Wholesale Goods"
        },
        {
            "category":"Shopping",
            "subcategory":"Florist",
            "type":"Retail Goods"
        }
    ],
    "sg:postcode":"EX31 1DW",
    "sg:province":"Devon",
    "sg:tags":[
        "breeder"
    ],
    "wof:name":"James,A,",
    "wof:placetype":"venue"
},
  "geometry": {"coordinates":[-4.061822,51.080002],"type":"Point"}
}