{
  "type": "Feature",
  "properties": {
    "iso:country":"GB",
    "sg:address":"Ty Mawr Farm, Brooks",
    "sg:city":"Welshpool",
    "sg:classifiers":[
        {
            "category":"Farming",
            "subcategory":"Livestock Farm",
            "type":"Manufacturing & Wholesale Goods"
        }
    ],
    "sg:phone":"+44 1686 650346",
    "sg:postcode":"SY21 8QS",
    "sg:province":"Shropshire",
    "sg:tags":[
        "others"
    ],
    "wof:name":"D W Evans & Sons",
    "wof:placetype":"venue"
},
  "geometry": {"coordinates":[-3.268884,52.588192],"type":"Point"}
}