{
  "type": "Feature",
  "properties": {
    "iso:country":"GB",
    "sg:address":"114 Pinner Road",
    "sg:city":"Northwood",
    "sg:classifiers":[
        {
            "category":"Building & Trades",
            "subcategory":"Construction",
            "type":"Services"
        }
    ],
    "sg:phone":"+44 1923 840660",
    "sg:postcode":"HA6 1BS",
    "sg:province":"Greater London",
    "sg:tags":[
        "conversion",
        "loft"
    ],
    "wof:name":"Loft Conversion Supplies Ltd.",
    "wof:placetype":"venue"
},
  "geometry": {"coordinates":[-0.4160160124,51.6045417786],"type":"Point"}
}