{
  "type": "Feature",
  "properties": {
    "addr:full":"Unit 4, Woodways Benskins Lane, Noak Hill Romford Essex RM4 1LB",
    "addr:housenumber":"unit 4",
    "addr:postcode":"rm4 1lb",
    "addr:street":"Benskins Lane Noak Hill",
    "iso:country":"GB",
    "sg:address":"Unit 4, Woodways Benskins Lane, Noak Hill",
    "sg:city":"Romford",
    "sg:classifiers":[
        {
            "category":"Professional",
            "subcategory":"Printing & Photocopies",
            "type":"Services"
        }
    ],
    "sg:phone":"+44 1708 384808",
    "sg:postcode":"RM4 1LB",
    "sg:province":"Essex",
    "sg:tags":[
        "typesetter"
    ],
    "wof:name":"Page Graphics",
    "wof:placetype":"venue"
},
  "geometry": {"coordinates":[0.225598,51.622402],"type":"Point"}
}