{
  "type": "Feature",
  "properties": {
    "iso:country":"GB",
    "sg:address":"Spalding House 90 Queen Street, Broughty Ferry",
    "sg:city":"Dundee",
    "sg:classifiers":[
        {
            "category":"Manufacturing",
            "subcategory":"Textiles",
            "type":"Manufacturing & Wholesale Goods"
        }
    ],
    "sg:phone":"+44 1307 464259",
    "sg:postcode":"DD5 1AJ",
    "sg:province":"Angus",
    "sg:tags":[
        "made-up"
    ],
    "wof:name":"Forfar Weavers Ltd.",
    "wof:placetype":"venue"
},
  "geometry": {"coordinates":[-2.878899,56.468922],"type":"Point"}
}