{
  "type": "Feature",
  "properties": {
    "addr:full":"23 Babington La Derby Derbyshire DE1 1TE",
    "addr:housenumber":"23",
    "addr:postcode":"de1 1te",
    "addr:street":"Babington La Derby",
    "iso:country":"GB",
    "sg:address":"23 Babington La",
    "sg:city":"Derby",
    "sg:classifiers":[
        {
            "category":"Autos & Motor Vehicles",
            "subcategory":"Auto Supplies",
            "type":"Retail Goods"
        },
        {
            "category":"Retail",
            "subcategory":"Auto Repair",
            "type":"Services"
        }
    ],
    "sg:phone":"+44 1332 344226",
    "sg:postcode":"DE1 1TE",
    "sg:province":"Derbyshire",
    "sg:tags":[
        "rubber",
        "car",
        "specialist",
        "tyre",
        "customizing"
    ],
    "wof:name":"Independent Tyres Ltd",
    "wof:placetype":"venue"
},
  "geometry": {"coordinates":[-1.4767589569,52.9189796448],"type":"Point"}
}