{
  "type": "Feature",
  "properties": {
    "iso:country":"GB",
    "sg:address":"Vale St",
    "sg:city":"Dudley",
    "sg:classifiers":[
        {
            "category":"Community Center",
            "type":"Public Place"
        }
    ],
    "sg:phone":"+44 1902 662003",
    "sg:postcode":"DY3 3XD",
    "sg:province":"Staffordshire",
    "sg:tags":[
        "recreation",
        "leisure",
        "centre"
    ],
    "wof:name":"Upper Gornal Voluntary Recreation Centre",
    "wof:placetype":"venue"
},
  "geometry": {"coordinates":[-2.120949,52.530602],"type":"Point"}
}