{
  "type": "Feature",
  "properties": {
    "iso:country":"GB",
    "sg:address":"222 Hardgate",
    "sg:city":"Aberdeen",
    "sg:classifiers":[
        {
            "category":"Building & Trades",
            "subcategory":"Plumbing",
            "type":"Services"
        }
    ],
    "sg:phone":"+44 1224 210000",
    "sg:postcode":"AB10 6AA",
    "sg:province":"Aberdeen City",
    "sg:tags":[
        "plumber",
        "heating"
    ],
    "wof:name":"CECIL A S DUNCAN",
    "wof:placetype":"venue"
},
  "geometry": {"coordinates":[-2.1140460968,57.1360092163],"type":"Point"}
}