{
  "type": "Feature",
  "properties": {
    "addr:full":"Palmers Lane, Chrishall Royston Bedfordshire SG8 8QW",
    "addr:postcode":"sg8 8qw",
    "addr:street":"Palmers Lane",
    "iso:country":"GB",
    "sg:address":"Palmers Lane, Chrishall",
    "sg:city":"Royston",
    "sg:classifiers":[
        {
            "category":"Education",
            "subcategory":"School",
            "type":"Public Place"
        }
    ],
    "sg:phone":"+44 1763 838592",
    "sg:postcode":"SG8 8QW",
    "sg:province":"Bedfordshire",
    "sg:tags":[
        "local",
        "authority"
    ],
    "wof:name":"Chrishall C of E Primary School",
    "wof:placetype":"venue"
},
  "geometry": {"coordinates":[0.1090840027,52.0293121338],"type":"Point"}
}