{
  "type": "Feature",
  "properties": {
    "addr:full":"278 High Road, Willesden London Greater London NW10 2EY",
    "addr:housenumber":"278",
    "addr:postcode":"nw10 2ey",
    "addr:street":"High Road",
    "iso:country":"GB",
    "sg:address":"278 High Road, Willesden",
    "sg:city":"London",
    "sg:classifiers":[
        {
            "category":"Shopping",
            "subcategory":"Shoes",
            "type":"Retail Goods"
        }
    ],
    "sg:postcode":"NW10 2EY",
    "sg:province":"Greater London",
    "wof:name":"Widefit Shoes",
    "wof:placetype":"venue"
},
  "geometry": {"coordinates":[-0.2386,51.548817],"type":"Point"}
}