{
  "type": "Feature",
  "properties": {
    "iso:country":"GB",
    "sg:address":"West Wing, Dukes House, Fellside",
    "sg:city":"Hexham",
    "sg:classifiers":[
        {
            "category":"Communications",
            "subcategory":"Film & Video Production",
            "type":"Services"
        }
    ],
    "sg:postcode":"NE46 1RQ",
    "sg:province":"Northumberland",
    "sg:tags":[
        "illustrator",
        "artist"
    ],
    "wof:name":"Phil Anderton Cartoonist",
    "wof:placetype":"venue"
},
  "geometry": {"coordinates":[-2.092081,54.964867],"type":"Point"}
}