{
  "type": "Feature",
  "properties": {
    "addr:full":"17 Bridge Street Hereford Herefordshire HR4 9DF",
    "addr:housenumber":"17",
    "addr:postcode":"hr4 9df",
    "addr:street":"Bridge Street",
    "iso:country":"GB",
    "sg:address":"17 Bridge Street",
    "sg:city":"Hereford",
    "sg:classifiers":[
        {
            "category":"Fast Food",
            "type":"Food & Drink"
        }
    ],
    "sg:phone":"+44 1432 352817",
    "sg:postcode":"HR4 9DF",
    "sg:province":"Herefordshire",
    "sg:tags":[
        "away",
        "take"
    ],
    "wof:name":"Dilshad",
    "wof:placetype":"venue"
},
  "geometry": {"coordinates":[-2.71861,52.053516],"type":"Point"}
}