{
  "type": "Feature",
  "properties": {
    "addr:full":"25 Inglestone Road, Wickwar Wotton-under-edge Gloucestershire GL12 8NH",
    "addr:housenumber":"25",
    "addr:postcode":"gl12 8nh",
    "addr:street":"Inglestone Road",
    "iso:country":"GB",
    "sg:address":"25 Inglestone Road, Wickwar",
    "sg:city":"Wotton-under-edge",
    "sg:classifiers":[
        {
            "category":"Professional",
            "subcategory":"Detective & Security Services",
            "type":"Services"
        }
    ],
    "sg:postcode":"GL12 8NH",
    "sg:province":"Gloucestershire",
    "sg:tags":[
        "equipment",
        "installers"
    ],
    "wof:name":"Magpie Security & Communications",
    "wof:placetype":"venue"
},
  "geometry": {"coordinates":[-2.3972649574,51.5938491821],"type":"Point"}
}