{
  "type": "Feature",
  "properties": {
    "addr:full":"Crossways, Welsh Road Chester Cheshire CH4 9LN",
    "addr:postcode":"ch4 9ln",
    "addr:street":"Welsh Road",
    "iso:country":"GB",
    "sg:address":"Crossways, Welsh Road",
    "sg:city":"Chester",
    "sg:classifiers":[
        {
            "category":"Building & Trades",
            "subcategory":"Construction",
            "type":"Services"
        }
    ],
    "sg:phone":"+44 1244 661315",
    "sg:postcode":"CH4 9LN",
    "sg:province":"Cheshire",
    "sg:tags":[
        "joiner",
        "carpenter"
    ],
    "wof:name":"R A Gittens",
    "wof:placetype":"venue"
},
  "geometry": {"coordinates":[-2.907134,53.162411],"type":"Point"}
}