{
  "type": "Feature",
  "properties": {
    "addr:full":"Baird Avenue, Dryburgh Industrial Estate Dunde Dundee Dundee City DD2 3TW",
    "addr:postcode":"dd2 3tw",
    "addr:street":"Baird Avenue Dryburgh Industrial Estate",
    "iso:country":"GB",
    "sg:address":"Baird Avenue, Dryburgh Industrial Estate Dunde",
    "sg:city":"Dundee",
    "sg:classifiers":[
        {
            "category":"Building & Trades",
            "subcategory":"Construction",
            "type":"Services"
        }
    ],
    "sg:phone":"+44 1382 812777",
    "sg:postcode":"DD2 3TW",
    "sg:province":"Dundee City",
    "sg:tags":[
        "joinery"
    ],
    "wof:name":"Magnet",
    "wof:placetype":"venue"
},
  "geometry": {"coordinates":[-3.014770031,56.4832992554],"type":"Point"}
}