{
  "type": "Feature",
  "properties": {
    "addr:full":"Beck Farm, Cundall York North Yorkshire YO61 2RN",
    "addr:postcode":"yo61 2rn",
    "iso:country":"GB",
    "sg:address":"Beck Farm, Cundall",
    "sg:city":"York",
    "sg:classifiers":[
        {
            "category":"Farming",
            "subcategory":"Farm",
            "type":"Manufacturing & Wholesale Goods"
        }
    ],
    "sg:postcode":"YO61 2RN",
    "sg:province":"North Yorkshire",
    "sg:tags":[
        "mixed",
        "crop"
    ],
    "wof:name":"J T Swiers",
    "wof:placetype":"venue"
},
  "geometry": {"coordinates":[-1.353029,54.14827],"type":"Point"}
}