{
  "type": "Feature",
  "properties": {
    "addr:full":"3 Peel Avenue, Hale Altrincham Cheshire WA14 2UG",
    "addr:housenumber":"3",
    "addr:postcode":"wa14 2ug",
    "addr:street":"Peel Avenue",
    "iso:country":"GB",
    "sg:address":"3 Peel Avenue, Hale",
    "sg:city":"Altrincham",
    "sg:classifiers":[
        {
            "category":"Banks & Credit Unions",
            "subcategory":"Financial Services",
            "type":"Services"
        }
    ],
    "sg:postcode":"WA14 2UG",
    "sg:province":"Cheshire",
    "sg:tags":[
        "consultant"
    ],
    "wof:name":"Arena Financial Services Ltd.",
    "wof:placetype":"venue"
},
  "geometry": {"coordinates":[-2.3504559994,53.3782958984],"type":"Point"}
}