{
  "type": "Feature",
  "properties": {
    "addr:full":"105 Piccadilly London Greater London W1J 7NJ",
    "addr:housenumber":"105",
    "addr:postcode":"w1j 7nj",
    "addr:street":"Piccadilly",
    "iso:country":"GB",
    "sg:address":"105 Piccadilly",
    "sg:city":"London",
    "sg:classifiers":[
        {
            "category":"Banks & Credit Unions",
            "subcategory":"Bank",
            "type":"Services"
        }
    ],
    "sg:postcode":"W1J 7NJ",
    "sg:province":"Greater London",
    "wof:name":"B C Partners Ltd.",
    "wof:placetype":"venue"
},
  "geometry": {"coordinates":[-0.1465220004,51.5049667358],"type":"Point"}
}