{
  "type": "Feature",
  "properties": {
    "iso:country":"GB",
    "sg:address":"9 Keld Avenue",
    "sg:city":"Uckfield",
    "sg:classifiers":[
        {
            "category":"Building & Trades",
            "subcategory":"Plumbing",
            "type":"Services"
        },
        {
            "category":"Building & Trades",
            "subcategory":"Construction",
            "type":"Services"
        }
    ],
    "sg:phone":"+44 1825 761151",
    "sg:postcode":"TN22 5BN",
    "sg:province":"East Sussex",
    "sg:tags":[
        "central",
        "installation",
        "system",
        "servicing",
        "heating"
    ],
    "wof:name":"Ian Poole",
    "wof:placetype":"venue"
},
  "geometry": {"coordinates":[0.102337,50.967789],"type":"Point"}
}