{
  "type": "Feature",
  "properties": {
    "addr:full":"10 Gloucester Place Edinburgh City of Edinburgh EH3 6EF",
    "addr:housenumber":"10",
    "addr:postcode":"eh3 6ef",
    "addr:street":"Gloucester Place Edinburgh",
    "iso:country":"GB",
    "sg:address":"10 Gloucester Place",
    "sg:city":"Edinburgh",
    "sg:classifiers":[
        {
            "category":"Organizations",
            "subcategory":"Membership Organization",
            "type":"Services"
        }
    ],
    "sg:postcode":"EH3 6EF",
    "sg:province":"City of Edinburgh",
    "sg:tags":[
        "club"
    ],
    "wof:name":"Scottish Breast Cancer Campaign",
    "wof:placetype":"venue"
},
  "geometry": {"coordinates":[-3.2071399689,55.9566688538],"type":"Point"}
}