{
  "type": "Feature",
  "properties": {
    "addr:full":"Turkey Shore Road Holyhead Isle of Anglesey LL65 2DE",
    "addr:postcode":"ll65 2de",
    "addr:street":"Turkey Shore Road",
    "iso:country":"GB",
    "sg:address":"Turkey Shore Road",
    "sg:city":"Holyhead",
    "sg:classifiers":[
        {
            "category":"Wholesale",
            "subcategory":"Construction Materials",
            "type":"Manufacturing & Wholesale Goods"
        },
        {
            "category":"Home & Garden",
            "subcategory":"Building Materials",
            "type":"Retail Goods"
        }
    ],
    "sg:phone":"+44 1407 760578",
    "sg:postcode":"LL65 2DE",
    "sg:province":"Isle of Anglesey",
    "sg:tags":[
        "ready",
        "mixed",
        "mortar",
        "concrete"
    ],
    "wof:name":"Ready Mixed Concrete (Wales) Ltd",
    "wof:placetype":"venue"
},
  "geometry": {"coordinates":[-4.627699,53.308361],"type":"Point"}
}