{
  "type": "Feature",
  "properties": {
    "addr:full":"The Works Birmingham West Midlands B1 3AG",
    "addr:postcode":"b1 3ag",
    "iso:country":"GB",
    "sg:address":"The Works",
    "sg:city":"Birmingham",
    "sg:classifiers":[
        {
            "category":"Shopping",
            "subcategory":"Computers & Home Electronics",
            "type":"Retail Goods"
        }
    ],
    "sg:phone":"+44 121 684 4114",
    "sg:postcode":"B1 3AG",
    "sg:province":"West Midlands",
    "sg:tags":[
        "equipment",
        "audio-visual"
    ],
    "wof:name":"Gearhouse Video Sales Ltd.",
    "wof:placetype":"venue"
},
  "geometry": {"coordinates":[-1.9147490263,52.4851303101],"type":"Point"}
}