{
  "type": "Feature",
  "properties": {
    "addr:full":"Loanside Cottage Inverurie Aberdeenshire AB51 5ER",
    "addr:postcode":"ab51 5er",
    "addr:street":"Inverurie",
    "iso:country":"GB",
    "sg:address":"Loanside Cottage",
    "sg:city":"Inverurie",
    "sg:classifiers":[
        {
            "category":"Home & Garden",
            "subcategory":"Hardware",
            "type":"Retail Goods"
        }
    ],
    "sg:phone":"+44 1467 681496",
    "sg:postcode":"AB51 5ER",
    "sg:province":"Aberdeenshire",
    "sg:tags":[
        "equipment",
        "wire",
        "cable"
    ],
    "wof:name":"Fibron Scotland",
    "wof:placetype":"venue"
},
  "geometry": {"coordinates":[-2.389794,57.291119],"type":"Point"}
}