{
  "type": "Feature",
  "properties": {
    "iso:country":"GB",
    "sg:address":"32 West St, Abbotsbury",
    "sg:city":"Weymouth",
    "sg:classifiers":[
        {
            "category":"Utilities",
            "type":"Services"
        }
    ],
    "sg:phone":"+44 1305 871181",
    "sg:postcode":"DT3 4JT",
    "sg:province":"Dorset",
    "sg:tags":[
        "internet"
    ],
    "wof:name":"Teqnet Internet Ltd",
    "wof:placetype":"venue"
},
  "geometry": {"coordinates":[-2.605414,50.666378],"type":"Point"}
}