{
  "type": "Feature",
  "properties": {
    "addr:full":"20 Oak Avenue Uxbridge Greater London UB10 8LP",
    "addr:housenumber":"20",
    "addr:postcode":"ub10 8lp",
    "addr:street":"Oak Avenue",
    "iso:country":"GB",
    "sg:address":"20 Oak Avenue",
    "sg:city":"Uxbridge",
    "sg:classifiers":[
        {
            "category":"Building & Trades",
            "subcategory":"Equipment Rental",
            "type":"Services"
        }
    ],
    "sg:phone":"+44 1895 639042",
    "sg:postcode":"UB10 8LP",
    "sg:province":"Greater London",
    "sg:tags":[
        "plant",
        "machinery"
    ],
    "wof:name":"Handley Sweepers",
    "wof:placetype":"venue"
},
  "geometry": {"coordinates":[-0.4432449937,51.5684165955],"type":"Point"}
}