{
  "type": "Feature",
  "properties": {
    "iso:country":"GB",
    "sg:address":"Phoenix House, High Spen Industrial Estate",
    "sg:city":"Rowlands Gill",
    "sg:classifiers":[
        {
            "category":"Manufacturing",
            "subcategory":"Petroleum Products",
            "type":"Manufacturing & Wholesale Goods"
        }
    ],
    "sg:postcode":"NE39 2EH",
    "sg:province":"Durham",
    "sg:tags":[
        "double",
        "glazing"
    ],
    "wof:name":"A1 Trade Windows Ltd",
    "wof:placetype":"venue"
},
  "geometry": {"coordinates":[-1.783992,54.92971],"type":"Point"}
}