{
  "type": "Feature",
  "properties": {
    "addr:full":"Peterson & Co, Nantyr Onnen House  Catsash Road Newport Monmouthshire NP18 2LZ",
    "addr:postcode":"np18 2lz",
    "addr:street":"Nantyr;Catsash Road",
    "iso:country":"GB",
    "sg:address":"Peterson & Co, Nantyr Onnen House  Catsash Road",
    "sg:city":"Newport",
    "sg:classifiers":[
        {
            "category":"Professional",
            "subcategory":"Management & Consulting",
            "type":"Services"
        }
    ],
    "sg:postcode":"NP18 2LZ",
    "sg:province":"Monmouthshire",
    "sg:tags":[
        "environmental",
        "consultant"
    ],
    "wof:name":"Bha Consulting Ltd",
    "wof:placetype":"venue"
},
  "geometry": {"coordinates":[-2.91098,51.605049],"type":"Point"}
}