{
  "type": "Feature",
  "properties": {
    "addr:full":"Old Hall, St Peters Churchyard Derby Derbyshire DE1 1NN",
    "addr:postcode":"de1 1nn",
    "addr:street":"Old Hall St Peters",
    "iso:country":"GB",
    "sg:address":"Old Hall, St Peters Churchyard",
    "sg:city":"Derby",
    "sg:classifiers":[
        {
            "category":"Shopping",
            "subcategory":"Computers & Home Electronics",
            "type":"Retail Goods"
        }
    ],
    "sg:phone":"+44 1332 202092",
    "sg:postcode":"DE1 1NN",
    "sg:province":"Derbyshire",
    "sg:tags":[
        "tape",
        "video"
    ],
    "wof:name":"The Video Corporation Ltd.",
    "wof:placetype":"venue"
},
  "geometry": {"coordinates":[-1.477984,52.920292],"type":"Point"}
}