{
  "type": "Feature",
  "properties": {
    "iso:country":"GB",
    "sg:address":"32 North Junction Street",
    "sg:city":"Edinburgh",
    "sg:classifiers":[
        {
            "category":"Bars & Pubs",
            "type":"Food & Drink"
        },
        {
            "category":"Food & Beverages",
            "subcategory":"Liquor & Beverages",
            "type":"Retail Goods"
        }
    ],
    "sg:phone":"+44 131 467 7717",
    "sg:postcode":"EH6 6HP",
    "sg:province":"City of Edinburgh",
    "sg:tags":[
        "pubs",
        "beer",
        "wine",
        "inn",
        "spirit"
    ],
    "wof:name":"Swanney's Bar",
    "wof:placetype":"venue"
},
  "geometry": {"coordinates":[-3.179346,55.976551],"type":"Point"}
}