{
  "type": "Feature",
  "properties": {
    "iso:country":"GB",
    "sg:address":"13 Eastwood Road",
    "sg:city":"Rayleigh",
    "sg:classifiers":[
        {
            "category":"Home & Garden",
            "subcategory":"Carpets & Floor Coverings",
            "type":"Retail Goods"
        }
    ],
    "sg:phone":"+44 1268 773801",
    "sg:postcode":"SS6 7JD",
    "sg:province":"Essex",
    "sg:tags":[
        "carpets",
        "rug",
        "matting"
    ],
    "wof:name":"Emerson & Massing Ltd.",
    "wof:placetype":"venue"
},
  "geometry": {"coordinates":[0.605856,51.585003],"type":"Point"}
}