{
  "type": "Feature",
  "properties": {
    "addr:full":"Clifton Road, Henlow Hitchin Bedfordshire SG16 6BD",
    "addr:postcode":"sg16 6bd",
    "addr:street":"Clifton Road",
    "iso:country":"GB",
    "sg:address":"Clifton Road, Henlow",
    "sg:city":"Hitchin",
    "sg:classifiers":[
        {
            "category":"Building & Trades",
            "subcategory":"Construction",
            "type":"Services"
        }
    ],
    "sg:phone":"+44 1462 850992",
    "sg:postcode":"SG16 6BD",
    "sg:province":"Bedfordshire",
    "sg:tags":[
        "builder"
    ],
    "wof:name":"Linxcroft Construction Ltd.",
    "wof:placetype":"venue"
},
  "geometry": {"coordinates":[-0.291684,52.029964],"type":"Point"}
}