{
  "type": "Feature",
  "properties": {
    "addr:full":"2 Goodley Hill, Pensham Pershore Worcestershire WR10 3HE",
    "addr:housenumber":"2",
    "addr:postcode":"wr10 3he",
    "addr:street":"Goodley Hill Pensham",
    "iso:country":"GB",
    "sg:address":"2 Goodley Hill, Pensham",
    "sg:city":"Pershore",
    "sg:classifiers":[
        {
            "category":"Education",
            "subcategory":"Music School",
            "type":"Public Place"
        }
    ],
    "sg:phone":"+44 1386 554759",
    "sg:postcode":"WR10 3HE",
    "sg:province":"Worcestershire",
    "sg:tags":[
        "conservatory"
    ],
    "wof:name":"Valtone Woodcraft",
    "wof:placetype":"venue"
},
  "geometry": {"coordinates":[-2.0764489174,52.0981445312],"type":"Point"}
}