{
  "type": "Feature",
  "properties": {
    "iso:country":"GB",
    "sg:address":"The Firs, Headington Hill",
    "sg:city":"Oxford",
    "sg:classifiers":[
        {
            "category":"Wholesale",
            "subcategory":"Books, Periodicals, & Newspapers",
            "type":"Manufacturing & Wholesale Goods"
        }
    ],
    "sg:phone":"+44 1865 742211",
    "sg:postcode":"OX3 0BT",
    "sg:province":"Oxfordshire",
    "sg:tags":[
        "publishing"
    ],
    "wof:name":"Atlas Publishing & Marketing Co",
    "wof:placetype":"venue"
},
  "geometry": {"coordinates":[-1.226609,51.75526],"type":"Point"}
}