{
  "type": "Feature",
  "properties": {
    "addr:full":"Pera Innovation Park, Nottingham Road Melton Mowbray Leicestershire LE13 0PB",
    "addr:postcode":"le13 0pb",
    "addr:street":"Park Nottingham Road",
    "iso:country":"GB",
    "sg:address":"Pera Innovation Park, Nottingham Road",
    "sg:city":"Melton Mowbray",
    "sg:classifiers":[
        {
            "category":"Professional",
            "subcategory":"Engineering",
            "type":"Services"
        }
    ],
    "sg:phone":"+44 1664 501501",
    "sg:postcode":"LE13 0PB",
    "sg:province":"Leicestershire",
    "sg:tags":[
        "consulting",
        "engineer"
    ],
    "wof:name":"Pera Innovation Ltd.",
    "wof:placetype":"venue"
},
  "geometry": {"coordinates":[-0.8895549774,52.7658691406],"type":"Point"}
}