{
  "type": "Feature",
  "properties": {
    "iso:country":"GB",
    "sg:address":"St Kew Highway, Wadebridge",
    "sg:city":"Bodmin",
    "sg:classifiers":[
        {
            "category":"Travel",
            "subcategory":"Hotels & Motels",
            "type":"Entertainment"
        }
    ],
    "sg:postcode":"PL30 3EQ",
    "sg:province":"Cornwall",
    "sg:tags":[
        "house",
        "guest"
    ],
    "wof:name":"Hendra Country House",
    "wof:placetype":"venue"
},
  "geometry": {"coordinates":[-4.79402,50.54303],"type":"Point"}
}