{
  "type": "Feature",
  "properties": {
    "iso:country":"GB",
    "sg:address":"Old Market Surgery, Penpitch Hill, St Clears",
    "sg:city":"Carmarthen",
    "sg:classifiers":[
        {
            "category":"Retail",
            "subcategory":"Veterinary Services",
            "type":"Services"
        }
    ],
    "sg:phone":"+44 1994 230451",
    "sg:postcode":"SA33 4DY",
    "sg:province":"Carmarthenshire",
    "sg:tags":[
        "surgeon"
    ],
    "wof:name":"Michell & Morgan",
    "wof:placetype":"venue"
},
  "geometry": {"coordinates":[-4.4979100227,51.8170585632],"type":"Point"}
}