{
  "type": "Feature",
  "properties": {
    "addr:full":"Metropolis House, 22 Percy Street London Greater London W1T 2BU",
    "addr:housenumber":"22",
    "addr:postcode":"w1t 2bu",
    "addr:street":"Percy Street",
    "iso:country":"GB",
    "sg:address":"Metropolis House, 22 Percy Street",
    "sg:city":"London",
    "sg:classifiers":[
        {
            "category":"Professional",
            "subcategory":"Management & Consulting",
            "type":"Services"
        }
    ],
    "sg:postcode":"W1T 2BU",
    "sg:province":"Greater London",
    "sg:tags":[
        "consultant",
        "business"
    ],
    "wof:name":"O S I Group Ltd.",
    "wof:placetype":"venue"
},
  "geometry": {"coordinates":[-0.132869,51.51873],"type":"Point"}
}