{
  "type": "Feature",
  "properties": {
    "addr:full":"Hodgson Centre, Hodgson Av Peterborough Cambridgeshire PE4 5EG",
    "addr:postcode":"pe4 5eg",
    "addr:street":"Hodgson Av Peterborough",
    "iso:country":"GB",
    "sg:address":"Hodgson Centre, Hodgson Av",
    "sg:city":"Peterborough",
    "sg:classifiers":[
        {
            "category":"Food & Beverages",
            "subcategory":"Groceries & Convenience Stores",
            "type":"Retail Goods"
        }
    ],
    "sg:phone":"+44 1733 328818",
    "sg:postcode":"PE4 5EG",
    "sg:province":"Cambridgeshire",
    "wof:name":"Dillions",
    "wof:placetype":"venue"
},
  "geometry": {"coordinates":[-0.279894,52.628101],"type":"Point"}
}