{
  "type": "Feature",
  "properties": {
    "iso:country":"GB",
    "sg:address":"1 Police Station Road",
    "sg:city":"Lowestoft",
    "sg:classifiers":[
        {
            "category":"Government",
            "subcategory":"Office",
            "type":"Public Place"
        }
    ],
    "sg:phone":"+44 1502 501800",
    "sg:postcode":"NR32 1NY",
    "sg:province":"Suffolk",
    "sg:tags":[
        "central"
    ],
    "wof:name":"The Probation Service",
    "wof:placetype":"venue"
},
  "geometry": {"coordinates":[1.753383,52.478157],"type":"Point"}
}