{
  "type": "Feature",
  "properties": {
    "addr:full":"284 Brighton Road South Croydon Surrey CR2 6AG",
    "addr:housenumber":"284",
    "addr:postcode":"cr2 6ag",
    "addr:street":"Brighton Road",
    "iso:country":"GB",
    "sg:address":"284 Brighton Road",
    "sg:city":"South Croydon",
    "sg:classifiers":[
        {
            "category":"Food & Beverages",
            "subcategory":"Meat & Fish",
            "type":"Retail Goods"
        },
        {
            "category":"Food & Beverages",
            "subcategory":"Groceries & Convenience Stores",
            "type":"Retail Goods"
        }
    ],
    "sg:postcode":"CR2 6AG",
    "sg:province":"Surrey",
    "sg:tags":[
        "shop",
        "chip"
    ],
    "wof:name":"SAVVIDES FISH BAR",
    "wof:placetype":"venue"
},
  "geometry": {"coordinates":[-0.0985200033,51.3525810242],"type":"Point"}
}