{
  "type": "Feature",
  "properties": {
    "addr:full":"41 Broadweir Bristol City of Bristol BS1 3AY",
    "addr:housenumber":"41",
    "addr:postcode":"bs1 3ay",
    "addr:street":"Broadweir",
    "iso:country":"GB",
    "sg:address":"41 Broadweir",
    "sg:city":"Bristol",
    "sg:classifiers":[
        {
            "category":"Shopping",
            "subcategory":"News",
            "type":"Retail Goods"
        }
    ],
    "sg:phone":"+44 117 949 6630",
    "sg:postcode":"BS1 3AY",
    "sg:province":"City of Bristol",
    "sg:tags":[
        "newsagent"
    ],
    "wof:name":"Beco News Ltd.",
    "wof:placetype":"venue"
},
  "geometry": {"coordinates":[-2.5868599415,51.4567985535],"type":"Point"}
}