{
  "type": "Feature",
  "properties": {
    "iso:country":"GB",
    "sg:address":"1 New Road, Appleby Magna",
    "sg:city":"Swadlincote",
    "sg:classifiers":[
        {
            "category":"Farming",
            "subcategory":"Livestock Farm",
            "type":"Manufacturing & Wholesale Goods"
        }
    ],
    "sg:postcode":"DE12 7AW",
    "sg:province":"Derbyshire",
    "sg:tags":[
        "others"
    ],
    "wof:name":"C A Masie & Sons",
    "wof:placetype":"venue"
},
  "geometry": {"coordinates":[-1.5437330008,52.6779060364],"type":"Point"}
}