{
  "type": "Feature",
  "properties": {
    "iso:country":"GB",
    "sg:address":"3a Church Street",
    "sg:city":"St Helens",
    "sg:classifiers":[
        {
            "category":"Education",
            "subcategory":"Special Training",
            "type":"Public Place"
        }
    ],
    "sg:phone":"+44 1744 24062",
    "sg:postcode":"WA10 1BA",
    "sg:province":"Merseyside",
    "sg:tags":[
        "product",
        "centre"
    ],
    "wof:name":"Lite Ltd.",
    "wof:placetype":"venue"
},
  "geometry": {"coordinates":[-2.736299,53.45229],"type":"Point"}
}