{
  "type": "Feature",
  "properties": {
    "addr:full":"58 Canford Cliffs Road Poole Dorset BH13 7AA",
    "addr:housenumber":"58",
    "addr:postcode":"bh13 7aa",
    "addr:street":"Canford Cliffs Road",
    "iso:country":"GB",
    "sg:address":"58 Canford Cliffs Road",
    "sg:city":"Poole",
    "sg:classifiers":[
        {
            "category":"Health Services",
            "subcategory":"Dentist",
            "type":"Services"
        }
    ],
    "sg:phone":"+44 1202 747552",
    "sg:postcode":"BH13 7AA",
    "sg:province":"Dorset",
    "wof:name":"A G Tetlow",
    "wof:placetype":"venue"
},
  "geometry": {"coordinates":[-1.925614,50.720013],"type":"Point"}
}