{
  "type": "Feature",
  "properties": {
    "addr:full":"Young Persons Housing & Advice, 4 Princes St Huntingdon Cambridgeshire PE18 6PA",
    "addr:housenumber":"young persons;4",
    "addr:postcode":"pe18 6pa",
    "addr:street":"Princes St",
    "iso:country":"GB",
    "sg:address":"Young Persons Housing & Advice, 4 Princes St",
    "sg:city":"Huntingdon",
    "sg:classifiers":[
        {
            "category":"Government",
            "subcategory":"Office",
            "type":"Public Place"
        }
    ],
    "sg:phone":"+44 1480 388590",
    "sg:postcode":"PE18 6PA",
    "sg:province":"Cambridgeshire",
    "sg:tags":[
        "local"
    ],
    "wof:name":"Huntingdonshire District Council",
    "wof:placetype":"venue"
},
  "geometry": {"coordinates":[-0.18379,52.329216],"type":"Point"}
}