{
  "type": "Feature",
  "properties": {
    "iso:country":"GB",
    "sg:address":"11 Brentford Road",
    "sg:city":"Birmingham",
    "sg:classifiers":[
        {
            "category":"Professional",
            "subcategory":"Printing & Photocopies",
            "type":"Services"
        }
    ],
    "sg:postcode":"B14 4DQ",
    "sg:province":"West Midlands",
    "sg:tags":[
        "t-shirt"
    ],
    "wof:name":"Studio 726 Ltd.",
    "wof:placetype":"venue"
},
  "geometry": {"coordinates":[-1.884313941,52.4214782715],"type":"Point"}
}