{
  "type": "Feature",
  "properties": {
    "iso:country":"GB",
    "sg:address":", Tottenham",
    "sg:city":"Tottenham",
    "sg:classifiers":[
        {
            "category":"Professional",
            "subcategory":"Detective & Security Services",
            "type":"Services"
        }
    ],
    "sg:phone":"+44 20 8880 4300",
    "sg:postcode":"N17 9LN",
    "sg:province":"Greater London",
    "sg:tags":[
        "equipment",
        "installers"
    ],
    "wof:name":"Shorrock Security",
    "wof:placetype":"venue"
},
  "geometry": {"coordinates":[-0.0601300001,51.5917892456],"type":"Point"}
}