{
  "type": "Feature",
  "properties": {
    "iso:country":"GB",
    "sg:address":"C/o Leeds College Of Building, North Street",
    "sg:city":"Leeds",
    "sg:classifiers":[
        {
            "category":"Education",
            "subcategory":"School",
            "type":"Public Place"
        }
    ],
    "sg:phone":"+44 113 234 3598",
    "sg:postcode":"LS2 7QT",
    "sg:province":"West Yorkshire",
    "sg:tags":[
        "local",
        "authority"
    ],
    "wof:name":"Nilta Ltd.",
    "wof:placetype":"venue"
},
  "geometry": {"coordinates":[-1.53522,53.80294],"type":"Point"}
}