{
  "type": "Feature",
  "properties": {
    "iso:country":"GB",
    "sg:address":"190-192 Goldhawk Rd",
    "sg:city":"London",
    "sg:classifiers":[
        {
            "category":"Building & Trades",
            "subcategory":"Construction",
            "type":"Services"
        }
    ],
    "sg:phone":"+44 20 8743 4406",
    "sg:postcode":"W12 9NS",
    "sg:province":"Greater London",
    "sg:tags":[
        "equipment"
    ],
    "wof:name":"Grayston White & Sparrow Ltd",
    "wof:placetype":"venue"
},
  "geometry": {"coordinates":[-0.234392,51.500767],"type":"Point"}
}