{
  "type": "Feature",
  "properties": {
    "addr:full":"Unit 6, Cromwell Road Grimsby Lincolnshire DN31 2BN",
    "addr:housenumber":"unit 6",
    "addr:postcode":"dn31 2bn",
    "addr:street":"Cromwell Road",
    "iso:country":"GB",
    "sg:address":"Unit 6, Cromwell Road",
    "sg:city":"Grimsby",
    "sg:classifiers":[
        {
            "category":"Manufacturing",
            "subcategory":"Petroleum Products",
            "type":"Manufacturing & Wholesale Goods"
        },
        {
            "category":"Home & Garden",
            "subcategory":"Building Materials",
            "type":"Retail Goods"
        }
    ],
    "sg:phone":"+44 1472 240340",
    "sg:postcode":"DN31 2BN",
    "sg:province":"Lincolnshire",
    "sg:tags":[
        "double",
        "window",
        "glazing",
        "frame"
    ],
    "wof:name":"Victoria Windows Ltd.",
    "wof:placetype":"venue"
},
  "geometry": {"coordinates":[-0.108529,53.567959],"type":"Point"}
}