{
  "type": "Feature",
  "properties": {
    "addr:full":"128 Myddleton Road London Greater London N22 4NQ",
    "addr:housenumber":"128",
    "addr:postcode":"n22 4nq",
    "addr:street":"Myddleton Road",
    "iso:country":"GB",
    "sg:address":"128 Myddleton Road",
    "sg:city":"London",
    "sg:classifiers":[
        {
            "category":"Building & Trades",
            "subcategory":"Construction",
            "type":"Services"
        }
    ],
    "sg:phone":"+44 20 8888 2848",
    "sg:postcode":"N22 4NQ",
    "sg:province":"Greater London",
    "sg:tags":[
        "builder"
    ],
    "wof:name":"Mead Contractors Ltd.",
    "wof:placetype":"venue"
},
  "geometry": {"coordinates":[-0.1191499978,51.6066131592],"type":"Point"}
}