{
  "type": "Feature",
  "properties": {
    "addr:full":"Mead House, Lissington Lincoln Lincolnshire LN3 5AE",
    "addr:postcode":"ln3 5ae",
    "iso:country":"GB",
    "sg:address":"Mead House, Lissington",
    "sg:city":"Lincoln",
    "sg:classifiers":[
        {
            "category":"Professional",
            "subcategory":"Management & Consulting",
            "type":"Services"
        },
        {
            "category":"Organizations",
            "subcategory":"Community Association",
            "type":"Services"
        }
    ],
    "sg:postcode":"LN3 5AE",
    "sg:province":"Lincolnshire",
    "sg:tags":[
        "consultant",
        "relation",
        "public",
        "business"
    ],
    "wof:name":"Honeymead Corporate Communications",
    "wof:placetype":"venue"
},
  "geometry": {"coordinates":[-0.3594009876,53.3263549805],"type":"Point"}
}