{
  "type": "Feature",
  "properties": {
    "addr:full":"19 Burman Road, Shirley Solihull West Midlands B90 2BE",
    "addr:housenumber":"19",
    "addr:postcode":"b90 2be",
    "addr:street":"Burman Road",
    "iso:country":"GB",
    "sg:address":"19 Burman Road, Shirley",
    "sg:city":"Solihull",
    "sg:classifiers":[
        {
            "category":"Home & Garden",
            "subcategory":"Garden Supply",
            "type":"Retail Goods"
        },
        {
            "category":"Home & Garden",
            "subcategory":"Hardware",
            "type":"Retail Goods"
        }
    ],
    "sg:phone":"+44 121 745 1675",
    "sg:postcode":"B90 2BE",
    "sg:province":"West Midlands",
    "sg:tags":[
        "lawnmowers",
        "machinery",
        "centre"
    ],
    "wof:name":"PRECISION LAWNMOWER GRINDING CO",
    "wof:placetype":"venue"
},
  "geometry": {"coordinates":[-1.8357169628,52.4035835266],"type":"Point"}
}