{
  "type": "Feature",
  "properties": {
    "iso:country":"GB",
    "sg:address":"128 Bensham Lane",
    "sg:city":"Thornton Heath",
    "sg:classifiers":[
        {
            "category":"Personal",
            "subcategory":"Beauty Salon",
            "type":"Services"
        }
    ],
    "sg:phone":"+44 20 8684 8540",
    "sg:postcode":"CR7 7ES",
    "sg:province":"Surrey",
    "sg:tags":[
        "unisex",
        "hairdresser"
    ],
    "wof:name":"Pyramids",
    "wof:placetype":"venue"
},
  "geometry": {"coordinates":[-0.106185,51.389584],"type":"Point"}
}