{
  "type": "Feature",
  "properties": {
    "iso:country":"GB",
    "sg:address":"24-26 Windmill St",
    "sg:city":"Saltcoats",
    "sg:classifiers":[
        {
            "category":"Bars & Pubs",
            "type":"Food & Drink"
        }
    ],
    "sg:phone":"+44 1294 470578",
    "sg:postcode":"KA21 5EN",
    "sg:province":"North Ayrshire",
    "sg:tags":[
        "pubs",
        "inn"
    ],
    "wof:name":"Gingers Bar",
    "wof:placetype":"venue"
},
  "geometry": {"coordinates":[-4.789947,55.633011],"type":"Point"}
}