{
  "type": "Feature",
  "properties": {
    "addr:full":"25 Witla Court Rd, Rumney Cardiff Caerphilly CF3 3LU",
    "addr:housenumber":"25",
    "addr:postcode":"cf3 3lu",
    "addr:street":"Witla Court Rd",
    "iso:country":"GB",
    "sg:address":"25 Witla Court Rd, Rumney",
    "sg:city":"Cardiff",
    "sg:classifiers":[
        {
            "category":"Banks & Credit Unions",
            "subcategory":"Financial Services",
            "type":"Services"
        }
    ],
    "sg:phone":"+44 29 2040 2888",
    "sg:postcode":"CF3 3LU",
    "sg:province":"Caerphilly",
    "sg:tags":[
        "adviser"
    ],
    "wof:name":"First Options",
    "wof:placetype":"venue"
},
  "geometry": {"coordinates":[-3.124065,51.509487],"type":"Point"}
}