{
  "type": "Feature",
  "properties": {
    "addr:full":"Stubbs Hall Farm, Stubbs Walden, Norton Doncaster North Yorkshire DN6 9BU",
    "addr:postcode":"dn6 9bu",
    "addr:street":"Stubbs Walden",
    "iso:country":"GB",
    "sg:address":"Stubbs Hall Farm, Stubbs Walden, Norton",
    "sg:city":"Doncaster",
    "sg:classifiers":[
        {
            "category":"Farming",
            "subcategory":"Livestock Farm",
            "type":"Manufacturing & Wholesale Goods"
        }
    ],
    "sg:phone":"+44 1302 701225",
    "sg:postcode":"DN6 9BU",
    "sg:province":"North Yorkshire",
    "sg:tags":[
        "others"
    ],
    "wof:name":"B J & C J Seels Bros",
    "wof:placetype":"venue"
},
  "geometry": {"coordinates":[-1.170524,53.632435],"type":"Point"}
}