{
  "type": "Feature",
  "properties": {
    "iso:country":"GB",
    "sg:address":"10 Station Street, Kibworth Beauchamp",
    "sg:city":"Leicester",
    "sg:classifiers":[
        {
            "category":"Professional",
            "subcategory":"Accounting & Tax Preparation",
            "type":"Services"
        }
    ],
    "sg:postcode":"LE8 0LN",
    "sg:province":"Leicestershire",
    "sg:tags":[
        "accountant"
    ],
    "wof:name":"Ireland & Longhill",
    "wof:placetype":"venue"
},
  "geometry": {"coordinates":[-0.99428,52.538284],"type":"Point"}
}