{
  "type": "Feature",
  "properties": {
    "iso:country":"GB",
    "sg:address":"Unit 5, 217-227 Two Mile Hill Road",
    "sg:city":"Bristol",
    "sg:classifiers":[
        {
            "category":"Retail",
            "subcategory":"Auto Repair",
            "type":"Services"
        }
    ],
    "sg:phone":"+44 117 961 6057",
    "sg:postcode":"BS15 1AZ",
    "sg:province":"City of Bristol",
    "sg:tags":[
        "modification",
        "garage"
    ],
    "wof:name":"Cartech Volvo Specialists",
    "wof:placetype":"venue"
},
  "geometry": {"coordinates":[-2.514919,51.463234],"type":"Point"}
}