{
  "type": "Feature",
  "properties": {
    "addr:full":"657-661 High Road Leyton Leyton Greater London E10 6RD",
    "addr:housenumber":"657-661",
    "addr:postcode":"e10 6rd",
    "addr:street":"High Road Leyton Leyton",
    "iso:country":"GB",
    "sg:address":"657-661 High Road Leyton",
    "sg:city":"Leyton",
    "sg:classifiers":[
        {
            "category":"Professional",
            "subcategory":"Engineering",
            "type":"Services"
        }
    ],
    "sg:phone":"+44 20 8539 1133",
    "sg:postcode":"E10 6RD",
    "sg:province":"Greater London",
    "sg:tags":[
        "contractor",
        "electrical",
        "engineer"
    ],
    "wof:name":"E I Ltd",
    "wof:placetype":"venue"
},
  "geometry": {"coordinates":[-0.0080700004,51.5700454712],"type":"Point"}
}