{
  "type": "Feature",
  "properties": {
    "iso:country":"GB",
    "sg:address":"42 Broad Lane, Norris Grn",
    "sg:city":"Liverpool",
    "sg:classifiers":[
        {
            "category":"Banks & Credit Unions",
            "subcategory":"Bank",
            "type":"Services"
        }
    ],
    "sg:phone":"+44 845 765 4321",
    "sg:postcode":"L11 1JH",
    "sg:province":"Merseyside",
    "wof:name":"Abbey National Plc",
    "wof:placetype":"venue"
},
  "geometry": {"coordinates":[-2.9302620888,53.44090271],"type":"Point"}
}