{
  "type": "Feature",
  "properties": {
    "addr:full":"Unit 2 Abbots Quay, Monks Ferry Birkenhead Merseyside L41 5LH",
    "addr:housenumber":"unit 2",
    "addr:postcode":"l41 5lh",
    "addr:street":"Abbots Quay Monks Ferry",
    "iso:country":"GB",
    "sg:address":"Unit 2 Abbots Quay, Monks Ferry",
    "sg:city":"Birkenhead",
    "sg:classifiers":[
        {
            "category":"Professional",
            "subcategory":"Accounting & Tax Preparation",
            "type":"Services"
        }
    ],
    "sg:phone":"+44 151 649 4700",
    "sg:postcode":"L41 5LH",
    "sg:province":"Merseyside",
    "sg:tags":[
        "accountant"
    ],
    "wof:name":"Owens Corning European Shared Services",
    "wof:placetype":"venue"
},
  "geometry": {"coordinates":[-3.0254900455,53.3925590515],"type":"Point"}
}