{
  "type": "Feature",
  "properties": {
    "iso:country":"GB",
    "sg:address":"303 Orbiston St",
    "sg:city":"Motherwell",
    "sg:classifiers":[
        {
            "category":"Building & Trades",
            "subcategory":"Construction",
            "type":"Services"
        }
    ],
    "sg:phone":"+44 1698 276677",
    "sg:postcode":"ML1 1QW",
    "sg:province":"North Lanarkshire",
    "sg:tags":[
        "equipment"
    ],
    "wof:name":"Hewden Tool Hire Ltd",
    "wof:placetype":"venue"
},
  "geometry": {"coordinates":[-3.989529,55.790562],"type":"Point"}
}