{
  "type": "Feature",
  "properties": {
    "iso:country":"GB",
    "sg:address":"Plas Gwynt, Sophia Close",
    "sg:city":"Cardiff",
    "sg:classifiers":[
        {
            "category":"Communications",
            "type":"Services"
        }
    ],
    "sg:phone":"+44 29 2025 5443",
    "sg:postcode":"CF1 9XY",
    "sg:province":"Cardiff",
    "sg:tags":[
        "broadcasting"
    ],
    "wof:name":"Composed Edits",
    "wof:placetype":"venue"
},
  "geometry": {"coordinates":[-3.18067,51.481258],"type":"Point"}
}