{
  "type": "Feature",
  "properties": {
    "addr:full":"Unit 19-22, Goldsworth Road Industrial Estate Woking Surrey GU21 6LY",
    "addr:housenumber":"unit 19-22",
    "addr:postcode":"gu21 6ly",
    "addr:street":"Goldsworth Road Industrial Estate",
    "iso:country":"GB",
    "sg:address":"Unit 19-22, Goldsworth Road Industrial Estate",
    "sg:city":"Woking",
    "sg:classifiers":[
        {
            "category":"Manufacturing",
            "subcategory":"Metals",
            "type":"Manufacturing & Wholesale Goods"
        },
        {
            "category":"Professional",
            "subcategory":"Engineering",
            "type":"Services"
        },
        {
            "category":"Organizations",
            "subcategory":"Professional Association",
            "type":"Services"
        }
    ],
    "sg:phone":"+44 1483 773444",
    "sg:postcode":"GU21 6LY",
    "sg:province":"Surrey",
    "sg:tags":[
        "control",
        "engineer",
        "system",
        "automation"
    ],
    "wof:name":"Automation Solutions Ltd",
    "wof:placetype":"venue"
},
  "geometry": {"coordinates":[-0.5609890223,51.3174591064],"type":"Point"}
}