{
  "type": "Feature",
  "properties": {
    "iso:country":"GB",
    "sg:address":"64b Green Lane",
    "sg:city":"Northwood",
    "sg:classifiers":[
        {
            "category":"Personal",
            "subcategory":"Beauty Salon",
            "type":"Services"
        },
        {
            "category":"Personal",
            "subcategory":"Barber",
            "type":"Services"
        }
    ],
    "sg:phone":"+44 1923 821692",
    "sg:postcode":"HA6 2XW",
    "sg:province":"Greater London",
    "sg:tags":[
        "unisex",
        "hairdresser"
    ],
    "wof:name":"STEVE'S",
    "wof:placetype":"venue"
},
  "geometry": {"coordinates":[-0.425659,51.611858],"type":"Point"}
}