{
  "type": "Feature",
  "properties": {
    "addr:full":"92 Ayresome St, Middlesbrough North Yorkshire TS1 4NJ",
    "addr:housenumber":"92",
    "addr:postcode":"ts1 4nj",
    "addr:street":"Ayresome St",
    "iso:country":"GB",
    "sg:address":"92 Ayresome St,",
    "sg:city":"Middlesbrough",
    "sg:classifiers":[
        {
            "category":"Building & Trades",
            "subcategory":"Construction",
            "type":"Services"
        },
        {
            "category":"Professional",
            "subcategory":"Printing & Photocopies",
            "type":"Services"
        }
    ],
    "sg:postcode":"TS1 4NJ",
    "sg:province":"North Yorkshire",
    "sg:tags":[
        "builder",
        "printer"
    ],
    "wof:name":"Sale Signs",
    "wof:placetype":"venue"
},
  "geometry": {"coordinates":[-1.2453260422,54.5654754639],"type":"Point"}
}