{
  "type": "Feature",
  "properties": {
    "addr:full":"The Old Fire Station, 21 Wellcroft Shipley West Yorkshire BD18 3QH",
    "addr:postcode":"bd18 3qh",
    "addr:street":"Wellcroft;West",
    "iso:country":"GB",
    "sg:address":"The Old Fire Station, 21 Wellcroft",
    "sg:city":"Shipley",
    "sg:classifiers":[
        {
            "category":"Building & Trades",
            "subcategory":"Landscaping Services",
            "type":"Services"
        },
        {
            "category":"Shopping",
            "subcategory":"Hobbies, Toys, & Games",
            "type":"Retail Goods"
        }
    ],
    "sg:phone":"+44 1274 581411",
    "sg:postcode":"BD18 3QH",
    "sg:province":"West Yorkshire",
    "sg:tags":[
        "horticultural",
        "computer",
        "consultant"
    ],
    "wof:name":"MARK R JEFFREYS",
    "wof:placetype":"venue"
},
  "geometry": {"coordinates":[-1.783725,53.834007],"type":"Point"}
}