{
  "type": "Feature",
  "properties": {
    "addr:full":"712 Preston Old Rd, Feniscowles Blackburn Lancashire BB2 5EP",
    "addr:housenumber":"712",
    "addr:postcode":"bb2 5ep",
    "addr:street":"Preston Old Rd",
    "iso:country":"GB",
    "sg:address":"712 Preston Old Rd, Feniscowles",
    "sg:city":"Blackburn",
    "sg:classifiers":[
        {
            "category":"Government",
            "subcategory":"Post Office",
            "type":"Public Place"
        }
    ],
    "sg:phone":"+44 1254 201611",
    "sg:postcode":"BB2 5EP",
    "sg:province":"Lancashire",
    "wof:name":"Feniscowles P.O",
    "wof:placetype":"venue"
},
  "geometry": {"coordinates":[-2.537535,53.72707],"type":"Point"}
}