{
  "type": "Feature",
  "properties": {
    "addr:full":"7 Culworth Road, Chipping Warden Banbury Northamptonshire OX17 1LB",
    "addr:housenumber":"7",
    "addr:postcode":"ox17 1lb",
    "addr:street":"Culworth Road",
    "iso:country":"GB",
    "sg:address":"7 Culworth Road, Chipping Warden",
    "sg:city":"Banbury",
    "sg:classifiers":[
        {
            "category":"Food & Beverages",
            "subcategory":"Meat & Fish",
            "type":"Retail Goods"
        }
    ],
    "sg:phone":"+44 1295 660348",
    "sg:postcode":"OX17 1LB",
    "sg:province":"Northamptonshire",
    "sg:tags":[
        "butcher"
    ],
    "wof:name":"P G & C Mumford",
    "wof:placetype":"venue"
},
  "geometry": {"coordinates":[-1.271262,52.135876],"type":"Point"}
}