{
  "type": "Feature",
  "properties": {
    "iso:country":"GB",
    "sg:address":"Mains Of Inveramsay, Pitcaple",
    "sg:city":"Inverurie",
    "sg:classifiers":[
        {
            "category":"Farming",
            "subcategory":"Farm",
            "type":"Manufacturing & Wholesale Goods"
        }
    ],
    "sg:postcode":"AB51 5DS",
    "sg:province":"Aberdeenshire",
    "sg:tags":[
        "mixed",
        "crop"
    ],
    "wof:name":"J Webster & Co.",
    "wof:placetype":"venue"
},
  "geometry": {"coordinates":[-2.466214,57.326145],"type":"Point"}
}