{
  "type": "Feature",
  "properties": {
    "iso:country":"GB",
    "sg:address":"Unit 5 Halifax Rd, Cressex Indstl Est",
    "sg:city":"High Wycombe",
    "sg:classifiers":[
        {
            "category":"Autos & Motor Vehicles",
            "subcategory":"Automobile Sales",
            "type":"Retail Goods"
        }
    ],
    "sg:postcode":"HP12 3ST",
    "sg:province":"Buckinghamshire",
    "sg:tags":[
        "car"
    ],
    "wof:name":"Lane,Maurice P,",
    "wof:placetype":"venue"
},
  "geometry": {"coordinates":[-0.7799140215,51.6209831238],"type":"Point"}
}