{
  "type": "Feature",
  "properties": {
    "iso:country":"GB",
    "sg:address":"8a Wood Street, Middleton",
    "sg:city":"Manchester",
    "sg:classifiers":[
        {
            "category":"Banks & Credit Unions",
            "subcategory":"Bank",
            "type":"Services"
        }
    ],
    "sg:phone":"+44 161 655 4029",
    "sg:postcode":"M24 5JZ",
    "sg:province":"Greater Manchester",
    "wof:name":"Yorkshire Bank Plc",
    "wof:placetype":"venue"
},
  "geometry": {"coordinates":[-2.21677,53.558689],"type":"Point"}
}