{
  "type": "Feature",
  "properties": {
    "iso:country":"GB",
    "sg:address":"2-4 Carlton Road, Warley",
    "sg:city":"Smethwick",
    "sg:classifiers":[
        {
            "category":"Shopping",
            "subcategory":"Department Store",
            "type":"Retail Goods"
        }
    ],
    "sg:phone":"+44 121 558 2099",
    "sg:postcode":"B66 2HN",
    "sg:province":"West Midlands",
    "wof:name":"Jandu Supersave",
    "wof:placetype":"venue"
},
  "geometry": {"coordinates":[-1.9642299414,52.5049057007],"type":"Point"}
}