{
  "type": "Feature",
  "properties": {
    "addr:full":"Station Road, Cymmer Port Talbot Neath Port Talbot SA13 3HR",
    "addr:postcode":"sa13 3hr",
    "addr:street":"Station Road",
    "iso:country":"GB",
    "sg:address":"Station Road, Cymmer",
    "sg:city":"Port Talbot",
    "sg:classifiers":[
        {
            "category":"Education",
            "subcategory":"Library",
            "type":"Public Place"
        }
    ],
    "sg:phone":"+44 1792 842148",
    "sg:postcode":"SA13 3HR",
    "sg:province":"Neath Port Talbot",
    "sg:tags":[
        "book"
    ],
    "wof:name":"Cymmer Afan Library",
    "wof:placetype":"venue"
},
  "geometry": {"coordinates":[-3.6009969711,51.65467453],"type":"Point"}
}