{
  "type": "Feature",
  "properties": {
    "iso:country":"GB",
    "sg:address":"52 Mitchell Street, South Moor",
    "sg:city":"Stanley",
    "sg:classifiers":[
        {
            "category":"Real Estate",
            "subcategory":"Architect",
            "type":"Services"
        }
    ],
    "sg:phone":"+44 1207 280095",
    "sg:postcode":"DH9 7BQ",
    "sg:province":"Durham",
    "wof:name":"Hugh Massey Architects",
    "wof:placetype":"venue"
},
  "geometry": {"coordinates":[-1.708497,54.860367],"type":"Point"}
}