{
  "type": "Feature",
  "properties": {
    "addr:full":"52 Mitchell Street, South Moor Stanley Durham DH9 7BQ",
    "addr:housenumber":"52",
    "addr:postcode":"dh9 7bq",
    "addr:street":"Mitchell Street South Moor Stanley",
    "iso:country":"GB",
    "sg:address":"52 Mitchell Street, South Moor",
    "sg:city":"Stanley",
    "sg:classifiers":[
        {
            "category":"Real Estate",
            "subcategory":"Architect",
            "type":"Services"
        }
    ],
    "sg:phone":"+44 1207 280095",
    "sg:postcode":"DH9 7BQ",
    "sg:province":"Durham",
    "wof:name":"Hugh Massey Architects",
    "wof:placetype":"venue"
},
  "geometry": {"coordinates":[-1.708497,54.860367],"type":"Point"}
}