{
  "type": "Feature",
  "properties": {
    "addr:full":"12a Holmes Rd Kentish Town Greater London NW5 3AE",
    "addr:housenumber":"12a",
    "addr:postcode":"nw5 3ae",
    "addr:street":"Holmes Rd",
    "iso:country":"GB",
    "sg:address":"12a Holmes Rd",
    "sg:city":"Kentish Town",
    "sg:classifiers":[
        {
            "category":"Government",
            "subcategory":"Police Station",
            "type":"Public Place"
        }
    ],
    "sg:phone":"+44 20 7388 1212",
    "sg:postcode":"NW5 3AE",
    "sg:province":"Greater London",
    "sg:tags":[
        "support"
    ],
    "wof:name":"Metropolitan Police Service",
    "wof:placetype":"venue"
},
  "geometry": {"coordinates":[-0.1422200054,51.5496292114],"type":"Point"}
}