{
  "type": "Feature",
  "properties": {
    "addr:full":"Aulton Farm, Kilmaurs Kilmarnock East Ayrshire KA3 2PQ",
    "addr:postcode":"ka3 2pq",
    "addr:street":"East",
    "iso:country":"GB",
    "sg:address":"Aulton Farm, Kilmaurs",
    "sg:city":"Kilmarnock",
    "sg:classifiers":[
        {
            "category":"Building & Trades",
            "subcategory":"Construction",
            "type":"Services"
        }
    ],
    "sg:phone":"+44 1563 538208",
    "sg:postcode":"KA3 2PQ",
    "sg:province":"East Ayrshire",
    "sg:tags":[
        "builder"
    ],
    "wof:name":"Hawkshaw Builders",
    "wof:placetype":"venue"
},
  "geometry": {"coordinates":[-4.5268239975,55.6388435364],"type":"Point"}
}