{
  "type": "Feature",
  "properties": {
    "addr:full":"87 Holly Road, Aspull Wigan Lancashire WN2 1RY",
    "addr:housenumber":"87",
    "addr:postcode":"wn2 1ry",
    "addr:street":"Holly Road Aspull",
    "iso:country":"GB",
    "sg:address":"87 Holly Road, Aspull",
    "sg:city":"Wigan",
    "sg:classifiers":[
        {
            "category":"Professional",
            "type":"Services"
        }
    ],
    "sg:phone":"+44 1942 510757",
    "sg:postcode":"WN2 1RY",
    "sg:province":"Lancashire",
    "sg:tags":[
        "entertainer"
    ],
    "wof:name":"Owen Hughes Entertainments",
    "wof:placetype":"venue"
},
  "geometry": {"coordinates":[-2.5917229652,53.5681152344],"type":"Point"}
}