{
  "type": "Feature",
  "properties": {
    "iso:country":"GB",
    "sg:address":"10 Panmure St",
    "sg:city":"Dundee",
    "sg:classifiers":[
        {
            "category":"Professional",
            "subcategory":"Lawyer & Legal Services",
            "type":"Services"
        }
    ],
    "sg:phone":"+44 1382 225040",
    "sg:postcode":"DD1 2BW",
    "sg:province":"Dundee City",
    "sg:tags":[
        "advice",
        "counselling"
    ],
    "wof:name":"Innocents Pregnancy Care Organisation The",
    "wof:placetype":"venue"
},
  "geometry": {"coordinates":[-2.97071,56.463215],"type":"Point"}
}