{
  "type": "Feature",
  "properties": {
    "iso:country":"GB",
    "sg:address":"38 Carriage Dr",
    "sg:city":"Kettering",
    "sg:classifiers":[
        {
            "category":"Travel",
            "subcategory":"Hotels & Motels",
            "type":"Entertainment"
        }
    ],
    "sg:postcode":"NN16 9EN",
    "sg:province":"Northamptonshire",
    "sg:tags":[
        "self",
        "catering"
    ],
    "wof:name":"Woodland Lodge Welsh Holidays",
    "wof:placetype":"venue"
},
  "geometry": {"coordinates":[-0.722993,52.418812],"type":"Point"}
}