{
  "type": "Feature",
  "properties": {
    "addr:full":"Croft Lane Skegness Lincolnshire PE24 4PF",
    "addr:postcode":"pe24 4pf",
    "addr:street":"Croft Lane",
    "iso:country":"GB",
    "sg:address":"Croft Lane",
    "sg:city":"Skegness",
    "sg:classifiers":[
        {
            "category":"Bars & Pubs",
            "type":"Food & Drink"
        }
    ],
    "sg:phone":"+44 1754 880320",
    "sg:postcode":"PE24 4PF",
    "sg:province":"Lincolnshire",
    "sg:tags":[
        "pubs",
        "inn"
    ],
    "wof:name":"Old Chequers Inn",
    "wof:placetype":"venue"
},
  "geometry": {"coordinates":[0.247037,53.136486],"type":"Point"}
}