{
  "type": "Feature",
  "properties": {
    "iso:country":"GB",
    "sg:address":"14 Harcourt Drive, Four Oaks",
    "sg:city":"Sutton Coldfield",
    "sg:classifiers":[
        {
            "category":"Building & Trades",
            "subcategory":"Plumbing",
            "type":"Services"
        }
    ],
    "sg:phone":"+44 121 353 3671",
    "sg:postcode":"B74 4LJ",
    "sg:province":"Staffordshire",
    "sg:tags":[
        "heating"
    ],
    "wof:name":"D Wood",
    "wof:placetype":"venue"
},
  "geometry": {"coordinates":[-1.84637,52.595131],"type":"Point"}
}