{
  "type": "Feature",
  "properties": {
    "addr:full":"33 Gerrard Street Widnes Cheshire WA8 6BF",
    "addr:housenumber":"33",
    "addr:postcode":"wa8 6bf",
    "addr:street":"Gerrard Street",
    "iso:country":"GB",
    "sg:address":"33 Gerrard Street",
    "sg:city":"Widnes",
    "sg:classifiers":[
        {
            "category":"Home & Garden",
            "subcategory":"Home Furnishings",
            "type":"Retail Goods"
        }
    ],
    "sg:phone":"+44 151 495 2606",
    "sg:postcode":"WA8 6BF",
    "sg:province":"Cheshire",
    "sg:tags":[
        "furnishers",
        "planner",
        "kitchen"
    ],
    "wof:name":"Simms Cross Home Improvements",
    "wof:placetype":"venue"
},
  "geometry": {"coordinates":[-2.7292990685,53.3659210205],"type":"Point"}
}