{
  "type": "Feature",
  "properties": {
    "addr:full":"5 Manor Court Av Nuneaton Leicestershire CV11 5HX",
    "addr:housenumber":"5",
    "addr:postcode":"cv11 5hx",
    "addr:street":"Manor Court Av",
    "iso:country":"GB",
    "sg:address":"5 Manor Court Av",
    "sg:city":"Nuneaton",
    "sg:classifiers":[
        {
            "category":"Health Services",
            "subcategory":"Doctor",
            "type":"Services"
        }
    ],
    "sg:phone":"+44 24 7638 1999",
    "sg:postcode":"CV11 5HX",
    "sg:province":"Leicestershire",
    "sg:tags":[
        "practitioners"
    ],
    "wof:name":"Necati, G",
    "wof:placetype":"venue"
},
  "geometry": {"coordinates":[-1.4775229692,52.5265769958],"type":"Point"}
}