{
  "type": "Feature",
  "properties": {
    "iso:country":"GB",
    "sg:address":"2 Hopton Parade, Streatham",
    "sg:city":"London",
    "sg:classifiers":[
        {
            "category":"Sports & Exercise",
            "subcategory":"Ice Rink",
            "type":"Entertainment"
        }
    ],
    "sg:postcode":"SW16 6EP",
    "sg:province":"Greater London",
    "sg:tags":[
        "skating"
    ],
    "wof:name":"Streatham Skate Shop",
    "wof:placetype":"venue"
},
  "geometry": {"coordinates":[-0.129797,51.425598],"type":"Point"}
}