{
  "type": "Feature",
  "properties": {
    "iso:country":"GB",
    "sg:address":"65 Bradleigh Avenue",
    "sg:city":"Grays",
    "sg:classifiers":[
        {
            "category":"Freight",
            "type":"Transportation"
        }
    ],
    "sg:phone":"+44 1708 554108",
    "sg:postcode":"RM17 5AJ",
    "sg:province":"Essex",
    "sg:tags":[
        "haulage",
        "road"
    ],
    "wof:name":"E J Fields (Haulage Contractors) Ltd.",
    "wof:placetype":"venue"
},
  "geometry": {"coordinates":[0.3316589892,51.4873313904],"type":"Point"}
}