{
  "type": "Feature",
  "properties": {
    "addr:full":"Unit 7/8, Dade Avenue, Inkersall Chesterfield Derbyshire S43 3SH",
    "addr:housenumber":"unit 7 / 8",
    "addr:postcode":"s43 3sh",
    "addr:street":"Dade Avenue Inkersall",
    "iso:country":"GB",
    "sg:address":"Unit 7/8, Dade Avenue, Inkersall",
    "sg:city":"Chesterfield",
    "sg:classifiers":[
        {
            "category":"Wholesale",
            "subcategory":"Scrap",
            "type":"Manufacturing & Wholesale Goods"
        }
    ],
    "sg:phone":"+44 1246 476189",
    "sg:postcode":"S43 3SH",
    "sg:province":"Derbyshire",
    "sg:tags":[
        "breaker",
        "dismantlers"
    ],
    "wof:name":"B B Autos",
    "wof:placetype":"venue"
},
  "geometry": {"coordinates":[-1.357435,53.24971],"type":"Point"}
}