{
  "type": "Feature",
  "properties": {
    "addr:full":"Budbrooke Road Industrial Estate, Budbrooke Road Warwick Warwickshire CV34 5WE",
    "addr:postcode":"cv34 5we",
    "addr:street":"Budbrooke Road Industrial Estate Budbrooke Road",
    "iso:country":"GB",
    "sg:address":"Budbrooke Road Industrial Estate, Budbrooke Road",
    "sg:city":"Warwick",
    "sg:classifiers":[
        {
            "category":"Building & Trades",
            "subcategory":"Construction",
            "type":"Services"
        }
    ],
    "sg:postcode":"CV34 5WE",
    "sg:province":"Warwickshire",
    "sg:tags":[
        "platform",
        "work",
        "scaffolding"
    ],
    "wof:name":"Sky Scaffolding",
    "wof:placetype":"venue"
},
  "geometry": {"coordinates":[-1.6039659977,52.2875137329],"type":"Point"}
}