{
  "type": "Feature",
  "properties": {
    "addr:full":"74b High St Honiton Devon EX14 1PD",
    "addr:housenumber":"74b",
    "addr:postcode":"ex14 1pd",
    "addr:street":"High St",
    "iso:country":"GB",
    "sg:address":"74b High St",
    "sg:city":"Honiton",
    "sg:classifiers":[
        {
            "category":"Professional",
            "type":"Services"
        }
    ],
    "sg:postcode":"EX14 1PD",
    "sg:province":"Devon",
    "sg:tags":[
        "directory",
        "pub"
    ],
    "wof:name":"East Devon Press",
    "wof:placetype":"venue"
},
  "geometry": {"coordinates":[-3.1886401176,50.7996406555],"type":"Point"}
}