{
  "type": "Feature",
  "properties": {
    "iso:country":"GB",
    "sg:address":"Solva",
    "sg:city":"Haverfordwest",
    "sg:classifiers":[
        {
            "category":"Education",
            "subcategory":"School",
            "type":"Public Place"
        }
    ],
    "sg:postcode":"SA62 6TS",
    "sg:province":"Pembrokeshire",
    "sg:tags":[
        "local",
        "authority"
    ],
    "wof:name":"Solva County Primary School",
    "wof:placetype":"venue"
},
  "geometry": {"coordinates":[-5.199,51.875019],"type":"Point"}
}