{
  "type": "Feature",
  "properties": {
    "addr:full":"197 Reid St Glasgow Glasgow City G40 4DX",
    "addr:housenumber":"197",
    "addr:postcode":"g40 4dx",
    "addr:street":"Reid St",
    "iso:country":"GB",
    "sg:address":"197 Reid St",
    "sg:city":"Glasgow",
    "sg:classifiers":[
        {
            "category":"Autos & Motor Vehicles",
            "subcategory":"Motorcycle Sales",
            "type":"Retail Goods"
        }
    ],
    "sg:postcode":"G40 4DX",
    "sg:province":"Glasgow City",
    "sg:tags":[
        "chauffeur",
        "driven",
        "car"
    ],
    "wof:name":"O'Hara,James,",
    "wof:placetype":"venue"
},
  "geometry": {"coordinates":[-4.224596,55.840984],"type":"Point"}
}