{
  "type": "Feature",
  "properties": {
    "iso:country":"GB",
    "sg:address":"15 King Street, Billinghay",
    "sg:city":"Lincoln",
    "sg:classifiers":[
        {
            "category":"Building & Trades",
            "subcategory":"Construction",
            "type":"Services"
        }
    ],
    "sg:phone":"+44 1526 861685",
    "sg:postcode":"LN4 4HJ",
    "sg:province":"Lincolnshire",
    "sg:tags":[
        "contractor"
    ],
    "wof:name":"S B Construction (Lincoln) Ltd.",
    "wof:placetype":"venue"
},
  "geometry": {"coordinates":[-0.2793219984,53.0789642334],"type":"Point"}
}