{
  "type": "Feature",
  "properties": {
    "addr:full":"18 Broadwalk Shopping Centre, Broad Walk Bristol City of Bristol BS4 2QU",
    "addr:housenumber":"18",
    "addr:postcode":"bs4 2qu",
    "addr:street":"Broadwalk Shopping;Broad Walk",
    "iso:country":"GB",
    "sg:address":"18 Broadwalk Shopping Centre, Broad Walk",
    "sg:city":"Bristol",
    "sg:classifiers":[
        {
            "category":"Shopping",
            "subcategory":"News",
            "type":"Retail Goods"
        }
    ],
    "sg:phone":"+44 117 972 0745",
    "sg:postcode":"BS4 2QU",
    "sg:province":"City of Bristol",
    "sg:tags":[
        "newsagent"
    ],
    "wof:name":"Forbuoys Ltd.",
    "wof:placetype":"venue"
},
  "geometry": {"coordinates":[-2.5680398941,51.4343795776],"type":"Point"}
}