{
  "type": "Feature",
  "properties": {
    "iso:country":"GB",
    "sg:address":"Sibleys Farm, Chickney Road, Henham",
    "sg:city":"Bishops Stortford",
    "sg:classifiers":[
        {
            "category":"Farming",
            "subcategory":"Livestock Farm",
            "type":"Manufacturing & Wholesale Goods"
        }
    ],
    "sg:phone":"+44 1279 850310",
    "sg:postcode":"CM22 6BH",
    "sg:province":"Essex",
    "sg:tags":[
        "others"
    ],
    "wof:name":"F J Lindsell & Son",
    "wof:placetype":"venue"
},
  "geometry": {"coordinates":[0.248807,51.933414],"type":"Point"}
}