{
  "type": "Feature",
  "properties": {
    "addr:full":"84 Princes Street Ardrossan North Ayrshire KA22 8DQ",
    "addr:housenumber":"84",
    "addr:postcode":"ka22 8dq",
    "addr:street":"Princes Street",
    "iso:country":"GB",
    "sg:address":"84 Princes Street",
    "sg:city":"Ardrossan",
    "sg:classifiers":[
        {
            "category":"Organizations",
            "subcategory":"Community Association",
            "type":"Services"
        },
        {
            "category":"Organizations",
            "subcategory":"Membership Organization",
            "type":"Services"
        }
    ],
    "sg:phone":"+44 1294 465103",
    "sg:postcode":"KA22 8DQ",
    "sg:province":"North Ayrshire",
    "sg:tags":[
        "club",
        "social"
    ],
    "wof:name":"ARDROSSAN UNIONIST CLUB",
    "wof:placetype":"venue"
},
  "geometry": {"coordinates":[-4.812257,55.63924],"type":"Point"}
}