{
  "type": "Feature",
  "properties": {
    "addr:full":"164 Chiltern Drive Surbiton Surrey KT5 8LS",
    "addr:housenumber":"164",
    "addr:postcode":"kt5 8ls",
    "addr:street":"Chiltern Drive",
    "iso:country":"GB",
    "sg:address":"164 Chiltern Drive",
    "sg:city":"Surbiton",
    "sg:classifiers":[
        {
            "category":"Food & Beverages",
            "subcategory":"Candy",
            "type":"Retail Goods"
        }
    ],
    "sg:phone":"+44 20 8255 9005",
    "sg:postcode":"KT5 8LS",
    "sg:province":"Surrey",
    "sg:tags":[
        "merchant",
        "produce"
    ],
    "wof:name":"Husa Distribution",
    "wof:placetype":"venue"
},
  "geometry": {"coordinates":[-0.2798570096,51.3989334106],"type":"Point"}
}