{
  "type": "Feature",
  "properties": {
    "iso:country":"GB",
    "sg:address":"192 Victoria Street",
    "sg:city":"Grimsby",
    "sg:classifiers":[
        {
            "category":"Building & Trades",
            "subcategory":"Construction",
            "type":"Services"
        }
    ],
    "sg:postcode":"DN31 1NX",
    "sg:province":"Lincolnshire",
    "sg:tags":[
        "flooring"
    ],
    "wof:name":"Dms Laminated Floors & Walls Ltd",
    "wof:placetype":"venue"
},
  "geometry": {"coordinates":[-0.0811590031,53.5704231262],"type":"Point"}
}