{
  "type": "Feature",
  "properties": {
    "addr:full":"The Elms, Back Lane Axbridge Somerset BS26 2PG",
    "addr:postcode":"bs26 2pg",
    "addr:street":"Back Lane",
    "iso:country":"GB",
    "sg:address":"The Elms, Back Lane",
    "sg:city":"Axbridge",
    "sg:classifiers":[
        {
            "category":"Building & Trades",
            "subcategory":"Construction",
            "type":"Services"
        }
    ],
    "sg:phone":"+44 1934 712593",
    "sg:postcode":"BS26 2PG",
    "sg:province":"Somerset",
    "sg:tags":[
        "platform",
        "work",
        "scaffolding"
    ],
    "wof:name":"Apex Scaffolding (South West) Ltd.",
    "wof:placetype":"venue"
},
  "geometry": {"coordinates":[-2.8184089661,51.2883911133],"type":"Point"}
}