{
  "type": "Feature",
  "properties": {
    "addr:full":"34 Brecon Close Melksham Wiltshire SN12 7RZ",
    "addr:housenumber":"34",
    "addr:postcode":"sn12 7rz",
    "addr:street":"Brecon Close",
    "iso:country":"GB",
    "sg:address":"34 Brecon Close",
    "sg:city":"Melksham",
    "sg:classifiers":[
        {
            "category":"Building & Trades",
            "subcategory":"Construction",
            "type":"Services"
        }
    ],
    "sg:phone":"+44 1225 706629",
    "sg:postcode":"SN12 7RZ",
    "sg:province":"Wiltshire",
    "sg:tags":[
        "joinery",
        "joiner",
        "carpenter",
        "carpentry"
    ],
    "wof:name":"John Galliers",
    "wof:placetype":"venue"
},
  "geometry": {"coordinates":[-2.1228260994,51.3730430603],"type":"Point"}
}