{
  "type": "Feature",
  "properties": {
    "addr:full":"10 Hounslow Gardens Hounslow Greater London TW3 2DU",
    "addr:housenumber":"10",
    "addr:postcode":"tw3 2du",
    "addr:street":"Hounslow Gardens",
    "iso:country":"GB",
    "sg:address":"10 Hounslow Gardens",
    "sg:city":"Hounslow",
    "sg:classifiers":[
        {
            "category":"Retail",
            "subcategory":"Auto Repair",
            "type":"Services"
        }
    ],
    "sg:postcode":"TW3 2DU",
    "sg:province":"Greater London",
    "sg:tags":[
        "modification",
        "garage"
    ],
    "wof:name":"Murray & Porteous",
    "wof:placetype":"venue"
},
  "geometry": {"coordinates":[-0.361715,51.461197],"type":"Point"}
}