{
  "type": "Feature",
  "properties": {
    "iso:country":"GB",
    "sg:address":"79 Burnthouse La",
    "sg:city":"Exeter",
    "sg:classifiers":[
        {
            "category":"Shopping",
            "subcategory":"News",
            "type":"Retail Goods"
        }
    ],
    "sg:postcode":"EX2 6AZ",
    "sg:province":"Devon",
    "sg:tags":[
        "newsagent"
    ],
    "wof:name":"Smith,Brian,",
    "wof:placetype":"venue"
},
  "geometry": {"coordinates":[-3.504183,50.7113],"type":"Point"}
}