{
  "type": "Feature",
  "properties": {
    "addr:full":"Silwood Park, Buckhurst Road Ascot Berkshire SL5 7QN",
    "addr:postcode":"sl5 7qn",
    "addr:street":"Park Buckhurst Road",
    "iso:country":"GB",
    "sg:address":"Silwood Park, Buckhurst Road",
    "sg:city":"Ascot",
    "sg:classifiers":[
        {
            "category":"Professional",
            "subcategory":"Engineering",
            "type":"Services"
        },
        {
            "category":"Health Services",
            "subcategory":"Medical Lab",
            "type":"Services"
        }
    ],
    "sg:phone":"+44 1344 636500",
    "sg:postcode":"SL5 7QN",
    "sg:province":"Berkshire",
    "sg:tags":[
        "based",
        "consultant",
        "research",
        "activity",
        "laboratory",
        "structural"
    ],
    "wof:name":"The Steel Construction Institute",
    "wof:placetype":"venue"
},
  "geometry": {"coordinates":[-0.642275,51.408432],"type":"Point"}
}