{
  "type": "Feature",
  "properties": {
    "addr:full":"Unit 7 Coventry Warwickshire CV7 9EJ",
    "addr:housenumber":"unit 7",
    "addr:postcode":"cv7 9ej",
    "iso:country":"GB",
    "sg:address":"Unit 7",
    "sg:city":"Coventry",
    "sg:classifiers":[
        {
            "category":"Professional",
            "subcategory":"Engineering",
            "type":"Services"
        }
    ],
    "sg:phone":"+44 24 7636 5103",
    "sg:postcode":"CV7 9EJ",
    "sg:province":"Warwickshire",
    "sg:tags":[
        "precision",
        "engineer"
    ],
    "wof:name":"Robson Engineering",
    "wof:placetype":"venue"
},
  "geometry": {"coordinates":[-1.471749,52.465481],"type":"Point"}
}