{
  "type": "Feature",
  "properties": {
    "iso:country":"GB",
    "sg:address":"59 Canterbury Road",
    "sg:city":"Worthing",
    "sg:classifiers":[
        {
            "category":"Building & Trades",
            "subcategory":"Construction",
            "type":"Services"
        }
    ],
    "sg:phone":"+44 1903 267370",
    "sg:postcode":"BN13 1AN",
    "sg:province":"West Sussex",
    "sg:tags":[
        "builder"
    ],
    "wof:name":"Kalvin Builders",
    "wof:placetype":"venue"
},
  "geometry": {"coordinates":[-0.399512,50.819298],"type":"Point"}
}