{
  "type": "Feature",
  "properties": {
    "iso:country":"GB",
    "sg:address":"102 Semilong Road",
    "sg:city":"Northampton",
    "sg:classifiers":[
        {
            "category":"Banks & Credit Unions",
            "subcategory":"Financial Services",
            "type":"Services"
        }
    ],
    "sg:postcode":"NN2 6HX",
    "sg:province":"Northamptonshire",
    "sg:tags":[
        "claim",
        "assessor"
    ],
    "wof:name":"Smith Capell & Co. (Northampton) Ltd.",
    "wof:placetype":"venue"
},
  "geometry": {"coordinates":[-0.9003300071,52.2490730286],"type":"Point"}
}