{
  "type": "Feature",
  "properties": {
    "addr:full":"77a School Lane Manchester Greater Manchester M20 6WN",
    "addr:housenumber":"77a",
    "addr:postcode":"m20 6wn",
    "addr:street":"School Lane",
    "iso:country":"GB",
    "sg:address":"77a School Lane",
    "sg:city":"Manchester",
    "sg:classifiers":[
        {
            "category":"Shopping",
            "subcategory":"Crafts & Fabrics",
            "type":"Retail Goods"
        }
    ],
    "sg:postcode":"M20 6WN",
    "sg:province":"Greater Manchester",
    "sg:tags":[
        "shop"
    ],
    "wof:name":"Hazeldress",
    "wof:placetype":"venue"
},
  "geometry": {"coordinates":[-2.225316,53.417091],"type":"Point"}
}