{
  "type": "Feature",
  "properties": {
    "addr:full":"8 Windsor Terrace, Clifton Bristol City of Bristol BS8 4LW",
    "addr:housenumber":"8",
    "addr:postcode":"bs8 4lw",
    "addr:street":"Windsor Terrace",
    "iso:country":"GB",
    "sg:address":"8 Windsor Terrace, Clifton",
    "sg:city":"Bristol",
    "sg:classifiers":[
        {
            "category":"Real Estate",
            "subcategory":"Developer",
            "type":"Services"
        }
    ],
    "sg:phone":"+44 117 921 1647",
    "sg:postcode":"BS8 4LW",
    "sg:province":"City of Bristol",
    "sg:tags":[
        "property"
    ],
    "wof:name":"8 Windsor Terrace Ltd.",
    "wof:placetype":"venue"
},
  "geometry": {"coordinates":[-2.62424,51.45145],"type":"Point"}
}