{
  "type": "Feature",
  "properties": {
    "iso:country":"GB",
    "sg:address":"71 Gladstone Avenue",
    "sg:city":"Twickenham",
    "sg:classifiers":[
        {
            "category":"Professional",
            "subcategory":"Accounting & Tax Preparation",
            "type":"Services"
        }
    ],
    "sg:phone":"+44 20 8898 0901",
    "sg:postcode":"TW2 7PS",
    "sg:province":"Greater London",
    "sg:tags":[
        "accountant"
    ],
    "wof:name":"K J Riley Chartered Accountant",
    "wof:placetype":"venue"
},
  "geometry": {"coordinates":[-0.349962,51.448872],"type":"Point"}
}