{
  "type": "Feature",
  "properties": {
    "iso:country":"GB",
    "sg:address":"94 Broomhill Rd",
    "sg:city":"Aberdeen",
    "sg:classifiers":[
        {
            "category":"Professional",
            "subcategory":"Engineering",
            "type":"Services"
        }
    ],
    "sg:phone":"+44 1224 592861",
    "sg:postcode":"AB10 6HX",
    "sg:province":"Aberdeen City",
    "sg:tags":[
        "contractor",
        "electrical",
        "engineer"
    ],
    "wof:name":"M & M Services Aberdeen Ltd",
    "wof:placetype":"venue"
},
  "geometry": {"coordinates":[-2.120133,57.134068],"type":"Point"}
}