{
  "type": "Feature",
  "properties": {
    "addr:full":"11 Lanark Square, Glengall Bridge London Greater London E14 9RE",
    "addr:housenumber":"11",
    "addr:postcode":"e14 9re",
    "addr:street":"Lanark Square Glengall Bridge",
    "iso:country":"GB",
    "sg:address":"11 Lanark Square, Glengall Bridge",
    "sg:city":"London",
    "sg:classifiers":[
        {
            "category":"Professional",
            "subcategory":"Lawyer & Legal Services",
            "type":"Services"
        }
    ],
    "sg:postcode":"E14 9RE",
    "sg:province":"Greater London",
    "sg:tags":[
        "solicitor"
    ],
    "wof:name":"Alexander Johnson",
    "wof:placetype":"venue"
},
  "geometry": {"coordinates":[-0.015389,51.495564],"type":"Point"}
}