{
  "type": "Feature",
  "properties": {
    "addr:full":"5 Stanstead Road London Greater London SE23 1HG",
    "addr:housenumber":"5",
    "addr:postcode":"se23 1hg",
    "addr:street":"Stanstead Road",
    "iso:country":"GB",
    "sg:address":"5 Stanstead Road",
    "sg:city":"London",
    "sg:classifiers":[
        {
            "category":"Home & Garden",
            "subcategory":"Home Furnishings",
            "type":"Retail Goods"
        }
    ],
    "sg:phone":"+44 20 8291 0777",
    "sg:postcode":"SE23 1HG",
    "sg:province":"Greater London",
    "sg:tags":[
        "awning",
        "canopy",
        "blinds"
    ],
    "wof:name":"Applied Blinds",
    "wof:placetype":"venue"
},
  "geometry": {"coordinates":[-0.051461,51.440357],"type":"Point"}
}