{
  "type": "Feature",
  "properties": {
    "iso:country":"GB",
    "sg:address":"35 Rossendale Clo",
    "sg:city":"Birkenhead",
    "sg:classifiers":[
        {
            "category":"Retail",
            "subcategory":"Driving School",
            "type":"Services"
        }
    ],
    "sg:phone":"+44 151 653 6809",
    "sg:postcode":"L43 9QP",
    "sg:province":"Merseyside",
    "wof:name":"Top Gear School Of Motoring",
    "wof:placetype":"venue"
},
  "geometry": {"coordinates":[-3.068609,53.380264],"type":"Point"}
}