{
  "type": "Feature",
  "properties": {
    "addr:full":"Eweford Farm Dunbar East Lothian EH42 1RF",
    "addr:postcode":"eh42 1rf",
    "iso:country":"GB",
    "sg:address":"Eweford Farm",
    "sg:city":"Dunbar",
    "sg:classifiers":[
        {
            "category":"Farming",
            "subcategory":"Crops",
            "type":"Manufacturing & Wholesale Goods"
        },
        {
            "category":"Farming",
            "subcategory":"Livestock Farm",
            "type":"Manufacturing & Wholesale Goods"
        }
    ],
    "sg:phone":"+44 1368 862218",
    "sg:postcode":"EH42 1RF",
    "sg:province":"East Lothian",
    "sg:tags":[
        "arable",
        "others"
    ],
    "wof:name":"Alex Taylor",
    "wof:placetype":"venue"
},
  "geometry": {"coordinates":[-2.5157740116,56.0019493103],"type":"Point"}
}