{
  "type": "Feature",
  "properties": {
    "iso:country":"GB",
    "sg:address":"James House, Worsley Road Industrial Estate, Worsley Road",
    "sg:city":"Bolton",
    "sg:classifiers":[
        {
            "category":"Building & Trades",
            "subcategory":"Construction",
            "type":"Services"
        }
    ],
    "sg:phone":"+44 1204 705777",
    "sg:postcode":"BL4 9NL",
    "sg:province":"Lancashire",
    "sg:tags":[
        "decorator",
        "painter"
    ],
    "wof:name":"M J Wyatt (Decorators) Ltd.",
    "wof:placetype":"venue"
},
  "geometry": {"coordinates":[-2.3998188972,53.5427246094],"type":"Point"}
}