{
  "type": "Feature",
  "properties": {
    "iso:country":"GB",
    "sg:address":"The Green, Glapwell",
    "sg:city":"Chesterfield",
    "sg:classifiers":[
        {
            "category":"Health Services",
            "subcategory":"Doctor",
            "type":"Services"
        }
    ],
    "sg:phone":"+44 1246 825487",
    "sg:postcode":"S44 5LW",
    "sg:province":"Derbyshire",
    "sg:tags":[
        "practitioners"
    ],
    "wof:name":"J P Cook",
    "wof:placetype":"venue"
},
  "geometry": {"coordinates":[-1.286619,53.187019],"type":"Point"}
}