{
  "type": "Feature",
  "properties": {
    "addr:full":"16-17 Bush Row, St Thomas' Green Haverfordwest Pembrokeshire SA61 1RJ",
    "addr:housenumber":"16-17",
    "addr:postcode":"sa61 1rj",
    "addr:street":"Bush Row;' Green",
    "iso:country":"GB",
    "sg:address":"16-17 Bush Row, St Thomas' Green",
    "sg:city":"Haverfordwest",
    "sg:classifiers":[
        {
            "category":"Shopping",
            "subcategory":"Pharmacy",
            "type":"Retail Goods"
        }
    ],
    "sg:phone":"+44 1437 762667",
    "sg:postcode":"SA61 1RJ",
    "sg:province":"Pembrokeshire",
    "sg:tags":[
        "pharmacist",
        "chemist"
    ],
    "wof:name":"Lloyds Pharmacy",
    "wof:placetype":"venue"
},
  "geometry": {"coordinates":[-4.96992,51.799191],"type":"Point"}
}