{
  "type": "Feature",
  "properties": {
    "addr:full":"Po Box 607 Whitecross Education Centre Lancaster Lancashire LA1 3SH",
    "addr:housenumber":"po",
    "addr:postcode":"la1 3sh",
    "addr:street":"Box 607 Whitecross",
    "iso:country":"GB",
    "sg:address":"Po Box 607 Whitecross Education Centre",
    "sg:city":"Lancaster",
    "sg:classifiers":[
        {
            "category":"Government",
            "subcategory":"Office",
            "type":"Public Place"
        }
    ],
    "sg:phone":"+44 1524 63243",
    "sg:postcode":"LA1 3SH",
    "sg:province":"Lancashire",
    "sg:tags":[
        "project",
        "gov",
        "community"
    ],
    "wof:name":"Community Services",
    "wof:placetype":"venue"
},
  "geometry": {"coordinates":[-2.7990291119,54.0445365906],"type":"Point"}
}