{
  "type": "Feature",
  "properties": {
    "addr:full":"23 Charlesworth Avenue, Hendley Wigan Lancashire WN2 4NU",
    "addr:housenumber":"23",
    "addr:postcode":"wn2 4nu",
    "addr:street":"Charlesworth Avenue",
    "iso:country":"GB",
    "sg:address":"23 Charlesworth Avenue, Hendley",
    "sg:city":"Wigan",
    "sg:classifiers":[
        {
            "category":"Bars & Pubs",
            "subcategory":"Nightclub",
            "type":"Food & Drink"
        }
    ],
    "sg:postcode":"WN2 4NU",
    "sg:province":"Lancashire",
    "sg:tags":[
        "karaoke"
    ],
    "wof:name":"Starlight Karaoke",
    "wof:placetype":"venue"
},
  "geometry": {"coordinates":[-2.56598,53.527924],"type":"Point"}
}