{
  "type": "Feature",
  "properties": {
    "addr:full":"53 West Wycombe Road High Wycombe Buckinghamshire HP11 2LR",
    "addr:housenumber":"53",
    "addr:postcode":"hp11 2lr",
    "addr:street":"West Wycombe Road",
    "iso:country":"GB",
    "sg:address":"53 West Wycombe Road",
    "sg:city":"High Wycombe",
    "sg:classifiers":[
        {
            "category":"Health Services",
            "subcategory":"Clinic",
            "type":"Services"
        },
        {
            "category":"Health Services",
            "subcategory":"Chiropractor",
            "type":"Services"
        }
    ],
    "sg:phone":"+44 1494 558061",
    "sg:postcode":"HP11 2LR",
    "sg:province":"Buckinghamshire",
    "sg:tags":[
        "injury",
        "sport"
    ],
    "wof:name":"West Wycombe Chiropractic Clinic",
    "wof:placetype":"venue"
},
  "geometry": {"coordinates":[-0.761996,51.634007],"type":"Point"}
}