{
  "type": "Feature",
  "properties": {
    "addr:full":"Manor Farm, Salton York North Yorkshire YO62 6RN",
    "addr:postcode":"north;yo62 6rn",
    "addr:street":"Manor;Salton",
    "iso:country":"GB",
    "sg:address":"Manor Farm, Salton",
    "sg:city":"York",
    "sg:classifiers":[
        {
            "category":"Farming",
            "subcategory":"Farm",
            "type":"Manufacturing & Wholesale Goods"
        }
    ],
    "sg:phone":"+44 1751 431295",
    "sg:postcode":"YO62 6RN",
    "sg:province":"North Yorkshire",
    "sg:tags":[
        "mixed",
        "crop"
    ],
    "wof:name":"W Bentley",
    "wof:placetype":"venue"
},
  "geometry": {"coordinates":[-0.903603971,54.2114257812],"type":"Point"}
}