{
  "type": "Feature",
  "properties": {
    "iso:country":"GB",
    "sg:address":"32 Sandhill",
    "sg:city":"Newcastle-upon-tyne",
    "sg:classifiers":[
        {
            "category":"Bars & Pubs",
            "type":"Food & Drink"
        }
    ],
    "sg:phone":"+44 191 261 1037",
    "sg:postcode":"NE1 3JF",
    "sg:province":"Tyne and Wear",
    "sg:tags":[
        "pubs",
        "inn"
    ],
    "wof:name":"The Red House",
    "wof:placetype":"venue"
},
  "geometry": {"coordinates":[-1.608179,54.968685],"type":"Point"}
}