{
  "type": "Feature",
  "properties": {
    "addr:full":"72c Skinnergate Darlington Durham DL3 7LL",
    "addr:housenumber":"72c",
    "addr:postcode":"dl3 7ll",
    "addr:street":"Skinnergate Darlington",
    "iso:country":"GB",
    "sg:address":"72c Skinnergate",
    "sg:city":"Darlington",
    "sg:classifiers":[
        {
            "category":"Shopping",
            "subcategory":"Clothing, Apparel, & Fashions",
            "type":"Retail Goods"
        }
    ],
    "sg:postcode":"DL3 7LL",
    "sg:province":"Durham",
    "sg:tags":[
        "haberdasher"
    ],
    "wof:name":"Normans House of Sewing",
    "wof:placetype":"venue"
},
  "geometry": {"coordinates":[-1.557308,54.524933],"type":"Point"}
}