{
  "type": "Feature",
  "properties": {
    "iso:country":"GB",
    "sg:address":"69 Leighton Rd",
    "sg:city":"Leighton Buzzard",
    "sg:classifiers":[
        {
            "category":"Home & Garden",
            "subcategory":"Building Materials",
            "type":"Retail Goods"
        }
    ],
    "sg:phone":"+44 1296 682101",
    "sg:postcode":"LU7 0NN",
    "sg:province":"Bedfordshire",
    "sg:tags":[
        "ventilator",
        "ventilation",
        "system"
    ],
    "wof:name":"Ventilation Services",
    "wof:placetype":"venue"
},
  "geometry": {"coordinates":[-0.7154480219,51.8968849182],"type":"Point"}
}