{
  "type": "Feature",
  "properties": {
    "addr:full":"Unit 1, Hilldrop Lane, Ramsbury Marlborough Berkshire SN8 2RB",
    "addr:housenumber":"unit 1",
    "addr:postcode":"sn8 2rb",
    "addr:street":"Hilldrop Lane",
    "iso:country":"GB",
    "sg:address":"Unit 1, Hilldrop Lane, Ramsbury",
    "sg:city":"Marlborough",
    "sg:classifiers":[
        {
            "category":"Education",
            "subcategory":"Special Training",
            "type":"Public Place"
        }
    ],
    "sg:phone":"+44 1672 520101",
    "sg:postcode":"SN8 2RB",
    "sg:province":"Berkshire",
    "sg:tags":[
        "product",
        "centre"
    ],
    "wof:name":"Esperan Ltd.",
    "wof:placetype":"venue"
},
  "geometry": {"coordinates":[-1.6135129929,51.4435348511],"type":"Point"}
}