{
  "type": "Feature",
  "properties": {
    "addr:full":"13 Paddock Close, Charlton Heights Wantage Berkshire OX12 7EQ",
    "addr:housenumber":"13",
    "addr:postcode":"ox12 7eq",
    "addr:street":"Paddock Close",
    "iso:country":"GB",
    "sg:address":"13 Paddock Close, Charlton Heights",
    "sg:city":"Wantage",
    "sg:classifiers":[
        {
            "category":"Building & Trades",
            "subcategory":"Plumbing",
            "type":"Services"
        }
    ],
    "sg:phone":"+44 1235 868489",
    "sg:postcode":"OX12 7EQ",
    "sg:province":"Berkshire",
    "sg:tags":[
        "plumber",
        "central",
        "heating"
    ],
    "wof:name":"S C MILES & SON",
    "wof:placetype":"venue"
},
  "geometry": {"coordinates":[-1.4153319597,51.5950164795],"type":"Point"}
}