{
  "type": "Feature",
  "properties": {
    "iso:country":"GB",
    "sg:address":"14 East Union Street",
    "sg:city":"Manchester",
    "sg:classifiers":[
        {
            "category":"Professional",
            "subcategory":"Engineering",
            "type":"Services"
        }
    ],
    "sg:phone":"+44 161 872 1704",
    "sg:postcode":"M16 9AE",
    "sg:province":"Cheshire",
    "sg:tags":[
        "gas",
        "engineer"
    ],
    "wof:name":"A E Woolley & Sons",
    "wof:placetype":"venue"
},
  "geometry": {"coordinates":[-2.267062,53.465679],"type":"Point"}
}