{
  "type": "Feature",
  "properties": {
    "iso:country":"GB",
    "sg:address":"60 Leinster Avenue",
    "sg:city":"Bristol",
    "sg:classifiers":[
        {
            "category":"Food & Beverages",
            "subcategory":"Meat & Fish",
            "type":"Retail Goods"
        }
    ],
    "sg:phone":"+44 117 966 3783",
    "sg:postcode":"BS4 1NL",
    "sg:province":"City of Bristol",
    "sg:tags":[
        "chip"
    ],
    "wof:name":"S & J Fishbar",
    "wof:placetype":"venue"
},
  "geometry": {"coordinates":[-2.592508,51.425495],"type":"Point"}
}