{
  "type": "Feature",
  "properties": {
    "addr:full":"71 Alvin Street Gloucester Gloucestershire GL1 3EH",
    "addr:housenumber":"71",
    "addr:postcode":"gl1 3eh",
    "addr:street":"Alvin Street",
    "iso:country":"GB",
    "sg:address":"71 Alvin Street",
    "sg:city":"Gloucester",
    "sg:classifiers":[
        {
            "category":"Food & Beverages",
            "subcategory":"Meat & Fish",
            "type":"Retail Goods"
        }
    ],
    "sg:postcode":"GL1 3EH",
    "sg:province":"Gloucestershire",
    "sg:tags":[
        "butcher"
    ],
    "wof:name":"C Duberley",
    "wof:placetype":"venue"
},
  "geometry": {"coordinates":[-2.241364,51.869091],"type":"Point"}
}