{
  "type": "Feature",
  "properties": {
    "addr:full":"76 Lemon Street Truro Cornwall TR1 2PN",
    "addr:housenumber":"76",
    "addr:postcode":"tr1 2pn",
    "addr:street":"Lemon Street",
    "iso:country":"GB",
    "sg:address":"76 Lemon Street",
    "sg:city":"Truro",
    "sg:classifiers":[
        {
            "category":"Food & Beverages",
            "subcategory":"Meat & Fish",
            "type":"Retail Goods"
        }
    ],
    "sg:phone":"+44 1872 273429",
    "sg:postcode":"TR1 2PN",
    "sg:province":"Cornwall",
    "sg:tags":[
        "chip"
    ],
    "wof:name":"Kernow Plaice",
    "wof:placetype":"venue"
},
  "geometry": {"coordinates":[-5.051921,50.262157],"type":"Point"}
}