{
  "type": "Feature",
  "properties": {
    "addr:full":"International House Derby Derbyshire DE1 2RF",
    "addr:postcode":"de1 2rf",
    "iso:country":"GB",
    "sg:address":"International House",
    "sg:city":"Derby",
    "sg:classifiers":[
        {
            "category":"Professional",
            "subcategory":"Employment Agencies",
            "type":"Services"
        }
    ],
    "sg:postcode":"DE1 2RF",
    "sg:province":"Derbyshire",
    "sg:tags":[
        "consultant"
    ],
    "wof:name":"Anthony Graham Associates Ltd.",
    "wof:placetype":"venue"
},
  "geometry": {"coordinates":[-1.4836839437,52.9251708984],"type":"Point"}
}