{
  "type": "Feature",
  "properties": {
    "iso:country":"GB",
    "sg:address":"23-25 Leinster Square",
    "sg:city":"London",
    "sg:classifiers":[
        {
            "category":"Travel",
            "subcategory":"Hotels & Motels",
            "type":"Entertainment"
        }
    ],
    "sg:phone":"+44 20 7727 8133",
    "sg:postcode":"W2 4NE",
    "sg:province":"Greater London",
    "wof:name":"Cliston Court Hotel",
    "wof:placetype":"venue"
},
  "geometry": {"coordinates":[-0.191619,51.51421],"type":"Point"}
}