{
  "type": "Feature",
  "properties": {
    "addr:full":"47 Brunswick Place London Greater London N1 6EB",
    "addr:housenumber":"47",
    "addr:postcode":"n1 6eb",
    "addr:street":"Brunswick Place",
    "iso:country":"GB",
    "sg:address":"47 Brunswick Place",
    "sg:city":"London",
    "sg:classifiers":[
        {
            "category":"Manufacturing",
            "subcategory":"Apparel",
            "type":"Manufacturing & Wholesale Goods"
        }
    ],
    "sg:phone":"+44 116 256 6000",
    "sg:postcode":"N1 6EB",
    "sg:province":"Greater London",
    "sg:tags":[
        "mnfr",
        "footwear"
    ],
    "wof:name":"Bracefix Ltd.",
    "wof:placetype":"venue"
},
  "geometry": {"coordinates":[-0.085536,51.527401],"type":"Point"}
}