{
  "type": "Feature",
  "properties": {
    "addr:full":"5 The Causeway, Great Baddow Chelmsford Essex CM2 7JX",
    "addr:housenumber":"5",
    "addr:postcode":"cm2 7jx",
    "addr:street":"The Causeway",
    "iso:country":"GB",
    "sg:address":"5 The Causeway, Great Baddow",
    "sg:city":"Chelmsford",
    "sg:classifiers":[
        {
            "category":"Professional",
            "subcategory":"Art Services",
            "type":"Services"
        }
    ],
    "sg:phone":"+44 1245 477684",
    "sg:postcode":"CM2 7JX",
    "sg:province":"Essex",
    "sg:tags":[
        "photographer"
    ],
    "wof:name":"Baddow Photography",
    "wof:placetype":"venue"
},
  "geometry": {"coordinates":[0.5019080043,51.717124939],"type":"Point"}
}