{
  "type": "Feature",
  "properties": {
    "addr:full":"Kidderminster Road Droitwich Worcestershire WR9 9AY",
    "addr:postcode":"wr9 9ay",
    "addr:street":"Kidderminster Road",
    "iso:country":"GB",
    "sg:address":"Kidderminster Road",
    "sg:city":"Droitwich",
    "sg:classifiers":[
        {
            "category":"Autos & Motor Vehicles",
            "subcategory":"Automobile Sales",
            "type":"Retail Goods"
        },
        {
            "category":"Retail",
            "subcategory":"Auto Repair",
            "type":"Services"
        }
    ],
    "sg:phone":"+44 1905 772909",
    "sg:postcode":"WR9 9AY",
    "sg:province":"Worcestershire",
    "sg:tags":[
        "modification",
        "garage",
        "car"
    ],
    "wof:name":"Grantham Bridge Motors",
    "wof:placetype":"venue"
},
  "geometry": {"coordinates":[-2.1537868977,52.2715950012],"type":"Point"}
}