{
  "type": "Feature",
  "properties": {
    "addr:full":"Boldock Street Ware Hertfordshire SG12 9DR",
    "addr:postcode":"sg12 9dr",
    "addr:street":"Boldock Street Ware",
    "iso:country":"GB",
    "sg:address":"Boldock Street",
    "sg:city":"Ware",
    "sg:classifiers":[
        {
            "category":"Travel",
            "subcategory":"Hotels & Motels",
            "type":"Entertainment"
        }
    ],
    "sg:phone":"+44 1920 409955",
    "sg:postcode":"SG12 9DR",
    "sg:province":"Hertfordshire",
    "wof:name":"Zoffany Hotels Ltd",
    "wof:placetype":"venue"
},
  "geometry": {"coordinates":[-0.0343630016,51.8132476807],"type":"Point"}
}