{
  "type": "Feature",
  "properties": {
    "addr:full":"80 The Ridings, Saughall Chester Cheshire CH1 6AX",
    "addr:housenumber":"80",
    "addr:postcode":"ch1 6ax",
    "addr:street":"The Ridings",
    "iso:country":"GB",
    "sg:address":"80 The Ridings, Saughall",
    "sg:city":"Chester",
    "sg:classifiers":[
        {
            "category":"Professional",
            "type":"Services"
        }
    ],
    "sg:phone":"+44 1244 881462",
    "sg:postcode":"CH1 6AX",
    "sg:province":"Cheshire",
    "sg:tags":[
        "entertainer"
    ],
    "wof:name":"Stephen Cooil",
    "wof:placetype":"venue"
},
  "geometry": {"coordinates":[-2.9552690983,53.2266998291],"type":"Point"}
}