{
  "type": "Feature",
  "properties": {
    "iso:country":"GB",
    "sg:address":"47 Bordeaux Close",
    "sg:city":"Northampton",
    "sg:classifiers":[
        {
            "category":"Food & Beverages",
            "subcategory":"Meat & Fish",
            "type":"Retail Goods"
        }
    ],
    "sg:phone":"+44 1604 583040",
    "sg:postcode":"NN5 6YR",
    "sg:province":"Northamptonshire",
    "sg:tags":[
        "chip"
    ],
    "wof:name":"Alsace Park Fish Bar",
    "wof:placetype":"venue"
},
  "geometry": {"coordinates":[-0.9630820155,52.254032135],"type":"Point"}
}