{
  "type": "Feature",
  "properties": {
    "iso:country":"GB",
    "sg:address":"95-97 High Street",
    "sg:city":"Poole",
    "sg:classifiers":[
        {
            "category":"Organizations",
            "subcategory":"Non-profit Organization",
            "type":"Services"
        }
    ],
    "sg:phone":"+44 1202 687443",
    "sg:postcode":"BH15 1AN",
    "sg:province":"Dorset",
    "sg:tags":[
        "organisation",
        "voluntary",
        "charity"
    ],
    "wof:name":"N C H Action for Children Ltd.",
    "wof:placetype":"venue"
},
  "geometry": {"coordinates":[-1.984241,50.714882],"type":"Point"}
}