{
  "type": "Feature",
  "properties": {
    "addr:full":"513 Wakefield Road Heckmondwike West Yorkshire WF15 6AU",
    "addr:housenumber":"513",
    "addr:postcode":"wf15 6au",
    "addr:street":"Wakefield Road",
    "iso:country":"GB",
    "sg:address":"513 Wakefield Road",
    "sg:city":"Heckmondwike",
    "sg:classifiers":[
        {
            "category":"Wholesale",
            "subcategory":"Sporting Goods",
            "type":"Manufacturing & Wholesale Goods"
        },
        {
            "category":"Professional",
            "subcategory":"Printing & Photocopies",
            "type":"Services"
        }
    ],
    "sg:phone":"+44 1924 404303",
    "sg:postcode":"WF15 6AU",
    "sg:province":"West Yorkshire",
    "sg:tags":[
        "engraving",
        "trophy",
        "supplier",
        "medal"
    ],
    "wof:name":"Pennine Trophies Ltd.",
    "wof:placetype":"venue"
},
  "geometry": {"coordinates":[-1.68216,53.70911],"type":"Point"}
}