{
  "type": "Feature",
  "properties": {
    "iso:country":"GB",
    "sg:address":"12a Station Road, Crayford",
    "sg:city":"Dartford",
    "sg:classifiers":[
        {
            "category":"Taxi",
            "type":"Transportation"
        }
    ],
    "sg:phone":"+44 1322 556444",
    "sg:postcode":"DA1 3QA",
    "sg:province":"Kent",
    "sg:tags":[
        "mini",
        "cab"
    ],
    "wof:name":"Central Express",
    "wof:placetype":"venue"
},
  "geometry": {"coordinates":[0.1816329956,51.4498710632],"type":"Point"}
}