{
  "type": "Feature",
  "properties": {
    "addr:full":"76 Osmaston Rd Derby Derbyshire DE1 2HZ",
    "addr:housenumber":"76",
    "addr:postcode":"de1 2hz",
    "addr:street":"Osmaston Rd",
    "iso:country":"GB",
    "sg:address":"76 Osmaston Rd",
    "sg:city":"Derby",
    "sg:classifiers":[
        {
            "category":"Autos & Motor Vehicles",
            "subcategory":"Automobile Sales",
            "type":"Retail Goods"
        }
    ],
    "sg:phone":"+44 1332 341615",
    "sg:postcode":"DE1 2HZ",
    "sg:province":"Derbyshire",
    "sg:tags":[
        "commercial"
    ],
    "wof:name":"Andy's Autos",
    "wof:placetype":"venue"
},
  "geometry": {"coordinates":[-1.474154,52.917126],"type":"Point"}
}