{
  "type": "Feature",
  "properties": {
    "addr:full":"1 Newstead Avenue, Hartshead Estate Ashton-under-lyne Greater Manchester OL6 8XB",
    "addr:housenumber":"1",
    "addr:postcode":"ol6 8xb",
    "addr:street":"Newstead Avenue Hartshead Estate",
    "iso:country":"GB",
    "sg:address":"1 Newstead Avenue, Hartshead Estate",
    "sg:city":"Ashton-under-lyne",
    "sg:classifiers":[
        {
            "category":"Building & Trades",
            "subcategory":"Plumbing",
            "type":"Services"
        }
    ],
    "sg:phone":"+44 161 330 6668",
    "sg:postcode":"OL6 8XB",
    "sg:province":"Greater Manchester",
    "sg:tags":[
        "plumber",
        "heating"
    ],
    "wof:name":"The Plumb Doctor",
    "wof:placetype":"venue"
},
  "geometry": {"coordinates":[-2.086809,53.508255],"type":"Point"}
}