{
  "type": "Feature",
  "properties": {
    "iso:country":"GB",
    "sg:address":"Clapton, Midsomer Norton",
    "sg:city":"Bath",
    "sg:classifiers":[
        {
            "category":"Bars & Pubs",
            "type":"Food & Drink"
        }
    ],
    "sg:phone":"+44 1761 413500",
    "sg:postcode":"BA3 4EB",
    "sg:province":"Somerset",
    "sg:tags":[
        "pubs",
        "inn"
    ],
    "wof:name":"The Crown Inn",
    "wof:placetype":"venue"
},
  "geometry": {"coordinates":[-2.507925,51.284355],"type":"Point"}
}