{
  "type": "Feature",
  "properties": {
    "addr:full":"5 Daniells Welwyn Garden City Hertfordshire AL7 1QY",
    "addr:housenumber":"5",
    "addr:postcode":"al7 1qy",
    "addr:street":"Daniells Welwyn",
    "iso:country":"GB",
    "sg:address":"5 Daniells",
    "sg:city":"Welwyn Garden City",
    "sg:classifiers":[
        {
            "category":"Home & Garden",
            "subcategory":"Home Furnishings",
            "type":"Retail Goods"
        },
        {
            "category":"Home & Garden",
            "subcategory":"Building Materials",
            "type":"Retail Goods"
        }
    ],
    "sg:phone":"+44 1707 377691",
    "sg:postcode":"AL7 1QY",
    "sg:province":"Hertfordshire",
    "sg:tags":[
        "installers",
        "planner",
        "kitchen",
        "furnishers"
    ],
    "wof:name":"Gelmec Kitchens",
    "wof:placetype":"venue"
},
  "geometry": {"coordinates":[-0.180935,51.801987],"type":"Point"}
}