{
  "type": "Feature",
  "properties": {
    "iso:country":"GB",
    "sg:address":"373 Station Road",
    "sg:city":"Harrow",
    "sg:classifiers":[
        {
            "category":"Bars & Pubs",
            "type":"Food & Drink"
        }
    ],
    "sg:postcode":"HA1 2AW",
    "sg:province":"Greater London",
    "sg:tags":[
        "pubs",
        "inn"
    ],
    "wof:name":"Moon on the Hill",
    "wof:placetype":"venue"
},
  "geometry": {"coordinates":[-0.334239,51.579544],"type":"Point"}
}