{
  "type": "Feature",
  "properties": {
    "iso:country":"GB",
    "sg:address":"56 Poets Walk, Walmer",
    "sg:city":"Deal",
    "sg:classifiers":[
        {
            "category":"Banks & Credit Unions",
            "subcategory":"Financial Services",
            "type":"Services"
        }
    ],
    "sg:postcode":"CT14 7QD",
    "sg:province":"Kent",
    "sg:tags":[
        "consultant"
    ],
    "wof:name":"Moneywise Services",
    "wof:placetype":"venue"
},
  "geometry": {"coordinates":[1.390449,51.201294],"type":"Point"}
}