{
  "type": "Feature",
  "properties": {
    "addr:full":"21 Ross Road Hereford Herefordshire HR2 7RJ",
    "addr:housenumber":"21",
    "addr:postcode":"hr2 7rj",
    "addr:street":"Ross Road",
    "iso:country":"GB",
    "sg:address":"21 Ross Road",
    "sg:city":"Hereford",
    "sg:classifiers":[
        {
            "category":"Community Center",
            "subcategory":"Youth",
            "type":"Public Place"
        },
        {
            "category":"Government",
            "subcategory":"Office",
            "type":"Public Place"
        }
    ],
    "sg:phone":"+44 1432 266050",
    "sg:postcode":"HR2 7RJ",
    "sg:province":"Herefordshire",
    "sg:tags":[
        "organisation",
        "local",
        "centre"
    ],
    "wof:name":"Hinton Youth Centre",
    "wof:placetype":"venue"
},
  "geometry": {"coordinates":[-2.720119,52.047028],"type":"Point"}
}