{
  "type": "Feature",
  "properties": {
    "addr:full":"2 Alexander Bldgs, Station App Rd Coulsdon Surrey CR5 2NS",
    "addr:housenumber":"2",
    "addr:postcode":"cr5 2ns",
    "addr:street":"Alexander Bldgs;App Rd",
    "iso:country":"GB",
    "sg:address":"2 Alexander Bldgs, Station App Rd",
    "sg:city":"Coulsdon",
    "sg:classifiers":[
        {
            "category":"Professional",
            "subcategory":"Management & Consulting",
            "type":"Services"
        }
    ],
    "sg:postcode":"CR5 2NS",
    "sg:province":"Surrey",
    "sg:tags":[
        "consultant",
        "business"
    ],
    "wof:name":"Drummond & Co (Human Resource Specialist",
    "wof:placetype":"venue"
},
  "geometry": {"coordinates":[-0.1391790062,51.3189239502],"type":"Point"}
}