{
  "type": "Feature",
  "properties": {
    "iso:country":"GB",
    "sg:address":"98a Wilfred Gro, The Meadows",
    "sg:city":"Nottingham",
    "sg:classifiers":[
        {
            "category":"Building & Trades",
            "subcategory":"Construction",
            "type":"Services"
        }
    ],
    "sg:phone":"+44 115 952 3941",
    "sg:postcode":"NG2 2DU",
    "sg:province":"Nottinghamshire",
    "sg:tags":[
        "roofing"
    ],
    "wof:name":"J Wright",
    "wof:placetype":"venue"
},
  "geometry": {"coordinates":[-1.1458799839,52.9408302307],"type":"Point"}
}