{
  "type": "Feature",
  "properties": {
    "addr:full":"Elm Cottage, Otley Bottom Ipswich Suffolk IP6 9NG",
    "addr:postcode":"ip6 9ng",
    "addr:street":"Bottom",
    "iso:country":"GB",
    "sg:address":"Elm Cottage, Otley Bottom",
    "sg:city":"Ipswich",
    "sg:classifiers":[
        {
            "category":"Transit Center",
            "subcategory":"Passenger",
            "type":"Transportation"
        }
    ],
    "sg:phone":"+44 1473 890406",
    "sg:postcode":"IP6 9NG",
    "sg:province":"Suffolk",
    "sg:tags":[
        "boarding",
        "kennel",
        "catteries"
    ],
    "wof:name":"S Chaplin",
    "wof:placetype":"venue"
},
  "geometry": {"coordinates":[1.22044,52.150902],"type":"Point"}
}