{
  "type": "Feature",
  "properties": {
    "addr:full":"35 Market Pl Barnard Castle Cumbria DL12 0RJ",
    "addr:housenumber":"35",
    "addr:postcode":"dl12 0rj",
    "addr:street":"Market Pl",
    "iso:country":"GB",
    "sg:address":"35 Market Pl",
    "sg:city":"Barnard Castle",
    "sg:classifiers":[
        {
            "category":"Food & Beverages",
            "subcategory":"Meat & Fish",
            "type":"Retail Goods"
        }
    ],
    "sg:phone":"+44 1833 640242",
    "sg:postcode":"DL12 0RJ",
    "sg:province":"Cumbria",
    "sg:tags":[
        "butcher"
    ],
    "wof:name":"D Howe",
    "wof:placetype":"venue"
},
  "geometry": {"coordinates":[-2.0835599899,54.6244468689],"type":"Point"}
}