{
  "type": "Feature",
  "properties": {
    "iso:country":"GB",
    "sg:address":"Holborn Farm Sawmill, Pumphouse Lane",
    "sg:city":"Redditch",
    "sg:classifiers":[
        {
            "category":"Manufacturing",
            "subcategory":"Lumber",
            "type":"Manufacturing & Wholesale Goods"
        }
    ],
    "sg:phone":"+44 1527 543688",
    "sg:postcode":"B97 5PH",
    "sg:province":"Warwickshire",
    "sg:tags":[
        "importer",
        "merchants",
        "agent",
        "timber"
    ],
    "wof:name":"Partridge",
    "wof:placetype":"venue"
},
  "geometry": {"coordinates":[-1.941267,52.30727],"type":"Point"}
}