{
  "type": "Feature",
  "properties": {
    "addr:full":"3 Sidford Close Bolton Lancashire BL3 1RW",
    "addr:housenumber":"3",
    "addr:postcode":"bl3 1rw",
    "addr:street":"Sidford Close",
    "iso:country":"GB",
    "sg:address":"3 Sidford Close",
    "sg:city":"Bolton",
    "sg:classifiers":[
        {
            "category":"Professional",
            "subcategory":"Engineering",
            "type":"Services"
        }
    ],
    "sg:phone":"+44 1204 531887",
    "sg:postcode":"BL3 1RW",
    "sg:province":"Lancashire",
    "sg:tags":[
        "engineer"
    ],
    "wof:name":"Integrated Ultrasonic Processors Ltd",
    "wof:placetype":"venue"
},
  "geometry": {"coordinates":[-2.4006700516,53.5700531006],"type":"Point"}
}