{
  "type": "Feature",
  "properties": {
    "addr:full":"Dental Surgery, 107 Hempstead Road Watford Hertfordshire WD17 3HE",
    "addr:housenumber":"107",
    "addr:postcode":"wd17 3he",
    "addr:street":"Hempstead Road",
    "iso:country":"GB",
    "sg:address":"Dental Surgery, 107 Hempstead Road",
    "sg:city":"Watford",
    "sg:classifiers":[
        {
            "category":"Health Services",
            "subcategory":"Dentist",
            "type":"Services"
        }
    ],
    "sg:postcode":"WD17 3HE",
    "sg:province":"Hertfordshire",
    "wof:name":"M Mullish",
    "wof:placetype":"venue"
},
  "geometry": {"coordinates":[-0.3907189965,51.6521186829],"type":"Point"}
}