{
  "type": "Feature",
  "properties": {
    "addr:full":"Maes Y Llan Lane, Ruabon Wrexham Wrexham LL14 6AE",
    "addr:postcode":"ll14 6ae",
    "addr:street":"Maes Y Llan Lane",
    "iso:country":"GB",
    "sg:address":"Maes Y Llan Lane, Ruabon",
    "sg:city":"Wrexham",
    "sg:classifiers":[
        {
            "category":"Education",
            "subcategory":"School",
            "type":"Public Place"
        },
        {
            "category":"Government",
            "subcategory":"Office",
            "type":"Public Place"
        }
    ],
    "sg:phone":"+44 1978 820991",
    "sg:postcode":"LL14 6AE",
    "sg:province":"Wrexham",
    "sg:tags":[
        "local",
        "authority"
    ],
    "wof:name":"Ysgol Maes Y Llan County Primary School",
    "wof:placetype":"venue"
},
  "geometry": {"coordinates":[-3.0369119644,52.9887275696],"type":"Point"}
}