{
  "type": "Feature",
  "properties": {
    "addr:full":"40 Station Road Egham Surrey TW20 9LF",
    "addr:housenumber":"40",
    "addr:postcode":"tw20 9lf",
    "addr:street":"Station Road",
    "iso:country":"GB",
    "sg:address":"40 Station Road",
    "sg:city":"Egham",
    "sg:classifiers":[
        {
            "category":"Bars & Pubs",
            "type":"Food & Drink"
        }
    ],
    "sg:phone":"+44 1784 430151",
    "sg:postcode":"TW20 9LF",
    "sg:province":"Surrey",
    "sg:tags":[
        "pubs",
        "inn"
    ],
    "wof:name":"The Tap & Spile",
    "wof:placetype":"venue"
},
  "geometry": {"coordinates":[-0.5478150249,51.4301567078],"type":"Point"}
}