{
  "type": "Feature",
  "properties": {
    "addr:full":"159 High St Pershore Worcestershire WR10 1EQ",
    "addr:housenumber":"159",
    "addr:postcode":"wr10 1eq",
    "addr:street":"High St",
    "iso:country":"GB",
    "sg:address":"159 High St",
    "sg:city":"Pershore",
    "sg:classifiers":[
        {
            "category":"Manufacturing",
            "subcategory":"Tools & Machinery",
            "type":"Manufacturing & Wholesale Goods"
        }
    ],
    "sg:phone":"+44 1386 555909",
    "sg:postcode":"WR10 1EQ",
    "sg:province":"Worcestershire",
    "wof:name":"Eternal Tools",
    "wof:placetype":"venue"
},
  "geometry": {"coordinates":[-2.0803859234,52.1141967773],"type":"Point"}
}