{
  "type": "Feature",
  "properties": {
    "iso:country":"GB",
    "sg:address":"71 Hornhill Road",
    "sg:city":"Rickmansworth",
    "sg:classifiers":[
        {
            "category":"Building & Trades",
            "subcategory":"Plumbing",
            "type":"Services"
        }
    ],
    "sg:postcode":"WD3 9TG",
    "sg:province":"Hertfordshire",
    "sg:tags":[
        "heating"
    ],
    "wof:name":"Peter J Floyd",
    "wof:placetype":"venue"
},
  "geometry": {"coordinates":[-0.512674,51.620693],"type":"Point"}
}