{
  "type": "Feature",
  "properties": {
    "iso:country":"GB",
    "sg:address":"100 Ashmill Street",
    "sg:city":"London",
    "sg:classifiers":[
        {
            "category":"Professional",
            "subcategory":"Management & Consulting",
            "type":"Services"
        }
    ],
    "sg:postcode":"NW1 6RA",
    "sg:province":"Greater London",
    "sg:tags":[
        "consultant",
        "business"
    ],
    "wof:name":"Merlins Consulting Ltd.",
    "wof:placetype":"venue"
},
  "geometry": {"coordinates":[-0.1659989953,51.5229682922],"type":"Point"}
}