{
  "type": "Feature",
  "properties": {
    "addr:full":"22 Brookfield Avenue, Larkfield Aylesford Kent ME20 6RT",
    "addr:housenumber":"22",
    "addr:postcode":"me20 6rt",
    "addr:street":"Brookfield Avenue",
    "iso:country":"GB",
    "sg:address":"22 Brookfield Avenue, Larkfield",
    "sg:city":"Aylesford",
    "sg:classifiers":[
        {
            "category":"Personal",
            "type":"Services"
        }
    ],
    "sg:phone":"+44 1622 791178",
    "sg:postcode":"ME20 6RT",
    "sg:province":"Kent",
    "sg:tags":[
        "slimming",
        "product"
    ],
    "wof:name":"Slimming World",
    "wof:placetype":"venue"
},
  "geometry": {"coordinates":[0.444991,51.310623],"type":"Point"}
}