{
  "type": "Feature",
  "properties": {
    "iso:country":"GB",
    "sg:address":"141 Holburn Street",
    "sg:city":"Aberdeen",
    "sg:classifiers":[
        {
            "category":"Shopping",
            "subcategory":"Florist",
            "type":"Retail Goods"
        }
    ],
    "sg:phone":"+44 1224 592734",
    "sg:postcode":"AB10 6BN",
    "sg:province":"Aberdeen City",
    "wof:name":"The Flower Shop",
    "wof:placetype":"venue"
},
  "geometry": {"coordinates":[-2.113541,57.1395],"type":"Point"}
}