{
  "type": "Feature",
  "properties": {
    "addr:full":"P O Box 170 Stratford-upon-avon Warwickshire CV37 6ZG",
    "addr:housenumber":"170",
    "addr:postcode":"cv37 6zg",
    "addr:street":"P O Box",
    "iso:country":"GB",
    "sg:address":"P O Box 170",
    "sg:city":"Stratford-upon-avon",
    "sg:classifiers":[
        {
            "category":"Fast Food",
            "type":"Food & Drink"
        },
        {
            "category":"Restaurant",
            "type":"Food & Drink"
        }
    ],
    "sg:phone":"+44 7836 769499",
    "sg:postcode":"CV37 6ZG",
    "sg:province":"Warwickshire",
    "sg:tags":[
        "away",
        "take"
    ],
    "wof:name":"Countess of Evesham",
    "wof:placetype":"venue"
},
  "geometry": {"coordinates":[-1.7072689533,52.1941337585],"type":"Point"}
}