{
  "type": "Feature",
  "properties": {
    "addr:full":"67 Engleheart Rd Catford Greater London SE6 2HN",
    "addr:housenumber":"67",
    "addr:postcode":"se6 2hn",
    "addr:street":"Engleheart Rd",
    "iso:country":"GB",
    "sg:address":"67 Engleheart Rd",
    "sg:city":"Catford",
    "sg:classifiers":[
        {
            "category":"Social Services",
            "type":"Services"
        }
    ],
    "sg:phone":"+44 20 8698 3775",
    "sg:postcode":"SE6 2HN",
    "sg:province":"Greater London",
    "sg:tags":[
        "need",
        "disability",
        "special"
    ],
    "wof:name":"Lewisham Community Transport",
    "wof:placetype":"venue"
},
  "geometry": {"coordinates":[-0.0152200004,51.4439582825],"type":"Point"}
}