{
  "type": "Feature",
  "properties": {
    "iso:country":"GB",
    "sg:address":"1 Mill Lane, Hilton",
    "sg:city":"Derby",
    "sg:classifiers":[
        {
            "category":"Travel",
            "subcategory":"Hotels & Motels",
            "type":"Entertainment"
        }
    ],
    "sg:phone":"+44 1283 732304",
    "sg:postcode":"DE65 5GP",
    "sg:province":"Derbyshire",
    "wof:name":"Hilton House Hotel Ltd.",
    "wof:placetype":"venue"
},
  "geometry": {"coordinates":[-1.639239,52.872337],"type":"Point"}
}