{
  "type": "Feature",
  "properties": {
    "iso:country":"GB",
    "sg:address":"286-288 Ewell Road",
    "sg:city":"Surbiton",
    "sg:classifiers":[
        {
            "category":"Restaurant",
            "type":"Food & Drink"
        }
    ],
    "sg:phone":"+44 20 8399 0749",
    "sg:postcode":"KT6 7AQ",
    "sg:province":"Surrey",
    "sg:tags":[
        "indian",
        "-"
    ],
    "wof:name":"Sarada Indian Restaurant",
    "wof:placetype":"venue"
},
  "geometry": {"coordinates":[-0.293604,51.384541],"type":"Point"}
}