{
  "type": "Feature",
  "properties": {
    "addr:full":"Sutherland Road, Longton Stoke-on-trent Staffordshire ST9 0DQ",
    "addr:postcode":"staffordshire st9 0dq",
    "addr:street":"Sutherland Road",
    "iso:country":"GB",
    "sg:address":"Sutherland Road, Longton",
    "sg:city":"Stoke-on-trent",
    "sg:classifiers":[
        {
            "category":"Utilities",
            "subcategory":"Refuse",
            "type":"Services"
        }
    ],
    "sg:phone":"+44 1782 324806",
    "sg:postcode":"ST9 0DQ",
    "sg:province":"Staffordshire",
    "sg:tags":[
        "skip",
        "hire"
    ],
    "wof:name":"Think Green Skip Hire",
    "wof:placetype":"venue"
},
  "geometry": {"coordinates":[-2.0661799908,53.0237617493],"type":"Point"}
}