{
  "type": "Feature",
  "properties": {
    "iso:country":"GB",
    "sg:address":"111 Greenock Road",
    "sg:city":"Bishopton",
    "sg:classifiers":[
        {
            "category":"Shopping",
            "subcategory":"Pharmacy",
            "type":"Retail Goods"
        }
    ],
    "sg:phone":"+44 1505 862370",
    "sg:postcode":"PA7 5AX",
    "sg:province":"Renfrewshire",
    "sg:tags":[
        "pharmacist",
        "dispensing",
        "chemist"
    ],
    "wof:name":"Andrew Hughes Chemists",
    "wof:placetype":"venue"
},
  "geometry": {"coordinates":[-4.499544,55.905113],"type":"Point"}
}