{
  "type": "Feature",
  "properties": {
    "iso:country":"GB",
    "sg:address":"Po Box 39",
    "sg:city":"Prestwick",
    "sg:classifiers":[
        {
            "category":"Professional",
            "subcategory":"Management & Consulting",
            "type":"Services"
        }
    ],
    "sg:phone":"+44 1292 671555",
    "sg:postcode":"KA9 1JG",
    "sg:province":"South Ayrshire",
    "sg:tags":[
        "consultant",
        "business"
    ],
    "wof:name":"G P B Management Consultancy",
    "wof:placetype":"venue"
},
  "geometry": {"coordinates":[-4.613889,55.494736],"type":"Point"}
}