{
  "type": "Feature",
  "properties": {
    "addr:full":"Church Rd, Distington Workington Cumbria CA14 5TE",
    "addr:postcode":"ca14 5te",
    "addr:street":"Church Rd",
    "iso:country":"GB",
    "sg:address":"Church Rd, Distington",
    "sg:city":"Workington",
    "sg:classifiers":[
        {
            "category":"Community Center",
            "type":"Public Place"
        }
    ],
    "sg:phone":"+44 1946 834297",
    "sg:postcode":"CA14 5TE",
    "sg:province":"Cumbria",
    "sg:tags":[
        "centre"
    ],
    "wof:name":"Distington Community Centre",
    "wof:placetype":"venue"
},
  "geometry": {"coordinates":[-3.5388290882,54.5976715088],"type":"Point"}
}