{
  "type": "Feature",
  "properties": {
    "addr:full":"48 Vicary Crescent Milford Haven Pembrokeshire SA73 2QH",
    "addr:housenumber":"48",
    "addr:postcode":"sa73 2qh",
    "addr:street":"Vicary Crescent",
    "iso:country":"GB",
    "sg:address":"48 Vicary Crescent",
    "sg:city":"Milford Haven",
    "sg:classifiers":[
        {
            "category":"Health Services",
            "subcategory":"Doctor",
            "type":"Services"
        }
    ],
    "sg:postcode":"SA73 2QH",
    "sg:province":"Pembrokeshire",
    "sg:tags":[
        "\\n"
    ],
    "sg:website":"not done yet",
    "wof:name":"Ra Energy",
    "wof:placetype":"venue"
},
  "geometry": {"coordinates":[-5.0270438194,51.7168083191],"type":"Point"}
}