{
  "type": "Feature",
  "properties": {
    "iso:country":"GB",
    "sg:address":"Old Rectory Broughton Poggs, Filkins",
    "sg:city":"Lechlade",
    "sg:classifiers":[
        {
            "category":"Professional",
            "subcategory":"Art Services",
            "type":"Services"
        }
    ],
    "sg:phone":"+44 1367 860511",
    "sg:postcode":"GL7 3JH",
    "sg:province":"Gloucestershire",
    "sg:tags":[
        "picture",
        "restoration"
    ],
    "wof:name":"B.A Christopher Hawkins",
    "wof:placetype":"venue"
},
  "geometry": {"coordinates":[-1.691909,51.694077],"type":"Point"}
}