{
  "type": "Feature",
  "properties": {
    "iso:country":"GB",
    "sg:address":"Greysich House, Greysich Lane",
    "sg:city":"Burton-on-trent",
    "sg:classifiers":[
        {
            "category":"Home & Garden",
            "subcategory":"Building Materials",
            "type":"Retail Goods"
        }
    ],
    "sg:phone":"+44 1283 550844",
    "sg:postcode":"DE15 0RH",
    "sg:province":"Derbyshire",
    "sg:tags":[
        "garage",
        "door"
    ],
    "wof:name":"The Perfect Approach Co. Ltd.",
    "wof:placetype":"venue"
},
  "geometry": {"coordinates":[-1.533847,52.800983],"type":"Point"}
}