{
  "type": "Feature",
  "properties": {
    "iso:country":"GB",
    "sg:address":"14 Eastgate Street",
    "sg:city":"Caernarfon",
    "sg:classifiers":[
        {
            "category":"Professional",
            "subcategory":"Advertising",
            "type":"Services"
        }
    ],
    "sg:phone":"+44 1286 675221",
    "sg:postcode":"LL55 1AG",
    "sg:province":"Gwynedd",
    "sg:tags":[
        "agency"
    ],
    "wof:name":"Canad Quadrant",
    "wof:placetype":"venue"
},
  "geometry": {"coordinates":[-4.275359,53.140823],"type":"Point"}
}