{
  "type": "Feature",
  "properties": {
    "addr:full":"6 High Street, Rampton Cambridge Cambridgeshire CB4 8QE",
    "addr:housenumber":"6",
    "addr:postcode":"cb4 8qe",
    "addr:street":"High Street",
    "iso:country":"GB",
    "sg:address":"6 High Street, Rampton",
    "sg:city":"Cambridge",
    "sg:classifiers":[
        {
            "category":"Bars & Pubs",
            "type":"Food & Drink"
        }
    ],
    "sg:phone":"+44 1954 251296",
    "sg:postcode":"CB4 8QE",
    "sg:province":"Cambridgeshire",
    "sg:tags":[
        "pubs",
        "inn"
    ],
    "wof:name":"The Black Horse",
    "wof:placetype":"venue"
},
  "geometry": {"coordinates":[0.131747,52.296696],"type":"Point"}
}