{
  "type": "Feature",
  "properties": {
    "addr:full":"Scallows Lane, West Wellow Romsey Hampshire SO51 6DX",
    "addr:postcode":"so51 6dx",
    "addr:street":"Scallows Lane",
    "iso:country":"GB",
    "sg:address":"Scallows Lane, West Wellow",
    "sg:city":"Romsey",
    "sg:classifiers":[
        {
            "category":"Farming",
            "subcategory":"Poultry Farm",
            "type":"Manufacturing & Wholesale Goods"
        }
    ],
    "sg:phone":"+44 1794 322225",
    "sg:postcode":"SO51 6DX",
    "sg:province":"Hampshire",
    "sg:tags":[
        "game"
    ],
    "wof:name":"P & M Dovey",
    "wof:placetype":"venue"
},
  "geometry": {"coordinates":[-1.587975,50.986069],"type":"Point"}
}