{
  "type": "Feature",
  "properties": {
    "addr:full":"3 Bennet Court, Bennet Road Reading Berkshire RG2 0QX",
    "addr:housenumber":"3",
    "addr:postcode":"rg2 0qx",
    "addr:street":"Bennet Court Bennet Road",
    "iso:country":"GB",
    "sg:address":"3 Bennet Court, Bennet Road",
    "sg:city":"Reading",
    "sg:classifiers":[
        {
            "category":"Manufacturing",
            "subcategory":"Electronics",
            "type":"Manufacturing & Wholesale Goods"
        }
    ],
    "sg:phone":"+44 118 963 3870",
    "sg:postcode":"RG2 0QX",
    "sg:province":"Berkshire",
    "sg:tags":[
        "control",
        "component",
        "-",
        "electronic"
    ],
    "wof:name":"Microtronica Ltd.",
    "wof:placetype":"venue"
},
  "geometry": {"coordinates":[-0.979598999,51.4258499146],"type":"Point"}
}