{
  "type": "Feature",
  "properties": {
    "iso:country":"GB",
    "sg:address":"263 Main Street, East Calder",
    "sg:city":"Livingston",
    "sg:classifiers":[
        {
            "category":"Home & Garden",
            "subcategory":"Carpets & Floor Coverings",
            "type":"Retail Goods"
        }
    ],
    "sg:phone":"+44 1506 882957",
    "sg:postcode":"EH53 0ED",
    "sg:province":"City of Edinburgh",
    "sg:tags":[
        "carpets",
        "retailer",
        "rug",
        "matting"
    ],
    "wof:name":"Home Choice Mobile Carpets",
    "wof:placetype":"venue"
},
  "geometry": {"coordinates":[-3.468481,55.894428],"type":"Point"}
}