{
  "type": "Feature",
  "properties": {
    "addr:full":"Edgware Road London Greater London NW9 6LU",
    "addr:postcode":"nw9 6lu",
    "addr:street":"Edgware Road",
    "iso:country":"GB",
    "sg:address":"Edgware Road",
    "sg:city":"London",
    "sg:classifiers":[
        {
            "category":"Real Estate",
            "subcategory":"Architect",
            "type":"Services"
        }
    ],
    "sg:phone":"+44 20 8200 8962",
    "sg:postcode":"NW9 6LU",
    "sg:province":"Greater London",
    "wof:name":"Ks Building Services Engineering Ltd.",
    "wof:placetype":"venue"
},
  "geometry": {"coordinates":[-0.256124,51.591095],"type":"Point"}
}