{
  "type": "Feature",
  "properties": {
    "iso:country":"GB",
    "sg:address":"Brightwells Clinic, Farnham Health Centre, East St",
    "sg:city":"Farnham",
    "sg:classifiers":[
        {
            "category":"Health Services",
            "subcategory":"Doctor",
            "type":"Services"
        }
    ],
    "sg:phone":"+44 1252 723122",
    "sg:postcode":"GU9 7SA",
    "sg:province":"Surrey",
    "sg:tags":[
        "practitioners"
    ],
    "wof:name":"Robinson, P C",
    "wof:placetype":"venue"
},
  "geometry": {"coordinates":[-0.8008369803,51.2143211365],"type":"Point"}
}