{
  "type": "Feature",
  "properties": {
    "iso:country":"GB",
    "sg:address":"130 Prince George Avenue",
    "sg:city":"Southgate",
    "sg:classifiers":[
        {
            "category":"Health Services",
            "subcategory":"Doctor",
            "type":"Services"
        }
    ],
    "sg:phone":"+44 20 8360 7372",
    "sg:postcode":"N14 4TA",
    "sg:province":"Greater London",
    "sg:tags":[
        "practitioners"
    ],
    "wof:name":"Stanton, M B",
    "wof:placetype":"venue"
},
  "geometry": {"coordinates":[-0.119822,51.64362],"type":"Point"}
}