{
  "type": "Feature",
  "properties": {
    "addr:full":"Holt Lodge Farm, Horton Heath, Horton Wimborne Dorset BH21 7JN",
    "addr:postcode":"bh21 7jn",
    "iso:country":"GB",
    "sg:address":"Holt Lodge Farm, Horton Heath, Horton",
    "sg:city":"Wimborne",
    "sg:classifiers":[
        {
            "category":"Farming",
            "subcategory":"Livestock Farm",
            "type":"Manufacturing & Wholesale Goods"
        }
    ],
    "sg:phone":"+44 1202 822209",
    "sg:postcode":"BH21 7JN",
    "sg:province":"Dorset",
    "sg:tags":[
        "others"
    ],
    "wof:name":"Anthony M Coleclough",
    "wof:placetype":"venue"
},
  "geometry": {"coordinates":[-1.9598939419,50.8675842285],"type":"Point"}
}