{
  "type": "Feature",
  "properties": {
    "iso:country":"GB",
    "sg:address":"Unit 7-8 Joseph Wilson Indust Est, Millstrood Rd",
    "sg:city":"Whitstable",
    "sg:classifiers":[
        {
            "category":"Home & Garden",
            "subcategory":"Carpets & Floor Coverings",
            "type":"Retail Goods"
        }
    ],
    "sg:phone":"+44 1227 277196",
    "sg:postcode":"CT5 3PS",
    "sg:province":"Kent",
    "sg:tags":[
        "rubber",
        "plastic"
    ],
    "wof:name":"Forge Industrial Mouldings Ltd",
    "wof:placetype":"venue"
},
  "geometry": {"coordinates":[1.0264060497,51.362247467],"type":"Point"}
}