{
  "type": "Feature",
  "properties": {
    "addr:full":"63 High Street New Malden Surrey KT3 4BT",
    "addr:housenumber":"63",
    "addr:postcode":"kt3 4bt",
    "addr:street":"High Street",
    "iso:country":"GB",
    "sg:address":"63 High Street",
    "sg:city":"New Malden",
    "sg:classifiers":[
        {
            "category":"Shopping",
            "subcategory":"Luggage & Leather Goods",
            "type":"Retail Goods"
        }
    ],
    "sg:phone":"+44 20 8949 3261",
    "sg:postcode":"KT3 4BT",
    "sg:province":"Surrey",
    "sg:tags":[
        "shop",
        "leathergoods"
    ],
    "wof:name":"Mitchel Sales Ltd.",
    "wof:placetype":"venue"
},
  "geometry": {"coordinates":[-0.2564049959,51.4017410278],"type":"Point"}
}