{
  "type": "Feature",
  "properties": {
    "addr:full":"156 Palatine Road Blackpool Lancashire FY1 4DS",
    "addr:housenumber":"156",
    "addr:postcode":"fy1 4ds",
    "addr:street":"Palatine Road",
    "iso:country":"GB",
    "sg:address":"156 Palatine Road",
    "sg:city":"Blackpool",
    "sg:classifiers":[
        {
            "category":"Utilities",
            "subcategory":"Refuse",
            "type":"Services"
        }
    ],
    "sg:phone":"+44 1253 751232",
    "sg:postcode":"FY1 4DS",
    "sg:province":"Lancashire",
    "sg:tags":[
        "disposal",
        "waste"
    ],
    "wof:name":"D & T Waste Disposal",
    "wof:placetype":"venue"
},
  "geometry": {"coordinates":[-3.040846,53.814461],"type":"Point"}
}