{
  "type": "Feature",
  "properties": {
    "iso:country":"GB",
    "sg:address":"6 Cleeve House, Lambourne Crescent, Llanishen",
    "sg:city":"Cardiff",
    "sg:classifiers":[
        {
            "category":"Organizations",
            "subcategory":"Non-profit Organization",
            "type":"Services"
        }
    ],
    "sg:phone":"+44 29 2074 7717",
    "sg:postcode":"CF14 5GP",
    "sg:province":"Cardiff",
    "sg:tags":[
        "organisation",
        "voluntary",
        "charity"
    ],
    "wof:name":"Women's Royal Voluntary Service",
    "wof:placetype":"venue"
},
  "geometry": {"coordinates":[-3.195525,51.528248],"type":"Point"}
}