{
  "type": "Feature",
  "properties": {
    "addr:full":"138 Cove Road Farnborough Hampshire GU14 0HJ",
    "addr:housenumber":"138",
    "addr:postcode":"gu14 0hj",
    "addr:street":"Cove Road",
    "iso:country":"GB",
    "sg:address":"138 Cove Road",
    "sg:city":"Farnborough",
    "sg:classifiers":[
        {
            "category":"Retail",
            "subcategory":"Auto Repair",
            "type":"Services"
        }
    ],
    "sg:phone":"+44 1252 660743",
    "sg:postcode":"GU14 0HJ",
    "sg:province":"Hampshire",
    "sg:tags":[
        "modification",
        "garage"
    ],
    "wof:name":"N Thomas Autos",
    "wof:placetype":"venue"
},
  "geometry": {"coordinates":[-0.7720890045,51.2941818237],"type":"Point"}
}