{
  "type": "Feature",
  "properties": {
    "addr:full":"67a Ellison Street Jarrow Tyne and Wear NE32 3JU",
    "addr:housenumber":"67a",
    "addr:postcode":"ne32 3ju",
    "addr:street":"Ellison Street",
    "iso:country":"GB",
    "sg:address":"67a Ellison Street",
    "sg:city":"Jarrow",
    "sg:classifiers":[
        {
            "category":"Personal",
            "subcategory":"Tattoo Parlor",
            "type":"Services"
        }
    ],
    "sg:phone":"+44 191 420 1977",
    "sg:postcode":"NE32 3JU",
    "sg:province":"Tyne and Wear",
    "sg:tags":[
        "tattooing",
        "piercing",
        "artist"
    ],
    "wof:name":"Viking Tattoo Studio",
    "wof:placetype":"venue"
},
  "geometry": {"coordinates":[-1.491072,54.981266],"type":"Point"}
}