{
  "type": "Feature",
  "properties": {
    "iso:country":"GB",
    "sg:address":"The Grain Store, Busk Lane",
    "sg:city":"Sedbergh",
    "sg:classifiers":[
        {
            "category":"Shopping",
            "subcategory":"Beauty & Cosmetics",
            "type":"Retail Goods"
        },
        {
            "category":"Shopping",
            "subcategory":"Pharmacy",
            "type":"Retail Goods"
        }
    ],
    "sg:phone":"+44 15396 21992",
    "sg:postcode":"LA10 5HF",
    "sg:province":"Cumbria",
    "sg:tags":[
        "product",
        "toiletry"
    ],
    "wof:name":"The Bath House Ltd.",
    "wof:placetype":"venue"
},
  "geometry": {"coordinates":[-2.527837,54.321945],"type":"Point"}
}