{
  "type": "Feature",
  "properties": {
    "addr:full":"Peak House, South Park Road Macclesfield Cheshire SK11 6SH",
    "addr:postcode":"sk11 6sh",
    "addr:street":"South Park Road",
    "iso:country":"GB",
    "sg:address":"Peak House, South Park Road",
    "sg:city":"Macclesfield",
    "sg:classifiers":[
        {
            "category":"Professional",
            "subcategory":"Computer Services",
            "type":"Services"
        }
    ],
    "sg:phone":"+44 1625 428220",
    "sg:postcode":"SK11 6SH",
    "sg:province":"Cheshire",
    "sg:tags":[
        "bureau",
        "facility"
    ],
    "wof:name":"Peak Software Ltd.",
    "wof:placetype":"venue"
},
  "geometry": {"coordinates":[-2.1308538914,53.25548172],"type":"Point"}
}