{
  "type": "Feature",
  "properties": {
    "iso:country":"GB",
    "sg:address":"32 Early Road",
    "sg:city":"Witney",
    "sg:classifiers":[
        {
            "category":"Professional",
            "subcategory":"Accounting & Tax Preparation",
            "type":"Services"
        },
        {
            "category":"Professional",
            "subcategory":"Management & Consulting",
            "type":"Services"
        }
    ],
    "sg:phone":"+44 1993 773665",
    "sg:postcode":"OX28 1EU",
    "sg:province":"Oxfordshire",
    "sg:tags":[
        "consultant",
        "business",
        "activity"
    ],
    "wof:name":"B R Consulting Ltd",
    "wof:placetype":"venue"
},
  "geometry": {"coordinates":[-1.4723449945,51.794719696],"type":"Point"}
}