{
  "type": "Feature",
  "properties": {
    "addr:full":"The Urmston Masonic Hall Ltd, The Masonic Club, Westbourne Rd Manchester Cheshire M41 0XQ",
    "addr:postcode":"m41 0xq",
    "addr:street":"Westbourne Rd",
    "iso:country":"GB",
    "sg:address":"The Urmston Masonic Hall Ltd, The Masonic Club, Westbourne Rd",
    "sg:city":"Manchester",
    "sg:classifiers":[
        {
            "category":"Organizations",
            "subcategory":"Community Association",
            "type":"Services"
        },
        {
            "category":"Organizations",
            "subcategory":"Membership Organization",
            "type":"Services"
        }
    ],
    "sg:phone":"+44 161 748 6533",
    "sg:postcode":"M41 0XQ",
    "sg:province":"Cheshire",
    "sg:tags":[
        "club",
        "social"
    ],
    "wof:name":"Urmston Masonic Hall Ltd (The)",
    "wof:placetype":"venue"
},
  "geometry": {"coordinates":[-2.34993,53.45071],"type":"Point"}
}