{
  "type": "Feature",
  "properties": {
    "addr:full":"The Studio, 60 High Street, Guilden Morden Royston Bedfordshire SG8 0JS",
    "addr:housenumber":"60",
    "addr:postcode":"sg8 0js",
    "addr:street":"High Street",
    "iso:country":"GB",
    "sg:address":"The Studio, 60 High Street, Guilden Morden",
    "sg:city":"Royston",
    "sg:classifiers":[
        {
            "category":"Communications",
            "subcategory":"Film & Video Production",
            "type":"Services"
        }
    ],
    "sg:postcode":"SG8 0JS",
    "sg:province":"Bedfordshire",
    "sg:tags":[
        "tv",
        "studio"
    ],
    "wof:name":"Age Film & Video",
    "wof:placetype":"venue"
},
  "geometry": {"coordinates":[-0.13353,52.082436],"type":"Point"}
}