{
  "type": "Feature",
  "properties": {
    "iso:country":"GB",
    "sg:address":"212 Kingston Road",
    "sg:city":"Teddington",
    "sg:classifiers":[
        {
            "category":"Cinema",
            "subcategory":"Movie Rental",
            "type":"Entertainment"
        }
    ],
    "sg:phone":"+44 20 8977 4110",
    "sg:postcode":"TW11 9JF",
    "sg:province":"Greater London",
    "sg:tags":[
        "video",
        "library"
    ],
    "wof:name":"Moonlight Movies",
    "wof:placetype":"venue"
},
  "geometry": {"coordinates":[-0.3186289966,51.4207572937],"type":"Point"}
}