{
  "type": "Feature",
  "properties": {
    "addr:full":"Suite 319, The Plaza, 535 Kings Rd London Greater London SW10 0TZ",
    "addr:housenumber":"suite 319;535",
    "addr:postcode":"sw10 0tz",
    "addr:street":"The;Kings Rd",
    "iso:country":"GB",
    "sg:address":"Suite 319, The Plaza, 535 Kings Rd",
    "sg:city":"London",
    "sg:classifiers":[
        {
            "category":"Travel",
            "subcategory":"Travel Agent",
            "type":"Entertainment"
        }
    ],
    "sg:phone":"+44 20 7376 4717",
    "sg:postcode":"SW10 0TZ",
    "sg:province":"Greater London",
    "sg:tags":[
        "hotel",
        "agency",
        "booking"
    ],
    "wof:name":"Contract Hotels & Travel Ltd",
    "wof:placetype":"venue"
},
  "geometry": {"coordinates":[-0.185407,51.480267],"type":"Point"}
}