{
  "type": "Feature",
  "properties": {
    "addr:full":"9-11 Deardengate, Haslingden Rossendale Lancashire BB4 5QN",
    "addr:housenumber":"9-11",
    "addr:postcode":"bb4 5qn",
    "addr:street":"Deardengate",
    "iso:country":"GB",
    "sg:address":"9-11 Deardengate, Haslingden",
    "sg:city":"Rossendale",
    "sg:classifiers":[
        {
            "category":"Recreation",
            "subcategory":"Water Park",
            "type":"Entertainment"
        }
    ],
    "sg:phone":"+44 1706 230220",
    "sg:postcode":"BB4 5QN",
    "sg:province":"Lancashire",
    "sg:tags":[
        "sport"
    ],
    "wof:name":"Dolphin Scuba Centre Ltd",
    "wof:placetype":"venue"
},
  "geometry": {"coordinates":[-2.325899,53.709122],"type":"Point"}
}