{
  "type": "Feature",
  "properties": {
    "iso:country":"GB",
    "sg:address":"43 Salisbury Road, Walmer",
    "sg:city":"Deal",
    "sg:classifiers":[
        {
            "category":"Organizations",
            "subcategory":"Non-profit Organization",
            "type":"Services"
        }
    ],
    "sg:postcode":"CT14 7QJ",
    "sg:province":"Kent",
    "sg:tags":[
        "organisation",
        "voluntary",
        "charity"
    ],
    "wof:name":"Arthritis Care",
    "wof:placetype":"venue"
},
  "geometry": {"coordinates":[1.390736,51.204994],"type":"Point"}
}