{
  "type": "Feature",
  "properties": {
    "iso:country":"GB",
    "sg:address":"18 Moss Drive, Haslingfield",
    "sg:city":"Cambridge",
    "sg:classifiers":[
        {
            "category":"Professional",
            "subcategory":"Management & Consulting",
            "type":"Services"
        }
    ],
    "sg:phone":"+44 1223 871606",
    "sg:postcode":"CB3 7JB",
    "sg:province":"Cambridgeshire",
    "sg:tags":[
        "consultant",
        "business"
    ],
    "wof:name":"Dr T.R Jarman",
    "wof:placetype":"venue"
},
  "geometry": {"coordinates":[0.059778,52.152489],"type":"Point"}
}