{
  "type": "Feature",
  "properties": {
    "iso:country":"GB",
    "sg:address":"Beech La",
    "sg:city":"Peterborough",
    "sg:classifiers":[
        {
            "category":"Retail",
            "subcategory":"Auto Repair",
            "type":"Services"
        }
    ],
    "sg:postcode":"PE6 7YG",
    "sg:province":"Cambridgeshire",
    "sg:tags":[
        "modification",
        "garage"
    ],
    "wof:name":"Fenland Autos",
    "wof:placetype":"venue"
},
  "geometry": {"coordinates":[-0.196963,52.607712],"type":"Point"}
}