{
  "type": "Feature",
  "properties": {
    "addr:full":"9 Meadow Rd Wolverhampton Staffordshire WV3 8EZ",
    "addr:housenumber":"9",
    "addr:postcode":"wv3 8ez",
    "addr:street":"Meadow Rd",
    "iso:country":"GB",
    "sg:address":"9 Meadow Rd",
    "sg:city":"Wolverhampton",
    "sg:classifiers":[
        {
            "category":"Professional",
            "subcategory":"Lawyer & Legal Services",
            "type":"Services"
        }
    ],
    "sg:phone":"+44 1902 761111",
    "sg:postcode":"WV3 8EZ",
    "sg:province":"Staffordshire",
    "sg:tags":[
        "solicitor"
    ],
    "wof:name":"David Bruce",
    "wof:placetype":"venue"
},
  "geometry": {"coordinates":[-2.1699159145,52.5783195496],"type":"Point"}
}