{
  "type": "Feature",
  "properties": {
    "addr:full":"Roselands Depot Eastbourne East Sussex BN22 8NB",
    "addr:postcode":"bn22 8nb",
    "iso:country":"GB",
    "sg:address":"Roselands Depot",
    "sg:city":"Eastbourne",
    "sg:classifiers":[
        {
            "category":"Utilities",
            "subcategory":"Refuse",
            "type":"Services"
        }
    ],
    "sg:phone":"+44 1323 431666",
    "sg:postcode":"BN22 8NB",
    "sg:province":"East Sussex",
    "sg:tags":[
        "disposal",
        "waste"
    ],
    "wof:name":"Sita Wastecare",
    "wof:placetype":"venue"
},
  "geometry": {"coordinates":[0.2976199985,50.7810745239],"type":"Point"}
}