{
  "type": "Feature",
  "properties": {
    "addr:full":"525 Norwood Road London Greater London SE27 9DL",
    "addr:housenumber":"525",
    "addr:postcode":"se27 9dl",
    "addr:street":"Norwood Road",
    "iso:country":"GB",
    "sg:address":"525 Norwood Road",
    "sg:city":"London",
    "sg:classifiers":[
        {
            "category":"Shopping",
            "subcategory":"Clothing, Apparel, & Fashions",
            "type":"Retail Goods"
        }
    ],
    "sg:postcode":"SE27 9DL",
    "sg:province":"Greater London",
    "sg:tags":[
        "shop"
    ],
    "wof:name":"Charisma",
    "wof:placetype":"venue"
},
  "geometry": {"coordinates":[-0.103836,51.43475],"type":"Point"}
}