{
  "type": "Feature",
  "properties": {
    "iso:country":"GB",
    "sg:address":"2 Little Castle St",
    "sg:city":"Truro",
    "sg:classifiers":[
        {
            "category":"Professional",
            "subcategory":"Printing & Photocopies",
            "type":"Services"
        }
    ],
    "sg:phone":"+44 1872 277371",
    "sg:postcode":"TR1 3DL",
    "sg:province":"Cornwall",
    "sg:tags":[
        "duplicating",
        "copying"
    ],
    "wof:name":"Truro Copy Centre",
    "wof:placetype":"venue"
},
  "geometry": {"coordinates":[-5.055568,50.263065],"type":"Point"}
}