{
  "type": "Feature",
  "properties": {
    "addr:full":"677 High Road Benfleet Essex SS7 5SF",
    "addr:housenumber":"677",
    "addr:postcode":"ss7 5sf",
    "addr:street":"High Road",
    "iso:country":"GB",
    "sg:address":"677 High Road",
    "sg:city":"Benfleet",
    "sg:classifiers":[
        {
            "category":"Manufacturing",
            "subcategory":"Wood Products",
            "type":"Manufacturing & Wholesale Goods"
        }
    ],
    "sg:postcode":"SS7 5SF",
    "sg:province":"Essex",
    "sg:tags":[
        "maker",
        "cabinet"
    ],
    "wof:name":"Unique Kitchen Co",
    "wof:placetype":"venue"
},
  "geometry": {"coordinates":[0.5503810048,51.566822052],"type":"Point"}
}