{
  "type": "Feature",
  "properties": {
    "addr:full":"Unicorn House, 3 Plough Yard London Greater London EC2A 3PW",
    "addr:housenumber":"3",
    "addr:postcode":"ec2a 3pw",
    "addr:street":"Plough Yard",
    "iso:country":"GB",
    "sg:address":"Unicorn House, 3 Plough Yard",
    "sg:city":"London",
    "sg:classifiers":[
        {
            "category":"Communications",
            "subcategory":"Newspaper",
            "type":"Services"
        }
    ],
    "sg:postcode":"EC2A 3PW",
    "sg:province":"Greater London",
    "sg:tags":[
        "magazine"
    ],
    "wof:name":"Alliance International Media Ltd.",
    "wof:placetype":"venue"
},
  "geometry": {"coordinates":[-0.079365,51.522526],"type":"Point"}
}