{
  "type": "Feature",
  "properties": {
    "iso:country":"GB",
    "sg:address":"200 Above Bar St",
    "sg:city":"Southampton",
    "sg:classifiers":[
        {
            "category":"Cafe",
            "type":"Food & Drink"
        }
    ],
    "sg:phone":"+44 23 8022 2412",
    "sg:postcode":"SO14 7DW",
    "sg:province":"Hampshire",
    "sg:tags":[
        "tea",
        "room"
    ],
    "wof:name":"DelMarco",
    "wof:placetype":"venue"
},
  "geometry": {"coordinates":[-1.404666,50.91008],"type":"Point"}
}