{
  "type": "Feature",
  "properties": {
    "addr:full":"135 Church Hill Road, Cheam Sutton Surrey SM3 8NE",
    "addr:housenumber":"135",
    "addr:postcode":"sm3 8ne",
    "addr:street":"Church Hill Road",
    "iso:country":"GB",
    "sg:address":"135 Church Hill Road, Cheam",
    "sg:city":"Sutton",
    "sg:classifiers":[
        {
            "category":"Shopping",
            "subcategory":"News",
            "type":"Retail Goods"
        }
    ],
    "sg:phone":"+44 20 8644 8701",
    "sg:postcode":"SM3 8NE",
    "sg:province":"Surrey",
    "sg:tags":[
        "newsagent"
    ],
    "wof:name":"R & S Newsagent",
    "wof:placetype":"venue"
},
  "geometry": {"coordinates":[-0.2185260057,51.3680152893],"type":"Point"}
}