{
  "type": "Feature",
  "properties": {
    "iso:country":"GB",
    "sg:address":"Oxford Rd, Gomersal",
    "sg:city":"Cleckheaton",
    "sg:classifiers":[
        {
            "category":"Health Services",
            "subcategory":"Nursing And Care Facility",
            "type":"Services"
        },
        {
            "category":"Social Services",
            "subcategory":"Retirement Home",
            "type":"Services"
        }
    ],
    "sg:phone":"+44 1274 862021",
    "sg:postcode":"BD19 4LA",
    "sg:province":"West Yorkshire",
    "sg:tags":[
        "residential"
    ],
    "wof:name":"Holme House",
    "wof:placetype":"venue"
},
  "geometry": {"coordinates":[-1.686614,53.73386],"type":"Point"}
}