{
  "type": "Feature",
  "properties": {
    "addr:full":"201 Newhall Road, Attercliffe Sheffield South Yorkshire S9 2QJ",
    "addr:housenumber":"201",
    "addr:postcode":"s9 2qj",
    "addr:street":"Newhall Road",
    "iso:country":"GB",
    "sg:address":"201 Newhall Road, Attercliffe",
    "sg:city":"Sheffield",
    "sg:classifiers":[
        {
            "category":"Manufacturing",
            "subcategory":"Tools & Machinery",
            "type":"Manufacturing & Wholesale Goods"
        },
        {
            "category":"Health Services",
            "subcategory":"Clinic",
            "type":"Services"
        }
    ],
    "sg:phone":"+44 114 261 1811",
    "sg:postcode":"S9 2QJ",
    "sg:province":"South Yorkshire",
    "sg:tags":[
        "instrument",
        "medical",
        "purpose",
        "manufacturer"
    ],
    "wof:name":"Eurocut Ltd",
    "wof:placetype":"venue"
},
  "geometry": {"coordinates":[-1.423229,53.40081],"type":"Point"}
}