{
  "type": "Feature",
  "properties": {
    "iso:country":"GB",
    "sg:address":"Unit 9 Ironbridge Wharf, Lanrick Rd",
    "sg:city":"London",
    "sg:classifiers":[
        {
            "category":"Autos & Motor Vehicles",
            "subcategory":"Motorcycle Sales",
            "type":"Retail Goods"
        }
    ],
    "sg:postcode":"E14 0JF",
    "sg:province":"Greater London",
    "sg:tags":[
        "hire"
    ],
    "wof:name":"Constanti,Paul,",
    "wof:placetype":"venue"
},
  "geometry": {"coordinates":[0.00223,51.515049],"type":"Point"}
}