{
  "type": "Feature",
  "properties": {
    "iso:country":"GB",
    "sg:address":"3 Tanton Close, Seamer",
    "sg:city":"Middlesbrough",
    "sg:classifiers":[
        {
            "category":"Professional",
            "subcategory":"Engineering",
            "type":"Services"
        }
    ],
    "sg:postcode":"TS9 5NP",
    "sg:province":"North Yorkshire",
    "wof:name":"T E E S (Tim Ellis Engineering Services)",
    "wof:placetype":"venue"
},
  "geometry": {"coordinates":[-1.228716,54.484673],"type":"Point"}
}