{
  "type": "Feature",
  "properties": {
    "iso:country":"GB",
    "sg:address":"Hanham Road Garage, 1 /15 Hanham Road, Kingswood",
    "sg:city":"Bristol",
    "sg:classifiers":[
        {
            "category":"Autos & Motor Vehicles",
            "subcategory":"Fuel & Gas Station",
            "type":"Retail Goods"
        }
    ],
    "sg:phone":"+44 117 960 0074",
    "sg:postcode":"BS15 8PR",
    "sg:province":"City of Bristol",
    "sg:tags":[
        "petrol",
        "filling"
    ],
    "wof:name":"Masters of Kingswood",
    "wof:placetype":"venue"
},
  "geometry": {"coordinates":[-2.591429,51.453667],"type":"Point"}
}