{
  "type": "Feature",
  "properties": {
    "addr:full":"11 Rosebery Avenue, South Shore Blackpool Lancashire FY4 1LA",
    "addr:housenumber":"11",
    "addr:postcode":"fy4 1la",
    "addr:street":"Rosebery Avenue",
    "iso:country":"GB",
    "sg:address":"11 Rosebery Avenue, South Shore",
    "sg:city":"Blackpool",
    "sg:classifiers":[
        {
            "category":"Social Services",
            "subcategory":"Retirement Home",
            "type":"Services"
        }
    ],
    "sg:phone":"+44 1253 342058",
    "sg:postcode":"FY4 1LA",
    "sg:province":"Lancashire",
    "sg:tags":[
        "rest"
    ],
    "wof:name":"Briarwood House Rest Home",
    "wof:placetype":"venue"
},
  "geometry": {"coordinates":[-3.049143,53.788177],"type":"Point"}
}