{
  "type": "Feature",
  "properties": {
    "addr:full":"151-153 Folkestone Road Dover Kent CT17 9SG",
    "addr:postcode":"151-153;ct17 9sg",
    "addr:street":"Folkestone Road",
    "iso:country":"GB",
    "sg:address":"151-153 Folkestone Road",
    "sg:city":"Dover",
    "sg:classifiers":[
        {
            "category":"Professional",
            "subcategory":"Business Services",
            "type":"Services"
        }
    ],
    "sg:phone":"+44 1304 211673",
    "sg:postcode":"CT17 9SG",
    "sg:province":"Kent",
    "sg:tags":[
        "accomodation"
    ],
    "wof:name":"Richard J West Ltd.",
    "wof:placetype":"venue"
},
  "geometry": {"coordinates":[1.300937,51.124115],"type":"Point"}
}