{
  "type": "Feature",
  "properties": {
    "iso:country":"GB",
    "sg:address":"18 Commerce Street",
    "sg:city":"Arbroath",
    "sg:classifiers":[
        {
            "category":"Shopping",
            "subcategory":"News",
            "type":"Retail Goods"
        }
    ],
    "sg:phone":"+44 1241 870969",
    "sg:postcode":"DD11 1NB",
    "sg:province":"Angus",
    "sg:tags":[
        "newsagent"
    ],
    "wof:name":"J & R Jack",
    "wof:placetype":"venue"
},
  "geometry": {"coordinates":[-2.5824539661,56.5581207275],"type":"Point"}
}