{
  "type": "Feature",
  "properties": {
    "addr:full":"74b Holmes Road London Greater London NW5 3AA",
    "addr:housenumber":"74b",
    "addr:postcode":"nw5 3aa",
    "addr:street":"Holmes Road",
    "iso:country":"GB",
    "sg:address":"74b Holmes Road",
    "sg:city":"London",
    "sg:classifiers":[
        {
            "category":"Professional",
            "subcategory":"Detective & Security Services",
            "type":"Services"
        }
    ],
    "sg:phone":"+44 20 7284 4142",
    "sg:postcode":"NW5 3AA",
    "sg:province":"Greater London",
    "sg:tags":[
        "locksmith"
    ],
    "wof:name":"Auto House",
    "wof:placetype":"venue"
},
  "geometry": {"coordinates":[-0.1412599981,51.5491981506],"type":"Point"}
}