{
  "type": "Feature",
  "properties": {
    "addr:full":"66 Stonor Rd, Hall Green Birmingham West Midlands B28 0QR",
    "addr:housenumber":"66",
    "addr:postcode":"b28 0qr",
    "addr:street":"Stonor Rd",
    "iso:country":"GB",
    "sg:address":"66 Stonor Rd, Hall Green",
    "sg:city":"Birmingham",
    "sg:classifiers":[
        {
            "category":"Professional",
            "subcategory":"Secretarial Services",
            "type":"Services"
        }
    ],
    "sg:phone":"+44 121 744 5778",
    "sg:postcode":"B28 0QR",
    "sg:province":"West Midlands",
    "wof:name":"Sharp Secretarial Services",
    "wof:placetype":"venue"
},
  "geometry": {"coordinates":[-1.835167,52.418587],"type":"Point"}
}