{
  "type": "Feature",
  "properties": {
    "addr:full":"133 Westbury Lane Newport Pagnell Buckinghamshire MK16 8SA",
    "addr:housenumber":"133",
    "addr:postcode":"mk16 8sa",
    "addr:street":"Westbury Lane",
    "iso:country":"GB",
    "sg:address":"133 Westbury Lane",
    "sg:city":"Newport Pagnell",
    "sg:classifiers":[
        {
            "category":"Farming",
            "subcategory":"Farm",
            "type":"Manufacturing & Wholesale Goods"
        }
    ],
    "sg:phone":"+44 1908 218014",
    "sg:postcode":"MK16 8SA",
    "sg:province":"Buckinghamshire",
    "sg:tags":[
        "agricultural"
    ],
    "wof:name":"Ridgway Services",
    "wof:placetype":"venue"
},
  "geometry": {"coordinates":[-0.7439200282,52.0895767212],"type":"Point"}
}