{
  "type": "Feature",
  "properties": {
    "addr:full":"229 Derby Rd Derby Derbyshire DE21 7LW",
    "addr:housenumber":"229",
    "addr:postcode":"de21 7lw",
    "addr:street":"Derby Rd",
    "iso:country":"GB",
    "sg:address":"229 Derby Rd",
    "sg:city":"Derby",
    "sg:classifiers":[
        {
            "category":"Shopping",
            "subcategory":"Clothing, Apparel, & Fashions",
            "type":"Retail Goods"
        }
    ],
    "sg:postcode":"DE21 7LW",
    "sg:province":"Derbyshire",
    "sg:tags":[
        "clothing",
        "fabric"
    ],
    "wof:name":"Ordu,Ann,",
    "wof:placetype":"venue"
},
  "geometry": {"coordinates":[-1.423459053,52.9187011719],"type":"Point"}
}