{
  "type": "Feature",
  "properties": {
    "addr:full":"57b High Street, Earith Huntingdon Bedfordshire PE28 3PP",
    "addr:housenumber":"57b",
    "addr:postcode":"pe28 3pp",
    "addr:street":"High Street",
    "iso:country":"GB",
    "sg:address":"57b High Street, Earith",
    "sg:city":"Huntingdon",
    "sg:classifiers":[
        {
            "category":"Personal",
            "subcategory":"Beauty Salon",
            "type":"Services"
        }
    ],
    "sg:phone":"+44 1487 842553",
    "sg:postcode":"PE28 3PP",
    "sg:province":"Bedfordshire",
    "sg:tags":[
        "unisex",
        "hairdresser"
    ],
    "wof:name":"Jenela Hair Salon",
    "wof:placetype":"venue"
},
  "geometry": {"coordinates":[0.032812,52.354019],"type":"Point"}
}