{
  "type": "Feature",
  "properties": {
    "iso:country":"GB",
    "sg:address":"144 Avenue Road, Acton",
    "sg:city":"London",
    "sg:classifiers":[
        {
            "category":"Home & Garden",
            "subcategory":"Furniture",
            "type":"Retail Goods"
        }
    ],
    "sg:phone":"+44 20 8992 6562",
    "sg:postcode":"W3 8QG",
    "sg:province":"Greater London",
    "wof:name":"The Automatic Button Co. Ltd.",
    "wof:placetype":"venue"
},
  "geometry": {"coordinates":[-0.2761250138,51.505027771],"type":"Point"}
}