{
  "type": "Feature",
  "properties": {
    "iso:country":"GB",
    "sg:address":"193 Lord Street",
    "sg:city":"Southport",
    "sg:classifiers":[
        {
            "category":"Shopping",
            "subcategory":"Luggage & Leather Goods",
            "type":"Retail Goods"
        }
    ],
    "sg:phone":"+44 1704 546280",
    "sg:postcode":"PR8 1PE",
    "sg:province":"Lancashire",
    "sg:tags":[
        "shop",
        "leathergoods"
    ],
    "wof:name":"Salisburys",
    "wof:placetype":"venue"
},
  "geometry": {"coordinates":[-3.008298,53.646984],"type":"Point"}
}