{
  "type": "Feature",
  "properties": {
    "iso:country":"GB",
    "sg:address":"Weekclose Farm, Pancrasweek",
    "sg:city":"Holsworthy",
    "sg:classifiers":[
        {
            "category":"Freight",
            "type":"Transportation"
        }
    ],
    "sg:postcode":"EX22 7JB",
    "sg:province":"Cornwall",
    "sg:tags":[
        "haulage",
        "road"
    ],
    "wof:name":"Storey,B A L,",
    "wof:placetype":"venue"
},
  "geometry": {"coordinates":[-4.419765,50.825985],"type":"Point"}
}