{
  "type": "Feature",
  "properties": {
    "iso:country":"GB",
    "sg:address":"93 Main Street, Broughton Astley",
    "sg:city":"Leicester",
    "sg:classifiers":[
        {
            "category":"Food & Beverages",
            "subcategory":"Supermarket",
            "type":"Retail Goods"
        }
    ],
    "sg:phone":"+44 1455 282262",
    "sg:postcode":"LE9 6RE",
    "sg:province":"Leicestershire",
    "wof:name":"Midland Co-Operative Society",
    "wof:placetype":"venue"
},
  "geometry": {"coordinates":[-1.230276,52.534336],"type":"Point"}
}