{
  "type": "Feature",
  "properties": {
    "iso:country":"GB",
    "sg:address":"66 Dovecot St",
    "sg:city":"Stockton On Tees",
    "sg:classifiers":[
        {
            "category":"Community Center",
            "type":"Public Place"
        }
    ],
    "sg:phone":"+44 1642 612400",
    "sg:postcode":"TS18 1LL",
    "sg:province":"Durham",
    "sg:tags":[
        "centre"
    ],
    "wof:name":"International Family Centre",
    "wof:placetype":"venue"
},
  "geometry": {"coordinates":[-1.3164319992,54.5643501282],"type":"Point"}
}