{
  "type": "Feature",
  "properties": {
    "addr:full":"6 Shepherds Loan Dundee Dundee City DD2 1AX",
    "addr:housenumber":"6",
    "addr:postcode":"dd2 1ax",
    "addr:street":"Shepherds Loan",
    "iso:country":"GB",
    "sg:address":"6 Shepherds Loan",
    "sg:city":"Dundee",
    "sg:classifiers":[
        {
            "category":"Building & Trades",
            "subcategory":"Construction",
            "type":"Services"
        }
    ],
    "sg:phone":"+44 1382 644456",
    "sg:postcode":"DD2 1AX",
    "sg:province":"Dundee City",
    "sg:tags":[
        "roofing"
    ],
    "wof:name":"James Wilson Slating & Plumbing Services",
    "wof:placetype":"venue"
},
  "geometry": {"coordinates":[-2.995093,56.455662],"type":"Point"}
}