{
  "type": "Feature",
  "properties": {
    "iso:country":"GB",
    "sg:address":"Unit 7, Coegnant Close",
    "sg:city":"Bridgend",
    "sg:classifiers":[
        {
            "category":"Shopping",
            "subcategory":"Computers & Home Electronics",
            "type":"Retail Goods"
        }
    ],
    "sg:phone":"+44 1656 766060",
    "sg:postcode":"CF31 2AQ",
    "sg:province":"Bridgend",
    "sg:tags":[
        "electrical"
    ],
    "wof:name":"A C A Cable Distributors",
    "wof:placetype":"venue"
},
  "geometry": {"coordinates":[-3.5593540668,51.5178794861],"type":"Point"}
}