{
  "type": "Feature",
  "properties": {
    "addr:full":"2 The Green, Tollerton York North Yorkshire YO61 1PX",
    "addr:housenumber":"2",
    "addr:postcode":"yo61 1px",
    "addr:street":"The Green",
    "iso:country":"GB",
    "sg:address":"2 The Green, Tollerton",
    "sg:city":"York",
    "sg:classifiers":[
        {
            "category":"Government",
            "subcategory":"Post Office",
            "type":"Public Place"
        }
    ],
    "sg:phone":"+44 1347 838436",
    "sg:postcode":"YO61 1PX",
    "sg:province":"North Yorkshire",
    "wof:name":"Tollerton Post Office & Stores",
    "wof:placetype":"venue"
},
  "geometry": {"coordinates":[-1.219419,54.071732],"type":"Point"}
}