{
  "type": "Feature",
  "properties": {
    "iso:country":"GB",
    "sg:address":"Unit 9",
    "sg:city":"Aberdeen",
    "sg:classifiers":[
        {
            "category":"Retail",
            "subcategory":"Auto Repair",
            "type":"Services"
        }
    ],
    "sg:phone":"+44 1224 875555",
    "sg:postcode":"AB12 3AB",
    "sg:province":"Aberdeen City",
    "sg:tags":[
        "modification",
        "garage"
    ],
    "wof:name":"Old Mill Motors",
    "wof:placetype":"venue"
},
  "geometry": {"coordinates":[-2.0895290375,57.1068000793],"type":"Point"}
}