{
  "type": "Feature",
  "properties": {
    "iso:country":"GB",
    "sg:address":"10 Mitcells Enterprise Centre, Bradberry Balk Lane, Wombwell",
    "sg:city":"Barnsley",
    "sg:classifiers":[
        {
            "category":"Building & Trades",
            "subcategory":"Cleaning & Sanitation",
            "type":"Services"
        },
        {
            "category":"Home & Garden",
            "subcategory":"Building Materials",
            "type":"Retail Goods"
        }
    ],
    "sg:phone":"+44 1226 751751",
    "sg:postcode":"S73 8HR",
    "sg:province":"South Yorkshire",
    "sg:tags":[
        "shutter",
        "door",
        "manufacturer"
    ],
    "wof:name":"Active Doors Ltd.",
    "wof:placetype":"venue"
},
  "geometry": {"coordinates":[-1.41062,53.530636],"type":"Point"}
}