{
  "type": "Feature",
  "properties": {
    "addr:full":"95 Cowslip Hill Letchworth Hertfordshire SG6 4EX",
    "addr:housenumber":"95",
    "addr:postcode":"sg6 4ex",
    "addr:street":"Cowslip Hill Letchworth",
    "iso:country":"GB",
    "sg:address":"95 Cowslip Hill",
    "sg:city":"Letchworth",
    "sg:classifiers":[
        {
            "category":"Education",
            "subcategory":"Music School",
            "type":"Public Place"
        }
    ],
    "sg:phone":"+44 1462 486000",
    "sg:postcode":"SG6 4EX",
    "sg:province":"Hertfordshire",
    "sg:tags":[
        "conservatory"
    ],
    "wof:name":"Dream Conservatories Ltd.",
    "wof:placetype":"venue"
},
  "geometry": {"coordinates":[-0.232719,51.98188],"type":"Point"}
}