{
  "type": "Feature",
  "properties": {
    "iso:country":"GB",
    "sg:address":"13 Cliff Hill, Gorleston",
    "sg:city":"Great Yarmouth",
    "sg:classifiers":[
        {
            "category":"Bars & Pubs",
            "type":"Food & Drink"
        }
    ],
    "sg:phone":"+44 1493 662118",
    "sg:postcode":"NR31 6DQ",
    "sg:province":"Norfolk",
    "sg:tags":[
        "pubs",
        "inn"
    ],
    "wof:name":"The White Lion Inn",
    "wof:placetype":"venue"
},
  "geometry": {"coordinates":[1.7306770086,52.5716171265],"type":"Point"}
}