{
  "type": "Feature",
  "properties": {
    "addr:full":"56 Pear Tree Avenue, Ditton Aylesford Kent ME20 6EB",
    "addr:housenumber":"56",
    "addr:postcode":"me20 6eb",
    "addr:street":"Pear Tree Avenue;Aylesford",
    "iso:country":"GB",
    "sg:address":"56 Pear Tree Avenue, Ditton",
    "sg:city":"Aylesford",
    "sg:classifiers":[
        {
            "category":"Home & Garden",
            "subcategory":"Carpets & Floor Coverings",
            "type":"Retail Goods"
        }
    ],
    "sg:postcode":"ME20 6EB",
    "sg:province":"Kent",
    "sg:tags":[
        "cleaner",
        "upholstery"
    ],
    "wof:name":"Key Cleaning Services",
    "wof:placetype":"venue"
},
  "geometry": {"coordinates":[0.4581660032,51.2951965332],"type":"Point"}
}