{
  "type": "Feature",
  "properties": {
    "iso:country":"GB",
    "sg:address":"1 City Bank Road",
    "sg:city":"Cirencester",
    "sg:classifiers":[
        {
            "category":"Professional",
            "subcategory":"Computer Services",
            "type":"Services"
        }
    ],
    "sg:phone":"+44 1285 644416",
    "sg:postcode":"GL7 1LG",
    "sg:province":"Gloucestershire",
    "sg:tags":[
        "aided",
        "design"
    ],
    "wof:name":"META4",
    "wof:placetype":"venue"
},
  "geometry": {"coordinates":[-1.958906,51.709496],"type":"Point"}
}