{
  "type": "Feature",
  "properties": {
    "iso:country":"GB",
    "sg:address":"93 Smallbrook Queensway",
    "sg:city":"Birmingham",
    "sg:classifiers":[
        {
            "category":"Bars & Pubs",
            "type":"Food & Drink"
        }
    ],
    "sg:phone":"+44 121 643 7572",
    "sg:postcode":"B5 4JL",
    "sg:province":"West Midlands",
    "sg:tags":[
        "pubs",
        "inn"
    ],
    "wof:name":"Quenchers",
    "wof:placetype":"venue"
},
  "geometry": {"coordinates":[-1.896354,52.476997],"type":"Point"}
}