{
  "type": "Feature",
  "properties": {
    "addr:full":"1967 Dumbarton Rd Glasgow Glasgow City G14 0HZ",
    "addr:housenumber":"1967",
    "addr:postcode":"g14 0hz",
    "addr:street":"Dumbarton Rd",
    "iso:country":"GB",
    "sg:address":"1967 Dumbarton Rd",
    "sg:city":"Glasgow",
    "sg:classifiers":[
        {
            "category":"Travel",
            "subcategory":"Travel Agent",
            "type":"Entertainment"
        }
    ],
    "sg:phone":"+44 141 959 0287",
    "sg:postcode":"G14 0HZ",
    "sg:province":"Glasgow City",
    "wof:name":"Crystal Schools Scotland",
    "wof:placetype":"venue"
},
  "geometry": {"coordinates":[-4.3660888672,55.8830375671],"type":"Point"}
}