{
  "type": "Feature",
  "properties": {
    "addr:full":"47 Maldon Rd, Margaretting Ingatestone Essex CM4 9JG",
    "addr:housenumber":"47",
    "addr:postcode":"cm4 9jg",
    "addr:street":"Maldon Rd",
    "iso:country":"GB",
    "sg:address":"47 Maldon Rd, Margaretting",
    "sg:city":"Ingatestone",
    "sg:classifiers":[
        {
            "category":"Sports & Exercise",
            "subcategory":"Tennis Court",
            "type":"Entertainment"
        }
    ],
    "sg:phone":"+44 1277 353951",
    "sg:postcode":"CM4 9JG",
    "sg:province":"Essex",
    "sg:tags":[
        "breakdown",
        "recovery"
    ],
    "wof:name":"Auto Assist 24 Hr Recovery",
    "wof:placetype":"venue"
},
  "geometry": {"coordinates":[0.422521,51.689388],"type":"Point"}
}