{
  "type": "Feature",
  "properties": {
    "addr:full":"Unit 11, Nuffield Industrial Estate, Sandy Lane West Oxford Oxfordshire OX4 6JS",
    "addr:housenumber":"unit 11",
    "addr:postcode":"ox4 6js",
    "addr:street":"Industrial;Sandy Lane West",
    "iso:country":"GB",
    "sg:address":"Unit 11, Nuffield Industrial Estate, Sandy Lane West",
    "sg:city":"Oxford",
    "sg:classifiers":[
        {
            "category":"Shopping",
            "subcategory":"Stationery & Office Supplies",
            "type":"Retail Goods"
        }
    ],
    "sg:phone":"+44 1865 717709",
    "sg:postcode":"OX4 6JS",
    "sg:province":"Oxfordshire",
    "sg:tags":[
        "printers'"
    ],
    "wof:name":"Litho Supplies (Thames Valley)",
    "wof:placetype":"venue"
},
  "geometry": {"coordinates":[-1.2131,51.722889],"type":"Point"}
}