{
  "type": "Feature",
  "properties": {
    "addr:full":"Well Close Sq Berwick Upon Tweed Northumberland TD15 1LL",
    "addr:postcode":"td15 1ll",
    "addr:street":"Well Close Sq",
    "iso:country":"GB",
    "sg:address":"Well Close Sq",
    "sg:city":"Berwick Upon Tweed",
    "sg:classifiers":[
        {
            "category":"Health Services",
            "subcategory":"Doctor",
            "type":"Services"
        }
    ],
    "sg:phone":"+44 1289 306634",
    "sg:postcode":"TD15 1LL",
    "sg:province":"Northumberland",
    "sg:tags":[
        "practitioners"
    ],
    "wof:name":"Lowe, T B G",
    "wof:placetype":"venue"
},
  "geometry": {"coordinates":[-2.004984,55.773029],"type":"Point"}
}