{
  "type": "Feature",
  "properties": {
    "iso:country":"GB",
    "sg:address":"45a The Strand",
    "sg:city":"Exmouth",
    "sg:classifiers":[
        {
            "category":"Health Services",
            "subcategory":"Nursing And Care Facility",
            "type":"Services"
        }
    ],
    "sg:phone":"+44 1395 227386",
    "sg:postcode":"EX8 2AL",
    "sg:province":"Devon",
    "sg:tags":[
        "home"
    ],
    "wof:name":"B N A",
    "wof:placetype":"venue"
},
  "geometry": {"coordinates":[-3.4145629406,50.6190414429],"type":"Point"}
}