{
  "type": "Feature",
  "properties": {
    "addr:full":"122 High Street, Selsey Chichester West Sussex PO20 0QE",
    "addr:housenumber":"122",
    "addr:postcode":"po20 0qe",
    "addr:street":"High Street",
    "iso:country":"GB",
    "sg:address":"122 High Street, Selsey",
    "sg:city":"Chichester",
    "sg:classifiers":[
        {
            "category":"Real Estate",
            "subcategory":"Real Estate Agent",
            "type":"Services"
        }
    ],
    "sg:phone":"+44 1243 606789",
    "sg:postcode":"PO20 0QE",
    "sg:province":"West Sussex",
    "wof:name":"Martlet Estate Agents Ltd.",
    "wof:placetype":"venue"
},
  "geometry": {"coordinates":[-0.7927340269,50.7320365906],"type":"Point"}
}