{
  "type": "Feature",
  "properties": {
    "addr:full":"Disability Resource Centre, Lancaster Rd Shrewsbury Shropshire SY1 3NJ",
    "addr:postcode":"sy1 3nj",
    "addr:street":"Lancaster Rd",
    "iso:country":"GB",
    "sg:address":"Disability Resource Centre, Lancaster Rd",
    "sg:city":"Shrewsbury",
    "sg:classifiers":[
        {
            "category":"Social Services",
            "type":"Services"
        }
    ],
    "sg:phone":"+44 1743 440060",
    "sg:postcode":"SY1 3NJ",
    "sg:province":"Shropshire",
    "sg:tags":[
        "need",
        "disability",
        "special"
    ],
    "wof:name":"Visual Interpreting & Communication Service",
    "wof:placetype":"venue"
},
  "geometry": {"coordinates":[-2.751284,52.706566],"type":"Point"}
}