{
  "type": "Feature",
  "properties": {
    "iso:country":"GB",
    "sg:address":"2a Rodley Lane, Rodley",
    "sg:city":"Leeds",
    "sg:classifiers":[
        {
            "category":"Government",
            "subcategory":"Post Office",
            "type":"Public Place"
        }
    ],
    "sg:phone":"+44 113 256 4681",
    "sg:postcode":"LS13 1HU",
    "sg:province":"West Yorkshire",
    "wof:name":"Rodley Sub Post Office",
    "wof:placetype":"venue"
},
  "geometry": {"coordinates":[-1.6626909971,53.8232765198],"type":"Point"}
}