{
  "type": "Feature",
  "properties": {
    "addr:full":"The Grove, Moorside Consett Durham DH8 8EP",
    "addr:postcode":"dh8 8ep",
    "addr:street":"Consett",
    "iso:country":"GB",
    "sg:address":"The Grove, Moorside",
    "sg:city":"Consett",
    "sg:classifiers":[
        {
            "category":"Bars & Pubs",
            "type":"Food & Drink"
        }
    ],
    "sg:phone":"+44 1207 581443",
    "sg:postcode":"DH8 8EP",
    "sg:province":"Durham",
    "sg:tags":[
        "pubs",
        "inn"
    ],
    "wof:name":"Whitbread Hotel Co. Ltd.",
    "wof:placetype":"venue"
},
  "geometry": {"coordinates":[-1.8701360226,54.840801239],"type":"Point"}
}