{
  "type": "Feature",
  "properties": {
    "addr:full":"91a Philip Lane London Greater London N15 4JR",
    "addr:housenumber":"91a",
    "addr:postcode":"n15 4jr",
    "addr:street":"Philip Lane",
    "iso:country":"GB",
    "sg:address":"91a Philip Lane",
    "sg:city":"London",
    "sg:classifiers":[
        {
            "category":"Professional",
            "subcategory":"Engineering",
            "type":"Services"
        },
        {
            "category":"Building & Trades",
            "subcategory":"Electrical",
            "type":"Services"
        }
    ],
    "sg:phone":"+44 20 8292 7692",
    "sg:postcode":"N15 4JR",
    "sg:province":"Greater London",
    "sg:tags":[
        "engineer",
        "electrician",
        "contractor"
    ],
    "wof:name":"R P Electrical",
    "wof:placetype":"venue"
},
  "geometry": {"coordinates":[-0.0775939971,51.5893363953],"type":"Point"}
}