{
  "type": "Feature",
  "properties": {
    "iso:country":"GB",
    "sg:address":"Unit 4, Pandy Industrial Estate",
    "sg:city":"Wrexham",
    "sg:classifiers":[
        {
            "category":"Wholesale",
            "subcategory":"Construction Materials",
            "type":"Manufacturing & Wholesale Goods"
        }
    ],
    "sg:phone":"+44 1978 266319",
    "sg:postcode":"LL11 2UA",
    "sg:province":"Wrexham",
    "sg:tags":[
        "merchant",
        "glass"
    ],
    "wof:name":"J R Boyle (Wrexham) Ltd.",
    "wof:placetype":"venue"
},
  "geometry": {"coordinates":[-3.011343,53.102955],"type":"Point"}
}