{
  "type": "Feature",
  "properties": {
    "addr:full":"Market Hall, High Street Evesham Gloucestershire WR11 1YN",
    "addr:postcode":"wr11 1yn",
    "addr:street":"High Street",
    "iso:country":"GB",
    "sg:address":"Market Hall, High Street",
    "sg:city":"Evesham",
    "sg:classifiers":[
        {
            "category":"Deli",
            "type":"Food & Drink"
        }
    ],
    "sg:postcode":"WR11 1YN",
    "sg:province":"Gloucestershire",
    "sg:tags":[
        "delicatessen"
    ],
    "wof:name":"Cotswold Provisions Retail",
    "wof:placetype":"venue"
},
  "geometry": {"coordinates":[-1.9439690113,52.1063919067],"type":"Point"}
}