{
  "type": "Feature",
  "properties": {
    "addr:full":"6 Norjo An Villas Chesham Buckinghamshire HP5 1SA",
    "addr:housenumber":"6",
    "addr:postcode":"hp5 1sa",
    "addr:street":"An Villas",
    "iso:country":"GB",
    "sg:address":"6 Norjo An Villas",
    "sg:city":"Chesham",
    "sg:classifiers":[
        {
            "category":"Manufacturing",
            "subcategory":"Wood Products",
            "type":"Manufacturing & Wholesale Goods"
        }
    ],
    "sg:phone":"+44 1494 793238",
    "sg:postcode":"HP5 1SA",
    "sg:province":"Buckinghamshire",
    "sg:tags":[
        "maker",
        "cabinet"
    ],
    "wof:name":"Matthew Biddle Furniture",
    "wof:placetype":"venue"
},
  "geometry": {"coordinates":[-0.6093329787,51.7105369568],"type":"Point"}
}