{
  "type": "Feature",
  "properties": {
    "iso:country":"GB",
    "sg:address":"95 High St",
    "sg:city":"Lee On The Solent",
    "sg:classifiers":[
        {
            "category":"Shopping",
            "subcategory":"Thrift Store",
            "type":"Retail Goods"
        }
    ],
    "sg:phone":"+44 23 9255 6058",
    "sg:postcode":"PO13 9BU",
    "sg:province":"Hampshire",
    "sg:tags":[
        "shop",
        "charity"
    ],
    "wof:name":"The Rowans Hospice",
    "wof:placetype":"venue"
},
  "geometry": {"coordinates":[-1.201642,50.80114],"type":"Point"}
}