{
  "type": "Feature",
  "properties": {
    "iso:country":"GB",
    "sg:address":"The Old Customs House, Stanhope Street",
    "sg:city":"Goole",
    "sg:classifiers":[
        {
            "category":"Professional",
            "subcategory":"Engineering",
            "type":"Services"
        }
    ],
    "sg:phone":"+44 1405 760670",
    "sg:postcode":"DN14 5BQ",
    "sg:province":"East Riding of Yorkshire",
    "sg:tags":[
        "engineer",
        "mechanical"
    ],
    "wof:name":"Goole Welding Ltd.",
    "wof:placetype":"venue"
},
  "geometry": {"coordinates":[-0.875729,53.703304],"type":"Point"}
}