{
  "type": "Feature",
  "properties": {
    "addr:full":"Pump Lane, Purleigh Chelmsford Essex CM3 6PJ",
    "addr:postcode":"cm3 6pj",
    "addr:street":"Pump Lane",
    "iso:country":"GB",
    "sg:address":"Pump Lane, Purleigh",
    "sg:city":"Chelmsford",
    "sg:classifiers":[
        {
            "category":"Education",
            "subcategory":"School",
            "type":"Public Place"
        }
    ],
    "sg:phone":"+44 1621 828282",
    "sg:postcode":"CM3 6PJ",
    "sg:province":"Essex",
    "sg:tags":[
        "local",
        "authority"
    ],
    "wof:name":"Purleigh Community Primary School",
    "wof:placetype":"venue"
},
  "geometry": {"coordinates":[0.6582790017,51.6871528625],"type":"Point"}
}