{
  "type": "Feature",
  "properties": {
    "addr:full":"208 Manchester Road Huddersfield West Yorkshire HD1 3JF",
    "addr:housenumber":"208",
    "addr:postcode":"hd1 3jf",
    "addr:street":"Manchester Road",
    "iso:country":"GB",
    "sg:address":"208 Manchester Road",
    "sg:city":"Huddersfield",
    "sg:classifiers":[
        {
            "category":"Food & Beverages",
            "subcategory":"Supermarket",
            "type":"Retail Goods"
        }
    ],
    "sg:phone":"+44 1484 300477",
    "sg:postcode":"HD1 3JF",
    "sg:province":"West Yorkshire",
    "wof:name":"Nazar Supermarket",
    "wof:placetype":"venue"
},
  "geometry": {"coordinates":[-1.7984390259,53.6404876709],"type":"Point"}
}