{
  "type": "Feature",
  "properties": {
    "addr:full":"40 Greyhound Road London Greater London W6 8NX",
    "addr:housenumber":"40",
    "addr:postcode":"w6 8nx",
    "addr:street":"Greyhound Road",
    "iso:country":"GB",
    "sg:address":"40 Greyhound Road",
    "sg:city":"London",
    "sg:classifiers":[
        {
            "category":"Professional",
            "subcategory":"Printing & Photocopies",
            "type":"Services"
        }
    ],
    "sg:phone":"+44 24 7686 7755",
    "sg:postcode":"W6 8NX",
    "sg:province":"Greater London",
    "sg:tags":[
        "printer"
    ],
    "wof:name":"Oasis Printing & Copying",
    "wof:placetype":"venue"
},
  "geometry": {"coordinates":[-0.218125999,51.4850692749],"type":"Point"}
}