{
  "type": "Feature",
  "properties": {
    "addr:full":"9 Priory Road Newport Isle of Wight PO30 5JS",
    "addr:housenumber":"9",
    "addr:postcode":"po30 5js",
    "addr:street":"Priory Road",
    "iso:country":"GB",
    "sg:address":"9 Priory Road",
    "sg:city":"Newport",
    "sg:classifiers":[
        {
            "category":"Professional",
            "subcategory":"Testing Lab",
            "type":"Services"
        },
        {
            "category":"Autos & Motor Vehicles",
            "subcategory":"Motorcycle Sales",
            "type":"Retail Goods"
        }
    ],
    "sg:phone":"+44 1983 522160",
    "sg:postcode":"PO30 5JS",
    "sg:province":"Isle of Wight",
    "sg:tags":[
        "scooter",
        "cycle",
        "mot"
    ],
    "sg:website":"http://www.davedeathmotorcycles.co.uk",
    "wof:name":"Dave Death Motorcycles Iw Ltd",
    "wof:placetype":"venue"
},
  "geometry": {"coordinates":[-1.315871,50.692474],"type":"Point"}
}