{
  "type": "Feature",
  "properties": {
    "addr:full":"2 Elleray Corner, College Rd Windermere Cumbria LA23 1BU",
    "addr:housenumber":"2",
    "addr:postcode":"la23 1bu",
    "addr:street":"Elleray Corner College Rd",
    "iso:country":"GB",
    "sg:address":"2 Elleray Corner, College Rd",
    "sg:city":"Windermere",
    "sg:classifiers":[
        {
            "category":"Shopping",
            "subcategory":"Baby Store",
            "type":"Retail Goods"
        }
    ],
    "sg:phone":"+44 15394 47123",
    "sg:postcode":"LA23 1BU",
    "sg:province":"Cumbria",
    "sg:tags":[
        "babywear",
        "childrens"
    ],
    "wof:name":"Kids Kit",
    "wof:placetype":"venue"
},
  "geometry": {"coordinates":[-2.906404,54.379665],"type":"Point"}
}