{
  "type": "Feature",
  "properties": {
    "addr:full":"Castlepark Primary School, Carron Pl, 3 Castlepark Irvine North Ayrshire KA12 9LQ",
    "addr:housenumber":"3",
    "addr:postcode":"ka12 9lq",
    "addr:street":"Carron Pl;Castlepark",
    "iso:country":"GB",
    "sg:address":"Castlepark Primary School, Carron Pl, 3 Castlepark",
    "sg:city":"Irvine",
    "sg:classifiers":[
        {
            "category":"Government",
            "subcategory":"Office",
            "type":"Public Place"
        }
    ],
    "sg:phone":"+44 1294 279764",
    "sg:postcode":"KA12 9LQ",
    "sg:province":"North Ayrshire",
    "sg:tags":[
        "local"
    ],
    "wof:name":"Borth Ayrshire Council",
    "wof:placetype":"venue"
},
  "geometry": {"coordinates":[-4.66459,55.62986],"type":"Point"}
}