{
  "type": "Feature",
  "properties": {
    "addr:full":"Rosla Block, Cumber Lane, Whiston Prescot Cheshire L35 2XG",
    "addr:postcode":"l35 2xg",
    "addr:street":"Cumber Lane",
    "iso:country":"GB",
    "sg:address":"Rosla Block, Cumber Lane, Whiston",
    "sg:city":"Prescot",
    "sg:classifiers":[
        {
            "category":"Professional",
            "subcategory":"Employment Agencies",
            "type":"Services"
        }
    ],
    "sg:phone":"+44 151 493 2813",
    "sg:postcode":"L35 2XG",
    "sg:province":"Cheshire",
    "sg:tags":[
        "career",
        "guidance"
    ],
    "wof:name":"G M C P (Enterprise) Ltd.",
    "wof:placetype":"venue"
},
  "geometry": {"coordinates":[-2.7876989841,53.4208335876],"type":"Point"}
}