{
  "type": "Feature",
  "properties": {
    "addr:full":"1 Rosemount Court, Strood Rochester Kent ME2 3NF",
    "addr:housenumber":"1",
    "addr:postcode":"me2 3nf",
    "addr:street":"Rosemount Court",
    "iso:country":"GB",
    "sg:address":"1 Rosemount Court, Strood",
    "sg:city":"Rochester",
    "sg:classifiers":[
        {
            "category":"Communications",
            "type":"Services"
        }
    ],
    "sg:postcode":"ME2 3NF",
    "sg:province":"Kent",
    "sg:tags":[
        "tv",
        "video",
        "radio"
    ],
    "wof:name":"Aerial & Satellite Systems Ltd.",
    "wof:placetype":"venue"
},
  "geometry": {"coordinates":[0.488671,51.403786],"type":"Point"}
}