{
  "type": "Feature",
  "properties": {
    "iso:country":"GB",
    "sg:address":"Abbots House, Abbey St",
    "sg:city":"Reading",
    "sg:classifiers":[
        {
            "category":"Professional",
            "subcategory":"Accounting & Tax Preparation",
            "type":"Services"
        }
    ],
    "sg:phone":"+44 118 925 0024",
    "sg:postcode":"RG1 3BD",
    "sg:province":"Berkshire",
    "sg:tags":[
        "accountant"
    ],
    "wof:name":"Binder Hamlyn",
    "wof:placetype":"venue"
},
  "geometry": {"coordinates":[-0.9660419822,51.4553527832],"type":"Point"}
}