{
  "type": "Feature",
  "properties": {
    "addr:full":"2 Young Street Inverness Highland IV3 5BL",
    "addr:housenumber":"2",
    "addr:postcode":"iv3 5bl",
    "addr:street":"Young Street",
    "iso:country":"GB",
    "sg:address":"2 Young Street",
    "sg:city":"Inverness",
    "sg:classifiers":[
        {
            "category":"Restaurant",
            "type":"Food & Drink"
        }
    ],
    "sg:phone":"+44 1463 712678",
    "sg:postcode":"IV3 5BL",
    "sg:province":"Highland",
    "sg:tags":[
        "italian"
    ],
    "wof:name":"Casa Italia (Inverness) Ltd.",
    "wof:placetype":"venue"
},
  "geometry": {"coordinates":[-4.2283592224,57.4767990112],"type":"Point"}
}