{
  "type": "Feature",
  "properties": {
    "iso:country":"GB",
    "sg:address":"18 High Park Road",
    "sg:city":"Broadstone",
    "sg:classifiers":[
        {
            "category":"Professional",
            "subcategory":"Engineering",
            "type":"Services"
        }
    ],
    "sg:postcode":"BH18 9DE",
    "sg:province":"Dorset",
    "sg:tags":[
        "contractor",
        "electrical",
        "engineer"
    ],
    "wof:name":"Martin Barker Electrical",
    "wof:placetype":"venue"
},
  "geometry": {"coordinates":[-2.008689,50.763367],"type":"Point"}
}