{
  "type": "Feature",
  "properties": {
    "iso:country":"GB",
    "sg:address":"21 Prince Street",
    "sg:city":"Newport",
    "sg:classifiers":[
        {
            "category":"Building & Trades",
            "subcategory":"Cleaning & Sanitation",
            "type":"Services"
        }
    ],
    "sg:postcode":"NP19 8DS",
    "sg:province":"Newport",
    "sg:tags":[
        "asbestos",
        "removal"
    ],
    "wof:name":"Abercarn Asbestos & Waste Services",
    "wof:placetype":"venue"
},
  "geometry": {"coordinates":[-2.9837949276,51.5911941528],"type":"Point"}
}