{
  "type": "Feature",
  "properties": {
    "iso:country":"GB",
    "sg:address":"2 Springfield Close",
    "sg:city":"Mansfield",
    "sg:classifiers":[
        {
            "category":"Bus Charters",
            "type":"Transportation"
        }
    ],
    "sg:postcode":"NG18 3PB",
    "sg:province":"Nottinghamshire",
    "sg:tags":[
        "mini",
        "hire",
        "leasing"
    ],
    "wof:name":"Springfield Travel",
    "wof:placetype":"venue"
},
  "geometry": {"coordinates":[-1.1621929407,53.1380157471],"type":"Point"}
}