{
  "type": "Feature",
  "properties": {
    "addr:full":"1 Eastway, Eastfield Scarborough North Yorkshire YO11 3LS",
    "addr:housenumber":"1",
    "addr:postcode":"yo11 3ls",
    "addr:street":"Eastway Eastfield",
    "iso:country":"GB",
    "sg:address":"1 Eastway, Eastfield",
    "sg:city":"Scarborough",
    "sg:classifiers":[
        {
            "category":"Health Services",
            "subcategory":"Doctor",
            "type":"Services"
        }
    ],
    "sg:phone":"+44 1723 582297",
    "sg:postcode":"YO11 3LS",
    "sg:province":"North Yorkshire",
    "sg:tags":[
        "practitioners"
    ],
    "wof:name":"Sengupta Walker",
    "wof:placetype":"venue"
},
  "geometry": {"coordinates":[-0.3962669969,54.2401618958],"type":"Point"}
}