{
  "type": "Feature",
  "properties": {
    "addr:full":"Skippers Lane Middlesbrough North Yorkshire TS6 6UB",
    "addr:postcode":"ts6 6ub",
    "addr:street":"Skippers Lane",
    "iso:country":"GB",
    "sg:address":"Skippers Lane",
    "sg:city":"Middlesbrough",
    "sg:classifiers":[
        {
            "category":"Home & Garden",
            "subcategory":"Home Furnishings",
            "type":"Retail Goods"
        }
    ],
    "sg:phone":"+44 1642 453286",
    "sg:postcode":"TS6 6UB",
    "sg:province":"North Yorkshire",
    "sg:tags":[
        "furnishers",
        "planner",
        "kitchen"
    ],
    "wof:name":"Moben Kitchens",
    "wof:placetype":"venue"
},
  "geometry": {"coordinates":[-1.1827169657,54.5765228271],"type":"Point"}
}