{
  "type": "Feature",
  "properties": {
    "addr:full":"53 Monument St Monument Greater London EC3R 8BU",
    "addr:housenumber":"53",
    "addr:postcode":"ec3r 8bu",
    "addr:street":"Monument St",
    "iso:country":"GB",
    "sg:address":"53 Monument St",
    "sg:city":"Monument",
    "sg:classifiers":[
        {
            "category":"Real Estate",
            "subcategory":"Architect",
            "type":"Services"
        }
    ],
    "sg:phone":"+44 20 7623 1515",
    "sg:postcode":"EC3R 8BU",
    "sg:province":"Greater London",
    "wof:name":"Yeoman McAllister Architects",
    "wof:placetype":"venue"
},
  "geometry": {"coordinates":[-0.08439,51.50946],"type":"Point"}
}