{
  "type": "Feature",
  "properties": {
    "addr:full":"Wycoller Country Park, Wycoller Road, Trawden Colne Lancashire BB8 8SY",
    "addr:postcode":"bb8 8sy",
    "addr:street":"Park Wycoller Road",
    "iso:country":"GB",
    "sg:address":"Wycoller Country Park, Wycoller Road, Trawden",
    "sg:city":"Colne",
    "sg:classifiers":[
        {
            "category":"Transit Center",
            "subcategory":"Freight",
            "type":"Transportation"
        }
    ],
    "sg:postcode":"BB8 8SY",
    "sg:province":"Lancashire",
    "sg:tags":[
        "shop",
        "craft",
        "centre"
    ],
    "wof:name":"Wycoller Craft Centre",
    "wof:placetype":"venue"
},
  "geometry": {"coordinates":[-2.1359539032,53.8467216492],"type":"Point"}
}