{
  "type": "Feature",
  "properties": {
    "addr:full":"99 Fishbourne Rd West Chichester West Sussex PO19 3JP",
    "addr:housenumber":"99",
    "addr:postcode":"po19 3jp",
    "addr:street":"Fishbourne Rd West",
    "iso:country":"GB",
    "sg:address":"99 Fishbourne Rd West",
    "sg:city":"Chichester",
    "sg:classifiers":[
        {
            "category":"Bars & Pubs",
            "type":"Food & Drink"
        }
    ],
    "sg:phone":"+44 1243 839895",
    "sg:postcode":"PO19 3JP",
    "sg:province":"West Sussex",
    "sg:tags":[
        "pubs",
        "inn"
    ],
    "wof:name":"The Bulls Head",
    "wof:placetype":"venue"
},
  "geometry": {"coordinates":[-0.8090059757,50.8353767395],"type":"Point"}
}