{
  "type": "Feature",
  "properties": {
    "addr:full":"Malvern Road Gloucester Gloucestershire GL19 3AQ",
    "addr:postcode":"gl19 3aq",
    "addr:street":"Malvern Road",
    "iso:country":"GB",
    "sg:address":"Malvern Road",
    "sg:city":"Gloucester",
    "sg:classifiers":[
        {
            "category":"Retail",
            "subcategory":"Auto Repair",
            "type":"Services"
        }
    ],
    "sg:phone":"+44 1452 840201",
    "sg:postcode":"GL19 3AQ",
    "sg:province":"Gloucestershire",
    "sg:tags":[
        "modification",
        "garage"
    ],
    "wof:name":"Staunton Cross Garage",
    "wof:placetype":"venue"
},
  "geometry": {"coordinates":[-2.3022770882,51.9659500122],"type":"Point"}
}