{
  "type": "Feature",
  "properties": {
    "addr:full":"22a Moorend Park Road Cheltenham Gloucestershire GL53 0JY",
    "addr:housenumber":"22a",
    "addr:postcode":"gl53 0jy",
    "addr:street":"Moorend Park Road",
    "iso:country":"GB",
    "sg:address":"22a Moorend Park Road",
    "sg:city":"Cheltenham",
    "sg:classifiers":[
        {
            "category":"Health Services",
            "subcategory":"Clinic",
            "type":"Services"
        }
    ],
    "sg:postcode":"GL53 0JY",
    "sg:province":"Gloucestershire",
    "sg:tags":[
        "private"
    ],
    "wof:name":"Spectrum Clinic",
    "wof:placetype":"venue"
},
  "geometry": {"coordinates":[-2.085936,51.884457],"type":"Point"}
}