{
  "type": "Feature",
  "properties": {
    "iso:country":"GB",
    "sg:address":"18 Colliers Walk",
    "sg:city":"Bristol",
    "sg:classifiers":[
        {
            "category":"Shopping",
            "type":"Retail Goods"
        }
    ],
    "sg:phone":"+44 1275 852852",
    "sg:postcode":"BS48 1RG",
    "sg:province":"Somerset",
    "sg:tags":[
        "part",
        "accessory"
    ],
    "wof:name":"Autopoint-Car Care",
    "wof:placetype":"venue"
},
  "geometry": {"coordinates":[-2.744785,51.435841],"type":"Point"}
}