{
  "type": "Feature",
  "properties": {
    "iso:country":"GB",
    "sg:address":"Main Road, Wrangle",
    "sg:city":"Boston",
    "sg:classifiers":[
        {
            "category":"Autos & Motor Vehicles",
            "subcategory":"Automobile Sales",
            "type":"Retail Goods"
        }
    ],
    "sg:phone":"+44 1205 870016",
    "sg:postcode":"PE22 9AX",
    "sg:province":"Lincolnshire",
    "sg:tags":[
        "car"
    ],
    "wof:name":"J & S Motors",
    "wof:placetype":"venue"
},
  "geometry": {"coordinates":[0.1088339984,53.0313682556],"type":"Point"}
}