{
  "type": "Feature",
  "properties": {
    "addr:full":"Cedar Barn, Cedar Avenue, Hazlemere High Wycombe Buckinghamshire HP15 7DW",
    "addr:postcode":"hp15 7dw",
    "addr:street":"Cedar;Cedar Avenue",
    "iso:country":"GB",
    "sg:address":"Cedar Barn, Cedar Avenue, Hazlemere",
    "sg:city":"High Wycombe",
    "sg:classifiers":[
        {
            "category":"Health Services",
            "subcategory":"Hospice",
            "type":"Services"
        }
    ],
    "sg:phone":"+44 1494 713888",
    "sg:postcode":"HP15 7DW",
    "sg:province":"Buckinghamshire",
    "wof:name":"Iain Rennie Hospice At Home",
    "wof:placetype":"venue"
},
  "geometry": {"coordinates":[-0.708729,51.651031],"type":"Point"}
}