{
  "type": "Feature",
  "properties": {
    "iso:country":"GB",
    "sg:address":"Sompting Road",
    "sg:city":"Worthing",
    "sg:classifiers":[
        {
            "category":"Home & Garden",
            "subcategory":"Home Furnishings",
            "type":"Retail Goods"
        }
    ],
    "sg:phone":"+44 1903 522555",
    "sg:postcode":"BN14 9EW",
    "sg:province":"West Sussex",
    "sg:tags":[
        "furnishers",
        "planner",
        "kitchen"
    ],
    "wof:name":"Crestneat Ltd.",
    "wof:placetype":"venue"
},
  "geometry": {"coordinates":[-0.367089,50.832516],"type":"Point"}
}