{
  "type": "Feature",
  "properties": {
    "addr:full":"14-16 St Annes Road West Lytham St Annes Lancashire FY8 1RF",
    "addr:housenumber":"14-16",
    "addr:postcode":"fy8 1rf",
    "addr:street":"St Annes Road West;St",
    "iso:country":"GB",
    "sg:address":"14-16 St Annes Road West",
    "sg:city":"Lytham St Annes",
    "sg:classifiers":[
        {
            "category":"Shopping",
            "subcategory":"Clothing, Apparel, & Fashions",
            "type":"Retail Goods"
        }
    ],
    "sg:phone":"+44 1253 713334",
    "sg:postcode":"FY8 1RF",
    "sg:province":"Lancashire",
    "sg:tags":[
        "shop"
    ],
    "wof:name":"Mackays",
    "wof:placetype":"venue"
},
  "geometry": {"coordinates":[-3.032020092,53.7509613037],"type":"Point"}
}