{
  "type": "Feature",
  "properties": {
    "addr:full":"1 Gordon House Road London Greater London NW5 1LN",
    "addr:housenumber":"1",
    "addr:postcode":"nw5 1ln",
    "addr:street":"Gordon House Road",
    "iso:country":"GB",
    "sg:address":"1 Gordon House Road",
    "sg:city":"London",
    "sg:classifiers":[
        {
            "category":"Place Of Worship",
            "type":"Public Place"
        }
    ],
    "sg:phone":"+44 20 7485 5524",
    "sg:postcode":"NW5 1LN",
    "sg:province":"Greater London",
    "wof:name":"Church of St. Cosmas & Damianos",
    "wof:placetype":"venue"
},
  "geometry": {"coordinates":[-0.146624,51.556423],"type":"Point"}
}