{
  "type": "Feature",
  "properties": {
    "addr:full":"Chisholm Pl Hexham Northumberland NE46 1QL",
    "addr:postcode":"ne46 1ql",
    "addr:street":"Chisholm Pl",
    "iso:country":"GB",
    "sg:address":"Chisholm Pl",
    "sg:city":"Hexham",
    "sg:classifiers":[
        {
            "category":"Organizations",
            "subcategory":"Membership Organization",
            "type":"Services"
        }
    ],
    "sg:phone":"+44 1434 602558",
    "sg:postcode":"NE46 1QL",
    "sg:province":"Northumberland",
    "sg:tags":[
        "club"
    ],
    "wof:name":"Eastgarth Club",
    "wof:placetype":"venue"
},
  "geometry": {"coordinates":[-2.101294,54.970036],"type":"Point"}
}