{
  "type": "Feature",
  "properties": {
    "iso:country":"GB",
    "sg:address":"Old Mill Works, The Street",
    "sg:city":"Great Yarmouth",
    "sg:classifiers":[
        {
            "category":"Autos & Motor Vehicles",
            "subcategory":"Boat Sales",
            "type":"Retail Goods"
        }
    ],
    "sg:phone":"+44 1692 582180",
    "sg:postcode":"NR29 5DH",
    "sg:province":"Norfolk",
    "sg:tags":[
        "repair",
        "builder"
    ],
    "wof:name":"Haines Marine Ltd.",
    "wof:placetype":"venue"
},
  "geometry": {"coordinates":[1.58972,52.700386],"type":"Point"}
}