{
  "type": "Feature",
  "properties": {
    "iso:country":"GB",
    "sg:address":"2 Fore Street, Ide",
    "sg:city":"Exeter",
    "sg:classifiers":[
        {
            "category":"Health Services",
            "subcategory":"Clinic",
            "type":"Services"
        }
    ],
    "sg:postcode":"EX2 9RQ",
    "sg:province":"Devon",
    "sg:tags":[
        "aromatherapy"
    ],
    "wof:name":"Kobashi Essential Oils",
    "wof:placetype":"venue"
},
  "geometry": {"coordinates":[-3.557558,50.704918],"type":"Point"}
}