{
  "type": "Feature",
  "properties": {
    "addr:full":"3 Whitmore Road Birmingham West Midlands B10 0NR",
    "addr:housenumber":"3",
    "addr:postcode":"b10 0nr",
    "addr:street":"Whitmore Road",
    "iso:country":"GB",
    "sg:address":"3 Whitmore Road",
    "sg:city":"Birmingham",
    "sg:classifiers":[
        {
            "category":"Shopping",
            "subcategory":"Used Merchandise",
            "type":"Retail Goods"
        }
    ],
    "sg:postcode":"B10 0NR",
    "sg:province":"West Midlands",
    "sg:tags":[
        "shop",
        "second-hand"
    ],
    "wof:name":"Bits & Bobs",
    "wof:placetype":"venue"
},
  "geometry": {"coordinates":[-1.8629020452,52.4710235596],"type":"Point"}
}