{
  "type": "Feature",
  "properties": {
    "iso:country":"GB",
    "sg:address":"197 Waterloo Rd",
    "sg:city":"Wolverhampton",
    "sg:classifiers":[
        {
            "category":"Place Of Worship",
            "type":"Public Place"
        }
    ],
    "sg:phone":"+44 1902 312232",
    "sg:postcode":"WV1 4RA",
    "sg:province":"West Midlands",
    "wof:name":"Wolverhampton Mosque Trust",
    "wof:placetype":"venue"
},
  "geometry": {"coordinates":[-2.1293931007,52.5961875916],"type":"Point"}
}