{
  "type": "Feature",
  "properties": {
    "addr:full":"1 Millfield Cambridge Cambridgeshire CB4 8RE",
    "addr:housenumber":"1",
    "addr:postcode":"cb4 8re",
    "addr:street":"Millfield",
    "iso:country":"GB",
    "sg:address":"1 Millfield",
    "sg:city":"Cambridge",
    "sg:classifiers":[
        {
            "category":"Building & Trades",
            "subcategory":"Cleaning & Sanitation",
            "type":"Services"
        }
    ],
    "sg:phone":"+44 1954 251380",
    "sg:postcode":"CB4 8RE",
    "sg:province":"Cambridgeshire",
    "sg:tags":[
        "polishing",
        "floor"
    ],
    "wof:name":"Cambridge Traditional Products",
    "wof:placetype":"venue"
},
  "geometry": {"coordinates":[0.1308789998,52.2889862061],"type":"Point"}
}