{
  "type": "Feature",
  "properties": {
    "addr:full":"27 Cheriton Gdns Folkestone Kent CT20 2AR",
    "addr:housenumber":"27",
    "addr:postcode":"ct20 2ar",
    "addr:street":"Cheriton Gdns",
    "iso:country":"GB",
    "sg:address":"27 Cheriton Gdns",
    "sg:city":"Folkestone",
    "sg:classifiers":[
        {
            "category":"Real Estate",
            "subcategory":"Real Estate Agent",
            "type":"Services"
        }
    ],
    "sg:postcode":"CT20 2AR",
    "sg:province":"Kent",
    "wof:name":"Bowles Well Gardens Estate Ltd",
    "wof:placetype":"venue"
},
  "geometry": {"coordinates":[1.1758290529,51.0788192749],"type":"Point"}
}