{
  "type": "Feature",
  "properties": {
    "addr:full":"Kelvin Hall International Sports Arena, Argyle St Glasgow Glasgow City G3 8AW",
    "addr:postcode":"g3 8aw",
    "addr:street":"Argyle St",
    "iso:country":"GB",
    "sg:address":"Kelvin Hall International Sports Arena, Argyle St",
    "sg:city":"Glasgow",
    "sg:classifiers":[
        {
            "category":"Arena",
            "subcategory":"Sports Club",
            "type":"Entertainment"
        }
    ],
    "sg:postcode":"G3 8AW",
    "sg:province":"Glasgow City",
    "wof:name":"Scottish Amateur Wrestling Association",
    "wof:placetype":"venue"
},
  "geometry": {"coordinates":[-4.29415,55.868542],"type":"Point"}
}