{
  "type": "Feature",
  "properties": {
    "addr:full":"302 Acton High Street London Greater London W3 9BJ",
    "addr:housenumber":"302",
    "addr:postcode":"w3 9bj",
    "addr:street":"Acton High Street",
    "iso:country":"GB",
    "sg:address":"302 Acton High Street",
    "sg:city":"London",
    "sg:classifiers":[
        {
            "category":"Professional",
            "subcategory":"Employment Agencies",
            "type":"Services"
        }
    ],
    "sg:phone":"+44 20 8993 6113",
    "sg:postcode":"W3 9BJ",
    "sg:province":"Greater London",
    "sg:tags":[
        "consultant"
    ],
    "wof:name":"Plan Personnel",
    "wof:placetype":"venue"
},
  "geometry": {"coordinates":[-0.27607,51.508411],"type":"Point"}
}