{
  "type": "Feature",
  "properties": {
    "iso:country":"GB",
    "sg:address":"225 Rosemount Place",
    "sg:city":"Aberdeen",
    "sg:classifiers":[
        {
            "category":"Professional",
            "subcategory":"Accounting & Tax Preparation",
            "type":"Services"
        }
    ],
    "sg:phone":"+44 1224 626226",
    "sg:postcode":"AB25 2XS",
    "sg:province":"Aberdeen City",
    "sg:tags":[
        "accountant"
    ],
    "wof:name":"Gardner & Partners",
    "wof:placetype":"venue"
},
  "geometry": {"coordinates":[-2.119477,57.149487],"type":"Point"}
}