{
  "type": "Feature",
  "properties": {
    "addr:full":"Unit 11b, The Corn Exchange Market Buildings Maidstone Kent ME14 1HP",
    "addr:housenumber":"unit 11b",
    "addr:postcode":"me14 1hp",
    "addr:street":"The",
    "iso:country":"GB",
    "sg:address":"Unit 11b, The Corn Exchange Market Buildings",
    "sg:city":"Maidstone",
    "sg:classifiers":[
        {
            "category":"Shopping",
            "subcategory":"Hobbies, Toys, & Games",
            "type":"Retail Goods"
        },
        {
            "category":"Government",
            "subcategory":"Customs House",
            "type":"Public Place"
        }
    ],
    "sg:phone":"+44 1622 755116",
    "sg:postcode":"ME14 1HP",
    "sg:province":"Kent",
    "sg:tags":[
        "doll",
        "dolls'"
    ],
    "wof:name":"Cornfield Miniatures",
    "wof:placetype":"venue"
},
  "geometry": {"coordinates":[0.5250849724,51.2737998962],"type":"Point"}
}