{
  "type": "Feature",
  "properties": {
    "addr:full":"Town Farm, Templeton Tiverton Devon EX16 8BL",
    "addr:postcode":"ex16 8bl",
    "addr:street":"Templeton",
    "iso:country":"GB",
    "sg:address":"Town Farm, Templeton",
    "sg:city":"Tiverton",
    "sg:classifiers":[
        {
            "category":"Farming",
            "subcategory":"Farm",
            "type":"Manufacturing & Wholesale Goods"
        }
    ],
    "sg:postcode":"EX16 8BL",
    "sg:province":"Devon",
    "sg:tags":[
        "mixed",
        "crop"
    ],
    "wof:name":"William Withers",
    "wof:placetype":"venue"
},
  "geometry": {"coordinates":[-3.584364,50.914906],"type":"Point"}
}