{
  "type": "Feature",
  "properties": {
    "addr:full":"Chapel School Room, Helstone Camelford Cornwall PL32 9RL",
    "addr:postcode":"pl32 9rl",
    "addr:street":"Helstone",
    "iso:country":"GB",
    "sg:address":"Chapel School Room, Helstone",
    "sg:city":"Camelford",
    "sg:classifiers":[
        {
            "category":"Manufacturing",
            "subcategory":"Pottery",
            "type":"Manufacturing & Wholesale Goods"
        }
    ],
    "sg:postcode":"PL32 9RL",
    "sg:province":"Cornwall",
    "sg:tags":[
        "supplier"
    ],
    "wof:name":"Lustere Pottery",
    "wof:placetype":"venue"
},
  "geometry": {"coordinates":[-4.678636,50.623116],"type":"Point"}
}