{
  "type": "Feature",
  "properties": {
    "addr:full":"Unit 22 Mitre Bridge Industrial Park, Scrubbs Lane London Greater London W10 6AH",
    "addr:housenumber":"unit 22",
    "addr:postcode":"w10 6ah",
    "addr:street":"Mitre Bridge Industrial Park Scrubbs Lane",
    "iso:country":"GB",
    "sg:address":"Unit 22 Mitre Bridge Industrial Park, Scrubbs Lane",
    "sg:city":"London",
    "sg:classifiers":[
        {
            "category":"Professional",
            "subcategory":"Art Services",
            "type":"Services"
        }
    ],
    "sg:phone":"+44 20 8960 6121",
    "sg:postcode":"W10 6AH",
    "sg:province":"Greater London",
    "sg:tags":[
        "model",
        "maker"
    ],
    "wof:name":"Every Body's Display",
    "wof:placetype":"venue"
},
  "geometry": {"coordinates":[-0.2282599956,51.5203285217],"type":"Point"}
}