{
  "type": "Feature",
  "properties": {
    "iso:country":"GB",
    "sg:address":"28 Western Ave",
    "sg:city":"Acton",
    "sg:classifiers":[
        {
            "category":"Restaurant",
            "type":"Food & Drink"
        }
    ],
    "sg:phone":"+44 20 8749 6625",
    "sg:postcode":"W3 7TZ",
    "sg:province":"Greater London",
    "sg:tags":[
        "indian"
    ],
    "wof:name":"Gangadin Indian Cuisine",
    "wof:placetype":"venue"
},
  "geometry": {"coordinates":[-0.250907,51.514084],"type":"Point"}
}