{
  "type": "Feature",
  "properties": {
    "addr:full":"23 Buckingham Gate Westminster Greater London SW1E 6LB",
    "addr:housenumber":"23",
    "addr:postcode":"sw1e 6lb",
    "addr:street":"Buckingham Gate",
    "iso:country":"GB",
    "sg:address":"23 Buckingham Gate",
    "sg:city":"Westminster",
    "sg:classifiers":[
        {
            "category":"Professional",
            "subcategory":"Computer Services",
            "type":"Services"
        }
    ],
    "sg:phone":"+44 171 828 8087",
    "sg:postcode":"SW1E 6LB",
    "sg:province":"Greater London",
    "sg:tags":[
        "consultant"
    ],
    "wof:name":"Heed Ltd",
    "wof:placetype":"venue"
},
  "geometry": {"coordinates":[-0.139707,51.499405],"type":"Point"}
}