{
  "type": "Feature",
  "properties": {
    "addr:full":"Coronation Road, Cressex Business Park High Wycombe Buckinghamshire HP12 3RP",
    "addr:postcode":"hp12 3rp",
    "addr:street":"Coronation Road Cressex Business Park High",
    "iso:country":"GB",
    "sg:address":"Coronation Road, Cressex Business Park",
    "sg:city":"High Wycombe",
    "sg:classifiers":[
        {
            "category":"Building & Trades",
            "subcategory":"Landscaping Services",
            "type":"Services"
        },
        {
            "category":"Professional",
            "subcategory":"Engineering",
            "type":"Services"
        },
        {
            "category":"Retail",
            "subcategory":"Auto Rental",
            "type":"Services"
        }
    ],
    "sg:phone":"+44 1494 522072",
    "sg:postcode":"HP12 3RP",
    "sg:province":"Buckinghamshire",
    "sg:tags":[
        "machine",
        "consultant",
        "tool",
        "sale",
        "horticultural"
    ],
    "wof:name":"Merit Machine Tools",
    "wof:placetype":"venue"
},
  "geometry": {"coordinates":[-0.768216,51.618961],"type":"Point"}
}