{
  "type": "Feature",
  "properties": {
    "iso:country":"GB",
    "sg:address":"2 New Road",
    "sg:city":"St Ives",
    "sg:classifiers":[
        {
            "category":"Shopping",
            "subcategory":"Books",
            "type":"Retail Goods"
        },
        {
            "category":"Wholesale",
            "subcategory":"Books, Periodicals, & Newspapers",
            "type":"Manufacturing & Wholesale Goods"
        }
    ],
    "sg:phone":"+44 1480 494515",
    "sg:postcode":"PE27 5BG",
    "sg:province":"Cambridgeshire",
    "sg:tags":[
        "publisher"
    ],
    "sg:website":"http://www.mdsl-net.com",
    "wof:name":"The Multimedia Design Studio Ltd",
    "wof:placetype":"venue"
},
  "geometry": {"coordinates":[-0.0691519976,52.3219299316],"type":"Point"}
}