{
  "type": "Feature",
  "properties": {
    "addr:full":"19 Osborne Street Colchester Essex CO2 7DP",
    "addr:housenumber":"19",
    "addr:postcode":"co2 7dp",
    "addr:street":"Osborne Street",
    "iso:country":"GB",
    "sg:address":"19 Osborne Street",
    "sg:city":"Colchester",
    "sg:classifiers":[
        {
            "category":"Restaurant",
            "type":"Food & Drink"
        }
    ],
    "sg:phone":"+44 1206 574486",
    "sg:postcode":"CO2 7DP",
    "sg:province":"Essex",
    "sg:tags":[
        "indian",
        "-"
    ],
    "wof:name":"Alishan Tandoori",
    "wof:placetype":"venue"
},
  "geometry": {"coordinates":[0.908010006,51.8775482178],"type":"Point"}
}