{
  "type": "Feature",
  "properties": {
    "iso:country":"GB",
    "sg:address":"Plymouth Rd, Barnt Green",
    "sg:city":"Birmingham",
    "sg:classifiers":[
        {
            "category":"Professional",
            "subcategory":"Employment Agencies",
            "type":"Services"
        }
    ],
    "sg:phone":"+44 121 447 8228",
    "sg:postcode":"B45 8JF",
    "sg:province":"West Midlands",
    "sg:tags":[
        "introduction"
    ],
    "wof:name":"Elite Introductions",
    "wof:placetype":"venue"
},
  "geometry": {"coordinates":[-1.988644,52.364037],"type":"Point"}
}