{
  "type": "Feature",
  "properties": {
    "iso:country":"GB",
    "sg:address":"Unit 14 Belvedere Trading Estate",
    "sg:city":"Taunton",
    "sg:classifiers":[
        {
            "category":"Building & Trades",
            "subcategory":"Plumbing",
            "type":"Services"
        }
    ],
    "sg:phone":"+44 1823 252396",
    "sg:postcode":"TA1 1BH",
    "sg:province":"Somerset",
    "sg:tags":[
        "drain",
        "clearance",
        "sewer"
    ],
    "wof:name":"Davidrain Services",
    "wof:placetype":"venue"
},
  "geometry": {"coordinates":[-3.107693,51.02264],"type":"Point"}
}