{
  "type": "Feature",
  "properties": {
    "addr:full":"C/o Swain & Co Ltd 1st Floor, St Johns House Wolverhampton West Midlands WV2 4BH",
    "addr:housenumber":"1st floor st",
    "addr:postcode":"wv2 4bh",
    "addr:street":"C / O",
    "iso:country":"GB",
    "sg:address":"C/o Swain & Co Ltd 1st Floor, St Johns House",
    "sg:city":"Wolverhampton",
    "sg:classifiers":[
        {
            "category":"Home & Garden",
            "subcategory":"Hardware",
            "type":"Retail Goods"
        }
    ],
    "sg:postcode":"WV2 4BH",
    "sg:province":"West Midlands",
    "sg:tags":[
        "compressor",
        "air"
    ],
    "wof:name":"Pro-Air Compressor Services Ltd.",
    "wof:placetype":"venue"
},
  "geometry": {"coordinates":[-2.12953,52.58131],"type":"Point"}
}