{
  "type": "Feature",
  "properties": {
    "addr:full":"Boldon La South Shields Tyne and Wear NE34 0LZ",
    "addr:postcode":"ne34 0lz",
    "iso:country":"GB",
    "sg:address":"Boldon La",
    "sg:city":"South Shields",
    "sg:classifiers":[
        {
            "category":"Community Center",
            "type":"Public Place"
        }
    ],
    "sg:phone":"+44 191 427 0011",
    "sg:postcode":"NE34 0LZ",
    "sg:province":"Tyne and Wear",
    "sg:tags":[
        "centre"
    ],
    "wof:name":"Boldon Lane Community Association",
    "wof:placetype":"venue"
},
  "geometry": {"coordinates":[-1.4386999607,54.9692306519],"type":"Point"}
}