{
  "type": "Feature",
  "properties": {
    "iso:country":"GB",
    "sg:address":"136-142a Colindale Ave",
    "sg:city":"London",
    "sg:classifiers":[
        {
            "category":"Social Services",
            "subcategory":"Adult Care",
            "type":"Services"
        }
    ],
    "sg:postcode":"NW9 5HU",
    "sg:province":"Greater London",
    "sg:tags":[
        "housing",
        "sheltered"
    ],
    "wof:name":"Colindale Avenue Sheltered Housing",
    "wof:placetype":"venue"
},
  "geometry": {"coordinates":[-0.251356,51.594337],"type":"Point"}
}