{
  "type": "Feature",
  "properties": {
    "addr:full":"Victoria Gate Taunton Somerset TA1 3HZ",
    "addr:postcode":"ta1 3hz",
    "addr:street":"Victoria Gate",
    "iso:country":"GB",
    "sg:address":"Victoria Gate",
    "sg:city":"Taunton",
    "sg:classifiers":[
        {
            "category":"Social Services",
            "subcategory":"Adult Care",
            "type":"Services"
        },
        {
            "category":"Government",
            "subcategory":"Office",
            "type":"Public Place"
        }
    ],
    "sg:phone":"+44 1823 286205",
    "sg:postcode":"TA1 3HZ",
    "sg:province":"Somerset",
    "sg:tags":[
        "housing",
        "local",
        "sheltered"
    ],
    "wof:name":"Victoria Gate Sheltered Housing",
    "wof:placetype":"venue"
},
  "geometry": {"coordinates":[-3.091734,51.017365],"type":"Point"}
}