{
  "type": "Feature",
  "properties": {
    "iso:country":"GB",
    "sg:address":"Unit 4, Herring Fishery Score",
    "sg:city":"Lowestoft",
    "sg:classifiers":[
        {
            "category":"Education",
            "subcategory":"Special Training",
            "type":"Public Place"
        }
    ],
    "sg:phone":"+44 1502 573200",
    "sg:postcode":"NR32 1XE",
    "sg:province":"Suffolk",
    "sg:tags":[
        "product",
        "centre"
    ],
    "wof:name":"Breakout",
    "wof:placetype":"venue"
},
  "geometry": {"coordinates":[1.75629,52.479111],"type":"Point"}
}