{
  "type": "Feature",
  "properties": {
    "iso:country":"GB",
    "sg:address":"Quayside Park",
    "sg:city":"Maldon",
    "sg:classifiers":[
        {
            "category":"Freight",
            "type":"Transportation"
        },
        {
            "category":"Professional",
            "subcategory":"Business Services",
            "type":"Services"
        }
    ],
    "sg:phone":"+44 1621 859768",
    "sg:postcode":"CM9 5FA",
    "sg:province":"Essex",
    "sg:tags":[
        "import",
        "export",
        "agent",
        "forwarders"
    ],
    "wof:name":"Skantrans P S L Ltd.",
    "wof:placetype":"venue"
},
  "geometry": {"coordinates":[0.675249,51.731377],"type":"Point"}
}