{
  "type": "Feature",
  "properties": {
    "addr:full":"123 Brick Lane London Greater London E1 6SE",
    "addr:housenumber":"123",
    "addr:postcode":"e1 6se",
    "addr:street":"Brick Lane",
    "iso:country":"GB",
    "sg:address":"123 Brick Lane",
    "sg:city":"London",
    "sg:classifiers":[
        {
            "category":"Real Estate",
            "subcategory":"Real Estate Agent",
            "type":"Services"
        }
    ],
    "sg:phone":"+44 20 7739 7172",
    "sg:postcode":"E1 6SE",
    "sg:province":"Greater London",
    "wof:name":"Eastender Estate Agents Ltd.",
    "wof:placetype":"venue"
},
  "geometry": {"coordinates":[-0.0718789995,51.5203018188],"type":"Point"}
}