{
  "type": "Feature",
  "properties": {
    "addr:full":"32 Foxley La Purley Surrey CR8 3EE",
    "addr:housenumber":"32",
    "addr:postcode":"cr8 3ee",
    "addr:street":"Foxley La Purley",
    "iso:country":"GB",
    "sg:address":"32 Foxley La",
    "sg:city":"Purley",
    "sg:classifiers":[
        {
            "category":"Health Services",
            "subcategory":"Doctor",
            "type":"Services"
        }
    ],
    "sg:phone":"+44 20 8660 1304",
    "sg:postcode":"CR8 3EE",
    "sg:province":"Surrey",
    "sg:tags":[
        "practitioners"
    ],
    "wof:name":"Carlisle, J M",
    "wof:placetype":"venue"
},
  "geometry": {"coordinates":[-0.123858,51.341019],"type":"Point"}
}