{
  "type": "Feature",
  "properties": {
    "addr:full":"82 Hill St Alloa Clackmannanshire FK10 2LW",
    "addr:housenumber":"82",
    "addr:postcode":"fk10 2lw",
    "addr:street":"Hill St",
    "iso:country":"GB",
    "sg:address":"82 Hill St",
    "sg:city":"Alloa",
    "sg:classifiers":[
        {
            "category":"Shopping",
            "subcategory":"News",
            "type":"Retail Goods"
        }
    ],
    "sg:phone":"+44 1259 724005",
    "sg:postcode":"FK10 2LW",
    "sg:province":"Clackmannanshire",
    "sg:tags":[
        "newsagent"
    ],
    "wof:name":"S Matchett",
    "wof:placetype":"venue"
},
  "geometry": {"coordinates":[-3.7965459824,56.1203422546],"type":"Point"}
}