{
  "type": "Feature",
  "properties": {
    "addr:full":"Unit F Harbet Road, Lea Valley Trading Estate, Edmonton London Greater London N18 3LD",
    "addr:postcode":"n18 3ld",
    "addr:street":"Harbet Road Lea",
    "iso:country":"GB",
    "sg:address":"Unit F Harbet Road, Lea Valley Trading Estate, Edmonton",
    "sg:city":"London",
    "sg:classifiers":[
        {
            "category":"Government",
            "subcategory":"Fire Station",
            "type":"Public Place"
        }
    ],
    "sg:phone":"+44 20 8884 3458",
    "sg:postcode":"N18 3LD",
    "sg:province":"Greater London",
    "sg:tags":[
        "w'sale",
        "lighting"
    ],
    "wof:name":"Segal Electrical Co.",
    "wof:placetype":"venue"
},
  "geometry": {"coordinates":[-0.038144,51.611671],"type":"Point"}
}