{
  "type": "Feature",
  "properties": {
    "iso:country":"GB",
    "sg:address":"21 Holburn Viaduct",
    "sg:city":"London",
    "sg:classifiers":[
        {
            "category":"Autos & Motor Vehicles",
            "subcategory":"Automobile Sales",
            "type":"Retail Goods"
        }
    ],
    "sg:postcode":"EC1A 2DY",
    "sg:province":"Greater London",
    "sg:tags":[
        "car"
    ],
    "wof:name":"M C Deliveries Ltd",
    "wof:placetype":"venue"
},
  "geometry": {"coordinates":[-0.104634,51.516945],"type":"Point"}
}