{
  "type": "Feature",
  "properties": {
    "iso:country":"GB",
    "sg:address":"636 Birmingham Rd, Lydiate Ash",
    "sg:city":"Bromsgrove",
    "sg:classifiers":[
        {
            "category":"Professional",
            "subcategory":"Accounting & Tax Preparation",
            "type":"Services"
        }
    ],
    "sg:postcode":"B61 0QB",
    "sg:province":"Worcestershire",
    "sg:tags":[
        "accountant"
    ],
    "wof:name":"Stewart & Co",
    "wof:placetype":"venue"
},
  "geometry": {"coordinates":[-2.041306,52.376278],"type":"Point"}
}