{
  "type": "Feature",
  "properties": {
    "iso:country":"GB",
    "sg:address":"115 Vere Road, Kirkmuirhill",
    "sg:city":"Lanark",
    "sg:classifiers":[
        {
            "category":"Parking",
            "type":"Transportation"
        }
    ],
    "sg:phone":"+44 1555 895590",
    "sg:postcode":"ML11 9QF",
    "sg:province":"South Lanarkshire",
    "sg:tags":[
        "car",
        "park"
    ],
    "wof:name":"Kehole Car Parks",
    "wof:placetype":"venue"
},
  "geometry": {"coordinates":[-3.7813839912,55.673866272],"type":"Point"}
}