{
  "type": "Feature",
  "properties": {
    "addr:full":"9 Bond St Egham Surrey TW20 0PG",
    "addr:housenumber":"9",
    "addr:postcode":"tw20 0pg",
    "addr:street":"Bond St",
    "iso:country":"GB",
    "sg:address":"9 Bond St",
    "sg:city":"Egham",
    "sg:classifiers":[
        {
            "category":"Professional",
            "subcategory":"Business Services",
            "type":"Services"
        }
    ],
    "sg:phone":"+44 1784 439351",
    "sg:postcode":"TW20 0PG",
    "sg:province":"Surrey",
    "sg:tags":[
        "planning",
        "design"
    ],
    "wof:name":"Chase Commercial Interior Contractors Ltd",
    "wof:placetype":"venue"
},
  "geometry": {"coordinates":[-0.57323,51.429691],"type":"Point"}
}