{
  "type": "Feature",
  "properties": {
    "addr:full":"58 West Street Tavistock Devon PL19 8JZ",
    "addr:housenumber":"58",
    "addr:postcode":"pl19 8jz",
    "addr:street":"West Street",
    "iso:country":"GB",
    "sg:address":"58 West Street",
    "sg:city":"Tavistock",
    "sg:classifiers":[
        {
            "category":"Health Services",
            "subcategory":"Chiropractor",
            "type":"Services"
        }
    ],
    "sg:phone":"+44 1822 616806",
    "sg:postcode":"PL19 8JZ",
    "sg:province":"Devon",
    "wof:name":"Tavistock Chiropractic Centre",
    "wof:placetype":"venue"
},
  "geometry": {"coordinates":[-4.1490659714,50.549030304],"type":"Point"}
}