{
  "type": "Feature",
  "properties": {
    "addr:full":"86 Kingsway Scunthorpe Lincolnshire DN15 7ER",
    "addr:housenumber":"86",
    "addr:postcode":"dn15 7er",
    "addr:street":"Kingsway",
    "iso:country":"GB",
    "sg:address":"86 Kingsway",
    "sg:city":"Scunthorpe",
    "sg:classifiers":[
        {
            "category":"Building & Trades",
            "subcategory":"Construction",
            "type":"Services"
        }
    ],
    "sg:phone":"+44 1724 855143",
    "sg:postcode":"DN15 7ER",
    "sg:province":"Lincolnshire",
    "sg:tags":[
        "builder"
    ],
    "wof:name":"A Conroy",
    "wof:placetype":"venue"
},
  "geometry": {"coordinates":[-0.6793789864,53.5891723633],"type":"Point"}
}