{
  "type": "Feature",
  "properties": {
    "addr:full":"2 Little Headlands Bedford Bedfordshire MK41 8JT",
    "addr:housenumber":"2",
    "addr:postcode":"mk41 8jt",
    "addr:street":"Little Headlands",
    "iso:country":"GB",
    "sg:address":"2 Little Headlands",
    "sg:city":"Bedford",
    "sg:classifiers":[
        {
            "category":"Home & Garden",
            "subcategory":"Household Appliances",
            "type":"Retail Goods"
        }
    ],
    "sg:postcode":"MK41 8JT",
    "sg:province":"Bedfordshire",
    "sg:tags":[
        "electrical"
    ],
    "wof:name":"Ivanilectrix",
    "wof:placetype":"venue"
},
  "geometry": {"coordinates":[-0.4396350086,52.1552314758],"type":"Point"}
}