{
  "type": "Feature",
  "properties": {
    "addr:full":"164 Thorold Road Ilford Essex IG1 4EZ",
    "addr:housenumber":"164",
    "addr:postcode":"ig1 4ez",
    "addr:street":"Thorold Road",
    "iso:country":"GB",
    "sg:address":"164 Thorold Road",
    "sg:city":"Ilford",
    "sg:classifiers":[
        {
            "category":"Organizations",
            "subcategory":"Labor Organization",
            "type":"Services"
        },
        {
            "category":"Professional",
            "subcategory":"Business Services",
            "type":"Services"
        }
    ],
    "sg:phone":"+44 20 8514 5024",
    "sg:postcode":"IG1 4EZ",
    "sg:province":"Essex",
    "sg:tags":[
        "import",
        "export",
        "agent"
    ],
    "wof:name":"Zamzim Ltd.",
    "wof:placetype":"venue"
},
  "geometry": {"coordinates":[0.0780780017,51.5629806519],"type":"Point"}
}