{
  "type": "Feature",
  "properties": {
    "addr:full":"2 Mill End, Thaxted Dunmow Essex CM6 2LT",
    "addr:housenumber":"2;thaxted",
    "addr:postcode":"cm6 2lt",
    "addr:street":"Mill End",
    "iso:country":"GB",
    "sg:address":"2 Mill End, Thaxted",
    "sg:city":"Dunmow",
    "sg:classifiers":[
        {
            "category":"Food & Beverages",
            "subcategory":"Meat & Fish",
            "type":"Retail Goods"
        }
    ],
    "sg:phone":"+44 1371 830909",
    "sg:postcode":"CM6 2LT",
    "sg:province":"Essex",
    "sg:tags":[
        "chip"
    ],
    "wof:name":"Skippers Delight",
    "wof:placetype":"venue"
},
  "geometry": {"coordinates":[0.3447650075,51.953163147],"type":"Point"}
}