{
  "type": "Feature",
  "properties": {
    "addr:full":"Rear Of 365b Limpsfield Road Warlingham Kent CR6 9HA",
    "addr:housenumber":"rear of 365b",
    "addr:postcode":"cr6 9ha",
    "addr:street":"Limpsfield Road",
    "iso:country":"GB",
    "sg:address":"Rear Of 365b Limpsfield Road",
    "sg:city":"Warlingham",
    "sg:classifiers":[
        {
            "category":"Retail",
            "subcategory":"Auto Repair",
            "type":"Services"
        }
    ],
    "sg:postcode":"CR6 9HA",
    "sg:province":"Kent",
    "sg:tags":[
        "modification",
        "garage"
    ],
    "wof:name":"van den Dyck Tony",
    "wof:placetype":"venue"
},
  "geometry": {"coordinates":[-0.057124,51.310558],"type":"Point"}
}