{
  "type": "Feature",
  "properties": {
    "addr:full":"7 Colestrete Close Stevenage Hertfordshire SG1 1RG",
    "addr:housenumber":"7",
    "addr:postcode":"sg1 1rg",
    "addr:street":"Colestrete Close",
    "iso:country":"GB",
    "sg:address":"7 Colestrete Close",
    "sg:city":"Stevenage",
    "sg:classifiers":[
        {
            "category":"Building & Trades",
            "subcategory":"Plumbing",
            "type":"Services"
        }
    ],
    "sg:phone":"+44 1438 236433",
    "sg:postcode":"SG1 1RG",
    "sg:province":"Hertfordshire",
    "sg:tags":[
        "heating"
    ],
    "wof:name":"Corrigan & Son",
    "wof:placetype":"venue"
},
  "geometry": {"coordinates":[-0.184001,51.901325],"type":"Point"}
}