{
  "type": "Feature",
  "properties": {
    "addr:full":"10 Fowlds Street Kilmarnock East Ayrshire KA1 3DG",
    "addr:housenumber":"10",
    "addr:postcode":"ka1 3dg",
    "addr:street":"Fowlds Street",
    "iso:country":"GB",
    "sg:address":"10 Fowlds Street",
    "sg:city":"Kilmarnock",
    "sg:classifiers":[
        {
            "category":"Banks & Credit Unions",
            "subcategory":"Financial Services",
            "type":"Services"
        }
    ],
    "sg:phone":"+44 1563 525651",
    "sg:postcode":"KA1 3DG",
    "sg:province":"East Ayrshire",
    "sg:tags":[
        "consultant"
    ],
    "wof:name":"Shopacheck Financial Services Ltd.",
    "wof:placetype":"venue"
},
  "geometry": {"coordinates":[-4.4969668388,55.6068992615],"type":"Point"}
}