{
  "type": "Feature",
  "properties": {
    "iso:country":"GB",
    "sg:address":"126 Celeborn Street, South Woodham Ferrers",
    "sg:city":"Chelmsford",
    "sg:classifiers":[
        {
            "category":"Building & Trades",
            "subcategory":"Construction",
            "type":"Services"
        },
        {
            "category":"Building & Trades",
            "subcategory":"Electrical",
            "type":"Services"
        }
    ],
    "sg:phone":"+44 1245 322439",
    "sg:postcode":"CM3 7AW",
    "sg:province":"Essex",
    "sg:tags":[
        "roofing",
        "electrician",
        "contractor"
    ],
    "wof:name":"K J Sinnott Electrical Ltd",
    "wof:placetype":"venue"
},
  "geometry": {"coordinates":[0.59972,51.639332],"type":"Point"}
}