{
  "type": "Feature",
  "properties": {
    "iso:country":"GB",
    "sg:address":"Park View, Anstey La",
    "sg:city":"Leicester",
    "sg:classifiers":[
        {
            "category":"Sports & Exercise",
            "subcategory":"Stables",
            "type":"Entertainment"
        }
    ],
    "sg:phone":"+44 116 236 4858",
    "sg:postcode":"LE7 7JB",
    "sg:province":"Leicestershire",
    "sg:tags":[
        "education",
        "equestrian"
    ],
    "wof:name":"McDonald J L",
    "wof:placetype":"venue"
},
  "geometry": {"coordinates":[-1.183559,52.673836],"type":"Point"}
}