{
  "type": "Feature",
  "properties": {
    "addr:full":"Hopetoun Lane Bathgate West Lothian EH48 1PP",
    "addr:postcode":"eh48 1pp",
    "addr:street":"Hopetoun Lane Bathgate",
    "iso:country":"GB",
    "sg:address":"Hopetoun Lane",
    "sg:city":"Bathgate",
    "sg:classifiers":[
        {
            "category":"Retail",
            "subcategory":"Auto Repair",
            "type":"Services"
        }
    ],
    "sg:postcode":"EH48 1PP",
    "sg:province":"West Lothian",
    "sg:tags":[
        "modification",
        "garage"
    ],
    "wof:name":"Bloom Motors",
    "wof:placetype":"venue"
},
  "geometry": {"coordinates":[-3.641629,55.900757],"type":"Point"}
}