{
  "type": "Feature",
  "properties": {
    "iso:country":"GB",
    "sg:address":"2 Mere Avenue",
    "sg:city":"Fleetwood",
    "sg:classifiers":[
        {
            "category":"Building & Trades",
            "subcategory":"Construction",
            "type":"Services"
        }
    ],
    "sg:phone":"+44 1253 778393",
    "sg:postcode":"FY7 8LX",
    "sg:province":"Lancashire",
    "sg:tags":[
        "builder"
    ],
    "wof:name":"C B J Multicraft Home Improvements",
    "wof:placetype":"venue"
},
  "geometry": {"coordinates":[-3.04162,53.908169],"type":"Point"}
}