{
  "type": "Feature",
  "properties": {
    "iso:country":"GB",
    "sg:address":"Sterling House, Canal Street",
    "sg:city":"Manchester",
    "sg:classifiers":[
        {
            "category":"Professional",
            "subcategory":"Accounting & Tax Preparation",
            "type":"Services"
        }
    ],
    "sg:postcode":"M43 7UN",
    "sg:province":"Greater Manchester",
    "sg:tags":[
        "accountant"
    ],
    "wof:name":"Ashdale Business Consultants Ltd",
    "wof:placetype":"venue"
},
  "geometry": {"coordinates":[-2.146344,53.478645],"type":"Point"}
}