{
  "type": "Feature",
  "properties": {
    "addr:full":"42 Hightown Road Luton Bedfordshire LU2 0DE",
    "addr:housenumber":"42",
    "addr:postcode":"lu2 0de",
    "addr:street":"Hightown Road",
    "iso:country":"GB",
    "sg:address":"42 Hightown Road",
    "sg:city":"Luton",
    "sg:classifiers":[
        {
            "category":"Shopping",
            "subcategory":"Clothing, Apparel, & Fashions",
            "type":"Retail Goods"
        }
    ],
    "sg:phone":"+44 1582 751777",
    "sg:postcode":"LU2 0DE",
    "sg:province":"Bedfordshire",
    "sg:tags":[
        "shop",
        "hat"
    ],
    "wof:name":"Double P",
    "wof:placetype":"venue"
},
  "geometry": {"coordinates":[-0.4088590145,51.8863182068],"type":"Point"}
}