{
  "type": "Feature",
  "properties": {
    "iso:country":"GB",
    "sg:address":"The Studio, Greenacres Farm",
    "sg:city":"Rochford",
    "sg:classifiers":[
        {
            "category":"Home & Garden",
            "subcategory":"Garden Supply",
            "type":"Retail Goods"
        }
    ],
    "sg:postcode":"SS4 3RR",
    "sg:province":"Essex",
    "sg:tags":[
        "pool",
        "swimming"
    ],
    "wof:name":"Capistrana Pool Villas Limited",
    "wof:placetype":"venue"
},
  "geometry": {"coordinates":[0.701389,51.583221],"type":"Point"}
}