{
  "type": "Feature",
  "properties": {
    "iso:country":"GB",
    "sg:address":"Unit 14 Industrial Estate, Corporation Rd",
    "sg:city":"Birkenhead",
    "sg:classifiers":[
        {
            "category":"Professional",
            "subcategory":"Engineering",
            "type":"Services"
        }
    ],
    "sg:phone":"+44 151 670 0660",
    "sg:postcode":"CH41 8FA",
    "sg:province":"Merseyside",
    "sg:tags":[
        "engineer",
        "mechanical"
    ],
    "wof:name":"Captone Engineering Ltd",
    "wof:placetype":"venue"
},
  "geometry": {"coordinates":[-3.040711,53.401546],"type":"Point"}
}