{
  "type": "Feature",
  "properties": {
    "addr:full":"4 Couchmore Avenue, Hinchleywood Esher Surrey KT10 9AS",
    "addr:housenumber":"4",
    "addr:postcode":"kt10 9as",
    "addr:street":"Couchmore Avenue Hinchleywood Esher",
    "iso:country":"GB",
    "sg:address":"4 Couchmore Avenue, Hinchleywood",
    "sg:city":"Esher",
    "sg:classifiers":[
        {
            "category":"Manufacturing",
            "subcategory":"Furniture",
            "type":"Manufacturing & Wholesale Goods"
        }
    ],
    "sg:phone":"+44 20 8398 2741",
    "sg:postcode":"KT10 9AS",
    "sg:province":"Surrey",
    "sg:tags":[
        "polishing",
        "french"
    ],
    "wof:name":"Peter Lesoing",
    "wof:placetype":"venue"
},
  "geometry": {"coordinates":[-0.3423950076,51.3796920776],"type":"Point"}
}