{
  "type": "Feature",
  "properties": {
    "addr:full":"Tan House Farm, Alder Lane, Cronton Widnes Cheshire WA8 5PP",
    "addr:postcode":"wa8 5pp",
    "addr:street":"Alder Lane",
    "iso:country":"GB",
    "sg:address":"Tan House Farm, Alder Lane, Cronton",
    "sg:city":"Widnes",
    "sg:classifiers":[
        {
            "category":"Wholesale",
            "subcategory":"Meat",
            "type":"Manufacturing & Wholesale Goods"
        }
    ],
    "sg:phone":"+44 151 423 1440",
    "sg:postcode":"WA8 5PP",
    "sg:province":"Cheshire",
    "sg:tags":[
        "-"
    ],
    "wof:name":"C S Morphet & Sons Ltd.",
    "wof:placetype":"venue"
},
  "geometry": {"coordinates":[-2.7604589462,53.3892211914],"type":"Point"}
}