{
  "type": "Feature",
  "properties": {
    "addr:full":"Levenshulme Islamic Centre, 2 Barlow Rd Manchester Greater Manchester M19 3DJ",
    "addr:housenumber":"2",
    "addr:postcode":"m19 3dj",
    "addr:street":"Barlow Rd",
    "iso:country":"GB",
    "sg:address":"Levenshulme Islamic Centre, 2 Barlow Rd",
    "sg:city":"Manchester",
    "sg:classifiers":[
        {
            "category":"Organizations",
            "subcategory":"Religious Organization",
            "type":"Services"
        }
    ],
    "sg:phone":"+44 161 248 4224",
    "sg:postcode":"M19 3DJ",
    "sg:province":"Greater Manchester",
    "sg:tags":[
        "organisation"
    ],
    "wof:name":"Islamic Society Of Britain",
    "wof:placetype":"venue"
},
  "geometry": {"coordinates":[-2.24881,53.479622],"type":"Point"}
}