{
  "type": "Feature",
  "properties": {
    "iso:country":"GB",
    "sg:address":"Unit G6 Fort Wallington Industrial Estate, Military Rd",
    "sg:city":"Fareham",
    "sg:classifiers":[
        {
            "category":"Freight",
            "type":"Transportation"
        }
    ],
    "sg:phone":"+44 1329 234351",
    "sg:postcode":"PO16 8TT",
    "sg:province":"Hampshire",
    "sg:tags":[
        "forwarders"
    ],
    "wof:name":"Eagleway Freight Ltd",
    "wof:placetype":"venue"
},
  "geometry": {"coordinates":[-1.1740989685,50.8527336121],"type":"Point"}
}