{
  "type": "Feature",
  "properties": {
    "iso:country":"GB",
    "sg:address":"5 Dodds Lane Rear Of 27 Preston, Street",
    "sg:city":"Faversham",
    "sg:classifiers":[
        {
            "category":"Bus Charters",
            "type":"Transportation"
        }
    ],
    "sg:postcode":"ME13 8PE",
    "sg:province":"Kent",
    "sg:tags":[
        "hire",
        "coach"
    ],
    "wof:name":"Queens Travel",
    "wof:placetype":"venue"
},
  "geometry": {"coordinates":[0.8834400177,51.3096046448],"type":"Point"}
}