{
  "type": "Feature",
  "properties": {
    "iso:country":"GB",
    "sg:address":"Shaftsbury Avenue, Simonside Industrial Estate",
    "sg:city":"South Shields",
    "sg:classifiers":[
        {
            "category":"Personal",
            "subcategory":"Skin Care",
            "type":"Services"
        }
    ],
    "sg:phone":"+44 191 455 2756",
    "sg:postcode":"NE34 9PE",
    "sg:province":"Tyne and Wear",
    "sg:tags":[
        "leather",
        "merchant"
    ],
    "wof:name":"Tyneside Leathercrafts Ltd.",
    "wof:placetype":"venue"
},
  "geometry": {"coordinates":[-1.4617739916,54.9705505371],"type":"Point"}
}