{
  "type": "Feature",
  "properties": {
    "addr:full":"173 Victoria Road Romford Essex RM1 2NP",
    "addr:housenumber":"173",
    "addr:postcode":"rm1 2np",
    "addr:street":"Victoria Road",
    "iso:country":"GB",
    "sg:address":"173 Victoria Road",
    "sg:city":"Romford",
    "sg:classifiers":[
        {
            "category":"Home & Garden",
            "subcategory":"Building Materials",
            "type":"Retail Goods"
        }
    ],
    "sg:phone":"+44 1708 725186",
    "sg:postcode":"RM1 2NP",
    "sg:province":"Essex",
    "sg:tags":[
        "ironwork",
        "diy",
        "wrought"
    ],
    "wof:name":"Salisbury Forge (1986) Ltd.",
    "wof:placetype":"venue"
},
  "geometry": {"coordinates":[0.1928160042,51.5769004822],"type":"Point"}
}