{
  "type": "Feature",
  "properties": {
    "iso:country":"GB",
    "sg:address":"3 New End, Hampstead",
    "sg:city":"London",
    "sg:classifiers":[
        {
            "category":"Professional",
            "subcategory":"Management & Consulting",
            "type":"Services"
        }
    ],
    "sg:postcode":"NW3 1JD",
    "sg:province":"Greater London",
    "sg:tags":[
        "marketing",
        "consultant"
    ],
    "wof:name":"Granton Marketing",
    "wof:placetype":"venue"
},
  "geometry": {"coordinates":[-0.1783570051,51.5588569641],"type":"Point"}
}