{
  "type": "Feature",
  "properties": {
    "addr:full":"96 Liverpool Road, Irlam Manchester Greater Manchester M44 6FF",
    "addr:housenumber":"96",
    "addr:postcode":"m44 6ff",
    "addr:street":"Liverpool Road",
    "iso:country":"GB",
    "sg:address":"96 Liverpool Road, Irlam",
    "sg:city":"Manchester",
    "sg:classifiers":[
        {
            "category":"Autos & Motor Vehicles",
            "subcategory":"Auto Supplies",
            "type":"Retail Goods"
        }
    ],
    "sg:phone":"+44 161 777 8577",
    "sg:postcode":"M44 6FF",
    "sg:province":"Greater Manchester",
    "sg:tags":[
        "car",
        "lacquer",
        "paint"
    ],
    "wof:name":"Autopaint International",
    "wof:placetype":"venue"
},
  "geometry": {"coordinates":[-2.412531,53.451843],"type":"Point"}
}