{
  "type": "Feature",
  "properties": {
    "addr:full":"473 Otley Road Leeds West Yorkshire LS16 7NR",
    "addr:housenumber":"473",
    "addr:postcode":"ls16 7nr",
    "addr:street":"Otley Road",
    "iso:country":"GB",
    "sg:address":"473 Otley Road",
    "sg:city":"Leeds",
    "sg:classifiers":[
        {
            "category":"Restaurant",
            "type":"Food & Drink"
        }
    ],
    "sg:phone":"+44 113 230 0600",
    "sg:postcode":"LS16 7NR",
    "sg:province":"West Yorkshire",
    "wof:name":"Bellinis",
    "wof:placetype":"venue"
},
  "geometry": {"coordinates":[-1.591574,53.854408],"type":"Point"}
}