{
  "type": "Feature",
  "properties": {
    "addr:full":"34 Middle Hill Egham Surrey TW20 0JQ",
    "addr:housenumber":"34",
    "addr:postcode":"tw20 0jq",
    "addr:street":"Middle Hill Egham",
    "iso:country":"GB",
    "sg:address":"34 Middle Hill",
    "sg:city":"Egham",
    "sg:classifiers":[
        {
            "category":"Bars & Pubs",
            "type":"Food & Drink"
        }
    ],
    "sg:phone":"+44 1784 431621",
    "sg:postcode":"TW20 0JQ",
    "sg:province":"Surrey",
    "sg:tags":[
        "pubs",
        "inn"
    ],
    "wof:name":"The Beehive",
    "wof:placetype":"venue"
},
  "geometry": {"coordinates":[-0.5628039837,51.429889679],"type":"Point"}
}