{
  "type": "Feature",
  "properties": {
    "addr:full":"Stone Street, Seal Sevenoaks Kent TN15 0LN",
    "addr:postcode":"tn15 0ln",
    "addr:street":"Stone Street",
    "iso:country":"GB",
    "sg:address":"Stone Street, Seal",
    "sg:city":"Sevenoaks",
    "sg:classifiers":[
        {
            "category":"Education",
            "subcategory":"School",
            "type":"Public Place"
        }
    ],
    "sg:phone":"+44 1732 761393",
    "sg:postcode":"TN15 0LN",
    "sg:province":"Kent",
    "sg:tags":[
        "local",
        "authority"
    ],
    "wof:name":"St Lawrence Church of England Primary School",
    "wof:placetype":"venue"
},
  "geometry": {"coordinates":[0.2548899949,51.2702102661],"type":"Point"}
}