{
  "type": "Feature",
  "properties": {
    "addr:full":"286 Old Brompton Road London Greater London SW5 9HR",
    "addr:housenumber":"286",
    "addr:postcode":"sw5 9hr",
    "addr:street":"Old Brompton Road",
    "iso:country":"GB",
    "sg:address":"286 Old Brompton Road",
    "sg:city":"London",
    "sg:classifiers":[
        {
            "category":"Food & Beverages",
            "subcategory":"Supermarket",
            "type":"Retail Goods"
        }
    ],
    "sg:phone":"+44 20 7370 5994",
    "sg:postcode":"SW5 9HR",
    "sg:province":"Greater London",
    "wof:name":"Fine Food",
    "wof:placetype":"venue"
},
  "geometry": {"coordinates":[-0.192248,51.488903],"type":"Point"}
}