{
  "type": "Feature",
  "properties": {
    "iso:country":"GB",
    "sg:address":"Top House Farm, New Road",
    "sg:city":"Wrexham",
    "sg:classifiers":[
        {
            "category":"Sports & Exercise",
            "subcategory":"Gym",
            "type":"Entertainment"
        }
    ],
    "sg:postcode":"LL11 2HP",
    "sg:province":"Wrexham",
    "sg:tags":[
        "fitness",
        "health",
        "centre"
    ],
    "wof:name":"Fitness & Leisure Centre",
    "wof:placetype":"venue"
},
  "geometry": {"coordinates":[-3.0014998913,53.0649986267],"type":"Point"}
}