{
  "type": "Feature",
  "properties": {
    "iso:country":"GB",
    "sg:address":"321 Glossop Road",
    "sg:city":"Sheffield",
    "sg:classifiers":[
        {
            "category":"Fast Food",
            "type":"Food & Drink"
        }
    ],
    "sg:phone":"+44 114 276 0232",
    "sg:postcode":"S10 2HP",
    "sg:province":"South Yorkshire",
    "sg:tags":[
        "away",
        "meal",
        "outlet",
        "take"
    ],
    "wof:name":"Scott's Pantry",
    "wof:placetype":"venue"
},
  "geometry": {"coordinates":[-1.488691,53.37944],"type":"Point"}
}