{
  "type": "Feature",
  "properties": {
    "addr:full":"Bridgeway Centre, Kingsnorth Industrial Estate Ashford Kent TN23 6LN",
    "addr:postcode":"tn23 6ln",
    "addr:street":"Bridgeway Centre Kingsnorth Industrial Estate",
    "iso:country":"GB",
    "sg:address":"Bridgeway Centre, Kingsnorth Industrial Estate",
    "sg:city":"Ashford",
    "sg:classifiers":[
        {
            "category":"Organizations",
            "subcategory":"Non-profit Organization",
            "type":"Services"
        }
    ],
    "sg:phone":"+44 1233 638660",
    "sg:postcode":"TN23 6LN",
    "sg:province":"Kent",
    "sg:tags":[
        "organisation",
        "voluntary",
        "charity"
    ],
    "wof:name":"Bridgeway Centre",
    "wof:placetype":"venue"
},
  "geometry": {"coordinates":[0.8760370016,51.1466331482],"type":"Point"}
}