{
  "type": "Feature",
  "properties": {
    "addr:full":"Stance A/1 Glasgow Fruit Market, Blochairn Road Glasgow East Dunbartonshire G21 2RT",
    "addr:housenumber":"1",
    "addr:postcode":"g21 2rt",
    "addr:street":"Blochairn Road",
    "iso:country":"GB",
    "sg:address":"Stance A/1 Glasgow Fruit Market, Blochairn Road",
    "sg:city":"Glasgow",
    "sg:classifiers":[
        {
            "category":"Wholesale",
            "subcategory":"Fruits & Vegetables",
            "type":"Manufacturing & Wholesale Goods"
        }
    ],
    "sg:phone":"+44 141 552 2704",
    "sg:postcode":"G21 2RT",
    "sg:province":"East Dunbartonshire",
    "wof:name":"J & P Brogan",
    "wof:placetype":"venue"
},
  "geometry": {"coordinates":[-4.21446,55.869228],"type":"Point"}
}