{
  "type": "Feature",
  "properties": {
    "iso:country":"GB",
    "sg:address":"Room 4 Frost House, Woodhouse Buisness Centre, Woodhouse Grn",
    "sg:city":"Rotherham",
    "sg:classifiers":[
        {
            "category":"Military Area",
            "subcategory":"Air Force Base",
            "type":"Public Place"
        }
    ],
    "sg:phone":"+44 1709 709999",
    "sg:postcode":"S66 9AN",
    "sg:province":"South Yorkshire",
    "sg:tags":[
        "taxi",
        "hire",
        "private"
    ],
    "wof:name":"Parish Private Hire",
    "wof:placetype":"venue"
},
  "geometry": {"coordinates":[-1.2633039951,53.3985557556],"type":"Point"}
}