{
  "type": "Feature",
  "properties": {
    "iso:country":"GB",
    "sg:address":"15 First Avenue",
    "sg:city":"Lancing",
    "sg:classifiers":[
        {
            "category":"Transit Center",
            "subcategory":"Freight",
            "type":"Transportation"
        }
    ],
    "sg:phone":"+44 1903 538098",
    "sg:postcode":"BN15 9QG",
    "sg:province":"West Sussex",
    "sg:tags":[
        "piano",
        "accessory"
    ],
    "wof:name":"Tim Cattermole",
    "wof:placetype":"venue"
},
  "geometry": {"coordinates":[-0.32083,50.832912],"type":"Point"}
}