{
  "type": "Feature",
  "properties": {
    "iso:country":"GB",
    "sg:address":"Garchell Farm, Balfron Station, Buchlyvie",
    "sg:city":"Glasgow",
    "sg:classifiers":[
        {
            "category":"Professional",
            "subcategory":"Printing & Photocopies",
            "type":"Services"
        }
    ],
    "sg:phone":"+44 1360 850289",
    "sg:postcode":"G63 0QY",
    "sg:province":"Argyll and Bute",
    "sg:tags":[
        "trophy",
        "medal"
    ],
    "wof:name":"Carruthers Rosette Co",
    "wof:placetype":"venue"
},
  "geometry": {"coordinates":[-4.3747692108,56.0735282898],"type":"Point"}
}