{
  "type": "Feature",
  "properties": {
    "addr:full":"Juniper Ho Beaminster Dorset DT8 3NZ",
    "addr:housenumber":"beaminster",
    "addr:postcode":"dt8 3nz",
    "addr:street":"Dorset",
    "iso:country":"GB",
    "sg:address":"Juniper Ho",
    "sg:city":"Beaminster",
    "sg:classifiers":[
        {
            "category":"Building & Trades",
            "subcategory":"Construction",
            "type":"Services"
        }
    ],
    "sg:phone":"+44 1308 863933",
    "sg:postcode":"DT8 3NZ",
    "sg:province":"Dorset",
    "sg:tags":[
        "builder"
    ],
    "wof:name":"Bugler Builders",
    "wof:placetype":"venue"
},
  "geometry": {"coordinates":[-2.7388939857,50.8090057373],"type":"Point"}
}