{
  "type": "Feature",
  "properties": {
    "addr:full":"34 Church Street Twickenham Greater London TW1 3NR",
    "addr:housenumber":"34",
    "addr:postcode":"tw1 3nr",
    "addr:street":"Church Street",
    "iso:country":"GB",
    "sg:address":"34 Church Street",
    "sg:city":"Twickenham",
    "sg:classifiers":[
        {
            "category":"Restaurant",
            "type":"Food & Drink"
        }
    ],
    "sg:phone":"+44 20 8892 6366",
    "sg:postcode":"TW1 3NR",
    "sg:province":"Greater London",
    "sg:tags":[
        "french"
    ],
    "wof:name":"Raefil's Restaurant",
    "wof:placetype":"venue"
},
  "geometry": {"coordinates":[-0.3276610076,51.4464492798],"type":"Point"}
}