{
  "type": "Feature",
  "properties": {
    "addr:full":"Perry Hill Farm, Clehonger Hereford Herefordshire HR2 9SB",
    "addr:postcode":"hr2 9sb",
    "addr:street":"Perry Hill",
    "iso:country":"GB",
    "sg:address":"Perry Hill Farm, Clehonger",
    "sg:city":"Hereford",
    "sg:classifiers":[
        {
            "category":"Home & Garden",
            "subcategory":"Garden Supply",
            "type":"Retail Goods"
        },
        {
            "category":"Farming",
            "subcategory":"Farm",
            "type":"Manufacturing & Wholesale Goods"
        }
    ],
    "sg:phone":"+44 1432 277354",
    "sg:postcode":"HR2 9SB",
    "sg:province":"Herefordshire",
    "sg:tags":[
        "mixed",
        "bulb",
        "grower"
    ],
    "wof:name":"L Thomas & Son",
    "wof:placetype":"venue"
},
  "geometry": {"coordinates":[-2.798818,52.035522],"type":"Point"}
}