{
  "type": "Feature",
  "properties": {
    "addr:full":"144 Lancaster Road, Cabus Preston Lancashire PR3 1JE",
    "addr:housenumber":"144",
    "addr:postcode":"pr3 1je",
    "addr:street":"Lancaster Road",
    "iso:country":"GB",
    "sg:address":"144 Lancaster Road, Cabus",
    "sg:city":"Preston",
    "sg:classifiers":[
        {
            "category":"Shopping",
            "subcategory":"News",
            "type":"Retail Goods"
        },
        {
            "category":"Food & Beverages",
            "subcategory":"Supermarket",
            "type":"Retail Goods"
        }
    ],
    "sg:postcode":"PR3 1JE",
    "sg:province":"Lancashire",
    "sg:tags":[
        "newsagent"
    ],
    "wof:name":"Cabus Spar & Post Office",
    "wof:placetype":"venue"
},
  "geometry": {"coordinates":[-2.77629,53.912289],"type":"Point"}
}