{
  "type": "Feature",
  "properties": {
    "iso:country":"GB",
    "sg:address":"3a Mews, Union Street",
    "sg:city":"Wells",
    "sg:classifiers":[
        {
            "category":"Personal",
            "subcategory":"Beauty Salon",
            "type":"Services"
        }
    ],
    "sg:phone":"+44 1749 677886",
    "sg:postcode":"BA5 2PU",
    "sg:province":"Somerset",
    "sg:tags":[
        "unisex",
        "hairdresser"
    ],
    "wof:name":"3 A's Hair Studio",
    "wof:placetype":"venue"
},
  "geometry": {"coordinates":[-2.647748,51.208645],"type":"Point"}
}