{
  "type": "Feature",
  "properties": {
    "iso:country":"GB",
    "sg:address":"Everest Bungalow, Amesbury Road",
    "sg:city":"Andover",
    "sg:classifiers":[
        {
            "category":"Autos & Motor Vehicles",
            "subcategory":"Automobile Sales",
            "type":"Retail Goods"
        }
    ],
    "sg:postcode":"SP11 8EA",
    "sg:province":"Hampshire",
    "sg:tags":[
        "car"
    ],
    "wof:name":"Geoffrey Mitchell",
    "wof:placetype":"venue"
},
  "geometry": {"coordinates":[-1.5683300495,51.2144393921],"type":"Point"}
}