{
  "type": "Feature",
  "properties": {
    "iso:country":"GB",
    "sg:address":"3 Oatfield Drive",
    "sg:city":"Cranbrook",
    "sg:classifiers":[
        {
            "category":"Personal",
            "type":"Services"
        }
    ],
    "sg:postcode":"TN17 3NJ",
    "sg:province":"Kent",
    "sg:tags":[
        "wedding"
    ],
    "wof:name":"One Stop Catering",
    "wof:placetype":"venue"
},
  "geometry": {"coordinates":[0.5310040116,51.1002082825],"type":"Point"}
}