{
  "type": "Feature",
  "properties": {
    "addr:full":"376 High Road Benfleet Essex SS7 5HN",
    "addr:housenumber":"376",
    "addr:postcode":"ss7 5hn",
    "addr:street":"High Road",
    "iso:country":"GB",
    "sg:address":"376 High Road",
    "sg:city":"Benfleet",
    "sg:classifiers":[
        {
            "category":"Government",
            "subcategory":"City Hall",
            "type":"Public Place"
        }
    ],
    "sg:postcode":"SS7 5HN",
    "sg:province":"Essex",
    "wof:name":"St.Mary's Church Hall",
    "wof:placetype":"venue"
},
  "geometry": {"coordinates":[0.554645,51.55508],"type":"Point"}
}