{
  "type": "Feature",
  "properties": {
    "addr:full":"4 Furlong Rd Bourne End Berkshire SL8 5AB",
    "addr:housenumber":"4",
    "addr:postcode":"sl8 5ab",
    "addr:street":"Furlong Rd",
    "iso:country":"GB",
    "sg:address":"4 Furlong Rd",
    "sg:city":"Bourne End",
    "sg:classifiers":[
        {
            "category":"Government",
            "subcategory":"Customs House",
            "type":"Public Place"
        }
    ],
    "sg:postcode":"SL8 5AB",
    "sg:province":"Berkshire",
    "sg:tags":[
        "clearance"
    ],
    "wof:name":"Passing Hands",
    "wof:placetype":"venue"
},
  "geometry": {"coordinates":[-0.709474,51.574871],"type":"Point"}
}