{
  "type": "Feature",
  "properties": {
    "addr:full":"3 Stonebridge Darlington Durham DL1 1PB",
    "addr:housenumber":"3",
    "addr:postcode":"dl1 1pb",
    "addr:street":"Stonebridge Darlington",
    "iso:country":"GB",
    "sg:address":"3 Stonebridge",
    "sg:city":"Darlington",
    "sg:classifiers":[
        {
            "category":"Shopping",
            "subcategory":"Baby Store",
            "type":"Retail Goods"
        }
    ],
    "sg:phone":"+44 1325 364136",
    "sg:postcode":"DL1 1PB",
    "sg:province":"Durham",
    "sg:tags":[
        "equipment",
        "nursery",
        "accessory"
    ],
    "wof:name":"Babycare",
    "wof:placetype":"venue"
},
  "geometry": {"coordinates":[-1.551846,54.525112],"type":"Point"}
}