{
  "type": "Feature",
  "properties": {
    "addr:full":"65 Chetwynd Road London Greater London NW5 1BX",
    "addr:housenumber":"65",
    "addr:postcode":"nw5 1bx",
    "addr:street":"Chetwynd Road",
    "iso:country":"GB",
    "sg:address":"65 Chetwynd Road",
    "sg:city":"London",
    "sg:classifiers":[
        {
            "category":"Organizations",
            "subcategory":"Non-profit Organization",
            "type":"Services"
        }
    ],
    "sg:phone":"+44 20 7284 4344",
    "sg:postcode":"NW5 1BX",
    "sg:province":"Greater London",
    "sg:tags":[
        "organisation",
        "animal",
        "welfare"
    ],
    "wof:name":"Heath Veterinary Practice",
    "wof:placetype":"venue"
},
  "geometry": {"coordinates":[-0.143384,51.55827],"type":"Point"}
}