{
  "type": "Feature",
  "properties": {
    "addr:full":"719 Aylestone Road Leicester Leicestershire LE2 8TG",
    "addr:housenumber":"719",
    "addr:postcode":"le2 8tg",
    "addr:street":"Aylestone Road",
    "iso:country":"GB",
    "sg:address":"719 Aylestone Road",
    "sg:city":"Leicester",
    "sg:classifiers":[
        {
            "category":"Fast Food",
            "type":"Food & Drink"
        }
    ],
    "sg:postcode":"LE2 8TG",
    "sg:province":"Leicestershire",
    "sg:tags":[
        "away",
        "take"
    ],
    "wof:name":"Fung Tao",
    "wof:placetype":"venue"
},
  "geometry": {"coordinates":[-1.1546200514,52.6030654907],"type":"Point"}
}