{
  "type": "Feature",
  "properties": {
    "addr:full":"Windsor Road Gerrards Cross Buckinghamshire SL9 7NL",
    "addr:postcode":"sl9 7nl",
    "addr:street":"Road",
    "iso:country":"GB",
    "sg:address":"Windsor Road",
    "sg:city":"Gerrards Cross",
    "sg:classifiers":[
        {
            "category":"Autos & Motor Vehicles",
            "subcategory":"Recreational Vehicle Sales",
            "type":"Retail Goods"
        }
    ],
    "sg:phone":"+44 1753 882184",
    "sg:postcode":"SL9 7NL",
    "sg:province":"Buckinghamshire",
    "sg:tags":[
        "caravan"
    ],
    "wof:name":"Leisuretrack Motorhomes",
    "wof:placetype":"venue"
},
  "geometry": {"coordinates":[-0.5638039708,51.5777435303],"type":"Point"}
}