{
  "type": "Feature",
  "properties": {
    "addr:full":"7 Cambray Pl Cheltenham Gloucestershire GL50 1JS",
    "addr:housenumber":"7",
    "addr:postcode":"gl50 1js",
    "addr:street":"Cambray Pl",
    "iso:country":"GB",
    "sg:address":"7 Cambray Pl",
    "sg:city":"Cheltenham",
    "sg:classifiers":[
        {
            "category":"Health Services",
            "subcategory":"Dentist",
            "type":"Services"
        }
    ],
    "sg:phone":"+44 1242 515599",
    "sg:postcode":"GL50 1JS",
    "sg:province":"Gloucestershire",
    "wof:name":"D J Poole",
    "wof:placetype":"venue"
},
  "geometry": {"coordinates":[-2.0739989281,51.8985671997],"type":"Point"}
}