{
  "type": "Feature",
  "properties": {
    "addr:full":"651 Bloxwich Rd Walsall Staffordshire WS3 2BQ",
    "addr:housenumber":"651",
    "addr:postcode":"ws3 2bq",
    "addr:street":"Bloxwich Rd",
    "iso:country":"GB",
    "sg:address":"651 Bloxwich Rd",
    "sg:city":"Walsall",
    "sg:classifiers":[
        {
            "category":"Retail",
            "subcategory":"Auto Rental",
            "type":"Services"
        }
    ],
    "sg:phone":"+44 1922 440700",
    "sg:postcode":"WS3 2BQ",
    "sg:province":"Staffordshire",
    "sg:tags":[
        "car",
        "hire",
        "truck"
    ],
    "wof:name":"Chequered Flag Self-Drive Hire Ltd",
    "wof:placetype":"venue"
},
  "geometry": {"coordinates":[-1.996085,52.608929],"type":"Point"}
}