{
  "type": "Feature",
  "properties": {
    "addr:full":"21 Hinton, Dunster Crescent Weston-super-mare Somerset BS24 9EE",
    "addr:housenumber":"21",
    "addr:postcode":"bs24 9ee",
    "addr:street":"Hinton Dunster Crescent",
    "iso:country":"GB",
    "sg:address":"21 Hinton, Dunster Crescent",
    "sg:city":"Weston-super-mare",
    "sg:classifiers":[
        {
            "category":"Retail",
            "subcategory":"Driving School",
            "type":"Services"
        }
    ],
    "sg:phone":"+44 1934 814762",
    "sg:postcode":"BS24 9EE",
    "sg:province":"Somerset",
    "wof:name":"Professional Driver Training",
    "wof:placetype":"venue"
},
  "geometry": {"coordinates":[-2.9614889622,51.3251304626],"type":"Point"}
}