{
  "type": "Feature",
  "properties": {
    "iso:country":"GB",
    "sg:address":"Snaygill Industrial Estate, Keighley Road",
    "sg:city":"Skipton",
    "sg:classifiers":[
        {
            "category":"Manufacturing",
            "subcategory":"Rubber & Plastics",
            "type":"Manufacturing & Wholesale Goods"
        }
    ],
    "sg:phone":"+44 1756 700359",
    "sg:postcode":"BD23 2QR",
    "sg:province":"Lancashire",
    "sg:tags":[
        "product",
        "moulding",
        "injection",
        "manufacturer"
    ],
    "wof:name":"DICKINSON-PHILLIPS & CO",
    "wof:placetype":"venue"
},
  "geometry": {"coordinates":[-2.0141789913,53.9458885193],"type":"Point"}
}