{
  "type": "Feature",
  "properties": {
    "addr:full":"Market Street Llandudno Conwy LL30 2SR",
    "addr:postcode":"ll30 2sr",
    "addr:street":"Market Street",
    "iso:country":"GB",
    "sg:address":"Market Street",
    "sg:city":"Llandudno",
    "sg:classifiers":[
        {
            "category":"Bars & Pubs",
            "type":"Food & Drink"
        },
        {
            "category":"Community Center",
            "subcategory":"Social",
            "type":"Public Place"
        }
    ],
    "sg:phone":"+44 1492 870762",
    "sg:postcode":"LL30 2SR",
    "sg:province":"Conwy",
    "sg:tags":[
        "pubs",
        "house",
        "inn",
        "activity"
    ],
    "wof:name":"STANGE INN & CO LTD",
    "wof:placetype":"venue"
},
  "geometry": {"coordinates":[-3.831859,53.32481],"type":"Point"}
}