{
  "type": "Feature",
  "properties": {
    "addr:full":"Fern House Feltham Greater London TW13 4EZ",
    "addr:postcode":"tw13 4ez",
    "iso:country":"GB",
    "sg:address":"Fern House",
    "sg:city":"Feltham",
    "sg:classifiers":[
        {
            "category":"Shopping",
            "subcategory":"Pharmacy",
            "type":"Retail Goods"
        }
    ],
    "sg:phone":"+44 20 8893 7400",
    "sg:postcode":"TW13 4EZ",
    "sg:province":"Greater London",
    "sg:tags":[
        "pharmacist",
        "chemist"
    ],
    "wof:name":"E Moss Ltd.",
    "wof:placetype":"venue"
},
  "geometry": {"coordinates":[-0.409204,51.447075],"type":"Point"}
}