{
  "type": "Feature",
  "properties": {
    "addr:full":"24 Leyburn Avenue Shrewsbury Shropshire SY3 8TP",
    "addr:housenumber":"24",
    "addr:postcode":"sy3 8tp",
    "addr:street":"Leyburn Avenue",
    "iso:country":"GB",
    "sg:address":"24 Leyburn Avenue",
    "sg:city":"Shrewsbury",
    "sg:classifiers":[
        {
            "category":"Shopping",
            "subcategory":"Musical Instruments",
            "type":"Retail Goods"
        }
    ],
    "sg:postcode":"SY3 8TP",
    "sg:province":"Shropshire",
    "wof:name":"William Edward Wilkins",
    "wof:placetype":"venue"
},
  "geometry": {"coordinates":[-2.7778940201,52.7124137878],"type":"Point"}
}