{
  "type": "Feature",
  "properties": {
    "addr:full":"The Waterbed Centre, High Street Mansfield Derbyshire NG19 8AN",
    "addr:postcode":"ng19 8an",
    "addr:street":"High Street",
    "iso:country":"GB",
    "sg:address":"The Waterbed Centre, High Street",
    "sg:city":"Mansfield",
    "sg:classifiers":[
        {
            "category":"Home & Garden",
            "subcategory":"Home Furnishings",
            "type":"Retail Goods"
        }
    ],
    "sg:phone":"+44 1623 468888",
    "sg:postcode":"NG19 8AN",
    "sg:province":"Derbyshire",
    "sg:tags":[
        "beds",
        "bedding",
        "blanket"
    ],
    "wof:name":"Righteous & Co. Ltd.",
    "wof:placetype":"venue"
},
  "geometry": {"coordinates":[-1.1925599575,53.1651191711],"type":"Point"}
}