{
  "type": "Feature",
  "properties": {
    "iso:country":"GB",
    "sg:address":"The Forge, Unit 52",
    "sg:city":"Glasgow",
    "sg:classifiers":[
        {
            "category":"Banks & Credit Unions",
            "subcategory":"Bank",
            "type":"Services"
        }
    ],
    "sg:phone":"+44 845 765 4321",
    "sg:postcode":"G31 4EB",
    "sg:province":"Glasgow City",
    "wof:name":"Abbey National Plc",
    "wof:placetype":"venue"
},
  "geometry": {"coordinates":[-4.289064,55.806389],"type":"Point"}
}