{
  "type": "Feature",
  "properties": {
    "addr:full":"248 Hook Road Chessington Surrey KT9 1PL",
    "addr:housenumber":"248",
    "addr:postcode":"kt9 1pl",
    "addr:street":"Hook Road",
    "iso:country":"GB",
    "sg:address":"248 Hook Road",
    "sg:city":"Chessington",
    "sg:classifiers":[
        {
            "category":"Autos & Motor Vehicles",
            "subcategory":"Automobile Sales",
            "type":"Retail Goods"
        }
    ],
    "sg:phone":"+44 1273 321956",
    "sg:postcode":"KT9 1PL",
    "sg:province":"Surrey",
    "sg:tags":[
        "car"
    ],
    "wof:name":"B J Turner & Sons Ltd.",
    "wof:placetype":"venue"
},
  "geometry": {"coordinates":[-0.3060339987,51.3706359863],"type":"Point"}
}