{
  "type": "Feature",
  "properties": {
    "iso:country":"GB",
    "sg:address":"Unit 1, 47-49 St Margarets Grove",
    "sg:city":"Twickenham",
    "sg:classifiers":[
        {
            "category":"Professional",
            "subcategory":"Detective & Security Services",
            "type":"Services"
        }
    ],
    "sg:postcode":"TW1 1JF",
    "sg:province":"Greater London",
    "wof:name":"Citywide Security Ltd",
    "wof:placetype":"venue"
},
  "geometry": {"coordinates":[-0.324704,51.456352],"type":"Point"}
}