{
  "type": "Feature",
  "properties": {
    "addr:full":"48 The Ridgeway, Disley Stockport Cheshire SK12 2JQ",
    "addr:housenumber":"48",
    "addr:postcode":"sk12 2jq",
    "addr:street":"The Ridgeway",
    "iso:country":"GB",
    "sg:address":"48 The Ridgeway, Disley",
    "sg:city":"Stockport",
    "sg:classifiers":[
        {
            "category":"Building & Trades",
            "subcategory":"Construction",
            "type":"Services"
        }
    ],
    "sg:postcode":"SK12 2JQ",
    "sg:province":"Cheshire",
    "sg:tags":[
        "builder"
    ],
    "wof:name":"Arena Business Services Ltd",
    "wof:placetype":"venue"
},
  "geometry": {"coordinates":[-2.040871,53.362587],"type":"Point"}
}