{
  "type": "Feature",
  "properties": {
    "iso:country":"GB",
    "sg:address":"Balannan Farm, Ringford",
    "sg:city":"Castle Douglas",
    "sg:classifiers":[
        {
            "category":"Farming",
            "subcategory":"Farm",
            "type":"Manufacturing & Wholesale Goods"
        }
    ],
    "sg:postcode":"DG7 2AF",
    "sg:province":"Dumfries and Galloway",
    "sg:tags":[
        "mixed",
        "crop"
    ],
    "wof:name":"Alexander Millar",
    "wof:placetype":"venue"
},
  "geometry": {"coordinates":[-4.04714,54.897846],"type":"Point"}
}