{
  "type": "Feature",
  "properties": {
    "iso:country":"GB",
    "sg:address":"1 Greystone Road",
    "sg:city":"Alford",
    "sg:classifiers":[
        {
            "category":"Sports & Exercise",
            "subcategory":"Sports Center",
            "type":"Entertainment"
        }
    ],
    "sg:phone":"+44 1975 562462",
    "sg:postcode":"AB33 8PY",
    "sg:province":"Aberdeenshire",
    "sg:tags":[
        "shop",
        "good"
    ],
    "wof:name":"David's Sports & Leisure",
    "wof:placetype":"venue"
},
  "geometry": {"coordinates":[-2.702733,57.231922],"type":"Point"}
}