{
  "type": "Feature",
  "properties": {
    "addr:full":"157 High Street Dumbarton Argyll and Bute G82 1NZ",
    "addr:housenumber":"157",
    "addr:postcode":"g82 1nz",
    "addr:street":"High Street",
    "iso:country":"GB",
    "sg:address":"157 High Street",
    "sg:city":"Dumbarton",
    "sg:classifiers":[
        {
            "category":"Shopping",
            "subcategory":"Pets & Pet Supplies",
            "type":"Retail Goods"
        }
    ],
    "sg:phone":"+44 1389 732552",
    "sg:postcode":"G82 1NZ",
    "sg:province":"Argyll and Bute",
    "wof:name":"Ryan's Pet Centre",
    "wof:placetype":"venue"
},
  "geometry": {"coordinates":[-4.573394,55.944492],"type":"Point"}
}