{
  "type": "Feature",
  "properties": {
    "iso:country":"GB",
    "sg:address":"77 All Saints Lane, Nettleham",
    "sg:city":"Lincoln",
    "sg:classifiers":[
        {
            "category":"Professional",
            "subcategory":"Engineering",
            "type":"Services"
        }
    ],
    "sg:phone":"+44 1522 750870",
    "sg:postcode":"LN2 2NJ",
    "sg:province":"Lincolnshire",
    "sg:tags":[
        "contractor",
        "electrical",
        "engineer"
    ],
    "wof:name":"G & A Beckett Ltd.",
    "wof:placetype":"venue"
},
  "geometry": {"coordinates":[-0.4936290085,53.2683868408],"type":"Point"}
}