{
  "type": "Feature",
  "properties": {
    "addr:full":"68 Wittsend Caravan Site, Almholme Lane, Arksey Doncaster South Yorkshire DN5 0TP",
    "addr:housenumber":"68",
    "addr:postcode":"dn5 0tp",
    "addr:street":"Almholme Lane",
    "iso:country":"GB",
    "sg:address":"68 Wittsend Caravan Site, Almholme Lane, Arksey",
    "sg:city":"Doncaster",
    "sg:classifiers":[
        {
            "category":"Building & Trades",
            "subcategory":"Construction",
            "type":"Services"
        }
    ],
    "sg:postcode":"DN5 0TP",
    "sg:province":"South Yorkshire",
    "sg:tags":[
        "decorator",
        "painter"
    ],
    "wof:name":"David East",
    "wof:placetype":"venue"
},
  "geometry": {"coordinates":[-1.125772,53.555622],"type":"Point"}
}