{
  "type": "Feature",
  "properties": {
    "addr:full":"24 Barbarolli Mall, Unit 24 Arndale Centre Manchester Greater Manchester M4 3AA",
    "addr:housenumber":"24;unit 24",
    "addr:postcode":"m4 3aa",
    "addr:street":"Barbarolli;Arndale Centre",
    "iso:country":"GB",
    "sg:address":"24 Barbarolli Mall, Unit 24 Arndale Centre",
    "sg:city":"Manchester",
    "sg:classifiers":[
        {
            "category":"Shopping",
            "subcategory":"Luggage & Leather Goods",
            "type":"Retail Goods"
        }
    ],
    "sg:postcode":"M4 3AA",
    "sg:province":"Greater Manchester",
    "sg:tags":[
        "shop",
        "leathergoods"
    ],
    "wof:name":"Live Mode",
    "wof:placetype":"venue"
},
  "geometry": {"coordinates":[-2.24126,53.48423],"type":"Point"}
}