{
  "type": "Feature",
  "properties": {
    "addr:full":"Lewis Lane Cirencester Gloucestershire GL7 1EA",
    "addr:postcode":"gl7 1ea",
    "addr:street":"Lewis Lane",
    "iso:country":"GB",
    "sg:address":"Lewis Lane",
    "sg:city":"Cirencester",
    "sg:classifiers":[
        {
            "category":"Cinema",
            "subcategory":"Movie Theater",
            "type":"Entertainment"
        }
    ],
    "sg:phone":"+44 1285 658755",
    "sg:postcode":"GL7 1EA",
    "sg:province":"Gloucestershire",
    "wof:name":"Regal Cinema",
    "wof:placetype":"venue"
},
  "geometry": {"coordinates":[-1.9626339674,51.7158699036],"type":"Point"}
}