{
  "type": "Feature",
  "properties": {
    "addr:full":"16-18 High Town Hereford Herefordshire HR1 2AA",
    "addr:housenumber":"16-18",
    "addr:postcode":"hr1 2aa",
    "addr:street":"High Town",
    "iso:country":"GB",
    "sg:address":"16-18 High Town",
    "sg:city":"Hereford",
    "sg:classifiers":[
        {
            "category":"Shopping",
            "subcategory":"Mobile Phones",
            "type":"Retail Goods"
        }
    ],
    "sg:phone":"+44 1432 278800",
    "sg:postcode":"HR1 2AA",
    "sg:province":"Herefordshire",
    "wof:name":"The Link",
    "wof:placetype":"venue"
},
  "geometry": {"coordinates":[-2.7156500816,52.056728363],"type":"Point"}
}