{
  "type": "Feature",
  "properties": {
    "addr:full":"Country Garden Centre, Bognor Road Merston Chichester West Sussex PO20 1EG",
    "addr:postcode":"po20 1eg",
    "addr:street":"Bognor Road Merston",
    "iso:country":"GB",
    "sg:address":"Country Garden Centre, Bognor Road Merston",
    "sg:city":"Chichester",
    "sg:classifiers":[
        {
            "category":"Building & Trades",
            "subcategory":"Landscaping Services",
            "type":"Services"
        }
    ],
    "sg:postcode":"PO20 1EG",
    "sg:province":"West Sussex",
    "sg:tags":[
        "pond",
        "aquarium"
    ],
    "wof:name":"Chichester Aquatic Centre",
    "wof:placetype":"venue"
},
  "geometry": {"coordinates":[-0.7316190004,50.8211097717],"type":"Point"}
}