{
  "type": "Feature",
  "properties": {
    "addr:full":"Advertising, 127 Newgate St Bishop Auckland Durham DL14 7EN",
    "addr:housenumber":"127",
    "addr:postcode":"dl14 7en",
    "addr:street":"Newgate St",
    "iso:country":"GB",
    "sg:address":"Advertising, 127 Newgate St",
    "sg:city":"Bishop Auckland",
    "sg:classifiers":[
        {
            "category":"Communications",
            "subcategory":"Newspaper",
            "type":"Services"
        }
    ],
    "sg:phone":"+44 1388 603231",
    "sg:postcode":"DL14 7EN",
    "sg:province":"Durham",
    "sg:tags":[
        "magazine"
    ],
    "wof:name":"Northern Echo",
    "wof:placetype":"venue"
},
  "geometry": {"coordinates":[-1.680494,54.650101],"type":"Point"}
}