{
  "type": "Feature",
  "properties": {
    "iso:country":"GB",
    "sg:address":"Primrose Cottage, Frognall",
    "sg:city":"Peterborough",
    "sg:classifiers":[
        {
            "category":"Building & Trades",
            "subcategory":"Plumbing",
            "type":"Services"
        }
    ],
    "sg:postcode":"PE6 8RR",
    "sg:province":"Cambridgeshire",
    "sg:tags":[
        "heating"
    ],
    "wof:name":"Roger Benjamin Beck",
    "wof:placetype":"venue"
},
  "geometry": {"coordinates":[-0.306779,52.679924],"type":"Point"}
}