{
  "type": "Feature",
  "properties": {
    "iso:country":"GB",
    "sg:address":"210 Prince Of Wales Lane, Yardley Wood",
    "sg:city":"Birmingham",
    "sg:classifiers":[
        {
            "category":"Retail",
            "subcategory":"Auto Repair",
            "type":"Services"
        }
    ],
    "sg:phone":"+44 121 608 4644",
    "sg:postcode":"B14 4LH",
    "sg:province":"West Midlands",
    "sg:tags":[
        "modification",
        "garage"
    ],
    "wof:name":"R Ayres",
    "wof:placetype":"venue"
},
  "geometry": {"coordinates":[-1.8695,52.408653],"type":"Point"}
}