{
  "type": "Feature",
  "properties": {
    "addr:full":"Adelaide St Health Centre Norwich Norfolk NR2 4JL",
    "addr:postcode":"nr2 4jl",
    "addr:street":"Adelaide;Norwich Norfolk",
    "iso:country":"GB",
    "sg:address":"Adelaide St Health Centre",
    "sg:city":"Norwich",
    "sg:classifiers":[
        {
            "category":"Health Services",
            "subcategory":"Doctor",
            "type":"Services"
        }
    ],
    "sg:postcode":"NR2 4JL",
    "sg:province":"Norfolk",
    "sg:tags":[
        "practitioners"
    ],
    "wof:name":"T Whitehead",
    "wof:placetype":"venue"
},
  "geometry": {"coordinates":[1.277495,52.637264],"type":"Point"}
}