{
  "type": "Feature",
  "properties": {
    "addr:full":"111 Stoke Road Gosport Hampshire PO12 1LR",
    "addr:housenumber":"111",
    "addr:postcode":"po12 1lr",
    "addr:street":"Stoke Road",
    "iso:country":"GB",
    "sg:address":"111 Stoke Road",
    "sg:city":"Gosport",
    "sg:classifiers":[
        {
            "category":"Professional",
            "subcategory":"Engineering",
            "type":"Services"
        }
    ],
    "sg:phone":"+44 23 9260 2969",
    "sg:postcode":"PO12 1LR",
    "sg:province":"Hampshire",
    "sg:tags":[
        "contractor",
        "electrical",
        "engineer"
    ],
    "wof:name":"Aladdins",
    "wof:placetype":"venue"
},
  "geometry": {"coordinates":[-1.1343250275,50.7932624817],"type":"Point"}
}