{
  "type": "Feature",
  "properties": {
    "iso:country":"GB",
    "sg:address":"5 Blooming Heather, Dearham",
    "sg:city":"Maryport",
    "sg:classifiers":[
        {
            "category":"Home & Garden",
            "subcategory":"Carpets & Floor Coverings",
            "type":"Retail Goods"
        }
    ],
    "sg:phone":"+44 1900 822221",
    "sg:postcode":"CA15 7EF",
    "sg:province":"Cumbria",
    "sg:tags":[
        "cleaner",
        "upholstery"
    ],
    "wof:name":"Raysons Cleaning Services",
    "wof:placetype":"venue"
},
  "geometry": {"coordinates":[-3.4642589092,54.7079086304],"type":"Point"}
}