{
  "type": "Feature",
  "properties": {
    "addr:full":"30 Balshaw Lane, Euxton Chorley Lancashire PR7 6HX",
    "addr:housenumber":"30",
    "addr:postcode":"pr7 6hx",
    "addr:street":"Balshaw Lane",
    "iso:country":"GB",
    "sg:address":"30 Balshaw Lane, Euxton",
    "sg:city":"Chorley",
    "sg:classifiers":[
        {
            "category":"Bars & Pubs",
            "type":"Food & Drink"
        }
    ],
    "sg:phone":"+44 1257 411531",
    "sg:postcode":"PR7 6HX",
    "sg:province":"Lancashire",
    "sg:tags":[
        "pubs",
        "house",
        "inn",
        "public",
        "activity"
    ],
    "wof:name":"The Talbot Arms",
    "wof:placetype":"venue"
},
  "geometry": {"coordinates":[-2.673541069,53.6610565186],"type":"Point"}
}