{
  "type": "Feature",
  "properties": {
    "addr:full":"132 Wakefield Rd Bradford West Yorkshire BD11 1DR",
    "addr:housenumber":"132",
    "addr:postcode":"bd11 1dr",
    "addr:street":"Wakefield Rd",
    "iso:country":"GB",
    "sg:address":"132 Wakefield Rd",
    "sg:city":"Bradford",
    "sg:classifiers":[
        {
            "category":"Autos & Motor Vehicles",
            "subcategory":"Automobile Sales",
            "type":"Retail Goods"
        }
    ],
    "sg:phone":"+44 113 285 4526",
    "sg:postcode":"BD11 1DR",
    "sg:province":"West Yorkshire",
    "sg:tags":[
        "commercial"
    ],
    "wof:name":"Gildersome Motors",
    "wof:placetype":"venue"
},
  "geometry": {"coordinates":[-1.651447,53.752552],"type":"Point"}
}