{
  "type": "Feature",
  "properties": {
    "addr:full":"14 Moseley Road Willenhall West Midlands WV13 3QB",
    "addr:housenumber":"14",
    "addr:postcode":"wv13 3qb",
    "addr:street":"Moseley Road",
    "iso:country":"GB",
    "sg:address":"14 Moseley Road",
    "sg:city":"Willenhall",
    "sg:classifiers":[
        {
            "category":"Personal",
            "subcategory":"Beauty Salon",
            "type":"Services"
        }
    ],
    "sg:phone":"+44 1902 631990",
    "sg:postcode":"WV13 3QB",
    "sg:province":"West Midlands",
    "sg:tags":[
        "unisex",
        "hairdresser"
    ],
    "wof:name":"Scissorhands",
    "wof:placetype":"venue"
},
  "geometry": {"coordinates":[-2.0797379017,52.5820083618],"type":"Point"}
}