{
  "type": "Feature",
  "properties": {
    "iso:country":"GB",
    "sg:address":"14 Coombe Park",
    "sg:city":"Sutton Coldfield",
    "sg:classifiers":[
        {
            "category":"Professional",
            "subcategory":"Management & Consulting",
            "type":"Services"
        }
    ],
    "sg:postcode":"B74 2QB",
    "sg:province":"Staffordshire",
    "sg:tags":[
        "consultant",
        "business"
    ],
    "wof:name":"I C Barnsley & Associates",
    "wof:placetype":"venue"
},
  "geometry": {"coordinates":[-1.839417,52.574448],"type":"Point"}
}