{
  "type": "Feature",
  "properties": {
    "addr:full":"Hollins Lane, Burnside Kendal Cumbria LA9 6QL",
    "addr:postcode":"la9 6ql",
    "addr:street":"Hollins Lane",
    "iso:country":"GB",
    "sg:address":"Hollins Lane, Burnside",
    "sg:city":"Kendal",
    "sg:classifiers":[
        {
            "category":"Manufacturing",
            "subcategory":"Metals",
            "type":"Manufacturing & Wholesale Goods"
        }
    ],
    "sg:postcode":"LA9 6QL",
    "sg:province":"Cumbria",
    "sg:tags":[
        "work",
        "sheet"
    ],
    "wof:name":"Lakeland Canoes",
    "wof:placetype":"venue"
},
  "geometry": {"coordinates":[-2.7648630142,54.3516387939],"type":"Point"}
}