{
  "type": "Feature",
  "properties": {
    "addr:full":"Sterling House, Dix's Field Exeter Devon EX1 1QA",
    "addr:postcode":"ex1 1qa",
    "addr:street":"Dix'S Field",
    "iso:country":"GB",
    "sg:address":"Sterling House, Dix's Field",
    "sg:city":"Exeter",
    "sg:classifiers":[
        {
            "category":"Building & Trades",
            "subcategory":"Construction",
            "type":"Services"
        }
    ],
    "sg:postcode":"EX1 1QA",
    "sg:province":"Devon",
    "sg:tags":[
        "builder"
    ],
    "wof:name":"Corporate Property Solutions",
    "wof:placetype":"venue"
},
  "geometry": {"coordinates":[-3.529685,50.72036],"type":"Point"}
}