{
  "type": "Feature",
  "properties": {
    "addr:full":"Sherwood St, Warsop Mansfield Derbyshire NG20 0JR",
    "addr:postcode":"ng20 0jr",
    "addr:street":"Sherwood St",
    "iso:country":"GB",
    "sg:address":"Sherwood St, Warsop",
    "sg:city":"Mansfield",
    "sg:classifiers":[
        {
            "category":"Bars & Pubs",
            "type":"Food & Drink"
        }
    ],
    "sg:postcode":"NG20 0JR",
    "sg:province":"Derbyshire",
    "sg:tags":[
        "pubs",
        "inn"
    ],
    "wof:name":"Dog & Rabbit (The)",
    "wof:placetype":"venue"
},
  "geometry": {"coordinates":[-1.1520830393,53.2049293518],"type":"Point"}
}