{
  "type": "Feature",
  "properties": {
    "addr:full":"Unit 19a Bon Accord Centre, George Street Aberdeen Aberdeen City AB25 1UG",
    "addr:housenumber":"unit 19a",
    "addr:postcode":"ab25 1ug",
    "addr:street":"Bon Accord Centre George Street",
    "iso:country":"GB",
    "sg:address":"Unit 19a Bon Accord Centre, George Street",
    "sg:city":"Aberdeen",
    "sg:classifiers":[
        {
            "category":"Shopping",
            "subcategory":"Department Store",
            "type":"Retail Goods"
        }
    ],
    "sg:phone":"+44 1224 625950",
    "sg:postcode":"AB25 1UG",
    "sg:province":"Aberdeen City",
    "wof:name":"Woolworths",
    "wof:placetype":"venue"
},
  "geometry": {"coordinates":[-2.1067891121,57.1538200378],"type":"Point"}
}