{
  "type": "Feature",
  "properties": {
    "addr:full":"40 High St, Nailsea Bristol Somerset BS48 1AU",
    "addr:housenumber":"40",
    "addr:postcode":"bs48 1au",
    "addr:street":"High St",
    "iso:country":"GB",
    "sg:address":"40 High St, Nailsea",
    "sg:city":"Bristol",
    "sg:classifiers":[
        {
            "category":"Autos & Motor Vehicles",
            "subcategory":"Automobile Sales",
            "type":"Retail Goods"
        }
    ],
    "sg:phone":"+44 1275 855400",
    "sg:postcode":"BS48 1AU",
    "sg:province":"Somerset",
    "sg:tags":[
        "car"
    ],
    "wof:name":"Fourways Logistics UK",
    "wof:placetype":"venue"
},
  "geometry": {"coordinates":[-2.7516241074,51.4362640381],"type":"Point"}
}