{
  "type": "Feature",
  "properties": {
    "iso:country":"GB",
    "sg:address":"51 Lloyd Baker Street",
    "sg:city":"London",
    "sg:classifiers":[
        {
            "category":"Manufacturing",
            "subcategory":"Textiles",
            "type":"Manufacturing & Wholesale Goods"
        }
    ],
    "sg:phone":"+44 20 7837 9702",
    "sg:postcode":"WC1X 9AA",
    "sg:province":"Greater London",
    "sg:tags":[
        "merchant",
        "agent"
    ],
    "wof:name":"W H Wagland (Textiles) Ltd.",
    "wof:placetype":"venue"
},
  "geometry": {"coordinates":[-0.113349,51.526649],"type":"Point"}
}