{
  "type": "Feature",
  "properties": {
    "addr:full":"96 Edgware Way Edgware Greater London HA8 8JS",
    "addr:housenumber":"96",
    "addr:postcode":"ha8 8js",
    "addr:street":"Edgware Way",
    "iso:country":"GB",
    "sg:address":"96 Edgware Way",
    "sg:city":"Edgware",
    "sg:classifiers":[
        {
            "category":"Sports & Exercise",
            "subcategory":"Gym",
            "type":"Entertainment"
        }
    ],
    "sg:postcode":"HA8 8JS",
    "sg:province":"Greater London",
    "sg:tags":[
        "fitness",
        "health",
        "centre"
    ],
    "wof:name":"Collins,Jane,",
    "wof:placetype":"venue"
},
  "geometry": {"coordinates":[-0.299759,51.632664],"type":"Point"}
}