{
  "type": "Feature",
  "properties": {
    "iso:country":"GB",
    "sg:address":"57 Hazel Barrow Drive, Willerby",
    "sg:city":"Hull",
    "sg:classifiers":[
        {
            "category":"Home & Garden",
            "subcategory":"Home Furnishings",
            "type":"Retail Goods"
        }
    ],
    "sg:phone":"+44 1482 653807",
    "sg:postcode":"HU10 6QX",
    "sg:province":"East Riding of Yorkshire",
    "sg:tags":[
        "furnishers",
        "planner",
        "kitchen"
    ],
    "wof:name":"The Fitting Service by Michael Pindar",
    "wof:placetype":"venue"
},
  "geometry": {"coordinates":[-0.427342,53.751427],"type":"Point"}
}