{
  "type": "Feature",
  "properties": {
    "addr:full":"Unit 4, Curtis Rd Dorking Surrey RH4 1EJ",
    "addr:housenumber":"unit 4",
    "addr:postcode":"rh4 1ej",
    "addr:street":"Curtis Rd",
    "iso:country":"GB",
    "sg:address":"Unit 4, Curtis Rd",
    "sg:city":"Dorking",
    "sg:classifiers":[
        {
            "category":"Professional",
            "subcategory":"Detective & Security Services",
            "type":"Services"
        }
    ],
    "sg:phone":"+44 1306 875511",
    "sg:postcode":"RH4 1EJ",
    "sg:province":"Surrey",
    "wof:name":"Jewel Facilities Ltd.",
    "wof:placetype":"venue"
},
  "geometry": {"coordinates":[-0.3375839889,51.2333831787],"type":"Point"}
}