{
  "type": "Feature",
  "properties": {
    "addr:full":"Duff Street La Edinburgh City of Edinburgh EH11 2HS",
    "addr:postcode":"eh11 2hs",
    "addr:street":"Duff Street La Edinburgh",
    "iso:country":"GB",
    "sg:address":"Duff Street La",
    "sg:city":"Edinburgh",
    "sg:classifiers":[
        {
            "category":"Retail",
            "subcategory":"Auto Repair",
            "type":"Services"
        }
    ],
    "sg:postcode":"EH11 2HS",
    "sg:province":"City of Edinburgh",
    "sg:tags":[
        "modification",
        "garage"
    ],
    "wof:name":"Ross,Brian,",
    "wof:placetype":"venue"
},
  "geometry": {"coordinates":[-3.2253088951,55.9426689148],"type":"Point"}
}