{
  "type": "Feature",
  "properties": {
    "iso:country":"GB",
    "sg:address":"1 Gatliff Road",
    "sg:city":"London",
    "sg:classifiers":[
        {
            "category":"Professional",
            "subcategory":"Art Services",
            "type":"Services"
        }
    ],
    "sg:postcode":"SW1W 8QR",
    "sg:province":"Greater London",
    "sg:tags":[
        "model",
        "maker"
    ],
    "wof:name":"Avanti G",
    "wof:placetype":"venue"
},
  "geometry": {"coordinates":[-0.150087,51.487049],"type":"Point"}
}