{
  "type": "Feature",
  "properties": {
    "iso:country":"GB",
    "sg:address":"The Lodge, 59 Whitham Road",
    "sg:city":"Sheffield",
    "sg:classifiers":[
        {
            "category":"Health Services",
            "subcategory":"Health Practitioner",
            "type":"Services"
        }
    ],
    "sg:phone":"+44 114 267 1171",
    "sg:postcode":"S10 2SL",
    "sg:province":"South Yorkshire",
    "sg:tags":[
        "acupuncture"
    ],
    "wof:name":"College of Oriental Medicine Ltd.",
    "wof:placetype":"venue"
},
  "geometry": {"coordinates":[-1.464544,53.38311],"type":"Point"}
}