{
  "type": "Feature",
  "properties": {
    "iso:country":"GB",
    "sg:address":"Bircholt Road",
    "sg:city":"Maidstone",
    "sg:classifiers":[
        {
            "category":"Autos & Motor Vehicles",
            "subcategory":"Automobile Sales",
            "type":"Retail Goods"
        }
    ],
    "sg:phone":"+44 1622 699200",
    "sg:postcode":"ME15 9XL",
    "sg:province":"Kent",
    "sg:tags":[
        "car"
    ],
    "wof:name":"The Dutton-Forshaw Motor Co. Ltd.",
    "wof:placetype":"venue"
},
  "geometry": {"coordinates":[0.5634350181,51.2391395569],"type":"Point"}
}