{
  "type": "Feature",
  "properties": {
    "addr:full":"22-23 Overcliffe Gravesend Kent DA11 0EH",
    "addr:housenumber":"22-23",
    "addr:postcode":"da11 0eh",
    "addr:street":"Overcliffe",
    "iso:country":"GB",
    "sg:address":"22-23 Overcliffe",
    "sg:city":"Gravesend",
    "sg:classifiers":[
        {
            "category":"Farming",
            "subcategory":"Nursery",
            "type":"Manufacturing & Wholesale Goods"
        },
        {
            "category":"Education",
            "subcategory":"Preschool",
            "type":"Public Place"
        }
    ],
    "sg:phone":"+44 1474 361354",
    "sg:postcode":"DA11 0EH",
    "sg:province":"Kent",
    "sg:tags":[
        "school",
        "creche"
    ],
    "wof:name":"SWAN HOUSE NURSERY SCHOOL",
    "wof:placetype":"venue"
},
  "geometry": {"coordinates":[0.359714,51.442211],"type":"Point"}
}