{
  "type": "Feature",
  "properties": {
    "iso:country":"GB",
    "sg:address":"Three Lea Hall",
    "sg:city":"Bishops Stortford",
    "sg:classifiers":[
        {
            "category":"Personal",
            "type":"Services"
        }
    ],
    "sg:phone":"+44 7860 300989",
    "sg:postcode":"CM22 7BL",
    "sg:province":"Essex",
    "sg:tags":[
        "wedding"
    ],
    "wof:name":"H M Marquees",
    "wof:placetype":"venue"
},
  "geometry": {"coordinates":[0.16195,51.87233],"type":"Point"}
}