{
  "type": "Feature",
  "properties": {
    "addr:full":"8 Falkland Street Liverpool Merseyside L3 8HB",
    "addr:housenumber":"8",
    "addr:postcode":"l3 8hb",
    "addr:street":"Falkland Street",
    "iso:country":"GB",
    "sg:address":"8 Falkland Street",
    "sg:city":"Liverpool",
    "sg:classifiers":[
        {
            "category":"Building & Trades",
            "subcategory":"Electrical",
            "type":"Services"
        },
        {
            "category":"Utilities",
            "type":"Services"
        }
    ],
    "sg:postcode":"L3 8HB",
    "sg:province":"Merseyside",
    "sg:tags":[
        "connection",
        "contractor",
        "electrician",
        "internet",
        "provider"
    ],
    "wof:name":"Mersinet Ltd.",
    "wof:placetype":"venue"
},
  "geometry": {"coordinates":[-2.969343,53.410343],"type":"Point"}
}