{
  "type": "Feature",
  "properties": {
    "addr:full":"Rectory Farm, Little Staughton Bedford Bedfordshire MK44 2TA",
    "addr:postcode":"mk44 2ta",
    "addr:street":"Rectory",
    "iso:country":"GB",
    "sg:address":"Rectory Farm, Little Staughton",
    "sg:city":"Bedford",
    "sg:classifiers":[
        {
            "category":"Farming",
            "subcategory":"Livestock Farm",
            "type":"Manufacturing & Wholesale Goods"
        }
    ],
    "sg:phone":"+44 1234 376364",
    "sg:postcode":"MK44 2TA",
    "sg:province":"Bedfordshire",
    "sg:tags":[
        "others"
    ],
    "wof:name":"A I Topham & Son",
    "wof:placetype":"venue"
},
  "geometry": {"coordinates":[-0.3820239902,52.2504959106],"type":"Point"}
}