{
  "type": "Feature",
  "properties": {
    "addr:full":"4 Glebe Close, Littleham Exmouth Devon EX8 2QU",
    "addr:housenumber":"4",
    "addr:postcode":"ex8 2qu",
    "addr:street":"Glebe Close",
    "iso:country":"GB",
    "sg:address":"4 Glebe Close, Littleham",
    "sg:city":"Exmouth",
    "sg:classifiers":[
        {
            "category":"Building & Trades",
            "subcategory":"Construction",
            "type":"Services"
        }
    ],
    "sg:phone":"+44 1395 266450",
    "sg:postcode":"EX8 2QU",
    "sg:province":"Devon",
    "sg:tags":[
        "glazier"
    ],
    "wof:name":"David M Hocking",
    "wof:placetype":"venue"
},
  "geometry": {"coordinates":[-3.385174036,50.6267585754],"type":"Point"}
}