{
  "type": "Feature",
  "properties": {
    "iso:country":"GB",
    "sg:address":"Blue Mills, Wickham Hill",
    "sg:city":"Witham",
    "sg:classifiers":[
        {
            "category":"Health Services",
            "subcategory":"Clinic",
            "type":"Services"
        }
    ],
    "sg:phone":"+44 1621 891459",
    "sg:postcode":"CM8 3LH",
    "sg:province":"Essex",
    "sg:tags":[
        "aromatherapy"
    ],
    "wof:name":"A M R Therapies",
    "wof:placetype":"venue"
},
  "geometry": {"coordinates":[0.656702,51.786121],"type":"Point"}
}