{
  "type": "Feature",
  "properties": {
    "addr:full":"79b Brook Lane, Walsall Wood Walsall Staffordshire WS9 9NA",
    "addr:housenumber":"79b",
    "addr:postcode":"ws9 9na",
    "addr:street":"Brook Lane",
    "iso:country":"GB",
    "sg:address":"79b Brook Lane, Walsall Wood",
    "sg:city":"Walsall",
    "sg:classifiers":[
        {
            "category":"Building & Trades",
            "subcategory":"Plumbing",
            "type":"Services"
        }
    ],
    "sg:phone":"+44 1543 378882",
    "sg:postcode":"WS9 9NA",
    "sg:province":"Staffordshire",
    "sg:tags":[
        "central",
        "heating"
    ],
    "wof:name":"Burntwood Plumbing & Heating Services",
    "wof:placetype":"venue"
},
  "geometry": {"coordinates":[-1.929391,52.62664],"type":"Point"}
}