{
  "type": "Feature",
  "properties": {
    "addr:full":"32-38 High Street, Epworth Doncaster Lincolnshire DN9 1EP",
    "addr:housenumber":"32-38",
    "addr:postcode":"dn9 1ep",
    "addr:street":"High Street",
    "iso:country":"GB",
    "sg:address":"32-38 High Street, Epworth",
    "sg:city":"Doncaster",
    "sg:classifiers":[
        {
            "category":"Banks & Credit Unions",
            "subcategory":"Financial Services",
            "type":"Services"
        },
        {
            "category":"Real Estate",
            "subcategory":"Real Estate Agent",
            "type":"Services"
        }
    ],
    "sg:phone":"+44 1427 873236",
    "sg:postcode":"DN9 1EP",
    "sg:province":"Lincolnshire",
    "sg:tags":[
        "consultant"
    ],
    "wof:name":"Keith Clough Properties",
    "wof:placetype":"venue"
},
  "geometry": {"coordinates":[-0.8210909963,53.5256271362],"type":"Point"}
}