{
  "type": "Feature",
  "properties": {
    "iso:country":"GB",
    "sg:address":"14 Galgate",
    "sg:city":"Barnard Castle",
    "sg:classifiers":[
        {
            "category":"Shopping",
            "type":"Retail Goods"
        }
    ],
    "sg:phone":"+44 1833 637224",
    "sg:postcode":"DL12 8BG",
    "sg:province":"Cumbria",
    "sg:tags":[
        "merchant"
    ],
    "wof:name":"Phillip Holden Rural",
    "wof:placetype":"venue"
},
  "geometry": {"coordinates":[-1.924615,54.545071],"type":"Point"}
}