{
  "type": "Feature",
  "properties": {
    "addr:full":"772 London Road Derby Derbyshire DE24 8UT",
    "addr:housenumber":"772",
    "addr:postcode":"de24 8ut",
    "addr:street":"London Road",
    "iso:country":"GB",
    "sg:address":"772 London Road",
    "sg:city":"Derby",
    "sg:classifiers":[
        {
            "category":"Wholesale",
            "subcategory":"Construction Materials",
            "type":"Manufacturing & Wholesale Goods"
        }
    ],
    "sg:phone":"+44 1332 755699",
    "sg:postcode":"DE24 8UT",
    "sg:province":"Derbyshire",
    "sg:tags":[
        "lift"
    ],
    "wof:name":"Hss Lift & Shift",
    "wof:placetype":"venue"
},
  "geometry": {"coordinates":[-1.447546,52.905067],"type":"Point"}
}