{
  "type": "Feature",
  "properties": {
    "iso:country":"GB",
    "sg:address":"Flat 1, Riverside Walk, Aberavon Shopping Centre",
    "sg:city":"Port Talbot",
    "sg:classifiers":[
        {
            "category":"Real Estate",
            "subcategory":"Architect",
            "type":"Services"
        }
    ],
    "sg:postcode":"SA13 1PB",
    "sg:province":"Neath Port Talbot",
    "wof:name":"Majento",
    "wof:placetype":"venue"
},
  "geometry": {"coordinates":[-3.78549,51.59676],"type":"Point"}
}