{
  "type": "Feature",
  "properties": {
    "addr:full":"112/116 Hazelwick Road, Three Bridges Crawley Surrey RH10 1NQ",
    "addr:housenumber":"112 / 116",
    "addr:postcode":"rh10 1nq",
    "addr:street":"Hazelwick Road",
    "iso:country":"GB",
    "sg:address":"112/116 Hazelwick Road, Three Bridges",
    "sg:city":"Crawley",
    "sg:classifiers":[
        {
            "category":"Professional",
            "subcategory":"Detective & Security Services",
            "type":"Services"
        }
    ],
    "sg:phone":"+44 1293 525673",
    "sg:postcode":"RH10 1NQ",
    "sg:province":"Surrey",
    "sg:tags":[
        "alarm",
        "burglar",
        "system"
    ],
    "wof:name":"Peter Weare (1984) Ltd.",
    "wof:placetype":"venue"
},
  "geometry": {"coordinates":[-0.167473,51.119202],"type":"Point"}
}