{
  "type": "Feature",
  "properties": {
    "addr:full":"11-13 Suffolk Rd Cheltenham Gloucestershire GL50 2AF",
    "addr:housenumber":"11-13",
    "addr:postcode":"gl50 2af",
    "addr:street":"Suffolk Rd",
    "iso:country":"GB",
    "sg:address":"11-13 Suffolk Rd",
    "sg:city":"Cheltenham",
    "sg:classifiers":[
        {
            "category":"Home & Garden",
            "subcategory":"Furniture",
            "type":"Retail Goods"
        }
    ],
    "sg:phone":"+44 1242 576277",
    "sg:postcode":"GL50 2AF",
    "sg:province":"Gloucestershire",
    "wof:name":"Benchmark",
    "wof:placetype":"venue"
},
  "geometry": {"coordinates":[-2.079833,51.891708],"type":"Point"}
}