{
  "type": "Feature",
  "properties": {
    "addr:full":"Home Farm, Main Street, Cottesbrooke Northampton Northamptonshire NN6 8PH",
    "addr:postcode":"nn6 8ph",
    "addr:street":"Main Street",
    "iso:country":"GB",
    "sg:address":"Home Farm, Main Street, Cottesbrooke",
    "sg:city":"Northampton",
    "sg:classifiers":[
        {
            "category":"Banks & Credit Unions",
            "subcategory":"Investment Brokerage",
            "type":"Services"
        }
    ],
    "sg:postcode":"NN6 8PH",
    "sg:province":"Northamptonshire",
    "sg:tags":[
        "contractor"
    ],
    "wof:name":"P T Harris & Son",
    "wof:placetype":"venue"
},
  "geometry": {"coordinates":[-0.957669,52.355358],"type":"Point"}
}