{
  "type": "Feature",
  "properties": {
    "addr:full":"21 Digbeth Birmingham West Midlands B5 6BL",
    "addr:housenumber":"21",
    "addr:postcode":"b5 6bl",
    "addr:street":"Digbeth",
    "iso:country":"GB",
    "sg:address":"21 Digbeth",
    "sg:city":"Birmingham",
    "sg:classifiers":[
        {
            "category":"Banks & Credit Unions",
            "subcategory":"Bank",
            "type":"Services"
        }
    ],
    "sg:phone":"+44 121 212 2220",
    "sg:postcode":"B5 6BL",
    "sg:province":"West Midlands",
    "wof:name":"NatWest",
    "wof:placetype":"venue"
},
  "geometry": {"coordinates":[-1.89,52.475796],"type":"Point"}
}