{
  "type": "Feature",
  "properties": {
    "addr:full":"9 St Bedes Avenue Blackpool Lancashire FY4 1AQ",
    "addr:housenumber":"9",
    "addr:postcode":"fy4 1aq",
    "addr:street":"St Bedes Avenue",
    "iso:country":"GB",
    "sg:address":"9 St Bedes Avenue",
    "sg:city":"Blackpool",
    "sg:classifiers":[
        {
            "category":"Travel",
            "subcategory":"Hotels & Motels",
            "type":"Entertainment"
        }
    ],
    "sg:phone":"+44 1253 342516",
    "sg:postcode":"FY4 1AQ",
    "sg:province":"Lancashire",
    "sg:tags":[
        "house",
        "guest"
    ],
    "wof:name":"Brimarl Guest House",
    "wof:placetype":"venue"
},
  "geometry": {"coordinates":[-3.053137,53.799095],"type":"Point"}
}