{
  "type": "Feature",
  "properties": {
    "iso:country":"GB",
    "sg:address":"366 York Road",
    "sg:city":"Leeds",
    "sg:classifiers":[
        {
            "category":"Building & Trades",
            "subcategory":"Construction",
            "type":"Services"
        }
    ],
    "sg:phone":"+44 113 248 3644",
    "sg:postcode":"LS9 9DN",
    "sg:province":"West Yorkshire",
    "sg:tags":[
        "roofing"
    ],
    "wof:name":"B Adams Roofing Contractors",
    "wof:placetype":"venue"
},
  "geometry": {"coordinates":[-1.5078,53.798958],"type":"Point"}
}