{
  "type": "Feature",
  "properties": {
    "iso:country":"GB",
    "sg:address":"23 Newgate Street",
    "sg:city":"Chester",
    "sg:classifiers":[
        {
            "category":"Real Estate",
            "subcategory":"Architect",
            "type":"Services"
        }
    ],
    "sg:phone":"+44 1244 327191",
    "sg:postcode":"CH1 1DE",
    "sg:province":"Cheshire",
    "wof:name":"Clifford Thompson",
    "wof:placetype":"venue"
},
  "geometry": {"coordinates":[-2.888446,53.189259],"type":"Point"}
}