{
  "type": "Feature",
  "properties": {
    "addr:full":"Tyr Cwrt, Manordilo Llandeilo Carmarthenshire SA19 7BL",
    "addr:postcode":"sa19 7bl",
    "iso:country":"GB",
    "sg:address":"Tyr Cwrt, Manordilo",
    "sg:city":"Llandeilo",
    "sg:classifiers":[
        {
            "category":"Shopping",
            "subcategory":"Party Supplies",
            "type":"Retail Goods"
        }
    ],
    "sg:postcode":"SA19 7BL",
    "sg:province":"Carmarthenshire",
    "sg:tags":[
        "marquees",
        "floor",
        "tent"
    ],
    "wof:name":"Thomas,Thomas G,",
    "wof:placetype":"venue"
},
  "geometry": {"coordinates":[-3.991857,51.884136],"type":"Point"}
}