{
  "type": "Feature",
  "properties": {
    "addr:full":"1 Small Holdings, Clentry Kelty Fife KY4 0JQ",
    "addr:housenumber":"1",
    "addr:postcode":"ky4 0jq",
    "addr:street":"Small Holdings",
    "iso:country":"GB",
    "sg:address":"1 Small Holdings, Clentry",
    "sg:city":"Kelty",
    "sg:classifiers":[
        {
            "category":"Home & Garden",
            "subcategory":"Building Materials",
            "type":"Retail Goods"
        }
    ],
    "sg:phone":"+44 1383 830538",
    "sg:postcode":"KY4 0JQ",
    "sg:province":"Fife",
    "sg:tags":[
        "fencing"
    ],
    "wof:name":"Forestry Firewood & Fencing",
    "wof:placetype":"venue"
},
  "geometry": {"coordinates":[-3.382089,56.136684],"type":"Point"}
}