{
  "type": "Feature",
  "properties": {
    "addr:full":"109-123 Southlands Road Bromley Kent BR2 9QT",
    "addr:housenumber":"109-123",
    "addr:postcode":"br2 9qt",
    "addr:street":"Southlands Road",
    "iso:country":"GB",
    "sg:address":"109-123 Southlands Road",
    "sg:city":"Bromley",
    "sg:classifiers":[
        {
            "category":"Home & Garden",
            "subcategory":"Carpets & Floor Coverings",
            "type":"Retail Goods"
        }
    ],
    "sg:phone":"+44 20 8460 6655",
    "sg:postcode":"BR2 9QT",
    "sg:province":"Kent",
    "sg:tags":[
        "material",
        "flooring"
    ],
    "wof:name":"A W Champion (Bromley) Ltd.",
    "wof:placetype":"venue"
},
  "geometry": {"coordinates":[0.0356170014,51.3951759338],"type":"Point"}
}