{
  "type": "Feature",
  "properties": {
    "iso:country":"GB",
    "sg:address":"478 Chiswick High Road",
    "sg:city":"London",
    "sg:classifiers":[
        {
            "category":"Professional",
            "type":"Services"
        }
    ],
    "sg:phone":"+44 20 8994 9993",
    "sg:postcode":"W4 5TT",
    "sg:province":"Greater London",
    "sg:tags":[
        "interior",
        "furnishers",
        "designer"
    ],
    "wof:name":"Helen Reid Designs",
    "wof:placetype":"venue"
},
  "geometry": {"coordinates":[-0.273029,51.492611],"type":"Point"}
}