{
  "type": "Feature",
  "properties": {
    "addr:full":"Fox & Driver Furniture Centre, Huddersfield Rd Mirfield West Yorkshire WF14 8AZ",
    "addr:postcode":"wf14 8az",
    "addr:street":"Huddersfield Rd",
    "iso:country":"GB",
    "sg:address":"Fox & Driver Furniture Centre, Huddersfield Rd",
    "sg:city":"Mirfield",
    "sg:classifiers":[
        {
            "category":"Home & Garden",
            "subcategory":"Home Furnishings",
            "type":"Retail Goods"
        }
    ],
    "sg:phone":"+44 1924 498732",
    "sg:postcode":"WF14 8AZ",
    "sg:province":"West Yorkshire",
    "sg:tags":[
        "furnishers",
        "planner",
        "kitchen"
    ],
    "wof:name":"Designs For Living",
    "wof:placetype":"venue"
},
  "geometry": {"coordinates":[-1.697329998,53.675491333],"type":"Point"}
}