{
  "type": "Feature",
  "properties": {
    "addr:full":"The New Market, Waterloo Road Blackpool Lancashire FY4 1AF",
    "addr:postcode":"fy4 1af",
    "addr:street":"Waterloo Road",
    "iso:country":"GB",
    "sg:address":"The New Market, Waterloo Road",
    "sg:city":"Blackpool",
    "sg:classifiers":[
        {
            "category":"Building & Trades",
            "subcategory":"Locksmith",
            "type":"Services"
        }
    ],
    "sg:postcode":"FY4 1AF",
    "sg:province":"Lancashire",
    "sg:tags":[
        "cutting",
        "key"
    ],
    "wof:name":"Shoe Care",
    "wof:placetype":"venue"
},
  "geometry": {"coordinates":[-3.055380106,53.7984199524],"type":"Point"}
}