{
  "type": "Feature",
  "properties": {
    "iso:country":"GB",
    "sg:address":"Shoreline Ho, 11-17 Fowler Rd",
    "sg:city":"Ilford",
    "sg:classifiers":[
        {
            "category":"Wholesale",
            "subcategory":"Sporting Goods",
            "type":"Manufacturing & Wholesale Goods"
        }
    ],
    "sg:phone":"+44 20 8500 2000",
    "sg:postcode":"IG6 3UJ",
    "sg:province":"Essex",
    "sg:tags":[
        "mnfr",
        "sport",
        "equipment"
    ],
    "wof:name":"Headstrong Sports Ltd",
    "wof:placetype":"venue"
},
  "geometry": {"coordinates":[0.12104,51.608391],"type":"Point"}
}