{
  "type": "Feature",
  "properties": {
    "iso:country":"GB",
    "sg:address":"Hertfordshire Cheshire Home, St. Johns Rd",
    "sg:city":"Hitchin",
    "sg:classifiers":[
        {
            "category":"Social Services",
            "subcategory":"Retirement Home",
            "type":"Services"
        }
    ],
    "sg:phone":"+44 1462 422664",
    "sg:postcode":"SG4 9DD",
    "sg:province":"Hertfordshire",
    "sg:tags":[
        "care"
    ],
    "wof:name":"North Herts Care at Home Service",
    "wof:placetype":"venue"
},
  "geometry": {"coordinates":[-0.27473,51.942039],"type":"Point"}
}