{
  "type": "Feature",
  "properties": {
    "iso:country":"GB",
    "sg:address":"39 Hall St",
    "sg:city":"Nottingham",
    "sg:classifiers":[
        {
            "category":"Professional",
            "subcategory":"Lawyer & Legal Services",
            "type":"Services"
        }
    ],
    "sg:phone":"+44 115 960 2734",
    "sg:postcode":"NG5 4AS",
    "sg:province":"Nottinghamshire",
    "sg:tags":[
        "advice",
        "counselling"
    ],
    "wof:name":"Pamela Breese",
    "wof:placetype":"venue"
},
  "geometry": {"coordinates":[-1.143095,52.983017],"type":"Point"}
}