{
  "type": "Feature",
  "properties": {
    "addr:full":"12 North Street, Ashburton Newton Abbot Devon TQ13 7QD",
    "addr:housenumber":"12",
    "addr:postcode":"tq13 7qd",
    "addr:street":"North Street",
    "iso:country":"GB",
    "sg:address":"12 North Street, Ashburton",
    "sg:city":"Newton Abbot",
    "sg:classifiers":[
        {
            "category":"Food & Beverages",
            "subcategory":"Liquor & Beverages",
            "type":"Retail Goods"
        }
    ],
    "sg:postcode":"TQ13 7QD",
    "sg:province":"Devon",
    "sg:tags":[
        "beer",
        "spirit",
        "wines"
    ],
    "wof:name":"Best Cellars",
    "wof:placetype":"venue"
},
  "geometry": {"coordinates":[-3.756385088,50.515789032],"type":"Point"}
}