{
  "type": "Feature",
  "properties": {
    "addr:full":"9-11 Victoria Street St Albans Hertfordshire AL1 3UB",
    "addr:housenumber":"9-11",
    "addr:postcode":"al1 3ub",
    "addr:street":"Victoria Street",
    "iso:country":"GB",
    "sg:address":"9-11 Victoria Street",
    "sg:city":"St Albans",
    "sg:classifiers":[
        {
            "category":"Real Estate",
            "subcategory":"Surveying",
            "type":"Services"
        },
        {
            "category":"Real Estate",
            "subcategory":"Real Estate Agent",
            "type":"Services"
        }
    ],
    "sg:phone":"+44 1727 794101",
    "sg:postcode":"AL1 3UB",
    "sg:province":"Hertfordshire",
    "sg:tags":[
        "surveyor",
        "valuer"
    ],
    "wof:name":"Halls Commercial",
    "wof:placetype":"venue"
},
  "geometry": {"coordinates":[-0.337123,51.751949],"type":"Point"}
}