{
  "type": "Feature",
  "properties": {
    "addr:full":"Unit 1, Maundrell Road Calne Wiltshire SN11 9PU",
    "addr:housenumber":"unit 1",
    "addr:postcode":"sn11 9pu",
    "addr:street":"Maundrell Road",
    "iso:country":"GB",
    "sg:address":"Unit 1, Maundrell Road",
    "sg:city":"Calne",
    "sg:classifiers":[
        {
            "category":"Professional",
            "subcategory":"Business Services",
            "type":"Services"
        }
    ],
    "sg:phone":"+44 1249 813170",
    "sg:postcode":"SN11 9PU",
    "sg:province":"Wiltshire",
    "sg:tags":[
        "import",
        "export",
        "agent"
    ],
    "wof:name":"Wiltshire Freight Services Ltd.",
    "wof:placetype":"venue"
},
  "geometry": {"coordinates":[-1.999594,51.450741],"type":"Point"}
}