{
  "type": "Feature",
  "properties": {
    "addr:full":"1 Bryn Ucha, New Rhosrobin, Rhosrobin Wrexham Wrexham LL11 4PL",
    "addr:housenumber":"1",
    "addr:postcode":"ll11 4pl",
    "addr:street":"Bryn Ucha New;Rhosrobin",
    "iso:country":"GB",
    "sg:address":"1 Bryn Ucha, New Rhosrobin, Rhosrobin",
    "sg:city":"Wrexham",
    "sg:classifiers":[
        {
            "category":"Building & Trades",
            "subcategory":"Landscaping Services",
            "type":"Services"
        },
        {
            "category":"Building & Trades",
            "subcategory":"Equipment Rental",
            "type":"Services"
        }
    ],
    "sg:phone":"+44 1978 361384",
    "sg:postcode":"LL11 4PL",
    "sg:province":"Wrexham",
    "sg:tags":[
        "gardening",
        "firefighting"
    ],
    "wof:name":"Border Fire Protection",
    "wof:placetype":"venue"
},
  "geometry": {"coordinates":[-3.002699,53.070621],"type":"Point"}
}