{
  "type": "Feature",
  "properties": {
    "iso:country":"GB",
    "sg:address":"19 Louisa Street",
    "sg:city":"London",
    "sg:classifiers":[
        {
            "category":"Insurance",
            "subcategory":"Insurance Agent",
            "type":"Services"
        }
    ],
    "sg:phone":"+44 20 7790 1963",
    "sg:postcode":"E1 4NF",
    "sg:province":"Greater London",
    "sg:tags":[
        "broker"
    ],
    "wof:name":"Phillippa Levy & Associates Ltd.",
    "wof:placetype":"venue"
},
  "geometry": {"coordinates":[-0.046817,51.520985],"type":"Point"}
}