{
  "type": "Feature",
  "properties": {
    "addr:full":"80 Rosedale Avenue York North Yorkshire YO26 5LQ",
    "addr:housenumber":"80",
    "addr:postcode":"yo26 5lq",
    "addr:street":"Rosedale Avenue",
    "iso:country":"GB",
    "sg:address":"80 Rosedale Avenue",
    "sg:city":"York",
    "sg:classifiers":[
        {
            "category":"Shopping",
            "subcategory":"Adult",
            "type":"Retail Goods"
        }
    ],
    "sg:postcode":"YO26 5LQ",
    "sg:province":"North Yorkshire",
    "sg:tags":[
        "graphologist"
    ],
    "wof:name":"Joyce Martin",
    "wof:placetype":"venue"
},
  "geometry": {"coordinates":[-1.131746,53.956451],"type":"Point"}
}