{
  "type": "Feature",
  "properties": {
    "addr:full":"Strawberry Hill, Station Wellesley Road Twickenham Greater London TW2 5SQ",
    "addr:postcode":"tw2 5sq",
    "addr:street":"Wellesley Road",
    "iso:country":"GB",
    "sg:address":"Strawberry Hill, Station Wellesley Road",
    "sg:city":"Twickenham",
    "sg:classifiers":[
        {
            "category":"Taxi",
            "type":"Transportation"
        }
    ],
    "sg:postcode":"TW2 5SQ",
    "sg:province":"Greater London",
    "sg:tags":[
        "mini",
        "cab"
    ],
    "wof:name":"Strawberry Hill Car Service",
    "wof:placetype":"venue"
},
  "geometry": {"coordinates":[-0.33983,51.438889],"type":"Point"}
}