{
  "type": "Feature",
  "properties": {
    "addr:full":"Old Shire Hall, Old Elvet Durham Durham DH1 3HP",
    "addr:postcode":"dh1 3hp",
    "addr:street":"Old;Old Elvet",
    "iso:country":"GB",
    "sg:address":"Old Shire Hall, Old Elvet",
    "sg:city":"Durham",
    "sg:classifiers":[
        {
            "category":"Professional",
            "subcategory":"Business Services",
            "type":"Services"
        }
    ],
    "sg:postcode":"DH1 3HP",
    "sg:province":"Durham",
    "sg:tags":[
        "assessment",
        "quality"
    ],
    "wof:name":"North East Microelectronics Centre Ltd",
    "wof:placetype":"venue"
},
  "geometry": {"coordinates":[-1.574608,54.777534],"type":"Point"}
}