{
  "type": "Feature",
  "properties": {
    "addr:full":"3a Piershill Pl Edinburgh City of Edinburgh EH8 7EH",
    "addr:housenumber":"3a",
    "addr:postcode":"eh8 7eh",
    "addr:street":"Piershill Pl",
    "iso:country":"GB",
    "sg:address":"3a Piershill Pl",
    "sg:city":"Edinburgh",
    "sg:classifiers":[
        {
            "category":"Building & Trades",
            "subcategory":"Construction",
            "type":"Services"
        }
    ],
    "sg:phone":"+44 131 652 0352",
    "sg:postcode":"EH8 7EH",
    "sg:province":"City of Edinburgh",
    "sg:tags":[
        "roofing"
    ],
    "wof:name":"Argos Roofing Services",
    "wof:placetype":"venue"
},
  "geometry": {"coordinates":[-3.1486051083,55.9550514221],"type":"Point"}
}