{
  "type": "Feature",
  "properties": {
    "iso:country":"GB",
    "sg:address":"15 Langdyke",
    "sg:city":"Peterborough",
    "sg:classifiers":[
        {
            "category":"Professional",
            "subcategory":"Art Services",
            "type":"Services"
        }
    ],
    "sg:phone":"+44 1733 898167",
    "sg:postcode":"PE1 4SS",
    "sg:province":"Cambridgeshire",
    "sg:tags":[
        "consultant",
        "design"
    ],
    "wof:name":"Zigzag Design",
    "wof:placetype":"venue"
},
  "geometry": {"coordinates":[-0.205819,52.592587],"type":"Point"}
}