{
  "type": "Feature",
  "properties": {
    "addr:full":"Wilmot Road Swadlincote Derbyshire DE11 9BJ",
    "addr:postcode":"de11 9bj",
    "addr:street":"Wilmot Road",
    "iso:country":"GB",
    "sg:address":"Wilmot Road",
    "sg:city":"Swadlincote",
    "sg:classifiers":[
        {
            "category":"Food & Beverages",
            "subcategory":"Groceries & Convenience Stores",
            "type":"Retail Goods"
        }
    ],
    "sg:phone":"+44 1283 219415",
    "sg:postcode":"DE11 9BJ",
    "sg:province":"Derbyshire",
    "wof:name":"The Chalet Mini Market",
    "wof:placetype":"venue"
},
  "geometry": {"coordinates":[-1.562974,52.771095],"type":"Point"}
}