{
  "type": "Feature",
  "properties": {
    "addr:full":"37-39 Anne Rd, Smetwick Birmingham West Midlands B66 2NZ",
    "addr:housenumber":"37-39",
    "addr:postcode":"b66 2nz",
    "addr:street":"Anne Rd",
    "iso:country":"GB",
    "sg:address":"37-39 Anne Rd, Smetwick",
    "sg:city":"Birmingham",
    "sg:classifiers":[
        {
            "category":"Retail",
            "subcategory":"Storage",
            "type":"Services"
        }
    ],
    "sg:phone":"+44 121 454 2157",
    "sg:postcode":"B66 2NZ",
    "sg:province":"West Midlands",
    "sg:tags":[
        "household",
        "removal"
    ],
    "wof:name":"Stevens",
    "wof:placetype":"venue"
},
  "geometry": {"coordinates":[-1.950209,52.500542],"type":"Point"}
}