{
  "type": "Feature",
  "properties": {
    "iso:country":"GB",
    "sg:address":"Marcassie Farm, Rafford",
    "sg:city":"Forres",
    "sg:classifiers":[
        {
            "category":"Building & Trades",
            "subcategory":"Construction",
            "type":"Services"
        }
    ],
    "sg:phone":"+44 1309 671700",
    "sg:postcode":"IV36 2RH",
    "sg:province":"Moray",
    "sg:tags":[
        "joinery"
    ],
    "wof:name":"Nor Build",
    "wof:placetype":"venue"
},
  "geometry": {"coordinates":[-3.574999,57.588848],"type":"Point"}
}