{
  "type": "Feature",
  "properties": {
    "addr:full":"33 William Street Edinburgh City of Edinburgh EH3 7LW",
    "addr:housenumber":"33",
    "addr:postcode":"eh3 7lw",
    "addr:street":"William Street",
    "iso:country":"GB",
    "sg:address":"33 William Street",
    "sg:city":"Edinburgh",
    "sg:classifiers":[
        {
            "category":"Professional",
            "type":"Services"
        }
    ],
    "sg:phone":"+44 131 538 7165",
    "sg:postcode":"EH3 7LW",
    "sg:province":"City of Edinburgh",
    "sg:tags":[
        "caterer"
    ],
    "wof:name":"Silvagni's Uppercrust",
    "wof:placetype":"venue"
},
  "geometry": {"coordinates":[-3.2137870789,55.9488182068],"type":"Point"}
}