{
  "type": "Feature",
  "properties": {
    "addr:full":"235 Lavender Hill, Battersea London Greater London SW11 1JW",
    "addr:housenumber":"235",
    "addr:postcode":"sw11 1jw",
    "addr:street":"Lavender Hill",
    "iso:country":"GB",
    "sg:address":"235 Lavender Hill, Battersea",
    "sg:city":"London",
    "sg:classifiers":[
        {
            "category":"Real Estate",
            "subcategory":"Real Estate Operator",
            "type":"Services"
        },
        {
            "category":"Real Estate",
            "subcategory":"Real Estate Agent",
            "type":"Services"
        }
    ],
    "sg:phone":"+44 20 7228 8686",
    "sg:postcode":"SW11 1JW",
    "sg:province":"Greater London",
    "sg:tags":[
        "letting"
    ],
    "wof:name":"Barnard Marcus",
    "wof:placetype":"venue"
},
  "geometry": {"coordinates":[-0.1626150012,51.4643363953],"type":"Point"}
}