{
  "type": "Feature",
  "properties": {
    "iso:country":"GB",
    "sg:address":"Ipswich Road",
    "sg:city":"Cardiff",
    "sg:classifiers":[
        {
            "category":"Retail",
            "subcategory":"Auto Rental",
            "type":"Services"
        }
    ],
    "sg:phone":"+44 29 2047 2800",
    "sg:postcode":"CF23 9AQ",
    "sg:province":"Cardiff",
    "sg:tags":[
        "car",
        "vehicle"
    ],
    "wof:name":"Enterprise Rent-A-Car UK Ltd",
    "wof:placetype":"venue"
},
  "geometry": {"coordinates":[-3.1448740959,51.5007553101],"type":"Point"}
}