{
  "type": "Feature",
  "properties": {
    "iso:country":"GB",
    "sg:address":"1 Angotts Mead",
    "sg:city":"Stevenage",
    "sg:classifiers":[
        {
            "category":"Building & Trades",
            "subcategory":"Construction",
            "type":"Services"
        }
    ],
    "sg:phone":"+44 1438 354299",
    "sg:postcode":"SG1 2NJ",
    "sg:province":"Hertfordshire",
    "sg:tags":[
        "builder"
    ],
    "wof:name":"Stevens & Barrett (Developments) Ltd.",
    "wof:placetype":"venue"
},
  "geometry": {"coordinates":[-0.216091,51.907333],"type":"Point"}
}