{
  "type": "Feature",
  "properties": {
    "iso:country":"GB",
    "sg:address":"Min-y-clwyd Lon Parcwr",
    "sg:city":"Ruthin",
    "sg:classifiers":[
        {
            "category":"Utilities",
            "subcategory":"Refuse",
            "type":"Services"
        }
    ],
    "sg:phone":"+44 1824 703653",
    "sg:postcode":"LL15 1NA",
    "sg:province":"Denbighshire",
    "sg:tags":[
        "skip",
        "hire"
    ],
    "wof:name":"Brian Williams",
    "wof:placetype":"venue"
},
  "geometry": {"coordinates":[-3.304522,53.114017],"type":"Point"}
}