{
  "type": "Feature",
  "properties": {
    "addr:full":"Pound Lane, North Benfleet Wickford Essex SS12 9JS",
    "addr:postcode":"ss12 9js",
    "addr:street":"Pound Lane North",
    "iso:country":"GB",
    "sg:address":"Pound Lane, North Benfleet",
    "sg:city":"Wickford",
    "sg:classifiers":[
        {
            "category":"Manufacturing",
            "subcategory":"Building Materials",
            "type":"Manufacturing & Wholesale Goods"
        }
    ],
    "sg:phone":"+44 1268 725990",
    "sg:postcode":"SS12 9JS",
    "sg:province":"Essex",
    "sg:tags":[
        "stonemason"
    ],
    "wof:name":"M J Memorials",
    "wof:placetype":"venue"
},
  "geometry": {"coordinates":[0.5363010168,51.5886039734],"type":"Point"}
}