{
  "type": "Feature",
  "properties": {
    "iso:country":"GB",
    "sg:address":"Chapel House, Turners Avenue",
    "sg:city":"Tenterden",
    "sg:classifiers":[
        {
            "category":"Social Services",
            "subcategory":"Adult Care",
            "type":"Services"
        }
    ],
    "sg:postcode":"TN30 6QB",
    "sg:province":"Kent",
    "sg:tags":[
        "domestic",
        "cleaning"
    ],
    "wof:name":"Scrubbers",
    "wof:placetype":"venue"
},
  "geometry": {"coordinates":[0.6910240054,51.0735702515],"type":"Point"}
}