{
  "type": "Feature",
  "properties": {
    "iso:country":"GB",
    "sg:address":"116 Putney Bridge Road",
    "sg:city":"London",
    "sg:classifiers":[
        {
            "category":"Shopping",
            "subcategory":"Stationery & Office Supplies",
            "type":"Retail Goods"
        }
    ],
    "sg:phone":"+44 20 8870 2350",
    "sg:postcode":"SW15 2NQ",
    "sg:province":"Greater London",
    "sg:tags":[
        "equipment"
    ],
    "wof:name":"Working With Momentum Ltd.",
    "wof:placetype":"venue"
},
  "geometry": {"coordinates":[-0.2082010061,51.4625892639],"type":"Point"}
}