{
  "type": "Feature",
  "properties": {
    "addr:full":"Postmill Clo Croydon Surrey CR0 5DY",
    "addr:postcode":"cr0 5dy",
    "iso:country":"GB",
    "sg:address":"Postmill Clo",
    "sg:city":"Croydon",
    "sg:classifiers":[
        {
            "category":"Personal",
            "subcategory":"Nail Salon",
            "type":"Services"
        }
    ],
    "sg:phone":"+44 20 8655 3734",
    "sg:postcode":"CR0 5DY",
    "sg:province":"Surrey",
    "sg:tags":[
        "technician"
    ],
    "wof:name":"Lyn's Nail Extension Services",
    "wof:placetype":"venue"
},
  "geometry": {"coordinates":[-0.0542990007,51.3689193726],"type":"Point"}
}