{
  "type": "Feature",
  "properties": {
    "iso:country":"GB",
    "sg:address":"Unit 117, Stirling Enterprise Park",
    "sg:city":"Stirling",
    "sg:classifiers":[
        {
            "category":"Professional",
            "subcategory":"Printing & Photocopies",
            "type":"Services"
        }
    ],
    "sg:phone":"+44 1786 446700",
    "sg:postcode":"FK7 7RP",
    "sg:province":"Falkirk",
    "sg:tags":[
        "duplicating",
        "copying"
    ],
    "wof:name":"Alamo Business Consultants Ltd.",
    "wof:placetype":"venue"
},
  "geometry": {"coordinates":[-3.9290599823,56.1164207458],"type":"Point"}
}