{
  "type": "Feature",
  "properties": {
    "addr:full":"Holly Bush Vale London Greater London NW3 6TX",
    "addr:postcode":"nw3 6tx",
    "addr:street":"Holly Bush Vale",
    "iso:country":"GB",
    "sg:address":"Holly Bush Vale",
    "sg:city":"London",
    "sg:classifiers":[
        {
            "category":"Education",
            "subcategory":"School",
            "type":"Public Place"
        }
    ],
    "sg:phone":"+44 20 7435 4135",
    "sg:postcode":"NW3 6TX",
    "sg:province":"Greater London",
    "sg:tags":[
        "local",
        "authority"
    ],
    "wof:name":"Hampstead Parochial School",
    "wof:placetype":"venue"
},
  "geometry": {"coordinates":[-0.179550007,51.5563011169],"type":"Point"}
}