{
  "type": "Feature",
  "properties": {
    "addr:full":"Palace Pound, St Marys Street Ross-on-wye Gloucestershire HR9 5HY",
    "addr:postcode":"hr9 5hy",
    "addr:street":"Pound St Marys Street",
    "iso:country":"GB",
    "sg:address":"Palace Pound, St Marys Street",
    "sg:city":"Ross-on-wye",
    "sg:classifiers":[
        {
            "category":"Arts & Performance",
            "subcategory":"Theater",
            "type":"Entertainment"
        }
    ],
    "sg:phone":"+44 1989 564570",
    "sg:postcode":"HR9 5HY",
    "sg:province":"Gloucestershire",
    "sg:tags":[
        "hall",
        "theatre",
        "concert"
    ],
    "wof:name":"The Phoenix Theatre",
    "wof:placetype":"venue"
},
  "geometry": {"coordinates":[-2.585676,51.914185],"type":"Point"}
}