{
  "type": "Feature",
  "properties": {
    "addr:full":"Rosemount Farm, Parkhead Road Blairgowrie Perth and Kinross PH10 6LP",
    "addr:postcode":"ph10 6lp",
    "addr:street":"Parkhead Road",
    "iso:country":"GB",
    "sg:address":"Rosemount Farm, Parkhead Road",
    "sg:city":"Blairgowrie",
    "sg:classifiers":[
        {
            "category":"Farming",
            "subcategory":"Farm",
            "type":"Manufacturing & Wholesale Goods"
        }
    ],
    "sg:phone":"+44 1250 873578",
    "sg:postcode":"PH10 6LP",
    "sg:province":"Perth and Kinross",
    "sg:tags":[
        "mixed",
        "crop"
    ],
    "wof:name":"C W S Agriculture",
    "wof:placetype":"venue"
},
  "geometry": {"coordinates":[-3.3369290829,56.5914306641],"type":"Point"}
}