{
  "type": "Feature",
  "properties": {
    "addr:full":"11a Bilbrook Road, Bilbrook, Codsall Wolverhampton Shropshire WV8 1EU",
    "addr:housenumber":"11a",
    "addr:postcode":"wv8 1eu",
    "addr:street":"Bilbrook Road",
    "iso:country":"GB",
    "sg:address":"11a Bilbrook Road, Bilbrook, Codsall",
    "sg:city":"Wolverhampton",
    "sg:classifiers":[
        {
            "category":"Wholesale",
            "subcategory":"Vending Machines",
            "type":"Manufacturing & Wholesale Goods"
        }
    ],
    "sg:postcode":"WV8 1EU",
    "sg:province":"Shropshire",
    "sg:tags":[
        "sale"
    ],
    "wof:name":"The Vending Co.",
    "wof:placetype":"venue"
},
  "geometry": {"coordinates":[-2.180191,52.627403],"type":"Point"}
}