{
  "type": "Feature",
  "properties": {
    "addr:full":"2 High St Tonbridge Kent TN9 1EL",
    "addr:housenumber":"2",
    "addr:postcode":"tn9 1el",
    "addr:street":"High St",
    "iso:country":"GB",
    "sg:address":"2 High St",
    "sg:city":"Tonbridge",
    "sg:classifiers":[
        {
            "category":"Real Estate",
            "subcategory":"Architect",
            "type":"Services"
        }
    ],
    "sg:phone":"+44 1732 362727",
    "sg:postcode":"TN9 1EL",
    "sg:province":"Kent",
    "wof:name":"Barton Willmore Partnership The",
    "wof:placetype":"venue"
},
  "geometry": {"coordinates":[0.2720339894,51.1924057007],"type":"Point"}
}