{
  "type": "Feature",
  "properties": {
    "addr:full":"17 Valley Close, Mossley Ashton-under-lyne Greater Manchester OL5 0NH",
    "addr:housenumber":"17",
    "addr:postcode":"ol5 0nh",
    "addr:street":"Valley Close",
    "iso:country":"GB",
    "sg:address":"17 Valley Close, Mossley",
    "sg:city":"Ashton-under-lyne",
    "sg:classifiers":[
        {
            "category":"Bus Charters",
            "type":"Transportation"
        },
        {
            "category":"Bus Stop",
            "subcategory":"None",
            "type":"Transportation"
        }
    ],
    "sg:phone":"+44 1457 832845",
    "sg:postcode":"OL5 0NH",
    "sg:province":"Greater Manchester",
    "sg:tags":[
        "mini",
        "hire",
        "coach"
    ],
    "wof:name":"Lendor Taxis & Luxury Mini Coach Travel",
    "wof:placetype":"venue"
},
  "geometry": {"coordinates":[-2.0507860184,53.5217819214],"type":"Point"}
}