{
  "type": "Feature",
  "properties": {
    "addr:full":"Wentworth House, 2 Wentworth Street Wakefield West Yorkshire WF1 2RX",
    "addr:housenumber":"2",
    "addr:postcode":"wf1 2rx",
    "addr:street":"Wentworth Street",
    "iso:country":"GB",
    "sg:address":"Wentworth House, 2 Wentworth Street",
    "sg:city":"Wakefield",
    "sg:classifiers":[
        {
            "category":"Professional",
            "subcategory":"Engineering",
            "type":"Services"
        }
    ],
    "sg:phone":"+44 1924 383836",
    "sg:postcode":"WF1 2RX",
    "sg:province":"West Yorkshire",
    "sg:tags":[
        "structural",
        "engineer"
    ],
    "sg:website":"http://www.bjbconsultancy.co.uk",
    "wof:name":"B J B Consultancy Ltd",
    "wof:placetype":"venue"
},
  "geometry": {"coordinates":[-1.5030189753,53.6990089417],"type":"Point"}
}