{
  "type": "Feature",
  "properties": {
    "iso:country":"GB",
    "sg:address":"35 Yoden Way",
    "sg:city":"Peterlee",
    "sg:classifiers":[
        {
            "category":"Banks & Credit Unions",
            "subcategory":"Bank",
            "type":"Services"
        }
    ],
    "sg:phone":"+44 845 740 4404",
    "sg:postcode":"SR8 1AT",
    "sg:province":"Durham",
    "wof:name":"H S B C Bank",
    "wof:placetype":"venue"
},
  "geometry": {"coordinates":[-1.3308589458,54.7586898804],"type":"Point"}
}