{
  "type": "Feature",
  "properties": {
    "iso:country":"GB",
    "sg:address":"Nant Ucha, Y Nentydd",
    "sg:city":"Abergele",
    "sg:classifiers":[
        {
            "category":"Farming",
            "subcategory":"Farm",
            "type":"Manufacturing & Wholesale Goods"
        }
    ],
    "sg:postcode":"LL22 8EF",
    "sg:province":"Conwy",
    "sg:tags":[
        "mixed",
        "crop"
    ],
    "wof:name":"M Edwards",
    "wof:placetype":"venue"
},
  "geometry": {"coordinates":[-3.581144,53.284355],"type":"Point"}
}