{
  "type": "Feature",
  "properties": {
    "addr:full":"Edgeworth House, 121 High St Arlesey Bedfordshire SG15 6SX",
    "addr:housenumber":"121",
    "addr:postcode":"sg15 6sx",
    "addr:street":"High St",
    "iso:country":"GB",
    "sg:address":"Edgeworth House, 121 High St",
    "sg:city":"Arlesey",
    "sg:classifiers":[
        {
            "category":"Professional",
            "subcategory":"Management & Consulting",
            "type":"Services"
        }
    ],
    "sg:postcode":"SG15 6SX",
    "sg:province":"Bedfordshire",
    "sg:tags":[
        "environmental",
        "consultant"
    ],
    "wof:name":"Hamilton & Garrod Ltd",
    "wof:placetype":"venue"
},
  "geometry": {"coordinates":[-0.2624480128,52.0105705261],"type":"Point"}
}