{
  "type": "Feature",
  "properties": {
    "addr:full":"West Main Street Darvel East Ayrshire KA17 0AE",
    "addr:postcode":"ka17 0ae",
    "addr:street":"West Main Street",
    "iso:country":"GB",
    "sg:address":"West Main Street",
    "sg:city":"Darvel",
    "sg:classifiers":[
        {
            "category":"Government",
            "subcategory":"City Hall",
            "type":"Public Place"
        },
        {
            "category":"Government",
            "subcategory":"Office",
            "type":"Public Place"
        }
    ],
    "sg:phone":"+44 1560 322437",
    "sg:postcode":"KA17 0AE",
    "sg:province":"East Ayrshire",
    "sg:tags":[
        "local"
    ],
    "wof:name":"Darvel Town Hall",
    "wof:placetype":"venue"
},
  "geometry": {"coordinates":[-4.2827939987,55.6096534729],"type":"Point"}
}