{
  "type": "Feature",
  "properties": {
    "addr:full":"67-72 Titchfield Street Kilmarnock East Ayrshire KA1 1QS",
    "addr:housenumber":"67-72",
    "addr:postcode":"ka1 1qs",
    "addr:street":"Titchfield Street",
    "iso:country":"GB",
    "sg:address":"67-72 Titchfield Street",
    "sg:city":"Kilmarnock",
    "sg:classifiers":[
        {
            "category":"Shopping",
            "subcategory":"Hobbies, Toys, & Games",
            "type":"Retail Goods"
        }
    ],
    "sg:phone":"+44 1563 570473",
    "sg:postcode":"KA1 1QS",
    "sg:province":"East Ayrshire",
    "sg:tags":[
        "computer"
    ],
    "wof:name":"Games Centre",
    "wof:placetype":"venue"
},
  "geometry": {"coordinates":[-4.497461,55.605335],"type":"Point"}
}