{
  "type": "Feature",
  "properties": {
    "iso:country":"GB",
    "sg:address":"82 Commercial Street",
    "sg:city":"Edinburgh",
    "sg:classifiers":[
        {
            "category":"Arts & Performance",
            "subcategory":"Comedy Club",
            "type":"Entertainment"
        }
    ],
    "sg:postcode":"EH6 6LX",
    "sg:province":"City of Edinburgh",
    "sg:tags":[
        "japanese"
    ],
    "wof:name":"Daruma-Ya",
    "wof:placetype":"venue"
},
  "geometry": {"coordinates":[-3.175147,55.977165],"type":"Point"}
}