{
  "type": "Feature",
  "properties": {
    "addr:full":"Howden Road Tiverton Devon EX16 5HL",
    "addr:postcode":"ex16 5hl",
    "addr:street":"Howden Road",
    "iso:country":"GB",
    "sg:address":"Howden Road",
    "sg:city":"Tiverton",
    "sg:classifiers":[
        {
            "category":"Retail",
            "subcategory":"Auto Repair",
            "type":"Services"
        }
    ],
    "sg:phone":"+44 1884 255128",
    "sg:postcode":"EX16 5HL",
    "sg:province":"Devon",
    "sg:tags":[
        "modification",
        "garage"
    ],
    "wof:name":"Pitstop",
    "wof:placetype":"venue"
},
  "geometry": {"coordinates":[-3.491416,50.899155],"type":"Point"}
}