{
  "type": "Feature",
  "properties": {
    "addr:full":"275 Shirley Road Southampton Hampshire SO15 3HS",
    "addr:housenumber":"275",
    "addr:postcode":"so15 3hs",
    "addr:street":"Shirley Road",
    "iso:country":"GB",
    "sg:address":"275 Shirley Road",
    "sg:city":"Southampton",
    "sg:classifiers":[
        {
            "category":"Retail",
            "subcategory":"Auto Repair",
            "type":"Services"
        }
    ],
    "sg:phone":"+44 23 8077 1777",
    "sg:postcode":"SO15 3HS",
    "sg:province":"Hampshire",
    "sg:tags":[
        "modification",
        "garage"
    ],
    "wof:name":"Nandrews Garage",
    "wof:placetype":"venue"
},
  "geometry": {"coordinates":[-1.42578,50.916443],"type":"Point"}
}