{
  "type": "Feature",
  "properties": {
    "iso:country":"GB",
    "sg:address":"27 Doncaster Road",
    "sg:city":"Mexborough",
    "sg:classifiers":[
        {
            "category":"Home & Garden",
            "subcategory":"Home Furnishings",
            "type":"Retail Goods"
        }
    ],
    "sg:postcode":"S64 0JS",
    "sg:province":"South Yorkshire",
    "sg:tags":[
        "wall",
        "wallpaper",
        "covering"
    ],
    "wof:name":"Hawkridge Wallpaper Co",
    "wof:placetype":"venue"
},
  "geometry": {"coordinates":[-1.278064,53.493439],"type":"Point"}
}