{
  "type": "Feature",
  "properties": {
    "addr:full":"Penhale Vean Helston Cornwall TR13 9NU",
    "addr:postcode":"tr13 9nu",
    "iso:country":"GB",
    "sg:address":"Penhale Vean",
    "sg:city":"Helston",
    "sg:classifiers":[
        {
            "category":"Building & Trades",
            "subcategory":"Construction",
            "type":"Services"
        }
    ],
    "sg:phone":"+44 1736 762822",
    "sg:postcode":"TR13 9NU",
    "sg:province":"Cornwall",
    "sg:tags":[
        "builder"
    ],
    "wof:name":"D P Johnson",
    "wof:placetype":"venue"
},
  "geometry": {"coordinates":[-5.3598341942,50.1074295044],"type":"Point"}
}