{
  "type": "Feature",
  "properties": {
    "addr:full":"30 Heathcote Close March Cambridgeshire PE15 9BD",
    "addr:housenumber":"30",
    "addr:postcode":"pe15 9bd",
    "addr:street":"Heathcote Close",
    "iso:country":"GB",
    "sg:address":"30 Heathcote Close",
    "sg:city":"March",
    "sg:classifiers":[
        {
            "category":"Building & Trades",
            "subcategory":"Construction",
            "type":"Services"
        }
    ],
    "sg:phone":"+44 1354 653897",
    "sg:postcode":"PE15 9BD",
    "sg:province":"Cambridgeshire",
    "sg:tags":[
        "dry",
        "plastering",
        "plasterers",
        "lining",
        "related",
        "installers",
        "insulation",
        "screeders"
    ],
    "wof:name":"M Lavender",
    "wof:placetype":"venue"
},
  "geometry": {"coordinates":[0.1044090018,52.5510292053],"type":"Point"}
}