{
  "type": "Feature",
  "properties": {
    "iso:country":"GB",
    "sg:address":"Chapel Ash",
    "sg:city":"Wolverhampton",
    "sg:classifiers":[
        {
            "category":"Autos & Motor Vehicles",
            "subcategory":"Automobile Sales",
            "type":"Retail Goods"
        }
    ],
    "sg:phone":"+44 1902 311611",
    "sg:postcode":"WV3 0TX",
    "sg:province":"Staffordshire",
    "sg:tags":[
        "car"
    ],
    "wof:name":"Trimoco Plc",
    "wof:placetype":"venue"
},
  "geometry": {"coordinates":[-2.140059,52.585426],"type":"Point"}
}