{
  "type": "Feature",
  "properties": {
    "addr:full":"74 London Rd Croydon Surrey CR0 2TB",
    "addr:housenumber":"74",
    "addr:postcode":"cr0 2tb",
    "addr:street":"London Rd",
    "iso:country":"GB",
    "sg:address":"74 London Rd",
    "sg:city":"Croydon",
    "sg:classifiers":[
        {
            "category":"Restaurant",
            "type":"Food & Drink"
        }
    ],
    "sg:phone":"+44 20 8686 0602",
    "sg:postcode":"CR0 2TB",
    "sg:province":"Surrey",
    "sg:tags":[
        "indian"
    ],
    "wof:name":"Changere Restaurant",
    "wof:placetype":"venue"
},
  "geometry": {"coordinates":[-0.1047279984,51.3805236816],"type":"Point"}
}