{
  "type": "Feature",
  "properties": {
    "addr:full":"Coombe Hill Farm, Coombe St Austell Cornwall PL26 7LW",
    "addr:postcode":"pl26 7lw",
    "addr:street":"Coombe",
    "iso:country":"GB",
    "sg:address":"Coombe Hill Farm, Coombe",
    "sg:city":"St Austell",
    "sg:classifiers":[
        {
            "category":"Building & Trades",
            "subcategory":"Construction",
            "type":"Services"
        }
    ],
    "sg:phone":"+44 1726 884107",
    "sg:postcode":"PL26 7LW",
    "sg:province":"Cornwall",
    "sg:tags":[
        "builder"
    ],
    "wof:name":"M F Bland Ltd.",
    "wof:placetype":"venue"
},
  "geometry": {"coordinates":[-4.8816690445,50.3261299133],"type":"Point"}
}