{
  "type": "Feature",
  "properties": {
    "iso:country":"GB",
    "sg:address":"Mamore Farm, Rahane",
    "sg:city":"Helensburgh",
    "sg:classifiers":[
        {
            "category":"Food & Beverages",
            "subcategory":"Meat & Fish",
            "type":"Retail Goods"
        }
    ],
    "sg:phone":"+44 1436 831320",
    "sg:postcode":"G84 0QW",
    "sg:province":"Argyll and Bute",
    "sg:tags":[
        "butcher"
    ],
    "wof:name":"R Macintyre",
    "wof:placetype":"venue"
},
  "geometry": {"coordinates":[-4.732149,56.006584],"type":"Point"}
}