{
  "type": "Feature",
  "properties": {
    "addr:full":"969 Leeds Road Bradford West Yorkshire BD3 8JB",
    "addr:housenumber":"969",
    "addr:postcode":"bd3 8jb",
    "addr:street":"Leeds Road",
    "iso:country":"GB",
    "sg:address":"969 Leeds Road",
    "sg:city":"Bradford",
    "sg:classifiers":[
        {
            "category":"Shopping",
            "subcategory":"Comic Books",
            "type":"Retail Goods"
        }
    ],
    "sg:phone":"+44 1274 663131",
    "sg:postcode":"BD3 8JB",
    "sg:province":"West Yorkshire",
    "sg:tags":[
        "jeweller"
    ],
    "wof:name":"Sona",
    "wof:placetype":"venue"
},
  "geometry": {"coordinates":[-1.7116969824,53.7976608276],"type":"Point"}
}