{
  "type": "Feature",
  "properties": {
    "addr:full":"Middle Street, Blackhall Colliery Hartlepool Durham TS27 4NA",
    "addr:postcode":"ts27 4na",
    "addr:street":"Middle Street",
    "iso:country":"GB",
    "sg:address":"Middle Street, Blackhall Colliery",
    "sg:city":"Hartlepool",
    "sg:classifiers":[
        {
            "category":"Education",
            "subcategory":"School",
            "type":"Public Place"
        },
        {
            "category":"Government",
            "subcategory":"Office",
            "type":"Public Place"
        }
    ],
    "sg:phone":"+44 191 586 4049",
    "sg:postcode":"TS27 4NA",
    "sg:province":"Durham",
    "sg:tags":[
        "local",
        "authority"
    ],
    "wof:name":"Blackhall Primary School",
    "wof:placetype":"venue"
},
  "geometry": {"coordinates":[-1.2938640118,54.7500915527],"type":"Point"}
}