{
  "type": "Feature",
  "properties": {
    "addr:full":"42 The Homend Ledbury Gloucestershire HR8 1BT",
    "addr:housenumber":"42",
    "addr:postcode":"hr8 1bt",
    "addr:street":"The Homend",
    "iso:country":"GB",
    "sg:address":"42 The Homend",
    "sg:city":"Ledbury",
    "sg:classifiers":[
        {
            "category":"Food & Beverages",
            "subcategory":"Bakery",
            "type":"Retail Goods"
        }
    ],
    "sg:phone":"+44 1531 634477",
    "sg:postcode":"HR8 1BT",
    "sg:province":"Gloucestershire",
    "sg:tags":[
        "baker"
    ],
    "wof:name":"Abbeys Bakery",
    "wof:placetype":"venue"
},
  "geometry": {"coordinates":[-2.4243071079,52.0385551453],"type":"Point"}
}