{
  "type": "Feature",
  "properties": {
    "addr:full":"Unit 6g Farm Lane Trading Estate, Farm Lane London Greater London SW6 1QJ",
    "addr:housenumber":"6g",
    "addr:postcode":"sw6 1qj",
    "addr:street":"Farm Lane Trading Estate Farm Lane",
    "iso:country":"GB",
    "sg:address":"Unit 6g Farm Lane Trading Estate, Farm Lane",
    "sg:city":"London",
    "sg:classifiers":[
        {
            "category":"Retail",
            "subcategory":"Laundry & Dry Cleaning",
            "type":"Services"
        }
    ],
    "sg:phone":"+44 20 7381 4770",
    "sg:postcode":"SW6 1QJ",
    "sg:province":"Greater London",
    "sg:tags":[
        "alteration"
    ],
    "wof:name":"Macgill of Kensington",
    "wof:placetype":"venue"
},
  "geometry": {"coordinates":[-0.1975899935,51.481590271],"type":"Point"}
}