{
  "type": "Feature",
  "properties": {
    "iso:country":"GB",
    "sg:address":"Howarth House Trent Valley Road",
    "sg:city":"Lichfield",
    "sg:classifiers":[
        {
            "category":"Manufacturing",
            "subcategory":"Electronics",
            "type":"Manufacturing & Wholesale Goods"
        }
    ],
    "sg:phone":"+44 1543 417471",
    "sg:postcode":"WS13 6EU",
    "sg:province":"Staffordshire",
    "sg:tags":[
        "control",
        "component",
        "-",
        "electronic"
    ],
    "wof:name":"J H Components Ltd.",
    "wof:placetype":"venue"
},
  "geometry": {"coordinates":[-1.8061840534,52.6870613098],"type":"Point"}
}