{
  "type": "Feature",
  "properties": {
    "iso:country":"GB",
    "sg:address":"3 Pippin Avenue",
    "sg:city":"Halesowen",
    "sg:classifiers":[
        {
            "category":"Building & Trades",
            "subcategory":"Plumbing",
            "type":"Services"
        }
    ],
    "sg:phone":"+44 1384 839590",
    "sg:postcode":"B63 2PW",
    "sg:province":"West Midlands",
    "sg:tags":[
        "heating"
    ],
    "wof:name":"Household Plumbing & Electrical Services",
    "wof:placetype":"venue"
},
  "geometry": {"coordinates":[-2.095026,52.464054],"type":"Point"}
}