{
  "type": "Feature",
  "properties": {
    "iso:country":"GB",
    "sg:address":"36 Arlington Square",
    "sg:city":"Margate",
    "sg:classifiers":[
        {
            "category":"Restaurant",
            "type":"Food & Drink"
        }
    ],
    "sg:phone":"+44 1843 294186",
    "sg:postcode":"CT9 1XN",
    "sg:province":"Kent",
    "wof:name":"THE ARLINGTON GRILL",
    "wof:placetype":"venue"
},
  "geometry": {"coordinates":[1.3746349812,51.3866615295],"type":"Point"}
}