{
  "type": "Feature",
  "properties": {
    "iso:country":"GB",
    "sg:address":"312 High Rd",
    "sg:city":"Seven Sisters",
    "sg:classifiers":[
        {
            "category":"Professional",
            "subcategory":"Management & Consulting",
            "type":"Services"
        }
    ],
    "sg:phone":"+44 20 8808 1836",
    "sg:postcode":"N15 4BN",
    "sg:province":"Greater London",
    "sg:tags":[
        "consultant"
    ],
    "wof:name":"Econergy",
    "wof:placetype":"venue"
},
  "geometry": {"coordinates":[-0.07039,51.588451],"type":"Point"}
}