{
  "type": "Feature",
  "properties": {
    "iso:country":"GB",
    "sg:address":"33 High St",
    "sg:city":"Staines",
    "sg:classifiers":[
        {
            "category":"Personal",
            "subcategory":"Beauty Salon",
            "type":"Services"
        }
    ],
    "sg:phone":"+44 1784 252464",
    "sg:postcode":"TW19 7LJ",
    "sg:province":"Berkshire",
    "sg:tags":[
        "unisex",
        "hairdresser"
    ],
    "wof:name":"Arlyn Hair Fashions",
    "wof:placetype":"venue"
},
  "geometry": {"coordinates":[-0.478957,51.457355],"type":"Point"}
}