{
  "type": "Feature",
  "properties": {
    "addr:full":"690 Mosspark Drive Glasgow Glasgow City G52 3AY",
    "addr:housenumber":"690",
    "addr:postcode":"g52 3ay",
    "addr:street":"Mosspark Drive",
    "iso:country":"GB",
    "sg:address":"690 Mosspark Drive",
    "sg:city":"Glasgow",
    "sg:classifiers":[
        {
            "category":"Education",
            "subcategory":"University",
            "type":"Public Place"
        }
    ],
    "sg:phone":"+44 141 272 3333",
    "sg:postcode":"G52 3AY",
    "sg:province":"Glasgow City",
    "sg:tags":[
        "school",
        "college",
        "higher"
    ],
    "wof:name":"Cardonald College",
    "wof:placetype":"venue"
},
  "geometry": {"coordinates":[-4.3373661041,55.8401908875],"type":"Point"}
}