{
  "type": "Feature",
  "properties": {
    "iso:country":"GB",
    "sg:address":"141 Church Street, Wolverton",
    "sg:city":"Milton Keynes",
    "sg:classifiers":[
        {
            "category":"Building & Trades",
            "subcategory":"Construction",
            "type":"Services"
        }
    ],
    "sg:postcode":"MK12 5LA",
    "sg:province":"Buckinghamshire",
    "sg:tags":[
        "roofing"
    ],
    "wof:name":"Absolute Flat Roofing",
    "wof:placetype":"venue"
},
  "geometry": {"coordinates":[-0.8149420023,52.0616798401],"type":"Point"}
}