{
  "type": "Feature",
  "properties": {
    "addr:full":"Park Street, Lydd Romney Marsh Kent TN29 9AX",
    "addr:postcode":"tn29 9ax",
    "addr:street":"Park Street",
    "iso:country":"GB",
    "sg:address":"Park Street, Lydd",
    "sg:city":"Romney Marsh",
    "sg:classifiers":[
        {
            "category":"Bars & Pubs",
            "type":"Food & Drink"
        }
    ],
    "sg:phone":"+44 1797 320241",
    "sg:postcode":"TN29 9AX",
    "sg:province":"Kent",
    "sg:tags":[
        "pubs",
        "inn"
    ],
    "wof:name":"The Royal Oak",
    "wof:placetype":"venue"
},
  "geometry": {"coordinates":[0.9034900069,50.9494934082],"type":"Point"}
}