{
  "type": "Feature",
  "properties": {
    "iso:country":"GB",
    "sg:address":"Accounts Northway House, 1379 High Road",
    "sg:city":"London",
    "sg:classifiers":[
        {
            "category":"Professional",
            "subcategory":"Business Services",
            "type":"Services"
        }
    ],
    "sg:postcode":"N20 9LP",
    "sg:province":"Greater London",
    "sg:tags":[
        "management",
        "pub"
    ],
    "wof:name":"Regent Inns Plc",
    "wof:placetype":"venue"
},
  "geometry": {"coordinates":[-0.1761189997,51.6336746216],"type":"Point"}
}