{
  "type": "Feature",
  "properties": {
    "addr:full":"108 Leeds Road, Bramhope Leeds West Yorkshire LS16 9AN",
    "addr:housenumber":"108",
    "addr:postcode":"ls16 9an",
    "addr:street":"Leeds Road",
    "iso:country":"GB",
    "sg:address":"108 Leeds Road, Bramhope",
    "sg:city":"Leeds",
    "sg:classifiers":[
        {
            "category":"Health Services",
            "subcategory":"Optometrist",
            "type":"Services"
        }
    ],
    "sg:postcode":"LS16 9AN",
    "sg:province":"West Yorkshire",
    "sg:tags":[
        "optician"
    ],
    "wof:name":"Maxwell Vites",
    "wof:placetype":"venue"
},
  "geometry": {"coordinates":[-1.608749,53.881569],"type":"Point"}
}