{
  "type": "Feature",
  "properties": {
    "iso:country":"GB",
    "sg:address":"Caledonia St",
    "sg:city":"Bilston",
    "sg:classifiers":[
        {
            "category":"Home & Garden",
            "subcategory":"Furniture",
            "type":"Retail Goods"
        }
    ],
    "sg:postcode":"WV14 6AE",
    "sg:province":"West Midlands",
    "wof:name":"Hartill,Denis,",
    "wof:placetype":"venue"
},
  "geometry": {"coordinates":[-2.074867,52.567608],"type":"Point"}
}