{
  "type": "Feature",
  "properties": {
    "addr:full":"113 High Street Thornton Heath Surrey CR7 8RZ",
    "addr:housenumber":"113",
    "addr:postcode":"cr7 8rz",
    "addr:street":"High Street",
    "iso:country":"GB",
    "sg:address":"113 High Street",
    "sg:city":"Thornton Heath",
    "sg:classifiers":[
        {
            "category":"Shopping",
            "subcategory":"Clothing, Apparel, & Fashions",
            "type":"Retail Goods"
        },
        {
            "category":"Shopping",
            "subcategory":"Baby Store",
            "type":"Retail Goods"
        }
    ],
    "sg:phone":"+44 20 8683 2773",
    "sg:postcode":"CR7 8RZ",
    "sg:province":"Surrey",
    "sg:tags":[
        "child",
        "childrens",
        "babywear"
    ],
    "wof:name":"Bubble Gum Childrenswear",
    "wof:placetype":"venue"
},
  "geometry": {"coordinates":[-0.09797,51.39883],"type":"Point"}
}