{
  "type": "Feature",
  "properties": {
    "addr:full":"25 Stanton Walk, Woodloes Pk Warwick Warwickshire CV34 5UY",
    "addr:housenumber":"25",
    "addr:postcode":"cv34 5uy",
    "addr:street":"Stanton Walk Woodloes Pk",
    "iso:country":"GB",
    "sg:address":"25 Stanton Walk, Woodloes Pk",
    "sg:city":"Warwick",
    "sg:classifiers":[
        {
            "category":"Farming",
            "subcategory":"Livestock Farm",
            "type":"Manufacturing & Wholesale Goods"
        }
    ],
    "sg:postcode":"CV34 5UY",
    "sg:province":"Warwickshire",
    "sg:tags":[
        "stud"
    ],
    "wof:name":"Collins,Patrick John,",
    "wof:placetype":"venue"
},
  "geometry": {"coordinates":[-1.5910340548,52.28175354],"type":"Point"}
}