{
  "type": "Feature",
  "properties": {
    "addr:full":"27 St Marys St, Eynesbury Huntingdon Bedfordshire PE19 2TA",
    "addr:housenumber":"27",
    "addr:postcode":"pe19 2ta",
    "addr:street":"St Marys St",
    "iso:country":"GB",
    "sg:address":"27 St Marys St, Eynesbury",
    "sg:city":"Huntingdon",
    "sg:classifiers":[
        {
            "category":"Fast Food",
            "type":"Food & Drink"
        }
    ],
    "sg:phone":"+44 1480 474376",
    "sg:postcode":"PE19 2TA",
    "sg:province":"Bedfordshire",
    "sg:tags":[
        "away",
        "take"
    ],
    "wof:name":"Little House",
    "wof:placetype":"venue"
},
  "geometry": {"coordinates":[-0.2648940086,52.2170562744],"type":"Point"}
}