{
  "type": "Feature",
  "properties": {
    "addr:full":"221 Neilston Rd Paisley East Renfrewshire PA2 6PY",
    "addr:housenumber":"221",
    "addr:postcode":"pa2 6py",
    "addr:street":"Neilston Rd",
    "iso:country":"GB",
    "sg:address":"221 Neilston Rd",
    "sg:city":"Paisley",
    "sg:classifiers":[
        {
            "category":"Building & Trades",
            "subcategory":"Construction",
            "type":"Services"
        }
    ],
    "sg:phone":"+44 141 884 3381",
    "sg:postcode":"PA2 6PY",
    "sg:province":"East Renfrewshire",
    "sg:tags":[
        "concrete"
    ],
    "wof:name":"Concrete Renovation Technology Ltd",
    "wof:placetype":"venue"
},
  "geometry": {"coordinates":[-4.421107,55.826775],"type":"Point"}
}