{
  "type": "Feature",
  "properties": {
    "addr:full":"25 Jorose Way, Bretton Peterborough Cambridgeshire PE3 9JR",
    "addr:housenumber":"25",
    "addr:postcode":"pe3 9jr",
    "addr:street":"Jorose Way",
    "iso:country":"GB",
    "sg:address":"25 Jorose Way, Bretton",
    "sg:city":"Peterborough",
    "sg:classifiers":[
        {
            "category":"Retail",
            "subcategory":"Storage",
            "type":"Services"
        }
    ],
    "sg:postcode":"PE3 9JR",
    "sg:province":"Cambridgeshire",
    "sg:tags":[
        "household",
        "removal"
    ],
    "wof:name":"S & S Removals",
    "wof:placetype":"venue"
},
  "geometry": {"coordinates":[-0.28885,52.58009],"type":"Point"}
}