{
  "type": "Feature",
  "properties": {
    "iso:country":"GB",
    "sg:address":"Edgar Street",
    "sg:city":"Hereford",
    "sg:classifiers":[
        {
            "category":"Autos & Motor Vehicles",
            "subcategory":"Fuel & Gas Station",
            "type":"Retail Goods"
        }
    ],
    "sg:postcode":"HR4 9JR",
    "sg:province":"Herefordshire",
    "sg:tags":[
        "hr",
        "petrol"
    ],
    "wof:name":"Edgar Street Filling Station",
    "wof:placetype":"venue"
},
  "geometry": {"coordinates":[-2.7176599503,52.0606689453],"type":"Point"}
}