{
  "type": "Feature",
  "properties": {
    "addr:full":"Harbour Court, Serbert Road Bristol Somerset BS20 7GB",
    "addr:postcode":"bs20 7gb",
    "addr:street":"Serbert Road",
    "iso:country":"GB",
    "sg:address":"Harbour Court, Serbert Road",
    "sg:city":"Bristol",
    "sg:classifiers":[
        {
            "category":"Banks & Credit Unions",
            "subcategory":"Financial Services",
            "type":"Services"
        }
    ],
    "sg:postcode":"BS20 7GB",
    "sg:province":"Somerset",
    "sg:tags":[
        "adviser"
    ],
    "wof:name":"Bristol & London Accident Management Ltd.",
    "wof:placetype":"venue"
},
  "geometry": {"coordinates":[-2.766294,51.486656],"type":"Point"}
}