{
  "type": "Feature",
  "properties": {
    "addr:full":"Playing Fields, Rawstron St, Whitworth Rochdale Lancashire OL12 8BA",
    "addr:postcode":"ol12 8ba",
    "addr:street":"St",
    "iso:country":"GB",
    "sg:address":"Playing Fields, Rawstron St, Whitworth",
    "sg:city":"Rochdale",
    "sg:classifiers":[
        {
            "category":"Arena",
            "subcategory":"Sports Club",
            "type":"Entertainment"
        }
    ],
    "sg:phone":"+44 1706 853030",
    "sg:postcode":"OL12 8BA",
    "sg:province":"Lancashire",
    "wof:name":"Whitworth Valley FC",
    "wof:placetype":"venue"
},
  "geometry": {"coordinates":[-2.1725618839,53.6626434326],"type":"Point"}
}