{
  "type": "Feature",
  "properties": {
    "addr:full":"10-10a High Street Wellington Devon TA21 8RA",
    "addr:housenumber":"10-10a",
    "addr:postcode":"ta21 8ra",
    "addr:street":"High Street",
    "iso:country":"GB",
    "sg:address":"10-10a High Street",
    "sg:city":"Wellington",
    "sg:classifiers":[
        {
            "category":"Shopping",
            "subcategory":"Pets & Pet Supplies",
            "type":"Retail Goods"
        }
    ],
    "sg:phone":"+44 1823 662914",
    "sg:postcode":"TA21 8RA",
    "sg:province":"Devon",
    "sg:tags":[
        "shop"
    ],
    "wof:name":"Wellington Pet & Garden Store",
    "wof:placetype":"venue"
},
  "geometry": {"coordinates":[-3.22696,50.978855],"type":"Point"}
}