{
  "type": "Feature",
  "properties": {
    "addr:full":"1a Avenue Road Herne Bay Kent CT6 8TA",
    "addr:housenumber":"1a",
    "addr:postcode":"ct6 8ta",
    "addr:street":"Avenue Road",
    "iso:country":"GB",
    "sg:address":"1a Avenue Road",
    "sg:city":"Herne Bay",
    "sg:classifiers":[
        {
            "category":"Personal",
            "subcategory":"Beauty Salon",
            "type":"Services"
        }
    ],
    "sg:postcode":"CT6 8TA",
    "sg:province":"Kent",
    "sg:tags":[
        "unisex",
        "hairdresser"
    ],
    "wof:name":"Simon's",
    "wof:placetype":"venue"
},
  "geometry": {"coordinates":[1.1212060452,51.3709907532],"type":"Point"}
}