{
  "type": "Feature",
  "properties": {
    "addr:full":"3 North Park Ave, Roundhay Leeds West Yorkshire LS8 1DN",
    "addr:housenumber":"3",
    "addr:postcode":"ls8 1dn",
    "addr:street":"Park Ave",
    "iso:country":"GB",
    "sg:address":"3 North Park Ave, Roundhay",
    "sg:city":"Leeds",
    "sg:classifiers":[
        {
            "category":"Organizations",
            "subcategory":"Non-profit Organization",
            "type":"Services"
        }
    ],
    "sg:postcode":"LS8 1DN",
    "sg:province":"West Yorkshire",
    "sg:tags":[
        "organisation",
        "animal",
        "welfare"
    ],
    "wof:name":"Leeds Hedgehog Sanctuary",
    "wof:placetype":"venue"
},
  "geometry": {"coordinates":[-1.508946,53.838821],"type":"Point"}
}