{
  "type": "Feature",
  "properties": {
    "iso:country":"GB",
    "sg:address":"21-22 Union Street",
    "sg:city":"Bath",
    "sg:classifiers":[
        {
            "category":"Shopping",
            "subcategory":"Department Store",
            "type":"Retail Goods"
        }
    ],
    "sg:phone":"+44 1225 481215",
    "sg:postcode":"BA1 1RS",
    "sg:province":"Bath and North East Somerset",
    "wof:name":"Farnworths",
    "wof:placetype":"venue"
},
  "geometry": {"coordinates":[-2.3603260517,51.3819007874],"type":"Point"}
}