{
  "type": "Feature",
  "properties": {
    "addr:full":"20 Parkside, Horsforth Leeds West Yorkshire LS18 4DN",
    "addr:housenumber":"20",
    "addr:postcode":"ls18 4dn",
    "addr:street":"Parkside",
    "iso:country":"GB",
    "sg:address":"20 Parkside, Horsforth",
    "sg:city":"Leeds",
    "sg:classifiers":[
        {
            "category":"Insurance",
            "subcategory":"Insurance Agent",
            "type":"Services"
        }
    ],
    "sg:phone":"+44 113 258 2219",
    "sg:postcode":"LS18 4DN",
    "sg:province":"West Yorkshire",
    "wof:name":"Milestone Insurance Consultants",
    "wof:placetype":"venue"
},
  "geometry": {"coordinates":[-1.6146290302,53.8371353149],"type":"Point"}
}