{
  "type": "Feature",
  "properties": {
    "addr:full":"192 Bancroft Road London Greater London E1 4ET",
    "addr:housenumber":"192",
    "addr:postcode":"e1 4et",
    "addr:street":"Bancroft Road",
    "iso:country":"GB",
    "sg:address":"192 Bancroft Road",
    "sg:city":"London",
    "sg:classifiers":[
        {
            "category":"Home & Garden",
            "subcategory":"Building Materials",
            "type":"Retail Goods"
        }
    ],
    "sg:postcode":"E1 4ET",
    "sg:province":"Greater London",
    "sg:tags":[
        "veneer"
    ],
    "wof:name":"Two-Way Veneering Co.",
    "wof:placetype":"venue"
},
  "geometry": {"coordinates":[-0.047369,51.525795],"type":"Point"}
}