{
  "type": "Feature",
  "properties": {
    "addr:full":"Unit 7 Centre Park, Marston Moor Business Park, Tockwith York North Yorkshire YO26 7QF",
    "addr:housenumber":"unit 7",
    "addr:postcode":"yo26 7qf",
    "addr:street":"Centre Park;Moor Business Park",
    "iso:country":"GB",
    "sg:address":"Unit 7 Centre Park, Marston Moor Business Park, Tockwith",
    "sg:city":"York",
    "sg:classifiers":[
        {
            "category":"Home & Garden",
            "subcategory":"Building Materials",
            "type":"Retail Goods"
        },
        {
            "category":"Home & Garden",
            "subcategory":"Kitchen Supply",
            "type":"Retail Goods"
        }
    ],
    "sg:phone":"+44 1423 358882",
    "sg:postcode":"YO26 7QF",
    "sg:province":"North Yorkshire",
    "sg:tags":[
        "installers",
        "ware",
        "planner"
    ],
    "wof:name":"Chantry Kitchens Ltd.",
    "wof:placetype":"venue"
},
  "geometry": {"coordinates":[-1.283604,53.964977],"type":"Point"}
}