{
  "type": "Feature",
  "properties": {
    "addr:full":"Gainsborough Road, Scotter Common Gainsborough Lincolnshire DN21 3JF",
    "addr:postcode":"dn21 3jf",
    "addr:street":"Gainsborough Road",
    "iso:country":"GB",
    "sg:address":"Gainsborough Road, Scotter Common",
    "sg:city":"Gainsborough",
    "sg:classifiers":[
        {
            "category":"Health Services",
            "subcategory":"Nursing And Care Facility",
            "type":"Services"
        }
    ],
    "sg:phone":"+44 1724 762678",
    "sg:postcode":"DN21 3JF",
    "sg:province":"Lincolnshire",
    "sg:tags":[
        "home"
    ],
    "wof:name":"Laughtoncroft Nursing Home",
    "wof:placetype":"venue"
},
  "geometry": {"coordinates":[-0.666376,53.498924],"type":"Point"}
}