{
  "type": "Feature",
  "properties": {
    "addr:full":"3 Bank Street Irvine North Ayrshire KA12 0AJ",
    "addr:housenumber":"3",
    "addr:postcode":"ka12 0aj",
    "addr:street":"Bank Street",
    "iso:country":"GB",
    "sg:address":"3 Bank Street",
    "sg:city":"Irvine",
    "sg:classifiers":[
        {
            "category":"Personal",
            "subcategory":"Beauty Salon",
            "type":"Services"
        },
        {
            "category":"Personal",
            "subcategory":"Barber",
            "type":"Services"
        }
    ],
    "sg:phone":"+44 1294 311211",
    "sg:postcode":"KA12 0AJ",
    "sg:province":"North Ayrshire",
    "sg:tags":[
        "unisex",
        "hairdresser"
    ],
    "wof:name":"Diamond Cut",
    "wof:placetype":"venue"
},
  "geometry": {"coordinates":[-4.649232,55.623783],"type":"Point"}
}