{
  "type": "Feature",
  "properties": {
    "iso:country":"GB",
    "sg:address":"Ashton Vale Primary School, Kitchen, Avebury Rd",
    "sg:city":"Bristol",
    "sg:classifiers":[
        {
            "category":"Government",
            "subcategory":"Office",
            "type":"Public Place"
        }
    ],
    "sg:phone":"+44 117 963 3953",
    "sg:postcode":"BS3 2QG",
    "sg:province":"City of Bristol",
    "sg:tags":[
        "local"
    ],
    "wof:name":"Bristol City Council",
    "wof:placetype":"venue"
},
  "geometry": {"coordinates":[-2.622624,51.433273],"type":"Point"}
}