{
  "type": "Feature",
  "properties": {
    "iso:country":"GB",
    "sg:address":"158 Sherwood Av",
    "sg:city":"Northampton",
    "sg:classifiers":[
        {
            "category":"Retail",
            "subcategory":"Driving School",
            "type":"Services"
        }
    ],
    "sg:phone":"+44 1604 844182",
    "sg:postcode":"NN2 8TE",
    "sg:province":"Northamptonshire",
    "wof:name":"Browns School Of Motoring",
    "wof:placetype":"venue"
},
  "geometry": {"coordinates":[-0.91616,52.275745],"type":"Point"}
}