{
  "type": "Feature",
  "properties": {
    "addr:full":"44 Bavelaw Road Edinburgh City of Edinburgh EH14 7AE",
    "addr:housenumber":"44",
    "addr:postcode":"eh14 7ae",
    "addr:street":"Bavelaw Road",
    "iso:country":"GB",
    "sg:address":"44 Bavelaw Road",
    "sg:city":"Edinburgh",
    "sg:classifiers":[
        {
            "category":"Manufacturing",
            "subcategory":"Signs",
            "type":"Manufacturing & Wholesale Goods"
        },
        {
            "category":"Organizations",
            "subcategory":"Professional Association",
            "type":"Services"
        }
    ],
    "sg:phone":"+44 131 449 3565",
    "sg:postcode":"EH14 7AE",
    "sg:province":"City of Edinburgh",
    "sg:tags":[
        "manufacture",
        "tag",
        "badge",
        "label"
    ],
    "wof:name":"Lothian Label Co",
    "wof:placetype":"venue"
},
  "geometry": {"coordinates":[-3.3392300606,55.882358551],"type":"Point"}
}