{
  "type": "Feature",
  "properties": {
    "iso:country":"GB",
    "sg:address":"2 Upper Park Road",
    "sg:city":"St Leonards-on-sea",
    "sg:classifiers":[
        {
            "category":"Home & Garden",
            "subcategory":"Garden Supply",
            "type":"Retail Goods"
        }
    ],
    "sg:phone":"+44 1424 439831",
    "sg:postcode":"TN37 6SJ",
    "sg:province":"East Sussex",
    "sg:tags":[
        "pool",
        "swimming"
    ],
    "wof:name":"Chris Thayre Swimming Pools",
    "wof:placetype":"venue"
},
  "geometry": {"coordinates":[0.55891,50.863548],"type":"Point"}
}