{
  "type": "Feature",
  "properties": {
    "addr:full":"Old Parish Hall, Gatcombe Newport Isle of Wight PO30 3EG",
    "addr:postcode":"po30 3eg",
    "iso:country":"GB",
    "sg:address":"Old Parish Hall, Gatcombe",
    "sg:city":"Newport",
    "sg:classifiers":[
        {
            "category":"Building & Trades",
            "subcategory":"Construction",
            "type":"Services"
        }
    ],
    "sg:phone":"+44 1983 721330",
    "sg:postcode":"PO30 3EG",
    "sg:province":"Isle of Wight",
    "sg:tags":[
        "joiner",
        "carpenter"
    ],
    "wof:name":"J M Gifford",
    "wof:placetype":"venue"
},
  "geometry": {"coordinates":[-1.308636,50.664509],"type":"Point"}
}