{
  "type": "Feature",
  "properties": {
    "iso:country":"GB",
    "sg:address":"1 Lovat Lane",
    "sg:city":"London",
    "sg:classifiers":[
        {
            "category":"Bars & Pubs",
            "subcategory":"Wine Bar",
            "type":"Food & Drink"
        }
    ],
    "sg:phone":"+44 20 7283 8367",
    "sg:postcode":"EC3R 8DT",
    "sg:province":"Greater London",
    "wof:name":"Sibills",
    "wof:placetype":"venue"
},
  "geometry": {"coordinates":[-0.084006,51.510601],"type":"Point"}
}