{
  "type": "Feature",
  "properties": {
    "iso:country":"GB",
    "sg:address":"Branston Rd, Heighington",
    "sg:city":"Lincoln",
    "sg:classifiers":[
        {
            "category":"Sports & Exercise",
            "subcategory":"Stables",
            "type":"Entertainment"
        },
        {
            "category":"Personal",
            "subcategory":"Adult",
            "type":"Services"
        }
    ],
    "sg:phone":"+44 1522 871788",
    "sg:postcode":"LN4 1QQ",
    "sg:province":"Lincolnshire",
    "sg:tags":[
        "schools",
        "riding",
        "livery",
        "equestrian",
        "centre"
    ],
    "wof:name":"Poppyfields Equestrian",
    "wof:placetype":"venue"
},
  "geometry": {"coordinates":[-0.470754,53.193501],"type":"Point"}
}