{
  "type": "Feature",
  "properties": {
    "iso:country":"GB",
    "sg:address":"20 Edward St, Altofts",
    "sg:city":"Normanton",
    "sg:classifiers":[
        {
            "category":"Building & Trades",
            "subcategory":"Construction",
            "type":"Services"
        }
    ],
    "sg:postcode":"WF6 2QU",
    "sg:province":"West Yorkshire",
    "sg:tags":[
        "decorator",
        "painter"
    ],
    "wof:name":"Broadhead,A,",
    "wof:placetype":"venue"
},
  "geometry": {"coordinates":[-1.4213440418,53.7139091492],"type":"Point"}
}