{
  "type": "Feature",
  "properties": {
    "addr:full":"Unit 17 Waterlooville Hampshire PO7 7UP",
    "addr:housenumber":"unit 17",
    "addr:postcode":"po7 7up",
    "iso:country":"GB",
    "sg:address":"Unit 17",
    "sg:city":"Waterlooville",
    "sg:classifiers":[
        {
            "category":"Retail",
            "subcategory":"Repair Shop",
            "type":"Services"
        }
    ],
    "sg:phone":"+44 23 9226 3202",
    "sg:postcode":"PO7 7UP",
    "sg:province":"Hampshire",
    "sg:tags":[
        "sharpening",
        "tool"
    ],
    "wof:name":"C R M Saw Co. Ltd.",
    "wof:placetype":"venue"
},
  "geometry": {"coordinates":[-1.031559,50.880089],"type":"Point"}
}