{
  "type": "Feature",
  "properties": {
    "addr:full":"Lewes Road, Lindfield Haywards Heath East Sussex RH16 2LG",
    "addr:postcode":"rh16 2lg",
    "addr:street":"Lewes Road",
    "iso:country":"GB",
    "sg:address":"Lewes Road, Lindfield",
    "sg:city":"Haywards Heath",
    "sg:classifiers":[
        {
            "category":"Shopping",
            "subcategory":"Florist",
            "type":"Retail Goods"
        }
    ],
    "sg:phone":"+44 1444 484472",
    "sg:postcode":"RH16 2LG",
    "sg:province":"East Sussex",
    "wof:name":"Flowercraft",
    "wof:placetype":"venue"
},
  "geometry": {"coordinates":[-0.080877997,51.0116424561],"type":"Point"}
}