{
  "type": "Feature",
  "properties": {
    "addr:full":"7 High Street, Bluntisham Huntingdon Bedfordshire PE28 3LD",
    "addr:housenumber":"7",
    "addr:postcode":"pe28 3ld",
    "addr:street":"High Street",
    "iso:country":"GB",
    "sg:address":"7 High Street, Bluntisham",
    "sg:city":"Huntingdon",
    "sg:classifiers":[
        {
            "category":"Professional",
            "type":"Services"
        },
        {
            "category":"Banks & Credit Unions",
            "subcategory":"Investment Brokerage",
            "type":"Services"
        }
    ],
    "sg:phone":"+44 1487 841632",
    "sg:postcode":"PE28 3LD",
    "sg:province":"Bedfordshire",
    "sg:tags":[
        "farm",
        "agricultural",
        "contractor"
    ],
    "wof:name":"G R Wadsworth & Son",
    "wof:placetype":"venue"
},
  "geometry": {"coordinates":[0.006881,52.3516578674],"type":"Point"}
}