{
  "type": "Feature",
  "properties": {
    "iso:country":"GB",
    "sg:address":"Cooper House Farm",
    "sg:city":"Harrogate",
    "sg:classifiers":[
        {
            "category":"Farming",
            "subcategory":"Livestock Farm",
            "type":"Manufacturing & Wholesale Goods"
        }
    ],
    "sg:phone":"+44 1943 880250",
    "sg:postcode":"HG3 1TE",
    "sg:province":"North Yorkshire",
    "sg:tags":[
        "others"
    ],
    "wof:name":"E Wood",
    "wof:placetype":"venue"
},
  "geometry": {"coordinates":[-1.6831899881,53.9733009338],"type":"Point"}
}