{
  "type": "Feature",
  "properties": {
    "addr:full":"Dental Surgery, 4 Durley Av Waterlooville Hampshire PO8 8XA",
    "addr:housenumber":"4",
    "addr:postcode":"po8 8xa",
    "addr:street":"Durley Av Waterlooville",
    "iso:country":"GB",
    "sg:address":"Dental Surgery, 4 Durley Av",
    "sg:city":"Waterlooville",
    "sg:classifiers":[
        {
            "category":"Health Services",
            "subcategory":"Dentist",
            "type":"Services"
        }
    ],
    "sg:phone":"+44 23 9226 2973",
    "sg:postcode":"PO8 8XA",
    "sg:province":"Hampshire",
    "wof:name":"M A Kelly",
    "wof:placetype":"venue"
},
  "geometry": {"coordinates":[-1.0192,50.895351],"type":"Point"}
}