{
  "type": "Feature",
  "properties": {
    "iso:country":"GB",
    "sg:address":"The Maltings, Peasmarsh",
    "sg:city":"Rye",
    "sg:classifiers":[
        {
            "category":"Manufacturing",
            "subcategory":"Pottery",
            "type":"Manufacturing & Wholesale Goods"
        }
    ],
    "sg:phone":"+44 1797 230400",
    "sg:postcode":"TN31 6ST",
    "sg:province":"East Sussex",
    "sg:tags":[
        "supplier"
    ],
    "wof:name":"James Dean Pottery",
    "wof:placetype":"venue"
},
  "geometry": {"coordinates":[0.67889,50.977589],"type":"Point"}
}