{
  "type": "Feature",
  "properties": {
    "addr:full":"9 Station Rd, Wombwell Barnsley South Yorkshire S73 0AH",
    "addr:housenumber":"9",
    "addr:postcode":"s73 0ah",
    "addr:street":"Station Rd;Yorkshire",
    "iso:country":"GB",
    "sg:address":"9 Station Rd, Wombwell",
    "sg:city":"Barnsley",
    "sg:classifiers":[
        {
            "category":"Shopping",
            "subcategory":"Shoes",
            "type":"Retail Goods"
        }
    ],
    "sg:postcode":"S73 0AH",
    "sg:province":"South Yorkshire",
    "sg:tags":[
        "shop"
    ],
    "wof:name":"Farfalla Shoes",
    "wof:placetype":"venue"
},
  "geometry": {"coordinates":[-1.3974750042,53.5223197937],"type":"Point"}
}