{
  "type": "Feature",
  "properties": {
    "addr:full":"Civic House, 20 Grand Depot Rd, Woolwich Woolwich Greater London SE18 6SF",
    "addr:housenumber":"20",
    "addr:postcode":"se18 6sf",
    "addr:street":"Grand Depot Rd",
    "iso:country":"GB",
    "sg:address":"Civic House, 20 Grand Depot Rd, Woolwich",
    "sg:city":"Woolwich",
    "sg:classifiers":[
        {
            "category":"Organizations",
            "subcategory":"Professional Association",
            "type":"Services"
        }
    ],
    "sg:phone":"+44 20 8854 2244",
    "sg:postcode":"SE18 6SF",
    "sg:province":"Greater London",
    "sg:tags":[
        "union",
        "trade"
    ],
    "wof:name":"UNISON",
    "wof:placetype":"venue"
},
  "geometry": {"coordinates":[0.065126,51.487938],"type":"Point"}
}