{
  "type": "Feature",
  "properties": {
    "addr:full":"119 Feltham Rd Ashford Greater London TW15 1AB",
    "addr:housenumber":"119",
    "addr:postcode":"tw15 1ab",
    "addr:street":"Feltham Rd",
    "iso:country":"GB",
    "sg:address":"119 Feltham Rd",
    "sg:city":"Ashford",
    "sg:classifiers":[
        {
            "category":"Manufacturing",
            "subcategory":"Tools & Machinery",
            "type":"Manufacturing & Wholesale Goods"
        }
    ],
    "sg:phone":"+44 1784 420622",
    "sg:postcode":"TW15 1AB",
    "sg:province":"Greater London",
    "sg:tags":[
        "society",
        "friendly"
    ],
    "wof:name":"Adams Insurance Services",
    "wof:placetype":"venue"
},
  "geometry": {"coordinates":[-0.447436,51.432949],"type":"Point"}
}