{
  "type": "Feature",
  "properties": {
    "addr:full":"39 Severn Stoke Worcester Gloucestershire WR8 9JA",
    "addr:housenumber":"39",
    "addr:postcode":"wr8 9ja",
    "addr:street":"Severn",
    "iso:country":"GB",
    "sg:address":"39 Severn Stoke",
    "sg:city":"Worcester",
    "sg:classifiers":[
        {
            "category":"Shopping",
            "subcategory":"Antiques",
            "type":"Retail Goods"
        }
    ],
    "sg:phone":"+44 1905 371339",
    "sg:postcode":"WR8 9JA",
    "sg:province":"Gloucestershire",
    "wof:name":"Director Furniture",
    "wof:placetype":"venue"
},
  "geometry": {"coordinates":[-2.20926,52.09671],"type":"Point"}
}