{
  "type": "Feature",
  "properties": {
    "addr:full":"Gresham Ho, 5-7 St. Pauls St Leeds West Yorkshire LS1 2JG",
    "addr:housenumber":"5-7",
    "addr:postcode":"ls1 2jg",
    "addr:street":"St. Pauls St",
    "iso:country":"GB",
    "sg:address":"Gresham Ho, 5-7 St. Pauls St",
    "sg:city":"Leeds",
    "sg:classifiers":[
        {
            "category":"Real Estate",
            "subcategory":"Surveying",
            "type":"Services"
        }
    ],
    "sg:phone":"+44 113 244 2874",
    "sg:postcode":"LS1 2JG",
    "sg:province":"West Yorkshire",
    "sg:tags":[
        "surveyor",
        "valuer"
    ],
    "wof:name":"Grimley",
    "wof:placetype":"venue"
},
  "geometry": {"coordinates":[-1.5465869904,53.7944946289],"type":"Point"}
}