{
  "type": "Feature",
  "properties": {
    "iso:country":"GB",
    "sg:address":"29a Dickson Road",
    "sg:city":"Blackpool",
    "sg:classifiers":[
        {
            "category":"Personal",
            "subcategory":"Beauty Salon",
            "type":"Services"
        },
        {
            "category":"Personal",
            "subcategory":"Barber",
            "type":"Services"
        }
    ],
    "sg:phone":"+44 1253 624737",
    "sg:postcode":"FY1 2AT",
    "sg:province":"Lancashire",
    "sg:tags":[
        "unisex",
        "hairdresser"
    ],
    "wof:name":"SABRE HAIR & BEAUTY",
    "wof:placetype":"venue"
},
  "geometry": {"coordinates":[-3.052314043,53.8218383789],"type":"Point"}
}