{
  "type": "Feature",
  "properties": {
    "iso:country":"GB",
    "sg:address":"3 Manor Park, Steeple Ashton",
    "sg:city":"Trowbridge",
    "sg:classifiers":[
        {
            "category":"Wholesale",
            "subcategory":"Sporting Goods",
            "type":"Manufacturing & Wholesale Goods"
        }
    ],
    "sg:phone":"+44 1380 871262",
    "sg:postcode":"BA14 6EP",
    "sg:province":"Wiltshire",
    "sg:tags":[
        "mnfr",
        "sport",
        "equipment"
    ],
    "wof:name":"Direct Sports",
    "wof:placetype":"venue"
},
  "geometry": {"coordinates":[-2.1452040672,51.3434829712],"type":"Point"}
}