{
  "type": "Feature",
  "properties": {
    "addr:full":"6 Gean Court, Cumbernauld Glasgow Falkirk G67 3LU",
    "addr:housenumber":"6",
    "addr:postcode":"g67 3lu",
    "addr:street":"Gean Court",
    "iso:country":"GB",
    "sg:address":"6 Gean Court, Cumbernauld",
    "sg:city":"Glasgow",
    "sg:classifiers":[
        {
            "category":"Retail",
            "subcategory":"Driving School",
            "type":"Services"
        }
    ],
    "sg:phone":"+44 1236 720389",
    "sg:postcode":"G67 3LU",
    "sg:province":"Falkirk",
    "wof:name":"Thistle School of Motoring",
    "wof:placetype":"venue"
},
  "geometry": {"coordinates":[-3.9461948872,55.9587631226],"type":"Point"}
}