{
  "type": "Feature",
  "properties": {
    "addr:full":"1a High St Epsom Surrey KT19 8DA",
    "addr:housenumber":"1a",
    "addr:postcode":"kt19 8da",
    "addr:street":"High St",
    "iso:country":"GB",
    "sg:address":"1a High St",
    "sg:city":"Epsom",
    "sg:classifiers":[
        {
            "category":"Shopping",
            "subcategory":"Stationery & Office Supplies",
            "type":"Retail Goods"
        }
    ],
    "sg:postcode":"KT19 8DA",
    "sg:province":"Surrey",
    "sg:tags":[
        "item",
        "promotional"
    ],
    "wof:name":"Eyecatchers Promotions Ltd",
    "wof:placetype":"venue"
},
  "geometry": {"coordinates":[-0.264315,51.333954],"type":"Point"}
}