{
  "type": "Feature",
  "properties": {
    "addr:full":"8 Greville Rd Kenilworth Warwickshire CV8 1EL",
    "addr:housenumber":"8",
    "addr:postcode":"cv8 1el",
    "addr:street":"Greville Rd",
    "iso:country":"GB",
    "sg:address":"8 Greville Rd",
    "sg:city":"Kenilworth",
    "sg:classifiers":[
        {
            "category":"Organizations",
            "subcategory":"Political Organization",
            "type":"Services"
        }
    ],
    "sg:phone":"+44 1926 854342",
    "sg:postcode":"CV8 1EL",
    "sg:province":"Warwickshire",
    "sg:tags":[
        "party"
    ],
    "wof:name":"Liberal Democrats",
    "wof:placetype":"venue"
},
  "geometry": {"coordinates":[-1.582901,52.341309],"type":"Point"}
}