{
  "type": "Feature",
  "properties": {
    "iso:country":"GB",
    "sg:address":"23 Amberley Avenue, Bulkington",
    "sg:city":"Nuneaton",
    "sg:classifiers":[
        {
            "category":"Building & Trades",
            "subcategory":"Plumbing",
            "type":"Services"
        }
    ],
    "sg:phone":"+44 24 7631 5394",
    "sg:postcode":"CV12 9QZ",
    "sg:province":"Warwickshire",
    "sg:tags":[
        "repair",
        "heating",
        "servicing",
        "boiler"
    ],
    "wof:name":"E T Boiler Services",
    "wof:placetype":"venue"
},
  "geometry": {"coordinates":[-1.41886,52.477779],"type":"Point"}
}