{
  "type": "Feature",
  "properties": {
    "addr:full":"2-4 St. Marys Place, Eltham Eltham Greater London SE9 1BL",
    "addr:housenumber":"2-4",
    "addr:postcode":"se9 1bl",
    "addr:street":"St. Marys Place",
    "iso:country":"GB",
    "sg:address":"2-4 St. Marys Place, Eltham",
    "sg:city":"Eltham",
    "sg:classifiers":[
        {
            "category":"Travel",
            "subcategory":"Travel Agent",
            "type":"Entertainment"
        }
    ],
    "sg:phone":"+44 20 8272 6000",
    "sg:postcode":"SE9 1BL",
    "sg:province":"Greater London",
    "wof:name":"Thomas Cook Travel",
    "wof:placetype":"venue"
},
  "geometry": {"coordinates":[0.05734,51.450581],"type":"Point"}
}