{
  "type": "Feature",
  "properties": {
    "addr:full":"Units 1-3 Tattenhall Road, Tattenhall Chester Cheshire CH3 9BD",
    "addr:housenumber":"units 1-3",
    "addr:postcode":"ch3 9bd",
    "addr:street":"Tattenhall Road",
    "iso:country":"GB",
    "sg:address":"Units 1-3 Tattenhall Road, Tattenhall",
    "sg:city":"Chester",
    "sg:classifiers":[
        {
            "category":"Retail",
            "subcategory":"Auto Repair",
            "type":"Services"
        }
    ],
    "sg:phone":"+44 1829 770566",
    "sg:postcode":"CH3 9BD",
    "sg:province":"Cheshire",
    "sg:tags":[
        "body",
        "garage",
        "modification",
        "car"
    ],
    "wof:name":"N M Sharp (Autocrash Repair Centre)",
    "wof:placetype":"venue"
},
  "geometry": {"coordinates":[-2.7728788853,53.1191558838],"type":"Point"}
}