{
  "type": "Feature",
  "properties": {
    "addr:full":"Town Foot, Rothbury Morpeth Northumberland NE65 7SL",
    "addr:postcode":"ne65 7sl",
    "addr:street":"Northumberland",
    "iso:country":"GB",
    "sg:address":"Town Foot, Rothbury",
    "sg:city":"Morpeth",
    "sg:classifiers":[
        {
            "category":"Home & Garden",
            "subcategory":"Hardware",
            "type":"Retail Goods"
        }
    ],
    "sg:postcode":"NE65 7SL",
    "sg:province":"Northumberland",
    "wof:name":"Little Friday",
    "wof:placetype":"venue"
},
  "geometry": {"coordinates":[-1.913994,55.309254],"type":"Point"}
}