{
  "type": "Feature",
  "properties": {
    "iso:country":"GB",
    "sg:address":"Willingdon Rd",
    "sg:city":"Eastbourne",
    "sg:classifiers":[
        {
            "category":"Place Of Worship",
            "type":"Public Place"
        }
    ],
    "sg:phone":"+44 1323 645740",
    "sg:postcode":"BN21 1TN",
    "sg:province":"East Sussex",
    "wof:name":"St Michael & All Angels Church",
    "wof:placetype":"venue"
},
  "geometry": {"coordinates":[0.2607600093,50.7846908569],"type":"Point"}
}