{
  "type": "Feature",
  "properties": {
    "addr:full":"58 Worcester Street Stourbridge Staffordshire DY8 1AS",
    "addr:housenumber":"58",
    "addr:postcode":"dy8 1as",
    "addr:street":"Worcester Street",
    "iso:country":"GB",
    "sg:address":"58 Worcester Street",
    "sg:city":"Stourbridge",
    "sg:classifiers":[
        {
            "category":"Professional",
            "subcategory":"Art Services",
            "type":"Services"
        }
    ],
    "sg:phone":"+44 1384 390170",
    "sg:postcode":"DY8 1AS",
    "sg:province":"Staffordshire",
    "sg:tags":[
        "picture",
        "framing"
    ],
    "wof:name":"Stourbridge Galleries",
    "wof:placetype":"venue"
},
  "geometry": {"coordinates":[-2.148107,52.452259],"type":"Point"}
}