{
  "type": "Feature",
  "properties": {
    "addr:full":"85 Cottage Beck Road Scunthorpe Lincolnshire DN16 1UE",
    "addr:housenumber":"85",
    "addr:postcode":"dn16 1ue",
    "addr:street":"Cottage Beck Road",
    "iso:country":"GB",
    "sg:address":"85 Cottage Beck Road",
    "sg:city":"Scunthorpe",
    "sg:classifiers":[
        {
            "category":"Food & Beverages",
            "subcategory":"Bakery",
            "type":"Retail Goods"
        },
        {
            "category":"Food & Beverages",
            "subcategory":"Groceries & Convenience Stores",
            "type":"Retail Goods"
        }
    ],
    "sg:phone":"+44 1724 844660",
    "sg:postcode":"DN16 1UE",
    "sg:province":"Lincolnshire",
    "sg:tags":[
        "shop",
        "baker"
    ],
    "wof:name":"The Chocolate Box",
    "wof:placetype":"venue"
},
  "geometry": {"coordinates":[-0.6446679831,53.5847396851],"type":"Point"}
}