{
  "type": "Feature",
  "properties": {
    "addr:full":"80 King Street Whitehaven Cumbria CA28 7LE",
    "addr:housenumber":"80",
    "addr:postcode":"ca28 7le",
    "addr:street":"King Street",
    "iso:country":"GB",
    "sg:address":"80 King Street",
    "sg:city":"Whitehaven",
    "sg:classifiers":[
        {
            "category":"Travel",
            "subcategory":"Travel Agent",
            "type":"Entertainment"
        }
    ],
    "sg:postcode":"CA28 7LE",
    "sg:province":"Cumbria",
    "wof:name":"Destinations Ltd.",
    "wof:placetype":"venue"
},
  "geometry": {"coordinates":[-3.5900990963,54.5480651855],"type":"Point"}
}