{
  "type": "Feature",
  "properties": {
    "addr:full":"Stalleon House, Fawkham Road, West Kingsdown Sevenoaks Kent TN15 6JS",
    "addr:postcode":"tn15 6js",
    "addr:street":"Fawkham Road West",
    "iso:country":"GB",
    "sg:address":"Stalleon House, Fawkham Road, West Kingsdown",
    "sg:city":"Sevenoaks",
    "sg:classifiers":[
        {
            "category":"Professional",
            "subcategory":"Management & Consulting",
            "type":"Services"
        }
    ],
    "sg:phone":"+44 1474 854444",
    "sg:postcode":"TN15 6JS",
    "sg:province":"Kent",
    "sg:tags":[
        "fire",
        "consultant",
        "protection"
    ],
    "wof:name":"Stalleon Control Systems Ltd.",
    "wof:placetype":"venue"
},
  "geometry": {"coordinates":[0.2673180103,51.3414421082],"type":"Point"}
}