{
  "type": "Feature",
  "properties": {
    "addr:full":"8 Salisbury Square London Greater London E4 8BB",
    "addr:housenumber":"8",
    "addr:postcode":"e4 8bb",
    "addr:street":"Salisbury Square",
    "iso:country":"GB",
    "sg:address":"8 Salisbury Square",
    "sg:city":"London",
    "sg:classifiers":[
        {
            "category":"Professional",
            "subcategory":"Accounting & Tax Preparation",
            "type":"Services"
        }
    ],
    "sg:postcode":"E4 8BB",
    "sg:province":"Greater London",
    "sg:tags":[
        "accountant"
    ],
    "wof:name":"K P M G Llp",
    "wof:placetype":"venue"
},
  "geometry": {"coordinates":[-0.0164129995,51.6200523376],"type":"Point"}
}