{
  "type": "Feature",
  "properties": {
    "addr:full":"15b Broadway House, 149-151 St Neots Road, Hardwick Cambridge Cambridgeshire CB3 7QJ",
    "addr:housenumber":"15b;149-151",
    "addr:postcode":"cb3 7qj",
    "addr:street":"Broadway;St Neots Road",
    "iso:country":"GB",
    "sg:address":"15b Broadway House, 149-151 St Neots Road, Hardwick",
    "sg:city":"Cambridge",
    "sg:classifiers":[
        {
            "category":"Personal",
            "subcategory":"Beauty Salon",
            "type":"Services"
        }
    ],
    "sg:phone":"+44 1954 211377",
    "sg:postcode":"CB3 7QJ",
    "sg:province":"Cambridgeshire",
    "sg:tags":[
        "unisex",
        "hairdresser"
    ],
    "wof:name":"The Hair Care Bunch",
    "wof:placetype":"venue"
},
  "geometry": {"coordinates":[0.00986,52.21796],"type":"Point"}
}