{
  "type": "Feature",
  "properties": {
    "addr:full":"136 Clifton Street Cardiff Cardiff CF24 1LY",
    "addr:housenumber":"136",
    "addr:postcode":"cf24 1ly",
    "addr:street":"Clifton Street",
    "iso:country":"GB",
    "sg:address":"136 Clifton Street",
    "sg:city":"Cardiff",
    "sg:classifiers":[
        {
            "category":"Shopping",
            "subcategory":"Thrift Store",
            "type":"Retail Goods"
        },
        {
            "category":"Organizations",
            "subcategory":"Non-profit Organization",
            "type":"Services"
        }
    ],
    "sg:phone":"+44 29 2048 3286",
    "sg:postcode":"CF24 1LY",
    "sg:province":"Cardiff",
    "sg:tags":[
        "shop",
        "charitable",
        "organisation",
        "charity"
    ],
    "wof:name":"British Red Cross Society",
    "wof:placetype":"venue"
},
  "geometry": {"coordinates":[-3.1586608887,51.4860115051],"type":"Point"}
}