{
  "type": "Feature",
  "properties": {
    "addr:full":"Unit 3, 9 Woodword Road, Howden Industrial Estate Tiverton Devon EX16 5HW",
    "addr:housenumber":"unit;9",
    "addr:postcode":"ex16 5hw",
    "addr:street":"Woodword Road;Industrial Estate",
    "iso:country":"GB",
    "sg:address":"Unit 3, 9 Woodword Road, Howden Industrial Estate",
    "sg:city":"Tiverton",
    "sg:classifiers":[
        {
            "category":"Shopping",
            "subcategory":"Computers & Home Electronics",
            "type":"Retail Goods"
        }
    ],
    "sg:phone":"+44 1884 255355",
    "sg:postcode":"EX16 5HW",
    "sg:province":"Devon",
    "sg:tags":[
        "consumables"
    ],
    "wof:name":"Lasarus Ltd.",
    "wof:placetype":"venue"
},
  "geometry": {"coordinates":[-3.493149,50.905025],"type":"Point"}
}