{
  "type": "Feature",
  "properties": {
    "addr:full":"Unit 4 Ringmer Business Centre, Chamberlaines Lane Lewes East Sussex BN8 5NF",
    "addr:housenumber":"unit 4 ringmer business centre",
    "addr:postcode":"bn8 5nf",
    "addr:street":"Chamberlaines Lane",
    "iso:country":"GB",
    "sg:address":"Unit 4 Ringmer Business Centre, Chamberlaines Lane",
    "sg:city":"Lewes",
    "sg:classifiers":[
        {
            "category":"Professional",
            "subcategory":"Engineering",
            "type":"Services"
        }
    ],
    "sg:phone":"+44 1273 814001",
    "sg:postcode":"BN8 5NF",
    "sg:province":"East Sussex",
    "sg:tags":[
        "precision",
        "engineer"
    ],
    "wof:name":"Winter Engineering",
    "wof:placetype":"venue"
},
  "geometry": {"coordinates":[0.0727799982,50.8942489624],"type":"Point"}
}