{
  "type": "Feature",
  "properties": {
    "iso:country":"GB",
    "sg:address":"Woodside Farm, Dean",
    "sg:city":"Workington",
    "sg:classifiers":[
        {
            "category":"Farming",
            "subcategory":"Dairy Farm",
            "type":"Manufacturing & Wholesale Goods"
        }
    ],
    "sg:phone":"+44 1946 861271",
    "sg:postcode":"CA14 4TQ",
    "sg:province":"Cumbria",
    "sg:tags":[
        "farmer"
    ],
    "wof:name":"John Sanderson",
    "wof:placetype":"venue"
},
  "geometry": {"coordinates":[-3.433943,54.613651],"type":"Point"}
}