{
  "type": "Feature",
  "properties": {
    "iso:country":"GB",
    "sg:address":"The Gatehouse, 49 Cemetary Road",
    "sg:city":"York",
    "sg:classifiers":[
        {
            "category":"Professional",
            "subcategory":"Lawyer & Legal Services",
            "type":"Services"
        }
    ],
    "sg:phone":"+44 1904 639991",
    "sg:postcode":"YO10 5AJ",
    "sg:province":"North Yorkshire",
    "sg:tags":[
        "solicitor"
    ],
    "wof:name":"Howard & Byrne",
    "wof:placetype":"venue"
},
  "geometry": {"coordinates":[-1.07325,53.94965],"type":"Point"}
}