{
  "type": "Feature",
  "properties": {
    "iso:country":"GB",
    "sg:address":"Old Coach Road",
    "sg:city":"Runcorn",
    "sg:classifiers":[
        {
            "category":"Manufacturing",
            "subcategory":"Lumber",
            "type":"Manufacturing & Wholesale Goods"
        }
    ],
    "sg:phone":"+44 1928 577749",
    "sg:postcode":"WA7 1QT",
    "sg:province":"Cheshire",
    "sg:tags":[
        "importer",
        "merchants",
        "agent",
        "timber"
    ],
    "wof:name":"Sandawn Timber",
    "wof:placetype":"venue"
},
  "geometry": {"coordinates":[-2.709019,53.330421],"type":"Point"}
}