{
  "type": "Feature",
  "properties": {
    "addr:full":"98 Cathedral Road Oldham Lancashire OL9 0RG",
    "addr:housenumber":"98",
    "addr:postcode":"ol9 0rg",
    "addr:street":"Cathedral Road",
    "iso:country":"GB",
    "sg:address":"98 Cathedral Road",
    "sg:city":"Oldham",
    "sg:classifiers":[
        {
            "category":"Food & Beverages",
            "subcategory":"Fruits & Vegetables",
            "type":"Retail Goods"
        }
    ],
    "sg:phone":"+44 161 624 7513",
    "sg:postcode":"OL9 0RG",
    "sg:province":"Lancashire",
    "sg:tags":[
        "greengrocer"
    ],
    "wof:name":"Food for Thought",
    "wof:placetype":"venue"
},
  "geometry": {"coordinates":[-2.1549739838,53.553314209],"type":"Point"}
}