{
  "type": "Feature",
  "properties": {
    "iso:country":"GB",
    "sg:address":"Caernarfon Road, Cwm Y Glo",
    "sg:city":"Caernarfon",
    "sg:classifiers":[
        {
            "category":"Autos & Motor Vehicles",
            "subcategory":"Automobile Sales",
            "type":"Retail Goods"
        }
    ],
    "sg:postcode":"LL55 4DE",
    "sg:province":"Gwynedd",
    "sg:tags":[
        "commercial"
    ],
    "wof:name":"Ceir Cwm",
    "wof:placetype":"venue"
},
  "geometry": {"coordinates":[-4.1587090492,53.1372299194],"type":"Point"}
}