{
  "type": "Feature",
  "properties": {
    "addr:full":"84 Stokes Drive Leicester Leicestershire LE3 9BS",
    "addr:housenumber":"84",
    "addr:postcode":"le3 9bs",
    "addr:street":"Stokes Drive",
    "iso:country":"GB",
    "sg:address":"84 Stokes Drive",
    "sg:city":"Leicester",
    "sg:classifiers":[
        {
            "category":"Professional",
            "subcategory":"Management & Consulting",
            "type":"Services"
        }
    ],
    "sg:phone":"+44 116 233 6305",
    "sg:postcode":"LE3 9BS",
    "sg:province":"Leicestershire",
    "sg:tags":[
        "environmental",
        "consultant"
    ],
    "wof:name":"A1 Safety Netting & Roofing",
    "wof:placetype":"venue"
},
  "geometry": {"coordinates":[-1.164214015,52.6479377747],"type":"Point"}
}