{
  "type": "Feature",
  "properties": {
    "iso:country":"GB",
    "sg:address":"1126 South St",
    "sg:city":"Glasgow",
    "sg:classifiers":[
        {
            "category":"Retail",
            "subcategory":"Auto Repair",
            "type":"Services"
        }
    ],
    "sg:postcode":"G14 0DT",
    "sg:province":"Glasgow City",
    "sg:tags":[
        "modification",
        "garage"
    ],
    "wof:name":"Macdonald,John,",
    "wof:placetype":"venue"
},
  "geometry": {"coordinates":[-4.352295,55.876781],"type":"Point"}
}