{
  "type": "Feature",
  "properties": {
    "iso:country":"GB",
    "sg:address":"57 Peas Hill Rd",
    "sg:city":"March",
    "sg:classifiers":[
        {
            "category":"Building & Trades",
            "subcategory":"Construction",
            "type":"Services"
        }
    ],
    "sg:phone":"+44 1354 652820",
    "sg:postcode":"PE15 8HE",
    "sg:province":"Cambridgeshire",
    "sg:tags":[
        "decorator",
        "painter"
    ],
    "wof:name":"March Partners",
    "wof:placetype":"venue"
},
  "geometry": {"coordinates":[0.067872,52.556267],"type":"Point"}
}