{
  "type": "Feature",
  "properties": {
    "iso:country":"GB",
    "sg:address":"Hills Jarrett, Gainsborough House, Sheering Lower Rd",
    "sg:city":"Sawbridgeworth",
    "sg:classifiers":[
        {
            "category":"Real Estate",
            "subcategory":"Developer",
            "type":"Services"
        }
    ],
    "sg:postcode":"CM21 9RG",
    "sg:province":"Essex",
    "sg:tags":[
        "property"
    ],
    "wof:name":"M.D. Nash & Company Ltd",
    "wof:placetype":"venue"
},
  "geometry": {"coordinates":[0.1578170061,51.8012237549],"type":"Point"}
}