{
  "type": "Feature",
  "properties": {
    "iso:country":"GB",
    "sg:address":"17 Brookvale Park Road",
    "sg:city":"Birmingham",
    "sg:classifiers":[
        {
            "category":"Organizations",
            "subcategory":"Membership Organization",
            "type":"Services"
        }
    ],
    "sg:phone":"+44 121 331 4002",
    "sg:postcode":"B23 7TY",
    "sg:province":"West Midlands",
    "sg:tags":[
        "club"
    ],
    "wof:name":"Central Association Of Disc Jockeys",
    "wof:placetype":"venue"
},
  "geometry": {"coordinates":[-1.876129,52.527493],"type":"Point"}
}