{
  "type": "Feature",
  "properties": {
    "addr:full":"41 Caprington Avenue Kilmarnock East Ayrshire KA1 4ST",
    "addr:housenumber":"41",
    "addr:postcode":"ka1 4st",
    "addr:street":"Caprington Avenue Kilmarnock East",
    "iso:country":"GB",
    "sg:address":"41 Caprington Avenue",
    "sg:city":"Kilmarnock",
    "sg:classifiers":[
        {
            "category":"Building & Trades",
            "subcategory":"Construction",
            "type":"Services"
        }
    ],
    "sg:phone":"+44 1563 570459",
    "sg:postcode":"KA1 4ST",
    "sg:province":"East Ayrshire",
    "sg:tags":[
        "decorator",
        "painter"
    ],
    "wof:name":"David Skilling",
    "wof:placetype":"venue"
},
  "geometry": {"coordinates":[-4.5000991821,55.5879211426],"type":"Point"}
}