{
  "type": "Feature",
  "properties": {
    "addr:full":"34 Queen Street Rhyl Conwy LL18 1RY",
    "addr:housenumber":"34",
    "addr:postcode":"ll18 1ry",
    "addr:street":"Queen Street",
    "iso:country":"GB",
    "sg:address":"34 Queen Street",
    "sg:city":"Rhyl",
    "sg:classifiers":[
        {
            "category":"Restaurant",
            "type":"Food & Drink"
        }
    ],
    "sg:phone":"+44 1745 343000",
    "sg:postcode":"LL18 1RY",
    "sg:province":"Conwy",
    "sg:tags":[
        "-",
        "chinese"
    ],
    "wof:name":"Dragon Boat Restaurant",
    "wof:placetype":"venue"
},
  "geometry": {"coordinates":[-3.4931390285,53.321105957],"type":"Point"}
}