{
  "type": "Feature",
  "properties": {
    "iso:country":"GB",
    "sg:address":"Butterley Court, Thornbury",
    "sg:city":"Bromyard",
    "sg:classifiers":[
        {
            "category":"Farming",
            "subcategory":"Dairy Farm",
            "type":"Manufacturing & Wholesale Goods"
        },
        {
            "category":"Farming",
            "subcategory":"Livestock Farm",
            "type":"Manufacturing & Wholesale Goods"
        }
    ],
    "sg:phone":"+44 1885 482410",
    "sg:postcode":"HR7 4NG",
    "sg:province":"Herefordshire",
    "sg:tags":[
        "others",
        "farmer"
    ],
    "wof:name":"T Legge & Son",
    "wof:placetype":"venue"
},
  "geometry": {"coordinates":[-2.510399,52.189098],"type":"Point"}
}