{
  "type": "Feature",
  "properties": {
    "addr:full":"Rushleys Farm, Ilam Ashbourne Derbyshire DE6 2BA",
    "addr:postcode":"de6 2ba",
    "addr:street":"Ashbourne",
    "iso:country":"GB",
    "sg:address":"Rushleys Farm, Ilam",
    "sg:city":"Ashbourne",
    "sg:classifiers":[
        {
            "category":"Farming",
            "subcategory":"Farm",
            "type":"Manufacturing & Wholesale Goods"
        }
    ],
    "sg:postcode":"DE6 2BA",
    "sg:province":"Derbyshire",
    "sg:tags":[
        "mixed",
        "crop"
    ],
    "wof:name":"V J Holland",
    "wof:placetype":"venue"
},
  "geometry": {"coordinates":[-1.800632,53.054989],"type":"Point"}
}