{
  "type": "Feature",
  "properties": {
    "addr:full":"Galdenoch Farm, Leswalt Stranraer Dumfries and Galloway DG9 0RS",
    "addr:postcode":"dg9 0rs",
    "iso:country":"GB",
    "sg:address":"Galdenoch Farm, Leswalt",
    "sg:city":"Stranraer",
    "sg:classifiers":[
        {
            "category":"Farming",
            "subcategory":"Livestock Farm",
            "type":"Manufacturing & Wholesale Goods"
        }
    ],
    "sg:postcode":"DG9 0RS",
    "sg:province":"Dumfries and Galloway",
    "sg:tags":[
        "others"
    ],
    "wof:name":"W & M Sloan",
    "wof:placetype":"venue"
},
  "geometry": {"coordinates":[-5.092904,54.930618],"type":"Point"}
}