{
  "type": "Feature",
  "properties": {
    "addr:full":"108 Canterbury Road Worthing West Sussex BN13 1AL",
    "addr:housenumber":"108",
    "addr:postcode":"bn13 1al",
    "addr:street":"Canterbury Road",
    "iso:country":"GB",
    "sg:address":"108 Canterbury Road",
    "sg:city":"Worthing",
    "sg:classifiers":[
        {
            "category":"Building & Trades",
            "subcategory":"Landscaping Services",
            "type":"Services"
        }
    ],
    "sg:postcode":"BN13 1AL",
    "sg:province":"West Sussex",
    "sg:tags":[
        "gardening"
    ],
    "wof:name":"All Clear Garden Services",
    "wof:placetype":"venue"
},
  "geometry": {"coordinates":[-0.400282,50.819336],"type":"Point"}
}