{
  "type": "Feature",
  "properties": {
    "iso:country":"GB",
    "sg:address":"Berry Farm, Scalloway",
    "sg:city":"Lerwick",
    "sg:classifiers":[
        {
            "category":"Farming",
            "subcategory":"Farm",
            "type":"Manufacturing & Wholesale Goods"
        }
    ],
    "sg:postcode":"ZE1 0UL",
    "sg:province":"Shetland Islands",
    "sg:tags":[
        "mixed",
        "crop"
    ],
    "wof:name":"Smith,James,",
    "wof:placetype":"venue"
},
  "geometry": {"coordinates":[-1.145224,60.151829],"type":"Point"}
}