{
  "type": "Feature",
  "properties": {
    "iso:country":"GB",
    "sg:address":"Glenmore Farm, Bullington End Road, Castlethorpe",
    "sg:city":"Milton Keynes",
    "sg:classifiers":[
        {
            "category":"Home & Garden",
            "subcategory":"Building Materials",
            "type":"Retail Goods"
        },
        {
            "category":"Building & Trades",
            "subcategory":"Construction",
            "type":"Services"
        }
    ],
    "sg:phone":"+44 1908 511169",
    "sg:postcode":"MK19 7ER",
    "sg:province":"Buckinghamshire",
    "sg:tags":[
        "fencing",
        "contractor"
    ],
    "wof:name":"I C Markham",
    "wof:placetype":"venue"
},
  "geometry": {"coordinates":[-0.8391709924,52.0926818848],"type":"Point"}
}