{
  "type": "Feature",
  "properties": {
    "addr:full":"Greylands Turfmoor, Egerley, Kinnerly Oswestry Shropshire SY10 8EW",
    "addr:postcode":"sy10 8ew",
    "iso:country":"GB",
    "sg:address":"Greylands Turfmoor, Egerley, Kinnerly",
    "sg:city":"Oswestry",
    "sg:classifiers":[
        {
            "category":"Building & Trades",
            "subcategory":"Landscaping Services",
            "type":"Services"
        }
    ],
    "sg:postcode":"SY10 8EW",
    "sg:province":"Shropshire",
    "sg:tags":[
        "landscape",
        "contractor"
    ],
    "wof:name":"Turfmoor Landscaping",
    "wof:placetype":"venue"
},
  "geometry": {"coordinates":[-2.9577100277,52.7647895813],"type":"Point"}
}