{
  "type": "Feature",
  "properties": {
    "iso:country":"GB",
    "sg:address":"Higher Tresawle Farm, Probus",
    "sg:city":"Truro",
    "sg:classifiers":[
        {
            "category":"Farming",
            "subcategory":"Livestock Farm",
            "type":"Manufacturing & Wholesale Goods"
        }
    ],
    "sg:phone":"+44 1872 520361",
    "sg:postcode":"TR2 4HN",
    "sg:province":"Cornwall",
    "sg:tags":[
        "others"
    ],
    "wof:name":"R D Withers",
    "wof:placetype":"venue"
},
  "geometry": {"coordinates":[-4.9554738998,50.2925796509],"type":"Point"}
}