{
  "type": "Feature",
  "properties": {
    "addr:full":"Quarter Cottage, Green Man Lane, Marholm Peterborough Cambridgeshire PE6 7HS",
    "addr:postcode":"pe6 7hs",
    "addr:street":"Green Man Lane",
    "iso:country":"GB",
    "sg:address":"Quarter Cottage, Green Man Lane, Marholm",
    "sg:city":"Peterborough",
    "sg:classifiers":[
        {
            "category":"Retail",
            "subcategory":"Repair Shop",
            "type":"Services"
        }
    ],
    "sg:postcode":"PE6 7HS",
    "sg:province":"Cambridgeshire",
    "sg:tags":[
        "radio",
        "television",
        "video"
    ],
    "wof:name":"A Videocare",
    "wof:placetype":"venue"
},
  "geometry": {"coordinates":[-0.304499,52.604851],"type":"Point"}
}