{
  "type": "Feature",
  "properties": {
    "iso:country":"GB",
    "sg:address":"27 High St",
    "sg:city":"York",
    "sg:classifiers":[
        {
            "category":"Food & Beverages",
            "subcategory":"Meat & Fish",
            "type":"Retail Goods"
        }
    ],
    "sg:phone":"+44 1423 322329",
    "sg:postcode":"YO5 9AW",
    "sg:province":"East Riding of Yorkshire",
    "sg:tags":[
        "butcher"
    ],
    "wof:name":"Stockhill Family Buthcers",
    "wof:placetype":"venue"
},
  "geometry": {"coordinates":[-1.395312,54.094933],"type":"Point"}
}