{
  "type": "Feature",
  "properties": {
    "iso:country":"GB",
    "sg:address":"Boundary Farm, Rainworth",
    "sg:city":"Mansfield",
    "sg:classifiers":[
        {
            "category":"Farming",
            "subcategory":"Farm",
            "type":"Manufacturing & Wholesale Goods"
        }
    ],
    "sg:postcode":"NG21 0HE",
    "sg:province":"Nottinghamshire",
    "sg:tags":[
        "mixed",
        "crop"
    ],
    "wof:name":"P R Gray",
    "wof:placetype":"venue"
},
  "geometry": {"coordinates":[-1.118713975,53.1182861328],"type":"Point"}
}