{
  "type": "Feature",
  "properties": {
    "iso:country":"GB",
    "sg:address":"496 Northolt Road",
    "sg:city":"Harrow",
    "sg:classifiers":[
        {
            "category":"Restaurant",
            "type":"Food & Drink"
        },
        {
            "category":"Bars & Pubs",
            "subcategory":"Wine Bar",
            "type":"Food & Drink"
        }
    ],
    "sg:phone":"+44 20 8426 6300",
    "sg:postcode":"HA2 8HA",
    "sg:province":"Greater London",
    "sg:tags":[
        "indian",
        "-"
    ],
    "wof:name":"Golden Sip",
    "wof:placetype":"venue"
},
  "geometry": {"coordinates":[-0.3623490036,51.5577697754],"type":"Point"}
}