{
  "type": "Feature",
  "properties": {
    "addr:full":"Diamond Hill Farm Bedale North Yorkshire DL8 1LS",
    "addr:postcode":"dl8 1ls",
    "addr:street":"Diamond",
    "iso:country":"GB",
    "sg:address":"Diamond Hill Farm",
    "sg:city":"Bedale",
    "sg:classifiers":[
        {
            "category":"Farming",
            "subcategory":"Farm",
            "type":"Manufacturing & Wholesale Goods"
        }
    ],
    "sg:postcode":"DL8 1LS",
    "sg:province":"North Yorkshire",
    "sg:tags":[
        "mixed",
        "crop"
    ],
    "wof:name":"J T Bell & Sons",
    "wof:placetype":"venue"
},
  "geometry": {"coordinates":[-1.592346,54.288811],"type":"Point"}
}