{
  "type": "Feature",
  "properties": {
    "addr:full":"Station Buildings, Station Road Cwmbran Monmouthshire NP44 1XH",
    "addr:postcode":"np44 1xh",
    "addr:street":"Station Road",
    "iso:country":"GB",
    "sg:address":"Station Buildings, Station Road",
    "sg:city":"Cwmbran",
    "sg:classifiers":[
        {
            "category":"Building & Trades",
            "subcategory":"Construction",
            "type":"Services"
        }
    ],
    "sg:phone":"+44 1633 860185",
    "sg:postcode":"NP44 1XH",
    "sg:province":"Monmouthshire",
    "sg:tags":[
        "builder",
        "contractor"
    ],
    "wof:name":"J & D Contractors (Gwent) Ltd.",
    "wof:placetype":"venue"
},
  "geometry": {"coordinates":[-3.023673,51.660748],"type":"Point"}
}