{
  "type": "Feature",
  "properties": {
    "addr:full":"35 New Hayes Road Stoke-on-trent Staffordshire ST6 5UF",
    "addr:housenumber":"35",
    "addr:postcode":"st6 5uf",
    "addr:street":"New Hayes Road",
    "iso:country":"GB",
    "sg:address":"35 New Hayes Road",
    "sg:city":"Stoke-on-trent",
    "sg:classifiers":[
        {
            "category":"Retail",
            "subcategory":"Repair Shop",
            "type":"Services"
        }
    ],
    "sg:phone":"+44 1782 817963",
    "sg:postcode":"ST6 5UF",
    "sg:province":"Staffordshire",
    "sg:tags":[
        "radio",
        "television",
        "video"
    ],
    "wof:name":"Dave Hall",
    "wof:placetype":"venue"
},
  "geometry": {"coordinates":[-2.2099699974,53.0642242432],"type":"Point"}
}