{
  "type": "Feature",
  "properties": {
    "iso:country":"GB",
    "sg:address":"55 Perrymount Road",
    "sg:city":"Haywards Heath",
    "sg:classifiers":[
        {
            "category":"Shopping",
            "subcategory":"Pharmacy",
            "type":"Retail Goods"
        }
    ],
    "sg:phone":"+44 1444 456699",
    "sg:postcode":"RH16 3BN",
    "sg:province":"East Sussex",
    "sg:tags":[
        "medicine",
        "therapy"
    ],
    "wof:name":"Haywards Heath Natural Therapy Rooms",
    "wof:placetype":"venue"
},
  "geometry": {"coordinates":[-0.103607,51.004204],"type":"Point"}
}