{
  "type": "Feature",
  "properties": {
    "addr:full":"20 Brookside Cramlington Northumberland NE23 7DL",
    "addr:housenumber":"20",
    "addr:postcode":"ne23 7dl",
    "addr:street":"Brookside;Northumberland",
    "iso:country":"GB",
    "sg:address":"20 Brookside",
    "sg:city":"Cramlington",
    "sg:classifiers":[
        {
            "category":"Building & Trades",
            "subcategory":"Construction",
            "type":"Services"
        }
    ],
    "sg:phone":"+44 191 250 0359",
    "sg:postcode":"NE23 7DL",
    "sg:province":"Northumberland",
    "sg:tags":[
        "builder"
    ],
    "wof:name":"N B Alexander",
    "wof:placetype":"venue"
},
  "geometry": {"coordinates":[-1.5909210443,55.0545196533],"type":"Point"}
}