{
  "type": "Feature",
  "properties": {
    "iso:country":"GB",
    "sg:address":"Harris Road",
    "sg:city":"Gosport",
    "sg:classifiers":[
        {
            "category":"Farming",
            "subcategory":"Nursery",
            "type":"Manufacturing & Wholesale Goods"
        }
    ],
    "sg:phone":"+44 1329 232095",
    "sg:postcode":"PO13 0UY",
    "sg:province":"Hampshire",
    "sg:tags":[
        "creche"
    ],
    "wof:name":"Haven Early Years Centre",
    "wof:placetype":"venue"
},
  "geometry": {"coordinates":[-1.1706240177,50.8281097412],"type":"Point"}
}