{
  "type": "Feature",
  "properties": {
    "addr:full":"163 Hamilton Avenue Surbiton Surrey KT6 7QA",
    "addr:housenumber":"163",
    "addr:postcode":"kt6 7qa",
    "addr:street":"Hamilton Avenue",
    "iso:country":"GB",
    "sg:address":"163 Hamilton Avenue",
    "sg:city":"Surbiton",
    "sg:classifiers":[
        {
            "category":"Building & Trades",
            "subcategory":"Landscaping Services",
            "type":"Services"
        }
    ],
    "sg:phone":"+44 20 8399 5959",
    "sg:postcode":"KT6 7QA",
    "sg:province":"Surrey",
    "sg:tags":[
        "gardening"
    ],
    "wof:name":"Garden Angels",
    "wof:placetype":"venue"
},
  "geometry": {"coordinates":[-0.282706,51.379784],"type":"Point"}
}