{
  "type": "Feature",
  "properties": {
    "iso:country":"GB",
    "sg:address":"5 Market Place",
    "sg:city":"Harleston",
    "sg:classifiers":[
        {
            "category":"Food & Beverages",
            "subcategory":"Bakery",
            "type":"Retail Goods"
        }
    ],
    "sg:phone":"+44 1379 854056",
    "sg:postcode":"IP20 9AD",
    "sg:province":"Norfolk",
    "sg:tags":[
        "shop",
        "baker"
    ],
    "wof:name":"The Tudor Bakehouse",
    "wof:placetype":"venue"
},
  "geometry": {"coordinates":[1.299041,52.401707],"type":"Point"}
}