{
  "type": "Feature",
  "properties": {
    "addr:full":"98 Gallows Hill Lane Abbots Langley Hertfordshire WD5 0BU",
    "addr:housenumber":"98",
    "addr:postcode":"wd5 0bu",
    "addr:street":"Gallows Hill Lane",
    "iso:country":"GB",
    "sg:address":"98 Gallows Hill Lane",
    "sg:city":"Abbots Langley",
    "sg:classifiers":[
        {
            "category":"Professional",
            "subcategory":"Engineering",
            "type":"Services"
        }
    ],
    "sg:postcode":"WD5 0BU",
    "sg:province":"Hertfordshire",
    "sg:tags":[
        "contractor",
        "electrical",
        "engineer"
    ],
    "wof:name":"Wheeler Services",
    "wof:placetype":"venue"
},
  "geometry": {"coordinates":[-0.4207339883,51.7032585144],"type":"Point"}
}