{
  "type": "Feature",
  "properties": {
    "addr:full":"201 Nab Lane Howden Clough, Birstall Batley West Yorkshire WF17 0HU",
    "addr:housenumber":"201",
    "addr:postcode":"wf17 0hu",
    "addr:street":"Nab Lane",
    "iso:country":"GB",
    "sg:address":"201 Nab Lane Howden Clough, Birstall",
    "sg:city":"Batley",
    "sg:classifiers":[
        {
            "category":"Retail",
            "subcategory":"Repair Shop",
            "type":"Services"
        },
        {
            "category":"Shopping",
            "subcategory":"Computers & Home Electronics",
            "type":"Retail Goods"
        }
    ],
    "sg:postcode":"WF17 0HU",
    "sg:province":"West Yorkshire",
    "sg:tags":[
        "upholsterer"
    ],
    "wof:name":"Prime Upholstery",
    "wof:placetype":"venue"
},
  "geometry": {"coordinates":[-1.6446809769,53.7382736206],"type":"Point"}
}