{
  "type": "Feature",
  "properties": {
    "iso:country":"GB",
    "sg:address":"456 New Hall Lane",
    "sg:city":"Preston",
    "sg:classifiers":[
        {
            "category":"Fast Food",
            "type":"Food & Drink"
        },
        {
            "category":"Food & Beverages",
            "subcategory":"Meat & Fish",
            "type":"Retail Goods"
        }
    ],
    "sg:postcode":"PR1 4TA",
    "sg:province":"Lancashire",
    "sg:tags":[
        "shop",
        "chip"
    ],
    "wof:name":"Hesketh Chippy",
    "wof:placetype":"venue"
},
  "geometry": {"coordinates":[-2.6635890007,53.7657394409],"type":"Point"}
}