{
  "type": "Feature",
  "properties": {
    "addr:full":"London Rd Bracknell Berkshire RG12 9FR",
    "addr:postcode":"rg12 9fr",
    "addr:street":"London Rd",
    "iso:country":"GB",
    "sg:address":"London Rd",
    "sg:city":"Bracknell",
    "sg:classifiers":[
        {
            "category":"Travel",
            "subcategory":"Hotels & Motels",
            "type":"Entertainment"
        }
    ],
    "sg:phone":"+44 1344 428367",
    "sg:postcode":"RG12 9FR",
    "sg:province":"Berkshire",
    "sg:tags":[
        "house",
        "guest"
    ],
    "wof:name":"Deepfold Farm",
    "wof:placetype":"venue"
},
  "geometry": {"coordinates":[-0.7242040038,51.4127502441],"type":"Point"}
}