{
  "type": "Feature",
  "properties": {
    "addr:full":"34a Black Moor Road Verwood Dorset BH31 6BB",
    "addr:housenumber":"34a",
    "addr:postcode":"bh31 6bb",
    "addr:street":"Black Moor Road",
    "iso:country":"GB",
    "sg:address":"34a Black Moor Road",
    "sg:city":"Verwood",
    "sg:classifiers":[
        {
            "category":"Shopping",
            "subcategory":"Gifts & Souvenirs",
            "type":"Retail Goods"
        }
    ],
    "sg:phone":"+44 1202 825155",
    "sg:postcode":"BH31 6BB",
    "sg:province":"Dorset",
    "sg:tags":[
        "giftware"
    ],
    "wof:name":"Honeycombe 78 Ltd.",
    "wof:placetype":"venue"
},
  "geometry": {"coordinates":[-1.853182,50.868843],"type":"Point"}
}