{
  "type": "Feature",
  "properties": {
    "iso:country":"GB",
    "sg:address":"5 Parklands View, Sketty",
    "sg:city":"Swansea",
    "sg:classifiers":[
        {
            "category":"Home & Garden",
            "subcategory":"Building Materials",
            "type":"Retail Goods"
        }
    ],
    "sg:phone":"+44 1792 207590",
    "sg:postcode":"SA2 8LX",
    "sg:province":"Swansea",
    "sg:tags":[
        "insulation",
        "installers"
    ],
    "wof:name":"Hill Insulation",
    "wof:placetype":"venue"
},
  "geometry": {"coordinates":[-4.0001168251,51.6154327393],"type":"Point"}
}