{
  "type": "Feature",
  "properties": {
    "addr:full":"North Hill, Trebartha Launceston Cornwall PL15 7PD",
    "addr:postcode":"pl15 7pd",
    "addr:street":"Hill",
    "iso:country":"GB",
    "sg:address":"North Hill, Trebartha",
    "sg:city":"Launceston",
    "sg:classifiers":[
        {
            "category":"Farming",
            "subcategory":"Livestock Farm",
            "type":"Manufacturing & Wholesale Goods"
        }
    ],
    "sg:postcode":"PL15 7PD",
    "sg:province":"Cornwall",
    "sg:tags":[
        "others"
    ],
    "wof:name":"Peter J Randall",
    "wof:placetype":"venue"
},
  "geometry": {"coordinates":[-4.441444,50.563454],"type":"Point"}
}