{
  "type": "Feature",
  "properties": {
    "addr:full":"W H Offices, Bodffordd Llangefni Gwynedd LL77 7DZ",
    "addr:postcode":"ll77 7dz",
    "addr:street":"W;Llangefni",
    "iso:country":"GB",
    "sg:address":"W H Offices, Bodffordd",
    "sg:city":"Llangefni",
    "sg:classifiers":[
        {
            "category":"Professional",
            "subcategory":"Engineering",
            "type":"Services"
        }
    ],
    "sg:phone":"+44 1248 750193",
    "sg:postcode":"LL77 7DZ",
    "sg:province":"Gwynedd",
    "sg:tags":[
        "civil",
        "engineer"
    ],
    "sg:website":"http://www.williamhughes.com",
    "wof:name":"William Hughes Civil Engineering Ltd",
    "wof:placetype":"venue"
},
  "geometry": {"coordinates":[-4.3131690025,53.2559509277],"type":"Point"}
}