{
  "type": "Feature",
  "properties": {
    "addr:full":"Dimbles Lane Lichfield Staffordshire WS13 7HT",
    "addr:postcode":"ws13 7ht",
    "addr:street":"Dimbles Lane",
    "iso:country":"GB",
    "sg:address":"Dimbles Lane",
    "sg:city":"Lichfield",
    "sg:classifiers":[
        {
            "category":"Health Services",
            "subcategory":"Doctor",
            "type":"Services"
        },
        {
            "category":"Health Services",
            "subcategory":"Clinic",
            "type":"Services"
        }
    ],
    "sg:phone":"+44 1543 258982",
    "sg:postcode":"WS13 7HT",
    "sg:province":"Staffordshire",
    "sg:tags":[
        "nh",
        "practitioners"
    ],
    "wof:name":"St.Chads Health Centre",
    "wof:placetype":"venue"
},
  "geometry": {"coordinates":[-1.833199,52.695686],"type":"Point"}
}