{
  "type": "Feature",
  "properties": {
    "iso:country":"GB",
    "sg:address":"Pools Platt Farm, Pools Platt Lane, Antrobus",
    "sg:city":"Northwich",
    "sg:classifiers":[
        {
            "category":"Farming",
            "subcategory":"Farm",
            "type":"Manufacturing & Wholesale Goods"
        }
    ],
    "sg:phone":"+44 1565 777283",
    "sg:postcode":"CW9 6JU",
    "sg:province":"Cheshire",
    "sg:tags":[
        "mixed",
        "crop"
    ],
    "wof:name":"B T Maddock",
    "wof:placetype":"venue"
},
  "geometry": {"coordinates":[-2.536402,53.313129],"type":"Point"}
}