{
  "type": "Feature",
  "properties": {
    "addr:full":"Unit 15, St Andrews Industrial Estate Birmingham West Midlands B9 4QB",
    "addr:housenumber":"unit 15",
    "addr:postcode":"b9 4qb",
    "addr:street":"St Andrews Industrial Estate",
    "iso:country":"GB",
    "sg:address":"Unit 15, St Andrews Industrial Estate",
    "sg:city":"Birmingham",
    "sg:classifiers":[
        {
            "category":"Professional",
            "subcategory":"Engineering",
            "type":"Services"
        },
        {
            "category":"Wholesale",
            "subcategory":"Machinery & Supplies",
            "type":"Manufacturing & Wholesale Goods"
        }
    ],
    "sg:phone":"+44 121 772 4414",
    "sg:postcode":"B9 4QB",
    "sg:province":"West Midlands",
    "sg:tags":[
        "equipment",
        "pneumatic",
        "system"
    ],
    "wof:name":"Prestision",
    "wof:placetype":"venue"
},
  "geometry": {"coordinates":[-1.8715889454,52.4770851135],"type":"Point"}
}