{
  "type": "Feature",
  "properties": {
    "iso:country":"GB",
    "sg:address":"Unit 10 Masthead Capstan Court, Crossways Business Park",
    "sg:city":"Dartford",
    "sg:classifiers":[
        {
            "category":"Freight",
            "type":"Transportation"
        }
    ],
    "sg:phone":"+44 1322 288873",
    "sg:postcode":"DA2 6QG",
    "sg:province":"Kent",
    "sg:tags":[
        "haulage",
        "road"
    ],
    "wof:name":"Stuart Curtis Haulage Ltd.",
    "wof:placetype":"venue"
},
  "geometry": {"coordinates":[0.2518349886,51.4565849304],"type":"Point"}
}