{
  "type": "Feature",
  "properties": {
    "iso:country":"GB",
    "sg:address":"2nd Floor 225 Bury New Rd",
    "sg:city":"Manchester",
    "sg:classifiers":[
        {
            "category":"Travel",
            "subcategory":"Travel Agent",
            "type":"Entertainment"
        }
    ],
    "sg:phone":"+44 161 766 5000",
    "sg:postcode":"M45 8GW",
    "sg:province":"Lancashire",
    "wof:name":"Destinair Travel Ltd",
    "wof:placetype":"venue"
},
  "geometry": {"coordinates":[-2.2960019112,53.5511474609],"type":"Point"}
}