{
  "type": "Feature",
  "properties": {
    "iso:country":"GB",
    "sg:address":"22 The Parade, Oadby",
    "sg:city":"Leicester",
    "sg:classifiers":[
        {
            "category":"Professional",
            "subcategory":"Lawyer & Legal Services",
            "type":"Services"
        }
    ],
    "sg:phone":"+44 116 271 4129",
    "sg:postcode":"LE2 5BF",
    "sg:province":"Leicestershire",
    "sg:tags":[
        "conveyancing",
        "solicitor"
    ],
    "wof:name":"Harvey Ingram Owston",
    "wof:placetype":"venue"
},
  "geometry": {"coordinates":[-1.083926,52.599182],"type":"Point"}
}