{
  "type": "Feature",
  "properties": {
    "addr:full":"92-116 Helen St Glasgow Glasgow City G51 3LH",
    "addr:housenumber":"92-116",
    "addr:postcode":"g51 3lh",
    "addr:street":"Helen St",
    "iso:country":"GB",
    "sg:address":"92-116 Helen St",
    "sg:city":"Glasgow",
    "sg:classifiers":[
        {
            "category":"Manufacturing",
            "subcategory":"Building Materials",
            "type":"Manufacturing & Wholesale Goods"
        }
    ],
    "sg:phone":"+44 141 445 5252",
    "sg:postcode":"G51 3LH",
    "sg:province":"Glasgow City",
    "sg:tags":[
        "merchant",
        "builder"
    ],
    "wof:name":"Jewson Ltd",
    "wof:placetype":"venue"
},
  "geometry": {"coordinates":[-4.313737,55.860306],"type":"Point"}
}