{
  "type": "Feature",
  "properties": {
    "addr:full":"51 London Road, Stapleford Cambridge Cambridgeshire CB2 5DG",
    "addr:housenumber":"51",
    "addr:postcode":"cb2 5dg",
    "addr:street":"London Road",
    "iso:country":"GB",
    "sg:address":"51 London Road, Stapleford",
    "sg:city":"Cambridge",
    "sg:classifiers":[
        {
            "category":"Professional",
            "subcategory":"Art Services",
            "type":"Services"
        }
    ],
    "sg:phone":"+44 1223 845550",
    "sg:postcode":"CB2 5DG",
    "sg:province":"Cambridgeshire",
    "sg:tags":[
        "graphic",
        "designer"
    ],
    "wof:name":"C B A Design",
    "wof:placetype":"venue"
},
  "geometry": {"coordinates":[0.094286,52.142838],"type":"Point"}
}