{
  "type": "Feature",
  "properties": {
    "addr:full":"Gardner Road Guildford Surrey GU1 4PG",
    "addr:postcode":"gu1 4pg",
    "addr:street":"Gardner Road",
    "iso:country":"GB",
    "sg:address":"Gardner Road",
    "sg:city":"Guildford",
    "sg:classifiers":[
        {
            "category":"Retail",
            "subcategory":"Veterinary Services",
            "type":"Services"
        }
    ],
    "sg:phone":"+44 1483 504156",
    "sg:postcode":"GU1 4PG",
    "sg:province":"Surrey",
    "sg:tags":[
        "surgeon"
    ],
    "wof:name":"Gayton Veterinary Centre",
    "wof:placetype":"venue"
},
  "geometry": {"coordinates":[-0.5750880241,51.2433624268],"type":"Point"}
}