{
  "type": "Feature",
  "properties": {
    "addr:full":"College Street Northampton Northamptonshire NN1 2QP",
    "addr:postcode":"nn1 2qp",
    "addr:street":"College Street",
    "iso:country":"GB",
    "sg:address":"College Street",
    "sg:city":"Northampton",
    "sg:classifiers":[
        {
            "category":"Farming",
            "subcategory":"Nursery",
            "type":"Manufacturing & Wholesale Goods"
        }
    ],
    "sg:postcode":"NN1 2QP",
    "sg:province":"Northamptonshire",
    "sg:tags":[
        "creche"
    ],
    "wof:name":"Tracey Sales",
    "wof:placetype":"venue"
},
  "geometry": {"coordinates":[-0.89838,52.238079],"type":"Point"}
}