{
  "type": "Feature",
  "properties": {
    "addr:full":"15 Newhall Street Cannock Staffordshire WS11 1AB",
    "addr:housenumber":"15",
    "addr:postcode":"ws11 1ab",
    "addr:street":"Newhall Street",
    "iso:country":"GB",
    "sg:address":"15 Newhall Street",
    "sg:city":"Cannock",
    "sg:classifiers":[
        {
            "category":"Health Services",
            "subcategory":"Podiatrist",
            "type":"Services"
        }
    ],
    "sg:postcode":"WS11 1AB",
    "sg:province":"Staffordshire",
    "sg:tags":[
        "podiatrists",
        "chiropodist"
    ],
    "wof:name":"C J Bradbury",
    "wof:placetype":"venue"
},
  "geometry": {"coordinates":[-2.033053,52.688755],"type":"Point"}
}