{
  "type": "Feature",
  "properties": {
    "addr:full":"1st Uxbridge Scout Hut, Rockingham Road Uxbridge Buckinghamshire UB8 2UW",
    "addr:postcode":"ub8 2uw",
    "addr:street":"Rockingham Road",
    "iso:country":"GB",
    "sg:address":"1st Uxbridge Scout Hut, Rockingham Road",
    "sg:city":"Uxbridge",
    "sg:classifiers":[
        {
            "category":"Education",
            "subcategory":"Preschool",
            "type":"Public Place"
        }
    ],
    "sg:phone":"+44 1895 255479",
    "sg:postcode":"UB8 2UW",
    "sg:province":"Buckinghamshire",
    "sg:tags":[
        "pre-school",
        "playgroups"
    ],
    "wof:name":"Once upon A Time Day Nursery",
    "wof:placetype":"venue"
},
  "geometry": {"coordinates":[-0.4745360017,51.5440711975],"type":"Point"}
}