{
  "type": "Feature",
  "properties": {
    "addr:full":"23 Silver Street Kettering Northamptonshire NN16 0BN",
    "addr:housenumber":"23",
    "addr:postcode":"nn16 0bn",
    "addr:street":"Silver Street",
    "iso:country":"GB",
    "sg:address":"23 Silver Street",
    "sg:city":"Kettering",
    "sg:classifiers":[
        {
            "category":"Shopping",
            "subcategory":"Baby Store",
            "type":"Retail Goods"
        }
    ],
    "sg:phone":"+44 1536 524564",
    "sg:postcode":"NN16 0BN",
    "sg:province":"Northamptonshire",
    "sg:tags":[
        "babywear",
        "childrens"
    ],
    "wof:name":"Malcolm& Patricia Bellamy",
    "wof:placetype":"venue"
},
  "geometry": {"coordinates":[-0.726015985,52.4008407593],"type":"Point"}
}