{
  "type": "Feature",
  "properties": {
    "addr:full":"Willow Ho, Stanneylands Rd Wilmslow Cheshire SK9 4EJ",
    "addr:postcode":"sk9 4ej",
    "addr:street":"Stanneylands Rd",
    "iso:country":"GB",
    "sg:address":"Willow Ho, Stanneylands Rd",
    "sg:city":"Wilmslow",
    "sg:classifiers":[
        {
            "category":"Manufacturing",
            "subcategory":"Petroleum Products",
            "type":"Manufacturing & Wholesale Goods"
        }
    ],
    "sg:phone":"+44 1625 549449",
    "sg:postcode":"SK9 4EJ",
    "sg:province":"Cheshire",
    "sg:tags":[
        "lubricant"
    ],
    "wof:name":"Ebony Solutions",
    "wof:placetype":"venue"
},
  "geometry": {"coordinates":[-2.2277638912,53.3434066772],"type":"Point"}
}