{
  "type": "Feature",
  "properties": {
    "addr:full":"Court Lane Estate, Court Lane Iver Berkshire SL0 9HL",
    "addr:postcode":"sl0 9hl",
    "addr:street":"Court Lane Estate Court Lane",
    "iso:country":"GB",
    "sg:address":"Court Lane Estate, Court Lane",
    "sg:city":"Iver",
    "sg:classifiers":[
        {
            "category":"Building & Trades",
            "subcategory":"Construction",
            "type":"Services"
        },
        {
            "category":"Manufacturing",
            "subcategory":"Building Materials",
            "type":"Manufacturing & Wholesale Goods"
        }
    ],
    "sg:phone":"+44 1753 650507",
    "sg:postcode":"SL0 9HL",
    "sg:province":"Berkshire",
    "sg:tags":[
        "mnfr",
        "specialist",
        "tiling",
        "marble",
        "contractor"
    ],
    "wof:name":"Classico Marble & Tiling Ltd.",
    "wof:placetype":"venue"
},
  "geometry": {"coordinates":[-0.5105739832,51.5206985474],"type":"Point"}
}