{
  "type": "Feature",
  "properties": {
    "addr:full":"1st Floor, Western Section, 1/3 Brixton Road London Greater London SW9 6DE",
    "addr:housenumber":"1 / 3",
    "addr:postcode":"sw9 6de",
    "addr:street":"Western;Brixton Road",
    "iso:country":"GB",
    "sg:address":"1st Floor, Western Section, 1/3 Brixton Road",
    "sg:city":"London",
    "sg:classifiers":[
        {
            "category":"Organizations",
            "subcategory":"Non-profit Organization",
            "type":"Services"
        }
    ],
    "sg:phone":"+44 20 7587 0214",
    "sg:postcode":"SW9 6DE",
    "sg:province":"Greater London",
    "sg:tags":[
        "organisation",
        "voluntary",
        "charity"
    ],
    "wof:name":"Ssaffa",
    "wof:placetype":"venue"
},
  "geometry": {"coordinates":[-0.1109900028,51.4797096252],"type":"Point"}
}