{
  "type": "Feature",
  "properties": {
    "iso:country":"GB",
    "sg:address":"236 City Road",
    "sg:city":"Cardiff",
    "sg:classifiers":[
        {
            "category":"Restaurant",
            "type":"Food & Drink"
        }
    ],
    "sg:postcode":"CF24 3JJ",
    "sg:province":"Cardiff",
    "wof:name":"Shaun Shah",
    "wof:placetype":"venue"
},
  "geometry": {"coordinates":[-3.171262,51.492157],"type":"Point"}
}