{
  "type": "Feature",
  "properties": {
    "addr:full":"4 Westhill Terr Newton Abbot Devon TQ12 5EJ",
    "addr:housenumber":"4",
    "addr:postcode":"tq12 5ej",
    "addr:street":"Westhill Terr",
    "iso:country":"GB",
    "sg:address":"4 Westhill Terr",
    "sg:city":"Newton Abbot",
    "sg:classifiers":[
        {
            "category":"Home & Garden",
            "subcategory":"Building Materials",
            "type":"Retail Goods"
        }
    ],
    "sg:phone":"+44 1803 556320",
    "sg:postcode":"TQ12 5EJ",
    "sg:province":"Devon",
    "sg:tags":[
        "fencing"
    ],
    "wof:name":"Torbay Fencing",
    "wof:placetype":"venue"
},
  "geometry": {"coordinates":[-3.5779941082,50.5005607605],"type":"Point"}
}