{
  "type": "Feature",
  "properties": {
    "addr:full":"29 Lutterworth Road Leicester Leicestershire LE2 8PH",
    "addr:housenumber":"29",
    "addr:postcode":"le2 8ph",
    "addr:street":"Lutterworth Road",
    "iso:country":"GB",
    "sg:address":"29 Lutterworth Road",
    "sg:city":"Leicester",
    "sg:classifiers":[
        {
            "category":"Retail",
            "subcategory":"Auto Repair",
            "type":"Services"
        }
    ],
    "sg:postcode":"LE2 8PH",
    "sg:province":"Leicestershire",
    "sg:tags":[
        "modification",
        "garage"
    ],
    "wof:name":"Robinsons Garage Used Cars",
    "wof:placetype":"venue"
},
  "geometry": {"coordinates":[-1.1575280428,52.6011543274],"type":"Point"}
}