{
  "type": "Feature",
  "properties": {
    "iso:country":"GB",
    "sg:address":"Syke Breck Farm, Blidworth La",
    "sg:city":"Mansfield",
    "sg:classifiers":[
        {
            "category":"Farming",
            "subcategory":"Farm",
            "type":"Manufacturing & Wholesale Goods"
        }
    ],
    "sg:phone":"+44 1623 792426",
    "sg:postcode":"NG21 0NZ",
    "sg:province":"Nottinghamshire",
    "sg:tags":[
        "egg",
        "producer"
    ],
    "wof:name":"P W Baker",
    "wof:placetype":"venue"
},
  "geometry": {"coordinates":[-1.1174639463,53.0990791321],"type":"Point"}
}