{
  "type": "Feature",
  "properties": {
    "iso:country":"GB",
    "sg:address":"60 Greenholm Road",
    "sg:city":"Birmingham",
    "sg:classifiers":[
        {
            "category":"Cafe",
            "type":"Food & Drink"
        }
    ],
    "sg:phone":"+44 121 356 0509",
    "sg:postcode":"B44 8HL",
    "sg:province":"West Midlands",
    "sg:tags":[
        "tea",
        "snack",
        "bar",
        "room"
    ],
    "wof:name":"Marlboro Cafe",
    "wof:placetype":"venue"
},
  "geometry": {"coordinates":[-1.8926999569,52.5356063843],"type":"Point"}
}