{
  "type": "Feature",
  "properties": {
    "addr:full":"Unit 2 Salter St Willesden Greater London NW10 6UN",
    "addr:housenumber":"unit 2",
    "addr:postcode":"nw10 6un",
    "addr:street":"Salter St",
    "iso:country":"GB",
    "sg:address":"Unit 2 Salter St",
    "sg:city":"Willesden",
    "sg:classifiers":[
        {
            "category":"Shopping",
            "subcategory":"Stationery & Office Supplies",
            "type":"Retail Goods"
        }
    ],
    "sg:phone":"+44 20 8960 4368",
    "sg:postcode":"NW10 6UN",
    "sg:province":"Greater London",
    "sg:tags":[
        "printers'"
    ],
    "wof:name":"Special Display Services",
    "wof:placetype":"venue"
},
  "geometry": {"coordinates":[-0.2404289991,51.5284156799],"type":"Point"}
}