{
  "type": "Feature",
  "properties": {
    "addr:full":"Newport Road, Hanslope Milton Keynes Buckinghamshire MK19 7ND",
    "addr:postcode":"mk19 7nd",
    "addr:street":"Newport Road",
    "iso:country":"GB",
    "sg:address":"Newport Road, Hanslope",
    "sg:city":"Milton Keynes",
    "sg:classifiers":[
        {
            "category":"Professional",
            "subcategory":"Computer Services",
            "type":"Services"
        }
    ],
    "sg:postcode":"MK19 7ND",
    "sg:province":"Buckinghamshire",
    "sg:tags":[
        "bureau",
        "facility"
    ],
    "wof:name":"Myriad I T Services",
    "wof:placetype":"venue"
},
  "geometry": {"coordinates":[-0.827989,52.115139],"type":"Point"}
}