{
  "type": "Feature",
  "properties": {
    "addr:full":"8 Upper Wimpole Street West End Hampshire W1M 7TD",
    "addr:housenumber":"8",
    "addr:postcode":"w1m 7td",
    "addr:street":"Upper Wimpole Street",
    "iso:country":"GB",
    "sg:address":"8 Upper Wimpole Street",
    "sg:city":"West End",
    "sg:classifiers":[
        {
            "category":"Health Services",
            "subcategory":"Hospital",
            "type":"Services"
        }
    ],
    "sg:phone":"+44 20 7486 8366",
    "sg:postcode":"W1M 7TD",
    "sg:province":"Hampshire",
    "wof:name":"Dr Charlotte Cowie",
    "wof:placetype":"venue"
},
  "geometry": {"coordinates":[-0.1389899999,51.5075798035],"type":"Point"}
}