{
  "type": "Feature",
  "properties": {
    "addr:full":"Dormston Trading Estate, Burton Road Dudley West Midlands DY1 2UF",
    "addr:postcode":"dy1 2uf",
    "addr:street":"Burton Road",
    "iso:country":"GB",
    "sg:address":"Dormston Trading Estate, Burton Road",
    "sg:city":"Dudley",
    "sg:classifiers":[
        {
            "category":"Home & Garden",
            "subcategory":"Furniture",
            "type":"Retail Goods"
        },
        {
            "category":"Military Area",
            "subcategory":"Air Force Base",
            "type":"Public Place"
        }
    ],
    "sg:postcode":"DY1 2UF",
    "sg:province":"West Midlands",
    "sg:tags":[
        "supplier",
        "mnfrs",
        "plaster"
    ],
    "wof:name":"Studio Four Regency",
    "wof:placetype":"venue"
},
  "geometry": {"coordinates":[-2.1115300655,52.5239601135],"type":"Point"}
}