{
  "type": "Feature",
  "properties": {
    "iso:country":"GB",
    "sg:address":"The Mill House, Lower Trevigoe, St Minver",
    "sg:city":"Wadebridge",
    "sg:classifiers":[
        {
            "category":"Farming",
            "subcategory":"Dairy Farm",
            "type":"Manufacturing & Wholesale Goods"
        }
    ],
    "sg:phone":"+44 1208 880586",
    "sg:postcode":"PL27 6RB",
    "sg:province":"Cornwall",
    "wof:name":"Peter A Vernon",
    "wof:placetype":"venue"
},
  "geometry": {"coordinates":[-4.87822,50.5811],"type":"Point"}
}