{
  "type": "Feature",
  "properties": {
    "iso:country":"GB",
    "sg:address":"12 Augusta Place",
    "sg:city":"Leamington Spa",
    "sg:classifiers":[
        {
            "category":"Bars & Pubs",
            "type":"Food & Drink"
        }
    ],
    "sg:postcode":"CV32 5EL",
    "sg:province":"Warwickshire",
    "sg:tags":[
        "pubs",
        "inn"
    ],
    "wof:name":"The Willoughby",
    "wof:placetype":"venue"
},
  "geometry": {"coordinates":[-1.538079,52.289585],"type":"Point"}
}