{
  "type": "Feature",
  "properties": {
    "addr:full":"Little Cwm Llechwedd, Llanbister Llandrindod Wells Powys LD1 6UG",
    "addr:postcode":"ld1 6ug",
    "addr:street":"Llandrindod Wells",
    "iso:country":"GB",
    "sg:address":"Little Cwm Llechwedd, Llanbister",
    "sg:city":"Llandrindod Wells",
    "sg:classifiers":[
        {
            "category":"Farming",
            "subcategory":"Livestock Farm",
            "type":"Manufacturing & Wholesale Goods"
        },
        {
            "category":"Farming",
            "subcategory":"Farm",
            "type":"Manufacturing & Wholesale Goods"
        }
    ],
    "sg:phone":"+44 1597 840218",
    "sg:postcode":"LD1 6UG",
    "sg:province":"Powys",
    "sg:tags":[
        "mixed",
        "crop",
        "others"
    ],
    "wof:name":"A Hardwich & Son",
    "wof:placetype":"venue"
},
  "geometry": {"coordinates":[-3.310491,52.351078],"type":"Point"}
}