{
  "type": "Feature",
  "properties": {
    "iso:country":"GB",
    "sg:address":"Lings Forum",
    "sg:city":"Northampton",
    "sg:classifiers":[
        {
            "category":"Cinema",
            "subcategory":"Movie Theater",
            "type":"Entertainment"
        }
    ],
    "sg:phone":"+44 1604 401006",
    "sg:postcode":"NN3 8JR",
    "sg:province":"Northamptonshire",
    "wof:name":"Forum Cinema",
    "wof:placetype":"venue"
},
  "geometry": {"coordinates":[-0.827538,52.273132],"type":"Point"}
}