{
  "type": "Feature",
  "properties": {
    "addr:full":"18 Akenside Terr Newcastle-upon-tyne Tyne and Wear NE2 1TN",
    "addr:housenumber":"18",
    "addr:postcode":"ne2 1tn",
    "addr:street":"Akenside Terr",
    "iso:country":"GB",
    "sg:address":"18 Akenside Terr",
    "sg:city":"Newcastle-upon-tyne",
    "sg:classifiers":[
        {
            "category":"Social Services",
            "subcategory":"Retirement Home",
            "type":"Services"
        }
    ],
    "sg:postcode":"NE2 1TN",
    "sg:province":"Tyne and Wear",
    "sg:tags":[
        "residential",
        "care"
    ],
    "wof:name":"Patterson,Bobby,",
    "wof:placetype":"venue"
},
  "geometry": {"coordinates":[-1.600721,54.985477],"type":"Point"}
}