{
  "type": "Feature",
  "properties": {
    "addr:full":"2-3 Pride Hill Shrewsbury Shropshire SY1 1DB",
    "addr:housenumber":"2-3",
    "addr:postcode":"sy1 1db",
    "addr:street":"Pride Hill",
    "iso:country":"GB",
    "sg:address":"2-3 Pride Hill",
    "sg:city":"Shrewsbury",
    "sg:classifiers":[
        {
            "category":"Shopping",
            "subcategory":"Clothing, Apparel, & Fashions",
            "type":"Retail Goods"
        }
    ],
    "sg:phone":"+44 1743 236501",
    "sg:postcode":"SY1 1DB",
    "sg:province":"Shropshire",
    "sg:tags":[
        "shop"
    ],
    "wof:name":"Principles",
    "wof:placetype":"venue"
},
  "geometry": {"coordinates":[-2.754272,52.708344],"type":"Point"}
}