{
  "type": "Feature",
  "properties": {
    "addr:full":"7 Horton Road Gloucester Gloucestershire GL1 3PX",
    "addr:housenumber":"7",
    "addr:postcode":"gl1 3px",
    "addr:street":"Horton Road",
    "iso:country":"GB",
    "sg:address":"7 Horton Road",
    "sg:city":"Gloucester",
    "sg:classifiers":[
        {
            "category":"Social Services",
            "subcategory":"Retirement Home",
            "type":"Services"
        }
    ],
    "sg:phone":"+44 1452 530004",
    "sg:postcode":"GL1 3PX",
    "sg:province":"Gloucestershire",
    "sg:tags":[
        "residential",
        "care"
    ],
    "wof:name":"Mayfield",
    "wof:placetype":"venue"
},
  "geometry": {"coordinates":[-2.2264521122,51.8674049377],"type":"Point"}
}