{
  "type": "Feature",
  "properties": {
    "iso:country":"GB",
    "sg:address":"Penrhyn Avenue",
    "sg:city":"Bangor",
    "sg:classifiers":[
        {
            "category":"Health Services",
            "subcategory":"Nursing And Care Facility",
            "type":"Services"
        },
        {
            "category":"Social Services",
            "subcategory":"Retirement Home",
            "type":"Services"
        }
    ],
    "sg:phone":"+44 1248 351827",
    "sg:postcode":"LL57 1LT",
    "sg:province":"Gwynedd",
    "sg:tags":[
        "residential"
    ],
    "wof:name":"Plas Hedd",
    "wof:placetype":"venue"
},
  "geometry": {"coordinates":[-4.1111011505,53.2271461487],"type":"Point"}
}