{
  "type": "Feature",
  "properties": {
    "addr:full":"31 Vesta Avenue St Albans Hertfordshire AL1 2PG",
    "addr:housenumber":"31",
    "addr:postcode":"al1 2pg",
    "addr:street":"Vesta Avenue",
    "iso:country":"GB",
    "sg:address":"31 Vesta Avenue",
    "sg:city":"St Albans",
    "sg:classifiers":[
        {
            "category":"Home & Garden",
            "subcategory":"Home Furnishings",
            "type":"Retail Goods"
        }
    ],
    "sg:phone":"+44 1727 848780",
    "sg:postcode":"AL1 2PG",
    "sg:province":"Hertfordshire",
    "sg:tags":[
        "blind",
        "manufacture",
        "fitting",
        "curtain"
    ],
    "wof:name":"A Stitch In Time",
    "wof:placetype":"venue"
},
  "geometry": {"coordinates":[-0.344392,51.739086],"type":"Point"}
}