{
  "type": "Feature",
  "properties": {
    "addr:full":"29a Main Street Glasgow Glasgow City G40 1QA",
    "addr:housenumber":"29a",
    "addr:postcode":"g40 1qa",
    "addr:street":"Main Street",
    "iso:country":"GB",
    "sg:address":"29a Main Street",
    "sg:city":"Glasgow",
    "sg:classifiers":[
        {
            "category":"Food & Beverages",
            "subcategory":"Meat & Fish",
            "type":"Retail Goods"
        }
    ],
    "sg:phone":"+44 141 554 4914",
    "sg:postcode":"G40 1QA",
    "sg:province":"Glasgow City",
    "sg:tags":[
        "butcher"
    ],
    "wof:name":"David Cox",
    "wof:placetype":"venue"
},
  "geometry": {"coordinates":[-4.2264370918,55.8480072021],"type":"Point"}
}