{
  "type": "Feature",
  "properties": {
    "addr:full":"Old Tye Avenue, Biggin Hill Westerham Kent TN16 3LY",
    "addr:postcode":"tn16 3ly",
    "addr:street":"Old Tye Avenue",
    "iso:country":"GB",
    "sg:address":"Old Tye Avenue, Biggin Hill",
    "sg:city":"Westerham",
    "sg:classifiers":[
        {
            "category":"Education",
            "subcategory":"School",
            "type":"Public Place"
        },
        {
            "category":"Government",
            "subcategory":"Office",
            "type":"Public Place"
        }
    ],
    "sg:phone":"+44 1959 572265",
    "sg:postcode":"TN16 3LY",
    "sg:province":"Kent",
    "sg:tags":[
        "local",
        "authority"
    ],
    "wof:name":"Biggin Hill Infants School",
    "wof:placetype":"venue"
},
  "geometry": {"coordinates":[0.0403620005,51.315574646],"type":"Point"}
}