{
  "type": "Feature",
  "properties": {
    "addr:full":"1 Dexter Street Liverpool Merseyside L8 1UT",
    "addr:housenumber":"1",
    "addr:postcode":"l8 1ut",
    "addr:street":"Dexter Street",
    "iso:country":"GB",
    "sg:address":"1 Dexter Street",
    "sg:city":"Liverpool",
    "sg:classifiers":[
        {
            "category":"Sports & Exercise",
            "subcategory":"Tennis Court",
            "type":"Entertainment"
        }
    ],
    "sg:phone":"+44 151 708 7922",
    "sg:postcode":"L8 1UT",
    "sg:province":"Merseyside",
    "sg:tags":[
        "breakdown",
        "recovery"
    ],
    "wof:name":"Eagle Recovery Service",
    "wof:placetype":"venue"
},
  "geometry": {"coordinates":[-2.9727940559,53.3937644958],"type":"Point"}
}