{
  "type": "Feature",
  "properties": {
    "addr:full":"20 Celandine Close, Marton Manor Middlesbrough North Yorkshire TS7 8RX",
    "addr:housenumber":"20",
    "addr:postcode":"ts7 8rx",
    "addr:street":"Celandine Close",
    "iso:country":"GB",
    "sg:address":"20 Celandine Close, Marton Manor",
    "sg:city":"Middlesbrough",
    "sg:classifiers":[
        {
            "category":"Professional",
            "subcategory":"Detective & Security Services",
            "type":"Services"
        }
    ],
    "sg:postcode":"TS7 8RX",
    "sg:province":"North Yorkshire",
    "wof:name":"Simkins Security Systems",
    "wof:placetype":"venue"
},
  "geometry": {"coordinates":[-1.2113130093,54.5378074646],"type":"Point"}
}