{
  "type": "Feature",
  "properties": {
    "iso:country":"GB",
    "sg:address":"Units 1-2, Paget Street",
    "sg:city":"Burton-on-trent",
    "sg:classifiers":[
        {
            "category":"Wholesale",
            "subcategory":"Machinery & Supplies",
            "type":"Manufacturing & Wholesale Goods"
        }
    ],
    "sg:postcode":"DE14 3TQ",
    "sg:province":"Derbyshire",
    "sg:tags":[
        "hydraulic"
    ],
    "wof:name":"Burton Hydraulic Services Ltd.",
    "wof:placetype":"venue"
},
  "geometry": {"coordinates":[-1.6410599947,52.8011207581],"type":"Point"}
}