{
  "type": "Feature",
  "properties": {
    "addr:full":"16 Cormorant Way, West Cross Swansea Swansea SA3 5RQ",
    "addr:housenumber":"16",
    "addr:postcode":"sa3 5rq",
    "addr:street":"Cormorant Way West Cross",
    "iso:country":"GB",
    "sg:address":"16 Cormorant Way, West Cross",
    "sg:city":"Swansea",
    "sg:classifiers":[
        {
            "category":"Professional",
            "subcategory":"Engineering",
            "type":"Services"
        }
    ],
    "sg:phone":"+44 1792 402566",
    "sg:postcode":"SA3 5RQ",
    "sg:province":"Swansea",
    "wof:name":"Cormorant Engineering",
    "wof:placetype":"venue"
},
  "geometry": {"coordinates":[-4.0162677765,51.5818061829],"type":"Point"}
}