{
  "type": "Feature",
  "properties": {
    "addr:full":"89 The Mall, The Stratford Centre London Greater London E15 1XG",
    "addr:housenumber":"89",
    "addr:postcode":"e15 1xg",
    "addr:street":"The Mall The",
    "iso:country":"GB",
    "sg:address":"89 The Mall, The Stratford Centre",
    "sg:city":"London",
    "sg:classifiers":[
        {
            "category":"Shopping",
            "subcategory":"Gifts & Souvenirs",
            "type":"Retail Goods"
        }
    ],
    "sg:phone":"+44 20 8534 7534",
    "sg:postcode":"E15 1XG",
    "sg:province":"Greater London",
    "sg:tags":[
        "poster",
        "card"
    ],
    "wof:name":"Clinton Cards",
    "wof:placetype":"venue"
},
  "geometry": {"coordinates":[0.00393,51.545898],"type":"Point"}
}