{
  "type": "Feature",
  "properties": {
    "addr:full":"39 Heath Gardens Twickenham Greater London TW1 4LY",
    "addr:housenumber":"39",
    "addr:postcode":"tw1 4ly",
    "addr:street":"Heath Gardens",
    "iso:country":"GB",
    "sg:address":"39 Heath Gardens",
    "sg:city":"Twickenham",
    "sg:classifiers":[
        {
            "category":"Professional",
            "subcategory":"Art Services",
            "type":"Services"
        }
    ],
    "sg:phone":"+44 20 8287 6772",
    "sg:postcode":"TW1 4LY",
    "sg:province":"Greater London",
    "sg:tags":[
        "photographer"
    ],
    "wof:name":"The Richmond Studio",
    "wof:placetype":"venue"
},
  "geometry": {"coordinates":[-0.337147,51.44397],"type":"Point"}
}