{
  "type": "Feature",
  "properties": {
    "addr:full":"Home Farm, Tong Lane Bradford West Yorkshire BD4 0RR",
    "addr:postcode":"bd4 0rr",
    "addr:street":"Tong Lane",
    "iso:country":"GB",
    "sg:address":"Home Farm, Tong Lane",
    "sg:city":"Bradford",
    "sg:classifiers":[
        {
            "category":"Professional",
            "subcategory":"Business Services",
            "type":"Services"
        },
        {
            "category":"Recreation",
            "subcategory":"Playground",
            "type":"Entertainment"
        }
    ],
    "sg:phone":"+44 113 285 4356",
    "sg:postcode":"BD4 0RR",
    "sg:province":"West Yorkshire",
    "sg:tags":[
        "hospitality",
        "corporate"
    ],
    "wof:name":"Park Wood Off Road Centre",
    "wof:placetype":"venue"
},
  "geometry": {"coordinates":[-1.663764,53.772091],"type":"Point"}
}