{
  "type": "Feature",
  "properties": {
    "iso:country":"GB",
    "sg:address":"Pleck Road",
    "sg:city":"Walsall",
    "sg:classifiers":[
        {
            "category":"Autos & Motor Vehicles",
            "subcategory":"Automobile Sales",
            "type":"Retail Goods"
        }
    ],
    "sg:phone":"+44 1922 748200",
    "sg:postcode":"WS2 9EX",
    "sg:province":"West Midlands",
    "sg:tags":[
        "car"
    ],
    "wof:name":"Reg Vardy Plc",
    "wof:placetype":"venue"
},
  "geometry": {"coordinates":[-1.995664,52.583076],"type":"Point"}
}