{
  "type": "Feature",
  "properties": {
    "iso:country":"GB",
    "sg:address":"35 High Street, Warboys",
    "sg:city":"Huntingdon",
    "sg:classifiers":[
        {
            "category":"Bars & Pubs",
            "type":"Food & Drink"
        },
        {
            "category":"Community Center",
            "subcategory":"Social",
            "type":"Public Place"
        }
    ],
    "sg:phone":"+44 1487 822462",
    "sg:postcode":"PE28 2TA",
    "sg:province":"Bedfordshire",
    "sg:tags":[
        "pubs",
        "house",
        "inn",
        "activity"
    ],
    "wof:name":"The White Hart",
    "wof:placetype":"venue"
},
  "geometry": {"coordinates":[-0.08074,52.40353],"type":"Point"}
}