{
  "type": "Feature",
  "properties": {
    "addr:full":"29 Royal Exchange Sq Glasgow Glasgow City G1 3AG",
    "addr:housenumber":"29",
    "addr:postcode":"g1 3ag",
    "addr:street":"Royal Exchange Sq",
    "iso:country":"GB",
    "sg:address":"29 Royal Exchange Sq",
    "sg:city":"Glasgow",
    "sg:classifiers":[
        {
            "category":"Personal",
            "subcategory":"Beauty Salon",
            "type":"Services"
        }
    ],
    "sg:phone":"+44 870 514 3789",
    "sg:postcode":"G1 3AG",
    "sg:province":"Glasgow City",
    "wof:name":"Salon Support Scotland",
    "wof:placetype":"venue"
},
  "geometry": {"coordinates":[-4.252932,55.859856],"type":"Point"}
}