{
  "type": "Feature",
  "properties": {
    "iso:country":"GB",
    "sg:address":"Unit 3 Kitewell Lane, Lydd",
    "sg:city":"Romney Marsh",
    "sg:classifiers":[
        {
            "category":"Autos & Motor Vehicles",
            "subcategory":"Automobile Sales",
            "type":"Retail Goods"
        }
    ],
    "sg:postcode":"TN29 9LP",
    "sg:province":"Kent",
    "sg:tags":[
        "car"
    ],
    "wof:name":"McM",
    "wof:placetype":"venue"
},
  "geometry": {"coordinates":[0.915212,50.956718],"type":"Point"}
}