{
  "type": "Feature",
  "properties": {
    "iso:country":"GB",
    "sg:address":"466 London Road",
    "sg:city":"Isleworth",
    "sg:classifiers":[
        {
            "category":"Building & Trades",
            "subcategory":"Cleaning & Sanitation",
            "type":"Services"
        }
    ],
    "sg:phone":"+44 20 8755 6700",
    "sg:postcode":"TW7 4BF",
    "sg:province":"Greater London",
    "sg:tags":[
        "commercial"
    ],
    "wof:name":"Atlas Cleaning Ltd.",
    "wof:placetype":"venue"
},
  "geometry": {"coordinates":[-0.3372110128,51.4750556946],"type":"Point"}
}