{
  "type": "Feature",
  "properties": {
    "iso:country":"GB",
    "sg:address":"135 Wembley Park Drive",
    "sg:city":"Wembley",
    "sg:classifiers":[
        {
            "category":"Food & Beverages",
            "subcategory":"Bakery",
            "type":"Retail Goods"
        }
    ],
    "sg:postcode":"HA9 8HQ",
    "sg:province":"Greater London",
    "sg:tags":[
        "pizza"
    ],
    "wof:name":"Euro Pizza",
    "wof:placetype":"venue"
},
  "geometry": {"coordinates":[-0.2814770043,51.5621414185],"type":"Point"}
}