{
  "type": "Feature",
  "properties": {
    "addr:full":"45 Codnor High St, Codnor Derby Derbyshire DE5 9QB",
    "addr:housenumber":"45",
    "addr:postcode":"de5 9qb",
    "addr:street":"Codnor High St",
    "iso:country":"GB",
    "sg:address":"45 Codnor High St, Codnor",
    "sg:city":"Derby",
    "sg:classifiers":[
        {
            "category":"Autos & Motor Vehicles",
            "subcategory":"Fuel & Gas Station",
            "type":"Retail Goods"
        }
    ],
    "sg:phone":"+44 1773 741380",
    "sg:postcode":"DE5 9QB",
    "sg:province":"Derbyshire",
    "sg:tags":[
        "petrol",
        "filling"
    ],
    "wof:name":"Codnor Service Station",
    "wof:placetype":"venue"
},
  "geometry": {"coordinates":[-1.375829,53.044216],"type":"Point"}
}