{
  "type": "Feature",
  "properties": {
    "addr:full":"Hollybush Ho, Parsons La Hinckley Leicestershire LE10 1XT",
    "addr:postcode":"le10 1xt",
    "addr:street":"Leicestershire",
    "iso:country":"GB",
    "sg:address":"Hollybush Ho, Parsons La",
    "sg:city":"Hinckley",
    "sg:classifiers":[
        {
            "category":"Building & Trades",
            "subcategory":"Construction",
            "type":"Services"
        }
    ],
    "sg:phone":"+44 1455 637412",
    "sg:postcode":"LE10 1XT",
    "sg:province":"Leicestershire",
    "sg:tags":[
        "heating",
        "contractor"
    ],
    "wof:name":"Brown & Johnson Plumbing Ltd",
    "wof:placetype":"venue"
},
  "geometry": {"coordinates":[-1.372754,52.542439],"type":"Point"}
}