{
  "type": "Feature",
  "properties": {
    "iso:country":"GB",
    "sg:address":"Central Avenue",
    "sg:city":"Ardrossan",
    "sg:classifiers":[
        {
            "category":"Health Services",
            "subcategory":"Clinic",
            "type":"Services"
        }
    ],
    "sg:phone":"+44 1294 603048",
    "sg:postcode":"KA22 7DX",
    "sg:province":"North Ayrshire",
    "sg:tags":[
        "nh"
    ],
    "wof:name":"Ardrossan Health Centre",
    "wof:placetype":"venue"
},
  "geometry": {"coordinates":[-4.805684,55.651772],"type":"Point"}
}