{
  "type": "Feature",
  "properties": {
    "addr:full":"27 Groveside, Bookham Leatherhead Surrey KT23 4LD",
    "addr:housenumber":"27",
    "addr:postcode":"kt23 4ld",
    "addr:street":"Groveside",
    "iso:country":"GB",
    "sg:address":"27 Groveside, Bookham",
    "sg:city":"Leatherhead",
    "sg:classifiers":[
        {
            "category":"Building & Trades",
            "subcategory":"Construction",
            "type":"Services"
        }
    ],
    "sg:phone":"+44 1372 459003",
    "sg:postcode":"KT23 4LD",
    "sg:province":"Surrey",
    "sg:tags":[
        "builder"
    ],
    "wof:name":"O'Reordan Building Contractors Ltd",
    "wof:placetype":"venue"
},
  "geometry": {"coordinates":[-0.3728789985,51.2765197754],"type":"Point"}
}