{
  "type": "Feature",
  "properties": {
    "iso:country":"GB",
    "sg:address":"Wilcock St",
    "sg:city":"Wigan",
    "sg:classifiers":[
        {
            "category":"Autos & Motor Vehicles",
            "subcategory":"Automobile Sales",
            "type":"Retail Goods"
        }
    ],
    "sg:phone":"+44 1942 820620",
    "sg:postcode":"WN3 4AR",
    "sg:province":"Lancashire",
    "sg:tags":[
        "car"
    ],
    "wof:name":"Bramwell Hyundai",
    "wof:placetype":"venue"
},
  "geometry": {"coordinates":[-2.6430029869,53.5436058044],"type":"Point"}
}