{
  "type": "Feature",
  "properties": {
    "iso:country":"GB",
    "sg:address":"Erw Faethlon",
    "sg:city":"Tywyn",
    "sg:classifiers":[
        {
            "category":"Farming",
            "subcategory":"Livestock Farm",
            "type":"Manufacturing & Wholesale Goods"
        }
    ],
    "sg:postcode":"LL36 9HY",
    "sg:province":"Gwynedd",
    "sg:tags":[
        "others"
    ],
    "wof:name":"E Evans",
    "wof:placetype":"venue"
},
  "geometry": {"coordinates":[-4.088419,52.586586],"type":"Point"}
}