{
  "type": "Feature",
  "properties": {
    "addr:full":"Terrace Road North, Binfield Bracknell Berkshire RG42 5JH",
    "addr:postcode":"rg42 5jh",
    "addr:street":"Terrace Road North",
    "iso:country":"GB",
    "sg:address":"Terrace Road North, Binfield",
    "sg:city":"Bracknell",
    "sg:classifiers":[
        {
            "category":"Professional",
            "subcategory":"Management & Consulting",
            "type":"Services"
        }
    ],
    "sg:phone":"+44 1344 642153",
    "sg:postcode":"RG42 5JH",
    "sg:province":"Berkshire",
    "sg:tags":[
        "consultant",
        "business"
    ],
    "wof:name":"Drivesys Consultancy Ltd.",
    "wof:placetype":"venue"
},
  "geometry": {"coordinates":[-0.784381,51.440144],"type":"Point"}
}