{
  "type": "Feature",
  "properties": {
    "iso:country":"GB",
    "sg:address":"Chelford Road, Ollerton",
    "sg:city":"Knutsford",
    "sg:classifiers":[
        {
            "category":"Bars & Pubs",
            "type":"Food & Drink"
        }
    ],
    "sg:postcode":"WA16 8RH",
    "sg:province":"Cheshire",
    "sg:tags":[
        "pubs",
        "inn"
    ],
    "wof:name":"D Shirley",
    "wof:placetype":"venue"
},
  "geometry": {"coordinates":[-2.364258,53.299583],"type":"Point"}
}