{
  "type": "Feature",
  "properties": {
    "addr:full":"117 Station Road, Stanbridge Leighton Buzzard Bedfordshire LU7 9JG",
    "addr:housenumber":"117",
    "addr:postcode":"lu7 9jg",
    "addr:street":"Station Road",
    "iso:country":"GB",
    "sg:address":"117 Station Road, Stanbridge",
    "sg:city":"Leighton Buzzard",
    "sg:classifiers":[
        {
            "category":"Communications",
            "subcategory":"Film & Video Production",
            "type":"Services"
        }
    ],
    "sg:postcode":"LU7 9JG",
    "sg:province":"Bedfordshire",
    "sg:tags":[
        "microfilming"
    ],
    "wof:name":"M R Management",
    "wof:placetype":"venue"
},
  "geometry": {"coordinates":[-0.596142,51.902676],"type":"Point"}
}