{
  "type": "Feature",
  "properties": {
    "addr:full":"38 Pollok Township Centre Glasgow East Renfrewshire G53 6QR",
    "addr:housenumber":"38",
    "addr:postcode":"g53 6qr",
    "addr:street":"Pollok Township Centre",
    "iso:country":"GB",
    "sg:address":"38 Pollok Township Centre",
    "sg:city":"Glasgow",
    "sg:classifiers":[
        {
            "category":"Shopping",
            "subcategory":"Pharmacy",
            "type":"Retail Goods"
        }
    ],
    "sg:phone":"+44 141 881 4552",
    "sg:postcode":"G53 6QR",
    "sg:province":"East Renfrewshire",
    "sg:tags":[
        "pharmacist",
        "chemist"
    ],
    "wof:name":"Pollok Pharmacy",
    "wof:placetype":"venue"
},
  "geometry": {"coordinates":[-4.3421001434,55.8229484558],"type":"Point"}
}