{
  "type": "Feature",
  "properties": {
    "addr:full":"6 Broad St Place, Blomfield Street London Greater London EC2M 7JH",
    "addr:housenumber":"6",
    "addr:postcode":"ec2m 7jh",
    "addr:street":"Broad St Place Blomfield Street",
    "iso:country":"GB",
    "sg:address":"6 Broad St Place, Blomfield Street",
    "sg:city":"London",
    "sg:classifiers":[
        {
            "category":"Transit Center",
            "subcategory":"Passenger",
            "type":"Transportation"
        }
    ],
    "sg:phone":"+44 20 8877 9465",
    "sg:postcode":"EC2M 7JH",
    "sg:province":"Greater London",
    "sg:tags":[
        "ship",
        "broker"
    ],
    "wof:name":"Western Island Ship Broking",
    "wof:placetype":"venue"
},
  "geometry": {"coordinates":[-0.0848100036,51.517791748],"type":"Point"}
}