{
  "type": "Feature",
  "properties": {
    "addr:full":"Hobart Street, Thatto Heath St Helens Cheshire WA9 5QX",
    "addr:postcode":"wa9 5qx",
    "addr:street":"Hobart Street Thatto Heath",
    "iso:country":"GB",
    "sg:address":"Hobart Street, Thatto Heath",
    "sg:city":"St Helens",
    "sg:classifiers":[
        {
            "category":"Education",
            "subcategory":"School",
            "type":"Public Place"
        },
        {
            "category":"Government",
            "subcategory":"Office",
            "type":"Public Place"
        }
    ],
    "sg:phone":"+44 1744 678710",
    "sg:postcode":"WA9 5QX",
    "sg:province":"Cheshire",
    "sg:tags":[
        "local",
        "authority"
    ],
    "wof:name":"Thatto Heath County Primary School",
    "wof:placetype":"venue"
},
  "geometry": {"coordinates":[-2.752374,53.436111],"type":"Point"}
}