{
  "type": "Feature",
  "properties": {
    "addr:full":"36 Beckett Street Bilston West Midlands WV14 7NT",
    "addr:housenumber":"36",
    "addr:postcode":"wv14 7nt",
    "addr:street":"Beckett Street",
    "iso:country":"GB",
    "sg:address":"36 Beckett Street",
    "sg:city":"Bilston",
    "sg:classifiers":[
        {
            "category":"Building & Trades",
            "subcategory":"Plumbing",
            "type":"Services"
        }
    ],
    "sg:postcode":"WV14 7NT",
    "sg:province":"West Midlands",
    "sg:tags":[
        "heating"
    ],
    "wof:name":"Brian W Dale",
    "wof:placetype":"venue"
},
  "geometry": {"coordinates":[-2.067159,52.568722],"type":"Point"}
}