{
  "type": "Feature",
  "properties": {
    "iso:country":"GB",
    "sg:address":"Broadway Buildings, Boston Road",
    "sg:city":"London",
    "sg:classifiers":[
        {
            "category":"Retail",
            "subcategory":"Laundry & Dry Cleaning",
            "type":"Services"
        }
    ],
    "sg:phone":"+44 20 8567 3996",
    "sg:postcode":"W7 3TT",
    "sg:province":"Greater London",
    "sg:tags":[
        "launderette"
    ],
    "wof:name":"Charlie Bubbles Launderette",
    "wof:placetype":"venue"
},
  "geometry": {"coordinates":[-0.337322,51.509109],"type":"Point"}
}