{
  "type": "Feature",
  "properties": {
    "iso:country":"GB",
    "sg:address":"7 Post Office Vaults, Market Place",
    "sg:city":"Wantage",
    "sg:classifiers":[
        {
            "category":"Social Services",
            "subcategory":"Retirement Home",
            "type":"Services"
        }
    ],
    "sg:phone":"+44 1235 772440",
    "sg:postcode":"OX12 8AT",
    "sg:province":"Berkshire",
    "sg:tags":[
        "care"
    ],
    "wof:name":"Day & Night Care Assistance",
    "wof:placetype":"venue"
},
  "geometry": {"coordinates":[-1.4251309633,51.5878677368],"type":"Point"}
}