{
  "type": "Feature",
  "properties": {
    "addr:full":"2 Headley Court, Headley Park Bristol City of Bristol BS13 7PD",
    "addr:housenumber":"2",
    "addr:postcode":"bs13 7pd",
    "addr:street":"Headley Court",
    "iso:country":"GB",
    "sg:address":"2 Headley Court, Headley Park",
    "sg:city":"Bristol",
    "sg:classifiers":[
        {
            "category":"Professional",
            "subcategory":"Computer Services",
            "type":"Services"
        }
    ],
    "sg:postcode":"BS13 7PD",
    "sg:province":"City of Bristol",
    "sg:tags":[
        "system",
        "software"
    ],
    "wof:name":"Cadco Services",
    "wof:placetype":"venue"
},
  "geometry": {"coordinates":[-2.608996,51.420479],"type":"Point"}
}