{
  "type": "Feature",
  "properties": {
    "iso:country":"GB",
    "sg:address":"Castell Gorwyn, Meidrim",
    "sg:city":"Carmarthen",
    "sg:classifiers":[
        {
            "category":"Farming",
            "subcategory":"Livestock Farm",
            "type":"Manufacturing & Wholesale Goods"
        }
    ],
    "sg:phone":"+44 1994 484219",
    "sg:postcode":"SA33 5PR",
    "sg:province":"Carmarthenshire",
    "sg:tags":[
        "others"
    ],
    "wof:name":"D V Davies",
    "wof:placetype":"venue"
},
  "geometry": {"coordinates":[-4.485577,51.860229],"type":"Point"}
}