{
  "type": "Feature",
  "properties": {
    "addr:full":"16 Market Hill Barnsley South Yorkshire S70 2QE",
    "addr:housenumber":"16",
    "addr:postcode":"s70 2qe",
    "addr:street":"Market Hill;Yorkshire",
    "iso:country":"GB",
    "sg:address":"16 Market Hill",
    "sg:city":"Barnsley",
    "sg:classifiers":[
        {
            "category":"Shopping",
            "subcategory":"Clothing, Apparel, & Fashions",
            "type":"Retail Goods"
        }
    ],
    "sg:phone":"+44 1226 291665",
    "sg:postcode":"S70 2QE",
    "sg:province":"South Yorkshire",
    "sg:tags":[
        "shop"
    ],
    "wof:name":"Pollyanna (Barnsley) Ltd.",
    "wof:placetype":"venue"
},
  "geometry": {"coordinates":[-1.4815069437,53.5533790588],"type":"Point"}
}