{
  "type": "Feature",
  "properties": {
    "addr:full":"Church House, Old Town Stratford-upon-avon Warwickshire CV37 6BG",
    "addr:postcode":"cv37 6bg",
    "iso:country":"GB",
    "sg:address":"Church House, Old Town",
    "sg:city":"Stratford-upon-avon",
    "sg:classifiers":[
        {
            "category":"Education",
            "subcategory":"School",
            "type":"Public Place"
        }
    ],
    "sg:phone":"+44 1789 297993",
    "sg:postcode":"CV37 6BG",
    "sg:province":"Warwickshire",
    "sg:tags":[
        "independent",
        "preparatory"
    ],
    "wof:name":"Stratford Preparatory School Ltd.",
    "wof:placetype":"venue"
},
  "geometry": {"coordinates":[-1.709022,52.188725],"type":"Point"}
}