{
  "type": "Feature",
  "properties": {
    "addr:full":"8 Old Steine Brighton East Sussex BN1 1EJ",
    "addr:housenumber":"8",
    "addr:postcode":"bn1 1ej",
    "addr:street":"Old Steine",
    "iso:country":"GB",
    "sg:address":"8 Old Steine",
    "sg:city":"Brighton",
    "sg:classifiers":[
        {
            "category":"Professional",
            "subcategory":"Printing & Photocopies",
            "type":"Services"
        }
    ],
    "sg:postcode":"BN1 1EJ",
    "sg:province":"East Sussex",
    "sg:tags":[
        "printer"
    ],
    "wof:name":"Mercury Press Ltd",
    "wof:placetype":"venue"
},
  "geometry": {"coordinates":[-0.1364700049,50.8214874268],"type":"Point"}
}