{
  "type": "Feature",
  "properties": {
    "addr:full":"37 Woodhouse Lane, Beighton Sheffield South Yorkshire S20 1AA",
    "addr:housenumber":"37",
    "addr:postcode":"s20 1aa",
    "addr:street":"Woodhouse Lane",
    "iso:country":"GB",
    "sg:address":"37 Woodhouse Lane, Beighton",
    "sg:city":"Sheffield",
    "sg:classifiers":[
        {
            "category":"Building & Trades",
            "subcategory":"Equipment Rental",
            "type":"Services"
        }
    ],
    "sg:phone":"+44 114 269 8455",
    "sg:postcode":"S20 1AA",
    "sg:province":"South Yorkshire",
    "sg:tags":[
        "plant",
        "machinery"
    ],
    "wof:name":"Doyle Excavations",
    "wof:placetype":"venue"
},
  "geometry": {"coordinates":[-1.339836,53.352489],"type":"Point"}
}