{
  "type": "Feature",
  "properties": {
    "addr:full":"The Kestrel, Seabrook Road Hythe Kent CT21 5QW",
    "addr:postcode":"ct21 5qw",
    "addr:street":"Seabrook Road",
    "iso:country":"GB",
    "sg:address":"The Kestrel, Seabrook Road",
    "sg:city":"Hythe",
    "sg:classifiers":[
        {
            "category":"Building & Trades",
            "subcategory":"Construction",
            "type":"Services"
        }
    ],
    "sg:postcode":"CT21 5QW",
    "sg:province":"Kent",
    "sg:tags":[
        "builder"
    ],
    "wof:name":"M A Jackson Ltd.",
    "wof:placetype":"venue"
},
  "geometry": {"coordinates":[1.0804810524,51.0708274841],"type":"Point"}
}