{
  "type": "Feature",
  "properties": {
    "iso:country":"GB",
    "sg:address":"99 Cotswold Crescent",
    "sg:city":"Billingham",
    "sg:classifiers":[
        {
            "category":"Building & Trades",
            "subcategory":"Construction",
            "type":"Services"
        }
    ],
    "sg:phone":"+44 1642 534613",
    "sg:postcode":"TS23 2QB",
    "sg:province":"Durham",
    "sg:tags":[
        "builder"
    ],
    "wof:name":"Jeff Whitehouse",
    "wof:placetype":"venue"
},
  "geometry": {"coordinates":[-1.292507,54.603065],"type":"Point"}
}