{
  "type": "Feature",
  "properties": {
    "iso:country":"GB",
    "sg:address":"32 Crewe Road",
    "sg:city":"Sandbach",
    "sg:classifiers":[
        {
            "category":"Farming",
            "subcategory":"Nursery",
            "type":"Manufacturing & Wholesale Goods"
        }
    ],
    "sg:phone":"+44 1270 767551",
    "sg:postcode":"CW11 4NE",
    "sg:province":"Cheshire",
    "sg:tags":[
        "creche"
    ],
    "wof:name":"Pine Lodge",
    "wof:placetype":"venue"
},
  "geometry": {"coordinates":[-2.3685688972,53.142490387],"type":"Point"}
}