{
  "type": "Feature",
  "properties": {
    "addr:full":"31 Albion Street Saxmundham Suffolk IP17 1BN",
    "addr:housenumber":"31",
    "addr:postcode":"ip17 1bn",
    "addr:street":"Albion Street",
    "iso:country":"GB",
    "sg:address":"31 Albion Street",
    "sg:city":"Saxmundham",
    "sg:classifiers":[
        {
            "category":"Professional",
            "subcategory":"Accounting & Tax Preparation",
            "type":"Services"
        }
    ],
    "sg:phone":"+44 1728 603553",
    "sg:postcode":"IP17 1BN",
    "sg:province":"Suffolk",
    "sg:tags":[
        "accountant"
    ],
    "wof:name":"Raymar Consultants Ltd.",
    "wof:placetype":"venue"
},
  "geometry": {"coordinates":[1.488463,52.214756],"type":"Point"}
}