{
  "type": "Feature",
  "properties": {
    "addr:full":"162 Windsor Rd Maidenhead Berkshire SL6 2DW",
    "addr:housenumber":"162",
    "addr:postcode":"sl6 2dw",
    "addr:street":"Windsor Rd",
    "iso:country":"GB",
    "sg:address":"162 Windsor Rd",
    "sg:city":"Maidenhead",
    "sg:classifiers":[
        {
            "category":"Communications",
            "type":"Services"
        }
    ],
    "sg:postcode":"SL6 2DW",
    "sg:province":"Berkshire",
    "sg:tags":[
        "audio-visual"
    ],
    "wof:name":"Couper-Johnston,Deborah,",
    "wof:placetype":"venue"
},
  "geometry": {"coordinates":[-0.7047989964,51.5001792908],"type":"Point"}
}