{
  "type": "Feature",
  "properties": {
    "addr:full":"14 Bell Lane Berkhamsted Bedfordshire HP4 3RD",
    "addr:housenumber":"14",
    "addr:postcode":"hp4 3rd",
    "addr:street":"Bell Lane",
    "iso:country":"GB",
    "sg:address":"14 Bell Lane",
    "sg:city":"Berkhamsted",
    "sg:classifiers":[
        {
            "category":"Building & Trades",
            "subcategory":"Construction",
            "type":"Services"
        }
    ],
    "sg:phone":"+44 1442 873579",
    "sg:postcode":"HP4 3RD",
    "sg:province":"Bedfordshire",
    "sg:tags":[
        "builder"
    ],
    "wof:name":"Gordon Ellis",
    "wof:placetype":"venue"
},
  "geometry": {"coordinates":[-0.589467,51.767952],"type":"Point"}
}