{
  "type": "Feature",
  "properties": {
    "addr:full":"19 Queens Approach Uckfield East Sussex TN22 1RU",
    "addr:housenumber":"19",
    "addr:postcode":"tn22 1ru",
    "addr:street":"Queens Approach",
    "iso:country":"GB",
    "sg:address":"19 Queens Approach",
    "sg:city":"Uckfield",
    "sg:classifiers":[
        {
            "category":"Professional",
            "subcategory":"Computer Services",
            "type":"Services"
        }
    ],
    "sg:phone":"+44 1825 760106",
    "sg:postcode":"TN22 1RU",
    "sg:province":"East Sussex",
    "sg:tags":[
        "system",
        "software"
    ],
    "wof:name":"Miracle Business Systems",
    "wof:placetype":"venue"
},
  "geometry": {"coordinates":[0.101929,50.978561],"type":"Point"}
}