{
  "type": "Feature",
  "properties": {
    "addr:full":"46 Durham Street Hartlepool Durham TS24 0HF",
    "addr:housenumber":"46",
    "addr:postcode":"ts24 0hf",
    "addr:street":"Durham Street",
    "iso:country":"GB",
    "sg:address":"46 Durham Street",
    "sg:city":"Hartlepool",
    "sg:classifiers":[
        {
            "category":"Bars & Pubs",
            "type":"Food & Drink"
        }
    ],
    "sg:phone":"+44 1429 267759",
    "sg:postcode":"TS24 0HF",
    "sg:province":"Durham",
    "sg:tags":[
        "pubs",
        "inn"
    ],
    "wof:name":"K & L Sandbach",
    "wof:placetype":"venue"
},
  "geometry": {"coordinates":[-1.185222,54.699844],"type":"Point"}
}