{
  "type": "Feature",
  "properties": {
    "addr:full":"Unit 13 Newcastle Enterprise Centre, High St Newcastle Staffordshire ST5 6BX",
    "addr:housenumber":"unit 13;enterprise centre",
    "addr:postcode":"st5 6bx",
    "addr:street":"High St",
    "iso:country":"GB",
    "sg:address":"Unit 13 Newcastle Enterprise Centre, High St",
    "sg:city":"Newcastle",
    "sg:classifiers":[
        {
            "category":"Professional",
            "type":"Services"
        }
    ],
    "sg:phone":"+44 1782 714372",
    "sg:postcode":"ST5 6BX",
    "sg:province":"Staffordshire",
    "sg:tags":[
        "caterer"
    ],
    "wof:name":"Mrs T'S",
    "wof:placetype":"venue"
},
  "geometry": {"coordinates":[-2.228601,53.008801],"type":"Point"}
}