{
  "type": "Feature",
  "properties": {
    "iso:country":"GB",
    "sg:address":"290-292 Marine Road Central",
    "sg:city":"Morecambe",
    "sg:classifiers":[
        {
            "category":"Bars & Pubs",
            "type":"Food & Drink"
        }
    ],
    "sg:phone":"+44 1524 419972",
    "sg:postcode":"LA4 5BY",
    "sg:province":"Lancashire",
    "sg:tags":[
        "pubs",
        "inn"
    ],
    "wof:name":"O'Rafferty's Irish Bar",
    "wof:placetype":"venue"
},
  "geometry": {"coordinates":[-2.864473,54.074116],"type":"Point"}
}