{
  "type": "Feature",
  "properties": {
    "addr:full":"3 Maddoxford Way, Botley Southampton Hampshire SO32 2DW",
    "addr:housenumber":"3",
    "addr:postcode":"so32 2dw",
    "addr:street":"Maddoxford Way",
    "iso:country":"GB",
    "sg:address":"3 Maddoxford Way, Botley",
    "sg:city":"Southampton",
    "sg:classifiers":[
        {
            "category":"Home & Garden",
            "subcategory":"Garden Supply",
            "type":"Retail Goods"
        }
    ],
    "sg:phone":"+44 1489 783556",
    "sg:postcode":"SO32 2DW",
    "sg:province":"Hampshire",
    "sg:tags":[
        "turfing"
    ],
    "wof:name":"J R Hack",
    "wof:placetype":"venue"
},
  "geometry": {"coordinates":[-1.279721,50.927689],"type":"Point"}
}