{
  "type": "Feature",
  "properties": {
    "iso:country":"GB",
    "sg:address":"Low Hall, Bedale Road, Hunton",
    "sg:city":"Bedale",
    "sg:classifiers":[
        {
            "category":"Farming",
            "subcategory":"Dairy Farm",
            "type":"Manufacturing & Wholesale Goods"
        }
    ],
    "sg:phone":"+44 1677 450276",
    "sg:postcode":"DL8 1QF",
    "sg:province":"North Yorkshire",
    "wof:name":"R Worsdale",
    "wof:placetype":"venue"
},
  "geometry": {"coordinates":[-1.592346,54.288811],"type":"Point"}
}