{
  "type": "Feature",
  "properties": {
    "iso:country":"GB",
    "sg:address":"74a Elston Road",
    "sg:city":"Aldershot",
    "sg:classifiers":[
        {
            "category":"Building & Trades",
            "subcategory":"Landscaping Services",
            "type":"Services"
        }
    ],
    "sg:phone":"+44 1252 312323",
    "sg:postcode":"GU12 4HZ",
    "sg:province":"Hampshire",
    "sg:tags":[
        "landscape",
        "contractor"
    ],
    "wof:name":"Paradise Garden Services",
    "wof:placetype":"venue"
},
  "geometry": {"coordinates":[-0.752113,51.24276],"type":"Point"}
}