{
  "type": "Feature",
  "properties": {
    "addr:full":"Springhill Ho, Springhill Rd Kidlington Buckinghamshire OX5 1RX",
    "addr:postcode":"ox5 1rx",
    "addr:street":"Springhill;Springhill Rd",
    "iso:country":"GB",
    "sg:address":"Springhill Ho, Springhill Rd",
    "sg:city":"Kidlington",
    "sg:classifiers":[
        {
            "category":"Building & Trades",
            "subcategory":"Landscaping Services",
            "type":"Services"
        }
    ],
    "sg:phone":"+44 1865 370507",
    "sg:postcode":"OX5 1RX",
    "sg:province":"Buckinghamshire",
    "sg:tags":[
        "gardening"
    ],
    "wof:name":"R J Mullins",
    "wof:placetype":"venue"
},
  "geometry": {"coordinates":[-1.319114,51.821705],"type":"Point"}
}