{
  "type": "Feature",
  "properties": {
    "addr:full":"Beechwood Lodge, Elmete Lane, Roundhay Leeds West Yorkshire LS8 2LG",
    "addr:postcode":"ls8 2lg",
    "addr:street":"Elmete Lane",
    "iso:country":"GB",
    "sg:address":"Beechwood Lodge, Elmete Lane, Roundhay",
    "sg:city":"Leeds",
    "sg:classifiers":[
        {
            "category":"Government",
            "subcategory":"Post Office",
            "type":"Public Place"
        }
    ],
    "sg:phone":"+44 113 216 4422",
    "sg:postcode":"LS8 2LG",
    "sg:province":"West Yorkshire",
    "sg:tags":[
        "messenger",
        "courier"
    ],
    "wof:name":"Nexus Couriers",
    "wof:placetype":"venue"
},
  "geometry": {"coordinates":[-1.5050899982,53.8385925293],"type":"Point"}
}