{
  "type": "Feature",
  "properties": {
    "iso:country":"GB",
    "sg:address":"The Pier",
    "sg:city":"Hastings",
    "sg:classifiers":[
        {
            "category":"Restaurant",
            "type":"Food & Drink"
        },
        {
            "category":"Community Center",
            "type":"Public Place"
        }
    ],
    "sg:postcode":"TN34 1LA",
    "sg:province":"East Sussex",
    "sg:tags":[
        "entertainment",
        "centre"
    ],
    "wof:name":"Hastings Pier Cafe",
    "wof:placetype":"venue"
},
  "geometry": {"coordinates":[0.575625,50.86256],"type":"Point"}
}