{
  "type": "Feature",
  "properties": {
    "addr:full":"20 Windsor Road Slough Berkshire SL1 2EJ",
    "addr:housenumber":"20",
    "addr:postcode":"sl1 2ej",
    "addr:street":"Windsor Road",
    "iso:country":"GB",
    "sg:address":"20 Windsor Road",
    "sg:city":"Slough",
    "sg:classifiers":[
        {
            "category":"Bars & Pubs",
            "type":"Food & Drink"
        }
    ],
    "sg:phone":"+44 1753 218031",
    "sg:postcode":"SL1 2EJ",
    "sg:province":"Berkshire",
    "sg:tags":[
        "pubs",
        "inn"
    ],
    "wof:name":"O'Neill's Irish Bar",
    "wof:placetype":"venue"
},
  "geometry": {"coordinates":[-0.5959349871,51.5087585449],"type":"Point"}
}