{
  "type": "Feature",
  "properties": {
    "addr:full":"Riverside Mill, The Backs Chepstow Gloucestershire NP16 5HS",
    "addr:postcode":"np16 5hs",
    "iso:country":"GB",
    "sg:address":"Riverside Mill, The Backs",
    "sg:city":"Chepstow",
    "sg:classifiers":[
        {
            "category":"Shopping",
            "type":"Retail Goods"
        }
    ],
    "sg:phone":"+44 1291 622225",
    "sg:postcode":"NP16 5HS",
    "sg:province":"Gloucestershire",
    "sg:tags":[
        "merchant"
    ],
    "wof:name":"West Midlands Farmers Association",
    "wof:placetype":"venue"
},
  "geometry": {"coordinates":[-2.6798119545,51.637878418],"type":"Point"}
}