{
  "type": "Feature",
  "properties": {
    "addr:full":"Booking Office, Dumbarton Road Stirling Stirling FK8 2QL",
    "addr:postcode":"fk8 2ql",
    "addr:street":"Dumbarton Road",
    "iso:country":"GB",
    "sg:address":"Booking Office, Dumbarton Road",
    "sg:city":"Stirling",
    "sg:classifiers":[
        {
            "category":"Arts & Performance",
            "subcategory":"Theater",
            "type":"Entertainment"
        }
    ],
    "sg:phone":"+44 1786 473544",
    "sg:postcode":"FK8 2QL",
    "sg:province":"Stirling",
    "sg:tags":[
        "hall",
        "theatre",
        "concert"
    ],
    "wof:name":"Albert Halls",
    "wof:placetype":"venue"
},
  "geometry": {"coordinates":[-3.93952,56.117359],"type":"Point"}
}