{
  "type": "Feature",
  "properties": {
    "addr:full":"23 North Street Bishops Stortford Essex CM23 2LD",
    "addr:housenumber":"23",
    "addr:postcode":"cm23 2ld",
    "addr:street":"North Street",
    "iso:country":"GB",
    "sg:address":"23 North Street",
    "sg:city":"Bishops Stortford",
    "sg:classifiers":[
        {
            "category":"Home & Garden",
            "subcategory":"Furniture",
            "type":"Retail Goods"
        }
    ],
    "sg:phone":"+44 1279 657118",
    "sg:postcode":"CM23 2LD",
    "sg:province":"Essex",
    "wof:name":"Lathams Country Store",
    "wof:placetype":"venue"
},
  "geometry": {"coordinates":[0.158267,51.872253],"type":"Point"}
}