{
  "type": "Feature",
  "properties": {
    "addr:full":"88 Saltergate Chesterfield Derbyshire S40 1LG",
    "addr:housenumber":"88",
    "addr:postcode":"s40 1lg",
    "addr:street":"Saltergate",
    "iso:country":"GB",
    "sg:address":"88 Saltergate",
    "sg:city":"Chesterfield",
    "sg:classifiers":[
        {
            "category":"Communications",
            "subcategory":"News Services",
            "type":"Services"
        }
    ],
    "sg:phone":"+44 1246 555484",
    "sg:postcode":"S40 1LG",
    "sg:province":"Derbyshire",
    "sg:tags":[
        "illustrator"
    ],
    "wof:name":"Horsey Humour",
    "wof:placetype":"venue"
},
  "geometry": {"coordinates":[-1.433442,53.23764],"type":"Point"}
}