{
  "type": "Feature",
  "properties": {
    "addr:full":"Wickhambrook Surgery, Boyden Close, Wickhambrook Newmarket Cambridgeshire CB8 8XU",
    "addr:postcode":"cb8 8xu",
    "addr:street":"Boyden Close",
    "iso:country":"GB",
    "sg:address":"Wickhambrook Surgery, Boyden Close, Wickhambrook",
    "sg:city":"Newmarket",
    "sg:classifiers":[
        {
            "category":"Health Services",
            "subcategory":"Doctor",
            "type":"Services"
        },
        {
            "category":"Health Services",
            "subcategory":"Clinic",
            "type":"Services"
        }
    ],
    "sg:phone":"+44 1440 820140",
    "sg:postcode":"CB8 8XU",
    "sg:province":"Cambridgeshire",
    "sg:tags":[
        "nh",
        "practitioners"
    ],
    "wof:name":"Wickhambrook Surgery",
    "wof:placetype":"venue"
},
  "geometry": {"coordinates":[0.557256,52.163754],"type":"Point"}
}