{
  "type": "Feature",
  "properties": {
    "addr:full":"The Squires, 5 Walsall Street Wednesbury West Midlands WS10 9BZ",
    "addr:housenumber":"5",
    "addr:postcode":"ws10 9bz",
    "addr:street":"The Squires;Walsall Street",
    "iso:country":"GB",
    "sg:address":"The Squires, 5 Walsall Street",
    "sg:city":"Wednesbury",
    "sg:classifiers":[
        {
            "category":"Professional",
            "subcategory":"Accounting & Tax Preparation",
            "type":"Services"
        }
    ],
    "sg:postcode":"WS10 9BZ",
    "sg:province":"West Midlands",
    "sg:tags":[
        "accountant"
    ],
    "wof:name":"Wright & Co.",
    "wof:placetype":"venue"
},
  "geometry": {"coordinates":[-2.0192539692,52.5527305603],"type":"Point"}
}