{
  "type": "Feature",
  "properties": {
    "addr:full":"Greenways, Alkerton Road Banbury Oxfordshire OX15 6JR",
    "addr:postcode":"ox15 6jr",
    "addr:street":"Alkerton Road",
    "iso:country":"GB",
    "sg:address":"Greenways, Alkerton Road",
    "sg:city":"Banbury",
    "sg:classifiers":[
        {
            "category":"Professional",
            "type":"Services"
        }
    ],
    "sg:postcode":"OX15 6JR",
    "sg:province":"Oxfordshire",
    "sg:tags":[
        "caterer"
    ],
    "wof:name":"Meli-Melo Cuisine",
    "wof:placetype":"venue"
},
  "geometry": {"coordinates":[-1.450666,52.082855],"type":"Point"}
}