{
  "type": "Feature",
  "properties": {
    "iso:country":"GB",
    "sg:address":"Ysguborwen Road",
    "sg:city":"Penmaenmawr",
    "sg:classifiers":[
        {
            "category":"Bars & Pubs",
            "type":"Food & Drink"
        }
    ],
    "sg:phone":"+44 1492 623231",
    "sg:postcode":"LL34 6PS",
    "sg:province":"Conwy",
    "sg:tags":[
        "pubs",
        "inn"
    ],
    "wof:name":"Legend Inn",
    "wof:placetype":"venue"
},
  "geometry": {"coordinates":[-3.9372639656,53.2669448853],"type":"Point"}
}