{
  "type": "Feature",
  "properties": {
    "iso:country":"GB",
    "sg:address":"11 Fyne Road, Broughty Ferry",
    "sg:city":"Dundee",
    "sg:classifiers":[
        {
            "category":"Shopping",
            "subcategory":"Computers & Home Electronics",
            "type":"Retail Goods"
        }
    ],
    "sg:phone":"+44 1382 776519",
    "sg:postcode":"DD5 3JF",
    "sg:province":"Angus",
    "sg:tags":[
        "aerial",
        "television",
        "radio"
    ],
    "wof:name":"Broughty Aerials",
    "wof:placetype":"venue"
},
  "geometry": {"coordinates":[-2.8669989109,56.47498703],"type":"Point"}
}