{
  "type": "Feature",
  "properties": {
    "iso:country":"GB",
    "sg:address":"Maryfield, East Worlington Crediton",
    "sg:city":"Crediton",
    "sg:classifiers":[
        {
            "category":"Real Estate",
            "subcategory":"Surveying",
            "type":"Services"
        }
    ],
    "sg:phone":"+44 1884 861004",
    "sg:postcode":"EX17 4SU",
    "sg:province":"Devon",
    "sg:tags":[
        "building",
        "surveyor"
    ],
    "wof:name":"V.C Building Services",
    "wof:placetype":"venue"
},
  "geometry": {"coordinates":[-3.743854,50.91095],"type":"Point"}
}