{
  "type": "Feature",
  "properties": {
    "addr:full":"22-24 Albion Street London Greater London SE16 7JQ",
    "addr:housenumber":"22-24",
    "addr:postcode":"se16 7jq",
    "addr:street":"Albion Street",
    "iso:country":"GB",
    "sg:address":"22-24 Albion Street",
    "sg:city":"London",
    "sg:classifiers":[
        {
            "category":"Food & Beverages",
            "subcategory":"Supermarket",
            "type":"Retail Goods"
        }
    ],
    "sg:phone":"+44 20 7231 3731",
    "sg:postcode":"SE16 7JQ",
    "sg:province":"Greater London",
    "wof:name":"Erens",
    "wof:placetype":"venue"
},
  "geometry": {"coordinates":[-0.053319,51.499268],"type":"Point"}
}