{
  "type": "Feature",
  "properties": {
    "addr:full":"131 Clifton Road Worthing West Sussex BN11 4DP",
    "addr:housenumber":"131",
    "addr:postcode":"bn11 4dp",
    "addr:street":"Clifton Road",
    "iso:country":"GB",
    "sg:address":"131 Clifton Road",
    "sg:city":"Worthing",
    "sg:classifiers":[
        {
            "category":"Food & Beverages",
            "subcategory":"Meat & Fish",
            "type":"Retail Goods"
        }
    ],
    "sg:postcode":"BN11 4DP",
    "sg:province":"West Sussex",
    "sg:tags":[
        "chip"
    ],
    "wof:name":"Oxfords Traditional Fish & Chips",
    "wof:placetype":"venue"
},
  "geometry": {"coordinates":[-0.378765,50.817585],"type":"Point"}
}