{
  "type": "Feature",
  "properties": {
    "addr:full":"12 Westminster Dr Bradford West Yorkshire BD14 6SL",
    "addr:housenumber":"12",
    "addr:postcode":"bd14 6sl",
    "addr:street":"Westminster Dr",
    "iso:country":"GB",
    "sg:address":"12 Westminster Dr",
    "sg:city":"Bradford",
    "sg:classifiers":[
        {
            "category":"Health Services",
            "subcategory":"Podiatrist",
            "type":"Services"
        }
    ],
    "sg:phone":"+44 1274 880169",
    "sg:postcode":"BD14 6SL",
    "sg:province":"West Yorkshire",
    "sg:tags":[
        "podiatrists",
        "chiropodist"
    ],
    "wof:name":"R L Churchill-Kenningham",
    "wof:placetype":"venue"
},
  "geometry": {"coordinates":[-1.8284519911,53.7808036804],"type":"Point"}
}