{
  "type": "Feature",
  "properties": {
    "addr:full":"102 Hunton Rd Birmingham West Midlands B23 6AH",
    "addr:housenumber":"102",
    "addr:postcode":"b23 6ah",
    "addr:street":"Hunton Rd",
    "iso:country":"GB",
    "sg:address":"102 Hunton Rd",
    "sg:city":"Birmingham",
    "sg:classifiers":[
        {
            "category":"Retail",
            "subcategory":"Auto Repair",
            "type":"Services"
        }
    ],
    "sg:postcode":"B23 6AH",
    "sg:province":"West Midlands",
    "sg:tags":[
        "modification",
        "garage"
    ],
    "wof:name":"Fellows,Barry,",
    "wof:placetype":"venue"
},
  "geometry": {"coordinates":[-1.8526890278,52.5190238953],"type":"Point"}
}