{
  "type": "Feature",
  "properties": {
    "addr:full":"73 Westbourne Grove London Greater London W2 4UJ",
    "addr:housenumber":"73",
    "addr:postcode":"w2 4uj",
    "addr:street":"Westbourne Grove",
    "iso:country":"GB",
    "sg:address":"73 Westbourne Grove",
    "sg:city":"London",
    "sg:classifiers":[
        {
            "category":"Cafe",
            "type":"Food & Drink"
        }
    ],
    "sg:phone":"+44 20 7229 0380",
    "sg:postcode":"W2 4UJ",
    "sg:province":"Greater London",
    "sg:tags":[
        "tea",
        "snack",
        "bar",
        "room"
    ],
    "wof:name":"L'Etoile Coffee Shop",
    "wof:placetype":"venue"
},
  "geometry": {"coordinates":[-0.178717,51.515606],"type":"Point"}
}