{
  "type": "Feature",
  "properties": {
    "addr:full":"Brent Way Brentford Greater London TW8 8ES",
    "addr:postcode":"tw8 8es",
    "addr:street":"Brent Way",
    "iso:country":"GB",
    "sg:address":"Brent Way",
    "sg:city":"Brentford",
    "sg:classifiers":[
        {
            "category":"Retail",
            "subcategory":"Auto Repair",
            "type":"Services"
        }
    ],
    "sg:phone":"+44 20 8560 6528",
    "sg:postcode":"TW8 8ES",
    "sg:province":"Greater London",
    "sg:tags":[
        "body",
        "car"
    ],
    "wof:name":"Bennett Bros Motor Body Repairs",
    "wof:placetype":"venue"
},
  "geometry": {"coordinates":[-0.3084470034,51.4826927185],"type":"Point"}
}