{
  "type": "Feature",
  "properties": {
    "iso:country":"GB",
    "sg:address":"9 Church Street",
    "sg:city":"Kidderminster",
    "sg:classifiers":[
        {
            "category":"Personal",
            "subcategory":"Beauty Salon",
            "type":"Services"
        }
    ],
    "sg:phone":"+44 1562 824828",
    "sg:postcode":"DY10 2AD",
    "sg:province":"Staffordshire",
    "sg:tags":[
        "unisex",
        "hairdresser"
    ],
    "wof:name":"A Cut Above",
    "wof:placetype":"venue"
},
  "geometry": {"coordinates":[-2.250079,52.389065],"type":"Point"}
}