{
  "type": "Feature",
  "properties": {
    "iso:country":"GB",
    "sg:address":"Wren Park, Hitchin Road",
    "sg:city":"Shefford",
    "sg:classifiers":[
        {
            "category":"Retail",
            "subcategory":"Auto Repair",
            "type":"Services"
        }
    ],
    "sg:phone":"+44 1462 811991",
    "sg:postcode":"SG17 5JD",
    "sg:province":"Bedfordshire",
    "sg:tags":[
        "engine",
        "car",
        "specialist"
    ],
    "wof:name":"Cylinder Head Engineering Ltd.",
    "wof:placetype":"venue"
},
  "geometry": {"coordinates":[-0.334879,52.04134],"type":"Point"}
}