{
  "type": "Feature",
  "properties": {
    "addr:full":"Broadway Ho, 112-134 The Broadway, Wimbledon London Greater London SW19 1RN",
    "addr:housenumber":"112-134",
    "addr:postcode":"sw19 1rn",
    "addr:street":"Broadway;The Broadway",
    "iso:country":"GB",
    "sg:address":"Broadway Ho, 112-134 The Broadway, Wimbledon",
    "sg:city":"London",
    "sg:classifiers":[
        {
            "category":"Real Estate",
            "subcategory":"Real Estate Agent",
            "type":"Services"
        }
    ],
    "sg:postcode":"SW19 1RN",
    "sg:province":"Greater London",
    "wof:name":"Canadian Real Estate Centre Ltd",
    "wof:placetype":"venue"
},
  "geometry": {"coordinates":[-0.19174,51.41983],"type":"Point"}
}