{
  "type": "Feature",
  "properties": {
    "iso:country":"GB",
    "sg:address":"Charles House, 5a Charles Street",
    "sg:city":"Petersfield",
    "sg:classifiers":[
        {
            "category":"Organizations",
            "subcategory":"Non-profit Organization",
            "type":"Services"
        }
    ],
    "sg:phone":"+44 1730 264208",
    "sg:postcode":"GU32 3EH",
    "sg:province":"Hampshire",
    "sg:tags":[
        "organisation",
        "animal",
        "welfare"
    ],
    "wof:name":"Compassion in World Farming Ltd.",
    "wof:placetype":"venue"
},
  "geometry": {"coordinates":[-0.940299,51.005573],"type":"Point"}
}