{
  "type": "Feature",
  "properties": {
    "iso:country":"GB",
    "sg:address":"Elsrickle Mains Farm, Elsrickle",
    "sg:city":"Biggar",
    "sg:classifiers":[
        {
            "category":"Farming",
            "subcategory":"Dairy Farm",
            "type":"Manufacturing & Wholesale Goods"
        }
    ],
    "sg:phone":"+44 1899 810232",
    "sg:postcode":"ML12 6QZ",
    "sg:province":"Dumfries and Galloway",
    "sg:tags":[
        "farmer"
    ],
    "wof:name":"J & M Kinloch",
    "wof:placetype":"venue"
},
  "geometry": {"coordinates":[-3.5230190754,55.624420166],"type":"Point"}
}