{
  "type": "Feature",
  "properties": {
    "addr:full":"9 Ashford Place York North Yorkshire YO24 4QU",
    "addr:housenumber":"9",
    "addr:postcode":"yo24 4qu",
    "addr:street":"Ashford Place York",
    "iso:country":"GB",
    "sg:address":"9 Ashford Place",
    "sg:city":"York",
    "sg:classifiers":[
        {
            "category":"Professional",
            "type":"Services"
        },
        {
            "category":"Government",
            "subcategory":"Office",
            "type":"Public Place"
        }
    ],
    "sg:postcode":"YO24 4QU",
    "sg:province":"North Yorkshire",
    "sg:tags":[
        "directory",
        "local",
        "pub"
    ],
    "wof:name":"CITY OF YORK COUNCIL",
    "wof:placetype":"venue"
},
  "geometry": {"coordinates":[-1.119384,53.947803],"type":"Point"}
}