{
  "type": "Feature",
  "properties": {
    "addr:full":"32-34 High Street Polegate East Sussex BN26 6AJ",
    "addr:housenumber":"32-34",
    "addr:postcode":"bn26 6aj",
    "addr:street":"High Street Polegate",
    "iso:country":"GB",
    "sg:address":"32-34 High Street",
    "sg:city":"Polegate",
    "sg:classifiers":[
        {
            "category":"Home & Garden",
            "subcategory":"Hardware",
            "type":"Retail Goods"
        }
    ],
    "sg:postcode":"BN26 6AJ",
    "sg:province":"East Sussex",
    "wof:name":"Fairways Home & Garden Centre",
    "wof:placetype":"venue"
},
  "geometry": {"coordinates":[0.244326,50.821991],"type":"Point"}
}