{
  "type": "Feature",
  "properties": {
    "iso:country":"GB",
    "sg:address":"Churchside Arcade Little Church St",
    "sg:city":"Rugby",
    "sg:classifiers":[
        {
            "category":"Shopping",
            "subcategory":"Department Store",
            "type":"Retail Goods"
        },
        {
            "category":"Shopping",
            "subcategory":"Crafts & Fabrics",
            "type":"Retail Goods"
        }
    ],
    "sg:postcode":"CV21 3AW",
    "sg:province":"Warwickshire",
    "sg:tags":[
        "shop"
    ],
    "wof:name":"Bradbrook,Judy,",
    "wof:placetype":"venue"
},
  "geometry": {"coordinates":[-1.2616000175,52.3717498779],"type":"Point"}
}