{
  "type": "Feature",
  "properties": {
    "iso:country":"GB",
    "sg:address":"33-35 Bollo Bridge Road",
    "sg:city":"London",
    "sg:classifiers":[
        {
            "category":"Building & Trades",
            "subcategory":"Construction",
            "type":"Services"
        }
    ],
    "sg:postcode":"W3 8AT",
    "sg:province":"Greater London",
    "sg:tags":[
        "builder"
    ],
    "wof:name":"Kirkwood Contracts Ltd",
    "wof:placetype":"venue"
},
  "geometry": {"coordinates":[-0.266344,51.503235],"type":"Point"}
}