{
  "type": "Feature",
  "properties": {
    "iso:country":"GB",
    "sg:address":"Rombalds Avenue",
    "sg:city":"Leeds",
    "sg:classifiers":[
        {
            "category":"Education",
            "subcategory":"School",
            "type":"Public Place"
        }
    ],
    "sg:phone":"+44 113 263 6810",
    "sg:postcode":"LS12 2BB",
    "sg:province":"West Yorkshire",
    "sg:tags":[
        "local",
        "authority"
    ],
    "wof:name":"Leeds City Council",
    "wof:placetype":"venue"
},
  "geometry": {"coordinates":[-1.588459,53.801281],"type":"Point"}
}