{
  "type": "Feature",
  "properties": {
    "addr:full":"41 Roseberry Square Redcar North Yorkshire TS10 4EN",
    "addr:housenumber":"41",
    "addr:postcode":"ts10 4en",
    "addr:street":"Roseberry Square",
    "iso:country":"GB",
    "sg:address":"41 Roseberry Square",
    "sg:city":"Redcar",
    "sg:classifiers":[
        {
            "category":"Shopping",
            "subcategory":"Used Merchandise",
            "type":"Retail Goods"
        }
    ],
    "sg:postcode":"TS10 4EN",
    "sg:province":"North Yorkshire",
    "sg:tags":[
        "shop",
        "second-hand"
    ],
    "wof:name":"Roseberry Square Trading",
    "wof:placetype":"venue"
},
  "geometry": {"coordinates":[-1.0703439713,54.6032066345],"type":"Point"}
}