{
  "type": "Feature",
  "properties": {
    "addr:full":"73 Lutyens House, Churchill Gardens London Greater London SW1V 3AD",
    "addr:housenumber":"73;house",
    "addr:postcode":"sw1v 3ad",
    "addr:street":"Churchill Gardens",
    "iso:country":"GB",
    "sg:address":"73 Lutyens House, Churchill Gardens",
    "sg:city":"London",
    "sg:classifiers":[
        {
            "category":"Professional",
            "subcategory":"Printing & Photocopies",
            "type":"Services"
        }
    ],
    "sg:phone":"+44 20 7828 8357",
    "sg:postcode":"SW1V 3AD",
    "sg:province":"Greater London",
    "sg:tags":[
        "plate",
        "lithographic",
        "maker"
    ],
    "wof:name":"Absolute Proof",
    "wof:placetype":"venue"
},
  "geometry": {"coordinates":[-0.142508,51.486305],"type":"Point"}
}