{
  "type": "Feature",
  "properties": {
    "addr:full":"25 Felstead Avenue Ilford Essex IG5 0QJ",
    "addr:housenumber":"25",
    "addr:postcode":"ig5 0qj",
    "addr:street":"Felstead Avenue Ilford",
    "iso:country":"GB",
    "sg:address":"25 Felstead Avenue",
    "sg:city":"Ilford",
    "sg:classifiers":[
        {
            "category":"Travel",
            "subcategory":"Travel Agent",
            "type":"Entertainment"
        }
    ],
    "sg:phone":"+44 20 8550 1941",
    "sg:postcode":"IG5 0QJ",
    "sg:province":"Essex",
    "wof:name":"Villa Fiore",
    "wof:placetype":"venue"
},
  "geometry": {"coordinates":[0.064412,51.596188],"type":"Point"}
}