{
  "type": "Feature",
  "properties": {
    "addr:full":"Seymour Road, Mannamead Plymouth Devon PL3 5AS",
    "addr:postcode":"pl3 5as",
    "addr:street":"Seymour Road",
    "iso:country":"GB",
    "sg:address":"Seymour Road, Mannamead",
    "sg:city":"Plymouth",
    "sg:classifiers":[
        {
            "category":"Education",
            "subcategory":"School",
            "type":"Public Place"
        }
    ],
    "sg:phone":"+44 1752 668558",
    "sg:postcode":"PL3 5AS",
    "sg:province":"Devon",
    "sg:tags":[
        "independent",
        "preparatory"
    ],
    "wof:name":"Plymouth College Prep School",
    "wof:placetype":"venue"
},
  "geometry": {"coordinates":[-4.1260561943,50.3853874207],"type":"Point"}
}