{
  "type": "Feature",
  "properties": {
    "addr:full":"360 Lightbowne Rd Manchester Greater Manchester M40 0HA",
    "addr:housenumber":"360",
    "addr:postcode":"m40 0ha",
    "addr:street":"Lightbowne Rd",
    "iso:country":"GB",
    "sg:address":"360 Lightbowne Rd",
    "sg:city":"Manchester",
    "sg:classifiers":[
        {
            "category":"Shopping",
            "subcategory":"Department Store",
            "type":"Retail Goods"
        }
    ],
    "sg:phone":"+44 161 681 9289",
    "sg:postcode":"M40 0HA",
    "sg:province":"Greater Manchester",
    "wof:name":"D & H Stores",
    "wof:placetype":"venue"
},
  "geometry": {"coordinates":[-2.1783130169,53.5209693909],"type":"Point"}
}