{
  "type": "Feature",
  "properties": {
    "addr:full":"46 Pilgrim Street Newcastle-upon-tyne Tyne and Wear NE1 6SF",
    "addr:housenumber":"46",
    "addr:postcode":"ne1 6sf",
    "addr:street":"Pilgrim Street",
    "iso:country":"GB",
    "sg:address":"46 Pilgrim Street",
    "sg:city":"Newcastle-upon-tyne",
    "sg:classifiers":[
        {
            "category":"Retail",
            "subcategory":"Repair Shop",
            "type":"Services"
        },
        {
            "category":"Shopping",
            "subcategory":"Used Merchandise",
            "type":"Retail Goods"
        }
    ],
    "sg:phone":"+44 191 261 4154",
    "sg:postcode":"NE1 6SF",
    "sg:province":"Tyne and Wear",
    "sg:tags":[
        "sale",
        "second-hand"
    ],
    "wof:name":"Smokey Joes Secondhand Shop",
    "wof:placetype":"venue"
},
  "geometry": {"coordinates":[-1.610991,54.972748],"type":"Point"}
}