{
  "type": "Feature",
  "properties": {
    "addr:full":"Charnaford, Witheridge Tiverton Devon EX16 8QL",
    "addr:postcode":"ex16 8ql",
    "addr:street":"Witheridge",
    "iso:country":"GB",
    "sg:address":"Charnaford, Witheridge",
    "sg:city":"Tiverton",
    "sg:classifiers":[
        {
            "category":"Farming",
            "subcategory":"Livestock Farm",
            "type":"Manufacturing & Wholesale Goods"
        }
    ],
    "sg:phone":"+44 1884 860417",
    "sg:postcode":"EX16 8QL",
    "sg:province":"Devon",
    "sg:tags":[
        "others"
    ],
    "wof:name":"T H Rice",
    "wof:placetype":"venue"
},
  "geometry": {"coordinates":[-3.700682,50.916611],"type":"Point"}
}