{
  "type": "Feature",
  "properties": {
    "addr:full":"185 Lyndhurst Road, Ashurst Southampton Hampshire SO40 7AR",
    "addr:housenumber":"185",
    "addr:postcode":"so40 7ar",
    "addr:street":"Lyndhurst Road",
    "iso:country":"GB",
    "sg:address":"185 Lyndhurst Road, Ashurst",
    "sg:city":"Southampton",
    "sg:classifiers":[
        {
            "category":"Shopping",
            "subcategory":"Books",
            "type":"Retail Goods"
        }
    ],
    "sg:phone":"+44 23 8029 3389",
    "sg:postcode":"SO40 7AR",
    "sg:province":"Hampshire",
    "sg:tags":[
        "second-hand"
    ],
    "wof:name":"Nova Foresta Books",
    "wof:placetype":"venue"
},
  "geometry": {"coordinates":[-1.5227930546,50.8923034668],"type":"Point"}
}