{
  "type": "Feature",
  "properties": {
    "addr:full":"45a Wakefield Road Ossett West Yorkshire WF5 9LB",
    "addr:housenumber":"45a",
    "addr:postcode":"wf5 9lb",
    "addr:street":"Wakefield Road",
    "iso:country":"GB",
    "sg:address":"45a Wakefield Road",
    "sg:city":"Ossett",
    "sg:classifiers":[
        {
            "category":"Autos & Motor Vehicles",
            "subcategory":"Automobile Sales",
            "type":"Retail Goods"
        }
    ],
    "sg:phone":"+44 1924 266500",
    "sg:postcode":"WF5 9LB",
    "sg:province":"West Yorkshire",
    "sg:tags":[
        "commercial"
    ],
    "wof:name":"Regal Valeting Services",
    "wof:placetype":"venue"
},
  "geometry": {"coordinates":[-1.5713740587,53.6859588623],"type":"Point"}
}