{
  "type": "Feature",
  "properties": {
    "addr:full":"24 Sudeley Street London Greater London N1 8HP",
    "addr:housenumber":"24",
    "addr:postcode":"n1 8hp",
    "addr:street":"Sudeley Street",
    "iso:country":"GB",
    "sg:address":"24 Sudeley Street",
    "sg:city":"London",
    "sg:classifiers":[
        {
            "category":"Professional",
            "subcategory":"Computer Services",
            "type":"Services"
        }
    ],
    "sg:phone":"+44 20 7689 0907",
    "sg:postcode":"N1 8HP",
    "sg:province":"Greater London",
    "sg:tags":[
        "system",
        "software"
    ],
    "wof:name":"Deltaway I T  Ltd.",
    "wof:placetype":"venue"
},
  "geometry": {"coordinates":[-0.101117,51.5317344666],"type":"Point"}
}