{
  "type": "Feature",
  "properties": {
    "iso:country":"GB",
    "sg:address":"Trafford House, Platt Fold Street",
    "sg:city":"Leigh",
    "sg:classifiers":[
        {
            "category":"Professional",
            "subcategory":"Engineering",
            "type":"Services"
        }
    ],
    "sg:phone":"+44 1942 603063",
    "sg:postcode":"WN7 1JH",
    "sg:province":"Lancashire",
    "sg:tags":[
        "civil",
        "engineer"
    ],
    "wof:name":"Bolton & Fleet Ltd.",
    "wof:placetype":"venue"
},
  "geometry": {"coordinates":[-2.510004,53.499023],"type":"Point"}
}