{
  "type": "Feature",
  "properties": {
    "addr:full":"65 Pall Mall London Greater London SW1Y 5HZ",
    "addr:housenumber":"65",
    "addr:postcode":"sw1y 5hz",
    "addr:street":"Pall Mall",
    "iso:country":"GB",
    "sg:address":"65 Pall Mall",
    "sg:city":"London",
    "sg:classifiers":[
        {
            "category":"Manufacturing",
            "subcategory":"Tobacco Products",
            "type":"Manufacturing & Wholesale Goods"
        }
    ],
    "sg:phone":"+44 20 7930 6937",
    "sg:postcode":"SW1Y 5HZ",
    "sg:province":"Greater London",
    "wof:name":"Rothmans of Pall Mall (Overseas) Ltd.",
    "wof:placetype":"venue"
},
  "geometry": {"coordinates":[-0.1378239989,51.5052833557],"type":"Point"}
}