{
  "type": "Feature",
  "properties": {
    "addr:full":"66 Dilloway St St. Helens Merseyside WA10 4LN",
    "addr:housenumber":"66",
    "addr:postcode":"wa10 4ln",
    "addr:street":"Dilloway St",
    "iso:country":"GB",
    "sg:address":"66 Dilloway St",
    "sg:city":"St. Helens",
    "sg:classifiers":[
        {
            "category":"Arts & Performance",
            "subcategory":"Music",
            "type":"Entertainment"
        }
    ],
    "sg:phone":"+44 1744 751211",
    "sg:postcode":"WA10 4LN",
    "sg:province":"Merseyside",
    "sg:tags":[
        "musician",
        "composer"
    ],
    "wof:name":"The Jazz Pack Swing Band",
    "wof:placetype":"venue"
},
  "geometry": {"coordinates":[-2.7538990974,53.4570274353],"type":"Point"}
}