{
  "type": "Feature",
  "properties": {
    "addr:full":"1 Chellaston Cottages, Swarkestone Road, Weston-on-trent Derby Derbyshire DE72 2BU",
    "addr:housenumber":"1",
    "addr:postcode":"de72 2bu",
    "addr:street":"Chellaston Cottages Swarkestone Road",
    "iso:country":"GB",
    "sg:address":"1 Chellaston Cottages, Swarkestone Road, Weston-on-trent",
    "sg:city":"Derby",
    "sg:classifiers":[
        {
            "category":"Transit Center",
            "subcategory":"Passenger",
            "type":"Transportation"
        },
        {
            "category":"Retail",
            "subcategory":"Pet Boarding",
            "type":"Services"
        }
    ],
    "sg:phone":"+44 1332 703532",
    "sg:postcode":"DE72 2BU",
    "sg:province":"Derbyshire",
    "sg:tags":[
        "kennel",
        "catteries"
    ],
    "wof:name":"Conifer Boarding Kennels & Cattery",
    "wof:placetype":"venue"
},
  "geometry": {"coordinates":[-1.400827,52.849232],"type":"Point"}
}