{
  "type": "Feature",
  "properties": {
    "addr:full":"15 Elmfield Road Cheltenham Gloucestershire GL51 9JJ",
    "addr:housenumber":"15",
    "addr:postcode":"gl51 9jj",
    "addr:street":"Elmfield Road",
    "iso:country":"GB",
    "sg:address":"15 Elmfield Road",
    "sg:city":"Cheltenham",
    "sg:classifiers":[
        {
            "category":"Social Services",
            "subcategory":"Adult Care",
            "type":"Services"
        }
    ],
    "sg:phone":"+44 1242 257219",
    "sg:postcode":"GL51 9JJ",
    "sg:province":"Gloucestershire",
    "sg:tags":[
        "domestic",
        "cleaning"
    ],
    "wof:name":"Daisies Ltd.",
    "wof:placetype":"venue"
},
  "geometry": {"coordinates":[-2.086549,51.910957],"type":"Point"}
}