{
  "type": "Feature",
  "properties": {
    "addr:full":"1 High Street Crowthorne Berkshire RG45 7AD",
    "addr:housenumber":"1",
    "addr:postcode":"rg45 7ad",
    "addr:street":"High Street",
    "iso:country":"GB",
    "sg:address":"1 High Street",
    "sg:city":"Crowthorne",
    "sg:classifiers":[
        {
            "category":"Home & Garden",
            "subcategory":"Hardware",
            "type":"Retail Goods"
        },
        {
            "category":"Farming",
            "subcategory":"Farm",
            "type":"Manufacturing & Wholesale Goods"
        }
    ],
    "sg:phone":"+44 1344 772724",
    "sg:postcode":"RG45 7AD",
    "sg:province":"Berkshire",
    "sg:tags":[
        "agricultural",
        "machinery",
        "lawnmowers"
    ],
    "wof:name":"Garden & Estate Machinery",
    "wof:placetype":"venue"
},
  "geometry": {"coordinates":[-0.791852,51.370167],"type":"Point"}
}