{
  "type": "Feature",
  "properties": {
    "iso:country":"GB",
    "sg:address":"107a Maldon Road",
    "sg:city":"Burnham-on-crouch",
    "sg:classifiers":[
        {
            "category":"Banks & Credit Unions",
            "subcategory":"Bureau De Change",
            "type":"Services"
        },
        {
            "category":"Park",
            "subcategory":"Town Common",
            "type":"Public Place"
        },
        {
            "category":"Real Estate",
            "subcategory":"Surveying",
            "type":"Services"
        }
    ],
    "sg:phone":"+44 1621 783417",
    "sg:postcode":"CM0 8DD",
    "sg:province":"Essex",
    "sg:tags":[
        "consultant",
        "planning",
        "city",
        "valuer",
        "surveyor"
    ],
    "wof:name":"Raymond D Stemp",
    "wof:placetype":"venue"
},
  "geometry": {"coordinates":[0.811926,51.636044],"type":"Point"}
}