{
  "type": "Feature",
  "properties": {
    "iso:country":"GB",
    "sg:address":"Lloyds Bank Chambers, 4 Salisbury Street Amesbury",
    "sg:city":"Salisbury",
    "sg:classifiers":[
        {
            "category":"Building & Trades",
            "subcategory":"Construction",
            "type":"Services"
        }
    ],
    "sg:postcode":"SP4 7HD",
    "sg:province":"Hampshire",
    "sg:tags":[
        "builder"
    ],
    "wof:name":"Just Decking Ltd",
    "wof:placetype":"venue"
},
  "geometry": {"coordinates":[-1.7772099972,51.1694755554],"type":"Point"}
}