{
  "type": "Feature",
  "properties": {
    "addr:full":"Garsdale Frome Somerset BA11 1RZ",
    "addr:postcode":"ba11 1rz",
    "iso:country":"GB",
    "sg:address":"Garsdale",
    "sg:city":"Frome",
    "sg:classifiers":[
        {
            "category":"Home & Garden",
            "subcategory":"Furniture",
            "type":"Retail Goods"
        }
    ],
    "sg:postcode":"BA11 1RZ",
    "sg:province":"Somerset",
    "wof:name":"Western Woodcraft",
    "wof:placetype":"venue"
},
  "geometry": {"coordinates":[-2.3161110878,51.2304191589],"type":"Point"}
}