{
  "type": "Feature",
  "properties": {
    "addr:full":"15 Gloster Road, Old Woking Surrey GU22 9EU",
    "addr:housenumber":"15",
    "addr:postcode":"gu22 9eu",
    "addr:street":"Gloster Road",
    "iso:country":"GB",
    "sg:address":"15 Gloster Road, Old",
    "sg:city":"Woking",
    "sg:classifiers":[
        {
            "category":"Building & Trades",
            "subcategory":"Construction",
            "type":"Services"
        }
    ],
    "sg:postcode":"GU22 9EU",
    "sg:province":"Surrey",
    "sg:tags":[
        "joiner",
        "carpenter"
    ],
    "wof:name":"Decorjust Ltd",
    "wof:placetype":"venue"
},
  "geometry": {"coordinates":[-0.546395,51.305],"type":"Point"}
}