{
  "type": "Feature",
  "properties": {
    "iso:country":"GB",
    "sg:address":"31 St Andrew's Road",
    "sg:city":"Leicester",
    "sg:classifiers":[
        {
            "category":"Organizations",
            "subcategory":"Membership Organization",
            "type":"Services"
        },
        {
            "category":"Arena",
            "subcategory":"Sports Club",
            "type":"Entertainment"
        }
    ],
    "sg:phone":"+44 116 244 0028",
    "sg:postcode":"LE2 8RE",
    "sg:province":"Leicestershire",
    "sg:website":"http://www.bmfa.org",
    "wof:name":"Society Of Model Aeronautical Engineers Ltd",
    "wof:placetype":"venue"
},
  "geometry": {"coordinates":[-1.2064110041,52.62317276],"type":"Point"}
}