{
  "type": "Feature",
  "properties": {
    "iso:country":"GB",
    "sg:address":"6 Hollings Lane, Ravenfield",
    "sg:city":"Rotherham",
    "sg:classifiers":[
        {
            "category":"Health Services",
            "subcategory":"Clinic",
            "type":"Services"
        },
        {
            "category":"Shopping",
            "subcategory":"Pharmacy",
            "type":"Retail Goods"
        }
    ],
    "sg:phone":"+44 1709 541318",
    "sg:postcode":"S65 4PU",
    "sg:province":"South Yorkshire",
    "sg:tags":[
        "nh",
        "pharmacist",
        "chemist",
        "dispensing"
    ],
    "wof:name":"Ravenfield Pharmacy",
    "wof:placetype":"venue"
},
  "geometry": {"coordinates":[-1.267673,53.437889],"type":"Point"}
}