{
  "type": "Feature",
  "properties": {
    "iso:country":"GB",
    "sg:address":"26 Cranworth Rd",
    "sg:city":"Winchester",
    "sg:classifiers":[
        {
            "category":"Health Services",
            "subcategory":"Health Practitioner",
            "type":"Services"
        }
    ],
    "sg:phone":"+44 1962 854657",
    "sg:postcode":"SO22 6SE",
    "sg:province":"Hampshire",
    "sg:tags":[
        "physiotherapist"
    ],
    "wof:name":"G M E Jones",
    "wof:placetype":"venue"
},
  "geometry": {"coordinates":[-1.321028,51.069038],"type":"Point"}
}