{
  "type": "Feature",
  "properties": {
    "addr:full":"10 Wilberforce Way Solihull West Midlands B92 0QA",
    "addr:housenumber":"10",
    "addr:postcode":"b92 0qa",
    "addr:street":"Wilberforce Way",
    "iso:country":"GB",
    "sg:address":"10 Wilberforce Way",
    "sg:city":"Solihull",
    "sg:classifiers":[
        {
            "category":"Home & Garden",
            "subcategory":"Household Appliances",
            "type":"Retail Goods"
        },
        {
            "category":"Building & Trades",
            "subcategory":"Construction",
            "type":"Services"
        }
    ],
    "sg:phone":"+44 121 704 0036",
    "sg:postcode":"B92 0QA",
    "sg:province":"West Midlands",
    "sg:tags":[
        "installation",
        "equipment",
        "ventilation",
        "air conditioning"
    ],
    "wof:name":"Airtrax Midlands Ltd.",
    "wof:placetype":"venue"
},
  "geometry": {"coordinates":[-1.7577940226,52.4272918701],"type":"Point"}
}