{
  "type": "Feature",
  "properties": {
    "addr:full":"Seabourne Road Bournemouth Dorset BH5 2HY",
    "addr:postcode":"bh5 2hy",
    "addr:street":"Seabourne Road",
    "iso:country":"GB",
    "sg:address":"Seabourne Road",
    "sg:city":"Bournemouth",
    "sg:classifiers":[
        {
            "category":"Education",
            "subcategory":"Library",
            "type":"Public Place"
        }
    ],
    "sg:phone":"+44 1202 428784",
    "sg:postcode":"BH5 2HY",
    "sg:province":"Dorset",
    "sg:tags":[
        "book"
    ],
    "wof:name":"Southbourne Library",
    "wof:placetype":"venue"
},
  "geometry": {"coordinates":[-1.823359,50.729977],"type":"Point"}
}