{
  "type": "Feature",
  "properties": {
    "iso:country":"GB",
    "sg:address":"2 Bowerfield Avenue",
    "sg:city":"Stockport",
    "sg:classifiers":[
        {
            "category":"Building & Trades",
            "subcategory":"Construction",
            "type":"Services"
        }
    ],
    "sg:phone":"+44 1625 850822",
    "sg:postcode":"SK7 6HZ",
    "sg:province":"Cheshire",
    "sg:tags":[
        "builder"
    ],
    "wof:name":"A Grafton",
    "wof:placetype":"venue"
},
  "geometry": {"coordinates":[-2.121906,53.370979],"type":"Point"}
}