{
  "type": "Feature",
  "properties": {
    "addr:full":"6 Windmill Lane Ashbourne Derbyshire DE6 1EY",
    "addr:housenumber":"6",
    "addr:postcode":"de6 1ey",
    "addr:street":"Windmill Lane",
    "iso:country":"GB",
    "sg:address":"6 Windmill Lane",
    "sg:city":"Ashbourne",
    "sg:classifiers":[
        {
            "category":"Social Services",
            "subcategory":"Job Training",
            "type":"Services"
        }
    ],
    "sg:phone":"+44 1335 342812",
    "sg:postcode":"DE6 1EY",
    "sg:province":"Derbyshire",
    "sg:tags":[
        "translator",
        "interpreter"
    ],
    "wof:name":"Translation A La Carte",
    "wof:placetype":"venue"
},
  "geometry": {"coordinates":[-1.7338839769,53.0208396912],"type":"Point"}
}