{
  "type": "Feature",
  "properties": {
    "addr:full":"Netherkypeside Farm Strathaven South Lanarkshire ML10 6PF",
    "addr:postcode":"ml10 6pf",
    "addr:street":"Strathaven",
    "iso:country":"GB",
    "sg:address":"Netherkypeside Farm",
    "sg:city":"Strathaven",
    "sg:classifiers":[
        {
            "category":"Farming",
            "subcategory":"Livestock Farm",
            "type":"Manufacturing & Wholesale Goods"
        }
    ],
    "sg:phone":"+44 1357 520112",
    "sg:postcode":"ML10 6PF",
    "sg:province":"South Lanarkshire",
    "sg:tags":[
        "others"
    ],
    "wof:name":"W D Meikle",
    "wof:placetype":"venue"
},
  "geometry": {"coordinates":[-4.066794,55.676979],"type":"Point"}
}