{
  "type": "Feature",
  "properties": {
    "iso:country":"GB",
    "sg:address":"Broom Valley Road",
    "sg:city":"Rotherham",
    "sg:classifiers":[
        {
            "category":"Social Services",
            "subcategory":"Retirement Home",
            "type":"Services"
        },
        {
            "category":"Government",
            "subcategory":"Office",
            "type":"Public Place"
        }
    ],
    "sg:phone":"+44 1709 370968",
    "sg:postcode":"S60 2QY",
    "sg:province":"South Yorkshire",
    "sg:tags":[
        "residential",
        "local",
        "care"
    ],
    "wof:name":"Broom Hayes Rehabilitation Unit",
    "wof:placetype":"venue"
},
  "geometry": {"coordinates":[-1.347289,53.426285],"type":"Point"}
}