{
  "type": "Feature",
  "properties": {
    "iso:country":"GB",
    "sg:address":"15 Carlton Walk",
    "sg:city":"Shipley",
    "sg:classifiers":[
        {
            "category":"Building & Trades",
            "subcategory":"Plumbing",
            "type":"Services"
        }
    ],
    "sg:phone":"+44 1274 402287",
    "sg:postcode":"BD18 4NP",
    "sg:province":"West Yorkshire",
    "sg:tags":[
        "central",
        "heating"
    ],
    "wof:name":"Carlton Heating & Electrical Ltd",
    "wof:placetype":"venue"
},
  "geometry": {"coordinates":[-1.7946799994,53.8372001648],"type":"Point"}
}