{
  "type": "Feature",
  "properties": {
    "addr:full":"159 Eccleshall Road Stafford Staffordshire ST16 1PD",
    "addr:housenumber":"159",
    "addr:postcode":"st16 1pd",
    "addr:street":"Eccleshall Road",
    "iso:country":"GB",
    "sg:address":"159 Eccleshall Road",
    "sg:city":"Stafford",
    "sg:classifiers":[
        {
            "category":"Social Services",
            "subcategory":"Retirement Home",
            "type":"Services"
        }
    ],
    "sg:phone":"+44 1785 240738",
    "sg:postcode":"ST16 1PD",
    "sg:province":"Staffordshire",
    "sg:tags":[
        "residential",
        "care"
    ],
    "wof:name":"Brookside",
    "wof:placetype":"venue"
},
  "geometry": {"coordinates":[-2.13162,52.818779],"type":"Point"}
}