{
  "type": "Feature",
  "properties": {
    "iso:country":"GB",
    "sg:address":"19 Brookhill Lane",
    "sg:city":"Nottingham",
    "sg:classifiers":[
        {
            "category":"Building & Trades",
            "subcategory":"Construction",
            "type":"Services"
        }
    ],
    "sg:phone":"+44 1773 810357",
    "sg:postcode":"NG16 6JX",
    "sg:province":"Derbyshire",
    "sg:tags":[
        "builder"
    ],
    "wof:name":"Clover Construction Co.",
    "wof:placetype":"venue"
},
  "geometry": {"coordinates":[-1.317948,53.097057],"type":"Point"}
}