{
  "type": "Feature",
  "properties": {
    "addr:full":"15 Gainsborough Way, Freshbrook Swindon Wiltshire SN5 8PD",
    "addr:housenumber":"15",
    "addr:postcode":"sn5 8pd",
    "addr:street":"Gainsborough Way",
    "iso:country":"GB",
    "sg:address":"15 Gainsborough Way, Freshbrook",
    "sg:city":"Swindon",
    "sg:classifiers":[
        {
            "category":"Organizations",
            "subcategory":"Non-profit Organization",
            "type":"Services"
        }
    ],
    "sg:phone":"+44 1793 871303",
    "sg:postcode":"SN5 8PD",
    "sg:province":"Wiltshire",
    "sg:tags":[
        "charitable",
        "organisation",
        "voluntary",
        "charity"
    ],
    "wof:name":"West Swindon Family & Community Project",
    "wof:placetype":"venue"
},
  "geometry": {"coordinates":[-1.834967,51.553905],"type":"Point"}
}