{
  "type": "Feature",
  "properties": {
    "addr:full":"15 Heathbourne Road Bacup Lancashire OL13 0SN",
    "addr:housenumber":"15",
    "addr:postcode":"ol13 0sn",
    "addr:street":"Heathbourne Road",
    "iso:country":"GB",
    "sg:address":"15 Heathbourne Road",
    "sg:city":"Bacup",
    "sg:classifiers":[
        {
            "category":"Building & Trades",
            "subcategory":"Plumbing",
            "type":"Services"
        }
    ],
    "sg:phone":"+44 1706 874878",
    "sg:postcode":"OL13 0SN",
    "sg:province":"Lancashire",
    "sg:tags":[
        "plumber",
        "heating"
    ],
    "wof:name":"Kevin Melia",
    "wof:placetype":"venue"
},
  "geometry": {"coordinates":[-2.2273690701,53.6930160522],"type":"Point"}
}