{
  "type": "Feature",
  "properties": {
    "addr:full":"Unit 8 Vicarage Road Hornchurch Essex RM12 4AS",
    "addr:housenumber":"unit 8",
    "addr:postcode":"rm12 4as",
    "addr:street":"Vicarage Road",
    "iso:country":"GB",
    "sg:address":"Unit 8 Vicarage Road",
    "sg:city":"Hornchurch",
    "sg:classifiers":[
        {
            "category":"Manufacturing",
            "subcategory":"Petroleum Products",
            "type":"Manufacturing & Wholesale Goods"
        }
    ],
    "sg:phone":"+44 1708 378880",
    "sg:postcode":"RM12 4AS",
    "sg:province":"Essex",
    "sg:tags":[
        "double",
        "glazing"
    ],
    "wof:name":"Sovereign Glass Windows & Doors",
    "wof:placetype":"venue"
},
  "geometry": {"coordinates":[0.1980720013,51.5635871887],"type":"Point"}
}