{
  "type": "Feature",
  "properties": {
    "addr:full":"Unit 8, Mill Rd Southampton Hampshire SO15 4JB",
    "addr:housenumber":"unit 8",
    "addr:postcode":"so15 4jb",
    "addr:street":"Mill Rd",
    "iso:country":"GB",
    "sg:address":"Unit 8, Mill Rd",
    "sg:city":"Southampton",
    "sg:classifiers":[
        {
            "category":"Building & Trades",
            "subcategory":"Construction",
            "type":"Services"
        }
    ],
    "sg:phone":"+44 23 8078 2203",
    "sg:postcode":"SO15 4JB",
    "sg:province":"Hampshire",
    "sg:tags":[
        "decorator",
        "painter"
    ],
    "wof:name":"Cundy Ltd",
    "wof:placetype":"venue"
},
  "geometry": {"coordinates":[-1.445405,50.916828],"type":"Point"}
}