{
  "type": "Feature",
  "properties": {
    "addr:full":"1 Ralston Drive Kirkcaldy Fife KY2 6HX",
    "addr:housenumber":"1",
    "addr:postcode":"ky2 6hx",
    "addr:street":"Ralston Drive",
    "iso:country":"GB",
    "sg:address":"1 Ralston Drive",
    "sg:city":"Kirkcaldy",
    "sg:classifiers":[
        {
            "category":"Food & Beverages",
            "subcategory":"Groceries & Convenience Stores",
            "type":"Retail Goods"
        }
    ],
    "sg:phone":"+44 1592 262486",
    "sg:postcode":"KY2 6HX",
    "sg:province":"Fife",
    "wof:name":"Spar",
    "wof:placetype":"venue"
},
  "geometry": {"coordinates":[-3.1778759956,56.1364326477],"type":"Point"}
}