{
  "type": "Feature",
  "properties": {
    "iso:country":"GB",
    "sg:address":"19a Wrey Avenue, Sticklepath",
    "sg:city":"Barnstaple",
    "sg:classifiers":[
        {
            "category":"Retail",
            "subcategory":"Driving School",
            "type":"Services"
        }
    ],
    "sg:postcode":"EX31 2EB",
    "sg:province":"Devon",
    "wof:name":"Barry's School of Motoring",
    "wof:placetype":"venue"
},
  "geometry": {"coordinates":[-4.075478,51.073692],"type":"Point"}
}