{
  "type": "Feature",
  "properties": {
    "addr:full":"The Kingstanding Centre Birmingham West Midlands B44 9HH",
    "addr:postcode":"b44 9hh",
    "iso:country":"GB",
    "sg:address":"The Kingstanding Centre",
    "sg:city":"Birmingham",
    "sg:classifiers":[
        {
            "category":"Shopping",
            "subcategory":"Clothing, Apparel, & Fashions",
            "type":"Retail Goods"
        }
    ],
    "sg:phone":"+44 121 354 9790",
    "sg:postcode":"B44 9HH",
    "sg:province":"West Midlands",
    "sg:tags":[
        "shop"
    ],
    "wof:name":"Be-Wise Ltd.",
    "wof:placetype":"venue"
},
  "geometry": {"coordinates":[-1.8821890354,52.5586853027],"type":"Point"}
}