{
  "type": "Feature",
  "properties": {
    "iso:country":"GB",
    "sg:address":"31 High Street",
    "sg:city":"Wellingborough",
    "sg:classifiers":[
        {
            "category":"Autos & Motor Vehicles",
            "subcategory":"Automobile Sales",
            "type":"Retail Goods"
        }
    ],
    "sg:postcode":"NN8 4HL",
    "sg:province":"Northamptonshire",
    "sg:tags":[
        "car"
    ],
    "wof:name":"Bob Wildings Ltd",
    "wof:placetype":"venue"
},
  "geometry": {"coordinates":[-0.696409,52.302605],"type":"Point"}
}