{
  "type": "Feature",
  "properties": {
    "addr:full":"Denhead, Potterton Aberdeen Aberdeen City AB23 8UB",
    "addr:postcode":"ab23 8ub",
    "iso:country":"GB",
    "sg:address":"Denhead, Potterton",
    "sg:city":"Aberdeen",
    "sg:classifiers":[
        {
            "category":"Bars & Pubs",
            "type":"Food & Drink"
        }
    ],
    "sg:postcode":"AB23 8UB",
    "sg:province":"Aberdeen City",
    "sg:tags":[
        "pubs",
        "inn"
    ],
    "wof:name":"D A & S Farrell",
    "wof:placetype":"venue"
},
  "geometry": {"coordinates":[-2.102241,57.233044],"type":"Point"}
}