{
  "type": "Feature",
  "properties": {
    "addr:full":"6 Durnsford Avenue Fleet Hampshire GU52 7TB",
    "addr:housenumber":"6",
    "addr:postcode":"gu52 7tb",
    "addr:street":"Durnsford Avenue",
    "iso:country":"GB",
    "sg:address":"6 Durnsford Avenue",
    "sg:city":"Fleet",
    "sg:classifiers":[
        {
            "category":"Home & Garden",
            "subcategory":"Home Furnishings",
            "type":"Retail Goods"
        }
    ],
    "sg:postcode":"GU52 7TB",
    "sg:province":"Hampshire",
    "sg:tags":[
        "furnishers",
        "planner",
        "bedroom"
    ],
    "wof:name":"Homemead Interiors",
    "wof:placetype":"venue"
},
  "geometry": {"coordinates":[-0.83534,51.27372],"type":"Point"}
}