{
  "type": "Feature",
  "properties": {
    "addr:full":"3 High Street, St Neots Huntingdon Bedfordshire PE19 1BU",
    "addr:housenumber":"3",
    "addr:postcode":"pe19 1bu",
    "addr:street":"High Street",
    "iso:country":"GB",
    "sg:address":"3 High Street, St Neots",
    "sg:city":"Huntingdon",
    "sg:classifiers":[
        {
            "category":"Shopping",
            "subcategory":"Clothing, Apparel, & Fashions",
            "type":"Retail Goods"
        }
    ],
    "sg:phone":"+44 1480 403119",
    "sg:postcode":"PE19 1BU",
    "sg:province":"Bedfordshire",
    "sg:tags":[
        "shop"
    ],
    "wof:name":"The Edinburgh Woollen Mill Ltd.",
    "wof:placetype":"venue"
},
  "geometry": {"coordinates":[-0.2691220045,52.2280578613],"type":"Point"}
}