{
  "type": "Feature",
  "properties": {
    "addr:full":"Marrysbrook, Leighton Shrewsbury Shropshire SY5 6RN",
    "addr:postcode":"sy5 6rn",
    "addr:street":"Shrewsbury",
    "iso:country":"GB",
    "sg:address":"Marrysbrook, Leighton",
    "sg:city":"Shrewsbury",
    "sg:classifiers":[
        {
            "category":"Building & Trades",
            "subcategory":"Construction",
            "type":"Services"
        }
    ],
    "sg:postcode":"SY5 6RN",
    "sg:province":"Shropshire",
    "sg:tags":[
        "builder"
    ],
    "wof:name":"Telford Building Contractors",
    "wof:placetype":"venue"
},
  "geometry": {"coordinates":[-2.574049,52.644321],"type":"Point"}
}