{
  "type": "Feature",
  "properties": {
    "addr:full":"Solway Road, Kells Whitehaven Cumbria CA28 9AW",
    "addr:postcode":"ca28 9aw",
    "addr:street":"Solway Road;Whitehaven",
    "iso:country":"GB",
    "sg:address":"Solway Road, Kells",
    "sg:city":"Whitehaven",
    "sg:classifiers":[
        {
            "category":"Retail",
            "subcategory":"Auto Repair",
            "type":"Services"
        }
    ],
    "sg:phone":"+44 1946 66857",
    "sg:postcode":"CA28 9AW",
    "sg:province":"Cumbria",
    "sg:tags":[
        "body",
        "car",
        "repairer"
    ],
    "wof:name":"PONDFIELD GARAGE",
    "wof:placetype":"venue"
},
  "geometry": {"coordinates":[-3.596245,54.54229],"type":"Point"}
}