{
  "type": "Feature",
  "properties": {
    "addr:full":"Lower Oaken Eaves Farm, Manchester Road Burnley Lancashire BB11 5NS",
    "addr:postcode":"bb11 5ns",
    "addr:street":"Lower Oaken Eaves;Manchester Road",
    "iso:country":"GB",
    "sg:address":"Lower Oaken Eaves Farm, Manchester Road",
    "sg:city":"Burnley",
    "sg:classifiers":[
        {
            "category":"Farming",
            "subcategory":"Livestock Farm",
            "type":"Manufacturing & Wholesale Goods"
        }
    ],
    "sg:phone":"+44 1282 427452",
    "sg:postcode":"BB11 5NS",
    "sg:province":"Lancashire",
    "sg:tags":[
        "others"
    ],
    "wof:name":"F Bell",
    "wof:placetype":"venue"
},
  "geometry": {"coordinates":[-2.260711,53.773342],"type":"Point"}
}