{
  "type": "Feature",
  "properties": {
    "addr:full":"Wood Street, Lanesfield Wolverhampton Staffordshire WV4 6LH",
    "addr:postcode":"wv4 6lh",
    "addr:street":"Wood Street",
    "iso:country":"GB",
    "sg:address":"Wood Street, Lanesfield",
    "sg:city":"Wolverhampton",
    "sg:classifiers":[
        {
            "category":"Bars & Pubs",
            "type":"Food & Drink"
        }
    ],
    "sg:phone":"+44 1902 491042",
    "sg:postcode":"WV4 6LH",
    "sg:province":"Staffordshire",
    "sg:tags":[
        "pubs",
        "inn"
    ],
    "wof:name":"The Rookery Tavern",
    "wof:placetype":"venue"
},
  "geometry": {"coordinates":[-2.1043379307,52.5590324402],"type":"Point"}
}