{
  "type": "Feature",
  "properties": {
    "addr:full":"1 Eastern Avenue Gloucester Gloucestershire GL4 6PD",
    "addr:housenumber":"1",
    "addr:postcode":"gl4 6pd",
    "addr:street":"Eastern Avenue",
    "iso:country":"GB",
    "sg:address":"1 Eastern Avenue",
    "sg:city":"Gloucester",
    "sg:classifiers":[
        {
            "category":"Retail",
            "subcategory":"Car Wash",
            "type":"Services"
        }
    ],
    "sg:phone":"+44 1452 300520",
    "sg:postcode":"GL4 6PD",
    "sg:province":"Gloucestershire",
    "sg:tags":[
        "polishing",
        "washing"
    ],
    "wof:name":"Oasis Carwash",
    "wof:placetype":"venue"
},
  "geometry": {"coordinates":[-2.22547,51.852787],"type":"Point"}
}