{
  "type": "Feature",
  "properties": {
    "iso:country":"GB",
    "sg:address":"Earls Ho, Earls Way, Team Valley Trading Est",
    "sg:city":"Gateshead",
    "sg:classifiers":[
        {
            "category":"Professional",
            "subcategory":"Art Services",
            "type":"Services"
        }
    ],
    "sg:phone":"+44 191 491 1053",
    "sg:postcode":"NE11 0RY",
    "sg:province":"Tyne and Wear",
    "sg:tags":[
        "graphic",
        "designer"
    ],
    "wof:name":"Hippo Graphics",
    "wof:placetype":"venue"
},
  "geometry": {"coordinates":[-1.620740056,54.9444885254],"type":"Point"}
}