{
  "type": "Feature",
  "properties": {
    "addr:full":"Royal Works, Canal Sidings, Edge Lane Manchester Cheshire M32 8HS",
    "addr:postcode":"m32 8hs",
    "addr:street":"Canal Sidings Edge Lane",
    "iso:country":"GB",
    "sg:address":"Royal Works, Canal Sidings, Edge Lane",
    "sg:city":"Manchester",
    "sg:classifiers":[
        {
            "category":"Building & Trades",
            "subcategory":"Construction",
            "type":"Services"
        }
    ],
    "sg:postcode":"M32 8HS",
    "sg:province":"Cheshire",
    "sg:tags":[
        "contractor",
        "paving",
        "driveway"
    ],
    "wof:name":"Evergreen Paving",
    "wof:placetype":"venue"
},
  "geometry": {"coordinates":[-2.248809,53.479622],"type":"Point"}
}