{
  "type": "Feature",
  "properties": {
    "iso:country":"GB",
    "sg:address":"2 Belgrave Road",
    "sg:city":"Halesowen",
    "sg:classifiers":[
        {
            "category":"Retail",
            "subcategory":"Auto Repair",
            "type":"Services"
        }
    ],
    "sg:phone":"+44 121 602 3166",
    "sg:postcode":"B62 9HA",
    "sg:province":"West Midlands",
    "sg:tags":[
        "modification",
        "garage"
    ],
    "wof:name":"Motor Car Spares & Repairs",
    "wof:placetype":"venue"
},
  "geometry": {"coordinates":[-2.0314040184,52.4706382751],"type":"Point"}
}