{
  "type": "Feature",
  "properties": {
    "iso:country":"GB",
    "sg:address":"62a Plodder Lane, Farnworth",
    "sg:city":"Bolton",
    "sg:classifiers":[
        {
            "category":"Shopping",
            "subcategory":"Pets & Pet Supplies",
            "type":"Retail Goods"
        }
    ],
    "sg:postcode":"BL4 0DA",
    "sg:province":"Lancashire",
    "sg:tags":[
        "food"
    ],
    "wof:name":"Birdquest Int",
    "wof:placetype":"venue"
},
  "geometry": {"coordinates":[-2.444355,53.549595],"type":"Point"}
}