{
  "type": "Feature",
  "properties": {
    "iso:country":"GB",
    "sg:address":"111 Camden High St",
    "sg:city":"Camden",
    "sg:classifiers":[
        {
            "category":"Sports & Exercise",
            "subcategory":"Playing Field",
            "type":"Entertainment"
        }
    ],
    "sg:phone":"+44 20 7387 6816",
    "sg:postcode":"NW1 7JN",
    "sg:province":"Greater London",
    "sg:tags":[
        "martial art"
    ],
    "wof:name":"Albany Kick Boxing",
    "wof:placetype":"venue"
},
  "geometry": {"coordinates":[-0.141064,51.537041],"type":"Point"}
}