{
  "type": "Feature",
  "properties": {
    "addr:full":"1 Tiptree Rd Ruislip Greater London HA4 0EW",
    "addr:housenumber":"1",
    "addr:postcode":"ha4 0ew",
    "addr:street":"Tiptree Rd",
    "iso:country":"GB",
    "sg:address":"1 Tiptree Rd",
    "sg:city":"Ruislip",
    "sg:classifiers":[
        {
            "category":"Shopping",
            "subcategory":"Antiques",
            "type":"Retail Goods"
        }
    ],
    "sg:postcode":"HA4 0EW",
    "sg:province":"Greater London",
    "wof:name":"Fitzpatrick,Michael,",
    "wof:placetype":"venue"
},
  "geometry": {"coordinates":[-0.4022,51.560925],"type":"Point"}
}