{
  "type": "Feature",
  "properties": {
    "iso:country":"GB",
    "sg:address":"The Coach House, 8 North Lane",
    "sg:city":"Canterbury",
    "sg:classifiers":[
        {
            "category":"Insurance",
            "subcategory":"Insurance Agent",
            "type":"Services"
        }
    ],
    "sg:phone":"+44 1227 763344",
    "sg:postcode":"CT2 7PZ",
    "sg:province":"Kent",
    "sg:tags":[
        "broker"
    ],
    "wof:name":"Innpak Ltd.",
    "wof:placetype":"venue"
},
  "geometry": {"coordinates":[1.075916,51.282234],"type":"Point"}
}