{
  "type": "Feature",
  "properties": {
    "iso:country":"GB",
    "sg:address":"Unit 4 Fairfield Park, Fairfield Road In Estate",
    "sg:city":"Halesowen",
    "sg:classifiers":[
        {
            "category":"Home & Garden",
            "subcategory":"Home Furnishings",
            "type":"Retail Goods"
        }
    ],
    "sg:phone":"+44 121 561 4245",
    "sg:postcode":"B62 9JL",
    "sg:province":"West Midlands",
    "sg:tags":[
        "furnishers",
        "planner",
        "kitchen"
    ],
    "wof:name":"Blackheath Products Ltd.",
    "wof:placetype":"venue"
},
  "geometry": {"coordinates":[-2.0256080627,52.4747505188],"type":"Point"}
}