{
  "type": "Feature",
  "properties": {
    "addr:full":"Arch 5, Viaduct Estate Road Carlisle Cumbria CA2 5BN",
    "addr:postcode":"ca2 5bn",
    "addr:street":"Arch;Viaduct Estate Road",
    "iso:country":"GB",
    "sg:address":"Arch 5, Viaduct Estate Road",
    "sg:city":"Carlisle",
    "sg:classifiers":[
        {
            "category":"Food & Beverages",
            "subcategory":"Liquor & Beverages",
            "type":"Retail Goods"
        }
    ],
    "sg:phone":"+44 1228 543033",
    "sg:postcode":"CA2 5BN",
    "sg:province":"Cumbria",
    "sg:tags":[
        "beer",
        "wine",
        "spirit",
        "wines"
    ],
    "wof:name":"Corkscrew Wines",
    "wof:placetype":"venue"
},
  "geometry": {"coordinates":[-2.94121,54.893669],"type":"Point"}
}