{
  "type": "Feature",
  "properties": {
    "addr:full":"5 Halkin Arcade, West Halkin Street London Greater London SW1X 8JT",
    "addr:housenumber":"5;arcade",
    "addr:postcode":"sw1x 8jt",
    "addr:street":"Halkin;Halkin Street",
    "iso:country":"GB",
    "sg:address":"5 Halkin Arcade, West Halkin Street",
    "sg:city":"London",
    "sg:classifiers":[
        {
            "category":"Bars & Pubs",
            "subcategory":"Nightclub",
            "type":"Food & Drink"
        }
    ],
    "sg:postcode":"SW1X 8JT",
    "sg:province":"Greater London",
    "sg:tags":[
        "club",
        "night"
    ],
    "wof:name":"Motcombs Club",
    "wof:placetype":"venue"
},
  "geometry": {"coordinates":[-0.1565649956,51.4988059998],"type":"Point"}
}