{
  "type": "Feature",
  "properties": {
    "addr:full":"107 Chalkwell Road Sittingbourne Kent ME10 2LP",
    "addr:housenumber":"107",
    "addr:postcode":"me10 2lp",
    "addr:street":"Chalkwell Road",
    "iso:country":"GB",
    "sg:address":"107 Chalkwell Road",
    "sg:city":"Sittingbourne",
    "sg:classifiers":[
        {
            "category":"Health Services",
            "subcategory":"Health Practitioner",
            "type":"Services"
        }
    ],
    "sg:phone":"+44 1795 477264",
    "sg:postcode":"ME10 2LP",
    "sg:province":"Kent",
    "sg:tags":[
        "osteopath"
    ],
    "wof:name":"A M HILLS & R M G DE SOUSA",
    "wof:placetype":"venue"
},
  "geometry": {"coordinates":[0.726669,51.346054],"type":"Point"}
}