{
  "type": "Feature",
  "properties": {
    "addr:full":"Flat 5 Burford Ct, 2 Manor Rd Bournemouth Dorset BH1 3HT",
    "addr:housenumber":"2",
    "addr:postcode":"bh1 3ht",
    "addr:street":"Burford Ct;Manor Rd",
    "iso:country":"GB",
    "sg:address":"Flat 5 Burford Ct, 2 Manor Rd",
    "sg:city":"Bournemouth",
    "sg:classifiers":[
        {
            "category":"Taxi",
            "type":"Transportation"
        }
    ],
    "sg:postcode":"BH1 3HT",
    "sg:province":"Dorset",
    "sg:tags":[
        "mini",
        "cab"
    ],
    "wof:name":"Harris,E,",
    "wof:placetype":"venue"
},
  "geometry": {"coordinates":[-1.86007,50.72187],"type":"Point"}
}